Workbook

Sheet Смета по ТСН-2001(с доп.67
A1: =Source!B1 -> Smeta.RU (495) 974-1589
J2: Форма № 4б
A3: Капитальный ремонт здания Государственного бюджетного общеобразовательного учреждения города Москвы «Школа №1574», расположенного по адресу: г. Москва, Старопименовский переулок, д. 5. 1 этап. | AP3: Капитальный ремонт здания Государственного бюджетного общеобразовательного учреждения города Москвы «Школа №1574», расположенного по адресу: г. Москва, Старопименовский переулок, д. 5. 1 этап.
A4: (наименование стройки и/или объекта)
A6: ЛОКАЛЬНАЯ СМЕТА № 02-01-05
A8: Система водоотведения.
A9: (наименование работ и затрат)
A11: =CONCATENATE( "Основание: чертежи № ", Source!J12) -> Основание: чертежи № 2024-00375-01-01-ИОС3.
I13: В базисном уровне цен | J13: В текущем уровне цен
E14: Сметная стоимость | I14: =I15+I16+I17+I18 -> 790.07 | J14: =J15+J16+J17+J18 -> 7149.3 | K14: тыс.руб.
E15: Строительные работы | I15: =ROUND((Source!F693)/1000, 2) -> 781.6 | J15: =ROUND((Source!P693)/1000, 2) -> 7023.29 | K15: тыс.руб.
E16: Работы по монтажу оборудования | I16: =ROUND((Source!F694)/1000, 2) -> 0 | J16: =ROUND((Source!P694)/1000, 2) -> 0 | K16: тыс.руб.
E17: Оборудование | I17: =ROUND((Source!F685)/1000, 2) -> 8.47 | J17: =ROUND((Source!P685)/1000, 2) -> 126.01 | K17: тыс.руб.
E18: Прочие работы и затраты | I18: =ROUND((Source!F695+Source!F696)/1000, 2) -> 0 | J18: =ROUND((Source!P695+Source!P696)/1000, 2) -> 0 | K18: тыс.руб.
E19: Средства на оплату труда | I19: =(Source!F691+ Source!F690)/1000 -> 25.40605 | J19: =((Source!P691 + Source!P690)/1000) -> 1431.631 | K19: тыс.руб.
E20: Затраты труда | I20: =Source!F698 -> 2029.9267 | K20: чел.-ч.
E21: Кроме того:
E22: Возврат материалов | I22: =SUM(Y1:Y833)/1000 -> 0 | J22: =SUM(Z1:Z833)/1000 -> 0 | K22: тыс.руб.
A24: Составлен(а) по ТСН-2001 с учетом Дополнения №: 81
A25: № и период сборника коэффициентов (индексов) пересчета: Коэффициенты к ТСН-2001 МГЭ Дополнение 81, ремонт №219/81 I квартал 2026 года и Коэффициенты к ТСН-2001.13-2 Дополнение 47 №64/47 I квартал 2026 года | AP25: № и период сборника коэффициентов (индексов) пересчета: Коэффициенты к ТСН-2001 МГЭ Дополнение 81, ремонт №219/81 I квартал 2026 года и Коэффициенты к ТСН-2001.13-2 Дополнение 47 №64/47 I квартал 2026 года
A26: № п/п | B26: Шифр расценки и коды ресурсов | C26: Наименование работ и затрат | D26: Ед. изм. | E26: Кол-во единиц | F26: Цена на ед. изм., руб. | G26: Попра- вочные коэффи- циенты | H26: Коэффи- циенты зимних удорожа- ний | I26: Всего в ценах на январь 2000 года, руб. | J26: Коэффи- циенты (индек- сы) пере- счета, нормы НР и СП | K26: ВСЕГО затрат в текущем уровне цен, руб.
A27: 1 | B27: 2 | C27: 3 | D27: 4 | E27: 5 | F27: 6 | G27: 7 | H27: 8 | I27: 9 | J27: 10 | K27: 11
A29: =CONCATENATE("Локальная смета: ",IF(Source!G20<>"Новая локальная смета", Source!G20, "")) -> Локальная смета: Система водоотведения.
A31: =CONCATENATE("Раздел: ",IF(Source!G24<>"Новый раздел", Source!G24, "")) -> Раздел: Демонтажные работы.
A32: 1 | B32: =Source!F28 -> 6.65-1-2 | C32: Разборка трубопроводов из водогазопроводных труб диаметром до 40 мм | D32: =Source!H28 -> 100 м | E32: =Source!I28 -> 0.38 | Q32: =Source!X28 -> 205.9 | R32: =Source!X29 -> 11602.62 | S32: =Source!Y28 -> 104.13 | T32: =Source!Y29 -> 5867.99 | U32: =ROUND((175/100)*ROUND(Source!R28, 2), 2) -> 0 | V32: =ROUND((0/100)*ROUND(Source!R29, 2), 2) -> 0 | AC32: 0
C33: ="Объем: "&Source!I28&"=(30+"&"8)/"&"100" -> Объем: 0,38=(30+8)/100
C34: ЗП | F34: =Source!AO28 -> 495.71 | G34: 1,2 | H34: =Source!AV29 -> 1.047 | I34: =Source!S28 -> 236.67 | J34: =IF(Source!BA29<> 0, Source!BA29, 1) -> 56.35 | K34: =Source!S29 -> 13336.35
C35: ЭМ | F35: =Source!AM28 -> 1.26 | G35: 1,2 | H35: =Source!AV29 -> 1.047 | I35: =Source!Q28 -> 0.6 | J35: =IF(Source!BB29<> 0, Source!BB29, 1) -> 9.29 | K35: =Source!Q29 -> 5.57
C36: МР | F36: =Source!AL28 -> 46.16 | H36: =Source!AW29 -> 1 | I36: =Source!P28 -> 17.54 | J36: =IF(Source!BC29<> 0, Source!BC29, 1) -> 15.53 | K36: =Source!P29 -> 272.4
C37: НР от ФОТ | D37: % | E37: =Source!BZ29 -> 87 | I37: =SUM(Q32:Q36) -> 205.9 | J37: =Source!AT29 -> 87 | K37: =SUM(R32:R36) -> 11602.62
C38: СП от ФОТ | D38: % | E38: =Source!CA29 -> 44 | I38: =SUM(S32:S37) -> 104.13 | J38: =Source!AU29 -> 44 | K38: =SUM(T32:T37) -> 5867.99
C39: ЗТР | D39: чел-ч | E39: =Source!AQ28 -> 45.52 | G39: 1,2 | H39: =Source!AV29 -> 1.047 | I39: =Source!U28 -> 21.732705
C40: ВСЕГО работ по позиции: | H40: =I34+I35+I36+I37+I38+0-0-0 -> 564.84 | J40: =K34+K35+K36+K37+K38+0-0-0 -> 31084.93
C41: ВСЕГО оборудование по позиции: | H41: =0+0 -> 0 | J41: =0+0 -> 0
C42: ВСЕГО по позиции: | H42: =I34+I35+I36+I37+I38+0 -> 564.84 | J42: =K34+K35+K36+K37+K38+0 -> 31084.93 | O42: =I34+I35+I36+I37+I38+0 -> 564.84 | P42: =K34+K35+K36+K37+K38+0 -> 31084.93
A44: 2 | B44: =Source!F30 -> 6.65-11-5 | C44: Разборка трубопроводов центрального отопления на сварке диаметром труб до 100 мм | D44: =Source!H30 -> 100 м | E44: =Source!I30 -> 0.15 | Q44: =Source!X30 -> 110.12 | R44: =Source!X31 -> 6205.52 | S44: =Source!Y30 -> 55.7 | T44: =Source!Y31 -> 3138.42 | U44: =ROUND((175/100)*ROUND(Source!R30, 2), 2) -> 0 | V44: =ROUND((0/100)*ROUND(Source!R31, 2), 2) -> 0 | AC44: 0
C45: ="Объем: "&Source!I30&"=15/"&"100" -> Объем: 0,15=15/100
C46: ЗП | F46: =Source!AO30 -> 819.08 | G46: 0,82*1,2 | H46: =Source!AV31 -> 1.047 | I46: =Source!S30 -> 126.58 | J46: =IF(Source!BA31<> 0, Source!BA31, 1) -> 56.35 | K46: =Source!S31 -> 7132.78
C47: ЭМ | F47: =Source!AM30 -> 1.82 | G47: 1,2 | H47: =Source!AV31 -> 1.047 | I47: =Source!Q30 -> 0.34 | J47: =IF(Source!BB31<> 0, Source!BB31, 1) -> 9.29 | K47: =Source!Q31 -> 3.16
C48: МР | F48: =Source!AL30 -> 76.84 | H48: =Source!AW31 -> 1 | I48: =Source!P30 -> 11.53 | J48: =IF(Source!BC31<> 0, Source!BC31, 1) -> 15.53 | K48: =Source!P31 -> 179.06
C49: НР от ФОТ | D49: % | E49: =Source!BZ31 -> 87 | I49: =SUM(Q44:Q48) -> 110.12 | J49: =Source!AT31 -> 87 | K49: =SUM(R44:R48) -> 6205.52
C50: СП от ФОТ | D50: % | E50: =Source!CA31 -> 44 | I50: =SUM(S44:S49) -> 55.7 | J50: =Source!AU31 -> 44 | K50: =SUM(T44:T49) -> 3138.42
C51: ЗТР | D51: чел-ч | E51: =Source!AQ30 -> 74.53 | G51: 0,82*1,2 | H51: =Source!AV31 -> 1.047 | I51: =Source!U30 -> 11.517658
C52: ВСЕГО работ по позиции: | H52: =I46+I47+I48+I49+I50+0-0-0 -> 304.27 | J52: =K46+K47+K48+K49+K50+0-0-0 -> 16658.94
C53: ВСЕГО оборудование по позиции: | H53: =0+0 -> 0 | J53: =0+0 -> 0
C54: ВСЕГО по позиции: | H54: =I46+I47+I48+I49+I50+0 -> 304.27 | J54: =K46+K47+K48+K49+K50+0 -> 16658.94 | O54: =I46+I47+I48+I49+I50+0 -> 304.27 | P54: =K46+K47+K48+K49+K50+0 -> 16658.94
A56: 3 | B56: =Source!F32 -> 3.16-40-4 | C56: Прокладка напорного трубопровода водоснабжения и отопления из многослойного полипропилена, армированного стекловолокном, из заранее собранных узлов, наружный диаметр 40 мм (демонтаж) | D56: =Source!H32 -> 100 м | E56: =Source!I32 -> 0.25 | Q56: =Source!X32 -> 23.47 | R56: =Source!X33 -> 1322.41 | S56: =Source!Y32 -> 13.13 | T56: =Source!Y33 -> 740.06 | U56: =ROUND((175/100)*ROUND(Source!R32, 2), 2) -> 0.33 | V56: =ROUND((0/100)*ROUND(Source!R33, 2), 2) -> 0 | AC56: 0
C57: ="Объем: "&Source!I32&"=(25)/"&"100" -> Объем: 0,25=(25)/100
C58: ЗП | F58: =Source!AO32 -> 166.66 | G58: 0,4*1,2 | H58: =Source!AV33 -> 1.067 | I58: =Source!S32 -> 21.34 | J58: =IF(Source!BA33<> 0, Source!BA33, 1) -> 56.35 | K58: =Source!S33 -> 1202.51
C59: ЭМ | F59: =Source!AM32 -> 24.17 | G59: 0,4*1,2 | H59: =Source!AV33 -> 1.067 | I59: =Source!Q32 -> 3.09 | J59: =IF(Source!BB33<> 0, Source!BB33, 1) -> 13.68 | K59: =Source!Q33 -> 42.27
C60: в т.ч. ЗПМ | F60: =Source!AN32 -> 1.51 | G60: 0,4*1,2 | H60: =Source!AV33 -> 1.067 | I60: =Source!R32 -> 0.19 | J60: =IF(Source!BS33<> 0, Source!BS33, 1) -> 56.35 | K60: =Source!R33 -> 10.71
C61: НР от ФОТ | D61: % | E61: =Source!BZ33 -> 109 | I61: =SUM(Q56:Q60) -> 23.47 | J61: =Source!AT33 -> 109 | K61: =SUM(R56:R60) -> 1322.41
C62: СП от ФОТ | D62: % | E62: =Source!CA33 -> 61 | I62: =SUM(S56:S61) -> 13.13 | J62: =Source!AU33 -> 61 | K62: =SUM(T56:T61) -> 740.06
C63: ЗТР | D63: чел-ч | E63: =Source!AQ32 -> 13.52 | G63: 0,4*1,2 | H63: =Source!AV33 -> 1.067 | I63: =Source!U32 -> 1.7311008
C64: ВСЕГО работ по позиции: | H64: =I58+I59+I61+I62+0-0-0 -> 61.03 | J64: =K58+K59+K61+K62+0-0-0 -> 3307.25
C65: ВСЕГО оборудование по позиции: | H65: =0+0 -> 0 | J65: =0+0 -> 0
C66: ВСЕГО по позиции: | H66: =I58+I59+I61+I62+0 -> 61.03 | J66: =K58+K59+K61+K62+0 -> 3307.25 | O66: =I58+I59+I61+I62+0 -> 61.03 | P66: =K58+K59+K61+K62+0 -> 3307.25
A68: 4 | B68: =Source!F34 -> 3.16-13-2 | C68: Прокладка трубопроводов канализации из ПВХ труб диаметром 100 мм - 150 мм (демонтаж) | D68: =Source!H34 -> 100 м | E68: =Source!I34 -> 2.3 | Q68: =Source!X34 -> 924.04 | R68: =Source!X35 -> 52069.46 | S68: =Source!Y34 -> 517.12 | T68: =Source!Y35 -> 29139.79 | U68: =ROUND((175/100)*ROUND(Source!R34, 2), 2) -> 5.9 | V68: =ROUND((0/100)*ROUND(Source!R35, 2), 2) -> 0 | AC68: 0
C69: ="Объем: "&Source!I34&"=(180+"&"18+"&"32)/"&"100" -> Объем: 2,3=(180+18+32)/100
C70: ЗП | F70: =Source!AO34 -> 716.8 | G70: 0,4*1,2 | H70: =Source!AV35 -> 1.067 | I70: =Source!S34 -> 844.37 | J70: =IF(Source!BA35<> 0, Source!BA35, 1) -> 56.35 | K70: =Source!S35 -> 47580.25
C71: ЭМ | F71: =Source!AM34 -> 20.2 | G71: 0,4*1,2 | H71: =Source!AV35 -> 1.067 | I71: =Source!Q34 -> 23.79 | J71: =IF(Source!BB35<> 0, Source!BB35, 1) -> 16.6 | K71: =Source!Q35 -> 394.91
C72: в т.ч. ЗПМ | F72: =Source!AN34 -> 2.86 | G72: 0,4*1,2 | H72: =Source!AV35 -> 1.067 | I72: =Source!R34 -> 3.37 | J72: =IF(Source!BS35<> 0, Source!BS35, 1) -> 56.35 | K72: =Source!R35 -> 189.9
C73: НР от ФОТ | D73: % | E73: =Source!BZ35 -> 109 | I73: =SUM(Q68:Q72) -> 924.04 | J73: =Source!AT35 -> 109 | K73: =SUM(R68:R72) -> 52069.46
C74: СП от ФОТ | D74: % | E74: =Source!CA35 -> 61 | I74: =SUM(S68:S73) -> 517.12 | J74: =Source!AU35 -> 61 | K74: =SUM(T68:T73) -> 29139.79
C75: ЗТР | D75: чел-ч | E75: =Source!AQ34 -> 56 | G75: 0,4*1,2 | H75: =Source!AV35 -> 1.067 | I75: =Source!U34 -> 65.966208
C76: ВСЕГО работ по позиции: | H76: =I70+I71+I73+I74+0-0-0 -> 2309.32 | J76: =K70+K71+K73+K74+0-0-0 -> 129184.41
C77: ВСЕГО оборудование по позиции: | H77: =0+0 -> 0 | J77: =0+0 -> 0
C78: ВСЕГО по позиции: | H78: =I70+I71+I73+I74+0 -> 2309.32 | J78: =K70+K71+K73+K74+0 -> 129184.41 | O78: =I70+I71+I73+I74+0 -> 2309.32 | P78: =K70+K71+K73+K74+0 -> 129184.41
A80: 5 | B80: =Source!F36 -> 3.16-13-1 | C80: Прокладка трубопроводов канализации из ПВХ труб диаметром до 50 мм (демонтаж) | D80: =Source!H36 -> 100 м | E80: =Source!I36 -> 1.4 | Q80: =Source!X36 -> 585.35 | R80: =Source!X37 -> 32984.58 | S80: =Source!Y36 -> 327.58 | T80: =Source!Y37 -> 18459.26 | U80: =ROUND((175/100)*ROUND(Source!R36, 2), 2) -> 1.8 | V80: =ROUND((0/100)*ROUND(Source!R37, 2), 2) -> 0 | AC80: 0
C81: ="Объем: "&Source!I36&"=(120+"&"20)/"&"100" -> Объем: 1,4=(120+20)/100
C82: ЗП | F82: =Source!AO36 -> 747.52 | G82: 0,4*1,2 | H82: =Source!AV37 -> 1.067 | I82: =Source!S36 -> 535.99 | J82: =IF(Source!BA37<> 0, Source!BA37, 1) -> 56.35 | K82: =Source!S37 -> 30203.04
C83: ЭМ | F83: =Source!AM36 -> 10.1 | G83: 0,4*1,2 | H83: =Source!AV37 -> 1.067 | I83: =Source!Q36 -> 7.24 | J83: =IF(Source!BB37<> 0, Source!BB37, 1) -> 16.6 | K83: =Source!Q37 -> 120.18
C84: в т.ч. ЗПМ | F84: =Source!AN36 -> 1.43 | G84: 0,4*1,2 | H84: =Source!AV37 -> 1.067 | I84: =Source!R36 -> 1.03 | J84: =IF(Source!BS37<> 0, Source!BS37, 1) -> 56.35 | K84: =Source!R37 -> 58.04
C85: НР от ФОТ | D85: % | E85: =Source!BZ37 -> 109 | I85: =SUM(Q80:Q84) -> 585.35 | J85: =Source!AT37 -> 109 | K85: =SUM(R80:R84) -> 32984.58
C86: СП от ФОТ | D86: % | E86: =Source!CA37 -> 61 | I86: =SUM(S80:S85) -> 327.58 | J86: =Source!AU37 -> 61 | K86: =SUM(T80:T85) -> 18459.26
C87: ЗТР | D87: чел-ч | E87: =Source!AQ36 -> 58.4 | G87: 0,4*1,2 | H87: =Source!AV37 -> 1.067 | I87: =Source!U36 -> 41.874202
C88: ВСЕГО работ по позиции: | H88: =I82+I83+I85+I86+0-0-0 -> 1456.16 | J88: =K82+K83+K85+K86+0-0-0 -> 81767.06
C89: ВСЕГО оборудование по позиции: | H89: =0+0 -> 0 | J89: =0+0 -> 0
C90: ВСЕГО по позиции: | H90: =I82+I83+I85+I86+0 -> 1456.16 | J90: =K82+K83+K85+K86+0 -> 81767.06 | O90: =I82+I83+I85+I86+0 -> 1456.16 | P90: =K82+K83+K85+K86+0 -> 81767.06
A92: 6 | B92: =Source!F38 -> 6.65-2-2 | C92: Разборка трубопроводов из чугунных канализационных труб диаметром до 100 мм | D92: =Source!H38 -> 100 м | E92: =Source!I38 -> 1.7 | Q92: =Source!X38 -> 1864.04 | R92: =Source!X39 -> 105038.42 | S92: =Source!Y38 -> 942.73 | T92: =Source!Y39 -> 53122.88 | U92: =ROUND((175/100)*ROUND(Source!R38, 2), 2) -> 0 | V92: =ROUND((0/100)*ROUND(Source!R39, 2), 2) -> 0 | AC92: 0
C93: ="Объем: "&Source!I38&"=(140+"&"30)/"&"100" -> Объем: 1,7=(140+30)/100
C94: ЗП | F94: =Source!AO38 -> 1003.13 | G94: 1,2 | H94: =Source!AV39 -> 1.047 | I94: =Source!S38 -> 2142.57 | J94: =IF(Source!BA39<> 0, Source!BA39, 1) -> 56.35 | K94: =Source!S39 -> 120733.82
C95: НР от ФОТ | D95: % | E95: =Source!BZ39 -> 87 | I95: =SUM(Q92:Q94) -> 1864.04 | J95: =Source!AT39 -> 87 | K95: =SUM(R92:R94) -> 105038.42
C96: СП от ФОТ | D96: % | E96: =Source!CA39 -> 44 | I96: =SUM(S92:S95) -> 942.73 | J96: =Source!AU39 -> 44 | K96: =SUM(T92:T95) -> 53122.88
C97: ЗТР | D97: чел-ч | E97: =Source!AQ38 -> 85.3 | G97: 1,2 | H97: =Source!AV39 -> 1.047 | I97: =Source!U38 -> 182.19056
C98: ВСЕГО работ по позиции: | H98: =I94+I95+I96+0-0-0 -> 4949.34 | J98: =K94+K95+K96+0-0-0 -> 278895.12
C99: ВСЕГО оборудование по позиции: | H99: =0+0 -> 0 | J99: =0+0 -> 0
C100: ВСЕГО по позиции: | H100: =I94+I95+I96+0 -> 4949.34 | J100: =K94+K95+K96+0 -> 278895.12 | O100: =I94+I95+I96+0 -> 4949.34 | P100: =K94+K95+K96+0 -> 278895.12
A102: 7 | B102: =Source!F40 -> 6.65-2-1 | C102: Разборка трубопроводов из чугунных канализационных труб диаметром до 50 мм | D102: =Source!H40 -> 100 м | E102: =Source!I40 -> 0.83 | Q102: =Source!X40 -> 750.89 | R102: =Source!X41 -> 42312.55 | S102: =Source!Y40 -> 379.76 | T102: =Source!Y41 -> 21399.45 | U102: =ROUND((175/100)*ROUND(Source!R40, 2), 2) -> 0 | V102: =ROUND((0/100)*ROUND(Source!R41, 2), 2) -> 0 | AC102: 0
C103: ="Объем: "&Source!I40&"=(52+"&"21+"&"10)/"&"100" -> Объем: 0,83=(52+21+10)/100
C104: ЗП | F104: =Source!AO40 -> 827.66 | G104: 1,2 | H104: =Source!AV41 -> 1.047 | I104: =Source!S40 -> 863.09 | J104: =IF(Source!BA41<> 0, Source!BA41, 1) -> 56.35 | K104: =Source!S41 -> 48635.12
C105: НР от ФОТ | D105: % | E105: =Source!BZ41 -> 87 | I105: =SUM(Q102:Q104) -> 750.89 | J105: =Source!AT41 -> 87 | K105: =SUM(R102:R104) -> 42312.55
C106: СП от ФОТ | D106: % | E106: =Source!CA41 -> 44 | I106: =SUM(S102:S105) -> 379.76 | J106: =Source!AU41 -> 44 | K106: =SUM(T102:T105) -> 21399.45
C107: ЗТР | D107: чел-ч | E107: =Source!AQ40 -> 68.8 | G107: 1,2 | H107: =Source!AV41 -> 1.047 | I107: =Source!U40 -> 71.745466
C108: ВСЕГО работ по позиции: | H108: =I104+I105+I106+0-0-0 -> 1993.74 | J108: =K104+K105+K106+0-0-0 -> 112347.12
C109: ВСЕГО оборудование по позиции: | H109: =0+0 -> 0 | J109: =0+0 -> 0
C110: ВСЕГО по позиции: | H110: =I104+I105+I106+0 -> 1993.74 | J110: =K104+K105+K106+0 -> 112347.12 | O110: =I104+I105+I106+0 -> 1993.74 | P110: =K104+K105+K106+0 -> 112347.12
A112: 8 | B112: =Source!F42 -> 6.65-4-3 | C112: Демонтаж санитарно-технических приборов унитазов со смывным бачком | D112: =Source!H42 -> 100 комплектов | E112: =Source!I42 -> 0.38 | Q112: =Source!X42 -> 698.51 | R112: =Source!X43 -> 39361.28 | S112: =Source!Y42 -> 353.27 | T112: =Source!Y43 -> 19906.85 | U112: =ROUND((175/100)*ROUND(Source!R42, 2), 2) -> 0 | V112: =ROUND((0/100)*ROUND(Source!R43, 2), 2) -> 0 | AC112: 0
C113: ="Объем: "&Source!I42&"=(37+"&"1)/"&"100" -> Объем: 0,38=(37+1)/100
C114: ЗП | F114: =Source!AO42 -> 1681.68 | G114: 1,2 | H114: =Source!AV43 -> 1.047 | I114: =Source!S42 -> 802.89 | J114: =IF(Source!BA43<> 0, Source!BA43, 1) -> 56.35 | K114: =Source!S43 -> 45242.85
...

Sheet Source
A1: 0 | B1: Smeta.RU (495) 974-1589 | D1: _PS_ | F1: 0 | G1: 0 | H1: 0 | I1: Smeta.RU | K1: 1 | L1: 74603 | M1: 10 | N1: 12 | O1: 1 | P1: 0 | Q1: 1
A4: 8 | B4: 1 | C4: -1 | F4: Новый проект | G4: Капитальный ремонт здания Государственного бюджетного общеобразовательного учреждения города Москвы «Школа №1574», расположенного по адресу: г. Москва, Старопименовский переулок, д. 5. 1 этап | EC4: 0
A12: 1 | B12: 717 | C12: 0 | D12: =ROW(A676) -> 676 | E12: 0 | F12: Новый объект строительства | I12: 0 | J12: 2024-00375-01-01-ИОС3. | K12: 0 | L12: 0 | M12: 4098 | O12: 0 | P12: 0 | Q12: 0 | R12: 0 | S12: 0 | T12: 1 | V12: 2 | BB12: 0 | BH12: Сметные нормы списания | BI12: Коды ОКП для ТСН-2001 МГЭ Дополнение 81 | BJ12: 1 | BK12: 1 | BL12: 0 | BM12: 0 | BN12: 1 | BO12: 0 | BP12: 6 | BQ12: 2 | BR12: 1 | BS12: 1 | BT12: 0 | BU12: 0 | BV12: 0 | BW12: 0 | BX12: 0 | BY12: ТСН-2001 (МГЭ) Доп 81 - Ремонт | BZ12: Типовой расчет для ТСН-2001 МГЭ, Дополнение 81, ремонт | CA12: Территориальные сметные нормативы для Москвы ТСН-2001 (МГЭ), дополнение 81 | CB12: Территориальные сметные нормативы для Москвы ТСН-2001 (МГЭ), дополнение 81 | CC12: Территориальные сметные нормативы для Москвы ТСН-2001 (МГЭ), дополнение 81 | CD12: Территориальные сметные нормативы для Москвы ТСН-2001 (МГЭ), дополнение 81 | CE12: Поправки для ТСН-2001 от 07.04.2026 г. доп.81 | CF12: 0 | CG12: 0 | CH12: 8200 | CK12: 81 | CQ12: Территориальные сметные нормативы для Москвы (ТСН-2001) | CR12: ТЕР | CS12: 41660 | CT12: 1 | CU12: 81 | CY12: 0 | EC12: 0
A15: 15 | B15: 1
A18: 52 | B18: =B676 -> 717 | C18: =C676 -> 1 | D18: =D676 -> 12 | E18: =E676 -> 0 | F18: =F676 -> Новый объект строительства | G18: =G676 | O18: =O676 -> 748838.28 | P18: =P676 -> 722350.83 | Q18: =Q676 -> 1237.2 | R18: =R676 -> 155.8 | S18: =S676 -> 25250.25 | T18: =T676 -> 0 | U18: =U676 -> 2029.9267 | V18: =V676 -> 0 | ... GX18: =GX676 -> 0
A20: 3 | B20: 1 | D20: =ROW(A643) -> 643 | F20: 02-01-05 | G20: Система водоотведения. | I20: 0 | J20: 2024-00375-01-0-ИОС3 | K20: -1 | L20: 02-01-05 | S20: 0 | T20: 0 | V20: 2 | BX20: 0 | CF20: 0 | CG20: 0
A22: 52 | B22: =B643 -> 1 | C22: =C643 -> 3 | D22: =D643 -> 20 | E22: =E643 -> 0 | F22: =F643 -> 02-01-05 | G22: =G643 -> Система водоотведения. | O22: =O643 -> 748838.28 | P22: =P643 -> 722350.83 | Q22: =Q643 -> 1237.2 | R22: =R643 -> 155.8 | S22: =S643 -> 25250.25 | T22: =T643 -> 0 | U22: =U643 -> 2029.9267 | V22: =V643 -> 0 | ... GX22: =GX643 -> 0
A24: 4 | B24: 1 | D24: =ROW(A49) -> 49 | F24: Новый раздел | G24: Демонтажные работы. | I24: 0 | K24: 0 | S24: 0 | T24: 0 | V24: 2 | BX24: 0 | CJ24: 0
A26: 52 | B26: =B49 -> 1 | C26: =C49 -> 4 | D26: =D49 -> 24 | E26: =E49 -> 0 | F26: =F49 -> Новый раздел | G26: =G49 -> Демонтажные работы. | O26: =O49 -> 6485.62 | P26: =P49 -> 29.07 | Q26: =Q49 -> 35.06 | R26: =R49 -> 4.59 | S26: =S49 -> 6421.49 | T26: =T49 -> 0 | U26: =U49 -> 537.80137 | V26: =V49 -> 0 | ... GX26: =GX49 -> 0
A28: 17 | B28: 1 | C28: =ROW(SmtRes!A5) -> 5 | D28: =ROW(EtalonRes!A5) -> 5 | E28: 1 | F28: 6.65-1-2 | G28: Разборка трубопроводов из водогазопроводных труб диаметром до 40 мм | H28: 100 м | I28: =ROUND((30+8)/100,9) -> 0.38 | J28: 0 | K28: =ROUND((30+8)/100,9) -> 0.38 | O28: =ROUND(CP28,2) -> 254.81 | P28: =ROUND((ROUND((AC28*AW28*I28),2)*BC28),2) -> 17.54 | Q28: =(ROUND((ROUND((((ET28*1.2))*AV28*I28),2)*BB28),2)+ROUND((ROUND(((AE28-((EU28*1.2)))*AV28*I28),2)*BS28),2)) -> 0.6 | R28: =(ROUND((ROUND((((EU28*1.2))*AV28*I28),2)*BS28),2)+ROUND((ROUND(((AE28-((EU28*1.2)))*AV28*I28),2)*BS28),2)) -> 0 | S28: =ROUND((ROUND((AF28*AV28*I28),2)*BA28),2) -> 236.67 | T28: =ROUND(CU28*I28,2) -> 0 | U28: =CV28*I28 -> 21.732705 | V28: =CW28*I28 -> 0 | W28: =ROUND(CX28*I28,2) -> 0 | X28: =(ROUND((((S28+ROUND((ROUND((((EU28*1.2))*AV28*I28),2)*BS28),2))*AT28)/100),2)+ROUND(((ROUND((ROUND(((AE28-((EU28*1.2)))*AV28*I28),2)*BS28),2)*AT28)/100),2)) -> 205.9 | Y28: =(ROUND((((S28+ROUND((ROUND((((EU28*1.2))*AV28*I28),2)*BS28),2))*AU28)/100),2)+ROUND(((ROUND((ROUND(((AE28-((EU28*1.2)))*AV28*I28),2)*BS28),2)*AU28)/100),2)) -> 104.13 | AA28: 86549534 | AB28: =ROUND((AC28+AD28+AF28),6) -> 642.524 | AC28: =ROUND(((ES28*1)),6) -> 46.16 | AD28: =ROUND(((((ET28*1.2))-((EU28*1.2)))+AE28),6) -> 1.512 | AE28: =ROUND(((EU28*1.2)),6) -> 0 | AF28: =ROUND(((EV28*1.2)),6) -> 594.852 | AG28: =ROUND((AP28),6) -> 0 | AH28: =((EW28*1.2)) -> 54.624 | AI28: =((EX28*1.2)) -> 0 | AJ28: =(AS28) -> 0 | AK28: 543.13 | AL28: 46.16 | AM28: 1.26 | AN28: 0 | AO28: 495.71 | AP28: 0 | AQ28: 45.52 | AR28: 0 | AS28: 0 | AT28: 87 | AU28: 44 | AV28: 1.047 | AW28: 1 | AZ28: 1 | BA28: 1 | BB28: 1 | BC28: 1 | BH28: 0 | BI28: 1 | BJ28: ТСН-2001.6 Доп. 79, Сб. 65, т. 1, поз. 2 | BM28: 102 | BN28: 0 | BO28: 6.65-1-2 | BP28: 1 | BQ28: 60 | BR28: 0 | BS28: 1 | BT28: 1 | BU28: 1 | BV28: 1 | BW28: 1 | BX28: 1 | BZ28: 87 | CA28: 44 | CE28: 1566 | CF28: 0 | CG28: 0 | CM28: 0 | CN28: Поправка: Гл.12.Прил.8.п.8. 3_12.00.01.11.001 Наименование: При наличии напряженных и стесненных условий производства работ (стесненность, сложность складирования и транспортной логистики и т.п.) для объектов, расположенных в пределах круговой магистральной системы улиц "Садовое кольцо" города Москвы | CO28: 0 | CP28: =(P28+Q28+S28) -> 254.81 | CQ28: =ROUND((ROUND((AC28*AW28*1),2)*BC28),2) -> 46.16 | CR28: =(ROUND((ROUND((((ET28*1.2))*AV28*1),2)*BB28),2)+ROUND((ROUND(((AE28-((EU28*1.2)))*AV28*1),2)*BS28),2)) -> 1.58 | CS28: =(ROUND((ROUND((((EU28*1.2))*AV28*1),2)*BS28),2)+ROUND((ROUND(((AE28-((EU28*1.2)))*AV28*1),2)*BS28),2)) -> 0 | CT28: =ROUND((ROUND((AF28*AV28*1),2)*BA28),2) -> 622.81 | CU28: =AG28 -> 0 | CV28: =(AH28*AV28) -> 57.191328 | CW28: =AI28 -> 0 | CX28: =AJ28 -> 0 | CY28: =(ROUND((((S28+ROUND((ROUND((((EU28*1.2))*AV28*1),2)*BS28),2))*AT28)/100),2)+ROUND(((ROUND((ROUND(((AE28-((EU28*1.2)))*AV28*1),2)*BS28),2)*AT28)/100),2)) -> 205.9 | CZ28: =(ROUND((((S28+ROUND((ROUND((((EU28*1.2))*AV28*1),2)*BS28),2))*AU28)/100),2)+ROUND(((ROUND((ROUND(((AE28-((EU28*1.2)))*AV28*1),2)*BS28),2)*AU28)/100),2)) -> 104.13 | DB28: 1 | DD28: *1 | DE28: *1,2 | DF28: *1,2 | DG28: *1,2 | DI28: *1,2 | DJ28: *1,2 | DN28: 0 | DO28: 0 | DP28: 1 | DQ28: 1 | DU28: 1003 | DV28: 100 м | DW28: 100 м | DX28: 100 | EE28: 85635475 | EF28: 60 | EG28: Ремонтно-строительные работы | EH28: 0 | EJ28: 1 | EK28: 102 | EL28: ТСН-2001.6-65. Внутренние санитарно-технические работы: демонтаж и разборка | EM28: ТСН-2001.6-65-1 | EO28: Поправка: Гл.12.Прил.8.п.8. 3_12.00.01.11.001 | EQ28: 131072 | ER28: 543.13 | ES28: 46.16 | ET28: 1.26 | EU28: 0 | EV28: 495.71 | EW28: 45.52 | EX28: 0 | EY28: 0 | FQ28: 0 | FR28: 0 | FS28: 0 | FX28: 87 | FY28: 44 | GD28: 1 | GF28: -1242219818 | GG28: 2 | GH28: 1 | GI28: 2 | GJ28: 0 | GK28: 0 | GL28: =ROUND(IF(AND(BH28=3,BI28=3,FS28<>0),P28,0),2) -> 0 | GM28: =ROUND(O28+X28+Y28,2)+GX28 -> 564.84 | GN28: =IF(OR(BI28=0,BI28=1),GM28-GX28,0) -> 564.84 | GO28: =IF(BI28=2,GM28-GX28,0) -> 0 | GP28: =IF(BI28=4,GM28-GX28,0) -> 0 | GR28: 0 | GS28: 3 | GT28: 0 | GV28: =ROUND((GT28),6) -> 0 | GW28: 1 | GX28: =ROUND(HC28*I28,2) -> 0 | HA28: 0 | HB28: 0 | HC28: =GV28*GW28 -> 0 | HS28: 0 | IK28: 0
A29: 17 | B29: 1 | C29: =ROW(SmtRes!A10) -> 10 | D29: =ROW(EtalonRes!A10) -> 10 | E29: 1 | F29: 6.65-1-2 | G29: Разборка трубопроводов из водогазопроводных труб диаметром до 40 мм | H29: 100 м | I29: =ROUND((30+8)/100,9) -> 0.38 | J29: 0 | K29: =ROUND((30+8)/100,9) -> 0.38 | O29: =ROUND(CP29,2) -> 13614.32 | P29: =ROUND((ROUND((AC29*AW29*I29),2)*BC29),2) -> 272.4 | Q29: =(ROUND((ROUND((((ET29*1.2))*AV29*I29),2)*BB29),2)+ROUND((ROUND(((AE29-((EU29*1.2)))*AV29*I29),2)*BS29),2)) -> 5.57 | R29: =(ROUND((ROUND((((EU29*1.2))*AV29*I29),2)*BS29),2)+ROUND((ROUND(((AE29-((EU29*1.2)))*AV29*I29),2)*BS29),2)) -> 0 | S29: =ROUND((ROUND((AF29*AV29*I29),2)*BA29),2) -> 13336.35 | T29: =ROUND(CU29*I29,2) -> 0 | U29: =CV29*I29 -> 21.732705 | V29: =CW29*I29 -> 0 | W29: =ROUND(CX29*I29,2) -> 0 | X29: =(ROUND((((S29+ROUND((ROUND((((EU29*1.2))*AV29*I29),2)*BS29),2))*AT29)/100),2)+ROUND(((ROUND((ROUND(((AE29-((EU29*1.2)))*AV29*I29),2)*BS29),2)*AT29)/100),2)) -> 11602.62 | Y29: =(ROUND((((S29+ROUND((ROUND((((EU29*1.2))*AV29*I29),2)*BS29),2))*AU29)/100),2)+ROUND(((ROUND((ROUND(((AE29-((EU29*1.2)))*AV29*I29),2)*BS29),2)*AU29)/100),2)) -> 5867.99 | AA29: 86549536 | AB29: =ROUND((AC29+AD29+AF29),6) -> 642.524 | AC29: =ROUND(((ES29*1)),6) -> 46.16 | AD29: =ROUND(((((ET29*1.2))-((EU29*1.2)))+AE29),6) -> 1.512 | AE29: =ROUND(((EU29*1.2)),6) -> 0 | AF29: =ROUND(((EV29*1.2)),6) -> 594.852 | AG29: =ROUND((AP29),6) -> 0 | AH29: =((EW29*1.2)) -> 54.624 | AI29: =((EX29*1.2)) -> 0 | AJ29: =(AS29) -> 0 | AK29: 543.13 | AL29: 46.16 | AM29: 1.26 | AN29: 0 | AO29: 495.71 | AP29: 0 | AQ29: 45.52 | AR29: 0 | AS29: 0 | AT29: 87 | AU29: 44 | AV29: 1.047 | AW29: 1 | AZ29: 1 | BA29: 56.35 | BB29: 9.29 | BC29: 15.53 | BH29: 0 | BI29: 1 | BJ29: ТСН-2001.6 Доп. 79, Сб. 65, т. 1, поз. 2 | BM29: 102 | BN29: 0 | BO29: 6.65-1-2 | BP29: 1 | BQ29: 60 | BR29: 0 | BS29: 56.35 | BT29: 1 | BU29: 1 | BV29: 1 | BW29: 1 | BX29: 1 | BZ29: 87 | CA29: 44 | CE29: 1566 | CF29: 0 | CG29: 0 | CM29: 0 | CN29: Поправка: Гл.12.Прил.8.п.8. 3_12.00.01.11.001 Наименование: При наличии напряженных и стесненных условий производства работ (стесненность, сложность складирования и транспортной логистики и т.п.) для объектов, расположенных в пределах круговой магистральной системы улиц "Садовое кольцо" города Москвы | CO29: 0 | CP29: =(P29+Q29+S29) -> 13614.32 | CQ29: =ROUND((ROUND((AC29*AW29*1),2)*BC29),2) -> 716.86 | CR29: =(ROUND((ROUND((((ET29*1.2))*AV29*1),2)*BB29),2)+ROUND((ROUND(((AE29-((EU29*1.2)))*AV29*1),2)*BS29),2)) -> 14.68 | CS29: =(ROUND((ROUND((((EU29*1.2))*AV29*1),2)*BS29),2)+ROUND((ROUND(((AE29-((EU29*1.2)))*AV29*1),2)*BS29),2)) -> 0 | CT29: =ROUND((ROUND((AF29*AV29*1),2)*BA29),2) -> 35095.34 | CU29: =AG29 -> 0 | CV29: =(AH29*AV29) -> 57.191328 | CW29: =AI29 -> 0 | CX29: =AJ29 -> 0 | CY29: =(ROUND((((S29+ROUND((ROUND((((EU29*1.2))*AV29*1),2)*BS29),2))*AT29)/100),2)+ROUND(((ROUND((ROUND(((AE29-((EU29*1.2)))*AV29*1),2)*BS29),2)*AT29)/100),2)) -> 11602.62 | CZ29: =(ROUND((((S29+ROUND((ROUND((((EU29*1.2))*AV29*1),2)*BS29),2))*AU29)/100),2)+ROUND(((ROUND((ROUND(((AE29-((EU29*1.2)))*AV29*1),2)*BS29),2)*AU29)/100),2)) -> 5867.99 | DB29: 2 | DD29: *1 | DE29: *1,2 | DF29: *1,2 | DG29: *1,2 | DI29: *1,2 | DJ29: *1,2 | DN29: 0 | DO29: 0 | DP29: 1 | DQ29: 1 | DU29: 1003 | DV29: 100 м | DW29: 100 м | DX29: 100 | EE29: 85635475 | EF29: 60 | EG29: Ремонтно-строительные работы | EH29: 0 | EJ29: 1 | EK29: 102 | EL29: ТСН-2001.6-65. Внутренние санитарно-технические работы: демонтаж и разборка | EM29: ТСН-2001.6-65-1 | EO29: Поправка: Гл.12.Прил.8.п.8. 3_12.00.01.11.001 | EQ29: 131072 | ER29: 543.13 | ES29: 46.16 | ET29: 1.26 | EU29: 0 | EV29: 495.71 | EW29: 45.52 | EX29: 0 | EY29: 0 | FQ29: 0 | FR29: 0 | FS29: 0 | FX29: 87 | FY29: 44 | GD29: 1 | GF29: -1242219818 | GG29: 2 | GH29: 1 | GI29: 2 | GJ29: 0 | GK29: 0 | GL29: =ROUND(IF(AND(BH29=3,BI29=3,FS29<>0),P29,0),2) -> 0 | GM29: =ROUND(O29+X29+Y29,2)+GX29 -> 31084.93 | GN29: =IF(OR(BI29=0,BI29=1),GM29-GX29,0) -> 31084.93 | GO29: =IF(BI29=2,GM29-GX29,0) -> 0 | GP29: =IF(BI29=4,GM29-GX29,0) -> 0 | GR29: 0 | GS29: 3 | GT29: 0 | GV29: =ROUND((GT29),6) -> 0 | GW29: 1 | GX29: =ROUND(HC29*I29,2) -> 0 | HA29: 0 | HB29: 0 | HC29: =GV29*GW29 -> 0 | HS29: 0 | IK29: 0
A30: 17 | B30: 1 | C30: =ROW(SmtRes!A15) -> 15 | D30: =ROW(EtalonRes!A15) -> 15 | E30: 2 | F30: 6.65-11-5 | G30: Разборка трубопроводов центрального отопления на сварке диаметром труб до 100 мм | H30: 100 м | I30: =ROUND(15/100,9) -> 0.15 | J30: 0 | K30: =ROUND(15/100,9) -> 0.15 | O30: =ROUND(CP30,2) -> 138.45 | P30: =ROUND((ROUND((AC30*AW30*I30),2)*BC30),2) -> 11.53 | Q30: =(ROUND((ROUND(((((ET30*1)*1.2))*AV30*I30),2)*BB30),2)+ROUND((ROUND(((AE30-(((EU30*1)*1.2)))*AV30*I30),2)*BS30),2)) -> 0.34 | R30: =(ROUND((ROUND(((((EU30*1)*1.2))*AV30*I30),2)*BS30),2)+ROUND((ROUND(((AE30-(((EU30*1)*1.2)))*AV30*I30),2)*BS30),2)) -> 0 | S30: =ROUND((ROUND((AF30*AV30*I30),2)*BA30),2) -> 126.58 | T30: =ROUND(CU30*I30,2) -> 0 | U30: =CV30*I30 -> 11.517658 | V30: =CW30*I30 -> 0 | W30: =ROUND(CX30*I30,2) -> 0 | X30: =(ROUND((((S30+ROUND((ROUND(((((EU30*1)*1.2))*AV30*I30),2)*BS30),2))*AT30)/100),2)+ROUND(((ROUND((ROUND(((AE30-(((EU30*1)*1.2)))*AV30*I30),2)*BS30),2)*AT30)/100),2)) -> 110.12 | Y30: =(ROUND((((S30+ROUND((ROUND(((((EU30*1)*1.2))*AV30*I30),2)*BS30),2))*AU30)/100),2)+ROUND(((ROUND((ROUND(((AE30-(((EU30*1)*1.2)))*AV30*I30),2)*BS30),2)*AU30)/100),2)) -> 55.7 | AA30: 86549534 | AB30: =ROUND((AC30+AD30+AF30),6) -> 884.99872 | AC30: =ROUND((((ES30*1)*1)),6) -> 76.84 | AD30: =ROUND((((((ET30*1)*1.2))-(((EU30*1)*1.2)))+AE30),6) -> 2.184 | AE30: =ROUND((((EU30*1)*1.2)),6) -> 0 | AF30: =ROUND((((EV30*0.82)*1.2)),6) -> 805.97472 | AG30: =ROUND((AP30),6) -> 0 | AH30: =(((EW30*0.82)*1.2)) -> 73.33752 | AI30: =(((EX30*1)*1.2)) -> 0 | AJ30: =(AS30) -> 0 | AK30: 897.74 | AL30: 76.84 | AM30: 1.82 | AN30: 0 | AO30: 819.08 | AP30: 0 | AQ30: 74.53 | AR30: 0 | AS30: 0 | AT30: 87 | AU30: 44 | AV30: 1.047 | AW30: 1 | AZ30: 1 | BA30: 1 | BB30: 1 | BC30: 1 | BH30: 0 | BI30: 1 | BJ30: ТСН-2001.6 Доп. 79, Сб. 65, т. 11, поз. 5 | BM30: 102 | BN30: 0 | BO30: 6.65-11-5 | BP30: 1 | BQ30: 60 | BR30: 0 | BS30: 1 | BT30: 1 | BU30: 1 | BV30: 1 | BW30: 1 | BX30: 1 | BZ30: 87 | CA30: 44 | CE30: 1566 | CF30: 0 | CG30: 0 | CM30: 0 | CN30: Поправка: Сб.6-65.т3.1.п.3.1.6_06.65.01.28.002 Наименование: При разборке трубопроводов без правки и чистки труб и фасонных частей от накипи и грязи Поправка: Гл.12.Прил.8.п.8. 3_12.00.01.11.001 Наименование: При наличии напряженных и стесненных условий производства работ (стесненность, сложность складирования и транспортной логистики и т.п.) для объектов, расположенных в пределах круговой магистральной системы улиц "Садовое кольцо" города Москвы | CO30: 0 | CP30: =(P30+Q30+S30) -> 138.45 | CQ30: =ROUND((ROUND((AC30*AW30*1),2)*BC30),2) -> 76.84 | CR30: =(ROUND((ROUND(((((ET30*1)*1.2))*AV30*1),2)*BB30),2)+ROUND((ROUND(((AE30-(((EU30*1)*1.2)))*AV30*1),2)*BS30),2)) -> 2.29 | CS30: =(ROUND((ROUND(((((EU30*1)*1.2))*AV30*1),2)*BS30),2)+ROUND((ROUND(((AE30-(((EU30*1)*1.2)))*AV30*1),2)*BS30),2)) -> 0 | CT30: =ROUND((ROUND((AF30*AV30*1),2)*BA30),2) -> 843.86 | CU30: =AG30 -> 0 | CV30: =(AH30*AV30) -> 76.784383 | CW30: =AI30 -> 0 | CX30: =AJ30 -> 0 | CY30: =(ROUND((((S30+ROUND((ROUND(((((EU30*1)*1.2))*AV30*1),2)*BS30),2))*AT30)/100),2)+ROUND(((ROUND((ROUND(((AE30-(((EU30*1)*1.2)))*AV30*1),2)*BS30),2)*AT30)/100),2)) -> 110.12 | CZ30: =(ROUND((((S30+ROUND((ROUND(((((EU30*1)*1.2))*AV30*1),2)*BS30),2))*AU30)/100),2)+ROUND(((ROUND((ROUND(((AE30-(((EU30*1)*1.2)))*AV30*1),2)*BS30),2)*AU30)/100),2)) -> 55.7 | DB30: 3 | DD30: *1)*1 | DE30: *1)*1,2 | DF30: *1)*1,2 | DG30: *0,82)*1,2 | DI30: *0,82)*1,2 | DJ30: *1)*1,2 | DN30: 0 | DO30: 0 | DP30: 1 | DQ30: 1 | DU30: 1003 | DV30: 100 м | DW30: 100 м | DX30: 100 | EE30: 85635475 | EF30: 60 | EG30: Ремонтно-строительные работы | EH30: 0 | EJ30: 1 | EK30: 102 | EL30: ТСН-2001.6-65. Внутренние санитарно-технические работы: демонтаж и разборка | EM30: ТСН-2001.6-65-1 | EO30: Поправка: Сб.6-65.т3.1.п.3.1.6_06.65.01.28.002 Поправка: Гл.12.Прил.8.п.8. 3_12.00.01.11.001 | EQ30: 131072 | ER30: 897.74 | ES30: 76.84 | ET30: 1.82 | EU30: 0 | EV30: 819.08 | EW30: 74.53 | EX30: 0 | EY30: 0 | FQ30: 0 | FR30: 0 | FS30: 0 | FX30: 87 | FY30: 44 | GD30: 1 | GF30: 1211388190 | GG30: 2 | GH30: 1 | GI30: 2 | GJ30: 0 | GK30: 0 | GL30: =ROUND(IF(AND(BH30=3,BI30=3,FS30<>0),P30,0),2) -> 0 | GM30: =ROUND(O30+X30+Y30,2)+GX30 -> 304.27 | GN30: =IF(OR(BI30=0,BI30=1),GM30-GX30,0) -> 304.27 | GO30: =IF(BI30=2,GM30-GX30,0) -> 0 | GP30: =IF(BI30=4,GM30-GX30,0) -> 0 | GR30: 0 | GS30: 3 | GT30: 0 | GV30: =ROUND((GT30),6) -> 0 | GW30: 1 | GX30: =ROUND(HC30*I30,2) -> 0 | HA30: 0 | HB30: 0 | HC30: =GV30*GW30 -> 0 | HS30: 0 | IK30: 0
A31: 17 | B31: 1 | C31: =ROW(SmtRes!A20) -> 20 | D31: =ROW(EtalonRes!A20) -> 20 | E31: 2 | F31: 6.65-11-5 | G31: Разборка трубопроводов центрального отопления на сварке диаметром труб до 100 мм | H31: 100 м | I31: =ROUND(15/100,9) -> 0.15 | J31: 0 | K31: =ROUND(15/100,9) -> 0.15 | O31: =ROUND(CP31,2) -> 7315 | P31: =ROUND((ROUND((AC31*AW31*I31),2)*BC31),2) -> 179.06 | Q31: =(ROUND((ROUND(((((ET31*1)*1.2))*AV31*I31),2)*BB31),2)+ROUND((ROUND(((AE31-(((EU31*1)*1.2)))*AV31*I31),2)*BS31),2)) -> 3.16 | R31: =(ROUND((ROUND(((((EU31*1)*1.2))*AV31*I31),2)*BS31),2)+ROUND((ROUND(((AE31-(((EU31*1)*1.2)))*AV31*I31),2)*BS31),2)) -> 0 | S31: =ROUND((ROUND((AF31*AV31*I31),2)*BA31),2) -> 7132.78 | T31: =ROUND(CU31*I31,2) -> 0 | U31: =CV31*I31 -> 11.517658 | V31: =CW31*I31 -> 0 | W31: =ROUND(CX31*I31,2) -> 0 | X31: =(ROUND((((S31+ROUND((ROUND(((((EU31*1)*1.2))*AV31*I31),2)*BS31),2))*AT31)/100),2)+ROUND(((ROUND((ROUND(((AE31-(((EU31*1)*1.2)))*AV31*I31),2)*BS31),2)*AT31)/100),2)) -> 6205.52 | Y31: =(ROUND((((S31+ROUND((ROUND(((((EU31*1)*1.2))*AV31*I31),2)*BS31),2))*AU31)/100),2)+ROUND(((ROUND((ROUND(((AE31-(((EU31*1)*1.2)))*AV31*I31),2)*BS31),2)*AU31)/100),2)) -> 3138.42 | AA31: 86549536 | AB31: =ROUND((AC31+AD31+AF31),6) -> 884.99872 | AC31: =ROUND((((ES31*1)*1)),6) -> 76.84 | AD31: =ROUND((((((ET31*1)*1.2))-(((EU31*1)*1.2)))+AE31),6) -> 2.184 | AE31: =ROUND((((EU31*1)*1.2)),6) -> 0 | AF31: =ROUND((((EV31*0.82)*1.2)),6) -> 805.97472 | AG31: =ROUND((AP31),6) -> 0 | AH31: =(((EW31*0.82)*1.2)) -> 73.33752 | AI31: =(((EX31*1)*1.2)) -> 0 | AJ31: =(AS31) -> 0 | AK31: 897.74 | AL31: 76.84 | AM31: 1.82 | AN31: 0 | AO31: 819.08 | AP31: 0 | AQ31: 74.53 | AR31: 0 | AS31: 0 | AT31: 87 | AU31: 44 | AV31: 1.047 | AW31: 1 | AZ31: 1 | BA31: 56.35 | BB31: 9.29 | BC31: 15.53 | BH31: 0 | BI31: 1 | BJ31: ТСН-2001.6 Доп. 79, Сб. 65, т. 11, поз. 5 | BM31: 102 | BN31: 0 | BO31: 6.65-11-5 | BP31: 1 | BQ31: 60 | BR31: 0 | BS31: 56.35 | BT31: 1 | BU31: 1 | BV31: 1 | BW31: 1 | BX31: 1 | BZ31: 87 | CA31: 44 | CE31: 1566 | CF31: 0 | CG31: 0 | CM31: 0 | CN31: Поправка: Сб.6-65.т3.1.п.3.1.6_06.65.01.28.002 Наименование: При разборке трубопроводов без правки и чистки труб и фасонных частей от накипи и грязи Поправка: Гл.12.Прил.8.п.8. 3_12.00.01.11.001 Наименование: При наличии напряженных и стесненных условий производства работ (стесненность, сложность складирования и транспортной логистики и т.п.) для объектов, расположенных в пределах круговой магистральной системы улиц "Садовое кольцо" города Москвы | CO31: 0 | CP31: =(P31+Q31+S31) -> 7315 | CQ31: =ROUND((ROUND((AC31*AW31*1),2)*BC31),2) -> 1193.33 | CR31: =(ROUND((ROUND(((((ET31*1)*1.2))*AV31*1),2)*BB31),2)+ROUND((ROUND(((AE31-(((EU31*1)*1.2)))*AV31*1),2)*BS31),2)) -> 21.27 | CS31: =(ROUND((ROUND(((((EU31*1)*1.2))*AV31*1),2)*BS31),2)+ROUND((ROUND(((AE31-(((EU31*1)*1.2)))*AV31*1),2)*BS31),2)) -> 0 | CT31: =ROUND((ROUND((AF31*AV31*1),2)*BA31),2) -> 47551.51 | CU31: =AG31 -> 0 | CV31: =(AH31*AV31) -> 76.784383 | CW31: =AI31 -> 0 | CX31: =AJ31 -> 0 | CY31: =(ROUND((((S31+ROUND((ROUND(((((EU31*1)*1.2))*AV31*1),2)*BS31),2))*AT31)/100),2)+ROUND(((ROUND((ROUND(((AE31-(((EU31*1)*1.2)))*AV31*1),2)*BS31),2)*AT31)/100),2)) -> 6205.52 | CZ31: =(ROUND((((S31+ROUND((ROUND(((((EU31*1)*1.2))*AV31*1),2)*BS31),2))*AU31)/100),2)+ROUND(((ROUND((ROUND(((AE31-(((EU31*1)*1.2)))*AV31*1),2)*BS31),2)*AU31)/100),2)) -> 3138.42 | DB31: 5 | DD31: *1)*1 | DE31: *1)*1,2 | DF31: *1)*1,2 | DG31: *0,82)*1,2 | DI31: *0,82)*1,2 | DJ31: *1)*1,2 | DN31: 0 | DO31: 0 | DP31: 1 | DQ31: 1 | DU31: 1003 | DV31: 100 м | DW31: 100 м | DX31: 100 | EE31: 85635475 | EF31: 60 | EG31: Ремонтно-строительные работы | EH31: 0 | EJ31: 1 | EK31: 102 | EL31: ТСН-2001.6-65. Внутренние санитарно-технические работы: демонтаж и разборка | EM31: ТСН-2001.6-65-1 | EO31: Поправка: Сб.6-65.т3.1.п.3.1.6_06.65.01.28.002 Поправка: Гл.12.Прил.8.п.8. 3_12.00.01.11.001 | EQ31: 131072 | ER31: 897.74 | ES31: 76.84 | ET31: 1.82 | EU31: 0 | EV31: 819.08 | EW31: 74.53 | EX31: 0 | EY31: 0 | FQ31: 0 | FR31: 0 | FS31: 0 | FX31: 87 | FY31: 44 | GD31: 1 | GF31: 1211388190 | GG31: 2 | GH31: 1 | GI31: 2 | GJ31: 0 | GK31: 0 | GL31: =ROUND(IF(AND(BH31=3,BI31=3,FS31<>0),P31,0),2) -> 0 | GM31: =ROUND(O31+X31+Y31,2)+GX31 -> 16658.94 | GN31: =IF(OR(BI31=0,BI31=1),GM31-GX31,0) -> 16658.94 | GO31: =IF(BI31=2,GM31-GX31,0) -> 0 | GP31: =IF(BI31=4,GM31-GX31,0) -> 0 | GR31: 0 | GS31: 3 | GT31: 0 | GV31: =ROUND((GT31),6) -> 0 | GW31: 1 | GX31: =ROUND(HC31*I31,2) -> 0 | HA31: 0 | HB31: 0 | HC31: =GV31*GW31 -> 0 | HS31: 0 | IK31: 0
A32: 17 | B32: 1 | C32: =ROW(SmtRes!A28) -> 28 | D32: =ROW(EtalonRes!A33) -> 33 | E32: 3 | F32: 3.16-40-4 | G32: Прокладка напорного трубопровода водоснабжения и отопления из многослойного полипропилена, армированного стекловолокном, из заранее собранных узлов, наружный диаметр 40 мм (демонтаж) | H32: 100 м | I32: =ROUND((25)/100,9) -> 0.25 | J32: 0 | K32: =ROUND((25)/100,9) -> 0.25 | O32: =ROUND(CP32,2) -> 24.43 | P32: =ROUND((ROUND((AC32*AW32*I32),2)*BC32),2) -> 0 | Q32: =(ROUND((ROUND(((((ET32*0.4)*1.2))*AV32*I32),2)*BB32),2)+ROUND((ROUND(((AE32-(((EU32*0.4)*1.2)))*AV32*I32),2)*BS32),2)) -> 3.09 | R32: =(ROUND((ROUND(((((EU32*0.4)*1.2))*AV32*I32),2)*BS32),2)+ROUND((ROUND(((AE32-(((EU32*0.4)*1.2)))*AV32*I32),2)*BS32),2)) -> 0.19 | S32: =ROUND((ROUND((AF32*AV32*I32),2)*BA32),2) -> 21.34 | T32: =ROUND(CU32*I32,2) -> 0 | U32: =CV32*I32 -> 1.7311008 | V32: =CW32*I32 -> 0 | W32: =ROUND(CX32*I32,2) -> 0 | X32: =(ROUND((((S32+ROUND((ROUND(((((EU32*0.4)*1.2))*AV32*I32),2)*BS32),2))*AT32)/100),2)+ROUND(((ROUND((ROUND(((AE32-(((EU32*0.4)*1.2)))*AV32*I32),2)*BS32),2)*AT32)/100),2)) -> 23.47 | Y32: =(ROUND((((S32+ROUND((ROUND(((((EU32*0.4)*1.2))*AV32*I32),2)*BS32),2))*AU32)/100),2)+ROUND(((ROUND((ROUND(((AE32-(((EU32*0.4)*1.2)))*AV32*I32),2)*BS32),2)*AU32)/100),2)) -> 13.13 | AA32: 86549534 | AB32: =ROUND((AC32+AD32+AF32),6) -> 91.5984 | AC32: =ROUND((((ES32*0)*1)),6) -> 0 | AD32: =ROUND((((((ET32*0.4)*1.2))-(((EU32*0.4)*1.2)))+AE32),6) -> 11.6016 | AE32: =ROUND((((EU32*0.4)*1.2)),6) -> 0.7248 | AF32: =ROUND((((EV32*0.4)*1.2)),6) -> 79.9968 | AG32: =ROUND((AP32),6) -> 0 | AH32: =(((EW32*0.4)*1.2)) -> 6.4896 | AI32: =(((EX32*0.4)*1.2)) -> 0 | AJ32: =(AS32) -> 0 | AK32: 312.82 | AL32: 121.99 | AM32: 24.17 | AN32: 1.51 | AO32: 166.66 | AP32: 0 | AQ32: 13.52 | AR32: 0 | AS32: 0 | AT32: 109 | AU32: 61 | AV32: 1.067 | AW32: 1 | AZ32: 1 | BA32: 1 | BB32: 1 | BC32: 1 | BH32: 0 | BI32: 1 | BJ32: ТСН-2001.3 Доп. 79, Сб. 16, т. 40, поз. 4 | BM32: 21 | BN32: 0 | BO32: 3.16-40-4 | BP32: 1 | BQ32: 30 | BR32: 0 | BS32: 1 | BT32: 1 | BU32: 1 | BV32: 1 | BW32: 1 | BX32: 1 | BZ32: 109 | CA32: 61 | CE32: 1566 | CF32: 0 | CG32: 0 | CM32: 0 | CN32: Поправка: Гл.6.Прил.2.2.п.2.2.13_06.00.01.35.003 Наименование: При демонтаже внутренних санитарно-технических устройств и газопроводов Поправка: Гл.12.Прил.8.п.8. 3_12.00.01.11.001 Наименование: При наличии напряженных и стесненных условий производства работ (стесненность, сложность складирования и транспортной логистики и т.п.) для объектов, расположенных в пределах круговой магистральной системы улиц "Садовое кольцо" города Москвы | CO32: 0 | CP32: =(P32+Q32+S32) -> 24.43 | CQ32: =ROUND((ROUND((AC32*AW32*1),2)*BC32),2) -> 0 | CR32: =(ROUND((ROUND(((((ET32*0.4)*1.2))*AV32*1),2)*BB32),2)+ROUND((ROUND(((AE32-(((EU32*0.4)*1.2)))*AV32*1),2)*BS32),2)) -> 12.38 | CS32: =(ROUND((ROUND(((((EU32*0.4)*1.2))*AV32*1),2)*BS32),2)+ROUND((ROUND(((AE32-(((EU32*0.4)*1.2)))*AV32*1),2)*BS32),2)) -> 0.77 | CT32: =ROUND((ROUND((AF32*AV32*1),2)*BA32),2) -> 85.36 | CU32: =AG32 -> 0 | CV32: =(AH32*AV32) -> 6.9244032 | CW32: =AI32 -> 0 | CX32: =AJ32 -> 0 | CY32: =(ROUND((((S32+ROUND((ROUND(((((EU32*0.4)*1.2))*AV32*1),2)*BS32),2))*AT32)/100),2)+ROUND(((ROUND((ROUND(((AE32-(((EU32*0.4)*1.2)))*AV32*1),2)*BS32),2)*AT32)/100),2)) -> 24.1 | CZ32: =(ROUND((((S32+ROUND((ROUND(((((EU32*0.4)*1.2))*AV32*1),2)*BS32),2))*AU32)/100),2)+ROUND(((ROUND((ROUND(((AE32-(((EU32*0.4)*1.2)))*AV32*1),2)*BS32),2)*AU32)/100),2)) -> 13.49 | DB32: 7 | DD32: *0)*1 | DE32: *0,4)*1,2 | DF32: *0,4)*1,2 | DG32: *0,4)*1,2 | DI32: *0,4)*1,2 | DJ32: *0,4)*1,2 | DN32: 0 | DO32: 0 | DP32: 1 | DQ32: 1 | DU32: 1003 | DV32: 100 м | DW32: 100 м | DX32: 100 | EE32: 85635393 | EF32: 30 | EG32: Строительные работы | EH32: 0 | EJ32: 1 | EK32: 21 | EL32: ТСН-2001.3-16. Трубопроводы внутренние | EM32: ТСН-2001.3-16-1 | EO32: Поправка: Гл.6.Прил.2.2.п.2.2.13_06.00.01.35.003 Поправка: Гл.12.Прил.8.п.8. 3_12.00.01.11.001 | EQ32: 131072 | ER32: 312.82 | ES32: 121.99 | ET32: 24.17 | EU32: 1.51 | EV32: 166.66 | EW32: 13.52 | EX32: 0 | EY32: 0 | FQ32: 0 | FR32: 0 | FS32: 0 | FX32: 109 | FY32: 61 | GD32: 1 | GF32: 1484051559 | GG32: 2 | GH32: 1 | GI32: 2 | GJ32: 0 | GK32: 0 | GL32: =ROUND(IF(AND(BH32=3,BI32=3,FS32<>0),P32,0),2) -> 0 | GM32: =ROUND(O32+X32+Y32,2)+GX32 -> 61.03 | GN32: =IF(OR(BI32=0,BI32=1),GM32-GX32,0) -> 61.03 | GO32: =IF(BI32=2,GM32-GX32,0) -> 0 | GP32: =IF(BI32=4,GM32-GX32,0) -> 0 | GR32: 0 | GS32: 3 | GT32: 0 | GV32: =ROUND((GT32),6) -> 0 | GW32: 1 | GX32: =ROUND(HC32*I32,2) -> 0 | HA32: 0 | HB32: 0 | HC32: =GV32*GW32 -> 0 | HS32: 0 | IK32: 0
A33: 17 | B33: 1 | C33: =ROW(SmtRes!A36) -> 36 | D33: =ROW(EtalonRes!A46) -> 46 | E33: 3 | F33: 3.16-40-4 | G33: Прокладка напорного трубопровода водоснабжения и отопления из многослойного полипропилена, армированного стекловолокном, из заранее собранных узлов, наружный диаметр 40 мм (демонтаж) | H33: 100 м | I33: =ROUND((25)/100,9) -> 0.25 | J33: 0 | K33: =ROUND((25)/100,9) -> 0.25 | O33: =ROUND(CP33,2) -> 1244.78 | P33: =ROUND((ROUND((AC33*AW33*I33),2)*BC33),2) -> 0 | Q33: =(ROUND((ROUND(((((ET33*0.4)*1.2))*AV33*I33),2)*BB33),2)+ROUND((ROUND(((AE33-(((EU33*0.4)*1.2)))*AV33*I33),2)*BS33),2)) -> 42.27 | R33: =(ROUND((ROUND(((((EU33*0.4)*1.2))*AV33*I33),2)*BS33),2)+ROUND((ROUND(((AE33-(((EU33*0.4)*1.2)))*AV33*I33),2)*BS33),2)) -> 10.71 | S33: =ROUND((ROUND((AF33*AV33*I33),2)*BA33),2) -> 1202.51 | T33: =ROUND(CU33*I33,2) -> 0 | U33: =CV33*I33 -> 1.7311008 | V33: =CW33*I33 -> 0 | W33: =ROUND(CX33*I33,2) -> 0 | X33: =(ROUND((((S33+ROUND((ROUND(((((EU33*0.4)*1.2))*AV33*I33),2)*BS33),2))*AT33)/100),2)+ROUND(((ROUND((ROUND(((AE33-(((EU33*0.4)*1.2)))*AV33*I33),2)*BS33),2)*AT33)/100),2)) -> 1322.41 | Y33: =(ROUND((((S33+ROUND((ROUND(((((EU33*0.4)*1.2))*AV33*I33),2)*BS33),2))*AU33)/100),2)+ROUND(((ROUND((ROUND(((AE33-(((EU33*0.4)*1.2)))*AV33*I33),2)*BS33),2)*AU33)/100),2)) -> 740.06 | AA33: 86549536 | AB33: =ROUND((AC33+AD33+AF33),6) -> 91.5984 | AC33: =ROUND((((ES33*0)*1)),6) -> 0 | AD33: =ROUND((((((ET33*0.4)*1.2))-(((EU33*0.4)*1.2)))+AE33),6) -> 11.6016 | AE33: =ROUND((((EU33*0.4)*1.2)),6) -> 0.7248 | AF33: =ROUND((((EV33*0.4)*1.2)),6) -> 79.9968 | AG33: =ROUND((AP33),6) -> 0 | AH33: =(((EW33*0.4)*1.2)) -> 6.4896 | AI33: =(((EX33*0.4)*1.2)) -> 0 | AJ33: =(AS33) -> 0 | AK33: 312.82 | AL33: 121.99 | AM33: 24.17 | AN33: 1.51 | AO33: 166.66 | AP33: 0 | AQ33: 13.52 | AR33: 0 | AS33: 0 | AT33: 109 | AU33: 61 | AV33: 1.067 | AW33: 1 | AZ33: 1 | BA33: 56.35 | BB33: 13.68 | BC33: 2.94 | BH33: 0 | BI33: 1 | BJ33: ТСН-2001.3 Доп. 79, Сб. 16, т. 40, поз. 4 | BM33: 21 | BN33: 0 | BO33: 3.16-40-4 | BP33: 1 | BQ33: 30 | BR33: 0 | BS33: 56.35 | BT33: 1 | BU33: 1 | BV33: 1 | BW33: 1 | BX33: 1 | BZ33: 109 | CA33: 61 | CE33: 1566 | CF33: 0 | CG33: 0 | CM33: 0 | CN33: Поправка: Гл.6.Прил.2.2.п.2.2.13_06.00.01.35.003 Наименование: При демонтаже внутренних санитарно-технических устройств и газопроводов Поправка: Гл.12.Прил.8.п.8. 3_12.00.01.11.001 Наименование: При наличии напряженных и стесненных условий производства работ (стесненность, сложность складирования и транспортной логистики и т.п.) для объектов, расположенных в пределах круговой магистральной системы улиц "Садовое кольцо" города Москвы | CO33: 0 | CP33: =(P33+Q33+S33) -> 1244.78 | CQ33: =ROUND((ROUND((AC33*AW33*1),2)*BC33),2) -> 0 | CR33: =(ROUND((ROUND(((((ET33*0.4)*1.2))*AV33*1),2)*BB33),2)+ROUND((ROUND(((AE33-(((EU33*0.4)*1.2)))*AV33*1),2)*BS33),2)) -> 169.36 | CS33: =(ROUND((ROUND(((((EU33*0.4)*1.2))*AV33*1),2)*BS33),2)+ROUND((ROUND(((AE33-(((EU33*0.4)*1.2)))*AV33*1),2)*BS33),2)) -> 43.39 | CT33: =ROUND((ROUND((AF33*AV33*1),2)*BA33),2) -> 4810.04 | CU33: =AG33 -> 0 | CV33: =(AH33*AV33) -> 6.9244032 | CW33: =AI33 -> 0 | CX33: =AJ33 -> 0 | CY33: =(ROUND((((S33+ROUND((ROUND(((((EU33*0.4)*1.2))*AV33*1),2)*BS33),2))*AT33)/100),2)+ROUND(((ROUND((ROUND(((AE33-(((EU33*0.4)*1.2)))*AV33*1),2)*BS33),2)*AT33)/100),2)) -> 1358.03 | CZ33: =(ROUND((((S33+ROUND((ROUND(((((EU33*0.4)*1.2))*AV33*1),2)*BS33),2))*AU33)/100),2)+ROUND(((ROUND((ROUND(((AE33-(((EU33*0.4)*1.2)))*AV33*1),2)*BS33),2)*AU33)/100),2)) -> 760 | DB33: 9 | DD33: *0)*1 | DE33: *0,4)*1,2 | DF33: *0,4)*1,2 | DG33: *0,4)*1,2 | DI33: *0,4)*1,2 | DJ33: *0,4)*1,2 | DN33: 0 | DO33: 0 | DP33: 1 | DQ33: 1 | DU33: 1003 | DV33: 100 м | DW33: 100 м | DX33: 100 | EE33: 85635393 | EF33: 30 | EG33: Строительные работы | EH33: 0 | EJ33: 1 | EK33: 21 | EL33: ТСН-2001.3-16. Трубопроводы внутренние | EM33: ТСН-2001.3-16-1 | EO33: Поправка: Гл.6.Прил.2.2.п.2.2.13_06.00.01.35.003 Поправка: Гл.12.Прил.8.п.8. 3_12.00.01.11.001 | EQ33: 131072 | ER33: 312.82 | ES33: 121.99 | ET33: 24.17 | EU33: 1.51 | EV33: 166.66 | EW33: 13.52 | EX33: 0 | EY33: 0 | FQ33: 0 | FR33: 0 | FS33: 0 | FX33: 109 | FY33: 61 | GD33: 1 | GF33: 1484051559 | GG33: 2 | GH33: 1 | GI33: 2 | GJ33: 0 | GK33: 0 | GL33: =ROUND(IF(AND(BH33=3,BI33=3,FS33<>0),P33,0),2) -> 0 | GM33: =ROUND(O33+X33+Y33,2)+GX33 -> 3307.25 | GN33: =IF(OR(BI33=0,BI33=1),GM33-GX33,0) -> 3307.25 | GO33: =IF(BI33=2,GM33-GX33,0) -> 0 | GP33: =IF(BI33=4,GM33-GX33,0) -> 0 | GR33: 0 | GS33: 3 | GT33: 0 | GV33: =ROUND((GT33),6) -> 0 | GW33: 1 | GX33: =ROUND(HC33*I33,2) -> 0 | HA33: 0 | HB33: 0 | HC33: =GV33*GW33 -> 0 | HS33: 0 | IK33: 0
A34: 17 | B34: 1 | C34: =ROW(SmtRes!A42) -> 42 | D34: =ROW(EtalonRes!A55) -> 55 | E34: 4 | F34: 3.16-13-2 | G34: Прокладка трубопроводов канализации из ПВХ труб диаметром 100 мм - 150 мм (демонтаж) | H34: 100 м | I34: =ROUND((180+18+32)/100,9) -> 2.3 | J34: 0 | K34: =ROUND((180+18+32)/100,9) -> 2.3 | O34: =ROUND(CP34,2) -> 868.16 | P34: =ROUND((ROUND((AC34*AW34*I34),2)*BC34),2) -> 0 | Q34: =(ROUND((ROUND(((((ET34*0.4)*1.2))*AV34*I34),2)*BB34),2)+ROUND((ROUND(((AE34-(((EU34*0.4)*1.2)))*AV34*I34),2)*BS34),2)) -> 23.79 | R34: =(ROUND((ROUND(((((EU34*0.4)*1.2))*AV34*I34),2)*BS34),2)+ROUND((ROUND(((AE34-(((EU34*0.4)*1.2)))*AV34*I34),2)*BS34),2)) -> 3.37 | S34: =ROUND((ROUND((AF34*AV34*I34),2)*BA34),2) -> 844.37 | T34: =ROUND(CU34*I34,2) -> 0 | U34: =CV34*I34 -> 65.966208 | V34: =CW34*I34 -> 0 | W34: =ROUND(CX34*I34,2) -> 0 | X34: =(ROUND((((S34+ROUND((ROUND(((((EU34*0.4)*1.2))*AV34*I34),2)*BS34),2))*AT34)/100),2)+ROUND(((ROUND((ROUND(((AE34-(((EU34*0.4)*1.2)))*AV34*I34),2)*BS34),2)*AT34)/100),2)) -> 924.04 | Y34: =(ROUND((((S34+ROUND((ROUND(((((EU34*0.4)*1.2))*AV34*I34),2)*BS34),2))*AU34)/100),2)+ROUND(((ROUND((ROUND(((AE34-(((EU34*0.4)*1.2)))*AV34*I34),2)*BS34),2)*AU34)/100),2)) -> 517.12 | AA34: 86549534 | AB34: =ROUND((AC34+AD34+AF34),6) -> 353.76 | AC34: =ROUND((((ES34*0)*1)),6) -> 0 | AD34: =ROUND((((((ET34*0.4)*1.2))-(((EU34*0.4)*1.2)))+AE34),6) -> 9.696 | AE34: =ROUND((((EU34*0.4)*1.2)),6) -> 1.3728 | AF34: =ROUND((((EV34*0.4)*1.2)),6) -> 344.064 | AG34: =ROUND((AP34),6) -> 0 | AH34: =(((EW34*0.4)*1.2)) -> 26.88 | AI34: =(((EX34*0.4)*1.2)) -> 0 | AJ34: =(AS34) -> 0 | AK34: 968.71 | AL34: 231.71 | AM34: 20.2 | AN34: 2.86 | AO34: 716.8 | AP34: 0 | AQ34: 56 | AR34: 0 | AS34: 0 | AT34: 109 | AU34: 61 | AV34: 1.067 | AW34: 1 | AZ34: 1 | BA34: 1 | BB34: 1 | BC34: 1 | BH34: 0 | BI34: 1 | BJ34: ТСН-2001.3 Доп. 79, Сб. 16, т. 13, поз. 2 | BM34: 21 | BN34: 0 | BO34: 3.16-13-2 | BP34: 1 | BQ34: 30 | BR34: 0 | BS34: 1 | BT34: 1 | BU34: 1 | BV34: 1 | BW34: 1 | BX34: 1 | BZ34: 109 | CA34: 61 | CE34: 1566 | CF34: 0 | CG34: 0 | CM34: 0 | CN34: Поправка: Гл.6.Прил.2.2.п.2.2.13_06.00.01.35.003 Наименование: При демонтаже внутренних санитарно-технических устройств и газопроводов Поправка: Гл.12.Прил.8.п.8. 3_12.00.01.11.001 Наименование: При наличии напряженных и стесненных условий производства работ (стесненность, сложность складирования и транспортной логистики и т.п.) для объектов, расположенных в пределах круговой магистральной системы улиц "Садовое кольцо" города Москвы | CO34: 0 | CP34: =(P34+Q34+S34) -> 868.16 | CQ34: =ROUND((ROUND((AC34*AW34*1),2)*BC34),2) -> 0 | CR34: =(ROUND((ROUND(((((ET34*0.4)*1.2))*AV34*1),2)*BB34),2)+ROUND((ROUND(((AE34-(((EU34*0.4)*1.2)))*AV34*1),2)*BS34),2)) -> 10.35 | CS34: =(ROUND((ROUND(((((EU34*0.4)*1.2))*AV34*1),2)*BS34),2)+ROUND((ROUND(((AE34-(((EU34*0.4)*1.2)))*AV34*1),2)*BS34),2)) -> 1.46 | CT34: =ROUND((ROUND((AF34*AV34*1),2)*BA34),2) -> 367.12 | CU34: =AG34 -> 0 | CV34: =(AH34*AV34) -> 28.68096 | CW34: =AI34 -> 0 | CX34: =AJ34 -> 0 | CY34: =(ROUND((((S34+ROUND((ROUND(((((EU34*0.4)*1.2))*AV34*1),2)*BS34),2))*AT34)/100),2)+ROUND(((ROUND((ROUND(((AE34-(((EU34*0.4)*1.2)))*AV34*1),2)*BS34),2)*AT34)/100),2)) -> 921.95 | CZ34: =(ROUND((((S34+ROUND((ROUND(((((EU34*0.4)*1.2))*AV34*1),2)*BS34),2))*AU34)/100),2)+ROUND(((ROUND((ROUND(((AE34-(((EU34*0.4)*1.2)))*AV34*1),2)*BS34),2)*AU34)/100),2)) -> 515.96 | DB34: 11 | DD34: *0)*1 | DE34: *0,4)*1,2 | DF34: *0,4)*1,2 | DG34: *0,4)*1,2 | DI34: *0,4)*1,2 | DJ34: *0,4)*1,2 | DN34: 0 | DO34: 0 | DP34: 1 | DQ34: 1 | DU34: 1003 | DV34: 100 м | DW34: 100 м | DX34: 100 | EE34: 85635393 | EF34: 30 | EG34: Строительные работы | EH34: 0 | EJ34: 1 | EK34: 21 | EL34: ТСН-2001.3-16. Трубопроводы внутренние | EM34: ТСН-2001.3-16-1 | EO34: Поправка: Гл.6.Прил.2.2.п.2.2.13_06.00.01.35.003 Поправка: Гл.12.Прил.8.п.8. 3_12.00.01.11.001 | EQ34: 131072 | ER34: 968.71 | ES34: 231.71 | ET34: 20.2 | EU34: 2.86 | EV34: 716.8 | EW34: 56 | EX34: 0 | EY34: 0 | FQ34: 0 | FR34: 0 | FS34: 0 | FX34: 109 | FY34: 61 | GD34: 1 | GF34: 554786944 | GG34: 2 | GH34: 1 | GI34: 2 | GJ34: 0 | GK34: 0 | GL34: =ROUND(IF(AND(BH34=3,BI34=3,FS34<>0),P34,0),2) -> 0 | GM34: =ROUND(O34+X34+Y34,2)+GX34 -> 2309.32 | GN34: =IF(OR(BI34=0,BI34=1),GM34-GX34,0) -> 2309.32 | GO34: =IF(BI34=2,GM34-GX34,0) -> 0 | GP34: =IF(BI34=4,GM34-GX34,0) -> 0 | GR34: 0 | GS34: 3 | GT34: 0 | GV34: =ROUND((GT34),6) -> 0 | GW34: 1 | GX34: =ROUND(HC34*I34,2) -> 0 | HA34: 0 | HB34: 0 | HC34: =GV34*GW34 -> 0 | HS34: 0 | IK34: 0
A35: 17 | B35: 1 | C35: =ROW(SmtRes!A48) -> 48 | D35: =ROW(EtalonRes!A64) -> 64 | E35: 4 | F35: 3.16-13-2 | G35: Прокладка трубопроводов канализации из ПВХ труб диаметром 100 мм - 150 мм (демонтаж) | H35: 100 м | I35: =ROUND((180+18+32)/100,9) -> 2.3 | J35: 0 | K35: =ROUND((180+18+32)/100,9) -> 2.3 | O35: =ROUND(CP35,2) -> 47975.16 | P35: =ROUND((ROUND((AC35*AW35*I35),2)*BC35),2) -> 0 | Q35: =(ROUND((ROUND(((((ET35*0.4)*1.2))*AV35*I35),2)*BB35),2)+ROUND((ROUND(((AE35-(((EU35*0.4)*1.2)))*AV35*I35),2)*BS35),2)) -> 394.91 | R35: =(ROUND((ROUND(((((EU35*0.4)*1.2))*AV35*I35),2)*BS35),2)+ROUND((ROUND(((AE35-(((EU35*0.4)*1.2)))*AV35*I35),2)*BS35),2)) -> 189.9 | S35: =ROUND((ROUND((AF35*AV35*I35),2)*BA35),2) -> 47580.25 | T35: =ROUND(CU35*I35,2) -> 0 | U35: =CV35*I35 -> 65.966208 | V35: =CW35*I35 -> 0 | W35: =ROUND(CX35*I35,2) -> 0 | X35: =(ROUND((((S35+ROUND((ROUND(((((EU35*0.4)*1.2))*AV35*I35),2)*BS35),2))*AT35)/100),2)+ROUND(((ROUND((ROUND(((AE35-(((EU35*0.4)*1.2)))*AV35*I35),2)*BS35),2)*AT35)/100),2)) -> 52069.46 | Y35: =(ROUND((((S35+ROUND((ROUND(((((EU35*0.4)*1.2))*AV35*I35),2)*BS35),2))*AU35)/100),2)+ROUND(((ROUND((ROUND(((AE35-(((EU35*0.4)*1.2)))*AV35*I35),2)*BS35),2)*AU35)/100),2)) -> 29139.79 | AA35: 86549536 | AB35: =ROUND((AC35+AD35+AF35),6) -> 353.76 | AC35: =ROUND((((ES35*0)*1)),6) -> 0 | AD35: =ROUND((((((ET35*0.4)*1.2))-(((EU35*0.4)*1.2)))+AE35),6) -> 9.696 | AE35: =ROUND((((EU35*0.4)*1.2)),6) -> 1.3728 | AF35: =ROUND((((EV35*0.4)*1.2)),6) -> 344.064 | AG35: =ROUND((AP35),6) -> 0 | AH35: =(((EW35*0.4)*1.2)) -> 26.88 | AI35: =(((EX35*0.4)*1.2)) -> 0 | AJ35: =(AS35) -> 0 | AK35: 968.71 | AL35: 231.71 | AM35: 20.2 | AN35: 2.86 | AO35: 716.8 | AP35: 0 | AQ35: 56 | AR35: 0 | AS35: 0 | AT35: 109 | AU35: 61 | AV35: 1.067 | AW35: 1 | AZ35: 1 | BA35: 56.35 | BB35: 16.6 | BC35: 12.86 | BH35: 0 | BI35: 1 | BJ35: ТСН-2001.3 Доп. 79, Сб. 16, т. 13, поз. 2 | BM35: 21 | BN35: 0 | BO35: 3.16-13-2 | BP35: 1 | BQ35: 30 | BR35: 0 | BS35: 56.35 | BT35: 1 | BU35: 1 | BV35: 1 | BW35: 1 | BX35: 1 | BZ35: 109 | CA35: 61 | CE35: 1566 | CF35: 0 | CG35: 0 | CM35: 0 | CN35: Поправка: Гл.6.Прил.2.2.п.2.2.13_06.00.01.35.003 Наименование: При демонтаже внутренних санитарно-технических устройств и газопроводов Поправка: Гл.12.Прил.8.п.8. 3_12.00.01.11.001 Наименование: При наличии напряженных и стесненных условий производства работ (стесненность, сложность складирования и транспортной логистики и т.п.) для объектов, расположенных в пределах круговой магистральной системы улиц "Садовое кольцо" города Москвы | CO35: 0 | CP35: =(P35+Q35+S35) -> 47975.16 | CQ35: =ROUND((ROUND((AC35*AW35*1),2)*BC35),2) -> 0 | CR35: =(ROUND((ROUND(((((ET35*0.4)*1.2))*AV35*1),2)*BB35),2)+ROUND((ROUND(((AE35-(((EU35*0.4)*1.2)))*AV35*1),2)*BS35),2)) -> 171.81 | CS35: =(ROUND((ROUND(((((EU35*0.4)*1.2))*AV35*1),2)*BS35),2)+ROUND((ROUND(((AE35-(((EU35*0.4)*1.2)))*AV35*1),2)*BS35),2)) -> 82.27 | CT35: =ROUND((ROUND((AF35*AV35*1),2)*BA35),2) -> 20687.21 | CU35: =AG35 -> 0 | CV35: =(AH35*AV35) -> 28.68096 | CW35: =AI35 -> 0 | CX35: =AJ35 -> 0 | CY35: =(ROUND((((S35+ROUND((ROUND(((((EU35*0.4)*1.2))*AV35*1),2)*BS35),2))*AT35)/100),2)+ROUND(((ROUND((ROUND(((AE35-(((EU35*0.4)*1.2)))*AV35*1),2)*BS35),2)*AT35)/100),2)) -> 51952.15 | CZ35: =(ROUND((((S35+ROUND((ROUND(((((EU35*0.4)*1.2))*AV35*1),2)*BS35),2))*AU35)/100),2)+ROUND(((ROUND((ROUND(((AE35-(((EU35*0.4)*1.2)))*AV35*1),2)*BS35),2)*AU35)/100),2)) -> 29074.14 | DB35: 13 | DD35: *0)*1 | DE35: *0,4)*1,2 | DF35: *0,4)*1,2 | DG35: *0,4)*1,2 | DI35: *0,4)*1,2 | DJ35: *0,4)*1,2 | DN35: 0 | DO35: 0 | DP35: 1 | DQ35: 1 | DU35: 1003 | DV35: 100 м | DW35: 100 м | DX35: 100 | EE35: 85635393 | EF35: 30 | EG35: Строительные работы | EH35: 0 | EJ35: 1 | EK35: 21 | EL35: ТСН-2001.3-16. Трубопроводы внутренние | EM35: ТСН-2001.3-16-1 | EO35: Поправка: Гл.6.Прил.2.2.п.2.2.13_06.00.01.35.003 Поправка: Гл.12.Прил.8.п.8. 3_12.00.01.11.001 | EQ35: 131072 | ER35: 968.71 | ES35: 231.71 | ET35: 20.2 | EU35: 2.86 | EV35: 716.8 | EW35: 56 | EX35: 0 | EY35: 0 | FQ35: 0 | FR35: 0 | FS35: 0 | FX35: 109 | FY35: 61 | GD35: 1 | GF35: 554786944 | GG35: 2 | GH35: 1 | GI35: 2 | GJ35: 0 | GK35: 0 | GL35: =ROUND(IF(AND(BH35=3,BI35=3,FS35<>0),P35,0),2) -> 0 | GM35: =ROUND(O35+X35+Y35,2)+GX35 -> 129184.41 | GN35: =IF(OR(BI35=0,BI35=1),GM35-GX35,0) -> 129184.41 | GO35: =IF(BI35=2,GM35-GX35,0) -> 0 | GP35: =IF(BI35=4,GM35-GX35,0) -> 0 | GR35: 0 | GS35: 3 | GT35: 0 | GV35: =ROUND((GT35),6) -> 0 | GW35: 1 | GX35: =ROUND(HC35*I35,2) -> 0 | HA35: 0 | HB35: 0 | HC35: =GV35*GW35 -> 0 | HS35: 0 | IK35: 0
A36: 17 | B36: 1 | C36: =ROW(SmtRes!A54) -> 54 | D36: =ROW(EtalonRes!A73) -> 73 | E36: 5 | F36: 3.16-13-1 | G36: Прокладка трубопроводов канализации из ПВХ труб диаметром до 50 мм (демонтаж) | H36: 100 м | I36: =ROUND((120+20)/100,9) -> 1.4 | J36: 0 | K36: =ROUND((120+20)/100,9) -> 1.4 | O36: =ROUND(CP36,2) -> 543.23 | P36: =ROUND((ROUND((AC36*AW36*I36),2)*BC36),2) -> 0 | Q36: =(ROUND((ROUND(((((ET36*0.4)*1.2))*AV36*I36),2)*BB36),2)+ROUND((ROUND(((AE36-(((EU36*0.4)*1.2)))*AV36*I36),2)*BS36),2)) -> 7.24 | R36: =(ROUND((ROUND(((((EU36*0.4)*1.2))*AV36*I36),2)*BS36),2)+ROUND((ROUND(((AE36-(((EU36*0.4)*1.2)))*AV36*I36),2)*BS36),2)) -> 1.03 | S36: =ROUND((ROUND((AF36*AV36*I36),2)*BA36),2) -> 535.99 | T36: =ROUND(CU36*I36,2) -> 0 | U36: =CV36*I36 -> 41.874202 | V36: =CW36*I36 -> 0 | W36: =ROUND(CX36*I36,2) -> 0 | X36: =(ROUND((((S36+ROUND((ROUND(((((EU36*0.4)*1.2))*AV36*I36),2)*BS36),2))*AT36)/100),2)+ROUND(((ROUND((ROUND(((AE36-(((EU36*0.4)*1.2)))*AV36*I36),2)*BS36),2)*AT36)/100),2)) -> 585.35 | Y36: =(ROUND((((S36+ROUND((ROUND(((((EU36*0.4)*1.2))*AV36*I36),2)*BS36),2))*AU36)/100),2)+ROUND(((ROUND((ROUND(((AE36-(((EU36*0.4)*1.2)))*AV36*I36),2)*BS36),2)*AU36)/100),2)) -> 327.58 | AA36: 86549534 | AB36: =ROUND((AC36+AD36+AF36),6) -> 363.6576 | AC36: =ROUND((((ES36*0)*1)),6) -> 0 | AD36: =ROUND((((((ET36*0.4)*1.2))-(((EU36*0.4)*1.2)))+AE36),6) -> 4.848 | AE36: =ROUND((((EU36*0.4)*1.2)),6) -> 0.6864 | AF36: =ROUND((((EV36*0.4)*1.2)),6) -> 358.8096 | AG36: =ROUND((AP36),6) -> 0 | AH36: =(((EW36*0.4)*1.2)) -> 28.032 | AI36: =(((EX36*0.4)*1.2)) -> 0 | AJ36: =(AS36) -> 0 | AK36: 842.78 | AL36: 85.16 | AM36: 10.1 | AN36: 1.43 | AO36: 747.52 | AP36: 0 | AQ36: 58.4 | AR36: 0 | AS36: 0 | AT36: 109 | AU36: 61 | AV36: 1.067 | AW36: 1 | AZ36: 1 | BA36: 1 | BB36: 1 | BC36: 1 | BH36: 0 | BI36: 1 | BJ36: ТСН-2001.3 Доп. 79, Сб. 16, т. 13, поз. 1 | BM36: 21 | BN36: 0 | BO36: 3.16-13-1 | BP36: 1 | BQ36: 30 | BR36: 0 | BS36: 1 | BT36: 1 | BU36: 1 | BV36: 1 | BW36: 1 | BX36: 1 | BZ36: 109 | CA36: 61 | CE36: 1566 | CF36: 0 | CG36: 0 | CM36: 0 | CN36: Поправка: Гл.6.Прил.2.2.п.2.2.13_06.00.01.35.003 Наименование: При демонтаже внутренних санитарно-технических устройств и газопроводов Поправка: Гл.12.Прил.8.п.8. 3_12.00.01.11.001 Наименование: При наличии напряженных и стесненных условий производства работ (стесненность, сложность складирования и транспортной логистики и т.п.) для объектов, расположенных в пределах круговой магистральной системы улиц "Садовое кольцо" города Москвы | CO36: 0 | CP36: =(P36+Q36+S36) -> 543.23 | CQ36: =ROUND((ROUND((AC36*AW36*1),2)*BC36),2) -> 0 | CR36: =(ROUND((ROUND(((((ET36*0.4)*1.2))*AV36*1),2)*BB36),2)+ROUND((ROUND(((AE36-(((EU36*0.4)*1.2)))*AV36*1),2)*BS36),2)) -> 5.17 | CS36: =(ROUND((ROUND(((((EU36*0.4)*1.2))*AV36*1),2)*BS36),2)+ROUND((ROUND(((AE36-(((EU36*0.4)*1.2)))*AV36*1),2)*BS36),2)) -> 0.73 | CT36: =ROUND((ROUND((AF36*AV36*1),2)*BA36),2) -> 382.85 | CU36: =AG36 -> 0 | CV36: =(AH36*AV36) -> 29.910144 | CW36: =AI36 -> 0 | CX36: =AJ36 -> 0 | CY36: =(ROUND((((S36+ROUND((ROUND(((((EU36*0.4)*1.2))*AV36*1),2)*BS36),2))*AT36)/100),2)+ROUND(((ROUND((ROUND(((AE36-(((EU36*0.4)*1.2)))*AV36*1),2)*BS36),2)*AT36)/100),2)) -> 585.02 | CZ36: =(ROUND((((S36+ROUND((ROUND(((((EU36*0.4)*1.2))*AV36*1),2)*BS36),2))*AU36)/100),2)+ROUND(((ROUND((ROUND(((AE36-(((EU36*0.4)*1.2)))*AV36*1),2)*BS36),2)*AU36)/100),2)) -> 327.4 | DB36: 15 | DD36: *0)*1 | DE36: *0,4)*1,2 | DF36: *0,4)*1,2 | DG36: *0,4)*1,2 | DI36: *0,4)*1,2 | DJ36: *0,4)*1,2 | DN36: 0 | DO36: 0 | DP36: 1 | DQ36: 1 | DU36: 1003 | DV36: 100 м | DW36: 100 м | DX36: 100 | EE36: 85635393 | EF36: 30 | EG36: Строительные работы | EH36: 0 | EJ36: 1 | EK36: 21 | EL36: ТСН-2001.3-16. Трубопроводы внутренние | EM36: ТСН-2001.3-16-1 | EO36: Поправка: Гл.6.Прил.2.2.п.2.2.13_06.00.01.35.003 Поправка: Гл.12.Прил.8.п.8. 3_12.00.01.11.001 | EQ36: 131072 | ER36: 842.78 | ES36: 85.16 | ET36: 10.1 | EU36: 1.43 | EV36: 747.52 | EW36: 58.4 | EX36: 0 | EY36: 0 | FQ36: 0 | FR36: 0 | FS36: 0 | FX36: 109 | FY36: 61 | GD36: 1 | GF36: 1569691367 | GG36: 2 | GH36: 1 | GI36: 2 | GJ36: 0 | GK36: 0 | GL36: =ROUND(IF(AND(BH36=3,BI36=3,FS36<>0),P36,0),2) -> 0 | GM36: =ROUND(O36+X36+Y36,2)+GX36 -> 1456.16 | GN36: =IF(OR(BI36=0,BI36=1),GM36-GX36,0) -> 1456.16 | GO36: =IF(BI36=2,GM36-GX36,0) -> 0 | GP36: =IF(BI36=4,GM36-GX36,0) -> 0 | GR36: 0 | GS36: 3 | GT36: 0 | GV36: =ROUND((GT36),6) -> 0 | GW36: 1 | GX36: =ROUND(HC36*I36,2) -> 0 | HA36: 0 | HB36: 0 | HC36: =GV36*GW36 -> 0 | HS36: 0 | IK36: 0
A37: 17 | B37: 1 | C37: =ROW(SmtRes!A60) -> 60 | D37: =ROW(EtalonRes!A82) -> 82 | E37: 5 | F37: 3.16-13-1 | G37: Прокладка трубопроводов канализации из ПВХ труб диаметром до 50 мм (демонтаж) | H37: 100 м | I37: =ROUND((120+20)/100,9) -> 1.4 | J37: 0 | K37: =ROUND((120+20)/100,9) -> 1.4 | O37: =ROUND(CP37,2) -> 30323.22 | P37: =ROUND((ROUND((AC37*AW37*I37),2)*BC37),2) -> 0 | Q37: =(ROUND((ROUND(((((ET37*0.4)*1.2))*AV37*I37),2)*BB37),2)+ROUND((ROUND(((AE37-(((EU37*0.4)*1.2)))*AV37*I37),2)*BS37),2)) -> 120.18 | R37: =(ROUND((ROUND(((((EU37*0.4)*1.2))*AV37*I37),2)*BS37),2)+ROUND((ROUND(((AE37-(((EU37*0.4)*1.2)))*AV37*I37),2)*BS37),2)) -> 58.04 | S37: =ROUND((ROUND((AF37*AV37*I37),2)*BA37),2) -> 30203.04 | T37: =ROUND(CU37*I37,2) -> 0 | U37: =CV37*I37 -> 41.874202 | V37: =CW37*I37 -> 0 | W37: =ROUND(CX37*I37,2) -> 0 | X37: =(ROUND((((S37+ROUND((ROUND(((((EU37*0.4)*1.2))*AV37*I37),2)*BS37),2))*AT37)/100),2)+ROUND(((ROUND((ROUND(((AE37-(((EU37*0.4)*1.2)))*AV37*I37),2)*BS37),2)*AT37)/100),2)) -> 32984.58 | Y37: =(ROUND((((S37+ROUND((ROUND(((((EU37*0.4)*1.2))*AV37*I37),2)*BS37),2))*AU37)/100),2)+ROUND(((ROUND((ROUND(((AE37-(((EU37*0.4)*1.2)))*AV37*I37),2)*BS37),2)*AU37)/100),2)) -> 18459.26 | AA37: 86549536 | AB37: =ROUND((AC37+AD37+AF37),6) -> 363.6576 | AC37: =ROUND((((ES37*0)*1)),6) -> 0 | AD37: =ROUND((((((ET37*0.4)*1.2))-(((EU37*0.4)*1.2)))+AE37),6) -> 4.848 | AE37: =ROUND((((EU37*0.4)*1.2)),6) -> 0.6864 | AF37: =ROUND((((EV37*0.4)*1.2)),6) -> 358.8096 | AG37: =ROUND((AP37),6) -> 0 | AH37: =(((EW37*0.4)*1.2)) -> 28.032 | AI37: =(((EX37*0.4)*1.2)) -> 0 | AJ37: =(AS37) -> 0 | AK37: 842.78 | AL37: 85.16 | AM37: 10.1 | AN37: 1.43 | AO37: 747.52 | AP37: 0 | AQ37: 58.4 | AR37: 0 | AS37: 0 | AT37: 109 | AU37: 61 | AV37: 1.067 | AW37: 1 | AZ37: 1 | BA37: 56.35 | BB37: 16.6 | BC37: 12.82 | BH37: 0 | BI37: 1 | BJ37: ТСН-2001.3 Доп. 79, Сб. 16, т. 13, поз. 1 | BM37: 21 | BN37: 0 | BO37: 3.16-13-1 | BP37: 1 | BQ37: 30 | BR37: 0 | BS37: 56.35 | BT37: 1 | BU37: 1 | BV37: 1 | BW37: 1 | BX37: 1 | BZ37: 109 | CA37: 61 | CE37: 1566 | CF37: 0 | CG37: 0 | CM37: 0 | CN37: Поправка: Гл.6.Прил.2.2.п.2.2.13_06.00.01.35.003 Наименование: При демонтаже внутренних санитарно-технических устройств и газопроводов Поправка: Гл.12.Прил.8.п.8. 3_12.00.01.11.001 Наименование: При наличии напряженных и стесненных условий производства работ (стесненность, сложность складирования и транспортной логистики и т.п.) для объектов, расположенных в пределах круговой магистральной системы улиц "Садовое кольцо" города Москвы | CO37: 0 | CP37: =(P37+Q37+S37) -> 30323.22 | CQ37: =ROUND((ROUND((AC37*AW37*1),2)*BC37),2) -> 0 | CR37: =(ROUND((ROUND(((((ET37*0.4)*1.2))*AV37*1),2)*BB37),2)+ROUND((ROUND(((AE37-(((EU37*0.4)*1.2)))*AV37*1),2)*BS37),2)) -> 85.82 | CS37: =(ROUND((ROUND(((((EU37*0.4)*1.2))*AV37*1),2)*BS37),2)+ROUND((ROUND(((AE37-(((EU37*0.4)*1.2)))*AV37*1),2)*BS37),2)) -> 41.14 | CT37: =ROUND((ROUND((AF37*AV37*1),2)*BA37),2) -> 21573.6 | CU37: =AG37 -> 0 | CV37: =(AH37*AV37) -> 29.910144 | CW37: =AI37 -> 0 | CX37: =AJ37 -> 0 | CY37: =(ROUND((((S37+ROUND((ROUND(((((EU37*0.4)*1.2))*AV37*1),2)*BS37),2))*AT37)/100),2)+ROUND(((ROUND((ROUND(((AE37-(((EU37*0.4)*1.2)))*AV37*1),2)*BS37),2)*AT37)/100),2)) -> 32966.16 | CZ37: =(ROUND((((S37+ROUND((ROUND(((((EU37*0.4)*1.2))*AV37*1),2)*BS37),2))*AU37)/100),2)+ROUND(((ROUND((ROUND(((AE37-(((EU37*0.4)*1.2)))*AV37*1),2)*BS37),2)*AU37)/100),2)) -> 18448.95 | DB37: 17 | DD37: *0)*1 | DE37: *0,4)*1,2 | DF37: *0,4)*1,2 | DG37: *0,4)*1,2 | DI37: *0,4)*1,2 | DJ37: *0,4)*1,2 | DN37: 0 | DO37: 0 | DP37: 1 | DQ37: 1 | DU37: 1003 | DV37: 100 м | DW37: 100 м | DX37: 100 | EE37: 85635393 | EF37: 30 | EG37: Строительные работы | EH37: 0 | EJ37: 1 | EK37: 21 | EL37: ТСН-2001.3-16. Трубопроводы внутренние | EM37: ТСН-2001.3-16-1 | EO37: Поправка: Гл.6.Прил.2.2.п.2.2.13_06.00.01.35.003 Поправка: Гл.12.Прил.8.п.8. 3_12.00.01.11.001 | EQ37: 131072 | ER37: 842.78 | ES37: 85.16 | ET37: 10.1 | EU37: 1.43 | EV37: 747.52 | EW37: 58.4 | EX37: 0 | EY37: 0 | FQ37: 0 | FR37: 0 | FS37: 0 | FX37: 109 | FY37: 61 | GD37: 1 | GF37: 1569691367 | GG37: 2 | GH37: 1 | GI37: 2 | GJ37: 0 | GK37: 0 | GL37: =ROUND(IF(AND(BH37=3,BI37=3,FS37<>0),P37,0),2) -> 0 | GM37: =ROUND(O37+X37+Y37,2)+GX37 -> 81767.06 | GN37: =IF(OR(BI37=0,BI37=1),GM37-GX37,0) -> 81767.06 | GO37: =IF(BI37=2,GM37-GX37,0) -> 0 | GP37: =IF(BI37=4,GM37-GX37,0) -> 0 | GR37: 0 | GS37: 3 | GT37: 0 | GV37: =ROUND((GT37),6) -> 0 | GW37: 1 | GX37: =ROUND(HC37*I37,2) -> 0 | HA37: 0 | HB37: 0 | HC37: =GV37*GW37 -> 0 | HS37: 0 | IK37: 0
A38: 17 | B38: 1 | C38: =ROW(SmtRes!A62) -> 62 | D38: =ROW(EtalonRes!A84) -> 84 | E38: 6 | F38: 6.65-2-2 | G38: Разборка трубопроводов из чугунных канализационных труб диаметром до 100 мм | H38: 100 м | I38: =ROUND((140+30)/100,9) -> 1.7 | J38: 0 | K38: =ROUND((140+30)/100,9) -> 1.7 | O38: =ROUND(CP38,2) -> 2142.57 | P38: =ROUND((ROUND((AC38*AW38*I38),2)*BC38),2) -> 0 | Q38: =(ROUND((ROUND((((ET38*1.2))*AV38*I38),2)*BB38),2)+ROUND((ROUND(((AE38-((EU38*1.2)))*AV38*I38),2)*BS38),2)) -> 0 | R38: =(ROUND((ROUND((((EU38*1.2))*AV38*I38),2)*BS38),2)+ROUND((ROUND(((AE38-((EU38*1.2)))*AV38*I38),2)*BS38),2)) -> 0 | S38: =ROUND((ROUND((AF38*AV38*I38),2)*BA38),2) -> 2142.57 | T38: =ROUND(CU38*I38,2) -> 0 | U38: =CV38*I38 -> 182.19056 | V38: =CW38*I38 -> 0 | W38: =ROUND(CX38*I38,2) -> 0 | X38: =(ROUND((((S38+ROUND((ROUND((((EU38*1.2))*AV38*I38),2)*BS38),2))*AT38)/100),2)+ROUND(((ROUND((ROUND(((AE38-((EU38*1.2)))*AV38*I38),2)*BS38),2)*AT38)/100),2)) -> 1864.04 | Y38: =(ROUND((((S38+ROUND((ROUND((((EU38*1.2))*AV38*I38),2)*BS38),2))*AU38)/100),2)+ROUND(((ROUND((ROUND(((AE38-((EU38*1.2)))*AV38*I38),2)*BS38),2)*AU38)/100),2)) -> 942.73 | AA38: 86549534 | AB38: =ROUND((AC38+AD38+AF38),6) -> 1203.756 | AC38: =ROUND(((ES38*1)),6) -> 0 | AD38: =ROUND(((((ET38*1.2))-((EU38*1.2)))+AE38),6) -> 0 | AE38: =ROUND(((EU38*1.2)),6) -> 0 | AF38: =ROUND(((EV38*1.2)),6) -> 1203.756 | AG38: =ROUND((AP38),6) -> 0 | AH38: =((EW38*1.2)) -> 102.36 | AI38: =((EX38*1.2)) -> 0 | AJ38: =(AS38) -> 0 | AK38: 1003.13 | AL38: 0 | AM38: 0 | AN38: 0 | AO38: 1003.13 | AP38: 0 | AQ38: 85.3 | AR38: 0 | AS38: 0 | AT38: 87 | AU38: 44 | AV38: 1.047 | AW38: 1 | AZ38: 1 | BA38: 1 | BB38: 1 | BC38: 1 | BH38: 0 | BI38: 1 | BJ38: ТСН-2001.6 Доп. 68, Сб. 65, т. 2, поз. 2 | BM38: 102 | BN38: 0 | BO38: 6.65-2-2 | BP38: 1 | BQ38: 60 | BR38: 0 | BS38: 1 | BT38: 1 | BU38: 1 | BV38: 1 | BW38: 1 | BX38: 1 | BZ38: 87 | CA38: 44 | CE38: 1566 | CF38: 0 | CG38: 0 | CM38: 0 | CN38: Поправка: Гл.12.Прил.8.п.8. 3_12.00.01.11.001 Наименование: При наличии напряженных и стесненных условий производства работ (стесненность, сложность складирования и транспортной логистики и т.п.) для объектов, расположенных в пределах круговой магистральной системы улиц "Садовое кольцо" города Москвы | CO38: 0 | CP38: =(P38+Q38+S38) -> 2142.57 | CQ38: =ROUND((ROUND((AC38*AW38*1),2)*BC38),2) -> 0 | CR38: =(ROUND((ROUND((((ET38*1.2))*AV38*1),2)*BB38),2)+ROUND((ROUND(((AE38-((EU38*1.2)))*AV38*1),2)*BS38),2)) -> 0 | CS38: =(ROUND((ROUND((((EU38*1.2))*AV38*1),2)*BS38),2)+ROUND((ROUND(((AE38-((EU38*1.2)))*AV38*1),2)*BS38),2)) -> 0 | CT38: =ROUND((ROUND((AF38*AV38*1),2)*BA38),2) -> 1260.33 | CU38: =AG38 -> 0 | CV38: =(AH38*AV38) -> 107.17092 | CW38: =AI38 -> 0 | CX38: =AJ38 -> 0 | CY38: =(ROUND((((S38+ROUND((ROUND((((EU38*1.2))*AV38*1),2)*BS38),2))*AT38)/100),2)+ROUND(((ROUND((ROUND(((AE38-((EU38*1.2)))*AV38*1),2)*BS38),2)*AT38)/100),2)) -> 1864.04 | CZ38: =(ROUND((((S38+ROUND((ROUND((((EU38*1.2))*AV38*1),2)*BS38),2))*AU38)/100),2)+ROUND(((ROUND((ROUND(((AE38-((EU38*1.2)))*AV38*1),2)*BS38),2)*AU38)/100),2)) -> 942.73 | DB38: 19 | DD38: *1 | DE38: *1,2 | DF38: *1,2 | DG38: *1,2 | DI38: *1,2 | DJ38: *1,2 | DN38: 0 | DO38: 0 | DP38: 1 | DQ38: 1 | DU38: 1003 | DV38: 100 м | DW38: 100 м | DX38: 100 | EE38: 85635475 | EF38: 60 | EG38: Ремонтно-строительные работы | EH38: 0 | EJ38: 1 | EK38: 102 | EL38: ТСН-2001.6-65. Внутренние санитарно-технические работы: демонтаж и разборка | EM38: ТСН-2001.6-65-1 | EO38: Поправка: Гл.12.Прил.8.п.8. 3_12.00.01.11.001 | EQ38: 131072 | ER38: 1003.13 | ES38: 0 | ET38: 0 | EU38: 0 | EV38: 1003.13 | EW38: 85.3 | EX38: 0 | EY38: 0 | FQ38: 0 | FR38: 0 | FS38: 0 | FX38: 87 | FY38: 44 | GD38: 1 | GF38: -1541502670 | GG38: 2 | GH38: 1 | GI38: 2 | GJ38: 0 | GK38: 0 | GL38: =ROUND(IF(AND(BH38=3,BI38=3,FS38<>0),P38,0),2) -> 0 | GM38: =ROUND(O38+X38+Y38,2)+GX38 -> 4949.34 | GN38: =IF(OR(BI38=0,BI38=1),GM38-GX38,0) -> 4949.34 | GO38: =IF(BI38=2,GM38-GX38,0) -> 0 | GP38: =IF(BI38=4,GM38-GX38,0) -> 0 | GR38: 0 | GS38: 3 | GT38: 0 | GV38: =ROUND((GT38),6) -> 0 | GW38: 1 | GX38: =ROUND(HC38*I38,2) -> 0 | HA38: 0 | HB38: 0 | HC38: =GV38*GW38 -> 0 | HS38: 0 | IK38: 0
A39: 17 | B39: 1 | C39: =ROW(SmtRes!A64) -> 64 | D39: =ROW(EtalonRes!A86) -> 86 | E39: 6 | F39: 6.65-2-2 | G39: Разборка трубопроводов из чугунных канализационных труб диаметром до 100 мм | H39: 100 м | I39: =ROUND((140+30)/100,9) -> 1.7 | J39: 0 | K39: =ROUND((140+30)/100,9) -> 1.7 | O39: =ROUND(CP39,2) -> 120733.82 | P39: =ROUND((ROUND((AC39*AW39*I39),2)*BC39),2) -> 0 | Q39: =(ROUND((ROUND((((ET39*1.2))*AV39*I39),2)*BB39),2)+ROUND((ROUND(((AE39-((EU39*1.2)))*AV39*I39),2)*BS39),2)) -> 0 | R39: =(ROUND((ROUND((((EU39*1.2))*AV39*I39),2)*BS39),2)+ROUND((ROUND(((AE39-((EU39*1.2)))*AV39*I39),2)*BS39),2)) -> 0 | S39: =ROUND((ROUND((AF39*AV39*I39),2)*BA39),2) -> 120733.82 | T39: =ROUND(CU39*I39,2) -> 0 | U39: =CV39*I39 -> 182.19056 | V39: =CW39*I39 -> 0 | W39: =ROUND(CX39*I39,2) -> 0 | X39: =(ROUND((((S39+ROUND((ROUND((((EU39*1.2))*AV39*I39),2)*BS39),2))*AT39)/100),2)+ROUND(((ROUND((ROUND(((AE39-((EU39*1.2)))*AV39*I39),2)*BS39),2)*AT39)/100),2)) -> 105038.42 | Y39: =(ROUND((((S39+ROUND((ROUND((((EU39*1.2))*AV39*I39),2)*BS39),2))*AU39)/100),2)+ROUND(((ROUND((ROUND(((AE39-((EU39*1.2)))*AV39*I39),2)*BS39),2)*AU39)/100),2)) -> 53122.88 | AA39: 86549536 | AB39: =ROUND((AC39+AD39+AF39),6) -> 1203.756 | AC39: =ROUND(((ES39*1)),6) -> 0 | AD39: =ROUND(((((ET39*1.2))-((EU39*1.2)))+AE39),6) -> 0 | AE39: =ROUND(((EU39*1.2)),6) -> 0 | AF39: =ROUND(((EV39*1.2)),6) -> 1203.756 | AG39: =ROUND((AP39),6) -> 0 | AH39: =((EW39*1.2)) -> 102.36 | AI39: =((EX39*1.2)) -> 0 | AJ39: =(AS39) -> 0 | AK39: 1003.13 | AL39: 0 | AM39: 0 | AN39: 0 | AO39: 1003.13 | AP39: 0 | AQ39: 85.3 | AR39: 0 | AS39: 0 | AT39: 87 | AU39: 44 | AV39: 1.047 | AW39: 1 | AZ39: 1 | BA39: 56.35 | BB39: 1 | BC39: 1 | BH39: 0 | BI39: 1 | BJ39: ТСН-2001.6 Доп. 68, Сб. 65, т. 2, поз. 2 | BM39: 102 | BN39: 0 | BO39: 6.65-2-2 | BP39: 1 | BQ39: 60 | BR39: 0 | BS39: 56.35 | BT39: 1 | BU39: 1 | BV39: 1 | BW39: 1 | BX39: 1 | BZ39: 87 | CA39: 44 | CE39: 1566 | CF39: 0 | CG39: 0 | CM39: 0 | CN39: Поправка: Гл.12.Прил.8.п.8. 3_12.00.01.11.001 Наименование: При наличии напряженных и стесненных условий производства работ (стесненность, сложность складирования и транспортной логистики и т.п.) для объектов, расположенных в пределах круговой магистральной системы улиц "Садовое кольцо" города Москвы | CO39: 0 | CP39: =(P39+Q39+S39) -> 120733.82 | CQ39: =ROUND((ROUND((AC39*AW39*1),2)*BC39),2) -> 0 | CR39: =(ROUND((ROUND((((ET39*1.2))*AV39*1),2)*BB39),2)+ROUND((ROUND(((AE39-((EU39*1.2)))*AV39*1),2)*BS39),2)) -> 0 | CS39: =(ROUND((ROUND((((EU39*1.2))*AV39*1),2)*BS39),2)+ROUND((ROUND(((AE39-((EU39*1.2)))*AV39*1),2)*BS39),2)) -> 0 | CT39: =ROUND((ROUND((AF39*AV39*1),2)*BA39),2) -> 71019.6 | CU39: =AG39 -> 0 | CV39: =(AH39*AV39) -> 107.17092 | CW39: =AI39 -> 0 | CX39: =AJ39 -> 0 | CY39: =(ROUND((((S39+ROUND((ROUND((((EU39*1.2))*AV39*1),2)*BS39),2))*AT39)/100),2)+ROUND(((ROUND((ROUND(((AE39-((EU39*1.2)))*AV39*1),2)*BS39),2)*AT39)/100),2)) -> 105038.42 | CZ39: =(ROUND((((S39+ROUND((ROUND((((EU39*1.2))*AV39*1),2)*BS39),2))*AU39)/100),2)+ROUND(((ROUND((ROUND(((AE39-((EU39*1.2)))*AV39*1),2)*BS39),2)*AU39)/100),2)) -> 53122.88 | DB39: 20 | DD39: *1 | DE39: *1,2 | DF39: *1,2 | DG39: *1,2 | DI39: *1,2 | DJ39: *1,2 | DN39: 0 | DO39: 0 | DP39: 1 | DQ39: 1 | DU39: 1003 | DV39: 100 м | DW39: 100 м | DX39: 100 | EE39: 85635475 | EF39: 60 | EG39: Ремонтно-строительные работы | EH39: 0 | EJ39: 1 | EK39: 102 | EL39: ТСН-2001.6-65. Внутренние санитарно-технические работы: демонтаж и разборка | EM39: ТСН-2001.6-65-1 | EO39: Поправка: Гл.12.Прил.8.п.8. 3_12.00.01.11.001 | EQ39: 131072 | ER39: 1003.13 | ES39: 0 | ET39: 0 | EU39: 0 | EV39: 1003.13 | EW39: 85.3 | EX39: 0 | EY39: 0 | FQ39: 0 | FR39: 0 | FS39: 0 | FX39: 87 | FY39: 44 | GD39: 1 | GF39: -1541502670 | GG39: 2 | GH39: 1 | GI39: 2 | GJ39: 0 | GK39: 0 | GL39: =ROUND(IF(AND(BH39=3,BI39=3,FS39<>0),P39,0),2) -> 0 | GM39: =ROUND(O39+X39+Y39,2)+GX39 -> 278895.12 | GN39: =IF(OR(BI39=0,BI39=1),GM39-GX39,0) -> 278895.12 | GO39: =IF(BI39=2,GM39-GX39,0) -> 0 | GP39: =IF(BI39=4,GM39-GX39,0) -> 0 | GR39: 0 | GS39: 3 | GT39: 0 | GV39: =ROUND((GT39),6) -> 0 | GW39: 1 | GX39: =ROUND(HC39*I39,2) -> 0 | HA39: 0 | HB39: 0 | HC39: =GV39*GW39 -> 0 | HS39: 0 | IK39: 0
A40: 17 | B40: 1 | C40: =ROW(SmtRes!A66) -> 66 | D40: =ROW(EtalonRes!A88) -> 88 | E40: 7 | F40: 6.65-2-1 | G40: Разборка трубопроводов из чугунных канализационных труб диаметром до 50 мм | H40: 100 м | I40: =ROUND((52+21+10)/100,9) -> 0.83 | J40: 0 | K40: =ROUND((52+21+10)/100,9) -> 0.83 | O40: =ROUND(CP40,2) -> 863.09 | P40: =ROUND((ROUND((AC40*AW40*I40),2)*BC40),2) -> 0 | Q40: =(ROUND((ROUND((((ET40*1.2))*AV40*I40),2)*BB40),2)+ROUND((ROUND(((AE40-((EU40*1.2)))*AV40*I40),2)*BS40),2)) -> 0 | R40: =(ROUND((ROUND((((EU40*1.2))*AV40*I40),2)*BS40),2)+ROUND((ROUND(((AE40-((EU40*1.2)))*AV40*I40),2)*BS40),2)) -> 0 | S40: =ROUND((ROUND((AF40*AV40*I40),2)*BA40),2) -> 863.09 | T40: =ROUND(CU40*I40,2) -> 0 | U40: =CV40*I40 -> 71.745466 | V40: =CW40*I40 -> 0 | W40: =ROUND(CX40*I40,2) -> 0 | X40: =(ROUND((((S40+ROUND((ROUND((((EU40*1.2))*AV40*I40),2)*BS40),2))*AT40)/100),2)+ROUND(((ROUND((ROUND(((AE40-((EU40*1.2)))*AV40*I40),2)*BS40),2)*AT40)/100),2)) -> 750.89 | Y40: =(ROUND((((S40+ROUND((ROUND((((EU40*1.2))*AV40*I40),2)*BS40),2))*AU40)/100),2)+ROUND(((ROUND((ROUND(((AE40-((EU40*1.2)))*AV40*I40),2)*BS40),2)*AU40)/100),2)) -> 379.76 | AA40: 86549534 | AB40: =ROUND((AC40+AD40+AF40),6) -> 993.192 | AC40: =ROUND(((ES40*1)),6) -> 0 | AD40: =ROUND(((((ET40*1.2))-((EU40*1.2)))+AE40),6) -> 0 | AE40: =ROUND(((EU40*1.2)),6) -> 0 | AF40: =ROUND(((EV40*1.2)),6) -> 993.192 | AG40: =ROUND((AP40),6) -> 0 | AH40: =((EW40*1.2)) -> 82.56 | AI40: =((EX40*1.2)) -> 0 | AJ40: =(AS40) -> 0 | AK40: 827.66 | AL40: 0 | AM40: 0 | AN40: 0 | AO40: 827.66 | AP40: 0 | AQ40: 68.8 | AR40: 0 | AS40: 0 | AT40: 87 | AU40: 44 | AV40: 1.047 | AW40: 1 | AZ40: 1 | BA40: 1 | BB40: 1 | BC40: 1 | BH40: 0 | BI40: 1 | BJ40: ТСН-2001.6 Доп. 68, Сб. 65, т. 2, поз. 1 | BM40: 102 | BN40: 0 | BO40: 6.65-2-1 | BP40: 1 | BQ40: 60 | BR40: 0 | BS40: 1 | BT40: 1 | BU40: 1 | BV40: 1 | BW40: 1 | BX40: 1 | BZ40: 87 | CA40: 44 | CE40: 1566 | CF40: 0 | CG40: 0 | CM40: 0 | CN40: Поправка: Гл.12.Прил.8.п.8. 3_12.00.01.11.001 Наименование: При наличии напряженных и стесненных условий производства работ (стесненность, сложность складирования и транспортной логистики и т.п.) для объектов, расположенных в пределах круговой магистральной системы улиц "Садовое кольцо" города Москвы | CO40: 0 | CP40: =(P40+Q40+S40) -> 863.09 | CQ40: =ROUND((ROUND((AC40*AW40*1),2)*BC40),2) -> 0 | CR40: =(ROUND((ROUND((((ET40*1.2))*AV40*1),2)*BB40),2)+ROUND((ROUND(((AE40-((EU40*1.2)))*AV40*1),2)*BS40),2)) -> 0 | CS40: =(ROUND((ROUND((((EU40*1.2))*AV40*1),2)*BS40),2)+ROUND((ROUND(((AE40-((EU40*1.2)))*AV40*1),2)*BS40),2)) -> 0 | CT40: =ROUND((ROUND((AF40*AV40*1),2)*BA40),2) -> 1039.87 | CU40: =AG40 -> 0 | CV40: =(AH40*AV40) -> 86.44032 | CW40: =AI40 -> 0 | CX40: =AJ40 -> 0 | CY40: =(ROUND((((S40+ROUND((ROUND((((EU40*1.2))*AV40*1),2)*BS40),2))*AT40)/100),2)+ROUND(((ROUND((ROUND(((AE40-((EU40*1.2)))*AV40*1),2)*BS40),2)*AT40)/100),2)) -> 750.89 | CZ40: =(ROUND((((S40+ROUND((ROUND((((EU40*1.2))*AV40*1),2)*BS40),2))*AU40)/100),2)+ROUND(((ROUND((ROUND(((AE40-((EU40*1.2)))*AV40*1),2)*BS40),2)*AU40)/100),2)) -> 379.76 | DB40: 21 | DD40: *1 | DE40: *1,2 | DF40: *1,2 | DG40: *1,2 | DI40: *1,2 | DJ40: *1,2 | DN40: 0 | DO40: 0 | DP40: 1 | DQ40: 1 | DU40: 1003 | DV40: 100 м | DW40: 100 м | DX40: 100 | EE40: 85635475 | EF40: 60 | EG40: Ремонтно-строительные работы | EH40: 0 | EJ40: 1 | EK40: 102 | EL40: ТСН-2001.6-65. Внутренние санитарно-технические работы: демонтаж и разборка | EM40: ТСН-2001.6-65-1 | EO40: Поправка: Гл.12.Прил.8.п.8. 3_12.00.01.11.001 | EQ40: 131072 | ER40: 827.66 | ES40: 0 | ET40: 0 | EU40: 0 | EV40: 827.66 | EW40: 68.8 | EX40: 0 | EY40: 0 | FQ40: 0 | FR40: 0 | FS40: 0 | FX40: 87 | FY40: 44 | GD40: 1 | GF40: 672191954 | GG40: 2 | GH40: 1 | GI40: 2 | GJ40: 0 | GK40: 0 | GL40: =ROUND(IF(AND(BH40=3,BI40=3,FS40<>0),P40,0),2) -> 0 | GM40: =ROUND(O40+X40+Y40,2)+GX40 -> 1993.74 | GN40: =IF(OR(BI40=0,BI40=1),GM40-GX40,0) -> 1993.74 | GO40: =IF(BI40=2,GM40-GX40,0) -> 0 | GP40: =IF(BI40=4,GM40-GX40,0) -> 0 | GR40: 0 | GS40: 3 | GT40: 0 | GV40: =ROUND((GT40),6) -> 0 | GW40: 1 | GX40: =ROUND(HC40*I40,2) -> 0 | HA40: 0 | HB40: 0 | HC40: =GV40*GW40 -> 0 | HS40: 0 | IK40: 0
A41: 17 | B41: 1 | C41: =ROW(SmtRes!A68) -> 68 | D41: =ROW(EtalonRes!A90) -> 90 | E41: 7 | F41: 6.65-2-1 | G41: Разборка трубопроводов из чугунных канализационных труб диаметром до 50 мм | H41: 100 м | I41: =ROUND((52+21+10)/100,9) -> 0.83 | J41: 0 | K41: =ROUND((52+21+10)/100,9) -> 0.83 | O41: =ROUND(CP41,2) -> 48635.12 | P41: =ROUND((ROUND((AC41*AW41*I41),2)*BC41),2) -> 0 | Q41: =(ROUND((ROUND((((ET41*1.2))*AV41*I41),2)*BB41),2)+ROUND((ROUND(((AE41-((EU41*1.2)))*AV41*I41),2)*BS41),2)) -> 0 | R41: =(ROUND((ROUND((((EU41*1.2))*AV41*I41),2)*BS41),2)+ROUND((ROUND(((AE41-((EU41*1.2)))*AV41*I41),2)*BS41),2)) -> 0 | S41: =ROUND((ROUND((AF41*AV41*I41),2)*BA41),2) -> 48635.12 | T41: =ROUND(CU41*I41,2) -> 0 | U41: =CV41*I41 -> 71.745466 | V41: =CW41*I41 -> 0 | W41: =ROUND(CX41*I41,2) -> 0 | X41: =(ROUND((((S41+ROUND((ROUND((((EU41*1.2))*AV41*I41),2)*BS41),2))*AT41)/100),2)+ROUND(((ROUND((ROUND(((AE41-((EU41*1.2)))*AV41*I41),2)*BS41),2)*AT41)/100),2)) -> 42312.55 | Y41: =(ROUND((((S41+ROUND((ROUND((((EU41*1.2))*AV41*I41),2)*BS41),2))*AU41)/100),2)+ROUND(((ROUND((ROUND(((AE41-((EU41*1.2)))*AV41*I41),2)*BS41),2)*AU41)/100),2)) -> 21399.45 | AA41: 86549536 | AB41: =ROUND((AC41+AD41+AF41),6) -> 993.192 | AC41: =ROUND(((ES41*1)),6) -> 0 | AD41: =ROUND(((((ET41*1.2))-((EU41*1.2)))+AE41),6) -> 0 | AE41: =ROUND(((EU41*1.2)),6) -> 0 | AF41: =ROUND(((EV41*1.2)),6) -> 993.192 | AG41: =ROUND((AP41),6) -> 0 | AH41: =((EW41*1.2)) -> 82.56 | AI41: =((EX41*1.2)) -> 0 | AJ41: =(AS41) -> 0 | AK41: 827.66 | AL41: 0 | AM41: 0 | AN41: 0 | AO41: 827.66 | AP41: 0 | AQ41: 68.8 | AR41: 0 | AS41: 0 | AT41: 87 | AU41: 44 | AV41: 1.047 | AW41: 1 | AZ41: 1 | BA41: 56.35 | BB41: 1 | BC41: 1 | BH41: 0 | BI41: 1 | BJ41: ТСН-2001.6 Доп. 68, Сб. 65, т. 2, поз. 1 | BM41: 102 | BN41: 0 | BO41: 6.65-2-1 | BP41: 1 | BQ41: 60 | BR41: 0 | BS41: 56.35 | BT41: 1 | BU41: 1 | BV41: 1 | BW41: 1 | BX41: 1 | BZ41: 87 | CA41: 44 | CE41: 1566 | CF41: 0 | CG41: 0 | CM41: 0 | CN41: Поправка: Гл.12.Прил.8.п.8. 3_12.00.01.11.001 Наименование: При наличии напряженных и стесненных условий производства работ (стесненность, сложность складирования и транспортной логистики и т.п.) для объектов, расположенных в пределах круговой магистральной системы улиц "Садовое кольцо" города Москвы | CO41: 0 | CP41: =(P41+Q41+S41) -> 48635.12 | CQ41: =ROUND((ROUND((AC41*AW41*1),2)*BC41),2) -> 0 | CR41: =(ROUND((ROUND((((ET41*1.2))*AV41*1),2)*BB41),2)+ROUND((ROUND(((AE41-((EU41*1.2)))*AV41*1),2)*BS41),2)) -> 0 | CS41: =(ROUND((ROUND((((EU41*1.2))*AV41*1),2)*BS41),2)+ROUND((ROUND(((AE41-((EU41*1.2)))*AV41*1),2)*BS41),2)) -> 0 | CT41: =ROUND((ROUND((AF41*AV41*1),2)*BA41),2) -> 58596.67 | CU41: =AG41 -> 0 | CV41: =(AH41*AV41) -> 86.44032 | CW41: =AI41 -> 0 | CX41: =AJ41 -> 0 | CY41: =(ROUND((((S41+ROUND((ROUND((((EU41*1.2))*AV41*1),2)*BS41),2))*AT41)/100),2)+ROUND(((ROUND((ROUND(((AE41-((EU41*1.2)))*AV41*1),2)*BS41),2)*AT41)/100),2)) -> 42312.55 | CZ41: =(ROUND((((S41+ROUND((ROUND((((EU41*1.2))*AV41*1),2)*BS41),2))*AU41)/100),2)+ROUND(((ROUND((ROUND(((AE41-((EU41*1.2)))*AV41*1),2)*BS41),2)*AU41)/100),2)) -> 21399.45 | DB41: 22 | DD41: *1 | DE41: *1,2 | DF41: *1,2 | DG41: *1,2 | DI41: *1,2 | DJ41: *1,2 | DN41: 0 | DO41: 0 | DP41: 1 | DQ41: 1 | DU41: 1003 | DV41: 100 м | DW41: 100 м | DX41: 100 | EE41: 85635475 | EF41: 60 | EG41: Ремонтно-строительные работы | EH41: 0 | EJ41: 1 | EK41: 102 | EL41: ТСН-2001.6-65. Внутренние санитарно-технические работы: демонтаж и разборка | EM41: ТСН-2001.6-65-1 | EO41: Поправка: Гл.12.Прил.8.п.8. 3_12.00.01.11.001 | EQ41: 131072 | ER41: 827.66 | ES41: 0 | ET41: 0 | EU41: 0 | EV41: 827.66 | EW41: 68.8 | EX41: 0 | EY41: 0 | FQ41: 0 | FR41: 0 | FS41: 0 | FX41: 87 | FY41: 44 | GD41: 1 | GF41: 672191954 | GG41: 2 | GH41: 1 | GI41: 2 | GJ41: 0 | GK41: 0 | GL41: =ROUND(IF(AND(BH41=3,BI41=3,FS41<>0),P41,0),2) -> 0 | GM41: =ROUND(O41+X41+Y41,2)+GX41 -> 112347.12 | GN41: =IF(OR(BI41=0,BI41=1),GM41-GX41,0) -> 112347.12 | GO41: =IF(BI41=2,GM41-GX41,0) -> 0 | GP41: =IF(BI41=4,GM41-GX41,0) -> 0 | GR41: 0 | GS41: 3 | GT41: 0 | GV41: =ROUND((GT41),6) -> 0 | GW41: 1 | GX41: =ROUND(HC41*I41,2) -> 0 | HA41: 0 | HB41: 0 | HC41: =GV41*GW41 -> 0 | HS41: 0 | IK41: 0
A42: 17 | B42: 1 | C42: =ROW(SmtRes!A70) -> 70 | D42: =ROW(EtalonRes!A92) -> 92 | E42: 8 | F42: 6.65-4-3 | G42: Демонтаж санитарно-технических приборов унитазов со смывным бачком | H42: 100 комплектов | I42: =ROUND((37+1)/100,9) -> 0.38 | J42: 0 | K42: =ROUND((37+1)/100,9) -> 0.38 | O42: =ROUND(CP42,2) -> 802.89 | P42: =ROUND((ROUND((AC42*AW42*I42),2)*BC42),2) -> 0 | Q42: =(ROUND((ROUND((((ET42*1.2))*AV42*I42),2)*BB42),2)+ROUND((ROUND(((AE42-((EU42*1.2)))*AV42*I42),2)*BS42),2)) -> 0 | R42: =(ROUND((ROUND((((EU42*1.2))*AV42*I42),2)*BS42),2)+ROUND((ROUND(((AE42-((EU42*1.2)))*AV42*I42),2)*BS42),2)) -> 0 | S42: =ROUND((ROUND((AF42*AV42*I42),2)*BA42),2) -> 802.89 | T42: =ROUND(CU42*I42,2) -> 0 | U42: =CV42*I42 -> 68.272776 | V42: =CW42*I42 -> 0 | W42: =ROUND(CX42*I42,2) -> 0 | X42: =(ROUND((((S42+ROUND((ROUND((((EU42*1.2))*AV42*I42),2)*BS42),2))*AT42)/100),2)+ROUND(((ROUND((ROUND(((AE42-((EU42*1.2)))*AV42*I42),2)*BS42),2)*AT42)/100),2)) -> 698.51 | Y42: =(ROUND((((S42+ROUND((ROUND((((EU42*1.2))*AV42*I42),2)*BS42),2))*AU42)/100),2)+ROUND(((ROUND((ROUND(((AE42-((EU42*1.2)))*AV42*I42),2)*BS42),2)*AU42)/100),2)) -> 353.27 | AA42: 86549534 | AB42: =ROUND((AC42+AD42+AF42),6) -> 2018.016 | AC42: =ROUND(((ES42*1)),6) -> 0 | AD42: =ROUND(((((ET42*1.2))-((EU42*1.2)))+AE42),6) -> 0 | AE42: =ROUND(((EU42*1.2)),6) -> 0 | AF42: =ROUND(((EV42*1.2)),6) -> 2018.016 | AG42: =ROUND((AP42),6) -> 0 | AH42: =((EW42*1.2)) -> 171.6 | AI42: =((EX42*1.2)) -> 0 | AJ42: =(AS42) -> 0 | AK42: 1681.68 | AL42: 0 | AM42: 0 | AN42: 0 | AO42: 1681.68 | AP42: 0 | AQ42: 143 | AR42: 0 | AS42: 0 | AT42: 87 | AU42: 44 | AV42: 1.047 | AW42: 1 | AZ42: 1 | BA42: 1 | BB42: 1 | BC42: 1 | BH42: 0 | BI42: 1 | BJ42: ТСН-2001.6 Доп. 80, Сб. 65, т. 4, поз. 3 | BM42: 102 | BN42: 0 | BO42: 6.65-4-3 | BP42: 1 | BQ42: 60 | BR42: 0 | BS42: 1 | BT42: 1 | BU42: 1 | BV42: 1 | BW42: 1 | BX42: 1 | BZ42: 87 | CA42: 44 | CE42: 1566 | CF42: 0 | CG42: 0 | CM42: 0 | CN42: Поправка: Гл.12.Прил.8.п.8. 3_12.00.01.11.001 Наименование: При наличии напряженных и стесненных условий производства работ (стесненность, сложность складирования и транспортной логистики и т.п.) для объектов, расположенных в пределах круговой магистральной системы улиц "Садовое кольцо" города Москвы | CO42: 0 | CP42: =(P42+Q42+S42) -> 802.89 | CQ42: =ROUND((ROUND((AC42*AW42*1),2)*BC42),2) -> 0 | CR42: =(ROUND((ROUND((((ET42*1.2))*AV42*1),2)*BB42),2)+ROUND((ROUND(((AE42-((EU42*1.2)))*AV42*1),2)*BS42),2)) -> 0 | CS42: =(ROUND((ROUND((((EU42*1.2))*AV42*1),2)*BS42),2)+ROUND((ROUND(((AE42-((EU42*1.2)))*AV42*1),2)*BS42),2)) -> 0 | CT42: =ROUND((ROUND((AF42*AV42*1),2)*BA42),2) -> 2112.86 | CU42: =AG42 -> 0 | CV42: =(AH42*AV42) -> 179.6652 | CW42: =AI42 -> 0 | CX42: =AJ42 -> 0 | CY42: =(ROUND((((S42+ROUND((ROUND((((EU42*1.2))*AV42*1),2)*BS42),2))*AT42)/100),2)+ROUND(((ROUND((ROUND(((AE42-((EU42*1.2)))*AV42*1),2)*BS42),2)*AT42)/100),2)) -> 698.51 | CZ42: =(ROUND((((S42+ROUND((ROUND((((EU42*1.2))*AV42*1),2)*BS42),2))*AU42)/100),2)+ROUND(((ROUND((ROUND(((AE42-((EU42*1.2)))*AV42*1),2)*BS42),2)*AU42)/100),2)) -> 353.27 | DB42: 23 | DD42: *1 | DE42: *1,2 | DF42: *1,2 | DG42: *1,2 | DI42: *1,2 | DJ42: *1,2 | DN42: 0 | DO42: 0 | DP42: 1 | DQ42: 1 | DU42: 1013 | DV42: 100 комплектов | DW42: 100 комплектов | DX42: 1 | EE42: 85635475 | EF42: 60 | EG42: Ремонтно-строительные работы | EH42: 0 | EJ42: 1 | EK42: 102 | EL42: ТСН-2001.6-65. Внутренние санитарно-технические работы: демонтаж и разборка | EM42: ТСН-2001.6-65-1 | EO42: Поправка: Гл.12.Прил.8.п.8. 3_12.00.01.11.001 | EQ42: 131072 | ER42: 1681.68 | ES42: 0 | ET42: 0 | EU42: 0 | EV42: 1681.68 | EW42: 143 | EX42: 0 | EY42: 0 | FQ42: 0 | FR42: 0 | FS42: 0 | FX42: 87 | FY42: 44 | GD42: 1 | GF42: 2018900478 | GG42: 2 | GH42: 1 | GI42: 2 | GJ42: 0 | GK42: 0 | GL42: =ROUND(IF(AND(BH42=3,BI42=3,FS42<>0),P42,0),2) -> 0 | GM42: =ROUND(O42+X42+Y42,2)+GX42 -> 1854.67 | GN42: =IF(OR(BI42=0,BI42=1),GM42-GX42,0) -> 1854.67 | GO42: =IF(BI42=2,GM42-GX42,0) -> 0 | GP42: =IF(BI42=4,GM42-GX42,0) -> 0 | GR42: 0 | GS42: 3 | GT42: 0 | GV42: =ROUND((GT42),6) -> 0 | GW42: 1 | GX42: =ROUND(HC42*I42,2) -> 0 | HA42: 0 | HB42: 0 | HC42: =GV42*GW42 -> 0 | HS42: 0 | IK42: 0
A43: 17 | B43: 1 | C43: =ROW(SmtRes!A72) -> 72 | D43: =ROW(EtalonRes!A94) -> 94 | E43: 8 | F43: 6.65-4-3 | G43: Демонтаж санитарно-технических приборов унитазов со смывным бачком | H43: 100 комплектов | I43: =ROUND((37+1)/100,9) -> 0.38 | J43: 0 | K43: =ROUND((37+1)/100,9) -> 0.38 | O43: =ROUND(CP43,2) -> 45242.85 | P43: =ROUND((ROUND((AC43*AW43*I43),2)*BC43),2) -> 0 | Q43: =(ROUND((ROUND((((ET43*1.2))*AV43*I43),2)*BB43),2)+ROUND((ROUND(((AE43-((EU43*1.2)))*AV43*I43),2)*BS43),2)) -> 0 | R43: =(ROUND((ROUND((((EU43*1.2))*AV43*I43),2)*BS43),2)+ROUND((ROUND(((AE43-((EU43*1.2)))*AV43*I43),2)*BS43),2)) -> 0 | S43: =ROUND((ROUND((AF43*AV43*I43),2)*BA43),2) -> 45242.85 | T43: =ROUND(CU43*I43,2) -> 0 | U43: =CV43*I43 -> 68.272776 | V43: =CW43*I43 -> 0 | W43: =ROUND(CX43*I43,2) -> 0 | X43: =(ROUND((((S43+ROUND((ROUND((((EU43*1.2))*AV43*I43),2)*BS43),2))*AT43)/100),2)+ROUND(((ROUND((ROUND(((AE43-((EU43*1.2)))*AV43*I43),2)*BS43),2)*AT43)/100),2)) -> 39361.28 | Y43: =(ROUND((((S43+ROUND((ROUND((((EU43*1.2))*AV43*I43),2)*BS43),2))*AU43)/100),2)+ROUND(((ROUND((ROUND(((AE43-((EU43*1.2)))*AV43*I43),2)*BS43),2)*AU43)/100),2)) -> 19906.85 | AA43: 86549536 | AB43: =ROUND((AC43+AD43+AF43),6) -> 2018.016 | AC43: =ROUND(((ES43*1)),6) -> 0 | AD43: =ROUND(((((ET43*1.2))-((EU43*1.2)))+AE43),6) -> 0 | AE43: =ROUND(((EU43*1.2)),6) -> 0 | AF43: =ROUND(((EV43*1.2)),6) -> 2018.016 | AG43: =ROUND((AP43),6) -> 0 | AH43: =((EW43*1.2)) -> 171.6 | AI43: =((EX43*1.2)) -> 0 | AJ43: =(AS43) -> 0 | AK43: 1681.68 | AL43: 0 | AM43: 0 | AN43: 0 | AO43: 1681.68 | AP43: 0 | AQ43: 143 | AR43: 0 | AS43: 0 | AT43: 87 | AU43: 44 | AV43: 1.047 | AW43: 1 | AZ43: 1 | BA43: 56.35 | BB43: 1 | BC43: 1 | BH43: 0 | BI43: 1 | BJ43: ТСН-2001.6 Доп. 80, Сб. 65, т. 4, поз. 3 | BM43: 102 | BN43: 0 | BO43: 6.65-4-3 | BP43: 1 | BQ43: 60 | BR43: 0 | BS43: 56.35 | BT43: 1 | BU43: 1 | BV43: 1 | BW43: 1 | BX43: 1 | BZ43: 87 | CA43: 44 | CE43: 1566 | CF43: 0 | CG43: 0 | CM43: 0 | CN43: Поправка: Гл.12.Прил.8.п.8. 3_12.00.01.11.001 Наименование: При наличии напряженных и стесненных условий производства работ (стесненность, сложность складирования и транспортной логистики и т.п.) для объектов, расположенных в пределах круговой магистральной системы улиц "Садовое кольцо" города Москвы | CO43: 0 | CP43: =(P43+Q43+S43) -> 45242.85 | CQ43: =ROUND((ROUND((AC43*AW43*1),2)*BC43),2) -> 0 | CR43: =(ROUND((ROUND((((ET43*1.2))*AV43*1),2)*BB43),2)+ROUND((ROUND(((AE43-((EU43*1.2)))*AV43*1),2)*BS43),2)) -> 0 | CS43: =(ROUND((ROUND((((EU43*1.2))*AV43*1),2)*BS43),2)+ROUND((ROUND(((AE43-((EU43*1.2)))*AV43*1),2)*BS43),2)) -> 0 | CT43: =ROUND((ROUND((AF43*AV43*1),2)*BA43),2) -> 119059.66 | CU43: =AG43 -> 0 | CV43: =(AH43*AV43) -> 179.6652 | CW43: =AI43 -> 0 | CX43: =AJ43 -> 0 | CY43: =(ROUND((((S43+ROUND((ROUND((((EU43*1.2))*AV43*1),2)*BS43),2))*AT43)/100),2)+ROUND(((ROUND((ROUND(((AE43-((EU43*1.2)))*AV43*1),2)*BS43),2)*AT43)/100),2)) -> 39361.28 | CZ43: =(ROUND((((S43+ROUND((ROUND((((EU43*1.2))*AV43*1),2)*BS43),2))*AU43)/100),2)+ROUND(((ROUND((ROUND(((AE43-((EU43*1.2)))*AV43*1),2)*BS43),2)*AU43)/100),2)) -> 19906.85 | DB43: 24 | DD43: *1 | DE43: *1,2 | DF43: *1,2 | DG43: *1,2 | DI43: *1,2 | DJ43: *1,2 | DN43: 0 | DO43: 0 | DP43: 1 | DQ43: 1 | DU43: 1013 | DV43: 100 комплектов | DW43: 100 комплектов | DX43: 1 | EE43: 85635475 | EF43: 60 | EG43: Ремонтно-строительные работы | EH43: 0 | EJ43: 1 | EK43: 102 | EL43: ТСН-2001.6-65. Внутренние санитарно-технические работы: демонтаж и разборка | EM43: ТСН-2001.6-65-1 | EO43: Поправка: Гл.12.Прил.8.п.8. 3_12.00.01.11.001 | EQ43: 131072 | ER43: 1681.68 | ES43: 0 | ET43: 0 | EU43: 0 | EV43: 1681.68 | EW43: 143 | EX43: 0 | EY43: 0 | FQ43: 0 | FR43: 0 | FS43: 0 | FX43: 87 | FY43: 44 | GD43: 1 | GF43: 2018900478 | GG43: 2 | GH43: 1 | GI43: 2 | GJ43: 0 | GK43: 0 | GL43: =ROUND(IF(AND(BH43=3,BI43=3,FS43<>0),P43,0),2) -> 0 | GM43: =ROUND(O43+X43+Y43,2)+GX43 -> 104510.98 | GN43: =IF(OR(BI43=0,BI43=1),GM43-GX43,0) -> 104510.98 | GO43: =IF(BI43=2,GM43-GX43,0) -> 0 | GP43: =IF(BI43=4,GM43-GX43,0) -> 0 | GR43: 0 | GS43: 3 | GT43: 0 | GV43: =ROUND((GT43),6) -> 0 | GW43: 1 | GX43: =ROUND(HC43*I43,2) -> 0 | HA43: 0 | HB43: 0 | HC43: =GV43*GW43 -> 0 | HS43: 0 | IK43: 0
A44: 17 | B44: 1 | C44: =ROW(SmtRes!A74) -> 74 | D44: =ROW(EtalonRes!A96) -> 96 | E44: 9 | F44: 6.65-4-1 | G44: Демонтаж санитарно-технических приборов умывальников или раковин | H44: 100 комплектов | I44: =ROUND((1+4*5+2*7+40)/100,9) -> 0.75 | J44: 0 | K44: =ROUND((1+4*5+2*7+40)/100,9) -> 0.75 | O44: =ROUND(CP44,2) -> 657.14 | P44: =ROUND((ROUND((AC44*AW44*I44),2)*BC44),2) -> 0 | Q44: =(ROUND((ROUND((((ET44*1.2))*AV44*I44),2)*BB44),2)+ROUND((ROUND(((AE44-((EU44*1.2)))*AV44*I44),2)*BS44),2)) -> 0 | R44: =(ROUND((ROUND((((EU44*1.2))*AV44*I44),2)*BS44),2)+ROUND((ROUND(((AE44-((EU44*1.2)))*AV44*I44),2)*BS44),2)) -> 0 | S44: =ROUND((ROUND((AF44*AV44*I44),2)*BA44),2) -> 657.14 | T44: =ROUND(CU44*I44,2) -> 0 | U44: =CV44*I44 -> 57.29184 | V44: =CW44*I44 -> 0 | W44: =ROUND(CX44*I44,2) -> 0 | X44: =(ROUND((((S44+ROUND((ROUND((((EU44*1.2))*AV44*I44),2)*BS44),2))*AT44)/100),2)+ROUND(((ROUND((ROUND(((AE44-((EU44*1.2)))*AV44*I44),2)*BS44),2)*AT44)/100),2)) -> 571.71 | Y44: =(ROUND((((S44+ROUND((ROUND((((EU44*1.2))*AV44*I44),2)*BS44),2))*AU44)/100),2)+ROUND(((ROUND((ROUND(((AE44-((EU44*1.2)))*AV44*I44),2)*BS44),2)*AU44)/100),2)) -> 289.14 | AA44: 86549534 | AB44: =ROUND((AC44+AD44+AF44),6) -> 836.856 | AC44: =ROUND(((ES44*1)),6) -> 0 | AD44: =ROUND(((((ET44*1.2))-((EU44*1.2)))+AE44),6) -> 0 | AE44: =ROUND(((EU44*1.2)),6) -> 0 | AF44: =ROUND(((EV44*1.2)),6) -> 836.856 | AG44: =ROUND((AP44),6) -> 0 | AH44: =((EW44*1.2)) -> 72.96 | AI44: =((EX44*1.2)) -> 0 | AJ44: =(AS44) -> 0 | AK44: 697.38 | AL44: 0 | AM44: 0 | AN44: 0 | AO44: 697.38 | AP44: 0 | AQ44: 60.8 | AR44: 0 | AS44: 0 | AT44: 87 | AU44: 44 | AV44: 1.047 | AW44: 1 | AZ44: 1 | BA44: 1 | BB44: 1 | BC44: 1 | BH44: 0 | BI44: 1 | BJ44: ТСН-2001.6 Доп. 80, Сб. 65, т. 4, поз. 1 | BM44: 102 | BN44: 0 | BO44: 6.65-4-1 | BP44: 1 | BQ44: 60 | BR44: 0 | BS44: 1 | BT44: 1 | BU44: 1 | BV44: 1 | BW44: 1 | BX44: 1 | BZ44: 87 | CA44: 44 | CE44: 1566 | CF44: 0 | CG44: 0 | CM44: 0 | CN44: Поправка: Гл.12.Прил.8.п.8. 3_12.00.01.11.001 Наименование: При наличии напряженных и стесненных условий производства работ (стесненность, сложность складирования и транспортной логистики и т.п.) для объектов, расположенных в пределах круговой магистральной системы улиц "Садовое кольцо" города Москвы | CO44: 0 | CP44: =(P44+Q44+S44) -> 657.14 | CQ44: =ROUND((ROUND((AC44*AW44*1),2)*BC44),2) -> 0 | CR44: =(ROUND((ROUND((((ET44*1.2))*AV44*1),2)*BB44),2)+ROUND((ROUND(((AE44-((EU44*1.2)))*AV44*1),2)*BS44),2)) -> 0 | CS44: =(ROUND((ROUND((((EU44*1.2))*AV44*1),2)*BS44),2)+ROUND((ROUND(((AE44-((EU44*1.2)))*AV44*1),2)*BS44),2)) -> 0 | CT44: =ROUND((ROUND((AF44*AV44*1),2)*BA44),2) -> 876.19 | CU44: =AG44 -> 0 | CV44: =(AH44*AV44) -> 76.38912 | CW44: =AI44 -> 0 | CX44: =AJ44 -> 0 | CY44: =(ROUND((((S44+ROUND((ROUND((((EU44*1.2))*AV44*1),2)*BS44),2))*AT44)/100),2)+ROUND(((ROUND((ROUND(((AE44-((EU44*1.2)))*AV44*1),2)*BS44),2)*AT44)/100),2)) -> 571.71 | CZ44: =(ROUND((((S44+ROUND((ROUND((((EU44*1.2))*AV44*1),2)*BS44),2))*AU44)/100),2)+ROUND(((ROUND((ROUND(((AE44-((EU44*1.2)))*AV44*1),2)*BS44),2)*AU44)/100),2)) -> 289.14 | DB44: 25 | DD44: *1 | DE44: *1,2 | DF44: *1,2 | DG44: *1,2 | DI44: *1,2 | DJ44: *1,2 | DN44: 0 | DO44: 0 | DP44: 1 | DQ44: 1 | DU44: 1013 | DV44: 100 комплектов | DW44: 100 комплектов | DX44: 1 | EE44: 85635475 | EF44: 60 | EG44: Ремонтно-строительные работы | EH44: 0 | EJ44: 1 | EK44: 102 | EL44: ТСН-2001.6-65. Внутренние санитарно-технические работы: демонтаж и разборка | EM44: ТСН-2001.6-65-1 | EO44: Поправка: Гл.12.Прил.8.п.8. 3_12.00.01.11.001 | EQ44: 131072 | ER44: 697.38 | ES44: 0 | ET44: 0 | EU44: 0 | EV44: 697.38 | EW44: 60.8 | EX44: 0 | EY44: 0 | FQ44: 0 | FR44: 0 | FS44: 0 | FX44: 87 | FY44: 44 | GD44: 1 | GF44: -1655995458 | GG44: 2 | GH44: 1 | GI44: 2 | GJ44: 0 | GK44: 0 | GL44: =ROUND(IF(AND(BH44=3,BI44=3,FS44<>0),P44,0),2) -> 0 | GM44: =ROUND(O44+X44+Y44,2)+GX44 -> 1517.99 | GN44: =IF(OR(BI44=0,BI44=1),GM44-GX44,0) -> 1517.99 | GO44: =IF(BI44=2,GM44-GX44,0) -> 0 | GP44: =IF(BI44=4,GM44-GX44,0) -> 0 | GR44: 0 | GS44: 3 | GT44: 0 | GV44: =ROUND((GT44),6) -> 0 | GW44: 1 | GX44: =ROUND(HC44*I44,2) -> 0 | HA44: 0 | HB44: 0 | HC44: =GV44*GW44 -> 0 | HS44: 0 | IK44: 0
A45: 17 | B45: 1 | C45: =ROW(SmtRes!A76) -> 76 | D45: =ROW(EtalonRes!A98) -> 98 | E45: 9 | F45: 6.65-4-1 | G45: Демонтаж санитарно-технических приборов умывальников или раковин | H45: 100 комплектов | I45: =ROUND((1+4*5+2*7+40)/100,9) -> 0.75 | J45: 0 | K45: =ROUND((1+4*5+2*7+40)/100,9) -> 0.75 | O45: =ROUND(CP45,2) -> 37029.84 | P45: =ROUND((ROUND((AC45*AW45*I45),2)*BC45),2) -> 0 | Q45: =(ROUND((ROUND((((ET45*1.2))*AV45*I45),2)*BB45),2)+ROUND((ROUND(((AE45-((EU45*1.2)))*AV45*I45),2)*BS45),2)) -> 0 | R45: =(ROUND((ROUND((((EU45*1.2))*AV45*I45),2)*BS45),2)+ROUND((ROUND(((AE45-((EU45*1.2)))*AV45*I45),2)*BS45),2)) -> 0 | S45: =ROUND((ROUND((AF45*AV45*I45),2)*BA45),2) -> 37029.84 | T45: =ROUND(CU45*I45,2) -> 0 | U45: =CV45*I45 -> 57.29184 | V45: =CW45*I45 -> 0 | W45: =ROUND(CX45*I45,2) -> 0 | X45: =(ROUND((((S45+ROUND((ROUND((((EU45*1.2))*AV45*I45),2)*BS45),2))*AT45)/100),2)+ROUND(((ROUND((ROUND(((AE45-((EU45*1.2)))*AV45*I45),2)*BS45),2)*AT45)/100),2)) -> 32215.96 | Y45: =(ROUND((((S45+ROUND((ROUND((((EU45*1.2))*AV45*I45),2)*BS45),2))*AU45)/100),2)+ROUND(((ROUND((ROUND(((AE45-((EU45*1.2)))*AV45*I45),2)*BS45),2)*AU45)/100),2)) -> 16293.13 | AA45: 86549536 | AB45: =ROUND((AC45+AD45+AF45),6) -> 836.856 | AC45: =ROUND(((ES45*1)),6) -> 0 | AD45: =ROUND(((((ET45*1.2))-((EU45*1.2)))+AE45),6) -> 0 | AE45: =ROUND(((EU45*1.2)),6) -> 0 | AF45: =ROUND(((EV45*1.2)),6) -> 836.856 | AG45: =ROUND((AP45),6) -> 0 | AH45: =((EW45*1.2)) -> 72.96 | AI45: =((EX45*1.2)) -> 0 | AJ45: =(AS45) -> 0 | AK45: 697.38 | AL45: 0 | AM45: 0 | AN45: 0 | AO45: 697.38 | AP45: 0 | AQ45: 60.8 | AR45: 0 | AS45: 0 | AT45: 87 | AU45: 44 | AV45: 1.047 | AW45: 1 | AZ45: 1 | BA45: 56.35 | BB45: 1 | BC45: 1 | BH45: 0 | BI45: 1 | BJ45: ТСН-2001.6 Доп. 80, Сб. 65, т. 4, поз. 1 | BM45: 102 | BN45: 0 | BO45: 6.65-4-1 | BP45: 1 | BQ45: 60 | BR45: 0 | BS45: 56.35 | BT45: 1 | BU45: 1 | BV45: 1 | BW45: 1 | BX45: 1 | BZ45: 87 | CA45: 44 | CE45: 1566 | CF45: 0 | CG45: 0 | CM45: 0 | CN45: Поправка: Гл.12.Прил.8.п.8. 3_12.00.01.11.001 Наименование: При наличии напряженных и стесненных условий производства работ (стесненность, сложность складирования и транспортной логистики и т.п.) для объектов, расположенных в пределах круговой магистральной системы улиц "Садовое кольцо" города Москвы | CO45: 0 | CP45: =(P45+Q45+S45) -> 37029.84 | CQ45: =ROUND((ROUND((AC45*AW45*1),2)*BC45),2) -> 0 | CR45: =(ROUND((ROUND((((ET45*1.2))*AV45*1),2)*BB45),2)+ROUND((ROUND(((AE45-((EU45*1.2)))*AV45*1),2)*BS45),2)) -> 0 | CS45: =(ROUND((ROUND((((EU45*1.2))*AV45*1),2)*BS45),2)+ROUND((ROUND(((AE45-((EU45*1.2)))*AV45*1),2)*BS45),2)) -> 0 | CT45: =ROUND((ROUND((AF45*AV45*1),2)*BA45),2) -> 49373.31 | CU45: =AG45 -> 0 | CV45: =(AH45*AV45) -> 76.38912 | CW45: =AI45 -> 0 | CX45: =AJ45 -> 0 | CY45: =(ROUND((((S45+ROUND((ROUND((((EU45*1.2))*AV45*1),2)*BS45),2))*AT45)/100),2)+ROUND(((ROUND((ROUND(((AE45-((EU45*1.2)))*AV45*1),2)*BS45),2)*AT45)/100),2)) -> 32215.96 | CZ45: =(ROUND((((S45+ROUND((ROUND((((EU45*1.2))*AV45*1),2)*BS45),2))*AU45)/100),2)+ROUND(((ROUND((ROUND(((AE45-((EU45*1.2)))*AV45*1),2)*BS45),2)*AU45)/100),2)) -> 16293.13 | DB45: 26 | DD45: *1 | DE45: *1,2 | DF45: *1,2 | DG45: *1,2 | DI45: *1,2 | DJ45: *1,2 | DN45: 0 | DO45: 0 | DP45: 1 | DQ45: 1 | DU45: 1013 | DV45: 100 комплектов | DW45: 100 комплектов | DX45: 1 | EE45: 85635475 | EF45: 60 | EG45: Ремонтно-строительные работы | EH45: 0 | EJ45: 1 | EK45: 102 | EL45: ТСН-2001.6-65. Внутренние санитарно-технические работы: демонтаж и разборка | EM45: ТСН-2001.6-65-1 | EO45: Поправка: Гл.12.Прил.8.п.8. 3_12.00.01.11.001 | EQ45: 131072 | ER45: 697.38 | ES45: 0 | ET45: 0 | EU45: 0 | EV45: 697.38 | EW45: 60.8 | EX45: 0 | EY45: 0 | FQ45: 0 | FR45: 0 | FS45: 0 | FX45: 87 | FY45: 44 | GD45: 1 | GF45: -1655995458 | GG45: 2 | GH45: 1 | GI45: 2 | GJ45: 0 | GK45: 0 | GL45: =ROUND(IF(AND(BH45=3,BI45=3,FS45<>0),P45,0),2) -> 0 | GM45: =ROUND(O45+X45+Y45,2)+GX45 -> 85538.93 | GN45: =IF(OR(BI45=0,BI45=1),GM45-GX45,0) -> 85538.93 | GO45: =IF(BI45=2,GM45-GX45,0) -> 0 | GP45: =IF(BI45=4,GM45-GX45,0) -> 0 | GR45: 0 | GS45: 3 | GT45: 0 | GV45: =ROUND((GT45),6) -> 0 | GW45: 1 | GX45: =ROUND(HC45*I45,2) -> 0 | HA45: 0 | HB45: 0 | HC45: =GV45*GW45 -> 0 | HS45: 0 | IK45: 0
A46: 17 | B46: 1 | C46: =ROW(SmtRes!A77) -> 77 | D46: =ROW(EtalonRes!A99) -> 99 | E46: 10 | F46: 6.65-4-7 | G46: Демонтаж санитарно-технических приборов поддонов | H46: 100 комплектов | I46: =ROUND(8/100,9) -> 0.08 | J46: 0 | K46: =ROUND(8/100,9) -> 0.08 | O46: =ROUND(CP46,2) -> 190.85 | P46: =ROUND((ROUND((AC46*AW46*I46),2)*BC46),2) -> 0 | Q46: =(ROUND((ROUND((((ET46*1.2))*AV46*I46),2)*BB46),2)+ROUND((ROUND(((AE46-((EU46*1.2)))*AV46*I46),2)*BS46),2)) -> 0 | R46: =(ROUND((ROUND((((EU46*1.2))*AV46*I46),2)*BS46),2)+ROUND((ROUND(((AE46-((EU46*1.2)))*AV46*I46),2)*BS46),2)) -> 0 | S46: =ROUND((ROUND((AF46*AV46*I46),2)*BA46),2) -> 190.85 | T46: =ROUND(CU46*I46,2) -> 0 | U46: =CV46*I46 -> 15.478848 | V46: =CW46*I46 -> 0 | W46: =ROUND(CX46*I46,2) -> 0 | X46: =(ROUND((((S46+ROUND((ROUND((((EU46*1.2))*AV46*I46),2)*BS46),2))*AT46)/100),2)+ROUND(((ROUND((ROUND(((AE46-((EU46*1.2)))*AV46*I46),2)*BS46),2)*AT46)/100),2)) -> 166.04 | Y46: =(ROUND((((S46+ROUND((ROUND((((EU46*1.2))*AV46*I46),2)*BS46),2))*AU46)/100),2)+ROUND(((ROUND((ROUND(((AE46-((EU46*1.2)))*AV46*I46),2)*BS46),2)*AU46)/100),2)) -> 83.97 | AA46: 86549534 | AB46: =ROUND((AC46+AD46+AF46),6) -> 2278.584 | AC46: =ROUND(((ES46*1)),6) -> 0 | AD46: =ROUND(((((ET46*1.2))-((EU46*1.2)))+AE46),6) -> 0 | AE46: =ROUND(((EU46*1.2)),6) -> 0 | AF46: =ROUND(((EV46*1.2)),6) -> 2278.584 | AG46: =ROUND((AP46),6) -> 0 | AH46: =((EW46*1.2)) -> 184.8 | AI46: =((EX46*1.2)) -> 0 | AJ46: =(AS46) -> 0 | AK46: 1898.82 | AL46: 0 | AM46: 0 | AN46: 0 | AO46: 1898.82 | AP46: 0 | AQ46: 154 | AR46: 0 | AS46: 0 | AT46: 87 | AU46: 44 | AV46: 1.047 | AW46: 1 | AZ46: 1 | BA46: 1 | BB46: 1 | BC46: 1 | BH46: 0 | BI46: 1 | BJ46: ТСН-2001.6 Доп. 80, Сб. 65, т. 4, поз. 7 | BM46: 102 | BN46: 0 | BO46: 6.65-4-7 | BP46: 1 | BQ46: 60 | BR46: 0 | BS46: 1 | BT46: 1 | BU46: 1 | BV46: 1 | BW46: 1 | BX46: 1 | BZ46: 87 | CA46: 44 | CE46: 1566 | CF46: 0 | CG46: 0 | CM46: 0 | CN46: Поправка: Гл.12.Прил.8.п.8. 3_12.00.01.11.001 Наименование: При наличии напряженных и стесненных условий производства работ (стесненность, сложность складирования и транспортной логистики и т.п.) для объектов, расположенных в пределах круговой магистральной системы улиц "Садовое кольцо" города Москвы | CO46: 0 | CP46: =(P46+Q46+S46) -> 190.85 | CQ46: =ROUND((ROUND((AC46*AW46*1),2)*BC46),2) -> 0 | CR46: =(ROUND((ROUND((((ET46*1.2))*AV46*1),2)*BB46),2)+ROUND((ROUND(((AE46-((EU46*1.2)))*AV46*1),2)*BS46),2)) -> 0 | CS46: =(ROUND((ROUND((((EU46*1.2))*AV46*1),2)*BS46),2)+ROUND((ROUND(((AE46-((EU46*1.2)))*AV46*1),2)*BS46),2)) -> 0 | CT46: =ROUND((ROUND((AF46*AV46*1),2)*BA46),2) -> 2385.68 | CU46: =AG46 -> 0 | CV46: =(AH46*AV46) -> 193.4856 | CW46: =AI46 -> 0 | CX46: =AJ46 -> 0 | CY46: =(ROUND((((S46+ROUND((ROUND((((EU46*1.2))*AV46*1),2)*BS46),2))*AT46)/100),2)+ROUND(((ROUND((ROUND(((AE46-((EU46*1.2)))*AV46*1),2)*BS46),2)*AT46)/100),2)) -> 166.04 | CZ46: =(ROUND((((S46+ROUND((ROUND((((EU46*1.2))*AV46*1),2)*BS46),2))*AU46)/100),2)+ROUND(((ROUND((ROUND(((AE46-((EU46*1.2)))*AV46*1),2)*BS46),2)*AU46)/100),2)) -> 83.97 | DB46: 27 | DD46: *1 | DE46: *1,2 | DF46: *1,2 | DG46: *1,2 | DI46: *1,2 | DJ46: *1,2 | DN46: 0 | DO46: 0 | DP46: 1 | DQ46: 1 | DU46: 1013 | DV46: 100 комплектов | DW46: 100 комплектов | DX46: 1 | EE46: 85635475 | EF46: 60 | EG46: Ремонтно-строительные работы | EH46: 0 | EJ46: 1 | EK46: 102 | EL46: ТСН-2001.6-65. Внутренние санитарно-технические работы: демонтаж и разборка | EM46: ТСН-2001.6-65-1 | EO46: Поправка: Гл.12.Прил.8.п.8. 3_12.00.01.11.001 | EQ46: 131072 | ER46: 1898.82 | ES46: 0 | ET46: 0 | EU46: 0 | EV46: 1898.82 | EW46: 154 | EX46: 0 | EY46: 0 | FQ46: 0 | FR46: 0 | FS46: 0 | FX46: 87 | FY46: 44 | GD46: 1 | GF46: 1859804374 | GG46: 2 | GH46: 1 | GI46: 2 | GJ46: 0 | GK46: 0 | GL46: =ROUND(IF(AND(BH46=3,BI46=3,FS46<>0),P46,0),2) -> 0 | GM46: =ROUND(O46+X46+Y46,2)+GX46 -> 440.86 | GN46: =IF(OR(BI46=0,BI46=1),GM46-GX46,0) -> 440.86 | GO46: =IF(BI46=2,GM46-GX46,0) -> 0 | GP46: =IF(BI46=4,GM46-GX46,0) -> 0 | GR46: 0 | GS46: 3 | GT46: 0 | GV46: =ROUND((GT46),6) -> 0 | GW46: 1 | GX46: =ROUND(HC46*I46,2) -> 0 | HA46: 0 | HB46: 0 | HC46: =GV46*GW46 -> 0 | HS46: 0 | IK46: 0
A47: 17 | B47: 1 | C47: =ROW(SmtRes!A78) -> 78 | D47: =ROW(EtalonRes!A100) -> 100 | E47: 10 | F47: 6.65-4-7 | G47: Демонтаж санитарно-технических приборов поддонов | H47: 100 комплектов | I47: =ROUND(8/100,9) -> 0.08 | J47: 0 | K47: =ROUND(8/100,9) -> 0.08 | O47: =ROUND(CP47,2) -> 10754.4 | P47: =ROUND((ROUND((AC47*AW47*I47),2)*BC47),2) -> 0 | Q47: =(ROUND((ROUND((((ET47*1.2))*AV47*I47),2)*BB47),2)+ROUND((ROUND(((AE47-((EU47*1.2)))*AV47*I47),2)*BS47),2)) -> 0 | R47: =(ROUND((ROUND((((EU47*1.2))*AV47*I47),2)*BS47),2)+ROUND((ROUND(((AE47-((EU47*1.2)))*AV47*I47),2)*BS47),2)) -> 0 | S47: =ROUND((ROUND((AF47*AV47*I47),2)*BA47),2) -> 10754.4 | T47: =ROUND(CU47*I47,2) -> 0 | U47: =CV47*I47 -> 15.478848 | V47: =CW47*I47 -> 0 | W47: =ROUND(CX47*I47,2) -> 0 | X47: =(ROUND((((S47+ROUND((ROUND((((EU47*1.2))*AV47*I47),2)*BS47),2))*AT47)/100),2)+ROUND(((ROUND((ROUND(((AE47-((EU47*1.2)))*AV47*I47),2)*BS47),2)*AT47)/100),2)) -> 9356.33 | Y47: =(ROUND((((S47+ROUND((ROUND((((EU47*1.2))*AV47*I47),2)*BS47),2))*AU47)/100),2)+ROUND(((ROUND((ROUND(((AE47-((EU47*1.2)))*AV47*I47),2)*BS47),2)*AU47)/100),2)) -> 4731.94 | AA47: 86549536 | AB47: =ROUND((AC47+AD47+AF47),6) -> 2278.584 | AC47: =ROUND(((ES47*1)),6) -> 0 | AD47: =ROUND(((((ET47*1.2))-((EU47*1.2)))+AE47),6) -> 0 | AE47: =ROUND(((EU47*1.2)),6) -> 0 | AF47: =ROUND(((EV47*1.2)),6) -> 2278.584 | AG47: =ROUND((AP47),6) -> 0 | AH47: =((EW47*1.2)) -> 184.8 | AI47: =((EX47*1.2)) -> 0 | AJ47: =(AS47) -> 0 | AK47: 1898.82 | AL47: 0 | AM47: 0 | AN47: 0 | AO47: 1898.82 | AP47: 0 | AQ47: 154 | AR47: 0 | AS47: 0 | AT47: 87 | AU47: 44 | AV47: 1.047 | AW47: 1 | AZ47: 1 | BA47: 56.35 | BB47: 1 | BC47: 1 | BH47: 0 | BI47: 1 | BJ47: ТСН-2001.6 Доп. 80, Сб. 65, т. 4, поз. 7 | BM47: 102 | BN47: 0 | BO47: 6.65-4-7 | BP47: 1 | BQ47: 60 | BR47: 0 | BS47: 56.35 | BT47: 1 | BU47: 1 | BV47: 1 | BW47: 1 | BX47: 1 | BZ47: 87 | CA47: 44 | CE47: 1566 | CF47: 0 | CG47: 0 | CM47: 0 | CN47: Поправка: Гл.12.Прил.8.п.8. 3_12.00.01.11.001 Наименование: При наличии напряженных и стесненных условий производства работ (стесненность, сложность складирования и транспортной логистики и т.п.) для объектов, расположенных в пределах круговой магистральной системы улиц "Садовое кольцо" города Москвы | CO47: 0 | CP47: =(P47+Q47+S47) -> 10754.4 | CQ47: =ROUND((ROUND((AC47*AW47*1),2)*BC47),2) -> 0 | CR47: =(ROUND((ROUND((((ET47*1.2))*AV47*1),2)*BB47),2)+ROUND((ROUND(((AE47-((EU47*1.2)))*AV47*1),2)*BS47),2)) -> 0 | CS47: =(ROUND((ROUND((((EU47*1.2))*AV47*1),2)*BS47),2)+ROUND((ROUND(((AE47-((EU47*1.2)))*AV47*1),2)*BS47),2)) -> 0 | CT47: =ROUND((ROUND((AF47*AV47*1),2)*BA47),2) -> 134433.07 | CU47: =AG47 -> 0 | CV47: =(AH47*AV47) -> 193.4856 | CW47: =AI47 -> 0 | CX47: =AJ47 -> 0 | CY47: =(ROUND((((S47+ROUND((ROUND((((EU47*1.2))*AV47*1),2)*BS47),2))*AT47)/100),2)+ROUND(((ROUND((ROUND(((AE47-((EU47*1.2)))*AV47*1),2)*BS47),2)*AT47)/100),2)) -> 9356.33 | CZ47: =(ROUND((((S47+ROUND((ROUND((((EU47*1.2))*AV47*1),2)*BS47),2))*AU47)/100),2)+ROUND(((ROUND((ROUND(((AE47-((EU47*1.2)))*AV47*1),2)*BS47),2)*AU47)/100),2)) -> 4731.94 | DB47: 28 | DD47: *1 | DE47: *1,2 | DF47: *1,2 | DG47: *1,2 | DI47: *1,2 | DJ47: *1,2 | DN47: 0 | DO47: 0 | DP47: 1 | DQ47: 1 | DU47: 1013 | DV47: 100 комплектов | DW47: 100 комплектов | DX47: 1 | EE47: 85635475 | EF47: 60 | EG47: Ремонтно-строительные работы | EH47: 0 | EJ47: 1 | EK47: 102 | EL47: ТСН-2001.6-65. Внутренние санитарно-технические работы: демонтаж и разборка | EM47: ТСН-2001.6-65-1 | EO47: Поправка: Гл.12.Прил.8.п.8. 3_12.00.01.11.001 | EQ47: 131072 | ER47: 1898.82 | ES47: 0 | ET47: 0 | EU47: 0 | EV47: 1898.82 | EW47: 154 | EX47: 0 | EY47: 0 | FQ47: 0 | FR47: 0 | FS47: 0 | FX47: 87 | FY47: 44 | GD47: 1 | GF47: 1859804374 | GG47: 2 | GH47: 1 | GI47: 2 | GJ47: 0 | GK47: 0 | GL47: =ROUND(IF(AND(BH47=3,BI47=3,FS47<>0),P47,0),2) -> 0 | GM47: =ROUND(O47+X47+Y47,2)+GX47 -> 24842.67 | GN47: =IF(OR(BI47=0,BI47=1),GM47-GX47,0) -> 24842.67 | GO47: =IF(BI47=2,GM47-GX47,0) -> 0 | GP47: =IF(BI47=4,GM47-GX47,0) -> 0 | GR47: 0 | GS47: 3 | GT47: 0 | GV47: =ROUND((GT47),6) -> 0 | GW47: 1 | GX47: =ROUND(HC47*I47,2) -> 0 | HA47: 0 | HB47: 0 | HC47: =GV47*GW47 -> 0 | HS47: 0 | IK47: 0
A49: 51 | B49: =B24 -> 1 | C49: =A24 -> 4 | D49: =ROW(A24) -> 24 | F49: =IF(F24<>"",F24,"") -> Новый раздел | G49: =IF(G24<>"",G24,"") -> Демонтажные работы. | H49: 0 | O49: =ROUND(AB49,2) -> 6485.62 | P49: =ROUND(AC49,2) -> 29.07 | Q49: =ROUND(AD49,2) -> 35.06 | R49: =ROUND(AE49,2) -> 4.59 | S49: =ROUND(AF49,2) -> 6421.49 | T49: =ROUND(AG49,2) -> 0 | U49: =AH49 -> 537.80137 | V49: =AI49 -> 0 | W49: =ROUND(AJ49,2) -> 0 | X49: =ROUND(AK49,2) -> 5900.07 | Y49: =ROUND(AL49,2) -> 3066.53 | AB49: =ROUND(SUMIF(AA28:AA47,"=86549534",O28:O47),2) -> 6485.62 | AC49: =ROUND(SUMIF(AA28:AA47,"=86549534",P28:P47),2) -> 29.07 | AD49: =ROUND(SUMIF(AA28:AA47,"=86549534",Q28:Q47),2) -> 35.06 | AE49: =ROUND(SUMIF(AA28:AA47,"=86549534",R28:R47),2) -> 4.59 | AF49: =ROUND(SUMIF(AA28:AA47,"=86549534",S28:S47),2) -> 6421.49 | AG49: =ROUND(SUMIF(AA28:AA47,"=86549534",T28:T47),2) -> 0 | AH49: =SUMIF(AA28:AA47,"=86549534",U28:U47) -> 537.80137 | AI49: =SUMIF(AA28:AA47,"=86549534",V28:V47) -> 0 | AJ49: =ROUND(SUMIF(AA28:AA47,"=86549534",W28:W47),2) -> 0 | AK49: =ROUND(SUMIF(AA28:AA47,"=86549534",X28:X47),2) -> 5900.07 | AL49: =ROUND(SUMIF(AA28:AA47,"=86549534",Y28:Y47),2) -> 3066.53 | AO49: =ROUND(BX49,2) -> 0 | AP49: =ROUND(BY49,2) -> 0 | AQ49: =ROUND(BZ49,2) -> 0 | AR49: =ROUND(CA49,2) -> 15452.22 | AS49: =ROUND(CB49,2) -> 15452.22 | AT49: =ROUND(CC49,2) -> 0 | AU49: =ROUND(CD49,2) -> 0 | AV49: =ROUND(CE49,2) -> 29.07 | ... BD49: =ROUND(CM49,2) -> 0 | BX49: =ROUND(SUMIF(AA28:AA47,"=86549534",FQ28:FQ47),2) -> 0 | BY49: =ROUND(SUMIF(AA28:AA47,"=86549534",FR28:FR47),2) -> 0 | BZ49: =ROUND(SUMIF(AA28:AA47,"=86549534",GL28:GL47),2) -> 0 | CA49: =ROUND(SUMIF(AA28:AA47,"=86549534",GM28:GM47),2) -> 15452.22 | CB49: =ROUND(SUMIF(AA28:AA47,"=86549534",GN28:GN47),2) -> 15452.22 | CC49: =ROUND(SUMIF(AA28:AA47,"=86549534",GO28:GO47),2) -> 0 | CD49: =ROUND(SUMIF(AA28:AA47,"=86549534",GP28:GP47),2) -> 0 | CE49: =AC49-BX49 -> 29.07 | CF49: =AC49-BY49 -> 29.07 | CG49: =BX49-BZ49 -> 0 | CH49: =AC49-BX49-BY49+BZ49 -> 29.07 | CI49: =BY49-BZ49 -> 0 | CJ49: =ROUND(SUMIF(AA28:AA47,"=86549534",GX28:GX47),2) -> 0 | CK49: =ROUND(SUMIF(AA28:AA47,"=86549534",GY28:GY47),2) -> 0 | CL49: =ROUND(SUMIF(AA28:AA47,"=86549534",GZ28:GZ47),2) -> 0 | CM49: =ROUND(SUMIF(AA28:AA47,"=86549534",HD28:HD47),2) -> 0 | DG49: =ROUND(DT49,2) -> 362868.51 | DH49: =ROUND(DU49,2) -> 451.46 | DI49: =ROUND(DV49,2) -> 566.09 | DJ49: =ROUND(DW49,2) -> 258.65 | DK49: =ROUND(DX49,2) -> 361850.96 | DL49: =ROUND(DY49,2) -> 0 | DM49: =DZ49 -> 537.80137 | DN49: =EA49 -> 0 | DO49: =ROUND(EB49,2) -> 0 | DP49: =ROUND(EC49,2) -> 332469.13 | DQ49: =ROUND(ED49,2) -> 172799.77 | DT49: =ROUND(SUMIF(AA28:AA47,"=86549536",O28:O47),2) -> 362868.51 | DU49: =ROUND(SUMIF(AA28:AA47,"=86549536",P28:P47),2) -> 451.46 | DV49: =ROUND(SUMIF(AA28:AA47,"=86549536",Q28:Q47),2) -> 566.09 | DW49: =ROUND(SUMIF(AA28:AA47,"=86549536",R28:R47),2) -> 258.65 | DX49: =ROUND(SUMIF(AA28:AA47,"=86549536",S28:S47),2) -> 361850.96 | DY49: =ROUND(SUMIF(AA28:AA47,"=86549536",T28:T47),2) -> 0 | DZ49: =SUMIF(AA28:AA47,"=86549536",U28:U47) -> 537.80137 | EA49: =SUMIF(AA28:AA47,"=86549536",V28:V47) -> 0 | EB49: =ROUND(SUMIF(AA28:AA47,"=86549536",W28:W47),2) -> 0 | EC49: =ROUND(SUMIF(AA28:AA47,"=86549536",X28:X47),2) -> 332469.13 | ED49: =ROUND(SUMIF(AA28:AA47,"=86549536",Y28:Y47),2) -> 172799.77 | EG49: =ROUND(FP49,2) -> 0 | EH49: =ROUND(FQ49,2) -> 0 | EI49: =ROUND(FR49,2) -> 0 | EJ49: =ROUND(FS49,2) -> 868137.41 | EK49: =ROUND(FT49,2) -> 868137.41 | EL49: =ROUND(FU49,2) -> 0 | EM49: =ROUND(FV49,2) -> 0 | EN49: =ROUND(FW49,2) -> 451.46 | ... EV49: =ROUND(GE49,2) -> 0 | FP49: =ROUND(SUMIF(AA28:AA47,"=86549536",FQ28:FQ47),2) -> 0 | FQ49: =ROUND(SUMIF(AA28:AA47,"=86549536",FR28:FR47),2) -> 0 | FR49: =ROUND(SUMIF(AA28:AA47,"=86549536",GL28:GL47),2) -> 0 | FS49: =ROUND(SUMIF(AA28:AA47,"=86549536",GM28:GM47),2) -> 868137.41 | FT49: =ROUND(SUMIF(AA28:AA47,"=86549536",GN28:GN47),2) -> 868137.41 | FU49: =ROUND(SUMIF(AA28:AA47,"=86549536",GO28:GO47),2) -> 0 | FV49: =ROUND(SUMIF(AA28:AA47,"=86549536",GP28:GP47),2) -> 0 | FW49: =DU49-FP49 -> 451.46 | FX49: =DU49-FQ49 -> 451.46 | FY49: =FP49-FR49 -> 0 | FZ49: =DU49-FP49-FQ49+FR49 -> 451.46 | GA49: =FQ49-FR49 -> 0 | GB49: =ROUND(SUMIF(AA28:AA47,"=86549536",GX28:GX47),2) -> 0 | GC49: =ROUND(SUMIF(AA28:AA47,"=86549536",GY28:GY47),2) -> 0 | GD49: =ROUND(SUMIF(AA28:AA47,"=86549536",GZ28:GZ47),2) -> 0 | GE49: =ROUND(SUMIF(AA28:AA47,"=86549536",HD28:HD47),2) -> 0 | GX49: 0
A51: 50 | B51: 0 | C51: 0 | D51: 1 | E51: 201 | F51: =ROUND(Source!O49,O51) -> 6485.62 | G51: ПЗ | H51: Прямые затраты | K51: 201 | L51: 1 | M51: 3 | O51: 2 | P51: =ROUND(Source!DG49,O51) -> 362868.51 | W51: 6485.62 | X51: 1 | Y51: 6485.62 | Z51: 362868.51 | AA51: 1 | AB51: 362868.51
A52: 50 | B52: 0 | C52: 0 | D52: 1 | E52: 202 | F52: =ROUND(Source!P49,O52) -> 29.07 | G52: СтМатОб | H52: Стоимость материальных ресурсов (всего) | K52: 202 | L52: 2 | M52: 3 | O52: 2 | P52: =ROUND(Source!DH49,O52) -> 451.46 | W52: 29.07 | X52: 1 | Y52: 29.07 | Z52: 451.46 | AA52: 1 | AB52: 451.46
A53: 50 | B53: 0 | C53: 0 | D53: 1 | E53: 222 | F53: =ROUND(Source!AO49,O53) -> 0 | G53: СтМатОбЗак | H53: Стоимость материалов и оборудования заказчика | K53: 222 | L53: 3 | M53: 3 | O53: 2 | P53: =ROUND(Source!EG49,O53) -> 0 | W53: 0 | X53: 1 | Y53: 0 | Z53: 0 | AA53: 1 | AB53: 0
A54: 50 | B54: 0 | C54: 0 | D54: 1 | E54: 225 | F54: =ROUND(Source!AV49,O54) -> 29.07 | G54: СтМатОбПод | H54: Стоимость материалов и оборудования подрядчика | K54: 225 | L54: 4 | M54: 3 | O54: 2 | P54: =ROUND(Source!EN49,O54) -> 451.46 | W54: 29.07 | X54: 1 | Y54: 29.07 | Z54: 451.46 | AA54: 1 | AB54: 451.46
A55: 50 | B55: 0 | C55: 0 | D55: 1 | E55: 226 | F55: =ROUND(Source!AW49,O55) -> 29.07 | G55: СтМат | H55: Стоимость материалов (всего) | K55: 226 | L55: 5 | M55: 3 | O55: 2 | P55: =ROUND(Source!EO49,O55) -> 451.46 | W55: 29.07 | X55: 1 | Y55: 29.07 | Z55: 451.46 | AA55: 1 | AB55: 451.46
A56: 50 | B56: 0 | C56: 0 | D56: 1 | E56: 227 | F56: =ROUND(Source!AX49,O56) -> 0 | G56: СтМатЗак | H56: Стоимость материалов заказчика | K56: 227 | L56: 6 | M56: 3 | O56: 2 | P56: =ROUND(Source!EP49,O56) -> 0 | W56: 0 | X56: 1 | Y56: 0 | Z56: 0 | AA56: 1 | AB56: 0
A57: 50 | B57: 0 | C57: 0 | D57: 1 | E57: 228 | F57: =ROUND(Source!AY49,O57) -> 29.07 | G57: СтМатПод | H57: Стоимость материалов подрядчика | K57: 228 | L57: 7 | M57: 3 | O57: 2 | P57: =ROUND(Source!EQ49,O57) -> 451.46 | W57: 29.07 | X57: 1 | Y57: 29.07 | Z57: 451.46 | AA57: 1 | AB57: 451.46
A58: 50 | B58: 0 | C58: 0 | D58: 1 | E58: 216 | F58: =ROUND(Source!AP49,O58) -> 0 | G58: Оборуд | H58: Стоимость оборудования (всего) | K58: 216 | L58: 8 | M58: 3 | O58: 2 | P58: =ROUND(Source!EH49,O58) -> 0 | W58: 0 | X58: 1 | Y58: 0 | Z58: 0 | AA58: 1 | AB58: 0
A59: 50 | B59: 0 | C59: 0 | D59: 1 | E59: 223 | F59: =ROUND(Source!AQ49,O59) -> 0 | G59: ОборудЗак | H59: Стоимость оборудования заказчика | K59: 223 | L59: 9 | M59: 3 | O59: 2 | P59: =ROUND(Source!EI49,O59) -> 0 | W59: 0 | X59: 1 | Y59: 0 | Z59: 0 | AA59: 1 | AB59: 0
A60: 50 | B60: 0 | C60: 0 | D60: 1 | E60: 229 | F60: =ROUND(Source!AZ49,O60) -> 0 | G60: ОборудПод | H60: Стоимость оборудования подрядчика | K60: 229 | L60: 10 | M60: 3 | O60: 2 | P60: =ROUND(Source!ER49,O60) -> 0 | W60: 0 | X60: 1 | Y60: 0 | Z60: 0 | AA60: 1 | AB60: 0
A61: 50 | B61: 0 | C61: 0 | D61: 1 | E61: 203 | F61: =ROUND(Source!Q49,O61) -> 35.06 | G61: ЭММ | H61: Эксплуатация машин | K61: 203 | L61: 11 | M61: 3 | O61: 2 | P61: =ROUND(Source!DI49,O61) -> 566.09 | W61: 35.06 | X61: 1 | Y61: 35.06 | Z61: 566.09 | AA61: 1 | AB61: 566.09
A62: 50 | B62: 0 | C62: 0 | D62: 1 | E62: 231 | F62: =ROUND(Source!BB49,O62) -> 0 | G62: ЭММсНРиСП | H62: Эксплуатация машин по ТСН-2001.16 | K62: 231 | L62: 12 | M62: 3 | O62: 2 | P62: =ROUND(Source!ET49,O62) -> 0 | W62: 0 | X62: 1 | Y62: 0 | Z62: 0 | AA62: 1 | AB62: 0
A63: 50 | B63: 0 | C63: 0 | D63: 1 | E63: 204 | F63: =ROUND(Source!R49,O63) -> 4.59 | G63: ЗПМ | H63: ЗП машинистов | K63: 204 | L63: 13 | M63: 3 | O63: 2 | P63: =ROUND(Source!DJ49,O63) -> 258.65 | W63: 4.59 | X63: 1 | Y63: 4.59 | Z63: 258.65 | AA63: 1 | AB63: 258.65
A64: 50 | B64: 0 | C64: 0 | D64: 1 | E64: 205 | F64: =ROUND(Source!S49,O64) -> 6421.49 | G64: ОЗП | H64: Основная ЗП рабочих | K64: 205 | L64: 14 | M64: 3 | O64: 2 | P64: =ROUND(Source!DK49,O64) -> 361850.96 | W64: 6421.49 | X64: 1 | Y64: 6421.49 | Z64: 361850.96 | AA64: 1 | AB64: 361850.96
A65: 50 | B65: 0 | C65: 0 | D65: 1 | E65: 232 | F65: =ROUND(Source!BC49,O65) -> 0 | G65: ОЗПсНРиСП | H65: Основная ЗП рабочих по ТСН-2001.16 | K65: 232 | L65: 15 | M65: 3 | O65: 2 | P65: =ROUND(Source!EU49,O65) -> 0 | W65: 0 | X65: 1 | Y65: 0 | Z65: 0 | AA65: 1 | AB65: 0
A66: 50 | B66: 0 | C66: 0 | D66: 1 | E66: 214 | F66: =ROUND(Source!AS49,O66) -> 15452.22 | G66: Строит | H66: Строительные работы с НР и СП | K66: 214 | L66: 16 | M66: 3 | O66: 2 | P66: =ROUND(Source!EK49,O66) -> 868137.41 | W66: 15452.22 | X66: 1 | Y66: 15452.22 | Z66: 868137.41 | AA66: 1 | AB66: 868137.41
A67: 50 | B67: 0 | C67: 0 | D67: 1 | E67: 215 | F67: =ROUND(Source!AT49,O67) -> 0 | G67: Монтаж | H67: Монтажные работы с НР и СП | K67: 215 | L67: 17 | M67: 3 | O67: 2 | P67: =ROUND(Source!EL49,O67) -> 0 | W67: 0 | X67: 1 | Y67: 0 | Z67: 0 | AA67: 1 | AB67: 0
A68: 50 | B68: 0 | C68: 0 | D68: 1 | E68: 217 | F68: =ROUND(Source!AU49,O68) -> 0 | G68: Прочие | H68: Прочие работы с НР и СП | K68: 217 | L68: 18 | M68: 3 | O68: 2 | P68: =ROUND(Source!EM49,O68) -> 0 | W68: 0 | X68: 1 | Y68: 0 | Z68: 0 | AA68: 1 | AB68: 0
A69: 50 | B69: 0 | C69: 0 | D69: 1 | E69: 230 | F69: =ROUND(Source!BA49,O69) -> 0 | G69: ПрочиеЗатр | H69: Прочие затраты по ТСН-2001.16 | K69: 230 | L69: 19 | M69: 3 | O69: 2 | P69: =ROUND(Source!ES49,O69) -> 0 | W69: 0 | X69: 1 | Y69: 0 | Z69: 0 | AA69: 1 | AB69: 0
A70: 50 | B70: 0 | C70: 0 | D70: 1 | E70: 206 | F70: =ROUND(Source!T49,O70) -> 0 | G70: ВозврМат | H70: Возврат материалов | K70: 206 | L70: 20 | M70: 3 | O70: 2 | P70: =ROUND(Source!DL49,O70) -> 0 | W70: 0 | X70: 1 | Y70: 0 | Z70: 0 | AA70: 1 | AB70: 0
A71: 50 | B71: 0 | C71: 0 | D71: 1 | E71: 207 | F71: =Source!U49 -> 537.80137 | G71: ТрудСтр | H71: Трудозатраты строителей | K71: 207 | L71: 21 | M71: 3 | O71: -1 | P71: =Source!DM49 -> 537.80137 | W71: 537.80137 | X71: 1 | Y71: 537.80137 | Z71: 537.80137 | AA71: 1 | AB71: 537.80137
A72: 50 | B72: 0 | C72: 0 | D72: 1 | E72: 208 | F72: =Source!V49 -> 0 | G72: ТрудМаш | H72: Трудозатраты машинистов | K72: 208 | L72: 22 | M72: 3 | O72: -1 | P72: =Source!DN49 -> 0 | W72: 0 | X72: 1 | Y72: 0 | Z72: 0 | AA72: 1 | AB72: 0
A73: 50 | B73: 0 | C73: 0 | D73: 1 | E73: 209 | F73: =ROUND(Source!W49,O73) -> 0 | G73: ТранспМат | H73: Транспорт материалов | K73: 209 | L73: 23 | M73: 3 | O73: 2 | P73: =ROUND(Source!DO49,O73) -> 0 | W73: 0 | X73: 1 | Y73: 0 | Z73: 0 | AA73: 1 | AB73: 0
A74: 50 | B74: 0 | C74: 0 | D74: 1 | E74: 233 | F74: =ROUND(Source!BD49,O74) -> 0 | G74: Перевозка | H74: Перевозка грузов | K74: 233 | L74: 24 | M74: 3 | O74: 2 | P74: =ROUND(Source!EV49,O74) -> 0 | W74: 0 | X74: 1 | Y74: 0 | Z74: 0 | AA74: 1 | AB74: 0
A75: 50 | B75: 0 | C75: 0 | D75: 1 | E75: 210 | F75: =ROUND(Source!X49,O75) -> 5900.07 | G75: НР | H75: Накладные расходы | K75: 210 | L75: 25 | M75: 3 | O75: 2 | P75: =ROUND(Source!DP49,O75) -> 332469.13 | W75: 5900.07 | X75: 1 | Y75: 5900.07 | Z75: 332469.13 | AA75: 1 | AB75: 332469.13
A76: 50 | B76: 0 | C76: 0 | D76: 1 | E76: 211 | F76: =ROUND(Source!Y49,O76) -> 3066.53 | G76: СмПриб | H76: Сметная прибыль | K76: 211 | L76: 26 | M76: 3 | O76: 2 | P76: =ROUND(Source!DQ49,O76) -> 172799.77 | W76: 3066.53 | X76: 1 | Y76: 3066.53 | Z76: 172799.77 | AA76: 1 | AB76: 172799.77
A77: 50 | B77: 0 | C77: 0 | D77: 1 | E77: 224 | F77: =ROUND(Source!AR49,O77) -> 15452.22 | G77: Всего | H77: Всего с НР и СП | K77: 224 | L77: 27 | M77: 3 | O77: 2 | P77: =ROUND(Source!EJ49,O77) -> 868137.41 | W77: 15452.22 | X77: 1 | Y77: 15452.22 | Z77: 868137.41 | AA77: 1 | AB77: 868137.41
A79: 4 | B79: 1 | D79: =ROW(A98) -> 98 | F79: Новый раздел | G79: Канализация бытовая К 1 (подвал) | I79: 0 | K79: 0 | S79: 0 | T79: 0 | V79: 2 | BX79: 0 | CJ79: 0
A81: 52 | B81: =B98 -> 1 | C81: =C98 -> 4 | D81: =D98 -> 79 | E81: =E98 -> 0 | F81: =F98 -> Новый раздел | G81: =G98 -> Канализация бытовая К 1 (подвал) | O81: =O98 -> 277827.24 | P81: =P98 -> 271654.03 | Q81: =Q98 -> 100.23 | R81: =R98 -> 8.75 | S81: =S98 -> 6072.98 | T81: =T98 -> 0 | U81: =U98 -> 472.42318 | V81: =V98 -> 0 | ... GX81: =GX98 -> 0
A83: 17 | B83: 1 | C83: =ROW(SmtRes!A86) -> 86 | D83: =ROW(EtalonRes!A108) -> 108 | E83: 11 | F83: 3.16-36-2 | G83: Прокладка трубопроводов канализации из чугунных безраструбных труб, диаметр 100 мм | H83: 100 м | I83: =ROUND((140)/100,9) -> 1.4 | J83: 0 | K83: =ROUND((140)/100,9) -> 1.4 | O83: =ROUND(CP83,2) -> 4725.23 | P83: =ROUND((ROUND((AC83*AW83*I83),2)*BC83),2) -> 16.53 | Q83: =(ROUND((ROUND(((((ET83*1.25)*1.2))*AV83*I83),2)*BB83),2)+ROUND((ROUND(((AE83-(((EU83*1.25)*1.2)))*AV83*I83),2)*BS83),2)) -> 82.26 | R83: =(ROUND((ROUND(((((EU83*1.25)*1.2))*AV83*I83),2)*BS83),2)+ROUND((ROUND(((AE83-(((EU83*1.25)*1.2)))*AV83*I83),2)*BS83),2)) -> 7.28 | S83: =ROUND((ROUND((AF83*AV83*I83),2)*BA83),2) -> 4626.44 | T83: =ROUND(CU83*I83,2) -> 0 | U83: =CV83*I83 -> 360.44348 | V83: =CW83*I83 -> 0 | W83: =ROUND(CX83*I83,2) -> 0 | X83: =(ROUND((((S83+ROUND((ROUND(((((EU83*1.25)*1.2))*AV83*I83),2)*BS83),2))*AT83)/100),2)+ROUND(((ROUND((ROUND(((AE83-(((EU83*1.25)*1.2)))*AV83*I83),2)*BS83),2)*AT83)/100),2)) -> 5050.75 | Y83: =(ROUND((((S83+ROUND((ROUND(((((EU83*1.25)*1.2))*AV83*I83),2)*BS83),2))*AU83)/100),2)+ROUND(((ROUND((ROUND(((AE83-(((EU83*1.25)*1.2)))*AV83*I83),2)*BS83),2)*AU83)/100),2)) -> 2826.57 | AA83: 86549534 | AB83: =ROUND((AC83+AD83+AF83),6) -> 3163.9676 | AC83: =ROUND((((ES83*1)*1)),6) -> 11.81 | AD83: =ROUND((((((ET83*1.25)*1.2))-(((EU83*1.25)*1.2)))+AE83),6) -> 55.065 | AE83: =ROUND((((EU83*1.25)*1.2)),6) -> 4.875 | AF83: =ROUND((((EV83*1.15)*1.2)),6) -> 3097.0926 | AG83: =ROUND((AP83),6) -> 0 | AH83: =(((EW83*1.15)*1.2)) -> 241.293 | AI83: =(((EX83*1.25)*1.2)) -> 0 | AJ83: =(AS83) -> 0 | AK83: 2292.79 | AL83: 11.81 | AM83: 36.71 | AN83: 3.25 | AO83: 2244.27 | AP83: 0 | AQ83: 174.85 | AR83: 0 | AS83: 0 | AT83: 109 | AU83: 61 | AV83: 1.067 | AW83: 1 | AZ83: 1 | BA83: 1 | BB83: 1 | BC83: 1 | BH83: 0 | BI83: 1 | BJ83: ТСН-2001.3 Доп. 76, Сб. 16, т. 36, поз. 2 | BM83: 21 | BN83: 0 | BO83: 3.16-36-2 | BP83: 1 | BQ83: 30 | BR83: 0 | BS83: 1 | BT83: 1 | BU83: 1 | BV83: 1 | BW83: 1 | BX83: 1 | BZ83: 109 | CA83: 61 | CE83: 1566 | CF83: 0 | CG83: 0 | CM83: 0 | CN83: Поправка: Гл.6.Прил.2.2.п.2.2.6_06.00.01.07.001 Наименование: При выполнении при капитальном ремонте и реконструкции работ, аналогичных технологическим процессам, характерным для нового строительства, и отсутствующих в сборниках на ремонтно-строительные работы ТСН-2001.6 Поправка: Гл.12.Прил.8.п.8. 3_12.00.01.11.001 Наименование: При наличии напряженных и стесненных условий производства работ (стесненность, сложность складирования и транспортной логистики и т.п.) для объектов, расположенных в пределах круговой магистральной системы улиц "Садовое кольцо" города Москвы | CO83: 0 | CP83: =(P83+Q83+S83) -> 4725.23 | CQ83: =ROUND((ROUND((AC83*AW83*1),2)*BC83),2) -> 11.81 | CR83: =(ROUND((ROUND(((((ET83*1.25)*1.2))*AV83*1),2)*BB83),2)+ROUND((ROUND(((AE83-(((EU83*1.25)*1.2)))*AV83*1),2)*BS83),2)) -> 58.75 | CS83: =(ROUND((ROUND(((((EU83*1.25)*1.2))*AV83*1),2)*BS83),2)+ROUND((ROUND(((AE83-(((EU83*1.25)*1.2)))*AV83*1),2)*BS83),2)) -> 5.2 | CT83: =ROUND((ROUND((AF83*AV83*1),2)*BA83),2) -> 3304.6 | CU83: =AG83 -> 0 | CV83: =(AH83*AV83) -> 257.45963 | CW83: =AI83 -> 0 | CX83: =AJ83 -> 0 | CY83: =(ROUND((((S83+ROUND((ROUND(((((EU83*1.25)*1.2))*AV83*1),2)*BS83),2))*AT83)/100),2)+ROUND(((ROUND((ROUND(((AE83-(((EU83*1.25)*1.2)))*AV83*1),2)*BS83),2)*AT83)/100),2)) -> 5048.49 | CZ83: =(ROUND((((S83+ROUND((ROUND(((((EU83*1.25)*1.2))*AV83*1),2)*BS83),2))*AU83)/100),2)+ROUND(((ROUND((ROUND(((AE83-(((EU83*1.25)*1.2)))*AV83*1),2)*BS83),2)*AU83)/100),2)) -> 2825.3 | DB83: 29 | DD83: *1)*1 | DE83: *1,25)*1,2 | DF83: *1,25)*1,2 | DG83: *1,15)*1,2 | DI83: *1,15)*1,2 | DJ83: *1,25)*1,2 | DN83: 0 | DO83: 0 | DP83: 1 | DQ83: 1 | DU83: 1003 | DV83: 100 м | DW83: 100 м | DX83: 100 | EE83: 85635393 | EF83: 30 | EG83: Строительные работы | EH83: 0 | EJ83: 1 | EK83: 21 | EL83: ТСН-2001.3-16. Трубопроводы внутренние | EM83: ТСН-2001.3-16-1 | EO83: Поправка: Гл.6.Прил.2.2.п.2.2.6_06.00.01.07.001 Поправка: Гл.12.Прил.8.п.8. 3_12.00.01.11.001 | EQ83: 131072 | ER83: 2292.79 | ES83: 11.81 | ET83: 36.71 | EU83: 3.25 | EV83: 2244.27 | EW83: 174.85 | EX83: 0 | EY83: 0 | FQ83: 0 | FR83: 0 | FS83: 0 | FX83: 109 | FY83: 61 | GD83: 1 | GF83: -932252128 | GG83: 2 | GH83: 1 | GI83: 2 | GJ83: 0 | GK83: 0 | GL83: =ROUND(IF(AND(BH83=3,BI83=3,FS83<>0),P83,0),2) -> 0 | GM83: =ROUND(O83+X83+Y83,2)+GX83 -> 12602.55 | GN83: =IF(OR(BI83=0,BI83=1),GM83-GX83,0) -> 12602.55 | GO83: =IF(BI83=2,GM83-GX83,0) -> 0 | GP83: =IF(BI83=4,GM83-GX83,0) -> 0 | GR83: 0 | GS83: 3 | GT83: 0 | GV83: =ROUND((GT83),6) -> 0 | GW83: 1 | GX83: =ROUND(HC83*I83,2) -> 0 | HA83: 0 | HB83: 0 | HC83: =GV83*GW83 -> 0 | HS83: 0 | IK83: 0
A84: 17 | B84: 1 | C84: =ROW(SmtRes!A94) -> 94 | D84: =ROW(EtalonRes!A116) -> 116 | E84: 11 | F84: 3.16-36-2 | G84: Прокладка трубопроводов канализации из чугунных безраструбных труб, диаметр 100 мм | H84: 100 м | I84: =ROUND((140)/100,9) -> 1.4 | J84: 0 | K84: =ROUND((140)/100,9) -> 1.4 | O84: =ROUND(CP84,2) -> 261989.05 | P84: =ROUND((ROUND((AC84*AW84*I84),2)*BC84),2) -> 135.05 | Q84: =(ROUND((ROUND(((((ET84*1.25)*1.2))*AV84*I84),2)*BB84),2)+ROUND((ROUND(((AE84-(((EU84*1.25)*1.2)))*AV84*I84),2)*BS84),2)) -> 1154.11 | R84: =(ROUND((ROUND(((((EU84*1.25)*1.2))*AV84*I84),2)*BS84),2)+ROUND((ROUND(((AE84-(((EU84*1.25)*1.2)))*AV84*I84),2)*BS84),2)) -> 410.23 | S84: =ROUND((ROUND((AF84*AV84*I84),2)*BA84),2) -> 260699.89 | T84: =ROUND(CU84*I84,2) -> 0 | U84: =CV84*I84 -> 360.44348 | V84: =CW84*I84 -> 0 | W84: =ROUND(CX84*I84,2) -> 0 | X84: =(ROUND((((S84+ROUND((ROUND(((((EU84*1.25)*1.2))*AV84*I84),2)*BS84),2))*AT84)/100),2)+ROUND(((ROUND((ROUND(((AE84-(((EU84*1.25)*1.2)))*AV84*I84),2)*BS84),2)*AT84)/100),2)) -> 284610.03 | Y84: =(ROUND((((S84+ROUND((ROUND(((((EU84*1.25)*1.2))*AV84*I84),2)*BS84),2))*AU84)/100),2)+ROUND(((ROUND((ROUND(((AE84-(((EU84*1.25)*1.2)))*AV84*I84),2)*BS84),2)*AU84)/100),2)) -> 159277.17 | AA84: 86549536 | AB84: =ROUND((AC84+AD84+AF84),6) -> 3163.9676 | AC84: =ROUND((((ES84*1)*1)),6) -> 11.81 | AD84: =ROUND((((((ET84*1.25)*1.2))-(((EU84*1.25)*1.2)))+AE84),6) -> 55.065 | AE84: =ROUND((((EU84*1.25)*1.2)),6) -> 4.875 | AF84: =ROUND((((EV84*1.15)*1.2)),6) -> 3097.0926 | AG84: =ROUND((AP84),6) -> 0 | AH84: =(((EW84*1.15)*1.2)) -> 241.293 | AI84: =(((EX84*1.25)*1.2)) -> 0 | AJ84: =(AS84) -> 0 | AK84: 2292.79 | AL84: 11.81 | AM84: 36.71 | AN84: 3.25 | AO84: 2244.27 | AP84: 0 | AQ84: 174.85 | AR84: 0 | AS84: 0 | AT84: 109 | AU84: 61 | AV84: 1.067 | AW84: 1 | AZ84: 1 | BA84: 56.35 | BB84: 14.03 | BC84: 8.17 | BH84: 0 | BI84: 1 | BJ84: ТСН-2001.3 Доп. 76, Сб. 16, т. 36, поз. 2 | BM84: 21 | BN84: 0 | BO84: 3.16-36-2 | BP84: 1 | BQ84: 30 | BR84: 0 | BS84: 56.35 | BT84: 1 | BU84: 1 | BV84: 1 | BW84: 1 | BX84: 1 | BZ84: 109 | CA84: 61 | CE84: 1566 | CF84: 0 | CG84: 0 | CM84: 0 | CN84: Поправка: Гл.6.Прил.2.2.п.2.2.6_06.00.01.07.001 Наименование: При выполнении при капитальном ремонте и реконструкции работ, аналогичных технологическим процессам, характерным для нового строительства, и отсутствующих в сборниках на ремонтно-строительные работы ТСН-2001.6 Поправка: Гл.12.Прил.8.п.8. 3_12.00.01.11.001 Наименование: При наличии напряженных и стесненных условий производства работ (стесненность, сложность складирования и транспортной логистики и т.п.) для объектов, расположенных в пределах круговой магистральной системы улиц "Садовое кольцо" города Москвы | CO84: 0 | CP84: =(P84+Q84+S84) -> 261989.05 | CQ84: =ROUND((ROUND((AC84*AW84*1),2)*BC84),2) -> 96.49 | CR84: =(ROUND((ROUND(((((ET84*1.25)*1.2))*AV84*1),2)*BB84),2)+ROUND((ROUND(((AE84-(((EU84*1.25)*1.2)))*AV84*1),2)*BS84),2)) -> 824.26 | CS84: =(ROUND((ROUND(((((EU84*1.25)*1.2))*AV84*1),2)*BS84),2)+ROUND((ROUND(((AE84-(((EU84*1.25)*1.2)))*AV84*1),2)*BS84),2)) -> 293.02 | CT84: =ROUND((ROUND((AF84*AV84*1),2)*BA84),2) -> 186214.21 | CU84: =AG84 -> 0 | CV84: =(AH84*AV84) -> 257.45963 | CW84: =AI84 -> 0 | CX84: =AJ84 -> 0 | CY84: =(ROUND((((S84+ROUND((ROUND(((((EU84*1.25)*1.2))*AV84*1),2)*BS84),2))*AT84)/100),2)+ROUND(((ROUND((ROUND(((AE84-(((EU84*1.25)*1.2)))*AV84*1),2)*BS84),2)*AT84)/100),2)) -> 284482.27 | CZ84: =(ROUND((((S84+ROUND((ROUND(((((EU84*1.25)*1.2))*AV84*1),2)*BS84),2))*AU84)/100),2)+ROUND(((ROUND((ROUND(((AE84-(((EU84*1.25)*1.2)))*AV84*1),2)*BS84),2)*AU84)/100),2)) -> 159205.68 | DB84: 31 | DD84: *1)*1 | DE84: *1,25)*1,2 | DF84: *1,25)*1,2 | DG84: *1,15)*1,2 | DI84: *1,15)*1,2 | DJ84: *1,25)*1,2 | DN84: 0 | DO84: 0 | DP84: 1 | DQ84: 1 | DU84: 1003 | DV84: 100 м | DW84: 100 м | DX84: 100 | EE84: 85635393 | EF84: 30 | EG84: Строительные работы | EH84: 0 | EJ84: 1 | EK84: 21 | EL84: ТСН-2001.3-16. Трубопроводы внутренние | EM84: ТСН-2001.3-16-1 | EO84: Поправка: Гл.6.Прил.2.2.п.2.2.6_06.00.01.07.001 Поправка: Гл.12.Прил.8.п.8. 3_12.00.01.11.001 | EQ84: 131072 | ER84: 2292.79 | ES84: 11.81 | ET84: 36.71 | EU84: 3.25 | EV84: 2244.27 | EW84: 174.85 | EX84: 0 | EY84: 0 | FQ84: 0 | FR84: 0 | FS84: 0 | FX84: 109 | FY84: 61 | GD84: 1 | GF84: -932252128 | GG84: 2 | GH84: 1 | GI84: 2 | GJ84: 0 | GK84: 0 | GL84: =ROUND(IF(AND(BH84=3,BI84=3,FS84<>0),P84,0),2) -> 0 | GM84: =ROUND(O84+X84+Y84,2)+GX84 -> 705876.25 | GN84: =IF(OR(BI84=0,BI84=1),GM84-GX84,0) -> 705876.25 | GO84: =IF(BI84=2,GM84-GX84,0) -> 0 | GP84: =IF(BI84=4,GM84-GX84,0) -> 0 | GR84: 0 | GS84: 3 | GT84: 0 | GV84: =ROUND((GT84),6) -> 0 | GW84: 1 | GX84: =ROUND(HC84*I84,2) -> 0 | HA84: 0 | HB84: 0 | HC84: =GV84*GW84 -> 0 | HS84: 0 | IK84: 0
A85: 18 | B85: 1 | C85: 86 | E85: 11,1 | F85: 1.12-8-75 | G85: Комплект деталей трубопроводов из чугуна с мелкодисперсным графитом с внутренним эпоксидным покрытием, наружным слоем краснокоричневой грунтовки (безраструбные трубы, фасонные части, крепеж), диаметр условного прохода 100 мм | H85: м | I85: =I83*J85 -> 140 | J85: 100 | K85: 100 | O85: =ROUND(CP85,2) -> 199323.6 | P85: =ROUND((ROUND((AC85*AW85*I85),2)*BC85),2) -> 199323.6 | Q85: =(ROUND((ROUND(((ET85)*AV85*I85),2)*BB85),2)+ROUND((ROUND(((AE85-(EU85))*AV85*I85),2)*BS85),2)) -> 0 | R85: =(ROUND((ROUND(((EU85)*AV85*I85),2)*BS85),2)+ROUND((ROUND(((AE85-(EU85))*AV85*I85),2)*BS85),2)) -> 0 | S85: =ROUND((ROUND((AF85*AV85*I85),2)*BA85),2) -> 0 | T85: =ROUND(CU85*I85,2) -> 0 | U85: =CV85*I85 -> 0 | V85: =CW85*I85 -> 0 | W85: =ROUND(CX85*I85,2) -> 0 | X85: =(ROUND((((S85+ROUND((ROUND(((EU85)*AV85*I85),2)*BS85),2))*AT85)/100),2)+ROUND(((ROUND((ROUND(((AE85-(EU85))*AV85*I85),2)*BS85),2)*AT85)/100),2)) -> 0 | Y85: =(ROUND((((S85+ROUND((ROUND(((EU85)*AV85*I85),2)*BS85),2))*AU85)/100),2)+ROUND(((ROUND((ROUND(((AE85-(EU85))*AV85*I85),2)*BS85),2)*AU85)/100),2)) -> 0 | AA85: 86549534 | AB85: =ROUND((AC85+AD85+AF85),6) -> 1423.74 | AC85: =ROUND((ES85),6) -> 1423.74 | AD85: =ROUND((((ET85)-(EU85))+AE85),6) -> 0 | AE85: =ROUND((EU85),6) -> 0 | AF85: =ROUND((EV85),6) -> 0 | AG85: =ROUND((AP85),6) -> 0 | AH85: =(EW85) -> 0 | AI85: =(EX85) -> 0 | AJ85: =(AS85) -> 0 | AK85: 1423.74 | AL85: 1423.74 | AM85: 0 | AN85: 0 | AO85: 0 | AP85: 0 | AQ85: 0 | AR85: 0 | AS85: 0 | AT85: 109 | AU85: 61 | AV85: 1 | AW85: 1 | AZ85: 1 | BA85: 1 | BB85: 1 | BC85: 1 | BH85: 3 | BI85: 1 | BJ85: ТСН-2001.1 Доп. 79, Р. 12, о. 8, поз. 75 | BM85: 21 | BN85: 0 | BP85: 0 | BQ85: 30 | BR85: 0 | BS85: 1 | BT85: 1 | BU85: 1 | BV85: 1 | BW85: 1 | BX85: 1 | BZ85: 109 | CA85: 61 | CE85: 1566 | CF85: 0 | CG85: 0 | CM85: 0 | CN85: Поправка: Гл.6.Прил.2.2.п.2.2.6_06.00.01.07.001_x000D_ Наименование: При выполнении при капитальном ремонте и реконструкции работ, аналогичных технологическим процессам, характерным для нового строительства, и отсутствующих в сборниках на ремонтно-строительные работы ТСН-2001.6_x000D_ Поправка: Гл.12.Прил.8.п.8. 3_12.00.01.11.001_x000D_ Наименование: При наличии напряженных и стесненных условий производства работ (стесненность, сложность складирования и транспортной логистики и т.п.) для объектов, расположенных в пределах круговой магистральной системы улиц "Садовое кольцо" города Москвы | CO85: 0 | CP85: =(P85+Q85+S85) -> 199323.6 | CQ85: =ROUND((ROUND((AC85*AW85*1),2)*BC85),2) -> 1423.74 | CR85: =(ROUND((ROUND(((ET85)*AV85*1),2)*BB85),2)+ROUND((ROUND(((AE85-(EU85))*AV85*1),2)*BS85),2)) -> 0 | CS85: =(ROUND((ROUND(((EU85)*AV85*1),2)*BS85),2)+ROUND((ROUND(((AE85-(EU85))*AV85*1),2)*BS85),2)) -> 0 | CT85: =ROUND((ROUND((AF85*AV85*1),2)*BA85),2) -> 0 | CU85: =AG85 -> 0 | CV85: =(AH85*AV85) -> 0 | CW85: =AI85 -> 0 | CX85: =AJ85 -> 0 | CY85: =(ROUND((((S85+ROUND((ROUND(((EU85)*AV85*1),2)*BS85),2))*AT85)/100),2)+ROUND(((ROUND((ROUND(((AE85-(EU85))*AV85*1),2)*BS85),2)*AT85)/100),2)) -> 0 | CZ85: =(ROUND((((S85+ROUND((ROUND(((EU85)*AV85*1),2)*BS85),2))*AU85)/100),2)+ROUND(((ROUND((ROUND(((AE85-(EU85))*AV85*1),2)*BS85),2)*AU85)/100),2)) -> 0 | DN85: 0 | DO85: 0 | DP85: 1 | DQ85: 1 | DU85: 1003 | DV85: м | DW85: м | DX85: 1 | EE85: 85635393 | EF85: 30 | EG85: Строительные работы | EH85: 0 | EJ85: 1 | EK85: 21 | EL85: ТСН-2001.3-16. Трубопроводы внутренние | EM85: ТСН-2001.3-16-1 | EO85: Поправка: Гл.6.Прил.2.2.п.2.2.6_06.00.01.07.001_x000D_ Поправка: Гл.12.Прил.8.п.8. 3_12.00.01.11.001 | EQ85: 0 | ER85: 1423.74 | ES85: 1423.74 | ET85: 0 | EU85: 0 | EV85: 0 | EW85: 0 | EX85: 0 | FQ85: 0 | FR85: 0 | FS85: 0 | FX85: 109 | FY85: 61 | GD85: 1 | GF85: 472920806 | GG85: 2 | GH85: 1 | GI85: -2 | GJ85: 0 | GK85: 0 | GL85: =ROUND(IF(AND(BH85=3,BI85=3,FS85<>0),P85,0),2) -> 0 | GM85: =ROUND(O85+X85+Y85,2)+GX85 -> 199323.6 | GN85: =IF(OR(BI85=0,BI85=1),GM85-GX85,0) -> 199323.6 | GO85: =IF(BI85=2,GM85-GX85,0) -> 0 | GP85: =IF(BI85=4,GM85-GX85,0) -> 0 | GR85: 0 | GS85: 3 | GT85: 0 | GV85: =ROUND((GT85),6) -> 0 | GW85: 1 | GX85: =ROUND(HC85*I85,2) -> 0 | HA85: 0 | HB85: 0 | HC85: =GV85*GW85 -> 0 | HM85: *1)*1 | HS85: 0 | IK85: 0
A86: 18 | B86: 1 | C86: 94 | E86: 11,1 | F86: 1.12-8-75 | G86: Комплект деталей трубопроводов из чугуна с мелкодисперсным графитом с внутренним эпоксидным покрытием, наружным слоем краснокоричневой грунтовки (безраструбные трубы, фасонные части, крепеж), диаметр условного прохода 100 мм | H86: м | I86: =I84*J86 -> 140 | J86: 100 | K86: 100 | O86: =ROUND(CP86,2) -> 366755.42 | P86: =ROUND((ROUND((AC86*AW86*I86),2)*BC86),2) -> 366755.42 | Q86: =(ROUND((ROUND(((ET86)*AV86*I86),2)*BB86),2)+ROUND((ROUND(((AE86-(EU86))*AV86*I86),2)*BS86),2)) -> 0 | R86: =(ROUND((ROUND(((EU86)*AV86*I86),2)*BS86),2)+ROUND((ROUND(((AE86-(EU86))*AV86*I86),2)*BS86),2)) -> 0 | S86: =ROUND((ROUND((AF86*AV86*I86),2)*BA86),2) -> 0 | T86: =ROUND(CU86*I86,2) -> 0 | U86: =CV86*I86 -> 0 | V86: =CW86*I86 -> 0 | W86: =ROUND(CX86*I86,2) -> 0 | X86: =(ROUND((((S86+ROUND((ROUND(((EU86)*AV86*I86),2)*BS86),2))*AT86)/100),2)+ROUND(((ROUND((ROUND(((AE86-(EU86))*AV86*I86),2)*BS86),2)*AT86)/100),2)) -> 0 | Y86: =(ROUND((((S86+ROUND((ROUND(((EU86)*AV86*I86),2)*BS86),2))*AU86)/100),2)+ROUND(((ROUND((ROUND(((AE86-(EU86))*AV86*I86),2)*BS86),2)*AU86)/100),2)) -> 0 | AA86: 86549536 | AB86: =ROUND((AC86+AD86+AF86),6) -> 1423.74 | AC86: =ROUND((ES86),6) -> 1423.74 | AD86: =ROUND((((ET86)-(EU86))+AE86),6) -> 0 | AE86: =ROUND((EU86),6) -> 0 | AF86: =ROUND((EV86),6) -> 0 | AG86: =ROUND((AP86),6) -> 0 | AH86: =(EW86) -> 0 | AI86: =(EX86) -> 0 | AJ86: =(AS86) -> 0 | AK86: 1423.74 | AL86: 1423.74 | AM86: 0 | AN86: 0 | AO86: 0 | AP86: 0 | AQ86: 0 | AR86: 0 | AS86: 0 | AT86: 109 | AU86: 61 | AV86: 1 | AW86: 1 | AZ86: 1 | BA86: 1 | BB86: 1 | BC86: 1.84 | BH86: 3 | BI86: 1 | BJ86: ТСН-2001.1 Доп. 79, Р. 12, о. 8, поз. 75 | BM86: 21 | BN86: 0 | BO86: 1.12-8-75 | BP86: 1 | BQ86: 30 | BR86: 0 | BS86: 1 | BT86: 1 | BU86: 1 | BV86: 1 | BW86: 1 | BX86: 1 | BZ86: 109 | CA86: 61 | CE86: 1566 | CF86: 0 | CG86: 0 | CM86: 0 | CN86: Поправка: Гл.6.Прил.2.2.п.2.2.6_06.00.01.07.001_x000D_ Наименование: При выполнении при капитальном ремонте и реконструкции работ, аналогичных технологическим процессам, характерным для нового строительства, и отсутствующих в сборниках на ремонтно-строительные работы ТСН-2001.6_x000D_ Поправка: Гл.12.Прил.8.п.8. 3_12.00.01.11.001_x000D_ Наименование: При наличии напряженных и стесненных условий производства работ (стесненность, сложность складирования и транспортной логистики и т.п.) для объектов, расположенных в пределах круговой магистральной системы улиц "Садовое кольцо" города Москвы | CO86: 0 | CP86: =(P86+Q86+S86) -> 366755.42 | CQ86: =ROUND((ROUND((AC86*AW86*1),2)*BC86),2) -> 2619.68 | CR86: =(ROUND((ROUND(((ET86)*AV86*1),2)*BB86),2)+ROUND((ROUND(((AE86-(EU86))*AV86*1),2)*BS86),2)) -> 0 | CS86: =(ROUND((ROUND(((EU86)*AV86*1),2)*BS86),2)+ROUND((ROUND(((AE86-(EU86))*AV86*1),2)*BS86),2)) -> 0 | CT86: =ROUND((ROUND((AF86*AV86*1),2)*BA86),2) -> 0 | CU86: =AG86 -> 0 | CV86: =(AH86*AV86) -> 0 | CW86: =AI86 -> 0 | CX86: =AJ86 -> 0 | CY86: =(ROUND((((S86+ROUND((ROUND(((EU86)*AV86*1),2)*BS86),2))*AT86)/100),2)+ROUND(((ROUND((ROUND(((AE86-(EU86))*AV86*1),2)*BS86),2)*AT86)/100),2)) -> 0 | CZ86: =(ROUND((((S86+ROUND((ROUND(((EU86)*AV86*1),2)*BS86),2))*AU86)/100),2)+ROUND(((ROUND((ROUND(((AE86-(EU86))*AV86*1),2)*BS86),2)*AU86)/100),2)) -> 0 | DN86: 0 | DO86: 0 | DP86: 1 | DQ86: 1 | DU86: 1003 | DV86: м | DW86: м | DX86: 1 | EE86: 85635393 | EF86: 30 | EG86: Строительные работы | EH86: 0 | EJ86: 1 | EK86: 21 | EL86: ТСН-2001.3-16. Трубопроводы внутренние | EM86: ТСН-2001.3-16-1 | EO86: Поправка: Гл.6.Прил.2.2.п.2.2.6_06.00.01.07.001_x000D_ Поправка: Гл.12.Прил.8.п.8. 3_12.00.01.11.001 | EQ86: 0 | ER86: 1423.74 | ES86: 1423.74 | ET86: 0 | EU86: 0 | EV86: 0 | EW86: 0 | EX86: 0 | FQ86: 0 | FR86: 0 | FS86: 0 | FX86: 109 | FY86: 61 | GD86: 1 | GF86: 472920806 | GG86: 2 | GH86: 1 | GI86: 2 | GJ86: 0 | GK86: 0 | GL86: =ROUND(IF(AND(BH86=3,BI86=3,FS86<>0),P86,0),2) -> 0 | GM86: =ROUND(O86+X86+Y86,2)+GX86 -> 366755.42 | GN86: =IF(OR(BI86=0,BI86=1),GM86-GX86,0) -> 366755.42 | GO86: =IF(BI86=2,GM86-GX86,0) -> 0 | GP86: =IF(BI86=4,GM86-GX86,0) -> 0 | GR86: 0 | GS86: 3 | GT86: 0 | GV86: =ROUND((GT86),6) -> 0 | GW86: 1 | GX86: =ROUND(HC86*I86,2) -> 0 | HA86: 0 | HB86: 0 | HC86: =GV86*GW86 -> 0 | HM86: *1)*1 | HS86: 0 | IK86: 0
A87: 17 | B87: 1 | C87: =ROW(SmtRes!A102) -> 102 | D87: =ROW(EtalonRes!A124) -> 124 | E87: 12 | F87: 3.16-36-1 | G87: Прокладка трубопроводов канализации из чугунных безраструбных труб, диаметр 50 мм | H87: 100 м | I87: =ROUND((52)/100,9) -> 0.52 | J87: 0 | K87: =ROUND((52)/100,9) -> 0.52 | O87: =ROUND(CP87,2) -> 1428.27 | P87: =ROUND((ROUND((AC87*AW87*I87),2)*BC87),2) -> 1.72 | Q87: =(ROUND((ROUND(((((ET87*1.25)*1.2))*AV87*I87),2)*BB87),2)+ROUND((ROUND(((AE87-(((EU87*1.25)*1.2)))*AV87*I87),2)*BS87),2)) -> 17.97 | R87: =(ROUND((ROUND(((((EU87*1.25)*1.2))*AV87*I87),2)*BS87),2)+ROUND((ROUND(((AE87-(((EU87*1.25)*1.2)))*AV87*I87),2)*BS87),2)) -> 1.47 | S87: =ROUND((ROUND((AF87*AV87*I87),2)*BA87),2) -> 1408.58 | T87: =ROUND(CU87*I87,2) -> 0 | U87: =CV87*I87 -> 108.96381 | V87: =CW87*I87 -> 0 | W87: =ROUND(CX87*I87,2) -> 0 | X87: =(ROUND((((S87+ROUND((ROUND(((((EU87*1.25)*1.2))*AV87*I87),2)*BS87),2))*AT87)/100),2)+ROUND(((ROUND((ROUND(((AE87-(((EU87*1.25)*1.2)))*AV87*I87),2)*BS87),2)*AT87)/100),2)) -> 1536.95 | Y87: =(ROUND((((S87+ROUND((ROUND(((((EU87*1.25)*1.2))*AV87*I87),2)*BS87),2))*AU87)/100),2)+ROUND(((ROUND((ROUND(((AE87-(((EU87*1.25)*1.2)))*AV87*I87),2)*BS87),2)*AU87)/100),2)) -> 860.13 | AA87: 86549534 | AB87: =ROUND((AC87+AD87+AF87),6) -> 2574.402 | AC87: =ROUND((((ES87*1)*1)),6) -> 3.3 | AD87: =ROUND((((((ET87*1.25)*1.2))-(((EU87*1.25)*1.2)))+AE87),6) -> 32.385 | AE87: =ROUND((((EU87*1.25)*1.2)),6) -> 2.655 | AF87: =ROUND((((EV87*1.15)*1.2)),6) -> 2538.717 | AG87: =ROUND((AP87),6) -> 0 | AH87: =(((EW87*1.15)*1.2)) -> 196.3878 | AI87: =(((EX87*1.25)*1.2)) -> 0 | AJ87: =(AS87) -> 0 | AK87: 1864.54 | AL87: 3.3 | AM87: 21.59 | AN87: 1.77 | AO87: 1839.65 | AP87: 0 | AQ87: 142.31 | AR87: 0 | AS87: 0 | AT87: 109 | AU87: 61 | AV87: 1.067 | AW87: 1 | AZ87: 1 | BA87: 1 | BB87: 1 | BC87: 1 | BH87: 0 | BI87: 1 | BJ87: ТСН-2001.3 Доп. 72, Сб. 16, т. 36, поз. 1 | BM87: 21 | BN87: 0 | BO87: 3.16-36-1 | BP87: 1 | BQ87: 30 | BR87: 0 | BS87: 1 | BT87: 1 | BU87: 1 | BV87: 1 | BW87: 1 | BX87: 1 | BZ87: 109 | CA87: 61 | CE87: 1566 | CF87: 0 | CG87: 0 | CM87: 0 | CN87: Поправка: Гл.6.Прил.2.2.п.2.2.6_06.00.01.07.001 Наименование: При выполнении при капитальном ремонте и реконструкции работ, аналогичных технологическим процессам, характерным для нового строительства, и отсутствующих в сборниках на ремонтно-строительные работы ТСН-2001.6 Поправка: Гл.12.Прил.8.п.8. 3_12.00.01.11.001 Наименование: При наличии напряженных и стесненных условий производства работ (стесненность, сложность складирования и транспортной логистики и т.п.) для объектов, расположенных в пределах круговой магистральной системы улиц "Садовое кольцо" города Москвы | CO87: 0 | CP87: =(P87+Q87+S87) -> 1428.27 | CQ87: =ROUND((ROUND((AC87*AW87*1),2)*BC87),2) -> 3.3 | CR87: =(ROUND((ROUND(((((ET87*1.25)*1.2))*AV87*1),2)*BB87),2)+ROUND((ROUND(((AE87-(((EU87*1.25)*1.2)))*AV87*1),2)*BS87),2)) -> 34.55 | CS87: =(ROUND((ROUND(((((EU87*1.25)*1.2))*AV87*1),2)*BS87),2)+ROUND((ROUND(((AE87-(((EU87*1.25)*1.2)))*AV87*1),2)*BS87),2)) -> 2.83 | CT87: =ROUND((ROUND((AF87*AV87*1),2)*BA87),2) -> 2708.81 | CU87: =AG87 -> 0 | CV87: =(AH87*AV87) -> 209.54578 | CW87: =AI87 -> 0 | CX87: =AJ87 -> 0 | CY87: =(ROUND((((S87+ROUND((ROUND(((((EU87*1.25)*1.2))*AV87*1),2)*BS87),2))*AT87)/100),2)+ROUND(((ROUND((ROUND(((AE87-(((EU87*1.25)*1.2)))*AV87*1),2)*BS87),2)*AT87)/100),2)) -> 1538.44 | CZ87: =(ROUND((((S87+ROUND((ROUND(((((EU87*1.25)*1.2))*AV87*1),2)*BS87),2))*AU87)/100),2)+ROUND(((ROUND((ROUND(((AE87-(((EU87*1.25)*1.2)))*AV87*1),2)*BS87),2)*AU87)/100),2)) -> 860.96 | DB87: 33 | DD87: *1)*1 | DE87: *1,25)*1,2 | DF87: *1,25)*1,2 | DG87: *1,15)*1,2 | DI87: *1,15)*1,2 | DJ87: *1,25)*1,2 | DN87: 0 | DO87: 0 | DP87: 1 | DQ87: 1 | DU87: 1003 | DV87: 100 м | DW87: 100 м | DX87: 100 | EE87: 85635393 | EF87: 30 | EG87: Строительные работы | EH87: 0 | EJ87: 1 | EK87: 21 | EL87: ТСН-2001.3-16. Трубопроводы внутренние | EM87: ТСН-2001.3-16-1 | EO87: Поправка: Гл.6.Прил.2.2.п.2.2.6_06.00.01.07.001 Поправка: Гл.12.Прил.8.п.8. 3_12.00.01.11.001 | EQ87: 131072 | ER87: 1864.54 | ES87: 3.3 | ET87: 21.59 | EU87: 1.77 | EV87: 1839.65 | EW87: 142.31 | EX87: 0 | EY87: 0 | FQ87: 0 | FR87: 0 | FS87: 0 | FX87: 109 | FY87: 61 | GD87: 1 | GF87: -932052613 | GG87: 2 | GH87: 1 | GI87: 2 | GJ87: 0 | GK87: 0 | GL87: =ROUND(IF(AND(BH87=3,BI87=3,FS87<>0),P87,0),2) -> 0 | GM87: =ROUND(O87+X87+Y87,2)+GX87 -> 3825.35 | GN87: =IF(OR(BI87=0,BI87=1),GM87-GX87,0) -> 3825.35 | GO87: =IF(BI87=2,GM87-GX87,0) -> 0 | GP87: =IF(BI87=4,GM87-GX87,0) -> 0 | GR87: 0 | GS87: 3 | GT87: 0 | GV87: =ROUND((GT87),6) -> 0 | GW87: 1 | GX87: =ROUND(HC87*I87,2) -> 0 | HA87: 0 | HB87: 0 | HC87: =GV87*GW87 -> 0 | HS87: 0 | IK87: 0
A88: 17 | B88: 1 | C88: =ROW(SmtRes!A110) -> 110 | D88: =ROW(EtalonRes!A132) -> 132 | E88: 12 | F88: 3.16-36-1 | G88: Прокладка трубопроводов канализации из чугунных безраструбных труб, диаметр 50 мм | H88: 100 м | I88: =ROUND((52)/100,9) -> 0.52 | J88: 0 | K88: =ROUND((52)/100,9) -> 0.52 | O88: =ROUND(CP88,2) -> 79635 | P88: =ROUND((ROUND((AC88*AW88*I88),2)*BC88),2) -> 15.33 | Q88: =(ROUND((ROUND(((((ET88*1.25)*1.2))*AV88*I88),2)*BB88),2)+ROUND((ROUND(((AE88-(((EU88*1.25)*1.2)))*AV88*I88),2)*BS88),2)) -> 246.19 | R88: =(ROUND((ROUND(((((EU88*1.25)*1.2))*AV88*I88),2)*BS88),2)+ROUND((ROUND(((AE88-(((EU88*1.25)*1.2)))*AV88*I88),2)*BS88),2)) -> 82.83 | S88: =ROUND((ROUND((AF88*AV88*I88),2)*BA88),2) -> 79373.48 | T88: =ROUND(CU88*I88,2) -> 0 | U88: =CV88*I88 -> 108.96381 | V88: =CW88*I88 -> 0 | W88: =ROUND(CX88*I88,2) -> 0 | X88: =(ROUND((((S88+ROUND((ROUND(((((EU88*1.25)*1.2))*AV88*I88),2)*BS88),2))*AT88)/100),2)+ROUND(((ROUND((ROUND(((AE88-(((EU88*1.25)*1.2)))*AV88*I88),2)*BS88),2)*AT88)/100),2)) -> 86607.38 | Y88: =(ROUND((((S88+ROUND((ROUND(((((EU88*1.25)*1.2))*AV88*I88),2)*BS88),2))*AU88)/100),2)+ROUND(((ROUND((ROUND(((AE88-(((EU88*1.25)*1.2)))*AV88*I88),2)*BS88),2)*AU88)/100),2)) -> 48468.35 | AA88: 86549536 | AB88: =ROUND((AC88+AD88+AF88),6) -> 2574.402 | AC88: =ROUND((((ES88*1)*1)),6) -> 3.3 | AD88: =ROUND((((((ET88*1.25)*1.2))-(((EU88*1.25)*1.2)))+AE88),6) -> 32.385 | AE88: =ROUND((((EU88*1.25)*1.2)),6) -> 2.655 | AF88: =ROUND((((EV88*1.15)*1.2)),6) -> 2538.717 | AG88: =ROUND((AP88),6) -> 0 | AH88: =(((EW88*1.15)*1.2)) -> 196.3878 | AI88: =(((EX88*1.25)*1.2)) -> 0 | AJ88: =(AS88) -> 0 | AK88: 1864.54 | AL88: 3.3 | AM88: 21.59 | AN88: 1.77 | AO88: 1839.65 | AP88: 0 | AQ88: 142.31 | AR88: 0 | AS88: 0 | AT88: 109 | AU88: 61 | AV88: 1.067 | AW88: 1 | AZ88: 1 | BA88: 56.35 | BB88: 13.7 | BC88: 8.91 | BH88: 0 | BI88: 1 | BJ88: ТСН-2001.3 Доп. 72, Сб. 16, т. 36, поз. 1 | BM88: 21 | BN88: 0 | BO88: 3.16-36-1 | BP88: 1 | BQ88: 30 | BR88: 0 | BS88: 56.35 | BT88: 1 | BU88: 1 | BV88: 1 | BW88: 1 | BX88: 1 | BZ88: 109 | CA88: 61 | CE88: 1566 | CF88: 0 | CG88: 0 | CM88: 0 | CN88: Поправка: Гл.6.Прил.2.2.п.2.2.6_06.00.01.07.001 Наименование: При выполнении при капитальном ремонте и реконструкции работ, аналогичных технологическим процессам, характерным для нового строительства, и отсутствующих в сборниках на ремонтно-строительные работы ТСН-2001.6 Поправка: Гл.12.Прил.8.п.8. 3_12.00.01.11.001 Наименование: При наличии напряженных и стесненных условий производства работ (стесненность, сложность складирования и транспортной логистики и т.п.) для объектов, расположенных в пределах круговой магистральной системы улиц "Садовое кольцо" города Москвы | CO88: 0 | CP88: =(P88+Q88+S88) -> 79635 | CQ88: =ROUND((ROUND((AC88*AW88*1),2)*BC88),2) -> 29.4 | CR88: =(ROUND((ROUND(((((ET88*1.25)*1.2))*AV88*1),2)*BB88),2)+ROUND((ROUND(((AE88-(((EU88*1.25)*1.2)))*AV88*1),2)*BS88),2)) -> 473.34 | CS88: =(ROUND((ROUND(((((EU88*1.25)*1.2))*AV88*1),2)*BS88),2)+ROUND((ROUND(((AE88-(((EU88*1.25)*1.2)))*AV88*1),2)*BS88),2)) -> 159.47 | CT88: =ROUND((ROUND((AF88*AV88*1),2)*BA88),2) -> 152641.44 | CU88: =AG88 -> 0 | CV88: =(AH88*AV88) -> 209.54578 | CW88: =AI88 -> 0 | CX88: =AJ88 -> 0 | CY88: =(ROUND((((S88+ROUND((ROUND(((((EU88*1.25)*1.2))*AV88*1),2)*BS88),2))*AT88)/100),2)+ROUND(((ROUND((ROUND(((AE88-(((EU88*1.25)*1.2)))*AV88*1),2)*BS88),2)*AT88)/100),2)) -> 86690.92 | CZ88: =(ROUND((((S88+ROUND((ROUND(((((EU88*1.25)*1.2))*AV88*1),2)*BS88),2))*AU88)/100),2)+ROUND(((ROUND((ROUND(((AE88-(((EU88*1.25)*1.2)))*AV88*1),2)*BS88),2)*AU88)/100),2)) -> 48515.1 | DB88: 35 | DD88: *1)*1 | DE88: *1,25)*1,2 | DF88: *1,25)*1,2 | DG88: *1,15)*1,2 | DI88: *1,15)*1,2 | DJ88: *1,25)*1,2 | DN88: 0 | DO88: 0 | DP88: 1 | DQ88: 1 | DU88: 1003 | DV88: 100 м | DW88: 100 м | DX88: 100 | EE88: 85635393 | EF88: 30 | EG88: Строительные работы | EH88: 0 | EJ88: 1 | EK88: 21 | EL88: ТСН-2001.3-16. Трубопроводы внутренние | EM88: ТСН-2001.3-16-1 | EO88: Поправка: Гл.6.Прил.2.2.п.2.2.6_06.00.01.07.001 Поправка: Гл.12.Прил.8.п.8. 3_12.00.01.11.001 | EQ88: 131072 | ER88: 1864.54 | ES88: 3.3 | ET88: 21.59 | EU88: 1.77 | EV88: 1839.65 | EW88: 142.31 | EX88: 0 | EY88: 0 | FQ88: 0 | FR88: 0 | FS88: 0 | FX88: 109 | FY88: 61 | GD88: 1 | GF88: -932052613 | GG88: 2 | GH88: 1 | GI88: 2 | GJ88: 0 | GK88: 0 | GL88: =ROUND(IF(AND(BH88=3,BI88=3,FS88<>0),P88,0),2) -> 0 | GM88: =ROUND(O88+X88+Y88,2)+GX88 -> 214710.73 | GN88: =IF(OR(BI88=0,BI88=1),GM88-GX88,0) -> 214710.73 | GO88: =IF(BI88=2,GM88-GX88,0) -> 0 | GP88: =IF(BI88=4,GM88-GX88,0) -> 0 | GR88: 0 | GS88: 3 | GT88: 0 | GV88: =ROUND((GT88),6) -> 0 | GW88: 1 | GX88: =ROUND(HC88*I88,2) -> 0 | HA88: 0 | HB88: 0 | HC88: =GV88*GW88 -> 0 | HS88: 0 | IK88: 0
A89: 18 | B89: 1 | C89: 102 | E89: 12,1 | F89: 1.12-8-74 | G89: Комплект деталей трубопроводов из чугуна с мелкодисперсным графитом с внутренним эпоксидным покрытием, наружным слоем краснокоричневой грунтовки (безраструбные трубы, фасонные части, крепеж), диаметр условного прохода 50 мм | H89: м | I89: =I87*J89 -> 52 | J89: 100 | K89: 100 | O89: =ROUND(CP89,2) -> 69100.72 | P89: =ROUND((ROUND((AC89*AW89*I89),2)*BC89),2) -> 69100.72 | Q89: =(ROUND((ROUND(((ET89)*AV89*I89),2)*BB89),2)+ROUND((ROUND(((AE89-(EU89))*AV89*I89),2)*BS89),2)) -> 0 | R89: =(ROUND((ROUND(((EU89)*AV89*I89),2)*BS89),2)+ROUND((ROUND(((AE89-(EU89))*AV89*I89),2)*BS89),2)) -> 0 | S89: =ROUND((ROUND((AF89*AV89*I89),2)*BA89),2) -> 0 | T89: =ROUND(CU89*I89,2) -> 0 | U89: =CV89*I89 -> 0 | V89: =CW89*I89 -> 0 | W89: =ROUND(CX89*I89,2) -> 0 | X89: =(ROUND((((S89+ROUND((ROUND(((EU89)*AV89*I89),2)*BS89),2))*AT89)/100),2)+ROUND(((ROUND((ROUND(((AE89-(EU89))*AV89*I89),2)*BS89),2)*AT89)/100),2)) -> 0 | Y89: =(ROUND((((S89+ROUND((ROUND(((EU89)*AV89*I89),2)*BS89),2))*AU89)/100),2)+ROUND(((ROUND((ROUND(((AE89-(EU89))*AV89*I89),2)*BS89),2)*AU89)/100),2)) -> 0 | AA89: 86549534 | AB89: =ROUND((AC89+AD89+AF89),6) -> 1328.86 | AC89: =ROUND((ES89),6) -> 1328.86 | AD89: =ROUND((((ET89)-(EU89))+AE89),6) -> 0 | AE89: =ROUND((EU89),6) -> 0 | AF89: =ROUND((EV89),6) -> 0 | AG89: =ROUND((AP89),6) -> 0 | AH89: =(EW89) -> 0 | AI89: =(EX89) -> 0 | AJ89: =(AS89) -> 0 | AK89: 1328.86 | AL89: 1328.86 | AM89: 0 | AN89: 0 | AO89: 0 | AP89: 0 | AQ89: 0 | AR89: 0 | AS89: 0 | AT89: 109 | AU89: 61 | AV89: 1 | AW89: 1 | AZ89: 1 | BA89: 1 | BB89: 1 | BC89: 1 | BH89: 3 | BI89: 1 | BJ89: ТСН-2001.1 Доп. 79, Р. 12, о. 8, поз. 74 | BM89: 21 | BN89: 0 | BP89: 0 | BQ89: 30 | BR89: 0 | BS89: 1 | BT89: 1 | BU89: 1 | BV89: 1 | BW89: 1 | BX89: 1 | BZ89: 109 | CA89: 61 | CE89: 1566 | CF89: 0 | CG89: 0 | CM89: 0 | CN89: Поправка: Гл.6.Прил.2.2.п.2.2.6_06.00.01.07.001_x000D_ Наименование: При выполнении при капитальном ремонте и реконструкции работ, аналогичных технологическим процессам, характерным для нового строительства, и отсутствующих в сборниках на ремонтно-строительные работы ТСН-2001.6_x000D_ Поправка: Гл.12.Прил.8.п.8. 3_12.00.01.11.001_x000D_ Наименование: При наличии напряженных и стесненных условий производства работ (стесненность, сложность складирования и транспортной логистики и т.п.) для объектов, расположенных в пределах круговой магистральной системы улиц "Садовое кольцо" города Москвы | CO89: 0 | CP89: =(P89+Q89+S89) -> 69100.72 | CQ89: =ROUND((ROUND((AC89*AW89*1),2)*BC89),2) -> 1328.86 | CR89: =(ROUND((ROUND(((ET89)*AV89*1),2)*BB89),2)+ROUND((ROUND(((AE89-(EU89))*AV89*1),2)*BS89),2)) -> 0 | CS89: =(ROUND((ROUND(((EU89)*AV89*1),2)*BS89),2)+ROUND((ROUND(((AE89-(EU89))*AV89*1),2)*BS89),2)) -> 0 | CT89: =ROUND((ROUND((AF89*AV89*1),2)*BA89),2) -> 0 | CU89: =AG89 -> 0 | CV89: =(AH89*AV89) -> 0 | CW89: =AI89 -> 0 | CX89: =AJ89 -> 0 | CY89: =(ROUND((((S89+ROUND((ROUND(((EU89)*AV89*1),2)*BS89),2))*AT89)/100),2)+ROUND(((ROUND((ROUND(((AE89-(EU89))*AV89*1),2)*BS89),2)*AT89)/100),2)) -> 0 | CZ89: =(ROUND((((S89+ROUND((ROUND(((EU89)*AV89*1),2)*BS89),2))*AU89)/100),2)+ROUND(((ROUND((ROUND(((AE89-(EU89))*AV89*1),2)*BS89),2)*AU89)/100),2)) -> 0 | DN89: 0 | DO89: 0 | DP89: 1 | DQ89: 1 | DU89: 1003 | DV89: м | DW89: м | DX89: 1 | EE89: 85635393 | EF89: 30 | EG89: Строительные работы | EH89: 0 | EJ89: 1 | EK89: 21 | EL89: ТСН-2001.3-16. Трубопроводы внутренние | EM89: ТСН-2001.3-16-1 | EO89: Поправка: Гл.6.Прил.2.2.п.2.2.6_06.00.01.07.001_x000D_ Поправка: Гл.12.Прил.8.п.8. 3_12.00.01.11.001 | EQ89: 0 | ER89: 1328.86 | ES89: 1328.86 | ET89: 0 | EU89: 0 | EV89: 0 | EW89: 0 | EX89: 0 | FQ89: 0 | FR89: 0 | FS89: 0 | FX89: 109 | FY89: 61 | GD89: 1 | GF89: -1161643105 | GG89: 2 | GH89: 1 | GI89: -2 | GJ89: 0 | GK89: 0 | GL89: =ROUND(IF(AND(BH89=3,BI89=3,FS89<>0),P89,0),2) -> 0 | GM89: =ROUND(O89+X89+Y89,2)+GX89 -> 69100.72 | GN89: =IF(OR(BI89=0,BI89=1),GM89-GX89,0) -> 69100.72 | GO89: =IF(BI89=2,GM89-GX89,0) -> 0 | GP89: =IF(BI89=4,GM89-GX89,0) -> 0 | GR89: 0 | GS89: 3 | GT89: 0 | GV89: =ROUND((GT89),6) -> 0 | GW89: 1 | GX89: =ROUND(HC89*I89,2) -> 0 | HA89: 0 | HB89: 0 | HC89: =GV89*GW89 -> 0 | HM89: *1)*1 | HS89: 0 | IK89: 0
A90: 18 | B90: 1 | C90: 110 | E90: 12,1 | F90: 1.12-8-74 | G90: Комплект деталей трубопроводов из чугуна с мелкодисперсным графитом с внутренним эпоксидным покрытием, наружным слоем краснокоричневой грунтовки (безраструбные трубы, фасонные части, крепеж), диаметр условного прохода 50 мм | H90: м | I90: =I88*J90 -> 52 | J90: 100 | K90: 100 | O90: =ROUND(CP90,2) -> 55971.58 | P90: =ROUND((ROUND((AC90*AW90*I90),2)*BC90),2) -> 55971.58 | Q90: =(ROUND((ROUND(((ET90)*AV90*I90),2)*BB90),2)+ROUND((ROUND(((AE90-(EU90))*AV90*I90),2)*BS90),2)) -> 0 | R90: =(ROUND((ROUND(((EU90)*AV90*I90),2)*BS90),2)+ROUND((ROUND(((AE90-(EU90))*AV90*I90),2)*BS90),2)) -> 0 | S90: =ROUND((ROUND((AF90*AV90*I90),2)*BA90),2) -> 0 | T90: =ROUND(CU90*I90,2) -> 0 | U90: =CV90*I90 -> 0 | V90: =CW90*I90 -> 0 | W90: =ROUND(CX90*I90,2) -> 0 | X90: =(ROUND((((S90+ROUND((ROUND(((EU90)*AV90*I90),2)*BS90),2))*AT90)/100),2)+ROUND(((ROUND((ROUND(((AE90-(EU90))*AV90*I90),2)*BS90),2)*AT90)/100),2)) -> 0 | Y90: =(ROUND((((S90+ROUND((ROUND(((EU90)*AV90*I90),2)*BS90),2))*AU90)/100),2)+ROUND(((ROUND((ROUND(((AE90-(EU90))*AV90*I90),2)*BS90),2)*AU90)/100),2)) -> 0 | AA90: 86549536 | AB90: =ROUND((AC90+AD90+AF90),6) -> 1328.86 | AC90: =ROUND((ES90),6) -> 1328.86 | AD90: =ROUND((((ET90)-(EU90))+AE90),6) -> 0 | AE90: =ROUND((EU90),6) -> 0 | AF90: =ROUND((EV90),6) -> 0 | AG90: =ROUND((AP90),6) -> 0 | AH90: =(EW90) -> 0 | AI90: =(EX90) -> 0 | AJ90: =(AS90) -> 0 | AK90: 1328.86 | AL90: 1328.86 | AM90: 0 | AN90: 0 | AO90: 0 | AP90: 0 | AQ90: 0 | AR90: 0 | AS90: 0 | AT90: 109 | AU90: 61 | AV90: 1 | AW90: 1 | AZ90: 1 | BA90: 1 | BB90: 1 | BC90: 0.81 | BH90: 3 | BI90: 1 | BJ90: ТСН-2001.1 Доп. 79, Р. 12, о. 8, поз. 74 | BM90: 21 | BN90: 0 | BO90: 1.12-8-74 | BP90: 1 | BQ90: 30 | BR90: 0 | BS90: 1 | BT90: 1 | BU90: 1 | BV90: 1 | BW90: 1 | BX90: 1 | BZ90: 109 | CA90: 61 | CE90: 1566 | CF90: 0 | CG90: 0 | CM90: 0 | CN90: Поправка: Гл.6.Прил.2.2.п.2.2.6_06.00.01.07.001_x000D_ Наименование: При выполнении при капитальном ремонте и реконструкции работ, аналогичных технологическим процессам, характерным для нового строительства, и отсутствующих в сборниках на ремонтно-строительные работы ТСН-2001.6_x000D_ Поправка: Гл.12.Прил.8.п.8. 3_12.00.01.11.001_x000D_ Наименование: При наличии напряженных и стесненных условий производства работ (стесненность, сложность складирования и транспортной логистики и т.п.) для объектов, расположенных в пределах круговой магистральной системы улиц "Садовое кольцо" города Москвы | CO90: 0 | CP90: =(P90+Q90+S90) -> 55971.58 | CQ90: =ROUND((ROUND((AC90*AW90*1),2)*BC90),2) -> 1076.38 | CR90: =(ROUND((ROUND(((ET90)*AV90*1),2)*BB90),2)+ROUND((ROUND(((AE90-(EU90))*AV90*1),2)*BS90),2)) -> 0 | CS90: =(ROUND((ROUND(((EU90)*AV90*1),2)*BS90),2)+ROUND((ROUND(((AE90-(EU90))*AV90*1),2)*BS90),2)) -> 0 | CT90: =ROUND((ROUND((AF90*AV90*1),2)*BA90),2) -> 0 | CU90: =AG90 -> 0 | CV90: =(AH90*AV90) -> 0 | CW90: =AI90 -> 0 | CX90: =AJ90 -> 0 | CY90: =(ROUND((((S90+ROUND((ROUND(((EU90)*AV90*1),2)*BS90),2))*AT90)/100),2)+ROUND(((ROUND((ROUND(((AE90-(EU90))*AV90*1),2)*BS90),2)*AT90)/100),2)) -> 0 | CZ90: =(ROUND((((S90+ROUND((ROUND(((EU90)*AV90*1),2)*BS90),2))*AU90)/100),2)+ROUND(((ROUND((ROUND(((AE90-(EU90))*AV90*1),2)*BS90),2)*AU90)/100),2)) -> 0 | DN90: 0 | DO90: 0 | DP90: 1 | DQ90: 1 | DU90: 1003 | DV90: м | DW90: м | DX90: 1 | EE90: 85635393 | EF90: 30 | EG90: Строительные работы | EH90: 0 | EJ90: 1 | EK90: 21 | EL90: ТСН-2001.3-16. Трубопроводы внутренние | EM90: ТСН-2001.3-16-1 | EO90: Поправка: Гл.6.Прил.2.2.п.2.2.6_06.00.01.07.001_x000D_ Поправка: Гл.12.Прил.8.п.8. 3_12.00.01.11.001 | EQ90: 0 | ER90: 1328.86 | ES90: 1328.86 | ET90: 0 | EU90: 0 | EV90: 0 | EW90: 0 | EX90: 0 | FQ90: 0 | FR90: 0 | FS90: 0 | FX90: 109 | FY90: 61 | GD90: 1 | GF90: -1161643105 | GG90: 2 | GH90: 1 | GI90: 2 | GJ90: 0 | GK90: 0 | GL90: =ROUND(IF(AND(BH90=3,BI90=3,FS90<>0),P90,0),2) -> 0 | GM90: =ROUND(O90+X90+Y90,2)+GX90 -> 55971.58 | GN90: =IF(OR(BI90=0,BI90=1),GM90-GX90,0) -> 55971.58 | GO90: =IF(BI90=2,GM90-GX90,0) -> 0 | GP90: =IF(BI90=4,GM90-GX90,0) -> 0 | GR90: 0 | GS90: 3 | GT90: 0 | GV90: =ROUND((GT90),6) -> 0 | GW90: 1 | GX90: =ROUND(HC90*I90,2) -> 0 | HA90: 0 | HB90: 0 | HC90: =GV90*GW90 -> 0 | HM90: *1)*1 | HS90: 0 | IK90: 0
A91: 17 | B91: 1 | C91: =ROW(SmtRes!A113) -> 113 | D91: =ROW(EtalonRes!A134) -> 134 | E91: 13 | F91: 3.16-33-1 | G91: Установка противопожарных муфт на канализационных стояках из полипропиленовых труб в междуэтажных перекрытиях, муфт обжимных | H91: 100 шт. | I91: =ROUND((8+6)/100,9) -> 0.14 | J91: 0 | K91: =ROUND((8+6)/100,9) -> 0.14 | O91: =ROUND(CP91,2) -> 37.96 | P91: =ROUND((ROUND((AC91*AW91*I91),2)*BC91),2) -> 0 | Q91: =(ROUND((ROUND(((((ET91*1.25)*1.2))*AV91*I91),2)*BB91),2)+ROUND((ROUND(((AE91-(((EU91*1.25)*1.2)))*AV91*I91),2)*BS91),2)) -> 0 | R91: =(ROUND((ROUND(((((EU91*1.25)*1.2))*AV91*I91),2)*BS91),2)+ROUND((ROUND(((AE91-(((EU91*1.25)*1.2)))*AV91*I91),2)*BS91),2)) -> 0 | S91: =ROUND((ROUND((AF91*AV91*I91),2)*BA91),2) -> 37.96 | T91: =ROUND(CU91*I91,2) -> 0 | U91: =CV91*I91 -> 3.0158926 | V91: =CW91*I91 -> 0 | W91: =ROUND(CX91*I91,2) -> 0 | X91: =(ROUND((((S91+ROUND((ROUND(((((EU91*1.25)*1.2))*AV91*I91),2)*BS91),2))*AT91)/100),2)+ROUND(((ROUND((ROUND(((AE91-(((EU91*1.25)*1.2)))*AV91*I91),2)*BS91),2)*AT91)/100),2)) -> 41.38 | Y91: =(ROUND((((S91+ROUND((ROUND(((((EU91*1.25)*1.2))*AV91*I91),2)*BS91),2))*AU91)/100),2)+ROUND(((ROUND((ROUND(((AE91-(((EU91*1.25)*1.2)))*AV91*I91),2)*BS91),2)*AU91)/100),2)) -> 23.16 | AA91: 86549534 | AB91: =ROUND((AC91+AD91+AF91),6) -> 254.0994 | AC91: =ROUND((((ES91*1)*1)),6) -> 0 | AD91: =ROUND((((((ET91*1.25)*1.2))-(((EU91*1.25)*1.2)))+AE91),6) -> 0 | AE91: =ROUND((((EU91*1.25)*1.2)),6) -> 0 | AF91: =ROUND((((EV91*1.15)*1.2)),6) -> 254.0994 | AG91: =ROUND((AP91),6) -> 0 | AH91: =(((EW91*1.15)*1.2)) -> 20.1894 | AI91: =(((EX91*1.25)*1.2)) -> 0 | AJ91: =(AS91) -> 0 | AK91: 184.13 | AL91: 0 | AM91: 0 | AN91: 0 | AO91: 184.13 | AP91: 0 | AQ91: 14.63 | AR91: 0 | AS91: 0 | AT91: 109 | AU91: 61 | AV91: 1.067 | AW91: 1 | AZ91: 1 | BA91: 1 | BB91: 1 | BC91: 1 | BH91: 0 | BI91: 1 | BJ91: ТСН-2001.3. Доп. 1-42. Сб. 16, т. 33, поз. 1 | BM91: 21 | BN91: 0 | BO91: 3.16-33-1 | BP91: 1 | BQ91: 30 | BR91: 0 | BS91: 1 | BT91: 1 | BU91: 1 | BV91: 1 | BW91: 1 | BX91: 1 | BZ91: 109 | CA91: 61 | CE91: 1566 | CF91: 0 | CG91: 0 | CM91: 0 | CN91: Поправка: Гл.6.Прил.2.2.п.2.2.6_06.00.01.07.001 Наименование: При выполнении при капитальном ремонте и реконструкции работ, аналогичных технологическим процессам, характерным для нового строительства, и отсутствующих в сборниках на ремонтно-строительные работы ТСН-2001.6 Поправка: Гл.12.Прил.8.п.8. 3_12.00.01.11.001 Наименование: При наличии напряженных и стесненных условий производства работ (стесненность, сложность складирования и транспортной логистики и т.п.) для объектов, расположенных в пределах круговой магистральной системы улиц "Садовое кольцо" города Москвы | CO91: 0 | CP91: =(P91+Q91+S91) -> 37.96 | CQ91: =ROUND((ROUND((AC91*AW91*1),2)*BC91),2) -> 0 | CR91: =(ROUND((ROUND(((((ET91*1.25)*1.2))*AV91*1),2)*BB91),2)+ROUND((ROUND(((AE91-(((EU91*1.25)*1.2)))*AV91*1),2)*BS91),2)) -> 0 | CS91: =(ROUND((ROUND(((((EU91*1.25)*1.2))*AV91*1),2)*BS91),2)+ROUND((ROUND(((AE91-(((EU91*1.25)*1.2)))*AV91*1),2)*BS91),2)) -> 0 | CT91: =ROUND((ROUND((AF91*AV91*1),2)*BA91),2) -> 271.12 | CU91: =AG91 -> 0 | CV91: =(AH91*AV91) -> 21.54209 | CW91: =AI91 -> 0 | CX91: =AJ91 -> 0 | CY91: =(ROUND((((S91+ROUND((ROUND(((((EU91*1.25)*1.2))*AV91*1),2)*BS91),2))*AT91)/100),2)+ROUND(((ROUND((ROUND(((AE91-(((EU91*1.25)*1.2)))*AV91*1),2)*BS91),2)*AT91)/100),2)) -> 41.38 | CZ91: =(ROUND((((S91+ROUND((ROUND(((((EU91*1.25)*1.2))*AV91*1),2)*BS91),2))*AU91)/100),2)+ROUND(((ROUND((ROUND(((AE91-(((EU91*1.25)*1.2)))*AV91*1),2)*BS91),2)*AU91)/100),2)) -> 23.16 | DB91: 37 | DD91: *1)*1 | DE91: *1,25)*1,2 | DF91: *1,25)*1,2 | DG91: *1,15)*1,2 | DI91: *1,15)*1,2 | DJ91: *1,25)*1,2 | DN91: 0 | DO91: 0 | DP91: 1 | DQ91: 1 | DU91: 1010 | DV91: 100 шт. | DW91: 100 шт. | DX91: 100 | EE91: 85635393 | EF91: 30 | EG91: Строительные работы | EH91: 0 | EJ91: 1 | EK91: 21 | EL91: ТСН-2001.3-16. Трубопроводы внутренние | EM91: ТСН-2001.3-16-1 | EO91: Поправка: Гл.6.Прил.2.2.п.2.2.6_06.00.01.07.001 Поправка: Гл.12.Прил.8.п.8. 3_12.00.01.11.001 | EQ91: 131072 | ER91: 184.13 | ES91: 0 | ET91: 0 | EU91: 0 | EV91: 184.13 | EW91: 14.63 | EX91: 0 | EY91: 0 | FQ91: 0 | FR91: 0 | FS91: 0 | FX91: 109 | FY91: 61 | GD91: 1 | GF91: 885968331 | GG91: 2 | GH91: 1 | GI91: 2 | GJ91: 0 | GK91: 0 | GL91: =ROUND(IF(AND(BH91=3,BI91=3,FS91<>0),P91,0),2) -> 0 | GM91: =ROUND(O91+X91+Y91,2)+GX91 -> 102.5 | GN91: =IF(OR(BI91=0,BI91=1),GM91-GX91,0) -> 102.5 | GO91: =IF(BI91=2,GM91-GX91,0) -> 0 | GP91: =IF(BI91=4,GM91-GX91,0) -> 0 | GR91: 0 | GS91: 3 | GT91: 0 | GV91: =ROUND((GT91),6) -> 0 | GW91: 1 | GX91: =ROUND(HC91*I91,2) -> 0 | HA91: 0 | HB91: 0 | HC91: =GV91*GW91 -> 0 | HS91: 0 | IK91: 0
A92: 17 | B92: 1 | C92: =ROW(SmtRes!A116) -> 116 | D92: =ROW(EtalonRes!A136) -> 136 | E92: 13 | F92: 3.16-33-1 | G92: Установка противопожарных муфт на канализационных стояках из полипропиленовых труб в междуэтажных перекрытиях, муфт обжимных | H92: 100 шт. | I92: =ROUND((8+6)/100,9) -> 0.14 | J92: 0 | K92: =ROUND((8+6)/100,9) -> 0.14 | O92: =ROUND(CP92,2) -> 2139.05 | P92: =ROUND((ROUND((AC92*AW92*I92),2)*BC92),2) -> 0 | Q92: =(ROUND((ROUND(((((ET92*1.25)*1.2))*AV92*I92),2)*BB92),2)+ROUND((ROUND(((AE92-(((EU92*1.25)*1.2)))*AV92*I92),2)*BS92),2)) -> 0 | R92: =(ROUND((ROUND(((((EU92*1.25)*1.2))*AV92*I92),2)*BS92),2)+ROUND((ROUND(((AE92-(((EU92*1.25)*1.2)))*AV92*I92),2)*BS92),2)) -> 0 | S92: =ROUND((ROUND((AF92*AV92*I92),2)*BA92),2) -> 2139.05 | T92: =ROUND(CU92*I92,2) -> 0 | U92: =CV92*I92 -> 3.0158926 | V92: =CW92*I92 -> 0 | W92: =ROUND(CX92*I92,2) -> 0 | X92: =(ROUND((((S92+ROUND((ROUND(((((EU92*1.25)*1.2))*AV92*I92),2)*BS92),2))*AT92)/100),2)+ROUND(((ROUND((ROUND(((AE92-(((EU92*1.25)*1.2)))*AV92*I92),2)*BS92),2)*AT92)/100),2)) -> 2331.56 | Y92: =(ROUND((((S92+ROUND((ROUND(((((EU92*1.25)*1.2))*AV92*I92),2)*BS92),2))*AU92)/100),2)+ROUND(((ROUND((ROUND(((AE92-(((EU92*1.25)*1.2)))*AV92*I92),2)*BS92),2)*AU92)/100),2)) -> 1304.82 | AA92: 86549536 | AB92: =ROUND((AC92+AD92+AF92),6) -> 254.0994 | AC92: =ROUND((((ES92*1)*1)),6) -> 0 | AD92: =ROUND((((((ET92*1.25)*1.2))-(((EU92*1.25)*1.2)))+AE92),6) -> 0 | AE92: =ROUND((((EU92*1.25)*1.2)),6) -> 0 | AF92: =ROUND((((EV92*1.15)*1.2)),6) -> 254.0994 | AG92: =ROUND((AP92),6) -> 0 | AH92: =(((EW92*1.15)*1.2)) -> 20.1894 | AI92: =(((EX92*1.25)*1.2)) -> 0 | AJ92: =(AS92) -> 0 | AK92: 184.13 | AL92: 0 | AM92: 0 | AN92: 0 | AO92: 184.13 | AP92: 0 | AQ92: 14.63 | AR92: 0 | AS92: 0 | AT92: 109 | AU92: 61 | AV92: 1.067 | AW92: 1 | AZ92: 1 | BA92: 56.35 | BB92: 1 | BC92: 1 | BH92: 0 | BI92: 1 | BJ92: ТСН-2001.3. Доп. 1-42. Сб. 16, т. 33, поз. 1 | BM92: 21 | BN92: 0 | BO92: 3.16-33-1 | BP92: 1 | BQ92: 30 | BR92: 0 | BS92: 56.35 | BT92: 1 | BU92: 1 | BV92: 1 | BW92: 1 | BX92: 1 | BZ92: 109 | CA92: 61 | CE92: 1566 | CF92: 0 | CG92: 0 | CM92: 0 | CN92: Поправка: Гл.6.Прил.2.2.п.2.2.6_06.00.01.07.001 Наименование: При выполнении при капитальном ремонте и реконструкции работ, аналогичных технологическим процессам, характерным для нового строительства, и отсутствующих в сборниках на ремонтно-строительные работы ТСН-2001.6 Поправка: Гл.12.Прил.8.п.8. 3_12.00.01.11.001 Наименование: При наличии напряженных и стесненных условий производства работ (стесненность, сложность складирования и транспортной логистики и т.п.) для объектов, расположенных в пределах круговой магистральной системы улиц "Садовое кольцо" города Москвы | CO92: 0 | CP92: =(P92+Q92+S92) -> 2139.05 | CQ92: =ROUND((ROUND((AC92*AW92*1),2)*BC92),2) -> 0 | CR92: =(ROUND((ROUND(((((ET92*1.25)*1.2))*AV92*1),2)*BB92),2)+ROUND((ROUND(((AE92-(((EU92*1.25)*1.2)))*AV92*1),2)*BS92),2)) -> 0 | CS92: =(ROUND((ROUND(((((EU92*1.25)*1.2))*AV92*1),2)*BS92),2)+ROUND((ROUND(((AE92-(((EU92*1.25)*1.2)))*AV92*1),2)*BS92),2)) -> 0 | CT92: =ROUND((ROUND((AF92*AV92*1),2)*BA92),2) -> 15277.61 | CU92: =AG92 -> 0 | CV92: =(AH92*AV92) -> 21.54209 | CW92: =AI92 -> 0 | CX92: =AJ92 -> 0 | CY92: =(ROUND((((S92+ROUND((ROUND(((((EU92*1.25)*1.2))*AV92*1),2)*BS92),2))*AT92)/100),2)+ROUND(((ROUND((ROUND(((AE92-(((EU92*1.25)*1.2)))*AV92*1),2)*BS92),2)*AT92)/100),2)) -> 2331.56 | CZ92: =(ROUND((((S92+ROUND((ROUND(((((EU92*1.25)*1.2))*AV92*1),2)*BS92),2))*AU92)/100),2)+ROUND(((ROUND((ROUND(((AE92-(((EU92*1.25)*1.2)))*AV92*1),2)*BS92),2)*AU92)/100),2)) -> 1304.82 | DB92: 39 | DD92: *1)*1 | DE92: *1,25)*1,2 | DF92: *1,25)*1,2 | DG92: *1,15)*1,2 | DI92: *1,15)*1,2 | DJ92: *1,25)*1,2 | DN92: 0 | DO92: 0 | DP92: 1 | DQ92: 1 | DU92: 1010 | DV92: 100 шт. | DW92: 100 шт. | DX92: 100 | EE92: 85635393 | EF92: 30 | EG92: Строительные работы | EH92: 0 | EJ92: 1 | EK92: 21 | EL92: ТСН-2001.3-16. Трубопроводы внутренние | EM92: ТСН-2001.3-16-1 | EO92: Поправка: Гл.6.Прил.2.2.п.2.2.6_06.00.01.07.001 Поправка: Гл.12.Прил.8.п.8. 3_12.00.01.11.001 | EQ92: 131072 | ER92: 184.13 | ES92: 0 | ET92: 0 | EU92: 0 | EV92: 184.13 | EW92: 14.63 | EX92: 0 | EY92: 0 | FQ92: 0 | FR92: 0 | FS92: 0 | FX92: 109 | FY92: 61 | GD92: 1 | GF92: 885968331 | GG92: 2 | GH92: 1 | GI92: 2 | GJ92: 0 | GK92: 0 | GL92: =ROUND(IF(AND(BH92=3,BI92=3,FS92<>0),P92,0),2) -> 0 | GM92: =ROUND(O92+X92+Y92,2)+GX92 -> 5775.43 | GN92: =IF(OR(BI92=0,BI92=1),GM92-GX92,0) -> 5775.43 | GO92: =IF(BI92=2,GM92-GX92,0) -> 0 | GP92: =IF(BI92=4,GM92-GX92,0) -> 0 | GR92: 0 | GS92: 3 | GT92: 0 | GV92: =ROUND((GT92),6) -> 0 | GW92: 1 | GX92: =ROUND(HC92*I92,2) -> 0 | HA92: 0 | HB92: 0 | HC92: =GV92*GW92 -> 0 | HS92: 0 | IK92: 0
A93: 18 | B93: 1 | C93: 112 | E93: 13,1 | F93: 1.12-5-456 | G93: Муфта противопожарная из нержавеющей стали, с вкладышем из терморасширяющейся резины, для трубы диаметром 110 мм | H93: шт. | I93: =I91*J93 -> 8 | J93: 57.142857 | K93: 57.142857 | O93: =ROUND(CP93,2) -> 2121.92 | P93: =ROUND((ROUND((AC93*AW93*I93),2)*BC93),2) -> 2121.92 | Q93: =(ROUND((ROUND(((ET93)*AV93*I93),2)*BB93),2)+ROUND((ROUND(((AE93-(EU93))*AV93*I93),2)*BS93),2)) -> 0 | R93: =(ROUND((ROUND(((EU93)*AV93*I93),2)*BS93),2)+ROUND((ROUND(((AE93-(EU93))*AV93*I93),2)*BS93),2)) -> 0 | S93: =ROUND((ROUND((AF93*AV93*I93),2)*BA93),2) -> 0 | T93: =ROUND(CU93*I93,2) -> 0 | U93: =CV93*I93 -> 0 | V93: =CW93*I93 -> 0 | W93: =ROUND(CX93*I93,2) -> 0 | X93: =(ROUND((((S93+ROUND((ROUND(((EU93)*AV93*I93),2)*BS93),2))*AT93)/100),2)+ROUND(((ROUND((ROUND(((AE93-(EU93))*AV93*I93),2)*BS93),2)*AT93)/100),2)) -> 0 | Y93: =(ROUND((((S93+ROUND((ROUND(((EU93)*AV93*I93),2)*BS93),2))*AU93)/100),2)+ROUND(((ROUND((ROUND(((AE93-(EU93))*AV93*I93),2)*BS93),2)*AU93)/100),2)) -> 0 | AA93: 86549534 | AB93: =ROUND((AC93+AD93+AF93),6) -> 265.24 | AC93: =ROUND((ES93),6) -> 265.24 | AD93: =ROUND((((ET93)-(EU93))+AE93),6) -> 0 | AE93: =ROUND((EU93),6) -> 0 | AF93: =ROUND((EV93),6) -> 0 | AG93: =ROUND((AP93),6) -> 0 | AH93: =(EW93) -> 0 | AI93: =(EX93) -> 0 | AJ93: =(AS93) -> 0 | AK93: 265.24 | AL93: 265.24 | AM93: 0 | AN93: 0 | AO93: 0 | AP93: 0 | AQ93: 0 | AR93: 0 | AS93: 0 | AT93: 109 | AU93: 61 | AV93: 1 | AW93: 1 | AZ93: 1 | BA93: 1 | BB93: 1 | BC93: 1 | BH93: 3 | BI93: 1 | BJ93: ТСН-2001.1 Доп. 73, Р. 12, о. 5, поз. 456 | BM93: 21 | BN93: 0 | BP93: 0 | BQ93: 30 | BR93: 0 | BS93: 1 | BT93: 1 | BU93: 1 | BV93: 1 | BW93: 1 | BX93: 1 | BZ93: 109 | CA93: 61 | CE93: 1566 | CF93: 0 | CG93: 0 | CM93: 0 | CN93: Поправка: Гл.6.Прил.2.2.п.2.2.6_06.00.01.07.001_x000D_ Наименование: При выполнении при капитальном ремонте и реконструкции работ, аналогичных технологическим процессам, характерным для нового строительства, и отсутствующих в сборниках на ремонтно-строительные работы ТСН-2001.6_x000D_ Поправка: Гл.12.Прил.8.п.8. 3_12.00.01.11.001_x000D_ Наименование: При наличии напряженных и стесненных условий производства работ (стесненность, сложность складирования и транспортной логистики и т.п.) для объектов, расположенных в пределах круговой магистральной системы улиц "Садовое кольцо" города Москвы | CO93: 0 | CP93: =(P93+Q93+S93) -> 2121.92 | CQ93: =ROUND((ROUND((AC93*AW93*1),2)*BC93),2) -> 265.24 | CR93: =(ROUND((ROUND(((ET93)*AV93*1),2)*BB93),2)+ROUND((ROUND(((AE93-(EU93))*AV93*1),2)*BS93),2)) -> 0 | CS93: =(ROUND((ROUND(((EU93)*AV93*1),2)*BS93),2)+ROUND((ROUND(((AE93-(EU93))*AV93*1),2)*BS93),2)) -> 0 | CT93: =ROUND((ROUND((AF93*AV93*1),2)*BA93),2) -> 0 | CU93: =AG93 -> 0 | CV93: =(AH93*AV93) -> 0 | CW93: =AI93 -> 0 | CX93: =AJ93 -> 0 | CY93: =(ROUND((((S93+ROUND((ROUND(((EU93)*AV93*1),2)*BS93),2))*AT93)/100),2)+ROUND(((ROUND((ROUND(((AE93-(EU93))*AV93*1),2)*BS93),2)*AT93)/100),2)) -> 0 | CZ93: =(ROUND((((S93+ROUND((ROUND(((EU93)*AV93*1),2)*BS93),2))*AU93)/100),2)+ROUND(((ROUND((ROUND(((AE93-(EU93))*AV93*1),2)*BS93),2)*AU93)/100),2)) -> 0 | DN93: 0 | DO93: 0 | DP93: 1 | DQ93: 1 | DU93: 1010 | DV93: шт. | DW93: шт. | DX93: 1 | EE93: 85635393 | EF93: 30 | EG93: Строительные работы | EH93: 0 | EJ93: 1 | EK93: 21 | EL93: ТСН-2001.3-16. Трубопроводы внутренние | EM93: ТСН-2001.3-16-1 | EO93: Поправка: Гл.6.Прил.2.2.п.2.2.6_06.00.01.07.001_x000D_ Поправка: Гл.12.Прил.8.п.8. 3_12.00.01.11.001 | EQ93: 0 | ER93: 265.24 | ES93: 265.24 | ET93: 0 | EU93: 0 | EV93: 0 | EW93: 0 | EX93: 0 | FQ93: 0 | FR93: 0 | FS93: 0 | FX93: 109 | FY93: 61 | GD93: 1 | GF93: 944493166 | GG93: 2 | GH93: 1 | GI93: -2 | GJ93: 0 | GK93: 0 | GL93: =ROUND(IF(AND(BH93=3,BI93=3,FS93<>0),P93,0),2) -> 0 | GM93: =ROUND(O93+X93+Y93,2)+GX93 -> 2121.92 | GN93: =IF(OR(BI93=0,BI93=1),GM93-GX93,0) -> 2121.92 | GO93: =IF(BI93=2,GM93-GX93,0) -> 0 | GP93: =IF(BI93=4,GM93-GX93,0) -> 0 | GR93: 0 | GS93: 3 | GT93: 0 | GV93: =ROUND((GT93),6) -> 0 | GW93: 1 | GX93: =ROUND(HC93*I93,2) -> 0 | HA93: 0 | HB93: 0 | HC93: =GV93*GW93 -> 0 | HM93: *1)*1 | HS93: 0 | IK93: 0
A94: 18 | B94: 1 | C94: 115 | E94: 13,1 | F94: 1.12-5-456 | G94: Муфта противопожарная из нержавеющей стали, с вкладышем из терморасширяющейся резины, для трубы диаметром 110 мм | H94: шт. | I94: =I92*J94 -> 8 | J94: 57.142857 | K94: 57.142857 | O94: =ROUND(CP94,2) -> 1761.19 | P94: =ROUND((ROUND((AC94*AW94*I94),2)*BC94),2) -> 1761.19 | Q94: =(ROUND((ROUND(((ET94)*AV94*I94),2)*BB94),2)+ROUND((ROUND(((AE94-(EU94))*AV94*I94),2)*BS94),2)) -> 0 | R94: =(ROUND((ROUND(((EU94)*AV94*I94),2)*BS94),2)+ROUND((ROUND(((AE94-(EU94))*AV94*I94),2)*BS94),2)) -> 0 | S94: =ROUND((ROUND((AF94*AV94*I94),2)*BA94),2) -> 0 | T94: =ROUND(CU94*I94,2) -> 0 | U94: =CV94*I94 -> 0 | V94: =CW94*I94 -> 0 | W94: =ROUND(CX94*I94,2) -> 0 | X94: =(ROUND((((S94+ROUND((ROUND(((EU94)*AV94*I94),2)*BS94),2))*AT94)/100),2)+ROUND(((ROUND((ROUND(((AE94-(EU94))*AV94*I94),2)*BS94),2)*AT94)/100),2)) -> 0 | Y94: =(ROUND((((S94+ROUND((ROUND(((EU94)*AV94*I94),2)*BS94),2))*AU94)/100),2)+ROUND(((ROUND((ROUND(((AE94-(EU94))*AV94*I94),2)*BS94),2)*AU94)/100),2)) -> 0 | AA94: 86549536 | AB94: =ROUND((AC94+AD94+AF94),6) -> 265.24 | AC94: =ROUND((ES94),6) -> 265.24 | AD94: =ROUND((((ET94)-(EU94))+AE94),6) -> 0 | AE94: =ROUND((EU94),6) -> 0 | AF94: =ROUND((EV94),6) -> 0 | AG94: =ROUND((AP94),6) -> 0 | AH94: =(EW94) -> 0 | AI94: =(EX94) -> 0 | AJ94: =(AS94) -> 0 | AK94: 265.24 | AL94: 265.24 | AM94: 0 | AN94: 0 | AO94: 0 | AP94: 0 | AQ94: 0 | AR94: 0 | AS94: 0 | AT94: 109 | AU94: 61 | AV94: 1 | AW94: 1 | AZ94: 1 | BA94: 1 | BB94: 1 | BC94: 0.83 | BH94: 3 | BI94: 1 | BJ94: ТСН-2001.1 Доп. 73, Р. 12, о. 5, поз. 456 | BM94: 21 | BN94: 0 | BO94: 1.12-5-456 | BP94: 1 | BQ94: 30 | BR94: 0 | BS94: 1 | BT94: 1 | BU94: 1 | BV94: 1 | BW94: 1 | BX94: 1 | BZ94: 109 | CA94: 61 | CE94: 1566 | CF94: 0 | CG94: 0 | CM94: 0 | CN94: Поправка: Гл.6.Прил.2.2.п.2.2.6_06.00.01.07.001_x000D_ Наименование: При выполнении при капитальном ремонте и реконструкции работ, аналогичных технологическим процессам, характерным для нового строительства, и отсутствующих в сборниках на ремонтно-строительные работы ТСН-2001.6_x000D_ Поправка: Гл.12.Прил.8.п.8. 3_12.00.01.11.001_x000D_ Наименование: При наличии напряженных и стесненных условий производства работ (стесненность, сложность складирования и транспортной логистики и т.п.) для объектов, расположенных в пределах круговой магистральной системы улиц "Садовое кольцо" города Москвы | CO94: 0 | CP94: =(P94+Q94+S94) -> 1761.19 | CQ94: =ROUND((ROUND((AC94*AW94*1),2)*BC94),2) -> 220.15 | CR94: =(ROUND((ROUND(((ET94)*AV94*1),2)*BB94),2)+ROUND((ROUND(((AE94-(EU94))*AV94*1),2)*BS94),2)) -> 0 | CS94: =(ROUND((ROUND(((EU94)*AV94*1),2)*BS94),2)+ROUND((ROUND(((AE94-(EU94))*AV94*1),2)*BS94),2)) -> 0 | CT94: =ROUND((ROUND((AF94*AV94*1),2)*BA94),2) -> 0 | CU94: =AG94 -> 0 | CV94: =(AH94*AV94) -> 0 | CW94: =AI94 -> 0 | CX94: =AJ94 -> 0 | CY94: =(ROUND((((S94+ROUND((ROUND(((EU94)*AV94*1),2)*BS94),2))*AT94)/100),2)+ROUND(((ROUND((ROUND(((AE94-(EU94))*AV94*1),2)*BS94),2)*AT94)/100),2)) -> 0 | CZ94: =(ROUND((((S94+ROUND((ROUND(((EU94)*AV94*1),2)*BS94),2))*AU94)/100),2)+ROUND(((ROUND((ROUND(((AE94-(EU94))*AV94*1),2)*BS94),2)*AU94)/100),2)) -> 0 | DN94: 0 | DO94: 0 | DP94: 1 | DQ94: 1 | DU94: 1010 | DV94: шт. | DW94: шт. | DX94: 1 | EE94: 85635393 | EF94: 30 | EG94: Строительные работы | EH94: 0 | EJ94: 1 | EK94: 21 | EL94: ТСН-2001.3-16. Трубопроводы внутренние | EM94: ТСН-2001.3-16-1 | EO94: Поправка: Гл.6.Прил.2.2.п.2.2.6_06.00.01.07.001_x000D_ Поправка: Гл.12.Прил.8.п.8. 3_12.00.01.11.001 | EQ94: 0 | ER94: 265.24 | ES94: 265.24 | ET94: 0 | EU94: 0 | EV94: 0 | EW94: 0 | EX94: 0 | FQ94: 0 | FR94: 0 | FS94: 0 | FX94: 109 | FY94: 61 | GD94: 1 | GF94: 944493166 | GG94: 2 | GH94: 1 | GI94: 2 | GJ94: 0 | GK94: 0 | GL94: =ROUND(IF(AND(BH94=3,BI94=3,FS94<>0),P94,0),2) -> 0 | GM94: =ROUND(O94+X94+Y94,2)+GX94 -> 1761.19 | GN94: =IF(OR(BI94=0,BI94=1),GM94-GX94,0) -> 1761.19 | GO94: =IF(BI94=2,GM94-GX94,0) -> 0 | GP94: =IF(BI94=4,GM94-GX94,0) -> 0 | GR94: 0 | GS94: 3 | GT94: 0 | GV94: =ROUND((GT94),6) -> 0 | GW94: 1 | GX94: =ROUND(HC94*I94,2) -> 0 | HA94: 0 | HB94: 0 | HC94: =GV94*GW94 -> 0 | HM94: *1)*1 | HS94: 0 | IK94: 0
A95: 18 | B95: 1 | C95: 113 | E95: 13,2 | F95: 1.12-5-542 | G95: Муфта противопожарная из нержавеющей стали, с вкладышем из терморасширяющейся резины, для трубы диаметром 50 мм | H95: шт. | I95: =I91*J95 -> 6 | J95: 42.857143 | K95: 42.857143 | O95: =ROUND(CP95,2) -> 1089.54 | P95: =ROUND((ROUND((AC95*AW95*I95),2)*BC95),2) -> 1089.54 | Q95: =(ROUND((ROUND(((ET95)*AV95*I95),2)*BB95),2)+ROUND((ROUND(((AE95-(EU95))*AV95*I95),2)*BS95),2)) -> 0 | R95: =(ROUND((ROUND(((EU95)*AV95*I95),2)*BS95),2)+ROUND((ROUND(((AE95-(EU95))*AV95*I95),2)*BS95),2)) -> 0 | S95: =ROUND((ROUND((AF95*AV95*I95),2)*BA95),2) -> 0 | T95: =ROUND(CU95*I95,2) -> 0 | U95: =CV95*I95 -> 0 | V95: =CW95*I95 -> 0 | W95: =ROUND(CX95*I95,2) -> 0 | X95: =(ROUND((((S95+ROUND((ROUND(((EU95)*AV95*I95),2)*BS95),2))*AT95)/100),2)+ROUND(((ROUND((ROUND(((AE95-(EU95))*AV95*I95),2)*BS95),2)*AT95)/100),2)) -> 0 | Y95: =(ROUND((((S95+ROUND((ROUND(((EU95)*AV95*I95),2)*BS95),2))*AU95)/100),2)+ROUND(((ROUND((ROUND(((AE95-(EU95))*AV95*I95),2)*BS95),2)*AU95)/100),2)) -> 0 | AA95: 86549534 | AB95: =ROUND((AC95+AD95+AF95),6) -> 181.59 | AC95: =ROUND((ES95),6) -> 181.59 | AD95: =ROUND((((ET95)-(EU95))+AE95),6) -> 0 | AE95: =ROUND((EU95),6) -> 0 | AF95: =ROUND((EV95),6) -> 0 | AG95: =ROUND((AP95),6) -> 0 | AH95: =(EW95) -> 0 | AI95: =(EX95) -> 0 | AJ95: =(AS95) -> 0 | AK95: 181.59 | AL95: 181.59 | AM95: 0 | AN95: 0 | AO95: 0 | AP95: 0 | AQ95: 0 | AR95: 0 | AS95: 0 | AT95: 109 | AU95: 61 | AV95: 1 | AW95: 1 | AZ95: 1 | BA95: 1 | BB95: 1 | BC95: 1 | BH95: 3 | BI95: 1 | BJ95: ТСН-2001.1 Доп. 67, Р. 12, о. 5, поз. 542 | BM95: 21 | BN95: 0 | BP95: 0 | BQ95: 30 | BR95: 0 | BS95: 1 | BT95: 1 | BU95: 1 | BV95: 1 | BW95: 1 | BX95: 1 | BZ95: 109 | CA95: 61 | CE95: 1566 | CF95: 0 | CG95: 0 | CM95: 0 | CN95: Поправка: Гл.6.Прил.2.2.п.2.2.6_06.00.01.07.001_x000D_ Наименование: При выполнении при капитальном ремонте и реконструкции работ, аналогичных технологическим процессам, характерным для нового строительства, и отсутствующих в сборниках на ремонтно-строительные работы ТСН-2001.6_x000D_ Поправка: Гл.12.Прил.8.п.8. 3_12.00.01.11.001_x000D_ Наименование: При наличии напряженных и стесненных условий производства работ (стесненность, сложность складирования и транспортной логистики и т.п.) для объектов, расположенных в пределах круговой магистральной системы улиц "Садовое кольцо" города Москвы | CO95: 0 | CP95: =(P95+Q95+S95) -> 1089.54 | CQ95: =ROUND((ROUND((AC95*AW95*1),2)*BC95),2) -> 181.59 | CR95: =(ROUND((ROUND(((ET95)*AV95*1),2)*BB95),2)+ROUND((ROUND(((AE95-(EU95))*AV95*1),2)*BS95),2)) -> 0 | CS95: =(ROUND((ROUND(((EU95)*AV95*1),2)*BS95),2)+ROUND((ROUND(((AE95-(EU95))*AV95*1),2)*BS95),2)) -> 0 | CT95: =ROUND((ROUND((AF95*AV95*1),2)*BA95),2) -> 0 | CU95: =AG95 -> 0 | CV95: =(AH95*AV95) -> 0 | CW95: =AI95 -> 0 | CX95: =AJ95 -> 0 | CY95: =(ROUND((((S95+ROUND((ROUND(((EU95)*AV95*1),2)*BS95),2))*AT95)/100),2)+ROUND(((ROUND((ROUND(((AE95-(EU95))*AV95*1),2)*BS95),2)*AT95)/100),2)) -> 0 | CZ95: =(ROUND((((S95+ROUND((ROUND(((EU95)*AV95*1),2)*BS95),2))*AU95)/100),2)+ROUND(((ROUND((ROUND(((AE95-(EU95))*AV95*1),2)*BS95),2)*AU95)/100),2)) -> 0 | DN95: 0 | DO95: 0 | DP95: 1 | DQ95: 1 | DU95: 1010 | DV95: шт. | DW95: шт. | DX95: 1 | EE95: 85635393 | EF95: 30 | EG95: Строительные работы | EH95: 0 | EJ95: 1 | EK95: 21 | EL95: ТСН-2001.3-16. Трубопроводы внутренние | EM95: ТСН-2001.3-16-1 | EO95: Поправка: Гл.6.Прил.2.2.п.2.2.6_06.00.01.07.001_x000D_ Поправка: Гл.12.Прил.8.п.8. 3_12.00.01.11.001 | EQ95: 0 | ER95: 181.59 | ES95: 181.59 | ET95: 0 | EU95: 0 | EV95: 0 | EW95: 0 | EX95: 0 | FQ95: 0 | FR95: 0 | FS95: 0 | FX95: 109 | FY95: 61 | GD95: 1 | GF95: 827097433 | GG95: 2 | GH95: 1 | GI95: -2 | GJ95: 0 | GK95: 0 | GL95: =ROUND(IF(AND(BH95=3,BI95=3,FS95<>0),P95,0),2) -> 0 | GM95: =ROUND(O95+X95+Y95,2)+GX95 -> 1089.54 | GN95: =IF(OR(BI95=0,BI95=1),GM95-GX95,0) -> 1089.54 | GO95: =IF(BI95=2,GM95-GX95,0) -> 0 | GP95: =IF(BI95=4,GM95-GX95,0) -> 0 | GR95: 0 | GS95: 3 | GT95: 0 | GV95: =ROUND((GT95),6) -> 0 | GW95: 1 | GX95: =ROUND(HC95*I95,2) -> 0 | HA95: 0 | HB95: 0 | HC95: =GV95*GW95 -> 0 | HM95: *1)*1 | HS95: 0 | IK95: 0
A96: 18 | B96: 1 | C96: 116 | E96: 13,2 | F96: 1.12-5-542 | G96: Муфта противопожарная из нержавеющей стали, с вкладышем из терморасширяющейся резины, для трубы диаметром 50 мм | H96: шт. | I96: =I92*J96 -> 6 | J96: 42.857143 | K96: 42.857143 | O96: =ROUND(CP96,2) -> 828.05 | P96: =ROUND((ROUND((AC96*AW96*I96),2)*BC96),2) -> 828.05 | Q96: =(ROUND((ROUND(((ET96)*AV96*I96),2)*BB96),2)+ROUND((ROUND(((AE96-(EU96))*AV96*I96),2)*BS96),2)) -> 0 | R96: =(ROUND((ROUND(((EU96)*AV96*I96),2)*BS96),2)+ROUND((ROUND(((AE96-(EU96))*AV96*I96),2)*BS96),2)) -> 0 | S96: =ROUND((ROUND((AF96*AV96*I96),2)*BA96),2) -> 0 | T96: =ROUND(CU96*I96,2) -> 0 | U96: =CV96*I96 -> 0 | V96: =CW96*I96 -> 0 | W96: =ROUND(CX96*I96,2) -> 0 | X96: =(ROUND((((S96+ROUND((ROUND(((EU96)*AV96*I96),2)*BS96),2))*AT96)/100),2)+ROUND(((ROUND((ROUND(((AE96-(EU96))*AV96*I96),2)*BS96),2)*AT96)/100),2)) -> 0 | Y96: =(ROUND((((S96+ROUND((ROUND(((EU96)*AV96*I96),2)*BS96),2))*AU96)/100),2)+ROUND(((ROUND((ROUND(((AE96-(EU96))*AV96*I96),2)*BS96),2)*AU96)/100),2)) -> 0 | AA96: 86549536 | AB96: =ROUND((AC96+AD96+AF96),6) -> 181.59 | AC96: =ROUND((ES96),6) -> 181.59 | AD96: =ROUND((((ET96)-(EU96))+AE96),6) -> 0 | AE96: =ROUND((EU96),6) -> 0 | AF96: =ROUND((EV96),6) -> 0 | AG96: =ROUND((AP96),6) -> 0 | AH96: =(EW96) -> 0 | AI96: =(EX96) -> 0 | AJ96: =(AS96) -> 0 | AK96: 181.59 | AL96: 181.59 | AM96: 0 | AN96: 0 | AO96: 0 | AP96: 0 | AQ96: 0 | AR96: 0 | AS96: 0 | AT96: 109 | AU96: 61 | AV96: 1 | AW96: 1 | AZ96: 1 | BA96: 1 | BB96: 1 | BC96: 0.76 | BH96: 3 | BI96: 1 | BJ96: ТСН-2001.1 Доп. 67, Р. 12, о. 5, поз. 542 | BM96: 21 | BN96: 0 | BO96: 1.12-5-542 | BP96: 1 | BQ96: 30 | BR96: 0 | BS96: 1 | BT96: 1 | BU96: 1 | BV96: 1 | BW96: 1 | BX96: 1 | BZ96: 109 | CA96: 61 | CE96: 1566 | CF96: 0 | CG96: 0 | CM96: 0 | CN96: Поправка: Гл.6.Прил.2.2.п.2.2.6_06.00.01.07.001_x000D_ Наименование: При выполнении при капитальном ремонте и реконструкции работ, аналогичных технологическим процессам, характерным для нового строительства, и отсутствующих в сборниках на ремонтно-строительные работы ТСН-2001.6_x000D_ Поправка: Гл.12.Прил.8.п.8. 3_12.00.01.11.001_x000D_ Наименование: При наличии напряженных и стесненных условий производства работ (стесненность, сложность складирования и транспортной логистики и т.п.) для объектов, расположенных в пределах круговой магистральной системы улиц "Садовое кольцо" города Москвы | CO96: 0 | CP96: =(P96+Q96+S96) -> 828.05 | CQ96: =ROUND((ROUND((AC96*AW96*1),2)*BC96),2) -> 138.01 | CR96: =(ROUND((ROUND(((ET96)*AV96*1),2)*BB96),2)+ROUND((ROUND(((AE96-(EU96))*AV96*1),2)*BS96),2)) -> 0 | CS96: =(ROUND((ROUND(((EU96)*AV96*1),2)*BS96),2)+ROUND((ROUND(((AE96-(EU96))*AV96*1),2)*BS96),2)) -> 0 | CT96: =ROUND((ROUND((AF96*AV96*1),2)*BA96),2) -> 0 | CU96: =AG96 -> 0 | CV96: =(AH96*AV96) -> 0 | CW96: =AI96 -> 0 | CX96: =AJ96 -> 0 | CY96: =(ROUND((((S96+ROUND((ROUND(((EU96)*AV96*1),2)*BS96),2))*AT96)/100),2)+ROUND(((ROUND((ROUND(((AE96-(EU96))*AV96*1),2)*BS96),2)*AT96)/100),2)) -> 0 | CZ96: =(ROUND((((S96+ROUND((ROUND(((EU96)*AV96*1),2)*BS96),2))*AU96)/100),2)+ROUND(((ROUND((ROUND(((AE96-(EU96))*AV96*1),2)*BS96),2)*AU96)/100),2)) -> 0 | DN96: 0 | DO96: 0 | DP96: 1 | DQ96: 1 | DU96: 1010 | DV96: шт. | DW96: шт. | DX96: 1 | EE96: 85635393 | EF96: 30 | EG96: Строительные работы | EH96: 0 | EJ96: 1 | EK96: 21 | EL96: ТСН-2001.3-16. Трубопроводы внутренние | EM96: ТСН-2001.3-16-1 | EO96: Поправка: Гл.6.Прил.2.2.п.2.2.6_06.00.01.07.001_x000D_ Поправка: Гл.12.Прил.8.п.8. 3_12.00.01.11.001 | EQ96: 0 | ER96: 181.59 | ES96: 181.59 | ET96: 0 | EU96: 0 | EV96: 0 | EW96: 0 | EX96: 0 | FQ96: 0 | FR96: 0 | FS96: 0 | FX96: 109 | FY96: 61 | GD96: 1 | GF96: 827097433 | GG96: 2 | GH96: 1 | GI96: 2 | GJ96: 0 | GK96: 0 | GL96: =ROUND(IF(AND(BH96=3,BI96=3,FS96<>0),P96,0),2) -> 0 | GM96: =ROUND(O96+X96+Y96,2)+GX96 -> 828.05 | GN96: =IF(OR(BI96=0,BI96=1),GM96-GX96,0) -> 828.05 | GO96: =IF(BI96=2,GM96-GX96,0) -> 0 | GP96: =IF(BI96=4,GM96-GX96,0) -> 0 | GR96: 0 | GS96: 3 | GT96: 0 | GV96: =ROUND((GT96),6) -> 0 | GW96: 1 | GX96: =ROUND(HC96*I96,2) -> 0 | HA96: 0 | HB96: 0 | HC96: =GV96*GW96 -> 0 | HM96: *1)*1 | HS96: 0 | IK96: 0
A98: 51 | B98: =B79 -> 1 | C98: =A79 -> 4 | D98: =ROW(A79) -> 79 | F98: =IF(F79<>"",F79,"") -> Новый раздел | G98: =IF(G79<>"",G79,"") -> Канализация бытовая К 1 (подвал) | H98: 0 | O98: =ROUND(AB98,2) -> 277827.24 | P98: =ROUND(AC98,2) -> 271654.03 | Q98: =ROUND(AD98,2) -> 100.23 | R98: =ROUND(AE98,2) -> 8.75 | S98: =ROUND(AF98,2) -> 6072.98 | T98: =ROUND(AG98,2) -> 0 | U98: =AH98 -> 472.42318 | V98: =AI98 -> 0 | W98: =ROUND(AJ98,2) -> 0 | X98: =ROUND(AK98,2) -> 6629.08 | Y98: =ROUND(AL98,2) -> 3709.86 | AB98: =ROUND(SUMIF(AA83:AA96,"=86549534",O83:O96),2) -> 277827.24 | AC98: =ROUND(SUMIF(AA83:AA96,"=86549534",P83:P96),2) -> 271654.03 | AD98: =ROUND(SUMIF(AA83:AA96,"=86549534",Q83:Q96),2) -> 100.23 | AE98: =ROUND(SUMIF(AA83:AA96,"=86549534",R83:R96),2) -> 8.75 | AF98: =ROUND(SUMIF(AA83:AA96,"=86549534",S83:S96),2) -> 6072.98 | AG98: =ROUND(SUMIF(AA83:AA96,"=86549534",T83:T96),2) -> 0 | AH98: =SUMIF(AA83:AA96,"=86549534",U83:U96) -> 472.42318 | AI98: =SUMIF(AA83:AA96,"=86549534",V83:V96) -> 0 | AJ98: =ROUND(SUMIF(AA83:AA96,"=86549534",W83:W96),2) -> 0 | AK98: =ROUND(SUMIF(AA83:AA96,"=86549534",X83:X96),2) -> 6629.08 | AL98: =ROUND(SUMIF(AA83:AA96,"=86549534",Y83:Y96),2) -> 3709.86 | AO98: =ROUND(BX98,2) -> 0 | AP98: =ROUND(BY98,2) -> 0 | AQ98: =ROUND(BZ98,2) -> 0 | AR98: =ROUND(CA98,2) -> 288166.18 | AS98: =ROUND(CB98,2) -> 288166.18 | AT98: =ROUND(CC98,2) -> 0 | AU98: =ROUND(CD98,2) -> 0 | AV98: =ROUND(CE98,2) -> 271654.03 | ... BD98: =ROUND(CM98,2) -> 0 | BX98: =ROUND(SUMIF(AA83:AA96,"=86549534",FQ83:FQ96),2) -> 0 | BY98: =ROUND(SUMIF(AA83:AA96,"=86549534",FR83:FR96),2) -> 0 | BZ98: =ROUND(SUMIF(AA83:AA96,"=86549534",GL83:GL96),2) -> 0 | CA98: =ROUND(SUMIF(AA83:AA96,"=86549534",GM83:GM96),2) -> 288166.18 | CB98: =ROUND(SUMIF(AA83:AA96,"=86549534",GN83:GN96),2) -> 288166.18 | CC98: =ROUND(SUMIF(AA83:AA96,"=86549534",GO83:GO96),2) -> 0 | CD98: =ROUND(SUMIF(AA83:AA96,"=86549534",GP83:GP96),2) -> 0 | CE98: =AC98-BX98 -> 271654.03 | CF98: =AC98-BY98 -> 271654.03 | CG98: =BX98-BZ98 -> 0 | CH98: =AC98-BX98-BY98+BZ98 -> 271654.03 | CI98: =BY98-BZ98 -> 0 | CJ98: =ROUND(SUMIF(AA83:AA96,"=86549534",GX83:GX96),2) -> 0 | CK98: =ROUND(SUMIF(AA83:AA96,"=86549534",GY83:GY96),2) -> 0 | CL98: =ROUND(SUMIF(AA83:AA96,"=86549534",GZ83:GZ96),2) -> 0 | CM98: =ROUND(SUMIF(AA83:AA96,"=86549534",HD83:HD96),2) -> 0 | DG98: =ROUND(DT98,2) -> 769079.34 | DH98: =ROUND(DU98,2) -> 425466.62 | DI98: =ROUND(DV98,2) -> 1400.3 | DJ98: =ROUND(DW98,2) -> 493.06 | DK98: =ROUND(DX98,2) -> 342212.42 | DL98: =ROUND(DY98,2) -> 0 | DM98: =DZ98 -> 472.42318 | DN98: =EA98 -> 0 | DO98: =ROUND(EB98,2) -> 0 | DP98: =ROUND(EC98,2) -> 373548.97 | DQ98: =ROUND(ED98,2) -> 209050.34 | DT98: =ROUND(SUMIF(AA83:AA96,"=86549536",O83:O96),2) -> 769079.34 | DU98: =ROUND(SUMIF(AA83:AA96,"=86549536",P83:P96),2) -> 425466.62 | DV98: =ROUND(SUMIF(AA83:AA96,"=86549536",Q83:Q96),2) -> 1400.3 | DW98: =ROUND(SUMIF(AA83:AA96,"=86549536",R83:R96),2) -> 493.06 | DX98: =ROUND(SUMIF(AA83:AA96,"=86549536",S83:S96),2) -> 342212.42 | DY98: =ROUND(SUMIF(AA83:AA96,"=86549536",T83:T96),2) -> 0 | DZ98: =SUMIF(AA83:AA96,"=86549536",U83:U96) -> 472.42318 | EA98: =SUMIF(AA83:AA96,"=86549536",V83:V96) -> 0 | EB98: =ROUND(SUMIF(AA83:AA96,"=86549536",W83:W96),2) -> 0 | EC98: =ROUND(SUMIF(AA83:AA96,"=86549536",X83:X96),2) -> 373548.97 | ED98: =ROUND(SUMIF(AA83:AA96,"=86549536",Y83:Y96),2) -> 209050.34 | EG98: =ROUND(FP98,2) -> 0 | EH98: =ROUND(FQ98,2) -> 0 | EI98: =ROUND(FR98,2) -> 0 | EJ98: =ROUND(FS98,2) -> 1351678.6 | EK98: =ROUND(FT98,2) -> 1351678.6 | EL98: =ROUND(FU98,2) -> 0 | EM98: =ROUND(FV98,2) -> 0 | EN98: =ROUND(FW98,2) -> 425466.62 | ... EV98: =ROUND(GE98,2) -> 0 | FP98: =ROUND(SUMIF(AA83:AA96,"=86549536",FQ83:FQ96),2) -> 0 | FQ98: =ROUND(SUMIF(AA83:AA96,"=86549536",FR83:FR96),2) -> 0 | FR98: =ROUND(SUMIF(AA83:AA96,"=86549536",GL83:GL96),2) -> 0 | FS98: =ROUND(SUMIF(AA83:AA96,"=86549536",GM83:GM96),2) -> 1351678.6 | FT98: =ROUND(SUMIF(AA83:AA96,"=86549536",GN83:GN96),2) -> 1351678.6 | FU98: =ROUND(SUMIF(AA83:AA96,"=86549536",GO83:GO96),2) -> 0 | FV98: =ROUND(SUMIF(AA83:AA96,"=86549536",GP83:GP96),2) -> 0 | FW98: =DU98-FP98 -> 425466.62 | FX98: =DU98-FQ98 -> 425466.62 | FY98: =FP98-FR98 -> 0 | FZ98: =DU98-FP98-FQ98+FR98 -> 425466.62 | GA98: =FQ98-FR98 -> 0 | GB98: =ROUND(SUMIF(AA83:AA96,"=86549536",GX83:GX96),2) -> 0 | GC98: =ROUND(SUMIF(AA83:AA96,"=86549536",GY83:GY96),2) -> 0 | GD98: =ROUND(SUMIF(AA83:AA96,"=86549536",GZ83:GZ96),2) -> 0 | GE98: =ROUND(SUMIF(AA83:AA96,"=86549536",HD83:HD96),2) -> 0 | GX98: 0
A100: 50 | B100: 0 | C100: 0 | D100: 1 | E100: 201 | F100: =ROUND(Source!O98,O100) -> 277827.24 | G100: ПЗ | H100: Прямые затраты | K100: 201 | L100: 1 | M100: 3 | O100: 2 | P100: =ROUND(Source!DG98,O100) -> 769079.34 | W100: 277827.24 | X100: 1 | Y100: 277827.24 | Z100: 769079.34 | AA100: 1 | AB100: 769079.34
A101: 50 | B101: 0 | C101: 0 | D101: 1 | E101: 202 | F101: =ROUND(Source!P98,O101) -> 271654.03 | G101: СтМатОб | H101: Стоимость материальных ресурсов (всего) | K101: 202 | L101: 2 | M101: 3 | O101: 2 | P101: =ROUND(Source!DH98,O101) -> 425466.62 | W101: 271654.03 | X101: 1 | Y101: 271654.03 | Z101: 425466.62 | AA101: 1 | AB101: 425466.62
A102: 50 | B102: 0 | C102: 0 | D102: 1 | E102: 222 | F102: =ROUND(Source!AO98,O102) -> 0 | G102: СтМатОбЗак | H102: Стоимость материалов и оборудования заказчика | K102: 222 | L102: 3 | M102: 3 | O102: 2 | P102: =ROUND(Source!EG98,O102) -> 0 | W102: 0 | X102: 1 | Y102: 0 | Z102: 0 | AA102: 1 | AB102: 0
A103: 50 | B103: 0 | C103: 0 | D103: 1 | E103: 225 | F103: =ROUND(Source!AV98,O103) -> 271654.03 | G103: СтМатОбПод | H103: Стоимость материалов и оборудования подрядчика | K103: 225 | L103: 4 | M103: 3 | O103: 2 | P103: =ROUND(Source!EN98,O103) -> 425466.62 | W103: 271654.03 | X103: 1 | Y103: 271654.03 | Z103: 425466.62 | AA103: 1 | AB103: 425466.62
A104: 50 | B104: 0 | C104: 0 | D104: 1 | E104: 226 | F104: =ROUND(Source!AW98,O104) -> 271654.03 | G104: СтМат | H104: Стоимость материалов (всего) | K104: 226 | L104: 5 | M104: 3 | O104: 2 | P104: =ROUND(Source!EO98,O104) -> 425466.62 | W104: 271654.03 | X104: 1 | Y104: 271654.03 | Z104: 425466.62 | AA104: 1 | AB104: 425466.62
A105: 50 | B105: 0 | C105: 0 | D105: 1 | E105: 227 | F105: =ROUND(Source!AX98,O105) -> 0 | G105: СтМатЗак | H105: Стоимость материалов заказчика | K105: 227 | L105: 6 | M105: 3 | O105: 2 | P105: =ROUND(Source!EP98,O105) -> 0 | W105: 0 | X105: 1 | Y105: 0 | Z105: 0 | AA105: 1 | AB105: 0
A106: 50 | B106: 0 | C106: 0 | D106: 1 | E106: 228 | F106: =ROUND(Source!AY98,O106) -> 271654.03 | G106: СтМатПод | H106: Стоимость материалов подрядчика | K106: 228 | L106: 7 | M106: 3 | O106: 2 | P106: =ROUND(Source!EQ98,O106) -> 425466.62 | W106: 271654.03 | X106: 1 | Y106: 271654.03 | Z106: 425466.62 | AA106: 1 | AB106: 425466.62
A107: 50 | B107: 0 | C107: 0 | D107: 1 | E107: 216 | F107: =ROUND(Source!AP98,O107) -> 0 | G107: Оборуд | H107: Стоимость оборудования (всего) | K107: 216 | L107: 8 | M107: 3 | O107: 2 | P107: =ROUND(Source!EH98,O107) -> 0 | W107: 0 | X107: 1 | Y107: 0 | Z107: 0 | AA107: 1 | AB107: 0
A108: 50 | B108: 0 | C108: 0 | D108: 1 | E108: 223 | F108: =ROUND(Source!AQ98,O108) -> 0 | G108: ОборудЗак | H108: Стоимость оборудования заказчика | K108: 223 | L108: 9 | M108: 3 | O108: 2 | P108: =ROUND(Source!EI98,O108) -> 0 | W108: 0 | X108: 1 | Y108: 0 | Z108: 0 | AA108: 1 | AB108: 0
A109: 50 | B109: 0 | C109: 0 | D109: 1 | E109: 229 | F109: =ROUND(Source!AZ98,O109) -> 0 | G109: ОборудПод | H109: Стоимость оборудования подрядчика | K109: 229 | L109: 10 | M109: 3 | O109: 2 | P109: =ROUND(Source!ER98,O109) -> 0 | W109: 0 | X109: 1 | Y109: 0 | Z109: 0 | AA109: 1 | AB109: 0
A110: 50 | B110: 0 | C110: 0 | D110: 1 | E110: 203 | F110: =ROUND(Source!Q98,O110) -> 100.23 | G110: ЭММ | H110: Эксплуатация машин | K110: 203 | L110: 11 | M110: 3 | O110: 2 | P110: =ROUND(Source!DI98,O110) -> 1400.3 | W110: 100.23 | X110: 1 | Y110: 100.23 | Z110: 1400.3 | AA110: 1 | AB110: 1400.3
A111: 50 | B111: 0 | C111: 0 | D111: 1 | E111: 231 | F111: =ROUND(Source!BB98,O111) -> 0 | G111: ЭММсНРиСП | H111: Эксплуатация машин по ТСН-2001.16 | K111: 231 | L111: 12 | M111: 3 | O111: 2 | P111: =ROUND(Source!ET98,O111) -> 0 | W111: 0 | X111: 1 | Y111: 0 | Z111: 0 | AA111: 1 | AB111: 0
A112: 50 | B112: 0 | C112: 0 | D112: 1 | E112: 204 | F112: =ROUND(Source!R98,O112) -> 8.75 | G112: ЗПМ | H112: ЗП машинистов | K112: 204 | L112: 13 | M112: 3 | O112: 2 | P112: =ROUND(Source!DJ98,O112) -> 493.06 | W112: 8.75 | X112: 1 | Y112: 8.75 | Z112: 493.06 | AA112: 1 | AB112: 493.06
A113: 50 | B113: 0 | C113: 0 | D113: 1 | E113: 205 | F113: =ROUND(Source!S98,O113) -> 6072.98 | G113: ОЗП | H113: Основная ЗП рабочих | K113: 205 | L113: 14 | M113: 3 | O113: 2 | P113: =ROUND(Source!DK98,O113) -> 342212.42 | W113: 6072.98 | X113: 1 | Y113: 6072.98 | Z113: 342212.42 | AA113: 1 | AB113: 342212.42
A114: 50 | B114: 0 | C114: 0 | D114: 1 | E114: 232 | F114: =ROUND(Source!BC98,O114) -> 0 | G114: ОЗПсНРиСП | H114: Основная ЗП рабочих по ТСН-2001.16 | K114: 232 | L114: 15 | M114: 3 | O114: 2 | P114: =ROUND(Source!EU98,O114) -> 0 | W114: 0 | X114: 1 | Y114: 0 | Z114: 0 | AA114: 1 | AB114: 0
A115: 50 | B115: 0 | C115: 0 | D115: 1 | E115: 214 | F115: =ROUND(Source!AS98,O115) -> 288166.18 | G115: Строит | H115: Строительные работы с НР и СП | K115: 214 | L115: 16 | M115: 3 | O115: 2 | P115: =ROUND(Source!EK98,O115) -> 1351678.6 | W115: 288166.18 | X115: 1 | Y115: 288166.18 | Z115: 1351678.6 | AA115: 1 | AB115: 1351678.6
A116: 50 | B116: 0 | C116: 0 | D116: 1 | E116: 215 | F116: =ROUND(Source!AT98,O116) -> 0 | G116: Монтаж | H116: Монтажные работы с НР и СП | K116: 215 | L116: 17 | M116: 3 | O116: 2 | P116: =ROUND(Source!EL98,O116) -> 0 | W116: 0 | X116: 1 | Y116: 0 | Z116: 0 | AA116: 1 | AB116: 0
A117: 50 | B117: 0 | C117: 0 | D117: 1 | E117: 217 | F117: =ROUND(Source!AU98,O117) -> 0 | G117: Прочие | H117: Прочие работы с НР и СП | K117: 217 | L117: 18 | M117: 3 | O117: 2 | P117: =ROUND(Source!EM98,O117) -> 0 | W117: 0 | X117: 1 | Y117: 0 | Z117: 0 | AA117: 1 | AB117: 0
A118: 50 | B118: 0 | C118: 0 | D118: 1 | E118: 230 | F118: =ROUND(Source!BA98,O118) -> 0 | G118: ПрочиеЗатр | H118: Прочие затраты по ТСН-2001.16 | K118: 230 | L118: 19 | M118: 3 | O118: 2 | P118: =ROUND(Source!ES98,O118) -> 0 | W118: 0 | X118: 1 | Y118: 0 | Z118: 0 | AA118: 1 | AB118: 0
A119: 50 | B119: 0 | C119: 0 | D119: 1 | E119: 206 | F119: =ROUND(Source!T98,O119) -> 0 | G119: ВозврМат | H119: Возврат материалов | K119: 206 | L119: 20 | M119: 3 | O119: 2 | P119: =ROUND(Source!DL98,O119) -> 0 | W119: 0 | X119: 1 | Y119: 0 | Z119: 0 | AA119: 1 | AB119: 0
A120: 50 | B120: 0 | C120: 0 | D120: 1 | E120: 207 | F120: =Source!U98 -> 472.42318 | G120: ТрудСтр | H120: Трудозатраты строителей | K120: 207 | L120: 21 | M120: 3 | O120: -1 | P120: =Source!DM98 -> 472.42318 | W120: 472.42318 | X120: 1 | Y120: 472.42318 | Z120: 472.42318 | AA120: 1 | AB120: 472.42318
A121: 50 | B121: 0 | C121: 0 | D121: 1 | E121: 208 | F121: =Source!V98 -> 0 | G121: ТрудМаш | H121: Трудозатраты машинистов | K121: 208 | L121: 22 | M121: 3 | O121: -1 | P121: =Source!DN98 -> 0 | W121: 0 | X121: 1 | Y121: 0 | Z121: 0 | AA121: 1 | AB121: 0
A122: 50 | B122: 0 | C122: 0 | D122: 1 | E122: 209 | F122: =ROUND(Source!W98,O122) -> 0 | G122: ТранспМат | H122: Транспорт материалов | K122: 209 | L122: 23 | M122: 3 | O122: 2 | P122: =ROUND(Source!DO98,O122) -> 0 | W122: 0 | X122: 1 | Y122: 0 | Z122: 0 | AA122: 1 | AB122: 0
A123: 50 | B123: 0 | C123: 0 | D123: 1 | E123: 233 | F123: =ROUND(Source!BD98,O123) -> 0 | G123: Перевозка | H123: Перевозка грузов | K123: 233 | L123: 24 | M123: 3 | O123: 2 | P123: =ROUND(Source!EV98,O123) -> 0 | W123: 0 | X123: 1 | Y123: 0 | Z123: 0 | AA123: 1 | AB123: 0
A124: 50 | B124: 0 | C124: 0 | D124: 1 | E124: 210 | F124: =ROUND(Source!X98,O124) -> 6629.08 | G124: НР | H124: Накладные расходы | K124: 210 | L124: 25 | M124: 3 | O124: 2 | P124: =ROUND(Source!DP98,O124) -> 373548.97 | W124: 6629.08 | X124: 1 | Y124: 6629.08 | Z124: 373548.97 | AA124: 1 | AB124: 373548.97
A125: 50 | B125: 0 | C125: 0 | D125: 1 | E125: 211 | F125: =ROUND(Source!Y98,O125) -> 3709.86 | G125: СмПриб | H125: Сметная прибыль | K125: 211 | L125: 26 | M125: 3 | O125: 2 | P125: =ROUND(Source!DQ98,O125) -> 209050.34 | W125: 3709.86 | X125: 1 | Y125: 3709.86 | Z125: 209050.34 | AA125: 1 | AB125: 209050.34
...

Sheet SourceObSm
A1: 0 | B1: Smeta.RU (495) 974-1589 | D1: _OBSM_ | F1: 0 | G1: 0 | H1: 0 | I1: Smeta.RU | K1: 1 | L1: 74603 | M1: 10 | N1: 12 | O1: 1 | P1: 0 | Q1: 1
A4: 8 | B4: 1 | C4: -1 | F4: Новый проект | G4: Капитальный ремонт здания Государственного бюджетного общеобразовательного учреждения города Москвы «Школа №1574», расположенного по адресу: г. Москва, Старопименовский переулок, д. 5. 1 этап | EC4: 0
A12: 1 | B12: 51 | C12: 0 | E12: 0 | F12: Новый объект строительства | I12: 0 | K12: 0 | L12: 0 | M12: 4098 | O12: 0 | P12: 0 | Q12: 0 | R12: 0 | S12: 0 | T12: 1 | V12: 2 | W12: г. Москва, Старопименовский переулок, д. 5. 1 этап | BB12: 0 | BH12: Сметные нормы списания | BI12: Коды ОКП для ТСН-2001 МГЭ Дополнение 81 | BJ12: 1 | BK12: 1 | BL12: 0 | BM12: 0 | BN12: 1 | BO12: 0 | BP12: 6 | BQ12: 2 | BR12: 1 | BS12: 1 | BT12: 0 | BU12: 0 | BV12: 0 | BW12: 0 | BX12: 0 | BY12: ТСН-2001 (МГЭ) Доп 81 - Ремонт | BZ12: Типовой расчет для ТСН-2001 МГЭ, Дополнение 81, ремонт | CA12: Территориальные сметные нормативы для Москвы ТСН-2001 (МГЭ), дополнение 81 | CB12: Территориальные сметные нормативы для Москвы ТСН-2001 (МГЭ), дополнение 81 | CC12: Территориальные сметные нормативы для Москвы ТСН-2001 (МГЭ), дополнение 81 | CD12: Территориальные сметные нормативы для Москвы ТСН-2001 (МГЭ), дополнение 81 | CE12: Поправки для ТСН-2001 от 07.04.2026 г. доп.81 | CF12: 0 | CG12: 0 | CH12: 8200 | CK12: 81 | CQ12: Территориальные сметные нормативы для Москвы (ТСН-2001) | CR12: ТЕР | CS12: 41660 | CT12: 1 | CU12: 81 | CY12: 0 | EC12: 0
A14: 22 | B14: 1 | C14: 0 | D14: 86549536 | E14: 86549534 | F14: 2 | G14: 1
A16: 3 | B16: 1 | C16: 02-01-05 | D16: Система водоотведения. | E16: =ROUND((Source!P660)/1000,2) -> 7023.29 | F16: =ROUND((Source!P661)/1000,2) -> 0 | G16: =ROUND((Source!P652)/1000,2) -> 126.01 | H16: =ROUND((Source!P662)/1000+(Source!P663)/1000,2) -> 0 | I16: =E16+F16+G16+H16 -> 7149.3 | J16: =ROUND((Source!P658+Source!P657)/1000,2) -> 1431.63 | K16: 8208.83 | L16: 0 | M16: 0 | N16: =I16+L16+M16 -> 7149.3 | T16: =ROUND((Source!F660)/1000,2) -> 781.6 | U16: =ROUND((Source!F661)/1000,2) -> 0 | V16: =ROUND((Source!F652)/1000,2) -> 8.47 | W16: =ROUND((Source!F662)/1000+(Source!F663)/1000,2) -> 0 | X16: =T16+U16+V16+W16 -> 790.07 | Y16: =ROUND((Source!F658+Source!F657)/1000,2) -> 25.41 | Z16: 1471.19 | AA16: 0 | AB16: 0 | AC16: =X16+AA16+AB16 -> 790.07 | AI16: 2 | AJ16: -1 | AN16: 0 | AT16: 4825840 | AU16: 3382989.5 | AV16: 0 | AW16: 126005.85 | AX16: 0 | AY16: 19998.9 | AZ16: 8779.36 | BA16: 1422851.6 | BB16: 7023289.3 | BC16: 0 | BD16: 0 | BE16: 0 | BF16: 2029.9267 | BG16: 0 | BH16: 0 | BI16: 1498247.4 | BJ16: 825207.79 | BK16: 7149295.2 | BR16: 748838.28 | BS16: 722350.83 | BT16: 0 | BU16: 8473.83 | BV16: 0 | BW16: 1237.2 | BX16: 155.8 | BY16: 25250.25 | BZ16: 781596.99 | CA16: 0 | CB16: 0 | CC16: 0 | CD16: 2029.9267 | CE16: 0 | CF16: 0 | CG16: 26588.23 | CH16: 14644.31 | CI16: 790070.82
A18: 51 | E18: 7023.29 | F18: 0 | G18: 126.01 | H18: 0 | I18: 7149.3 | J18: 1431.63 | K18: 8208.83 | L18: 0 | M18: 0 | N18: 7149.3 | T18: 781.6 | U18: 0 | V18: 8.47 | W18: 0 | X18: 790.07 | Y18: 25.41 | Z18: 1471.19 | AA18: 0 | AB18: 0 | AC18: 790.07
A20: 50 | B20: 0 | C20: 0 | D20: 1 | E20: 201 | F20: 4825840 | G20: ПЗ | H20: Прямые затраты | K20: 201 | L20: 1 | M20: 3 | O20: 2 | P20: 748838.28
A21: 50 | B21: 0 | C21: 0 | D21: 1 | E21: 202 | F21: 3382989.5 | G21: СтМатОб | H21: Стоимость материальных ресурсов (всего) | K21: 202 | L21: 2 | M21: 3 | O21: 2 | P21: 722350.83
A22: 50 | B22: 0 | C22: 0 | D22: 1 | E22: 222 | F22: 0 | G22: СтМатОбЗак | H22: Стоимость материалов и оборудования заказчика | K22: 222 | L22: 3 | M22: 3 | O22: 2 | P22: 0
A23: 50 | B23: 0 | C23: 0 | D23: 1 | E23: 225 | F23: 3382989.5 | G23: СтМатОбПод | H23: Стоимость материалов и оборудования подрядчика | K23: 225 | L23: 4 | M23: 3 | O23: 2 | P23: 722350.83
A24: 50 | B24: 0 | C24: 0 | D24: 1 | E24: 226 | F24: 3256983.6 | G24: СтМат | H24: Стоимость материалов (всего) | K24: 226 | L24: 5 | M24: 3 | O24: 2 | P24: 713877
A25: 50 | B25: 0 | C25: 0 | D25: 1 | E25: 227 | F25: 0 | G25: СтМатЗак | H25: Стоимость материалов заказчика | K25: 227 | L25: 6 | M25: 3 | O25: 2 | P25: 0
A26: 50 | B26: 0 | C26: 0 | D26: 1 | E26: 228 | F26: 3256983.6 | G26: СтМатПод | H26: Стоимость материалов подрядчика | K26: 228 | L26: 7 | M26: 3 | O26: 2 | P26: 713877
A27: 50 | B27: 0 | C27: 0 | D27: 1 | E27: 216 | F27: 126005.85 | G27: Оборуд | H27: Стоимость оборудования (всего) | K27: 216 | L27: 8 | M27: 3 | O27: 2 | P27: 8473.83
A28: 50 | B28: 0 | C28: 0 | D28: 1 | E28: 223 | F28: 0 | G28: ОборудЗак | H28: Стоимость оборудования заказчика | K28: 223 | L28: 9 | M28: 3 | O28: 2 | P28: 0
A29: 50 | B29: 0 | C29: 0 | D29: 1 | E29: 229 | F29: 126005.85 | G29: ОборудПод | H29: Стоимость оборудования подрядчика | K29: 229 | L29: 10 | M29: 3 | O29: 2 | P29: 8473.83
A30: 50 | B30: 0 | C30: 0 | D30: 1 | E30: 203 | F30: 19998.9 | G30: ЭММ | H30: Эксплуатация машин | K30: 203 | L30: 11 | M30: 3 | O30: 2 | P30: 1237.2
A31: 50 | B31: 0 | C31: 0 | D31: 1 | E31: 231 | F31: 0 | G31: ЭММсНРиСП | H31: Эксплуатация машин по ТСН-2001.16 | K31: 231 | L31: 12 | M31: 3 | O31: 2 | P31: 0
... A46: 50 | B46: 0 | C46: 0 | D46: 1 | E46: 224 | F46: 7149295.2 | G46: Всего | H46: Всего с НР и СП | K46: 224 | L46: 27 | M46: 3 | O46: 2 | P46: 790070.82
A48: -1
A51: 75 | B51: Текущий уровень цен | C51: 2026 | D51: 1 | E51: 0 | G51: 0 | H51: 1 | I51: 1 | J51: 1 | K51: 0 | L51: 0 | M51: 1 | N51: 86549536 | O51: 1
A52: 1 | B52: Сборник индексов | C52: Коэффициенты к ТСН-2001 МГЭ Дополнение 81, ремонт | D52: 2026 | E52: 1 | F52: 1 | G52: 1 | H52: 0 | I52: 2 | J52: 1 | K52: 9.84 | L52: 7.57 | M52: 1 | N52: 1 | O52: 9.84 | P52: 7.57 | Q52: 1 | AA52: 219/81 | AN52: 86549537
A53: 1 | B53: Сборник индексов | C53: Коэффициенты к ТСН-2001.13-2 Дополнение 47 | D53: 2026 | E53: 1 | F53: 1 | G53: 1 | H53: 0 | I53: 2 | J53: 1 | K53: 1 | L53: 1 | M53: 1 | N53: 1 | O53: 1 | P53: 1 | Q53: 1 | AA53: 64/47 | AN53: 86549538
A54: 75 | B54: Базовый уровень цен | C54: 2000 | D54: 0 | E54: 1 | F54: 0 | G54: 0 | H54: 1 | I54: 1 | J54: 3 | K54: 0 | L54: 0 | M54: 0 | N54: 86549534 | O54: 2
A55: 1 | B55: Сборник индексов | C55: Коэффициенты к ТСН-2001 МГЭ Дополнение 81, ремонт | D55: 2000 | E55: 1 | F55: 1 | G55: 1 | H55: 0 | I55: 2 | J55: 1 | K55: 1 | L55: 1 | M55: 1 | N55: 1 | O55: 1 | P55: 1 | Q55: 1 | AA55: 0 | AN55: 86549535

Sheet SmtRes
A1: =ROW(Source!A28) -> 28 | B1: 86549534 | C1: 86550942 | D1: 85665773 | E1: 1081 | F1: 1 | G1: 1081 | H1: 1 | I1: 9999990008 | K1: Трудозатраты рабочих | L1: 1191 | N1: 1013 | O1: чел.-ч. | P1: чел.-ч. | Q1: 1 | W1: 0 | X1: 476480486 | Y1: =(AT1*1.2) -> 54.624 | AA1: 0 | AB1: 0 | AC1: 0 | AD1: 0 | AE1: 0 | AF1: 0 | AG1: 0 | AH1: 0 | AI1: 1 | AJ1: 1 | AK1: 1 | AL1: 1 | AM1: -2 | AN1: 0 | AO1: 1 | AP1: 1 | AQ1: 0 | AR1: 0 | AT1: 45.52 | AU1: *1,2 | AV1: 1 | AW1: 2 | AX1: 86550948 | AY1: 1 | AZ1: 0 | BA1: 1 | BB1: 0 | BC1: 0 | BD1: 0 | BE1: 0 | BF1: 0 | BG1: 0 | BH1: 0 | BI1: 0 | BJ1: 0 | BK1: 0 | BL1: 0 | BM1: 0 | BN1: 0 | BO1: 0 | BP1: 0 | BQ1: 0 | BR1: 0 | BS1: 0 | BT1: 0 | BU1: 0 | BV1: 0 | BW1: 0 | CU1: =ROUND(AT1*Source!I28*AH1*AL1,2) -> 0 | CV1: =ROUND(Y1*Source!I28,9) -> 20.75712 | CW1: 0 | CX1: =ROUND(Y1*Source!I28,9) -> 20.75712 | CY1: =AD1 -> 0 | CZ1: =AH1 -> 0 | DA1: =AL1 -> 1 | DB1: =ROUND((ROUND(AT1*CZ1,2)*1.2),6) -> 0 | DC1: =ROUND((ROUND(AT1*AG1,2)*1.2),6) -> 0 | DF1: =ROUND(ROUND(AE1,2)*CX1,2) -> 0 | DG1: =ROUND(ROUND(AF1,2)*CX1,2) -> 0 | DH1: =ROUND(ROUND(AG1,2)*CX1,2) -> 0 | DI1: =ROUND(ROUND(AH1,2)*CX1,2) -> 0 | DJ1: =DI1 -> 0 | DK1: 0 | DM1: 0 | DO1: 0
