Workbook

Sheet Смета по ТСН-2001(с доп.67
A1: =Source!B1 -> Smeta.RU (495) 974-1589
J2: Форма № 4б
B3: "СОГЛАСОВАНО" | G3: "УТВЕРЖДАЮ"
B6: =CONCATENATE("______________________ ", IF(Source!AL12<>"", Source!AL12, "")) -> ______________________ | G6: =CONCATENATE("______________________ ", IF(Source!AH12<>"", Source!AH12, "")) -> ______________________
B7: "_____"________________ 2026 г. | G7: "_____"________________ 2026 г.
A10: Капитальный ремонт здания Государственного бюджетного общеобразовательного учреждения города Москвы «Школа №1574», расположенного по адресу: г. Москва, Старопименовский переулок, д. 5. 1 этап. | AP10: Капитальный ремонт здания Государственного бюджетного общеобразовательного учреждения города Москвы «Школа №1574», расположенного по адресу: г. Москва, Старопименовский переулок, д. 5. 1 этап. 02-01-12 СКТ
A11: (наименование стройки и/или объекта)
A13: =CONCATENATE( "ЛОКАЛЬНАЯ СМЕТА № ",IF(Source!F12<>"Новый объект", Source!F12, "")) -> ЛОКАЛЬНАЯ СМЕТА № 02-01-12
A15: =Source!G20 -> Система кабельного телевидения
A16: (наименование работ и затрат)
A18: =CONCATENATE( "Основание: чертежи № ", Source!J12) -> Основание: чертежи № 2024-00375-01-0-ИОС5.5
I20: В базисном уровне цен | J20: В текущем уровне цен
E21: Сметная стоимость | I21: =I22+I23+I24+I25 -> 99.05 | J21: =J22+J23+J24+J25 -> 928.24 | K21: тыс.руб.
E22: Строительные работы | I22: =ROUND((Source!F332)/1000, 2) -> 3.09 | J22: =ROUND((Source!P332)/1000, 2) -> 173.99 | K22: тыс.руб.
E23: Работы по монтажу оборудования | I23: =ROUND((Source!F333)/1000, 2) -> 87.48 | J23: =ROUND((Source!P333)/1000, 2) -> 670.79 | K23: тыс.руб.
E24: Оборудование | I24: =ROUND((Source!F324)/1000, 2) -> 8.48 | J24: =ROUND((Source!P324)/1000, 2) -> 83.46 | K24: тыс.руб.
E25: Прочие работы и затраты | I25: =ROUND((Source!F334+Source!F335)/1000, 2) -> 0 | J25: =ROUND((Source!P334+Source!P335)/1000, 2) -> 0 | K25: тыс.руб.
E26: Средства на оплату труда | I26: =(Source!F330+ Source!F329)/1000 -> 4.38015 | J26: =((Source!P330 + Source!P329)/1000) -> 246.82146 | K26: тыс.руб.
E27: Затраты труда | I27: =Source!F337 -> 323.30434 | K27: чел.-ч.
E28: Кроме того:
E29: Возврат материалов | I29: =SUM(Y1:Y355)/1000 -> 0 | J29: =SUM(Z1:Z355)/1000 -> 0 | K29: тыс.руб.
A31: Составлен(а) по ТСН-2001 с учетом Дополнения №: 81
A32: № и период сборника коэффициентов (индексов) пересчета: Коэффициенты к ТСН-2001 МГЭ Дополнение 81, строительство №219/81 I квартал 2026 года и Коэффициенты к ТСН-2001.13-2 Дополнение 47 №64/47 I квартал 2026 года | AP32: № и период сборника коэффициентов (индексов) пересчета: Коэффициенты к ТСН-2001 МГЭ Дополнение 81, строительство №219/81 I квартал 2026 года и Коэффициенты к ТСН-2001.13-2 Дополнение 47 №64/47 I квартал 2026 года
A33: № п/п | B33: Шифр расценки и коды ресурсов | C33: Наименование работ и затрат | D33: Ед. изм. | E33: Кол-во единиц | F33: Цена на ед. изм., руб. | G33: Попра- вочные коэффи- циенты | H33: Коэффи- циенты зимних удорожа- ний | I33: Всего в ценах на январь 2000 года, руб. | J33: Коэффи- циенты (индек- сы) пере- счета, нормы НР и СП | K33: ВСЕГО затрат в текущем уровне цен, руб.
A34: 1 | B34: 2 | C34: 3 | D34: 4 | E34: 5 | F34: 6 | G34: 7 | H34: 8 | I34: 9 | J34: 10 | K34: 11
A36: =CONCATENATE("Локальная смета: ",IF(Source!G20<>"Новая локальная смета", Source!G20, "")) -> Локальная смета: Система кабельного телевидения
A38: =CONCATENATE("Раздел: ",IF(Source!G24<>"Новый раздел", Source!G24, "")) -> Раздел: Демонтаж
A39: 1 | B39: =Source!F28 -> 4.10-134-4 | C39: Монтаж антенны коллективной для приема ТВ на антенной опоре высотой до 9 м с одним ярусом оттяжек / демонтаж эфирной антенны | D39: =Source!H28 -> 1 антенна | E39: =Source!I28 -> 1 | Q39: =Source!X28 -> 28.31 | R39: =Source!X29 -> 1595.27 | S39: =Source!Y28 -> 15.79 | T39: =Source!Y29 -> 889.99 | U39: =ROUND((175/100)*ROUND(Source!R28, 2), 2) -> 0 | V39: =ROUND((0/100)*ROUND(Source!R29, 2), 2) -> 0 | AC39: 0
C40: ЗП | F40: =Source!AO28 -> 76.15 | G40: 1,2*0,3 | H40: =Source!AV29 -> 1.087 | I40: =Source!S28 -> 29.8 | J40: =IF(Source!BA29<> 0, Source!BA29, 1) -> 56.35 | K40: =Source!S29 -> 1679.23
C41: НР от ФОТ | D41: % | E41: =Source!BZ29 -> 95 | I41: =SUM(Q39:Q40) -> 28.31 | J41: =Source!AT29 -> 95 | K41: =SUM(R39:R40) -> 1595.27
C42: СП от ФОТ | D42: % | E42: =Source!CA29 -> 53 | I42: =SUM(S39:S41) -> 15.79 | J42: =Source!AU29 -> 53 | K42: =SUM(T39:T41) -> 889.99
C43: ЗТР | D43: чел-ч | E43: =Source!AQ28 -> 5.37 | G43: 1,2*0,3 | H43: =Source!AV29 -> 1.087 | I43: =Source!U28 -> 2.1013884
C44: ВСЕГО работ по позиции: | H44: =I40+I41+I42+0-0-0 -> 73.9 | J44: =K40+K41+K42+0-0-0 -> 4164.49
C45: ВСЕГО оборудование по позиции: | H45: =0+0 -> 0 | J45: =0+0 -> 0
C46: ВСЕГО по позиции: | H46: =I40+I41+I42+0 -> 73.9 | J46: =K40+K41+K42+0 -> 4164.49 | O46: =I40+I41+I42+0 -> 73.9 | P46: =K40+K41+K42+0 -> 4164.49
A48: 2 | B48: =Source!F30 -> 4.10-136-1 | C48: Монтаж коробки телевизионной (ответвители, разветвители магистральные, домовые, абонентские), УСС, БФТК / демонтаж грозозащиты | D48: =Source!H30 -> 1 ШТ. | E48: =Source!I30 -> 1 | Q48: =Source!X30 -> 4.09 | R48: =Source!X31 -> 230.73 | S48: =Source!Y30 -> 2.28 | T48: =Source!Y31 -> 128.72 | U48: =ROUND((175/100)*ROUND(Source!R30, 2), 2) -> 0 | V48: =ROUND((0/100)*ROUND(Source!R31, 2), 2) -> 0 | AC48: 0
C49: ЗП | F49: =Source!AO30 -> 11.02 | G49: 1,2*0,3 | H49: =Source!AV31 -> 1.087 | I49: =Source!S30 -> 4.31 | J49: =IF(Source!BA31<> 0, Source!BA31, 1) -> 56.35 | K49: =Source!S31 -> 242.87
C50: НР от ФОТ | D50: % | E50: =Source!BZ31 -> 95 | I50: =SUM(Q48:Q49) -> 4.09 | J50: =Source!AT31 -> 95 | K50: =SUM(R48:R49) -> 230.73
C51: СП от ФОТ | D51: % | E51: =Source!CA31 -> 53 | I51: =SUM(S48:S50) -> 2.28 | J51: =Source!AU31 -> 53 | K51: =SUM(T48:T50) -> 128.72
C52: ЗТР | D52: чел-ч | E52: =Source!AQ30 -> 0.8 | G52: 1,2*0,3 | H52: =Source!AV31 -> 1.087 | I52: =Source!U30 -> 0.313056
C53: ВСЕГО работ по позиции: | H53: =I49+I50+I51+0-0-0 -> 10.68 | J53: =K49+K50+K51+0-0-0 -> 602.32
C54: ВСЕГО оборудование по позиции: | H54: =0+0 -> 0 | J54: =0+0 -> 0
C55: ВСЕГО по позиции: | H55: =I49+I50+I51+0 -> 10.68 | J55: =K49+K50+K51+0 -> 602.32 | O55: =I49+I50+I51+0 -> 10.68 | P55: =K49+K50+K51+0 -> 602.32
A57: 3 | B57: =Source!F32 -> 4.8-240-4 | C57: Монтаж пультов и шкафов управления, шкафа (пульта) управления навесного, высотой, шириной, глубиной до 600х600х350 мм / демонтаж голосовой станции в металлическом шкафу | D57: =Source!H32 -> 1 ШТ. | E57: =Source!I32 -> 1 | Q57: =Source!X32 -> 10.94 | R57: =Source!X33 -> 616.56 | S57: =Source!Y32 -> 5.75 | T57: =Source!Y33 -> 324.17 | U57: =ROUND((175/100)*ROUND(Source!R32, 2), 2) -> 2.08 | V57: =ROUND((0/100)*ROUND(Source!R33, 2), 2) -> 0 | AC57: 0
C58: ЗП | F58: =Source!AO32 -> 26.76 | G58: 1,2*0,3 | H58: =Source!AV33 -> 1.047 | I58: =Source!S32 -> 10.09 | J58: =IF(Source!BA33<> 0, Source!BA33, 1) -> 56.35 | K58: =Source!S33 -> 568.57
C59: ЭМ | F59: =Source!AM32 -> 17.42 | G59: 1,2*0,3 | H59: =Source!AV33 -> 1.047 | I59: =Source!Q32 -> 6.57 | J59: =IF(Source!BB33<> 0, Source!BB33, 1) -> 19.89 | K59: =Source!Q33 -> 130.68
C60: в т.ч. ЗПМ | F60: =Source!AN32 -> 3.16 | G60: 1,2*0,3 | H60: =Source!AV33 -> 1.047 | I60: =Source!R32 -> 1.19 | J60: =IF(Source!BS33<> 0, Source!BS33, 1) -> 56.35 | K60: =Source!R33 -> 67.06
C61: НР от ФОТ | D61: % | E61: =Source!BZ33 -> 97 | I61: =SUM(Q57:Q60) -> 10.94 | J61: =Source!AT33 -> 97 | K61: =SUM(R57:R60) -> 616.56
C62: СП от ФОТ | D62: % | E62: =Source!CA33 -> 51 | I62: =SUM(S57:S61) -> 5.75 | J62: =Source!AU33 -> 51 | K62: =SUM(T57:T61) -> 324.17
C63: ЗТР | D63: чел-ч | E63: =Source!AQ32 -> 2.06 | G63: 1,2*0,3 | H63: =Source!AV33 -> 1.047 | I63: =Source!U32 -> 0.7764552
C64: ВСЕГО работ по позиции: | H64: =I58+I59+I61+I62+0-0-0 -> 33.35 | J64: =K58+K59+K61+K62+0-0-0 -> 1639.98
C65: ВСЕГО оборудование по позиции: | H65: =0+0 -> 0 | J65: =0+0 -> 0
C66: ВСЕГО по позиции: | H66: =I58+I59+I61+I62+0 -> 33.35 | J66: =K58+K59+K61+K62+0 -> 1639.98 | O66: =I58+I59+I61+I62+0 -> 33.35 | P66: =K58+K59+K61+K62+0 -> 1639.98
A68: 4 | B68: =Source!F34 -> 4.10-136-3 | C68: Монтаж антенного ТВ усилителя на мачте (без измерений) без повала мачты / демонтаж мачтового усилителя | D68: =Source!H34 -> 1 ШТ. | E68: =Source!I34 -> 1 | Q68: =Source!X34 -> 9.59 | R68: =Source!X35 -> 540.14 | S68: =Source!Y34 -> 5.35 | T68: =Source!Y35 -> 301.34 | U68: =ROUND((175/100)*ROUND(Source!R34, 2), 2) -> 0 | V68: =ROUND((0/100)*ROUND(Source!R35, 2), 2) -> 0 | AC68: 0
C69: ЗП | F69: =Source!AO34 -> 25.78 | G69: 1,2*0,3 | H69: =Source!AV35 -> 1.087 | I69: =Source!S34 -> 10.09 | J69: =IF(Source!BA35<> 0, Source!BA35, 1) -> 56.35 | K69: =Source!S35 -> 568.57
C70: НР от ФОТ | D70: % | E70: =Source!BZ35 -> 95 | I70: =SUM(Q68:Q69) -> 9.59 | J70: =Source!AT35 -> 95 | K70: =SUM(R68:R69) -> 540.14
C71: СП от ФОТ | D71: % | E71: =Source!CA35 -> 53 | I71: =SUM(S68:S70) -> 5.35 | J71: =Source!AU35 -> 53 | K71: =SUM(T68:T70) -> 301.34
C72: ЗТР | D72: чел-ч | E72: =Source!AQ34 -> 1.9 | G72: 1,2*0,3 | H72: =Source!AV35 -> 1.087 | I72: =Source!U34 -> 0.743508
C73: ВСЕГО работ по позиции: | H73: =I69+I70+I71+0-0-0 -> 25.03 | J73: =K69+K70+K71+0-0-0 -> 1410.05
C74: ВСЕГО оборудование по позиции: | H74: =0+0 -> 0 | J74: =0+0 -> 0
C75: ВСЕГО по позиции: | H75: =I69+I70+I71+0 -> 25.03 | J75: =K69+K70+K71+0 -> 1410.05 | O75: =I69+I70+I71+0 -> 25.03 | P75: =K69+K70+K71+0 -> 1410.05
A77: 5 | B77: =Source!F36 -> 4.10-136-4 | C77: Монтаж тв усилителя настенного типа, блока питания / демонтаж блока питания | D77: =Source!H36 -> 1 ШТ. | E77: =Source!I36 -> 1 | Q77: =Source!X36 -> 9.39 | R77: =Source!X37 -> 528.9 | S77: =Source!Y36 -> 5.24 | T77: =Source!Y37 -> 295.07 | U77: =ROUND((175/100)*ROUND(Source!R36, 2), 2) -> 0 | V77: =ROUND((0/100)*ROUND(Source!R37, 2), 2) -> 0 | AC77: 0
C78: ЗП | F78: =Source!AO36 -> 25.24 | G78: 1,2*0,3 | H78: =Source!AV37 -> 1.087 | I78: =Source!S36 -> 9.88 | J78: =IF(Source!BA37<> 0, Source!BA37, 1) -> 56.35 | K78: =Source!S37 -> 556.74
C79: НР от ФОТ | D79: % | E79: =Source!BZ37 -> 95 | I79: =SUM(Q77:Q78) -> 9.39 | J79: =Source!AT37 -> 95 | K79: =SUM(R77:R78) -> 528.9
C80: СП от ФОТ | D80: % | E80: =Source!CA37 -> 53 | I80: =SUM(S77:S79) -> 5.24 | J80: =Source!AU37 -> 53 | K80: =SUM(T77:T79) -> 295.07
C81: ЗТР | D81: чел-ч | E81: =Source!AQ36 -> 2 | G81: 1,2*0,3 | H81: =Source!AV37 -> 1.087 | I81: =Source!U36 -> 0.78264
C82: ВСЕГО работ по позиции: | H82: =I78+I79+I80+0-0-0 -> 24.51 | J82: =K78+K79+K80+0-0-0 -> 1380.71
C83: ВСЕГО оборудование по позиции: | H83: =0+0 -> 0 | J83: =0+0 -> 0
C84: ВСЕГО по позиции: | H84: =I78+I79+I80+0 -> 24.51 | J84: =K78+K79+K80+0 -> 1380.71 | O84: =I78+I79+I80+0 -> 24.51 | P84: =K78+K79+K80+0 -> 1380.71
A86: 6 | B86: =Source!F38 -> 4.10-136-1 | C86: Монтаж коробки телевизионной (ответвители, разветвители магистральные, домовые, абонентские), УСС, БФТК / демонтаж ответвителя | D86: =Source!H38 -> 1 ШТ. | E86: =Source!I38 -> 6 | Q86: =Source!X38 -> 24.58 | R86: =Source!X39 -> 1384.88 | S86: =Source!Y38 -> 13.71 | T86: =Source!Y39 -> 772.62 | U86: =ROUND((175/100)*ROUND(Source!R38, 2), 2) -> 0 | V86: =ROUND((0/100)*ROUND(Source!R39, 2), 2) -> 0 | AC86: 0
C87: ЗП | F87: =Source!AO38 -> 11.02 | G87: 1,2*0,3 | H87: =Source!AV39 -> 1.087 | I87: =Source!S38 -> 25.87 | J87: =IF(Source!BA39<> 0, Source!BA39, 1) -> 56.35 | K87: =Source!S39 -> 1457.77
C88: НР от ФОТ | D88: % | E88: =Source!BZ39 -> 95 | I88: =SUM(Q86:Q87) -> 24.58 | J88: =Source!AT39 -> 95 | K88: =SUM(R86:R87) -> 1384.88
C89: СП от ФОТ | D89: % | E89: =Source!CA39 -> 53 | I89: =SUM(S86:S88) -> 13.71 | J89: =Source!AU39 -> 53 | K89: =SUM(T86:T88) -> 772.62
C90: ЗТР | D90: чел-ч | E90: =Source!AQ38 -> 0.8 | G90: 1,2*0,3 | H90: =Source!AV39 -> 1.087 | I90: =Source!U38 -> 1.878336
C91: ВСЕГО работ по позиции: | H91: =I87+I88+I89+0-0-0 -> 64.16 | J91: =K87+K88+K89+0-0-0 -> 3615.27
C92: ВСЕГО оборудование по позиции: | H92: =0+0 -> 0 | J92: =0+0 -> 0
C93: ВСЕГО по позиции: | H93: =I87+I88+I89+0 -> 64.16 | J93: =K87+K88+K89+0 -> 3615.27 | O93: =I87+I88+I89+0 -> 64.16 | P93: =K87+K88+K89+0 -> 3615.27
A95: 7 | B95: =Source!F40 -> 6.67-7-1 | C95: Демонтаж осветительных приборов, выключатели, розетки | D95: =Source!H40 -> 100 шт. | E95: =Source!I40 -> 0.06 | Q95: =Source!X40 -> 4.1 | R95: =Source!X41 -> 230.76 | S95: =Source!Y40 -> 2.16 | T95: =Source!Y41 -> 121.72 | U95: =ROUND((175/100)*ROUND(Source!R40, 2), 2) -> 0 | V95: =ROUND((0/100)*ROUND(Source!R41, 2), 2) -> 0 | AC95: 0
C96: ="Объем: "&Source!I40&"=6/"&"100" -> Объем: 0,06=6/100
C97: ЗП | F97: =Source!AO40 -> 59.68 | G97: 1,2 | H97: =Source!AV41 -> 1.047 | I97: =Source!S40 -> 4.5 | J97: =IF(Source!BA41<> 0, Source!BA41, 1) -> 56.35 | K97: =Source!S41 -> 253.58
C98: НР от ФОТ | D98: % | E98: =Source!BZ41 -> 91 | I98: =SUM(Q95:Q97) -> 4.1 | J98: =Source!AT41 -> 91 | K98: =SUM(R95:R97) -> 230.76
C99: СП от ФОТ | D99: % | E99: =Source!CA41 -> 48 | I99: =SUM(S95:S98) -> 2.16 | J99: =Source!AU41 -> 48 | K99: =SUM(T95:T98) -> 121.72
C100: ЗТР | D100: чел-ч | E100: =Source!AQ40 -> 5.84 | G100: 1,2 | H100: =Source!AV41 -> 1.047 | I100: =Source!U40 -> 0.44024256
C101: ВСЕГО работ по позиции: | H101: =I97+I98+I99+0-0-0 -> 10.76 | J101: =K97+K98+K99+0-0-0 -> 606.06
C102: ВСЕГО оборудование по позиции: | H102: =0+0 -> 0 | J102: =0+0 -> 0
C103: ВСЕГО по позиции: | H103: =I97+I98+I99+0 -> 10.76 | J103: =K97+K98+K99+0 -> 606.06 | O103: =I97+I98+I99+0 -> 10.76 | P103: =K97+K98+K99+0 -> 606.06
A105: 8 | B105: =Source!F42 -> 6.67-6-1 | C105: Демонтаж кабеля | D105: =Source!H42 -> 100 м | E105: =Source!I42 -> 3.9 | Q105: =Source!X42 -> 439.29 | R105: =Source!X43 -> 24754.18 | S105: =Source!Y42 -> 231.72 | T105: =Source!Y43 -> 13057.15 | U105: =ROUND((175/100)*ROUND(Source!R42, 2), 2) -> 0 | V105: =ROUND((0/100)*ROUND(Source!R43, 2), 2) -> 0 | AC105: 0
C106: ="Объем: "&Source!I42&"=(80+"&"300+"&"10)/"&"100" -> Объем: 3,9=(80+300+10)/100
C107: ЗП | F107: =Source!AO42 -> 98.52 | G107: 1,2 | H107: =Source!AV43 -> 1.047 | I107: =Source!S42 -> 482.74 | J107: =IF(Source!BA43<> 0, Source!BA43, 1) -> 56.35 | K107: =Source!S43 -> 27202.4
C108: НР от ФОТ | D108: % | E108: =Source!BZ43 -> 91 | I108: =SUM(Q105:Q107) -> 439.29 | J108: =Source!AT43 -> 91 | K108: =SUM(R105:R107) -> 24754.18
C109: СП от ФОТ | D109: % | E109: =Source!CA43 -> 48 | I109: =SUM(S105:S108) -> 231.72 | J109: =Source!AU43 -> 48 | K109: =SUM(T105:T108) -> 13057.15
C110: ЗТР | D110: чел-ч | E110: =Source!AQ42 -> 9.64 | G110: 1,2 | H110: =Source!AV43 -> 1.047 | I110: =Source!U42 -> 47.235614
C111: ВСЕГО работ по позиции: | H111: =I107+I108+I109+0-0-0 -> 1153.75 | J111: =K107+K108+K109+0-0-0 -> 65013.73
C112: ВСЕГО оборудование по позиции: | H112: =0+0 -> 0 | J112: =0+0 -> 0
C113: ВСЕГО по позиции: | H113: =I107+I108+I109+0 -> 1153.75 | J113: =K107+K108+K109+0 -> 65013.73 | O113: =I107+I108+I109+0 -> 1153.75 | P113: =K107+K108+K109+0 -> 65013.73
A115: 9 | B115: =Source!F44 -> 6.67-5-12 | C115: Демонтаж трубных проводок, трубы в борозде диаметром 25 мм / ПВХ | D115: =Source!H44 -> 100 м | E115: =Source!I44 -> 2 | Q115: =Source!X44 -> 732.25 | R115: =Source!X45 -> 41262.27 | S115: =Source!Y44 -> 386.24 | T115: =Source!Y45 -> 21764.71 | U115: =ROUND((175/100)*ROUND(Source!R44, 2), 2) -> 0 | V115: =ROUND((0/100)*ROUND(Source!R45, 2), 2) -> 0 | AC115: 0
C116: ="Объем: "&Source!I44&"=200/"&"100" -> Объем: 2=200/100
C117: ЗП | F117: =Source!AO44 -> 320.23 | G117: 1,2 | H117: =Source!AV45 -> 1.047 | I117: =Source!S44 -> 804.67 | J117: =IF(Source!BA45<> 0, Source!BA45, 1) -> 56.35 | K117: =Source!S45 -> 45343.15
C118: НР от ФОТ | D118: % | E118: =Source!BZ45 -> 91 | I118: =SUM(Q115:Q117) -> 732.25 | J118: =Source!AT45 -> 91 | K118: =SUM(R115:R117) -> 41262.27
C119: СП от ФОТ | D119: % | E119: =Source!CA45 -> 48 | I119: =SUM(S115:S118) -> 386.24 | J119: =Source!AU45 -> 48 | K119: =SUM(T115:T118) -> 21764.71
...

Sheet Source
A1: 0 | B1: Smeta.RU (495) 974-1589 | D1: _PS_ | F1: 0 | G1: 0 | H1: 0 | I1: Smeta.RU | K1: 1 | L1: 74599 | M1: 10 | N1: 12 | O1: 1 | P1: 0 | Q1: 1
A4: 1 | B4: 1 | C4: -1 | G4: Капитальный ремонт здания Государственного бюджетного общеобразовательного учреждения города Москвы «Школа №1574», расположенного по адресу: г. Москва, Старопименовский переулок, д. 5. 1 этап | EC4: 0
A5: 8 | B5: 1 | C5: -1 | G5: Капитальный ремонт здания Государственного бюджетного общеобразовательного учреждения города Москвы «Школа №1574», расположенного по адресу: г. Москва, Старопименовский переулок, д. 5. 1 этап | EC5: 0
A12: 1 | B12: 354 | C12: 0 | D12: =ROW(A315) -> 315 | E12: 0 | F12: 02-01-12 | G12: 02-01-12 СКТ | I12: 0 | J12: 2024-00375-01-0-ИОС5.5 | K12: 0 | L12: 0 | M12: 4098 | O12: 0 | P12: 0 | Q12: 0 | R12: 0 | S12: 0 | T12: 1 | V12: 0 | BB12: 0 | BH12: Сметные нормы списания | BI12: Коды ОКП для ТСН-2001 МГЭ Дополнение 81 | BJ12: 1 | BK12: 1 | BL12: 0 | BM12: 0 | BN12: 1 | BO12: 0 | BP12: 6 | BQ12: 2 | BR12: 1 | BS12: 1 | BT12: 0 | BU12: 0 | BV12: 0 | BW12: 0 | BX12: 0 | BY12: ТСН-2001 (МГЭ) Доп 81 - Новое строительство | BZ12: Типовой расчет для ТСН-2001 МГЭ, Дополнение 81, строительство | CA12: Территориальные сметные нормативы для Москвы ТСН-2001 (МГЭ), дополнение 81 | CB12: Территориальные сметные нормативы для Москвы ТСН-2001 (МГЭ), дополнение 81 | CC12: Территориальные сметные нормативы для Москвы ТСН-2001 (МГЭ), дополнение 81 | CD12: Территориальные сметные нормативы для Москвы ТСН-2001 (МГЭ), дополнение 81 | CE12: Поправки для ТСН-2001 от 07.04.2026 г. доп.81 | CF12: 0 | CG12: 0 | CH12: 8200 | CK12: 81 | CQ12: Территориальные сметные нормативы для Москвы (ТСН-2001) | CR12: ТЕР | CS12: 41660 | CT12: 1 | CU12: 81 | CY12: 0 | EC12: 0
A15: 15 | B15: 1
A18: 52 | B18: =B315 -> 354 | C18: =C315 -> 1 | D18: =D315 -> 12 | E18: =E315 -> 0 | F18: =F315 -> 02-01-12 | G18: =G315 -> 02-01-12 СКТ | O18: =O315 -> 92685.73 | P18: =P315 -> 87368.36 | Q18: =Q315 -> 1518.75 | R18: =R315 -> 581.53 | S18: =S315 -> 3798.62 | T18: =T315 -> 0 | U18: =U315 -> 323.30434 | V18: =V315 -> 0 | ... GX18: =GX315 -> 0
A20: 3 | B20: 1 | D20: =ROW(A285) -> 285 | F20: 02-01-12 | G20: Система кабельного телевидения | I20: 0 | J20: 2024-00375-01-0-ИОС5.5 | K20: -1 | L20: 02-01-12 | S20: 0 | T20: 0 | V20: 0 | BX20: 0 | CF20: 0 | CG20: 0
A22: 52 | B22: =B285 -> 1 | C22: =C285 -> 3 | D22: =D285 -> 20 | E22: =E285 -> 0 | F22: =F285 -> 02-01-12 | G22: =G285 -> Система кабельного телевидения | O22: =O285 -> 92685.73 | P22: =P285 -> 87368.36 | Q22: =Q285 -> 1518.75 | R22: =R285 -> 581.53 | S22: =S285 -> 3798.62 | T22: =T285 -> 0 | U22: =U285 -> 323.30434 | V22: =V285 -> 0 | ... GX22: =GX285 -> 0
A24: 4 | B24: 1 | D24: =ROW(A49) -> 49 | F24: Новый раздел | G24: Демонтаж | I24: 0 | K24: 0 | S24: 0 | T24: 0 | V24: 0 | BX24: 0 | CJ24: 0
A26: 52 | B26: =B49 -> 1 | C26: =C49 -> 4 | D26: =D49 -> 24 | E26: =E49 -> 0 | F26: =F49 -> Новый раздел | G26: =G49 -> Демонтаж | O26: =O49 -> 1407.26 | P26: =P49 -> 0 | Q26: =Q49 -> 11.43 | R26: =R49 -> 1.28 | S26: =S49 -> 1395.83 | T26: =T49 -> 0 | U26: =U49 -> 131.88786 | V26: =V49 -> 0 | ... GX26: =GX49 -> 0
A28: 17 | B28: 1 | C28: =ROW(SmtRes!A2) -> 2 | D28: =ROW(EtalonRes!A2) -> 2 | E28: 1 | F28: 4.10-134-4 | G28: Монтаж антенны коллективной для приема ТВ на антенной опоре высотой до 9 м с одним ярусом оттяжек / демонтаж эфирной антенны | H28: 1 антенна | I28: 1 | J28: 0 | K28: 1 | O28: =ROUND(CP28,2) -> 29.8 | P28: =ROUND((ROUND((AC28*AW28*I28),2)*BC28),2) -> 0 | Q28: =(ROUND((ROUND(((((ET28*1.2)*0.3))*AV28*I28),2)*BB28),2)+ROUND((ROUND(((AE28-(((EU28*1.2)*0.3)))*AV28*I28),2)*BS28),2)) -> 0 | R28: =(ROUND((ROUND(((((EU28*1.2)*0.3))*AV28*I28),2)*BS28),2)+ROUND((ROUND(((AE28-(((EU28*1.2)*0.3)))*AV28*I28),2)*BS28),2)) -> 0 | S28: =ROUND((ROUND((AF28*AV28*I28),2)*BA28),2) -> 29.8 | T28: =ROUND(CU28*I28,2) -> 0 | U28: =CV28*I28 -> 2.1013884 | V28: =CW28*I28 -> 0 | W28: =ROUND(CX28*I28,2) -> 0 | X28: =(ROUND((((S28+ROUND((ROUND(((((EU28*1.2)*0.3))*AV28*I28),2)*BS28),2))*AT28)/100),2)+ROUND(((ROUND((ROUND(((AE28-(((EU28*1.2)*0.3)))*AV28*I28),2)*BS28),2)*AT28)/100),2)) -> 28.31 | Y28: =(ROUND((((S28+ROUND((ROUND(((((EU28*1.2)*0.3))*AV28*I28),2)*BS28),2))*AU28)/100),2)+ROUND(((ROUND((ROUND(((AE28-(((EU28*1.2)*0.3)))*AV28*I28),2)*BS28),2)*AU28)/100),2)) -> 15.79 | AA28: 55919547 | AB28: =ROUND((AC28+AD28+AF28),6) -> 27.414 | AC28: =ROUND((((ES28*1)*0)),6) -> 0 | AD28: =ROUND((((((ET28*1.2)*0.3))-(((EU28*1.2)*0.3)))+AE28),6) -> 0 | AE28: =ROUND((((EU28*1.2)*0.3)),6) -> 0 | AF28: =ROUND((((EV28*1.2)*0.3)),6) -> 27.414 | AG28: =ROUND((AP28),6) -> 0 | AH28: =(((EW28*1.2)*0.3)) -> 1.9332 | AI28: =(((EX28*1.2)*0.3)) -> 0 | AJ28: =(AS28) -> 0 | AK28: 76.52 | AL28: 0.37 | AM28: 0 | AN28: 0 | AO28: 76.15 | AP28: 0 | AQ28: 5.37 | AR28: 0 | AS28: 0 | AT28: 95 | AU28: 53 | AV28: 1.087 | AW28: 1 | AZ28: 1 | BA28: 1 | BB28: 1 | BC28: 1 | BH28: 0 | BI28: 2 | BJ28: ТСН-2001.4 Доп. 81, Сб. 10, т. 134, поз. 4 | BM28: 69 | BN28: 0 | BO28: 4.10-134-4 | BP28: 1 | BQ28: 40 | BR28: 0 | BS28: 1 | BT28: 1 | BU28: 1 | BV28: 1 | BW28: 1 | BX28: 1 | BZ28: 95 | CA28: 53 | CE28: 1566 | CF28: 0 | CG28: 0 | CM28: 0 | CN28: Поправка: Гл.12.Прил.8.п.8. 3_12.00.01.11.001 Наименование: При наличии напряженных и стесненных условий производства работ (стесненность, сложность складирования и транспортной логистики и т.п.) для объектов, расположенных в пределах круговой магистральной системы улиц "Садовое кольцо" города Москвы Поправка: Гл.4.Прил.2.2.п.2.2.29_04.00.01.35.003 Наименование: При демонтаже оборудования, предназначенного в лом | CO28: 0 | CP28: =(P28+Q28+S28) -> 29.8 | CQ28: =ROUND((ROUND((AC28*AW28*1),2)*BC28),2) -> 0 | CR28: =(ROUND((ROUND(((((ET28*1.2)*0.3))*AV28*1),2)*BB28),2)+ROUND((ROUND(((AE28-(((EU28*1.2)*0.3)))*AV28*1),2)*BS28),2)) -> 0 | CS28: =(ROUND((ROUND(((((EU28*1.2)*0.3))*AV28*1),2)*BS28),2)+ROUND((ROUND(((AE28-(((EU28*1.2)*0.3)))*AV28*1),2)*BS28),2)) -> 0 | CT28: =ROUND((ROUND((AF28*AV28*1),2)*BA28),2) -> 29.8 | CU28: =AG28 -> 0 | CV28: =(AH28*AV28) -> 2.1013884 | CW28: =AI28 -> 0 | CX28: =AJ28 -> 0 | CY28: =(ROUND((((S28+ROUND((ROUND(((((EU28*1.2)*0.3))*AV28*1),2)*BS28),2))*AT28)/100),2)+ROUND(((ROUND((ROUND(((AE28-(((EU28*1.2)*0.3)))*AV28*1),2)*BS28),2)*AT28)/100),2)) -> 28.31 | CZ28: =(ROUND((((S28+ROUND((ROUND(((((EU28*1.2)*0.3))*AV28*1),2)*BS28),2))*AU28)/100),2)+ROUND(((ROUND((ROUND(((AE28-(((EU28*1.2)*0.3)))*AV28*1),2)*BS28),2)*AU28)/100),2)) -> 15.79 | DB28: 1 | DD28: *1)*0 | DE28: *1,2)*0,3 | DF28: *1,2)*0,3 | DG28: *1,2)*0,3 | DI28: *1,2)*0,3 | DJ28: *1,2)*0,3 | DN28: 0 | DO28: 0 | DP28: 1 | DQ28: 1 | DU28: 1013 | DV28: 1 антенна | DW28: 1 антенна | DX28: 1 | EE28: 55393701 | EF28: 40 | EG28: Монтаж оборудования | EH28: 0 | EJ28: 2 | EK28: 69 | EL28: ТСН-2001.4-10. Монтаж радиотелевизионного и электронного оборудования | EM28: ТСН-2001.4-10-2 | EO28: Поправка: Гл.12.Прил.8.п.8. 3_12.00.01.11.001 Поправка: Гл.4.Прил.2.2.п.2.2.29_04.00.01.35.003 | EQ28: 0 | ER28: 76.52 | ES28: 0.37 | ET28: 0 | EU28: 0 | EV28: 76.15 | EW28: 5.37 | EX28: 0 | EY28: 0 | FQ28: 0 | FR28: 0 | FS28: 0 | FX28: 95 | FY28: 53 | GD28: 1 | GF28: 765739885 | GG28: 2 | GH28: 1 | GI28: 2 | GJ28: 0 | GK28: 0 | GL28: =ROUND(IF(AND(BH28=3,BI28=3,FS28<>0),P28,0),2) -> 0 | GM28: =ROUND(O28+X28+Y28,2)+GX28 -> 73.9 | GN28: =IF(OR(BI28=0,BI28=1),GM28-GX28,0) -> 0 | GO28: =IF(BI28=2,GM28-GX28,0) -> 73.9 | GP28: =IF(BI28=4,GM28-GX28,0) -> 0 | GR28: 0 | GS28: 3 | GT28: 0 | GV28: =ROUND((GT28),6) -> 0 | GW28: 1 | GX28: =ROUND(HC28*I28,2) -> 0 | HA28: 0 | HB28: 0 | HC28: =GV28*GW28 -> 0 | HS28: 0 | IK28: 0
A29: 17 | B29: 1 | C29: =ROW(SmtRes!A4) -> 4 | D29: =ROW(EtalonRes!A4) -> 4 | E29: 1 | F29: 4.10-134-4 | G29: Монтаж антенны коллективной для приема ТВ на антенной опоре высотой до 9 м с одним ярусом оттяжек / демонтаж эфирной антенны | H29: 1 антенна | I29: 1 | J29: 0 | K29: 1 | O29: =ROUND(CP29,2) -> 1679.23 | P29: =ROUND((ROUND((AC29*AW29*I29),2)*BC29),2) -> 0 | Q29: =(ROUND((ROUND(((((ET29*1.2)*0.3))*AV29*I29),2)*BB29),2)+ROUND((ROUND(((AE29-(((EU29*1.2)*0.3)))*AV29*I29),2)*BS29),2)) -> 0 | R29: =(ROUND((ROUND(((((EU29*1.2)*0.3))*AV29*I29),2)*BS29),2)+ROUND((ROUND(((AE29-(((EU29*1.2)*0.3)))*AV29*I29),2)*BS29),2)) -> 0 | S29: =ROUND((ROUND((AF29*AV29*I29),2)*BA29),2) -> 1679.23 | T29: =ROUND(CU29*I29,2) -> 0 | U29: =CV29*I29 -> 2.1013884 | V29: =CW29*I29 -> 0 | W29: =ROUND(CX29*I29,2) -> 0 | X29: =(ROUND((((S29+ROUND((ROUND(((((EU29*1.2)*0.3))*AV29*I29),2)*BS29),2))*AT29)/100),2)+ROUND(((ROUND((ROUND(((AE29-(((EU29*1.2)*0.3)))*AV29*I29),2)*BS29),2)*AT29)/100),2)) -> 1595.27 | Y29: =(ROUND((((S29+ROUND((ROUND(((((EU29*1.2)*0.3))*AV29*I29),2)*BS29),2))*AU29)/100),2)+ROUND(((ROUND((ROUND(((AE29-(((EU29*1.2)*0.3)))*AV29*I29),2)*BS29),2)*AU29)/100),2)) -> 889.99 | AA29: 55919549 | AB29: =ROUND((AC29+AD29+AF29),6) -> 27.414 | AC29: =ROUND((((ES29*1)*0)),6) -> 0 | AD29: =ROUND((((((ET29*1.2)*0.3))-(((EU29*1.2)*0.3)))+AE29),6) -> 0 | AE29: =ROUND((((EU29*1.2)*0.3)),6) -> 0 | AF29: =ROUND((((EV29*1.2)*0.3)),6) -> 27.414 | AG29: =ROUND((AP29),6) -> 0 | AH29: =(((EW29*1.2)*0.3)) -> 1.9332 | AI29: =(((EX29*1.2)*0.3)) -> 0 | AJ29: =(AS29) -> 0 | AK29: 76.52 | AL29: 0.37 | AM29: 0 | AN29: 0 | AO29: 76.15 | AP29: 0 | AQ29: 5.37 | AR29: 0 | AS29: 0 | AT29: 95 | AU29: 53 | AV29: 1.087 | AW29: 1 | AZ29: 1 | BA29: 56.35 | BB29: 1 | BC29: 5.46 | BH29: 0 | BI29: 2 | BJ29: ТСН-2001.4 Доп. 81, Сб. 10, т. 134, поз. 4 | BM29: 69 | BN29: 0 | BO29: 4.10-134-4 | BP29: 1 | BQ29: 40 | BR29: 0 | BS29: 56.35 | BT29: 1 | BU29: 1 | BV29: 1 | BW29: 1 | BX29: 1 | BZ29: 95 | CA29: 53 | CE29: 1566 | CF29: 0 | CG29: 0 | CM29: 0 | CN29: Поправка: Гл.12.Прил.8.п.8. 3_12.00.01.11.001 Наименование: При наличии напряженных и стесненных условий производства работ (стесненность, сложность складирования и транспортной логистики и т.п.) для объектов, расположенных в пределах круговой магистральной системы улиц "Садовое кольцо" города Москвы Поправка: Гл.4.Прил.2.2.п.2.2.29_04.00.01.35.003 Наименование: При демонтаже оборудования, предназначенного в лом | CO29: 0 | CP29: =(P29+Q29+S29) -> 1679.23 | CQ29: =ROUND((ROUND((AC29*AW29*1),2)*BC29),2) -> 0 | CR29: =(ROUND((ROUND(((((ET29*1.2)*0.3))*AV29*1),2)*BB29),2)+ROUND((ROUND(((AE29-(((EU29*1.2)*0.3)))*AV29*1),2)*BS29),2)) -> 0 | CS29: =(ROUND((ROUND(((((EU29*1.2)*0.3))*AV29*1),2)*BS29),2)+ROUND((ROUND(((AE29-(((EU29*1.2)*0.3)))*AV29*1),2)*BS29),2)) -> 0 | CT29: =ROUND((ROUND((AF29*AV29*1),2)*BA29),2) -> 1679.23 | CU29: =AG29 -> 0 | CV29: =(AH29*AV29) -> 2.1013884 | CW29: =AI29 -> 0 | CX29: =AJ29 -> 0 | CY29: =(ROUND((((S29+ROUND((ROUND(((((EU29*1.2)*0.3))*AV29*1),2)*BS29),2))*AT29)/100),2)+ROUND(((ROUND((ROUND(((AE29-(((EU29*1.2)*0.3)))*AV29*1),2)*BS29),2)*AT29)/100),2)) -> 1595.27 | CZ29: =(ROUND((((S29+ROUND((ROUND(((((EU29*1.2)*0.3))*AV29*1),2)*BS29),2))*AU29)/100),2)+ROUND(((ROUND((ROUND(((AE29-(((EU29*1.2)*0.3)))*AV29*1),2)*BS29),2)*AU29)/100),2)) -> 889.99 | DB29: 3 | DD29: *1)*0 | DE29: *1,2)*0,3 | DF29: *1,2)*0,3 | DG29: *1,2)*0,3 | DI29: *1,2)*0,3 | DJ29: *1,2)*0,3 | DN29: 0 | DO29: 0 | DP29: 1 | DQ29: 1 | DU29: 1013 | DV29: 1 антенна | DW29: 1 антенна | DX29: 1 | EE29: 55393701 | EF29: 40 | EG29: Монтаж оборудования | EH29: 0 | EJ29: 2 | EK29: 69 | EL29: ТСН-2001.4-10. Монтаж радиотелевизионного и электронного оборудования | EM29: ТСН-2001.4-10-2 | EO29: Поправка: Гл.12.Прил.8.п.8. 3_12.00.01.11.001 Поправка: Гл.4.Прил.2.2.п.2.2.29_04.00.01.35.003 | EQ29: 0 | ER29: 76.52 | ES29: 0.37 | ET29: 0 | EU29: 0 | EV29: 76.15 | EW29: 5.37 | EX29: 0 | EY29: 0 | FQ29: 0 | FR29: 0 | FS29: 0 | FX29: 95 | FY29: 53 | GD29: 1 | GF29: 765739885 | GG29: 2 | GH29: 1 | GI29: 2 | GJ29: 0 | GK29: 0 | GL29: =ROUND(IF(AND(BH29=3,BI29=3,FS29<>0),P29,0),2) -> 0 | GM29: =ROUND(O29+X29+Y29,2)+GX29 -> 4164.49 | GN29: =IF(OR(BI29=0,BI29=1),GM29-GX29,0) -> 0 | GO29: =IF(BI29=2,GM29-GX29,0) -> 4164.49 | GP29: =IF(BI29=4,GM29-GX29,0) -> 0 | GR29: 0 | GS29: 3 | GT29: 0 | GV29: =ROUND((GT29),6) -> 0 | GW29: 1 | GX29: =ROUND(HC29*I29,2) -> 0 | HA29: 0 | HB29: 0 | HC29: =GV29*GW29 -> 0 | HS29: 0 | IK29: 0
A30: 17 | B30: 1 | C30: =ROW(SmtRes!A6) -> 6 | D30: =ROW(EtalonRes!A6) -> 6 | E30: 2 | F30: 4.10-136-1 | G30: Монтаж коробки телевизионной (ответвители, разветвители магистральные, домовые, абонентские), УСС, БФТК / демонтаж грозозащиты | H30: 1 ШТ. | I30: 1 | J30: 0 | K30: 1 | O30: =ROUND(CP30,2) -> 4.31 | P30: =ROUND((ROUND((AC30*AW30*I30),2)*BC30),2) -> 0 | Q30: =(ROUND((ROUND(((((ET30*1.2)*0.3))*AV30*I30),2)*BB30),2)+ROUND((ROUND(((AE30-(((EU30*1.2)*0.3)))*AV30*I30),2)*BS30),2)) -> 0 | R30: =(ROUND((ROUND(((((EU30*1.2)*0.3))*AV30*I30),2)*BS30),2)+ROUND((ROUND(((AE30-(((EU30*1.2)*0.3)))*AV30*I30),2)*BS30),2)) -> 0 | S30: =ROUND((ROUND((AF30*AV30*I30),2)*BA30),2) -> 4.31 | T30: =ROUND(CU30*I30,2) -> 0 | U30: =CV30*I30 -> 0.313056 | V30: =CW30*I30 -> 0 | W30: =ROUND(CX30*I30,2) -> 0 | X30: =(ROUND((((S30+ROUND((ROUND(((((EU30*1.2)*0.3))*AV30*I30),2)*BS30),2))*AT30)/100),2)+ROUND(((ROUND((ROUND(((AE30-(((EU30*1.2)*0.3)))*AV30*I30),2)*BS30),2)*AT30)/100),2)) -> 4.09 | Y30: =(ROUND((((S30+ROUND((ROUND(((((EU30*1.2)*0.3))*AV30*I30),2)*BS30),2))*AU30)/100),2)+ROUND(((ROUND((ROUND(((AE30-(((EU30*1.2)*0.3)))*AV30*I30),2)*BS30),2)*AU30)/100),2)) -> 2.28 | AA30: 55919547 | AB30: =ROUND((AC30+AD30+AF30),6) -> 3.9672 | AC30: =ROUND((((ES30*1)*0)),6) -> 0 | AD30: =ROUND((((((ET30*1.2)*0.3))-(((EU30*1.2)*0.3)))+AE30),6) -> 0 | AE30: =ROUND((((EU30*1.2)*0.3)),6) -> 0 | AF30: =ROUND((((EV30*1.2)*0.3)),6) -> 3.9672 | AG30: =ROUND((AP30),6) -> 0 | AH30: =(((EW30*1.2)*0.3)) -> 0.288 | AI30: =(((EX30*1.2)*0.3)) -> 0 | AJ30: =(AS30) -> 0 | AK30: 11.32 | AL30: 0.3 | AM30: 0 | AN30: 0 | AO30: 11.02 | AP30: 0 | AQ30: 0.8 | AR30: 0 | AS30: 0 | AT30: 95 | AU30: 53 | AV30: 1.087 | AW30: 1 | AZ30: 1 | BA30: 1 | BB30: 1 | BC30: 1 | BH30: 0 | BI30: 2 | BJ30: ТСН-2001.4 Доп. 81, Сб. 10, т. 136, поз. 1 | BM30: 69 | BN30: 0 | BO30: 4.10-136-1 | BP30: 1 | BQ30: 40 | BR30: 0 | BS30: 1 | BT30: 1 | BU30: 1 | BV30: 1 | BW30: 1 | BX30: 1 | BZ30: 95 | CA30: 53 | CE30: 1566 | CF30: 0 | CG30: 0 | CM30: 0 | CN30: Поправка: Гл.12.Прил.8.п.8. 3_12.00.01.11.001 Наименование: При наличии напряженных и стесненных условий производства работ (стесненность, сложность складирования и транспортной логистики и т.п.) для объектов, расположенных в пределах круговой магистральной системы улиц "Садовое кольцо" города Москвы Поправка: Гл.4.Прил.2.2.п.2.2.29_04.00.01.35.003 Наименование: При демонтаже оборудования, предназначенного в лом | CO30: 0 | CP30: =(P30+Q30+S30) -> 4.31 | CQ30: =ROUND((ROUND((AC30*AW30*1),2)*BC30),2) -> 0 | CR30: =(ROUND((ROUND(((((ET30*1.2)*0.3))*AV30*1),2)*BB30),2)+ROUND((ROUND(((AE30-(((EU30*1.2)*0.3)))*AV30*1),2)*BS30),2)) -> 0 | CS30: =(ROUND((ROUND(((((EU30*1.2)*0.3))*AV30*1),2)*BS30),2)+ROUND((ROUND(((AE30-(((EU30*1.2)*0.3)))*AV30*1),2)*BS30),2)) -> 0 | CT30: =ROUND((ROUND((AF30*AV30*1),2)*BA30),2) -> 4.31 | CU30: =AG30 -> 0 | CV30: =(AH30*AV30) -> 0.313056 | CW30: =AI30 -> 0 | CX30: =AJ30 -> 0 | CY30: =(ROUND((((S30+ROUND((ROUND(((((EU30*1.2)*0.3))*AV30*1),2)*BS30),2))*AT30)/100),2)+ROUND(((ROUND((ROUND(((AE30-(((EU30*1.2)*0.3)))*AV30*1),2)*BS30),2)*AT30)/100),2)) -> 4.09 | CZ30: =(ROUND((((S30+ROUND((ROUND(((((EU30*1.2)*0.3))*AV30*1),2)*BS30),2))*AU30)/100),2)+ROUND(((ROUND((ROUND(((AE30-(((EU30*1.2)*0.3)))*AV30*1),2)*BS30),2)*AU30)/100),2)) -> 2.28 | DB30: 5 | DD30: *1)*0 | DE30: *1,2)*0,3 | DF30: *1,2)*0,3 | DG30: *1,2)*0,3 | DI30: *1,2)*0,3 | DJ30: *1,2)*0,3 | DN30: 0 | DO30: 0 | DP30: 1 | DQ30: 1 | DU30: 1013 | DV30: 1 ШТ. | DW30: 1 ШТ. | DX30: 1 | EE30: 55393701 | EF30: 40 | EG30: Монтаж оборудования | EH30: 0 | EJ30: 2 | EK30: 69 | EL30: ТСН-2001.4-10. Монтаж радиотелевизионного и электронного оборудования | EM30: ТСН-2001.4-10-2 | EO30: Поправка: Гл.12.Прил.8.п.8. 3_12.00.01.11.001 Поправка: Гл.4.Прил.2.2.п.2.2.29_04.00.01.35.003 | EQ30: 0 | ER30: 11.32 | ES30: 0.3 | ET30: 0 | EU30: 0 | EV30: 11.02 | EW30: 0.8 | EX30: 0 | EY30: 0 | FQ30: 0 | FR30: 0 | FS30: 0 | FX30: 95 | FY30: 53 | GD30: 1 | GF30: -843285439 | GG30: 2 | GH30: 1 | GI30: 2 | GJ30: 0 | GK30: 0 | GL30: =ROUND(IF(AND(BH30=3,BI30=3,FS30<>0),P30,0),2) -> 0 | GM30: =ROUND(O30+X30+Y30,2)+GX30 -> 10.68 | GN30: =IF(OR(BI30=0,BI30=1),GM30-GX30,0) -> 0 | GO30: =IF(BI30=2,GM30-GX30,0) -> 10.68 | GP30: =IF(BI30=4,GM30-GX30,0) -> 0 | GR30: 0 | GS30: 3 | GT30: 0 | GV30: =ROUND((GT30),6) -> 0 | GW30: 1 | GX30: =ROUND(HC30*I30,2) -> 0 | HA30: 0 | HB30: 0 | HC30: =GV30*GW30 -> 0 | HS30: 0 | IK30: 0
A31: 17 | B31: 1 | C31: =ROW(SmtRes!A8) -> 8 | D31: =ROW(EtalonRes!A8) -> 8 | E31: 2 | F31: 4.10-136-1 | G31: Монтаж коробки телевизионной (ответвители, разветвители магистральные, домовые, абонентские), УСС, БФТК / демонтаж грозозащиты | H31: 1 ШТ. | I31: 1 | J31: 0 | K31: 1 | O31: =ROUND(CP31,2) -> 242.87 | P31: =ROUND((ROUND((AC31*AW31*I31),2)*BC31),2) -> 0 | Q31: =(ROUND((ROUND(((((ET31*1.2)*0.3))*AV31*I31),2)*BB31),2)+ROUND((ROUND(((AE31-(((EU31*1.2)*0.3)))*AV31*I31),2)*BS31),2)) -> 0 | R31: =(ROUND((ROUND(((((EU31*1.2)*0.3))*AV31*I31),2)*BS31),2)+ROUND((ROUND(((AE31-(((EU31*1.2)*0.3)))*AV31*I31),2)*BS31),2)) -> 0 | S31: =ROUND((ROUND((AF31*AV31*I31),2)*BA31),2) -> 242.87 | T31: =ROUND(CU31*I31,2) -> 0 | U31: =CV31*I31 -> 0.313056 | V31: =CW31*I31 -> 0 | W31: =ROUND(CX31*I31,2) -> 0 | X31: =(ROUND((((S31+ROUND((ROUND(((((EU31*1.2)*0.3))*AV31*I31),2)*BS31),2))*AT31)/100),2)+ROUND(((ROUND((ROUND(((AE31-(((EU31*1.2)*0.3)))*AV31*I31),2)*BS31),2)*AT31)/100),2)) -> 230.73 | Y31: =(ROUND((((S31+ROUND((ROUND(((((EU31*1.2)*0.3))*AV31*I31),2)*BS31),2))*AU31)/100),2)+ROUND(((ROUND((ROUND(((AE31-(((EU31*1.2)*0.3)))*AV31*I31),2)*BS31),2)*AU31)/100),2)) -> 128.72 | AA31: 55919549 | AB31: =ROUND((AC31+AD31+AF31),6) -> 3.9672 | AC31: =ROUND((((ES31*1)*0)),6) -> 0 | AD31: =ROUND((((((ET31*1.2)*0.3))-(((EU31*1.2)*0.3)))+AE31),6) -> 0 | AE31: =ROUND((((EU31*1.2)*0.3)),6) -> 0 | AF31: =ROUND((((EV31*1.2)*0.3)),6) -> 3.9672 | AG31: =ROUND((AP31),6) -> 0 | AH31: =(((EW31*1.2)*0.3)) -> 0.288 | AI31: =(((EX31*1.2)*0.3)) -> 0 | AJ31: =(AS31) -> 0 | AK31: 11.32 | AL31: 0.3 | AM31: 0 | AN31: 0 | AO31: 11.02 | AP31: 0 | AQ31: 0.8 | AR31: 0 | AS31: 0 | AT31: 95 | AU31: 53 | AV31: 1.087 | AW31: 1 | AZ31: 1 | BA31: 56.35 | BB31: 1 | BC31: 7.37 | BH31: 0 | BI31: 2 | BJ31: ТСН-2001.4 Доп. 81, Сб. 10, т. 136, поз. 1 | BM31: 69 | BN31: 0 | BO31: 4.10-136-1 | BP31: 1 | BQ31: 40 | BR31: 0 | BS31: 56.35 | BT31: 1 | BU31: 1 | BV31: 1 | BW31: 1 | BX31: 1 | BZ31: 95 | CA31: 53 | CE31: 1566 | CF31: 0 | CG31: 0 | CM31: 0 | CN31: Поправка: Гл.12.Прил.8.п.8. 3_12.00.01.11.001 Наименование: При наличии напряженных и стесненных условий производства работ (стесненность, сложность складирования и транспортной логистики и т.п.) для объектов, расположенных в пределах круговой магистральной системы улиц "Садовое кольцо" города Москвы Поправка: Гл.4.Прил.2.2.п.2.2.29_04.00.01.35.003 Наименование: При демонтаже оборудования, предназначенного в лом | CO31: 0 | CP31: =(P31+Q31+S31) -> 242.87 | CQ31: =ROUND((ROUND((AC31*AW31*1),2)*BC31),2) -> 0 | CR31: =(ROUND((ROUND(((((ET31*1.2)*0.3))*AV31*1),2)*BB31),2)+ROUND((ROUND(((AE31-(((EU31*1.2)*0.3)))*AV31*1),2)*BS31),2)) -> 0 | CS31: =(ROUND((ROUND(((((EU31*1.2)*0.3))*AV31*1),2)*BS31),2)+ROUND((ROUND(((AE31-(((EU31*1.2)*0.3)))*AV31*1),2)*BS31),2)) -> 0 | CT31: =ROUND((ROUND((AF31*AV31*1),2)*BA31),2) -> 242.87 | CU31: =AG31 -> 0 | CV31: =(AH31*AV31) -> 0.313056 | CW31: =AI31 -> 0 | CX31: =AJ31 -> 0 | CY31: =(ROUND((((S31+ROUND((ROUND(((((EU31*1.2)*0.3))*AV31*1),2)*BS31),2))*AT31)/100),2)+ROUND(((ROUND((ROUND(((AE31-(((EU31*1.2)*0.3)))*AV31*1),2)*BS31),2)*AT31)/100),2)) -> 230.73 | CZ31: =(ROUND((((S31+ROUND((ROUND(((((EU31*1.2)*0.3))*AV31*1),2)*BS31),2))*AU31)/100),2)+ROUND(((ROUND((ROUND(((AE31-(((EU31*1.2)*0.3)))*AV31*1),2)*BS31),2)*AU31)/100),2)) -> 128.72 | DB31: 7 | DD31: *1)*0 | DE31: *1,2)*0,3 | DF31: *1,2)*0,3 | DG31: *1,2)*0,3 | DI31: *1,2)*0,3 | DJ31: *1,2)*0,3 | DN31: 0 | DO31: 0 | DP31: 1 | DQ31: 1 | DU31: 1013 | DV31: 1 ШТ. | DW31: 1 ШТ. | DX31: 1 | EE31: 55393701 | EF31: 40 | EG31: Монтаж оборудования | EH31: 0 | EJ31: 2 | EK31: 69 | EL31: ТСН-2001.4-10. Монтаж радиотелевизионного и электронного оборудования | EM31: ТСН-2001.4-10-2 | EO31: Поправка: Гл.12.Прил.8.п.8. 3_12.00.01.11.001 Поправка: Гл.4.Прил.2.2.п.2.2.29_04.00.01.35.003 | EQ31: 0 | ER31: 11.32 | ES31: 0.3 | ET31: 0 | EU31: 0 | EV31: 11.02 | EW31: 0.8 | EX31: 0 | EY31: 0 | FQ31: 0 | FR31: 0 | FS31: 0 | FX31: 95 | FY31: 53 | GD31: 1 | GF31: -843285439 | GG31: 2 | GH31: 1 | GI31: 2 | GJ31: 0 | GK31: 0 | GL31: =ROUND(IF(AND(BH31=3,BI31=3,FS31<>0),P31,0),2) -> 0 | GM31: =ROUND(O31+X31+Y31,2)+GX31 -> 602.32 | GN31: =IF(OR(BI31=0,BI31=1),GM31-GX31,0) -> 0 | GO31: =IF(BI31=2,GM31-GX31,0) -> 602.32 | GP31: =IF(BI31=4,GM31-GX31,0) -> 0 | GR31: 0 | GS31: 3 | GT31: 0 | GV31: =ROUND((GT31),6) -> 0 | GW31: 1 | GX31: =ROUND(HC31*I31,2) -> 0 | HA31: 0 | HB31: 0 | HC31: =GV31*GW31 -> 0 | HS31: 0 | IK31: 0
A32: 17 | B32: 1 | C32: =ROW(SmtRes!A15) -> 15 | D32: =ROW(EtalonRes!A17) -> 17 | E32: 3 | F32: 4.8-240-4 | G32: Монтаж пультов и шкафов управления, шкафа (пульта) управления навесного, высотой, шириной, глубиной до 600х600х350 мм / демонтаж голосовой станции в металлическом шкафу | H32: 1 ШТ. | I32: 1 | J32: 0 | K32: 1 | O32: =ROUND(CP32,2) -> 16.66 | P32: =ROUND((ROUND((AC32*AW32*I32),2)*BC32),2) -> 0 | Q32: =(ROUND((ROUND(((((ET32*1.2)*0.3))*AV32*I32),2)*BB32),2)+ROUND((ROUND(((AE32-(((EU32*1.2)*0.3)))*AV32*I32),2)*BS32),2)) -> 6.57 | R32: =(ROUND((ROUND(((((EU32*1.2)*0.3))*AV32*I32),2)*BS32),2)+ROUND((ROUND(((AE32-(((EU32*1.2)*0.3)))*AV32*I32),2)*BS32),2)) -> 1.19 | S32: =ROUND((ROUND((AF32*AV32*I32),2)*BA32),2) -> 10.09 | T32: =ROUND(CU32*I32,2) -> 0 | U32: =CV32*I32 -> 0.7764552 | V32: =CW32*I32 -> 0 | W32: =ROUND(CX32*I32,2) -> 0 | X32: =(ROUND((((S32+ROUND((ROUND(((((EU32*1.2)*0.3))*AV32*I32),2)*BS32),2))*AT32)/100),2)+ROUND(((ROUND((ROUND(((AE32-(((EU32*1.2)*0.3)))*AV32*I32),2)*BS32),2)*AT32)/100),2)) -> 10.94 | Y32: =(ROUND((((S32+ROUND((ROUND(((((EU32*1.2)*0.3))*AV32*I32),2)*BS32),2))*AU32)/100),2)+ROUND(((ROUND((ROUND(((AE32-(((EU32*1.2)*0.3)))*AV32*I32),2)*BS32),2)*AU32)/100),2)) -> 5.75 | AA32: 55919547 | AB32: =ROUND((AC32+AD32+AF32),6) -> 15.9048 | AC32: =ROUND((((ES32*1)*0)),6) -> 0 | AD32: =ROUND((((((ET32*1.2)*0.3))-(((EU32*1.2)*0.3)))+AE32),6) -> 6.2712 | AE32: =ROUND((((EU32*1.2)*0.3)),6) -> 1.1376 | AF32: =ROUND((((EV32*1.2)*0.3)),6) -> 9.6336 | AG32: =ROUND((AP32),6) -> 0 | AH32: =(((EW32*1.2)*0.3)) -> 0.7416 | AI32: =(((EX32*1.2)*0.3)) -> 0 | AJ32: =(AS32) -> 0 | AK32: 45.64 | AL32: 1.46 | AM32: 17.42 | AN32: 3.16 | AO32: 26.76 | AP32: 0 | AQ32: 2.06 | AR32: 0 | AS32: 0 | AT32: 97 | AU32: 51 | AV32: 1.047 | AW32: 1 | AZ32: 1 | BA32: 1 | BB32: 1 | BC32: 1 | BH32: 0 | BI32: 2 | BJ32: ТСН-2001.4 Доп. 80, Сб. 8, т. 240, поз. 4 | BM32: 67 | BN32: 0 | BO32: 4.8-240-4 | BP32: 1 | BQ32: 40 | BR32: 0 | BS32: 1 | BT32: 1 | BU32: 1 | BV32: 1 | BW32: 1 | BX32: 1 | BZ32: 97 | CA32: 51 | CE32: 1566 | CF32: 0 | CG32: 0 | CM32: 0 | CN32: Поправка: Гл.12.Прил.8.п.8. 3_12.00.01.11.001 Наименование: При наличии напряженных и стесненных условий производства работ (стесненность, сложность складирования и транспортной логистики и т.п.) для объектов, расположенных в пределах круговой магистральной системы улиц "Садовое кольцо" города Москвы Поправка: Гл.4.Прил.2.2.п.2.2.29_04.00.01.35.003 Наименование: При демонтаже оборудования, предназначенного в лом | CO32: 0 | CP32: =(P32+Q32+S32) -> 16.66 | CQ32: =ROUND((ROUND((AC32*AW32*1),2)*BC32),2) -> 0 | CR32: =(ROUND((ROUND(((((ET32*1.2)*0.3))*AV32*1),2)*BB32),2)+ROUND((ROUND(((AE32-(((EU32*1.2)*0.3)))*AV32*1),2)*BS32),2)) -> 6.57 | CS32: =(ROUND((ROUND(((((EU32*1.2)*0.3))*AV32*1),2)*BS32),2)+ROUND((ROUND(((AE32-(((EU32*1.2)*0.3)))*AV32*1),2)*BS32),2)) -> 1.19 | CT32: =ROUND((ROUND((AF32*AV32*1),2)*BA32),2) -> 10.09 | CU32: =AG32 -> 0 | CV32: =(AH32*AV32) -> 0.7764552 | CW32: =AI32 -> 0 | CX32: =AJ32 -> 0 | CY32: =(ROUND((((S32+ROUND((ROUND(((((EU32*1.2)*0.3))*AV32*1),2)*BS32),2))*AT32)/100),2)+ROUND(((ROUND((ROUND(((AE32-(((EU32*1.2)*0.3)))*AV32*1),2)*BS32),2)*AT32)/100),2)) -> 10.94 | CZ32: =(ROUND((((S32+ROUND((ROUND(((((EU32*1.2)*0.3))*AV32*1),2)*BS32),2))*AU32)/100),2)+ROUND(((ROUND((ROUND(((AE32-(((EU32*1.2)*0.3)))*AV32*1),2)*BS32),2)*AU32)/100),2)) -> 5.75 | DB32: 9 | DD32: *1)*0 | DE32: *1,2)*0,3 | DF32: *1,2)*0,3 | DG32: *1,2)*0,3 | DI32: *1,2)*0,3 | DJ32: *1,2)*0,3 | DN32: 0 | DO32: 0 | DP32: 1 | DQ32: 1 | DU32: 1013 | DV32: 1 ШТ. | DW32: 1 ШТ. | DX32: 1 | EE32: 55393699 | EF32: 40 | EG32: Монтаж оборудования | EH32: 0 | EJ32: 2 | EK32: 67 | EL32: ТСН-2001.4-8. Электротехнические установки | EM32: ТСН-2001.4-8-1 | EO32: Поправка: Гл.12.Прил.8.п.8. 3_12.00.01.11.001 Поправка: Гл.4.Прил.2.2.п.2.2.29_04.00.01.35.003 | EQ32: 0 | ER32: 45.64 | ES32: 1.46 | ET32: 17.42 | EU32: 3.16 | EV32: 26.76 | EW32: 2.06 | EX32: 0 | EY32: 0 | FQ32: 0 | FR32: 0 | FS32: 0 | FX32: 97 | FY32: 51 | GD32: 1 | GF32: 1257402012 | GG32: 2 | GH32: 1 | GI32: 2 | GJ32: 0 | GK32: 0 | GL32: =ROUND(IF(AND(BH32=3,BI32=3,FS32<>0),P32,0),2) -> 0 | GM32: =ROUND(O32+X32+Y32,2)+GX32 -> 33.35 | GN32: =IF(OR(BI32=0,BI32=1),GM32-GX32,0) -> 0 | GO32: =IF(BI32=2,GM32-GX32,0) -> 33.35 | GP32: =IF(BI32=4,GM32-GX32,0) -> 0 | GR32: 0 | GS32: 3 | GT32: 0 | GV32: =ROUND((GT32),6) -> 0 | GW32: 1 | GX32: =ROUND(HC32*I32,2) -> 0 | HA32: 0 | HB32: 0 | HC32: =GV32*GW32 -> 0 | HS32: 0 | IK32: 0
A33: 17 | B33: 1 | C33: =ROW(SmtRes!A22) -> 22 | D33: =ROW(EtalonRes!A26) -> 26 | E33: 3 | F33: 4.8-240-4 | G33: Монтаж пультов и шкафов управления, шкафа (пульта) управления навесного, высотой, шириной, глубиной до 600х600х350 мм / демонтаж голосовой станции в металлическом шкафу | H33: 1 ШТ. | I33: 1 | J33: 0 | K33: 1 | O33: =ROUND(CP33,2) -> 699.25 | P33: =ROUND((ROUND((AC33*AW33*I33),2)*BC33),2) -> 0 | Q33: =(ROUND((ROUND(((((ET33*1.2)*0.3))*AV33*I33),2)*BB33),2)+ROUND((ROUND(((AE33-(((EU33*1.2)*0.3)))*AV33*I33),2)*BS33),2)) -> 130.68 | R33: =(ROUND((ROUND(((((EU33*1.2)*0.3))*AV33*I33),2)*BS33),2)+ROUND((ROUND(((AE33-(((EU33*1.2)*0.3)))*AV33*I33),2)*BS33),2)) -> 67.06 | S33: =ROUND((ROUND((AF33*AV33*I33),2)*BA33),2) -> 568.57 | T33: =ROUND(CU33*I33,2) -> 0 | U33: =CV33*I33 -> 0.7764552 | V33: =CW33*I33 -> 0 | W33: =ROUND(CX33*I33,2) -> 0 | X33: =(ROUND((((S33+ROUND((ROUND(((((EU33*1.2)*0.3))*AV33*I33),2)*BS33),2))*AT33)/100),2)+ROUND(((ROUND((ROUND(((AE33-(((EU33*1.2)*0.3)))*AV33*I33),2)*BS33),2)*AT33)/100),2)) -> 616.56 | Y33: =(ROUND((((S33+ROUND((ROUND(((((EU33*1.2)*0.3))*AV33*I33),2)*BS33),2))*AU33)/100),2)+ROUND(((ROUND((ROUND(((AE33-(((EU33*1.2)*0.3)))*AV33*I33),2)*BS33),2)*AU33)/100),2)) -> 324.17 | AA33: 55919549 | AB33: =ROUND((AC33+AD33+AF33),6) -> 15.9048 | AC33: =ROUND((((ES33*1)*0)),6) -> 0 | AD33: =ROUND((((((ET33*1.2)*0.3))-(((EU33*1.2)*0.3)))+AE33),6) -> 6.2712 | AE33: =ROUND((((EU33*1.2)*0.3)),6) -> 1.1376 | AF33: =ROUND((((EV33*1.2)*0.3)),6) -> 9.6336 | AG33: =ROUND((AP33),6) -> 0 | AH33: =(((EW33*1.2)*0.3)) -> 0.7416 | AI33: =(((EX33*1.2)*0.3)) -> 0 | AJ33: =(AS33) -> 0 | AK33: 45.64 | AL33: 1.46 | AM33: 17.42 | AN33: 3.16 | AO33: 26.76 | AP33: 0 | AQ33: 2.06 | AR33: 0 | AS33: 0 | AT33: 97 | AU33: 51 | AV33: 1.047 | AW33: 1 | AZ33: 1 | BA33: 56.35 | BB33: 19.89 | BC33: 11.05 | BH33: 0 | BI33: 2 | BJ33: ТСН-2001.4 Доп. 80, Сб. 8, т. 240, поз. 4 | BM33: 67 | BN33: 0 | BO33: 4.8-240-4 | BP33: 1 | BQ33: 40 | BR33: 0 | BS33: 56.35 | BT33: 1 | BU33: 1 | BV33: 1 | BW33: 1 | BX33: 1 | BZ33: 97 | CA33: 51 | CE33: 1566 | CF33: 0 | CG33: 0 | CM33: 0 | CN33: Поправка: Гл.12.Прил.8.п.8. 3_12.00.01.11.001 Наименование: При наличии напряженных и стесненных условий производства работ (стесненность, сложность складирования и транспортной логистики и т.п.) для объектов, расположенных в пределах круговой магистральной системы улиц "Садовое кольцо" города Москвы Поправка: Гл.4.Прил.2.2.п.2.2.29_04.00.01.35.003 Наименование: При демонтаже оборудования, предназначенного в лом | CO33: 0 | CP33: =(P33+Q33+S33) -> 699.25 | CQ33: =ROUND((ROUND((AC33*AW33*1),2)*BC33),2) -> 0 | CR33: =(ROUND((ROUND(((((ET33*1.2)*0.3))*AV33*1),2)*BB33),2)+ROUND((ROUND(((AE33-(((EU33*1.2)*0.3)))*AV33*1),2)*BS33),2)) -> 130.68 | CS33: =(ROUND((ROUND(((((EU33*1.2)*0.3))*AV33*1),2)*BS33),2)+ROUND((ROUND(((AE33-(((EU33*1.2)*0.3)))*AV33*1),2)*BS33),2)) -> 67.06 | CT33: =ROUND((ROUND((AF33*AV33*1),2)*BA33),2) -> 568.57 | CU33: =AG33 -> 0 | CV33: =(AH33*AV33) -> 0.7764552 | CW33: =AI33 -> 0 | CX33: =AJ33 -> 0 | CY33: =(ROUND((((S33+ROUND((ROUND(((((EU33*1.2)*0.3))*AV33*1),2)*BS33),2))*AT33)/100),2)+ROUND(((ROUND((ROUND(((AE33-(((EU33*1.2)*0.3)))*AV33*1),2)*BS33),2)*AT33)/100),2)) -> 616.56 | CZ33: =(ROUND((((S33+ROUND((ROUND(((((EU33*1.2)*0.3))*AV33*1),2)*BS33),2))*AU33)/100),2)+ROUND(((ROUND((ROUND(((AE33-(((EU33*1.2)*0.3)))*AV33*1),2)*BS33),2)*AU33)/100),2)) -> 324.17 | DB33: 11 | DD33: *1)*0 | DE33: *1,2)*0,3 | DF33: *1,2)*0,3 | DG33: *1,2)*0,3 | DI33: *1,2)*0,3 | DJ33: *1,2)*0,3 | DN33: 0 | DO33: 0 | DP33: 1 | DQ33: 1 | DU33: 1013 | DV33: 1 ШТ. | DW33: 1 ШТ. | DX33: 1 | EE33: 55393699 | EF33: 40 | EG33: Монтаж оборудования | EH33: 0 | EJ33: 2 | EK33: 67 | EL33: ТСН-2001.4-8. Электротехнические установки | EM33: ТСН-2001.4-8-1 | EO33: Поправка: Гл.12.Прил.8.п.8. 3_12.00.01.11.001 Поправка: Гл.4.Прил.2.2.п.2.2.29_04.00.01.35.003 | EQ33: 0 | ER33: 45.64 | ES33: 1.46 | ET33: 17.42 | EU33: 3.16 | EV33: 26.76 | EW33: 2.06 | EX33: 0 | EY33: 0 | FQ33: 0 | FR33: 0 | FS33: 0 | FX33: 97 | FY33: 51 | GD33: 1 | GF33: 1257402012 | GG33: 2 | GH33: 1 | GI33: 2 | GJ33: 0 | GK33: 0 | GL33: =ROUND(IF(AND(BH33=3,BI33=3,FS33<>0),P33,0),2) -> 0 | GM33: =ROUND(O33+X33+Y33,2)+GX33 -> 1639.98 | GN33: =IF(OR(BI33=0,BI33=1),GM33-GX33,0) -> 0 | GO33: =IF(BI33=2,GM33-GX33,0) -> 1639.98 | GP33: =IF(BI33=4,GM33-GX33,0) -> 0 | GR33: 0 | GS33: 3 | GT33: 0 | GV33: =ROUND((GT33),6) -> 0 | GW33: 1 | GX33: =ROUND(HC33*I33,2) -> 0 | HA33: 0 | HB33: 0 | HC33: =GV33*GW33 -> 0 | HS33: 0 | IK33: 0
A34: 17 | B34: 1 | C34: =ROW(SmtRes!A24) -> 24 | D34: =ROW(EtalonRes!A28) -> 28 | E34: 4 | F34: 4.10-136-3 | G34: Монтаж антенного ТВ усилителя на мачте (без измерений) без повала мачты / демонтаж мачтового усилителя | H34: 1 ШТ. | I34: 1 | J34: 0 | K34: 1 | O34: =ROUND(CP34,2) -> 10.09 | P34: =ROUND((ROUND((AC34*AW34*I34),2)*BC34),2) -> 0 | Q34: =(ROUND((ROUND(((((ET34*1.2)*0.3))*AV34*I34),2)*BB34),2)+ROUND((ROUND(((AE34-(((EU34*1.2)*0.3)))*AV34*I34),2)*BS34),2)) -> 0 | R34: =(ROUND((ROUND(((((EU34*1.2)*0.3))*AV34*I34),2)*BS34),2)+ROUND((ROUND(((AE34-(((EU34*1.2)*0.3)))*AV34*I34),2)*BS34),2)) -> 0 | S34: =ROUND((ROUND((AF34*AV34*I34),2)*BA34),2) -> 10.09 | T34: =ROUND(CU34*I34,2) -> 0 | U34: =CV34*I34 -> 0.743508 | V34: =CW34*I34 -> 0 | W34: =ROUND(CX34*I34,2) -> 0 | X34: =(ROUND((((S34+ROUND((ROUND(((((EU34*1.2)*0.3))*AV34*I34),2)*BS34),2))*AT34)/100),2)+ROUND(((ROUND((ROUND(((AE34-(((EU34*1.2)*0.3)))*AV34*I34),2)*BS34),2)*AT34)/100),2)) -> 9.59 | Y34: =(ROUND((((S34+ROUND((ROUND(((((EU34*1.2)*0.3))*AV34*I34),2)*BS34),2))*AU34)/100),2)+ROUND(((ROUND((ROUND(((AE34-(((EU34*1.2)*0.3)))*AV34*I34),2)*BS34),2)*AU34)/100),2)) -> 5.35 | AA34: 55919547 | AB34: =ROUND((AC34+AD34+AF34),6) -> 9.2808 | AC34: =ROUND((((ES34*1)*0)),6) -> 0 | AD34: =ROUND((((((ET34*1.2)*0.3))-(((EU34*1.2)*0.3)))+AE34),6) -> 0 | AE34: =ROUND((((EU34*1.2)*0.3)),6) -> 0 | AF34: =ROUND((((EV34*1.2)*0.3)),6) -> 9.2808 | AG34: =ROUND((AP34),6) -> 0 | AH34: =(((EW34*1.2)*0.3)) -> 0.684 | AI34: =(((EX34*1.2)*0.3)) -> 0 | AJ34: =(AS34) -> 0 | AK34: 25.96 | AL34: 0.18 | AM34: 0 | AN34: 0 | AO34: 25.78 | AP34: 0 | AQ34: 1.9 | AR34: 0 | AS34: 0 | AT34: 95 | AU34: 53 | AV34: 1.087 | AW34: 1 | AZ34: 1 | BA34: 1 | BB34: 1 | BC34: 1 | BH34: 0 | BI34: 2 | BJ34: ТСН-2001.4 Доп. 81, Сб. 10, т. 136, поз. 3 | BM34: 69 | BN34: 0 | BO34: 4.10-136-3 | BP34: 1 | BQ34: 40 | BR34: 0 | BS34: 1 | BT34: 1 | BU34: 1 | BV34: 1 | BW34: 1 | BX34: 1 | BZ34: 95 | CA34: 53 | CE34: 1566 | CF34: 0 | CG34: 0 | CM34: 0 | CN34: Поправка: Гл.12.Прил.8.п.8. 3_12.00.01.11.001 Наименование: При наличии напряженных и стесненных условий производства работ (стесненность, сложность складирования и транспортной логистики и т.п.) для объектов, расположенных в пределах круговой магистральной системы улиц "Садовое кольцо" города Москвы Поправка: Гл.4.Прил.2.2.п.2.2.29_04.00.01.35.003 Наименование: При демонтаже оборудования, предназначенного в лом | CO34: 0 | CP34: =(P34+Q34+S34) -> 10.09 | CQ34: =ROUND((ROUND((AC34*AW34*1),2)*BC34),2) -> 0 | CR34: =(ROUND((ROUND(((((ET34*1.2)*0.3))*AV34*1),2)*BB34),2)+ROUND((ROUND(((AE34-(((EU34*1.2)*0.3)))*AV34*1),2)*BS34),2)) -> 0 | CS34: =(ROUND((ROUND(((((EU34*1.2)*0.3))*AV34*1),2)*BS34),2)+ROUND((ROUND(((AE34-(((EU34*1.2)*0.3)))*AV34*1),2)*BS34),2)) -> 0 | CT34: =ROUND((ROUND((AF34*AV34*1),2)*BA34),2) -> 10.09 | CU34: =AG34 -> 0 | CV34: =(AH34*AV34) -> 0.743508 | CW34: =AI34 -> 0 | CX34: =AJ34 -> 0 | CY34: =(ROUND((((S34+ROUND((ROUND(((((EU34*1.2)*0.3))*AV34*1),2)*BS34),2))*AT34)/100),2)+ROUND(((ROUND((ROUND(((AE34-(((EU34*1.2)*0.3)))*AV34*1),2)*BS34),2)*AT34)/100),2)) -> 9.59 | CZ34: =(ROUND((((S34+ROUND((ROUND(((((EU34*1.2)*0.3))*AV34*1),2)*BS34),2))*AU34)/100),2)+ROUND(((ROUND((ROUND(((AE34-(((EU34*1.2)*0.3)))*AV34*1),2)*BS34),2)*AU34)/100),2)) -> 5.35 | DB34: 13 | DD34: *1)*0 | DE34: *1,2)*0,3 | DF34: *1,2)*0,3 | DG34: *1,2)*0,3 | DI34: *1,2)*0,3 | DJ34: *1,2)*0,3 | DN34: 0 | DO34: 0 | DP34: 1 | DQ34: 1 | DU34: 1013 | DV34: 1 ШТ. | DW34: 1 ШТ. | DX34: 1 | EE34: 55393701 | EF34: 40 | EG34: Монтаж оборудования | EH34: 0 | EJ34: 2 | EK34: 69 | EL34: ТСН-2001.4-10. Монтаж радиотелевизионного и электронного оборудования | EM34: ТСН-2001.4-10-2 | EO34: Поправка: Гл.12.Прил.8.п.8. 3_12.00.01.11.001 Поправка: Гл.4.Прил.2.2.п.2.2.29_04.00.01.35.003 | EQ34: 0 | ER34: 25.96 | ES34: 0.18 | ET34: 0 | EU34: 0 | EV34: 25.78 | EW34: 1.9 | EX34: 0 | EY34: 0 | FQ34: 0 | FR34: 0 | FS34: 0 | FX34: 95 | FY34: 53 | GD34: 1 | GF34: 1660434457 | GG34: 2 | GH34: 1 | GI34: 2 | GJ34: 0 | GK34: 0 | GL34: =ROUND(IF(AND(BH34=3,BI34=3,FS34<>0),P34,0),2) -> 0 | GM34: =ROUND(O34+X34+Y34,2)+GX34 -> 25.03 | GN34: =IF(OR(BI34=0,BI34=1),GM34-GX34,0) -> 0 | GO34: =IF(BI34=2,GM34-GX34,0) -> 25.03 | GP34: =IF(BI34=4,GM34-GX34,0) -> 0 | GR34: 0 | GS34: 3 | GT34: 0 | GV34: =ROUND((GT34),6) -> 0 | GW34: 1 | GX34: =ROUND(HC34*I34,2) -> 0 | HA34: 0 | HB34: 0 | HC34: =GV34*GW34 -> 0 | HS34: 0 | IK34: 0
A35: 17 | B35: 1 | C35: =ROW(SmtRes!A26) -> 26 | D35: =ROW(EtalonRes!A30) -> 30 | E35: 4 | F35: 4.10-136-3 | G35: Монтаж антенного ТВ усилителя на мачте (без измерений) без повала мачты / демонтаж мачтового усилителя | H35: 1 ШТ. | I35: 1 | J35: 0 | K35: 1 | O35: =ROUND(CP35,2) -> 568.57 | P35: =ROUND((ROUND((AC35*AW35*I35),2)*BC35),2) -> 0 | Q35: =(ROUND((ROUND(((((ET35*1.2)*0.3))*AV35*I35),2)*BB35),2)+ROUND((ROUND(((AE35-(((EU35*1.2)*0.3)))*AV35*I35),2)*BS35),2)) -> 0 | R35: =(ROUND((ROUND(((((EU35*1.2)*0.3))*AV35*I35),2)*BS35),2)+ROUND((ROUND(((AE35-(((EU35*1.2)*0.3)))*AV35*I35),2)*BS35),2)) -> 0 | S35: =ROUND((ROUND((AF35*AV35*I35),2)*BA35),2) -> 568.57 | T35: =ROUND(CU35*I35,2) -> 0 | U35: =CV35*I35 -> 0.743508 | V35: =CW35*I35 -> 0 | W35: =ROUND(CX35*I35,2) -> 0 | X35: =(ROUND((((S35+ROUND((ROUND(((((EU35*1.2)*0.3))*AV35*I35),2)*BS35),2))*AT35)/100),2)+ROUND(((ROUND((ROUND(((AE35-(((EU35*1.2)*0.3)))*AV35*I35),2)*BS35),2)*AT35)/100),2)) -> 540.14 | Y35: =(ROUND((((S35+ROUND((ROUND(((((EU35*1.2)*0.3))*AV35*I35),2)*BS35),2))*AU35)/100),2)+ROUND(((ROUND((ROUND(((AE35-(((EU35*1.2)*0.3)))*AV35*I35),2)*BS35),2)*AU35)/100),2)) -> 301.34 | AA35: 55919549 | AB35: =ROUND((AC35+AD35+AF35),6) -> 9.2808 | AC35: =ROUND((((ES35*1)*0)),6) -> 0 | AD35: =ROUND((((((ET35*1.2)*0.3))-(((EU35*1.2)*0.3)))+AE35),6) -> 0 | AE35: =ROUND((((EU35*1.2)*0.3)),6) -> 0 | AF35: =ROUND((((EV35*1.2)*0.3)),6) -> 9.2808 | AG35: =ROUND((AP35),6) -> 0 | AH35: =(((EW35*1.2)*0.3)) -> 0.684 | AI35: =(((EX35*1.2)*0.3)) -> 0 | AJ35: =(AS35) -> 0 | AK35: 25.96 | AL35: 0.18 | AM35: 0 | AN35: 0 | AO35: 25.78 | AP35: 0 | AQ35: 1.9 | AR35: 0 | AS35: 0 | AT35: 95 | AU35: 53 | AV35: 1.087 | AW35: 1 | AZ35: 1 | BA35: 56.35 | BB35: 1 | BC35: 5.61 | BH35: 0 | BI35: 2 | BJ35: ТСН-2001.4 Доп. 81, Сб. 10, т. 136, поз. 3 | BM35: 69 | BN35: 0 | BO35: 4.10-136-3 | BP35: 1 | BQ35: 40 | BR35: 0 | BS35: 56.35 | BT35: 1 | BU35: 1 | BV35: 1 | BW35: 1 | BX35: 1 | BZ35: 95 | CA35: 53 | CE35: 1566 | CF35: 0 | CG35: 0 | CM35: 0 | CN35: Поправка: Гл.12.Прил.8.п.8. 3_12.00.01.11.001 Наименование: При наличии напряженных и стесненных условий производства работ (стесненность, сложность складирования и транспортной логистики и т.п.) для объектов, расположенных в пределах круговой магистральной системы улиц "Садовое кольцо" города Москвы Поправка: Гл.4.Прил.2.2.п.2.2.29_04.00.01.35.003 Наименование: При демонтаже оборудования, предназначенного в лом | CO35: 0 | CP35: =(P35+Q35+S35) -> 568.57 | CQ35: =ROUND((ROUND((AC35*AW35*1),2)*BC35),2) -> 0 | CR35: =(ROUND((ROUND(((((ET35*1.2)*0.3))*AV35*1),2)*BB35),2)+ROUND((ROUND(((AE35-(((EU35*1.2)*0.3)))*AV35*1),2)*BS35),2)) -> 0 | CS35: =(ROUND((ROUND(((((EU35*1.2)*0.3))*AV35*1),2)*BS35),2)+ROUND((ROUND(((AE35-(((EU35*1.2)*0.3)))*AV35*1),2)*BS35),2)) -> 0 | CT35: =ROUND((ROUND((AF35*AV35*1),2)*BA35),2) -> 568.57 | CU35: =AG35 -> 0 | CV35: =(AH35*AV35) -> 0.743508 | CW35: =AI35 -> 0 | CX35: =AJ35 -> 0 | CY35: =(ROUND((((S35+ROUND((ROUND(((((EU35*1.2)*0.3))*AV35*1),2)*BS35),2))*AT35)/100),2)+ROUND(((ROUND((ROUND(((AE35-(((EU35*1.2)*0.3)))*AV35*1),2)*BS35),2)*AT35)/100),2)) -> 540.14 | CZ35: =(ROUND((((S35+ROUND((ROUND(((((EU35*1.2)*0.3))*AV35*1),2)*BS35),2))*AU35)/100),2)+ROUND(((ROUND((ROUND(((AE35-(((EU35*1.2)*0.3)))*AV35*1),2)*BS35),2)*AU35)/100),2)) -> 301.34 | DB35: 15 | DD35: *1)*0 | DE35: *1,2)*0,3 | DF35: *1,2)*0,3 | DG35: *1,2)*0,3 | DI35: *1,2)*0,3 | DJ35: *1,2)*0,3 | DN35: 0 | DO35: 0 | DP35: 1 | DQ35: 1 | DU35: 1013 | DV35: 1 ШТ. | DW35: 1 ШТ. | DX35: 1 | EE35: 55393701 | EF35: 40 | EG35: Монтаж оборудования | EH35: 0 | EJ35: 2 | EK35: 69 | EL35: ТСН-2001.4-10. Монтаж радиотелевизионного и электронного оборудования | EM35: ТСН-2001.4-10-2 | EO35: Поправка: Гл.12.Прил.8.п.8. 3_12.00.01.11.001 Поправка: Гл.4.Прил.2.2.п.2.2.29_04.00.01.35.003 | EQ35: 0 | ER35: 25.96 | ES35: 0.18 | ET35: 0 | EU35: 0 | EV35: 25.78 | EW35: 1.9 | EX35: 0 | EY35: 0 | FQ35: 0 | FR35: 0 | FS35: 0 | FX35: 95 | FY35: 53 | GD35: 1 | GF35: 1660434457 | GG35: 2 | GH35: 1 | GI35: 2 | GJ35: 0 | GK35: 0 | GL35: =ROUND(IF(AND(BH35=3,BI35=3,FS35<>0),P35,0),2) -> 0 | GM35: =ROUND(O35+X35+Y35,2)+GX35 -> 1410.05 | GN35: =IF(OR(BI35=0,BI35=1),GM35-GX35,0) -> 0 | GO35: =IF(BI35=2,GM35-GX35,0) -> 1410.05 | GP35: =IF(BI35=4,GM35-GX35,0) -> 0 | GR35: 0 | GS35: 3 | GT35: 0 | GV35: =ROUND((GT35),6) -> 0 | GW35: 1 | GX35: =ROUND(HC35*I35,2) -> 0 | HA35: 0 | HB35: 0 | HC35: =GV35*GW35 -> 0 | HS35: 0 | IK35: 0
A36: 17 | B36: 1 | C36: =ROW(SmtRes!A28) -> 28 | D36: =ROW(EtalonRes!A32) -> 32 | E36: 5 | F36: 4.10-136-4 | G36: Монтаж тв усилителя настенного типа, блока питания / демонтаж блока питания | H36: 1 ШТ. | I36: 1 | J36: 0 | K36: 1 | O36: =ROUND(CP36,2) -> 9.88 | P36: =ROUND((ROUND((AC36*AW36*I36),2)*BC36),2) -> 0 | Q36: =(ROUND((ROUND(((((ET36*1.2)*0.3))*AV36*I36),2)*BB36),2)+ROUND((ROUND(((AE36-(((EU36*1.2)*0.3)))*AV36*I36),2)*BS36),2)) -> 0 | R36: =(ROUND((ROUND(((((EU36*1.2)*0.3))*AV36*I36),2)*BS36),2)+ROUND((ROUND(((AE36-(((EU36*1.2)*0.3)))*AV36*I36),2)*BS36),2)) -> 0 | S36: =ROUND((ROUND((AF36*AV36*I36),2)*BA36),2) -> 9.88 | T36: =ROUND(CU36*I36,2) -> 0 | U36: =CV36*I36 -> 0.78264 | V36: =CW36*I36 -> 0 | W36: =ROUND(CX36*I36,2) -> 0 | X36: =(ROUND((((S36+ROUND((ROUND(((((EU36*1.2)*0.3))*AV36*I36),2)*BS36),2))*AT36)/100),2)+ROUND(((ROUND((ROUND(((AE36-(((EU36*1.2)*0.3)))*AV36*I36),2)*BS36),2)*AT36)/100),2)) -> 9.39 | Y36: =(ROUND((((S36+ROUND((ROUND(((((EU36*1.2)*0.3))*AV36*I36),2)*BS36),2))*AU36)/100),2)+ROUND(((ROUND((ROUND(((AE36-(((EU36*1.2)*0.3)))*AV36*I36),2)*BS36),2)*AU36)/100),2)) -> 5.24 | AA36: 55919547 | AB36: =ROUND((AC36+AD36+AF36),6) -> 9.0864 | AC36: =ROUND((((ES36*1)*0)),6) -> 0 | AD36: =ROUND((((((ET36*1.2)*0.3))-(((EU36*1.2)*0.3)))+AE36),6) -> 0 | AE36: =ROUND((((EU36*1.2)*0.3)),6) -> 0 | AF36: =ROUND((((EV36*1.2)*0.3)),6) -> 9.0864 | AG36: =ROUND((AP36),6) -> 0 | AH36: =(((EW36*1.2)*0.3)) -> 0.72 | AI36: =(((EX36*1.2)*0.3)) -> 0 | AJ36: =(AS36) -> 0 | AK36: 25.54 | AL36: 0.3 | AM36: 0 | AN36: 0 | AO36: 25.24 | AP36: 0 | AQ36: 2 | AR36: 0 | AS36: 0 | AT36: 95 | AU36: 53 | AV36: 1.087 | AW36: 1 | AZ36: 1 | BA36: 1 | BB36: 1 | BC36: 1 | BH36: 0 | BI36: 2 | BJ36: ТСН-2001.4 Доп. 81, Сб. 10, т. 136, поз. 4 | BM36: 69 | BN36: 0 | BO36: 4.10-136-4 | BP36: 1 | BQ36: 40 | BR36: 0 | BS36: 1 | BT36: 1 | BU36: 1 | BV36: 1 | BW36: 1 | BX36: 1 | BZ36: 95 | CA36: 53 | CE36: 1566 | CF36: 0 | CG36: 0 | CM36: 0 | CN36: Поправка: Гл.12.Прил.8.п.8. 3_12.00.01.11.001 Наименование: При наличии напряженных и стесненных условий производства работ (стесненность, сложность складирования и транспортной логистики и т.п.) для объектов, расположенных в пределах круговой магистральной системы улиц "Садовое кольцо" города Москвы Поправка: Гл.4.Прил.2.2.п.2.2.29_04.00.01.35.003 Наименование: При демонтаже оборудования, предназначенного в лом | CO36: 0 | CP36: =(P36+Q36+S36) -> 9.88 | CQ36: =ROUND((ROUND((AC36*AW36*1),2)*BC36),2) -> 0 | CR36: =(ROUND((ROUND(((((ET36*1.2)*0.3))*AV36*1),2)*BB36),2)+ROUND((ROUND(((AE36-(((EU36*1.2)*0.3)))*AV36*1),2)*BS36),2)) -> 0 | CS36: =(ROUND((ROUND(((((EU36*1.2)*0.3))*AV36*1),2)*BS36),2)+ROUND((ROUND(((AE36-(((EU36*1.2)*0.3)))*AV36*1),2)*BS36),2)) -> 0 | CT36: =ROUND((ROUND((AF36*AV36*1),2)*BA36),2) -> 9.88 | CU36: =AG36 -> 0 | CV36: =(AH36*AV36) -> 0.78264 | CW36: =AI36 -> 0 | CX36: =AJ36 -> 0 | CY36: =(ROUND((((S36+ROUND((ROUND(((((EU36*1.2)*0.3))*AV36*1),2)*BS36),2))*AT36)/100),2)+ROUND(((ROUND((ROUND(((AE36-(((EU36*1.2)*0.3)))*AV36*1),2)*BS36),2)*AT36)/100),2)) -> 9.39 | CZ36: =(ROUND((((S36+ROUND((ROUND(((((EU36*1.2)*0.3))*AV36*1),2)*BS36),2))*AU36)/100),2)+ROUND(((ROUND((ROUND(((AE36-(((EU36*1.2)*0.3)))*AV36*1),2)*BS36),2)*AU36)/100),2)) -> 5.24 | DB36: 17 | DD36: *1)*0 | DE36: *1,2)*0,3 | DF36: *1,2)*0,3 | DG36: *1,2)*0,3 | DI36: *1,2)*0,3 | DJ36: *1,2)*0,3 | DN36: 0 | DO36: 0 | DP36: 1 | DQ36: 1 | DU36: 1013 | DV36: 1 ШТ. | DW36: 1 ШТ. | DX36: 1 | EE36: 55393701 | EF36: 40 | EG36: Монтаж оборудования | EH36: 0 | EJ36: 2 | EK36: 69 | EL36: ТСН-2001.4-10. Монтаж радиотелевизионного и электронного оборудования | EM36: ТСН-2001.4-10-2 | EO36: Поправка: Гл.12.Прил.8.п.8. 3_12.00.01.11.001 Поправка: Гл.4.Прил.2.2.п.2.2.29_04.00.01.35.003 | EQ36: 0 | ER36: 25.54 | ES36: 0.3 | ET36: 0 | EU36: 0 | EV36: 25.24 | EW36: 2 | EX36: 0 | EY36: 0 | FQ36: 0 | FR36: 0 | FS36: 0 | FX36: 95 | FY36: 53 | GD36: 1 | GF36: -405642349 | GG36: 2 | GH36: 1 | GI36: 2 | GJ36: 0 | GK36: 0 | GL36: =ROUND(IF(AND(BH36=3,BI36=3,FS36<>0),P36,0),2) -> 0 | GM36: =ROUND(O36+X36+Y36,2)+GX36 -> 24.51 | GN36: =IF(OR(BI36=0,BI36=1),GM36-GX36,0) -> 0 | GO36: =IF(BI36=2,GM36-GX36,0) -> 24.51 | GP36: =IF(BI36=4,GM36-GX36,0) -> 0 | GR36: 0 | GS36: 3 | GT36: 0 | GV36: =ROUND((GT36),6) -> 0 | GW36: 1 | GX36: =ROUND(HC36*I36,2) -> 0 | HA36: 0 | HB36: 0 | HC36: =GV36*GW36 -> 0 | HS36: 0 | IK36: 0
A37: 17 | B37: 1 | C37: =ROW(SmtRes!A30) -> 30 | D37: =ROW(EtalonRes!A34) -> 34 | E37: 5 | F37: 4.10-136-4 | G37: Монтаж тв усилителя настенного типа, блока питания / демонтаж блока питания | H37: 1 ШТ. | I37: 1 | J37: 0 | K37: 1 | O37: =ROUND(CP37,2) -> 556.74 | P37: =ROUND((ROUND((AC37*AW37*I37),2)*BC37),2) -> 0 | Q37: =(ROUND((ROUND(((((ET37*1.2)*0.3))*AV37*I37),2)*BB37),2)+ROUND((ROUND(((AE37-(((EU37*1.2)*0.3)))*AV37*I37),2)*BS37),2)) -> 0 | R37: =(ROUND((ROUND(((((EU37*1.2)*0.3))*AV37*I37),2)*BS37),2)+ROUND((ROUND(((AE37-(((EU37*1.2)*0.3)))*AV37*I37),2)*BS37),2)) -> 0 | S37: =ROUND((ROUND((AF37*AV37*I37),2)*BA37),2) -> 556.74 | T37: =ROUND(CU37*I37,2) -> 0 | U37: =CV37*I37 -> 0.78264 | V37: =CW37*I37 -> 0 | W37: =ROUND(CX37*I37,2) -> 0 | X37: =(ROUND((((S37+ROUND((ROUND(((((EU37*1.2)*0.3))*AV37*I37),2)*BS37),2))*AT37)/100),2)+ROUND(((ROUND((ROUND(((AE37-(((EU37*1.2)*0.3)))*AV37*I37),2)*BS37),2)*AT37)/100),2)) -> 528.9 | Y37: =(ROUND((((S37+ROUND((ROUND(((((EU37*1.2)*0.3))*AV37*I37),2)*BS37),2))*AU37)/100),2)+ROUND(((ROUND((ROUND(((AE37-(((EU37*1.2)*0.3)))*AV37*I37),2)*BS37),2)*AU37)/100),2)) -> 295.07 | AA37: 55919549 | AB37: =ROUND((AC37+AD37+AF37),6) -> 9.0864 | AC37: =ROUND((((ES37*1)*0)),6) -> 0 | AD37: =ROUND((((((ET37*1.2)*0.3))-(((EU37*1.2)*0.3)))+AE37),6) -> 0 | AE37: =ROUND((((EU37*1.2)*0.3)),6) -> 0 | AF37: =ROUND((((EV37*1.2)*0.3)),6) -> 9.0864 | AG37: =ROUND((AP37),6) -> 0 | AH37: =(((EW37*1.2)*0.3)) -> 0.72 | AI37: =(((EX37*1.2)*0.3)) -> 0 | AJ37: =(AS37) -> 0 | AK37: 25.54 | AL37: 0.3 | AM37: 0 | AN37: 0 | AO37: 25.24 | AP37: 0 | AQ37: 2 | AR37: 0 | AS37: 0 | AT37: 95 | AU37: 53 | AV37: 1.087 | AW37: 1 | AZ37: 1 | BA37: 56.35 | BB37: 1 | BC37: 7.37 | BH37: 0 | BI37: 2 | BJ37: ТСН-2001.4 Доп. 81, Сб. 10, т. 136, поз. 4 | BM37: 69 | BN37: 0 | BO37: 4.10-136-4 | BP37: 1 | BQ37: 40 | BR37: 0 | BS37: 56.35 | BT37: 1 | BU37: 1 | BV37: 1 | BW37: 1 | BX37: 1 | BZ37: 95 | CA37: 53 | CE37: 1566 | CF37: 0 | CG37: 0 | CM37: 0 | CN37: Поправка: Гл.12.Прил.8.п.8. 3_12.00.01.11.001 Наименование: При наличии напряженных и стесненных условий производства работ (стесненность, сложность складирования и транспортной логистики и т.п.) для объектов, расположенных в пределах круговой магистральной системы улиц "Садовое кольцо" города Москвы Поправка: Гл.4.Прил.2.2.п.2.2.29_04.00.01.35.003 Наименование: При демонтаже оборудования, предназначенного в лом | CO37: 0 | CP37: =(P37+Q37+S37) -> 556.74 | CQ37: =ROUND((ROUND((AC37*AW37*1),2)*BC37),2) -> 0 | CR37: =(ROUND((ROUND(((((ET37*1.2)*0.3))*AV37*1),2)*BB37),2)+ROUND((ROUND(((AE37-(((EU37*1.2)*0.3)))*AV37*1),2)*BS37),2)) -> 0 | CS37: =(ROUND((ROUND(((((EU37*1.2)*0.3))*AV37*1),2)*BS37),2)+ROUND((ROUND(((AE37-(((EU37*1.2)*0.3)))*AV37*1),2)*BS37),2)) -> 0 | CT37: =ROUND((ROUND((AF37*AV37*1),2)*BA37),2) -> 556.74 | CU37: =AG37 -> 0 | CV37: =(AH37*AV37) -> 0.78264 | CW37: =AI37 -> 0 | CX37: =AJ37 -> 0 | CY37: =(ROUND((((S37+ROUND((ROUND(((((EU37*1.2)*0.3))*AV37*1),2)*BS37),2))*AT37)/100),2)+ROUND(((ROUND((ROUND(((AE37-(((EU37*1.2)*0.3)))*AV37*1),2)*BS37),2)*AT37)/100),2)) -> 528.9 | CZ37: =(ROUND((((S37+ROUND((ROUND(((((EU37*1.2)*0.3))*AV37*1),2)*BS37),2))*AU37)/100),2)+ROUND(((ROUND((ROUND(((AE37-(((EU37*1.2)*0.3)))*AV37*1),2)*BS37),2)*AU37)/100),2)) -> 295.07 | DB37: 19 | DD37: *1)*0 | DE37: *1,2)*0,3 | DF37: *1,2)*0,3 | DG37: *1,2)*0,3 | DI37: *1,2)*0,3 | DJ37: *1,2)*0,3 | DN37: 0 | DO37: 0 | DP37: 1 | DQ37: 1 | DU37: 1013 | DV37: 1 ШТ. | DW37: 1 ШТ. | DX37: 1 | EE37: 55393701 | EF37: 40 | EG37: Монтаж оборудования | EH37: 0 | EJ37: 2 | EK37: 69 | EL37: ТСН-2001.4-10. Монтаж радиотелевизионного и электронного оборудования | EM37: ТСН-2001.4-10-2 | EO37: Поправка: Гл.12.Прил.8.п.8. 3_12.00.01.11.001 Поправка: Гл.4.Прил.2.2.п.2.2.29_04.00.01.35.003 | EQ37: 0 | ER37: 25.54 | ES37: 0.3 | ET37: 0 | EU37: 0 | EV37: 25.24 | EW37: 2 | EX37: 0 | EY37: 0 | FQ37: 0 | FR37: 0 | FS37: 0 | FX37: 95 | FY37: 53 | GD37: 1 | GF37: -405642349 | GG37: 2 | GH37: 1 | GI37: 2 | GJ37: 0 | GK37: 0 | GL37: =ROUND(IF(AND(BH37=3,BI37=3,FS37<>0),P37,0),2) -> 0 | GM37: =ROUND(O37+X37+Y37,2)+GX37 -> 1380.71 | GN37: =IF(OR(BI37=0,BI37=1),GM37-GX37,0) -> 0 | GO37: =IF(BI37=2,GM37-GX37,0) -> 1380.71 | GP37: =IF(BI37=4,GM37-GX37,0) -> 0 | GR37: 0 | GS37: 3 | GT37: 0 | GV37: =ROUND((GT37),6) -> 0 | GW37: 1 | GX37: =ROUND(HC37*I37,2) -> 0 | HA37: 0 | HB37: 0 | HC37: =GV37*GW37 -> 0 | HS37: 0 | IK37: 0
A38: 17 | B38: 1 | C38: =ROW(SmtRes!A32) -> 32 | D38: =ROW(EtalonRes!A36) -> 36 | E38: 6 | F38: 4.10-136-1 | G38: Монтаж коробки телевизионной (ответвители, разветвители магистральные, домовые, абонентские), УСС, БФТК / демонтаж ответвителя | H38: 1 ШТ. | I38: 6 | J38: 0 | K38: 6 | O38: =ROUND(CP38,2) -> 25.87 | P38: =ROUND((ROUND((AC38*AW38*I38),2)*BC38),2) -> 0 | Q38: =(ROUND((ROUND(((((ET38*1.2)*0.3))*AV38*I38),2)*BB38),2)+ROUND((ROUND(((AE38-(((EU38*1.2)*0.3)))*AV38*I38),2)*BS38),2)) -> 0 | R38: =(ROUND((ROUND(((((EU38*1.2)*0.3))*AV38*I38),2)*BS38),2)+ROUND((ROUND(((AE38-(((EU38*1.2)*0.3)))*AV38*I38),2)*BS38),2)) -> 0 | S38: =ROUND((ROUND((AF38*AV38*I38),2)*BA38),2) -> 25.87 | T38: =ROUND(CU38*I38,2) -> 0 | U38: =CV38*I38 -> 1.878336 | V38: =CW38*I38 -> 0 | W38: =ROUND(CX38*I38,2) -> 0 | X38: =(ROUND((((S38+ROUND((ROUND(((((EU38*1.2)*0.3))*AV38*I38),2)*BS38),2))*AT38)/100),2)+ROUND(((ROUND((ROUND(((AE38-(((EU38*1.2)*0.3)))*AV38*I38),2)*BS38),2)*AT38)/100),2)) -> 24.58 | Y38: =(ROUND((((S38+ROUND((ROUND(((((EU38*1.2)*0.3))*AV38*I38),2)*BS38),2))*AU38)/100),2)+ROUND(((ROUND((ROUND(((AE38-(((EU38*1.2)*0.3)))*AV38*I38),2)*BS38),2)*AU38)/100),2)) -> 13.71 | AA38: 55919547 | AB38: =ROUND((AC38+AD38+AF38),6) -> 3.9672 | AC38: =ROUND((((ES38*1)*0)),6) -> 0 | AD38: =ROUND((((((ET38*1.2)*0.3))-(((EU38*1.2)*0.3)))+AE38),6) -> 0 | AE38: =ROUND((((EU38*1.2)*0.3)),6) -> 0 | AF38: =ROUND((((EV38*1.2)*0.3)),6) -> 3.9672 | AG38: =ROUND((AP38),6) -> 0 | AH38: =(((EW38*1.2)*0.3)) -> 0.288 | AI38: =(((EX38*1.2)*0.3)) -> 0 | AJ38: =(AS38) -> 0 | AK38: 11.32 | AL38: 0.3 | AM38: 0 | AN38: 0 | AO38: 11.02 | AP38: 0 | AQ38: 0.8 | AR38: 0 | AS38: 0 | AT38: 95 | AU38: 53 | AV38: 1.087 | AW38: 1 | AZ38: 1 | BA38: 1 | BB38: 1 | BC38: 1 | BH38: 0 | BI38: 2 | BJ38: ТСН-2001.4 Доп. 81, Сб. 10, т. 136, поз. 1 | BM38: 69 | BN38: 0 | BO38: 4.10-136-1 | BP38: 1 | BQ38: 40 | BR38: 0 | BS38: 1 | BT38: 1 | BU38: 1 | BV38: 1 | BW38: 1 | BX38: 1 | BZ38: 95 | CA38: 53 | CE38: 1566 | CF38: 0 | CG38: 0 | CM38: 0 | CN38: Поправка: Гл.12.Прил.8.п.8. 3_12.00.01.11.001 Наименование: При наличии напряженных и стесненных условий производства работ (стесненность, сложность складирования и транспортной логистики и т.п.) для объектов, расположенных в пределах круговой магистральной системы улиц "Садовое кольцо" города Москвы Поправка: Гл.4.Прил.2.2.п.2.2.29_04.00.01.35.003 Наименование: При демонтаже оборудования, предназначенного в лом | CO38: 0 | CP38: =(P38+Q38+S38) -> 25.87 | CQ38: =ROUND((ROUND((AC38*AW38*1),2)*BC38),2) -> 0 | CR38: =(ROUND((ROUND(((((ET38*1.2)*0.3))*AV38*1),2)*BB38),2)+ROUND((ROUND(((AE38-(((EU38*1.2)*0.3)))*AV38*1),2)*BS38),2)) -> 0 | CS38: =(ROUND((ROUND(((((EU38*1.2)*0.3))*AV38*1),2)*BS38),2)+ROUND((ROUND(((AE38-(((EU38*1.2)*0.3)))*AV38*1),2)*BS38),2)) -> 0 | CT38: =ROUND((ROUND((AF38*AV38*1),2)*BA38),2) -> 4.31 | CU38: =AG38 -> 0 | CV38: =(AH38*AV38) -> 0.313056 | CW38: =AI38 -> 0 | CX38: =AJ38 -> 0 | CY38: =(ROUND((((S38+ROUND((ROUND(((((EU38*1.2)*0.3))*AV38*1),2)*BS38),2))*AT38)/100),2)+ROUND(((ROUND((ROUND(((AE38-(((EU38*1.2)*0.3)))*AV38*1),2)*BS38),2)*AT38)/100),2)) -> 24.58 | CZ38: =(ROUND((((S38+ROUND((ROUND(((((EU38*1.2)*0.3))*AV38*1),2)*BS38),2))*AU38)/100),2)+ROUND(((ROUND((ROUND(((AE38-(((EU38*1.2)*0.3)))*AV38*1),2)*BS38),2)*AU38)/100),2)) -> 13.71 | DB38: 21 | DD38: *1)*0 | DE38: *1,2)*0,3 | DF38: *1,2)*0,3 | DG38: *1,2)*0,3 | DI38: *1,2)*0,3 | DJ38: *1,2)*0,3 | DN38: 0 | DO38: 0 | DP38: 1 | DQ38: 1 | DU38: 1013 | DV38: 1 ШТ. | DW38: 1 ШТ. | DX38: 1 | EE38: 55393701 | EF38: 40 | EG38: Монтаж оборудования | EH38: 0 | EJ38: 2 | EK38: 69 | EL38: ТСН-2001.4-10. Монтаж радиотелевизионного и электронного оборудования | EM38: ТСН-2001.4-10-2 | EO38: Поправка: Гл.12.Прил.8.п.8. 3_12.00.01.11.001 Поправка: Гл.4.Прил.2.2.п.2.2.29_04.00.01.35.003 | EQ38: 0 | ER38: 11.32 | ES38: 0.3 | ET38: 0 | EU38: 0 | EV38: 11.02 | EW38: 0.8 | EX38: 0 | EY38: 0 | FQ38: 0 | FR38: 0 | FS38: 0 | FX38: 95 | FY38: 53 | GD38: 1 | GF38: -1076361322 | GG38: 2 | GH38: 1 | GI38: 2 | GJ38: 0 | GK38: 0 | GL38: =ROUND(IF(AND(BH38=3,BI38=3,FS38<>0),P38,0),2) -> 0 | GM38: =ROUND(O38+X38+Y38,2)+GX38 -> 64.16 | GN38: =IF(OR(BI38=0,BI38=1),GM38-GX38,0) -> 0 | GO38: =IF(BI38=2,GM38-GX38,0) -> 64.16 | GP38: =IF(BI38=4,GM38-GX38,0) -> 0 | GR38: 0 | GS38: 3 | GT38: 0 | GV38: =ROUND((GT38),6) -> 0 | GW38: 1 | GX38: =ROUND(HC38*I38,2) -> 0 | HA38: 0 | HB38: 0 | HC38: =GV38*GW38 -> 0 | HS38: 0 | IK38: 0
A39: 17 | B39: 1 | C39: =ROW(SmtRes!A34) -> 34 | D39: =ROW(EtalonRes!A38) -> 38 | E39: 6 | F39: 4.10-136-1 | G39: Монтаж коробки телевизионной (ответвители, разветвители магистральные, домовые, абонентские), УСС, БФТК / демонтаж ответвителя | H39: 1 ШТ. | I39: 6 | J39: 0 | K39: 6 | O39: =ROUND(CP39,2) -> 1457.77 | P39: =ROUND((ROUND((AC39*AW39*I39),2)*BC39),2) -> 0 | Q39: =(ROUND((ROUND(((((ET39*1.2)*0.3))*AV39*I39),2)*BB39),2)+ROUND((ROUND(((AE39-(((EU39*1.2)*0.3)))*AV39*I39),2)*BS39),2)) -> 0 | R39: =(ROUND((ROUND(((((EU39*1.2)*0.3))*AV39*I39),2)*BS39),2)+ROUND((ROUND(((AE39-(((EU39*1.2)*0.3)))*AV39*I39),2)*BS39),2)) -> 0 | S39: =ROUND((ROUND((AF39*AV39*I39),2)*BA39),2) -> 1457.77 | T39: =ROUND(CU39*I39,2) -> 0 | U39: =CV39*I39 -> 1.878336 | V39: =CW39*I39 -> 0 | W39: =ROUND(CX39*I39,2) -> 0 | X39: =(ROUND((((S39+ROUND((ROUND(((((EU39*1.2)*0.3))*AV39*I39),2)*BS39),2))*AT39)/100),2)+ROUND(((ROUND((ROUND(((AE39-(((EU39*1.2)*0.3)))*AV39*I39),2)*BS39),2)*AT39)/100),2)) -> 1384.88 | Y39: =(ROUND((((S39+ROUND((ROUND(((((EU39*1.2)*0.3))*AV39*I39),2)*BS39),2))*AU39)/100),2)+ROUND(((ROUND((ROUND(((AE39-(((EU39*1.2)*0.3)))*AV39*I39),2)*BS39),2)*AU39)/100),2)) -> 772.62 | AA39: 55919549 | AB39: =ROUND((AC39+AD39+AF39),6) -> 3.9672 | AC39: =ROUND((((ES39*1)*0)),6) -> 0 | AD39: =ROUND((((((ET39*1.2)*0.3))-(((EU39*1.2)*0.3)))+AE39),6) -> 0 | AE39: =ROUND((((EU39*1.2)*0.3)),6) -> 0 | AF39: =ROUND((((EV39*1.2)*0.3)),6) -> 3.9672 | AG39: =ROUND((AP39),6) -> 0 | AH39: =(((EW39*1.2)*0.3)) -> 0.288 | AI39: =(((EX39*1.2)*0.3)) -> 0 | AJ39: =(AS39) -> 0 | AK39: 11.32 | AL39: 0.3 | AM39: 0 | AN39: 0 | AO39: 11.02 | AP39: 0 | AQ39: 0.8 | AR39: 0 | AS39: 0 | AT39: 95 | AU39: 53 | AV39: 1.087 | AW39: 1 | AZ39: 1 | BA39: 56.35 | BB39: 1 | BC39: 7.37 | BH39: 0 | BI39: 2 | BJ39: ТСН-2001.4 Доп. 81, Сб. 10, т. 136, поз. 1 | BM39: 69 | BN39: 0 | BO39: 4.10-136-1 | BP39: 1 | BQ39: 40 | BR39: 0 | BS39: 56.35 | BT39: 1 | BU39: 1 | BV39: 1 | BW39: 1 | BX39: 1 | BZ39: 95 | CA39: 53 | CE39: 1566 | CF39: 0 | CG39: 0 | CM39: 0 | CN39: Поправка: Гл.12.Прил.8.п.8. 3_12.00.01.11.001 Наименование: При наличии напряженных и стесненных условий производства работ (стесненность, сложность складирования и транспортной логистики и т.п.) для объектов, расположенных в пределах круговой магистральной системы улиц "Садовое кольцо" города Москвы Поправка: Гл.4.Прил.2.2.п.2.2.29_04.00.01.35.003 Наименование: При демонтаже оборудования, предназначенного в лом | CO39: 0 | CP39: =(P39+Q39+S39) -> 1457.77 | CQ39: =ROUND((ROUND((AC39*AW39*1),2)*BC39),2) -> 0 | CR39: =(ROUND((ROUND(((((ET39*1.2)*0.3))*AV39*1),2)*BB39),2)+ROUND((ROUND(((AE39-(((EU39*1.2)*0.3)))*AV39*1),2)*BS39),2)) -> 0 | CS39: =(ROUND((ROUND(((((EU39*1.2)*0.3))*AV39*1),2)*BS39),2)+ROUND((ROUND(((AE39-(((EU39*1.2)*0.3)))*AV39*1),2)*BS39),2)) -> 0 | CT39: =ROUND((ROUND((AF39*AV39*1),2)*BA39),2) -> 242.87 | CU39: =AG39 -> 0 | CV39: =(AH39*AV39) -> 0.313056 | CW39: =AI39 -> 0 | CX39: =AJ39 -> 0 | CY39: =(ROUND((((S39+ROUND((ROUND(((((EU39*1.2)*0.3))*AV39*1),2)*BS39),2))*AT39)/100),2)+ROUND(((ROUND((ROUND(((AE39-(((EU39*1.2)*0.3)))*AV39*1),2)*BS39),2)*AT39)/100),2)) -> 1384.88 | CZ39: =(ROUND((((S39+ROUND((ROUND(((((EU39*1.2)*0.3))*AV39*1),2)*BS39),2))*AU39)/100),2)+ROUND(((ROUND((ROUND(((AE39-(((EU39*1.2)*0.3)))*AV39*1),2)*BS39),2)*AU39)/100),2)) -> 772.62 | DB39: 23 | DD39: *1)*0 | DE39: *1,2)*0,3 | DF39: *1,2)*0,3 | DG39: *1,2)*0,3 | DI39: *1,2)*0,3 | DJ39: *1,2)*0,3 | DN39: 0 | DO39: 0 | DP39: 1 | DQ39: 1 | DU39: 1013 | DV39: 1 ШТ. | DW39: 1 ШТ. | DX39: 1 | EE39: 55393701 | EF39: 40 | EG39: Монтаж оборудования | EH39: 0 | EJ39: 2 | EK39: 69 | EL39: ТСН-2001.4-10. Монтаж радиотелевизионного и электронного оборудования | EM39: ТСН-2001.4-10-2 | EO39: Поправка: Гл.12.Прил.8.п.8. 3_12.00.01.11.001 Поправка: Гл.4.Прил.2.2.п.2.2.29_04.00.01.35.003 | EQ39: 0 | ER39: 11.32 | ES39: 0.3 | ET39: 0 | EU39: 0 | EV39: 11.02 | EW39: 0.8 | EX39: 0 | EY39: 0 | FQ39: 0 | FR39: 0 | FS39: 0 | FX39: 95 | FY39: 53 | GD39: 1 | GF39: -1076361322 | GG39: 2 | GH39: 1 | GI39: 2 | GJ39: 0 | GK39: 0 | GL39: =ROUND(IF(AND(BH39=3,BI39=3,FS39<>0),P39,0),2) -> 0 | GM39: =ROUND(O39+X39+Y39,2)+GX39 -> 3615.27 | GN39: =IF(OR(BI39=0,BI39=1),GM39-GX39,0) -> 0 | GO39: =IF(BI39=2,GM39-GX39,0) -> 3615.27 | GP39: =IF(BI39=4,GM39-GX39,0) -> 0 | GR39: 0 | GS39: 3 | GT39: 0 | GV39: =ROUND((GT39),6) -> 0 | GW39: 1 | GX39: =ROUND(HC39*I39,2) -> 0 | HA39: 0 | HB39: 0 | HC39: =GV39*GW39 -> 0 | HS39: 0 | IK39: 0
A40: 17 | B40: 1 | C40: =ROW(SmtRes!A35) -> 35 | D40: =ROW(EtalonRes!A39) -> 39 | E40: 7 | F40: 6.67-7-1 | G40: Демонтаж осветительных приборов, выключатели, розетки | H40: 100 шт. | I40: =ROUND(6/100,9) -> 0.06 | J40: 0 | K40: =ROUND(6/100,9) -> 0.06 | O40: =ROUND(CP40,2) -> 4.5 | P40: =ROUND((ROUND((AC40*AW40*I40),2)*BC40),2) -> 0 | Q40: =(ROUND((ROUND((((ET40*1.2))*AV40*I40),2)*BB40),2)+ROUND((ROUND(((AE40-((EU40*1.2)))*AV40*I40),2)*BS40),2)) -> 0 | R40: =(ROUND((ROUND((((EU40*1.2))*AV40*I40),2)*BS40),2)+ROUND((ROUND(((AE40-((EU40*1.2)))*AV40*I40),2)*BS40),2)) -> 0 | S40: =ROUND((ROUND((AF40*AV40*I40),2)*BA40),2) -> 4.5 | T40: =ROUND(CU40*I40,2) -> 0 | U40: =CV40*I40 -> 0.44024256 | V40: =CW40*I40 -> 0 | W40: =ROUND(CX40*I40,2) -> 0 | X40: =(ROUND((((S40+ROUND((ROUND((((EU40*1.2))*AV40*I40),2)*BS40),2))*AT40)/100),2)+ROUND(((ROUND((ROUND(((AE40-((EU40*1.2)))*AV40*I40),2)*BS40),2)*AT40)/100),2)) -> 4.1 | Y40: =(ROUND((((S40+ROUND((ROUND((((EU40*1.2))*AV40*I40),2)*BS40),2))*AU40)/100),2)+ROUND(((ROUND((ROUND(((AE40-((EU40*1.2)))*AV40*I40),2)*BS40),2)*AU40)/100),2)) -> 2.16 | AA40: 55919547 | AB40: =ROUND((AC40+AD40+AF40),6) -> 71.616 | AC40: =ROUND(((ES40*1)),6) -> 0 | AD40: =ROUND(((((ET40*1.2))-((EU40*1.2)))+AE40),6) -> 0 | AE40: =ROUND(((EU40*1.2)),6) -> 0 | AF40: =ROUND(((EV40*1.2)),6) -> 71.616 | AG40: =ROUND((AP40),6) -> 0 | AH40: =((EW40*1.2)) -> 7.008 | AI40: =((EX40*1.2)) -> 0 | AJ40: =(AS40) -> 0 | AK40: 59.68 | AL40: 0 | AM40: 0 | AN40: 0 | AO40: 59.68 | AP40: 0 | AQ40: 5.84 | AR40: 0 | AS40: 0 | AT40: 91 | AU40: 48 | AV40: 1.047 | AW40: 1 | AZ40: 1 | BA40: 1 | BB40: 1 | BC40: 1 | BH40: 0 | BI40: 1 | BJ40: ТСН-2001.6. Доп. 1-42. Сб. 67, т. 7, поз. 1 | BM40: 106 | BN40: 0 | BO40: 6.67-7-1 | BP40: 1 | BQ40: 60 | BR40: 0 | BS40: 1 | BT40: 1 | BU40: 1 | BV40: 1 | BW40: 1 | BX40: 1 | BZ40: 91 | CA40: 48 | CE40: 1566 | CF40: 0 | CG40: 0 | CM40: 0 | CN40: Поправка: Гл.12.Прил.8.п.8. 3_12.00.01.11.001 Наименование: При наличии напряженных и стесненных условий производства работ (стесненность, сложность складирования и транспортной логистики и т.п.) для объектов, расположенных в пределах круговой магистральной системы улиц "Садовое кольцо" города Москвы | CO40: 0 | CP40: =(P40+Q40+S40) -> 4.5 | CQ40: =ROUND((ROUND((AC40*AW40*1),2)*BC40),2) -> 0 | CR40: =(ROUND((ROUND((((ET40*1.2))*AV40*1),2)*BB40),2)+ROUND((ROUND(((AE40-((EU40*1.2)))*AV40*1),2)*BS40),2)) -> 0 | CS40: =(ROUND((ROUND((((EU40*1.2))*AV40*1),2)*BS40),2)+ROUND((ROUND(((AE40-((EU40*1.2)))*AV40*1),2)*BS40),2)) -> 0 | CT40: =ROUND((ROUND((AF40*AV40*1),2)*BA40),2) -> 74.98 | CU40: =AG40 -> 0 | CV40: =(AH40*AV40) -> 7.337376 | CW40: =AI40 -> 0 | CX40: =AJ40 -> 0 | CY40: =(ROUND((((S40+ROUND((ROUND((((EU40*1.2))*AV40*1),2)*BS40),2))*AT40)/100),2)+ROUND(((ROUND((ROUND(((AE40-((EU40*1.2)))*AV40*1),2)*BS40),2)*AT40)/100),2)) -> 4.1 | CZ40: =(ROUND((((S40+ROUND((ROUND((((EU40*1.2))*AV40*1),2)*BS40),2))*AU40)/100),2)+ROUND(((ROUND((ROUND(((AE40-((EU40*1.2)))*AV40*1),2)*BS40),2)*AU40)/100),2)) -> 2.16 | DB40: 25 | DD40: *1 | DE40: *1,2 | DF40: *1,2 | DG40: *1,2 | DI40: *1,2 | DJ40: *1,2 | DN40: 0 | DO40: 0 | DP40: 1 | DQ40: 1 | DU40: 1010 | DV40: 100 шт. | DW40: 100 шт. | DX40: 100 | EE40: 55393738 | EF40: 60 | EG40: Ремонтно-строительные работы | EH40: 0 | EJ40: 1 | EK40: 106 | EL40: ТСН-2001.6-67. Электромонтажные работы | EM40: ТСН-2001.6-67-1 | EO40: Поправка: Гл.12.Прил.8.п.8. 3_12.00.01.11.001 | EQ40: 0 | ER40: 59.68 | ES40: 0 | ET40: 0 | EU40: 0 | EV40: 59.68 | EW40: 5.84 | EX40: 0 | EY40: 0 | FQ40: 0 | FR40: 0 | FS40: 0 | FX40: 91 | FY40: 48 | GD40: 1 | GF40: 1478850760 | GG40: 2 | GH40: 1 | GI40: 2 | GJ40: 0 | GK40: 0 | GL40: =ROUND(IF(AND(BH40=3,BI40=3,FS40<>0),P40,0),2) -> 0 | GM40: =ROUND(O40+X40+Y40,2)+GX40 -> 10.76 | GN40: =IF(OR(BI40=0,BI40=1),GM40-GX40,0) -> 10.76 | GO40: =IF(BI40=2,GM40-GX40,0) -> 0 | GP40: =IF(BI40=4,GM40-GX40,0) -> 0 | GR40: 0 | GS40: 3 | GT40: 0 | GV40: =ROUND((GT40),6) -> 0 | GW40: 1 | GX40: =ROUND(HC40*I40,2) -> 0 | HA40: 0 | HB40: 0 | HC40: =GV40*GW40 -> 0 | HS40: 0 | IK40: 0
A41: 17 | B41: 1 | C41: =ROW(SmtRes!A36) -> 36 | D41: =ROW(EtalonRes!A40) -> 40 | E41: 7 | F41: 6.67-7-1 | G41: Демонтаж осветительных приборов, выключатели, розетки | H41: 100 шт. | I41: =ROUND(6/100,9) -> 0.06 | J41: 0 | K41: =ROUND(6/100,9) -> 0.06 | O41: =ROUND(CP41,2) -> 253.58 | P41: =ROUND((ROUND((AC41*AW41*I41),2)*BC41),2) -> 0 | Q41: =(ROUND((ROUND((((ET41*1.2))*AV41*I41),2)*BB41),2)+ROUND((ROUND(((AE41-((EU41*1.2)))*AV41*I41),2)*BS41),2)) -> 0 | R41: =(ROUND((ROUND((((EU41*1.2))*AV41*I41),2)*BS41),2)+ROUND((ROUND(((AE41-((EU41*1.2)))*AV41*I41),2)*BS41),2)) -> 0 | S41: =ROUND((ROUND((AF41*AV41*I41),2)*BA41),2) -> 253.58 | T41: =ROUND(CU41*I41,2) -> 0 | U41: =CV41*I41 -> 0.44024256 | V41: =CW41*I41 -> 0 | W41: =ROUND(CX41*I41,2) -> 0 | X41: =(ROUND((((S41+ROUND((ROUND((((EU41*1.2))*AV41*I41),2)*BS41),2))*AT41)/100),2)+ROUND(((ROUND((ROUND(((AE41-((EU41*1.2)))*AV41*I41),2)*BS41),2)*AT41)/100),2)) -> 230.76 | Y41: =(ROUND((((S41+ROUND((ROUND((((EU41*1.2))*AV41*I41),2)*BS41),2))*AU41)/100),2)+ROUND(((ROUND((ROUND(((AE41-((EU41*1.2)))*AV41*I41),2)*BS41),2)*AU41)/100),2)) -> 121.72 | AA41: 55919549 | AB41: =ROUND((AC41+AD41+AF41),6) -> 71.616 | AC41: =ROUND(((ES41*1)),6) -> 0 | AD41: =ROUND(((((ET41*1.2))-((EU41*1.2)))+AE41),6) -> 0 | AE41: =ROUND(((EU41*1.2)),6) -> 0 | AF41: =ROUND(((EV41*1.2)),6) -> 71.616 | AG41: =ROUND((AP41),6) -> 0 | AH41: =((EW41*1.2)) -> 7.008 | AI41: =((EX41*1.2)) -> 0 | AJ41: =(AS41) -> 0 | AK41: 59.68 | AL41: 0 | AM41: 0 | AN41: 0 | AO41: 59.68 | AP41: 0 | AQ41: 5.84 | AR41: 0 | AS41: 0 | AT41: 91 | AU41: 48 | AV41: 1.047 | AW41: 1 | AZ41: 1 | BA41: 56.35 | BB41: 1 | BC41: 1 | BH41: 0 | BI41: 1 | BJ41: ТСН-2001.6. Доп. 1-42. Сб. 67, т. 7, поз. 1 | BM41: 106 | BN41: 0 | BO41: 6.67-7-1 | BP41: 1 | BQ41: 60 | BR41: 0 | BS41: 56.35 | BT41: 1 | BU41: 1 | BV41: 1 | BW41: 1 | BX41: 1 | BZ41: 91 | CA41: 48 | CE41: 1566 | CF41: 0 | CG41: 0 | CM41: 0 | CN41: Поправка: Гл.12.Прил.8.п.8. 3_12.00.01.11.001 Наименование: При наличии напряженных и стесненных условий производства работ (стесненность, сложность складирования и транспортной логистики и т.п.) для объектов, расположенных в пределах круговой магистральной системы улиц "Садовое кольцо" города Москвы | CO41: 0 | CP41: =(P41+Q41+S41) -> 253.58 | CQ41: =ROUND((ROUND((AC41*AW41*1),2)*BC41),2) -> 0 | CR41: =(ROUND((ROUND((((ET41*1.2))*AV41*1),2)*BB41),2)+ROUND((ROUND(((AE41-((EU41*1.2)))*AV41*1),2)*BS41),2)) -> 0 | CS41: =(ROUND((ROUND((((EU41*1.2))*AV41*1),2)*BS41),2)+ROUND((ROUND(((AE41-((EU41*1.2)))*AV41*1),2)*BS41),2)) -> 0 | CT41: =ROUND((ROUND((AF41*AV41*1),2)*BA41),2) -> 4225.12 | CU41: =AG41 -> 0 | CV41: =(AH41*AV41) -> 7.337376 | CW41: =AI41 -> 0 | CX41: =AJ41 -> 0 | CY41: =(ROUND((((S41+ROUND((ROUND((((EU41*1.2))*AV41*1),2)*BS41),2))*AT41)/100),2)+ROUND(((ROUND((ROUND(((AE41-((EU41*1.2)))*AV41*1),2)*BS41),2)*AT41)/100),2)) -> 230.76 | CZ41: =(ROUND((((S41+ROUND((ROUND((((EU41*1.2))*AV41*1),2)*BS41),2))*AU41)/100),2)+ROUND(((ROUND((ROUND(((AE41-((EU41*1.2)))*AV41*1),2)*BS41),2)*AU41)/100),2)) -> 121.72 | DB41: 26 | DD41: *1 | DE41: *1,2 | DF41: *1,2 | DG41: *1,2 | DI41: *1,2 | DJ41: *1,2 | DN41: 0 | DO41: 0 | DP41: 1 | DQ41: 1 | DU41: 1010 | DV41: 100 шт. | DW41: 100 шт. | DX41: 100 | EE41: 55393738 | EF41: 60 | EG41: Ремонтно-строительные работы | EH41: 0 | EJ41: 1 | EK41: 106 | EL41: ТСН-2001.6-67. Электромонтажные работы | EM41: ТСН-2001.6-67-1 | EO41: Поправка: Гл.12.Прил.8.п.8. 3_12.00.01.11.001 | EQ41: 0 | ER41: 59.68 | ES41: 0 | ET41: 0 | EU41: 0 | EV41: 59.68 | EW41: 5.84 | EX41: 0 | EY41: 0 | FQ41: 0 | FR41: 0 | FS41: 0 | FX41: 91 | FY41: 48 | GD41: 1 | GF41: 1478850760 | GG41: 2 | GH41: 1 | GI41: 2 | GJ41: 0 | GK41: 0 | GL41: =ROUND(IF(AND(BH41=3,BI41=3,FS41<>0),P41,0),2) -> 0 | GM41: =ROUND(O41+X41+Y41,2)+GX41 -> 606.06 | GN41: =IF(OR(BI41=0,BI41=1),GM41-GX41,0) -> 606.06 | GO41: =IF(BI41=2,GM41-GX41,0) -> 0 | GP41: =IF(BI41=4,GM41-GX41,0) -> 0 | GR41: 0 | GS41: 3 | GT41: 0 | GV41: =ROUND((GT41),6) -> 0 | GW41: 1 | GX41: =ROUND(HC41*I41,2) -> 0 | HA41: 0 | HB41: 0 | HC41: =GV41*GW41 -> 0 | HS41: 0 | IK41: 0
A42: 17 | B42: 1 | C42: =ROW(SmtRes!A37) -> 37 | D42: =ROW(EtalonRes!A41) -> 41 | E42: 8 | F42: 6.67-6-1 | G42: Демонтаж кабеля | H42: 100 м | I42: =ROUND((80+300+10)/100,9) -> 3.9 | J42: 0 | K42: =ROUND((80+300+10)/100,9) -> 3.9 | O42: =ROUND(CP42,2) -> 482.74 | P42: =ROUND((ROUND((AC42*AW42*I42),2)*BC42),2) -> 0 | Q42: =(ROUND((ROUND((((ET42*1.2))*AV42*I42),2)*BB42),2)+ROUND((ROUND(((AE42-((EU42*1.2)))*AV42*I42),2)*BS42),2)) -> 0 | R42: =(ROUND((ROUND((((EU42*1.2))*AV42*I42),2)*BS42),2)+ROUND((ROUND(((AE42-((EU42*1.2)))*AV42*I42),2)*BS42),2)) -> 0 | S42: =ROUND((ROUND((AF42*AV42*I42),2)*BA42),2) -> 482.74 | T42: =ROUND(CU42*I42,2) -> 0 | U42: =CV42*I42 -> 47.235614 | V42: =CW42*I42 -> 0 | W42: =ROUND(CX42*I42,2) -> 0 | X42: =(ROUND((((S42+ROUND((ROUND((((EU42*1.2))*AV42*I42),2)*BS42),2))*AT42)/100),2)+ROUND(((ROUND((ROUND(((AE42-((EU42*1.2)))*AV42*I42),2)*BS42),2)*AT42)/100),2)) -> 439.29 | Y42: =(ROUND((((S42+ROUND((ROUND((((EU42*1.2))*AV42*I42),2)*BS42),2))*AU42)/100),2)+ROUND(((ROUND((ROUND(((AE42-((EU42*1.2)))*AV42*I42),2)*BS42),2)*AU42)/100),2)) -> 231.72 | AA42: 55919547 | AB42: =ROUND((AC42+AD42+AF42),6) -> 118.224 | AC42: =ROUND(((ES42*1)),6) -> 0 | AD42: =ROUND(((((ET42*1.2))-((EU42*1.2)))+AE42),6) -> 0 | AE42: =ROUND(((EU42*1.2)),6) -> 0 | AF42: =ROUND(((EV42*1.2)),6) -> 118.224 | AG42: =ROUND((AP42),6) -> 0 | AH42: =((EW42*1.2)) -> 11.568 | AI42: =((EX42*1.2)) -> 0 | AJ42: =(AS42) -> 0 | AK42: 98.52 | AL42: 0 | AM42: 0 | AN42: 0 | AO42: 98.52 | AP42: 0 | AQ42: 9.64 | AR42: 0 | AS42: 0 | AT42: 91 | AU42: 48 | AV42: 1.047 | AW42: 1 | AZ42: 1 | BA42: 1 | BB42: 1 | BC42: 1 | BH42: 0 | BI42: 1 | BJ42: ТСН-2001.6. Доп. 1-42. Сб. 67, т. 6, поз. 1 | BM42: 106 | BN42: 0 | BO42: 6.67-6-1 | BP42: 1 | BQ42: 60 | BR42: 0 | BS42: 1 | BT42: 1 | BU42: 1 | BV42: 1 | BW42: 1 | BX42: 1 | BZ42: 91 | CA42: 48 | CE42: 1566 | CF42: 0 | CG42: 0 | CM42: 0 | CN42: Поправка: Гл.12.Прил.8.п.8. 3_12.00.01.11.001 Наименование: При наличии напряженных и стесненных условий производства работ (стесненность, сложность складирования и транспортной логистики и т.п.) для объектов, расположенных в пределах круговой магистральной системы улиц "Садовое кольцо" города Москвы | CO42: 0 | CP42: =(P42+Q42+S42) -> 482.74 | CQ42: =ROUND((ROUND((AC42*AW42*1),2)*BC42),2) -> 0 | CR42: =(ROUND((ROUND((((ET42*1.2))*AV42*1),2)*BB42),2)+ROUND((ROUND(((AE42-((EU42*1.2)))*AV42*1),2)*BS42),2)) -> 0 | CS42: =(ROUND((ROUND((((EU42*1.2))*AV42*1),2)*BS42),2)+ROUND((ROUND(((AE42-((EU42*1.2)))*AV42*1),2)*BS42),2)) -> 0 | CT42: =ROUND((ROUND((AF42*AV42*1),2)*BA42),2) -> 123.78 | CU42: =AG42 -> 0 | CV42: =(AH42*AV42) -> 12.111696 | CW42: =AI42 -> 0 | CX42: =AJ42 -> 0 | CY42: =(ROUND((((S42+ROUND((ROUND((((EU42*1.2))*AV42*1),2)*BS42),2))*AT42)/100),2)+ROUND(((ROUND((ROUND(((AE42-((EU42*1.2)))*AV42*1),2)*BS42),2)*AT42)/100),2)) -> 439.29 | CZ42: =(ROUND((((S42+ROUND((ROUND((((EU42*1.2))*AV42*1),2)*BS42),2))*AU42)/100),2)+ROUND(((ROUND((ROUND(((AE42-((EU42*1.2)))*AV42*1),2)*BS42),2)*AU42)/100),2)) -> 231.72 | DB42: 27 | DD42: *1 | DE42: *1,2 | DF42: *1,2 | DG42: *1,2 | DI42: *1,2 | DJ42: *1,2 | DN42: 0 | DO42: 0 | DP42: 1 | DQ42: 1 | DU42: 1003 | DV42: 100 м | DW42: 100 м | DX42: 100 | EE42: 55393738 | EF42: 60 | EG42: Ремонтно-строительные работы | EH42: 0 | EJ42: 1 | EK42: 106 | EL42: ТСН-2001.6-67. Электромонтажные работы | EM42: ТСН-2001.6-67-1 | EO42: Поправка: Гл.12.Прил.8.п.8. 3_12.00.01.11.001 | EQ42: 0 | ER42: 98.52 | ES42: 0 | ET42: 0 | EU42: 0 | EV42: 98.52 | EW42: 9.64 | EX42: 0 | EY42: 0 | FQ42: 0 | FR42: 0 | FS42: 0 | FX42: 91 | FY42: 48 | GD42: 1 | GF42: 1114236003 | GG42: 2 | GH42: 1 | GI42: 2 | GJ42: 0 | GK42: 0 | GL42: =ROUND(IF(AND(BH42=3,BI42=3,FS42<>0),P42,0),2) -> 0 | GM42: =ROUND(O42+X42+Y42,2)+GX42 -> 1153.75 | GN42: =IF(OR(BI42=0,BI42=1),GM42-GX42,0) -> 1153.75 | GO42: =IF(BI42=2,GM42-GX42,0) -> 0 | GP42: =IF(BI42=4,GM42-GX42,0) -> 0 | GR42: 0 | GS42: 3 | GT42: 0 | GV42: =ROUND((GT42),6) -> 0 | GW42: 1 | GX42: =ROUND(HC42*I42,2) -> 0 | HA42: 0 | HB42: 0 | HC42: =GV42*GW42 -> 0 | HS42: 0 | IK42: 0
A43: 17 | B43: 1 | C43: =ROW(SmtRes!A38) -> 38 | D43: =ROW(EtalonRes!A42) -> 42 | E43: 8 | F43: 6.67-6-1 | G43: Демонтаж кабеля | H43: 100 м | I43: =ROUND((80+300+10)/100,9) -> 3.9 | J43: 0 | K43: =ROUND((80+300+10)/100,9) -> 3.9 | O43: =ROUND(CP43,2) -> 27202.4 | P43: =ROUND((ROUND((AC43*AW43*I43),2)*BC43),2) -> 0 | Q43: =(ROUND((ROUND((((ET43*1.2))*AV43*I43),2)*BB43),2)+ROUND((ROUND(((AE43-((EU43*1.2)))*AV43*I43),2)*BS43),2)) -> 0 | R43: =(ROUND((ROUND((((EU43*1.2))*AV43*I43),2)*BS43),2)+ROUND((ROUND(((AE43-((EU43*1.2)))*AV43*I43),2)*BS43),2)) -> 0 | S43: =ROUND((ROUND((AF43*AV43*I43),2)*BA43),2) -> 27202.4 | T43: =ROUND(CU43*I43,2) -> 0 | U43: =CV43*I43 -> 47.235614 | V43: =CW43*I43 -> 0 | W43: =ROUND(CX43*I43,2) -> 0 | X43: =(ROUND((((S43+ROUND((ROUND((((EU43*1.2))*AV43*I43),2)*BS43),2))*AT43)/100),2)+ROUND(((ROUND((ROUND(((AE43-((EU43*1.2)))*AV43*I43),2)*BS43),2)*AT43)/100),2)) -> 24754.18 | Y43: =(ROUND((((S43+ROUND((ROUND((((EU43*1.2))*AV43*I43),2)*BS43),2))*AU43)/100),2)+ROUND(((ROUND((ROUND(((AE43-((EU43*1.2)))*AV43*I43),2)*BS43),2)*AU43)/100),2)) -> 13057.15 | AA43: 55919549 | AB43: =ROUND((AC43+AD43+AF43),6) -> 118.224 | AC43: =ROUND(((ES43*1)),6) -> 0 | AD43: =ROUND(((((ET43*1.2))-((EU43*1.2)))+AE43),6) -> 0 | AE43: =ROUND(((EU43*1.2)),6) -> 0 | AF43: =ROUND(((EV43*1.2)),6) -> 118.224 | AG43: =ROUND((AP43),6) -> 0 | AH43: =((EW43*1.2)) -> 11.568 | AI43: =((EX43*1.2)) -> 0 | AJ43: =(AS43) -> 0 | AK43: 98.52 | AL43: 0 | AM43: 0 | AN43: 0 | AO43: 98.52 | AP43: 0 | AQ43: 9.64 | AR43: 0 | AS43: 0 | AT43: 91 | AU43: 48 | AV43: 1.047 | AW43: 1 | AZ43: 1 | BA43: 56.35 | BB43: 1 | BC43: 1 | BH43: 0 | BI43: 1 | BJ43: ТСН-2001.6. Доп. 1-42. Сб. 67, т. 6, поз. 1 | BM43: 106 | BN43: 0 | BO43: 6.67-6-1 | BP43: 1 | BQ43: 60 | BR43: 0 | BS43: 56.35 | BT43: 1 | BU43: 1 | BV43: 1 | BW43: 1 | BX43: 1 | BZ43: 91 | CA43: 48 | CE43: 1566 | CF43: 0 | CG43: 0 | CM43: 0 | CN43: Поправка: Гл.12.Прил.8.п.8. 3_12.00.01.11.001 Наименование: При наличии напряженных и стесненных условий производства работ (стесненность, сложность складирования и транспортной логистики и т.п.) для объектов, расположенных в пределах круговой магистральной системы улиц "Садовое кольцо" города Москвы | CO43: 0 | CP43: =(P43+Q43+S43) -> 27202.4 | CQ43: =ROUND((ROUND((AC43*AW43*1),2)*BC43),2) -> 0 | CR43: =(ROUND((ROUND((((ET43*1.2))*AV43*1),2)*BB43),2)+ROUND((ROUND(((AE43-((EU43*1.2)))*AV43*1),2)*BS43),2)) -> 0 | CS43: =(ROUND((ROUND((((EU43*1.2))*AV43*1),2)*BS43),2)+ROUND((ROUND(((AE43-((EU43*1.2)))*AV43*1),2)*BS43),2)) -> 0 | CT43: =ROUND((ROUND((AF43*AV43*1),2)*BA43),2) -> 6975 | CU43: =AG43 -> 0 | CV43: =(AH43*AV43) -> 12.111696 | CW43: =AI43 -> 0 | CX43: =AJ43 -> 0 | CY43: =(ROUND((((S43+ROUND((ROUND((((EU43*1.2))*AV43*1),2)*BS43),2))*AT43)/100),2)+ROUND(((ROUND((ROUND(((AE43-((EU43*1.2)))*AV43*1),2)*BS43),2)*AT43)/100),2)) -> 24754.18 | CZ43: =(ROUND((((S43+ROUND((ROUND((((EU43*1.2))*AV43*1),2)*BS43),2))*AU43)/100),2)+ROUND(((ROUND((ROUND(((AE43-((EU43*1.2)))*AV43*1),2)*BS43),2)*AU43)/100),2)) -> 13057.15 | DB43: 28 | DD43: *1 | DE43: *1,2 | DF43: *1,2 | DG43: *1,2 | DI43: *1,2 | DJ43: *1,2 | DN43: 0 | DO43: 0 | DP43: 1 | DQ43: 1 | DU43: 1003 | DV43: 100 м | DW43: 100 м | DX43: 100 | EE43: 55393738 | EF43: 60 | EG43: Ремонтно-строительные работы | EH43: 0 | EJ43: 1 | EK43: 106 | EL43: ТСН-2001.6-67. Электромонтажные работы | EM43: ТСН-2001.6-67-1 | EO43: Поправка: Гл.12.Прил.8.п.8. 3_12.00.01.11.001 | EQ43: 0 | ER43: 98.52 | ES43: 0 | ET43: 0 | EU43: 0 | EV43: 98.52 | EW43: 9.64 | EX43: 0 | EY43: 0 | FQ43: 0 | FR43: 0 | FS43: 0 | FX43: 91 | FY43: 48 | GD43: 1 | GF43: 1114236003 | GG43: 2 | GH43: 1 | GI43: 2 | GJ43: 0 | GK43: 0 | GL43: =ROUND(IF(AND(BH43=3,BI43=3,FS43<>0),P43,0),2) -> 0 | GM43: =ROUND(O43+X43+Y43,2)+GX43 -> 65013.73 | GN43: =IF(OR(BI43=0,BI43=1),GM43-GX43,0) -> 65013.73 | GO43: =IF(BI43=2,GM43-GX43,0) -> 0 | GP43: =IF(BI43=4,GM43-GX43,0) -> 0 | GR43: 0 | GS43: 3 | GT43: 0 | GV43: =ROUND((GT43),6) -> 0 | GW43: 1 | GX43: =ROUND(HC43*I43,2) -> 0 | HA43: 0 | HB43: 0 | HC43: =GV43*GW43 -> 0 | HS43: 0 | IK43: 0
A44: 17 | B44: 1 | C44: =ROW(SmtRes!A40) -> 40 | D44: =ROW(EtalonRes!A44) -> 44 | E44: 9 | F44: 6.67-5-12 | G44: Демонтаж трубных проводок, трубы в борозде диаметром 25 мм / ПВХ | H44: 100 м | I44: =ROUND(200/100,9) -> 2 | J44: 0 | K44: =ROUND(200/100,9) -> 2 | O44: =ROUND(CP44,2) -> 804.67 | P44: =ROUND((ROUND((AC44*AW44*I44),2)*BC44),2) -> 0 | Q44: =(ROUND((ROUND((((ET44*1.2))*AV44*I44),2)*BB44),2)+ROUND((ROUND(((AE44-((EU44*1.2)))*AV44*I44),2)*BS44),2)) -> 0 | R44: =(ROUND((ROUND((((EU44*1.2))*AV44*I44),2)*BS44),2)+ROUND((ROUND(((AE44-((EU44*1.2)))*AV44*I44),2)*BS44),2)) -> 0 | S44: =ROUND((ROUND((AF44*AV44*I44),2)*BA44),2) -> 804.67 | T44: =ROUND(CU44*I44,2) -> 0 | U44: =CV44*I44 -> 76.489632 | V44: =CW44*I44 -> 0 | W44: =ROUND(CX44*I44,2) -> 0 | X44: =(ROUND((((S44+ROUND((ROUND((((EU44*1.2))*AV44*I44),2)*BS44),2))*AT44)/100),2)+ROUND(((ROUND((ROUND(((AE44-((EU44*1.2)))*AV44*I44),2)*BS44),2)*AT44)/100),2)) -> 732.25 | Y44: =(ROUND((((S44+ROUND((ROUND((((EU44*1.2))*AV44*I44),2)*BS44),2))*AU44)/100),2)+ROUND(((ROUND((ROUND(((AE44-((EU44*1.2)))*AV44*I44),2)*BS44),2)*AU44)/100),2)) -> 386.24 | AA44: 55919547 | AB44: =ROUND((AC44+AD44+AF44),6) -> 384.276 | AC44: =ROUND(((ES44*1)),6) -> 0 | AD44: =ROUND(((((ET44*1.2))-((EU44*1.2)))+AE44),6) -> 0 | AE44: =ROUND(((EU44*1.2)),6) -> 0 | AF44: =ROUND(((EV44*1.2)),6) -> 384.276 | AG44: =ROUND((AP44),6) -> 0 | AH44: =((EW44*1.2)) -> 36.528 | AI44: =((EX44*1.2)) -> 0 | AJ44: =(AS44) -> 0 | AK44: 320.23 | AL44: 0 | AM44: 0 | AN44: 0 | AO44: 320.23 | AP44: 0 | AQ44: 30.44 | AR44: 0 | AS44: 0 | AT44: 91 | AU44: 48 | AV44: 1.047 | AW44: 1 | AZ44: 1 | BA44: 1 | BB44: 1 | BC44: 1 | BH44: 0 | BI44: 1 | BJ44: ТСН-2001.6. Доп. 1-42. Сб. 67, т. 5, поз. 12 | BM44: 106 | BN44: 0 | BO44: 6.67-5-12 | BP44: 1 | BQ44: 60 | BR44: 0 | BS44: 1 | BT44: 1 | BU44: 1 | BV44: 1 | BW44: 1 | BX44: 1 | BZ44: 91 | CA44: 48 | CE44: 1566 | CF44: 0 | CG44: 0 | CM44: 0 | CN44: Поправка: Гл.12.Прил.8.п.8. 3_12.00.01.11.001 Наименование: При наличии напряженных и стесненных условий производства работ (стесненность, сложность складирования и транспортной логистики и т.п.) для объектов, расположенных в пределах круговой магистральной системы улиц "Садовое кольцо" города Москвы | CO44: 0 | CP44: =(P44+Q44+S44) -> 804.67 | CQ44: =ROUND((ROUND((AC44*AW44*1),2)*BC44),2) -> 0 | CR44: =(ROUND((ROUND((((ET44*1.2))*AV44*1),2)*BB44),2)+ROUND((ROUND(((AE44-((EU44*1.2)))*AV44*1),2)*BS44),2)) -> 0 | CS44: =(ROUND((ROUND((((EU44*1.2))*AV44*1),2)*BS44),2)+ROUND((ROUND(((AE44-((EU44*1.2)))*AV44*1),2)*BS44),2)) -> 0 | CT44: =ROUND((ROUND((AF44*AV44*1),2)*BA44),2) -> 402.34 | CU44: =AG44 -> 0 | CV44: =(AH44*AV44) -> 38.244816 | CW44: =AI44 -> 0 | CX44: =AJ44 -> 0 | CY44: =(ROUND((((S44+ROUND((ROUND((((EU44*1.2))*AV44*1),2)*BS44),2))*AT44)/100),2)+ROUND(((ROUND((ROUND(((AE44-((EU44*1.2)))*AV44*1),2)*BS44),2)*AT44)/100),2)) -> 732.25 | CZ44: =(ROUND((((S44+ROUND((ROUND((((EU44*1.2))*AV44*1),2)*BS44),2))*AU44)/100),2)+ROUND(((ROUND((ROUND(((AE44-((EU44*1.2)))*AV44*1),2)*BS44),2)*AU44)/100),2)) -> 386.24 | DB44: 29 | DD44: *1 | DE44: *1,2 | DF44: *1,2 | DG44: *1,2 | DI44: *1,2 | DJ44: *1,2 | DN44: 0 | DO44: 0 | DP44: 1 | DQ44: 1 | DU44: 1003 | DV44: 100 м | DW44: 100 м | DX44: 100 | EE44: 55393738 | EF44: 60 | EG44: Ремонтно-строительные работы | EH44: 0 | EJ44: 1 | EK44: 106 | EL44: ТСН-2001.6-67. Электромонтажные работы | EM44: ТСН-2001.6-67-1 | EO44: Поправка: Гл.12.Прил.8.п.8. 3_12.00.01.11.001 | EQ44: 0 | ER44: 320.23 | ES44: 0 | ET44: 0 | EU44: 0 | EV44: 320.23 | EW44: 30.44 | EX44: 0 | EY44: 0 | FQ44: 0 | FR44: 0 | FS44: 0 | FX44: 91 | FY44: 48 | GD44: 1 | GF44: -1403822920 | GG44: 2 | GH44: 1 | GI44: 2 | GJ44: 0 | GK44: 0 | GL44: =ROUND(IF(AND(BH44=3,BI44=3,FS44<>0),P44,0),2) -> 0 | GM44: =ROUND(O44+X44+Y44,2)+GX44 -> 1923.16 | GN44: =IF(OR(BI44=0,BI44=1),GM44-GX44,0) -> 1923.16 | GO44: =IF(BI44=2,GM44-GX44,0) -> 0 | GP44: =IF(BI44=4,GM44-GX44,0) -> 0 | GR44: 0 | GS44: 3 | GT44: 0 | GV44: =ROUND((GT44),6) -> 0 | GW44: 1 | GX44: =ROUND(HC44*I44,2) -> 0 | HA44: 0 | HB44: 0 | HC44: =GV44*GW44 -> 0 | HS44: 0 | IK44: 0
A45: 17 | B45: 1 | C45: =ROW(SmtRes!A42) -> 42 | D45: =ROW(EtalonRes!A46) -> 46 | E45: 9 | F45: 6.67-5-12 | G45: Демонтаж трубных проводок, трубы в борозде диаметром 25 мм / ПВХ | H45: 100 м | I45: =ROUND(200/100,9) -> 2 | J45: 0 | K45: =ROUND(200/100,9) -> 2 | O45: =ROUND(CP45,2) -> 45343.15 | P45: =ROUND((ROUND((AC45*AW45*I45),2)*BC45),2) -> 0 | Q45: =(ROUND((ROUND((((ET45*1.2))*AV45*I45),2)*BB45),2)+ROUND((ROUND(((AE45-((EU45*1.2)))*AV45*I45),2)*BS45),2)) -> 0 | R45: =(ROUND((ROUND((((EU45*1.2))*AV45*I45),2)*BS45),2)+ROUND((ROUND(((AE45-((EU45*1.2)))*AV45*I45),2)*BS45),2)) -> 0 | S45: =ROUND((ROUND((AF45*AV45*I45),2)*BA45),2) -> 45343.15 | T45: =ROUND(CU45*I45,2) -> 0 | U45: =CV45*I45 -> 76.489632 | V45: =CW45*I45 -> 0 | W45: =ROUND(CX45*I45,2) -> 0 | X45: =(ROUND((((S45+ROUND((ROUND((((EU45*1.2))*AV45*I45),2)*BS45),2))*AT45)/100),2)+ROUND(((ROUND((ROUND(((AE45-((EU45*1.2)))*AV45*I45),2)*BS45),2)*AT45)/100),2)) -> 41262.27 | Y45: =(ROUND((((S45+ROUND((ROUND((((EU45*1.2))*AV45*I45),2)*BS45),2))*AU45)/100),2)+ROUND(((ROUND((ROUND(((AE45-((EU45*1.2)))*AV45*I45),2)*BS45),2)*AU45)/100),2)) -> 21764.71 | AA45: 55919549 | AB45: =ROUND((AC45+AD45+AF45),6) -> 384.276 | AC45: =ROUND(((ES45*1)),6) -> 0 | AD45: =ROUND(((((ET45*1.2))-((EU45*1.2)))+AE45),6) -> 0 | AE45: =ROUND(((EU45*1.2)),6) -> 0 | AF45: =ROUND(((EV45*1.2)),6) -> 384.276 | AG45: =ROUND((AP45),6) -> 0 | AH45: =((EW45*1.2)) -> 36.528 | AI45: =((EX45*1.2)) -> 0 | AJ45: =(AS45) -> 0 | AK45: 320.23 | AL45: 0 | AM45: 0 | AN45: 0 | AO45: 320.23 | AP45: 0 | AQ45: 30.44 | AR45: 0 | AS45: 0 | AT45: 91 | AU45: 48 | AV45: 1.047 | AW45: 1 | AZ45: 1 | BA45: 56.35 | BB45: 1 | BC45: 1 | BH45: 0 | BI45: 1 | BJ45: ТСН-2001.6. Доп. 1-42. Сб. 67, т. 5, поз. 12 | BM45: 106 | BN45: 0 | BO45: 6.67-5-12 | BP45: 1 | BQ45: 60 | BR45: 0 | BS45: 56.35 | BT45: 1 | BU45: 1 | BV45: 1 | BW45: 1 | BX45: 1 | BZ45: 91 | CA45: 48 | CE45: 1566 | CF45: 0 | CG45: 0 | CM45: 0 | CN45: Поправка: Гл.12.Прил.8.п.8. 3_12.00.01.11.001 Наименование: При наличии напряженных и стесненных условий производства работ (стесненность, сложность складирования и транспортной логистики и т.п.) для объектов, расположенных в пределах круговой магистральной системы улиц "Садовое кольцо" города Москвы | CO45: 0 | CP45: =(P45+Q45+S45) -> 45343.15 | CQ45: =ROUND((ROUND((AC45*AW45*1),2)*BC45),2) -> 0 | CR45: =(ROUND((ROUND((((ET45*1.2))*AV45*1),2)*BB45),2)+ROUND((ROUND(((AE45-((EU45*1.2)))*AV45*1),2)*BS45),2)) -> 0 | CS45: =(ROUND((ROUND((((EU45*1.2))*AV45*1),2)*BS45),2)+ROUND((ROUND(((AE45-((EU45*1.2)))*AV45*1),2)*BS45),2)) -> 0 | CT45: =ROUND((ROUND((AF45*AV45*1),2)*BA45),2) -> 22671.86 | CU45: =AG45 -> 0 | CV45: =(AH45*AV45) -> 38.244816 | CW45: =AI45 -> 0 | CX45: =AJ45 -> 0 | CY45: =(ROUND((((S45+ROUND((ROUND((((EU45*1.2))*AV45*1),2)*BS45),2))*AT45)/100),2)+ROUND(((ROUND((ROUND(((AE45-((EU45*1.2)))*AV45*1),2)*BS45),2)*AT45)/100),2)) -> 41262.27 | CZ45: =(ROUND((((S45+ROUND((ROUND((((EU45*1.2))*AV45*1),2)*BS45),2))*AU45)/100),2)+ROUND(((ROUND((ROUND(((AE45-((EU45*1.2)))*AV45*1),2)*BS45),2)*AU45)/100),2)) -> 21764.71 | DB45: 30 | DD45: *1 | DE45: *1,2 | DF45: *1,2 | DG45: *1,2 | DI45: *1,2 | DJ45: *1,2 | DN45: 0 | DO45: 0 | DP45: 1 | DQ45: 1 | DU45: 1003 | DV45: 100 м | DW45: 100 м | DX45: 100 | EE45: 55393738 | EF45: 60 | EG45: Ремонтно-строительные работы | EH45: 0 | EJ45: 1 | EK45: 106 | EL45: ТСН-2001.6-67. Электромонтажные работы | EM45: ТСН-2001.6-67-1 | EO45: Поправка: Гл.12.Прил.8.п.8. 3_12.00.01.11.001 | EQ45: 0 | ER45: 320.23 | ES45: 0 | ET45: 0 | EU45: 0 | EV45: 320.23 | EW45: 30.44 | EX45: 0 | EY45: 0 | FQ45: 0 | FR45: 0 | FS45: 0 | FX45: 91 | FY45: 48 | GD45: 1 | GF45: -1403822920 | GG45: 2 | GH45: 1 | GI45: 2 | GJ45: 0 | GK45: 0 | GL45: =ROUND(IF(AND(BH45=3,BI45=3,FS45<>0),P45,0),2) -> 0 | GM45: =ROUND(O45+X45+Y45,2)+GX45 -> 108370.13 | GN45: =IF(OR(BI45=0,BI45=1),GM45-GX45,0) -> 108370.13 | GO45: =IF(BI45=2,GM45-GX45,0) -> 0 | GP45: =IF(BI45=4,GM45-GX45,0) -> 0 | GR45: 0 | GS45: 3 | GT45: 0 | GV45: =ROUND((GT45),6) -> 0 | GW45: 1 | GX45: =ROUND(HC45*I45,2) -> 0 | HA45: 0 | HB45: 0 | HC45: =GV45*GW45 -> 0 | HS45: 0 | IK45: 0
A46: 17 | B46: 1 | C46: =ROW(SmtRes!A53) -> 53 | D46: =ROW(EtalonRes!A62) -> 62 | E46: 10 | F46: 4.8-174-1 | G46: Прокладка металлического рукава, наружный диаметр до 48 мм / демонтаж металлорукава | H46: 100 м | I46: =ROUND(10/100,9) -> 0.1 | J46: 0 | K46: =ROUND(10/100,9) -> 0.1 | O46: =ROUND(CP46,2) -> 18.74 | P46: =ROUND((ROUND((AC46*AW46*I46),2)*BC46),2) -> 0 | Q46: =(ROUND((ROUND(((((ET46*1.2)*0.3))*AV46*I46),2)*BB46),2)+ROUND((ROUND(((AE46-(((EU46*1.2)*0.3)))*AV46*I46),2)*BS46),2)) -> 4.86 | R46: =(ROUND((ROUND(((((EU46*1.2)*0.3))*AV46*I46),2)*BS46),2)+ROUND((ROUND(((AE46-(((EU46*1.2)*0.3)))*AV46*I46),2)*BS46),2)) -> 0.09 | S46: =ROUND((ROUND((AF46*AV46*I46),2)*BA46),2) -> 13.88 | T46: =ROUND(CU46*I46,2) -> 0 | U46: =CV46*I46 -> 1.1269908 | V46: =CW46*I46 -> 0 | W46: =ROUND(CX46*I46,2) -> 0 | X46: =(ROUND((((S46+ROUND((ROUND(((((EU46*1.2)*0.3))*AV46*I46),2)*BS46),2))*AT46)/100),2)+ROUND(((ROUND((ROUND(((AE46-(((EU46*1.2)*0.3)))*AV46*I46),2)*BS46),2)*AT46)/100),2)) -> 13.55 | Y46: =(ROUND((((S46+ROUND((ROUND(((((EU46*1.2)*0.3))*AV46*I46),2)*BS46),2))*AU46)/100),2)+ROUND(((ROUND((ROUND(((AE46-(((EU46*1.2)*0.3)))*AV46*I46),2)*BS46),2)*AU46)/100),2)) -> 7.12 | AA46: 55919547 | AB46: =ROUND((AC46+AD46+AF46),6) -> 179.0748 | AC46: =ROUND((((ES46*1)*0)),6) -> 0 | AD46: =ROUND((((((ET46*1.2)*0.3))-(((EU46*1.2)*0.3)))+AE46),6) -> 46.4616 | AE46: =ROUND((((EU46*1.2)*0.3)),6) -> 0.9072 | AF46: =ROUND((((EV46*1.2)*0.3)),6) -> 132.6132 | AG46: =ROUND((AP46),6) -> 0 | AH46: =(((EW46*1.2)*0.3)) -> 10.764 | AI46: =(((EX46*1.2)*0.3)) -> 0 | AJ46: =(AS46) -> 0 | AK46: 2261.17 | AL46: 1763.74 | AM46: 129.06 | AN46: 2.52 | AO46: 368.37 | AP46: 0 | AQ46: 29.9 | AR46: 0 | AS46: 0 | AT46: 97 | AU46: 51 | AV46: 1.047 | AW46: 1 | AZ46: 1 | BA46: 1 | BB46: 1 | BC46: 1 | BH46: 0 | BI46: 2 | BJ46: ТСН-2001.4 Доп. 80, Сб. 8, т. 174, поз. 1 | BM46: 67 | BN46: 0 | BO46: 4.8-174-1 | BP46: 1 | BQ46: 40 | BR46: 0 | BS46: 1 | BT46: 1 | BU46: 1 | BV46: 1 | BW46: 1 | BX46: 1 | BZ46: 97 | CA46: 51 | CE46: 1566 | CF46: 0 | CG46: 0 | CM46: 0 | CN46: Поправка: Гл.12.Прил.8.п.8. 3_12.00.01.11.001 Наименование: При наличии напряженных и стесненных условий производства работ (стесненность, сложность складирования и транспортной логистики и т.п.) для объектов, расположенных в пределах круговой магистральной системы улиц "Садовое кольцо" города Москвы Поправка: Гл.4.Прил.2.2.п.2.2.29_04.00.01.35.003 Наименование: При демонтаже оборудования, предназначенного в лом | CO46: 0 | CP46: =(P46+Q46+S46) -> 18.74 | CQ46: =ROUND((ROUND((AC46*AW46*1),2)*BC46),2) -> 0 | CR46: =(ROUND((ROUND(((((ET46*1.2)*0.3))*AV46*1),2)*BB46),2)+ROUND((ROUND(((AE46-(((EU46*1.2)*0.3)))*AV46*1),2)*BS46),2)) -> 48.65 | CS46: =(ROUND((ROUND(((((EU46*1.2)*0.3))*AV46*1),2)*BS46),2)+ROUND((ROUND(((AE46-(((EU46*1.2)*0.3)))*AV46*1),2)*BS46),2)) -> 0.95 | CT46: =ROUND((ROUND((AF46*AV46*1),2)*BA46),2) -> 138.85 | CU46: =AG46 -> 0 | CV46: =(AH46*AV46) -> 11.269908 | CW46: =AI46 -> 0 | CX46: =AJ46 -> 0 | CY46: =(ROUND((((S46+ROUND((ROUND(((((EU46*1.2)*0.3))*AV46*1),2)*BS46),2))*AT46)/100),2)+ROUND(((ROUND((ROUND(((AE46-(((EU46*1.2)*0.3)))*AV46*1),2)*BS46),2)*AT46)/100),2)) -> 14.39 | CZ46: =(ROUND((((S46+ROUND((ROUND(((((EU46*1.2)*0.3))*AV46*1),2)*BS46),2))*AU46)/100),2)+ROUND(((ROUND((ROUND(((AE46-(((EU46*1.2)*0.3)))*AV46*1),2)*BS46),2)*AU46)/100),2)) -> 7.56 | DB46: 31 | DD46: *1)*0 | DE46: *1,2)*0,3 | DF46: *1,2)*0,3 | DG46: *1,2)*0,3 | DI46: *1,2)*0,3 | DJ46: *1,2)*0,3 | DN46: 0 | DO46: 0 | DP46: 1 | DQ46: 1 | DU46: 1003 | DV46: 100 м | DW46: 100 м | DX46: 100 | EE46: 55393699 | EF46: 40 | EG46: Монтаж оборудования | EH46: 0 | EJ46: 2 | EK46: 67 | EL46: ТСН-2001.4-8. Электротехнические установки | EM46: ТСН-2001.4-8-1 | EO46: Поправка: Гл.12.Прил.8.п.8. 3_12.00.01.11.001 Поправка: Гл.4.Прил.2.2.п.2.2.29_04.00.01.35.003 | EQ46: 0 | ER46: 2261.17 | ES46: 1763.74 | ET46: 129.06 | EU46: 2.52 | EV46: 368.37 | EW46: 29.9 | EX46: 0 | EY46: 0 | FQ46: 0 | FR46: 0 | FS46: 0 | FX46: 97 | FY46: 51 | GD46: 1 | GF46: 303861211 | GG46: 2 | GH46: 1 | GI46: 2 | GJ46: 0 | GK46: 0 | GL46: =ROUND(IF(AND(BH46=3,BI46=3,FS46<>0),P46,0),2) -> 0 | GM46: =ROUND(O46+X46+Y46,2)+GX46 -> 39.41 | GN46: =IF(OR(BI46=0,BI46=1),GM46-GX46,0) -> 0 | GO46: =IF(BI46=2,GM46-GX46,0) -> 39.41 | GP46: =IF(BI46=4,GM46-GX46,0) -> 0 | GR46: 0 | GS46: 3 | GT46: 0 | GV46: =ROUND((GT46),6) -> 0 | GW46: 1 | GX46: =ROUND(HC46*I46,2) -> 0 | HA46: 0 | HB46: 0 | HC46: =GV46*GW46 -> 0 | HS46: 0 | IK46: 0
A47: 17 | B47: 1 | C47: =ROW(SmtRes!A64) -> 64 | D47: =ROW(EtalonRes!A78) -> 78 | E47: 10 | F47: 4.8-174-1 | G47: Прокладка металлического рукава, наружный диаметр до 48 мм / демонтаж металлорукава | H47: 100 м | I47: =ROUND(10/100,9) -> 0.1 | J47: 0 | K47: =ROUND(10/100,9) -> 0.1 | O47: =ROUND(CP47,2) -> 849.4 | P47: =ROUND((ROUND((AC47*AW47*I47),2)*BC47),2) -> 0 | Q47: =(ROUND((ROUND(((((ET47*1.2)*0.3))*AV47*I47),2)*BB47),2)+ROUND((ROUND(((AE47-(((EU47*1.2)*0.3)))*AV47*I47),2)*BS47),2)) -> 67.26 | R47: =(ROUND((ROUND(((((EU47*1.2)*0.3))*AV47*I47),2)*BS47),2)+ROUND((ROUND(((AE47-(((EU47*1.2)*0.3)))*AV47*I47),2)*BS47),2)) -> 5.07 | S47: =ROUND((ROUND((AF47*AV47*I47),2)*BA47),2) -> 782.14 | T47: =ROUND(CU47*I47,2) -> 0 | U47: =CV47*I47 -> 1.1269908 | V47: =CW47*I47 -> 0 | W47: =ROUND(CX47*I47,2) -> 0 | X47: =(ROUND((((S47+ROUND((ROUND(((((EU47*1.2)*0.3))*AV47*I47),2)*BS47),2))*AT47)/100),2)+ROUND(((ROUND((ROUND(((AE47-(((EU47*1.2)*0.3)))*AV47*I47),2)*BS47),2)*AT47)/100),2)) -> 763.59 | Y47: =(ROUND((((S47+ROUND((ROUND(((((EU47*1.2)*0.3))*AV47*I47),2)*BS47),2))*AU47)/100),2)+ROUND(((ROUND((ROUND(((AE47-(((EU47*1.2)*0.3)))*AV47*I47),2)*BS47),2)*AU47)/100),2)) -> 401.48 | AA47: 55919549 | AB47: =ROUND((AC47+AD47+AF47),6) -> 179.0748 | AC47: =ROUND((((ES47*1)*0)),6) -> 0 | AD47: =ROUND((((((ET47*1.2)*0.3))-(((EU47*1.2)*0.3)))+AE47),6) -> 46.4616 | AE47: =ROUND((((EU47*1.2)*0.3)),6) -> 0.9072 | AF47: =ROUND((((EV47*1.2)*0.3)),6) -> 132.6132 | AG47: =ROUND((AP47),6) -> 0 | AH47: =(((EW47*1.2)*0.3)) -> 10.764 | AI47: =(((EX47*1.2)*0.3)) -> 0 | AJ47: =(AS47) -> 0 | AK47: 2261.17 | AL47: 1763.74 | AM47: 129.06 | AN47: 2.52 | AO47: 368.37 | AP47: 0 | AQ47: 29.9 | AR47: 0 | AS47: 0 | AT47: 97 | AU47: 51 | AV47: 1.047 | AW47: 1 | AZ47: 1 | BA47: 56.35 | BB47: 13.84 | BC47: 4.04 | BH47: 0 | BI47: 2 | BJ47: ТСН-2001.4 Доп. 80, Сб. 8, т. 174, поз. 1 | BM47: 67 | BN47: 0 | BO47: 4.8-174-1 | BP47: 1 | BQ47: 40 | BR47: 0 | BS47: 56.35 | BT47: 1 | BU47: 1 | BV47: 1 | BW47: 1 | BX47: 1 | BZ47: 97 | CA47: 51 | CE47: 1566 | CF47: 0 | CG47: 0 | CM47: 0 | CN47: Поправка: Гл.12.Прил.8.п.8. 3_12.00.01.11.001 Наименование: При наличии напряженных и стесненных условий производства работ (стесненность, сложность складирования и транспортной логистики и т.п.) для объектов, расположенных в пределах круговой магистральной системы улиц "Садовое кольцо" города Москвы Поправка: Гл.4.Прил.2.2.п.2.2.29_04.00.01.35.003 Наименование: При демонтаже оборудования, предназначенного в лом | CO47: 0 | CP47: =(P47+Q47+S47) -> 849.4 | CQ47: =ROUND((ROUND((AC47*AW47*1),2)*BC47),2) -> 0 | CR47: =(ROUND((ROUND(((((ET47*1.2)*0.3))*AV47*1),2)*BB47),2)+ROUND((ROUND(((AE47-(((EU47*1.2)*0.3)))*AV47*1),2)*BS47),2)) -> 673.32 | CS47: =(ROUND((ROUND(((((EU47*1.2)*0.3))*AV47*1),2)*BS47),2)+ROUND((ROUND(((AE47-(((EU47*1.2)*0.3)))*AV47*1),2)*BS47),2)) -> 53.53 | CT47: =ROUND((ROUND((AF47*AV47*1),2)*BA47),2) -> 7824.2 | CU47: =AG47 -> 0 | CV47: =(AH47*AV47) -> 11.269908 | CW47: =AI47 -> 0 | CX47: =AJ47 -> 0 | CY47: =(ROUND((((S47+ROUND((ROUND(((((EU47*1.2)*0.3))*AV47*1),2)*BS47),2))*AT47)/100),2)+ROUND(((ROUND((ROUND(((AE47-(((EU47*1.2)*0.3)))*AV47*1),2)*BS47),2)*AT47)/100),2)) -> 810.6 | CZ47: =(ROUND((((S47+ROUND((ROUND(((((EU47*1.2)*0.3))*AV47*1),2)*BS47),2))*AU47)/100),2)+ROUND(((ROUND((ROUND(((AE47-(((EU47*1.2)*0.3)))*AV47*1),2)*BS47),2)*AU47)/100),2)) -> 426.19 | DB47: 33 | DD47: *1)*0 | DE47: *1,2)*0,3 | DF47: *1,2)*0,3 | DG47: *1,2)*0,3 | DI47: *1,2)*0,3 | DJ47: *1,2)*0,3 | DN47: 0 | DO47: 0 | DP47: 1 | DQ47: 1 | DU47: 1003 | DV47: 100 м | DW47: 100 м | DX47: 100 | EE47: 55393699 | EF47: 40 | EG47: Монтаж оборудования | EH47: 0 | EJ47: 2 | EK47: 67 | EL47: ТСН-2001.4-8. Электротехнические установки | EM47: ТСН-2001.4-8-1 | EO47: Поправка: Гл.12.Прил.8.п.8. 3_12.00.01.11.001 Поправка: Гл.4.Прил.2.2.п.2.2.29_04.00.01.35.003 | EQ47: 0 | ER47: 2261.17 | ES47: 1763.74 | ET47: 129.06 | EU47: 2.52 | EV47: 368.37 | EW47: 29.9 | EX47: 0 | EY47: 0 | FQ47: 0 | FR47: 0 | FS47: 0 | FX47: 97 | FY47: 51 | GD47: 1 | GF47: 303861211 | GG47: 2 | GH47: 1 | GI47: 2 | GJ47: 0 | GK47: 0 | GL47: =ROUND(IF(AND(BH47=3,BI47=3,FS47<>0),P47,0),2) -> 0 | GM47: =ROUND(O47+X47+Y47,2)+GX47 -> 2014.47 | GN47: =IF(OR(BI47=0,BI47=1),GM47-GX47,0) -> 0 | GO47: =IF(BI47=2,GM47-GX47,0) -> 2014.47 | GP47: =IF(BI47=4,GM47-GX47,0) -> 0 | GR47: 0 | GS47: 3 | GT47: 0 | GV47: =ROUND((GT47),6) -> 0 | GW47: 1 | GX47: =ROUND(HC47*I47,2) -> 0 | HA47: 0 | HB47: 0 | HC47: =GV47*GW47 -> 0 | HS47: 0 | IK47: 0
A49: 51 | B49: =B24 -> 1 | C49: =A24 -> 4 | D49: =ROW(A24) -> 24 | F49: =IF(F24<>"",F24,"") -> Новый раздел | G49: =IF(G24<>"",G24,"") -> Демонтаж | H49: 0 | O49: =ROUND(AB49,2) -> 1407.26 | P49: =ROUND(AC49,2) -> 0 | Q49: =ROUND(AD49,2) -> 11.43 | R49: =ROUND(AE49,2) -> 1.28 | S49: =ROUND(AF49,2) -> 1395.83 | T49: =ROUND(AG49,2) -> 0 | U49: =AH49 -> 131.88786 | V49: =AI49 -> 0 | W49: =ROUND(AJ49,2) -> 0 | X49: =ROUND(AK49,2) -> 1276.09 | Y49: =ROUND(AL49,2) -> 675.36 | AB49: =ROUND(SUMIF(AA28:AA47,"=55919547",O28:O47),2) -> 1407.26 | AC49: =ROUND(SUMIF(AA28:AA47,"=55919547",P28:P47),2) -> 0 | AD49: =ROUND(SUMIF(AA28:AA47,"=55919547",Q28:Q47),2) -> 11.43 | AE49: =ROUND(SUMIF(AA28:AA47,"=55919547",R28:R47),2) -> 1.28 | AF49: =ROUND(SUMIF(AA28:AA47,"=55919547",S28:S47),2) -> 1395.83 | AG49: =ROUND(SUMIF(AA28:AA47,"=55919547",T28:T47),2) -> 0 | AH49: =SUMIF(AA28:AA47,"=55919547",U28:U47) -> 131.88786 | AI49: =SUMIF(AA28:AA47,"=55919547",V28:V47) -> 0 | AJ49: =ROUND(SUMIF(AA28:AA47,"=55919547",W28:W47),2) -> 0 | AK49: =ROUND(SUMIF(AA28:AA47,"=55919547",X28:X47),2) -> 1276.09 | AL49: =ROUND(SUMIF(AA28:AA47,"=55919547",Y28:Y47),2) -> 675.36 | AO49: =ROUND(BX49,2) -> 0 | AP49: =ROUND(BY49,2) -> 0 | AQ49: =ROUND(BZ49,2) -> 0 | AR49: =ROUND(CA49,2) -> 3358.71 | AS49: =ROUND(CB49,2) -> 3087.67 | AT49: =ROUND(CC49,2) -> 271.04 | AU49: =ROUND(CD49,2) -> 0 | AV49: =ROUND(CE49,2) -> 0 | ... BD49: =ROUND(CM49,2) -> 0 | BX49: =ROUND(SUMIF(AA28:AA47,"=55919547",FQ28:FQ47),2) -> 0 | BY49: =ROUND(SUMIF(AA28:AA47,"=55919547",FR28:FR47),2) -> 0 | BZ49: =ROUND(SUMIF(AA28:AA47,"=55919547",GL28:GL47),2) -> 0 | CA49: =ROUND(SUMIF(AA28:AA47,"=55919547",GM28:GM47),2) -> 3358.71 | CB49: =ROUND(SUMIF(AA28:AA47,"=55919547",GN28:GN47),2) -> 3087.67 | CC49: =ROUND(SUMIF(AA28:AA47,"=55919547",GO28:GO47),2) -> 271.04 | CD49: =ROUND(SUMIF(AA28:AA47,"=55919547",GP28:GP47),2) -> 0 | CE49: =AC49-BX49 -> 0 | CF49: =AC49-BY49 -> 0 | CG49: =BX49-BZ49 -> 0 | CH49: =AC49-BX49-BY49+BZ49 -> 0 | CI49: =BY49-BZ49 -> 0 | CJ49: =ROUND(SUMIF(AA28:AA47,"=55919547",GX28:GX47),2) -> 0 | CK49: =ROUND(SUMIF(AA28:AA47,"=55919547",GY28:GY47),2) -> 0 | CL49: =ROUND(SUMIF(AA28:AA47,"=55919547",GZ28:GZ47),2) -> 0 | CM49: =ROUND(SUMIF(AA28:AA47,"=55919547",HD28:HD47),2) -> 0 | DG49: =ROUND(DT49,2) -> 78852.96 | DH49: =ROUND(DU49,2) -> 0 | DI49: =ROUND(DV49,2) -> 197.94 | DJ49: =ROUND(DW49,2) -> 72.13 | DK49: =ROUND(DX49,2) -> 78655.02 | DL49: =ROUND(DY49,2) -> 0 | DM49: =DZ49 -> 131.88786 | DN49: =EA49 -> 0 | DO49: =ROUND(EB49,2) -> 0 | DP49: =ROUND(EC49,2) -> 71907.28 | DQ49: =ROUND(ED49,2) -> 38056.97 | DT49: =ROUND(SUMIF(AA28:AA47,"=55919549",O28:O47),2) -> 78852.96 | DU49: =ROUND(SUMIF(AA28:AA47,"=55919549",P28:P47),2) -> 0 | DV49: =ROUND(SUMIF(AA28:AA47,"=55919549",Q28:Q47),2) -> 197.94 | DW49: =ROUND(SUMIF(AA28:AA47,"=55919549",R28:R47),2) -> 72.13 | DX49: =ROUND(SUMIF(AA28:AA47,"=55919549",S28:S47),2) -> 78655.02 | DY49: =ROUND(SUMIF(AA28:AA47,"=55919549",T28:T47),2) -> 0 | DZ49: =SUMIF(AA28:AA47,"=55919549",U28:U47) -> 131.88786 | EA49: =SUMIF(AA28:AA47,"=55919549",V28:V47) -> 0 | EB49: =ROUND(SUMIF(AA28:AA47,"=55919549",W28:W47),2) -> 0 | EC49: =ROUND(SUMIF(AA28:AA47,"=55919549",X28:X47),2) -> 71907.28 | ED49: =ROUND(SUMIF(AA28:AA47,"=55919549",Y28:Y47),2) -> 38056.97 | EG49: =ROUND(FP49,2) -> 0 | EH49: =ROUND(FQ49,2) -> 0 | EI49: =ROUND(FR49,2) -> 0 | EJ49: =ROUND(FS49,2) -> 188817.21 | EK49: =ROUND(FT49,2) -> 173989.92 | EL49: =ROUND(FU49,2) -> 14827.29 | EM49: =ROUND(FV49,2) -> 0 | EN49: =ROUND(FW49,2) -> 0 | ... EV49: =ROUND(GE49,2) -> 0 | FP49: =ROUND(SUMIF(AA28:AA47,"=55919549",FQ28:FQ47),2) -> 0 | FQ49: =ROUND(SUMIF(AA28:AA47,"=55919549",FR28:FR47),2) -> 0 | FR49: =ROUND(SUMIF(AA28:AA47,"=55919549",GL28:GL47),2) -> 0 | FS49: =ROUND(SUMIF(AA28:AA47,"=55919549",GM28:GM47),2) -> 188817.21 | FT49: =ROUND(SUMIF(AA28:AA47,"=55919549",GN28:GN47),2) -> 173989.92 | FU49: =ROUND(SUMIF(AA28:AA47,"=55919549",GO28:GO47),2) -> 14827.29 | FV49: =ROUND(SUMIF(AA28:AA47,"=55919549",GP28:GP47),2) -> 0 | FW49: =DU49-FP49 -> 0 | FX49: =DU49-FQ49 -> 0 | FY49: =FP49-FR49 -> 0 | FZ49: =DU49-FP49-FQ49+FR49 -> 0 | GA49: =FQ49-FR49 -> 0 | GB49: =ROUND(SUMIF(AA28:AA47,"=55919549",GX28:GX47),2) -> 0 | GC49: =ROUND(SUMIF(AA28:AA47,"=55919549",GY28:GY47),2) -> 0 | GD49: =ROUND(SUMIF(AA28:AA47,"=55919549",GZ28:GZ47),2) -> 0 | GE49: =ROUND(SUMIF(AA28:AA47,"=55919549",HD28:HD47),2) -> 0 | GX49: 0
A51: 50 | B51: 0 | C51: 0 | D51: 1 | E51: 201 | F51: =ROUND(Source!O49,O51) -> 1407.26 | G51: ПЗ | H51: Прямые затраты | K51: 201 | L51: 1 | M51: 3 | O51: 2 | P51: =ROUND(Source!DG49,O51) -> 78852.96 | W51: 1407.26 | X51: 1 | Y51: 1407.26 | Z51: 78852.96 | AA51: 1 | AB51: 78852.96
A52: 50 | B52: 0 | C52: 0 | D52: 1 | E52: 202 | F52: =ROUND(Source!P49,O52) -> 0 | G52: СтМатОб | H52: Стоимость материальных ресурсов (всего) | K52: 202 | L52: 2 | M52: 3 | O52: 2 | P52: =ROUND(Source!DH49,O52) -> 0 | W52: 0 | X52: 1 | Y52: 0 | Z52: 0 | AA52: 1 | AB52: 0
A53: 50 | B53: 0 | C53: 0 | D53: 1 | E53: 222 | F53: =ROUND(Source!AO49,O53) -> 0 | G53: СтМатОбЗак | H53: Стоимость материалов и оборудования заказчика | K53: 222 | L53: 3 | M53: 3 | O53: 2 | P53: =ROUND(Source!EG49,O53) -> 0 | W53: 0 | X53: 1 | Y53: 0 | Z53: 0 | AA53: 1 | AB53: 0
A54: 50 | B54: 0 | C54: 0 | D54: 1 | E54: 225 | F54: =ROUND(Source!AV49,O54) -> 0 | G54: СтМатОбПод | H54: Стоимость материалов и оборудования подрядчика | K54: 225 | L54: 4 | M54: 3 | O54: 2 | P54: =ROUND(Source!EN49,O54) -> 0 | W54: 0 | X54: 1 | Y54: 0 | Z54: 0 | AA54: 1 | AB54: 0
A55: 50 | B55: 0 | C55: 0 | D55: 1 | E55: 226 | F55: =ROUND(Source!AW49,O55) -> 0 | G55: СтМат | H55: Стоимость материалов (всего) | K55: 226 | L55: 5 | M55: 3 | O55: 2 | P55: =ROUND(Source!EO49,O55) -> 0 | W55: 0 | X55: 1 | Y55: 0 | Z55: 0 | AA55: 1 | AB55: 0
A56: 50 | B56: 0 | C56: 0 | D56: 1 | E56: 227 | F56: =ROUND(Source!AX49,O56) -> 0 | G56: СтМатЗак | H56: Стоимость материалов заказчика | K56: 227 | L56: 6 | M56: 3 | O56: 2 | P56: =ROUND(Source!EP49,O56) -> 0 | W56: 0 | X56: 1 | Y56: 0 | Z56: 0 | AA56: 1 | AB56: 0
A57: 50 | B57: 0 | C57: 0 | D57: 1 | E57: 228 | F57: =ROUND(Source!AY49,O57) -> 0 | G57: СтМатПод | H57: Стоимость материалов подрядчика | K57: 228 | L57: 7 | M57: 3 | O57: 2 | P57: =ROUND(Source!EQ49,O57) -> 0 | W57: 0 | X57: 1 | Y57: 0 | Z57: 0 | AA57: 1 | AB57: 0
A58: 50 | B58: 0 | C58: 0 | D58: 1 | E58: 216 | F58: =ROUND(Source!AP49,O58) -> 0 | G58: Оборуд | H58: Стоимость оборудования (всего) | K58: 216 | L58: 8 | M58: 3 | O58: 2 | P58: =ROUND(Source!EH49,O58) -> 0 | W58: 0 | X58: 1 | Y58: 0 | Z58: 0 | AA58: 1 | AB58: 0
A59: 50 | B59: 0 | C59: 0 | D59: 1 | E59: 223 | F59: =ROUND(Source!AQ49,O59) -> 0 | G59: ОборудЗак | H59: Стоимость оборудования заказчика | K59: 223 | L59: 9 | M59: 3 | O59: 2 | P59: =ROUND(Source!EI49,O59) -> 0 | W59: 0 | X59: 1 | Y59: 0 | Z59: 0 | AA59: 1 | AB59: 0
A60: 50 | B60: 0 | C60: 0 | D60: 1 | E60: 229 | F60: =ROUND(Source!AZ49,O60) -> 0 | G60: ОборудПод | H60: Стоимость оборудования подрядчика | K60: 229 | L60: 10 | M60: 3 | O60: 2 | P60: =ROUND(Source!ER49,O60) -> 0 | W60: 0 | X60: 1 | Y60: 0 | Z60: 0 | AA60: 1 | AB60: 0
A61: 50 | B61: 0 | C61: 0 | D61: 1 | E61: 203 | F61: =ROUND(Source!Q49,O61) -> 11.43 | G61: ЭММ | H61: Эксплуатация машин | K61: 203 | L61: 11 | M61: 3 | O61: 2 | P61: =ROUND(Source!DI49,O61) -> 197.94 | W61: 11.43 | X61: 1 | Y61: 11.43 | Z61: 197.94 | AA61: 1 | AB61: 197.94
A62: 50 | B62: 0 | C62: 0 | D62: 1 | E62: 231 | F62: =ROUND(Source!BB49,O62) -> 0 | G62: ЭММсНРиСП | H62: Эксплуатация машин по ТСН-2001.16 | K62: 231 | L62: 12 | M62: 3 | O62: 2 | P62: =ROUND(Source!ET49,O62) -> 0 | W62: 0 | X62: 1 | Y62: 0 | Z62: 0 | AA62: 1 | AB62: 0
A63: 50 | B63: 0 | C63: 0 | D63: 1 | E63: 204 | F63: =ROUND(Source!R49,O63) -> 1.28 | G63: ЗПМ | H63: ЗП машинистов | K63: 204 | L63: 13 | M63: 3 | O63: 2 | P63: =ROUND(Source!DJ49,O63) -> 72.13 | W63: 1.28 | X63: 1 | Y63: 1.28 | Z63: 72.13 | AA63: 1 | AB63: 72.13
A64: 50 | B64: 0 | C64: 0 | D64: 1 | E64: 205 | F64: =ROUND(Source!S49,O64) -> 1395.83 | G64: ОЗП | H64: Основная ЗП рабочих | K64: 205 | L64: 14 | M64: 3 | O64: 2 | P64: =ROUND(Source!DK49,O64) -> 78655.02 | W64: 1395.83 | X64: 1 | Y64: 1395.83 | Z64: 78655.02 | AA64: 1 | AB64: 78655.02
A65: 50 | B65: 0 | C65: 0 | D65: 1 | E65: 232 | F65: =ROUND(Source!BC49,O65) -> 0 | G65: ОЗПсНРиСП | H65: Основная ЗП рабочих по ТСН-2001.16 | K65: 232 | L65: 15 | M65: 3 | O65: 2 | P65: =ROUND(Source!EU49,O65) -> 0 | W65: 0 | X65: 1 | Y65: 0 | Z65: 0 | AA65: 1 | AB65: 0
A66: 50 | B66: 0 | C66: 0 | D66: 1 | E66: 214 | F66: =ROUND(Source!AS49,O66) -> 3087.67 | G66: Строит | H66: Строительные работы с НР и СП | K66: 214 | L66: 16 | M66: 3 | O66: 2 | P66: =ROUND(Source!EK49,O66) -> 173989.92 | W66: 3087.67 | X66: 1 | Y66: 3087.67 | Z66: 173989.92 | AA66: 1 | AB66: 173989.92
A67: 50 | B67: 0 | C67: 0 | D67: 1 | E67: 215 | F67: =ROUND(Source!AT49,O67) -> 271.04 | G67: Монтаж | H67: Монтажные работы с НР и СП | K67: 215 | L67: 17 | M67: 3 | O67: 2 | P67: =ROUND(Source!EL49,O67) -> 14827.29 | W67: 271.04 | X67: 1 | Y67: 271.04 | Z67: 14827.29 | AA67: 1 | AB67: 14827.29
A68: 50 | B68: 0 | C68: 0 | D68: 1 | E68: 217 | F68: =ROUND(Source!AU49,O68) -> 0 | G68: Прочие | H68: Прочие работы с НР и СП | K68: 217 | L68: 18 | M68: 3 | O68: 2 | P68: =ROUND(Source!EM49,O68) -> 0 | W68: 0 | X68: 1 | Y68: 0 | Z68: 0 | AA68: 1 | AB68: 0
A69: 50 | B69: 0 | C69: 0 | D69: 1 | E69: 230 | F69: =ROUND(Source!BA49,O69) -> 0 | G69: ПрочиеЗатр | H69: Прочие затраты по ТСН-2001.16 | K69: 230 | L69: 19 | M69: 3 | O69: 2 | P69: =ROUND(Source!ES49,O69) -> 0 | W69: 0 | X69: 1 | Y69: 0 | Z69: 0 | AA69: 1 | AB69: 0
A70: 50 | B70: 0 | C70: 0 | D70: 1 | E70: 206 | F70: =ROUND(Source!T49,O70) -> 0 | G70: ВозврМат | H70: Возврат материалов | K70: 206 | L70: 20 | M70: 3 | O70: 2 | P70: =ROUND(Source!DL49,O70) -> 0 | W70: 0 | X70: 1 | Y70: 0 | Z70: 0 | AA70: 1 | AB70: 0
A71: 50 | B71: 0 | C71: 0 | D71: 1 | E71: 207 | F71: =Source!U49 -> 131.88786 | G71: ТрудСтр | H71: Трудозатраты строителей | K71: 207 | L71: 21 | M71: 3 | O71: -1 | P71: =Source!DM49 -> 131.88786 | W71: 131.88786 | X71: 1 | Y71: 131.88786 | Z71: 131.88786 | AA71: 1 | AB71: 131.88786
A72: 50 | B72: 0 | C72: 0 | D72: 1 | E72: 208 | F72: =Source!V49 -> 0 | G72: ТрудМаш | H72: Трудозатраты машинистов | K72: 208 | L72: 22 | M72: 3 | O72: -1 | P72: =Source!DN49 -> 0 | W72: 0 | X72: 1 | Y72: 0 | Z72: 0 | AA72: 1 | AB72: 0
A73: 50 | B73: 0 | C73: 0 | D73: 1 | E73: 209 | F73: =ROUND(Source!W49,O73) -> 0 | G73: ТранспМат | H73: Транспорт материалов | K73: 209 | L73: 23 | M73: 3 | O73: 2 | P73: =ROUND(Source!DO49,O73) -> 0 | W73: 0 | X73: 1 | Y73: 0 | Z73: 0 | AA73: 1 | AB73: 0
A74: 50 | B74: 0 | C74: 0 | D74: 1 | E74: 233 | F74: =ROUND(Source!BD49,O74) -> 0 | G74: Перевозка | H74: Перевозка грузов | K74: 233 | L74: 24 | M74: 3 | O74: 2 | P74: =ROUND(Source!EV49,O74) -> 0 | W74: 0 | X74: 1 | Y74: 0 | Z74: 0 | AA74: 1 | AB74: 0
A75: 50 | B75: 0 | C75: 0 | D75: 1 | E75: 210 | F75: =ROUND(Source!X49,O75) -> 1276.09 | G75: НР | H75: Накладные расходы | K75: 210 | L75: 25 | M75: 3 | O75: 2 | P75: =ROUND(Source!DP49,O75) -> 71907.28 | W75: 1276.09 | X75: 1 | Y75: 1276.09 | Z75: 71907.28 | AA75: 1 | AB75: 71907.28
A76: 50 | B76: 0 | C76: 0 | D76: 1 | E76: 211 | F76: =ROUND(Source!Y49,O76) -> 675.36 | G76: СмПриб | H76: Сметная прибыль | K76: 211 | L76: 26 | M76: 3 | O76: 2 | P76: =ROUND(Source!DQ49,O76) -> 38056.97 | W76: 675.36 | X76: 1 | Y76: 675.36 | Z76: 38056.97 | AA76: 1 | AB76: 38056.97
A77: 50 | B77: 0 | C77: 0 | D77: 1 | E77: 224 | F77: =ROUND(Source!AR49,O77) -> 3358.71 | G77: Всего | H77: Всего с НР и СП | K77: 224 | L77: 27 | M77: 3 | O77: 2 | P77: =ROUND(Source!EJ49,O77) -> 188817.21 | W77: 3358.71 | X77: 1 | Y77: 3358.71 | Z77: 188817.21 | AA77: 1 | AB77: 188817.21
A79: 4 | B79: 1 | D79: =ROW(A110) -> 110 | F79: 1 | G79: Комплект основного оборудования | I79: 0 | K79: -1 | S79: 0 | T79: 0 | V79: 0 | BX79: 0 | CJ79: 0
A81: 52 | B81: =B110 -> 1 | C81: =C110 -> 4 | D81: =D110 -> 79 | E81: =E110 -> 0 | F81: =F110 -> 1 | G81: =G110 -> Комплект основного оборудования | O81: =O110 -> 10887.22 | P81: =P110 -> 10505.78 | Q81: =Q110 -> 21.89 | R81: =R110 -> 3.97 | S81: =S110 -> 359.55 | T81: =T110 -> 0 | U81: =U110 -> 26.158692 | V81: =V110 -> 0 | ... GX81: =GX110 -> 0
A83: 17 | B83: 1 | C83: =ROW(SmtRes!A66) -> 66 | D83: =ROW(EtalonRes!A80) -> 80 | E83: 11 | F83: 4.10-134-4 | G83: Монтаж антенны коллективной для приема ТВ на антенной опоре высотой до 9 м с одним ярусом оттяжек | H83: 1 антенна | I83: 1 | J83: 0 | K83: 1 | O83: =ROUND(CP83,2) -> 99.7 | P83: =ROUND((ROUND((AC83*AW83*I83),2)*BC83),2) -> 0.37 | Q83: =(ROUND((ROUND((((ET83*1.2))*AV83*I83),2)*BB83),2)+ROUND((ROUND(((AE83-((EU83*1.2)))*AV83*I83),2)*BS83),2)) -> 0 | R83: =(ROUND((ROUND((((EU83*1.2))*AV83*I83),2)*BS83),2)+ROUND((ROUND(((AE83-((EU83*1.2)))*AV83*I83),2)*BS83),2)) -> 0 | S83: =ROUND((ROUND((AF83*AV83*I83),2)*BA83),2) -> 99.33 | T83: =ROUND(CU83*I83,2) -> 0 | U83: =CV83*I83 -> 7.004628 | V83: =CW83*I83 -> 0 | W83: =ROUND(CX83*I83,2) -> 0 | X83: =(ROUND((((S83+ROUND((ROUND((((EU83*1.2))*AV83*I83),2)*BS83),2))*AT83)/100),2)+ROUND(((ROUND((ROUND(((AE83-((EU83*1.2)))*AV83*I83),2)*BS83),2)*AT83)/100),2)) -> 94.36 | Y83: =(ROUND((((S83+ROUND((ROUND((((EU83*1.2))*AV83*I83),2)*BS83),2))*AU83)/100),2)+ROUND(((ROUND((ROUND(((AE83-((EU83*1.2)))*AV83*I83),2)*BS83),2)*AU83)/100),2)) -> 52.64 | AA83: 55919547 | AB83: =ROUND((AC83+AD83+AF83),6) -> 91.75 | AC83: =ROUND(((ES83*1)),6) -> 0.37 | AD83: =ROUND(((((ET83*1.2))-((EU83*1.2)))+AE83),6) -> 0 | AE83: =ROUND(((EU83*1.2)),6) -> 0 | AF83: =ROUND(((EV83*1.2)),6) -> 91.38 | AG83: =ROUND((AP83),6) -> 0 | AH83: =((EW83*1.2)) -> 6.444 | AI83: =((EX83*1.2)) -> 0 | AJ83: =(AS83) -> 0 | AK83: 76.52 | AL83: 0.37 | AM83: 0 | AN83: 0 | AO83: 76.15 | AP83: 0 | AQ83: 5.37 | AR83: 0 | AS83: 0 | AT83: 95 | AU83: 53 | AV83: 1.087 | AW83: 1 | AZ83: 1 | BA83: 1 | BB83: 1 | BC83: 1 | BH83: 0 | BI83: 2 | BJ83: ТСН-2001.4 Доп. 81, Сб. 10, т. 134, поз. 4 | BM83: 69 | BN83: 0 | BO83: 4.10-134-4 | BP83: 1 | BQ83: 40 | BR83: 0 | BS83: 1 | BT83: 1 | BU83: 1 | BV83: 1 | BW83: 1 | BX83: 1 | BZ83: 95 | CA83: 53 | CE83: 1566 | CF83: 0 | CG83: 0 | CM83: 0 | CN83: Поправка: Гл.12.Прил.8.п.8. 3_12.00.01.11.001 Наименование: При наличии напряженных и стесненных условий производства работ (стесненность, сложность складирования и транспортной логистики и т.п.) для объектов, расположенных в пределах круговой магистральной системы улиц "Садовое кольцо" города Москвы | CO83: 0 | CP83: =(P83+Q83+S83) -> 99.7 | CQ83: =ROUND((ROUND((AC83*AW83*1),2)*BC83),2) -> 0.37 | CR83: =(ROUND((ROUND((((ET83*1.2))*AV83*1),2)*BB83),2)+ROUND((ROUND(((AE83-((EU83*1.2)))*AV83*1),2)*BS83),2)) -> 0 | CS83: =(ROUND((ROUND((((EU83*1.2))*AV83*1),2)*BS83),2)+ROUND((ROUND(((AE83-((EU83*1.2)))*AV83*1),2)*BS83),2)) -> 0 | CT83: =ROUND((ROUND((AF83*AV83*1),2)*BA83),2) -> 99.33 | CU83: =AG83 -> 0 | CV83: =(AH83*AV83) -> 7.004628 | CW83: =AI83 -> 0 | CX83: =AJ83 -> 0 | CY83: =(ROUND((((S83+ROUND((ROUND((((EU83*1.2))*AV83*1),2)*BS83),2))*AT83)/100),2)+ROUND(((ROUND((ROUND(((AE83-((EU83*1.2)))*AV83*1),2)*BS83),2)*AT83)/100),2)) -> 94.36 | CZ83: =(ROUND((((S83+ROUND((ROUND((((EU83*1.2))*AV83*1),2)*BS83),2))*AU83)/100),2)+ROUND(((ROUND((ROUND(((AE83-((EU83*1.2)))*AV83*1),2)*BS83),2)*AU83)/100),2)) -> 52.64 | DB83: 35 | DD83: *1 | DE83: *1,2 | DF83: *1,2 | DG83: *1,2 | DI83: *1,2 | DJ83: *1,2 | DN83: 0 | DO83: 0 | DP83: 1 | DQ83: 1 | DU83: 1013 | DV83: 1 антенна | DW83: 1 антенна | DX83: 1 | EE83: 55393701 | EF83: 40 | EG83: Монтаж оборудования | EH83: 0 | EJ83: 2 | EK83: 69 | EL83: ТСН-2001.4-10. Монтаж радиотелевизионного и электронного оборудования | EM83: ТСН-2001.4-10-2 | EO83: Поправка: Гл.12.Прил.8.п.8. 3_12.00.01.11.001 | EQ83: 0 | ER83: 76.52 | ES83: 0.37 | ET83: 0 | EU83: 0 | EV83: 76.15 | EW83: 5.37 | EX83: 0 | EY83: 0 | FQ83: 0 | FR83: 0 | FS83: 0 | FX83: 95 | FY83: 53 | GD83: 1 | GF83: 1760566508 | GG83: 2 | GH83: 1 | GI83: 2 | GJ83: 0 | GK83: 0 | GL83: =ROUND(IF(AND(BH83=3,BI83=3,FS83<>0),P83,0),2) -> 0 | GM83: =ROUND(O83+X83+Y83,2)+GX83 -> 246.7 | GN83: =IF(OR(BI83=0,BI83=1),GM83-GX83,0) -> 0 | GO83: =IF(BI83=2,GM83-GX83,0) -> 246.7 | GP83: =IF(BI83=4,GM83-GX83,0) -> 0 | GR83: 0 | GS83: 3 | GT83: 0 | GV83: =ROUND((GT83),6) -> 0 | GW83: 1 | GX83: =ROUND(HC83*I83,2) -> 0 | HA83: 0 | HB83: 0 | HC83: =GV83*GW83 -> 0 | HS83: 0 | IK83: 0
A84: 17 | B84: 1 | C84: =ROW(SmtRes!A68) -> 68 | D84: =ROW(EtalonRes!A82) -> 82 | E84: 11 | F84: 4.10-134-4 | G84: Монтаж антенны коллективной для приема ТВ на антенной опоре высотой до 9 м с одним ярусом оттяжек | H84: 1 антенна | I84: 1 | J84: 0 | K84: 1 | O84: =ROUND(CP84,2) -> 5599.27 | P84: =ROUND((ROUND((AC84*AW84*I84),2)*BC84),2) -> 2.02 | Q84: =(ROUND((ROUND((((ET84*1.2))*AV84*I84),2)*BB84),2)+ROUND((ROUND(((AE84-((EU84*1.2)))*AV84*I84),2)*BS84),2)) -> 0 | R84: =(ROUND((ROUND((((EU84*1.2))*AV84*I84),2)*BS84),2)+ROUND((ROUND(((AE84-((EU84*1.2)))*AV84*I84),2)*BS84),2)) -> 0 | S84: =ROUND((ROUND((AF84*AV84*I84),2)*BA84),2) -> 5597.25 | T84: =ROUND(CU84*I84,2) -> 0 | U84: =CV84*I84 -> 7.004628 | V84: =CW84*I84 -> 0 | W84: =ROUND(CX84*I84,2) -> 0 | X84: =(ROUND((((S84+ROUND((ROUND((((EU84*1.2))*AV84*I84),2)*BS84),2))*AT84)/100),2)+ROUND(((ROUND((ROUND(((AE84-((EU84*1.2)))*AV84*I84),2)*BS84),2)*AT84)/100),2)) -> 5317.39 | Y84: =(ROUND((((S84+ROUND((ROUND((((EU84*1.2))*AV84*I84),2)*BS84),2))*AU84)/100),2)+ROUND(((ROUND((ROUND(((AE84-((EU84*1.2)))*AV84*I84),2)*BS84),2)*AU84)/100),2)) -> 2966.54 | AA84: 55919549 | AB84: =ROUND((AC84+AD84+AF84),6) -> 91.75 | AC84: =ROUND(((ES84*1)),6) -> 0.37 | AD84: =ROUND(((((ET84*1.2))-((EU84*1.2)))+AE84),6) -> 0 | AE84: =ROUND(((EU84*1.2)),6) -> 0 | AF84: =ROUND(((EV84*1.2)),6) -> 91.38 | AG84: =ROUND((AP84),6) -> 0 | AH84: =((EW84*1.2)) -> 6.444 | AI84: =((EX84*1.2)) -> 0 | AJ84: =(AS84) -> 0 | AK84: 76.52 | AL84: 0.37 | AM84: 0 | AN84: 0 | AO84: 76.15 | AP84: 0 | AQ84: 5.37 | AR84: 0 | AS84: 0 | AT84: 95 | AU84: 53 | AV84: 1.087 | AW84: 1 | AZ84: 1 | BA84: 56.35 | BB84: 1 | BC84: 5.46 | BH84: 0 | BI84: 2 | BJ84: ТСН-2001.4 Доп. 81, Сб. 10, т. 134, поз. 4 | BM84: 69 | BN84: 0 | BO84: 4.10-134-4 | BP84: 1 | BQ84: 40 | BR84: 0 | BS84: 56.35 | BT84: 1 | BU84: 1 | BV84: 1 | BW84: 1 | BX84: 1 | BZ84: 95 | CA84: 53 | CE84: 1566 | CF84: 0 | CG84: 0 | CM84: 0 | CN84: Поправка: Гл.12.Прил.8.п.8. 3_12.00.01.11.001 Наименование: При наличии напряженных и стесненных условий производства работ (стесненность, сложность складирования и транспортной логистики и т.п.) для объектов, расположенных в пределах круговой магистральной системы улиц "Садовое кольцо" города Москвы | CO84: 0 | CP84: =(P84+Q84+S84) -> 5599.27 | CQ84: =ROUND((ROUND((AC84*AW84*1),2)*BC84),2) -> 2.02 | CR84: =(ROUND((ROUND((((ET84*1.2))*AV84*1),2)*BB84),2)+ROUND((ROUND(((AE84-((EU84*1.2)))*AV84*1),2)*BS84),2)) -> 0 | CS84: =(ROUND((ROUND((((EU84*1.2))*AV84*1),2)*BS84),2)+ROUND((ROUND(((AE84-((EU84*1.2)))*AV84*1),2)*BS84),2)) -> 0 | CT84: =ROUND((ROUND((AF84*AV84*1),2)*BA84),2) -> 5597.25 | CU84: =AG84 -> 0 | CV84: =(AH84*AV84) -> 7.004628 | CW84: =AI84 -> 0 | CX84: =AJ84 -> 0 | CY84: =(ROUND((((S84+ROUND((ROUND((((EU84*1.2))*AV84*1),2)*BS84),2))*AT84)/100),2)+ROUND(((ROUND((ROUND(((AE84-((EU84*1.2)))*AV84*1),2)*BS84),2)*AT84)/100),2)) -> 5317.39 | CZ84: =(ROUND((((S84+ROUND((ROUND((((EU84*1.2))*AV84*1),2)*BS84),2))*AU84)/100),2)+ROUND(((ROUND((ROUND(((AE84-((EU84*1.2)))*AV84*1),2)*BS84),2)*AU84)/100),2)) -> 2966.54 | DB84: 36 | DD84: *1 | DE84: *1,2 | DF84: *1,2 | DG84: *1,2 | DI84: *1,2 | DJ84: *1,2 | DN84: 0 | DO84: 0 | DP84: 1 | DQ84: 1 | DU84: 1013 | DV84: 1 антенна | DW84: 1 антенна | DX84: 1 | EE84: 55393701 | EF84: 40 | EG84: Монтаж оборудования | EH84: 0 | EJ84: 2 | EK84: 69 | EL84: ТСН-2001.4-10. Монтаж радиотелевизионного и электронного оборудования | EM84: ТСН-2001.4-10-2 | EO84: Поправка: Гл.12.Прил.8.п.8. 3_12.00.01.11.001 | EQ84: 0 | ER84: 76.52 | ES84: 0.37 | ET84: 0 | EU84: 0 | EV84: 76.15 | EW84: 5.37 | EX84: 0 | EY84: 0 | FQ84: 0 | FR84: 0 | FS84: 0 | FX84: 95 | FY84: 53 | GD84: 1 | GF84: 1760566508 | GG84: 2 | GH84: 1 | GI84: 2 | GJ84: 0 | GK84: 0 | GL84: =ROUND(IF(AND(BH84=3,BI84=3,FS84<>0),P84,0),2) -> 0 | GM84: =ROUND(O84+X84+Y84,2)+GX84 -> 13883.2 | GN84: =IF(OR(BI84=0,BI84=1),GM84-GX84,0) -> 0 | GO84: =IF(BI84=2,GM84-GX84,0) -> 13883.2 | GP84: =IF(BI84=4,GM84-GX84,0) -> 0 | GR84: 0 | GS84: 3 | GT84: 0 | GV84: =ROUND((GT84),6) -> 0 | GW84: 1 | GX84: =ROUND(HC84*I84,2) -> 0 | HA84: 0 | HB84: 0 | HC84: =GV84*GW84 -> 0 | HS84: 0 | IK84: 0
A85: 17 | B85: 1 | E85: 12 | F85: КА, п.1 | G85: Антенна эфирная ДМВ диапазона EB45LTE | H85: ШТ | I85: 1 | J85: 0 | K85: 1 | O85: =ROUND(CP85,2) -> 477.56 | P85: =ROUND((ROUND((AC85*AW85*I85),2)*BC85),2) -> 477.56 | Q85: =(ROUND((ROUND(((ET85)*AV85*I85),2)*BB85),2)+ROUND((ROUND(((AE85-(EU85))*AV85*I85),2)*BS85),2)) -> 0 | R85: =(ROUND((ROUND(((EU85)*AV85*I85),2)*BS85),2)+ROUND((ROUND(((AE85-(EU85))*AV85*I85),2)*BS85),2)) -> 0 | S85: =ROUND((ROUND((AF85*AV85*I85),2)*BA85),2) -> 0 | T85: =ROUND(CU85*I85,2) -> 0 | U85: =CV85*I85 -> 0 | V85: =CW85*I85 -> 0 | W85: =ROUND(CX85*I85,2) -> 0 | X85: =(ROUND((((S85+ROUND((ROUND(((EU85)*AV85*I85),2)*BS85),2))*AT85)/100),2)+ROUND(((ROUND((ROUND(((AE85-(EU85))*AV85*I85),2)*BS85),2)*AT85)/100),2)) -> 0 | Y85: =(ROUND((((S85+ROUND((ROUND(((EU85)*AV85*I85),2)*BS85),2))*AU85)/100),2)+ROUND(((ROUND((ROUND(((AE85-(EU85))*AV85*I85),2)*BS85),2)*AU85)/100),2)) -> 0 | AA85: 55919547 | AB85: =ROUND((AC85+AD85+AF85),6) -> 477.56 | AC85: =ROUND((ES85),6) -> 477.56 | AD85: =ROUND((((ET85)-(EU85))+AE85),6) -> 0 | AE85: =ROUND((EU85),6) -> 0 | AF85: =ROUND((EV85),6) -> 0 | AG85: =ROUND((AP85),6) -> 0 | AH85: =(EW85) -> 0 | AI85: =(EX85) -> 0 | AJ85: =(AS85) -> 0 | AK85: 477.56 | AL85: 477.56 | AM85: 0 | AN85: 0 | AO85: 0 | AP85: 0 | AQ85: 0 | AR85: 0 | AS85: 0 | AT85: 0 | AU85: 0 | AV85: 1 | AW85: 1 | AZ85: 1 | BA85: 1 | BB85: 1 | BC85: 1 | BH85: 3 | BI85: 3 | BJ85: КА, п.1 | BM85: 400007 | BN85: 0 | BP85: 0 | BQ85: 214 | BR85: 0 | BS85: 1 | BT85: 1 | BU85: 1 | BV85: 1 | BW85: 1 | BX85: 1 | BZ85: 0 | CA85: 0 | CE85: 1566 | CF85: 0 | CG85: 0 | CM85: 0 | CO85: 0 | CP85: =(P85+Q85+S85) -> 477.56 | CQ85: =ROUND((ROUND((AC85*AW85*1),2)*BC85),2) -> 477.56 | CR85: =(ROUND((ROUND(((ET85)*AV85*1),2)*BB85),2)+ROUND((ROUND(((AE85-(EU85))*AV85*1),2)*BS85),2)) -> 0 | CS85: =(ROUND((ROUND(((EU85)*AV85*1),2)*BS85),2)+ROUND((ROUND(((AE85-(EU85))*AV85*1),2)*BS85),2)) -> 0 | CT85: =ROUND((ROUND((AF85*AV85*1),2)*BA85),2) -> 0 | CU85: =AG85 -> 0 | CV85: =(AH85*AV85) -> 0 | CW85: =AI85 -> 0 | CX85: =AJ85 -> 0 | CY85: =(ROUND((((S85+ROUND((ROUND(((EU85)*AV85*1),2)*BS85),2))*AT85)/100),2)+ROUND(((ROUND((ROUND(((AE85-(EU85))*AV85*1),2)*BS85),2)*AT85)/100),2)) -> 0 | CZ85: =(ROUND((((S85+ROUND((ROUND(((EU85)*AV85*1),2)*BS85),2))*AU85)/100),2)+ROUND(((ROUND((ROUND(((AE85-(EU85))*AV85*1),2)*BS85),2)*AU85)/100),2)) -> 0 | DN85: 0 | DO85: 0 | DP85: 1 | DQ85: 1 | DU85: 1013 | DV85: ШТ | DW85: ШТ | DX85: 1 | EE85: 55393630 | EF85: 214 | EG85: Оборудование, отсутствующие в СНБ | EH85: 0 | EJ85: 3 | EK85: 400007 | EL85: Оборудование, отсутствующие в СНБ | EM85: Оборуд. КА | EQ85: 16 | ER85: 0 | ES85: 477.56 | ET85: 0 | EU85: 0 | EV85: 0 | EW85: 0 | EX85: 0 | EY85: 0 | FQ85: 0 | FR85: =P85 -> 477.56 | FS85: 0 | FX85: 0 | FY85: 0 | GA85: [5 500 / 1,22 / 9,84] + 1,2% Трансп + 3% Заг.скл | GD85: 1 | GF85: 1035702266 | GG85: 2 | GH85: 4 | GI85: -2 | GJ85: 0 | GK85: 0 | GL85: =ROUND(IF(AND(BH85=3,BI85=3,FS85<>0),P85,0),2) -> 0 | GM85: =ROUND(O85+X85+Y85,2)+GX85 -> 477.56 | GN85: =IF(OR(BI85=0,BI85=1),GM85-GX85,0) -> 0 | GO85: =IF(BI85=2,GM85-GX85,0) -> 0 | GP85: =IF(BI85=4,GM85-GX85,0) -> 0 | GR85: 1 | GS85: 2 | GT85: 0 | GV85: =ROUND((GT85),6) -> 0 | GW85: 1 | GX85: =ROUND(HC85*I85,2) -> 0 | HA85: 0 | HB85: 0 | HC85: =GV85*GW85 -> 0 | HE85: 1,2 | HF85: 3 | HS85: 0 | IK85: 0
A86: 17 | B86: 1 | E86: 12 | F86: КА, п.1 | G86: Антенна эфирная ДМВ диапазона EB45LTE | H86: ШТ | I86: 1 | J86: 0 | K86: 1 | O86: =ROUND(CP86,2) -> 4699.19 | P86: =ROUND((ROUND((AC86*AW86*I86),2)*BC86),2) -> 4699.19 | Q86: =(ROUND((ROUND(((ET86)*AV86*I86),2)*BB86),2)+ROUND((ROUND(((AE86-(EU86))*AV86*I86),2)*BS86),2)) -> 0 | R86: =(ROUND((ROUND(((EU86)*AV86*I86),2)*BS86),2)+ROUND((ROUND(((AE86-(EU86))*AV86*I86),2)*BS86),2)) -> 0 | S86: =ROUND((ROUND((AF86*AV86*I86),2)*BA86),2) -> 0 | T86: =ROUND(CU86*I86,2) -> 0 | U86: =CV86*I86 -> 0 | V86: =CW86*I86 -> 0 | W86: =ROUND(CX86*I86,2) -> 0 | X86: =(ROUND((((S86+ROUND((ROUND(((EU86)*AV86*I86),2)*BS86),2))*AT86)/100),2)+ROUND(((ROUND((ROUND(((AE86-(EU86))*AV86*I86),2)*BS86),2)*AT86)/100),2)) -> 0 | Y86: =(ROUND((((S86+ROUND((ROUND(((EU86)*AV86*I86),2)*BS86),2))*AU86)/100),2)+ROUND(((ROUND((ROUND(((AE86-(EU86))*AV86*I86),2)*BS86),2)*AU86)/100),2)) -> 0 | AA86: 55919549 | AB86: =ROUND((AC86+AD86+AF86),6) -> 477.56 | AC86: =ROUND((ES86),6) -> 477.56 | AD86: =ROUND((((ET86)-(EU86))+AE86),6) -> 0 | AE86: =ROUND((EU86),6) -> 0 | AF86: =ROUND((EV86),6) -> 0 | AG86: =ROUND((AP86),6) -> 0 | AH86: =(EW86) -> 0 | AI86: =(EX86) -> 0 | AJ86: =(AS86) -> 0 | AK86: 477.56 | AL86: 477.56 | AM86: 0 | AN86: 0 | AO86: 0 | AP86: 0 | AQ86: 0 | AR86: 0 | AS86: 0 | AT86: 0 | AU86: 0 | AV86: 1 | AW86: 1 | AZ86: 1 | BA86: 1 | BB86: 1 | BC86: 9.84 | BH86: 3 | BI86: 3 | BJ86: КА, п.1 | BM86: 400007 | BN86: 0 | BP86: 0 | BQ86: 214 | BR86: 0 | BS86: 1 | BT86: 1 | BU86: 1 | BV86: 1 | BW86: 1 | BX86: 1 | BZ86: 0 | CA86: 0 | CE86: 1566 | CF86: 0 | CG86: 0 | CM86: 0 | CO86: 0 | CP86: =(P86+Q86+S86) -> 4699.19 | CQ86: =ROUND((ROUND((AC86*AW86*1),2)*BC86),2) -> 4699.19 | CR86: =(ROUND((ROUND(((ET86)*AV86*1),2)*BB86),2)+ROUND((ROUND(((AE86-(EU86))*AV86*1),2)*BS86),2)) -> 0 | CS86: =(ROUND((ROUND(((EU86)*AV86*1),2)*BS86),2)+ROUND((ROUND(((AE86-(EU86))*AV86*1),2)*BS86),2)) -> 0 | CT86: =ROUND((ROUND((AF86*AV86*1),2)*BA86),2) -> 0 | CU86: =AG86 -> 0 | CV86: =(AH86*AV86) -> 0 | CW86: =AI86 -> 0 | CX86: =AJ86 -> 0 | CY86: =(ROUND((((S86+ROUND((ROUND(((EU86)*AV86*1),2)*BS86),2))*AT86)/100),2)+ROUND(((ROUND((ROUND(((AE86-(EU86))*AV86*1),2)*BS86),2)*AT86)/100),2)) -> 0 | CZ86: =(ROUND((((S86+ROUND((ROUND(((EU86)*AV86*1),2)*BS86),2))*AU86)/100),2)+ROUND(((ROUND((ROUND(((AE86-(EU86))*AV86*1),2)*BS86),2)*AU86)/100),2)) -> 0 | DN86: 0 | DO86: 0 | DP86: 1 | DQ86: 1 | DU86: 1013 | DV86: ШТ | DW86: ШТ | DX86: 1 | EE86: 55393630 | EF86: 214 | EG86: Оборудование, отсутствующие в СНБ | EH86: 0 | EJ86: 3 | EK86: 400007 | EL86: Оборудование, отсутствующие в СНБ | EM86: Оборуд. КА | EQ86: 16 | ER86: 0 | ES86: 477.56 | ET86: 0 | EU86: 0 | EV86: 0 | EW86: 0 | EX86: 0 | EY86: 0 | EZ86: 5 | FC86: 1 | FD86: 18 | FF86: 5500 | FQ86: 0 | FR86: =P86 -> 4699.19 | FS86: 0 | FX86: 0 | FY86: 0 | GA86: [5 500 / 1,22 / 9,84] + 1,2% Трансп + 3% Заг.скл | GD86: 1 | GF86: 1035702266 | GG86: 2 | GH86: 3 | GI86: 5 | GJ86: 0 | GK86: 0 | GL86: =ROUND(IF(AND(BH86=3,BI86=3,FS86<>0),P86,0),2) -> 0 | GM86: =ROUND(O86+X86+Y86,2)+GX86 -> 4699.19 | GN86: =IF(OR(BI86=0,BI86=1),GM86-GX86,0) -> 0 | GO86: =IF(BI86=2,GM86-GX86,0) -> 0 | GP86: =IF(BI86=4,GM86-GX86,0) -> 0 | GR86: 1 | GS86: 1 | GT86: 0 | GV86: =ROUND((GT86),6) -> 0 | GW86: 1 | GX86: =ROUND(HC86*I86,2) -> 0 | HA86: 0 | HB86: 0 | HC86: =GV86*GW86 -> 0 | HE86: 1,2 | HF86: 3 | HS86: 0 | IK86: 0
A87: 17 | B87: 1 | C87: =ROW(SmtRes!A70) -> 70 | D87: =ROW(EtalonRes!A84) -> 84 | E87: 13 | F87: 4.10-136-1 | G87: Монтаж коробки телевизионной (ответвители, разветвители магистральные, домовые, абонентские), УСС, БФТК | H87: 1 ШТ. | I87: 1 | J87: 0 | K87: 1 | O87: =ROUND(CP87,2) -> 14.67 | P87: =ROUND((ROUND((AC87*AW87*I87),2)*BC87),2) -> 0.3 | Q87: =(ROUND((ROUND((((ET87*1.2))*AV87*I87),2)*BB87),2)+ROUND((ROUND(((AE87-((EU87*1.2)))*AV87*I87),2)*BS87),2)) -> 0 | R87: =(ROUND((ROUND((((EU87*1.2))*AV87*I87),2)*BS87),2)+ROUND((ROUND(((AE87-((EU87*1.2)))*AV87*I87),2)*BS87),2)) -> 0 | S87: =ROUND((ROUND((AF87*AV87*I87),2)*BA87),2) -> 14.37 | T87: =ROUND(CU87*I87,2) -> 0 | U87: =CV87*I87 -> 1.04352 | V87: =CW87*I87 -> 0 | W87: =ROUND(CX87*I87,2) -> 0 | X87: =(ROUND((((S87+ROUND((ROUND((((EU87*1.2))*AV87*I87),2)*BS87),2))*AT87)/100),2)+ROUND(((ROUND((ROUND(((AE87-((EU87*1.2)))*AV87*I87),2)*BS87),2)*AT87)/100),2)) -> 13.65 | Y87: =(ROUND((((S87+ROUND((ROUND((((EU87*1.2))*AV87*I87),2)*BS87),2))*AU87)/100),2)+ROUND(((ROUND((ROUND(((AE87-((EU87*1.2)))*AV87*I87),2)*BS87),2)*AU87)/100),2)) -> 7.62 | AA87: 55919547 | AB87: =ROUND((AC87+AD87+AF87),6) -> 13.524 | AC87: =ROUND(((ES87*1)),6) -> 0.3 | AD87: =ROUND(((((ET87*1.2))-((EU87*1.2)))+AE87),6) -> 0 | AE87: =ROUND(((EU87*1.2)),6) -> 0 | AF87: =ROUND(((EV87*1.2)),6) -> 13.224 | AG87: =ROUND((AP87),6) -> 0 | AH87: =((EW87*1.2)) -> 0.96 | AI87: =((EX87*1.2)) -> 0 | AJ87: =(AS87) -> 0 | AK87: 11.32 | AL87: 0.3 | AM87: 0 | AN87: 0 | AO87: 11.02 | AP87: 0 | AQ87: 0.8 | AR87: 0 | AS87: 0 | AT87: 95 | AU87: 53 | AV87: 1.087 | AW87: 1 | AZ87: 1 | BA87: 1 | BB87: 1 | BC87: 1 | BH87: 0 | BI87: 2 | BJ87: ТСН-2001.4 Доп. 81, Сб. 10, т. 136, поз. 1 | BM87: 69 | BN87: 0 | BO87: 4.10-136-1 | BP87: 1 | BQ87: 40 | BR87: 0 | BS87: 1 | BT87: 1 | BU87: 1 | BV87: 1 | BW87: 1 | BX87: 1 | BZ87: 95 | CA87: 53 | CE87: 1566 | CF87: 0 | CG87: 0 | CM87: 0 | CN87: Поправка: Гл.12.Прил.8.п.8. 3_12.00.01.11.001 Наименование: При наличии напряженных и стесненных условий производства работ (стесненность, сложность складирования и транспортной логистики и т.п.) для объектов, расположенных в пределах круговой магистральной системы улиц "Садовое кольцо" города Москвы | CO87: 0 | CP87: =(P87+Q87+S87) -> 14.67 | CQ87: =ROUND((ROUND((AC87*AW87*1),2)*BC87),2) -> 0.3 | CR87: =(ROUND((ROUND((((ET87*1.2))*AV87*1),2)*BB87),2)+ROUND((ROUND(((AE87-((EU87*1.2)))*AV87*1),2)*BS87),2)) -> 0 | CS87: =(ROUND((ROUND((((EU87*1.2))*AV87*1),2)*BS87),2)+ROUND((ROUND(((AE87-((EU87*1.2)))*AV87*1),2)*BS87),2)) -> 0 | CT87: =ROUND((ROUND((AF87*AV87*1),2)*BA87),2) -> 14.37 | CU87: =AG87 -> 0 | CV87: =(AH87*AV87) -> 1.04352 | CW87: =AI87 -> 0 | CX87: =AJ87 -> 0 | CY87: =(ROUND((((S87+ROUND((ROUND((((EU87*1.2))*AV87*1),2)*BS87),2))*AT87)/100),2)+ROUND(((ROUND((ROUND(((AE87-((EU87*1.2)))*AV87*1),2)*BS87),2)*AT87)/100),2)) -> 13.65 | CZ87: =(ROUND((((S87+ROUND((ROUND((((EU87*1.2))*AV87*1),2)*BS87),2))*AU87)/100),2)+ROUND(((ROUND((ROUND(((AE87-((EU87*1.2)))*AV87*1),2)*BS87),2)*AU87)/100),2)) -> 7.62 | DB87: 37 | DD87: *1 | DE87: *1,2 | DF87: *1,2 | DG87: *1,2 | DI87: *1,2 | DJ87: *1,2 | DN87: 0 | DO87: 0 | DP87: 1 | DQ87: 1 | DU87: 1013 | DV87: 1 ШТ. | DW87: 1 ШТ. | DX87: 1 | EE87: 55393701 | EF87: 40 | EG87: Монтаж оборудования | EH87: 0 | EJ87: 2 | EK87: 69 | EL87: ТСН-2001.4-10. Монтаж радиотелевизионного и электронного оборудования | EM87: ТСН-2001.4-10-2 | EO87: Поправка: Гл.12.Прил.8.п.8. 3_12.00.01.11.001 | EQ87: 0 | ER87: 11.32 | ES87: 0.3 | ET87: 0 | EU87: 0 | EV87: 11.02 | EW87: 0.8 | EX87: 0 | EY87: 0 | FQ87: 0 | FR87: 0 | FS87: 0 | FX87: 95 | FY87: 53 | GD87: 1 | GF87: 765090221 | GG87: 2 | GH87: 1 | GI87: 2 | GJ87: 0 | GK87: 0 | GL87: =ROUND(IF(AND(BH87=3,BI87=3,FS87<>0),P87,0),2) -> 0 | GM87: =ROUND(O87+X87+Y87,2)+GX87 -> 35.94 | GN87: =IF(OR(BI87=0,BI87=1),GM87-GX87,0) -> 0 | GO87: =IF(BI87=2,GM87-GX87,0) -> 35.94 | GP87: =IF(BI87=4,GM87-GX87,0) -> 0 | GR87: 0 | GS87: 3 | GT87: 0 | GV87: =ROUND((GT87),6) -> 0 | GW87: 1 | GX87: =ROUND(HC87*I87,2) -> 0 | HA87: 0 | HB87: 0 | HC87: =GV87*GW87 -> 0 | HS87: 0 | IK87: 0
A88: 17 | B88: 1 | C88: =ROW(SmtRes!A72) -> 72 | D88: =ROW(EtalonRes!A86) -> 86 | E88: 13 | F88: 4.10-136-1 | G88: Монтаж коробки телевизионной (ответвители, разветвители магистральные, домовые, абонентские), УСС, БФТК | H88: 1 ШТ. | I88: 1 | J88: 0 | K88: 1 | O88: =ROUND(CP88,2) -> 811.96 | P88: =ROUND((ROUND((AC88*AW88*I88),2)*BC88),2) -> 2.21 | Q88: =(ROUND((ROUND((((ET88*1.2))*AV88*I88),2)*BB88),2)+ROUND((ROUND(((AE88-((EU88*1.2)))*AV88*I88),2)*BS88),2)) -> 0 | R88: =(ROUND((ROUND((((EU88*1.2))*AV88*I88),2)*BS88),2)+ROUND((ROUND(((AE88-((EU88*1.2)))*AV88*I88),2)*BS88),2)) -> 0 | S88: =ROUND((ROUND((AF88*AV88*I88),2)*BA88),2) -> 809.75 | T88: =ROUND(CU88*I88,2) -> 0 | U88: =CV88*I88 -> 1.04352 | V88: =CW88*I88 -> 0 | W88: =ROUND(CX88*I88,2) -> 0 | X88: =(ROUND((((S88+ROUND((ROUND((((EU88*1.2))*AV88*I88),2)*BS88),2))*AT88)/100),2)+ROUND(((ROUND((ROUND(((AE88-((EU88*1.2)))*AV88*I88),2)*BS88),2)*AT88)/100),2)) -> 769.26 | Y88: =(ROUND((((S88+ROUND((ROUND((((EU88*1.2))*AV88*I88),2)*BS88),2))*AU88)/100),2)+ROUND(((ROUND((ROUND(((AE88-((EU88*1.2)))*AV88*I88),2)*BS88),2)*AU88)/100),2)) -> 429.17 | AA88: 55919549 | AB88: =ROUND((AC88+AD88+AF88),6) -> 13.524 | AC88: =ROUND(((ES88*1)),6) -> 0.3 | AD88: =ROUND(((((ET88*1.2))-((EU88*1.2)))+AE88),6) -> 0 | AE88: =ROUND(((EU88*1.2)),6) -> 0 | AF88: =ROUND(((EV88*1.2)),6) -> 13.224 | AG88: =ROUND((AP88),6) -> 0 | AH88: =((EW88*1.2)) -> 0.96 | AI88: =((EX88*1.2)) -> 0 | AJ88: =(AS88) -> 0 | AK88: 11.32 | AL88: 0.3 | AM88: 0 | AN88: 0 | AO88: 11.02 | AP88: 0 | AQ88: 0.8 | AR88: 0 | AS88: 0 | AT88: 95 | AU88: 53 | AV88: 1.087 | AW88: 1 | AZ88: 1 | BA88: 56.35 | BB88: 1 | BC88: 7.37 | BH88: 0 | BI88: 2 | BJ88: ТСН-2001.4 Доп. 81, Сб. 10, т. 136, поз. 1 | BM88: 69 | BN88: 0 | BO88: 4.10-136-1 | BP88: 1 | BQ88: 40 | BR88: 0 | BS88: 56.35 | BT88: 1 | BU88: 1 | BV88: 1 | BW88: 1 | BX88: 1 | BZ88: 95 | CA88: 53 | CE88: 1566 | CF88: 0 | CG88: 0 | CM88: 0 | CN88: Поправка: Гл.12.Прил.8.п.8. 3_12.00.01.11.001 Наименование: При наличии напряженных и стесненных условий производства работ (стесненность, сложность складирования и транспортной логистики и т.п.) для объектов, расположенных в пределах круговой магистральной системы улиц "Садовое кольцо" города Москвы | CO88: 0 | CP88: =(P88+Q88+S88) -> 811.96 | CQ88: =ROUND((ROUND((AC88*AW88*1),2)*BC88),2) -> 2.21 | CR88: =(ROUND((ROUND((((ET88*1.2))*AV88*1),2)*BB88),2)+ROUND((ROUND(((AE88-((EU88*1.2)))*AV88*1),2)*BS88),2)) -> 0 | CS88: =(ROUND((ROUND((((EU88*1.2))*AV88*1),2)*BS88),2)+ROUND((ROUND(((AE88-((EU88*1.2)))*AV88*1),2)*BS88),2)) -> 0 | CT88: =ROUND((ROUND((AF88*AV88*1),2)*BA88),2) -> 809.75 | CU88: =AG88 -> 0 | CV88: =(AH88*AV88) -> 1.04352 | CW88: =AI88 -> 0 | CX88: =AJ88 -> 0 | CY88: =(ROUND((((S88+ROUND((ROUND((((EU88*1.2))*AV88*1),2)*BS88),2))*AT88)/100),2)+ROUND(((ROUND((ROUND(((AE88-((EU88*1.2)))*AV88*1),2)*BS88),2)*AT88)/100),2)) -> 769.26 | CZ88: =(ROUND((((S88+ROUND((ROUND((((EU88*1.2))*AV88*1),2)*BS88),2))*AU88)/100),2)+ROUND(((ROUND((ROUND(((AE88-((EU88*1.2)))*AV88*1),2)*BS88),2)*AU88)/100),2)) -> 429.17 | DB88: 38 | DD88: *1 | DE88: *1,2 | DF88: *1,2 | DG88: *1,2 | DI88: *1,2 | DJ88: *1,2 | DN88: 0 | DO88: 0 | DP88: 1 | DQ88: 1 | DU88: 1013 | DV88: 1 ШТ. | DW88: 1 ШТ. | DX88: 1 | EE88: 55393701 | EF88: 40 | EG88: Монтаж оборудования | EH88: 0 | EJ88: 2 | EK88: 69 | EL88: ТСН-2001.4-10. Монтаж радиотелевизионного и электронного оборудования | EM88: ТСН-2001.4-10-2 | EO88: Поправка: Гл.12.Прил.8.п.8. 3_12.00.01.11.001 | EQ88: 0 | ER88: 11.32 | ES88: 0.3 | ET88: 0 | EU88: 0 | EV88: 11.02 | EW88: 0.8 | EX88: 0 | EY88: 0 | FQ88: 0 | FR88: 0 | FS88: 0 | FX88: 95 | FY88: 53 | GD88: 1 | GF88: 765090221 | GG88: 2 | GH88: 1 | GI88: 2 | GJ88: 0 | GK88: 0 | GL88: =ROUND(IF(AND(BH88=3,BI88=3,FS88<>0),P88,0),2) -> 0 | GM88: =ROUND(O88+X88+Y88,2)+GX88 -> 2010.39 | GN88: =IF(OR(BI88=0,BI88=1),GM88-GX88,0) -> 0 | GO88: =IF(BI88=2,GM88-GX88,0) -> 2010.39 | GP88: =IF(BI88=4,GM88-GX88,0) -> 0 | GR88: 0 | GS88: 3 | GT88: 0 | GV88: =ROUND((GT88),6) -> 0 | GW88: 1 | GX88: =ROUND(HC88*I88,2) -> 0 | HA88: 0 | HB88: 0 | HC88: =GV88*GW88 -> 0 | HS88: 0 | IK88: 0
A89: 17 | B89: 1 | E89: 14 | F89: КА, п.2 | G89: Грозозащита ОВР | H89: ШТ | I89: 1 | J89: 0 | K89: 1 | O89: =ROUND(CP89,2) -> 527.14 | P89: =ROUND((ROUND((AC89*AW89*I89),2)*BC89),2) -> 527.14 | Q89: =(ROUND((ROUND(((ET89)*AV89*I89),2)*BB89),2)+ROUND((ROUND(((AE89-(EU89))*AV89*I89),2)*BS89),2)) -> 0 | R89: =(ROUND((ROUND(((EU89)*AV89*I89),2)*BS89),2)+ROUND((ROUND(((AE89-(EU89))*AV89*I89),2)*BS89),2)) -> 0 | S89: =ROUND((ROUND((AF89*AV89*I89),2)*BA89),2) -> 0 | T89: =ROUND(CU89*I89,2) -> 0 | U89: =CV89*I89 -> 0 | V89: =CW89*I89 -> 0 | W89: =ROUND(CX89*I89,2) -> 0 | X89: =(ROUND((((S89+ROUND((ROUND(((EU89)*AV89*I89),2)*BS89),2))*AT89)/100),2)+ROUND(((ROUND((ROUND(((AE89-(EU89))*AV89*I89),2)*BS89),2)*AT89)/100),2)) -> 0 | Y89: =(ROUND((((S89+ROUND((ROUND(((EU89)*AV89*I89),2)*BS89),2))*AU89)/100),2)+ROUND(((ROUND((ROUND(((AE89-(EU89))*AV89*I89),2)*BS89),2)*AU89)/100),2)) -> 0 | AA89: 55919547 | AB89: =ROUND((AC89+AD89+AF89),6) -> 527.14 | AC89: =ROUND((ES89),6) -> 527.14 | AD89: =ROUND((((ET89)-(EU89))+AE89),6) -> 0 | AE89: =ROUND((EU89),6) -> 0 | AF89: =ROUND((EV89),6) -> 0 | AG89: =ROUND((AP89),6) -> 0 | AH89: =(EW89) -> 0 | AI89: =(EX89) -> 0 | AJ89: =(AS89) -> 0 | AK89: 527.14 | AL89: 527.14 | AM89: 0 | AN89: 0 | AO89: 0 | AP89: 0 | AQ89: 0 | AR89: 0 | AS89: 0 | AT89: 0 | AU89: 0 | AV89: 1 | AW89: 1 | AZ89: 1 | BA89: 1 | BB89: 1 | BC89: 1 | BH89: 3 | BI89: 3 | BJ89: КА, п.2 | BM89: 400007 | BN89: 0 | BP89: 0 | BQ89: 214 | BR89: 0 | BS89: 1 | BT89: 1 | BU89: 1 | BV89: 1 | BW89: 1 | BX89: 1 | BZ89: 0 | CA89: 0 | CE89: 1566 | CF89: 0 | CG89: 0 | CM89: 0 | CO89: 0 | CP89: =(P89+Q89+S89) -> 527.14 | CQ89: =ROUND((ROUND((AC89*AW89*1),2)*BC89),2) -> 527.14 | CR89: =(ROUND((ROUND(((ET89)*AV89*1),2)*BB89),2)+ROUND((ROUND(((AE89-(EU89))*AV89*1),2)*BS89),2)) -> 0 | CS89: =(ROUND((ROUND(((EU89)*AV89*1),2)*BS89),2)+ROUND((ROUND(((AE89-(EU89))*AV89*1),2)*BS89),2)) -> 0 | CT89: =ROUND((ROUND((AF89*AV89*1),2)*BA89),2) -> 0 | CU89: =AG89 -> 0 | CV89: =(AH89*AV89) -> 0 | CW89: =AI89 -> 0 | CX89: =AJ89 -> 0 | CY89: =(ROUND((((S89+ROUND((ROUND(((EU89)*AV89*1),2)*BS89),2))*AT89)/100),2)+ROUND(((ROUND((ROUND(((AE89-(EU89))*AV89*1),2)*BS89),2)*AT89)/100),2)) -> 0 | CZ89: =(ROUND((((S89+ROUND((ROUND(((EU89)*AV89*1),2)*BS89),2))*AU89)/100),2)+ROUND(((ROUND((ROUND(((AE89-(EU89))*AV89*1),2)*BS89),2)*AU89)/100),2)) -> 0 | DN89: 0 | DO89: 0 | DP89: 1 | DQ89: 1 | DU89: 1013 | DV89: ШТ | DW89: ШТ | DX89: 1 | EE89: 55393630 | EF89: 214 | EG89: Оборудование, отсутствующие в СНБ | EH89: 0 | EJ89: 3 | EK89: 400007 | EL89: Оборудование, отсутствующие в СНБ | EM89: Оборуд. КА | EQ89: 16 | ER89: 0 | ES89: 527.14 | ET89: 0 | EU89: 0 | EV89: 0 | EW89: 0 | EX89: 0 | EY89: 0 | FQ89: 0 | FR89: =P89 -> 527.14 | FS89: 0 | FX89: 0 | FY89: 0 | GA89: [6 071,03 / 1,22 / 9,84] + 1,2% Трансп + 3% Заг.скл | GD89: 1 | GF89: 1590157922 | GG89: 2 | GH89: 4 | GI89: -2 | GJ89: 0 | GK89: 0 | GL89: =ROUND(IF(AND(BH89=3,BI89=3,FS89<>0),P89,0),2) -> 0 | GM89: =ROUND(O89+X89+Y89,2)+GX89 -> 527.14 | GN89: =IF(OR(BI89=0,BI89=1),GM89-GX89,0) -> 0 | GO89: =IF(BI89=2,GM89-GX89,0) -> 0 | GP89: =IF(BI89=4,GM89-GX89,0) -> 0 | GR89: 1 | GS89: 2 | GT89: 0 | GV89: =ROUND((GT89),6) -> 0 | GW89: 1 | GX89: =ROUND(HC89*I89,2) -> 0 | HA89: 0 | HB89: 0 | HC89: =GV89*GW89 -> 0 | HE89: 1,2 | HF89: 3 | HS89: 0 | IK89: 0
A90: 17 | B90: 1 | E90: 14 | F90: КА, п.2 | G90: Грозозащита ОВР | H90: ШТ | I90: 1 | J90: 0 | K90: 1 | O90: =ROUND(CP90,2) -> 5187.06 | P90: =ROUND((ROUND((AC90*AW90*I90),2)*BC90),2) -> 5187.06 | Q90: =(ROUND((ROUND(((ET90)*AV90*I90),2)*BB90),2)+ROUND((ROUND(((AE90-(EU90))*AV90*I90),2)*BS90),2)) -> 0 | R90: =(ROUND((ROUND(((EU90)*AV90*I90),2)*BS90),2)+ROUND((ROUND(((AE90-(EU90))*AV90*I90),2)*BS90),2)) -> 0 | S90: =ROUND((ROUND((AF90*AV90*I90),2)*BA90),2) -> 0 | T90: =ROUND(CU90*I90,2) -> 0 | U90: =CV90*I90 -> 0 | V90: =CW90*I90 -> 0 | W90: =ROUND(CX90*I90,2) -> 0 | X90: =(ROUND((((S90+ROUND((ROUND(((EU90)*AV90*I90),2)*BS90),2))*AT90)/100),2)+ROUND(((ROUND((ROUND(((AE90-(EU90))*AV90*I90),2)*BS90),2)*AT90)/100),2)) -> 0 | Y90: =(ROUND((((S90+ROUND((ROUND(((EU90)*AV90*I90),2)*BS90),2))*AU90)/100),2)+ROUND(((ROUND((ROUND(((AE90-(EU90))*AV90*I90),2)*BS90),2)*AU90)/100),2)) -> 0 | AA90: 55919549 | AB90: =ROUND((AC90+AD90+AF90),6) -> 527.14 | AC90: =ROUND((ES90),6) -> 527.14 | AD90: =ROUND((((ET90)-(EU90))+AE90),6) -> 0 | AE90: =ROUND((EU90),6) -> 0 | AF90: =ROUND((EV90),6) -> 0 | AG90: =ROUND((AP90),6) -> 0 | AH90: =(EW90) -> 0 | AI90: =(EX90) -> 0 | AJ90: =(AS90) -> 0 | AK90: 527.14 | AL90: 527.14 | AM90: 0 | AN90: 0 | AO90: 0 | AP90: 0 | AQ90: 0 | AR90: 0 | AS90: 0 | AT90: 0 | AU90: 0 | AV90: 1 | AW90: 1 | AZ90: 1 | BA90: 1 | BB90: 1 | BC90: 9.84 | BH90: 3 | BI90: 3 | BJ90: КА, п.2 | BM90: 400007 | BN90: 0 | BP90: 0 | BQ90: 214 | BR90: 0 | BS90: 1 | BT90: 1 | BU90: 1 | BV90: 1 | BW90: 1 | BX90: 1 | BZ90: 0 | CA90: 0 | CE90: 1566 | CF90: 0 | CG90: 0 | CM90: 0 | CO90: 0 | CP90: =(P90+Q90+S90) -> 5187.06 | CQ90: =ROUND((ROUND((AC90*AW90*1),2)*BC90),2) -> 5187.06 | CR90: =(ROUND((ROUND(((ET90)*AV90*1),2)*BB90),2)+ROUND((ROUND(((AE90-(EU90))*AV90*1),2)*BS90),2)) -> 0 | CS90: =(ROUND((ROUND(((EU90)*AV90*1),2)*BS90),2)+ROUND((ROUND(((AE90-(EU90))*AV90*1),2)*BS90),2)) -> 0 | CT90: =ROUND((ROUND((AF90*AV90*1),2)*BA90),2) -> 0 | CU90: =AG90 -> 0 | CV90: =(AH90*AV90) -> 0 | CW90: =AI90 -> 0 | CX90: =AJ90 -> 0 | CY90: =(ROUND((((S90+ROUND((ROUND(((EU90)*AV90*1),2)*BS90),2))*AT90)/100),2)+ROUND(((ROUND((ROUND(((AE90-(EU90))*AV90*1),2)*BS90),2)*AT90)/100),2)) -> 0 | CZ90: =(ROUND((((S90+ROUND((ROUND(((EU90)*AV90*1),2)*BS90),2))*AU90)/100),2)+ROUND(((ROUND((ROUND(((AE90-(EU90))*AV90*1),2)*BS90),2)*AU90)/100),2)) -> 0 | DN90: 0 | DO90: 0 | DP90: 1 | DQ90: 1 | DU90: 1013 | DV90: ШТ | DW90: ШТ | DX90: 1 | EE90: 55393630 | EF90: 214 | EG90: Оборудование, отсутствующие в СНБ | EH90: 0 | EJ90: 3 | EK90: 400007 | EL90: Оборудование, отсутствующие в СНБ | EM90: Оборуд. КА | EQ90: 16 | ER90: 0 | ES90: 527.14 | ET90: 0 | EU90: 0 | EV90: 0 | EW90: 0 | EX90: 0 | EY90: 0 | EZ90: 5 | FC90: 1 | FD90: 18 | FF90: 6071.03 | FQ90: 0 | FR90: =P90 -> 5187.06 | FS90: 0 | FX90: 0 | FY90: 0 | GA90: [6 071,03 / 1,22 / 9,84] + 1,2% Трансп + 3% Заг.скл | GD90: 1 | GF90: 1590157922 | GG90: 2 | GH90: 3 | GI90: 5 | GJ90: 0 | GK90: 0 | GL90: =ROUND(IF(AND(BH90=3,BI90=3,FS90<>0),P90,0),2) -> 0 | GM90: =ROUND(O90+X90+Y90,2)+GX90 -> 5187.06 | GN90: =IF(OR(BI90=0,BI90=1),GM90-GX90,0) -> 0 | GO90: =IF(BI90=2,GM90-GX90,0) -> 0 | GP90: =IF(BI90=4,GM90-GX90,0) -> 0 | GR90: 1 | GS90: 1 | GT90: 0 | GV90: =ROUND((GT90),6) -> 0 | GW90: 1 | GX90: =ROUND(HC90*I90,2) -> 0 | HA90: 0 | HB90: 0 | HC90: =GV90*GW90 -> 0 | HE90: 1,2 | HF90: 3 | HS90: 0 | IK90: 0
A91: 17 | B91: 1 | C91: =ROW(SmtRes!A81) -> 81 | D91: =ROW(EtalonRes!A95) -> 95 | E91: 15 | F91: 4.8-240-4 | G91: Монтаж пультов и шкафов управления, шкафа (пульта) управления навесного, высотой, шириной, глубиной до 600х600х350 мм | H91: 1 ШТ. | I91: 1 | J91: 0 | K91: 1 | O91: =ROUND(CP91,2) -> 56.97 | P91: =ROUND((ROUND((AC91*AW91*I91),2)*BC91),2) -> 1.46 | Q91: =(ROUND((ROUND((((ET91*1.2))*AV91*I91),2)*BB91),2)+ROUND((ROUND(((AE91-((EU91*1.2)))*AV91*I91),2)*BS91),2)) -> 21.89 | R91: =(ROUND((ROUND((((EU91*1.2))*AV91*I91),2)*BS91),2)+ROUND((ROUND(((AE91-((EU91*1.2)))*AV91*I91),2)*BS91),2)) -> 3.97 | S91: =ROUND((ROUND((AF91*AV91*I91),2)*BA91),2) -> 33.62 | T91: =ROUND(CU91*I91,2) -> 0 | U91: =CV91*I91 -> 2.588184 | V91: =CW91*I91 -> 0 | W91: =ROUND(CX91*I91,2) -> 0 | X91: =(ROUND((((S91+ROUND((ROUND((((EU91*1.2))*AV91*I91),2)*BS91),2))*AT91)/100),2)+ROUND(((ROUND((ROUND(((AE91-((EU91*1.2)))*AV91*I91),2)*BS91),2)*AT91)/100),2)) -> 36.46 | Y91: =(ROUND((((S91+ROUND((ROUND((((EU91*1.2))*AV91*I91),2)*BS91),2))*AU91)/100),2)+ROUND(((ROUND((ROUND(((AE91-((EU91*1.2)))*AV91*I91),2)*BS91),2)*AU91)/100),2)) -> 19.17 | AA91: 55919547 | AB91: =ROUND((AC91+AD91+AF91),6) -> 54.476 | AC91: =ROUND(((ES91*1)),6) -> 1.46 | AD91: =ROUND(((((ET91*1.2))-((EU91*1.2)))+AE91),6) -> 20.904 | AE91: =ROUND(((EU91*1.2)),6) -> 3.792 | AF91: =ROUND(((EV91*1.2)),6) -> 32.112 | AG91: =ROUND((AP91),6) -> 0 | AH91: =((EW91*1.2)) -> 2.472 | AI91: =((EX91*1.2)) -> 0 | AJ91: =(AS91) -> 0 | AK91: 45.64 | AL91: 1.46 | AM91: 17.42 | AN91: 3.16 | AO91: 26.76 | AP91: 0 | AQ91: 2.06 | AR91: 0 | AS91: 0 | AT91: 97 | AU91: 51 | AV91: 1.047 | AW91: 1 | AZ91: 1 | BA91: 1 | BB91: 1 | BC91: 1 | BH91: 0 | BI91: 2 | BJ91: ТСН-2001.4 Доп. 80, Сб. 8, т. 240, поз. 4 | BM91: 67 | BN91: 0 | BO91: 4.8-240-4 | BP91: 1 | BQ91: 40 | BR91: 0 | BS91: 1 | BT91: 1 | BU91: 1 | BV91: 1 | BW91: 1 | BX91: 1 | BZ91: 97 | CA91: 51 | CE91: 1566 | CF91: 0 | CG91: 0 | CM91: 0 | CN91: Поправка: Гл.12.Прил.8.п.8. 3_12.00.01.11.001 Наименование: При наличии напряженных и стесненных условий производства работ (стесненность, сложность складирования и транспортной логистики и т.п.) для объектов, расположенных в пределах круговой магистральной системы улиц "Садовое кольцо" города Москвы | CO91: 0 | CP91: =(P91+Q91+S91) -> 56.97 | CQ91: =ROUND((ROUND((AC91*AW91*1),2)*BC91),2) -> 1.46 | CR91: =(ROUND((ROUND((((ET91*1.2))*AV91*1),2)*BB91),2)+ROUND((ROUND(((AE91-((EU91*1.2)))*AV91*1),2)*BS91),2)) -> 21.89 | CS91: =(ROUND((ROUND((((EU91*1.2))*AV91*1),2)*BS91),2)+ROUND((ROUND(((AE91-((EU91*1.2)))*AV91*1),2)*BS91),2)) -> 3.97 | CT91: =ROUND((ROUND((AF91*AV91*1),2)*BA91),2) -> 33.62 | CU91: =AG91 -> 0 | CV91: =(AH91*AV91) -> 2.588184 | CW91: =AI91 -> 0 | CX91: =AJ91 -> 0 | CY91: =(ROUND((((S91+ROUND((ROUND((((EU91*1.2))*AV91*1),2)*BS91),2))*AT91)/100),2)+ROUND(((ROUND((ROUND(((AE91-((EU91*1.2)))*AV91*1),2)*BS91),2)*AT91)/100),2)) -> 36.46 | CZ91: =(ROUND((((S91+ROUND((ROUND((((EU91*1.2))*AV91*1),2)*BS91),2))*AU91)/100),2)+ROUND(((ROUND((ROUND(((AE91-((EU91*1.2)))*AV91*1),2)*BS91),2)*AU91)/100),2)) -> 19.17 | DB91: 39 | DD91: *1 | DE91: *1,2 | DF91: *1,2 | DG91: *1,2 | DI91: *1,2 | DJ91: *1,2 | DN91: 0 | DO91: 0 | DP91: 1 | DQ91: 1 | DU91: 1013 | DV91: 1 ШТ. | DW91: 1 ШТ. | DX91: 1 | EE91: 55393699 | EF91: 40 | EG91: Монтаж оборудования | EH91: 0 | EJ91: 2 | EK91: 67 | EL91: ТСН-2001.4-8. Электротехнические установки | EM91: ТСН-2001.4-8-1 | EO91: Поправка: Гл.12.Прил.8.п.8. 3_12.00.01.11.001 | EQ91: 0 | ER91: 45.64 | ES91: 1.46 | ET91: 17.42 | EU91: 3.16 | EV91: 26.76 | EW91: 2.06 | EX91: 0 | EY91: 0 | FQ91: 0 | FR91: 0 | FS91: 0 | FX91: 97 | FY91: 51 | GD91: 1 | GF91: -1842782186 | GG91: 2 | GH91: 1 | GI91: 2 | GJ91: 0 | GK91: 0 | GL91: =ROUND(IF(AND(BH91=3,BI91=3,FS91<>0),P91,0),2) -> 0 | GM91: =ROUND(O91+X91+Y91,2)+GX91 -> 112.6 | GN91: =IF(OR(BI91=0,BI91=1),GM91-GX91,0) -> 0 | GO91: =IF(BI91=2,GM91-GX91,0) -> 112.6 | GP91: =IF(BI91=4,GM91-GX91,0) -> 0 | GR91: 0 | GS91: 3 | GT91: 0 | GV91: =ROUND((GT91),6) -> 0 | GW91: 1 | GX91: =ROUND(HC91*I91,2) -> 0 | HA91: 0 | HB91: 0 | HC91: =GV91*GW91 -> 0 | HS91: 0 | IK91: 0
A92: 17 | B92: 1 | C92: =ROW(SmtRes!A90) -> 90 | D92: =ROW(EtalonRes!A104) -> 104 | E92: 15 | F92: 4.8-240-4 | G92: Монтаж пультов и шкафов управления, шкафа (пульта) управления навесного, высотой, шириной, глубиной до 600х600х350 мм | H92: 1 ШТ. | I92: 1 | J92: 0 | K92: 1 | O92: =ROUND(CP92,2) -> 2346.01 | P92: =ROUND((ROUND((AC92*AW92*I92),2)*BC92),2) -> 16.13 | Q92: =(ROUND((ROUND((((ET92*1.2))*AV92*I92),2)*BB92),2)+ROUND((ROUND(((AE92-((EU92*1.2)))*AV92*I92),2)*BS92),2)) -> 435.39 | R92: =(ROUND((ROUND((((EU92*1.2))*AV92*I92),2)*BS92),2)+ROUND((ROUND(((AE92-((EU92*1.2)))*AV92*I92),2)*BS92),2)) -> 223.71 | S92: =ROUND((ROUND((AF92*AV92*I92),2)*BA92),2) -> 1894.49 | T92: =ROUND(CU92*I92,2) -> 0 | U92: =CV92*I92 -> 2.588184 | V92: =CW92*I92 -> 0 | W92: =ROUND(CX92*I92,2) -> 0 | X92: =(ROUND((((S92+ROUND((ROUND((((EU92*1.2))*AV92*I92),2)*BS92),2))*AT92)/100),2)+ROUND(((ROUND((ROUND(((AE92-((EU92*1.2)))*AV92*I92),2)*BS92),2)*AT92)/100),2)) -> 2054.65 | Y92: =(ROUND((((S92+ROUND((ROUND((((EU92*1.2))*AV92*I92),2)*BS92),2))*AU92)/100),2)+ROUND(((ROUND((ROUND(((AE92-((EU92*1.2)))*AV92*I92),2)*BS92),2)*AU92)/100),2)) -> 1080.28 | AA92: 55919549 | AB92: =ROUND((AC92+AD92+AF92),6) -> 54.476 | AC92: =ROUND(((ES92*1)),6) -> 1.46 | AD92: =ROUND(((((ET92*1.2))-((EU92*1.2)))+AE92),6) -> 20.904 | AE92: =ROUND(((EU92*1.2)),6) -> 3.792 | AF92: =ROUND(((EV92*1.2)),6) -> 32.112 | AG92: =ROUND((AP92),6) -> 0 | AH92: =((EW92*1.2)) -> 2.472 | AI92: =((EX92*1.2)) -> 0 | AJ92: =(AS92) -> 0 | AK92: 45.64 | AL92: 1.46 | AM92: 17.42 | AN92: 3.16 | AO92: 26.76 | AP92: 0 | AQ92: 2.06 | AR92: 0 | AS92: 0 | AT92: 97 | AU92: 51 | AV92: 1.047 | AW92: 1 | AZ92: 1 | BA92: 56.35 | BB92: 19.89 | BC92: 11.05 | BH92: 0 | BI92: 2 | BJ92: ТСН-2001.4 Доп. 80, Сб. 8, т. 240, поз. 4 | BM92: 67 | BN92: 0 | BO92: 4.8-240-4 | BP92: 1 | BQ92: 40 | BR92: 0 | BS92: 56.35 | BT92: 1 | BU92: 1 | BV92: 1 | BW92: 1 | BX92: 1 | BZ92: 97 | CA92: 51 | CE92: 1566 | CF92: 0 | CG92: 0 | CM92: 0 | CN92: Поправка: Гл.12.Прил.8.п.8. 3_12.00.01.11.001 Наименование: При наличии напряженных и стесненных условий производства работ (стесненность, сложность складирования и транспортной логистики и т.п.) для объектов, расположенных в пределах круговой магистральной системы улиц "Садовое кольцо" города Москвы | CO92: 0 | CP92: =(P92+Q92+S92) -> 2346.01 | CQ92: =ROUND((ROUND((AC92*AW92*1),2)*BC92),2) -> 16.13 | CR92: =(ROUND((ROUND((((ET92*1.2))*AV92*1),2)*BB92),2)+ROUND((ROUND(((AE92-((EU92*1.2)))*AV92*1),2)*BS92),2)) -> 435.39 | CS92: =(ROUND((ROUND((((EU92*1.2))*AV92*1),2)*BS92),2)+ROUND((ROUND(((AE92-((EU92*1.2)))*AV92*1),2)*BS92),2)) -> 223.71 | CT92: =ROUND((ROUND((AF92*AV92*1),2)*BA92),2) -> 1894.49 | CU92: =AG92 -> 0 | CV92: =(AH92*AV92) -> 2.588184 | CW92: =AI92 -> 0 | CX92: =AJ92 -> 0 | CY92: =(ROUND((((S92+ROUND((ROUND((((EU92*1.2))*AV92*1),2)*BS92),2))*AT92)/100),2)+ROUND(((ROUND((ROUND(((AE92-((EU92*1.2)))*AV92*1),2)*BS92),2)*AT92)/100),2)) -> 2054.65 | CZ92: =(ROUND((((S92+ROUND((ROUND((((EU92*1.2))*AV92*1),2)*BS92),2))*AU92)/100),2)+ROUND(((ROUND((ROUND(((AE92-((EU92*1.2)))*AV92*1),2)*BS92),2)*AU92)/100),2)) -> 1080.28 | DB92: 40 | DD92: *1 | DE92: *1,2 | DF92: *1,2 | DG92: *1,2 | DI92: *1,2 | DJ92: *1,2 | DN92: 0 | DO92: 0 | DP92: 1 | DQ92: 1 | DU92: 1013 | DV92: 1 ШТ. | DW92: 1 ШТ. | DX92: 1 | EE92: 55393699 | EF92: 40 | EG92: Монтаж оборудования | EH92: 0 | EJ92: 2 | EK92: 67 | EL92: ТСН-2001.4-8. Электротехнические установки | EM92: ТСН-2001.4-8-1 | EO92: Поправка: Гл.12.Прил.8.п.8. 3_12.00.01.11.001 | EQ92: 0 | ER92: 45.64 | ES92: 1.46 | ET92: 17.42 | EU92: 3.16 | EV92: 26.76 | EW92: 2.06 | EX92: 0 | EY92: 0 | FQ92: 0 | FR92: 0 | FS92: 0 | FX92: 97 | FY92: 51 | GD92: 1 | GF92: -1842782186 | GG92: 2 | GH92: 1 | GI92: 2 | GJ92: 0 | GK92: 0 | GL92: =ROUND(IF(AND(BH92=3,BI92=3,FS92<>0),P92,0),2) -> 0 | GM92: =ROUND(O92+X92+Y92,2)+GX92 -> 5480.94 | GN92: =IF(OR(BI92=0,BI92=1),GM92-GX92,0) -> 0 | GO92: =IF(BI92=2,GM92-GX92,0) -> 5480.94 | GP92: =IF(BI92=4,GM92-GX92,0) -> 0 | GR92: 0 | GS92: 3 | GT92: 0 | GV92: =ROUND((GT92),6) -> 0 | GW92: 1 | GX92: =ROUND(HC92*I92,2) -> 0 | HA92: 0 | HB92: 0 | HC92: =GV92*GW92 -> 0 | HS92: 0 | IK92: 0
A93: 18 | B93: 1 | C93: 80 | E93: 15,1 | F93: 1.1-1-8146 | G93: Болты стальные оцинкованные с шестигранной головкой, с полной резьбой, с гайкой оцинкованной, М6, длина от 12 до 60 мм | H93: кг | I93: =I91*J93 -> 0.1 | J93: 0.1 | K93: 0.1 | O93: =ROUND(CP93,2) -> 3.11 | P93: =ROUND((ROUND((AC93*AW93*I93),2)*BC93),2) -> 3.11 | Q93: =(ROUND((ROUND(((ET93)*AV93*I93),2)*BB93),2)+ROUND((ROUND(((AE93-(EU93))*AV93*I93),2)*BS93),2)) -> 0 | R93: =(ROUND((ROUND(((EU93)*AV93*I93),2)*BS93),2)+ROUND((ROUND(((AE93-(EU93))*AV93*I93),2)*BS93),2)) -> 0 | S93: =ROUND((ROUND((AF93*AV93*I93),2)*BA93),2) -> 0 | T93: =ROUND(CU93*I93,2) -> 0 | U93: =CV93*I93 -> 0 | V93: =CW93*I93 -> 0 | W93: =ROUND(CX93*I93,2) -> 0 | X93: =(ROUND((((S93+ROUND((ROUND(((EU93)*AV93*I93),2)*BS93),2))*AT93)/100),2)+ROUND(((ROUND((ROUND(((AE93-(EU93))*AV93*I93),2)*BS93),2)*AT93)/100),2)) -> 0 | Y93: =(ROUND((((S93+ROUND((ROUND(((EU93)*AV93*I93),2)*BS93),2))*AU93)/100),2)+ROUND(((ROUND((ROUND(((AE93-(EU93))*AV93*I93),2)*BS93),2)*AU93)/100),2)) -> 0 | AA93: 55919547 | AB93: =ROUND((AC93+AD93+AF93),6) -> 31.08 | AC93: =ROUND((ES93),6) -> 31.08 | AD93: =ROUND((((ET93)-(EU93))+AE93),6) -> 0 | AE93: =ROUND((EU93),6) -> 0 | AF93: =ROUND((EV93),6) -> 0 | AG93: =ROUND((AP93),6) -> 0 | AH93: =(EW93) -> 0 | AI93: =(EX93) -> 0 | AJ93: =(AS93) -> 0 | AK93: 31.08 | AL93: 31.08 | AM93: 0 | AN93: 0 | AO93: 0 | AP93: 0 | AQ93: 0 | AR93: 0 | AS93: 0 | AT93: 97 | AU93: 51 | AV93: 1 | AW93: 1 | AZ93: 1 | BA93: 1 | BB93: 1 | BC93: 1 | BH93: 3 | BI93: 2 | BJ93: ТСН-2001.1 Доп. 79, Р. 1, о. 1, поз. 8146 | BM93: 67 | BN93: 0 | BP93: 0 | BQ93: 40 | BR93: 0 | BS93: 1 | BT93: 1 | BU93: 1 | BV93: 1 | BW93: 1 | BX93: 1 | BZ93: 97 | CA93: 51 | CE93: 1566 | CF93: 0 | CG93: 0 | CM93: 0 | CN93: Поправка: Гл.12.Прил.8.п.8. 3_12.00.01.11.001_x000D_ Наименование: При наличии напряженных и стесненных условий производства работ (стесненность, сложность складирования и транспортной логистики и т.п.) для объектов, расположенных в пределах круговой магистральной системы улиц "Садовое кольцо" города Москвы | CO93: 0 | CP93: =(P93+Q93+S93) -> 3.11 | CQ93: =ROUND((ROUND((AC93*AW93*1),2)*BC93),2) -> 31.08 | CR93: =(ROUND((ROUND(((ET93)*AV93*1),2)*BB93),2)+ROUND((ROUND(((AE93-(EU93))*AV93*1),2)*BS93),2)) -> 0 | CS93: =(ROUND((ROUND(((EU93)*AV93*1),2)*BS93),2)+ROUND((ROUND(((AE93-(EU93))*AV93*1),2)*BS93),2)) -> 0 | CT93: =ROUND((ROUND((AF93*AV93*1),2)*BA93),2) -> 0 | CU93: =AG93 -> 0 | CV93: =(AH93*AV93) -> 0 | CW93: =AI93 -> 0 | CX93: =AJ93 -> 0 | CY93: =(ROUND((((S93+ROUND((ROUND(((EU93)*AV93*1),2)*BS93),2))*AT93)/100),2)+ROUND(((ROUND((ROUND(((AE93-(EU93))*AV93*1),2)*BS93),2)*AT93)/100),2)) -> 0 | CZ93: =(ROUND((((S93+ROUND((ROUND(((EU93)*AV93*1),2)*BS93),2))*AU93)/100),2)+ROUND(((ROUND((ROUND(((AE93-(EU93))*AV93*1),2)*BS93),2)*AU93)/100),2)) -> 0 | DN93: 0 | DO93: 0 | DP93: 1 | DQ93: 1 | DU93: 1009 | DV93: кг | DW93: кг | DX93: 1 | EE93: 55393699 | EF93: 40 | EG93: Монтаж оборудования | EH93: 0 | EJ93: 2 | EK93: 67 | EL93: ТСН-2001.4-8. Электротехнические установки | EM93: ТСН-2001.4-8-1 | EO93: Поправка: Гл.12.Прил.8.п.8. 3_12.00.01.11.001 | EQ93: 0 | ER93: 31.08 | ES93: 31.08 | ET93: 0 | EU93: 0 | EV93: 0 | EW93: 0 | EX93: 0 | FQ93: 0 | FR93: 0 | FS93: 0 | FX93: 97 | FY93: 51 | GD93: 1 | GF93: -2097101800 | GG93: 2 | GH93: 1 | GI93: -2 | GJ93: 0 | GK93: 0 | GL93: =ROUND(IF(AND(BH93=3,BI93=3,FS93<>0),P93,0),2) -> 0 | GM93: =ROUND(O93+X93+Y93,2)+GX93 -> 3.11 | GN93: =IF(OR(BI93=0,BI93=1),GM93-GX93,0) -> 0 | GO93: =IF(BI93=2,GM93-GX93,0) -> 3.11 | GP93: =IF(BI93=4,GM93-GX93,0) -> 0 | GR93: 0 | GS93: 3 | GT93: 0 | GV93: =ROUND((GT93),6) -> 0 | GW93: 1 | GX93: =ROUND(HC93*I93,2) -> 0 | HA93: 0 | HB93: 0 | HC93: =GV93*GW93 -> 0 | HM93: *1 | HS93: 0 | IK93: 0
A94: 18 | B94: 1 | C94: 89 | E94: 15,1 | F94: 1.1-1-8146 | G94: Болты стальные оцинкованные с шестигранной головкой, с полной резьбой, с гайкой оцинкованной, М6, длина от 12 до 60 мм | H94: кг | I94: =I92*J94 -> 0.1 | J94: 0.1 | K94: 0.1 | O94: =ROUND(CP94,2) -> 11.16 | P94: =ROUND((ROUND((AC94*AW94*I94),2)*BC94),2) -> 11.16 | Q94: =(ROUND((ROUND(((ET94)*AV94*I94),2)*BB94),2)+ROUND((ROUND(((AE94-(EU94))*AV94*I94),2)*BS94),2)) -> 0 | R94: =(ROUND((ROUND(((EU94)*AV94*I94),2)*BS94),2)+ROUND((ROUND(((AE94-(EU94))*AV94*I94),2)*BS94),2)) -> 0 | S94: =ROUND((ROUND((AF94*AV94*I94),2)*BA94),2) -> 0 | T94: =ROUND(CU94*I94,2) -> 0 | U94: =CV94*I94 -> 0 | V94: =CW94*I94 -> 0 | W94: =ROUND(CX94*I94,2) -> 0 | X94: =(ROUND((((S94+ROUND((ROUND(((EU94)*AV94*I94),2)*BS94),2))*AT94)/100),2)+ROUND(((ROUND((ROUND(((AE94-(EU94))*AV94*I94),2)*BS94),2)*AT94)/100),2)) -> 0 | Y94: =(ROUND((((S94+ROUND((ROUND(((EU94)*AV94*I94),2)*BS94),2))*AU94)/100),2)+ROUND(((ROUND((ROUND(((AE94-(EU94))*AV94*I94),2)*BS94),2)*AU94)/100),2)) -> 0 | AA94: 55919549 | AB94: =ROUND((AC94+AD94+AF94),6) -> 31.08 | AC94: =ROUND((ES94),6) -> 31.08 | AD94: =ROUND((((ET94)-(EU94))+AE94),6) -> 0 | AE94: =ROUND((EU94),6) -> 0 | AF94: =ROUND((EV94),6) -> 0 | AG94: =ROUND((AP94),6) -> 0 | AH94: =(EW94) -> 0 | AI94: =(EX94) -> 0 | AJ94: =(AS94) -> 0 | AK94: 31.08 | AL94: 31.08 | AM94: 0 | AN94: 0 | AO94: 0 | AP94: 0 | AQ94: 0 | AR94: 0 | AS94: 0 | AT94: 97 | AU94: 51 | AV94: 1 | AW94: 1 | AZ94: 1 | BA94: 1 | BB94: 1 | BC94: 3.59 | BH94: 3 | BI94: 2 | BJ94: ТСН-2001.1 Доп. 79, Р. 1, о. 1, поз. 8146 | BM94: 67 | BN94: 0 | BO94: 1.1-1-8146 | BP94: 1 | BQ94: 40 | BR94: 0 | BS94: 1 | BT94: 1 | BU94: 1 | BV94: 1 | BW94: 1 | BX94: 1 | BZ94: 97 | CA94: 51 | CE94: 1566 | CF94: 0 | CG94: 0 | CM94: 0 | CN94: Поправка: Гл.12.Прил.8.п.8. 3_12.00.01.11.001_x000D_ Наименование: При наличии напряженных и стесненных условий производства работ (стесненность, сложность складирования и транспортной логистики и т.п.) для объектов, расположенных в пределах круговой магистральной системы улиц "Садовое кольцо" города Москвы | CO94: 0 | CP94: =(P94+Q94+S94) -> 11.16 | CQ94: =ROUND((ROUND((AC94*AW94*1),2)*BC94),2) -> 111.58 | CR94: =(ROUND((ROUND(((ET94)*AV94*1),2)*BB94),2)+ROUND((ROUND(((AE94-(EU94))*AV94*1),2)*BS94),2)) -> 0 | CS94: =(ROUND((ROUND(((EU94)*AV94*1),2)*BS94),2)+ROUND((ROUND(((AE94-(EU94))*AV94*1),2)*BS94),2)) -> 0 | CT94: =ROUND((ROUND((AF94*AV94*1),2)*BA94),2) -> 0 | CU94: =AG94 -> 0 | CV94: =(AH94*AV94) -> 0 | CW94: =AI94 -> 0 | CX94: =AJ94 -> 0 | CY94: =(ROUND((((S94+ROUND((ROUND(((EU94)*AV94*1),2)*BS94),2))*AT94)/100),2)+ROUND(((ROUND((ROUND(((AE94-(EU94))*AV94*1),2)*BS94),2)*AT94)/100),2)) -> 0 | CZ94: =(ROUND((((S94+ROUND((ROUND(((EU94)*AV94*1),2)*BS94),2))*AU94)/100),2)+ROUND(((ROUND((ROUND(((AE94-(EU94))*AV94*1),2)*BS94),2)*AU94)/100),2)) -> 0 | DN94: 0 | DO94: 0 | DP94: 1 | DQ94: 1 | DU94: 1009 | DV94: кг | DW94: кг | DX94: 1 | EE94: 55393699 | EF94: 40 | EG94: Монтаж оборудования | EH94: 0 | EJ94: 2 | EK94: 67 | EL94: ТСН-2001.4-8. Электротехнические установки | EM94: ТСН-2001.4-8-1 | EO94: Поправка: Гл.12.Прил.8.п.8. 3_12.00.01.11.001 | EQ94: 0 | ER94: 31.08 | ES94: 31.08 | ET94: 0 | EU94: 0 | EV94: 0 | EW94: 0 | EX94: 0 | FQ94: 0 | FR94: 0 | FS94: 0 | FX94: 97 | FY94: 51 | GD94: 1 | GF94: -2097101800 | GG94: 2 | GH94: 1 | GI94: 2 | GJ94: 0 | GK94: 0 | GL94: =ROUND(IF(AND(BH94=3,BI94=3,FS94<>0),P94,0),2) -> 0 | GM94: =ROUND(O94+X94+Y94,2)+GX94 -> 11.16 | GN94: =IF(OR(BI94=0,BI94=1),GM94-GX94,0) -> 0 | GO94: =IF(BI94=2,GM94-GX94,0) -> 11.16 | GP94: =IF(BI94=4,GM94-GX94,0) -> 0 | GR94: 0 | GS94: 3 | GT94: 0 | GV94: =ROUND((GT94),6) -> 0 | GW94: 1 | GX94: =ROUND(HC94*I94,2) -> 0 | HA94: 0 | HB94: 0 | HC94: =GV94*GW94 -> 0 | HM94: *1 | HS94: 0 | IK94: 0
A95: 18 | B95: 1 | C95: 81 | E95: 15,2 | F95: 1.21-1-65 | G95: Щит навесной, с дверцей и монтажной панелью, степень защиты IР65, размер 600х400х250 мм, металлоконструкция без аппаратов | H95: шт. | I95: =I91*J95 -> 1 | J95: 1 | K95: 1 | O95: =ROUND(CP95,2) -> 2017.95 | P95: =ROUND((ROUND((AC95*AW95*I95),2)*BC95),2) -> 2017.95 | Q95: =(ROUND((ROUND(((ET95)*AV95*I95),2)*BB95),2)+ROUND((ROUND(((AE95-(EU95))*AV95*I95),2)*BS95),2)) -> 0 | R95: =(ROUND((ROUND(((EU95)*AV95*I95),2)*BS95),2)+ROUND((ROUND(((AE95-(EU95))*AV95*I95),2)*BS95),2)) -> 0 | S95: =ROUND((ROUND((AF95*AV95*I95),2)*BA95),2) -> 0 | T95: =ROUND(CU95*I95,2) -> 0 | U95: =CV95*I95 -> 0 | V95: =CW95*I95 -> 0 | W95: =ROUND(CX95*I95,2) -> 0 | X95: =(ROUND((((S95+ROUND((ROUND(((EU95)*AV95*I95),2)*BS95),2))*AT95)/100),2)+ROUND(((ROUND((ROUND(((AE95-(EU95))*AV95*I95),2)*BS95),2)*AT95)/100),2)) -> 0 | Y95: =(ROUND((((S95+ROUND((ROUND(((EU95)*AV95*I95),2)*BS95),2))*AU95)/100),2)+ROUND(((ROUND((ROUND(((AE95-(EU95))*AV95*I95),2)*BS95),2)*AU95)/100),2)) -> 0 | AA95: 55919547 | AB95: =ROUND((AC95+AD95+AF95),6) -> 2017.95 | AC95: =ROUND((ES95),6) -> 2017.95 | AD95: =ROUND((((ET95)-(EU95))+AE95),6) -> 0 | AE95: =ROUND((EU95),6) -> 0 | AF95: =ROUND((EV95),6) -> 0 | AG95: =ROUND((AP95),6) -> 0 | AH95: =(EW95) -> 0 | AI95: =(EX95) -> 0 | AJ95: =(AS95) -> 0 | AK95: 2017.95 | AL95: 2017.95 | AM95: 0 | AN95: 0 | AO95: 0 | AP95: 0 | AQ95: 0 | AR95: 0 | AS95: 0 | AT95: 97 | AU95: 51 | AV95: 1 | AW95: 1 | AZ95: 1 | BA95: 1 | BB95: 1 | BC95: 1 | BH95: 3 | BI95: 2 | BJ95: ТСН-2001.1 Доп. 79, Р. 21, о. 1, поз. 65 | BM95: 67 | BN95: 0 | BP95: 0 | BQ95: 40 | BR95: 0 | BS95: 1 | BT95: 1 | BU95: 1 | BV95: 1 | BW95: 1 | BX95: 1 | BZ95: 97 | CA95: 51 | CE95: 1566 | CF95: 0 | CG95: 0 | CM95: 0 | CN95: Поправка: Гл.12.Прил.8.п.8. 3_12.00.01.11.001_x000D_ Наименование: При наличии напряженных и стесненных условий производства работ (стесненность, сложность складирования и транспортной логистики и т.п.) для объектов, расположенных в пределах круговой магистральной системы улиц "Садовое кольцо" города Москвы | CO95: 0 | CP95: =(P95+Q95+S95) -> 2017.95 | CQ95: =ROUND((ROUND((AC95*AW95*1),2)*BC95),2) -> 2017.95 | CR95: =(ROUND((ROUND(((ET95)*AV95*1),2)*BB95),2)+ROUND((ROUND(((AE95-(EU95))*AV95*1),2)*BS95),2)) -> 0 | CS95: =(ROUND((ROUND(((EU95)*AV95*1),2)*BS95),2)+ROUND((ROUND(((AE95-(EU95))*AV95*1),2)*BS95),2)) -> 0 | CT95: =ROUND((ROUND((AF95*AV95*1),2)*BA95),2) -> 0 | CU95: =AG95 -> 0 | CV95: =(AH95*AV95) -> 0 | CW95: =AI95 -> 0 | CX95: =AJ95 -> 0 | CY95: =(ROUND((((S95+ROUND((ROUND(((EU95)*AV95*1),2)*BS95),2))*AT95)/100),2)+ROUND(((ROUND((ROUND(((AE95-(EU95))*AV95*1),2)*BS95),2)*AT95)/100),2)) -> 0 | CZ95: =(ROUND((((S95+ROUND((ROUND(((EU95)*AV95*1),2)*BS95),2))*AU95)/100),2)+ROUND(((ROUND((ROUND(((AE95-(EU95))*AV95*1),2)*BS95),2)*AU95)/100),2)) -> 0 | DN95: 0 | DO95: 0 | DP95: 1 | DQ95: 1 | DU95: 1010 | DV95: шт. | DW95: шт. | DX95: 1 | EE95: 55393699 | EF95: 40 | EG95: Монтаж оборудования | EH95: 0 | EJ95: 2 | EK95: 67 | EL95: ТСН-2001.4-8. Электротехнические установки | EM95: ТСН-2001.4-8-1 | EO95: Поправка: Гл.12.Прил.8.п.8. 3_12.00.01.11.001 | EQ95: 0 | ER95: 2017.95 | ES95: 2017.95 | ET95: 0 | EU95: 0 | EV95: 0 | EW95: 0 | EX95: 0 | FQ95: 0 | FR95: 0 | FS95: 0 | FX95: 97 | FY95: 51 | GD95: 1 | GF95: -573150796 | GG95: 2 | GH95: 1 | GI95: -2 | GJ95: 0 | GK95: 0 | GL95: =ROUND(IF(AND(BH95=3,BI95=3,FS95<>0),P95,0),2) -> 0 | GM95: =ROUND(O95+X95+Y95,2)+GX95 -> 2017.95 | GN95: =IF(OR(BI95=0,BI95=1),GM95-GX95,0) -> 0 | GO95: =IF(BI95=2,GM95-GX95,0) -> 2017.95 | GP95: =IF(BI95=4,GM95-GX95,0) -> 0 | GR95: 0 | GS95: 3 | GT95: 0 | GV95: =ROUND((GT95),6) -> 0 | GW95: 1 | GX95: =ROUND(HC95*I95,2) -> 0 | HA95: 0 | HB95: 0 | HC95: =GV95*GW95 -> 0 | HM95: *1 | HS95: 0 | IK95: 0
A96: 18 | B96: 1 | C96: 90 | E96: 15,2 | F96: 1.21-1-65 | G96: Щит навесной, с дверцей и монтажной панелью, степень защиты IР65, размер 600х400х250 мм, металлоконструкция без аппаратов | H96: шт. | I96: =I92*J96 -> 1 | J96: 1 | K96: 1 | O96: =ROUND(CP96,2) -> 8031.44 | P96: =ROUND((ROUND((AC96*AW96*I96),2)*BC96),2) -> 8031.44 | Q96: =(ROUND((ROUND(((ET96)*AV96*I96),2)*BB96),2)+ROUND((ROUND(((AE96-(EU96))*AV96*I96),2)*BS96),2)) -> 0 | R96: =(ROUND((ROUND(((EU96)*AV96*I96),2)*BS96),2)+ROUND((ROUND(((AE96-(EU96))*AV96*I96),2)*BS96),2)) -> 0 | S96: =ROUND((ROUND((AF96*AV96*I96),2)*BA96),2) -> 0 | T96: =ROUND(CU96*I96,2) -> 0 | U96: =CV96*I96 -> 0 | V96: =CW96*I96 -> 0 | W96: =ROUND(CX96*I96,2) -> 0 | X96: =(ROUND((((S96+ROUND((ROUND(((EU96)*AV96*I96),2)*BS96),2))*AT96)/100),2)+ROUND(((ROUND((ROUND(((AE96-(EU96))*AV96*I96),2)*BS96),2)*AT96)/100),2)) -> 0 | Y96: =(ROUND((((S96+ROUND((ROUND(((EU96)*AV96*I96),2)*BS96),2))*AU96)/100),2)+ROUND(((ROUND((ROUND(((AE96-(EU96))*AV96*I96),2)*BS96),2)*AU96)/100),2)) -> 0 | AA96: 55919549 | AB96: =ROUND((AC96+AD96+AF96),6) -> 2017.95 | AC96: =ROUND((ES96),6) -> 2017.95 | AD96: =ROUND((((ET96)-(EU96))+AE96),6) -> 0 | AE96: =ROUND((EU96),6) -> 0 | AF96: =ROUND((EV96),6) -> 0 | AG96: =ROUND((AP96),6) -> 0 | AH96: =(EW96) -> 0 | AI96: =(EX96) -> 0 | AJ96: =(AS96) -> 0 | AK96: 2017.95 | AL96: 2017.95 | AM96: 0 | AN96: 0 | AO96: 0 | AP96: 0 | AQ96: 0 | AR96: 0 | AS96: 0 | AT96: 97 | AU96: 51 | AV96: 1 | AW96: 1 | AZ96: 1 | BA96: 1 | BB96: 1 | BC96: 3.98 | BH96: 3 | BI96: 2 | BJ96: ТСН-2001.1 Доп. 79, Р. 21, о. 1, поз. 65 | BM96: 67 | BN96: 0 | BO96: 1.21-1-65 | BP96: 1 | BQ96: 40 | BR96: 0 | BS96: 1 | BT96: 1 | BU96: 1 | BV96: 1 | BW96: 1 | BX96: 1 | BZ96: 97 | CA96: 51 | CE96: 1566 | CF96: 0 | CG96: 0 | CM96: 0 | CN96: Поправка: Гл.12.Прил.8.п.8. 3_12.00.01.11.001_x000D_ Наименование: При наличии напряженных и стесненных условий производства работ (стесненность, сложность складирования и транспортной логистики и т.п.) для объектов, расположенных в пределах круговой магистральной системы улиц "Садовое кольцо" города Москвы | CO96: 0 | CP96: =(P96+Q96+S96) -> 8031.44 | CQ96: =ROUND((ROUND((AC96*AW96*1),2)*BC96),2) -> 8031.44 | CR96: =(ROUND((ROUND(((ET96)*AV96*1),2)*BB96),2)+ROUND((ROUND(((AE96-(EU96))*AV96*1),2)*BS96),2)) -> 0 | CS96: =(ROUND((ROUND(((EU96)*AV96*1),2)*BS96),2)+ROUND((ROUND(((AE96-(EU96))*AV96*1),2)*BS96),2)) -> 0 | CT96: =ROUND((ROUND((AF96*AV96*1),2)*BA96),2) -> 0 | CU96: =AG96 -> 0 | CV96: =(AH96*AV96) -> 0 | CW96: =AI96 -> 0 | CX96: =AJ96 -> 0 | CY96: =(ROUND((((S96+ROUND((ROUND(((EU96)*AV96*1),2)*BS96),2))*AT96)/100),2)+ROUND(((ROUND((ROUND(((AE96-(EU96))*AV96*1),2)*BS96),2)*AT96)/100),2)) -> 0 | CZ96: =(ROUND((((S96+ROUND((ROUND(((EU96)*AV96*1),2)*BS96),2))*AU96)/100),2)+ROUND(((ROUND((ROUND(((AE96-(EU96))*AV96*1),2)*BS96),2)*AU96)/100),2)) -> 0 | DN96: 0 | DO96: 0 | DP96: 1 | DQ96: 1 | DU96: 1010 | DV96: шт. | DW96: шт. | DX96: 1 | EE96: 55393699 | EF96: 40 | EG96: Монтаж оборудования | EH96: 0 | EJ96: 2 | EK96: 67 | EL96: ТСН-2001.4-8. Электротехнические установки | EM96: ТСН-2001.4-8-1 | EO96: Поправка: Гл.12.Прил.8.п.8. 3_12.00.01.11.001 | EQ96: 0 | ER96: 2017.95 | ES96: 2017.95 | ET96: 0 | EU96: 0 | EV96: 0 | EW96: 0 | EX96: 0 | FQ96: 0 | FR96: 0 | FS96: 0 | FX96: 97 | FY96: 51 | GD96: 1 | GF96: -573150796 | GG96: 2 | GH96: 1 | GI96: 2 | GJ96: 0 | GK96: 0 | GL96: =ROUND(IF(AND(BH96=3,BI96=3,FS96<>0),P96,0),2) -> 0 | GM96: =ROUND(O96+X96+Y96,2)+GX96 -> 8031.44 | GN96: =IF(OR(BI96=0,BI96=1),GM96-GX96,0) -> 0 | GO96: =IF(BI96=2,GM96-GX96,0) -> 8031.44 | GP96: =IF(BI96=4,GM96-GX96,0) -> 0 | GR96: 0 | GS96: 3 | GT96: 0 | GV96: =ROUND((GT96),6) -> 0 | GW96: 1 | GX96: =ROUND(HC96*I96,2) -> 0 | HA96: 0 | HB96: 0 | HC96: =GV96*GW96 -> 0 | HM96: *1 | HS96: 0 | IK96: 0
A97: 17 | B97: 1 | C97: =ROW(SmtRes!A92) -> 92 | D97: =ROW(EtalonRes!A106) -> 106 | E97: 16 | F97: 4.10-136-5 | G97: Монтаж базового блока головной станции настенного типа | H97: 1 ШТ. | I97: 1 | J97: 0 | K97: 1 | O97: =ROUND(CP97,2) -> 145.98 | P97: =ROUND((ROUND((AC97*AW97*I97),2)*BC97),2) -> 0.3 | Q97: =(ROUND((ROUND((((ET97*1.2))*AV97*I97),2)*BB97),2)+ROUND((ROUND(((AE97-((EU97*1.2)))*AV97*I97),2)*BS97),2)) -> 0 | R97: =(ROUND((ROUND((((EU97*1.2))*AV97*I97),2)*BS97),2)+ROUND((ROUND(((AE97-((EU97*1.2)))*AV97*I97),2)*BS97),2)) -> 0 | S97: =ROUND((ROUND((AF97*AV97*I97),2)*BA97),2) -> 145.68 | T97: =ROUND(CU97*I97,2) -> 0 | U97: =CV97*I97 -> 10.4352 | V97: =CW97*I97 -> 0 | W97: =ROUND(CX97*I97,2) -> 0 | X97: =(ROUND((((S97+ROUND((ROUND((((EU97*1.2))*AV97*I97),2)*BS97),2))*AT97)/100),2)+ROUND(((ROUND((ROUND(((AE97-((EU97*1.2)))*AV97*I97),2)*BS97),2)*AT97)/100),2)) -> 138.4 | Y97: =(ROUND((((S97+ROUND((ROUND((((EU97*1.2))*AV97*I97),2)*BS97),2))*AU97)/100),2)+ROUND(((ROUND((ROUND(((AE97-((EU97*1.2)))*AV97*I97),2)*BS97),2)*AU97)/100),2)) -> 77.21 | AA97: 55919547 | AB97: =ROUND((AC97+AD97+AF97),6) -> 134.316 | AC97: =ROUND(((ES97*1)),6) -> 0.3 | AD97: =ROUND(((((ET97*1.2))-((EU97*1.2)))+AE97),6) -> 0 | AE97: =ROUND(((EU97*1.2)),6) -> 0 | AF97: =ROUND(((EV97*1.2)),6) -> 134.016 | AG97: =ROUND((AP97),6) -> 0 | AH97: =((EW97*1.2)) -> 9.6 | AI97: =((EX97*1.2)) -> 0 | AJ97: =(AS97) -> 0 | AK97: 111.98 | AL97: 0.3 | AM97: 0 | AN97: 0 | AO97: 111.68 | AP97: 0 | AQ97: 8 | AR97: 0 | AS97: 0 | AT97: 95 | AU97: 53 | AV97: 1.087 | AW97: 1 | AZ97: 1 | BA97: 1 | BB97: 1 | BC97: 1 | BH97: 0 | BI97: 2 | BJ97: ТСН-2001.4 Доп. 81, Сб. 10, т. 136, поз. 5 | BM97: 69 | BN97: 0 | BO97: 4.10-136-5 | BP97: 1 | BQ97: 40 | BR97: 0 | BS97: 1 | BT97: 1 | BU97: 1 | BV97: 1 | BW97: 1 | BX97: 1 | BZ97: 95 | CA97: 53 | CE97: 1566 | CF97: 0 | CG97: 0 | CM97: 0 | CN97: Поправка: Гл.12.Прил.8.п.8. 3_12.00.01.11.001 Наименование: При наличии напряженных и стесненных условий производства работ (стесненность, сложность складирования и транспортной логистики и т.п.) для объектов, расположенных в пределах круговой магистральной системы улиц "Садовое кольцо" города Москвы | CO97: 0 | CP97: =(P97+Q97+S97) -> 145.98 | CQ97: =ROUND((ROUND((AC97*AW97*1),2)*BC97),2) -> 0.3 | CR97: =(ROUND((ROUND((((ET97*1.2))*AV97*1),2)*BB97),2)+ROUND((ROUND(((AE97-((EU97*1.2)))*AV97*1),2)*BS97),2)) -> 0 | CS97: =(ROUND((ROUND((((EU97*1.2))*AV97*1),2)*BS97),2)+ROUND((ROUND(((AE97-((EU97*1.2)))*AV97*1),2)*BS97),2)) -> 0 | CT97: =ROUND((ROUND((AF97*AV97*1),2)*BA97),2) -> 145.68 | CU97: =AG97 -> 0 | CV97: =(AH97*AV97) -> 10.4352 | CW97: =AI97 -> 0 | CX97: =AJ97 -> 0 | CY97: =(ROUND((((S97+ROUND((ROUND((((EU97*1.2))*AV97*1),2)*BS97),2))*AT97)/100),2)+ROUND(((ROUND((ROUND(((AE97-((EU97*1.2)))*AV97*1),2)*BS97),2)*AT97)/100),2)) -> 138.4 | CZ97: =(ROUND((((S97+ROUND((ROUND((((EU97*1.2))*AV97*1),2)*BS97),2))*AU97)/100),2)+ROUND(((ROUND((ROUND(((AE97-((EU97*1.2)))*AV97*1),2)*BS97),2)*AU97)/100),2)) -> 77.21 | DB97: 41 | DD97: *1 | DE97: *1,2 | DF97: *1,2 | DG97: *1,2 | DI97: *1,2 | DJ97: *1,2 | DN97: 0 | DO97: 0 | DP97: 1 | DQ97: 1 | DU97: 1013 | DV97: 1 ШТ. | DW97: 1 ШТ. | DX97: 1 | EE97: 55393701 | EF97: 40 | EG97: Монтаж оборудования | EH97: 0 | EJ97: 2 | EK97: 69 | EL97: ТСН-2001.4-10. Монтаж радиотелевизионного и электронного оборудования | EM97: ТСН-2001.4-10-2 | EO97: Поправка: Гл.12.Прил.8.п.8. 3_12.00.01.11.001 | EQ97: 0 | ER97: 111.98 | ES97: 0.3 | ET97: 0 | EU97: 0 | EV97: 111.68 | EW97: 8 | EX97: 0 | EY97: 0 | FQ97: 0 | FR97: 0 | FS97: 0 | FX97: 95 | FY97: 53 | GD97: 1 | GF97: -1615482096 | GG97: 2 | GH97: 1 | GI97: 2 | GJ97: 0 | GK97: 0 | GL97: =ROUND(IF(AND(BH97=3,BI97=3,FS97<>0),P97,0),2) -> 0 | GM97: =ROUND(O97+X97+Y97,2)+GX97 -> 361.59 | GN97: =IF(OR(BI97=0,BI97=1),GM97-GX97,0) -> 0 | GO97: =IF(BI97=2,GM97-GX97,0) -> 361.59 | GP97: =IF(BI97=4,GM97-GX97,0) -> 0 | GR97: 0 | GS97: 3 | GT97: 0 | GV97: =ROUND((GT97),6) -> 0 | GW97: 1 | GX97: =ROUND(HC97*I97,2) -> 0 | HA97: 0 | HB97: 0 | HC97: =GV97*GW97 -> 0 | HS97: 0 | IK97: 0
A98: 17 | B98: 1 | C98: =ROW(SmtRes!A94) -> 94 | D98: =ROW(EtalonRes!A108) -> 108 | E98: 16 | F98: 4.10-136-5 | G98: Монтаж базового блока головной станции настенного типа | H98: 1 ШТ. | I98: 1 | J98: 0 | K98: 1 | O98: =ROUND(CP98,2) -> 8211.28 | P98: =ROUND((ROUND((AC98*AW98*I98),2)*BC98),2) -> 2.21 | Q98: =(ROUND((ROUND((((ET98*1.2))*AV98*I98),2)*BB98),2)+ROUND((ROUND(((AE98-((EU98*1.2)))*AV98*I98),2)*BS98),2)) -> 0 | R98: =(ROUND((ROUND((((EU98*1.2))*AV98*I98),2)*BS98),2)+ROUND((ROUND(((AE98-((EU98*1.2)))*AV98*I98),2)*BS98),2)) -> 0 | S98: =ROUND((ROUND((AF98*AV98*I98),2)*BA98),2) -> 8209.07 | T98: =ROUND(CU98*I98,2) -> 0 | U98: =CV98*I98 -> 10.4352 | V98: =CW98*I98 -> 0 | W98: =ROUND(CX98*I98,2) -> 0 | X98: =(ROUND((((S98+ROUND((ROUND((((EU98*1.2))*AV98*I98),2)*BS98),2))*AT98)/100),2)+ROUND(((ROUND((ROUND(((AE98-((EU98*1.2)))*AV98*I98),2)*BS98),2)*AT98)/100),2)) -> 7798.62 | Y98: =(ROUND((((S98+ROUND((ROUND((((EU98*1.2))*AV98*I98),2)*BS98),2))*AU98)/100),2)+ROUND(((ROUND((ROUND(((AE98-((EU98*1.2)))*AV98*I98),2)*BS98),2)*AU98)/100),2)) -> 4350.81 | AA98: 55919549 | AB98: =ROUND((AC98+AD98+AF98),6) -> 134.316 | AC98: =ROUND(((ES98*1)),6) -> 0.3 | AD98: =ROUND(((((ET98*1.2))-((EU98*1.2)))+AE98),6) -> 0 | AE98: =ROUND(((EU98*1.2)),6) -> 0 | AF98: =ROUND(((EV98*1.2)),6) -> 134.016 | AG98: =ROUND((AP98),6) -> 0 | AH98: =((EW98*1.2)) -> 9.6 | AI98: =((EX98*1.2)) -> 0 | AJ98: =(AS98) -> 0 | AK98: 111.98 | AL98: 0.3 | AM98: 0 | AN98: 0 | AO98: 111.68 | AP98: 0 | AQ98: 8 | AR98: 0 | AS98: 0 | AT98: 95 | AU98: 53 | AV98: 1.087 | AW98: 1 | AZ98: 1 | BA98: 56.35 | BB98: 1 | BC98: 7.37 | BH98: 0 | BI98: 2 | BJ98: ТСН-2001.4 Доп. 81, Сб. 10, т. 136, поз. 5 | BM98: 69 | BN98: 0 | BO98: 4.10-136-5 | BP98: 1 | BQ98: 40 | BR98: 0 | BS98: 56.35 | BT98: 1 | BU98: 1 | BV98: 1 | BW98: 1 | BX98: 1 | BZ98: 95 | CA98: 53 | CE98: 1566 | CF98: 0 | CG98: 0 | CM98: 0 | CN98: Поправка: Гл.12.Прил.8.п.8. 3_12.00.01.11.001 Наименование: При наличии напряженных и стесненных условий производства работ (стесненность, сложность складирования и транспортной логистики и т.п.) для объектов, расположенных в пределах круговой магистральной системы улиц "Садовое кольцо" города Москвы | CO98: 0 | CP98: =(P98+Q98+S98) -> 8211.28 | CQ98: =ROUND((ROUND((AC98*AW98*1),2)*BC98),2) -> 2.21 | CR98: =(ROUND((ROUND((((ET98*1.2))*AV98*1),2)*BB98),2)+ROUND((ROUND(((AE98-((EU98*1.2)))*AV98*1),2)*BS98),2)) -> 0 | CS98: =(ROUND((ROUND((((EU98*1.2))*AV98*1),2)*BS98),2)+ROUND((ROUND(((AE98-((EU98*1.2)))*AV98*1),2)*BS98),2)) -> 0 | CT98: =ROUND((ROUND((AF98*AV98*1),2)*BA98),2) -> 8209.07 | CU98: =AG98 -> 0 | CV98: =(AH98*AV98) -> 10.4352 | CW98: =AI98 -> 0 | CX98: =AJ98 -> 0 | CY98: =(ROUND((((S98+ROUND((ROUND((((EU98*1.2))*AV98*1),2)*BS98),2))*AT98)/100),2)+ROUND(((ROUND((ROUND(((AE98-((EU98*1.2)))*AV98*1),2)*BS98),2)*AT98)/100),2)) -> 7798.62 | CZ98: =(ROUND((((S98+ROUND((ROUND((((EU98*1.2))*AV98*1),2)*BS98),2))*AU98)/100),2)+ROUND(((ROUND((ROUND(((AE98-((EU98*1.2)))*AV98*1),2)*BS98),2)*AU98)/100),2)) -> 4350.81 | DB98: 42 | DD98: *1 | DE98: *1,2 | DF98: *1,2 | DG98: *1,2 | DI98: *1,2 | DJ98: *1,2 | DN98: 0 | DO98: 0 | DP98: 1 | DQ98: 1 | DU98: 1013 | DV98: 1 ШТ. | DW98: 1 ШТ. | DX98: 1 | EE98: 55393701 | EF98: 40 | EG98: Монтаж оборудования | EH98: 0 | EJ98: 2 | EK98: 69 | EL98: ТСН-2001.4-10. Монтаж радиотелевизионного и электронного оборудования | EM98: ТСН-2001.4-10-2 | EO98: Поправка: Гл.12.Прил.8.п.8. 3_12.00.01.11.001 | EQ98: 0 | ER98: 111.98 | ES98: 0.3 | ET98: 0 | EU98: 0 | EV98: 111.68 | EW98: 8 | EX98: 0 | EY98: 0 | FQ98: 0 | FR98: 0 | FS98: 0 | FX98: 95 | FY98: 53 | GD98: 1 | GF98: -1615482096 | GG98: 2 | GH98: 1 | GI98: 2 | GJ98: 0 | GK98: 0 | GL98: =ROUND(IF(AND(BH98=3,BI98=3,FS98<>0),P98,0),2) -> 0 | GM98: =ROUND(O98+X98+Y98,2)+GX98 -> 20360.71 | GN98: =IF(OR(BI98=0,BI98=1),GM98-GX98,0) -> 0 | GO98: =IF(BI98=2,GM98-GX98,0) -> 20360.71 | GP98: =IF(BI98=4,GM98-GX98,0) -> 0 | GR98: 0 | GS98: 3 | GT98: 0 | GV98: =ROUND((GT98),6) -> 0 | GW98: 1 | GX98: =ROUND(HC98*I98,2) -> 0 | HA98: 0 | HB98: 0 | HC98: =GV98*GW98 -> 0 | HS98: 0 | IK98: 0
A99: 17 | B99: 1 | E99: 17 | F99: КА, п.3 | G99: Головная станция СКТ "ГС мини" | H99: ШТ | I99: 1 | J99: 0 | K99: 1 | O99: =ROUND(CP99,2) -> 7200.12 | P99: =ROUND((ROUND((AC99*AW99*I99),2)*BC99),2) -> 7200.12 | Q99: =(ROUND((ROUND(((ET99)*AV99*I99),2)*BB99),2)+ROUND((ROUND(((AE99-(EU99))*AV99*I99),2)*BS99),2)) -> 0 | R99: =(ROUND((ROUND(((EU99)*AV99*I99),2)*BS99),2)+ROUND((ROUND(((AE99-(EU99))*AV99*I99),2)*BS99),2)) -> 0 | S99: =ROUND((ROUND((AF99*AV99*I99),2)*BA99),2) -> 0 | T99: =ROUND(CU99*I99,2) -> 0 | U99: =CV99*I99 -> 0 | V99: =CW99*I99 -> 0 | W99: =ROUND(CX99*I99,2) -> 0 | X99: =(ROUND((((S99+ROUND((ROUND(((EU99)*AV99*I99),2)*BS99),2))*AT99)/100),2)+ROUND(((ROUND((ROUND(((AE99-(EU99))*AV99*I99),2)*BS99),2)*AT99)/100),2)) -> 0 | Y99: =(ROUND((((S99+ROUND((ROUND(((EU99)*AV99*I99),2)*BS99),2))*AU99)/100),2)+ROUND(((ROUND((ROUND(((AE99-(EU99))*AV99*I99),2)*BS99),2)*AU99)/100),2)) -> 0 | AA99: 55919547 | AB99: =ROUND((AC99+AD99+AF99),6) -> 7200.12 | AC99: =ROUND((ES99),6) -> 7200.12 | AD99: =ROUND((((ET99)-(EU99))+AE99),6) -> 0 | AE99: =ROUND((EU99),6) -> 0 | AF99: =ROUND((EV99),6) -> 0 | AG99: =ROUND((AP99),6) -> 0 | AH99: =(EW99) -> 0 | AI99: =(EX99) -> 0 | AJ99: =(AS99) -> 0 | AK99: 7200.12 | AL99: 7200.12 | AM99: 0 | AN99: 0 | AO99: 0 | AP99: 0 | AQ99: 0 | AR99: 0 | AS99: 0 | AT99: 0 | AU99: 0 | AV99: 1 | AW99: 1 | AZ99: 1 | BA99: 1 | BB99: 1 | BC99: 1 | BH99: 3 | BI99: 3 | BJ99: КА, п.3 | BM99: 400007 | BN99: 0 | BP99: 0 | BQ99: 214 | BR99: 0 | BS99: 1 | BT99: 1 | BU99: 1 | BV99: 1 | BW99: 1 | BX99: 1 | BZ99: 0 | CA99: 0 | CE99: 1566 | CF99: 0 | CG99: 0 | CM99: 0 | CO99: 0 | CP99: =(P99+Q99+S99) -> 7200.12 | CQ99: =ROUND((ROUND((AC99*AW99*1),2)*BC99),2) -> 7200.12 | CR99: =(ROUND((ROUND(((ET99)*AV99*1),2)*BB99),2)+ROUND((ROUND(((AE99-(EU99))*AV99*1),2)*BS99),2)) -> 0 | CS99: =(ROUND((ROUND(((EU99)*AV99*1),2)*BS99),2)+ROUND((ROUND(((AE99-(EU99))*AV99*1),2)*BS99),2)) -> 0 | CT99: =ROUND((ROUND((AF99*AV99*1),2)*BA99),2) -> 0 | CU99: =AG99 -> 0 | CV99: =(AH99*AV99) -> 0 | CW99: =AI99 -> 0 | CX99: =AJ99 -> 0 | CY99: =(ROUND((((S99+ROUND((ROUND(((EU99)*AV99*1),2)*BS99),2))*AT99)/100),2)+ROUND(((ROUND((ROUND(((AE99-(EU99))*AV99*1),2)*BS99),2)*AT99)/100),2)) -> 0 | CZ99: =(ROUND((((S99+ROUND((ROUND(((EU99)*AV99*1),2)*BS99),2))*AU99)/100),2)+ROUND(((ROUND((ROUND(((AE99-(EU99))*AV99*1),2)*BS99),2)*AU99)/100),2)) -> 0 | DN99: 0 | DO99: 0 | DP99: 1 | DQ99: 1 | DU99: 1013 | DV99: ШТ | DW99: ШТ | DX99: 1 | EE99: 55393630 | EF99: 214 | EG99: Оборудование, отсутствующие в СНБ | EH99: 0 | EJ99: 3 | EK99: 400007 | EL99: Оборудование, отсутствующие в СНБ | EM99: Оборуд. КА | EQ99: 16 | ER99: 0 | ES99: 7200.12 | ET99: 0 | EU99: 0 | EV99: 0 | EW99: 0 | EX99: 0 | EY99: 0 | FQ99: 0 | FR99: =P99 -> 7200.12 | FS99: 0 | FX99: 0 | FY99: 0 | GA99: [82 923,38 / 1,22 / 9,84] + 1,2% Трансп + 3% Заг.скл | GD99: 1 | GF99: 1728382367 | GG99: 2 | GH99: 4 | GI99: -2 | GJ99: 0 | GK99: 0 | GL99: =ROUND(IF(AND(BH99=3,BI99=3,FS99<>0),P99,0),2) -> 0 | GM99: =ROUND(O99+X99+Y99,2)+GX99 -> 7200.12 | GN99: =IF(OR(BI99=0,BI99=1),GM99-GX99,0) -> 0 | GO99: =IF(BI99=2,GM99-GX99,0) -> 0 | GP99: =IF(BI99=4,GM99-GX99,0) -> 0 | GR99: 1 | GS99: 2 | GT99: 0 | GV99: =ROUND((GT99),6) -> 0 | GW99: 1 | GX99: =ROUND(HC99*I99,2) -> 0 | HA99: 0 | HB99: 0 | HC99: =GV99*GW99 -> 0 | HE99: 1,2 | HF99: 3 | HS99: 0 | IK99: 0
A100: 17 | B100: 1 | E100: 17 | F100: КА, п.3 | G100: Головная станция СКТ "ГС мини" | H100: ШТ | I100: 1 | J100: 0 | K100: 1 | O100: =ROUND(CP100,2) -> 70849.18 | P100: =ROUND((ROUND((AC100*AW100*I100),2)*BC100),2) -> 70849.18 | Q100: =(ROUND((ROUND(((ET100)*AV100*I100),2)*BB100),2)+ROUND((ROUND(((AE100-(EU100))*AV100*I100),2)*BS100),2)) -> 0 | R100: =(ROUND((ROUND(((EU100)*AV100*I100),2)*BS100),2)+ROUND((ROUND(((AE100-(EU100))*AV100*I100),2)*BS100),2)) -> 0 | S100: =ROUND((ROUND((AF100*AV100*I100),2)*BA100),2) -> 0 | T100: =ROUND(CU100*I100,2) -> 0 | U100: =CV100*I100 -> 0 | V100: =CW100*I100 -> 0 | W100: =ROUND(CX100*I100,2) -> 0 | X100: =(ROUND((((S100+ROUND((ROUND(((EU100)*AV100*I100),2)*BS100),2))*AT100)/100),2)+ROUND(((ROUND((ROUND(((AE100-(EU100))*AV100*I100),2)*BS100),2)*AT100)/100),2)) -> 0 | Y100: =(ROUND((((S100+ROUND((ROUND(((EU100)*AV100*I100),2)*BS100),2))*AU100)/100),2)+ROUND(((ROUND((ROUND(((AE100-(EU100))*AV100*I100),2)*BS100),2)*AU100)/100),2)) -> 0 | AA100: 55919549 | AB100: =ROUND((AC100+AD100+AF100),6) -> 7200.12 | AC100: =ROUND((ES100),6) -> 7200.12 | AD100: =ROUND((((ET100)-(EU100))+AE100),6) -> 0 | AE100: =ROUND((EU100),6) -> 0 | AF100: =ROUND((EV100),6) -> 0 | AG100: =ROUND((AP100),6) -> 0 | AH100: =(EW100) -> 0 | AI100: =(EX100) -> 0 | AJ100: =(AS100) -> 0 | AK100: 7200.12 | AL100: 7200.12 | AM100: 0 | AN100: 0 | AO100: 0 | AP100: 0 | AQ100: 0 | AR100: 0 | AS100: 0 | AT100: 0 | AU100: 0 | AV100: 1 | AW100: 1 | AZ100: 1 | BA100: 1 | BB100: 1 | BC100: 9.84 | BH100: 3 | BI100: 3 | BJ100: КА, п.3 | BM100: 400007 | BN100: 0 | BP100: 0 | BQ100: 214 | BR100: 0 | BS100: 1 | BT100: 1 | BU100: 1 | BV100: 1 | BW100: 1 | BX100: 1 | BZ100: 0 | CA100: 0 | CE100: 1566 | CF100: 0 | CG100: 0 | CM100: 0 | CO100: 0 | CP100: =(P100+Q100+S100) -> 70849.18 | CQ100: =ROUND((ROUND((AC100*AW100*1),2)*BC100),2) -> 70849.18 | CR100: =(ROUND((ROUND(((ET100)*AV100*1),2)*BB100),2)+ROUND((ROUND(((AE100-(EU100))*AV100*1),2)*BS100),2)) -> 0 | CS100: =(ROUND((ROUND(((EU100)*AV100*1),2)*BS100),2)+ROUND((ROUND(((AE100-(EU100))*AV100*1),2)*BS100),2)) -> 0 | CT100: =ROUND((ROUND((AF100*AV100*1),2)*BA100),2) -> 0 | CU100: =AG100 -> 0 | CV100: =(AH100*AV100) -> 0 | CW100: =AI100 -> 0 | CX100: =AJ100 -> 0 | CY100: =(ROUND((((S100+ROUND((ROUND(((EU100)*AV100*1),2)*BS100),2))*AT100)/100),2)+ROUND(((ROUND((ROUND(((AE100-(EU100))*AV100*1),2)*BS100),2)*AT100)/100),2)) -> 0 | CZ100: =(ROUND((((S100+ROUND((ROUND(((EU100)*AV100*1),2)*BS100),2))*AU100)/100),2)+ROUND(((ROUND((ROUND(((AE100-(EU100))*AV100*1),2)*BS100),2)*AU100)/100),2)) -> 0 | DN100: 0 | DO100: 0 | DP100: 1 | DQ100: 1 | DU100: 1013 | DV100: ШТ | DW100: ШТ | DX100: 1 | EE100: 55393630 | EF100: 214 | EG100: Оборудование, отсутствующие в СНБ | EH100: 0 | EJ100: 3 | EK100: 400007 | EL100: Оборудование, отсутствующие в СНБ | EM100: Оборуд. КА | EQ100: 16 | ER100: 0 | ES100: 7200.12 | ET100: 0 | EU100: 0 | EV100: 0 | EW100: 0 | EX100: 0 | EY100: 0 | EZ100: 5 | FC100: 1 | FD100: 18 | FF100: 82923.38 | FQ100: 0 | FR100: =P100 -> 70849.18 | FS100: 0 | FX100: 0 | FY100: 0 | GA100: [82 923,38 / 1,22 / 9,84] + 1,2% Трансп + 3% Заг.скл | GD100: 1 | GF100: 1728382367 | GG100: 2 | GH100: 3 | GI100: 5 | GJ100: 0 | GK100: 0 | GL100: =ROUND(IF(AND(BH100=3,BI100=3,FS100<>0),P100,0),2) -> 0 | GM100: =ROUND(O100+X100+Y100,2)+GX100 -> 70849.18 | GN100: =IF(OR(BI100=0,BI100=1),GM100-GX100,0) -> 0 | GO100: =IF(BI100=2,GM100-GX100,0) -> 0 | GP100: =IF(BI100=4,GM100-GX100,0) -> 0 | GR100: 1 | GS100: 1 | GT100: 0 | GV100: =ROUND((GT100),6) -> 0 | GW100: 1 | GX100: =ROUND(HC100*I100,2) -> 0 | HA100: 0 | HB100: 0 | HC100: =GV100*GW100 -> 0 | HE100: 1,2 | HF100: 3 | HS100: 0 | IK100: 0
A101: 17 | B101: 1 | C101: =ROW(SmtRes!A96) -> 96 | D101: =ROW(EtalonRes!A110) -> 110 | E101: 18 | F101: 4.10-136-3 | G101: Монтаж антенного ТВ усилителя на мачте (без измерений) без повала мачты | H101: 1 ШТ. | I101: 1 | J101: 0 | K101: 1 | O101: =ROUND(CP101,2) -> 33.81 | P101: =ROUND((ROUND((AC101*AW101*I101),2)*BC101),2) -> 0.18 | Q101: =(ROUND((ROUND((((ET101*1.2))*AV101*I101),2)*BB101),2)+ROUND((ROUND(((AE101-((EU101*1.2)))*AV101*I101),2)*BS101),2)) -> 0 | R101: =(ROUND((ROUND((((EU101*1.2))*AV101*I101),2)*BS101),2)+ROUND((ROUND(((AE101-((EU101*1.2)))*AV101*I101),2)*BS101),2)) -> 0 | S101: =ROUND((ROUND((AF101*AV101*I101),2)*BA101),2) -> 33.63 | T101: =ROUND(CU101*I101,2) -> 0 | U101: =CV101*I101 -> 2.47836 | V101: =CW101*I101 -> 0 | W101: =ROUND(CX101*I101,2) -> 0 | X101: =(ROUND((((S101+ROUND((ROUND((((EU101*1.2))*AV101*I101),2)*BS101),2))*AT101)/100),2)+ROUND(((ROUND((ROUND(((AE101-((EU101*1.2)))*AV101*I101),2)*BS101),2)*AT101)/100),2)) -> 31.95 | Y101: =(ROUND((((S101+ROUND((ROUND((((EU101*1.2))*AV101*I101),2)*BS101),2))*AU101)/100),2)+ROUND(((ROUND((ROUND(((AE101-((EU101*1.2)))*AV101*I101),2)*BS101),2)*AU101)/100),2)) -> 17.82 | AA101: 55919547 | AB101: =ROUND((AC101+AD101+AF101),6) -> 31.116 | AC101: =ROUND(((ES101*1)),6) -> 0.18 | AD101: =ROUND(((((ET101*1.2))-((EU101*1.2)))+AE101),6) -> 0 | AE101: =ROUND(((EU101*1.2)),6) -> 0 | AF101: =ROUND(((EV101*1.2)),6) -> 30.936 | AG101: =ROUND((AP101),6) -> 0 | AH101: =((EW101*1.2)) -> 2.28 | AI101: =((EX101*1.2)) -> 0 | AJ101: =(AS101) -> 0 | AK101: 25.96 | AL101: 0.18 | AM101: 0 | AN101: 0 | AO101: 25.78 | AP101: 0 | AQ101: 1.9 | AR101: 0 | AS101: 0 | AT101: 95 | AU101: 53 | AV101: 1.087 | AW101: 1 | AZ101: 1 | BA101: 1 | BB101: 1 | BC101: 1 | BH101: 0 | BI101: 2 | BJ101: ТСН-2001.4 Доп. 81, Сб. 10, т. 136, поз. 3 | BM101: 69 | BN101: 0 | BO101: 4.10-136-3 | BP101: 1 | BQ101: 40 | BR101: 0 | BS101: 1 | BT101: 1 | BU101: 1 | BV101: 1 | BW101: 1 | BX101: 1 | BZ101: 95 | CA101: 53 | CE101: 1566 | CF101: 0 | CG101: 0 | CM101: 0 | CN101: Поправка: Гл.12.Прил.8.п.8. 3_12.00.01.11.001 Наименование: При наличии напряженных и стесненных условий производства работ (стесненность, сложность складирования и транспортной логистики и т.п.) для объектов, расположенных в пределах круговой магистральной системы улиц "Садовое кольцо" города Москвы | CO101: 0 | CP101: =(P101+Q101+S101) -> 33.81 | CQ101: =ROUND((ROUND((AC101*AW101*1),2)*BC101),2) -> 0.18 | CR101: =(ROUND((ROUND((((ET101*1.2))*AV101*1),2)*BB101),2)+ROUND((ROUND(((AE101-((EU101*1.2)))*AV101*1),2)*BS101),2)) -> 0 | CS101: =(ROUND((ROUND((((EU101*1.2))*AV101*1),2)*BS101),2)+ROUND((ROUND(((AE101-((EU101*1.2)))*AV101*1),2)*BS101),2)) -> 0 | CT101: =ROUND((ROUND((AF101*AV101*1),2)*BA101),2) -> 33.63 | CU101: =AG101 -> 0 | CV101: =(AH101*AV101) -> 2.47836 | CW101: =AI101 -> 0 | CX101: =AJ101 -> 0 | CY101: =(ROUND((((S101+ROUND((ROUND((((EU101*1.2))*AV101*1),2)*BS101),2))*AT101)/100),2)+ROUND(((ROUND((ROUND(((AE101-((EU101*1.2)))*AV101*1),2)*BS101),2)*AT101)/100),2)) -> 31.95 | CZ101: =(ROUND((((S101+ROUND((ROUND((((EU101*1.2))*AV101*1),2)*BS101),2))*AU101)/100),2)+ROUND(((ROUND((ROUND(((AE101-((EU101*1.2)))*AV101*1),2)*BS101),2)*AU101)/100),2)) -> 17.82 | DB101: 43 | DD101: *1 | DE101: *1,2 | DF101: *1,2 | DG101: *1,2 | DI101: *1,2 | DJ101: *1,2 | DN101: 0 | DO101: 0 | DP101: 1 | DQ101: 1 | DU101: 1013 | DV101: 1 ШТ. | DW101: 1 ШТ. | DX101: 1 | EE101: 55393701 | EF101: 40 | EG101: Монтаж оборудования | EH101: 0 | EJ101: 2 | EK101: 69 | EL101: ТСН-2001.4-10. Монтаж радиотелевизионного и электронного оборудования | EM101: ТСН-2001.4-10-2 | EO101: Поправка: Гл.12.Прил.8.п.8. 3_12.00.01.11.001 | EQ101: 0 | ER101: 25.96 | ES101: 0.18 | ET101: 0 | EU101: 0 | EV101: 25.78 | EW101: 1.9 | EX101: 0 | EY101: 0 | FQ101: 0 | FR101: 0 | FS101: 0 | FX101: 95 | FY101: 53 | GD101: 1 | GF101: 2109770002 | GG101: 2 | GH101: 1 | GI101: 2 | GJ101: 0 | GK101: 0 | GL101: =ROUND(IF(AND(BH101=3,BI101=3,FS101<>0),P101,0),2) -> 0 | GM101: =ROUND(O101+X101+Y101,2)+GX101 -> 83.58 | GN101: =IF(OR(BI101=0,BI101=1),GM101-GX101,0) -> 0 | GO101: =IF(BI101=2,GM101-GX101,0) -> 83.58 | GP101: =IF(BI101=4,GM101-GX101,0) -> 0 | GR101: 0 | GS101: 3 | GT101: 0 | GV101: =ROUND((GT101),6) -> 0 | GW101: 1 | GX101: =ROUND(HC101*I101,2) -> 0 | HA101: 0 | HB101: 0 | HC101: =GV101*GW101 -> 0 | HS101: 0 | IK101: 0
A102: 17 | B102: 1 | C102: =ROW(SmtRes!A98) -> 98 | D102: =ROW(EtalonRes!A112) -> 112 | E102: 18 | F102: 4.10-136-3 | G102: Монтаж антенного ТВ усилителя на мачте (без измерений) без повала мачты | H102: 1 ШТ. | I102: 1 | J102: 0 | K102: 1 | O102: =ROUND(CP102,2) -> 1896.06 | P102: =ROUND((ROUND((AC102*AW102*I102),2)*BC102),2) -> 1.01 | Q102: =(ROUND((ROUND((((ET102*1.2))*AV102*I102),2)*BB102),2)+ROUND((ROUND(((AE102-((EU102*1.2)))*AV102*I102),2)*BS102),2)) -> 0 | R102: =(ROUND((ROUND((((EU102*1.2))*AV102*I102),2)*BS102),2)+ROUND((ROUND(((AE102-((EU102*1.2)))*AV102*I102),2)*BS102),2)) -> 0 | S102: =ROUND((ROUND((AF102*AV102*I102),2)*BA102),2) -> 1895.05 | T102: =ROUND(CU102*I102,2) -> 0 | U102: =CV102*I102 -> 2.47836 | V102: =CW102*I102 -> 0 | W102: =ROUND(CX102*I102,2) -> 0 | X102: =(ROUND((((S102+ROUND((ROUND((((EU102*1.2))*AV102*I102),2)*BS102),2))*AT102)/100),2)+ROUND(((ROUND((ROUND(((AE102-((EU102*1.2)))*AV102*I102),2)*BS102),2)*AT102)/100),2)) -> 1800.3 | Y102: =(ROUND((((S102+ROUND((ROUND((((EU102*1.2))*AV102*I102),2)*BS102),2))*AU102)/100),2)+ROUND(((ROUND((ROUND(((AE102-((EU102*1.2)))*AV102*I102),2)*BS102),2)*AU102)/100),2)) -> 1004.38 | AA102: 55919549 | AB102: =ROUND((AC102+AD102+AF102),6) -> 31.116 | AC102: =ROUND(((ES102*1)),6) -> 0.18 | AD102: =ROUND(((((ET102*1.2))-((EU102*1.2)))+AE102),6) -> 0 | AE102: =ROUND(((EU102*1.2)),6) -> 0 | AF102: =ROUND(((EV102*1.2)),6) -> 30.936 | AG102: =ROUND((AP102),6) -> 0 | AH102: =((EW102*1.2)) -> 2.28 | AI102: =((EX102*1.2)) -> 0 | AJ102: =(AS102) -> 0 | AK102: 25.96 | AL102: 0.18 | AM102: 0 | AN102: 0 | AO102: 25.78 | AP102: 0 | AQ102: 1.9 | AR102: 0 | AS102: 0 | AT102: 95 | AU102: 53 | AV102: 1.087 | AW102: 1 | AZ102: 1 | BA102: 56.35 | BB102: 1 | BC102: 5.61 | BH102: 0 | BI102: 2 | BJ102: ТСН-2001.4 Доп. 81, Сб. 10, т. 136, поз. 3 | BM102: 69 | BN102: 0 | BO102: 4.10-136-3 | BP102: 1 | BQ102: 40 | BR102: 0 | BS102: 56.35 | BT102: 1 | BU102: 1 | BV102: 1 | BW102: 1 | BX102: 1 | BZ102: 95 | CA102: 53 | CE102: 1566 | CF102: 0 | CG102: 0 | CM102: 0 | CN102: Поправка: Гл.12.Прил.8.п.8. 3_12.00.01.11.001 Наименование: При наличии напряженных и стесненных условий производства работ (стесненность, сложность складирования и транспортной логистики и т.п.) для объектов, расположенных в пределах круговой магистральной системы улиц "Садовое кольцо" города Москвы | CO102: 0 | CP102: =(P102+Q102+S102) -> 1896.06 | CQ102: =ROUND((ROUND((AC102*AW102*1),2)*BC102),2) -> 1.01 | CR102: =(ROUND((ROUND((((ET102*1.2))*AV102*1),2)*BB102),2)+ROUND((ROUND(((AE102-((EU102*1.2)))*AV102*1),2)*BS102),2)) -> 0 | CS102: =(ROUND((ROUND((((EU102*1.2))*AV102*1),2)*BS102),2)+ROUND((ROUND(((AE102-((EU102*1.2)))*AV102*1),2)*BS102),2)) -> 0 | CT102: =ROUND((ROUND((AF102*AV102*1),2)*BA102),2) -> 1895.05 | CU102: =AG102 -> 0 | CV102: =(AH102*AV102) -> 2.47836 | CW102: =AI102 -> 0 | CX102: =AJ102 -> 0 | CY102: =(ROUND((((S102+ROUND((ROUND((((EU102*1.2))*AV102*1),2)*BS102),2))*AT102)/100),2)+ROUND(((ROUND((ROUND(((AE102-((EU102*1.2)))*AV102*1),2)*BS102),2)*AT102)/100),2)) -> 1800.3 | CZ102: =(ROUND((((S102+ROUND((ROUND((((EU102*1.2))*AV102*1),2)*BS102),2))*AU102)/100),2)+ROUND(((ROUND((ROUND(((AE102-((EU102*1.2)))*AV102*1),2)*BS102),2)*AU102)/100),2)) -> 1004.38 | DB102: 44 | DD102: *1 | DE102: *1,2 | DF102: *1,2 | DG102: *1,2 | DI102: *1,2 | DJ102: *1,2 | DN102: 0 | DO102: 0 | DP102: 1 | DQ102: 1 | DU102: 1013 | DV102: 1 ШТ. | DW102: 1 ШТ. | DX102: 1 | EE102: 55393701 | EF102: 40 | EG102: Монтаж оборудования | EH102: 0 | EJ102: 2 | EK102: 69 | EL102: ТСН-2001.4-10. Монтаж радиотелевизионного и электронного оборудования | EM102: ТСН-2001.4-10-2 | EO102: Поправка: Гл.12.Прил.8.п.8. 3_12.00.01.11.001 | EQ102: 0 | ER102: 25.96 | ES102: 0.18 | ET102: 0 | EU102: 0 | EV102: 25.78 | EW102: 1.9 | EX102: 0 | EY102: 0 | FQ102: 0 | FR102: 0 | FS102: 0 | FX102: 95 | FY102: 53 | GD102: 1 | GF102: 2109770002 | GG102: 2 | GH102: 1 | GI102: 2 | GJ102: 0 | GK102: 0 | GL102: =ROUND(IF(AND(BH102=3,BI102=3,FS102<>0),P102,0),2) -> 0 | GM102: =ROUND(O102+X102+Y102,2)+GX102 -> 4700.74 | GN102: =IF(OR(BI102=0,BI102=1),GM102-GX102,0) -> 0 | GO102: =IF(BI102=2,GM102-GX102,0) -> 4700.74 | GP102: =IF(BI102=4,GM102-GX102,0) -> 0 | GR102: 0 | GS102: 3 | GT102: 0 | GV102: =ROUND((GT102),6) -> 0 | GW102: 1 | GX102: =ROUND(HC102*I102,2) -> 0 | HA102: 0 | HB102: 0 | HC102: =GV102*GW102 -> 0 | HS102: 0 | IK102: 0
A103: 17 | B103: 1 | E103: 19 | F103: КА, п.4 | G103: Мачтовый усилитель ДМВ(DVB-T2) AB 011 | H103: ШТ | I103: 1 | J103: 0 | K103: 1 | O103: =ROUND(CP103,2) -> 120.7 | P103: =ROUND((ROUND((AC103*AW103*I103),2)*BC103),2) -> 120.7 | Q103: =(ROUND((ROUND(((ET103)*AV103*I103),2)*BB103),2)+ROUND((ROUND(((AE103-(EU103))*AV103*I103),2)*BS103),2)) -> 0 | R103: =(ROUND((ROUND(((EU103)*AV103*I103),2)*BS103),2)+ROUND((ROUND(((AE103-(EU103))*AV103*I103),2)*BS103),2)) -> 0 | S103: =ROUND((ROUND((AF103*AV103*I103),2)*BA103),2) -> 0 | T103: =ROUND(CU103*I103,2) -> 0 | U103: =CV103*I103 -> 0 | V103: =CW103*I103 -> 0 | W103: =ROUND(CX103*I103,2) -> 0 | X103: =(ROUND((((S103+ROUND((ROUND(((EU103)*AV103*I103),2)*BS103),2))*AT103)/100),2)+ROUND(((ROUND((ROUND(((AE103-(EU103))*AV103*I103),2)*BS103),2)*AT103)/100),2)) -> 0 | Y103: =(ROUND((((S103+ROUND((ROUND(((EU103)*AV103*I103),2)*BS103),2))*AU103)/100),2)+ROUND(((ROUND((ROUND(((AE103-(EU103))*AV103*I103),2)*BS103),2)*AU103)/100),2)) -> 0 | AA103: 55919547 | AB103: =ROUND((AC103+AD103+AF103),6) -> 120.7 | AC103: =ROUND((ES103),6) -> 120.7 | AD103: =ROUND((((ET103)-(EU103))+AE103),6) -> 0 | AE103: =ROUND((EU103),6) -> 0 | AF103: =ROUND((EV103),6) -> 0 | AG103: =ROUND((AP103),6) -> 0 | AH103: =(EW103) -> 0 | AI103: =(EX103) -> 0 | AJ103: =(AS103) -> 0 | AK103: 120.7 | AL103: 120.7 | AM103: 0 | AN103: 0 | AO103: 0 | AP103: 0 | AQ103: 0 | AR103: 0 | AS103: 0 | AT103: 0 | AU103: 0 | AV103: 1 | AW103: 1 | AZ103: 1 | BA103: 1 | BB103: 1 | BC103: 1 | BH103: 3 | BI103: 3 | BJ103: КА, п.4 | BM103: 400007 | BN103: 0 | BP103: 0 | BQ103: 214 | BR103: 0 | BS103: 1 | BT103: 1 | BU103: 1 | BV103: 1 | BW103: 1 | BX103: 1 | BZ103: 0 | CA103: 0 | CE103: 1566 | CF103: 0 | CG103: 0 | CM103: 0 | CO103: 0 | CP103: =(P103+Q103+S103) -> 120.7 | CQ103: =ROUND((ROUND((AC103*AW103*1),2)*BC103),2) -> 120.7 | CR103: =(ROUND((ROUND(((ET103)*AV103*1),2)*BB103),2)+ROUND((ROUND(((AE103-(EU103))*AV103*1),2)*BS103),2)) -> 0 | CS103: =(ROUND((ROUND(((EU103)*AV103*1),2)*BS103),2)+ROUND((ROUND(((AE103-(EU103))*AV103*1),2)*BS103),2)) -> 0 | CT103: =ROUND((ROUND((AF103*AV103*1),2)*BA103),2) -> 0 | CU103: =AG103 -> 0 | CV103: =(AH103*AV103) -> 0 | CW103: =AI103 -> 0 | CX103: =AJ103 -> 0 | CY103: =(ROUND((((S103+ROUND((ROUND(((EU103)*AV103*1),2)*BS103),2))*AT103)/100),2)+ROUND(((ROUND((ROUND(((AE103-(EU103))*AV103*1),2)*BS103),2)*AT103)/100),2)) -> 0 | CZ103: =(ROUND((((S103+ROUND((ROUND(((EU103)*AV103*1),2)*BS103),2))*AU103)/100),2)+ROUND(((ROUND((ROUND(((AE103-(EU103))*AV103*1),2)*BS103),2)*AU103)/100),2)) -> 0 | DN103: 0 | DO103: 0 | DP103: 1 | DQ103: 1 | DU103: 1013 | DV103: ШТ | DW103: ШТ | DX103: 1 | EE103: 55393630 | EF103: 214 | EG103: Оборудование, отсутствующие в СНБ | EH103: 0 | EJ103: 3 | EK103: 400007 | EL103: Оборудование, отсутствующие в СНБ | EM103: Оборуд. КА | EQ103: 16 | ER103: 0 | ES103: 120.7 | ET103: 0 | EU103: 0 | EV103: 0 | EW103: 0 | EX103: 0 | EY103: 0 | FQ103: 0 | FR103: =P103 -> 120.7 | FS103: 0 | FX103: 0 | FY103: 0 | GA103: [1 390 / 1,22 / 9,84] + 1,2% Трансп + 3% Заг.скл | GD103: 1 | GF103: -1294044009 | GG103: 2 | GH103: 4 | GI103: -2 | GJ103: 0 | GK103: 0 | GL103: =ROUND(IF(AND(BH103=3,BI103=3,FS103<>0),P103,0),2) -> 0 | GM103: =ROUND(O103+X103+Y103,2)+GX103 -> 120.7 | GN103: =IF(OR(BI103=0,BI103=1),GM103-GX103,0) -> 0 | GO103: =IF(BI103=2,GM103-GX103,0) -> 0 | GP103: =IF(BI103=4,GM103-GX103,0) -> 0 | GR103: 1 | GS103: 2 | GT103: 0 | GV103: =ROUND((GT103),6) -> 0 | GW103: 1 | GX103: =ROUND(HC103*I103,2) -> 0 | HA103: 0 | HB103: 0 | HC103: =GV103*GW103 -> 0 | HE103: 1,2 | HF103: 3 | HS103: 0 | IK103: 0
