Workbook

Sheet 02-01-21
A1: =Source!B1 -> Smeta.RU (495) 974-1589
J2: Форма № 4б
A3: =Source!G4 -> Капитальный ремонт здания Государственного бюджетного общеобразовательного учреждения города Москвы «Школа №1574», расположенного по адресу: г. Москва, Старопименовский переулок, д. 5. 1 этап | AP3: Капитальный ремонт здания Государственного бюджетного общеобразовательного учреждения города Москвы «Школа №1574», расположенного по адресу: г. Москва, пер. Старопименовский, д. 5. Спринклерное пожаротушение
A4: (наименование стройки и/или объекта)
A6: =CONCATENATE( "ЛОКАЛЬНАЯ СМЕТА № ",IF(Source!F20<>"Новая локальная смета", Source!F20, "")) -> ЛОКАЛЬНАЯ СМЕТА № 02-01-21
A8: =IF(Source!G20<>"Новая локальная смета", Source!G20, "") -> Спринклерное пожаротушение.
A9: (наименование работ и затрат)
A11: =CONCATENATE( "Основание: чертежи № ", Source!J20) -> Основание: чертежи № 2024-00375-01-0-ИОС3.
I13: В базисном уровне цен | J13: В текущем уровне цен
E14: Сметная стоимость | I14: =I15+I16+I17+I18 -> 904.56 | J14: =J15+J16+J17+J18 -> 19336.73 | K14: тыс.руб.
E15: Строительные работы | I15: =ROUND((Source!F303)/1000, 2) -> 30.02 | J15: =ROUND((Source!P303)/1000, 2) -> 993.63 | K15: тыс.руб.
E16: Работы по монтажу оборудования | I16: =ROUND((Source!F304)/1000, 2) -> 636.59 | J16: =ROUND((Source!P304)/1000, 2) -> 16451.1 | K16: тыс.руб.
E17: Оборудование | I17: =ROUND((Source!F295)/1000, 2) -> 237.95 | J17: =ROUND((Source!P295)/1000, 2) -> 1892 | K17: тыс.руб.
E18: Прочие работы и затраты | I18: =ROUND((Source!F305+Source!F306)/1000, 2) -> 0 | J18: =ROUND((Source!P305+Source!P306)/1000, 2) -> 0 | K18: тыс.руб.
E19: Средства на оплату труда | I19: =(Source!F301+ Source!F300)/1000 -> 97.7491 | J19: =((Source!P301 + Source!P300)/1000) -> 5508.1618 | K19: тыс.руб.
E20: Затраты труда | I20: =Source!F308 -> 7442.2286 | K20: чел.-ч.
E21: Кроме того:
E22: Возврат материалов | I22: =SUM(Y28:Y586)/1000 -> 0 | J22: =SUM(Z28:Z586)/1000 -> 0 | K22: тыс.руб.
A24: Составлен(а) по ТСН-2001 с учетом Дополнения №: 81
A25: № и период сборника коэффициентов (индексов) пересчета: Коэффициенты к ТСН-2001 МГЭ Дополнение 81, ремонт №219/81 I квартал 2026 года и Коэффициенты к ТСН-2001.13-2 Дополнение 47 №64/47 I квартал 2026 года | AP25: № и период сборника коэффициентов (индексов) пересчета: Коэффициенты к ТСН-2001 МГЭ Дополнение 81, ремонт №219/81 I квартал 2026 года и Коэффициенты к ТСН-2001.13-2 Дополнение 47 №64/47 I квартал 2026 года
A26: № п/п | B26: Шифр расценки и коды ресурсов | C26: Наименование работ и затрат | D26: Ед. изм. | E26: Кол-во единиц | F26: Цена на ед. изм., руб. | G26: Попра- вочные коэффи- циенты | H26: Коэффи- циенты зимних удорожа- ний | I26: Всего в ценах на январь 2000 года, руб. | J26: Коэффи- циенты (индек- сы) пере- счета, нормы НР и СП | K26: ВСЕГО затрат в текущем уровне цен, руб.
A27: 1 | B27: 2 | C27: 3 | D27: 4 | E27: 5 | F27: 6 | G27: 7 | H27: 8 | I27: 9 | J27: 10 | K27: 11 | L27: цена за ед с ндс
A29: =CONCATENATE("Раздел: ",IF(Source!G24<>"Новый раздел", Source!G24, "")) -> Раздел: Насосная установка.
A30: 1 | B30: =Source!F28 -> 4.7-21-3 | C30: Монтаж насосного агрегата лопастного центробежного одноступенчатого, многоступенчатого объемного, вихревого, поршневого, приводного, роторного на общей фундаментной плите или моноблочный массой 0,425 т | D30: =Source!H28 -> 1 ШТ. | E30: =Source!I28 -> 2 | Q30: =Source!X28 -> 694.1 | R30: =Source!X29 -> 39112.67 | S30: =Source!Y28 -> 358.49 | T30: =Source!Y29 -> 20201.05 | U30: =ROUND((175/100)*ROUND(Source!R28, 2), 2) -> 9.75 | V30: =ROUND((0/100)*ROUND(Source!R29, 2), 2) -> 0 | AC30: 0
C31: ЗП | F31: =Source!AO28 -> 394.24 | G31: 0,75*1,2 | H31: =Source!AV29 -> 1.067 | I31: =Source!S28 -> 757.18 | J31: =IF(Source!BA29<> 0, Source!BA29, 1) -> 56.35 | K31: =Source!S29 -> 42667.09
C32: ЭМ | F32: =Source!AM28 -> 42.08 | G32: 0,75*1,2 | H32: =Source!AV29 -> 1.067 | I32: =Source!Q28 -> 80.82 | J32: =IF(Source!BB29<> 0, Source!BB29, 1) -> 14.74 | K32: =Source!Q29 -> 1191.29
C33: в т.ч. ЗПМ | F33: =Source!AN28 -> 2.9 | G33: 0,75*1,2 | H33: =Source!AV29 -> 1.067 | I33: =Source!R28 -> 5.57 | J33: =IF(Source!BS29<> 0, Source!BS29, 1) -> 56.35 | K33: =Source!R29 -> 313.87
C34: МР | F34: =Source!AL28 -> 45.53 | G34: 0,75 | H34: =Source!AW29 -> 1.028 | I34: =Source!P28 -> 70.21 | J34: =IF(Source!BC29<> 0, Source!BC29, 1) -> 11.98 | K34: =Source!P29 -> 841.12
C35: НР от ФОТ | D35: % | E35: =Source!BZ29 -> 91 | I35: =SUM(Q30:Q34) -> 694.1 | J35: =Source!AT29 -> 91 | K35: =SUM(R30:R34) -> 39112.67
C36: СП от ФОТ | D36: % | E36: =Source!CA29 -> 47 | I36: =SUM(S30:S35) -> 358.49 | J36: =Source!AU29 -> 47 | K36: =SUM(T30:T35) -> 20201.05
C37: ЗТР | D37: чел-ч | E37: =Source!AQ28 -> 32 | G37: 0,75*1,2 | H37: =Source!AV29 -> 1.067 | I37: =Source!U28 -> 61.4592
C38: ВСЕГО работ по позиции: | H38: =I31+I32+I34+I35+I36+0-0-0 -> 1960.8 | J38: =K31+K32+K34+K35+K36+0-0-0 -> 104013.22
C39: ВСЕГО оборудование по позиции: | H39: =0+0 -> 0 | J39: =0+0 -> 0
C40: ВСЕГО по позиции: | H40: =I31+I32+I34+I35+I36+0 -> 1960.8 | J40: =K31+K32+K34+K35+K36+0 -> 104013.22 | O40: =I31+I32+I34+I35+I36+0 -> 1960.8 | P40: =K31+K32+K34+K35+K36+0 -> 104013.22
A42: 2 | B42: =Source!F30 -> 4.7-21-1 | C42: Монтаж насосного агрегата лопастного центробежного одноступенчатого, многоступенчатого объемного, вихревого, поршневого, приводного, роторного на общей фундаментной плите или моноблочный массой 0,064 т | D42: =Source!H30 -> 1 ШТ. | E42: =Source!I30 -> 1 | Q42: =Source!X30 -> 399.52 | R42: =Source!X31 -> 22512.8 | S42: =Source!Y30 -> 206.34 | T42: =Source!Y31 -> 11627.49 | U42: =ROUND((175/100)*ROUND(Source!R30, 2), 2) -> 0.86 | V42: =ROUND((0/100)*ROUND(Source!R31, 2), 2) -> 0 | AC42: 0
C43: ЗП | F43: =Source!AO30 -> 342.5 | G43: 1,2 | H43: =Source!AV31 -> 1.067 | I43: =Source!S30 -> 438.54 | J43: =IF(Source!BA31<> 0, Source!BA31, 1) -> 56.35 | K43: =Source!S31 -> 24711.73
C44: ЭМ | F44: =Source!AM30 -> 24.5 | G44: 1,2 | H44: =Source!AV31 -> 1.067 | I44: =Source!Q30 -> 31.37 | J44: =IF(Source!BB31<> 0, Source!BB31, 1) -> 13.34 | K44: =Source!Q31 -> 418.48
C45: в т.ч. ЗПМ | F45: =Source!AN30 -> 0.38 | G45: 1,2 | H45: =Source!AV31 -> 1.067 | I45: =Source!R30 -> 0.49 | J45: =IF(Source!BS31<> 0, Source!BS31, 1) -> 56.35 | K45: =Source!R31 -> 27.61
C46: МР | F46: =Source!AL30 -> 42.34 | H46: =Source!AW31 -> 1.028 | I46: =Source!P30 -> 43.53 | J46: =IF(Source!BC31<> 0, Source!BC31, 1) -> 11.66 | K46: =Source!P31 -> 507.56
C47: НР от ФОТ | D47: % | E47: =Source!BZ31 -> 91 | I47: =SUM(Q42:Q46) -> 399.52 | J47: =Source!AT31 -> 91 | K47: =SUM(R42:R46) -> 22512.8
C48: СП от ФОТ | D48: % | E48: =Source!CA31 -> 47 | I48: =SUM(S42:S47) -> 206.34 | J48: =Source!AU31 -> 47 | K48: =SUM(T42:T47) -> 11627.49
C49: ЗТР | D49: чел-ч | E49: =Source!AQ30 -> 27.8 | G49: 1,2 | H49: =Source!AV31 -> 1.067 | I49: =Source!U30 -> 35.59512
C50: ВСЕГО работ по позиции: | H50: =I43+I44+I46+I47+I48+0-0-0 -> 1119.3 | J50: =K43+K44+K46+K47+K48+0-0-0 -> 59778.06
C51: ВСЕГО оборудование по позиции: | H51: =0+0 -> 0 | J51: =0+0 -> 0
C52: ВСЕГО по позиции: | H52: =I43+I44+I46+I47+I48+0 -> 1119.3 | J52: =K43+K44+K46+K47+K48+0 -> 59778.06 | O52: =I43+I44+I46+I47+I48+0 -> 1119.3 | P52: =K43+K44+K46+K47+K48+0 -> 59778.06
A54: 3 | B54: =Source!F32 -> 4.6-48-4 | C54: Бак внутренней установки без давления цилиндрический вертикальный, вместимость 1,0 м3 (60 л.) | D54: =Source!H32 -> 1 Т | E54: =Source!I32 -> 0.009 | Q54: =Source!X32 -> 66.75 | R54: =Source!X33 -> 3761.36 | S54: =Source!Y32 -> 33.75 | T54: =Source!Y33 -> 1901.81 | U54: =ROUND((175/100)*ROUND(Source!R32, 2), 2) -> 18.6 | V54: =ROUND((0/100)*ROUND(Source!R33, 2), 2) -> 0 | AC54: 0
C55: ЗП | F55: =Source!AO32 -> 5585.89 | G55: 1,2 | H55: =Source!AV33 -> 1.067 | I55: =Source!S32 -> 64.37 | J55: =IF(Source!BA33<> 0, Source!BA33, 1) -> 56.35 | K55: =Source!S33 -> 3627.25
C56: ЭМ | F56: =Source!AM32 -> 3066.32 | G56: 1,2 | H56: =Source!AV33 -> 1.067 | I56: =Source!Q32 -> 35.34 | J56: =IF(Source!BB33<> 0, Source!BB33, 1) -> 24.62 | K56: =Source!Q33 -> 870.07
C57: в т.ч. ЗПМ | F57: =Source!AN32 -> 922.56 | G57: 1,2 | H57: =Source!AV33 -> 1.067 | I57: =Source!R32 -> 10.63 | J57: =IF(Source!BS33<> 0, Source!BS33, 1) -> 56.35 | K57: =Source!R33 -> 599
C58: МР | F58: =Source!AL32 -> 133 | H58: =Source!AW33 -> 1.028 | I58: =Source!P32 -> 1.23 | J58: =IF(Source!BC33<> 0, Source!BC33, 1) -> 9.84 | K58: =Source!P33 -> 12.1
C59: НР от ФОТ | D59: % | E59: =Source!BZ33 -> 89 | I59: =SUM(Q54:Q58) -> 66.75 | J59: =Source!AT33 -> 89 | K59: =SUM(R54:R58) -> 3761.36
C60: СП от ФОТ | D60: % | E60: =Source!CA33 -> 45 | I60: =SUM(S54:S59) -> 33.75 | J60: =Source!AU33 -> 45 | K60: =SUM(T54:T59) -> 1901.81
C61: ЗТР | D61: чел-ч | E61: =Source!AQ32 -> 487 | G61: 1,2 | H61: =Source!AV33 -> 1.067 | I61: =Source!U32 -> 5.6119932
C62: ВСЕГО работ по позиции: | H62: =I55+I56+I58+I59+I60+0-0-0 -> 201.44 | J62: =K55+K56+K58+K59+K60+0-0-0 -> 10172.59
C63: ВСЕГО оборудование по позиции: | H63: =0+0 -> 0 | J63: =0+0 -> 0
C64: ВСЕГО по позиции: | H64: =I55+I56+I58+I59+I60+0 -> 201.44 | J64: =K55+K56+K58+K59+K60+0 -> 10172.59 | O64: =I55+I56+I58+I59+I60+0 -> 201.44 | P64: =K55+K56+K58+K59+K60+0 -> 10172.59
A66: 4 | B66: =Source!F36 -> 4.8-240-4 | C66: Монтаж пультов и шкафов управления, шкафа (пульта) управления навесного, высотой, шириной, глубиной до 600х600х350 мм | D66: =Source!H36 -> 1 ШТ. | E66: =Source!I36 -> 1 | Q66: =Source!X36 -> 36.46 | R66: =Source!X37 -> 2054.65 | S66: =Source!Y36 -> 19.17 | T66: =Source!Y37 -> 1080.28 | U66: =ROUND((175/100)*ROUND(Source!R36, 2), 2) -> 6.95 | V66: =ROUND((0/100)*ROUND(Source!R37, 2), 2) -> 0 | AC66: 0
C67: ЗП | F67: =Source!AO36 -> 26.76 | G67: 1,2 | H67: =Source!AV37 -> 1.047 | I67: =Source!S36 -> 33.62 | J67: =IF(Source!BA37<> 0, Source!BA37, 1) -> 56.35 | K67: =Source!S37 -> 1894.49
C68: ЭМ | F68: =Source!AM36 -> 17.42 | G68: 1,2 | H68: =Source!AV37 -> 1.047 | I68: =Source!Q36 -> 21.89 | J68: =IF(Source!BB37<> 0, Source!BB37, 1) -> 19.89 | K68: =Source!Q37 -> 435.39
C69: в т.ч. ЗПМ | F69: =Source!AN36 -> 3.16 | G69: 1,2 | H69: =Source!AV37 -> 1.047 | I69: =Source!R36 -> 3.97 | J69: =IF(Source!BS37<> 0, Source!BS37, 1) -> 56.35 | K69: =Source!R37 -> 223.71
C70: МР | F70: =Source!AL36 -> 1.46 | H70: =Source!AW37 -> 1 | I70: =Source!P36 -> 1.46 | J70: =IF(Source!BC37<> 0, Source!BC37, 1) -> 11.05 | K70: =Source!P37 -> 16.13
C71: НР от ФОТ | D71: % | E71: =Source!BZ37 -> 97 | I71: =SUM(Q66:Q70) -> 36.46 | J71: =Source!AT37 -> 97 | K71: =SUM(R66:R70) -> 2054.65
C72: СП от ФОТ | D72: % | E72: =Source!CA37 -> 51 | I72: =SUM(S66:S71) -> 19.17 | J72: =Source!AU37 -> 51 | K72: =SUM(T66:T71) -> 1080.28
C73: ЗТР | D73: чел-ч | E73: =Source!AQ36 -> 2.06 | G73: 1,2 | H73: =Source!AV37 -> 1.047 | I73: =Source!U36 -> 2.588184
C74: ВСЕГО работ по позиции: | H74: =I67+I68+I70+I71+I72+0-0-0 -> 112.6 | J74: =K67+K68+K70+K71+K72+0-0-0 -> 5480.94
C75: ВСЕГО оборудование по позиции: | H75: =0+0 -> 0 | J75: =0+0 -> 0
C76: ВСЕГО по позиции: | H76: =I67+I68+I70+I71+I72+0 -> 112.6 | J76: =K67+K68+K70+K71+K72+0 -> 5480.94 | O76: =I67+I68+I70+I71+I72+0 -> 112.6 | P76: =K67+K68+K70+K71+K72+0 -> 5480.94
A78: 5 | B78: =Source!F38 -> 4.12-48-9 | C78: Монтаж арматуры фланцевой с ручным приводом или без привода на номинальное давление до 4 МПа, номинальный диаметр прохода 80 мм (обратный клапан, затвор поворотный) | D78: =Source!H38 -> 1 ШТ. | E78: =Source!I38 -> 6 | Q78: =Source!X38 -> 350.76 | R78: =Source!X39 -> 19765.15 | S78: =Source!Y38 -> 179.28 | T78: =Source!Y39 -> 10102.19 | U78: =ROUND((175/100)*ROUND(Source!R38, 2), 2) -> 3.36 | V78: =ROUND((0/100)*ROUND(Source!R39, 2), 2) -> 0 | AC78: 0
C79: ="Объем: "&Source!I38&"=2+"&"4" -> Объем: 6=2+4
C80: ЗП | F80: =Source!AO38 -> 50.48 | G80: 1,2 | H80: =Source!AV39 -> 1.067 | I80: =Source!S38 -> 387.81 | J80: =IF(Source!BA39<> 0, Source!BA39, 1) -> 56.35 | K80: =Source!S39 -> 21853.09
C81: ЭМ | F81: =Source!AM38 -> 1.66 | G81: 1,2 | H81: =Source!AV39 -> 1.067 | I81: =Source!Q38 -> 12.75 | J81: =IF(Source!BB39<> 0, Source!BB39, 1) -> 17.09 | K81: =Source!Q39 -> 217.9
C82: в т.ч. ЗПМ | F82: =Source!AN38 -> 0.25 | G82: 1,2 | H82: =Source!AV39 -> 1.067 | I82: =Source!R38 -> 1.92 | J82: =IF(Source!BS39<> 0, Source!BS39, 1) -> 56.35 | K82: =Source!R39 -> 108.19
C83: МР | F83: =Source!AL38 -> 2.77 | H83: =Source!AW39 -> 1.028 | I83: =Source!P38 -> 17.09 | J83: =IF(Source!BC39<> 0, Source!BC39, 1) -> 4.5 | K83: =Source!P39 -> 76.91
C84: НР от ФОТ | D84: % | E84: =Source!BZ39 -> 90 | I84: =SUM(Q78:Q83) -> 350.76 | J84: =Source!AT39 -> 90 | K84: =SUM(R78:R83) -> 19765.15
C85: СП от ФОТ | D85: % | E85: =Source!CA39 -> 46 | I85: =SUM(S78:S84) -> 179.28 | J85: =Source!AU39 -> 46 | K85: =SUM(T78:T84) -> 10102.19
C86: ЗТР | D86: чел-ч | E86: =Source!AQ38 -> 4 | G86: 1,2 | H86: =Source!AV39 -> 1.067 | I86: =Source!U38 -> 30.7296
C87: ВСЕГО работ по позиции: | H87: =I80+I81+I83+I84+I85+0-0-0 -> 947.69 | J87: =K80+K81+K83+K84+K85+0-0-0 -> 52015.24
C88: ВСЕГО оборудование по позиции: | H88: =0+0 -> 0 | J88: =0+0 -> 0
C89: ВСЕГО по позиции: | H89: =I80+I81+I83+I84+I85+0 -> 947.69 | J89: =K80+K81+K83+K84+K85+0 -> 52015.24 | O89: =I80+I81+I83+I84+I85+0 -> 947.69 | P89: =K80+K81+K83+K84+K85+0 -> 52015.24
A91: 6 | B91: =Source!F40 -> 4.12-48-11 | C91: Монтаж арматуры фланцевой с ручным приводом или без привода на номинальное давление до 4 МПа, номинальный диаметр прохода 125 мм (затвор поворотный разделительный) | D91: =Source!H40 -> 1 ШТ. | E91: =Source!I40 -> 2 | Q91: =Source!X40 -> 158.22 | R91: =Source!X41 -> 8915.7 | S91: =Source!Y40 -> 80.87 | T91: =Source!Y41 -> 4556.91 | U91: =ROUND((175/100)*ROUND(Source!R40, 2), 2) -> 2.24 | V91: =ROUND((0/100)*ROUND(Source!R41, 2), 2) -> 0 | AC91: 0
C92: ЗП | F92: =Source!AO40 -> 68.15 | G92: 1,2 | H92: =Source!AV41 -> 1.067 | I92: =Source!S40 -> 174.52 | J92: =IF(Source!BA41<> 0, Source!BA41, 1) -> 56.35 | K92: =Source!S41 -> 9834.2
C93: ЭМ | F93: =Source!AM40 -> 3.32 | G93: 1,2 | H93: =Source!AV41 -> 1.067 | I93: =Source!Q40 -> 8.5 | J93: =IF(Source!BB41<> 0, Source!BB41, 1) -> 17.09 | K93: =Source!Q41 -> 145.27
C94: в т.ч. ЗПМ | F94: =Source!AN40 -> 0.5 | G94: 1,2 | H94: =Source!AV41 -> 1.067 | I94: =Source!R40 -> 1.28 | J94: =IF(Source!BS41<> 0, Source!BS41, 1) -> 56.35 | K94: =Source!R41 -> 72.13
C95: МР | F95: =Source!AL40 -> 3.93 | H95: =Source!AW41 -> 1.028 | I95: =Source!P40 -> 8.08 | J95: =IF(Source!BC41<> 0, Source!BC41, 1) -> 4.49 | K95: =Source!P41 -> 36.28
C96: НР от ФОТ | D96: % | E96: =Source!BZ41 -> 90 | I96: =SUM(Q91:Q95) -> 158.22 | J96: =Source!AT41 -> 90 | K96: =SUM(R91:R95) -> 8915.7
C97: СП от ФОТ | D97: % | E97: =Source!CA41 -> 46 | I97: =SUM(S91:S96) -> 80.87 | J97: =Source!AU41 -> 46 | K97: =SUM(T91:T96) -> 4556.91
C98: ЗТР | D98: чел-ч | E98: =Source!AQ40 -> 5.4 | G98: 1,2 | H98: =Source!AV41 -> 1.067 | I98: =Source!U40 -> 13.82832
C99: ВСЕГО работ по позиции: | H99: =I92+I93+I95+I96+I97+0-0-0 -> 430.19 | J99: =K92+K93+K95+K96+K97+0-0-0 -> 23488.36
C100: ВСЕГО оборудование по позиции: | H100: =0+0 -> 0 | J100: =0+0 -> 0
C101: ВСЕГО по позиции: | H101: =I92+I93+I95+I96+I97+0 -> 430.19 | J101: =K92+K93+K95+K96+K97+0 -> 23488.36 | O101: =I92+I93+I95+I96+I97+0 -> 430.19 | P101: =K92+K93+K95+K96+K97+0 -> 23488.36
A103: 7 | B103: =Source!F42 -> 4.12-48-4 | C103: Монтаж арматуры фланцевой с ручным приводом или без привода на номинальное давление до 4 МПа, номинальный диаметр прохода 25 мм (обратный клапан, затвор поворотный для жокея) | D103: =Source!H42 -> 1 ШТ. | E103: =Source!I42 -> 3 | Q103: =Source!X42 -> 130.89 | R103: =Source!X43 -> 7375.48 | S103: =Source!Y42 -> 66.9 | T103: =Source!Y43 -> 3769.69 | U103: =ROUND((175/100)*ROUND(Source!R42, 2), 2) -> 0 | V103: =ROUND((0/100)*ROUND(Source!R43, 2), 2) -> 0 | AC103: 0
C104: ="Объем: "&Source!I42&"=1+"&"2" -> Объем: 3=1+2
C105: ЗП | F105: =Source!AO42 -> 37.86 | G105: 1,2 | H105: =Source!AV43 -> 1.067 | I105: =Source!S42 -> 145.43 | J105: =IF(Source!BA43<> 0, Source!BA43, 1) -> 56.35 | K105: =Source!S43 -> 8194.98
C106: МР | F106: =Source!AL42 -> 0.69 | H106: =Source!AW43 -> 1.028 | I106: =Source!P42 -> 2.13 | J106: =IF(Source!BC43<> 0, Source!BC43, 1) -> 4.52 | K106: =Source!P43 -> 9.63
C107: НР от ФОТ | D107: % | E107: =Source!BZ43 -> 90 | I107: =SUM(Q103:Q106) -> 130.89 | J107: =Source!AT43 -> 90 | K107: =SUM(R103:R106) -> 7375.48
C108: СП от ФОТ | D108: % | E108: =Source!CA43 -> 46 | I108: =SUM(S103:S107) -> 66.9 | J108: =Source!AU43 -> 46 | K108: =SUM(T103:T107) -> 3769.69
C109: ЗТР | D109: чел-ч | E109: =Source!AQ42 -> 3 | G109: 1,2 | H109: =Source!AV43 -> 1.067 | I109: =Source!U42 -> 11.5236
C110: ВСЕГО работ по позиции: | H110: =I105+I106+I107+I108+0-0-0 -> 345.35 | J110: =K105+K106+K107+K108+0-0-0 -> 19349.78
C111: ВСЕГО оборудование по позиции: | H111: =0+0 -> 0 | J111: =0+0 -> 0
C112: ВСЕГО по позиции: | H112: =I105+I106+I107+I108+0 -> 345.35 | J112: =K105+K106+K107+K108+0 -> 19349.78 | O112: =I105+I106+I107+I108+0 -> 345.35 | P112: =K105+K106+K107+K108+0 -> 19349.78
...

Sheet Source
A1: 0 | B1: Smeta.RU (495) 974-1589 | D1: _PS_ | F1: 0 | G1: 0 | H1: 0 | I1: Smeta.RU | K1: 1 | L1: 74600 | M1: 10 | N1: 12 | O1: 1 | P1: 0 | Q1: 1
A4: 8 | B4: 1 | C4: -1 | G4: Капитальный ремонт здания Государственного бюджетного общеобразовательного учреждения города Москвы «Школа №1574», расположенного по адресу: г. Москва, Старопименовский переулок, д. 5. 1 этап | EC4: 0
A12: 1 | B12: 361 | C12: 0 | D12: =ROW(A319) -> 319 | E12: 0 | F12: Новый объект | G12: Спринклерное пожаротушение | I12: 0 | K12: 0 | L12: 0 | M12: 4098 | O12: 0 | P12: 0 | Q12: 0 | R12: 0 | S12: 0 | T12: 1 | V12: 0 | BB12: 0 | BH12: Сметные нормы списания | BI12: Коды ОКП для ТСН-2001 МГЭ Дополнение 81 | BJ12: 1 | BK12: 1 | BL12: 0 | BM12: 0 | BN12: 1 | BO12: 0 | BP12: 6 | BQ12: 2 | BR12: 1 | BS12: 1 | BT12: 0 | BU12: 0 | BV12: 0 | BW12: 0 | BX12: 0 | BY12: ТСН-2001 (МГЭ) Доп 81 - Новое строительство | BZ12: Типовой расчет для ТСН-2001 МГЭ, Дополнение 81, строительство | CA12: Территориальные сметные нормативы для Москвы ТСН-2001 (МГЭ), дополнение 81 | CB12: Территориальные сметные нормативы для Москвы ТСН-2001 (МГЭ), дополнение 81 | CC12: Территориальные сметные нормативы для Москвы ТСН-2001 (МГЭ), дополнение 81 | CD12: Территориальные сметные нормативы для Москвы ТСН-2001 (МГЭ), дополнение 81 | CE12: Поправки для ТСН-2001 от 07.04.2026 г. доп.81 | CF12: 0 | CG12: 0 | CH12: 8200 | CK12: 81 | CQ12: Территориальные сметные нормативы для Москвы (ТСН-2001) | CR12: ТЕР | CS12: 41660 | CT12: 1 | CU12: 81 | CY12: 0 | EC12: 0
A15: 15 | B15: 1
A18: 52 | B18: =B319 -> 361 | C18: =C319 -> 1 | D18: =D319 -> 12 | E18: =E319 -> 0 | F18: =F319 -> Новый объект | G18: =G319 -> Спринклерное пожаротушение | O18: =O319 -> 770382.96 | P18: =P319 -> 651102.71 | Q18: =Q319 -> 25446.09 | R18: =R319 -> 3914.94 | S18: =S319 -> 93834.16 | T18: =T319 -> 0 | U18: =U319 -> 7442.2286 | V18: =V319 -> 0 | ... GX18: =GX319 -> 0
A20: 3 | B20: 1 | D20: =ROW(A286) -> 286 | F20: 02-01-21 | G20: Спринклерное пожаротушение. | I20: 0 | J20: 2024-00375-01-0-ИОС3. | K20: -1 | L20: 02-01-21 | S20: 0 | T20: 0 | V20: 2 | BX20: 0 | CF20: 0 | CG20: 0
A22: 52 | B22: =B286 -> 1 | C22: =C286 -> 3 | D22: =D286 -> 20 | E22: =E286 -> 0 | F22: =F286 -> 02-01-21 | G22: =G286 -> Спринклерное пожаротушение. | O22: =O286 -> 770382.96 | P22: =P286 -> 651102.71 | Q22: =Q286 -> 25446.09 | R22: =R286 -> 3914.94 | S22: =S286 -> 93834.16 | T22: =T286 -> 0 | U22: =U286 -> 7442.2286 | V22: =V286 -> 0 | ... GX22: =GX286 -> 0
A24: 4 | B24: 1 | D24: =ROW(A139) -> 139 | F24: Новый раздел | G24: Насосная установка. | I24: 0 | K24: 0 | S24: 0 | T24: 0 | V24: 2 | BX24: 0 | CJ24: 0
A26: 52 | B26: =B139 -> 1 | C26: =C139 -> 4 | D26: =D139 -> 24 | E26: =E139 -> 0 | F26: =F139 -> Новый раздел | G26: =G139 -> Насосная установка. | O26: =O139 -> 315114.06 | P26: =P139 -> 300967.81 | Q26: =Q139 -> 2307.81 | R26: =R139 -> 330.58 | S26: =S139 -> 11838.44 | T26: =T139 -> 0 | U26: =U139 -> 925.57626 | V26: =V139 -> 0 | ... GX26: =GX139 -> 0
A28: 17 | B28: 1 | C28: =ROW(SmtRes!A10) -> 10 | D28: =ROW(EtalonRes!A11) -> 11 | E28: 1 | F28: 4.7-21-3 | G28: Монтаж насосного агрегата лопастного центробежного одноступенчатого, многоступенчатого объемного, вихревого, поршневого, приводного, роторного на общей фундаментной плите или моноблочный массой 0,425 т | H28: 1 ШТ. | I28: 2 | J28: 0 | K28: 2 | O28: =ROUND(CP28,2) -> 908.21 | P28: =ROUND((ROUND((AC28*AW28*I28),2)*BC28),2) -> 70.21 | Q28: =(ROUND((ROUND(((((ET28*0.75)*1.2))*AV28*I28),2)*BB28),2)+ROUND((ROUND(((AE28-(((EU28*0.75)*1.2)))*AV28*I28),2)*BS28),2)) -> 80.82 | R28: =(ROUND((ROUND(((((EU28*0.75)*1.2))*AV28*I28),2)*BS28),2)+ROUND((ROUND(((AE28-(((EU28*0.75)*1.2)))*AV28*I28),2)*BS28),2)) -> 5.57 | S28: =ROUND((ROUND((AF28*AV28*I28),2)*BA28),2) -> 757.18 | T28: =ROUND(CU28*I28,2) -> 0 | U28: =CV28*I28 -> 61.4592 | V28: =CW28*I28 -> 0 | W28: =ROUND(CX28*I28,2) -> 0 | X28: =(ROUND((((S28+ROUND((ROUND(((((EU28*0.75)*1.2))*AV28*I28),2)*BS28),2))*AT28)/100),2)+ROUND(((ROUND((ROUND(((AE28-(((EU28*0.75)*1.2)))*AV28*I28),2)*BS28),2)*AT28)/100),2)) -> 694.1 | Y28: =(ROUND((((S28+ROUND((ROUND(((((EU28*0.75)*1.2))*AV28*I28),2)*BS28),2))*AU28)/100),2)+ROUND(((ROUND((ROUND(((AE28-(((EU28*0.75)*1.2)))*AV28*I28),2)*BS28),2)*AU28)/100),2)) -> 358.49 | AA28: 85739205 | AB28: =ROUND((AC28+AD28+AF28),6) -> 426.8355 | AC28: =ROUND((((ES28*0.75)*1)),6) -> 34.1475 | AD28: =ROUND((((((ET28*0.75)*1.2))-(((EU28*0.75)*1.2)))+AE28),6) -> 37.872 | AE28: =ROUND((((EU28*0.75)*1.2)),6) -> 2.61 | AF28: =ROUND((((EV28*0.75)*1.2)),6) -> 354.816 | AG28: =ROUND((AP28),6) -> 0 | AH28: =(((EW28*0.75)*1.2)) -> 28.8 | AI28: =(((EX28*0.75)*1.2)) -> 0 | AJ28: =(AS28) -> 0 | AK28: 481.85 | AL28: 45.53 | AM28: 42.08 | AN28: 2.9 | AO28: 394.24 | AP28: 0 | AQ28: 32 | AR28: 0 | AS28: 0 | AT28: 91 | AU28: 47 | AV28: 1.067 | AW28: 1.028 | AZ28: 1 | BA28: 1 | BB28: 1 | BC28: 1 | BH28: 0 | BI28: 2 | BJ28: ТСН-2001.4 Доп. 80, Сб. 7, т. 21, поз. 3 | BM28: 66 | BN28: 0 | BO28: 4.7-21-3 | BP28: 1 | BQ28: 40 | BR28: 0 | BS28: 1 | BT28: 1 | BU28: 1 | BV28: 1 | BW28: 1 | BX28: 1 | BZ28: 91 | CA28: 47 | CE28: 1566 | CF28: 0 | CG28: 0 | CM28: 0 | CN28: Поправка: Гл.4.Прил.2.2.п.2.2.17_04.00.01.24.001 Наименование: При разнице в массе оборудования более 10% к норме и расценке ближайшего по массе оборудования при коэффициенте изменения массы оборудования до 0,5 т Поправка: Гл.12.Прил.8.п.8. 3_12.00.01.11.001 Наименование: При наличии напряженных и стесненных условий производства работ (стесненность, сложность складирования и транспортной логистики и т.п.) для объектов, расположенных в пределах круговой магистральной системы улиц "Садовое кольцо" города Москвы | CO28: 0 | CP28: =(P28+Q28+S28) -> 908.21 | CQ28: =ROUND((ROUND((AC28*AW28*1),2)*BC28),2) -> 35.1 | CR28: =(ROUND((ROUND(((((ET28*0.75)*1.2))*AV28*1),2)*BB28),2)+ROUND((ROUND(((AE28-(((EU28*0.75)*1.2)))*AV28*1),2)*BS28),2)) -> 40.41 | CS28: =(ROUND((ROUND(((((EU28*0.75)*1.2))*AV28*1),2)*BS28),2)+ROUND((ROUND(((AE28-(((EU28*0.75)*1.2)))*AV28*1),2)*BS28),2)) -> 2.78 | CT28: =ROUND((ROUND((AF28*AV28*1),2)*BA28),2) -> 378.59 | CU28: =AG28 -> 0 | CV28: =(AH28*AV28) -> 30.7296 | CW28: =AI28 -> 0 | CX28: =AJ28 -> 0 | CY28: =(ROUND((((S28+ROUND((ROUND(((((EU28*0.75)*1.2))*AV28*1),2)*BS28),2))*AT28)/100),2)+ROUND(((ROUND((ROUND(((AE28-(((EU28*0.75)*1.2)))*AV28*1),2)*BS28),2)*AT28)/100),2)) -> 691.56 | CZ28: =(ROUND((((S28+ROUND((ROUND(((((EU28*0.75)*1.2))*AV28*1),2)*BS28),2))*AU28)/100),2)+ROUND(((ROUND((ROUND(((AE28-(((EU28*0.75)*1.2)))*AV28*1),2)*BS28),2)*AU28)/100),2)) -> 357.18 | DB28: 1 | DD28: *0,75)*1 | DE28: *0,75)*1,2 | DF28: *0,75)*1,2 | DG28: *0,75)*1,2 | DI28: *0,75)*1,2 | DJ28: *0,75)*1,2 | DN28: 0 | DO28: 0 | DP28: 1 | DQ28: 1 | DU28: 1013 | DV28: 1 ШТ. | DW28: 1 ШТ. | DX28: 1 | EE28: 85133415 | EF28: 40 | EG28: Монтаж оборудования | EH28: 0 | EJ28: 2 | EK28: 66 | EL28: ТСН-2001.4-7. Компрессорные машины, насосы, вентиляторы | EM28: ТСН-2001.4-7-1 | EO28: Поправка: Гл.4.Прил.2.2.п.2.2.17_04.00.01.24.001 Поправка: Гл.12.Прил.8.п.8. 3_12.00.01.11.001 | EQ28: 0 | ER28: 481.85 | ES28: 45.53 | ET28: 42.08 | EU28: 2.9 | EV28: 394.24 | EW28: 32 | EX28: 0 | EY28: 0 | FQ28: 0 | FR28: 0 | FS28: 2 | FX28: 91 | FY28: 47 | GD28: 1 | GF28: 2029985936 | GG28: 2 | GH28: 1 | GI28: 2 | GJ28: 0 | GK28: 0 | GL28: =ROUND(IF(AND(BH28=3,BI28=3,FS28<>0),P28,0),2) -> 0 | GM28: =ROUND(O28+X28+Y28,2)+GX28 -> 1960.8 | GN28: =IF(OR(BI28=0,BI28=1),GM28-GX28,0) -> 0 | GO28: =IF(BI28=2,GM28-GX28,0) -> 1960.8 | GP28: =IF(BI28=4,GM28-GX28,0) -> 0 | GR28: 0 | GS28: 3 | GT28: 0 | GV28: =ROUND((GT28),6) -> 0 | GW28: 1 | GX28: =ROUND(HC28*I28,2) -> 0 | HA28: 0 | HB28: 0 | HC28: =GV28*GW28 -> 0 | HS28: 0 | IK28: 0
A29: 17 | B29: 1 | C29: =ROW(SmtRes!A20) -> 20 | D29: =ROW(EtalonRes!A22) -> 22 | E29: 1 | F29: 4.7-21-3 | G29: Монтаж насосного агрегата лопастного центробежного одноступенчатого, многоступенчатого объемного, вихревого, поршневого, приводного, роторного на общей фундаментной плите или моноблочный массой 0,425 т | H29: 1 ШТ. | I29: 2 | J29: 0 | K29: 2 | O29: =ROUND(CP29,2) -> 44699.5 | P29: =ROUND((ROUND((AC29*AW29*I29),2)*BC29),2) -> 841.12 | Q29: =(ROUND((ROUND(((((ET29*0.75)*1.2))*AV29*I29),2)*BB29),2)+ROUND((ROUND(((AE29-(((EU29*0.75)*1.2)))*AV29*I29),2)*BS29),2)) -> 1191.29 | R29: =(ROUND((ROUND(((((EU29*0.75)*1.2))*AV29*I29),2)*BS29),2)+ROUND((ROUND(((AE29-(((EU29*0.75)*1.2)))*AV29*I29),2)*BS29),2)) -> 313.87 | S29: =ROUND((ROUND((AF29*AV29*I29),2)*BA29),2) -> 42667.09 | T29: =ROUND(CU29*I29,2) -> 0 | U29: =CV29*I29 -> 61.4592 | V29: =CW29*I29 -> 0 | W29: =ROUND(CX29*I29,2) -> 0 | X29: =(ROUND((((S29+ROUND((ROUND(((((EU29*0.75)*1.2))*AV29*I29),2)*BS29),2))*AT29)/100),2)+ROUND(((ROUND((ROUND(((AE29-(((EU29*0.75)*1.2)))*AV29*I29),2)*BS29),2)*AT29)/100),2)) -> 39112.67 | Y29: =(ROUND((((S29+ROUND((ROUND(((((EU29*0.75)*1.2))*AV29*I29),2)*BS29),2))*AU29)/100),2)+ROUND(((ROUND((ROUND(((AE29-(((EU29*0.75)*1.2)))*AV29*I29),2)*BS29),2)*AU29)/100),2)) -> 20201.05 | AA29: 85739207 | AB29: =ROUND((AC29+AD29+AF29),6) -> 426.8355 | AC29: =ROUND((((ES29*0.75)*1)),6) -> 34.1475 | AD29: =ROUND((((((ET29*0.75)*1.2))-(((EU29*0.75)*1.2)))+AE29),6) -> 37.872 | AE29: =ROUND((((EU29*0.75)*1.2)),6) -> 2.61 | AF29: =ROUND((((EV29*0.75)*1.2)),6) -> 354.816 | AG29: =ROUND((AP29),6) -> 0 | AH29: =(((EW29*0.75)*1.2)) -> 28.8 | AI29: =(((EX29*0.75)*1.2)) -> 0 | AJ29: =(AS29) -> 0 | AK29: 481.85 | AL29: 45.53 | AM29: 42.08 | AN29: 2.9 | AO29: 394.24 | AP29: 0 | AQ29: 32 | AR29: 0 | AS29: 0 | AT29: 91 | AU29: 47 | AV29: 1.067 | AW29: 1.028 | AZ29: 1 | BA29: 56.35 | BB29: 14.74 | BC29: 11.98 | BH29: 0 | BI29: 2 | BJ29: ТСН-2001.4 Доп. 80, Сб. 7, т. 21, поз. 3 | BM29: 66 | BN29: 0 | BO29: 4.7-21-3 | BP29: 1 | BQ29: 40 | BR29: 0 | BS29: 56.35 | BT29: 1 | BU29: 1 | BV29: 1 | BW29: 1 | BX29: 1 | BZ29: 91 | CA29: 47 | CE29: 1566 | CF29: 0 | CG29: 0 | CM29: 0 | CN29: Поправка: Гл.4.Прил.2.2.п.2.2.17_04.00.01.24.001 Наименование: При разнице в массе оборудования более 10% к норме и расценке ближайшего по массе оборудования при коэффициенте изменения массы оборудования до 0,5 т Поправка: Гл.12.Прил.8.п.8. 3_12.00.01.11.001 Наименование: При наличии напряженных и стесненных условий производства работ (стесненность, сложность складирования и транспортной логистики и т.п.) для объектов, расположенных в пределах круговой магистральной системы улиц "Садовое кольцо" города Москвы | CO29: 0 | CP29: =(P29+Q29+S29) -> 44699.5 | CQ29: =ROUND((ROUND((AC29*AW29*1),2)*BC29),2) -> 420.5 | CR29: =(ROUND((ROUND(((((ET29*0.75)*1.2))*AV29*1),2)*BB29),2)+ROUND((ROUND(((AE29-(((EU29*0.75)*1.2)))*AV29*1),2)*BS29),2)) -> 595.64 | CS29: =(ROUND((ROUND(((((EU29*0.75)*1.2))*AV29*1),2)*BS29),2)+ROUND((ROUND(((AE29-(((EU29*0.75)*1.2)))*AV29*1),2)*BS29),2)) -> 156.65 | CT29: =ROUND((ROUND((AF29*AV29*1),2)*BA29),2) -> 21333.55 | CU29: =AG29 -> 0 | CV29: =(AH29*AV29) -> 30.7296 | CW29: =AI29 -> 0 | CX29: =AJ29 -> 0 | CY29: =(ROUND((((S29+ROUND((ROUND(((((EU29*0.75)*1.2))*AV29*1),2)*BS29),2))*AT29)/100),2)+ROUND(((ROUND((ROUND(((AE29-(((EU29*0.75)*1.2)))*AV29*1),2)*BS29),2)*AT29)/100),2)) -> 38969.6 | CZ29: =(ROUND((((S29+ROUND((ROUND(((((EU29*0.75)*1.2))*AV29*1),2)*BS29),2))*AU29)/100),2)+ROUND(((ROUND((ROUND(((AE29-(((EU29*0.75)*1.2)))*AV29*1),2)*BS29),2)*AU29)/100),2)) -> 20127.16 | DB29: 3 | DD29: *0,75)*1 | DE29: *0,75)*1,2 | DF29: *0,75)*1,2 | DG29: *0,75)*1,2 | DI29: *0,75)*1,2 | DJ29: *0,75)*1,2 | DN29: 0 | DO29: 0 | DP29: 1 | DQ29: 1 | DU29: 1013 | DV29: 1 ШТ. | DW29: 1 ШТ. | DX29: 1 | EE29: 85133415 | EF29: 40 | EG29: Монтаж оборудования | EH29: 0 | EJ29: 2 | EK29: 66 | EL29: ТСН-2001.4-7. Компрессорные машины, насосы, вентиляторы | EM29: ТСН-2001.4-7-1 | EO29: Поправка: Гл.4.Прил.2.2.п.2.2.17_04.00.01.24.001 Поправка: Гл.12.Прил.8.п.8. 3_12.00.01.11.001 | EQ29: 0 | ER29: 481.85 | ES29: 45.53 | ET29: 42.08 | EU29: 2.9 | EV29: 394.24 | EW29: 32 | EX29: 0 | EY29: 0 | FQ29: 0 | FR29: 0 | FS29: 2 | FX29: 91 | FY29: 47 | GD29: 1 | GF29: 2029985936 | GG29: 2 | GH29: 1 | GI29: 2 | GJ29: 0 | GK29: 0 | GL29: =ROUND(IF(AND(BH29=3,BI29=3,FS29<>0),P29,0),2) -> 0 | GM29: =ROUND(O29+X29+Y29,2)+GX29 -> 104013.22 | GN29: =IF(OR(BI29=0,BI29=1),GM29-GX29,0) -> 0 | GO29: =IF(BI29=2,GM29-GX29,0) -> 104013.22 | GP29: =IF(BI29=4,GM29-GX29,0) -> 0 | GR29: 0 | GS29: 3 | GT29: 0 | GV29: =ROUND((GT29),6) -> 0 | GW29: 1 | GX29: =ROUND(HC29*I29,2) -> 0 | HA29: 0 | HB29: 0 | HC29: =GV29*GW29 -> 0 | HS29: 0 | IK29: 0
A30: 17 | B30: 1 | C30: =ROW(SmtRes!A30) -> 30 | D30: =ROW(EtalonRes!A33) -> 33 | E30: 2 | F30: 4.7-21-1 | G30: Монтаж насосного агрегата лопастного центробежного одноступенчатого, многоступенчатого объемного, вихревого, поршневого, приводного, роторного на общей фундаментной плите или моноблочный массой 0,064 т | H30: 1 ШТ. | I30: =ROUND(1,9) -> 1 | J30: 0 | K30: =ROUND(1,9) -> 1 | O30: =ROUND(CP30,2) -> 513.44 | P30: =ROUND((ROUND((AC30*AW30*I30),2)*BC30),2) -> 43.53 | Q30: =(ROUND((ROUND((((ET30*1.2))*AV30*I30),2)*BB30),2)+ROUND((ROUND(((AE30-((EU30*1.2)))*AV30*I30),2)*BS30),2)) -> 31.37 | R30: =(ROUND((ROUND((((EU30*1.2))*AV30*I30),2)*BS30),2)+ROUND((ROUND(((AE30-((EU30*1.2)))*AV30*I30),2)*BS30),2)) -> 0.49 | S30: =ROUND((ROUND((AF30*AV30*I30),2)*BA30),2) -> 438.54 | T30: =ROUND(CU30*I30,2) -> 0 | U30: =CV30*I30 -> 35.59512 | V30: =CW30*I30 -> 0 | W30: =ROUND(CX30*I30,2) -> 0 | X30: =(ROUND((((S30+ROUND((ROUND((((EU30*1.2))*AV30*I30),2)*BS30),2))*AT30)/100),2)+ROUND(((ROUND((ROUND(((AE30-((EU30*1.2)))*AV30*I30),2)*BS30),2)*AT30)/100),2)) -> 399.52 | Y30: =(ROUND((((S30+ROUND((ROUND((((EU30*1.2))*AV30*I30),2)*BS30),2))*AU30)/100),2)+ROUND(((ROUND((ROUND(((AE30-((EU30*1.2)))*AV30*I30),2)*BS30),2)*AU30)/100),2)) -> 206.34 | AA30: 85739205 | AB30: =ROUND((AC30+AD30+AF30),6) -> 482.74 | AC30: =ROUND(((ES30*1)),6) -> 42.34 | AD30: =ROUND(((((ET30*1.2))-((EU30*1.2)))+AE30),6) -> 29.4 | AE30: =ROUND(((EU30*1.2)),6) -> 0.456 | AF30: =ROUND(((EV30*1.2)),6) -> 411 | AG30: =ROUND((AP30),6) -> 0 | AH30: =((EW30*1.2)) -> 33.36 | AI30: =((EX30*1.2)) -> 0 | AJ30: =(AS30) -> 0 | AK30: 409.34 | AL30: 42.34 | AM30: 24.5 | AN30: 0.38 | AO30: 342.5 | AP30: 0 | AQ30: 27.8 | AR30: 0 | AS30: 0 | AT30: 91 | AU30: 47 | AV30: 1.067 | AW30: 1.028 | AZ30: 1 | BA30: 1 | BB30: 1 | BC30: 1 | BH30: 0 | BI30: 2 | BJ30: ТСН-2001.4 Доп. 80, Сб. 7, т. 21, поз. 1 | BM30: 66 | BN30: 0 | BO30: 4.7-21-1 | BP30: 1 | BQ30: 40 | BR30: 0 | BS30: 1 | BT30: 1 | BU30: 1 | BV30: 1 | BW30: 1 | BX30: 1 | BZ30: 91 | CA30: 47 | CE30: 1566 | CF30: 0 | CG30: 0 | CM30: 0 | CN30: Поправка: Гл.12.Прил.8.п.8. 3_12.00.01.11.001 Наименование: При наличии напряженных и стесненных условий производства работ (стесненность, сложность складирования и транспортной логистики и т.п.) для объектов, расположенных в пределах круговой магистральной системы улиц "Садовое кольцо" города Москвы | CO30: 0 | CP30: =(P30+Q30+S30) -> 513.44 | CQ30: =ROUND((ROUND((AC30*AW30*1),2)*BC30),2) -> 43.53 | CR30: =(ROUND((ROUND((((ET30*1.2))*AV30*1),2)*BB30),2)+ROUND((ROUND(((AE30-((EU30*1.2)))*AV30*1),2)*BS30),2)) -> 31.37 | CS30: =(ROUND((ROUND((((EU30*1.2))*AV30*1),2)*BS30),2)+ROUND((ROUND(((AE30-((EU30*1.2)))*AV30*1),2)*BS30),2)) -> 0.49 | CT30: =ROUND((ROUND((AF30*AV30*1),2)*BA30),2) -> 438.54 | CU30: =AG30 -> 0 | CV30: =(AH30*AV30) -> 35.59512 | CW30: =AI30 -> 0 | CX30: =AJ30 -> 0 | CY30: =(ROUND((((S30+ROUND((ROUND((((EU30*1.2))*AV30*1),2)*BS30),2))*AT30)/100),2)+ROUND(((ROUND((ROUND(((AE30-((EU30*1.2)))*AV30*1),2)*BS30),2)*AT30)/100),2)) -> 399.52 | CZ30: =(ROUND((((S30+ROUND((ROUND((((EU30*1.2))*AV30*1),2)*BS30),2))*AU30)/100),2)+ROUND(((ROUND((ROUND(((AE30-((EU30*1.2)))*AV30*1),2)*BS30),2)*AU30)/100),2)) -> 206.34 | DB30: 5 | DD30: *1 | DE30: *1,2 | DF30: *1,2 | DG30: *1,2 | DI30: *1,2 | DJ30: *1,2 | DN30: 0 | DO30: 0 | DP30: 1 | DQ30: 1 | DU30: 1013 | DV30: 1 ШТ. | DW30: 1 ШТ. | DX30: 1 | EE30: 85133415 | EF30: 40 | EG30: Монтаж оборудования | EH30: 0 | EJ30: 2 | EK30: 66 | EL30: ТСН-2001.4-7. Компрессорные машины, насосы, вентиляторы | EM30: ТСН-2001.4-7-1 | EO30: Поправка: Гл.12.Прил.8.п.8. 3_12.00.01.11.001 | EQ30: 0 | ER30: 409.34 | ES30: 42.34 | ET30: 24.5 | EU30: 0.38 | EV30: 342.5 | EW30: 27.8 | EX30: 0 | EY30: 0 | FQ30: 0 | FR30: 0 | FS30: 2 | FX30: 91 | FY30: 47 | GD30: 1 | GF30: -1722888311 | GG30: 2 | GH30: 1 | GI30: 2 | GJ30: 0 | GK30: 0 | GL30: =ROUND(IF(AND(BH30=3,BI30=3,FS30<>0),P30,0),2) -> 0 | GM30: =ROUND(O30+X30+Y30,2)+GX30 -> 1119.3 | GN30: =IF(OR(BI30=0,BI30=1),GM30-GX30,0) -> 0 | GO30: =IF(BI30=2,GM30-GX30,0) -> 1119.3 | GP30: =IF(BI30=4,GM30-GX30,0) -> 0 | GR30: 0 | GS30: 3 | GT30: 0 | GV30: =ROUND((GT30),6) -> 0 | GW30: 1 | GX30: =ROUND(HC30*I30,2) -> 0 | HA30: 0 | HB30: 0 | HC30: =GV30*GW30 -> 0 | HS30: 0 | IK30: 0
A31: 17 | B31: 1 | C31: =ROW(SmtRes!A40) -> 40 | D31: =ROW(EtalonRes!A44) -> 44 | E31: 2 | F31: 4.7-21-1 | G31: Монтаж насосного агрегата лопастного центробежного одноступенчатого, многоступенчатого объемного, вихревого, поршневого, приводного, роторного на общей фундаментной плите или моноблочный массой 0,064 т | H31: 1 ШТ. | I31: =ROUND(1,9) -> 1 | J31: 0 | K31: =ROUND(1,9) -> 1 | O31: =ROUND(CP31,2) -> 25637.77 | P31: =ROUND((ROUND((AC31*AW31*I31),2)*BC31),2) -> 507.56 | Q31: =(ROUND((ROUND((((ET31*1.2))*AV31*I31),2)*BB31),2)+ROUND((ROUND(((AE31-((EU31*1.2)))*AV31*I31),2)*BS31),2)) -> 418.48 | R31: =(ROUND((ROUND((((EU31*1.2))*AV31*I31),2)*BS31),2)+ROUND((ROUND(((AE31-((EU31*1.2)))*AV31*I31),2)*BS31),2)) -> 27.61 | S31: =ROUND((ROUND((AF31*AV31*I31),2)*BA31),2) -> 24711.73 | T31: =ROUND(CU31*I31,2) -> 0 | U31: =CV31*I31 -> 35.59512 | V31: =CW31*I31 -> 0 | W31: =ROUND(CX31*I31,2) -> 0 | X31: =(ROUND((((S31+ROUND((ROUND((((EU31*1.2))*AV31*I31),2)*BS31),2))*AT31)/100),2)+ROUND(((ROUND((ROUND(((AE31-((EU31*1.2)))*AV31*I31),2)*BS31),2)*AT31)/100),2)) -> 22512.8 | Y31: =(ROUND((((S31+ROUND((ROUND((((EU31*1.2))*AV31*I31),2)*BS31),2))*AU31)/100),2)+ROUND(((ROUND((ROUND(((AE31-((EU31*1.2)))*AV31*I31),2)*BS31),2)*AU31)/100),2)) -> 11627.49 | AA31: 85739207 | AB31: =ROUND((AC31+AD31+AF31),6) -> 482.74 | AC31: =ROUND(((ES31*1)),6) -> 42.34 | AD31: =ROUND(((((ET31*1.2))-((EU31*1.2)))+AE31),6) -> 29.4 | AE31: =ROUND(((EU31*1.2)),6) -> 0.456 | AF31: =ROUND(((EV31*1.2)),6) -> 411 | AG31: =ROUND((AP31),6) -> 0 | AH31: =((EW31*1.2)) -> 33.36 | AI31: =((EX31*1.2)) -> 0 | AJ31: =(AS31) -> 0 | AK31: 409.34 | AL31: 42.34 | AM31: 24.5 | AN31: 0.38 | AO31: 342.5 | AP31: 0 | AQ31: 27.8 | AR31: 0 | AS31: 0 | AT31: 91 | AU31: 47 | AV31: 1.067 | AW31: 1.028 | AZ31: 1 | BA31: 56.35 | BB31: 13.34 | BC31: 11.66 | BH31: 0 | BI31: 2 | BJ31: ТСН-2001.4 Доп. 80, Сб. 7, т. 21, поз. 1 | BM31: 66 | BN31: 0 | BO31: 4.7-21-1 | BP31: 1 | BQ31: 40 | BR31: 0 | BS31: 56.35 | BT31: 1 | BU31: 1 | BV31: 1 | BW31: 1 | BX31: 1 | BZ31: 91 | CA31: 47 | CE31: 1566 | CF31: 0 | CG31: 0 | CM31: 0 | CN31: Поправка: Гл.12.Прил.8.п.8. 3_12.00.01.11.001 Наименование: При наличии напряженных и стесненных условий производства работ (стесненность, сложность складирования и транспортной логистики и т.п.) для объектов, расположенных в пределах круговой магистральной системы улиц "Садовое кольцо" города Москвы | CO31: 0 | CP31: =(P31+Q31+S31) -> 25637.77 | CQ31: =ROUND((ROUND((AC31*AW31*1),2)*BC31),2) -> 507.56 | CR31: =(ROUND((ROUND((((ET31*1.2))*AV31*1),2)*BB31),2)+ROUND((ROUND(((AE31-((EU31*1.2)))*AV31*1),2)*BS31),2)) -> 418.48 | CS31: =(ROUND((ROUND((((EU31*1.2))*AV31*1),2)*BS31),2)+ROUND((ROUND(((AE31-((EU31*1.2)))*AV31*1),2)*BS31),2)) -> 27.61 | CT31: =ROUND((ROUND((AF31*AV31*1),2)*BA31),2) -> 24711.73 | CU31: =AG31 -> 0 | CV31: =(AH31*AV31) -> 35.59512 | CW31: =AI31 -> 0 | CX31: =AJ31 -> 0 | CY31: =(ROUND((((S31+ROUND((ROUND((((EU31*1.2))*AV31*1),2)*BS31),2))*AT31)/100),2)+ROUND(((ROUND((ROUND(((AE31-((EU31*1.2)))*AV31*1),2)*BS31),2)*AT31)/100),2)) -> 22512.8 | CZ31: =(ROUND((((S31+ROUND((ROUND((((EU31*1.2))*AV31*1),2)*BS31),2))*AU31)/100),2)+ROUND(((ROUND((ROUND(((AE31-((EU31*1.2)))*AV31*1),2)*BS31),2)*AU31)/100),2)) -> 11627.49 | DB31: 6 | DD31: *1 | DE31: *1,2 | DF31: *1,2 | DG31: *1,2 | DI31: *1,2 | DJ31: *1,2 | DN31: 0 | DO31: 0 | DP31: 1 | DQ31: 1 | DU31: 1013 | DV31: 1 ШТ. | DW31: 1 ШТ. | DX31: 1 | EE31: 85133415 | EF31: 40 | EG31: Монтаж оборудования | EH31: 0 | EJ31: 2 | EK31: 66 | EL31: ТСН-2001.4-7. Компрессорные машины, насосы, вентиляторы | EM31: ТСН-2001.4-7-1 | EO31: Поправка: Гл.12.Прил.8.п.8. 3_12.00.01.11.001 | EQ31: 0 | ER31: 409.34 | ES31: 42.34 | ET31: 24.5 | EU31: 0.38 | EV31: 342.5 | EW31: 27.8 | EX31: 0 | EY31: 0 | FQ31: 0 | FR31: 0 | FS31: 2 | FX31: 91 | FY31: 47 | GD31: 1 | GF31: -1722888311 | GG31: 2 | GH31: 1 | GI31: 2 | GJ31: 0 | GK31: 0 | GL31: =ROUND(IF(AND(BH31=3,BI31=3,FS31<>0),P31,0),2) -> 0 | GM31: =ROUND(O31+X31+Y31,2)+GX31 -> 59778.06 | GN31: =IF(OR(BI31=0,BI31=1),GM31-GX31,0) -> 0 | GO31: =IF(BI31=2,GM31-GX31,0) -> 59778.06 | GP31: =IF(BI31=4,GM31-GX31,0) -> 0 | GR31: 0 | GS31: 3 | GT31: 0 | GV31: =ROUND((GT31),6) -> 0 | GW31: 1 | GX31: =ROUND(HC31*I31,2) -> 0 | HA31: 0 | HB31: 0 | HC31: =GV31*GW31 -> 0 | HS31: 0 | IK31: 0
A32: 17 | B32: 1 | C32: =ROW(SmtRes!A41) -> 41 | D32: =ROW(EtalonRes!A45) -> 45 | E32: 3 | F32: 4.6-48-4 | G32: Бак внутренней установки без давления цилиндрический вертикальный, вместимость 1,0 м3 (60 л.) | H32: 1 Т | I32: 0.009 | J32: 0 | K32: 0.009 | O32: =ROUND(CP32,2) -> 100.94 | P32: =ROUND((ROUND((AC32*AW32*I32),2)*BC32),2) -> 1.23 | Q32: =(ROUND((ROUND((((ET32*1.2))*AV32*I32),2)*BB32),2)+ROUND((ROUND(((AE32-((EU32*1.2)))*AV32*I32),2)*BS32),2)) -> 35.34 | R32: =(ROUND((ROUND((((EU32*1.2))*AV32*I32),2)*BS32),2)+ROUND((ROUND(((AE32-((EU32*1.2)))*AV32*I32),2)*BS32),2)) -> 10.63 | S32: =ROUND((ROUND((AF32*AV32*I32),2)*BA32),2) -> 64.37 | T32: =ROUND(CU32*I32,2) -> 0 | U32: =CV32*I32 -> 5.6119932 | V32: =CW32*I32 -> 0 | W32: =ROUND(CX32*I32,2) -> 0 | X32: =(ROUND((((S32+ROUND((ROUND((((EU32*1.2))*AV32*I32),2)*BS32),2))*AT32)/100),2)+ROUND(((ROUND((ROUND(((AE32-((EU32*1.2)))*AV32*I32),2)*BS32),2)*AT32)/100),2)) -> 66.75 | Y32: =(ROUND((((S32+ROUND((ROUND((((EU32*1.2))*AV32*I32),2)*BS32),2))*AU32)/100),2)+ROUND(((ROUND((ROUND(((AE32-((EU32*1.2)))*AV32*I32),2)*BS32),2)*AU32)/100),2)) -> 33.75 | AA32: 85739205 | AB32: =ROUND((AC32+AD32+AF32),6) -> 10515.652 | AC32: =ROUND(((ES32*1)),6) -> 133 | AD32: =ROUND(((((ET32*1.2))-((EU32*1.2)))+AE32),6) -> 3679.584 | AE32: =ROUND(((EU32*1.2)),6) -> 1107.072 | AF32: =ROUND(((EV32*1.2)),6) -> 6703.068 | AG32: =ROUND((AP32),6) -> 0 | AH32: =((EW32*1.2)) -> 584.4 | AI32: =((EX32*1.2)) -> 0 | AJ32: =(AS32) -> 0 | AK32: 8785.21 | AL32: 133 | AM32: 3066.32 | AN32: 922.56 | AO32: 5585.89 | AP32: 0 | AQ32: 487 | AR32: 0 | AS32: 0 | AT32: 89 | AU32: 45 | AV32: 1.067 | AW32: 1.028 | AZ32: 1 | BA32: 1 | BB32: 1 | BC32: 1 | BH32: 0 | BI32: 2 | BJ32: ТСН-2001.4. Доп. 1-42. Сб. 6, т. 48, поз. 4 | BM32: 65 | BN32: 0 | BO32: 4.6-48-4 | BP32: 1 | BQ32: 40 | BR32: 0 | BS32: 1 | BT32: 1 | BU32: 1 | BV32: 1 | BW32: 1 | BX32: 1 | BZ32: 89 | CA32: 45 | CE32: 1566 | CF32: 0 | CG32: 0 | CM32: 0 | CN32: Поправка: Гл.12.Прил.8.п.8. 3_12.00.01.11.001 Наименование: При наличии напряженных и стесненных условий производства работ (стесненность, сложность складирования и транспортной логистики и т.п.) для объектов, расположенных в пределах круговой магистральной системы улиц "Садовое кольцо" города Москвы | CO32: 0 | CP32: =(P32+Q32+S32) -> 100.94 | CQ32: =ROUND((ROUND((AC32*AW32*1),2)*BC32),2) -> 136.72 | CR32: =(ROUND((ROUND((((ET32*1.2))*AV32*1),2)*BB32),2)+ROUND((ROUND(((AE32-((EU32*1.2)))*AV32*1),2)*BS32),2)) -> 3926.12 | CS32: =(ROUND((ROUND((((EU32*1.2))*AV32*1),2)*BS32),2)+ROUND((ROUND(((AE32-((EU32*1.2)))*AV32*1),2)*BS32),2)) -> 1181.25 | CT32: =ROUND((ROUND((AF32*AV32*1),2)*BA32),2) -> 7152.17 | CU32: =AG32 -> 0 | CV32: =(AH32*AV32) -> 623.5548 | CW32: =AI32 -> 0 | CX32: =AJ32 -> 0 | CY32: =(ROUND((((S32+ROUND((ROUND((((EU32*1.2))*AV32*1),2)*BS32),2))*AT32)/100),2)+ROUND(((ROUND((ROUND(((AE32-((EU32*1.2)))*AV32*1),2)*BS32),2)*AT32)/100),2)) -> 1108.6 | CZ32: =(ROUND((((S32+ROUND((ROUND((((EU32*1.2))*AV32*1),2)*BS32),2))*AU32)/100),2)+ROUND(((ROUND((ROUND(((AE32-((EU32*1.2)))*AV32*1),2)*BS32),2)*AU32)/100),2)) -> 560.53 | DB32: 7 | DD32: *1 | DE32: *1,2 | DF32: *1,2 | DG32: *1,2 | DI32: *1,2 | DJ32: *1,2 | DN32: 0 | DO32: 0 | DP32: 1 | DQ32: 1 | DU32: 1013 | DV32: 1 Т | DW32: 1 Т | DX32: 1 | EE32: 85133414 | EF32: 40 | EG32: Монтаж оборудования | EH32: 0 | EJ32: 2 | EK32: 65 | EL32: ТСН-2001.4-6. Теплосиловое оборудование | EM32: ТСН-2001.4-6-1 | EO32: Поправка: Гл.12.Прил.8.п.8. 3_12.00.01.11.001 | EQ32: 0 | ER32: 8785.21 | ES32: 133 | ET32: 3066.32 | EU32: 922.56 | EV32: 5585.89 | EW32: 487 | EX32: 0 | EY32: 0 | FQ32: 0 | FR32: 0 | FS32: 2 | FX32: 89 | FY32: 45 | GD32: 1 | GF32: -966979253 | GG32: 2 | GH32: 1 | GI32: 2 | GJ32: 0 | GK32: 0 | GL32: =ROUND(IF(AND(BH32=3,BI32=3,FS32<>0),P32,0),2) -> 0 | GM32: =ROUND(O32+X32+Y32,2)+GX32 -> 201.44 | GN32: =IF(OR(BI32=0,BI32=1),GM32-GX32,0) -> 0 | GO32: =IF(BI32=2,GM32-GX32,0) -> 201.44 | GP32: =IF(BI32=4,GM32-GX32,0) -> 0 | GR32: 0 | GS32: 3 | GT32: 0 | GV32: =ROUND((GT32),6) -> 0 | GW32: 1 | GX32: =ROUND(HC32*I32,2) -> 0 | HA32: 0 | HB32: 0 | HC32: =GV32*GW32 -> 0 | HS32: 0 | IK32: 0
A33: 17 | B33: 1 | C33: =ROW(SmtRes!A42) -> 42 | D33: =ROW(EtalonRes!A46) -> 46 | E33: 3 | F33: 4.6-48-4 | G33: Бак внутренней установки без давления цилиндрический вертикальный, вместимость 1,0 м3 (60 л.) | H33: 1 Т | I33: 0.009 | J33: 0 | K33: 0.009 | O33: =ROUND(CP33,2) -> 4509.42 | P33: =ROUND((ROUND((AC33*AW33*I33),2)*BC33),2) -> 12.1 | Q33: =(ROUND((ROUND((((ET33*1.2))*AV33*I33),2)*BB33),2)+ROUND((ROUND(((AE33-((EU33*1.2)))*AV33*I33),2)*BS33),2)) -> 870.07 | R33: =(ROUND((ROUND((((EU33*1.2))*AV33*I33),2)*BS33),2)+ROUND((ROUND(((AE33-((EU33*1.2)))*AV33*I33),2)*BS33),2)) -> 599 | S33: =ROUND((ROUND((AF33*AV33*I33),2)*BA33),2) -> 3627.25 | T33: =ROUND(CU33*I33,2) -> 0 | U33: =CV33*I33 -> 5.6119932 | V33: =CW33*I33 -> 0 | W33: =ROUND(CX33*I33,2) -> 0 | X33: =(ROUND((((S33+ROUND((ROUND((((EU33*1.2))*AV33*I33),2)*BS33),2))*AT33)/100),2)+ROUND(((ROUND((ROUND(((AE33-((EU33*1.2)))*AV33*I33),2)*BS33),2)*AT33)/100),2)) -> 3761.36 | Y33: =(ROUND((((S33+ROUND((ROUND((((EU33*1.2))*AV33*I33),2)*BS33),2))*AU33)/100),2)+ROUND(((ROUND((ROUND(((AE33-((EU33*1.2)))*AV33*I33),2)*BS33),2)*AU33)/100),2)) -> 1901.81 | AA33: 85739207 | AB33: =ROUND((AC33+AD33+AF33),6) -> 10515.652 | AC33: =ROUND(((ES33*1)),6) -> 133 | AD33: =ROUND(((((ET33*1.2))-((EU33*1.2)))+AE33),6) -> 3679.584 | AE33: =ROUND(((EU33*1.2)),6) -> 1107.072 | AF33: =ROUND(((EV33*1.2)),6) -> 6703.068 | AG33: =ROUND((AP33),6) -> 0 | AH33: =((EW33*1.2)) -> 584.4 | AI33: =((EX33*1.2)) -> 0 | AJ33: =(AS33) -> 0 | AK33: 8785.21 | AL33: 133 | AM33: 3066.32 | AN33: 922.56 | AO33: 5585.89 | AP33: 0 | AQ33: 487 | AR33: 0 | AS33: 0 | AT33: 89 | AU33: 45 | AV33: 1.067 | AW33: 1.028 | AZ33: 1 | BA33: 56.35 | BB33: 24.62 | BC33: 9.84 | BH33: 0 | BI33: 2 | BJ33: ТСН-2001.4. Доп. 1-42. Сб. 6, т. 48, поз. 4 | BM33: 65 | BN33: 0 | BO33: 4.6-48-4 | BP33: 1 | BQ33: 40 | BR33: 0 | BS33: 56.35 | BT33: 1 | BU33: 1 | BV33: 1 | BW33: 1 | BX33: 1 | BZ33: 89 | CA33: 45 | CE33: 1566 | CF33: 0 | CG33: 0 | CM33: 0 | CN33: Поправка: Гл.12.Прил.8.п.8. 3_12.00.01.11.001 Наименование: При наличии напряженных и стесненных условий производства работ (стесненность, сложность складирования и транспортной логистики и т.п.) для объектов, расположенных в пределах круговой магистральной системы улиц "Садовое кольцо" города Москвы | CO33: 0 | CP33: =(P33+Q33+S33) -> 4509.42 | CQ33: =ROUND((ROUND((AC33*AW33*1),2)*BC33),2) -> 1345.32 | CR33: =(ROUND((ROUND((((ET33*1.2))*AV33*1),2)*BB33),2)+ROUND((ROUND(((AE33-((EU33*1.2)))*AV33*1),2)*BS33),2)) -> 96661.07 | CS33: =(ROUND((ROUND((((EU33*1.2))*AV33*1),2)*BS33),2)+ROUND((ROUND(((AE33-((EU33*1.2)))*AV33*1),2)*BS33),2)) -> 66563.44 | CT33: =ROUND((ROUND((AF33*AV33*1),2)*BA33),2) -> 403024.78 | CU33: =AG33 -> 0 | CV33: =(AH33*AV33) -> 623.5548 | CW33: =AI33 -> 0 | CX33: =AJ33 -> 0 | CY33: =(ROUND((((S33+ROUND((ROUND((((EU33*1.2))*AV33*1),2)*BS33),2))*AT33)/100),2)+ROUND(((ROUND((ROUND(((AE33-((EU33*1.2)))*AV33*1),2)*BS33),2)*AT33)/100),2)) -> 62469.71 | CZ33: =(ROUND((((S33+ROUND((ROUND((((EU33*1.2))*AV33*1),2)*BS33),2))*AU33)/100),2)+ROUND(((ROUND((ROUND(((AE33-((EU33*1.2)))*AV33*1),2)*BS33),2)*AU33)/100),2)) -> 31585.81 | DB33: 8 | DD33: *1 | DE33: *1,2 | DF33: *1,2 | DG33: *1,2 | DI33: *1,2 | DJ33: *1,2 | DN33: 0 | DO33: 0 | DP33: 1 | DQ33: 1 | DU33: 1013 | DV33: 1 Т | DW33: 1 Т | DX33: 1 | EE33: 85133414 | EF33: 40 | EG33: Монтаж оборудования | EH33: 0 | EJ33: 2 | EK33: 65 | EL33: ТСН-2001.4-6. Теплосиловое оборудование | EM33: ТСН-2001.4-6-1 | EO33: Поправка: Гл.12.Прил.8.п.8. 3_12.00.01.11.001 | EQ33: 0 | ER33: 8785.21 | ES33: 133 | ET33: 3066.32 | EU33: 922.56 | EV33: 5585.89 | EW33: 487 | EX33: 0 | EY33: 0 | FQ33: 0 | FR33: 0 | FS33: 2 | FX33: 89 | FY33: 45 | GD33: 1 | GF33: -966979253 | GG33: 2 | GH33: 1 | GI33: 2 | GJ33: 0 | GK33: 0 | GL33: =ROUND(IF(AND(BH33=3,BI33=3,FS33<>0),P33,0),2) -> 0 | GM33: =ROUND(O33+X33+Y33,2)+GX33 -> 10172.59 | GN33: =IF(OR(BI33=0,BI33=1),GM33-GX33,0) -> 0 | GO33: =IF(BI33=2,GM33-GX33,0) -> 10172.59 | GP33: =IF(BI33=4,GM33-GX33,0) -> 0 | GR33: 0 | GS33: 3 | GT33: 0 | GV33: =ROUND((GT33),6) -> 0 | GW33: 1 | GX33: =ROUND(HC33*I33,2) -> 0 | HA33: 0 | HB33: 0 | HC33: =GV33*GW33 -> 0 | HS33: 0 | IK33: 0
A34: 17 | B34: 1 | C34: =ROW(SmtRes!A50) -> 50 | D34: =ROW(EtalonRes!A55) -> 55 | F34: 3.18-8-1 | G34: Установка баков расширительных круглых и прямоугольных вместимостью до 0,1 м3 (60 л.) | H34: 1 бак | I34: 1 | J34: 0 | K34: 1 | O34: =ROUND(CP34,2) -> 57.22 | P34: =ROUND((ROUND((AC34*AW34*I34),2)*BC34),2) -> 4.19 | Q34: =(ROUND((ROUND(((ET34)*AV34*I34),2)*BB34),2)+ROUND((ROUND(((AE34-(EU34))*AV34*I34),2)*BS34),2)) -> 8.07 | R34: =(ROUND((ROUND(((EU34)*AV34*I34),2)*BS34),2)+ROUND((ROUND(((AE34-(EU34))*AV34*I34),2)*BS34),2)) -> 0.63 | S34: =ROUND((ROUND((AF34*AV34*I34),2)*BA34),2) -> 44.96 | T34: =ROUND(CU34*I34,2) -> 0 | U34: =CV34*I34 -> 3.87321 | V34: =CW34*I34 -> 0 | W34: =ROUND(CX34*I34,2) -> 0 | X34: =(ROUND((((S34+ROUND((ROUND(((EU34)*AV34*I34),2)*BS34),2))*AT34)/100),2)+ROUND(((ROUND((ROUND(((AE34-(EU34))*AV34*I34),2)*BS34),2)*AT34)/100),2)) -> 55.16 | Y34: =(ROUND((((S34+ROUND((ROUND(((EU34)*AV34*I34),2)*BS34),2))*AU34)/100),2)+ROUND(((ROUND((ROUND(((AE34-(EU34))*AV34*I34),2)*BS34),2)*AU34)/100),2)) -> 32.82 | AA34: -1 | AB34: =ROUND((AC34+AD34+AF34),6) -> 53.89 | AC34: =ROUND((ES34),6) -> 4.19 | AD34: =ROUND((((ET34)-(EU34))+AE34),6) -> 7.56 | AE34: =ROUND((EU34),6) -> 0.59 | AF34: =ROUND((EV34),6) -> 42.14 | AG34: =ROUND((AP34),6) -> 0 | AH34: =(EW34) -> 3.63 | AI34: =(EX34) -> 0 | AJ34: =(AS34) -> 0 | AK34: 53.89 | AL34: 4.19 | AM34: 7.56 | AN34: 0.59 | AO34: 42.14 | AP34: 0 | AQ34: 3.63 | AR34: 0 | AS34: 0 | AT34: 121 | AU34: 72 | AV34: 1.067 | AW34: 1 | AZ34: 1 | BA34: 1 | BB34: 1 | BC34: 1 | BH34: 0 | BI34: 1 | BJ34: ТСН-2001.3 Доп. 72, Сб. 18, т. 8, поз. 1 | BM34: 23 | BN34: 0 | BO34: 3.18-8-1 | BP34: 1 | BQ34: 30 | BR34: 0 | BS34: 1 | BT34: 1 | BU34: 1 | BV34: 1 | BW34: 1 | BX34: 1 | BZ34: 121 | CA34: 72 | CE34: 1566 | CF34: 0 | CG34: 0 | CM34: 0 | CO34: 0 | CP34: =(P34+Q34+S34) -> 57.22 | CQ34: =ROUND((ROUND((AC34*AW34*1),2)*BC34),2) -> 4.19 | CR34: =(ROUND((ROUND(((ET34)*AV34*1),2)*BB34),2)+ROUND((ROUND(((AE34-(EU34))*AV34*1),2)*BS34),2)) -> 8.07 | CS34: =(ROUND((ROUND(((EU34)*AV34*1),2)*BS34),2)+ROUND((ROUND(((AE34-(EU34))*AV34*1),2)*BS34),2)) -> 0.63 | CT34: =ROUND((ROUND((AF34*AV34*1),2)*BA34),2) -> 44.96 | CU34: =AG34 -> 0 | CV34: =(AH34*AV34) -> 3.87321 | CW34: =AI34 -> 0 | CX34: =AJ34 -> 0 | CY34: =(ROUND((((S34+ROUND((ROUND(((EU34)*AV34*1),2)*BS34),2))*AT34)/100),2)+ROUND(((ROUND((ROUND(((AE34-(EU34))*AV34*1),2)*BS34),2)*AT34)/100),2)) -> 55.16 | CZ34: =(ROUND((((S34+ROUND((ROUND(((EU34)*AV34*1),2)*BS34),2))*AU34)/100),2)+ROUND(((ROUND((ROUND(((AE34-(EU34))*AV34*1),2)*BS34),2)*AU34)/100),2)) -> 32.82 | DN34: 0 | DO34: 0 | DP34: 1 | DQ34: 1 | DU34: 1013 | DV34: 1 бак | DW34: 1 бак | DX34: 1 | EE34: 85133369 | EF34: 30 | EG34: Строительные работы | EH34: 0 | EJ34: 1 | EK34: 23 | EL34: ТСН-2001.3-18. Отопление - внутренние устройства | EM34: ТСН-2001.3-18-1 | EQ34: 1024 | ER34: 53.89 | ES34: 4.19 | ET34: 7.56 | EU34: 0.59 | EV34: 42.14 | EW34: 3.63 | EX34: 0 | EY34: 0 | FQ34: 0 | FR34: 0 | FS34: 0 | FX34: 121 | FY34: 72 | GD34: 1 | GF34: 1630609332 | GG34: 2 | GH34: 1 | GI34: 2 | GJ34: 0 | GK34: 0 | GL34: =ROUND(IF(AND(BH34=3,BI34=3,FS34<>0),P34,0),2) -> 0 | GM34: =ROUND(O34+X34+Y34,2)+GX34 -> 145.2 | GN34: =IF(OR(BI34=0,BI34=1),GM34-GX34,0) -> 145.2 | GO34: =IF(BI34=2,GM34-GX34,0) -> 0 | GP34: =IF(BI34=4,GM34-GX34,0) -> 0 | GR34: 0 | GS34: 3 | GT34: 0 | GV34: =ROUND((GT34),6) -> 0 | GW34: 1 | GX34: =ROUND(HC34*I34,2) -> 0 | HA34: 0 | HB34: 0 | HC34: =GV34*GW34 -> 0 | HS34: 0 | IK34: 0
A35: 17 | B35: 1 | C35: =ROW(SmtRes!A58) -> 58 | D35: =ROW(EtalonRes!A64) -> 64 | F35: 3.18-8-1 | G35: Установка баков расширительных круглых и прямоугольных вместимостью до 0,1 м3 (60 л.) | H35: 1 бак | I35: 1 | J35: 0 | K35: 1 | O35: =ROUND(CP35,2) -> 2672.58 | P35: =ROUND((ROUND((AC35*AW35*I35),2)*BC35),2) -> 24.89 | Q35: =(ROUND((ROUND(((ET35)*AV35*I35),2)*BB35),2)+ROUND((ROUND(((AE35-(EU35))*AV35*I35),2)*BS35),2)) -> 114.19 | R35: =(ROUND((ROUND(((EU35)*AV35*I35),2)*BS35),2)+ROUND((ROUND(((AE35-(EU35))*AV35*I35),2)*BS35),2)) -> 35.5 | S35: =ROUND((ROUND((AF35*AV35*I35),2)*BA35),2) -> 2533.5 | T35: =ROUND(CU35*I35,2) -> 0 | U35: =CV35*I35 -> 3.87321 | V35: =CW35*I35 -> 0 | W35: =ROUND(CX35*I35,2) -> 0 | X35: =(ROUND((((S35+ROUND((ROUND(((EU35)*AV35*I35),2)*BS35),2))*AT35)/100),2)+ROUND(((ROUND((ROUND(((AE35-(EU35))*AV35*I35),2)*BS35),2)*AT35)/100),2)) -> 3108.49 | Y35: =(ROUND((((S35+ROUND((ROUND(((EU35)*AV35*I35),2)*BS35),2))*AU35)/100),2)+ROUND(((ROUND((ROUND(((AE35-(EU35))*AV35*I35),2)*BS35),2)*AU35)/100),2)) -> 1849.68 | AA35: -1 | AB35: =ROUND((AC35+AD35+AF35),6) -> 53.89 | AC35: =ROUND((ES35),6) -> 4.19 | AD35: =ROUND((((ET35)-(EU35))+AE35),6) -> 7.56 | AE35: =ROUND((EU35),6) -> 0.59 | AF35: =ROUND((EV35),6) -> 42.14 | AG35: =ROUND((AP35),6) -> 0 | AH35: =(EW35) -> 3.63 | AI35: =(EX35) -> 0 | AJ35: =(AS35) -> 0 | AK35: 53.89 | AL35: 4.19 | AM35: 7.56 | AN35: 0.59 | AO35: 42.14 | AP35: 0 | AQ35: 3.63 | AR35: 0 | AS35: 0 | AT35: 121 | AU35: 72 | AV35: 1.067 | AW35: 1 | AZ35: 1 | BA35: 56.35 | BB35: 14.15 | BC35: 5.94 | BH35: 0 | BI35: 1 | BJ35: ТСН-2001.3 Доп. 72, Сб. 18, т. 8, поз. 1 | BM35: 23 | BN35: 0 | BO35: 3.18-8-1 | BP35: 1 | BQ35: 30 | BR35: 0 | BS35: 56.35 | BT35: 1 | BU35: 1 | BV35: 1 | BW35: 1 | BX35: 1 | BZ35: 121 | CA35: 72 | CE35: 1566 | CF35: 0 | CG35: 0 | CM35: 0 | CO35: 0 | CP35: =(P35+Q35+S35) -> 2672.58 | CQ35: =ROUND((ROUND((AC35*AW35*1),2)*BC35),2) -> 24.89 | CR35: =(ROUND((ROUND(((ET35)*AV35*1),2)*BB35),2)+ROUND((ROUND(((AE35-(EU35))*AV35*1),2)*BS35),2)) -> 114.19 | CS35: =(ROUND((ROUND(((EU35)*AV35*1),2)*BS35),2)+ROUND((ROUND(((AE35-(EU35))*AV35*1),2)*BS35),2)) -> 35.5 | CT35: =ROUND((ROUND((AF35*AV35*1),2)*BA35),2) -> 2533.5 | CU35: =AG35 -> 0 | CV35: =(AH35*AV35) -> 3.87321 | CW35: =AI35 -> 0 | CX35: =AJ35 -> 0 | CY35: =(ROUND((((S35+ROUND((ROUND(((EU35)*AV35*1),2)*BS35),2))*AT35)/100),2)+ROUND(((ROUND((ROUND(((AE35-(EU35))*AV35*1),2)*BS35),2)*AT35)/100),2)) -> 3108.49 | CZ35: =(ROUND((((S35+ROUND((ROUND(((EU35)*AV35*1),2)*BS35),2))*AU35)/100),2)+ROUND(((ROUND((ROUND(((AE35-(EU35))*AV35*1),2)*BS35),2)*AU35)/100),2)) -> 1849.68 | DN35: 0 | DO35: 0 | DP35: 1 | DQ35: 1 | DU35: 1013 | DV35: 1 бак | DW35: 1 бак | DX35: 1 | EE35: 85133369 | EF35: 30 | EG35: Строительные работы | EH35: 0 | EJ35: 1 | EK35: 23 | EL35: ТСН-2001.3-18. Отопление - внутренние устройства | EM35: ТСН-2001.3-18-1 | EQ35: 1024 | ER35: 53.89 | ES35: 4.19 | ET35: 7.56 | EU35: 0.59 | EV35: 42.14 | EW35: 3.63 | EX35: 0 | EY35: 0 | FQ35: 0 | FR35: 0 | FS35: 0 | FX35: 121 | FY35: 72 | GD35: 1 | GF35: 1630609332 | GG35: 2 | GH35: 1 | GI35: 2 | GJ35: 0 | GK35: 0 | GL35: =ROUND(IF(AND(BH35=3,BI35=3,FS35<>0),P35,0),2) -> 0 | GM35: =ROUND(O35+X35+Y35,2)+GX35 -> 7630.75 | GN35: =IF(OR(BI35=0,BI35=1),GM35-GX35,0) -> 7630.75 | GO35: =IF(BI35=2,GM35-GX35,0) -> 0 | GP35: =IF(BI35=4,GM35-GX35,0) -> 0 | GR35: 0 | GS35: 3 | GT35: 0 | GV35: =ROUND((GT35),6) -> 0 | GW35: 1 | GX35: =ROUND(HC35*I35,2) -> 0 | HA35: 0 | HB35: 0 | HC35: =GV35*GW35 -> 0 | HS35: 0 | IK35: 0
A36: 17 | B36: 1 | C36: =ROW(SmtRes!A65) -> 65 | D36: =ROW(EtalonRes!A73) -> 73 | E36: 4 | F36: 4.8-240-4 | G36: Монтаж пультов и шкафов управления, шкафа (пульта) управления навесного, высотой, шириной, глубиной до 600х600х350 мм | H36: 1 ШТ. | I36: 1 | J36: 0 | K36: 1 | O36: =ROUND(CP36,2) -> 56.97 | P36: =ROUND((ROUND((AC36*AW36*I36),2)*BC36),2) -> 1.46 | Q36: =(ROUND((ROUND((((ET36*1.2))*AV36*I36),2)*BB36),2)+ROUND((ROUND(((AE36-((EU36*1.2)))*AV36*I36),2)*BS36),2)) -> 21.89 | R36: =(ROUND((ROUND((((EU36*1.2))*AV36*I36),2)*BS36),2)+ROUND((ROUND(((AE36-((EU36*1.2)))*AV36*I36),2)*BS36),2)) -> 3.97 | S36: =ROUND((ROUND((AF36*AV36*I36),2)*BA36),2) -> 33.62 | T36: =ROUND(CU36*I36,2) -> 0 | U36: =CV36*I36 -> 2.588184 | V36: =CW36*I36 -> 0 | W36: =ROUND(CX36*I36,2) -> 0 | X36: =(ROUND((((S36+ROUND((ROUND((((EU36*1.2))*AV36*I36),2)*BS36),2))*AT36)/100),2)+ROUND(((ROUND((ROUND(((AE36-((EU36*1.2)))*AV36*I36),2)*BS36),2)*AT36)/100),2)) -> 36.46 | Y36: =(ROUND((((S36+ROUND((ROUND((((EU36*1.2))*AV36*I36),2)*BS36),2))*AU36)/100),2)+ROUND(((ROUND((ROUND(((AE36-((EU36*1.2)))*AV36*I36),2)*BS36),2)*AU36)/100),2)) -> 19.17 | AA36: 85739205 | AB36: =ROUND((AC36+AD36+AF36),6) -> 54.476 | AC36: =ROUND(((ES36*1)),6) -> 1.46 | AD36: =ROUND(((((ET36*1.2))-((EU36*1.2)))+AE36),6) -> 20.904 | AE36: =ROUND(((EU36*1.2)),6) -> 3.792 | AF36: =ROUND(((EV36*1.2)),6) -> 32.112 | AG36: =ROUND((AP36),6) -> 0 | AH36: =((EW36*1.2)) -> 2.472 | AI36: =((EX36*1.2)) -> 0 | AJ36: =(AS36) -> 0 | AK36: 45.64 | AL36: 1.46 | AM36: 17.42 | AN36: 3.16 | AO36: 26.76 | AP36: 0 | AQ36: 2.06 | AR36: 0 | AS36: 0 | AT36: 97 | AU36: 51 | AV36: 1.047 | AW36: 1 | AZ36: 1 | BA36: 1 | BB36: 1 | BC36: 1 | BH36: 0 | BI36: 2 | BJ36: ТСН-2001.4 Доп. 80, Сб. 8, т. 240, поз. 4 | BM36: 67 | BN36: 0 | BO36: 4.8-240-4 | BP36: 1 | BQ36: 40 | BR36: 0 | BS36: 1 | BT36: 1 | BU36: 1 | BV36: 1 | BW36: 1 | BX36: 1 | BZ36: 97 | CA36: 51 | CE36: 1566 | CF36: 0 | CG36: 0 | CM36: 0 | CN36: Поправка: Гл.12.Прил.8.п.8. 3_12.00.01.11.001 Наименование: При наличии напряженных и стесненных условий производства работ (стесненность, сложность складирования и транспортной логистики и т.п.) для объектов, расположенных в пределах круговой магистральной системы улиц "Садовое кольцо" города Москвы | CO36: 0 | CP36: =(P36+Q36+S36) -> 56.97 | CQ36: =ROUND((ROUND((AC36*AW36*1),2)*BC36),2) -> 1.46 | CR36: =(ROUND((ROUND((((ET36*1.2))*AV36*1),2)*BB36),2)+ROUND((ROUND(((AE36-((EU36*1.2)))*AV36*1),2)*BS36),2)) -> 21.89 | CS36: =(ROUND((ROUND((((EU36*1.2))*AV36*1),2)*BS36),2)+ROUND((ROUND(((AE36-((EU36*1.2)))*AV36*1),2)*BS36),2)) -> 3.97 | CT36: =ROUND((ROUND((AF36*AV36*1),2)*BA36),2) -> 33.62 | CU36: =AG36 -> 0 | CV36: =(AH36*AV36) -> 2.588184 | CW36: =AI36 -> 0 | CX36: =AJ36 -> 0 | CY36: =(ROUND((((S36+ROUND((ROUND((((EU36*1.2))*AV36*1),2)*BS36),2))*AT36)/100),2)+ROUND(((ROUND((ROUND(((AE36-((EU36*1.2)))*AV36*1),2)*BS36),2)*AT36)/100),2)) -> 36.46 | CZ36: =(ROUND((((S36+ROUND((ROUND((((EU36*1.2))*AV36*1),2)*BS36),2))*AU36)/100),2)+ROUND(((ROUND((ROUND(((AE36-((EU36*1.2)))*AV36*1),2)*BS36),2)*AU36)/100),2)) -> 19.17 | DB36: 9 | DD36: *1 | DE36: *1,2 | DF36: *1,2 | DG36: *1,2 | DI36: *1,2 | DJ36: *1,2 | DN36: 0 | DO36: 0 | DP36: 1 | DQ36: 1 | DU36: 1013 | DV36: 1 ШТ. | DW36: 1 ШТ. | DX36: 1 | EE36: 85133416 | EF36: 40 | EG36: Монтаж оборудования | EH36: 0 | EJ36: 2 | EK36: 67 | EL36: ТСН-2001.4-8. Электротехнические установки | EM36: ТСН-2001.4-8-1 | EO36: Поправка: Гл.12.Прил.8.п.8. 3_12.00.01.11.001 | EQ36: 0 | ER36: 45.64 | ES36: 1.46 | ET36: 17.42 | EU36: 3.16 | EV36: 26.76 | EW36: 2.06 | EX36: 0 | EY36: 0 | FQ36: 0 | FR36: 0 | FS36: 0 | FX36: 97 | FY36: 51 | GD36: 1 | GF36: -1842782186 | GG36: 2 | GH36: 1 | GI36: 2 | GJ36: 0 | GK36: 0 | GL36: =ROUND(IF(AND(BH36=3,BI36=3,FS36<>0),P36,0),2) -> 0 | GM36: =ROUND(O36+X36+Y36,2)+GX36 -> 112.6 | GN36: =IF(OR(BI36=0,BI36=1),GM36-GX36,0) -> 0 | GO36: =IF(BI36=2,GM36-GX36,0) -> 112.6 | GP36: =IF(BI36=4,GM36-GX36,0) -> 0 | GR36: 0 | GS36: 3 | GT36: 0 | GV36: =ROUND((GT36),6) -> 0 | GW36: 1 | GX36: =ROUND(HC36*I36,2) -> 0 | HA36: 0 | HB36: 0 | HC36: =GV36*GW36 -> 0 | HS36: 0 | IK36: 0
A37: 17 | B37: 1 | C37: =ROW(SmtRes!A72) -> 72 | D37: =ROW(EtalonRes!A82) -> 82 | E37: 4 | F37: 4.8-240-4 | G37: Монтаж пультов и шкафов управления, шкафа (пульта) управления навесного, высотой, шириной, глубиной до 600х600х350 мм | H37: 1 ШТ. | I37: 1 | J37: 0 | K37: 1 | O37: =ROUND(CP37,2) -> 2346.01 | P37: =ROUND((ROUND((AC37*AW37*I37),2)*BC37),2) -> 16.13 | Q37: =(ROUND((ROUND((((ET37*1.2))*AV37*I37),2)*BB37),2)+ROUND((ROUND(((AE37-((EU37*1.2)))*AV37*I37),2)*BS37),2)) -> 435.39 | R37: =(ROUND((ROUND((((EU37*1.2))*AV37*I37),2)*BS37),2)+ROUND((ROUND(((AE37-((EU37*1.2)))*AV37*I37),2)*BS37),2)) -> 223.71 | S37: =ROUND((ROUND((AF37*AV37*I37),2)*BA37),2) -> 1894.49 | T37: =ROUND(CU37*I37,2) -> 0 | U37: =CV37*I37 -> 2.588184 | V37: =CW37*I37 -> 0 | W37: =ROUND(CX37*I37,2) -> 0 | X37: =(ROUND((((S37+ROUND((ROUND((((EU37*1.2))*AV37*I37),2)*BS37),2))*AT37)/100),2)+ROUND(((ROUND((ROUND(((AE37-((EU37*1.2)))*AV37*I37),2)*BS37),2)*AT37)/100),2)) -> 2054.65 | Y37: =(ROUND((((S37+ROUND((ROUND((((EU37*1.2))*AV37*I37),2)*BS37),2))*AU37)/100),2)+ROUND(((ROUND((ROUND(((AE37-((EU37*1.2)))*AV37*I37),2)*BS37),2)*AU37)/100),2)) -> 1080.28 | AA37: 85739207 | AB37: =ROUND((AC37+AD37+AF37),6) -> 54.476 | AC37: =ROUND(((ES37*1)),6) -> 1.46 | AD37: =ROUND(((((ET37*1.2))-((EU37*1.2)))+AE37),6) -> 20.904 | AE37: =ROUND(((EU37*1.2)),6) -> 3.792 | AF37: =ROUND(((EV37*1.2)),6) -> 32.112 | AG37: =ROUND((AP37),6) -> 0 | AH37: =((EW37*1.2)) -> 2.472 | AI37: =((EX37*1.2)) -> 0 | AJ37: =(AS37) -> 0 | AK37: 45.64 | AL37: 1.46 | AM37: 17.42 | AN37: 3.16 | AO37: 26.76 | AP37: 0 | AQ37: 2.06 | AR37: 0 | AS37: 0 | AT37: 97 | AU37: 51 | AV37: 1.047 | AW37: 1 | AZ37: 1 | BA37: 56.35 | BB37: 19.89 | BC37: 11.05 | BH37: 0 | BI37: 2 | BJ37: ТСН-2001.4 Доп. 80, Сб. 8, т. 240, поз. 4 | BM37: 67 | BN37: 0 | BO37: 4.8-240-4 | BP37: 1 | BQ37: 40 | BR37: 0 | BS37: 56.35 | BT37: 1 | BU37: 1 | BV37: 1 | BW37: 1 | BX37: 1 | BZ37: 97 | CA37: 51 | CE37: 1566 | CF37: 0 | CG37: 0 | CM37: 0 | CN37: Поправка: Гл.12.Прил.8.п.8. 3_12.00.01.11.001 Наименование: При наличии напряженных и стесненных условий производства работ (стесненность, сложность складирования и транспортной логистики и т.п.) для объектов, расположенных в пределах круговой магистральной системы улиц "Садовое кольцо" города Москвы | CO37: 0 | CP37: =(P37+Q37+S37) -> 2346.01 | CQ37: =ROUND((ROUND((AC37*AW37*1),2)*BC37),2) -> 16.13 | CR37: =(ROUND((ROUND((((ET37*1.2))*AV37*1),2)*BB37),2)+ROUND((ROUND(((AE37-((EU37*1.2)))*AV37*1),2)*BS37),2)) -> 435.39 | CS37: =(ROUND((ROUND((((EU37*1.2))*AV37*1),2)*BS37),2)+ROUND((ROUND(((AE37-((EU37*1.2)))*AV37*1),2)*BS37),2)) -> 223.71 | CT37: =ROUND((ROUND((AF37*AV37*1),2)*BA37),2) -> 1894.49 | CU37: =AG37 -> 0 | CV37: =(AH37*AV37) -> 2.588184 | CW37: =AI37 -> 0 | CX37: =AJ37 -> 0 | CY37: =(ROUND((((S37+ROUND((ROUND((((EU37*1.2))*AV37*1),2)*BS37),2))*AT37)/100),2)+ROUND(((ROUND((ROUND(((AE37-((EU37*1.2)))*AV37*1),2)*BS37),2)*AT37)/100),2)) -> 2054.65 | CZ37: =(ROUND((((S37+ROUND((ROUND((((EU37*1.2))*AV37*1),2)*BS37),2))*AU37)/100),2)+ROUND(((ROUND((ROUND(((AE37-((EU37*1.2)))*AV37*1),2)*BS37),2)*AU37)/100),2)) -> 1080.28 | DB37: 10 | DD37: *1 | DE37: *1,2 | DF37: *1,2 | DG37: *1,2 | DI37: *1,2 | DJ37: *1,2 | DN37: 0 | DO37: 0 | DP37: 1 | DQ37: 1 | DU37: 1013 | DV37: 1 ШТ. | DW37: 1 ШТ. | DX37: 1 | EE37: 85133416 | EF37: 40 | EG37: Монтаж оборудования | EH37: 0 | EJ37: 2 | EK37: 67 | EL37: ТСН-2001.4-8. Электротехнические установки | EM37: ТСН-2001.4-8-1 | EO37: Поправка: Гл.12.Прил.8.п.8. 3_12.00.01.11.001 | EQ37: 0 | ER37: 45.64 | ES37: 1.46 | ET37: 17.42 | EU37: 3.16 | EV37: 26.76 | EW37: 2.06 | EX37: 0 | EY37: 0 | FQ37: 0 | FR37: 0 | FS37: 0 | FX37: 97 | FY37: 51 | GD37: 1 | GF37: -1842782186 | GG37: 2 | GH37: 1 | GI37: 2 | GJ37: 0 | GK37: 0 | GL37: =ROUND(IF(AND(BH37=3,BI37=3,FS37<>0),P37,0),2) -> 0 | GM37: =ROUND(O37+X37+Y37,2)+GX37 -> 5480.94 | GN37: =IF(OR(BI37=0,BI37=1),GM37-GX37,0) -> 0 | GO37: =IF(BI37=2,GM37-GX37,0) -> 5480.94 | GP37: =IF(BI37=4,GM37-GX37,0) -> 0 | GR37: 0 | GS37: 3 | GT37: 0 | GV37: =ROUND((GT37),6) -> 0 | GW37: 1 | GX37: =ROUND(HC37*I37,2) -> 0 | HA37: 0 | HB37: 0 | HC37: =GV37*GW37 -> 0 | HS37: 0 | IK37: 0
A38: 17 | B38: 1 | C38: =ROW(SmtRes!A75) -> 75 | D38: =ROW(EtalonRes!A87) -> 87 | E38: 5 | F38: 4.12-48-9 | G38: Монтаж арматуры фланцевой с ручным приводом или без привода на номинальное давление до 4 МПа, номинальный диаметр прохода 80 мм (обратный клапан, затвор поворотный) | H38: 1 ШТ. | I38: =ROUND(2+4,9) -> 6 | J38: 0 | K38: =ROUND(2+4,9) -> 6 | O38: =ROUND(CP38,2) -> 417.65 | P38: =ROUND((ROUND((AC38*AW38*I38),2)*BC38),2) -> 17.09 | Q38: =(ROUND((ROUND((((ET38*1.2))*AV38*I38),2)*BB38),2)+ROUND((ROUND(((AE38-((EU38*1.2)))*AV38*I38),2)*BS38),2)) -> 12.75 | R38: =(ROUND((ROUND((((EU38*1.2))*AV38*I38),2)*BS38),2)+ROUND((ROUND(((AE38-((EU38*1.2)))*AV38*I38),2)*BS38),2)) -> 1.92 | S38: =ROUND((ROUND((AF38*AV38*I38),2)*BA38),2) -> 387.81 | T38: =ROUND(CU38*I38,2) -> 0 | U38: =CV38*I38 -> 30.7296 | V38: =CW38*I38 -> 0 | W38: =ROUND(CX38*I38,2) -> 0 | X38: =(ROUND((((S38+ROUND((ROUND((((EU38*1.2))*AV38*I38),2)*BS38),2))*AT38)/100),2)+ROUND(((ROUND((ROUND(((AE38-((EU38*1.2)))*AV38*I38),2)*BS38),2)*AT38)/100),2)) -> 350.76 | Y38: =(ROUND((((S38+ROUND((ROUND((((EU38*1.2))*AV38*I38),2)*BS38),2))*AU38)/100),2)+ROUND(((ROUND((ROUND(((AE38-((EU38*1.2)))*AV38*I38),2)*BS38),2)*AU38)/100),2)) -> 179.28 | AA38: 85739205 | AB38: =ROUND((AC38+AD38+AF38),6) -> 65.338 | AC38: =ROUND(((ES38*1)),6) -> 2.77 | AD38: =ROUND(((((ET38*1.2))-((EU38*1.2)))+AE38),6) -> 1.992 | AE38: =ROUND(((EU38*1.2)),6) -> 0.3 | AF38: =ROUND(((EV38*1.2)),6) -> 60.576 | AG38: =ROUND((AP38),6) -> 0 | AH38: =((EW38*1.2)) -> 4.8 | AI38: =((EX38*1.2)) -> 0 | AJ38: =(AS38) -> 0 | AK38: 54.91 | AL38: 2.77 | AM38: 1.66 | AN38: 0.25 | AO38: 50.48 | AP38: 0 | AQ38: 4 | AR38: 0 | AS38: 0 | AT38: 90 | AU38: 46 | AV38: 1.067 | AW38: 1.028 | AZ38: 1 | BA38: 1 | BB38: 1 | BC38: 1 | BH38: 0 | BI38: 2 | BJ38: ТСН-2001.4 Доп. 68, Сб. 12, т. 48, поз. 9 | BM38: 73 | BN38: 0 | BO38: 4.12-48-9 | BP38: 1 | BQ38: 40 | BR38: 0 | BS38: 1 | BT38: 1 | BU38: 1 | BV38: 1 | BW38: 1 | BX38: 1 | BZ38: 90 | CA38: 46 | CE38: 1566 | CF38: 0 | CG38: 0 | CM38: 0 | CN38: Поправка: Гл.12.Прил.8.п.8. 3_12.00.01.11.001 Наименование: При наличии напряженных и стесненных условий производства работ (стесненность, сложность складирования и транспортной логистики и т.п.) для объектов, расположенных в пределах круговой магистральной системы улиц "Садовое кольцо" города Москвы | CO38: 0 | CP38: =(P38+Q38+S38) -> 417.65 | CQ38: =ROUND((ROUND((AC38*AW38*1),2)*BC38),2) -> 2.85 | CR38: =(ROUND((ROUND((((ET38*1.2))*AV38*1),2)*BB38),2)+ROUND((ROUND(((AE38-((EU38*1.2)))*AV38*1),2)*BS38),2)) -> 2.13 | CS38: =(ROUND((ROUND((((EU38*1.2))*AV38*1),2)*BS38),2)+ROUND((ROUND(((AE38-((EU38*1.2)))*AV38*1),2)*BS38),2)) -> 0.32 | CT38: =ROUND((ROUND((AF38*AV38*1),2)*BA38),2) -> 64.63 | CU38: =AG38 -> 0 | CV38: =(AH38*AV38) -> 5.1216 | CW38: =AI38 -> 0 | CX38: =AJ38 -> 0 | CY38: =(ROUND((((S38+ROUND((ROUND((((EU38*1.2))*AV38*1),2)*BS38),2))*AT38)/100),2)+ROUND(((ROUND((ROUND(((AE38-((EU38*1.2)))*AV38*1),2)*BS38),2)*AT38)/100),2)) -> 349.32 | CZ38: =(ROUND((((S38+ROUND((ROUND((((EU38*1.2))*AV38*1),2)*BS38),2))*AU38)/100),2)+ROUND(((ROUND((ROUND(((AE38-((EU38*1.2)))*AV38*1),2)*BS38),2)*AU38)/100),2)) -> 178.54 | DB38: 11 | DD38: *1 | DE38: *1,2 | DF38: *1,2 | DG38: *1,2 | DI38: *1,2 | DJ38: *1,2 | DN38: 0 | DO38: 0 | DP38: 1 | DQ38: 1 | DU38: 1013 | DV38: 1 ШТ. | DW38: 1 ШТ. | DX38: 1 | EE38: 85133422 | EF38: 40 | EG38: Монтаж оборудования | EH38: 0 | EJ38: 2 | EK38: 73 | EL38: ТСН-2001.4-12. Технологические трубопроводы | EM38: ТСН-2001.4-12-1 | EO38: Поправка: Гл.12.Прил.8.п.8. 3_12.00.01.11.001 | EQ38: 0 | ER38: 54.91 | ES38: 2.77 | ET38: 1.66 | EU38: 0.25 | EV38: 50.48 | EW38: 4 | EX38: 0 | EY38: 0 | FQ38: 0 | FR38: 0 | FS38: 2 | FX38: 90 | FY38: 46 | GD38: 1 | GF38: 742127146 | GG38: 2 | GH38: 1 | GI38: 2 | GJ38: 0 | GK38: 0 | GL38: =ROUND(IF(AND(BH38=3,BI38=3,FS38<>0),P38,0),2) -> 0 | GM38: =ROUND(O38+X38+Y38,2)+GX38 -> 947.69 | GN38: =IF(OR(BI38=0,BI38=1),GM38-GX38,0) -> 0 | GO38: =IF(BI38=2,GM38-GX38,0) -> 947.69 | GP38: =IF(BI38=4,GM38-GX38,0) -> 0 | GR38: 0 | GS38: 3 | GT38: 0 | GV38: =ROUND((GT38),6) -> 0 | GW38: 1 | GX38: =ROUND(HC38*I38,2) -> 0 | HA38: 0 | HB38: 0 | HC38: =GV38*GW38 -> 0 | HS38: 0 | IK38: 0
A39: 17 | B39: 1 | C39: =ROW(SmtRes!A78) -> 78 | D39: =ROW(EtalonRes!A92) -> 92 | E39: 5 | F39: 4.12-48-9 | G39: Монтаж арматуры фланцевой с ручным приводом или без привода на номинальное давление до 4 МПа, номинальный диаметр прохода 80 мм (обратный клапан, затвор поворотный) | H39: 1 ШТ. | I39: =ROUND(2+4,9) -> 6 | J39: 0 | K39: =ROUND(2+4,9) -> 6 | O39: =ROUND(CP39,2) -> 22147.9 | P39: =ROUND((ROUND((AC39*AW39*I39),2)*BC39),2) -> 76.91 | Q39: =(ROUND((ROUND((((ET39*1.2))*AV39*I39),2)*BB39),2)+ROUND((ROUND(((AE39-((EU39*1.2)))*AV39*I39),2)*BS39),2)) -> 217.9 | R39: =(ROUND((ROUND((((EU39*1.2))*AV39*I39),2)*BS39),2)+ROUND((ROUND(((AE39-((EU39*1.2)))*AV39*I39),2)*BS39),2)) -> 108.19 | S39: =ROUND((ROUND((AF39*AV39*I39),2)*BA39),2) -> 21853.09 | T39: =ROUND(CU39*I39,2) -> 0 | U39: =CV39*I39 -> 30.7296 | V39: =CW39*I39 -> 0 | W39: =ROUND(CX39*I39,2) -> 0 | X39: =(ROUND((((S39+ROUND((ROUND((((EU39*1.2))*AV39*I39),2)*BS39),2))*AT39)/100),2)+ROUND(((ROUND((ROUND(((AE39-((EU39*1.2)))*AV39*I39),2)*BS39),2)*AT39)/100),2)) -> 19765.15 | Y39: =(ROUND((((S39+ROUND((ROUND((((EU39*1.2))*AV39*I39),2)*BS39),2))*AU39)/100),2)+ROUND(((ROUND((ROUND(((AE39-((EU39*1.2)))*AV39*I39),2)*BS39),2)*AU39)/100),2)) -> 10102.19 | AA39: 85739207 | AB39: =ROUND((AC39+AD39+AF39),6) -> 65.338 | AC39: =ROUND(((ES39*1)),6) -> 2.77 | AD39: =ROUND(((((ET39*1.2))-((EU39*1.2)))+AE39),6) -> 1.992 | AE39: =ROUND(((EU39*1.2)),6) -> 0.3 | AF39: =ROUND(((EV39*1.2)),6) -> 60.576 | AG39: =ROUND((AP39),6) -> 0 | AH39: =((EW39*1.2)) -> 4.8 | AI39: =((EX39*1.2)) -> 0 | AJ39: =(AS39) -> 0 | AK39: 54.91 | AL39: 2.77 | AM39: 1.66 | AN39: 0.25 | AO39: 50.48 | AP39: 0 | AQ39: 4 | AR39: 0 | AS39: 0 | AT39: 90 | AU39: 46 | AV39: 1.067 | AW39: 1.028 | AZ39: 1 | BA39: 56.35 | BB39: 17.09 | BC39: 4.5 | BH39: 0 | BI39: 2 | BJ39: ТСН-2001.4 Доп. 68, Сб. 12, т. 48, поз. 9 | BM39: 73 | BN39: 0 | BO39: 4.12-48-9 | BP39: 1 | BQ39: 40 | BR39: 0 | BS39: 56.35 | BT39: 1 | BU39: 1 | BV39: 1 | BW39: 1 | BX39: 1 | BZ39: 90 | CA39: 46 | CE39: 1566 | CF39: 0 | CG39: 0 | CM39: 0 | CN39: Поправка: Гл.12.Прил.8.п.8. 3_12.00.01.11.001 Наименование: При наличии напряженных и стесненных условий производства работ (стесненность, сложность складирования и транспортной логистики и т.п.) для объектов, расположенных в пределах круговой магистральной системы улиц "Садовое кольцо" города Москвы | CO39: 0 | CP39: =(P39+Q39+S39) -> 22147.9 | CQ39: =ROUND((ROUND((AC39*AW39*1),2)*BC39),2) -> 12.83 | CR39: =(ROUND((ROUND((((ET39*1.2))*AV39*1),2)*BB39),2)+ROUND((ROUND(((AE39-((EU39*1.2)))*AV39*1),2)*BS39),2)) -> 36.4 | CS39: =(ROUND((ROUND((((EU39*1.2))*AV39*1),2)*BS39),2)+ROUND((ROUND(((AE39-((EU39*1.2)))*AV39*1),2)*BS39),2)) -> 18.03 | CT39: =ROUND((ROUND((AF39*AV39*1),2)*BA39),2) -> 3641.9 | CU39: =AG39 -> 0 | CV39: =(AH39*AV39) -> 5.1216 | CW39: =AI39 -> 0 | CX39: =AJ39 -> 0 | CY39: =(ROUND((((S39+ROUND((ROUND((((EU39*1.2))*AV39*1),2)*BS39),2))*AT39)/100),2)+ROUND(((ROUND((ROUND(((AE39-((EU39*1.2)))*AV39*1),2)*BS39),2)*AT39)/100),2)) -> 19684.01 | CZ39: =(ROUND((((S39+ROUND((ROUND((((EU39*1.2))*AV39*1),2)*BS39),2))*AU39)/100),2)+ROUND(((ROUND((ROUND(((AE39-((EU39*1.2)))*AV39*1),2)*BS39),2)*AU39)/100),2)) -> 10060.72 | DB39: 12 | DD39: *1 | DE39: *1,2 | DF39: *1,2 | DG39: *1,2 | DI39: *1,2 | DJ39: *1,2 | DN39: 0 | DO39: 0 | DP39: 1 | DQ39: 1 | DU39: 1013 | DV39: 1 ШТ. | DW39: 1 ШТ. | DX39: 1 | EE39: 85133422 | EF39: 40 | EG39: Монтаж оборудования | EH39: 0 | EJ39: 2 | EK39: 73 | EL39: ТСН-2001.4-12. Технологические трубопроводы | EM39: ТСН-2001.4-12-1 | EO39: Поправка: Гл.12.Прил.8.п.8. 3_12.00.01.11.001 | EQ39: 0 | ER39: 54.91 | ES39: 2.77 | ET39: 1.66 | EU39: 0.25 | EV39: 50.48 | EW39: 4 | EX39: 0 | EY39: 0 | FQ39: 0 | FR39: 0 | FS39: 2 | FX39: 90 | FY39: 46 | GD39: 1 | GF39: 742127146 | GG39: 2 | GH39: 1 | GI39: 2 | GJ39: 0 | GK39: 0 | GL39: =ROUND(IF(AND(BH39=3,BI39=3,FS39<>0),P39,0),2) -> 0 | GM39: =ROUND(O39+X39+Y39,2)+GX39 -> 52015.24 | GN39: =IF(OR(BI39=0,BI39=1),GM39-GX39,0) -> 0 | GO39: =IF(BI39=2,GM39-GX39,0) -> 52015.24 | GP39: =IF(BI39=4,GM39-GX39,0) -> 0 | GR39: 0 | GS39: 3 | GT39: 0 | GV39: =ROUND((GT39),6) -> 0 | GW39: 1 | GX39: =ROUND(HC39*I39,2) -> 0 | HA39: 0 | HB39: 0 | HC39: =GV39*GW39 -> 0 | HS39: 0 | IK39: 0
A40: 17 | B40: 1 | C40: =ROW(SmtRes!A81) -> 81 | D40: =ROW(EtalonRes!A97) -> 97 | E40: 6 | F40: 4.12-48-11 | G40: Монтаж арматуры фланцевой с ручным приводом или без привода на номинальное давление до 4 МПа, номинальный диаметр прохода 125 мм (затвор поворотный разделительный) | H40: 1 ШТ. | I40: =ROUND(2,9) -> 2 | J40: 0 | K40: =ROUND(2,9) -> 2 | O40: =ROUND(CP40,2) -> 191.1 | P40: =ROUND((ROUND((AC40*AW40*I40),2)*BC40),2) -> 8.08 | Q40: =(ROUND((ROUND((((ET40*1.2))*AV40*I40),2)*BB40),2)+ROUND((ROUND(((AE40-((EU40*1.2)))*AV40*I40),2)*BS40),2)) -> 8.5 | R40: =(ROUND((ROUND((((EU40*1.2))*AV40*I40),2)*BS40),2)+ROUND((ROUND(((AE40-((EU40*1.2)))*AV40*I40),2)*BS40),2)) -> 1.28 | S40: =ROUND((ROUND((AF40*AV40*I40),2)*BA40),2) -> 174.52 | T40: =ROUND(CU40*I40,2) -> 0 | U40: =CV40*I40 -> 13.82832 | V40: =CW40*I40 -> 0 | W40: =ROUND(CX40*I40,2) -> 0 | X40: =(ROUND((((S40+ROUND((ROUND((((EU40*1.2))*AV40*I40),2)*BS40),2))*AT40)/100),2)+ROUND(((ROUND((ROUND(((AE40-((EU40*1.2)))*AV40*I40),2)*BS40),2)*AT40)/100),2)) -> 158.22 | Y40: =(ROUND((((S40+ROUND((ROUND((((EU40*1.2))*AV40*I40),2)*BS40),2))*AU40)/100),2)+ROUND(((ROUND((ROUND(((AE40-((EU40*1.2)))*AV40*I40),2)*BS40),2)*AU40)/100),2)) -> 80.87 | AA40: 85739205 | AB40: =ROUND((AC40+AD40+AF40),6) -> 89.694 | AC40: =ROUND(((ES40*1)),6) -> 3.93 | AD40: =ROUND(((((ET40*1.2))-((EU40*1.2)))+AE40),6) -> 3.984 | AE40: =ROUND(((EU40*1.2)),6) -> 0.6 | AF40: =ROUND(((EV40*1.2)),6) -> 81.78 | AG40: =ROUND((AP40),6) -> 0 | AH40: =((EW40*1.2)) -> 6.48 | AI40: =((EX40*1.2)) -> 0 | AJ40: =(AS40) -> 0 | AK40: 75.4 | AL40: 3.93 | AM40: 3.32 | AN40: 0.5 | AO40: 68.15 | AP40: 0 | AQ40: 5.4 | AR40: 0 | AS40: 0 | AT40: 90 | AU40: 46 | AV40: 1.067 | AW40: 1.028 | AZ40: 1 | BA40: 1 | BB40: 1 | BC40: 1 | BH40: 0 | BI40: 2 | BJ40: ТСН-2001.4 Доп. 68, Сб. 12, т. 48, поз. 11 | BM40: 73 | BN40: 0 | BO40: 4.12-48-11 | BP40: 1 | BQ40: 40 | BR40: 0 | BS40: 1 | BT40: 1 | BU40: 1 | BV40: 1 | BW40: 1 | BX40: 1 | BZ40: 90 | CA40: 46 | CE40: 1566 | CF40: 0 | CG40: 0 | CM40: 0 | CN40: Поправка: Гл.12.Прил.8.п.8. 3_12.00.01.11.001 Наименование: При наличии напряженных и стесненных условий производства работ (стесненность, сложность складирования и транспортной логистики и т.п.) для объектов, расположенных в пределах круговой магистральной системы улиц "Садовое кольцо" города Москвы | CO40: 0 | CP40: =(P40+Q40+S40) -> 191.1 | CQ40: =ROUND((ROUND((AC40*AW40*1),2)*BC40),2) -> 4.04 | CR40: =(ROUND((ROUND((((ET40*1.2))*AV40*1),2)*BB40),2)+ROUND((ROUND(((AE40-((EU40*1.2)))*AV40*1),2)*BS40),2)) -> 4.25 | CS40: =(ROUND((ROUND((((EU40*1.2))*AV40*1),2)*BS40),2)+ROUND((ROUND(((AE40-((EU40*1.2)))*AV40*1),2)*BS40),2)) -> 0.64 | CT40: =ROUND((ROUND((AF40*AV40*1),2)*BA40),2) -> 87.26 | CU40: =AG40 -> 0 | CV40: =(AH40*AV40) -> 6.91416 | CW40: =AI40 -> 0 | CX40: =AJ40 -> 0 | CY40: =(ROUND((((S40+ROUND((ROUND((((EU40*1.2))*AV40*1),2)*BS40),2))*AT40)/100),2)+ROUND(((ROUND((ROUND(((AE40-((EU40*1.2)))*AV40*1),2)*BS40),2)*AT40)/100),2)) -> 157.64 | CZ40: =(ROUND((((S40+ROUND((ROUND((((EU40*1.2))*AV40*1),2)*BS40),2))*AU40)/100),2)+ROUND(((ROUND((ROUND(((AE40-((EU40*1.2)))*AV40*1),2)*BS40),2)*AU40)/100),2)) -> 80.57 | DB40: 13 | DD40: *1 | DE40: *1,2 | DF40: *1,2 | DG40: *1,2 | DI40: *1,2 | DJ40: *1,2 | DN40: 0 | DO40: 0 | DP40: 1 | DQ40: 1 | DU40: 1013 | DV40: 1 ШТ. | DW40: 1 ШТ. | DX40: 1 | EE40: 85133422 | EF40: 40 | EG40: Монтаж оборудования | EH40: 0 | EJ40: 2 | EK40: 73 | EL40: ТСН-2001.4-12. Технологические трубопроводы | EM40: ТСН-2001.4-12-1 | EO40: Поправка: Гл.12.Прил.8.п.8. 3_12.00.01.11.001 | EQ40: 0 | ER40: 75.4 | ES40: 3.93 | ET40: 3.32 | EU40: 0.5 | EV40: 68.15 | EW40: 5.4 | EX40: 0 | EY40: 0 | FQ40: 0 | FR40: 0 | FS40: 2 | FX40: 90 | FY40: 46 | GD40: 1 | GF40: 434457661 | GG40: 2 | GH40: 1 | GI40: 2 | GJ40: 0 | GK40: 0 | GL40: =ROUND(IF(AND(BH40=3,BI40=3,FS40<>0),P40,0),2) -> 0 | GM40: =ROUND(O40+X40+Y40,2)+GX40 -> 430.19 | GN40: =IF(OR(BI40=0,BI40=1),GM40-GX40,0) -> 0 | GO40: =IF(BI40=2,GM40-GX40,0) -> 430.19 | GP40: =IF(BI40=4,GM40-GX40,0) -> 0 | GR40: 0 | GS40: 3 | GT40: 0 | GV40: =ROUND((GT40),6) -> 0 | GW40: 1 | GX40: =ROUND(HC40*I40,2) -> 0 | HA40: 0 | HB40: 0 | HC40: =GV40*GW40 -> 0 | HS40: 0 | IK40: 0
A41: 17 | B41: 1 | C41: =ROW(SmtRes!A84) -> 84 | D41: =ROW(EtalonRes!A102) -> 102 | E41: 6 | F41: 4.12-48-11 | G41: Монтаж арматуры фланцевой с ручным приводом или без привода на номинальное давление до 4 МПа, номинальный диаметр прохода 125 мм (затвор поворотный разделительный) | H41: 1 ШТ. | I41: =ROUND(2,9) -> 2 | J41: 0 | K41: =ROUND(2,9) -> 2 | O41: =ROUND(CP41,2) -> 10015.75 | P41: =ROUND((ROUND((AC41*AW41*I41),2)*BC41),2) -> 36.28 | Q41: =(ROUND((ROUND((((ET41*1.2))*AV41*I41),2)*BB41),2)+ROUND((ROUND(((AE41-((EU41*1.2)))*AV41*I41),2)*BS41),2)) -> 145.27 | R41: =(ROUND((ROUND((((EU41*1.2))*AV41*I41),2)*BS41),2)+ROUND((ROUND(((AE41-((EU41*1.2)))*AV41*I41),2)*BS41),2)) -> 72.13 | S41: =ROUND((ROUND((AF41*AV41*I41),2)*BA41),2) -> 9834.2 | T41: =ROUND(CU41*I41,2) -> 0 | U41: =CV41*I41 -> 13.82832 | V41: =CW41*I41 -> 0 | W41: =ROUND(CX41*I41,2) -> 0 | X41: =(ROUND((((S41+ROUND((ROUND((((EU41*1.2))*AV41*I41),2)*BS41),2))*AT41)/100),2)+ROUND(((ROUND((ROUND(((AE41-((EU41*1.2)))*AV41*I41),2)*BS41),2)*AT41)/100),2)) -> 8915.7 | Y41: =(ROUND((((S41+ROUND((ROUND((((EU41*1.2))*AV41*I41),2)*BS41),2))*AU41)/100),2)+ROUND(((ROUND((ROUND(((AE41-((EU41*1.2)))*AV41*I41),2)*BS41),2)*AU41)/100),2)) -> 4556.91 | AA41: 85739207 | AB41: =ROUND((AC41+AD41+AF41),6) -> 89.694 | AC41: =ROUND(((ES41*1)),6) -> 3.93 | AD41: =ROUND(((((ET41*1.2))-((EU41*1.2)))+AE41),6) -> 3.984 | AE41: =ROUND(((EU41*1.2)),6) -> 0.6 | AF41: =ROUND(((EV41*1.2)),6) -> 81.78 | AG41: =ROUND((AP41),6) -> 0 | AH41: =((EW41*1.2)) -> 6.48 | AI41: =((EX41*1.2)) -> 0 | AJ41: =(AS41) -> 0 | AK41: 75.4 | AL41: 3.93 | AM41: 3.32 | AN41: 0.5 | AO41: 68.15 | AP41: 0 | AQ41: 5.4 | AR41: 0 | AS41: 0 | AT41: 90 | AU41: 46 | AV41: 1.067 | AW41: 1.028 | AZ41: 1 | BA41: 56.35 | BB41: 17.09 | BC41: 4.49 | BH41: 0 | BI41: 2 | BJ41: ТСН-2001.4 Доп. 68, Сб. 12, т. 48, поз. 11 | BM41: 73 | BN41: 0 | BO41: 4.12-48-11 | BP41: 1 | BQ41: 40 | BR41: 0 | BS41: 56.35 | BT41: 1 | BU41: 1 | BV41: 1 | BW41: 1 | BX41: 1 | BZ41: 90 | CA41: 46 | CE41: 1566 | CF41: 0 | CG41: 0 | CM41: 0 | CN41: Поправка: Гл.12.Прил.8.п.8. 3_12.00.01.11.001 Наименование: При наличии напряженных и стесненных условий производства работ (стесненность, сложность складирования и транспортной логистики и т.п.) для объектов, расположенных в пределах круговой магистральной системы улиц "Садовое кольцо" города Москвы | CO41: 0 | CP41: =(P41+Q41+S41) -> 10015.75 | CQ41: =ROUND((ROUND((AC41*AW41*1),2)*BC41),2) -> 18.14 | CR41: =(ROUND((ROUND((((ET41*1.2))*AV41*1),2)*BB41),2)+ROUND((ROUND(((AE41-((EU41*1.2)))*AV41*1),2)*BS41),2)) -> 72.63 | CS41: =(ROUND((ROUND((((EU41*1.2))*AV41*1),2)*BS41),2)+ROUND((ROUND(((AE41-((EU41*1.2)))*AV41*1),2)*BS41),2)) -> 36.06 | CT41: =ROUND((ROUND((AF41*AV41*1),2)*BA41),2) -> 4917.1 | CU41: =AG41 -> 0 | CV41: =(AH41*AV41) -> 6.91416 | CW41: =AI41 -> 0 | CX41: =AJ41 -> 0 | CY41: =(ROUND((((S41+ROUND((ROUND((((EU41*1.2))*AV41*1),2)*BS41),2))*AT41)/100),2)+ROUND(((ROUND((ROUND(((AE41-((EU41*1.2)))*AV41*1),2)*BS41),2)*AT41)/100),2)) -> 8883.23 | CZ41: =(ROUND((((S41+ROUND((ROUND((((EU41*1.2))*AV41*1),2)*BS41),2))*AU41)/100),2)+ROUND(((ROUND((ROUND(((AE41-((EU41*1.2)))*AV41*1),2)*BS41),2)*AU41)/100),2)) -> 4540.32 | DB41: 14 | DD41: *1 | DE41: *1,2 | DF41: *1,2 | DG41: *1,2 | DI41: *1,2 | DJ41: *1,2 | DN41: 0 | DO41: 0 | DP41: 1 | DQ41: 1 | DU41: 1013 | DV41: 1 ШТ. | DW41: 1 ШТ. | DX41: 1 | EE41: 85133422 | EF41: 40 | EG41: Монтаж оборудования | EH41: 0 | EJ41: 2 | EK41: 73 | EL41: ТСН-2001.4-12. Технологические трубопроводы | EM41: ТСН-2001.4-12-1 | EO41: Поправка: Гл.12.Прил.8.п.8. 3_12.00.01.11.001 | EQ41: 0 | ER41: 75.4 | ES41: 3.93 | ET41: 3.32 | EU41: 0.5 | EV41: 68.15 | EW41: 5.4 | EX41: 0 | EY41: 0 | FQ41: 0 | FR41: 0 | FS41: 2 | FX41: 90 | FY41: 46 | GD41: 1 | GF41: 434457661 | GG41: 2 | GH41: 1 | GI41: 2 | GJ41: 0 | GK41: 0 | GL41: =ROUND(IF(AND(BH41=3,BI41=3,FS41<>0),P41,0),2) -> 0 | GM41: =ROUND(O41+X41+Y41,2)+GX41 -> 23488.36 | GN41: =IF(OR(BI41=0,BI41=1),GM41-GX41,0) -> 0 | GO41: =IF(BI41=2,GM41-GX41,0) -> 23488.36 | GP41: =IF(BI41=4,GM41-GX41,0) -> 0 | GR41: 0 | GS41: 3 | GT41: 0 | GV41: =ROUND((GT41),6) -> 0 | GW41: 1 | GX41: =ROUND(HC41*I41,2) -> 0 | HA41: 0 | HB41: 0 | HC41: =GV41*GW41 -> 0 | HS41: 0 | IK41: 0
A42: 17 | B42: 1 | C42: =ROW(SmtRes!A86) -> 86 | D42: =ROW(EtalonRes!A106) -> 106 | E42: 7 | F42: 4.12-48-4 | G42: Монтаж арматуры фланцевой с ручным приводом или без привода на номинальное давление до 4 МПа, номинальный диаметр прохода 25 мм (обратный клапан, затвор поворотный для жокея) | H42: 1 ШТ. | I42: =ROUND(1+2,9) -> 3 | J42: 0 | K42: =ROUND(1+2,9) -> 3 | O42: =ROUND(CP42,2) -> 147.56 | P42: =ROUND((ROUND((AC42*AW42*I42),2)*BC42),2) -> 2.13 | Q42: =(ROUND((ROUND((((ET42*1.2))*AV42*I42),2)*BB42),2)+ROUND((ROUND(((AE42-((EU42*1.2)))*AV42*I42),2)*BS42),2)) -> 0 | R42: =(ROUND((ROUND((((EU42*1.2))*AV42*I42),2)*BS42),2)+ROUND((ROUND(((AE42-((EU42*1.2)))*AV42*I42),2)*BS42),2)) -> 0 | S42: =ROUND((ROUND((AF42*AV42*I42),2)*BA42),2) -> 145.43 | T42: =ROUND(CU42*I42,2) -> 0 | U42: =CV42*I42 -> 11.5236 | V42: =CW42*I42 -> 0 | W42: =ROUND(CX42*I42,2) -> 0 | X42: =(ROUND((((S42+ROUND((ROUND((((EU42*1.2))*AV42*I42),2)*BS42),2))*AT42)/100),2)+ROUND(((ROUND((ROUND(((AE42-((EU42*1.2)))*AV42*I42),2)*BS42),2)*AT42)/100),2)) -> 130.89 | Y42: =(ROUND((((S42+ROUND((ROUND((((EU42*1.2))*AV42*I42),2)*BS42),2))*AU42)/100),2)+ROUND(((ROUND((ROUND(((AE42-((EU42*1.2)))*AV42*I42),2)*BS42),2)*AU42)/100),2)) -> 66.9 | AA42: 85739205 | AB42: =ROUND((AC42+AD42+AF42),6) -> 46.122 | AC42: =ROUND(((ES42*1)),6) -> 0.69 | AD42: =ROUND(((((ET42*1.2))-((EU42*1.2)))+AE42),6) -> 0 | AE42: =ROUND(((EU42*1.2)),6) -> 0 | AF42: =ROUND(((EV42*1.2)),6) -> 45.432 | AG42: =ROUND((AP42),6) -> 0 | AH42: =((EW42*1.2)) -> 3.6 | AI42: =((EX42*1.2)) -> 0 | AJ42: =(AS42) -> 0 | AK42: 38.55 | AL42: 0.69 | AM42: 0 | AN42: 0 | AO42: 37.86 | AP42: 0 | AQ42: 3 | AR42: 0 | AS42: 0 | AT42: 90 | AU42: 46 | AV42: 1.067 | AW42: 1.028 | AZ42: 1 | BA42: 1 | BB42: 1 | BC42: 1 | BH42: 0 | BI42: 2 | BJ42: ТСН-2001.4 Доп. 67, Сб. 12, т. 48, поз. 4 | BM42: 73 | BN42: 0 | BO42: 4.12-48-4 | BP42: 1 | BQ42: 40 | BR42: 0 | BS42: 1 | BT42: 1 | BU42: 1 | BV42: 1 | BW42: 1 | BX42: 1 | BZ42: 90 | CA42: 46 | CE42: 1566 | CF42: 0 | CG42: 0 | CM42: 0 | CN42: Поправка: Гл.12.Прил.8.п.8. 3_12.00.01.11.001 Наименование: При наличии напряженных и стесненных условий производства работ (стесненность, сложность складирования и транспортной логистики и т.п.) для объектов, расположенных в пределах круговой магистральной системы улиц "Садовое кольцо" города Москвы | CO42: 0 | CP42: =(P42+Q42+S42) -> 147.56 | CQ42: =ROUND((ROUND((AC42*AW42*1),2)*BC42),2) -> 0.71 | CR42: =(ROUND((ROUND((((ET42*1.2))*AV42*1),2)*BB42),2)+ROUND((ROUND(((AE42-((EU42*1.2)))*AV42*1),2)*BS42),2)) -> 0 | CS42: =(ROUND((ROUND((((EU42*1.2))*AV42*1),2)*BS42),2)+ROUND((ROUND(((AE42-((EU42*1.2)))*AV42*1),2)*BS42),2)) -> 0 | CT42: =ROUND((ROUND((AF42*AV42*1),2)*BA42),2) -> 48.48 | CU42: =AG42 -> 0 | CV42: =(AH42*AV42) -> 3.8412 | CW42: =AI42 -> 0 | CX42: =AJ42 -> 0 | CY42: =(ROUND((((S42+ROUND((ROUND((((EU42*1.2))*AV42*1),2)*BS42),2))*AT42)/100),2)+ROUND(((ROUND((ROUND(((AE42-((EU42*1.2)))*AV42*1),2)*BS42),2)*AT42)/100),2)) -> 130.89 | CZ42: =(ROUND((((S42+ROUND((ROUND((((EU42*1.2))*AV42*1),2)*BS42),2))*AU42)/100),2)+ROUND(((ROUND((ROUND(((AE42-((EU42*1.2)))*AV42*1),2)*BS42),2)*AU42)/100),2)) -> 66.9 | DB42: 15 | DD42: *1 | DE42: *1,2 | DF42: *1,2 | DG42: *1,2 | DI42: *1,2 | DJ42: *1,2 | DN42: 0 | DO42: 0 | DP42: 1 | DQ42: 1 | DU42: 1013 | DV42: 1 ШТ. | DW42: 1 ШТ. | DX42: 1 | EE42: 85133422 | EF42: 40 | EG42: Монтаж оборудования | EH42: 0 | EJ42: 2 | EK42: 73 | EL42: ТСН-2001.4-12. Технологические трубопроводы | EM42: ТСН-2001.4-12-1 | EO42: Поправка: Гл.12.Прил.8.п.8. 3_12.00.01.11.001 | EQ42: 0 | ER42: 38.55 | ES42: 0.69 | ET42: 0 | EU42: 0 | EV42: 37.86 | EW42: 3 | EX42: 0 | EY42: 0 | FQ42: 0 | FR42: 0 | FS42: 2 | FX42: 90 | FY42: 46 | GD42: 1 | GF42: 2121044303 | GG42: 2 | GH42: 1 | GI42: 2 | GJ42: 0 | GK42: 0 | GL42: =ROUND(IF(AND(BH42=3,BI42=3,FS42<>0),P42,0),2) -> 0 | GM42: =ROUND(O42+X42+Y42,2)+GX42 -> 345.35 | GN42: =IF(OR(BI42=0,BI42=1),GM42-GX42,0) -> 0 | GO42: =IF(BI42=2,GM42-GX42,0) -> 345.35 | GP42: =IF(BI42=4,GM42-GX42,0) -> 0 | GR42: 0 | GS42: 3 | GT42: 0 | GV42: =ROUND((GT42),6) -> 0 | GW42: 1 | GX42: =ROUND(HC42*I42,2) -> 0 | HA42: 0 | HB42: 0 | HC42: =GV42*GW42 -> 0 | HS42: 0 | IK42: 0
A43: 17 | B43: 1 | C43: =ROW(SmtRes!A88) -> 88 | D43: =ROW(EtalonRes!A110) -> 110 | E43: 7 | F43: 4.12-48-4 | G43: Монтаж арматуры фланцевой с ручным приводом или без привода на номинальное давление до 4 МПа, номинальный диаметр прохода 25 мм (обратный клапан, затвор поворотный для жокея) | H43: 1 ШТ. | I43: =ROUND(1+2,9) -> 3 | J43: 0 | K43: =ROUND(1+2,9) -> 3 | O43: =ROUND(CP43,2) -> 8204.61 | P43: =ROUND((ROUND((AC43*AW43*I43),2)*BC43),2) -> 9.63 | Q43: =(ROUND((ROUND((((ET43*1.2))*AV43*I43),2)*BB43),2)+ROUND((ROUND(((AE43-((EU43*1.2)))*AV43*I43),2)*BS43),2)) -> 0 | R43: =(ROUND((ROUND((((EU43*1.2))*AV43*I43),2)*BS43),2)+ROUND((ROUND(((AE43-((EU43*1.2)))*AV43*I43),2)*BS43),2)) -> 0 | S43: =ROUND((ROUND((AF43*AV43*I43),2)*BA43),2) -> 8194.98 | T43: =ROUND(CU43*I43,2) -> 0 | U43: =CV43*I43 -> 11.5236 | V43: =CW43*I43 -> 0 | W43: =ROUND(CX43*I43,2) -> 0 | X43: =(ROUND((((S43+ROUND((ROUND((((EU43*1.2))*AV43*I43),2)*BS43),2))*AT43)/100),2)+ROUND(((ROUND((ROUND(((AE43-((EU43*1.2)))*AV43*I43),2)*BS43),2)*AT43)/100),2)) -> 7375.48 | Y43: =(ROUND((((S43+ROUND((ROUND((((EU43*1.2))*AV43*I43),2)*BS43),2))*AU43)/100),2)+ROUND(((ROUND((ROUND(((AE43-((EU43*1.2)))*AV43*I43),2)*BS43),2)*AU43)/100),2)) -> 3769.69 | AA43: 85739207 | AB43: =ROUND((AC43+AD43+AF43),6) -> 46.122 | AC43: =ROUND(((ES43*1)),6) -> 0.69 | AD43: =ROUND(((((ET43*1.2))-((EU43*1.2)))+AE43),6) -> 0 | AE43: =ROUND(((EU43*1.2)),6) -> 0 | AF43: =ROUND(((EV43*1.2)),6) -> 45.432 | AG43: =ROUND((AP43),6) -> 0 | AH43: =((EW43*1.2)) -> 3.6 | AI43: =((EX43*1.2)) -> 0 | AJ43: =(AS43) -> 0 | AK43: 38.55 | AL43: 0.69 | AM43: 0 | AN43: 0 | AO43: 37.86 | AP43: 0 | AQ43: 3 | AR43: 0 | AS43: 0 | AT43: 90 | AU43: 46 | AV43: 1.067 | AW43: 1.028 | AZ43: 1 | BA43: 56.35 | BB43: 1 | BC43: 4.52 | BH43: 0 | BI43: 2 | BJ43: ТСН-2001.4 Доп. 67, Сб. 12, т. 48, поз. 4 | BM43: 73 | BN43: 0 | BO43: 4.12-48-4 | BP43: 1 | BQ43: 40 | BR43: 0 | BS43: 56.35 | BT43: 1 | BU43: 1 | BV43: 1 | BW43: 1 | BX43: 1 | BZ43: 90 | CA43: 46 | CE43: 1566 | CF43: 0 | CG43: 0 | CM43: 0 | CN43: Поправка: Гл.12.Прил.8.п.8. 3_12.00.01.11.001 Наименование: При наличии напряженных и стесненных условий производства работ (стесненность, сложность складирования и транспортной логистики и т.п.) для объектов, расположенных в пределах круговой магистральной системы улиц "Садовое кольцо" города Москвы | CO43: 0 | CP43: =(P43+Q43+S43) -> 8204.61 | CQ43: =ROUND((ROUND((AC43*AW43*1),2)*BC43),2) -> 3.21 | CR43: =(ROUND((ROUND((((ET43*1.2))*AV43*1),2)*BB43),2)+ROUND((ROUND(((AE43-((EU43*1.2)))*AV43*1),2)*BS43),2)) -> 0 | CS43: =(ROUND((ROUND((((EU43*1.2))*AV43*1),2)*BS43),2)+ROUND((ROUND(((AE43-((EU43*1.2)))*AV43*1),2)*BS43),2)) -> 0 | CT43: =ROUND((ROUND((AF43*AV43*1),2)*BA43),2) -> 2731.85 | CU43: =AG43 -> 0 | CV43: =(AH43*AV43) -> 3.8412 | CW43: =AI43 -> 0 | CX43: =AJ43 -> 0 | CY43: =(ROUND((((S43+ROUND((ROUND((((EU43*1.2))*AV43*1),2)*BS43),2))*AT43)/100),2)+ROUND(((ROUND((ROUND(((AE43-((EU43*1.2)))*AV43*1),2)*BS43),2)*AT43)/100),2)) -> 7375.48 | CZ43: =(ROUND((((S43+ROUND((ROUND((((EU43*1.2))*AV43*1),2)*BS43),2))*AU43)/100),2)+ROUND(((ROUND((ROUND(((AE43-((EU43*1.2)))*AV43*1),2)*BS43),2)*AU43)/100),2)) -> 3769.69 | DB43: 16 | DD43: *1 | DE43: *1,2 | DF43: *1,2 | DG43: *1,2 | DI43: *1,2 | DJ43: *1,2 | DN43: 0 | DO43: 0 | DP43: 1 | DQ43: 1 | DU43: 1013 | DV43: 1 ШТ. | DW43: 1 ШТ. | DX43: 1 | EE43: 85133422 | EF43: 40 | EG43: Монтаж оборудования | EH43: 0 | EJ43: 2 | EK43: 73 | EL43: ТСН-2001.4-12. Технологические трубопроводы | EM43: ТСН-2001.4-12-1 | EO43: Поправка: Гл.12.Прил.8.п.8. 3_12.00.01.11.001 | EQ43: 0 | ER43: 38.55 | ES43: 0.69 | ET43: 0 | EU43: 0 | EV43: 37.86 | EW43: 3 | EX43: 0 | EY43: 0 | FQ43: 0 | FR43: 0 | FS43: 2 | FX43: 90 | FY43: 46 | GD43: 1 | GF43: 2121044303 | GG43: 2 | GH43: 1 | GI43: 2 | GJ43: 0 | GK43: 0 | GL43: =ROUND(IF(AND(BH43=3,BI43=3,FS43<>0),P43,0),2) -> 0 | GM43: =ROUND(O43+X43+Y43,2)+GX43 -> 19349.78 | GN43: =IF(OR(BI43=0,BI43=1),GM43-GX43,0) -> 0 | GO43: =IF(BI43=2,GM43-GX43,0) -> 19349.78 | GP43: =IF(BI43=4,GM43-GX43,0) -> 0 | GR43: 0 | GS43: 3 | GT43: 0 | GV43: =ROUND((GT43),6) -> 0 | GW43: 1 | GX43: =ROUND(HC43*I43,2) -> 0 | HA43: 0 | HB43: 0 | HC43: =GV43*GW43 -> 0 | HS43: 0 | IK43: 0
A44: 17 | B44: 1 | C44: =ROW(SmtRes!A92) -> 92 | D44: =ROW(EtalonRes!A116) -> 116 | E44: 8 | F44: 3.18-20-2 | G44: Установка манометров с трехходовым краном (реле давления, манометр) | H44: 1 комплект | I44: =ROUND(2+2+4,9) -> 8 | J44: 0 | K44: =ROUND(2+2+4,9) -> 8 | O44: =ROUND(CP44,2) -> 41.13 | P44: =ROUND((ROUND((AC44*AW44*I44),2)*BC44),2) -> 7.44 | Q44: =(ROUND((ROUND(((((ET44*1.25)*1.2))*AV44*I44),2)*BB44),2)+ROUND((ROUND(((AE44-(((EU44*1.25)*1.2)))*AV44*I44),2)*BS44),2)) -> 0 | R44: =(ROUND((ROUND(((((EU44*1.25)*1.2))*AV44*I44),2)*BS44),2)+ROUND((ROUND(((AE44-(((EU44*1.25)*1.2)))*AV44*I44),2)*BS44),2)) -> 0 | S44: =ROUND((ROUND((AF44*AV44*I44),2)*BA44),2) -> 33.69 | T44: =ROUND(CU44*I44,2) -> 0 | U44: =CV44*I44 -> 2.5915296 | V44: =CW44*I44 -> 0 | W44: =ROUND(CX44*I44,2) -> 0 | X44: =(ROUND((((S44+ROUND((ROUND(((((EU44*1.25)*1.2))*AV44*I44),2)*BS44),2))*AT44)/100),2)+ROUND(((ROUND((ROUND(((AE44-(((EU44*1.25)*1.2)))*AV44*I44),2)*BS44),2)*AT44)/100),2)) -> 40.76 | Y44: =(ROUND((((S44+ROUND((ROUND(((((EU44*1.25)*1.2))*AV44*I44),2)*BS44),2))*AU44)/100),2)+ROUND(((ROUND((ROUND(((AE44-(((EU44*1.25)*1.2)))*AV44*I44),2)*BS44),2)*AU44)/100),2)) -> 24.26 | AA44: 85739205 | AB44: =ROUND((AC44+AD44+AF44),6) -> 4.8768 | AC44: =ROUND((((ES44*1)*1)),6) -> 0.93 | AD44: =ROUND((((((ET44*1.25)*1.2))-(((EU44*1.25)*1.2)))+AE44),6) -> 0 | AE44: =ROUND((((EU44*1.25)*1.2)),6) -> 0 | AF44: =ROUND((((EV44*1.15)*1.2)),6) -> 3.9468 | AG44: =ROUND((AP44),6) -> 0 | AH44: =(((EW44*1.15)*1.2)) -> 0.3036 | AI44: =(((EX44*1.25)*1.2)) -> 0 | AJ44: =(AS44) -> 0 | AK44: 3.79 | AL44: 0.93 | AM44: 0 | AN44: 0 | AO44: 2.86 | AP44: 0 | AQ44: 0.22 | AR44: 0 | AS44: 0 | AT44: 121 | AU44: 72 | AV44: 1.067 | AW44: 1 | AZ44: 1 | BA44: 1 | BB44: 1 | BC44: 1 | BH44: 0 | BI44: 1 | BJ44: ТСН-2001.3. Доп. 1-42. Сб. 18, т. 20, поз. 2 | BM44: 23 | BN44: 0 | BO44: 3.18-20-2 | BP44: 1 | BQ44: 30 | BR44: 0 | BS44: 1 | BT44: 1 | BU44: 1 | BV44: 1 | BW44: 1 | BX44: 1 | BZ44: 121 | CA44: 72 | CE44: 1566 | CF44: 0 | CG44: 0 | CM44: 0 | CN44: Поправка: Гл.6.Прил.2.2.п.2.2.6_06.00.01.07.001 Наименование: При выполнении при капитальном ремонте и реконструкции работ, аналогичных технологическим процессам, характерным для нового строительства, и отсутствующих в сборниках на ремонтно-строительные работы ТСН-2001.6 Поправка: Гл.12.Прил.8.п.8. 3_12.00.01.11.001 Наименование: При наличии напряженных и стесненных условий производства работ (стесненность, сложность складирования и транспортной логистики и т.п.) для объектов, расположенных в пределах круговой магистральной системы улиц "Садовое кольцо" города Москвы | CO44: 0 | CP44: =(P44+Q44+S44) -> 41.13 | CQ44: =ROUND((ROUND((AC44*AW44*1),2)*BC44),2) -> 0.93 | CR44: =(ROUND((ROUND(((((ET44*1.25)*1.2))*AV44*1),2)*BB44),2)+ROUND((ROUND(((AE44-(((EU44*1.25)*1.2)))*AV44*1),2)*BS44),2)) -> 0 | CS44: =(ROUND((ROUND(((((EU44*1.25)*1.2))*AV44*1),2)*BS44),2)+ROUND((ROUND(((AE44-(((EU44*1.25)*1.2)))*AV44*1),2)*BS44),2)) -> 0 | CT44: =ROUND((ROUND((AF44*AV44*1),2)*BA44),2) -> 4.21 | CU44: =AG44 -> 0 | CV44: =(AH44*AV44) -> 0.3239412 | CW44: =AI44 -> 0 | CX44: =AJ44 -> 0 | CY44: =(ROUND((((S44+ROUND((ROUND(((((EU44*1.25)*1.2))*AV44*1),2)*BS44),2))*AT44)/100),2)+ROUND(((ROUND((ROUND(((AE44-(((EU44*1.25)*1.2)))*AV44*1),2)*BS44),2)*AT44)/100),2)) -> 40.76 | CZ44: =(ROUND((((S44+ROUND((ROUND(((((EU44*1.25)*1.2))*AV44*1),2)*BS44),2))*AU44)/100),2)+ROUND(((ROUND((ROUND(((AE44-(((EU44*1.25)*1.2)))*AV44*1),2)*BS44),2)*AU44)/100),2)) -> 24.26 | DB44: 17 | DD44: *1)*1 | DE44: *1,25)*1,2 | DF44: *1,25)*1,2 | DG44: *1,15)*1,2 | DI44: *1,15)*1,2 | DJ44: *1,25)*1,2 | DN44: 0 | DO44: 0 | DP44: 1 | DQ44: 1 | DU44: 1013 | DV44: 1 комплект | DW44: 1 комплект | DX44: 1 | EE44: 85133369 | EF44: 30 | EG44: Строительные работы | EH44: 0 | EJ44: 1 | EK44: 23 | EL44: ТСН-2001.3-18. Отопление - внутренние устройства | EM44: ТСН-2001.3-18-1 | EO44: Поправка: Гл.6.Прил.2.2.п.2.2.6_06.00.01.07.001 Поправка: Гл.12.Прил.8.п.8. 3_12.00.01.11.001 | EQ44: 0 | ER44: 3.79 | ES44: 0.93 | ET44: 0 | EU44: 0 | EV44: 2.86 | EW44: 0.22 | EX44: 0 | EY44: 0 | FQ44: 0 | FR44: 0 | FS44: 0 | FX44: 121 | FY44: 72 | GD44: 1 | GF44: 2014171460 | GG44: 2 | GH44: 1 | GI44: 2 | GJ44: 0 | GK44: 0 | GL44: =ROUND(IF(AND(BH44=3,BI44=3,FS44<>0),P44,0),2) -> 0 | GM44: =ROUND(O44+X44+Y44,2)+GX44 -> 106.15 | GN44: =IF(OR(BI44=0,BI44=1),GM44-GX44,0) -> 106.15 | GO44: =IF(BI44=2,GM44-GX44,0) -> 0 | GP44: =IF(BI44=4,GM44-GX44,0) -> 0 | GR44: 0 | GS44: 3 | GT44: 0 | GV44: =ROUND((GT44),6) -> 0 | GW44: 1 | GX44: =ROUND(HC44*I44,2) -> 0 | HA44: 0 | HB44: 0 | HC44: =GV44*GW44 -> 0 | HS44: 0 | IK44: 0
A45: 17 | B45: 1 | C45: =ROW(SmtRes!A96) -> 96 | D45: =ROW(EtalonRes!A122) -> 122 | E45: 8 | F45: 3.18-20-2 | G45: Установка манометров с трехходовым краном (реле давления, манометр) | H45: 1 комплект | I45: =ROUND(2+2+4,9) -> 8 | J45: 0 | K45: =ROUND(2+2+4,9) -> 8 | O45: =ROUND(CP45,2) -> 1939.13 | P45: =ROUND((ROUND((AC45*AW45*I45),2)*BC45),2) -> 40.7 | Q45: =(ROUND((ROUND(((((ET45*1.25)*1.2))*AV45*I45),2)*BB45),2)+ROUND((ROUND(((AE45-(((EU45*1.25)*1.2)))*AV45*I45),2)*BS45),2)) -> 0 | R45: =(ROUND((ROUND(((((EU45*1.25)*1.2))*AV45*I45),2)*BS45),2)+ROUND((ROUND(((AE45-(((EU45*1.25)*1.2)))*AV45*I45),2)*BS45),2)) -> 0 | S45: =ROUND((ROUND((AF45*AV45*I45),2)*BA45),2) -> 1898.43 | T45: =ROUND(CU45*I45,2) -> 0 | U45: =CV45*I45 -> 2.5915296 | V45: =CW45*I45 -> 0 | W45: =ROUND(CX45*I45,2) -> 0 | X45: =(ROUND((((S45+ROUND((ROUND(((((EU45*1.25)*1.2))*AV45*I45),2)*BS45),2))*AT45)/100),2)+ROUND(((ROUND((ROUND(((AE45-(((EU45*1.25)*1.2)))*AV45*I45),2)*BS45),2)*AT45)/100),2)) -> 2297.1 | Y45: =(ROUND((((S45+ROUND((ROUND(((((EU45*1.25)*1.2))*AV45*I45),2)*BS45),2))*AU45)/100),2)+ROUND(((ROUND((ROUND(((AE45-(((EU45*1.25)*1.2)))*AV45*I45),2)*BS45),2)*AU45)/100),2)) -> 1366.87 | AA45: 85739207 | AB45: =ROUND((AC45+AD45+AF45),6) -> 4.8768 | AC45: =ROUND((((ES45*1)*1)),6) -> 0.93 | AD45: =ROUND((((((ET45*1.25)*1.2))-(((EU45*1.25)*1.2)))+AE45),6) -> 0 | AE45: =ROUND((((EU45*1.25)*1.2)),6) -> 0 | AF45: =ROUND((((EV45*1.15)*1.2)),6) -> 3.9468 | AG45: =ROUND((AP45),6) -> 0 | AH45: =(((EW45*1.15)*1.2)) -> 0.3036 | AI45: =(((EX45*1.25)*1.2)) -> 0 | AJ45: =(AS45) -> 0 | AK45: 3.79 | AL45: 0.93 | AM45: 0 | AN45: 0 | AO45: 2.86 | AP45: 0 | AQ45: 0.22 | AR45: 0 | AS45: 0 | AT45: 121 | AU45: 72 | AV45: 1.067 | AW45: 1 | AZ45: 1 | BA45: 56.35 | BB45: 1 | BC45: 5.47 | BH45: 0 | BI45: 1 | BJ45: ТСН-2001.3. Доп. 1-42. Сб. 18, т. 20, поз. 2 | BM45: 23 | BN45: 0 | BO45: 3.18-20-2 | BP45: 1 | BQ45: 30 | BR45: 0 | BS45: 56.35 | BT45: 1 | BU45: 1 | BV45: 1 | BW45: 1 | BX45: 1 | BZ45: 121 | CA45: 72 | CE45: 1566 | CF45: 0 | CG45: 0 | CM45: 0 | CN45: Поправка: Гл.6.Прил.2.2.п.2.2.6_06.00.01.07.001 Наименование: При выполнении при капитальном ремонте и реконструкции работ, аналогичных технологическим процессам, характерным для нового строительства, и отсутствующих в сборниках на ремонтно-строительные работы ТСН-2001.6 Поправка: Гл.12.Прил.8.п.8. 3_12.00.01.11.001 Наименование: При наличии напряженных и стесненных условий производства работ (стесненность, сложность складирования и транспортной логистики и т.п.) для объектов, расположенных в пределах круговой магистральной системы улиц "Садовое кольцо" города Москвы | CO45: 0 | CP45: =(P45+Q45+S45) -> 1939.13 | CQ45: =ROUND((ROUND((AC45*AW45*1),2)*BC45),2) -> 5.09 | CR45: =(ROUND((ROUND(((((ET45*1.25)*1.2))*AV45*1),2)*BB45),2)+ROUND((ROUND(((AE45-(((EU45*1.25)*1.2)))*AV45*1),2)*BS45),2)) -> 0 | CS45: =(ROUND((ROUND(((((EU45*1.25)*1.2))*AV45*1),2)*BS45),2)+ROUND((ROUND(((AE45-(((EU45*1.25)*1.2)))*AV45*1),2)*BS45),2)) -> 0 | CT45: =ROUND((ROUND((AF45*AV45*1),2)*BA45),2) -> 237.23 | CU45: =AG45 -> 0 | CV45: =(AH45*AV45) -> 0.3239412 | CW45: =AI45 -> 0 | CX45: =AJ45 -> 0 | CY45: =(ROUND((((S45+ROUND((ROUND(((((EU45*1.25)*1.2))*AV45*1),2)*BS45),2))*AT45)/100),2)+ROUND(((ROUND((ROUND(((AE45-(((EU45*1.25)*1.2)))*AV45*1),2)*BS45),2)*AT45)/100),2)) -> 2297.1 | CZ45: =(ROUND((((S45+ROUND((ROUND(((((EU45*1.25)*1.2))*AV45*1),2)*BS45),2))*AU45)/100),2)+ROUND(((ROUND((ROUND(((AE45-(((EU45*1.25)*1.2)))*AV45*1),2)*BS45),2)*AU45)/100),2)) -> 1366.87 | DB45: 19 | DD45: *1)*1 | DE45: *1,25)*1,2 | DF45: *1,25)*1,2 | DG45: *1,15)*1,2 | DI45: *1,15)*1,2 | DJ45: *1,25)*1,2 | DN45: 0 | DO45: 0 | DP45: 1 | DQ45: 1 | DU45: 1013 | DV45: 1 комплект | DW45: 1 комплект | DX45: 1 | EE45: 85133369 | EF45: 30 | EG45: Строительные работы | EH45: 0 | EJ45: 1 | EK45: 23 | EL45: ТСН-2001.3-18. Отопление - внутренние устройства | EM45: ТСН-2001.3-18-1 | EO45: Поправка: Гл.6.Прил.2.2.п.2.2.6_06.00.01.07.001 Поправка: Гл.12.Прил.8.п.8. 3_12.00.01.11.001 | EQ45: 0 | ER45: 3.79 | ES45: 0.93 | ET45: 0 | EU45: 0 | EV45: 2.86 | EW45: 0.22 | EX45: 0 | EY45: 0 | FQ45: 0 | FR45: 0 | FS45: 0 | FX45: 121 | FY45: 72 | GD45: 1 | GF45: 2014171460 | GG45: 2 | GH45: 1 | GI45: 2 | GJ45: 0 | GK45: 0 | GL45: =ROUND(IF(AND(BH45=3,BI45=3,FS45<>0),P45,0),2) -> 0 | GM45: =ROUND(O45+X45+Y45,2)+GX45 -> 5603.1 | GN45: =IF(OR(BI45=0,BI45=1),GM45-GX45,0) -> 5603.1 | GO45: =IF(BI45=2,GM45-GX45,0) -> 0 | GP45: =IF(BI45=4,GM45-GX45,0) -> 0 | GR45: 0 | GS45: 3 | GT45: 0 | GV45: =ROUND((GT45),6) -> 0 | GW45: 1 | GX45: =ROUND(HC45*I45,2) -> 0 | HA45: 0 | HB45: 0 | HC45: =GV45*GW45 -> 0 | HS45: 0 | IK45: 0
A46: 17 | B46: 1 | E46: 9 | F46: КА. п. 1 | G46: Насосная установка пожаротушения Q-66,38 (м3/ч), H- 25,0 м.в.ст., Жокей насос Q-3.0 (м3/ч),H- 30,0 м.в.ст., комплектно со шкафом автоматического управления ШУПН-3-С ОН/РН/ЖН-18,5/18,5/1,5-УПП/УПП/П-В и комплектно с выносной панелью индикации ВП | H46: компл. | I46: 1 | J46: 0 | K46: 1 | O46: =ROUND(CP46,2) -> 227909.79 | P46: =ROUND((ROUND((AC46*I46),2)*BC46),2) -> 227909.79 | Q46: =(ROUND((ROUND(((ET46)*AV46*I46),2)*BB46),2)+ROUND((ROUND(((AE46-(EU46))*AV46*I46),2)*BS46),2)) -> 0 | R46: =(ROUND((ROUND(((EU46)*AV46*I46),2)*BS46),2)+ROUND((ROUND(((AE46-(EU46))*AV46*I46),2)*BS46),2)) -> 0 | S46: =ROUND((ROUND((AF46*AV46*I46),2)*BA46),2) -> 0 | T46: =ROUND(CU46*I46,2) -> 0 | U46: =CV46*I46 -> 0 | V46: =CW46*I46 -> 0 | W46: =ROUND(CX46*I46,2) -> 0 | X46: =(ROUND((((S46+ROUND((ROUND(((EU46)*AV46*I46),2)*BS46),2))*AT46)/100),2)+ROUND(((ROUND((ROUND(((AE46-(EU46))*AV46*I46),2)*BS46),2)*AT46)/100),2)) -> 0 | Y46: =(ROUND((((S46+ROUND((ROUND(((EU46)*AV46*I46),2)*BS46),2))*AU46)/100),2)+ROUND(((ROUND((ROUND(((AE46-(EU46))*AV46*I46),2)*BS46),2)*AU46)/100),2)) -> 0 | AA46: 85739205 | AB46: =ROUND((AC46+AD46+AF46),6) -> 227909.79 | AC46: =ROUND((ES46),6) -> 227909.79 | AD46: =ROUND((((ET46)-(EU46))+AE46),6) -> 0 | AE46: =ROUND((EU46),6) -> 0 | AF46: =ROUND((EV46),6) -> 0 | AG46: =ROUND((AP46),6) -> 0 | AH46: =(EW46) -> 0 | AI46: =(EX46) -> 0 | AJ46: =(AS46) -> 0 | AK46: 227909.79 | AL46: 227909.79 | AM46: 0 | AN46: 0 | AO46: 0 | AP46: 0 | AQ46: 0 | AR46: 0 | AS46: 0 | AT46: 0 | AU46: 0 | AV46: 1 | AW46: 1 | AZ46: 1 | BA46: 1 | BB46: 1 | BC46: 1 | BH46: 3 | BI46: 3 | BM46: 746 | BN46: 0 | BP46: 0 | BQ46: 130 | BR46: 0 | BS46: 1 | BT46: 1 | BU46: 1 | BV46: 1 | BW46: 1 | BX46: 1 | BZ46: 0 | CA46: 0 | CE46: 1566 | CF46: 0 | CG46: 0 | CM46: 0 | CN46: Поправка: Гл.4.Прил.2.2.п.2.2.17_04.00.01.24.001_x000D_ Наименование: При разнице в массе оборудования более 10% к норме и расценке ближайшего по массе оборудования при коэффициенте изменения массы оборудования до 0,5 т | CO46: 0 | CP46: =(P46+Q46+S46) -> 227909.79 | CQ46: =ROUND((ROUND((AC46*1),2)*BC46),2) -> 227909.79 | CR46: =(ROUND((ROUND(((ET46)*AV46*1),2)*BB46),2)+ROUND((ROUND(((AE46-(EU46))*AV46*1),2)*BS46),2)) -> 0 | CS46: =(ROUND((ROUND(((EU46)*AV46*1),2)*BS46),2)+ROUND((ROUND(((AE46-(EU46))*AV46*1),2)*BS46),2)) -> 0 | CT46: =ROUND((ROUND((AF46*AV46*1),2)*BA46),2) -> 0 | CU46: =AG46 -> 0 | CV46: =(AH46*AV46) -> 0 | CW46: =AI46 -> 0 | CX46: =AJ46 -> 0 | CY46: =(ROUND((((S46+ROUND((ROUND(((EU46)*AV46*1),2)*BS46),2))*AT46)/100),2)+ROUND(((ROUND((ROUND(((AE46-(EU46))*AV46*1),2)*BS46),2)*AT46)/100),2)) -> 0 | CZ46: =(ROUND((((S46+ROUND((ROUND(((EU46)*AV46*1),2)*BS46),2))*AU46)/100),2)+ROUND(((ROUND((ROUND(((AE46-(EU46))*AV46*1),2)*BS46),2)*AU46)/100),2)) -> 0 | DN46: 0 | DO46: 0 | DP46: 1 | DQ46: 1 | DU46: 1013 | DV46: компл. | DW46: компл. | DX46: 1 | EE46: 85133523 | EF46: 130 | EG46: Сметная стоимость оборудования | EH46: 0 | EJ46: 3 | EK46: 746 | EL46: ТСН-2001.13. Сметная стоимость оборудования | EM46: ТСН-2001.13 | EO46: Поправка: Гл.4.Прил.2.2.п.2.2.17_04.00.01.24.001 | EQ46: 2097152 | ER46: 0 | ES46: 227909.79 | ET46: 0 | EU46: 0 | EV46: 0 | EW46: 0 | EX46: 0 | EY46: 0 | FQ46: 0 | FR46: =P46 -> 227909.79 | FS46: 0 | FX46: 0 | FY46: 0 | GD46: 1 | GF46: -1036281574 | GG46: 2 | GH46: 4 | GI46: -2 | GJ46: 0 | GK46: 0 | GL46: =ROUND(IF(AND(BH46=3,BI46=3,FS46<>0),P46,0),2) -> 0 | GM46: =ROUND(O46+X46+Y46,2)+GX46 -> 227909.79 | GN46: =IF(OR(BI46=0,BI46=1),GM46-GX46,0) -> 0 | GO46: =IF(BI46=2,GM46-GX46,0) -> 0 | GP46: =IF(BI46=4,GM46-GX46,0) -> 0 | GR46: 0 | GS46: 2 | GT46: 0 | GV46: =ROUND((GT46),6) -> 0 | GW46: 1 | GX46: =ROUND(HC46*I46,2) -> 0 | HA46: 0 | HB46: 0 | HC46: =GV46*GW46 -> 0 | HS46: 0 | IK46: 0
A47: 17 | B47: 1 | E47: 9 | F47: КА. п. 1 | G47: Насосная установка пожаротушения Q-66,38 (м3/ч), H- 25,0 м.в.ст., Жокей насос Q-3.0 (м3/ч),H- 30,0 м.в.ст., комплектно со шкафом автоматического управления ШУПН-3-С ОН/РН/ЖН-18,5/18,5/1,5-УПП/УПП/П-В и комплектно с выносной панелью индикации ВП | H47: компл. | I47: 1 | J47: 0 | K47: 1 | O47: =ROUND(CP47,2) -> 1816013.2 | P47: =ROUND((ROUND((AC47*I47),2)*BC47),2) -> 1816013.2 | Q47: =(ROUND((ROUND(((ET47)*AV47*I47),2)*BB47),2)+ROUND((ROUND(((AE47-(EU47))*AV47*I47),2)*BS47),2)) -> 0 | R47: =(ROUND((ROUND(((EU47)*AV47*I47),2)*BS47),2)+ROUND((ROUND(((AE47-(EU47))*AV47*I47),2)*BS47),2)) -> 0 | S47: =ROUND((ROUND((AF47*AV47*I47),2)*BA47),2) -> 0 | T47: =ROUND(CU47*I47,2) -> 0 | U47: =CV47*I47 -> 0 | V47: =CW47*I47 -> 0 | W47: =ROUND(CX47*I47,2) -> 0 | X47: =(ROUND((((S47+ROUND((ROUND(((EU47)*AV47*I47),2)*BS47),2))*AT47)/100),2)+ROUND(((ROUND((ROUND(((AE47-(EU47))*AV47*I47),2)*BS47),2)*AT47)/100),2)) -> 0 | Y47: =(ROUND((((S47+ROUND((ROUND(((EU47)*AV47*I47),2)*BS47),2))*AU47)/100),2)+ROUND(((ROUND((ROUND(((AE47-(EU47))*AV47*I47),2)*BS47),2)*AU47)/100),2)) -> 0 | AA47: 85739207 | AB47: =ROUND((AC47+AD47+AF47),6) -> 239896.07 | AC47: =ROUND((ES47),6) -> 239896.07 | AD47: =ROUND((((ET47)-(EU47))+AE47),6) -> 0 | AE47: =ROUND((EU47),6) -> 0 | AF47: =ROUND((EV47),6) -> 0 | AG47: =ROUND((AP47),6) -> 0 | AH47: =(EW47) -> 0 | AI47: =(EX47) -> 0 | AJ47: =(AS47) -> 0 | AK47: 239896.07 | AL47: 239896.07 | AM47: 0 | AN47: 0 | AO47: 0 | AP47: 0 | AQ47: 0 | AR47: 0 | AS47: 0 | AT47: 0 | AU47: 0 | AV47: 1 | AW47: 1 | AZ47: 1 | BA47: 1 | BB47: 1 | BC47: 7.57 | BH47: 3 | BI47: 3 | BM47: 746 | BN47: 0 | BP47: 0 | BQ47: 130 | BR47: 0 | BS47: 1 | BT47: 1 | BU47: 1 | BV47: 1 | BW47: 1 | BX47: 1 | BZ47: 0 | CA47: 0 | CE47: 1566 | CF47: 0 | CG47: 0 | CM47: 0 | CN47: Поправка: Гл.4.Прил.2.2.п.2.2.17_04.00.01.24.001_x000D_ Наименование: При разнице в массе оборудования более 10% к норме и расценке ближайшего по массе оборудования при коэффициенте изменения массы оборудования до 0,5 т | CO47: 0 | CP47: =(P47+Q47+S47) -> 1816013.2 | CQ47: =ROUND((ROUND((AC47*1),2)*BC47),2) -> 1816013.2 | CR47: =(ROUND((ROUND(((ET47)*AV47*1),2)*BB47),2)+ROUND((ROUND(((AE47-(EU47))*AV47*1),2)*BS47),2)) -> 0 | CS47: =(ROUND((ROUND(((EU47)*AV47*1),2)*BS47),2)+ROUND((ROUND(((AE47-(EU47))*AV47*1),2)*BS47),2)) -> 0 | CT47: =ROUND((ROUND((AF47*AV47*1),2)*BA47),2) -> 0 | CU47: =AG47 -> 0 | CV47: =(AH47*AV47) -> 0 | CW47: =AI47 -> 0 | CX47: =AJ47 -> 0 | CY47: =(ROUND((((S47+ROUND((ROUND(((EU47)*AV47*1),2)*BS47),2))*AT47)/100),2)+ROUND(((ROUND((ROUND(((AE47-(EU47))*AV47*1),2)*BS47),2)*AT47)/100),2)) -> 0 | CZ47: =(ROUND((((S47+ROUND((ROUND(((EU47)*AV47*1),2)*BS47),2))*AU47)/100),2)+ROUND(((ROUND((ROUND(((AE47-(EU47))*AV47*1),2)*BS47),2)*AU47)/100),2)) -> 0 | DN47: 0 | DO47: 0 | DP47: 1 | DQ47: 1 | DU47: 1013 | DV47: компл. | DW47: компл. | DX47: 1 | EE47: 85133523 | EF47: 130 | EG47: Сметная стоимость оборудования | EH47: 0 | EJ47: 3 | EK47: 746 | EL47: ТСН-2001.13. Сметная стоимость оборудования | EM47: ТСН-2001.13 | EO47: Поправка: Гл.4.Прил.2.2.п.2.2.17_04.00.01.24.001 | EQ47: 2097152 | ER47: 239896.07 | ES47: 239896.07 | ET47: 0 | EU47: 0 | EV47: 0 | EW47: 0 | EX47: 0 | EY47: 0 | EZ47: 5 | FC47: 1 | FD47: 18 | FF47: 2125500 | FQ47: 0 | FR47: =P47 -> 1816013.2 | FS47: 0 | FX47: 0 | FY47: 0 | GA47: [2 125 500 / 1,22 / 7,57] + 3% Трансп + 1,2% Заг.скл | GD47: 1 | GF47: -1036281574 | GG47: 2 | GH47: 3 | GI47: 5 | GJ47: 0 | GK47: 0 | GL47: =ROUND(IF(AND(BH47=3,BI47=3,FS47<>0),P47,0),2) -> 0 | GM47: =ROUND(O47+X47+Y47,2)+GX47 -> 1816013.2 | GN47: =IF(OR(BI47=0,BI47=1),GM47-GX47,0) -> 0 | GO47: =IF(BI47=2,GM47-GX47,0) -> 0 | GP47: =IF(BI47=4,GM47-GX47,0) -> 0 | GR47: 1 | GS47: 1 | GT47: 0 | GV47: =ROUND((GT47),6) -> 0 | GW47: 1 | GX47: =ROUND(HC47*I47,2) -> 0 | HA47: 0 | HB47: 0 | HC47: =GV47*GW47 -> 0 | HE47: 3 | HF47: 1,2 | HS47: 0 | IK47: 0
A48: 17 | B48: 1 | C48: =ROW(SmtRes!A100) -> 100 | D48: =ROW(EtalonRes!A127) -> 127 | E48: 10 | F48: 4.12-50-6 | G48: Монтаж арматуры фланцевой с электрическим приводом на номинальное давление до 4 МПа, номинальный диаметр прохода 100 мм | H48: 1 ШТ. | I48: 1 | J48: 0 | K48: 1 | O48: =ROUND(CP48,2) -> 102.49 | P48: =ROUND((ROUND((AC48*AW48*I48),2)*BC48),2) -> 4.04 | Q48: =(ROUND((ROUND((((ET48*1.2))*AV48*I48),2)*BB48),2)+ROUND((ROUND(((AE48-((EU48*1.2)))*AV48*I48),2)*BS48),2)) -> 9.58 | R48: =(ROUND((ROUND((((EU48*1.2))*AV48*I48),2)*BS48),2)+ROUND((ROUND(((AE48-((EU48*1.2)))*AV48*I48),2)*BS48),2)) -> 1.46 | S48: =ROUND((ROUND((AF48*AV48*I48),2)*BA48),2) -> 88.87 | T48: =ROUND(CU48*I48,2) -> 0 | U48: =CV48*I48 -> 7.0422 | V48: =CW48*I48 -> 0 | W48: =ROUND(CX48*I48,2) -> 0 | X48: =(ROUND((((S48+ROUND((ROUND((((EU48*1.2))*AV48*I48),2)*BS48),2))*AT48)/100),2)+ROUND(((ROUND((ROUND(((AE48-((EU48*1.2)))*AV48*I48),2)*BS48),2)*AT48)/100),2)) -> 81.3 | Y48: =(ROUND((((S48+ROUND((ROUND((((EU48*1.2))*AV48*I48),2)*BS48),2))*AU48)/100),2)+ROUND(((ROUND((ROUND(((AE48-((EU48*1.2)))*AV48*I48),2)*BS48),2)*AU48)/100),2)) -> 41.55 | AA48: 85739205 | AB48: =ROUND((AC48+AD48+AF48),6) -> 96.198 | AC48: =ROUND(((ES48*1)),6) -> 3.93 | AD48: =ROUND(((((ET48*1.2))-((EU48*1.2)))+AE48),6) -> 8.976 | AE48: =ROUND(((EU48*1.2)),6) -> 1.368 | AF48: =ROUND(((EV48*1.2)),6) -> 83.292 | AG48: =ROUND((AP48),6) -> 0 | AH48: =((EW48*1.2)) -> 6.6 | AI48: =((EX48*1.2)) -> 0 | AJ48: =(AS48) -> 0 | AK48: 80.82 | AL48: 3.93 | AM48: 7.48 | AN48: 1.14 | AO48: 69.41 | AP48: 0 | AQ48: 5.5 | AR48: 0 | AS48: 0 | AT48: 90 | AU48: 46 | AV48: 1.067 | AW48: 1.028 | AZ48: 1 | BA48: 1 | BB48: 1 | BC48: 1 | BH48: 0 | BI48: 2 | BJ48: ТСН-2001.4 Доп. 68, Сб. 12, т. 50, поз. 6 | BM48: 73 | BN48: 0 | BO48: 4.12-50-6 | BP48: 1 | BQ48: 40 | BR48: 0 | BS48: 1 | BT48: 1 | BU48: 1 | BV48: 1 | BW48: 1 | BX48: 1 | BZ48: 90 | CA48: 46 | CE48: 1566 | CF48: 0 | CG48: 0 | CM48: 0 | CN48: Поправка: Гл.12.Прил.8.п.8. 3_12.00.01.11.001 Наименование: При наличии напряженных и стесненных условий производства работ (стесненность, сложность складирования и транспортной логистики и т.п.) для объектов, расположенных в пределах круговой магистральной системы улиц "Садовое кольцо" города Москвы | CO48: 0 | CP48: =(P48+Q48+S48) -> 102.49 | CQ48: =ROUND((ROUND((AC48*AW48*1),2)*BC48),2) -> 4.04 | CR48: =(ROUND((ROUND((((ET48*1.2))*AV48*1),2)*BB48),2)+ROUND((ROUND(((AE48-((EU48*1.2)))*AV48*1),2)*BS48),2)) -> 9.58 | CS48: =(ROUND((ROUND((((EU48*1.2))*AV48*1),2)*BS48),2)+ROUND((ROUND(((AE48-((EU48*1.2)))*AV48*1),2)*BS48),2)) -> 1.46 | CT48: =ROUND((ROUND((AF48*AV48*1),2)*BA48),2) -> 88.87 | CU48: =AG48 -> 0 | CV48: =(AH48*AV48) -> 7.0422 | CW48: =AI48 -> 0 | CX48: =AJ48 -> 0 | CY48: =(ROUND((((S48+ROUND((ROUND((((EU48*1.2))*AV48*1),2)*BS48),2))*AT48)/100),2)+ROUND(((ROUND((ROUND(((AE48-((EU48*1.2)))*AV48*1),2)*BS48),2)*AT48)/100),2)) -> 81.3 | CZ48: =(ROUND((((S48+ROUND((ROUND((((EU48*1.2))*AV48*1),2)*BS48),2))*AU48)/100),2)+ROUND(((ROUND((ROUND(((AE48-((EU48*1.2)))*AV48*1),2)*BS48),2)*AU48)/100),2)) -> 41.55 | DB48: 21 | DD48: *1 | DE48: *1,2 | DF48: *1,2 | DG48: *1,2 | DI48: *1,2 | DJ48: *1,2 | DN48: 0 | DO48: 0 | DP48: 1 | DQ48: 1 | DU48: 1013 | DV48: 1 ШТ. | DW48: 1 ШТ. | DX48: 1 | EE48: 85133422 | EF48: 40 | EG48: Монтаж оборудования | EH48: 0 | EJ48: 2 | EK48: 73 | EL48: ТСН-2001.4-12. Технологические трубопроводы | EM48: ТСН-2001.4-12-1 | EO48: Поправка: Гл.12.Прил.8.п.8. 3_12.00.01.11.001 | EQ48: 0 | ER48: 80.82 | ES48: 3.93 | ET48: 7.48 | EU48: 1.14 | EV48: 69.41 | EW48: 5.5 | EX48: 0 | EY48: 0 | FQ48: 0 | FR48: 0 | FS48: 2 | FX48: 90 | FY48: 46 | GD48: 1 | GF48: -355409604 | GG48: 2 | GH48: 1 | GI48: 2 | GJ48: 0 | GK48: 0 | GL48: =ROUND(IF(AND(BH48=3,BI48=3,FS48<>0),P48,0),2) -> 0 | GM48: =ROUND(O48+X48+Y48,2)+GX48 -> 225.34 | GN48: =IF(OR(BI48=0,BI48=1),GM48-GX48,0) -> 0 | GO48: =IF(BI48=2,GM48-GX48,0) -> 225.34 | GP48: =IF(BI48=4,GM48-GX48,0) -> 0 | GR48: 0 | GS48: 3 | GT48: 0 | GV48: =ROUND((GT48),6) -> 0 | GW48: 1 | GX48: =ROUND(HC48*I48,2) -> 0 | HA48: 0 | HB48: 0 | HC48: =GV48*GW48 -> 0 | HS48: 0 | IK48: 0
A49: 17 | B49: 1 | C49: =ROW(SmtRes!A104) -> 104 | D49: =ROW(EtalonRes!A132) -> 132 | E49: 10 | F49: 4.12-50-6 | G49: Монтаж арматуры фланцевой с электрическим приводом на номинальное давление до 4 МПа, номинальный диаметр прохода 100 мм | H49: 1 ШТ. | I49: 1 | J49: 0 | K49: 1 | O49: =ROUND(CP49,2) -> 5189.49 | P49: =ROUND((ROUND((AC49*AW49*I49),2)*BC49),2) -> 18.14 | Q49: =(ROUND((ROUND((((ET49*1.2))*AV49*I49),2)*BB49),2)+ROUND((ROUND(((AE49-((EU49*1.2)))*AV49*I49),2)*BS49),2)) -> 163.53 | R49: =(ROUND((ROUND((((EU49*1.2))*AV49*I49),2)*BS49),2)+ROUND((ROUND(((AE49-((EU49*1.2)))*AV49*I49),2)*BS49),2)) -> 82.27 | S49: =ROUND((ROUND((AF49*AV49*I49),2)*BA49),2) -> 5007.82 | T49: =ROUND(CU49*I49,2) -> 0 | U49: =CV49*I49 -> 7.0422 | V49: =CW49*I49 -> 0 | W49: =ROUND(CX49*I49,2) -> 0 | X49: =(ROUND((((S49+ROUND((ROUND((((EU49*1.2))*AV49*I49),2)*BS49),2))*AT49)/100),2)+ROUND(((ROUND((ROUND(((AE49-((EU49*1.2)))*AV49*I49),2)*BS49),2)*AT49)/100),2)) -> 4581.08 | Y49: =(ROUND((((S49+ROUND((ROUND((((EU49*1.2))*AV49*I49),2)*BS49),2))*AU49)/100),2)+ROUND(((ROUND((ROUND(((AE49-((EU49*1.2)))*AV49*I49),2)*BS49),2)*AU49)/100),2)) -> 2341.44 | AA49: 85739207 | AB49: =ROUND((AC49+AD49+AF49),6) -> 96.198 | AC49: =ROUND(((ES49*1)),6) -> 3.93 | AD49: =ROUND(((((ET49*1.2))-((EU49*1.2)))+AE49),6) -> 8.976 | AE49: =ROUND(((EU49*1.2)),6) -> 1.368 | AF49: =ROUND(((EV49*1.2)),6) -> 83.292 | AG49: =ROUND((AP49),6) -> 0 | AH49: =((EW49*1.2)) -> 6.6 | AI49: =((EX49*1.2)) -> 0 | AJ49: =(AS49) -> 0 | AK49: 80.82 | AL49: 3.93 | AM49: 7.48 | AN49: 1.14 | AO49: 69.41 | AP49: 0 | AQ49: 5.5 | AR49: 0 | AS49: 0 | AT49: 90 | AU49: 46 | AV49: 1.067 | AW49: 1.028 | AZ49: 1 | BA49: 56.35 | BB49: 17.07 | BC49: 4.49 | BH49: 0 | BI49: 2 | BJ49: ТСН-2001.4 Доп. 68, Сб. 12, т. 50, поз. 6 | BM49: 73 | BN49: 0 | BO49: 4.12-50-6 | BP49: 1 | BQ49: 40 | BR49: 0 | BS49: 56.35 | BT49: 1 | BU49: 1 | BV49: 1 | BW49: 1 | BX49: 1 | BZ49: 90 | CA49: 46 | CE49: 1566 | CF49: 0 | CG49: 0 | CM49: 0 | CN49: Поправка: Гл.12.Прил.8.п.8. 3_12.00.01.11.001 Наименование: При наличии напряженных и стесненных условий производства работ (стесненность, сложность складирования и транспортной логистики и т.п.) для объектов, расположенных в пределах круговой магистральной системы улиц "Садовое кольцо" города Москвы | CO49: 0 | CP49: =(P49+Q49+S49) -> 5189.49 | CQ49: =ROUND((ROUND((AC49*AW49*1),2)*BC49),2) -> 18.14 | CR49: =(ROUND((ROUND((((ET49*1.2))*AV49*1),2)*BB49),2)+ROUND((ROUND(((AE49-((EU49*1.2)))*AV49*1),2)*BS49),2)) -> 163.53 | CS49: =(ROUND((ROUND((((EU49*1.2))*AV49*1),2)*BS49),2)+ROUND((ROUND(((AE49-((EU49*1.2)))*AV49*1),2)*BS49),2)) -> 82.27 | CT49: =ROUND((ROUND((AF49*AV49*1),2)*BA49),2) -> 5007.82 | CU49: =AG49 -> 0 | CV49: =(AH49*AV49) -> 7.0422 | CW49: =AI49 -> 0 | CX49: =AJ49 -> 0 | CY49: =(ROUND((((S49+ROUND((ROUND((((EU49*1.2))*AV49*1),2)*BS49),2))*AT49)/100),2)+ROUND(((ROUND((ROUND(((AE49-((EU49*1.2)))*AV49*1),2)*BS49),2)*AT49)/100),2)) -> 4581.08 | CZ49: =(ROUND((((S49+ROUND((ROUND((((EU49*1.2))*AV49*1),2)*BS49),2))*AU49)/100),2)+ROUND(((ROUND((ROUND(((AE49-((EU49*1.2)))*AV49*1),2)*BS49),2)*AU49)/100),2)) -> 2341.44 | DB49: 22 | DD49: *1 | DE49: *1,2 | DF49: *1,2 | DG49: *1,2 | DI49: *1,2 | DJ49: *1,2 | DN49: 0 | DO49: 0 | DP49: 1 | DQ49: 1 | DU49: 1013 | DV49: 1 ШТ. | DW49: 1 ШТ. | DX49: 1 | EE49: 85133422 | EF49: 40 | EG49: Монтаж оборудования | EH49: 0 | EJ49: 2 | EK49: 73 | EL49: ТСН-2001.4-12. Технологические трубопроводы | EM49: ТСН-2001.4-12-1 | EO49: Поправка: Гл.12.Прил.8.п.8. 3_12.00.01.11.001 | EQ49: 0 | ER49: 80.82 | ES49: 3.93 | ET49: 7.48 | EU49: 1.14 | EV49: 69.41 | EW49: 5.5 | EX49: 0 | EY49: 0 | FQ49: 0 | FR49: 0 | FS49: 2 | FX49: 90 | FY49: 46 | GD49: 1 | GF49: -355409604 | GG49: 2 | GH49: 1 | GI49: 2 | GJ49: 0 | GK49: 0 | GL49: =ROUND(IF(AND(BH49=3,BI49=3,FS49<>0),P49,0),2) -> 0 | GM49: =ROUND(O49+X49+Y49,2)+GX49 -> 12112.01 | GN49: =IF(OR(BI49=0,BI49=1),GM49-GX49,0) -> 0 | GO49: =IF(BI49=2,GM49-GX49,0) -> 12112.01 | GP49: =IF(BI49=4,GM49-GX49,0) -> 0 | GR49: 0 | GS49: 3 | GT49: 0 | GV49: =ROUND((GT49),6) -> 0 | GW49: 1 | GX49: =ROUND(HC49*I49,2) -> 0 | HA49: 0 | HB49: 0 | HC49: =GV49*GW49 -> 0 | HS49: 0 | IK49: 0
A50: 18 | B50: 1 | C50: 100 | E50: 10,1 | F50: КА. п. 2 | G50: Узел управления спринклерный водозаполненный УУ-С100/1,6В-ВФ.О4 Прямоточный-100 | H50: шт. | I50: =I48*J50 -> 1 | J50: 1 | K50: 1 | O50: =ROUND(CP50,2) -> 8238.95 | P50: =ROUND((ROUND((AC50*I50),2)*BC50),2) -> 8238.95 | Q50: =(ROUND((ROUND(((ET50)*AV50*I50),2)*BB50),2)+ROUND((ROUND(((AE50-(EU50))*AV50*I50),2)*BS50),2)) -> 0 | R50: =(ROUND((ROUND(((EU50)*AV50*I50),2)*BS50),2)+ROUND((ROUND(((AE50-(EU50))*AV50*I50),2)*BS50),2)) -> 0 | S50: =ROUND((ROUND((AF50*AV50*I50),2)*BA50),2) -> 0 | T50: =ROUND(CU50*I50,2) -> 0 | U50: =CV50*I50 -> 0 | V50: =CW50*I50 -> 0 | W50: =ROUND(CX50*I50,2) -> 0 | X50: =(ROUND((((S50+ROUND((ROUND(((EU50)*AV50*I50),2)*BS50),2))*AT50)/100),2)+ROUND(((ROUND((ROUND(((AE50-(EU50))*AV50*I50),2)*BS50),2)*AT50)/100),2)) -> 0 | Y50: =(ROUND((((S50+ROUND((ROUND(((EU50)*AV50*I50),2)*BS50),2))*AU50)/100),2)+ROUND(((ROUND((ROUND(((AE50-(EU50))*AV50*I50),2)*BS50),2)*AU50)/100),2)) -> 0 | AA50: 85739205 | AB50: =ROUND((AC50+AD50+AF50),6) -> 8238.95 | AC50: =ROUND((ES50),6) -> 8238.95 | AD50: =ROUND((((ET50)-(EU50))+AE50),6) -> 0 | AE50: =ROUND((EU50),6) -> 0 | AF50: =ROUND((EV50),6) -> 0 | AG50: =ROUND((AP50),6) -> 0 | AH50: =(EW50) -> 0 | AI50: =(EX50) -> 0 | AJ50: =(AS50) -> 0 | AK50: 8238.95 | AL50: 8238.95 | AM50: 0 | AN50: 0 | AO50: 0 | AP50: 0 | AQ50: 0 | AR50: 0 | AS50: 0 | AT50: 0 | AU50: 0 | AV50: 1 | AW50: 1 | AZ50: 1 | BA50: 1 | BB50: 1 | BC50: 1 | BH50: 3 | BI50: 3 | BM50: 746 | BN50: 0 | BP50: 0 | BQ50: 130 | BR50: 0 | BS50: 1 | BT50: 1 | BU50: 1 | BV50: 1 | BW50: 1 | BX50: 1 | BZ50: 90 | CA50: 46 | CE50: 1566 | CF50: 0 | CG50: 0 | CM50: 0 | CN50: Поправка: Гл.12.Прил.8.п.8. 3_12.00.01.11.001_x000D_ Наименование: При наличии напряженных и стесненных условий производства работ (стесненность, сложность складирования и транспортной логистики и т.п.) для объектов, расположенных в пределах круговой магистральной системы улиц "Садовое кольцо" города Москвы | CO50: 0 | CP50: =(P50+Q50+S50) -> 8238.95 | CQ50: =ROUND((ROUND((AC50*1),2)*BC50),2) -> 8238.95 | CR50: =(ROUND((ROUND(((ET50)*AV50*1),2)*BB50),2)+ROUND((ROUND(((AE50-(EU50))*AV50*1),2)*BS50),2)) -> 0 | CS50: =(ROUND((ROUND(((EU50)*AV50*1),2)*BS50),2)+ROUND((ROUND(((AE50-(EU50))*AV50*1),2)*BS50),2)) -> 0 | CT50: =ROUND((ROUND((AF50*AV50*1),2)*BA50),2) -> 0 | CU50: =AG50 -> 0 | CV50: =(AH50*AV50) -> 0 | CW50: =AI50 -> 0 | CX50: =AJ50 -> 0 | CY50: =(ROUND((((S50+ROUND((ROUND(((EU50)*AV50*1),2)*BS50),2))*AT50)/100),2)+ROUND(((ROUND((ROUND(((AE50-(EU50))*AV50*1),2)*BS50),2)*AT50)/100),2)) -> 0 | CZ50: =(ROUND((((S50+ROUND((ROUND(((EU50)*AV50*1),2)*BS50),2))*AU50)/100),2)+ROUND(((ROUND((ROUND(((AE50-(EU50))*AV50*1),2)*BS50),2)*AU50)/100),2)) -> 0 | DN50: 0 | DO50: 0 | DP50: 1 | DQ50: 1 | DU50: 1010 | DV50: шт. | DW50: шт. | DX50: 1 | EE50: 85133523 | EF50: 130 | EG50: Сметная стоимость оборудования | EH50: 0 | EJ50: 3 | EK50: 746 | EL50: ТСН-2001.13. Сметная стоимость оборудования | EM50: ТСН-2001.13 | EO50: Поправка: Гл.12.Прил.8.п.8. 3_12.00.01.11.001 | EQ50: 2097152 | ER50: 0 | ES50: 8238.95 | ET50: 0 | EU50: 0 | EV50: 0 | EW50: 0 | EX50: 0 | FQ50: 0 | FR50: =P50 -> 8238.95 | FS50: 0 | FX50: 90 | FY50: 46 | GA50: [72 997,8 / 1,22 / 7,57] + 3% Трансп + 1,2% Заг.скл | GD50: 1 | GF50: -255262661 | GG50: 2 | GH50: 4 | GI50: -2 | GJ50: 0 | GK50: 0 | GL50: =ROUND(IF(AND(BH50=3,BI50=3,FS50<>0),P50,0),2) -> 0 | GM50: =ROUND(O50+X50+Y50,2)+GX50 -> 8238.95 | GN50: =IF(OR(BI50=0,BI50=1),GM50-GX50,0) -> 0 | GO50: =IF(BI50=2,GM50-GX50,0) -> 0 | GP50: =IF(BI50=4,GM50-GX50,0) -> 0 | GR50: 0 | GS50: 2 | GT50: 0 | GV50: =ROUND((GT50),6) -> 0 | GW50: 1 | GX50: =ROUND(HC50*I50,2) -> 0 | HA50: 0 | HB50: 0 | HC50: =GV50*GW50 -> 0 | HE50: 3 | HF50: 1,2 | HM50: *1 | HS50: 0 | IK50: 0
A51: 18 | B51: 1 | C51: 104 | E51: 10,1 | F51: КА. п. 2 | G51: Узел управления спринклерный водозаполненный УУ-С100/1,6В-ВФ.О4 Прямоточный-100 | H51: шт. | I51: =I49*J51 -> 1 | J51: 1 | K51: 1 | O51: =ROUND(CP51,2) -> 62368.85 | P51: =ROUND((ROUND((AC51*I51),2)*BC51),2) -> 62368.85 | Q51: =(ROUND((ROUND(((ET51)*AV51*I51),2)*BB51),2)+ROUND((ROUND(((AE51-(EU51))*AV51*I51),2)*BS51),2)) -> 0 | R51: =(ROUND((ROUND(((EU51)*AV51*I51),2)*BS51),2)+ROUND((ROUND(((AE51-(EU51))*AV51*I51),2)*BS51),2)) -> 0 | S51: =ROUND((ROUND((AF51*AV51*I51),2)*BA51),2) -> 0 | T51: =ROUND(CU51*I51,2) -> 0 | U51: =CV51*I51 -> 0 | V51: =CW51*I51 -> 0 | W51: =ROUND(CX51*I51,2) -> 0 | X51: =(ROUND((((S51+ROUND((ROUND(((EU51)*AV51*I51),2)*BS51),2))*AT51)/100),2)+ROUND(((ROUND((ROUND(((AE51-(EU51))*AV51*I51),2)*BS51),2)*AT51)/100),2)) -> 0 | Y51: =(ROUND((((S51+ROUND((ROUND(((EU51)*AV51*I51),2)*BS51),2))*AU51)/100),2)+ROUND(((ROUND((ROUND(((AE51-(EU51))*AV51*I51),2)*BS51),2)*AU51)/100),2)) -> 0 | AA51: 85739207 | AB51: =ROUND((AC51+AD51+AF51),6) -> 8238.95 | AC51: =ROUND((ES51),6) -> 8238.95 | AD51: =ROUND((((ET51)-(EU51))+AE51),6) -> 0 | AE51: =ROUND((EU51),6) -> 0 | AF51: =ROUND((EV51),6) -> 0 | AG51: =ROUND((AP51),6) -> 0 | AH51: =(EW51) -> 0 | AI51: =(EX51) -> 0 | AJ51: =(AS51) -> 0 | AK51: 8238.95 | AL51: 8238.95 | AM51: 0 | AN51: 0 | AO51: 0 | AP51: 0 | AQ51: 0 | AR51: 0 | AS51: 0 | AT51: 0 | AU51: 0 | AV51: 1 | AW51: 1 | AZ51: 1 | BA51: 1 | BB51: 1 | BC51: 7.57 | BH51: 3 | BI51: 3 | BM51: 746 | BN51: 0 | BP51: 0 | BQ51: 130 | BR51: 0 | BS51: 1 | BT51: 1 | BU51: 1 | BV51: 1 | BW51: 1 | BX51: 1 | BZ51: 90 | CA51: 46 | CE51: 1566 | CF51: 0 | CG51: 0 | CM51: 0 | CN51: Поправка: Гл.12.Прил.8.п.8. 3_12.00.01.11.001_x000D_ Наименование: При наличии напряженных и стесненных условий производства работ (стесненность, сложность складирования и транспортной логистики и т.п.) для объектов, расположенных в пределах круговой магистральной системы улиц "Садовое кольцо" города Москвы | CO51: 0 | CP51: =(P51+Q51+S51) -> 62368.85 | CQ51: =ROUND((ROUND((AC51*1),2)*BC51),2) -> 62368.85 | CR51: =(ROUND((ROUND(((ET51)*AV51*1),2)*BB51),2)+ROUND((ROUND(((AE51-(EU51))*AV51*1),2)*BS51),2)) -> 0 | CS51: =(ROUND((ROUND(((EU51)*AV51*1),2)*BS51),2)+ROUND((ROUND(((AE51-(EU51))*AV51*1),2)*BS51),2)) -> 0 | CT51: =ROUND((ROUND((AF51*AV51*1),2)*BA51),2) -> 0 | CU51: =AG51 -> 0 | CV51: =(AH51*AV51) -> 0 | CW51: =AI51 -> 0 | CX51: =AJ51 -> 0 | CY51: =(ROUND((((S51+ROUND((ROUND(((EU51)*AV51*1),2)*BS51),2))*AT51)/100),2)+ROUND(((ROUND((ROUND(((AE51-(EU51))*AV51*1),2)*BS51),2)*AT51)/100),2)) -> 0 | CZ51: =(ROUND((((S51+ROUND((ROUND(((EU51)*AV51*1),2)*BS51),2))*AU51)/100),2)+ROUND(((ROUND((ROUND(((AE51-(EU51))*AV51*1),2)*BS51),2)*AU51)/100),2)) -> 0 | DN51: 0 | DO51: 0 | DP51: 1 | DQ51: 1 | DU51: 1010 | DV51: шт. | DW51: шт. | DX51: 1 | EE51: 85133523 | EF51: 130 | EG51: Сметная стоимость оборудования | EH51: 0 | EJ51: 3 | EK51: 746 | EL51: ТСН-2001.13. Сметная стоимость оборудования | EM51: ТСН-2001.13 | EO51: Поправка: Гл.12.Прил.8.п.8. 3_12.00.01.11.001 | EQ51: 2097152 | ER51: 8238.95 | ES51: 8238.95 | ET51: 0 | EU51: 0 | EV51: 0 | EW51: 0 | EX51: 0 | EZ51: 5 | FC51: 1 | FD51: 18 | FF51: 72997.8 | FQ51: 0 | FR51: =P51 -> 62368.85 | FS51: 0 | FX51: 90 | FY51: 46 | GA51: [72 997,8 / 1,22 / 7,57] + 3% Трансп + 1,2% Заг.скл | GD51: 1 | GF51: -255262661 | GG51: 2 | GH51: 3 | GI51: 5 | GJ51: 0 | GK51: 0 | GL51: =ROUND(IF(AND(BH51=3,BI51=3,FS51<>0),P51,0),2) -> 0 | GM51: =ROUND(O51+X51+Y51,2)+GX51 -> 62368.85 | GN51: =IF(OR(BI51=0,BI51=1),GM51-GX51,0) -> 0 | GO51: =IF(BI51=2,GM51-GX51,0) -> 0 | GP51: =IF(BI51=4,GM51-GX51,0) -> 0 | GR51: 1 | GS51: 1 | GT51: 0 | GV51: =ROUND((GT51),6) -> 0 | GW51: 1 | GX51: =ROUND(HC51*I51,2) -> 0 | HA51: 0 | HB51: 0 | HC51: =GV51*GW51 -> 0 | HE51: 3 | HF51: 1,2 | HM51: *1 | HS51: 0 | IK51: 0
A52: 17 | B52: 1 | C52: =ROW(SmtRes!A108) -> 108 | D52: =ROW(EtalonRes!A137) -> 137 | E52: 11 | F52: 4.12-48-10 | G52: Монтаж арматуры фланцевой с ручным приводом или без привода на номинальное давление до 4 МПа, номинальный диаметр прохода 100 мм | H52: 1 ШТ. | I52: =ROUND(9,9) -> 9 | J52: 0 | K52: =ROUND(9,9) -> 9 | O52: =ROUND(CP52,2) -> 661.28 | P52: =ROUND((ROUND((AC52*AW52*I52),2)*BC52),2) -> 36.36 | Q52: =(ROUND((ROUND((((ET52*1.2))*AV52*I52),2)*BB52),2)+ROUND((ROUND(((AE52-((EU52*1.2)))*AV52*I52),2)*BS52),2)) -> 28.69 | R52: =(ROUND((ROUND((((EU52*1.2))*AV52*I52),2)*BS52),2)+ROUND((ROUND(((AE52-((EU52*1.2)))*AV52*I52),2)*BS52),2)) -> 4.38 | S52: =ROUND((ROUND((AF52*AV52*I52),2)*BA52),2) -> 596.23 | T52: =ROUND(CU52*I52,2) -> 0 | U52: =CV52*I52 -> 47.24676 | V52: =CW52*I52 -> 0 | W52: =ROUND(CX52*I52,2) -> 0 | X52: =(ROUND((((S52+ROUND((ROUND((((EU52*1.2))*AV52*I52),2)*BS52),2))*AT52)/100),2)+ROUND(((ROUND((ROUND(((AE52-((EU52*1.2)))*AV52*I52),2)*BS52),2)*AT52)/100),2)) -> 540.55 | Y52: =(ROUND((((S52+ROUND((ROUND((((EU52*1.2))*AV52*I52),2)*BS52),2))*AU52)/100),2)+ROUND(((ROUND((ROUND(((AE52-((EU52*1.2)))*AV52*I52),2)*BS52),2)*AU52)/100),2)) -> 276.28 | AA52: 85739205 | AB52: =ROUND((AC52+AD52+AF52),6) -> 69.006 | AC52: =ROUND(((ES52*1)),6) -> 3.93 | AD52: =ROUND(((((ET52*1.2))-((EU52*1.2)))+AE52),6) -> 2.988 | AE52: =ROUND(((EU52*1.2)),6) -> 0.456 | AF52: =ROUND(((EV52*1.2)),6) -> 62.088 | AG52: =ROUND((AP52),6) -> 0 | AH52: =((EW52*1.2)) -> 4.92 | AI52: =((EX52*1.2)) -> 0 | AJ52: =(AS52) -> 0 | AK52: 58.16 | AL52: 3.93 | AM52: 2.49 | AN52: 0.38 | AO52: 51.74 | AP52: 0 | AQ52: 4.1 | AR52: 0 | AS52: 0 | AT52: 90 | AU52: 46 | AV52: 1.067 | AW52: 1.028 | AZ52: 1 | BA52: 1 | BB52: 1 | BC52: 1 | BH52: 0 | BI52: 2 | BJ52: ТСН-2001.4 Доп. 68, Сб. 12, т. 48, поз. 10 | BM52: 73 | BN52: 0 | BO52: 4.12-48-10 | BP52: 1 | BQ52: 40 | BR52: 0 | BS52: 1 | BT52: 1 | BU52: 1 | BV52: 1 | BW52: 1 | BX52: 1 | BZ52: 90 | CA52: 46 | CE52: 1566 | CF52: 0 | CG52: 0 | CM52: 0 | CN52: Поправка: Гл.12.Прил.8.п.8. 3_12.00.01.11.001 Наименование: При наличии напряженных и стесненных условий производства работ (стесненность, сложность складирования и транспортной логистики и т.п.) для объектов, расположенных в пределах круговой магистральной системы улиц "Садовое кольцо" города Москвы | CO52: 0 | CP52: =(P52+Q52+S52) -> 661.28 | CQ52: =ROUND((ROUND((AC52*AW52*1),2)*BC52),2) -> 4.04 | CR52: =(ROUND((ROUND((((ET52*1.2))*AV52*1),2)*BB52),2)+ROUND((ROUND(((AE52-((EU52*1.2)))*AV52*1),2)*BS52),2)) -> 3.19 | CS52: =(ROUND((ROUND((((EU52*1.2))*AV52*1),2)*BS52),2)+ROUND((ROUND(((AE52-((EU52*1.2)))*AV52*1),2)*BS52),2)) -> 0.49 | CT52: =ROUND((ROUND((AF52*AV52*1),2)*BA52),2) -> 66.25 | CU52: =AG52 -> 0 | CV52: =(AH52*AV52) -> 5.24964 | CW52: =AI52 -> 0 | CX52: =AJ52 -> 0 | CY52: =(ROUND((((S52+ROUND((ROUND((((EU52*1.2))*AV52*1),2)*BS52),2))*AT52)/100),2)+ROUND(((ROUND((ROUND(((AE52-((EU52*1.2)))*AV52*1),2)*BS52),2)*AT52)/100),2)) -> 537.05 | CZ52: =(ROUND((((S52+ROUND((ROUND((((EU52*1.2))*AV52*1),2)*BS52),2))*AU52)/100),2)+ROUND(((ROUND((ROUND(((AE52-((EU52*1.2)))*AV52*1),2)*BS52),2)*AU52)/100),2)) -> 274.49 | DB52: 23 | DD52: *1 | DE52: *1,2 | DF52: *1,2 | DG52: *1,2 | DI52: *1,2 | DJ52: *1,2 | DN52: 0 | DO52: 0 | DP52: 1 | DQ52: 1 | DU52: 1013 | DV52: 1 ШТ. | DW52: 1 ШТ. | DX52: 1 | EE52: 85133422 | EF52: 40 | EG52: Монтаж оборудования | EH52: 0 | EJ52: 2 | EK52: 73 | EL52: ТСН-2001.4-12. Технологические трубопроводы | EM52: ТСН-2001.4-12-1 | EO52: Поправка: Гл.12.Прил.8.п.8. 3_12.00.01.11.001 | EQ52: 0 | ER52: 58.16 | ES52: 3.93 | ET52: 2.49 | EU52: 0.38 | EV52: 51.74 | EW52: 4.1 | EX52: 0 | EY52: 0 | FQ52: 0 | FR52: 0 | FS52: 2 | FX52: 90 | FY52: 46 | GD52: 1 | GF52: 1723816868 | GG52: 2 | GH52: 1 | GI52: 2 | GJ52: 0 | GK52: 0 | GL52: =ROUND(IF(AND(BH52=3,BI52=3,FS52<>0),P52,0),2) -> 0 | GM52: =ROUND(O52+X52+Y52,2)+GX52 -> 1478.11 | GN52: =IF(OR(BI52=0,BI52=1),GM52-GX52,0) -> 0 | GO52: =IF(BI52=2,GM52-GX52,0) -> 1478.11 | GP52: =IF(BI52=4,GM52-GX52,0) -> 0 | GR52: 0 | GS52: 3 | GT52: 0 | GV52: =ROUND((GT52),6) -> 0 | GW52: 1 | GX52: =ROUND(HC52*I52,2) -> 0 | HA52: 0 | HB52: 0 | HC52: =GV52*GW52 -> 0 | HS52: 0 | IK52: 0
A53: 17 | B53: 1 | C53: =ROW(SmtRes!A112) -> 112 | D53: =ROW(EtalonRes!A142) -> 142 | E53: 11 | F53: 4.12-48-10 | G53: Монтаж арматуры фланцевой с ручным приводом или без привода на номинальное давление до 4 МПа, номинальный диаметр прохода 100 мм | H53: 1 ШТ. | I53: =ROUND(9,9) -> 9 | J53: 0 | K53: =ROUND(9,9) -> 9 | O53: =ROUND(CP53,2) -> 34251.13 | P53: =ROUND((ROUND((AC53*AW53*I53),2)*BC53),2) -> 163.26 | Q53: =(ROUND((ROUND((((ET53*1.2))*AV53*I53),2)*BB53),2)+ROUND((ROUND(((AE53-((EU53*1.2)))*AV53*I53),2)*BS53),2)) -> 490.31 | R53: =(ROUND((ROUND((((EU53*1.2))*AV53*I53),2)*BS53),2)+ROUND((ROUND(((AE53-((EU53*1.2)))*AV53*I53),2)*BS53),2)) -> 246.81 | S53: =ROUND((ROUND((AF53*AV53*I53),2)*BA53),2) -> 33597.56 | T53: =ROUND(CU53*I53,2) -> 0 | U53: =CV53*I53 -> 47.24676 | V53: =CW53*I53 -> 0 | W53: =ROUND(CX53*I53,2) -> 0 | X53: =(ROUND((((S53+ROUND((ROUND((((EU53*1.2))*AV53*I53),2)*BS53),2))*AT53)/100),2)+ROUND(((ROUND((ROUND(((AE53-((EU53*1.2)))*AV53*I53),2)*BS53),2)*AT53)/100),2)) -> 30459.93 | Y53: =(ROUND((((S53+ROUND((ROUND((((EU53*1.2))*AV53*I53),2)*BS53),2))*AU53)/100),2)+ROUND(((ROUND((ROUND(((AE53-((EU53*1.2)))*AV53*I53),2)*BS53),2)*AU53)/100),2)) -> 15568.41 | AA53: 85739207 | AB53: =ROUND((AC53+AD53+AF53),6) -> 69.006 | AC53: =ROUND(((ES53*1)),6) -> 3.93 | AD53: =ROUND(((((ET53*1.2))-((EU53*1.2)))+AE53),6) -> 2.988 | AE53: =ROUND(((EU53*1.2)),6) -> 0.456 | AF53: =ROUND(((EV53*1.2)),6) -> 62.088 | AG53: =ROUND((AP53),6) -> 0 | AH53: =((EW53*1.2)) -> 4.92 | AI53: =((EX53*1.2)) -> 0 | AJ53: =(AS53) -> 0 | AK53: 58.16 | AL53: 3.93 | AM53: 2.49 | AN53: 0.38 | AO53: 51.74 | AP53: 0 | AQ53: 4.1 | AR53: 0 | AS53: 0 | AT53: 90 | AU53: 46 | AV53: 1.067 | AW53: 1.028 | AZ53: 1 | BA53: 56.35 | BB53: 17.09 | BC53: 4.49 | BH53: 0 | BI53: 2 | BJ53: ТСН-2001.4 Доп. 68, Сб. 12, т. 48, поз. 10 | BM53: 73 | BN53: 0 | BO53: 4.12-48-10 | BP53: 1 | BQ53: 40 | BR53: 0 | BS53: 56.35 | BT53: 1 | BU53: 1 | BV53: 1 | BW53: 1 | BX53: 1 | BZ53: 90 | CA53: 46 | CE53: 1566 | CF53: 0 | CG53: 0 | CM53: 0 | CN53: Поправка: Гл.12.Прил.8.п.8. 3_12.00.01.11.001 Наименование: При наличии напряженных и стесненных условий производства работ (стесненность, сложность складирования и транспортной логистики и т.п.) для объектов, расположенных в пределах круговой магистральной системы улиц "Садовое кольцо" города Москвы | CO53: 0 | CP53: =(P53+Q53+S53) -> 34251.13 | CQ53: =ROUND((ROUND((AC53*AW53*1),2)*BC53),2) -> 18.14 | CR53: =(ROUND((ROUND((((ET53*1.2))*AV53*1),2)*BB53),2)+ROUND((ROUND(((AE53-((EU53*1.2)))*AV53*1),2)*BS53),2)) -> 54.52 | CS53: =(ROUND((ROUND((((EU53*1.2))*AV53*1),2)*BS53),2)+ROUND((ROUND(((AE53-((EU53*1.2)))*AV53*1),2)*BS53),2)) -> 27.61 | CT53: =ROUND((ROUND((AF53*AV53*1),2)*BA53),2) -> 3733.19 | CU53: =AG53 -> 0 | CV53: =(AH53*AV53) -> 5.24964 | CW53: =AI53 -> 0 | CX53: =AJ53 -> 0 | CY53: =(ROUND((((S53+ROUND((ROUND((((EU53*1.2))*AV53*1),2)*BS53),2))*AT53)/100),2)+ROUND(((ROUND((ROUND(((AE53-((EU53*1.2)))*AV53*1),2)*BS53),2)*AT53)/100),2)) -> 30262.65 | CZ53: =(ROUND((((S53+ROUND((ROUND((((EU53*1.2))*AV53*1),2)*BS53),2))*AU53)/100),2)+ROUND(((ROUND((ROUND(((AE53-((EU53*1.2)))*AV53*1),2)*BS53),2)*AU53)/100),2)) -> 15467.58 | DB53: 24 | DD53: *1 | DE53: *1,2 | DF53: *1,2 | DG53: *1,2 | DI53: *1,2 | DJ53: *1,2 | DN53: 0 | DO53: 0 | DP53: 1 | DQ53: 1 | DU53: 1013 | DV53: 1 ШТ. | DW53: 1 ШТ. | DX53: 1 | EE53: 85133422 | EF53: 40 | EG53: Монтаж оборудования | EH53: 0 | EJ53: 2 | EK53: 73 | EL53: ТСН-2001.4-12. Технологические трубопроводы | EM53: ТСН-2001.4-12-1 | EO53: Поправка: Гл.12.Прил.8.п.8. 3_12.00.01.11.001 | EQ53: 0 | ER53: 58.16 | ES53: 3.93 | ET53: 2.49 | EU53: 0.38 | EV53: 51.74 | EW53: 4.1 | EX53: 0 | EY53: 0 | FQ53: 0 | FR53: 0 | FS53: 2 | FX53: 90 | FY53: 46 | GD53: 1 | GF53: 1723816868 | GG53: 2 | GH53: 1 | GI53: 2 | GJ53: 0 | GK53: 0 | GL53: =ROUND(IF(AND(BH53=3,BI53=3,FS53<>0),P53,0),2) -> 0 | GM53: =ROUND(O53+X53+Y53,2)+GX53 -> 80279.47 | GN53: =IF(OR(BI53=0,BI53=1),GM53-GX53,0) -> 0 | GO53: =IF(BI53=2,GM53-GX53,0) -> 80279.47 | GP53: =IF(BI53=4,GM53-GX53,0) -> 0 | GR53: 0 | GS53: 3 | GT53: 0 | GV53: =ROUND((GT53),6) -> 0 | GW53: 1 | GX53: =ROUND(HC53*I53,2) -> 0 | HA53: 0 | HB53: 0 | HC53: =GV53*GW53 -> 0 | HS53: 0 | IK53: 0
A54: 18 | B54: 1 | C54: 108 | E54: 11,1 | F54: 1.13-5-40 | G54: Затвор дисковый, поворотный, корпус из чугуна, диск из нержавеющей стали, с ручкой, номинальное давление PN 1,6 МПа, номинальный диаметр DN 100 мм | H54: шт. | I54: =I52*J54 -> 9 | J54: 1 | K54: 1 | O54: =ROUND(CP54,2) -> 19601.37 | P54: =ROUND((ROUND((AC54*AW54*I54),2)*BC54),2) -> 19601.37 | Q54: =(ROUND((ROUND(((ET54)*AV54*I54),2)*BB54),2)+ROUND((ROUND(((AE54-(EU54))*AV54*I54),2)*BS54),2)) -> 0 | R54: =(ROUND((ROUND(((EU54)*AV54*I54),2)*BS54),2)+ROUND((ROUND(((AE54-(EU54))*AV54*I54),2)*BS54),2)) -> 0 | S54: =ROUND((ROUND((AF54*AV54*I54),2)*BA54),2) -> 0 | T54: =ROUND(CU54*I54,2) -> 0 | U54: =CV54*I54 -> 0 | V54: =CW54*I54 -> 0 | W54: =ROUND(CX54*I54,2) -> 0 | X54: =(ROUND((((S54+ROUND((ROUND(((EU54)*AV54*I54),2)*BS54),2))*AT54)/100),2)+ROUND(((ROUND((ROUND(((AE54-(EU54))*AV54*I54),2)*BS54),2)*AT54)/100),2)) -> 0 | Y54: =(ROUND((((S54+ROUND((ROUND(((EU54)*AV54*I54),2)*BS54),2))*AU54)/100),2)+ROUND(((ROUND((ROUND(((AE54-(EU54))*AV54*I54),2)*BS54),2)*AU54)/100),2)) -> 0 | AA54: 85739205 | AB54: =ROUND((AC54+AD54+AF54),6) -> 2177.93 | AC54: =ROUND((ES54),6) -> 2177.93 | AD54: =ROUND((((ET54)-(EU54))+AE54),6) -> 0 | AE54: =ROUND((EU54),6) -> 0 | AF54: =ROUND((EV54),6) -> 0 | AG54: =ROUND((AP54),6) -> 0 | AH54: =(EW54) -> 0 | AI54: =(EX54) -> 0 | AJ54: =(AS54) -> 0 | AK54: 2177.93 | AL54: 2177.93 | AM54: 0 | AN54: 0 | AO54: 0 | AP54: 0 | AQ54: 0 | AR54: 0 | AS54: 0 | AT54: 90 | AU54: 46 | AV54: 1 | AW54: 1 | AZ54: 1 | BA54: 1 | BB54: 1 | BC54: 1 | BH54: 3 | BI54: 2 | BJ54: ТСН-2001.1 Доп. 79, Р. 13, о. 5, поз. 40 | BM54: 73 | BN54: 0 | BP54: 0 | BQ54: 40 | BR54: 0 | BS54: 1 | BT54: 1 | BU54: 1 | BV54: 1 | BW54: 1 | BX54: 1 | BZ54: 90 | CA54: 46 | CE54: 1566 | CF54: 0 | CG54: 0 | CM54: 0 | CN54: Поправка: Гл.12.Прил.8.п.8. 3_12.00.01.11.001_x000D_ Наименование: При наличии напряженных и стесненных условий производства работ (стесненность, сложность складирования и транспортной логистики и т.п.) для объектов, расположенных в пределах круговой магистральной системы улиц "Садовое кольцо" города Москвы | CO54: 0 | CP54: =(P54+Q54+S54) -> 19601.37 | CQ54: =ROUND((ROUND((AC54*AW54*1),2)*BC54),2) -> 2177.93 | CR54: =(ROUND((ROUND(((ET54)*AV54*1),2)*BB54),2)+ROUND((ROUND(((AE54-(EU54))*AV54*1),2)*BS54),2)) -> 0 | CS54: =(ROUND((ROUND(((EU54)*AV54*1),2)*BS54),2)+ROUND((ROUND(((AE54-(EU54))*AV54*1),2)*BS54),2)) -> 0 | CT54: =ROUND((ROUND((AF54*AV54*1),2)*BA54),2) -> 0 | CU54: =AG54 -> 0 | CV54: =(AH54*AV54) -> 0 | CW54: =AI54 -> 0 | CX54: =AJ54 -> 0 | CY54: =(ROUND((((S54+ROUND((ROUND(((EU54)*AV54*1),2)*BS54),2))*AT54)/100),2)+ROUND(((ROUND((ROUND(((AE54-(EU54))*AV54*1),2)*BS54),2)*AT54)/100),2)) -> 0 | CZ54: =(ROUND((((S54+ROUND((ROUND(((EU54)*AV54*1),2)*BS54),2))*AU54)/100),2)+ROUND(((ROUND((ROUND(((AE54-(EU54))*AV54*1),2)*BS54),2)*AU54)/100),2)) -> 0 | DN54: 0 | DO54: 0 | DP54: 1 | DQ54: 1 | DU54: 1010 | DV54: шт. | DW54: шт. | DX54: 1 | EE54: 85133422 | EF54: 40 | EG54: Монтаж оборудования | EH54: 0 | EJ54: 2 | EK54: 73 | EL54: ТСН-2001.4-12. Технологические трубопроводы | EM54: ТСН-2001.4-12-1 | EO54: Поправка: Гл.12.Прил.8.п.8. 3_12.00.01.11.001 | EQ54: 0 | ER54: 2177.93 | ES54: 2177.93 | ET54: 0 | EU54: 0 | EV54: 0 | EW54: 0 | EX54: 0 | FQ54: 0 | FR54: 0 | FS54: 0 | FX54: 90 | FY54: 46 | GD54: 1 | GF54: 873960273 | GG54: 2 | GH54: 1 | GI54: -2 | GJ54: 0 | GK54: 0 | GL54: =ROUND(IF(AND(BH54=3,BI54=3,FS54<>0),P54,0),2) -> 0 | GM54: =ROUND(O54+X54+Y54,2)+GX54 -> 19601.37 | GN54: =IF(OR(BI54=0,BI54=1),GM54-GX54,0) -> 0 | GO54: =IF(BI54=2,GM54-GX54,0) -> 19601.37 | GP54: =IF(BI54=4,GM54-GX54,0) -> 0 | GR54: 0 | GS54: 3 | GT54: 0 | GV54: =ROUND((GT54),6) -> 0 | GW54: 1 | GX54: =ROUND(HC54*I54,2) -> 0 | HA54: 0 | HB54: 0 | HC54: =GV54*GW54 -> 0 | HM54: *1 | HS54: 0 | IK54: 0
A55: 18 | B55: 1 | C55: 112 | E55: 11,1 | F55: 1.13-5-40 | G55: Затвор дисковый, поворотный, корпус из чугуна, диск из нержавеющей стали, с ручкой, номинальное давление PN 1,6 МПа, номинальный диаметр DN 100 мм | H55: шт. | I55: =I53*J55 -> 9 | J55: 1 | K55: 1 | O55: =ROUND(CP55,2) -> 60960.26 | P55: =ROUND((ROUND((AC55*AW55*I55),2)*BC55),2) -> 60960.26 | Q55: =(ROUND((ROUND(((ET55)*AV55*I55),2)*BB55),2)+ROUND((ROUND(((AE55-(EU55))*AV55*I55),2)*BS55),2)) -> 0 | R55: =(ROUND((ROUND(((EU55)*AV55*I55),2)*BS55),2)+ROUND((ROUND(((AE55-(EU55))*AV55*I55),2)*BS55),2)) -> 0 | S55: =ROUND((ROUND((AF55*AV55*I55),2)*BA55),2) -> 0 | T55: =ROUND(CU55*I55,2) -> 0 | U55: =CV55*I55 -> 0 | V55: =CW55*I55 -> 0 | W55: =ROUND(CX55*I55,2) -> 0 | X55: =(ROUND((((S55+ROUND((ROUND(((EU55)*AV55*I55),2)*BS55),2))*AT55)/100),2)+ROUND(((ROUND((ROUND(((AE55-(EU55))*AV55*I55),2)*BS55),2)*AT55)/100),2)) -> 0 | Y55: =(ROUND((((S55+ROUND((ROUND(((EU55)*AV55*I55),2)*BS55),2))*AU55)/100),2)+ROUND(((ROUND((ROUND(((AE55-(EU55))*AV55*I55),2)*BS55),2)*AU55)/100),2)) -> 0 | AA55: 85739207 | AB55: =ROUND((AC55+AD55+AF55),6) -> 2177.93 | AC55: =ROUND((ES55),6) -> 2177.93 | AD55: =ROUND((((ET55)-(EU55))+AE55),6) -> 0 | AE55: =ROUND((EU55),6) -> 0 | AF55: =ROUND((EV55),6) -> 0 | AG55: =ROUND((AP55),6) -> 0 | AH55: =(EW55) -> 0 | AI55: =(EX55) -> 0 | AJ55: =(AS55) -> 0 | AK55: 2177.93 | AL55: 2177.93 | AM55: 0 | AN55: 0 | AO55: 0 | AP55: 0 | AQ55: 0 | AR55: 0 | AS55: 0 | AT55: 90 | AU55: 46 | AV55: 1 | AW55: 1 | AZ55: 1 | BA55: 1 | BB55: 1 | BC55: 3.11 | BH55: 3 | BI55: 2 | BJ55: ТСН-2001.1 Доп. 79, Р. 13, о. 5, поз. 40 | BM55: 73 | BN55: 0 | BO55: 1.13-5-40 | BP55: 1 | BQ55: 40 | BR55: 0 | BS55: 1 | BT55: 1 | BU55: 1 | BV55: 1 | BW55: 1 | BX55: 1 | BZ55: 90 | CA55: 46 | CE55: 1566 | CF55: 0 | CG55: 0 | CM55: 0 | CN55: Поправка: Гл.12.Прил.8.п.8. 3_12.00.01.11.001_x000D_ Наименование: При наличии напряженных и стесненных условий производства работ (стесненность, сложность складирования и транспортной логистики и т.п.) для объектов, расположенных в пределах круговой магистральной системы улиц "Садовое кольцо" города Москвы | CO55: 0 | CP55: =(P55+Q55+S55) -> 60960.26 | CQ55: =ROUND((ROUND((AC55*AW55*1),2)*BC55),2) -> 6773.36 | CR55: =(ROUND((ROUND(((ET55)*AV55*1),2)*BB55),2)+ROUND((ROUND(((AE55-(EU55))*AV55*1),2)*BS55),2)) -> 0 | CS55: =(ROUND((ROUND(((EU55)*AV55*1),2)*BS55),2)+ROUND((ROUND(((AE55-(EU55))*AV55*1),2)*BS55),2)) -> 0 | CT55: =ROUND((ROUND((AF55*AV55*1),2)*BA55),2) -> 0 | CU55: =AG55 -> 0 | CV55: =(AH55*AV55) -> 0 | CW55: =AI55 -> 0 | CX55: =AJ55 -> 0 | CY55: =(ROUND((((S55+ROUND((ROUND(((EU55)*AV55*1),2)*BS55),2))*AT55)/100),2)+ROUND(((ROUND((ROUND(((AE55-(EU55))*AV55*1),2)*BS55),2)*AT55)/100),2)) -> 0 | CZ55: =(ROUND((((S55+ROUND((ROUND(((EU55)*AV55*1),2)*BS55),2))*AU55)/100),2)+ROUND(((ROUND((ROUND(((AE55-(EU55))*AV55*1),2)*BS55),2)*AU55)/100),2)) -> 0 | DN55: 0 | DO55: 0 | DP55: 1 | DQ55: 1 | DU55: 1010 | DV55: шт. | DW55: шт. | DX55: 1 | EE55: 85133422 | EF55: 40 | EG55: Монтаж оборудования | EH55: 0 | EJ55: 2 | EK55: 73 | EL55: ТСН-2001.4-12. Технологические трубопроводы | EM55: ТСН-2001.4-12-1 | EO55: Поправка: Гл.12.Прил.8.п.8. 3_12.00.01.11.001 | EQ55: 0 | ER55: 2177.93 | ES55: 2177.93 | ET55: 0 | EU55: 0 | EV55: 0 | EW55: 0 | EX55: 0 | FQ55: 0 | FR55: 0 | FS55: 0 | FX55: 90 | FY55: 46 | GD55: 1 | GF55: 873960273 | GG55: 2 | GH55: 1 | GI55: 2 | GJ55: 0 | GK55: 0 | GL55: =ROUND(IF(AND(BH55=3,BI55=3,FS55<>0),P55,0),2) -> 0 | GM55: =ROUND(O55+X55+Y55,2)+GX55 -> 60960.26 | GN55: =IF(OR(BI55=0,BI55=1),GM55-GX55,0) -> 0 | GO55: =IF(BI55=2,GM55-GX55,0) -> 60960.26 | GP55: =IF(BI55=4,GM55-GX55,0) -> 0 | GR55: 0 | GS55: 3 | GT55: 0 | GV55: =ROUND((GT55),6) -> 0 | GW55: 1 | GX55: =ROUND(HC55*I55,2) -> 0 | HA55: 0 | HB55: 0 | HC55: =GV55*GW55 -> 0 | HM55: *1 | HS55: 0 | IK55: 0
A56: 17 | B56: 1 | C56: =ROW(SmtRes!A117) -> 117 | D56: =ROW(EtalonRes!A147) -> 147 | E56: 12 | F56: 4.12-48-9 | G56: Монтаж арматуры фланцевой с ручным приводом или без привода на номинальное давление до 4 МПа, номинальный диаметр прохода 80 мм | H56: 1 ШТ. | I56: =ROUND(4+4,9) -> 8 | J56: 0 | K56: =ROUND(4+4,9) -> 8 | O56: =ROUND(CP56,2) -> 556.86 | P56: =ROUND((ROUND((AC56*AW56*I56),2)*BC56),2) -> 22.78 | Q56: =(ROUND((ROUND((((ET56*1.2))*AV56*I56),2)*BB56),2)+ROUND((ROUND(((AE56-((EU56*1.2)))*AV56*I56),2)*BS56),2)) -> 17 | R56: =(ROUND((ROUND((((EU56*1.2))*AV56*I56),2)*BS56),2)+ROUND((ROUND(((AE56-((EU56*1.2)))*AV56*I56),2)*BS56),2)) -> 2.56 | S56: =ROUND((ROUND((AF56*AV56*I56),2)*BA56),2) -> 517.08 | T56: =ROUND(CU56*I56,2) -> 0 | U56: =CV56*I56 -> 40.9728 | V56: =CW56*I56 -> 0 | W56: =ROUND(CX56*I56,2) -> 0 | X56: =(ROUND((((S56+ROUND((ROUND((((EU56*1.2))*AV56*I56),2)*BS56),2))*AT56)/100),2)+ROUND(((ROUND((ROUND(((AE56-((EU56*1.2)))*AV56*I56),2)*BS56),2)*AT56)/100),2)) -> 467.68 | Y56: =(ROUND((((S56+ROUND((ROUND((((EU56*1.2))*AV56*I56),2)*BS56),2))*AU56)/100),2)+ROUND(((ROUND((ROUND(((AE56-((EU56*1.2)))*AV56*I56),2)*BS56),2)*AU56)/100),2)) -> 239.03 | AA56: 85739205 | AB56: =ROUND((AC56+AD56+AF56),6) -> 65.338 | AC56: =ROUND(((ES56*1)),6) -> 2.77 | AD56: =ROUND(((((ET56*1.2))-((EU56*1.2)))+AE56),6) -> 1.992 | AE56: =ROUND(((EU56*1.2)),6) -> 0.3 | AF56: =ROUND(((EV56*1.2)),6) -> 60.576 | AG56: =ROUND((AP56),6) -> 0 | AH56: =((EW56*1.2)) -> 4.8 | AI56: =((EX56*1.2)) -> 0 | AJ56: =(AS56) -> 0 | AK56: 54.91 | AL56: 2.77 | AM56: 1.66 | AN56: 0.25 | AO56: 50.48 | AP56: 0 | AQ56: 4 | AR56: 0 | AS56: 0 | AT56: 90 | AU56: 46 | AV56: 1.067 | AW56: 1.028 | AZ56: 1 | BA56: 1 | BB56: 1 | BC56: 1 | BH56: 0 | BI56: 2 | BJ56: ТСН-2001.4 Доп. 68, Сб. 12, т. 48, поз. 9 | BM56: 73 | BN56: 0 | BO56: 4.12-48-9 | BP56: 1 | BQ56: 40 | BR56: 0 | BS56: 1 | BT56: 1 | BU56: 1 | BV56: 1 | BW56: 1 | BX56: 1 | BZ56: 90 | CA56: 46 | CE56: 1566 | CF56: 0 | CG56: 0 | CM56: 0 | CN56: Поправка: Гл.12.Прил.8.п.8. 3_12.00.01.11.001 Наименование: При наличии напряженных и стесненных условий производства работ (стесненность, сложность складирования и транспортной логистики и т.п.) для объектов, расположенных в пределах круговой магистральной системы улиц "Садовое кольцо" города Москвы | CO56: 0 | CP56: =(P56+Q56+S56) -> 556.86 | CQ56: =ROUND((ROUND((AC56*AW56*1),2)*BC56),2) -> 2.85 | CR56: =(ROUND((ROUND((((ET56*1.2))*AV56*1),2)*BB56),2)+ROUND((ROUND(((AE56-((EU56*1.2)))*AV56*1),2)*BS56),2)) -> 2.13 | CS56: =(ROUND((ROUND((((EU56*1.2))*AV56*1),2)*BS56),2)+ROUND((ROUND(((AE56-((EU56*1.2)))*AV56*1),2)*BS56),2)) -> 0.32 | CT56: =ROUND((ROUND((AF56*AV56*1),2)*BA56),2) -> 64.63 | CU56: =AG56 -> 0 | CV56: =(AH56*AV56) -> 5.1216 | CW56: =AI56 -> 0 | CX56: =AJ56 -> 0 | CY56: =(ROUND((((S56+ROUND((ROUND((((EU56*1.2))*AV56*1),2)*BS56),2))*AT56)/100),2)+ROUND(((ROUND((ROUND(((AE56-((EU56*1.2)))*AV56*1),2)*BS56),2)*AT56)/100),2)) -> 465.66 | CZ56: =(ROUND((((S56+ROUND((ROUND((((EU56*1.2))*AV56*1),2)*BS56),2))*AU56)/100),2)+ROUND(((ROUND((ROUND(((AE56-((EU56*1.2)))*AV56*1),2)*BS56),2)*AU56)/100),2)) -> 238 | DB56: 25 | DD56: *1 | DE56: *1,2 | DF56: *1,2 | DG56: *1,2 | DI56: *1,2 | DJ56: *1,2 | DN56: 0 | DO56: 0 | DP56: 1 | DQ56: 1 | DU56: 1013 | DV56: 1 ШТ. | DW56: 1 ШТ. | DX56: 1 | EE56: 85133422 | EF56: 40 | EG56: Монтаж оборудования | EH56: 0 | EJ56: 2 | EK56: 73 | EL56: ТСН-2001.4-12. Технологические трубопроводы | EM56: ТСН-2001.4-12-1 | EO56: Поправка: Гл.12.Прил.8.п.8. 3_12.00.01.11.001 | EQ56: 0 | ER56: 54.91 | ES56: 2.77 | ET56: 1.66 | EU56: 0.25 | EV56: 50.48 | EW56: 4 | EX56: 0 | EY56: 0 | FQ56: 0 | FR56: 0 | FS56: 2 | FX56: 90 | FY56: 46 | GD56: 1 | GF56: -202371068 | GG56: 2 | GH56: 1 | GI56: 2 | GJ56: 0 | GK56: 0 | GL56: =ROUND(IF(AND(BH56=3,BI56=3,FS56<>0),P56,0),2) -> 0 | GM56: =ROUND(O56+X56+Y56,2)+GX56 -> 1263.57 | GN56: =IF(OR(BI56=0,BI56=1),GM56-GX56,0) -> 0 | GO56: =IF(BI56=2,GM56-GX56,0) -> 1263.57 | GP56: =IF(BI56=4,GM56-GX56,0) -> 0 | GR56: 0 | GS56: 3 | GT56: 0 | GV56: =ROUND((GT56),6) -> 0 | GW56: 1 | GX56: =ROUND(HC56*I56,2) -> 0 | HA56: 0 | HB56: 0 | HC56: =GV56*GW56 -> 0 | HS56: 0 | IK56: 0
A57: 17 | B57: 1 | C57: =ROW(SmtRes!A122) -> 122 | D57: =ROW(EtalonRes!A152) -> 152 | E57: 12 | F57: 4.12-48-9 | G57: Монтаж арматуры фланцевой с ручным приводом или без привода на номинальное давление до 4 МПа, номинальный диаметр прохода 80 мм | H57: 1 ШТ. | I57: =ROUND(4+4,9) -> 8 | J57: 0 | K57: =ROUND(4+4,9) -> 8 | O57: =ROUND(CP57,2) -> 29530.5 | P57: =ROUND((ROUND((AC57*AW57*I57),2)*BC57),2) -> 102.51 | Q57: =(ROUND((ROUND((((ET57*1.2))*AV57*I57),2)*BB57),2)+ROUND((ROUND(((AE57-((EU57*1.2)))*AV57*I57),2)*BS57),2)) -> 290.53 | R57: =(ROUND((ROUND((((EU57*1.2))*AV57*I57),2)*BS57),2)+ROUND((ROUND(((AE57-((EU57*1.2)))*AV57*I57),2)*BS57),2)) -> 144.26 | S57: =ROUND((ROUND((AF57*AV57*I57),2)*BA57),2) -> 29137.46 | T57: =ROUND(CU57*I57,2) -> 0 | U57: =CV57*I57 -> 40.9728 | V57: =CW57*I57 -> 0 | W57: =ROUND(CX57*I57,2) -> 0 | X57: =(ROUND((((S57+ROUND((ROUND((((EU57*1.2))*AV57*I57),2)*BS57),2))*AT57)/100),2)+ROUND(((ROUND((ROUND(((AE57-((EU57*1.2)))*AV57*I57),2)*BS57),2)*AT57)/100),2)) -> 26353.55 | Y57: =(ROUND((((S57+ROUND((ROUND((((EU57*1.2))*AV57*I57),2)*BS57),2))*AU57)/100),2)+ROUND(((ROUND((ROUND(((AE57-((EU57*1.2)))*AV57*I57),2)*BS57),2)*AU57)/100),2)) -> 13469.59 | AA57: 85739207 | AB57: =ROUND((AC57+AD57+AF57),6) -> 65.338 | AC57: =ROUND(((ES57*1)),6) -> 2.77 | AD57: =ROUND(((((ET57*1.2))-((EU57*1.2)))+AE57),6) -> 1.992 | AE57: =ROUND(((EU57*1.2)),6) -> 0.3 | AF57: =ROUND(((EV57*1.2)),6) -> 60.576 | AG57: =ROUND((AP57),6) -> 0 | AH57: =((EW57*1.2)) -> 4.8 | AI57: =((EX57*1.2)) -> 0 | AJ57: =(AS57) -> 0 | AK57: 54.91 | AL57: 2.77 | AM57: 1.66 | AN57: 0.25 | AO57: 50.48 | AP57: 0 | AQ57: 4 | AR57: 0 | AS57: 0 | AT57: 90 | AU57: 46 | AV57: 1.067 | AW57: 1.028 | AZ57: 1 | BA57: 56.35 | BB57: 17.09 | BC57: 4.5 | BH57: 0 | BI57: 2 | BJ57: ТСН-2001.4 Доп. 68, Сб. 12, т. 48, поз. 9 | BM57: 73 | BN57: 0 | BO57: 4.12-48-9 | BP57: 1 | BQ57: 40 | BR57: 0 | BS57: 56.35 | BT57: 1 | BU57: 1 | BV57: 1 | BW57: 1 | BX57: 1 | BZ57: 90 | CA57: 46 | CE57: 1566 | CF57: 0 | CG57: 0 | CM57: 0 | CN57: Поправка: Гл.12.Прил.8.п.8. 3_12.00.01.11.001 Наименование: При наличии напряженных и стесненных условий производства работ (стесненность, сложность складирования и транспортной логистики и т.п.) для объектов, расположенных в пределах круговой магистральной системы улиц "Садовое кольцо" города Москвы | CO57: 0 | CP57: =(P57+Q57+S57) -> 29530.5 | CQ57: =ROUND((ROUND((AC57*AW57*1),2)*BC57),2) -> 12.83 | CR57: =(ROUND((ROUND((((ET57*1.2))*AV57*1),2)*BB57),2)+ROUND((ROUND(((AE57-((EU57*1.2)))*AV57*1),2)*BS57),2)) -> 36.4 | CS57: =(ROUND((ROUND((((EU57*1.2))*AV57*1),2)*BS57),2)+ROUND((ROUND(((AE57-((EU57*1.2)))*AV57*1),2)*BS57),2)) -> 18.03 | CT57: =ROUND((ROUND((AF57*AV57*1),2)*BA57),2) -> 3641.9 | CU57: =AG57 -> 0 | CV57: =(AH57*AV57) -> 5.1216 | CW57: =AI57 -> 0 | CX57: =AJ57 -> 0 | CY57: =(ROUND((((S57+ROUND((ROUND((((EU57*1.2))*AV57*1),2)*BS57),2))*AT57)/100),2)+ROUND(((ROUND((ROUND(((AE57-((EU57*1.2)))*AV57*1),2)*BS57),2)*AT57)/100),2)) -> 26239.94 | CZ57: =(ROUND((((S57+ROUND((ROUND((((EU57*1.2))*AV57*1),2)*BS57),2))*AU57)/100),2)+ROUND(((ROUND((ROUND(((AE57-((EU57*1.2)))*AV57*1),2)*BS57),2)*AU57)/100),2)) -> 13411.53 | DB57: 26 | DD57: *1 | DE57: *1,2 | DF57: *1,2 | DG57: *1,2 | DI57: *1,2 | DJ57: *1,2 | DN57: 0 | DO57: 0 | DP57: 1 | DQ57: 1 | DU57: 1013 | DV57: 1 ШТ. | DW57: 1 ШТ. | DX57: 1 | EE57: 85133422 | EF57: 40 | EG57: Монтаж оборудования | EH57: 0 | EJ57: 2 | EK57: 73 | EL57: ТСН-2001.4-12. Технологические трубопроводы | EM57: ТСН-2001.4-12-1 | EO57: Поправка: Гл.12.Прил.8.п.8. 3_12.00.01.11.001 | EQ57: 0 | ER57: 54.91 | ES57: 2.77 | ET57: 1.66 | EU57: 0.25 | EV57: 50.48 | EW57: 4 | EX57: 0 | EY57: 0 | FQ57: 0 | FR57: 0 | FS57: 2 | FX57: 90 | FY57: 46 | GD57: 1 | GF57: -202371068 | GG57: 2 | GH57: 1 | GI57: 2 | GJ57: 0 | GK57: 0 | GL57: =ROUND(IF(AND(BH57=3,BI57=3,FS57<>0),P57,0),2) -> 0 | GM57: =ROUND(O57+X57+Y57,2)+GX57 -> 69353.64 | GN57: =IF(OR(BI57=0,BI57=1),GM57-GX57,0) -> 0 | GO57: =IF(BI57=2,GM57-GX57,0) -> 69353.64 | GP57: =IF(BI57=4,GM57-GX57,0) -> 0 | GR57: 0 | GS57: 3 | GT57: 0 | GV57: =ROUND((GT57),6) -> 0 | GW57: 1 | GX57: =ROUND(HC57*I57,2) -> 0 | HA57: 0 | HB57: 0 | HC57: =GV57*GW57 -> 0 | HS57: 0 | IK57: 0
A58: 18 | B58: 1 | C58: 116 | E58: 12,1 | F58: 1.13-3-109 | G58: Клапан обратный, чугунный, фланцевый, температура рабочей среды от -10 до +100°С, условная пропускная способность 222 м3/ч, номинальное давление РN 1,6 МПа, номинальный диаметр DN 80 мм | H58: шт. | I58: =I56*J58 -> 4 | J58: 0.5 | K58: 0.5 | O58: =ROUND(CP58,2) -> 12121.96 | P58: =ROUND((ROUND((AC58*AW58*I58),2)*BC58),2) -> 12121.96 | Q58: =(ROUND((ROUND(((ET58)*AV58*I58),2)*BB58),2)+ROUND((ROUND(((AE58-(EU58))*AV58*I58),2)*BS58),2)) -> 0 | R58: =(ROUND((ROUND(((EU58)*AV58*I58),2)*BS58),2)+ROUND((ROUND(((AE58-(EU58))*AV58*I58),2)*BS58),2)) -> 0 | S58: =ROUND((ROUND((AF58*AV58*I58),2)*BA58),2) -> 0 | T58: =ROUND(CU58*I58,2) -> 0 | U58: =CV58*I58 -> 0 | V58: =CW58*I58 -> 0 | W58: =ROUND(CX58*I58,2) -> 0 | X58: =(ROUND((((S58+ROUND((ROUND(((EU58)*AV58*I58),2)*BS58),2))*AT58)/100),2)+ROUND(((ROUND((ROUND(((AE58-(EU58))*AV58*I58),2)*BS58),2)*AT58)/100),2)) -> 0 | Y58: =(ROUND((((S58+ROUND((ROUND(((EU58)*AV58*I58),2)*BS58),2))*AU58)/100),2)+ROUND(((ROUND((ROUND(((AE58-(EU58))*AV58*I58),2)*BS58),2)*AU58)/100),2)) -> 0 | AA58: 85739205 | AB58: =ROUND((AC58+AD58+AF58),6) -> 3030.49 | AC58: =ROUND((ES58),6) -> 3030.49 | AD58: =ROUND((((ET58)-(EU58))+AE58),6) -> 0 | AE58: =ROUND((EU58),6) -> 0 | AF58: =ROUND((EV58),6) -> 0 | AG58: =ROUND((AP58),6) -> 0 | AH58: =(EW58) -> 0 | AI58: =(EX58) -> 0 | AJ58: =(AS58) -> 0 | AK58: 3030.49 | AL58: 3030.49 | AM58: 0 | AN58: 0 | AO58: 0 | AP58: 0 | AQ58: 0 | AR58: 0 | AS58: 0 | AT58: 90 | AU58: 46 | AV58: 1 | AW58: 1 | AZ58: 1 | BA58: 1 | BB58: 1 | BC58: 1 | BH58: 3 | BI58: 2 | BJ58: ТСН-2001.1 Доп. 79, Р. 13, о. 3, поз. 109 | BM58: 73 | BN58: 0 | BP58: 0 | BQ58: 40 | BR58: 0 | BS58: 1 | BT58: 1 | BU58: 1 | BV58: 1 | BW58: 1 | BX58: 1 | BZ58: 90 | CA58: 46 | CE58: 1566 | CF58: 0 | CG58: 0 | CM58: 0 | CN58: Поправка: Гл.12.Прил.8.п.8. 3_12.00.01.11.001_x000D_ Наименование: При наличии напряженных и стесненных условий производства работ (стесненность, сложность складирования и транспортной логистики и т.п.) для объектов, расположенных в пределах круговой магистральной системы улиц "Садовое кольцо" города Москвы | CO58: 0 | CP58: =(P58+Q58+S58) -> 12121.96 | CQ58: =ROUND((ROUND((AC58*AW58*1),2)*BC58),2) -> 3030.49 | CR58: =(ROUND((ROUND(((ET58)*AV58*1),2)*BB58),2)+ROUND((ROUND(((AE58-(EU58))*AV58*1),2)*BS58),2)) -> 0 | CS58: =(ROUND((ROUND(((EU58)*AV58*1),2)*BS58),2)+ROUND((ROUND(((AE58-(EU58))*AV58*1),2)*BS58),2)) -> 0 | CT58: =ROUND((ROUND((AF58*AV58*1),2)*BA58),2) -> 0 | CU58: =AG58 -> 0 | CV58: =(AH58*AV58) -> 0 | CW58: =AI58 -> 0 | CX58: =AJ58 -> 0 | CY58: =(ROUND((((S58+ROUND((ROUND(((EU58)*AV58*1),2)*BS58),2))*AT58)/100),2)+ROUND(((ROUND((ROUND(((AE58-(EU58))*AV58*1),2)*BS58),2)*AT58)/100),2)) -> 0 | CZ58: =(ROUND((((S58+ROUND((ROUND(((EU58)*AV58*1),2)*BS58),2))*AU58)/100),2)+ROUND(((ROUND((ROUND(((AE58-(EU58))*AV58*1),2)*BS58),2)*AU58)/100),2)) -> 0 | DN58: 0 | DO58: 0 | DP58: 1 | DQ58: 1 | DU58: 1010 | DV58: шт. | DW58: шт. | DX58: 1 | EE58: 85133422 | EF58: 40 | EG58: Монтаж оборудования | EH58: 0 | EJ58: 2 | EK58: 73 | EL58: ТСН-2001.4-12. Технологические трубопроводы | EM58: ТСН-2001.4-12-1 | EO58: Поправка: Гл.12.Прил.8.п.8. 3_12.00.01.11.001 | EQ58: 0 | ER58: 3030.49 | ES58: 3030.49 | ET58: 0 | EU58: 0 | EV58: 0 | EW58: 0 | EX58: 0 | FQ58: 0 | FR58: 0 | FS58: 0 | FX58: 90 | FY58: 46 | GD58: 1 | GF58: -1962529768 | GG58: 2 | GH58: 1 | GI58: -2 | GJ58: 0 | GK58: 0 | GL58: =ROUND(IF(AND(BH58=3,BI58=3,FS58<>0),P58,0),2) -> 0 | GM58: =ROUND(O58+X58+Y58,2)+GX58 -> 12121.96 | GN58: =IF(OR(BI58=0,BI58=1),GM58-GX58,0) -> 0 | GO58: =IF(BI58=2,GM58-GX58,0) -> 12121.96 | GP58: =IF(BI58=4,GM58-GX58,0) -> 0 | GR58: 0 | GS58: 3 | GT58: 0 | GV58: =ROUND((GT58),6) -> 0 | GW58: 1 | GX58: =ROUND(HC58*I58,2) -> 0 | HA58: 0 | HB58: 0 | HC58: =GV58*GW58 -> 0 | HM58: *1 | HS58: 0 | IK58: 0
A59: 18 | B59: 1 | C59: 121 | E59: 12,1 | F59: 1.13-3-109 | G59: Клапан обратный, чугунный, фланцевый, температура рабочей среды от -10 до +100°С, условная пропускная способность 222 м3/ч, номинальное давление РN 1,6 МПа, номинальный диаметр DN 80 мм | H59: шт. | I59: =I57*J59 -> 4 | J59: 0.5 | K59: 0.5 | O59: =ROUND(CP59,2) -> 75762.25 | P59: =ROUND((ROUND((AC59*AW59*I59),2)*BC59),2) -> 75762.25 | Q59: =(ROUND((ROUND(((ET59)*AV59*I59),2)*BB59),2)+ROUND((ROUND(((AE59-(EU59))*AV59*I59),2)*BS59),2)) -> 0 | R59: =(ROUND((ROUND(((EU59)*AV59*I59),2)*BS59),2)+ROUND((ROUND(((AE59-(EU59))*AV59*I59),2)*BS59),2)) -> 0 | S59: =ROUND((ROUND((AF59*AV59*I59),2)*BA59),2) -> 0 | T59: =ROUND(CU59*I59,2) -> 0 | U59: =CV59*I59 -> 0 | V59: =CW59*I59 -> 0 | W59: =ROUND(CX59*I59,2) -> 0 | X59: =(ROUND((((S59+ROUND((ROUND(((EU59)*AV59*I59),2)*BS59),2))*AT59)/100),2)+ROUND(((ROUND((ROUND(((AE59-(EU59))*AV59*I59),2)*BS59),2)*AT59)/100),2)) -> 0 | Y59: =(ROUND((((S59+ROUND((ROUND(((EU59)*AV59*I59),2)*BS59),2))*AU59)/100),2)+ROUND(((ROUND((ROUND(((AE59-(EU59))*AV59*I59),2)*BS59),2)*AU59)/100),2)) -> 0 | AA59: 85739207 | AB59: =ROUND((AC59+AD59+AF59),6) -> 3030.49 | AC59: =ROUND((ES59),6) -> 3030.49 | AD59: =ROUND((((ET59)-(EU59))+AE59),6) -> 0 | AE59: =ROUND((EU59),6) -> 0 | AF59: =ROUND((EV59),6) -> 0 | AG59: =ROUND((AP59),6) -> 0 | AH59: =(EW59) -> 0 | AI59: =(EX59) -> 0 | AJ59: =(AS59) -> 0 | AK59: 3030.49 | AL59: 3030.49 | AM59: 0 | AN59: 0 | AO59: 0 | AP59: 0 | AQ59: 0 | AR59: 0 | AS59: 0 | AT59: 90 | AU59: 46 | AV59: 1 | AW59: 1 | AZ59: 1 | BA59: 1 | BB59: 1 | BC59: 6.25 | BH59: 3 | BI59: 2 | BJ59: ТСН-2001.1 Доп. 79, Р. 13, о. 3, поз. 109 | BM59: 73 | BN59: 0 | BO59: 1.13-3-109 | BP59: 1 | BQ59: 40 | BR59: 0 | BS59: 1 | BT59: 1 | BU59: 1 | BV59: 1 | BW59: 1 | BX59: 1 | BZ59: 90 | CA59: 46 | CE59: 1566 | CF59: 0 | CG59: 0 | CM59: 0 | CN59: Поправка: Гл.12.Прил.8.п.8. 3_12.00.01.11.001_x000D_ Наименование: При наличии напряженных и стесненных условий производства работ (стесненность, сложность складирования и транспортной логистики и т.п.) для объектов, расположенных в пределах круговой магистральной системы улиц "Садовое кольцо" города Москвы | CO59: 0 | CP59: =(P59+Q59+S59) -> 75762.25 | CQ59: =ROUND((ROUND((AC59*AW59*1),2)*BC59),2) -> 18940.56 | CR59: =(ROUND((ROUND(((ET59)*AV59*1),2)*BB59),2)+ROUND((ROUND(((AE59-(EU59))*AV59*1),2)*BS59),2)) -> 0 | CS59: =(ROUND((ROUND(((EU59)*AV59*1),2)*BS59),2)+ROUND((ROUND(((AE59-(EU59))*AV59*1),2)*BS59),2)) -> 0 | CT59: =ROUND((ROUND((AF59*AV59*1),2)*BA59),2) -> 0 | CU59: =AG59 -> 0 | CV59: =(AH59*AV59) -> 0 | CW59: =AI59 -> 0 | CX59: =AJ59 -> 0 | CY59: =(ROUND((((S59+ROUND((ROUND(((EU59)*AV59*1),2)*BS59),2))*AT59)/100),2)+ROUND(((ROUND((ROUND(((AE59-(EU59))*AV59*1),2)*BS59),2)*AT59)/100),2)) -> 0 | CZ59: =(ROUND((((S59+ROUND((ROUND(((EU59)*AV59*1),2)*BS59),2))*AU59)/100),2)+ROUND(((ROUND((ROUND(((AE59-(EU59))*AV59*1),2)*BS59),2)*AU59)/100),2)) -> 0 | DN59: 0 | DO59: 0 | DP59: 1 | DQ59: 1 | DU59: 1010 | DV59: шт. | DW59: шт. | DX59: 1 | EE59: 85133422 | EF59: 40 | EG59: Монтаж оборудования | EH59: 0 | EJ59: 2 | EK59: 73 | EL59: ТСН-2001.4-12. Технологические трубопроводы | EM59: ТСН-2001.4-12-1 | EO59: Поправка: Гл.12.Прил.8.п.8. 3_12.00.01.11.001 | EQ59: 0 | ER59: 3030.49 | ES59: 3030.49 | ET59: 0 | EU59: 0 | EV59: 0 | EW59: 0 | EX59: 0 | FQ59: 0 | FR59: 0 | FS59: 0 | FX59: 90 | FY59: 46 | GD59: 1 | GF59: -1962529768 | GG59: 2 | GH59: 1 | GI59: 2 | GJ59: 0 | GK59: 0 | GL59: =ROUND(IF(AND(BH59=3,BI59=3,FS59<>0),P59,0),2) -> 0 | GM59: =ROUND(O59+X59+Y59,2)+GX59 -> 75762.25 | GN59: =IF(OR(BI59=0,BI59=1),GM59-GX59,0) -> 0 | GO59: =IF(BI59=2,GM59-GX59,0) -> 75762.25 | GP59: =IF(BI59=4,GM59-GX59,0) -> 0 | GR59: 0 | GS59: 3 | GT59: 0 | GV59: =ROUND((GT59),6) -> 0 | GW59: 1 | GX59: =ROUND(HC59*I59,2) -> 0 | HA59: 0 | HB59: 0 | HC59: =GV59*GW59 -> 0 | HM59: *1 | HS59: 0 | IK59: 0
A60: 18 | B60: 1 | C60: 117 | E60: 12,2 | F60: 1.13-5-39 | G60: Затвор дисковый, поворотный, корпус из чугуна, диск из нержавеющей стали, с ручкой, номинальное давление PN 1,6 МПа, номинальный диаметр DN 80 мм | H60: шт. | I60: =I56*J60 -> 4 | J60: 0.5 | K60: 0.5 | O60: =ROUND(CP60,2) -> 7897.72 | P60: =ROUND((ROUND((AC60*AW60*I60),2)*BC60),2) -> 7897.72 | Q60: =(ROUND((ROUND(((ET60)*AV60*I60),2)*BB60),2)+ROUND((ROUND(((AE60-(EU60))*AV60*I60),2)*BS60),2)) -> 0 | R60: =(ROUND((ROUND(((EU60)*AV60*I60),2)*BS60),2)+ROUND((ROUND(((AE60-(EU60))*AV60*I60),2)*BS60),2)) -> 0 | S60: =ROUND((ROUND((AF60*AV60*I60),2)*BA60),2) -> 0 | T60: =ROUND(CU60*I60,2) -> 0 | U60: =CV60*I60 -> 0 | V60: =CW60*I60 -> 0 | W60: =ROUND(CX60*I60,2) -> 0 | X60: =(ROUND((((S60+ROUND((ROUND(((EU60)*AV60*I60),2)*BS60),2))*AT60)/100),2)+ROUND(((ROUND((ROUND(((AE60-(EU60))*AV60*I60),2)*BS60),2)*AT60)/100),2)) -> 0 | Y60: =(ROUND((((S60+ROUND((ROUND(((EU60)*AV60*I60),2)*BS60),2))*AU60)/100),2)+ROUND(((ROUND((ROUND(((AE60-(EU60))*AV60*I60),2)*BS60),2)*AU60)/100),2)) -> 0 | AA60: 85739205 | AB60: =ROUND((AC60+AD60+AF60),6) -> 1974.43 | AC60: =ROUND((ES60),6) -> 1974.43 | AD60: =ROUND((((ET60)-(EU60))+AE60),6) -> 0 | AE60: =ROUND((EU60),6) -> 0 | AF60: =ROUND((EV60),6) -> 0 | AG60: =ROUND((AP60),6) -> 0 | AH60: =(EW60) -> 0 | AI60: =(EX60) -> 0 | AJ60: =(AS60) -> 0 | AK60: 1974.43 | AL60: 1974.43 | AM60: 0 | AN60: 0 | AO60: 0 | AP60: 0 | AQ60: 0 | AR60: 0 | AS60: 0 | AT60: 90 | AU60: 46 | AV60: 1 | AW60: 1 | AZ60: 1 | BA60: 1 | BB60: 1 | BC60: 1 | BH60: 3 | BI60: 2 | BJ60: ТСН-2001.1 Доп. 79, Р. 13, о. 5, поз. 39 | BM60: 73 | BN60: 0 | BP60: 0 | BQ60: 40 | BR60: 0 | BS60: 1 | BT60: 1 | BU60: 1 | BV60: 1 | BW60: 1 | BX60: 1 | BZ60: 90 | CA60: 46 | CE60: 1566 | CF60: 0 | CG60: 0 | CM60: 0 | CN60: Поправка: Гл.12.Прил.8.п.8. 3_12.00.01.11.001_x000D_ Наименование: При наличии напряженных и стесненных условий производства работ (стесненность, сложность складирования и транспортной логистики и т.п.) для объектов, расположенных в пределах круговой магистральной системы улиц "Садовое кольцо" города Москвы | CO60: 0 | CP60: =(P60+Q60+S60) -> 7897.72 | CQ60: =ROUND((ROUND((AC60*AW60*1),2)*BC60),2) -> 1974.43 | CR60: =(ROUND((ROUND(((ET60)*AV60*1),2)*BB60),2)+ROUND((ROUND(((AE60-(EU60))*AV60*1),2)*BS60),2)) -> 0 | CS60: =(ROUND((ROUND(((EU60)*AV60*1),2)*BS60),2)+ROUND((ROUND(((AE60-(EU60))*AV60*1),2)*BS60),2)) -> 0 | CT60: =ROUND((ROUND((AF60*AV60*1),2)*BA60),2) -> 0 | CU60: =AG60 -> 0 | CV60: =(AH60*AV60) -> 0 | CW60: =AI60 -> 0 | CX60: =AJ60 -> 0 | CY60: =(ROUND((((S60+ROUND((ROUND(((EU60)*AV60*1),2)*BS60),2))*AT60)/100),2)+ROUND(((ROUND((ROUND(((AE60-(EU60))*AV60*1),2)*BS60),2)*AT60)/100),2)) -> 0 | CZ60: =(ROUND((((S60+ROUND((ROUND(((EU60)*AV60*1),2)*BS60),2))*AU60)/100),2)+ROUND(((ROUND((ROUND(((AE60-(EU60))*AV60*1),2)*BS60),2)*AU60)/100),2)) -> 0 | DN60: 0 | DO60: 0 | DP60: 1 | DQ60: 1 | DU60: 1010 | DV60: шт. | DW60: шт. | DX60: 1 | EE60: 85133422 | EF60: 40 | EG60: Монтаж оборудования | EH60: 0 | EJ60: 2 | EK60: 73 | EL60: ТСН-2001.4-12. Технологические трубопроводы | EM60: ТСН-2001.4-12-1 | EO60: Поправка: Гл.12.Прил.8.п.8. 3_12.00.01.11.001 | EQ60: 0 | ER60: 1974.43 | ES60: 1974.43 | ET60: 0 | EU60: 0 | EV60: 0 | EW60: 0 | EX60: 0 | FQ60: 0 | FR60: 0 | FS60: 0 | FX60: 90 | FY60: 46 | GD60: 1 | GF60: -2105799508 | GG60: 2 | GH60: 1 | GI60: -2 | GJ60: 0 | GK60: 0 | GL60: =ROUND(IF(AND(BH60=3,BI60=3,FS60<>0),P60,0),2) -> 0 | GM60: =ROUND(O60+X60+Y60,2)+GX60 -> 7897.72 | GN60: =IF(OR(BI60=0,BI60=1),GM60-GX60,0) -> 0 | GO60: =IF(BI60=2,GM60-GX60,0) -> 7897.72 | GP60: =IF(BI60=4,GM60-GX60,0) -> 0 | GR60: 0 | GS60: 3 | GT60: 0 | GV60: =ROUND((GT60),6) -> 0 | GW60: 1 | GX60: =ROUND(HC60*I60,2) -> 0 | HA60: 0 | HB60: 0 | HC60: =GV60*GW60 -> 0 | HM60: *1 | HS60: 0 | IK60: 0
A61: 18 | B61: 1 | C61: 122 | E61: 12,2 | F61: 1.13-5-39 | G61: Затвор дисковый, поворотный, корпус из чугуна, диск из нержавеющей стали, с ручкой, номинальное давление PN 1,6 МПа, номинальный диаметр DN 80 мм | H61: шт. | I61: =I57*J61 -> 4 | J61: 0.5 | K61: 0.5 | O61: =ROUND(CP61,2) -> 14057.94 | P61: =ROUND((ROUND((AC61*AW61*I61),2)*BC61),2) -> 14057.94 | Q61: =(ROUND((ROUND(((ET61)*AV61*I61),2)*BB61),2)+ROUND((ROUND(((AE61-(EU61))*AV61*I61),2)*BS61),2)) -> 0 | R61: =(ROUND((ROUND(((EU61)*AV61*I61),2)*BS61),2)+ROUND((ROUND(((AE61-(EU61))*AV61*I61),2)*BS61),2)) -> 0 | S61: =ROUND((ROUND((AF61*AV61*I61),2)*BA61),2) -> 0 | T61: =ROUND(CU61*I61,2) -> 0 | U61: =CV61*I61 -> 0 | V61: =CW61*I61 -> 0 | W61: =ROUND(CX61*I61,2) -> 0 | X61: =(ROUND((((S61+ROUND((ROUND(((EU61)*AV61*I61),2)*BS61),2))*AT61)/100),2)+ROUND(((ROUND((ROUND(((AE61-(EU61))*AV61*I61),2)*BS61),2)*AT61)/100),2)) -> 0 | Y61: =(ROUND((((S61+ROUND((ROUND(((EU61)*AV61*I61),2)*BS61),2))*AU61)/100),2)+ROUND(((ROUND((ROUND(((AE61-(EU61))*AV61*I61),2)*BS61),2)*AU61)/100),2)) -> 0 | AA61: 85739207 | AB61: =ROUND((AC61+AD61+AF61),6) -> 1974.43 | AC61: =ROUND((ES61),6) -> 1974.43 | AD61: =ROUND((((ET61)-(EU61))+AE61),6) -> 0 | AE61: =ROUND((EU61),6) -> 0 | AF61: =ROUND((EV61),6) -> 0 | AG61: =ROUND((AP61),6) -> 0 | AH61: =(EW61) -> 0 | AI61: =(EX61) -> 0 | AJ61: =(AS61) -> 0 | AK61: 1974.43 | AL61: 1974.43 | AM61: 0 | AN61: 0 | AO61: 0 | AP61: 0 | AQ61: 0 | AR61: 0 | AS61: 0 | AT61: 90 | AU61: 46 | AV61: 1 | AW61: 1 | AZ61: 1 | BA61: 1 | BB61: 1 | BC61: 1.78 | BH61: 3 | BI61: 2 | BJ61: ТСН-2001.1 Доп. 79, Р. 13, о. 5, поз. 39 | BM61: 73 | BN61: 0 | BO61: 1.13-5-39 | BP61: 1 | BQ61: 40 | BR61: 0 | BS61: 1 | BT61: 1 | BU61: 1 | BV61: 1 | BW61: 1 | BX61: 1 | BZ61: 90 | CA61: 46 | CE61: 1566 | CF61: 0 | CG61: 0 | CM61: 0 | CN61: Поправка: Гл.12.Прил.8.п.8. 3_12.00.01.11.001_x000D_ Наименование: При наличии напряженных и стесненных условий производства работ (стесненность, сложность складирования и транспортной логистики и т.п.) для объектов, расположенных в пределах круговой магистральной системы улиц "Садовое кольцо" города Москвы | CO61: 0 | CP61: =(P61+Q61+S61) -> 14057.94 | CQ61: =ROUND((ROUND((AC61*AW61*1),2)*BC61),2) -> 3514.49 | CR61: =(ROUND((ROUND(((ET61)*AV61*1),2)*BB61),2)+ROUND((ROUND(((AE61-(EU61))*AV61*1),2)*BS61),2)) -> 0 | CS61: =(ROUND((ROUND(((EU61)*AV61*1),2)*BS61),2)+ROUND((ROUND(((AE61-(EU61))*AV61*1),2)*BS61),2)) -> 0 | CT61: =ROUND((ROUND((AF61*AV61*1),2)*BA61),2) -> 0 | CU61: =AG61 -> 0 | CV61: =(AH61*AV61) -> 0 | CW61: =AI61 -> 0 | CX61: =AJ61 -> 0 | CY61: =(ROUND((((S61+ROUND((ROUND(((EU61)*AV61*1),2)*BS61),2))*AT61)/100),2)+ROUND(((ROUND((ROUND(((AE61-(EU61))*AV61*1),2)*BS61),2)*AT61)/100),2)) -> 0 | CZ61: =(ROUND((((S61+ROUND((ROUND(((EU61)*AV61*1),2)*BS61),2))*AU61)/100),2)+ROUND(((ROUND((ROUND(((AE61-(EU61))*AV61*1),2)*BS61),2)*AU61)/100),2)) -> 0 | DN61: 0 | DO61: 0 | DP61: 1 | DQ61: 1 | DU61: 1010 | DV61: шт. | DW61: шт. | DX61: 1 | EE61: 85133422 | EF61: 40 | EG61: Монтаж оборудования | EH61: 0 | EJ61: 2 | EK61: 73 | EL61: ТСН-2001.4-12. Технологические трубопроводы | EM61: ТСН-2001.4-12-1 | EO61: Поправка: Гл.12.Прил.8.п.8. 3_12.00.01.11.001 | EQ61: 0 | ER61: 1974.43 | ES61: 1974.43 | ET61: 0 | EU61: 0 | EV61: 0 | EW61: 0 | EX61: 0 | FQ61: 0 | FR61: 0 | FS61: 0 | FX61: 90 | FY61: 46 | GD61: 1 | GF61: -2105799508 | GG61: 2 | GH61: 1 | GI61: 2 | GJ61: 0 | GK61: 0 | GL61: =ROUND(IF(AND(BH61=3,BI61=3,FS61<>0),P61,0),2) -> 0 | GM61: =ROUND(O61+X61+Y61,2)+GX61 -> 14057.94 | GN61: =IF(OR(BI61=0,BI61=1),GM61-GX61,0) -> 0 | GO61: =IF(BI61=2,GM61-GX61,0) -> 14057.94 | GP61: =IF(BI61=4,GM61-GX61,0) -> 0 | GR61: 0 | GS61: 3 | GT61: 0 | GV61: =ROUND((GT61),6) -> 0 | GW61: 1 | GX61: =ROUND(HC61*I61,2) -> 0 | HA61: 0 | HB61: 0 | HC61: =GV61*GW61 -> 0 | HM61: *1 | HS61: 0 | IK61: 0
A62: 17 | B62: 1 | C62: =ROW(SmtRes!A129) -> 129 | D62: =ROW(EtalonRes!A159) -> 159 | E62: 13 | F62: 4.12-52-12 | G62: Монтаж арматуры приварной с ручным приводом или без привода на номинальное давление до 4 МПа, номинальный диаметр 150 мм | H62: 1 ШТ. | I62: 4 | J62: 0 | K62: 4 | O62: =ROUND(CP62,2) -> 593.22 | P62: =ROUND((ROUND((AC62*AW62*I62),2)*BC62),2) -> 27.34 | Q62: =(ROUND((ROUND((((ET62*1.2))*AV62*I62),2)*BB62),2)+ROUND((ROUND(((AE62-((EU62*1.2)))*AV62*I62),2)*BS62),2)) -> 74.67 | R62: =(ROUND((ROUND((((EU62*1.2))*AV62*I62),2)*BS62),2)+ROUND((ROUND(((AE62-((EU62*1.2)))*AV62*I62),2)*BS62),2)) -> 1.95 | S62: =ROUND((ROUND((AF62*AV62*I62),2)*BA62),2) -> 491.21 | T62: =ROUND(CU62*I62,2) -> 0 | U62: =CV62*I62 -> 38.92416 | V62: =CW62*I62 -> 0 | W62: =ROUND(CX62*I62,2) -> 0 | X62: =(ROUND((((S62+ROUND((ROUND((((EU62*1.2))*AV62*I62),2)*BS62),2))*AT62)/100),2)+ROUND(((ROUND((ROUND(((AE62-((EU62*1.2)))*AV62*I62),2)*BS62),2)*AT62)/100),2)) -> 443.84 | Y62: =(ROUND((((S62+ROUND((ROUND((((EU62*1.2))*AV62*I62),2)*BS62),2))*AU62)/100),2)+ROUND(((ROUND((ROUND(((AE62-((EU62*1.2)))*AV62*I62),2)*BS62),2)*AU62)/100),2)) -> 226.85 | AA62: 85739205 | AB62: =ROUND((AC62+AD62+AF62),6) -> 139.238 | AC62: =ROUND(((ES62*1)),6) -> 6.65 | AD62: =ROUND(((((ET62*1.2))-((EU62*1.2)))+AE62),6) -> 17.496 | AE62: =ROUND(((EU62*1.2)),6) -> 0.456 | AF62: =ROUND(((EV62*1.2)),6) -> 115.092 | AG62: =ROUND((AP62),6) -> 0 | AH62: =((EW62*1.2)) -> 9.12 | AI62: =((EX62*1.2)) -> 0 | AJ62: =(AS62) -> 0 | AK62: 117.14 | AL62: 6.65 | AM62: 14.58 | AN62: 0.38 | AO62: 95.91 | AP62: 0 | AQ62: 7.6 | AR62: 0 | AS62: 0 | AT62: 90 | AU62: 46 | AV62: 1.067 | AW62: 1.028 | AZ62: 1 | BA62: 1 | BB62: 1 | BC62: 1 | BH62: 0 | BI62: 2 | BJ62: ТСН-2001.4 Доп. 79, Сб. 12, т. 52, поз. 12 | BM62: 73 | BN62: 0 | BO62: 4.12-52-12 | BP62: 1 | BQ62: 40 | BR62: 0 | BS62: 1 | BT62: 1 | BU62: 1 | BV62: 1 | BW62: 1 | BX62: 1 | BZ62: 90 | CA62: 46 | CE62: 1566 | CF62: 0 | CG62: 0 | CM62: 0 | CN62: Поправка: Гл.12.Прил.8.п.8. 3_12.00.01.11.001 Наименование: При наличии напряженных и стесненных условий производства работ (стесненность, сложность складирования и транспортной логистики и т.п.) для объектов, расположенных в пределах круговой магистральной системы улиц "Садовое кольцо" города Москвы | CO62: 0 | CP62: =(P62+Q62+S62) -> 593.22 | CQ62: =ROUND((ROUND((AC62*AW62*1),2)*BC62),2) -> 6.84 | CR62: =(ROUND((ROUND((((ET62*1.2))*AV62*1),2)*BB62),2)+ROUND((ROUND(((AE62-((EU62*1.2)))*AV62*1),2)*BS62),2)) -> 18.67 | CS62: =(ROUND((ROUND((((EU62*1.2))*AV62*1),2)*BS62),2)+ROUND((ROUND(((AE62-((EU62*1.2)))*AV62*1),2)*BS62),2)) -> 0.49 | CT62: =ROUND((ROUND((AF62*AV62*1),2)*BA62),2) -> 122.8 | CU62: =AG62 -> 0 | CV62: =(AH62*AV62) -> 9.73104 | CW62: =AI62 -> 0 | CX62: =AJ62 -> 0 | CY62: =(ROUND((((S62+ROUND((ROUND((((EU62*1.2))*AV62*1),2)*BS62),2))*AT62)/100),2)+ROUND(((ROUND((ROUND(((AE62-((EU62*1.2)))*AV62*1),2)*BS62),2)*AT62)/100),2)) -> 442.53 | CZ62: =(ROUND((((S62+ROUND((ROUND((((EU62*1.2))*AV62*1),2)*BS62),2))*AU62)/100),2)+ROUND(((ROUND((ROUND(((AE62-((EU62*1.2)))*AV62*1),2)*BS62),2)*AU62)/100),2)) -> 226.18 | DB62: 27 | DD62: *1 | DE62: *1,2 | DF62: *1,2 | DG62: *1,2 | DI62: *1,2 | DJ62: *1,2 | DN62: 0 | DO62: 0 | DP62: 1 | DQ62: 1 | DU62: 1013 | DV62: 1 ШТ. | DW62: 1 ШТ. | DX62: 1 | EE62: 85133422 | EF62: 40 | EG62: Монтаж оборудования | EH62: 0 | EJ62: 2 | EK62: 73 | EL62: ТСН-2001.4-12. Технологические трубопроводы | EM62: ТСН-2001.4-12-1 | EO62: Поправка: Гл.12.Прил.8.п.8. 3_12.00.01.11.001 | EQ62: 0 | ER62: 117.14 | ES62: 6.65 | ET62: 14.58 | EU62: 0.38 | EV62: 95.91 | EW62: 7.6 | EX62: 0 | EY62: 0 | FQ62: 0 | FR62: 0 | FS62: 2 | FX62: 90 | FY62: 46 | GD62: 1 | GF62: 295159665 | GG62: 2 | GH62: 1 | GI62: 2 | GJ62: 0 | GK62: 0 | GL62: =ROUND(IF(AND(BH62=3,BI62=3,FS62<>0),P62,0),2) -> 0 | GM62: =ROUND(O62+X62+Y62,2)+GX62 -> 1263.91 | GN62: =IF(OR(BI62=0,BI62=1),GM62-GX62,0) -> 0 | GO62: =IF(BI62=2,GM62-GX62,0) -> 1263.91 | GP62: =IF(BI62=4,GM62-GX62,0) -> 0 | GR62: 0 | GS62: 3 | GT62: 0 | GV62: =ROUND((GT62),6) -> 0 | GW62: 1 | GX62: =ROUND(HC62*I62,2) -> 0 | HA62: 0 | HB62: 0 | HC62: =GV62*GW62 -> 0 | HS62: 0 | IK62: 0
A63: 17 | B63: 1 | C63: =ROW(SmtRes!A136) -> 136 | D63: =ROW(EtalonRes!A166) -> 166 | E63: 13 | F63: 4.12-52-12 | G63: Монтаж арматуры приварной с ручным приводом или без привода на номинальное давление до 4 МПа, номинальный диаметр 150 мм | H63: 1 ШТ. | I63: 4 | J63: 0 | K63: 4 | O63: =ROUND(CP63,2) -> 29023.84 | P63: =ROUND((ROUND((AC63*AW63*I63),2)*BC63),2) -> 292.81 | Q63: =(ROUND((ROUND((((ET63*1.2))*AV63*I63),2)*BB63),2)+ROUND((ROUND(((AE63-((EU63*1.2)))*AV63*I63),2)*BS63),2)) -> 1051.35 | R63: =(ROUND((ROUND((((EU63*1.2))*AV63*I63),2)*BS63),2)+ROUND((ROUND(((AE63-((EU63*1.2)))*AV63*I63),2)*BS63),2)) -> 109.88 | S63: =ROUND((ROUND((AF63*AV63*I63),2)*BA63),2) -> 27679.68 | T63: =ROUND(CU63*I63,2) -> 0 | U63: =CV63*I63 -> 38.92416 | V63: =CW63*I63 -> 0 | W63: =ROUND(CX63*I63,2) -> 0 | X63: =(ROUND((((S63+ROUND((ROUND((((EU63*1.2))*AV63*I63),2)*BS63),2))*AT63)/100),2)+ROUND(((ROUND((ROUND(((AE63-((EU63*1.2)))*AV63*I63),2)*BS63),2)*AT63)/100),2)) -> 25010.6 | Y63: =(ROUND((((S63+ROUND((ROUND((((EU63*1.2))*AV63*I63),2)*BS63),2))*AU63)/100),2)+ROUND(((ROUND((ROUND(((AE63-((EU63*1.2)))*AV63*I63),2)*BS63),2)*AU63)/100),2)) -> 12783.2 | AA63: 85739207 | AB63: =ROUND((AC63+AD63+AF63),6) -> 139.238 | AC63: =ROUND(((ES63*1)),6) -> 6.65 | AD63: =ROUND(((((ET63*1.2))-((EU63*1.2)))+AE63),6) -> 17.496 | AE63: =ROUND(((EU63*1.2)),6) -> 0.456 | AF63: =ROUND(((EV63*1.2)),6) -> 115.092 | AG63: =ROUND((AP63),6) -> 0 | AH63: =((EW63*1.2)) -> 9.12 | AI63: =((EX63*1.2)) -> 0 | AJ63: =(AS63) -> 0 | AK63: 117.14 | AL63: 6.65 | AM63: 14.58 | AN63: 0.38 | AO63: 95.91 | AP63: 0 | AQ63: 7.6 | AR63: 0 | AS63: 0 | AT63: 90 | AU63: 46 | AV63: 1.067 | AW63: 1.028 | AZ63: 1 | BA63: 56.35 | BB63: 14.08 | BC63: 10.71 | BH63: 0 | BI63: 2 | BJ63: ТСН-2001.4 Доп. 79, Сб. 12, т. 52, поз. 12 | BM63: 73 | BN63: 0 | BO63: 4.12-52-12 | BP63: 1 | BQ63: 40 | BR63: 0 | BS63: 56.35 | BT63: 1 | BU63: 1 | BV63: 1 | BW63: 1 | BX63: 1 | BZ63: 90 | CA63: 46 | CE63: 1566 | CF63: 0 | CG63: 0 | CM63: 0 | CN63: Поправка: Гл.12.Прил.8.п.8. 3_12.00.01.11.001 Наименование: При наличии напряженных и стесненных условий производства работ (стесненность, сложность складирования и транспортной логистики и т.п.) для объектов, расположенных в пределах круговой магистральной системы улиц "Садовое кольцо" города Москвы | CO63: 0 | CP63: =(P63+Q63+S63) -> 29023.84 | CQ63: =ROUND((ROUND((AC63*AW63*1),2)*BC63),2) -> 73.26 | CR63: =(ROUND((ROUND((((ET63*1.2))*AV63*1),2)*BB63),2)+ROUND((ROUND(((AE63-((EU63*1.2)))*AV63*1),2)*BS63),2)) -> 262.87 | CS63: =(ROUND((ROUND((((EU63*1.2))*AV63*1),2)*BS63),2)+ROUND((ROUND(((AE63-((EU63*1.2)))*AV63*1),2)*BS63),2)) -> 27.61 | CT63: =ROUND((ROUND((AF63*AV63*1),2)*BA63),2) -> 6919.78 | CU63: =AG63 -> 0 | CV63: =(AH63*AV63) -> 9.73104 | CW63: =AI63 -> 0 | CX63: =AJ63 -> 0 | CY63: =(ROUND((((S63+ROUND((ROUND((((EU63*1.2))*AV63*1),2)*BS63),2))*AT63)/100),2)+ROUND(((ROUND((ROUND(((AE63-((EU63*1.2)))*AV63*1),2)*BS63),2)*AT63)/100),2)) -> 24936.56 | CZ63: =(ROUND((((S63+ROUND((ROUND((((EU63*1.2))*AV63*1),2)*BS63),2))*AU63)/100),2)+ROUND(((ROUND((ROUND(((AE63-((EU63*1.2)))*AV63*1),2)*BS63),2)*AU63)/100),2)) -> 12745.35 | DB63: 28 | DD63: *1 | DE63: *1,2 | DF63: *1,2 | DG63: *1,2 | DI63: *1,2 | DJ63: *1,2 | DN63: 0 | DO63: 0 | DP63: 1 | DQ63: 1 | DU63: 1013 | DV63: 1 ШТ. | DW63: 1 ШТ. | DX63: 1 | EE63: 85133422 | EF63: 40 | EG63: Монтаж оборудования | EH63: 0 | EJ63: 2 | EK63: 73 | EL63: ТСН-2001.4-12. Технологические трубопроводы | EM63: ТСН-2001.4-12-1 | EO63: Поправка: Гл.12.Прил.8.п.8. 3_12.00.01.11.001 | EQ63: 0 | ER63: 117.14 | ES63: 6.65 | ET63: 14.58 | EU63: 0.38 | EV63: 95.91 | EW63: 7.6 | EX63: 0 | EY63: 0 | FQ63: 0 | FR63: 0 | FS63: 2 | FX63: 90 | FY63: 46 | GD63: 1 | GF63: 295159665 | GG63: 2 | GH63: 1 | GI63: 2 | GJ63: 0 | GK63: 0 | GL63: =ROUND(IF(AND(BH63=3,BI63=3,FS63<>0),P63,0),2) -> 0 | GM63: =ROUND(O63+X63+Y63,2)+GX63 -> 66817.64 | GN63: =IF(OR(BI63=0,BI63=1),GM63-GX63,0) -> 0 | GO63: =IF(BI63=2,GM63-GX63,0) -> 66817.64 | GP63: =IF(BI63=4,GM63-GX63,0) -> 0 | GR63: 0 | GS63: 3 | GT63: 0 | GV63: =ROUND((GT63),6) -> 0 | GW63: 1 | GX63: =ROUND(HC63*I63,2) -> 0 | HA63: 0 | HB63: 0 | HC63: =GV63*GW63 -> 0 | HS63: 0 | IK63: 0
A64: 18 | B64: 1 | C64: 129 | E64: 13,1 | F64: 1.12-11-52 | G64: Отвод крутоизогнутый, стальной, оцинкованный, ГОСТ 17375-01, наружный диаметр 159 мм, толщина стенки от 4,5 от 5,0 мм, под углом 90° | H64: шт. | I64: =I62*J64 -> 4 | J64: 1 | K64: 1 | O64: =ROUND(CP64,2) -> 1361.64 | P64: =ROUND((ROUND((AC64*AW64*I64),2)*BC64),2) -> 1361.64 | Q64: =(ROUND((ROUND(((ET64)*AV64*I64),2)*BB64),2)+ROUND((ROUND(((AE64-(EU64))*AV64*I64),2)*BS64),2)) -> 0 | R64: =(ROUND((ROUND(((EU64)*AV64*I64),2)*BS64),2)+ROUND((ROUND(((AE64-(EU64))*AV64*I64),2)*BS64),2)) -> 0 | S64: =ROUND((ROUND((AF64*AV64*I64),2)*BA64),2) -> 0 | T64: =ROUND(CU64*I64,2) -> 0 | U64: =CV64*I64 -> 0 | V64: =CW64*I64 -> 0 | W64: =ROUND(CX64*I64,2) -> 0 | X64: =(ROUND((((S64+ROUND((ROUND(((EU64)*AV64*I64),2)*BS64),2))*AT64)/100),2)+ROUND(((ROUND((ROUND(((AE64-(EU64))*AV64*I64),2)*BS64),2)*AT64)/100),2)) -> 0 | Y64: =(ROUND((((S64+ROUND((ROUND(((EU64)*AV64*I64),2)*BS64),2))*AU64)/100),2)+ROUND(((ROUND((ROUND(((AE64-(EU64))*AV64*I64),2)*BS64),2)*AU64)/100),2)) -> 0 | AA64: 85739205 | AB64: =ROUND((AC64+AD64+AF64),6) -> 340.41 | AC64: =ROUND((ES64),6) -> 340.41 | AD64: =ROUND((((ET64)-(EU64))+AE64),6) -> 0 | AE64: =ROUND((EU64),6) -> 0 | AF64: =ROUND((EV64),6) -> 0 | AG64: =ROUND((AP64),6) -> 0 | AH64: =(EW64) -> 0 | AI64: =(EX64) -> 0 | AJ64: =(AS64) -> 0 | AK64: 340.41 | AL64: 340.41 | AM64: 0 | AN64: 0 | AO64: 0 | AP64: 0 | AQ64: 0 | AR64: 0 | AS64: 0 | AT64: 90 | AU64: 46 | AV64: 1 | AW64: 1 | AZ64: 1 | BA64: 1 | BB64: 1 | BC64: 1 | BH64: 3 | BI64: 2 | BJ64: ТСН-2001.1 Доп. 79, Р. 12, о. 11, поз. 52 | BM64: 73 | BN64: 0 | BP64: 0 | BQ64: 40 | BR64: 0 | BS64: 1 | BT64: 1 | BU64: 1 | BV64: 1 | BW64: 1 | BX64: 1 | BZ64: 90 | CA64: 46 | CE64: 1566 | CF64: 0 | CG64: 0 | CM64: 0 | CN64: Поправка: Гл.12.Прил.8.п.8. 3_12.00.01.11.001_x000D_ Наименование: При наличии напряженных и стесненных условий производства работ (стесненность, сложность складирования и транспортной логистики и т.п.) для объектов, расположенных в пределах круговой магистральной системы улиц "Садовое кольцо" города Москвы | CO64: 0 | CP64: =(P64+Q64+S64) -> 1361.64 | CQ64: =ROUND((ROUND((AC64*AW64*1),2)*BC64),2) -> 340.41 | CR64: =(ROUND((ROUND(((ET64)*AV64*1),2)*BB64),2)+ROUND((ROUND(((AE64-(EU64))*AV64*1),2)*BS64),2)) -> 0 | CS64: =(ROUND((ROUND(((EU64)*AV64*1),2)*BS64),2)+ROUND((ROUND(((AE64-(EU64))*AV64*1),2)*BS64),2)) -> 0 | CT64: =ROUND((ROUND((AF64*AV64*1),2)*BA64),2) -> 0 | CU64: =AG64 -> 0 | CV64: =(AH64*AV64) -> 0 | CW64: =AI64 -> 0 | CX64: =AJ64 -> 0 | CY64: =(ROUND((((S64+ROUND((ROUND(((EU64)*AV64*1),2)*BS64),2))*AT64)/100),2)+ROUND(((ROUND((ROUND(((AE64-(EU64))*AV64*1),2)*BS64),2)*AT64)/100),2)) -> 0 | CZ64: =(ROUND((((S64+ROUND((ROUND(((EU64)*AV64*1),2)*BS64),2))*AU64)/100),2)+ROUND(((ROUND((ROUND(((AE64-(EU64))*AV64*1),2)*BS64),2)*AU64)/100),2)) -> 0 | DN64: 0 | DO64: 0 | DP64: 1 | DQ64: 1 | DU64: 1010 | DV64: шт. | DW64: шт. | DX64: 1 | EE64: 85133422 | EF64: 40 | EG64: Монтаж оборудования | EH64: 0 | EJ64: 2 | EK64: 73 | EL64: ТСН-2001.4-12. Технологические трубопроводы | EM64: ТСН-2001.4-12-1 | EO64: Поправка: Гл.12.Прил.8.п.8. 3_12.00.01.11.001 | EQ64: 0 | ER64: 340.41 | ES64: 340.41 | ET64: 0 | EU64: 0 | EV64: 0 | EW64: 0 | EX64: 0 | FQ64: 0 | FR64: 0 | FS64: 0 | FX64: 90 | FY64: 46 | GD64: 1 | GF64: 774186860 | GG64: 2 | GH64: 1 | GI64: -2 | GJ64: 0 | GK64: 0 | GL64: =ROUND(IF(AND(BH64=3,BI64=3,FS64<>0),P64,0),2) -> 0 | GM64: =ROUND(O64+X64+Y64,2)+GX64 -> 1361.64 | GN64: =IF(OR(BI64=0,BI64=1),GM64-GX64,0) -> 0 | GO64: =IF(BI64=2,GM64-GX64,0) -> 1361.64 | GP64: =IF(BI64=4,GM64-GX64,0) -> 0 | GR64: 0 | GS64: 3 | GT64: 0 | GV64: =ROUND((GT64),6) -> 0 | GW64: 1 | GX64: =ROUND(HC64*I64,2) -> 0 | HA64: 0 | HB64: 0 | HC64: =GV64*GW64 -> 0 | HM64: *1 | HS64: 0 | IK64: 0
A65: 18 | B65: 1 | C65: 136 | E65: 13,1 | F65: 1.12-11-52 | G65: Отвод крутоизогнутый, стальной, оцинкованный, ГОСТ 17375-01, наружный диаметр 159 мм, толщина стенки от 4,5 от 5,0 мм, под углом 90° | H65: шт. | I65: =I63*J65 -> 4 | J65: 1 | K65: 1 | O65: =ROUND(CP65,2) -> 6127.38 | P65: =ROUND((ROUND((AC65*AW65*I65),2)*BC65),2) -> 6127.38 | Q65: =(ROUND((ROUND(((ET65)*AV65*I65),2)*BB65),2)+ROUND((ROUND(((AE65-(EU65))*AV65*I65),2)*BS65),2)) -> 0 | R65: =(ROUND((ROUND(((EU65)*AV65*I65),2)*BS65),2)+ROUND((ROUND(((AE65-(EU65))*AV65*I65),2)*BS65),2)) -> 0 | S65: =ROUND((ROUND((AF65*AV65*I65),2)*BA65),2) -> 0 | T65: =ROUND(CU65*I65,2) -> 0 | U65: =CV65*I65 -> 0 | V65: =CW65*I65 -> 0 | W65: =ROUND(CX65*I65,2) -> 0 | X65: =(ROUND((((S65+ROUND((ROUND(((EU65)*AV65*I65),2)*BS65),2))*AT65)/100),2)+ROUND(((ROUND((ROUND(((AE65-(EU65))*AV65*I65),2)*BS65),2)*AT65)/100),2)) -> 0 | Y65: =(ROUND((((S65+ROUND((ROUND(((EU65)*AV65*I65),2)*BS65),2))*AU65)/100),2)+ROUND(((ROUND((ROUND(((AE65-(EU65))*AV65*I65),2)*BS65),2)*AU65)/100),2)) -> 0 | AA65: 85739207 | AB65: =ROUND((AC65+AD65+AF65),6) -> 340.41 | AC65: =ROUND((ES65),6) -> 340.41 | AD65: =ROUND((((ET65)-(EU65))+AE65),6) -> 0 | AE65: =ROUND((EU65),6) -> 0 | AF65: =ROUND((EV65),6) -> 0 | AG65: =ROUND((AP65),6) -> 0 | AH65: =(EW65) -> 0 | AI65: =(EX65) -> 0 | AJ65: =(AS65) -> 0 | AK65: 340.41 | AL65: 340.41 | AM65: 0 | AN65: 0 | AO65: 0 | AP65: 0 | AQ65: 0 | AR65: 0 | AS65: 0 | AT65: 90 | AU65: 46 | AV65: 1 | AW65: 1 | AZ65: 1 | BA65: 1 | BB65: 1 | BC65: 4.5 | BH65: 3 | BI65: 2 | BJ65: ТСН-2001.1 Доп. 79, Р. 12, о. 11, поз. 52 | BM65: 73 | BN65: 0 | BO65: 1.12-11-52 | BP65: 1 | BQ65: 40 | BR65: 0 | BS65: 1 | BT65: 1 | BU65: 1 | BV65: 1 | BW65: 1 | BX65: 1 | BZ65: 90 | CA65: 46 | CE65: 1566 | CF65: 0 | CG65: 0 | CM65: 0 | CN65: Поправка: Гл.12.Прил.8.п.8. 3_12.00.01.11.001_x000D_ Наименование: При наличии напряженных и стесненных условий производства работ (стесненность, сложность складирования и транспортной логистики и т.п.) для объектов, расположенных в пределах круговой магистральной системы улиц "Садовое кольцо" города Москвы | CO65: 0 | CP65: =(P65+Q65+S65) -> 6127.38 | CQ65: =ROUND((ROUND((AC65*AW65*1),2)*BC65),2) -> 1531.85 | CR65: =(ROUND((ROUND(((ET65)*AV65*1),2)*BB65),2)+ROUND((ROUND(((AE65-(EU65))*AV65*1),2)*BS65),2)) -> 0 | CS65: =(ROUND((ROUND(((EU65)*AV65*1),2)*BS65),2)+ROUND((ROUND(((AE65-(EU65))*AV65*1),2)*BS65),2)) -> 0 | CT65: =ROUND((ROUND((AF65*AV65*1),2)*BA65),2) -> 0 | CU65: =AG65 -> 0 | CV65: =(AH65*AV65) -> 0 | CW65: =AI65 -> 0 | CX65: =AJ65 -> 0 | CY65: =(ROUND((((S65+ROUND((ROUND(((EU65)*AV65*1),2)*BS65),2))*AT65)/100),2)+ROUND(((ROUND((ROUND(((AE65-(EU65))*AV65*1),2)*BS65),2)*AT65)/100),2)) -> 0 | CZ65: =(ROUND((((S65+ROUND((ROUND(((EU65)*AV65*1),2)*BS65),2))*AU65)/100),2)+ROUND(((ROUND((ROUND(((AE65-(EU65))*AV65*1),2)*BS65),2)*AU65)/100),2)) -> 0 | DN65: 0 | DO65: 0 | DP65: 1 | DQ65: 1 | DU65: 1010 | DV65: шт. | DW65: шт. | DX65: 1 | EE65: 85133422 | EF65: 40 | EG65: Монтаж оборудования | EH65: 0 | EJ65: 2 | EK65: 73 | EL65: ТСН-2001.4-12. Технологические трубопроводы | EM65: ТСН-2001.4-12-1 | EO65: Поправка: Гл.12.Прил.8.п.8. 3_12.00.01.11.001 | EQ65: 0 | ER65: 340.41 | ES65: 340.41 | ET65: 0 | EU65: 0 | EV65: 0 | EW65: 0 | EX65: 0 | FQ65: 0 | FR65: 0 | FS65: 0 | FX65: 90 | FY65: 46 | GD65: 1 | GF65: 774186860 | GG65: 2 | GH65: 1 | GI65: 2 | GJ65: 0 | GK65: 0 | GL65: =ROUND(IF(AND(BH65=3,BI65=3,FS65<>0),P65,0),2) -> 0 | GM65: =ROUND(O65+X65+Y65,2)+GX65 -> 6127.38 | GN65: =IF(OR(BI65=0,BI65=1),GM65-GX65,0) -> 0 | GO65: =IF(BI65=2,GM65-GX65,0) -> 6127.38 | GP65: =IF(BI65=4,GM65-GX65,0) -> 0 | GR65: 0 | GS65: 3 | GT65: 0 | GV65: =ROUND((GT65),6) -> 0 | GW65: 1 | GX65: =ROUND(HC65*I65,2) -> 0 | HA65: 0 | HB65: 0 | HC65: =GV65*GW65 -> 0 | HM65: *1 | HS65: 0 | IK65: 0
A66: 17 | B66: 1 | C66: =ROW(SmtRes!A144) -> 144 | D66: =ROW(EtalonRes!A173) -> 173 | E66: 14 | F66: 4.12-52-10 | G66: Монтаж арматуры приварной с ручным приводом или без привода на номинальное давление до 4 МПа, номинальный диаметр 100 мм | H66: 1 ШТ. | I66: =ROUND(1+9+6,9) -> 16 | J66: 0 | K66: =ROUND(1+9+6,9) -> 16 | O66: =ROUND(CP66,2) -> 1632.49 | P66: =ROUND((ROUND((AC66*AW66*I66),2)*BC66),2) -> 71.22 | Q66: =(ROUND((ROUND((((ET66*1.2))*AV66*I66),2)*BB66),2)+ROUND((ROUND(((AE66-((EU66*1.2)))*AV66*I66),2)*BS66),2)) -> 165.12 | R66: =(ROUND((ROUND((((EU66*1.2))*AV66*I66),2)*BS66),2)+ROUND((ROUND(((AE66-((EU66*1.2)))*AV66*I66),2)*BS66),2)) -> 5.12 | S66: =ROUND((ROUND((AF66*AV66*I66),2)*BA66),2) -> 1396.15 | T66: =ROUND(CU66*I66,2) -> 0 | U66: =CV66*I66 -> 110.62656 | V66: =CW66*I66 -> 0 | W66: =ROUND(CX66*I66,2) -> 0 | X66: =(ROUND((((S66+ROUND((ROUND((((EU66*1.2))*AV66*I66),2)*BS66),2))*AT66)/100),2)+ROUND(((ROUND((ROUND(((AE66-((EU66*1.2)))*AV66*I66),2)*BS66),2)*AT66)/100),2)) -> 1261.14 | Y66: =(ROUND((((S66+ROUND((ROUND((((EU66*1.2))*AV66*I66),2)*BS66),2))*AU66)/100),2)+ROUND(((ROUND((ROUND(((AE66-((EU66*1.2)))*AV66*I66),2)*BS66),2)*AU66)/100),2)) -> 644.58 | AA66: 85739205 | AB66: =ROUND((AC66+AD66+AF66),6) -> 95.782 | AC66: =ROUND(((ES66*1)),6) -> 4.33 | AD66: =ROUND(((((ET66*1.2))-((EU66*1.2)))+AE66),6) -> 9.672 | AE66: =ROUND(((EU66*1.2)),6) -> 0.3 | AF66: =ROUND(((EV66*1.2)),6) -> 81.78 | AG66: =ROUND((AP66),6) -> 0 | AH66: =((EW66*1.2)) -> 6.48 | AI66: =((EX66*1.2)) -> 0 | AJ66: =(AS66) -> 0 | AK66: 80.54 | AL66: 4.33 | AM66: 8.06 | AN66: 0.25 | AO66: 68.15 | AP66: 0 | AQ66: 5.4 | AR66: 0 | AS66: 0 | AT66: 90 | AU66: 46 | AV66: 1.067 | AW66: 1.028 | AZ66: 1 | BA66: 1 | BB66: 1 | BC66: 1 | BH66: 0 | BI66: 2 | BJ66: ТСН-2001.4 Доп. 80, Сб. 12, т. 52, поз. 10 | BM66: 73 | BN66: 0 | BO66: 4.12-52-10 | BP66: 1 | BQ66: 40 | BR66: 0 | BS66: 1 | BT66: 1 | BU66: 1 | BV66: 1 | BW66: 1 | BX66: 1 | BZ66: 90 | CA66: 46 | CE66: 1566 | CF66: 0 | CG66: 0 | CM66: 0 | CN66: Поправка: Гл.12.Прил.8.п.8. 3_12.00.01.11.001 Наименование: При наличии напряженных и стесненных условий производства работ (стесненность, сложность складирования и транспортной логистики и т.п.) для объектов, расположенных в пределах круговой магистральной системы улиц "Садовое кольцо" города Москвы | CO66: 0 | CP66: =(P66+Q66+S66) -> 1632.49 | CQ66: =ROUND((ROUND((AC66*AW66*1),2)*BC66),2) -> 4.45 | CR66: =(ROUND((ROUND((((ET66*1.2))*AV66*1),2)*BB66),2)+ROUND((ROUND(((AE66-((EU66*1.2)))*AV66*1),2)*BS66),2)) -> 10.32 | CS66: =(ROUND((ROUND((((EU66*1.2))*AV66*1),2)*BS66),2)+ROUND((ROUND(((AE66-((EU66*1.2)))*AV66*1),2)*BS66),2)) -> 0.32 | CT66: =ROUND((ROUND((AF66*AV66*1),2)*BA66),2) -> 87.26 | CU66: =AG66 -> 0 | CV66: =(AH66*AV66) -> 6.91416 | CW66: =AI66 -> 0 | CX66: =AJ66 -> 0 | CY66: =(ROUND((((S66+ROUND((ROUND((((EU66*1.2))*AV66*1),2)*BS66),2))*AT66)/100),2)+ROUND(((ROUND((ROUND(((AE66-((EU66*1.2)))*AV66*1),2)*BS66),2)*AT66)/100),2)) -> 1256.82 | CZ66: =(ROUND((((S66+ROUND((ROUND((((EU66*1.2))*AV66*1),2)*BS66),2))*AU66)/100),2)+ROUND(((ROUND((ROUND(((AE66-((EU66*1.2)))*AV66*1),2)*BS66),2)*AU66)/100),2)) -> 642.38 | DB66: 29 | DD66: *1 | DE66: *1,2 | DF66: *1,2 | DG66: *1,2 | DI66: *1,2 | DJ66: *1,2 | DN66: 0 | DO66: 0 | DP66: 1 | DQ66: 1 | DU66: 1013 | DV66: 1 ШТ. | DW66: 1 ШТ. | DX66: 1 | EE66: 85133422 | EF66: 40 | EG66: Монтаж оборудования | EH66: 0 | EJ66: 2 | EK66: 73 | EL66: ТСН-2001.4-12. Технологические трубопроводы | EM66: ТСН-2001.4-12-1 | EO66: Поправка: Гл.12.Прил.8.п.8. 3_12.00.01.11.001 | EQ66: 0 | ER66: 80.54 | ES66: 4.33 | ET66: 8.06 | EU66: 0.25 | EV66: 68.15 | EW66: 5.4 | EX66: 0 | EY66: 0 | FQ66: 0 | FR66: 0 | FS66: 2 | FX66: 90 | FY66: 46 | GD66: 1 | GF66: -914769333 | GG66: 2 | GH66: 1 | GI66: 2 | GJ66: 0 | GK66: 0 | GL66: =ROUND(IF(AND(BH66=3,BI66=3,FS66<>0),P66,0),2) -> 0 | GM66: =ROUND(O66+X66+Y66,2)+GX66 -> 3538.21 | GN66: =IF(OR(BI66=0,BI66=1),GM66-GX66,0) -> 0 | GO66: =IF(BI66=2,GM66-GX66,0) -> 3538.21 | GP66: =IF(BI66=4,GM66-GX66,0) -> 0 | GR66: 0 | GS66: 3 | GT66: 0 | GV66: =ROUND((GT66),6) -> 0 | GW66: 1 | GX66: =ROUND(HC66*I66,2) -> 0 | HA66: 0 | HB66: 0 | HC66: =GV66*GW66 -> 0 | HS66: 0 | IK66: 0
A67: 17 | B67: 1 | C67: =ROW(SmtRes!A152) -> 152 | D67: =ROW(EtalonRes!A180) -> 180 | E67: 14 | F67: 4.12-52-10 | G67: Монтаж арматуры приварной с ручным приводом или без привода на номинальное давление до 4 МПа, номинальный диаметр 100 мм | H67: 1 ШТ. | I67: =ROUND(1+9+6,9) -> 16 | J67: 0 | K67: =ROUND(1+9+6,9) -> 16 | O67: =ROUND(CP67,2) -> 81773.63 | P67: =ROUND((ROUND((AC67*AW67*I67),2)*BC67),2) -> 754.22 | Q67: =(ROUND((ROUND((((ET67*1.2))*AV67*I67),2)*BB67),2)+ROUND((ROUND(((AE67-((EU67*1.2)))*AV67*I67),2)*BS67),2)) -> 2346.36 | R67: =(ROUND((ROUND((((EU67*1.2))*AV67*I67),2)*BS67),2)+ROUND((ROUND(((AE67-((EU67*1.2)))*AV67*I67),2)*BS67),2)) -> 288.51 | S67: =ROUND((ROUND((AF67*AV67*I67),2)*BA67),2) -> 78673.05 | T67: =ROUND(CU67*I67,2) -> 0 | U67: =CV67*I67 -> 110.62656 | V67: =CW67*I67 -> 0 | W67: =ROUND(CX67*I67,2) -> 0 | X67: =(ROUND((((S67+ROUND((ROUND((((EU67*1.2))*AV67*I67),2)*BS67),2))*AT67)/100),2)+ROUND(((ROUND((ROUND(((AE67-((EU67*1.2)))*AV67*I67),2)*BS67),2)*AT67)/100),2)) -> 71065.4 | Y67: =(ROUND((((S67+ROUND((ROUND((((EU67*1.2))*AV67*I67),2)*BS67),2))*AU67)/100),2)+ROUND(((ROUND((ROUND(((AE67-((EU67*1.2)))*AV67*I67),2)*BS67),2)*AU67)/100),2)) -> 36322.32 | AA67: 85739207 | AB67: =ROUND((AC67+AD67+AF67),6) -> 95.782 | AC67: =ROUND(((ES67*1)),6) -> 4.33 | AD67: =ROUND(((((ET67*1.2))-((EU67*1.2)))+AE67),6) -> 9.672 | AE67: =ROUND(((EU67*1.2)),6) -> 0.3 | AF67: =ROUND(((EV67*1.2)),6) -> 81.78 | AG67: =ROUND((AP67),6) -> 0 | AH67: =((EW67*1.2)) -> 6.48 | AI67: =((EX67*1.2)) -> 0 | AJ67: =(AS67) -> 0 | AK67: 80.54 | AL67: 4.33 | AM67: 8.06 | AN67: 0.25 | AO67: 68.15 | AP67: 0 | AQ67: 5.4 | AR67: 0 | AS67: 0 | AT67: 90 | AU67: 46 | AV67: 1.067 | AW67: 1.028 | AZ67: 1 | BA67: 56.35 | BB67: 14.21 | BC67: 10.59 | BH67: 0 | BI67: 2 | BJ67: ТСН-2001.4 Доп. 80, Сб. 12, т. 52, поз. 10 | BM67: 73 | BN67: 0 | BO67: 4.12-52-10 | BP67: 1 | BQ67: 40 | BR67: 0 | BS67: 56.35 | BT67: 1 | BU67: 1 | BV67: 1 | BW67: 1 | BX67: 1 | BZ67: 90 | CA67: 46 | CE67: 1566 | CF67: 0 | CG67: 0 | CM67: 0 | CN67: Поправка: Гл.12.Прил.8.п.8. 3_12.00.01.11.001 Наименование: При наличии напряженных и стесненных условий производства работ (стесненность, сложность складирования и транспортной логистики и т.п.) для объектов, расположенных в пределах круговой магистральной системы улиц "Садовое кольцо" города Москвы | CO67: 0 | CP67: =(P67+Q67+S67) -> 81773.63 | CQ67: =ROUND((ROUND((AC67*AW67*1),2)*BC67),2) -> 47.13 | CR67: =(ROUND((ROUND((((ET67*1.2))*AV67*1),2)*BB67),2)+ROUND((ROUND(((AE67-((EU67*1.2)))*AV67*1),2)*BS67),2)) -> 146.65 | CS67: =(ROUND((ROUND((((EU67*1.2))*AV67*1),2)*BS67),2)+ROUND((ROUND(((AE67-((EU67*1.2)))*AV67*1),2)*BS67),2)) -> 18.03 | CT67: =ROUND((ROUND((AF67*AV67*1),2)*BA67),2) -> 4917.1 | CU67: =AG67 -> 0 | CV67: =(AH67*AV67) -> 6.91416 | CW67: =AI67 -> 0 | CX67: =AJ67 -> 0 | CY67: =(ROUND((((S67+ROUND((ROUND((((EU67*1.2))*AV67*1),2)*BS67),2))*AT67)/100),2)+ROUND(((ROUND((ROUND(((AE67-((EU67*1.2)))*AV67*1),2)*BS67),2)*AT67)/100),2)) -> 70821.97 | CZ67: =(ROUND((((S67+ROUND((ROUND((((EU67*1.2))*AV67*1),2)*BS67),2))*AU67)/100),2)+ROUND(((ROUND((ROUND(((AE67-((EU67*1.2)))*AV67*1),2)*BS67),2)*AU67)/100),2)) -> 36197.9 | DB67: 30 | DD67: *1 | DE67: *1,2 | DF67: *1,2 | DG67: *1,2 | DI67: *1,2 | DJ67: *1,2 | DN67: 0 | DO67: 0 | DP67: 1 | DQ67: 1 | DU67: 1013 | DV67: 1 ШТ. | DW67: 1 ШТ. | DX67: 1 | EE67: 85133422 | EF67: 40 | EG67: Монтаж оборудования | EH67: 0 | EJ67: 2 | EK67: 73 | EL67: ТСН-2001.4-12. Технологические трубопроводы | EM67: ТСН-2001.4-12-1 | EO67: Поправка: Гл.12.Прил.8.п.8. 3_12.00.01.11.001 | EQ67: 0 | ER67: 80.54 | ES67: 4.33 | ET67: 8.06 | EU67: 0.25 | EV67: 68.15 | EW67: 5.4 | EX67: 0 | EY67: 0 | FQ67: 0 | FR67: 0 | FS67: 2 | FX67: 90 | FY67: 46 | GD67: 1 | GF67: -914769333 | GG67: 2 | GH67: 1 | GI67: 2 | GJ67: 0 | GK67: 0 | GL67: =ROUND(IF(AND(BH67=3,BI67=3,FS67<>0),P67,0),2) -> 0 | GM67: =ROUND(O67+X67+Y67,2)+GX67 -> 189161.35 | GN67: =IF(OR(BI67=0,BI67=1),GM67-GX67,0) -> 0 | GO67: =IF(BI67=2,GM67-GX67,0) -> 189161.35 | GP67: =IF(BI67=4,GM67-GX67,0) -> 0 | GR67: 0 | GS67: 3 | GT67: 0 | GV67: =ROUND((GT67),6) -> 0 | GW67: 1 | GX67: =ROUND(HC67*I67,2) -> 0 | HA67: 0 | HB67: 0 | HC67: =GV67*GW67 -> 0 | HS67: 0 | IK67: 0
A68: 18 | B68: 1 | C68: 144 | E68: 14,1 | F68: 1.12-9-21 | G68: Фланец стальной плоский приварной с соединительным выступом, ГОСТ 33259-2015, из стали Ст3сп, номинальное давление PN 1,6 МПа, номинальный диаметр DN 100 мм | H68: шт. | I68: =I66*J68 -> 20 | J68: 1.25 | K68: 1.25 | O68: =ROUND(CP68,2) -> 2144.6 | P68: =ROUND((ROUND((AC68*AW68*I68),2)*BC68),2) -> 2144.6 | Q68: =(ROUND((ROUND(((ET68)*AV68*I68),2)*BB68),2)+ROUND((ROUND(((AE68-(EU68))*AV68*I68),2)*BS68),2)) -> 0 | R68: =(ROUND((ROUND(((EU68)*AV68*I68),2)*BS68),2)+ROUND((ROUND(((AE68-(EU68))*AV68*I68),2)*BS68),2)) -> 0 | S68: =ROUND((ROUND((AF68*AV68*I68),2)*BA68),2) -> 0 | T68: =ROUND(CU68*I68,2) -> 0 | U68: =CV68*I68 -> 0 | V68: =CW68*I68 -> 0 | W68: =ROUND(CX68*I68,2) -> 0 | X68: =(ROUND((((S68+ROUND((ROUND(((EU68)*AV68*I68),2)*BS68),2))*AT68)/100),2)+ROUND(((ROUND((ROUND(((AE68-(EU68))*AV68*I68),2)*BS68),2)*AT68)/100),2)) -> 0 | Y68: =(ROUND((((S68+ROUND((ROUND(((EU68)*AV68*I68),2)*BS68),2))*AU68)/100),2)+ROUND(((ROUND((ROUND(((AE68-(EU68))*AV68*I68),2)*BS68),2)*AU68)/100),2)) -> 0 | AA68: 85739205 | AB68: =ROUND((AC68+AD68+AF68),6) -> 107.23 | AC68: =ROUND((ES68),6) -> 107.23 | AD68: =ROUND((((ET68)-(EU68))+AE68),6) -> 0 | AE68: =ROUND((EU68),6) -> 0 | AF68: =ROUND((EV68),6) -> 0 | AG68: =ROUND((AP68),6) -> 0 | AH68: =(EW68) -> 0 | AI68: =(EX68) -> 0 | AJ68: =(AS68) -> 0 | AK68: 107.23 | AL68: 107.23 | AM68: 0 | AN68: 0 | AO68: 0 | AP68: 0 | AQ68: 0 | AR68: 0 | AS68: 0 | AT68: 90 | AU68: 46 | AV68: 1 | AW68: 1 | AZ68: 1 | BA68: 1 | BB68: 1 | BC68: 1 | BH68: 3 | BI68: 2 | BJ68: ТСН-2001.1 Доп. 80, Р. 12, о. 9, поз. 21 | BM68: 73 | BN68: 0 | BP68: 0 | BQ68: 40 | BR68: 0 | BS68: 1 | BT68: 1 | BU68: 1 | BV68: 1 | BW68: 1 | BX68: 1 | BZ68: 90 | CA68: 46 | CE68: 1566 | CF68: 0 | CG68: 0 | CM68: 0 | CN68: Поправка: Гл.12.Прил.8.п.8. 3_12.00.01.11.001_x000D_ Наименование: При наличии напряженных и стесненных условий производства работ (стесненность, сложность складирования и транспортной логистики и т.п.) для объектов, расположенных в пределах круговой магистральной системы улиц "Садовое кольцо" города Москвы | CO68: 0 | CP68: =(P68+Q68+S68) -> 2144.6 | CQ68: =ROUND((ROUND((AC68*AW68*1),2)*BC68),2) -> 107.23 | CR68: =(ROUND((ROUND(((ET68)*AV68*1),2)*BB68),2)+ROUND((ROUND(((AE68-(EU68))*AV68*1),2)*BS68),2)) -> 0 | CS68: =(ROUND((ROUND(((EU68)*AV68*1),2)*BS68),2)+ROUND((ROUND(((AE68-(EU68))*AV68*1),2)*BS68),2)) -> 0 | CT68: =ROUND((ROUND((AF68*AV68*1),2)*BA68),2) -> 0 | CU68: =AG68 -> 0 | CV68: =(AH68*AV68) -> 0 | CW68: =AI68 -> 0 | CX68: =AJ68 -> 0 | CY68: =(ROUND((((S68+ROUND((ROUND(((EU68)*AV68*1),2)*BS68),2))*AT68)/100),2)+ROUND(((ROUND((ROUND(((AE68-(EU68))*AV68*1),2)*BS68),2)*AT68)/100),2)) -> 0 | CZ68: =(ROUND((((S68+ROUND((ROUND(((EU68)*AV68*1),2)*BS68),2))*AU68)/100),2)+ROUND(((ROUND((ROUND(((AE68-(EU68))*AV68*1),2)*BS68),2)*AU68)/100),2)) -> 0 | DN68: 0 | DO68: 0 | DP68: 1 | DQ68: 1 | DU68: 1010 | DV68: шт. | DW68: шт. | DX68: 1 | EE68: 85133422 | EF68: 40 | EG68: Монтаж оборудования | EH68: 0 | EJ68: 2 | EK68: 73 | EL68: ТСН-2001.4-12. Технологические трубопроводы | EM68: ТСН-2001.4-12-1 | EO68: Поправка: Гл.12.Прил.8.п.8. 3_12.00.01.11.001 | EQ68: 0 | ER68: 107.23 | ES68: 107.23 | ET68: 0 | EU68: 0 | EV68: 0 | EW68: 0 | EX68: 0 | FQ68: 0 | FR68: 0 | FS68: 0 | FX68: 90 | FY68: 46 | GD68: 1 | GF68: 235948314 | GG68: 2 | GH68: 1 | GI68: -2 | GJ68: 0 | GK68: 0 | GL68: =ROUND(IF(AND(BH68=3,BI68=3,FS68<>0),P68,0),2) -> 0 | GM68: =ROUND(O68+X68+Y68,2)+GX68 -> 2144.6 | GN68: =IF(OR(BI68=0,BI68=1),GM68-GX68,0) -> 0 | GO68: =IF(BI68=2,GM68-GX68,0) -> 2144.6 | GP68: =IF(BI68=4,GM68-GX68,0) -> 0 | GR68: 0 | GS68: 3 | GT68: 0 | GV68: =ROUND((GT68),6) -> 0 | GW68: 1 | GX68: =ROUND(HC68*I68,2) -> 0 | HA68: 0 | HB68: 0 | HC68: =GV68*GW68 -> 0 | HM68: *1 | HS68: 0 | IK68: 0
A69: 18 | B69: 1 | C69: 152 | E69: 14,1 | F69: 1.12-9-21 | G69: Фланец стальной плоский приварной с соединительным выступом, ГОСТ 33259-2015, из стали Ст3сп, номинальное давление PN 1,6 МПа, номинальный диаметр DN 100 мм | H69: шт. | I69: =I67*J69 -> 20 | J69: 1.25 | K69: 1.25 | O69: =ROUND(CP69,2) -> 14883.52 | P69: =ROUND((ROUND((AC69*AW69*I69),2)*BC69),2) -> 14883.52 | Q69: =(ROUND((ROUND(((ET69)*AV69*I69),2)*BB69),2)+ROUND((ROUND(((AE69-(EU69))*AV69*I69),2)*BS69),2)) -> 0 | R69: =(ROUND((ROUND(((EU69)*AV69*I69),2)*BS69),2)+ROUND((ROUND(((AE69-(EU69))*AV69*I69),2)*BS69),2)) -> 0 | S69: =ROUND((ROUND((AF69*AV69*I69),2)*BA69),2) -> 0 | T69: =ROUND(CU69*I69,2) -> 0 | U69: =CV69*I69 -> 0 | V69: =CW69*I69 -> 0 | W69: =ROUND(CX69*I69,2) -> 0 | X69: =(ROUND((((S69+ROUND((ROUND(((EU69)*AV69*I69),2)*BS69),2))*AT69)/100),2)+ROUND(((ROUND((ROUND(((AE69-(EU69))*AV69*I69),2)*BS69),2)*AT69)/100),2)) -> 0 | Y69: =(ROUND((((S69+ROUND((ROUND(((EU69)*AV69*I69),2)*BS69),2))*AU69)/100),2)+ROUND(((ROUND((ROUND(((AE69-(EU69))*AV69*I69),2)*BS69),2)*AU69)/100),2)) -> 0 | AA69: 85739207 | AB69: =ROUND((AC69+AD69+AF69),6) -> 107.23 | AC69: =ROUND((ES69),6) -> 107.23 | AD69: =ROUND((((ET69)-(EU69))+AE69),6) -> 0 | AE69: =ROUND((EU69),6) -> 0 | AF69: =ROUND((EV69),6) -> 0 | AG69: =ROUND((AP69),6) -> 0 | AH69: =(EW69) -> 0 | AI69: =(EX69) -> 0 | AJ69: =(AS69) -> 0 | AK69: 107.23 | AL69: 107.23 | AM69: 0 | AN69: 0 | AO69: 0 | AP69: 0 | AQ69: 0 | AR69: 0 | AS69: 0 | AT69: 90 | AU69: 46 | AV69: 1 | AW69: 1 | AZ69: 1 | BA69: 1 | BB69: 1 | BC69: 6.94 | BH69: 3 | BI69: 2 | BJ69: ТСН-2001.1 Доп. 80, Р. 12, о. 9, поз. 21 | BM69: 73 | BN69: 0 | BO69: 1.12-9-21 | BP69: 1 | BQ69: 40 | BR69: 0 | BS69: 1 | BT69: 1 | BU69: 1 | BV69: 1 | BW69: 1 | BX69: 1 | BZ69: 90 | CA69: 46 | CE69: 1566 | CF69: 0 | CG69: 0 | CM69: 0 | CN69: Поправка: Гл.12.Прил.8.п.8. 3_12.00.01.11.001_x000D_ Наименование: При наличии напряженных и стесненных условий производства работ (стесненность, сложность складирования и транспортной логистики и т.п.) для объектов, расположенных в пределах круговой магистральной системы улиц "Садовое кольцо" города Москвы | CO69: 0 | CP69: =(P69+Q69+S69) -> 14883.52 | CQ69: =ROUND((ROUND((AC69*AW69*1),2)*BC69),2) -> 744.18 | CR69: =(ROUND((ROUND(((ET69)*AV69*1),2)*BB69),2)+ROUND((ROUND(((AE69-(EU69))*AV69*1),2)*BS69),2)) -> 0 | CS69: =(ROUND((ROUND(((EU69)*AV69*1),2)*BS69),2)+ROUND((ROUND(((AE69-(EU69))*AV69*1),2)*BS69),2)) -> 0 | CT69: =ROUND((ROUND((AF69*AV69*1),2)*BA69),2) -> 0 | CU69: =AG69 -> 0 | CV69: =(AH69*AV69) -> 0 | CW69: =AI69 -> 0 | CX69: =AJ69 -> 0 | CY69: =(ROUND((((S69+ROUND((ROUND(((EU69)*AV69*1),2)*BS69),2))*AT69)/100),2)+ROUND(((ROUND((ROUND(((AE69-(EU69))*AV69*1),2)*BS69),2)*AT69)/100),2)) -> 0 | CZ69: =(ROUND((((S69+ROUND((ROUND(((EU69)*AV69*1),2)*BS69),2))*AU69)/100),2)+ROUND(((ROUND((ROUND(((AE69-(EU69))*AV69*1),2)*BS69),2)*AU69)/100),2)) -> 0 | DN69: 0 | DO69: 0 | DP69: 1 | DQ69: 1 | DU69: 1010 | DV69: шт. | DW69: шт. | DX69: 1 | EE69: 85133422 | EF69: 40 | EG69: Монтаж оборудования | EH69: 0 | EJ69: 2 | EK69: 73 | EL69: ТСН-2001.4-12. Технологические трубопроводы | EM69: ТСН-2001.4-12-1 | EO69: Поправка: Гл.12.Прил.8.п.8. 3_12.00.01.11.001 | EQ69: 0 | ER69: 107.23 | ES69: 107.23 | ET69: 0 | EU69: 0 | EV69: 0 | EW69: 0 | EX69: 0 | FQ69: 0 | FR69: 0 | FS69: 0 | FX69: 90 | FY69: 46 | GD69: 1 | GF69: 235948314 | GG69: 2 | GH69: 1 | GI69: 2 | GJ69: 0 | GK69: 0 | GL69: =ROUND(IF(AND(BH69=3,BI69=3,FS69<>0),P69,0),2) -> 0 | GM69: =ROUND(O69+X69+Y69,2)+GX69 -> 14883.52 | GN69: =IF(OR(BI69=0,BI69=1),GM69-GX69,0) -> 0 | GO69: =IF(BI69=2,GM69-GX69,0) -> 14883.52 | GP69: =IF(BI69=4,GM69-GX69,0) -> 0 | GR69: 0 | GS69: 3 | GT69: 0 | GV69: =ROUND((GT69),6) -> 0 | GW69: 1 | GX69: =ROUND(HC69*I69,2) -> 0 | HA69: 0 | HB69: 0 | HC69: =GV69*GW69 -> 0 | HM69: *1 | HS69: 0 | IK69: 0
A70: 18 | B70: 1 | C70: 143 | E70: 14,2 | F70: 1.12-11-48 | G70: Отвод крутоизогнутый, стальной, оцинкованный, ГОСТ 17375-01, наружный диаметр 108 мм, толщина стенки 4,0 мм, под углом 90° | H70: шт. | I70: =I66*J70 -> 6 | J70: 0.375 | K70: 0.375 | O70: =ROUND(CP70,2) -> 780.42 | P70: =ROUND((ROUND((AC70*AW70*I70),2)*BC70),2) -> 780.42 | Q70: =(ROUND((ROUND(((ET70)*AV70*I70),2)*BB70),2)+ROUND((ROUND(((AE70-(EU70))*AV70*I70),2)*BS70),2)) -> 0 | R70: =(ROUND((ROUND(((EU70)*AV70*I70),2)*BS70),2)+ROUND((ROUND(((AE70-(EU70))*AV70*I70),2)*BS70),2)) -> 0 | S70: =ROUND((ROUND((AF70*AV70*I70),2)*BA70),2) -> 0 | T70: =ROUND(CU70*I70,2) -> 0 | U70: =CV70*I70 -> 0 | V70: =CW70*I70 -> 0 | W70: =ROUND(CX70*I70,2) -> 0 | X70: =(ROUND((((S70+ROUND((ROUND(((EU70)*AV70*I70),2)*BS70),2))*AT70)/100),2)+ROUND(((ROUND((ROUND(((AE70-(EU70))*AV70*I70),2)*BS70),2)*AT70)/100),2)) -> 0 | Y70: =(ROUND((((S70+ROUND((ROUND(((EU70)*AV70*I70),2)*BS70),2))*AU70)/100),2)+ROUND(((ROUND((ROUND(((AE70-(EU70))*AV70*I70),2)*BS70),2)*AU70)/100),2)) -> 0 | AA70: 85739205 | AB70: =ROUND((AC70+AD70+AF70),6) -> 130.07 | AC70: =ROUND((ES70),6) -> 130.07 | AD70: =ROUND((((ET70)-(EU70))+AE70),6) -> 0 | AE70: =ROUND((EU70),6) -> 0 | AF70: =ROUND((EV70),6) -> 0 | AG70: =ROUND((AP70),6) -> 0 | AH70: =(EW70) -> 0 | AI70: =(EX70) -> 0 | AJ70: =(AS70) -> 0 | AK70: 130.07 | AL70: 130.07 | AM70: 0 | AN70: 0 | AO70: 0 | AP70: 0 | AQ70: 0 | AR70: 0 | AS70: 0 | AT70: 90 | AU70: 46 | AV70: 1 | AW70: 1 | AZ70: 1 | BA70: 1 | BB70: 1 | BC70: 1 | BH70: 3 | BI70: 2 | BJ70: ТСН-2001.1 Доп. 79, Р. 12, о. 11, поз. 48 | BM70: 73 | BN70: 0 | BP70: 0 | BQ70: 40 | BR70: 0 | BS70: 1 | BT70: 1 | BU70: 1 | BV70: 1 | BW70: 1 | BX70: 1 | BZ70: 90 | CA70: 46 | CE70: 1566 | CF70: 0 | CG70: 0 | CM70: 0 | CN70: Поправка: Гл.12.Прил.8.п.8. 3_12.00.01.11.001_x000D_ Наименование: При наличии напряженных и стесненных условий производства работ (стесненность, сложность складирования и транспортной логистики и т.п.) для объектов, расположенных в пределах круговой магистральной системы улиц "Садовое кольцо" города Москвы | CO70: 0 | CP70: =(P70+Q70+S70) -> 780.42 | CQ70: =ROUND((ROUND((AC70*AW70*1),2)*BC70),2) -> 130.07 | CR70: =(ROUND((ROUND(((ET70)*AV70*1),2)*BB70),2)+ROUND((ROUND(((AE70-(EU70))*AV70*1),2)*BS70),2)) -> 0 | CS70: =(ROUND((ROUND(((EU70)*AV70*1),2)*BS70),2)+ROUND((ROUND(((AE70-(EU70))*AV70*1),2)*BS70),2)) -> 0 | CT70: =ROUND((ROUND((AF70*AV70*1),2)*BA70),2) -> 0 | CU70: =AG70 -> 0 | CV70: =(AH70*AV70) -> 0 | CW70: =AI70 -> 0 | CX70: =AJ70 -> 0 | CY70: =(ROUND((((S70+ROUND((ROUND(((EU70)*AV70*1),2)*BS70),2))*AT70)/100),2)+ROUND(((ROUND((ROUND(((AE70-(EU70))*AV70*1),2)*BS70),2)*AT70)/100),2)) -> 0 | CZ70: =(ROUND((((S70+ROUND((ROUND(((EU70)*AV70*1),2)*BS70),2))*AU70)/100),2)+ROUND(((ROUND((ROUND(((AE70-(EU70))*AV70*1),2)*BS70),2)*AU70)/100),2)) -> 0 | DN70: 0 | DO70: 0 | DP70: 1 | DQ70: 1 | DU70: 1010 | DV70: шт. | DW70: шт. | DX70: 1 | EE70: 85133422 | EF70: 40 | EG70: Монтаж оборудования | EH70: 0 | EJ70: 2 | EK70: 73 | EL70: ТСН-2001.4-12. Технологические трубопроводы | EM70: ТСН-2001.4-12-1 | EO70: Поправка: Гл.12.Прил.8.п.8. 3_12.00.01.11.001 | EQ70: 0 | ER70: 130.07 | ES70: 130.07 | ET70: 0 | EU70: 0 | EV70: 0 | EW70: 0 | EX70: 0 | FQ70: 0 | FR70: 0 | FS70: 0 | FX70: 90 | FY70: 46 | GD70: 1 | GF70: -1214401210 | GG70: 2 | GH70: 1 | GI70: -2 | GJ70: 0 | GK70: 0 | GL70: =ROUND(IF(AND(BH70=3,BI70=3,FS70<>0),P70,0),2) -> 0 | GM70: =ROUND(O70+X70+Y70,2)+GX70 -> 780.42 | GN70: =IF(OR(BI70=0,BI70=1),GM70-GX70,0) -> 0 | GO70: =IF(BI70=2,GM70-GX70,0) -> 780.42 | GP70: =IF(BI70=4,GM70-GX70,0) -> 0 | GR70: 0 | GS70: 3 | GT70: 0 | GV70: =ROUND((GT70),6) -> 0 | GW70: 1 | GX70: =ROUND(HC70*I70,2) -> 0 | HA70: 0 | HB70: 0 | HC70: =GV70*GW70 -> 0 | HM70: *1 | HS70: 0 | IK70: 0
A71: 18 | B71: 1 | C71: 151 | E71: 14,2 | F71: 1.12-11-48 | G71: Отвод крутоизогнутый, стальной, оцинкованный, ГОСТ 17375-01, наружный диаметр 108 мм, толщина стенки 4,0 мм, под углом 90° | H71: шт. | I71: =I67*J71 -> 6 | J71: 0.375 | K71: 0.375 | O71: =ROUND(CP71,2) -> 3761.62 | P71: =ROUND((ROUND((AC71*AW71*I71),2)*BC71),2) -> 3761.62 | Q71: =(ROUND((ROUND(((ET71)*AV71*I71),2)*BB71),2)+ROUND((ROUND(((AE71-(EU71))*AV71*I71),2)*BS71),2)) -> 0 | R71: =(ROUND((ROUND(((EU71)*AV71*I71),2)*BS71),2)+ROUND((ROUND(((AE71-(EU71))*AV71*I71),2)*BS71),2)) -> 0 | S71: =ROUND((ROUND((AF71*AV71*I71),2)*BA71),2) -> 0 | T71: =ROUND(CU71*I71,2) -> 0 | U71: =CV71*I71 -> 0 | V71: =CW71*I71 -> 0 | W71: =ROUND(CX71*I71,2) -> 0 | X71: =(ROUND((((S71+ROUND((ROUND(((EU71)*AV71*I71),2)*BS71),2))*AT71)/100),2)+ROUND(((ROUND((ROUND(((AE71-(EU71))*AV71*I71),2)*BS71),2)*AT71)/100),2)) -> 0 | Y71: =(ROUND((((S71+ROUND((ROUND(((EU71)*AV71*I71),2)*BS71),2))*AU71)/100),2)+ROUND(((ROUND((ROUND(((AE71-(EU71))*AV71*I71),2)*BS71),2)*AU71)/100),2)) -> 0 | AA71: 85739207 | AB71: =ROUND((AC71+AD71+AF71),6) -> 130.07 | AC71: =ROUND((ES71),6) -> 130.07 | AD71: =ROUND((((ET71)-(EU71))+AE71),6) -> 0 | AE71: =ROUND((EU71),6) -> 0 | AF71: =ROUND((EV71),6) -> 0 | AG71: =ROUND((AP71),6) -> 0 | AH71: =(EW71) -> 0 | AI71: =(EX71) -> 0 | AJ71: =(AS71) -> 0 | AK71: 130.07 | AL71: 130.07 | AM71: 0 | AN71: 0 | AO71: 0 | AP71: 0 | AQ71: 0 | AR71: 0 | AS71: 0 | AT71: 90 | AU71: 46 | AV71: 1 | AW71: 1 | AZ71: 1 | BA71: 1 | BB71: 1 | BC71: 4.82 | BH71: 3 | BI71: 2 | BJ71: ТСН-2001.1 Доп. 79, Р. 12, о. 11, поз. 48 | BM71: 73 | BN71: 0 | BO71: 1.12-11-48 | BP71: 1 | BQ71: 40 | BR71: 0 | BS71: 1 | BT71: 1 | BU71: 1 | BV71: 1 | BW71: 1 | BX71: 1 | BZ71: 90 | CA71: 46 | CE71: 1566 | CF71: 0 | CG71: 0 | CM71: 0 | CN71: Поправка: Гл.12.Прил.8.п.8. 3_12.00.01.11.001_x000D_ Наименование: При наличии напряженных и стесненных условий производства работ (стесненность, сложность складирования и транспортной логистики и т.п.) для объектов, расположенных в пределах круговой магистральной системы улиц "Садовое кольцо" города Москвы | CO71: 0 | CP71: =(P71+Q71+S71) -> 3761.62 | CQ71: =ROUND((ROUND((AC71*AW71*1),2)*BC71),2) -> 626.94 | CR71: =(ROUND((ROUND(((ET71)*AV71*1),2)*BB71),2)+ROUND((ROUND(((AE71-(EU71))*AV71*1),2)*BS71),2)) -> 0 | CS71: =(ROUND((ROUND(((EU71)*AV71*1),2)*BS71),2)+ROUND((ROUND(((AE71-(EU71))*AV71*1),2)*BS71),2)) -> 0 | CT71: =ROUND((ROUND((AF71*AV71*1),2)*BA71),2) -> 0 | CU71: =AG71 -> 0 | CV71: =(AH71*AV71) -> 0 | CW71: =AI71 -> 0 | CX71: =AJ71 -> 0 | CY71: =(ROUND((((S71+ROUND((ROUND(((EU71)*AV71*1),2)*BS71),2))*AT71)/100),2)+ROUND(((ROUND((ROUND(((AE71-(EU71))*AV71*1),2)*BS71),2)*AT71)/100),2)) -> 0 | CZ71: =(ROUND((((S71+ROUND((ROUND(((EU71)*AV71*1),2)*BS71),2))*AU71)/100),2)+ROUND(((ROUND((ROUND(((AE71-(EU71))*AV71*1),2)*BS71),2)*AU71)/100),2)) -> 0 | DN71: 0 | DO71: 0 | DP71: 1 | DQ71: 1 | DU71: 1010 | DV71: шт. | DW71: шт. | DX71: 1 | EE71: 85133422 | EF71: 40 | EG71: Монтаж оборудования | EH71: 0 | EJ71: 2 | EK71: 73 | EL71: ТСН-2001.4-12. Технологические трубопроводы | EM71: ТСН-2001.4-12-1 | EO71: Поправка: Гл.12.Прил.8.п.8. 3_12.00.01.11.001 | EQ71: 0 | ER71: 130.07 | ES71: 130.07 | ET71: 0 | EU71: 0 | EV71: 0 | EW71: 0 | EX71: 0 | FQ71: 0 | FR71: 0 | FS71: 0 | FX71: 90 | FY71: 46 | GD71: 1 | GF71: -1214401210 | GG71: 2 | GH71: 1 | GI71: 2 | GJ71: 0 | GK71: 0 | GL71: =ROUND(IF(AND(BH71=3,BI71=3,FS71<>0),P71,0),2) -> 0 | GM71: =ROUND(O71+X71+Y71,2)+GX71 -> 3761.62 | GN71: =IF(OR(BI71=0,BI71=1),GM71-GX71,0) -> 0 | GO71: =IF(BI71=2,GM71-GX71,0) -> 3761.62 | GP71: =IF(BI71=4,GM71-GX71,0) -> 0 | GR71: 0 | GS71: 3 | GT71: 0 | GV71: =ROUND((GT71),6) -> 0 | GW71: 1 | GX71: =ROUND(HC71*I71,2) -> 0 | HA71: 0 | HB71: 0 | HC71: =GV71*GW71 -> 0 | HM71: *1 | HS71: 0 | IK71: 0
