Workbook

Sheet Смета по ТСН-2001(с доп.67
A1: =Source!B1 -> Smeta.RU (495) 974-1589
J2: Форма № 4б
B3: "СОГЛАСОВАНО" | G3: "УТВЕРЖДАЮ"
B6: =CONCATENATE("______________________ ", IF(Source!AL12<>"", Source!AL12, "")) -> ______________________ | G6: =CONCATENATE("______________________ ", IF(Source!AH12<>"", Source!AH12, "")) -> ______________________
B7: "_____"________________ 2026 г. | G7: "_____"________________ 2026 г.
A10: Капитальный ремонт здания Государственного бюджетного общеобразовательного учреждения города Москвы «Школа №1574», расположенного по адресу: г. Москва, Старопименовский переулок, д. 5. 1 этап. | AP10: Капитальный ремонт здания Государственного бюджетного общеобразовательного учреждения города Москвы «Школа №1574», расположенного по адресу: г. Москва, Старопименовский переулок, д. 5. 1 этап. 02-01-13 СКС
A11: (наименование стройки и/или объекта)
A13: =CONCATENATE( "ЛОКАЛЬНАЯ СМЕТА № ",IF(Source!F12<>"Новый объект", Source!F12, "")) -> ЛОКАЛЬНАЯ СМЕТА № 02-01-13
A15: =Source!G20 -> Структурированная кабельная система. Локальная вычислительная сеть. Телефонизация
A16: (наименование работ и затрат)
A18: =CONCATENATE( "Основание: чертежи № ", Source!J12) -> Основание: чертежи № 2024-00375-01-0-ИОС5.6
I20: В базисном уровне цен | J20: В текущем уровне цен
E21: Сметная стоимость | I21: =I22+I23+I24+I25 -> 1679.96 | J21: =J22+J23+J24+J25 -> 24694.28 | K21: тыс.руб.
E22: Строительные работы | I22: =ROUND((Source!F550)/1000, 2) -> 123.48 | J22: =ROUND((Source!P550)/1000, 2) -> 6958 | K22: тыс.руб.
E23: Работы по монтажу оборудования | I23: =ROUND((Source!F551)/1000, 2) -> 881.07 | J23: =ROUND((Source!P551)/1000, 2) -> 12576.05 | K23: тыс.руб.
E24: Оборудование | I24: =ROUND((Source!F542)/1000, 2) -> 675.41 | J24: =ROUND((Source!P542)/1000, 2) -> 5160.23 | K24: тыс.руб.
E25: Прочие работы и затраты | I25: =ROUND((Source!F552+Source!F553)/1000, 2) -> 0 | J25: =ROUND((Source!P552+Source!P553)/1000, 2) -> 0 | K25: тыс.руб.
E26: Средства на оплату труда | I26: =(Source!F548+ Source!F547)/1000 -> 101.00099 | J26: =((Source!P548 + Source!P547)/1000) -> 5691.4058 | K26: тыс.руб.
E27: Затраты труда | I27: =Source!F555 -> 9027.0877 | K27: чел.-ч.
E28: Кроме того:
E29: Возврат материалов | I29: =SUM(Y1:Y967)/1000 -> 0 | J29: =SUM(Z1:Z967)/1000 -> 0 | K29: тыс.руб.
A31: Составлен(а) по ТСН-2001 с учетом Дополнения №: 81
A32: № и период сборника коэффициентов (индексов) пересчета: Коэффициенты к ТСН-2001 МГЭ Дополнение 81, строительство №219/81 I квартал 2026 года и Коэффициенты к ТСН-2001.13-2 Дополнение 47 №64/47 I квартал 2026 года | AP32: № и период сборника коэффициентов (индексов) пересчета: Коэффициенты к ТСН-2001 МГЭ Дополнение 81, строительство №219/81 I квартал 2026 года и Коэффициенты к ТСН-2001.13-2 Дополнение 47 №64/47 I квартал 2026 года
A33: № п/п | B33: Шифр расценки и коды ресурсов | C33: Наименование работ и затрат | D33: Ед. изм. | E33: Кол-во единиц | F33: Цена на ед. изм., руб. | G33: Попра- вочные коэффи- циенты | H33: Коэффи- циенты зимних удорожа- ний | I33: Всего в ценах на январь 2000 года, руб. | J33: Коэффи- циенты (индек- сы) пере- счета, нормы НР и СП | K33: ВСЕГО затрат в текущем уровне цен, руб.
A34: 1 | B34: 2 | C34: 3 | D34: 4 | E34: 5 | F34: 6 | G34: 7 | H34: 8 | I34: 9 | J34: 10 | K34: 11
A36: =CONCATENATE("Локальная смета: ",IF(Source!G20<>"Новая локальная смета", Source!G20, "")) -> Локальная смета: Структурированная кабельная система. Локальная вычислительная сеть. Телефонизация | AP36: =CONCATENATE("Локальная смета: ",IF(Source!G20<>"Новая локальная смета", Source!G20, "")) -> Локальная смета: Структурированная кабельная система. Локальная вычислительная сеть. Телефонизация
A38: =CONCATENATE("Раздел: ",IF(Source!G24<>"Новый раздел", Source!G24, "")) -> Раздел: Демонтажные работы
A39: 1 | B39: =Source!F28 -> 4.10-34-5 | C39: Монтаж коммутатора служебной связи / демонтаж коммутатора | D39: =Source!H28 -> 1 ШТ. | E39: =Source!I28 -> 9 | Q39: =Source!X28 -> 248.52 | R39: =Source!X29 -> 14003.93 | S39: =Source!Y28 -> 127.02 | T39: =Source!Y29 -> 7157.56 | U39: =ROUND((175/100)*ROUND(Source!R28, 2), 2) -> 18.76 | V39: =ROUND((0/100)*ROUND(Source!R29, 2), 2) -> 0 | AC39: 0
C40: ="Объем: "&Source!I28&"=5+"&"3+"&"1" -> Объем: 9=5+3+1
C41: ЗП | F41: =Source!AO28 -> 78.24 | G41: 1,2*0,3 | H41: =Source!AV29 -> 1.047 | I41: =Source!S28 -> 265.41 | J41: =IF(Source!BA29<> 0, Source!BA29, 1) -> 56.35 | K41: =Source!S29 -> 14955.85
C42: ЭМ | F42: =Source!AM28 -> 28.71 | G42: 1,2*0,3 | H42: =Source!AV29 -> 1.047 | I42: =Source!Q28 -> 97.39 | J42: =IF(Source!BB29<> 0, Source!BB29, 1) -> 16.16 | K42: =Source!Q29 -> 1573.82
C43: в т.ч. ЗПМ | F43: =Source!AN28 -> 3.16 | G43: 1,2*0,3 | H43: =Source!AV29 -> 1.047 | I43: =Source!R28 -> 10.72 | J43: =IF(Source!BS29<> 0, Source!BS29, 1) -> 56.35 | K43: =Source!R29 -> 604.07
C44: НР от ФОТ | D44: % | E44: =Source!BZ29 -> 90 | I44: =SUM(Q39:Q43) -> 248.52 | J44: =Source!AT29 -> 90 | K44: =SUM(R39:R43) -> 14003.93
C45: СП от ФОТ | D45: % | E45: =Source!CA29 -> 46 | I45: =SUM(S39:S44) -> 127.02 | J45: =Source!AU29 -> 46 | K45: =SUM(T39:T44) -> 7157.56
C46: ЗТР | D46: чел-ч | E46: =Source!AQ28 -> 6.2 | G46: 1,2*0,3 | H46: =Source!AV29 -> 1.047 | I46: =Source!U28 -> 21.032136
C47: ВСЕГО работ по позиции: | H47: =I41+I42+I44+I45+0-0-0 -> 738.34 | J47: =K41+K42+K44+K45+0-0-0 -> 37691.16
C48: ВСЕГО оборудование по позиции: | H48: =0+0 -> 0 | J48: =0+0 -> 0
C49: ВСЕГО по позиции: | H49: =I41+I42+I44+I45+0 -> 738.34 | J49: =K41+K42+K44+K45+0 -> 37691.16 | O49: =I41+I42+I44+I45+0 -> 738.34 | P49: =K41+K42+K44+K45+0 -> 37691.16
A51: 2 | B51: =Source!F30 -> 4.10-19-6 | C51: Монтаж отдельно устанавливаемого преобразователя или блока питания / демонтаж модуля питания | D51: =Source!H30 -> 1 ШТ. | E51: =Source!I30 -> 6 | Q51: =Source!X30 -> 285.5 | R51: =Source!X31 -> 16087.82 | S51: =Source!Y30 -> 145.92 | T51: =Source!Y31 -> 8222.66 | U51: =ROUND((175/100)*ROUND(Source!R30, 2), 2) -> 19.99 | V51: =ROUND((0/100)*ROUND(Source!R31, 2), 2) -> 0 | AC51: 0
C52: ЗП | F52: =Source!AO30 -> 135.22 | G52: 1,2*0,3 | H52: =Source!AV31 -> 1.047 | I52: =Source!S30 -> 305.8 | J52: =IF(Source!BA31<> 0, Source!BA31, 1) -> 56.35 | K52: =Source!S31 -> 17231.83
C53: ЭМ | F53: =Source!AM30 -> 45.93 | G53: 1,2*0,3 | H53: =Source!AV31 -> 1.047 | I53: =Source!Q30 -> 103.87 | J53: =IF(Source!BB31<> 0, Source!BB31, 1) -> 16.16 | K53: =Source!Q31 -> 1678.54
C54: в т.ч. ЗПМ | F54: =Source!AN30 -> 5.05 | G54: 1,2*0,3 | H54: =Source!AV31 -> 1.047 | I54: =Source!R30 -> 11.42 | J54: =IF(Source!BS31<> 0, Source!BS31, 1) -> 56.35 | K54: =Source!R31 -> 643.52
C55: НР от ФОТ | D55: % | E55: =Source!BZ31 -> 90 | I55: =SUM(Q51:Q54) -> 285.5 | J55: =Source!AT31 -> 90 | K55: =SUM(R51:R54) -> 16087.82
C56: СП от ФОТ | D56: % | E56: =Source!CA31 -> 46 | I56: =SUM(S51:S55) -> 145.92 | J56: =Source!AU31 -> 46 | K56: =SUM(T51:T55) -> 8222.66
C57: ЗТР | D57: чел-ч | E57: =Source!AQ30 -> 9.3 | G57: 1,2*0,3 | H57: =Source!AV31 -> 1.047 | I57: =Source!U30 -> 21.032136
C58: ВСЕГО работ по позиции: | H58: =I52+I53+I55+I56+0-0-0 -> 841.09 | J58: =K52+K53+K55+K56+0-0-0 -> 43220.85
C59: ВСЕГО оборудование по позиции: | H59: =0+0 -> 0 | J59: =0+0 -> 0
C60: ВСЕГО по позиции: | H60: =I52+I53+I55+I56+0 -> 841.09 | J60: =K52+K53+K55+K56+0 -> 43220.85 | O60: =I52+I53+I55+I56+0 -> 841.09 | P60: =K52+K53+K55+K56+0 -> 43220.85
A62: 3 | B62: =Source!F32 -> 4.11-12-1 | C62: Установка съемных и выдвижных блоков (модулей, ячеек, ТЭЗ) массой до 5 кг / демонтаж SFP модулей | D62: =Source!H32 -> 1 ШТ. | E62: =Source!I32 -> 14 | Q62: =Source!X32 -> 55.71 | R62: =Source!X33 -> 3139.26 | S62: =Source!Y32 -> 28.47 | T62: =Source!Y33 -> 1604.51 | U62: =ROUND((175/100)*ROUND(Source!R32, 2), 2) -> 0.74 | V62: =ROUND((0/100)*ROUND(Source!R33, 2), 2) -> 0 | AC62: 0
C63: ="Объем: "&Source!I32&"=2+"&"12" -> Объем: 14=2+12
C64: ЗП | F64: =Source!AO32 -> 11.65 | G64: 1,2*0,3 | H64: =Source!AV33 -> 1.047 | I64: =Source!S32 -> 61.48 | J64: =IF(Source!BA33<> 0, Source!BA33, 1) -> 56.35 | K64: =Source!S33 -> 3464.4
C65: ЭМ | F65: =Source!AM32 -> 0.5 | G65: 1,2*0,3 | H65: =Source!AV33 -> 1.047 | I65: =Source!Q32 -> 2.64 | J65: =IF(Source!BB33<> 0, Source!BB33, 1) -> 17.02 | K65: =Source!Q33 -> 44.93
C66: в т.ч. ЗПМ | F66: =Source!AN32 -> 0.08 | G66: 1,2*0,3 | H66: =Source!AV33 -> 1.047 | I66: =Source!R32 -> 0.42 | J66: =IF(Source!BS33<> 0, Source!BS33, 1) -> 56.35 | K66: =Source!R33 -> 23.67
C67: НР от ФОТ | D67: % | E67: =Source!BZ33 -> 90 | I67: =SUM(Q62:Q66) -> 55.71 | J67: =Source!AT33 -> 90 | K67: =SUM(R62:R66) -> 3139.26
C68: СП от ФОТ | D68: % | E68: =Source!CA33 -> 46 | I68: =SUM(S62:S67) -> 28.47 | J68: =Source!AU33 -> 46 | K68: =SUM(T62:T67) -> 1604.51
C69: ЗТР | D69: чел-ч | E69: =Source!AQ32 -> 1.03 | G69: 1,2*0,3 | H69: =Source!AV33 -> 1.047 | I69: =Source!U32 -> 5.4351864
C70: ВСЕГО работ по позиции: | H70: =I64+I65+I67+I68+0-0-0 -> 148.3 | J70: =K64+K65+K67+K68+0-0-0 -> 8253.1
C71: ВСЕГО оборудование по позиции: | H71: =0+0 -> 0 | J71: =0+0 -> 0
C72: ВСЕГО по позиции: | H72: =I64+I65+I67+I68+0 -> 148.3 | J72: =K64+K65+K67+K68+0 -> 8253.1 | O72: =I64+I65+I67+I68+0 -> 148.3 | P72: =K64+K65+K67+K68+0 -> 8253.1
A74: 4 | B74: =Source!F34 -> 4.10-142-5 | C74: Монтаж и настройка электронных АТС типа Миником DX-500, станция с количеством номеров до 500, монтаж станции | D74: =Source!H34 -> 100 номеров | E74: =Source!I34 -> 0.01 | Q74: =Source!X34 -> 1.93 | R74: =Source!X35 -> 108.53 | S74: =Source!Y34 -> 0.98 | T74: =Source!Y35 -> 55.47 | U74: =ROUND((175/100)*ROUND(Source!R34, 2), 2) -> 0 | V74: =ROUND((0/100)*ROUND(Source!R35, 2), 2) -> 0 | AC74: 0
C75: ="Объем: "&Source!I34&"=1/"&"100" -> Объем: 0,01=1/100
C76: ЗП | F76: =Source!AO34 -> 567.06 | G76: 1,2*0,3 | H76: =Source!AV35 -> 1.047 | I76: =Source!S34 -> 2.14 | J76: =IF(Source!BA35<> 0, Source!BA35, 1) -> 56.35 | K76: =Source!S35 -> 120.59
C77: НР от ФОТ | D77: % | E77: =Source!BZ35 -> 90 | I77: =SUM(Q74:Q76) -> 1.93 | J77: =Source!AT35 -> 90 | K77: =SUM(R74:R76) -> 108.53
C78: СП от ФОТ | D78: % | E78: =Source!CA35 -> 46 | I78: =SUM(S74:S77) -> 0.98 | J78: =Source!AU35 -> 46 | K78: =SUM(T74:T77) -> 55.47
C79: ЗТР | D79: чел-ч | E79: =Source!AQ34 -> 39 | G79: 1,2*0,3 | H79: =Source!AV35 -> 1.047 | I79: =Source!U34 -> 0.1469988
C80: ВСЕГО работ по позиции: | H80: =I76+I77+I78+0-0-0 -> 5.05 | J80: =K76+K77+K78+0-0-0 -> 284.59
C81: ВСЕГО оборудование по позиции: | H81: =0+0 -> 0 | J81: =0+0 -> 0
C82: ВСЕГО по позиции: | H82: =I76+I77+I78+0 -> 5.05 | J82: =K76+K77+K78+0 -> 284.59 | O82: =I76+I77+I78+0 -> 5.05 | P82: =K76+K77+K78+0 -> 284.59
A84: 5 | B84: =Source!F36 -> 4.10-19-6 | C84: Монтаж отдельно устанавливаемого преобразователя или блока питания / демонтаж ИБП | D84: =Source!H36 -> 1 ШТ. | E84: =Source!I36 -> 4 | Q84: =Source!X36 -> 190.33 | R84: =Source!X37 -> 10725.2 | S84: =Source!Y36 -> 97.28 | T84: =Source!Y37 -> 5481.77 | U84: =ROUND((175/100)*ROUND(Source!R36, 2), 2) -> 13.32 | V84: =ROUND((0/100)*ROUND(Source!R37, 2), 2) -> 0 | AC84: 0
C85: ="Объем: "&Source!I36&"=1+"&"3" -> Объем: 4=1+3
C86: ЗП | F86: =Source!AO36 -> 135.22 | G86: 1,2*0,3 | H86: =Source!AV37 -> 1.047 | I86: =Source!S36 -> 203.87 | J86: =IF(Source!BA37<> 0, Source!BA37, 1) -> 56.35 | K86: =Source!S37 -> 11488.07
C87: ЭМ | F87: =Source!AM36 -> 45.93 | G87: 1,2*0,3 | H87: =Source!AV37 -> 1.047 | I87: =Source!Q36 -> 69.25 | J87: =IF(Source!BB37<> 0, Source!BB37, 1) -> 16.16 | K87: =Source!Q37 -> 1119.08
C88: в т.ч. ЗПМ | F88: =Source!AN36 -> 5.05 | G88: 1,2*0,3 | H88: =Source!AV37 -> 1.047 | I88: =Source!R36 -> 7.61 | J88: =IF(Source!BS37<> 0, Source!BS37, 1) -> 56.35 | K88: =Source!R37 -> 428.82
C89: НР от ФОТ | D89: % | E89: =Source!BZ37 -> 90 | I89: =SUM(Q84:Q88) -> 190.33 | J89: =Source!AT37 -> 90 | K89: =SUM(R84:R88) -> 10725.2
C90: СП от ФОТ | D90: % | E90: =Source!CA37 -> 46 | I90: =SUM(S84:S89) -> 97.28 | J90: =Source!AU37 -> 46 | K90: =SUM(T84:T89) -> 5481.77
C91: ЗТР | D91: чел-ч | E91: =Source!AQ36 -> 9.3 | G91: 1,2*0,3 | H91: =Source!AV37 -> 1.047 | I91: =Source!U36 -> 14.021424
C92: ВСЕГО работ по позиции: | H92: =I86+I87+I89+I90+0-0-0 -> 560.73 | J92: =K86+K87+K89+K90+0-0-0 -> 28814.12
C93: ВСЕГО оборудование по позиции: | H93: =0+0 -> 0 | J93: =0+0 -> 0
C94: ВСЕГО по позиции: | H94: =I86+I87+I89+I90+0 -> 560.73 | J94: =K86+K87+K89+K90+0 -> 28814.12 | O94: =I86+I87+I89+I90+0 -> 560.73 | P94: =K86+K87+K89+K90+0 -> 28814.12
A96: 6 | B96: =Source!F38 -> 4.10-181-4 | C96: Монтаж оптического кросса с учетом измерений на волоконно-оптическом кабеле с числом волокон: 4 / демонтаж оптического кросса | D96: =Source!H38 -> 1 ШТ. | E96: =Source!I38 -> 3 | Q96: =Source!X38 -> 37.74 | R96: =Source!X39 -> 2126.48 | S96: =Source!Y38 -> 19.29 | T96: =Source!Y39 -> 1086.87 | U96: =ROUND((175/100)*ROUND(Source!R38, 2), 2) -> 0 | V96: =ROUND((0/100)*ROUND(Source!R39, 2), 2) -> 0 | AC96: 0
C97: ЗП | F97: =Source!AO38 -> 36.39 | G97: 1,2*0,3 | H97: =Source!AV39 -> 1.067 | I97: =Source!S38 -> 41.93 | J97: =IF(Source!BA39<> 0, Source!BA39, 1) -> 56.35 | K97: =Source!S39 -> 2362.76
C98: ЭМ | F98: =Source!AM38 -> 2.41 | G98: 1,2*0,3 | H98: =Source!AV39 -> 1.067 | I98: =Source!Q38 -> 2.78 | J98: =IF(Source!BB39<> 0, Source!BB39, 1) -> 9.35 | K98: =Source!Q39 -> 25.99
C99: НР от ФОТ | D99: % | E99: =Source!BZ39 -> 90 | I99: =SUM(Q96:Q98) -> 37.74 | J99: =Source!AT39 -> 90 | K99: =SUM(R96:R98) -> 2126.48
C100: СП от ФОТ | D100: % | E100: =Source!CA39 -> 46 | I100: =SUM(S96:S99) -> 19.29 | J100: =Source!AU39 -> 46 | K100: =SUM(T96:T99) -> 1086.87
C101: ЗТР | D101: чел-ч | E101: =Source!AQ38 -> 1.87 | G101: 1,2*0,3 | H101: =Source!AV39 -> 1.067 | I101: =Source!U38 -> 2.1549132
C102: ВСЕГО работ по позиции: | H102: =I97+I98+I99+I100+0-0-0 -> 101.74 | J102: =K97+K98+K99+K100+0-0-0 -> 5602.1
C103: ВСЕГО оборудование по позиции: | H103: =0+0 -> 0 | J103: =0+0 -> 0
C104: ВСЕГО по позиции: | H104: =I97+I98+I99+I100+0 -> 101.74 | J104: =K97+K98+K99+K100+0 -> 5602.1 | O104: =I97+I98+I99+I100+0 -> 101.74 | P104: =K97+K98+K99+K100+0 -> 5602.1
A106: 7 | B106: =Source!F40 -> 4.10-32-2 | C106: Монтаж стойки, полустойки, каркаса стойки или шкафа массой до 300 кг / демонтаж шкафов | D106: =Source!H40 -> 1 ШТ. | E106: =Source!I40 -> 5 | Q106: =Source!X40 -> 265.64 | R106: =Source!X41 -> 14969.04 | S106: =Source!Y40 -> 135.77 | T106: =Source!Y41 -> 7650.84 | U106: =ROUND((175/100)*ROUND(Source!R40, 2), 2) -> 22.45 | V106: =ROUND((0/100)*ROUND(Source!R41, 2), 2) -> 0 | AC106: 0
C107: ="Объем: "&Source!I40&"=1+"&"4" -> Объем: 5=1+4
C108: ЗП | F108: =Source!AO40 -> 149.81 | G108: 1,2*0,3 | H108: =Source!AV41 -> 1.047 | I108: =Source!S40 -> 282.33 | J108: =IF(Source!BA41<> 0, Source!BA41, 1) -> 56.35 | K108: =Source!S41 -> 15909.3
C109: ЭМ | F109: =Source!AM40 -> 63.24 | G109: 1,2*0,3 | H109: =Source!AV41 -> 1.047 | I109: =Source!Q40 -> 119.18 | J109: =IF(Source!BB41<> 0, Source!BB41, 1) -> 16.04 | K109: =Source!Q41 -> 1911.65
C110: в т.ч. ЗПМ | F110: =Source!AN40 -> 6.81 | G110: 1,2*0,3 | H110: =Source!AV41 -> 1.047 | I110: =Source!R40 -> 12.83 | J110: =IF(Source!BS41<> 0, Source!BS41, 1) -> 56.35 | K110: =Source!R41 -> 722.97
C111: НР от ФОТ | D111: % | E111: =Source!BZ41 -> 90 | I111: =SUM(Q106:Q110) -> 265.64 | J111: =Source!AT41 -> 90 | K111: =SUM(R106:R110) -> 14969.04
C112: СП от ФОТ | D112: % | E112: =Source!CA41 -> 46 | I112: =SUM(S106:S111) -> 135.77 | J112: =Source!AU41 -> 46 | K112: =SUM(T106:T111) -> 7650.84
C113: ЗТР | D113: чел-ч | E113: =Source!AQ40 -> 13.4 | G113: 1,2*0,3 | H113: =Source!AV41 -> 1.047 | I113: =Source!U40 -> 25.25364
C114: ВСЕГО работ по позиции: | H114: =I108+I109+I111+I112+0-0-0 -> 802.92 | J114: =K108+K109+K111+K112+0-0-0 -> 40440.83
C115: ВСЕГО оборудование по позиции: | H115: =0+0 -> 0 | J115: =0+0 -> 0
C116: ВСЕГО по позиции: | H116: =I108+I109+I111+I112+0 -> 802.92 | J116: =K108+K109+K111+K112+0 -> 40440.83 | O116: =I108+I109+I111+I112+0 -> 802.92 | P116: =K108+K109+K111+K112+0 -> 40440.83
A118: 8 | B118: =Source!F42 -> 6.67-7-1 | C118: Демонтаж осветительных приборов, выключатели, розетки | D118: =Source!H42 -> 100 шт. | E118: =Source!I42 -> 2.22 | Q118: =Source!X42 -> 151.48 | R118: =Source!X43 -> 8535.82 | S118: =Source!Y42 -> 79.9 | T118: =Source!Y43 -> 4502.41 | U118: =ROUND((175/100)*ROUND(Source!R42, 2), 2) -> 0 | V118: =ROUND((0/100)*ROUND(Source!R43, 2), 2) -> 0 | AC118: 0
...

Sheet Source
A1: 0 | B1: Smeta.RU (495) 974-1589 | D1: _PS_ | F1: 0 | G1: 0 | H1: 0 | I1: Smeta.RU | K1: 1 | L1: 74599 | M1: 10 | N1: 12 | O1: 1 | P1: 0 | Q1: 1
A4: 1 | B4: 1 | C4: -1 | G4: Капитальный ремонт здания Государственного бюджетного общеобразовательного учреждения города Москвы «Школа №1574», расположенного по адресу: г. Москва, Старопименовский переулок, д. 5. 1 этап | EC4: 0
A5: 8 | B5: 1 | C5: -1 | G5: Капитальный ремонт здания Государственного бюджетного общеобразовательного учреждения города Москвы «Школа №1574», расположенного по адресу: г. Москва, Старопименовский переулок, д. 5. 1 этап | EC5: 0
A12: 1 | B12: 572 | C12: 0 | D12: =ROW(A533) -> 533 | E12: 0 | F12: 02-01-13 | G12: 02-01-13 СКС | I12: 0 | J12: 2024-00375-01-0-ИОС5.6 | K12: 0 | L12: 0 | M12: 4098 | O12: 0 | P12: 0 | Q12: 0 | R12: 0 | S12: 0 | T12: 1 | V12: 0 | BB12: 0 | BH12: Сметные нормы списания | BI12: Коды ОКП для ТСН-2001 МГЭ Дополнение 81 | BJ12: 1 | BK12: 1 | BL12: 0 | BM12: 0 | BN12: 1 | BO12: 0 | BP12: 6 | BQ12: 2 | BR12: 1 | BS12: 1 | BT12: 0 | BU12: 0 | BV12: 0 | BW12: 0 | BX12: 0 | BY12: ТСН-2001 (МГЭ) Доп 81 - Новое строительство | BZ12: Типовой расчет для ТСН-2001 МГЭ, Дополнение 81, строительство | CA12: Территориальные сметные нормативы для Москвы ТСН-2001 (МГЭ), дополнение 81 | CB12: Территориальные сметные нормативы для Москвы ТСН-2001 (МГЭ), дополнение 81 | CC12: Территориальные сметные нормативы для Москвы ТСН-2001 (МГЭ), дополнение 81 | CD12: Территориальные сметные нормативы для Москвы ТСН-2001 (МГЭ), дополнение 81 | CE12: Поправки для ТСН-2001 от 07.04.2026 г. доп.81 | CF12: 0 | CG12: 0 | CH12: 8200 | CK12: 81 | CQ12: Территориальные сметные нормативы для Москвы (ТСН-2001) | CR12: ТЕР | CS12: 41660 | CT12: 1 | CU12: 81 | CY12: 0 | EC12: 0
A15: 15 | B15: 1
A18: 52 | B18: =B533 -> 572 | C18: =C533 -> 1 | D18: =D533 -> 12 | E18: =E533 -> 0 | F18: =F533 -> 02-01-13 | G18: =G533 -> 02-01-13 СКС | O18: =O533 -> 1537471.4 | P18: =P533 -> 1433742.1 | Q18: =Q533 -> 3062.82 | R18: =R533 -> 334.51 | S18: =S533 -> 100666.48 | T18: =T533 -> 0 | U18: =U533 -> 9027.0877 | V18: =V533 -> 0 | ... GX18: =GX533 -> 0
A20: 3 | B20: 1 | D20: =ROW(A503) -> 503 | F20: 02-01-13 | G20: Структурированная кабельная система. Локальная вычислительная сеть. Телефонизация | I20: 0 | J20: 2024-00375-01-0-ИОС5.6 | K20: -1 | L20: 02-01-13 | S20: 0 | T20: 0 | V20: 0 | BX20: 0 | CF20: 0 | CG20: 0
A22: 52 | B22: =B503 -> 1 | C22: =C503 -> 3 | D22: =D503 -> 20 | E22: =E503 -> 0 | F22: =F503 -> 02-01-13 | G22: =G503 -> Структурированная кабельная система. Локальная вычислительная сеть. Телефонизация | O22: =O503 -> 1537471.4 | P22: =P503 -> 1433742.1 | Q22: =Q503 -> 3062.82 | R22: =R503 -> 334.51 | S22: =S503 -> 100666.48 | T22: =T503 -> 0 | U22: =U503 -> 9027.0877 | V22: =V503 -> 0 | ... GX22: =GX503 -> 0
A24: 4 | B24: 1 | D24: =ROW(A59) -> 59 | F24: Новый раздел | G24: Демонтажные работы | I24: 0 | K24: 0 | S24: 0 | T24: 0 | V24: 0 | BX24: 0 | CJ24: 0
A26: 52 | B26: =B59 -> 1 | C26: =C59 -> 4 | D26: =D59 -> 24 | E26: =E59 -> 0 | F26: =F59 -> Новый раздел | G26: =G59 -> Демонтажные работы | O26: =O59 -> 54097.66 | P26: =P59 -> 0 | Q26: =Q59 -> 429.77 | R26: =R59 -> 48.08 | S26: =S59 -> 53667.89 | T26: =T59 -> 0 | U26: =U59 -> 5166.3111 | V26: =V59 -> 0 | ... GX26: =GX59 -> 0
A28: 17 | B28: 1 | C28: =ROW(SmtRes!A4) -> 4 | D28: =ROW(EtalonRes!A5) -> 5 | E28: 1 | F28: 4.10-34-5 | G28: Монтаж коммутатора служебной связи / демонтаж коммутатора | H28: 1 ШТ. | I28: =ROUND(5+3+1,9) -> 9 | J28: 0 | K28: =ROUND(5+3+1,9) -> 9 | O28: =ROUND(CP28,2) -> 362.8 | P28: =ROUND((ROUND((AC28*AW28*I28),2)*BC28),2) -> 0 | Q28: =(ROUND((ROUND(((((ET28*1.2)*0.3))*AV28*I28),2)*BB28),2)+ROUND((ROUND(((AE28-(((EU28*1.2)*0.3)))*AV28*I28),2)*BS28),2)) -> 97.39 | R28: =(ROUND((ROUND(((((EU28*1.2)*0.3))*AV28*I28),2)*BS28),2)+ROUND((ROUND(((AE28-(((EU28*1.2)*0.3)))*AV28*I28),2)*BS28),2)) -> 10.72 | S28: =ROUND((ROUND((AF28*AV28*I28),2)*BA28),2) -> 265.41 | T28: =ROUND(CU28*I28,2) -> 0 | U28: =CV28*I28 -> 21.032136 | V28: =CW28*I28 -> 0 | W28: =ROUND(CX28*I28,2) -> 0 | X28: =(ROUND((((S28+ROUND((ROUND(((((EU28*1.2)*0.3))*AV28*I28),2)*BS28),2))*AT28)/100),2)+ROUND(((ROUND((ROUND(((AE28-(((EU28*1.2)*0.3)))*AV28*I28),2)*BS28),2)*AT28)/100),2)) -> 248.52 | Y28: =(ROUND((((S28+ROUND((ROUND(((((EU28*1.2)*0.3))*AV28*I28),2)*BS28),2))*AU28)/100),2)+ROUND(((ROUND((ROUND(((AE28-(((EU28*1.2)*0.3)))*AV28*I28),2)*BS28),2)*AU28)/100),2)) -> 127.02 | AA28: 55929113 | AB28: =ROUND((AC28+AD28+AF28),6) -> 38.502 | AC28: =ROUND((((ES28*1)*0)),6) -> 0 | AD28: =ROUND((((((ET28*1.2)*0.3))-(((EU28*1.2)*0.3)))+AE28),6) -> 10.3356 | AE28: =ROUND((((EU28*1.2)*0.3)),6) -> 1.1376 | AF28: =ROUND((((EV28*1.2)*0.3)),6) -> 28.1664 | AG28: =ROUND((AP28),6) -> 0 | AH28: =(((EW28*1.2)*0.3)) -> 2.232 | AI28: =(((EX28*1.2)*0.3)) -> 0 | AJ28: =(AS28) -> 0 | AK28: 119.3 | AL28: 12.35 | AM28: 28.71 | AN28: 3.16 | AO28: 78.24 | AP28: 0 | AQ28: 6.2 | AR28: 0 | AS28: 0 | AT28: 90 | AU28: 46 | AV28: 1.047 | AW28: 1 | AZ28: 1 | BA28: 1 | BB28: 1 | BC28: 1 | BH28: 0 | BI28: 2 | BJ28: ТСН-2001.4 Доп. 80, Сб. 10, т. 34, поз. 5 | BM28: 68 | BN28: 0 | BO28: 4.10-34-5 | BP28: 1 | BQ28: 40 | BR28: 0 | BS28: 1 | BT28: 1 | BU28: 1 | BV28: 1 | BW28: 1 | BX28: 1 | BZ28: 90 | CA28: 46 | CE28: 1566 | CF28: 0 | CG28: 0 | CM28: 0 | CN28: Поправка: Гл.12.Прил.8.п.8. 3_12.00.01.11.001 Наименование: При наличии напряженных и стесненных условий производства работ (стесненность, сложность складирования и транспортной логистики и т.п.) для объектов, расположенных в пределах круговой магистральной системы улиц "Садовое кольцо" города Москвы Поправка: Гл.4.Прил.2.2.п.2.2.29_04.00.01.35.003 Наименование: При демонтаже оборудования, предназначенного в лом | CO28: 0 | CP28: =(P28+Q28+S28) -> 362.8 | CQ28: =ROUND((ROUND((AC28*AW28*1),2)*BC28),2) -> 0 | CR28: =(ROUND((ROUND(((((ET28*1.2)*0.3))*AV28*1),2)*BB28),2)+ROUND((ROUND(((AE28-(((EU28*1.2)*0.3)))*AV28*1),2)*BS28),2)) -> 10.82 | CS28: =(ROUND((ROUND(((((EU28*1.2)*0.3))*AV28*1),2)*BS28),2)+ROUND((ROUND(((AE28-(((EU28*1.2)*0.3)))*AV28*1),2)*BS28),2)) -> 1.19 | CT28: =ROUND((ROUND((AF28*AV28*1),2)*BA28),2) -> 29.49 | CU28: =AG28 -> 0 | CV28: =(AH28*AV28) -> 2.336904 | CW28: =AI28 -> 0 | CX28: =AJ28 -> 0 | CY28: =(ROUND((((S28+ROUND((ROUND(((((EU28*1.2)*0.3))*AV28*1),2)*BS28),2))*AT28)/100),2)+ROUND(((ROUND((ROUND(((AE28-(((EU28*1.2)*0.3)))*AV28*1),2)*BS28),2)*AT28)/100),2)) -> 239.94 | CZ28: =(ROUND((((S28+ROUND((ROUND(((((EU28*1.2)*0.3))*AV28*1),2)*BS28),2))*AU28)/100),2)+ROUND(((ROUND((ROUND(((AE28-(((EU28*1.2)*0.3)))*AV28*1),2)*BS28),2)*AU28)/100),2)) -> 122.64 | DB28: 1 | DD28: *1)*0 | DE28: *1,2)*0,3 | DF28: *1,2)*0,3 | DG28: *1,2)*0,3 | DI28: *1,2)*0,3 | DJ28: *1,2)*0,3 | DN28: 0 | DO28: 0 | DP28: 1 | DQ28: 1 | DU28: 1013 | DV28: 1 ШТ. | DW28: 1 ШТ. | DX28: 1 | EE28: 55393700 | EF28: 40 | EG28: Монтаж оборудования | EH28: 0 | EJ28: 2 | EK28: 68 | EL28: ТСН-2001.4-10. Прокладка и монтаж сетей связи | EM28: ТСН-2001.4-10-1 | EO28: Поправка: Гл.12.Прил.8.п.8. 3_12.00.01.11.001 Поправка: Гл.4.Прил.2.2.п.2.2.29_04.00.01.35.003 | EQ28: 0 | ER28: 119.3 | ES28: 12.35 | ET28: 28.71 | EU28: 3.16 | EV28: 78.24 | EW28: 6.2 | EX28: 0 | EY28: 0 | FQ28: 0 | FR28: 0 | FS28: 0 | FX28: 90 | FY28: 46 | GD28: 1 | GF28: -1384911768 | GG28: 2 | GH28: 1 | GI28: 2 | GJ28: 0 | GK28: 0 | GL28: =ROUND(IF(AND(BH28=3,BI28=3,FS28<>0),P28,0),2) -> 0 | GM28: =ROUND(O28+X28+Y28,2)+GX28 -> 738.34 | GN28: =IF(OR(BI28=0,BI28=1),GM28-GX28,0) -> 0 | GO28: =IF(BI28=2,GM28-GX28,0) -> 738.34 | GP28: =IF(BI28=4,GM28-GX28,0) -> 0 | GR28: 0 | GS28: 3 | GT28: 0 | GV28: =ROUND((GT28),6) -> 0 | GW28: 1 | GX28: =ROUND(HC28*I28,2) -> 0 | HA28: 0 | HB28: 0 | HC28: =GV28*GW28 -> 0 | HS28: 0 | IK28: 0
A29: 17 | B29: 1 | C29: =ROW(SmtRes!A8) -> 8 | D29: =ROW(EtalonRes!A10) -> 10 | E29: 1 | F29: 4.10-34-5 | G29: Монтаж коммутатора служебной связи / демонтаж коммутатора | H29: 1 ШТ. | I29: =ROUND(5+3+1,9) -> 9 | J29: 0 | K29: =ROUND(5+3+1,9) -> 9 | O29: =ROUND(CP29,2) -> 16529.67 | P29: =ROUND((ROUND((AC29*AW29*I29),2)*BC29),2) -> 0 | Q29: =(ROUND((ROUND(((((ET29*1.2)*0.3))*AV29*I29),2)*BB29),2)+ROUND((ROUND(((AE29-(((EU29*1.2)*0.3)))*AV29*I29),2)*BS29),2)) -> 1573.82 | R29: =(ROUND((ROUND(((((EU29*1.2)*0.3))*AV29*I29),2)*BS29),2)+ROUND((ROUND(((AE29-(((EU29*1.2)*0.3)))*AV29*I29),2)*BS29),2)) -> 604.07 | S29: =ROUND((ROUND((AF29*AV29*I29),2)*BA29),2) -> 14955.85 | T29: =ROUND(CU29*I29,2) -> 0 | U29: =CV29*I29 -> 21.032136 | V29: =CW29*I29 -> 0 | W29: =ROUND(CX29*I29,2) -> 0 | X29: =(ROUND((((S29+ROUND((ROUND(((((EU29*1.2)*0.3))*AV29*I29),2)*BS29),2))*AT29)/100),2)+ROUND(((ROUND((ROUND(((AE29-(((EU29*1.2)*0.3)))*AV29*I29),2)*BS29),2)*AT29)/100),2)) -> 14003.93 | Y29: =(ROUND((((S29+ROUND((ROUND(((((EU29*1.2)*0.3))*AV29*I29),2)*BS29),2))*AU29)/100),2)+ROUND(((ROUND((ROUND(((AE29-(((EU29*1.2)*0.3)))*AV29*I29),2)*BS29),2)*AU29)/100),2)) -> 7157.56 | AA29: 55929115 | AB29: =ROUND((AC29+AD29+AF29),6) -> 38.502 | AC29: =ROUND((((ES29*1)*0)),6) -> 0 | AD29: =ROUND((((((ET29*1.2)*0.3))-(((EU29*1.2)*0.3)))+AE29),6) -> 10.3356 | AE29: =ROUND((((EU29*1.2)*0.3)),6) -> 1.1376 | AF29: =ROUND((((EV29*1.2)*0.3)),6) -> 28.1664 | AG29: =ROUND((AP29),6) -> 0 | AH29: =(((EW29*1.2)*0.3)) -> 2.232 | AI29: =(((EX29*1.2)*0.3)) -> 0 | AJ29: =(AS29) -> 0 | AK29: 119.3 | AL29: 12.35 | AM29: 28.71 | AN29: 3.16 | AO29: 78.24 | AP29: 0 | AQ29: 6.2 | AR29: 0 | AS29: 0 | AT29: 90 | AU29: 46 | AV29: 1.047 | AW29: 1 | AZ29: 1 | BA29: 56.35 | BB29: 16.16 | BC29: 14.7 | BH29: 0 | BI29: 2 | BJ29: ТСН-2001.4 Доп. 80, Сб. 10, т. 34, поз. 5 | BM29: 68 | BN29: 0 | BO29: 4.10-34-5 | BP29: 1 | BQ29: 40 | BR29: 0 | BS29: 56.35 | BT29: 1 | BU29: 1 | BV29: 1 | BW29: 1 | BX29: 1 | BZ29: 90 | CA29: 46 | CE29: 1566 | CF29: 0 | CG29: 0 | CM29: 0 | CN29: Поправка: Гл.12.Прил.8.п.8. 3_12.00.01.11.001 Наименование: При наличии напряженных и стесненных условий производства работ (стесненность, сложность складирования и транспортной логистики и т.п.) для объектов, расположенных в пределах круговой магистральной системы улиц "Садовое кольцо" города Москвы Поправка: Гл.4.Прил.2.2.п.2.2.29_04.00.01.35.003 Наименование: При демонтаже оборудования, предназначенного в лом | CO29: 0 | CP29: =(P29+Q29+S29) -> 16529.67 | CQ29: =ROUND((ROUND((AC29*AW29*1),2)*BC29),2) -> 0 | CR29: =(ROUND((ROUND(((((ET29*1.2)*0.3))*AV29*1),2)*BB29),2)+ROUND((ROUND(((AE29-(((EU29*1.2)*0.3)))*AV29*1),2)*BS29),2)) -> 174.85 | CS29: =(ROUND((ROUND(((((EU29*1.2)*0.3))*AV29*1),2)*BS29),2)+ROUND((ROUND(((AE29-(((EU29*1.2)*0.3)))*AV29*1),2)*BS29),2)) -> 67.06 | CT29: =ROUND((ROUND((AF29*AV29*1),2)*BA29),2) -> 1661.76 | CU29: =AG29 -> 0 | CV29: =(AH29*AV29) -> 2.336904 | CW29: =AI29 -> 0 | CX29: =AJ29 -> 0 | CY29: =(ROUND((((S29+ROUND((ROUND(((((EU29*1.2)*0.3))*AV29*1),2)*BS29),2))*AT29)/100),2)+ROUND(((ROUND((ROUND(((AE29-(((EU29*1.2)*0.3)))*AV29*1),2)*BS29),2)*AT29)/100),2)) -> 13520.62 | CZ29: =(ROUND((((S29+ROUND((ROUND(((((EU29*1.2)*0.3))*AV29*1),2)*BS29),2))*AU29)/100),2)+ROUND(((ROUND((ROUND(((AE29-(((EU29*1.2)*0.3)))*AV29*1),2)*BS29),2)*AU29)/100),2)) -> 6910.54 | DB29: 3 | DD29: *1)*0 | DE29: *1,2)*0,3 | DF29: *1,2)*0,3 | DG29: *1,2)*0,3 | DI29: *1,2)*0,3 | DJ29: *1,2)*0,3 | DN29: 0 | DO29: 0 | DP29: 1 | DQ29: 1 | DU29: 1013 | DV29: 1 ШТ. | DW29: 1 ШТ. | DX29: 1 | EE29: 55393700 | EF29: 40 | EG29: Монтаж оборудования | EH29: 0 | EJ29: 2 | EK29: 68 | EL29: ТСН-2001.4-10. Прокладка и монтаж сетей связи | EM29: ТСН-2001.4-10-1 | EO29: Поправка: Гл.12.Прил.8.п.8. 3_12.00.01.11.001 Поправка: Гл.4.Прил.2.2.п.2.2.29_04.00.01.35.003 | EQ29: 0 | ER29: 119.3 | ES29: 12.35 | ET29: 28.71 | EU29: 3.16 | EV29: 78.24 | EW29: 6.2 | EX29: 0 | EY29: 0 | FQ29: 0 | FR29: 0 | FS29: 0 | FX29: 90 | FY29: 46 | GD29: 1 | GF29: -1384911768 | GG29: 2 | GH29: 1 | GI29: 2 | GJ29: 0 | GK29: 0 | GL29: =ROUND(IF(AND(BH29=3,BI29=3,FS29<>0),P29,0),2) -> 0 | GM29: =ROUND(O29+X29+Y29,2)+GX29 -> 37691.16 | GN29: =IF(OR(BI29=0,BI29=1),GM29-GX29,0) -> 0 | GO29: =IF(BI29=2,GM29-GX29,0) -> 37691.16 | GP29: =IF(BI29=4,GM29-GX29,0) -> 0 | GR29: 0 | GS29: 3 | GT29: 0 | GV29: =ROUND((GT29),6) -> 0 | GW29: 1 | GX29: =ROUND(HC29*I29,2) -> 0 | HA29: 0 | HB29: 0 | HC29: =GV29*GW29 -> 0 | HS29: 0 | IK29: 0
A30: 17 | B30: 1 | C30: =ROW(SmtRes!A21) -> 21 | D30: =ROW(EtalonRes!A26) -> 26 | E30: 2 | F30: 4.10-19-6 | G30: Монтаж отдельно устанавливаемого преобразователя или блока питания / демонтаж модуля питания | H30: 1 ШТ. | I30: 6 | J30: 0 | K30: 6 | O30: =ROUND(CP30,2) -> 409.67 | P30: =ROUND((ROUND((AC30*AW30*I30),2)*BC30),2) -> 0 | Q30: =(ROUND((ROUND(((((ET30*1.2)*0.3))*AV30*I30),2)*BB30),2)+ROUND((ROUND(((AE30-(((EU30*1.2)*0.3)))*AV30*I30),2)*BS30),2)) -> 103.87 | R30: =(ROUND((ROUND(((((EU30*1.2)*0.3))*AV30*I30),2)*BS30),2)+ROUND((ROUND(((AE30-(((EU30*1.2)*0.3)))*AV30*I30),2)*BS30),2)) -> 11.42 | S30: =ROUND((ROUND((AF30*AV30*I30),2)*BA30),2) -> 305.8 | T30: =ROUND(CU30*I30,2) -> 0 | U30: =CV30*I30 -> 21.032136 | V30: =CW30*I30 -> 0 | W30: =ROUND(CX30*I30,2) -> 0 | X30: =(ROUND((((S30+ROUND((ROUND(((((EU30*1.2)*0.3))*AV30*I30),2)*BS30),2))*AT30)/100),2)+ROUND(((ROUND((ROUND(((AE30-(((EU30*1.2)*0.3)))*AV30*I30),2)*BS30),2)*AT30)/100),2)) -> 285.5 | Y30: =(ROUND((((S30+ROUND((ROUND(((((EU30*1.2)*0.3))*AV30*I30),2)*BS30),2))*AU30)/100),2)+ROUND(((ROUND((ROUND(((AE30-(((EU30*1.2)*0.3)))*AV30*I30),2)*BS30),2)*AU30)/100),2)) -> 145.92 | AA30: 55929113 | AB30: =ROUND((AC30+AD30+AF30),6) -> 65.214 | AC30: =ROUND((((ES30*1)*0)),6) -> 0 | AD30: =ROUND((((((ET30*1.2)*0.3))-(((EU30*1.2)*0.3)))+AE30),6) -> 16.5348 | AE30: =ROUND((((EU30*1.2)*0.3)),6) -> 1.818 | AF30: =ROUND((((EV30*1.2)*0.3)),6) -> 48.6792 | AG30: =ROUND((AP30),6) -> 0 | AH30: =(((EW30*1.2)*0.3)) -> 3.348 | AI30: =(((EX30*1.2)*0.3)) -> 0 | AJ30: =(AS30) -> 0 | AK30: 236.95 | AL30: 55.8 | AM30: 45.93 | AN30: 5.05 | AO30: 135.22 | AP30: 0 | AQ30: 9.3 | AR30: 0 | AS30: 0 | AT30: 90 | AU30: 46 | AV30: 1.047 | AW30: 1 | AZ30: 1 | BA30: 1 | BB30: 1 | BC30: 1 | BH30: 0 | BI30: 2 | BJ30: ТСН-2001.4 Доп. 70, Сб. 10, т. 19, поз. 6 | BM30: 68 | BN30: 0 | BO30: 4.10-19-6 | BP30: 1 | BQ30: 40 | BR30: 0 | BS30: 1 | BT30: 1 | BU30: 1 | BV30: 1 | BW30: 1 | BX30: 1 | BZ30: 90 | CA30: 46 | CE30: 1566 | CF30: 0 | CG30: 0 | CM30: 0 | CN30: Поправка: Гл.12.Прил.8.п.8. 3_12.00.01.11.001 Наименование: При наличии напряженных и стесненных условий производства работ (стесненность, сложность складирования и транспортной логистики и т.п.) для объектов, расположенных в пределах круговой магистральной системы улиц "Садовое кольцо" города Москвы Поправка: Гл.4.Прил.2.2.п.2.2.29_04.00.01.35.003 Наименование: При демонтаже оборудования, предназначенного в лом | CO30: 0 | CP30: =(P30+Q30+S30) -> 409.67 | CQ30: =ROUND((ROUND((AC30*AW30*1),2)*BC30),2) -> 0 | CR30: =(ROUND((ROUND(((((ET30*1.2)*0.3))*AV30*1),2)*BB30),2)+ROUND((ROUND(((AE30-(((EU30*1.2)*0.3)))*AV30*1),2)*BS30),2)) -> 17.31 | CS30: =(ROUND((ROUND(((((EU30*1.2)*0.3))*AV30*1),2)*BS30),2)+ROUND((ROUND(((AE30-(((EU30*1.2)*0.3)))*AV30*1),2)*BS30),2)) -> 1.9 | CT30: =ROUND((ROUND((AF30*AV30*1),2)*BA30),2) -> 50.97 | CU30: =AG30 -> 0 | CV30: =(AH30*AV30) -> 3.505356 | CW30: =AI30 -> 0 | CX30: =AJ30 -> 0 | CY30: =(ROUND((((S30+ROUND((ROUND(((((EU30*1.2)*0.3))*AV30*1),2)*BS30),2))*AT30)/100),2)+ROUND(((ROUND((ROUND(((AE30-(((EU30*1.2)*0.3)))*AV30*1),2)*BS30),2)*AT30)/100),2)) -> 276.93 | CZ30: =(ROUND((((S30+ROUND((ROUND(((((EU30*1.2)*0.3))*AV30*1),2)*BS30),2))*AU30)/100),2)+ROUND(((ROUND((ROUND(((AE30-(((EU30*1.2)*0.3)))*AV30*1),2)*BS30),2)*AU30)/100),2)) -> 141.54 | DB30: 5 | DD30: *1)*0 | DE30: *1,2)*0,3 | DF30: *1,2)*0,3 | DG30: *1,2)*0,3 | DI30: *1,2)*0,3 | DJ30: *1,2)*0,3 | DN30: 0 | DO30: 0 | DP30: 1 | DQ30: 1 | DU30: 1013 | DV30: 1 ШТ. | DW30: 1 ШТ. | DX30: 1 | EE30: 55393700 | EF30: 40 | EG30: Монтаж оборудования | EH30: 0 | EJ30: 2 | EK30: 68 | EL30: ТСН-2001.4-10. Прокладка и монтаж сетей связи | EM30: ТСН-2001.4-10-1 | EO30: Поправка: Гл.12.Прил.8.п.8. 3_12.00.01.11.001 Поправка: Гл.4.Прил.2.2.п.2.2.29_04.00.01.35.003 | EQ30: 0 | ER30: 236.95 | ES30: 55.8 | ET30: 45.93 | EU30: 5.05 | EV30: 135.22 | EW30: 9.3 | EX30: 0 | EY30: 0 | FQ30: 0 | FR30: 0 | FS30: 0 | FX30: 90 | FY30: 46 | GD30: 1 | GF30: 224001626 | GG30: 2 | GH30: 1 | GI30: 2 | GJ30: 0 | GK30: 0 | GL30: =ROUND(IF(AND(BH30=3,BI30=3,FS30<>0),P30,0),2) -> 0 | GM30: =ROUND(O30+X30+Y30,2)+GX30 -> 841.09 | GN30: =IF(OR(BI30=0,BI30=1),GM30-GX30,0) -> 0 | GO30: =IF(BI30=2,GM30-GX30,0) -> 841.09 | GP30: =IF(BI30=4,GM30-GX30,0) -> 0 | GR30: 0 | GS30: 3 | GT30: 0 | GV30: =ROUND((GT30),6) -> 0 | GW30: 1 | GX30: =ROUND(HC30*I30,2) -> 0 | HA30: 0 | HB30: 0 | HC30: =GV30*GW30 -> 0 | HS30: 0 | IK30: 0
A31: 17 | B31: 1 | C31: =ROW(SmtRes!A34) -> 34 | D31: =ROW(EtalonRes!A42) -> 42 | E31: 2 | F31: 4.10-19-6 | G31: Монтаж отдельно устанавливаемого преобразователя или блока питания / демонтаж модуля питания | H31: 1 ШТ. | I31: 6 | J31: 0 | K31: 6 | O31: =ROUND(CP31,2) -> 18910.37 | P31: =ROUND((ROUND((AC31*AW31*I31),2)*BC31),2) -> 0 | Q31: =(ROUND((ROUND(((((ET31*1.2)*0.3))*AV31*I31),2)*BB31),2)+ROUND((ROUND(((AE31-(((EU31*1.2)*0.3)))*AV31*I31),2)*BS31),2)) -> 1678.54 | R31: =(ROUND((ROUND(((((EU31*1.2)*0.3))*AV31*I31),2)*BS31),2)+ROUND((ROUND(((AE31-(((EU31*1.2)*0.3)))*AV31*I31),2)*BS31),2)) -> 643.52 | S31: =ROUND((ROUND((AF31*AV31*I31),2)*BA31),2) -> 17231.83 | T31: =ROUND(CU31*I31,2) -> 0 | U31: =CV31*I31 -> 21.032136 | V31: =CW31*I31 -> 0 | W31: =ROUND(CX31*I31,2) -> 0 | X31: =(ROUND((((S31+ROUND((ROUND(((((EU31*1.2)*0.3))*AV31*I31),2)*BS31),2))*AT31)/100),2)+ROUND(((ROUND((ROUND(((AE31-(((EU31*1.2)*0.3)))*AV31*I31),2)*BS31),2)*AT31)/100),2)) -> 16087.82 | Y31: =(ROUND((((S31+ROUND((ROUND(((((EU31*1.2)*0.3))*AV31*I31),2)*BS31),2))*AU31)/100),2)+ROUND(((ROUND((ROUND(((AE31-(((EU31*1.2)*0.3)))*AV31*I31),2)*BS31),2)*AU31)/100),2)) -> 8222.66 | AA31: 55929115 | AB31: =ROUND((AC31+AD31+AF31),6) -> 65.214 | AC31: =ROUND((((ES31*1)*0)),6) -> 0 | AD31: =ROUND((((((ET31*1.2)*0.3))-(((EU31*1.2)*0.3)))+AE31),6) -> 16.5348 | AE31: =ROUND((((EU31*1.2)*0.3)),6) -> 1.818 | AF31: =ROUND((((EV31*1.2)*0.3)),6) -> 48.6792 | AG31: =ROUND((AP31),6) -> 0 | AH31: =(((EW31*1.2)*0.3)) -> 3.348 | AI31: =(((EX31*1.2)*0.3)) -> 0 | AJ31: =(AS31) -> 0 | AK31: 236.95 | AL31: 55.8 | AM31: 45.93 | AN31: 5.05 | AO31: 135.22 | AP31: 0 | AQ31: 9.3 | AR31: 0 | AS31: 0 | AT31: 90 | AU31: 46 | AV31: 1.047 | AW31: 1 | AZ31: 1 | BA31: 56.35 | BB31: 16.16 | BC31: 10.51 | BH31: 0 | BI31: 2 | BJ31: ТСН-2001.4 Доп. 70, Сб. 10, т. 19, поз. 6 | BM31: 68 | BN31: 0 | BO31: 4.10-19-6 | BP31: 1 | BQ31: 40 | BR31: 0 | BS31: 56.35 | BT31: 1 | BU31: 1 | BV31: 1 | BW31: 1 | BX31: 1 | BZ31: 90 | CA31: 46 | CE31: 1566 | CF31: 0 | CG31: 0 | CM31: 0 | CN31: Поправка: Гл.12.Прил.8.п.8. 3_12.00.01.11.001 Наименование: При наличии напряженных и стесненных условий производства работ (стесненность, сложность складирования и транспортной логистики и т.п.) для объектов, расположенных в пределах круговой магистральной системы улиц "Садовое кольцо" города Москвы Поправка: Гл.4.Прил.2.2.п.2.2.29_04.00.01.35.003 Наименование: При демонтаже оборудования, предназначенного в лом | CO31: 0 | CP31: =(P31+Q31+S31) -> 18910.37 | CQ31: =ROUND((ROUND((AC31*AW31*1),2)*BC31),2) -> 0 | CR31: =(ROUND((ROUND(((((ET31*1.2)*0.3))*AV31*1),2)*BB31),2)+ROUND((ROUND(((AE31-(((EU31*1.2)*0.3)))*AV31*1),2)*BS31),2)) -> 279.73 | CS31: =(ROUND((ROUND(((((EU31*1.2)*0.3))*AV31*1),2)*BS31),2)+ROUND((ROUND(((AE31-(((EU31*1.2)*0.3)))*AV31*1),2)*BS31),2)) -> 107.07 | CT31: =ROUND((ROUND((AF31*AV31*1),2)*BA31),2) -> 2872.16 | CU31: =AG31 -> 0 | CV31: =(AH31*AV31) -> 3.505356 | CW31: =AI31 -> 0 | CX31: =AJ31 -> 0 | CY31: =(ROUND((((S31+ROUND((ROUND(((((EU31*1.2)*0.3))*AV31*1),2)*BS31),2))*AT31)/100),2)+ROUND(((ROUND((ROUND(((AE31-(((EU31*1.2)*0.3)))*AV31*1),2)*BS31),2)*AT31)/100),2)) -> 15605.01 | CZ31: =(ROUND((((S31+ROUND((ROUND(((((EU31*1.2)*0.3))*AV31*1),2)*BS31),2))*AU31)/100),2)+ROUND(((ROUND((ROUND(((AE31-(((EU31*1.2)*0.3)))*AV31*1),2)*BS31),2)*AU31)/100),2)) -> 7975.89 | DB31: 7 | DD31: *1)*0 | DE31: *1,2)*0,3 | DF31: *1,2)*0,3 | DG31: *1,2)*0,3 | DI31: *1,2)*0,3 | DJ31: *1,2)*0,3 | DN31: 0 | DO31: 0 | DP31: 1 | DQ31: 1 | DU31: 1013 | DV31: 1 ШТ. | DW31: 1 ШТ. | DX31: 1 | EE31: 55393700 | EF31: 40 | EG31: Монтаж оборудования | EH31: 0 | EJ31: 2 | EK31: 68 | EL31: ТСН-2001.4-10. Прокладка и монтаж сетей связи | EM31: ТСН-2001.4-10-1 | EO31: Поправка: Гл.12.Прил.8.п.8. 3_12.00.01.11.001 Поправка: Гл.4.Прил.2.2.п.2.2.29_04.00.01.35.003 | EQ31: 0 | ER31: 236.95 | ES31: 55.8 | ET31: 45.93 | EU31: 5.05 | EV31: 135.22 | EW31: 9.3 | EX31: 0 | EY31: 0 | FQ31: 0 | FR31: 0 | FS31: 0 | FX31: 90 | FY31: 46 | GD31: 1 | GF31: 224001626 | GG31: 2 | GH31: 1 | GI31: 2 | GJ31: 0 | GK31: 0 | GL31: =ROUND(IF(AND(BH31=3,BI31=3,FS31<>0),P31,0),2) -> 0 | GM31: =ROUND(O31+X31+Y31,2)+GX31 -> 43220.85 | GN31: =IF(OR(BI31=0,BI31=1),GM31-GX31,0) -> 0 | GO31: =IF(BI31=2,GM31-GX31,0) -> 43220.85 | GP31: =IF(BI31=4,GM31-GX31,0) -> 0 | GR31: 0 | GS31: 3 | GT31: 0 | GV31: =ROUND((GT31),6) -> 0 | GW31: 1 | GX31: =ROUND(HC31*I31,2) -> 0 | HA31: 0 | HB31: 0 | HC31: =GV31*GW31 -> 0 | HS31: 0 | IK31: 0
A32: 17 | B32: 1 | C32: =ROW(SmtRes!A36) -> 36 | D32: =ROW(EtalonRes!A45) -> 45 | E32: 3 | F32: 4.11-12-1 | G32: Установка съемных и выдвижных блоков (модулей, ячеек, ТЭЗ) массой до 5 кг / демонтаж SFP модулей | H32: 1 ШТ. | I32: =ROUND(2+12,9) -> 14 | J32: 0 | K32: =ROUND(2+12,9) -> 14 | O32: =ROUND(CP32,2) -> 64.12 | P32: =ROUND((ROUND((AC32*AW32*I32),2)*BC32),2) -> 0 | Q32: =(ROUND((ROUND(((((ET32*1.2)*0.3))*AV32*I32),2)*BB32),2)+ROUND((ROUND(((AE32-(((EU32*1.2)*0.3)))*AV32*I32),2)*BS32),2)) -> 2.64 | R32: =(ROUND((ROUND(((((EU32*1.2)*0.3))*AV32*I32),2)*BS32),2)+ROUND((ROUND(((AE32-(((EU32*1.2)*0.3)))*AV32*I32),2)*BS32),2)) -> 0.42 | S32: =ROUND((ROUND((AF32*AV32*I32),2)*BA32),2) -> 61.48 | T32: =ROUND(CU32*I32,2) -> 0 | U32: =CV32*I32 -> 5.4351864 | V32: =CW32*I32 -> 0 | W32: =ROUND(CX32*I32,2) -> 0 | X32: =(ROUND((((S32+ROUND((ROUND(((((EU32*1.2)*0.3))*AV32*I32),2)*BS32),2))*AT32)/100),2)+ROUND(((ROUND((ROUND(((AE32-(((EU32*1.2)*0.3)))*AV32*I32),2)*BS32),2)*AT32)/100),2)) -> 55.71 | Y32: =(ROUND((((S32+ROUND((ROUND(((((EU32*1.2)*0.3))*AV32*I32),2)*BS32),2))*AU32)/100),2)+ROUND(((ROUND((ROUND(((AE32-(((EU32*1.2)*0.3)))*AV32*I32),2)*BS32),2)*AU32)/100),2)) -> 28.47 | AA32: 55929113 | AB32: =ROUND((AC32+AD32+AF32),6) -> 4.374 | AC32: =ROUND((((ES32*1)*0)),6) -> 0 | AD32: =ROUND((((((ET32*1.2)*0.3))-(((EU32*1.2)*0.3)))+AE32),6) -> 0.18 | AE32: =ROUND((((EU32*1.2)*0.3)),6) -> 0.0288 | AF32: =ROUND((((EV32*1.2)*0.3)),6) -> 4.194 | AG32: =ROUND((AP32),6) -> 0 | AH32: =(((EW32*1.2)*0.3)) -> 0.3708 | AI32: =(((EX32*1.2)*0.3)) -> 0 | AJ32: =(AS32) -> 0 | AK32: 12.15 | AL32: 0 | AM32: 0.5 | AN32: 0.08 | AO32: 11.65 | AP32: 0 | AQ32: 1.03 | AR32: 0 | AS32: 0 | AT32: 90 | AU32: 46 | AV32: 1.047 | AW32: 1 | AZ32: 1 | BA32: 1 | BB32: 1 | BC32: 1 | BH32: 0 | BI32: 2 | BJ32: ТСН-2001.4 Доп. 68, Сб. 11, т. 12, поз. 1 | BM32: 72 | BN32: 0 | BO32: 4.11-12-1 | BP32: 1 | BQ32: 40 | BR32: 0 | BS32: 1 | BT32: 1 | BU32: 1 | BV32: 1 | BW32: 1 | BX32: 1 | BZ32: 90 | CA32: 46 | CE32: 1566 | CF32: 0 | CG32: 0 | CM32: 0 | CN32: Поправка: Гл.12.Прил.8.п.8. 3_12.00.01.11.001 Наименование: При наличии напряженных и стесненных условий производства работ (стесненность, сложность складирования и транспортной логистики и т.п.) для объектов, расположенных в пределах круговой магистральной системы улиц "Садовое кольцо" города Москвы Поправка: Гл.4.Прил.2.2.п.2.2.29_04.00.01.35.003 Наименование: При демонтаже оборудования, предназначенного в лом | CO32: 0 | CP32: =(P32+Q32+S32) -> 64.12 | CQ32: =ROUND((ROUND((AC32*AW32*1),2)*BC32),2) -> 0 | CR32: =(ROUND((ROUND(((((ET32*1.2)*0.3))*AV32*1),2)*BB32),2)+ROUND((ROUND(((AE32-(((EU32*1.2)*0.3)))*AV32*1),2)*BS32),2)) -> 0.19 | CS32: =(ROUND((ROUND(((((EU32*1.2)*0.3))*AV32*1),2)*BS32),2)+ROUND((ROUND(((AE32-(((EU32*1.2)*0.3)))*AV32*1),2)*BS32),2)) -> 0.03 | CT32: =ROUND((ROUND((AF32*AV32*1),2)*BA32),2) -> 4.39 | CU32: =AG32 -> 0 | CV32: =(AH32*AV32) -> 0.3882276 | CW32: =AI32 -> 0 | CX32: =AJ32 -> 0 | CY32: =(ROUND((((S32+ROUND((ROUND(((((EU32*1.2)*0.3))*AV32*1),2)*BS32),2))*AT32)/100),2)+ROUND(((ROUND((ROUND(((AE32-(((EU32*1.2)*0.3)))*AV32*1),2)*BS32),2)*AT32)/100),2)) -> 55.36 | CZ32: =(ROUND((((S32+ROUND((ROUND(((((EU32*1.2)*0.3))*AV32*1),2)*BS32),2))*AU32)/100),2)+ROUND(((ROUND((ROUND(((AE32-(((EU32*1.2)*0.3)))*AV32*1),2)*BS32),2)*AU32)/100),2)) -> 28.29 | DB32: 9 | DD32: *1)*0 | DE32: *1,2)*0,3 | DF32: *1,2)*0,3 | DG32: *1,2)*0,3 | DI32: *1,2)*0,3 | DJ32: *1,2)*0,3 | DN32: 0 | DO32: 0 | DP32: 1 | DQ32: 1 | DU32: 1013 | DV32: 1 ШТ. | DW32: 1 ШТ. | DX32: 1 | EE32: 55393704 | EF32: 40 | EG32: Монтаж оборудования | EH32: 0 | EJ32: 2 | EK32: 72 | EL32: ТСН-2001.4-11. Приборы и средства автоматизации и вычислительной техники | EM32: ТСН-2001.4-11-1 | EO32: Поправка: Гл.12.Прил.8.п.8. 3_12.00.01.11.001 Поправка: Гл.4.Прил.2.2.п.2.2.29_04.00.01.35.003 | EQ32: 0 | ER32: 12.15 | ES32: 0 | ET32: 0.5 | EU32: 0.08 | EV32: 11.65 | EW32: 1.03 | EX32: 0 | EY32: 0 | FQ32: 0 | FR32: 0 | FS32: 0 | FX32: 90 | FY32: 46 | GD32: 1 | GF32: -1677673030 | GG32: 2 | GH32: 1 | GI32: 2 | GJ32: 0 | GK32: 0 | GL32: =ROUND(IF(AND(BH32=3,BI32=3,FS32<>0),P32,0),2) -> 0 | GM32: =ROUND(O32+X32+Y32,2)+GX32 -> 148.3 | GN32: =IF(OR(BI32=0,BI32=1),GM32-GX32,0) -> 0 | GO32: =IF(BI32=2,GM32-GX32,0) -> 148.3 | GP32: =IF(BI32=4,GM32-GX32,0) -> 0 | GR32: 0 | GS32: 3 | GT32: 0 | GV32: =ROUND((GT32),6) -> 0 | GW32: 1 | GX32: =ROUND(HC32*I32,2) -> 0 | HA32: 0 | HB32: 0 | HC32: =GV32*GW32 -> 0 | HS32: 0 | IK32: 0
A33: 17 | B33: 1 | C33: =ROW(SmtRes!A38) -> 38 | D33: =ROW(EtalonRes!A48) -> 48 | E33: 3 | F33: 4.11-12-1 | G33: Установка съемных и выдвижных блоков (модулей, ячеек, ТЭЗ) массой до 5 кг / демонтаж SFP модулей | H33: 1 ШТ. | I33: =ROUND(2+12,9) -> 14 | J33: 0 | K33: =ROUND(2+12,9) -> 14 | O33: =ROUND(CP33,2) -> 3509.33 | P33: =ROUND((ROUND((AC33*AW33*I33),2)*BC33),2) -> 0 | Q33: =(ROUND((ROUND(((((ET33*1.2)*0.3))*AV33*I33),2)*BB33),2)+ROUND((ROUND(((AE33-(((EU33*1.2)*0.3)))*AV33*I33),2)*BS33),2)) -> 44.93 | R33: =(ROUND((ROUND(((((EU33*1.2)*0.3))*AV33*I33),2)*BS33),2)+ROUND((ROUND(((AE33-(((EU33*1.2)*0.3)))*AV33*I33),2)*BS33),2)) -> 23.67 | S33: =ROUND((ROUND((AF33*AV33*I33),2)*BA33),2) -> 3464.4 | T33: =ROUND(CU33*I33,2) -> 0 | U33: =CV33*I33 -> 5.4351864 | V33: =CW33*I33 -> 0 | W33: =ROUND(CX33*I33,2) -> 0 | X33: =(ROUND((((S33+ROUND((ROUND(((((EU33*1.2)*0.3))*AV33*I33),2)*BS33),2))*AT33)/100),2)+ROUND(((ROUND((ROUND(((AE33-(((EU33*1.2)*0.3)))*AV33*I33),2)*BS33),2)*AT33)/100),2)) -> 3139.26 | Y33: =(ROUND((((S33+ROUND((ROUND(((((EU33*1.2)*0.3))*AV33*I33),2)*BS33),2))*AU33)/100),2)+ROUND(((ROUND((ROUND(((AE33-(((EU33*1.2)*0.3)))*AV33*I33),2)*BS33),2)*AU33)/100),2)) -> 1604.51 | AA33: 55929115 | AB33: =ROUND((AC33+AD33+AF33),6) -> 4.374 | AC33: =ROUND((((ES33*1)*0)),6) -> 0 | AD33: =ROUND((((((ET33*1.2)*0.3))-(((EU33*1.2)*0.3)))+AE33),6) -> 0.18 | AE33: =ROUND((((EU33*1.2)*0.3)),6) -> 0.0288 | AF33: =ROUND((((EV33*1.2)*0.3)),6) -> 4.194 | AG33: =ROUND((AP33),6) -> 0 | AH33: =(((EW33*1.2)*0.3)) -> 0.3708 | AI33: =(((EX33*1.2)*0.3)) -> 0 | AJ33: =(AS33) -> 0 | AK33: 12.15 | AL33: 0 | AM33: 0.5 | AN33: 0.08 | AO33: 11.65 | AP33: 0 | AQ33: 1.03 | AR33: 0 | AS33: 0 | AT33: 90 | AU33: 46 | AV33: 1.047 | AW33: 1 | AZ33: 1 | BA33: 56.35 | BB33: 17.02 | BC33: 1 | BH33: 0 | BI33: 2 | BJ33: ТСН-2001.4 Доп. 68, Сб. 11, т. 12, поз. 1 | BM33: 72 | BN33: 0 | BO33: 4.11-12-1 | BP33: 1 | BQ33: 40 | BR33: 0 | BS33: 56.35 | BT33: 1 | BU33: 1 | BV33: 1 | BW33: 1 | BX33: 1 | BZ33: 90 | CA33: 46 | CE33: 1566 | CF33: 0 | CG33: 0 | CM33: 0 | CN33: Поправка: Гл.12.Прил.8.п.8. 3_12.00.01.11.001 Наименование: При наличии напряженных и стесненных условий производства работ (стесненность, сложность складирования и транспортной логистики и т.п.) для объектов, расположенных в пределах круговой магистральной системы улиц "Садовое кольцо" города Москвы Поправка: Гл.4.Прил.2.2.п.2.2.29_04.00.01.35.003 Наименование: При демонтаже оборудования, предназначенного в лом | CO33: 0 | CP33: =(P33+Q33+S33) -> 3509.33 | CQ33: =ROUND((ROUND((AC33*AW33*1),2)*BC33),2) -> 0 | CR33: =(ROUND((ROUND(((((ET33*1.2)*0.3))*AV33*1),2)*BB33),2)+ROUND((ROUND(((AE33-(((EU33*1.2)*0.3)))*AV33*1),2)*BS33),2)) -> 3.23 | CS33: =(ROUND((ROUND(((((EU33*1.2)*0.3))*AV33*1),2)*BS33),2)+ROUND((ROUND(((AE33-(((EU33*1.2)*0.3)))*AV33*1),2)*BS33),2)) -> 1.69 | CT33: =ROUND((ROUND((AF33*AV33*1),2)*BA33),2) -> 247.38 | CU33: =AG33 -> 0 | CV33: =(AH33*AV33) -> 0.3882276 | CW33: =AI33 -> 0 | CX33: =AJ33 -> 0 | CY33: =(ROUND((((S33+ROUND((ROUND(((((EU33*1.2)*0.3))*AV33*1),2)*BS33),2))*AT33)/100),2)+ROUND(((ROUND((ROUND(((AE33-(((EU33*1.2)*0.3)))*AV33*1),2)*BS33),2)*AT33)/100),2)) -> 3119.48 | CZ33: =(ROUND((((S33+ROUND((ROUND(((((EU33*1.2)*0.3))*AV33*1),2)*BS33),2))*AU33)/100),2)+ROUND(((ROUND((ROUND(((AE33-(((EU33*1.2)*0.3)))*AV33*1),2)*BS33),2)*AU33)/100),2)) -> 1594.4 | DB33: 11 | DD33: *1)*0 | DE33: *1,2)*0,3 | DF33: *1,2)*0,3 | DG33: *1,2)*0,3 | DI33: *1,2)*0,3 | DJ33: *1,2)*0,3 | DN33: 0 | DO33: 0 | DP33: 1 | DQ33: 1 | DU33: 1013 | DV33: 1 ШТ. | DW33: 1 ШТ. | DX33: 1 | EE33: 55393704 | EF33: 40 | EG33: Монтаж оборудования | EH33: 0 | EJ33: 2 | EK33: 72 | EL33: ТСН-2001.4-11. Приборы и средства автоматизации и вычислительной техники | EM33: ТСН-2001.4-11-1 | EO33: Поправка: Гл.12.Прил.8.п.8. 3_12.00.01.11.001 Поправка: Гл.4.Прил.2.2.п.2.2.29_04.00.01.35.003 | EQ33: 0 | ER33: 12.15 | ES33: 0 | ET33: 0.5 | EU33: 0.08 | EV33: 11.65 | EW33: 1.03 | EX33: 0 | EY33: 0 | FQ33: 0 | FR33: 0 | FS33: 0 | FX33: 90 | FY33: 46 | GD33: 1 | GF33: -1677673030 | GG33: 2 | GH33: 1 | GI33: 2 | GJ33: 0 | GK33: 0 | GL33: =ROUND(IF(AND(BH33=3,BI33=3,FS33<>0),P33,0),2) -> 0 | GM33: =ROUND(O33+X33+Y33,2)+GX33 -> 8253.1 | GN33: =IF(OR(BI33=0,BI33=1),GM33-GX33,0) -> 0 | GO33: =IF(BI33=2,GM33-GX33,0) -> 8253.1 | GP33: =IF(BI33=4,GM33-GX33,0) -> 0 | GR33: 0 | GS33: 3 | GT33: 0 | GV33: =ROUND((GT33),6) -> 0 | GW33: 1 | GX33: =ROUND(HC33*I33,2) -> 0 | HA33: 0 | HB33: 0 | HC33: =GV33*GW33 -> 0 | HS33: 0 | IK33: 0
A34: 17 | B34: 1 | C34: =ROW(SmtRes!A39) -> 39 | D34: =ROW(EtalonRes!A49) -> 49 | E34: 4 | F34: 4.10-142-5 | G34: Монтаж и настройка электронных АТС типа Миником DX-500, станция с количеством номеров до 500, монтаж станции | H34: 100 номеров | I34: =ROUND(1/100,9) -> 0.01 | J34: 0 | K34: =ROUND(1/100,9) -> 0.01 | O34: =ROUND(CP34,2) -> 2.14 | P34: =ROUND((ROUND((AC34*AW34*I34),2)*BC34),2) -> 0 | Q34: =(ROUND((ROUND(((((ET34*1.2)*0.3))*AV34*I34),2)*BB34),2)+ROUND((ROUND(((AE34-(((EU34*1.2)*0.3)))*AV34*I34),2)*BS34),2)) -> 0 | R34: =(ROUND((ROUND(((((EU34*1.2)*0.3))*AV34*I34),2)*BS34),2)+ROUND((ROUND(((AE34-(((EU34*1.2)*0.3)))*AV34*I34),2)*BS34),2)) -> 0 | S34: =ROUND((ROUND((AF34*AV34*I34),2)*BA34),2) -> 2.14 | T34: =ROUND(CU34*I34,2) -> 0 | U34: =CV34*I34 -> 0.1469988 | V34: =CW34*I34 -> 0 | W34: =ROUND(CX34*I34,2) -> 0 | X34: =(ROUND((((S34+ROUND((ROUND(((((EU34*1.2)*0.3))*AV34*I34),2)*BS34),2))*AT34)/100),2)+ROUND(((ROUND((ROUND(((AE34-(((EU34*1.2)*0.3)))*AV34*I34),2)*BS34),2)*AT34)/100),2)) -> 1.93 | Y34: =(ROUND((((S34+ROUND((ROUND(((((EU34*1.2)*0.3))*AV34*I34),2)*BS34),2))*AU34)/100),2)+ROUND(((ROUND((ROUND(((AE34-(((EU34*1.2)*0.3)))*AV34*I34),2)*BS34),2)*AU34)/100),2)) -> 0.98 | AA34: 55929113 | AB34: =ROUND((AC34+AD34+AF34),6) -> 204.1416 | AC34: =ROUND((((ES34*1)*0)),6) -> 0 | AD34: =ROUND((((((ET34*1.2)*0.3))-(((EU34*1.2)*0.3)))+AE34),6) -> 0 | AE34: =ROUND((((EU34*1.2)*0.3)),6) -> 0 | AF34: =ROUND((((EV34*1.2)*0.3)),6) -> 204.1416 | AG34: =ROUND((AP34),6) -> 0 | AH34: =(((EW34*1.2)*0.3)) -> 14.04 | AI34: =(((EX34*1.2)*0.3)) -> 0 | AJ34: =(AS34) -> 0 | AK34: 567.06 | AL34: 0 | AM34: 0 | AN34: 0 | AO34: 567.06 | AP34: 0 | AQ34: 39 | AR34: 0 | AS34: 0 | AT34: 90 | AU34: 46 | AV34: 1.047 | AW34: 1 | AZ34: 1 | BA34: 1 | BB34: 1 | BC34: 1 | BH34: 0 | BI34: 2 | BJ34: ТСН-2001.4. Доп. 1-42. Сб. 10, т. 142, поз. 5 | BM34: 68 | BN34: 0 | BO34: 4.10-142-5 | BP34: 1 | BQ34: 40 | BR34: 0 | BS34: 1 | BT34: 1 | BU34: 1 | BV34: 1 | BW34: 1 | BX34: 1 | BZ34: 90 | CA34: 46 | CE34: 1566 | CF34: 0 | CG34: 0 | CM34: 0 | CN34: Поправка: Гл.12.Прил.8.п.8. 3_12.00.01.11.001 Наименование: При наличии напряженных и стесненных условий производства работ (стесненность, сложность складирования и транспортной логистики и т.п.) для объектов, расположенных в пределах круговой магистральной системы улиц "Садовое кольцо" города Москвы Поправка: Гл.4.Прил.2.2.п.2.2.29_04.00.01.35.003 Наименование: При демонтаже оборудования, предназначенного в лом | CO34: 0 | CP34: =(P34+Q34+S34) -> 2.14 | CQ34: =ROUND((ROUND((AC34*AW34*1),2)*BC34),2) -> 0 | CR34: =(ROUND((ROUND(((((ET34*1.2)*0.3))*AV34*1),2)*BB34),2)+ROUND((ROUND(((AE34-(((EU34*1.2)*0.3)))*AV34*1),2)*BS34),2)) -> 0 | CS34: =(ROUND((ROUND(((((EU34*1.2)*0.3))*AV34*1),2)*BS34),2)+ROUND((ROUND(((AE34-(((EU34*1.2)*0.3)))*AV34*1),2)*BS34),2)) -> 0 | CT34: =ROUND((ROUND((AF34*AV34*1),2)*BA34),2) -> 213.74 | CU34: =AG34 -> 0 | CV34: =(AH34*AV34) -> 14.69988 | CW34: =AI34 -> 0 | CX34: =AJ34 -> 0 | CY34: =(ROUND((((S34+ROUND((ROUND(((((EU34*1.2)*0.3))*AV34*1),2)*BS34),2))*AT34)/100),2)+ROUND(((ROUND((ROUND(((AE34-(((EU34*1.2)*0.3)))*AV34*1),2)*BS34),2)*AT34)/100),2)) -> 1.93 | CZ34: =(ROUND((((S34+ROUND((ROUND(((((EU34*1.2)*0.3))*AV34*1),2)*BS34),2))*AU34)/100),2)+ROUND(((ROUND((ROUND(((AE34-(((EU34*1.2)*0.3)))*AV34*1),2)*BS34),2)*AU34)/100),2)) -> 0.98 | DB34: 13 | DD34: *1)*0 | DE34: *1,2)*0,3 | DF34: *1,2)*0,3 | DG34: *1,2)*0,3 | DI34: *1,2)*0,3 | DJ34: *1,2)*0,3 | DN34: 0 | DO34: 0 | DP34: 1 | DQ34: 1 | DU34: 1013 | DV34: 100 номеров | DW34: 100 номеров | DX34: 1 | EE34: 55393700 | EF34: 40 | EG34: Монтаж оборудования | EH34: 0 | EJ34: 2 | EK34: 68 | EL34: ТСН-2001.4-10. Прокладка и монтаж сетей связи | EM34: ТСН-2001.4-10-1 | EO34: Поправка: Гл.12.Прил.8.п.8. 3_12.00.01.11.001 Поправка: Гл.4.Прил.2.2.п.2.2.29_04.00.01.35.003 | EQ34: 0 | ER34: 567.06 | ES34: 0 | ET34: 0 | EU34: 0 | EV34: 567.06 | EW34: 39 | EX34: 0 | EY34: 0 | FQ34: 0 | FR34: 0 | FS34: 0 | FX34: 90 | FY34: 46 | GD34: 1 | GF34: -821238356 | GG34: 2 | GH34: 1 | GI34: 2 | GJ34: 0 | GK34: 0 | GL34: =ROUND(IF(AND(BH34=3,BI34=3,FS34<>0),P34,0),2) -> 0 | GM34: =ROUND(O34+X34+Y34,2)+GX34 -> 5.05 | GN34: =IF(OR(BI34=0,BI34=1),GM34-GX34,0) -> 0 | GO34: =IF(BI34=2,GM34-GX34,0) -> 5.05 | GP34: =IF(BI34=4,GM34-GX34,0) -> 0 | GR34: 0 | GS34: 3 | GT34: 0 | GV34: =ROUND((GT34),6) -> 0 | GW34: 1 | GX34: =ROUND(HC34*I34,2) -> 0 | HA34: 0 | HB34: 0 | HC34: =GV34*GW34 -> 0 | HS34: 0 | IK34: 0
A35: 17 | B35: 1 | C35: =ROW(SmtRes!A40) -> 40 | D35: =ROW(EtalonRes!A50) -> 50 | E35: 4 | F35: 4.10-142-5 | G35: Монтаж и настройка электронных АТС типа Миником DX-500, станция с количеством номеров до 500, монтаж станции | H35: 100 номеров | I35: =ROUND(1/100,9) -> 0.01 | J35: 0 | K35: =ROUND(1/100,9) -> 0.01 | O35: =ROUND(CP35,2) -> 120.59 | P35: =ROUND((ROUND((AC35*AW35*I35),2)*BC35),2) -> 0 | Q35: =(ROUND((ROUND(((((ET35*1.2)*0.3))*AV35*I35),2)*BB35),2)+ROUND((ROUND(((AE35-(((EU35*1.2)*0.3)))*AV35*I35),2)*BS35),2)) -> 0 | R35: =(ROUND((ROUND(((((EU35*1.2)*0.3))*AV35*I35),2)*BS35),2)+ROUND((ROUND(((AE35-(((EU35*1.2)*0.3)))*AV35*I35),2)*BS35),2)) -> 0 | S35: =ROUND((ROUND((AF35*AV35*I35),2)*BA35),2) -> 120.59 | T35: =ROUND(CU35*I35,2) -> 0 | U35: =CV35*I35 -> 0.1469988 | V35: =CW35*I35 -> 0 | W35: =ROUND(CX35*I35,2) -> 0 | X35: =(ROUND((((S35+ROUND((ROUND(((((EU35*1.2)*0.3))*AV35*I35),2)*BS35),2))*AT35)/100),2)+ROUND(((ROUND((ROUND(((AE35-(((EU35*1.2)*0.3)))*AV35*I35),2)*BS35),2)*AT35)/100),2)) -> 108.53 | Y35: =(ROUND((((S35+ROUND((ROUND(((((EU35*1.2)*0.3))*AV35*I35),2)*BS35),2))*AU35)/100),2)+ROUND(((ROUND((ROUND(((AE35-(((EU35*1.2)*0.3)))*AV35*I35),2)*BS35),2)*AU35)/100),2)) -> 55.47 | AA35: 55929115 | AB35: =ROUND((AC35+AD35+AF35),6) -> 204.1416 | AC35: =ROUND((((ES35*1)*0)),6) -> 0 | AD35: =ROUND((((((ET35*1.2)*0.3))-(((EU35*1.2)*0.3)))+AE35),6) -> 0 | AE35: =ROUND((((EU35*1.2)*0.3)),6) -> 0 | AF35: =ROUND((((EV35*1.2)*0.3)),6) -> 204.1416 | AG35: =ROUND((AP35),6) -> 0 | AH35: =(((EW35*1.2)*0.3)) -> 14.04 | AI35: =(((EX35*1.2)*0.3)) -> 0 | AJ35: =(AS35) -> 0 | AK35: 567.06 | AL35: 0 | AM35: 0 | AN35: 0 | AO35: 567.06 | AP35: 0 | AQ35: 39 | AR35: 0 | AS35: 0 | AT35: 90 | AU35: 46 | AV35: 1.047 | AW35: 1 | AZ35: 1 | BA35: 56.35 | BB35: 1 | BC35: 1 | BH35: 0 | BI35: 2 | BJ35: ТСН-2001.4. Доп. 1-42. Сб. 10, т. 142, поз. 5 | BM35: 68 | BN35: 0 | BO35: 4.10-142-5 | BP35: 1 | BQ35: 40 | BR35: 0 | BS35: 56.35 | BT35: 1 | BU35: 1 | BV35: 1 | BW35: 1 | BX35: 1 | BZ35: 90 | CA35: 46 | CE35: 1566 | CF35: 0 | CG35: 0 | CM35: 0 | CN35: Поправка: Гл.12.Прил.8.п.8. 3_12.00.01.11.001 Наименование: При наличии напряженных и стесненных условий производства работ (стесненность, сложность складирования и транспортной логистики и т.п.) для объектов, расположенных в пределах круговой магистральной системы улиц "Садовое кольцо" города Москвы Поправка: Гл.4.Прил.2.2.п.2.2.29_04.00.01.35.003 Наименование: При демонтаже оборудования, предназначенного в лом | CO35: 0 | CP35: =(P35+Q35+S35) -> 120.59 | CQ35: =ROUND((ROUND((AC35*AW35*1),2)*BC35),2) -> 0 | CR35: =(ROUND((ROUND(((((ET35*1.2)*0.3))*AV35*1),2)*BB35),2)+ROUND((ROUND(((AE35-(((EU35*1.2)*0.3)))*AV35*1),2)*BS35),2)) -> 0 | CS35: =(ROUND((ROUND(((((EU35*1.2)*0.3))*AV35*1),2)*BS35),2)+ROUND((ROUND(((AE35-(((EU35*1.2)*0.3)))*AV35*1),2)*BS35),2)) -> 0 | CT35: =ROUND((ROUND((AF35*AV35*1),2)*BA35),2) -> 12044.25 | CU35: =AG35 -> 0 | CV35: =(AH35*AV35) -> 14.69988 | CW35: =AI35 -> 0 | CX35: =AJ35 -> 0 | CY35: =(ROUND((((S35+ROUND((ROUND(((((EU35*1.2)*0.3))*AV35*1),2)*BS35),2))*AT35)/100),2)+ROUND(((ROUND((ROUND(((AE35-(((EU35*1.2)*0.3)))*AV35*1),2)*BS35),2)*AT35)/100),2)) -> 108.53 | CZ35: =(ROUND((((S35+ROUND((ROUND(((((EU35*1.2)*0.3))*AV35*1),2)*BS35),2))*AU35)/100),2)+ROUND(((ROUND((ROUND(((AE35-(((EU35*1.2)*0.3)))*AV35*1),2)*BS35),2)*AU35)/100),2)) -> 55.47 | DB35: 15 | DD35: *1)*0 | DE35: *1,2)*0,3 | DF35: *1,2)*0,3 | DG35: *1,2)*0,3 | DI35: *1,2)*0,3 | DJ35: *1,2)*0,3 | DN35: 0 | DO35: 0 | DP35: 1 | DQ35: 1 | DU35: 1013 | DV35: 100 номеров | DW35: 100 номеров | DX35: 1 | EE35: 55393700 | EF35: 40 | EG35: Монтаж оборудования | EH35: 0 | EJ35: 2 | EK35: 68 | EL35: ТСН-2001.4-10. Прокладка и монтаж сетей связи | EM35: ТСН-2001.4-10-1 | EO35: Поправка: Гл.12.Прил.8.п.8. 3_12.00.01.11.001 Поправка: Гл.4.Прил.2.2.п.2.2.29_04.00.01.35.003 | EQ35: 0 | ER35: 567.06 | ES35: 0 | ET35: 0 | EU35: 0 | EV35: 567.06 | EW35: 39 | EX35: 0 | EY35: 0 | FQ35: 0 | FR35: 0 | FS35: 0 | FX35: 90 | FY35: 46 | GD35: 1 | GF35: -821238356 | GG35: 2 | GH35: 1 | GI35: 2 | GJ35: 0 | GK35: 0 | GL35: =ROUND(IF(AND(BH35=3,BI35=3,FS35<>0),P35,0),2) -> 0 | GM35: =ROUND(O35+X35+Y35,2)+GX35 -> 284.59 | GN35: =IF(OR(BI35=0,BI35=1),GM35-GX35,0) -> 0 | GO35: =IF(BI35=2,GM35-GX35,0) -> 284.59 | GP35: =IF(BI35=4,GM35-GX35,0) -> 0 | GR35: 0 | GS35: 3 | GT35: 0 | GV35: =ROUND((GT35),6) -> 0 | GW35: 1 | GX35: =ROUND(HC35*I35,2) -> 0 | HA35: 0 | HB35: 0 | HC35: =GV35*GW35 -> 0 | HS35: 0 | IK35: 0
A36: 17 | B36: 1 | C36: =ROW(SmtRes!A53) -> 53 | D36: =ROW(EtalonRes!A66) -> 66 | E36: 5 | F36: 4.10-19-6 | G36: Монтаж отдельно устанавливаемого преобразователя или блока питания / демонтаж ИБП | H36: 1 ШТ. | I36: =ROUND(1+3,9) -> 4 | J36: 0 | K36: =ROUND(1+3,9) -> 4 | O36: =ROUND(CP36,2) -> 273.12 | P36: =ROUND((ROUND((AC36*AW36*I36),2)*BC36),2) -> 0 | Q36: =(ROUND((ROUND(((((ET36*1.2)*0.3))*AV36*I36),2)*BB36),2)+ROUND((ROUND(((AE36-(((EU36*1.2)*0.3)))*AV36*I36),2)*BS36),2)) -> 69.25 | R36: =(ROUND((ROUND(((((EU36*1.2)*0.3))*AV36*I36),2)*BS36),2)+ROUND((ROUND(((AE36-(((EU36*1.2)*0.3)))*AV36*I36),2)*BS36),2)) -> 7.61 | S36: =ROUND((ROUND((AF36*AV36*I36),2)*BA36),2) -> 203.87 | T36: =ROUND(CU36*I36,2) -> 0 | U36: =CV36*I36 -> 14.021424 | V36: =CW36*I36 -> 0 | W36: =ROUND(CX36*I36,2) -> 0 | X36: =(ROUND((((S36+ROUND((ROUND(((((EU36*1.2)*0.3))*AV36*I36),2)*BS36),2))*AT36)/100),2)+ROUND(((ROUND((ROUND(((AE36-(((EU36*1.2)*0.3)))*AV36*I36),2)*BS36),2)*AT36)/100),2)) -> 190.33 | Y36: =(ROUND((((S36+ROUND((ROUND(((((EU36*1.2)*0.3))*AV36*I36),2)*BS36),2))*AU36)/100),2)+ROUND(((ROUND((ROUND(((AE36-(((EU36*1.2)*0.3)))*AV36*I36),2)*BS36),2)*AU36)/100),2)) -> 97.28 | AA36: 55929113 | AB36: =ROUND((AC36+AD36+AF36),6) -> 65.214 | AC36: =ROUND((((ES36*1)*0)),6) -> 0 | AD36: =ROUND((((((ET36*1.2)*0.3))-(((EU36*1.2)*0.3)))+AE36),6) -> 16.5348 | AE36: =ROUND((((EU36*1.2)*0.3)),6) -> 1.818 | AF36: =ROUND((((EV36*1.2)*0.3)),6) -> 48.6792 | AG36: =ROUND((AP36),6) -> 0 | AH36: =(((EW36*1.2)*0.3)) -> 3.348 | AI36: =(((EX36*1.2)*0.3)) -> 0 | AJ36: =(AS36) -> 0 | AK36: 236.95 | AL36: 55.8 | AM36: 45.93 | AN36: 5.05 | AO36: 135.22 | AP36: 0 | AQ36: 9.3 | AR36: 0 | AS36: 0 | AT36: 90 | AU36: 46 | AV36: 1.047 | AW36: 1 | AZ36: 1 | BA36: 1 | BB36: 1 | BC36: 1 | BH36: 0 | BI36: 2 | BJ36: ТСН-2001.4 Доп. 70, Сб. 10, т. 19, поз. 6 | BM36: 68 | BN36: 0 | BO36: 4.10-19-6 | BP36: 1 | BQ36: 40 | BR36: 0 | BS36: 1 | BT36: 1 | BU36: 1 | BV36: 1 | BW36: 1 | BX36: 1 | BZ36: 90 | CA36: 46 | CE36: 1566 | CF36: 0 | CG36: 0 | CM36: 0 | CN36: Поправка: Гл.12.Прил.8.п.8. 3_12.00.01.11.001 Наименование: При наличии напряженных и стесненных условий производства работ (стесненность, сложность складирования и транспортной логистики и т.п.) для объектов, расположенных в пределах круговой магистральной системы улиц "Садовое кольцо" города Москвы Поправка: Гл.4.Прил.2.2.п.2.2.29_04.00.01.35.003 Наименование: При демонтаже оборудования, предназначенного в лом | CO36: 0 | CP36: =(P36+Q36+S36) -> 273.12 | CQ36: =ROUND((ROUND((AC36*AW36*1),2)*BC36),2) -> 0 | CR36: =(ROUND((ROUND(((((ET36*1.2)*0.3))*AV36*1),2)*BB36),2)+ROUND((ROUND(((AE36-(((EU36*1.2)*0.3)))*AV36*1),2)*BS36),2)) -> 17.31 | CS36: =(ROUND((ROUND(((((EU36*1.2)*0.3))*AV36*1),2)*BS36),2)+ROUND((ROUND(((AE36-(((EU36*1.2)*0.3)))*AV36*1),2)*BS36),2)) -> 1.9 | CT36: =ROUND((ROUND((AF36*AV36*1),2)*BA36),2) -> 50.97 | CU36: =AG36 -> 0 | CV36: =(AH36*AV36) -> 3.505356 | CW36: =AI36 -> 0 | CX36: =AJ36 -> 0 | CY36: =(ROUND((((S36+ROUND((ROUND(((((EU36*1.2)*0.3))*AV36*1),2)*BS36),2))*AT36)/100),2)+ROUND(((ROUND((ROUND(((AE36-(((EU36*1.2)*0.3)))*AV36*1),2)*BS36),2)*AT36)/100),2)) -> 185.19 | CZ36: =(ROUND((((S36+ROUND((ROUND(((((EU36*1.2)*0.3))*AV36*1),2)*BS36),2))*AU36)/100),2)+ROUND(((ROUND((ROUND(((AE36-(((EU36*1.2)*0.3)))*AV36*1),2)*BS36),2)*AU36)/100),2)) -> 94.65 | DB36: 17 | DD36: *1)*0 | DE36: *1,2)*0,3 | DF36: *1,2)*0,3 | DG36: *1,2)*0,3 | DI36: *1,2)*0,3 | DJ36: *1,2)*0,3 | DN36: 0 | DO36: 0 | DP36: 1 | DQ36: 1 | DU36: 1013 | DV36: 1 ШТ. | DW36: 1 ШТ. | DX36: 1 | EE36: 55393700 | EF36: 40 | EG36: Монтаж оборудования | EH36: 0 | EJ36: 2 | EK36: 68 | EL36: ТСН-2001.4-10. Прокладка и монтаж сетей связи | EM36: ТСН-2001.4-10-1 | EO36: Поправка: Гл.12.Прил.8.п.8. 3_12.00.01.11.001 Поправка: Гл.4.Прил.2.2.п.2.2.29_04.00.01.35.003 | EQ36: 0 | ER36: 236.95 | ES36: 55.8 | ET36: 45.93 | EU36: 5.05 | EV36: 135.22 | EW36: 9.3 | EX36: 0 | EY36: 0 | FQ36: 0 | FR36: 0 | FS36: 0 | FX36: 90 | FY36: 46 | GD36: 1 | GF36: -1252701960 | GG36: 2 | GH36: 1 | GI36: 2 | GJ36: 0 | GK36: 0 | GL36: =ROUND(IF(AND(BH36=3,BI36=3,FS36<>0),P36,0),2) -> 0 | GM36: =ROUND(O36+X36+Y36,2)+GX36 -> 560.73 | GN36: =IF(OR(BI36=0,BI36=1),GM36-GX36,0) -> 0 | GO36: =IF(BI36=2,GM36-GX36,0) -> 560.73 | GP36: =IF(BI36=4,GM36-GX36,0) -> 0 | GR36: 0 | GS36: 3 | GT36: 0 | GV36: =ROUND((GT36),6) -> 0 | GW36: 1 | GX36: =ROUND(HC36*I36,2) -> 0 | HA36: 0 | HB36: 0 | HC36: =GV36*GW36 -> 0 | HS36: 0 | IK36: 0
A37: 17 | B37: 1 | C37: =ROW(SmtRes!A66) -> 66 | D37: =ROW(EtalonRes!A82) -> 82 | E37: 5 | F37: 4.10-19-6 | G37: Монтаж отдельно устанавливаемого преобразователя или блока питания / демонтаж ИБП | H37: 1 ШТ. | I37: =ROUND(1+3,9) -> 4 | J37: 0 | K37: =ROUND(1+3,9) -> 4 | O37: =ROUND(CP37,2) -> 12607.15 | P37: =ROUND((ROUND((AC37*AW37*I37),2)*BC37),2) -> 0 | Q37: =(ROUND((ROUND(((((ET37*1.2)*0.3))*AV37*I37),2)*BB37),2)+ROUND((ROUND(((AE37-(((EU37*1.2)*0.3)))*AV37*I37),2)*BS37),2)) -> 1119.08 | R37: =(ROUND((ROUND(((((EU37*1.2)*0.3))*AV37*I37),2)*BS37),2)+ROUND((ROUND(((AE37-(((EU37*1.2)*0.3)))*AV37*I37),2)*BS37),2)) -> 428.82 | S37: =ROUND((ROUND((AF37*AV37*I37),2)*BA37),2) -> 11488.07 | T37: =ROUND(CU37*I37,2) -> 0 | U37: =CV37*I37 -> 14.021424 | V37: =CW37*I37 -> 0 | W37: =ROUND(CX37*I37,2) -> 0 | X37: =(ROUND((((S37+ROUND((ROUND(((((EU37*1.2)*0.3))*AV37*I37),2)*BS37),2))*AT37)/100),2)+ROUND(((ROUND((ROUND(((AE37-(((EU37*1.2)*0.3)))*AV37*I37),2)*BS37),2)*AT37)/100),2)) -> 10725.2 | Y37: =(ROUND((((S37+ROUND((ROUND(((((EU37*1.2)*0.3))*AV37*I37),2)*BS37),2))*AU37)/100),2)+ROUND(((ROUND((ROUND(((AE37-(((EU37*1.2)*0.3)))*AV37*I37),2)*BS37),2)*AU37)/100),2)) -> 5481.77 | AA37: 55929115 | AB37: =ROUND((AC37+AD37+AF37),6) -> 65.214 | AC37: =ROUND((((ES37*1)*0)),6) -> 0 | AD37: =ROUND((((((ET37*1.2)*0.3))-(((EU37*1.2)*0.3)))+AE37),6) -> 16.5348 | AE37: =ROUND((((EU37*1.2)*0.3)),6) -> 1.818 | AF37: =ROUND((((EV37*1.2)*0.3)),6) -> 48.6792 | AG37: =ROUND((AP37),6) -> 0 | AH37: =(((EW37*1.2)*0.3)) -> 3.348 | AI37: =(((EX37*1.2)*0.3)) -> 0 | AJ37: =(AS37) -> 0 | AK37: 236.95 | AL37: 55.8 | AM37: 45.93 | AN37: 5.05 | AO37: 135.22 | AP37: 0 | AQ37: 9.3 | AR37: 0 | AS37: 0 | AT37: 90 | AU37: 46 | AV37: 1.047 | AW37: 1 | AZ37: 1 | BA37: 56.35 | BB37: 16.16 | BC37: 10.51 | BH37: 0 | BI37: 2 | BJ37: ТСН-2001.4 Доп. 70, Сб. 10, т. 19, поз. 6 | BM37: 68 | BN37: 0 | BO37: 4.10-19-6 | BP37: 1 | BQ37: 40 | BR37: 0 | BS37: 56.35 | BT37: 1 | BU37: 1 | BV37: 1 | BW37: 1 | BX37: 1 | BZ37: 90 | CA37: 46 | CE37: 1566 | CF37: 0 | CG37: 0 | CM37: 0 | CN37: Поправка: Гл.12.Прил.8.п.8. 3_12.00.01.11.001 Наименование: При наличии напряженных и стесненных условий производства работ (стесненность, сложность складирования и транспортной логистики и т.п.) для объектов, расположенных в пределах круговой магистральной системы улиц "Садовое кольцо" города Москвы Поправка: Гл.4.Прил.2.2.п.2.2.29_04.00.01.35.003 Наименование: При демонтаже оборудования, предназначенного в лом | CO37: 0 | CP37: =(P37+Q37+S37) -> 12607.15 | CQ37: =ROUND((ROUND((AC37*AW37*1),2)*BC37),2) -> 0 | CR37: =(ROUND((ROUND(((((ET37*1.2)*0.3))*AV37*1),2)*BB37),2)+ROUND((ROUND(((AE37-(((EU37*1.2)*0.3)))*AV37*1),2)*BS37),2)) -> 279.73 | CS37: =(ROUND((ROUND(((((EU37*1.2)*0.3))*AV37*1),2)*BS37),2)+ROUND((ROUND(((AE37-(((EU37*1.2)*0.3)))*AV37*1),2)*BS37),2)) -> 107.07 | CT37: =ROUND((ROUND((AF37*AV37*1),2)*BA37),2) -> 2872.16 | CU37: =AG37 -> 0 | CV37: =(AH37*AV37) -> 3.505356 | CW37: =AI37 -> 0 | CX37: =AJ37 -> 0 | CY37: =(ROUND((((S37+ROUND((ROUND(((((EU37*1.2)*0.3))*AV37*1),2)*BS37),2))*AT37)/100),2)+ROUND(((ROUND((ROUND(((AE37-(((EU37*1.2)*0.3)))*AV37*1),2)*BS37),2)*AT37)/100),2)) -> 10435.63 | CZ37: =(ROUND((((S37+ROUND((ROUND(((((EU37*1.2)*0.3))*AV37*1),2)*BS37),2))*AU37)/100),2)+ROUND(((ROUND((ROUND(((AE37-(((EU37*1.2)*0.3)))*AV37*1),2)*BS37),2)*AU37)/100),2)) -> 5333.76 | DB37: 19 | DD37: *1)*0 | DE37: *1,2)*0,3 | DF37: *1,2)*0,3 | DG37: *1,2)*0,3 | DI37: *1,2)*0,3 | DJ37: *1,2)*0,3 | DN37: 0 | DO37: 0 | DP37: 1 | DQ37: 1 | DU37: 1013 | DV37: 1 ШТ. | DW37: 1 ШТ. | DX37: 1 | EE37: 55393700 | EF37: 40 | EG37: Монтаж оборудования | EH37: 0 | EJ37: 2 | EK37: 68 | EL37: ТСН-2001.4-10. Прокладка и монтаж сетей связи | EM37: ТСН-2001.4-10-1 | EO37: Поправка: Гл.12.Прил.8.п.8. 3_12.00.01.11.001 Поправка: Гл.4.Прил.2.2.п.2.2.29_04.00.01.35.003 | EQ37: 0 | ER37: 236.95 | ES37: 55.8 | ET37: 45.93 | EU37: 5.05 | EV37: 135.22 | EW37: 9.3 | EX37: 0 | EY37: 0 | FQ37: 0 | FR37: 0 | FS37: 0 | FX37: 90 | FY37: 46 | GD37: 1 | GF37: -1252701960 | GG37: 2 | GH37: 1 | GI37: 2 | GJ37: 0 | GK37: 0 | GL37: =ROUND(IF(AND(BH37=3,BI37=3,FS37<>0),P37,0),2) -> 0 | GM37: =ROUND(O37+X37+Y37,2)+GX37 -> 28814.12 | GN37: =IF(OR(BI37=0,BI37=1),GM37-GX37,0) -> 0 | GO37: =IF(BI37=2,GM37-GX37,0) -> 28814.12 | GP37: =IF(BI37=4,GM37-GX37,0) -> 0 | GR37: 0 | GS37: 3 | GT37: 0 | GV37: =ROUND((GT37),6) -> 0 | GW37: 1 | GX37: =ROUND(HC37*I37,2) -> 0 | HA37: 0 | HB37: 0 | HC37: =GV37*GW37 -> 0 | HS37: 0 | IK37: 0
A38: 17 | B38: 1 | C38: =ROW(SmtRes!A72) -> 72 | D38: =ROW(EtalonRes!A89) -> 89 | E38: 6 | F38: 4.10-181-4 | G38: Монтаж оптического кросса с учетом измерений на волоконно-оптическом кабеле с числом волокон: 4 / демонтаж оптического кросса | H38: 1 ШТ. | I38: 3 | J38: 0 | K38: 3 | O38: =ROUND(CP38,2) -> 44.71 | P38: =ROUND((ROUND((AC38*AW38*I38),2)*BC38),2) -> 0 | Q38: =(ROUND((ROUND(((((ET38*1.2)*0.3))*AV38*I38),2)*BB38),2)+ROUND((ROUND(((AE38-(((EU38*1.2)*0.3)))*AV38*I38),2)*BS38),2)) -> 2.78 | R38: =(ROUND((ROUND(((((EU38*1.2)*0.3))*AV38*I38),2)*BS38),2)+ROUND((ROUND(((AE38-(((EU38*1.2)*0.3)))*AV38*I38),2)*BS38),2)) -> 0 | S38: =ROUND((ROUND((AF38*AV38*I38),2)*BA38),2) -> 41.93 | T38: =ROUND(CU38*I38,2) -> 0 | U38: =CV38*I38 -> 2.1549132 | V38: =CW38*I38 -> 0 | W38: =ROUND(CX38*I38,2) -> 0 | X38: =(ROUND((((S38+ROUND((ROUND(((((EU38*1.2)*0.3))*AV38*I38),2)*BS38),2))*AT38)/100),2)+ROUND(((ROUND((ROUND(((AE38-(((EU38*1.2)*0.3)))*AV38*I38),2)*BS38),2)*AT38)/100),2)) -> 37.74 | Y38: =(ROUND((((S38+ROUND((ROUND(((((EU38*1.2)*0.3))*AV38*I38),2)*BS38),2))*AU38)/100),2)+ROUND(((ROUND((ROUND(((AE38-(((EU38*1.2)*0.3)))*AV38*I38),2)*BS38),2)*AU38)/100),2)) -> 19.29 | AA38: 55929113 | AB38: =ROUND((AC38+AD38+AF38),6) -> 13.968 | AC38: =ROUND((((ES38*1)*0)),6) -> 0 | AD38: =ROUND((((((ET38*1.2)*0.3))-(((EU38*1.2)*0.3)))+AE38),6) -> 0.8676 | AE38: =ROUND((((EU38*1.2)*0.3)),6) -> 0 | AF38: =ROUND((((EV38*1.2)*0.3)),6) -> 13.1004 | AG38: =ROUND((AP38),6) -> 0 | AH38: =(((EW38*1.2)*0.3)) -> 0.6732 | AI38: =(((EX38*1.2)*0.3)) -> 0 | AJ38: =(AS38) -> 0 | AK38: 40.17 | AL38: 1.37 | AM38: 2.41 | AN38: 0 | AO38: 36.39 | AP38: 0 | AQ38: 1.87 | AR38: 0 | AS38: 0 | AT38: 90 | AU38: 46 | AV38: 1.067 | AW38: 1.081 | AZ38: 1 | BA38: 1 | BB38: 1 | BC38: 1 | BH38: 0 | BI38: 2 | BJ38: ТСН-2001.4 Доп. 79, Сб. 10, т. 181, поз. 4 | BM38: 71 | BN38: 0 | BO38: 4.10-181-4 | BP38: 1 | BQ38: 40 | BR38: 0 | BS38: 1 | BT38: 1 | BU38: 1 | BV38: 1 | BW38: 1 | BX38: 1 | BZ38: 90 | CA38: 46 | CE38: 1566 | CF38: 0 | CG38: 0 | CM38: 0 | CN38: Поправка: Гл.12.Прил.8.п.8. 3_12.00.01.11.001 Наименование: При наличии напряженных и стесненных условий производства работ (стесненность, сложность складирования и транспортной логистики и т.п.) для объектов, расположенных в пределах круговой магистральной системы улиц "Садовое кольцо" города Москвы Поправка: Гл.4.Прил.2.2.п.2.2.29_04.00.01.35.003 Наименование: При демонтаже оборудования, предназначенного в лом | CO38: 0 | CP38: =(P38+Q38+S38) -> 44.71 | CQ38: =ROUND((ROUND((AC38*AW38*1),2)*BC38),2) -> 0 | CR38: =(ROUND((ROUND(((((ET38*1.2)*0.3))*AV38*1),2)*BB38),2)+ROUND((ROUND(((AE38-(((EU38*1.2)*0.3)))*AV38*1),2)*BS38),2)) -> 0.93 | CS38: =(ROUND((ROUND(((((EU38*1.2)*0.3))*AV38*1),2)*BS38),2)+ROUND((ROUND(((AE38-(((EU38*1.2)*0.3)))*AV38*1),2)*BS38),2)) -> 0 | CT38: =ROUND((ROUND((AF38*AV38*1),2)*BA38),2) -> 13.98 | CU38: =AG38 -> 0 | CV38: =(AH38*AV38) -> 0.7183044 | CW38: =AI38 -> 0 | CX38: =AJ38 -> 0 | CY38: =(ROUND((((S38+ROUND((ROUND(((((EU38*1.2)*0.3))*AV38*1),2)*BS38),2))*AT38)/100),2)+ROUND(((ROUND((ROUND(((AE38-(((EU38*1.2)*0.3)))*AV38*1),2)*BS38),2)*AT38)/100),2)) -> 37.74 | CZ38: =(ROUND((((S38+ROUND((ROUND(((((EU38*1.2)*0.3))*AV38*1),2)*BS38),2))*AU38)/100),2)+ROUND(((ROUND((ROUND(((AE38-(((EU38*1.2)*0.3)))*AV38*1),2)*BS38),2)*AU38)/100),2)) -> 19.29 | DB38: 21 | DD38: *1)*0 | DE38: *1,2)*0,3 | DF38: *1,2)*0,3 | DG38: *1,2)*0,3 | DI38: *1,2)*0,3 | DJ38: *1,2)*0,3 | DN38: 0 | DO38: 0 | DP38: 1 | DQ38: 1 | DU38: 1013 | DV38: 1 ШТ. | DW38: 1 ШТ. | DX38: 1 | EE38: 55393703 | EF38: 40 | EG38: Монтаж оборудования | EH38: 0 | EJ38: 2 | EK38: 71 | EL38: ТСН-2001.4-10. Прокладка и монтаж сетей связи/прокладка и монтаж междугородных линий связи | EM38: ТСН-2001.4-10-4 | EO38: Поправка: Гл.12.Прил.8.п.8. 3_12.00.01.11.001 Поправка: Гл.4.Прил.2.2.п.2.2.29_04.00.01.35.003 | EQ38: 0 | ER38: 40.17 | ES38: 1.37 | ET38: 2.41 | EU38: 0 | EV38: 36.39 | EW38: 1.87 | EX38: 0 | EY38: 0 | FQ38: 0 | FR38: 0 | FS38: 2 | FX38: 90 | FY38: 46 | GD38: 1 | GF38: -746104756 | GG38: 2 | GH38: 1 | GI38: 2 | GJ38: 0 | GK38: 0 | GL38: =ROUND(IF(AND(BH38=3,BI38=3,FS38<>0),P38,0),2) -> 0 | GM38: =ROUND(O38+X38+Y38,2)+GX38 -> 101.74 | GN38: =IF(OR(BI38=0,BI38=1),GM38-GX38,0) -> 0 | GO38: =IF(BI38=2,GM38-GX38,0) -> 101.74 | GP38: =IF(BI38=4,GM38-GX38,0) -> 0 | GR38: 0 | GS38: 3 | GT38: 0 | GV38: =ROUND((GT38),6) -> 0 | GW38: 1 | GX38: =ROUND(HC38*I38,2) -> 0 | HA38: 0 | HB38: 0 | HC38: =GV38*GW38 -> 0 | HS38: 0 | IK38: 0
A39: 17 | B39: 1 | C39: =ROW(SmtRes!A78) -> 78 | D39: =ROW(EtalonRes!A96) -> 96 | E39: 6 | F39: 4.10-181-4 | G39: Монтаж оптического кросса с учетом измерений на волоконно-оптическом кабеле с числом волокон: 4 / демонтаж оптического кросса | H39: 1 ШТ. | I39: 3 | J39: 0 | K39: 3 | O39: =ROUND(CP39,2) -> 2388.75 | P39: =ROUND((ROUND((AC39*AW39*I39),2)*BC39),2) -> 0 | Q39: =(ROUND((ROUND(((((ET39*1.2)*0.3))*AV39*I39),2)*BB39),2)+ROUND((ROUND(((AE39-(((EU39*1.2)*0.3)))*AV39*I39),2)*BS39),2)) -> 25.99 | R39: =(ROUND((ROUND(((((EU39*1.2)*0.3))*AV39*I39),2)*BS39),2)+ROUND((ROUND(((AE39-(((EU39*1.2)*0.3)))*AV39*I39),2)*BS39),2)) -> 0 | S39: =ROUND((ROUND((AF39*AV39*I39),2)*BA39),2) -> 2362.76 | T39: =ROUND(CU39*I39,2) -> 0 | U39: =CV39*I39 -> 2.1549132 | V39: =CW39*I39 -> 0 | W39: =ROUND(CX39*I39,2) -> 0 | X39: =(ROUND((((S39+ROUND((ROUND(((((EU39*1.2)*0.3))*AV39*I39),2)*BS39),2))*AT39)/100),2)+ROUND(((ROUND((ROUND(((AE39-(((EU39*1.2)*0.3)))*AV39*I39),2)*BS39),2)*AT39)/100),2)) -> 2126.48 | Y39: =(ROUND((((S39+ROUND((ROUND(((((EU39*1.2)*0.3))*AV39*I39),2)*BS39),2))*AU39)/100),2)+ROUND(((ROUND((ROUND(((AE39-(((EU39*1.2)*0.3)))*AV39*I39),2)*BS39),2)*AU39)/100),2)) -> 1086.87 | AA39: 55929115 | AB39: =ROUND((AC39+AD39+AF39),6) -> 13.968 | AC39: =ROUND((((ES39*1)*0)),6) -> 0 | AD39: =ROUND((((((ET39*1.2)*0.3))-(((EU39*1.2)*0.3)))+AE39),6) -> 0.8676 | AE39: =ROUND((((EU39*1.2)*0.3)),6) -> 0 | AF39: =ROUND((((EV39*1.2)*0.3)),6) -> 13.1004 | AG39: =ROUND((AP39),6) -> 0 | AH39: =(((EW39*1.2)*0.3)) -> 0.6732 | AI39: =(((EX39*1.2)*0.3)) -> 0 | AJ39: =(AS39) -> 0 | AK39: 40.17 | AL39: 1.37 | AM39: 2.41 | AN39: 0 | AO39: 36.39 | AP39: 0 | AQ39: 1.87 | AR39: 0 | AS39: 0 | AT39: 90 | AU39: 46 | AV39: 1.067 | AW39: 1.081 | AZ39: 1 | BA39: 56.35 | BB39: 9.35 | BC39: 15.35 | BH39: 0 | BI39: 2 | BJ39: ТСН-2001.4 Доп. 79, Сб. 10, т. 181, поз. 4 | BM39: 71 | BN39: 0 | BO39: 4.10-181-4 | BP39: 1 | BQ39: 40 | BR39: 0 | BS39: 56.35 | BT39: 1 | BU39: 1 | BV39: 1 | BW39: 1 | BX39: 1 | BZ39: 90 | CA39: 46 | CE39: 1566 | CF39: 0 | CG39: 0 | CM39: 0 | CN39: Поправка: Гл.12.Прил.8.п.8. 3_12.00.01.11.001 Наименование: При наличии напряженных и стесненных условий производства работ (стесненность, сложность складирования и транспортной логистики и т.п.) для объектов, расположенных в пределах круговой магистральной системы улиц "Садовое кольцо" города Москвы Поправка: Гл.4.Прил.2.2.п.2.2.29_04.00.01.35.003 Наименование: При демонтаже оборудования, предназначенного в лом | CO39: 0 | CP39: =(P39+Q39+S39) -> 2388.75 | CQ39: =ROUND((ROUND((AC39*AW39*1),2)*BC39),2) -> 0 | CR39: =(ROUND((ROUND(((((ET39*1.2)*0.3))*AV39*1),2)*BB39),2)+ROUND((ROUND(((AE39-(((EU39*1.2)*0.3)))*AV39*1),2)*BS39),2)) -> 8.7 | CS39: =(ROUND((ROUND(((((EU39*1.2)*0.3))*AV39*1),2)*BS39),2)+ROUND((ROUND(((AE39-(((EU39*1.2)*0.3)))*AV39*1),2)*BS39),2)) -> 0 | CT39: =ROUND((ROUND((AF39*AV39*1),2)*BA39),2) -> 787.77 | CU39: =AG39 -> 0 | CV39: =(AH39*AV39) -> 0.7183044 | CW39: =AI39 -> 0 | CX39: =AJ39 -> 0 | CY39: =(ROUND((((S39+ROUND((ROUND(((((EU39*1.2)*0.3))*AV39*1),2)*BS39),2))*AT39)/100),2)+ROUND(((ROUND((ROUND(((AE39-(((EU39*1.2)*0.3)))*AV39*1),2)*BS39),2)*AT39)/100),2)) -> 2126.48 | CZ39: =(ROUND((((S39+ROUND((ROUND(((((EU39*1.2)*0.3))*AV39*1),2)*BS39),2))*AU39)/100),2)+ROUND(((ROUND((ROUND(((AE39-(((EU39*1.2)*0.3)))*AV39*1),2)*BS39),2)*AU39)/100),2)) -> 1086.87 | DB39: 23 | DD39: *1)*0 | DE39: *1,2)*0,3 | DF39: *1,2)*0,3 | DG39: *1,2)*0,3 | DI39: *1,2)*0,3 | DJ39: *1,2)*0,3 | DN39: 0 | DO39: 0 | DP39: 1 | DQ39: 1 | DU39: 1013 | DV39: 1 ШТ. | DW39: 1 ШТ. | DX39: 1 | EE39: 55393703 | EF39: 40 | EG39: Монтаж оборудования | EH39: 0 | EJ39: 2 | EK39: 71 | EL39: ТСН-2001.4-10. Прокладка и монтаж сетей связи/прокладка и монтаж междугородных линий связи | EM39: ТСН-2001.4-10-4 | EO39: Поправка: Гл.12.Прил.8.п.8. 3_12.00.01.11.001 Поправка: Гл.4.Прил.2.2.п.2.2.29_04.00.01.35.003 | EQ39: 0 | ER39: 40.17 | ES39: 1.37 | ET39: 2.41 | EU39: 0 | EV39: 36.39 | EW39: 1.87 | EX39: 0 | EY39: 0 | FQ39: 0 | FR39: 0 | FS39: 2 | FX39: 90 | FY39: 46 | GD39: 1 | GF39: -746104756 | GG39: 2 | GH39: 1 | GI39: 2 | GJ39: 0 | GK39: 0 | GL39: =ROUND(IF(AND(BH39=3,BI39=3,FS39<>0),P39,0),2) -> 0 | GM39: =ROUND(O39+X39+Y39,2)+GX39 -> 5602.1 | GN39: =IF(OR(BI39=0,BI39=1),GM39-GX39,0) -> 0 | GO39: =IF(BI39=2,GM39-GX39,0) -> 5602.1 | GP39: =IF(BI39=4,GM39-GX39,0) -> 0 | GR39: 0 | GS39: 3 | GT39: 0 | GV39: =ROUND((GT39),6) -> 0 | GW39: 1 | GX39: =ROUND(HC39*I39,2) -> 0 | HA39: 0 | HB39: 0 | HC39: =GV39*GW39 -> 0 | HS39: 0 | IK39: 0
A40: 17 | B40: 1 | C40: =ROW(SmtRes!A83) -> 83 | D40: =ROW(EtalonRes!A102) -> 102 | E40: 7 | F40: 4.10-32-2 | G40: Монтаж стойки, полустойки, каркаса стойки или шкафа массой до 300 кг / демонтаж шкафов | H40: 1 ШТ. | I40: =ROUND(1+4,9) -> 5 | J40: 0 | K40: =ROUND(1+4,9) -> 5 | O40: =ROUND(CP40,2) -> 401.51 | P40: =ROUND((ROUND((AC40*AW40*I40),2)*BC40),2) -> 0 | Q40: =(ROUND((ROUND(((((ET40*1.2)*0.3))*AV40*I40),2)*BB40),2)+ROUND((ROUND(((AE40-(((EU40*1.2)*0.3)))*AV40*I40),2)*BS40),2)) -> 119.18 | R40: =(ROUND((ROUND(((((EU40*1.2)*0.3))*AV40*I40),2)*BS40),2)+ROUND((ROUND(((AE40-(((EU40*1.2)*0.3)))*AV40*I40),2)*BS40),2)) -> 12.83 | S40: =ROUND((ROUND((AF40*AV40*I40),2)*BA40),2) -> 282.33 | T40: =ROUND(CU40*I40,2) -> 0 | U40: =CV40*I40 -> 25.25364 | V40: =CW40*I40 -> 0 | W40: =ROUND(CX40*I40,2) -> 0 | X40: =(ROUND((((S40+ROUND((ROUND(((((EU40*1.2)*0.3))*AV40*I40),2)*BS40),2))*AT40)/100),2)+ROUND(((ROUND((ROUND(((AE40-(((EU40*1.2)*0.3)))*AV40*I40),2)*BS40),2)*AT40)/100),2)) -> 265.64 | Y40: =(ROUND((((S40+ROUND((ROUND(((((EU40*1.2)*0.3))*AV40*I40),2)*BS40),2))*AU40)/100),2)+ROUND(((ROUND((ROUND(((AE40-(((EU40*1.2)*0.3)))*AV40*I40),2)*BS40),2)*AU40)/100),2)) -> 135.77 | AA40: 55929113 | AB40: =ROUND((AC40+AD40+AF40),6) -> 76.698 | AC40: =ROUND((((ES40*1)*0)),6) -> 0 | AD40: =ROUND((((((ET40*1.2)*0.3))-(((EU40*1.2)*0.3)))+AE40),6) -> 22.7664 | AE40: =ROUND((((EU40*1.2)*0.3)),6) -> 2.4516 | AF40: =ROUND((((EV40*1.2)*0.3)),6) -> 53.9316 | AG40: =ROUND((AP40),6) -> 0 | AH40: =(((EW40*1.2)*0.3)) -> 4.824 | AI40: =(((EX40*1.2)*0.3)) -> 0 | AJ40: =(AS40) -> 0 | AK40: 216.97 | AL40: 3.92 | AM40: 63.24 | AN40: 6.81 | AO40: 149.81 | AP40: 0 | AQ40: 13.4 | AR40: 0 | AS40: 0 | AT40: 90 | AU40: 46 | AV40: 1.047 | AW40: 1 | AZ40: 1 | BA40: 1 | BB40: 1 | BC40: 1 | BH40: 0 | BI40: 2 | BJ40: ТСН-2001.4 Доп. 80, Сб. 10, т. 32, поз. 2 | BM40: 68 | BN40: 0 | BO40: 4.10-32-2 | BP40: 1 | BQ40: 40 | BR40: 0 | BS40: 1 | BT40: 1 | BU40: 1 | BV40: 1 | BW40: 1 | BX40: 1 | BZ40: 90 | CA40: 46 | CE40: 1566 | CF40: 0 | CG40: 0 | CM40: 0 | CN40: Поправка: Гл.12.Прил.8.п.8. 3_12.00.01.11.001 Наименование: При наличии напряженных и стесненных условий производства работ (стесненность, сложность складирования и транспортной логистики и т.п.) для объектов, расположенных в пределах круговой магистральной системы улиц "Садовое кольцо" города Москвы Поправка: Гл.4.Прил.2.2.п.2.2.29_04.00.01.35.003 Наименование: При демонтаже оборудования, предназначенного в лом | CO40: 0 | CP40: =(P40+Q40+S40) -> 401.51 | CQ40: =ROUND((ROUND((AC40*AW40*1),2)*BC40),2) -> 0 | CR40: =(ROUND((ROUND(((((ET40*1.2)*0.3))*AV40*1),2)*BB40),2)+ROUND((ROUND(((AE40-(((EU40*1.2)*0.3)))*AV40*1),2)*BS40),2)) -> 23.84 | CS40: =(ROUND((ROUND(((((EU40*1.2)*0.3))*AV40*1),2)*BS40),2)+ROUND((ROUND(((AE40-(((EU40*1.2)*0.3)))*AV40*1),2)*BS40),2)) -> 2.57 | CT40: =ROUND((ROUND((AF40*AV40*1),2)*BA40),2) -> 56.47 | CU40: =AG40 -> 0 | CV40: =(AH40*AV40) -> 5.050728 | CW40: =AI40 -> 0 | CX40: =AJ40 -> 0 | CY40: =(ROUND((((S40+ROUND((ROUND(((((EU40*1.2)*0.3))*AV40*1),2)*BS40),2))*AT40)/100),2)+ROUND(((ROUND((ROUND(((AE40-(((EU40*1.2)*0.3)))*AV40*1),2)*BS40),2)*AT40)/100),2)) -> 256.41 | CZ40: =(ROUND((((S40+ROUND((ROUND(((((EU40*1.2)*0.3))*AV40*1),2)*BS40),2))*AU40)/100),2)+ROUND(((ROUND((ROUND(((AE40-(((EU40*1.2)*0.3)))*AV40*1),2)*BS40),2)*AU40)/100),2)) -> 131.05 | DB40: 25 | DD40: *1)*0 | DE40: *1,2)*0,3 | DF40: *1,2)*0,3 | DG40: *1,2)*0,3 | DI40: *1,2)*0,3 | DJ40: *1,2)*0,3 | DN40: 0 | DO40: 0 | DP40: 1 | DQ40: 1 | DU40: 1013 | DV40: 1 ШТ. | DW40: 1 ШТ. | DX40: 1 | EE40: 55393700 | EF40: 40 | EG40: Монтаж оборудования | EH40: 0 | EJ40: 2 | EK40: 68 | EL40: ТСН-2001.4-10. Прокладка и монтаж сетей связи | EM40: ТСН-2001.4-10-1 | EO40: Поправка: Гл.12.Прил.8.п.8. 3_12.00.01.11.001 Поправка: Гл.4.Прил.2.2.п.2.2.29_04.00.01.35.003 | EQ40: 0 | ER40: 216.97 | ES40: 3.92 | ET40: 63.24 | EU40: 6.81 | EV40: 149.81 | EW40: 13.4 | EX40: 0 | EY40: 0 | FQ40: 0 | FR40: 0 | FS40: 0 | FX40: 90 | FY40: 46 | GD40: 1 | GF40: -1476025260 | GG40: 2 | GH40: 1 | GI40: 2 | GJ40: 0 | GK40: 0 | GL40: =ROUND(IF(AND(BH40=3,BI40=3,FS40<>0),P40,0),2) -> 0 | GM40: =ROUND(O40+X40+Y40,2)+GX40 -> 802.92 | GN40: =IF(OR(BI40=0,BI40=1),GM40-GX40,0) -> 0 | GO40: =IF(BI40=2,GM40-GX40,0) -> 802.92 | GP40: =IF(BI40=4,GM40-GX40,0) -> 0 | GR40: 0 | GS40: 3 | GT40: 0 | GV40: =ROUND((GT40),6) -> 0 | GW40: 1 | GX40: =ROUND(HC40*I40,2) -> 0 | HA40: 0 | HB40: 0 | HC40: =GV40*GW40 -> 0 | HS40: 0 | IK40: 0
A41: 17 | B41: 1 | C41: =ROW(SmtRes!A88) -> 88 | D41: =ROW(EtalonRes!A108) -> 108 | E41: 7 | F41: 4.10-32-2 | G41: Монтаж стойки, полустойки, каркаса стойки или шкафа массой до 300 кг / демонтаж шкафов | H41: 1 ШТ. | I41: =ROUND(1+4,9) -> 5 | J41: 0 | K41: =ROUND(1+4,9) -> 5 | O41: =ROUND(CP41,2) -> 17820.95 | P41: =ROUND((ROUND((AC41*AW41*I41),2)*BC41),2) -> 0 | Q41: =(ROUND((ROUND(((((ET41*1.2)*0.3))*AV41*I41),2)*BB41),2)+ROUND((ROUND(((AE41-(((EU41*1.2)*0.3)))*AV41*I41),2)*BS41),2)) -> 1911.65 | R41: =(ROUND((ROUND(((((EU41*1.2)*0.3))*AV41*I41),2)*BS41),2)+ROUND((ROUND(((AE41-(((EU41*1.2)*0.3)))*AV41*I41),2)*BS41),2)) -> 722.97 | S41: =ROUND((ROUND((AF41*AV41*I41),2)*BA41),2) -> 15909.3 | T41: =ROUND(CU41*I41,2) -> 0 | U41: =CV41*I41 -> 25.25364 | V41: =CW41*I41 -> 0 | W41: =ROUND(CX41*I41,2) -> 0 | X41: =(ROUND((((S41+ROUND((ROUND(((((EU41*1.2)*0.3))*AV41*I41),2)*BS41),2))*AT41)/100),2)+ROUND(((ROUND((ROUND(((AE41-(((EU41*1.2)*0.3)))*AV41*I41),2)*BS41),2)*AT41)/100),2)) -> 14969.04 | Y41: =(ROUND((((S41+ROUND((ROUND(((((EU41*1.2)*0.3))*AV41*I41),2)*BS41),2))*AU41)/100),2)+ROUND(((ROUND((ROUND(((AE41-(((EU41*1.2)*0.3)))*AV41*I41),2)*BS41),2)*AU41)/100),2)) -> 7650.84 | AA41: 55929115 | AB41: =ROUND((AC41+AD41+AF41),6) -> 76.698 | AC41: =ROUND((((ES41*1)*0)),6) -> 0 | AD41: =ROUND((((((ET41*1.2)*0.3))-(((EU41*1.2)*0.3)))+AE41),6) -> 22.7664 | AE41: =ROUND((((EU41*1.2)*0.3)),6) -> 2.4516 | AF41: =ROUND((((EV41*1.2)*0.3)),6) -> 53.9316 | AG41: =ROUND((AP41),6) -> 0 | AH41: =(((EW41*1.2)*0.3)) -> 4.824 | AI41: =(((EX41*1.2)*0.3)) -> 0 | AJ41: =(AS41) -> 0 | AK41: 216.97 | AL41: 3.92 | AM41: 63.24 | AN41: 6.81 | AO41: 149.81 | AP41: 0 | AQ41: 13.4 | AR41: 0 | AS41: 0 | AT41: 90 | AU41: 46 | AV41: 1.047 | AW41: 1 | AZ41: 1 | BA41: 56.35 | BB41: 16.04 | BC41: 7.12 | BH41: 0 | BI41: 2 | BJ41: ТСН-2001.4 Доп. 80, Сб. 10, т. 32, поз. 2 | BM41: 68 | BN41: 0 | BO41: 4.10-32-2 | BP41: 1 | BQ41: 40 | BR41: 0 | BS41: 56.35 | BT41: 1 | BU41: 1 | BV41: 1 | BW41: 1 | BX41: 1 | BZ41: 90 | CA41: 46 | CE41: 1566 | CF41: 0 | CG41: 0 | CM41: 0 | CN41: Поправка: Гл.12.Прил.8.п.8. 3_12.00.01.11.001 Наименование: При наличии напряженных и стесненных условий производства работ (стесненность, сложность складирования и транспортной логистики и т.п.) для объектов, расположенных в пределах круговой магистральной системы улиц "Садовое кольцо" города Москвы Поправка: Гл.4.Прил.2.2.п.2.2.29_04.00.01.35.003 Наименование: При демонтаже оборудования, предназначенного в лом | CO41: 0 | CP41: =(P41+Q41+S41) -> 17820.95 | CQ41: =ROUND((ROUND((AC41*AW41*1),2)*BC41),2) -> 0 | CR41: =(ROUND((ROUND(((((ET41*1.2)*0.3))*AV41*1),2)*BB41),2)+ROUND((ROUND(((AE41-(((EU41*1.2)*0.3)))*AV41*1),2)*BS41),2)) -> 382.39 | CS41: =(ROUND((ROUND(((((EU41*1.2)*0.3))*AV41*1),2)*BS41),2)+ROUND((ROUND(((AE41-(((EU41*1.2)*0.3)))*AV41*1),2)*BS41),2)) -> 144.82 | CT41: =ROUND((ROUND((AF41*AV41*1),2)*BA41),2) -> 3182.08 | CU41: =AG41 -> 0 | CV41: =(AH41*AV41) -> 5.050728 | CW41: =AI41 -> 0 | CX41: =AJ41 -> 0 | CY41: =(ROUND((((S41+ROUND((ROUND(((((EU41*1.2)*0.3))*AV41*1),2)*BS41),2))*AT41)/100),2)+ROUND(((ROUND((ROUND(((AE41-(((EU41*1.2)*0.3)))*AV41*1),2)*BS41),2)*AT41)/100),2)) -> 14448.71 | CZ41: =(ROUND((((S41+ROUND((ROUND(((((EU41*1.2)*0.3))*AV41*1),2)*BS41),2))*AU41)/100),2)+ROUND(((ROUND((ROUND(((AE41-(((EU41*1.2)*0.3)))*AV41*1),2)*BS41),2)*AU41)/100),2)) -> 7384.9 | DB41: 27 | DD41: *1)*0 | DE41: *1,2)*0,3 | DF41: *1,2)*0,3 | DG41: *1,2)*0,3 | DI41: *1,2)*0,3 | DJ41: *1,2)*0,3 | DN41: 0 | DO41: 0 | DP41: 1 | DQ41: 1 | DU41: 1013 | DV41: 1 ШТ. | DW41: 1 ШТ. | DX41: 1 | EE41: 55393700 | EF41: 40 | EG41: Монтаж оборудования | EH41: 0 | EJ41: 2 | EK41: 68 | EL41: ТСН-2001.4-10. Прокладка и монтаж сетей связи | EM41: ТСН-2001.4-10-1 | EO41: Поправка: Гл.12.Прил.8.п.8. 3_12.00.01.11.001 Поправка: Гл.4.Прил.2.2.п.2.2.29_04.00.01.35.003 | EQ41: 0 | ER41: 216.97 | ES41: 3.92 | ET41: 63.24 | EU41: 6.81 | EV41: 149.81 | EW41: 13.4 | EX41: 0 | EY41: 0 | FQ41: 0 | FR41: 0 | FS41: 0 | FX41: 90 | FY41: 46 | GD41: 1 | GF41: -1476025260 | GG41: 2 | GH41: 1 | GI41: 2 | GJ41: 0 | GK41: 0 | GL41: =ROUND(IF(AND(BH41=3,BI41=3,FS41<>0),P41,0),2) -> 0 | GM41: =ROUND(O41+X41+Y41,2)+GX41 -> 40440.83 | GN41: =IF(OR(BI41=0,BI41=1),GM41-GX41,0) -> 0 | GO41: =IF(BI41=2,GM41-GX41,0) -> 40440.83 | GP41: =IF(BI41=4,GM41-GX41,0) -> 0 | GR41: 0 | GS41: 3 | GT41: 0 | GV41: =ROUND((GT41),6) -> 0 | GW41: 1 | GX41: =ROUND(HC41*I41,2) -> 0 | HA41: 0 | HB41: 0 | HC41: =GV41*GW41 -> 0 | HS41: 0 | IK41: 0
A42: 17 | B42: 1 | C42: =ROW(SmtRes!A89) -> 89 | D42: =ROW(EtalonRes!A109) -> 109 | E42: 8 | F42: 6.67-7-1 | G42: Демонтаж осветительных приборов, выключатели, розетки | H42: 100 шт. | I42: =ROUND((51+43+128)/100,9) -> 2.22 | J42: 0 | K42: =ROUND((51+43+128)/100,9) -> 2.22 | O42: =ROUND(CP42,2) -> 166.46 | P42: =ROUND((ROUND((AC42*AW42*I42),2)*BC42),2) -> 0 | Q42: =(ROUND((ROUND((((ET42*1.2))*AV42*I42),2)*BB42),2)+ROUND((ROUND(((AE42-((EU42*1.2)))*AV42*I42),2)*BS42),2)) -> 0 | R42: =(ROUND((ROUND((((EU42*1.2))*AV42*I42),2)*BS42),2)+ROUND((ROUND(((AE42-((EU42*1.2)))*AV42*I42),2)*BS42),2)) -> 0 | S42: =ROUND((ROUND((AF42*AV42*I42),2)*BA42),2) -> 166.46 | T42: =ROUND(CU42*I42,2) -> 0 | U42: =CV42*I42 -> 16.288975 | V42: =CW42*I42 -> 0 | W42: =ROUND(CX42*I42,2) -> 0 | X42: =(ROUND((((S42+ROUND((ROUND((((EU42*1.2))*AV42*I42),2)*BS42),2))*AT42)/100),2)+ROUND(((ROUND((ROUND(((AE42-((EU42*1.2)))*AV42*I42),2)*BS42),2)*AT42)/100),2)) -> 151.48 | Y42: =(ROUND((((S42+ROUND((ROUND((((EU42*1.2))*AV42*I42),2)*BS42),2))*AU42)/100),2)+ROUND(((ROUND((ROUND(((AE42-((EU42*1.2)))*AV42*I42),2)*BS42),2)*AU42)/100),2)) -> 79.9 | AA42: 55929113 | AB42: =ROUND((AC42+AD42+AF42),6) -> 71.616 | AC42: =ROUND(((ES42*1)),6) -> 0 | AD42: =ROUND(((((ET42*1.2))-((EU42*1.2)))+AE42),6) -> 0 | AE42: =ROUND(((EU42*1.2)),6) -> 0 | AF42: =ROUND(((EV42*1.2)),6) -> 71.616 | AG42: =ROUND((AP42),6) -> 0 | AH42: =((EW42*1.2)) -> 7.008 | AI42: =((EX42*1.2)) -> 0 | AJ42: =(AS42) -> 0 | AK42: 59.68 | AL42: 0 | AM42: 0 | AN42: 0 | AO42: 59.68 | AP42: 0 | AQ42: 5.84 | AR42: 0 | AS42: 0 | AT42: 91 | AU42: 48 | AV42: 1.047 | AW42: 1 | AZ42: 1 | BA42: 1 | BB42: 1 | BC42: 1 | BH42: 0 | BI42: 1 | BJ42: ТСН-2001.6. Доп. 1-42. Сб. 67, т. 7, поз. 1 | BM42: 106 | BN42: 0 | BO42: 6.67-7-1 | BP42: 1 | BQ42: 60 | BR42: 0 | BS42: 1 | BT42: 1 | BU42: 1 | BV42: 1 | BW42: 1 | BX42: 1 | BZ42: 91 | CA42: 48 | CE42: 1566 | CF42: 0 | CG42: 0 | CM42: 0 | CN42: Поправка: Гл.12.Прил.8.п.8. 3_12.00.01.11.001 Наименование: При наличии напряженных и стесненных условий производства работ (стесненность, сложность складирования и транспортной логистики и т.п.) для объектов, расположенных в пределах круговой магистральной системы улиц "Садовое кольцо" города Москвы | CO42: 0 | CP42: =(P42+Q42+S42) -> 166.46 | CQ42: =ROUND((ROUND((AC42*AW42*1),2)*BC42),2) -> 0 | CR42: =(ROUND((ROUND((((ET42*1.2))*AV42*1),2)*BB42),2)+ROUND((ROUND(((AE42-((EU42*1.2)))*AV42*1),2)*BS42),2)) -> 0 | CS42: =(ROUND((ROUND((((EU42*1.2))*AV42*1),2)*BS42),2)+ROUND((ROUND(((AE42-((EU42*1.2)))*AV42*1),2)*BS42),2)) -> 0 | CT42: =ROUND((ROUND((AF42*AV42*1),2)*BA42),2) -> 74.98 | CU42: =AG42 -> 0 | CV42: =(AH42*AV42) -> 7.337376 | CW42: =AI42 -> 0 | CX42: =AJ42 -> 0 | CY42: =(ROUND((((S42+ROUND((ROUND((((EU42*1.2))*AV42*1),2)*BS42),2))*AT42)/100),2)+ROUND(((ROUND((ROUND(((AE42-((EU42*1.2)))*AV42*1),2)*BS42),2)*AT42)/100),2)) -> 151.48 | CZ42: =(ROUND((((S42+ROUND((ROUND((((EU42*1.2))*AV42*1),2)*BS42),2))*AU42)/100),2)+ROUND(((ROUND((ROUND(((AE42-((EU42*1.2)))*AV42*1),2)*BS42),2)*AU42)/100),2)) -> 79.9 | DB42: 29 | DD42: *1 | DE42: *1,2 | DF42: *1,2 | DG42: *1,2 | DI42: *1,2 | DJ42: *1,2 | DN42: 0 | DO42: 0 | DP42: 1 | DQ42: 1 | DU42: 1010 | DV42: 100 шт. | DW42: 100 шт. | DX42: 100 | EE42: 55393738 | EF42: 60 | EG42: Ремонтно-строительные работы | EH42: 0 | EJ42: 1 | EK42: 106 | EL42: ТСН-2001.6-67. Электромонтажные работы | EM42: ТСН-2001.6-67-1 | EO42: Поправка: Гл.12.Прил.8.п.8. 3_12.00.01.11.001 | EQ42: 0 | ER42: 59.68 | ES42: 0 | ET42: 0 | EU42: 0 | EV42: 59.68 | EW42: 5.84 | EX42: 0 | EY42: 0 | FQ42: 0 | FR42: 0 | FS42: 0 | FX42: 91 | FY42: 48 | GD42: 1 | GF42: 1478850760 | GG42: 2 | GH42: 1 | GI42: 2 | GJ42: 0 | GK42: 0 | GL42: =ROUND(IF(AND(BH42=3,BI42=3,FS42<>0),P42,0),2) -> 0 | GM42: =ROUND(O42+X42+Y42,2)+GX42 -> 397.84 | GN42: =IF(OR(BI42=0,BI42=1),GM42-GX42,0) -> 397.84 | GO42: =IF(BI42=2,GM42-GX42,0) -> 0 | GP42: =IF(BI42=4,GM42-GX42,0) -> 0 | GR42: 0 | GS42: 3 | GT42: 0 | GV42: =ROUND((GT42),6) -> 0 | GW42: 1 | GX42: =ROUND(HC42*I42,2) -> 0 | HA42: 0 | HB42: 0 | HC42: =GV42*GW42 -> 0 | HS42: 0 | IK42: 0
A43: 17 | B43: 1 | C43: =ROW(SmtRes!A90) -> 90 | D43: =ROW(EtalonRes!A110) -> 110 | E43: 8 | F43: 6.67-7-1 | G43: Демонтаж осветительных приборов, выключатели, розетки | H43: 100 шт. | I43: =ROUND((51+43+128)/100,9) -> 2.22 | J43: 0 | K43: =ROUND((51+43+128)/100,9) -> 2.22 | O43: =ROUND(CP43,2) -> 9380.02 | P43: =ROUND((ROUND((AC43*AW43*I43),2)*BC43),2) -> 0 | Q43: =(ROUND((ROUND((((ET43*1.2))*AV43*I43),2)*BB43),2)+ROUND((ROUND(((AE43-((EU43*1.2)))*AV43*I43),2)*BS43),2)) -> 0 | R43: =(ROUND((ROUND((((EU43*1.2))*AV43*I43),2)*BS43),2)+ROUND((ROUND(((AE43-((EU43*1.2)))*AV43*I43),2)*BS43),2)) -> 0 | S43: =ROUND((ROUND((AF43*AV43*I43),2)*BA43),2) -> 9380.02 | T43: =ROUND(CU43*I43,2) -> 0 | U43: =CV43*I43 -> 16.288975 | V43: =CW43*I43 -> 0 | W43: =ROUND(CX43*I43,2) -> 0 | X43: =(ROUND((((S43+ROUND((ROUND((((EU43*1.2))*AV43*I43),2)*BS43),2))*AT43)/100),2)+ROUND(((ROUND((ROUND(((AE43-((EU43*1.2)))*AV43*I43),2)*BS43),2)*AT43)/100),2)) -> 8535.82 | Y43: =(ROUND((((S43+ROUND((ROUND((((EU43*1.2))*AV43*I43),2)*BS43),2))*AU43)/100),2)+ROUND(((ROUND((ROUND(((AE43-((EU43*1.2)))*AV43*I43),2)*BS43),2)*AU43)/100),2)) -> 4502.41 | AA43: 55929115 | AB43: =ROUND((AC43+AD43+AF43),6) -> 71.616 | AC43: =ROUND(((ES43*1)),6) -> 0 | AD43: =ROUND(((((ET43*1.2))-((EU43*1.2)))+AE43),6) -> 0 | AE43: =ROUND(((EU43*1.2)),6) -> 0 | AF43: =ROUND(((EV43*1.2)),6) -> 71.616 | AG43: =ROUND((AP43),6) -> 0 | AH43: =((EW43*1.2)) -> 7.008 | AI43: =((EX43*1.2)) -> 0 | AJ43: =(AS43) -> 0 | AK43: 59.68 | AL43: 0 | AM43: 0 | AN43: 0 | AO43: 59.68 | AP43: 0 | AQ43: 5.84 | AR43: 0 | AS43: 0 | AT43: 91 | AU43: 48 | AV43: 1.047 | AW43: 1 | AZ43: 1 | BA43: 56.35 | BB43: 1 | BC43: 1 | BH43: 0 | BI43: 1 | BJ43: ТСН-2001.6. Доп. 1-42. Сб. 67, т. 7, поз. 1 | BM43: 106 | BN43: 0 | BO43: 6.67-7-1 | BP43: 1 | BQ43: 60 | BR43: 0 | BS43: 56.35 | BT43: 1 | BU43: 1 | BV43: 1 | BW43: 1 | BX43: 1 | BZ43: 91 | CA43: 48 | CE43: 1566 | CF43: 0 | CG43: 0 | CM43: 0 | CN43: Поправка: Гл.12.Прил.8.п.8. 3_12.00.01.11.001 Наименование: При наличии напряженных и стесненных условий производства работ (стесненность, сложность складирования и транспортной логистики и т.п.) для объектов, расположенных в пределах круговой магистральной системы улиц "Садовое кольцо" города Москвы | CO43: 0 | CP43: =(P43+Q43+S43) -> 9380.02 | CQ43: =ROUND((ROUND((AC43*AW43*1),2)*BC43),2) -> 0 | CR43: =(ROUND((ROUND((((ET43*1.2))*AV43*1),2)*BB43),2)+ROUND((ROUND(((AE43-((EU43*1.2)))*AV43*1),2)*BS43),2)) -> 0 | CS43: =(ROUND((ROUND((((EU43*1.2))*AV43*1),2)*BS43),2)+ROUND((ROUND(((AE43-((EU43*1.2)))*AV43*1),2)*BS43),2)) -> 0 | CT43: =ROUND((ROUND((AF43*AV43*1),2)*BA43),2) -> 4225.12 | CU43: =AG43 -> 0 | CV43: =(AH43*AV43) -> 7.337376 | CW43: =AI43 -> 0 | CX43: =AJ43 -> 0 | CY43: =(ROUND((((S43+ROUND((ROUND((((EU43*1.2))*AV43*1),2)*BS43),2))*AT43)/100),2)+ROUND(((ROUND((ROUND(((AE43-((EU43*1.2)))*AV43*1),2)*BS43),2)*AT43)/100),2)) -> 8535.82 | CZ43: =(ROUND((((S43+ROUND((ROUND((((EU43*1.2))*AV43*1),2)*BS43),2))*AU43)/100),2)+ROUND(((ROUND((ROUND(((AE43-((EU43*1.2)))*AV43*1),2)*BS43),2)*AU43)/100),2)) -> 4502.41 | DB43: 30 | DD43: *1 | DE43: *1,2 | DF43: *1,2 | DG43: *1,2 | DI43: *1,2 | DJ43: *1,2 | DN43: 0 | DO43: 0 | DP43: 1 | DQ43: 1 | DU43: 1010 | DV43: 100 шт. | DW43: 100 шт. | DX43: 100 | EE43: 55393738 | EF43: 60 | EG43: Ремонтно-строительные работы | EH43: 0 | EJ43: 1 | EK43: 106 | EL43: ТСН-2001.6-67. Электромонтажные работы | EM43: ТСН-2001.6-67-1 | EO43: Поправка: Гл.12.Прил.8.п.8. 3_12.00.01.11.001 | EQ43: 0 | ER43: 59.68 | ES43: 0 | ET43: 0 | EU43: 0 | EV43: 59.68 | EW43: 5.84 | EX43: 0 | EY43: 0 | FQ43: 0 | FR43: 0 | FS43: 0 | FX43: 91 | FY43: 48 | GD43: 1 | GF43: 1478850760 | GG43: 2 | GH43: 1 | GI43: 2 | GJ43: 0 | GK43: 0 | GL43: =ROUND(IF(AND(BH43=3,BI43=3,FS43<>0),P43,0),2) -> 0 | GM43: =ROUND(O43+X43+Y43,2)+GX43 -> 22418.25 | GN43: =IF(OR(BI43=0,BI43=1),GM43-GX43,0) -> 22418.25 | GO43: =IF(BI43=2,GM43-GX43,0) -> 0 | GP43: =IF(BI43=4,GM43-GX43,0) -> 0 | GR43: 0 | GS43: 3 | GT43: 0 | GV43: =ROUND((GT43),6) -> 0 | GW43: 1 | GX43: =ROUND(HC43*I43,2) -> 0 | HA43: 0 | HB43: 0 | HC43: =GV43*GW43 -> 0 | HS43: 0 | IK43: 0
A44: 17 | B44: 1 | C44: =ROW(SmtRes!A96) -> 96 | D44: =ROW(EtalonRes!A117) -> 117 | E44: 9 | F44: 4.8-332-1 | G44: Монтаж установочной коробки скрытого типа / демонтаж коробок | H44: 100 шт. | I44: =ROUND(94/100,9) -> 0.94 | J44: 0 | K44: =ROUND(94/100,9) -> 0.94 | O44: =ROUND(CP44,2) -> 127.18 | P44: =ROUND((ROUND((AC44*AW44*I44),2)*BC44),2) -> 0 | Q44: =(ROUND((ROUND(((((ET44*1.2)*0.3))*AV44*I44),2)*BB44),2)+ROUND((ROUND(((AE44-(((EU44*1.2)*0.3)))*AV44*I44),2)*BS44),2)) -> 5.37 | R44: =(ROUND((ROUND(((((EU44*1.2)*0.3))*AV44*I44),2)*BS44),2)+ROUND((ROUND(((AE44-(((EU44*1.2)*0.3)))*AV44*I44),2)*BS44),2)) -> 0.05 | S44: =ROUND((ROUND((AF44*AV44*I44),2)*BA44),2) -> 121.81 | T44: =ROUND(CU44*I44,2) -> 0 | U44: =CV44*I44 -> 10.894873 | V44: =CW44*I44 -> 0 | W44: =ROUND(CX44*I44,2) -> 0 | X44: =(ROUND((((S44+ROUND((ROUND(((((EU44*1.2)*0.3))*AV44*I44),2)*BS44),2))*AT44)/100),2)+ROUND(((ROUND((ROUND(((AE44-(((EU44*1.2)*0.3)))*AV44*I44),2)*BS44),2)*AT44)/100),2)) -> 118.2 | Y44: =(ROUND((((S44+ROUND((ROUND(((((EU44*1.2)*0.3))*AV44*I44),2)*BS44),2))*AU44)/100),2)+ROUND(((ROUND((ROUND(((AE44-(((EU44*1.2)*0.3)))*AV44*I44),2)*BS44),2)*AU44)/100),2)) -> 62.15 | AA44: 55929113 | AB44: =ROUND((AC44+AD44+AF44),6) -> 129.2328 | AC44: =ROUND((((ES44*1)*0)),6) -> 0 | AD44: =ROUND((((((ET44*1.2)*0.3))-(((EU44*1.2)*0.3)))+AE44),6) -> 5.4612 | AE44: =ROUND((((EU44*1.2)*0.3)),6) -> 0.0468 | AF44: =ROUND((((EV44*1.2)*0.3)),6) -> 123.7716 | AG44: =ROUND((AP44),6) -> 0 | AH44: =(((EW44*1.2)*0.3)) -> 11.07 | AI44: =(((EX44*1.2)*0.3)) -> 0 | AJ44: =(AS44) -> 0 | AK44: 1892.95 | AL44: 1533.97 | AM44: 15.17 | AN44: 0.13 | AO44: 343.81 | AP44: 0 | AQ44: 30.75 | AR44: 0 | AS44: 0 | AT44: 97 | AU44: 51 | AV44: 1.047 | AW44: 1 | AZ44: 1 | BA44: 1 | BB44: 1 | BC44: 1 | BH44: 0 | BI44: 2 | BJ44: ТСН-2001.4 Доп. 81, Сб. 8, т. 332, поз. 1 | BM44: 67 | BN44: 0 | BO44: 4.8-332-1 | BP44: 1 | BQ44: 40 | BR44: 0 | BS44: 1 | BT44: 1 | BU44: 1 | BV44: 1 | BW44: 1 | BX44: 1 | BZ44: 97 | CA44: 51 | CE44: 1566 | CF44: 0 | CG44: 0 | CM44: 0 | CN44: Поправка: Гл.12.Прил.8.п.8. 3_12.00.01.11.001 Наименование: При наличии напряженных и стесненных условий производства работ (стесненность, сложность складирования и транспортной логистики и т.п.) для объектов, расположенных в пределах круговой магистральной системы улиц "Садовое кольцо" города Москвы Поправка: Гл.4.Прил.2.2.п.2.2.29_04.00.01.35.003 Наименование: При демонтаже оборудования, предназначенного в лом | CO44: 0 | CP44: =(P44+Q44+S44) -> 127.18 | CQ44: =ROUND((ROUND((AC44*AW44*1),2)*BC44),2) -> 0 | CR44: =(ROUND((ROUND(((((ET44*1.2)*0.3))*AV44*1),2)*BB44),2)+ROUND((ROUND(((AE44-(((EU44*1.2)*0.3)))*AV44*1),2)*BS44),2)) -> 5.72 | CS44: =(ROUND((ROUND(((((EU44*1.2)*0.3))*AV44*1),2)*BS44),2)+ROUND((ROUND(((AE44-(((EU44*1.2)*0.3)))*AV44*1),2)*BS44),2)) -> 0.05 | CT44: =ROUND((ROUND((AF44*AV44*1),2)*BA44),2) -> 129.59 | CU44: =AG44 -> 0 | CV44: =(AH44*AV44) -> 11.59029 | CW44: =AI44 -> 0 | CX44: =AJ44 -> 0 | CY44: =(ROUND((((S44+ROUND((ROUND(((((EU44*1.2)*0.3))*AV44*1),2)*BS44),2))*AT44)/100),2)+ROUND(((ROUND((ROUND(((AE44-(((EU44*1.2)*0.3)))*AV44*1),2)*BS44),2)*AT44)/100),2)) -> 118.2 | CZ44: =(ROUND((((S44+ROUND((ROUND(((((EU44*1.2)*0.3))*AV44*1),2)*BS44),2))*AU44)/100),2)+ROUND(((ROUND((ROUND(((AE44-(((EU44*1.2)*0.3)))*AV44*1),2)*BS44),2)*AU44)/100),2)) -> 62.15 | DB44: 31 | DD44: *1)*0 | DE44: *1,2)*0,3 | DF44: *1,2)*0,3 | DG44: *1,2)*0,3 | DI44: *1,2)*0,3 | DJ44: *1,2)*0,3 | DN44: 0 | DO44: 0 | DP44: 1 | DQ44: 1 | DU44: 1010 | DV44: 100 шт. | DW44: 100 шт. | DX44: 100 | EE44: 55393699 | EF44: 40 | EG44: Монтаж оборудования | EH44: 0 | EJ44: 2 | EK44: 67 | EL44: ТСН-2001.4-8. Электротехнические установки | EM44: ТСН-2001.4-8-1 | EO44: Поправка: Гл.12.Прил.8.п.8. 3_12.00.01.11.001 Поправка: Гл.4.Прил.2.2.п.2.2.29_04.00.01.35.003 | EQ44: 0 | ER44: 1892.95 | ES44: 1533.97 | ET44: 15.17 | EU44: 0.13 | EV44: 343.81 | EW44: 30.75 | EX44: 0 | EY44: 0 | FQ44: 0 | FR44: 0 | FS44: 0 | FX44: 97 | FY44: 51 | GD44: 1 | GF44: -602613933 | GG44: 2 | GH44: 1 | GI44: 2 | GJ44: 0 | GK44: 0 | GL44: =ROUND(IF(AND(BH44=3,BI44=3,FS44<>0),P44,0),2) -> 0 | GM44: =ROUND(O44+X44+Y44,2)+GX44 -> 307.53 | GN44: =IF(OR(BI44=0,BI44=1),GM44-GX44,0) -> 0 | GO44: =IF(BI44=2,GM44-GX44,0) -> 307.53 | GP44: =IF(BI44=4,GM44-GX44,0) -> 0 | GR44: 0 | GS44: 3 | GT44: 0 | GV44: =ROUND((GT44),6) -> 0 | GW44: 1 | GX44: =ROUND(HC44*I44,2) -> 0 | HA44: 0 | HB44: 0 | HC44: =GV44*GW44 -> 0 | HS44: 0 | IK44: 0
A45: 17 | B45: 1 | C45: =ROW(SmtRes!A102) -> 102 | D45: =ROW(EtalonRes!A124) -> 124 | E45: 9 | F45: 4.8-332-1 | G45: Монтаж установочной коробки скрытого типа / демонтаж коробок | H45: 100 шт. | I45: =ROUND(94/100,9) -> 0.94 | J45: 0 | K45: =ROUND(94/100,9) -> 0.94 | O45: =ROUND(CP45,2) -> 6917.53 | P45: =ROUND((ROUND((AC45*AW45*I45),2)*BC45),2) -> 0 | Q45: =(ROUND((ROUND(((((ET45*1.2)*0.3))*AV45*I45),2)*BB45),2)+ROUND((ROUND(((AE45-(((EU45*1.2)*0.3)))*AV45*I45),2)*BS45),2)) -> 53.54 | R45: =(ROUND((ROUND(((((EU45*1.2)*0.3))*AV45*I45),2)*BS45),2)+ROUND((ROUND(((AE45-(((EU45*1.2)*0.3)))*AV45*I45),2)*BS45),2)) -> 2.82 | S45: =ROUND((ROUND((AF45*AV45*I45),2)*BA45),2) -> 6863.99 | T45: =ROUND(CU45*I45,2) -> 0 | U45: =CV45*I45 -> 10.894873 | V45: =CW45*I45 -> 0 | W45: =ROUND(CX45*I45,2) -> 0 | X45: =(ROUND((((S45+ROUND((ROUND(((((EU45*1.2)*0.3))*AV45*I45),2)*BS45),2))*AT45)/100),2)+ROUND(((ROUND((ROUND(((AE45-(((EU45*1.2)*0.3)))*AV45*I45),2)*BS45),2)*AT45)/100),2)) -> 6660.81 | Y45: =(ROUND((((S45+ROUND((ROUND(((((EU45*1.2)*0.3))*AV45*I45),2)*BS45),2))*AU45)/100),2)+ROUND(((ROUND((ROUND(((AE45-(((EU45*1.2)*0.3)))*AV45*I45),2)*BS45),2)*AU45)/100),2)) -> 3502.07 | AA45: 55929115 | AB45: =ROUND((AC45+AD45+AF45),6) -> 129.2328 | AC45: =ROUND((((ES45*1)*0)),6) -> 0 | AD45: =ROUND((((((ET45*1.2)*0.3))-(((EU45*1.2)*0.3)))+AE45),6) -> 5.4612 | AE45: =ROUND((((EU45*1.2)*0.3)),6) -> 0.0468 | AF45: =ROUND((((EV45*1.2)*0.3)),6) -> 123.7716 | AG45: =ROUND((AP45),6) -> 0 | AH45: =(((EW45*1.2)*0.3)) -> 11.07 | AI45: =(((EX45*1.2)*0.3)) -> 0 | AJ45: =(AS45) -> 0 | AK45: 1892.95 | AL45: 1533.97 | AM45: 15.17 | AN45: 0.13 | AO45: 343.81 | AP45: 0 | AQ45: 30.75 | AR45: 0 | AS45: 0 | AT45: 97 | AU45: 51 | AV45: 1.047 | AW45: 1 | AZ45: 1 | BA45: 56.35 | BB45: 9.97 | BC45: 2.84 | BH45: 0 | BI45: 2 | BJ45: ТСН-2001.4 Доп. 81, Сб. 8, т. 332, поз. 1 | BM45: 67 | BN45: 0 | BO45: 4.8-332-1 | BP45: 1 | BQ45: 40 | BR45: 0 | BS45: 56.35 | BT45: 1 | BU45: 1 | BV45: 1 | BW45: 1 | BX45: 1 | BZ45: 97 | CA45: 51 | CE45: 1566 | CF45: 0 | CG45: 0 | CM45: 0 | CN45: Поправка: Гл.12.Прил.8.п.8. 3_12.00.01.11.001 Наименование: При наличии напряженных и стесненных условий производства работ (стесненность, сложность складирования и транспортной логистики и т.п.) для объектов, расположенных в пределах круговой магистральной системы улиц "Садовое кольцо" города Москвы Поправка: Гл.4.Прил.2.2.п.2.2.29_04.00.01.35.003 Наименование: При демонтаже оборудования, предназначенного в лом | CO45: 0 | CP45: =(P45+Q45+S45) -> 6917.53 | CQ45: =ROUND((ROUND((AC45*AW45*1),2)*BC45),2) -> 0 | CR45: =(ROUND((ROUND(((((ET45*1.2)*0.3))*AV45*1),2)*BB45),2)+ROUND((ROUND(((AE45-(((EU45*1.2)*0.3)))*AV45*1),2)*BS45),2)) -> 57.03 | CS45: =(ROUND((ROUND(((((EU45*1.2)*0.3))*AV45*1),2)*BS45),2)+ROUND((ROUND(((AE45-(((EU45*1.2)*0.3)))*AV45*1),2)*BS45),2)) -> 2.82 | CT45: =ROUND((ROUND((AF45*AV45*1),2)*BA45),2) -> 7302.4 | CU45: =AG45 -> 0 | CV45: =(AH45*AV45) -> 11.59029 | CW45: =AI45 -> 0 | CX45: =AJ45 -> 0 | CY45: =(ROUND((((S45+ROUND((ROUND(((((EU45*1.2)*0.3))*AV45*1),2)*BS45),2))*AT45)/100),2)+ROUND(((ROUND((ROUND(((AE45-(((EU45*1.2)*0.3)))*AV45*1),2)*BS45),2)*AT45)/100),2)) -> 6660.81 | CZ45: =(ROUND((((S45+ROUND((ROUND(((((EU45*1.2)*0.3))*AV45*1),2)*BS45),2))*AU45)/100),2)+ROUND(((ROUND((ROUND(((AE45-(((EU45*1.2)*0.3)))*AV45*1),2)*BS45),2)*AU45)/100),2)) -> 3502.07 | DB45: 33 | DD45: *1)*0 | DE45: *1,2)*0,3 | DF45: *1,2)*0,3 | DG45: *1,2)*0,3 | DI45: *1,2)*0,3 | DJ45: *1,2)*0,3 | DN45: 0 | DO45: 0 | DP45: 1 | DQ45: 1 | DU45: 1010 | DV45: 100 шт. | DW45: 100 шт. | DX45: 100 | EE45: 55393699 | EF45: 40 | EG45: Монтаж оборудования | EH45: 0 | EJ45: 2 | EK45: 67 | EL45: ТСН-2001.4-8. Электротехнические установки | EM45: ТСН-2001.4-8-1 | EO45: Поправка: Гл.12.Прил.8.п.8. 3_12.00.01.11.001 Поправка: Гл.4.Прил.2.2.п.2.2.29_04.00.01.35.003 | EQ45: 0 | ER45: 1892.95 | ES45: 1533.97 | ET45: 15.17 | EU45: 0.13 | EV45: 343.81 | EW45: 30.75 | EX45: 0 | EY45: 0 | FQ45: 0 | FR45: 0 | FS45: 0 | FX45: 97 | FY45: 51 | GD45: 1 | GF45: -602613933 | GG45: 2 | GH45: 1 | GI45: 2 | GJ45: 0 | GK45: 0 | GL45: =ROUND(IF(AND(BH45=3,BI45=3,FS45<>0),P45,0),2) -> 0 | GM45: =ROUND(O45+X45+Y45,2)+GX45 -> 17080.41 | GN45: =IF(OR(BI45=0,BI45=1),GM45-GX45,0) -> 0 | GO45: =IF(BI45=2,GM45-GX45,0) -> 17080.41 | GP45: =IF(BI45=4,GM45-GX45,0) -> 0 | GR45: 0 | GS45: 3 | GT45: 0 | GV45: =ROUND((GT45),6) -> 0 | GW45: 1 | GX45: =ROUND(HC45*I45,2) -> 0 | HA45: 0 | HB45: 0 | HC45: =GV45*GW45 -> 0 | HS45: 0 | IK45: 0
A46: 17 | B46: 1 | C46: =ROW(SmtRes!A108) -> 108 | D46: =ROW(EtalonRes!A131) -> 131 | E46: 10 | F46: 4.10-174-1 | G46: Монтаж внутренней камеры видеонаблюдения / демонтаж | H46: 10 шт. | I46: =ROUND(4/10,9) -> 0.4 | J46: 0 | K46: =ROUND(4/10,9) -> 0.4 | O46: =ROUND(CP46,2) -> 37.66 | P46: =ROUND((ROUND((AC46*AW46*I46),2)*BC46),2) -> 0 | Q46: =(ROUND((ROUND(((((ET46*1.2)*0.3))*AV46*I46),2)*BB46),2)+ROUND((ROUND(((AE46-(((EU46*1.2)*0.3)))*AV46*I46),2)*BS46),2)) -> 0.36 | R46: =(ROUND((ROUND(((((EU46*1.2)*0.3))*AV46*I46),2)*BS46),2)+ROUND((ROUND(((AE46-(((EU46*1.2)*0.3)))*AV46*I46),2)*BS46),2)) -> 0.02 | S46: =ROUND((ROUND((AF46*AV46*I46),2)*BA46),2) -> 37.3 | T46: =ROUND(CU46*I46,2) -> 0 | U46: =CV46*I46 -> 2.3429347 | V46: =CW46*I46 -> 0 | W46: =ROUND(CX46*I46,2) -> 0 | X46: =(ROUND((((S46+ROUND((ROUND(((((EU46*1.2)*0.3))*AV46*I46),2)*BS46),2))*AT46)/100),2)+ROUND(((ROUND((ROUND(((AE46-(((EU46*1.2)*0.3)))*AV46*I46),2)*BS46),2)*AT46)/100),2)) -> 33.59 | Y46: =(ROUND((((S46+ROUND((ROUND(((((EU46*1.2)*0.3))*AV46*I46),2)*BS46),2))*AU46)/100),2)+ROUND(((ROUND((ROUND(((AE46-(((EU46*1.2)*0.3)))*AV46*I46),2)*BS46),2)*AU46)/100),2)) -> 17.17 | AA46: 55929113 | AB46: =ROUND((AC46+AD46+AF46),6) -> 89.9208 | AC46: =ROUND((((ES46*1)*0)),6) -> 0 | AD46: =ROUND((((((ET46*1.2)*0.3))-(((EU46*1.2)*0.3)))+AE46),6) -> 0.8496 | AE46: =ROUND((((EU46*1.2)*0.3)),6) -> 0.0468 | AF46: =ROUND((((EV46*1.2)*0.3)),6) -> 89.0712 | AG46: =ROUND((AP46),6) -> 0 | AH46: =(((EW46*1.2)*0.3)) -> 5.5944 | AI46: =(((EX46*1.2)*0.3)) -> 0 | AJ46: =(AS46) -> 0 | AK46: 292.29 | AL46: 42.51 | AM46: 2.36 | AN46: 0.13 | AO46: 247.42 | AP46: 0 | AQ46: 15.54 | AR46: 0 | AS46: 0 | AT46: 90 | AU46: 46 | AV46: 1.047 | AW46: 1 | AZ46: 1 | BA46: 1 | BB46: 1 | BC46: 1 | BH46: 0 | BI46: 2 | BJ46: ТСН-2001.4 Доп. 68, Сб. 10, т. 174, поз. 1 | BM46: 68 | BN46: 0 | BO46: 4.10-174-1 | BP46: 1 | BQ46: 40 | BR46: 0 | BS46: 1 | BT46: 1 | BU46: 1 | BV46: 1 | BW46: 1 | BX46: 1 | BZ46: 90 | CA46: 46 | CE46: 1566 | CF46: 0 | CG46: 0 | CM46: 0 | CN46: Поправка: Гл.12.Прил.8.п.8. 3_12.00.01.11.001 Наименование: При наличии напряженных и стесненных условий производства работ (стесненность, сложность складирования и транспортной логистики и т.п.) для объектов, расположенных в пределах круговой магистральной системы улиц "Садовое кольцо" города Москвы Поправка: Гл.4.Прил.2.2.п.2.2.29_04.00.01.35.003 Наименование: При демонтаже оборудования, предназначенного в лом | CO46: 0 | CP46: =(P46+Q46+S46) -> 37.66 | CQ46: =ROUND((ROUND((AC46*AW46*1),2)*BC46),2) -> 0 | CR46: =(ROUND((ROUND(((((ET46*1.2)*0.3))*AV46*1),2)*BB46),2)+ROUND((ROUND(((AE46-(((EU46*1.2)*0.3)))*AV46*1),2)*BS46),2)) -> 0.89 | CS46: =(ROUND((ROUND(((((EU46*1.2)*0.3))*AV46*1),2)*BS46),2)+ROUND((ROUND(((AE46-(((EU46*1.2)*0.3)))*AV46*1),2)*BS46),2)) -> 0.05 | CT46: =ROUND((ROUND((AF46*AV46*1),2)*BA46),2) -> 93.26 | CU46: =AG46 -> 0 | CV46: =(AH46*AV46) -> 5.8573368 | CW46: =AI46 -> 0 | CX46: =AJ46 -> 0 | CY46: =(ROUND((((S46+ROUND((ROUND(((((EU46*1.2)*0.3))*AV46*1),2)*BS46),2))*AT46)/100),2)+ROUND(((ROUND((ROUND(((AE46-(((EU46*1.2)*0.3)))*AV46*1),2)*BS46),2)*AT46)/100),2)) -> 33.62 | CZ46: =(ROUND((((S46+ROUND((ROUND(((((EU46*1.2)*0.3))*AV46*1),2)*BS46),2))*AU46)/100),2)+ROUND(((ROUND((ROUND(((AE46-(((EU46*1.2)*0.3)))*AV46*1),2)*BS46),2)*AU46)/100),2)) -> 17.18 | DB46: 35 | DD46: *1)*0 | DE46: *1,2)*0,3 | DF46: *1,2)*0,3 | DG46: *1,2)*0,3 | DI46: *1,2)*0,3 | DJ46: *1,2)*0,3 | DN46: 0 | DO46: 0 | DP46: 1 | DQ46: 1 | DU46: 1010 | DV46: 10 шт. | DW46: 10 шт. | DX46: 10 | EE46: 55393700 | EF46: 40 | EG46: Монтаж оборудования | EH46: 0 | EJ46: 2 | EK46: 68 | EL46: ТСН-2001.4-10. Прокладка и монтаж сетей связи | EM46: ТСН-2001.4-10-1 | EO46: Поправка: Гл.12.Прил.8.п.8. 3_12.00.01.11.001 Поправка: Гл.4.Прил.2.2.п.2.2.29_04.00.01.35.003 | EQ46: 0 | ER46: 292.29 | ES46: 42.51 | ET46: 2.36 | EU46: 0.13 | EV46: 247.42 | EW46: 15.54 | EX46: 0 | EY46: 0 | FQ46: 0 | FR46: 0 | FS46: 0 | FX46: 90 | FY46: 46 | GD46: 1 | GF46: 1698093513 | GG46: 2 | GH46: 1 | GI46: 2 | GJ46: 0 | GK46: 0 | GL46: =ROUND(IF(AND(BH46=3,BI46=3,FS46<>0),P46,0),2) -> 0 | GM46: =ROUND(O46+X46+Y46,2)+GX46 -> 88.42 | GN46: =IF(OR(BI46=0,BI46=1),GM46-GX46,0) -> 0 | GO46: =IF(BI46=2,GM46-GX46,0) -> 88.42 | GP46: =IF(BI46=4,GM46-GX46,0) -> 0 | GR46: 0 | GS46: 3 | GT46: 0 | GV46: =ROUND((GT46),6) -> 0 | GW46: 1 | GX46: =ROUND(HC46*I46,2) -> 0 | HA46: 0 | HB46: 0 | HC46: =GV46*GW46 -> 0 | HS46: 0 | IK46: 0
A47: 17 | B47: 1 | C47: =ROW(SmtRes!A114) -> 114 | D47: =ROW(EtalonRes!A138) -> 138 | E47: 10 | F47: 4.10-174-1 | G47: Монтаж внутренней камеры видеонаблюдения / демонтаж | H47: 10 шт. | I47: =ROUND(4/10,9) -> 0.4 | J47: 0 | K47: =ROUND(4/10,9) -> 0.4 | O47: =ROUND(CP47,2) -> 2106.26 | P47: =ROUND((ROUND((AC47*AW47*I47),2)*BC47),2) -> 0 | Q47: =(ROUND((ROUND(((((ET47*1.2)*0.3))*AV47*I47),2)*BB47),2)+ROUND((ROUND(((AE47-(((EU47*1.2)*0.3)))*AV47*I47),2)*BS47),2)) -> 4.4 | R47: =(ROUND((ROUND(((((EU47*1.2)*0.3))*AV47*I47),2)*BS47),2)+ROUND((ROUND(((AE47-(((EU47*1.2)*0.3)))*AV47*I47),2)*BS47),2)) -> 1.13 | S47: =ROUND((ROUND((AF47*AV47*I47),2)*BA47),2) -> 2101.86 | T47: =ROUND(CU47*I47,2) -> 0 | U47: =CV47*I47 -> 2.3429347 | V47: =CW47*I47 -> 0 | W47: =ROUND(CX47*I47,2) -> 0 | X47: =(ROUND((((S47+ROUND((ROUND(((((EU47*1.2)*0.3))*AV47*I47),2)*BS47),2))*AT47)/100),2)+ROUND(((ROUND((ROUND(((AE47-(((EU47*1.2)*0.3)))*AV47*I47),2)*BS47),2)*AT47)/100),2)) -> 1892.69 | Y47: =(ROUND((((S47+ROUND((ROUND(((((EU47*1.2)*0.3))*AV47*I47),2)*BS47),2))*AU47)/100),2)+ROUND(((ROUND((ROUND(((AE47-(((EU47*1.2)*0.3)))*AV47*I47),2)*BS47),2)*AU47)/100),2)) -> 967.38 | AA47: 55929115 | AB47: =ROUND((AC47+AD47+AF47),6) -> 89.9208 | AC47: =ROUND((((ES47*1)*0)),6) -> 0 | AD47: =ROUND((((((ET47*1.2)*0.3))-(((EU47*1.2)*0.3)))+AE47),6) -> 0.8496 | AE47: =ROUND((((EU47*1.2)*0.3)),6) -> 0.0468 | AF47: =ROUND((((EV47*1.2)*0.3)),6) -> 89.0712 | AG47: =ROUND((AP47),6) -> 0 | AH47: =(((EW47*1.2)*0.3)) -> 5.5944 | AI47: =(((EX47*1.2)*0.3)) -> 0 | AJ47: =(AS47) -> 0 | AK47: 292.29 | AL47: 42.51 | AM47: 2.36 | AN47: 0.13 | AO47: 247.42 | AP47: 0 | AQ47: 15.54 | AR47: 0 | AS47: 0 | AT47: 90 | AU47: 46 | AV47: 1.047 | AW47: 1 | AZ47: 1 | BA47: 56.35 | BB47: 12.21 | BC47: 1.84 | BH47: 0 | BI47: 2 | BJ47: ТСН-2001.4 Доп. 68, Сб. 10, т. 174, поз. 1 | BM47: 68 | BN47: 0 | BO47: 4.10-174-1 | BP47: 1 | BQ47: 40 | BR47: 0 | BS47: 56.35 | BT47: 1 | BU47: 1 | BV47: 1 | BW47: 1 | BX47: 1 | BZ47: 90 | CA47: 46 | CE47: 1566 | CF47: 0 | CG47: 0 | CM47: 0 | CN47: Поправка: Гл.12.Прил.8.п.8. 3_12.00.01.11.001 Наименование: При наличии напряженных и стесненных условий производства работ (стесненность, сложность складирования и транспортной логистики и т.п.) для объектов, расположенных в пределах круговой магистральной системы улиц "Садовое кольцо" города Москвы Поправка: Гл.4.Прил.2.2.п.2.2.29_04.00.01.35.003 Наименование: При демонтаже оборудования, предназначенного в лом | CO47: 0 | CP47: =(P47+Q47+S47) -> 2106.26 | CQ47: =ROUND((ROUND((AC47*AW47*1),2)*BC47),2) -> 0 | CR47: =(ROUND((ROUND(((((ET47*1.2)*0.3))*AV47*1),2)*BB47),2)+ROUND((ROUND(((AE47-(((EU47*1.2)*0.3)))*AV47*1),2)*BS47),2)) -> 10.87 | CS47: =(ROUND((ROUND(((((EU47*1.2)*0.3))*AV47*1),2)*BS47),2)+ROUND((ROUND(((AE47-(((EU47*1.2)*0.3)))*AV47*1),2)*BS47),2)) -> 2.82 | CT47: =ROUND((ROUND((AF47*AV47*1),2)*BA47),2) -> 5255.2 | CU47: =AG47 -> 0 | CV47: =(AH47*AV47) -> 5.8573368 | CW47: =AI47 -> 0 | CX47: =AJ47 -> 0 | CY47: =(ROUND((((S47+ROUND((ROUND(((((EU47*1.2)*0.3))*AV47*1),2)*BS47),2))*AT47)/100),2)+ROUND(((ROUND((ROUND(((AE47-(((EU47*1.2)*0.3)))*AV47*1),2)*BS47),2)*AT47)/100),2)) -> 1894.21 | CZ47: =(ROUND((((S47+ROUND((ROUND(((((EU47*1.2)*0.3))*AV47*1),2)*BS47),2))*AU47)/100),2)+ROUND(((ROUND((ROUND(((AE47-(((EU47*1.2)*0.3)))*AV47*1),2)*BS47),2)*AU47)/100),2)) -> 968.15 | DB47: 37 | DD47: *1)*0 | DE47: *1,2)*0,3 | DF47: *1,2)*0,3 | DG47: *1,2)*0,3 | DI47: *1,2)*0,3 | DJ47: *1,2)*0,3 | DN47: 0 | DO47: 0 | DP47: 1 | DQ47: 1 | DU47: 1010 | DV47: 10 шт. | DW47: 10 шт. | DX47: 10 | EE47: 55393700 | EF47: 40 | EG47: Монтаж оборудования | EH47: 0 | EJ47: 2 | EK47: 68 | EL47: ТСН-2001.4-10. Прокладка и монтаж сетей связи | EM47: ТСН-2001.4-10-1 | EO47: Поправка: Гл.12.Прил.8.п.8. 3_12.00.01.11.001 Поправка: Гл.4.Прил.2.2.п.2.2.29_04.00.01.35.003 | EQ47: 0 | ER47: 292.29 | ES47: 42.51 | ET47: 2.36 | EU47: 0.13 | EV47: 247.42 | EW47: 15.54 | EX47: 0 | EY47: 0 | FQ47: 0 | FR47: 0 | FS47: 0 | FX47: 90 | FY47: 46 | GD47: 1 | GF47: 1698093513 | GG47: 2 | GH47: 1 | GI47: 2 | GJ47: 0 | GK47: 0 | GL47: =ROUND(IF(AND(BH47=3,BI47=3,FS47<>0),P47,0),2) -> 0 | GM47: =ROUND(O47+X47+Y47,2)+GX47 -> 4966.33 | GN47: =IF(OR(BI47=0,BI47=1),GM47-GX47,0) -> 0 | GO47: =IF(BI47=2,GM47-GX47,0) -> 4966.33 | GP47: =IF(BI47=4,GM47-GX47,0) -> 0 | GR47: 0 | GS47: 3 | GT47: 0 | GV47: =ROUND((GT47),6) -> 0 | GW47: 1 | GX47: =ROUND(HC47*I47,2) -> 0 | HA47: 0 | HB47: 0 | HC47: =GV47*GW47 -> 0 | HS47: 0 | IK47: 0
A48: 17 | B48: 1 | C48: =ROW(SmtRes!A115) -> 115 | D48: =ROW(EtalonRes!A139) -> 139 | E48: 11 | F48: 6.67-6-1 | G48: Демонтаж кабеля | H48: 100 м | I48: =ROUND((26500+150+100)/100,9) -> 267.5 | J48: 0 | K48: =ROUND((26500+150+100)/100,9) -> 267.5 | O48: =ROUND(CP48,2) -> 33111.29 | P48: =ROUND((ROUND((AC48*AW48*I48),2)*BC48),2) -> 0 | Q48: =(ROUND((ROUND((((ET48*1.2))*AV48*I48),2)*BB48),2)+ROUND((ROUND(((AE48-((EU48*1.2)))*AV48*I48),2)*BS48),2)) -> 0 | R48: =(ROUND((ROUND((((EU48*1.2))*AV48*I48),2)*BS48),2)+ROUND((ROUND(((AE48-((EU48*1.2)))*AV48*I48),2)*BS48),2)) -> 0 | S48: =ROUND((ROUND((AF48*AV48*I48),2)*BA48),2) -> 33111.29 | T48: =ROUND(CU48*I48,2) -> 0 | U48: =CV48*I48 -> 3239.8787 | V48: =CW48*I48 -> 0 | W48: =ROUND(CX48*I48,2) -> 0 | X48: =(ROUND((((S48+ROUND((ROUND((((EU48*1.2))*AV48*I48),2)*BS48),2))*AT48)/100),2)+ROUND(((ROUND((ROUND(((AE48-((EU48*1.2)))*AV48*I48),2)*BS48),2)*AT48)/100),2)) -> 30131.27 | Y48: =(ROUND((((S48+ROUND((ROUND((((EU48*1.2))*AV48*I48),2)*BS48),2))*AU48)/100),2)+ROUND(((ROUND((ROUND(((AE48-((EU48*1.2)))*AV48*I48),2)*BS48),2)*AU48)/100),2)) -> 15893.42 | AA48: 55929113 | AB48: =ROUND((AC48+AD48+AF48),6) -> 118.224 | AC48: =ROUND(((ES48*1)),6) -> 0 | AD48: =ROUND(((((ET48*1.2))-((EU48*1.2)))+AE48),6) -> 0 | AE48: =ROUND(((EU48*1.2)),6) -> 0 | AF48: =ROUND(((EV48*1.2)),6) -> 118.224 | AG48: =ROUND((AP48),6) -> 0 | AH48: =((EW48*1.2)) -> 11.568 | AI48: =((EX48*1.2)) -> 0 | AJ48: =(AS48) -> 0 | AK48: 98.52 | AL48: 0 | AM48: 0 | AN48: 0 | AO48: 98.52 | AP48: 0 | AQ48: 9.64 | AR48: 0 | AS48: 0 | AT48: 91 | AU48: 48 | AV48: 1.047 | AW48: 1 | AZ48: 1 | BA48: 1 | BB48: 1 | BC48: 1 | BH48: 0 | BI48: 1 | BJ48: ТСН-2001.6. Доп. 1-42. Сб. 67, т. 6, поз. 1 | BM48: 106 | BN48: 0 | BO48: 6.67-6-1 | BP48: 1 | BQ48: 60 | BR48: 0 | BS48: 1 | BT48: 1 | BU48: 1 | BV48: 1 | BW48: 1 | BX48: 1 | BZ48: 91 | CA48: 48 | CE48: 1566 | CF48: 0 | CG48: 0 | CM48: 0 | CN48: Поправка: Гл.12.Прил.8.п.8. 3_12.00.01.11.001 Наименование: При наличии напряженных и стесненных условий производства работ (стесненность, сложность складирования и транспортной логистики и т.п.) для объектов, расположенных в пределах круговой магистральной системы улиц "Садовое кольцо" города Москвы | CO48: 0 | CP48: =(P48+Q48+S48) -> 33111.29 | CQ48: =ROUND((ROUND((AC48*AW48*1),2)*BC48),2) -> 0 | CR48: =(ROUND((ROUND((((ET48*1.2))*AV48*1),2)*BB48),2)+ROUND((ROUND(((AE48-((EU48*1.2)))*AV48*1),2)*BS48),2)) -> 0 | CS48: =(ROUND((ROUND((((EU48*1.2))*AV48*1),2)*BS48),2)+ROUND((ROUND(((AE48-((EU48*1.2)))*AV48*1),2)*BS48),2)) -> 0 | CT48: =ROUND((ROUND((AF48*AV48*1),2)*BA48),2) -> 123.78 | CU48: =AG48 -> 0 | CV48: =(AH48*AV48) -> 12.111696 | CW48: =AI48 -> 0 | CX48: =AJ48 -> 0 | CY48: =(ROUND((((S48+ROUND((ROUND((((EU48*1.2))*AV48*1),2)*BS48),2))*AT48)/100),2)+ROUND(((ROUND((ROUND(((AE48-((EU48*1.2)))*AV48*1),2)*BS48),2)*AT48)/100),2)) -> 30131.27 | CZ48: =(ROUND((((S48+ROUND((ROUND((((EU48*1.2))*AV48*1),2)*BS48),2))*AU48)/100),2)+ROUND(((ROUND((ROUND(((AE48-((EU48*1.2)))*AV48*1),2)*BS48),2)*AU48)/100),2)) -> 15893.42 | DB48: 39 | DD48: *1 | DE48: *1,2 | DF48: *1,2 | DG48: *1,2 | DI48: *1,2 | DJ48: *1,2 | DN48: 0 | DO48: 0 | DP48: 1 | DQ48: 1 | DU48: 1003 | DV48: 100 м | DW48: 100 м | DX48: 100 | EE48: 55393738 | EF48: 60 | EG48: Ремонтно-строительные работы | EH48: 0 | EJ48: 1 | EK48: 106 | EL48: ТСН-2001.6-67. Электромонтажные работы | EM48: ТСН-2001.6-67-1 | EO48: Поправка: Гл.12.Прил.8.п.8. 3_12.00.01.11.001 | EQ48: 0 | ER48: 98.52 | ES48: 0 | ET48: 0 | EU48: 0 | EV48: 98.52 | EW48: 9.64 | EX48: 0 | EY48: 0 | FQ48: 0 | FR48: 0 | FS48: 0 | FX48: 91 | FY48: 48 | GD48: 1 | GF48: 1114236003 | GG48: 2 | GH48: 1 | GI48: 2 | GJ48: 0 | GK48: 0 | GL48: =ROUND(IF(AND(BH48=3,BI48=3,FS48<>0),P48,0),2) -> 0 | GM48: =ROUND(O48+X48+Y48,2)+GX48 -> 79135.98 | GN48: =IF(OR(BI48=0,BI48=1),GM48-GX48,0) -> 79135.98 | GO48: =IF(BI48=2,GM48-GX48,0) -> 0 | GP48: =IF(BI48=4,GM48-GX48,0) -> 0 | GR48: 0 | GS48: 3 | GT48: 0 | GV48: =ROUND((GT48),6) -> 0 | GW48: 1 | GX48: =ROUND(HC48*I48,2) -> 0 | HA48: 0 | HB48: 0 | HC48: =GV48*GW48 -> 0 | HS48: 0 | IK48: 0
A49: 17 | B49: 1 | C49: =ROW(SmtRes!A116) -> 116 | D49: =ROW(EtalonRes!A140) -> 140 | E49: 11 | F49: 6.67-6-1 | G49: Демонтаж кабеля | H49: 100 м | I49: =ROUND((26500+150+100)/100,9) -> 267.5 | J49: 0 | K49: =ROUND((26500+150+100)/100,9) -> 267.5 | O49: =ROUND(CP49,2) -> 1865821.2 | P49: =ROUND((ROUND((AC49*AW49*I49),2)*BC49),2) -> 0 | Q49: =(ROUND((ROUND((((ET49*1.2))*AV49*I49),2)*BB49),2)+ROUND((ROUND(((AE49-((EU49*1.2)))*AV49*I49),2)*BS49),2)) -> 0 | R49: =(ROUND((ROUND((((EU49*1.2))*AV49*I49),2)*BS49),2)+ROUND((ROUND(((AE49-((EU49*1.2)))*AV49*I49),2)*BS49),2)) -> 0 | S49: =ROUND((ROUND((AF49*AV49*I49),2)*BA49),2) -> 1865821.2 | T49: =ROUND(CU49*I49,2) -> 0 | U49: =CV49*I49 -> 3239.8787 | V49: =CW49*I49 -> 0 | W49: =ROUND(CX49*I49,2) -> 0 | X49: =(ROUND((((S49+ROUND((ROUND((((EU49*1.2))*AV49*I49),2)*BS49),2))*AT49)/100),2)+ROUND(((ROUND((ROUND(((AE49-((EU49*1.2)))*AV49*I49),2)*BS49),2)*AT49)/100),2)) -> 1697897.3 | Y49: =(ROUND((((S49+ROUND((ROUND((((EU49*1.2))*AV49*I49),2)*BS49),2))*AU49)/100),2)+ROUND(((ROUND((ROUND(((AE49-((EU49*1.2)))*AV49*I49),2)*BS49),2)*AU49)/100),2)) -> 895594.17 | AA49: 55929115 | AB49: =ROUND((AC49+AD49+AF49),6) -> 118.224 | AC49: =ROUND(((ES49*1)),6) -> 0 | AD49: =ROUND(((((ET49*1.2))-((EU49*1.2)))+AE49),6) -> 0 | AE49: =ROUND(((EU49*1.2)),6) -> 0 | AF49: =ROUND(((EV49*1.2)),6) -> 118.224 | AG49: =ROUND((AP49),6) -> 0 | AH49: =((EW49*1.2)) -> 11.568 | AI49: =((EX49*1.2)) -> 0 | AJ49: =(AS49) -> 0 | AK49: 98.52 | AL49: 0 | AM49: 0 | AN49: 0 | AO49: 98.52 | AP49: 0 | AQ49: 9.64 | AR49: 0 | AS49: 0 | AT49: 91 | AU49: 48 | AV49: 1.047 | AW49: 1 | AZ49: 1 | BA49: 56.35 | BB49: 1 | BC49: 1 | BH49: 0 | BI49: 1 | BJ49: ТСН-2001.6. Доп. 1-42. Сб. 67, т. 6, поз. 1 | BM49: 106 | BN49: 0 | BO49: 6.67-6-1 | BP49: 1 | BQ49: 60 | BR49: 0 | BS49: 56.35 | BT49: 1 | BU49: 1 | BV49: 1 | BW49: 1 | BX49: 1 | BZ49: 91 | CA49: 48 | CE49: 1566 | CF49: 0 | CG49: 0 | CM49: 0 | CN49: Поправка: Гл.12.Прил.8.п.8. 3_12.00.01.11.001 Наименование: При наличии напряженных и стесненных условий производства работ (стесненность, сложность складирования и транспортной логистики и т.п.) для объектов, расположенных в пределах круговой магистральной системы улиц "Садовое кольцо" города Москвы | CO49: 0 | CP49: =(P49+Q49+S49) -> 1865821.2 | CQ49: =ROUND((ROUND((AC49*AW49*1),2)*BC49),2) -> 0 | CR49: =(ROUND((ROUND((((ET49*1.2))*AV49*1),2)*BB49),2)+ROUND((ROUND(((AE49-((EU49*1.2)))*AV49*1),2)*BS49),2)) -> 0 | CS49: =(ROUND((ROUND((((EU49*1.2))*AV49*1),2)*BS49),2)+ROUND((ROUND(((AE49-((EU49*1.2)))*AV49*1),2)*BS49),2)) -> 0 | CT49: =ROUND((ROUND((AF49*AV49*1),2)*BA49),2) -> 6975 | CU49: =AG49 -> 0 | CV49: =(AH49*AV49) -> 12.111696 | CW49: =AI49 -> 0 | CX49: =AJ49 -> 0 | CY49: =(ROUND((((S49+ROUND((ROUND((((EU49*1.2))*AV49*1),2)*BS49),2))*AT49)/100),2)+ROUND(((ROUND((ROUND(((AE49-((EU49*1.2)))*AV49*1),2)*BS49),2)*AT49)/100),2)) -> 1697897.3 | CZ49: =(ROUND((((S49+ROUND((ROUND((((EU49*1.2))*AV49*1),2)*BS49),2))*AU49)/100),2)+ROUND(((ROUND((ROUND(((AE49-((EU49*1.2)))*AV49*1),2)*BS49),2)*AU49)/100),2)) -> 895594.17 | DB49: 40 | DD49: *1 | DE49: *1,2 | DF49: *1,2 | DG49: *1,2 | DI49: *1,2 | DJ49: *1,2 | DN49: 0 | DO49: 0 | DP49: 1 | DQ49: 1 | DU49: 1003 | DV49: 100 м | DW49: 100 м | DX49: 100 | EE49: 55393738 | EF49: 60 | EG49: Ремонтно-строительные работы | EH49: 0 | EJ49: 1 | EK49: 106 | EL49: ТСН-2001.6-67. Электромонтажные работы | EM49: ТСН-2001.6-67-1 | EO49: Поправка: Гл.12.Прил.8.п.8. 3_12.00.01.11.001 | EQ49: 0 | ER49: 98.52 | ES49: 0 | ET49: 0 | EU49: 0 | EV49: 98.52 | EW49: 9.64 | EX49: 0 | EY49: 0 | FQ49: 0 | FR49: 0 | FS49: 0 | FX49: 91 | FY49: 48 | GD49: 1 | GF49: 1114236003 | GG49: 2 | GH49: 1 | GI49: 2 | GJ49: 0 | GK49: 0 | GL49: =ROUND(IF(AND(BH49=3,BI49=3,FS49<>0),P49,0),2) -> 0 | GM49: =ROUND(O49+X49+Y49,2)+GX49 -> 4459312.6 | GN49: =IF(OR(BI49=0,BI49=1),GM49-GX49,0) -> 4459312.6 | GO49: =IF(BI49=2,GM49-GX49,0) -> 0 | GP49: =IF(BI49=4,GM49-GX49,0) -> 0 | GR49: 0 | GS49: 3 | GT49: 0 | GV49: =ROUND((GT49),6) -> 0 | GW49: 1 | GX49: =ROUND(HC49*I49,2) -> 0 | HA49: 0 | HB49: 0 | HC49: =GV49*GW49 -> 0 | HS49: 0 | IK49: 0
A50: 17 | B50: 1 | C50: =ROW(SmtRes!A124) -> 124 | D50: =ROW(EtalonRes!A153) -> 153 | E50: 12 | F50: 4.8-331-2 | G50: Прокладка металлического перфорированного лотка по установленным конструкциям, массой погонного метра до 4 кг / демонтаж лотков | H50: 100 М ТРАССЫ | I50: =ROUND((450+100)/100,9) -> 5.5 | J50: 0 | K50: =ROUND((450+100)/100,9) -> 5.5 | O50: =ROUND(CP50,2) -> 441.23 | P50: =ROUND((ROUND((AC50*AW50*I50),2)*BC50),2) -> 0 | Q50: =(ROUND((ROUND(((((ET50*1.2)*0.3))*AV50*I50),2)*BB50),2)+ROUND((ROUND(((AE50-(((EU50*1.2)*0.3)))*AV50*I50),2)*BS50),2)) -> 13.83 | R50: =(ROUND((ROUND(((((EU50*1.2)*0.3))*AV50*I50),2)*BS50),2)+ROUND((ROUND(((AE50-(((EU50*1.2)*0.3)))*AV50*I50),2)*BS50),2)) -> 2.49 | S50: =ROUND((ROUND((AF50*AV50*I50),2)*BA50),2) -> 427.4 | T50: =ROUND(CU50*I50,2) -> 0 | U50: =CV50*I50 -> 37.605308 | V50: =CW50*I50 -> 0 | W50: =ROUND(CX50*I50,2) -> 0 | X50: =(ROUND((((S50+ROUND((ROUND(((((EU50*1.2)*0.3))*AV50*I50),2)*BS50),2))*AT50)/100),2)+ROUND(((ROUND((ROUND(((AE50-(((EU50*1.2)*0.3)))*AV50*I50),2)*BS50),2)*AT50)/100),2)) -> 416.99 | Y50: =(ROUND((((S50+ROUND((ROUND(((((EU50*1.2)*0.3))*AV50*I50),2)*BS50),2))*AU50)/100),2)+ROUND(((ROUND((ROUND(((AE50-(((EU50*1.2)*0.3)))*AV50*I50),2)*BS50),2)*AU50)/100),2)) -> 219.24 | AA50: 55929113 | AB50: =ROUND((AC50+AD50+AF50),6) -> 76.6224 | AC50: =ROUND((((ES50*1)*0)),6) -> 0 | AD50: =ROUND((((((ET50*1.2)*0.3))-(((EU50*1.2)*0.3)))+AE50),6) -> 2.4012 | AE50: =ROUND((((EU50*1.2)*0.3)),6) -> 0.432 | AF50: =ROUND((((EV50*1.2)*0.3)),6) -> 74.2212 | AG50: =ROUND((AP50),6) -> 0 | AH50: =(((EW50*1.2)*0.3)) -> 6.5304 | AI50: =(((EX50*1.2)*0.3)) -> 0 | AJ50: =(AS50) -> 0 | AK50: 224.18 | AL50: 11.34 | AM50: 6.67 | AN50: 1.2 | AO50: 206.17 | AP50: 0 | AQ50: 18.14 | AR50: 0 | AS50: 0 | AT50: 97 | AU50: 51 | AV50: 1.047 | AW50: 1 | AZ50: 1 | BA50: 1 | BB50: 1 | BC50: 1 | BH50: 0 | BI50: 2 | BJ50: ТСН-2001.4 Доп. 81, Сб. 8, т. 331, поз. 2 | BM50: 67 | BN50: 0 | BO50: 4.8-331-2 | BP50: 1 | BQ50: 40 | BR50: 0 | BS50: 1 | BT50: 1 | BU50: 1 | BV50: 1 | BW50: 1 | BX50: 1 | BZ50: 97 | CA50: 51 | CE50: 1566 | CF50: 0 | CG50: 0 | CM50: 0 | CN50: Поправка: Гл.12.Прил.8.п.8. 3_12.00.01.11.001 Наименование: При наличии напряженных и стесненных условий производства работ (стесненность, сложность складирования и транспортной логистики и т.п.) для объектов, расположенных в пределах круговой магистральной системы улиц "Садовое кольцо" города Москвы Поправка: Гл.4.Прил.2.2.п.2.2.29_04.00.01.35.003 Наименование: При демонтаже оборудования, предназначенного в лом | CO50: 0 | CP50: =(P50+Q50+S50) -> 441.23 | CQ50: =ROUND((ROUND((AC50*AW50*1),2)*BC50),2) -> 0 | CR50: =(ROUND((ROUND(((((ET50*1.2)*0.3))*AV50*1),2)*BB50),2)+ROUND((ROUND(((AE50-(((EU50*1.2)*0.3)))*AV50*1),2)*BS50),2)) -> 2.51 | CS50: =(ROUND((ROUND(((((EU50*1.2)*0.3))*AV50*1),2)*BS50),2)+ROUND((ROUND(((AE50-(((EU50*1.2)*0.3)))*AV50*1),2)*BS50),2)) -> 0.45 | CT50: =ROUND((ROUND((AF50*AV50*1),2)*BA50),2) -> 77.71 | CU50: =AG50 -> 0 | CV50: =(AH50*AV50) -> 6.8373288 | CW50: =AI50 -> 0 | CX50: =AJ50 -> 0 | CY50: =(ROUND((((S50+ROUND((ROUND(((((EU50*1.2)*0.3))*AV50*1),2)*BS50),2))*AT50)/100),2)+ROUND(((ROUND((ROUND(((AE50-(((EU50*1.2)*0.3)))*AV50*1),2)*BS50),2)*AT50)/100),2)) -> 415.01 | CZ50: =(ROUND((((S50+ROUND((ROUND(((((EU50*1.2)*0.3))*AV50*1),2)*BS50),2))*AU50)/100),2)+ROUND(((ROUND((ROUND(((AE50-(((EU50*1.2)*0.3)))*AV50*1),2)*BS50),2)*AU50)/100),2)) -> 218.2 | DB50: 41 | DD50: *1)*0 | DE50: *1,2)*0,3 | DF50: *1,2)*0,3 | DG50: *1,2)*0,3 | DI50: *1,2)*0,3 | DJ50: *1,2)*0,3 | DN50: 0 | DO50: 0 | DP50: 1 | DQ50: 1 | DU50: 1013 | DV50: 100 М ТРАССЫ | DW50: 100 М ТРАССЫ | DX50: 1 | EE50: 55393699 | EF50: 40 | EG50: Монтаж оборудования | EH50: 0 | EJ50: 2 | EK50: 67 | EL50: ТСН-2001.4-8. Электротехнические установки | EM50: ТСН-2001.4-8-1 | EO50: Поправка: Гл.12.Прил.8.п.8. 3_12.00.01.11.001 Поправка: Гл.4.Прил.2.2.п.2.2.29_04.00.01.35.003 | EQ50: 0 | ER50: 224.18 | ES50: 11.34 | ET50: 6.67 | EU50: 1.2 | EV50: 206.17 | EW50: 18.14 | EX50: 0 | EY50: 0 | FQ50: 0 | FR50: 0 | FS50: 0 | FX50: 97 | FY50: 51 | GD50: 1 | GF50: 1878904797 | GG50: 2 | GH50: 1 | GI50: 2 | GJ50: 0 | GK50: 0 | GL50: =ROUND(IF(AND(BH50=3,BI50=3,FS50<>0),P50,0),2) -> 0 | GM50: =ROUND(O50+X50+Y50,2)+GX50 -> 1077.46 | GN50: =IF(OR(BI50=0,BI50=1),GM50-GX50,0) -> 0 | GO50: =IF(BI50=2,GM50-GX50,0) -> 1077.46 | GP50: =IF(BI50=4,GM50-GX50,0) -> 0 | GR50: 0 | GS50: 3 | GT50: 0 | GV50: =ROUND((GT50),6) -> 0 | GW50: 1 | GX50: =ROUND(HC50*I50,2) -> 0 | HA50: 0 | HB50: 0 | HC50: =GV50*GW50 -> 0 | HS50: 0 | IK50: 0
A51: 17 | B51: 1 | C51: =ROW(SmtRes!A132) -> 132 | D51: =ROW(EtalonRes!A166) -> 166 | E51: 12 | F51: 4.8-331-2 | G51: Прокладка металлического перфорированного лотка по установленным конструкциям, массой погонного метра до 4 кг / демонтаж лотков | H51: 100 М ТРАССЫ | I51: =ROUND((450+100)/100,9) -> 5.5 | J51: 0 | K51: =ROUND((450+100)/100,9) -> 5.5 | O51: =ROUND(CP51,2) -> 24346.21 | P51: =ROUND((ROUND((AC51*AW51*I51),2)*BC51),2) -> 0 | Q51: =(ROUND((ROUND(((((ET51*1.2)*0.3))*AV51*I51),2)*BB51),2)+ROUND((ROUND(((AE51-(((EU51*1.2)*0.3)))*AV51*I51),2)*BS51),2)) -> 262.22 | R51: =(ROUND((ROUND(((((EU51*1.2)*0.3))*AV51*I51),2)*BS51),2)+ROUND((ROUND(((AE51-(((EU51*1.2)*0.3)))*AV51*I51),2)*BS51),2)) -> 140.31 | S51: =ROUND((ROUND((AF51*AV51*I51),2)*BA51),2) -> 24083.99 | T51: =ROUND(CU51*I51,2) -> 0 | U51: =CV51*I51 -> 37.605308 | V51: =CW51*I51 -> 0 | W51: =ROUND(CX51*I51,2) -> 0 | X51: =(ROUND((((S51+ROUND((ROUND(((((EU51*1.2)*0.3))*AV51*I51),2)*BS51),2))*AT51)/100),2)+ROUND(((ROUND((ROUND(((AE51-(((EU51*1.2)*0.3)))*AV51*I51),2)*BS51),2)*AT51)/100),2)) -> 23497.57 | Y51: =(ROUND((((S51+ROUND((ROUND(((((EU51*1.2)*0.3))*AV51*I51),2)*BS51),2))*AU51)/100),2)+ROUND(((ROUND((ROUND(((AE51-(((EU51*1.2)*0.3)))*AV51*I51),2)*BS51),2)*AU51)/100),2)) -> 12354.39 | AA51: 55929115 | AB51: =ROUND((AC51+AD51+AF51),6) -> 76.6224 | AC51: =ROUND((((ES51*1)*0)),6) -> 0 | AD51: =ROUND((((((ET51*1.2)*0.3))-(((EU51*1.2)*0.3)))+AE51),6) -> 2.4012 | AE51: =ROUND((((EU51*1.2)*0.3)),6) -> 0.432 | AF51: =ROUND((((EV51*1.2)*0.3)),6) -> 74.2212 | AG51: =ROUND((AP51),6) -> 0 | AH51: =(((EW51*1.2)*0.3)) -> 6.5304 | AI51: =(((EX51*1.2)*0.3)) -> 0 | AJ51: =(AS51) -> 0 | AK51: 224.18 | AL51: 11.34 | AM51: 6.67 | AN51: 1.2 | AO51: 206.17 | AP51: 0 | AQ51: 18.14 | AR51: 0 | AS51: 0 | AT51: 97 | AU51: 51 | AV51: 1.047 | AW51: 1 | AZ51: 1 | BA51: 56.35 | BB51: 18.96 | BC51: 8.24 | BH51: 0 | BI51: 2 | BJ51: ТСН-2001.4 Доп. 81, Сб. 8, т. 331, поз. 2 | BM51: 67 | BN51: 0 | BO51: 4.8-331-2 | BP51: 1 | BQ51: 40 | BR51: 0 | BS51: 56.35 | BT51: 1 | BU51: 1 | BV51: 1 | BW51: 1 | BX51: 1 | BZ51: 97 | CA51: 51 | CE51: 1566 | CF51: 0 | CG51: 0 | CM51: 0 | CN51: Поправка: Гл.12.Прил.8.п.8. 3_12.00.01.11.001 Наименование: При наличии напряженных и стесненных условий производства работ (стесненность, сложность складирования и транспортной логистики и т.п.) для объектов, расположенных в пределах круговой магистральной системы улиц "Садовое кольцо" города Москвы Поправка: Гл.4.Прил.2.2.п.2.2.29_04.00.01.35.003 Наименование: При демонтаже оборудования, предназначенного в лом | CO51: 0 | CP51: =(P51+Q51+S51) -> 24346.21 | CQ51: =ROUND((ROUND((AC51*AW51*1),2)*BC51),2) -> 0 | CR51: =(ROUND((ROUND(((((ET51*1.2)*0.3))*AV51*1),2)*BB51),2)+ROUND((ROUND(((AE51-(((EU51*1.2)*0.3)))*AV51*1),2)*BS51),2)) -> 47.59 | CS51: =(ROUND((ROUND(((((EU51*1.2)*0.3))*AV51*1),2)*BS51),2)+ROUND((ROUND(((AE51-(((EU51*1.2)*0.3)))*AV51*1),2)*BS51),2)) -> 25.36 | CT51: =ROUND((ROUND((AF51*AV51*1),2)*BA51),2) -> 4378.96 | CU51: =AG51 -> 0 | CV51: =(AH51*AV51) -> 6.8373288 | CW51: =AI51 -> 0 | CX51: =AJ51 -> 0 | CY51: =(ROUND((((S51+ROUND((ROUND(((((EU51*1.2)*0.3))*AV51*1),2)*BS51),2))*AT51)/100),2)+ROUND(((ROUND((ROUND(((AE51-(((EU51*1.2)*0.3)))*AV51*1),2)*BS51),2)*AT51)/100),2)) -> 23386.07 | CZ51: =(ROUND((((S51+ROUND((ROUND(((((EU51*1.2)*0.3))*AV51*1),2)*BS51),2))*AU51)/100),2)+ROUND(((ROUND((ROUND(((AE51-(((EU51*1.2)*0.3)))*AV51*1),2)*BS51),2)*AU51)/100),2)) -> 12295.77 | DB51: 43 | DD51: *1)*0 | DE51: *1,2)*0,3 | DF51: *1,2)*0,3 | DG51: *1,2)*0,3 | DI51: *1,2)*0,3 | DJ51: *1,2)*0,3 | DN51: 0 | DO51: 0 | DP51: 1 | DQ51: 1 | DU51: 1013 | DV51: 100 М ТРАССЫ | DW51: 100 М ТРАССЫ | DX51: 1 | EE51: 55393699 | EF51: 40 | EG51: Монтаж оборудования | EH51: 0 | EJ51: 2 | EK51: 67 | EL51: ТСН-2001.4-8. Электротехнические установки | EM51: ТСН-2001.4-8-1 | EO51: Поправка: Гл.12.Прил.8.п.8. 3_12.00.01.11.001 Поправка: Гл.4.Прил.2.2.п.2.2.29_04.00.01.35.003 | EQ51: 0 | ER51: 224.18 | ES51: 11.34 | ET51: 6.67 | EU51: 1.2 | EV51: 206.17 | EW51: 18.14 | EX51: 0 | EY51: 0 | FQ51: 0 | FR51: 0 | FS51: 0 | FX51: 97 | FY51: 51 | GD51: 1 | GF51: 1878904797 | GG51: 2 | GH51: 1 | GI51: 2 | GJ51: 0 | GK51: 0 | GL51: =ROUND(IF(AND(BH51=3,BI51=3,FS51<>0),P51,0),2) -> 0 | GM51: =ROUND(O51+X51+Y51,2)+GX51 -> 60198.17 | GN51: =IF(OR(BI51=0,BI51=1),GM51-GX51,0) -> 0 | GO51: =IF(BI51=2,GM51-GX51,0) -> 60198.17 | GP51: =IF(BI51=4,GM51-GX51,0) -> 0 | GR51: 0 | GS51: 3 | GT51: 0 | GV51: =ROUND((GT51),6) -> 0 | GW51: 1 | GX51: =ROUND(HC51*I51,2) -> 0 | HA51: 0 | HB51: 0 | HC51: =GV51*GW51 -> 0 | HS51: 0 | IK51: 0
A52: 17 | B52: 1 | C52: =ROW(SmtRes!A142) -> 142 | D52: =ROW(EtalonRes!A180) -> 180 | E52: 13 | F52: 4.8-331-12 | G52: Установка крышек металлических на лотки металлические перфорированные и неперфорированные массой 1 м свыше 2 до 4 кг / демонтаж крышек лотков | H52: 100 М ТРАССЫ | I52: =ROUND((450+100)/100,9) -> 5.5 | J52: 0 | K52: =ROUND((450+100)/100,9) -> 5.5 | O52: =ROUND(CP52,2) -> 181.77 | P52: =ROUND((ROUND((AC52*AW52*I52),2)*BC52),2) -> 0 | Q52: =(ROUND((ROUND(((((ET52*1.2)*0.3))*AV52*I52),2)*BB52),2)+ROUND((ROUND(((AE52-(((EU52*1.2)*0.3)))*AV52*I52),2)*BS52),2)) -> 11.9 | R52: =(ROUND((ROUND(((((EU52*1.2)*0.3))*AV52*I52),2)*BS52),2)+ROUND((ROUND(((AE52-(((EU52*1.2)*0.3)))*AV52*I52),2)*BS52),2)) -> 2.18 | S52: =ROUND((ROUND((AF52*AV52*I52),2)*BA52),2) -> 169.87 | T52: =ROUND(CU52*I52,2) -> 0 | U52: =CV52*I52 -> 15.071146 | V52: =CW52*I52 -> 0 | W52: =ROUND(CX52*I52,2) -> 0 | X52: =(ROUND((((S52+ROUND((ROUND(((((EU52*1.2)*0.3))*AV52*I52),2)*BS52),2))*AT52)/100),2)+ROUND(((ROUND((ROUND(((AE52-(((EU52*1.2)*0.3)))*AV52*I52),2)*BS52),2)*AT52)/100),2)) -> 166.89 | Y52: =(ROUND((((S52+ROUND((ROUND(((((EU52*1.2)*0.3))*AV52*I52),2)*BS52),2))*AU52)/100),2)+ROUND(((ROUND((ROUND(((AE52-(((EU52*1.2)*0.3)))*AV52*I52),2)*BS52),2)*AU52)/100),2)) -> 87.75 | AA52: 55929113 | AB52: =ROUND((AC52+AD52+AF52),6) -> 31.5648 | AC52: =ROUND((((ES52*1)*0)),6) -> 0 | AD52: =ROUND((((((ET52*1.2)*0.3))-(((EU52*1.2)*0.3)))+AE52),6) -> 2.0664 | AE52: =ROUND((((EU52*1.2)*0.3)),6) -> 0.378 | AF52: =ROUND((((EV52*1.2)*0.3)),6) -> 29.4984 | AG52: =ROUND((AP52),6) -> 0 | AH52: =(((EW52*1.2)*0.3)) -> 2.6172 | AI52: =(((EX52*1.2)*0.3)) -> 0 | AJ52: =(AS52) -> 0 | AK52: 104.14 | AL52: 16.46 | AM52: 5.74 | AN52: 1.05 | AO52: 81.94 | AP52: 0 | AQ52: 7.27 | AR52: 0 | AS52: 0 | AT52: 97 | AU52: 51 | AV52: 1.047 | AW52: 1 | AZ52: 1 | BA52: 1 | BB52: 1 | BC52: 1 | BH52: 0 | BI52: 2 | BJ52: ТСН-2001.4 Доп. 80, Сб. 8, т. 331, поз. 12 | BM52: 67 | BN52: 0 | BO52: 4.8-331-12 | BP52: 1 | BQ52: 40 | BR52: 0 | BS52: 1 | BT52: 1 | BU52: 1 | BV52: 1 | BW52: 1 | BX52: 1 | BZ52: 97 | CA52: 51 | CE52: 1566 | CF52: 0 | CG52: 0 | CM52: 0 | CN52: Поправка: Гл.12.Прил.8.п.8. 3_12.00.01.11.001 Наименование: При наличии напряженных и стесненных условий производства работ (стесненность, сложность складирования и транспортной логистики и т.п.) для объектов, расположенных в пределах круговой магистральной системы улиц "Садовое кольцо" города Москвы Поправка: Гл.4.Прил.2.2.п.2.2.29_04.00.01.35.003 Наименование: При демонтаже оборудования, предназначенного в лом | CO52: 0 | CP52: =(P52+Q52+S52) -> 181.77 | CQ52: =ROUND((ROUND((AC52*AW52*1),2)*BC52),2) -> 0 | CR52: =(ROUND((ROUND(((((ET52*1.2)*0.3))*AV52*1),2)*BB52),2)+ROUND((ROUND(((AE52-(((EU52*1.2)*0.3)))*AV52*1),2)*BS52),2)) -> 2.16 | CS52: =(ROUND((ROUND(((((EU52*1.2)*0.3))*AV52*1),2)*BS52),2)+ROUND((ROUND(((AE52-(((EU52*1.2)*0.3)))*AV52*1),2)*BS52),2)) -> 0.4 | CT52: =ROUND((ROUND((AF52*AV52*1),2)*BA52),2) -> 30.88 | CU52: =AG52 -> 0 | CV52: =(AH52*AV52) -> 2.7402084 | CW52: =AI52 -> 0 | CX52: =AJ52 -> 0 | CY52: =(ROUND((((S52+ROUND((ROUND(((((EU52*1.2)*0.3))*AV52*1),2)*BS52),2))*AT52)/100),2)+ROUND(((ROUND((ROUND(((AE52-(((EU52*1.2)*0.3)))*AV52*1),2)*BS52),2)*AT52)/100),2)) -> 165.16 | CZ52: =(ROUND((((S52+ROUND((ROUND(((((EU52*1.2)*0.3))*AV52*1),2)*BS52),2))*AU52)/100),2)+ROUND(((ROUND((ROUND(((AE52-(((EU52*1.2)*0.3)))*AV52*1),2)*BS52),2)*AU52)/100),2)) -> 86.84 | DB52: 45 | DD52: *1)*0 | DE52: *1,2)*0,3 | DF52: *1,2)*0,3 | DG52: *1,2)*0,3 | DI52: *1,2)*0,3 | DJ52: *1,2)*0,3 | DN52: 0 | DO52: 0 | DP52: 1 | DQ52: 1 | DU52: 1013 | DV52: 100 М ТРАССЫ | DW52: 100 М ТРАССЫ | DX52: 1 | EE52: 55393699 | EF52: 40 | EG52: Монтаж оборудования | EH52: 0 | EJ52: 2 | EK52: 67 | EL52: ТСН-2001.4-8. Электротехнические установки | EM52: ТСН-2001.4-8-1 | EO52: Поправка: Гл.12.Прил.8.п.8. 3_12.00.01.11.001 Поправка: Гл.4.Прил.2.2.п.2.2.29_04.00.01.35.003 | EQ52: 0 | ER52: 104.14 | ES52: 16.46 | ET52: 5.74 | EU52: 1.05 | EV52: 81.94 | EW52: 7.27 | EX52: 0 | EY52: 0 | FQ52: 0 | FR52: 0 | FS52: 0 | FX52: 97 | FY52: 51 | GD52: 1 | GF52: -1382004924 | GG52: 2 | GH52: 1 | GI52: 2 | GJ52: 0 | GK52: 0 | GL52: =ROUND(IF(AND(BH52=3,BI52=3,FS52<>0),P52,0),2) -> 0 | GM52: =ROUND(O52+X52+Y52,2)+GX52 -> 436.41 | GN52: =IF(OR(BI52=0,BI52=1),GM52-GX52,0) -> 0 | GO52: =IF(BI52=2,GM52-GX52,0) -> 436.41 | GP52: =IF(BI52=4,GM52-GX52,0) -> 0 | GR52: 0 | GS52: 3 | GT52: 0 | GV52: =ROUND((GT52),6) -> 0 | GW52: 1 | GX52: =ROUND(HC52*I52,2) -> 0 | HA52: 0 | HB52: 0 | HC52: =GV52*GW52 -> 0 | HS52: 0 | IK52: 0
A53: 17 | B53: 1 | C53: =ROW(SmtRes!A152) -> 152 | D53: =ROW(EtalonRes!A194) -> 194 | E53: 13 | F53: 4.8-331-12 | G53: Установка крышек металлических на лотки металлические перфорированные и неперфорированные массой 1 м свыше 2 до 4 кг / демонтаж крышек лотков | H53: 100 М ТРАССЫ | I53: =ROUND((450+100)/100,9) -> 5.5 | J53: 0 | K53: =ROUND((450+100)/100,9) -> 5.5 | O53: =ROUND(CP53,2) -> 9800.29 | P53: =ROUND((ROUND((AC53*AW53*I53),2)*BC53),2) -> 0 | Q53: =(ROUND((ROUND(((((ET53*1.2)*0.3))*AV53*I53),2)*BB53),2)+ROUND((ROUND(((AE53-(((EU53*1.2)*0.3)))*AV53*I53),2)*BS53),2)) -> 228.12 | R53: =(ROUND((ROUND(((((EU53*1.2)*0.3))*AV53*I53),2)*BS53),2)+ROUND((ROUND(((AE53-(((EU53*1.2)*0.3)))*AV53*I53),2)*BS53),2)) -> 122.84 | S53: =ROUND((ROUND((AF53*AV53*I53),2)*BA53),2) -> 9572.17 | T53: =ROUND(CU53*I53,2) -> 0 | U53: =CV53*I53 -> 15.071146 | V53: =CW53*I53 -> 0 | W53: =ROUND(CX53*I53,2) -> 0 | X53: =(ROUND((((S53+ROUND((ROUND(((((EU53*1.2)*0.3))*AV53*I53),2)*BS53),2))*AT53)/100),2)+ROUND(((ROUND((ROUND(((AE53-(((EU53*1.2)*0.3)))*AV53*I53),2)*BS53),2)*AT53)/100),2)) -> 9404.16 | Y53: =(ROUND((((S53+ROUND((ROUND(((((EU53*1.2)*0.3))*AV53*I53),2)*BS53),2))*AU53)/100),2)+ROUND(((ROUND((ROUND(((AE53-(((EU53*1.2)*0.3)))*AV53*I53),2)*BS53),2)*AU53)/100),2)) -> 4944.46 | AA53: 55929115 | AB53: =ROUND((AC53+AD53+AF53),6) -> 31.5648 | AC53: =ROUND((((ES53*1)*0)),6) -> 0 | AD53: =ROUND((((((ET53*1.2)*0.3))-(((EU53*1.2)*0.3)))+AE53),6) -> 2.0664 | AE53: =ROUND((((EU53*1.2)*0.3)),6) -> 0.378 | AF53: =ROUND((((EV53*1.2)*0.3)),6) -> 29.4984 | AG53: =ROUND((AP53),6) -> 0 | AH53: =(((EW53*1.2)*0.3)) -> 2.6172 | AI53: =(((EX53*1.2)*0.3)) -> 0 | AJ53: =(AS53) -> 0 | AK53: 104.14 | AL53: 16.46 | AM53: 5.74 | AN53: 1.05 | AO53: 81.94 | AP53: 0 | AQ53: 7.27 | AR53: 0 | AS53: 0 | AT53: 97 | AU53: 51 | AV53: 1.047 | AW53: 1 | AZ53: 1 | BA53: 56.35 | BB53: 19.17 | BC53: 7.31 | BH53: 0 | BI53: 2 | BJ53: ТСН-2001.4 Доп. 80, Сб. 8, т. 331, поз. 12 | BM53: 67 | BN53: 0 | BO53: 4.8-331-12 | BP53: 1 | BQ53: 40 | BR53: 0 | BS53: 56.35 | BT53: 1 | BU53: 1 | BV53: 1 | BW53: 1 | BX53: 1 | BZ53: 97 | CA53: 51 | CE53: 1566 | CF53: 0 | CG53: 0 | CM53: 0 | CN53: Поправка: Гл.12.Прил.8.п.8. 3_12.00.01.11.001 Наименование: При наличии напряженных и стесненных условий производства работ (стесненность, сложность складирования и транспортной логистики и т.п.) для объектов, расположенных в пределах круговой магистральной системы улиц "Садовое кольцо" города Москвы Поправка: Гл.4.Прил.2.2.п.2.2.29_04.00.01.35.003 Наименование: При демонтаже оборудования, предназначенного в лом | CO53: 0 | CP53: =(P53+Q53+S53) -> 9800.29 | CQ53: =ROUND((ROUND((AC53*AW53*1),2)*BC53),2) -> 0 | CR53: =(ROUND((ROUND(((((ET53*1.2)*0.3))*AV53*1),2)*BB53),2)+ROUND((ROUND(((AE53-(((EU53*1.2)*0.3)))*AV53*1),2)*BS53),2)) -> 41.41 | CS53: =(ROUND((ROUND(((((EU53*1.2)*0.3))*AV53*1),2)*BS53),2)+ROUND((ROUND(((AE53-(((EU53*1.2)*0.3)))*AV53*1),2)*BS53),2)) -> 22.54 | CT53: =ROUND((ROUND((AF53*AV53*1),2)*BA53),2) -> 1740.09 | CU53: =AG53 -> 0 | CV53: =(AH53*AV53) -> 2.7402084 | CW53: =AI53 -> 0 | CX53: =AJ53 -> 0 | CY53: =(ROUND((((S53+ROUND((ROUND(((((EU53*1.2)*0.3))*AV53*1),2)*BS53),2))*AT53)/100),2)+ROUND(((ROUND((ROUND(((AE53-(((EU53*1.2)*0.3)))*AV53*1),2)*BS53),2)*AT53)/100),2)) -> 9306.87 | CZ53: =(ROUND((((S53+ROUND((ROUND(((((EU53*1.2)*0.3))*AV53*1),2)*BS53),2))*AU53)/100),2)+ROUND(((ROUND((ROUND(((AE53-(((EU53*1.2)*0.3)))*AV53*1),2)*BS53),2)*AU53)/100),2)) -> 4893.3 | DB53: 47 | DD53: *1)*0 | DE53: *1,2)*0,3 | DF53: *1,2)*0,3 | DG53: *1,2)*0,3 | DI53: *1,2)*0,3 | DJ53: *1,2)*0,3 | DN53: 0 | DO53: 0 | DP53: 1 | DQ53: 1 | DU53: 1013 | DV53: 100 М ТРАССЫ | DW53: 100 М ТРАССЫ | DX53: 1 | EE53: 55393699 | EF53: 40 | EG53: Монтаж оборудования | EH53: 0 | EJ53: 2 | EK53: 67 | EL53: ТСН-2001.4-8. Электротехнические установки | EM53: ТСН-2001.4-8-1 | EO53: Поправка: Гл.12.Прил.8.п.8. 3_12.00.01.11.001 Поправка: Гл.4.Прил.2.2.п.2.2.29_04.00.01.35.003 | EQ53: 0 | ER53: 104.14 | ES53: 16.46 | ET53: 5.74 | EU53: 1.05 | EV53: 81.94 | EW53: 7.27 | EX53: 0 | EY53: 0 | FQ53: 0 | FR53: 0 | FS53: 0 | FX53: 97 | FY53: 51 | GD53: 1 | GF53: -1382004924 | GG53: 2 | GH53: 1 | GI53: 2 | GJ53: 0 | GK53: 0 | GL53: =ROUND(IF(AND(BH53=3,BI53=3,FS53<>0),P53,0),2) -> 0 | GM53: =ROUND(O53+X53+Y53,2)+GX53 -> 24148.91 | GN53: =IF(OR(BI53=0,BI53=1),GM53-GX53,0) -> 0 | GO53: =IF(BI53=2,GM53-GX53,0) -> 24148.91 | GP53: =IF(BI53=4,GM53-GX53,0) -> 0 | GR53: 0 | GS53: 3 | GT53: 0 | GV53: =ROUND((GT53),6) -> 0 | GW53: 1 | GX53: =ROUND(HC53*I53,2) -> 0 | HA53: 0 | HB53: 0 | HC53: =GV53*GW53 -> 0 | HS53: 0 | IK53: 0
A54: 17 | B54: 1 | C54: =ROW(SmtRes!A156) -> 156 | D54: =ROW(EtalonRes!A200) -> 200 | E54: 14 | F54: 4.8-331-14 | G54: Установка конструкций металлических: консольных кронштейнов по бетонным основаниям / демонтаж консолей | H54: 100 шт. | I54: =ROUND((50+40)/100,9) -> 0.9 | J54: 0 | K54: =ROUND((50+40)/100,9) -> 0.9 | O54: =ROUND(CP54,2) -> 87.2 | P54: =ROUND((ROUND((AC54*AW54*I54),2)*BC54),2) -> 0 | Q54: =(ROUND((ROUND(((((ET54*1.2)*0.3))*AV54*I54),2)*BB54),2)+ROUND((ROUND(((AE54-(((EU54*1.2)*0.3)))*AV54*I54),2)*BS54),2)) -> 3.2 | R54: =(ROUND((ROUND(((((EU54*1.2)*0.3))*AV54*I54),2)*BS54),2)+ROUND((ROUND(((AE54-(((EU54*1.2)*0.3)))*AV54*I54),2)*BS54),2)) -> 0.34 | S54: =ROUND((ROUND((AF54*AV54*I54),2)*BA54),2) -> 84 | T54: =ROUND(CU54*I54,2) -> 0 | U54: =CV54*I54 -> 7.3646399 | V54: =CW54*I54 -> 0 | W54: =ROUND(CX54*I54,2) -> 0 | X54: =(ROUND((((S54+ROUND((ROUND(((((EU54*1.2)*0.3))*AV54*I54),2)*BS54),2))*AT54)/100),2)+ROUND(((ROUND((ROUND(((AE54-(((EU54*1.2)*0.3)))*AV54*I54),2)*BS54),2)*AT54)/100),2)) -> 81.81 | Y54: =(ROUND((((S54+ROUND((ROUND(((((EU54*1.2)*0.3))*AV54*I54),2)*BS54),2))*AU54)/100),2)+ROUND(((ROUND((ROUND(((AE54-(((EU54*1.2)*0.3)))*AV54*I54),2)*BS54),2)*AU54)/100),2)) -> 43.01 | AA54: 55929113 | AB54: =ROUND((AC54+AD54+AF54),6) -> 92.5308 | AC54: =ROUND((((ES54*1)*0)),6) -> 0 | AD54: =ROUND((((((ET54*1.2)*0.3))-(((EU54*1.2)*0.3)))+AE54),6) -> 3.3912 | AE54: =ROUND((((EU54*1.2)*0.3)),6) -> 0.3636 | AF54: =ROUND((((EV54*1.2)*0.3)),6) -> 89.1396 | AG54: =ROUND((AP54),6) -> 0 | AH54: =(((EW54*1.2)*0.3)) -> 7.8156 | AI54: =(((EX54*1.2)*0.3)) -> 0 | AJ54: =(AS54) -> 0 | AK54: 260.87 | AL54: 3.84 | AM54: 9.42 | AN54: 1.01 | AO54: 247.61 | AP54: 0 | AQ54: 21.71 | AR54: 0 | AS54: 0 | AT54: 97 | AU54: 51 | AV54: 1.047 | AW54: 1 | AZ54: 1 | BA54: 1 | BB54: 1 | BC54: 1 | BH54: 0 | BI54: 2 | BJ54: ТСН-2001.4 Доп. 79, Сб. 8, т. 331, поз. 14 | BM54: 67 | BN54: 0 | BO54: 4.8-331-14 | BP54: 1 | BQ54: 40 | BR54: 0 | BS54: 1 | BT54: 1 | BU54: 1 | BV54: 1 | BW54: 1 | BX54: 1 | BZ54: 97 | CA54: 51 | CE54: 1566 | CF54: 0 | CG54: 0 | CM54: 0 | CN54: Поправка: Гл.12.Прил.8.п.8. 3_12.00.01.11.001 Наименование: При наличии напряженных и стесненных условий производства работ (стесненность, сложность складирования и транспортной логистики и т.п.) для объектов, расположенных в пределах круговой магистральной системы улиц "Садовое кольцо" города Москвы Поправка: Гл.4.Прил.2.2.п.2.2.29_04.00.01.35.003 Наименование: При демонтаже оборудования, предназначенного в лом | CO54: 0 | CP54: =(P54+Q54+S54) -> 87.2 | CQ54: =ROUND((ROUND((AC54*AW54*1),2)*BC54),2) -> 0 | CR54: =(ROUND((ROUND(((((ET54*1.2)*0.3))*AV54*1),2)*BB54),2)+ROUND((ROUND(((AE54-(((EU54*1.2)*0.3)))*AV54*1),2)*BS54),2)) -> 3.55 | CS54: =(ROUND((ROUND(((((EU54*1.2)*0.3))*AV54*1),2)*BS54),2)+ROUND((ROUND(((AE54-(((EU54*1.2)*0.3)))*AV54*1),2)*BS54),2)) -> 0.38 | CT54: =ROUND((ROUND((AF54*AV54*1),2)*BA54),2) -> 93.33 | CU54: =AG54 -> 0 | CV54: =(AH54*AV54) -> 8.1829332 | CW54: =AI54 -> 0 | CX54: =AJ54 -> 0 | CY54: =(ROUND((((S54+ROUND((ROUND(((((EU54*1.2)*0.3))*AV54*1),2)*BS54),2))*AT54)/100),2)+ROUND(((ROUND((ROUND(((AE54-(((EU54*1.2)*0.3)))*AV54*1),2)*BS54),2)*AT54)/100),2)) -> 81.85 | CZ54: =(ROUND((((S54+ROUND((ROUND(((((EU54*1.2)*0.3))*AV54*1),2)*BS54),2))*AU54)/100),2)+ROUND(((ROUND((ROUND(((AE54-(((EU54*1.2)*0.3)))*AV54*1),2)*BS54),2)*AU54)/100),2)) -> 43.03 | DB54: 49 | DD54: *1)*0 | DE54: *1,2)*0,3 | DF54: *1,2)*0,3 | DG54: *1,2)*0,3 | DI54: *1,2)*0,3 | DJ54: *1,2)*0,3 | DN54: 0 | DO54: 0 | DP54: 1 | DQ54: 1 | DU54: 1010 | DV54: 100 шт. | DW54: 100 шт. | DX54: 100 | EE54: 55393699 | EF54: 40 | EG54: Монтаж оборудования | EH54: 0 | EJ54: 2 | EK54: 67 | EL54: ТСН-2001.4-8. Электротехнические установки | EM54: ТСН-2001.4-8-1 | EO54: Поправка: Гл.12.Прил.8.п.8. 3_12.00.01.11.001 Поправка: Гл.4.Прил.2.2.п.2.2.29_04.00.01.35.003 | EQ54: 0 | ER54: 260.87 | ES54: 3.84 | ET54: 9.42 | EU54: 1.01 | EV54: 247.61 | EW54: 21.71 | EX54: 0 | EY54: 0 | FQ54: 0 | FR54: 0 | FS54: 0 | FX54: 97 | FY54: 51 | GD54: 1 | GF54: 154324872 | GG54: 2 | GH54: 1 | GI54: 2 | GJ54: 0 | GK54: 0 | GL54: =ROUND(IF(AND(BH54=3,BI54=3,FS54<>0),P54,0),2) -> 0 | GM54: =ROUND(O54+X54+Y54,2)+GX54 -> 212.02 | GN54: =IF(OR(BI54=0,BI54=1),GM54-GX54,0) -> 0 | GO54: =IF(BI54=2,GM54-GX54,0) -> 212.02 | GP54: =IF(BI54=4,GM54-GX54,0) -> 0 | GR54: 0 | GS54: 3 | GT54: 0 | GV54: =ROUND((GT54),6) -> 0 | GW54: 1 | GX54: =ROUND(HC54*I54,2) -> 0 | HA54: 0 | HB54: 0 | HC54: =GV54*GW54 -> 0 | HS54: 0 | IK54: 0
A55: 17 | B55: 1 | C55: =ROW(SmtRes!A160) -> 160 | D55: =ROW(EtalonRes!A206) -> 206 | E55: 14 | F55: 4.8-331-14 | G55: Установка конструкций металлических: консольных кронштейнов по бетонным основаниям / демонтаж консолей | H55: 100 шт. | I55: =ROUND((50+40)/100,9) -> 0.9 | J55: 0 | K55: =ROUND((50+40)/100,9) -> 0.9 | O55: =ROUND(CP55,2) -> 4780.92 | P55: =ROUND((ROUND((AC55*AW55*I55),2)*BC55),2) -> 0 | Q55: =(ROUND((ROUND(((((ET55*1.2)*0.3))*AV55*I55),2)*BB55),2)+ROUND((ROUND(((AE55-(((EU55*1.2)*0.3)))*AV55*I55),2)*BS55),2)) -> 47.52 | R55: =(ROUND((ROUND(((((EU55*1.2)*0.3))*AV55*I55),2)*BS55),2)+ROUND((ROUND(((AE55-(((EU55*1.2)*0.3)))*AV55*I55),2)*BS55),2)) -> 19.16 | S55: =ROUND((ROUND((AF55*AV55*I55),2)*BA55),2) -> 4733.4 | T55: =ROUND(CU55*I55,2) -> 0 | U55: =CV55*I55 -> 7.3646399 | V55: =CW55*I55 -> 0 | W55: =ROUND(CX55*I55,2) -> 0 | X55: =(ROUND((((S55+ROUND((ROUND(((((EU55*1.2)*0.3))*AV55*I55),2)*BS55),2))*AT55)/100),2)+ROUND(((ROUND((ROUND(((AE55-(((EU55*1.2)*0.3)))*AV55*I55),2)*BS55),2)*AT55)/100),2)) -> 4609.98 | Y55: =(ROUND((((S55+ROUND((ROUND(((((EU55*1.2)*0.3))*AV55*I55),2)*BS55),2))*AU55)/100),2)+ROUND(((ROUND((ROUND(((AE55-(((EU55*1.2)*0.3)))*AV55*I55),2)*BS55),2)*AU55)/100),2)) -> 2423.81 | AA55: 55929115 | AB55: =ROUND((AC55+AD55+AF55),6) -> 92.5308 | AC55: =ROUND((((ES55*1)*0)),6) -> 0 | AD55: =ROUND((((((ET55*1.2)*0.3))-(((EU55*1.2)*0.3)))+AE55),6) -> 3.3912 | AE55: =ROUND((((EU55*1.2)*0.3)),6) -> 0.3636 | AF55: =ROUND((((EV55*1.2)*0.3)),6) -> 89.1396 | AG55: =ROUND((AP55),6) -> 0 | AH55: =(((EW55*1.2)*0.3)) -> 7.8156 | AI55: =(((EX55*1.2)*0.3)) -> 0 | AJ55: =(AS55) -> 0 | AK55: 260.87 | AL55: 3.84 | AM55: 9.42 | AN55: 1.01 | AO55: 247.61 | AP55: 0 | AQ55: 21.71 | AR55: 0 | AS55: 0 | AT55: 97 | AU55: 51 | AV55: 1.047 | AW55: 1 | AZ55: 1 | BA55: 56.35 | BB55: 14.85 | BC55: 11.66 | BH55: 0 | BI55: 2 | BJ55: ТСН-2001.4 Доп. 79, Сб. 8, т. 331, поз. 14 | BM55: 67 | BN55: 0 | BO55: 4.8-331-14 | BP55: 1 | BQ55: 40 | BR55: 0 | BS55: 56.35 | BT55: 1 | BU55: 1 | BV55: 1 | BW55: 1 | BX55: 1 | BZ55: 97 | CA55: 51 | CE55: 1566 | CF55: 0 | CG55: 0 | CM55: 0 | CN55: Поправка: Гл.12.Прил.8.п.8. 3_12.00.01.11.001 Наименование: При наличии напряженных и стесненных условий производства работ (стесненность, сложность складирования и транспортной логистики и т.п.) для объектов, расположенных в пределах круговой магистральной системы улиц "Садовое кольцо" города Москвы Поправка: Гл.4.Прил.2.2.п.2.2.29_04.00.01.35.003 Наименование: При демонтаже оборудования, предназначенного в лом | CO55: 0 | CP55: =(P55+Q55+S55) -> 4780.92 | CQ55: =ROUND((ROUND((AC55*AW55*1),2)*BC55),2) -> 0 | CR55: =(ROUND((ROUND(((((ET55*1.2)*0.3))*AV55*1),2)*BB55),2)+ROUND((ROUND(((AE55-(((EU55*1.2)*0.3)))*AV55*1),2)*BS55),2)) -> 52.72 | CS55: =(ROUND((ROUND(((((EU55*1.2)*0.3))*AV55*1),2)*BS55),2)+ROUND((ROUND(((AE55-(((EU55*1.2)*0.3)))*AV55*1),2)*BS55),2)) -> 21.41 | CT55: =ROUND((ROUND((AF55*AV55*1),2)*BA55),2) -> 5259.15 | CU55: =AG55 -> 0 | CV55: =(AH55*AV55) -> 8.1829332 | CW55: =AI55 -> 0 | CX55: =AJ55 -> 0 | CY55: =(ROUND((((S55+ROUND((ROUND(((((EU55*1.2)*0.3))*AV55*1),2)*BS55),2))*AT55)/100),2)+ROUND(((ROUND((ROUND(((AE55-(((EU55*1.2)*0.3)))*AV55*1),2)*BS55),2)*AT55)/100),2)) -> 4612.17 | CZ55: =(ROUND((((S55+ROUND((ROUND(((((EU55*1.2)*0.3))*AV55*1),2)*BS55),2))*AU55)/100),2)+ROUND(((ROUND((ROUND(((AE55-(((EU55*1.2)*0.3)))*AV55*1),2)*BS55),2)*AU55)/100),2)) -> 2424.95 | DB55: 51 | DD55: *1)*0 | DE55: *1,2)*0,3 | DF55: *1,2)*0,3 | DG55: *1,2)*0,3 | DI55: *1,2)*0,3 | DJ55: *1,2)*0,3 | DN55: 0 | DO55: 0 | DP55: 1 | DQ55: 1 | DU55: 1010 | DV55: 100 шт. | DW55: 100 шт. | DX55: 100 | EE55: 55393699 | EF55: 40 | EG55: Монтаж оборудования | EH55: 0 | EJ55: 2 | EK55: 67 | EL55: ТСН-2001.4-8. Электротехнические установки | EM55: ТСН-2001.4-8-1 | EO55: Поправка: Гл.12.Прил.8.п.8. 3_12.00.01.11.001 Поправка: Гл.4.Прил.2.2.п.2.2.29_04.00.01.35.003 | EQ55: 0 | ER55: 260.87 | ES55: 3.84 | ET55: 9.42 | EU55: 1.01 | EV55: 247.61 | EW55: 21.71 | EX55: 0 | EY55: 0 | FQ55: 0 | FR55: 0 | FS55: 0 | FX55: 97 | FY55: 51 | GD55: 1 | GF55: 154324872 | GG55: 2 | GH55: 1 | GI55: 2 | GJ55: 0 | GK55: 0 | GL55: =ROUND(IF(AND(BH55=3,BI55=3,FS55<>0),P55,0),2) -> 0 | GM55: =ROUND(O55+X55+Y55,2)+GX55 -> 11814.71 | GN55: =IF(OR(BI55=0,BI55=1),GM55-GX55,0) -> 0 | GO55: =IF(BI55=2,GM55-GX55,0) -> 11814.71 | GP55: =IF(BI55=4,GM55-GX55,0) -> 0 | GR55: 0 | GS55: 3 | GT55: 0 | GV55: =ROUND((GT55),6) -> 0 | GW55: 1 | GX55: =ROUND(HC55*I55,2) -> 0 | HA55: 0 | HB55: 0 | HC55: =GV55*GW55 -> 0 | HS55: 0 | IK55: 0
A56: 17 | B56: 1 | C56: =ROW(SmtRes!A162) -> 162 | D56: =ROW(EtalonRes!A208) -> 208 | E56: 15 | F56: 6.67-5-12 | G56: Демонтаж трубных проводок, трубы в борозде диаметром 25 мм / ПВХ | H56: 100 м | I56: =ROUND((2500+2000+70)/100,9) -> 45.7 | J56: 0 | K56: =ROUND((2500+2000+70)/100,9) -> 45.7 | O56: =ROUND(CP56,2) -> 18386.8 | P56: =ROUND((ROUND((AC56*AW56*I56),2)*BC56),2) -> 0 | Q56: =(ROUND((ROUND((((ET56*1.2))*AV56*I56),2)*BB56),2)+ROUND((ROUND(((AE56-((EU56*1.2)))*AV56*I56),2)*BS56),2)) -> 0 | R56: =(ROUND((ROUND((((EU56*1.2))*AV56*I56),2)*BS56),2)+ROUND((ROUND(((AE56-((EU56*1.2)))*AV56*I56),2)*BS56),2)) -> 0 | S56: =ROUND((ROUND((AF56*AV56*I56),2)*BA56),2) -> 18386.8 | T56: =ROUND(CU56*I56,2) -> 0 | U56: =CV56*I56 -> 1747.7881 | V56: =CW56*I56 -> 0 | W56: =ROUND(CX56*I56,2) -> 0 | X56: =(ROUND((((S56+ROUND((ROUND((((EU56*1.2))*AV56*I56),2)*BS56),2))*AT56)/100),2)+ROUND(((ROUND((ROUND(((AE56-((EU56*1.2)))*AV56*I56),2)*BS56),2)*AT56)/100),2)) -> 16731.99 | Y56: =(ROUND((((S56+ROUND((ROUND((((EU56*1.2))*AV56*I56),2)*BS56),2))*AU56)/100),2)+ROUND(((ROUND((ROUND(((AE56-((EU56*1.2)))*AV56*I56),2)*BS56),2)*AU56)/100),2)) -> 8825.66 | AA56: 55929113 | AB56: =ROUND((AC56+AD56+AF56),6) -> 384.276 | AC56: =ROUND(((ES56*1)),6) -> 0 | AD56: =ROUND(((((ET56*1.2))-((EU56*1.2)))+AE56),6) -> 0 | AE56: =ROUND(((EU56*1.2)),6) -> 0 | AF56: =ROUND(((EV56*1.2)),6) -> 384.276 | AG56: =ROUND((AP56),6) -> 0 | AH56: =((EW56*1.2)) -> 36.528 | AI56: =((EX56*1.2)) -> 0 | AJ56: =(AS56) -> 0 | AK56: 320.23 | AL56: 0 | AM56: 0 | AN56: 0 | AO56: 320.23 | AP56: 0 | AQ56: 30.44 | AR56: 0 | AS56: 0 | AT56: 91 | AU56: 48 | AV56: 1.047 | AW56: 1 | AZ56: 1 | BA56: 1 | BB56: 1 | BC56: 1 | BH56: 0 | BI56: 1 | BJ56: ТСН-2001.6. Доп. 1-42. Сб. 67, т. 5, поз. 12 | BM56: 106 | BN56: 0 | BO56: 6.67-5-12 | BP56: 1 | BQ56: 60 | BR56: 0 | BS56: 1 | BT56: 1 | BU56: 1 | BV56: 1 | BW56: 1 | BX56: 1 | BZ56: 91 | CA56: 48 | CE56: 1566 | CF56: 0 | CG56: 0 | CM56: 0 | CN56: Поправка: Гл.12.Прил.8.п.8. 3_12.00.01.11.001 Наименование: При наличии напряженных и стесненных условий производства работ (стесненность, сложность складирования и транспортной логистики и т.п.) для объектов, расположенных в пределах круговой магистральной системы улиц "Садовое кольцо" города Москвы | CO56: 0 | CP56: =(P56+Q56+S56) -> 18386.8 | CQ56: =ROUND((ROUND((AC56*AW56*1),2)*BC56),2) -> 0 | CR56: =(ROUND((ROUND((((ET56*1.2))*AV56*1),2)*BB56),2)+ROUND((ROUND(((AE56-((EU56*1.2)))*AV56*1),2)*BS56),2)) -> 0 | CS56: =(ROUND((ROUND((((EU56*1.2))*AV56*1),2)*BS56),2)+ROUND((ROUND(((AE56-((EU56*1.2)))*AV56*1),2)*BS56),2)) -> 0 | CT56: =ROUND((ROUND((AF56*AV56*1),2)*BA56),2) -> 402.34 | CU56: =AG56 -> 0 | CV56: =(AH56*AV56) -> 38.244816 | CW56: =AI56 -> 0 | CX56: =AJ56 -> 0 | CY56: =(ROUND((((S56+ROUND((ROUND((((EU56*1.2))*AV56*1),2)*BS56),2))*AT56)/100),2)+ROUND(((ROUND((ROUND(((AE56-((EU56*1.2)))*AV56*1),2)*BS56),2)*AT56)/100),2)) -> 16731.99 | CZ56: =(ROUND((((S56+ROUND((ROUND((((EU56*1.2))*AV56*1),2)*BS56),2))*AU56)/100),2)+ROUND(((ROUND((ROUND(((AE56-((EU56*1.2)))*AV56*1),2)*BS56),2)*AU56)/100),2)) -> 8825.66 | DB56: 53 | DD56: *1 | DE56: *1,2 | DF56: *1,2 | DG56: *1,2 | DI56: *1,2 | DJ56: *1,2 | DN56: 0 | DO56: 0 | DP56: 1 | DQ56: 1 | DU56: 1003 | DV56: 100 м | DW56: 100 м | DX56: 100 | EE56: 55393738 | EF56: 60 | EG56: Ремонтно-строительные работы | EH56: 0 | EJ56: 1 | EK56: 106 | EL56: ТСН-2001.6-67. Электромонтажные работы | EM56: ТСН-2001.6-67-1 | EO56: Поправка: Гл.12.Прил.8.п.8. 3_12.00.01.11.001 | EQ56: 0 | ER56: 320.23 | ES56: 0 | ET56: 0 | EU56: 0 | EV56: 320.23 | EW56: 30.44 | EX56: 0 | EY56: 0 | FQ56: 0 | FR56: 0 | FS56: 0 | FX56: 91 | FY56: 48 | GD56: 1 | GF56: -1403822920 | GG56: 2 | GH56: 1 | GI56: 2 | GJ56: 0 | GK56: 0 | GL56: =ROUND(IF(AND(BH56=3,BI56=3,FS56<>0),P56,0),2) -> 0 | GM56: =ROUND(O56+X56+Y56,2)+GX56 -> 43944.45 | GN56: =IF(OR(BI56=0,BI56=1),GM56-GX56,0) -> 43944.45 | GO56: =IF(BI56=2,GM56-GX56,0) -> 0 | GP56: =IF(BI56=4,GM56-GX56,0) -> 0 | GR56: 0 | GS56: 3 | GT56: 0 | GV56: =ROUND((GT56),6) -> 0 | GW56: 1 | GX56: =ROUND(HC56*I56,2) -> 0 | HA56: 0 | HB56: 0 | HC56: =GV56*GW56 -> 0 | HS56: 0 | IK56: 0
A57: 17 | B57: 1 | C57: =ROW(SmtRes!A164) -> 164 | D57: =ROW(EtalonRes!A210) -> 210 | E57: 15 | F57: 6.67-5-12 | G57: Демонтаж трубных проводок, трубы в борозде диаметром 25 мм / ПВХ | H57: 100 м | I57: =ROUND((2500+2000+70)/100,9) -> 45.7 | J57: 0 | K57: =ROUND((2500+2000+70)/100,9) -> 45.7 | O57: =ROUND(CP57,2) -> 1036096.2 | P57: =ROUND((ROUND((AC57*AW57*I57),2)*BC57),2) -> 0 | Q57: =(ROUND((ROUND((((ET57*1.2))*AV57*I57),2)*BB57),2)+ROUND((ROUND(((AE57-((EU57*1.2)))*AV57*I57),2)*BS57),2)) -> 0 | R57: =(ROUND((ROUND((((EU57*1.2))*AV57*I57),2)*BS57),2)+ROUND((ROUND(((AE57-((EU57*1.2)))*AV57*I57),2)*BS57),2)) -> 0 | S57: =ROUND((ROUND((AF57*AV57*I57),2)*BA57),2) -> 1036096.2 | T57: =ROUND(CU57*I57,2) -> 0 | U57: =CV57*I57 -> 1747.7881 | V57: =CW57*I57 -> 0 | W57: =ROUND(CX57*I57,2) -> 0 | X57: =(ROUND((((S57+ROUND((ROUND((((EU57*1.2))*AV57*I57),2)*BS57),2))*AT57)/100),2)+ROUND(((ROUND((ROUND(((AE57-((EU57*1.2)))*AV57*I57),2)*BS57),2)*AT57)/100),2)) -> 942847.52 | Y57: =(ROUND((((S57+ROUND((ROUND((((EU57*1.2))*AV57*I57),2)*BS57),2))*AU57)/100),2)+ROUND(((ROUND((ROUND(((AE57-((EU57*1.2)))*AV57*I57),2)*BS57),2)*AU57)/100),2)) -> 497326.17 | AA57: 55929115 | AB57: =ROUND((AC57+AD57+AF57),6) -> 384.276 | AC57: =ROUND(((ES57*1)),6) -> 0 | AD57: =ROUND(((((ET57*1.2))-((EU57*1.2)))+AE57),6) -> 0 | AE57: =ROUND(((EU57*1.2)),6) -> 0 | AF57: =ROUND(((EV57*1.2)),6) -> 384.276 | AG57: =ROUND((AP57),6) -> 0 | AH57: =((EW57*1.2)) -> 36.528 | AI57: =((EX57*1.2)) -> 0 | AJ57: =(AS57) -> 0 | AK57: 320.23 | AL57: 0 | AM57: 0 | AN57: 0 | AO57: 320.23 | AP57: 0 | AQ57: 30.44 | AR57: 0 | AS57: 0 | AT57: 91 | AU57: 48 | AV57: 1.047 | AW57: 1 | AZ57: 1 | BA57: 56.35 | BB57: 1 | BC57: 1 | BH57: 0 | BI57: 1 | BJ57: ТСН-2001.6. Доп. 1-42. Сб. 67, т. 5, поз. 12 | BM57: 106 | BN57: 0 | BO57: 6.67-5-12 | BP57: 1 | BQ57: 60 | BR57: 0 | BS57: 56.35 | BT57: 1 | BU57: 1 | BV57: 1 | BW57: 1 | BX57: 1 | BZ57: 91 | CA57: 48 | CE57: 1566 | CF57: 0 | CG57: 0 | CM57: 0 | CN57: Поправка: Гл.12.Прил.8.п.8. 3_12.00.01.11.001 Наименование: При наличии напряженных и стесненных условий производства работ (стесненность, сложность складирования и транспортной логистики и т.п.) для объектов, расположенных в пределах круговой магистральной системы улиц "Садовое кольцо" города Москвы | CO57: 0 | CP57: =(P57+Q57+S57) -> 1036096.2 | CQ57: =ROUND((ROUND((AC57*AW57*1),2)*BC57),2) -> 0 | CR57: =(ROUND((ROUND((((ET57*1.2))*AV57*1),2)*BB57),2)+ROUND((ROUND(((AE57-((EU57*1.2)))*AV57*1),2)*BS57),2)) -> 0 | CS57: =(ROUND((ROUND((((EU57*1.2))*AV57*1),2)*BS57),2)+ROUND((ROUND(((AE57-((EU57*1.2)))*AV57*1),2)*BS57),2)) -> 0 | CT57: =ROUND((ROUND((AF57*AV57*1),2)*BA57),2) -> 22671.86 | CU57: =AG57 -> 0 | CV57: =(AH57*AV57) -> 38.244816 | CW57: =AI57 -> 0 | CX57: =AJ57 -> 0 | CY57: =(ROUND((((S57+ROUND((ROUND((((EU57*1.2))*AV57*1),2)*BS57),2))*AT57)/100),2)+ROUND(((ROUND((ROUND(((AE57-((EU57*1.2)))*AV57*1),2)*BS57),2)*AT57)/100),2)) -> 942847.52 | CZ57: =(ROUND((((S57+ROUND((ROUND((((EU57*1.2))*AV57*1),2)*BS57),2))*AU57)/100),2)+ROUND(((ROUND((ROUND(((AE57-((EU57*1.2)))*AV57*1),2)*BS57),2)*AU57)/100),2)) -> 497326.17 | DB57: 54 | DD57: *1 | DE57: *1,2 | DF57: *1,2 | DG57: *1,2 | DI57: *1,2 | DJ57: *1,2 | DN57: 0 | DO57: 0 | DP57: 1 | DQ57: 1 | DU57: 1003 | DV57: 100 м | DW57: 100 м | DX57: 100 | EE57: 55393738 | EF57: 60 | EG57: Ремонтно-строительные работы | EH57: 0 | EJ57: 1 | EK57: 106 | EL57: ТСН-2001.6-67. Электромонтажные работы | EM57: ТСН-2001.6-67-1 | EO57: Поправка: Гл.12.Прил.8.п.8. 3_12.00.01.11.001 | EQ57: 0 | ER57: 320.23 | ES57: 0 | ET57: 0 | EU57: 0 | EV57: 320.23 | EW57: 30.44 | EX57: 0 | EY57: 0 | FQ57: 0 | FR57: 0 | FS57: 0 | FX57: 91 | FY57: 48 | GD57: 1 | GF57: -1403822920 | GG57: 2 | GH57: 1 | GI57: 2 | GJ57: 0 | GK57: 0 | GL57: =ROUND(IF(AND(BH57=3,BI57=3,FS57<>0),P57,0),2) -> 0 | GM57: =ROUND(O57+X57+Y57,2)+GX57 -> 2476269.9 | GN57: =IF(OR(BI57=0,BI57=1),GM57-GX57,0) -> 2476269.9 | GO57: =IF(BI57=2,GM57-GX57,0) -> 0 | GP57: =IF(BI57=4,GM57-GX57,0) -> 0 | GR57: 0 | GS57: 3 | GT57: 0 | GV57: =ROUND((GT57),6) -> 0 | GW57: 1 | GX57: =ROUND(HC57*I57,2) -> 0 | HA57: 0 | HB57: 0 | HC57: =GV57*GW57 -> 0 | HS57: 0 | IK57: 0
A59: 51 | B59: =B24 -> 1 | C59: =A24 -> 4 | D59: =ROW(A24) -> 24 | F59: =IF(F24<>"",F24,"") -> Новый раздел | G59: =IF(G24<>"",G24,"") -> Демонтажные работы | H59: 0 | O59: =ROUND(AB59,2) -> 54097.66 | P59: =ROUND(AC59,2) -> 0 | Q59: =ROUND(AD59,2) -> 429.77 | R59: =ROUND(AE59,2) -> 48.08 | S59: =ROUND(AF59,2) -> 53667.89 | T59: =ROUND(AG59,2) -> 0 | U59: =AH59 -> 5166.3111 | V59: =AI59 -> 0 | W59: =ROUND(AJ59,2) -> 0 | X59: =ROUND(AK59,2) -> 48917.59 | Y59: =ROUND(AL59,2) -> 25783.03 | AB59: =ROUND(SUMIF(AA28:AA57,"=55929113",O28:O57),2) -> 54097.66 | AC59: =ROUND(SUMIF(AA28:AA57,"=55929113",P28:P57),2) -> 0 | AD59: =ROUND(SUMIF(AA28:AA57,"=55929113",Q28:Q57),2) -> 429.77 | AE59: =ROUND(SUMIF(AA28:AA57,"=55929113",R28:R57),2) -> 48.08 | AF59: =ROUND(SUMIF(AA28:AA57,"=55929113",S28:S57),2) -> 53667.89 | AG59: =ROUND(SUMIF(AA28:AA57,"=55929113",T28:T57),2) -> 0 | AH59: =SUMIF(AA28:AA57,"=55929113",U28:U57) -> 5166.3111 | AI59: =SUMIF(AA28:AA57,"=55929113",V28:V57) -> 0 | AJ59: =ROUND(SUMIF(AA28:AA57,"=55929113",W28:W57),2) -> 0 | AK59: =ROUND(SUMIF(AA28:AA57,"=55929113",X28:X57),2) -> 48917.59 | AL59: =ROUND(SUMIF(AA28:AA57,"=55929113",Y28:Y57),2) -> 25783.03 | AO59: =ROUND(BX59,2) -> 0 | AP59: =ROUND(BY59,2) -> 0 | AQ59: =ROUND(BZ59,2) -> 0 | AR59: =ROUND(CA59,2) -> 128798.28 | AS59: =ROUND(CB59,2) -> 123478.27 | AT59: =ROUND(CC59,2) -> 5320.01 | AU59: =ROUND(CD59,2) -> 0 | AV59: =ROUND(CE59,2) -> 0 | ... BD59: =ROUND(CM59,2) -> 0 | BX59: =ROUND(SUMIF(AA28:AA57,"=55929113",FQ28:FQ57),2) -> 0 | BY59: =ROUND(SUMIF(AA28:AA57,"=55929113",FR28:FR57),2) -> 0 | BZ59: =ROUND(SUMIF(AA28:AA57,"=55929113",GL28:GL57),2) -> 0 | CA59: =ROUND(SUMIF(AA28:AA57,"=55929113",GM28:GM57),2) -> 128798.28 | CB59: =ROUND(SUMIF(AA28:AA57,"=55929113",GN28:GN57),2) -> 123478.27 | CC59: =ROUND(SUMIF(AA28:AA57,"=55929113",GO28:GO57),2) -> 5320.01 | CD59: =ROUND(SUMIF(AA28:AA57,"=55929113",GP28:GP57),2) -> 0 | CE59: =AC59-BX59 -> 0 | CF59: =AC59-BY59 -> 0 | CG59: =BX59-BZ59 -> 0 | CH59: =AC59-BX59-BY59+BZ59 -> 0 | CI59: =BY59-BZ59 -> 0 | CJ59: =ROUND(SUMIF(AA28:AA57,"=55929113",GX28:GX57),2) -> 0 | CK59: =ROUND(SUMIF(AA28:AA57,"=55929113",GY28:GY57),2) -> 0 | CL59: =ROUND(SUMIF(AA28:AA57,"=55929113",GZ28:GZ57),2) -> 0 | CM59: =ROUND(SUMIF(AA28:AA57,"=55929113",HD28:HD57),2) -> 0 | DG59: =ROUND(DT59,2) -> 3031135.4 | DH59: =ROUND(DU59,2) -> 0 | DI59: =ROUND(DV59,2) -> 6949.81 | DJ59: =ROUND(DW59,2) -> 2709.31 | DK59: =ROUND(DX59,2) -> 3024185.6 | DL59: =ROUND(DY59,2) -> 0 | DM59: =DZ59 -> 5166.3111 | DN59: =EA59 -> 0 | DO59: =ROUND(EB59,2) -> 0 | DP59: =ROUND(EC59,2) -> 2756506.1 | DQ59: =ROUND(ED59,2) -> 1452874.5 | DT59: =ROUND(SUMIF(AA28:AA57,"=55929115",O28:O57),2) -> 3031135.4 | DU59: =ROUND(SUMIF(AA28:AA57,"=55929115",P28:P57),2) -> 0 | DV59: =ROUND(SUMIF(AA28:AA57,"=55929115",Q28:Q57),2) -> 6949.81 | DW59: =ROUND(SUMIF(AA28:AA57,"=55929115",R28:R57),2) -> 2709.31 | DX59: =ROUND(SUMIF(AA28:AA57,"=55929115",S28:S57),2) -> 3024185.6 | DY59: =ROUND(SUMIF(AA28:AA57,"=55929115",T28:T57),2) -> 0 | DZ59: =SUMIF(AA28:AA57,"=55929115",U28:U57) -> 5166.3111 | EA59: =SUMIF(AA28:AA57,"=55929115",V28:V57) -> 0 | EB59: =ROUND(SUMIF(AA28:AA57,"=55929115",W28:W57),2) -> 0 | EC59: =ROUND(SUMIF(AA28:AA57,"=55929115",X28:X57),2) -> 2756506.1 | ED59: =ROUND(SUMIF(AA28:AA57,"=55929115",Y28:Y57),2) -> 1452874.5 | EG59: =ROUND(FP59,2) -> 0 | EH59: =ROUND(FQ59,2) -> 0 | EI59: =ROUND(FR59,2) -> 0 | EJ59: =ROUND(FS59,2) -> 7240516 | EK59: =ROUND(FT59,2) -> 6958000.8 | EL59: =ROUND(FU59,2) -> 282515.28 | EM59: =ROUND(FV59,2) -> 0 | EN59: =ROUND(FW59,2) -> 0 | ... EV59: =ROUND(GE59,2) -> 0 | FP59: =ROUND(SUMIF(AA28:AA57,"=55929115",FQ28:FQ57),2) -> 0 | FQ59: =ROUND(SUMIF(AA28:AA57,"=55929115",FR28:FR57),2) -> 0 | FR59: =ROUND(SUMIF(AA28:AA57,"=55929115",GL28:GL57),2) -> 0 | FS59: =ROUND(SUMIF(AA28:AA57,"=55929115",GM28:GM57),2) -> 7240516 | FT59: =ROUND(SUMIF(AA28:AA57,"=55929115",GN28:GN57),2) -> 6958000.8 | FU59: =ROUND(SUMIF(AA28:AA57,"=55929115",GO28:GO57),2) -> 282515.28 | FV59: =ROUND(SUMIF(AA28:AA57,"=55929115",GP28:GP57),2) -> 0 | FW59: =DU59-FP59 -> 0 | FX59: =DU59-FQ59 -> 0 | FY59: =FP59-FR59 -> 0 | FZ59: =DU59-FP59-FQ59+FR59 -> 0 | GA59: =FQ59-FR59 -> 0 | GB59: =ROUND(SUMIF(AA28:AA57,"=55929115",GX28:GX57),2) -> 0 | GC59: =ROUND(SUMIF(AA28:AA57,"=55929115",GY28:GY57),2) -> 0 | GD59: =ROUND(SUMIF(AA28:AA57,"=55929115",GZ28:GZ57),2) -> 0 | GE59: =ROUND(SUMIF(AA28:AA57,"=55929115",HD28:HD57),2) -> 0 | GX59: 0
A61: 50 | B61: 0 | C61: 0 | D61: 1 | E61: 201 | F61: =ROUND(Source!O59,O61) -> 54097.66 | G61: ПЗ | H61: Прямые затраты | K61: 201 | L61: 1 | M61: 3 | O61: 2 | P61: =ROUND(Source!DG59,O61) -> 3031135.4 | W61: 54097.66 | X61: 1 | Y61: 54097.66 | Z61: 3031135.4 | AA61: 1 | AB61: 3031135.4
A62: 50 | B62: 0 | C62: 0 | D62: 1 | E62: 202 | F62: =ROUND(Source!P59,O62) -> 0 | G62: СтМатОб | H62: Стоимость материальных ресурсов (всего) | K62: 202 | L62: 2 | M62: 3 | O62: 2 | P62: =ROUND(Source!DH59,O62) -> 0 | W62: 0 | X62: 1 | Y62: 0 | Z62: 0 | AA62: 1 | AB62: 0
A63: 50 | B63: 0 | C63: 0 | D63: 1 | E63: 222 | F63: =ROUND(Source!AO59,O63) -> 0 | G63: СтМатОбЗак | H63: Стоимость материалов и оборудования заказчика | K63: 222 | L63: 3 | M63: 3 | O63: 2 | P63: =ROUND(Source!EG59,O63) -> 0 | W63: 0 | X63: 1 | Y63: 0 | Z63: 0 | AA63: 1 | AB63: 0
A64: 50 | B64: 0 | C64: 0 | D64: 1 | E64: 225 | F64: =ROUND(Source!AV59,O64) -> 0 | G64: СтМатОбПод | H64: Стоимость материалов и оборудования подрядчика | K64: 225 | L64: 4 | M64: 3 | O64: 2 | P64: =ROUND(Source!EN59,O64) -> 0 | W64: 0 | X64: 1 | Y64: 0 | Z64: 0 | AA64: 1 | AB64: 0
A65: 50 | B65: 0 | C65: 0 | D65: 1 | E65: 226 | F65: =ROUND(Source!AW59,O65) -> 0 | G65: СтМат | H65: Стоимость материалов (всего) | K65: 226 | L65: 5 | M65: 3 | O65: 2 | P65: =ROUND(Source!EO59,O65) -> 0 | W65: 0 | X65: 1 | Y65: 0 | Z65: 0 | AA65: 1 | AB65: 0
A66: 50 | B66: 0 | C66: 0 | D66: 1 | E66: 227 | F66: =ROUND(Source!AX59,O66) -> 0 | G66: СтМатЗак | H66: Стоимость материалов заказчика | K66: 227 | L66: 6 | M66: 3 | O66: 2 | P66: =ROUND(Source!EP59,O66) -> 0 | W66: 0 | X66: 1 | Y66: 0 | Z66: 0 | AA66: 1 | AB66: 0
A67: 50 | B67: 0 | C67: 0 | D67: 1 | E67: 228 | F67: =ROUND(Source!AY59,O67) -> 0 | G67: СтМатПод | H67: Стоимость материалов подрядчика | K67: 228 | L67: 7 | M67: 3 | O67: 2 | P67: =ROUND(Source!EQ59,O67) -> 0 | W67: 0 | X67: 1 | Y67: 0 | Z67: 0 | AA67: 1 | AB67: 0
A68: 50 | B68: 0 | C68: 0 | D68: 1 | E68: 216 | F68: =ROUND(Source!AP59,O68) -> 0 | G68: Оборуд | H68: Стоимость оборудования (всего) | K68: 216 | L68: 8 | M68: 3 | O68: 2 | P68: =ROUND(Source!EH59,O68) -> 0 | W68: 0 | X68: 1 | Y68: 0 | Z68: 0 | AA68: 1 | AB68: 0
A69: 50 | B69: 0 | C69: 0 | D69: 1 | E69: 223 | F69: =ROUND(Source!AQ59,O69) -> 0 | G69: ОборудЗак | H69: Стоимость оборудования заказчика | K69: 223 | L69: 9 | M69: 3 | O69: 2 | P69: =ROUND(Source!EI59,O69) -> 0 | W69: 0 | X69: 1 | Y69: 0 | Z69: 0 | AA69: 1 | AB69: 0
A70: 50 | B70: 0 | C70: 0 | D70: 1 | E70: 229 | F70: =ROUND(Source!AZ59,O70) -> 0 | G70: ОборудПод | H70: Стоимость оборудования подрядчика | K70: 229 | L70: 10 | M70: 3 | O70: 2 | P70: =ROUND(Source!ER59,O70) -> 0 | W70: 0 | X70: 1 | Y70: 0 | Z70: 0 | AA70: 1 | AB70: 0
A71: 50 | B71: 0 | C71: 0 | D71: 1 | E71: 203 | F71: =ROUND(Source!Q59,O71) -> 429.77 | G71: ЭММ | H71: Эксплуатация машин | K71: 203 | L71: 11 | M71: 3 | O71: 2 | P71: =ROUND(Source!DI59,O71) -> 6949.81 | W71: 429.77 | X71: 1 | Y71: 429.77 | Z71: 6949.81 | AA71: 1 | AB71: 6949.81
A72: 50 | B72: 0 | C72: 0 | D72: 1 | E72: 231 | F72: =ROUND(Source!BB59,O72) -> 0 | G72: ЭММсНРиСП | H72: Эксплуатация машин по ТСН-2001.16 | K72: 231 | L72: 12 | M72: 3 | O72: 2 | P72: =ROUND(Source!ET59,O72) -> 0 | W72: 0 | X72: 1 | Y72: 0 | Z72: 0 | AA72: 1 | AB72: 0
A73: 50 | B73: 0 | C73: 0 | D73: 1 | E73: 204 | F73: =ROUND(Source!R59,O73) -> 48.08 | G73: ЗПМ | H73: ЗП машинистов | K73: 204 | L73: 13 | M73: 3 | O73: 2 | P73: =ROUND(Source!DJ59,O73) -> 2709.31 | W73: 48.08 | X73: 1 | Y73: 48.08 | Z73: 2709.31 | AA73: 1 | AB73: 2709.31
A74: 50 | B74: 0 | C74: 0 | D74: 1 | E74: 205 | F74: =ROUND(Source!S59,O74) -> 53667.89 | G74: ОЗП | H74: Основная ЗП рабочих | K74: 205 | L74: 14 | M74: 3 | O74: 2 | P74: =ROUND(Source!DK59,O74) -> 3024185.6 | W74: 53667.89 | X74: 1 | Y74: 53667.89 | Z74: 3024185.6 | AA74: 1 | AB74: 3024185.6
A75: 50 | B75: 0 | C75: 0 | D75: 1 | E75: 232 | F75: =ROUND(Source!BC59,O75) -> 0 | G75: ОЗПсНРиСП | H75: Основная ЗП рабочих по ТСН-2001.16 | K75: 232 | L75: 15 | M75: 3 | O75: 2 | P75: =ROUND(Source!EU59,O75) -> 0 | W75: 0 | X75: 1 | Y75: 0 | Z75: 0 | AA75: 1 | AB75: 0
A76: 50 | B76: 0 | C76: 0 | D76: 1 | E76: 214 | F76: =ROUND(Source!AS59,O76) -> 123478.27 | G76: Строит | H76: Строительные работы с НР и СП | K76: 214 | L76: 16 | M76: 3 | O76: 2 | P76: =ROUND(Source!EK59,O76) -> 6958000.8 | W76: 123478.27 | X76: 1 | Y76: 123478.27 | Z76: 6958000.8 | AA76: 1 | AB76: 6958000.8
A77: 50 | B77: 0 | C77: 0 | D77: 1 | E77: 215 | F77: =ROUND(Source!AT59,O77) -> 5320.01 | G77: Монтаж | H77: Монтажные работы с НР и СП | K77: 215 | L77: 17 | M77: 3 | O77: 2 | P77: =ROUND(Source!EL59,O77) -> 282515.28 | W77: 5320.01 | X77: 1 | Y77: 5320.01 | Z77: 282515.28 | AA77: 1 | AB77: 282515.28
A78: 50 | B78: 0 | C78: 0 | D78: 1 | E78: 217 | F78: =ROUND(Source!AU59,O78) -> 0 | G78: Прочие | H78: Прочие работы с НР и СП | K78: 217 | L78: 18 | M78: 3 | O78: 2 | P78: =ROUND(Source!EM59,O78) -> 0 | W78: 0 | X78: 1 | Y78: 0 | Z78: 0 | AA78: 1 | AB78: 0
A79: 50 | B79: 0 | C79: 0 | D79: 1 | E79: 230 | F79: =ROUND(Source!BA59,O79) -> 0 | G79: ПрочиеЗатр | H79: Прочие затраты по ТСН-2001.16 | K79: 230 | L79: 19 | M79: 3 | O79: 2 | P79: =ROUND(Source!ES59,O79) -> 0 | W79: 0 | X79: 1 | Y79: 0 | Z79: 0 | AA79: 1 | AB79: 0
A80: 50 | B80: 0 | C80: 0 | D80: 1 | E80: 206 | F80: =ROUND(Source!T59,O80) -> 0 | G80: ВозврМат | H80: Возврат материалов | K80: 206 | L80: 20 | M80: 3 | O80: 2 | P80: =ROUND(Source!DL59,O80) -> 0 | W80: 0 | X80: 1 | Y80: 0 | Z80: 0 | AA80: 1 | AB80: 0
A81: 50 | B81: 0 | C81: 0 | D81: 1 | E81: 207 | F81: =Source!U59 -> 5166.3111 | G81: ТрудСтр | H81: Трудозатраты строителей | K81: 207 | L81: 21 | M81: 3 | O81: -1 | P81: =Source!DM59 -> 5166.3111 | W81: 5166.3111 | X81: 1 | Y81: 5166.3111 | Z81: 5166.3111 | AA81: 1 | AB81: 5166.3111
A82: 50 | B82: 0 | C82: 0 | D82: 1 | E82: 208 | F82: =Source!V59 -> 0 | G82: ТрудМаш | H82: Трудозатраты машинистов | K82: 208 | L82: 22 | M82: 3 | O82: -1 | P82: =Source!DN59 -> 0 | W82: 0 | X82: 1 | Y82: 0 | Z82: 0 | AA82: 1 | AB82: 0
A83: 50 | B83: 0 | C83: 0 | D83: 1 | E83: 209 | F83: =ROUND(Source!W59,O83) -> 0 | G83: ТранспМат | H83: Транспорт материалов | K83: 209 | L83: 23 | M83: 3 | O83: 2 | P83: =ROUND(Source!DO59,O83) -> 0 | W83: 0 | X83: 1 | Y83: 0 | Z83: 0 | AA83: 1 | AB83: 0
A84: 50 | B84: 0 | C84: 0 | D84: 1 | E84: 233 | F84: =ROUND(Source!BD59,O84) -> 0 | G84: Перевозка | H84: Перевозка грузов | K84: 233 | L84: 24 | M84: 3 | O84: 2 | P84: =ROUND(Source!EV59,O84) -> 0 | W84: 0 | X84: 1 | Y84: 0 | Z84: 0 | AA84: 1 | AB84: 0
A85: 50 | B85: 0 | C85: 0 | D85: 1 | E85: 210 | F85: =ROUND(Source!X59,O85) -> 48917.59 | G85: НР | H85: Накладные расходы | K85: 210 | L85: 25 | M85: 3 | O85: 2 | P85: =ROUND(Source!DP59,O85) -> 2756506.1 | W85: 48917.59 | X85: 1 | Y85: 48917.59 | Z85: 2756506.1 | AA85: 1 | AB85: 2756506.1
A86: 50 | B86: 0 | C86: 0 | D86: 1 | E86: 211 | F86: =ROUND(Source!Y59,O86) -> 25783.03 | G86: СмПриб | H86: Сметная прибыль | K86: 211 | L86: 26 | M86: 3 | O86: 2 | P86: =ROUND(Source!DQ59,O86) -> 1452874.5 | W86: 25783.03 | X86: 1 | Y86: 25783.03 | Z86: 1452874.5 | AA86: 1 | AB86: 1452874.5
A87: 50 | B87: 0 | C87: 0 | D87: 1 | E87: 224 | F87: =ROUND(Source!AR59,O87) -> 128798.28 | G87: Всего | H87: Всего с НР и СП | K87: 224 | L87: 27 | M87: 3 | O87: 2 | P87: =ROUND(Source!EJ59,O87) -> 7240516 | W87: 128798.28 | X87: 1 | Y87: 128798.28 | Z87: 7240516 | AA87: 1 | AB87: 7240516
A89: 4 | B89: 1 | D89: =ROW(A216) -> 216 | F89: 1 | G89: Центральное оборудование | I89: 0 | K89: -1 | S89: 0 | T89: 0 | V89: 0 | BX89: 0 | CJ89: 0
A91: 52 | B91: =B216 -> 1 | C91: =C216 -> 4 | D91: =D216 -> 89 | E91: =E216 -> 0 | F91: =F216 -> 1 | G91: =G216 -> Центральное оборудование | O91: =O216 -> 617708.57 | P91: =P216 -> 610594.64 | Q91: =Q216 -> 1658.98 | R91: =R216 -> 184.46 | S91: =S216 -> 5454.95 | T91: =T216 -> 0 | U91: =U216 -> 427.34512 | V91: =V216 -> 0 | ... GX91: =GX216 -> 0
A93: 17 | B93: 1 | C93: =ROW(SmtRes!A168) -> 168 | D93: =ROW(EtalonRes!A215) -> 215 | E93: 16 | F93: 4.10-34-5 | G93: Монтаж коммутатора служебной связи | H93: 1 ШТ. | I93: =ROUND(5+3,9) -> 8 | J93: 0 | K93: =ROUND(5+3,9) -> 8 | O93: =ROUND(CP93,2) -> 1173.78 | P93: =ROUND((ROUND((AC93*AW93*I93),2)*BC93),2) -> 98.8 | Q93: =(ROUND((ROUND((((ET93*1.2))*AV93*I93),2)*BB93),2)+ROUND((ROUND(((AE93-((EU93*1.2)))*AV93*I93),2)*BS93),2)) -> 288.57 | R93: =(ROUND((ROUND((((EU93*1.2))*AV93*I93),2)*BS93),2)+ROUND((ROUND(((AE93-((EU93*1.2)))*AV93*I93),2)*BS93),2)) -> 31.76 | S93: =ROUND((ROUND((AF93*AV93*I93),2)*BA93),2) -> 786.41 | T93: =ROUND(CU93*I93,2) -> 0 | U93: =CV93*I93 -> 62.31744 | V93: =CW93*I93 -> 0 | W93: =ROUND(CX93*I93,2) -> 0 | X93: =(ROUND((((S93+ROUND((ROUND((((EU93*1.2))*AV93*I93),2)*BS93),2))*AT93)/100),2)+ROUND(((ROUND((ROUND(((AE93-((EU93*1.2)))*AV93*I93),2)*BS93),2)*AT93)/100),2)) -> 736.35 | Y93: =(ROUND((((S93+ROUND((ROUND((((EU93*1.2))*AV93*I93),2)*BS93),2))*AU93)/100),2)+ROUND(((ROUND((ROUND(((AE93-((EU93*1.2)))*AV93*I93),2)*BS93),2)*AU93)/100),2)) -> 376.36 | AA93: 55929113 | AB93: =ROUND((AC93+AD93+AF93),6) -> 140.69 | AC93: =ROUND(((ES93*1)),6) -> 12.35 | AD93: =ROUND(((((ET93*1.2))-((EU93*1.2)))+AE93),6) -> 34.452 | AE93: =ROUND(((EU93*1.2)),6) -> 3.792 | AF93: =ROUND(((EV93*1.2)),6) -> 93.888 | AG93: =ROUND((AP93),6) -> 0 | AH93: =((EW93*1.2)) -> 7.44 | AI93: =((EX93*1.2)) -> 0 | AJ93: =(AS93) -> 0 | AK93: 119.3 | AL93: 12.35 | AM93: 28.71 | AN93: 3.16 | AO93: 78.24 | AP93: 0 | AQ93: 6.2 | AR93: 0 | AS93: 0 | AT93: 90 | AU93: 46 | AV93: 1.047 | AW93: 1 | AZ93: 1 | BA93: 1 | BB93: 1 | BC93: 1 | BH93: 0 | BI93: 2 | BJ93: ТСН-2001.4 Доп. 80, Сб. 10, т. 34, поз. 5 | BM93: 68 | BN93: 0 | BO93: 4.10-34-5 | BP93: 1 | BQ93: 40 | BR93: 0 | BS93: 1 | BT93: 1 | BU93: 1 | BV93: 1 | BW93: 1 | BX93: 1 | BZ93: 90 | CA93: 46 | CE93: 1566 | CF93: 0 | CG93: 0 | CM93: 0 | CN93: Поправка: Гл.12.Прил.8.п.8. 3_12.00.01.11.001 Наименование: При наличии напряженных и стесненных условий производства работ (стесненность, сложность складирования и транспортной логистики и т.п.) для объектов, расположенных в пределах круговой магистральной системы улиц "Садовое кольцо" города Москвы | CO93: 0 | CP93: =(P93+Q93+S93) -> 1173.78 | CQ93: =ROUND((ROUND((AC93*AW93*1),2)*BC93),2) -> 12.35 | CR93: =(ROUND((ROUND((((ET93*1.2))*AV93*1),2)*BB93),2)+ROUND((ROUND(((AE93-((EU93*1.2)))*AV93*1),2)*BS93),2)) -> 36.07 | CS93: =(ROUND((ROUND((((EU93*1.2))*AV93*1),2)*BS93),2)+ROUND((ROUND(((AE93-((EU93*1.2)))*AV93*1),2)*BS93),2)) -> 3.97 | CT93: =ROUND((ROUND((AF93*AV93*1),2)*BA93),2) -> 98.3 | CU93: =AG93 -> 0 | CV93: =(AH93*AV93) -> 7.78968 | CW93: =AI93 -> 0 | CX93: =AJ93 -> 0 | CY93: =(ROUND((((S93+ROUND((ROUND((((EU93*1.2))*AV93*1),2)*BS93),2))*AT93)/100),2)+ROUND(((ROUND((ROUND(((AE93-((EU93*1.2)))*AV93*1),2)*BS93),2)*AT93)/100),2)) -> 711.34 | CZ93: =(ROUND((((S93+ROUND((ROUND((((EU93*1.2))*AV93*1),2)*BS93),2))*AU93)/100),2)+ROUND(((ROUND((ROUND(((AE93-((EU93*1.2)))*AV93*1),2)*BS93),2)*AU93)/100),2)) -> 363.57 | DB93: 55 | DD93: *1 | DE93: *1,2 | DF93: *1,2 | DG93: *1,2 | DI93: *1,2 | DJ93: *1,2 | DN93: 0 | DO93: 0 | DP93: 1 | DQ93: 1 | DU93: 1013 | DV93: 1 ШТ. | DW93: 1 ШТ. | DX93: 1 | EE93: 55393700 | EF93: 40 | EG93: Монтаж оборудования | EH93: 0 | EJ93: 2 | EK93: 68 | EL93: ТСН-2001.4-10. Прокладка и монтаж сетей связи | EM93: ТСН-2001.4-10-1 | EO93: Поправка: Гл.12.Прил.8.п.8. 3_12.00.01.11.001 | EQ93: 0 | ER93: 119.3 | ES93: 12.35 | ET93: 28.71 | EU93: 3.16 | EV93: 78.24 | EW93: 6.2 | EX93: 0 | EY93: 0 | FQ93: 0 | FR93: 0 | FS93: 0 | FX93: 90 | FY93: 46 | GD93: 1 | GF93: 982292204 | GG93: 2 | GH93: 1 | GI93: 2 | GJ93: 0 | GK93: 0 | GL93: =ROUND(IF(AND(BH93=3,BI93=3,FS93<>0),P93,0),2) -> 0 | GM93: =ROUND(O93+X93+Y93,2)+GX93 -> 2286.49 | GN93: =IF(OR(BI93=0,BI93=1),GM93-GX93,0) -> 0 | GO93: =IF(BI93=2,GM93-GX93,0) -> 2286.49 | GP93: =IF(BI93=4,GM93-GX93,0) -> 0 | GR93: 0 | GS93: 3 | GT93: 0 | GV93: =ROUND((GT93),6) -> 0 | GW93: 1 | GX93: =ROUND(HC93*I93,2) -> 0 | HA93: 0 | HB93: 0 | HC93: =GV93*GW93 -> 0 | HS93: 0 | IK93: 0
A94: 17 | B94: 1 | C94: =ROW(SmtRes!A172) -> 172 | D94: =ROW(EtalonRes!A220) -> 220 | E94: 16 | F94: 4.10-34-5 | G94: Монтаж коммутатора служебной связи | H94: 1 ШТ. | I94: =ROUND(5+3,9) -> 8 | J94: 0 | K94: =ROUND(5+3,9) -> 8 | O94: =ROUND(CP94,2) -> 50429.85 | P94: =ROUND((ROUND((AC94*AW94*I94),2)*BC94),2) -> 1452.36 | Q94: =(ROUND((ROUND((((ET94*1.2))*AV94*I94),2)*BB94),2)+ROUND((ROUND(((AE94-((EU94*1.2)))*AV94*I94),2)*BS94),2)) -> 4663.29 | R94: =(ROUND((ROUND((((EU94*1.2))*AV94*I94),2)*BS94),2)+ROUND((ROUND(((AE94-((EU94*1.2)))*AV94*I94),2)*BS94),2)) -> 1789.68 | S94: =ROUND((ROUND((AF94*AV94*I94),2)*BA94),2) -> 44314.2 | T94: =ROUND(CU94*I94,2) -> 0 | U94: =CV94*I94 -> 62.31744 | V94: =CW94*I94 -> 0 | W94: =ROUND(CX94*I94,2) -> 0 | X94: =(ROUND((((S94+ROUND((ROUND((((EU94*1.2))*AV94*I94),2)*BS94),2))*AT94)/100),2)+ROUND(((ROUND((ROUND(((AE94-((EU94*1.2)))*AV94*I94),2)*BS94),2)*AT94)/100),2)) -> 41493.49 | Y94: =(ROUND((((S94+ROUND((ROUND((((EU94*1.2))*AV94*I94),2)*BS94),2))*AU94)/100),2)+ROUND(((ROUND((ROUND(((AE94-((EU94*1.2)))*AV94*I94),2)*BS94),2)*AU94)/100),2)) -> 21207.78 | AA94: 55929115 | AB94: =ROUND((AC94+AD94+AF94),6) -> 140.69 | AC94: =ROUND(((ES94*1)),6) -> 12.35 | AD94: =ROUND(((((ET94*1.2))-((EU94*1.2)))+AE94),6) -> 34.452 | AE94: =ROUND(((EU94*1.2)),6) -> 3.792 | AF94: =ROUND(((EV94*1.2)),6) -> 93.888 | AG94: =ROUND((AP94),6) -> 0 | AH94: =((EW94*1.2)) -> 7.44 | AI94: =((EX94*1.2)) -> 0 | AJ94: =(AS94) -> 0 | AK94: 119.3 | AL94: 12.35 | AM94: 28.71 | AN94: 3.16 | AO94: 78.24 | AP94: 0 | AQ94: 6.2 | AR94: 0 | AS94: 0 | AT94: 90 | AU94: 46 | AV94: 1.047 | AW94: 1 | AZ94: 1 | BA94: 56.35 | BB94: 16.16 | BC94: 14.7 | BH94: 0 | BI94: 2 | BJ94: ТСН-2001.4 Доп. 80, Сб. 10, т. 34, поз. 5 | BM94: 68 | BN94: 0 | BO94: 4.10-34-5 | BP94: 1 | BQ94: 40 | BR94: 0 | BS94: 56.35 | BT94: 1 | BU94: 1 | BV94: 1 | BW94: 1 | BX94: 1 | BZ94: 90 | CA94: 46 | CE94: 1566 | CF94: 0 | CG94: 0 | CM94: 0 | CN94: Поправка: Гл.12.Прил.8.п.8. 3_12.00.01.11.001 Наименование: При наличии напряженных и стесненных условий производства работ (стесненность, сложность складирования и транспортной логистики и т.п.) для объектов, расположенных в пределах круговой магистральной системы улиц "Садовое кольцо" города Москвы | CO94: 0 | CP94: =(P94+Q94+S94) -> 50429.85 | CQ94: =ROUND((ROUND((AC94*AW94*1),2)*BC94),2) -> 181.55 | CR94: =(ROUND((ROUND((((ET94*1.2))*AV94*1),2)*BB94),2)+ROUND((ROUND(((AE94-((EU94*1.2)))*AV94*1),2)*BS94),2)) -> 582.89 | CS94: =(ROUND((ROUND((((EU94*1.2))*AV94*1),2)*BS94),2)+ROUND((ROUND(((AE94-((EU94*1.2)))*AV94*1),2)*BS94),2)) -> 223.71 | CT94: =ROUND((ROUND((AF94*AV94*1),2)*BA94),2) -> 5539.21 | CU94: =AG94 -> 0 | CV94: =(AH94*AV94) -> 7.78968 | CW94: =AI94 -> 0 | CX94: =AJ94 -> 0 | CY94: =(ROUND((((S94+ROUND((ROUND((((EU94*1.2))*AV94*1),2)*BS94),2))*AT94)/100),2)+ROUND(((ROUND((ROUND(((AE94-((EU94*1.2)))*AV94*1),2)*BS94),2)*AT94)/100),2)) -> 40084.12 | CZ94: =(ROUND((((S94+ROUND((ROUND((((EU94*1.2))*AV94*1),2)*BS94),2))*AU94)/100),2)+ROUND(((ROUND((ROUND(((AE94-((EU94*1.2)))*AV94*1),2)*BS94),2)*AU94)/100),2)) -> 20487.44 | DB94: 56 | DD94: *1 | DE94: *1,2 | DF94: *1,2 | DG94: *1,2 | DI94: *1,2 | DJ94: *1,2 | DN94: 0 | DO94: 0 | DP94: 1 | DQ94: 1 | DU94: 1013 | DV94: 1 ШТ. | DW94: 1 ШТ. | DX94: 1 | EE94: 55393700 | EF94: 40 | EG94: Монтаж оборудования | EH94: 0 | EJ94: 2 | EK94: 68 | EL94: ТСН-2001.4-10. Прокладка и монтаж сетей связи | EM94: ТСН-2001.4-10-1 | EO94: Поправка: Гл.12.Прил.8.п.8. 3_12.00.01.11.001 | EQ94: 0 | ER94: 119.3 | ES94: 12.35 | ET94: 28.71 | EU94: 3.16 | EV94: 78.24 | EW94: 6.2 | EX94: 0 | EY94: 0 | FQ94: 0 | FR94: 0 | FS94: 0 | FX94: 90 | FY94: 46 | GD94: 1 | GF94: 982292204 | GG94: 2 | GH94: 1 | GI94: 2 | GJ94: 0 | GK94: 0 | GL94: =ROUND(IF(AND(BH94=3,BI94=3,FS94<>0),P94,0),2) -> 0 | GM94: =ROUND(O94+X94+Y94,2)+GX94 -> 113131.12 | GN94: =IF(OR(BI94=0,BI94=1),GM94-GX94,0) -> 0 | GO94: =IF(BI94=2,GM94-GX94,0) -> 113131.12 | GP94: =IF(BI94=4,GM94-GX94,0) -> 0 | GR94: 0 | GS94: 3 | GT94: 0 | GV94: =ROUND((GT94),6) -> 0 | GW94: 1 | GX94: =ROUND(HC94*I94,2) -> 0 | HA94: 0 | HB94: 0 | HC94: =GV94*GW94 -> 0 | HS94: 0 | IK94: 0
A95: 17 | B95: 1 | E95: 17 | F95: КА, п.1 | G95: Коммутатор доступа 48 портов 1000/100/10, 4 SFP+ MES2348B_AC | H95: ШТ | I95: 5 | J95: 0 | K95: 5 | O95: =ROUND(CP95,2) -> 158525.55 | P95: =ROUND((ROUND((AC95*AW95*I95),2)*BC95),2) -> 158525.55 | Q95: =(ROUND((ROUND(((ET95)*AV95*I95),2)*BB95),2)+ROUND((ROUND(((AE95-(EU95))*AV95*I95),2)*BS95),2)) -> 0 | R95: =(ROUND((ROUND(((EU95)*AV95*I95),2)*BS95),2)+ROUND((ROUND(((AE95-(EU95))*AV95*I95),2)*BS95),2)) -> 0 | S95: =ROUND((ROUND((AF95*AV95*I95),2)*BA95),2) -> 0 | T95: =ROUND(CU95*I95,2) -> 0 | U95: =CV95*I95 -> 0 | V95: =CW95*I95 -> 0 | W95: =ROUND(CX95*I95,2) -> 0 | X95: =(ROUND((((S95+ROUND((ROUND(((EU95)*AV95*I95),2)*BS95),2))*AT95)/100),2)+ROUND(((ROUND((ROUND(((AE95-(EU95))*AV95*I95),2)*BS95),2)*AT95)/100),2)) -> 0 | Y95: =(ROUND((((S95+ROUND((ROUND(((EU95)*AV95*I95),2)*BS95),2))*AU95)/100),2)+ROUND(((ROUND((ROUND(((AE95-(EU95))*AV95*I95),2)*BS95),2)*AU95)/100),2)) -> 0 | AA95: 55929113 | AB95: =ROUND((AC95+AD95+AF95),6) -> 31705.11 | AC95: =ROUND((ES95),6) -> 31705.11 | AD95: =ROUND((((ET95)-(EU95))+AE95),6) -> 0 | AE95: =ROUND((EU95),6) -> 0 | AF95: =ROUND((EV95),6) -> 0 | AG95: =ROUND((AP95),6) -> 0 | AH95: =(EW95) -> 0 | AI95: =(EX95) -> 0 | AJ95: =(AS95) -> 0 | AK95: 31705.11 | AL95: 31705.11 | AM95: 0 | AN95: 0 | AO95: 0 | AP95: 0 | AQ95: 0 | AR95: 0 | AS95: 0 | AT95: 0 | AU95: 0 | AV95: 1 | AW95: 1 | AZ95: 1 | BA95: 1 | BB95: 1 | BC95: 1 | BH95: 3 | BI95: 3 | BJ95: КА, п.1 | BM95: 400007 | BN95: 0 | BP95: 0 | BQ95: 214 | BR95: 0 | BS95: 1 | BT95: 1 | BU95: 1 | BV95: 1 | BW95: 1 | BX95: 1 | BZ95: 0 | CA95: 0 | CE95: 1566 | CF95: 0 | CG95: 0 | CM95: 0 | CO95: 0 | CP95: =(P95+Q95+S95) -> 158525.55 | CQ95: =ROUND((ROUND((AC95*AW95*1),2)*BC95),2) -> 31705.11 | CR95: =(ROUND((ROUND(((ET95)*AV95*1),2)*BB95),2)+ROUND((ROUND(((AE95-(EU95))*AV95*1),2)*BS95),2)) -> 0 | CS95: =(ROUND((ROUND(((EU95)*AV95*1),2)*BS95),2)+ROUND((ROUND(((AE95-(EU95))*AV95*1),2)*BS95),2)) -> 0 | CT95: =ROUND((ROUND((AF95*AV95*1),2)*BA95),2) -> 0 | CU95: =AG95 -> 0 | CV95: =(AH95*AV95) -> 0 | CW95: =AI95 -> 0 | CX95: =AJ95 -> 0 | CY95: =(ROUND((((S95+ROUND((ROUND(((EU95)*AV95*1),2)*BS95),2))*AT95)/100),2)+ROUND(((ROUND((ROUND(((AE95-(EU95))*AV95*1),2)*BS95),2)*AT95)/100),2)) -> 0 | CZ95: =(ROUND((((S95+ROUND((ROUND(((EU95)*AV95*1),2)*BS95),2))*AU95)/100),2)+ROUND(((ROUND((ROUND(((AE95-(EU95))*AV95*1),2)*BS95),2)*AU95)/100),2)) -> 0 | DN95: 0 | DO95: 0 | DP95: 1 | DQ95: 1 | DU95: 1013 | DV95: ШТ | DW95: ШТ | DX95: 1 | EE95: 55393630 | EF95: 214 | EG95: Оборудование, отсутствующие в СНБ | EH95: 0 | EJ95: 3 | EK95: 400007 | EL95: Оборудование, отсутствующие в СНБ | EM95: Оборуд. КА | EQ95: 16 | ER95: 0 | ES95: 31705.11 | ET95: 0 | EU95: 0 | EV95: 0 | EW95: 0 | EX95: 0 | EY95: 0 | FQ95: 0 | FR95: =P95 -> 158525.55 | FS95: 0 | FX95: 0 | FY95: 0 | GA95: [280 910 / 1,22 / 7,57] + 3% Трансп + 1,2% Заг.скл | GD95: 1 | GF95: -1938986092 | GG95: 2 | GH95: 4 | GI95: -2 | GJ95: 0 | GK95: 0 | GL95: =ROUND(IF(AND(BH95=3,BI95=3,FS95<>0),P95,0),2) -> 0 | GM95: =ROUND(O95+X95+Y95,2)+GX95 -> 158525.55 | GN95: =IF(OR(BI95=0,BI95=1),GM95-GX95,0) -> 0 | GO95: =IF(BI95=2,GM95-GX95,0) -> 0 | GP95: =IF(BI95=4,GM95-GX95,0) -> 0 | GR95: 1 | GS95: 2 | GT95: 0 | GV95: =ROUND((GT95),6) -> 0 | GW95: 1 | GX95: =ROUND(HC95*I95,2) -> 0 | HA95: 0 | HB95: 0 | HC95: =GV95*GW95 -> 0 | HE95: 3 | HF95: 1,2 | HS95: 0 | IK95: 0
A96: 17 | B96: 1 | E96: 17 | F96: КА, п.1 | G96: Коммутатор доступа 48 портов 1000/100/10, 4 SFP+ MES2348B_AC | H96: ШТ | I96: 5 | J96: 0 | K96: 5 | O96: =ROUND(CP96,2) -> 1200038.4 | P96: =ROUND((ROUND((AC96*AW96*I96),2)*BC96),2) -> 1200038.4 | Q96: =(ROUND((ROUND(((ET96)*AV96*I96),2)*BB96),2)+ROUND((ROUND(((AE96-(EU96))*AV96*I96),2)*BS96),2)) -> 0 | R96: =(ROUND((ROUND(((EU96)*AV96*I96),2)*BS96),2)+ROUND((ROUND(((AE96-(EU96))*AV96*I96),2)*BS96),2)) -> 0 | S96: =ROUND((ROUND((AF96*AV96*I96),2)*BA96),2) -> 0 | T96: =ROUND(CU96*I96,2) -> 0 | U96: =CV96*I96 -> 0 | V96: =CW96*I96 -> 0 | W96: =ROUND(CX96*I96,2) -> 0 | X96: =(ROUND((((S96+ROUND((ROUND(((EU96)*AV96*I96),2)*BS96),2))*AT96)/100),2)+ROUND(((ROUND((ROUND(((AE96-(EU96))*AV96*I96),2)*BS96),2)*AT96)/100),2)) -> 0 | Y96: =(ROUND((((S96+ROUND((ROUND(((EU96)*AV96*I96),2)*BS96),2))*AU96)/100),2)+ROUND(((ROUND((ROUND(((AE96-(EU96))*AV96*I96),2)*BS96),2)*AU96)/100),2)) -> 0 | AA96: 55929115 | AB96: =ROUND((AC96+AD96+AF96),6) -> 31705.11 | AC96: =ROUND((ES96),6) -> 31705.11 | AD96: =ROUND((((ET96)-(EU96))+AE96),6) -> 0 | AE96: =ROUND((EU96),6) -> 0 | AF96: =ROUND((EV96),6) -> 0 | AG96: =ROUND((AP96),6) -> 0 | AH96: =(EW96) -> 0 | AI96: =(EX96) -> 0 | AJ96: =(AS96) -> 0 | AK96: 31705.11 | AL96: 31705.11 | AM96: 0 | AN96: 0 | AO96: 0 | AP96: 0 | AQ96: 0 | AR96: 0 | AS96: 0 | AT96: 0 | AU96: 0 | AV96: 1 | AW96: 1 | AZ96: 1 | BA96: 1 | BB96: 1 | BC96: 7.57 | BH96: 3 | BI96: 3 | BJ96: КА, п.1 | BM96: 400007 | BN96: 0 | BP96: 0 | BQ96: 214 | BR96: 0 | BS96: 1 | BT96: 1 | BU96: 1 | BV96: 1 | BW96: 1 | BX96: 1 | BZ96: 0 | CA96: 0 | CE96: 1566 | CF96: 0 | CG96: 0 | CM96: 0 | CO96: 0 | CP96: =(P96+Q96+S96) -> 1200038.4 | CQ96: =ROUND((ROUND((AC96*AW96*1),2)*BC96),2) -> 240007.68 | CR96: =(ROUND((ROUND(((ET96)*AV96*1),2)*BB96),2)+ROUND((ROUND(((AE96-(EU96))*AV96*1),2)*BS96),2)) -> 0 | CS96: =(ROUND((ROUND(((EU96)*AV96*1),2)*BS96),2)+ROUND((ROUND(((AE96-(EU96))*AV96*1),2)*BS96),2)) -> 0 | CT96: =ROUND((ROUND((AF96*AV96*1),2)*BA96),2) -> 0 | CU96: =AG96 -> 0 | CV96: =(AH96*AV96) -> 0 | CW96: =AI96 -> 0 | CX96: =AJ96 -> 0 | CY96: =(ROUND((((S96+ROUND((ROUND(((EU96)*AV96*1),2)*BS96),2))*AT96)/100),2)+ROUND(((ROUND((ROUND(((AE96-(EU96))*AV96*1),2)*BS96),2)*AT96)/100),2)) -> 0 | CZ96: =(ROUND((((S96+ROUND((ROUND(((EU96)*AV96*1),2)*BS96),2))*AU96)/100),2)+ROUND(((ROUND((ROUND(((AE96-(EU96))*AV96*1),2)*BS96),2)*AU96)/100),2)) -> 0 | DN96: 0 | DO96: 0 | DP96: 1 | DQ96: 1 | DU96: 1013 | DV96: ШТ | DW96: ШТ | DX96: 1 | EE96: 55393630 | EF96: 214 | EG96: Оборудование, отсутствующие в СНБ | EH96: 0 | EJ96: 3 | EK96: 400007 | EL96: Оборудование, отсутствующие в СНБ | EM96: Оборуд. КА | EQ96: 16 | ER96: 0 | ES96: 31705.11 | ET96: 0 | EU96: 0 | EV96: 0 | EW96: 0 | EX96: 0 | EY96: 0 | EZ96: 5 | FC96: 1 | FD96: 18 | FF96: 280910 | FQ96: 0 | FR96: =P96 -> 1200038.4 | FS96: 0 | FX96: 0 | FY96: 0 | GA96: [280 910 / 1,22 / 7,57] + 3% Трансп + 1,2% Заг.скл | GD96: 1 | GF96: -1938986092 | GG96: 2 | GH96: 3 | GI96: 5 | GJ96: 0 | GK96: 0 | GL96: =ROUND(IF(AND(BH96=3,BI96=3,FS96<>0),P96,0),2) -> 0 | GM96: =ROUND(O96+X96+Y96,2)+GX96 -> 1200038.4 | GN96: =IF(OR(BI96=0,BI96=1),GM96-GX96,0) -> 0 | GO96: =IF(BI96=2,GM96-GX96,0) -> 0 | GP96: =IF(BI96=4,GM96-GX96,0) -> 0 | GR96: 1 | GS96: 1 | GT96: 0 | GV96: =ROUND((GT96),6) -> 0 | GW96: 1 | GX96: =ROUND(HC96*I96,2) -> 0 | HA96: 0 | HB96: 0 | HC96: =GV96*GW96 -> 0 | HE96: 3 | HF96: 1,2 | HS96: 0 | IK96: 0
A97: 17 | B97: 1 | E97: 18 | F97: КА, п.2 | G97: Коммутатор доступа 48 портов 1000/100/10, 4 SFP+, РоЕ MES2348P | H97: ШТ | I97: 3 | J97: 0 | K97: 3 | O97: =ROUND(CP97,2) -> 196059.93 | P97: =ROUND((ROUND((AC97*AW97*I97),2)*BC97),2) -> 196059.93 | Q97: =(ROUND((ROUND(((ET97)*AV97*I97),2)*BB97),2)+ROUND((ROUND(((AE97-(EU97))*AV97*I97),2)*BS97),2)) -> 0 | R97: =(ROUND((ROUND(((EU97)*AV97*I97),2)*BS97),2)+ROUND((ROUND(((AE97-(EU97))*AV97*I97),2)*BS97),2)) -> 0 | S97: =ROUND((ROUND((AF97*AV97*I97),2)*BA97),2) -> 0 | T97: =ROUND(CU97*I97,2) -> 0 | U97: =CV97*I97 -> 0 | V97: =CW97*I97 -> 0 | W97: =ROUND(CX97*I97,2) -> 0 | X97: =(ROUND((((S97+ROUND((ROUND(((EU97)*AV97*I97),2)*BS97),2))*AT97)/100),2)+ROUND(((ROUND((ROUND(((AE97-(EU97))*AV97*I97),2)*BS97),2)*AT97)/100),2)) -> 0 | Y97: =(ROUND((((S97+ROUND((ROUND(((EU97)*AV97*I97),2)*BS97),2))*AU97)/100),2)+ROUND(((ROUND((ROUND(((AE97-(EU97))*AV97*I97),2)*BS97),2)*AU97)/100),2)) -> 0 | AA97: 55929113 | AB97: =ROUND((AC97+AD97+AF97),6) -> 65353.31 | AC97: =ROUND((ES97),6) -> 65353.31 | AD97: =ROUND((((ET97)-(EU97))+AE97),6) -> 0 | AE97: =ROUND((EU97),6) -> 0 | AF97: =ROUND((EV97),6) -> 0 | AG97: =ROUND((AP97),6) -> 0 | AH97: =(EW97) -> 0 | AI97: =(EX97) -> 0 | AJ97: =(AS97) -> 0 | AK97: 65353.31 | AL97: 65353.31 | AM97: 0 | AN97: 0 | AO97: 0 | AP97: 0 | AQ97: 0 | AR97: 0 | AS97: 0 | AT97: 0 | AU97: 0 | AV97: 1 | AW97: 1 | AZ97: 1 | BA97: 1 | BB97: 1 | BC97: 1 | BH97: 3 | BI97: 3 | BJ97: КА, п.2 | BM97: 400007 | BN97: 0 | BP97: 0 | BQ97: 214 | BR97: 0 | BS97: 1 | BT97: 1 | BU97: 1 | BV97: 1 | BW97: 1 | BX97: 1 | BZ97: 0 | CA97: 0 | CE97: 1566 | CF97: 0 | CG97: 0 | CM97: 0 | CO97: 0 | CP97: =(P97+Q97+S97) -> 196059.93 | CQ97: =ROUND((ROUND((AC97*AW97*1),2)*BC97),2) -> 65353.31 | CR97: =(ROUND((ROUND(((ET97)*AV97*1),2)*BB97),2)+ROUND((ROUND(((AE97-(EU97))*AV97*1),2)*BS97),2)) -> 0 | CS97: =(ROUND((ROUND(((EU97)*AV97*1),2)*BS97),2)+ROUND((ROUND(((AE97-(EU97))*AV97*1),2)*BS97),2)) -> 0 | CT97: =ROUND((ROUND((AF97*AV97*1),2)*BA97),2) -> 0 | CU97: =AG97 -> 0 | CV97: =(AH97*AV97) -> 0 | CW97: =AI97 -> 0 | CX97: =AJ97 -> 0 | CY97: =(ROUND((((S97+ROUND((ROUND(((EU97)*AV97*1),2)*BS97),2))*AT97)/100),2)+ROUND(((ROUND((ROUND(((AE97-(EU97))*AV97*1),2)*BS97),2)*AT97)/100),2)) -> 0 | CZ97: =(ROUND((((S97+ROUND((ROUND(((EU97)*AV97*1),2)*BS97),2))*AU97)/100),2)+ROUND(((ROUND((ROUND(((AE97-(EU97))*AV97*1),2)*BS97),2)*AU97)/100),2)) -> 0 | DN97: 0 | DO97: 0 | DP97: 1 | DQ97: 1 | DU97: 1013 | DV97: ШТ | DW97: ШТ | DX97: 1 | EE97: 55393630 | EF97: 214 | EG97: Оборудование, отсутствующие в СНБ | EH97: 0 | EJ97: 3 | EK97: 400007 | EL97: Оборудование, отсутствующие в СНБ | EM97: Оборуд. КА | EQ97: 16 | ER97: 0 | ES97: 65353.31 | ET97: 0 | EU97: 0 | EV97: 0 | EW97: 0 | EX97: 0 | EY97: 0 | FQ97: 0 | FR97: =P97 -> 196059.93 | FS97: 0 | FX97: 0 | FY97: 0 | GA97: [579 036 / 1,22 / 7,57] + 3% Трансп + 1,2% Заг.скл | GD97: 1 | GF97: -250941930 | GG97: 2 | GH97: 4 | GI97: -2 | GJ97: 0 | GK97: 0 | GL97: =ROUND(IF(AND(BH97=3,BI97=3,FS97<>0),P97,0),2) -> 0 | GM97: =ROUND(O97+X97+Y97,2)+GX97 -> 196059.93 | GN97: =IF(OR(BI97=0,BI97=1),GM97-GX97,0) -> 0 | GO97: =IF(BI97=2,GM97-GX97,0) -> 0 | GP97: =IF(BI97=4,GM97-GX97,0) -> 0 | GR97: 1 | GS97: 2 | GT97: 0 | GV97: =ROUND((GT97),6) -> 0 | GW97: 1 | GX97: =ROUND(HC97*I97,2) -> 0 | HA97: 0 | HB97: 0 | HC97: =GV97*GW97 -> 0 | HE97: 3 | HF97: 1,2 | HS97: 0 | IK97: 0
A98: 17 | B98: 1 | E98: 18 | F98: КА, п.2 | G98: Коммутатор доступа 48 портов 1000/100/10, 4 SFP+, РоЕ MES2348P | H98: ШТ | I98: 3 | J98: 0 | K98: 3 | O98: =ROUND(CP98,2) -> 1484173.7 | P98: =ROUND((ROUND((AC98*AW98*I98),2)*BC98),2) -> 1484173.7 | Q98: =(ROUND((ROUND(((ET98)*AV98*I98),2)*BB98),2)+ROUND((ROUND(((AE98-(EU98))*AV98*I98),2)*BS98),2)) -> 0 | R98: =(ROUND((ROUND(((EU98)*AV98*I98),2)*BS98),2)+ROUND((ROUND(((AE98-(EU98))*AV98*I98),2)*BS98),2)) -> 0 | S98: =ROUND((ROUND((AF98*AV98*I98),2)*BA98),2) -> 0 | T98: =ROUND(CU98*I98,2) -> 0 | U98: =CV98*I98 -> 0 | V98: =CW98*I98 -> 0 | W98: =ROUND(CX98*I98,2) -> 0 | X98: =(ROUND((((S98+ROUND((ROUND(((EU98)*AV98*I98),2)*BS98),2))*AT98)/100),2)+ROUND(((ROUND((ROUND(((AE98-(EU98))*AV98*I98),2)*BS98),2)*AT98)/100),2)) -> 0 | Y98: =(ROUND((((S98+ROUND((ROUND(((EU98)*AV98*I98),2)*BS98),2))*AU98)/100),2)+ROUND(((ROUND((ROUND(((AE98-(EU98))*AV98*I98),2)*BS98),2)*AU98)/100),2)) -> 0 | AA98: 55929115 | AB98: =ROUND((AC98+AD98+AF98),6) -> 65353.31 | AC98: =ROUND((ES98),6) -> 65353.31 | AD98: =ROUND((((ET98)-(EU98))+AE98),6) -> 0 | AE98: =ROUND((EU98),6) -> 0 | AF98: =ROUND((EV98),6) -> 0 | AG98: =ROUND((AP98),6) -> 0 | AH98: =(EW98) -> 0 | AI98: =(EX98) -> 0 | AJ98: =(AS98) -> 0 | AK98: 65353.31 | AL98: 65353.31 | AM98: 0 | AN98: 0 | AO98: 0 | AP98: 0 | AQ98: 0 | AR98: 0 | AS98: 0 | AT98: 0 | AU98: 0 | AV98: 1 | AW98: 1 | AZ98: 1 | BA98: 1 | BB98: 1 | BC98: 7.57 | BH98: 3 | BI98: 3 | BJ98: КА, п.2 | BM98: 400007 | BN98: 0 | BP98: 0 | BQ98: 214 | BR98: 0 | BS98: 1 | BT98: 1 | BU98: 1 | BV98: 1 | BW98: 1 | BX98: 1 | BZ98: 0 | CA98: 0 | CE98: 1566 | CF98: 0 | CG98: 0 | CM98: 0 | CO98: 0 | CP98: =(P98+Q98+S98) -> 1484173.7 | CQ98: =ROUND((ROUND((AC98*AW98*1),2)*BC98),2) -> 494724.56 | CR98: =(ROUND((ROUND(((ET98)*AV98*1),2)*BB98),2)+ROUND((ROUND(((AE98-(EU98))*AV98*1),2)*BS98),2)) -> 0 | CS98: =(ROUND((ROUND(((EU98)*AV98*1),2)*BS98),2)+ROUND((ROUND(((AE98-(EU98))*AV98*1),2)*BS98),2)) -> 0 | CT98: =ROUND((ROUND((AF98*AV98*1),2)*BA98),2) -> 0 | CU98: =AG98 -> 0 | CV98: =(AH98*AV98) -> 0 | CW98: =AI98 -> 0 | CX98: =AJ98 -> 0 | CY98: =(ROUND((((S98+ROUND((ROUND(((EU98)*AV98*1),2)*BS98),2))*AT98)/100),2)+ROUND(((ROUND((ROUND(((AE98-(EU98))*AV98*1),2)*BS98),2)*AT98)/100),2)) -> 0 | CZ98: =(ROUND((((S98+ROUND((ROUND(((EU98)*AV98*1),2)*BS98),2))*AU98)/100),2)+ROUND(((ROUND((ROUND(((AE98-(EU98))*AV98*1),2)*BS98),2)*AU98)/100),2)) -> 0 | DN98: 0 | DO98: 0 | DP98: 1 | DQ98: 1 | DU98: 1013 | DV98: ШТ | DW98: ШТ | DX98: 1 | EE98: 55393630 | EF98: 214 | EG98: Оборудование, отсутствующие в СНБ | EH98: 0 | EJ98: 3 | EK98: 400007 | EL98: Оборудование, отсутствующие в СНБ | EM98: Оборуд. КА | EQ98: 16 | ER98: 0 | ES98: 65353.31 | ET98: 0 | EU98: 0 | EV98: 0 | EW98: 0 | EX98: 0 | EY98: 0 | EZ98: 5 | FC98: 1 | FD98: 18 | FF98: 579036 | FQ98: 0 | FR98: =P98 -> 1484173.7 | FS98: 0 | FX98: 0 | FY98: 0 | GA98: [579 036 / 1,22 / 7,57] + 3% Трансп + 1,2% Заг.скл | GD98: 1 | GF98: -250941930 | GG98: 2 | GH98: 3 | GI98: 5 | GJ98: 0 | GK98: 0 | GL98: =ROUND(IF(AND(BH98=3,BI98=3,FS98<>0),P98,0),2) -> 0 | GM98: =ROUND(O98+X98+Y98,2)+GX98 -> 1484173.7 | GN98: =IF(OR(BI98=0,BI98=1),GM98-GX98,0) -> 0 | GO98: =IF(BI98=2,GM98-GX98,0) -> 0 | GP98: =IF(BI98=4,GM98-GX98,0) -> 0 | GR98: 1 | GS98: 1 | GT98: 0 | GV98: =ROUND((GT98),6) -> 0 | GW98: 1 | GX98: =ROUND(HC98*I98,2) -> 0 | HA98: 0 | HB98: 0 | HC98: =GV98*GW98 -> 0 | HE98: 3 | HF98: 1,2 | HS98: 0 | IK98: 0
A99: 17 | B99: 1 | C99: =ROW(SmtRes!A187) -> 187 | D99: =ROW(EtalonRes!A236) -> 236 | E99: 19 | F99: 4.10-19-6 | G99: Монтаж отдельно устанавливаемого преобразователя или блока питания | H99: 1 ШТ. | I99: 6 | J99: 0 | K99: 6 | O99: =ROUND(CP99,2) -> 1700.38 | P99: =ROUND((ROUND((AC99*AW99*I99),2)*BC99),2) -> 334.8 | Q99: =(ROUND((ROUND((((ET99*1.2))*AV99*I99),2)*BB99),2)+ROUND((ROUND(((AE99-((EU99*1.2)))*AV99*I99),2)*BS99),2)) -> 346.24 | R99: =(ROUND((ROUND((((EU99*1.2))*AV99*I99),2)*BS99),2)+ROUND((ROUND(((AE99-((EU99*1.2)))*AV99*I99),2)*BS99),2)) -> 38.07 | S99: =ROUND((ROUND((AF99*AV99*I99),2)*BA99),2) -> 1019.34 | T99: =ROUND(CU99*I99,2) -> 0 | U99: =CV99*I99 -> 70.10712 | V99: =CW99*I99 -> 0 | W99: =ROUND(CX99*I99,2) -> 0 | X99: =(ROUND((((S99+ROUND((ROUND((((EU99*1.2))*AV99*I99),2)*BS99),2))*AT99)/100),2)+ROUND(((ROUND((ROUND(((AE99-((EU99*1.2)))*AV99*I99),2)*BS99),2)*AT99)/100),2)) -> 951.67 | Y99: =(ROUND((((S99+ROUND((ROUND((((EU99*1.2))*AV99*I99),2)*BS99),2))*AU99)/100),2)+ROUND(((ROUND((ROUND(((AE99-((EU99*1.2)))*AV99*I99),2)*BS99),2)*AU99)/100),2)) -> 486.41 | AA99: 55929113 | AB99: =ROUND((AC99+AD99+AF99),6) -> 273.18 | AC99: =ROUND(((ES99*1)),6) -> 55.8 | AD99: =ROUND(((((ET99*1.2))-((EU99*1.2)))+AE99),6) -> 55.116 | AE99: =ROUND(((EU99*1.2)),6) -> 6.06 | AF99: =ROUND(((EV99*1.2)),6) -> 162.264 | AG99: =ROUND((AP99),6) -> 0 | AH99: =((EW99*1.2)) -> 11.16 | AI99: =((EX99*1.2)) -> 0 | AJ99: =(AS99) -> 0 | AK99: 236.95 | AL99: 55.8 | AM99: 45.93 | AN99: 5.05 | AO99: 135.22 | AP99: 0 | AQ99: 9.3 | AR99: 0 | AS99: 0 | AT99: 90 | AU99: 46 | AV99: 1.047 | AW99: 1 | AZ99: 1 | BA99: 1 | BB99: 1 | BC99: 1 | BH99: 0 | BI99: 2 | BJ99: ТСН-2001.4 Доп. 70, Сб. 10, т. 19, поз. 6 | BM99: 68 | BN99: 0 | BO99: 4.10-19-6 | BP99: 1 | BQ99: 40 | BR99: 0 | BS99: 1 | BT99: 1 | BU99: 1 | BV99: 1 | BW99: 1 | BX99: 1 | BZ99: 90 | CA99: 46 | CE99: 1566 | CF99: 0 | CG99: 0 | CM99: 0 | CN99: Поправка: Гл.12.Прил.8.п.8. 3_12.00.01.11.001 Наименование: При наличии напряженных и стесненных условий производства работ (стесненность, сложность складирования и транспортной логистики и т.п.) для объектов, расположенных в пределах круговой магистральной системы улиц "Садовое кольцо" города Москвы | CO99: 0 | CP99: =(P99+Q99+S99) -> 1700.38 | CQ99: =ROUND((ROUND((AC99*AW99*1),2)*BC99),2) -> 55.8 | CR99: =(ROUND((ROUND((((ET99*1.2))*AV99*1),2)*BB99),2)+ROUND((ROUND(((AE99-((EU99*1.2)))*AV99*1),2)*BS99),2)) -> 57.71 | CS99: =(ROUND((ROUND((((EU99*1.2))*AV99*1),2)*BS99),2)+ROUND((ROUND(((AE99-((EU99*1.2)))*AV99*1),2)*BS99),2)) -> 6.34 | CT99: =ROUND((ROUND((AF99*AV99*1),2)*BA99),2) -> 169.89 | CU99: =AG99 -> 0 | CV99: =(AH99*AV99) -> 11.68452 | CW99: =AI99 -> 0 | CX99: =AJ99 -> 0 | CY99: =(ROUND((((S99+ROUND((ROUND((((EU99*1.2))*AV99*1),2)*BS99),2))*AT99)/100),2)+ROUND(((ROUND((ROUND(((AE99-((EU99*1.2)))*AV99*1),2)*BS99),2)*AT99)/100),2)) -> 923.11 | CZ99: =(ROUND((((S99+ROUND((ROUND((((EU99*1.2))*AV99*1),2)*BS99),2))*AU99)/100),2)+ROUND(((ROUND((ROUND(((AE99-((EU99*1.2)))*AV99*1),2)*BS99),2)*AU99)/100),2)) -> 471.81 | DB99: 57 | DD99: *1 | DE99: *1,2 | DF99: *1,2 | DG99: *1,2 | DI99: *1,2 | DJ99: *1,2 | DN99: 0 | DO99: 0 | DP99: 1 | DQ99: 1 | DU99: 1013 | DV99: 1 ШТ. | DW99: 1 ШТ. | DX99: 1 | EE99: 55393700 | EF99: 40 | EG99: Монтаж оборудования | EH99: 0 | EJ99: 2 | EK99: 68 | EL99: ТСН-2001.4-10. Прокладка и монтаж сетей связи | EM99: ТСН-2001.4-10-1 | EO99: Поправка: Гл.12.Прил.8.п.8. 3_12.00.01.11.001 | EQ99: 0 | ER99: 236.95 | ES99: 55.8 | ET99: 45.93 | EU99: 5.05 | EV99: 135.22 | EW99: 9.3 | EX99: 0 | EY99: 0 | FQ99: 0 | FR99: 0 | FS99: 0 | FX99: 90 | FY99: 46 | GD99: 1 | GF99: 1573787508 | GG99: 2 | GH99: 1 | GI99: 2 | GJ99: 0 | GK99: 0 | GL99: =ROUND(IF(AND(BH99=3,BI99=3,FS99<>0),P99,0),2) -> 0 | GM99: =ROUND(O99+X99+Y99,2)+GX99 -> 3138.46 | GN99: =IF(OR(BI99=0,BI99=1),GM99-GX99,0) -> 0 | GO99: =IF(BI99=2,GM99-GX99,0) -> 3138.46 | GP99: =IF(BI99=4,GM99-GX99,0) -> 0 | GR99: 0 | GS99: 3 | GT99: 0 | GV99: =ROUND((GT99),6) -> 0 | GW99: 1 | GX99: =ROUND(HC99*I99,2) -> 0 | HA99: 0 | HB99: 0 | HC99: =GV99*GW99 -> 0 | HS99: 0 | IK99: 0
A100: 17 | B100: 1 | C100: =ROW(SmtRes!A202) -> 202 | D100: =ROW(EtalonRes!A252) -> 252 | E100: 19 | F100: 4.10-19-6 | G100: Монтаж отдельно устанавливаемого преобразователя или блока питания | H100: 1 ШТ. | I100: 6 | J100: 0 | K100: 6 | O100: =ROUND(CP100,2) -> 66553.8 | P100: =ROUND((ROUND((AC100*AW100*I100),2)*BC100),2) -> 3518.75 | Q100: =(ROUND((ROUND((((ET100*1.2))*AV100*I100),2)*BB100),2)+ROUND((ROUND(((AE100-((EU100*1.2)))*AV100*I100),2)*BS100),2)) -> 5595.24 | R100: =(ROUND((ROUND((((EU100*1.2))*AV100*I100),2)*BS100),2)+ROUND((ROUND(((AE100-((EU100*1.2)))*AV100*I100),2)*BS100),2)) -> 2145.24 | S100: =ROUND((ROUND((AF100*AV100*I100),2)*BA100),2) -> 57439.81 | T100: =ROUND(CU100*I100,2) -> 0 | U100: =CV100*I100 -> 70.10712 | V100: =CW100*I100 -> 0 | W100: =ROUND(CX100*I100,2) -> 0 | X100: =(ROUND((((S100+ROUND((ROUND((((EU100*1.2))*AV100*I100),2)*BS100),2))*AT100)/100),2)+ROUND(((ROUND((ROUND(((AE100-((EU100*1.2)))*AV100*I100),2)*BS100),2)*AT100)/100),2)) -> 53626.55 | Y100: =(ROUND((((S100+ROUND((ROUND((((EU100*1.2))*AV100*I100),2)*BS100),2))*AU100)/100),2)+ROUND(((ROUND((ROUND(((AE100-((EU100*1.2)))*AV100*I100),2)*BS100),2)*AU100)/100),2)) -> 27409.12 | AA100: 55929115 | AB100: =ROUND((AC100+AD100+AF100),6) -> 273.18 | AC100: =ROUND(((ES100*1)),6) -> 55.8 | AD100: =ROUND(((((ET100*1.2))-((EU100*1.2)))+AE100),6) -> 55.116 | AE100: =ROUND(((EU100*1.2)),6) -> 6.06 | AF100: =ROUND(((EV100*1.2)),6) -> 162.264 | AG100: =ROUND((AP100),6) -> 0 | AH100: =((EW100*1.2)) -> 11.16 | AI100: =((EX100*1.2)) -> 0 | AJ100: =(AS100) -> 0 | AK100: 236.95 | AL100: 55.8 | AM100: 45.93 | AN100: 5.05 | AO100: 135.22 | AP100: 0 | AQ100: 9.3 | AR100: 0 | AS100: 0 | AT100: 90 | AU100: 46 | AV100: 1.047 | AW100: 1 | AZ100: 1 | BA100: 56.35 | BB100: 16.16 | BC100: 10.51 | BH100: 0 | BI100: 2 | BJ100: ТСН-2001.4 Доп. 70, Сб. 10, т. 19, поз. 6 | BM100: 68 | BN100: 0 | BO100: 4.10-19-6 | BP100: 1 | BQ100: 40 | BR100: 0 | BS100: 56.35 | BT100: 1 | BU100: 1 | BV100: 1 | BW100: 1 | BX100: 1 | BZ100: 90 | CA100: 46 | CE100: 1566 | CF100: 0 | CG100: 0 | CM100: 0 | CN100: Поправка: Гл.12.Прил.8.п.8. 3_12.00.01.11.001 Наименование: При наличии напряженных и стесненных условий производства работ (стесненность, сложность складирования и транспортной логистики и т.п.) для объектов, расположенных в пределах круговой магистральной системы улиц "Садовое кольцо" города Москвы | CO100: 0 | CP100: =(P100+Q100+S100) -> 66553.8 | CQ100: =ROUND((ROUND((AC100*AW100*1),2)*BC100),2) -> 586.46 | CR100: =(ROUND((ROUND((((ET100*1.2))*AV100*1),2)*BB100),2)+ROUND((ROUND(((AE100-((EU100*1.2)))*AV100*1),2)*BS100),2)) -> 932.59 | CS100: =(ROUND((ROUND((((EU100*1.2))*AV100*1),2)*BS100),2)+ROUND((ROUND(((AE100-((EU100*1.2)))*AV100*1),2)*BS100),2)) -> 357.26 | CT100: =ROUND((ROUND((AF100*AV100*1),2)*BA100),2) -> 9573.3 | CU100: =AG100 -> 0 | CV100: =(AH100*AV100) -> 11.68452 | CW100: =AI100 -> 0 | CX100: =AJ100 -> 0 | CY100: =(ROUND((((S100+ROUND((ROUND((((EU100*1.2))*AV100*1),2)*BS100),2))*AT100)/100),2)+ROUND(((ROUND((ROUND(((AE100-((EU100*1.2)))*AV100*1),2)*BS100),2)*AT100)/100),2)) -> 52017.36 | CZ100: =(ROUND((((S100+ROUND((ROUND((((EU100*1.2))*AV100*1),2)*BS100),2))*AU100)/100),2)+ROUND(((ROUND((ROUND(((AE100-((EU100*1.2)))*AV100*1),2)*BS100),2)*AU100)/100),2)) -> 26586.65 | DB100: 58 | DD100: *1 | DE100: *1,2 | DF100: *1,2 | DG100: *1,2 | DI100: *1,2 | DJ100: *1,2 | DN100: 0 | DO100: 0 | DP100: 1 | DQ100: 1 | DU100: 1013 | DV100: 1 ШТ. | DW100: 1 ШТ. | DX100: 1 | EE100: 55393700 | EF100: 40 | EG100: Монтаж оборудования | EH100: 0 | EJ100: 2 | EK100: 68 | EL100: ТСН-2001.4-10. Прокладка и монтаж сетей связи | EM100: ТСН-2001.4-10-1 | EO100: Поправка: Гл.12.Прил.8.п.8. 3_12.00.01.11.001 | EQ100: 0 | ER100: 236.95 | ES100: 55.8 | ET100: 45.93 | EU100: 5.05 | EV100: 135.22 | EW100: 9.3 | EX100: 0 | EY100: 0 | FQ100: 0 | FR100: 0 | FS100: 0 | FX100: 90 | FY100: 46 | GD100: 1 | GF100: 1573787508 | GG100: 2 | GH100: 1 | GI100: 2 | GJ100: 0 | GK100: 0 | GL100: =ROUND(IF(AND(BH100=3,BI100=3,FS100<>0),P100,0),2) -> 0 | GM100: =ROUND(O100+X100+Y100,2)+GX100 -> 147589.47 | GN100: =IF(OR(BI100=0,BI100=1),GM100-GX100,0) -> 0 | GO100: =IF(BI100=2,GM100-GX100,0) -> 147589.47 | GP100: =IF(BI100=4,GM100-GX100,0) -> 0 | GR100: 0 | GS100: 3 | GT100: 0 | GV100: =ROUND((GT100),6) -> 0 | GW100: 1 | GX100: =ROUND(HC100*I100,2) -> 0 | HA100: 0 | HB100: 0 | HC100: =GV100*GW100 -> 0 | HS100: 0 | IK100: 0
A101: 18 | B101: 1 | C101: 180 | E101: 19,1 | F101: 1.1-1-8146 | G101: Болты стальные оцинкованные с шестигранной головкой, с полной резьбой, с гайкой оцинкованной, М6, длина от 12 до 60 мм | H101: кг | I101: =I99*J101 -> 1.8 | J101: 0.3 | K101: 0.3 | O101: =ROUND(CP101,2) -> 55.94 | P101: =ROUND((ROUND((AC101*AW101*I101),2)*BC101),2) -> 55.94 | Q101: =(ROUND((ROUND(((ET101)*AV101*I101),2)*BB101),2)+ROUND((ROUND(((AE101-(EU101))*AV101*I101),2)*BS101),2)) -> 0 | R101: =(ROUND((ROUND(((EU101)*AV101*I101),2)*BS101),2)+ROUND((ROUND(((AE101-(EU101))*AV101*I101),2)*BS101),2)) -> 0 | S101: =ROUND((ROUND((AF101*AV101*I101),2)*BA101),2) -> 0 | T101: =ROUND(CU101*I101,2) -> 0 | U101: =CV101*I101 -> 0 | V101: =CW101*I101 -> 0 | W101: =ROUND(CX101*I101,2) -> 0 | X101: =(ROUND((((S101+ROUND((ROUND(((EU101)*AV101*I101),2)*BS101),2))*AT101)/100),2)+ROUND(((ROUND((ROUND(((AE101-(EU101))*AV101*I101),2)*BS101),2)*AT101)/100),2)) -> 0 | Y101: =(ROUND((((S101+ROUND((ROUND(((EU101)*AV101*I101),2)*BS101),2))*AU101)/100),2)+ROUND(((ROUND((ROUND(((AE101-(EU101))*AV101*I101),2)*BS101),2)*AU101)/100),2)) -> 0 | AA101: 55929113 | AB101: =ROUND((AC101+AD101+AF101),6) -> 31.08 | AC101: =ROUND((ES101),6) -> 31.08 | AD101: =ROUND((((ET101)-(EU101))+AE101),6) -> 0 | AE101: =ROUND((EU101),6) -> 0 | AF101: =ROUND((EV101),6) -> 0 | AG101: =ROUND((AP101),6) -> 0 | AH101: =(EW101) -> 0 | AI101: =(EX101) -> 0 | AJ101: =(AS101) -> 0 | AK101: 31.08 | AL101: 31.08 | AM101: 0 | AN101: 0 | AO101: 0 | AP101: 0 | AQ101: 0 | AR101: 0 | AS101: 0 | AT101: 90 | AU101: 46 | AV101: 1 | AW101: 1 | AZ101: 1 | BA101: 1 | BB101: 1 | BC101: 1 | BH101: 3 | BI101: 2 | BJ101: ТСН-2001.1 Доп. 79, Р. 1, о. 1, поз. 8146 | BM101: 68 | BN101: 0 | BP101: 0 | BQ101: 40 | BR101: 0 | BS101: 1 | BT101: 1 | BU101: 1 | BV101: 1 | BW101: 1 | BX101: 1 | BZ101: 90 | CA101: 46 | CE101: 1566 | CF101: 0 | CG101: 0 | CM101: 0 | CN101: Поправка: Гл.12.Прил.8.п.8. 3_12.00.01.11.001_x000D_ Наименование: При наличии напряженных и стесненных условий производства работ (стесненность, сложность складирования и транспортной логистики и т.п.) для объектов, расположенных в пределах круговой магистральной системы улиц "Садовое кольцо" города Москвы | CO101: 0 | CP101: =(P101+Q101+S101) -> 55.94 | CQ101: =ROUND((ROUND((AC101*AW101*1),2)*BC101),2) -> 31.08 | CR101: =(ROUND((ROUND(((ET101)*AV101*1),2)*BB101),2)+ROUND((ROUND(((AE101-(EU101))*AV101*1),2)*BS101),2)) -> 0 | CS101: =(ROUND((ROUND(((EU101)*AV101*1),2)*BS101),2)+ROUND((ROUND(((AE101-(EU101))*AV101*1),2)*BS101),2)) -> 0 | CT101: =ROUND((ROUND((AF101*AV101*1),2)*BA101),2) -> 0 | CU101: =AG101 -> 0 | CV101: =(AH101*AV101) -> 0 | CW101: =AI101 -> 0 | CX101: =AJ101 -> 0 | CY101: =(ROUND((((S101+ROUND((ROUND(((EU101)*AV101*1),2)*BS101),2))*AT101)/100),2)+ROUND(((ROUND((ROUND(((AE101-(EU101))*AV101*1),2)*BS101),2)*AT101)/100),2)) -> 0 | CZ101: =(ROUND((((S101+ROUND((ROUND(((EU101)*AV101*1),2)*BS101),2))*AU101)/100),2)+ROUND(((ROUND((ROUND(((AE101-(EU101))*AV101*1),2)*BS101),2)*AU101)/100),2)) -> 0 | DN101: 0 | DO101: 0 | DP101: 1 | DQ101: 1 | DU101: 1009 | DV101: кг | DW101: кг | DX101: 1 | EE101: 55393700 | EF101: 40 | EG101: Монтаж оборудования | EH101: 0 | EJ101: 2 | EK101: 68 | EL101: ТСН-2001.4-10. Прокладка и монтаж сетей связи | EM101: ТСН-2001.4-10-1 | EO101: Поправка: Гл.12.Прил.8.п.8. 3_12.00.01.11.001 | EQ101: 0 | ER101: 31.08 | ES101: 31.08 | ET101: 0 | EU101: 0 | EV101: 0 | EW101: 0 | EX101: 0 | FQ101: 0 | FR101: 0 | FS101: 0 | FX101: 90 | FY101: 46 | GD101: 1 | GF101: -2097101800 | GG101: 2 | GH101: 1 | GI101: -2 | GJ101: 0 | GK101: 0 | GL101: =ROUND(IF(AND(BH101=3,BI101=3,FS101<>0),P101,0),2) -> 0 | GM101: =ROUND(O101+X101+Y101,2)+GX101 -> 55.94 | GN101: =IF(OR(BI101=0,BI101=1),GM101-GX101,0) -> 0 | GO101: =IF(BI101=2,GM101-GX101,0) -> 55.94 | GP101: =IF(BI101=4,GM101-GX101,0) -> 0 | GR101: 0 | GS101: 3 | GT101: 0 | GV101: =ROUND((GT101),6) -> 0 | GW101: 1 | GX101: =ROUND(HC101*I101,2) -> 0 | HA101: 0 | HB101: 0 | HC101: =GV101*GW101 -> 0 | HM101: *1 | HS101: 0 | IK101: 0
