Workbook

Sheet Смета по ТСН-2001(с доп.67
A1: =Source!B1 -> Smeta.RU (495) 974-1589
J2: Форма № 4б
B3: "СОГЛАСОВАНО" | G3: "УТВЕРЖДАЮ"
B6: =CONCATENATE("______________________ ", IF(Source!AL12<>"", Source!AL12, "")) -> ______________________ | G6: =CONCATENATE("______________________ ", IF(Source!AH12<>"", Source!AH12, "")) -> ______________________
B7: "_____"________________ 2026 г. | G7: "_____"________________ 2026 г.
A10: Капитальный ремонт здания Государственного бюджетного общеобразовательного учреждения города Москвы «Школа №1574», расположенного по адресу: г. Москва, Старопименовский переулок, д. 5. 1 этап. | AP10: Капитальный ремонт здания Государственного бюджетного общеобразовательного учреждения города Москвы «Школа №1574», расположенного по адресу: г. Москва, Старопименовский переулок, д. 5. 1 этап. 02-01-19 АУГП
A11: (наименование стройки и/или объекта)
A13: =CONCATENATE( "ЛОКАЛЬНАЯ СМЕТА № ",IF(Source!F12<>"Новый объект", Source!F12, "")) -> ЛОКАЛЬНАЯ СМЕТА № 02-01-19
A15: =Source!G20 -> Автоматическая установка газового пожаротушения
A16: (наименование работ и затрат)
A18: =CONCATENATE( "Основание: чертежи № ", Source!J12) -> Основание: чертежи № 2024-00375-01-0-ИОС5.12
I20: В базисном уровне цен | J20: В текущем уровне цен
E21: Сметная стоимость | I21: =I22+I23+I24+I25 -> 418.42 | J21: =J22+J23+J24+J25 -> 4162.61 | K21: тыс.руб.
E22: Строительные работы | I22: =ROUND((Source!F381)/1000, 2) -> 34.37 | J22: =ROUND((Source!P381)/1000, 2) -> 710.35 | K22: тыс.руб.
E23: Работы по монтажу оборудования | I23: =ROUND((Source!F382)/1000, 2) -> 59.83 | J23: =ROUND((Source!P382)/1000, 2) -> 1047.19 | K23: тыс.руб.
E24: Оборудование | I24: =ROUND((Source!F373)/1000, 2) -> 324.22 | J24: =ROUND((Source!P373)/1000, 2) -> 2405.07 | K24: тыс.руб.
E25: Прочие работы и затраты | I25: =ROUND((Source!F383+Source!F384)/1000, 2) -> 0 | J25: =ROUND((Source!P383+Source!P384)/1000, 2) -> 0 | K25: тыс.руб.
E26: Средства на оплату труда | I26: =(Source!F379+ Source!F378)/1000 -> 10.06379 | J26: =((Source!P379 + Source!P378)/1000) -> 567.09459 | K26: тыс.руб.
E27: Затраты труда | I27: =Source!F386 -> 856.39852 | K27: чел.-ч.
E28: Кроме того:
E29: Возврат материалов | I29: =SUM(Y1:Y625)/1000 -> 0 | J29: =SUM(Z1:Z625)/1000 -> 0 | K29: тыс.руб.
A31: Составлен(а) по ТСН-2001 с учетом Дополнения №: 81
A32: № и период сборника коэффициентов (индексов) пересчета: Коэффициенты к ТСН-2001 МГЭ Дополнение 81, строительство №219/81 I квартал 2026 года и Коэффициенты к ТСН-2001.13-2 Дополнение 47 №64/47 I квартал 2026 года | AP32: № и период сборника коэффициентов (индексов) пересчета: Коэффициенты к ТСН-2001 МГЭ Дополнение 81, строительство №219/81 I квартал 2026 года и Коэффициенты к ТСН-2001.13-2 Дополнение 47 №64/47 I квартал 2026 года
A33: № п/п | B33: Шифр расценки и коды ресурсов | C33: Наименование работ и затрат | D33: Ед. изм. | E33: Кол-во единиц | F33: Цена на ед. изм., руб. | G33: Попра- вочные коэффи- циенты | H33: Коэффи- циенты зимних удорожа- ний | I33: Всего в ценах на январь 2000 года, руб. | J33: Коэффи- циенты (индек- сы) пере- счета, нормы НР и СП | K33: ВСЕГО затрат в текущем уровне цен, руб.
A34: 1 | B34: 2 | C34: 3 | D34: 4 | E34: 5 | F34: 6 | G34: 7 | H34: 8 | I34: 9 | J34: 10 | K34: 11 | L34: цена за ед с ндс
A36: =CONCATENATE("Локальная смета: ",IF(Source!G20<>"Новая локальная смета", Source!G20, "")) -> Локальная смета: Автоматическая установка газового пожаротушения
A38: =CONCATENATE("Раздел: ",IF(Source!G24<>"Новый раздел", Source!G24, "")) -> Раздел: Демонтажные работы
A39: 1 | B39: =Source!F28 -> 4.10-80-5 | C39: Аппараты приемные, приборы ПС приемно-контрольные, пусковые, прибор ПС на 1 луч / демонтаж модуля автоматики пожаротушения | D39: =Source!H28 -> 1 ШТ. | E39: =Source!I28 -> 8 | Q39: =Source!X28 -> 62.55 | R39: =Source!X29 -> 3524.69 | S39: =Source!Y28 -> 31.97 | T39: =Source!Y29 -> 1801.51 | U39: =ROUND((175/100)*ROUND(Source!R28, 2), 2) -> 0.05 | V39: =ROUND((0/100)*ROUND(Source!R29, 2), 2) -> 0 | AC39: 0
C40: ЗП | F40: =Source!AO28 -> 23.04 | G40: 1,2*0,3 | H40: =Source!AV29 -> 1.047 | I40: =Source!S28 -> 69.47 | J40: =IF(Source!BA29<> 0, Source!BA29, 1) -> 56.35 | K40: =Source!S29 -> 3914.63
C41: ЭМ | F41: =Source!AM28 -> 0.05 | G41: 1,2*0,3 | H41: =Source!AV29 -> 1.047 | I41: =Source!Q28 -> 0.15 | J41: =IF(Source!BB29<> 0, Source!BB29, 1) -> 20 | K41: =Source!Q29 -> 3
C42: в т.ч. ЗПМ | F42: =Source!AN28 -> 0.01 | G42: 1,2*0,3 | H42: =Source!AV29 -> 1.047 | I42: =Source!R28 -> 0.03 | J42: =IF(Source!BS29<> 0, Source!BS29, 1) -> 56.35 | K42: =Source!R29 -> 1.69
C43: НР от ФОТ | D43: % | E43: =Source!BZ29 -> 90 | I43: =SUM(Q39:Q42) -> 62.55 | J43: =Source!AT29 -> 90 | K43: =SUM(R39:R42) -> 3524.69
C44: СП от ФОТ | D44: % | E44: =Source!CA29 -> 46 | I44: =SUM(S39:S43) -> 31.97 | J44: =Source!AU29 -> 46 | K44: =SUM(T39:T43) -> 1801.51
C45: ЗТР | D45: чел-ч | E45: =Source!AQ28 -> 1.8 | G45: 1,2*0,3 | H45: =Source!AV29 -> 1.047 | I45: =Source!U28 -> 5.427648
C46: ВСЕГО работ по позиции: | H46: =I40+I41+I43+I44+0-0-0 -> 164.14 | J46: =K40+K41+K43+K44+0-0-0 -> 9243.83
C47: ВСЕГО оборудование по позиции: | H47: =0+0 -> 0 | J47: =0+0 -> 0
C48: ВСЕГО по позиции: | H48: =I40+I41+I43+I44+0 -> 164.14 | J48: =K40+K41+K43+K44+0 -> 9243.83 | O48: =I40+I41+I43+I44+0 -> 164.14 | P48: =K40+K41+K43+K44+0 -> 9243.83
A50: 2 | B50: =Source!F30 -> 4.10-80-2 | C50: Аппараты приемные, приборы ПС приемно-контрольные, пусковые, концентратор, блок базовый на 20 лучей / демонтаж прибора приемно-контрольного и управления охранно-пожарного | D50: =Source!H30 -> 1 ШТ. | E50: =Source!I30 -> 1 | Q50: =Source!X30 -> 52.39 | R50: =Source!X31 -> 2952.12 | S50: =Source!Y30 -> 26.78 | T50: =Source!Y31 -> 1508.86 | U50: =ROUND((175/100)*ROUND(Source!R30, 2), 2) -> 0 | V50: =ROUND((0/100)*ROUND(Source!R31, 2), 2) -> 0 | AC50: 0
C51: ЗП | F51: =Source!AO30 -> 154.44 | G51: 1,2*0,3 | H51: =Source!AV31 -> 1.047 | I51: =Source!S30 -> 58.21 | J51: =IF(Source!BA31<> 0, Source!BA31, 1) -> 56.35 | K51: =Source!S31 -> 3280.13
C52: ЭМ | F52: =Source!AM30 -> 0.06 | G52: 1,2*0,3 | H52: =Source!AV31 -> 1.047 | I52: =Source!Q30 -> 0.02 | J52: =IF(Source!BB31<> 0, Source!BB31, 1) -> 18.5 | K52: =Source!Q31 -> 0.37
C53: НР от ФОТ | D53: % | E53: =Source!BZ31 -> 90 | I53: =SUM(Q50:Q52) -> 52.39 | J53: =Source!AT31 -> 90 | K53: =SUM(R50:R52) -> 2952.12
C54: СП от ФОТ | D54: % | E54: =Source!CA31 -> 46 | I54: =SUM(S50:S53) -> 26.78 | J54: =Source!AU31 -> 46 | K54: =SUM(T50:T53) -> 1508.86
C55: ЗТР | D55: чел-ч | E55: =Source!AQ30 -> 11.7 | G55: 1,2*0,3 | H55: =Source!AV31 -> 1.047 | I55: =Source!U30 -> 4.409964
C56: ВСЕГО работ по позиции: | H56: =I51+I52+I53+I54+0-0-0 -> 137.4 | J56: =K51+K52+K53+K54+0-0-0 -> 7741.48
C57: ВСЕГО оборудование по позиции: | H57: =0+0 -> 0 | J57: =0+0 -> 0
C58: ВСЕГО по позиции: | H58: =I51+I52+I53+I54+0 -> 137.4 | J58: =K51+K52+K53+K54+0 -> 7741.48 | O58: =I51+I52+I53+I54+0 -> 137.4 | P58: =K51+K52+K53+K54+0 -> 7741.48
A60: 3 | B60: =Source!F32 -> 4.10-163-2 | C60: Монтаж охранно-пожарного пульта (ОПП) в диспетчерской / демонтаж пульта дистанционного управления | D60: =Source!H32 -> 1 устройство | E60: =Source!I32 -> 1 | Q60: =Source!X32 -> 27.25 | R60: =Source!X33 -> 1535.65 | S60: =Source!Y32 -> 13.93 | T60: =Source!Y33 -> 784.89 | U60: =ROUND((175/100)*ROUND(Source!R32, 2), 2) -> 0 | V60: =ROUND((0/100)*ROUND(Source!R33, 2), 2) -> 0 | AC60: 0
C61: ЗП | F61: =Source!AO32 -> 80.33 | G61: 1,2*0,3 | H61: =Source!AV33 -> 1.047 | I61: =Source!S32 -> 30.28 | J61: =IF(Source!BA33<> 0, Source!BA33, 1) -> 56.35 | K61: =Source!S33 -> 1706.28
C62: ЭМ | F62: =Source!AM32 -> 0.82 | G62: 1,2*0,3 | H62: =Source!AV33 -> 1.047 | I62: =Source!Q32 -> 0.31 | J62: =IF(Source!BB33<> 0, Source!BB33, 1) -> 9.52 | K62: =Source!Q33 -> 2.95
C63: НР от ФОТ | D63: % | E63: =Source!BZ33 -> 90 | I63: =SUM(Q60:Q62) -> 27.25 | J63: =Source!AT33 -> 90 | K63: =SUM(R60:R62) -> 1535.65
C64: СП от ФОТ | D64: % | E64: =Source!CA33 -> 46 | I64: =SUM(S60:S63) -> 13.93 | J64: =Source!AU33 -> 46 | K64: =SUM(T60:T63) -> 784.89
C65: ЗТР | D65: чел-ч | E65: =Source!AQ32 -> 6.01 | G65: 1,2*0,3 | H65: =Source!AV33 -> 1.047 | I65: =Source!U32 -> 2.2652892
C66: ВСЕГО работ по позиции: | H66: =I61+I62+I63+I64+0-0-0 -> 71.77 | J66: =K61+K62+K63+K64+0-0-0 -> 4029.77
C67: ВСЕГО оборудование по позиции: | H67: =0+0 -> 0 | J67: =0+0 -> 0
C68: ВСЕГО по позиции: | H68: =I61+I62+I63+I64+0 -> 71.77 | J68: =K61+K62+K63+K64+0 -> 4029.77 | O68: =I61+I62+I63+I64+0 -> 71.77 | P68: =K61+K62+K63+K64+0 -> 4029.77
A70: 4 | B70: =Source!F34 -> 4.10-167-1 | C70: Монтаж блока питания сети (БПС) в диспетчерской / демонтаж блоков электропитания | D70: =Source!H34 -> 1 ШТ. | E70: =Source!I34 -> 16 | Q70: =Source!X34 -> 102.8 | R70: =Source!X35 -> 5792.67 | S70: =Source!Y34 -> 52.54 | T70: =Source!Y35 -> 2960.7 | U70: =ROUND((175/100)*ROUND(Source!R34, 2), 2) -> 0 | V70: =ROUND((0/100)*ROUND(Source!R35, 2), 2) -> 0 | AC70: 0
C71: ="Объем: "&Source!I34&"=4+"&"1+"&"1+"&"8+"&"2" -> Объем: 16=4+1+1+8+2
C72: ЗП | F72: =Source!AO34 -> 18.94 | G72: 1,2*0,3 | H72: =Source!AV35 -> 1.047 | I72: =Source!S34 -> 114.22 | J72: =IF(Source!BA35<> 0, Source!BA35, 1) -> 56.35 | K72: =Source!S35 -> 6436.3
C73: ЭМ | F73: =Source!AM34 -> 0.02 | G73: 1,2*0,3 | H73: =Source!AV35 -> 1.047 | I73: =Source!Q34 -> 0.12 | J73: =IF(Source!BB35<> 0, Source!BB35, 1) -> 11 | K73: =Source!Q35 -> 1.32
C74: НР от ФОТ | D74: % | E74: =Source!BZ35 -> 90 | I74: =SUM(Q70:Q73) -> 102.8 | J74: =Source!AT35 -> 90 | K74: =SUM(R70:R73) -> 5792.67
C75: СП от ФОТ | D75: % | E75: =Source!CA35 -> 46 | I75: =SUM(S70:S74) -> 52.54 | J75: =Source!AU35 -> 46 | K75: =SUM(T70:T74) -> 2960.7
C76: ЗТР | D76: чел-ч | E76: =Source!AQ34 -> 1.36 | G76: 1,2*0,3 | H76: =Source!AV35 -> 1.047 | I76: =Source!U34 -> 8.2017792
C77: ВСЕГО работ по позиции: | H77: =I72+I73+I74+I75+0-0-0 -> 269.68 | J77: =K72+K73+K74+K75+0-0-0 -> 15190.99
C78: ВСЕГО оборудование по позиции: | H78: =0+0 -> 0 | J78: =0+0 -> 0
C79: ВСЕГО по позиции: | H79: =I72+I73+I74+I75+0 -> 269.68 | J79: =K72+K73+K74+K75+0 -> 15190.99 | O79: =I72+I73+I74+I75+0 -> 269.68 | P79: =K72+K73+K74+K75+0 -> 15190.99
A81: 5 | B81: =Source!F36 -> 4.10-81-2 | C81: Извещатели ПС автоматические, дымовой, фотоэлектрический, радиоизотопный, световой в нормальном исполнении / демонтаж извещателей | D81: =Source!H36 -> 1 ШТ. | E81: =Source!I36 -> 8 | Q81: =Source!X36 -> 57.56 | R81: =Source!X37 -> 3243.74 | S81: =Source!Y36 -> 29.42 | T81: =Source!Y37 -> 1657.91 | U81: =ROUND((175/100)*ROUND(Source!R36, 2), 2) -> 0.05 | V81: =ROUND((0/100)*ROUND(Source!R37, 2), 2) -> 0 | AC81: 0
C82: ЗП | F82: =Source!AO36 -> 21.2 | G82: 1,2*0,3 | H82: =Source!AV37 -> 1.047 | I82: =Source!S36 -> 63.93 | J82: =IF(Source!BA37<> 0, Source!BA37, 1) -> 56.35 | K82: =Source!S37 -> 3602.46
C83: ЭМ | F83: =Source!AM36 -> 0.06 | G83: 1,2*0,3 | H83: =Source!AV37 -> 1.047 | I83: =Source!Q36 -> 0.18 | J83: =IF(Source!BB37<> 0, Source!BB37, 1) -> 18.5 | K83: =Source!Q37 -> 3.33
C84: в т.ч. ЗПМ | F84: =Source!AN36 -> 0.01 | G84: 1,2*0,3 | H84: =Source!AV37 -> 1.047 | I84: =Source!R36 -> 0.03 | J84: =IF(Source!BS37<> 0, Source!BS37, 1) -> 56.35 | K84: =Source!R37 -> 1.69
C85: НР от ФОТ | D85: % | E85: =Source!BZ37 -> 90 | I85: =SUM(Q81:Q84) -> 57.56 | J85: =Source!AT37 -> 90 | K85: =SUM(R81:R84) -> 3243.74
C86: СП от ФОТ | D86: % | E86: =Source!CA37 -> 46 | I86: =SUM(S81:S85) -> 29.42 | J86: =Source!AU37 -> 46 | K86: =SUM(T81:T85) -> 1657.91
C87: ЗТР | D87: чел-ч | E87: =Source!AQ36 -> 1.68 | G87: 1,2*0,3 | H87: =Source!AV37 -> 1.047 | I87: =Source!U36 -> 5.0658048
C88: ВСЕГО работ по позиции: | H88: =I82+I83+I85+I86+0-0-0 -> 151.09 | J88: =K82+K83+K85+K86+0-0-0 -> 8507.44
C89: ВСЕГО оборудование по позиции: | H89: =0+0 -> 0 | J89: =0+0 -> 0
C90: ВСЕГО по позиции: | H90: =I82+I83+I85+I86+0 -> 151.09 | J90: =K82+K83+K85+K86+0 -> 8507.44 | O90: =I82+I83+I85+I86+0 -> 151.09 | P90: =K82+K83+K85+K86+0 -> 8507.44
A92: 6 | B92: =Source!F38 -> 4.10-76-10 | C92: Монтаж ключа или кнопки на панели | D92: =Source!H38 -> 1 ШТ. | E92: =Source!I38 -> 4 | Q92: =Source!X38 -> 17.03 | R92: =Source!X39 -> 959.84 | S92: =Source!Y38 -> 9.5 | T92: =Source!Y39 -> 535.49 | U92: =ROUND((175/100)*ROUND(Source!R38, 2), 2) -> 0 | V92: =ROUND((0/100)*ROUND(Source!R39, 2), 2) -> 0 | AC92: 0
C93: ЗП | F93: =Source!AO38 -> 11.89 | G93: 1,2*0,3 | H93: =Source!AV39 -> 1.047 | I93: =Source!S38 -> 17.93 | J93: =IF(Source!BA39<> 0, Source!BA39, 1) -> 56.35 | K93: =Source!S39 -> 1010.36
C94: НР от ФОТ | D94: % | E94: =Source!BZ39 -> 95 | I94: =SUM(Q92:Q93) -> 17.03 | J94: =Source!AT39 -> 95 | K94: =SUM(R92:R93) -> 959.84
C95: СП от ФОТ | D95: % | E95: =Source!CA39 -> 53 | I95: =SUM(S92:S94) -> 9.5 | J95: =Source!AU39 -> 53 | K95: =SUM(T92:T94) -> 535.49
C96: ЗТР | D96: чел-ч | E96: =Source!AQ38 -> 1 | G96: 1,2*0,3 | H96: =Source!AV39 -> 1.047 | I96: =Source!U38 -> 1.50768
C97: ВСЕГО работ по позиции: | H97: =I93+I94+I95+0-0-0 -> 44.46 | J97: =K93+K94+K95+0-0-0 -> 2505.69
C98: ВСЕГО оборудование по позиции: | H98: =0+0 -> 0 | J98: =0+0 -> 0
C99: ВСЕГО по позиции: | H99: =I93+I94+I95+0 -> 44.46 | J99: =K93+K94+K95+0 -> 2505.69 | O99: =I93+I94+I95+0 -> 44.46 | P99: =K93+K94+K95+0 -> 2505.69
A101: 7 | B101: =Source!F40 -> 4.10-81-4 | C101: Извещатели ОС автоматические, контактный, магнито-контактный на открывание окон, дверей / демонтаж извещателей | D101: =Source!H40 -> 1 ШТ. | E101: =Source!I40 -> 4 | Q101: =Source!X40 -> 14.38 | R101: =Source!X41 -> 810.42 | S101: =Source!Y40 -> 7.35 | T101: =Source!Y41 -> 414.22 | U101: =ROUND((175/100)*ROUND(Source!R40, 2), 2) -> 0 | V101: =ROUND((0/100)*ROUND(Source!R41, 2), 2) -> 0 | AC101: 0
C102: ЗП | F102: =Source!AO40 -> 10.6 | G102: 1,2*0,3 | H102: =Source!AV41 -> 1.047 | I102: =Source!S40 -> 15.98 | J102: =IF(Source!BA41<> 0, Source!BA41, 1) -> 56.35 | K102: =Source!S41 -> 900.47
C103: НР от ФОТ | D103: % | E103: =Source!BZ41 -> 90 | I103: =SUM(Q101:Q102) -> 14.38 | J103: =Source!AT41 -> 90 | K103: =SUM(R101:R102) -> 810.42
C104: СП от ФОТ | D104: % | E104: =Source!CA41 -> 46 | I104: =SUM(S101:S103) -> 7.35 | J104: =Source!AU41 -> 46 | K104: =SUM(T101:T103) -> 414.22
C105: ЗТР | D105: чел-ч | E105: =Source!AQ40 -> 0.84 | G105: 1,2*0,3 | H105: =Source!AV41 -> 1.047 | I105: =Source!U40 -> 1.2664512
C106: ВСЕГО работ по позиции: | H106: =I102+I103+I104+0-0-0 -> 37.71 | J106: =K102+K103+K104+0-0-0 -> 2125.11
C107: ВСЕГО оборудование по позиции: | H107: =0+0 -> 0 | J107: =0+0 -> 0
C108: ВСЕГО по позиции: | H108: =I102+I103+I104+0 -> 37.71 | J108: =K102+K103+K104+0 -> 2125.11 | O108: =I102+I103+I104+0 -> 37.71 | P108: =K102+K103+K104+0 -> 2125.11
A110: 8 | B110: =Source!F42 -> 4.8-245-10 | C110: Монтаж светильников с лампами накаливания, светового настенного указателя / демонтаж оповещателя пожарного светового | D110: =Source!H42 -> 100 шт. | E110: =Source!I42 -> 0.12 | Q110: =Source!X42 -> 48.83 | R110: =Source!X43 -> 2751.56 | S110: =Source!Y42 -> 25.67 | T110: =Source!Y43 -> 1446.7 | U110: =ROUND((175/100)*ROUND(Source!R42, 2), 2) -> 1.03 | V110: =ROUND((0/100)*ROUND(Source!R43, 2), 2) -> 0 | AC110: 0
C111: ="Объем: "&Source!I42&"=(4+"&"4+"&"4)/"&"100" -> Объем: 0,12=(4+4+4)/100
C112: ЗП | F112: =Source!AO42 -> 1099.86 | G112: 1,2*0,3 | H112: =Source!AV43 -> 1.047 | I112: =Source!S42 -> 49.75 | J112: =IF(Source!BA43<> 0, Source!BA43, 1) -> 56.35 | K112: =Source!S43 -> 2803.41
C113: ЭМ | F113: =Source!AM42 -> 93.32 | G113: 1,2*0,3 | H113: =Source!AV43 -> 1.047 | I113: =Source!Q42 -> 4.22 | J113: =IF(Source!BB43<> 0, Source!BB43, 1) -> 16.42 | K113: =Source!Q43 -> 69.29
C114: в т.ч. ЗПМ | F114: =Source!AN42 -> 13 | G114: 1,2*0,3 | H114: =Source!AV43 -> 1.047 | I114: =Source!R42 -> 0.59 | J114: =IF(Source!BS43<> 0, Source!BS43, 1) -> 56.35 | K114: =Source!R43 -> 33.25
C115: НР от ФОТ | D115: % | E115: =Source!BZ43 -> 97 | I115: =SUM(Q110:Q114) -> 48.83 | J115: =Source!AT43 -> 97 | K115: =SUM(R110:R114) -> 2751.56
C116: СП от ФОТ | D116: % | E116: =Source!CA43 -> 51 | I116: =SUM(S110:S115) -> 25.67 | J116: =Source!AU43 -> 51 | K116: =SUM(T110:T115) -> 1446.7
C117: ЗТР | D117: чел-ч | E117: =Source!AQ42 -> 84.67 | G117: 1,2*0,3 | H117: =Source!AV43 -> 1.047 | I117: =Source!U42 -> 3.829658
C118: ВСЕГО работ по позиции: | H118: =I112+I113+I115+I116+0-0-0 -> 128.47 | J118: =K112+K113+K115+K116+0-0-0 -> 7070.96
...

Sheet Source
A1: 0 | B1: Smeta.RU (495) 974-1589 | D1: _PS_ | F1: 0 | G1: 0 | H1: 0 | I1: Smeta.RU | K1: 1 | L1: 74599 | M1: 10 | N1: 12 | O1: 1 | P1: 0 | Q1: 1
A4: 1 | B4: 1 | C4: -1 | G4: Капитальный ремонт здания Государственного бюджетного общеобразовательного учреждения города Москвы «Школа №1574», расположенного по адресу: г. Москва, Старопименовский переулок, д. 5. 1 этап | EC4: 0
A5: 8 | B5: 1 | C5: -1 | G5: Капитальный ремонт здания Государственного бюджетного общеобразовательного учреждения города Москвы «Школа №1574», расположенного по адресу: г. Москва, Старопименовский переулок, д. 5. 1 этап | EC5: 0
A12: 1 | B12: 403 | C12: 0 | D12: =ROW(A364) -> 364 | E12: 0 | F12: 02-01-19 | G12: 02-01-19 АУГП | I12: 0 | J12: 2024-00375-01-0-ИОС5.12 | K12: 0 | L12: 0 | M12: 4098 | O12: 0 | P12: 0 | Q12: 0 | R12: 0 | S12: 0 | T12: 1 | V12: 0 | BB12: 0 | BH12: Сметные нормы списания | BI12: Коды ОКП для ТСН-2001 МГЭ Дополнение 81 | BJ12: 1 | BK12: 1 | BL12: 0 | BM12: 0 | BN12: 1 | BO12: 0 | BP12: 6 | BQ12: 2 | BR12: 1 | BS12: 1 | BT12: 0 | BU12: 0 | BV12: 0 | BW12: 0 | BX12: 0 | BY12: ТСН-2001 (МГЭ) Доп 81 - Новое строительство | BZ12: Типовой расчет для ТСН-2001 МГЭ, Дополнение 81, строительство | CA12: Территориальные сметные нормативы для Москвы ТСН-2001 (МГЭ), дополнение 81 | CB12: Территориальные сметные нормативы для Москвы ТСН-2001 (МГЭ), дополнение 81 | CC12: Территориальные сметные нормативы для Москвы ТСН-2001 (МГЭ), дополнение 81 | CD12: Территориальные сметные нормативы для Москвы ТСН-2001 (МГЭ), дополнение 81 | CE12: Поправки для ТСН-2001 от 07.04.2026 г. доп.81 | CF12: 0 | CG12: 0 | CH12: 8200 | CK12: 81 | CQ12: Территориальные сметные нормативы для Москвы (ТСН-2001) | CR12: ТЕР | CS12: 41660 | CT12: 1 | CU12: 81 | CY12: 0 | EC12: 0
A15: 15 | B15: 1
A18: 52 | B18: =B364 -> 403 | C18: =C364 -> 1 | D18: =D364 -> 12 | E18: =E364 -> 0 | F18: =F364 -> 02-01-19 | G18: =G364 -> 02-01-19 АУГП | O18: =O364 -> 404036.74 | P18: =P364 -> 393519.72 | Q18: =Q364 -> 540.87 | R18: =R364 -> 87.64 | S18: =S364 -> 9976.15 | T18: =T364 -> 0 | U18: =U364 -> 856.39852 | V18: =V364 -> 0 | ... GX18: =GX364 -> 0
A20: 3 | B20: 1 | D20: =ROW(A334) -> 334 | F20: 02-01-19 | G20: Автоматическая установка газового пожаротушения | I20: 0 | J20: 2024-00375-01-0-ИОС5.12 | K20: -1 | L20: 02-01-19 | S20: 0 | T20: 0 | V20: 0 | BX20: 0 | CF20: 0 | CG20: 0
A22: 52 | B22: =B334 -> 1 | C22: =C334 -> 3 | D22: =D334 -> 20 | E22: =E334 -> 0 | F22: =F334 -> 02-01-19 | G22: =G334 -> Автоматическая установка газового пожаротушения | O22: =O334 -> 404036.74 | P22: =P334 -> 393519.72 | Q22: =Q334 -> 540.87 | R22: =R334 -> 87.64 | S22: =S334 -> 9976.15 | T22: =T334 -> 0 | U22: =U334 -> 856.39852 | V22: =V334 -> 0 | ... GX22: =GX334 -> 0
A24: 4 | B24: 1 | D24: =ROW(A63) -> 63 | F24: Новый раздел | G24: Демонтажные работы | I24: 0 | K24: 0 | S24: 0 | T24: 0 | V24: 0 | BX24: 0 | CJ24: 0
A26: 52 | B26: =B63 -> 1 | C26: =C63 -> 4 | D26: =D63 -> 24 | E26: =E63 -> 0 | F26: =F63 -> Новый раздел | G26: =G63 -> Демонтажные работы | O26: =O63 -> 5104.31 | P26: =P63 -> 137.83 | Q26: =Q63 -> 54.29 | R26: =R63 -> 7.99 | S26: =S63 -> 4912.19 | T26: =T63 -> 0 | U26: =U63 -> 459.3159 | V26: =V63 -> 0 | ... GX26: =GX63 -> 0
A28: 17 | B28: 1 | C28: =ROW(SmtRes!A1) -> 1 | D28: =ROW(EtalonRes!A1) -> 1 | E28: 1 | F28: 4.10-80-5 | G28: Аппараты приемные, приборы ПС приемно-контрольные, пусковые, прибор ПС на 1 луч / демонтаж модуля автоматики пожаротушения | H28: 1 ШТ. | I28: 8 | J28: 0 | K28: 8 | O28: =ROUND(CP28,2) -> 69.62 | P28: =ROUND((ROUND((AC28*AW28*I28),2)*BC28),2) -> 0 | Q28: =(ROUND((ROUND(((((ET28*1.2)*0.3))*AV28*I28),2)*BB28),2)+ROUND((ROUND(((AE28-(((EU28*1.2)*0.3)))*AV28*I28),2)*BS28),2)) -> 0.15 | R28: =(ROUND((ROUND(((((EU28*1.2)*0.3))*AV28*I28),2)*BS28),2)+ROUND((ROUND(((AE28-(((EU28*1.2)*0.3)))*AV28*I28),2)*BS28),2)) -> 0.03 | S28: =ROUND((ROUND((AF28*AV28*I28),2)*BA28),2) -> 69.47 | T28: =ROUND(CU28*I28,2) -> 0 | U28: =CV28*I28 -> 5.427648 | V28: =CW28*I28 -> 0 | W28: =ROUND(CX28*I28,2) -> 0 | X28: =(ROUND((((S28+ROUND((ROUND(((((EU28*1.2)*0.3))*AV28*I28),2)*BS28),2))*AT28)/100),2)+ROUND(((ROUND((ROUND(((AE28-(((EU28*1.2)*0.3)))*AV28*I28),2)*BS28),2)*AT28)/100),2)) -> 62.55 | Y28: =(ROUND((((S28+ROUND((ROUND(((((EU28*1.2)*0.3))*AV28*I28),2)*BS28),2))*AU28)/100),2)+ROUND(((ROUND((ROUND(((AE28-(((EU28*1.2)*0.3)))*AV28*I28),2)*BS28),2)*AU28)/100),2)) -> 31.97 | AA28: 55937296 | AB28: =ROUND((AC28+AD28+AF28),6) -> 8.3124 | AC28: =ROUND((((ES28*1)*0)),6) -> 0 | AD28: =ROUND((((((ET28*1.2)*0.3))-(((EU28*1.2)*0.3)))+AE28),6) -> 0.018 | AE28: =ROUND((((EU28*1.2)*0.3)),6) -> 0.0036 | AF28: =ROUND((((EV28*1.2)*0.3)),6) -> 8.2944 | AG28: =ROUND((AP28),6) -> 0 | AH28: =(((EW28*1.2)*0.3)) -> 0.648 | AI28: =(((EX28*1.2)*0.3)) -> 0 | AJ28: =(AS28) -> 0 | AK28: 26.52 | AL28: 3.43 | AM28: 0.05 | AN28: 0.01 | AO28: 23.04 | AP28: 0 | AQ28: 1.8 | AR28: 0 | AS28: 0 | AT28: 90 | AU28: 46 | AV28: 1.047 | AW28: 1 | AZ28: 1 | BA28: 1 | BB28: 1 | BC28: 1 | BH28: 0 | BI28: 2 | BJ28: ТСН-2001.4. Доп. 1-42. Сб. 10, т. 80, поз. 5 | BM28: 68 | BN28: 0 | BO28: 4.10-80-5 | BP28: 1 | BQ28: 40 | BR28: 0 | BS28: 1 | BT28: 1 | BU28: 1 | BV28: 1 | BW28: 1 | BX28: 1 | BZ28: 90 | CA28: 46 | CE28: 1566 | CF28: 0 | CG28: 0 | CM28: 0 | CN28: Поправка: Гл.12.Прил.8.п.8. 3_12.00.01.11.001 Наименование: При наличии напряженных и стесненных условий производства работ (стесненность, сложность складирования и транспортной логистики и т.п.) для объектов, расположенных в пределах круговой магистральной системы улиц "Садовое кольцо" города Москвы Поправка: Гл.4.Прил.2.2.п.2.2.29_04.00.01.35.003 Наименование: При демонтаже оборудования, предназначенного в лом | CO28: 0 | CP28: =(P28+Q28+S28) -> 69.62 | CQ28: =ROUND((ROUND((AC28*AW28*1),2)*BC28),2) -> 0 | CR28: =(ROUND((ROUND(((((ET28*1.2)*0.3))*AV28*1),2)*BB28),2)+ROUND((ROUND(((AE28-(((EU28*1.2)*0.3)))*AV28*1),2)*BS28),2)) -> 0.02 | CS28: =(ROUND((ROUND(((((EU28*1.2)*0.3))*AV28*1),2)*BS28),2)+ROUND((ROUND(((AE28-(((EU28*1.2)*0.3)))*AV28*1),2)*BS28),2)) -> 0 | CT28: =ROUND((ROUND((AF28*AV28*1),2)*BA28),2) -> 8.68 | CU28: =AG28 -> 0 | CV28: =(AH28*AV28) -> 0.678456 | CW28: =AI28 -> 0 | CX28: =AJ28 -> 0 | CY28: =(ROUND((((S28+ROUND((ROUND(((((EU28*1.2)*0.3))*AV28*1),2)*BS28),2))*AT28)/100),2)+ROUND(((ROUND((ROUND(((AE28-(((EU28*1.2)*0.3)))*AV28*1),2)*BS28),2)*AT28)/100),2)) -> 62.52 | CZ28: =(ROUND((((S28+ROUND((ROUND(((((EU28*1.2)*0.3))*AV28*1),2)*BS28),2))*AU28)/100),2)+ROUND(((ROUND((ROUND(((AE28-(((EU28*1.2)*0.3)))*AV28*1),2)*BS28),2)*AU28)/100),2)) -> 31.96 | DB28: 1 | DD28: *1)*0 | DE28: *1,2)*0,3 | DF28: *1,2)*0,3 | DG28: *1,2)*0,3 | DI28: *1,2)*0,3 | DJ28: *1,2)*0,3 | DN28: 0 | DO28: 0 | DP28: 1 | DQ28: 1 | DU28: 1013 | DV28: 1 ШТ. | DW28: 1 ШТ. | DX28: 1 | EE28: 55393700 | EF28: 40 | EG28: Монтаж оборудования | EH28: 0 | EJ28: 2 | EK28: 68 | EL28: ТСН-2001.4-10. Прокладка и монтаж сетей связи | EM28: ТСН-2001.4-10-1 | EO28: Поправка: Гл.12.Прил.8.п.8. 3_12.00.01.11.001 Поправка: Гл.4.Прил.2.2.п.2.2.29_04.00.01.35.003 | EQ28: 0 | ER28: 26.52 | ES28: 3.43 | ET28: 0.05 | EU28: 0.01 | EV28: 23.04 | EW28: 1.8 | EX28: 0 | EY28: 0 | FQ28: 0 | FR28: 0 | FS28: 0 | FX28: 90 | FY28: 46 | GD28: 1 | GF28: -2080333219 | GG28: 2 | GH28: 1 | GI28: 2 | GJ28: 0 | GK28: 0 | GL28: =ROUND(IF(AND(BH28=3,BI28=3,FS28<>0),P28,0),2) -> 0 | GM28: =ROUND(O28+X28+Y28,2)+GX28 -> 164.14 | GN28: =IF(OR(BI28=0,BI28=1),GM28-GX28,0) -> 0 | GO28: =IF(BI28=2,GM28-GX28,0) -> 164.14 | GP28: =IF(BI28=4,GM28-GX28,0) -> 0 | GR28: 0 | GS28: 3 | GT28: 0 | GV28: =ROUND((GT28),6) -> 0 | GW28: 1 | GX28: =ROUND(HC28*I28,2) -> 0 | HA28: 0 | HB28: 0 | HC28: =GV28*GW28 -> 0 | HS28: 0 | IK28: 0
A29: 17 | B29: 1 | C29: =ROW(SmtRes!A2) -> 2 | D29: =ROW(EtalonRes!A2) -> 2 | E29: 1 | F29: 4.10-80-5 | G29: Аппараты приемные, приборы ПС приемно-контрольные, пусковые, прибор ПС на 1 луч / демонтаж модуля автоматики пожаротушения | H29: 1 ШТ. | I29: 8 | J29: 0 | K29: 8 | O29: =ROUND(CP29,2) -> 3917.63 | P29: =ROUND((ROUND((AC29*AW29*I29),2)*BC29),2) -> 0 | Q29: =(ROUND((ROUND(((((ET29*1.2)*0.3))*AV29*I29),2)*BB29),2)+ROUND((ROUND(((AE29-(((EU29*1.2)*0.3)))*AV29*I29),2)*BS29),2)) -> 3 | R29: =(ROUND((ROUND(((((EU29*1.2)*0.3))*AV29*I29),2)*BS29),2)+ROUND((ROUND(((AE29-(((EU29*1.2)*0.3)))*AV29*I29),2)*BS29),2)) -> 1.69 | S29: =ROUND((ROUND((AF29*AV29*I29),2)*BA29),2) -> 3914.63 | T29: =ROUND(CU29*I29,2) -> 0 | U29: =CV29*I29 -> 5.427648 | V29: =CW29*I29 -> 0 | W29: =ROUND(CX29*I29,2) -> 0 | X29: =(ROUND((((S29+ROUND((ROUND(((((EU29*1.2)*0.3))*AV29*I29),2)*BS29),2))*AT29)/100),2)+ROUND(((ROUND((ROUND(((AE29-(((EU29*1.2)*0.3)))*AV29*I29),2)*BS29),2)*AT29)/100),2)) -> 3524.69 | Y29: =(ROUND((((S29+ROUND((ROUND(((((EU29*1.2)*0.3))*AV29*I29),2)*BS29),2))*AU29)/100),2)+ROUND(((ROUND((ROUND(((AE29-(((EU29*1.2)*0.3)))*AV29*I29),2)*BS29),2)*AU29)/100),2)) -> 1801.51 | AA29: 55937298 | AB29: =ROUND((AC29+AD29+AF29),6) -> 8.3124 | AC29: =ROUND((((ES29*1)*0)),6) -> 0 | AD29: =ROUND((((((ET29*1.2)*0.3))-(((EU29*1.2)*0.3)))+AE29),6) -> 0.018 | AE29: =ROUND((((EU29*1.2)*0.3)),6) -> 0.0036 | AF29: =ROUND((((EV29*1.2)*0.3)),6) -> 8.2944 | AG29: =ROUND((AP29),6) -> 0 | AH29: =(((EW29*1.2)*0.3)) -> 0.648 | AI29: =(((EX29*1.2)*0.3)) -> 0 | AJ29: =(AS29) -> 0 | AK29: 26.52 | AL29: 3.43 | AM29: 0.05 | AN29: 0.01 | AO29: 23.04 | AP29: 0 | AQ29: 1.8 | AR29: 0 | AS29: 0 | AT29: 90 | AU29: 46 | AV29: 1.047 | AW29: 1 | AZ29: 1 | BA29: 56.35 | BB29: 20 | BC29: 9.84 | BH29: 0 | BI29: 2 | BJ29: ТСН-2001.4. Доп. 1-42. Сб. 10, т. 80, поз. 5 | BM29: 68 | BN29: 0 | BO29: 4.10-80-5 | BP29: 1 | BQ29: 40 | BR29: 0 | BS29: 56.35 | BT29: 1 | BU29: 1 | BV29: 1 | BW29: 1 | BX29: 1 | BZ29: 90 | CA29: 46 | CE29: 1566 | CF29: 0 | CG29: 0 | CM29: 0 | CN29: Поправка: Гл.12.Прил.8.п.8. 3_12.00.01.11.001 Наименование: При наличии напряженных и стесненных условий производства работ (стесненность, сложность складирования и транспортной логистики и т.п.) для объектов, расположенных в пределах круговой магистральной системы улиц "Садовое кольцо" города Москвы Поправка: Гл.4.Прил.2.2.п.2.2.29_04.00.01.35.003 Наименование: При демонтаже оборудования, предназначенного в лом | CO29: 0 | CP29: =(P29+Q29+S29) -> 3917.63 | CQ29: =ROUND((ROUND((AC29*AW29*1),2)*BC29),2) -> 0 | CR29: =(ROUND((ROUND(((((ET29*1.2)*0.3))*AV29*1),2)*BB29),2)+ROUND((ROUND(((AE29-(((EU29*1.2)*0.3)))*AV29*1),2)*BS29),2)) -> 0.4 | CS29: =(ROUND((ROUND(((((EU29*1.2)*0.3))*AV29*1),2)*BS29),2)+ROUND((ROUND(((AE29-(((EU29*1.2)*0.3)))*AV29*1),2)*BS29),2)) -> 0 | CT29: =ROUND((ROUND((AF29*AV29*1),2)*BA29),2) -> 489.12 | CU29: =AG29 -> 0 | CV29: =(AH29*AV29) -> 0.678456 | CW29: =AI29 -> 0 | CX29: =AJ29 -> 0 | CY29: =(ROUND((((S29+ROUND((ROUND(((((EU29*1.2)*0.3))*AV29*1),2)*BS29),2))*AT29)/100),2)+ROUND(((ROUND((ROUND(((AE29-(((EU29*1.2)*0.3)))*AV29*1),2)*BS29),2)*AT29)/100),2)) -> 3523.17 | CZ29: =(ROUND((((S29+ROUND((ROUND(((((EU29*1.2)*0.3))*AV29*1),2)*BS29),2))*AU29)/100),2)+ROUND(((ROUND((ROUND(((AE29-(((EU29*1.2)*0.3)))*AV29*1),2)*BS29),2)*AU29)/100),2)) -> 1800.73 | DB29: 3 | DD29: *1)*0 | DE29: *1,2)*0,3 | DF29: *1,2)*0,3 | DG29: *1,2)*0,3 | DI29: *1,2)*0,3 | DJ29: *1,2)*0,3 | DN29: 0 | DO29: 0 | DP29: 1 | DQ29: 1 | DU29: 1013 | DV29: 1 ШТ. | DW29: 1 ШТ. | DX29: 1 | EE29: 55393700 | EF29: 40 | EG29: Монтаж оборудования | EH29: 0 | EJ29: 2 | EK29: 68 | EL29: ТСН-2001.4-10. Прокладка и монтаж сетей связи | EM29: ТСН-2001.4-10-1 | EO29: Поправка: Гл.12.Прил.8.п.8. 3_12.00.01.11.001 Поправка: Гл.4.Прил.2.2.п.2.2.29_04.00.01.35.003 | EQ29: 0 | ER29: 26.52 | ES29: 3.43 | ET29: 0.05 | EU29: 0.01 | EV29: 23.04 | EW29: 1.8 | EX29: 0 | EY29: 0 | FQ29: 0 | FR29: 0 | FS29: 0 | FX29: 90 | FY29: 46 | GD29: 1 | GF29: -2080333219 | GG29: 2 | GH29: 1 | GI29: 2 | GJ29: 0 | GK29: 0 | GL29: =ROUND(IF(AND(BH29=3,BI29=3,FS29<>0),P29,0),2) -> 0 | GM29: =ROUND(O29+X29+Y29,2)+GX29 -> 9243.83 | GN29: =IF(OR(BI29=0,BI29=1),GM29-GX29,0) -> 0 | GO29: =IF(BI29=2,GM29-GX29,0) -> 9243.83 | GP29: =IF(BI29=4,GM29-GX29,0) -> 0 | GR29: 0 | GS29: 3 | GT29: 0 | GV29: =ROUND((GT29),6) -> 0 | GW29: 1 | GX29: =ROUND(HC29*I29,2) -> 0 | HA29: 0 | HB29: 0 | HC29: =GV29*GW29 -> 0 | HS29: 0 | IK29: 0
A30: 17 | B30: 1 | C30: =ROW(SmtRes!A3) -> 3 | D30: =ROW(EtalonRes!A3) -> 3 | E30: 2 | F30: 4.10-80-2 | G30: Аппараты приемные, приборы ПС приемно-контрольные, пусковые, концентратор, блок базовый на 20 лучей / демонтаж прибора приемно-контрольного и управления охранно-пожарного | H30: 1 ШТ. | I30: 1 | J30: 0 | K30: 1 | O30: =ROUND(CP30,2) -> 58.23 | P30: =ROUND((ROUND((AC30*AW30*I30),2)*BC30),2) -> 0 | Q30: =(ROUND((ROUND(((((ET30*1.2)*0.3))*AV30*I30),2)*BB30),2)+ROUND((ROUND(((AE30-(((EU30*1.2)*0.3)))*AV30*I30),2)*BS30),2)) -> 0.02 | R30: =(ROUND((ROUND(((((EU30*1.2)*0.3))*AV30*I30),2)*BS30),2)+ROUND((ROUND(((AE30-(((EU30*1.2)*0.3)))*AV30*I30),2)*BS30),2)) -> 0 | S30: =ROUND((ROUND((AF30*AV30*I30),2)*BA30),2) -> 58.21 | T30: =ROUND(CU30*I30,2) -> 0 | U30: =CV30*I30 -> 4.409964 | V30: =CW30*I30 -> 0 | W30: =ROUND(CX30*I30,2) -> 0 | X30: =(ROUND((((S30+ROUND((ROUND(((((EU30*1.2)*0.3))*AV30*I30),2)*BS30),2))*AT30)/100),2)+ROUND(((ROUND((ROUND(((AE30-(((EU30*1.2)*0.3)))*AV30*I30),2)*BS30),2)*AT30)/100),2)) -> 52.39 | Y30: =(ROUND((((S30+ROUND((ROUND(((((EU30*1.2)*0.3))*AV30*I30),2)*BS30),2))*AU30)/100),2)+ROUND(((ROUND((ROUND(((AE30-(((EU30*1.2)*0.3)))*AV30*I30),2)*BS30),2)*AU30)/100),2)) -> 26.78 | AA30: 55937296 | AB30: =ROUND((AC30+AD30+AF30),6) -> 55.62 | AC30: =ROUND((((ES30*1)*0)),6) -> 0 | AD30: =ROUND((((((ET30*1.2)*0.3))-(((EU30*1.2)*0.3)))+AE30),6) -> 0.0216 | AE30: =ROUND((((EU30*1.2)*0.3)),6) -> 0.0036 | AF30: =ROUND((((EV30*1.2)*0.3)),6) -> 55.5984 | AG30: =ROUND((AP30),6) -> 0 | AH30: =(((EW30*1.2)*0.3)) -> 4.212 | AI30: =(((EX30*1.2)*0.3)) -> 0 | AJ30: =(AS30) -> 0 | AK30: 175.43 | AL30: 20.93 | AM30: 0.06 | AN30: 0.01 | AO30: 154.44 | AP30: 0 | AQ30: 11.7 | AR30: 0 | AS30: 0 | AT30: 90 | AU30: 46 | AV30: 1.047 | AW30: 1 | AZ30: 1 | BA30: 1 | BB30: 1 | BC30: 1 | BH30: 0 | BI30: 2 | BJ30: ТСН-2001.4 Доп. 68, Сб. 10, т. 80, поз. 2 | BM30: 68 | BN30: 0 | BO30: 4.10-80-2 | BP30: 1 | BQ30: 40 | BR30: 0 | BS30: 1 | BT30: 1 | BU30: 1 | BV30: 1 | BW30: 1 | BX30: 1 | BZ30: 90 | CA30: 46 | CE30: 1566 | CF30: 0 | CG30: 0 | CM30: 0 | CN30: Поправка: Гл.12.Прил.8.п.8. 3_12.00.01.11.001 Наименование: При наличии напряженных и стесненных условий производства работ (стесненность, сложность складирования и транспортной логистики и т.п.) для объектов, расположенных в пределах круговой магистральной системы улиц "Садовое кольцо" города Москвы Поправка: Гл.4.Прил.2.2.п.2.2.29_04.00.01.35.003 Наименование: При демонтаже оборудования, предназначенного в лом | CO30: 0 | CP30: =(P30+Q30+S30) -> 58.23 | CQ30: =ROUND((ROUND((AC30*AW30*1),2)*BC30),2) -> 0 | CR30: =(ROUND((ROUND(((((ET30*1.2)*0.3))*AV30*1),2)*BB30),2)+ROUND((ROUND(((AE30-(((EU30*1.2)*0.3)))*AV30*1),2)*BS30),2)) -> 0.02 | CS30: =(ROUND((ROUND(((((EU30*1.2)*0.3))*AV30*1),2)*BS30),2)+ROUND((ROUND(((AE30-(((EU30*1.2)*0.3)))*AV30*1),2)*BS30),2)) -> 0 | CT30: =ROUND((ROUND((AF30*AV30*1),2)*BA30),2) -> 58.21 | CU30: =AG30 -> 0 | CV30: =(AH30*AV30) -> 4.409964 | CW30: =AI30 -> 0 | CX30: =AJ30 -> 0 | CY30: =(ROUND((((S30+ROUND((ROUND(((((EU30*1.2)*0.3))*AV30*1),2)*BS30),2))*AT30)/100),2)+ROUND(((ROUND((ROUND(((AE30-(((EU30*1.2)*0.3)))*AV30*1),2)*BS30),2)*AT30)/100),2)) -> 52.39 | CZ30: =(ROUND((((S30+ROUND((ROUND(((((EU30*1.2)*0.3))*AV30*1),2)*BS30),2))*AU30)/100),2)+ROUND(((ROUND((ROUND(((AE30-(((EU30*1.2)*0.3)))*AV30*1),2)*BS30),2)*AU30)/100),2)) -> 26.78 | DB30: 5 | DD30: *1)*0 | DE30: *1,2)*0,3 | DF30: *1,2)*0,3 | DG30: *1,2)*0,3 | DI30: *1,2)*0,3 | DJ30: *1,2)*0,3 | DN30: 0 | DO30: 0 | DP30: 1 | DQ30: 1 | DU30: 1013 | DV30: 1 ШТ. | DW30: 1 ШТ. | DX30: 1 | EE30: 55393700 | EF30: 40 | EG30: Монтаж оборудования | EH30: 0 | EJ30: 2 | EK30: 68 | EL30: ТСН-2001.4-10. Прокладка и монтаж сетей связи | EM30: ТСН-2001.4-10-1 | EO30: Поправка: Гл.12.Прил.8.п.8. 3_12.00.01.11.001 Поправка: Гл.4.Прил.2.2.п.2.2.29_04.00.01.35.003 | EQ30: 0 | ER30: 175.43 | ES30: 20.93 | ET30: 0.06 | EU30: 0.01 | EV30: 154.44 | EW30: 11.7 | EX30: 0 | EY30: 0 | FQ30: 0 | FR30: 0 | FS30: 0 | FX30: 90 | FY30: 46 | GD30: 1 | GF30: 625023618 | GG30: 2 | GH30: 1 | GI30: 2 | GJ30: 0 | GK30: 0 | GL30: =ROUND(IF(AND(BH30=3,BI30=3,FS30<>0),P30,0),2) -> 0 | GM30: =ROUND(O30+X30+Y30,2)+GX30 -> 137.4 | GN30: =IF(OR(BI30=0,BI30=1),GM30-GX30,0) -> 0 | GO30: =IF(BI30=2,GM30-GX30,0) -> 137.4 | GP30: =IF(BI30=4,GM30-GX30,0) -> 0 | GR30: 0 | GS30: 3 | GT30: 0 | GV30: =ROUND((GT30),6) -> 0 | GW30: 1 | GX30: =ROUND(HC30*I30,2) -> 0 | HA30: 0 | HB30: 0 | HC30: =GV30*GW30 -> 0 | HS30: 0 | IK30: 0
A31: 17 | B31: 1 | C31: =ROW(SmtRes!A4) -> 4 | D31: =ROW(EtalonRes!A4) -> 4 | E31: 2 | F31: 4.10-80-2 | G31: Аппараты приемные, приборы ПС приемно-контрольные, пусковые, концентратор, блок базовый на 20 лучей / демонтаж прибора приемно-контрольного и управления охранно-пожарного | H31: 1 ШТ. | I31: 1 | J31: 0 | K31: 1 | O31: =ROUND(CP31,2) -> 3280.5 | P31: =ROUND((ROUND((AC31*AW31*I31),2)*BC31),2) -> 0 | Q31: =(ROUND((ROUND(((((ET31*1.2)*0.3))*AV31*I31),2)*BB31),2)+ROUND((ROUND(((AE31-(((EU31*1.2)*0.3)))*AV31*I31),2)*BS31),2)) -> 0.37 | R31: =(ROUND((ROUND(((((EU31*1.2)*0.3))*AV31*I31),2)*BS31),2)+ROUND((ROUND(((AE31-(((EU31*1.2)*0.3)))*AV31*I31),2)*BS31),2)) -> 0 | S31: =ROUND((ROUND((AF31*AV31*I31),2)*BA31),2) -> 3280.13 | T31: =ROUND(CU31*I31,2) -> 0 | U31: =CV31*I31 -> 4.409964 | V31: =CW31*I31 -> 0 | W31: =ROUND(CX31*I31,2) -> 0 | X31: =(ROUND((((S31+ROUND((ROUND(((((EU31*1.2)*0.3))*AV31*I31),2)*BS31),2))*AT31)/100),2)+ROUND(((ROUND((ROUND(((AE31-(((EU31*1.2)*0.3)))*AV31*I31),2)*BS31),2)*AT31)/100),2)) -> 2952.12 | Y31: =(ROUND((((S31+ROUND((ROUND(((((EU31*1.2)*0.3))*AV31*I31),2)*BS31),2))*AU31)/100),2)+ROUND(((ROUND((ROUND(((AE31-(((EU31*1.2)*0.3)))*AV31*I31),2)*BS31),2)*AU31)/100),2)) -> 1508.86 | AA31: 55937298 | AB31: =ROUND((AC31+AD31+AF31),6) -> 55.62 | AC31: =ROUND((((ES31*1)*0)),6) -> 0 | AD31: =ROUND((((((ET31*1.2)*0.3))-(((EU31*1.2)*0.3)))+AE31),6) -> 0.0216 | AE31: =ROUND((((EU31*1.2)*0.3)),6) -> 0.0036 | AF31: =ROUND((((EV31*1.2)*0.3)),6) -> 55.5984 | AG31: =ROUND((AP31),6) -> 0 | AH31: =(((EW31*1.2)*0.3)) -> 4.212 | AI31: =(((EX31*1.2)*0.3)) -> 0 | AJ31: =(AS31) -> 0 | AK31: 175.43 | AL31: 20.93 | AM31: 0.06 | AN31: 0.01 | AO31: 154.44 | AP31: 0 | AQ31: 11.7 | AR31: 0 | AS31: 0 | AT31: 90 | AU31: 46 | AV31: 1.047 | AW31: 1 | AZ31: 1 | BA31: 56.35 | BB31: 18.5 | BC31: 9.84 | BH31: 0 | BI31: 2 | BJ31: ТСН-2001.4 Доп. 68, Сб. 10, т. 80, поз. 2 | BM31: 68 | BN31: 0 | BO31: 4.10-80-2 | BP31: 1 | BQ31: 40 | BR31: 0 | BS31: 56.35 | BT31: 1 | BU31: 1 | BV31: 1 | BW31: 1 | BX31: 1 | BZ31: 90 | CA31: 46 | CE31: 1566 | CF31: 0 | CG31: 0 | CM31: 0 | CN31: Поправка: Гл.12.Прил.8.п.8. 3_12.00.01.11.001 Наименование: При наличии напряженных и стесненных условий производства работ (стесненность, сложность складирования и транспортной логистики и т.п.) для объектов, расположенных в пределах круговой магистральной системы улиц "Садовое кольцо" города Москвы Поправка: Гл.4.Прил.2.2.п.2.2.29_04.00.01.35.003 Наименование: При демонтаже оборудования, предназначенного в лом | CO31: 0 | CP31: =(P31+Q31+S31) -> 3280.5 | CQ31: =ROUND((ROUND((AC31*AW31*1),2)*BC31),2) -> 0 | CR31: =(ROUND((ROUND(((((ET31*1.2)*0.3))*AV31*1),2)*BB31),2)+ROUND((ROUND(((AE31-(((EU31*1.2)*0.3)))*AV31*1),2)*BS31),2)) -> 0.37 | CS31: =(ROUND((ROUND(((((EU31*1.2)*0.3))*AV31*1),2)*BS31),2)+ROUND((ROUND(((AE31-(((EU31*1.2)*0.3)))*AV31*1),2)*BS31),2)) -> 0 | CT31: =ROUND((ROUND((AF31*AV31*1),2)*BA31),2) -> 3280.13 | CU31: =AG31 -> 0 | CV31: =(AH31*AV31) -> 4.409964 | CW31: =AI31 -> 0 | CX31: =AJ31 -> 0 | CY31: =(ROUND((((S31+ROUND((ROUND(((((EU31*1.2)*0.3))*AV31*1),2)*BS31),2))*AT31)/100),2)+ROUND(((ROUND((ROUND(((AE31-(((EU31*1.2)*0.3)))*AV31*1),2)*BS31),2)*AT31)/100),2)) -> 2952.12 | CZ31: =(ROUND((((S31+ROUND((ROUND(((((EU31*1.2)*0.3))*AV31*1),2)*BS31),2))*AU31)/100),2)+ROUND(((ROUND((ROUND(((AE31-(((EU31*1.2)*0.3)))*AV31*1),2)*BS31),2)*AU31)/100),2)) -> 1508.86 | DB31: 7 | DD31: *1)*0 | DE31: *1,2)*0,3 | DF31: *1,2)*0,3 | DG31: *1,2)*0,3 | DI31: *1,2)*0,3 | DJ31: *1,2)*0,3 | DN31: 0 | DO31: 0 | DP31: 1 | DQ31: 1 | DU31: 1013 | DV31: 1 ШТ. | DW31: 1 ШТ. | DX31: 1 | EE31: 55393700 | EF31: 40 | EG31: Монтаж оборудования | EH31: 0 | EJ31: 2 | EK31: 68 | EL31: ТСН-2001.4-10. Прокладка и монтаж сетей связи | EM31: ТСН-2001.4-10-1 | EO31: Поправка: Гл.12.Прил.8.п.8. 3_12.00.01.11.001 Поправка: Гл.4.Прил.2.2.п.2.2.29_04.00.01.35.003 | EQ31: 0 | ER31: 175.43 | ES31: 20.93 | ET31: 0.06 | EU31: 0.01 | EV31: 154.44 | EW31: 11.7 | EX31: 0 | EY31: 0 | FQ31: 0 | FR31: 0 | FS31: 0 | FX31: 90 | FY31: 46 | GD31: 1 | GF31: 625023618 | GG31: 2 | GH31: 1 | GI31: 2 | GJ31: 0 | GK31: 0 | GL31: =ROUND(IF(AND(BH31=3,BI31=3,FS31<>0),P31,0),2) -> 0 | GM31: =ROUND(O31+X31+Y31,2)+GX31 -> 7741.48 | GN31: =IF(OR(BI31=0,BI31=1),GM31-GX31,0) -> 0 | GO31: =IF(BI31=2,GM31-GX31,0) -> 7741.48 | GP31: =IF(BI31=4,GM31-GX31,0) -> 0 | GR31: 0 | GS31: 3 | GT31: 0 | GV31: =ROUND((GT31),6) -> 0 | GW31: 1 | GX31: =ROUND(HC31*I31,2) -> 0 | HA31: 0 | HB31: 0 | HC31: =GV31*GW31 -> 0 | HS31: 0 | IK31: 0
A32: 17 | B32: 1 | C32: =ROW(SmtRes!A13) -> 13 | D32: =ROW(EtalonRes!A18) -> 18 | E32: 3 | F32: 4.10-163-2 | G32: Монтаж охранно-пожарного пульта (ОПП) в диспетчерской / демонтаж пульта дистанционного управления | H32: 1 устройство | I32: 1 | J32: 0 | K32: 1 | O32: =ROUND(CP32,2) -> 30.59 | P32: =ROUND((ROUND((AC32*AW32*I32),2)*BC32),2) -> 0 | Q32: =(ROUND((ROUND(((((ET32*1.2)*0.3))*AV32*I32),2)*BB32),2)+ROUND((ROUND(((AE32-(((EU32*1.2)*0.3)))*AV32*I32),2)*BS32),2)) -> 0.31 | R32: =(ROUND((ROUND(((((EU32*1.2)*0.3))*AV32*I32),2)*BS32),2)+ROUND((ROUND(((AE32-(((EU32*1.2)*0.3)))*AV32*I32),2)*BS32),2)) -> 0 | S32: =ROUND((ROUND((AF32*AV32*I32),2)*BA32),2) -> 30.28 | T32: =ROUND(CU32*I32,2) -> 0 | U32: =CV32*I32 -> 2.2652892 | V32: =CW32*I32 -> 0 | W32: =ROUND(CX32*I32,2) -> 0 | X32: =(ROUND((((S32+ROUND((ROUND(((((EU32*1.2)*0.3))*AV32*I32),2)*BS32),2))*AT32)/100),2)+ROUND(((ROUND((ROUND(((AE32-(((EU32*1.2)*0.3)))*AV32*I32),2)*BS32),2)*AT32)/100),2)) -> 27.25 | Y32: =(ROUND((((S32+ROUND((ROUND(((((EU32*1.2)*0.3))*AV32*I32),2)*BS32),2))*AU32)/100),2)+ROUND(((ROUND((ROUND(((AE32-(((EU32*1.2)*0.3)))*AV32*I32),2)*BS32),2)*AU32)/100),2)) -> 13.93 | AA32: 55937296 | AB32: =ROUND((AC32+AD32+AF32),6) -> 29.214 | AC32: =ROUND((((ES32*1)*0)),6) -> 0 | AD32: =ROUND((((((ET32*1.2)*0.3))-(((EU32*1.2)*0.3)))+AE32),6) -> 0.2952 | AE32: =ROUND((((EU32*1.2)*0.3)),6) -> 0 | AF32: =ROUND((((EV32*1.2)*0.3)),6) -> 28.9188 | AG32: =ROUND((AP32),6) -> 0 | AH32: =(((EW32*1.2)*0.3)) -> 2.1636 | AI32: =(((EX32*1.2)*0.3)) -> 0 | AJ32: =(AS32) -> 0 | AK32: 90.3 | AL32: 9.15 | AM32: 0.82 | AN32: 0 | AO32: 80.33 | AP32: 0 | AQ32: 6.01 | AR32: 0 | AS32: 0 | AT32: 90 | AU32: 46 | AV32: 1.047 | AW32: 1 | AZ32: 1 | BA32: 1 | BB32: 1 | BC32: 1 | BH32: 0 | BI32: 2 | BJ32: ТСН-2001.4 Доп. 70, Сб. 10, т. 163, поз. 2 | BM32: 68 | BN32: 0 | BO32: 4.10-163-2 | BP32: 1 | BQ32: 40 | BR32: 0 | BS32: 1 | BT32: 1 | BU32: 1 | BV32: 1 | BW32: 1 | BX32: 1 | BZ32: 90 | CA32: 46 | CE32: 1566 | CF32: 0 | CG32: 0 | CM32: 0 | CN32: Поправка: Гл.12.Прил.8.п.8. 3_12.00.01.11.001 Наименование: При наличии напряженных и стесненных условий производства работ (стесненность, сложность складирования и транспортной логистики и т.п.) для объектов, расположенных в пределах круговой магистральной системы улиц "Садовое кольцо" города Москвы Поправка: Гл.4.Прил.2.2.п.2.2.29_04.00.01.35.003 Наименование: При демонтаже оборудования, предназначенного в лом | CO32: 0 | CP32: =(P32+Q32+S32) -> 30.59 | CQ32: =ROUND((ROUND((AC32*AW32*1),2)*BC32),2) -> 0 | CR32: =(ROUND((ROUND(((((ET32*1.2)*0.3))*AV32*1),2)*BB32),2)+ROUND((ROUND(((AE32-(((EU32*1.2)*0.3)))*AV32*1),2)*BS32),2)) -> 0.31 | CS32: =(ROUND((ROUND(((((EU32*1.2)*0.3))*AV32*1),2)*BS32),2)+ROUND((ROUND(((AE32-(((EU32*1.2)*0.3)))*AV32*1),2)*BS32),2)) -> 0 | CT32: =ROUND((ROUND((AF32*AV32*1),2)*BA32),2) -> 30.28 | CU32: =AG32 -> 0 | CV32: =(AH32*AV32) -> 2.2652892 | CW32: =AI32 -> 0 | CX32: =AJ32 -> 0 | CY32: =(ROUND((((S32+ROUND((ROUND(((((EU32*1.2)*0.3))*AV32*1),2)*BS32),2))*AT32)/100),2)+ROUND(((ROUND((ROUND(((AE32-(((EU32*1.2)*0.3)))*AV32*1),2)*BS32),2)*AT32)/100),2)) -> 27.25 | CZ32: =(ROUND((((S32+ROUND((ROUND(((((EU32*1.2)*0.3))*AV32*1),2)*BS32),2))*AU32)/100),2)+ROUND(((ROUND((ROUND(((AE32-(((EU32*1.2)*0.3)))*AV32*1),2)*BS32),2)*AU32)/100),2)) -> 13.93 | DB32: 9 | DD32: *1)*0 | DE32: *1,2)*0,3 | DF32: *1,2)*0,3 | DG32: *1,2)*0,3 | DI32: *1,2)*0,3 | DJ32: *1,2)*0,3 | DN32: 0 | DO32: 0 | DP32: 1 | DQ32: 1 | DU32: 1013 | DV32: 1 устройство | DW32: 1 устройство | DX32: 1 | EE32: 55393700 | EF32: 40 | EG32: Монтаж оборудования | EH32: 0 | EJ32: 2 | EK32: 68 | EL32: ТСН-2001.4-10. Прокладка и монтаж сетей связи | EM32: ТСН-2001.4-10-1 | EO32: Поправка: Гл.12.Прил.8.п.8. 3_12.00.01.11.001 Поправка: Гл.4.Прил.2.2.п.2.2.29_04.00.01.35.003 | EQ32: 0 | ER32: 90.3 | ES32: 9.15 | ET32: 0.82 | EU32: 0 | EV32: 80.33 | EW32: 6.01 | EX32: 0 | EY32: 0 | FQ32: 0 | FR32: 0 | FS32: 0 | FX32: 90 | FY32: 46 | GD32: 1 | GF32: 1335746288 | GG32: 2 | GH32: 1 | GI32: 2 | GJ32: 0 | GK32: 0 | GL32: =ROUND(IF(AND(BH32=3,BI32=3,FS32<>0),P32,0),2) -> 0 | GM32: =ROUND(O32+X32+Y32,2)+GX32 -> 71.77 | GN32: =IF(OR(BI32=0,BI32=1),GM32-GX32,0) -> 0 | GO32: =IF(BI32=2,GM32-GX32,0) -> 71.77 | GP32: =IF(BI32=4,GM32-GX32,0) -> 0 | GR32: 0 | GS32: 3 | GT32: 0 | GV32: =ROUND((GT32),6) -> 0 | GW32: 1 | GX32: =ROUND(HC32*I32,2) -> 0 | HA32: 0 | HB32: 0 | HC32: =GV32*GW32 -> 0 | HS32: 0 | IK32: 0
A33: 17 | B33: 1 | C33: =ROW(SmtRes!A22) -> 22 | D33: =ROW(EtalonRes!A32) -> 32 | E33: 3 | F33: 4.10-163-2 | G33: Монтаж охранно-пожарного пульта (ОПП) в диспетчерской / демонтаж пульта дистанционного управления | H33: 1 устройство | I33: 1 | J33: 0 | K33: 1 | O33: =ROUND(CP33,2) -> 1709.23 | P33: =ROUND((ROUND((AC33*AW33*I33),2)*BC33),2) -> 0 | Q33: =(ROUND((ROUND(((((ET33*1.2)*0.3))*AV33*I33),2)*BB33),2)+ROUND((ROUND(((AE33-(((EU33*1.2)*0.3)))*AV33*I33),2)*BS33),2)) -> 2.95 | R33: =(ROUND((ROUND(((((EU33*1.2)*0.3))*AV33*I33),2)*BS33),2)+ROUND((ROUND(((AE33-(((EU33*1.2)*0.3)))*AV33*I33),2)*BS33),2)) -> 0 | S33: =ROUND((ROUND((AF33*AV33*I33),2)*BA33),2) -> 1706.28 | T33: =ROUND(CU33*I33,2) -> 0 | U33: =CV33*I33 -> 2.2652892 | V33: =CW33*I33 -> 0 | W33: =ROUND(CX33*I33,2) -> 0 | X33: =(ROUND((((S33+ROUND((ROUND(((((EU33*1.2)*0.3))*AV33*I33),2)*BS33),2))*AT33)/100),2)+ROUND(((ROUND((ROUND(((AE33-(((EU33*1.2)*0.3)))*AV33*I33),2)*BS33),2)*AT33)/100),2)) -> 1535.65 | Y33: =(ROUND((((S33+ROUND((ROUND(((((EU33*1.2)*0.3))*AV33*I33),2)*BS33),2))*AU33)/100),2)+ROUND(((ROUND((ROUND(((AE33-(((EU33*1.2)*0.3)))*AV33*I33),2)*BS33),2)*AU33)/100),2)) -> 784.89 | AA33: 55937298 | AB33: =ROUND((AC33+AD33+AF33),6) -> 29.214 | AC33: =ROUND((((ES33*1)*0)),6) -> 0 | AD33: =ROUND((((((ET33*1.2)*0.3))-(((EU33*1.2)*0.3)))+AE33),6) -> 0.2952 | AE33: =ROUND((((EU33*1.2)*0.3)),6) -> 0 | AF33: =ROUND((((EV33*1.2)*0.3)),6) -> 28.9188 | AG33: =ROUND((AP33),6) -> 0 | AH33: =(((EW33*1.2)*0.3)) -> 2.1636 | AI33: =(((EX33*1.2)*0.3)) -> 0 | AJ33: =(AS33) -> 0 | AK33: 90.3 | AL33: 9.15 | AM33: 0.82 | AN33: 0 | AO33: 80.33 | AP33: 0 | AQ33: 6.01 | AR33: 0 | AS33: 0 | AT33: 90 | AU33: 46 | AV33: 1.047 | AW33: 1 | AZ33: 1 | BA33: 56.35 | BB33: 9.52 | BC33: 6.42 | BH33: 0 | BI33: 2 | BJ33: ТСН-2001.4 Доп. 70, Сб. 10, т. 163, поз. 2 | BM33: 68 | BN33: 0 | BO33: 4.10-163-2 | BP33: 1 | BQ33: 40 | BR33: 0 | BS33: 56.35 | BT33: 1 | BU33: 1 | BV33: 1 | BW33: 1 | BX33: 1 | BZ33: 90 | CA33: 46 | CE33: 1566 | CF33: 0 | CG33: 0 | CM33: 0 | CN33: Поправка: Гл.12.Прил.8.п.8. 3_12.00.01.11.001 Наименование: При наличии напряженных и стесненных условий производства работ (стесненность, сложность складирования и транспортной логистики и т.п.) для объектов, расположенных в пределах круговой магистральной системы улиц "Садовое кольцо" города Москвы Поправка: Гл.4.Прил.2.2.п.2.2.29_04.00.01.35.003 Наименование: При демонтаже оборудования, предназначенного в лом | CO33: 0 | CP33: =(P33+Q33+S33) -> 1709.23 | CQ33: =ROUND((ROUND((AC33*AW33*1),2)*BC33),2) -> 0 | CR33: =(ROUND((ROUND(((((ET33*1.2)*0.3))*AV33*1),2)*BB33),2)+ROUND((ROUND(((AE33-(((EU33*1.2)*0.3)))*AV33*1),2)*BS33),2)) -> 2.95 | CS33: =(ROUND((ROUND(((((EU33*1.2)*0.3))*AV33*1),2)*BS33),2)+ROUND((ROUND(((AE33-(((EU33*1.2)*0.3)))*AV33*1),2)*BS33),2)) -> 0 | CT33: =ROUND((ROUND((AF33*AV33*1),2)*BA33),2) -> 1706.28 | CU33: =AG33 -> 0 | CV33: =(AH33*AV33) -> 2.2652892 | CW33: =AI33 -> 0 | CX33: =AJ33 -> 0 | CY33: =(ROUND((((S33+ROUND((ROUND(((((EU33*1.2)*0.3))*AV33*1),2)*BS33),2))*AT33)/100),2)+ROUND(((ROUND((ROUND(((AE33-(((EU33*1.2)*0.3)))*AV33*1),2)*BS33),2)*AT33)/100),2)) -> 1535.65 | CZ33: =(ROUND((((S33+ROUND((ROUND(((((EU33*1.2)*0.3))*AV33*1),2)*BS33),2))*AU33)/100),2)+ROUND(((ROUND((ROUND(((AE33-(((EU33*1.2)*0.3)))*AV33*1),2)*BS33),2)*AU33)/100),2)) -> 784.89 | DB33: 11 | DD33: *1)*0 | DE33: *1,2)*0,3 | DF33: *1,2)*0,3 | DG33: *1,2)*0,3 | DI33: *1,2)*0,3 | DJ33: *1,2)*0,3 | DN33: 0 | DO33: 0 | DP33: 1 | DQ33: 1 | DU33: 1013 | DV33: 1 устройство | DW33: 1 устройство | DX33: 1 | EE33: 55393700 | EF33: 40 | EG33: Монтаж оборудования | EH33: 0 | EJ33: 2 | EK33: 68 | EL33: ТСН-2001.4-10. Прокладка и монтаж сетей связи | EM33: ТСН-2001.4-10-1 | EO33: Поправка: Гл.12.Прил.8.п.8. 3_12.00.01.11.001 Поправка: Гл.4.Прил.2.2.п.2.2.29_04.00.01.35.003 | EQ33: 0 | ER33: 90.3 | ES33: 9.15 | ET33: 0.82 | EU33: 0 | EV33: 80.33 | EW33: 6.01 | EX33: 0 | EY33: 0 | FQ33: 0 | FR33: 0 | FS33: 0 | FX33: 90 | FY33: 46 | GD33: 1 | GF33: 1335746288 | GG33: 2 | GH33: 1 | GI33: 2 | GJ33: 0 | GK33: 0 | GL33: =ROUND(IF(AND(BH33=3,BI33=3,FS33<>0),P33,0),2) -> 0 | GM33: =ROUND(O33+X33+Y33,2)+GX33 -> 4029.77 | GN33: =IF(OR(BI33=0,BI33=1),GM33-GX33,0) -> 0 | GO33: =IF(BI33=2,GM33-GX33,0) -> 4029.77 | GP33: =IF(BI33=4,GM33-GX33,0) -> 0 | GR33: 0 | GS33: 3 | GT33: 0 | GV33: =ROUND((GT33),6) -> 0 | GW33: 1 | GX33: =ROUND(HC33*I33,2) -> 0 | HA33: 0 | HB33: 0 | HC33: =GV33*GW33 -> 0 | HS33: 0 | IK33: 0
A34: 17 | B34: 1 | C34: =ROW(SmtRes!A28) -> 28 | D34: =ROW(EtalonRes!A39) -> 39 | E34: 4 | F34: 4.10-167-1 | G34: Монтаж блока питания сети (БПС) в диспетчерской / демонтаж блоков электропитания | H34: 1 ШТ. | I34: =ROUND(4+1+1+8+2,9) -> 16 | J34: 0 | K34: =ROUND(4+1+1+8+2,9) -> 16 | O34: =ROUND(CP34,2) -> 114.34 | P34: =ROUND((ROUND((AC34*AW34*I34),2)*BC34),2) -> 0 | Q34: =(ROUND((ROUND(((((ET34*1.2)*0.3))*AV34*I34),2)*BB34),2)+ROUND((ROUND(((AE34-(((EU34*1.2)*0.3)))*AV34*I34),2)*BS34),2)) -> 0.12 | R34: =(ROUND((ROUND(((((EU34*1.2)*0.3))*AV34*I34),2)*BS34),2)+ROUND((ROUND(((AE34-(((EU34*1.2)*0.3)))*AV34*I34),2)*BS34),2)) -> 0 | S34: =ROUND((ROUND((AF34*AV34*I34),2)*BA34),2) -> 114.22 | T34: =ROUND(CU34*I34,2) -> 0 | U34: =CV34*I34 -> 8.2017792 | V34: =CW34*I34 -> 0 | W34: =ROUND(CX34*I34,2) -> 0 | X34: =(ROUND((((S34+ROUND((ROUND(((((EU34*1.2)*0.3))*AV34*I34),2)*BS34),2))*AT34)/100),2)+ROUND(((ROUND((ROUND(((AE34-(((EU34*1.2)*0.3)))*AV34*I34),2)*BS34),2)*AT34)/100),2)) -> 102.8 | Y34: =(ROUND((((S34+ROUND((ROUND(((((EU34*1.2)*0.3))*AV34*I34),2)*BS34),2))*AU34)/100),2)+ROUND(((ROUND((ROUND(((AE34-(((EU34*1.2)*0.3)))*AV34*I34),2)*BS34),2)*AU34)/100),2)) -> 52.54 | AA34: 55937296 | AB34: =ROUND((AC34+AD34+AF34),6) -> 6.8256 | AC34: =ROUND((((ES34*1)*0)),6) -> 0 | AD34: =ROUND((((((ET34*1.2)*0.3))-(((EU34*1.2)*0.3)))+AE34),6) -> 0.0072 | AE34: =ROUND((((EU34*1.2)*0.3)),6) -> 0 | AF34: =ROUND((((EV34*1.2)*0.3)),6) -> 6.8184 | AG34: =ROUND((AP34),6) -> 0 | AH34: =(((EW34*1.2)*0.3)) -> 0.4896 | AI34: =(((EX34*1.2)*0.3)) -> 0 | AJ34: =(AS34) -> 0 | AK34: 21.3 | AL34: 2.34 | AM34: 0.02 | AN34: 0 | AO34: 18.94 | AP34: 0 | AQ34: 1.36 | AR34: 0 | AS34: 0 | AT34: 90 | AU34: 46 | AV34: 1.047 | AW34: 1 | AZ34: 1 | BA34: 1 | BB34: 1 | BC34: 1 | BH34: 0 | BI34: 2 | BJ34: ТСН-2001.4 Доп. 69, Сб. 10, т. 167, поз. 1 | BM34: 68 | BN34: 0 | BO34: 4.10-167-1 | BP34: 1 | BQ34: 40 | BR34: 0 | BS34: 1 | BT34: 1 | BU34: 1 | BV34: 1 | BW34: 1 | BX34: 1 | BZ34: 90 | CA34: 46 | CE34: 1566 | CF34: 0 | CG34: 0 | CM34: 0 | CN34: Поправка: Гл.12.Прил.8.п.8. 3_12.00.01.11.001 Наименование: При наличии напряженных и стесненных условий производства работ (стесненность, сложность складирования и транспортной логистики и т.п.) для объектов, расположенных в пределах круговой магистральной системы улиц "Садовое кольцо" города Москвы Поправка: Гл.4.Прил.2.2.п.2.2.29_04.00.01.35.003 Наименование: При демонтаже оборудования, предназначенного в лом | CO34: 0 | CP34: =(P34+Q34+S34) -> 114.34 | CQ34: =ROUND((ROUND((AC34*AW34*1),2)*BC34),2) -> 0 | CR34: =(ROUND((ROUND(((((ET34*1.2)*0.3))*AV34*1),2)*BB34),2)+ROUND((ROUND(((AE34-(((EU34*1.2)*0.3)))*AV34*1),2)*BS34),2)) -> 0.01 | CS34: =(ROUND((ROUND(((((EU34*1.2)*0.3))*AV34*1),2)*BS34),2)+ROUND((ROUND(((AE34-(((EU34*1.2)*0.3)))*AV34*1),2)*BS34),2)) -> 0 | CT34: =ROUND((ROUND((AF34*AV34*1),2)*BA34),2) -> 7.14 | CU34: =AG34 -> 0 | CV34: =(AH34*AV34) -> 0.5126112 | CW34: =AI34 -> 0 | CX34: =AJ34 -> 0 | CY34: =(ROUND((((S34+ROUND((ROUND(((((EU34*1.2)*0.3))*AV34*1),2)*BS34),2))*AT34)/100),2)+ROUND(((ROUND((ROUND(((AE34-(((EU34*1.2)*0.3)))*AV34*1),2)*BS34),2)*AT34)/100),2)) -> 102.8 | CZ34: =(ROUND((((S34+ROUND((ROUND(((((EU34*1.2)*0.3))*AV34*1),2)*BS34),2))*AU34)/100),2)+ROUND(((ROUND((ROUND(((AE34-(((EU34*1.2)*0.3)))*AV34*1),2)*BS34),2)*AU34)/100),2)) -> 52.54 | DB34: 13 | DD34: *1)*0 | DE34: *1,2)*0,3 | DF34: *1,2)*0,3 | DG34: *1,2)*0,3 | DI34: *1,2)*0,3 | DJ34: *1,2)*0,3 | DN34: 0 | DO34: 0 | DP34: 1 | DQ34: 1 | DU34: 1013 | DV34: 1 ШТ. | DW34: 1 ШТ. | DX34: 1 | EE34: 55393700 | EF34: 40 | EG34: Монтаж оборудования | EH34: 0 | EJ34: 2 | EK34: 68 | EL34: ТСН-2001.4-10. Прокладка и монтаж сетей связи | EM34: ТСН-2001.4-10-1 | EO34: Поправка: Гл.12.Прил.8.п.8. 3_12.00.01.11.001 Поправка: Гл.4.Прил.2.2.п.2.2.29_04.00.01.35.003 | EQ34: 0 | ER34: 21.3 | ES34: 2.34 | ET34: 0.02 | EU34: 0 | EV34: 18.94 | EW34: 1.36 | EX34: 0 | EY34: 0 | FQ34: 0 | FR34: 0 | FS34: 0 | FX34: 90 | FY34: 46 | GD34: 1 | GF34: -1291988825 | GG34: 2 | GH34: 1 | GI34: 2 | GJ34: 0 | GK34: 0 | GL34: =ROUND(IF(AND(BH34=3,BI34=3,FS34<>0),P34,0),2) -> 0 | GM34: =ROUND(O34+X34+Y34,2)+GX34 -> 269.68 | GN34: =IF(OR(BI34=0,BI34=1),GM34-GX34,0) -> 0 | GO34: =IF(BI34=2,GM34-GX34,0) -> 269.68 | GP34: =IF(BI34=4,GM34-GX34,0) -> 0 | GR34: 0 | GS34: 3 | GT34: 0 | GV34: =ROUND((GT34),6) -> 0 | GW34: 1 | GX34: =ROUND(HC34*I34,2) -> 0 | HA34: 0 | HB34: 0 | HC34: =GV34*GW34 -> 0 | HS34: 0 | IK34: 0
A35: 17 | B35: 1 | C35: =ROW(SmtRes!A34) -> 34 | D35: =ROW(EtalonRes!A46) -> 46 | E35: 4 | F35: 4.10-167-1 | G35: Монтаж блока питания сети (БПС) в диспетчерской / демонтаж блоков электропитания | H35: 1 ШТ. | I35: =ROUND(4+1+1+8+2,9) -> 16 | J35: 0 | K35: =ROUND(4+1+1+8+2,9) -> 16 | O35: =ROUND(CP35,2) -> 6437.62 | P35: =ROUND((ROUND((AC35*AW35*I35),2)*BC35),2) -> 0 | Q35: =(ROUND((ROUND(((((ET35*1.2)*0.3))*AV35*I35),2)*BB35),2)+ROUND((ROUND(((AE35-(((EU35*1.2)*0.3)))*AV35*I35),2)*BS35),2)) -> 1.32 | R35: =(ROUND((ROUND(((((EU35*1.2)*0.3))*AV35*I35),2)*BS35),2)+ROUND((ROUND(((AE35-(((EU35*1.2)*0.3)))*AV35*I35),2)*BS35),2)) -> 0 | S35: =ROUND((ROUND((AF35*AV35*I35),2)*BA35),2) -> 6436.3 | T35: =ROUND(CU35*I35,2) -> 0 | U35: =CV35*I35 -> 8.2017792 | V35: =CW35*I35 -> 0 | W35: =ROUND(CX35*I35,2) -> 0 | X35: =(ROUND((((S35+ROUND((ROUND(((((EU35*1.2)*0.3))*AV35*I35),2)*BS35),2))*AT35)/100),2)+ROUND(((ROUND((ROUND(((AE35-(((EU35*1.2)*0.3)))*AV35*I35),2)*BS35),2)*AT35)/100),2)) -> 5792.67 | Y35: =(ROUND((((S35+ROUND((ROUND(((((EU35*1.2)*0.3))*AV35*I35),2)*BS35),2))*AU35)/100),2)+ROUND(((ROUND((ROUND(((AE35-(((EU35*1.2)*0.3)))*AV35*I35),2)*BS35),2)*AU35)/100),2)) -> 2960.7 | AA35: 55937298 | AB35: =ROUND((AC35+AD35+AF35),6) -> 6.8256 | AC35: =ROUND((((ES35*1)*0)),6) -> 0 | AD35: =ROUND((((((ET35*1.2)*0.3))-(((EU35*1.2)*0.3)))+AE35),6) -> 0.0072 | AE35: =ROUND((((EU35*1.2)*0.3)),6) -> 0 | AF35: =ROUND((((EV35*1.2)*0.3)),6) -> 6.8184 | AG35: =ROUND((AP35),6) -> 0 | AH35: =(((EW35*1.2)*0.3)) -> 0.4896 | AI35: =(((EX35*1.2)*0.3)) -> 0 | AJ35: =(AS35) -> 0 | AK35: 21.3 | AL35: 2.34 | AM35: 0.02 | AN35: 0 | AO35: 18.94 | AP35: 0 | AQ35: 1.36 | AR35: 0 | AS35: 0 | AT35: 90 | AU35: 46 | AV35: 1.047 | AW35: 1 | AZ35: 1 | BA35: 56.35 | BB35: 11 | BC35: 10.24 | BH35: 0 | BI35: 2 | BJ35: ТСН-2001.4 Доп. 69, Сб. 10, т. 167, поз. 1 | BM35: 68 | BN35: 0 | BO35: 4.10-167-1 | BP35: 1 | BQ35: 40 | BR35: 0 | BS35: 56.35 | BT35: 1 | BU35: 1 | BV35: 1 | BW35: 1 | BX35: 1 | BZ35: 90 | CA35: 46 | CE35: 1566 | CF35: 0 | CG35: 0 | CM35: 0 | CN35: Поправка: Гл.12.Прил.8.п.8. 3_12.00.01.11.001 Наименование: При наличии напряженных и стесненных условий производства работ (стесненность, сложность складирования и транспортной логистики и т.п.) для объектов, расположенных в пределах круговой магистральной системы улиц "Садовое кольцо" города Москвы Поправка: Гл.4.Прил.2.2.п.2.2.29_04.00.01.35.003 Наименование: При демонтаже оборудования, предназначенного в лом | CO35: 0 | CP35: =(P35+Q35+S35) -> 6437.62 | CQ35: =ROUND((ROUND((AC35*AW35*1),2)*BC35),2) -> 0 | CR35: =(ROUND((ROUND(((((ET35*1.2)*0.3))*AV35*1),2)*BB35),2)+ROUND((ROUND(((AE35-(((EU35*1.2)*0.3)))*AV35*1),2)*BS35),2)) -> 0.11 | CS35: =(ROUND((ROUND(((((EU35*1.2)*0.3))*AV35*1),2)*BS35),2)+ROUND((ROUND(((AE35-(((EU35*1.2)*0.3)))*AV35*1),2)*BS35),2)) -> 0 | CT35: =ROUND((ROUND((AF35*AV35*1),2)*BA35),2) -> 402.34 | CU35: =AG35 -> 0 | CV35: =(AH35*AV35) -> 0.5126112 | CW35: =AI35 -> 0 | CX35: =AJ35 -> 0 | CY35: =(ROUND((((S35+ROUND((ROUND(((((EU35*1.2)*0.3))*AV35*1),2)*BS35),2))*AT35)/100),2)+ROUND(((ROUND((ROUND(((AE35-(((EU35*1.2)*0.3)))*AV35*1),2)*BS35),2)*AT35)/100),2)) -> 5792.67 | CZ35: =(ROUND((((S35+ROUND((ROUND(((((EU35*1.2)*0.3))*AV35*1),2)*BS35),2))*AU35)/100),2)+ROUND(((ROUND((ROUND(((AE35-(((EU35*1.2)*0.3)))*AV35*1),2)*BS35),2)*AU35)/100),2)) -> 2960.7 | DB35: 15 | DD35: *1)*0 | DE35: *1,2)*0,3 | DF35: *1,2)*0,3 | DG35: *1,2)*0,3 | DI35: *1,2)*0,3 | DJ35: *1,2)*0,3 | DN35: 0 | DO35: 0 | DP35: 1 | DQ35: 1 | DU35: 1013 | DV35: 1 ШТ. | DW35: 1 ШТ. | DX35: 1 | EE35: 55393700 | EF35: 40 | EG35: Монтаж оборудования | EH35: 0 | EJ35: 2 | EK35: 68 | EL35: ТСН-2001.4-10. Прокладка и монтаж сетей связи | EM35: ТСН-2001.4-10-1 | EO35: Поправка: Гл.12.Прил.8.п.8. 3_12.00.01.11.001 Поправка: Гл.4.Прил.2.2.п.2.2.29_04.00.01.35.003 | EQ35: 0 | ER35: 21.3 | ES35: 2.34 | ET35: 0.02 | EU35: 0 | EV35: 18.94 | EW35: 1.36 | EX35: 0 | EY35: 0 | FQ35: 0 | FR35: 0 | FS35: 0 | FX35: 90 | FY35: 46 | GD35: 1 | GF35: -1291988825 | GG35: 2 | GH35: 1 | GI35: 2 | GJ35: 0 | GK35: 0 | GL35: =ROUND(IF(AND(BH35=3,BI35=3,FS35<>0),P35,0),2) -> 0 | GM35: =ROUND(O35+X35+Y35,2)+GX35 -> 15190.99 | GN35: =IF(OR(BI35=0,BI35=1),GM35-GX35,0) -> 0 | GO35: =IF(BI35=2,GM35-GX35,0) -> 15190.99 | GP35: =IF(BI35=4,GM35-GX35,0) -> 0 | GR35: 0 | GS35: 3 | GT35: 0 | GV35: =ROUND((GT35),6) -> 0 | GW35: 1 | GX35: =ROUND(HC35*I35,2) -> 0 | HA35: 0 | HB35: 0 | HC35: =GV35*GW35 -> 0 | HS35: 0 | IK35: 0
A36: 17 | B36: 1 | C36: =ROW(SmtRes!A35) -> 35 | D36: =ROW(EtalonRes!A47) -> 47 | E36: 5 | F36: 4.10-81-2 | G36: Извещатели ПС автоматические, дымовой, фотоэлектрический, радиоизотопный, световой в нормальном исполнении / демонтаж извещателей | H36: 1 ШТ. | I36: 8 | J36: 0 | K36: 8 | O36: =ROUND(CP36,2) -> 64.11 | P36: =ROUND((ROUND((AC36*AW36*I36),2)*BC36),2) -> 0 | Q36: =(ROUND((ROUND(((((ET36*1.2)*0.3))*AV36*I36),2)*BB36),2)+ROUND((ROUND(((AE36-(((EU36*1.2)*0.3)))*AV36*I36),2)*BS36),2)) -> 0.18 | R36: =(ROUND((ROUND(((((EU36*1.2)*0.3))*AV36*I36),2)*BS36),2)+ROUND((ROUND(((AE36-(((EU36*1.2)*0.3)))*AV36*I36),2)*BS36),2)) -> 0.03 | S36: =ROUND((ROUND((AF36*AV36*I36),2)*BA36),2) -> 63.93 | T36: =ROUND(CU36*I36,2) -> 0 | U36: =CV36*I36 -> 5.0658048 | V36: =CW36*I36 -> 0 | W36: =ROUND(CX36*I36,2) -> 0 | X36: =(ROUND((((S36+ROUND((ROUND(((((EU36*1.2)*0.3))*AV36*I36),2)*BS36),2))*AT36)/100),2)+ROUND(((ROUND((ROUND(((AE36-(((EU36*1.2)*0.3)))*AV36*I36),2)*BS36),2)*AT36)/100),2)) -> 57.56 | Y36: =(ROUND((((S36+ROUND((ROUND(((((EU36*1.2)*0.3))*AV36*I36),2)*BS36),2))*AU36)/100),2)+ROUND(((ROUND((ROUND(((AE36-(((EU36*1.2)*0.3)))*AV36*I36),2)*BS36),2)*AU36)/100),2)) -> 29.42 | AA36: 55937296 | AB36: =ROUND((AC36+AD36+AF36),6) -> 7.6536 | AC36: =ROUND((((ES36*1)*0)),6) -> 0 | AD36: =ROUND((((((ET36*1.2)*0.3))-(((EU36*1.2)*0.3)))+AE36),6) -> 0.0216 | AE36: =ROUND((((EU36*1.2)*0.3)),6) -> 0.0036 | AF36: =ROUND((((EV36*1.2)*0.3)),6) -> 7.632 | AG36: =ROUND((AP36),6) -> 0 | AH36: =(((EW36*1.2)*0.3)) -> 0.6048 | AI36: =(((EX36*1.2)*0.3)) -> 0 | AJ36: =(AS36) -> 0 | AK36: 22.52 | AL36: 1.26 | AM36: 0.06 | AN36: 0.01 | AO36: 21.2 | AP36: 0 | AQ36: 1.68 | AR36: 0 | AS36: 0 | AT36: 90 | AU36: 46 | AV36: 1.047 | AW36: 1 | AZ36: 1 | BA36: 1 | BB36: 1 | BC36: 1 | BH36: 0 | BI36: 2 | BJ36: ТСН-2001.4. Доп. 1-42. Сб. 10, т. 81, поз. 2 | BM36: 68 | BN36: 0 | BO36: 4.10-81-2 | BP36: 1 | BQ36: 40 | BR36: 0 | BS36: 1 | BT36: 1 | BU36: 1 | BV36: 1 | BW36: 1 | BX36: 1 | BZ36: 90 | CA36: 46 | CE36: 1566 | CF36: 0 | CG36: 0 | CM36: 0 | CN36: Поправка: Гл.12.Прил.8.п.8. 3_12.00.01.11.001 Наименование: При наличии напряженных и стесненных условий производства работ (стесненность, сложность складирования и транспортной логистики и т.п.) для объектов, расположенных в пределах круговой магистральной системы улиц "Садовое кольцо" города Москвы Поправка: Гл.4.Прил.2.2.п.2.2.29_04.00.01.35.003 Наименование: При демонтаже оборудования, предназначенного в лом | CO36: 0 | CP36: =(P36+Q36+S36) -> 64.11 | CQ36: =ROUND((ROUND((AC36*AW36*1),2)*BC36),2) -> 0 | CR36: =(ROUND((ROUND(((((ET36*1.2)*0.3))*AV36*1),2)*BB36),2)+ROUND((ROUND(((AE36-(((EU36*1.2)*0.3)))*AV36*1),2)*BS36),2)) -> 0.02 | CS36: =(ROUND((ROUND(((((EU36*1.2)*0.3))*AV36*1),2)*BS36),2)+ROUND((ROUND(((AE36-(((EU36*1.2)*0.3)))*AV36*1),2)*BS36),2)) -> 0 | CT36: =ROUND((ROUND((AF36*AV36*1),2)*BA36),2) -> 7.99 | CU36: =AG36 -> 0 | CV36: =(AH36*AV36) -> 0.6332256 | CW36: =AI36 -> 0 | CX36: =AJ36 -> 0 | CY36: =(ROUND((((S36+ROUND((ROUND(((((EU36*1.2)*0.3))*AV36*1),2)*BS36),2))*AT36)/100),2)+ROUND(((ROUND((ROUND(((AE36-(((EU36*1.2)*0.3)))*AV36*1),2)*BS36),2)*AT36)/100),2)) -> 57.54 | CZ36: =(ROUND((((S36+ROUND((ROUND(((((EU36*1.2)*0.3))*AV36*1),2)*BS36),2))*AU36)/100),2)+ROUND(((ROUND((ROUND(((AE36-(((EU36*1.2)*0.3)))*AV36*1),2)*BS36),2)*AU36)/100),2)) -> 29.41 | DB36: 17 | DD36: *1)*0 | DE36: *1,2)*0,3 | DF36: *1,2)*0,3 | DG36: *1,2)*0,3 | DI36: *1,2)*0,3 | DJ36: *1,2)*0,3 | DN36: 0 | DO36: 0 | DP36: 1 | DQ36: 1 | DU36: 1013 | DV36: 1 ШТ. | DW36: 1 ШТ. | DX36: 1 | EE36: 55393700 | EF36: 40 | EG36: Монтаж оборудования | EH36: 0 | EJ36: 2 | EK36: 68 | EL36: ТСН-2001.4-10. Прокладка и монтаж сетей связи | EM36: ТСН-2001.4-10-1 | EO36: Поправка: Гл.12.Прил.8.п.8. 3_12.00.01.11.001 Поправка: Гл.4.Прил.2.2.п.2.2.29_04.00.01.35.003 | EQ36: 0 | ER36: 22.52 | ES36: 1.26 | ET36: 0.06 | EU36: 0.01 | EV36: 21.2 | EW36: 1.68 | EX36: 0 | EY36: 0 | FQ36: 0 | FR36: 0 | FS36: 0 | FX36: 90 | FY36: 46 | GD36: 1 | GF36: -1660079002 | GG36: 2 | GH36: 1 | GI36: 2 | GJ36: 0 | GK36: 0 | GL36: =ROUND(IF(AND(BH36=3,BI36=3,FS36<>0),P36,0),2) -> 0 | GM36: =ROUND(O36+X36+Y36,2)+GX36 -> 151.09 | GN36: =IF(OR(BI36=0,BI36=1),GM36-GX36,0) -> 0 | GO36: =IF(BI36=2,GM36-GX36,0) -> 151.09 | GP36: =IF(BI36=4,GM36-GX36,0) -> 0 | GR36: 0 | GS36: 3 | GT36: 0 | GV36: =ROUND((GT36),6) -> 0 | GW36: 1 | GX36: =ROUND(HC36*I36,2) -> 0 | HA36: 0 | HB36: 0 | HC36: =GV36*GW36 -> 0 | HS36: 0 | IK36: 0
A37: 17 | B37: 1 | C37: =ROW(SmtRes!A36) -> 36 | D37: =ROW(EtalonRes!A48) -> 48 | E37: 5 | F37: 4.10-81-2 | G37: Извещатели ПС автоматические, дымовой, фотоэлектрический, радиоизотопный, световой в нормальном исполнении / демонтаж извещателей | H37: 1 ШТ. | I37: 8 | J37: 0 | K37: 8 | O37: =ROUND(CP37,2) -> 3605.79 | P37: =ROUND((ROUND((AC37*AW37*I37),2)*BC37),2) -> 0 | Q37: =(ROUND((ROUND(((((ET37*1.2)*0.3))*AV37*I37),2)*BB37),2)+ROUND((ROUND(((AE37-(((EU37*1.2)*0.3)))*AV37*I37),2)*BS37),2)) -> 3.33 | R37: =(ROUND((ROUND(((((EU37*1.2)*0.3))*AV37*I37),2)*BS37),2)+ROUND((ROUND(((AE37-(((EU37*1.2)*0.3)))*AV37*I37),2)*BS37),2)) -> 1.69 | S37: =ROUND((ROUND((AF37*AV37*I37),2)*BA37),2) -> 3602.46 | T37: =ROUND(CU37*I37,2) -> 0 | U37: =CV37*I37 -> 5.0658048 | V37: =CW37*I37 -> 0 | W37: =ROUND(CX37*I37,2) -> 0 | X37: =(ROUND((((S37+ROUND((ROUND(((((EU37*1.2)*0.3))*AV37*I37),2)*BS37),2))*AT37)/100),2)+ROUND(((ROUND((ROUND(((AE37-(((EU37*1.2)*0.3)))*AV37*I37),2)*BS37),2)*AT37)/100),2)) -> 3243.74 | Y37: =(ROUND((((S37+ROUND((ROUND(((((EU37*1.2)*0.3))*AV37*I37),2)*BS37),2))*AU37)/100),2)+ROUND(((ROUND((ROUND(((AE37-(((EU37*1.2)*0.3)))*AV37*I37),2)*BS37),2)*AU37)/100),2)) -> 1657.91 | AA37: 55937298 | AB37: =ROUND((AC37+AD37+AF37),6) -> 7.6536 | AC37: =ROUND((((ES37*1)*0)),6) -> 0 | AD37: =ROUND((((((ET37*1.2)*0.3))-(((EU37*1.2)*0.3)))+AE37),6) -> 0.0216 | AE37: =ROUND((((EU37*1.2)*0.3)),6) -> 0.0036 | AF37: =ROUND((((EV37*1.2)*0.3)),6) -> 7.632 | AG37: =ROUND((AP37),6) -> 0 | AH37: =(((EW37*1.2)*0.3)) -> 0.6048 | AI37: =(((EX37*1.2)*0.3)) -> 0 | AJ37: =(AS37) -> 0 | AK37: 22.52 | AL37: 1.26 | AM37: 0.06 | AN37: 0.01 | AO37: 21.2 | AP37: 0 | AQ37: 1.68 | AR37: 0 | AS37: 0 | AT37: 90 | AU37: 46 | AV37: 1.047 | AW37: 1 | AZ37: 1 | BA37: 56.35 | BB37: 18.5 | BC37: 9.84 | BH37: 0 | BI37: 2 | BJ37: ТСН-2001.4. Доп. 1-42. Сб. 10, т. 81, поз. 2 | BM37: 68 | BN37: 0 | BO37: 4.10-81-2 | BP37: 1 | BQ37: 40 | BR37: 0 | BS37: 56.35 | BT37: 1 | BU37: 1 | BV37: 1 | BW37: 1 | BX37: 1 | BZ37: 90 | CA37: 46 | CE37: 1566 | CF37: 0 | CG37: 0 | CM37: 0 | CN37: Поправка: Гл.12.Прил.8.п.8. 3_12.00.01.11.001 Наименование: При наличии напряженных и стесненных условий производства работ (стесненность, сложность складирования и транспортной логистики и т.п.) для объектов, расположенных в пределах круговой магистральной системы улиц "Садовое кольцо" города Москвы Поправка: Гл.4.Прил.2.2.п.2.2.29_04.00.01.35.003 Наименование: При демонтаже оборудования, предназначенного в лом | CO37: 0 | CP37: =(P37+Q37+S37) -> 3605.79 | CQ37: =ROUND((ROUND((AC37*AW37*1),2)*BC37),2) -> 0 | CR37: =(ROUND((ROUND(((((ET37*1.2)*0.3))*AV37*1),2)*BB37),2)+ROUND((ROUND(((AE37-(((EU37*1.2)*0.3)))*AV37*1),2)*BS37),2)) -> 0.37 | CS37: =(ROUND((ROUND(((((EU37*1.2)*0.3))*AV37*1),2)*BS37),2)+ROUND((ROUND(((AE37-(((EU37*1.2)*0.3)))*AV37*1),2)*BS37),2)) -> 0 | CT37: =ROUND((ROUND((AF37*AV37*1),2)*BA37),2) -> 450.24 | CU37: =AG37 -> 0 | CV37: =(AH37*AV37) -> 0.6332256 | CW37: =AI37 -> 0 | CX37: =AJ37 -> 0 | CY37: =(ROUND((((S37+ROUND((ROUND(((((EU37*1.2)*0.3))*AV37*1),2)*BS37),2))*AT37)/100),2)+ROUND(((ROUND((ROUND(((AE37-(((EU37*1.2)*0.3)))*AV37*1),2)*BS37),2)*AT37)/100),2)) -> 3242.21 | CZ37: =(ROUND((((S37+ROUND((ROUND(((((EU37*1.2)*0.3))*AV37*1),2)*BS37),2))*AU37)/100),2)+ROUND(((ROUND((ROUND(((AE37-(((EU37*1.2)*0.3)))*AV37*1),2)*BS37),2)*AU37)/100),2)) -> 1657.13 | DB37: 19 | DD37: *1)*0 | DE37: *1,2)*0,3 | DF37: *1,2)*0,3 | DG37: *1,2)*0,3 | DI37: *1,2)*0,3 | DJ37: *1,2)*0,3 | DN37: 0 | DO37: 0 | DP37: 1 | DQ37: 1 | DU37: 1013 | DV37: 1 ШТ. | DW37: 1 ШТ. | DX37: 1 | EE37: 55393700 | EF37: 40 | EG37: Монтаж оборудования | EH37: 0 | EJ37: 2 | EK37: 68 | EL37: ТСН-2001.4-10. Прокладка и монтаж сетей связи | EM37: ТСН-2001.4-10-1 | EO37: Поправка: Гл.12.Прил.8.п.8. 3_12.00.01.11.001 Поправка: Гл.4.Прил.2.2.п.2.2.29_04.00.01.35.003 | EQ37: 0 | ER37: 22.52 | ES37: 1.26 | ET37: 0.06 | EU37: 0.01 | EV37: 21.2 | EW37: 1.68 | EX37: 0 | EY37: 0 | FQ37: 0 | FR37: 0 | FS37: 0 | FX37: 90 | FY37: 46 | GD37: 1 | GF37: -1660079002 | GG37: 2 | GH37: 1 | GI37: 2 | GJ37: 0 | GK37: 0 | GL37: =ROUND(IF(AND(BH37=3,BI37=3,FS37<>0),P37,0),2) -> 0 | GM37: =ROUND(O37+X37+Y37,2)+GX37 -> 8507.44 | GN37: =IF(OR(BI37=0,BI37=1),GM37-GX37,0) -> 0 | GO37: =IF(BI37=2,GM37-GX37,0) -> 8507.44 | GP37: =IF(BI37=4,GM37-GX37,0) -> 0 | GR37: 0 | GS37: 3 | GT37: 0 | GV37: =ROUND((GT37),6) -> 0 | GW37: 1 | GX37: =ROUND(HC37*I37,2) -> 0 | HA37: 0 | HB37: 0 | HC37: =GV37*GW37 -> 0 | HS37: 0 | IK37: 0
A38: 17 | B38: 1 | C38: =ROW(SmtRes!A39) -> 39 | D38: =ROW(EtalonRes!A52) -> 52 | E38: 6 | F38: 4.10-76-10 | G38: Монтаж ключа или кнопки на панели | H38: 1 ШТ. | I38: 4 | J38: 0 | K38: 4 | O38: =ROUND(CP38,2) -> 17.93 | P38: =ROUND((ROUND((AC38*AW38*I38),2)*BC38),2) -> 0 | Q38: =(ROUND((ROUND(((((ET38*1.2)*0.3))*AV38*I38),2)*BB38),2)+ROUND((ROUND(((AE38-(((EU38*1.2)*0.3)))*AV38*I38),2)*BS38),2)) -> 0 | R38: =(ROUND((ROUND(((((EU38*1.2)*0.3))*AV38*I38),2)*BS38),2)+ROUND((ROUND(((AE38-(((EU38*1.2)*0.3)))*AV38*I38),2)*BS38),2)) -> 0 | S38: =ROUND((ROUND((AF38*AV38*I38),2)*BA38),2) -> 17.93 | T38: =ROUND(CU38*I38,2) -> 0 | U38: =CV38*I38 -> 1.50768 | V38: =CW38*I38 -> 0 | W38: =ROUND(CX38*I38,2) -> 0 | X38: =(ROUND((((S38+ROUND((ROUND(((((EU38*1.2)*0.3))*AV38*I38),2)*BS38),2))*AT38)/100),2)+ROUND(((ROUND((ROUND(((AE38-(((EU38*1.2)*0.3)))*AV38*I38),2)*BS38),2)*AT38)/100),2)) -> 17.03 | Y38: =(ROUND((((S38+ROUND((ROUND(((((EU38*1.2)*0.3))*AV38*I38),2)*BS38),2))*AU38)/100),2)+ROUND(((ROUND((ROUND(((AE38-(((EU38*1.2)*0.3)))*AV38*I38),2)*BS38),2)*AU38)/100),2)) -> 9.5 | AA38: 55937296 | AB38: =ROUND((AC38+AD38+AF38),6) -> 4.2804 | AC38: =ROUND((((ES38*1)*0)),6) -> 0 | AD38: =ROUND((((((ET38*1.2)*0.3))-(((EU38*1.2)*0.3)))+AE38),6) -> 0 | AE38: =ROUND((((EU38*1.2)*0.3)),6) -> 0 | AF38: =ROUND((((EV38*1.2)*0.3)),6) -> 4.2804 | AG38: =ROUND((AP38),6) -> 0 | AH38: =(((EW38*1.2)*0.3)) -> 0.36 | AI38: =(((EX38*1.2)*0.3)) -> 0 | AJ38: =(AS38) -> 0 | AK38: 13.56 | AL38: 1.67 | AM38: 0 | AN38: 0 | AO38: 11.89 | AP38: 0 | AQ38: 1 | AR38: 0 | AS38: 0 | AT38: 95 | AU38: 53 | AV38: 1.047 | AW38: 1 | AZ38: 1 | BA38: 1 | BB38: 1 | BC38: 1 | BH38: 0 | BI38: 2 | BJ38: ТСН-2001.4 Доп. 79, Сб. 10, т. 76, поз. 10 | BM38: 69 | BN38: 0 | BO38: 4.10-76-10 | BP38: 1 | BQ38: 40 | BR38: 0 | BS38: 1 | BT38: 1 | BU38: 1 | BV38: 1 | BW38: 1 | BX38: 1 | BZ38: 95 | CA38: 53 | CE38: 1566 | CF38: 0 | CG38: 0 | CM38: 0 | CN38: Поправка: Гл.12.Прил.8.п.8. 3_12.00.01.11.001 Наименование: При наличии напряженных и стесненных условий производства работ (стесненность, сложность складирования и транспортной логистики и т.п.) для объектов, расположенных в пределах круговой магистральной системы улиц "Садовое кольцо" города Москвы Поправка: Гл.4.Прил.2.2.п.2.2.29_04.00.01.35.003 Наименование: При демонтаже оборудования, предназначенного в лом | CO38: 0 | CP38: =(P38+Q38+S38) -> 17.93 | CQ38: =ROUND((ROUND((AC38*AW38*1),2)*BC38),2) -> 0 | CR38: =(ROUND((ROUND(((((ET38*1.2)*0.3))*AV38*1),2)*BB38),2)+ROUND((ROUND(((AE38-(((EU38*1.2)*0.3)))*AV38*1),2)*BS38),2)) -> 0 | CS38: =(ROUND((ROUND(((((EU38*1.2)*0.3))*AV38*1),2)*BS38),2)+ROUND((ROUND(((AE38-(((EU38*1.2)*0.3)))*AV38*1),2)*BS38),2)) -> 0 | CT38: =ROUND((ROUND((AF38*AV38*1),2)*BA38),2) -> 4.48 | CU38: =AG38 -> 0 | CV38: =(AH38*AV38) -> 0.37692 | CW38: =AI38 -> 0 | CX38: =AJ38 -> 0 | CY38: =(ROUND((((S38+ROUND((ROUND(((((EU38*1.2)*0.3))*AV38*1),2)*BS38),2))*AT38)/100),2)+ROUND(((ROUND((ROUND(((AE38-(((EU38*1.2)*0.3)))*AV38*1),2)*BS38),2)*AT38)/100),2)) -> 17.03 | CZ38: =(ROUND((((S38+ROUND((ROUND(((((EU38*1.2)*0.3))*AV38*1),2)*BS38),2))*AU38)/100),2)+ROUND(((ROUND((ROUND(((AE38-(((EU38*1.2)*0.3)))*AV38*1),2)*BS38),2)*AU38)/100),2)) -> 9.5 | DB38: 21 | DD38: *1)*0 | DE38: *1,2)*0,3 | DF38: *1,2)*0,3 | DG38: *1,2)*0,3 | DI38: *1,2)*0,3 | DJ38: *1,2)*0,3 | DN38: 0 | DO38: 0 | DP38: 1 | DQ38: 1 | DU38: 1013 | DV38: 1 ШТ. | DW38: 1 ШТ. | DX38: 1 | EE38: 55393701 | EF38: 40 | EG38: Монтаж оборудования | EH38: 0 | EJ38: 2 | EK38: 69 | EL38: ТСН-2001.4-10. Монтаж радиотелевизионного и электронного оборудования | EM38: ТСН-2001.4-10-2 | EO38: Поправка: Гл.12.Прил.8.п.8. 3_12.00.01.11.001 Поправка: Гл.4.Прил.2.2.п.2.2.29_04.00.01.35.003 | EQ38: 0 | ER38: 13.56 | ES38: 1.67 | ET38: 0 | EU38: 0 | EV38: 11.89 | EW38: 1 | EX38: 0 | EY38: 0 | FQ38: 0 | FR38: 0 | FS38: 0 | FX38: 95 | FY38: 53 | GD38: 1 | GF38: 205901832 | GG38: 2 | GH38: 1 | GI38: 2 | GJ38: 0 | GK38: 0 | GL38: =ROUND(IF(AND(BH38=3,BI38=3,FS38<>0),P38,0),2) -> 0 | GM38: =ROUND(O38+X38+Y38,2)+GX38 -> 44.46 | GN38: =IF(OR(BI38=0,BI38=1),GM38-GX38,0) -> 0 | GO38: =IF(BI38=2,GM38-GX38,0) -> 44.46 | GP38: =IF(BI38=4,GM38-GX38,0) -> 0 | GR38: 0 | GS38: 3 | GT38: 0 | GV38: =ROUND((GT38),6) -> 0 | GW38: 1 | GX38: =ROUND(HC38*I38,2) -> 0 | HA38: 0 | HB38: 0 | HC38: =GV38*GW38 -> 0 | HS38: 0 | IK38: 0
A39: 17 | B39: 1 | C39: =ROW(SmtRes!A42) -> 42 | D39: =ROW(EtalonRes!A56) -> 56 | E39: 6 | F39: 4.10-76-10 | G39: Монтаж ключа или кнопки на панели | H39: 1 ШТ. | I39: 4 | J39: 0 | K39: 4 | O39: =ROUND(CP39,2) -> 1010.36 | P39: =ROUND((ROUND((AC39*AW39*I39),2)*BC39),2) -> 0 | Q39: =(ROUND((ROUND(((((ET39*1.2)*0.3))*AV39*I39),2)*BB39),2)+ROUND((ROUND(((AE39-(((EU39*1.2)*0.3)))*AV39*I39),2)*BS39),2)) -> 0 | R39: =(ROUND((ROUND(((((EU39*1.2)*0.3))*AV39*I39),2)*BS39),2)+ROUND((ROUND(((AE39-(((EU39*1.2)*0.3)))*AV39*I39),2)*BS39),2)) -> 0 | S39: =ROUND((ROUND((AF39*AV39*I39),2)*BA39),2) -> 1010.36 | T39: =ROUND(CU39*I39,2) -> 0 | U39: =CV39*I39 -> 1.50768 | V39: =CW39*I39 -> 0 | W39: =ROUND(CX39*I39,2) -> 0 | X39: =(ROUND((((S39+ROUND((ROUND(((((EU39*1.2)*0.3))*AV39*I39),2)*BS39),2))*AT39)/100),2)+ROUND(((ROUND((ROUND(((AE39-(((EU39*1.2)*0.3)))*AV39*I39),2)*BS39),2)*AT39)/100),2)) -> 959.84 | Y39: =(ROUND((((S39+ROUND((ROUND(((((EU39*1.2)*0.3))*AV39*I39),2)*BS39),2))*AU39)/100),2)+ROUND(((ROUND((ROUND(((AE39-(((EU39*1.2)*0.3)))*AV39*I39),2)*BS39),2)*AU39)/100),2)) -> 535.49 | AA39: 55937298 | AB39: =ROUND((AC39+AD39+AF39),6) -> 4.2804 | AC39: =ROUND((((ES39*1)*0)),6) -> 0 | AD39: =ROUND((((((ET39*1.2)*0.3))-(((EU39*1.2)*0.3)))+AE39),6) -> 0 | AE39: =ROUND((((EU39*1.2)*0.3)),6) -> 0 | AF39: =ROUND((((EV39*1.2)*0.3)),6) -> 4.2804 | AG39: =ROUND((AP39),6) -> 0 | AH39: =(((EW39*1.2)*0.3)) -> 0.36 | AI39: =(((EX39*1.2)*0.3)) -> 0 | AJ39: =(AS39) -> 0 | AK39: 13.56 | AL39: 1.67 | AM39: 0 | AN39: 0 | AO39: 11.89 | AP39: 0 | AQ39: 1 | AR39: 0 | AS39: 0 | AT39: 95 | AU39: 53 | AV39: 1.047 | AW39: 1 | AZ39: 1 | BA39: 56.35 | BB39: 1 | BC39: 17.87 | BH39: 0 | BI39: 2 | BJ39: ТСН-2001.4 Доп. 79, Сб. 10, т. 76, поз. 10 | BM39: 69 | BN39: 0 | BO39: 4.10-76-10 | BP39: 1 | BQ39: 40 | BR39: 0 | BS39: 56.35 | BT39: 1 | BU39: 1 | BV39: 1 | BW39: 1 | BX39: 1 | BZ39: 95 | CA39: 53 | CE39: 1566 | CF39: 0 | CG39: 0 | CM39: 0 | CN39: Поправка: Гл.12.Прил.8.п.8. 3_12.00.01.11.001 Наименование: При наличии напряженных и стесненных условий производства работ (стесненность, сложность складирования и транспортной логистики и т.п.) для объектов, расположенных в пределах круговой магистральной системы улиц "Садовое кольцо" города Москвы Поправка: Гл.4.Прил.2.2.п.2.2.29_04.00.01.35.003 Наименование: При демонтаже оборудования, предназначенного в лом | CO39: 0 | CP39: =(P39+Q39+S39) -> 1010.36 | CQ39: =ROUND((ROUND((AC39*AW39*1),2)*BC39),2) -> 0 | CR39: =(ROUND((ROUND(((((ET39*1.2)*0.3))*AV39*1),2)*BB39),2)+ROUND((ROUND(((AE39-(((EU39*1.2)*0.3)))*AV39*1),2)*BS39),2)) -> 0 | CS39: =(ROUND((ROUND(((((EU39*1.2)*0.3))*AV39*1),2)*BS39),2)+ROUND((ROUND(((AE39-(((EU39*1.2)*0.3)))*AV39*1),2)*BS39),2)) -> 0 | CT39: =ROUND((ROUND((AF39*AV39*1),2)*BA39),2) -> 252.45 | CU39: =AG39 -> 0 | CV39: =(AH39*AV39) -> 0.37692 | CW39: =AI39 -> 0 | CX39: =AJ39 -> 0 | CY39: =(ROUND((((S39+ROUND((ROUND(((((EU39*1.2)*0.3))*AV39*1),2)*BS39),2))*AT39)/100),2)+ROUND(((ROUND((ROUND(((AE39-(((EU39*1.2)*0.3)))*AV39*1),2)*BS39),2)*AT39)/100),2)) -> 959.84 | CZ39: =(ROUND((((S39+ROUND((ROUND(((((EU39*1.2)*0.3))*AV39*1),2)*BS39),2))*AU39)/100),2)+ROUND(((ROUND((ROUND(((AE39-(((EU39*1.2)*0.3)))*AV39*1),2)*BS39),2)*AU39)/100),2)) -> 535.49 | DB39: 23 | DD39: *1)*0 | DE39: *1,2)*0,3 | DF39: *1,2)*0,3 | DG39: *1,2)*0,3 | DI39: *1,2)*0,3 | DJ39: *1,2)*0,3 | DN39: 0 | DO39: 0 | DP39: 1 | DQ39: 1 | DU39: 1013 | DV39: 1 ШТ. | DW39: 1 ШТ. | DX39: 1 | EE39: 55393701 | EF39: 40 | EG39: Монтаж оборудования | EH39: 0 | EJ39: 2 | EK39: 69 | EL39: ТСН-2001.4-10. Монтаж радиотелевизионного и электронного оборудования | EM39: ТСН-2001.4-10-2 | EO39: Поправка: Гл.12.Прил.8.п.8. 3_12.00.01.11.001 Поправка: Гл.4.Прил.2.2.п.2.2.29_04.00.01.35.003 | EQ39: 0 | ER39: 13.56 | ES39: 1.67 | ET39: 0 | EU39: 0 | EV39: 11.89 | EW39: 1 | EX39: 0 | EY39: 0 | FQ39: 0 | FR39: 0 | FS39: 0 | FX39: 95 | FY39: 53 | GD39: 1 | GF39: 205901832 | GG39: 2 | GH39: 1 | GI39: 2 | GJ39: 0 | GK39: 0 | GL39: =ROUND(IF(AND(BH39=3,BI39=3,FS39<>0),P39,0),2) -> 0 | GM39: =ROUND(O39+X39+Y39,2)+GX39 -> 2505.69 | GN39: =IF(OR(BI39=0,BI39=1),GM39-GX39,0) -> 0 | GO39: =IF(BI39=2,GM39-GX39,0) -> 2505.69 | GP39: =IF(BI39=4,GM39-GX39,0) -> 0 | GR39: 0 | GS39: 3 | GT39: 0 | GV39: =ROUND((GT39),6) -> 0 | GW39: 1 | GX39: =ROUND(HC39*I39,2) -> 0 | HA39: 0 | HB39: 0 | HC39: =GV39*GW39 -> 0 | HS39: 0 | IK39: 0
A40: 17 | B40: 1 | C40: =ROW(SmtRes!A43) -> 43 | D40: =ROW(EtalonRes!A57) -> 57 | E40: 7 | F40: 4.10-81-4 | G40: Извещатели ОС автоматические, контактный, магнито-контактный на открывание окон, дверей / демонтаж извещателей | H40: 1 ШТ. | I40: 4 | J40: 0 | K40: 4 | O40: =ROUND(CP40,2) -> 15.98 | P40: =ROUND((ROUND((AC40*AW40*I40),2)*BC40),2) -> 0 | Q40: =(ROUND((ROUND(((((ET40*1.2)*0.3))*AV40*I40),2)*BB40),2)+ROUND((ROUND(((AE40-(((EU40*1.2)*0.3)))*AV40*I40),2)*BS40),2)) -> 0 | R40: =(ROUND((ROUND(((((EU40*1.2)*0.3))*AV40*I40),2)*BS40),2)+ROUND((ROUND(((AE40-(((EU40*1.2)*0.3)))*AV40*I40),2)*BS40),2)) -> 0 | S40: =ROUND((ROUND((AF40*AV40*I40),2)*BA40),2) -> 15.98 | T40: =ROUND(CU40*I40,2) -> 0 | U40: =CV40*I40 -> 1.2664512 | V40: =CW40*I40 -> 0 | W40: =ROUND(CX40*I40,2) -> 0 | X40: =(ROUND((((S40+ROUND((ROUND(((((EU40*1.2)*0.3))*AV40*I40),2)*BS40),2))*AT40)/100),2)+ROUND(((ROUND((ROUND(((AE40-(((EU40*1.2)*0.3)))*AV40*I40),2)*BS40),2)*AT40)/100),2)) -> 14.38 | Y40: =(ROUND((((S40+ROUND((ROUND(((((EU40*1.2)*0.3))*AV40*I40),2)*BS40),2))*AU40)/100),2)+ROUND(((ROUND((ROUND(((AE40-(((EU40*1.2)*0.3)))*AV40*I40),2)*BS40),2)*AU40)/100),2)) -> 7.35 | AA40: 55937296 | AB40: =ROUND((AC40+AD40+AF40),6) -> 3.816 | AC40: =ROUND((((ES40*1)*0)),6) -> 0 | AD40: =ROUND((((((ET40*1.2)*0.3))-(((EU40*1.2)*0.3)))+AE40),6) -> 0 | AE40: =ROUND((((EU40*1.2)*0.3)),6) -> 0 | AF40: =ROUND((((EV40*1.2)*0.3)),6) -> 3.816 | AG40: =ROUND((AP40),6) -> 0 | AH40: =(((EW40*1.2)*0.3)) -> 0.3024 | AI40: =(((EX40*1.2)*0.3)) -> 0 | AJ40: =(AS40) -> 0 | AK40: 11.65 | AL40: 1.05 | AM40: 0 | AN40: 0 | AO40: 10.6 | AP40: 0 | AQ40: 0.84 | AR40: 0 | AS40: 0 | AT40: 90 | AU40: 46 | AV40: 1.047 | AW40: 1 | AZ40: 1 | BA40: 1 | BB40: 1 | BC40: 1 | BH40: 0 | BI40: 2 | BJ40: ТСН-2001.4. Доп. 1-42. Сб. 10, т. 81, поз. 4 | BM40: 68 | BN40: 0 | BO40: 4.10-81-4 | BP40: 1 | BQ40: 40 | BR40: 0 | BS40: 1 | BT40: 1 | BU40: 1 | BV40: 1 | BW40: 1 | BX40: 1 | BZ40: 90 | CA40: 46 | CE40: 1566 | CF40: 0 | CG40: 0 | CM40: 0 | CN40: Поправка: Гл.12.Прил.8.п.8. 3_12.00.01.11.001 Наименование: При наличии напряженных и стесненных условий производства работ (стесненность, сложность складирования и транспортной логистики и т.п.) для объектов, расположенных в пределах круговой магистральной системы улиц "Садовое кольцо" города Москвы Поправка: Гл.4.Прил.2.2.п.2.2.29_04.00.01.35.003 Наименование: При демонтаже оборудования, предназначенного в лом | CO40: 0 | CP40: =(P40+Q40+S40) -> 15.98 | CQ40: =ROUND((ROUND((AC40*AW40*1),2)*BC40),2) -> 0 | CR40: =(ROUND((ROUND(((((ET40*1.2)*0.3))*AV40*1),2)*BB40),2)+ROUND((ROUND(((AE40-(((EU40*1.2)*0.3)))*AV40*1),2)*BS40),2)) -> 0 | CS40: =(ROUND((ROUND(((((EU40*1.2)*0.3))*AV40*1),2)*BS40),2)+ROUND((ROUND(((AE40-(((EU40*1.2)*0.3)))*AV40*1),2)*BS40),2)) -> 0 | CT40: =ROUND((ROUND((AF40*AV40*1),2)*BA40),2) -> 4 | CU40: =AG40 -> 0 | CV40: =(AH40*AV40) -> 0.3166128 | CW40: =AI40 -> 0 | CX40: =AJ40 -> 0 | CY40: =(ROUND((((S40+ROUND((ROUND(((((EU40*1.2)*0.3))*AV40*1),2)*BS40),2))*AT40)/100),2)+ROUND(((ROUND((ROUND(((AE40-(((EU40*1.2)*0.3)))*AV40*1),2)*BS40),2)*AT40)/100),2)) -> 14.38 | CZ40: =(ROUND((((S40+ROUND((ROUND(((((EU40*1.2)*0.3))*AV40*1),2)*BS40),2))*AU40)/100),2)+ROUND(((ROUND((ROUND(((AE40-(((EU40*1.2)*0.3)))*AV40*1),2)*BS40),2)*AU40)/100),2)) -> 7.35 | DB40: 25 | DD40: *1)*0 | DE40: *1,2)*0,3 | DF40: *1,2)*0,3 | DG40: *1,2)*0,3 | DI40: *1,2)*0,3 | DJ40: *1,2)*0,3 | DN40: 0 | DO40: 0 | DP40: 1 | DQ40: 1 | DU40: 1013 | DV40: 1 ШТ. | DW40: 1 ШТ. | DX40: 1 | EE40: 55393700 | EF40: 40 | EG40: Монтаж оборудования | EH40: 0 | EJ40: 2 | EK40: 68 | EL40: ТСН-2001.4-10. Прокладка и монтаж сетей связи | EM40: ТСН-2001.4-10-1 | EO40: Поправка: Гл.12.Прил.8.п.8. 3_12.00.01.11.001 Поправка: Гл.4.Прил.2.2.п.2.2.29_04.00.01.35.003 | EQ40: 0 | ER40: 11.65 | ES40: 1.05 | ET40: 0 | EU40: 0 | EV40: 10.6 | EW40: 0.84 | EX40: 0 | EY40: 0 | FQ40: 0 | FR40: 0 | FS40: 0 | FX40: 90 | FY40: 46 | GD40: 1 | GF40: -1537307853 | GG40: 2 | GH40: 1 | GI40: 2 | GJ40: 0 | GK40: 0 | GL40: =ROUND(IF(AND(BH40=3,BI40=3,FS40<>0),P40,0),2) -> 0 | GM40: =ROUND(O40+X40+Y40,2)+GX40 -> 37.71 | GN40: =IF(OR(BI40=0,BI40=1),GM40-GX40,0) -> 0 | GO40: =IF(BI40=2,GM40-GX40,0) -> 37.71 | GP40: =IF(BI40=4,GM40-GX40,0) -> 0 | GR40: 0 | GS40: 3 | GT40: 0 | GV40: =ROUND((GT40),6) -> 0 | GW40: 1 | GX40: =ROUND(HC40*I40,2) -> 0 | HA40: 0 | HB40: 0 | HC40: =GV40*GW40 -> 0 | HS40: 0 | IK40: 0
A41: 17 | B41: 1 | C41: =ROW(SmtRes!A44) -> 44 | D41: =ROW(EtalonRes!A58) -> 58 | E41: 7 | F41: 4.10-81-4 | G41: Извещатели ОС автоматические, контактный, магнито-контактный на открывание окон, дверей / демонтаж извещателей | H41: 1 ШТ. | I41: 4 | J41: 0 | K41: 4 | O41: =ROUND(CP41,2) -> 900.47 | P41: =ROUND((ROUND((AC41*AW41*I41),2)*BC41),2) -> 0 | Q41: =(ROUND((ROUND(((((ET41*1.2)*0.3))*AV41*I41),2)*BB41),2)+ROUND((ROUND(((AE41-(((EU41*1.2)*0.3)))*AV41*I41),2)*BS41),2)) -> 0 | R41: =(ROUND((ROUND(((((EU41*1.2)*0.3))*AV41*I41),2)*BS41),2)+ROUND((ROUND(((AE41-(((EU41*1.2)*0.3)))*AV41*I41),2)*BS41),2)) -> 0 | S41: =ROUND((ROUND((AF41*AV41*I41),2)*BA41),2) -> 900.47 | T41: =ROUND(CU41*I41,2) -> 0 | U41: =CV41*I41 -> 1.2664512 | V41: =CW41*I41 -> 0 | W41: =ROUND(CX41*I41,2) -> 0 | X41: =(ROUND((((S41+ROUND((ROUND(((((EU41*1.2)*0.3))*AV41*I41),2)*BS41),2))*AT41)/100),2)+ROUND(((ROUND((ROUND(((AE41-(((EU41*1.2)*0.3)))*AV41*I41),2)*BS41),2)*AT41)/100),2)) -> 810.42 | Y41: =(ROUND((((S41+ROUND((ROUND(((((EU41*1.2)*0.3))*AV41*I41),2)*BS41),2))*AU41)/100),2)+ROUND(((ROUND((ROUND(((AE41-(((EU41*1.2)*0.3)))*AV41*I41),2)*BS41),2)*AU41)/100),2)) -> 414.22 | AA41: 55937298 | AB41: =ROUND((AC41+AD41+AF41),6) -> 3.816 | AC41: =ROUND((((ES41*1)*0)),6) -> 0 | AD41: =ROUND((((((ET41*1.2)*0.3))-(((EU41*1.2)*0.3)))+AE41),6) -> 0 | AE41: =ROUND((((EU41*1.2)*0.3)),6) -> 0 | AF41: =ROUND((((EV41*1.2)*0.3)),6) -> 3.816 | AG41: =ROUND((AP41),6) -> 0 | AH41: =(((EW41*1.2)*0.3)) -> 0.3024 | AI41: =(((EX41*1.2)*0.3)) -> 0 | AJ41: =(AS41) -> 0 | AK41: 11.65 | AL41: 1.05 | AM41: 0 | AN41: 0 | AO41: 10.6 | AP41: 0 | AQ41: 0.84 | AR41: 0 | AS41: 0 | AT41: 90 | AU41: 46 | AV41: 1.047 | AW41: 1 | AZ41: 1 | BA41: 56.35 | BB41: 1 | BC41: 9.84 | BH41: 0 | BI41: 2 | BJ41: ТСН-2001.4. Доп. 1-42. Сб. 10, т. 81, поз. 4 | BM41: 68 | BN41: 0 | BO41: 4.10-81-4 | BP41: 1 | BQ41: 40 | BR41: 0 | BS41: 56.35 | BT41: 1 | BU41: 1 | BV41: 1 | BW41: 1 | BX41: 1 | BZ41: 90 | CA41: 46 | CE41: 1566 | CF41: 0 | CG41: 0 | CM41: 0 | CN41: Поправка: Гл.12.Прил.8.п.8. 3_12.00.01.11.001 Наименование: При наличии напряженных и стесненных условий производства работ (стесненность, сложность складирования и транспортной логистики и т.п.) для объектов, расположенных в пределах круговой магистральной системы улиц "Садовое кольцо" города Москвы Поправка: Гл.4.Прил.2.2.п.2.2.29_04.00.01.35.003 Наименование: При демонтаже оборудования, предназначенного в лом | CO41: 0 | CP41: =(P41+Q41+S41) -> 900.47 | CQ41: =ROUND((ROUND((AC41*AW41*1),2)*BC41),2) -> 0 | CR41: =(ROUND((ROUND(((((ET41*1.2)*0.3))*AV41*1),2)*BB41),2)+ROUND((ROUND(((AE41-(((EU41*1.2)*0.3)))*AV41*1),2)*BS41),2)) -> 0 | CS41: =(ROUND((ROUND(((((EU41*1.2)*0.3))*AV41*1),2)*BS41),2)+ROUND((ROUND(((AE41-(((EU41*1.2)*0.3)))*AV41*1),2)*BS41),2)) -> 0 | CT41: =ROUND((ROUND((AF41*AV41*1),2)*BA41),2) -> 225.4 | CU41: =AG41 -> 0 | CV41: =(AH41*AV41) -> 0.3166128 | CW41: =AI41 -> 0 | CX41: =AJ41 -> 0 | CY41: =(ROUND((((S41+ROUND((ROUND(((((EU41*1.2)*0.3))*AV41*1),2)*BS41),2))*AT41)/100),2)+ROUND(((ROUND((ROUND(((AE41-(((EU41*1.2)*0.3)))*AV41*1),2)*BS41),2)*AT41)/100),2)) -> 810.42 | CZ41: =(ROUND((((S41+ROUND((ROUND(((((EU41*1.2)*0.3))*AV41*1),2)*BS41),2))*AU41)/100),2)+ROUND(((ROUND((ROUND(((AE41-(((EU41*1.2)*0.3)))*AV41*1),2)*BS41),2)*AU41)/100),2)) -> 414.22 | DB41: 27 | DD41: *1)*0 | DE41: *1,2)*0,3 | DF41: *1,2)*0,3 | DG41: *1,2)*0,3 | DI41: *1,2)*0,3 | DJ41: *1,2)*0,3 | DN41: 0 | DO41: 0 | DP41: 1 | DQ41: 1 | DU41: 1013 | DV41: 1 ШТ. | DW41: 1 ШТ. | DX41: 1 | EE41: 55393700 | EF41: 40 | EG41: Монтаж оборудования | EH41: 0 | EJ41: 2 | EK41: 68 | EL41: ТСН-2001.4-10. Прокладка и монтаж сетей связи | EM41: ТСН-2001.4-10-1 | EO41: Поправка: Гл.12.Прил.8.п.8. 3_12.00.01.11.001 Поправка: Гл.4.Прил.2.2.п.2.2.29_04.00.01.35.003 | EQ41: 0 | ER41: 11.65 | ES41: 1.05 | ET41: 0 | EU41: 0 | EV41: 10.6 | EW41: 0.84 | EX41: 0 | EY41: 0 | FQ41: 0 | FR41: 0 | FS41: 0 | FX41: 90 | FY41: 46 | GD41: 1 | GF41: -1537307853 | GG41: 2 | GH41: 1 | GI41: 2 | GJ41: 0 | GK41: 0 | GL41: =ROUND(IF(AND(BH41=3,BI41=3,FS41<>0),P41,0),2) -> 0 | GM41: =ROUND(O41+X41+Y41,2)+GX41 -> 2125.11 | GN41: =IF(OR(BI41=0,BI41=1),GM41-GX41,0) -> 0 | GO41: =IF(BI41=2,GM41-GX41,0) -> 2125.11 | GP41: =IF(BI41=4,GM41-GX41,0) -> 0 | GR41: 0 | GS41: 3 | GT41: 0 | GV41: =ROUND((GT41),6) -> 0 | GW41: 1 | GX41: =ROUND(HC41*I41,2) -> 0 | HA41: 0 | HB41: 0 | HC41: =GV41*GW41 -> 0 | HS41: 0 | IK41: 0
A42: 17 | B42: 1 | C42: =ROW(SmtRes!A50) -> 50 | D42: =ROW(EtalonRes!A66) -> 66 | E42: 8 | F42: 4.8-245-10 | G42: Монтаж светильников с лампами накаливания, светового настенного указателя / демонтаж оповещателя пожарного светового | H42: 100 шт. | I42: =ROUND((4+4+4)/100,9) -> 0.12 | J42: 0 | K42: =ROUND((4+4+4)/100,9) -> 0.12 | O42: =ROUND(CP42,2) -> 53.97 | P42: =ROUND((ROUND((AC42*AW42*I42),2)*BC42),2) -> 0 | Q42: =(ROUND((ROUND(((((ET42*1.2)*0.3))*AV42*I42),2)*BB42),2)+ROUND((ROUND(((AE42-(((EU42*1.2)*0.3)))*AV42*I42),2)*BS42),2)) -> 4.22 | R42: =(ROUND((ROUND(((((EU42*1.2)*0.3))*AV42*I42),2)*BS42),2)+ROUND((ROUND(((AE42-(((EU42*1.2)*0.3)))*AV42*I42),2)*BS42),2)) -> 0.59 | S42: =ROUND((ROUND((AF42*AV42*I42),2)*BA42),2) -> 49.75 | T42: =ROUND(CU42*I42,2) -> 0 | U42: =CV42*I42 -> 3.829658 | V42: =CW42*I42 -> 0 | W42: =ROUND(CX42*I42,2) -> 0 | X42: =(ROUND((((S42+ROUND((ROUND(((((EU42*1.2)*0.3))*AV42*I42),2)*BS42),2))*AT42)/100),2)+ROUND(((ROUND((ROUND(((AE42-(((EU42*1.2)*0.3)))*AV42*I42),2)*BS42),2)*AT42)/100),2)) -> 48.83 | Y42: =(ROUND((((S42+ROUND((ROUND(((((EU42*1.2)*0.3))*AV42*I42),2)*BS42),2))*AU42)/100),2)+ROUND(((ROUND((ROUND(((AE42-(((EU42*1.2)*0.3)))*AV42*I42),2)*BS42),2)*AU42)/100),2)) -> 25.67 | AA42: 55937296 | AB42: =ROUND((AC42+AD42+AF42),6) -> 429.5448 | AC42: =ROUND((((ES42*1)*0)),6) -> 0 | AD42: =ROUND((((((ET42*1.2)*0.3))-(((EU42*1.2)*0.3)))+AE42),6) -> 33.5952 | AE42: =ROUND((((EU42*1.2)*0.3)),6) -> 4.68 | AF42: =ROUND((((EV42*1.2)*0.3)),6) -> 395.9496 | AG42: =ROUND((AP42),6) -> 0 | AH42: =(((EW42*1.2)*0.3)) -> 30.4812 | AI42: =(((EX42*1.2)*0.3)) -> 0 | AJ42: =(AS42) -> 0 | AK42: 1274.54 | AL42: 81.36 | AM42: 93.32 | AN42: 13 | AO42: 1099.86 | AP42: 0 | AQ42: 84.67 | AR42: 0 | AS42: 0 | AT42: 97 | AU42: 51 | AV42: 1.047 | AW42: 1 | AZ42: 1 | BA42: 1 | BB42: 1 | BC42: 1 | BH42: 0 | BI42: 2 | BJ42: ТСН-2001.4 Доп. 79, Сб. 8, т. 245, поз. 10 | BM42: 67 | BN42: 0 | BO42: 4.8-245-10 | BP42: 1 | BQ42: 40 | BR42: 0 | BS42: 1 | BT42: 1 | BU42: 1 | BV42: 1 | BW42: 1 | BX42: 1 | BZ42: 97 | CA42: 51 | CE42: 1566 | CF42: 0 | CG42: 0 | CM42: 0 | CN42: Поправка: Гл.12.Прил.8.п.8. 3_12.00.01.11.001 Наименование: При наличии напряженных и стесненных условий производства работ (стесненность, сложность складирования и транспортной логистики и т.п.) для объектов, расположенных в пределах круговой магистральной системы улиц "Садовое кольцо" города Москвы Поправка: Гл.4.Прил.2.2.п.2.2.29_04.00.01.35.003 Наименование: При демонтаже оборудования, предназначенного в лом | CO42: 0 | CP42: =(P42+Q42+S42) -> 53.97 | CQ42: =ROUND((ROUND((AC42*AW42*1),2)*BC42),2) -> 0 | CR42: =(ROUND((ROUND(((((ET42*1.2)*0.3))*AV42*1),2)*BB42),2)+ROUND((ROUND(((AE42-(((EU42*1.2)*0.3)))*AV42*1),2)*BS42),2)) -> 35.17 | CS42: =(ROUND((ROUND(((((EU42*1.2)*0.3))*AV42*1),2)*BS42),2)+ROUND((ROUND(((AE42-(((EU42*1.2)*0.3)))*AV42*1),2)*BS42),2)) -> 4.9 | CT42: =ROUND((ROUND((AF42*AV42*1),2)*BA42),2) -> 414.56 | CU42: =AG42 -> 0 | CV42: =(AH42*AV42) -> 31.913816 | CW42: =AI42 -> 0 | CX42: =AJ42 -> 0 | CY42: =(ROUND((((S42+ROUND((ROUND(((((EU42*1.2)*0.3))*AV42*1),2)*BS42),2))*AT42)/100),2)+ROUND(((ROUND((ROUND(((AE42-(((EU42*1.2)*0.3)))*AV42*1),2)*BS42),2)*AT42)/100),2)) -> 53.01 | CZ42: =(ROUND((((S42+ROUND((ROUND(((((EU42*1.2)*0.3))*AV42*1),2)*BS42),2))*AU42)/100),2)+ROUND(((ROUND((ROUND(((AE42-(((EU42*1.2)*0.3)))*AV42*1),2)*BS42),2)*AU42)/100),2)) -> 27.87 | DB42: 29 | DD42: *1)*0 | DE42: *1,2)*0,3 | DF42: *1,2)*0,3 | DG42: *1,2)*0,3 | DI42: *1,2)*0,3 | DJ42: *1,2)*0,3 | DN42: 0 | DO42: 0 | DP42: 1 | DQ42: 1 | DU42: 1010 | DV42: 100 шт. | DW42: 100 шт. | DX42: 100 | EE42: 55393699 | EF42: 40 | EG42: Монтаж оборудования | EH42: 0 | EJ42: 2 | EK42: 67 | EL42: ТСН-2001.4-8. Электротехнические установки | EM42: ТСН-2001.4-8-1 | EO42: Поправка: Гл.12.Прил.8.п.8. 3_12.00.01.11.001 Поправка: Гл.4.Прил.2.2.п.2.2.29_04.00.01.35.003 | EQ42: 0 | ER42: 1274.54 | ES42: 81.36 | ET42: 93.32 | EU42: 13 | EV42: 1099.86 | EW42: 84.67 | EX42: 0 | EY42: 0 | FQ42: 0 | FR42: 0 | FS42: 0 | FX42: 97 | FY42: 51 | GD42: 1 | GF42: -1893547232 | GG42: 2 | GH42: 1 | GI42: 2 | GJ42: 0 | GK42: 0 | GL42: =ROUND(IF(AND(BH42=3,BI42=3,FS42<>0),P42,0),2) -> 0 | GM42: =ROUND(O42+X42+Y42,2)+GX42 -> 128.47 | GN42: =IF(OR(BI42=0,BI42=1),GM42-GX42,0) -> 0 | GO42: =IF(BI42=2,GM42-GX42,0) -> 128.47 | GP42: =IF(BI42=4,GM42-GX42,0) -> 0 | GR42: 0 | GS42: 3 | GT42: 0 | GV42: =ROUND((GT42),6) -> 0 | GW42: 1 | GX42: =ROUND(HC42*I42,2) -> 0 | HA42: 0 | HB42: 0 | HC42: =GV42*GW42 -> 0 | HS42: 0 | IK42: 0
A43: 17 | B43: 1 | C43: =ROW(SmtRes!A56) -> 56 | D43: =ROW(EtalonRes!A74) -> 74 | E43: 8 | F43: 4.8-245-10 | G43: Монтаж светильников с лампами накаливания, светового настенного указателя / демонтаж оповещателя пожарного светового | H43: 100 шт. | I43: =ROUND((4+4+4)/100,9) -> 0.12 | J43: 0 | K43: =ROUND((4+4+4)/100,9) -> 0.12 | O43: =ROUND(CP43,2) -> 2872.7 | P43: =ROUND((ROUND((AC43*AW43*I43),2)*BC43),2) -> 0 | Q43: =(ROUND((ROUND(((((ET43*1.2)*0.3))*AV43*I43),2)*BB43),2)+ROUND((ROUND(((AE43-(((EU43*1.2)*0.3)))*AV43*I43),2)*BS43),2)) -> 69.29 | R43: =(ROUND((ROUND(((((EU43*1.2)*0.3))*AV43*I43),2)*BS43),2)+ROUND((ROUND(((AE43-(((EU43*1.2)*0.3)))*AV43*I43),2)*BS43),2)) -> 33.25 | S43: =ROUND((ROUND((AF43*AV43*I43),2)*BA43),2) -> 2803.41 | T43: =ROUND(CU43*I43,2) -> 0 | U43: =CV43*I43 -> 3.829658 | V43: =CW43*I43 -> 0 | W43: =ROUND(CX43*I43,2) -> 0 | X43: =(ROUND((((S43+ROUND((ROUND(((((EU43*1.2)*0.3))*AV43*I43),2)*BS43),2))*AT43)/100),2)+ROUND(((ROUND((ROUND(((AE43-(((EU43*1.2)*0.3)))*AV43*I43),2)*BS43),2)*AT43)/100),2)) -> 2751.56 | Y43: =(ROUND((((S43+ROUND((ROUND(((((EU43*1.2)*0.3))*AV43*I43),2)*BS43),2))*AU43)/100),2)+ROUND(((ROUND((ROUND(((AE43-(((EU43*1.2)*0.3)))*AV43*I43),2)*BS43),2)*AU43)/100),2)) -> 1446.7 | AA43: 55937298 | AB43: =ROUND((AC43+AD43+AF43),6) -> 429.5448 | AC43: =ROUND((((ES43*1)*0)),6) -> 0 | AD43: =ROUND((((((ET43*1.2)*0.3))-(((EU43*1.2)*0.3)))+AE43),6) -> 33.5952 | AE43: =ROUND((((EU43*1.2)*0.3)),6) -> 4.68 | AF43: =ROUND((((EV43*1.2)*0.3)),6) -> 395.9496 | AG43: =ROUND((AP43),6) -> 0 | AH43: =(((EW43*1.2)*0.3)) -> 30.4812 | AI43: =(((EX43*1.2)*0.3)) -> 0 | AJ43: =(AS43) -> 0 | AK43: 1274.54 | AL43: 81.36 | AM43: 93.32 | AN43: 13 | AO43: 1099.86 | AP43: 0 | AQ43: 84.67 | AR43: 0 | AS43: 0 | AT43: 97 | AU43: 51 | AV43: 1.047 | AW43: 1 | AZ43: 1 | BA43: 56.35 | BB43: 16.42 | BC43: 10.65 | BH43: 0 | BI43: 2 | BJ43: ТСН-2001.4 Доп. 79, Сб. 8, т. 245, поз. 10 | BM43: 67 | BN43: 0 | BO43: 4.8-245-10 | BP43: 1 | BQ43: 40 | BR43: 0 | BS43: 56.35 | BT43: 1 | BU43: 1 | BV43: 1 | BW43: 1 | BX43: 1 | BZ43: 97 | CA43: 51 | CE43: 1566 | CF43: 0 | CG43: 0 | CM43: 0 | CN43: Поправка: Гл.12.Прил.8.п.8. 3_12.00.01.11.001 Наименование: При наличии напряженных и стесненных условий производства работ (стесненность, сложность складирования и транспортной логистики и т.п.) для объектов, расположенных в пределах круговой магистральной системы улиц "Садовое кольцо" города Москвы Поправка: Гл.4.Прил.2.2.п.2.2.29_04.00.01.35.003 Наименование: При демонтаже оборудования, предназначенного в лом | CO43: 0 | CP43: =(P43+Q43+S43) -> 2872.7 | CQ43: =ROUND((ROUND((AC43*AW43*1),2)*BC43),2) -> 0 | CR43: =(ROUND((ROUND(((((ET43*1.2)*0.3))*AV43*1),2)*BB43),2)+ROUND((ROUND(((AE43-(((EU43*1.2)*0.3)))*AV43*1),2)*BS43),2)) -> 577.49 | CS43: =(ROUND((ROUND(((((EU43*1.2)*0.3))*AV43*1),2)*BS43),2)+ROUND((ROUND(((AE43-(((EU43*1.2)*0.3)))*AV43*1),2)*BS43),2)) -> 276.12 | CT43: =ROUND((ROUND((AF43*AV43*1),2)*BA43),2) -> 23360.46 | CU43: =AG43 -> 0 | CV43: =(AH43*AV43) -> 31.913816 | CW43: =AI43 -> 0 | CX43: =AJ43 -> 0 | CY43: =(ROUND((((S43+ROUND((ROUND(((((EU43*1.2)*0.3))*AV43*1),2)*BS43),2))*AT43)/100),2)+ROUND(((ROUND((ROUND(((AE43-(((EU43*1.2)*0.3)))*AV43*1),2)*BS43),2)*AT43)/100),2)) -> 2987.14 | CZ43: =(ROUND((((S43+ROUND((ROUND(((((EU43*1.2)*0.3))*AV43*1),2)*BS43),2))*AU43)/100),2)+ROUND(((ROUND((ROUND(((AE43-(((EU43*1.2)*0.3)))*AV43*1),2)*BS43),2)*AU43)/100),2)) -> 1570.56 | DB43: 31 | DD43: *1)*0 | DE43: *1,2)*0,3 | DF43: *1,2)*0,3 | DG43: *1,2)*0,3 | DI43: *1,2)*0,3 | DJ43: *1,2)*0,3 | DN43: 0 | DO43: 0 | DP43: 1 | DQ43: 1 | DU43: 1010 | DV43: 100 шт. | DW43: 100 шт. | DX43: 100 | EE43: 55393699 | EF43: 40 | EG43: Монтаж оборудования | EH43: 0 | EJ43: 2 | EK43: 67 | EL43: ТСН-2001.4-8. Электротехнические установки | EM43: ТСН-2001.4-8-1 | EO43: Поправка: Гл.12.Прил.8.п.8. 3_12.00.01.11.001 Поправка: Гл.4.Прил.2.2.п.2.2.29_04.00.01.35.003 | EQ43: 0 | ER43: 1274.54 | ES43: 81.36 | ET43: 93.32 | EU43: 13 | EV43: 1099.86 | EW43: 84.67 | EX43: 0 | EY43: 0 | FQ43: 0 | FR43: 0 | FS43: 0 | FX43: 97 | FY43: 51 | GD43: 1 | GF43: -1893547232 | GG43: 2 | GH43: 1 | GI43: 2 | GJ43: 0 | GK43: 0 | GL43: =ROUND(IF(AND(BH43=3,BI43=3,FS43<>0),P43,0),2) -> 0 | GM43: =ROUND(O43+X43+Y43,2)+GX43 -> 7070.96 | GN43: =IF(OR(BI43=0,BI43=1),GM43-GX43,0) -> 0 | GO43: =IF(BI43=2,GM43-GX43,0) -> 7070.96 | GP43: =IF(BI43=4,GM43-GX43,0) -> 0 | GR43: 0 | GS43: 3 | GT43: 0 | GV43: =ROUND((GT43),6) -> 0 | GW43: 1 | GX43: =ROUND(HC43*I43,2) -> 0 | HA43: 0 | HB43: 0 | HC43: =GV43*GW43 -> 0 | HS43: 0 | IK43: 0
A44: 17 | B44: 1 | C44: =ROW(SmtRes!A57) -> 57 | D44: =ROW(EtalonRes!A75) -> 75 | E44: 9 | F44: 4.10-81-2 | G44: Извещатели ПС автоматические, дымовой, фотоэлектрический, радиоизотопный, световой в нормальном исполнении / демонтаж оповещателей | H44: 1 ШТ. | I44: 4 | J44: 0 | K44: 4 | O44: =ROUND(CP44,2) -> 32.05 | P44: =ROUND((ROUND((AC44*AW44*I44),2)*BC44),2) -> 0 | Q44: =(ROUND((ROUND(((((ET44*1.2)*0.3))*AV44*I44),2)*BB44),2)+ROUND((ROUND(((AE44-(((EU44*1.2)*0.3)))*AV44*I44),2)*BS44),2)) -> 0.09 | R44: =(ROUND((ROUND(((((EU44*1.2)*0.3))*AV44*I44),2)*BS44),2)+ROUND((ROUND(((AE44-(((EU44*1.2)*0.3)))*AV44*I44),2)*BS44),2)) -> 0.02 | S44: =ROUND((ROUND((AF44*AV44*I44),2)*BA44),2) -> 31.96 | T44: =ROUND(CU44*I44,2) -> 0 | U44: =CV44*I44 -> 2.5329024 | V44: =CW44*I44 -> 0 | W44: =ROUND(CX44*I44,2) -> 0 | X44: =(ROUND((((S44+ROUND((ROUND(((((EU44*1.2)*0.3))*AV44*I44),2)*BS44),2))*AT44)/100),2)+ROUND(((ROUND((ROUND(((AE44-(((EU44*1.2)*0.3)))*AV44*I44),2)*BS44),2)*AT44)/100),2)) -> 28.78 | Y44: =(ROUND((((S44+ROUND((ROUND(((((EU44*1.2)*0.3))*AV44*I44),2)*BS44),2))*AU44)/100),2)+ROUND(((ROUND((ROUND(((AE44-(((EU44*1.2)*0.3)))*AV44*I44),2)*BS44),2)*AU44)/100),2)) -> 14.71 | AA44: 55937296 | AB44: =ROUND((AC44+AD44+AF44),6) -> 7.6536 | AC44: =ROUND((((ES44*1)*0)),6) -> 0 | AD44: =ROUND((((((ET44*1.2)*0.3))-(((EU44*1.2)*0.3)))+AE44),6) -> 0.0216 | AE44: =ROUND((((EU44*1.2)*0.3)),6) -> 0.0036 | AF44: =ROUND((((EV44*1.2)*0.3)),6) -> 7.632 | AG44: =ROUND((AP44),6) -> 0 | AH44: =(((EW44*1.2)*0.3)) -> 0.6048 | AI44: =(((EX44*1.2)*0.3)) -> 0 | AJ44: =(AS44) -> 0 | AK44: 22.52 | AL44: 1.26 | AM44: 0.06 | AN44: 0.01 | AO44: 21.2 | AP44: 0 | AQ44: 1.68 | AR44: 0 | AS44: 0 | AT44: 90 | AU44: 46 | AV44: 1.047 | AW44: 1 | AZ44: 1 | BA44: 1 | BB44: 1 | BC44: 1 | BH44: 0 | BI44: 2 | BJ44: ТСН-2001.4. Доп. 1-42. Сб. 10, т. 81, поз. 2 | BM44: 68 | BN44: 0 | BO44: 4.10-81-2 | BP44: 1 | BQ44: 40 | BR44: 0 | BS44: 1 | BT44: 1 | BU44: 1 | BV44: 1 | BW44: 1 | BX44: 1 | BZ44: 90 | CA44: 46 | CE44: 1566 | CF44: 0 | CG44: 0 | CM44: 0 | CN44: Поправка: Гл.12.Прил.8.п.8. 3_12.00.01.11.001 Наименование: При наличии напряженных и стесненных условий производства работ (стесненность, сложность складирования и транспортной логистики и т.п.) для объектов, расположенных в пределах круговой магистральной системы улиц "Садовое кольцо" города Москвы Поправка: Гл.4.Прил.2.2.п.2.2.29_04.00.01.35.003 Наименование: При демонтаже оборудования, предназначенного в лом | CO44: 0 | CP44: =(P44+Q44+S44) -> 32.05 | CQ44: =ROUND((ROUND((AC44*AW44*1),2)*BC44),2) -> 0 | CR44: =(ROUND((ROUND(((((ET44*1.2)*0.3))*AV44*1),2)*BB44),2)+ROUND((ROUND(((AE44-(((EU44*1.2)*0.3)))*AV44*1),2)*BS44),2)) -> 0.02 | CS44: =(ROUND((ROUND(((((EU44*1.2)*0.3))*AV44*1),2)*BS44),2)+ROUND((ROUND(((AE44-(((EU44*1.2)*0.3)))*AV44*1),2)*BS44),2)) -> 0 | CT44: =ROUND((ROUND((AF44*AV44*1),2)*BA44),2) -> 7.99 | CU44: =AG44 -> 0 | CV44: =(AH44*AV44) -> 0.6332256 | CW44: =AI44 -> 0 | CX44: =AJ44 -> 0 | CY44: =(ROUND((((S44+ROUND((ROUND(((((EU44*1.2)*0.3))*AV44*1),2)*BS44),2))*AT44)/100),2)+ROUND(((ROUND((ROUND(((AE44-(((EU44*1.2)*0.3)))*AV44*1),2)*BS44),2)*AT44)/100),2)) -> 28.76 | CZ44: =(ROUND((((S44+ROUND((ROUND(((((EU44*1.2)*0.3))*AV44*1),2)*BS44),2))*AU44)/100),2)+ROUND(((ROUND((ROUND(((AE44-(((EU44*1.2)*0.3)))*AV44*1),2)*BS44),2)*AU44)/100),2)) -> 14.7 | DB44: 33 | DD44: *1)*0 | DE44: *1,2)*0,3 | DF44: *1,2)*0,3 | DG44: *1,2)*0,3 | DI44: *1,2)*0,3 | DJ44: *1,2)*0,3 | DN44: 0 | DO44: 0 | DP44: 1 | DQ44: 1 | DU44: 1013 | DV44: 1 ШТ. | DW44: 1 ШТ. | DX44: 1 | EE44: 55393700 | EF44: 40 | EG44: Монтаж оборудования | EH44: 0 | EJ44: 2 | EK44: 68 | EL44: ТСН-2001.4-10. Прокладка и монтаж сетей связи | EM44: ТСН-2001.4-10-1 | EO44: Поправка: Гл.12.Прил.8.п.8. 3_12.00.01.11.001 Поправка: Гл.4.Прил.2.2.п.2.2.29_04.00.01.35.003 | EQ44: 0 | ER44: 22.52 | ES44: 1.26 | ET44: 0.06 | EU44: 0.01 | EV44: 21.2 | EW44: 1.68 | EX44: 0 | EY44: 0 | FQ44: 0 | FR44: 0 | FS44: 0 | FX44: 90 | FY44: 46 | GD44: 1 | GF44: -324079866 | GG44: 2 | GH44: 1 | GI44: 2 | GJ44: 0 | GK44: 0 | GL44: =ROUND(IF(AND(BH44=3,BI44=3,FS44<>0),P44,0),2) -> 0 | GM44: =ROUND(O44+X44+Y44,2)+GX44 -> 75.54 | GN44: =IF(OR(BI44=0,BI44=1),GM44-GX44,0) -> 0 | GO44: =IF(BI44=2,GM44-GX44,0) -> 75.54 | GP44: =IF(BI44=4,GM44-GX44,0) -> 0 | GR44: 0 | GS44: 3 | GT44: 0 | GV44: =ROUND((GT44),6) -> 0 | GW44: 1 | GX44: =ROUND(HC44*I44,2) -> 0 | HA44: 0 | HB44: 0 | HC44: =GV44*GW44 -> 0 | HS44: 0 | IK44: 0
A45: 17 | B45: 1 | C45: =ROW(SmtRes!A58) -> 58 | D45: =ROW(EtalonRes!A76) -> 76 | E45: 9 | F45: 4.10-81-2 | G45: Извещатели ПС автоматические, дымовой, фотоэлектрический, радиоизотопный, световой в нормальном исполнении / демонтаж оповещателей | H45: 1 ШТ. | I45: 4 | J45: 0 | K45: 4 | O45: =ROUND(CP45,2) -> 1802.62 | P45: =ROUND((ROUND((AC45*AW45*I45),2)*BC45),2) -> 0 | Q45: =(ROUND((ROUND(((((ET45*1.2)*0.3))*AV45*I45),2)*BB45),2)+ROUND((ROUND(((AE45-(((EU45*1.2)*0.3)))*AV45*I45),2)*BS45),2)) -> 1.67 | R45: =(ROUND((ROUND(((((EU45*1.2)*0.3))*AV45*I45),2)*BS45),2)+ROUND((ROUND(((AE45-(((EU45*1.2)*0.3)))*AV45*I45),2)*BS45),2)) -> 1.13 | S45: =ROUND((ROUND((AF45*AV45*I45),2)*BA45),2) -> 1800.95 | T45: =ROUND(CU45*I45,2) -> 0 | U45: =CV45*I45 -> 2.5329024 | V45: =CW45*I45 -> 0 | W45: =ROUND(CX45*I45,2) -> 0 | X45: =(ROUND((((S45+ROUND((ROUND(((((EU45*1.2)*0.3))*AV45*I45),2)*BS45),2))*AT45)/100),2)+ROUND(((ROUND((ROUND(((AE45-(((EU45*1.2)*0.3)))*AV45*I45),2)*BS45),2)*AT45)/100),2)) -> 1621.87 | Y45: =(ROUND((((S45+ROUND((ROUND(((((EU45*1.2)*0.3))*AV45*I45),2)*BS45),2))*AU45)/100),2)+ROUND(((ROUND((ROUND(((AE45-(((EU45*1.2)*0.3)))*AV45*I45),2)*BS45),2)*AU45)/100),2)) -> 828.96 | AA45: 55937298 | AB45: =ROUND((AC45+AD45+AF45),6) -> 7.6536 | AC45: =ROUND((((ES45*1)*0)),6) -> 0 | AD45: =ROUND((((((ET45*1.2)*0.3))-(((EU45*1.2)*0.3)))+AE45),6) -> 0.0216 | AE45: =ROUND((((EU45*1.2)*0.3)),6) -> 0.0036 | AF45: =ROUND((((EV45*1.2)*0.3)),6) -> 7.632 | AG45: =ROUND((AP45),6) -> 0 | AH45: =(((EW45*1.2)*0.3)) -> 0.6048 | AI45: =(((EX45*1.2)*0.3)) -> 0 | AJ45: =(AS45) -> 0 | AK45: 22.52 | AL45: 1.26 | AM45: 0.06 | AN45: 0.01 | AO45: 21.2 | AP45: 0 | AQ45: 1.68 | AR45: 0 | AS45: 0 | AT45: 90 | AU45: 46 | AV45: 1.047 | AW45: 1 | AZ45: 1 | BA45: 56.35 | BB45: 18.5 | BC45: 9.84 | BH45: 0 | BI45: 2 | BJ45: ТСН-2001.4. Доп. 1-42. Сб. 10, т. 81, поз. 2 | BM45: 68 | BN45: 0 | BO45: 4.10-81-2 | BP45: 1 | BQ45: 40 | BR45: 0 | BS45: 56.35 | BT45: 1 | BU45: 1 | BV45: 1 | BW45: 1 | BX45: 1 | BZ45: 90 | CA45: 46 | CE45: 1566 | CF45: 0 | CG45: 0 | CM45: 0 | CN45: Поправка: Гл.12.Прил.8.п.8. 3_12.00.01.11.001 Наименование: При наличии напряженных и стесненных условий производства работ (стесненность, сложность складирования и транспортной логистики и т.п.) для объектов, расположенных в пределах круговой магистральной системы улиц "Садовое кольцо" города Москвы Поправка: Гл.4.Прил.2.2.п.2.2.29_04.00.01.35.003 Наименование: При демонтаже оборудования, предназначенного в лом | CO45: 0 | CP45: =(P45+Q45+S45) -> 1802.62 | CQ45: =ROUND((ROUND((AC45*AW45*1),2)*BC45),2) -> 0 | CR45: =(ROUND((ROUND(((((ET45*1.2)*0.3))*AV45*1),2)*BB45),2)+ROUND((ROUND(((AE45-(((EU45*1.2)*0.3)))*AV45*1),2)*BS45),2)) -> 0.37 | CS45: =(ROUND((ROUND(((((EU45*1.2)*0.3))*AV45*1),2)*BS45),2)+ROUND((ROUND(((AE45-(((EU45*1.2)*0.3)))*AV45*1),2)*BS45),2)) -> 0 | CT45: =ROUND((ROUND((AF45*AV45*1),2)*BA45),2) -> 450.24 | CU45: =AG45 -> 0 | CV45: =(AH45*AV45) -> 0.6332256 | CW45: =AI45 -> 0 | CX45: =AJ45 -> 0 | CY45: =(ROUND((((S45+ROUND((ROUND(((((EU45*1.2)*0.3))*AV45*1),2)*BS45),2))*AT45)/100),2)+ROUND(((ROUND((ROUND(((AE45-(((EU45*1.2)*0.3)))*AV45*1),2)*BS45),2)*AT45)/100),2)) -> 1620.86 | CZ45: =(ROUND((((S45+ROUND((ROUND(((((EU45*1.2)*0.3))*AV45*1),2)*BS45),2))*AU45)/100),2)+ROUND(((ROUND((ROUND(((AE45-(((EU45*1.2)*0.3)))*AV45*1),2)*BS45),2)*AU45)/100),2)) -> 828.44 | DB45: 35 | DD45: *1)*0 | DE45: *1,2)*0,3 | DF45: *1,2)*0,3 | DG45: *1,2)*0,3 | DI45: *1,2)*0,3 | DJ45: *1,2)*0,3 | DN45: 0 | DO45: 0 | DP45: 1 | DQ45: 1 | DU45: 1013 | DV45: 1 ШТ. | DW45: 1 ШТ. | DX45: 1 | EE45: 55393700 | EF45: 40 | EG45: Монтаж оборудования | EH45: 0 | EJ45: 2 | EK45: 68 | EL45: ТСН-2001.4-10. Прокладка и монтаж сетей связи | EM45: ТСН-2001.4-10-1 | EO45: Поправка: Гл.12.Прил.8.п.8. 3_12.00.01.11.001 Поправка: Гл.4.Прил.2.2.п.2.2.29_04.00.01.35.003 | EQ45: 0 | ER45: 22.52 | ES45: 1.26 | ET45: 0.06 | EU45: 0.01 | EV45: 21.2 | EW45: 1.68 | EX45: 0 | EY45: 0 | FQ45: 0 | FR45: 0 | FS45: 0 | FX45: 90 | FY45: 46 | GD45: 1 | GF45: -324079866 | GG45: 2 | GH45: 1 | GI45: 2 | GJ45: 0 | GK45: 0 | GL45: =ROUND(IF(AND(BH45=3,BI45=3,FS45<>0),P45,0),2) -> 0 | GM45: =ROUND(O45+X45+Y45,2)+GX45 -> 4253.45 | GN45: =IF(OR(BI45=0,BI45=1),GM45-GX45,0) -> 0 | GO45: =IF(BI45=2,GM45-GX45,0) -> 4253.45 | GP45: =IF(BI45=4,GM45-GX45,0) -> 0 | GR45: 0 | GS45: 3 | GT45: 0 | GV45: =ROUND((GT45),6) -> 0 | GW45: 1 | GX45: =ROUND(HC45*I45,2) -> 0 | HA45: 0 | HB45: 0 | HC45: =GV45*GW45 -> 0 | HS45: 0 | IK45: 0
A46: 17 | B46: 1 | C46: =ROW(SmtRes!A62) -> 62 | D46: =ROW(EtalonRes!A82) -> 82 | E46: 10 | F46: 4.37-18-4 | G46: Монтаж модуля установки пожаротушения тонкораспыленной водой объемом 13 л за подвесным потолком / демонтаж модулей газового пожаротушения | H46: 1 ШТ. | I46: =ROUND(3+2+2+2,9) -> 9 | J46: 0 | K46: =ROUND(3+2+2+2,9) -> 9 | O46: =ROUND(CP46,2) -> 33.88 | P46: =ROUND((ROUND((AC46*AW46*I46),2)*BC46),2) -> 0 | Q46: =(ROUND((ROUND(((((ET46*1.2)*0.3))*AV46*I46),2)*BB46),2)+ROUND((ROUND(((AE46-(((EU46*1.2)*0.3)))*AV46*I46),2)*BS46),2)) -> 0.17 | R46: =(ROUND((ROUND(((((EU46*1.2)*0.3))*AV46*I46),2)*BS46),2)+ROUND((ROUND(((AE46-(((EU46*1.2)*0.3)))*AV46*I46),2)*BS46),2)) -> 0 | S46: =ROUND((ROUND((AF46*AV46*I46),2)*BA46),2) -> 33.71 | T46: =ROUND(CU46*I46,2) -> 0 | U46: =CV46*I46 -> 2.074248 | V46: =CW46*I46 -> 0 | W46: =ROUND(CX46*I46,2) -> 0 | X46: =(ROUND((((S46+ROUND((ROUND(((((EU46*1.2)*0.3))*AV46*I46),2)*BS46),2))*AT46)/100),2)+ROUND(((ROUND((ROUND(((AE46-(((EU46*1.2)*0.3)))*AV46*I46),2)*BS46),2)*AT46)/100),2)) -> 31.01 | Y46: =(ROUND((((S46+ROUND((ROUND(((((EU46*1.2)*0.3))*AV46*I46),2)*BS46),2))*AU46)/100),2)+ROUND(((ROUND((ROUND(((AE46-(((EU46*1.2)*0.3)))*AV46*I46),2)*BS46),2)*AU46)/100),2)) -> 16.52 | AA46: 55937296 | AB46: =ROUND((AC46+AD46+AF46),6) -> 3.528 | AC46: =ROUND((((ES46*1)*0)),6) -> 0 | AD46: =ROUND((((((ET46*1.2)*0.3))-(((EU46*1.2)*0.3)))+AE46),6) -> 0.018 | AE46: =ROUND((((EU46*1.2)*0.3)),6) -> 0 | AF46: =ROUND((((EV46*1.2)*0.3)),6) -> 3.51 | AG46: =ROUND((AP46),6) -> 0 | AH46: =(((EW46*1.2)*0.3)) -> 0.216 | AI46: =(((EX46*1.2)*0.3)) -> 0 | AJ46: =(AS46) -> 0 | AK46: 11.11 | AL46: 1.31 | AM46: 0.05 | AN46: 0 | AO46: 9.75 | AP46: 0 | AQ46: 0.6 | AR46: 0 | AS46: 0 | AT46: 92 | AU46: 49 | AV46: 1.067 | AW46: 1.028 | AZ46: 1 | BA46: 1 | BB46: 1 | BC46: 1 | BH46: 0 | BI46: 2 | BJ46: ТСН-2001.4 Доп. 68, Сб. 37, т. 18, поз. 4 | BM46: 84 | BN46: 0 | BO46: 4.37-18-4 | BP46: 1 | BQ46: 40 | BR46: 0 | BS46: 1 | BT46: 1 | BU46: 1 | BV46: 1 | BW46: 1 | BX46: 1 | BZ46: 92 | CA46: 49 | CE46: 1566 | CF46: 0 | CG46: 0 | CM46: 0 | CN46: Поправка: Гл.12.Прил.8.п.8. 3_12.00.01.11.001 Наименование: При наличии напряженных и стесненных условий производства работ (стесненность, сложность складирования и транспортной логистики и т.п.) для объектов, расположенных в пределах круговой магистральной системы улиц "Садовое кольцо" города Москвы Поправка: Гл.4.Прил.2.2.п.2.2.29_04.00.01.35.003 Наименование: При демонтаже оборудования, предназначенного в лом | CO46: 0 | CP46: =(P46+Q46+S46) -> 33.88 | CQ46: =ROUND((ROUND((AC46*AW46*1),2)*BC46),2) -> 0 | CR46: =(ROUND((ROUND(((((ET46*1.2)*0.3))*AV46*1),2)*BB46),2)+ROUND((ROUND(((AE46-(((EU46*1.2)*0.3)))*AV46*1),2)*BS46),2)) -> 0.02 | CS46: =(ROUND((ROUND(((((EU46*1.2)*0.3))*AV46*1),2)*BS46),2)+ROUND((ROUND(((AE46-(((EU46*1.2)*0.3)))*AV46*1),2)*BS46),2)) -> 0 | CT46: =ROUND((ROUND((AF46*AV46*1),2)*BA46),2) -> 3.75 | CU46: =AG46 -> 0 | CV46: =(AH46*AV46) -> 0.230472 | CW46: =AI46 -> 0 | CX46: =AJ46 -> 0 | CY46: =(ROUND((((S46+ROUND((ROUND(((((EU46*1.2)*0.3))*AV46*1),2)*BS46),2))*AT46)/100),2)+ROUND(((ROUND((ROUND(((AE46-(((EU46*1.2)*0.3)))*AV46*1),2)*BS46),2)*AT46)/100),2)) -> 31.01 | CZ46: =(ROUND((((S46+ROUND((ROUND(((((EU46*1.2)*0.3))*AV46*1),2)*BS46),2))*AU46)/100),2)+ROUND(((ROUND((ROUND(((AE46-(((EU46*1.2)*0.3)))*AV46*1),2)*BS46),2)*AU46)/100),2)) -> 16.52 | DB46: 37 | DD46: *1)*0 | DE46: *1,2)*0,3 | DF46: *1,2)*0,3 | DG46: *1,2)*0,3 | DI46: *1,2)*0,3 | DJ46: *1,2)*0,3 | DN46: 0 | DO46: 0 | DP46: 1 | DQ46: 1 | DU46: 1013 | DV46: 1 ШТ. | DW46: 1 ШТ. | DX46: 1 | EE46: 55393716 | EF46: 40 | EG46: Монтаж оборудования | EH46: 0 | EJ46: 2 | EK46: 84 | EL46: ТСН-2001.4-37. Оборудование общего назначения | EM46: ТСН-2001.4-37-1 | EO46: Поправка: Гл.12.Прил.8.п.8. 3_12.00.01.11.001 Поправка: Гл.4.Прил.2.2.п.2.2.29_04.00.01.35.003 | EQ46: 0 | ER46: 11.11 | ES46: 1.31 | ET46: 0.05 | EU46: 0 | EV46: 9.75 | EW46: 0.6 | EX46: 0 | EY46: 0 | FQ46: 0 | FR46: 0 | FS46: 2 | FX46: 92 | FY46: 49 | GD46: 1 | GF46: -1753372494 | GG46: 2 | GH46: 1 | GI46: 2 | GJ46: 0 | GK46: 0 | GL46: =ROUND(IF(AND(BH46=3,BI46=3,FS46<>0),P46,0),2) -> 0 | GM46: =ROUND(O46+X46+Y46,2)+GX46 -> 81.41 | GN46: =IF(OR(BI46=0,BI46=1),GM46-GX46,0) -> 0 | GO46: =IF(BI46=2,GM46-GX46,0) -> 81.41 | GP46: =IF(BI46=4,GM46-GX46,0) -> 0 | GR46: 0 | GS46: 3 | GT46: 0 | GV46: =ROUND((GT46),6) -> 0 | GW46: 1 | GX46: =ROUND(HC46*I46,2) -> 0 | HA46: 0 | HB46: 0 | HC46: =GV46*GW46 -> 0 | HS46: 0 | IK46: 0
A47: 17 | B47: 1 | C47: =ROW(SmtRes!A66) -> 66 | D47: =ROW(EtalonRes!A88) -> 88 | E47: 10 | F47: 4.37-18-4 | G47: Монтаж модуля установки пожаротушения тонкораспыленной водой объемом 13 л за подвесным потолком / демонтаж модулей газового пожаротушения | H47: 1 ШТ. | I47: =ROUND(3+2+2+2,9) -> 9 | J47: 0 | K47: =ROUND(3+2+2+2,9) -> 9 | O47: =ROUND(CP47,2) -> 1901.06 | P47: =ROUND((ROUND((AC47*AW47*I47),2)*BC47),2) -> 0 | Q47: =(ROUND((ROUND(((((ET47*1.2)*0.3))*AV47*I47),2)*BB47),2)+ROUND((ROUND(((AE47-(((EU47*1.2)*0.3)))*AV47*I47),2)*BS47),2)) -> 1.5 | R47: =(ROUND((ROUND(((((EU47*1.2)*0.3))*AV47*I47),2)*BS47),2)+ROUND((ROUND(((AE47-(((EU47*1.2)*0.3)))*AV47*I47),2)*BS47),2)) -> 0 | S47: =ROUND((ROUND((AF47*AV47*I47),2)*BA47),2) -> 1899.56 | T47: =ROUND(CU47*I47,2) -> 0 | U47: =CV47*I47 -> 2.074248 | V47: =CW47*I47 -> 0 | W47: =ROUND(CX47*I47,2) -> 0 | X47: =(ROUND((((S47+ROUND((ROUND(((((EU47*1.2)*0.3))*AV47*I47),2)*BS47),2))*AT47)/100),2)+ROUND(((ROUND((ROUND(((AE47-(((EU47*1.2)*0.3)))*AV47*I47),2)*BS47),2)*AT47)/100),2)) -> 1747.6 | Y47: =(ROUND((((S47+ROUND((ROUND(((((EU47*1.2)*0.3))*AV47*I47),2)*BS47),2))*AU47)/100),2)+ROUND(((ROUND((ROUND(((AE47-(((EU47*1.2)*0.3)))*AV47*I47),2)*BS47),2)*AU47)/100),2)) -> 930.78 | AA47: 55937298 | AB47: =ROUND((AC47+AD47+AF47),6) -> 3.528 | AC47: =ROUND((((ES47*1)*0)),6) -> 0 | AD47: =ROUND((((((ET47*1.2)*0.3))-(((EU47*1.2)*0.3)))+AE47),6) -> 0.018 | AE47: =ROUND((((EU47*1.2)*0.3)),6) -> 0 | AF47: =ROUND((((EV47*1.2)*0.3)),6) -> 3.51 | AG47: =ROUND((AP47),6) -> 0 | AH47: =(((EW47*1.2)*0.3)) -> 0.216 | AI47: =(((EX47*1.2)*0.3)) -> 0 | AJ47: =(AS47) -> 0 | AK47: 11.11 | AL47: 1.31 | AM47: 0.05 | AN47: 0 | AO47: 9.75 | AP47: 0 | AQ47: 0.6 | AR47: 0 | AS47: 0 | AT47: 92 | AU47: 49 | AV47: 1.067 | AW47: 1.028 | AZ47: 1 | BA47: 56.35 | BB47: 8.8 | BC47: 2.9 | BH47: 0 | BI47: 2 | BJ47: ТСН-2001.4 Доп. 68, Сб. 37, т. 18, поз. 4 | BM47: 84 | BN47: 0 | BO47: 4.37-18-4 | BP47: 1 | BQ47: 40 | BR47: 0 | BS47: 56.35 | BT47: 1 | BU47: 1 | BV47: 1 | BW47: 1 | BX47: 1 | BZ47: 92 | CA47: 49 | CE47: 1566 | CF47: 0 | CG47: 0 | CM47: 0 | CN47: Поправка: Гл.12.Прил.8.п.8. 3_12.00.01.11.001 Наименование: При наличии напряженных и стесненных условий производства работ (стесненность, сложность складирования и транспортной логистики и т.п.) для объектов, расположенных в пределах круговой магистральной системы улиц "Садовое кольцо" города Москвы Поправка: Гл.4.Прил.2.2.п.2.2.29_04.00.01.35.003 Наименование: При демонтаже оборудования, предназначенного в лом | CO47: 0 | CP47: =(P47+Q47+S47) -> 1901.06 | CQ47: =ROUND((ROUND((AC47*AW47*1),2)*BC47),2) -> 0 | CR47: =(ROUND((ROUND(((((ET47*1.2)*0.3))*AV47*1),2)*BB47),2)+ROUND((ROUND(((AE47-(((EU47*1.2)*0.3)))*AV47*1),2)*BS47),2)) -> 0.18 | CS47: =(ROUND((ROUND(((((EU47*1.2)*0.3))*AV47*1),2)*BS47),2)+ROUND((ROUND(((AE47-(((EU47*1.2)*0.3)))*AV47*1),2)*BS47),2)) -> 0 | CT47: =ROUND((ROUND((AF47*AV47*1),2)*BA47),2) -> 211.31 | CU47: =AG47 -> 0 | CV47: =(AH47*AV47) -> 0.230472 | CW47: =AI47 -> 0 | CX47: =AJ47 -> 0 | CY47: =(ROUND((((S47+ROUND((ROUND(((((EU47*1.2)*0.3))*AV47*1),2)*BS47),2))*AT47)/100),2)+ROUND(((ROUND((ROUND(((AE47-(((EU47*1.2)*0.3)))*AV47*1),2)*BS47),2)*AT47)/100),2)) -> 1747.6 | CZ47: =(ROUND((((S47+ROUND((ROUND(((((EU47*1.2)*0.3))*AV47*1),2)*BS47),2))*AU47)/100),2)+ROUND(((ROUND((ROUND(((AE47-(((EU47*1.2)*0.3)))*AV47*1),2)*BS47),2)*AU47)/100),2)) -> 930.78 | DB47: 39 | DD47: *1)*0 | DE47: *1,2)*0,3 | DF47: *1,2)*0,3 | DG47: *1,2)*0,3 | DI47: *1,2)*0,3 | DJ47: *1,2)*0,3 | DN47: 0 | DO47: 0 | DP47: 1 | DQ47: 1 | DU47: 1013 | DV47: 1 ШТ. | DW47: 1 ШТ. | DX47: 1 | EE47: 55393716 | EF47: 40 | EG47: Монтаж оборудования | EH47: 0 | EJ47: 2 | EK47: 84 | EL47: ТСН-2001.4-37. Оборудование общего назначения | EM47: ТСН-2001.4-37-1 | EO47: Поправка: Гл.12.Прил.8.п.8. 3_12.00.01.11.001 Поправка: Гл.4.Прил.2.2.п.2.2.29_04.00.01.35.003 | EQ47: 0 | ER47: 11.11 | ES47: 1.31 | ET47: 0.05 | EU47: 0 | EV47: 9.75 | EW47: 0.6 | EX47: 0 | EY47: 0 | FQ47: 0 | FR47: 0 | FS47: 2 | FX47: 92 | FY47: 49 | GD47: 1 | GF47: -1753372494 | GG47: 2 | GH47: 1 | GI47: 2 | GJ47: 0 | GK47: 0 | GL47: =ROUND(IF(AND(BH47=3,BI47=3,FS47<>0),P47,0),2) -> 0 | GM47: =ROUND(O47+X47+Y47,2)+GX47 -> 4579.44 | GN47: =IF(OR(BI47=0,BI47=1),GM47-GX47,0) -> 0 | GO47: =IF(BI47=2,GM47-GX47,0) -> 4579.44 | GP47: =IF(BI47=4,GM47-GX47,0) -> 0 | GR47: 0 | GS47: 3 | GT47: 0 | GV47: =ROUND((GT47),6) -> 0 | GW47: 1 | GX47: =ROUND(HC47*I47,2) -> 0 | HA47: 0 | HB47: 0 | HC47: =GV47*GW47 -> 0 | HS47: 0 | IK47: 0
A48: 17 | B48: 1 | C48: =ROW(SmtRes!A73) -> 73 | D48: =ROW(EtalonRes!A96) -> 96 | E48: 11 | F48: 3.9-74-1 | G48: Установка противопожарных металлических однопольных дверных блоков / демонтаж металлических дверных блоков | H48: 10 шт. | I48: =ROUND(4/10,9) -> 0.4 | J48: 0 | K48: =ROUND(4/10,9) -> 0.4 | O48: =ROUND(CP48,2) -> 235.71 | P48: =ROUND((ROUND((AC48*AW48*I48),2)*BC48),2) -> 117.09 | Q48: =(ROUND((ROUND((((((ET48*1.25)*1.2)*0.6))*AV48*I48),2)*BB48),2)+ROUND((ROUND(((AE48-((((EU48*1.25)*1.2)*0.6)))*AV48*I48),2)*BS48),2)) -> 44.5 | R48: =(ROUND((ROUND((((((EU48*1.25)*1.2)*0.6))*AV48*I48),2)*BS48),2)+ROUND((ROUND(((AE48-((((EU48*1.25)*1.2)*0.6)))*AV48*I48),2)*BS48),2)) -> 6.72 | S48: =ROUND((ROUND((AF48*AV48*I48),2)*BA48),2) -> 74.12 | T48: =ROUND(CU48*I48,2) -> 0 | U48: =CV48*I48 -> 6.6170647 | V48: =CW48*I48 -> 0 | W48: =ROUND(CX48*I48,2) -> 0 | X48: =(ROUND((((S48+ROUND((ROUND((((((EU48*1.25)*1.2)*0.6))*AV48*I48),2)*BS48),2))*AT48)/100),2)+ROUND(((ROUND((ROUND(((AE48-((((EU48*1.25)*1.2)*0.6)))*AV48*I48),2)*BS48),2)*AT48)/100),2)) -> 75.18 | Y48: =(ROUND((((S48+ROUND((ROUND((((((EU48*1.25)*1.2)*0.6))*AV48*I48),2)*BS48),2))*AU48)/100),2)+ROUND(((ROUND((ROUND(((AE48-((((EU48*1.25)*1.2)*0.6)))*AV48*I48),2)*BS48),2)*AU48)/100),2)) -> 50.12 | AA48: 55937296 | AB48: =ROUND((AC48+AD48+AF48),6) -> 565.56192 | AC48: =ROUND(((((ES48*1)*1)*0.6)),6) -> 292.728 | AD48: =ROUND(((((((ET48*1.25)*1.2)*0.6))-((((EU48*1.25)*1.2)*0.6)))+AE48),6) -> 102.357 | AE48: =ROUND(((((EU48*1.25)*1.2)*0.6)),6) -> 15.444 | AF48: =ROUND(((((EV48*1.15)*1.2)*0.6)),6) -> 170.47692 | AG48: =ROUND((AP48),6) -> 0 | AH48: =((((EW48*1.15)*1.2)*0.6)) -> 15.21864 | AI48: =((((EX48*1.25)*1.2)*0.6)) -> 0 | AJ48: =(AS48) -> 0 | AK48: 807.5 | AL48: 487.88 | AM48: 113.73 | AN48: 17.16 | AO48: 205.89 | AP48: 0 | AQ48: 18.38 | AR48: 0 | AS48: 0 | AT48: 93 | AU48: 62 | AV48: 1.087 | AW48: 1 | AZ48: 1 | BA48: 1 | BB48: 1 | BC48: 1 | BH48: 0 | BI48: 1 | BJ48: ТСН-2001.3 Доп. 79, Сб. 9, т. 74, поз. 1 | BM48: 13 | BN48: 0 | BO48: 3.9-74-1 | BP48: 1 | BQ48: 30 | BR48: 0 | BS48: 1 | BT48: 1 | BU48: 1 | BV48: 1 | BW48: 1 | BX48: 1 | BZ48: 93 | CA48: 62 | CE48: 1566 | CF48: 0 | CG48: 0 | CM48: 0 | CN48: Поправка: Гл.6.Прил.2.2.п.2.2.6_06.00.01.07.001 Наименование: При выполнении при капитальном ремонте и реконструкции работ, аналогичных технологическим процессам, характерным для нового строительства, и отсутствующих в сборниках на ремонтно-строительные работы ТСН-2001.6 Поправка: Гл.12.Прил.8.п.8. 3_12.00.01.11.001 Наименование: При наличии напряженных и стесненных условий производства работ (стесненность, сложность складирования и транспортной логистики и т.п.) для объектов, расположенных в пределах круговой магистральной системы улиц "Садовое кольцо" города Москвы Поправка: Гл.6.Прил.2.2.п.2.2.16_06.00.01.35.006 Наименование: При демонтаже металлических конструкций (в т.ч. к стоимости вспомогательных материалов) | CO48: 0 | CP48: =(P48+Q48+S48) -> 235.71 | CQ48: =ROUND((ROUND((AC48*AW48*1),2)*BC48),2) -> 292.73 | CR48: =(ROUND((ROUND((((((ET48*1.25)*1.2)*0.6))*AV48*1),2)*BB48),2)+ROUND((ROUND(((AE48-((((EU48*1.25)*1.2)*0.6)))*AV48*1),2)*BS48),2)) -> 111.26 | CS48: =(ROUND((ROUND((((((EU48*1.25)*1.2)*0.6))*AV48*1),2)*BS48),2)+ROUND((ROUND(((AE48-((((EU48*1.25)*1.2)*0.6)))*AV48*1),2)*BS48),2)) -> 16.79 | CT48: =ROUND((ROUND((AF48*AV48*1),2)*BA48),2) -> 185.31 | CU48: =AG48 -> 0 | CV48: =(AH48*AV48) -> 16.542662 | CW48: =AI48 -> 0 | CX48: =AJ48 -> 0 | CY48: =(ROUND((((S48+ROUND((ROUND((((((EU48*1.25)*1.2)*0.6))*AV48*1),2)*BS48),2))*AT48)/100),2)+ROUND(((ROUND((ROUND(((AE48-((((EU48*1.25)*1.2)*0.6)))*AV48*1),2)*BS48),2)*AT48)/100),2)) -> 84.55 | CZ48: =(ROUND((((S48+ROUND((ROUND((((((EU48*1.25)*1.2)*0.6))*AV48*1),2)*BS48),2))*AU48)/100),2)+ROUND(((ROUND((ROUND(((AE48-((((EU48*1.25)*1.2)*0.6)))*AV48*1),2)*BS48),2)*AU48)/100),2)) -> 56.36 | DB48: 41 | DD48: *1)*1)*0,6 | DE48: *1,25)*1,2)*0,6 | DF48: *1,25)*1,2)*0,6 | DG48: *1,15)*1,2)*0,6 | DI48: *1,15)*1,2)*0,6 | DJ48: *1,25)*1,2)*0,6 | DN48: 0 | DO48: 0 | DP48: 1 | DQ48: 1 | DU48: 1010 | DV48: 10 шт. | DW48: 10 шт. | DX48: 10 | EE48: 55393642 | EF48: 30 | EG48: Строительные работы | EH48: 0 | EJ48: 1 | EK48: 13 | EL48: ТСН-2001.3-9. Металлические конструкции | EM48: ТСН-2001.3-9-1 | EO48: Поправка: Гл.6.Прил.2.2.п.2.2.6_06.00.01.07.001 Поправка: Гл.12.Прил.8.п.8. 3_12.00.01.11.001 Поправка: Гл.6.Прил.2.2.п.2.2.16_06.00.01.35.006 | EQ48: 0 | ER48: 807.5 | ES48: 487.88 | ET48: 113.73 | EU48: 17.16 | EV48: 205.89 | EW48: 18.38 | EX48: 0 | EY48: 0 | FQ48: 0 | FR48: 0 | FS48: 0 | FX48: 93 | FY48: 62 | GD48: 1 | GF48: -39335557 | GG48: 2 | GH48: 1 | GI48: 2 | GJ48: 0 | GK48: 0 | GL48: =ROUND(IF(AND(BH48=3,BI48=3,FS48<>0),P48,0),2) -> 0 | GM48: =ROUND(O48+X48+Y48,2)+GX48 -> 361.01 | GN48: =IF(OR(BI48=0,BI48=1),GM48-GX48,0) -> 361.01 | GO48: =IF(BI48=2,GM48-GX48,0) -> 0 | GP48: =IF(BI48=4,GM48-GX48,0) -> 0 | GR48: 0 | GS48: 3 | GT48: 0 | GV48: =ROUND((GT48),6) -> 0 | GW48: 1 | GX48: =ROUND(HC48*I48,2) -> 0 | HA48: 0 | HB48: 0 | HC48: =GV48*GW48 -> 0 | HS48: 0 | IK48: 0
A49: 17 | B49: 1 | C49: =ROW(SmtRes!A80) -> 80 | D49: =ROW(EtalonRes!A104) -> 104 | E49: 11 | F49: 3.9-74-1 | G49: Установка противопожарных металлических однопольных дверных блоков / демонтаж металлических дверных блоков | H49: 10 шт. | I49: =ROUND(4/10,9) -> 0.4 | J49: 0 | K49: =ROUND(4/10,9) -> 0.4 | O49: =ROUND(CP49,2) -> 5683.43 | P49: =ROUND((ROUND((AC49*AW49*I49),2)*BC49),2) -> 749.38 | Q49: =(ROUND((ROUND((((((ET49*1.25)*1.2)*0.6))*AV49*I49),2)*BB49),2)+ROUND((ROUND(((AE49-((((EU49*1.25)*1.2)*0.6)))*AV49*I49),2)*BS49),2)) -> 757.39 | R49: =(ROUND((ROUND((((((EU49*1.25)*1.2)*0.6))*AV49*I49),2)*BS49),2)+ROUND((ROUND(((AE49-((((EU49*1.25)*1.2)*0.6)))*AV49*I49),2)*BS49),2)) -> 378.67 | S49: =ROUND((ROUND((AF49*AV49*I49),2)*BA49),2) -> 4176.66 | T49: =ROUND(CU49*I49,2) -> 0 | U49: =CV49*I49 -> 6.6170647 | V49: =CW49*I49 -> 0 | W49: =ROUND(CX49*I49,2) -> 0 | X49: =(ROUND((((S49+ROUND((ROUND((((((EU49*1.25)*1.2)*0.6))*AV49*I49),2)*BS49),2))*AT49)/100),2)+ROUND(((ROUND((ROUND(((AE49-((((EU49*1.25)*1.2)*0.6)))*AV49*I49),2)*BS49),2)*AT49)/100),2)) -> 4236.46 | Y49: =(ROUND((((S49+ROUND((ROUND((((((EU49*1.25)*1.2)*0.6))*AV49*I49),2)*BS49),2))*AU49)/100),2)+ROUND(((ROUND((ROUND(((AE49-((((EU49*1.25)*1.2)*0.6)))*AV49*I49),2)*BS49),2)*AU49)/100),2)) -> 2824.3 | AA49: 55937298 | AB49: =ROUND((AC49+AD49+AF49),6) -> 565.56192 | AC49: =ROUND(((((ES49*1)*1)*0.6)),6) -> 292.728 | AD49: =ROUND(((((((ET49*1.25)*1.2)*0.6))-((((EU49*1.25)*1.2)*0.6)))+AE49),6) -> 102.357 | AE49: =ROUND(((((EU49*1.25)*1.2)*0.6)),6) -> 15.444 | AF49: =ROUND(((((EV49*1.15)*1.2)*0.6)),6) -> 170.47692 | AG49: =ROUND((AP49),6) -> 0 | AH49: =((((EW49*1.15)*1.2)*0.6)) -> 15.21864 | AI49: =((((EX49*1.25)*1.2)*0.6)) -> 0 | AJ49: =(AS49) -> 0 | AK49: 807.5 | AL49: 487.88 | AM49: 113.73 | AN49: 17.16 | AO49: 205.89 | AP49: 0 | AQ49: 18.38 | AR49: 0 | AS49: 0 | AT49: 93 | AU49: 62 | AV49: 1.087 | AW49: 1 | AZ49: 1 | BA49: 56.35 | BB49: 17.02 | BC49: 6.4 | BH49: 0 | BI49: 1 | BJ49: ТСН-2001.3 Доп. 79, Сб. 9, т. 74, поз. 1 | BM49: 13 | BN49: 0 | BO49: 3.9-74-1 | BP49: 1 | BQ49: 30 | BR49: 0 | BS49: 56.35 | BT49: 1 | BU49: 1 | BV49: 1 | BW49: 1 | BX49: 1 | BZ49: 93 | CA49: 62 | CE49: 1566 | CF49: 0 | CG49: 0 | CM49: 0 | CN49: Поправка: Гл.6.Прил.2.2.п.2.2.6_06.00.01.07.001 Наименование: При выполнении при капитальном ремонте и реконструкции работ, аналогичных технологическим процессам, характерным для нового строительства, и отсутствующих в сборниках на ремонтно-строительные работы ТСН-2001.6 Поправка: Гл.12.Прил.8.п.8. 3_12.00.01.11.001 Наименование: При наличии напряженных и стесненных условий производства работ (стесненность, сложность складирования и транспортной логистики и т.п.) для объектов, расположенных в пределах круговой магистральной системы улиц "Садовое кольцо" города Москвы Поправка: Гл.6.Прил.2.2.п.2.2.16_06.00.01.35.006 Наименование: При демонтаже металлических конструкций (в т.ч. к стоимости вспомогательных материалов) | CO49: 0 | CP49: =(P49+Q49+S49) -> 5683.43 | CQ49: =ROUND((ROUND((AC49*AW49*1),2)*BC49),2) -> 1873.47 | CR49: =(ROUND((ROUND((((((ET49*1.25)*1.2)*0.6))*AV49*1),2)*BB49),2)+ROUND((ROUND(((AE49-((((EU49*1.25)*1.2)*0.6)))*AV49*1),2)*BS49),2)) -> 1893.65 | CS49: =(ROUND((ROUND((((((EU49*1.25)*1.2)*0.6))*AV49*1),2)*BS49),2)+ROUND((ROUND(((AE49-((((EU49*1.25)*1.2)*0.6)))*AV49*1),2)*BS49),2)) -> 946.12 | CT49: =ROUND((ROUND((AF49*AV49*1),2)*BA49),2) -> 10442.22 | CU49: =AG49 -> 0 | CV49: =(AH49*AV49) -> 16.542662 | CW49: =AI49 -> 0 | CX49: =AJ49 -> 0 | CY49: =(ROUND((((S49+ROUND((ROUND((((((EU49*1.25)*1.2)*0.6))*AV49*1),2)*BS49),2))*AT49)/100),2)+ROUND(((ROUND((ROUND(((AE49-((((EU49*1.25)*1.2)*0.6)))*AV49*1),2)*BS49),2)*AT49)/100),2)) -> 4764.19 | CZ49: =(ROUND((((S49+ROUND((ROUND((((((EU49*1.25)*1.2)*0.6))*AV49*1),2)*BS49),2))*AU49)/100),2)+ROUND(((ROUND((ROUND(((AE49-((((EU49*1.25)*1.2)*0.6)))*AV49*1),2)*BS49),2)*AU49)/100),2)) -> 3176.12 | DB49: 44 | DD49: *1)*1)*0,6 | DE49: *1,25)*1,2)*0,6 | DF49: *1,25)*1,2)*0,6 | DG49: *1,15)*1,2)*0,6 | DI49: *1,15)*1,2)*0,6 | DJ49: *1,25)*1,2)*0,6 | DN49: 0 | DO49: 0 | DP49: 1 | DQ49: 1 | DU49: 1010 | DV49: 10 шт. | DW49: 10 шт. | DX49: 10 | EE49: 55393642 | EF49: 30 | EG49: Строительные работы | EH49: 0 | EJ49: 1 | EK49: 13 | EL49: ТСН-2001.3-9. Металлические конструкции | EM49: ТСН-2001.3-9-1 | EO49: Поправка: Гл.6.Прил.2.2.п.2.2.6_06.00.01.07.001 Поправка: Гл.12.Прил.8.п.8. 3_12.00.01.11.001 Поправка: Гл.6.Прил.2.2.п.2.2.16_06.00.01.35.006 | EQ49: 0 | ER49: 807.5 | ES49: 487.88 | ET49: 113.73 | EU49: 17.16 | EV49: 205.89 | EW49: 18.38 | EX49: 0 | EY49: 0 | FQ49: 0 | FR49: 0 | FS49: 0 | FX49: 93 | FY49: 62 | GD49: 1 | GF49: -39335557 | GG49: 2 | GH49: 1 | GI49: 2 | GJ49: 0 | GK49: 0 | GL49: =ROUND(IF(AND(BH49=3,BI49=3,FS49<>0),P49,0),2) -> 0 | GM49: =ROUND(O49+X49+Y49,2)+GX49 -> 12744.19 | GN49: =IF(OR(BI49=0,BI49=1),GM49-GX49,0) -> 12744.19 | GO49: =IF(BI49=2,GM49-GX49,0) -> 0 | GP49: =IF(BI49=4,GM49-GX49,0) -> 0 | GR49: 0 | GS49: 3 | GT49: 0 | GV49: =ROUND((GT49),6) -> 0 | GW49: 1 | GX49: =ROUND(HC49*I49,2) -> 0 | HA49: 0 | HB49: 0 | HC49: =GV49*GW49 -> 0 | HS49: 0 | IK49: 0
A50: 17 | B50: 1 | C50: =ROW(SmtRes!A81) -> 81 | D50: =ROW(EtalonRes!A106) -> 106 | E50: 12 | F50: 4.10-1-12 | G50: Установка рамки со штифтами на винтах в нарезных отверстиях / демонтаж стыковочных узлов | H50: 1 рамка | I50: =ROUND(4*2,9) -> 8 | J50: 0 | K50: =ROUND(4*2,9) -> 8 | O50: =ROUND(CP50,2) -> 2.35 | P50: =ROUND((ROUND((AC50*AW50*I50),2)*BC50),2) -> 0 | Q50: =(ROUND((ROUND(((((ET50*1.2)*0.3))*AV50*I50),2)*BB50),2)+ROUND((ROUND(((AE50-(((EU50*1.2)*0.3)))*AV50*I50),2)*BS50),2)) -> 0 | R50: =(ROUND((ROUND(((((EU50*1.2)*0.3))*AV50*I50),2)*BS50),2)+ROUND((ROUND(((AE50-(((EU50*1.2)*0.3)))*AV50*I50),2)*BS50),2)) -> 0 | S50: =ROUND((ROUND((AF50*AV50*I50),2)*BA50),2) -> 2.35 | T50: =ROUND(CU50*I50,2) -> 0 | U50: =CV50*I50 -> 0.2110752 | V50: =CW50*I50 -> 0 | W50: =ROUND(CX50*I50,2) -> 0 | X50: =(ROUND((((S50+ROUND((ROUND(((((EU50*1.2)*0.3))*AV50*I50),2)*BS50),2))*AT50)/100),2)+ROUND(((ROUND((ROUND(((AE50-(((EU50*1.2)*0.3)))*AV50*I50),2)*BS50),2)*AT50)/100),2)) -> 2.12 | Y50: =(ROUND((((S50+ROUND((ROUND(((((EU50*1.2)*0.3))*AV50*I50),2)*BS50),2))*AU50)/100),2)+ROUND(((ROUND((ROUND(((AE50-(((EU50*1.2)*0.3)))*AV50*I50),2)*BS50),2)*AU50)/100),2)) -> 1.08 | AA50: 55937296 | AB50: =ROUND((AC50+AD50+AF50),6) -> 0.2808 | AC50: =ROUND((((ES50*1)*0)),6) -> 0 | AD50: =ROUND((((((ET50*1.2)*0.3))-(((EU50*1.2)*0.3)))+AE50),6) -> 0 | AE50: =ROUND((((EU50*1.2)*0.3)),6) -> 0 | AF50: =ROUND((((EV50*1.2)*0.3)),6) -> 0.2808 | AG50: =ROUND((AP50),6) -> 0 | AH50: =(((EW50*1.2)*0.3)) -> 0.0252 | AI50: =(((EX50*1.2)*0.3)) -> 0 | AJ50: =(AS50) -> 0 | AK50: 0.78 | AL50: 0 | AM50: 0 | AN50: 0 | AO50: 0.78 | AP50: 0 | AQ50: 0.07 | AR50: 0 | AS50: 0 | AT50: 90 | AU50: 46 | AV50: 1.047 | AW50: 1 | AZ50: 1 | BA50: 1 | BB50: 1 | BC50: 1 | BH50: 0 | BI50: 2 | BJ50: ТСН-2001.4 Доп. 67, Сб. 10, т. 1, поз. 12 | BM50: 68 | BN50: 0 | BO50: 4.10-1-12 | BP50: 1 | BQ50: 40 | BR50: 0 | BS50: 1 | BT50: 1 | BU50: 1 | BV50: 1 | BW50: 1 | BX50: 1 | BZ50: 90 | CA50: 46 | CE50: 1566 | CF50: 0 | CG50: 0 | CM50: 0 | CN50: Поправка: Гл.12.Прил.8.п.8. 3_12.00.01.11.001 Наименование: При наличии напряженных и стесненных условий производства работ (стесненность, сложность складирования и транспортной логистики и т.п.) для объектов, расположенных в пределах круговой магистральной системы улиц "Садовое кольцо" города Москвы Поправка: Гл.4.Прил.2.2.п.2.2.29_04.00.01.35.003 Наименование: При демонтаже оборудования, предназначенного в лом | CO50: 0 | CP50: =(P50+Q50+S50) -> 2.35 | CQ50: =ROUND((ROUND((AC50*AW50*1),2)*BC50),2) -> 0 | CR50: =(ROUND((ROUND(((((ET50*1.2)*0.3))*AV50*1),2)*BB50),2)+ROUND((ROUND(((AE50-(((EU50*1.2)*0.3)))*AV50*1),2)*BS50),2)) -> 0 | CS50: =(ROUND((ROUND(((((EU50*1.2)*0.3))*AV50*1),2)*BS50),2)+ROUND((ROUND(((AE50-(((EU50*1.2)*0.3)))*AV50*1),2)*BS50),2)) -> 0 | CT50: =ROUND((ROUND((AF50*AV50*1),2)*BA50),2) -> 0.29 | CU50: =AG50 -> 0 | CV50: =(AH50*AV50) -> 0.0263844 | CW50: =AI50 -> 0 | CX50: =AJ50 -> 0 | CY50: =(ROUND((((S50+ROUND((ROUND(((((EU50*1.2)*0.3))*AV50*1),2)*BS50),2))*AT50)/100),2)+ROUND(((ROUND((ROUND(((AE50-(((EU50*1.2)*0.3)))*AV50*1),2)*BS50),2)*AT50)/100),2)) -> 2.12 | CZ50: =(ROUND((((S50+ROUND((ROUND(((((EU50*1.2)*0.3))*AV50*1),2)*BS50),2))*AU50)/100),2)+ROUND(((ROUND((ROUND(((AE50-(((EU50*1.2)*0.3)))*AV50*1),2)*BS50),2)*AU50)/100),2)) -> 1.08 | DB50: 47 | DD50: *1)*0 | DE50: *1,2)*0,3 | DF50: *1,2)*0,3 | DG50: *1,2)*0,3 | DI50: *1,2)*0,3 | DJ50: *1,2)*0,3 | DN50: 0 | DO50: 0 | DP50: 1 | DQ50: 1 | DU50: 1013 | DV50: 1 рамка | DW50: 1 рамка | DX50: 1 | EE50: 55393700 | EF50: 40 | EG50: Монтаж оборудования | EH50: 0 | EJ50: 2 | EK50: 68 | EL50: ТСН-2001.4-10. Прокладка и монтаж сетей связи | EM50: ТСН-2001.4-10-1 | EO50: Поправка: Гл.12.Прил.8.п.8. 3_12.00.01.11.001 Поправка: Гл.4.Прил.2.2.п.2.2.29_04.00.01.35.003 | EQ50: 0 | ER50: 0.78 | ES50: 0 | ET50: 0 | EU50: 0 | EV50: 0.78 | EW50: 0.07 | EX50: 0 | EY50: 0 | FQ50: 0 | FR50: 0 | FS50: 0 | FX50: 90 | FY50: 46 | GD50: 1 | GF50: 1577802063 | GG50: 2 | GH50: 1 | GI50: 2 | GJ50: 0 | GK50: 0 | GL50: =ROUND(IF(AND(BH50=3,BI50=3,FS50<>0),P50,0),2) -> 0 | GM50: =ROUND(O50+X50+Y50,2)+GX50 -> 5.55 | GN50: =IF(OR(BI50=0,BI50=1),GM50-GX50,0) -> 0 | GO50: =IF(BI50=2,GM50-GX50,0) -> 5.55 | GP50: =IF(BI50=4,GM50-GX50,0) -> 0 | GR50: 0 | GS50: 3 | GT50: 0 | GV50: =ROUND((GT50),6) -> 0 | GW50: 1 | GX50: =ROUND(HC50*I50,2) -> 0 | HA50: 0 | HB50: 0 | HC50: =GV50*GW50 -> 0 | HS50: 0 | IK50: 0
A51: 17 | B51: 1 | C51: =ROW(SmtRes!A82) -> 82 | D51: =ROW(EtalonRes!A108) -> 108 | E51: 12 | F51: 4.10-1-12 | G51: Установка рамки со штифтами на винтах в нарезных отверстиях / демонтаж стыковочных узлов | H51: 1 рамка | I51: =ROUND(4*2,9) -> 8 | J51: 0 | K51: =ROUND(4*2,9) -> 8 | O51: =ROUND(CP51,2) -> 132.42 | P51: =ROUND((ROUND((AC51*AW51*I51),2)*BC51),2) -> 0 | Q51: =(ROUND((ROUND(((((ET51*1.2)*0.3))*AV51*I51),2)*BB51),2)+ROUND((ROUND(((AE51-(((EU51*1.2)*0.3)))*AV51*I51),2)*BS51),2)) -> 0 | R51: =(ROUND((ROUND(((((EU51*1.2)*0.3))*AV51*I51),2)*BS51),2)+ROUND((ROUND(((AE51-(((EU51*1.2)*0.3)))*AV51*I51),2)*BS51),2)) -> 0 | S51: =ROUND((ROUND((AF51*AV51*I51),2)*BA51),2) -> 132.42 | T51: =ROUND(CU51*I51,2) -> 0 | U51: =CV51*I51 -> 0.2110752 | V51: =CW51*I51 -> 0 | W51: =ROUND(CX51*I51,2) -> 0 | X51: =(ROUND((((S51+ROUND((ROUND(((((EU51*1.2)*0.3))*AV51*I51),2)*BS51),2))*AT51)/100),2)+ROUND(((ROUND((ROUND(((AE51-(((EU51*1.2)*0.3)))*AV51*I51),2)*BS51),2)*AT51)/100),2)) -> 119.18 | Y51: =(ROUND((((S51+ROUND((ROUND(((((EU51*1.2)*0.3))*AV51*I51),2)*BS51),2))*AU51)/100),2)+ROUND(((ROUND((ROUND(((AE51-(((EU51*1.2)*0.3)))*AV51*I51),2)*BS51),2)*AU51)/100),2)) -> 60.91 | AA51: 55937298 | AB51: =ROUND((AC51+AD51+AF51),6) -> 0.2808 | AC51: =ROUND((((ES51*1)*0)),6) -> 0 | AD51: =ROUND((((((ET51*1.2)*0.3))-(((EU51*1.2)*0.3)))+AE51),6) -> 0 | AE51: =ROUND((((EU51*1.2)*0.3)),6) -> 0 | AF51: =ROUND((((EV51*1.2)*0.3)),6) -> 0.2808 | AG51: =ROUND((AP51),6) -> 0 | AH51: =(((EW51*1.2)*0.3)) -> 0.0252 | AI51: =(((EX51*1.2)*0.3)) -> 0 | AJ51: =(AS51) -> 0 | AK51: 0.78 | AL51: 0 | AM51: 0 | AN51: 0 | AO51: 0.78 | AP51: 0 | AQ51: 0.07 | AR51: 0 | AS51: 0 | AT51: 90 | AU51: 46 | AV51: 1.047 | AW51: 1 | AZ51: 1 | BA51: 56.35 | BB51: 1 | BC51: 1 | BH51: 0 | BI51: 2 | BJ51: ТСН-2001.4 Доп. 67, Сб. 10, т. 1, поз. 12 | BM51: 68 | BN51: 0 | BO51: 4.10-1-12 | BP51: 1 | BQ51: 40 | BR51: 0 | BS51: 56.35 | BT51: 1 | BU51: 1 | BV51: 1 | BW51: 1 | BX51: 1 | BZ51: 90 | CA51: 46 | CE51: 1566 | CF51: 0 | CG51: 0 | CM51: 0 | CN51: Поправка: Гл.12.Прил.8.п.8. 3_12.00.01.11.001 Наименование: При наличии напряженных и стесненных условий производства работ (стесненность, сложность складирования и транспортной логистики и т.п.) для объектов, расположенных в пределах круговой магистральной системы улиц "Садовое кольцо" города Москвы Поправка: Гл.4.Прил.2.2.п.2.2.29_04.00.01.35.003 Наименование: При демонтаже оборудования, предназначенного в лом | CO51: 0 | CP51: =(P51+Q51+S51) -> 132.42 | CQ51: =ROUND((ROUND((AC51*AW51*1),2)*BC51),2) -> 0 | CR51: =(ROUND((ROUND(((((ET51*1.2)*0.3))*AV51*1),2)*BB51),2)+ROUND((ROUND(((AE51-(((EU51*1.2)*0.3)))*AV51*1),2)*BS51),2)) -> 0 | CS51: =(ROUND((ROUND(((((EU51*1.2)*0.3))*AV51*1),2)*BS51),2)+ROUND((ROUND(((AE51-(((EU51*1.2)*0.3)))*AV51*1),2)*BS51),2)) -> 0 | CT51: =ROUND((ROUND((AF51*AV51*1),2)*BA51),2) -> 16.34 | CU51: =AG51 -> 0 | CV51: =(AH51*AV51) -> 0.0263844 | CW51: =AI51 -> 0 | CX51: =AJ51 -> 0 | CY51: =(ROUND((((S51+ROUND((ROUND(((((EU51*1.2)*0.3))*AV51*1),2)*BS51),2))*AT51)/100),2)+ROUND(((ROUND((ROUND(((AE51-(((EU51*1.2)*0.3)))*AV51*1),2)*BS51),2)*AT51)/100),2)) -> 119.18 | CZ51: =(ROUND((((S51+ROUND((ROUND(((((EU51*1.2)*0.3))*AV51*1),2)*BS51),2))*AU51)/100),2)+ROUND(((ROUND((ROUND(((AE51-(((EU51*1.2)*0.3)))*AV51*1),2)*BS51),2)*AU51)/100),2)) -> 60.91 | DB51: 49 | DD51: *1)*0 | DE51: *1,2)*0,3 | DF51: *1,2)*0,3 | DG51: *1,2)*0,3 | DI51: *1,2)*0,3 | DJ51: *1,2)*0,3 | DN51: 0 | DO51: 0 | DP51: 1 | DQ51: 1 | DU51: 1013 | DV51: 1 рамка | DW51: 1 рамка | DX51: 1 | EE51: 55393700 | EF51: 40 | EG51: Монтаж оборудования | EH51: 0 | EJ51: 2 | EK51: 68 | EL51: ТСН-2001.4-10. Прокладка и монтаж сетей связи | EM51: ТСН-2001.4-10-1 | EO51: Поправка: Гл.12.Прил.8.п.8. 3_12.00.01.11.001 Поправка: Гл.4.Прил.2.2.п.2.2.29_04.00.01.35.003 | EQ51: 0 | ER51: 0.78 | ES51: 0 | ET51: 0 | EU51: 0 | EV51: 0.78 | EW51: 0.07 | EX51: 0 | EY51: 0 | FQ51: 0 | FR51: 0 | FS51: 0 | FX51: 90 | FY51: 46 | GD51: 1 | GF51: 1577802063 | GG51: 2 | GH51: 1 | GI51: 2 | GJ51: 0 | GK51: 0 | GL51: =ROUND(IF(AND(BH51=3,BI51=3,FS51<>0),P51,0),2) -> 0 | GM51: =ROUND(O51+X51+Y51,2)+GX51 -> 312.51 | GN51: =IF(OR(BI51=0,BI51=1),GM51-GX51,0) -> 0 | GO51: =IF(BI51=2,GM51-GX51,0) -> 312.51 | GP51: =IF(BI51=4,GM51-GX51,0) -> 0 | GR51: 0 | GS51: 3 | GT51: 0 | GV51: =ROUND((GT51),6) -> 0 | GW51: 1 | GX51: =ROUND(HC51*I51,2) -> 0 | HA51: 0 | HB51: 0 | HC51: =GV51*GW51 -> 0 | HS51: 0 | IK51: 0
A52: 17 | B52: 1 | C52: =ROW(SmtRes!A88) -> 88 | D52: =ROW(EtalonRes!A115) -> 115 | E52: 13 | F52: 3.70-434-1 | G52: Установка дверного доводчика или синхронизатора к металлическим дверям / демонтаж дверного доводчика | H52: 100 шт. | I52: =ROUND(4/100,9) -> 0.04 | J52: 0 | K52: =ROUND(4/100,9) -> 0.04 | O52: =ROUND(CP52,2) -> 10.86 | P52: =ROUND((ROUND((AC52*AW52*I52),2)*BC52),2) -> 3.18 | Q52: =(ROUND((ROUND((((((ET52*1.25)*1.2)*0.6))*AV52*I52),2)*BB52),2)+ROUND((ROUND(((AE52-((((EU52*1.25)*1.2)*0.6)))*AV52*I52),2)*BS52),2)) -> 0.73 | R52: =(ROUND((ROUND((((((EU52*1.25)*1.2)*0.6))*AV52*I52),2)*BS52),2)+ROUND((ROUND(((AE52-((((EU52*1.25)*1.2)*0.6)))*AV52*I52),2)*BS52),2)) -> 0.09 | S52: =ROUND((ROUND((AF52*AV52*I52),2)*BA52),2) -> 6.95 | T52: =ROUND(CU52*I52,2) -> 0 | U52: =CV52*I52 -> 0.41653666 | V52: =CW52*I52 -> 0 | W52: =ROUND(CX52*I52,2) -> 0 | X52: =(ROUND((((S52+ROUND((ROUND((((((EU52*1.25)*1.2)*0.6))*AV52*I52),2)*BS52),2))*AT52)/100),2)+ROUND(((ROUND((ROUND(((AE52-((((EU52*1.25)*1.2)*0.6)))*AV52*I52),2)*BS52),2)*AT52)/100),2)) -> 6.55 | Y52: =(ROUND((((S52+ROUND((ROUND((((((EU52*1.25)*1.2)*0.6))*AV52*I52),2)*BS52),2))*AU52)/100),2)+ROUND(((ROUND((ROUND(((AE52-((((EU52*1.25)*1.2)*0.6)))*AV52*I52),2)*BS52),2)*AU52)/100),2)) -> 4.36 | AA52: 55937296 | AB52: =ROUND((AC52+AD52+AF52),6) -> 256.13664 | AC52: =ROUND(((((ES52*1)*1)*0.6)),6) -> 79.404 | AD52: =ROUND(((((((ET52*1.25)*1.2)*0.6))-((((EU52*1.25)*1.2)*0.6)))+AE52),6) -> 16.821 | AE52: =ROUND(((((EU52*1.25)*1.2)*0.6)),6) -> 2.043 | AF52: =ROUND(((((EV52*1.15)*1.2)*0.6)),6) -> 159.91164 | AG52: =ROUND((AP52),6) -> 0 | AH52: =((((EW52*1.15)*1.2)*0.6)) -> 9.57996 | AI52: =((((EX52*1.25)*1.2)*0.6)) -> 0 | AJ52: =(AS52) -> 0 | AK52: 344.16 | AL52: 132.34 | AM52: 18.69 | AN52: 2.27 | AO52: 193.13 | AP52: 0 | AQ52: 11.57 | AR52: 0 | AS52: 0 | AT52: 93 | AU52: 62 | AV52: 1.087 | AW52: 1 | AZ52: 1 | BA52: 1 | BB52: 1 | BC52: 1 | BH52: 0 | BI52: 1 | BJ52: ТСН-2001.3 Доп. 81, Сб. 70, т. 434, поз. 1 | BM52: 55 | BN52: 0 | BO52: 3.70-434-1 | BP52: 1 | BQ52: 30 | BR52: 0 | BS52: 1 | BT52: 1 | BU52: 1 | BV52: 1 | BW52: 1 | BX52: 1 | BZ52: 93 | CA52: 62 | CE52: 1566 | CF52: 0 | CG52: 0 | CM52: 0 | CN52: Поправка: Гл.6.Прил.2.2.п.2.2.6_06.00.01.07.001 Наименование: При выполнении при капитальном ремонте и реконструкции работ, аналогичных технологическим процессам, характерным для нового строительства, и отсутствующих в сборниках на ремонтно-строительные работы ТСН-2001.6 Поправка: Гл.12.Прил.8.п.8. 3_12.00.01.11.001 Наименование: При наличии напряженных и стесненных условий производства работ (стесненность, сложность складирования и транспортной логистики и т.п.) для объектов, расположенных в пределах круговой магистральной системы улиц "Садовое кольцо" города Москвы Поправка: Гл.6.Прил.2.2.п.2.2.16_06.00.01.35.006 Наименование: При демонтаже металлических конструкций (в т.ч. к стоимости вспомогательных материалов) | CO52: 0 | CP52: =(P52+Q52+S52) -> 10.86 | CQ52: =ROUND((ROUND((AC52*AW52*1),2)*BC52),2) -> 79.4 | CR52: =(ROUND((ROUND((((((ET52*1.25)*1.2)*0.6))*AV52*1),2)*BB52),2)+ROUND((ROUND(((AE52-((((EU52*1.25)*1.2)*0.6)))*AV52*1),2)*BS52),2)) -> 18.28 | CS52: =(ROUND((ROUND((((((EU52*1.25)*1.2)*0.6))*AV52*1),2)*BS52),2)+ROUND((ROUND(((AE52-((((EU52*1.25)*1.2)*0.6)))*AV52*1),2)*BS52),2)) -> 2.22 | CT52: =ROUND((ROUND((AF52*AV52*1),2)*BA52),2) -> 173.82 | CU52: =AG52 -> 0 | CV52: =(AH52*AV52) -> 10.413417 | CW52: =AI52 -> 0 | CX52: =AJ52 -> 0 | CY52: =(ROUND((((S52+ROUND((ROUND((((((EU52*1.25)*1.2)*0.6))*AV52*1),2)*BS52),2))*AT52)/100),2)+ROUND(((ROUND((ROUND(((AE52-((((EU52*1.25)*1.2)*0.6)))*AV52*1),2)*BS52),2)*AT52)/100),2)) -> 8.53 | CZ52: =(ROUND((((S52+ROUND((ROUND((((((EU52*1.25)*1.2)*0.6))*AV52*1),2)*BS52),2))*AU52)/100),2)+ROUND(((ROUND((ROUND(((AE52-((((EU52*1.25)*1.2)*0.6)))*AV52*1),2)*BS52),2)*AU52)/100),2)) -> 5.69 | DB52: 51 | DD52: *1)*1)*0,6 | DE52: *1,25)*1,2)*0,6 | DF52: *1,25)*1,2)*0,6 | DG52: *1,15)*1,2)*0,6 | DI52: *1,15)*1,2)*0,6 | DJ52: *1,25)*1,2)*0,6 | DN52: 0 | DO52: 0 | DP52: 1 | DQ52: 1 | DU52: 1010 | DV52: 100 шт. | DW52: 100 шт. | DX52: 100 | EE52: 55393688 | EF52: 30 | EG52: Строительные работы | EH52: 0 | EJ52: 1 | EK52: 55 | EL52: ТСН-2001.3-70. Металлические конструкции | EM52: ТСН-2001.3-70-4 | EO52: Поправка: Гл.6.Прил.2.2.п.2.2.6_06.00.01.07.001 Поправка: Гл.12.Прил.8.п.8. 3_12.00.01.11.001 Поправка: Гл.6.Прил.2.2.п.2.2.16_06.00.01.35.006 | EQ52: 0 | ER52: 344.16 | ES52: 132.34 | ET52: 18.69 | EU52: 2.27 | EV52: 193.13 | EW52: 11.57 | EX52: 0 | EY52: 0 | FQ52: 0 | FR52: 0 | FS52: 0 | FX52: 93 | FY52: 62 | GD52: 1 | GF52: -208235524 | GG52: 2 | GH52: 1 | GI52: 2 | GJ52: 0 | GK52: 0 | GL52: =ROUND(IF(AND(BH52=3,BI52=3,FS52<>0),P52,0),2) -> 0 | GM52: =ROUND(O52+X52+Y52,2)+GX52 -> 21.77 | GN52: =IF(OR(BI52=0,BI52=1),GM52-GX52,0) -> 21.77 | GO52: =IF(BI52=2,GM52-GX52,0) -> 0 | GP52: =IF(BI52=4,GM52-GX52,0) -> 0 | GR52: 0 | GS52: 3 | GT52: 0 | GV52: =ROUND((GT52),6) -> 0 | GW52: 1 | GX52: =ROUND(HC52*I52,2) -> 0 | HA52: 0 | HB52: 0 | HC52: =GV52*GW52 -> 0 | HS52: 0 | IK52: 0
A53: 17 | B53: 1 | C53: =ROW(SmtRes!A94) -> 94 | D53: =ROW(EtalonRes!A122) -> 122 | E53: 13 | F53: 3.70-434-1 | G53: Установка дверного доводчика или синхронизатора к металлическим дверям / демонтаж дверного доводчика | H53: 100 шт. | I53: =ROUND(4/100,9) -> 0.04 | J53: 0 | K53: =ROUND(4/100,9) -> 0.04 | O53: =ROUND(CP53,2) -> 414 | P53: =ROUND((ROUND((AC53*AW53*I53),2)*BC53),2) -> 11 | Q53: =(ROUND((ROUND((((((ET53*1.25)*1.2)*0.6))*AV53*I53),2)*BB53),2)+ROUND((ROUND(((AE53-((((EU53*1.25)*1.2)*0.6)))*AV53*I53),2)*BS53),2)) -> 11.37 | R53: =(ROUND((ROUND((((((EU53*1.25)*1.2)*0.6))*AV53*I53),2)*BS53),2)+ROUND((ROUND(((AE53-((((EU53*1.25)*1.2)*0.6)))*AV53*I53),2)*BS53),2)) -> 5.07 | S53: =ROUND((ROUND((AF53*AV53*I53),2)*BA53),2) -> 391.63 | T53: =ROUND(CU53*I53,2) -> 0 | U53: =CV53*I53 -> 0.41653666 | V53: =CW53*I53 -> 0 | W53: =ROUND(CX53*I53,2) -> 0 | X53: =(ROUND((((S53+ROUND((ROUND((((((EU53*1.25)*1.2)*0.6))*AV53*I53),2)*BS53),2))*AT53)/100),2)+ROUND(((ROUND((ROUND(((AE53-((((EU53*1.25)*1.2)*0.6)))*AV53*I53),2)*BS53),2)*AT53)/100),2)) -> 368.93 | Y53: =(ROUND((((S53+ROUND((ROUND((((((EU53*1.25)*1.2)*0.6))*AV53*I53),2)*BS53),2))*AU53)/100),2)+ROUND(((ROUND((ROUND(((AE53-((((EU53*1.25)*1.2)*0.6)))*AV53*I53),2)*BS53),2)*AU53)/100),2)) -> 245.95 | AA53: 55937298 | AB53: =ROUND((AC53+AD53+AF53),6) -> 256.13664 | AC53: =ROUND(((((ES53*1)*1)*0.6)),6) -> 79.404 | AD53: =ROUND(((((((ET53*1.25)*1.2)*0.6))-((((EU53*1.25)*1.2)*0.6)))+AE53),6) -> 16.821 | AE53: =ROUND(((((EU53*1.25)*1.2)*0.6)),6) -> 2.043 | AF53: =ROUND(((((EV53*1.15)*1.2)*0.6)),6) -> 159.91164 | AG53: =ROUND((AP53),6) -> 0 | AH53: =((((EW53*1.15)*1.2)*0.6)) -> 9.57996 | AI53: =((((EX53*1.25)*1.2)*0.6)) -> 0 | AJ53: =(AS53) -> 0 | AK53: 344.16 | AL53: 132.34 | AM53: 18.69 | AN53: 2.27 | AO53: 193.13 | AP53: 0 | AQ53: 11.57 | AR53: 0 | AS53: 0 | AT53: 93 | AU53: 62 | AV53: 1.087 | AW53: 1 | AZ53: 1 | BA53: 56.35 | BB53: 15.58 | BC53: 3.46 | BH53: 0 | BI53: 1 | BJ53: ТСН-2001.3 Доп. 81, Сб. 70, т. 434, поз. 1 | BM53: 55 | BN53: 0 | BO53: 3.70-434-1 | BP53: 1 | BQ53: 30 | BR53: 0 | BS53: 56.35 | BT53: 1 | BU53: 1 | BV53: 1 | BW53: 1 | BX53: 1 | BZ53: 93 | CA53: 62 | CE53: 1566 | CF53: 0 | CG53: 0 | CM53: 0 | CN53: Поправка: Гл.6.Прил.2.2.п.2.2.6_06.00.01.07.001 Наименование: При выполнении при капитальном ремонте и реконструкции работ, аналогичных технологическим процессам, характерным для нового строительства, и отсутствующих в сборниках на ремонтно-строительные работы ТСН-2001.6 Поправка: Гл.12.Прил.8.п.8. 3_12.00.01.11.001 Наименование: При наличии напряженных и стесненных условий производства работ (стесненность, сложность складирования и транспортной логистики и т.п.) для объектов, расположенных в пределах круговой магистральной системы улиц "Садовое кольцо" города Москвы Поправка: Гл.6.Прил.2.2.п.2.2.16_06.00.01.35.006 Наименование: При демонтаже металлических конструкций (в т.ч. к стоимости вспомогательных материалов) | CO53: 0 | CP53: =(P53+Q53+S53) -> 414 | CQ53: =ROUND((ROUND((AC53*AW53*1),2)*BC53),2) -> 274.72 | CR53: =(ROUND((ROUND((((((ET53*1.25)*1.2)*0.6))*AV53*1),2)*BB53),2)+ROUND((ROUND(((AE53-((((EU53*1.25)*1.2)*0.6)))*AV53*1),2)*BS53),2)) -> 284.8 | CS53: =(ROUND((ROUND((((((EU53*1.25)*1.2)*0.6))*AV53*1),2)*BS53),2)+ROUND((ROUND(((AE53-((((EU53*1.25)*1.2)*0.6)))*AV53*1),2)*BS53),2)) -> 125.1 | CT53: =ROUND((ROUND((AF53*AV53*1),2)*BA53),2) -> 9794.76 | CU53: =AG53 -> 0 | CV53: =(AH53*AV53) -> 10.413417 | CW53: =AI53 -> 0 | CX53: =AJ53 -> 0 | CY53: =(ROUND((((S53+ROUND((ROUND((((((EU53*1.25)*1.2)*0.6))*AV53*1),2)*BS53),2))*AT53)/100),2)+ROUND(((ROUND((ROUND(((AE53-((((EU53*1.25)*1.2)*0.6)))*AV53*1),2)*BS53),2)*AT53)/100),2)) -> 480.56 | CZ53: =(ROUND((((S53+ROUND((ROUND((((((EU53*1.25)*1.2)*0.6))*AV53*1),2)*BS53),2))*AU53)/100),2)+ROUND(((ROUND((ROUND(((AE53-((((EU53*1.25)*1.2)*0.6)))*AV53*1),2)*BS53),2)*AU53)/100),2)) -> 320.37 | DB53: 54 | DD53: *1)*1)*0,6 | DE53: *1,25)*1,2)*0,6 | DF53: *1,25)*1,2)*0,6 | DG53: *1,15)*1,2)*0,6 | DI53: *1,15)*1,2)*0,6 | DJ53: *1,25)*1,2)*0,6 | DN53: 0 | DO53: 0 | DP53: 1 | DQ53: 1 | DU53: 1010 | DV53: 100 шт. | DW53: 100 шт. | DX53: 100 | EE53: 55393688 | EF53: 30 | EG53: Строительные работы | EH53: 0 | EJ53: 1 | EK53: 55 | EL53: ТСН-2001.3-70. Металлические конструкции | EM53: ТСН-2001.3-70-4 | EO53: Поправка: Гл.6.Прил.2.2.п.2.2.6_06.00.01.07.001 Поправка: Гл.12.Прил.8.п.8. 3_12.00.01.11.001 Поправка: Гл.6.Прил.2.2.п.2.2.16_06.00.01.35.006 | EQ53: 0 | ER53: 344.16 | ES53: 132.34 | ET53: 18.69 | EU53: 2.27 | EV53: 193.13 | EW53: 11.57 | EX53: 0 | EY53: 0 | FQ53: 0 | FR53: 0 | FS53: 0 | FX53: 93 | FY53: 62 | GD53: 1 | GF53: -208235524 | GG53: 2 | GH53: 1 | GI53: 2 | GJ53: 0 | GK53: 0 | GL53: =ROUND(IF(AND(BH53=3,BI53=3,FS53<>0),P53,0),2) -> 0 | GM53: =ROUND(O53+X53+Y53,2)+GX53 -> 1028.88 | GN53: =IF(OR(BI53=0,BI53=1),GM53-GX53,0) -> 1028.88 | GO53: =IF(BI53=2,GM53-GX53,0) -> 0 | GP53: =IF(BI53=4,GM53-GX53,0) -> 0 | GR53: 0 | GS53: 3 | GT53: 0 | GV53: =ROUND((GT53),6) -> 0 | GW53: 1 | GX53: =ROUND(HC53*I53,2) -> 0 | HA53: 0 | HB53: 0 | HC53: =GV53*GW53 -> 0 | HS53: 0 | IK53: 0
A54: 17 | B54: 1 | C54: =ROW(SmtRes!A98) -> 98 | D54: =ROW(EtalonRes!A128) -> 128 | E54: 14 | F54: 3.20-11-1 | G54: Установка клапанов обратных диаметром до 355 мм / демонтаж клапана сброса избыточного давления КСИД | H54: 1 клапан | I54: 4 | J54: 0 | K54: 4 | O54: =ROUND(CP54,2) -> 54.79 | P54: =ROUND((ROUND((AC54*AW54*I54),2)*BC54),2) -> 9.02 | Q54: =(ROUND((ROUND((((((ET54*1.25)*1.2)*0.6))*AV54*I54),2)*BB54),2)+ROUND((ROUND(((AE54-((((EU54*1.25)*1.2)*0.6)))*AV54*I54),2)*BS54),2)) -> 3.5 | R54: =(ROUND((ROUND((((((EU54*1.25)*1.2)*0.6))*AV54*I54),2)*BS54),2)+ROUND((ROUND(((AE54-((((EU54*1.25)*1.2)*0.6)))*AV54*I54),2)*BS54),2)) -> 0.5 | S54: =ROUND((ROUND((AF54*AV54*I54),2)*BA54),2) -> 42.27 | T54: =ROUND(CU54*I54,2) -> 0 | U54: =CV54*I54 -> 3.6399211 | V54: =CW54*I54 -> 0 | W54: =ROUND(CX54*I54,2) -> 0 | X54: =(ROUND((((S54+ROUND((ROUND((((((EU54*1.25)*1.2)*0.6))*AV54*I54),2)*BS54),2))*AT54)/100),2)+ROUND(((ROUND((ROUND(((AE54-((((EU54*1.25)*1.2)*0.6)))*AV54*I54),2)*BS54),2)*AT54)/100),2)) -> 51.75 | Y54: =(ROUND((((S54+ROUND((ROUND((((((EU54*1.25)*1.2)*0.6))*AV54*I54),2)*BS54),2))*AU54)/100),2)+ROUND(((ROUND((ROUND(((AE54-((((EU54*1.25)*1.2)*0.6)))*AV54*I54),2)*BS54),2)*AU54)/100),2)) -> 30.79 | AA54: 55937296 | AB54: =ROUND((AC54+AD54+AF54),6) -> 12.97788 | AC54: =ROUND(((((ES54*1)*1)*0.6)),6) -> 2.256 | AD54: =ROUND(((((((ET54*1.25)*1.2)*0.6))-((((EU54*1.25)*1.2)*0.6)))+AE54),6) -> 0.819 | AE54: =ROUND(((((EU54*1.25)*1.2)*0.6)),6) -> 0.117 | AF54: =ROUND(((((EV54*1.15)*1.2)*0.6)),6) -> 9.90288 | AG54: =ROUND((AP54),6) -> 0 | AH54: =((((EW54*1.15)*1.2)*0.6)) -> 0.85284 | AI54: =((((EX54*1.25)*1.2)*0.6)) -> 0 | AJ54: =(AS54) -> 0 | AK54: 16.63 | AL54: 3.76 | AM54: 0.91 | AN54: 0.13 | AO54: 11.96 | AP54: 0 | AQ54: 1.03 | AR54: 0 | AS54: 0 | AT54: 121 | AU54: 72 | AV54: 1.067 | AW54: 1 | AZ54: 1 | BA54: 1 | BB54: 1 | BC54: 1 | BH54: 0 | BI54: 1 | BJ54: ТСН-2001.3 Доп. 72, Сб. 20, т. 11, поз. 1 | BM54: 25 | BN54: 0 | BO54: 3.20-11-1 | BP54: 1 | BQ54: 30 | BR54: 0 | BS54: 1 | BT54: 1 | BU54: 1 | BV54: 1 | BW54: 1 | BX54: 1 | BZ54: 121 | CA54: 72 | CE54: 1566 | CF54: 0 | CG54: 0 | CM54: 0 | CN54: Поправка: Гл.6.Прил.2.2.п.2.2.6_06.00.01.07.001 Наименование: При выполнении при капитальном ремонте и реконструкции работ, аналогичных технологическим процессам, характерным для нового строительства, и отсутствующих в сборниках на ремонтно-строительные работы ТСН-2001.6 Поправка: Гл.12.Прил.8.п.8. 3_12.00.01.11.001 Наименование: При наличии напряженных и стесненных условий производства работ (стесненность, сложность складирования и транспортной логистики и т.п.) для объектов, расположенных в пределах круговой магистральной системы улиц "Садовое кольцо" города Москвы Поправка: Гл.6.Прил.2.2.п.2.2.16_06.00.01.35.006 Наименование: При демонтаже металлических конструкций (в т.ч. к стоимости вспомогательных материалов) | CO54: 0 | CP54: =(P54+Q54+S54) -> 54.79 | CQ54: =ROUND((ROUND((AC54*AW54*1),2)*BC54),2) -> 2.26 | CR54: =(ROUND((ROUND((((((ET54*1.25)*1.2)*0.6))*AV54*1),2)*BB54),2)+ROUND((ROUND(((AE54-((((EU54*1.25)*1.2)*0.6)))*AV54*1),2)*BS54),2)) -> 0.87 | CS54: =(ROUND((ROUND((((((EU54*1.25)*1.2)*0.6))*AV54*1),2)*BS54),2)+ROUND((ROUND(((AE54-((((EU54*1.25)*1.2)*0.6)))*AV54*1),2)*BS54),2)) -> 0.12 | CT54: =ROUND((ROUND((AF54*AV54*1),2)*BA54),2) -> 10.57 | CU54: =AG54 -> 0 | CV54: =(AH54*AV54) -> 0.90998028 | CW54: =AI54 -> 0 | CX54: =AJ54 -> 0 | CY54: =(ROUND((((S54+ROUND((ROUND((((((EU54*1.25)*1.2)*0.6))*AV54*1),2)*BS54),2))*AT54)/100),2)+ROUND(((ROUND((ROUND(((AE54-((((EU54*1.25)*1.2)*0.6)))*AV54*1),2)*BS54),2)*AT54)/100),2)) -> 51.29 | CZ54: =(ROUND((((S54+ROUND((ROUND((((((EU54*1.25)*1.2)*0.6))*AV54*1),2)*BS54),2))*AU54)/100),2)+ROUND(((ROUND((ROUND(((AE54-((((EU54*1.25)*1.2)*0.6)))*AV54*1),2)*BS54),2)*AU54)/100),2)) -> 30.52 | DB54: 57 | DD54: *1)*1)*0,6 | DE54: *1,25)*1,2)*0,6 | DF54: *1,25)*1,2)*0,6 | DG54: *1,15)*1,2)*0,6 | DI54: *1,15)*1,2)*0,6 | DJ54: *1,25)*1,2)*0,6 | DN54: 0 | DO54: 0 | DP54: 1 | DQ54: 1 | DU54: 1013 | DV54: 1 клапан | DW54: 1 клапан | DX54: 1 | EE54: 55393654 | EF54: 30 | EG54: Строительные работы | EH54: 0 | EJ54: 1 | EK54: 25 | EL54: ТСН-2001.3-20. Вентиляция и кондиционирование воздуха | EM54: ТСН-2001.3-20-1 | EO54: Поправка: Гл.6.Прил.2.2.п.2.2.6_06.00.01.07.001 Поправка: Гл.12.Прил.8.п.8. 3_12.00.01.11.001 Поправка: Гл.6.Прил.2.2.п.2.2.16_06.00.01.35.006 | EQ54: 0 | ER54: 16.63 | ES54: 3.76 | ET54: 0.91 | EU54: 0.13 | EV54: 11.96 | EW54: 1.03 | EX54: 0 | EY54: 0 | FQ54: 0 | FR54: 0 | FS54: 0 | FX54: 121 | FY54: 72 | GD54: 1 | GF54: -2031960075 | GG54: 2 | GH54: 1 | GI54: 2 | GJ54: 0 | GK54: 0 | GL54: =ROUND(IF(AND(BH54=3,BI54=3,FS54<>0),P54,0),2) -> 0 | GM54: =ROUND(O54+X54+Y54,2)+GX54 -> 137.33 | GN54: =IF(OR(BI54=0,BI54=1),GM54-GX54,0) -> 137.33 | GO54: =IF(BI54=2,GM54-GX54,0) -> 0 | GP54: =IF(BI54=4,GM54-GX54,0) -> 0 | GR54: 0 | GS54: 3 | GT54: 0 | GV54: =ROUND((GT54),6) -> 0 | GW54: 1 | GX54: =ROUND(HC54*I54,2) -> 0 | HA54: 0 | HB54: 0 | HC54: =GV54*GW54 -> 0 | HS54: 0 | IK54: 0
A55: 17 | B55: 1 | C55: =ROW(SmtRes!A102) -> 102 | D55: =ROW(EtalonRes!A134) -> 134 | E55: 14 | F55: 3.20-11-1 | G55: Установка клапанов обратных диаметром до 355 мм / демонтаж клапана сброса избыточного давления КСИД | H55: 1 клапан | I55: 4 | J55: 0 | K55: 4 | O55: =ROUND(CP55,2) -> 2498.41 | P55: =ROUND((ROUND((AC55*AW55*I55),2)*BC55),2) -> 58.99 | Q55: =(ROUND((ROUND((((((ET55*1.25)*1.2)*0.6))*AV55*I55),2)*BB55),2)+ROUND((ROUND(((AE55-((((EU55*1.25)*1.2)*0.6)))*AV55*I55),2)*BS55),2)) -> 57.51 | R55: =(ROUND((ROUND((((((EU55*1.25)*1.2)*0.6))*AV55*I55),2)*BS55),2)+ROUND((ROUND(((AE55-((((EU55*1.25)*1.2)*0.6)))*AV55*I55),2)*BS55),2)) -> 28.18 | S55: =ROUND((ROUND((AF55*AV55*I55),2)*BA55),2) -> 2381.91 | T55: =ROUND(CU55*I55,2) -> 0 | U55: =CV55*I55 -> 3.6399211 | V55: =CW55*I55 -> 0 | W55: =ROUND(CX55*I55,2) -> 0 | X55: =(ROUND((((S55+ROUND((ROUND((((((EU55*1.25)*1.2)*0.6))*AV55*I55),2)*BS55),2))*AT55)/100),2)+ROUND(((ROUND((ROUND(((AE55-((((EU55*1.25)*1.2)*0.6)))*AV55*I55),2)*BS55),2)*AT55)/100),2)) -> 2916.21 | Y55: =(ROUND((((S55+ROUND((ROUND((((((EU55*1.25)*1.2)*0.6))*AV55*I55),2)*BS55),2))*AU55)/100),2)+ROUND(((ROUND((ROUND(((AE55-((((EU55*1.25)*1.2)*0.6)))*AV55*I55),2)*BS55),2)*AU55)/100),2)) -> 1735.26 | AA55: 55937298 | AB55: =ROUND((AC55+AD55+AF55),6) -> 12.97788 | AC55: =ROUND(((((ES55*1)*1)*0.6)),6) -> 2.256 | AD55: =ROUND(((((((ET55*1.25)*1.2)*0.6))-((((EU55*1.25)*1.2)*0.6)))+AE55),6) -> 0.819 | AE55: =ROUND(((((EU55*1.25)*1.2)*0.6)),6) -> 0.117 | AF55: =ROUND(((((EV55*1.15)*1.2)*0.6)),6) -> 9.90288 | AG55: =ROUND((AP55),6) -> 0 | AH55: =((((EW55*1.15)*1.2)*0.6)) -> 0.85284 | AI55: =((((EX55*1.25)*1.2)*0.6)) -> 0 | AJ55: =(AS55) -> 0 | AK55: 16.63 | AL55: 3.76 | AM55: 0.91 | AN55: 0.13 | AO55: 11.96 | AP55: 0 | AQ55: 1.03 | AR55: 0 | AS55: 0 | AT55: 121 | AU55: 72 | AV55: 1.067 | AW55: 1 | AZ55: 1 | BA55: 56.35 | BB55: 16.43 | BC55: 6.54 | BH55: 0 | BI55: 1 | BJ55: ТСН-2001.3 Доп. 72, Сб. 20, т. 11, поз. 1 | BM55: 25 | BN55: 0 | BO55: 3.20-11-1 | BP55: 1 | BQ55: 30 | BR55: 0 | BS55: 56.35 | BT55: 1 | BU55: 1 | BV55: 1 | BW55: 1 | BX55: 1 | BZ55: 121 | CA55: 72 | CE55: 1566 | CF55: 0 | CG55: 0 | CM55: 0 | CN55: Поправка: Гл.6.Прил.2.2.п.2.2.6_06.00.01.07.001 Наименование: При выполнении при капитальном ремонте и реконструкции работ, аналогичных технологическим процессам, характерным для нового строительства, и отсутствующих в сборниках на ремонтно-строительные работы ТСН-2001.6 Поправка: Гл.12.Прил.8.п.8. 3_12.00.01.11.001 Наименование: При наличии напряженных и стесненных условий производства работ (стесненность, сложность складирования и транспортной логистики и т.п.) для объектов, расположенных в пределах круговой магистральной системы улиц "Садовое кольцо" города Москвы Поправка: Гл.6.Прил.2.2.п.2.2.16_06.00.01.35.006 Наименование: При демонтаже металлических конструкций (в т.ч. к стоимости вспомогательных материалов) | CO55: 0 | CP55: =(P55+Q55+S55) -> 2498.41 | CQ55: =ROUND((ROUND((AC55*AW55*1),2)*BC55),2) -> 14.78 | CR55: =(ROUND((ROUND((((((ET55*1.25)*1.2)*0.6))*AV55*1),2)*BB55),2)+ROUND((ROUND(((AE55-((((EU55*1.25)*1.2)*0.6)))*AV55*1),2)*BS55),2)) -> 14.29 | CS55: =(ROUND((ROUND((((((EU55*1.25)*1.2)*0.6))*AV55*1),2)*BS55),2)+ROUND((ROUND(((AE55-((((EU55*1.25)*1.2)*0.6)))*AV55*1),2)*BS55),2)) -> 6.76 | CT55: =ROUND((ROUND((AF55*AV55*1),2)*BA55),2) -> 595.62 | CU55: =AG55 -> 0 | CV55: =(AH55*AV55) -> 0.90998028 | CW55: =AI55 -> 0 | CX55: =AJ55 -> 0 | CY55: =(ROUND((((S55+ROUND((ROUND((((((EU55*1.25)*1.2)*0.6))*AV55*1),2)*BS55),2))*AT55)/100),2)+ROUND(((ROUND((ROUND(((AE55-((((EU55*1.25)*1.2)*0.6)))*AV55*1),2)*BS55),2)*AT55)/100),2)) -> 2890.29 | CZ55: =(ROUND((((S55+ROUND((ROUND((((((EU55*1.25)*1.2)*0.6))*AV55*1),2)*BS55),2))*AU55)/100),2)+ROUND(((ROUND((ROUND(((AE55-((((EU55*1.25)*1.2)*0.6)))*AV55*1),2)*BS55),2)*AU55)/100),2)) -> 1719.84 | DB55: 60 | DD55: *1)*1)*0,6 | DE55: *1,25)*1,2)*0,6 | DF55: *1,25)*1,2)*0,6 | DG55: *1,15)*1,2)*0,6 | DI55: *1,15)*1,2)*0,6 | DJ55: *1,25)*1,2)*0,6 | DN55: 0 | DO55: 0 | DP55: 1 | DQ55: 1 | DU55: 1013 | DV55: 1 клапан | DW55: 1 клапан | DX55: 1 | EE55: 55393654 | EF55: 30 | EG55: Строительные работы | EH55: 0 | EJ55: 1 | EK55: 25 | EL55: ТСН-2001.3-20. Вентиляция и кондиционирование воздуха | EM55: ТСН-2001.3-20-1 | EO55: Поправка: Гл.6.Прил.2.2.п.2.2.6_06.00.01.07.001 Поправка: Гл.12.Прил.8.п.8. 3_12.00.01.11.001 Поправка: Гл.6.Прил.2.2.п.2.2.16_06.00.01.35.006 | EQ55: 0 | ER55: 16.63 | ES55: 3.76 | ET55: 0.91 | EU55: 0.13 | EV55: 11.96 | EW55: 1.03 | EX55: 0 | EY55: 0 | FQ55: 0 | FR55: 0 | FS55: 0 | FX55: 121 | FY55: 72 | GD55: 1 | GF55: -2031960075 | GG55: 2 | GH55: 1 | GI55: 2 | GJ55: 0 | GK55: 0 | GL55: =ROUND(IF(AND(BH55=3,BI55=3,FS55<>0),P55,0),2) -> 0 | GM55: =ROUND(O55+X55+Y55,2)+GX55 -> 7149.88 | GN55: =IF(OR(BI55=0,BI55=1),GM55-GX55,0) -> 7149.88 | GO55: =IF(BI55=2,GM55-GX55,0) -> 0 | GP55: =IF(BI55=4,GM55-GX55,0) -> 0 | GR55: 0 | GS55: 3 | GT55: 0 | GV55: =ROUND((GT55),6) -> 0 | GW55: 1 | GX55: =ROUND(HC55*I55,2) -> 0 | HA55: 0 | HB55: 0 | HC55: =GV55*GW55 -> 0 | HS55: 0 | IK55: 0
A56: 17 | B56: 1 | C56: =ROW(SmtRes!A107) -> 107 | D56: =ROW(EtalonRes!A141) -> 141 | E56: 15 | F56: 3.17-12-1 | G56: Установка вентиляционных решеток площадью в свету до 0,05 м2 / демонтаж защитной решетки для КСИД | H56: 100 шт. | I56: =ROUND(4/100,9) -> 0.04 | J56: 0 | K56: =ROUND(4/100,9) -> 0.04 | O56: =ROUND(CP56,2) -> 18.64 | P56: =ROUND((ROUND((AC56*AW56*I56),2)*BC56),2) -> 8.54 | Q56: =(ROUND((ROUND((((((ET56*1.25)*1.2)*0.6))*AV56*I56),2)*BB56),2)+ROUND((ROUND(((AE56-((((EU56*1.25)*1.2)*0.6)))*AV56*I56),2)*BS56),2)) -> 0.3 | R56: =(ROUND((ROUND((((((EU56*1.25)*1.2)*0.6))*AV56*I56),2)*BS56),2)+ROUND((ROUND(((AE56-((((EU56*1.25)*1.2)*0.6)))*AV56*I56),2)*BS56),2)) -> 0.01 | S56: =ROUND((ROUND((AF56*AV56*I56),2)*BA56),2) -> 9.8 | T56: =ROUND(CU56*I56,2) -> 0 | U56: =CV56*I56 -> 0.87640819 | V56: =CW56*I56 -> 0 | W56: =ROUND(CX56*I56,2) -> 0 | X56: =(ROUND((((S56+ROUND((ROUND((((((EU56*1.25)*1.2)*0.6))*AV56*I56),2)*BS56),2))*AT56)/100),2)+ROUND(((ROUND((ROUND(((AE56-((((EU56*1.25)*1.2)*0.6)))*AV56*I56),2)*BS56),2)*AT56)/100),2)) -> 11.87 | Y56: =(ROUND((((S56+ROUND((ROUND((((((EU56*1.25)*1.2)*0.6))*AV56*I56),2)*BS56),2))*AU56)/100),2)+ROUND(((ROUND((ROUND(((AE56-((((EU56*1.25)*1.2)*0.6)))*AV56*I56),2)*BS56),2)*AU56)/100),2)) -> 7.06 | AA56: 55937296 | AB56: =ROUND((AC56+AD56+AF56),6) -> 450.19188 | AC56: =ROUND(((((ES56*1)*1)*0.6)),6) -> 213.624 | AD56: =ROUND(((((((ET56*1.25)*1.2)*0.6))-((((EU56*1.25)*1.2)*0.6)))+AE56),6) -> 7.038 | AE56: =ROUND(((((EU56*1.25)*1.2)*0.6)),6) -> 0.225 | AF56: =ROUND(((((EV56*1.15)*1.2)*0.6)),6) -> 229.52988 | AG56: =ROUND((AP56),6) -> 0 | AH56: =((((EW56*1.15)*1.2)*0.6)) -> 20.5344 | AI56: =((((EX56*1.25)*1.2)*0.6)) -> 0 | AJ56: =(AS56) -> 0 | AK56: 641.07 | AL56: 356.04 | AM56: 7.82 | AN56: 0.25 | AO56: 277.21 | AP56: 0 | AQ56: 24.8 | AR56: 0 | AS56: 0 | AT56: 121 | AU56: 72 | AV56: 1.067 | AW56: 1 | AZ56: 1 | BA56: 1 | BB56: 1 | BC56: 1 | BH56: 0 | BI56: 1 | BJ56: ТСН-2001.3 Доп. 79, Сб. 17, т. 12, поз. 1 | BM56: 22 | BN56: 0 | BO56: 3.17-12-1 | BP56: 1 | BQ56: 30 | BR56: 0 | BS56: 1 | BT56: 1 | BU56: 1 | BV56: 1 | BW56: 1 | BX56: 1 | BZ56: 121 | CA56: 72 | CE56: 1566 | CF56: 0 | CG56: 0 | CM56: 0 | CN56: Поправка: Гл.6.Прил.2.2.п.2.2.6_06.00.01.07.001 Наименование: При выполнении при капитальном ремонте и реконструкции работ, аналогичных технологическим процессам, характерным для нового строительства, и отсутствующих в сборниках на ремонтно-строительные работы ТСН-2001.6 Поправка: Гл.12.Прил.8.п.8. 3_12.00.01.11.001 Наименование: При наличии напряженных и стесненных условий производства работ (стесненность, сложность складирования и транспортной логистики и т.п.) для объектов, расположенных в пределах круговой магистральной системы улиц "Садовое кольцо" города Москвы Поправка: Гл.6.Прил.2.2.п.2.2.16_06.00.01.35.006 Наименование: При демонтаже металлических конструкций (в т.ч. к стоимости вспомогательных материалов) | CO56: 0 | CP56: =(P56+Q56+S56) -> 18.64 | CQ56: =ROUND((ROUND((AC56*AW56*1),2)*BC56),2) -> 213.62 | CR56: =(ROUND((ROUND((((((ET56*1.25)*1.2)*0.6))*AV56*1),2)*BB56),2)+ROUND((ROUND(((AE56-((((EU56*1.25)*1.2)*0.6)))*AV56*1),2)*BS56),2)) -> 7.51 | CS56: =(ROUND((ROUND((((((EU56*1.25)*1.2)*0.6))*AV56*1),2)*BS56),2)+ROUND((ROUND(((AE56-((((EU56*1.25)*1.2)*0.6)))*AV56*1),2)*BS56),2)) -> 0.24 | CT56: =ROUND((ROUND((AF56*AV56*1),2)*BA56),2) -> 244.91 | CU56: =AG56 -> 0 | CV56: =(AH56*AV56) -> 21.910205 | CW56: =AI56 -> 0 | CX56: =AJ56 -> 0 | CY56: =(ROUND((((S56+ROUND((ROUND((((((EU56*1.25)*1.2)*0.6))*AV56*1),2)*BS56),2))*AT56)/100),2)+ROUND(((ROUND((ROUND(((AE56-((((EU56*1.25)*1.2)*0.6)))*AV56*1),2)*BS56),2)*AT56)/100),2)) -> 12.15 | CZ56: =(ROUND((((S56+ROUND((ROUND((((((EU56*1.25)*1.2)*0.6))*AV56*1),2)*BS56),2))*AU56)/100),2)+ROUND(((ROUND((ROUND(((AE56-((((EU56*1.25)*1.2)*0.6)))*AV56*1),2)*BS56),2)*AU56)/100),2)) -> 7.23 | DB56: 63 | DD56: *1)*1)*0,6 | DE56: *1,25)*1,2)*0,6 | DF56: *1,25)*1,2)*0,6 | DG56: *1,15)*1,2)*0,6 | DI56: *1,15)*1,2)*0,6 | DJ56: *1,25)*1,2)*0,6 | DN56: 0 | DO56: 0 | DP56: 1 | DQ56: 1 | DU56: 1010 | DV56: 100 шт. | DW56: 100 шт. | DX56: 100 | EE56: 55393651 | EF56: 30 | EG56: Строительные работы | EH56: 0 | EJ56: 1 | EK56: 22 | EL56: ТСН-2001.3-17. Водопровод и канализация - внутренние устройства | EM56: ТСН-2001.3-17-1 | EO56: Поправка: Гл.6.Прил.2.2.п.2.2.6_06.00.01.07.001 Поправка: Гл.12.Прил.8.п.8. 3_12.00.01.11.001 Поправка: Гл.6.Прил.2.2.п.2.2.16_06.00.01.35.006 | EQ56: 0 | ER56: 641.07 | ES56: 356.04 | ET56: 7.82 | EU56: 0.25 | EV56: 277.21 | EW56: 24.8 | EX56: 0 | EY56: 0 | FQ56: 0 | FR56: 0 | FS56: 0 | FX56: 121 | FY56: 72 | GD56: 1 | GF56: -1508474127 | GG56: 2 | GH56: 1 | GI56: 2 | GJ56: 0 | GK56: 0 | GL56: =ROUND(IF(AND(BH56=3,BI56=3,FS56<>0),P56,0),2) -> 0 | GM56: =ROUND(O56+X56+Y56,2)+GX56 -> 37.57 | GN56: =IF(OR(BI56=0,BI56=1),GM56-GX56,0) -> 37.57 | GO56: =IF(BI56=2,GM56-GX56,0) -> 0 | GP56: =IF(BI56=4,GM56-GX56,0) -> 0 | GR56: 0 | GS56: 3 | GT56: 0 | GV56: =ROUND((GT56),6) -> 0 | GW56: 1 | GX56: =ROUND(HC56*I56,2) -> 0 | HA56: 0 | HB56: 0 | HC56: =GV56*GW56 -> 0 | HS56: 0 | IK56: 0
A57: 17 | B57: 1 | C57: =ROW(SmtRes!A112) -> 112 | D57: =ROW(EtalonRes!A148) -> 148 | E57: 15 | F57: 3.17-12-1 | G57: Установка вентиляционных решеток площадью в свету до 0,05 м2 / демонтаж защитной решетки для КСИД | H57: 100 шт. | I57: =ROUND(4/100,9) -> 0.04 | J57: 0 | K57: =ROUND(4/100,9) -> 0.04 | O57: =ROUND(CP57,2) -> 584.79 | P57: =ROUND((ROUND((AC57*AW57*I57),2)*BC57),2) -> 29.21 | Q57: =(ROUND((ROUND((((((ET57*1.25)*1.2)*0.6))*AV57*I57),2)*BB57),2)+ROUND((ROUND(((AE57-((((EU57*1.25)*1.2)*0.6)))*AV57*I57),2)*BS57),2)) -> 3.35 | R57: =(ROUND((ROUND((((((EU57*1.25)*1.2)*0.6))*AV57*I57),2)*BS57),2)+ROUND((ROUND(((AE57-((((EU57*1.25)*1.2)*0.6)))*AV57*I57),2)*BS57),2)) -> 0.56 | S57: =ROUND((ROUND((AF57*AV57*I57),2)*BA57),2) -> 552.23 | T57: =ROUND(CU57*I57,2) -> 0 | U57: =CV57*I57 -> 0.87640819 | V57: =CW57*I57 -> 0 | W57: =ROUND(CX57*I57,2) -> 0 | X57: =(ROUND((((S57+ROUND((ROUND((((((EU57*1.25)*1.2)*0.6))*AV57*I57),2)*BS57),2))*AT57)/100),2)+ROUND(((ROUND((ROUND(((AE57-((((EU57*1.25)*1.2)*0.6)))*AV57*I57),2)*BS57),2)*AT57)/100),2)) -> 668.88 | Y57: =(ROUND((((S57+ROUND((ROUND((((((EU57*1.25)*1.2)*0.6))*AV57*I57),2)*BS57),2))*AU57)/100),2)+ROUND(((ROUND((ROUND(((AE57-((((EU57*1.25)*1.2)*0.6)))*AV57*I57),2)*BS57),2)*AU57)/100),2)) -> 398.01 | AA57: 55937298 | AB57: =ROUND((AC57+AD57+AF57),6) -> 450.19188 | AC57: =ROUND(((((ES57*1)*1)*0.6)),6) -> 213.624 | AD57: =ROUND(((((((ET57*1.25)*1.2)*0.6))-((((EU57*1.25)*1.2)*0.6)))+AE57),6) -> 7.038 | AE57: =ROUND(((((EU57*1.25)*1.2)*0.6)),6) -> 0.225 | AF57: =ROUND(((((EV57*1.15)*1.2)*0.6)),6) -> 229.52988 | AG57: =ROUND((AP57),6) -> 0 | AH57: =((((EW57*1.15)*1.2)*0.6)) -> 20.5344 | AI57: =((((EX57*1.25)*1.2)*0.6)) -> 0 | AJ57: =(AS57) -> 0 | AK57: 641.07 | AL57: 356.04 | AM57: 7.82 | AN57: 0.25 | AO57: 277.21 | AP57: 0 | AQ57: 24.8 | AR57: 0 | AS57: 0 | AT57: 121 | AU57: 72 | AV57: 1.067 | AW57: 1 | AZ57: 1 | BA57: 56.35 | BB57: 11.16 | BC57: 3.42 | BH57: 0 | BI57: 1 | BJ57: ТСН-2001.3 Доп. 79, Сб. 17, т. 12, поз. 1 | BM57: 22 | BN57: 0 | BO57: 3.17-12-1 | BP57: 1 | BQ57: 30 | BR57: 0 | BS57: 56.35 | BT57: 1 | BU57: 1 | BV57: 1 | BW57: 1 | BX57: 1 | BZ57: 121 | CA57: 72 | CE57: 1566 | CF57: 0 | CG57: 0 | CM57: 0 | CN57: Поправка: Гл.6.Прил.2.2.п.2.2.6_06.00.01.07.001 Наименование: При выполнении при капитальном ремонте и реконструкции работ, аналогичных технологическим процессам, характерным для нового строительства, и отсутствующих в сборниках на ремонтно-строительные работы ТСН-2001.6 Поправка: Гл.12.Прил.8.п.8. 3_12.00.01.11.001 Наименование: При наличии напряженных и стесненных условий производства работ (стесненность, сложность складирования и транспортной логистики и т.п.) для объектов, расположенных в пределах круговой магистральной системы улиц "Садовое кольцо" города Москвы Поправка: Гл.6.Прил.2.2.п.2.2.16_06.00.01.35.006 Наименование: При демонтаже металлических конструкций (в т.ч. к стоимости вспомогательных материалов) | CO57: 0 | CP57: =(P57+Q57+S57) -> 584.79 | CQ57: =ROUND((ROUND((AC57*AW57*1),2)*BC57),2) -> 730.58 | CR57: =(ROUND((ROUND((((((ET57*1.25)*1.2)*0.6))*AV57*1),2)*BB57),2)+ROUND((ROUND(((AE57-((((EU57*1.25)*1.2)*0.6)))*AV57*1),2)*BS57),2)) -> 83.81 | CS57: =(ROUND((ROUND((((((EU57*1.25)*1.2)*0.6))*AV57*1),2)*BS57),2)+ROUND((ROUND(((AE57-((((EU57*1.25)*1.2)*0.6)))*AV57*1),2)*BS57),2)) -> 13.52 | CT57: =ROUND((ROUND((AF57*AV57*1),2)*BA57),2) -> 13800.68 | CU57: =AG57 -> 0 | CV57: =(AH57*AV57) -> 21.910205 | CW57: =AI57 -> 0 | CX57: =AJ57 -> 0 | CY57: =(ROUND((((S57+ROUND((ROUND((((((EU57*1.25)*1.2)*0.6))*AV57*1),2)*BS57),2))*AT57)/100),2)+ROUND(((ROUND((ROUND(((AE57-((((EU57*1.25)*1.2)*0.6)))*AV57*1),2)*BS57),2)*AT57)/100),2)) -> 684.56 | CZ57: =(ROUND((((S57+ROUND((ROUND((((((EU57*1.25)*1.2)*0.6))*AV57*1),2)*BS57),2))*AU57)/100),2)+ROUND(((ROUND((ROUND(((AE57-((((EU57*1.25)*1.2)*0.6)))*AV57*1),2)*BS57),2)*AU57)/100),2)) -> 407.34 | DB57: 66 | DD57: *1)*1)*0,6 | DE57: *1,25)*1,2)*0,6 | DF57: *1,25)*1,2)*0,6 | DG57: *1,15)*1,2)*0,6 | DI57: *1,15)*1,2)*0,6 | DJ57: *1,25)*1,2)*0,6 | DN57: 0 | DO57: 0 | DP57: 1 | DQ57: 1 | DU57: 1010 | DV57: 100 шт. | DW57: 100 шт. | DX57: 100 | EE57: 55393651 | EF57: 30 | EG57: Строительные работы | EH57: 0 | EJ57: 1 | EK57: 22 | EL57: ТСН-2001.3-17. Водопровод и канализация - внутренние устройства | EM57: ТСН-2001.3-17-1 | EO57: Поправка: Гл.6.Прил.2.2.п.2.2.6_06.00.01.07.001 Поправка: Гл.12.Прил.8.п.8. 3_12.00.01.11.001 Поправка: Гл.6.Прил.2.2.п.2.2.16_06.00.01.35.006 | EQ57: 0 | ER57: 641.07 | ES57: 356.04 | ET57: 7.82 | EU57: 0.25 | EV57: 277.21 | EW57: 24.8 | EX57: 0 | EY57: 0 | FQ57: 0 | FR57: 0 | FS57: 0 | FX57: 121 | FY57: 72 | GD57: 1 | GF57: -1508474127 | GG57: 2 | GH57: 1 | GI57: 2 | GJ57: 0 | GK57: 0 | GL57: =ROUND(IF(AND(BH57=3,BI57=3,FS57<>0),P57,0),2) -> 0 | GM57: =ROUND(O57+X57+Y57,2)+GX57 -> 1651.68 | GN57: =IF(OR(BI57=0,BI57=1),GM57-GX57,0) -> 1651.68 | GO57: =IF(BI57=2,GM57-GX57,0) -> 0 | GP57: =IF(BI57=4,GM57-GX57,0) -> 0 | GR57: 0 | GS57: 3 | GT57: 0 | GV57: =ROUND((GT57),6) -> 0 | GW57: 1 | GX57: =ROUND(HC57*I57,2) -> 0 | HA57: 0 | HB57: 0 | HC57: =GV57*GW57 -> 0 | HS57: 0 | IK57: 0
A58: 17 | B58: 1 | C58: =ROW(SmtRes!A113) -> 113 | D58: =ROW(EtalonRes!A149) -> 149 | E58: 16 | F58: 6.67-6-1 | G58: Демонтаж кабеля | H58: 100 м | I58: =ROUND((642+4+150+90)/100,9) -> 8.86 | J58: 0 | K58: =ROUND((642+4+150+90)/100,9) -> 8.86 | O58: =ROUND(CP58,2) -> 1096.7 | P58: =ROUND((ROUND((AC58*AW58*I58),2)*BC58),2) -> 0 | Q58: =(ROUND((ROUND((((ET58*1.2))*AV58*I58),2)*BB58),2)+ROUND((ROUND(((AE58-((EU58*1.2)))*AV58*I58),2)*BS58),2)) -> 0 | R58: =(ROUND((ROUND((((EU58*1.2))*AV58*I58),2)*BS58),2)+ROUND((ROUND(((AE58-((EU58*1.2)))*AV58*I58),2)*BS58),2)) -> 0 | S58: =ROUND((ROUND((AF58*AV58*I58),2)*BA58),2) -> 1096.7 | T58: =ROUND(CU58*I58,2) -> 0 | U58: =CV58*I58 -> 107.30963 | V58: =CW58*I58 -> 0 | W58: =ROUND(CX58*I58,2) -> 0 | X58: =(ROUND((((S58+ROUND((ROUND((((EU58*1.2))*AV58*I58),2)*BS58),2))*AT58)/100),2)+ROUND(((ROUND((ROUND(((AE58-((EU58*1.2)))*AV58*I58),2)*BS58),2)*AT58)/100),2)) -> 998 | Y58: =(ROUND((((S58+ROUND((ROUND((((EU58*1.2))*AV58*I58),2)*BS58),2))*AU58)/100),2)+ROUND(((ROUND((ROUND(((AE58-((EU58*1.2)))*AV58*I58),2)*BS58),2)*AU58)/100),2)) -> 526.42 | AA58: 55937296 | AB58: =ROUND((AC58+AD58+AF58),6) -> 118.224 | AC58: =ROUND(((ES58*1)),6) -> 0 | AD58: =ROUND(((((ET58*1.2))-((EU58*1.2)))+AE58),6) -> 0 | AE58: =ROUND(((EU58*1.2)),6) -> 0 | AF58: =ROUND(((EV58*1.2)),6) -> 118.224 | AG58: =ROUND((AP58),6) -> 0 | AH58: =((EW58*1.2)) -> 11.568 | AI58: =((EX58*1.2)) -> 0 | AJ58: =(AS58) -> 0 | AK58: 98.52 | AL58: 0 | AM58: 0 | AN58: 0 | AO58: 98.52 | AP58: 0 | AQ58: 9.64 | AR58: 0 | AS58: 0 | AT58: 91 | AU58: 48 | AV58: 1.047 | AW58: 1 | AZ58: 1 | BA58: 1 | BB58: 1 | BC58: 1 | BH58: 0 | BI58: 1 | BJ58: ТСН-2001.6. Доп. 1-42. Сб. 67, т. 6, поз. 1 | BM58: 106 | BN58: 0 | BO58: 6.67-6-1 | BP58: 1 | BQ58: 60 | BR58: 0 | BS58: 1 | BT58: 1 | BU58: 1 | BV58: 1 | BW58: 1 | BX58: 1 | BZ58: 91 | CA58: 48 | CE58: 1566 | CF58: 0 | CG58: 0 | CM58: 0 | CN58: Поправка: Гл.12.Прил.8.п.8. 3_12.00.01.11.001 Наименование: При наличии напряженных и стесненных условий производства работ (стесненность, сложность складирования и транспортной логистики и т.п.) для объектов, расположенных в пределах круговой магистральной системы улиц "Садовое кольцо" города Москвы | CO58: 0 | CP58: =(P58+Q58+S58) -> 1096.7 | CQ58: =ROUND((ROUND((AC58*AW58*1),2)*BC58),2) -> 0 | CR58: =(ROUND((ROUND((((ET58*1.2))*AV58*1),2)*BB58),2)+ROUND((ROUND(((AE58-((EU58*1.2)))*AV58*1),2)*BS58),2)) -> 0 | CS58: =(ROUND((ROUND((((EU58*1.2))*AV58*1),2)*BS58),2)+ROUND((ROUND(((AE58-((EU58*1.2)))*AV58*1),2)*BS58),2)) -> 0 | CT58: =ROUND((ROUND((AF58*AV58*1),2)*BA58),2) -> 123.78 | CU58: =AG58 -> 0 | CV58: =(AH58*AV58) -> 12.111696 | CW58: =AI58 -> 0 | CX58: =AJ58 -> 0 | CY58: =(ROUND((((S58+ROUND((ROUND((((EU58*1.2))*AV58*1),2)*BS58),2))*AT58)/100),2)+ROUND(((ROUND((ROUND(((AE58-((EU58*1.2)))*AV58*1),2)*BS58),2)*AT58)/100),2)) -> 998 | CZ58: =(ROUND((((S58+ROUND((ROUND((((EU58*1.2))*AV58*1),2)*BS58),2))*AU58)/100),2)+ROUND(((ROUND((ROUND(((AE58-((EU58*1.2)))*AV58*1),2)*BS58),2)*AU58)/100),2)) -> 526.42 | DB58: 69 | DD58: *1 | DE58: *1,2 | DF58: *1,2 | DG58: *1,2 | DI58: *1,2 | DJ58: *1,2 | DN58: 0 | DO58: 0 | DP58: 1 | DQ58: 1 | DU58: 1003 | DV58: 100 м | DW58: 100 м | DX58: 100 | EE58: 55393738 | EF58: 60 | EG58: Ремонтно-строительные работы | EH58: 0 | EJ58: 1 | EK58: 106 | EL58: ТСН-2001.6-67. Электромонтажные работы | EM58: ТСН-2001.6-67-1 | EO58: Поправка: Гл.12.Прил.8.п.8. 3_12.00.01.11.001 | EQ58: 0 | ER58: 98.52 | ES58: 0 | ET58: 0 | EU58: 0 | EV58: 98.52 | EW58: 9.64 | EX58: 0 | EY58: 0 | FQ58: 0 | FR58: 0 | FS58: 0 | FX58: 91 | FY58: 48 | GD58: 1 | GF58: 1114236003 | GG58: 2 | GH58: 1 | GI58: 2 | GJ58: 0 | GK58: 0 | GL58: =ROUND(IF(AND(BH58=3,BI58=3,FS58<>0),P58,0),2) -> 0 | GM58: =ROUND(O58+X58+Y58,2)+GX58 -> 2621.12 | GN58: =IF(OR(BI58=0,BI58=1),GM58-GX58,0) -> 2621.12 | GO58: =IF(BI58=2,GM58-GX58,0) -> 0 | GP58: =IF(BI58=4,GM58-GX58,0) -> 0 | GR58: 0 | GS58: 3 | GT58: 0 | GV58: =ROUND((GT58),6) -> 0 | GW58: 1 | GX58: =ROUND(HC58*I58,2) -> 0 | HA58: 0 | HB58: 0 | HC58: =GV58*GW58 -> 0 | HS58: 0 | IK58: 0
A59: 17 | B59: 1 | C59: =ROW(SmtRes!A114) -> 114 | D59: =ROW(EtalonRes!A150) -> 150 | E59: 16 | F59: 6.67-6-1 | G59: Демонтаж кабеля | H59: 100 м | I59: =ROUND((642+4+150+90)/100,9) -> 8.86 | J59: 0 | K59: =ROUND((642+4+150+90)/100,9) -> 8.86 | O59: =ROUND(CP59,2) -> 61799.05 | P59: =ROUND((ROUND((AC59*AW59*I59),2)*BC59),2) -> 0 | Q59: =(ROUND((ROUND((((ET59*1.2))*AV59*I59),2)*BB59),2)+ROUND((ROUND(((AE59-((EU59*1.2)))*AV59*I59),2)*BS59),2)) -> 0 | R59: =(ROUND((ROUND((((EU59*1.2))*AV59*I59),2)*BS59),2)+ROUND((ROUND(((AE59-((EU59*1.2)))*AV59*I59),2)*BS59),2)) -> 0 | S59: =ROUND((ROUND((AF59*AV59*I59),2)*BA59),2) -> 61799.05 | T59: =ROUND(CU59*I59,2) -> 0 | U59: =CV59*I59 -> 107.30963 | V59: =CW59*I59 -> 0 | W59: =ROUND(CX59*I59,2) -> 0 | X59: =(ROUND((((S59+ROUND((ROUND((((EU59*1.2))*AV59*I59),2)*BS59),2))*AT59)/100),2)+ROUND(((ROUND((ROUND(((AE59-((EU59*1.2)))*AV59*I59),2)*BS59),2)*AT59)/100),2)) -> 56237.14 | Y59: =(ROUND((((S59+ROUND((ROUND((((EU59*1.2))*AV59*I59),2)*BS59),2))*AU59)/100),2)+ROUND(((ROUND((ROUND(((AE59-((EU59*1.2)))*AV59*I59),2)*BS59),2)*AU59)/100),2)) -> 29663.54 | AA59: 55937298 | AB59: =ROUND((AC59+AD59+AF59),6) -> 118.224 | AC59: =ROUND(((ES59*1)),6) -> 0 | AD59: =ROUND(((((ET59*1.2))-((EU59*1.2)))+AE59),6) -> 0 | AE59: =ROUND(((EU59*1.2)),6) -> 0 | AF59: =ROUND(((EV59*1.2)),6) -> 118.224 | AG59: =ROUND((AP59),6) -> 0 | AH59: =((EW59*1.2)) -> 11.568 | AI59: =((EX59*1.2)) -> 0 | AJ59: =(AS59) -> 0 | AK59: 98.52 | AL59: 0 | AM59: 0 | AN59: 0 | AO59: 98.52 | AP59: 0 | AQ59: 9.64 | AR59: 0 | AS59: 0 | AT59: 91 | AU59: 48 | AV59: 1.047 | AW59: 1 | AZ59: 1 | BA59: 56.35 | BB59: 1 | BC59: 1 | BH59: 0 | BI59: 1 | BJ59: ТСН-2001.6. Доп. 1-42. Сб. 67, т. 6, поз. 1 | BM59: 106 | BN59: 0 | BO59: 6.67-6-1 | BP59: 1 | BQ59: 60 | BR59: 0 | BS59: 56.35 | BT59: 1 | BU59: 1 | BV59: 1 | BW59: 1 | BX59: 1 | BZ59: 91 | CA59: 48 | CE59: 1566 | CF59: 0 | CG59: 0 | CM59: 0 | CN59: Поправка: Гл.12.Прил.8.п.8. 3_12.00.01.11.001 Наименование: При наличии напряженных и стесненных условий производства работ (стесненность, сложность складирования и транспортной логистики и т.п.) для объектов, расположенных в пределах круговой магистральной системы улиц "Садовое кольцо" города Москвы | CO59: 0 | CP59: =(P59+Q59+S59) -> 61799.05 | CQ59: =ROUND((ROUND((AC59*AW59*1),2)*BC59),2) -> 0 | CR59: =(ROUND((ROUND((((ET59*1.2))*AV59*1),2)*BB59),2)+ROUND((ROUND(((AE59-((EU59*1.2)))*AV59*1),2)*BS59),2)) -> 0 | CS59: =(ROUND((ROUND((((EU59*1.2))*AV59*1),2)*BS59),2)+ROUND((ROUND(((AE59-((EU59*1.2)))*AV59*1),2)*BS59),2)) -> 0 | CT59: =ROUND((ROUND((AF59*AV59*1),2)*BA59),2) -> 6975 | CU59: =AG59 -> 0 | CV59: =(AH59*AV59) -> 12.111696 | CW59: =AI59 -> 0 | CX59: =AJ59 -> 0 | CY59: =(ROUND((((S59+ROUND((ROUND((((EU59*1.2))*AV59*1),2)*BS59),2))*AT59)/100),2)+ROUND(((ROUND((ROUND(((AE59-((EU59*1.2)))*AV59*1),2)*BS59),2)*AT59)/100),2)) -> 56237.14 | CZ59: =(ROUND((((S59+ROUND((ROUND((((EU59*1.2))*AV59*1),2)*BS59),2))*AU59)/100),2)+ROUND(((ROUND((ROUND(((AE59-((EU59*1.2)))*AV59*1),2)*BS59),2)*AU59)/100),2)) -> 29663.54 | DB59: 70 | DD59: *1 | DE59: *1,2 | DF59: *1,2 | DG59: *1,2 | DI59: *1,2 | DJ59: *1,2 | DN59: 0 | DO59: 0 | DP59: 1 | DQ59: 1 | DU59: 1003 | DV59: 100 м | DW59: 100 м | DX59: 100 | EE59: 55393738 | EF59: 60 | EG59: Ремонтно-строительные работы | EH59: 0 | EJ59: 1 | EK59: 106 | EL59: ТСН-2001.6-67. Электромонтажные работы | EM59: ТСН-2001.6-67-1 | EO59: Поправка: Гл.12.Прил.8.п.8. 3_12.00.01.11.001 | EQ59: 0 | ER59: 98.52 | ES59: 0 | ET59: 0 | EU59: 0 | EV59: 98.52 | EW59: 9.64 | EX59: 0 | EY59: 0 | FQ59: 0 | FR59: 0 | FS59: 0 | FX59: 91 | FY59: 48 | GD59: 1 | GF59: 1114236003 | GG59: 2 | GH59: 1 | GI59: 2 | GJ59: 0 | GK59: 0 | GL59: =ROUND(IF(AND(BH59=3,BI59=3,FS59<>0),P59,0),2) -> 0 | GM59: =ROUND(O59+X59+Y59,2)+GX59 -> 147699.73 | GN59: =IF(OR(BI59=0,BI59=1),GM59-GX59,0) -> 147699.73 | GO59: =IF(BI59=2,GM59-GX59,0) -> 0 | GP59: =IF(BI59=4,GM59-GX59,0) -> 0 | GR59: 0 | GS59: 3 | GT59: 0 | GV59: =ROUND((GT59),6) -> 0 | GW59: 1 | GX59: =ROUND(HC59*I59,2) -> 0 | HA59: 0 | HB59: 0 | HC59: =GV59*GW59 -> 0 | HS59: 0 | IK59: 0
A60: 17 | B60: 1 | C60: =ROW(SmtRes!A116) -> 116 | D60: =ROW(EtalonRes!A152) -> 152 | E60: 17 | F60: 6.67-5-12 | G60: Демонтаж трубных проводок, трубы в борозде диаметром 25 мм | H60: 100 м | I60: =ROUND((642+150+2)/100,9) -> 7.94 | J60: 0 | K60: =ROUND((642+150+2)/100,9) -> 7.94 | O60: =ROUND(CP60,2) -> 3194.56 | P60: =ROUND((ROUND((AC60*AW60*I60),2)*BC60),2) -> 0 | Q60: =(ROUND((ROUND((((ET60*1.2))*AV60*I60),2)*BB60),2)+ROUND((ROUND(((AE60-((EU60*1.2)))*AV60*I60),2)*BS60),2)) -> 0 | R60: =(ROUND((ROUND((((EU60*1.2))*AV60*I60),2)*BS60),2)+ROUND((ROUND(((AE60-((EU60*1.2)))*AV60*I60),2)*BS60),2)) -> 0 | S60: =ROUND((ROUND((AF60*AV60*I60),2)*BA60),2) -> 3194.56 | T60: =ROUND(CU60*I60,2) -> 0 | U60: =CV60*I60 -> 303.66384 | V60: =CW60*I60 -> 0 | W60: =ROUND(CX60*I60,2) -> 0 | X60: =(ROUND((((S60+ROUND((ROUND((((EU60*1.2))*AV60*I60),2)*BS60),2))*AT60)/100),2)+ROUND(((ROUND((ROUND(((AE60-((EU60*1.2)))*AV60*I60),2)*BS60),2)*AT60)/100),2)) -> 2907.05 | Y60: =(ROUND((((S60+ROUND((ROUND((((EU60*1.2))*AV60*I60),2)*BS60),2))*AU60)/100),2)+ROUND(((ROUND((ROUND(((AE60-((EU60*1.2)))*AV60*I60),2)*BS60),2)*AU60)/100),2)) -> 1533.39 | AA60: 55937296 | AB60: =ROUND((AC60+AD60+AF60),6) -> 384.276 | AC60: =ROUND(((ES60*1)),6) -> 0 | AD60: =ROUND(((((ET60*1.2))-((EU60*1.2)))+AE60),6) -> 0 | AE60: =ROUND(((EU60*1.2)),6) -> 0 | AF60: =ROUND(((EV60*1.2)),6) -> 384.276 | AG60: =ROUND((AP60),6) -> 0 | AH60: =((EW60*1.2)) -> 36.528 | AI60: =((EX60*1.2)) -> 0 | AJ60: =(AS60) -> 0 | AK60: 320.23 | AL60: 0 | AM60: 0 | AN60: 0 | AO60: 320.23 | AP60: 0 | AQ60: 30.44 | AR60: 0 | AS60: 0 | AT60: 91 | AU60: 48 | AV60: 1.047 | AW60: 1 | AZ60: 1 | BA60: 1 | BB60: 1 | BC60: 1 | BH60: 0 | BI60: 1 | BJ60: ТСН-2001.6. Доп. 1-42. Сб. 67, т. 5, поз. 12 | BM60: 106 | BN60: 0 | BO60: 6.67-5-12 | BP60: 1 | BQ60: 60 | BR60: 0 | BS60: 1 | BT60: 1 | BU60: 1 | BV60: 1 | BW60: 1 | BX60: 1 | BZ60: 91 | CA60: 48 | CE60: 1566 | CF60: 0 | CG60: 0 | CM60: 0 | CN60: Поправка: Гл.12.Прил.8.п.8. 3_12.00.01.11.001 Наименование: При наличии напряженных и стесненных условий производства работ (стесненность, сложность складирования и транспортной логистики и т.п.) для объектов, расположенных в пределах круговой магистральной системы улиц "Садовое кольцо" города Москвы | CO60: 0 | CP60: =(P60+Q60+S60) -> 3194.56 | CQ60: =ROUND((ROUND((AC60*AW60*1),2)*BC60),2) -> 0 | CR60: =(ROUND((ROUND((((ET60*1.2))*AV60*1),2)*BB60),2)+ROUND((ROUND(((AE60-((EU60*1.2)))*AV60*1),2)*BS60),2)) -> 0 | CS60: =(ROUND((ROUND((((EU60*1.2))*AV60*1),2)*BS60),2)+ROUND((ROUND(((AE60-((EU60*1.2)))*AV60*1),2)*BS60),2)) -> 0 | CT60: =ROUND((ROUND((AF60*AV60*1),2)*BA60),2) -> 402.34 | CU60: =AG60 -> 0 | CV60: =(AH60*AV60) -> 38.244816 | CW60: =AI60 -> 0 | CX60: =AJ60 -> 0 | CY60: =(ROUND((((S60+ROUND((ROUND((((EU60*1.2))*AV60*1),2)*BS60),2))*AT60)/100),2)+ROUND(((ROUND((ROUND(((AE60-((EU60*1.2)))*AV60*1),2)*BS60),2)*AT60)/100),2)) -> 2907.05 | CZ60: =(ROUND((((S60+ROUND((ROUND((((EU60*1.2))*AV60*1),2)*BS60),2))*AU60)/100),2)+ROUND(((ROUND((ROUND(((AE60-((EU60*1.2)))*AV60*1),2)*BS60),2)*AU60)/100),2)) -> 1533.39 | DB60: 71 | DD60: *1 | DE60: *1,2 | DF60: *1,2 | DG60: *1,2 | DI60: *1,2 | DJ60: *1,2 | DN60: 0 | DO60: 0 | DP60: 1 | DQ60: 1 | DU60: 1003 | DV60: 100 м | DW60: 100 м | DX60: 100 | EE60: 55393738 | EF60: 60 | EG60: Ремонтно-строительные работы | EH60: 0 | EJ60: 1 | EK60: 106 | EL60: ТСН-2001.6-67. Электромонтажные работы | EM60: ТСН-2001.6-67-1 | EO60: Поправка: Гл.12.Прил.8.п.8. 3_12.00.01.11.001 | EQ60: 0 | ER60: 320.23 | ES60: 0 | ET60: 0 | EU60: 0 | EV60: 320.23 | EW60: 30.44 | EX60: 0 | EY60: 0 | FQ60: 0 | FR60: 0 | FS60: 0 | FX60: 91 | FY60: 48 | GD60: 1 | GF60: -1527708470 | GG60: 2 | GH60: 1 | GI60: 2 | GJ60: 0 | GK60: 0 | GL60: =ROUND(IF(AND(BH60=3,BI60=3,FS60<>0),P60,0),2) -> 0 | GM60: =ROUND(O60+X60+Y60,2)+GX60 -> 7635 | GN60: =IF(OR(BI60=0,BI60=1),GM60-GX60,0) -> 7635 | GO60: =IF(BI60=2,GM60-GX60,0) -> 0 | GP60: =IF(BI60=4,GM60-GX60,0) -> 0 | GR60: 0 | GS60: 3 | GT60: 0 | GV60: =ROUND((GT60),6) -> 0 | GW60: 1 | GX60: =ROUND(HC60*I60,2) -> 0 | HA60: 0 | HB60: 0 | HC60: =GV60*GW60 -> 0 | HS60: 0 | IK60: 0
A61: 17 | B61: 1 | C61: =ROW(SmtRes!A118) -> 118 | D61: =ROW(EtalonRes!A154) -> 154 | E61: 17 | F61: 6.67-5-12 | G61: Демонтаж трубных проводок, трубы в борозде диаметром 25 мм | H61: 100 м | I61: =ROUND((642+150+2)/100,9) -> 7.94 | J61: 0 | K61: =ROUND((642+150+2)/100,9) -> 7.94 | O61: =ROUND(CP61,2) -> 180013.46 | P61: =ROUND((ROUND((AC61*AW61*I61),2)*BC61),2) -> 0 | Q61: =(ROUND((ROUND((((ET61*1.2))*AV61*I61),2)*BB61),2)+ROUND((ROUND(((AE61-((EU61*1.2)))*AV61*I61),2)*BS61),2)) -> 0 | R61: =(ROUND((ROUND((((EU61*1.2))*AV61*I61),2)*BS61),2)+ROUND((ROUND(((AE61-((EU61*1.2)))*AV61*I61),2)*BS61),2)) -> 0 | S61: =ROUND((ROUND((AF61*AV61*I61),2)*BA61),2) -> 180013.46 | T61: =ROUND(CU61*I61,2) -> 0 | U61: =CV61*I61 -> 303.66384 | V61: =CW61*I61 -> 0 | W61: =ROUND(CX61*I61,2) -> 0 | X61: =(ROUND((((S61+ROUND((ROUND((((EU61*1.2))*AV61*I61),2)*BS61),2))*AT61)/100),2)+ROUND(((ROUND((ROUND(((AE61-((EU61*1.2)))*AV61*I61),2)*BS61),2)*AT61)/100),2)) -> 163812.25 | Y61: =(ROUND((((S61+ROUND((ROUND((((EU61*1.2))*AV61*I61),2)*BS61),2))*AU61)/100),2)+ROUND(((ROUND((ROUND(((AE61-((EU61*1.2)))*AV61*I61),2)*BS61),2)*AU61)/100),2)) -> 86406.46 | AA61: 55937298 | AB61: =ROUND((AC61+AD61+AF61),6) -> 384.276 | AC61: =ROUND(((ES61*1)),6) -> 0 | AD61: =ROUND(((((ET61*1.2))-((EU61*1.2)))+AE61),6) -> 0 | AE61: =ROUND(((EU61*1.2)),6) -> 0 | AF61: =ROUND(((EV61*1.2)),6) -> 384.276 | AG61: =ROUND((AP61),6) -> 0 | AH61: =((EW61*1.2)) -> 36.528 | AI61: =((EX61*1.2)) -> 0 | AJ61: =(AS61) -> 0 | AK61: 320.23 | AL61: 0 | AM61: 0 | AN61: 0 | AO61: 320.23 | AP61: 0 | AQ61: 30.44 | AR61: 0 | AS61: 0 | AT61: 91 | AU61: 48 | AV61: 1.047 | AW61: 1 | AZ61: 1 | BA61: 56.35 | BB61: 1 | BC61: 1 | BH61: 0 | BI61: 1 | BJ61: ТСН-2001.6. Доп. 1-42. Сб. 67, т. 5, поз. 12 | BM61: 106 | BN61: 0 | BO61: 6.67-5-12 | BP61: 1 | BQ61: 60 | BR61: 0 | BS61: 56.35 | BT61: 1 | BU61: 1 | BV61: 1 | BW61: 1 | BX61: 1 | BZ61: 91 | CA61: 48 | CE61: 1566 | CF61: 0 | CG61: 0 | CM61: 0 | CN61: Поправка: Гл.12.Прил.8.п.8. 3_12.00.01.11.001 Наименование: При наличии напряженных и стесненных условий производства работ (стесненность, сложность складирования и транспортной логистики и т.п.) для объектов, расположенных в пределах круговой магистральной системы улиц "Садовое кольцо" города Москвы | CO61: 0 | CP61: =(P61+Q61+S61) -> 180013.46 | CQ61: =ROUND((ROUND((AC61*AW61*1),2)*BC61),2) -> 0 | CR61: =(ROUND((ROUND((((ET61*1.2))*AV61*1),2)*BB61),2)+ROUND((ROUND(((AE61-((EU61*1.2)))*AV61*1),2)*BS61),2)) -> 0 | CS61: =(ROUND((ROUND((((EU61*1.2))*AV61*1),2)*BS61),2)+ROUND((ROUND(((AE61-((EU61*1.2)))*AV61*1),2)*BS61),2)) -> 0 | CT61: =ROUND((ROUND((AF61*AV61*1),2)*BA61),2) -> 22671.86 | CU61: =AG61 -> 0 | CV61: =(AH61*AV61) -> 38.244816 | CW61: =AI61 -> 0 | CX61: =AJ61 -> 0 | CY61: =(ROUND((((S61+ROUND((ROUND((((EU61*1.2))*AV61*1),2)*BS61),2))*AT61)/100),2)+ROUND(((ROUND((ROUND(((AE61-((EU61*1.2)))*AV61*1),2)*BS61),2)*AT61)/100),2)) -> 163812.25 | CZ61: =(ROUND((((S61+ROUND((ROUND((((EU61*1.2))*AV61*1),2)*BS61),2))*AU61)/100),2)+ROUND(((ROUND((ROUND(((AE61-((EU61*1.2)))*AV61*1),2)*BS61),2)*AU61)/100),2)) -> 86406.46 | DB61: 72 | DD61: *1 | DE61: *1,2 | DF61: *1,2 | DG61: *1,2 | DI61: *1,2 | DJ61: *1,2 | DN61: 0 | DO61: 0 | DP61: 1 | DQ61: 1 | DU61: 1003 | DV61: 100 м | DW61: 100 м | DX61: 100 | EE61: 55393738 | EF61: 60 | EG61: Ремонтно-строительные работы | EH61: 0 | EJ61: 1 | EK61: 106 | EL61: ТСН-2001.6-67. Электромонтажные работы | EM61: ТСН-2001.6-67-1 | EO61: Поправка: Гл.12.Прил.8.п.8. 3_12.00.01.11.001 | EQ61: 0 | ER61: 320.23 | ES61: 0 | ET61: 0 | EU61: 0 | EV61: 320.23 | EW61: 30.44 | EX61: 0 | EY61: 0 | FQ61: 0 | FR61: 0 | FS61: 0 | FX61: 91 | FY61: 48 | GD61: 1 | GF61: -1527708470 | GG61: 2 | GH61: 1 | GI61: 2 | GJ61: 0 | GK61: 0 | GL61: =ROUND(IF(AND(BH61=3,BI61=3,FS61<>0),P61,0),2) -> 0 | GM61: =ROUND(O61+X61+Y61,2)+GX61 -> 430232.17 | GN61: =IF(OR(BI61=0,BI61=1),GM61-GX61,0) -> 430232.17 | GO61: =IF(BI61=2,GM61-GX61,0) -> 0 | GP61: =IF(BI61=4,GM61-GX61,0) -> 0 | GR61: 0 | GS61: 3 | GT61: 0 | GV61: =ROUND((GT61),6) -> 0 | GW61: 1 | GX61: =ROUND(HC61*I61,2) -> 0 | HA61: 0 | HB61: 0 | HC61: =GV61*GW61 -> 0 | HS61: 0 | IK61: 0
A63: 51 | B63: =B24 -> 1 | C63: =A24 -> 4 | D63: =ROW(A24) -> 24 | F63: =IF(F24<>"",F24,"") -> Новый раздел | G63: =IF(G24<>"",G24,"") -> Демонтажные работы | H63: 0 | O63: =ROUND(AB63,2) -> 5104.31 | P63: =ROUND(AC63,2) -> 137.83 | Q63: =ROUND(AD63,2) -> 54.29 | R63: =ROUND(AE63,2) -> 7.99 | S63: =ROUND(AF63,2) -> 4912.19 | T63: =ROUND(AG63,2) -> 0 | U63: =AH63 -> 459.3159 | V63: =AI63 -> 0 | W63: =ROUND(AJ63,2) -> 0 | X63: =ROUND(AK63,2) -> 4495.1 | Y63: =ROUND(AL63,2) -> 2381.61 | AB63: =ROUND(SUMIF(AA28:AA61,"=55937296",O28:O61),2) -> 5104.31 | AC63: =ROUND(SUMIF(AA28:AA61,"=55937296",P28:P61),2) -> 137.83 | AD63: =ROUND(SUMIF(AA28:AA61,"=55937296",Q28:Q61),2) -> 54.29 | AE63: =ROUND(SUMIF(AA28:AA61,"=55937296",R28:R61),2) -> 7.99 | AF63: =ROUND(SUMIF(AA28:AA61,"=55937296",S28:S61),2) -> 4912.19 | AG63: =ROUND(SUMIF(AA28:AA61,"=55937296",T28:T61),2) -> 0 | AH63: =SUMIF(AA28:AA61,"=55937296",U28:U61) -> 459.3159 | AI63: =SUMIF(AA28:AA61,"=55937296",V28:V61) -> 0 | AJ63: =ROUND(SUMIF(AA28:AA61,"=55937296",W28:W61),2) -> 0 | AK63: =ROUND(SUMIF(AA28:AA61,"=55937296",X28:X61),2) -> 4495.1 | AL63: =ROUND(SUMIF(AA28:AA61,"=55937296",Y28:Y61),2) -> 2381.61 | AO63: =ROUND(BX63,2) -> 0 | AP63: =ROUND(BY63,2) -> 0 | AQ63: =ROUND(BZ63,2) -> 0 | AR63: =ROUND(CA63,2) -> 11981.02 | AS63: =ROUND(CB63,2) -> 10813.8 | AT63: =ROUND(CC63,2) -> 1167.22 | AU63: =ROUND(CD63,2) -> 0 | AV63: =ROUND(CE63,2) -> 137.83 | ... BD63: =ROUND(CM63,2) -> 0 | BX63: =ROUND(SUMIF(AA28:AA61,"=55937296",FQ28:FQ61),2) -> 0 | BY63: =ROUND(SUMIF(AA28:AA61,"=55937296",FR28:FR61),2) -> 0 | BZ63: =ROUND(SUMIF(AA28:AA61,"=55937296",GL28:GL61),2) -> 0 | CA63: =ROUND(SUMIF(AA28:AA61,"=55937296",GM28:GM61),2) -> 11981.02 | CB63: =ROUND(SUMIF(AA28:AA61,"=55937296",GN28:GN61),2) -> 10813.8 | CC63: =ROUND(SUMIF(AA28:AA61,"=55937296",GO28:GO61),2) -> 1167.22 | CD63: =ROUND(SUMIF(AA28:AA61,"=55937296",GP28:GP61),2) -> 0 | CE63: =AC63-BX63 -> 137.83 | CF63: =AC63-BY63 -> 137.83 | CG63: =BX63-BZ63 -> 0 | CH63: =AC63-BX63-BY63+BZ63 -> 137.83 | CI63: =BY63-BZ63 -> 0 | CJ63: =ROUND(SUMIF(AA28:AA61,"=55937296",GX28:GX61),2) -> 0 | CK63: =ROUND(SUMIF(AA28:AA61,"=55937296",GY28:GY61),2) -> 0 | CL63: =ROUND(SUMIF(AA28:AA61,"=55937296",GZ28:GZ61),2) -> 0 | CM63: =ROUND(SUMIF(AA28:AA61,"=55937296",HD28:HD61),2) -> 0 | DG63: =ROUND(DT63,2) -> 278563.54 | DH63: =ROUND(DU63,2) -> 848.58 | DI63: =ROUND(DV63,2) -> 913.05 | DJ63: =ROUND(DW63,2) -> 450.24 | DK63: =ROUND(DX63,2) -> 276801.91 | DL63: =ROUND(DY63,2) -> 0 | DM63: =DZ63 -> 459.3159 | DN63: =EA63 -> 0 | DO63: =ROUND(EB63,2) -> 0 | DP63: =ROUND(EC63,2) -> 253299.21 | DQ63: =ROUND(ED63,2) -> 134204.45 | DT63: =ROUND(SUMIF(AA28:AA61,"=55937298",O28:O61),2) -> 278563.54 | DU63: =ROUND(SUMIF(AA28:AA61,"=55937298",P28:P61),2) -> 848.58 | DV63: =ROUND(SUMIF(AA28:AA61,"=55937298",Q28:Q61),2) -> 913.05 | DW63: =ROUND(SUMIF(AA28:AA61,"=55937298",R28:R61),2) -> 450.24 | DX63: =ROUND(SUMIF(AA28:AA61,"=55937298",S28:S61),2) -> 276801.91 | DY63: =ROUND(SUMIF(AA28:AA61,"=55937298",T28:T61),2) -> 0 | DZ63: =SUMIF(AA28:AA61,"=55937298",U28:U61) -> 459.3159 | EA63: =SUMIF(AA28:AA61,"=55937298",V28:V61) -> 0 | EB63: =ROUND(SUMIF(AA28:AA61,"=55937298",W28:W61),2) -> 0 | EC63: =ROUND(SUMIF(AA28:AA61,"=55937298",X28:X61),2) -> 253299.21 | ED63: =ROUND(SUMIF(AA28:AA61,"=55937298",Y28:Y61),2) -> 134204.45 | EG63: =ROUND(FP63,2) -> 0 | EH63: =ROUND(FQ63,2) -> 0 | EI63: =ROUND(FR63,2) -> 0 | EJ63: =ROUND(FS63,2) -> 666067.2 | EK63: =ROUND(FT63,2) -> 600506.53 | EL63: =ROUND(FU63,2) -> 65560.67 | EM63: =ROUND(FV63,2) -> 0 | EN63: =ROUND(FW63,2) -> 848.58 | ... EV63: =ROUND(GE63,2) -> 0 | FP63: =ROUND(SUMIF(AA28:AA61,"=55937298",FQ28:FQ61),2) -> 0 | FQ63: =ROUND(SUMIF(AA28:AA61,"=55937298",FR28:FR61),2) -> 0 | FR63: =ROUND(SUMIF(AA28:AA61,"=55937298",GL28:GL61),2) -> 0 | FS63: =ROUND(SUMIF(AA28:AA61,"=55937298",GM28:GM61),2) -> 666067.2 | FT63: =ROUND(SUMIF(AA28:AA61,"=55937298",GN28:GN61),2) -> 600506.53 | FU63: =ROUND(SUMIF(AA28:AA61,"=55937298",GO28:GO61),2) -> 65560.67 | FV63: =ROUND(SUMIF(AA28:AA61,"=55937298",GP28:GP61),2) -> 0 | FW63: =DU63-FP63 -> 848.58 | FX63: =DU63-FQ63 -> 848.58 | FY63: =FP63-FR63 -> 0 | FZ63: =DU63-FP63-FQ63+FR63 -> 848.58 | GA63: =FQ63-FR63 -> 0 | GB63: =ROUND(SUMIF(AA28:AA61,"=55937298",GX28:GX61),2) -> 0 | GC63: =ROUND(SUMIF(AA28:AA61,"=55937298",GY28:GY61),2) -> 0 | GD63: =ROUND(SUMIF(AA28:AA61,"=55937298",GZ28:GZ61),2) -> 0 | GE63: =ROUND(SUMIF(AA28:AA61,"=55937298",HD28:HD61),2) -> 0 | GX63: 0
A65: 50 | B65: 0 | C65: 0 | D65: 1 | E65: 201 | F65: =ROUND(Source!O63,O65) -> 5104.31 | G65: ПЗ | H65: Прямые затраты | K65: 201 | L65: 1 | M65: 3 | O65: 2 | P65: =ROUND(Source!DG63,O65) -> 278563.54 | W65: 5104.31 | X65: 1 | Y65: 5104.31 | Z65: 278563.54 | AA65: 1 | AB65: 278563.54
A66: 50 | B66: 0 | C66: 0 | D66: 1 | E66: 202 | F66: =ROUND(Source!P63,O66) -> 137.83 | G66: СтМатОб | H66: Стоимость материальных ресурсов (всего) | K66: 202 | L66: 2 | M66: 3 | O66: 2 | P66: =ROUND(Source!DH63,O66) -> 848.58 | W66: 137.83 | X66: 1 | Y66: 137.83 | Z66: 848.58 | AA66: 1 | AB66: 848.58
A67: 50 | B67: 0 | C67: 0 | D67: 1 | E67: 222 | F67: =ROUND(Source!AO63,O67) -> 0 | G67: СтМатОбЗак | H67: Стоимость материалов и оборудования заказчика | K67: 222 | L67: 3 | M67: 3 | O67: 2 | P67: =ROUND(Source!EG63,O67) -> 0 | W67: 0 | X67: 1 | Y67: 0 | Z67: 0 | AA67: 1 | AB67: 0
A68: 50 | B68: 0 | C68: 0 | D68: 1 | E68: 225 | F68: =ROUND(Source!AV63,O68) -> 137.83 | G68: СтМатОбПод | H68: Стоимость материалов и оборудования подрядчика | K68: 225 | L68: 4 | M68: 3 | O68: 2 | P68: =ROUND(Source!EN63,O68) -> 848.58 | W68: 137.83 | X68: 1 | Y68: 137.83 | Z68: 848.58 | AA68: 1 | AB68: 848.58
A69: 50 | B69: 0 | C69: 0 | D69: 1 | E69: 226 | F69: =ROUND(Source!AW63,O69) -> 137.83 | G69: СтМат | H69: Стоимость материалов (всего) | K69: 226 | L69: 5 | M69: 3 | O69: 2 | P69: =ROUND(Source!EO63,O69) -> 848.58 | W69: 137.83 | X69: 1 | Y69: 137.83 | Z69: 848.58 | AA69: 1 | AB69: 848.58
A70: 50 | B70: 0 | C70: 0 | D70: 1 | E70: 227 | F70: =ROUND(Source!AX63,O70) -> 0 | G70: СтМатЗак | H70: Стоимость материалов заказчика | K70: 227 | L70: 6 | M70: 3 | O70: 2 | P70: =ROUND(Source!EP63,O70) -> 0 | W70: 0 | X70: 1 | Y70: 0 | Z70: 0 | AA70: 1 | AB70: 0
A71: 50 | B71: 0 | C71: 0 | D71: 1 | E71: 228 | F71: =ROUND(Source!AY63,O71) -> 137.83 | G71: СтМатПод | H71: Стоимость материалов подрядчика | K71: 228 | L71: 7 | M71: 3 | O71: 2 | P71: =ROUND(Source!EQ63,O71) -> 848.58 | W71: 137.83 | X71: 1 | Y71: 137.83 | Z71: 848.58 | AA71: 1 | AB71: 848.58
A72: 50 | B72: 0 | C72: 0 | D72: 1 | E72: 216 | F72: =ROUND(Source!AP63,O72) -> 0 | G72: Оборуд | H72: Стоимость оборудования (всего) | K72: 216 | L72: 8 | M72: 3 | O72: 2 | P72: =ROUND(Source!EH63,O72) -> 0 | W72: 0 | X72: 1 | Y72: 0 | Z72: 0 | AA72: 1 | AB72: 0
A73: 50 | B73: 0 | C73: 0 | D73: 1 | E73: 223 | F73: =ROUND(Source!AQ63,O73) -> 0 | G73: ОборудЗак | H73: Стоимость оборудования заказчика | K73: 223 | L73: 9 | M73: 3 | O73: 2 | P73: =ROUND(Source!EI63,O73) -> 0 | W73: 0 | X73: 1 | Y73: 0 | Z73: 0 | AA73: 1 | AB73: 0
A74: 50 | B74: 0 | C74: 0 | D74: 1 | E74: 229 | F74: =ROUND(Source!AZ63,O74) -> 0 | G74: ОборудПод | H74: Стоимость оборудования подрядчика | K74: 229 | L74: 10 | M74: 3 | O74: 2 | P74: =ROUND(Source!ER63,O74) -> 0 | W74: 0 | X74: 1 | Y74: 0 | Z74: 0 | AA74: 1 | AB74: 0
A75: 50 | B75: 0 | C75: 0 | D75: 1 | E75: 203 | F75: =ROUND(Source!Q63,O75) -> 54.29 | G75: ЭММ | H75: Эксплуатация машин | K75: 203 | L75: 11 | M75: 3 | O75: 2 | P75: =ROUND(Source!DI63,O75) -> 913.05 | W75: 54.29 | X75: 1 | Y75: 54.29 | Z75: 913.05 | AA75: 1 | AB75: 913.05
A76: 50 | B76: 0 | C76: 0 | D76: 1 | E76: 231 | F76: =ROUND(Source!BB63,O76) -> 0 | G76: ЭММсНРиСП | H76: Эксплуатация машин по ТСН-2001.16 | K76: 231 | L76: 12 | M76: 3 | O76: 2 | P76: =ROUND(Source!ET63,O76) -> 0 | W76: 0 | X76: 1 | Y76: 0 | Z76: 0 | AA76: 1 | AB76: 0
A77: 50 | B77: 0 | C77: 0 | D77: 1 | E77: 204 | F77: =ROUND(Source!R63,O77) -> 7.99 | G77: ЗПМ | H77: ЗП машинистов | K77: 204 | L77: 13 | M77: 3 | O77: 2 | P77: =ROUND(Source!DJ63,O77) -> 450.24 | W77: 7.99 | X77: 1 | Y77: 7.99 | Z77: 450.24 | AA77: 1 | AB77: 450.24
A78: 50 | B78: 0 | C78: 0 | D78: 1 | E78: 205 | F78: =ROUND(Source!S63,O78) -> 4912.19 | G78: ОЗП | H78: Основная ЗП рабочих | K78: 205 | L78: 14 | M78: 3 | O78: 2 | P78: =ROUND(Source!DK63,O78) -> 276801.91 | W78: 4912.19 | X78: 1 | Y78: 4912.19 | Z78: 276801.91 | AA78: 1 | AB78: 276801.91
A79: 50 | B79: 0 | C79: 0 | D79: 1 | E79: 232 | F79: =ROUND(Source!BC63,O79) -> 0 | G79: ОЗПсНРиСП | H79: Основная ЗП рабочих по ТСН-2001.16 | K79: 232 | L79: 15 | M79: 3 | O79: 2 | P79: =ROUND(Source!EU63,O79) -> 0 | W79: 0 | X79: 1 | Y79: 0 | Z79: 0 | AA79: 1 | AB79: 0
A80: 50 | B80: 0 | C80: 0 | D80: 1 | E80: 214 | F80: =ROUND(Source!AS63,O80) -> 10813.8 | G80: Строит | H80: Строительные работы с НР и СП | K80: 214 | L80: 16 | M80: 3 | O80: 2 | P80: =ROUND(Source!EK63,O80) -> 600506.53 | W80: 10813.8 | X80: 1 | Y80: 10813.8 | Z80: 600506.53 | AA80: 1 | AB80: 600506.53
A81: 50 | B81: 0 | C81: 0 | D81: 1 | E81: 215 | F81: =ROUND(Source!AT63,O81) -> 1167.22 | G81: Монтаж | H81: Монтажные работы с НР и СП | K81: 215 | L81: 17 | M81: 3 | O81: 2 | P81: =ROUND(Source!EL63,O81) -> 65560.67 | W81: 1167.22 | X81: 1 | Y81: 1167.22 | Z81: 65560.67 | AA81: 1 | AB81: 65560.67
A82: 50 | B82: 0 | C82: 0 | D82: 1 | E82: 217 | F82: =ROUND(Source!AU63,O82) -> 0 | G82: Прочие | H82: Прочие работы с НР и СП | K82: 217 | L82: 18 | M82: 3 | O82: 2 | P82: =ROUND(Source!EM63,O82) -> 0 | W82: 0 | X82: 1 | Y82: 0 | Z82: 0 | AA82: 1 | AB82: 0
A83: 50 | B83: 0 | C83: 0 | D83: 1 | E83: 230 | F83: =ROUND(Source!BA63,O83) -> 0 | G83: ПрочиеЗатр | H83: Прочие затраты по ТСН-2001.16 | K83: 230 | L83: 19 | M83: 3 | O83: 2 | P83: =ROUND(Source!ES63,O83) -> 0 | W83: 0 | X83: 1 | Y83: 0 | Z83: 0 | AA83: 1 | AB83: 0
A84: 50 | B84: 0 | C84: 0 | D84: 1 | E84: 206 | F84: =ROUND(Source!T63,O84) -> 0 | G84: ВозврМат | H84: Возврат материалов | K84: 206 | L84: 20 | M84: 3 | O84: 2 | P84: =ROUND(Source!DL63,O84) -> 0 | W84: 0 | X84: 1 | Y84: 0 | Z84: 0 | AA84: 1 | AB84: 0
A85: 50 | B85: 0 | C85: 0 | D85: 1 | E85: 207 | F85: =Source!U63 -> 459.3159 | G85: ТрудСтр | H85: Трудозатраты строителей | K85: 207 | L85: 21 | M85: 3 | O85: -1 | P85: =Source!DM63 -> 459.3159 | W85: 459.3159 | X85: 1 | Y85: 459.3159 | Z85: 459.3159 | AA85: 1 | AB85: 459.3159
A86: 50 | B86: 0 | C86: 0 | D86: 1 | E86: 208 | F86: =Source!V63 -> 0 | G86: ТрудМаш | H86: Трудозатраты машинистов | K86: 208 | L86: 22 | M86: 3 | O86: -1 | P86: =Source!DN63 -> 0 | W86: 0 | X86: 1 | Y86: 0 | Z86: 0 | AA86: 1 | AB86: 0
A87: 50 | B87: 0 | C87: 0 | D87: 1 | E87: 209 | F87: =ROUND(Source!W63,O87) -> 0 | G87: ТранспМат | H87: Транспорт материалов | K87: 209 | L87: 23 | M87: 3 | O87: 2 | P87: =ROUND(Source!DO63,O87) -> 0 | W87: 0 | X87: 1 | Y87: 0 | Z87: 0 | AA87: 1 | AB87: 0
A88: 50 | B88: 0 | C88: 0 | D88: 1 | E88: 233 | F88: =ROUND(Source!BD63,O88) -> 0 | G88: Перевозка | H88: Перевозка грузов | K88: 233 | L88: 24 | M88: 3 | O88: 2 | P88: =ROUND(Source!EV63,O88) -> 0 | W88: 0 | X88: 1 | Y88: 0 | Z88: 0 | AA88: 1 | AB88: 0
A89: 50 | B89: 0 | C89: 0 | D89: 1 | E89: 210 | F89: =ROUND(Source!X63,O89) -> 4495.1 | G89: НР | H89: Накладные расходы | K89: 210 | L89: 25 | M89: 3 | O89: 2 | P89: =ROUND(Source!DP63,O89) -> 253299.21 | W89: 4495.1 | X89: 1 | Y89: 4495.1 | Z89: 253299.21 | AA89: 1 | AB89: 253299.21
A90: 50 | B90: 0 | C90: 0 | D90: 1 | E90: 211 | F90: =ROUND(Source!Y63,O90) -> 2381.61 | G90: СмПриб | H90: Сметная прибыль | K90: 211 | L90: 26 | M90: 3 | O90: 2 | P90: =ROUND(Source!DQ63,O90) -> 134204.45 | W90: 2381.61 | X90: 1 | Y90: 2381.61 | Z90: 134204.45 | AA90: 1 | AB90: 134204.45
A91: 50 | B91: 0 | C91: 0 | D91: 1 | E91: 224 | F91: =ROUND(Source!AR63,O91) -> 11981.02 | G91: Всего | H91: Всего с НР и СП | K91: 224 | L91: 27 | M91: 3 | O91: 2 | P91: =ROUND(Source!EJ63,O91) -> 666067.2 | W91: 11981.02 | X91: 1 | Y91: 11981.02 | Z91: 666067.2 | AA91: 1 | AB91: 666067.2
A93: 4 | B93: 1 | D93: =ROW(A180) -> 180 | F93: 1 | G93: Оборудование | I93: 0 | K93: -1 | S93: 0 | T93: 0 | V93: 0 | BX93: 0 | CJ93: 0
A95: 52 | B95: =B180 -> 1 | C95: =C180 -> 4 | D95: =D180 -> 93 | E95: =E180 -> 0 | F95: =F180 -> 1 | G95: =G180 -> Оборудование | O95: =O180 -> 301197.34 | P95: =P180 -> 299250.2 | Q95: =Q180 -> 99.28 | R95: =R180 -> 14.41 | S95: =S180 -> 1847.86 | T95: =T180 -> 0 | U95: =U180 -> 141.89155 | V95: =V180 -> 0 | ... GX95: =GX180 -> 0
A97: 17 | B97: 1 | C97: =ROW(SmtRes!A119) -> 119 | D97: =ROW(EtalonRes!A155) -> 155 | E97: 18 | F97: 4.10-80-5 | G97: Аппараты приемные, приборы ПС приемно-контрольные, пусковые, прибор ПС на 1 луч | H97: 1 ШТ. | I97: 8 | J97: 0 | K97: 8 | O97: =ROUND(CP97,2) -> 259.52 | P97: =ROUND((ROUND((AC97*AW97*I97),2)*BC97),2) -> 27.44 | Q97: =(ROUND((ROUND((((ET97*1.2))*AV97*I97),2)*BB97),2)+ROUND((ROUND(((AE97-((EU97*1.2)))*AV97*I97),2)*BS97),2)) -> 0.5 | R97: =(ROUND((ROUND((((EU97*1.2))*AV97*I97),2)*BS97),2)+ROUND((ROUND(((AE97-((EU97*1.2)))*AV97*I97),2)*BS97),2)) -> 0.1 | S97: =ROUND((ROUND((AF97*AV97*I97),2)*BA97),2) -> 231.58 | T97: =ROUND(CU97*I97,2) -> 0 | U97: =CV97*I97 -> 18.09216 | V97: =CW97*I97 -> 0 | W97: =ROUND(CX97*I97,2) -> 0 | X97: =(ROUND((((S97+ROUND((ROUND((((EU97*1.2))*AV97*I97),2)*BS97),2))*AT97)/100),2)+ROUND(((ROUND((ROUND(((AE97-((EU97*1.2)))*AV97*I97),2)*BS97),2)*AT97)/100),2)) -> 208.51 | Y97: =(ROUND((((S97+ROUND((ROUND((((EU97*1.2))*AV97*I97),2)*BS97),2))*AU97)/100),2)+ROUND(((ROUND((ROUND(((AE97-((EU97*1.2)))*AV97*I97),2)*BS97),2)*AU97)/100),2)) -> 106.57 | AA97: 55937296 | AB97: =ROUND((AC97+AD97+AF97),6) -> 31.138 | AC97: =ROUND(((ES97*1)),6) -> 3.43 | AD97: =ROUND(((((ET97*1.2))-((EU97*1.2)))+AE97),6) -> 0.06 | AE97: =ROUND(((EU97*1.2)),6) -> 0.012 | AF97: =ROUND(((EV97*1.2)),6) -> 27.648 | AG97: =ROUND((AP97),6) -> 0 | AH97: =((EW97*1.2)) -> 2.16 | AI97: =((EX97*1.2)) -> 0 | AJ97: =(AS97) -> 0 | AK97: 26.52 | AL97: 3.43 | AM97: 0.05 | AN97: 0.01 | AO97: 23.04 | AP97: 0 | AQ97: 1.8 | AR97: 0 | AS97: 0 | AT97: 90 | AU97: 46 | AV97: 1.047 | AW97: 1 | AZ97: 1 | BA97: 1 | BB97: 1 | BC97: 1 | BH97: 0 | BI97: 2 | BJ97: ТСН-2001.4. Доп. 1-42. Сб. 10, т. 80, поз. 5 | BM97: 68 | BN97: 0 | BO97: 4.10-80-5 | BP97: 1 | BQ97: 40 | BR97: 0 | BS97: 1 | BT97: 1 | BU97: 1 | BV97: 1 | BW97: 1 | BX97: 1 | BZ97: 90 | CA97: 46 | CE97: 1566 | CF97: 0 | CG97: 0 | CM97: 0 | CN97: Поправка: Гл.12.Прил.8.п.8. 3_12.00.01.11.001 Наименование: При наличии напряженных и стесненных условий производства работ (стесненность, сложность складирования и транспортной логистики и т.п.) для объектов, расположенных в пределах круговой магистральной системы улиц "Садовое кольцо" города Москвы | CO97: 0 | CP97: =(P97+Q97+S97) -> 259.52 | CQ97: =ROUND((ROUND((AC97*AW97*1),2)*BC97),2) -> 3.43 | CR97: =(ROUND((ROUND((((ET97*1.2))*AV97*1),2)*BB97),2)+ROUND((ROUND(((AE97-((EU97*1.2)))*AV97*1),2)*BS97),2)) -> 0.06 | CS97: =(ROUND((ROUND((((EU97*1.2))*AV97*1),2)*BS97),2)+ROUND((ROUND(((AE97-((EU97*1.2)))*AV97*1),2)*BS97),2)) -> 0.01 | CT97: =ROUND((ROUND((AF97*AV97*1),2)*BA97),2) -> 28.95 | CU97: =AG97 -> 0 | CV97: =(AH97*AV97) -> 2.26152 | CW97: =AI97 -> 0 | CX97: =AJ97 -> 0 | CY97: =(ROUND((((S97+ROUND((ROUND((((EU97*1.2))*AV97*1),2)*BS97),2))*AT97)/100),2)+ROUND(((ROUND((ROUND(((AE97-((EU97*1.2)))*AV97*1),2)*BS97),2)*AT97)/100),2)) -> 208.43 | CZ97: =(ROUND((((S97+ROUND((ROUND((((EU97*1.2))*AV97*1),2)*BS97),2))*AU97)/100),2)+ROUND(((ROUND((ROUND(((AE97-((EU97*1.2)))*AV97*1),2)*BS97),2)*AU97)/100),2)) -> 106.53 | DB97: 73 | DD97: *1 | DE97: *1,2 | DF97: *1,2 | DG97: *1,2 | DI97: *1,2 | DJ97: *1,2 | DN97: 0 | DO97: 0 | DP97: 1 | DQ97: 1 | DU97: 1013 | DV97: 1 ШТ. | DW97: 1 ШТ. | DX97: 1 | EE97: 55393700 | EF97: 40 | EG97: Монтаж оборудования | EH97: 0 | EJ97: 2 | EK97: 68 | EL97: ТСН-2001.4-10. Прокладка и монтаж сетей связи | EM97: ТСН-2001.4-10-1 | EO97: Поправка: Гл.12.Прил.8.п.8. 3_12.00.01.11.001 | EQ97: 0 | ER97: 26.52 | ES97: 3.43 | ET97: 0.05 | EU97: 0.01 | EV97: 23.04 | EW97: 1.8 | EX97: 0 | EY97: 0 | FQ97: 0 | FR97: 0 | FS97: 0 | FX97: 90 | FY97: 46 | GD97: 1 | GF97: 1250165502 | GG97: 2 | GH97: 1 | GI97: 2 | GJ97: 0 | GK97: 0 | GL97: =ROUND(IF(AND(BH97=3,BI97=3,FS97<>0),P97,0),2) -> 0 | GM97: =ROUND(O97+X97+Y97,2)+GX97 -> 574.6 | GN97: =IF(OR(BI97=0,BI97=1),GM97-GX97,0) -> 0 | GO97: =IF(BI97=2,GM97-GX97,0) -> 574.6 | GP97: =IF(BI97=4,GM97-GX97,0) -> 0 | GR97: 0 | GS97: 3 | GT97: 0 | GV97: =ROUND((GT97),6) -> 0 | GW97: 1 | GX97: =ROUND(HC97*I97,2) -> 0 | HA97: 0 | HB97: 0 | HC97: =GV97*GW97 -> 0 | HS97: 0 | IK97: 0
A98: 17 | B98: 1 | C98: =ROW(SmtRes!A120) -> 120 | D98: =ROW(EtalonRes!A156) -> 156 | E98: 18 | F98: 4.10-80-5 | G98: Аппараты приемные, приборы ПС приемно-контрольные, пусковые, прибор ПС на 1 луч | H98: 1 ШТ. | I98: 8 | J98: 0 | K98: 8 | O98: =ROUND(CP98,2) -> 13329.54 | P98: =ROUND((ROUND((AC98*AW98*I98),2)*BC98),2) -> 270.01 | Q98: =(ROUND((ROUND((((ET98*1.2))*AV98*I98),2)*BB98),2)+ROUND((ROUND(((AE98-((EU98*1.2)))*AV98*I98),2)*BS98),2)) -> 10 | R98: =(ROUND((ROUND((((EU98*1.2))*AV98*I98),2)*BS98),2)+ROUND((ROUND(((AE98-((EU98*1.2)))*AV98*I98),2)*BS98),2)) -> 5.64 | S98: =ROUND((ROUND((AF98*AV98*I98),2)*BA98),2) -> 13049.53 | T98: =ROUND(CU98*I98,2) -> 0 | U98: =CV98*I98 -> 18.09216 | V98: =CW98*I98 -> 0 | W98: =ROUND(CX98*I98,2) -> 0 | X98: =(ROUND((((S98+ROUND((ROUND((((EU98*1.2))*AV98*I98),2)*BS98),2))*AT98)/100),2)+ROUND(((ROUND((ROUND(((AE98-((EU98*1.2)))*AV98*I98),2)*BS98),2)*AT98)/100),2)) -> 11749.65 | Y98: =(ROUND((((S98+ROUND((ROUND((((EU98*1.2))*AV98*I98),2)*BS98),2))*AU98)/100),2)+ROUND(((ROUND((ROUND(((AE98-((EU98*1.2)))*AV98*I98),2)*BS98),2)*AU98)/100),2)) -> 6005.38 | AA98: 55937298 | AB98: =ROUND((AC98+AD98+AF98),6) -> 31.138 | AC98: =ROUND(((ES98*1)),6) -> 3.43 | AD98: =ROUND(((((ET98*1.2))-((EU98*1.2)))+AE98),6) -> 0.06 | AE98: =ROUND(((EU98*1.2)),6) -> 0.012 | AF98: =ROUND(((EV98*1.2)),6) -> 27.648 | AG98: =ROUND((AP98),6) -> 0 | AH98: =((EW98*1.2)) -> 2.16 | AI98: =((EX98*1.2)) -> 0 | AJ98: =(AS98) -> 0 | AK98: 26.52 | AL98: 3.43 | AM98: 0.05 | AN98: 0.01 | AO98: 23.04 | AP98: 0 | AQ98: 1.8 | AR98: 0 | AS98: 0 | AT98: 90 | AU98: 46 | AV98: 1.047 | AW98: 1 | AZ98: 1 | BA98: 56.35 | BB98: 20 | BC98: 9.84 | BH98: 0 | BI98: 2 | BJ98: ТСН-2001.4. Доп. 1-42. Сб. 10, т. 80, поз. 5 | BM98: 68 | BN98: 0 | BO98: 4.10-80-5 | BP98: 1 | BQ98: 40 | BR98: 0 | BS98: 56.35 | BT98: 1 | BU98: 1 | BV98: 1 | BW98: 1 | BX98: 1 | BZ98: 90 | CA98: 46 | CE98: 1566 | CF98: 0 | CG98: 0 | CM98: 0 | CN98: Поправка: Гл.12.Прил.8.п.8. 3_12.00.01.11.001 Наименование: При наличии напряженных и стесненных условий производства работ (стесненность, сложность складирования и транспортной логистики и т.п.) для объектов, расположенных в пределах круговой магистральной системы улиц "Садовое кольцо" города Москвы | CO98: 0 | CP98: =(P98+Q98+S98) -> 13329.54 | CQ98: =ROUND((ROUND((AC98*AW98*1),2)*BC98),2) -> 33.75 | CR98: =(ROUND((ROUND((((ET98*1.2))*AV98*1),2)*BB98),2)+ROUND((ROUND(((AE98-((EU98*1.2)))*AV98*1),2)*BS98),2)) -> 1.2 | CS98: =(ROUND((ROUND((((EU98*1.2))*AV98*1),2)*BS98),2)+ROUND((ROUND(((AE98-((EU98*1.2)))*AV98*1),2)*BS98),2)) -> 0.56 | CT98: =ROUND((ROUND((AF98*AV98*1),2)*BA98),2) -> 1631.33 | CU98: =AG98 -> 0 | CV98: =(AH98*AV98) -> 2.26152 | CW98: =AI98 -> 0 | CX98: =AJ98 -> 0 | CY98: =(ROUND((((S98+ROUND((ROUND((((EU98*1.2))*AV98*1),2)*BS98),2))*AT98)/100),2)+ROUND(((ROUND((ROUND(((AE98-((EU98*1.2)))*AV98*1),2)*BS98),2)*AT98)/100),2)) -> 11745.08 | CZ98: =(ROUND((((S98+ROUND((ROUND((((EU98*1.2))*AV98*1),2)*BS98),2))*AU98)/100),2)+ROUND(((ROUND((ROUND(((AE98-((EU98*1.2)))*AV98*1),2)*BS98),2)*AU98)/100),2)) -> 6003.04 | DB98: 74 | DD98: *1 | DE98: *1,2 | DF98: *1,2 | DG98: *1,2 | DI98: *1,2 | DJ98: *1,2 | DN98: 0 | DO98: 0 | DP98: 1 | DQ98: 1 | DU98: 1013 | DV98: 1 ШТ. | DW98: 1 ШТ. | DX98: 1 | EE98: 55393700 | EF98: 40 | EG98: Монтаж оборудования | EH98: 0 | EJ98: 2 | EK98: 68 | EL98: ТСН-2001.4-10. Прокладка и монтаж сетей связи | EM98: ТСН-2001.4-10-1 | EO98: Поправка: Гл.12.Прил.8.п.8. 3_12.00.01.11.001 | EQ98: 0 | ER98: 26.52 | ES98: 3.43 | ET98: 0.05 | EU98: 0.01 | EV98: 23.04 | EW98: 1.8 | EX98: 0 | EY98: 0 | FQ98: 0 | FR98: 0 | FS98: 0 | FX98: 90 | FY98: 46 | GD98: 1 | GF98: 1250165502 | GG98: 2 | GH98: 1 | GI98: 2 | GJ98: 0 | GK98: 0 | GL98: =ROUND(IF(AND(BH98=3,BI98=3,FS98<>0),P98,0),2) -> 0 | GM98: =ROUND(O98+X98+Y98,2)+GX98 -> 31084.57 | GN98: =IF(OR(BI98=0,BI98=1),GM98-GX98,0) -> 0 | GO98: =IF(BI98=2,GM98-GX98,0) -> 31084.57 | GP98: =IF(BI98=4,GM98-GX98,0) -> 0 | GR98: 0 | GS98: 3 | GT98: 0 | GV98: =ROUND((GT98),6) -> 0 | GW98: 1 | GX98: =ROUND(HC98*I98,2) -> 0 | HA98: 0 | HB98: 0 | HC98: =GV98*GW98 -> 0 | HS98: 0 | IK98: 0
A99: 17 | B99: 1 | E99: 19 | F99: КА, п.1 | G99: Модуль автоматики пожаротушения МПТ-1 прот.R3 RBZ-073406 | H99: ШТ | I99: 8 | J99: 0 | K99: 8 | O99: =ROUND(CP99,2) -> 6597.84 | P99: =ROUND((ROUND((AC99*AW99*I99),2)*BC99),2) -> 6597.84 | Q99: =(ROUND((ROUND(((ET99)*AV99*I99),2)*BB99),2)+ROUND((ROUND(((AE99-(EU99))*AV99*I99),2)*BS99),2)) -> 0 | R99: =(ROUND((ROUND(((EU99)*AV99*I99),2)*BS99),2)+ROUND((ROUND(((AE99-(EU99))*AV99*I99),2)*BS99),2)) -> 0 | S99: =ROUND((ROUND((AF99*AV99*I99),2)*BA99),2) -> 0 | T99: =ROUND(CU99*I99,2) -> 0 | U99: =CV99*I99 -> 0 | V99: =CW99*I99 -> 0 | W99: =ROUND(CX99*I99,2) -> 0 | X99: =(ROUND((((S99+ROUND((ROUND(((EU99)*AV99*I99),2)*BS99),2))*AT99)/100),2)+ROUND(((ROUND((ROUND(((AE99-(EU99))*AV99*I99),2)*BS99),2)*AT99)/100),2)) -> 0 | Y99: =(ROUND((((S99+ROUND((ROUND(((EU99)*AV99*I99),2)*BS99),2))*AU99)/100),2)+ROUND(((ROUND((ROUND(((AE99-(EU99))*AV99*I99),2)*BS99),2)*AU99)/100),2)) -> 0 | AA99: 55937296 | AB99: =ROUND((AC99+AD99+AF99),6) -> 824.73 | AC99: =ROUND((ES99),6) -> 824.73 | AD99: =ROUND((((ET99)-(EU99))+AE99),6) -> 0 | AE99: =ROUND((EU99),6) -> 0 | AF99: =ROUND((EV99),6) -> 0 | AG99: =ROUND((AP99),6) -> 0 | AH99: =(EW99) -> 0 | AI99: =(EX99) -> 0 | AJ99: =(AS99) -> 0 | AK99: 824.73 | AL99: 824.73 | AM99: 0 | AN99: 0 | AO99: 0 | AP99: 0 | AQ99: 0 | AR99: 0 | AS99: 0 | AT99: 0 | AU99: 0 | AV99: 1 | AW99: 1 | AZ99: 1 | BA99: 1 | BB99: 1 | BC99: 1 | BH99: 3 | BI99: 3 | BJ99: КА, п.1 | BM99: 400007 | BN99: 0 | BP99: 0 | BQ99: 214 | BR99: 0 | BS99: 1 | BT99: 1 | BU99: 1 | BV99: 1 | BW99: 1 | BX99: 1 | BZ99: 0 | CA99: 0 | CE99: 1566 | CF99: 0 | CG99: 0 | CM99: 0 | CO99: 0 | CP99: =(P99+Q99+S99) -> 6597.84 | CQ99: =ROUND((ROUND((AC99*AW99*1),2)*BC99),2) -> 824.73 | CR99: =(ROUND((ROUND(((ET99)*AV99*1),2)*BB99),2)+ROUND((ROUND(((AE99-(EU99))*AV99*1),2)*BS99),2)) -> 0 | CS99: =(ROUND((ROUND(((EU99)*AV99*1),2)*BS99),2)+ROUND((ROUND(((AE99-(EU99))*AV99*1),2)*BS99),2)) -> 0 | CT99: =ROUND((ROUND((AF99*AV99*1),2)*BA99),2) -> 0 | CU99: =AG99 -> 0 | CV99: =(AH99*AV99) -> 0 | CW99: =AI99 -> 0 | CX99: =AJ99 -> 0 | CY99: =(ROUND((((S99+ROUND((ROUND(((EU99)*AV99*1),2)*BS99),2))*AT99)/100),2)+ROUND(((ROUND((ROUND(((AE99-(EU99))*AV99*1),2)*BS99),2)*AT99)/100),2)) -> 0 | CZ99: =(ROUND((((S99+ROUND((ROUND(((EU99)*AV99*1),2)*BS99),2))*AU99)/100),2)+ROUND(((ROUND((ROUND(((AE99-(EU99))*AV99*1),2)*BS99),2)*AU99)/100),2)) -> 0 | DN99: 0 | DO99: 0 | DP99: 1 | DQ99: 1 | DU99: 1013 | DV99: ШТ | DW99: ШТ | DX99: 1 | EE99: 55393630 | EF99: 214 | EG99: Оборудование, отсутствующие в СНБ | EH99: 0 | EJ99: 3 | EK99: 400007 | EL99: Оборудование, отсутствующие в СНБ | EM99: Оборуд. КА | EQ99: 16 | ER99: 0 | ES99: 824.73 | ET99: 0 | EU99: 0 | EV99: 0 | EW99: 0 | EX99: 0 | EY99: 0 | FQ99: 0 | FR99: =P99 -> 6597.84 | FS99: 0 | FX99: 0 | FY99: 0 | GA99: [7 394 / 1,22 / 7,66] + 3% Трансп + 1,2% Заг.скл | GD99: 1 | GF99: 1086867714 | GG99: 2 | GH99: 4 | GI99: -2 | GJ99: 0 | GK99: 0 | GL99: =ROUND(IF(AND(BH99=3,BI99=3,FS99<>0),P99,0),2) -> 0 | GM99: =ROUND(O99+X99+Y99,2)+GX99 -> 6597.84 | GN99: =IF(OR(BI99=0,BI99=1),GM99-GX99,0) -> 0 | GO99: =IF(BI99=2,GM99-GX99,0) -> 0 | GP99: =IF(BI99=4,GM99-GX99,0) -> 0 | GR99: 1 | GS99: 2 | GT99: 0 | GV99: =ROUND((GT99),6) -> 0 | GW99: 1 | GX99: =ROUND(HC99*I99,2) -> 0 | HA99: 0 | HB99: 0 | HC99: =GV99*GW99 -> 0 | HE99: 3 | HF99: 1,2 | HS99: 0 | IK99: 0
