Workbook

Sheet Смета по ТСН-2001(с доп.67
A1: =Source!B1 -> Smeta.RU (495) 974-1589
J2: Форма № 4б
B3: "СОГЛАСОВАНО" | G3: "УТВЕРЖДАЮ"
B6: =CONCATENATE("______________________ ", IF(Source!AL12<>"", Source!AL12, "")) -> ______________________ | G6: =CONCATENATE("______________________ ", IF(Source!AH12<>"", Source!AH12, "")) -> ______________________
B7: "_____"________________ 2026 г. | G7: "_____"________________ 2026 г.
A10: Капитальный ремонт здания Государственного бюджетного общеобразовательного учреждения города Москвы «Школа №1574», расположенного по адресу: г. Москва, Старопименовский переулок, д. 5. 1 этап. | AP10: Капитальный ремонт здания Государственного бюджетного общеобразовательного учреждения города Москвы «Школа №1574», расположенного по адресу: г. Москва, Старопименовский переулок, д. 5. 1 этап. 02-01-17 СДС
A11: (наименование стройки и/или объекта)
A13: =CONCATENATE( "ЛОКАЛЬНАЯ СМЕТА № ",IF(Source!F12<>"Новый объект", Source!F12, "")) -> ЛОКАЛЬНАЯ СМЕТА № 02-01-17
A15: =Source!G20 -> Система двухсторонней связи
A16: (наименование работ и затрат)
A18: =CONCATENATE( "Основание: чертежи № ", Source!J12) -> Основание: чертежи № 2024-00375-01-0-ИОС5.10
I20: В базисном уровне цен | J20: В текущем уровне цен
E21: Сметная стоимость | I21: =I22+I23+I24+I25 -> 407.42 | J21: =J22+J23+J24+J25 -> 7732.03 | K21: тыс.руб.
E22: Строительные работы | I22: =ROUND((Source!F290)/1000, 2) -> 54.18 | J22: =ROUND((Source!P290)/1000, 2) -> 3001.07 | K22: тыс.руб.
E23: Работы по монтажу оборудования | I23: =ROUND((Source!F291)/1000, 2) -> 91.98 | J23: =ROUND((Source!P291)/1000, 2) -> 2751.29 | K23: тыс.руб.
E24: Оборудование | I24: =ROUND((Source!F282)/1000, 2) -> 261.26 | J24: =ROUND((Source!P282)/1000, 2) -> 1979.67 | K24: тыс.руб. | L24: СОГЛ
E25: Прочие работы и затраты | I25: =ROUND((Source!F292+Source!F293)/1000, 2) -> 0 | J25: =ROUND((Source!P292+Source!P293)/1000, 2) -> 0 | K25: тыс.руб.
E26: Средства на оплату труда | I26: =(Source!F288+ Source!F287)/1000 -> 38.44482 | J26: =((Source!P288 + Source!P287)/1000) -> 2166.3656 | K26: тыс.руб.
E27: Затраты труда | I27: =Source!F295 -> 3360.6185 | K27: чел.-ч.
E28: Кроме того:
E29: Возврат материалов | I29: =SUM(Y1:Y349)/1000 -> 0 | J29: =SUM(Z1:Z349)/1000 -> 0 | K29: тыс.руб.
A31: Составлен(а) по ТСН-2001 с учетом Дополнения №: 81
A32: № и период сборника коэффициентов (индексов) пересчета: Коэффициенты к ТСН-2001 МГЭ Дополнение 81, ремонт №219/81 I квартал 2026 года и Коэффициенты к ТСН-2001.13-2 Дополнение 47 №64/47 I квартал 2026 года | AP32: № и период сборника коэффициентов (индексов) пересчета: Коэффициенты к ТСН-2001 МГЭ Дополнение 81, ремонт №219/81 I квартал 2026 года и Коэффициенты к ТСН-2001.13-2 Дополнение 47 №64/47 I квартал 2026 года
A33: № п/п | B33: Шифр расценки и коды ресурсов | C33: Наименование работ и затрат | D33: Ед. изм. | E33: Кол-во единиц | F33: Цена на ед. изм., руб. | G33: Попра- вочные коэффи- циенты | H33: Коэффи- циенты зимних удорожа- ний | I33: Всего в ценах на январь 2000 года, руб. | J33: Коэффи- циенты (индек- сы) пере- счета, нормы НР и СП | K33: ВСЕГО затрат в текущем уровне цен, руб.
A34: 1 | B34: 2 | C34: 3 | D34: 4 | E34: 5 | F34: 6 | G34: 7 | H34: 8 | I34: 9 | J34: 10 | K34: 11
A36: =CONCATENATE("Локальная смета: ",IF(Source!G20<>"Новая локальная смета", Source!G20, "")) -> Локальная смета: Система двухсторонней связи
A38: =CONCATENATE("Раздел: ",IF(Source!G24<>"Новый раздел", Source!G24, "")) -> Раздел: Демонтажные работы
A39: 1 | B39: =Source!F28 -> 4.11-7-1 | C39: Установка аппарата настольного массой до 0,015 т / демонтаж пульта диспетчера | D39: =Source!H28 -> 1ШТ. | E39: =Source!I28 -> 1 | Q39: =Source!X28 -> 4.59 | R39: =Source!X29 -> 258.65 | S39: =Source!Y28 -> 2.35 | T39: =Source!Y29 -> 132.2 | U39: =ROUND((175/100)*ROUND(Source!R28, 2), 2) -> 1.33 | V39: =ROUND((0/100)*ROUND(Source!R29, 2), 2) -> 0 | AC39: 0
C40: ЗП | F40: =Source!AO28 -> 11.52 | G40: 1,2*0,3 | H40: =Source!AV29 -> 1.047 | I40: =Source!S28 -> 4.34 | J40: =IF(Source!BA29<> 0, Source!BA29, 1) -> 56.35 | K40: =Source!S29 -> 244.56
C41: ЭМ | F41: =Source!AM28 -> 13.3 | G41: 1,2*0,3 | H41: =Source!AV29 -> 1.047 | I41: =Source!Q28 -> 5.01 | J41: =IF(Source!BB29<> 0, Source!BB29, 1) -> 17.06 | K41: =Source!Q29 -> 85.47
C42: в т.ч. ЗПМ | F42: =Source!AN28 -> 2.02 | G42: 1,2*0,3 | H42: =Source!AV29 -> 1.047 | I42: =Source!R28 -> 0.76 | J42: =IF(Source!BS29<> 0, Source!BS29, 1) -> 56.35 | K42: =Source!R29 -> 42.83
C43: НР от ФОТ | D43: % | E43: =Source!BZ29 -> 90 | I43: =SUM(Q39:Q42) -> 4.59 | J43: =Source!AT29 -> 90 | K43: =SUM(R39:R42) -> 258.65
C44: СП от ФОТ | D44: % | E44: =Source!CA29 -> 46 | I44: =SUM(S39:S43) -> 2.35 | J44: =Source!AU29 -> 46 | K44: =SUM(T39:T43) -> 132.2
C45: ЗТР | D45: чел-ч | E45: =Source!AQ28 -> 1.03 | G45: 1,2*0,3 | H45: =Source!AV29 -> 1.047 | I45: =Source!U28 -> 0.3882276
C46: ВСЕГО работ по позиции: | H46: =I40+I41+I43+I44+0-0-0 -> 16.29 | J46: =K40+K41+K43+K44+0-0-0 -> 720.88
C47: ВСЕГО оборудование по позиции: | H47: =0+0 -> 0 | J47: =0+0 -> 0
C48: ВСЕГО по позиции: | H48: =I40+I41+I43+I44+0 -> 16.29 | J48: =K40+K41+K43+K44+0 -> 720.88 | O48: =I40+I41+I43+I44+0 -> 16.29 | P48: =K40+K41+K43+K44+0 -> 720.88
A50: 2 | B50: =Source!F30 -> 4.10-34-5 | C50: Монтаж коммутатора служебной связи / демонтаж блока коммутации | D50: =Source!H30 -> 1 ШТ. | E50: =Source!I30 -> 5 | Q50: =Source!X30 -> 138.07 | R50: =Source!X31 -> 7780.19 | S50: =Source!Y30 -> 70.57 | T50: =Source!Y31 -> 3976.54 | U50: =ROUND((175/100)*ROUND(Source!R30, 2), 2) -> 10.43 | V50: =ROUND((0/100)*ROUND(Source!R31, 2), 2) -> 0 | AC50: 0
C51: ="Объем: "&Source!I30&"=4+"&"1" -> Объем: 5=4+1
C52: ЗП | F52: =Source!AO30 -> 78.24 | G52: 1,2*0,3 | H52: =Source!AV31 -> 1.047 | I52: =Source!S30 -> 147.45 | J52: =IF(Source!BA31<> 0, Source!BA31, 1) -> 56.35 | K52: =Source!S31 -> 8308.81
C53: ЭМ | F53: =Source!AM30 -> 28.71 | G53: 1,2*0,3 | H53: =Source!AV31 -> 1.047 | I53: =Source!Q30 -> 54.11 | J53: =IF(Source!BB31<> 0, Source!BB31, 1) -> 16.16 | K53: =Source!Q31 -> 874.42
C54: в т.ч. ЗПМ | F54: =Source!AN30 -> 3.16 | G54: 1,2*0,3 | H54: =Source!AV31 -> 1.047 | I54: =Source!R30 -> 5.96 | J54: =IF(Source!BS31<> 0, Source!BS31, 1) -> 56.35 | K54: =Source!R31 -> 335.85
C55: НР от ФОТ | D55: % | E55: =Source!BZ31 -> 90 | I55: =SUM(Q50:Q54) -> 138.07 | J55: =Source!AT31 -> 90 | K55: =SUM(R50:R54) -> 7780.19
C56: СП от ФОТ | D56: % | E56: =Source!CA31 -> 46 | I56: =SUM(S50:S55) -> 70.57 | J56: =Source!AU31 -> 46 | K56: =SUM(T50:T55) -> 3976.54
C57: ЗТР | D57: чел-ч | E57: =Source!AQ30 -> 6.2 | G57: 1,2*0,3 | H57: =Source!AV31 -> 1.047 | I57: =Source!U30 -> 11.68452
C58: ВСЕГО работ по позиции: | H58: =I52+I53+I55+I56+0-0-0 -> 410.2 | J58: =K52+K53+K55+K56+0-0-0 -> 20939.96
C59: ВСЕГО оборудование по позиции: | H59: =0+0 -> 0 | J59: =0+0 -> 0
C60: ВСЕГО по позиции: | H60: =I52+I53+I55+I56+0 -> 410.2 | J60: =K52+K53+K55+K56+0 -> 20939.96 | O60: =I52+I53+I55+I56+0 -> 410.2 | P60: =K52+K53+K55+K56+0 -> 20939.96
A62: 3 | B62: =Source!F32 -> 4.11-1-4 | C62: Монтаж конструкции для установки приборов и средств автоматизации массой до 5 кг / демонтаж стойки считывателя | D62: =Source!H32 -> 1ШТ. | E62: =Source!I32 -> 2 | Q62: =Source!X32 -> 8.84 | R62: =Source!X33 -> 498.02 | S62: =Source!Y32 -> 4.52 | T62: =Source!Y33 -> 254.55 | U62: =ROUND((175/100)*ROUND(Source!R32, 2), 2) -> 1.63 | V62: =ROUND((0/100)*ROUND(Source!R33, 2), 2) -> 0 | AC62: 0
C63: ЗП | F63: =Source!AO32 -> 11.79 | G63: 1,2*0,3 | H63: =Source!AV33 -> 1.047 | I63: =Source!S32 -> 8.89 | J63: =IF(Source!BA33<> 0, Source!BA33, 1) -> 56.35 | K63: =Source!S33 -> 500.95
C64: ЭМ | F64: =Source!AM32 -> 5.37 | G64: 1,2*0,3 | H64: =Source!AV33 -> 1.047 | I64: =Source!Q32 -> 4.05 | J64: =IF(Source!BB33<> 0, Source!BB33, 1) -> 22.63 | K64: =Source!Q33 -> 91.65
C65: в т.ч. ЗПМ | F65: =Source!AN32 -> 1.23 | G65: 1,2*0,3 | H65: =Source!AV33 -> 1.047 | I65: =Source!R32 -> 0.93 | J65: =IF(Source!BS33<> 0, Source!BS33, 1) -> 56.35 | K65: =Source!R33 -> 52.41
C66: НР от ФОТ | D66: % | E66: =Source!BZ33 -> 90 | I66: =SUM(Q62:Q65) -> 8.84 | J66: =Source!AT33 -> 90 | K66: =SUM(R62:R65) -> 498.02
C67: СП от ФОТ | D67: % | E67: =Source!CA33 -> 46 | I67: =SUM(S62:S66) -> 4.52 | J67: =Source!AU33 -> 46 | K67: =SUM(T62:T66) -> 254.55
C68: ЗТР | D68: чел-ч | E68: =Source!AQ32 -> 1.03 | G68: 1,2*0,3 | H68: =Source!AV33 -> 1.047 | I68: =Source!U32 -> 0.7764552
C69: ВСЕГО работ по позиции: | H69: =I63+I64+I66+I67+0-0-0 -> 26.3 | J69: =K63+K64+K66+K67+0-0-0 -> 1345.17
C70: ВСЕГО оборудование по позиции: | H70: =0+0 -> 0 | J70: =0+0 -> 0
C71: ВСЕГО по позиции: | H71: =I63+I64+I66+I67+0 -> 26.3 | J71: =K63+K64+K66+K67+0 -> 1345.17 | O71: =I63+I64+I66+I67+0 -> 26.3 | P71: =K63+K64+K66+K67+0 -> 1345.17
A73: 4 | B73: =Source!F34 -> 4.10-76-10 | C73: Монтаж ключа или кнопки на панели / демонтаж кнопки вызова | D73: =Source!H34 -> 1ШТ. | E73: =Source!I34 -> 2 | Q73: =Source!X34 -> 8.51 | R73: =Source!X35 -> 479.66 | S73: =Source!Y34 -> 4.75 | T73: =Source!Y35 -> 267.6 | U73: =ROUND((175/100)*ROUND(Source!R34, 2), 2) -> 0 | V73: =ROUND((0/100)*ROUND(Source!R35, 2), 2) -> 0 | AC73: 0
C74: ЗП | F74: =Source!AO34 -> 11.89 | G74: 1,2*0,3 | H74: =Source!AV35 -> 1.047 | I74: =Source!S34 -> 8.96 | J74: =IF(Source!BA35<> 0, Source!BA35, 1) -> 56.35 | K74: =Source!S35 -> 504.9
C75: НР от ФОТ | D75: % | E75: =Source!BZ35 -> 95 | I75: =SUM(Q73:Q74) -> 8.51 | J75: =Source!AT35 -> 95 | K75: =SUM(R73:R74) -> 479.66
C76: СП от ФОТ | D76: % | E76: =Source!CA35 -> 53 | I76: =SUM(S73:S75) -> 4.75 | J76: =Source!AU35 -> 53 | K76: =SUM(T73:T75) -> 267.6
C77: ЗТР | D77: чел-ч | E77: =Source!AQ34 -> 1 | G77: 1,2*0,3 | H77: =Source!AV35 -> 1.047 | I77: =Source!U34 -> 0.75384
C78: ВСЕГО работ по позиции: | H78: =I74+I75+I76+0-0-0 -> 22.22 | J78: =K74+K75+K76+0-0-0 -> 1252.16
C79: ВСЕГО оборудование по позиции: | H79: =0+0 -> 0 | J79: =0+0 -> 0
C80: ВСЕГО по позиции: | H80: =I74+I75+I76+0 -> 22.22 | J80: =K74+K75+K76+0 -> 1252.16 | O80: =I74+I75+I76+0 -> 22.22 | P80: =K74+K75+K76+0 -> 1252.16
A82: 5 | B82: =Source!F36 -> 4.10-76-15 | C82: Монтаж транспаранта светового (табло) / демонтаж светозвукового сигнализитора | D82: =Source!H36 -> 1ШТ. | E82: =Source!I36 -> 1 | Q82: =Source!X36 -> 9.03 | R82: =Source!X37 -> 509.1 | S82: =Source!Y36 -> 5.04 | T82: =Source!Y37 -> 284.02 | U82: =ROUND((175/100)*ROUND(Source!R36, 2), 2) -> 0 | V82: =ROUND((0/100)*ROUND(Source!R37, 2), 2) -> 0 | AC82: 0
C83: ЗП | F83: =Source!AO36 -> 25.24 | G83: 1,2*0,3 | H83: =Source!AV37 -> 1.047 | I83: =Source!S36 -> 9.51 | J83: =IF(Source!BA37<> 0, Source!BA37, 1) -> 56.35 | K83: =Source!S37 -> 535.89
C84: НР от ФОТ | D84: % | E84: =Source!BZ37 -> 95 | I84: =SUM(Q82:Q83) -> 9.03 | J84: =Source!AT37 -> 95 | K84: =SUM(R82:R83) -> 509.1
C85: СП от ФОТ | D85: % | E85: =Source!CA37 -> 53 | I85: =SUM(S82:S84) -> 5.04 | J85: =Source!AU37 -> 53 | K85: =SUM(T82:T84) -> 284.02
C86: ЗТР | D86: чел-ч | E86: =Source!AQ36 -> 2 | G86: 1,2*0,3 | H86: =Source!AV37 -> 1.047 | I86: =Source!U36 -> 0.75384
C87: ВСЕГО работ по позиции: | H87: =I83+I84+I85+0-0-0 -> 23.58 | J87: =K83+K84+K85+0-0-0 -> 1329.01
C88: ВСЕГО оборудование по позиции: | H88: =0+0 -> 0 | J88: =0+0 -> 0
C89: ВСЕГО по позиции: | H89: =I83+I84+I85+0 -> 23.58 | J89: =K83+K84+K85+0 -> 1329.01 | O89: =I83+I84+I85+0 -> 23.58 | P89: =K83+K84+K85+0 -> 1329.01
A91: 6 | B91: =Source!F38 -> 4.10-177-1 | C91: Монтаж устройства связи с согласующим устройством (вызывная панель) / демонтаж абонентского переговорного устройства | D91: =Source!H38 -> 10 шт. | E91: =Source!I38 -> 3.1 | Q91: =Source!X38 -> 239.98 | R91: =Source!X39 -> 13522.64 | S91: =Source!Y38 -> 122.65 | T91: =Source!Y39 -> 6911.57 | U91: =ROUND((175/100)*ROUND(Source!R38, 2), 2) -> 1.56 | V91: =ROUND((0/100)*ROUND(Source!R39, 2), 2) -> 0 | AC91: 0
C92: ="Объем: "&Source!I38&"=31/"&"10" -> Объем: 3,1=31/10
C93: ЗП | F93: =Source!AO38 -> 227.44 | G93: 1,2*0,3 | H93: =Source!AV39 -> 1.047 | I93: =Source!S38 -> 265.75 | J93: =IF(Source!BA39<> 0, Source!BA39, 1) -> 56.35 | K93: =Source!S39 -> 14975.01
C94: ЭМ | F94: =Source!AM38 -> 6.07 | G94: 1,2*0,3 | H94: =Source!AV39 -> 1.047 | I94: =Source!Q38 -> 7.09 | J94: =IF(Source!BB39<> 0, Source!BB39, 1) -> 15.73 | K94: =Source!Q39 -> 111.53
C95: в т.ч. ЗПМ | F95: =Source!AN38 -> 0.76 | G95: 1,2*0,3 | H95: =Source!AV39 -> 1.047 | I95: =Source!R38 -> 0.89 | J95: =IF(Source!BS39<> 0, Source!BS39, 1) -> 56.35 | K95: =Source!R39 -> 50.15
C96: НР от ФОТ | D96: % | E96: =Source!BZ39 -> 90 | I96: =SUM(Q91:Q95) -> 239.98 | J96: =Source!AT39 -> 90 | K96: =SUM(R91:R95) -> 13522.64
C97: СП от ФОТ | D97: % | E97: =Source!CA39 -> 46 | I97: =SUM(S91:S96) -> 122.65 | J97: =Source!AU39 -> 46 | K97: =SUM(T91:T96) -> 6911.57
C98: ЗТР | D98: чел-ч | E98: =Source!AQ38 -> 14.64 | G98: 1,2*0,3 | H98: =Source!AV39 -> 1.047 | I98: =Source!U38 -> 17.106137
C99: ВСЕГО работ по позиции: | H99: =I93+I94+I96+I97+0-0-0 -> 635.47 | J99: =K93+K94+K96+K97+0-0-0 -> 35520.75
C100: ВСЕГО оборудование по позиции: | H100: =0+0 -> 0 | J100: =0+0 -> 0
C101: ВСЕГО по позиции: | H101: =I93+I94+I96+I97+0 -> 635.47 | J101: =K93+K94+K96+K97+0 -> 35520.75 | O101: =I93+I94+I96+I97+0 -> 635.47 | P101: =K93+K94+K96+K97+0 -> 35520.75
A103: 7 | B103: =Source!F40 -> 4.10-167-1 | C103: Монтаж блока питания сети (БПС) в диспетчерской / демонтаж источника электропитания | D103: =Source!H40 -> 1ШТ. | E103: =Source!I40 -> 2 | Q103: =Source!X40 -> 12.85 | R103: =Source!X41 -> 724.21 | S103: =Source!Y40 -> 6.57 | T103: =Source!Y41 -> 370.15 | U103: =ROUND((175/100)*ROUND(Source!R40, 2), 2) -> 0 | V103: =ROUND((0/100)*ROUND(Source!R41, 2), 2) -> 0 | AC103: 0
C104: ЗП | F104: =Source!AO40 -> 18.94 | G104: 1,2*0,3 | H104: =Source!AV41 -> 1.047 | I104: =Source!S40 -> 14.28 | J104: =IF(Source!BA41<> 0, Source!BA41, 1) -> 56.35 | K104: =Source!S41 -> 804.68
C105: ЭМ | F105: =Source!AM40 -> 0.02 | G105: 1,2*0,3 | H105: =Source!AV41 -> 1.047 | I105: =Source!Q40 -> 0.02 | J105: =IF(Source!BB41<> 0, Source!BB41, 1) -> 11 | K105: =Source!Q41 -> 0.22
C106: НР от ФОТ | D106: % | E106: =Source!BZ41 -> 90 | I106: =SUM(Q103:Q105) -> 12.85 | J106: =Source!AT41 -> 90 | K106: =SUM(R103:R105) -> 724.21
C107: СП от ФОТ | D107: % | E107: =Source!CA41 -> 46 | I107: =SUM(S103:S106) -> 6.57 | J107: =Source!AU41 -> 46 | K107: =SUM(T103:T106) -> 370.15
C108: ЗТР | D108: чел-ч | E108: =Source!AQ40 -> 1.36 | G108: 1,2*0,3 | H108: =Source!AV41 -> 1.047 | I108: =Source!U40 -> 1.0252224
C109: ВСЕГО работ по позиции: | H109: =I104+I105+I106+I107+0-0-0 -> 33.72 | J109: =K104+K105+K106+K107+0-0-0 -> 1899.26
C110: ВСЕГО оборудование по позиции: | H110: =0+0 -> 0 | J110: =0+0 -> 0
C111: ВСЕГО по позиции: | H111: =I104+I105+I106+I107+0 -> 33.72 | J111: =K104+K105+K106+K107+0 -> 1899.26 | O111: =I104+I105+I106+I107+0 -> 33.72 | P111: =K104+K105+K106+K107+0 -> 1899.26
A113: 8 | B113: =Source!F42 -> 4.8-70-1 | C113: Монтаж аккумулятора кислотного стационарного типа С-1, СК-1 / демонтаж аккумуляторной батареи | D113: =Source!H42 -> 1ШТ. | E113: =Source!I42 -> 4 | Q113: =Source!X42 -> 38.02 | R113: =Source!X43 -> 2142.65 | S113: =Source!Y42 -> 19.99 | T113: =Source!Y43 -> 1126.55 | U113: =ROUND((175/100)*ROUND(Source!R42, 2), 2) -> 0 | V113: =ROUND((0/100)*ROUND(Source!R43, 2), 2) -> 0 | AC113: 0
C114: ЗП | F114: =Source!AO42 -> 26 | G114: 1,2*0,3 | H114: =Source!AV43 -> 1.047 | I114: =Source!S42 -> 39.2 | J114: =IF(Source!BA43<> 0, Source!BA43, 1) -> 56.35 | K114: =Source!S43 -> 2208.92
C115: НР от ФОТ | D115: % | E115: =Source!BZ43 -> 97 | I115: =SUM(Q113:Q114) -> 38.02 | J115: =Source!AT43 -> 97 | K115: =SUM(R113:R114) -> 2142.65
C116: СП от ФОТ | D116: % | E116: =Source!CA43 -> 51 | I116: =SUM(S113:S115) -> 19.99 | J116: =Source!AU43 -> 51 | K116: =SUM(T113:T115) -> 1126.55
C117: ЗТР | D117: чел-ч | E117: =Source!AQ42 -> 2.06 | G117: 1,2*0,3 | H117: =Source!AV43 -> 1.047 | I117: =Source!U42 -> 3.1058208
C118: ВСЕГО работ по позиции: | H118: =I114+I115+I116+0-0-0 -> 97.21 | J118: =K114+K115+K116+0-0-0 -> 5478.12
...

Sheet Source
A1: 0 | B1: Smeta.RU (495) 974-1589 | D1: _PS_ | F1: 0 | G1: 0 | H1: 0 | I1: Smeta.RU | K1: 1 | L1: 74599 | M1: 10 | N1: 12 | O1: 1 | P1: 0 | Q1: 1
A4: 1 | B4: 1 | C4: -1 | G4: Капитальный ремонт здания Государственного бюджетного общеобразовательного учреждения города Москвы «Школа №1574», расположенного по адресу: г. Москва, Старопименовский переулок, д. 5. 1 этап | EC4: 0
A5: 8 | B5: 1 | C5: -1 | G5: Капитальный ремонт здания Государственного бюджетного общеобразовательного учреждения города Москвы «Школа №1574», расположенного по адресу: г. Москва, Старопименовский переулок, д. 5. 1 этап | EC5: 0
A12: 1 | B12: 314 | C12: 0 | D12: =ROW(A273) -> 273 | E12: 0 | F12: 02-01-17 | G12: 02-01-17 СДС | I12: 0 | J12: 2024-00375-01-0-ИОС5.10 | K12: 0 | L12: 0 | M12: 4098 | O12: 0 | P12: 0 | Q12: 0 | R12: 0 | S12: 0 | T12: 1 | U12: Капитальный ремонт здания Государственного бюджетного общеобразовательного учреждения города Москвы «Школа №1574» | V12: 2 | W12: г. Москва, Старопименовский переулок, д. 5. 1 этап | AB12: Гришечкина О.А. | AC12: Ведущий инженер-сметчик | AD12: Феденко И.В. | AE12: Руководитель отдела | BB12: 0 | BH12: Сметные нормы списания | BI12: Коды ОКП для ТСН-2001 МГЭ Дополнение 81 | BJ12: 1 | BK12: 1 | BL12: 0 | BM12: 0 | BN12: 1 | BO12: 0 | BP12: 6 | BQ12: 2 | BR12: 1 | BS12: 1 | BT12: 0 | BU12: 0 | BV12: 0 | BW12: 0 | BX12: 0 | BY12: ТСН-2001 (МГЭ) Доп 81 - Ремонт | BZ12: Типовой расчет для ТСН-2001 МГЭ, Дополнение 81, ремонт | CA12: Территориальные сметные нормативы для Москвы ТСН-2001 (МГЭ), дополнение 81 | CB12: Территориальные сметные нормативы для Москвы ТСН-2001 (МГЭ), дополнение 81 | CC12: Территориальные сметные нормативы для Москвы ТСН-2001 (МГЭ), дополнение 81 | CD12: Территориальные сметные нормативы для Москвы ТСН-2001 (МГЭ), дополнение 81 | CE12: Поправки для ТСН-2001 от 07.04.2026 г. доп.81 | CF12: 0 | CG12: 0 | CH12: 8200 | CK12: 81 | CQ12: Территориальные сметные нормативы для Москвы (ТСН-2001) | CR12: ТЕР | CS12: 41660 | CT12: 1 | CU12: 81 | CY12: 0 | EC12: 0
A15: 15 | B15: 1
A18: 52 | B18: =B273 -> 314 | C18: =C273 -> 1 | D18: =D273 -> 12 | E18: =E273 -> 0 | F18: =F273 -> 02-01-17 | G18: =G273 -> 02-01-17 СДС | O18: =O273 -> 352743.35 | P18: =P273 -> 312343.87 | Q18: =Q273 -> 2325.66 | R18: =R273 -> 371 | S18: =S273 -> 38073.82 | T18: =T273 -> 0 | U18: =U273 -> 3360.6185 | V18: =V273 -> 0 | ... GX18: =GX273 -> 0
A20: 3 | B20: 1 | D20: =ROW(A240) -> 240 | F20: 02-01-17 | G20: Система двухсторонней связи | I20: 0 | J20: 2024-00375-01-0-ИОС5.10 | K20: -1 | L20: 02-01-17 | S20: 0 | T20: 0 | V20: 2 | BX20: 0 | CF20: 0 | CG20: 0
A22: 52 | B22: =B240 -> 1 | C22: =C240 -> 3 | D22: =D240 -> 20 | E22: =E240 -> 0 | F22: =F240 -> 02-01-17 | G22: =G240 -> Система двухсторонней связи | O22: =O240 -> 352743.35 | P22: =P240 -> 312343.87 | Q22: =Q240 -> 2325.66 | R22: =R240 -> 371 | S22: =S240 -> 38073.82 | T22: =T240 -> 0 | U22: =U240 -> 3360.6185 | V22: =V240 -> 0 | ... GX22: =GX240 -> 0
A24: 4 | B24: 1 | D24: =ROW(A49) -> 49 | F24: Новый раздел | G24: Демонтажные работы | I24: 0 | K24: 0 | S24: 0 | T24: 0 | V24: 2 | BX24: 0 | CJ24: 0
A26: 52 | B26: =B49 -> 1 | C26: =C49 -> 4 | D26: =D49 -> 24 | E26: =E49 -> 0 | F26: =F49 -> Новый раздел | G26: =G49 -> Демонтажные работы | O26: =O49 -> 22770.82 | P26: =P49 -> 0 | Q26: =Q49 -> 70.28 | R26: =R49 -> 8.54 | S26: =S49 -> 22700.54 | T26: =T49 -> 0 | U26: =U49 -> 2160.6389 | V26: =V49 -> 0 | ... GX26: =GX49 -> 0
A28: 17 | B28: 1 | E28: 1 | F28: 4.11-7-1 | G28: Установка аппарата настольного массой до 0,015 т / демонтаж пульта диспетчера | H28: 1ШТ. | I28: 1 | J28: 0 | K28: 1 | O28: =ROUND(CP28,2) -> 9.35 | P28: =ROUND((ROUND((AC28*AW28*I28),2)*BC28),2) -> 0 | Q28: =(ROUND((ROUND(((((ET28*1.2)*0.3))*AV28*I28),2)*BB28),2)+ROUND((ROUND(((AE28-(((EU28*1.2)*0.3)))*AV28*I28),2)*BS28),2)) -> 5.01 | R28: =(ROUND((ROUND(((((EU28*1.2)*0.3))*AV28*I28),2)*BS28),2)+ROUND((ROUND(((AE28-(((EU28*1.2)*0.3)))*AV28*I28),2)*BS28),2)) -> 0.76 | S28: =ROUND((ROUND((AF28*AV28*I28),2)*BA28),2) -> 4.34 | T28: =ROUND(CU28*I28,2) -> 0 | U28: =CV28*I28 -> 0.3882276 | V28: =CW28*I28 -> 0 | W28: =ROUND(CX28*I28,2) -> 0 | X28: =(ROUND((((S28+ROUND((ROUND(((((EU28*1.2)*0.3))*AV28*I28),2)*BS28),2))*AT28)/100),2)+ROUND(((ROUND((ROUND(((AE28-(((EU28*1.2)*0.3)))*AV28*I28),2)*BS28),2)*AT28)/100),2)) -> 4.59 | Y28: =(ROUND((((S28+ROUND((ROUND(((((EU28*1.2)*0.3))*AV28*I28),2)*BS28),2))*AU28)/100),2)+ROUND(((ROUND((ROUND(((AE28-(((EU28*1.2)*0.3)))*AV28*I28),2)*BS28),2)*AU28)/100),2)) -> 2.35 | AA28: 55943566 | AB28: =ROUND((AC28+AD28+AF28),6) -> 8.9352 | AC28: =ROUND((((ES28*1)*0)),6) -> 0 | AD28: =ROUND((((((ET28*1.2)*0.3))-(((EU28*1.2)*0.3)))+AE28),6) -> 4.788 | AE28: =ROUND((((EU28*1.2)*0.3)),6) -> 0.7272 | AF28: =ROUND((((EV28*1.2)*0.3)),6) -> 4.1472 | AG28: =ROUND((AP28),6) -> 0 | AH28: =(((EW28*1.2)*0.3)) -> 0.3708 | AI28: =(((EX28*1.2)*0.3)) -> 0 | AJ28: =(AS28) -> 0 | AK28: 24.82 | AL28: 0 | AM28: 13.3 | AN28: 2.02 | AO28: 11.52 | AP28: 0 | AQ28: 1.03 | AR28: 0 | AS28: 0 | AT28: 90 | AU28: 46 | AV28: 1.047 | AW28: 1 | AZ28: 1 | BA28: 1 | BB28: 1 | BC28: 1 | BH28: 0 | BI28: 2 | BJ28: ТСН-2001.4 Доп. 68, Сб. 11, т. 7, поз. 1 | BM28: 72 | BN28: 0 | BO28: 4.11-7-1 | BP28: 1 | BQ28: 40 | BR28: 0 | BS28: 1 | BT28: 1 | BU28: 1 | BV28: 1 | BW28: 1 | BX28: 1 | BZ28: 90 | CA28: 46 | CE28: 1566 | CF28: 0 | CG28: 0 | CM28: 0 | CN28: Поправка: Гл.12.Прил.8.п.8. 3_12.00.01.11.001 Наименование: При наличии напряженных и стесненных условий производства работ (стесненность, сложность складирования и транспортной логистики и т.п.) для объектов, расположенных в пределах круговой магистральной системы улиц "Садовое кольцо" города Москвы Поправка: Гл.4.Прил.2.2.п.2.2.29_04.00.01.35.003 Наименование: При демонтаже оборудования, предназначенного в лом | CO28: 0 | CP28: =(P28+Q28+S28) -> 9.35 | CQ28: =ROUND((ROUND((AC28*AW28*1),2)*BC28),2) -> 0 | CR28: =(ROUND((ROUND(((((ET28*1.2)*0.3))*AV28*1),2)*BB28),2)+ROUND((ROUND(((AE28-(((EU28*1.2)*0.3)))*AV28*1),2)*BS28),2)) -> 5.01 | CS28: =(ROUND((ROUND(((((EU28*1.2)*0.3))*AV28*1),2)*BS28),2)+ROUND((ROUND(((AE28-(((EU28*1.2)*0.3)))*AV28*1),2)*BS28),2)) -> 0.76 | CT28: =ROUND((ROUND((AF28*AV28*1),2)*BA28),2) -> 4.34 | CU28: =AG28 -> 0 | CV28: =(AH28*AV28) -> 0.3882276 | CW28: =AI28 -> 0 | CX28: =AJ28 -> 0 | CY28: =(ROUND((((S28+ROUND((ROUND(((((EU28*1.2)*0.3))*AV28*1),2)*BS28),2))*AT28)/100),2)+ROUND(((ROUND((ROUND(((AE28-(((EU28*1.2)*0.3)))*AV28*1),2)*BS28),2)*AT28)/100),2)) -> 4.59 | CZ28: =(ROUND((((S28+ROUND((ROUND(((((EU28*1.2)*0.3))*AV28*1),2)*BS28),2))*AU28)/100),2)+ROUND(((ROUND((ROUND(((AE28-(((EU28*1.2)*0.3)))*AV28*1),2)*BS28),2)*AU28)/100),2)) -> 2.35 | DB28: 1 | DD28: *1)*0 | DE28: *1,2)*0,3 | DF28: *1,2)*0,3 | DG28: *1,2)*0,3 | DI28: *1,2)*0,3 | DJ28: *1,2)*0,3 | DN28: 0 | DO28: 0 | DP28: 1 | DQ28: 1 | DU28: 1013 | DV28: 1ШТ. | DW28: 1 ШТ. | DX28: 1 | EE28: 55393976 | EF28: 40 | EG28: Монтаж оборудования | EH28: 0 | EJ28: 2 | EK28: 72 | EL28: ТСН-2001.4-11. Приборы и средства автоматизации и вычислительной техники | EM28: ТСН-2001.4-11-1 | EO28: Поправка: Гл.12.Прил.8.п.8. 3_12.00.01.11.001 Поправка: Гл.4.Прил.2.2.п.2.2.29_04.00.01.35.003 | EQ28: 0 | ER28: 24.82 | ES28: 0 | ET28: 13.3 | EU28: 2.02 | EV28: 11.52 | EW28: 1.03 | EX28: 0 | EY28: 0 | FQ28: 0 | FR28: 0 | FS28: 0 | FX28: 90 | FY28: 46 | GD28: 1 | GF28: 207925144 | GG28: 2 | GH28: 1 | GI28: 2 | GJ28: 0 | GK28: 0 | GL28: =ROUND(IF(AND(BH28=3,BI28=3,FS28<>0),P28,0),2) -> 0 | GM28: =ROUND(O28+X28+Y28,2)+GX28 -> 16.29 | GN28: =IF(OR(BI28=0,BI28=1),GM28-GX28,0) -> 0 | GO28: =IF(BI28=2,GM28-GX28,0) -> 16.29 | GP28: =IF(BI28=4,GM28-GX28,0) -> 0 | GR28: 0 | GS28: 3 | GT28: 0 | GV28: =ROUND((GT28),6) -> 0 | GW28: 1 | GX28: =ROUND(HC28*I28,2) -> 0 | HA28: 0 | HB28: 0 | HC28: =GV28*GW28 -> 0 | HS28: 0 | IK28: 0
A29: 17 | B29: 1 | E29: 1 | F29: 4.11-7-1 | G29: Установка аппарата настольного массой до 0,015 т / демонтаж пульта диспетчера | H29: 1ШТ. | I29: 1 | J29: 0 | K29: 1 | O29: =ROUND(CP29,2) -> 330.03 | P29: =ROUND((ROUND((AC29*AW29*I29),2)*BC29),2) -> 0 | Q29: =(ROUND((ROUND(((((ET29*1.2)*0.3))*AV29*I29),2)*BB29),2)+ROUND((ROUND(((AE29-(((EU29*1.2)*0.3)))*AV29*I29),2)*BS29),2)) -> 85.47 | R29: =(ROUND((ROUND(((((EU29*1.2)*0.3))*AV29*I29),2)*BS29),2)+ROUND((ROUND(((AE29-(((EU29*1.2)*0.3)))*AV29*I29),2)*BS29),2)) -> 42.83 | S29: =ROUND((ROUND((AF29*AV29*I29),2)*BA29),2) -> 244.56 | T29: =ROUND(CU29*I29,2) -> 0 | U29: =CV29*I29 -> 0.3882276 | V29: =CW29*I29 -> 0 | W29: =ROUND(CX29*I29,2) -> 0 | X29: =(ROUND((((S29+ROUND((ROUND(((((EU29*1.2)*0.3))*AV29*I29),2)*BS29),2))*AT29)/100),2)+ROUND(((ROUND((ROUND(((AE29-(((EU29*1.2)*0.3)))*AV29*I29),2)*BS29),2)*AT29)/100),2)) -> 258.65 | Y29: =(ROUND((((S29+ROUND((ROUND(((((EU29*1.2)*0.3))*AV29*I29),2)*BS29),2))*AU29)/100),2)+ROUND(((ROUND((ROUND(((AE29-(((EU29*1.2)*0.3)))*AV29*I29),2)*BS29),2)*AU29)/100),2)) -> 132.2 | AA29: 55943568 | AB29: =ROUND((AC29+AD29+AF29),6) -> 8.9352 | AC29: =ROUND((((ES29*1)*0)),6) -> 0 | AD29: =ROUND((((((ET29*1.2)*0.3))-(((EU29*1.2)*0.3)))+AE29),6) -> 4.788 | AE29: =ROUND((((EU29*1.2)*0.3)),6) -> 0.7272 | AF29: =ROUND((((EV29*1.2)*0.3)),6) -> 4.1472 | AG29: =ROUND((AP29),6) -> 0 | AH29: =(((EW29*1.2)*0.3)) -> 0.3708 | AI29: =(((EX29*1.2)*0.3)) -> 0 | AJ29: =(AS29) -> 0 | AK29: 24.82 | AL29: 0 | AM29: 13.3 | AN29: 2.02 | AO29: 11.52 | AP29: 0 | AQ29: 1.03 | AR29: 0 | AS29: 0 | AT29: 90 | AU29: 46 | AV29: 1.047 | AW29: 1 | AZ29: 1 | BA29: 56.35 | BB29: 17.06 | BC29: 1 | BH29: 0 | BI29: 2 | BJ29: ТСН-2001.4 Доп. 68, Сб. 11, т. 7, поз. 1 | BM29: 72 | BN29: 0 | BO29: 4.11-7-1 | BP29: 1 | BQ29: 40 | BR29: 0 | BS29: 56.35 | BT29: 1 | BU29: 1 | BV29: 1 | BW29: 1 | BX29: 1 | BZ29: 90 | CA29: 46 | CE29: 1566 | CF29: 0 | CG29: 0 | CM29: 0 | CN29: Поправка: Гл.12.Прил.8.п.8. 3_12.00.01.11.001 Наименование: При наличии напряженных и стесненных условий производства работ (стесненность, сложность складирования и транспортной логистики и т.п.) для объектов, расположенных в пределах круговой магистральной системы улиц "Садовое кольцо" города Москвы Поправка: Гл.4.Прил.2.2.п.2.2.29_04.00.01.35.003 Наименование: При демонтаже оборудования, предназначенного в лом | CO29: 0 | CP29: =(P29+Q29+S29) -> 330.03 | CQ29: =ROUND((ROUND((AC29*AW29*1),2)*BC29),2) -> 0 | CR29: =(ROUND((ROUND(((((ET29*1.2)*0.3))*AV29*1),2)*BB29),2)+ROUND((ROUND(((AE29-(((EU29*1.2)*0.3)))*AV29*1),2)*BS29),2)) -> 85.47 | CS29: =(ROUND((ROUND(((((EU29*1.2)*0.3))*AV29*1),2)*BS29),2)+ROUND((ROUND(((AE29-(((EU29*1.2)*0.3)))*AV29*1),2)*BS29),2)) -> 42.83 | CT29: =ROUND((ROUND((AF29*AV29*1),2)*BA29),2) -> 244.56 | CU29: =AG29 -> 0 | CV29: =(AH29*AV29) -> 0.3882276 | CW29: =AI29 -> 0 | CX29: =AJ29 -> 0 | CY29: =(ROUND((((S29+ROUND((ROUND(((((EU29*1.2)*0.3))*AV29*1),2)*BS29),2))*AT29)/100),2)+ROUND(((ROUND((ROUND(((AE29-(((EU29*1.2)*0.3)))*AV29*1),2)*BS29),2)*AT29)/100),2)) -> 258.65 | CZ29: =(ROUND((((S29+ROUND((ROUND(((((EU29*1.2)*0.3))*AV29*1),2)*BS29),2))*AU29)/100),2)+ROUND(((ROUND((ROUND(((AE29-(((EU29*1.2)*0.3)))*AV29*1),2)*BS29),2)*AU29)/100),2)) -> 132.2 | DB29: 3 | DD29: *1)*0 | DE29: *1,2)*0,3 | DF29: *1,2)*0,3 | DG29: *1,2)*0,3 | DI29: *1,2)*0,3 | DJ29: *1,2)*0,3 | DN29: 0 | DO29: 0 | DP29: 1 | DQ29: 1 | DU29: 1013 | DV29: 1ШТ. | DW29: 1 ШТ. | DX29: 1 | EE29: 55393976 | EF29: 40 | EG29: Монтаж оборудования | EH29: 0 | EJ29: 2 | EK29: 72 | EL29: ТСН-2001.4-11. Приборы и средства автоматизации и вычислительной техники | EM29: ТСН-2001.4-11-1 | EO29: Поправка: Гл.12.Прил.8.п.8. 3_12.00.01.11.001 Поправка: Гл.4.Прил.2.2.п.2.2.29_04.00.01.35.003 | EQ29: 0 | ER29: 24.82 | ES29: 0 | ET29: 13.3 | EU29: 2.02 | EV29: 11.52 | EW29: 1.03 | EX29: 0 | EY29: 0 | FQ29: 0 | FR29: 0 | FS29: 0 | FX29: 90 | FY29: 46 | GD29: 1 | GF29: 207925144 | GG29: 2 | GH29: 1 | GI29: 2 | GJ29: 0 | GK29: 0 | GL29: =ROUND(IF(AND(BH29=3,BI29=3,FS29<>0),P29,0),2) -> 0 | GM29: =ROUND(O29+X29+Y29,2)+GX29 -> 720.88 | GN29: =IF(OR(BI29=0,BI29=1),GM29-GX29,0) -> 0 | GO29: =IF(BI29=2,GM29-GX29,0) -> 720.88 | GP29: =IF(BI29=4,GM29-GX29,0) -> 0 | GR29: 0 | GS29: 3 | GT29: 0 | GV29: =ROUND((GT29),6) -> 0 | GW29: 1 | GX29: =ROUND(HC29*I29,2) -> 0 | HA29: 0 | HB29: 0 | HC29: =GV29*GW29 -> 0 | HS29: 0 | IK29: 0
A30: 17 | B30: 1 | E30: 2 | F30: 4.10-34-5 | G30: Монтаж коммутатора служебной связи / демонтаж блока коммутации | H30: 1 ШТ. | I30: =ROUND(4+1,9) -> 5 | J30: 0 | K30: =ROUND(4+1,9) -> 5 | O30: =ROUND(CP30,2) -> 201.56 | P30: =ROUND((ROUND((AC30*AW30*I30),2)*BC30),2) -> 0 | Q30: =(ROUND((ROUND(((((ET30*1.2)*0.3))*AV30*I30),2)*BB30),2)+ROUND((ROUND(((AE30-(((EU30*1.2)*0.3)))*AV30*I30),2)*BS30),2)) -> 54.11 | R30: =(ROUND((ROUND(((((EU30*1.2)*0.3))*AV30*I30),2)*BS30),2)+ROUND((ROUND(((AE30-(((EU30*1.2)*0.3)))*AV30*I30),2)*BS30),2)) -> 5.96 | S30: =ROUND((ROUND((AF30*AV30*I30),2)*BA30),2) -> 147.45 | T30: =ROUND(CU30*I30,2) -> 0 | U30: =CV30*I30 -> 11.68452 | V30: =CW30*I30 -> 0 | W30: =ROUND(CX30*I30,2) -> 0 | X30: =(ROUND((((S30+ROUND((ROUND(((((EU30*1.2)*0.3))*AV30*I30),2)*BS30),2))*AT30)/100),2)+ROUND(((ROUND((ROUND(((AE30-(((EU30*1.2)*0.3)))*AV30*I30),2)*BS30),2)*AT30)/100),2)) -> 138.07 | Y30: =(ROUND((((S30+ROUND((ROUND(((((EU30*1.2)*0.3))*AV30*I30),2)*BS30),2))*AU30)/100),2)+ROUND(((ROUND((ROUND(((AE30-(((EU30*1.2)*0.3)))*AV30*I30),2)*BS30),2)*AU30)/100),2)) -> 70.57 | AA30: 55943566 | AB30: =ROUND((AC30+AD30+AF30),6) -> 38.502 | AC30: =ROUND((((ES30*1)*0)),6) -> 0 | AD30: =ROUND((((((ET30*1.2)*0.3))-(((EU30*1.2)*0.3)))+AE30),6) -> 10.3356 | AE30: =ROUND((((EU30*1.2)*0.3)),6) -> 1.1376 | AF30: =ROUND((((EV30*1.2)*0.3)),6) -> 28.1664 | AG30: =ROUND((AP30),6) -> 0 | AH30: =(((EW30*1.2)*0.3)) -> 2.232 | AI30: =(((EX30*1.2)*0.3)) -> 0 | AJ30: =(AS30) -> 0 | AK30: 119.3 | AL30: 12.35 | AM30: 28.71 | AN30: 3.16 | AO30: 78.24 | AP30: 0 | AQ30: 6.2 | AR30: 0 | AS30: 0 | AT30: 90 | AU30: 46 | AV30: 1.047 | AW30: 1 | AZ30: 1 | BA30: 1 | BB30: 1 | BC30: 1 | BH30: 0 | BI30: 2 | BJ30: ТСН-2001.4 Доп. 80, Сб. 10, т. 34, поз. 5 | BM30: 68 | BN30: 0 | BO30: 4.10-34-5 | BP30: 1 | BQ30: 40 | BR30: 0 | BS30: 1 | BT30: 1 | BU30: 1 | BV30: 1 | BW30: 1 | BX30: 1 | BZ30: 90 | CA30: 46 | CE30: 1566 | CF30: 0 | CG30: 0 | CM30: 0 | CN30: Поправка: Гл.12.Прил.8.п.8. 3_12.00.01.11.001 Наименование: При наличии напряженных и стесненных условий производства работ (стесненность, сложность складирования и транспортной логистики и т.п.) для объектов, расположенных в пределах круговой магистральной системы улиц "Садовое кольцо" города Москвы Поправка: Гл.4.Прил.2.2.п.2.2.29_04.00.01.35.003 Наименование: При демонтаже оборудования, предназначенного в лом | CO30: 0 | CP30: =(P30+Q30+S30) -> 201.56 | CQ30: =ROUND((ROUND((AC30*AW30*1),2)*BC30),2) -> 0 | CR30: =(ROUND((ROUND(((((ET30*1.2)*0.3))*AV30*1),2)*BB30),2)+ROUND((ROUND(((AE30-(((EU30*1.2)*0.3)))*AV30*1),2)*BS30),2)) -> 10.82 | CS30: =(ROUND((ROUND(((((EU30*1.2)*0.3))*AV30*1),2)*BS30),2)+ROUND((ROUND(((AE30-(((EU30*1.2)*0.3)))*AV30*1),2)*BS30),2)) -> 1.19 | CT30: =ROUND((ROUND((AF30*AV30*1),2)*BA30),2) -> 29.49 | CU30: =AG30 -> 0 | CV30: =(AH30*AV30) -> 2.336904 | CW30: =AI30 -> 0 | CX30: =AJ30 -> 0 | CY30: =(ROUND((((S30+ROUND((ROUND(((((EU30*1.2)*0.3))*AV30*1),2)*BS30),2))*AT30)/100),2)+ROUND(((ROUND((ROUND(((AE30-(((EU30*1.2)*0.3)))*AV30*1),2)*BS30),2)*AT30)/100),2)) -> 133.78 | CZ30: =(ROUND((((S30+ROUND((ROUND(((((EU30*1.2)*0.3))*AV30*1),2)*BS30),2))*AU30)/100),2)+ROUND(((ROUND((ROUND(((AE30-(((EU30*1.2)*0.3)))*AV30*1),2)*BS30),2)*AU30)/100),2)) -> 68.37 | DB30: 5 | DD30: *1)*0 | DE30: *1,2)*0,3 | DF30: *1,2)*0,3 | DG30: *1,2)*0,3 | DI30: *1,2)*0,3 | DJ30: *1,2)*0,3 | DN30: 0 | DO30: 0 | DP30: 1 | DQ30: 1 | DU30: 1013 | DV30: 1 ШТ. | DW30: 1 ШТ. | DX30: 1 | EE30: 55393972 | EF30: 40 | EG30: Монтаж оборудования | EH30: 0 | EJ30: 2 | EK30: 68 | EL30: ТСН-2001.4-10. Прокладка и монтаж сетей связи | EM30: ТСН-2001.4-10-1 | EO30: Поправка: Гл.12.Прил.8.п.8. 3_12.00.01.11.001 Поправка: Гл.4.Прил.2.2.п.2.2.29_04.00.01.35.003 | EQ30: 0 | ER30: 119.3 | ES30: 12.35 | ET30: 28.71 | EU30: 3.16 | EV30: 78.24 | EW30: 6.2 | EX30: 0 | EY30: 0 | FQ30: 0 | FR30: 0 | FS30: 0 | FX30: 90 | FY30: 46 | GD30: 1 | GF30: 268219509 | GG30: 2 | GH30: 1 | GI30: 2 | GJ30: 0 | GK30: 0 | GL30: =ROUND(IF(AND(BH30=3,BI30=3,FS30<>0),P30,0),2) -> 0 | GM30: =ROUND(O30+X30+Y30,2)+GX30 -> 410.2 | GN30: =IF(OR(BI30=0,BI30=1),GM30-GX30,0) -> 0 | GO30: =IF(BI30=2,GM30-GX30,0) -> 410.2 | GP30: =IF(BI30=4,GM30-GX30,0) -> 0 | GR30: 0 | GS30: 3 | GT30: 0 | GV30: =ROUND((GT30),6) -> 0 | GW30: 1 | GX30: =ROUND(HC30*I30,2) -> 0 | HA30: 0 | HB30: 0 | HC30: =GV30*GW30 -> 0 | HS30: 0 | IK30: 0
A31: 17 | B31: 1 | E31: 2 | F31: 4.10-34-5 | G31: Монтаж коммутатора служебной связи / демонтаж блока коммутации | H31: 1 ШТ. | I31: =ROUND(4+1,9) -> 5 | J31: 0 | K31: =ROUND(4+1,9) -> 5 | O31: =ROUND(CP31,2) -> 9183.23 | P31: =ROUND((ROUND((AC31*AW31*I31),2)*BC31),2) -> 0 | Q31: =(ROUND((ROUND(((((ET31*1.2)*0.3))*AV31*I31),2)*BB31),2)+ROUND((ROUND(((AE31-(((EU31*1.2)*0.3)))*AV31*I31),2)*BS31),2)) -> 874.42 | R31: =(ROUND((ROUND(((((EU31*1.2)*0.3))*AV31*I31),2)*BS31),2)+ROUND((ROUND(((AE31-(((EU31*1.2)*0.3)))*AV31*I31),2)*BS31),2)) -> 335.85 | S31: =ROUND((ROUND((AF31*AV31*I31),2)*BA31),2) -> 8308.81 | T31: =ROUND(CU31*I31,2) -> 0 | U31: =CV31*I31 -> 11.68452 | V31: =CW31*I31 -> 0 | W31: =ROUND(CX31*I31,2) -> 0 | X31: =(ROUND((((S31+ROUND((ROUND(((((EU31*1.2)*0.3))*AV31*I31),2)*BS31),2))*AT31)/100),2)+ROUND(((ROUND((ROUND(((AE31-(((EU31*1.2)*0.3)))*AV31*I31),2)*BS31),2)*AT31)/100),2)) -> 7780.19 | Y31: =(ROUND((((S31+ROUND((ROUND(((((EU31*1.2)*0.3))*AV31*I31),2)*BS31),2))*AU31)/100),2)+ROUND(((ROUND((ROUND(((AE31-(((EU31*1.2)*0.3)))*AV31*I31),2)*BS31),2)*AU31)/100),2)) -> 3976.54 | AA31: 55943568 | AB31: =ROUND((AC31+AD31+AF31),6) -> 38.502 | AC31: =ROUND((((ES31*1)*0)),6) -> 0 | AD31: =ROUND((((((ET31*1.2)*0.3))-(((EU31*1.2)*0.3)))+AE31),6) -> 10.3356 | AE31: =ROUND((((EU31*1.2)*0.3)),6) -> 1.1376 | AF31: =ROUND((((EV31*1.2)*0.3)),6) -> 28.1664 | AG31: =ROUND((AP31),6) -> 0 | AH31: =(((EW31*1.2)*0.3)) -> 2.232 | AI31: =(((EX31*1.2)*0.3)) -> 0 | AJ31: =(AS31) -> 0 | AK31: 119.3 | AL31: 12.35 | AM31: 28.71 | AN31: 3.16 | AO31: 78.24 | AP31: 0 | AQ31: 6.2 | AR31: 0 | AS31: 0 | AT31: 90 | AU31: 46 | AV31: 1.047 | AW31: 1 | AZ31: 1 | BA31: 56.35 | BB31: 16.16 | BC31: 14.7 | BH31: 0 | BI31: 2 | BJ31: ТСН-2001.4 Доп. 80, Сб. 10, т. 34, поз. 5 | BM31: 68 | BN31: 0 | BO31: 4.10-34-5 | BP31: 1 | BQ31: 40 | BR31: 0 | BS31: 56.35 | BT31: 1 | BU31: 1 | BV31: 1 | BW31: 1 | BX31: 1 | BZ31: 90 | CA31: 46 | CE31: 1566 | CF31: 0 | CG31: 0 | CM31: 0 | CN31: Поправка: Гл.12.Прил.8.п.8. 3_12.00.01.11.001 Наименование: При наличии напряженных и стесненных условий производства работ (стесненность, сложность складирования и транспортной логистики и т.п.) для объектов, расположенных в пределах круговой магистральной системы улиц "Садовое кольцо" города Москвы Поправка: Гл.4.Прил.2.2.п.2.2.29_04.00.01.35.003 Наименование: При демонтаже оборудования, предназначенного в лом | CO31: 0 | CP31: =(P31+Q31+S31) -> 9183.23 | CQ31: =ROUND((ROUND((AC31*AW31*1),2)*BC31),2) -> 0 | CR31: =(ROUND((ROUND(((((ET31*1.2)*0.3))*AV31*1),2)*BB31),2)+ROUND((ROUND(((AE31-(((EU31*1.2)*0.3)))*AV31*1),2)*BS31),2)) -> 174.85 | CS31: =(ROUND((ROUND(((((EU31*1.2)*0.3))*AV31*1),2)*BS31),2)+ROUND((ROUND(((AE31-(((EU31*1.2)*0.3)))*AV31*1),2)*BS31),2)) -> 67.06 | CT31: =ROUND((ROUND((AF31*AV31*1),2)*BA31),2) -> 1661.76 | CU31: =AG31 -> 0 | CV31: =(AH31*AV31) -> 2.336904 | CW31: =AI31 -> 0 | CX31: =AJ31 -> 0 | CY31: =(ROUND((((S31+ROUND((ROUND(((((EU31*1.2)*0.3))*AV31*1),2)*BS31),2))*AT31)/100),2)+ROUND(((ROUND((ROUND(((AE31-(((EU31*1.2)*0.3)))*AV31*1),2)*BS31),2)*AT31)/100),2)) -> 7538.28 | CZ31: =(ROUND((((S31+ROUND((ROUND(((((EU31*1.2)*0.3))*AV31*1),2)*BS31),2))*AU31)/100),2)+ROUND(((ROUND((ROUND(((AE31-(((EU31*1.2)*0.3)))*AV31*1),2)*BS31),2)*AU31)/100),2)) -> 3852.9 | DB31: 7 | DD31: *1)*0 | DE31: *1,2)*0,3 | DF31: *1,2)*0,3 | DG31: *1,2)*0,3 | DI31: *1,2)*0,3 | DJ31: *1,2)*0,3 | DN31: 0 | DO31: 0 | DP31: 1 | DQ31: 1 | DU31: 1013 | DV31: 1 ШТ. | DW31: 1 ШТ. | DX31: 1 | EE31: 55393972 | EF31: 40 | EG31: Монтаж оборудования | EH31: 0 | EJ31: 2 | EK31: 68 | EL31: ТСН-2001.4-10. Прокладка и монтаж сетей связи | EM31: ТСН-2001.4-10-1 | EO31: Поправка: Гл.12.Прил.8.п.8. 3_12.00.01.11.001 Поправка: Гл.4.Прил.2.2.п.2.2.29_04.00.01.35.003 | EQ31: 0 | ER31: 119.3 | ES31: 12.35 | ET31: 28.71 | EU31: 3.16 | EV31: 78.24 | EW31: 6.2 | EX31: 0 | EY31: 0 | FQ31: 0 | FR31: 0 | FS31: 0 | FX31: 90 | FY31: 46 | GD31: 1 | GF31: 268219509 | GG31: 2 | GH31: 1 | GI31: 2 | GJ31: 0 | GK31: 0 | GL31: =ROUND(IF(AND(BH31=3,BI31=3,FS31<>0),P31,0),2) -> 0 | GM31: =ROUND(O31+X31+Y31,2)+GX31 -> 20939.96 | GN31: =IF(OR(BI31=0,BI31=1),GM31-GX31,0) -> 0 | GO31: =IF(BI31=2,GM31-GX31,0) -> 20939.96 | GP31: =IF(BI31=4,GM31-GX31,0) -> 0 | GR31: 0 | GS31: 3 | GT31: 0 | GV31: =ROUND((GT31),6) -> 0 | GW31: 1 | GX31: =ROUND(HC31*I31,2) -> 0 | HA31: 0 | HB31: 0 | HC31: =GV31*GW31 -> 0 | HS31: 0 | IK31: 0
A32: 17 | B32: 1 | E32: 3 | F32: 4.11-1-4 | G32: Монтаж конструкции для установки приборов и средств автоматизации массой до 5 кг / демонтаж стойки считывателя | H32: 1ШТ. | I32: 2 | J32: 0 | K32: 2 | O32: =ROUND(CP32,2) -> 12.94 | P32: =ROUND((ROUND((AC32*AW32*I32),2)*BC32),2) -> 0 | Q32: =(ROUND((ROUND(((((ET32*1.2)*0.3))*AV32*I32),2)*BB32),2)+ROUND((ROUND(((AE32-(((EU32*1.2)*0.3)))*AV32*I32),2)*BS32),2)) -> 4.05 | R32: =(ROUND((ROUND(((((EU32*1.2)*0.3))*AV32*I32),2)*BS32),2)+ROUND((ROUND(((AE32-(((EU32*1.2)*0.3)))*AV32*I32),2)*BS32),2)) -> 0.93 | S32: =ROUND((ROUND((AF32*AV32*I32),2)*BA32),2) -> 8.89 | T32: =ROUND(CU32*I32,2) -> 0 | U32: =CV32*I32 -> 0.7764552 | V32: =CW32*I32 -> 0 | W32: =ROUND(CX32*I32,2) -> 0 | X32: =(ROUND((((S32+ROUND((ROUND(((((EU32*1.2)*0.3))*AV32*I32),2)*BS32),2))*AT32)/100),2)+ROUND(((ROUND((ROUND(((AE32-(((EU32*1.2)*0.3)))*AV32*I32),2)*BS32),2)*AT32)/100),2)) -> 8.84 | Y32: =(ROUND((((S32+ROUND((ROUND(((((EU32*1.2)*0.3))*AV32*I32),2)*BS32),2))*AU32)/100),2)+ROUND(((ROUND((ROUND(((AE32-(((EU32*1.2)*0.3)))*AV32*I32),2)*BS32),2)*AU32)/100),2)) -> 4.52 | AA32: 55943566 | AB32: =ROUND((AC32+AD32+AF32),6) -> 6.1776 | AC32: =ROUND((((ES32*1)*0)),6) -> 0 | AD32: =ROUND((((((ET32*1.2)*0.3))-(((EU32*1.2)*0.3)))+AE32),6) -> 1.9332 | AE32: =ROUND((((EU32*1.2)*0.3)),6) -> 0.4428 | AF32: =ROUND((((EV32*1.2)*0.3)),6) -> 4.2444 | AG32: =ROUND((AP32),6) -> 0 | AH32: =(((EW32*1.2)*0.3)) -> 0.3708 | AI32: =(((EX32*1.2)*0.3)) -> 0 | AJ32: =(AS32) -> 0 | AK32: 68.19 | AL32: 51.03 | AM32: 5.37 | AN32: 1.23 | AO32: 11.79 | AP32: 0 | AQ32: 1.03 | AR32: 0 | AS32: 0 | AT32: 90 | AU32: 46 | AV32: 1.047 | AW32: 1 | AZ32: 1 | BA32: 1 | BB32: 1 | BC32: 1 | BH32: 0 | BI32: 2 | BJ32: ТСН-2001.4 Доп. 79, Сб. 11, т. 1, поз. 4 | BM32: 72 | BN32: 0 | BO32: 4.11-1-4 | BP32: 1 | BQ32: 40 | BR32: 0 | BS32: 1 | BT32: 1 | BU32: 1 | BV32: 1 | BW32: 1 | BX32: 1 | BZ32: 90 | CA32: 46 | CE32: 1566 | CF32: 0 | CG32: 0 | CM32: 0 | CN32: Поправка: Гл.12.Прил.8.п.8. 3_12.00.01.11.001 Наименование: При наличии напряженных и стесненных условий производства работ (стесненность, сложность складирования и транспортной логистики и т.п.) для объектов, расположенных в пределах круговой магистральной системы улиц "Садовое кольцо" города Москвы Поправка: Гл.4.Прил.2.2.п.2.2.29_04.00.01.35.003 Наименование: При демонтаже оборудования, предназначенного в лом | CO32: 0 | CP32: =(P32+Q32+S32) -> 12.94 | CQ32: =ROUND((ROUND((AC32*AW32*1),2)*BC32),2) -> 0 | CR32: =(ROUND((ROUND(((((ET32*1.2)*0.3))*AV32*1),2)*BB32),2)+ROUND((ROUND(((AE32-(((EU32*1.2)*0.3)))*AV32*1),2)*BS32),2)) -> 2.02 | CS32: =(ROUND((ROUND(((((EU32*1.2)*0.3))*AV32*1),2)*BS32),2)+ROUND((ROUND(((AE32-(((EU32*1.2)*0.3)))*AV32*1),2)*BS32),2)) -> 0.46 | CT32: =ROUND((ROUND((AF32*AV32*1),2)*BA32),2) -> 4.44 | CU32: =AG32 -> 0 | CV32: =(AH32*AV32) -> 0.3882276 | CW32: =AI32 -> 0 | CX32: =AJ32 -> 0 | CY32: =(ROUND((((S32+ROUND((ROUND(((((EU32*1.2)*0.3))*AV32*1),2)*BS32),2))*AT32)/100),2)+ROUND(((ROUND((ROUND(((AE32-(((EU32*1.2)*0.3)))*AV32*1),2)*BS32),2)*AT32)/100),2)) -> 8.42 | CZ32: =(ROUND((((S32+ROUND((ROUND(((((EU32*1.2)*0.3))*AV32*1),2)*BS32),2))*AU32)/100),2)+ROUND(((ROUND((ROUND(((AE32-(((EU32*1.2)*0.3)))*AV32*1),2)*BS32),2)*AU32)/100),2)) -> 4.3 | DB32: 9 | DD32: *1)*0 | DE32: *1,2)*0,3 | DF32: *1,2)*0,3 | DG32: *1,2)*0,3 | DI32: *1,2)*0,3 | DJ32: *1,2)*0,3 | DN32: 0 | DO32: 0 | DP32: 1 | DQ32: 1 | DU32: 1013 | DV32: 1ШТ. | DW32: 1 ШТ. | DX32: 1 | EE32: 55393976 | EF32: 40 | EG32: Монтаж оборудования | EH32: 0 | EJ32: 2 | EK32: 72 | EL32: ТСН-2001.4-11. Приборы и средства автоматизации и вычислительной техники | EM32: ТСН-2001.4-11-1 | EO32: Поправка: Гл.12.Прил.8.п.8. 3_12.00.01.11.001 Поправка: Гл.4.Прил.2.2.п.2.2.29_04.00.01.35.003 | EQ32: 0 | ER32: 68.19 | ES32: 51.03 | ET32: 5.37 | EU32: 1.23 | EV32: 11.79 | EW32: 1.03 | EX32: 0 | EY32: 0 | FQ32: 0 | FR32: 0 | FS32: 0 | FX32: 90 | FY32: 46 | GD32: 1 | GF32: 462033332 | GG32: 2 | GH32: 1 | GI32: 2 | GJ32: 0 | GK32: 0 | GL32: =ROUND(IF(AND(BH32=3,BI32=3,FS32<>0),P32,0),2) -> 0 | GM32: =ROUND(O32+X32+Y32,2)+GX32 -> 26.3 | GN32: =IF(OR(BI32=0,BI32=1),GM32-GX32,0) -> 0 | GO32: =IF(BI32=2,GM32-GX32,0) -> 26.3 | GP32: =IF(BI32=4,GM32-GX32,0) -> 0 | GR32: 0 | GS32: 3 | GT32: 0 | GV32: =ROUND((GT32),6) -> 0 | GW32: 1 | GX32: =ROUND(HC32*I32,2) -> 0 | HA32: 0 | HB32: 0 | HC32: =GV32*GW32 -> 0 | HS32: 0 | IK32: 0
A33: 17 | B33: 1 | E33: 3 | F33: 4.11-1-4 | G33: Монтаж конструкции для установки приборов и средств автоматизации массой до 5 кг / демонтаж стойки считывателя | H33: 1ШТ. | I33: 2 | J33: 0 | K33: 2 | O33: =ROUND(CP33,2) -> 592.6 | P33: =ROUND((ROUND((AC33*AW33*I33),2)*BC33),2) -> 0 | Q33: =(ROUND((ROUND(((((ET33*1.2)*0.3))*AV33*I33),2)*BB33),2)+ROUND((ROUND(((AE33-(((EU33*1.2)*0.3)))*AV33*I33),2)*BS33),2)) -> 91.65 | R33: =(ROUND((ROUND(((((EU33*1.2)*0.3))*AV33*I33),2)*BS33),2)+ROUND((ROUND(((AE33-(((EU33*1.2)*0.3)))*AV33*I33),2)*BS33),2)) -> 52.41 | S33: =ROUND((ROUND((AF33*AV33*I33),2)*BA33),2) -> 500.95 | T33: =ROUND(CU33*I33,2) -> 0 | U33: =CV33*I33 -> 0.7764552 | V33: =CW33*I33 -> 0 | W33: =ROUND(CX33*I33,2) -> 0 | X33: =(ROUND((((S33+ROUND((ROUND(((((EU33*1.2)*0.3))*AV33*I33),2)*BS33),2))*AT33)/100),2)+ROUND(((ROUND((ROUND(((AE33-(((EU33*1.2)*0.3)))*AV33*I33),2)*BS33),2)*AT33)/100),2)) -> 498.02 | Y33: =(ROUND((((S33+ROUND((ROUND(((((EU33*1.2)*0.3))*AV33*I33),2)*BS33),2))*AU33)/100),2)+ROUND(((ROUND((ROUND(((AE33-(((EU33*1.2)*0.3)))*AV33*I33),2)*BS33),2)*AU33)/100),2)) -> 254.55 | AA33: 55943568 | AB33: =ROUND((AC33+AD33+AF33),6) -> 6.1776 | AC33: =ROUND((((ES33*1)*0)),6) -> 0 | AD33: =ROUND((((((ET33*1.2)*0.3))-(((EU33*1.2)*0.3)))+AE33),6) -> 1.9332 | AE33: =ROUND((((EU33*1.2)*0.3)),6) -> 0.4428 | AF33: =ROUND((((EV33*1.2)*0.3)),6) -> 4.2444 | AG33: =ROUND((AP33),6) -> 0 | AH33: =(((EW33*1.2)*0.3)) -> 0.3708 | AI33: =(((EX33*1.2)*0.3)) -> 0 | AJ33: =(AS33) -> 0 | AK33: 68.19 | AL33: 51.03 | AM33: 5.37 | AN33: 1.23 | AO33: 11.79 | AP33: 0 | AQ33: 1.03 | AR33: 0 | AS33: 0 | AT33: 90 | AU33: 46 | AV33: 1.047 | AW33: 1 | AZ33: 1 | BA33: 56.35 | BB33: 22.63 | BC33: 8.95 | BH33: 0 | BI33: 2 | BJ33: ТСН-2001.4 Доп. 79, Сб. 11, т. 1, поз. 4 | BM33: 72 | BN33: 0 | BO33: 4.11-1-4 | BP33: 1 | BQ33: 40 | BR33: 0 | BS33: 56.35 | BT33: 1 | BU33: 1 | BV33: 1 | BW33: 1 | BX33: 1 | BZ33: 90 | CA33: 46 | CE33: 1566 | CF33: 0 | CG33: 0 | CM33: 0 | CN33: Поправка: Гл.12.Прил.8.п.8. 3_12.00.01.11.001 Наименование: При наличии напряженных и стесненных условий производства работ (стесненность, сложность складирования и транспортной логистики и т.п.) для объектов, расположенных в пределах круговой магистральной системы улиц "Садовое кольцо" города Москвы Поправка: Гл.4.Прил.2.2.п.2.2.29_04.00.01.35.003 Наименование: При демонтаже оборудования, предназначенного в лом | CO33: 0 | CP33: =(P33+Q33+S33) -> 592.6 | CQ33: =ROUND((ROUND((AC33*AW33*1),2)*BC33),2) -> 0 | CR33: =(ROUND((ROUND(((((ET33*1.2)*0.3))*AV33*1),2)*BB33),2)+ROUND((ROUND(((AE33-(((EU33*1.2)*0.3)))*AV33*1),2)*BS33),2)) -> 45.71 | CS33: =(ROUND((ROUND(((((EU33*1.2)*0.3))*AV33*1),2)*BS33),2)+ROUND((ROUND(((AE33-(((EU33*1.2)*0.3)))*AV33*1),2)*BS33),2)) -> 25.92 | CT33: =ROUND((ROUND((AF33*AV33*1),2)*BA33),2) -> 250.19 | CU33: =AG33 -> 0 | CV33: =(AH33*AV33) -> 0.3882276 | CW33: =AI33 -> 0 | CX33: =AJ33 -> 0 | CY33: =(ROUND((((S33+ROUND((ROUND(((((EU33*1.2)*0.3))*AV33*1),2)*BS33),2))*AT33)/100),2)+ROUND(((ROUND((ROUND(((AE33-(((EU33*1.2)*0.3)))*AV33*1),2)*BS33),2)*AT33)/100),2)) -> 474.18 | CZ33: =(ROUND((((S33+ROUND((ROUND(((((EU33*1.2)*0.3))*AV33*1),2)*BS33),2))*AU33)/100),2)+ROUND(((ROUND((ROUND(((AE33-(((EU33*1.2)*0.3)))*AV33*1),2)*BS33),2)*AU33)/100),2)) -> 242.36 | DB33: 11 | DD33: *1)*0 | DE33: *1,2)*0,3 | DF33: *1,2)*0,3 | DG33: *1,2)*0,3 | DI33: *1,2)*0,3 | DJ33: *1,2)*0,3 | DN33: 0 | DO33: 0 | DP33: 1 | DQ33: 1 | DU33: 1013 | DV33: 1ШТ. | DW33: 1 ШТ. | DX33: 1 | EE33: 55393976 | EF33: 40 | EG33: Монтаж оборудования | EH33: 0 | EJ33: 2 | EK33: 72 | EL33: ТСН-2001.4-11. Приборы и средства автоматизации и вычислительной техники | EM33: ТСН-2001.4-11-1 | EO33: Поправка: Гл.12.Прил.8.п.8. 3_12.00.01.11.001 Поправка: Гл.4.Прил.2.2.п.2.2.29_04.00.01.35.003 | EQ33: 0 | ER33: 68.19 | ES33: 51.03 | ET33: 5.37 | EU33: 1.23 | EV33: 11.79 | EW33: 1.03 | EX33: 0 | EY33: 0 | FQ33: 0 | FR33: 0 | FS33: 0 | FX33: 90 | FY33: 46 | GD33: 1 | GF33: 462033332 | GG33: 2 | GH33: 1 | GI33: 2 | GJ33: 0 | GK33: 0 | GL33: =ROUND(IF(AND(BH33=3,BI33=3,FS33<>0),P33,0),2) -> 0 | GM33: =ROUND(O33+X33+Y33,2)+GX33 -> 1345.17 | GN33: =IF(OR(BI33=0,BI33=1),GM33-GX33,0) -> 0 | GO33: =IF(BI33=2,GM33-GX33,0) -> 1345.17 | GP33: =IF(BI33=4,GM33-GX33,0) -> 0 | GR33: 0 | GS33: 3 | GT33: 0 | GV33: =ROUND((GT33),6) -> 0 | GW33: 1 | GX33: =ROUND(HC33*I33,2) -> 0 | HA33: 0 | HB33: 0 | HC33: =GV33*GW33 -> 0 | HS33: 0 | IK33: 0
A34: 17 | B34: 1 | E34: 4 | F34: 4.10-76-10 | G34: Монтаж ключа или кнопки на панели / демонтаж кнопки вызова | H34: 1ШТ. | I34: 2 | J34: 0 | K34: 2 | O34: =ROUND(CP34,2) -> 8.96 | P34: =ROUND((ROUND((AC34*AW34*I34),2)*BC34),2) -> 0 | Q34: =(ROUND((ROUND(((((ET34*1.2)*0.3))*AV34*I34),2)*BB34),2)+ROUND((ROUND(((AE34-(((EU34*1.2)*0.3)))*AV34*I34),2)*BS34),2)) -> 0 | R34: =(ROUND((ROUND(((((EU34*1.2)*0.3))*AV34*I34),2)*BS34),2)+ROUND((ROUND(((AE34-(((EU34*1.2)*0.3)))*AV34*I34),2)*BS34),2)) -> 0 | S34: =ROUND((ROUND((AF34*AV34*I34),2)*BA34),2) -> 8.96 | T34: =ROUND(CU34*I34,2) -> 0 | U34: =CV34*I34 -> 0.75384 | V34: =CW34*I34 -> 0 | W34: =ROUND(CX34*I34,2) -> 0 | X34: =(ROUND((((S34+ROUND((ROUND(((((EU34*1.2)*0.3))*AV34*I34),2)*BS34),2))*AT34)/100),2)+ROUND(((ROUND((ROUND(((AE34-(((EU34*1.2)*0.3)))*AV34*I34),2)*BS34),2)*AT34)/100),2)) -> 8.51 | Y34: =(ROUND((((S34+ROUND((ROUND(((((EU34*1.2)*0.3))*AV34*I34),2)*BS34),2))*AU34)/100),2)+ROUND(((ROUND((ROUND(((AE34-(((EU34*1.2)*0.3)))*AV34*I34),2)*BS34),2)*AU34)/100),2)) -> 4.75 | AA34: 55943566 | AB34: =ROUND((AC34+AD34+AF34),6) -> 4.2804 | AC34: =ROUND((((ES34*1)*0)),6) -> 0 | AD34: =ROUND((((((ET34*1.2)*0.3))-(((EU34*1.2)*0.3)))+AE34),6) -> 0 | AE34: =ROUND((((EU34*1.2)*0.3)),6) -> 0 | AF34: =ROUND((((EV34*1.2)*0.3)),6) -> 4.2804 | AG34: =ROUND((AP34),6) -> 0 | AH34: =(((EW34*1.2)*0.3)) -> 0.36 | AI34: =(((EX34*1.2)*0.3)) -> 0 | AJ34: =(AS34) -> 0 | AK34: 13.56 | AL34: 1.67 | AM34: 0 | AN34: 0 | AO34: 11.89 | AP34: 0 | AQ34: 1 | AR34: 0 | AS34: 0 | AT34: 95 | AU34: 53 | AV34: 1.047 | AW34: 1 | AZ34: 1 | BA34: 1 | BB34: 1 | BC34: 1 | BH34: 0 | BI34: 2 | BJ34: ТСН-2001.4 Доп. 79, Сб. 10, т. 76, поз. 10 | BM34: 69 | BN34: 0 | BO34: 4.10-76-10 | BP34: 1 | BQ34: 40 | BR34: 0 | BS34: 1 | BT34: 1 | BU34: 1 | BV34: 1 | BW34: 1 | BX34: 1 | BZ34: 95 | CA34: 53 | CE34: 1566 | CF34: 0 | CG34: 0 | CM34: 0 | CN34: Поправка: Гл.12.Прил.8.п.8. 3_12.00.01.11.001 Наименование: При наличии напряженных и стесненных условий производства работ (стесненность, сложность складирования и транспортной логистики и т.п.) для объектов, расположенных в пределах круговой магистральной системы улиц "Садовое кольцо" города Москвы Поправка: Гл.4.Прил.2.2.п.2.2.29_04.00.01.35.003 Наименование: При демонтаже оборудования, предназначенного в лом | CO34: 0 | CP34: =(P34+Q34+S34) -> 8.96 | CQ34: =ROUND((ROUND((AC34*AW34*1),2)*BC34),2) -> 0 | CR34: =(ROUND((ROUND(((((ET34*1.2)*0.3))*AV34*1),2)*BB34),2)+ROUND((ROUND(((AE34-(((EU34*1.2)*0.3)))*AV34*1),2)*BS34),2)) -> 0 | CS34: =(ROUND((ROUND(((((EU34*1.2)*0.3))*AV34*1),2)*BS34),2)+ROUND((ROUND(((AE34-(((EU34*1.2)*0.3)))*AV34*1),2)*BS34),2)) -> 0 | CT34: =ROUND((ROUND((AF34*AV34*1),2)*BA34),2) -> 4.48 | CU34: =AG34 -> 0 | CV34: =(AH34*AV34) -> 0.37692 | CW34: =AI34 -> 0 | CX34: =AJ34 -> 0 | CY34: =(ROUND((((S34+ROUND((ROUND(((((EU34*1.2)*0.3))*AV34*1),2)*BS34),2))*AT34)/100),2)+ROUND(((ROUND((ROUND(((AE34-(((EU34*1.2)*0.3)))*AV34*1),2)*BS34),2)*AT34)/100),2)) -> 8.51 | CZ34: =(ROUND((((S34+ROUND((ROUND(((((EU34*1.2)*0.3))*AV34*1),2)*BS34),2))*AU34)/100),2)+ROUND(((ROUND((ROUND(((AE34-(((EU34*1.2)*0.3)))*AV34*1),2)*BS34),2)*AU34)/100),2)) -> 4.75 | DB34: 13 | DD34: *1)*0 | DE34: *1,2)*0,3 | DF34: *1,2)*0,3 | DG34: *1,2)*0,3 | DI34: *1,2)*0,3 | DJ34: *1,2)*0,3 | DN34: 0 | DO34: 0 | DP34: 1 | DQ34: 1 | DU34: 1013 | DV34: 1ШТ. | DW34: 1 ШТ. | DX34: 1 | EE34: 55393973 | EF34: 40 | EG34: Монтаж оборудования | EH34: 0 | EJ34: 2 | EK34: 69 | EL34: ТСН-2001.4-10. Монтаж радиотелевизионного и электронного оборудования | EM34: ТСН-2001.4-10-2 | EO34: Поправка: Гл.12.Прил.8.п.8. 3_12.00.01.11.001 Поправка: Гл.4.Прил.2.2.п.2.2.29_04.00.01.35.003 | EQ34: 0 | ER34: 13.56 | ES34: 1.67 | ET34: 0 | EU34: 0 | EV34: 11.89 | EW34: 1 | EX34: 0 | EY34: 0 | FQ34: 0 | FR34: 0 | FS34: 0 | FX34: 95 | FY34: 53 | GD34: 1 | GF34: 1926572578 | GG34: 2 | GH34: 1 | GI34: 2 | GJ34: 0 | GK34: 0 | GL34: =ROUND(IF(AND(BH34=3,BI34=3,FS34<>0),P34,0),2) -> 0 | GM34: =ROUND(O34+X34+Y34,2)+GX34 -> 22.22 | GN34: =IF(OR(BI34=0,BI34=1),GM34-GX34,0) -> 0 | GO34: =IF(BI34=2,GM34-GX34,0) -> 22.22 | GP34: =IF(BI34=4,GM34-GX34,0) -> 0 | GR34: 0 | GS34: 3 | GT34: 0 | GV34: =ROUND((GT34),6) -> 0 | GW34: 1 | GX34: =ROUND(HC34*I34,2) -> 0 | HA34: 0 | HB34: 0 | HC34: =GV34*GW34 -> 0 | HS34: 0 | IK34: 0
A35: 17 | B35: 1 | E35: 4 | F35: 4.10-76-10 | G35: Монтаж ключа или кнопки на панели / демонтаж кнопки вызова | H35: 1ШТ. | I35: 2 | J35: 0 | K35: 2 | O35: =ROUND(CP35,2) -> 504.9 | P35: =ROUND((ROUND((AC35*AW35*I35),2)*BC35),2) -> 0 | Q35: =(ROUND((ROUND(((((ET35*1.2)*0.3))*AV35*I35),2)*BB35),2)+ROUND((ROUND(((AE35-(((EU35*1.2)*0.3)))*AV35*I35),2)*BS35),2)) -> 0 | R35: =(ROUND((ROUND(((((EU35*1.2)*0.3))*AV35*I35),2)*BS35),2)+ROUND((ROUND(((AE35-(((EU35*1.2)*0.3)))*AV35*I35),2)*BS35),2)) -> 0 | S35: =ROUND((ROUND((AF35*AV35*I35),2)*BA35),2) -> 504.9 | T35: =ROUND(CU35*I35,2) -> 0 | U35: =CV35*I35 -> 0.75384 | V35: =CW35*I35 -> 0 | W35: =ROUND(CX35*I35,2) -> 0 | X35: =(ROUND((((S35+ROUND((ROUND(((((EU35*1.2)*0.3))*AV35*I35),2)*BS35),2))*AT35)/100),2)+ROUND(((ROUND((ROUND(((AE35-(((EU35*1.2)*0.3)))*AV35*I35),2)*BS35),2)*AT35)/100),2)) -> 479.66 | Y35: =(ROUND((((S35+ROUND((ROUND(((((EU35*1.2)*0.3))*AV35*I35),2)*BS35),2))*AU35)/100),2)+ROUND(((ROUND((ROUND(((AE35-(((EU35*1.2)*0.3)))*AV35*I35),2)*BS35),2)*AU35)/100),2)) -> 267.6 | AA35: 55943568 | AB35: =ROUND((AC35+AD35+AF35),6) -> 4.2804 | AC35: =ROUND((((ES35*1)*0)),6) -> 0 | AD35: =ROUND((((((ET35*1.2)*0.3))-(((EU35*1.2)*0.3)))+AE35),6) -> 0 | AE35: =ROUND((((EU35*1.2)*0.3)),6) -> 0 | AF35: =ROUND((((EV35*1.2)*0.3)),6) -> 4.2804 | AG35: =ROUND((AP35),6) -> 0 | AH35: =(((EW35*1.2)*0.3)) -> 0.36 | AI35: =(((EX35*1.2)*0.3)) -> 0 | AJ35: =(AS35) -> 0 | AK35: 13.56 | AL35: 1.67 | AM35: 0 | AN35: 0 | AO35: 11.89 | AP35: 0 | AQ35: 1 | AR35: 0 | AS35: 0 | AT35: 95 | AU35: 53 | AV35: 1.047 | AW35: 1 | AZ35: 1 | BA35: 56.35 | BB35: 1 | BC35: 17.87 | BH35: 0 | BI35: 2 | BJ35: ТСН-2001.4 Доп. 79, Сб. 10, т. 76, поз. 10 | BM35: 69 | BN35: 0 | BO35: 4.10-76-10 | BP35: 1 | BQ35: 40 | BR35: 0 | BS35: 56.35 | BT35: 1 | BU35: 1 | BV35: 1 | BW35: 1 | BX35: 1 | BZ35: 95 | CA35: 53 | CE35: 1566 | CF35: 0 | CG35: 0 | CM35: 0 | CN35: Поправка: Гл.12.Прил.8.п.8. 3_12.00.01.11.001 Наименование: При наличии напряженных и стесненных условий производства работ (стесненность, сложность складирования и транспортной логистики и т.п.) для объектов, расположенных в пределах круговой магистральной системы улиц "Садовое кольцо" города Москвы Поправка: Гл.4.Прил.2.2.п.2.2.29_04.00.01.35.003 Наименование: При демонтаже оборудования, предназначенного в лом | CO35: 0 | CP35: =(P35+Q35+S35) -> 504.9 | CQ35: =ROUND((ROUND((AC35*AW35*1),2)*BC35),2) -> 0 | CR35: =(ROUND((ROUND(((((ET35*1.2)*0.3))*AV35*1),2)*BB35),2)+ROUND((ROUND(((AE35-(((EU35*1.2)*0.3)))*AV35*1),2)*BS35),2)) -> 0 | CS35: =(ROUND((ROUND(((((EU35*1.2)*0.3))*AV35*1),2)*BS35),2)+ROUND((ROUND(((AE35-(((EU35*1.2)*0.3)))*AV35*1),2)*BS35),2)) -> 0 | CT35: =ROUND((ROUND((AF35*AV35*1),2)*BA35),2) -> 252.45 | CU35: =AG35 -> 0 | CV35: =(AH35*AV35) -> 0.37692 | CW35: =AI35 -> 0 | CX35: =AJ35 -> 0 | CY35: =(ROUND((((S35+ROUND((ROUND(((((EU35*1.2)*0.3))*AV35*1),2)*BS35),2))*AT35)/100),2)+ROUND(((ROUND((ROUND(((AE35-(((EU35*1.2)*0.3)))*AV35*1),2)*BS35),2)*AT35)/100),2)) -> 479.66 | CZ35: =(ROUND((((S35+ROUND((ROUND(((((EU35*1.2)*0.3))*AV35*1),2)*BS35),2))*AU35)/100),2)+ROUND(((ROUND((ROUND(((AE35-(((EU35*1.2)*0.3)))*AV35*1),2)*BS35),2)*AU35)/100),2)) -> 267.6 | DB35: 15 | DD35: *1)*0 | DE35: *1,2)*0,3 | DF35: *1,2)*0,3 | DG35: *1,2)*0,3 | DI35: *1,2)*0,3 | DJ35: *1,2)*0,3 | DN35: 0 | DO35: 0 | DP35: 1 | DQ35: 1 | DU35: 1013 | DV35: 1ШТ. | DW35: 1 ШТ. | DX35: 1 | EE35: 55393973 | EF35: 40 | EG35: Монтаж оборудования | EH35: 0 | EJ35: 2 | EK35: 69 | EL35: ТСН-2001.4-10. Монтаж радиотелевизионного и электронного оборудования | EM35: ТСН-2001.4-10-2 | EO35: Поправка: Гл.12.Прил.8.п.8. 3_12.00.01.11.001 Поправка: Гл.4.Прил.2.2.п.2.2.29_04.00.01.35.003 | EQ35: 0 | ER35: 13.56 | ES35: 1.67 | ET35: 0 | EU35: 0 | EV35: 11.89 | EW35: 1 | EX35: 0 | EY35: 0 | FQ35: 0 | FR35: 0 | FS35: 0 | FX35: 95 | FY35: 53 | GD35: 1 | GF35: 1926572578 | GG35: 2 | GH35: 1 | GI35: 2 | GJ35: 0 | GK35: 0 | GL35: =ROUND(IF(AND(BH35=3,BI35=3,FS35<>0),P35,0),2) -> 0 | GM35: =ROUND(O35+X35+Y35,2)+GX35 -> 1252.16 | GN35: =IF(OR(BI35=0,BI35=1),GM35-GX35,0) -> 0 | GO35: =IF(BI35=2,GM35-GX35,0) -> 1252.16 | GP35: =IF(BI35=4,GM35-GX35,0) -> 0 | GR35: 0 | GS35: 3 | GT35: 0 | GV35: =ROUND((GT35),6) -> 0 | GW35: 1 | GX35: =ROUND(HC35*I35,2) -> 0 | HA35: 0 | HB35: 0 | HC35: =GV35*GW35 -> 0 | HS35: 0 | IK35: 0
A36: 17 | B36: 1 | E36: 5 | F36: 4.10-76-15 | G36: Монтаж транспаранта светового (табло) / демонтаж светозвукового сигнализитора | H36: 1ШТ. | I36: 1 | J36: 0 | K36: 1 | O36: =ROUND(CP36,2) -> 9.51 | P36: =ROUND((ROUND((AC36*AW36*I36),2)*BC36),2) -> 0 | Q36: =(ROUND((ROUND(((((ET36*1.2)*0.3))*AV36*I36),2)*BB36),2)+ROUND((ROUND(((AE36-(((EU36*1.2)*0.3)))*AV36*I36),2)*BS36),2)) -> 0 | R36: =(ROUND((ROUND(((((EU36*1.2)*0.3))*AV36*I36),2)*BS36),2)+ROUND((ROUND(((AE36-(((EU36*1.2)*0.3)))*AV36*I36),2)*BS36),2)) -> 0 | S36: =ROUND((ROUND((AF36*AV36*I36),2)*BA36),2) -> 9.51 | T36: =ROUND(CU36*I36,2) -> 0 | U36: =CV36*I36 -> 0.75384 | V36: =CW36*I36 -> 0 | W36: =ROUND(CX36*I36,2) -> 0 | X36: =(ROUND((((S36+ROUND((ROUND(((((EU36*1.2)*0.3))*AV36*I36),2)*BS36),2))*AT36)/100),2)+ROUND(((ROUND((ROUND(((AE36-(((EU36*1.2)*0.3)))*AV36*I36),2)*BS36),2)*AT36)/100),2)) -> 9.03 | Y36: =(ROUND((((S36+ROUND((ROUND(((((EU36*1.2)*0.3))*AV36*I36),2)*BS36),2))*AU36)/100),2)+ROUND(((ROUND((ROUND(((AE36-(((EU36*1.2)*0.3)))*AV36*I36),2)*BS36),2)*AU36)/100),2)) -> 5.04 | AA36: 55943566 | AB36: =ROUND((AC36+AD36+AF36),6) -> 9.0864 | AC36: =ROUND((((ES36*1)*0)),6) -> 0 | AD36: =ROUND((((((ET36*1.2)*0.3))-(((EU36*1.2)*0.3)))+AE36),6) -> 0 | AE36: =ROUND((((EU36*1.2)*0.3)),6) -> 0 | AF36: =ROUND((((EV36*1.2)*0.3)),6) -> 9.0864 | AG36: =ROUND((AP36),6) -> 0 | AH36: =(((EW36*1.2)*0.3)) -> 0.72 | AI36: =(((EX36*1.2)*0.3)) -> 0 | AJ36: =(AS36) -> 0 | AK36: 32.96 | AL36: 7.72 | AM36: 0 | AN36: 0 | AO36: 25.24 | AP36: 0 | AQ36: 2 | AR36: 0 | AS36: 0 | AT36: 95 | AU36: 53 | AV36: 1.047 | AW36: 1 | AZ36: 1 | BA36: 1 | BB36: 1 | BC36: 1 | BH36: 0 | BI36: 2 | BJ36: ТСН-2001.4 Доп. 67, Сб. 10, т. 76, поз. 15 | BM36: 69 | BN36: 0 | BO36: 4.10-76-15 | BP36: 1 | BQ36: 40 | BR36: 0 | BS36: 1 | BT36: 1 | BU36: 1 | BV36: 1 | BW36: 1 | BX36: 1 | BZ36: 95 | CA36: 53 | CE36: 1566 | CF36: 0 | CG36: 0 | CM36: 0 | CN36: Поправка: Гл.12.Прил.8.п.8. 3_12.00.01.11.001 Наименование: При наличии напряженных и стесненных условий производства работ (стесненность, сложность складирования и транспортной логистики и т.п.) для объектов, расположенных в пределах круговой магистральной системы улиц "Садовое кольцо" города Москвы Поправка: Гл.4.Прил.2.2.п.2.2.29_04.00.01.35.003 Наименование: При демонтаже оборудования, предназначенного в лом | CO36: 0 | CP36: =(P36+Q36+S36) -> 9.51 | CQ36: =ROUND((ROUND((AC36*AW36*1),2)*BC36),2) -> 0 | CR36: =(ROUND((ROUND(((((ET36*1.2)*0.3))*AV36*1),2)*BB36),2)+ROUND((ROUND(((AE36-(((EU36*1.2)*0.3)))*AV36*1),2)*BS36),2)) -> 0 | CS36: =(ROUND((ROUND(((((EU36*1.2)*0.3))*AV36*1),2)*BS36),2)+ROUND((ROUND(((AE36-(((EU36*1.2)*0.3)))*AV36*1),2)*BS36),2)) -> 0 | CT36: =ROUND((ROUND((AF36*AV36*1),2)*BA36),2) -> 9.51 | CU36: =AG36 -> 0 | CV36: =(AH36*AV36) -> 0.75384 | CW36: =AI36 -> 0 | CX36: =AJ36 -> 0 | CY36: =(ROUND((((S36+ROUND((ROUND(((((EU36*1.2)*0.3))*AV36*1),2)*BS36),2))*AT36)/100),2)+ROUND(((ROUND((ROUND(((AE36-(((EU36*1.2)*0.3)))*AV36*1),2)*BS36),2)*AT36)/100),2)) -> 9.03 | CZ36: =(ROUND((((S36+ROUND((ROUND(((((EU36*1.2)*0.3))*AV36*1),2)*BS36),2))*AU36)/100),2)+ROUND(((ROUND((ROUND(((AE36-(((EU36*1.2)*0.3)))*AV36*1),2)*BS36),2)*AU36)/100),2)) -> 5.04 | DB36: 17 | DD36: *1)*0 | DE36: *1,2)*0,3 | DF36: *1,2)*0,3 | DG36: *1,2)*0,3 | DI36: *1,2)*0,3 | DJ36: *1,2)*0,3 | DN36: 0 | DO36: 0 | DP36: 1 | DQ36: 1 | DU36: 1013 | DV36: 1ШТ. | DW36: 1 ШТ. | DX36: 1 | EE36: 55393973 | EF36: 40 | EG36: Монтаж оборудования | EH36: 0 | EJ36: 2 | EK36: 69 | EL36: ТСН-2001.4-10. Монтаж радиотелевизионного и электронного оборудования | EM36: ТСН-2001.4-10-2 | EO36: Поправка: Гл.12.Прил.8.п.8. 3_12.00.01.11.001 Поправка: Гл.4.Прил.2.2.п.2.2.29_04.00.01.35.003 | EQ36: 0 | ER36: 32.96 | ES36: 7.72 | ET36: 0 | EU36: 0 | EV36: 25.24 | EW36: 2 | EX36: 0 | EY36: 0 | FQ36: 0 | FR36: 0 | FS36: 0 | FX36: 95 | FY36: 53 | GD36: 1 | GF36: 826094471 | GG36: 2 | GH36: 1 | GI36: 2 | GJ36: 0 | GK36: 0 | GL36: =ROUND(IF(AND(BH36=3,BI36=3,FS36<>0),P36,0),2) -> 0 | GM36: =ROUND(O36+X36+Y36,2)+GX36 -> 23.58 | GN36: =IF(OR(BI36=0,BI36=1),GM36-GX36,0) -> 0 | GO36: =IF(BI36=2,GM36-GX36,0) -> 23.58 | GP36: =IF(BI36=4,GM36-GX36,0) -> 0 | GR36: 0 | GS36: 3 | GT36: 0 | GV36: =ROUND((GT36),6) -> 0 | GW36: 1 | GX36: =ROUND(HC36*I36,2) -> 0 | HA36: 0 | HB36: 0 | HC36: =GV36*GW36 -> 0 | HS36: 0 | IK36: 0
A37: 17 | B37: 1 | E37: 5 | F37: 4.10-76-15 | G37: Монтаж транспаранта светового (табло) / демонтаж светозвукового сигнализитора | H37: 1ШТ. | I37: 1 | J37: 0 | K37: 1 | O37: =ROUND(CP37,2) -> 535.89 | P37: =ROUND((ROUND((AC37*AW37*I37),2)*BC37),2) -> 0 | Q37: =(ROUND((ROUND(((((ET37*1.2)*0.3))*AV37*I37),2)*BB37),2)+ROUND((ROUND(((AE37-(((EU37*1.2)*0.3)))*AV37*I37),2)*BS37),2)) -> 0 | R37: =(ROUND((ROUND(((((EU37*1.2)*0.3))*AV37*I37),2)*BS37),2)+ROUND((ROUND(((AE37-(((EU37*1.2)*0.3)))*AV37*I37),2)*BS37),2)) -> 0 | S37: =ROUND((ROUND((AF37*AV37*I37),2)*BA37),2) -> 535.89 | T37: =ROUND(CU37*I37,2) -> 0 | U37: =CV37*I37 -> 0.75384 | V37: =CW37*I37 -> 0 | W37: =ROUND(CX37*I37,2) -> 0 | X37: =(ROUND((((S37+ROUND((ROUND(((((EU37*1.2)*0.3))*AV37*I37),2)*BS37),2))*AT37)/100),2)+ROUND(((ROUND((ROUND(((AE37-(((EU37*1.2)*0.3)))*AV37*I37),2)*BS37),2)*AT37)/100),2)) -> 509.1 | Y37: =(ROUND((((S37+ROUND((ROUND(((((EU37*1.2)*0.3))*AV37*I37),2)*BS37),2))*AU37)/100),2)+ROUND(((ROUND((ROUND(((AE37-(((EU37*1.2)*0.3)))*AV37*I37),2)*BS37),2)*AU37)/100),2)) -> 284.02 | AA37: 55943568 | AB37: =ROUND((AC37+AD37+AF37),6) -> 9.0864 | AC37: =ROUND((((ES37*1)*0)),6) -> 0 | AD37: =ROUND((((((ET37*1.2)*0.3))-(((EU37*1.2)*0.3)))+AE37),6) -> 0 | AE37: =ROUND((((EU37*1.2)*0.3)),6) -> 0 | AF37: =ROUND((((EV37*1.2)*0.3)),6) -> 9.0864 | AG37: =ROUND((AP37),6) -> 0 | AH37: =(((EW37*1.2)*0.3)) -> 0.72 | AI37: =(((EX37*1.2)*0.3)) -> 0 | AJ37: =(AS37) -> 0 | AK37: 32.96 | AL37: 7.72 | AM37: 0 | AN37: 0 | AO37: 25.24 | AP37: 0 | AQ37: 2 | AR37: 0 | AS37: 0 | AT37: 95 | AU37: 53 | AV37: 1.047 | AW37: 1 | AZ37: 1 | BA37: 56.35 | BB37: 1 | BC37: 7.17 | BH37: 0 | BI37: 2 | BJ37: ТСН-2001.4 Доп. 67, Сб. 10, т. 76, поз. 15 | BM37: 69 | BN37: 0 | BO37: 4.10-76-15 | BP37: 1 | BQ37: 40 | BR37: 0 | BS37: 56.35 | BT37: 1 | BU37: 1 | BV37: 1 | BW37: 1 | BX37: 1 | BZ37: 95 | CA37: 53 | CE37: 1566 | CF37: 0 | CG37: 0 | CM37: 0 | CN37: Поправка: Гл.12.Прил.8.п.8. 3_12.00.01.11.001 Наименование: При наличии напряженных и стесненных условий производства работ (стесненность, сложность складирования и транспортной логистики и т.п.) для объектов, расположенных в пределах круговой магистральной системы улиц "Садовое кольцо" города Москвы Поправка: Гл.4.Прил.2.2.п.2.2.29_04.00.01.35.003 Наименование: При демонтаже оборудования, предназначенного в лом | CO37: 0 | CP37: =(P37+Q37+S37) -> 535.89 | CQ37: =ROUND((ROUND((AC37*AW37*1),2)*BC37),2) -> 0 | CR37: =(ROUND((ROUND(((((ET37*1.2)*0.3))*AV37*1),2)*BB37),2)+ROUND((ROUND(((AE37-(((EU37*1.2)*0.3)))*AV37*1),2)*BS37),2)) -> 0 | CS37: =(ROUND((ROUND(((((EU37*1.2)*0.3))*AV37*1),2)*BS37),2)+ROUND((ROUND(((AE37-(((EU37*1.2)*0.3)))*AV37*1),2)*BS37),2)) -> 0 | CT37: =ROUND((ROUND((AF37*AV37*1),2)*BA37),2) -> 535.89 | CU37: =AG37 -> 0 | CV37: =(AH37*AV37) -> 0.75384 | CW37: =AI37 -> 0 | CX37: =AJ37 -> 0 | CY37: =(ROUND((((S37+ROUND((ROUND(((((EU37*1.2)*0.3))*AV37*1),2)*BS37),2))*AT37)/100),2)+ROUND(((ROUND((ROUND(((AE37-(((EU37*1.2)*0.3)))*AV37*1),2)*BS37),2)*AT37)/100),2)) -> 509.1 | CZ37: =(ROUND((((S37+ROUND((ROUND(((((EU37*1.2)*0.3))*AV37*1),2)*BS37),2))*AU37)/100),2)+ROUND(((ROUND((ROUND(((AE37-(((EU37*1.2)*0.3)))*AV37*1),2)*BS37),2)*AU37)/100),2)) -> 284.02 | DB37: 19 | DD37: *1)*0 | DE37: *1,2)*0,3 | DF37: *1,2)*0,3 | DG37: *1,2)*0,3 | DI37: *1,2)*0,3 | DJ37: *1,2)*0,3 | DN37: 0 | DO37: 0 | DP37: 1 | DQ37: 1 | DU37: 1013 | DV37: 1ШТ. | DW37: 1 ШТ. | DX37: 1 | EE37: 55393973 | EF37: 40 | EG37: Монтаж оборудования | EH37: 0 | EJ37: 2 | EK37: 69 | EL37: ТСН-2001.4-10. Монтаж радиотелевизионного и электронного оборудования | EM37: ТСН-2001.4-10-2 | EO37: Поправка: Гл.12.Прил.8.п.8. 3_12.00.01.11.001 Поправка: Гл.4.Прил.2.2.п.2.2.29_04.00.01.35.003 | EQ37: 0 | ER37: 32.96 | ES37: 7.72 | ET37: 0 | EU37: 0 | EV37: 25.24 | EW37: 2 | EX37: 0 | EY37: 0 | FQ37: 0 | FR37: 0 | FS37: 0 | FX37: 95 | FY37: 53 | GD37: 1 | GF37: 826094471 | GG37: 2 | GH37: 1 | GI37: 2 | GJ37: 0 | GK37: 0 | GL37: =ROUND(IF(AND(BH37=3,BI37=3,FS37<>0),P37,0),2) -> 0 | GM37: =ROUND(O37+X37+Y37,2)+GX37 -> 1329.01 | GN37: =IF(OR(BI37=0,BI37=1),GM37-GX37,0) -> 0 | GO37: =IF(BI37=2,GM37-GX37,0) -> 1329.01 | GP37: =IF(BI37=4,GM37-GX37,0) -> 0 | GR37: 0 | GS37: 3 | GT37: 0 | GV37: =ROUND((GT37),6) -> 0 | GW37: 1 | GX37: =ROUND(HC37*I37,2) -> 0 | HA37: 0 | HB37: 0 | HC37: =GV37*GW37 -> 0 | HS37: 0 | IK37: 0
A38: 17 | B38: 1 | E38: 6 | F38: 4.10-177-1 | G38: Монтаж устройства связи с согласующим устройством (вызывная панель) / демонтаж абонентского переговорного устройства | H38: 10 шт. | I38: =ROUND(31/10,9) -> 3.1 | J38: 0 | K38: =ROUND(31/10,9) -> 3.1 | O38: =ROUND(CP38,2) -> 272.84 | P38: =ROUND((ROUND((AC38*AW38*I38),2)*BC38),2) -> 0 | Q38: =(ROUND((ROUND(((((ET38*1.2)*0.3))*AV38*I38),2)*BB38),2)+ROUND((ROUND(((AE38-(((EU38*1.2)*0.3)))*AV38*I38),2)*BS38),2)) -> 7.09 | R38: =(ROUND((ROUND(((((EU38*1.2)*0.3))*AV38*I38),2)*BS38),2)+ROUND((ROUND(((AE38-(((EU38*1.2)*0.3)))*AV38*I38),2)*BS38),2)) -> 0.89 | S38: =ROUND((ROUND((AF38*AV38*I38),2)*BA38),2) -> 265.75 | T38: =ROUND(CU38*I38,2) -> 0 | U38: =CV38*I38 -> 17.106137 | V38: =CW38*I38 -> 0 | W38: =ROUND(CX38*I38,2) -> 0 | X38: =(ROUND((((S38+ROUND((ROUND(((((EU38*1.2)*0.3))*AV38*I38),2)*BS38),2))*AT38)/100),2)+ROUND(((ROUND((ROUND(((AE38-(((EU38*1.2)*0.3)))*AV38*I38),2)*BS38),2)*AT38)/100),2)) -> 239.98 | Y38: =(ROUND((((S38+ROUND((ROUND(((((EU38*1.2)*0.3))*AV38*I38),2)*BS38),2))*AU38)/100),2)+ROUND(((ROUND((ROUND(((AE38-(((EU38*1.2)*0.3)))*AV38*I38),2)*BS38),2)*AU38)/100),2)) -> 122.65 | AA38: 55943566 | AB38: =ROUND((AC38+AD38+AF38),6) -> 84.0636 | AC38: =ROUND((((ES38*1)*0)),6) -> 0 | AD38: =ROUND((((((ET38*1.2)*0.3))-(((EU38*1.2)*0.3)))+AE38),6) -> 2.1852 | AE38: =ROUND((((EU38*1.2)*0.3)),6) -> 0.2736 | AF38: =ROUND((((EV38*1.2)*0.3)),6) -> 81.8784 | AG38: =ROUND((AP38),6) -> 0 | AH38: =(((EW38*1.2)*0.3)) -> 5.2704 | AI38: =(((EX38*1.2)*0.3)) -> 0 | AJ38: =(AS38) -> 0 | AK38: 235.95 | AL38: 2.44 | AM38: 6.07 | AN38: 0.76 | AO38: 227.44 | AP38: 0 | AQ38: 14.64 | AR38: 0 | AS38: 0 | AT38: 90 | AU38: 46 | AV38: 1.047 | AW38: 1 | AZ38: 1 | BA38: 1 | BB38: 1 | BC38: 1 | BH38: 0 | BI38: 2 | BJ38: ТСН-2001.4 Доп. 80, Сб. 10, т. 177, поз. 1 | BM38: 68 | BN38: 0 | BO38: 4.10-177-1 | BP38: 1 | BQ38: 40 | BR38: 0 | BS38: 1 | BT38: 1 | BU38: 1 | BV38: 1 | BW38: 1 | BX38: 1 | BZ38: 90 | CA38: 46 | CE38: 1566 | CF38: 0 | CG38: 0 | CM38: 0 | CN38: Поправка: Гл.12.Прил.8.п.8. 3_12.00.01.11.001 Наименование: При наличии напряженных и стесненных условий производства работ (стесненность, сложность складирования и транспортной логистики и т.п.) для объектов, расположенных в пределах круговой магистральной системы улиц "Садовое кольцо" города Москвы Поправка: Гл.4.Прил.2.2.п.2.2.29_04.00.01.35.003 Наименование: При демонтаже оборудования, предназначенного в лом | CO38: 0 | CP38: =(P38+Q38+S38) -> 272.84 | CQ38: =ROUND((ROUND((AC38*AW38*1),2)*BC38),2) -> 0 | CR38: =(ROUND((ROUND(((((ET38*1.2)*0.3))*AV38*1),2)*BB38),2)+ROUND((ROUND(((AE38-(((EU38*1.2)*0.3)))*AV38*1),2)*BS38),2)) -> 2.29 | CS38: =(ROUND((ROUND(((((EU38*1.2)*0.3))*AV38*1),2)*BS38),2)+ROUND((ROUND(((AE38-(((EU38*1.2)*0.3)))*AV38*1),2)*BS38),2)) -> 0.29 | CT38: =ROUND((ROUND((AF38*AV38*1),2)*BA38),2) -> 85.73 | CU38: =AG38 -> 0 | CV38: =(AH38*AV38) -> 5.5181088 | CW38: =AI38 -> 0 | CX38: =AJ38 -> 0 | CY38: =(ROUND((((S38+ROUND((ROUND(((((EU38*1.2)*0.3))*AV38*1),2)*BS38),2))*AT38)/100),2)+ROUND(((ROUND((ROUND(((AE38-(((EU38*1.2)*0.3)))*AV38*1),2)*BS38),2)*AT38)/100),2)) -> 239.44 | CZ38: =(ROUND((((S38+ROUND((ROUND(((((EU38*1.2)*0.3))*AV38*1),2)*BS38),2))*AU38)/100),2)+ROUND(((ROUND((ROUND(((AE38-(((EU38*1.2)*0.3)))*AV38*1),2)*BS38),2)*AU38)/100),2)) -> 122.38 | DB38: 21 | DD38: *1)*0 | DE38: *1,2)*0,3 | DF38: *1,2)*0,3 | DG38: *1,2)*0,3 | DI38: *1,2)*0,3 | DJ38: *1,2)*0,3 | DN38: 0 | DO38: 0 | DP38: 1 | DQ38: 1 | DU38: 1010 | DV38: 10 шт. | DW38: 10 шт. | DX38: 10 | EE38: 55393972 | EF38: 40 | EG38: Монтаж оборудования | EH38: 0 | EJ38: 2 | EK38: 68 | EL38: ТСН-2001.4-10. Прокладка и монтаж сетей связи | EM38: ТСН-2001.4-10-1 | EO38: Поправка: Гл.12.Прил.8.п.8. 3_12.00.01.11.001 Поправка: Гл.4.Прил.2.2.п.2.2.29_04.00.01.35.003 | EQ38: 0 | ER38: 235.95 | ES38: 2.44 | ET38: 6.07 | EU38: 0.76 | EV38: 227.44 | EW38: 14.64 | EX38: 0 | EY38: 0 | FQ38: 0 | FR38: 0 | FS38: 0 | FX38: 90 | FY38: 46 | GD38: 1 | GF38: 1087320022 | GG38: 2 | GH38: 1 | GI38: 2 | GJ38: 0 | GK38: 0 | GL38: =ROUND(IF(AND(BH38=3,BI38=3,FS38<>0),P38,0),2) -> 0 | GM38: =ROUND(O38+X38+Y38,2)+GX38 -> 635.47 | GN38: =IF(OR(BI38=0,BI38=1),GM38-GX38,0) -> 0 | GO38: =IF(BI38=2,GM38-GX38,0) -> 635.47 | GP38: =IF(BI38=4,GM38-GX38,0) -> 0 | GR38: 0 | GS38: 3 | GT38: 0 | GV38: =ROUND((GT38),6) -> 0 | GW38: 1 | GX38: =ROUND(HC38*I38,2) -> 0 | HA38: 0 | HB38: 0 | HC38: =GV38*GW38 -> 0 | HS38: 0 | IK38: 0
A39: 17 | B39: 1 | E39: 6 | F39: 4.10-177-1 | G39: Монтаж устройства связи с согласующим устройством (вызывная панель) / демонтаж абонентского переговорного устройства | H39: 10 шт. | I39: =ROUND(31/10,9) -> 3.1 | J39: 0 | K39: =ROUND(31/10,9) -> 3.1 | O39: =ROUND(CP39,2) -> 15086.54 | P39: =ROUND((ROUND((AC39*AW39*I39),2)*BC39),2) -> 0 | Q39: =(ROUND((ROUND(((((ET39*1.2)*0.3))*AV39*I39),2)*BB39),2)+ROUND((ROUND(((AE39-(((EU39*1.2)*0.3)))*AV39*I39),2)*BS39),2)) -> 111.53 | R39: =(ROUND((ROUND(((((EU39*1.2)*0.3))*AV39*I39),2)*BS39),2)+ROUND((ROUND(((AE39-(((EU39*1.2)*0.3)))*AV39*I39),2)*BS39),2)) -> 50.15 | S39: =ROUND((ROUND((AF39*AV39*I39),2)*BA39),2) -> 14975.01 | T39: =ROUND(CU39*I39,2) -> 0 | U39: =CV39*I39 -> 17.106137 | V39: =CW39*I39 -> 0 | W39: =ROUND(CX39*I39,2) -> 0 | X39: =(ROUND((((S39+ROUND((ROUND(((((EU39*1.2)*0.3))*AV39*I39),2)*BS39),2))*AT39)/100),2)+ROUND(((ROUND((ROUND(((AE39-(((EU39*1.2)*0.3)))*AV39*I39),2)*BS39),2)*AT39)/100),2)) -> 13522.64 | Y39: =(ROUND((((S39+ROUND((ROUND(((((EU39*1.2)*0.3))*AV39*I39),2)*BS39),2))*AU39)/100),2)+ROUND(((ROUND((ROUND(((AE39-(((EU39*1.2)*0.3)))*AV39*I39),2)*BS39),2)*AU39)/100),2)) -> 6911.57 | AA39: 55943568 | AB39: =ROUND((AC39+AD39+AF39),6) -> 84.0636 | AC39: =ROUND((((ES39*1)*0)),6) -> 0 | AD39: =ROUND((((((ET39*1.2)*0.3))-(((EU39*1.2)*0.3)))+AE39),6) -> 2.1852 | AE39: =ROUND((((EU39*1.2)*0.3)),6) -> 0.2736 | AF39: =ROUND((((EV39*1.2)*0.3)),6) -> 81.8784 | AG39: =ROUND((AP39),6) -> 0 | AH39: =(((EW39*1.2)*0.3)) -> 5.2704 | AI39: =(((EX39*1.2)*0.3)) -> 0 | AJ39: =(AS39) -> 0 | AK39: 235.95 | AL39: 2.44 | AM39: 6.07 | AN39: 0.76 | AO39: 227.44 | AP39: 0 | AQ39: 14.64 | AR39: 0 | AS39: 0 | AT39: 90 | AU39: 46 | AV39: 1.047 | AW39: 1 | AZ39: 1 | BA39: 56.35 | BB39: 15.73 | BC39: 7.61 | BH39: 0 | BI39: 2 | BJ39: ТСН-2001.4 Доп. 80, Сб. 10, т. 177, поз. 1 | BM39: 68 | BN39: 0 | BO39: 4.10-177-1 | BP39: 1 | BQ39: 40 | BR39: 0 | BS39: 56.35 | BT39: 1 | BU39: 1 | BV39: 1 | BW39: 1 | BX39: 1 | BZ39: 90 | CA39: 46 | CE39: 1566 | CF39: 0 | CG39: 0 | CM39: 0 | CN39: Поправка: Гл.12.Прил.8.п.8. 3_12.00.01.11.001 Наименование: При наличии напряженных и стесненных условий производства работ (стесненность, сложность складирования и транспортной логистики и т.п.) для объектов, расположенных в пределах круговой магистральной системы улиц "Садовое кольцо" города Москвы Поправка: Гл.4.Прил.2.2.п.2.2.29_04.00.01.35.003 Наименование: При демонтаже оборудования, предназначенного в лом | CO39: 0 | CP39: =(P39+Q39+S39) -> 15086.54 | CQ39: =ROUND((ROUND((AC39*AW39*1),2)*BC39),2) -> 0 | CR39: =(ROUND((ROUND(((((ET39*1.2)*0.3))*AV39*1),2)*BB39),2)+ROUND((ROUND(((AE39-(((EU39*1.2)*0.3)))*AV39*1),2)*BS39),2)) -> 36.02 | CS39: =(ROUND((ROUND(((((EU39*1.2)*0.3))*AV39*1),2)*BS39),2)+ROUND((ROUND(((AE39-(((EU39*1.2)*0.3)))*AV39*1),2)*BS39),2)) -> 16.34 | CT39: =ROUND((ROUND((AF39*AV39*1),2)*BA39),2) -> 4830.89 | CU39: =AG39 -> 0 | CV39: =(AH39*AV39) -> 5.5181088 | CW39: =AI39 -> 0 | CX39: =AJ39 -> 0 | CY39: =(ROUND((((S39+ROUND((ROUND(((((EU39*1.2)*0.3))*AV39*1),2)*BS39),2))*AT39)/100),2)+ROUND(((ROUND((ROUND(((AE39-(((EU39*1.2)*0.3)))*AV39*1),2)*BS39),2)*AT39)/100),2)) -> 13492.22 | CZ39: =(ROUND((((S39+ROUND((ROUND(((((EU39*1.2)*0.3))*AV39*1),2)*BS39),2))*AU39)/100),2)+ROUND(((ROUND((ROUND(((AE39-(((EU39*1.2)*0.3)))*AV39*1),2)*BS39),2)*AU39)/100),2)) -> 6896.02 | DB39: 23 | DD39: *1)*0 | DE39: *1,2)*0,3 | DF39: *1,2)*0,3 | DG39: *1,2)*0,3 | DI39: *1,2)*0,3 | DJ39: *1,2)*0,3 | DN39: 0 | DO39: 0 | DP39: 1 | DQ39: 1 | DU39: 1010 | DV39: 10 шт. | DW39: 10 шт. | DX39: 10 | EE39: 55393972 | EF39: 40 | EG39: Монтаж оборудования | EH39: 0 | EJ39: 2 | EK39: 68 | EL39: ТСН-2001.4-10. Прокладка и монтаж сетей связи | EM39: ТСН-2001.4-10-1 | EO39: Поправка: Гл.12.Прил.8.п.8. 3_12.00.01.11.001 Поправка: Гл.4.Прил.2.2.п.2.2.29_04.00.01.35.003 | EQ39: 0 | ER39: 235.95 | ES39: 2.44 | ET39: 6.07 | EU39: 0.76 | EV39: 227.44 | EW39: 14.64 | EX39: 0 | EY39: 0 | FQ39: 0 | FR39: 0 | FS39: 0 | FX39: 90 | FY39: 46 | GD39: 1 | GF39: 1087320022 | GG39: 2 | GH39: 1 | GI39: 2 | GJ39: 0 | GK39: 0 | GL39: =ROUND(IF(AND(BH39=3,BI39=3,FS39<>0),P39,0),2) -> 0 | GM39: =ROUND(O39+X39+Y39,2)+GX39 -> 35520.75 | GN39: =IF(OR(BI39=0,BI39=1),GM39-GX39,0) -> 0 | GO39: =IF(BI39=2,GM39-GX39,0) -> 35520.75 | GP39: =IF(BI39=4,GM39-GX39,0) -> 0 | GR39: 0 | GS39: 3 | GT39: 0 | GV39: =ROUND((GT39),6) -> 0 | GW39: 1 | GX39: =ROUND(HC39*I39,2) -> 0 | HA39: 0 | HB39: 0 | HC39: =GV39*GW39 -> 0 | HS39: 0 | IK39: 0
A40: 17 | B40: 1 | E40: 7 | F40: 4.10-167-1 | G40: Монтаж блока питания сети (БПС) в диспетчерской / демонтаж источника электропитания | H40: 1ШТ. | I40: 2 | J40: 0 | K40: 2 | O40: =ROUND(CP40,2) -> 14.3 | P40: =ROUND((ROUND((AC40*AW40*I40),2)*BC40),2) -> 0 | Q40: =(ROUND((ROUND(((((ET40*1.2)*0.3))*AV40*I40),2)*BB40),2)+ROUND((ROUND(((AE40-(((EU40*1.2)*0.3)))*AV40*I40),2)*BS40),2)) -> 0.02 | R40: =(ROUND((ROUND(((((EU40*1.2)*0.3))*AV40*I40),2)*BS40),2)+ROUND((ROUND(((AE40-(((EU40*1.2)*0.3)))*AV40*I40),2)*BS40),2)) -> 0 | S40: =ROUND((ROUND((AF40*AV40*I40),2)*BA40),2) -> 14.28 | T40: =ROUND(CU40*I40,2) -> 0 | U40: =CV40*I40 -> 1.0252224 | V40: =CW40*I40 -> 0 | W40: =ROUND(CX40*I40,2) -> 0 | X40: =(ROUND((((S40+ROUND((ROUND(((((EU40*1.2)*0.3))*AV40*I40),2)*BS40),2))*AT40)/100),2)+ROUND(((ROUND((ROUND(((AE40-(((EU40*1.2)*0.3)))*AV40*I40),2)*BS40),2)*AT40)/100),2)) -> 12.85 | Y40: =(ROUND((((S40+ROUND((ROUND(((((EU40*1.2)*0.3))*AV40*I40),2)*BS40),2))*AU40)/100),2)+ROUND(((ROUND((ROUND(((AE40-(((EU40*1.2)*0.3)))*AV40*I40),2)*BS40),2)*AU40)/100),2)) -> 6.57 | AA40: 55943566 | AB40: =ROUND((AC40+AD40+AF40),6) -> 6.8256 | AC40: =ROUND((((ES40*1)*0)),6) -> 0 | AD40: =ROUND((((((ET40*1.2)*0.3))-(((EU40*1.2)*0.3)))+AE40),6) -> 0.0072 | AE40: =ROUND((((EU40*1.2)*0.3)),6) -> 0 | AF40: =ROUND((((EV40*1.2)*0.3)),6) -> 6.8184 | AG40: =ROUND((AP40),6) -> 0 | AH40: =(((EW40*1.2)*0.3)) -> 0.4896 | AI40: =(((EX40*1.2)*0.3)) -> 0 | AJ40: =(AS40) -> 0 | AK40: 21.3 | AL40: 2.34 | AM40: 0.02 | AN40: 0 | AO40: 18.94 | AP40: 0 | AQ40: 1.36 | AR40: 0 | AS40: 0 | AT40: 90 | AU40: 46 | AV40: 1.047 | AW40: 1 | AZ40: 1 | BA40: 1 | BB40: 1 | BC40: 1 | BH40: 0 | BI40: 2 | BJ40: ТСН-2001.4 Доп. 69, Сб. 10, т. 167, поз. 1 | BM40: 68 | BN40: 0 | BO40: 4.10-167-1 | BP40: 1 | BQ40: 40 | BR40: 0 | BS40: 1 | BT40: 1 | BU40: 1 | BV40: 1 | BW40: 1 | BX40: 1 | BZ40: 90 | CA40: 46 | CE40: 1566 | CF40: 0 | CG40: 0 | CM40: 0 | CN40: Поправка: Гл.12.Прил.8.п.8. 3_12.00.01.11.001 Наименование: При наличии напряженных и стесненных условий производства работ (стесненность, сложность складирования и транспортной логистики и т.п.) для объектов, расположенных в пределах круговой магистральной системы улиц "Садовое кольцо" города Москвы Поправка: Гл.4.Прил.2.2.п.2.2.29_04.00.01.35.003 Наименование: При демонтаже оборудования, предназначенного в лом | CO40: 0 | CP40: =(P40+Q40+S40) -> 14.3 | CQ40: =ROUND((ROUND((AC40*AW40*1),2)*BC40),2) -> 0 | CR40: =(ROUND((ROUND(((((ET40*1.2)*0.3))*AV40*1),2)*BB40),2)+ROUND((ROUND(((AE40-(((EU40*1.2)*0.3)))*AV40*1),2)*BS40),2)) -> 0.01 | CS40: =(ROUND((ROUND(((((EU40*1.2)*0.3))*AV40*1),2)*BS40),2)+ROUND((ROUND(((AE40-(((EU40*1.2)*0.3)))*AV40*1),2)*BS40),2)) -> 0 | CT40: =ROUND((ROUND((AF40*AV40*1),2)*BA40),2) -> 7.14 | CU40: =AG40 -> 0 | CV40: =(AH40*AV40) -> 0.5126112 | CW40: =AI40 -> 0 | CX40: =AJ40 -> 0 | CY40: =(ROUND((((S40+ROUND((ROUND(((((EU40*1.2)*0.3))*AV40*1),2)*BS40),2))*AT40)/100),2)+ROUND(((ROUND((ROUND(((AE40-(((EU40*1.2)*0.3)))*AV40*1),2)*BS40),2)*AT40)/100),2)) -> 12.85 | CZ40: =(ROUND((((S40+ROUND((ROUND(((((EU40*1.2)*0.3))*AV40*1),2)*BS40),2))*AU40)/100),2)+ROUND(((ROUND((ROUND(((AE40-(((EU40*1.2)*0.3)))*AV40*1),2)*BS40),2)*AU40)/100),2)) -> 6.57 | DB40: 25 | DD40: *1)*0 | DE40: *1,2)*0,3 | DF40: *1,2)*0,3 | DG40: *1,2)*0,3 | DI40: *1,2)*0,3 | DJ40: *1,2)*0,3 | DN40: 0 | DO40: 0 | DP40: 1 | DQ40: 1 | DU40: 1013 | DV40: 1ШТ. | DW40: 1 ШТ. | DX40: 1 | EE40: 55393972 | EF40: 40 | EG40: Монтаж оборудования | EH40: 0 | EJ40: 2 | EK40: 68 | EL40: ТСН-2001.4-10. Прокладка и монтаж сетей связи | EM40: ТСН-2001.4-10-1 | EO40: Поправка: Гл.12.Прил.8.п.8. 3_12.00.01.11.001 Поправка: Гл.4.Прил.2.2.п.2.2.29_04.00.01.35.003 | EQ40: 0 | ER40: 21.3 | ES40: 2.34 | ET40: 0.02 | EU40: 0 | EV40: 18.94 | EW40: 1.36 | EX40: 0 | EY40: 0 | FQ40: 0 | FR40: 0 | FS40: 0 | FX40: 90 | FY40: 46 | GD40: 1 | GF40: 255067873 | GG40: 2 | GH40: 1 | GI40: 2 | GJ40: 0 | GK40: 0 | GL40: =ROUND(IF(AND(BH40=3,BI40=3,FS40<>0),P40,0),2) -> 0 | GM40: =ROUND(O40+X40+Y40,2)+GX40 -> 33.72 | GN40: =IF(OR(BI40=0,BI40=1),GM40-GX40,0) -> 0 | GO40: =IF(BI40=2,GM40-GX40,0) -> 33.72 | GP40: =IF(BI40=4,GM40-GX40,0) -> 0 | GR40: 0 | GS40: 3 | GT40: 0 | GV40: =ROUND((GT40),6) -> 0 | GW40: 1 | GX40: =ROUND(HC40*I40,2) -> 0 | HA40: 0 | HB40: 0 | HC40: =GV40*GW40 -> 0 | HS40: 0 | IK40: 0
A41: 17 | B41: 1 | E41: 7 | F41: 4.10-167-1 | G41: Монтаж блока питания сети (БПС) в диспетчерской / демонтаж источника электропитания | H41: 1ШТ. | I41: 2 | J41: 0 | K41: 2 | O41: =ROUND(CP41,2) -> 804.9 | P41: =ROUND((ROUND((AC41*AW41*I41),2)*BC41),2) -> 0 | Q41: =(ROUND((ROUND(((((ET41*1.2)*0.3))*AV41*I41),2)*BB41),2)+ROUND((ROUND(((AE41-(((EU41*1.2)*0.3)))*AV41*I41),2)*BS41),2)) -> 0.22 | R41: =(ROUND((ROUND(((((EU41*1.2)*0.3))*AV41*I41),2)*BS41),2)+ROUND((ROUND(((AE41-(((EU41*1.2)*0.3)))*AV41*I41),2)*BS41),2)) -> 0 | S41: =ROUND((ROUND((AF41*AV41*I41),2)*BA41),2) -> 804.68 | T41: =ROUND(CU41*I41,2) -> 0 | U41: =CV41*I41 -> 1.0252224 | V41: =CW41*I41 -> 0 | W41: =ROUND(CX41*I41,2) -> 0 | X41: =(ROUND((((S41+ROUND((ROUND(((((EU41*1.2)*0.3))*AV41*I41),2)*BS41),2))*AT41)/100),2)+ROUND(((ROUND((ROUND(((AE41-(((EU41*1.2)*0.3)))*AV41*I41),2)*BS41),2)*AT41)/100),2)) -> 724.21 | Y41: =(ROUND((((S41+ROUND((ROUND(((((EU41*1.2)*0.3))*AV41*I41),2)*BS41),2))*AU41)/100),2)+ROUND(((ROUND((ROUND(((AE41-(((EU41*1.2)*0.3)))*AV41*I41),2)*BS41),2)*AU41)/100),2)) -> 370.15 | AA41: 55943568 | AB41: =ROUND((AC41+AD41+AF41),6) -> 6.8256 | AC41: =ROUND((((ES41*1)*0)),6) -> 0 | AD41: =ROUND((((((ET41*1.2)*0.3))-(((EU41*1.2)*0.3)))+AE41),6) -> 0.0072 | AE41: =ROUND((((EU41*1.2)*0.3)),6) -> 0 | AF41: =ROUND((((EV41*1.2)*0.3)),6) -> 6.8184 | AG41: =ROUND((AP41),6) -> 0 | AH41: =(((EW41*1.2)*0.3)) -> 0.4896 | AI41: =(((EX41*1.2)*0.3)) -> 0 | AJ41: =(AS41) -> 0 | AK41: 21.3 | AL41: 2.34 | AM41: 0.02 | AN41: 0 | AO41: 18.94 | AP41: 0 | AQ41: 1.36 | AR41: 0 | AS41: 0 | AT41: 90 | AU41: 46 | AV41: 1.047 | AW41: 1 | AZ41: 1 | BA41: 56.35 | BB41: 11 | BC41: 10.24 | BH41: 0 | BI41: 2 | BJ41: ТСН-2001.4 Доп. 69, Сб. 10, т. 167, поз. 1 | BM41: 68 | BN41: 0 | BO41: 4.10-167-1 | BP41: 1 | BQ41: 40 | BR41: 0 | BS41: 56.35 | BT41: 1 | BU41: 1 | BV41: 1 | BW41: 1 | BX41: 1 | BZ41: 90 | CA41: 46 | CE41: 1566 | CF41: 0 | CG41: 0 | CM41: 0 | CN41: Поправка: Гл.12.Прил.8.п.8. 3_12.00.01.11.001 Наименование: При наличии напряженных и стесненных условий производства работ (стесненность, сложность складирования и транспортной логистики и т.п.) для объектов, расположенных в пределах круговой магистральной системы улиц "Садовое кольцо" города Москвы Поправка: Гл.4.Прил.2.2.п.2.2.29_04.00.01.35.003 Наименование: При демонтаже оборудования, предназначенного в лом | CO41: 0 | CP41: =(P41+Q41+S41) -> 804.9 | CQ41: =ROUND((ROUND((AC41*AW41*1),2)*BC41),2) -> 0 | CR41: =(ROUND((ROUND(((((ET41*1.2)*0.3))*AV41*1),2)*BB41),2)+ROUND((ROUND(((AE41-(((EU41*1.2)*0.3)))*AV41*1),2)*BS41),2)) -> 0.11 | CS41: =(ROUND((ROUND(((((EU41*1.2)*0.3))*AV41*1),2)*BS41),2)+ROUND((ROUND(((AE41-(((EU41*1.2)*0.3)))*AV41*1),2)*BS41),2)) -> 0 | CT41: =ROUND((ROUND((AF41*AV41*1),2)*BA41),2) -> 402.34 | CU41: =AG41 -> 0 | CV41: =(AH41*AV41) -> 0.5126112 | CW41: =AI41 -> 0 | CX41: =AJ41 -> 0 | CY41: =(ROUND((((S41+ROUND((ROUND(((((EU41*1.2)*0.3))*AV41*1),2)*BS41),2))*AT41)/100),2)+ROUND(((ROUND((ROUND(((AE41-(((EU41*1.2)*0.3)))*AV41*1),2)*BS41),2)*AT41)/100),2)) -> 724.21 | CZ41: =(ROUND((((S41+ROUND((ROUND(((((EU41*1.2)*0.3))*AV41*1),2)*BS41),2))*AU41)/100),2)+ROUND(((ROUND((ROUND(((AE41-(((EU41*1.2)*0.3)))*AV41*1),2)*BS41),2)*AU41)/100),2)) -> 370.15 | DB41: 27 | DD41: *1)*0 | DE41: *1,2)*0,3 | DF41: *1,2)*0,3 | DG41: *1,2)*0,3 | DI41: *1,2)*0,3 | DJ41: *1,2)*0,3 | DN41: 0 | DO41: 0 | DP41: 1 | DQ41: 1 | DU41: 1013 | DV41: 1ШТ. | DW41: 1 ШТ. | DX41: 1 | EE41: 55393972 | EF41: 40 | EG41: Монтаж оборудования | EH41: 0 | EJ41: 2 | EK41: 68 | EL41: ТСН-2001.4-10. Прокладка и монтаж сетей связи | EM41: ТСН-2001.4-10-1 | EO41: Поправка: Гл.12.Прил.8.п.8. 3_12.00.01.11.001 Поправка: Гл.4.Прил.2.2.п.2.2.29_04.00.01.35.003 | EQ41: 0 | ER41: 21.3 | ES41: 2.34 | ET41: 0.02 | EU41: 0 | EV41: 18.94 | EW41: 1.36 | EX41: 0 | EY41: 0 | FQ41: 0 | FR41: 0 | FS41: 0 | FX41: 90 | FY41: 46 | GD41: 1 | GF41: 255067873 | GG41: 2 | GH41: 1 | GI41: 2 | GJ41: 0 | GK41: 0 | GL41: =ROUND(IF(AND(BH41=3,BI41=3,FS41<>0),P41,0),2) -> 0 | GM41: =ROUND(O41+X41+Y41,2)+GX41 -> 1899.26 | GN41: =IF(OR(BI41=0,BI41=1),GM41-GX41,0) -> 0 | GO41: =IF(BI41=2,GM41-GX41,0) -> 1899.26 | GP41: =IF(BI41=4,GM41-GX41,0) -> 0 | GR41: 0 | GS41: 3 | GT41: 0 | GV41: =ROUND((GT41),6) -> 0 | GW41: 1 | GX41: =ROUND(HC41*I41,2) -> 0 | HA41: 0 | HB41: 0 | HC41: =GV41*GW41 -> 0 | HS41: 0 | IK41: 0
A42: 17 | B42: 1 | E42: 8 | F42: 4.8-70-1 | G42: Монтаж аккумулятора кислотного стационарного типа С-1, СК-1 / демонтаж аккумуляторной батареи | H42: 1ШТ. | I42: 4 | J42: 0 | K42: 4 | O42: =ROUND(CP42,2) -> 39.2 | P42: =ROUND((ROUND((AC42*AW42*I42),2)*BC42),2) -> 0 | Q42: =(ROUND((ROUND(((((ET42*1.2)*0.3))*AV42*I42),2)*BB42),2)+ROUND((ROUND(((AE42-(((EU42*1.2)*0.3)))*AV42*I42),2)*BS42),2)) -> 0 | R42: =(ROUND((ROUND(((((EU42*1.2)*0.3))*AV42*I42),2)*BS42),2)+ROUND((ROUND(((AE42-(((EU42*1.2)*0.3)))*AV42*I42),2)*BS42),2)) -> 0 | S42: =ROUND((ROUND((AF42*AV42*I42),2)*BA42),2) -> 39.2 | T42: =ROUND(CU42*I42,2) -> 0 | U42: =CV42*I42 -> 3.1058208 | V42: =CW42*I42 -> 0 | W42: =ROUND(CX42*I42,2) -> 0 | X42: =(ROUND((((S42+ROUND((ROUND(((((EU42*1.2)*0.3))*AV42*I42),2)*BS42),2))*AT42)/100),2)+ROUND(((ROUND((ROUND(((AE42-(((EU42*1.2)*0.3)))*AV42*I42),2)*BS42),2)*AT42)/100),2)) -> 38.02 | Y42: =(ROUND((((S42+ROUND((ROUND(((((EU42*1.2)*0.3))*AV42*I42),2)*BS42),2))*AU42)/100),2)+ROUND(((ROUND((ROUND(((AE42-(((EU42*1.2)*0.3)))*AV42*I42),2)*BS42),2)*AU42)/100),2)) -> 19.99 | AA42: 55943566 | AB42: =ROUND((AC42+AD42+AF42),6) -> 9.36 | AC42: =ROUND((((ES42*1)*0)),6) -> 0 | AD42: =ROUND((((((ET42*1.2)*0.3))-(((EU42*1.2)*0.3)))+AE42),6) -> 0 | AE42: =ROUND((((EU42*1.2)*0.3)),6) -> 0 | AF42: =ROUND((((EV42*1.2)*0.3)),6) -> 9.36 | AG42: =ROUND((AP42),6) -> 0 | AH42: =(((EW42*1.2)*0.3)) -> 0.7416 | AI42: =(((EX42*1.2)*0.3)) -> 0 | AJ42: =(AS42) -> 0 | AK42: 49.04 | AL42: 23.04 | AM42: 0 | AN42: 0 | AO42: 26 | AP42: 0 | AQ42: 2.06 | AR42: 0 | AS42: 0 | AT42: 97 | AU42: 51 | AV42: 1.047 | AW42: 1 | AZ42: 1 | BA42: 1 | BB42: 1 | BC42: 1 | BH42: 0 | BI42: 2 | BJ42: ТСН-2001.4 Доп. 80, Сб. 8, т. 70, поз. 1 | BM42: 67 | BN42: 0 | BO42: 4.8-70-1 | BP42: 1 | BQ42: 40 | BR42: 0 | BS42: 1 | BT42: 1 | BU42: 1 | BV42: 1 | BW42: 1 | BX42: 1 | BZ42: 97 | CA42: 51 | CE42: 1566 | CF42: 0 | CG42: 0 | CM42: 0 | CN42: Поправка: Гл.12.Прил.8.п.8. 3_12.00.01.11.001 Наименование: При наличии напряженных и стесненных условий производства работ (стесненность, сложность складирования и транспортной логистики и т.п.) для объектов, расположенных в пределах круговой магистральной системы улиц "Садовое кольцо" города Москвы Поправка: Гл.4.Прил.2.2.п.2.2.29_04.00.01.35.003 Наименование: При демонтаже оборудования, предназначенного в лом | CO42: 0 | CP42: =(P42+Q42+S42) -> 39.2 | CQ42: =ROUND((ROUND((AC42*AW42*1),2)*BC42),2) -> 0 | CR42: =(ROUND((ROUND(((((ET42*1.2)*0.3))*AV42*1),2)*BB42),2)+ROUND((ROUND(((AE42-(((EU42*1.2)*0.3)))*AV42*1),2)*BS42),2)) -> 0 | CS42: =(ROUND((ROUND(((((EU42*1.2)*0.3))*AV42*1),2)*BS42),2)+ROUND((ROUND(((AE42-(((EU42*1.2)*0.3)))*AV42*1),2)*BS42),2)) -> 0 | CT42: =ROUND((ROUND((AF42*AV42*1),2)*BA42),2) -> 9.8 | CU42: =AG42 -> 0 | CV42: =(AH42*AV42) -> 0.7764552 | CW42: =AI42 -> 0 | CX42: =AJ42 -> 0 | CY42: =(ROUND((((S42+ROUND((ROUND(((((EU42*1.2)*0.3))*AV42*1),2)*BS42),2))*AT42)/100),2)+ROUND(((ROUND((ROUND(((AE42-(((EU42*1.2)*0.3)))*AV42*1),2)*BS42),2)*AT42)/100),2)) -> 38.02 | CZ42: =(ROUND((((S42+ROUND((ROUND(((((EU42*1.2)*0.3))*AV42*1),2)*BS42),2))*AU42)/100),2)+ROUND(((ROUND((ROUND(((AE42-(((EU42*1.2)*0.3)))*AV42*1),2)*BS42),2)*AU42)/100),2)) -> 19.99 | DB42: 29 | DD42: *1)*0 | DE42: *1,2)*0,3 | DF42: *1,2)*0,3 | DG42: *1,2)*0,3 | DI42: *1,2)*0,3 | DJ42: *1,2)*0,3 | DN42: 0 | DO42: 0 | DP42: 1 | DQ42: 1 | DU42: 1013 | DV42: 1ШТ. | DW42: 1 ШТ. | DX42: 1 | EE42: 55393971 | EF42: 40 | EG42: Монтаж оборудования | EH42: 0 | EJ42: 2 | EK42: 67 | EL42: ТСН-2001.4-8. Электротехнические установки | EM42: ТСН-2001.4-8-1 | EO42: Поправка: Гл.12.Прил.8.п.8. 3_12.00.01.11.001 Поправка: Гл.4.Прил.2.2.п.2.2.29_04.00.01.35.003 | EQ42: 0 | ER42: 49.04 | ES42: 23.04 | ET42: 0 | EU42: 0 | EV42: 26 | EW42: 2.06 | EX42: 0 | EY42: 0 | FQ42: 0 | FR42: 0 | FS42: 0 | FX42: 97 | FY42: 51 | GD42: 1 | GF42: 1505069591 | GG42: 2 | GH42: 1 | GI42: 2 | GJ42: 0 | GK42: 0 | GL42: =ROUND(IF(AND(BH42=3,BI42=3,FS42<>0),P42,0),2) -> 0 | GM42: =ROUND(O42+X42+Y42,2)+GX42 -> 97.21 | GN42: =IF(OR(BI42=0,BI42=1),GM42-GX42,0) -> 0 | GO42: =IF(BI42=2,GM42-GX42,0) -> 97.21 | GP42: =IF(BI42=4,GM42-GX42,0) -> 0 | GR42: 0 | GS42: 3 | GT42: 0 | GV42: =ROUND((GT42),6) -> 0 | GW42: 1 | GX42: =ROUND(HC42*I42,2) -> 0 | HA42: 0 | HB42: 0 | HC42: =GV42*GW42 -> 0 | HS42: 0 | IK42: 0
A43: 17 | B43: 1 | E43: 8 | F43: 4.8-70-1 | G43: Монтаж аккумулятора кислотного стационарного типа С-1, СК-1 / демонтаж аккумуляторной батареи | H43: 1ШТ. | I43: 4 | J43: 0 | K43: 4 | O43: =ROUND(CP43,2) -> 2208.92 | P43: =ROUND((ROUND((AC43*AW43*I43),2)*BC43),2) -> 0 | Q43: =(ROUND((ROUND(((((ET43*1.2)*0.3))*AV43*I43),2)*BB43),2)+ROUND((ROUND(((AE43-(((EU43*1.2)*0.3)))*AV43*I43),2)*BS43),2)) -> 0 | R43: =(ROUND((ROUND(((((EU43*1.2)*0.3))*AV43*I43),2)*BS43),2)+ROUND((ROUND(((AE43-(((EU43*1.2)*0.3)))*AV43*I43),2)*BS43),2)) -> 0 | S43: =ROUND((ROUND((AF43*AV43*I43),2)*BA43),2) -> 2208.92 | T43: =ROUND(CU43*I43,2) -> 0 | U43: =CV43*I43 -> 3.1058208 | V43: =CW43*I43 -> 0 | W43: =ROUND(CX43*I43,2) -> 0 | X43: =(ROUND((((S43+ROUND((ROUND(((((EU43*1.2)*0.3))*AV43*I43),2)*BS43),2))*AT43)/100),2)+ROUND(((ROUND((ROUND(((AE43-(((EU43*1.2)*0.3)))*AV43*I43),2)*BS43),2)*AT43)/100),2)) -> 2142.65 | Y43: =(ROUND((((S43+ROUND((ROUND(((((EU43*1.2)*0.3))*AV43*I43),2)*BS43),2))*AU43)/100),2)+ROUND(((ROUND((ROUND(((AE43-(((EU43*1.2)*0.3)))*AV43*I43),2)*BS43),2)*AU43)/100),2)) -> 1126.55 | AA43: 55943568 | AB43: =ROUND((AC43+AD43+AF43),6) -> 9.36 | AC43: =ROUND((((ES43*1)*0)),6) -> 0 | AD43: =ROUND((((((ET43*1.2)*0.3))-(((EU43*1.2)*0.3)))+AE43),6) -> 0 | AE43: =ROUND((((EU43*1.2)*0.3)),6) -> 0 | AF43: =ROUND((((EV43*1.2)*0.3)),6) -> 9.36 | AG43: =ROUND((AP43),6) -> 0 | AH43: =(((EW43*1.2)*0.3)) -> 0.7416 | AI43: =(((EX43*1.2)*0.3)) -> 0 | AJ43: =(AS43) -> 0 | AK43: 49.04 | AL43: 23.04 | AM43: 0 | AN43: 0 | AO43: 26 | AP43: 0 | AQ43: 2.06 | AR43: 0 | AS43: 0 | AT43: 97 | AU43: 51 | AV43: 1.047 | AW43: 1 | AZ43: 1 | BA43: 56.35 | BB43: 1 | BC43: 4.06 | BH43: 0 | BI43: 2 | BJ43: ТСН-2001.4 Доп. 80, Сб. 8, т. 70, поз. 1 | BM43: 67 | BN43: 0 | BO43: 4.8-70-1 | BP43: 1 | BQ43: 40 | BR43: 0 | BS43: 56.35 | BT43: 1 | BU43: 1 | BV43: 1 | BW43: 1 | BX43: 1 | BZ43: 97 | CA43: 51 | CE43: 1566 | CF43: 0 | CG43: 0 | CM43: 0 | CN43: Поправка: Гл.12.Прил.8.п.8. 3_12.00.01.11.001 Наименование: При наличии напряженных и стесненных условий производства работ (стесненность, сложность складирования и транспортной логистики и т.п.) для объектов, расположенных в пределах круговой магистральной системы улиц "Садовое кольцо" города Москвы Поправка: Гл.4.Прил.2.2.п.2.2.29_04.00.01.35.003 Наименование: При демонтаже оборудования, предназначенного в лом | CO43: 0 | CP43: =(P43+Q43+S43) -> 2208.92 | CQ43: =ROUND((ROUND((AC43*AW43*1),2)*BC43),2) -> 0 | CR43: =(ROUND((ROUND(((((ET43*1.2)*0.3))*AV43*1),2)*BB43),2)+ROUND((ROUND(((AE43-(((EU43*1.2)*0.3)))*AV43*1),2)*BS43),2)) -> 0 | CS43: =(ROUND((ROUND(((((EU43*1.2)*0.3))*AV43*1),2)*BS43),2)+ROUND((ROUND(((AE43-(((EU43*1.2)*0.3)))*AV43*1),2)*BS43),2)) -> 0 | CT43: =ROUND((ROUND((AF43*AV43*1),2)*BA43),2) -> 552.23 | CU43: =AG43 -> 0 | CV43: =(AH43*AV43) -> 0.7764552 | CW43: =AI43 -> 0 | CX43: =AJ43 -> 0 | CY43: =(ROUND((((S43+ROUND((ROUND(((((EU43*1.2)*0.3))*AV43*1),2)*BS43),2))*AT43)/100),2)+ROUND(((ROUND((ROUND(((AE43-(((EU43*1.2)*0.3)))*AV43*1),2)*BS43),2)*AT43)/100),2)) -> 2142.65 | CZ43: =(ROUND((((S43+ROUND((ROUND(((((EU43*1.2)*0.3))*AV43*1),2)*BS43),2))*AU43)/100),2)+ROUND(((ROUND((ROUND(((AE43-(((EU43*1.2)*0.3)))*AV43*1),2)*BS43),2)*AU43)/100),2)) -> 1126.55 | DB43: 31 | DD43: *1)*0 | DE43: *1,2)*0,3 | DF43: *1,2)*0,3 | DG43: *1,2)*0,3 | DI43: *1,2)*0,3 | DJ43: *1,2)*0,3 | DN43: 0 | DO43: 0 | DP43: 1 | DQ43: 1 | DU43: 1013 | DV43: 1ШТ. | DW43: 1 ШТ. | DX43: 1 | EE43: 55393971 | EF43: 40 | EG43: Монтаж оборудования | EH43: 0 | EJ43: 2 | EK43: 67 | EL43: ТСН-2001.4-8. Электротехнические установки | EM43: ТСН-2001.4-8-1 | EO43: Поправка: Гл.12.Прил.8.п.8. 3_12.00.01.11.001 Поправка: Гл.4.Прил.2.2.п.2.2.29_04.00.01.35.003 | EQ43: 0 | ER43: 49.04 | ES43: 23.04 | ET43: 0 | EU43: 0 | EV43: 26 | EW43: 2.06 | EX43: 0 | EY43: 0 | FQ43: 0 | FR43: 0 | FS43: 0 | FX43: 97 | FY43: 51 | GD43: 1 | GF43: 1505069591 | GG43: 2 | GH43: 1 | GI43: 2 | GJ43: 0 | GK43: 0 | GL43: =ROUND(IF(AND(BH43=3,BI43=3,FS43<>0),P43,0),2) -> 0 | GM43: =ROUND(O43+X43+Y43,2)+GX43 -> 5478.12 | GN43: =IF(OR(BI43=0,BI43=1),GM43-GX43,0) -> 0 | GO43: =IF(BI43=2,GM43-GX43,0) -> 5478.12 | GP43: =IF(BI43=4,GM43-GX43,0) -> 0 | GR43: 0 | GS43: 3 | GT43: 0 | GV43: =ROUND((GT43),6) -> 0 | GW43: 1 | GX43: =ROUND(HC43*I43,2) -> 0 | HA43: 0 | HB43: 0 | HC43: =GV43*GW43 -> 0 | HS43: 0 | IK43: 0
A44: 17 | B44: 1 | C44: =ROW(SmtRes!A2) -> 2 | D44: =ROW(EtalonRes!A2) -> 2 | E44: 9 | F44: 6.67-5-12 | G44: Демонтаж трубных проводок, трубы в борозде диаметром 25 мм / ПВХ | H44: 100 м | I44: =ROUND(4220/100,9) -> 42.2 | J44: 0 | K44: =ROUND(4220/100,9) -> 42.2 | O44: =ROUND(CP44,2) -> 16978.62 | P44: =ROUND((ROUND((AC44*AW44*I44),2)*BC44),2) -> 0 | Q44: =(ROUND((ROUND((((ET44*1.2))*AV44*I44),2)*BB44),2)+ROUND((ROUND(((AE44-((EU44*1.2)))*AV44*I44),2)*BS44),2)) -> 0 | R44: =(ROUND((ROUND((((EU44*1.2))*AV44*I44),2)*BS44),2)+ROUND((ROUND(((AE44-((EU44*1.2)))*AV44*I44),2)*BS44),2)) -> 0 | S44: =ROUND((ROUND((AF44*AV44*I44),2)*BA44),2) -> 16978.62 | T44: =ROUND(CU44*I44,2) -> 0 | U44: =CV44*I44 -> 1613.9312 | V44: =CW44*I44 -> 0 | W44: =ROUND(CX44*I44,2) -> 0 | X44: =(ROUND((((S44+ROUND((ROUND((((EU44*1.2))*AV44*I44),2)*BS44),2))*AT44)/100),2)+ROUND(((ROUND((ROUND(((AE44-((EU44*1.2)))*AV44*I44),2)*BS44),2)*AT44)/100),2)) -> 15450.54 | Y44: =(ROUND((((S44+ROUND((ROUND((((EU44*1.2))*AV44*I44),2)*BS44),2))*AU44)/100),2)+ROUND(((ROUND((ROUND(((AE44-((EU44*1.2)))*AV44*I44),2)*BS44),2)*AU44)/100),2)) -> 8149.74 | AA44: 55943566 | AB44: =ROUND((AC44+AD44+AF44),6) -> 384.276 | AC44: =ROUND(((ES44*1)),6) -> 0 | AD44: =ROUND(((((ET44*1.2))-((EU44*1.2)))+AE44),6) -> 0 | AE44: =ROUND(((EU44*1.2)),6) -> 0 | AF44: =ROUND(((EV44*1.2)),6) -> 384.276 | AG44: =ROUND((AP44),6) -> 0 | AH44: =((EW44*1.2)) -> 36.528 | AI44: =((EX44*1.2)) -> 0 | AJ44: =(AS44) -> 0 | AK44: 320.23 | AL44: 0 | AM44: 0 | AN44: 0 | AO44: 320.23 | AP44: 0 | AQ44: 30.44 | AR44: 0 | AS44: 0 | AT44: 91 | AU44: 48 | AV44: 1.047 | AW44: 1 | AZ44: 1 | BA44: 1 | BB44: 1 | BC44: 1 | BH44: 0 | BI44: 1 | BJ44: ТСН-2001.6. Доп. 1-42. Сб. 67, т. 5, поз. 12 | BM44: 106 | BN44: 0 | BO44: 6.67-5-12 | BP44: 1 | BQ44: 60 | BR44: 0 | BS44: 1 | BT44: 1 | BU44: 1 | BV44: 1 | BW44: 1 | BX44: 1 | BZ44: 91 | CA44: 48 | CE44: 1566 | CF44: 0 | CG44: 0 | CM44: 0 | CN44: Поправка: Гл.12.Прил.8.п.8. 3_12.00.01.11.001 Наименование: При наличии напряженных и стесненных условий производства работ (стесненность, сложность складирования и транспортной логистики и т.п.) для объектов, расположенных в пределах круговой магистральной системы улиц "Садовое кольцо" города Москвы | CO44: 0 | CP44: =(P44+Q44+S44) -> 16978.62 | CQ44: =ROUND((ROUND((AC44*AW44*1),2)*BC44),2) -> 0 | CR44: =(ROUND((ROUND((((ET44*1.2))*AV44*1),2)*BB44),2)+ROUND((ROUND(((AE44-((EU44*1.2)))*AV44*1),2)*BS44),2)) -> 0 | CS44: =(ROUND((ROUND((((EU44*1.2))*AV44*1),2)*BS44),2)+ROUND((ROUND(((AE44-((EU44*1.2)))*AV44*1),2)*BS44),2)) -> 0 | CT44: =ROUND((ROUND((AF44*AV44*1),2)*BA44),2) -> 402.34 | CU44: =AG44 -> 0 | CV44: =(AH44*AV44) -> 38.244816 | CW44: =AI44 -> 0 | CX44: =AJ44 -> 0 | CY44: =(ROUND((((S44+ROUND((ROUND((((EU44*1.2))*AV44*1),2)*BS44),2))*AT44)/100),2)+ROUND(((ROUND((ROUND(((AE44-((EU44*1.2)))*AV44*1),2)*BS44),2)*AT44)/100),2)) -> 15450.54 | CZ44: =(ROUND((((S44+ROUND((ROUND((((EU44*1.2))*AV44*1),2)*BS44),2))*AU44)/100),2)+ROUND(((ROUND((ROUND(((AE44-((EU44*1.2)))*AV44*1),2)*BS44),2)*AU44)/100),2)) -> 8149.74 | DB44: 33 | DD44: *1 | DE44: *1,2 | DF44: *1,2 | DG44: *1,2 | DI44: *1,2 | DJ44: *1,2 | DN44: 0 | DO44: 0 | DP44: 1 | DQ44: 1 | DU44: 1003 | DV44: 100 м | DW44: 100 м | DX44: 100 | EE44: 55394010 | EF44: 60 | EG44: Ремонтно-строительные работы | EH44: 0 | EJ44: 1 | EK44: 106 | EL44: ТСН-2001.6-67. Электромонтажные работы | EM44: ТСН-2001.6-67-1 | EO44: Поправка: Гл.12.Прил.8.п.8. 3_12.00.01.11.001 | EQ44: 0 | ER44: 320.23 | ES44: 0 | ET44: 0 | EU44: 0 | EV44: 320.23 | EW44: 30.44 | EX44: 0 | EY44: 0 | FQ44: 0 | FR44: 0 | FS44: 0 | FX44: 91 | FY44: 48 | GD44: 1 | GF44: -1403822920 | GG44: 2 | GH44: 1 | GI44: 2 | GJ44: 0 | GK44: 0 | GL44: =ROUND(IF(AND(BH44=3,BI44=3,FS44<>0),P44,0),2) -> 0 | GM44: =ROUND(O44+X44+Y44,2)+GX44 -> 40578.9 | GN44: =IF(OR(BI44=0,BI44=1),GM44-GX44,0) -> 40578.9 | GO44: =IF(BI44=2,GM44-GX44,0) -> 0 | GP44: =IF(BI44=4,GM44-GX44,0) -> 0 | GR44: 0 | GS44: 3 | GT44: 0 | GV44: =ROUND((GT44),6) -> 0 | GW44: 1 | GX44: =ROUND(HC44*I44,2) -> 0 | HA44: 0 | HB44: 0 | HC44: =GV44*GW44 -> 0 | HS44: 0 | IK44: 0
A45: 17 | B45: 1 | C45: =ROW(SmtRes!A4) -> 4 | D45: =ROW(EtalonRes!A4) -> 4 | E45: 9 | F45: 6.67-5-12 | G45: Демонтаж трубных проводок, трубы в борозде диаметром 25 мм / ПВХ | H45: 100 м | I45: =ROUND(4220/100,9) -> 42.2 | J45: 0 | K45: =ROUND(4220/100,9) -> 42.2 | O45: =ROUND(CP45,2) -> 956745.24 | P45: =ROUND((ROUND((AC45*AW45*I45),2)*BC45),2) -> 0 | Q45: =(ROUND((ROUND((((ET45*1.2))*AV45*I45),2)*BB45),2)+ROUND((ROUND(((AE45-((EU45*1.2)))*AV45*I45),2)*BS45),2)) -> 0 | R45: =(ROUND((ROUND((((EU45*1.2))*AV45*I45),2)*BS45),2)+ROUND((ROUND(((AE45-((EU45*1.2)))*AV45*I45),2)*BS45),2)) -> 0 | S45: =ROUND((ROUND((AF45*AV45*I45),2)*BA45),2) -> 956745.24 | T45: =ROUND(CU45*I45,2) -> 0 | U45: =CV45*I45 -> 1613.9312 | V45: =CW45*I45 -> 0 | W45: =ROUND(CX45*I45,2) -> 0 | X45: =(ROUND((((S45+ROUND((ROUND((((EU45*1.2))*AV45*I45),2)*BS45),2))*AT45)/100),2)+ROUND(((ROUND((ROUND(((AE45-((EU45*1.2)))*AV45*I45),2)*BS45),2)*AT45)/100),2)) -> 870638.17 | Y45: =(ROUND((((S45+ROUND((ROUND((((EU45*1.2))*AV45*I45),2)*BS45),2))*AU45)/100),2)+ROUND(((ROUND((ROUND(((AE45-((EU45*1.2)))*AV45*I45),2)*BS45),2)*AU45)/100),2)) -> 459237.72 | AA45: 55943568 | AB45: =ROUND((AC45+AD45+AF45),6) -> 384.276 | AC45: =ROUND(((ES45*1)),6) -> 0 | AD45: =ROUND(((((ET45*1.2))-((EU45*1.2)))+AE45),6) -> 0 | AE45: =ROUND(((EU45*1.2)),6) -> 0 | AF45: =ROUND(((EV45*1.2)),6) -> 384.276 | AG45: =ROUND((AP45),6) -> 0 | AH45: =((EW45*1.2)) -> 36.528 | AI45: =((EX45*1.2)) -> 0 | AJ45: =(AS45) -> 0 | AK45: 320.23 | AL45: 0 | AM45: 0 | AN45: 0 | AO45: 320.23 | AP45: 0 | AQ45: 30.44 | AR45: 0 | AS45: 0 | AT45: 91 | AU45: 48 | AV45: 1.047 | AW45: 1 | AZ45: 1 | BA45: 56.35 | BB45: 1 | BC45: 1 | BH45: 0 | BI45: 1 | BJ45: ТСН-2001.6. Доп. 1-42. Сб. 67, т. 5, поз. 12 | BM45: 106 | BN45: 0 | BO45: 6.67-5-12 | BP45: 1 | BQ45: 60 | BR45: 0 | BS45: 56.35 | BT45: 1 | BU45: 1 | BV45: 1 | BW45: 1 | BX45: 1 | BZ45: 91 | CA45: 48 | CE45: 1566 | CF45: 0 | CG45: 0 | CM45: 0 | CN45: Поправка: Гл.12.Прил.8.п.8. 3_12.00.01.11.001 Наименование: При наличии напряженных и стесненных условий производства работ (стесненность, сложность складирования и транспортной логистики и т.п.) для объектов, расположенных в пределах круговой магистральной системы улиц "Садовое кольцо" города Москвы | CO45: 0 | CP45: =(P45+Q45+S45) -> 956745.24 | CQ45: =ROUND((ROUND((AC45*AW45*1),2)*BC45),2) -> 0 | CR45: =(ROUND((ROUND((((ET45*1.2))*AV45*1),2)*BB45),2)+ROUND((ROUND(((AE45-((EU45*1.2)))*AV45*1),2)*BS45),2)) -> 0 | CS45: =(ROUND((ROUND((((EU45*1.2))*AV45*1),2)*BS45),2)+ROUND((ROUND(((AE45-((EU45*1.2)))*AV45*1),2)*BS45),2)) -> 0 | CT45: =ROUND((ROUND((AF45*AV45*1),2)*BA45),2) -> 22671.86 | CU45: =AG45 -> 0 | CV45: =(AH45*AV45) -> 38.244816 | CW45: =AI45 -> 0 | CX45: =AJ45 -> 0 | CY45: =(ROUND((((S45+ROUND((ROUND((((EU45*1.2))*AV45*1),2)*BS45),2))*AT45)/100),2)+ROUND(((ROUND((ROUND(((AE45-((EU45*1.2)))*AV45*1),2)*BS45),2)*AT45)/100),2)) -> 870638.17 | CZ45: =(ROUND((((S45+ROUND((ROUND((((EU45*1.2))*AV45*1),2)*BS45),2))*AU45)/100),2)+ROUND(((ROUND((ROUND(((AE45-((EU45*1.2)))*AV45*1),2)*BS45),2)*AU45)/100),2)) -> 459237.72 | DB45: 34 | DD45: *1 | DE45: *1,2 | DF45: *1,2 | DG45: *1,2 | DI45: *1,2 | DJ45: *1,2 | DN45: 0 | DO45: 0 | DP45: 1 | DQ45: 1 | DU45: 1003 | DV45: 100 м | DW45: 100 м | DX45: 100 | EE45: 55394010 | EF45: 60 | EG45: Ремонтно-строительные работы | EH45: 0 | EJ45: 1 | EK45: 106 | EL45: ТСН-2001.6-67. Электромонтажные работы | EM45: ТСН-2001.6-67-1 | EO45: Поправка: Гл.12.Прил.8.п.8. 3_12.00.01.11.001 | EQ45: 0 | ER45: 320.23 | ES45: 0 | ET45: 0 | EU45: 0 | EV45: 320.23 | EW45: 30.44 | EX45: 0 | EY45: 0 | FQ45: 0 | FR45: 0 | FS45: 0 | FX45: 91 | FY45: 48 | GD45: 1 | GF45: -1403822920 | GG45: 2 | GH45: 1 | GI45: 2 | GJ45: 0 | GK45: 0 | GL45: =ROUND(IF(AND(BH45=3,BI45=3,FS45<>0),P45,0),2) -> 0 | GM45: =ROUND(O45+X45+Y45,2)+GX45 -> 2286621.1 | GN45: =IF(OR(BI45=0,BI45=1),GM45-GX45,0) -> 2286621.1 | GO45: =IF(BI45=2,GM45-GX45,0) -> 0 | GP45: =IF(BI45=4,GM45-GX45,0) -> 0 | GR45: 0 | GS45: 3 | GT45: 0 | GV45: =ROUND((GT45),6) -> 0 | GW45: 1 | GX45: =ROUND(HC45*I45,2) -> 0 | HA45: 0 | HB45: 0 | HC45: =GV45*GW45 -> 0 | HS45: 0 | IK45: 0
A46: 17 | B46: 1 | C46: =ROW(SmtRes!A5) -> 5 | D46: =ROW(EtalonRes!A5) -> 5 | E46: 10 | F46: 6.67-6-1 | G46: Демонтаж кабеля | H46: 100 м | I46: =ROUND(4220/100,9) -> 42.2 | J46: 0 | K46: =ROUND(4220/100,9) -> 42.2 | O46: =ROUND(CP46,2) -> 5223.54 | P46: =ROUND((ROUND((AC46*AW46*I46),2)*BC46),2) -> 0 | Q46: =(ROUND((ROUND((((ET46*1.2))*AV46*I46),2)*BB46),2)+ROUND((ROUND(((AE46-((EU46*1.2)))*AV46*I46),2)*BS46),2)) -> 0 | R46: =(ROUND((ROUND((((EU46*1.2))*AV46*I46),2)*BS46),2)+ROUND((ROUND(((AE46-((EU46*1.2)))*AV46*I46),2)*BS46),2)) -> 0 | S46: =ROUND((ROUND((AF46*AV46*I46),2)*BA46),2) -> 5223.54 | T46: =ROUND(CU46*I46,2) -> 0 | U46: =CV46*I46 -> 511.11357 | V46: =CW46*I46 -> 0 | W46: =ROUND(CX46*I46,2) -> 0 | X46: =(ROUND((((S46+ROUND((ROUND((((EU46*1.2))*AV46*I46),2)*BS46),2))*AT46)/100),2)+ROUND(((ROUND((ROUND(((AE46-((EU46*1.2)))*AV46*I46),2)*BS46),2)*AT46)/100),2)) -> 4753.42 | Y46: =(ROUND((((S46+ROUND((ROUND((((EU46*1.2))*AV46*I46),2)*BS46),2))*AU46)/100),2)+ROUND(((ROUND((ROUND(((AE46-((EU46*1.2)))*AV46*I46),2)*BS46),2)*AU46)/100),2)) -> 2507.3 | AA46: 55943566 | AB46: =ROUND((AC46+AD46+AF46),6) -> 118.224 | AC46: =ROUND(((ES46*1)),6) -> 0 | AD46: =ROUND(((((ET46*1.2))-((EU46*1.2)))+AE46),6) -> 0 | AE46: =ROUND(((EU46*1.2)),6) -> 0 | AF46: =ROUND(((EV46*1.2)),6) -> 118.224 | AG46: =ROUND((AP46),6) -> 0 | AH46: =((EW46*1.2)) -> 11.568 | AI46: =((EX46*1.2)) -> 0 | AJ46: =(AS46) -> 0 | AK46: 98.52 | AL46: 0 | AM46: 0 | AN46: 0 | AO46: 98.52 | AP46: 0 | AQ46: 9.64 | AR46: 0 | AS46: 0 | AT46: 91 | AU46: 48 | AV46: 1.047 | AW46: 1 | AZ46: 1 | BA46: 1 | BB46: 1 | BC46: 1 | BH46: 0 | BI46: 1 | BJ46: ТСН-2001.6. Доп. 1-42. Сб. 67, т. 6, поз. 1 | BM46: 106 | BN46: 0 | BO46: 6.67-6-1 | BP46: 1 | BQ46: 60 | BR46: 0 | BS46: 1 | BT46: 1 | BU46: 1 | BV46: 1 | BW46: 1 | BX46: 1 | BZ46: 91 | CA46: 48 | CE46: 1566 | CF46: 0 | CG46: 0 | CM46: 0 | CN46: Поправка: Гл.12.Прил.8.п.8. 3_12.00.01.11.001 Наименование: При наличии напряженных и стесненных условий производства работ (стесненность, сложность складирования и транспортной логистики и т.п.) для объектов, расположенных в пределах круговой магистральной системы улиц "Садовое кольцо" города Москвы | CO46: 0 | CP46: =(P46+Q46+S46) -> 5223.54 | CQ46: =ROUND((ROUND((AC46*AW46*1),2)*BC46),2) -> 0 | CR46: =(ROUND((ROUND((((ET46*1.2))*AV46*1),2)*BB46),2)+ROUND((ROUND(((AE46-((EU46*1.2)))*AV46*1),2)*BS46),2)) -> 0 | CS46: =(ROUND((ROUND((((EU46*1.2))*AV46*1),2)*BS46),2)+ROUND((ROUND(((AE46-((EU46*1.2)))*AV46*1),2)*BS46),2)) -> 0 | CT46: =ROUND((ROUND((AF46*AV46*1),2)*BA46),2) -> 123.78 | CU46: =AG46 -> 0 | CV46: =(AH46*AV46) -> 12.111696 | CW46: =AI46 -> 0 | CX46: =AJ46 -> 0 | CY46: =(ROUND((((S46+ROUND((ROUND((((EU46*1.2))*AV46*1),2)*BS46),2))*AT46)/100),2)+ROUND(((ROUND((ROUND(((AE46-((EU46*1.2)))*AV46*1),2)*BS46),2)*AT46)/100),2)) -> 4753.42 | CZ46: =(ROUND((((S46+ROUND((ROUND((((EU46*1.2))*AV46*1),2)*BS46),2))*AU46)/100),2)+ROUND(((ROUND((ROUND(((AE46-((EU46*1.2)))*AV46*1),2)*BS46),2)*AU46)/100),2)) -> 2507.3 | DB46: 35 | DD46: *1 | DE46: *1,2 | DF46: *1,2 | DG46: *1,2 | DI46: *1,2 | DJ46: *1,2 | DN46: 0 | DO46: 0 | DP46: 1 | DQ46: 1 | DU46: 1003 | DV46: 100 м | DW46: 100 м | DX46: 100 | EE46: 55394010 | EF46: 60 | EG46: Ремонтно-строительные работы | EH46: 0 | EJ46: 1 | EK46: 106 | EL46: ТСН-2001.6-67. Электромонтажные работы | EM46: ТСН-2001.6-67-1 | EO46: Поправка: Гл.12.Прил.8.п.8. 3_12.00.01.11.001 | EQ46: 0 | ER46: 98.52 | ES46: 0 | ET46: 0 | EU46: 0 | EV46: 98.52 | EW46: 9.64 | EX46: 0 | EY46: 0 | FQ46: 0 | FR46: 0 | FS46: 0 | FX46: 91 | FY46: 48 | GD46: 1 | GF46: 1114236003 | GG46: 2 | GH46: 1 | GI46: 2 | GJ46: 0 | GK46: 0 | GL46: =ROUND(IF(AND(BH46=3,BI46=3,FS46<>0),P46,0),2) -> 0 | GM46: =ROUND(O46+X46+Y46,2)+GX46 -> 12484.26 | GN46: =IF(OR(BI46=0,BI46=1),GM46-GX46,0) -> 12484.26 | GO46: =IF(BI46=2,GM46-GX46,0) -> 0 | GP46: =IF(BI46=4,GM46-GX46,0) -> 0 | GR46: 0 | GS46: 3 | GT46: 0 | GV46: =ROUND((GT46),6) -> 0 | GW46: 1 | GX46: =ROUND(HC46*I46,2) -> 0 | HA46: 0 | HB46: 0 | HC46: =GV46*GW46 -> 0 | HS46: 0 | IK46: 0
A47: 17 | B47: 1 | C47: =ROW(SmtRes!A6) -> 6 | D47: =ROW(EtalonRes!A6) -> 6 | E47: 10 | F47: 6.67-6-1 | G47: Демонтаж кабеля | H47: 100 м | I47: =ROUND(4220/100,9) -> 42.2 | J47: 0 | K47: =ROUND(4220/100,9) -> 42.2 | O47: =ROUND(CP47,2) -> 294346.48 | P47: =ROUND((ROUND((AC47*AW47*I47),2)*BC47),2) -> 0 | Q47: =(ROUND((ROUND((((ET47*1.2))*AV47*I47),2)*BB47),2)+ROUND((ROUND(((AE47-((EU47*1.2)))*AV47*I47),2)*BS47),2)) -> 0 | R47: =(ROUND((ROUND((((EU47*1.2))*AV47*I47),2)*BS47),2)+ROUND((ROUND(((AE47-((EU47*1.2)))*AV47*I47),2)*BS47),2)) -> 0 | S47: =ROUND((ROUND((AF47*AV47*I47),2)*BA47),2) -> 294346.48 | T47: =ROUND(CU47*I47,2) -> 0 | U47: =CV47*I47 -> 511.11357 | V47: =CW47*I47 -> 0 | W47: =ROUND(CX47*I47,2) -> 0 | X47: =(ROUND((((S47+ROUND((ROUND((((EU47*1.2))*AV47*I47),2)*BS47),2))*AT47)/100),2)+ROUND(((ROUND((ROUND(((AE47-((EU47*1.2)))*AV47*I47),2)*BS47),2)*AT47)/100),2)) -> 267855.3 | Y47: =(ROUND((((S47+ROUND((ROUND((((EU47*1.2))*AV47*I47),2)*BS47),2))*AU47)/100),2)+ROUND(((ROUND((ROUND(((AE47-((EU47*1.2)))*AV47*I47),2)*BS47),2)*AU47)/100),2)) -> 141286.31 | AA47: 55943568 | AB47: =ROUND((AC47+AD47+AF47),6) -> 118.224 | AC47: =ROUND(((ES47*1)),6) -> 0 | AD47: =ROUND(((((ET47*1.2))-((EU47*1.2)))+AE47),6) -> 0 | AE47: =ROUND(((EU47*1.2)),6) -> 0 | AF47: =ROUND(((EV47*1.2)),6) -> 118.224 | AG47: =ROUND((AP47),6) -> 0 | AH47: =((EW47*1.2)) -> 11.568 | AI47: =((EX47*1.2)) -> 0 | AJ47: =(AS47) -> 0 | AK47: 98.52 | AL47: 0 | AM47: 0 | AN47: 0 | AO47: 98.52 | AP47: 0 | AQ47: 9.64 | AR47: 0 | AS47: 0 | AT47: 91 | AU47: 48 | AV47: 1.047 | AW47: 1 | AZ47: 1 | BA47: 56.35 | BB47: 1 | BC47: 1 | BH47: 0 | BI47: 1 | BJ47: ТСН-2001.6. Доп. 1-42. Сб. 67, т. 6, поз. 1 | BM47: 106 | BN47: 0 | BO47: 6.67-6-1 | BP47: 1 | BQ47: 60 | BR47: 0 | BS47: 56.35 | BT47: 1 | BU47: 1 | BV47: 1 | BW47: 1 | BX47: 1 | BZ47: 91 | CA47: 48 | CE47: 1566 | CF47: 0 | CG47: 0 | CM47: 0 | CN47: Поправка: Гл.12.Прил.8.п.8. 3_12.00.01.11.001 Наименование: При наличии напряженных и стесненных условий производства работ (стесненность, сложность складирования и транспортной логистики и т.п.) для объектов, расположенных в пределах круговой магистральной системы улиц "Садовое кольцо" города Москвы | CO47: 0 | CP47: =(P47+Q47+S47) -> 294346.48 | CQ47: =ROUND((ROUND((AC47*AW47*1),2)*BC47),2) -> 0 | CR47: =(ROUND((ROUND((((ET47*1.2))*AV47*1),2)*BB47),2)+ROUND((ROUND(((AE47-((EU47*1.2)))*AV47*1),2)*BS47),2)) -> 0 | CS47: =(ROUND((ROUND((((EU47*1.2))*AV47*1),2)*BS47),2)+ROUND((ROUND(((AE47-((EU47*1.2)))*AV47*1),2)*BS47),2)) -> 0 | CT47: =ROUND((ROUND((AF47*AV47*1),2)*BA47),2) -> 6975 | CU47: =AG47 -> 0 | CV47: =(AH47*AV47) -> 12.111696 | CW47: =AI47 -> 0 | CX47: =AJ47 -> 0 | CY47: =(ROUND((((S47+ROUND((ROUND((((EU47*1.2))*AV47*1),2)*BS47),2))*AT47)/100),2)+ROUND(((ROUND((ROUND(((AE47-((EU47*1.2)))*AV47*1),2)*BS47),2)*AT47)/100),2)) -> 267855.3 | CZ47: =(ROUND((((S47+ROUND((ROUND((((EU47*1.2))*AV47*1),2)*BS47),2))*AU47)/100),2)+ROUND(((ROUND((ROUND(((AE47-((EU47*1.2)))*AV47*1),2)*BS47),2)*AU47)/100),2)) -> 141286.31 | DB47: 36 | DD47: *1 | DE47: *1,2 | DF47: *1,2 | DG47: *1,2 | DI47: *1,2 | DJ47: *1,2 | DN47: 0 | DO47: 0 | DP47: 1 | DQ47: 1 | DU47: 1003 | DV47: 100 м | DW47: 100 м | DX47: 100 | EE47: 55394010 | EF47: 60 | EG47: Ремонтно-строительные работы | EH47: 0 | EJ47: 1 | EK47: 106 | EL47: ТСН-2001.6-67. Электромонтажные работы | EM47: ТСН-2001.6-67-1 | EO47: Поправка: Гл.12.Прил.8.п.8. 3_12.00.01.11.001 | EQ47: 0 | ER47: 98.52 | ES47: 0 | ET47: 0 | EU47: 0 | EV47: 98.52 | EW47: 9.64 | EX47: 0 | EY47: 0 | FQ47: 0 | FR47: 0 | FS47: 0 | FX47: 91 | FY47: 48 | GD47: 1 | GF47: 1114236003 | GG47: 2 | GH47: 1 | GI47: 2 | GJ47: 0 | GK47: 0 | GL47: =ROUND(IF(AND(BH47=3,BI47=3,FS47<>0),P47,0),2) -> 0 | GM47: =ROUND(O47+X47+Y47,2)+GX47 -> 703488.09 | GN47: =IF(OR(BI47=0,BI47=1),GM47-GX47,0) -> 703488.09 | GO47: =IF(BI47=2,GM47-GX47,0) -> 0 | GP47: =IF(BI47=4,GM47-GX47,0) -> 0 | GR47: 0 | GS47: 3 | GT47: 0 | GV47: =ROUND((GT47),6) -> 0 | GW47: 1 | GX47: =ROUND(HC47*I47,2) -> 0 | HA47: 0 | HB47: 0 | HC47: =GV47*GW47 -> 0 | HS47: 0 | IK47: 0
A49: 51 | B49: =B24 -> 1 | C49: =A24 -> 4 | D49: =ROW(A24) -> 24 | F49: =IF(F24<>"",F24,"") -> Новый раздел | G49: =IF(G24<>"",G24,"") -> Демонтажные работы | H49: 0 | O49: =ROUND(AB49,2) -> 22770.82 | P49: =ROUND(AC49,2) -> 0 | Q49: =ROUND(AD49,2) -> 70.28 | R49: =ROUND(AE49,2) -> 8.54 | S49: =ROUND(AF49,2) -> 22700.54 | T49: =ROUND(AG49,2) -> 0 | U49: =AH49 -> 2160.6389 | V49: =AI49 -> 0 | W49: =ROUND(AJ49,2) -> 0 | X49: =ROUND(AK49,2) -> 20663.85 | Y49: =ROUND(AL49,2) -> 10893.48 | AB49: =ROUND(SUMIF(AA28:AA47,"=55943566",O28:O47),2) -> 22770.82 | AC49: =ROUND(SUMIF(AA28:AA47,"=55943566",P28:P47),2) -> 0 | AD49: =ROUND(SUMIF(AA28:AA47,"=55943566",Q28:Q47),2) -> 70.28 | AE49: =ROUND(SUMIF(AA28:AA47,"=55943566",R28:R47),2) -> 8.54 | AF49: =ROUND(SUMIF(AA28:AA47,"=55943566",S28:S47),2) -> 22700.54 | AG49: =ROUND(SUMIF(AA28:AA47,"=55943566",T28:T47),2) -> 0 | AH49: =SUMIF(AA28:AA47,"=55943566",U28:U47) -> 2160.6389 | AI49: =SUMIF(AA28:AA47,"=55943566",V28:V47) -> 0 | AJ49: =ROUND(SUMIF(AA28:AA47,"=55943566",W28:W47),2) -> 0 | AK49: =ROUND(SUMIF(AA28:AA47,"=55943566",X28:X47),2) -> 20663.85 | AL49: =ROUND(SUMIF(AA28:AA47,"=55943566",Y28:Y47),2) -> 10893.48 | AO49: =ROUND(BX49,2) -> 0 | AP49: =ROUND(BY49,2) -> 0 | AQ49: =ROUND(BZ49,2) -> 0 | AR49: =ROUND(CA49,2) -> 54328.15 | AS49: =ROUND(CB49,2) -> 53063.16 | AT49: =ROUND(CC49,2) -> 1264.99 | AU49: =ROUND(CD49,2) -> 0 | AV49: =ROUND(CE49,2) -> 0 | ... BD49: =ROUND(CM49,2) -> 0 | BX49: =ROUND(SUMIF(AA28:AA47,"=55943566",FQ28:FQ47),2) -> 0 | BY49: =ROUND(SUMIF(AA28:AA47,"=55943566",FR28:FR47),2) -> 0 | BZ49: =ROUND(SUMIF(AA28:AA47,"=55943566",GL28:GL47),2) -> 0 | CA49: =ROUND(SUMIF(AA28:AA47,"=55943566",GM28:GM47),2) -> 54328.15 | CB49: =ROUND(SUMIF(AA28:AA47,"=55943566",GN28:GN47),2) -> 53063.16 | CC49: =ROUND(SUMIF(AA28:AA47,"=55943566",GO28:GO47),2) -> 1264.99 | CD49: =ROUND(SUMIF(AA28:AA47,"=55943566",GP28:GP47),2) -> 0 | CE49: =AC49-BX49 -> 0 | CF49: =AC49-BY49 -> 0 | CG49: =BX49-BZ49 -> 0 | CH49: =AC49-BX49-BY49+BZ49 -> 0 | CI49: =BY49-BZ49 -> 0 | CJ49: =ROUND(SUMIF(AA28:AA47,"=55943566",GX28:GX47),2) -> 0 | CK49: =ROUND(SUMIF(AA28:AA47,"=55943566",GY28:GY47),2) -> 0 | CL49: =ROUND(SUMIF(AA28:AA47,"=55943566",GZ28:GZ47),2) -> 0 | CM49: =ROUND(SUMIF(AA28:AA47,"=55943566",HD28:HD47),2) -> 0 | DG49: =ROUND(DT49,2) -> 1280338.7 | DH49: =ROUND(DU49,2) -> 0 | DI49: =ROUND(DV49,2) -> 1163.29 | DJ49: =ROUND(DW49,2) -> 481.24 | DK49: =ROUND(DX49,2) -> 1279175.4 | DL49: =ROUND(DY49,2) -> 0 | DM49: =DZ49 -> 2160.6389 | DN49: =EA49 -> 0 | DO49: =ROUND(EB49,2) -> 0 | DP49: =ROUND(EC49,2) -> 1164408.6 | DQ49: =ROUND(ED49,2) -> 613847.21 | DT49: =ROUND(SUMIF(AA28:AA47,"=55943568",O28:O47),2) -> 1280338.7 | DU49: =ROUND(SUMIF(AA28:AA47,"=55943568",P28:P47),2) -> 0 | DV49: =ROUND(SUMIF(AA28:AA47,"=55943568",Q28:Q47),2) -> 1163.29 | DW49: =ROUND(SUMIF(AA28:AA47,"=55943568",R28:R47),2) -> 481.24 | DX49: =ROUND(SUMIF(AA28:AA47,"=55943568",S28:S47),2) -> 1279175.4 | DY49: =ROUND(SUMIF(AA28:AA47,"=55943568",T28:T47),2) -> 0 | DZ49: =SUMIF(AA28:AA47,"=55943568",U28:U47) -> 2160.6389 | EA49: =SUMIF(AA28:AA47,"=55943568",V28:V47) -> 0 | EB49: =ROUND(SUMIF(AA28:AA47,"=55943568",W28:W47),2) -> 0 | EC49: =ROUND(SUMIF(AA28:AA47,"=55943568",X28:X47),2) -> 1164408.6 | ED49: =ROUND(SUMIF(AA28:AA47,"=55943568",Y28:Y47),2) -> 613847.21 | EG49: =ROUND(FP49,2) -> 0 | EH49: =ROUND(FQ49,2) -> 0 | EI49: =ROUND(FR49,2) -> 0 | EJ49: =ROUND(FS49,2) -> 3058594.5 | EK49: =ROUND(FT49,2) -> 2990109.2 | EL49: =ROUND(FU49,2) -> 68485.31 | EM49: =ROUND(FV49,2) -> 0 | EN49: =ROUND(FW49,2) -> 0 | ... EV49: =ROUND(GE49,2) -> 0 | FP49: =ROUND(SUMIF(AA28:AA47,"=55943568",FQ28:FQ47),2) -> 0 | FQ49: =ROUND(SUMIF(AA28:AA47,"=55943568",FR28:FR47),2) -> 0 | FR49: =ROUND(SUMIF(AA28:AA47,"=55943568",GL28:GL47),2) -> 0 | FS49: =ROUND(SUMIF(AA28:AA47,"=55943568",GM28:GM47),2) -> 3058594.5 | FT49: =ROUND(SUMIF(AA28:AA47,"=55943568",GN28:GN47),2) -> 2990109.2 | FU49: =ROUND(SUMIF(AA28:AA47,"=55943568",GO28:GO47),2) -> 68485.31 | FV49: =ROUND(SUMIF(AA28:AA47,"=55943568",GP28:GP47),2) -> 0 | FW49: =DU49-FP49 -> 0 | FX49: =DU49-FQ49 -> 0 | FY49: =FP49-FR49 -> 0 | FZ49: =DU49-FP49-FQ49+FR49 -> 0 | GA49: =FQ49-FR49 -> 0 | GB49: =ROUND(SUMIF(AA28:AA47,"=55943568",GX28:GX47),2) -> 0 | GC49: =ROUND(SUMIF(AA28:AA47,"=55943568",GY28:GY47),2) -> 0 | GD49: =ROUND(SUMIF(AA28:AA47,"=55943568",GZ28:GZ47),2) -> 0 | GE49: =ROUND(SUMIF(AA28:AA47,"=55943568",HD28:HD47),2) -> 0 | GX49: 0
A51: 50 | B51: 0 | C51: 0 | D51: 1 | E51: 201 | F51: =ROUND(Source!O49,O51) -> 22770.82 | G51: ПЗ | H51: Прямые затраты | K51: 201 | L51: 1 | M51: 3 | O51: 2 | P51: =ROUND(Source!DG49,O51) -> 1280338.7 | W51: 22770.82 | X51: 1 | Y51: 22770.82 | Z51: 1280338.7 | AA51: 1 | AB51: 1280338.7
A52: 50 | B52: 0 | C52: 0 | D52: 1 | E52: 202 | F52: =ROUND(Source!P49,O52) -> 0 | G52: СтМатОб | H52: Стоимость материальных ресурсов (всего) | K52: 202 | L52: 2 | M52: 3 | O52: 2 | P52: =ROUND(Source!DH49,O52) -> 0 | W52: 0 | X52: 1 | Y52: 0 | Z52: 0 | AA52: 1 | AB52: 0
A53: 50 | B53: 0 | C53: 0 | D53: 1 | E53: 222 | F53: =ROUND(Source!AO49,O53) -> 0 | G53: СтМатОбЗак | H53: Стоимость материалов и оборудования заказчика | K53: 222 | L53: 3 | M53: 3 | O53: 2 | P53: =ROUND(Source!EG49,O53) -> 0 | W53: 0 | X53: 1 | Y53: 0 | Z53: 0 | AA53: 1 | AB53: 0
A54: 50 | B54: 0 | C54: 0 | D54: 1 | E54: 225 | F54: =ROUND(Source!AV49,O54) -> 0 | G54: СтМатОбПод | H54: Стоимость материалов и оборудования подрядчика | K54: 225 | L54: 4 | M54: 3 | O54: 2 | P54: =ROUND(Source!EN49,O54) -> 0 | W54: 0 | X54: 1 | Y54: 0 | Z54: 0 | AA54: 1 | AB54: 0
A55: 50 | B55: 0 | C55: 0 | D55: 1 | E55: 226 | F55: =ROUND(Source!AW49,O55) -> 0 | G55: СтМат | H55: Стоимость материалов (всего) | K55: 226 | L55: 5 | M55: 3 | O55: 2 | P55: =ROUND(Source!EO49,O55) -> 0 | W55: 0 | X55: 1 | Y55: 0 | Z55: 0 | AA55: 1 | AB55: 0
A56: 50 | B56: 0 | C56: 0 | D56: 1 | E56: 227 | F56: =ROUND(Source!AX49,O56) -> 0 | G56: СтМатЗак | H56: Стоимость материалов заказчика | K56: 227 | L56: 6 | M56: 3 | O56: 2 | P56: =ROUND(Source!EP49,O56) -> 0 | W56: 0 | X56: 1 | Y56: 0 | Z56: 0 | AA56: 1 | AB56: 0
A57: 50 | B57: 0 | C57: 0 | D57: 1 | E57: 228 | F57: =ROUND(Source!AY49,O57) -> 0 | G57: СтМатПод | H57: Стоимость материалов подрядчика | K57: 228 | L57: 7 | M57: 3 | O57: 2 | P57: =ROUND(Source!EQ49,O57) -> 0 | W57: 0 | X57: 1 | Y57: 0 | Z57: 0 | AA57: 1 | AB57: 0
A58: 50 | B58: 0 | C58: 0 | D58: 1 | E58: 216 | F58: =ROUND(Source!AP49,O58) -> 0 | G58: Оборуд | H58: Стоимость оборудования (всего) | K58: 216 | L58: 8 | M58: 3 | O58: 2 | P58: =ROUND(Source!EH49,O58) -> 0 | W58: 0 | X58: 1 | Y58: 0 | Z58: 0 | AA58: 1 | AB58: 0
A59: 50 | B59: 0 | C59: 0 | D59: 1 | E59: 223 | F59: =ROUND(Source!AQ49,O59) -> 0 | G59: ОборудЗак | H59: Стоимость оборудования заказчика | K59: 223 | L59: 9 | M59: 3 | O59: 2 | P59: =ROUND(Source!EI49,O59) -> 0 | W59: 0 | X59: 1 | Y59: 0 | Z59: 0 | AA59: 1 | AB59: 0
A60: 50 | B60: 0 | C60: 0 | D60: 1 | E60: 229 | F60: =ROUND(Source!AZ49,O60) -> 0 | G60: ОборудПод | H60: Стоимость оборудования подрядчика | K60: 229 | L60: 10 | M60: 3 | O60: 2 | P60: =ROUND(Source!ER49,O60) -> 0 | W60: 0 | X60: 1 | Y60: 0 | Z60: 0 | AA60: 1 | AB60: 0
A61: 50 | B61: 0 | C61: 0 | D61: 1 | E61: 203 | F61: =ROUND(Source!Q49,O61) -> 70.28 | G61: ЭММ | H61: Эксплуатация машин | K61: 203 | L61: 11 | M61: 3 | O61: 2 | P61: =ROUND(Source!DI49,O61) -> 1163.29 | W61: 70.28 | X61: 1 | Y61: 70.28 | Z61: 1163.29 | AA61: 1 | AB61: 1163.29
A62: 50 | B62: 0 | C62: 0 | D62: 1 | E62: 231 | F62: =ROUND(Source!BB49,O62) -> 0 | G62: ЭММсНРиСП | H62: Эксплуатация машин по ТСН-2001.16 | K62: 231 | L62: 12 | M62: 3 | O62: 2 | P62: =ROUND(Source!ET49,O62) -> 0 | W62: 0 | X62: 1 | Y62: 0 | Z62: 0 | AA62: 1 | AB62: 0
A63: 50 | B63: 0 | C63: 0 | D63: 1 | E63: 204 | F63: =ROUND(Source!R49,O63) -> 8.54 | G63: ЗПМ | H63: ЗП машинистов | K63: 204 | L63: 13 | M63: 3 | O63: 2 | P63: =ROUND(Source!DJ49,O63) -> 481.24 | W63: 8.54 | X63: 1 | Y63: 8.54 | Z63: 481.24 | AA63: 1 | AB63: 481.24
A64: 50 | B64: 0 | C64: 0 | D64: 1 | E64: 205 | F64: =ROUND(Source!S49,O64) -> 22700.54 | G64: ОЗП | H64: Основная ЗП рабочих | K64: 205 | L64: 14 | M64: 3 | O64: 2 | P64: =ROUND(Source!DK49,O64) -> 1279175.4 | W64: 22700.54 | X64: 1 | Y64: 22700.54 | Z64: 1279175.4 | AA64: 1 | AB64: 1279175.4
A65: 50 | B65: 0 | C65: 0 | D65: 1 | E65: 232 | F65: =ROUND(Source!BC49,O65) -> 0 | G65: ОЗПсНРиСП | H65: Основная ЗП рабочих по ТСН-2001.16 | K65: 232 | L65: 15 | M65: 3 | O65: 2 | P65: =ROUND(Source!EU49,O65) -> 0 | W65: 0 | X65: 1 | Y65: 0 | Z65: 0 | AA65: 1 | AB65: 0
A66: 50 | B66: 0 | C66: 0 | D66: 1 | E66: 214 | F66: =ROUND(Source!AS49,O66) -> 53063.16 | G66: Строит | H66: Строительные работы с НР и СП | K66: 214 | L66: 16 | M66: 3 | O66: 2 | P66: =ROUND(Source!EK49,O66) -> 2990109.2 | W66: 53063.16 | X66: 1 | Y66: 53063.16 | Z66: 2990109.2 | AA66: 1 | AB66: 2990109.2
A67: 50 | B67: 0 | C67: 0 | D67: 1 | E67: 215 | F67: =ROUND(Source!AT49,O67) -> 1264.99 | G67: Монтаж | H67: Монтажные работы с НР и СП | K67: 215 | L67: 17 | M67: 3 | O67: 2 | P67: =ROUND(Source!EL49,O67) -> 68485.31 | W67: 1264.99 | X67: 1 | Y67: 1264.99 | Z67: 68485.31 | AA67: 1 | AB67: 68485.31
A68: 50 | B68: 0 | C68: 0 | D68: 1 | E68: 217 | F68: =ROUND(Source!AU49,O68) -> 0 | G68: Прочие | H68: Прочие работы с НР и СП | K68: 217 | L68: 18 | M68: 3 | O68: 2 | P68: =ROUND(Source!EM49,O68) -> 0 | W68: 0 | X68: 1 | Y68: 0 | Z68: 0 | AA68: 1 | AB68: 0
A69: 50 | B69: 0 | C69: 0 | D69: 1 | E69: 230 | F69: =ROUND(Source!BA49,O69) -> 0 | G69: ПрочиеЗатр | H69: Прочие затраты по ТСН-2001.16 | K69: 230 | L69: 19 | M69: 3 | O69: 2 | P69: =ROUND(Source!ES49,O69) -> 0 | W69: 0 | X69: 1 | Y69: 0 | Z69: 0 | AA69: 1 | AB69: 0
A70: 50 | B70: 0 | C70: 0 | D70: 1 | E70: 206 | F70: =ROUND(Source!T49,O70) -> 0 | G70: ВозврМат | H70: Возврат материалов | K70: 206 | L70: 20 | M70: 3 | O70: 2 | P70: =ROUND(Source!DL49,O70) -> 0 | W70: 0 | X70: 1 | Y70: 0 | Z70: 0 | AA70: 1 | AB70: 0
A71: 50 | B71: 0 | C71: 0 | D71: 1 | E71: 207 | F71: =Source!U49 -> 2160.6389 | G71: ТрудСтр | H71: Трудозатраты строителей | K71: 207 | L71: 21 | M71: 3 | O71: -1 | P71: =Source!DM49 -> 2160.6389 | W71: 2160.6389 | X71: 1 | Y71: 2160.6389 | Z71: 2160.6389 | AA71: 1 | AB71: 2160.6389
A72: 50 | B72: 0 | C72: 0 | D72: 1 | E72: 208 | F72: =Source!V49 -> 0 | G72: ТрудМаш | H72: Трудозатраты машинистов | K72: 208 | L72: 22 | M72: 3 | O72: -1 | P72: =Source!DN49 -> 0 | W72: 0 | X72: 1 | Y72: 0 | Z72: 0 | AA72: 1 | AB72: 0
A73: 50 | B73: 0 | C73: 0 | D73: 1 | E73: 209 | F73: =ROUND(Source!W49,O73) -> 0 | G73: ТранспМат | H73: Транспорт материалов | K73: 209 | L73: 23 | M73: 3 | O73: 2 | P73: =ROUND(Source!DO49,O73) -> 0 | W73: 0 | X73: 1 | Y73: 0 | Z73: 0 | AA73: 1 | AB73: 0
A74: 50 | B74: 0 | C74: 0 | D74: 1 | E74: 233 | F74: =ROUND(Source!BD49,O74) -> 0 | G74: Перевозка | H74: Перевозка грузов | K74: 233 | L74: 24 | M74: 3 | O74: 2 | P74: =ROUND(Source!EV49,O74) -> 0 | W74: 0 | X74: 1 | Y74: 0 | Z74: 0 | AA74: 1 | AB74: 0
A75: 50 | B75: 0 | C75: 0 | D75: 1 | E75: 210 | F75: =ROUND(Source!X49,O75) -> 20663.85 | G75: НР | H75: Накладные расходы | K75: 210 | L75: 25 | M75: 3 | O75: 2 | P75: =ROUND(Source!DP49,O75) -> 1164408.6 | W75: 20663.85 | X75: 1 | Y75: 20663.85 | Z75: 1164408.6 | AA75: 1 | AB75: 1164408.6
A76: 50 | B76: 0 | C76: 0 | D76: 1 | E76: 211 | F76: =ROUND(Source!Y49,O76) -> 10893.48 | G76: СмПриб | H76: Сметная прибыль | K76: 211 | L76: 26 | M76: 3 | O76: 2 | P76: =ROUND(Source!DQ49,O76) -> 613847.21 | W76: 10893.48 | X76: 1 | Y76: 10893.48 | Z76: 613847.21 | AA76: 1 | AB76: 613847.21
A77: 50 | B77: 0 | C77: 0 | D77: 1 | E77: 224 | F77: =ROUND(Source!AR49,O77) -> 54328.15 | G77: Всего | H77: Всего с НР и СП | K77: 224 | L77: 27 | M77: 3 | O77: 2 | P77: =ROUND(Source!EJ49,O77) -> 3058594.5 | W77: 54328.15 | X77: 1 | Y77: 54328.15 | Z77: 3058594.5 | AA77: 1 | AB77: 3058594.5
A79: 4 | B79: 1 | D79: =ROW(A118) -> 118 | F79: Новый раздел | G79: Оборудование системы двусторонней связи | I79: 0 | K79: -1 | S79: 0 | T79: 0 | V79: 2 | BX79: 0 | CJ79: 0
A81: 52 | B81: =B118 -> 1 | C81: =C118 -> 4 | D81: =D118 -> 79 | E81: =E118 -> 0 | F81: =F118 -> Новый раздел | G81: =G118 -> Оборудование системы двусторонней связи | O81: =O118 -> 255351.62 | P81: =P118 -> 253634.39 | Q81: =Q118 -> 234.2 | R81: =R118 -> 28.44 | S81: =S118 -> 1483.03 | T81: =T118 -> 0 | U81: =U118 -> 104.87673 | V81: =V118 -> 0 | ... GX81: =GX118 -> 0
A83: 17 | B83: 1 | E83: 11 | F83: 4.11-7-1 | G83: Установка аппарата настольного массой до 0,015 т | H83: 1ШТ. | I83: 1 | J83: 0 | K83: 1 | O83: =ROUND(CP83,2) -> 31.18 | P83: =ROUND((ROUND((AC83*AW83*I83),2)*BC83),2) -> 0 | Q83: =(ROUND((ROUND((((ET83*1.2))*AV83*I83),2)*BB83),2)+ROUND((ROUND(((AE83-((EU83*1.2)))*AV83*I83),2)*BS83),2)) -> 16.71 | R83: =(ROUND((ROUND((((EU83*1.2))*AV83*I83),2)*BS83),2)+ROUND((ROUND(((AE83-((EU83*1.2)))*AV83*I83),2)*BS83),2)) -> 2.54 | S83: =ROUND((ROUND((AF83*AV83*I83),2)*BA83),2) -> 14.47 | T83: =ROUND(CU83*I83,2) -> 0 | U83: =CV83*I83 -> 1.294092 | V83: =CW83*I83 -> 0 | W83: =ROUND(CX83*I83,2) -> 0 | X83: =(ROUND((((S83+ROUND((ROUND((((EU83*1.2))*AV83*I83),2)*BS83),2))*AT83)/100),2)+ROUND(((ROUND((ROUND(((AE83-((EU83*1.2)))*AV83*I83),2)*BS83),2)*AT83)/100),2)) -> 15.31 | Y83: =(ROUND((((S83+ROUND((ROUND((((EU83*1.2))*AV83*I83),2)*BS83),2))*AU83)/100),2)+ROUND(((ROUND((ROUND(((AE83-((EU83*1.2)))*AV83*I83),2)*BS83),2)*AU83)/100),2)) -> 7.82 | AA83: 55943566 | AB83: =ROUND((AC83+AD83+AF83),6) -> 29.784 | AC83: =ROUND(((ES83*1)),6) -> 0 | AD83: =ROUND(((((ET83*1.2))-((EU83*1.2)))+AE83),6) -> 15.96 | AE83: =ROUND(((EU83*1.2)),6) -> 2.424 | AF83: =ROUND(((EV83*1.2)),6) -> 13.824 | AG83: =ROUND((AP83),6) -> 0 | AH83: =((EW83*1.2)) -> 1.236 | AI83: =((EX83*1.2)) -> 0 | AJ83: =(AS83) -> 0 | AK83: 24.82 | AL83: 0 | AM83: 13.3 | AN83: 2.02 | AO83: 11.52 | AP83: 0 | AQ83: 1.03 | AR83: 0 | AS83: 0 | AT83: 90 | AU83: 46 | AV83: 1.047 | AW83: 1 | AZ83: 1 | BA83: 1 | BB83: 1 | BC83: 1 | BH83: 0 | BI83: 2 | BJ83: ТСН-2001.4 Доп. 68, Сб. 11, т. 7, поз. 1 | BM83: 72 | BN83: 0 | BO83: 4.11-7-1 | BP83: 1 | BQ83: 40 | BR83: 0 | BS83: 1 | BT83: 1 | BU83: 1 | BV83: 1 | BW83: 1 | BX83: 1 | BZ83: 90 | CA83: 46 | CE83: 1566 | CF83: 0 | CG83: 0 | CM83: 0 | CN83: Поправка: Гл.12.Прил.8.п.8. 3_12.00.01.11.001 Наименование: При наличии напряженных и стесненных условий производства работ (стесненность, сложность складирования и транспортной логистики и т.п.) для объектов, расположенных в пределах круговой магистральной системы улиц "Садовое кольцо" города Москвы | CO83: 0 | CP83: =(P83+Q83+S83) -> 31.18 | CQ83: =ROUND((ROUND((AC83*AW83*1),2)*BC83),2) -> 0 | CR83: =(ROUND((ROUND((((ET83*1.2))*AV83*1),2)*BB83),2)+ROUND((ROUND(((AE83-((EU83*1.2)))*AV83*1),2)*BS83),2)) -> 16.71 | CS83: =(ROUND((ROUND((((EU83*1.2))*AV83*1),2)*BS83),2)+ROUND((ROUND(((AE83-((EU83*1.2)))*AV83*1),2)*BS83),2)) -> 2.54 | CT83: =ROUND((ROUND((AF83*AV83*1),2)*BA83),2) -> 14.47 | CU83: =AG83 -> 0 | CV83: =(AH83*AV83) -> 1.294092 | CW83: =AI83 -> 0 | CX83: =AJ83 -> 0 | CY83: =(ROUND((((S83+ROUND((ROUND((((EU83*1.2))*AV83*1),2)*BS83),2))*AT83)/100),2)+ROUND(((ROUND((ROUND(((AE83-((EU83*1.2)))*AV83*1),2)*BS83),2)*AT83)/100),2)) -> 15.31 | CZ83: =(ROUND((((S83+ROUND((ROUND((((EU83*1.2))*AV83*1),2)*BS83),2))*AU83)/100),2)+ROUND(((ROUND((ROUND(((AE83-((EU83*1.2)))*AV83*1),2)*BS83),2)*AU83)/100),2)) -> 7.82 | DB83: 37 | DD83: *1 | DE83: *1,2 | DF83: *1,2 | DG83: *1,2 | DI83: *1,2 | DJ83: *1,2 | DN83: 0 | DO83: 0 | DP83: 1 | DQ83: 1 | DU83: 1013 | DV83: 1ШТ. | DW83: 1 ШТ. | DX83: 1 | EE83: 55393976 | EF83: 40 | EG83: Монтаж оборудования | EH83: 0 | EJ83: 2 | EK83: 72 | EL83: ТСН-2001.4-11. Приборы и средства автоматизации и вычислительной техники | EM83: ТСН-2001.4-11-1 | EO83: Поправка: Гл.12.Прил.8.п.8. 3_12.00.01.11.001 | EQ83: 131072 | ER83: 24.82 | ES83: 0 | ET83: 13.3 | EU83: 2.02 | EV83: 11.52 | EW83: 1.03 | EX83: 0 | EY83: 0 | FQ83: 0 | FR83: 0 | FS83: 0 | FX83: 90 | FY83: 46 | GD83: 1 | GF83: 1504310839 | GG83: 2 | GH83: 1 | GI83: 2 | GJ83: 0 | GK83: 0 | GL83: =ROUND(IF(AND(BH83=3,BI83=3,FS83<>0),P83,0),2) -> 0 | GM83: =ROUND(O83+X83+Y83,2)+GX83 -> 54.31 | GN83: =IF(OR(BI83=0,BI83=1),GM83-GX83,0) -> 0 | GO83: =IF(BI83=2,GM83-GX83,0) -> 54.31 | GP83: =IF(BI83=4,GM83-GX83,0) -> 0 | GR83: 0 | GS83: 3 | GT83: 0 | GV83: =ROUND((GT83),6) -> 0 | GW83: 1 | GX83: =ROUND(HC83*I83,2) -> 0 | HA83: 0 | HB83: 0 | HC83: =GV83*GW83 -> 0 | HS83: 0 | IK83: 0
A84: 17 | B84: 1 | E84: 11 | F84: 4.11-7-1 | G84: Установка аппарата настольного массой до 0,015 т | H84: 1ШТ. | I84: 1 | J84: 0 | K84: 1 | O84: =ROUND(CP84,2) -> 1100.45 | P84: =ROUND((ROUND((AC84*AW84*I84),2)*BC84),2) -> 0 | Q84: =(ROUND((ROUND((((ET84*1.2))*AV84*I84),2)*BB84),2)+ROUND((ROUND(((AE84-((EU84*1.2)))*AV84*I84),2)*BS84),2)) -> 285.07 | R84: =(ROUND((ROUND((((EU84*1.2))*AV84*I84),2)*BS84),2)+ROUND((ROUND(((AE84-((EU84*1.2)))*AV84*I84),2)*BS84),2)) -> 143.13 | S84: =ROUND((ROUND((AF84*AV84*I84),2)*BA84),2) -> 815.38 | T84: =ROUND(CU84*I84,2) -> 0 | U84: =CV84*I84 -> 1.294092 | V84: =CW84*I84 -> 0 | W84: =ROUND(CX84*I84,2) -> 0 | X84: =(ROUND((((S84+ROUND((ROUND((((EU84*1.2))*AV84*I84),2)*BS84),2))*AT84)/100),2)+ROUND(((ROUND((ROUND(((AE84-((EU84*1.2)))*AV84*I84),2)*BS84),2)*AT84)/100),2)) -> 862.66 | Y84: =(ROUND((((S84+ROUND((ROUND((((EU84*1.2))*AV84*I84),2)*BS84),2))*AU84)/100),2)+ROUND(((ROUND((ROUND(((AE84-((EU84*1.2)))*AV84*I84),2)*BS84),2)*AU84)/100),2)) -> 440.91 | AA84: 55943568 | AB84: =ROUND((AC84+AD84+AF84),6) -> 29.784 | AC84: =ROUND(((ES84*1)),6) -> 0 | AD84: =ROUND(((((ET84*1.2))-((EU84*1.2)))+AE84),6) -> 15.96 | AE84: =ROUND(((EU84*1.2)),6) -> 2.424 | AF84: =ROUND(((EV84*1.2)),6) -> 13.824 | AG84: =ROUND((AP84),6) -> 0 | AH84: =((EW84*1.2)) -> 1.236 | AI84: =((EX84*1.2)) -> 0 | AJ84: =(AS84) -> 0 | AK84: 24.82 | AL84: 0 | AM84: 13.3 | AN84: 2.02 | AO84: 11.52 | AP84: 0 | AQ84: 1.03 | AR84: 0 | AS84: 0 | AT84: 90 | AU84: 46 | AV84: 1.047 | AW84: 1 | AZ84: 1 | BA84: 56.35 | BB84: 17.06 | BC84: 1 | BH84: 0 | BI84: 2 | BJ84: ТСН-2001.4 Доп. 68, Сб. 11, т. 7, поз. 1 | BM84: 72 | BN84: 0 | BO84: 4.11-7-1 | BP84: 1 | BQ84: 40 | BR84: 0 | BS84: 56.35 | BT84: 1 | BU84: 1 | BV84: 1 | BW84: 1 | BX84: 1 | BZ84: 90 | CA84: 46 | CE84: 1566 | CF84: 0 | CG84: 0 | CM84: 0 | CN84: Поправка: Гл.12.Прил.8.п.8. 3_12.00.01.11.001 Наименование: При наличии напряженных и стесненных условий производства работ (стесненность, сложность складирования и транспортной логистики и т.п.) для объектов, расположенных в пределах круговой магистральной системы улиц "Садовое кольцо" города Москвы | CO84: 0 | CP84: =(P84+Q84+S84) -> 1100.45 | CQ84: =ROUND((ROUND((AC84*AW84*1),2)*BC84),2) -> 0 | CR84: =(ROUND((ROUND((((ET84*1.2))*AV84*1),2)*BB84),2)+ROUND((ROUND(((AE84-((EU84*1.2)))*AV84*1),2)*BS84),2)) -> 285.07 | CS84: =(ROUND((ROUND((((EU84*1.2))*AV84*1),2)*BS84),2)+ROUND((ROUND(((AE84-((EU84*1.2)))*AV84*1),2)*BS84),2)) -> 143.13 | CT84: =ROUND((ROUND((AF84*AV84*1),2)*BA84),2) -> 815.38 | CU84: =AG84 -> 0 | CV84: =(AH84*AV84) -> 1.294092 | CW84: =AI84 -> 0 | CX84: =AJ84 -> 0 | CY84: =(ROUND((((S84+ROUND((ROUND((((EU84*1.2))*AV84*1),2)*BS84),2))*AT84)/100),2)+ROUND(((ROUND((ROUND(((AE84-((EU84*1.2)))*AV84*1),2)*BS84),2)*AT84)/100),2)) -> 862.66 | CZ84: =(ROUND((((S84+ROUND((ROUND((((EU84*1.2))*AV84*1),2)*BS84),2))*AU84)/100),2)+ROUND(((ROUND((ROUND(((AE84-((EU84*1.2)))*AV84*1),2)*BS84),2)*AU84)/100),2)) -> 440.91 | DB84: 38 | DD84: *1 | DE84: *1,2 | DF84: *1,2 | DG84: *1,2 | DI84: *1,2 | DJ84: *1,2 | DN84: 0 | DO84: 0 | DP84: 1 | DQ84: 1 | DU84: 1013 | DV84: 1ШТ. | DW84: 1 ШТ. | DX84: 1 | EE84: 55393976 | EF84: 40 | EG84: Монтаж оборудования | EH84: 0 | EJ84: 2 | EK84: 72 | EL84: ТСН-2001.4-11. Приборы и средства автоматизации и вычислительной техники | EM84: ТСН-2001.4-11-1 | EO84: Поправка: Гл.12.Прил.8.п.8. 3_12.00.01.11.001 | EQ84: 131072 | ER84: 24.82 | ES84: 0 | ET84: 13.3 | EU84: 2.02 | EV84: 11.52 | EW84: 1.03 | EX84: 0 | EY84: 0 | FQ84: 0 | FR84: 0 | FS84: 0 | FX84: 90 | FY84: 46 | GD84: 1 | GF84: 1504310839 | GG84: 2 | GH84: 1 | GI84: 2 | GJ84: 0 | GK84: 0 | GL84: =ROUND(IF(AND(BH84=3,BI84=3,FS84<>0),P84,0),2) -> 0 | GM84: =ROUND(O84+X84+Y84,2)+GX84 -> 2404.02 | GN84: =IF(OR(BI84=0,BI84=1),GM84-GX84,0) -> 0 | GO84: =IF(BI84=2,GM84-GX84,0) -> 2404.02 | GP84: =IF(BI84=4,GM84-GX84,0) -> 0 | GR84: 0 | GS84: 3 | GT84: 0 | GV84: =ROUND((GT84),6) -> 0 | GW84: 1 | GX84: =ROUND(HC84*I84,2) -> 0 | HA84: 0 | HB84: 0 | HC84: =GV84*GW84 -> 0 | HS84: 0 | IK84: 0
A85: 17 | B85: 1 | E85: 12 | F85: КА, п.1 | G85: Пульт диспетчера (32 абонента) AN-CO32 | H85: ШТ | I85: 1 | J85: 0 | K85: 1 | O85: =ROUND(CP85,2) -> 14083.83 | P85: =ROUND((ROUND((AC85*AW85*I85),2)*BC85),2) -> 14083.83 | Q85: =(ROUND((ROUND(((ET85)*AV85*I85),2)*BB85),2)+ROUND((ROUND(((AE85-(EU85))*AV85*I85),2)*BS85),2)) -> 0 | R85: =(ROUND((ROUND(((EU85)*AV85*I85),2)*BS85),2)+ROUND((ROUND(((AE85-(EU85))*AV85*I85),2)*BS85),2)) -> 0 | S85: =ROUND((ROUND((AF85*AV85*I85),2)*BA85),2) -> 0 | T85: =ROUND(CU85*I85,2) -> 0 | U85: =CV85*I85 -> 0 | V85: =CW85*I85 -> 0 | W85: =ROUND(CX85*I85,2) -> 0 | X85: =(ROUND((((S85+ROUND((ROUND(((EU85)*AV85*I85),2)*BS85),2))*AT85)/100),2)+ROUND(((ROUND((ROUND(((AE85-(EU85))*AV85*I85),2)*BS85),2)*AT85)/100),2)) -> 0 | Y85: =(ROUND((((S85+ROUND((ROUND(((EU85)*AV85*I85),2)*BS85),2))*AU85)/100),2)+ROUND(((ROUND((ROUND(((AE85-(EU85))*AV85*I85),2)*BS85),2)*AU85)/100),2)) -> 0 | AA85: 55943566 | AB85: =ROUND((AC85+AD85+AF85),6) -> 14083.83 | AC85: =ROUND((ES85),6) -> 14083.83 | AD85: =ROUND((((ET85)-(EU85))+AE85),6) -> 0 | AE85: =ROUND((EU85),6) -> 0 | AF85: =ROUND((EV85),6) -> 0 | AG85: =ROUND((AP85),6) -> 0 | AH85: =(EW85) -> 0 | AI85: =(EX85) -> 0 | AJ85: =(AS85) -> 0 | AK85: 14083.83 | AL85: 14083.83 | AM85: 0 | AN85: 0 | AO85: 0 | AP85: 0 | AQ85: 0 | AR85: 0 | AS85: 0 | AT85: 0 | AU85: 0 | AV85: 1 | AW85: 1 | AZ85: 1 | BA85: 1 | BB85: 1 | BC85: 1 | BH85: 3 | BI85: 3 | BJ85: КА, п.1 | BM85: 400007 | BN85: 0 | BP85: 0 | BQ85: 214 | BR85: 0 | BS85: 1 | BT85: 1 | BU85: 1 | BV85: 1 | BW85: 1 | BX85: 1 | BZ85: 0 | CA85: 0 | CE85: 1566 | CF85: 0 | CG85: 0 | CM85: 0 | CO85: 0 | CP85: =(P85+Q85+S85) -> 14083.83 | CQ85: =ROUND((ROUND((AC85*AW85*1),2)*BC85),2) -> 14083.83 | CR85: =(ROUND((ROUND(((ET85)*AV85*1),2)*BB85),2)+ROUND((ROUND(((AE85-(EU85))*AV85*1),2)*BS85),2)) -> 0 | CS85: =(ROUND((ROUND(((EU85)*AV85*1),2)*BS85),2)+ROUND((ROUND(((AE85-(EU85))*AV85*1),2)*BS85),2)) -> 0 | CT85: =ROUND((ROUND((AF85*AV85*1),2)*BA85),2) -> 0 | CU85: =AG85 -> 0 | CV85: =(AH85*AV85) -> 0 | CW85: =AI85 -> 0 | CX85: =AJ85 -> 0 | CY85: =(ROUND((((S85+ROUND((ROUND(((EU85)*AV85*1),2)*BS85),2))*AT85)/100),2)+ROUND(((ROUND((ROUND(((AE85-(EU85))*AV85*1),2)*BS85),2)*AT85)/100),2)) -> 0 | CZ85: =(ROUND((((S85+ROUND((ROUND(((EU85)*AV85*1),2)*BS85),2))*AU85)/100),2)+ROUND(((ROUND((ROUND(((AE85-(EU85))*AV85*1),2)*BS85),2)*AU85)/100),2)) -> 0 | DN85: 0 | DO85: 0 | DP85: 1 | DQ85: 1 | DU85: 1013 | DV85: ШТ | DW85: ШТ | DX85: 1 | EE85: 55393904 | EF85: 214 | EG85: Оборудование, отсутствующие в СНБ | EH85: 0 | EJ85: 3 | EK85: 400007 | EL85: Оборудование, отсутствующие в СНБ | EM85: Оборуд. КА | EQ85: 131088 | ER85: 0 | ES85: 14083.83 | ET85: 0 | EU85: 0 | EV85: 0 | EW85: 0 | EX85: 0 | EY85: 0 | FQ85: 0 | FR85: =P85 -> 14083.83 | FS85: 0 | FX85: 0 | FY85: 0 | GA85: [124 784 / 1,22 / 7,57] + 3% Трансп + 1,2% Заг.скл | GD85: 1 | GF85: -1835517610 | GG85: 2 | GH85: 4 | GI85: -2 | GJ85: 0 | GK85: 0 | GL85: =ROUND(IF(AND(BH85=3,BI85=3,FS85<>0),P85,0),2) -> 0 | GM85: =ROUND(O85+X85+Y85,2)+GX85 -> 14083.83 | GN85: =IF(OR(BI85=0,BI85=1),GM85-GX85,0) -> 0 | GO85: =IF(BI85=2,GM85-GX85,0) -> 0 | GP85: =IF(BI85=4,GM85-GX85,0) -> 0 | GR85: 0 | GS85: 2 | GT85: 0 | GV85: =ROUND((GT85),6) -> 0 | GW85: 1 | GX85: =ROUND(HC85*I85,2) -> 0 | HA85: 0 | HB85: 0 | HC85: =GV85*GW85 -> 0 | HE85: 3 | HF85: 1,2 | HS85: 0 | IK85: 0
A86: 17 | B86: 1 | E86: 12 | F86: КА, п.1 | G86: Пульт диспетчера (32 абонента) AN-CO32 | H86: ШТ | I86: 1 | J86: 0 | K86: 1 | O86: =ROUND(CP86,2) -> 106614.59 | P86: =ROUND((ROUND((AC86*AW86*I86),2)*BC86),2) -> 106614.59 | Q86: =(ROUND((ROUND(((ET86)*AV86*I86),2)*BB86),2)+ROUND((ROUND(((AE86-(EU86))*AV86*I86),2)*BS86),2)) -> 0 | R86: =(ROUND((ROUND(((EU86)*AV86*I86),2)*BS86),2)+ROUND((ROUND(((AE86-(EU86))*AV86*I86),2)*BS86),2)) -> 0 | S86: =ROUND((ROUND((AF86*AV86*I86),2)*BA86),2) -> 0 | T86: =ROUND(CU86*I86,2) -> 0 | U86: =CV86*I86 -> 0 | V86: =CW86*I86 -> 0 | W86: =ROUND(CX86*I86,2) -> 0 | X86: =(ROUND((((S86+ROUND((ROUND(((EU86)*AV86*I86),2)*BS86),2))*AT86)/100),2)+ROUND(((ROUND((ROUND(((AE86-(EU86))*AV86*I86),2)*BS86),2)*AT86)/100),2)) -> 0 | Y86: =(ROUND((((S86+ROUND((ROUND(((EU86)*AV86*I86),2)*BS86),2))*AU86)/100),2)+ROUND(((ROUND((ROUND(((AE86-(EU86))*AV86*I86),2)*BS86),2)*AU86)/100),2)) -> 0 | AA86: 55943568 | AB86: =ROUND((AC86+AD86+AF86),6) -> 14083.83 | AC86: =ROUND((ES86),6) -> 14083.83 | AD86: =ROUND((((ET86)-(EU86))+AE86),6) -> 0 | AE86: =ROUND((EU86),6) -> 0 | AF86: =ROUND((EV86),6) -> 0 | AG86: =ROUND((AP86),6) -> 0 | AH86: =(EW86) -> 0 | AI86: =(EX86) -> 0 | AJ86: =(AS86) -> 0 | AK86: 14083.83 | AL86: 14083.83 | AM86: 0 | AN86: 0 | AO86: 0 | AP86: 0 | AQ86: 0 | AR86: 0 | AS86: 0 | AT86: 0 | AU86: 0 | AV86: 1 | AW86: 1 | AZ86: 1 | BA86: 1 | BB86: 1 | BC86: 7.57 | BH86: 3 | BI86: 3 | BJ86: КА, п.1 | BM86: 400007 | BN86: 0 | BP86: 0 | BQ86: 214 | BR86: 0 | BS86: 1 | BT86: 1 | BU86: 1 | BV86: 1 | BW86: 1 | BX86: 1 | BZ86: 0 | CA86: 0 | CE86: 1566 | CF86: 0 | CG86: 0 | CM86: 0 | CO86: 0 | CP86: =(P86+Q86+S86) -> 106614.59 | CQ86: =ROUND((ROUND((AC86*AW86*1),2)*BC86),2) -> 106614.59 | CR86: =(ROUND((ROUND(((ET86)*AV86*1),2)*BB86),2)+ROUND((ROUND(((AE86-(EU86))*AV86*1),2)*BS86),2)) -> 0 | CS86: =(ROUND((ROUND(((EU86)*AV86*1),2)*BS86),2)+ROUND((ROUND(((AE86-(EU86))*AV86*1),2)*BS86),2)) -> 0 | CT86: =ROUND((ROUND((AF86*AV86*1),2)*BA86),2) -> 0 | CU86: =AG86 -> 0 | CV86: =(AH86*AV86) -> 0 | CW86: =AI86 -> 0 | CX86: =AJ86 -> 0 | CY86: =(ROUND((((S86+ROUND((ROUND(((EU86)*AV86*1),2)*BS86),2))*AT86)/100),2)+ROUND(((ROUND((ROUND(((AE86-(EU86))*AV86*1),2)*BS86),2)*AT86)/100),2)) -> 0 | CZ86: =(ROUND((((S86+ROUND((ROUND(((EU86)*AV86*1),2)*BS86),2))*AU86)/100),2)+ROUND(((ROUND((ROUND(((AE86-(EU86))*AV86*1),2)*BS86),2)*AU86)/100),2)) -> 0 | DN86: 0 | DO86: 0 | DP86: 1 | DQ86: 1 | DU86: 1013 | DV86: ШТ | DW86: ШТ | DX86: 1 | EE86: 55393904 | EF86: 214 | EG86: Оборудование, отсутствующие в СНБ | EH86: 0 | EJ86: 3 | EK86: 400007 | EL86: Оборудование, отсутствующие в СНБ | EM86: Оборуд. КА | EQ86: 131088 | ER86: 13918.36 | ES86: 14083.83 | ET86: 0 | EU86: 0 | EV86: 0 | EW86: 0 | EX86: 0 | EY86: 0 | EZ86: 5 | FC86: 1 | FD86: 18 | FF86: 124784 | FQ86: 0 | FR86: =P86 -> 106614.59 | FS86: 0 | FX86: 0 | FY86: 0 | GA86: [124 784 / 1,22 / 7,57] + 3% Трансп + 1,2% Заг.скл | GD86: 1 | GF86: -1835517610 | GG86: 2 | GH86: 3 | GI86: 3 | GJ86: 0 | GK86: 0 | GL86: =ROUND(IF(AND(BH86=3,BI86=3,FS86<>0),P86,0),2) -> 0 | GM86: =ROUND(O86+X86+Y86,2)+GX86 -> 106614.59 | GN86: =IF(OR(BI86=0,BI86=1),GM86-GX86,0) -> 0 | GO86: =IF(BI86=2,GM86-GX86,0) -> 0 | GP86: =IF(BI86=4,GM86-GX86,0) -> 0 | GR86: 1 | GS86: 1 | GT86: 0 | GV86: =ROUND((GT86),6) -> 0 | GW86: 1 | GX86: =ROUND(HC86*I86,2) -> 0 | HA86: 0 | HB86: 0 | HC86: =GV86*GW86 -> 0 | HE86: 3 | HF86: 1,2 | HS86: 0 | IK86: 0
A87: 17 | B87: 1 | E87: 13 | F87: 4.10-34-5 | G87: Монтаж коммутатора служебной связи | H87: 1 ШТ. | I87: =ROUND(4+1,9) -> 5 | J87: 0 | K87: =ROUND(4+1,9) -> 5 | O87: =ROUND(CP87,2) -> 733.61 | P87: =ROUND((ROUND((AC87*AW87*I87),2)*BC87),2) -> 61.75 | Q87: =(ROUND((ROUND((((ET87*1.2))*AV87*I87),2)*BB87),2)+ROUND((ROUND(((AE87-((EU87*1.2)))*AV87*I87),2)*BS87),2)) -> 180.36 | R87: =(ROUND((ROUND((((EU87*1.2))*AV87*I87),2)*BS87),2)+ROUND((ROUND(((AE87-((EU87*1.2)))*AV87*I87),2)*BS87),2)) -> 19.85 | S87: =ROUND((ROUND((AF87*AV87*I87),2)*BA87),2) -> 491.5 | T87: =ROUND(CU87*I87,2) -> 0 | U87: =CV87*I87 -> 38.9484 | V87: =CW87*I87 -> 0 | W87: =ROUND(CX87*I87,2) -> 0 | X87: =(ROUND((((S87+ROUND((ROUND((((EU87*1.2))*AV87*I87),2)*BS87),2))*AT87)/100),2)+ROUND(((ROUND((ROUND(((AE87-((EU87*1.2)))*AV87*I87),2)*BS87),2)*AT87)/100),2)) -> 460.22 | Y87: =(ROUND((((S87+ROUND((ROUND((((EU87*1.2))*AV87*I87),2)*BS87),2))*AU87)/100),2)+ROUND(((ROUND((ROUND(((AE87-((EU87*1.2)))*AV87*I87),2)*BS87),2)*AU87)/100),2)) -> 235.22 | AA87: 55943566 | AB87: =ROUND((AC87+AD87+AF87),6) -> 140.69 | AC87: =ROUND(((ES87*1)),6) -> 12.35 | AD87: =ROUND(((((ET87*1.2))-((EU87*1.2)))+AE87),6) -> 34.452 | AE87: =ROUND(((EU87*1.2)),6) -> 3.792 | AF87: =ROUND(((EV87*1.2)),6) -> 93.888 | AG87: =ROUND((AP87),6) -> 0 | AH87: =((EW87*1.2)) -> 7.44 | AI87: =((EX87*1.2)) -> 0 | AJ87: =(AS87) -> 0 | AK87: 119.3 | AL87: 12.35 | AM87: 28.71 | AN87: 3.16 | AO87: 78.24 | AP87: 0 | AQ87: 6.2 | AR87: 0 | AS87: 0 | AT87: 90 | AU87: 46 | AV87: 1.047 | AW87: 1 | AZ87: 1 | BA87: 1 | BB87: 1 | BC87: 1 | BH87: 0 | BI87: 2 | BJ87: ТСН-2001.4 Доп. 80, Сб. 10, т. 34, поз. 5 | BM87: 68 | BN87: 0 | BO87: 4.10-34-5 | BP87: 1 | BQ87: 40 | BR87: 0 | BS87: 1 | BT87: 1 | BU87: 1 | BV87: 1 | BW87: 1 | BX87: 1 | BZ87: 90 | CA87: 46 | CE87: 1566 | CF87: 0 | CG87: 0 | CM87: 0 | CN87: Поправка: Гл.12.Прил.8.п.8. 3_12.00.01.11.001 Наименование: При наличии напряженных и стесненных условий производства работ (стесненность, сложность складирования и транспортной логистики и т.п.) для объектов, расположенных в пределах круговой магистральной системы улиц "Садовое кольцо" города Москвы | CO87: 0 | CP87: =(P87+Q87+S87) -> 733.61 | CQ87: =ROUND((ROUND((AC87*AW87*1),2)*BC87),2) -> 12.35 | CR87: =(ROUND((ROUND((((ET87*1.2))*AV87*1),2)*BB87),2)+ROUND((ROUND(((AE87-((EU87*1.2)))*AV87*1),2)*BS87),2)) -> 36.07 | CS87: =(ROUND((ROUND((((EU87*1.2))*AV87*1),2)*BS87),2)+ROUND((ROUND(((AE87-((EU87*1.2)))*AV87*1),2)*BS87),2)) -> 3.97 | CT87: =ROUND((ROUND((AF87*AV87*1),2)*BA87),2) -> 98.3 | CU87: =AG87 -> 0 | CV87: =(AH87*AV87) -> 7.78968 | CW87: =AI87 -> 0 | CX87: =AJ87 -> 0 | CY87: =(ROUND((((S87+ROUND((ROUND((((EU87*1.2))*AV87*1),2)*BS87),2))*AT87)/100),2)+ROUND(((ROUND((ROUND(((AE87-((EU87*1.2)))*AV87*1),2)*BS87),2)*AT87)/100),2)) -> 445.92 | CZ87: =(ROUND((((S87+ROUND((ROUND((((EU87*1.2))*AV87*1),2)*BS87),2))*AU87)/100),2)+ROUND(((ROUND((ROUND(((AE87-((EU87*1.2)))*AV87*1),2)*BS87),2)*AU87)/100),2)) -> 227.92 | DB87: 39 | DD87: *1 | DE87: *1,2 | DF87: *1,2 | DG87: *1,2 | DI87: *1,2 | DJ87: *1,2 | DN87: 0 | DO87: 0 | DP87: 1 | DQ87: 1 | DU87: 1013 | DV87: 1 ШТ. | DW87: 1 ШТ. | DX87: 1 | EE87: 55393972 | EF87: 40 | EG87: Монтаж оборудования | EH87: 0 | EJ87: 2 | EK87: 68 | EL87: ТСН-2001.4-10. Прокладка и монтаж сетей связи | EM87: ТСН-2001.4-10-1 | EO87: Поправка: Гл.12.Прил.8.п.8. 3_12.00.01.11.001 | EQ87: 131072 | ER87: 119.3 | ES87: 12.35 | ET87: 28.71 | EU87: 3.16 | EV87: 78.24 | EW87: 6.2 | EX87: 0 | EY87: 0 | FQ87: 0 | FR87: 0 | FS87: 0 | FX87: 90 | FY87: 46 | GD87: 1 | GF87: 982292204 | GG87: 2 | GH87: 1 | GI87: 2 | GJ87: 0 | GK87: 0 | GL87: =ROUND(IF(AND(BH87=3,BI87=3,FS87<>0),P87,0),2) -> 0 | GM87: =ROUND(O87+X87+Y87,2)+GX87 -> 1429.05 | GN87: =IF(OR(BI87=0,BI87=1),GM87-GX87,0) -> 0 | GO87: =IF(BI87=2,GM87-GX87,0) -> 1429.05 | GP87: =IF(BI87=4,GM87-GX87,0) -> 0 | GR87: 0 | GS87: 3 | GT87: 0 | GV87: =ROUND((GT87),6) -> 0 | GW87: 1 | GX87: =ROUND(HC87*I87,2) -> 0 | HA87: 0 | HB87: 0 | HC87: =GV87*GW87 -> 0 | HS87: 0 | IK87: 0
A88: 17 | B88: 1 | E88: 13 | F88: 4.10-34-5 | G88: Монтаж коммутатора служебной связи | H88: 1 ШТ. | I88: =ROUND(4+1,9) -> 5 | J88: 0 | K88: =ROUND(4+1,9) -> 5 | O88: =ROUND(CP88,2) -> 31518.38 | P88: =ROUND((ROUND((AC88*AW88*I88),2)*BC88),2) -> 907.73 | Q88: =(ROUND((ROUND((((ET88*1.2))*AV88*I88),2)*BB88),2)+ROUND((ROUND(((AE88-((EU88*1.2)))*AV88*I88),2)*BS88),2)) -> 2914.62 | R88: =(ROUND((ROUND((((EU88*1.2))*AV88*I88),2)*BS88),2)+ROUND((ROUND(((AE88-((EU88*1.2)))*AV88*I88),2)*BS88),2)) -> 1118.55 | S88: =ROUND((ROUND((AF88*AV88*I88),2)*BA88),2) -> 27696.03 | T88: =ROUND(CU88*I88,2) -> 0 | U88: =CV88*I88 -> 38.9484 | V88: =CW88*I88 -> 0 | W88: =ROUND(CX88*I88,2) -> 0 | X88: =(ROUND((((S88+ROUND((ROUND((((EU88*1.2))*AV88*I88),2)*BS88),2))*AT88)/100),2)+ROUND(((ROUND((ROUND(((AE88-((EU88*1.2)))*AV88*I88),2)*BS88),2)*AT88)/100),2)) -> 25933.12 | Y88: =(ROUND((((S88+ROUND((ROUND((((EU88*1.2))*AV88*I88),2)*BS88),2))*AU88)/100),2)+ROUND(((ROUND((ROUND(((AE88-((EU88*1.2)))*AV88*I88),2)*BS88),2)*AU88)/100),2)) -> 13254.71 | AA88: 55943568 | AB88: =ROUND((AC88+AD88+AF88),6) -> 140.69 | AC88: =ROUND(((ES88*1)),6) -> 12.35 | AD88: =ROUND(((((ET88*1.2))-((EU88*1.2)))+AE88),6) -> 34.452 | AE88: =ROUND(((EU88*1.2)),6) -> 3.792 | AF88: =ROUND(((EV88*1.2)),6) -> 93.888 | AG88: =ROUND((AP88),6) -> 0 | AH88: =((EW88*1.2)) -> 7.44 | AI88: =((EX88*1.2)) -> 0 | AJ88: =(AS88) -> 0 | AK88: 119.3 | AL88: 12.35 | AM88: 28.71 | AN88: 3.16 | AO88: 78.24 | AP88: 0 | AQ88: 6.2 | AR88: 0 | AS88: 0 | AT88: 90 | AU88: 46 | AV88: 1.047 | AW88: 1 | AZ88: 1 | BA88: 56.35 | BB88: 16.16 | BC88: 14.7 | BH88: 0 | BI88: 2 | BJ88: ТСН-2001.4 Доп. 80, Сб. 10, т. 34, поз. 5 | BM88: 68 | BN88: 0 | BO88: 4.10-34-5 | BP88: 1 | BQ88: 40 | BR88: 0 | BS88: 56.35 | BT88: 1 | BU88: 1 | BV88: 1 | BW88: 1 | BX88: 1 | BZ88: 90 | CA88: 46 | CE88: 1566 | CF88: 0 | CG88: 0 | CM88: 0 | CN88: Поправка: Гл.12.Прил.8.п.8. 3_12.00.01.11.001 Наименование: При наличии напряженных и стесненных условий производства работ (стесненность, сложность складирования и транспортной логистики и т.п.) для объектов, расположенных в пределах круговой магистральной системы улиц "Садовое кольцо" города Москвы | CO88: 0 | CP88: =(P88+Q88+S88) -> 31518.38 | CQ88: =ROUND((ROUND((AC88*AW88*1),2)*BC88),2) -> 181.55 | CR88: =(ROUND((ROUND((((ET88*1.2))*AV88*1),2)*BB88),2)+ROUND((ROUND(((AE88-((EU88*1.2)))*AV88*1),2)*BS88),2)) -> 582.89 | CS88: =(ROUND((ROUND((((EU88*1.2))*AV88*1),2)*BS88),2)+ROUND((ROUND(((AE88-((EU88*1.2)))*AV88*1),2)*BS88),2)) -> 223.71 | CT88: =ROUND((ROUND((AF88*AV88*1),2)*BA88),2) -> 5539.21 | CU88: =AG88 -> 0 | CV88: =(AH88*AV88) -> 7.78968 | CW88: =AI88 -> 0 | CX88: =AJ88 -> 0 | CY88: =(ROUND((((S88+ROUND((ROUND((((EU88*1.2))*AV88*1),2)*BS88),2))*AT88)/100),2)+ROUND(((ROUND((ROUND(((AE88-((EU88*1.2)))*AV88*1),2)*BS88),2)*AT88)/100),2)) -> 25127.77 | CZ88: =(ROUND((((S88+ROUND((ROUND((((EU88*1.2))*AV88*1),2)*BS88),2))*AU88)/100),2)+ROUND(((ROUND((ROUND(((AE88-((EU88*1.2)))*AV88*1),2)*BS88),2)*AU88)/100),2)) -> 12843.08 | DB88: 40 | DD88: *1 | DE88: *1,2 | DF88: *1,2 | DG88: *1,2 | DI88: *1,2 | DJ88: *1,2 | DN88: 0 | DO88: 0 | DP88: 1 | DQ88: 1 | DU88: 1013 | DV88: 1 ШТ. | DW88: 1 ШТ. | DX88: 1 | EE88: 55393972 | EF88: 40 | EG88: Монтаж оборудования | EH88: 0 | EJ88: 2 | EK88: 68 | EL88: ТСН-2001.4-10. Прокладка и монтаж сетей связи | EM88: ТСН-2001.4-10-1 | EO88: Поправка: Гл.12.Прил.8.п.8. 3_12.00.01.11.001 | EQ88: 131072 | ER88: 119.3 | ES88: 12.35 | ET88: 28.71 | EU88: 3.16 | EV88: 78.24 | EW88: 6.2 | EX88: 0 | EY88: 0 | FQ88: 0 | FR88: 0 | FS88: 0 | FX88: 90 | FY88: 46 | GD88: 1 | GF88: 982292204 | GG88: 2 | GH88: 1 | GI88: 2 | GJ88: 0 | GK88: 0 | GL88: =ROUND(IF(AND(BH88=3,BI88=3,FS88<>0),P88,0),2) -> 0 | GM88: =ROUND(O88+X88+Y88,2)+GX88 -> 70706.21 | GN88: =IF(OR(BI88=0,BI88=1),GM88-GX88,0) -> 0 | GO88: =IF(BI88=2,GM88-GX88,0) -> 70706.21 | GP88: =IF(BI88=4,GM88-GX88,0) -> 0 | GR88: 0 | GS88: 3 | GT88: 0 | GV88: =ROUND((GT88),6) -> 0 | GW88: 1 | GX88: =ROUND(HC88*I88,2) -> 0 | HA88: 0 | HB88: 0 | HC88: =GV88*GW88 -> 0 | HS88: 0 | IK88: 0
A89: 17 | B89: 1 | E89: 14 | F89: КА, п.2 | G89: Блок коммутации (не более 4-х для одного пульта AN-CO32, 8 линий) AN-X8 | H89: ШТ | I89: 4 | J89: 0 | K89: 4 | O89: =ROUND(CP89,2) -> 41874.52 | P89: =ROUND((ROUND((AC89*AW89*I89),2)*BC89),2) -> 41874.52 | Q89: =(ROUND((ROUND(((ET89)*AV89*I89),2)*BB89),2)+ROUND((ROUND(((AE89-(EU89))*AV89*I89),2)*BS89),2)) -> 0 | R89: =(ROUND((ROUND(((EU89)*AV89*I89),2)*BS89),2)+ROUND((ROUND(((AE89-(EU89))*AV89*I89),2)*BS89),2)) -> 0 | S89: =ROUND((ROUND((AF89*AV89*I89),2)*BA89),2) -> 0 | T89: =ROUND(CU89*I89,2) -> 0 | U89: =CV89*I89 -> 0 | V89: =CW89*I89 -> 0 | W89: =ROUND(CX89*I89,2) -> 0 | X89: =(ROUND((((S89+ROUND((ROUND(((EU89)*AV89*I89),2)*BS89),2))*AT89)/100),2)+ROUND(((ROUND((ROUND(((AE89-(EU89))*AV89*I89),2)*BS89),2)*AT89)/100),2)) -> 0 | Y89: =(ROUND((((S89+ROUND((ROUND(((EU89)*AV89*I89),2)*BS89),2))*AU89)/100),2)+ROUND(((ROUND((ROUND(((AE89-(EU89))*AV89*I89),2)*BS89),2)*AU89)/100),2)) -> 0 | AA89: 55943566 | AB89: =ROUND((AC89+AD89+AF89),6) -> 10468.63 | AC89: =ROUND((ES89),6) -> 10468.63 | AD89: =ROUND((((ET89)-(EU89))+AE89),6) -> 0 | AE89: =ROUND((EU89),6) -> 0 | AF89: =ROUND((EV89),6) -> 0 | AG89: =ROUND((AP89),6) -> 0 | AH89: =(EW89) -> 0 | AI89: =(EX89) -> 0 | AJ89: =(AS89) -> 0 | AK89: 10468.63 | AL89: 10468.63 | AM89: 0 | AN89: 0 | AO89: 0 | AP89: 0 | AQ89: 0 | AR89: 0 | AS89: 0 | AT89: 0 | AU89: 0 | AV89: 1 | AW89: 1 | AZ89: 1 | BA89: 1 | BB89: 1 | BC89: 1 | BH89: 3 | BI89: 3 | BJ89: КА, п.2 | BM89: 400007 | BN89: 0 | BP89: 0 | BQ89: 214 | BR89: 0 | BS89: 1 | BT89: 1 | BU89: 1 | BV89: 1 | BW89: 1 | BX89: 1 | BZ89: 0 | CA89: 0 | CE89: 1566 | CF89: 0 | CG89: 0 | CM89: 0 | CO89: 0 | CP89: =(P89+Q89+S89) -> 41874.52 | CQ89: =ROUND((ROUND((AC89*AW89*1),2)*BC89),2) -> 10468.63 | CR89: =(ROUND((ROUND(((ET89)*AV89*1),2)*BB89),2)+ROUND((ROUND(((AE89-(EU89))*AV89*1),2)*BS89),2)) -> 0 | CS89: =(ROUND((ROUND(((EU89)*AV89*1),2)*BS89),2)+ROUND((ROUND(((AE89-(EU89))*AV89*1),2)*BS89),2)) -> 0 | CT89: =ROUND((ROUND((AF89*AV89*1),2)*BA89),2) -> 0 | CU89: =AG89 -> 0 | CV89: =(AH89*AV89) -> 0 | CW89: =AI89 -> 0 | CX89: =AJ89 -> 0 | CY89: =(ROUND((((S89+ROUND((ROUND(((EU89)*AV89*1),2)*BS89),2))*AT89)/100),2)+ROUND(((ROUND((ROUND(((AE89-(EU89))*AV89*1),2)*BS89),2)*AT89)/100),2)) -> 0 | CZ89: =(ROUND((((S89+ROUND((ROUND(((EU89)*AV89*1),2)*BS89),2))*AU89)/100),2)+ROUND(((ROUND((ROUND(((AE89-(EU89))*AV89*1),2)*BS89),2)*AU89)/100),2)) -> 0 | DN89: 0 | DO89: 0 | DP89: 1 | DQ89: 1 | DU89: 1013 | DV89: ШТ | DW89: ШТ | DX89: 1 | EE89: 55393904 | EF89: 214 | EG89: Оборудование, отсутствующие в СНБ | EH89: 0 | EJ89: 3 | EK89: 400007 | EL89: Оборудование, отсутствующие в СНБ | EM89: Оборуд. КА | EQ89: 131088 | ER89: 0 | ES89: 10468.63 | ET89: 0 | EU89: 0 | EV89: 0 | EW89: 0 | EX89: 0 | EY89: 0 | FQ89: 0 | FR89: =P89 -> 41874.52 | FS89: 0 | FX89: 0 | FY89: 0 | GA89: [96 682 / 1,22 / 7,57] | GD89: 1 | GF89: 467054729 | GG89: 2 | GH89: 4 | GI89: -2 | GJ89: 0 | GK89: 0 | GL89: =ROUND(IF(AND(BH89=3,BI89=3,FS89<>0),P89,0),2) -> 0 | GM89: =ROUND(O89+X89+Y89,2)+GX89 -> 41874.52 | GN89: =IF(OR(BI89=0,BI89=1),GM89-GX89,0) -> 0 | GO89: =IF(BI89=2,GM89-GX89,0) -> 0 | GP89: =IF(BI89=4,GM89-GX89,0) -> 0 | GR89: 1 | GS89: 2 | GT89: 0 | GV89: =ROUND((GT89),6) -> 0 | GW89: 1 | GX89: =ROUND(HC89*I89,2) -> 0 | HA89: 0 | HB89: 0 | HC89: =GV89*GW89 -> 0 | HE89: 0 | HF89: 0 | HS89: 0 | IK89: 0
A90: 17 | B90: 1 | E90: 14 | F90: КА, п.2 | G90: Блок коммутации (не более 4-х для одного пульта AN-CO32, 8 линий) AN-X8 | H90: ШТ | I90: 4 | J90: 0 | K90: 4 | O90: =ROUND(CP90,2) -> 316990.12 | P90: =ROUND((ROUND((AC90*AW90*I90),2)*BC90),2) -> 316990.12 | Q90: =(ROUND((ROUND(((ET90)*AV90*I90),2)*BB90),2)+ROUND((ROUND(((AE90-(EU90))*AV90*I90),2)*BS90),2)) -> 0 | R90: =(ROUND((ROUND(((EU90)*AV90*I90),2)*BS90),2)+ROUND((ROUND(((AE90-(EU90))*AV90*I90),2)*BS90),2)) -> 0 | S90: =ROUND((ROUND((AF90*AV90*I90),2)*BA90),2) -> 0 | T90: =ROUND(CU90*I90,2) -> 0 | U90: =CV90*I90 -> 0 | V90: =CW90*I90 -> 0 | W90: =ROUND(CX90*I90,2) -> 0 | X90: =(ROUND((((S90+ROUND((ROUND(((EU90)*AV90*I90),2)*BS90),2))*AT90)/100),2)+ROUND(((ROUND((ROUND(((AE90-(EU90))*AV90*I90),2)*BS90),2)*AT90)/100),2)) -> 0 | Y90: =(ROUND((((S90+ROUND((ROUND(((EU90)*AV90*I90),2)*BS90),2))*AU90)/100),2)+ROUND(((ROUND((ROUND(((AE90-(EU90))*AV90*I90),2)*BS90),2)*AU90)/100),2)) -> 0 | AA90: 55943568 | AB90: =ROUND((AC90+AD90+AF90),6) -> 10468.63 | AC90: =ROUND((ES90),6) -> 10468.63 | AD90: =ROUND((((ET90)-(EU90))+AE90),6) -> 0 | AE90: =ROUND((EU90),6) -> 0 | AF90: =ROUND((EV90),6) -> 0 | AG90: =ROUND((AP90),6) -> 0 | AH90: =(EW90) -> 0 | AI90: =(EX90) -> 0 | AJ90: =(AS90) -> 0 | AK90: 10468.63 | AL90: 10468.63 | AM90: 0 | AN90: 0 | AO90: 0 | AP90: 0 | AQ90: 0 | AR90: 0 | AS90: 0 | AT90: 0 | AU90: 0 | AV90: 1 | AW90: 1 | AZ90: 1 | BA90: 1 | BB90: 1 | BC90: 7.57 | BH90: 3 | BI90: 3 | BJ90: КА, п.2 | BM90: 400007 | BN90: 0 | BP90: 0 | BQ90: 214 | BR90: 0 | BS90: 1 | BT90: 1 | BU90: 1 | BV90: 1 | BW90: 1 | BX90: 1 | BZ90: 0 | CA90: 0 | CE90: 1566 | CF90: 0 | CG90: 0 | CM90: 0 | CO90: 0 | CP90: =(P90+Q90+S90) -> 316990.12 | CQ90: =ROUND((ROUND((AC90*AW90*1),2)*BC90),2) -> 79247.53 | CR90: =(ROUND((ROUND(((ET90)*AV90*1),2)*BB90),2)+ROUND((ROUND(((AE90-(EU90))*AV90*1),2)*BS90),2)) -> 0 | CS90: =(ROUND((ROUND(((EU90)*AV90*1),2)*BS90),2)+ROUND((ROUND(((AE90-(EU90))*AV90*1),2)*BS90),2)) -> 0 | CT90: =ROUND((ROUND((AF90*AV90*1),2)*BA90),2) -> 0 | CU90: =AG90 -> 0 | CV90: =(AH90*AV90) -> 0 | CW90: =AI90 -> 0 | CX90: =AJ90 -> 0 | CY90: =(ROUND((((S90+ROUND((ROUND(((EU90)*AV90*1),2)*BS90),2))*AT90)/100),2)+ROUND(((ROUND((ROUND(((AE90-(EU90))*AV90*1),2)*BS90),2)*AT90)/100),2)) -> 0 | CZ90: =(ROUND((((S90+ROUND((ROUND(((EU90)*AV90*1),2)*BS90),2))*AU90)/100),2)+ROUND(((ROUND((ROUND(((AE90-(EU90))*AV90*1),2)*BS90),2)*AU90)/100),2)) -> 0 | DN90: 0 | DO90: 0 | DP90: 1 | DQ90: 1 | DU90: 1013 | DV90: ШТ | DW90: ШТ | DX90: 1 | EE90: 55393904 | EF90: 214 | EG90: Оборудование, отсутствующие в СНБ | EH90: 0 | EJ90: 3 | EK90: 400007 | EL90: Оборудование, отсутствующие в СНБ | EM90: Оборуд. КА | EQ90: 131088 | ER90: 0 | ES90: 10468.63 | ET90: 0 | EU90: 0 | EV90: 0 | EW90: 0 | EX90: 0 | EY90: 0 | EZ90: 5 | FC90: 1 | FD90: 18 | FF90: 96682 | FQ90: 0 | FR90: =P90 -> 316990.12 | FS90: 0 | FX90: 0 | FY90: 0 | GA90: [96 682 / 1,22 / 7,57] | GD90: 1 | GF90: 467054729 | GG90: 2 | GH90: 3 | GI90: 3 | GJ90: 0 | GK90: 0 | GL90: =ROUND(IF(AND(BH90=3,BI90=3,FS90<>0),P90,0),2) -> 0 | GM90: =ROUND(O90+X90+Y90,2)+GX90 -> 316990.12 | GN90: =IF(OR(BI90=0,BI90=1),GM90-GX90,0) -> 0 | GO90: =IF(BI90=2,GM90-GX90,0) -> 0 | GP90: =IF(BI90=4,GM90-GX90,0) -> 0 | GR90: 1 | GS90: 1 | GT90: 0 | GV90: =ROUND((GT90),6) -> 0 | GW90: 1 | GX90: =ROUND(HC90*I90,2) -> 0 | HA90: 0 | HB90: 0 | HC90: =GV90*GW90 -> 0 | HE90: 0 | HF90: 0 | HS90: 0 | IK90: 0
A91: 17 | B91: 1 | E91: 15 | F91: КА, п.3 | G91: Блок коммутации абонентских линий AN-X8 MGN | H91: ШТ | I91: 1 | J91: 0 | K91: 1 | O91: =ROUND(CP91,2) -> 15062.8 | P91: =ROUND((ROUND((AC91*AW91*I91),2)*BC91),2) -> 15062.8 | Q91: =(ROUND((ROUND(((ET91)*AV91*I91),2)*BB91),2)+ROUND((ROUND(((AE91-(EU91))*AV91*I91),2)*BS91),2)) -> 0 | R91: =(ROUND((ROUND(((EU91)*AV91*I91),2)*BS91),2)+ROUND((ROUND(((AE91-(EU91))*AV91*I91),2)*BS91),2)) -> 0 | S91: =ROUND((ROUND((AF91*AV91*I91),2)*BA91),2) -> 0 | T91: =ROUND(CU91*I91,2) -> 0 | U91: =CV91*I91 -> 0 | V91: =CW91*I91 -> 0 | W91: =ROUND(CX91*I91,2) -> 0 | X91: =(ROUND((((S91+ROUND((ROUND(((EU91)*AV91*I91),2)*BS91),2))*AT91)/100),2)+ROUND(((ROUND((ROUND(((AE91-(EU91))*AV91*I91),2)*BS91),2)*AT91)/100),2)) -> 0 | Y91: =(ROUND((((S91+ROUND((ROUND(((EU91)*AV91*I91),2)*BS91),2))*AU91)/100),2)+ROUND(((ROUND((ROUND(((AE91-(EU91))*AV91*I91),2)*BS91),2)*AU91)/100),2)) -> 0 | AA91: 55943566 | AB91: =ROUND((AC91+AD91+AF91),6) -> 15062.8 | AC91: =ROUND((ES91),6) -> 15062.8 | AD91: =ROUND((((ET91)-(EU91))+AE91),6) -> 0 | AE91: =ROUND((EU91),6) -> 0 | AF91: =ROUND((EV91),6) -> 0 | AG91: =ROUND((AP91),6) -> 0 | AH91: =(EW91) -> 0 | AI91: =(EX91) -> 0 | AJ91: =(AS91) -> 0 | AK91: 15062.8 | AL91: 15062.8 | AM91: 0 | AN91: 0 | AO91: 0 | AP91: 0 | AQ91: 0 | AR91: 0 | AS91: 0 | AT91: 0 | AU91: 0 | AV91: 1 | AW91: 1 | AZ91: 1 | BA91: 1 | BB91: 1 | BC91: 1 | BH91: 3 | BI91: 3 | BJ91: КА, п.3 | BM91: 400007 | BN91: 0 | BP91: 0 | BQ91: 214 | BR91: 0 | BS91: 1 | BT91: 1 | BU91: 1 | BV91: 1 | BW91: 1 | BX91: 1 | BZ91: 0 | CA91: 0 | CE91: 1566 | CF91: 0 | CG91: 0 | CM91: 0 | CO91: 0 | CP91: =(P91+Q91+S91) -> 15062.8 | CQ91: =ROUND((ROUND((AC91*AW91*1),2)*BC91),2) -> 15062.8 | CR91: =(ROUND((ROUND(((ET91)*AV91*1),2)*BB91),2)+ROUND((ROUND(((AE91-(EU91))*AV91*1),2)*BS91),2)) -> 0 | CS91: =(ROUND((ROUND(((EU91)*AV91*1),2)*BS91),2)+ROUND((ROUND(((AE91-(EU91))*AV91*1),2)*BS91),2)) -> 0 | CT91: =ROUND((ROUND((AF91*AV91*1),2)*BA91),2) -> 0 | CU91: =AG91 -> 0 | CV91: =(AH91*AV91) -> 0 | CW91: =AI91 -> 0 | CX91: =AJ91 -> 0 | CY91: =(ROUND((((S91+ROUND((ROUND(((EU91)*AV91*1),2)*BS91),2))*AT91)/100),2)+ROUND(((ROUND((ROUND(((AE91-(EU91))*AV91*1),2)*BS91),2)*AT91)/100),2)) -> 0 | CZ91: =(ROUND((((S91+ROUND((ROUND(((EU91)*AV91*1),2)*BS91),2))*AU91)/100),2)+ROUND(((ROUND((ROUND(((AE91-(EU91))*AV91*1),2)*BS91),2)*AU91)/100),2)) -> 0 | DN91: 0 | DO91: 0 | DP91: 1 | DQ91: 1 | DU91: 1013 | DV91: ШТ | DW91: ШТ | DX91: 1 | EE91: 55393904 | EF91: 214 | EG91: Оборудование, отсутствующие в СНБ | EH91: 0 | EJ91: 3 | EK91: 400007 | EL91: Оборудование, отсутствующие в СНБ | EM91: Оборуд. КА | EQ91: 131088 | ER91: 0 | ES91: 15062.8 | ET91: 0 | EU91: 0 | EV91: 0 | EW91: 0 | EX91: 0 | EY91: 0 | FQ91: 0 | FR91: =P91 -> 15062.8 | FS91: 0 | FX91: 0 | FY91: 0 | GA91: [139 111 / 1,22 / 7,57] | GD91: 1 | GF91: -2051834592 | GG91: 2 | GH91: 4 | GI91: -2 | GJ91: 0 | GK91: 0 | GL91: =ROUND(IF(AND(BH91=3,BI91=3,FS91<>0),P91,0),2) -> 0 | GM91: =ROUND(O91+X91+Y91,2)+GX91 -> 15062.8 | GN91: =IF(OR(BI91=0,BI91=1),GM91-GX91,0) -> 0 | GO91: =IF(BI91=2,GM91-GX91,0) -> 0 | GP91: =IF(BI91=4,GM91-GX91,0) -> 0 | GR91: 1 | GS91: 2 | GT91: 0 | GV91: =ROUND((GT91),6) -> 0 | GW91: 1 | GX91: =ROUND(HC91*I91,2) -> 0 | HA91: 0 | HB91: 0 | HC91: =GV91*GW91 -> 0 | HE91: 0 | HF91: 0 | HS91: 0 | IK91: 0
A92: 17 | B92: 1 | E92: 15 | F92: КА, п.3 | G92: Блок коммутации абонентских линий AN-X8 MGN | H92: ШТ | I92: 1 | J92: 0 | K92: 1 | O92: =ROUND(CP92,2) -> 114025.4 | P92: =ROUND((ROUND((AC92*AW92*I92),2)*BC92),2) -> 114025.4 | Q92: =(ROUND((ROUND(((ET92)*AV92*I92),2)*BB92),2)+ROUND((ROUND(((AE92-(EU92))*AV92*I92),2)*BS92),2)) -> 0 | R92: =(ROUND((ROUND(((EU92)*AV92*I92),2)*BS92),2)+ROUND((ROUND(((AE92-(EU92))*AV92*I92),2)*BS92),2)) -> 0 | S92: =ROUND((ROUND((AF92*AV92*I92),2)*BA92),2) -> 0 | T92: =ROUND(CU92*I92,2) -> 0 | U92: =CV92*I92 -> 0 | V92: =CW92*I92 -> 0 | W92: =ROUND(CX92*I92,2) -> 0 | X92: =(ROUND((((S92+ROUND((ROUND(((EU92)*AV92*I92),2)*BS92),2))*AT92)/100),2)+ROUND(((ROUND((ROUND(((AE92-(EU92))*AV92*I92),2)*BS92),2)*AT92)/100),2)) -> 0 | Y92: =(ROUND((((S92+ROUND((ROUND(((EU92)*AV92*I92),2)*BS92),2))*AU92)/100),2)+ROUND(((ROUND((ROUND(((AE92-(EU92))*AV92*I92),2)*BS92),2)*AU92)/100),2)) -> 0 | AA92: 55943568 | AB92: =ROUND((AC92+AD92+AF92),6) -> 15062.8 | AC92: =ROUND((ES92),6) -> 15062.8 | AD92: =ROUND((((ET92)-(EU92))+AE92),6) -> 0 | AE92: =ROUND((EU92),6) -> 0 | AF92: =ROUND((EV92),6) -> 0 | AG92: =ROUND((AP92),6) -> 0 | AH92: =(EW92) -> 0 | AI92: =(EX92) -> 0 | AJ92: =(AS92) -> 0 | AK92: 15062.8 | AL92: 15062.8 | AM92: 0 | AN92: 0 | AO92: 0 | AP92: 0 | AQ92: 0 | AR92: 0 | AS92: 0 | AT92: 0 | AU92: 0 | AV92: 1 | AW92: 1 | AZ92: 1 | BA92: 1 | BB92: 1 | BC92: 7.57 | BH92: 3 | BI92: 3 | BJ92: КА, п.3 | BM92: 400007 | BN92: 0 | BP92: 0 | BQ92: 214 | BR92: 0 | BS92: 1 | BT92: 1 | BU92: 1 | BV92: 1 | BW92: 1 | BX92: 1 | BZ92: 0 | CA92: 0 | CE92: 1566 | CF92: 0 | CG92: 0 | CM92: 0 | CO92: 0 | CP92: =(P92+Q92+S92) -> 114025.4 | CQ92: =ROUND((ROUND((AC92*AW92*1),2)*BC92),2) -> 114025.4 | CR92: =(ROUND((ROUND(((ET92)*AV92*1),2)*BB92),2)+ROUND((ROUND(((AE92-(EU92))*AV92*1),2)*BS92),2)) -> 0 | CS92: =(ROUND((ROUND(((EU92)*AV92*1),2)*BS92),2)+ROUND((ROUND(((AE92-(EU92))*AV92*1),2)*BS92),2)) -> 0 | CT92: =ROUND((ROUND((AF92*AV92*1),2)*BA92),2) -> 0 | CU92: =AG92 -> 0 | CV92: =(AH92*AV92) -> 0 | CW92: =AI92 -> 0 | CX92: =AJ92 -> 0 | CY92: =(ROUND((((S92+ROUND((ROUND(((EU92)*AV92*1),2)*BS92),2))*AT92)/100),2)+ROUND(((ROUND((ROUND(((AE92-(EU92))*AV92*1),2)*BS92),2)*AT92)/100),2)) -> 0 | CZ92: =(ROUND((((S92+ROUND((ROUND(((EU92)*AV92*1),2)*BS92),2))*AU92)/100),2)+ROUND(((ROUND((ROUND(((AE92-(EU92))*AV92*1),2)*BS92),2)*AU92)/100),2)) -> 0 | DN92: 0 | DO92: 0 | DP92: 1 | DQ92: 1 | DU92: 1013 | DV92: ШТ | DW92: ШТ | DX92: 1 | EE92: 55393904 | EF92: 214 | EG92: Оборудование, отсутствующие в СНБ | EH92: 0 | EJ92: 3 | EK92: 400007 | EL92: Оборудование, отсутствующие в СНБ | EM92: Оборуд. КА | EQ92: 131088 | ER92: 0 | ES92: 15062.8 | ET92: 0 | EU92: 0 | EV92: 0 | EW92: 0 | EX92: 0 | EY92: 0 | EZ92: 5 | FC92: 1 | FD92: 18 | FF92: 139111 | FQ92: 0 | FR92: =P92 -> 114025.4 | FS92: 0 | FX92: 0 | FY92: 0 | GA92: [139 111 / 1,22 / 7,57] | GD92: 1 | GF92: -2051834592 | GG92: 2 | GH92: 3 | GI92: 3 | GJ92: 0 | GK92: 0 | GL92: =ROUND(IF(AND(BH92=3,BI92=3,FS92<>0),P92,0),2) -> 0 | GM92: =ROUND(O92+X92+Y92,2)+GX92 -> 114025.4 | GN92: =IF(OR(BI92=0,BI92=1),GM92-GX92,0) -> 0 | GO92: =IF(BI92=2,GM92-GX92,0) -> 0 | GP92: =IF(BI92=4,GM92-GX92,0) -> 0 | GR92: 1 | GS92: 1 | GT92: 0 | GV92: =ROUND((GT92),6) -> 0 | GW92: 1 | GX92: =ROUND(HC92*I92,2) -> 0 | HA92: 0 | HB92: 0 | HC92: =GV92*GW92 -> 0 | HE92: 0 | HF92: 0 | HS92: 0 | IK92: 0
A93: 17 | B93: 1 | E93: 16 | F93: 4.11-1-4 | G93: Монтаж конструкции для установки приборов и средств автоматизации массой до 5 кг | H93: 1ШТ. | I93: 2 | J93: 0 | K93: 2 | O93: =ROUND(CP93,2) -> 145.18 | P93: =ROUND((ROUND((AC93*AW93*I93),2)*BC93),2) -> 102.06 | Q93: =(ROUND((ROUND((((ET93*1.2))*AV93*I93),2)*BB93),2)+ROUND((ROUND(((AE93-((EU93*1.2)))*AV93*I93),2)*BS93),2)) -> 13.49 | R93: =(ROUND((ROUND((((EU93*1.2))*AV93*I93),2)*BS93),2)+ROUND((ROUND(((AE93-((EU93*1.2)))*AV93*I93),2)*BS93),2)) -> 3.09 | S93: =ROUND((ROUND((AF93*AV93*I93),2)*BA93),2) -> 29.63 | T93: =ROUND(CU93*I93,2) -> 0 | U93: =CV93*I93 -> 2.588184 | V93: =CW93*I93 -> 0 | W93: =ROUND(CX93*I93,2) -> 0 | X93: =(ROUND((((S93+ROUND((ROUND((((EU93*1.2))*AV93*I93),2)*BS93),2))*AT93)/100),2)+ROUND(((ROUND((ROUND(((AE93-((EU93*1.2)))*AV93*I93),2)*BS93),2)*AT93)/100),2)) -> 29.45 | Y93: =(ROUND((((S93+ROUND((ROUND((((EU93*1.2))*AV93*I93),2)*BS93),2))*AU93)/100),2)+ROUND(((ROUND((ROUND(((AE93-((EU93*1.2)))*AV93*I93),2)*BS93),2)*AU93)/100),2)) -> 15.05 | AA93: 55943566 | AB93: =ROUND((AC93+AD93+AF93),6) -> 71.622 | AC93: =ROUND(((ES93*1)),6) -> 51.03 | AD93: =ROUND(((((ET93*1.2))-((EU93*1.2)))+AE93),6) -> 6.444 | AE93: =ROUND(((EU93*1.2)),6) -> 1.476 | AF93: =ROUND(((EV93*1.2)),6) -> 14.148 | AG93: =ROUND((AP93),6) -> 0 | AH93: =((EW93*1.2)) -> 1.236 | AI93: =((EX93*1.2)) -> 0 | AJ93: =(AS93) -> 0 | AK93: 68.19 | AL93: 51.03 | AM93: 5.37 | AN93: 1.23 | AO93: 11.79 | AP93: 0 | AQ93: 1.03 | AR93: 0 | AS93: 0 | AT93: 90 | AU93: 46 | AV93: 1.047 | AW93: 1 | AZ93: 1 | BA93: 1 | BB93: 1 | BC93: 1 | BH93: 0 | BI93: 2 | BJ93: ТСН-2001.4 Доп. 79, Сб. 11, т. 1, поз. 4 | BM93: 72 | BN93: 0 | BO93: 4.11-1-4 | BP93: 1 | BQ93: 40 | BR93: 0 | BS93: 1 | BT93: 1 | BU93: 1 | BV93: 1 | BW93: 1 | BX93: 1 | BZ93: 90 | CA93: 46 | CE93: 1566 | CF93: 0 | CG93: 0 | CM93: 0 | CN93: Поправка: Гл.12.Прил.8.п.8. 3_12.00.01.11.001 Наименование: При наличии напряженных и стесненных условий производства работ (стесненность, сложность складирования и транспортной логистики и т.п.) для объектов, расположенных в пределах круговой магистральной системы улиц "Садовое кольцо" города Москвы | CO93: 0 | CP93: =(P93+Q93+S93) -> 145.18 | CQ93: =ROUND((ROUND((AC93*AW93*1),2)*BC93),2) -> 51.03 | CR93: =(ROUND((ROUND((((ET93*1.2))*AV93*1),2)*BB93),2)+ROUND((ROUND(((AE93-((EU93*1.2)))*AV93*1),2)*BS93),2)) -> 6.75 | CS93: =(ROUND((ROUND((((EU93*1.2))*AV93*1),2)*BS93),2)+ROUND((ROUND(((AE93-((EU93*1.2)))*AV93*1),2)*BS93),2)) -> 1.55 | CT93: =ROUND((ROUND((AF93*AV93*1),2)*BA93),2) -> 14.81 | CU93: =AG93 -> 0 | CV93: =(AH93*AV93) -> 1.294092 | CW93: =AI93 -> 0 | CX93: =AJ93 -> 0 | CY93: =(ROUND((((S93+ROUND((ROUND((((EU93*1.2))*AV93*1),2)*BS93),2))*AT93)/100),2)+ROUND(((ROUND((ROUND(((AE93-((EU93*1.2)))*AV93*1),2)*BS93),2)*AT93)/100),2)) -> 28.06 | CZ93: =(ROUND((((S93+ROUND((ROUND((((EU93*1.2))*AV93*1),2)*BS93),2))*AU93)/100),2)+ROUND(((ROUND((ROUND(((AE93-((EU93*1.2)))*AV93*1),2)*BS93),2)*AU93)/100),2)) -> 14.34 | DB93: 41 | DD93: *1 | DE93: *1,2 | DF93: *1,2 | DG93: *1,2 | DI93: *1,2 | DJ93: *1,2 | DN93: 0 | DO93: 0 | DP93: 1 | DQ93: 1 | DU93: 1013 | DV93: 1ШТ. | DW93: 1 ШТ. | DX93: 1 | EE93: 55393976 | EF93: 40 | EG93: Монтаж оборудования | EH93: 0 | EJ93: 2 | EK93: 72 | EL93: ТСН-2001.4-11. Приборы и средства автоматизации и вычислительной техники | EM93: ТСН-2001.4-11-1 | EO93: Поправка: Гл.12.Прил.8.п.8. 3_12.00.01.11.001 | EQ93: 131072 | ER93: 68.19 | ES93: 51.03 | ET93: 5.37 | EU93: 1.23 | EV93: 11.79 | EW93: 1.03 | EX93: 0 | EY93: 0 | FQ93: 0 | FR93: 0 | FS93: 0 | FX93: 90 | FY93: 46 | GD93: 1 | GF93: -1093617697 | GG93: 2 | GH93: 1 | GI93: 2 | GJ93: 0 | GK93: 0 | GL93: =ROUND(IF(AND(BH93=3,BI93=3,FS93<>0),P93,0),2) -> 0 | GM93: =ROUND(O93+X93+Y93,2)+GX93 -> 189.68 | GN93: =IF(OR(BI93=0,BI93=1),GM93-GX93,0) -> 0 | GO93: =IF(BI93=2,GM93-GX93,0) -> 189.68 | GP93: =IF(BI93=4,GM93-GX93,0) -> 0 | GR93: 0 | GS93: 3 | GT93: 0 | GV93: =ROUND((GT93),6) -> 0 | GW93: 1 | GX93: =ROUND(HC93*I93,2) -> 0 | HA93: 0 | HB93: 0 | HC93: =GV93*GW93 -> 0 | HS93: 0 | IK93: 0
A94: 17 | B94: 1 | E94: 16 | F94: 4.11-1-4 | G94: Монтаж конструкции для установки приборов и средств автоматизации массой до 5 кг | H94: 1ШТ. | I94: 2 | J94: 0 | K94: 2 | O94: =ROUND(CP94,2) -> 2888.37 | P94: =ROUND((ROUND((AC94*AW94*I94),2)*BC94),2) -> 913.44 | Q94: =(ROUND((ROUND((((ET94*1.2))*AV94*I94),2)*BB94),2)+ROUND((ROUND(((AE94-((EU94*1.2)))*AV94*I94),2)*BS94),2)) -> 305.28 | R94: =(ROUND((ROUND((((EU94*1.2))*AV94*I94),2)*BS94),2)+ROUND((ROUND(((AE94-((EU94*1.2)))*AV94*I94),2)*BS94),2)) -> 174.12 | S94: =ROUND((ROUND((AF94*AV94*I94),2)*BA94),2) -> 1669.65 | T94: =ROUND(CU94*I94,2) -> 0 | U94: =CV94*I94 -> 2.588184 | V94: =CW94*I94 -> 0 | W94: =ROUND(CX94*I94,2) -> 0 | X94: =(ROUND((((S94+ROUND((ROUND((((EU94*1.2))*AV94*I94),2)*BS94),2))*AT94)/100),2)+ROUND(((ROUND((ROUND(((AE94-((EU94*1.2)))*AV94*I94),2)*BS94),2)*AT94)/100),2)) -> 1659.39 | Y94: =(ROUND((((S94+ROUND((ROUND((((EU94*1.2))*AV94*I94),2)*BS94),2))*AU94)/100),2)+ROUND(((ROUND((ROUND(((AE94-((EU94*1.2)))*AV94*I94),2)*BS94),2)*AU94)/100),2)) -> 848.13 | AA94: 55943568 | AB94: =ROUND((AC94+AD94+AF94),6) -> 71.622 | AC94: =ROUND(((ES94*1)),6) -> 51.03 | AD94: =ROUND(((((ET94*1.2))-((EU94*1.2)))+AE94),6) -> 6.444 | AE94: =ROUND(((EU94*1.2)),6) -> 1.476 | AF94: =ROUND(((EV94*1.2)),6) -> 14.148 | AG94: =ROUND((AP94),6) -> 0 | AH94: =((EW94*1.2)) -> 1.236 | AI94: =((EX94*1.2)) -> 0 | AJ94: =(AS94) -> 0 | AK94: 68.19 | AL94: 51.03 | AM94: 5.37 | AN94: 1.23 | AO94: 11.79 | AP94: 0 | AQ94: 1.03 | AR94: 0 | AS94: 0 | AT94: 90 | AU94: 46 | AV94: 1.047 | AW94: 1 | AZ94: 1 | BA94: 56.35 | BB94: 22.63 | BC94: 8.95 | BH94: 0 | BI94: 2 | BJ94: ТСН-2001.4 Доп. 79, Сб. 11, т. 1, поз. 4 | BM94: 72 | BN94: 0 | BO94: 4.11-1-4 | BP94: 1 | BQ94: 40 | BR94: 0 | BS94: 56.35 | BT94: 1 | BU94: 1 | BV94: 1 | BW94: 1 | BX94: 1 | BZ94: 90 | CA94: 46 | CE94: 1566 | CF94: 0 | CG94: 0 | CM94: 0 | CN94: Поправка: Гл.12.Прил.8.п.8. 3_12.00.01.11.001 Наименование: При наличии напряженных и стесненных условий производства работ (стесненность, сложность складирования и транспортной логистики и т.п.) для объектов, расположенных в пределах круговой магистральной системы улиц "Садовое кольцо" города Москвы | CO94: 0 | CP94: =(P94+Q94+S94) -> 2888.37 | CQ94: =ROUND((ROUND((AC94*AW94*1),2)*BC94),2) -> 456.72 | CR94: =(ROUND((ROUND((((ET94*1.2))*AV94*1),2)*BB94),2)+ROUND((ROUND(((AE94-((EU94*1.2)))*AV94*1),2)*BS94),2)) -> 152.75 | CS94: =(ROUND((ROUND((((EU94*1.2))*AV94*1),2)*BS94),2)+ROUND((ROUND(((AE94-((EU94*1.2)))*AV94*1),2)*BS94),2)) -> 87.34 | CT94: =ROUND((ROUND((AF94*AV94*1),2)*BA94),2) -> 834.54 | CU94: =AG94 -> 0 | CV94: =(AH94*AV94) -> 1.294092 | CW94: =AI94 -> 0 | CX94: =AJ94 -> 0 | CY94: =(ROUND((((S94+ROUND((ROUND((((EU94*1.2))*AV94*1),2)*BS94),2))*AT94)/100),2)+ROUND(((ROUND((ROUND(((AE94-((EU94*1.2)))*AV94*1),2)*BS94),2)*AT94)/100),2)) -> 1581.29 | CZ94: =(ROUND((((S94+ROUND((ROUND((((EU94*1.2))*AV94*1),2)*BS94),2))*AU94)/100),2)+ROUND(((ROUND((ROUND(((AE94-((EU94*1.2)))*AV94*1),2)*BS94),2)*AU94)/100),2)) -> 808.22 | DB94: 42 | DD94: *1 | DE94: *1,2 | DF94: *1,2 | DG94: *1,2 | DI94: *1,2 | DJ94: *1,2 | DN94: 0 | DO94: 0 | DP94: 1 | DQ94: 1 | DU94: 1013 | DV94: 1ШТ. | DW94: 1 ШТ. | DX94: 1 | EE94: 55393976 | EF94: 40 | EG94: Монтаж оборудования | EH94: 0 | EJ94: 2 | EK94: 72 | EL94: ТСН-2001.4-11. Приборы и средства автоматизации и вычислительной техники | EM94: ТСН-2001.4-11-1 | EO94: Поправка: Гл.12.Прил.8.п.8. 3_12.00.01.11.001 | EQ94: 131072 | ER94: 68.19 | ES94: 51.03 | ET94: 5.37 | EU94: 1.23 | EV94: 11.79 | EW94: 1.03 | EX94: 0 | EY94: 0 | FQ94: 0 | FR94: 0 | FS94: 0 | FX94: 90 | FY94: 46 | GD94: 1 | GF94: -1093617697 | GG94: 2 | GH94: 1 | GI94: 2 | GJ94: 0 | GK94: 0 | GL94: =ROUND(IF(AND(BH94=3,BI94=3,FS94<>0),P94,0),2) -> 0 | GM94: =ROUND(O94+X94+Y94,2)+GX94 -> 5395.89 | GN94: =IF(OR(BI94=0,BI94=1),GM94-GX94,0) -> 0 | GO94: =IF(BI94=2,GM94-GX94,0) -> 5395.89 | GP94: =IF(BI94=4,GM94-GX94,0) -> 0 | GR94: 0 | GS94: 3 | GT94: 0 | GV94: =ROUND((GT94),6) -> 0 | GW94: 1 | GX94: =ROUND(HC94*I94,2) -> 0 | HA94: 0 | HB94: 0 | HC94: =GV94*GW94 -> 0 | HS94: 0 | IK94: 0
A95: 18 | B95: 1 | E95: 16,1 | F95: 1.1-1-57 | G95: Болты строительные с гайками и шайбами, черные, М10х100 мм | H95: т | I95: =I93*J95 -> 2e-05 | J95: 1e-05 | K95: 1e-05 | O95: =ROUND(CP95,2) -> 0.36 | P95: =ROUND((ROUND((AC95*AW95*I95),2)*BC95),2) -> 0.36 | Q95: =(ROUND((ROUND(((ET95)*AV95*I95),2)*BB95),2)+ROUND((ROUND(((AE95-(EU95))*AV95*I95),2)*BS95),2)) -> 0 | R95: =(ROUND((ROUND(((EU95)*AV95*I95),2)*BS95),2)+ROUND((ROUND(((AE95-(EU95))*AV95*I95),2)*BS95),2)) -> 0 | S95: =ROUND((ROUND((AF95*AV95*I95),2)*BA95),2) -> 0 | T95: =ROUND(CU95*I95,2) -> 0 | U95: =CV95*I95 -> 0 | V95: =CW95*I95 -> 0 | W95: =ROUND(CX95*I95,2) -> 0 | X95: =(ROUND((((S95+ROUND((ROUND(((EU95)*AV95*I95),2)*BS95),2))*AT95)/100),2)+ROUND(((ROUND((ROUND(((AE95-(EU95))*AV95*I95),2)*BS95),2)*AT95)/100),2)) -> 0 | Y95: =(ROUND((((S95+ROUND((ROUND(((EU95)*AV95*I95),2)*BS95),2))*AU95)/100),2)+ROUND(((ROUND((ROUND(((AE95-(EU95))*AV95*I95),2)*BS95),2)*AU95)/100),2)) -> 0 | AA95: 55943566 | AB95: =ROUND((AC95+AD95+AF95),6) -> 17868.28 | AC95: =ROUND((ES95),6) -> 17868.28 | AD95: =ROUND((((ET95)-(EU95))+AE95),6) -> 0 | AE95: =ROUND((EU95),6) -> 0 | AF95: =ROUND((EV95),6) -> 0 | AG95: =ROUND((AP95),6) -> 0 | AH95: =(EW95) -> 0 | AI95: =(EX95) -> 0 | AJ95: =(AS95) -> 0 | AK95: 17868.28 | AL95: 17868.28 | AM95: 0 | AN95: 0 | AO95: 0 | AP95: 0 | AQ95: 0 | AR95: 0 | AS95: 0 | AT95: 90 | AU95: 46 | AV95: 1 | AW95: 1 | AZ95: 1 | BA95: 1 | BB95: 1 | BC95: 1 | BH95: 3 | BI95: 2 | BJ95: ТСН-2001.1 Доп. 79, Р. 1, о. 1, поз. 57 | BM95: 72 | BN95: 0 | BP95: 0 | BQ95: 40 | BR95: 0 | BS95: 1 | BT95: 1 | BU95: 1 | BV95: 1 | BW95: 1 | BX95: 1 | BZ95: 90 | CA95: 46 | CE95: 1566 | CF95: 0 | CG95: 0 | CM95: 0 | CO95: 0 | CP95: =(P95+Q95+S95) -> 0.36 | CQ95: =ROUND((ROUND((AC95*AW95*1),2)*BC95),2) -> 17868.28 | CR95: =(ROUND((ROUND(((ET95)*AV95*1),2)*BB95),2)+ROUND((ROUND(((AE95-(EU95))*AV95*1),2)*BS95),2)) -> 0 | CS95: =(ROUND((ROUND(((EU95)*AV95*1),2)*BS95),2)+ROUND((ROUND(((AE95-(EU95))*AV95*1),2)*BS95),2)) -> 0 | CT95: =ROUND((ROUND((AF95*AV95*1),2)*BA95),2) -> 0 | CU95: =AG95 -> 0 | CV95: =(AH95*AV95) -> 0 | CW95: =AI95 -> 0 | CX95: =AJ95 -> 0 | CY95: =(ROUND((((S95+ROUND((ROUND(((EU95)*AV95*1),2)*BS95),2))*AT95)/100),2)+ROUND(((ROUND((ROUND(((AE95-(EU95))*AV95*1),2)*BS95),2)*AT95)/100),2)) -> 0 | CZ95: =(ROUND((((S95+ROUND((ROUND(((EU95)*AV95*1),2)*BS95),2))*AU95)/100),2)+ROUND(((ROUND((ROUND(((AE95-(EU95))*AV95*1),2)*BS95),2)*AU95)/100),2)) -> 0 | DN95: 0 | DO95: 0 | DP95: 1 | DQ95: 1 | DU95: 1009 | DV95: т | DW95: т | DX95: 1000 | EE95: 55393976 | EF95: 40 | EG95: Монтаж оборудования | EH95: 0 | EJ95: 2 | EK95: 72 | EL95: ТСН-2001.4-11. Приборы и средства автоматизации и вычислительной техники | EM95: ТСН-2001.4-11-1 | EQ95: 0 | ER95: 17868.28 | ES95: 17868.28 | ET95: 0 | EU95: 0 | EV95: 0 | EW95: 0 | EX95: 0 | FQ95: 0 | FR95: 0 | FS95: 0 | FX95: 90 | FY95: 46 | GD95: 1 | GF95: -1123198217 | GG95: 2 | GH95: 1 | GI95: -2 | GJ95: 0 | GK95: 0 | GL95: =ROUND(IF(AND(BH95=3,BI95=3,FS95<>0),P95,0),2) -> 0 | GM95: =ROUND(O95+X95+Y95,2)+GX95 -> 0.36 | GN95: =IF(OR(BI95=0,BI95=1),GM95-GX95,0) -> 0 | GO95: =IF(BI95=2,GM95-GX95,0) -> 0.36 | GP95: =IF(BI95=4,GM95-GX95,0) -> 0 | GR95: 0 | GS95: 3 | GT95: 0 | GV95: =ROUND((GT95),6) -> 0 | GW95: 1 | GX95: =ROUND(HC95*I95,2) -> 0 | HA95: 0 | HB95: 0 | HC95: =GV95*GW95 -> 0 | HS95: 0 | IK95: 0
A96: 18 | B96: 1 | E96: 16,1 | F96: 1.1-1-57 | G96: Болты строительные с гайками и шайбами, черные, М10х100 мм | H96: т | I96: =I94*J96 -> 2e-05 | J96: 1e-05 | K96: 1e-05 | O96: =ROUND(CP96,2) -> 2.45 | P96: =ROUND((ROUND((AC96*AW96*I96),2)*BC96),2) -> 2.45 | Q96: =(ROUND((ROUND(((ET96)*AV96*I96),2)*BB96),2)+ROUND((ROUND(((AE96-(EU96))*AV96*I96),2)*BS96),2)) -> 0 | R96: =(ROUND((ROUND(((EU96)*AV96*I96),2)*BS96),2)+ROUND((ROUND(((AE96-(EU96))*AV96*I96),2)*BS96),2)) -> 0 | S96: =ROUND((ROUND((AF96*AV96*I96),2)*BA96),2) -> 0 | T96: =ROUND(CU96*I96,2) -> 0 | U96: =CV96*I96 -> 0 | V96: =CW96*I96 -> 0 | W96: =ROUND(CX96*I96,2) -> 0 | X96: =(ROUND((((S96+ROUND((ROUND(((EU96)*AV96*I96),2)*BS96),2))*AT96)/100),2)+ROUND(((ROUND((ROUND(((AE96-(EU96))*AV96*I96),2)*BS96),2)*AT96)/100),2)) -> 0 | Y96: =(ROUND((((S96+ROUND((ROUND(((EU96)*AV96*I96),2)*BS96),2))*AU96)/100),2)+ROUND(((ROUND((ROUND(((AE96-(EU96))*AV96*I96),2)*BS96),2)*AU96)/100),2)) -> 0 | AA96: 55943568 | AB96: =ROUND((AC96+AD96+AF96),6) -> 17868.28 | AC96: =ROUND((ES96),6) -> 17868.28 | AD96: =ROUND((((ET96)-(EU96))+AE96),6) -> 0 | AE96: =ROUND((EU96),6) -> 0 | AF96: =ROUND((EV96),6) -> 0 | AG96: =ROUND((AP96),6) -> 0 | AH96: =(EW96) -> 0 | AI96: =(EX96) -> 0 | AJ96: =(AS96) -> 0 | AK96: 17868.28 | AL96: 17868.28 | AM96: 0 | AN96: 0 | AO96: 0 | AP96: 0 | AQ96: 0 | AR96: 0 | AS96: 0 | AT96: 90 | AU96: 46 | AV96: 1 | AW96: 1 | AZ96: 1 | BA96: 1 | BB96: 1 | BC96: 6.81 | BH96: 3 | BI96: 2 | BJ96: ТСН-2001.1 Доп. 79, Р. 1, о. 1, поз. 57 | BM96: 72 | BN96: 0 | BO96: 1.1-1-57 | BP96: 1 | BQ96: 40 | BR96: 0 | BS96: 1 | BT96: 1 | BU96: 1 | BV96: 1 | BW96: 1 | BX96: 1 | BZ96: 90 | CA96: 46 | CE96: 1566 | CF96: 0 | CG96: 0 | CM96: 0 | CO96: 0 | CP96: =(P96+Q96+S96) -> 2.45 | CQ96: =ROUND((ROUND((AC96*AW96*1),2)*BC96),2) -> 121682.99 | CR96: =(ROUND((ROUND(((ET96)*AV96*1),2)*BB96),2)+ROUND((ROUND(((AE96-(EU96))*AV96*1),2)*BS96),2)) -> 0 | CS96: =(ROUND((ROUND(((EU96)*AV96*1),2)*BS96),2)+ROUND((ROUND(((AE96-(EU96))*AV96*1),2)*BS96),2)) -> 0 | CT96: =ROUND((ROUND((AF96*AV96*1),2)*BA96),2) -> 0 | CU96: =AG96 -> 0 | CV96: =(AH96*AV96) -> 0 | CW96: =AI96 -> 0 | CX96: =AJ96 -> 0 | CY96: =(ROUND((((S96+ROUND((ROUND(((EU96)*AV96*1),2)*BS96),2))*AT96)/100),2)+ROUND(((ROUND((ROUND(((AE96-(EU96))*AV96*1),2)*BS96),2)*AT96)/100),2)) -> 0 | CZ96: =(ROUND((((S96+ROUND((ROUND(((EU96)*AV96*1),2)*BS96),2))*AU96)/100),2)+ROUND(((ROUND((ROUND(((AE96-(EU96))*AV96*1),2)*BS96),2)*AU96)/100),2)) -> 0 | DN96: 0 | DO96: 0 | DP96: 1 | DQ96: 1 | DU96: 1009 | DV96: т | DW96: т | DX96: 1000 | EE96: 55393976 | EF96: 40 | EG96: Монтаж оборудования | EH96: 0 | EJ96: 2 | EK96: 72 | EL96: ТСН-2001.4-11. Приборы и средства автоматизации и вычислительной техники | EM96: ТСН-2001.4-11-1 | EQ96: 0 | ER96: 17868.28 | ES96: 17868.28 | ET96: 0 | EU96: 0 | EV96: 0 | EW96: 0 | EX96: 0 | FQ96: 0 | FR96: 0 | FS96: 0 | FX96: 90 | FY96: 46 | GD96: 1 | GF96: -1123198217 | GG96: 2 | GH96: 1 | GI96: 2 | GJ96: 0 | GK96: 0 | GL96: =ROUND(IF(AND(BH96=3,BI96=3,FS96<>0),P96,0),2) -> 0 | GM96: =ROUND(O96+X96+Y96,2)+GX96 -> 2.45 | GN96: =IF(OR(BI96=0,BI96=1),GM96-GX96,0) -> 0 | GO96: =IF(BI96=2,GM96-GX96,0) -> 2.45 | GP96: =IF(BI96=4,GM96-GX96,0) -> 0 | GR96: 0 | GS96: 3 | GT96: 0 | GV96: =ROUND((GT96),6) -> 0 | GW96: 1 | GX96: =ROUND(HC96*I96,2) -> 0 | HA96: 0 | HB96: 0 | HC96: =GV96*GW96 -> 0 | HS96: 0 | IK96: 0
A97: 17 | B97: 1 | E97: 17 | F97: КА, п.10 | G97: Стойка для считывателя Stolz (Штольц) 150х150 мм | H97: ШТ | I97: 2 | J97: 0 | K97: 2 | O97: =ROUND(CP97,2) -> 925.94 | P97: =ROUND((ROUND((AC97*AW97*I97),2)*BC97),2) -> 925.94 | Q97: =(ROUND((ROUND(((ET97)*AV97*I97),2)*BB97),2)+ROUND((ROUND(((AE97-(EU97))*AV97*I97),2)*BS97),2)) -> 0 | R97: =(ROUND((ROUND(((EU97)*AV97*I97),2)*BS97),2)+ROUND((ROUND(((AE97-(EU97))*AV97*I97),2)*BS97),2)) -> 0 | S97: =ROUND((ROUND((AF97*AV97*I97),2)*BA97),2) -> 0 | T97: =ROUND(CU97*I97,2) -> 0 | U97: =CV97*I97 -> 0 | V97: =CW97*I97 -> 0 | W97: =ROUND(CX97*I97,2) -> 0 | X97: =(ROUND((((S97+ROUND((ROUND(((EU97)*AV97*I97),2)*BS97),2))*AT97)/100),2)+ROUND(((ROUND((ROUND(((AE97-(EU97))*AV97*I97),2)*BS97),2)*AT97)/100),2)) -> 0 | Y97: =(ROUND((((S97+ROUND((ROUND(((EU97)*AV97*I97),2)*BS97),2))*AU97)/100),2)+ROUND(((ROUND((ROUND(((AE97-(EU97))*AV97*I97),2)*BS97),2)*AU97)/100),2)) -> 0 | AA97: 55943566 | AB97: =ROUND((AC97+AD97+AF97),6) -> 462.97 | AC97: =ROUND((ES97),6) -> 462.97 | AD97: =ROUND((((ET97)-(EU97))+AE97),6) -> 0 | AE97: =ROUND((EU97),6) -> 0 | AF97: =ROUND((EV97),6) -> 0 | AG97: =ROUND((AP97),6) -> 0 | AH97: =(EW97) -> 0 | AI97: =(EX97) -> 0 | AJ97: =(AS97) -> 0 | AK97: 462.97 | AL97: 462.97 | AM97: 0 | AN97: 0 | AO97: 0 | AP97: 0 | AQ97: 0 | AR97: 0 | AS97: 0 | AT97: 0 | AU97: 0 | AV97: 1 | AW97: 1 | AZ97: 1 | BA97: 1 | BB97: 1 | BC97: 1 | BH97: 3 | BI97: 1 | BJ97: КА, п.10 | BM97: 400005 | BN97: 0 | BP97: 0 | BQ97: 213 | BR97: 0 | BS97: 1 | BT97: 1 | BU97: 1 | BV97: 1 | BW97: 1 | BX97: 1 | BZ97: 0 | CA97: 0 | CE97: 1566 | CF97: 0 | CG97: 0 | CM97: 0 | CO97: 0 | CP97: =(P97+Q97+S97) -> 925.94 | CQ97: =ROUND((ROUND((AC97*AW97*1),2)*BC97),2) -> 462.97 | CR97: =(ROUND((ROUND(((ET97)*AV97*1),2)*BB97),2)+ROUND((ROUND(((AE97-(EU97))*AV97*1),2)*BS97),2)) -> 0 | CS97: =(ROUND((ROUND(((EU97)*AV97*1),2)*BS97),2)+ROUND((ROUND(((AE97-(EU97))*AV97*1),2)*BS97),2)) -> 0 | CT97: =ROUND((ROUND((AF97*AV97*1),2)*BA97),2) -> 0 | CU97: =AG97 -> 0 | CV97: =(AH97*AV97) -> 0 | CW97: =AI97 -> 0 | CX97: =AJ97 -> 0 | CY97: =(ROUND((((S97+ROUND((ROUND(((EU97)*AV97*1),2)*BS97),2))*AT97)/100),2)+ROUND(((ROUND((ROUND(((AE97-(EU97))*AV97*1),2)*BS97),2)*AT97)/100),2)) -> 0 | CZ97: =(ROUND((((S97+ROUND((ROUND(((EU97)*AV97*1),2)*BS97),2))*AU97)/100),2)+ROUND(((ROUND((ROUND(((AE97-(EU97))*AV97*1),2)*BS97),2)*AU97)/100),2)) -> 0 | DN97: 0 | DO97: 0 | DP97: 1 | DQ97: 1 | DU97: 1013 | DV97: ШТ | DW97: ШТ | DX97: 1 | EE97: 55393902 | EF97: 213 | EG97: Материалы, отсутствующие в СНБ (Строительные) | EH97: 0 | EJ97: 1 | EK97: 400005 | EL97: Материалы, отсутствующие в СНБ (Строительные) | EM97: МР КА Строительные | EQ97: 131088 | ER97: 0 | ES97: 462.97 | ET97: 0 | EU97: 0 | EV97: 0 | EW97: 0 | EX97: 0 | EY97: 0 | FQ97: 0 | FR97: 0 | FS97: 0 | FX97: 0 | FY97: 0 | GA97: [5 448,84 / 1,22 / 9,84] + 2% Заг.скл | GD97: 1 | GF97: 335141282 | GG97: 2 | GH97: 4 | GI97: -2 | GJ97: 0 | GK97: 0 | GL97: =ROUND(IF(AND(BH97=3,BI97=3,FS97<>0),P97,0),2) -> 0 | GM97: =ROUND(O97+X97+Y97,2)+GX97 -> 925.94 | GN97: =IF(OR(BI97=0,BI97=1),GM97-GX97,0) -> 925.94 | GO97: =IF(BI97=2,GM97-GX97,0) -> 0 | GP97: =IF(BI97=4,GM97-GX97,0) -> 0 | GR97: 0 | GS97: 2 | GT97: 0 | GV97: =ROUND((GT97),6) -> 0 | GW97: 1 | GX97: =ROUND(HC97*I97,2) -> 0 | HA97: 0 | HB97: 0 | HC97: =GV97*GW97 -> 0 | HE97: 0 | HF97: 2 | HS97: 0 | IK97: 0
A98: 17 | B98: 1 | E98: 17 | F98: КА, п.10 | G98: Стойка для считывателя Stolz (Штольц) 150х150 мм | H98: ШТ | I98: 2 | J98: 0 | K98: 2 | O98: =ROUND(CP98,2) -> 9111.25 | P98: =ROUND((ROUND((AC98*AW98*I98),2)*BC98),2) -> 9111.25 | Q98: =(ROUND((ROUND(((ET98)*AV98*I98),2)*BB98),2)+ROUND((ROUND(((AE98-(EU98))*AV98*I98),2)*BS98),2)) -> 0 | R98: =(ROUND((ROUND(((EU98)*AV98*I98),2)*BS98),2)+ROUND((ROUND(((AE98-(EU98))*AV98*I98),2)*BS98),2)) -> 0 | S98: =ROUND((ROUND((AF98*AV98*I98),2)*BA98),2) -> 0 | T98: =ROUND(CU98*I98,2) -> 0 | U98: =CV98*I98 -> 0 | V98: =CW98*I98 -> 0 | W98: =ROUND(CX98*I98,2) -> 0 | X98: =(ROUND((((S98+ROUND((ROUND(((EU98)*AV98*I98),2)*BS98),2))*AT98)/100),2)+ROUND(((ROUND((ROUND(((AE98-(EU98))*AV98*I98),2)*BS98),2)*AT98)/100),2)) -> 0 | Y98: =(ROUND((((S98+ROUND((ROUND(((EU98)*AV98*I98),2)*BS98),2))*AU98)/100),2)+ROUND(((ROUND((ROUND(((AE98-(EU98))*AV98*I98),2)*BS98),2)*AU98)/100),2)) -> 0 | AA98: 55943568 | AB98: =ROUND((AC98+AD98+AF98),6) -> 462.97 | AC98: =ROUND((ES98),6) -> 462.97 | AD98: =ROUND((((ET98)-(EU98))+AE98),6) -> 0 | AE98: =ROUND((EU98),6) -> 0 | AF98: =ROUND((EV98),6) -> 0 | AG98: =ROUND((AP98),6) -> 0 | AH98: =(EW98) -> 0 | AI98: =(EX98) -> 0 | AJ98: =(AS98) -> 0 | AK98: 462.97 | AL98: 462.97 | AM98: 0 | AN98: 0 | AO98: 0 | AP98: 0 | AQ98: 0 | AR98: 0 | AS98: 0 | AT98: 0 | AU98: 0 | AV98: 1 | AW98: 1 | AZ98: 1 | BA98: 1 | BB98: 1 | BC98: 9.84 | BH98: 3 | BI98: 1 | BJ98: КА, п.10 | BM98: 400005 | BN98: 0 | BP98: 0 | BQ98: 213 | BR98: 0 | BS98: 1 | BT98: 1 | BU98: 1 | BV98: 1 | BW98: 1 | BX98: 1 | BZ98: 0 | CA98: 0 | CE98: 1566 | CF98: 0 | CG98: 0 | CM98: 0 | CO98: 0 | CP98: =(P98+Q98+S98) -> 9111.25 | CQ98: =ROUND((ROUND((AC98*AW98*1),2)*BC98),2) -> 4555.62 | CR98: =(ROUND((ROUND(((ET98)*AV98*1),2)*BB98),2)+ROUND((ROUND(((AE98-(EU98))*AV98*1),2)*BS98),2)) -> 0 | CS98: =(ROUND((ROUND(((EU98)*AV98*1),2)*BS98),2)+ROUND((ROUND(((AE98-(EU98))*AV98*1),2)*BS98),2)) -> 0 | CT98: =ROUND((ROUND((AF98*AV98*1),2)*BA98),2) -> 0 | CU98: =AG98 -> 0 | CV98: =(AH98*AV98) -> 0 | CW98: =AI98 -> 0 | CX98: =AJ98 -> 0 | CY98: =(ROUND((((S98+ROUND((ROUND(((EU98)*AV98*1),2)*BS98),2))*AT98)/100),2)+ROUND(((ROUND((ROUND(((AE98-(EU98))*AV98*1),2)*BS98),2)*AT98)/100),2)) -> 0 | CZ98: =(ROUND((((S98+ROUND((ROUND(((EU98)*AV98*1),2)*BS98),2))*AU98)/100),2)+ROUND(((ROUND((ROUND(((AE98-(EU98))*AV98*1),2)*BS98),2)*AU98)/100),2)) -> 0 | DN98: 0 | DO98: 0 | DP98: 1 | DQ98: 1 | DU98: 1013 | DV98: ШТ | DW98: ШТ | DX98: 1 | EE98: 55393902 | EF98: 213 | EG98: Материалы, отсутствующие в СНБ (Строительные) | EH98: 0 | EJ98: 1 | EK98: 400005 | EL98: Материалы, отсутствующие в СНБ (Строительные) | EM98: МР КА Строительные | EQ98: 131088 | ER98: 462.03 | ES98: 462.97 | ET98: 0 | EU98: 0 | EV98: 0 | EW98: 0 | EX98: 0 | EY98: 0 | EZ98: 5 | FC98: 1 | FD98: 18 | FF98: 5448.84 | FQ98: 0 | FR98: 0 | FS98: 0 | FX98: 0 | FY98: 0 | GA98: [5 448,84 / 1,22 / 9,84] + 2% Заг.скл | GD98: 1 | GF98: 335141282 | GG98: 2 | GH98: 3 | GI98: 3 | GJ98: 0 | GK98: 0 | GL98: =ROUND(IF(AND(BH98=3,BI98=3,FS98<>0),P98,0),2) -> 0 | GM98: =ROUND(O98+X98+Y98,2)+GX98 -> 9111.25 | GN98: =IF(OR(BI98=0,BI98=1),GM98-GX98,0) -> 9111.25 | GO98: =IF(BI98=2,GM98-GX98,0) -> 0 | GP98: =IF(BI98=4,GM98-GX98,0) -> 0 | GR98: 1 | GS98: 1 | GT98: 0 | GV98: =ROUND((GT98),6) -> 0 | GW98: 1 | GX98: =ROUND(HC98*I98,2) -> 0 | HA98: 0 | HB98: 0 | HC98: =GV98*GW98 -> 0 | HE98: 0 | HF98: 2 | HS98: 0 | IK98: 0
A99: 17 | B99: 1 | E99: 18 | F99: 4.10-76-10 | G99: Монтаж ключа или кнопки на панели | H99: 1ШТ. | I99: 2 | J99: 0 | K99: 2 | O99: =ROUND(CP99,2) -> 33.22 | P99: =ROUND((ROUND((AC99*AW99*I99),2)*BC99),2) -> 3.34 | Q99: =(ROUND((ROUND((((ET99*1.2))*AV99*I99),2)*BB99),2)+ROUND((ROUND(((AE99-((EU99*1.2)))*AV99*I99),2)*BS99),2)) -> 0 | R99: =(ROUND((ROUND((((EU99*1.2))*AV99*I99),2)*BS99),2)+ROUND((ROUND(((AE99-((EU99*1.2)))*AV99*I99),2)*BS99),2)) -> 0 | S99: =ROUND((ROUND((AF99*AV99*I99),2)*BA99),2) -> 29.88 | T99: =ROUND(CU99*I99,2) -> 0 | U99: =CV99*I99 -> 2.5128 | V99: =CW99*I99 -> 0 | W99: =ROUND(CX99*I99,2) -> 0 | X99: =(ROUND((((S99+ROUND((ROUND((((EU99*1.2))*AV99*I99),2)*BS99),2))*AT99)/100),2)+ROUND(((ROUND((ROUND(((AE99-((EU99*1.2)))*AV99*I99),2)*BS99),2)*AT99)/100),2)) -> 28.39 | Y99: =(ROUND((((S99+ROUND((ROUND((((EU99*1.2))*AV99*I99),2)*BS99),2))*AU99)/100),2)+ROUND(((ROUND((ROUND(((AE99-((EU99*1.2)))*AV99*I99),2)*BS99),2)*AU99)/100),2)) -> 15.84 | AA99: 55943566 | AB99: =ROUND((AC99+AD99+AF99),6) -> 15.938 | AC99: =ROUND(((ES99*1)),6) -> 1.67 | AD99: =ROUND(((((ET99*1.2))-((EU99*1.2)))+AE99),6) -> 0 | AE99: =ROUND(((EU99*1.2)),6) -> 0 | AF99: =ROUND(((EV99*1.2)),6) -> 14.268 | AG99: =ROUND((AP99),6) -> 0 | AH99: =((EW99*1.2)) -> 1.2 | AI99: =((EX99*1.2)) -> 0 | AJ99: =(AS99) -> 0 | AK99: 13.56 | AL99: 1.67 | AM99: 0 | AN99: 0 | AO99: 11.89 | AP99: 0 | AQ99: 1 | AR99: 0 | AS99: 0 | AT99: 95 | AU99: 53 | AV99: 1.047 | AW99: 1 | AZ99: 1 | BA99: 1 | BB99: 1 | BC99: 1 | BH99: 0 | BI99: 2 | BJ99: ТСН-2001.4 Доп. 79, Сб. 10, т. 76, поз. 10 | BM99: 69 | BN99: 0 | BO99: 4.10-76-10 | BP99: 1 | BQ99: 40 | BR99: 0 | BS99: 1 | BT99: 1 | BU99: 1 | BV99: 1 | BW99: 1 | BX99: 1 | BZ99: 95 | CA99: 53 | CE99: 1566 | CF99: 0 | CG99: 0 | CM99: 0 | CN99: Поправка: Гл.12.Прил.8.п.8. 3_12.00.01.11.001 Наименование: При наличии напряженных и стесненных условий производства работ (стесненность, сложность складирования и транспортной логистики и т.п.) для объектов, расположенных в пределах круговой магистральной системы улиц "Садовое кольцо" города Москвы | CO99: 0 | CP99: =(P99+Q99+S99) -> 33.22 | CQ99: =ROUND((ROUND((AC99*AW99*1),2)*BC99),2) -> 1.67 | CR99: =(ROUND((ROUND((((ET99*1.2))*AV99*1),2)*BB99),2)+ROUND((ROUND(((AE99-((EU99*1.2)))*AV99*1),2)*BS99),2)) -> 0 | CS99: =(ROUND((ROUND((((EU99*1.2))*AV99*1),2)*BS99),2)+ROUND((ROUND(((AE99-((EU99*1.2)))*AV99*1),2)*BS99),2)) -> 0 | CT99: =ROUND((ROUND((AF99*AV99*1),2)*BA99),2) -> 14.94 | CU99: =AG99 -> 0 | CV99: =(AH99*AV99) -> 1.2564 | CW99: =AI99 -> 0 | CX99: =AJ99 -> 0 | CY99: =(ROUND((((S99+ROUND((ROUND((((EU99*1.2))*AV99*1),2)*BS99),2))*AT99)/100),2)+ROUND(((ROUND((ROUND(((AE99-((EU99*1.2)))*AV99*1),2)*BS99),2)*AT99)/100),2)) -> 28.39 | CZ99: =(ROUND((((S99+ROUND((ROUND((((EU99*1.2))*AV99*1),2)*BS99),2))*AU99)/100),2)+ROUND(((ROUND((ROUND(((AE99-((EU99*1.2)))*AV99*1),2)*BS99),2)*AU99)/100),2)) -> 15.84 | DB99: 43 | DD99: *1 | DE99: *1,2 | DF99: *1,2 | DG99: *1,2 | DI99: *1,2 | DJ99: *1,2 | DN99: 0 | DO99: 0 | DP99: 1 | DQ99: 1 | DU99: 1013 | DV99: 1ШТ. | DW99: 1 ШТ. | DX99: 1 | EE99: 55393973 | EF99: 40 | EG99: Монтаж оборудования | EH99: 0 | EJ99: 2 | EK99: 69 | EL99: ТСН-2001.4-10. Монтаж радиотелевизионного и электронного оборудования | EM99: ТСН-2001.4-10-2 | EO99: Поправка: Гл.12.Прил.8.п.8. 3_12.00.01.11.001 | EQ99: 131072 | ER99: 13.56 | ES99: 1.67 | ET99: 0 | EU99: 0 | EV99: 11.89 | EW99: 1 | EX99: 0 | EY99: 0 | FQ99: 0 | FR99: 0 | FS99: 0 | FX99: 95 | FY99: 53 | GD99: 1 | GF99: 659640111 | GG99: 2 | GH99: 1 | GI99: 2 | GJ99: 0 | GK99: 0 | GL99: =ROUND(IF(AND(BH99=3,BI99=3,FS99<>0),P99,0),2) -> 0 | GM99: =ROUND(O99+X99+Y99,2)+GX99 -> 77.45 | GN99: =IF(OR(BI99=0,BI99=1),GM99-GX99,0) -> 0 | GO99: =IF(BI99=2,GM99-GX99,0) -> 77.45 | GP99: =IF(BI99=4,GM99-GX99,0) -> 0 | GR99: 0 | GS99: 3 | GT99: 0 | GV99: =ROUND((GT99),6) -> 0 | GW99: 1 | GX99: =ROUND(HC99*I99,2) -> 0 | HA99: 0 | HB99: 0 | HC99: =GV99*GW99 -> 0 | HS99: 0 | IK99: 0
A100: 17 | B100: 1 | E100: 18 | F100: 4.10-76-10 | G100: Монтаж ключа или кнопки на панели | H100: 1ШТ. | I100: 2 | J100: 0 | K100: 2 | O100: =ROUND(CP100,2) -> 1743.43 | P100: =ROUND((ROUND((AC100*AW100*I100),2)*BC100),2) -> 59.69 | Q100: =(ROUND((ROUND((((ET100*1.2))*AV100*I100),2)*BB100),2)+ROUND((ROUND(((AE100-((EU100*1.2)))*AV100*I100),2)*BS100),2)) -> 0 | R100: =(ROUND((ROUND((((EU100*1.2))*AV100*I100),2)*BS100),2)+ROUND((ROUND(((AE100-((EU100*1.2)))*AV100*I100),2)*BS100),2)) -> 0 | S100: =ROUND((ROUND((AF100*AV100*I100),2)*BA100),2) -> 1683.74 | T100: =ROUND(CU100*I100,2) -> 0 | U100: =CV100*I100 -> 2.5128 | V100: =CW100*I100 -> 0 | W100: =ROUND(CX100*I100,2) -> 0 | X100: =(ROUND((((S100+ROUND((ROUND((((EU100*1.2))*AV100*I100),2)*BS100),2))*AT100)/100),2)+ROUND(((ROUND((ROUND(((AE100-((EU100*1.2)))*AV100*I100),2)*BS100),2)*AT100)/100),2)) -> 1599.55 | Y100: =(ROUND((((S100+ROUND((ROUND((((EU100*1.2))*AV100*I100),2)*BS100),2))*AU100)/100),2)+ROUND(((ROUND((ROUND(((AE100-((EU100*1.2)))*AV100*I100),2)*BS100),2)*AU100)/100),2)) -> 892.38 | AA100: 55943568 | AB100: =ROUND((AC100+AD100+AF100),6) -> 15.938 | AC100: =ROUND(((ES100*1)),6) -> 1.67 | AD100: =ROUND(((((ET100*1.2))-((EU100*1.2)))+AE100),6) -> 0 | AE100: =ROUND(((EU100*1.2)),6) -> 0 | AF100: =ROUND(((EV100*1.2)),6) -> 14.268 | AG100: =ROUND((AP100),6) -> 0 | AH100: =((EW100*1.2)) -> 1.2 | AI100: =((EX100*1.2)) -> 0 | AJ100: =(AS100) -> 0 | AK100: 13.56 | AL100: 1.67 | AM100: 0 | AN100: 0 | AO100: 11.89 | AP100: 0 | AQ100: 1 | AR100: 0 | AS100: 0 | AT100: 95 | AU100: 53 | AV100: 1.047 | AW100: 1 | AZ100: 1 | BA100: 56.35 | BB100: 1 | BC100: 17.87 | BH100: 0 | BI100: 2 | BJ100: ТСН-2001.4 Доп. 79, Сб. 10, т. 76, поз. 10 | BM100: 69 | BN100: 0 | BO100: 4.10-76-10 | BP100: 1 | BQ100: 40 | BR100: 0 | BS100: 56.35 | BT100: 1 | BU100: 1 | BV100: 1 | BW100: 1 | BX100: 1 | BZ100: 95 | CA100: 53 | CE100: 1566 | CF100: 0 | CG100: 0 | CM100: 0 | CN100: Поправка: Гл.12.Прил.8.п.8. 3_12.00.01.11.001 Наименование: При наличии напряженных и стесненных условий производства работ (стесненность, сложность складирования и транспортной логистики и т.п.) для объектов, расположенных в пределах круговой магистральной системы улиц "Садовое кольцо" города Москвы | CO100: 0 | CP100: =(P100+Q100+S100) -> 1743.43 | CQ100: =ROUND((ROUND((AC100*AW100*1),2)*BC100),2) -> 29.84 | CR100: =(ROUND((ROUND((((ET100*1.2))*AV100*1),2)*BB100),2)+ROUND((ROUND(((AE100-((EU100*1.2)))*AV100*1),2)*BS100),2)) -> 0 | CS100: =(ROUND((ROUND((((EU100*1.2))*AV100*1),2)*BS100),2)+ROUND((ROUND(((AE100-((EU100*1.2)))*AV100*1),2)*BS100),2)) -> 0 | CT100: =ROUND((ROUND((AF100*AV100*1),2)*BA100),2) -> 841.87 | CU100: =AG100 -> 0 | CV100: =(AH100*AV100) -> 1.2564 | CW100: =AI100 -> 0 | CX100: =AJ100 -> 0 | CY100: =(ROUND((((S100+ROUND((ROUND((((EU100*1.2))*AV100*1),2)*BS100),2))*AT100)/100),2)+ROUND(((ROUND((ROUND(((AE100-((EU100*1.2)))*AV100*1),2)*BS100),2)*AT100)/100),2)) -> 1599.55 | CZ100: =(ROUND((((S100+ROUND((ROUND((((EU100*1.2))*AV100*1),2)*BS100),2))*AU100)/100),2)+ROUND(((ROUND((ROUND(((AE100-((EU100*1.2)))*AV100*1),2)*BS100),2)*AU100)/100),2)) -> 892.38 | DB100: 44 | DD100: *1 | DE100: *1,2 | DF100: *1,2 | DG100: *1,2 | DI100: *1,2 | DJ100: *1,2 | DN100: 0 | DO100: 0 | DP100: 1 | DQ100: 1 | DU100: 1013 | DV100: 1ШТ. | DW100: 1 ШТ. | DX100: 1 | EE100: 55393973 | EF100: 40 | EG100: Монтаж оборудования | EH100: 0 | EJ100: 2 | EK100: 69 | EL100: ТСН-2001.4-10. Монтаж радиотелевизионного и электронного оборудования | EM100: ТСН-2001.4-10-2 | EO100: Поправка: Гл.12.Прил.8.п.8. 3_12.00.01.11.001 | EQ100: 131072 | ER100: 13.56 | ES100: 1.67 | ET100: 0 | EU100: 0 | EV100: 11.89 | EW100: 1 | EX100: 0 | EY100: 0 | FQ100: 0 | FR100: 0 | FS100: 0 | FX100: 95 | FY100: 53 | GD100: 1 | GF100: 659640111 | GG100: 2 | GH100: 1 | GI100: 2 | GJ100: 0 | GK100: 0 | GL100: =ROUND(IF(AND(BH100=3,BI100=3,FS100<>0),P100,0),2) -> 0 | GM100: =ROUND(O100+X100+Y100,2)+GX100 -> 4235.36 | GN100: =IF(OR(BI100=0,BI100=1),GM100-GX100,0) -> 0 | GO100: =IF(BI100=2,GM100-GX100,0) -> 4235.36 | GP100: =IF(BI100=4,GM100-GX100,0) -> 0 | GR100: 0 | GS100: 3 | GT100: 0 | GV100: =ROUND((GT100),6) -> 0 | GW100: 1 | GX100: =ROUND(HC100*I100,2) -> 0 | HA100: 0 | HB100: 0 | HC100: =GV100*GW100 -> 0 | HS100: 0 | IK100: 0
A101: 17 | B101: 1 | E101: 19 | F101: КА, п.4 | G101: Устройство вызова AL-RB | H101: ШТ | I101: 1 | J101: 0 | K101: 1 | O101: =ROUND(CP101,2) -> 963.68 | P101: =ROUND((ROUND((AC101*AW101*I101),2)*BC101),2) -> 963.68 | Q101: =(ROUND((ROUND(((ET101)*AV101*I101),2)*BB101),2)+ROUND((ROUND(((AE101-(EU101))*AV101*I101),2)*BS101),2)) -> 0 | R101: =(ROUND((ROUND(((EU101)*AV101*I101),2)*BS101),2)+ROUND((ROUND(((AE101-(EU101))*AV101*I101),2)*BS101),2)) -> 0 | S101: =ROUND((ROUND((AF101*AV101*I101),2)*BA101),2) -> 0 | T101: =ROUND(CU101*I101,2) -> 0 | U101: =CV101*I101 -> 0 | V101: =CW101*I101 -> 0 | W101: =ROUND(CX101*I101,2) -> 0 | X101: =(ROUND((((S101+ROUND((ROUND(((EU101)*AV101*I101),2)*BS101),2))*AT101)/100),2)+ROUND(((ROUND((ROUND(((AE101-(EU101))*AV101*I101),2)*BS101),2)*AT101)/100),2)) -> 0 | Y101: =(ROUND((((S101+ROUND((ROUND(((EU101)*AV101*I101),2)*BS101),2))*AU101)/100),2)+ROUND(((ROUND((ROUND(((AE101-(EU101))*AV101*I101),2)*BS101),2)*AU101)/100),2)) -> 0 | AA101: 55943566 | AB101: =ROUND((AC101+AD101+AF101),6) -> 963.68 | AC101: =ROUND((ES101),6) -> 963.68 | AD101: =ROUND((((ET101)-(EU101))+AE101),6) -> 0 | AE101: =ROUND((EU101),6) -> 0 | AF101: =ROUND((EV101),6) -> 0 | AG101: =ROUND((AP101),6) -> 0 | AH101: =(EW101) -> 0 | AI101: =(EX101) -> 0 | AJ101: =(AS101) -> 0 | AK101: 963.68 | AL101: 963.68 | AM101: 0 | AN101: 0 | AO101: 0 | AP101: 0 | AQ101: 0 | AR101: 0 | AS101: 0 | AT101: 0 | AU101: 0 | AV101: 1 | AW101: 1 | AZ101: 1 | BA101: 1 | BB101: 1 | BC101: 1 | BH101: 3 | BI101: 3 | BJ101: КА, п.4 | BM101: 400007 | BN101: 0 | BP101: 0 | BQ101: 214 | BR101: 0 | BS101: 1 | BT101: 1 | BU101: 1 | BV101: 1 | BW101: 1 | BX101: 1 | BZ101: 0 | CA101: 0 | CE101: 1566 | CF101: 0 | CG101: 0 | CM101: 0 | CO101: 0 | CP101: =(P101+Q101+S101) -> 963.68 | CQ101: =ROUND((ROUND((AC101*AW101*1),2)*BC101),2) -> 963.68 | CR101: =(ROUND((ROUND(((ET101)*AV101*1),2)*BB101),2)+ROUND((ROUND(((AE101-(EU101))*AV101*1),2)*BS101),2)) -> 0 | CS101: =(ROUND((ROUND(((EU101)*AV101*1),2)*BS101),2)+ROUND((ROUND(((AE101-(EU101))*AV101*1),2)*BS101),2)) -> 0 | CT101: =ROUND((ROUND((AF101*AV101*1),2)*BA101),2) -> 0 | CU101: =AG101 -> 0 | CV101: =(AH101*AV101) -> 0 | CW101: =AI101 -> 0 | CX101: =AJ101 -> 0 | CY101: =(ROUND((((S101+ROUND((ROUND(((EU101)*AV101*1),2)*BS101),2))*AT101)/100),2)+ROUND(((ROUND((ROUND(((AE101-(EU101))*AV101*1),2)*BS101),2)*AT101)/100),2)) -> 0 | CZ101: =(ROUND((((S101+ROUND((ROUND(((EU101)*AV101*1),2)*BS101),2))*AU101)/100),2)+ROUND(((ROUND((ROUND(((AE101-(EU101))*AV101*1),2)*BS101),2)*AU101)/100),2)) -> 0 | DN101: 0 | DO101: 0 | DP101: 1 | DQ101: 1 | DU101: 1013 | DV101: ШТ | DW101: ШТ | DX101: 1 | EE101: 55393904 | EF101: 214 | EG101: Оборудование, отсутствующие в СНБ | EH101: 0 | EJ101: 3 | EK101: 400007 | EL101: Оборудование, отсутствующие в СНБ | EM101: Оборуд. КА | EQ101: 131088 | ER101: 0 | ES101: 963.68 | ET101: 0 | EU101: 0 | EV101: 0 | EW101: 0 | EX101: 0 | EY101: 0 | FQ101: 0 | FR101: =P101 -> 963.68 | FS101: 0 | FX101: 0 | FY101: 0 | GA101: [8 900 / 1,22 / 7,57] | GD101: 1 | GF101: -1102805674 | GG101: 2 | GH101: 4 | GI101: -2 | GJ101: 0 | GK101: 0 | GL101: =ROUND(IF(AND(BH101=3,BI101=3,FS101<>0),P101,0),2) -> 0 | GM101: =ROUND(O101+X101+Y101,2)+GX101 -> 963.68 | GN101: =IF(OR(BI101=0,BI101=1),GM101-GX101,0) -> 0 | GO101: =IF(BI101=2,GM101-GX101,0) -> 0 | GP101: =IF(BI101=4,GM101-GX101,0) -> 0 | GR101: 1 | GS101: 2 | GT101: 0 | GV101: =ROUND((GT101),6) -> 0 | GW101: 1 | GX101: =ROUND(HC101*I101,2) -> 0 | HA101: 0 | HB101: 0 | HC101: =GV101*GW101 -> 0 | HE101: 0 | HF101: 0 | HS101: 0 | IK101: 0
A102: 17 | B102: 1 | E102: 19 | F102: КА, п.4 | G102: Устройство вызова AL-RB | H102: ШТ | I102: 1 | J102: 0 | K102: 1 | O102: =ROUND(CP102,2) -> 7295.06 | P102: =ROUND((ROUND((AC102*AW102*I102),2)*BC102),2) -> 7295.06 | Q102: =(ROUND((ROUND(((ET102)*AV102*I102),2)*BB102),2)+ROUND((ROUND(((AE102-(EU102))*AV102*I102),2)*BS102),2)) -> 0 | R102: =(ROUND((ROUND(((EU102)*AV102*I102),2)*BS102),2)+ROUND((ROUND(((AE102-(EU102))*AV102*I102),2)*BS102),2)) -> 0 | S102: =ROUND((ROUND((AF102*AV102*I102),2)*BA102),2) -> 0 | T102: =ROUND(CU102*I102,2) -> 0 | U102: =CV102*I102 -> 0 | V102: =CW102*I102 -> 0 | W102: =ROUND(CX102*I102,2) -> 0 | X102: =(ROUND((((S102+ROUND((ROUND(((EU102)*AV102*I102),2)*BS102),2))*AT102)/100),2)+ROUND(((ROUND((ROUND(((AE102-(EU102))*AV102*I102),2)*BS102),2)*AT102)/100),2)) -> 0 | Y102: =(ROUND((((S102+ROUND((ROUND(((EU102)*AV102*I102),2)*BS102),2))*AU102)/100),2)+ROUND(((ROUND((ROUND(((AE102-(EU102))*AV102*I102),2)*BS102),2)*AU102)/100),2)) -> 0 | AA102: 55943568 | AB102: =ROUND((AC102+AD102+AF102),6) -> 963.68 | AC102: =ROUND((ES102),6) -> 963.68 | AD102: =ROUND((((ET102)-(EU102))+AE102),6) -> 0 | AE102: =ROUND((EU102),6) -> 0 | AF102: =ROUND((EV102),6) -> 0 | AG102: =ROUND((AP102),6) -> 0 | AH102: =(EW102) -> 0 | AI102: =(EX102) -> 0 | AJ102: =(AS102) -> 0 | AK102: 963.68 | AL102: 963.68 | AM102: 0 | AN102: 0 | AO102: 0 | AP102: 0 | AQ102: 0 | AR102: 0 | AS102: 0 | AT102: 0 | AU102: 0 | AV102: 1 | AW102: 1 | AZ102: 1 | BA102: 1 | BB102: 1 | BC102: 7.57 | BH102: 3 | BI102: 3 | BJ102: КА, п.4 | BM102: 400007 | BN102: 0 | BP102: 0 | BQ102: 214 | BR102: 0 | BS102: 1 | BT102: 1 | BU102: 1 | BV102: 1 | BW102: 1 | BX102: 1 | BZ102: 0 | CA102: 0 | CE102: 1566 | CF102: 0 | CG102: 0 | CM102: 0 | CO102: 0 | CP102: =(P102+Q102+S102) -> 7295.06 | CQ102: =ROUND((ROUND((AC102*AW102*1),2)*BC102),2) -> 7295.06 | CR102: =(ROUND((ROUND(((ET102)*AV102*1),2)*BB102),2)+ROUND((ROUND(((AE102-(EU102))*AV102*1),2)*BS102),2)) -> 0 | CS102: =(ROUND((ROUND(((EU102)*AV102*1),2)*BS102),2)+ROUND((ROUND(((AE102-(EU102))*AV102*1),2)*BS102),2)) -> 0 | CT102: =ROUND((ROUND((AF102*AV102*1),2)*BA102),2) -> 0 | CU102: =AG102 -> 0 | CV102: =(AH102*AV102) -> 0 | CW102: =AI102 -> 0 | CX102: =AJ102 -> 0 | CY102: =(ROUND((((S102+ROUND((ROUND(((EU102)*AV102*1),2)*BS102),2))*AT102)/100),2)+ROUND(((ROUND((ROUND(((AE102-(EU102))*AV102*1),2)*BS102),2)*AT102)/100),2)) -> 0 | CZ102: =(ROUND((((S102+ROUND((ROUND(((EU102)*AV102*1),2)*BS102),2))*AU102)/100),2)+ROUND(((ROUND((ROUND(((AE102-(EU102))*AV102*1),2)*BS102),2)*AU102)/100),2)) -> 0 | DN102: 0 | DO102: 0 | DP102: 1 | DQ102: 1 | DU102: 1013 | DV102: ШТ | DW102: ШТ | DX102: 1 | EE102: 55393904 | EF102: 214 | EG102: Оборудование, отсутствующие в СНБ | EH102: 0 | EJ102: 3 | EK102: 400007 | EL102: Оборудование, отсутствующие в СНБ | EM102: Оборуд. КА | EQ102: 131088 | ER102: 0 | ES102: 963.68 | ET102: 0 | EU102: 0 | EV102: 0 | EW102: 0 | EX102: 0 | EY102: 0 | EZ102: 5 | FC102: 1 | FD102: 18 | FF102: 8900 | FQ102: 0 | FR102: =P102 -> 7295.06 | FS102: 0 | FX102: 0 | FY102: 0 | GA102: [8 900 / 1,22 / 7,57] | GD102: 1 | GF102: -1102805674 | GG102: 2 | GH102: 3 | GI102: 3 | GJ102: 0 | GK102: 0 | GL102: =ROUND(IF(AND(BH102=3,BI102=3,FS102<>0),P102,0),2) -> 0 | GM102: =ROUND(O102+X102+Y102,2)+GX102 -> 7295.06 | GN102: =IF(OR(BI102=0,BI102=1),GM102-GX102,0) -> 0 | GO102: =IF(BI102=2,GM102-GX102,0) -> 0 | GP102: =IF(BI102=4,GM102-GX102,0) -> 0 | GR102: 1 | GS102: 1 | GT102: 0 | GV102: =ROUND((GT102),6) -> 0 | GW102: 1 | GX102: =ROUND(HC102*I102,2) -> 0 | HA102: 0 | HB102: 0 | HC102: =GV102*GW102 -> 0 | HE102: 0 | HF102: 0 | HS102: 0 | IK102: 0
A103: 17 | B103: 1 | E103: 20 | F103: КА, п.5 | G103: Устройство отмены вызова AL-CB | H103: ШТ | I103: 1 | J103: 0 | K103: 1 | O103: =ROUND(CP103,2) -> 1894.88 | P103: =ROUND((ROUND((AC103*AW103*I103),2)*BC103),2) -> 1894.88 | Q103: =(ROUND((ROUND(((ET103)*AV103*I103),2)*BB103),2)+ROUND((ROUND(((AE103-(EU103))*AV103*I103),2)*BS103),2)) -> 0 | R103: =(ROUND((ROUND(((EU103)*AV103*I103),2)*BS103),2)+ROUND((ROUND(((AE103-(EU103))*AV103*I103),2)*BS103),2)) -> 0 | S103: =ROUND((ROUND((AF103*AV103*I103),2)*BA103),2) -> 0 | T103: =ROUND(CU103*I103,2) -> 0 | U103: =CV103*I103 -> 0 | V103: =CW103*I103 -> 0 | W103: =ROUND(CX103*I103,2) -> 0 | X103: =(ROUND((((S103+ROUND((ROUND(((EU103)*AV103*I103),2)*BS103),2))*AT103)/100),2)+ROUND(((ROUND((ROUND(((AE103-(EU103))*AV103*I103),2)*BS103),2)*AT103)/100),2)) -> 0 | Y103: =(ROUND((((S103+ROUND((ROUND(((EU103)*AV103*I103),2)*BS103),2))*AU103)/100),2)+ROUND(((ROUND((ROUND(((AE103-(EU103))*AV103*I103),2)*BS103),2)*AU103)/100),2)) -> 0 | AA103: 55943566 | AB103: =ROUND((AC103+AD103+AF103),6) -> 1894.88 | AC103: =ROUND((ES103),6) -> 1894.88 | AD103: =ROUND((((ET103)-(EU103))+AE103),6) -> 0 | AE103: =ROUND((EU103),6) -> 0 | AF103: =ROUND((EV103),6) -> 0 | AG103: =ROUND((AP103),6) -> 0 | AH103: =(EW103) -> 0 | AI103: =(EX103) -> 0 | AJ103: =(AS103) -> 0 | AK103: 1894.88 | AL103: 1894.88 | AM103: 0 | AN103: 0 | AO103: 0 | AP103: 0 | AQ103: 0 | AR103: 0 | AS103: 0 | AT103: 0 | AU103: 0 | AV103: 1 | AW103: 1 | AZ103: 1 | BA103: 1 | BB103: 1 | BC103: 1 | BH103: 3 | BI103: 3 | BJ103: КА, п.5 | BM103: 400007 | BN103: 0 | BP103: 0 | BQ103: 214 | BR103: 0 | BS103: 1 | BT103: 1 | BU103: 1 | BV103: 1 | BW103: 1 | BX103: 1 | BZ103: 0 | CA103: 0 | CE103: 1566 | CF103: 0 | CG103: 0 | CM103: 0 | CO103: 0 | CP103: =(P103+Q103+S103) -> 1894.88 | CQ103: =ROUND((ROUND((AC103*AW103*1),2)*BC103),2) -> 1894.88 | CR103: =(ROUND((ROUND(((ET103)*AV103*1),2)*BB103),2)+ROUND((ROUND(((AE103-(EU103))*AV103*1),2)*BS103),2)) -> 0 | CS103: =(ROUND((ROUND(((EU103)*AV103*1),2)*BS103),2)+ROUND((ROUND(((AE103-(EU103))*AV103*1),2)*BS103),2)) -> 0 | CT103: =ROUND((ROUND((AF103*AV103*1),2)*BA103),2) -> 0 | CU103: =AG103 -> 0 | CV103: =(AH103*AV103) -> 0 | CW103: =AI103 -> 0 | CX103: =AJ103 -> 0 | CY103: =(ROUND((((S103+ROUND((ROUND(((EU103)*AV103*1),2)*BS103),2))*AT103)/100),2)+ROUND(((ROUND((ROUND(((AE103-(EU103))*AV103*1),2)*BS103),2)*AT103)/100),2)) -> 0 | CZ103: =(ROUND((((S103+ROUND((ROUND(((EU103)*AV103*1),2)*BS103),2))*AU103)/100),2)+ROUND(((ROUND((ROUND(((AE103-(EU103))*AV103*1),2)*BS103),2)*AU103)/100),2)) -> 0 | DN103: 0 | DO103: 0 | DP103: 1 | DQ103: 1 | DU103: 1013 | DV103: ШТ | DW103: ШТ | DX103: 1 | EE103: 55393904 | EF103: 214 | EG103: Оборудование, отсутствующие в СНБ | EH103: 0 | EJ103: 3 | EK103: 400007 | EL103: Оборудование, отсутствующие в СНБ | EM103: Оборуд. КА | EQ103: 131088 | ER103: 0 | ES103: 1894.88 | ET103: 0 | EU103: 0 | EV103: 0 | EW103: 0 | EX103: 0 | EY103: 0 | FQ103: 0 | FR103: =P103 -> 1894.88 | FS103: 0 | FX103: 0 | FY103: 0 | GA103: [17 500 / 1,22 / 7,57] | GD103: 1 | GF103: 1330220109 | GG103: 2 | GH103: 4 | GI103: -2 | GJ103: 0 | GK103: 0 | GL103: =ROUND(IF(AND(BH103=3,BI103=3,FS103<>0),P103,0),2) -> 0 | GM103: =ROUND(O103+X103+Y103,2)+GX103 -> 1894.88 | GN103: =IF(OR(BI103=0,BI103=1),GM103-GX103,0) -> 0 | GO103: =IF(BI103=2,GM103-GX103,0) -> 0 | GP103: =IF(BI103=4,GM103-GX103,0) -> 0 | GR103: 1 | GS103: 2 | GT103: 0 | GV103: =ROUND((GT103),6) -> 0 | GW103: 1 | GX103: =ROUND(HC103*I103,2) -> 0 | HA103: 0 | HB103: 0 | HC103: =GV103*GW103 -> 0 | HE103: 0 | HF103: 0 | HS103: 0 | IK103: 0
A104: 17 | B104: 1 | E104: 20 | F104: КА, п.5 | G104: Устройство отмены вызова AL-CB | H104: ШТ | I104: 1 | J104: 0 | K104: 1 | O104: =ROUND(CP104,2) -> 14344.24 | P104: =ROUND((ROUND((AC104*AW104*I104),2)*BC104),2) -> 14344.24 | Q104: =(ROUND((ROUND(((ET104)*AV104*I104),2)*BB104),2)+ROUND((ROUND(((AE104-(EU104))*AV104*I104),2)*BS104),2)) -> 0 | R104: =(ROUND((ROUND(((EU104)*AV104*I104),2)*BS104),2)+ROUND((ROUND(((AE104-(EU104))*AV104*I104),2)*BS104),2)) -> 0 | S104: =ROUND((ROUND((AF104*AV104*I104),2)*BA104),2) -> 0 | T104: =ROUND(CU104*I104,2) -> 0 | U104: =CV104*I104 -> 0 | V104: =CW104*I104 -> 0 | W104: =ROUND(CX104*I104,2) -> 0 | X104: =(ROUND((((S104+ROUND((ROUND(((EU104)*AV104*I104),2)*BS104),2))*AT104)/100),2)+ROUND(((ROUND((ROUND(((AE104-(EU104))*AV104*I104),2)*BS104),2)*AT104)/100),2)) -> 0 | Y104: =(ROUND((((S104+ROUND((ROUND(((EU104)*AV104*I104),2)*BS104),2))*AU104)/100),2)+ROUND(((ROUND((ROUND(((AE104-(EU104))*AV104*I104),2)*BS104),2)*AU104)/100),2)) -> 0 | AA104: 55943568 | AB104: =ROUND((AC104+AD104+AF104),6) -> 1894.88 | AC104: =ROUND((ES104),6) -> 1894.88 | AD104: =ROUND((((ET104)-(EU104))+AE104),6) -> 0 | AE104: =ROUND((EU104),6) -> 0 | AF104: =ROUND((EV104),6) -> 0 | AG104: =ROUND((AP104),6) -> 0 | AH104: =(EW104) -> 0 | AI104: =(EX104) -> 0 | AJ104: =(AS104) -> 0 | AK104: 1894.88 | AL104: 1894.88 | AM104: 0 | AN104: 0 | AO104: 0 | AP104: 0 | AQ104: 0 | AR104: 0 | AS104: 0 | AT104: 0 | AU104: 0 | AV104: 1 | AW104: 1 | AZ104: 1 | BA104: 1 | BB104: 1 | BC104: 7.57 | BH104: 3 | BI104: 3 | BJ104: КА, п.5 | BM104: 400007 | BN104: 0 | BP104: 0 | BQ104: 214 | BR104: 0 | BS104: 1 | BT104: 1 | BU104: 1 | BV104: 1 | BW104: 1 | BX104: 1 | BZ104: 0 | CA104: 0 | CE104: 1566 | CF104: 0 | CG104: 0 | CM104: 0 | CO104: 0 | CP104: =(P104+Q104+S104) -> 14344.24 | CQ104: =ROUND((ROUND((AC104*AW104*1),2)*BC104),2) -> 14344.24 | CR104: =(ROUND((ROUND(((ET104)*AV104*1),2)*BB104),2)+ROUND((ROUND(((AE104-(EU104))*AV104*1),2)*BS104),2)) -> 0 | CS104: =(ROUND((ROUND(((EU104)*AV104*1),2)*BS104),2)+ROUND((ROUND(((AE104-(EU104))*AV104*1),2)*BS104),2)) -> 0 | CT104: =ROUND((ROUND((AF104*AV104*1),2)*BA104),2) -> 0 | CU104: =AG104 -> 0 | CV104: =(AH104*AV104) -> 0 | CW104: =AI104 -> 0 | CX104: =AJ104 -> 0 | CY104: =(ROUND((((S104+ROUND((ROUND(((EU104)*AV104*1),2)*BS104),2))*AT104)/100),2)+ROUND(((ROUND((ROUND(((AE104-(EU104))*AV104*1),2)*BS104),2)*AT104)/100),2)) -> 0 | CZ104: =(ROUND((((S104+ROUND((ROUND(((EU104)*AV104*1),2)*BS104),2))*AU104)/100),2)+ROUND(((ROUND((ROUND(((AE104-(EU104))*AV104*1),2)*BS104),2)*AU104)/100),2)) -> 0 | DN104: 0 | DO104: 0 | DP104: 1 | DQ104: 1 | DU104: 1013 | DV104: ШТ | DW104: ШТ | DX104: 1 | EE104: 55393904 | EF104: 214 | EG104: Оборудование, отсутствующие в СНБ | EH104: 0 | EJ104: 3 | EK104: 400007 | EL104: Оборудование, отсутствующие в СНБ | EM104: Оборуд. КА | EQ104: 131088 | ER104: 0 | ES104: 1894.88 | ET104: 0 | EU104: 0 | EV104: 0 | EW104: 0 | EX104: 0 | EY104: 0 | EZ104: 5 | FC104: 1 | FD104: 18 | FF104: 17500 | FQ104: 0 | FR104: =P104 -> 14344.24 | FS104: 0 | FX104: 0 | FY104: 0 | GA104: [17 500 / 1,22 / 7,57] | GD104: 1 | GF104: 1330220109 | GG104: 2 | GH104: 3 | GI104: 3 | GJ104: 0 | GK104: 0 | GL104: =ROUND(IF(AND(BH104=3,BI104=3,FS104<>0),P104,0),2) -> 0 | GM104: =ROUND(O104+X104+Y104,2)+GX104 -> 14344.24 | GN104: =IF(OR(BI104=0,BI104=1),GM104-GX104,0) -> 0 | GO104: =IF(BI104=2,GM104-GX104,0) -> 0 | GP104: =IF(BI104=4,GM104-GX104,0) -> 0 | GR104: 1 | GS104: 1 | GT104: 0 | GV104: =ROUND((GT104),6) -> 0 | GW104: 1 | GX104: =ROUND(HC104*I104,2) -> 0 | HA104: 0 | HB104: 0 | HC104: =GV104*GW104 -> 0 | HE104: 0 | HF104: 0 | HS104: 0 | IK104: 0
