Workbook

Sheet 02-01-04
A1: =Source!B1 -> Smeta.RU (495) 974-1589
J2: Форма № 4б
A3: =Source!G4 -> Капитальный ремонт здания Государственного бюджетного общеобразовательного учреждения города Москвы «Школа №1574», расположенного по адресу: г. Москва, Старопименовский переулок, д. 5. 1 этап | AP3: Капитальный ремонт здания Государственного бюджетного общеобразовательного учреждения города Москвы «Школа №1574», расположенного по адресу: г. Москва, пер. Старопименовский, д. 5. Водоснабжение.
A4: (наименование стройки и/или объекта)
A6: =CONCATENATE( "ЛОКАЛЬНАЯ СМЕТА № ",IF(Source!F20<>"Новая локальная смета", Source!F20, "")) -> ЛОКАЛЬНАЯ СМЕТА № 02-01-04
A8: =IF(Source!G20<>"Новая локальная смета", Source!G20, "") -> Система водоснабжения.
A9: (наименование работ и затрат)
A11: =CONCATENATE( "Основание: чертежи № ", Source!J20) -> Основание: чертежи № 2024-00375-01-0-ИОС2
I13: В базисном уровне цен | J13: В текущем уровне цен
E14: Сметная стоимость | I14: =I15+I16+I17+I18 -> 335.56 | J14: =J15+J16+J17+J18 -> 6275.41 | K14: тыс.руб.
E15: Строительные работы | I15: =ROUND((Source!F688)/1000, 2) -> 303.96 | J15: =ROUND((Source!P688)/1000, 2) -> 6036.17 | K15: тыс.руб.
E16: Работы по монтажу оборудования | I16: =ROUND((Source!F689)/1000, 2) -> 0 | J16: =ROUND((Source!P689)/1000, 2) -> 0 | K16: тыс.руб.
E17: Оборудование | I17: =ROUND((Source!F680)/1000, 2) -> 31.6 | J17: =ROUND((Source!P680)/1000, 2) -> 239.24 | K17: тыс.руб.
E18: Прочие работы и затраты | I18: =ROUND((Source!F690+Source!F691)/1000, 2) -> 0 | J18: =ROUND((Source!P690+Source!P691)/1000, 2) -> 0 | K18: тыс.руб.
E19: Средства на оплату труда | I19: =(Source!F686+ Source!F685)/1000 -> 25.94258 | J19: =((Source!P686 + Source!P685)/1000) -> 1461.8644 | K19: тыс.руб.
E20: Затраты труда | I20: =Source!F693 -> 2104.7977 | K20: чел.-ч.
E21: Кроме того:
E22: Возврат материалов | I22: =SUM(Y28:Y954)/1000 -> 0 | J22: =SUM(Z28:Z954)/1000 -> 0 | K22: тыс.руб.
A24: Составлен(а) по ТСН-2001 с учетом Дополнения №: 81
A25: № и период сборника коэффициентов (индексов) пересчета: Коэффициенты к ТСН-2001 МГЭ Дополнение 81, ремонт №219/81 I квартал 2026 года и Коэффициенты к ТСН-2001.13-2 Дополнение 47 №64/47 I квартал 2026 года | AP25: № и период сборника коэффициентов (индексов) пересчета: Коэффициенты к ТСН-2001 МГЭ Дополнение 81, ремонт №219/81 I квартал 2026 года и Коэффициенты к ТСН-2001.13-2 Дополнение 47 №64/47 I квартал 2026 года
A26: № п/п | B26: Шифр расценки и коды ресурсов | C26: Наименование работ и затрат | D26: Ед. изм. | E26: Кол-во единиц | F26: Цена на ед. изм., руб. | G26: Попра- вочные коэффи- циенты | H26: Коэффи- циенты зимних удорожа- ний | I26: Всего в ценах на январь 2000 года, руб. | J26: Коэффи- циенты (индек- сы) пере- счета, нормы НР и СП | K26: ВСЕГО затрат в текущем уровне цен, руб.
A27: 1 | B27: 2 | C27: 3 | D27: 4 | E27: 5 | F27: 6 | G27: 7 | H27: 8 | I27: 9 | J27: 10 | K27: 11 | L27: цена за ед с ндс
A29: =CONCATENATE("Раздел: ",IF(Source!G24<>"Новый раздел", Source!G24, "")) -> Раздел: Демонтажные работы.
A30: 1 | B30: =Source!F28 -> 6.65-1-1 | C30: Разборка трубопроводов из водогазопроводных труб диаметром до 25 мм | D30: =Source!H28 -> 100 м | E30: =Source!I28 -> 7.37 | Q30: =Source!X28 -> 2289.41 | R30: =Source!X29 -> 129008.46 | S30: =Source!Y28 -> 1157.86 | T30: =Source!Y29 -> 65245.66 | U30: =ROUND((175/100)*ROUND(Source!R28, 2), 2) -> 0 | V30: =ROUND((0/100)*ROUND(Source!R29, 2), 2) -> 0 | AC30: 0
C31: ="Объем: "&Source!I28&"=(28+"&"45+"&"35+"&"75+"&"90+"&"75+"&"33+"&"87+"&"25+"&"90+"&"100+"&"54)/"&"100" -> Объем: 7,37=(28+45+35+75+90+75+33+87+25+90+100+54)/100
C32: ЗП | F32: =Source!AO28 -> 284.19 | G32: 1,2 | H32: =Source!AV29 -> 1.047 | I32: =Source!S28 -> 2631.51 | J32: =IF(Source!BA29<> 0, Source!BA29, 1) -> 56.35 | K32: =Source!S29 -> 148285.59
C33: ЭМ | F33: =Source!AM28 -> 0.7 | G33: 1,2 | H33: =Source!AV29 -> 1.047 | I33: =Source!Q28 -> 6.48 | J33: =IF(Source!BB29<> 0, Source!BB29, 1) -> 9.29 | K33: =Source!Q29 -> 60.2
C34: МР | F34: =Source!AL28 -> 32.56 | H34: =Source!AW29 -> 1 | I34: =Source!P28 -> 239.97 | J34: =IF(Source!BC29<> 0, Source!BC29, 1) -> 15.53 | K34: =Source!P29 -> 3726.73
C35: НР от ФОТ | D35: % | E35: =Source!BZ29 -> 87 | I35: =SUM(Q30:Q34) -> 2289.41 | J35: =Source!AT29 -> 87 | K35: =SUM(R30:R34) -> 129008.46
C36: СП от ФОТ | D36: % | E36: =Source!CA29 -> 44 | I36: =SUM(S30:S35) -> 1157.86 | J36: =Source!AU29 -> 44 | K36: =SUM(T30:T35) -> 65245.66
C37: ЗТР | D37: чел-ч | E37: =Source!AQ28 -> 26.56 | G37: 1,2 | H37: =Source!AV29 -> 1.047 | I37: =Source!U28 -> 245.93678
C38: ВСЕГО работ по позиции: | H38: =I32+I33+I34+I35+I36+0-0-0 -> 6325.23 | J38: =K32+K33+K34+K35+K36+0-0-0 -> 346326.64
C39: ВСЕГО оборудование по позиции: | H39: =0+0 -> 0 | J39: =0+0 -> 0
C40: ВСЕГО по позиции: | H40: =I32+I33+I34+I35+I36+0 -> 6325.23 | J40: =K32+K33+K34+K35+K36+0 -> 346326.64 | O40: =I32+I33+I34+I35+I36+0 -> 6325.23 | P40: =K32+K33+K34+K35+K36+0 -> 346326.64
A42: 2 | B42: =Source!F30 -> 6.65-1-2 | C42: Разборка трубопроводов из водогазопроводных труб диаметром до 40 мм | D42: =Source!H30 -> 100 м | E42: =Source!I30 -> 3.31 | Q42: =Source!X30 -> 1793.51 | R42: =Source!X31 -> 101064.01 | S42: =Source!Y30 -> 907.06 | T42: =Source!Y31 -> 51112.83 | U42: =ROUND((175/100)*ROUND(Source!R30, 2), 2) -> 0 | V42: =ROUND((0/100)*ROUND(Source!R31, 2), 2) -> 0 | AC42: 0
C43: ="Объем: "&Source!I30&"=(22+"&"55+"&"50+"&"64+"&"95+"&"45)/"&"100" -> Объем: 3,31=(22+55+50+64+95+45)/100
C44: ЗП | F44: =Source!AO30 -> 495.71 | G44: 1,2 | H44: =Source!AV31 -> 1.047 | I44: =Source!S30 -> 2061.5 | J44: =IF(Source!BA31<> 0, Source!BA31, 1) -> 56.35 | K44: =Source!S31 -> 116165.53
C45: ЭМ | F45: =Source!AM30 -> 1.26 | G45: 1,2 | H45: =Source!AV31 -> 1.047 | I45: =Source!Q30 -> 5.24 | J45: =IF(Source!BB31<> 0, Source!BB31, 1) -> 9.29 | K45: =Source!Q31 -> 48.68
C46: МР | F46: =Source!AL30 -> 46.16 | H46: =Source!AW31 -> 1 | I46: =Source!P30 -> 152.79 | J46: =IF(Source!BC31<> 0, Source!BC31, 1) -> 15.53 | K46: =Source!P31 -> 2372.83
C47: НР от ФОТ | D47: % | E47: =Source!BZ31 -> 87 | I47: =SUM(Q42:Q46) -> 1793.51 | J47: =Source!AT31 -> 87 | K47: =SUM(R42:R46) -> 101064.01
C48: СП от ФОТ | D48: % | E48: =Source!CA31 -> 44 | I48: =SUM(S42:S47) -> 907.06 | J48: =Source!AU31 -> 44 | K48: =SUM(T42:T47) -> 51112.83
C49: ЗТР | D49: чел-ч | E49: =Source!AQ30 -> 45.52 | G49: 1,2 | H49: =Source!AV31 -> 1.047 | I49: =Source!U30 -> 189.3033
C50: ВСЕГО работ по позиции: | H50: =I44+I45+I46+I47+I48+0-0-0 -> 4920.1 | J50: =K44+K45+K46+K47+K48+0-0-0 -> 270763.88
C51: ВСЕГО оборудование по позиции: | H51: =0+0 -> 0 | J51: =0+0 -> 0
C52: ВСЕГО по позиции: | H52: =I44+I45+I46+I47+I48+0 -> 4920.1 | J52: =K44+K45+K46+K47+K48+0 -> 270763.88 | O52: =I44+I45+I46+I47+I48+0 -> 4920.1 | P52: =K44+K45+K46+K47+K48+0 -> 270763.88
A54: 3 | B54: =Source!F32 -> 6.65-1-3 | C54: Разборка трубопроводов из водогазопроводных труб диаметром до 50 мм | D54: =Source!H32 -> 100 м | E54: =Source!I32 -> 1.22 | Q54: =Source!X32 -> 875.98 | R54: =Source!X33 -> 49361.29 | S54: =Source!Y32 -> 443.02 | T54: =Source!Y33 -> 24964.33 | U54: =ROUND((175/100)*ROUND(Source!R32, 2), 2) -> 0 | V54: =ROUND((0/100)*ROUND(Source!R33, 2), 2) -> 0 | AC54: 0
C55: ="Объем: "&Source!I32&"=(110+"&"12)/"&"100" -> Объем: 1,22=(110+12)/100
C56: ЗП | F56: =Source!AO32 -> 656.88 | G56: 1,2 | H56: =Source!AV33 -> 1.047 | I56: =Source!S32 -> 1006.87 | J56: =IF(Source!BA33<> 0, Source!BA33, 1) -> 56.35 | K56: =Source!S33 -> 56737.12
C57: ЭМ | F57: =Source!AM32 -> 1.37 | G57: 1,2 | H57: =Source!AV33 -> 1.047 | I57: =Source!Q32 -> 2.1 | J57: =IF(Source!BB33<> 0, Source!BB33, 1) -> 9.3 | K57: =Source!Q33 -> 19.53
C58: МР | F58: =Source!AL32 -> 55.28 | H58: =Source!AW33 -> 1 | I58: =Source!P32 -> 67.44 | J58: =IF(Source!BC33<> 0, Source!BC33, 1) -> 15.54 | K58: =Source!P33 -> 1048.02
C59: НР от ФОТ | D59: % | E59: =Source!BZ33 -> 87 | I59: =SUM(Q54:Q58) -> 875.98 | J59: =Source!AT33 -> 87 | K59: =SUM(R54:R58) -> 49361.29
C60: СП от ФОТ | D60: % | E60: =Source!CA33 -> 44 | I60: =SUM(S54:S59) -> 443.02 | J60: =Source!AU33 -> 44 | K60: =SUM(T54:T59) -> 24964.33
C61: ЗТР | D61: чел-ч | E61: =Source!AQ32 -> 60.32 | G61: 1,2 | H61: =Source!AV33 -> 1.047 | I61: =Source!U32 -> 92.458979
C62: ВСЕГО работ по позиции: | H62: =I56+I57+I58+I59+I60+0-0-0 -> 2395.41 | J62: =K56+K57+K58+K59+K60+0-0-0 -> 132130.29
C63: ВСЕГО оборудование по позиции: | H63: =0+0 -> 0 | J63: =0+0 -> 0
C64: ВСЕГО по позиции: | H64: =I56+I57+I58+I59+I60+0 -> 2395.41 | J64: =K56+K57+K58+K59+K60+0 -> 132130.29 | O64: =I56+I57+I58+I59+I60+0 -> 2395.41 | P64: =K56+K57+K58+K59+K60+0 -> 132130.29
A66: 4 | B66: =Source!F34 -> 6.65-11-5 | C66: Разборка трубопроводов центрального отопления на сварке диаметром труб до 100 мм | D66: =Source!H34 -> 100 м | E66: =Source!I34 -> 0.32 | Q66: =Source!X34 -> 234.93 | R66: =Source!X35 -> 13238.09 | S66: =Source!Y34 -> 118.81 | T66: =Source!Y35 -> 6695.12 | U66: =ROUND((175/100)*ROUND(Source!R34, 2), 2) -> 0 | V66: =ROUND((0/100)*ROUND(Source!R35, 2), 2) -> 0 | AC66: 0
C67: ="Объем: "&Source!I34&"=(16+"&"16)/"&"100" -> Объем: 0,32=(16+16)/100
C68: ЗП | F68: =Source!AO34 -> 819.08 | G68: 0,82*1,2 | H68: =Source!AV35 -> 1.047 | I68: =Source!S34 -> 270.03 | J68: =IF(Source!BA35<> 0, Source!BA35, 1) -> 56.35 | K68: =Source!S35 -> 15216.19
C69: ЭМ | F69: =Source!AM34 -> 1.82 | G69: 1,2 | H69: =Source!AV35 -> 1.047 | I69: =Source!Q34 -> 0.73 | J69: =IF(Source!BB35<> 0, Source!BB35, 1) -> 9.29 | K69: =Source!Q35 -> 6.78
C70: МР | F70: =Source!AL34 -> 76.84 | H70: =Source!AW35 -> 1 | I70: =Source!P34 -> 24.59 | J70: =IF(Source!BC35<> 0, Source!BC35, 1) -> 15.53 | K70: =Source!P35 -> 381.88
C71: НР от ФОТ | D71: % | E71: =Source!BZ35 -> 87 | I71: =SUM(Q66:Q70) -> 234.93 | J71: =Source!AT35 -> 87 | K71: =SUM(R66:R70) -> 13238.09
C72: СП от ФОТ | D72: % | E72: =Source!CA35 -> 44 | I72: =SUM(S66:S71) -> 118.81 | J72: =Source!AU35 -> 44 | K72: =SUM(T66:T71) -> 6695.12
C73: ЗТР | D73: чел-ч | E73: =Source!AQ34 -> 74.53 | G73: 0,82*1,2 | H73: =Source!AV35 -> 1.047 | I73: =Source!U34 -> 24.571003
C74: ВСЕГО работ по позиции: | H74: =I68+I69+I70+I71+I72+0-0-0 -> 649.09 | J74: =K68+K69+K70+K71+K72+0-0-0 -> 35538.06
C75: ВСЕГО оборудование по позиции: | H75: =0+0 -> 0 | J75: =0+0 -> 0
C76: ВСЕГО по позиции: | H76: =I68+I69+I70+I71+I72+0 -> 649.09 | J76: =K68+K69+K70+K71+K72+0 -> 35538.06 | O76: =I68+I69+I70+I71+I72+0 -> 649.09 | P76: =K68+K69+K70+K71+K72+0 -> 35538.06
A78: 5 | B78: =Source!F36 -> 3.16-40-1 | C78: Прокладка напорного трубопровода водоснабжения и отопления из многослойного полипропилена, армированного стекловолокном, из заранее собранных узлов, наружный диаметр 20 мм (демонтаж) | D78: =Source!H36 -> 100 м | E78: =Source!I36 -> 0.73 | Q78: =Source!X36 -> 73.68 | R78: =Source!X37 -> 4152.09 | S78: =Source!Y36 -> 41.24 | T78: =Source!Y37 -> 2323.65 | U78: =ROUND((175/100)*ROUND(Source!R36, 2), 2) -> 0.33 | V78: =ROUND((0/100)*ROUND(Source!R37, 2), 2) -> 0 | AC78: 0
C79: ="Объем: "&Source!I36&"=(43+"&"30)/"&"100" -> Объем: 0,73=(43+30)/100
C80: ЗП | F80: =Source!AO36 -> 180.31 | G80: 0,4*1,2 | H80: =Source!AV37 -> 1.067 | I80: =Source!S36 -> 67.41 | J80: =IF(Source!BA37<> 0, Source!BA37, 1) -> 56.35 | K80: =Source!S37 -> 3798.55
C81: ЭМ | F81: =Source!AM36 -> 18.38 | G81: 0,4*1,2 | H81: =Source!AV37 -> 1.067 | I81: =Source!Q36 -> 6.87 | J81: =IF(Source!BB37<> 0, Source!BB37, 1) -> 12.26 | K81: =Source!Q37 -> 84.23
C82: в т.ч. ЗПМ | F82: =Source!AN36 -> 0.5 | G82: 0,4*1,2 | H82: =Source!AV37 -> 1.067 | I82: =Source!R36 -> 0.19 | J82: =IF(Source!BS37<> 0, Source!BS37, 1) -> 56.35 | K82: =Source!R37 -> 10.71
C83: НР от ФОТ | D83: % | E83: =Source!BZ37 -> 109 | I83: =SUM(Q78:Q82) -> 73.68 | J83: =Source!AT37 -> 109 | K83: =SUM(R78:R82) -> 4152.09
C84: СП от ФОТ | D84: % | E84: =Source!CA37 -> 61 | I84: =SUM(S78:S83) -> 41.24 | J84: =Source!AU37 -> 61 | K84: =SUM(T78:T83) -> 2323.65
C85: ЗТР | D85: чел-ч | E85: =Source!AQ36 -> 14.56 | G85: 0,4*1,2 | H85: =Source!AV37 -> 1.067 | I85: =Source!U36 -> 5.4436462
C86: ВСЕГО работ по позиции: | H86: =I80+I81+I83+I84+0-0-0 -> 189.2 | J86: =K80+K81+K83+K84+0-0-0 -> 10358.52
C87: ВСЕГО оборудование по позиции: | H87: =0+0 -> 0 | J87: =0+0 -> 0
C88: ВСЕГО по позиции: | H88: =I80+I81+I83+I84+0 -> 189.2 | J88: =K80+K81+K83+K84+0 -> 10358.52 | O88: =I80+I81+I83+I84+0 -> 189.2 | P88: =K80+K81+K83+K84+0 -> 10358.52
A90: 6 | B90: =Source!F38 -> 3.16-40-2 | C90: Прокладка напорного трубопровода водоснабжения и отопления из многослойного полипропилена, армированного стекловолокном, из заранее собранных узлов, наружный диаметр 25 мм (демонтаж) | D90: =Source!H38 -> 100 м | E90: =Source!I38 -> 1.75 | Q90: =Source!X38 -> 170.8 | R90: =Source!X39 -> 9624.75 | S90: =Source!Y38 -> 95.59 | T90: =Source!Y39 -> 5386.33 | U90: =ROUND((175/100)*ROUND(Source!R38, 2), 2) -> 1.19 | V90: =ROUND((0/100)*ROUND(Source!R39, 2), 2) -> 0 | AC90: 0
C91: ="Объем: "&Source!I38&"=(145+"&"30)/"&"100" -> Объем: 1,75=(145+30)/100
C92: ЗП | F92: =Source!AO38 -> 174.07 | G92: 0,4*1,2 | H92: =Source!AV39 -> 1.067 | I92: =Source!S38 -> 156.02 | J92: =IF(Source!BA39<> 0, Source!BA39, 1) -> 56.35 | K92: =Source!S39 -> 8791.73
C93: ЭМ | F93: =Source!AM38 -> 19.67 | G93: 0,4*1,2 | H93: =Source!AV39 -> 1.067 | I93: =Source!Q38 -> 17.63 | J93: =IF(Source!BB39<> 0, Source!BB39, 1) -> 12.72 | K93: =Source!Q39 -> 224.25
C94: в т.ч. ЗПМ | F94: =Source!AN38 -> 0.76 | G94: 0,4*1,2 | H94: =Source!AV39 -> 1.067 | I94: =Source!R38 -> 0.68 | J94: =IF(Source!BS39<> 0, Source!BS39, 1) -> 56.35 | K94: =Source!R39 -> 38.32
C95: НР от ФОТ | D95: % | E95: =Source!BZ39 -> 109 | I95: =SUM(Q90:Q94) -> 170.8 | J95: =Source!AT39 -> 109 | K95: =SUM(R90:R94) -> 9624.75
C96: СП от ФОТ | D96: % | E96: =Source!CA39 -> 61 | I96: =SUM(S90:S95) -> 95.59 | J96: =Source!AU39 -> 61 | K96: =SUM(T90:T95) -> 5386.33
C97: ЗТР | D97: чел-ч | E97: =Source!AQ38 -> 14.08 | G97: 0,4*1,2 | H97: =Source!AV39 -> 1.067 | I97: =Source!U38 -> 12.619622
C98: ВСЕГО работ по позиции: | H98: =I92+I93+I95+I96+0-0-0 -> 440.04 | J98: =K92+K93+K95+K96+0-0-0 -> 24027.06
C99: ВСЕГО оборудование по позиции: | H99: =0+0 -> 0 | J99: =0+0 -> 0
C100: ВСЕГО по позиции: | H100: =I92+I93+I95+I96+0 -> 440.04 | J100: =K92+K93+K95+K96+0 -> 24027.06 | O100: =I92+I93+I95+I96+0 -> 440.04 | P100: =K92+K93+K95+K96+0 -> 24027.06
A102: 7 | B102: =Source!F40 -> 6.66-162-1 | C102: Разборка тепловой изоляции из плит, сегментов и скорлуп | D102: =Source!H40 -> 100 м2 | E102: =Source!I40 -> 1.6074 | Q102: =Source!X40 -> 265.31 | R102: =Source!X41 -> 14950.17 | S102: =Source!Y40 -> 131.16 | T102: =Source!Y41 -> 7391.09 | U102: =ROUND((175/100)*ROUND(Source!R40, 2), 2) -> 0 | V102: =ROUND((0/100)*ROUND(Source!R41, 2), 2) -> 0 | AC102: 0
C103: ="Объем: "&Source!I40&"=((18+"&"75+"&"90)*"&"0,11+"&"(40+"&"90+"&"100)*"&"0,13+"&"(30+"&"75+"&"54)*"&"0,16+"&"(20+"&"50+"&"45)*"&"0,18+"&"55*"&"0,21+"&"110*"&"0,26+"&"16*"&"0,37+"&"3,3+"&"8,7+"&"2,5+"&"4)/"&"100" -> Объем: 1,6074=((18+75+90)*0,11+(40+90+100)*0,13+(30+75+54)*0,16+(20+50+45)*0,18+55*0,21+110*0,26+16*0,37+3,3+8,7+2,5+4)/100
C104: ЗП | F104: =Source!AO40 -> 144.84 | G104: 1,2 | H104: =Source!AV41 -> 1.067 | I104: =Source!S40 -> 298.1 | J104: =IF(Source!BA41<> 0, Source!BA41, 1) -> 56.35 | K104: =Source!S41 -> 16797.94
C105: НР от ФОТ | D105: % | E105: =Source!BZ41 -> 89 | I105: =SUM(Q102:Q104) -> 265.31 | J105: =Source!AT41 -> 89 | K105: =SUM(R102:R104) -> 14950.17
C106: СП от ФОТ | D106: % | E106: =Source!CA41 -> 44 | I106: =SUM(S102:S105) -> 131.16 | J106: =Source!AU41 -> 44 | K106: =SUM(T102:T105) -> 7391.09
C107: ЗТР | D107: чел-ч | E107: =Source!AQ40 -> 13.3 | G107: 1,2 | H107: =Source!AV41 -> 1.067 | I107: =Source!U40 -> 27.372929
C108: ВСЕГО работ по позиции: | H108: =I104+I105+I106+0-0-0 -> 694.57 | J108: =K104+K105+K106+0-0-0 -> 39139.2
C109: ВСЕГО оборудование по позиции: | H109: =0+0 -> 0 | J109: =0+0 -> 0
C110: ВСЕГО по позиции: | H110: =I104+I105+I106+0 -> 694.57 | J110: =K104+K105+K106+0 -> 39139.2 | O110: =I104+I105+I106+0 -> 694.57 | P110: =K104+K105+K106+0 -> 39139.2
A112: 8 | B112: =Source!F42 -> 6.65-3-4 | C112: Демонтаж задвижки фланцевой диаметром 100 мм | D112: =Source!H42 -> 100 шт. | E112: =Source!I42 -> 0.03 | Q112: =Source!X42 -> 70.03 | R112: =Source!X43 -> 3945.98 | S112: =Source!Y42 -> 35.42 | T112: =Source!Y43 -> 1995.67 | U112: =ROUND((175/100)*ROUND(Source!R42, 2), 2) -> 0 | V112: =ROUND((0/100)*ROUND(Source!R43, 2), 2) -> 0 | AC112: 0
C113: ="Объем: "&Source!I42&"=3/"&"100" -> Объем: 0,03=3/100
...

Sheet Source
A1: 0 | B1: Smeta.RU (495) 974-1589 | D1: _PS_ | F1: 0 | G1: 0 | H1: 0 | I1: Smeta.RU | K1: 1 | L1: 74600 | M1: 10 | N1: 12 | O1: 1 | P1: 0 | Q1: 1
A4: 8 | B4: 1 | C4: -1 | G4: Капитальный ремонт здания Государственного бюджетного общеобразовательного учреждения города Москвы «Школа №1574», расположенного по адресу: г. Москва, Старопименовский переулок, д. 5. 1 этап | EC4: 0
A12: 1 | B12: 748 | C12: 0 | D12: =ROW(A704) -> 704 | E12: 0 | F12: 02-01-04 | G12: Водоснабжение. | I12: 0 | J12: 2024-00375-01-0-ИОС2 | K12: 0 | L12: 0 | M12: 4098 | O12: 0 | P12: 0 | Q12: 0 | R12: 0 | S12: 0 | T12: 1 | V12: 0 | BB12: 0 | BH12: Сметные нормы списания | BI12: Коды ОКП для ТСН-2001 МГЭ Дополнение 81 | BJ12: 1 | BK12: 1 | BL12: 0 | BM12: 0 | BN12: 1 | BO12: 0 | BP12: 6 | BQ12: 2 | BR12: 1 | BS12: 1 | BT12: 0 | BU12: 0 | BV12: 0 | BW12: 0 | BX12: 0 | BY12: ТСН-2001 (МГЭ) Доп 81 - Ремонт | BZ12: Типовой расчет для ТСН-2001 МГЭ, Дополнение 81, ремонт | CA12: Территориальные сметные нормативы для Москвы ТСН-2001 (МГЭ), дополнение 81 | CB12: Территориальные сметные нормативы для Москвы ТСН-2001 (МГЭ), дополнение 81 | CC12: Территориальные сметные нормативы для Москвы ТСН-2001 (МГЭ), дополнение 81 | CD12: Территориальные сметные нормативы для Москвы ТСН-2001 (МГЭ), дополнение 81 | CE12: Поправки для ТСН-2001 от 07.04.2026 г. доп.81 | CF12: 0 | CG12: 0 | CH12: 8200 | CK12: 81 | CQ12: Территориальные сметные нормативы для Москвы (ТСН-2001) | CR12: ТЕР | CS12: 41660 | CT12: 1 | CU12: 81 | CY12: 0 | EC12: 0
A15: 15 | B15: 1
A18: 52 | B18: =B704 -> 748 | C18: =C704 -> 1 | D18: =D704 -> 12 | E18: =E704 -> 0 | F18: =F704 -> 02-01-04 | G18: =G704 -> Водоснабжение. | O18: =O704 -> 296424.21 | P18: =P704 -> 268991.6 | Q18: =Q704 -> 1680.25 | R18: =R704 -> 190.22 | S18: =S704 -> 25752.36 | T18: =T704 -> 0 | U18: =U704 -> 2104.7977 | V18: =V704 -> 0 | ... GX18: =GX704 -> 0
A20: 3 | B20: 1 | D20: =ROW(A671) -> 671 | F20: 02-01-04 | G20: Система водоснабжения. | I20: 0 | J20: 2024-00375-01-0-ИОС2 | K20: -1 | L20: 02-01-04 | S20: 0 | T20: 0 | V20: 0 | BX20: 0 | CF20: 0 | CG20: 0
A22: 52 | B22: =B671 -> 1 | C22: =C671 -> 3 | D22: =D671 -> 20 | E22: =E671 -> 0 | F22: =F671 -> 02-01-04 | G22: =G671 -> Система водоснабжения. | O22: =O671 -> 296424.21 | P22: =P671 -> 268991.6 | Q22: =Q671 -> 1680.25 | R22: =R671 -> 190.22 | S22: =S671 -> 25752.36 | T22: =T671 -> 0 | U22: =U671 -> 2104.7977 | V22: =V671 -> 0 | ... GX22: =GX671 -> 0
A24: 4 | B24: 1 | D24: =ROW(A49) -> 49 | F24: Новый раздел | G24: Демонтажные работы. | I24: 0 | K24: 0 | S24: 0 | T24: 0 | V24: 0 | BX24: 0 | CJ24: 0
A26: 52 | B26: =B49 -> 1 | C26: =C49 -> 4 | D26: =D49 -> 24 | E26: =E49 -> 0 | F26: =F49 -> Новый раздел | G26: =G49 -> Демонтажные работы. | O26: =O49 -> 9788.2 | P26: =P49 -> 484.79 | Q26: =Q49 -> 39.05 | R26: =R49 -> 0.87 | S26: =S49 -> 9264.36 | T26: =T49 -> 0 | U26: =U49 -> 820.47351 | V26: =V49 -> 0 | ... GX26: =GX49 -> 0
A28: 17 | B28: 1 | C28: =ROW(SmtRes!A5) -> 5 | D28: =ROW(EtalonRes!A5) -> 5 | E28: 1 | F28: 6.65-1-1 | G28: Разборка трубопроводов из водогазопроводных труб диаметром до 25 мм | H28: 100 м | I28: =ROUND((28+45+35+75+90+75+33+87+25+90+100+54)/100,9) -> 7.37 | J28: 0 | K28: =ROUND((28+45+35+75+90+75+33+87+25+90+100+54)/100,9) -> 7.37 | O28: =ROUND(CP28,2) -> 2877.96 | P28: =ROUND((ROUND((AC28*AW28*I28),2)*BC28),2) -> 239.97 | Q28: =(ROUND((ROUND((((ET28*1.2))*AV28*I28),2)*BB28),2)+ROUND((ROUND(((AE28-((EU28*1.2)))*AV28*I28),2)*BS28),2)) -> 6.48 | R28: =(ROUND((ROUND((((EU28*1.2))*AV28*I28),2)*BS28),2)+ROUND((ROUND(((AE28-((EU28*1.2)))*AV28*I28),2)*BS28),2)) -> 0 | S28: =ROUND((ROUND((AF28*AV28*I28),2)*BA28),2) -> 2631.51 | T28: =ROUND(CU28*I28,2) -> 0 | U28: =CV28*I28 -> 245.93678 | V28: =CW28*I28 -> 0 | W28: =ROUND(CX28*I28,2) -> 0 | X28: =(ROUND((((S28+ROUND((ROUND((((EU28*1.2))*AV28*I28),2)*BS28),2))*AT28)/100),2)+ROUND(((ROUND((ROUND(((AE28-((EU28*1.2)))*AV28*I28),2)*BS28),2)*AT28)/100),2)) -> 2289.41 | Y28: =(ROUND((((S28+ROUND((ROUND((((EU28*1.2))*AV28*I28),2)*BS28),2))*AU28)/100),2)+ROUND(((ROUND((ROUND(((AE28-((EU28*1.2)))*AV28*I28),2)*BS28),2)*AU28)/100),2)) -> 1157.86 | AA28: 85736471 | AB28: =ROUND((AC28+AD28+AF28),6) -> 374.428 | AC28: =ROUND(((ES28*1)),6) -> 32.56 | AD28: =ROUND(((((ET28*1.2))-((EU28*1.2)))+AE28),6) -> 0.84 | AE28: =ROUND(((EU28*1.2)),6) -> 0 | AF28: =ROUND(((EV28*1.2)),6) -> 341.028 | AG28: =ROUND((AP28),6) -> 0 | AH28: =((EW28*1.2)) -> 31.872 | AI28: =((EX28*1.2)) -> 0 | AJ28: =(AS28) -> 0 | AK28: 317.45 | AL28: 32.56 | AM28: 0.7 | AN28: 0 | AO28: 284.19 | AP28: 0 | AQ28: 26.56 | AR28: 0 | AS28: 0 | AT28: 87 | AU28: 44 | AV28: 1.047 | AW28: 1 | AZ28: 1 | BA28: 1 | BB28: 1 | BC28: 1 | BH28: 0 | BI28: 1 | BJ28: ТСН-2001.6 Доп. 79, Сб. 65, т. 1, поз. 1 | BM28: 102 | BN28: 0 | BO28: 6.65-1-1 | BP28: 1 | BQ28: 60 | BR28: 0 | BS28: 1 | BT28: 1 | BU28: 1 | BV28: 1 | BW28: 1 | BX28: 1 | BZ28: 87 | CA28: 44 | CE28: 1566 | CF28: 0 | CG28: 0 | CM28: 0 | CN28: Поправка: Гл.12.Прил.8.п.8. 3_12.00.01.11.001 Наименование: При наличии напряженных и стесненных условий производства работ (стесненность, сложность складирования и транспортной логистики и т.п.) для объектов, расположенных в пределах круговой магистральной системы улиц "Садовое кольцо" города Москвы | CO28: 0 | CP28: =(P28+Q28+S28) -> 2877.96 | CQ28: =ROUND((ROUND((AC28*AW28*1),2)*BC28),2) -> 32.56 | CR28: =(ROUND((ROUND((((ET28*1.2))*AV28*1),2)*BB28),2)+ROUND((ROUND(((AE28-((EU28*1.2)))*AV28*1),2)*BS28),2)) -> 0.88 | CS28: =(ROUND((ROUND((((EU28*1.2))*AV28*1),2)*BS28),2)+ROUND((ROUND(((AE28-((EU28*1.2)))*AV28*1),2)*BS28),2)) -> 0 | CT28: =ROUND((ROUND((AF28*AV28*1),2)*BA28),2) -> 357.06 | CU28: =AG28 -> 0 | CV28: =(AH28*AV28) -> 33.369984 | CW28: =AI28 -> 0 | CX28: =AJ28 -> 0 | CY28: =(ROUND((((S28+ROUND((ROUND((((EU28*1.2))*AV28*1),2)*BS28),2))*AT28)/100),2)+ROUND(((ROUND((ROUND(((AE28-((EU28*1.2)))*AV28*1),2)*BS28),2)*AT28)/100),2)) -> 2289.41 | CZ28: =(ROUND((((S28+ROUND((ROUND((((EU28*1.2))*AV28*1),2)*BS28),2))*AU28)/100),2)+ROUND(((ROUND((ROUND(((AE28-((EU28*1.2)))*AV28*1),2)*BS28),2)*AU28)/100),2)) -> 1157.86 | DB28: 1 | DD28: *1 | DE28: *1,2 | DF28: *1,2 | DG28: *1,2 | DI28: *1,2 | DJ28: *1,2 | DN28: 0 | DO28: 0 | DP28: 1 | DQ28: 1 | DU28: 1003 | DV28: 100 м | DW28: 100 м | DX28: 100 | EE28: 85133723 | EF28: 60 | EG28: Ремонтно-строительные работы | EH28: 0 | EJ28: 1 | EK28: 102 | EL28: ТСН-2001.6-65. Внутренние санитарно-технические работы: демонтаж и разборка | EM28: ТСН-2001.6-65-1 | EO28: Поправка: Гл.12.Прил.8.п.8. 3_12.00.01.11.001 | EQ28: 0 | ER28: 317.45 | ES28: 32.56 | ET28: 0.7 | EU28: 0 | EV28: 284.19 | EW28: 26.56 | EX28: 0 | EY28: 0 | FQ28: 0 | FR28: 0 | FS28: 0 | FX28: 87 | FY28: 44 | GD28: 1 | GF28: 1544923571 | GG28: 2 | GH28: 1 | GI28: 2 | GJ28: 0 | GK28: 0 | GL28: =ROUND(IF(AND(BH28=3,BI28=3,FS28<>0),P28,0),2) -> 0 | GM28: =ROUND(O28+X28+Y28,2)+GX28 -> 6325.23 | GN28: =IF(OR(BI28=0,BI28=1),GM28-GX28,0) -> 6325.23 | GO28: =IF(BI28=2,GM28-GX28,0) -> 0 | GP28: =IF(BI28=4,GM28-GX28,0) -> 0 | GR28: 0 | GS28: 3 | GT28: 0 | GV28: =ROUND((GT28),6) -> 0 | GW28: 1 | GX28: =ROUND(HC28*I28,2) -> 0 | HA28: 0 | HB28: 0 | HC28: =GV28*GW28 -> 0 | HS28: 0 | IK28: 0
A29: 17 | B29: 1 | C29: =ROW(SmtRes!A10) -> 10 | D29: =ROW(EtalonRes!A10) -> 10 | E29: 1 | F29: 6.65-1-1 | G29: Разборка трубопроводов из водогазопроводных труб диаметром до 25 мм | H29: 100 м | I29: =ROUND((28+45+35+75+90+75+33+87+25+90+100+54)/100,9) -> 7.37 | J29: 0 | K29: =ROUND((28+45+35+75+90+75+33+87+25+90+100+54)/100,9) -> 7.37 | O29: =ROUND(CP29,2) -> 152072.52 | P29: =ROUND((ROUND((AC29*AW29*I29),2)*BC29),2) -> 3726.73 | Q29: =(ROUND((ROUND((((ET29*1.2))*AV29*I29),2)*BB29),2)+ROUND((ROUND(((AE29-((EU29*1.2)))*AV29*I29),2)*BS29),2)) -> 60.2 | R29: =(ROUND((ROUND((((EU29*1.2))*AV29*I29),2)*BS29),2)+ROUND((ROUND(((AE29-((EU29*1.2)))*AV29*I29),2)*BS29),2)) -> 0 | S29: =ROUND((ROUND((AF29*AV29*I29),2)*BA29),2) -> 148285.59 | T29: =ROUND(CU29*I29,2) -> 0 | U29: =CV29*I29 -> 245.93678 | V29: =CW29*I29 -> 0 | W29: =ROUND(CX29*I29,2) -> 0 | X29: =(ROUND((((S29+ROUND((ROUND((((EU29*1.2))*AV29*I29),2)*BS29),2))*AT29)/100),2)+ROUND(((ROUND((ROUND(((AE29-((EU29*1.2)))*AV29*I29),2)*BS29),2)*AT29)/100),2)) -> 129008.46 | Y29: =(ROUND((((S29+ROUND((ROUND((((EU29*1.2))*AV29*I29),2)*BS29),2))*AU29)/100),2)+ROUND(((ROUND((ROUND(((AE29-((EU29*1.2)))*AV29*I29),2)*BS29),2)*AU29)/100),2)) -> 65245.66 | AA29: 85736473 | AB29: =ROUND((AC29+AD29+AF29),6) -> 374.428 | AC29: =ROUND(((ES29*1)),6) -> 32.56 | AD29: =ROUND(((((ET29*1.2))-((EU29*1.2)))+AE29),6) -> 0.84 | AE29: =ROUND(((EU29*1.2)),6) -> 0 | AF29: =ROUND(((EV29*1.2)),6) -> 341.028 | AG29: =ROUND((AP29),6) -> 0 | AH29: =((EW29*1.2)) -> 31.872 | AI29: =((EX29*1.2)) -> 0 | AJ29: =(AS29) -> 0 | AK29: 317.45 | AL29: 32.56 | AM29: 0.7 | AN29: 0 | AO29: 284.19 | AP29: 0 | AQ29: 26.56 | AR29: 0 | AS29: 0 | AT29: 87 | AU29: 44 | AV29: 1.047 | AW29: 1 | AZ29: 1 | BA29: 56.35 | BB29: 9.29 | BC29: 15.53 | BH29: 0 | BI29: 1 | BJ29: ТСН-2001.6 Доп. 79, Сб. 65, т. 1, поз. 1 | BM29: 102 | BN29: 0 | BO29: 6.65-1-1 | BP29: 1 | BQ29: 60 | BR29: 0 | BS29: 56.35 | BT29: 1 | BU29: 1 | BV29: 1 | BW29: 1 | BX29: 1 | BZ29: 87 | CA29: 44 | CE29: 1566 | CF29: 0 | CG29: 0 | CM29: 0 | CN29: Поправка: Гл.12.Прил.8.п.8. 3_12.00.01.11.001 Наименование: При наличии напряженных и стесненных условий производства работ (стесненность, сложность складирования и транспортной логистики и т.п.) для объектов, расположенных в пределах круговой магистральной системы улиц "Садовое кольцо" города Москвы | CO29: 0 | CP29: =(P29+Q29+S29) -> 152072.52 | CQ29: =ROUND((ROUND((AC29*AW29*1),2)*BC29),2) -> 505.66 | CR29: =(ROUND((ROUND((((ET29*1.2))*AV29*1),2)*BB29),2)+ROUND((ROUND(((AE29-((EU29*1.2)))*AV29*1),2)*BS29),2)) -> 8.18 | CS29: =(ROUND((ROUND((((EU29*1.2))*AV29*1),2)*BS29),2)+ROUND((ROUND(((AE29-((EU29*1.2)))*AV29*1),2)*BS29),2)) -> 0 | CT29: =ROUND((ROUND((AF29*AV29*1),2)*BA29),2) -> 20120.33 | CU29: =AG29 -> 0 | CV29: =(AH29*AV29) -> 33.369984 | CW29: =AI29 -> 0 | CX29: =AJ29 -> 0 | CY29: =(ROUND((((S29+ROUND((ROUND((((EU29*1.2))*AV29*1),2)*BS29),2))*AT29)/100),2)+ROUND(((ROUND((ROUND(((AE29-((EU29*1.2)))*AV29*1),2)*BS29),2)*AT29)/100),2)) -> 129008.46 | CZ29: =(ROUND((((S29+ROUND((ROUND((((EU29*1.2))*AV29*1),2)*BS29),2))*AU29)/100),2)+ROUND(((ROUND((ROUND(((AE29-((EU29*1.2)))*AV29*1),2)*BS29),2)*AU29)/100),2)) -> 65245.66 | DB29: 2 | DD29: *1 | DE29: *1,2 | DF29: *1,2 | DG29: *1,2 | DI29: *1,2 | DJ29: *1,2 | DN29: 0 | DO29: 0 | DP29: 1 | DQ29: 1 | DU29: 1003 | DV29: 100 м | DW29: 100 м | DX29: 100 | EE29: 85133723 | EF29: 60 | EG29: Ремонтно-строительные работы | EH29: 0 | EJ29: 1 | EK29: 102 | EL29: ТСН-2001.6-65. Внутренние санитарно-технические работы: демонтаж и разборка | EM29: ТСН-2001.6-65-1 | EO29: Поправка: Гл.12.Прил.8.п.8. 3_12.00.01.11.001 | EQ29: 0 | ER29: 317.45 | ES29: 32.56 | ET29: 0.7 | EU29: 0 | EV29: 284.19 | EW29: 26.56 | EX29: 0 | EY29: 0 | FQ29: 0 | FR29: 0 | FS29: 0 | FX29: 87 | FY29: 44 | GD29: 1 | GF29: 1544923571 | GG29: 2 | GH29: 1 | GI29: 2 | GJ29: 0 | GK29: 0 | GL29: =ROUND(IF(AND(BH29=3,BI29=3,FS29<>0),P29,0),2) -> 0 | GM29: =ROUND(O29+X29+Y29,2)+GX29 -> 346326.64 | GN29: =IF(OR(BI29=0,BI29=1),GM29-GX29,0) -> 346326.64 | GO29: =IF(BI29=2,GM29-GX29,0) -> 0 | GP29: =IF(BI29=4,GM29-GX29,0) -> 0 | GR29: 0 | GS29: 3 | GT29: 0 | GV29: =ROUND((GT29),6) -> 0 | GW29: 1 | GX29: =ROUND(HC29*I29,2) -> 0 | HA29: 0 | HB29: 0 | HC29: =GV29*GW29 -> 0 | HS29: 0 | IK29: 0
A30: 17 | B30: 1 | C30: =ROW(SmtRes!A15) -> 15 | D30: =ROW(EtalonRes!A15) -> 15 | E30: 2 | F30: 6.65-1-2 | G30: Разборка трубопроводов из водогазопроводных труб диаметром до 40 мм | H30: 100 м | I30: =ROUND((22+55+50+64+95+45)/100,9) -> 3.31 | J30: 0 | K30: =ROUND((22+55+50+64+95+45)/100,9) -> 3.31 | O30: =ROUND(CP30,2) -> 2219.53 | P30: =ROUND((ROUND((AC30*AW30*I30),2)*BC30),2) -> 152.79 | Q30: =(ROUND((ROUND((((ET30*1.2))*AV30*I30),2)*BB30),2)+ROUND((ROUND(((AE30-((EU30*1.2)))*AV30*I30),2)*BS30),2)) -> 5.24 | R30: =(ROUND((ROUND((((EU30*1.2))*AV30*I30),2)*BS30),2)+ROUND((ROUND(((AE30-((EU30*1.2)))*AV30*I30),2)*BS30),2)) -> 0 | S30: =ROUND((ROUND((AF30*AV30*I30),2)*BA30),2) -> 2061.5 | T30: =ROUND(CU30*I30,2) -> 0 | U30: =CV30*I30 -> 189.3033 | V30: =CW30*I30 -> 0 | W30: =ROUND(CX30*I30,2) -> 0 | X30: =(ROUND((((S30+ROUND((ROUND((((EU30*1.2))*AV30*I30),2)*BS30),2))*AT30)/100),2)+ROUND(((ROUND((ROUND(((AE30-((EU30*1.2)))*AV30*I30),2)*BS30),2)*AT30)/100),2)) -> 1793.51 | Y30: =(ROUND((((S30+ROUND((ROUND((((EU30*1.2))*AV30*I30),2)*BS30),2))*AU30)/100),2)+ROUND(((ROUND((ROUND(((AE30-((EU30*1.2)))*AV30*I30),2)*BS30),2)*AU30)/100),2)) -> 907.06 | AA30: 85736471 | AB30: =ROUND((AC30+AD30+AF30),6) -> 642.524 | AC30: =ROUND(((ES30*1)),6) -> 46.16 | AD30: =ROUND(((((ET30*1.2))-((EU30*1.2)))+AE30),6) -> 1.512 | AE30: =ROUND(((EU30*1.2)),6) -> 0 | AF30: =ROUND(((EV30*1.2)),6) -> 594.852 | AG30: =ROUND((AP30),6) -> 0 | AH30: =((EW30*1.2)) -> 54.624 | AI30: =((EX30*1.2)) -> 0 | AJ30: =(AS30) -> 0 | AK30: 543.13 | AL30: 46.16 | AM30: 1.26 | AN30: 0 | AO30: 495.71 | AP30: 0 | AQ30: 45.52 | AR30: 0 | AS30: 0 | AT30: 87 | AU30: 44 | AV30: 1.047 | AW30: 1 | AZ30: 1 | BA30: 1 | BB30: 1 | BC30: 1 | BH30: 0 | BI30: 1 | BJ30: ТСН-2001.6 Доп. 79, Сб. 65, т. 1, поз. 2 | BM30: 102 | BN30: 0 | BO30: 6.65-1-2 | BP30: 1 | BQ30: 60 | BR30: 0 | BS30: 1 | BT30: 1 | BU30: 1 | BV30: 1 | BW30: 1 | BX30: 1 | BZ30: 87 | CA30: 44 | CE30: 1566 | CF30: 0 | CG30: 0 | CM30: 0 | CN30: Поправка: Гл.12.Прил.8.п.8. 3_12.00.01.11.001 Наименование: При наличии напряженных и стесненных условий производства работ (стесненность, сложность складирования и транспортной логистики и т.п.) для объектов, расположенных в пределах круговой магистральной системы улиц "Садовое кольцо" города Москвы | CO30: 0 | CP30: =(P30+Q30+S30) -> 2219.53 | CQ30: =ROUND((ROUND((AC30*AW30*1),2)*BC30),2) -> 46.16 | CR30: =(ROUND((ROUND((((ET30*1.2))*AV30*1),2)*BB30),2)+ROUND((ROUND(((AE30-((EU30*1.2)))*AV30*1),2)*BS30),2)) -> 1.58 | CS30: =(ROUND((ROUND((((EU30*1.2))*AV30*1),2)*BS30),2)+ROUND((ROUND(((AE30-((EU30*1.2)))*AV30*1),2)*BS30),2)) -> 0 | CT30: =ROUND((ROUND((AF30*AV30*1),2)*BA30),2) -> 622.81 | CU30: =AG30 -> 0 | CV30: =(AH30*AV30) -> 57.191328 | CW30: =AI30 -> 0 | CX30: =AJ30 -> 0 | CY30: =(ROUND((((S30+ROUND((ROUND((((EU30*1.2))*AV30*1),2)*BS30),2))*AT30)/100),2)+ROUND(((ROUND((ROUND(((AE30-((EU30*1.2)))*AV30*1),2)*BS30),2)*AT30)/100),2)) -> 1793.51 | CZ30: =(ROUND((((S30+ROUND((ROUND((((EU30*1.2))*AV30*1),2)*BS30),2))*AU30)/100),2)+ROUND(((ROUND((ROUND(((AE30-((EU30*1.2)))*AV30*1),2)*BS30),2)*AU30)/100),2)) -> 907.06 | DB30: 3 | DD30: *1 | DE30: *1,2 | DF30: *1,2 | DG30: *1,2 | DI30: *1,2 | DJ30: *1,2 | DN30: 0 | DO30: 0 | DP30: 1 | DQ30: 1 | DU30: 1003 | DV30: 100 м | DW30: 100 м | DX30: 100 | EE30: 85133723 | EF30: 60 | EG30: Ремонтно-строительные работы | EH30: 0 | EJ30: 1 | EK30: 102 | EL30: ТСН-2001.6-65. Внутренние санитарно-технические работы: демонтаж и разборка | EM30: ТСН-2001.6-65-1 | EO30: Поправка: Гл.12.Прил.8.п.8. 3_12.00.01.11.001 | EQ30: 0 | ER30: 543.13 | ES30: 46.16 | ET30: 1.26 | EU30: 0 | EV30: 495.71 | EW30: 45.52 | EX30: 0 | EY30: 0 | FQ30: 0 | FR30: 0 | FS30: 0 | FX30: 87 | FY30: 44 | GD30: 1 | GF30: -1242219818 | GG30: 2 | GH30: 1 | GI30: 2 | GJ30: 0 | GK30: 0 | GL30: =ROUND(IF(AND(BH30=3,BI30=3,FS30<>0),P30,0),2) -> 0 | GM30: =ROUND(O30+X30+Y30,2)+GX30 -> 4920.1 | GN30: =IF(OR(BI30=0,BI30=1),GM30-GX30,0) -> 4920.1 | GO30: =IF(BI30=2,GM30-GX30,0) -> 0 | GP30: =IF(BI30=4,GM30-GX30,0) -> 0 | GR30: 0 | GS30: 3 | GT30: 0 | GV30: =ROUND((GT30),6) -> 0 | GW30: 1 | GX30: =ROUND(HC30*I30,2) -> 0 | HA30: 0 | HB30: 0 | HC30: =GV30*GW30 -> 0 | HS30: 0 | IK30: 0
A31: 17 | B31: 1 | C31: =ROW(SmtRes!A20) -> 20 | D31: =ROW(EtalonRes!A20) -> 20 | E31: 2 | F31: 6.65-1-2 | G31: Разборка трубопроводов из водогазопроводных труб диаметром до 40 мм | H31: 100 м | I31: =ROUND((22+55+50+64+95+45)/100,9) -> 3.31 | J31: 0 | K31: =ROUND((22+55+50+64+95+45)/100,9) -> 3.31 | O31: =ROUND(CP31,2) -> 118587.04 | P31: =ROUND((ROUND((AC31*AW31*I31),2)*BC31),2) -> 2372.83 | Q31: =(ROUND((ROUND((((ET31*1.2))*AV31*I31),2)*BB31),2)+ROUND((ROUND(((AE31-((EU31*1.2)))*AV31*I31),2)*BS31),2)) -> 48.68 | R31: =(ROUND((ROUND((((EU31*1.2))*AV31*I31),2)*BS31),2)+ROUND((ROUND(((AE31-((EU31*1.2)))*AV31*I31),2)*BS31),2)) -> 0 | S31: =ROUND((ROUND((AF31*AV31*I31),2)*BA31),2) -> 116165.53 | T31: =ROUND(CU31*I31,2) -> 0 | U31: =CV31*I31 -> 189.3033 | V31: =CW31*I31 -> 0 | W31: =ROUND(CX31*I31,2) -> 0 | X31: =(ROUND((((S31+ROUND((ROUND((((EU31*1.2))*AV31*I31),2)*BS31),2))*AT31)/100),2)+ROUND(((ROUND((ROUND(((AE31-((EU31*1.2)))*AV31*I31),2)*BS31),2)*AT31)/100),2)) -> 101064.01 | Y31: =(ROUND((((S31+ROUND((ROUND((((EU31*1.2))*AV31*I31),2)*BS31),2))*AU31)/100),2)+ROUND(((ROUND((ROUND(((AE31-((EU31*1.2)))*AV31*I31),2)*BS31),2)*AU31)/100),2)) -> 51112.83 | AA31: 85736473 | AB31: =ROUND((AC31+AD31+AF31),6) -> 642.524 | AC31: =ROUND(((ES31*1)),6) -> 46.16 | AD31: =ROUND(((((ET31*1.2))-((EU31*1.2)))+AE31),6) -> 1.512 | AE31: =ROUND(((EU31*1.2)),6) -> 0 | AF31: =ROUND(((EV31*1.2)),6) -> 594.852 | AG31: =ROUND((AP31),6) -> 0 | AH31: =((EW31*1.2)) -> 54.624 | AI31: =((EX31*1.2)) -> 0 | AJ31: =(AS31) -> 0 | AK31: 543.13 | AL31: 46.16 | AM31: 1.26 | AN31: 0 | AO31: 495.71 | AP31: 0 | AQ31: 45.52 | AR31: 0 | AS31: 0 | AT31: 87 | AU31: 44 | AV31: 1.047 | AW31: 1 | AZ31: 1 | BA31: 56.35 | BB31: 9.29 | BC31: 15.53 | BH31: 0 | BI31: 1 | BJ31: ТСН-2001.6 Доп. 79, Сб. 65, т. 1, поз. 2 | BM31: 102 | BN31: 0 | BO31: 6.65-1-2 | BP31: 1 | BQ31: 60 | BR31: 0 | BS31: 56.35 | BT31: 1 | BU31: 1 | BV31: 1 | BW31: 1 | BX31: 1 | BZ31: 87 | CA31: 44 | CE31: 1566 | CF31: 0 | CG31: 0 | CM31: 0 | CN31: Поправка: Гл.12.Прил.8.п.8. 3_12.00.01.11.001 Наименование: При наличии напряженных и стесненных условий производства работ (стесненность, сложность складирования и транспортной логистики и т.п.) для объектов, расположенных в пределах круговой магистральной системы улиц "Садовое кольцо" города Москвы | CO31: 0 | CP31: =(P31+Q31+S31) -> 118587.04 | CQ31: =ROUND((ROUND((AC31*AW31*1),2)*BC31),2) -> 716.86 | CR31: =(ROUND((ROUND((((ET31*1.2))*AV31*1),2)*BB31),2)+ROUND((ROUND(((AE31-((EU31*1.2)))*AV31*1),2)*BS31),2)) -> 14.68 | CS31: =(ROUND((ROUND((((EU31*1.2))*AV31*1),2)*BS31),2)+ROUND((ROUND(((AE31-((EU31*1.2)))*AV31*1),2)*BS31),2)) -> 0 | CT31: =ROUND((ROUND((AF31*AV31*1),2)*BA31),2) -> 35095.34 | CU31: =AG31 -> 0 | CV31: =(AH31*AV31) -> 57.191328 | CW31: =AI31 -> 0 | CX31: =AJ31 -> 0 | CY31: =(ROUND((((S31+ROUND((ROUND((((EU31*1.2))*AV31*1),2)*BS31),2))*AT31)/100),2)+ROUND(((ROUND((ROUND(((AE31-((EU31*1.2)))*AV31*1),2)*BS31),2)*AT31)/100),2)) -> 101064.01 | CZ31: =(ROUND((((S31+ROUND((ROUND((((EU31*1.2))*AV31*1),2)*BS31),2))*AU31)/100),2)+ROUND(((ROUND((ROUND(((AE31-((EU31*1.2)))*AV31*1),2)*BS31),2)*AU31)/100),2)) -> 51112.83 | DB31: 4 | DD31: *1 | DE31: *1,2 | DF31: *1,2 | DG31: *1,2 | DI31: *1,2 | DJ31: *1,2 | DN31: 0 | DO31: 0 | DP31: 1 | DQ31: 1 | DU31: 1003 | DV31: 100 м | DW31: 100 м | DX31: 100 | EE31: 85133723 | EF31: 60 | EG31: Ремонтно-строительные работы | EH31: 0 | EJ31: 1 | EK31: 102 | EL31: ТСН-2001.6-65. Внутренние санитарно-технические работы: демонтаж и разборка | EM31: ТСН-2001.6-65-1 | EO31: Поправка: Гл.12.Прил.8.п.8. 3_12.00.01.11.001 | EQ31: 0 | ER31: 543.13 | ES31: 46.16 | ET31: 1.26 | EU31: 0 | EV31: 495.71 | EW31: 45.52 | EX31: 0 | EY31: 0 | FQ31: 0 | FR31: 0 | FS31: 0 | FX31: 87 | FY31: 44 | GD31: 1 | GF31: -1242219818 | GG31: 2 | GH31: 1 | GI31: 2 | GJ31: 0 | GK31: 0 | GL31: =ROUND(IF(AND(BH31=3,BI31=3,FS31<>0),P31,0),2) -> 0 | GM31: =ROUND(O31+X31+Y31,2)+GX31 -> 270763.88 | GN31: =IF(OR(BI31=0,BI31=1),GM31-GX31,0) -> 270763.88 | GO31: =IF(BI31=2,GM31-GX31,0) -> 0 | GP31: =IF(BI31=4,GM31-GX31,0) -> 0 | GR31: 0 | GS31: 3 | GT31: 0 | GV31: =ROUND((GT31),6) -> 0 | GW31: 1 | GX31: =ROUND(HC31*I31,2) -> 0 | HA31: 0 | HB31: 0 | HC31: =GV31*GW31 -> 0 | HS31: 0 | IK31: 0
A32: 17 | B32: 1 | C32: =ROW(SmtRes!A25) -> 25 | D32: =ROW(EtalonRes!A25) -> 25 | E32: 3 | F32: 6.65-1-3 | G32: Разборка трубопроводов из водогазопроводных труб диаметром до 50 мм | H32: 100 м | I32: =ROUND((110+12)/100,9) -> 1.22 | J32: 0 | K32: =ROUND((110+12)/100,9) -> 1.22 | O32: =ROUND(CP32,2) -> 1076.41 | P32: =ROUND((ROUND((AC32*AW32*I32),2)*BC32),2) -> 67.44 | Q32: =(ROUND((ROUND((((ET32*1.2))*AV32*I32),2)*BB32),2)+ROUND((ROUND(((AE32-((EU32*1.2)))*AV32*I32),2)*BS32),2)) -> 2.1 | R32: =(ROUND((ROUND((((EU32*1.2))*AV32*I32),2)*BS32),2)+ROUND((ROUND(((AE32-((EU32*1.2)))*AV32*I32),2)*BS32),2)) -> 0 | S32: =ROUND((ROUND((AF32*AV32*I32),2)*BA32),2) -> 1006.87 | T32: =ROUND(CU32*I32,2) -> 0 | U32: =CV32*I32 -> 92.458979 | V32: =CW32*I32 -> 0 | W32: =ROUND(CX32*I32,2) -> 0 | X32: =(ROUND((((S32+ROUND((ROUND((((EU32*1.2))*AV32*I32),2)*BS32),2))*AT32)/100),2)+ROUND(((ROUND((ROUND(((AE32-((EU32*1.2)))*AV32*I32),2)*BS32),2)*AT32)/100),2)) -> 875.98 | Y32: =(ROUND((((S32+ROUND((ROUND((((EU32*1.2))*AV32*I32),2)*BS32),2))*AU32)/100),2)+ROUND(((ROUND((ROUND(((AE32-((EU32*1.2)))*AV32*I32),2)*BS32),2)*AU32)/100),2)) -> 443.02 | AA32: 85736471 | AB32: =ROUND((AC32+AD32+AF32),6) -> 845.18 | AC32: =ROUND(((ES32*1)),6) -> 55.28 | AD32: =ROUND(((((ET32*1.2))-((EU32*1.2)))+AE32),6) -> 1.644 | AE32: =ROUND(((EU32*1.2)),6) -> 0 | AF32: =ROUND(((EV32*1.2)),6) -> 788.256 | AG32: =ROUND((AP32),6) -> 0 | AH32: =((EW32*1.2)) -> 72.384 | AI32: =((EX32*1.2)) -> 0 | AJ32: =(AS32) -> 0 | AK32: 713.53 | AL32: 55.28 | AM32: 1.37 | AN32: 0 | AO32: 656.88 | AP32: 0 | AQ32: 60.32 | AR32: 0 | AS32: 0 | AT32: 87 | AU32: 44 | AV32: 1.047 | AW32: 1 | AZ32: 1 | BA32: 1 | BB32: 1 | BC32: 1 | BH32: 0 | BI32: 1 | BJ32: ТСН-2001.6 Доп. 79, Сб. 65, т. 1, поз. 3 | BM32: 102 | BN32: 0 | BO32: 6.65-1-3 | BP32: 1 | BQ32: 60 | BR32: 0 | BS32: 1 | BT32: 1 | BU32: 1 | BV32: 1 | BW32: 1 | BX32: 1 | BZ32: 87 | CA32: 44 | CE32: 1566 | CF32: 0 | CG32: 0 | CM32: 0 | CN32: Поправка: Гл.12.Прил.8.п.8. 3_12.00.01.11.001 Наименование: При наличии напряженных и стесненных условий производства работ (стесненность, сложность складирования и транспортной логистики и т.п.) для объектов, расположенных в пределах круговой магистральной системы улиц "Садовое кольцо" города Москвы | CO32: 0 | CP32: =(P32+Q32+S32) -> 1076.41 | CQ32: =ROUND((ROUND((AC32*AW32*1),2)*BC32),2) -> 55.28 | CR32: =(ROUND((ROUND((((ET32*1.2))*AV32*1),2)*BB32),2)+ROUND((ROUND(((AE32-((EU32*1.2)))*AV32*1),2)*BS32),2)) -> 1.72 | CS32: =(ROUND((ROUND((((EU32*1.2))*AV32*1),2)*BS32),2)+ROUND((ROUND(((AE32-((EU32*1.2)))*AV32*1),2)*BS32),2)) -> 0 | CT32: =ROUND((ROUND((AF32*AV32*1),2)*BA32),2) -> 825.3 | CU32: =AG32 -> 0 | CV32: =(AH32*AV32) -> 75.786048 | CW32: =AI32 -> 0 | CX32: =AJ32 -> 0 | CY32: =(ROUND((((S32+ROUND((ROUND((((EU32*1.2))*AV32*1),2)*BS32),2))*AT32)/100),2)+ROUND(((ROUND((ROUND(((AE32-((EU32*1.2)))*AV32*1),2)*BS32),2)*AT32)/100),2)) -> 875.98 | CZ32: =(ROUND((((S32+ROUND((ROUND((((EU32*1.2))*AV32*1),2)*BS32),2))*AU32)/100),2)+ROUND(((ROUND((ROUND(((AE32-((EU32*1.2)))*AV32*1),2)*BS32),2)*AU32)/100),2)) -> 443.02 | DB32: 5 | DD32: *1 | DE32: *1,2 | DF32: *1,2 | DG32: *1,2 | DI32: *1,2 | DJ32: *1,2 | DN32: 0 | DO32: 0 | DP32: 1 | DQ32: 1 | DU32: 1003 | DV32: 100 м | DW32: 100 м | DX32: 100 | EE32: 85133723 | EF32: 60 | EG32: Ремонтно-строительные работы | EH32: 0 | EJ32: 1 | EK32: 102 | EL32: ТСН-2001.6-65. Внутренние санитарно-технические работы: демонтаж и разборка | EM32: ТСН-2001.6-65-1 | EO32: Поправка: Гл.12.Прил.8.п.8. 3_12.00.01.11.001 | EQ32: 0 | ER32: 713.53 | ES32: 55.28 | ET32: 1.37 | EU32: 0 | EV32: 656.88 | EW32: 60.32 | EX32: 0 | EY32: 0 | FQ32: 0 | FR32: 0 | FS32: 0 | FX32: 87 | FY32: 44 | GD32: 1 | GF32: -952300200 | GG32: 2 | GH32: 1 | GI32: 2 | GJ32: 0 | GK32: 0 | GL32: =ROUND(IF(AND(BH32=3,BI32=3,FS32<>0),P32,0),2) -> 0 | GM32: =ROUND(O32+X32+Y32,2)+GX32 -> 2395.41 | GN32: =IF(OR(BI32=0,BI32=1),GM32-GX32,0) -> 2395.41 | GO32: =IF(BI32=2,GM32-GX32,0) -> 0 | GP32: =IF(BI32=4,GM32-GX32,0) -> 0 | GR32: 0 | GS32: 3 | GT32: 0 | GV32: =ROUND((GT32),6) -> 0 | GW32: 1 | GX32: =ROUND(HC32*I32,2) -> 0 | HA32: 0 | HB32: 0 | HC32: =GV32*GW32 -> 0 | HS32: 0 | IK32: 0
A33: 17 | B33: 1 | C33: =ROW(SmtRes!A30) -> 30 | D33: =ROW(EtalonRes!A30) -> 30 | E33: 3 | F33: 6.65-1-3 | G33: Разборка трубопроводов из водогазопроводных труб диаметром до 50 мм | H33: 100 м | I33: =ROUND((110+12)/100,9) -> 1.22 | J33: 0 | K33: =ROUND((110+12)/100,9) -> 1.22 | O33: =ROUND(CP33,2) -> 57804.67 | P33: =ROUND((ROUND((AC33*AW33*I33),2)*BC33),2) -> 1048.02 | Q33: =(ROUND((ROUND((((ET33*1.2))*AV33*I33),2)*BB33),2)+ROUND((ROUND(((AE33-((EU33*1.2)))*AV33*I33),2)*BS33),2)) -> 19.53 | R33: =(ROUND((ROUND((((EU33*1.2))*AV33*I33),2)*BS33),2)+ROUND((ROUND(((AE33-((EU33*1.2)))*AV33*I33),2)*BS33),2)) -> 0 | S33: =ROUND((ROUND((AF33*AV33*I33),2)*BA33),2) -> 56737.12 | T33: =ROUND(CU33*I33,2) -> 0 | U33: =CV33*I33 -> 92.458979 | V33: =CW33*I33 -> 0 | W33: =ROUND(CX33*I33,2) -> 0 | X33: =(ROUND((((S33+ROUND((ROUND((((EU33*1.2))*AV33*I33),2)*BS33),2))*AT33)/100),2)+ROUND(((ROUND((ROUND(((AE33-((EU33*1.2)))*AV33*I33),2)*BS33),2)*AT33)/100),2)) -> 49361.29 | Y33: =(ROUND((((S33+ROUND((ROUND((((EU33*1.2))*AV33*I33),2)*BS33),2))*AU33)/100),2)+ROUND(((ROUND((ROUND(((AE33-((EU33*1.2)))*AV33*I33),2)*BS33),2)*AU33)/100),2)) -> 24964.33 | AA33: 85736473 | AB33: =ROUND((AC33+AD33+AF33),6) -> 845.18 | AC33: =ROUND(((ES33*1)),6) -> 55.28 | AD33: =ROUND(((((ET33*1.2))-((EU33*1.2)))+AE33),6) -> 1.644 | AE33: =ROUND(((EU33*1.2)),6) -> 0 | AF33: =ROUND(((EV33*1.2)),6) -> 788.256 | AG33: =ROUND((AP33),6) -> 0 | AH33: =((EW33*1.2)) -> 72.384 | AI33: =((EX33*1.2)) -> 0 | AJ33: =(AS33) -> 0 | AK33: 713.53 | AL33: 55.28 | AM33: 1.37 | AN33: 0 | AO33: 656.88 | AP33: 0 | AQ33: 60.32 | AR33: 0 | AS33: 0 | AT33: 87 | AU33: 44 | AV33: 1.047 | AW33: 1 | AZ33: 1 | BA33: 56.35 | BB33: 9.3 | BC33: 15.54 | BH33: 0 | BI33: 1 | BJ33: ТСН-2001.6 Доп. 79, Сб. 65, т. 1, поз. 3 | BM33: 102 | BN33: 0 | BO33: 6.65-1-3 | BP33: 1 | BQ33: 60 | BR33: 0 | BS33: 56.35 | BT33: 1 | BU33: 1 | BV33: 1 | BW33: 1 | BX33: 1 | BZ33: 87 | CA33: 44 | CE33: 1566 | CF33: 0 | CG33: 0 | CM33: 0 | CN33: Поправка: Гл.12.Прил.8.п.8. 3_12.00.01.11.001 Наименование: При наличии напряженных и стесненных условий производства работ (стесненность, сложность складирования и транспортной логистики и т.п.) для объектов, расположенных в пределах круговой магистральной системы улиц "Садовое кольцо" города Москвы | CO33: 0 | CP33: =(P33+Q33+S33) -> 57804.67 | CQ33: =ROUND((ROUND((AC33*AW33*1),2)*BC33),2) -> 859.05 | CR33: =(ROUND((ROUND((((ET33*1.2))*AV33*1),2)*BB33),2)+ROUND((ROUND(((AE33-((EU33*1.2)))*AV33*1),2)*BS33),2)) -> 16 | CS33: =(ROUND((ROUND((((EU33*1.2))*AV33*1),2)*BS33),2)+ROUND((ROUND(((AE33-((EU33*1.2)))*AV33*1),2)*BS33),2)) -> 0 | CT33: =ROUND((ROUND((AF33*AV33*1),2)*BA33),2) -> 46505.66 | CU33: =AG33 -> 0 | CV33: =(AH33*AV33) -> 75.786048 | CW33: =AI33 -> 0 | CX33: =AJ33 -> 0 | CY33: =(ROUND((((S33+ROUND((ROUND((((EU33*1.2))*AV33*1),2)*BS33),2))*AT33)/100),2)+ROUND(((ROUND((ROUND(((AE33-((EU33*1.2)))*AV33*1),2)*BS33),2)*AT33)/100),2)) -> 49361.29 | CZ33: =(ROUND((((S33+ROUND((ROUND((((EU33*1.2))*AV33*1),2)*BS33),2))*AU33)/100),2)+ROUND(((ROUND((ROUND(((AE33-((EU33*1.2)))*AV33*1),2)*BS33),2)*AU33)/100),2)) -> 24964.33 | DB33: 6 | DD33: *1 | DE33: *1,2 | DF33: *1,2 | DG33: *1,2 | DI33: *1,2 | DJ33: *1,2 | DN33: 0 | DO33: 0 | DP33: 1 | DQ33: 1 | DU33: 1003 | DV33: 100 м | DW33: 100 м | DX33: 100 | EE33: 85133723 | EF33: 60 | EG33: Ремонтно-строительные работы | EH33: 0 | EJ33: 1 | EK33: 102 | EL33: ТСН-2001.6-65. Внутренние санитарно-технические работы: демонтаж и разборка | EM33: ТСН-2001.6-65-1 | EO33: Поправка: Гл.12.Прил.8.п.8. 3_12.00.01.11.001 | EQ33: 0 | ER33: 713.53 | ES33: 55.28 | ET33: 1.37 | EU33: 0 | EV33: 656.88 | EW33: 60.32 | EX33: 0 | EY33: 0 | FQ33: 0 | FR33: 0 | FS33: 0 | FX33: 87 | FY33: 44 | GD33: 1 | GF33: -952300200 | GG33: 2 | GH33: 1 | GI33: 2 | GJ33: 0 | GK33: 0 | GL33: =ROUND(IF(AND(BH33=3,BI33=3,FS33<>0),P33,0),2) -> 0 | GM33: =ROUND(O33+X33+Y33,2)+GX33 -> 132130.29 | GN33: =IF(OR(BI33=0,BI33=1),GM33-GX33,0) -> 132130.29 | GO33: =IF(BI33=2,GM33-GX33,0) -> 0 | GP33: =IF(BI33=4,GM33-GX33,0) -> 0 | GR33: 0 | GS33: 3 | GT33: 0 | GV33: =ROUND((GT33),6) -> 0 | GW33: 1 | GX33: =ROUND(HC33*I33,2) -> 0 | HA33: 0 | HB33: 0 | HC33: =GV33*GW33 -> 0 | HS33: 0 | IK33: 0
A34: 17 | B34: 1 | C34: =ROW(SmtRes!A35) -> 35 | D34: =ROW(EtalonRes!A35) -> 35 | E34: 4 | F34: 6.65-11-5 | G34: Разборка трубопроводов центрального отопления на сварке диаметром труб до 100 мм | H34: 100 м | I34: =ROUND((16+16)/100,9) -> 0.32 | J34: 0 | K34: =ROUND((16+16)/100,9) -> 0.32 | O34: =ROUND(CP34,2) -> 295.35 | P34: =ROUND((ROUND((AC34*AW34*I34),2)*BC34),2) -> 24.59 | Q34: =(ROUND((ROUND(((((ET34*1)*1.2))*AV34*I34),2)*BB34),2)+ROUND((ROUND(((AE34-(((EU34*1)*1.2)))*AV34*I34),2)*BS34),2)) -> 0.73 | R34: =(ROUND((ROUND(((((EU34*1)*1.2))*AV34*I34),2)*BS34),2)+ROUND((ROUND(((AE34-(((EU34*1)*1.2)))*AV34*I34),2)*BS34),2)) -> 0 | S34: =ROUND((ROUND((AF34*AV34*I34),2)*BA34),2) -> 270.03 | T34: =ROUND(CU34*I34,2) -> 0 | U34: =CV34*I34 -> 24.571003 | V34: =CW34*I34 -> 0 | W34: =ROUND(CX34*I34,2) -> 0 | X34: =(ROUND((((S34+ROUND((ROUND(((((EU34*1)*1.2))*AV34*I34),2)*BS34),2))*AT34)/100),2)+ROUND(((ROUND((ROUND(((AE34-(((EU34*1)*1.2)))*AV34*I34),2)*BS34),2)*AT34)/100),2)) -> 234.93 | Y34: =(ROUND((((S34+ROUND((ROUND(((((EU34*1)*1.2))*AV34*I34),2)*BS34),2))*AU34)/100),2)+ROUND(((ROUND((ROUND(((AE34-(((EU34*1)*1.2)))*AV34*I34),2)*BS34),2)*AU34)/100),2)) -> 118.81 | AA34: 85736471 | AB34: =ROUND((AC34+AD34+AF34),6) -> 884.99872 | AC34: =ROUND((((ES34*1)*1)),6) -> 76.84 | AD34: =ROUND((((((ET34*1)*1.2))-(((EU34*1)*1.2)))+AE34),6) -> 2.184 | AE34: =ROUND((((EU34*1)*1.2)),6) -> 0 | AF34: =ROUND((((EV34*0.82)*1.2)),6) -> 805.97472 | AG34: =ROUND((AP34),6) -> 0 | AH34: =(((EW34*0.82)*1.2)) -> 73.33752 | AI34: =(((EX34*1)*1.2)) -> 0 | AJ34: =(AS34) -> 0 | AK34: 897.74 | AL34: 76.84 | AM34: 1.82 | AN34: 0 | AO34: 819.08 | AP34: 0 | AQ34: 74.53 | AR34: 0 | AS34: 0 | AT34: 87 | AU34: 44 | AV34: 1.047 | AW34: 1 | AZ34: 1 | BA34: 1 | BB34: 1 | BC34: 1 | BH34: 0 | BI34: 1 | BJ34: ТСН-2001.6 Доп. 79, Сб. 65, т. 11, поз. 5 | BM34: 102 | BN34: 0 | BO34: 6.65-11-5 | BP34: 1 | BQ34: 60 | BR34: 0 | BS34: 1 | BT34: 1 | BU34: 1 | BV34: 1 | BW34: 1 | BX34: 1 | BZ34: 87 | CA34: 44 | CE34: 1566 | CF34: 0 | CG34: 0 | CM34: 0 | CN34: Поправка: Сб.6-65.т3.1.п.3.1.6_06.65.01.28.002 Наименование: При разборке трубопроводов без правки и чистки труб и фасонных частей от накипи и грязи Поправка: Гл.12.Прил.8.п.8. 3_12.00.01.11.001 Наименование: При наличии напряженных и стесненных условий производства работ (стесненность, сложность складирования и транспортной логистики и т.п.) для объектов, расположенных в пределах круговой магистральной системы улиц "Садовое кольцо" города Москвы | CO34: 0 | CP34: =(P34+Q34+S34) -> 295.35 | CQ34: =ROUND((ROUND((AC34*AW34*1),2)*BC34),2) -> 76.84 | CR34: =(ROUND((ROUND(((((ET34*1)*1.2))*AV34*1),2)*BB34),2)+ROUND((ROUND(((AE34-(((EU34*1)*1.2)))*AV34*1),2)*BS34),2)) -> 2.29 | CS34: =(ROUND((ROUND(((((EU34*1)*1.2))*AV34*1),2)*BS34),2)+ROUND((ROUND(((AE34-(((EU34*1)*1.2)))*AV34*1),2)*BS34),2)) -> 0 | CT34: =ROUND((ROUND((AF34*AV34*1),2)*BA34),2) -> 843.86 | CU34: =AG34 -> 0 | CV34: =(AH34*AV34) -> 76.784383 | CW34: =AI34 -> 0 | CX34: =AJ34 -> 0 | CY34: =(ROUND((((S34+ROUND((ROUND(((((EU34*1)*1.2))*AV34*1),2)*BS34),2))*AT34)/100),2)+ROUND(((ROUND((ROUND(((AE34-(((EU34*1)*1.2)))*AV34*1),2)*BS34),2)*AT34)/100),2)) -> 234.93 | CZ34: =(ROUND((((S34+ROUND((ROUND(((((EU34*1)*1.2))*AV34*1),2)*BS34),2))*AU34)/100),2)+ROUND(((ROUND((ROUND(((AE34-(((EU34*1)*1.2)))*AV34*1),2)*BS34),2)*AU34)/100),2)) -> 118.81 | DB34: 7 | DD34: *1)*1 | DE34: *1)*1,2 | DF34: *1)*1,2 | DG34: *0,82)*1,2 | DI34: *0,82)*1,2 | DJ34: *1)*1,2 | DN34: 0 | DO34: 0 | DP34: 1 | DQ34: 1 | DU34: 1003 | DV34: 100 м | DW34: 100 м | DX34: 100 | EE34: 85133723 | EF34: 60 | EG34: Ремонтно-строительные работы | EH34: 0 | EJ34: 1 | EK34: 102 | EL34: ТСН-2001.6-65. Внутренние санитарно-технические работы: демонтаж и разборка | EM34: ТСН-2001.6-65-1 | EO34: Поправка: Сб.6-65.т3.1.п.3.1.6_06.65.01.28.002 Поправка: Гл.12.Прил.8.п.8. 3_12.00.01.11.001 | EQ34: 0 | ER34: 897.74 | ES34: 76.84 | ET34: 1.82 | EU34: 0 | EV34: 819.08 | EW34: 74.53 | EX34: 0 | EY34: 0 | FQ34: 0 | FR34: 0 | FS34: 0 | FX34: 87 | FY34: 44 | GD34: 1 | GF34: 1211388190 | GG34: 2 | GH34: 1 | GI34: 2 | GJ34: 0 | GK34: 0 | GL34: =ROUND(IF(AND(BH34=3,BI34=3,FS34<>0),P34,0),2) -> 0 | GM34: =ROUND(O34+X34+Y34,2)+GX34 -> 649.09 | GN34: =IF(OR(BI34=0,BI34=1),GM34-GX34,0) -> 649.09 | GO34: =IF(BI34=2,GM34-GX34,0) -> 0 | GP34: =IF(BI34=4,GM34-GX34,0) -> 0 | GR34: 0 | GS34: 3 | GT34: 0 | GV34: =ROUND((GT34),6) -> 0 | GW34: 1 | GX34: =ROUND(HC34*I34,2) -> 0 | HA34: 0 | HB34: 0 | HC34: =GV34*GW34 -> 0 | HS34: 0 | IK34: 0
A35: 17 | B35: 1 | C35: =ROW(SmtRes!A40) -> 40 | D35: =ROW(EtalonRes!A40) -> 40 | E35: 4 | F35: 6.65-11-5 | G35: Разборка трубопроводов центрального отопления на сварке диаметром труб до 100 мм | H35: 100 м | I35: =ROUND((16+16)/100,9) -> 0.32 | J35: 0 | K35: =ROUND((16+16)/100,9) -> 0.32 | O35: =ROUND(CP35,2) -> 15604.85 | P35: =ROUND((ROUND((AC35*AW35*I35),2)*BC35),2) -> 381.88 | Q35: =(ROUND((ROUND(((((ET35*1)*1.2))*AV35*I35),2)*BB35),2)+ROUND((ROUND(((AE35-(((EU35*1)*1.2)))*AV35*I35),2)*BS35),2)) -> 6.78 | R35: =(ROUND((ROUND(((((EU35*1)*1.2))*AV35*I35),2)*BS35),2)+ROUND((ROUND(((AE35-(((EU35*1)*1.2)))*AV35*I35),2)*BS35),2)) -> 0 | S35: =ROUND((ROUND((AF35*AV35*I35),2)*BA35),2) -> 15216.19 | T35: =ROUND(CU35*I35,2) -> 0 | U35: =CV35*I35 -> 24.571003 | V35: =CW35*I35 -> 0 | W35: =ROUND(CX35*I35,2) -> 0 | X35: =(ROUND((((S35+ROUND((ROUND(((((EU35*1)*1.2))*AV35*I35),2)*BS35),2))*AT35)/100),2)+ROUND(((ROUND((ROUND(((AE35-(((EU35*1)*1.2)))*AV35*I35),2)*BS35),2)*AT35)/100),2)) -> 13238.09 | Y35: =(ROUND((((S35+ROUND((ROUND(((((EU35*1)*1.2))*AV35*I35),2)*BS35),2))*AU35)/100),2)+ROUND(((ROUND((ROUND(((AE35-(((EU35*1)*1.2)))*AV35*I35),2)*BS35),2)*AU35)/100),2)) -> 6695.12 | AA35: 85736473 | AB35: =ROUND((AC35+AD35+AF35),6) -> 884.99872 | AC35: =ROUND((((ES35*1)*1)),6) -> 76.84 | AD35: =ROUND((((((ET35*1)*1.2))-(((EU35*1)*1.2)))+AE35),6) -> 2.184 | AE35: =ROUND((((EU35*1)*1.2)),6) -> 0 | AF35: =ROUND((((EV35*0.82)*1.2)),6) -> 805.97472 | AG35: =ROUND((AP35),6) -> 0 | AH35: =(((EW35*0.82)*1.2)) -> 73.33752 | AI35: =(((EX35*1)*1.2)) -> 0 | AJ35: =(AS35) -> 0 | AK35: 897.74 | AL35: 76.84 | AM35: 1.82 | AN35: 0 | AO35: 819.08 | AP35: 0 | AQ35: 74.53 | AR35: 0 | AS35: 0 | AT35: 87 | AU35: 44 | AV35: 1.047 | AW35: 1 | AZ35: 1 | BA35: 56.35 | BB35: 9.29 | BC35: 15.53 | BH35: 0 | BI35: 1 | BJ35: ТСН-2001.6 Доп. 79, Сб. 65, т. 11, поз. 5 | BM35: 102 | BN35: 0 | BO35: 6.65-11-5 | BP35: 1 | BQ35: 60 | BR35: 0 | BS35: 56.35 | BT35: 1 | BU35: 1 | BV35: 1 | BW35: 1 | BX35: 1 | BZ35: 87 | CA35: 44 | CE35: 1566 | CF35: 0 | CG35: 0 | CM35: 0 | CN35: Поправка: Сб.6-65.т3.1.п.3.1.6_06.65.01.28.002 Наименование: При разборке трубопроводов без правки и чистки труб и фасонных частей от накипи и грязи Поправка: Гл.12.Прил.8.п.8. 3_12.00.01.11.001 Наименование: При наличии напряженных и стесненных условий производства работ (стесненность, сложность складирования и транспортной логистики и т.п.) для объектов, расположенных в пределах круговой магистральной системы улиц "Садовое кольцо" города Москвы | CO35: 0 | CP35: =(P35+Q35+S35) -> 15604.85 | CQ35: =ROUND((ROUND((AC35*AW35*1),2)*BC35),2) -> 1193.33 | CR35: =(ROUND((ROUND(((((ET35*1)*1.2))*AV35*1),2)*BB35),2)+ROUND((ROUND(((AE35-(((EU35*1)*1.2)))*AV35*1),2)*BS35),2)) -> 21.27 | CS35: =(ROUND((ROUND(((((EU35*1)*1.2))*AV35*1),2)*BS35),2)+ROUND((ROUND(((AE35-(((EU35*1)*1.2)))*AV35*1),2)*BS35),2)) -> 0 | CT35: =ROUND((ROUND((AF35*AV35*1),2)*BA35),2) -> 47551.51 | CU35: =AG35 -> 0 | CV35: =(AH35*AV35) -> 76.784383 | CW35: =AI35 -> 0 | CX35: =AJ35 -> 0 | CY35: =(ROUND((((S35+ROUND((ROUND(((((EU35*1)*1.2))*AV35*1),2)*BS35),2))*AT35)/100),2)+ROUND(((ROUND((ROUND(((AE35-(((EU35*1)*1.2)))*AV35*1),2)*BS35),2)*AT35)/100),2)) -> 13238.09 | CZ35: =(ROUND((((S35+ROUND((ROUND(((((EU35*1)*1.2))*AV35*1),2)*BS35),2))*AU35)/100),2)+ROUND(((ROUND((ROUND(((AE35-(((EU35*1)*1.2)))*AV35*1),2)*BS35),2)*AU35)/100),2)) -> 6695.12 | DB35: 9 | DD35: *1)*1 | DE35: *1)*1,2 | DF35: *1)*1,2 | DG35: *0,82)*1,2 | DI35: *0,82)*1,2 | DJ35: *1)*1,2 | DN35: 0 | DO35: 0 | DP35: 1 | DQ35: 1 | DU35: 1003 | DV35: 100 м | DW35: 100 м | DX35: 100 | EE35: 85133723 | EF35: 60 | EG35: Ремонтно-строительные работы | EH35: 0 | EJ35: 1 | EK35: 102 | EL35: ТСН-2001.6-65. Внутренние санитарно-технические работы: демонтаж и разборка | EM35: ТСН-2001.6-65-1 | EO35: Поправка: Сб.6-65.т3.1.п.3.1.6_06.65.01.28.002 Поправка: Гл.12.Прил.8.п.8. 3_12.00.01.11.001 | EQ35: 0 | ER35: 897.74 | ES35: 76.84 | ET35: 1.82 | EU35: 0 | EV35: 819.08 | EW35: 74.53 | EX35: 0 | EY35: 0 | FQ35: 0 | FR35: 0 | FS35: 0 | FX35: 87 | FY35: 44 | GD35: 1 | GF35: 1211388190 | GG35: 2 | GH35: 1 | GI35: 2 | GJ35: 0 | GK35: 0 | GL35: =ROUND(IF(AND(BH35=3,BI35=3,FS35<>0),P35,0),2) -> 0 | GM35: =ROUND(O35+X35+Y35,2)+GX35 -> 35538.06 | GN35: =IF(OR(BI35=0,BI35=1),GM35-GX35,0) -> 35538.06 | GO35: =IF(BI35=2,GM35-GX35,0) -> 0 | GP35: =IF(BI35=4,GM35-GX35,0) -> 0 | GR35: 0 | GS35: 3 | GT35: 0 | GV35: =ROUND((GT35),6) -> 0 | GW35: 1 | GX35: =ROUND(HC35*I35,2) -> 0 | HA35: 0 | HB35: 0 | HC35: =GV35*GW35 -> 0 | HS35: 0 | IK35: 0
A36: 17 | B36: 1 | C36: =ROW(SmtRes!A48) -> 48 | D36: =ROW(EtalonRes!A53) -> 53 | E36: 5 | F36: 3.16-40-1 | G36: Прокладка напорного трубопровода водоснабжения и отопления из многослойного полипропилена, армированного стекловолокном, из заранее собранных узлов, наружный диаметр 20 мм (демонтаж) | H36: 100 м | I36: =ROUND((43+30)/100,9) -> 0.73 | J36: 0 | K36: =ROUND((43+30)/100,9) -> 0.73 | O36: =ROUND(CP36,2) -> 74.28 | P36: =ROUND((ROUND((AC36*AW36*I36),2)*BC36),2) -> 0 | Q36: =(ROUND((ROUND(((((ET36*0.4)*1.2))*AV36*I36),2)*BB36),2)+ROUND((ROUND(((AE36-(((EU36*0.4)*1.2)))*AV36*I36),2)*BS36),2)) -> 6.87 | R36: =(ROUND((ROUND(((((EU36*0.4)*1.2))*AV36*I36),2)*BS36),2)+ROUND((ROUND(((AE36-(((EU36*0.4)*1.2)))*AV36*I36),2)*BS36),2)) -> 0.19 | S36: =ROUND((ROUND((AF36*AV36*I36),2)*BA36),2) -> 67.41 | T36: =ROUND(CU36*I36,2) -> 0 | U36: =CV36*I36 -> 5.4436462 | V36: =CW36*I36 -> 0 | W36: =ROUND(CX36*I36,2) -> 0 | X36: =(ROUND((((S36+ROUND((ROUND(((((EU36*0.4)*1.2))*AV36*I36),2)*BS36),2))*AT36)/100),2)+ROUND(((ROUND((ROUND(((AE36-(((EU36*0.4)*1.2)))*AV36*I36),2)*BS36),2)*AT36)/100),2)) -> 73.68 | Y36: =(ROUND((((S36+ROUND((ROUND(((((EU36*0.4)*1.2))*AV36*I36),2)*BS36),2))*AU36)/100),2)+ROUND(((ROUND((ROUND(((AE36-(((EU36*0.4)*1.2)))*AV36*I36),2)*BS36),2)*AU36)/100),2)) -> 41.24 | AA36: 85736471 | AB36: =ROUND((AC36+AD36+AF36),6) -> 95.3712 | AC36: =ROUND((((ES36*0)*1)),6) -> 0 | AD36: =ROUND((((((ET36*0.4)*1.2))-(((EU36*0.4)*1.2)))+AE36),6) -> 8.8224 | AE36: =ROUND((((EU36*0.4)*1.2)),6) -> 0.24 | AF36: =ROUND((((EV36*0.4)*1.2)),6) -> 86.5488 | AG36: =ROUND((AP36),6) -> 0 | AH36: =(((EW36*0.4)*1.2)) -> 6.9888 | AI36: =(((EX36*0.4)*1.2)) -> 0 | AJ36: =(AS36) -> 0 | AK36: 351.79 | AL36: 153.1 | AM36: 18.38 | AN36: 0.5 | AO36: 180.31 | AP36: 0 | AQ36: 14.56 | AR36: 0 | AS36: 0 | AT36: 109 | AU36: 61 | AV36: 1.067 | AW36: 1 | AZ36: 1 | BA36: 1 | BB36: 1 | BC36: 1 | BH36: 0 | BI36: 1 | BJ36: ТСН-2001.3 Доп. 79, Сб. 16, т. 40, поз. 1 | BM36: 21 | BN36: 0 | BO36: 3.16-40-1 | BP36: 1 | BQ36: 30 | BR36: 0 | BS36: 1 | BT36: 1 | BU36: 1 | BV36: 1 | BW36: 1 | BX36: 1 | BZ36: 109 | CA36: 61 | CE36: 1566 | CF36: 0 | CG36: 0 | CM36: 0 | CN36: Поправка: Гл.6.Прил.2.2.п.2.2.13_06.00.01.35.003 Наименование: При демонтаже внутренних санитарно-технических устройств и газопроводов Поправка: Гл.12.Прил.8.п.8. 3_12.00.01.11.001 Наименование: При наличии напряженных и стесненных условий производства работ (стесненность, сложность складирования и транспортной логистики и т.п.) для объектов, расположенных в пределах круговой магистральной системы улиц "Садовое кольцо" города Москвы | CO36: 0 | CP36: =(P36+Q36+S36) -> 74.28 | CQ36: =ROUND((ROUND((AC36*AW36*1),2)*BC36),2) -> 0 | CR36: =(ROUND((ROUND(((((ET36*0.4)*1.2))*AV36*1),2)*BB36),2)+ROUND((ROUND(((AE36-(((EU36*0.4)*1.2)))*AV36*1),2)*BS36),2)) -> 9.41 | CS36: =(ROUND((ROUND(((((EU36*0.4)*1.2))*AV36*1),2)*BS36),2)+ROUND((ROUND(((AE36-(((EU36*0.4)*1.2)))*AV36*1),2)*BS36),2)) -> 0.26 | CT36: =ROUND((ROUND((AF36*AV36*1),2)*BA36),2) -> 92.35 | CU36: =AG36 -> 0 | CV36: =(AH36*AV36) -> 7.4570496 | CW36: =AI36 -> 0 | CX36: =AJ36 -> 0 | CY36: =(ROUND((((S36+ROUND((ROUND(((((EU36*0.4)*1.2))*AV36*1),2)*BS36),2))*AT36)/100),2)+ROUND(((ROUND((ROUND(((AE36-(((EU36*0.4)*1.2)))*AV36*1),2)*BS36),2)*AT36)/100),2)) -> 73.76 | CZ36: =(ROUND((((S36+ROUND((ROUND(((((EU36*0.4)*1.2))*AV36*1),2)*BS36),2))*AU36)/100),2)+ROUND(((ROUND((ROUND(((AE36-(((EU36*0.4)*1.2)))*AV36*1),2)*BS36),2)*AU36)/100),2)) -> 41.28 | DB36: 11 | DD36: *0)*1 | DE36: *0,4)*1,2 | DF36: *0,4)*1,2 | DG36: *0,4)*1,2 | DI36: *0,4)*1,2 | DJ36: *0,4)*1,2 | DN36: 0 | DO36: 0 | DP36: 1 | DQ36: 1 | DU36: 1003 | DV36: 100 м | DW36: 100 м | DX36: 100 | EE36: 85133641 | EF36: 30 | EG36: Строительные работы | EH36: 0 | EJ36: 1 | EK36: 21 | EL36: ТСН-2001.3-16. Трубопроводы внутренние | EM36: ТСН-2001.3-16-1 | EO36: Поправка: Гл.6.Прил.2.2.п.2.2.13_06.00.01.35.003 Поправка: Гл.12.Прил.8.п.8. 3_12.00.01.11.001 | EQ36: 0 | ER36: 351.79 | ES36: 153.1 | ET36: 18.38 | EU36: 0.5 | EV36: 180.31 | EW36: 14.56 | EX36: 0 | EY36: 0 | FQ36: 0 | FR36: 0 | FS36: 0 | FX36: 109 | FY36: 61 | GD36: 1 | GF36: 470604376 | GG36: 2 | GH36: 1 | GI36: 2 | GJ36: 0 | GK36: 0 | GL36: =ROUND(IF(AND(BH36=3,BI36=3,FS36<>0),P36,0),2) -> 0 | GM36: =ROUND(O36+X36+Y36,2)+GX36 -> 189.2 | GN36: =IF(OR(BI36=0,BI36=1),GM36-GX36,0) -> 189.2 | GO36: =IF(BI36=2,GM36-GX36,0) -> 0 | GP36: =IF(BI36=4,GM36-GX36,0) -> 0 | GR36: 0 | GS36: 3 | GT36: 0 | GV36: =ROUND((GT36),6) -> 0 | GW36: 1 | GX36: =ROUND(HC36*I36,2) -> 0 | HA36: 0 | HB36: 0 | HC36: =GV36*GW36 -> 0 | HS36: 0 | IK36: 0
A37: 17 | B37: 1 | C37: =ROW(SmtRes!A56) -> 56 | D37: =ROW(EtalonRes!A66) -> 66 | E37: 5 | F37: 3.16-40-1 | G37: Прокладка напорного трубопровода водоснабжения и отопления из многослойного полипропилена, армированного стекловолокном, из заранее собранных узлов, наружный диаметр 20 мм (демонтаж) | H37: 100 м | I37: =ROUND((43+30)/100,9) -> 0.73 | J37: 0 | K37: =ROUND((43+30)/100,9) -> 0.73 | O37: =ROUND(CP37,2) -> 3882.78 | P37: =ROUND((ROUND((AC37*AW37*I37),2)*BC37),2) -> 0 | Q37: =(ROUND((ROUND(((((ET37*0.4)*1.2))*AV37*I37),2)*BB37),2)+ROUND((ROUND(((AE37-(((EU37*0.4)*1.2)))*AV37*I37),2)*BS37),2)) -> 84.23 | R37: =(ROUND((ROUND(((((EU37*0.4)*1.2))*AV37*I37),2)*BS37),2)+ROUND((ROUND(((AE37-(((EU37*0.4)*1.2)))*AV37*I37),2)*BS37),2)) -> 10.71 | S37: =ROUND((ROUND((AF37*AV37*I37),2)*BA37),2) -> 3798.55 | T37: =ROUND(CU37*I37,2) -> 0 | U37: =CV37*I37 -> 5.4436462 | V37: =CW37*I37 -> 0 | W37: =ROUND(CX37*I37,2) -> 0 | X37: =(ROUND((((S37+ROUND((ROUND(((((EU37*0.4)*1.2))*AV37*I37),2)*BS37),2))*AT37)/100),2)+ROUND(((ROUND((ROUND(((AE37-(((EU37*0.4)*1.2)))*AV37*I37),2)*BS37),2)*AT37)/100),2)) -> 4152.09 | Y37: =(ROUND((((S37+ROUND((ROUND(((((EU37*0.4)*1.2))*AV37*I37),2)*BS37),2))*AU37)/100),2)+ROUND(((ROUND((ROUND(((AE37-(((EU37*0.4)*1.2)))*AV37*I37),2)*BS37),2)*AU37)/100),2)) -> 2323.65 | AA37: 85736473 | AB37: =ROUND((AC37+AD37+AF37),6) -> 95.3712 | AC37: =ROUND((((ES37*0)*1)),6) -> 0 | AD37: =ROUND((((((ET37*0.4)*1.2))-(((EU37*0.4)*1.2)))+AE37),6) -> 8.8224 | AE37: =ROUND((((EU37*0.4)*1.2)),6) -> 0.24 | AF37: =ROUND((((EV37*0.4)*1.2)),6) -> 86.5488 | AG37: =ROUND((AP37),6) -> 0 | AH37: =(((EW37*0.4)*1.2)) -> 6.9888 | AI37: =(((EX37*0.4)*1.2)) -> 0 | AJ37: =(AS37) -> 0 | AK37: 351.79 | AL37: 153.1 | AM37: 18.38 | AN37: 0.5 | AO37: 180.31 | AP37: 0 | AQ37: 14.56 | AR37: 0 | AS37: 0 | AT37: 109 | AU37: 61 | AV37: 1.067 | AW37: 1 | AZ37: 1 | BA37: 56.35 | BB37: 12.26 | BC37: 1.98 | BH37: 0 | BI37: 1 | BJ37: ТСН-2001.3 Доп. 79, Сб. 16, т. 40, поз. 1 | BM37: 21 | BN37: 0 | BO37: 3.16-40-1 | BP37: 1 | BQ37: 30 | BR37: 0 | BS37: 56.35 | BT37: 1 | BU37: 1 | BV37: 1 | BW37: 1 | BX37: 1 | BZ37: 109 | CA37: 61 | CE37: 1566 | CF37: 0 | CG37: 0 | CM37: 0 | CN37: Поправка: Гл.6.Прил.2.2.п.2.2.13_06.00.01.35.003 Наименование: При демонтаже внутренних санитарно-технических устройств и газопроводов Поправка: Гл.12.Прил.8.п.8. 3_12.00.01.11.001 Наименование: При наличии напряженных и стесненных условий производства работ (стесненность, сложность складирования и транспортной логистики и т.п.) для объектов, расположенных в пределах круговой магистральной системы улиц "Садовое кольцо" города Москвы | CO37: 0 | CP37: =(P37+Q37+S37) -> 3882.78 | CQ37: =ROUND((ROUND((AC37*AW37*1),2)*BC37),2) -> 0 | CR37: =(ROUND((ROUND(((((ET37*0.4)*1.2))*AV37*1),2)*BB37),2)+ROUND((ROUND(((AE37-(((EU37*0.4)*1.2)))*AV37*1),2)*BS37),2)) -> 115.37 | CS37: =(ROUND((ROUND(((((EU37*0.4)*1.2))*AV37*1),2)*BS37),2)+ROUND((ROUND(((AE37-(((EU37*0.4)*1.2)))*AV37*1),2)*BS37),2)) -> 14.65 | CT37: =ROUND((ROUND((AF37*AV37*1),2)*BA37),2) -> 5203.92 | CU37: =AG37 -> 0 | CV37: =(AH37*AV37) -> 7.4570496 | CW37: =AI37 -> 0 | CX37: =AJ37 -> 0 | CY37: =(ROUND((((S37+ROUND((ROUND(((((EU37*0.4)*1.2))*AV37*1),2)*BS37),2))*AT37)/100),2)+ROUND(((ROUND((ROUND(((AE37-(((EU37*0.4)*1.2)))*AV37*1),2)*BS37),2)*AT37)/100),2)) -> 4156.39 | CZ37: =(ROUND((((S37+ROUND((ROUND(((((EU37*0.4)*1.2))*AV37*1),2)*BS37),2))*AU37)/100),2)+ROUND(((ROUND((ROUND(((AE37-(((EU37*0.4)*1.2)))*AV37*1),2)*BS37),2)*AU37)/100),2)) -> 2326.05 | DB37: 13 | DD37: *0)*1 | DE37: *0,4)*1,2 | DF37: *0,4)*1,2 | DG37: *0,4)*1,2 | DI37: *0,4)*1,2 | DJ37: *0,4)*1,2 | DN37: 0 | DO37: 0 | DP37: 1 | DQ37: 1 | DU37: 1003 | DV37: 100 м | DW37: 100 м | DX37: 100 | EE37: 85133641 | EF37: 30 | EG37: Строительные работы | EH37: 0 | EJ37: 1 | EK37: 21 | EL37: ТСН-2001.3-16. Трубопроводы внутренние | EM37: ТСН-2001.3-16-1 | EO37: Поправка: Гл.6.Прил.2.2.п.2.2.13_06.00.01.35.003 Поправка: Гл.12.Прил.8.п.8. 3_12.00.01.11.001 | EQ37: 0 | ER37: 351.79 | ES37: 153.1 | ET37: 18.38 | EU37: 0.5 | EV37: 180.31 | EW37: 14.56 | EX37: 0 | EY37: 0 | FQ37: 0 | FR37: 0 | FS37: 0 | FX37: 109 | FY37: 61 | GD37: 1 | GF37: 470604376 | GG37: 2 | GH37: 1 | GI37: 2 | GJ37: 0 | GK37: 0 | GL37: =ROUND(IF(AND(BH37=3,BI37=3,FS37<>0),P37,0),2) -> 0 | GM37: =ROUND(O37+X37+Y37,2)+GX37 -> 10358.52 | GN37: =IF(OR(BI37=0,BI37=1),GM37-GX37,0) -> 10358.52 | GO37: =IF(BI37=2,GM37-GX37,0) -> 0 | GP37: =IF(BI37=4,GM37-GX37,0) -> 0 | GR37: 0 | GS37: 3 | GT37: 0 | GV37: =ROUND((GT37),6) -> 0 | GW37: 1 | GX37: =ROUND(HC37*I37,2) -> 0 | HA37: 0 | HB37: 0 | HC37: =GV37*GW37 -> 0 | HS37: 0 | IK37: 0
A38: 17 | B38: 1 | C38: =ROW(SmtRes!A64) -> 64 | D38: =ROW(EtalonRes!A79) -> 79 | E38: 6 | F38: 3.16-40-2 | G38: Прокладка напорного трубопровода водоснабжения и отопления из многослойного полипропилена, армированного стекловолокном, из заранее собранных узлов, наружный диаметр 25 мм (демонтаж) | H38: 100 м | I38: =ROUND((145+30)/100,9) -> 1.75 | J38: 0 | K38: =ROUND((145+30)/100,9) -> 1.75 | O38: =ROUND(CP38,2) -> 173.65 | P38: =ROUND((ROUND((AC38*AW38*I38),2)*BC38),2) -> 0 | Q38: =(ROUND((ROUND(((((ET38*0.4)*1.2))*AV38*I38),2)*BB38),2)+ROUND((ROUND(((AE38-(((EU38*0.4)*1.2)))*AV38*I38),2)*BS38),2)) -> 17.63 | R38: =(ROUND((ROUND(((((EU38*0.4)*1.2))*AV38*I38),2)*BS38),2)+ROUND((ROUND(((AE38-(((EU38*0.4)*1.2)))*AV38*I38),2)*BS38),2)) -> 0.68 | S38: =ROUND((ROUND((AF38*AV38*I38),2)*BA38),2) -> 156.02 | T38: =ROUND(CU38*I38,2) -> 0 | U38: =CV38*I38 -> 12.619622 | V38: =CW38*I38 -> 0 | W38: =ROUND(CX38*I38,2) -> 0 | X38: =(ROUND((((S38+ROUND((ROUND(((((EU38*0.4)*1.2))*AV38*I38),2)*BS38),2))*AT38)/100),2)+ROUND(((ROUND((ROUND(((AE38-(((EU38*0.4)*1.2)))*AV38*I38),2)*BS38),2)*AT38)/100),2)) -> 170.8 | Y38: =(ROUND((((S38+ROUND((ROUND(((((EU38*0.4)*1.2))*AV38*I38),2)*BS38),2))*AU38)/100),2)+ROUND(((ROUND((ROUND(((AE38-(((EU38*0.4)*1.2)))*AV38*I38),2)*BS38),2)*AU38)/100),2)) -> 95.59 | AA38: 85736471 | AB38: =ROUND((AC38+AD38+AF38),6) -> 92.9952 | AC38: =ROUND((((ES38*0)*1)),6) -> 0 | AD38: =ROUND((((((ET38*0.4)*1.2))-(((EU38*0.4)*1.2)))+AE38),6) -> 9.4416 | AE38: =ROUND((((EU38*0.4)*1.2)),6) -> 0.3648 | AF38: =ROUND((((EV38*0.4)*1.2)),6) -> 83.5536 | AG38: =ROUND((AP38),6) -> 0 | AH38: =(((EW38*0.4)*1.2)) -> 6.7584 | AI38: =(((EX38*0.4)*1.2)) -> 0 | AJ38: =(AS38) -> 0 | AK38: 328.44 | AL38: 134.7 | AM38: 19.67 | AN38: 0.76 | AO38: 174.07 | AP38: 0 | AQ38: 14.08 | AR38: 0 | AS38: 0 | AT38: 109 | AU38: 61 | AV38: 1.067 | AW38: 1 | AZ38: 1 | BA38: 1 | BB38: 1 | BC38: 1 | BH38: 0 | BI38: 1 | BJ38: ТСН-2001.3 Доп. 79, Сб. 16, т. 40, поз. 2 | BM38: 21 | BN38: 0 | BO38: 3.16-40-2 | BP38: 1 | BQ38: 30 | BR38: 0 | BS38: 1 | BT38: 1 | BU38: 1 | BV38: 1 | BW38: 1 | BX38: 1 | BZ38: 109 | CA38: 61 | CE38: 1566 | CF38: 0 | CG38: 0 | CM38: 0 | CN38: Поправка: Гл.6.Прил.2.2.п.2.2.13_06.00.01.35.003 Наименование: При демонтаже внутренних санитарно-технических устройств и газопроводов Поправка: Гл.12.Прил.8.п.8. 3_12.00.01.11.001 Наименование: При наличии напряженных и стесненных условий производства работ (стесненность, сложность складирования и транспортной логистики и т.п.) для объектов, расположенных в пределах круговой магистральной системы улиц "Садовое кольцо" города Москвы | CO38: 0 | CP38: =(P38+Q38+S38) -> 173.65 | CQ38: =ROUND((ROUND((AC38*AW38*1),2)*BC38),2) -> 0 | CR38: =(ROUND((ROUND(((((ET38*0.4)*1.2))*AV38*1),2)*BB38),2)+ROUND((ROUND(((AE38-(((EU38*0.4)*1.2)))*AV38*1),2)*BS38),2)) -> 10.07 | CS38: =(ROUND((ROUND(((((EU38*0.4)*1.2))*AV38*1),2)*BS38),2)+ROUND((ROUND(((AE38-(((EU38*0.4)*1.2)))*AV38*1),2)*BS38),2)) -> 0.39 | CT38: =ROUND((ROUND((AF38*AV38*1),2)*BA38),2) -> 89.15 | CU38: =AG38 -> 0 | CV38: =(AH38*AV38) -> 7.2112128 | CW38: =AI38 -> 0 | CX38: =AJ38 -> 0 | CY38: =(ROUND((((S38+ROUND((ROUND(((((EU38*0.4)*1.2))*AV38*1),2)*BS38),2))*AT38)/100),2)+ROUND(((ROUND((ROUND(((AE38-(((EU38*0.4)*1.2)))*AV38*1),2)*BS38),2)*AT38)/100),2)) -> 170.49 | CZ38: =(ROUND((((S38+ROUND((ROUND(((((EU38*0.4)*1.2))*AV38*1),2)*BS38),2))*AU38)/100),2)+ROUND(((ROUND((ROUND(((AE38-(((EU38*0.4)*1.2)))*AV38*1),2)*BS38),2)*AU38)/100),2)) -> 95.41 | DB38: 15 | DD38: *0)*1 | DE38: *0,4)*1,2 | DF38: *0,4)*1,2 | DG38: *0,4)*1,2 | DI38: *0,4)*1,2 | DJ38: *0,4)*1,2 | DN38: 0 | DO38: 0 | DP38: 1 | DQ38: 1 | DU38: 1003 | DV38: 100 м | DW38: 100 м | DX38: 100 | EE38: 85133641 | EF38: 30 | EG38: Строительные работы | EH38: 0 | EJ38: 1 | EK38: 21 | EL38: ТСН-2001.3-16. Трубопроводы внутренние | EM38: ТСН-2001.3-16-1 | EO38: Поправка: Гл.6.Прил.2.2.п.2.2.13_06.00.01.35.003 Поправка: Гл.12.Прил.8.п.8. 3_12.00.01.11.001 | EQ38: 0 | ER38: 328.44 | ES38: 134.7 | ET38: 19.67 | EU38: 0.76 | EV38: 174.07 | EW38: 14.08 | EX38: 0 | EY38: 0 | FQ38: 0 | FR38: 0 | FS38: 0 | FX38: 109 | FY38: 61 | GD38: 1 | GF38: -23638325 | GG38: 2 | GH38: 1 | GI38: 2 | GJ38: 0 | GK38: 0 | GL38: =ROUND(IF(AND(BH38=3,BI38=3,FS38<>0),P38,0),2) -> 0 | GM38: =ROUND(O38+X38+Y38,2)+GX38 -> 440.04 | GN38: =IF(OR(BI38=0,BI38=1),GM38-GX38,0) -> 440.04 | GO38: =IF(BI38=2,GM38-GX38,0) -> 0 | GP38: =IF(BI38=4,GM38-GX38,0) -> 0 | GR38: 0 | GS38: 3 | GT38: 0 | GV38: =ROUND((GT38),6) -> 0 | GW38: 1 | GX38: =ROUND(HC38*I38,2) -> 0 | HA38: 0 | HB38: 0 | HC38: =GV38*GW38 -> 0 | HS38: 0 | IK38: 0
A39: 17 | B39: 1 | C39: =ROW(SmtRes!A72) -> 72 | D39: =ROW(EtalonRes!A92) -> 92 | E39: 6 | F39: 3.16-40-2 | G39: Прокладка напорного трубопровода водоснабжения и отопления из многослойного полипропилена, армированного стекловолокном, из заранее собранных узлов, наружный диаметр 25 мм (демонтаж) | H39: 100 м | I39: =ROUND((145+30)/100,9) -> 1.75 | J39: 0 | K39: =ROUND((145+30)/100,9) -> 1.75 | O39: =ROUND(CP39,2) -> 9015.98 | P39: =ROUND((ROUND((AC39*AW39*I39),2)*BC39),2) -> 0 | Q39: =(ROUND((ROUND(((((ET39*0.4)*1.2))*AV39*I39),2)*BB39),2)+ROUND((ROUND(((AE39-(((EU39*0.4)*1.2)))*AV39*I39),2)*BS39),2)) -> 224.25 | R39: =(ROUND((ROUND(((((EU39*0.4)*1.2))*AV39*I39),2)*BS39),2)+ROUND((ROUND(((AE39-(((EU39*0.4)*1.2)))*AV39*I39),2)*BS39),2)) -> 38.32 | S39: =ROUND((ROUND((AF39*AV39*I39),2)*BA39),2) -> 8791.73 | T39: =ROUND(CU39*I39,2) -> 0 | U39: =CV39*I39 -> 12.619622 | V39: =CW39*I39 -> 0 | W39: =ROUND(CX39*I39,2) -> 0 | X39: =(ROUND((((S39+ROUND((ROUND(((((EU39*0.4)*1.2))*AV39*I39),2)*BS39),2))*AT39)/100),2)+ROUND(((ROUND((ROUND(((AE39-(((EU39*0.4)*1.2)))*AV39*I39),2)*BS39),2)*AT39)/100),2)) -> 9624.75 | Y39: =(ROUND((((S39+ROUND((ROUND(((((EU39*0.4)*1.2))*AV39*I39),2)*BS39),2))*AU39)/100),2)+ROUND(((ROUND((ROUND(((AE39-(((EU39*0.4)*1.2)))*AV39*I39),2)*BS39),2)*AU39)/100),2)) -> 5386.33 | AA39: 85736473 | AB39: =ROUND((AC39+AD39+AF39),6) -> 92.9952 | AC39: =ROUND((((ES39*0)*1)),6) -> 0 | AD39: =ROUND((((((ET39*0.4)*1.2))-(((EU39*0.4)*1.2)))+AE39),6) -> 9.4416 | AE39: =ROUND((((EU39*0.4)*1.2)),6) -> 0.3648 | AF39: =ROUND((((EV39*0.4)*1.2)),6) -> 83.5536 | AG39: =ROUND((AP39),6) -> 0 | AH39: =(((EW39*0.4)*1.2)) -> 6.7584 | AI39: =(((EX39*0.4)*1.2)) -> 0 | AJ39: =(AS39) -> 0 | AK39: 328.44 | AL39: 134.7 | AM39: 19.67 | AN39: 0.76 | AO39: 174.07 | AP39: 0 | AQ39: 14.08 | AR39: 0 | AS39: 0 | AT39: 109 | AU39: 61 | AV39: 1.067 | AW39: 1 | AZ39: 1 | BA39: 56.35 | BB39: 12.72 | BC39: 2.14 | BH39: 0 | BI39: 1 | BJ39: ТСН-2001.3 Доп. 79, Сб. 16, т. 40, поз. 2 | BM39: 21 | BN39: 0 | BO39: 3.16-40-2 | BP39: 1 | BQ39: 30 | BR39: 0 | BS39: 56.35 | BT39: 1 | BU39: 1 | BV39: 1 | BW39: 1 | BX39: 1 | BZ39: 109 | CA39: 61 | CE39: 1566 | CF39: 0 | CG39: 0 | CM39: 0 | CN39: Поправка: Гл.6.Прил.2.2.п.2.2.13_06.00.01.35.003 Наименование: При демонтаже внутренних санитарно-технических устройств и газопроводов Поправка: Гл.12.Прил.8.п.8. 3_12.00.01.11.001 Наименование: При наличии напряженных и стесненных условий производства работ (стесненность, сложность складирования и транспортной логистики и т.п.) для объектов, расположенных в пределах круговой магистральной системы улиц "Садовое кольцо" города Москвы | CO39: 0 | CP39: =(P39+Q39+S39) -> 9015.98 | CQ39: =ROUND((ROUND((AC39*AW39*1),2)*BC39),2) -> 0 | CR39: =(ROUND((ROUND(((((ET39*0.4)*1.2))*AV39*1),2)*BB39),2)+ROUND((ROUND(((AE39-(((EU39*0.4)*1.2)))*AV39*1),2)*BS39),2)) -> 128.09 | CS39: =(ROUND((ROUND(((((EU39*0.4)*1.2))*AV39*1),2)*BS39),2)+ROUND((ROUND(((AE39-(((EU39*0.4)*1.2)))*AV39*1),2)*BS39),2)) -> 21.98 | CT39: =ROUND((ROUND((AF39*AV39*1),2)*BA39),2) -> 5023.6 | CU39: =AG39 -> 0 | CV39: =(AH39*AV39) -> 7.2112128 | CW39: =AI39 -> 0 | CX39: =AJ39 -> 0 | CY39: =(ROUND((((S39+ROUND((ROUND(((((EU39*0.4)*1.2))*AV39*1),2)*BS39),2))*AT39)/100),2)+ROUND(((ROUND((ROUND(((AE39-(((EU39*0.4)*1.2)))*AV39*1),2)*BS39),2)*AT39)/100),2)) -> 9606.94 | CZ39: =(ROUND((((S39+ROUND((ROUND(((((EU39*0.4)*1.2))*AV39*1),2)*BS39),2))*AU39)/100),2)+ROUND(((ROUND((ROUND(((AE39-(((EU39*0.4)*1.2)))*AV39*1),2)*BS39),2)*AU39)/100),2)) -> 5376.36 | DB39: 17 | DD39: *0)*1 | DE39: *0,4)*1,2 | DF39: *0,4)*1,2 | DG39: *0,4)*1,2 | DI39: *0,4)*1,2 | DJ39: *0,4)*1,2 | DN39: 0 | DO39: 0 | DP39: 1 | DQ39: 1 | DU39: 1003 | DV39: 100 м | DW39: 100 м | DX39: 100 | EE39: 85133641 | EF39: 30 | EG39: Строительные работы | EH39: 0 | EJ39: 1 | EK39: 21 | EL39: ТСН-2001.3-16. Трубопроводы внутренние | EM39: ТСН-2001.3-16-1 | EO39: Поправка: Гл.6.Прил.2.2.п.2.2.13_06.00.01.35.003 Поправка: Гл.12.Прил.8.п.8. 3_12.00.01.11.001 | EQ39: 0 | ER39: 328.44 | ES39: 134.7 | ET39: 19.67 | EU39: 0.76 | EV39: 174.07 | EW39: 14.08 | EX39: 0 | EY39: 0 | FQ39: 0 | FR39: 0 | FS39: 0 | FX39: 109 | FY39: 61 | GD39: 1 | GF39: -23638325 | GG39: 2 | GH39: 1 | GI39: 2 | GJ39: 0 | GK39: 0 | GL39: =ROUND(IF(AND(BH39=3,BI39=3,FS39<>0),P39,0),2) -> 0 | GM39: =ROUND(O39+X39+Y39,2)+GX39 -> 24027.06 | GN39: =IF(OR(BI39=0,BI39=1),GM39-GX39,0) -> 24027.06 | GO39: =IF(BI39=2,GM39-GX39,0) -> 0 | GP39: =IF(BI39=4,GM39-GX39,0) -> 0 | GR39: 0 | GS39: 3 | GT39: 0 | GV39: =ROUND((GT39),6) -> 0 | GW39: 1 | GX39: =ROUND(HC39*I39,2) -> 0 | HA39: 0 | HB39: 0 | HC39: =GV39*GW39 -> 0 | HS39: 0 | IK39: 0
A40: 17 | B40: 1 | C40: =ROW(SmtRes!A73) -> 73 | D40: =ROW(EtalonRes!A93) -> 93 | E40: 7 | F40: 6.66-162-1 | G40: Разборка тепловой изоляции из плит, сегментов и скорлуп | H40: 100 м2 | I40: =ROUND(((18+75+90)*0.11+(40+90+100)*0.13+(30+75+54)*0.16+(20+50+45)*0.18+55*0.21+110*0.26+16*0.37+3.3+8.7+2.5+4)/100,9) -> 1.6074 | J40: 0 | K40: =ROUND(((18+75+90)*0.11+(40+90+100)*0.13+(30+75+54)*0.16+(20+50+45)*0.18+55*0.21+110*0.26+16*0.37+3.3+8.7+2.5+4)/100,9) -> 1.6074 | O40: =ROUND(CP40,2) -> 298.1 | P40: =ROUND((ROUND((AC40*AW40*I40),2)*BC40),2) -> 0 | Q40: =(ROUND((ROUND((((ET40*1.2))*AV40*I40),2)*BB40),2)+ROUND((ROUND(((AE40-((EU40*1.2)))*AV40*I40),2)*BS40),2)) -> 0 | R40: =(ROUND((ROUND((((EU40*1.2))*AV40*I40),2)*BS40),2)+ROUND((ROUND(((AE40-((EU40*1.2)))*AV40*I40),2)*BS40),2)) -> 0 | S40: =ROUND((ROUND((AF40*AV40*I40),2)*BA40),2) -> 298.1 | T40: =ROUND(CU40*I40,2) -> 0 | U40: =CV40*I40 -> 27.372929 | V40: =CW40*I40 -> 0 | W40: =ROUND(CX40*I40,2) -> 0 | X40: =(ROUND((((S40+ROUND((ROUND((((EU40*1.2))*AV40*I40),2)*BS40),2))*AT40)/100),2)+ROUND(((ROUND((ROUND(((AE40-((EU40*1.2)))*AV40*I40),2)*BS40),2)*AT40)/100),2)) -> 265.31 | Y40: =(ROUND((((S40+ROUND((ROUND((((EU40*1.2))*AV40*I40),2)*BS40),2))*AU40)/100),2)+ROUND(((ROUND((ROUND(((AE40-((EU40*1.2)))*AV40*I40),2)*BS40),2)*AU40)/100),2)) -> 131.16 | AA40: 85736471 | AB40: =ROUND((AC40+AD40+AF40),6) -> 173.808 | AC40: =ROUND(((ES40*1)),6) -> 0 | AD40: =ROUND(((((ET40*1.2))-((EU40*1.2)))+AE40),6) -> 0 | AE40: =ROUND(((EU40*1.2)),6) -> 0 | AF40: =ROUND(((EV40*1.2)),6) -> 173.808 | AG40: =ROUND((AP40),6) -> 0 | AH40: =((EW40*1.2)) -> 15.96 | AI40: =((EX40*1.2)) -> 0 | AJ40: =(AS40) -> 0 | AK40: 144.84 | AL40: 0 | AM40: 0 | AN40: 0 | AO40: 144.84 | AP40: 0 | AQ40: 13.3 | AR40: 0 | AS40: 0 | AT40: 89 | AU40: 44 | AV40: 1.067 | AW40: 1.003 | AZ40: 1 | BA40: 1 | BB40: 1 | BC40: 1 | BH40: 0 | BI40: 1 | BJ40: ТСН-2001.6. Доп. 1-42. Сб. 66, т. 162, поз. 1 | BM40: 104 | BN40: 0 | BO40: 6.66-162-1 | BP40: 1 | BQ40: 60 | BR40: 0 | BS40: 1 | BT40: 1 | BU40: 1 | BV40: 1 | BW40: 1 | BX40: 1 | BZ40: 89 | CA40: 44 | CE40: 1566 | CF40: 0 | CG40: 0 | CM40: 0 | CN40: Поправка: Гл.12.Прил.8.п.8. 3_12.00.01.11.001 Наименование: При наличии напряженных и стесненных условий производства работ (стесненность, сложность складирования и транспортной логистики и т.п.) для объектов, расположенных в пределах круговой магистральной системы улиц "Садовое кольцо" города Москвы | CO40: 0 | CP40: =(P40+Q40+S40) -> 298.1 | CQ40: =ROUND((ROUND((AC40*AW40*1),2)*BC40),2) -> 0 | CR40: =(ROUND((ROUND((((ET40*1.2))*AV40*1),2)*BB40),2)+ROUND((ROUND(((AE40-((EU40*1.2)))*AV40*1),2)*BS40),2)) -> 0 | CS40: =(ROUND((ROUND((((EU40*1.2))*AV40*1),2)*BS40),2)+ROUND((ROUND(((AE40-((EU40*1.2)))*AV40*1),2)*BS40),2)) -> 0 | CT40: =ROUND((ROUND((AF40*AV40*1),2)*BA40),2) -> 185.45 | CU40: =AG40 -> 0 | CV40: =(AH40*AV40) -> 17.02932 | CW40: =AI40 -> 0 | CX40: =AJ40 -> 0 | CY40: =(ROUND((((S40+ROUND((ROUND((((EU40*1.2))*AV40*1),2)*BS40),2))*AT40)/100),2)+ROUND(((ROUND((ROUND(((AE40-((EU40*1.2)))*AV40*1),2)*BS40),2)*AT40)/100),2)) -> 265.31 | CZ40: =(ROUND((((S40+ROUND((ROUND((((EU40*1.2))*AV40*1),2)*BS40),2))*AU40)/100),2)+ROUND(((ROUND((ROUND(((AE40-((EU40*1.2)))*AV40*1),2)*BS40),2)*AU40)/100),2)) -> 131.16 | DB40: 19 | DD40: *1 | DE40: *1,2 | DF40: *1,2 | DG40: *1,2 | DI40: *1,2 | DJ40: *1,2 | DN40: 0 | DO40: 0 | DP40: 1 | DQ40: 1 | DU40: 1005 | DV40: 100 м2 | DW40: 100 м2 | DX40: 100 | EE40: 85133725 | EF40: 60 | EG40: Ремонтно-строительные работы | EH40: 0 | EJ40: 1 | EK40: 104 | EL40: ТСН-2001.6-66. Наружные инженерные сети: демонтаж, разборка, очистка | EM40: ТСН-2001.6-66-1 | EO40: Поправка: Гл.12.Прил.8.п.8. 3_12.00.01.11.001 | EQ40: 0 | ER40: 144.84 | ES40: 0 | ET40: 0 | EU40: 0 | EV40: 144.84 | EW40: 13.3 | EX40: 0 | EY40: 0 | FQ40: 0 | FR40: 0 | FS40: 0 | FX40: 89 | FY40: 44 | GD40: 1 | GF40: -1398351047 | GG40: 2 | GH40: 1 | GI40: 2 | GJ40: 0 | GK40: 0 | GL40: =ROUND(IF(AND(BH40=3,BI40=3,FS40<>0),P40,0),2) -> 0 | GM40: =ROUND(O40+X40+Y40,2)+GX40 -> 694.57 | GN40: =IF(OR(BI40=0,BI40=1),GM40-GX40,0) -> 694.57 | GO40: =IF(BI40=2,GM40-GX40,0) -> 0 | GP40: =IF(BI40=4,GM40-GX40,0) -> 0 | GR40: 0 | GS40: 3 | GT40: 0 | GV40: =ROUND((GT40),6) -> 0 | GW40: 1 | GX40: =ROUND(HC40*I40,2) -> 0 | HA40: 0 | HB40: 0 | HC40: =GV40*GW40 -> 0 | HS40: 0 | IK40: 0
A41: 17 | B41: 1 | C41: =ROW(SmtRes!A74) -> 74 | D41: =ROW(EtalonRes!A94) -> 94 | E41: 7 | F41: 6.66-162-1 | G41: Разборка тепловой изоляции из плит, сегментов и скорлуп | H41: 100 м2 | I41: =ROUND(((18+75+90)*0.11+(40+90+100)*0.13+(30+75+54)*0.16+(20+50+45)*0.18+55*0.21+110*0.26+16*0.37+3.3+8.7+2.5+4)/100,9) -> 1.6074 | J41: 0 | K41: =ROUND(((18+75+90)*0.11+(40+90+100)*0.13+(30+75+54)*0.16+(20+50+45)*0.18+55*0.21+110*0.26+16*0.37+3.3+8.7+2.5+4)/100,9) -> 1.6074 | O41: =ROUND(CP41,2) -> 16797.94 | P41: =ROUND((ROUND((AC41*AW41*I41),2)*BC41),2) -> 0 | Q41: =(ROUND((ROUND((((ET41*1.2))*AV41*I41),2)*BB41),2)+ROUND((ROUND(((AE41-((EU41*1.2)))*AV41*I41),2)*BS41),2)) -> 0 | R41: =(ROUND((ROUND((((EU41*1.2))*AV41*I41),2)*BS41),2)+ROUND((ROUND(((AE41-((EU41*1.2)))*AV41*I41),2)*BS41),2)) -> 0 | S41: =ROUND((ROUND((AF41*AV41*I41),2)*BA41),2) -> 16797.94 | T41: =ROUND(CU41*I41,2) -> 0 | U41: =CV41*I41 -> 27.372929 | V41: =CW41*I41 -> 0 | W41: =ROUND(CX41*I41,2) -> 0 | X41: =(ROUND((((S41+ROUND((ROUND((((EU41*1.2))*AV41*I41),2)*BS41),2))*AT41)/100),2)+ROUND(((ROUND((ROUND(((AE41-((EU41*1.2)))*AV41*I41),2)*BS41),2)*AT41)/100),2)) -> 14950.17 | Y41: =(ROUND((((S41+ROUND((ROUND((((EU41*1.2))*AV41*I41),2)*BS41),2))*AU41)/100),2)+ROUND(((ROUND((ROUND(((AE41-((EU41*1.2)))*AV41*I41),2)*BS41),2)*AU41)/100),2)) -> 7391.09 | AA41: 85736473 | AB41: =ROUND((AC41+AD41+AF41),6) -> 173.808 | AC41: =ROUND(((ES41*1)),6) -> 0 | AD41: =ROUND(((((ET41*1.2))-((EU41*1.2)))+AE41),6) -> 0 | AE41: =ROUND(((EU41*1.2)),6) -> 0 | AF41: =ROUND(((EV41*1.2)),6) -> 173.808 | AG41: =ROUND((AP41),6) -> 0 | AH41: =((EW41*1.2)) -> 15.96 | AI41: =((EX41*1.2)) -> 0 | AJ41: =(AS41) -> 0 | AK41: 144.84 | AL41: 0 | AM41: 0 | AN41: 0 | AO41: 144.84 | AP41: 0 | AQ41: 13.3 | AR41: 0 | AS41: 0 | AT41: 89 | AU41: 44 | AV41: 1.067 | AW41: 1.003 | AZ41: 1 | BA41: 56.35 | BB41: 1 | BC41: 1 | BH41: 0 | BI41: 1 | BJ41: ТСН-2001.6. Доп. 1-42. Сб. 66, т. 162, поз. 1 | BM41: 104 | BN41: 0 | BO41: 6.66-162-1 | BP41: 1 | BQ41: 60 | BR41: 0 | BS41: 56.35 | BT41: 1 | BU41: 1 | BV41: 1 | BW41: 1 | BX41: 1 | BZ41: 89 | CA41: 44 | CE41: 1566 | CF41: 0 | CG41: 0 | CM41: 0 | CN41: Поправка: Гл.12.Прил.8.п.8. 3_12.00.01.11.001 Наименование: При наличии напряженных и стесненных условий производства работ (стесненность, сложность складирования и транспортной логистики и т.п.) для объектов, расположенных в пределах круговой магистральной системы улиц "Садовое кольцо" города Москвы | CO41: 0 | CP41: =(P41+Q41+S41) -> 16797.94 | CQ41: =ROUND((ROUND((AC41*AW41*1),2)*BC41),2) -> 0 | CR41: =(ROUND((ROUND((((ET41*1.2))*AV41*1),2)*BB41),2)+ROUND((ROUND(((AE41-((EU41*1.2)))*AV41*1),2)*BS41),2)) -> 0 | CS41: =(ROUND((ROUND((((EU41*1.2))*AV41*1),2)*BS41),2)+ROUND((ROUND(((AE41-((EU41*1.2)))*AV41*1),2)*BS41),2)) -> 0 | CT41: =ROUND((ROUND((AF41*AV41*1),2)*BA41),2) -> 10450.11 | CU41: =AG41 -> 0 | CV41: =(AH41*AV41) -> 17.02932 | CW41: =AI41 -> 0 | CX41: =AJ41 -> 0 | CY41: =(ROUND((((S41+ROUND((ROUND((((EU41*1.2))*AV41*1),2)*BS41),2))*AT41)/100),2)+ROUND(((ROUND((ROUND(((AE41-((EU41*1.2)))*AV41*1),2)*BS41),2)*AT41)/100),2)) -> 14950.17 | CZ41: =(ROUND((((S41+ROUND((ROUND((((EU41*1.2))*AV41*1),2)*BS41),2))*AU41)/100),2)+ROUND(((ROUND((ROUND(((AE41-((EU41*1.2)))*AV41*1),2)*BS41),2)*AU41)/100),2)) -> 7391.09 | DB41: 20 | DD41: *1 | DE41: *1,2 | DF41: *1,2 | DG41: *1,2 | DI41: *1,2 | DJ41: *1,2 | DN41: 0 | DO41: 0 | DP41: 1 | DQ41: 1 | DU41: 1005 | DV41: 100 м2 | DW41: 100 м2 | DX41: 100 | EE41: 85133725 | EF41: 60 | EG41: Ремонтно-строительные работы | EH41: 0 | EJ41: 1 | EK41: 104 | EL41: ТСН-2001.6-66. Наружные инженерные сети: демонтаж, разборка, очистка | EM41: ТСН-2001.6-66-1 | EO41: Поправка: Гл.12.Прил.8.п.8. 3_12.00.01.11.001 | EQ41: 0 | ER41: 144.84 | ES41: 0 | ET41: 0 | EU41: 0 | EV41: 144.84 | EW41: 13.3 | EX41: 0 | EY41: 0 | FQ41: 0 | FR41: 0 | FS41: 0 | FX41: 89 | FY41: 44 | GD41: 1 | GF41: -1398351047 | GG41: 2 | GH41: 1 | GI41: 2 | GJ41: 0 | GK41: 0 | GL41: =ROUND(IF(AND(BH41=3,BI41=3,FS41<>0),P41,0),2) -> 0 | GM41: =ROUND(O41+X41+Y41,2)+GX41 -> 39139.2 | GN41: =IF(OR(BI41=0,BI41=1),GM41-GX41,0) -> 39139.2 | GO41: =IF(BI41=2,GM41-GX41,0) -> 0 | GP41: =IF(BI41=4,GM41-GX41,0) -> 0 | GR41: 0 | GS41: 3 | GT41: 0 | GV41: =ROUND((GT41),6) -> 0 | GW41: 1 | GX41: =ROUND(HC41*I41,2) -> 0 | HA41: 0 | HB41: 0 | HC41: =GV41*GW41 -> 0 | HS41: 0 | IK41: 0
A42: 17 | B42: 1 | C42: =ROW(SmtRes!A76) -> 76 | D42: =ROW(EtalonRes!A96) -> 96 | E42: 8 | F42: 6.65-3-4 | G42: Демонтаж задвижки фланцевой диаметром 100 мм | H42: 100 шт. | I42: =ROUND(3/100,9) -> 0.03 | J42: 0 | K42: =ROUND(3/100,9) -> 0.03 | O42: =ROUND(CP42,2) -> 80.49 | P42: =ROUND((ROUND((AC42*AW42*I42),2)*BC42),2) -> 0 | Q42: =(ROUND((ROUND((((ET42*1.2))*AV42*I42),2)*BB42),2)+ROUND((ROUND(((AE42-((EU42*1.2)))*AV42*I42),2)*BS42),2)) -> 0 | R42: =(ROUND((ROUND((((EU42*1.2))*AV42*I42),2)*BS42),2)+ROUND((ROUND(((AE42-((EU42*1.2)))*AV42*I42),2)*BS42),2)) -> 0 | S42: =ROUND((ROUND((AF42*AV42*I42),2)*BA42),2) -> 80.49 | T42: =ROUND(CU42*I42,2) -> 0 | U42: =CV42*I42 -> 7.199172 | V42: =CW42*I42 -> 0 | W42: =ROUND(CX42*I42,2) -> 0 | X42: =(ROUND((((S42+ROUND((ROUND((((EU42*1.2))*AV42*I42),2)*BS42),2))*AT42)/100),2)+ROUND(((ROUND((ROUND(((AE42-((EU42*1.2)))*AV42*I42),2)*BS42),2)*AT42)/100),2)) -> 70.03 | Y42: =(ROUND((((S42+ROUND((ROUND((((EU42*1.2))*AV42*I42),2)*BS42),2))*AU42)/100),2)+ROUND(((ROUND((ROUND(((AE42-((EU42*1.2)))*AV42*I42),2)*BS42),2)*AU42)/100),2)) -> 35.42 | AA42: 85736471 | AB42: =ROUND((AC42+AD42+AF42),6) -> 2562.456 | AC42: =ROUND(((ES42*1)),6) -> 0 | AD42: =ROUND(((((ET42*1.2))-((EU42*1.2)))+AE42),6) -> 0 | AE42: =ROUND(((EU42*1.2)),6) -> 0 | AF42: =ROUND(((EV42*1.2)),6) -> 2562.456 | AG42: =ROUND((AP42),6) -> 0 | AH42: =((EW42*1.2)) -> 229.2 | AI42: =((EX42*1.2)) -> 0 | AJ42: =(AS42) -> 0 | AK42: 2135.38 | AL42: 0 | AM42: 0 | AN42: 0 | AO42: 2135.38 | AP42: 0 | AQ42: 191 | AR42: 0 | AS42: 0 | AT42: 87 | AU42: 44 | AV42: 1.047 | AW42: 1 | AZ42: 1 | BA42: 1 | BB42: 1 | BC42: 1 | BH42: 0 | BI42: 1 | BJ42: ТСН-2001.6 Доп. 77, Сб. 65, т. 3, поз. 4 | BM42: 102 | BN42: 0 | BO42: 6.65-3-4 | BP42: 1 | BQ42: 60 | BR42: 0 | BS42: 1 | BT42: 1 | BU42: 1 | BV42: 1 | BW42: 1 | BX42: 1 | BZ42: 87 | CA42: 44 | CE42: 1566 | CF42: 0 | CG42: 0 | CM42: 0 | CN42: Поправка: Гл.12.Прил.8.п.8. 3_12.00.01.11.001 Наименование: При наличии напряженных и стесненных условий производства работ (стесненность, сложность складирования и транспортной логистики и т.п.) для объектов, расположенных в пределах круговой магистральной системы улиц "Садовое кольцо" города Москвы | CO42: 0 | CP42: =(P42+Q42+S42) -> 80.49 | CQ42: =ROUND((ROUND((AC42*AW42*1),2)*BC42),2) -> 0 | CR42: =(ROUND((ROUND((((ET42*1.2))*AV42*1),2)*BB42),2)+ROUND((ROUND(((AE42-((EU42*1.2)))*AV42*1),2)*BS42),2)) -> 0 | CS42: =(ROUND((ROUND((((EU42*1.2))*AV42*1),2)*BS42),2)+ROUND((ROUND(((AE42-((EU42*1.2)))*AV42*1),2)*BS42),2)) -> 0 | CT42: =ROUND((ROUND((AF42*AV42*1),2)*BA42),2) -> 2682.89 | CU42: =AG42 -> 0 | CV42: =(AH42*AV42) -> 239.9724 | CW42: =AI42 -> 0 | CX42: =AJ42 -> 0 | CY42: =(ROUND((((S42+ROUND((ROUND((((EU42*1.2))*AV42*1),2)*BS42),2))*AT42)/100),2)+ROUND(((ROUND((ROUND(((AE42-((EU42*1.2)))*AV42*1),2)*BS42),2)*AT42)/100),2)) -> 70.03 | CZ42: =(ROUND((((S42+ROUND((ROUND((((EU42*1.2))*AV42*1),2)*BS42),2))*AU42)/100),2)+ROUND(((ROUND((ROUND(((AE42-((EU42*1.2)))*AV42*1),2)*BS42),2)*AU42)/100),2)) -> 35.42 | DB42: 21 | DD42: *1 | DE42: *1,2 | DF42: *1,2 | DG42: *1,2 | DI42: *1,2 | DJ42: *1,2 | DN42: 0 | DO42: 0 | DP42: 1 | DQ42: 1 | DU42: 1010 | DV42: 100 шт. | DW42: 100 шт. | DX42: 100 | EE42: 85133723 | EF42: 60 | EG42: Ремонтно-строительные работы | EH42: 0 | EJ42: 1 | EK42: 102 | EL42: ТСН-2001.6-65. Внутренние санитарно-технические работы: демонтаж и разборка | EM42: ТСН-2001.6-65-1 | EO42: Поправка: Гл.12.Прил.8.п.8. 3_12.00.01.11.001 | EQ42: 0 | ER42: 2135.38 | ES42: 0 | ET42: 0 | EU42: 0 | EV42: 2135.38 | EW42: 191 | EX42: 0 | EY42: 0 | FQ42: 0 | FR42: 0 | FS42: 0 | FX42: 87 | FY42: 44 | GD42: 1 | GF42: -1388814122 | GG42: 2 | GH42: 1 | GI42: 2 | GJ42: 0 | GK42: 0 | GL42: =ROUND(IF(AND(BH42=3,BI42=3,FS42<>0),P42,0),2) -> 0 | GM42: =ROUND(O42+X42+Y42,2)+GX42 -> 185.94 | GN42: =IF(OR(BI42=0,BI42=1),GM42-GX42,0) -> 185.94 | GO42: =IF(BI42=2,GM42-GX42,0) -> 0 | GP42: =IF(BI42=4,GM42-GX42,0) -> 0 | GR42: 0 | GS42: 3 | GT42: 0 | GV42: =ROUND((GT42),6) -> 0 | GW42: 1 | GX42: =ROUND(HC42*I42,2) -> 0 | HA42: 0 | HB42: 0 | HC42: =GV42*GW42 -> 0 | HS42: 0 | IK42: 0
A43: 17 | B43: 1 | C43: =ROW(SmtRes!A78) -> 78 | D43: =ROW(EtalonRes!A98) -> 98 | E43: 8 | F43: 6.65-3-4 | G43: Демонтаж задвижки фланцевой диаметром 100 мм | H43: 100 шт. | I43: =ROUND(3/100,9) -> 0.03 | J43: 0 | K43: =ROUND(3/100,9) -> 0.03 | O43: =ROUND(CP43,2) -> 4535.61 | P43: =ROUND((ROUND((AC43*AW43*I43),2)*BC43),2) -> 0 | Q43: =(ROUND((ROUND((((ET43*1.2))*AV43*I43),2)*BB43),2)+ROUND((ROUND(((AE43-((EU43*1.2)))*AV43*I43),2)*BS43),2)) -> 0 | R43: =(ROUND((ROUND((((EU43*1.2))*AV43*I43),2)*BS43),2)+ROUND((ROUND(((AE43-((EU43*1.2)))*AV43*I43),2)*BS43),2)) -> 0 | S43: =ROUND((ROUND((AF43*AV43*I43),2)*BA43),2) -> 4535.61 | T43: =ROUND(CU43*I43,2) -> 0 | U43: =CV43*I43 -> 7.199172 | V43: =CW43*I43 -> 0 | W43: =ROUND(CX43*I43,2) -> 0 | X43: =(ROUND((((S43+ROUND((ROUND((((EU43*1.2))*AV43*I43),2)*BS43),2))*AT43)/100),2)+ROUND(((ROUND((ROUND(((AE43-((EU43*1.2)))*AV43*I43),2)*BS43),2)*AT43)/100),2)) -> 3945.98 | Y43: =(ROUND((((S43+ROUND((ROUND((((EU43*1.2))*AV43*I43),2)*BS43),2))*AU43)/100),2)+ROUND(((ROUND((ROUND(((AE43-((EU43*1.2)))*AV43*I43),2)*BS43),2)*AU43)/100),2)) -> 1995.67 | AA43: 85736473 | AB43: =ROUND((AC43+AD43+AF43),6) -> 2562.456 | AC43: =ROUND(((ES43*1)),6) -> 0 | AD43: =ROUND(((((ET43*1.2))-((EU43*1.2)))+AE43),6) -> 0 | AE43: =ROUND(((EU43*1.2)),6) -> 0 | AF43: =ROUND(((EV43*1.2)),6) -> 2562.456 | AG43: =ROUND((AP43),6) -> 0 | AH43: =((EW43*1.2)) -> 229.2 | AI43: =((EX43*1.2)) -> 0 | AJ43: =(AS43) -> 0 | AK43: 2135.38 | AL43: 0 | AM43: 0 | AN43: 0 | AO43: 2135.38 | AP43: 0 | AQ43: 191 | AR43: 0 | AS43: 0 | AT43: 87 | AU43: 44 | AV43: 1.047 | AW43: 1 | AZ43: 1 | BA43: 56.35 | BB43: 1 | BC43: 1 | BH43: 0 | BI43: 1 | BJ43: ТСН-2001.6 Доп. 77, Сб. 65, т. 3, поз. 4 | BM43: 102 | BN43: 0 | BO43: 6.65-3-4 | BP43: 1 | BQ43: 60 | BR43: 0 | BS43: 56.35 | BT43: 1 | BU43: 1 | BV43: 1 | BW43: 1 | BX43: 1 | BZ43: 87 | CA43: 44 | CE43: 1566 | CF43: 0 | CG43: 0 | CM43: 0 | CN43: Поправка: Гл.12.Прил.8.п.8. 3_12.00.01.11.001 Наименование: При наличии напряженных и стесненных условий производства работ (стесненность, сложность складирования и транспортной логистики и т.п.) для объектов, расположенных в пределах круговой магистральной системы улиц "Садовое кольцо" города Москвы | CO43: 0 | CP43: =(P43+Q43+S43) -> 4535.61 | CQ43: =ROUND((ROUND((AC43*AW43*1),2)*BC43),2) -> 0 | CR43: =(ROUND((ROUND((((ET43*1.2))*AV43*1),2)*BB43),2)+ROUND((ROUND(((AE43-((EU43*1.2)))*AV43*1),2)*BS43),2)) -> 0 | CS43: =(ROUND((ROUND((((EU43*1.2))*AV43*1),2)*BS43),2)+ROUND((ROUND(((AE43-((EU43*1.2)))*AV43*1),2)*BS43),2)) -> 0 | CT43: =ROUND((ROUND((AF43*AV43*1),2)*BA43),2) -> 151180.85 | CU43: =AG43 -> 0 | CV43: =(AH43*AV43) -> 239.9724 | CW43: =AI43 -> 0 | CX43: =AJ43 -> 0 | CY43: =(ROUND((((S43+ROUND((ROUND((((EU43*1.2))*AV43*1),2)*BS43),2))*AT43)/100),2)+ROUND(((ROUND((ROUND(((AE43-((EU43*1.2)))*AV43*1),2)*BS43),2)*AT43)/100),2)) -> 3945.98 | CZ43: =(ROUND((((S43+ROUND((ROUND((((EU43*1.2))*AV43*1),2)*BS43),2))*AU43)/100),2)+ROUND(((ROUND((ROUND(((AE43-((EU43*1.2)))*AV43*1),2)*BS43),2)*AU43)/100),2)) -> 1995.67 | DB43: 22 | DD43: *1 | DE43: *1,2 | DF43: *1,2 | DG43: *1,2 | DI43: *1,2 | DJ43: *1,2 | DN43: 0 | DO43: 0 | DP43: 1 | DQ43: 1 | DU43: 1010 | DV43: 100 шт. | DW43: 100 шт. | DX43: 100 | EE43: 85133723 | EF43: 60 | EG43: Ремонтно-строительные работы | EH43: 0 | EJ43: 1 | EK43: 102 | EL43: ТСН-2001.6-65. Внутренние санитарно-технические работы: демонтаж и разборка | EM43: ТСН-2001.6-65-1 | EO43: Поправка: Гл.12.Прил.8.п.8. 3_12.00.01.11.001 | EQ43: 0 | ER43: 2135.38 | ES43: 0 | ET43: 0 | EU43: 0 | EV43: 2135.38 | EW43: 191 | EX43: 0 | EY43: 0 | FQ43: 0 | FR43: 0 | FS43: 0 | FX43: 87 | FY43: 44 | GD43: 1 | GF43: -1388814122 | GG43: 2 | GH43: 1 | GI43: 2 | GJ43: 0 | GK43: 0 | GL43: =ROUND(IF(AND(BH43=3,BI43=3,FS43<>0),P43,0),2) -> 0 | GM43: =ROUND(O43+X43+Y43,2)+GX43 -> 10477.26 | GN43: =IF(OR(BI43=0,BI43=1),GM43-GX43,0) -> 10477.26 | GO43: =IF(BI43=2,GM43-GX43,0) -> 0 | GP43: =IF(BI43=4,GM43-GX43,0) -> 0 | GR43: 0 | GS43: 3 | GT43: 0 | GV43: =ROUND((GT43),6) -> 0 | GW43: 1 | GX43: =ROUND(HC43*I43,2) -> 0 | HA43: 0 | HB43: 0 | HC43: =GV43*GW43 -> 0 | HS43: 0 | IK43: 0
A44: 17 | B44: 1 | C44: =ROW(SmtRes!A80) -> 80 | D44: =ROW(EtalonRes!A100) -> 100 | E44: 9 | F44: 6.65-3-3 | G44: Демонтаж крана водоразборного | H44: 100 шт. | I44: =ROUND((12+12+4+1+2+23+4+150+20+4+26+22+3+2+29+19+3)/100,9) -> 3.36 | J44: 0 | K44: =ROUND((12+12+4+1+2+23+4+150+20+4+26+22+3+2+29+19+3)/100,9) -> 3.36 | O44: =ROUND(CP44,2) -> 347.98 | P44: =ROUND((ROUND((AC44*AW44*I44),2)*BC44),2) -> 0 | Q44: =(ROUND((ROUND((((ET44*1.2))*AV44*I44),2)*BB44),2)+ROUND((ROUND(((AE44-((EU44*1.2)))*AV44*I44),2)*BS44),2)) -> 0 | R44: =(ROUND((ROUND((((EU44*1.2))*AV44*I44),2)*BS44),2)+ROUND((ROUND(((AE44-((EU44*1.2)))*AV44*I44),2)*BS44),2)) -> 0 | S44: =ROUND((ROUND((AF44*AV44*I44),2)*BA44),2) -> 347.98 | T44: =ROUND(CU44*I44,2) -> 0 | U44: =CV44*I44 -> 27.861926 | V44: =CW44*I44 -> 0 | W44: =ROUND(CX44*I44,2) -> 0 | X44: =(ROUND((((S44+ROUND((ROUND((((EU44*1.2))*AV44*I44),2)*BS44),2))*AT44)/100),2)+ROUND(((ROUND((ROUND(((AE44-((EU44*1.2)))*AV44*I44),2)*BS44),2)*AT44)/100),2)) -> 302.74 | Y44: =(ROUND((((S44+ROUND((ROUND((((EU44*1.2))*AV44*I44),2)*BS44),2))*AU44)/100),2)+ROUND(((ROUND((ROUND(((AE44-((EU44*1.2)))*AV44*I44),2)*BS44),2)*AU44)/100),2)) -> 153.11 | AA44: 85736471 | AB44: =ROUND((AC44+AD44+AF44),6) -> 98.916 | AC44: =ROUND(((ES44*1)),6) -> 0 | AD44: =ROUND(((((ET44*1.2))-((EU44*1.2)))+AE44),6) -> 0 | AE44: =ROUND(((EU44*1.2)),6) -> 0 | AF44: =ROUND(((EV44*1.2)),6) -> 98.916 | AG44: =ROUND((AP44),6) -> 0 | AH44: =((EW44*1.2)) -> 7.92 | AI44: =((EX44*1.2)) -> 0 | AJ44: =(AS44) -> 0 | AK44: 82.43 | AL44: 0 | AM44: 0 | AN44: 0 | AO44: 82.43 | AP44: 0 | AQ44: 6.6 | AR44: 0 | AS44: 0 | AT44: 87 | AU44: 44 | AV44: 1.047 | AW44: 1 | AZ44: 1 | BA44: 1 | BB44: 1 | BC44: 1 | BH44: 0 | BI44: 1 | BJ44: ТСН-2001.6 Доп. 68, Сб. 65, т. 3, поз. 3 | BM44: 102 | BN44: 0 | BO44: 6.65-3-3 | BP44: 1 | BQ44: 60 | BR44: 0 | BS44: 1 | BT44: 1 | BU44: 1 | BV44: 1 | BW44: 1 | BX44: 1 | BZ44: 87 | CA44: 44 | CE44: 1566 | CF44: 0 | CG44: 0 | CM44: 0 | CN44: Поправка: Гл.12.Прил.8.п.8. 3_12.00.01.11.001 Наименование: При наличии напряженных и стесненных условий производства работ (стесненность, сложность складирования и транспортной логистики и т.п.) для объектов, расположенных в пределах круговой магистральной системы улиц "Садовое кольцо" города Москвы | CO44: 0 | CP44: =(P44+Q44+S44) -> 347.98 | CQ44: =ROUND((ROUND((AC44*AW44*1),2)*BC44),2) -> 0 | CR44: =(ROUND((ROUND((((ET44*1.2))*AV44*1),2)*BB44),2)+ROUND((ROUND(((AE44-((EU44*1.2)))*AV44*1),2)*BS44),2)) -> 0 | CS44: =(ROUND((ROUND((((EU44*1.2))*AV44*1),2)*BS44),2)+ROUND((ROUND(((AE44-((EU44*1.2)))*AV44*1),2)*BS44),2)) -> 0 | CT44: =ROUND((ROUND((AF44*AV44*1),2)*BA44),2) -> 103.57 | CU44: =AG44 -> 0 | CV44: =(AH44*AV44) -> 8.29224 | CW44: =AI44 -> 0 | CX44: =AJ44 -> 0 | CY44: =(ROUND((((S44+ROUND((ROUND((((EU44*1.2))*AV44*1),2)*BS44),2))*AT44)/100),2)+ROUND(((ROUND((ROUND(((AE44-((EU44*1.2)))*AV44*1),2)*BS44),2)*AT44)/100),2)) -> 302.74 | CZ44: =(ROUND((((S44+ROUND((ROUND((((EU44*1.2))*AV44*1),2)*BS44),2))*AU44)/100),2)+ROUND(((ROUND((ROUND(((AE44-((EU44*1.2)))*AV44*1),2)*BS44),2)*AU44)/100),2)) -> 153.11 | DB44: 23 | DD44: *1 | DE44: *1,2 | DF44: *1,2 | DG44: *1,2 | DI44: *1,2 | DJ44: *1,2 | DN44: 0 | DO44: 0 | DP44: 1 | DQ44: 1 | DU44: 1010 | DV44: 100 шт. | DW44: 100 шт. | DX44: 100 | EE44: 85133723 | EF44: 60 | EG44: Ремонтно-строительные работы | EH44: 0 | EJ44: 1 | EK44: 102 | EL44: ТСН-2001.6-65. Внутренние санитарно-технические работы: демонтаж и разборка | EM44: ТСН-2001.6-65-1 | EO44: Поправка: Гл.12.Прил.8.п.8. 3_12.00.01.11.001 | EQ44: 0 | ER44: 82.43 | ES44: 0 | ET44: 0 | EU44: 0 | EV44: 82.43 | EW44: 6.6 | EX44: 0 | EY44: 0 | FQ44: 0 | FR44: 0 | FS44: 0 | FX44: 87 | FY44: 44 | GD44: 1 | GF44: -1542409641 | GG44: 2 | GH44: 1 | GI44: 2 | GJ44: 0 | GK44: 0 | GL44: =ROUND(IF(AND(BH44=3,BI44=3,FS44<>0),P44,0),2) -> 0 | GM44: =ROUND(O44+X44+Y44,2)+GX44 -> 803.83 | GN44: =IF(OR(BI44=0,BI44=1),GM44-GX44,0) -> 803.83 | GO44: =IF(BI44=2,GM44-GX44,0) -> 0 | GP44: =IF(BI44=4,GM44-GX44,0) -> 0 | GR44: 0 | GS44: 3 | GT44: 0 | GV44: =ROUND((GT44),6) -> 0 | GW44: 1 | GX44: =ROUND(HC44*I44,2) -> 0 | HA44: 0 | HB44: 0 | HC44: =GV44*GW44 -> 0 | HS44: 0 | IK44: 0
A45: 17 | B45: 1 | C45: =ROW(SmtRes!A82) -> 82 | D45: =ROW(EtalonRes!A102) -> 102 | E45: 9 | F45: 6.65-3-3 | G45: Демонтаж крана водоразборного | H45: 100 шт. | I45: =ROUND((12+12+4+1+2+23+4+150+20+4+26+22+3+2+29+19+3)/100,9) -> 3.36 | J45: 0 | K45: =ROUND((12+12+4+1+2+23+4+150+20+4+26+22+3+2+29+19+3)/100,9) -> 3.36 | O45: =ROUND(CP45,2) -> 19608.67 | P45: =ROUND((ROUND((AC45*AW45*I45),2)*BC45),2) -> 0 | Q45: =(ROUND((ROUND((((ET45*1.2))*AV45*I45),2)*BB45),2)+ROUND((ROUND(((AE45-((EU45*1.2)))*AV45*I45),2)*BS45),2)) -> 0 | R45: =(ROUND((ROUND((((EU45*1.2))*AV45*I45),2)*BS45),2)+ROUND((ROUND(((AE45-((EU45*1.2)))*AV45*I45),2)*BS45),2)) -> 0 | S45: =ROUND((ROUND((AF45*AV45*I45),2)*BA45),2) -> 19608.67 | T45: =ROUND(CU45*I45,2) -> 0 | U45: =CV45*I45 -> 27.861926 | V45: =CW45*I45 -> 0 | W45: =ROUND(CX45*I45,2) -> 0 | X45: =(ROUND((((S45+ROUND((ROUND((((EU45*1.2))*AV45*I45),2)*BS45),2))*AT45)/100),2)+ROUND(((ROUND((ROUND(((AE45-((EU45*1.2)))*AV45*I45),2)*BS45),2)*AT45)/100),2)) -> 17059.54 | Y45: =(ROUND((((S45+ROUND((ROUND((((EU45*1.2))*AV45*I45),2)*BS45),2))*AU45)/100),2)+ROUND(((ROUND((ROUND(((AE45-((EU45*1.2)))*AV45*I45),2)*BS45),2)*AU45)/100),2)) -> 8627.81 | AA45: 85736473 | AB45: =ROUND((AC45+AD45+AF45),6) -> 98.916 | AC45: =ROUND(((ES45*1)),6) -> 0 | AD45: =ROUND(((((ET45*1.2))-((EU45*1.2)))+AE45),6) -> 0 | AE45: =ROUND(((EU45*1.2)),6) -> 0 | AF45: =ROUND(((EV45*1.2)),6) -> 98.916 | AG45: =ROUND((AP45),6) -> 0 | AH45: =((EW45*1.2)) -> 7.92 | AI45: =((EX45*1.2)) -> 0 | AJ45: =(AS45) -> 0 | AK45: 82.43 | AL45: 0 | AM45: 0 | AN45: 0 | AO45: 82.43 | AP45: 0 | AQ45: 6.6 | AR45: 0 | AS45: 0 | AT45: 87 | AU45: 44 | AV45: 1.047 | AW45: 1 | AZ45: 1 | BA45: 56.35 | BB45: 1 | BC45: 1 | BH45: 0 | BI45: 1 | BJ45: ТСН-2001.6 Доп. 68, Сб. 65, т. 3, поз. 3 | BM45: 102 | BN45: 0 | BO45: 6.65-3-3 | BP45: 1 | BQ45: 60 | BR45: 0 | BS45: 56.35 | BT45: 1 | BU45: 1 | BV45: 1 | BW45: 1 | BX45: 1 | BZ45: 87 | CA45: 44 | CE45: 1566 | CF45: 0 | CG45: 0 | CM45: 0 | CN45: Поправка: Гл.12.Прил.8.п.8. 3_12.00.01.11.001 Наименование: При наличии напряженных и стесненных условий производства работ (стесненность, сложность складирования и транспортной логистики и т.п.) для объектов, расположенных в пределах круговой магистральной системы улиц "Садовое кольцо" города Москвы | CO45: 0 | CP45: =(P45+Q45+S45) -> 19608.67 | CQ45: =ROUND((ROUND((AC45*AW45*1),2)*BC45),2) -> 0 | CR45: =(ROUND((ROUND((((ET45*1.2))*AV45*1),2)*BB45),2)+ROUND((ROUND(((AE45-((EU45*1.2)))*AV45*1),2)*BS45),2)) -> 0 | CS45: =(ROUND((ROUND((((EU45*1.2))*AV45*1),2)*BS45),2)+ROUND((ROUND(((AE45-((EU45*1.2)))*AV45*1),2)*BS45),2)) -> 0 | CT45: =ROUND((ROUND((AF45*AV45*1),2)*BA45),2) -> 5836.17 | CU45: =AG45 -> 0 | CV45: =(AH45*AV45) -> 8.29224 | CW45: =AI45 -> 0 | CX45: =AJ45 -> 0 | CY45: =(ROUND((((S45+ROUND((ROUND((((EU45*1.2))*AV45*1),2)*BS45),2))*AT45)/100),2)+ROUND(((ROUND((ROUND(((AE45-((EU45*1.2)))*AV45*1),2)*BS45),2)*AT45)/100),2)) -> 17059.54 | CZ45: =(ROUND((((S45+ROUND((ROUND((((EU45*1.2))*AV45*1),2)*BS45),2))*AU45)/100),2)+ROUND(((ROUND((ROUND(((AE45-((EU45*1.2)))*AV45*1),2)*BS45),2)*AU45)/100),2)) -> 8627.81 | DB45: 24 | DD45: *1 | DE45: *1,2 | DF45: *1,2 | DG45: *1,2 | DI45: *1,2 | DJ45: *1,2 | DN45: 0 | DO45: 0 | DP45: 1 | DQ45: 1 | DU45: 1010 | DV45: 100 шт. | DW45: 100 шт. | DX45: 100 | EE45: 85133723 | EF45: 60 | EG45: Ремонтно-строительные работы | EH45: 0 | EJ45: 1 | EK45: 102 | EL45: ТСН-2001.6-65. Внутренние санитарно-технические работы: демонтаж и разборка | EM45: ТСН-2001.6-65-1 | EO45: Поправка: Гл.12.Прил.8.п.8. 3_12.00.01.11.001 | EQ45: 0 | ER45: 82.43 | ES45: 0 | ET45: 0 | EU45: 0 | EV45: 82.43 | EW45: 6.6 | EX45: 0 | EY45: 0 | FQ45: 0 | FR45: 0 | FS45: 0 | FX45: 87 | FY45: 44 | GD45: 1 | GF45: -1542409641 | GG45: 2 | GH45: 1 | GI45: 2 | GJ45: 0 | GK45: 0 | GL45: =ROUND(IF(AND(BH45=3,BI45=3,FS45<>0),P45,0),2) -> 0 | GM45: =ROUND(O45+X45+Y45,2)+GX45 -> 45296.02 | GN45: =IF(OR(BI45=0,BI45=1),GM45-GX45,0) -> 45296.02 | GO45: =IF(BI45=2,GM45-GX45,0) -> 0 | GP45: =IF(BI45=4,GM45-GX45,0) -> 0 | GR45: 0 | GS45: 3 | GT45: 0 | GV45: =ROUND((GT45),6) -> 0 | GW45: 1 | GX45: =ROUND(HC45*I45,2) -> 0 | HA45: 0 | HB45: 0 | HC45: =GV45*GW45 -> 0 | HS45: 0 | IK45: 0
A46: 17 | B46: 1 | C46: =ROW(SmtRes!A84) -> 84 | D46: =ROW(EtalonRes!A104) -> 104 | E46: 10 | F46: 6.65-3-1 | G46: Демонтаж смесителя с душем | H46: 100 шт. | I46: =ROUND((8+6+1+40+31+1+2+1)/100,9) -> 0.9 | J46: 0 | K46: =ROUND((8+6+1+40+31+1+2+1)/100,9) -> 0.9 | O46: =ROUND(CP46,2) -> 2344.45 | P46: =ROUND((ROUND((AC46*AW46*I46),2)*BC46),2) -> 0 | Q46: =(ROUND((ROUND((((ET46*1.2))*AV46*I46),2)*BB46),2)+ROUND((ROUND(((AE46-((EU46*1.2)))*AV46*I46),2)*BS46),2)) -> 0 | R46: =(ROUND((ROUND((((EU46*1.2))*AV46*I46),2)*BS46),2)+ROUND((ROUND(((AE46-((EU46*1.2)))*AV46*I46),2)*BS46),2)) -> 0 | S46: =ROUND((ROUND((AF46*AV46*I46),2)*BA46),2) -> 2344.45 | T46: =ROUND(CU46*I46,2) -> 0 | U46: =CV46*I46 -> 187.70616 | V46: =CW46*I46 -> 0 | W46: =ROUND(CX46*I46,2) -> 0 | X46: =(ROUND((((S46+ROUND((ROUND((((EU46*1.2))*AV46*I46),2)*BS46),2))*AT46)/100),2)+ROUND(((ROUND((ROUND(((AE46-((EU46*1.2)))*AV46*I46),2)*BS46),2)*AT46)/100),2)) -> 2039.67 | Y46: =(ROUND((((S46+ROUND((ROUND((((EU46*1.2))*AV46*I46),2)*BS46),2))*AU46)/100),2)+ROUND(((ROUND((ROUND(((AE46-((EU46*1.2)))*AV46*I46),2)*BS46),2)*AU46)/100),2)) -> 1031.56 | AA46: 85736471 | AB46: =ROUND((AC46+AD46+AF46),6) -> 2488.008 | AC46: =ROUND(((ES46*1)),6) -> 0 | AD46: =ROUND(((((ET46*1.2))-((EU46*1.2)))+AE46),6) -> 0 | AE46: =ROUND(((EU46*1.2)),6) -> 0 | AF46: =ROUND(((EV46*1.2)),6) -> 2488.008 | AG46: =ROUND((AP46),6) -> 0 | AH46: =((EW46*1.2)) -> 199.2 | AI46: =((EX46*1.2)) -> 0 | AJ46: =(AS46) -> 0 | AK46: 2073.34 | AL46: 0 | AM46: 0 | AN46: 0 | AO46: 2073.34 | AP46: 0 | AQ46: 166 | AR46: 0 | AS46: 0 | AT46: 87 | AU46: 44 | AV46: 1.047 | AW46: 1 | AZ46: 1 | BA46: 1 | BB46: 1 | BC46: 1 | BH46: 0 | BI46: 1 | BJ46: ТСН-2001.6 Доп. 68, Сб. 65, т. 3, поз. 1 | BM46: 102 | BN46: 0 | BO46: 6.65-3-1 | BP46: 1 | BQ46: 60 | BR46: 0 | BS46: 1 | BT46: 1 | BU46: 1 | BV46: 1 | BW46: 1 | BX46: 1 | BZ46: 87 | CA46: 44 | CE46: 1566 | CF46: 0 | CG46: 0 | CM46: 0 | CN46: Поправка: Гл.12.Прил.8.п.8. 3_12.00.01.11.001 Наименование: При наличии напряженных и стесненных условий производства работ (стесненность, сложность складирования и транспортной логистики и т.п.) для объектов, расположенных в пределах круговой магистральной системы улиц "Садовое кольцо" города Москвы | CO46: 0 | CP46: =(P46+Q46+S46) -> 2344.45 | CQ46: =ROUND((ROUND((AC46*AW46*1),2)*BC46),2) -> 0 | CR46: =(ROUND((ROUND((((ET46*1.2))*AV46*1),2)*BB46),2)+ROUND((ROUND(((AE46-((EU46*1.2)))*AV46*1),2)*BS46),2)) -> 0 | CS46: =(ROUND((ROUND((((EU46*1.2))*AV46*1),2)*BS46),2)+ROUND((ROUND(((AE46-((EU46*1.2)))*AV46*1),2)*BS46),2)) -> 0 | CT46: =ROUND((ROUND((AF46*AV46*1),2)*BA46),2) -> 2604.94 | CU46: =AG46 -> 0 | CV46: =(AH46*AV46) -> 208.5624 | CW46: =AI46 -> 0 | CX46: =AJ46 -> 0 | CY46: =(ROUND((((S46+ROUND((ROUND((((EU46*1.2))*AV46*1),2)*BS46),2))*AT46)/100),2)+ROUND(((ROUND((ROUND(((AE46-((EU46*1.2)))*AV46*1),2)*BS46),2)*AT46)/100),2)) -> 2039.67 | CZ46: =(ROUND((((S46+ROUND((ROUND((((EU46*1.2))*AV46*1),2)*BS46),2))*AU46)/100),2)+ROUND(((ROUND((ROUND(((AE46-((EU46*1.2)))*AV46*1),2)*BS46),2)*AU46)/100),2)) -> 1031.56 | DB46: 25 | DD46: *1 | DE46: *1,2 | DF46: *1,2 | DG46: *1,2 | DI46: *1,2 | DJ46: *1,2 | DN46: 0 | DO46: 0 | DP46: 1 | DQ46: 1 | DU46: 1010 | DV46: 100 шт. | DW46: 100 шт. | DX46: 100 | EE46: 85133723 | EF46: 60 | EG46: Ремонтно-строительные работы | EH46: 0 | EJ46: 1 | EK46: 102 | EL46: ТСН-2001.6-65. Внутренние санитарно-технические работы: демонтаж и разборка | EM46: ТСН-2001.6-65-1 | EO46: Поправка: Гл.12.Прил.8.п.8. 3_12.00.01.11.001 | EQ46: 0 | ER46: 2073.34 | ES46: 0 | ET46: 0 | EU46: 0 | EV46: 2073.34 | EW46: 166 | EX46: 0 | EY46: 0 | FQ46: 0 | FR46: 0 | FS46: 0 | FX46: 87 | FY46: 44 | GD46: 1 | GF46: -1721976045 | GG46: 2 | GH46: 1 | GI46: 2 | GJ46: 0 | GK46: 0 | GL46: =ROUND(IF(AND(BH46=3,BI46=3,FS46<>0),P46,0),2) -> 0 | GM46: =ROUND(O46+X46+Y46,2)+GX46 -> 5415.68 | GN46: =IF(OR(BI46=0,BI46=1),GM46-GX46,0) -> 5415.68 | GO46: =IF(BI46=2,GM46-GX46,0) -> 0 | GP46: =IF(BI46=4,GM46-GX46,0) -> 0 | GR46: 0 | GS46: 3 | GT46: 0 | GV46: =ROUND((GT46),6) -> 0 | GW46: 1 | GX46: =ROUND(HC46*I46,2) -> 0 | HA46: 0 | HB46: 0 | HC46: =GV46*GW46 -> 0 | HS46: 0 | IK46: 0
A47: 17 | B47: 1 | C47: =ROW(SmtRes!A86) -> 86 | D47: =ROW(EtalonRes!A106) -> 106 | E47: 10 | F47: 6.65-3-1 | G47: Демонтаж смесителя с душем | H47: 100 шт. | I47: =ROUND((8+6+1+40+31+1+2+1)/100,9) -> 0.9 | J47: 0 | K47: =ROUND((8+6+1+40+31+1+2+1)/100,9) -> 0.9 | O47: =ROUND(CP47,2) -> 132109.76 | P47: =ROUND((ROUND((AC47*AW47*I47),2)*BC47),2) -> 0 | Q47: =(ROUND((ROUND((((ET47*1.2))*AV47*I47),2)*BB47),2)+ROUND((ROUND(((AE47-((EU47*1.2)))*AV47*I47),2)*BS47),2)) -> 0 | R47: =(ROUND((ROUND((((EU47*1.2))*AV47*I47),2)*BS47),2)+ROUND((ROUND(((AE47-((EU47*1.2)))*AV47*I47),2)*BS47),2)) -> 0 | S47: =ROUND((ROUND((AF47*AV47*I47),2)*BA47),2) -> 132109.76 | T47: =ROUND(CU47*I47,2) -> 0 | U47: =CV47*I47 -> 187.70616 | V47: =CW47*I47 -> 0 | W47: =ROUND(CX47*I47,2) -> 0 | X47: =(ROUND((((S47+ROUND((ROUND((((EU47*1.2))*AV47*I47),2)*BS47),2))*AT47)/100),2)+ROUND(((ROUND((ROUND(((AE47-((EU47*1.2)))*AV47*I47),2)*BS47),2)*AT47)/100),2)) -> 114935.49 | Y47: =(ROUND((((S47+ROUND((ROUND((((EU47*1.2))*AV47*I47),2)*BS47),2))*AU47)/100),2)+ROUND(((ROUND((ROUND(((AE47-((EU47*1.2)))*AV47*I47),2)*BS47),2)*AU47)/100),2)) -> 58128.29 | AA47: 85736473 | AB47: =ROUND((AC47+AD47+AF47),6) -> 2488.008 | AC47: =ROUND(((ES47*1)),6) -> 0 | AD47: =ROUND(((((ET47*1.2))-((EU47*1.2)))+AE47),6) -> 0 | AE47: =ROUND(((EU47*1.2)),6) -> 0 | AF47: =ROUND(((EV47*1.2)),6) -> 2488.008 | AG47: =ROUND((AP47),6) -> 0 | AH47: =((EW47*1.2)) -> 199.2 | AI47: =((EX47*1.2)) -> 0 | AJ47: =(AS47) -> 0 | AK47: 2073.34 | AL47: 0 | AM47: 0 | AN47: 0 | AO47: 2073.34 | AP47: 0 | AQ47: 166 | AR47: 0 | AS47: 0 | AT47: 87 | AU47: 44 | AV47: 1.047 | AW47: 1 | AZ47: 1 | BA47: 56.35 | BB47: 1 | BC47: 1 | BH47: 0 | BI47: 1 | BJ47: ТСН-2001.6 Доп. 68, Сб. 65, т. 3, поз. 1 | BM47: 102 | BN47: 0 | BO47: 6.65-3-1 | BP47: 1 | BQ47: 60 | BR47: 0 | BS47: 56.35 | BT47: 1 | BU47: 1 | BV47: 1 | BW47: 1 | BX47: 1 | BZ47: 87 | CA47: 44 | CE47: 1566 | CF47: 0 | CG47: 0 | CM47: 0 | CN47: Поправка: Гл.12.Прил.8.п.8. 3_12.00.01.11.001 Наименование: При наличии напряженных и стесненных условий производства работ (стесненность, сложность складирования и транспортной логистики и т.п.) для объектов, расположенных в пределах круговой магистральной системы улиц "Садовое кольцо" города Москвы | CO47: 0 | CP47: =(P47+Q47+S47) -> 132109.76 | CQ47: =ROUND((ROUND((AC47*AW47*1),2)*BC47),2) -> 0 | CR47: =(ROUND((ROUND((((ET47*1.2))*AV47*1),2)*BB47),2)+ROUND((ROUND(((AE47-((EU47*1.2)))*AV47*1),2)*BS47),2)) -> 0 | CS47: =(ROUND((ROUND((((EU47*1.2))*AV47*1),2)*BS47),2)+ROUND((ROUND(((AE47-((EU47*1.2)))*AV47*1),2)*BS47),2)) -> 0 | CT47: =ROUND((ROUND((AF47*AV47*1),2)*BA47),2) -> 146788.37 | CU47: =AG47 -> 0 | CV47: =(AH47*AV47) -> 208.5624 | CW47: =AI47 -> 0 | CX47: =AJ47 -> 0 | CY47: =(ROUND((((S47+ROUND((ROUND((((EU47*1.2))*AV47*1),2)*BS47),2))*AT47)/100),2)+ROUND(((ROUND((ROUND(((AE47-((EU47*1.2)))*AV47*1),2)*BS47),2)*AT47)/100),2)) -> 114935.49 | CZ47: =(ROUND((((S47+ROUND((ROUND((((EU47*1.2))*AV47*1),2)*BS47),2))*AU47)/100),2)+ROUND(((ROUND((ROUND(((AE47-((EU47*1.2)))*AV47*1),2)*BS47),2)*AU47)/100),2)) -> 58128.29 | DB47: 26 | DD47: *1 | DE47: *1,2 | DF47: *1,2 | DG47: *1,2 | DI47: *1,2 | DJ47: *1,2 | DN47: 0 | DO47: 0 | DP47: 1 | DQ47: 1 | DU47: 1010 | DV47: 100 шт. | DW47: 100 шт. | DX47: 100 | EE47: 85133723 | EF47: 60 | EG47: Ремонтно-строительные работы | EH47: 0 | EJ47: 1 | EK47: 102 | EL47: ТСН-2001.6-65. Внутренние санитарно-технические работы: демонтаж и разборка | EM47: ТСН-2001.6-65-1 | EO47: Поправка: Гл.12.Прил.8.п.8. 3_12.00.01.11.001 | EQ47: 0 | ER47: 2073.34 | ES47: 0 | ET47: 0 | EU47: 0 | EV47: 2073.34 | EW47: 166 | EX47: 0 | EY47: 0 | FQ47: 0 | FR47: 0 | FS47: 0 | FX47: 87 | FY47: 44 | GD47: 1 | GF47: -1721976045 | GG47: 2 | GH47: 1 | GI47: 2 | GJ47: 0 | GK47: 0 | GL47: =ROUND(IF(AND(BH47=3,BI47=3,FS47<>0),P47,0),2) -> 0 | GM47: =ROUND(O47+X47+Y47,2)+GX47 -> 305173.54 | GN47: =IF(OR(BI47=0,BI47=1),GM47-GX47,0) -> 305173.54 | GO47: =IF(BI47=2,GM47-GX47,0) -> 0 | GP47: =IF(BI47=4,GM47-GX47,0) -> 0 | GR47: 0 | GS47: 3 | GT47: 0 | GV47: =ROUND((GT47),6) -> 0 | GW47: 1 | GX47: =ROUND(HC47*I47,2) -> 0 | HA47: 0 | HB47: 0 | HC47: =GV47*GW47 -> 0 | HS47: 0 | IK47: 0
A49: 51 | B49: =B24 -> 1 | C49: =A24 -> 4 | D49: =ROW(A24) -> 24 | F49: =IF(F24<>"",F24,"") -> Новый раздел | G49: =IF(G24<>"",G24,"") -> Демонтажные работы. | H49: 0 | O49: =ROUND(AB49,2) -> 9788.2 | P49: =ROUND(AC49,2) -> 484.79 | Q49: =ROUND(AD49,2) -> 39.05 | R49: =ROUND(AE49,2) -> 0.87 | S49: =ROUND(AF49,2) -> 9264.36 | T49: =ROUND(AG49,2) -> 0 | U49: =AH49 -> 820.47351 | V49: =AI49 -> 0 | W49: =ROUND(AJ49,2) -> 0 | X49: =ROUND(AK49,2) -> 8116.06 | Y49: =ROUND(AL49,2) -> 4114.83 | AB49: =ROUND(SUMIF(AA28:AA47,"=85736471",O28:O47),2) -> 9788.2 | AC49: =ROUND(SUMIF(AA28:AA47,"=85736471",P28:P47),2) -> 484.79 | AD49: =ROUND(SUMIF(AA28:AA47,"=85736471",Q28:Q47),2) -> 39.05 | AE49: =ROUND(SUMIF(AA28:AA47,"=85736471",R28:R47),2) -> 0.87 | AF49: =ROUND(SUMIF(AA28:AA47,"=85736471",S28:S47),2) -> 9264.36 | AG49: =ROUND(SUMIF(AA28:AA47,"=85736471",T28:T47),2) -> 0 | AH49: =SUMIF(AA28:AA47,"=85736471",U28:U47) -> 820.47351 | AI49: =SUMIF(AA28:AA47,"=85736471",V28:V47) -> 0 | AJ49: =ROUND(SUMIF(AA28:AA47,"=85736471",W28:W47),2) -> 0 | AK49: =ROUND(SUMIF(AA28:AA47,"=85736471",X28:X47),2) -> 8116.06 | AL49: =ROUND(SUMIF(AA28:AA47,"=85736471",Y28:Y47),2) -> 4114.83 | AO49: =ROUND(BX49,2) -> 0 | AP49: =ROUND(BY49,2) -> 0 | AQ49: =ROUND(BZ49,2) -> 0 | AR49: =ROUND(CA49,2) -> 22019.09 | AS49: =ROUND(CB49,2) -> 22019.09 | AT49: =ROUND(CC49,2) -> 0 | AU49: =ROUND(CD49,2) -> 0 | AV49: =ROUND(CE49,2) -> 484.79 | ... BD49: =ROUND(CM49,2) -> 0 | BX49: =ROUND(SUMIF(AA28:AA47,"=85736471",FQ28:FQ47),2) -> 0 | BY49: =ROUND(SUMIF(AA28:AA47,"=85736471",FR28:FR47),2) -> 0 | BZ49: =ROUND(SUMIF(AA28:AA47,"=85736471",GL28:GL47),2) -> 0 | CA49: =ROUND(SUMIF(AA28:AA47,"=85736471",GM28:GM47),2) -> 22019.09 | CB49: =ROUND(SUMIF(AA28:AA47,"=85736471",GN28:GN47),2) -> 22019.09 | CC49: =ROUND(SUMIF(AA28:AA47,"=85736471",GO28:GO47),2) -> 0 | CD49: =ROUND(SUMIF(AA28:AA47,"=85736471",GP28:GP47),2) -> 0 | CE49: =AC49-BX49 -> 484.79 | CF49: =AC49-BY49 -> 484.79 | CG49: =BX49-BZ49 -> 0 | CH49: =AC49-BX49-BY49+BZ49 -> 484.79 | CI49: =BY49-BZ49 -> 0 | CJ49: =ROUND(SUMIF(AA28:AA47,"=85736471",GX28:GX47),2) -> 0 | CK49: =ROUND(SUMIF(AA28:AA47,"=85736471",GY28:GY47),2) -> 0 | CL49: =ROUND(SUMIF(AA28:AA47,"=85736471",GZ28:GZ47),2) -> 0 | CM49: =ROUND(SUMIF(AA28:AA47,"=85736471",HD28:HD47),2) -> 0 | DG49: =ROUND(DT49,2) -> 530019.82 | DH49: =ROUND(DU49,2) -> 7529.46 | DI49: =ROUND(DV49,2) -> 443.67 | DJ49: =ROUND(DW49,2) -> 49.03 | DK49: =ROUND(DX49,2) -> 522046.69 | DL49: =ROUND(DY49,2) -> 0 | DM49: =DZ49 -> 820.47351 | DN49: =EA49 -> 0 | DO49: =ROUND(EB49,2) -> 0 | DP49: =ROUND(EC49,2) -> 457339.87 | DQ49: =ROUND(ED49,2) -> 231870.78 | DT49: =ROUND(SUMIF(AA28:AA47,"=85736473",O28:O47),2) -> 530019.82 | DU49: =ROUND(SUMIF(AA28:AA47,"=85736473",P28:P47),2) -> 7529.46 | DV49: =ROUND(SUMIF(AA28:AA47,"=85736473",Q28:Q47),2) -> 443.67 | DW49: =ROUND(SUMIF(AA28:AA47,"=85736473",R28:R47),2) -> 49.03 | DX49: =ROUND(SUMIF(AA28:AA47,"=85736473",S28:S47),2) -> 522046.69 | DY49: =ROUND(SUMIF(AA28:AA47,"=85736473",T28:T47),2) -> 0 | DZ49: =SUMIF(AA28:AA47,"=85736473",U28:U47) -> 820.47351 | EA49: =SUMIF(AA28:AA47,"=85736473",V28:V47) -> 0 | EB49: =ROUND(SUMIF(AA28:AA47,"=85736473",W28:W47),2) -> 0 | EC49: =ROUND(SUMIF(AA28:AA47,"=85736473",X28:X47),2) -> 457339.87 | ED49: =ROUND(SUMIF(AA28:AA47,"=85736473",Y28:Y47),2) -> 231870.78 | EG49: =ROUND(FP49,2) -> 0 | EH49: =ROUND(FQ49,2) -> 0 | EI49: =ROUND(FR49,2) -> 0 | EJ49: =ROUND(FS49,2) -> 1219230.5 | EK49: =ROUND(FT49,2) -> 1219230.5 | EL49: =ROUND(FU49,2) -> 0 | EM49: =ROUND(FV49,2) -> 0 | EN49: =ROUND(FW49,2) -> 7529.46 | ... EV49: =ROUND(GE49,2) -> 0 | FP49: =ROUND(SUMIF(AA28:AA47,"=85736473",FQ28:FQ47),2) -> 0 | FQ49: =ROUND(SUMIF(AA28:AA47,"=85736473",FR28:FR47),2) -> 0 | FR49: =ROUND(SUMIF(AA28:AA47,"=85736473",GL28:GL47),2) -> 0 | FS49: =ROUND(SUMIF(AA28:AA47,"=85736473",GM28:GM47),2) -> 1219230.5 | FT49: =ROUND(SUMIF(AA28:AA47,"=85736473",GN28:GN47),2) -> 1219230.5 | FU49: =ROUND(SUMIF(AA28:AA47,"=85736473",GO28:GO47),2) -> 0 | FV49: =ROUND(SUMIF(AA28:AA47,"=85736473",GP28:GP47),2) -> 0 | FW49: =DU49-FP49 -> 7529.46 | FX49: =DU49-FQ49 -> 7529.46 | FY49: =FP49-FR49 -> 0 | FZ49: =DU49-FP49-FQ49+FR49 -> 7529.46 | GA49: =FQ49-FR49 -> 0 | GB49: =ROUND(SUMIF(AA28:AA47,"=85736473",GX28:GX47),2) -> 0 | GC49: =ROUND(SUMIF(AA28:AA47,"=85736473",GY28:GY47),2) -> 0 | GD49: =ROUND(SUMIF(AA28:AA47,"=85736473",GZ28:GZ47),2) -> 0 | GE49: =ROUND(SUMIF(AA28:AA47,"=85736473",HD28:HD47),2) -> 0 | GX49: 0
A51: 50 | B51: 0 | C51: 0 | D51: 1 | E51: 201 | F51: =ROUND(Source!O49,O51) -> 9788.2 | G51: ПЗ | H51: Прямые затраты | K51: 201 | L51: 1 | M51: 3 | O51: 2 | P51: =ROUND(Source!DG49,O51) -> 530019.82 | W51: 9788.2 | X51: 1 | Y51: 9788.2 | Z51: 530019.82 | AA51: 1 | AB51: 530019.82
A52: 50 | B52: 0 | C52: 0 | D52: 1 | E52: 202 | F52: =ROUND(Source!P49,O52) -> 484.79 | G52: СтМатОб | H52: Стоимость материальных ресурсов (всего) | K52: 202 | L52: 2 | M52: 3 | O52: 2 | P52: =ROUND(Source!DH49,O52) -> 7529.46 | W52: 484.79 | X52: 1 | Y52: 484.79 | Z52: 7529.46 | AA52: 1 | AB52: 7529.46
A53: 50 | B53: 0 | C53: 0 | D53: 1 | E53: 222 | F53: =ROUND(Source!AO49,O53) -> 0 | G53: СтМатОбЗак | H53: Стоимость материалов и оборудования заказчика | K53: 222 | L53: 3 | M53: 3 | O53: 2 | P53: =ROUND(Source!EG49,O53) -> 0 | W53: 0 | X53: 1 | Y53: 0 | Z53: 0 | AA53: 1 | AB53: 0
A54: 50 | B54: 0 | C54: 0 | D54: 1 | E54: 225 | F54: =ROUND(Source!AV49,O54) -> 484.79 | G54: СтМатОбПод | H54: Стоимость материалов и оборудования подрядчика | K54: 225 | L54: 4 | M54: 3 | O54: 2 | P54: =ROUND(Source!EN49,O54) -> 7529.46 | W54: 484.79 | X54: 1 | Y54: 484.79 | Z54: 7529.46 | AA54: 1 | AB54: 7529.46
A55: 50 | B55: 0 | C55: 0 | D55: 1 | E55: 226 | F55: =ROUND(Source!AW49,O55) -> 484.79 | G55: СтМат | H55: Стоимость материалов (всего) | K55: 226 | L55: 5 | M55: 3 | O55: 2 | P55: =ROUND(Source!EO49,O55) -> 7529.46 | W55: 484.79 | X55: 1 | Y55: 484.79 | Z55: 7529.46 | AA55: 1 | AB55: 7529.46
A56: 50 | B56: 0 | C56: 0 | D56: 1 | E56: 227 | F56: =ROUND(Source!AX49,O56) -> 0 | G56: СтМатЗак | H56: Стоимость материалов заказчика | K56: 227 | L56: 6 | M56: 3 | O56: 2 | P56: =ROUND(Source!EP49,O56) -> 0 | W56: 0 | X56: 1 | Y56: 0 | Z56: 0 | AA56: 1 | AB56: 0
A57: 50 | B57: 0 | C57: 0 | D57: 1 | E57: 228 | F57: =ROUND(Source!AY49,O57) -> 484.79 | G57: СтМатПод | H57: Стоимость материалов подрядчика | K57: 228 | L57: 7 | M57: 3 | O57: 2 | P57: =ROUND(Source!EQ49,O57) -> 7529.46 | W57: 484.79 | X57: 1 | Y57: 484.79 | Z57: 7529.46 | AA57: 1 | AB57: 7529.46
A58: 50 | B58: 0 | C58: 0 | D58: 1 | E58: 216 | F58: =ROUND(Source!AP49,O58) -> 0 | G58: Оборуд | H58: Стоимость оборудования (всего) | K58: 216 | L58: 8 | M58: 3 | O58: 2 | P58: =ROUND(Source!EH49,O58) -> 0 | W58: 0 | X58: 1 | Y58: 0 | Z58: 0 | AA58: 1 | AB58: 0
A59: 50 | B59: 0 | C59: 0 | D59: 1 | E59: 223 | F59: =ROUND(Source!AQ49,O59) -> 0 | G59: ОборудЗак | H59: Стоимость оборудования заказчика | K59: 223 | L59: 9 | M59: 3 | O59: 2 | P59: =ROUND(Source!EI49,O59) -> 0 | W59: 0 | X59: 1 | Y59: 0 | Z59: 0 | AA59: 1 | AB59: 0
A60: 50 | B60: 0 | C60: 0 | D60: 1 | E60: 229 | F60: =ROUND(Source!AZ49,O60) -> 0 | G60: ОборудПод | H60: Стоимость оборудования подрядчика | K60: 229 | L60: 10 | M60: 3 | O60: 2 | P60: =ROUND(Source!ER49,O60) -> 0 | W60: 0 | X60: 1 | Y60: 0 | Z60: 0 | AA60: 1 | AB60: 0
A61: 50 | B61: 0 | C61: 0 | D61: 1 | E61: 203 | F61: =ROUND(Source!Q49,O61) -> 39.05 | G61: ЭММ | H61: Эксплуатация машин | K61: 203 | L61: 11 | M61: 3 | O61: 2 | P61: =ROUND(Source!DI49,O61) -> 443.67 | W61: 39.05 | X61: 1 | Y61: 39.05 | Z61: 443.67 | AA61: 1 | AB61: 443.67
A62: 50 | B62: 0 | C62: 0 | D62: 1 | E62: 231 | F62: =ROUND(Source!BB49,O62) -> 0 | G62: ЭММсНРиСП | H62: Эксплуатация машин по ТСН-2001.16 | K62: 231 | L62: 12 | M62: 3 | O62: 2 | P62: =ROUND(Source!ET49,O62) -> 0 | W62: 0 | X62: 1 | Y62: 0 | Z62: 0 | AA62: 1 | AB62: 0
A63: 50 | B63: 0 | C63: 0 | D63: 1 | E63: 204 | F63: =ROUND(Source!R49,O63) -> 0.87 | G63: ЗПМ | H63: ЗП машинистов | K63: 204 | L63: 13 | M63: 3 | O63: 2 | P63: =ROUND(Source!DJ49,O63) -> 49.03 | W63: 0.87 | X63: 1 | Y63: 0.87 | Z63: 49.03 | AA63: 1 | AB63: 49.03
A64: 50 | B64: 0 | C64: 0 | D64: 1 | E64: 205 | F64: =ROUND(Source!S49,O64) -> 9264.36 | G64: ОЗП | H64: Основная ЗП рабочих | K64: 205 | L64: 14 | M64: 3 | O64: 2 | P64: =ROUND(Source!DK49,O64) -> 522046.69 | W64: 9264.36 | X64: 1 | Y64: 9264.36 | Z64: 522046.69 | AA64: 1 | AB64: 522046.69
A65: 50 | B65: 0 | C65: 0 | D65: 1 | E65: 232 | F65: =ROUND(Source!BC49,O65) -> 0 | G65: ОЗПсНРиСП | H65: Основная ЗП рабочих по ТСН-2001.16 | K65: 232 | L65: 15 | M65: 3 | O65: 2 | P65: =ROUND(Source!EU49,O65) -> 0 | W65: 0 | X65: 1 | Y65: 0 | Z65: 0 | AA65: 1 | AB65: 0
A66: 50 | B66: 0 | C66: 0 | D66: 1 | E66: 214 | F66: =ROUND(Source!AS49,O66) -> 22019.09 | G66: Строит | H66: Строительные работы с НР и СП | K66: 214 | L66: 16 | M66: 3 | O66: 2 | P66: =ROUND(Source!EK49,O66) -> 1219230.5 | W66: 22019.09 | X66: 1 | Y66: 22019.09 | Z66: 1219230.5 | AA66: 1 | AB66: 1219230.5
A67: 50 | B67: 0 | C67: 0 | D67: 1 | E67: 215 | F67: =ROUND(Source!AT49,O67) -> 0 | G67: Монтаж | H67: Монтажные работы с НР и СП | K67: 215 | L67: 17 | M67: 3 | O67: 2 | P67: =ROUND(Source!EL49,O67) -> 0 | W67: 0 | X67: 1 | Y67: 0 | Z67: 0 | AA67: 1 | AB67: 0
A68: 50 | B68: 0 | C68: 0 | D68: 1 | E68: 217 | F68: =ROUND(Source!AU49,O68) -> 0 | G68: Прочие | H68: Прочие работы с НР и СП | K68: 217 | L68: 18 | M68: 3 | O68: 2 | P68: =ROUND(Source!EM49,O68) -> 0 | W68: 0 | X68: 1 | Y68: 0 | Z68: 0 | AA68: 1 | AB68: 0
A69: 50 | B69: 0 | C69: 0 | D69: 1 | E69: 230 | F69: =ROUND(Source!BA49,O69) -> 0 | G69: ПрочиеЗатр | H69: Прочие затраты по ТСН-2001.16 | K69: 230 | L69: 19 | M69: 3 | O69: 2 | P69: =ROUND(Source!ES49,O69) -> 0 | W69: 0 | X69: 1 | Y69: 0 | Z69: 0 | AA69: 1 | AB69: 0
A70: 50 | B70: 0 | C70: 0 | D70: 1 | E70: 206 | F70: =ROUND(Source!T49,O70) -> 0 | G70: ВозврМат | H70: Возврат материалов | K70: 206 | L70: 20 | M70: 3 | O70: 2 | P70: =ROUND(Source!DL49,O70) -> 0 | W70: 0 | X70: 1 | Y70: 0 | Z70: 0 | AA70: 1 | AB70: 0
A71: 50 | B71: 0 | C71: 0 | D71: 1 | E71: 207 | F71: =Source!U49 -> 820.47351 | G71: ТрудСтр | H71: Трудозатраты строителей | K71: 207 | L71: 21 | M71: 3 | O71: -1 | P71: =Source!DM49 -> 820.47351 | W71: 820.47351 | X71: 1 | Y71: 820.47351 | Z71: 820.47351 | AA71: 1 | AB71: 820.47351
A72: 50 | B72: 0 | C72: 0 | D72: 1 | E72: 208 | F72: =Source!V49 -> 0 | G72: ТрудМаш | H72: Трудозатраты машинистов | K72: 208 | L72: 22 | M72: 3 | O72: -1 | P72: =Source!DN49 -> 0 | W72: 0 | X72: 1 | Y72: 0 | Z72: 0 | AA72: 1 | AB72: 0
A73: 50 | B73: 0 | C73: 0 | D73: 1 | E73: 209 | F73: =ROUND(Source!W49,O73) -> 0 | G73: ТранспМат | H73: Транспорт материалов | K73: 209 | L73: 23 | M73: 3 | O73: 2 | P73: =ROUND(Source!DO49,O73) -> 0 | W73: 0 | X73: 1 | Y73: 0 | Z73: 0 | AA73: 1 | AB73: 0
A74: 50 | B74: 0 | C74: 0 | D74: 1 | E74: 233 | F74: =ROUND(Source!BD49,O74) -> 0 | G74: Перевозка | H74: Перевозка грузов | K74: 233 | L74: 24 | M74: 3 | O74: 2 | P74: =ROUND(Source!EV49,O74) -> 0 | W74: 0 | X74: 1 | Y74: 0 | Z74: 0 | AA74: 1 | AB74: 0
A75: 50 | B75: 0 | C75: 0 | D75: 1 | E75: 210 | F75: =ROUND(Source!X49,O75) -> 8116.06 | G75: НР | H75: Накладные расходы | K75: 210 | L75: 25 | M75: 3 | O75: 2 | P75: =ROUND(Source!DP49,O75) -> 457339.87 | W75: 8116.06 | X75: 1 | Y75: 8116.06 | Z75: 457339.87 | AA75: 1 | AB75: 457339.87
A76: 50 | B76: 0 | C76: 0 | D76: 1 | E76: 211 | F76: =ROUND(Source!Y49,O76) -> 4114.83 | G76: СмПриб | H76: Сметная прибыль | K76: 211 | L76: 26 | M76: 3 | O76: 2 | P76: =ROUND(Source!DQ49,O76) -> 231870.78 | W76: 4114.83 | X76: 1 | Y76: 4114.83 | Z76: 231870.78 | AA76: 1 | AB76: 231870.78
A77: 50 | B77: 0 | C77: 0 | D77: 1 | E77: 224 | F77: =ROUND(Source!AR49,O77) -> 22019.09 | G77: Всего | H77: Всего с НР и СП | K77: 224 | L77: 27 | M77: 3 | O77: 2 | P77: =ROUND(Source!EJ49,O77) -> 1219230.5 | W77: 22019.09 | X77: 1 | Y77: 22019.09 | Z77: 1219230.5 | AA77: 1 | AB77: 1219230.5
A79: 4 | B79: 1 | D79: =ROW(A200) -> 200 | F79: Новый раздел | G79: Водопровод хозяйственно-питьевой В 1 (подземная часть) | I79: 0 | K79: -1 | S79: 0 | T79: 0 | V79: 0 | BX79: 0 | CJ79: 0
A81: 52 | B81: =B200 -> 1 | C81: =C200 -> 4 | D81: =D200 -> 79 | E81: =E200 -> 0 | F81: =F200 -> Новый раздел | G81: =G200 -> Водопровод хозяйственно-питьевой В 1 (подземная часть) | O81: =O200 -> 40592.77 | P81: =P200 -> 36719.23 | Q81: =Q200 -> 258.23 | R81: =R200 -> 28.18 | S81: =S200 -> 3615.31 | T81: =T200 -> 0 | U81: =U200 -> 281.54812 | V81: =V200 -> 0 | ... GX81: =GX200 -> 0
A83: 17 | B83: 1 | C83: =ROW(SmtRes!A101) -> 101 | D83: =ROW(EtalonRes!A121) -> 121 | E83: 11 | F83: 3.16-7-1 | G83: Прокладка трубопроводов водоснабжения из стальных водогазопроводных оцинкованных труб диаметром 15 мм | H83: 100 м трубопровода | I83: =ROUND((28)/100,9) -> 0.28 | J83: 0 | K83: =ROUND((28)/100,9) -> 0.28 | O83: =ROUND(CP83,2) -> 209.23 | P83: =ROUND((ROUND((AC83*AW83*I83),2)*BC83),2) -> 12.48 | Q83: =(ROUND((ROUND(((((ET83*1.25)*1.2))*AV83*I83),2)*BB83),2)+ROUND((ROUND(((AE83-(((EU83*1.25)*1.2)))*AV83*I83),2)*BS83),2)) -> 21.41 | R83: =(ROUND((ROUND(((((EU83*1.25)*1.2))*AV83*I83),2)*BS83),2)+ROUND((ROUND(((AE83-(((EU83*1.25)*1.2)))*AV83*I83),2)*BS83),2)) -> 2.72 | S83: =ROUND((ROUND((AF83*AV83*I83),2)*BA83),2) -> 175.34 | T83: =ROUND(CU83*I83,2) -> 0 | U83: =CV83*I83 -> 13.894133 | V83: =CW83*I83 -> 0 | W83: =ROUND(CX83*I83,2) -> 0 | X83: =(ROUND((((S83+ROUND((ROUND(((((EU83*1.25)*1.2))*AV83*I83),2)*BS83),2))*AT83)/100),2)+ROUND(((ROUND((ROUND(((AE83-(((EU83*1.25)*1.2)))*AV83*I83),2)*BS83),2)*AT83)/100),2)) -> 194.09 | Y83: =(ROUND((((S83+ROUND((ROUND(((((EU83*1.25)*1.2))*AV83*I83),2)*BS83),2))*AU83)/100),2)+ROUND(((ROUND((ROUND(((AE83-(((EU83*1.25)*1.2)))*AV83*I83),2)*BS83),2)*AU83)/100),2)) -> 108.62 | AA83: 85736471 | AB83: =ROUND((AC83+AD83+AF83),6) -> 703.1352 | AC83: =ROUND((((ES83*1)*1)),6) -> 44.58 | AD83: =ROUND((((((ET83*1.25)*1.2))-(((EU83*1.25)*1.2)))+AE83),6) -> 71.655 | AE83: =ROUND((((EU83*1.25)*1.2)),6) -> 9.09 | AF83: =ROUND((((EV83*1.15)*1.2)),6) -> 586.9002 | AG83: =ROUND((AP83),6) -> 0 | AH83: =(((EW83*1.15)*1.2)) -> 46.506 | AI83: =(((EX83*1.25)*1.2)) -> 0 | AJ83: =(AS83) -> 0 | AK83: 517.64 | AL83: 44.58 | AM83: 47.77 | AN83: 6.06 | AO83: 425.29 | AP83: 0 | AQ83: 33.7 | AR83: 0 | AS83: 0 | AT83: 109 | AU83: 61 | AV83: 1.067 | AW83: 1 | AZ83: 1 | BA83: 1 | BB83: 1 | BC83: 1 | BH83: 0 | BI83: 1 | BJ83: ТСН-2001.3 Доп. 79, Сб. 16, т. 7, поз. 1 | BM83: 21 | BN83: 0 | BO83: 3.16-7-1 | BP83: 1 | BQ83: 30 | BR83: 0 | BS83: 1 | BT83: 1 | BU83: 1 | BV83: 1 | BW83: 1 | BX83: 1 | BZ83: 109 | CA83: 61 | CE83: 1566 | CF83: 0 | CG83: 0 | CM83: 0 | CN83: Поправка: Гл.6.Прил.2.2.п.2.2.6_06.00.01.07.001 Наименование: При выполнении при капитальном ремонте и реконструкции работ, аналогичных технологическим процессам, характерным для нового строительства, и отсутствующих в сборниках на ремонтно-строительные работы ТСН-2001.6 Поправка: Гл.12.Прил.8.п.8. 3_12.00.01.11.001 Наименование: При наличии напряженных и стесненных условий производства работ (стесненность, сложность складирования и транспортной логистики и т.п.) для объектов, расположенных в пределах круговой магистральной системы улиц "Садовое кольцо" города Москвы | CO83: 0 | CP83: =(P83+Q83+S83) -> 209.23 | CQ83: =ROUND((ROUND((AC83*AW83*1),2)*BC83),2) -> 44.58 | CR83: =(ROUND((ROUND(((((ET83*1.25)*1.2))*AV83*1),2)*BB83),2)+ROUND((ROUND(((AE83-(((EU83*1.25)*1.2)))*AV83*1),2)*BS83),2)) -> 76.46 | CS83: =(ROUND((ROUND(((((EU83*1.25)*1.2))*AV83*1),2)*BS83),2)+ROUND((ROUND(((AE83-(((EU83*1.25)*1.2)))*AV83*1),2)*BS83),2)) -> 9.7 | CT83: =ROUND((ROUND((AF83*AV83*1),2)*BA83),2) -> 626.22 | CU83: =AG83 -> 0 | CV83: =(AH83*AV83) -> 49.621902 | CW83: =AI83 -> 0 | CX83: =AJ83 -> 0 | CY83: =(ROUND((((S83+ROUND((ROUND(((((EU83*1.25)*1.2))*AV83*1),2)*BS83),2))*AT83)/100),2)+ROUND(((ROUND((ROUND(((AE83-(((EU83*1.25)*1.2)))*AV83*1),2)*BS83),2)*AT83)/100),2)) -> 201.69 | CZ83: =(ROUND((((S83+ROUND((ROUND(((((EU83*1.25)*1.2))*AV83*1),2)*BS83),2))*AU83)/100),2)+ROUND(((ROUND((ROUND(((AE83-(((EU83*1.25)*1.2)))*AV83*1),2)*BS83),2)*AU83)/100),2)) -> 112.87 | DB83: 27 | DD83: *1)*1 | DE83: *1,25)*1,2 | DF83: *1,25)*1,2 | DG83: *1,15)*1,2 | DI83: *1,15)*1,2 | DJ83: *1,25)*1,2 | DN83: 0 | DO83: 0 | DP83: 1 | DQ83: 1 | DU83: 1013 | DV83: 100 м трубопровода | DW83: 100 м трубопровода | DX83: 1 | EE83: 85133641 | EF83: 30 | EG83: Строительные работы | EH83: 0 | EJ83: 1 | EK83: 21 | EL83: ТСН-2001.3-16. Трубопроводы внутренние | EM83: ТСН-2001.3-16-1 | EO83: Поправка: Гл.6.Прил.2.2.п.2.2.6_06.00.01.07.001 Поправка: Гл.12.Прил.8.п.8. 3_12.00.01.11.001 | EQ83: 0 | ER83: 517.64 | ES83: 44.58 | ET83: 47.77 | EU83: 6.06 | EV83: 425.29 | EW83: 33.7 | EX83: 0 | EY83: 0 | FQ83: 0 | FR83: 0 | FS83: 0 | FX83: 109 | FY83: 61 | GD83: 1 | GF83: 1707806610 | GG83: 2 | GH83: 1 | GI83: 2 | GJ83: 0 | GK83: 0 | GL83: =ROUND(IF(AND(BH83=3,BI83=3,FS83<>0),P83,0),2) -> 0 | GM83: =ROUND(O83+X83+Y83,2)+GX83 -> 511.94 | GN83: =IF(OR(BI83=0,BI83=1),GM83-GX83,0) -> 511.94 | GO83: =IF(BI83=2,GM83-GX83,0) -> 0 | GP83: =IF(BI83=4,GM83-GX83,0) -> 0 | GR83: 0 | GS83: 3 | GT83: 0 | GV83: =ROUND((GT83),6) -> 0 | GW83: 1 | GX83: =ROUND(HC83*I83,2) -> 0 | HA83: 0 | HB83: 0 | HC83: =GV83*GW83 -> 0 | HS83: 0 | IK83: 0
A84: 17 | B84: 1 | C84: =ROW(SmtRes!A116) -> 116 | D84: =ROW(EtalonRes!A136) -> 136 | E84: 11 | F84: 3.16-7-1 | G84: Прокладка трубопроводов водоснабжения из стальных водогазопроводных оцинкованных труб диаметром 15 мм | H84: 100 м трубопровода | I84: =ROUND((28)/100,9) -> 0.28 | J84: 0 | K84: =ROUND((28)/100,9) -> 0.28 | O84: =ROUND(CP84,2) -> 10305.72 | P84: =ROUND((ROUND((AC84*AW84*I84),2)*BC84),2) -> 78.25 | Q84: =(ROUND((ROUND(((((ET84*1.25)*1.2))*AV84*I84),2)*BB84),2)+ROUND((ROUND(((AE84-(((EU84*1.25)*1.2)))*AV84*I84),2)*BS84),2)) -> 347.06 | R84: =(ROUND((ROUND(((((EU84*1.25)*1.2))*AV84*I84),2)*BS84),2)+ROUND((ROUND(((AE84-(((EU84*1.25)*1.2)))*AV84*I84),2)*BS84),2)) -> 153.27 | S84: =ROUND((ROUND((AF84*AV84*I84),2)*BA84),2) -> 9880.41 | T84: =ROUND(CU84*I84,2) -> 0 | U84: =CV84*I84 -> 13.894133 | V84: =CW84*I84 -> 0 | W84: =ROUND(CX84*I84,2) -> 0 | X84: =(ROUND((((S84+ROUND((ROUND(((((EU84*1.25)*1.2))*AV84*I84),2)*BS84),2))*AT84)/100),2)+ROUND(((ROUND((ROUND(((AE84-(((EU84*1.25)*1.2)))*AV84*I84),2)*BS84),2)*AT84)/100),2)) -> 10936.71 | Y84: =(ROUND((((S84+ROUND((ROUND(((((EU84*1.25)*1.2))*AV84*I84),2)*BS84),2))*AU84)/100),2)+ROUND(((ROUND((ROUND(((AE84-(((EU84*1.25)*1.2)))*AV84*I84),2)*BS84),2)*AU84)/100),2)) -> 6120.54 | AA84: 85736473 | AB84: =ROUND((AC84+AD84+AF84),6) -> 703.1352 | AC84: =ROUND((((ES84*1)*1)),6) -> 44.58 | AD84: =ROUND((((((ET84*1.25)*1.2))-(((EU84*1.25)*1.2)))+AE84),6) -> 71.655 | AE84: =ROUND((((EU84*1.25)*1.2)),6) -> 9.09 | AF84: =ROUND((((EV84*1.15)*1.2)),6) -> 586.9002 | AG84: =ROUND((AP84),6) -> 0 | AH84: =(((EW84*1.15)*1.2)) -> 46.506 | AI84: =(((EX84*1.25)*1.2)) -> 0 | AJ84: =(AS84) -> 0 | AK84: 517.64 | AL84: 44.58 | AM84: 47.77 | AN84: 6.06 | AO84: 425.29 | AP84: 0 | AQ84: 33.7 | AR84: 0 | AS84: 0 | AT84: 109 | AU84: 61 | AV84: 1.067 | AW84: 1 | AZ84: 1 | BA84: 56.35 | BB84: 16.21 | BC84: 6.27 | BH84: 0 | BI84: 1 | BJ84: ТСН-2001.3 Доп. 79, Сб. 16, т. 7, поз. 1 | BM84: 21 | BN84: 0 | BO84: 3.16-7-1 | BP84: 1 | BQ84: 30 | BR84: 0 | BS84: 56.35 | BT84: 1 | BU84: 1 | BV84: 1 | BW84: 1 | BX84: 1 | BZ84: 109 | CA84: 61 | CE84: 1566 | CF84: 0 | CG84: 0 | CM84: 0 | CN84: Поправка: Гл.6.Прил.2.2.п.2.2.6_06.00.01.07.001 Наименование: При выполнении при капитальном ремонте и реконструкции работ, аналогичных технологическим процессам, характерным для нового строительства, и отсутствующих в сборниках на ремонтно-строительные работы ТСН-2001.6 Поправка: Гл.12.Прил.8.п.8. 3_12.00.01.11.001 Наименование: При наличии напряженных и стесненных условий производства работ (стесненность, сложность складирования и транспортной логистики и т.п.) для объектов, расположенных в пределах круговой магистральной системы улиц "Садовое кольцо" города Москвы | CO84: 0 | CP84: =(P84+Q84+S84) -> 10305.72 | CQ84: =ROUND((ROUND((AC84*AW84*1),2)*BC84),2) -> 279.52 | CR84: =(ROUND((ROUND(((((ET84*1.25)*1.2))*AV84*1),2)*BB84),2)+ROUND((ROUND(((AE84-(((EU84*1.25)*1.2)))*AV84*1),2)*BS84),2)) -> 1239.42 | CS84: =(ROUND((ROUND(((((EU84*1.25)*1.2))*AV84*1),2)*BS84),2)+ROUND((ROUND(((AE84-(((EU84*1.25)*1.2)))*AV84*1),2)*BS84),2)) -> 546.6 | CT84: =ROUND((ROUND((AF84*AV84*1),2)*BA84),2) -> 35287.5 | CU84: =AG84 -> 0 | CV84: =(AH84*AV84) -> 49.621902 | CW84: =AI84 -> 0 | CX84: =AJ84 -> 0 | CY84: =(ROUND((((S84+ROUND((ROUND(((((EU84*1.25)*1.2))*AV84*1),2)*BS84),2))*AT84)/100),2)+ROUND(((ROUND((ROUND(((AE84-(((EU84*1.25)*1.2)))*AV84*1),2)*BS84),2)*AT84)/100),2)) -> 11365.44 | CZ84: =(ROUND((((S84+ROUND((ROUND(((((EU84*1.25)*1.2))*AV84*1),2)*BS84),2))*AU84)/100),2)+ROUND(((ROUND((ROUND(((AE84-(((EU84*1.25)*1.2)))*AV84*1),2)*BS84),2)*AU84)/100),2)) -> 6360.48 | DB84: 29 | DD84: *1)*1 | DE84: *1,25)*1,2 | DF84: *1,25)*1,2 | DG84: *1,15)*1,2 | DI84: *1,15)*1,2 | DJ84: *1,25)*1,2 | DN84: 0 | DO84: 0 | DP84: 1 | DQ84: 1 | DU84: 1013 | DV84: 100 м трубопровода | DW84: 100 м трубопровода | DX84: 1 | EE84: 85133641 | EF84: 30 | EG84: Строительные работы | EH84: 0 | EJ84: 1 | EK84: 21 | EL84: ТСН-2001.3-16. Трубопроводы внутренние | EM84: ТСН-2001.3-16-1 | EO84: Поправка: Гл.6.Прил.2.2.п.2.2.6_06.00.01.07.001 Поправка: Гл.12.Прил.8.п.8. 3_12.00.01.11.001 | EQ84: 0 | ER84: 517.64 | ES84: 44.58 | ET84: 47.77 | EU84: 6.06 | EV84: 425.29 | EW84: 33.7 | EX84: 0 | EY84: 0 | FQ84: 0 | FR84: 0 | FS84: 0 | FX84: 109 | FY84: 61 | GD84: 1 | GF84: 1707806610 | GG84: 2 | GH84: 1 | GI84: 2 | GJ84: 0 | GK84: 0 | GL84: =ROUND(IF(AND(BH84=3,BI84=3,FS84<>0),P84,0),2) -> 0 | GM84: =ROUND(O84+X84+Y84,2)+GX84 -> 27362.97 | GN84: =IF(OR(BI84=0,BI84=1),GM84-GX84,0) -> 27362.97 | GO84: =IF(BI84=2,GM84-GX84,0) -> 0 | GP84: =IF(BI84=4,GM84-GX84,0) -> 0 | GR84: 0 | GS84: 3 | GT84: 0 | GV84: =ROUND((GT84),6) -> 0 | GW84: 1 | GX84: =ROUND(HC84*I84,2) -> 0 | HA84: 0 | HB84: 0 | HC84: =GV84*GW84 -> 0 | HS84: 0 | IK84: 0
A85: 18 | B85: 1 | C85: 101 | E85: 11,1 | F85: 1.13-4-61 | G85: Кран шаровой, латунный, никелированный, полнопроходной, с алюминиевой рукояткой, муфтовый, температура рабочей среды от -15 до +110°С, номинальное давление PN 4,0 МПа, номинальный диаметр DN 15 мм | H85: шт. | I85: =I83*J85 -> 12 | J85: 42.857143 | K85: 42.857143 | O85: =ROUND(CP85,2) -> 419.64 | P85: =ROUND((ROUND((AC85*AW85*I85),2)*BC85),2) -> 419.64 | Q85: =(ROUND((ROUND(((ET85)*AV85*I85),2)*BB85),2)+ROUND((ROUND(((AE85-(EU85))*AV85*I85),2)*BS85),2)) -> 0 | R85: =(ROUND((ROUND(((EU85)*AV85*I85),2)*BS85),2)+ROUND((ROUND(((AE85-(EU85))*AV85*I85),2)*BS85),2)) -> 0 | S85: =ROUND((ROUND((AF85*AV85*I85),2)*BA85),2) -> 0 | T85: =ROUND(CU85*I85,2) -> 0 | U85: =CV85*I85 -> 0 | V85: =CW85*I85 -> 0 | W85: =ROUND(CX85*I85,2) -> 0 | X85: =(ROUND((((S85+ROUND((ROUND(((EU85)*AV85*I85),2)*BS85),2))*AT85)/100),2)+ROUND(((ROUND((ROUND(((AE85-(EU85))*AV85*I85),2)*BS85),2)*AT85)/100),2)) -> 0 | Y85: =(ROUND((((S85+ROUND((ROUND(((EU85)*AV85*I85),2)*BS85),2))*AU85)/100),2)+ROUND(((ROUND((ROUND(((AE85-(EU85))*AV85*I85),2)*BS85),2)*AU85)/100),2)) -> 0 | AA85: 85736471 | AB85: =ROUND((AC85+AD85+AF85),6) -> 34.97 | AC85: =ROUND((ES85),6) -> 34.97 | AD85: =ROUND((((ET85)-(EU85))+AE85),6) -> 0 | AE85: =ROUND((EU85),6) -> 0 | AF85: =ROUND((EV85),6) -> 0 | AG85: =ROUND((AP85),6) -> 0 | AH85: =(EW85) -> 0 | AI85: =(EX85) -> 0 | AJ85: =(AS85) -> 0 | AK85: 34.97 | AL85: 34.97 | AM85: 0 | AN85: 0 | AO85: 0 | AP85: 0 | AQ85: 0 | AR85: 0 | AS85: 0 | AT85: 109 | AU85: 61 | AV85: 1 | AW85: 1 | AZ85: 1 | BA85: 1 | BB85: 1 | BC85: 1 | BH85: 3 | BI85: 1 | BJ85: ТСН-2001.1 Доп. 73, Р. 13, о. 4, поз. 61 | BM85: 21 | BN85: 0 | BP85: 0 | BQ85: 30 | BR85: 0 | BS85: 1 | BT85: 1 | BU85: 1 | BV85: 1 | BW85: 1 | BX85: 1 | BZ85: 109 | CA85: 61 | CE85: 1566 | CF85: 0 | CG85: 0 | CM85: 0 | CN85: Поправка: Гл.6.Прил.2.2.п.2.2.6_06.00.01.07.001_x000D_ Наименование: При выполнении при капитальном ремонте и реконструкции работ, аналогичных технологическим процессам, характерным для нового строительства, и отсутствующих в сборниках на ремонтно-строительные работы ТСН-2001.6_x000D_ Поправка: Гл.12.Прил.8.п.8. 3_12.00.01.11.001_x000D_ Наименование: При наличии напряженных и стесненных условий производства работ (стесненность, сложность складирования и транспортной логистики и т.п.) для объектов, расположенных в пределах круговой магистральной системы улиц "Садовое кольцо" города Москвы | CO85: 0 | CP85: =(P85+Q85+S85) -> 419.64 | CQ85: =ROUND((ROUND((AC85*AW85*1),2)*BC85),2) -> 34.97 | CR85: =(ROUND((ROUND(((ET85)*AV85*1),2)*BB85),2)+ROUND((ROUND(((AE85-(EU85))*AV85*1),2)*BS85),2)) -> 0 | CS85: =(ROUND((ROUND(((EU85)*AV85*1),2)*BS85),2)+ROUND((ROUND(((AE85-(EU85))*AV85*1),2)*BS85),2)) -> 0 | CT85: =ROUND((ROUND((AF85*AV85*1),2)*BA85),2) -> 0 | CU85: =AG85 -> 0 | CV85: =(AH85*AV85) -> 0 | CW85: =AI85 -> 0 | CX85: =AJ85 -> 0 | CY85: =(ROUND((((S85+ROUND((ROUND(((EU85)*AV85*1),2)*BS85),2))*AT85)/100),2)+ROUND(((ROUND((ROUND(((AE85-(EU85))*AV85*1),2)*BS85),2)*AT85)/100),2)) -> 0 | CZ85: =(ROUND((((S85+ROUND((ROUND(((EU85)*AV85*1),2)*BS85),2))*AU85)/100),2)+ROUND(((ROUND((ROUND(((AE85-(EU85))*AV85*1),2)*BS85),2)*AU85)/100),2)) -> 0 | DN85: 0 | DO85: 0 | DP85: 1 | DQ85: 1 | DU85: 1010 | DV85: шт. | DW85: шт. | DX85: 1 | EE85: 85133641 | EF85: 30 | EG85: Строительные работы | EH85: 0 | EJ85: 1 | EK85: 21 | EL85: ТСН-2001.3-16. Трубопроводы внутренние | EM85: ТСН-2001.3-16-1 | EO85: Поправка: Гл.6.Прил.2.2.п.2.2.6_06.00.01.07.001_x000D_ Поправка: Гл.12.Прил.8.п.8. 3_12.00.01.11.001 | EQ85: 0 | ER85: 34.97 | ES85: 34.97 | ET85: 0 | EU85: 0 | EV85: 0 | EW85: 0 | EX85: 0 | FQ85: 0 | FR85: 0 | FS85: 0 | FX85: 109 | FY85: 61 | GD85: 1 | GF85: -1344566016 | GG85: 2 | GH85: 1 | GI85: -2 | GJ85: 0 | GK85: 0 | GL85: =ROUND(IF(AND(BH85=3,BI85=3,FS85<>0),P85,0),2) -> 0 | GM85: =ROUND(O85+X85+Y85,2)+GX85 -> 419.64 | GN85: =IF(OR(BI85=0,BI85=1),GM85-GX85,0) -> 419.64 | GO85: =IF(BI85=2,GM85-GX85,0) -> 0 | GP85: =IF(BI85=4,GM85-GX85,0) -> 0 | GR85: 0 | GS85: 3 | GT85: 0 | GV85: =ROUND((GT85),6) -> 0 | GW85: 1 | GX85: =ROUND(HC85*I85,2) -> 0 | HA85: 0 | HB85: 0 | HC85: =GV85*GW85 -> 0 | HM85: *1)*1 | HS85: 0 | IK85: 0
A86: 18 | B86: 1 | C86: 116 | E86: 11,1 | F86: 1.13-4-61 | G86: Кран шаровой, латунный, никелированный, полнопроходной, с алюминиевой рукояткой, муфтовый, температура рабочей среды от -15 до +110°С, номинальное давление PN 4,0 МПа, номинальный диаметр DN 15 мм | H86: шт. | I86: =I84*J86 -> 12 | J86: 42.857143 | K86: 42.857143 | O86: =ROUND(CP86,2) -> 8162 | P86: =ROUND((ROUND((AC86*AW86*I86),2)*BC86),2) -> 8162 | Q86: =(ROUND((ROUND(((ET86)*AV86*I86),2)*BB86),2)+ROUND((ROUND(((AE86-(EU86))*AV86*I86),2)*BS86),2)) -> 0 | R86: =(ROUND((ROUND(((EU86)*AV86*I86),2)*BS86),2)+ROUND((ROUND(((AE86-(EU86))*AV86*I86),2)*BS86),2)) -> 0 | S86: =ROUND((ROUND((AF86*AV86*I86),2)*BA86),2) -> 0 | T86: =ROUND(CU86*I86,2) -> 0 | U86: =CV86*I86 -> 0 | V86: =CW86*I86 -> 0 | W86: =ROUND(CX86*I86,2) -> 0 | X86: =(ROUND((((S86+ROUND((ROUND(((EU86)*AV86*I86),2)*BS86),2))*AT86)/100),2)+ROUND(((ROUND((ROUND(((AE86-(EU86))*AV86*I86),2)*BS86),2)*AT86)/100),2)) -> 0 | Y86: =(ROUND((((S86+ROUND((ROUND(((EU86)*AV86*I86),2)*BS86),2))*AU86)/100),2)+ROUND(((ROUND((ROUND(((AE86-(EU86))*AV86*I86),2)*BS86),2)*AU86)/100),2)) -> 0 | AA86: 85736473 | AB86: =ROUND((AC86+AD86+AF86),6) -> 34.97 | AC86: =ROUND((ES86),6) -> 34.97 | AD86: =ROUND((((ET86)-(EU86))+AE86),6) -> 0 | AE86: =ROUND((EU86),6) -> 0 | AF86: =ROUND((EV86),6) -> 0 | AG86: =ROUND((AP86),6) -> 0 | AH86: =(EW86) -> 0 | AI86: =(EX86) -> 0 | AJ86: =(AS86) -> 0 | AK86: 34.97 | AL86: 34.97 | AM86: 0 | AN86: 0 | AO86: 0 | AP86: 0 | AQ86: 0 | AR86: 0 | AS86: 0 | AT86: 109 | AU86: 61 | AV86: 1 | AW86: 1 | AZ86: 1 | BA86: 1 | BB86: 1 | BC86: 19.45 | BH86: 3 | BI86: 1 | BJ86: ТСН-2001.1 Доп. 73, Р. 13, о. 4, поз. 61 | BM86: 21 | BN86: 0 | BO86: 1.13-4-61 | BP86: 1 | BQ86: 30 | BR86: 0 | BS86: 1 | BT86: 1 | BU86: 1 | BV86: 1 | BW86: 1 | BX86: 1 | BZ86: 109 | CA86: 61 | CE86: 1566 | CF86: 0 | CG86: 0 | CM86: 0 | CN86: Поправка: Гл.6.Прил.2.2.п.2.2.6_06.00.01.07.001_x000D_ Наименование: При выполнении при капитальном ремонте и реконструкции работ, аналогичных технологическим процессам, характерным для нового строительства, и отсутствующих в сборниках на ремонтно-строительные работы ТСН-2001.6_x000D_ Поправка: Гл.12.Прил.8.п.8. 3_12.00.01.11.001_x000D_ Наименование: При наличии напряженных и стесненных условий производства работ (стесненность, сложность складирования и транспортной логистики и т.п.) для объектов, расположенных в пределах круговой магистральной системы улиц "Садовое кольцо" города Москвы | CO86: 0 | CP86: =(P86+Q86+S86) -> 8162 | CQ86: =ROUND((ROUND((AC86*AW86*1),2)*BC86),2) -> 680.17 | CR86: =(ROUND((ROUND(((ET86)*AV86*1),2)*BB86),2)+ROUND((ROUND(((AE86-(EU86))*AV86*1),2)*BS86),2)) -> 0 | CS86: =(ROUND((ROUND(((EU86)*AV86*1),2)*BS86),2)+ROUND((ROUND(((AE86-(EU86))*AV86*1),2)*BS86),2)) -> 0 | CT86: =ROUND((ROUND((AF86*AV86*1),2)*BA86),2) -> 0 | CU86: =AG86 -> 0 | CV86: =(AH86*AV86) -> 0 | CW86: =AI86 -> 0 | CX86: =AJ86 -> 0 | CY86: =(ROUND((((S86+ROUND((ROUND(((EU86)*AV86*1),2)*BS86),2))*AT86)/100),2)+ROUND(((ROUND((ROUND(((AE86-(EU86))*AV86*1),2)*BS86),2)*AT86)/100),2)) -> 0 | CZ86: =(ROUND((((S86+ROUND((ROUND(((EU86)*AV86*1),2)*BS86),2))*AU86)/100),2)+ROUND(((ROUND((ROUND(((AE86-(EU86))*AV86*1),2)*BS86),2)*AU86)/100),2)) -> 0 | DN86: 0 | DO86: 0 | DP86: 1 | DQ86: 1 | DU86: 1010 | DV86: шт. | DW86: шт. | DX86: 1 | EE86: 85133641 | EF86: 30 | EG86: Строительные работы | EH86: 0 | EJ86: 1 | EK86: 21 | EL86: ТСН-2001.3-16. Трубопроводы внутренние | EM86: ТСН-2001.3-16-1 | EO86: Поправка: Гл.6.Прил.2.2.п.2.2.6_06.00.01.07.001_x000D_ Поправка: Гл.12.Прил.8.п.8. 3_12.00.01.11.001 | EQ86: 0 | ER86: 34.97 | ES86: 34.97 | ET86: 0 | EU86: 0 | EV86: 0 | EW86: 0 | EX86: 0 | FQ86: 0 | FR86: 0 | FS86: 0 | FX86: 109 | FY86: 61 | GD86: 1 | GF86: -1344566016 | GG86: 2 | GH86: 1 | GI86: 2 | GJ86: 0 | GK86: 0 | GL86: =ROUND(IF(AND(BH86=3,BI86=3,FS86<>0),P86,0),2) -> 0 | GM86: =ROUND(O86+X86+Y86,2)+GX86 -> 8162 | GN86: =IF(OR(BI86=0,BI86=1),GM86-GX86,0) -> 8162 | GO86: =IF(BI86=2,GM86-GX86,0) -> 0 | GP86: =IF(BI86=4,GM86-GX86,0) -> 0 | GR86: 0 | GS86: 3 | GT86: 0 | GV86: =ROUND((GT86),6) -> 0 | GW86: 1 | GX86: =ROUND(HC86*I86,2) -> 0 | HA86: 0 | HB86: 0 | HC86: =GV86*GW86 -> 0 | HM86: *1)*1 | HS86: 0 | IK86: 0
A87: 18 | B87: 1 | C87: 100 | E87: 11,2 | F87: 1.13-4-137 | G87: Кран шаровой, латунный, никелированный, спускной, с наружной резьбой, с насадкой для шланга, с алюминиевой рукояткой, температура рабочей среды от -15 до +90°С, пропускная способность 1,9 м3/ч, номинальное давление PN 1,0 МПа, номинальный диаметр DN 15 мм | H87: шт. | I87: =I83*J87 -> 23 | J87: 82.142857 | K87: 82.142857 | O87: =ROUND(CP87,2) -> 566.03 | P87: =ROUND((ROUND((AC87*AW87*I87),2)*BC87),2) -> 566.03 | Q87: =(ROUND((ROUND(((ET87)*AV87*I87),2)*BB87),2)+ROUND((ROUND(((AE87-(EU87))*AV87*I87),2)*BS87),2)) -> 0 | R87: =(ROUND((ROUND(((EU87)*AV87*I87),2)*BS87),2)+ROUND((ROUND(((AE87-(EU87))*AV87*I87),2)*BS87),2)) -> 0 | S87: =ROUND((ROUND((AF87*AV87*I87),2)*BA87),2) -> 0 | T87: =ROUND(CU87*I87,2) -> 0 | U87: =CV87*I87 -> 0 | V87: =CW87*I87 -> 0 | W87: =ROUND(CX87*I87,2) -> 0 | X87: =(ROUND((((S87+ROUND((ROUND(((EU87)*AV87*I87),2)*BS87),2))*AT87)/100),2)+ROUND(((ROUND((ROUND(((AE87-(EU87))*AV87*I87),2)*BS87),2)*AT87)/100),2)) -> 0 | Y87: =(ROUND((((S87+ROUND((ROUND(((EU87)*AV87*I87),2)*BS87),2))*AU87)/100),2)+ROUND(((ROUND((ROUND(((AE87-(EU87))*AV87*I87),2)*BS87),2)*AU87)/100),2)) -> 0 | AA87: 85736471 | AB87: =ROUND((AC87+AD87+AF87),6) -> 24.61 | AC87: =ROUND((ES87),6) -> 24.61 | AD87: =ROUND((((ET87)-(EU87))+AE87),6) -> 0 | AE87: =ROUND((EU87),6) -> 0 | AF87: =ROUND((EV87),6) -> 0 | AG87: =ROUND((AP87),6) -> 0 | AH87: =(EW87) -> 0 | AI87: =(EX87) -> 0 | AJ87: =(AS87) -> 0 | AK87: 24.61 | AL87: 24.61 | AM87: 0 | AN87: 0 | AO87: 0 | AP87: 0 | AQ87: 0 | AR87: 0 | AS87: 0 | AT87: 109 | AU87: 61 | AV87: 1 | AW87: 1 | AZ87: 1 | BA87: 1 | BB87: 1 | BC87: 1 | BH87: 3 | BI87: 1 | BJ87: ТСН-2001.1 Доп. 73, Р. 13, о. 4, поз. 137 | BM87: 21 | BN87: 0 | BP87: 0 | BQ87: 30 | BR87: 0 | BS87: 1 | BT87: 1 | BU87: 1 | BV87: 1 | BW87: 1 | BX87: 1 | BZ87: 109 | CA87: 61 | CE87: 1566 | CF87: 0 | CG87: 0 | CM87: 0 | CN87: Поправка: Гл.6.Прил.2.2.п.2.2.6_06.00.01.07.001_x000D_ Наименование: При выполнении при капитальном ремонте и реконструкции работ, аналогичных технологическим процессам, характерным для нового строительства, и отсутствующих в сборниках на ремонтно-строительные работы ТСН-2001.6_x000D_ Поправка: Гл.12.Прил.8.п.8. 3_12.00.01.11.001_x000D_ Наименование: При наличии напряженных и стесненных условий производства работ (стесненность, сложность складирования и транспортной логистики и т.п.) для объектов, расположенных в пределах круговой магистральной системы улиц "Садовое кольцо" города Москвы | CO87: 0 | CP87: =(P87+Q87+S87) -> 566.03 | CQ87: =ROUND((ROUND((AC87*AW87*1),2)*BC87),2) -> 24.61 | CR87: =(ROUND((ROUND(((ET87)*AV87*1),2)*BB87),2)+ROUND((ROUND(((AE87-(EU87))*AV87*1),2)*BS87),2)) -> 0 | CS87: =(ROUND((ROUND(((EU87)*AV87*1),2)*BS87),2)+ROUND((ROUND(((AE87-(EU87))*AV87*1),2)*BS87),2)) -> 0 | CT87: =ROUND((ROUND((AF87*AV87*1),2)*BA87),2) -> 0 | CU87: =AG87 -> 0 | CV87: =(AH87*AV87) -> 0 | CW87: =AI87 -> 0 | CX87: =AJ87 -> 0 | CY87: =(ROUND((((S87+ROUND((ROUND(((EU87)*AV87*1),2)*BS87),2))*AT87)/100),2)+ROUND(((ROUND((ROUND(((AE87-(EU87))*AV87*1),2)*BS87),2)*AT87)/100),2)) -> 0 | CZ87: =(ROUND((((S87+ROUND((ROUND(((EU87)*AV87*1),2)*BS87),2))*AU87)/100),2)+ROUND(((ROUND((ROUND(((AE87-(EU87))*AV87*1),2)*BS87),2)*AU87)/100),2)) -> 0 | DN87: 0 | DO87: 0 | DP87: 1 | DQ87: 1 | DU87: 1010 | DV87: шт. | DW87: шт. | DX87: 1 | EE87: 85133641 | EF87: 30 | EG87: Строительные работы | EH87: 0 | EJ87: 1 | EK87: 21 | EL87: ТСН-2001.3-16. Трубопроводы внутренние | EM87: ТСН-2001.3-16-1 | EO87: Поправка: Гл.6.Прил.2.2.п.2.2.6_06.00.01.07.001_x000D_ Поправка: Гл.12.Прил.8.п.8. 3_12.00.01.11.001 | EQ87: 0 | ER87: 24.61 | ES87: 24.61 | ET87: 0 | EU87: 0 | EV87: 0 | EW87: 0 | EX87: 0 | FQ87: 0 | FR87: 0 | FS87: 0 | FX87: 109 | FY87: 61 | GD87: 1 | GF87: 470324337 | GG87: 2 | GH87: 1 | GI87: -2 | GJ87: 0 | GK87: 0 | GL87: =ROUND(IF(AND(BH87=3,BI87=3,FS87<>0),P87,0),2) -> 0 | GM87: =ROUND(O87+X87+Y87,2)+GX87 -> 566.03 | GN87: =IF(OR(BI87=0,BI87=1),GM87-GX87,0) -> 566.03 | GO87: =IF(BI87=2,GM87-GX87,0) -> 0 | GP87: =IF(BI87=4,GM87-GX87,0) -> 0 | GR87: 0 | GS87: 3 | GT87: 0 | GV87: =ROUND((GT87),6) -> 0 | GW87: 1 | GX87: =ROUND(HC87*I87,2) -> 0 | HA87: 0 | HB87: 0 | HC87: =GV87*GW87 -> 0 | HM87: *1)*1 | HS87: 0 | IK87: 0
A88: 18 | B88: 1 | C88: 115 | E88: 11,2 | F88: 1.13-4-137 | G88: Кран шаровой, латунный, никелированный, спускной, с наружной резьбой, с насадкой для шланга, с алюминиевой рукояткой, температура рабочей среды от -15 до +90°С, пропускная способность 1,9 м3/ч, номинальное давление PN 1,0 МПа, номинальный диаметр DN 15 мм | H88: шт. | I88: =I84*J88 -> 23 | J88: 82.142857 | K88: 82.142857 | O88: =ROUND(CP88,2) -> 21316.69 | P88: =ROUND((ROUND((AC88*AW88*I88),2)*BC88),2) -> 21316.69 | Q88: =(ROUND((ROUND(((ET88)*AV88*I88),2)*BB88),2)+ROUND((ROUND(((AE88-(EU88))*AV88*I88),2)*BS88),2)) -> 0 | R88: =(ROUND((ROUND(((EU88)*AV88*I88),2)*BS88),2)+ROUND((ROUND(((AE88-(EU88))*AV88*I88),2)*BS88),2)) -> 0 | S88: =ROUND((ROUND((AF88*AV88*I88),2)*BA88),2) -> 0 | T88: =ROUND(CU88*I88,2) -> 0 | U88: =CV88*I88 -> 0 | V88: =CW88*I88 -> 0 | W88: =ROUND(CX88*I88,2) -> 0 | X88: =(ROUND((((S88+ROUND((ROUND(((EU88)*AV88*I88),2)*BS88),2))*AT88)/100),2)+ROUND(((ROUND((ROUND(((AE88-(EU88))*AV88*I88),2)*BS88),2)*AT88)/100),2)) -> 0 | Y88: =(ROUND((((S88+ROUND((ROUND(((EU88)*AV88*I88),2)*BS88),2))*AU88)/100),2)+ROUND(((ROUND((ROUND(((AE88-(EU88))*AV88*I88),2)*BS88),2)*AU88)/100),2)) -> 0 | AA88: 85736473 | AB88: =ROUND((AC88+AD88+AF88),6) -> 24.61 | AC88: =ROUND((ES88),6) -> 24.61 | AD88: =ROUND((((ET88)-(EU88))+AE88),6) -> 0 | AE88: =ROUND((EU88),6) -> 0 | AF88: =ROUND((EV88),6) -> 0 | AG88: =ROUND((AP88),6) -> 0 | AH88: =(EW88) -> 0 | AI88: =(EX88) -> 0 | AJ88: =(AS88) -> 0 | AK88: 24.61 | AL88: 24.61 | AM88: 0 | AN88: 0 | AO88: 0 | AP88: 0 | AQ88: 0 | AR88: 0 | AS88: 0 | AT88: 109 | AU88: 61 | AV88: 1 | AW88: 1 | AZ88: 1 | BA88: 1 | BB88: 1 | BC88: 37.66 | BH88: 3 | BI88: 1 | BJ88: ТСН-2001.1 Доп. 73, Р. 13, о. 4, поз. 137 | BM88: 21 | BN88: 0 | BO88: 1.13-4-137 | BP88: 1 | BQ88: 30 | BR88: 0 | BS88: 1 | BT88: 1 | BU88: 1 | BV88: 1 | BW88: 1 | BX88: 1 | BZ88: 109 | CA88: 61 | CE88: 1566 | CF88: 0 | CG88: 0 | CM88: 0 | CN88: Поправка: Гл.6.Прил.2.2.п.2.2.6_06.00.01.07.001_x000D_ Наименование: При выполнении при капитальном ремонте и реконструкции работ, аналогичных технологическим процессам, характерным для нового строительства, и отсутствующих в сборниках на ремонтно-строительные работы ТСН-2001.6_x000D_ Поправка: Гл.12.Прил.8.п.8. 3_12.00.01.11.001_x000D_ Наименование: При наличии напряженных и стесненных условий производства работ (стесненность, сложность складирования и транспортной логистики и т.п.) для объектов, расположенных в пределах круговой магистральной системы улиц "Садовое кольцо" города Москвы | CO88: 0 | CP88: =(P88+Q88+S88) -> 21316.69 | CQ88: =ROUND((ROUND((AC88*AW88*1),2)*BC88),2) -> 926.81 | CR88: =(ROUND((ROUND(((ET88)*AV88*1),2)*BB88),2)+ROUND((ROUND(((AE88-(EU88))*AV88*1),2)*BS88),2)) -> 0 | CS88: =(ROUND((ROUND(((EU88)*AV88*1),2)*BS88),2)+ROUND((ROUND(((AE88-(EU88))*AV88*1),2)*BS88),2)) -> 0 | CT88: =ROUND((ROUND((AF88*AV88*1),2)*BA88),2) -> 0 | CU88: =AG88 -> 0 | CV88: =(AH88*AV88) -> 0 | CW88: =AI88 -> 0 | CX88: =AJ88 -> 0 | CY88: =(ROUND((((S88+ROUND((ROUND(((EU88)*AV88*1),2)*BS88),2))*AT88)/100),2)+ROUND(((ROUND((ROUND(((AE88-(EU88))*AV88*1),2)*BS88),2)*AT88)/100),2)) -> 0 | CZ88: =(ROUND((((S88+ROUND((ROUND(((EU88)*AV88*1),2)*BS88),2))*AU88)/100),2)+ROUND(((ROUND((ROUND(((AE88-(EU88))*AV88*1),2)*BS88),2)*AU88)/100),2)) -> 0 | DN88: 0 | DO88: 0 | DP88: 1 | DQ88: 1 | DU88: 1010 | DV88: шт. | DW88: шт. | DX88: 1 | EE88: 85133641 | EF88: 30 | EG88: Строительные работы | EH88: 0 | EJ88: 1 | EK88: 21 | EL88: ТСН-2001.3-16. Трубопроводы внутренние | EM88: ТСН-2001.3-16-1 | EO88: Поправка: Гл.6.Прил.2.2.п.2.2.6_06.00.01.07.001_x000D_ Поправка: Гл.12.Прил.8.п.8. 3_12.00.01.11.001 | EQ88: 0 | ER88: 24.61 | ES88: 24.61 | ET88: 0 | EU88: 0 | EV88: 0 | EW88: 0 | EX88: 0 | FQ88: 0 | FR88: 0 | FS88: 0 | FX88: 109 | FY88: 61 | GD88: 1 | GF88: 470324337 | GG88: 2 | GH88: 1 | GI88: 2 | GJ88: 0 | GK88: 0 | GL88: =ROUND(IF(AND(BH88=3,BI88=3,FS88<>0),P88,0),2) -> 0 | GM88: =ROUND(O88+X88+Y88,2)+GX88 -> 21316.69 | GN88: =IF(OR(BI88=0,BI88=1),GM88-GX88,0) -> 21316.69 | GO88: =IF(BI88=2,GM88-GX88,0) -> 0 | GP88: =IF(BI88=4,GM88-GX88,0) -> 0 | GR88: 0 | GS88: 3 | GT88: 0 | GV88: =ROUND((GT88),6) -> 0 | GW88: 1 | GX88: =ROUND(HC88*I88,2) -> 0 | HA88: 0 | HB88: 0 | HC88: =GV88*GW88 -> 0 | HM88: *1)*1 | HS88: 0 | IK88: 0
A89: 18 | B89: 1 | C89: 99 | E89: 11,3 | F89: 1.12-1-52 | G89: Узел трубопровода из стальных водогазопроводных оцинкованных труб, с гильзами, для водоснабжения, диаметр условного прохода 15 мм | H89: м | I89: =I83*J89 -> 28 | J89: 100 | K89: 100 | O89: =ROUND(CP89,2) -> 786.8 | P89: =ROUND((ROUND((AC89*AW89*I89),2)*BC89),2) -> 786.8 | Q89: =(ROUND((ROUND(((ET89)*AV89*I89),2)*BB89),2)+ROUND((ROUND(((AE89-(EU89))*AV89*I89),2)*BS89),2)) -> 0 | R89: =(ROUND((ROUND(((EU89)*AV89*I89),2)*BS89),2)+ROUND((ROUND(((AE89-(EU89))*AV89*I89),2)*BS89),2)) -> 0 | S89: =ROUND((ROUND((AF89*AV89*I89),2)*BA89),2) -> 0 | T89: =ROUND(CU89*I89,2) -> 0 | U89: =CV89*I89 -> 0 | V89: =CW89*I89 -> 0 | W89: =ROUND(CX89*I89,2) -> 0 | X89: =(ROUND((((S89+ROUND((ROUND(((EU89)*AV89*I89),2)*BS89),2))*AT89)/100),2)+ROUND(((ROUND((ROUND(((AE89-(EU89))*AV89*I89),2)*BS89),2)*AT89)/100),2)) -> 0 | Y89: =(ROUND((((S89+ROUND((ROUND(((EU89)*AV89*I89),2)*BS89),2))*AU89)/100),2)+ROUND(((ROUND((ROUND(((AE89-(EU89))*AV89*I89),2)*BS89),2)*AU89)/100),2)) -> 0 | AA89: 85736471 | AB89: =ROUND((AC89+AD89+AF89),6) -> 28.1 | AC89: =ROUND((ES89),6) -> 28.1 | AD89: =ROUND((((ET89)-(EU89))+AE89),6) -> 0 | AE89: =ROUND((EU89),6) -> 0 | AF89: =ROUND((EV89),6) -> 0 | AG89: =ROUND((AP89),6) -> 0 | AH89: =(EW89) -> 0 | AI89: =(EX89) -> 0 | AJ89: =(AS89) -> 0 | AK89: 28.1 | AL89: 28.1 | AM89: 0 | AN89: 0 | AO89: 0 | AP89: 0 | AQ89: 0 | AR89: 0 | AS89: 0 | AT89: 109 | AU89: 61 | AV89: 1 | AW89: 1 | AZ89: 1 | BA89: 1 | BB89: 1 | BC89: 1 | BH89: 3 | BI89: 1 | BJ89: ТСН-2001.1 Доп. 79, Р. 12, о. 1, поз. 52 | BM89: 21 | BN89: 0 | BP89: 0 | BQ89: 30 | BR89: 0 | BS89: 1 | BT89: 1 | BU89: 1 | BV89: 1 | BW89: 1 | BX89: 1 | BZ89: 109 | CA89: 61 | CE89: 1566 | CF89: 0 | CG89: 0 | CM89: 0 | CN89: Поправка: Гл.6.Прил.2.2.п.2.2.6_06.00.01.07.001_x000D_ Наименование: При выполнении при капитальном ремонте и реконструкции работ, аналогичных технологическим процессам, характерным для нового строительства, и отсутствующих в сборниках на ремонтно-строительные работы ТСН-2001.6_x000D_ Поправка: Гл.12.Прил.8.п.8. 3_12.00.01.11.001_x000D_ Наименование: При наличии напряженных и стесненных условий производства работ (стесненность, сложность складирования и транспортной логистики и т.п.) для объектов, расположенных в пределах круговой магистральной системы улиц "Садовое кольцо" города Москвы | CO89: 0 | CP89: =(P89+Q89+S89) -> 786.8 | CQ89: =ROUND((ROUND((AC89*AW89*1),2)*BC89),2) -> 28.1 | CR89: =(ROUND((ROUND(((ET89)*AV89*1),2)*BB89),2)+ROUND((ROUND(((AE89-(EU89))*AV89*1),2)*BS89),2)) -> 0 | CS89: =(ROUND((ROUND(((EU89)*AV89*1),2)*BS89),2)+ROUND((ROUND(((AE89-(EU89))*AV89*1),2)*BS89),2)) -> 0 | CT89: =ROUND((ROUND((AF89*AV89*1),2)*BA89),2) -> 0 | CU89: =AG89 -> 0 | CV89: =(AH89*AV89) -> 0 | CW89: =AI89 -> 0 | CX89: =AJ89 -> 0 | CY89: =(ROUND((((S89+ROUND((ROUND(((EU89)*AV89*1),2)*BS89),2))*AT89)/100),2)+ROUND(((ROUND((ROUND(((AE89-(EU89))*AV89*1),2)*BS89),2)*AT89)/100),2)) -> 0 | CZ89: =(ROUND((((S89+ROUND((ROUND(((EU89)*AV89*1),2)*BS89),2))*AU89)/100),2)+ROUND(((ROUND((ROUND(((AE89-(EU89))*AV89*1),2)*BS89),2)*AU89)/100),2)) -> 0 | DN89: 0 | DO89: 0 | DP89: 1 | DQ89: 1 | DU89: 1003 | DV89: м | DW89: м | DX89: 1 | EE89: 85133641 | EF89: 30 | EG89: Строительные работы | EH89: 0 | EJ89: 1 | EK89: 21 | EL89: ТСН-2001.3-16. Трубопроводы внутренние | EM89: ТСН-2001.3-16-1 | EO89: Поправка: Гл.6.Прил.2.2.п.2.2.6_06.00.01.07.001_x000D_ Поправка: Гл.12.Прил.8.п.8. 3_12.00.01.11.001 | EQ89: 0 | ER89: 28.1 | ES89: 28.1 | ET89: 0 | EU89: 0 | EV89: 0 | EW89: 0 | EX89: 0 | FQ89: 0 | FR89: 0 | FS89: 0 | FX89: 109 | FY89: 61 | GD89: 1 | GF89: -367345504 | GG89: 2 | GH89: 1 | GI89: -2 | GJ89: 0 | GK89: 0 | GL89: =ROUND(IF(AND(BH89=3,BI89=3,FS89<>0),P89,0),2) -> 0 | GM89: =ROUND(O89+X89+Y89,2)+GX89 -> 786.8 | GN89: =IF(OR(BI89=0,BI89=1),GM89-GX89,0) -> 786.8 | GO89: =IF(BI89=2,GM89-GX89,0) -> 0 | GP89: =IF(BI89=4,GM89-GX89,0) -> 0 | GR89: 0 | GS89: 3 | GT89: 0 | GV89: =ROUND((GT89),6) -> 0 | GW89: 1 | GX89: =ROUND(HC89*I89,2) -> 0 | HA89: 0 | HB89: 0 | HC89: =GV89*GW89 -> 0 | HM89: *1)*1 | HS89: 0 | IK89: 0
A90: 18 | B90: 1 | C90: 114 | E90: 11,3 | F90: 1.12-1-52 | G90: Узел трубопровода из стальных водогазопроводных оцинкованных труб, с гильзами, для водоснабжения, диаметр условного прохода 15 мм | H90: м | I90: =I84*J90 -> 28 | J90: 100 | K90: 100 | O90: =ROUND(CP90,2) -> 14658.08 | P90: =ROUND((ROUND((AC90*AW90*I90),2)*BC90),2) -> 14658.08 | Q90: =(ROUND((ROUND(((ET90)*AV90*I90),2)*BB90),2)+ROUND((ROUND(((AE90-(EU90))*AV90*I90),2)*BS90),2)) -> 0 | R90: =(ROUND((ROUND(((EU90)*AV90*I90),2)*BS90),2)+ROUND((ROUND(((AE90-(EU90))*AV90*I90),2)*BS90),2)) -> 0 | S90: =ROUND((ROUND((AF90*AV90*I90),2)*BA90),2) -> 0 | T90: =ROUND(CU90*I90,2) -> 0 | U90: =CV90*I90 -> 0 | V90: =CW90*I90 -> 0 | W90: =ROUND(CX90*I90,2) -> 0 | X90: =(ROUND((((S90+ROUND((ROUND(((EU90)*AV90*I90),2)*BS90),2))*AT90)/100),2)+ROUND(((ROUND((ROUND(((AE90-(EU90))*AV90*I90),2)*BS90),2)*AT90)/100),2)) -> 0 | Y90: =(ROUND((((S90+ROUND((ROUND(((EU90)*AV90*I90),2)*BS90),2))*AU90)/100),2)+ROUND(((ROUND((ROUND(((AE90-(EU90))*AV90*I90),2)*BS90),2)*AU90)/100),2)) -> 0 | AA90: 85736473 | AB90: =ROUND((AC90+AD90+AF90),6) -> 28.1 | AC90: =ROUND((ES90),6) -> 28.1 | AD90: =ROUND((((ET90)-(EU90))+AE90),6) -> 0 | AE90: =ROUND((EU90),6) -> 0 | AF90: =ROUND((EV90),6) -> 0 | AG90: =ROUND((AP90),6) -> 0 | AH90: =(EW90) -> 0 | AI90: =(EX90) -> 0 | AJ90: =(AS90) -> 0 | AK90: 28.1 | AL90: 28.1 | AM90: 0 | AN90: 0 | AO90: 0 | AP90: 0 | AQ90: 0 | AR90: 0 | AS90: 0 | AT90: 109 | AU90: 61 | AV90: 1 | AW90: 1 | AZ90: 1 | BA90: 1 | BB90: 1 | BC90: 18.63 | BH90: 3 | BI90: 1 | BJ90: ТСН-2001.1 Доп. 79, Р. 12, о. 1, поз. 52 | BM90: 21 | BN90: 0 | BO90: 1.12-1-52 | BP90: 1 | BQ90: 30 | BR90: 0 | BS90: 1 | BT90: 1 | BU90: 1 | BV90: 1 | BW90: 1 | BX90: 1 | BZ90: 109 | CA90: 61 | CE90: 1566 | CF90: 0 | CG90: 0 | CM90: 0 | CN90: Поправка: Гл.6.Прил.2.2.п.2.2.6_06.00.01.07.001_x000D_ Наименование: При выполнении при капитальном ремонте и реконструкции работ, аналогичных технологическим процессам, характерным для нового строительства, и отсутствующих в сборниках на ремонтно-строительные работы ТСН-2001.6_x000D_ Поправка: Гл.12.Прил.8.п.8. 3_12.00.01.11.001_x000D_ Наименование: При наличии напряженных и стесненных условий производства работ (стесненность, сложность складирования и транспортной логистики и т.п.) для объектов, расположенных в пределах круговой магистральной системы улиц "Садовое кольцо" города Москвы | CO90: 0 | CP90: =(P90+Q90+S90) -> 14658.08 | CQ90: =ROUND((ROUND((AC90*AW90*1),2)*BC90),2) -> 523.5 | CR90: =(ROUND((ROUND(((ET90)*AV90*1),2)*BB90),2)+ROUND((ROUND(((AE90-(EU90))*AV90*1),2)*BS90),2)) -> 0 | CS90: =(ROUND((ROUND(((EU90)*AV90*1),2)*BS90),2)+ROUND((ROUND(((AE90-(EU90))*AV90*1),2)*BS90),2)) -> 0 | CT90: =ROUND((ROUND((AF90*AV90*1),2)*BA90),2) -> 0 | CU90: =AG90 -> 0 | CV90: =(AH90*AV90) -> 0 | CW90: =AI90 -> 0 | CX90: =AJ90 -> 0 | CY90: =(ROUND((((S90+ROUND((ROUND(((EU90)*AV90*1),2)*BS90),2))*AT90)/100),2)+ROUND(((ROUND((ROUND(((AE90-(EU90))*AV90*1),2)*BS90),2)*AT90)/100),2)) -> 0 | CZ90: =(ROUND((((S90+ROUND((ROUND(((EU90)*AV90*1),2)*BS90),2))*AU90)/100),2)+ROUND(((ROUND((ROUND(((AE90-(EU90))*AV90*1),2)*BS90),2)*AU90)/100),2)) -> 0 | DN90: 0 | DO90: 0 | DP90: 1 | DQ90: 1 | DU90: 1003 | DV90: м | DW90: м | DX90: 1 | EE90: 85133641 | EF90: 30 | EG90: Строительные работы | EH90: 0 | EJ90: 1 | EK90: 21 | EL90: ТСН-2001.3-16. Трубопроводы внутренние | EM90: ТСН-2001.3-16-1 | EO90: Поправка: Гл.6.Прил.2.2.п.2.2.6_06.00.01.07.001_x000D_ Поправка: Гл.12.Прил.8.п.8. 3_12.00.01.11.001 | EQ90: 0 | ER90: 28.1 | ES90: 28.1 | ET90: 0 | EU90: 0 | EV90: 0 | EW90: 0 | EX90: 0 | FQ90: 0 | FR90: 0 | FS90: 0 | FX90: 109 | FY90: 61 | GD90: 1 | GF90: -367345504 | GG90: 2 | GH90: 1 | GI90: 2 | GJ90: 0 | GK90: 0 | GL90: =ROUND(IF(AND(BH90=3,BI90=3,FS90<>0),P90,0),2) -> 0 | GM90: =ROUND(O90+X90+Y90,2)+GX90 -> 14658.08 | GN90: =IF(OR(BI90=0,BI90=1),GM90-GX90,0) -> 14658.08 | GO90: =IF(BI90=2,GM90-GX90,0) -> 0 | GP90: =IF(BI90=4,GM90-GX90,0) -> 0 | GR90: 0 | GS90: 3 | GT90: 0 | GV90: =ROUND((GT90),6) -> 0 | GW90: 1 | GX90: =ROUND(HC90*I90,2) -> 0 | HA90: 0 | HB90: 0 | HC90: =GV90*GW90 -> 0 | HM90: *1)*1 | HS90: 0 | IK90: 0
A91: 17 | B91: 1 | C91: =ROW(SmtRes!A130) -> 130 | D91: =ROW(EtalonRes!A151) -> 151 | E91: 12 | F91: 3.16-7-2 | G91: Прокладка трубопроводов водоснабжения из стальных водогазопроводных оцинкованных труб диаметром 20 мм | H91: 100 м трубопровода | I91: =ROUND((45)/100,9) -> 0.45 | J91: 0 | K91: =ROUND((45)/100,9) -> 0.45 | O91: =ROUND(CP91,2) -> 336.35 | P91: =ROUND((ROUND((AC91*AW91*I91),2)*BC91),2) -> 20.14 | Q91: =(ROUND((ROUND(((((ET91*1.25)*1.2))*AV91*I91),2)*BB91),2)+ROUND((ROUND(((AE91-(((EU91*1.25)*1.2)))*AV91*I91),2)*BS91),2)) -> 34.41 | R91: =(ROUND((ROUND(((((EU91*1.25)*1.2))*AV91*I91),2)*BS91),2)+ROUND((ROUND(((AE91-(((EU91*1.25)*1.2)))*AV91*I91),2)*BS91),2)) -> 4.36 | S91: =ROUND((ROUND((AF91*AV91*I91),2)*BA91),2) -> 281.8 | T91: =ROUND(CU91*I91,2) -> 0 | U91: =CV91*I91 -> 22.329856 | V91: =CW91*I91 -> 0 | W91: =ROUND(CX91*I91,2) -> 0 | X91: =(ROUND((((S91+ROUND((ROUND(((((EU91*1.25)*1.2))*AV91*I91),2)*BS91),2))*AT91)/100),2)+ROUND(((ROUND((ROUND(((AE91-(((EU91*1.25)*1.2)))*AV91*I91),2)*BS91),2)*AT91)/100),2)) -> 311.91 | Y91: =(ROUND((((S91+ROUND((ROUND(((((EU91*1.25)*1.2))*AV91*I91),2)*BS91),2))*AU91)/100),2)+ROUND(((ROUND((ROUND(((AE91-(((EU91*1.25)*1.2)))*AV91*I91),2)*BS91),2)*AU91)/100),2)) -> 174.56 | AA91: 85736471 | AB91: =ROUND((AC91+AD91+AF91),6) -> 703.3152 | AC91: =ROUND((((ES91*1)*1)),6) -> 44.76 | AD91: =ROUND((((((ET91*1.25)*1.2))-(((EU91*1.25)*1.2)))+AE91),6) -> 71.655 | AE91: =ROUND((((EU91*1.25)*1.2)),6) -> 9.09 | AF91: =ROUND((((EV91*1.15)*1.2)),6) -> 586.9002 | AG91: =ROUND((AP91),6) -> 0 | AH91: =(((EW91*1.15)*1.2)) -> 46.506 | AI91: =(((EX91*1.25)*1.2)) -> 0 | AJ91: =(AS91) -> 0 | AK91: 517.82 | AL91: 44.76 | AM91: 47.77 | AN91: 6.06 | AO91: 425.29 | AP91: 0 | AQ91: 33.7 | AR91: 0 | AS91: 0 | AT91: 109 | AU91: 61 | AV91: 1.067 | AW91: 1 | AZ91: 1 | BA91: 1 | BB91: 1 | BC91: 1 | BH91: 0 | BI91: 1 | BJ91: ТСН-2001.3 Доп. 79, Сб. 16, т. 7, поз. 2 | BM91: 21 | BN91: 0 | BO91: 3.16-7-2 | BP91: 1 | BQ91: 30 | BR91: 0 | BS91: 1 | BT91: 1 | BU91: 1 | BV91: 1 | BW91: 1 | BX91: 1 | BZ91: 109 | CA91: 61 | CE91: 1566 | CF91: 0 | CG91: 0 | CM91: 0 | CN91: Поправка: Гл.6.Прил.2.2.п.2.2.6_06.00.01.07.001 Наименование: При выполнении при капитальном ремонте и реконструкции работ, аналогичных технологическим процессам, характерным для нового строительства, и отсутствующих в сборниках на ремонтно-строительные работы ТСН-2001.6 Поправка: Гл.12.Прил.8.п.8. 3_12.00.01.11.001 Наименование: При наличии напряженных и стесненных условий производства работ (стесненность, сложность складирования и транспортной логистики и т.п.) для объектов, расположенных в пределах круговой магистральной системы улиц "Садовое кольцо" города Москвы | CO91: 0 | CP91: =(P91+Q91+S91) -> 336.35 | CQ91: =ROUND((ROUND((AC91*AW91*1),2)*BC91),2) -> 44.76 | CR91: =(ROUND((ROUND(((((ET91*1.25)*1.2))*AV91*1),2)*BB91),2)+ROUND((ROUND(((AE91-(((EU91*1.25)*1.2)))*AV91*1),2)*BS91),2)) -> 76.46 | CS91: =(ROUND((ROUND(((((EU91*1.25)*1.2))*AV91*1),2)*BS91),2)+ROUND((ROUND(((AE91-(((EU91*1.25)*1.2)))*AV91*1),2)*BS91),2)) -> 9.7 | CT91: =ROUND((ROUND((AF91*AV91*1),2)*BA91),2) -> 626.22 | CU91: =AG91 -> 0 | CV91: =(AH91*AV91) -> 49.621902 | CW91: =AI91 -> 0 | CX91: =AJ91 -> 0 | CY91: =(ROUND((((S91+ROUND((ROUND(((((EU91*1.25)*1.2))*AV91*1),2)*BS91),2))*AT91)/100),2)+ROUND(((ROUND((ROUND(((AE91-(((EU91*1.25)*1.2)))*AV91*1),2)*BS91),2)*AT91)/100),2)) -> 317.74 | CZ91: =(ROUND((((S91+ROUND((ROUND(((((EU91*1.25)*1.2))*AV91*1),2)*BS91),2))*AU91)/100),2)+ROUND(((ROUND((ROUND(((AE91-(((EU91*1.25)*1.2)))*AV91*1),2)*BS91),2)*AU91)/100),2)) -> 177.82 | DB91: 31 | DD91: *1)*1 | DE91: *1,25)*1,2 | DF91: *1,25)*1,2 | DG91: *1,15)*1,2 | DI91: *1,15)*1,2 | DJ91: *1,25)*1,2 | DN91: 0 | DO91: 0 | DP91: 1 | DQ91: 1 | DU91: 1013 | DV91: 100 м трубопровода | DW91: 100 м трубопровода | DX91: 1 | EE91: 85133641 | EF91: 30 | EG91: Строительные работы | EH91: 0 | EJ91: 1 | EK91: 21 | EL91: ТСН-2001.3-16. Трубопроводы внутренние | EM91: ТСН-2001.3-16-1 | EO91: Поправка: Гл.6.Прил.2.2.п.2.2.6_06.00.01.07.001 Поправка: Гл.12.Прил.8.п.8. 3_12.00.01.11.001 | EQ91: 0 | ER91: 517.82 | ES91: 44.76 | ET91: 47.77 | EU91: 6.06 | EV91: 425.29 | EW91: 33.7 | EX91: 0 | EY91: 0 | FQ91: 0 | FR91: 0 | FS91: 0 | FX91: 109 | FY91: 61 | GD91: 1 | GF91: -756103936 | GG91: 2 | GH91: 1 | GI91: 2 | GJ91: 0 | GK91: 0 | GL91: =ROUND(IF(AND(BH91=3,BI91=3,FS91<>0),P91,0),2) -> 0 | GM91: =ROUND(O91+X91+Y91,2)+GX91 -> 822.82 | GN91: =IF(OR(BI91=0,BI91=1),GM91-GX91,0) -> 822.82 | GO91: =IF(BI91=2,GM91-GX91,0) -> 0 | GP91: =IF(BI91=4,GM91-GX91,0) -> 0 | GR91: 0 | GS91: 3 | GT91: 0 | GV91: =ROUND((GT91),6) -> 0 | GW91: 1 | GX91: =ROUND(HC91*I91,2) -> 0 | HA91: 0 | HB91: 0 | HC91: =GV91*GW91 -> 0 | HS91: 0 | IK91: 0
A92: 17 | B92: 1 | C92: =ROW(SmtRes!A144) -> 144 | D92: =ROW(EtalonRes!A166) -> 166 | E92: 12 | F92: 3.16-7-2 | G92: Прокладка трубопроводов водоснабжения из стальных водогазопроводных оцинкованных труб диаметром 20 мм | H92: 100 м трубопровода | I92: =ROUND((45)/100,9) -> 0.45 | J92: 0 | K92: =ROUND((45)/100,9) -> 0.45 | O92: =ROUND(CP92,2) -> 16563.7 | P92: =ROUND((ROUND((AC92*AW92*I92),2)*BC92),2) -> 126.48 | Q92: =(ROUND((ROUND(((((ET92*1.25)*1.2))*AV92*I92),2)*BB92),2)+ROUND((ROUND(((AE92-(((EU92*1.25)*1.2)))*AV92*I92),2)*BS92),2)) -> 557.79 | R92: =(ROUND((ROUND(((((EU92*1.25)*1.2))*AV92*I92),2)*BS92),2)+ROUND((ROUND(((AE92-(((EU92*1.25)*1.2)))*AV92*I92),2)*BS92),2)) -> 245.69 | S92: =ROUND((ROUND((AF92*AV92*I92),2)*BA92),2) -> 15879.43 | T92: =ROUND(CU92*I92,2) -> 0 | U92: =CV92*I92 -> 22.329856 | V92: =CW92*I92 -> 0 | W92: =ROUND(CX92*I92,2) -> 0 | X92: =(ROUND((((S92+ROUND((ROUND(((((EU92*1.25)*1.2))*AV92*I92),2)*BS92),2))*AT92)/100),2)+ROUND(((ROUND((ROUND(((AE92-(((EU92*1.25)*1.2)))*AV92*I92),2)*BS92),2)*AT92)/100),2)) -> 17576.38 | Y92: =(ROUND((((S92+ROUND((ROUND(((((EU92*1.25)*1.2))*AV92*I92),2)*BS92),2))*AU92)/100),2)+ROUND(((ROUND((ROUND(((AE92-(((EU92*1.25)*1.2)))*AV92*I92),2)*BS92),2)*AU92)/100),2)) -> 9836.32 | AA92: 85736473 | AB92: =ROUND((AC92+AD92+AF92),6) -> 703.3152 | AC92: =ROUND((((ES92*1)*1)),6) -> 44.76 | AD92: =ROUND((((((ET92*1.25)*1.2))-(((EU92*1.25)*1.2)))+AE92),6) -> 71.655 | AE92: =ROUND((((EU92*1.25)*1.2)),6) -> 9.09 | AF92: =ROUND((((EV92*1.15)*1.2)),6) -> 586.9002 | AG92: =ROUND((AP92),6) -> 0 | AH92: =(((EW92*1.15)*1.2)) -> 46.506 | AI92: =(((EX92*1.25)*1.2)) -> 0 | AJ92: =(AS92) -> 0 | AK92: 517.82 | AL92: 44.76 | AM92: 47.77 | AN92: 6.06 | AO92: 425.29 | AP92: 0 | AQ92: 33.7 | AR92: 0 | AS92: 0 | AT92: 109 | AU92: 61 | AV92: 1.067 | AW92: 1 | AZ92: 1 | BA92: 56.35 | BB92: 16.21 | BC92: 6.28 | BH92: 0 | BI92: 1 | BJ92: ТСН-2001.3 Доп. 79, Сб. 16, т. 7, поз. 2 | BM92: 21 | BN92: 0 | BO92: 3.16-7-2 | BP92: 1 | BQ92: 30 | BR92: 0 | BS92: 56.35 | BT92: 1 | BU92: 1 | BV92: 1 | BW92: 1 | BX92: 1 | BZ92: 109 | CA92: 61 | CE92: 1566 | CF92: 0 | CG92: 0 | CM92: 0 | CN92: Поправка: Гл.6.Прил.2.2.п.2.2.6_06.00.01.07.001 Наименование: При выполнении при капитальном ремонте и реконструкции работ, аналогичных технологическим процессам, характерным для нового строительства, и отсутствующих в сборниках на ремонтно-строительные работы ТСН-2001.6 Поправка: Гл.12.Прил.8.п.8. 3_12.00.01.11.001 Наименование: При наличии напряженных и стесненных условий производства работ (стесненность, сложность складирования и транспортной логистики и т.п.) для объектов, расположенных в пределах круговой магистральной системы улиц "Садовое кольцо" города Москвы | CO92: 0 | CP92: =(P92+Q92+S92) -> 16563.7 | CQ92: =ROUND((ROUND((AC92*AW92*1),2)*BC92),2) -> 281.09 | CR92: =(ROUND((ROUND(((((ET92*1.25)*1.2))*AV92*1),2)*BB92),2)+ROUND((ROUND(((AE92-(((EU92*1.25)*1.2)))*AV92*1),2)*BS92),2)) -> 1239.42 | CS92: =(ROUND((ROUND(((((EU92*1.25)*1.2))*AV92*1),2)*BS92),2)+ROUND((ROUND(((AE92-(((EU92*1.25)*1.2)))*AV92*1),2)*BS92),2)) -> 546.6 | CT92: =ROUND((ROUND((AF92*AV92*1),2)*BA92),2) -> 35287.5 | CU92: =AG92 -> 0 | CV92: =(AH92*AV92) -> 49.621902 | CW92: =AI92 -> 0 | CX92: =AJ92 -> 0 | CY92: =(ROUND((((S92+ROUND((ROUND(((((EU92*1.25)*1.2))*AV92*1),2)*BS92),2))*AT92)/100),2)+ROUND(((ROUND((ROUND(((AE92-(((EU92*1.25)*1.2)))*AV92*1),2)*BS92),2)*AT92)/100),2)) -> 17904.37 | CZ92: =(ROUND((((S92+ROUND((ROUND(((((EU92*1.25)*1.2))*AV92*1),2)*BS92),2))*AU92)/100),2)+ROUND(((ROUND((ROUND(((AE92-(((EU92*1.25)*1.2)))*AV92*1),2)*BS92),2)*AU92)/100),2)) -> 10019.88 | DB92: 33 | DD92: *1)*1 | DE92: *1,25)*1,2 | DF92: *1,25)*1,2 | DG92: *1,15)*1,2 | DI92: *1,15)*1,2 | DJ92: *1,25)*1,2 | DN92: 0 | DO92: 0 | DP92: 1 | DQ92: 1 | DU92: 1013 | DV92: 100 м трубопровода | DW92: 100 м трубопровода | DX92: 1 | EE92: 85133641 | EF92: 30 | EG92: Строительные работы | EH92: 0 | EJ92: 1 | EK92: 21 | EL92: ТСН-2001.3-16. Трубопроводы внутренние | EM92: ТСН-2001.3-16-1 | EO92: Поправка: Гл.6.Прил.2.2.п.2.2.6_06.00.01.07.001 Поправка: Гл.12.Прил.8.п.8. 3_12.00.01.11.001 | EQ92: 0 | ER92: 517.82 | ES92: 44.76 | ET92: 47.77 | EU92: 6.06 | EV92: 425.29 | EW92: 33.7 | EX92: 0 | EY92: 0 | FQ92: 0 | FR92: 0 | FS92: 0 | FX92: 109 | FY92: 61 | GD92: 1 | GF92: -756103936 | GG92: 2 | GH92: 1 | GI92: 2 | GJ92: 0 | GK92: 0 | GL92: =ROUND(IF(AND(BH92=3,BI92=3,FS92<>0),P92,0),2) -> 0 | GM92: =ROUND(O92+X92+Y92,2)+GX92 -> 43976.4 | GN92: =IF(OR(BI92=0,BI92=1),GM92-GX92,0) -> 43976.4 | GO92: =IF(BI92=2,GM92-GX92,0) -> 0 | GP92: =IF(BI92=4,GM92-GX92,0) -> 0 | GR92: 0 | GS92: 3 | GT92: 0 | GV92: =ROUND((GT92),6) -> 0 | GW92: 1 | GX92: =ROUND(HC92*I92,2) -> 0 | HA92: 0 | HB92: 0 | HC92: =GV92*GW92 -> 0 | HS92: 0 | IK92: 0
A93: 18 | B93: 1 | C93: 130 | E93: 12,1 | F93: 1.13-4-62 | G93: Кран шаровой, латунный, никелированный, полнопроходной, с алюминиевой рукояткой, муфтовый, температура рабочей среды от -15 до +110°С, номинальное давление PN 4,0 МПа, номинальный диаметр DN 20 мм | H93: шт. | I93: =I91*J93 -> 12 | J93: 26.666667 | K93: 26.666667 | O93: =ROUND(CP93,2) -> 566.88 | P93: =ROUND((ROUND((AC93*AW93*I93),2)*BC93),2) -> 566.88 | Q93: =(ROUND((ROUND(((ET93)*AV93*I93),2)*BB93),2)+ROUND((ROUND(((AE93-(EU93))*AV93*I93),2)*BS93),2)) -> 0 | R93: =(ROUND((ROUND(((EU93)*AV93*I93),2)*BS93),2)+ROUND((ROUND(((AE93-(EU93))*AV93*I93),2)*BS93),2)) -> 0 | S93: =ROUND((ROUND((AF93*AV93*I93),2)*BA93),2) -> 0 | T93: =ROUND(CU93*I93,2) -> 0 | U93: =CV93*I93 -> 0 | V93: =CW93*I93 -> 0 | W93: =ROUND(CX93*I93,2) -> 0 | X93: =(ROUND((((S93+ROUND((ROUND(((EU93)*AV93*I93),2)*BS93),2))*AT93)/100),2)+ROUND(((ROUND((ROUND(((AE93-(EU93))*AV93*I93),2)*BS93),2)*AT93)/100),2)) -> 0 | Y93: =(ROUND((((S93+ROUND((ROUND(((EU93)*AV93*I93),2)*BS93),2))*AU93)/100),2)+ROUND(((ROUND((ROUND(((AE93-(EU93))*AV93*I93),2)*BS93),2)*AU93)/100),2)) -> 0 | AA93: 85736471 | AB93: =ROUND((AC93+AD93+AF93),6) -> 47.24 | AC93: =ROUND((ES93),6) -> 47.24 | AD93: =ROUND((((ET93)-(EU93))+AE93),6) -> 0 | AE93: =ROUND((EU93),6) -> 0 | AF93: =ROUND((EV93),6) -> 0 | AG93: =ROUND((AP93),6) -> 0 | AH93: =(EW93) -> 0 | AI93: =(EX93) -> 0 | AJ93: =(AS93) -> 0 | AK93: 47.24 | AL93: 47.24 | AM93: 0 | AN93: 0 | AO93: 0 | AP93: 0 | AQ93: 0 | AR93: 0 | AS93: 0 | AT93: 109 | AU93: 61 | AV93: 1 | AW93: 1 | AZ93: 1 | BA93: 1 | BB93: 1 | BC93: 1 | BH93: 3 | BI93: 1 | BJ93: ТСН-2001.1 Доп. 73, Р. 13, о. 4, поз. 62 | BM93: 21 | BN93: 0 | BP93: 0 | BQ93: 30 | BR93: 0 | BS93: 1 | BT93: 1 | BU93: 1 | BV93: 1 | BW93: 1 | BX93: 1 | BZ93: 109 | CA93: 61 | CE93: 1566 | CF93: 0 | CG93: 0 | CM93: 0 | CN93: Поправка: Гл.6.Прил.2.2.п.2.2.6_06.00.01.07.001_x000D_ Наименование: При выполнении при капитальном ремонте и реконструкции работ, аналогичных технологическим процессам, характерным для нового строительства, и отсутствующих в сборниках на ремонтно-строительные работы ТСН-2001.6_x000D_ Поправка: Гл.12.Прил.8.п.8. 3_12.00.01.11.001_x000D_ Наименование: При наличии напряженных и стесненных условий производства работ (стесненность, сложность складирования и транспортной логистики и т.п.) для объектов, расположенных в пределах круговой магистральной системы улиц "Садовое кольцо" города Москвы | CO93: 0 | CP93: =(P93+Q93+S93) -> 566.88 | CQ93: =ROUND((ROUND((AC93*AW93*1),2)*BC93),2) -> 47.24 | CR93: =(ROUND((ROUND(((ET93)*AV93*1),2)*BB93),2)+ROUND((ROUND(((AE93-(EU93))*AV93*1),2)*BS93),2)) -> 0 | CS93: =(ROUND((ROUND(((EU93)*AV93*1),2)*BS93),2)+ROUND((ROUND(((AE93-(EU93))*AV93*1),2)*BS93),2)) -> 0 | CT93: =ROUND((ROUND((AF93*AV93*1),2)*BA93),2) -> 0 | CU93: =AG93 -> 0 | CV93: =(AH93*AV93) -> 0 | CW93: =AI93 -> 0 | CX93: =AJ93 -> 0 | CY93: =(ROUND((((S93+ROUND((ROUND(((EU93)*AV93*1),2)*BS93),2))*AT93)/100),2)+ROUND(((ROUND((ROUND(((AE93-(EU93))*AV93*1),2)*BS93),2)*AT93)/100),2)) -> 0 | CZ93: =(ROUND((((S93+ROUND((ROUND(((EU93)*AV93*1),2)*BS93),2))*AU93)/100),2)+ROUND(((ROUND((ROUND(((AE93-(EU93))*AV93*1),2)*BS93),2)*AU93)/100),2)) -> 0 | DN93: 0 | DO93: 0 | DP93: 1 | DQ93: 1 | DU93: 1010 | DV93: шт. | DW93: шт. | DX93: 1 | EE93: 85133641 | EF93: 30 | EG93: Строительные работы | EH93: 0 | EJ93: 1 | EK93: 21 | EL93: ТСН-2001.3-16. Трубопроводы внутренние | EM93: ТСН-2001.3-16-1 | EO93: Поправка: Гл.6.Прил.2.2.п.2.2.6_06.00.01.07.001_x000D_ Поправка: Гл.12.Прил.8.п.8. 3_12.00.01.11.001 | EQ93: 0 | ER93: 47.24 | ES93: 47.24 | ET93: 0 | EU93: 0 | EV93: 0 | EW93: 0 | EX93: 0 | FQ93: 0 | FR93: 0 | FS93: 0 | FX93: 109 | FY93: 61 | GD93: 1 | GF93: -720383431 | GG93: 2 | GH93: 1 | GI93: -2 | GJ93: 0 | GK93: 0 | GL93: =ROUND(IF(AND(BH93=3,BI93=3,FS93<>0),P93,0),2) -> 0 | GM93: =ROUND(O93+X93+Y93,2)+GX93 -> 566.88 | GN93: =IF(OR(BI93=0,BI93=1),GM93-GX93,0) -> 566.88 | GO93: =IF(BI93=2,GM93-GX93,0) -> 0 | GP93: =IF(BI93=4,GM93-GX93,0) -> 0 | GR93: 0 | GS93: 3 | GT93: 0 | GV93: =ROUND((GT93),6) -> 0 | GW93: 1 | GX93: =ROUND(HC93*I93,2) -> 0 | HA93: 0 | HB93: 0 | HC93: =GV93*GW93 -> 0 | HM93: *1)*1 | HS93: 0 | IK93: 0
A94: 18 | B94: 1 | C94: 144 | E94: 12,1 | F94: 1.13-4-62 | G94: Кран шаровой, латунный, никелированный, полнопроходной, с алюминиевой рукояткой, муфтовый, температура рабочей среды от -15 до +110°С, номинальное давление PN 4,0 МПа, номинальный диаметр DN 20 мм | H94: шт. | I94: =I92*J94 -> 12 | J94: 26.666667 | K94: 26.666667 | O94: =ROUND(CP94,2) -> 12142.57 | P94: =ROUND((ROUND((AC94*AW94*I94),2)*BC94),2) -> 12142.57 | Q94: =(ROUND((ROUND(((ET94)*AV94*I94),2)*BB94),2)+ROUND((ROUND(((AE94-(EU94))*AV94*I94),2)*BS94),2)) -> 0 | R94: =(ROUND((ROUND(((EU94)*AV94*I94),2)*BS94),2)+ROUND((ROUND(((AE94-(EU94))*AV94*I94),2)*BS94),2)) -> 0 | S94: =ROUND((ROUND((AF94*AV94*I94),2)*BA94),2) -> 0 | T94: =ROUND(CU94*I94,2) -> 0 | U94: =CV94*I94 -> 0 | V94: =CW94*I94 -> 0 | W94: =ROUND(CX94*I94,2) -> 0 | X94: =(ROUND((((S94+ROUND((ROUND(((EU94)*AV94*I94),2)*BS94),2))*AT94)/100),2)+ROUND(((ROUND((ROUND(((AE94-(EU94))*AV94*I94),2)*BS94),2)*AT94)/100),2)) -> 0 | Y94: =(ROUND((((S94+ROUND((ROUND(((EU94)*AV94*I94),2)*BS94),2))*AU94)/100),2)+ROUND(((ROUND((ROUND(((AE94-(EU94))*AV94*I94),2)*BS94),2)*AU94)/100),2)) -> 0 | AA94: 85736473 | AB94: =ROUND((AC94+AD94+AF94),6) -> 47.24 | AC94: =ROUND((ES94),6) -> 47.24 | AD94: =ROUND((((ET94)-(EU94))+AE94),6) -> 0 | AE94: =ROUND((EU94),6) -> 0 | AF94: =ROUND((EV94),6) -> 0 | AG94: =ROUND((AP94),6) -> 0 | AH94: =(EW94) -> 0 | AI94: =(EX94) -> 0 | AJ94: =(AS94) -> 0 | AK94: 47.24 | AL94: 47.24 | AM94: 0 | AN94: 0 | AO94: 0 | AP94: 0 | AQ94: 0 | AR94: 0 | AS94: 0 | AT94: 109 | AU94: 61 | AV94: 1 | AW94: 1 | AZ94: 1 | BA94: 1 | BB94: 1 | BC94: 21.42 | BH94: 3 | BI94: 1 | BJ94: ТСН-2001.1 Доп. 73, Р. 13, о. 4, поз. 62 | BM94: 21 | BN94: 0 | BO94: 1.13-4-62 | BP94: 1 | BQ94: 30 | BR94: 0 | BS94: 1 | BT94: 1 | BU94: 1 | BV94: 1 | BW94: 1 | BX94: 1 | BZ94: 109 | CA94: 61 | CE94: 1566 | CF94: 0 | CG94: 0 | CM94: 0 | CN94: Поправка: Гл.6.Прил.2.2.п.2.2.6_06.00.01.07.001_x000D_ Наименование: При выполнении при капитальном ремонте и реконструкции работ, аналогичных технологическим процессам, характерным для нового строительства, и отсутствующих в сборниках на ремонтно-строительные работы ТСН-2001.6_x000D_ Поправка: Гл.12.Прил.8.п.8. 3_12.00.01.11.001_x000D_ Наименование: При наличии напряженных и стесненных условий производства работ (стесненность, сложность складирования и транспортной логистики и т.п.) для объектов, расположенных в пределах круговой магистральной системы улиц "Садовое кольцо" города Москвы | CO94: 0 | CP94: =(P94+Q94+S94) -> 12142.57 | CQ94: =ROUND((ROUND((AC94*AW94*1),2)*BC94),2) -> 1011.88 | CR94: =(ROUND((ROUND(((ET94)*AV94*1),2)*BB94),2)+ROUND((ROUND(((AE94-(EU94))*AV94*1),2)*BS94),2)) -> 0 | CS94: =(ROUND((ROUND(((EU94)*AV94*1),2)*BS94),2)+ROUND((ROUND(((AE94-(EU94))*AV94*1),2)*BS94),2)) -> 0 | CT94: =ROUND((ROUND((AF94*AV94*1),2)*BA94),2) -> 0 | CU94: =AG94 -> 0 | CV94: =(AH94*AV94) -> 0 | CW94: =AI94 -> 0 | CX94: =AJ94 -> 0 | CY94: =(ROUND((((S94+ROUND((ROUND(((EU94)*AV94*1),2)*BS94),2))*AT94)/100),2)+ROUND(((ROUND((ROUND(((AE94-(EU94))*AV94*1),2)*BS94),2)*AT94)/100),2)) -> 0 | CZ94: =(ROUND((((S94+ROUND((ROUND(((EU94)*AV94*1),2)*BS94),2))*AU94)/100),2)+ROUND(((ROUND((ROUND(((AE94-(EU94))*AV94*1),2)*BS94),2)*AU94)/100),2)) -> 0 | DN94: 0 | DO94: 0 | DP94: 1 | DQ94: 1 | DU94: 1010 | DV94: шт. | DW94: шт. | DX94: 1 | EE94: 85133641 | EF94: 30 | EG94: Строительные работы | EH94: 0 | EJ94: 1 | EK94: 21 | EL94: ТСН-2001.3-16. Трубопроводы внутренние | EM94: ТСН-2001.3-16-1 | EO94: Поправка: Гл.6.Прил.2.2.п.2.2.6_06.00.01.07.001_x000D_ Поправка: Гл.12.Прил.8.п.8. 3_12.00.01.11.001 | EQ94: 0 | ER94: 47.24 | ES94: 47.24 | ET94: 0 | EU94: 0 | EV94: 0 | EW94: 0 | EX94: 0 | FQ94: 0 | FR94: 0 | FS94: 0 | FX94: 109 | FY94: 61 | GD94: 1 | GF94: -720383431 | GG94: 2 | GH94: 1 | GI94: 2 | GJ94: 0 | GK94: 0 | GL94: =ROUND(IF(AND(BH94=3,BI94=3,FS94<>0),P94,0),2) -> 0 | GM94: =ROUND(O94+X94+Y94,2)+GX94 -> 12142.57 | GN94: =IF(OR(BI94=0,BI94=1),GM94-GX94,0) -> 12142.57 | GO94: =IF(BI94=2,GM94-GX94,0) -> 0 | GP94: =IF(BI94=4,GM94-GX94,0) -> 0 | GR94: 0 | GS94: 3 | GT94: 0 | GV94: =ROUND((GT94),6) -> 0 | GW94: 1 | GX94: =ROUND(HC94*I94,2) -> 0 | HA94: 0 | HB94: 0 | HC94: =GV94*GW94 -> 0 | HM94: *1)*1 | HS94: 0 | IK94: 0
A95: 18 | B95: 1 | C95: 129 | E95: 12,2 | F95: 1.12-1-53 | G95: Узел трубопровода из стальных водогазопроводных оцинкованных труб, с гильзами, для водоснабжения, диаметр условного прохода 20 мм | H95: м | I95: =I91*J95 -> 45 | J95: 100 | K95: 100 | O95: =ROUND(CP95,2) -> 1413.45 | P95: =ROUND((ROUND((AC95*AW95*I95),2)*BC95),2) -> 1413.45 | Q95: =(ROUND((ROUND(((ET95)*AV95*I95),2)*BB95),2)+ROUND((ROUND(((AE95-(EU95))*AV95*I95),2)*BS95),2)) -> 0 | R95: =(ROUND((ROUND(((EU95)*AV95*I95),2)*BS95),2)+ROUND((ROUND(((AE95-(EU95))*AV95*I95),2)*BS95),2)) -> 0 | S95: =ROUND((ROUND((AF95*AV95*I95),2)*BA95),2) -> 0 | T95: =ROUND(CU95*I95,2) -> 0 | U95: =CV95*I95 -> 0 | V95: =CW95*I95 -> 0 | W95: =ROUND(CX95*I95,2) -> 0 | X95: =(ROUND((((S95+ROUND((ROUND(((EU95)*AV95*I95),2)*BS95),2))*AT95)/100),2)+ROUND(((ROUND((ROUND(((AE95-(EU95))*AV95*I95),2)*BS95),2)*AT95)/100),2)) -> 0 | Y95: =(ROUND((((S95+ROUND((ROUND(((EU95)*AV95*I95),2)*BS95),2))*AU95)/100),2)+ROUND(((ROUND((ROUND(((AE95-(EU95))*AV95*I95),2)*BS95),2)*AU95)/100),2)) -> 0 | AA95: 85736471 | AB95: =ROUND((AC95+AD95+AF95),6) -> 31.41 | AC95: =ROUND((ES95),6) -> 31.41 | AD95: =ROUND((((ET95)-(EU95))+AE95),6) -> 0 | AE95: =ROUND((EU95),6) -> 0 | AF95: =ROUND((EV95),6) -> 0 | AG95: =ROUND((AP95),6) -> 0 | AH95: =(EW95) -> 0 | AI95: =(EX95) -> 0 | AJ95: =(AS95) -> 0 | AK95: 31.41 | AL95: 31.41 | AM95: 0 | AN95: 0 | AO95: 0 | AP95: 0 | AQ95: 0 | AR95: 0 | AS95: 0 | AT95: 109 | AU95: 61 | AV95: 1 | AW95: 1 | AZ95: 1 | BA95: 1 | BB95: 1 | BC95: 1 | BH95: 3 | BI95: 1 | BJ95: ТСН-2001.1 Доп. 79, Р. 12, о. 1, поз. 53 | BM95: 21 | BN95: 0 | BP95: 0 | BQ95: 30 | BR95: 0 | BS95: 1 | BT95: 1 | BU95: 1 | BV95: 1 | BW95: 1 | BX95: 1 | BZ95: 109 | CA95: 61 | CE95: 1566 | CF95: 0 | CG95: 0 | CM95: 0 | CN95: Поправка: Гл.6.Прил.2.2.п.2.2.6_06.00.01.07.001_x000D_ Наименование: При выполнении при капитальном ремонте и реконструкции работ, аналогичных технологическим процессам, характерным для нового строительства, и отсутствующих в сборниках на ремонтно-строительные работы ТСН-2001.6_x000D_ Поправка: Гл.12.Прил.8.п.8. 3_12.00.01.11.001_x000D_ Наименование: При наличии напряженных и стесненных условий производства работ (стесненность, сложность складирования и транспортной логистики и т.п.) для объектов, расположенных в пределах круговой магистральной системы улиц "Садовое кольцо" города Москвы | CO95: 0 | CP95: =(P95+Q95+S95) -> 1413.45 | CQ95: =ROUND((ROUND((AC95*AW95*1),2)*BC95),2) -> 31.41 | CR95: =(ROUND((ROUND(((ET95)*AV95*1),2)*BB95),2)+ROUND((ROUND(((AE95-(EU95))*AV95*1),2)*BS95),2)) -> 0 | CS95: =(ROUND((ROUND(((EU95)*AV95*1),2)*BS95),2)+ROUND((ROUND(((AE95-(EU95))*AV95*1),2)*BS95),2)) -> 0 | CT95: =ROUND((ROUND((AF95*AV95*1),2)*BA95),2) -> 0 | CU95: =AG95 -> 0 | CV95: =(AH95*AV95) -> 0 | CW95: =AI95 -> 0 | CX95: =AJ95 -> 0 | CY95: =(ROUND((((S95+ROUND((ROUND(((EU95)*AV95*1),2)*BS95),2))*AT95)/100),2)+ROUND(((ROUND((ROUND(((AE95-(EU95))*AV95*1),2)*BS95),2)*AT95)/100),2)) -> 0 | CZ95: =(ROUND((((S95+ROUND((ROUND(((EU95)*AV95*1),2)*BS95),2))*AU95)/100),2)+ROUND(((ROUND((ROUND(((AE95-(EU95))*AV95*1),2)*BS95),2)*AU95)/100),2)) -> 0 | DN95: 0 | DO95: 0 | DP95: 1 | DQ95: 1 | DU95: 1003 | DV95: м | DW95: м | DX95: 1 | EE95: 85133641 | EF95: 30 | EG95: Строительные работы | EH95: 0 | EJ95: 1 | EK95: 21 | EL95: ТСН-2001.3-16. Трубопроводы внутренние | EM95: ТСН-2001.3-16-1 | EO95: Поправка: Гл.6.Прил.2.2.п.2.2.6_06.00.01.07.001_x000D_ Поправка: Гл.12.Прил.8.п.8. 3_12.00.01.11.001 | EQ95: 0 | ER95: 31.41 | ES95: 31.41 | ET95: 0 | EU95: 0 | EV95: 0 | EW95: 0 | EX95: 0 | FQ95: 0 | FR95: 0 | FS95: 0 | FX95: 109 | FY95: 61 | GD95: 1 | GF95: 935342670 | GG95: 2 | GH95: 1 | GI95: -2 | GJ95: 0 | GK95: 0 | GL95: =ROUND(IF(AND(BH95=3,BI95=3,FS95<>0),P95,0),2) -> 0 | GM95: =ROUND(O95+X95+Y95,2)+GX95 -> 1413.45 | GN95: =IF(OR(BI95=0,BI95=1),GM95-GX95,0) -> 1413.45 | GO95: =IF(BI95=2,GM95-GX95,0) -> 0 | GP95: =IF(BI95=4,GM95-GX95,0) -> 0 | GR95: 0 | GS95: 3 | GT95: 0 | GV95: =ROUND((GT95),6) -> 0 | GW95: 1 | GX95: =ROUND(HC95*I95,2) -> 0 | HA95: 0 | HB95: 0 | HC95: =GV95*GW95 -> 0 | HM95: *1)*1 | HS95: 0 | IK95: 0
A96: 18 | B96: 1 | C96: 143 | E96: 12,2 | F96: 1.12-1-53 | G96: Узел трубопровода из стальных водогазопроводных оцинкованных труб, с гильзами, для водоснабжения, диаметр условного прохода 20 мм | H96: м | I96: =I92*J96 -> 45 | J96: 100 | K96: 100 | O96: =ROUND(CP96,2) -> 26162.96 | P96: =ROUND((ROUND((AC96*AW96*I96),2)*BC96),2) -> 26162.96 | Q96: =(ROUND((ROUND(((ET96)*AV96*I96),2)*BB96),2)+ROUND((ROUND(((AE96-(EU96))*AV96*I96),2)*BS96),2)) -> 0 | R96: =(ROUND((ROUND(((EU96)*AV96*I96),2)*BS96),2)+ROUND((ROUND(((AE96-(EU96))*AV96*I96),2)*BS96),2)) -> 0 | S96: =ROUND((ROUND((AF96*AV96*I96),2)*BA96),2) -> 0 | T96: =ROUND(CU96*I96,2) -> 0 | U96: =CV96*I96 -> 0 | V96: =CW96*I96 -> 0 | W96: =ROUND(CX96*I96,2) -> 0 | X96: =(ROUND((((S96+ROUND((ROUND(((EU96)*AV96*I96),2)*BS96),2))*AT96)/100),2)+ROUND(((ROUND((ROUND(((AE96-(EU96))*AV96*I96),2)*BS96),2)*AT96)/100),2)) -> 0 | Y96: =(ROUND((((S96+ROUND((ROUND(((EU96)*AV96*I96),2)*BS96),2))*AU96)/100),2)+ROUND(((ROUND((ROUND(((AE96-(EU96))*AV96*I96),2)*BS96),2)*AU96)/100),2)) -> 0 | AA96: 85736473 | AB96: =ROUND((AC96+AD96+AF96),6) -> 31.41 | AC96: =ROUND((ES96),6) -> 31.41 | AD96: =ROUND((((ET96)-(EU96))+AE96),6) -> 0 | AE96: =ROUND((EU96),6) -> 0 | AF96: =ROUND((EV96),6) -> 0 | AG96: =ROUND((AP96),6) -> 0 | AH96: =(EW96) -> 0 | AI96: =(EX96) -> 0 | AJ96: =(AS96) -> 0 | AK96: 31.41 | AL96: 31.41 | AM96: 0 | AN96: 0 | AO96: 0 | AP96: 0 | AQ96: 0 | AR96: 0 | AS96: 0 | AT96: 109 | AU96: 61 | AV96: 1 | AW96: 1 | AZ96: 1 | BA96: 1 | BB96: 1 | BC96: 18.51 | BH96: 3 | BI96: 1 | BJ96: ТСН-2001.1 Доп. 79, Р. 12, о. 1, поз. 53 | BM96: 21 | BN96: 0 | BO96: 1.12-1-53 | BP96: 1 | BQ96: 30 | BR96: 0 | BS96: 1 | BT96: 1 | BU96: 1 | BV96: 1 | BW96: 1 | BX96: 1 | BZ96: 109 | CA96: 61 | CE96: 1566 | CF96: 0 | CG96: 0 | CM96: 0 | CN96: Поправка: Гл.6.Прил.2.2.п.2.2.6_06.00.01.07.001_x000D_ Наименование: При выполнении при капитальном ремонте и реконструкции работ, аналогичных технологическим процессам, характерным для нового строительства, и отсутствующих в сборниках на ремонтно-строительные работы ТСН-2001.6_x000D_ Поправка: Гл.12.Прил.8.п.8. 3_12.00.01.11.001_x000D_ Наименование: При наличии напряженных и стесненных условий производства работ (стесненность, сложность складирования и транспортной логистики и т.п.) для объектов, расположенных в пределах круговой магистральной системы улиц "Садовое кольцо" города Москвы | CO96: 0 | CP96: =(P96+Q96+S96) -> 26162.96 | CQ96: =ROUND((ROUND((AC96*AW96*1),2)*BC96),2) -> 581.4 | CR96: =(ROUND((ROUND(((ET96)*AV96*1),2)*BB96),2)+ROUND((ROUND(((AE96-(EU96))*AV96*1),2)*BS96),2)) -> 0 | CS96: =(ROUND((ROUND(((EU96)*AV96*1),2)*BS96),2)+ROUND((ROUND(((AE96-(EU96))*AV96*1),2)*BS96),2)) -> 0 | CT96: =ROUND((ROUND((AF96*AV96*1),2)*BA96),2) -> 0 | CU96: =AG96 -> 0 | CV96: =(AH96*AV96) -> 0 | CW96: =AI96 -> 0 | CX96: =AJ96 -> 0 | CY96: =(ROUND((((S96+ROUND((ROUND(((EU96)*AV96*1),2)*BS96),2))*AT96)/100),2)+ROUND(((ROUND((ROUND(((AE96-(EU96))*AV96*1),2)*BS96),2)*AT96)/100),2)) -> 0 | CZ96: =(ROUND((((S96+ROUND((ROUND(((EU96)*AV96*1),2)*BS96),2))*AU96)/100),2)+ROUND(((ROUND((ROUND(((AE96-(EU96))*AV96*1),2)*BS96),2)*AU96)/100),2)) -> 0 | DN96: 0 | DO96: 0 | DP96: 1 | DQ96: 1 | DU96: 1003 | DV96: м | DW96: м | DX96: 1 | EE96: 85133641 | EF96: 30 | EG96: Строительные работы | EH96: 0 | EJ96: 1 | EK96: 21 | EL96: ТСН-2001.3-16. Трубопроводы внутренние | EM96: ТСН-2001.3-16-1 | EO96: Поправка: Гл.6.Прил.2.2.п.2.2.6_06.00.01.07.001_x000D_ Поправка: Гл.12.Прил.8.п.8. 3_12.00.01.11.001 | EQ96: 0 | ER96: 31.41 | ES96: 31.41 | ET96: 0 | EU96: 0 | EV96: 0 | EW96: 0 | EX96: 0 | FQ96: 0 | FR96: 0 | FS96: 0 | FX96: 109 | FY96: 61 | GD96: 1 | GF96: 935342670 | GG96: 2 | GH96: 1 | GI96: 2 | GJ96: 0 | GK96: 0 | GL96: =ROUND(IF(AND(BH96=3,BI96=3,FS96<>0),P96,0),2) -> 0 | GM96: =ROUND(O96+X96+Y96,2)+GX96 -> 26162.96 | GN96: =IF(OR(BI96=0,BI96=1),GM96-GX96,0) -> 26162.96 | GO96: =IF(BI96=2,GM96-GX96,0) -> 0 | GP96: =IF(BI96=4,GM96-GX96,0) -> 0 | GR96: 0 | GS96: 3 | GT96: 0 | GV96: =ROUND((GT96),6) -> 0 | GW96: 1 | GX96: =ROUND(HC96*I96,2) -> 0 | HA96: 0 | HB96: 0 | HC96: =GV96*GW96 -> 0 | HM96: *1)*1 | HS96: 0 | IK96: 0
A97: 17 | B97: 1 | C97: =ROW(SmtRes!A158) -> 158 | D97: =ROW(EtalonRes!A181) -> 181 | E97: 13 | F97: 3.16-7-3 | G97: Прокладка трубопроводов водоснабжения из стальных водогазопроводных оцинкованных труб диаметром 25 мм | H97: 100 м трубопровода | I97: =ROUND((35)/100,9) -> 0.35 | J97: 0 | K97: =ROUND((35)/100,9) -> 0.35 | O97: =ROUND(CP97,2) -> 261.69 | P97: =ROUND((ROUND((AC97*AW97*I97),2)*BC97),2) -> 15.75 | Q97: =(ROUND((ROUND(((((ET97*1.25)*1.2))*AV97*I97),2)*BB97),2)+ROUND((ROUND(((AE97-(((EU97*1.25)*1.2)))*AV97*I97),2)*BS97),2)) -> 26.76 | R97: =(ROUND((ROUND(((((EU97*1.25)*1.2))*AV97*I97),2)*BS97),2)+ROUND((ROUND(((AE97-(((EU97*1.25)*1.2)))*AV97*I97),2)*BS97),2)) -> 3.39 | S97: =ROUND((ROUND((AF97*AV97*I97),2)*BA97),2) -> 219.18 | T97: =ROUND(CU97*I97,2) -> 0 | U97: =CV97*I97 -> 17.367666 | V97: =CW97*I97 -> 0 | W97: =ROUND(CX97*I97,2) -> 0 | X97: =(ROUND((((S97+ROUND((ROUND(((((EU97*1.25)*1.2))*AV97*I97),2)*BS97),2))*AT97)/100),2)+ROUND(((ROUND((ROUND(((AE97-(((EU97*1.25)*1.2)))*AV97*I97),2)*BS97),2)*AT97)/100),2)) -> 242.6 | Y97: =(ROUND((((S97+ROUND((ROUND(((((EU97*1.25)*1.2))*AV97*I97),2)*BS97),2))*AU97)/100),2)+ROUND(((ROUND((ROUND(((AE97-(((EU97*1.25)*1.2)))*AV97*I97),2)*BS97),2)*AU97)/100),2)) -> 135.77 | AA97: 85736471 | AB97: =ROUND((AC97+AD97+AF97),6) -> 703.5552 | AC97: =ROUND((((ES97*1)*1)),6) -> 45 | AD97: =ROUND((((((ET97*1.25)*1.2))-(((EU97*1.25)*1.2)))+AE97),6) -> 71.655 | AE97: =ROUND((((EU97*1.25)*1.2)),6) -> 9.09 | AF97: =ROUND((((EV97*1.15)*1.2)),6) -> 586.9002 | AG97: =ROUND((AP97),6) -> 0 | AH97: =(((EW97*1.15)*1.2)) -> 46.506 | AI97: =(((EX97*1.25)*1.2)) -> 0 | AJ97: =(AS97) -> 0 | AK97: 518.06 | AL97: 45 | AM97: 47.77 | AN97: 6.06 | AO97: 425.29 | AP97: 0 | AQ97: 33.7 | AR97: 0 | AS97: 0 | AT97: 109 | AU97: 61 | AV97: 1.067 | AW97: 1 | AZ97: 1 | BA97: 1 | BB97: 1 | BC97: 1 | BH97: 0 | BI97: 1 | BJ97: ТСН-2001.3 Доп. 79, Сб. 16, т. 7, поз. 3 | BM97: 21 | BN97: 0 | BO97: 3.16-7-3 | BP97: 1 | BQ97: 30 | BR97: 0 | BS97: 1 | BT97: 1 | BU97: 1 | BV97: 1 | BW97: 1 | BX97: 1 | BZ97: 109 | CA97: 61 | CE97: 1566 | CF97: 0 | CG97: 0 | CM97: 0 | CN97: Поправка: Гл.6.Прил.2.2.п.2.2.6_06.00.01.07.001 Наименование: При выполнении при капитальном ремонте и реконструкции работ, аналогичных технологическим процессам, характерным для нового строительства, и отсутствующих в сборниках на ремонтно-строительные работы ТСН-2001.6 Поправка: Гл.12.Прил.8.п.8. 3_12.00.01.11.001 Наименование: При наличии напряженных и стесненных условий производства работ (стесненность, сложность складирования и транспортной логистики и т.п.) для объектов, расположенных в пределах круговой магистральной системы улиц "Садовое кольцо" города Москвы | CO97: 0 | CP97: =(P97+Q97+S97) -> 261.69 | CQ97: =ROUND((ROUND((AC97*AW97*1),2)*BC97),2) -> 45 | CR97: =(ROUND((ROUND(((((ET97*1.25)*1.2))*AV97*1),2)*BB97),2)+ROUND((ROUND(((AE97-(((EU97*1.25)*1.2)))*AV97*1),2)*BS97),2)) -> 76.46 | CS97: =(ROUND((ROUND(((((EU97*1.25)*1.2))*AV97*1),2)*BS97),2)+ROUND((ROUND(((AE97-(((EU97*1.25)*1.2)))*AV97*1),2)*BS97),2)) -> 9.7 | CT97: =ROUND((ROUND((AF97*AV97*1),2)*BA97),2) -> 626.22 | CU97: =AG97 -> 0 | CV97: =(AH97*AV97) -> 49.621902 | CW97: =AI97 -> 0 | CX97: =AJ97 -> 0 | CY97: =(ROUND((((S97+ROUND((ROUND(((((EU97*1.25)*1.2))*AV97*1),2)*BS97),2))*AT97)/100),2)+ROUND(((ROUND((ROUND(((AE97-(((EU97*1.25)*1.2)))*AV97*1),2)*BS97),2)*AT97)/100),2)) -> 249.48 | CZ97: =(ROUND((((S97+ROUND((ROUND(((((EU97*1.25)*1.2))*AV97*1),2)*BS97),2))*AU97)/100),2)+ROUND(((ROUND((ROUND(((AE97-(((EU97*1.25)*1.2)))*AV97*1),2)*BS97),2)*AU97)/100),2)) -> 139.62 | DB97: 35 | DD97: *1)*1 | DE97: *1,25)*1,2 | DF97: *1,25)*1,2 | DG97: *1,15)*1,2 | DI97: *1,15)*1,2 | DJ97: *1,25)*1,2 | DN97: 0 | DO97: 0 | DP97: 1 | DQ97: 1 | DU97: 1013 | DV97: 100 м трубопровода | DW97: 100 м трубопровода | DX97: 1 | EE97: 85133641 | EF97: 30 | EG97: Строительные работы | EH97: 0 | EJ97: 1 | EK97: 21 | EL97: ТСН-2001.3-16. Трубопроводы внутренние | EM97: ТСН-2001.3-16-1 | EO97: Поправка: Гл.6.Прил.2.2.п.2.2.6_06.00.01.07.001 Поправка: Гл.12.Прил.8.п.8. 3_12.00.01.11.001 | EQ97: 0 | ER97: 518.06 | ES97: 45 | ET97: 47.77 | EU97: 6.06 | EV97: 425.29 | EW97: 33.7 | EX97: 0 | EY97: 0 | FQ97: 0 | FR97: 0 | FS97: 0 | FX97: 109 | FY97: 61 | GD97: 1 | GF97: 124743446 | GG97: 2 | GH97: 1 | GI97: 2 | GJ97: 0 | GK97: 0 | GL97: =ROUND(IF(AND(BH97=3,BI97=3,FS97<>0),P97,0),2) -> 0 | GM97: =ROUND(O97+X97+Y97,2)+GX97 -> 640.06 | GN97: =IF(OR(BI97=0,BI97=1),GM97-GX97,0) -> 640.06 | GO97: =IF(BI97=2,GM97-GX97,0) -> 0 | GP97: =IF(BI97=4,GM97-GX97,0) -> 0 | GR97: 0 | GS97: 3 | GT97: 0 | GV97: =ROUND((GT97),6) -> 0 | GW97: 1 | GX97: =ROUND(HC97*I97,2) -> 0 | HA97: 0 | HB97: 0 | HC97: =GV97*GW97 -> 0 | HS97: 0 | IK97: 0
A98: 17 | B98: 1 | C98: =ROW(SmtRes!A172) -> 172 | D98: =ROW(EtalonRes!A196) -> 196 | E98: 13 | F98: 3.16-7-3 | G98: Прокладка трубопроводов водоснабжения из стальных водогазопроводных оцинкованных труб диаметром 25 мм | H98: 100 м трубопровода | I98: =ROUND((35)/100,9) -> 0.35 | J98: 0 | K98: =ROUND((35)/100,9) -> 0.35 | O98: =ROUND(CP98,2) -> 12883.64 | P98: =ROUND((ROUND((AC98*AW98*I98),2)*BC98),2) -> 99.07 | Q98: =(ROUND((ROUND(((((ET98*1.25)*1.2))*AV98*I98),2)*BB98),2)+ROUND((ROUND(((AE98-(((EU98*1.25)*1.2)))*AV98*I98),2)*BS98),2)) -> 433.78 | R98: =(ROUND((ROUND(((((EU98*1.25)*1.2))*AV98*I98),2)*BS98),2)+ROUND((ROUND(((AE98-(((EU98*1.25)*1.2)))*AV98*I98),2)*BS98),2)) -> 191.03 | S98: =ROUND((ROUND((AF98*AV98*I98),2)*BA98),2) -> 12350.79 | T98: =ROUND(CU98*I98,2) -> 0 | U98: =CV98*I98 -> 17.367666 | V98: =CW98*I98 -> 0 | W98: =ROUND(CX98*I98,2) -> 0 | X98: =(ROUND((((S98+ROUND((ROUND(((((EU98*1.25)*1.2))*AV98*I98),2)*BS98),2))*AT98)/100),2)+ROUND(((ROUND((ROUND(((AE98-(((EU98*1.25)*1.2)))*AV98*I98),2)*BS98),2)*AT98)/100),2)) -> 13670.58 | Y98: =(ROUND((((S98+ROUND((ROUND(((((EU98*1.25)*1.2))*AV98*I98),2)*BS98),2))*AU98)/100),2)+ROUND(((ROUND((ROUND(((AE98-(((EU98*1.25)*1.2)))*AV98*I98),2)*BS98),2)*AU98)/100),2)) -> 7650.51 | AA98: 85736473 | AB98: =ROUND((AC98+AD98+AF98),6) -> 703.5552 | AC98: =ROUND((((ES98*1)*1)),6) -> 45 | AD98: =ROUND((((((ET98*1.25)*1.2))-(((EU98*1.25)*1.2)))+AE98),6) -> 71.655 | AE98: =ROUND((((EU98*1.25)*1.2)),6) -> 9.09 | AF98: =ROUND((((EV98*1.15)*1.2)),6) -> 586.9002 | AG98: =ROUND((AP98),6) -> 0 | AH98: =(((EW98*1.15)*1.2)) -> 46.506 | AI98: =(((EX98*1.25)*1.2)) -> 0 | AJ98: =(AS98) -> 0 | AK98: 518.06 | AL98: 45 | AM98: 47.77 | AN98: 6.06 | AO98: 425.29 | AP98: 0 | AQ98: 33.7 | AR98: 0 | AS98: 0 | AT98: 109 | AU98: 61 | AV98: 1.067 | AW98: 1 | AZ98: 1 | BA98: 56.35 | BB98: 16.21 | BC98: 6.29 | BH98: 0 | BI98: 1 | BJ98: ТСН-2001.3 Доп. 79, Сб. 16, т. 7, поз. 3 | BM98: 21 | BN98: 0 | BO98: 3.16-7-3 | BP98: 1 | BQ98: 30 | BR98: 0 | BS98: 56.35 | BT98: 1 | BU98: 1 | BV98: 1 | BW98: 1 | BX98: 1 | BZ98: 109 | CA98: 61 | CE98: 1566 | CF98: 0 | CG98: 0 | CM98: 0 | CN98: Поправка: Гл.6.Прил.2.2.п.2.2.6_06.00.01.07.001 Наименование: При выполнении при капитальном ремонте и реконструкции работ, аналогичных технологическим процессам, характерным для нового строительства, и отсутствующих в сборниках на ремонтно-строительные работы ТСН-2001.6 Поправка: Гл.12.Прил.8.п.8. 3_12.00.01.11.001 Наименование: При наличии напряженных и стесненных условий производства работ (стесненность, сложность складирования и транспортной логистики и т.п.) для объектов, расположенных в пределах круговой магистральной системы улиц "Садовое кольцо" города Москвы | CO98: 0 | CP98: =(P98+Q98+S98) -> 12883.64 | CQ98: =ROUND((ROUND((AC98*AW98*1),2)*BC98),2) -> 283.05 | CR98: =(ROUND((ROUND(((((ET98*1.25)*1.2))*AV98*1),2)*BB98),2)+ROUND((ROUND(((AE98-(((EU98*1.25)*1.2)))*AV98*1),2)*BS98),2)) -> 1239.42 | CS98: =(ROUND((ROUND(((((EU98*1.25)*1.2))*AV98*1),2)*BS98),2)+ROUND((ROUND(((AE98-(((EU98*1.25)*1.2)))*AV98*1),2)*BS98),2)) -> 546.6 | CT98: =ROUND((ROUND((AF98*AV98*1),2)*BA98),2) -> 35287.5 | CU98: =AG98 -> 0 | CV98: =(AH98*AV98) -> 49.621902 | CW98: =AI98 -> 0 | CX98: =AJ98 -> 0 | CY98: =(ROUND((((S98+ROUND((ROUND(((((EU98*1.25)*1.2))*AV98*1),2)*BS98),2))*AT98)/100),2)+ROUND(((ROUND((ROUND(((AE98-(((EU98*1.25)*1.2)))*AV98*1),2)*BS98),2)*AT98)/100),2)) -> 14058.16 | CZ98: =(ROUND((((S98+ROUND((ROUND(((((EU98*1.25)*1.2))*AV98*1),2)*BS98),2))*AU98)/100),2)+ROUND(((ROUND((ROUND(((AE98-(((EU98*1.25)*1.2)))*AV98*1),2)*BS98),2)*AU98)/100),2)) -> 7867.41 | DB98: 37 | DD98: *1)*1 | DE98: *1,25)*1,2 | DF98: *1,25)*1,2 | DG98: *1,15)*1,2 | DI98: *1,15)*1,2 | DJ98: *1,25)*1,2 | DN98: 0 | DO98: 0 | DP98: 1 | DQ98: 1 | DU98: 1013 | DV98: 100 м трубопровода | DW98: 100 м трубопровода | DX98: 1 | EE98: 85133641 | EF98: 30 | EG98: Строительные работы | EH98: 0 | EJ98: 1 | EK98: 21 | EL98: ТСН-2001.3-16. Трубопроводы внутренние | EM98: ТСН-2001.3-16-1 | EO98: Поправка: Гл.6.Прил.2.2.п.2.2.6_06.00.01.07.001 Поправка: Гл.12.Прил.8.п.8. 3_12.00.01.11.001 | EQ98: 0 | ER98: 518.06 | ES98: 45 | ET98: 47.77 | EU98: 6.06 | EV98: 425.29 | EW98: 33.7 | EX98: 0 | EY98: 0 | FQ98: 0 | FR98: 0 | FS98: 0 | FX98: 109 | FY98: 61 | GD98: 1 | GF98: 124743446 | GG98: 2 | GH98: 1 | GI98: 2 | GJ98: 0 | GK98: 0 | GL98: =ROUND(IF(AND(BH98=3,BI98=3,FS98<>0),P98,0),2) -> 0 | GM98: =ROUND(O98+X98+Y98,2)+GX98 -> 34204.73 | GN98: =IF(OR(BI98=0,BI98=1),GM98-GX98,0) -> 34204.73 | GO98: =IF(BI98=2,GM98-GX98,0) -> 0 | GP98: =IF(BI98=4,GM98-GX98,0) -> 0 | GR98: 0 | GS98: 3 | GT98: 0 | GV98: =ROUND((GT98),6) -> 0 | GW98: 1 | GX98: =ROUND(HC98*I98,2) -> 0 | HA98: 0 | HB98: 0 | HC98: =GV98*GW98 -> 0 | HS98: 0 | IK98: 0
A99: 18 | B99: 1 | C99: 158 | E99: 13,1 | F99: 1.13-4-63 | G99: Кран шаровой, латунный, никелированный, полнопроходной, с алюминиевой рукояткой, муфтовый, температура рабочей среды от -15 до +110°С, номинальное давление PN 4,0 МПа, номинальный диаметр DN 25 мм | H99: шт. | I99: =I97*J99 -> 4 | J99: 11.428571 | K99: 11.428571 | O99: =ROUND(CP99,2) -> 297.44 | P99: =ROUND((ROUND((AC99*AW99*I99),2)*BC99),2) -> 297.44 | Q99: =(ROUND((ROUND(((ET99)*AV99*I99),2)*BB99),2)+ROUND((ROUND(((AE99-(EU99))*AV99*I99),2)*BS99),2)) -> 0 | R99: =(ROUND((ROUND(((EU99)*AV99*I99),2)*BS99),2)+ROUND((ROUND(((AE99-(EU99))*AV99*I99),2)*BS99),2)) -> 0 | S99: =ROUND((ROUND((AF99*AV99*I99),2)*BA99),2) -> 0 | T99: =ROUND(CU99*I99,2) -> 0 | U99: =CV99*I99 -> 0 | V99: =CW99*I99 -> 0 | W99: =ROUND(CX99*I99,2) -> 0 | X99: =(ROUND((((S99+ROUND((ROUND(((EU99)*AV99*I99),2)*BS99),2))*AT99)/100),2)+ROUND(((ROUND((ROUND(((AE99-(EU99))*AV99*I99),2)*BS99),2)*AT99)/100),2)) -> 0 | Y99: =(ROUND((((S99+ROUND((ROUND(((EU99)*AV99*I99),2)*BS99),2))*AU99)/100),2)+ROUND(((ROUND((ROUND(((AE99-(EU99))*AV99*I99),2)*BS99),2)*AU99)/100),2)) -> 0 | AA99: 85736471 | AB99: =ROUND((AC99+AD99+AF99),6) -> 74.36 | AC99: =ROUND((ES99),6) -> 74.36 | AD99: =ROUND((((ET99)-(EU99))+AE99),6) -> 0 | AE99: =ROUND((EU99),6) -> 0 | AF99: =ROUND((EV99),6) -> 0 | AG99: =ROUND((AP99),6) -> 0 | AH99: =(EW99) -> 0 | AI99: =(EX99) -> 0 | AJ99: =(AS99) -> 0 | AK99: 74.36 | AL99: 74.36 | AM99: 0 | AN99: 0 | AO99: 0 | AP99: 0 | AQ99: 0 | AR99: 0 | AS99: 0 | AT99: 109 | AU99: 61 | AV99: 1 | AW99: 1 | AZ99: 1 | BA99: 1 | BB99: 1 | BC99: 1 | BH99: 3 | BI99: 1 | BJ99: ТСН-2001.1 Доп. 79, Р. 13, о. 4, поз. 63 | BM99: 21 | BN99: 0 | BP99: 0 | BQ99: 30 | BR99: 0 | BS99: 1 | BT99: 1 | BU99: 1 | BV99: 1 | BW99: 1 | BX99: 1 | BZ99: 109 | CA99: 61 | CE99: 1566 | CF99: 0 | CG99: 0 | CM99: 0 | CN99: Поправка: Гл.6.Прил.2.2.п.2.2.6_06.00.01.07.001_x000D_ Наименование: При выполнении при капитальном ремонте и реконструкции работ, аналогичных технологическим процессам, характерным для нового строительства, и отсутствующих в сборниках на ремонтно-строительные работы ТСН-2001.6_x000D_ Поправка: Гл.12.Прил.8.п.8. 3_12.00.01.11.001_x000D_ Наименование: При наличии напряженных и стесненных условий производства работ (стесненность, сложность складирования и транспортной логистики и т.п.) для объектов, расположенных в пределах круговой магистральной системы улиц "Садовое кольцо" города Москвы | CO99: 0 | CP99: =(P99+Q99+S99) -> 297.44 | CQ99: =ROUND((ROUND((AC99*AW99*1),2)*BC99),2) -> 74.36 | CR99: =(ROUND((ROUND(((ET99)*AV99*1),2)*BB99),2)+ROUND((ROUND(((AE99-(EU99))*AV99*1),2)*BS99),2)) -> 0 | CS99: =(ROUND((ROUND(((EU99)*AV99*1),2)*BS99),2)+ROUND((ROUND(((AE99-(EU99))*AV99*1),2)*BS99),2)) -> 0 | CT99: =ROUND((ROUND((AF99*AV99*1),2)*BA99),2) -> 0 | CU99: =AG99 -> 0 | CV99: =(AH99*AV99) -> 0 | CW99: =AI99 -> 0 | CX99: =AJ99 -> 0 | CY99: =(ROUND((((S99+ROUND((ROUND(((EU99)*AV99*1),2)*BS99),2))*AT99)/100),2)+ROUND(((ROUND((ROUND(((AE99-(EU99))*AV99*1),2)*BS99),2)*AT99)/100),2)) -> 0 | CZ99: =(ROUND((((S99+ROUND((ROUND(((EU99)*AV99*1),2)*BS99),2))*AU99)/100),2)+ROUND(((ROUND((ROUND(((AE99-(EU99))*AV99*1),2)*BS99),2)*AU99)/100),2)) -> 0 | DN99: 0 | DO99: 0 | DP99: 1 | DQ99: 1 | DU99: 1010 | DV99: шт. | DW99: шт. | DX99: 1 | EE99: 85133641 | EF99: 30 | EG99: Строительные работы | EH99: 0 | EJ99: 1 | EK99: 21 | EL99: ТСН-2001.3-16. Трубопроводы внутренние | EM99: ТСН-2001.3-16-1 | EO99: Поправка: Гл.6.Прил.2.2.п.2.2.6_06.00.01.07.001_x000D_ Поправка: Гл.12.Прил.8.п.8. 3_12.00.01.11.001 | EQ99: 0 | ER99: 74.36 | ES99: 74.36 | ET99: 0 | EU99: 0 | EV99: 0 | EW99: 0 | EX99: 0 | FQ99: 0 | FR99: 0 | FS99: 0 | FX99: 109 | FY99: 61 | GD99: 1 | GF99: -254914390 | GG99: 2 | GH99: 1 | GI99: -2 | GJ99: 0 | GK99: 0 | GL99: =ROUND(IF(AND(BH99=3,BI99=3,FS99<>0),P99,0),2) -> 0 | GM99: =ROUND(O99+X99+Y99,2)+GX99 -> 297.44 | GN99: =IF(OR(BI99=0,BI99=1),GM99-GX99,0) -> 297.44 | GO99: =IF(BI99=2,GM99-GX99,0) -> 0 | GP99: =IF(BI99=4,GM99-GX99,0) -> 0 | GR99: 0 | GS99: 3 | GT99: 0 | GV99: =ROUND((GT99),6) -> 0 | GW99: 1 | GX99: =ROUND(HC99*I99,2) -> 0 | HA99: 0 | HB99: 0 | HC99: =GV99*GW99 -> 0 | HM99: *1)*1 | HS99: 0 | IK99: 0
A100: 18 | B100: 1 | C100: 172 | E100: 13,1 | F100: 1.13-4-63 | G100: Кран шаровой, латунный, никелированный, полнопроходной, с алюминиевой рукояткой, муфтовый, температура рабочей среды от -15 до +110°С, номинальное давление PN 4,0 МПа, номинальный диаметр DN 25 мм | H100: шт. | I100: =I98*J100 -> 4 | J100: 11.428571 | K100: 11.428571 | O100: =ROUND(CP100,2) -> 5850.64 | P100: =ROUND((ROUND((AC100*AW100*I100),2)*BC100),2) -> 5850.64 | Q100: =(ROUND((ROUND(((ET100)*AV100*I100),2)*BB100),2)+ROUND((ROUND(((AE100-(EU100))*AV100*I100),2)*BS100),2)) -> 0 | R100: =(ROUND((ROUND(((EU100)*AV100*I100),2)*BS100),2)+ROUND((ROUND(((AE100-(EU100))*AV100*I100),2)*BS100),2)) -> 0 | S100: =ROUND((ROUND((AF100*AV100*I100),2)*BA100),2) -> 0 | T100: =ROUND(CU100*I100,2) -> 0 | U100: =CV100*I100 -> 0 | V100: =CW100*I100 -> 0 | W100: =ROUND(CX100*I100,2) -> 0 | X100: =(ROUND((((S100+ROUND((ROUND(((EU100)*AV100*I100),2)*BS100),2))*AT100)/100),2)+ROUND(((ROUND((ROUND(((AE100-(EU100))*AV100*I100),2)*BS100),2)*AT100)/100),2)) -> 0 | Y100: =(ROUND((((S100+ROUND((ROUND(((EU100)*AV100*I100),2)*BS100),2))*AU100)/100),2)+ROUND(((ROUND((ROUND(((AE100-(EU100))*AV100*I100),2)*BS100),2)*AU100)/100),2)) -> 0 | AA100: 85736473 | AB100: =ROUND((AC100+AD100+AF100),6) -> 74.36 | AC100: =ROUND((ES100),6) -> 74.36 | AD100: =ROUND((((ET100)-(EU100))+AE100),6) -> 0 | AE100: =ROUND((EU100),6) -> 0 | AF100: =ROUND((EV100),6) -> 0 | AG100: =ROUND((AP100),6) -> 0 | AH100: =(EW100) -> 0 | AI100: =(EX100) -> 0 | AJ100: =(AS100) -> 0 | AK100: 74.36 | AL100: 74.36 | AM100: 0 | AN100: 0 | AO100: 0 | AP100: 0 | AQ100: 0 | AR100: 0 | AS100: 0 | AT100: 109 | AU100: 61 | AV100: 1 | AW100: 1 | AZ100: 1 | BA100: 1 | BB100: 1 | BC100: 19.67 | BH100: 3 | BI100: 1 | BJ100: ТСН-2001.1 Доп. 79, Р. 13, о. 4, поз. 63 | BM100: 21 | BN100: 0 | BO100: 1.13-4-63 | BP100: 1 | BQ100: 30 | BR100: 0 | BS100: 1 | BT100: 1 | BU100: 1 | BV100: 1 | BW100: 1 | BX100: 1 | BZ100: 109 | CA100: 61 | CE100: 1566 | CF100: 0 | CG100: 0 | CM100: 0 | CN100: Поправка: Гл.6.Прил.2.2.п.2.2.6_06.00.01.07.001_x000D_ Наименование: При выполнении при капитальном ремонте и реконструкции работ, аналогичных технологическим процессам, характерным для нового строительства, и отсутствующих в сборниках на ремонтно-строительные работы ТСН-2001.6_x000D_ Поправка: Гл.12.Прил.8.п.8. 3_12.00.01.11.001_x000D_ Наименование: При наличии напряженных и стесненных условий производства работ (стесненность, сложность складирования и транспортной логистики и т.п.) для объектов, расположенных в пределах круговой магистральной системы улиц "Садовое кольцо" города Москвы | CO100: 0 | CP100: =(P100+Q100+S100) -> 5850.64 | CQ100: =ROUND((ROUND((AC100*AW100*1),2)*BC100),2) -> 1462.66 | CR100: =(ROUND((ROUND(((ET100)*AV100*1),2)*BB100),2)+ROUND((ROUND(((AE100-(EU100))*AV100*1),2)*BS100),2)) -> 0 | CS100: =(ROUND((ROUND(((EU100)*AV100*1),2)*BS100),2)+ROUND((ROUND(((AE100-(EU100))*AV100*1),2)*BS100),2)) -> 0 | CT100: =ROUND((ROUND((AF100*AV100*1),2)*BA100),2) -> 0 | CU100: =AG100 -> 0 | CV100: =(AH100*AV100) -> 0 | CW100: =AI100 -> 0 | CX100: =AJ100 -> 0 | CY100: =(ROUND((((S100+ROUND((ROUND(((EU100)*AV100*1),2)*BS100),2))*AT100)/100),2)+ROUND(((ROUND((ROUND(((AE100-(EU100))*AV100*1),2)*BS100),2)*AT100)/100),2)) -> 0 | CZ100: =(ROUND((((S100+ROUND((ROUND(((EU100)*AV100*1),2)*BS100),2))*AU100)/100),2)+ROUND(((ROUND((ROUND(((AE100-(EU100))*AV100*1),2)*BS100),2)*AU100)/100),2)) -> 0 | DN100: 0 | DO100: 0 | DP100: 1 | DQ100: 1 | DU100: 1010 | DV100: шт. | DW100: шт. | DX100: 1 | EE100: 85133641 | EF100: 30 | EG100: Строительные работы | EH100: 0 | EJ100: 1 | EK100: 21 | EL100: ТСН-2001.3-16. Трубопроводы внутренние | EM100: ТСН-2001.3-16-1 | EO100: Поправка: Гл.6.Прил.2.2.п.2.2.6_06.00.01.07.001_x000D_ Поправка: Гл.12.Прил.8.п.8. 3_12.00.01.11.001 | EQ100: 0 | ER100: 74.36 | ES100: 74.36 | ET100: 0 | EU100: 0 | EV100: 0 | EW100: 0 | EX100: 0 | FQ100: 0 | FR100: 0 | FS100: 0 | FX100: 109 | FY100: 61 | GD100: 1 | GF100: -254914390 | GG100: 2 | GH100: 1 | GI100: 2 | GJ100: 0 | GK100: 0 | GL100: =ROUND(IF(AND(BH100=3,BI100=3,FS100<>0),P100,0),2) -> 0 | GM100: =ROUND(O100+X100+Y100,2)+GX100 -> 5850.64 | GN100: =IF(OR(BI100=0,BI100=1),GM100-GX100,0) -> 5850.64 | GO100: =IF(BI100=2,GM100-GX100,0) -> 0 | GP100: =IF(BI100=4,GM100-GX100,0) -> 0 | GR100: 0 | GS100: 3 | GT100: 0 | GV100: =ROUND((GT100),6) -> 0 | GW100: 1 | GX100: =ROUND(HC100*I100,2) -> 0 | HA100: 0 | HB100: 0 | HC100: =GV100*GW100 -> 0 | HM100: *1)*1 | HS100: 0 | IK100: 0
