Workbook

Sheet Смета по ТСН-2001(с доп.67
A1: =Source!B1 -> Smeta.RU (495) 974-1589
J2: Форма № 4б
A3: Капитальный ремонт здания Государственного бюджетного общеобразовательного учреждения города Москвы «Школа №1574» по адресу: г. Москва, Старопименовский пер., д. №5. | AP3: Капитальный ремонт здания Государственного бюджетного общеобразовательного учреждения города Москвы «Школа №1574» по адресу: г. Москва, Старопименовский пер., д. №5. 02-01-07 Вентиляция и кондиционирование воздуха
A4: (наименование стройки и/или объекта)
A6: =CONCATENATE( "ЛОКАЛЬНАЯ СМЕТА № ",IF(Source!F12<>"Новый объект", Source!F12, "")) -> ЛОКАЛЬНАЯ СМЕТА № 02-01-07
A8: Вентиляция и кондиционирование воздуха
A9: (наименование работ и затрат)
A11: =CONCATENATE( "Основание: чертежи № ", Source!J12) -> Основание: чертежи № 2024-00375-01-0-ИОС4.2
I13: В базисном уровне цен | J13: В текущем уровне цен
E14: Сметная стоимость | I14: =I15+I16+I17+I18 -> 5753.96 | J14: =J15+J16+J17+J18 -> 53075.77 | K14: тыс.руб.
E15: Строительные работы | I15: =ROUND((Source!F1553)/1000, 2) -> 1985.27 | J15: =ROUND((Source!P1553)/1000, 2) -> 24368.16 | K15: тыс.руб.
E16: Работы по монтажу оборудования | I16: =ROUND((Source!F1554)/1000, 2) -> 0.44 | J16: =ROUND((Source!P1554)/1000, 2) -> 23.73 | K16: тыс.руб.
E17: Оборудование | I17: =ROUND((Source!F1545)/1000, 2) -> 3768.25 | J17: =ROUND((Source!P1545)/1000, 2) -> 28683.88 | K17: тыс.руб.
E18: Прочие работы и затраты | I18: =ROUND((Source!F1555+Source!F1556)/1000, 2) -> 0 | J18: =ROUND((Source!P1555+Source!P1556)/1000, 2) -> 0 | K18: тыс.руб.
E19: Средства на оплату труда | I19: =(Source!F1551+ Source!F1550)/1000 -> 94.58857 | J19: =((Source!P1551 + Source!P1550)/1000) -> 5330.0659 | K19: тыс.руб.
E20: Затраты труда | I20: =Source!F1558 -> 7684.5827 | K20: чел.-ч.
E21: Кроме того:
E22: Возврат материалов | I22: =SUM(Y1:Y1692)/1000 -> 0 | J22: =SUM(Z1:Z1692)/1000 -> 0 | K22: тыс.руб.
A24: Составлен(а) по ТСН-2001 с учетом Дополнения №: 81
A25: № и период сборника коэффициентов (индексов) пересчета: Коэффициенты к ТСН-2001 МГЭ Дополнение 81, ремонт №219/81 I квартал 2026 года и Коэффициенты к ТСН-2001.13-2 Дополнение 47 №64/47 I квартал 2026 года | AP25: № и период сборника коэффициентов (индексов) пересчета: Коэффициенты к ТСН-2001 МГЭ Дополнение 81, ремонт №219/81 I квартал 2026 года и Коэффициенты к ТСН-2001.13-2 Дополнение 47 №64/47 I квартал 2026 года
A26: № п/п | B26: Шифр расценки и коды ресурсов | C26: Наименование работ и затрат | D26: Ед. изм. | E26: Кол-во единиц | F26: Цена на ед. изм., руб. | G26: Попра- вочные коэффи- циенты | H26: Коэффи- циенты зимних удорожа- ний | I26: Всего в ценах на январь 2000 года, руб. | J26: Коэффи- циенты (индек- сы) пере- счета, нормы НР и СП | K26: ВСЕГО затрат в текущем уровне цен, руб.
A27: 1 | B27: 2 | C27: 3 | D27: 4 | E27: 5 | F27: 6 | G27: 7 | H27: 8 | I27: 9 | J27: 10 | K27: 11
A29: =CONCATENATE("Локальная смета: ",IF(Source!G20<>"Новая локальная смета", Source!G20, "")) -> Локальная смета: Вентиляция и кондиционирование воздуха
A31: =CONCATENATE("Раздел: ",IF(Source!G24<>"Новый раздел", Source!G24, "")) -> Раздел: Вентиляция
A33: =CONCATENATE("Подраздел: ",IF(Source!G28<>"Новый подраздел", Source!G28, "")) -> Подраздел: Приточные установки
A34: 1 | B34: =Source!F32 -> 3.20-40-1 | C34: Установка камер приточных типовых без секции орошения и установок приточных производительностью до 10 тыс.м3/час | D34: =Source!H32 -> 1 КАМЕРА | E34: =Source!I32 -> 16 | Q34: =Source!X32 -> 13217.43 | R34: =Source!X33 -> 744802.02 | S34: =Source!Y32 -> 7396.91 | T34: =Source!Y33 -> 416815.81 | U34: =ROUND((175/100)*ROUND(Source!R32, 2), 2) -> 337.38 | V34: =ROUND((0/100)*ROUND(Source!R33, 2), 2) -> 0 | AC34: 0
C35: ЗП | F35: =Source!AO32 -> 482.4 | G35: 1,2*1,15*1,05 | H35: =Source!AV33 -> 1.067 | I35: =Source!S32 -> 11933.29 | J35: =IF(Source!BA33<> 0, Source!BA33, 1) -> 56.35 | K35: =Source!S33 -> 672440.89
C36: ЭМ | F36: =Source!AM32 -> 71.07 | G36: 1,2*1,25*1,05 | H36: =Source!AV33 -> 1.067 | I36: =Source!Q32 -> 1910.96 | J36: =IF(Source!BB33<> 0, Source!BB33, 1) -> 15.22 | K36: =Source!Q33 -> 29084.81
C37: в т.ч. ЗПМ | F37: =Source!AN32 -> 7.17 | G37: 1,2*1,25*1,05 | H37: =Source!AV33 -> 1.067 | I37: =Source!R32 -> 192.79 | J37: =IF(Source!BS33<> 0, Source!BS33, 1) -> 56.35 | K37: =Source!R33 -> 10863.72
C38: МР | F38: =Source!AL32 -> 223.41 | H38: =Source!AW33 -> 1 | I38: =Source!P32 -> 3574.56 | J38: =IF(Source!BC33<> 0, Source!BC33, 1) -> 9.16 | K38: =Source!P33 -> 32742.97
C39: НР от ФОТ | D39: % | E39: =Source!BZ33 -> 109 | I39: =SUM(Q34:Q38) -> 13217.43 | J39: =Source!AT33 -> 109 | K39: =SUM(R34:R38) -> 744802.02
C40: СП от ФОТ | D40: % | E40: =Source!CA33 -> 61 | I40: =SUM(S34:S39) -> 7396.91 | J40: =Source!AU33 -> 61 | K40: =SUM(T34:T39) -> 416815.81
C41: ЗТР | D41: чел-ч | E41: =Source!AQ32 -> 40.1 | G41: 1,2*1,15*1,05 | H41: =Source!AV33 -> 1.067 | I41: =Source!U32 -> 991.96685
C42: ВСЕГО работ по позиции: | H42: =I35+I36+I38+I39+I40+0-0-0 -> 38033.15 | J42: =K35+K36+K38+K39+K40+0-0-0 -> 1895886.5
C43: ВСЕГО оборудование по позиции: | H43: =0+0 -> 0 | J43: =0+0 -> 0
C44: ВСЕГО по позиции: | H44: =I35+I36+I38+I39+I40+0 -> 38033.15 | J44: =K35+K36+K38+K39+K40+0 -> 1895886.5 | O44: =I35+I36+I38+I39+I40+0 -> 38033.15 | P44: =K35+K36+K38+K39+K40+0 -> 1895886.5
A46: 2 | B46: =Source!F34 -> КА, п.1 | C46: ОБОРУДОВАНИЕ:_x000D_ Приточная установка П1 (L=1890 м3/ч, Pc=500 Па) 38 705,03 = [342 930 / 1,22 / 7,57] + 3% Трансп + 1,2% Заг.скл | D46: =Source!H34 -> ШТ | E46: =Source!I34 -> 1 | F46: =Source!AL34 -> 38705.03 | H46: =Source!AW35 -> 1 | I46: =Source!P34 -> 38705.03 | J46: =IF(Source!BC35<> 0, Source!BC35, 1) -> 7.57 | K46: =Source!P35 -> 292997.08 | Q46: =Source!X34 -> 0 | R46: =Source!X35 -> 0 | S46: =Source!Y34 -> 0 | T46: =Source!Y35 -> 0 | U46: =ROUND((175/100)*ROUND(Source!R34, 2), 2) -> 0 | V46: =ROUND((0/100)*ROUND(Source!R35, 2), 2) -> 0 | AC46: 5
C47: ВСЕГО по позиции: | H47: =I46+0 -> 38705.03 | J47: =K46+0 -> 292997.08 | O47: =I46+0 -> 38705.03 | P47: =K46+0 -> 292997.08
A49: 3 | B49: =Source!F36 -> КА, п.3 | C49: ОБОРУДОВАНИЕ:_x000D_ Приточная установка П2 (L=3600 м3/ч, Pc=500 Па) 45 981,50 = [407 400 / 1,22 / 7,57] + 3% Трансп + 1,2% Заг.скл | D49: =Source!H36 -> ШТ | E49: =Source!I36 -> 1 | F49: =Source!AL36 -> 45981.5 | H49: =Source!AW37 -> 1 | I49: =Source!P36 -> 45981.5 | J49: =IF(Source!BC37<> 0, Source!BC37, 1) -> 7.57 | K49: =Source!P37 -> 348079.96 | Q49: =Source!X36 -> 0 | R49: =Source!X37 -> 0 | S49: =Source!Y36 -> 0 | T49: =Source!Y37 -> 0 | U49: =ROUND((175/100)*ROUND(Source!R36, 2), 2) -> 0 | V49: =ROUND((0/100)*ROUND(Source!R37, 2), 2) -> 0 | AC49: 5
C50: ВСЕГО по позиции: | H50: =I49+0 -> 45981.5 | J50: =K49+0 -> 348079.96 | O50: =I49+0 -> 45981.5 | P50: =K49+0 -> 348079.96
A52: 4 | B52: =Source!F38 -> КА, п.5 | C52: ОБОРУДОВАНИЕ:_x000D_ Приточная установка П3 (L=700 м3/ч, Pc=400 Па) 64 350,39 = [570 150 / 1,22 / 7,57] + 3% Трансп + 1,2% Заг.скл | D52: =Source!H38 -> ШТ | E52: =Source!I38 -> 1 | F52: =Source!AL38 -> 64350.39 | H52: =Source!AW39 -> 1 | I52: =Source!P38 -> 64350.39 | J52: =IF(Source!BC39<> 0, Source!BC39, 1) -> 7.57 | K52: =Source!P39 -> 487132.45 | Q52: =Source!X38 -> 0 | R52: =Source!X39 -> 0 | S52: =Source!Y38 -> 0 | T52: =Source!Y39 -> 0 | U52: =ROUND((175/100)*ROUND(Source!R38, 2), 2) -> 0 | V52: =ROUND((0/100)*ROUND(Source!R39, 2), 2) -> 0 | AC52: 5
C53: ВСЕГО по позиции: | H53: =I52+0 -> 64350.39 | J53: =K52+0 -> 487132.45 | O53: =I52+0 -> 64350.39 | P53: =K52+0 -> 487132.45
A55: 5 | B55: =Source!F40 -> КА, п.7 | C55: ОБОРУДОВАНИЕ:_x000D_ Приточная установка П4 (L=4970 м3/ч, Pc=500 Па) 59 491,52 = [527 100 / 1,22 / 7,57] + 3% Трансп + 1,2% Заг.скл | D55: =Source!H40 -> ШТ | E55: =Source!I40 -> 1 | F55: =Source!AL40 -> 59491.52 | H55: =Source!AW41 -> 1 | I55: =Source!P40 -> 59491.52 | J55: =IF(Source!BC41<> 0, Source!BC41, 1) -> 7.57 | K55: =Source!P41 -> 450350.81 | Q55: =Source!X40 -> 0 | R55: =Source!X41 -> 0 | S55: =Source!Y40 -> 0 | T55: =Source!Y41 -> 0 | U55: =ROUND((175/100)*ROUND(Source!R40, 2), 2) -> 0 | V55: =ROUND((0/100)*ROUND(Source!R41, 2), 2) -> 0 | AC55: 5
C56: ВСЕГО по позиции: | H56: =I55+0 -> 59491.52 | J56: =K55+0 -> 450350.81 | O56: =I55+0 -> 59491.52 | P56: =K55+0 -> 450350.81
A58: 6 | B58: =Source!F42 -> КА, п.8 | C58: ОБОРУДОВАНИЕ:_x000D_ Приточная установка П5 (L=8010 м3/ч, Pc=700 Па) 143 952,88 = [1 275 435 / 1,22 / 7,57] + 3% Трансп + 1,2% Заг.скл | D58: =Source!H42 -> ШТ | E58: =Source!I42 -> 1 | F58: =Source!AL42 -> 143952.88 | H58: =Source!AW43 -> 1 | I58: =Source!P42 -> 143952.88 | J58: =IF(Source!BC43<> 0, Source!BC43, 1) -> 7.57 | K58: =Source!P43 -> 1089723.3 | Q58: =Source!X42 -> 0 | R58: =Source!X43 -> 0 | S58: =Source!Y42 -> 0 | T58: =Source!Y43 -> 0 | U58: =ROUND((175/100)*ROUND(Source!R42, 2), 2) -> 0 | V58: =ROUND((0/100)*ROUND(Source!R43, 2), 2) -> 0 | AC58: 5
C59: ВСЕГО по позиции: | H59: =I58+0 -> 143952.88 | J59: =K58+0 -> 1089723.3 | O59: =I58+0 -> 143952.88 | P59: =K58+0 -> 1089723.3
A61: 7 | B61: =Source!F44 -> КА, п.10 | C61: ОБОРУДОВАНИЕ:_x000D_ Приточная установка П6 (L=620 м3/ч, Pc=400 Па) 31 120,46 = [275 730 / 1,22 / 7,57] + 3% Трансп + 1,2% Заг.скл | D61: =Source!H44 -> ШТ | E61: =Source!I44 -> 1 | F61: =Source!AL44 -> 31120.46 | H61: =Source!AW45 -> 1 | I61: =Source!P44 -> 31120.46 | J61: =IF(Source!BC45<> 0, Source!BC45, 1) -> 7.57 | K61: =Source!P45 -> 235581.88 | Q61: =Source!X44 -> 0 | R61: =Source!X45 -> 0 | S61: =Source!Y44 -> 0 | T61: =Source!Y45 -> 0 | U61: =ROUND((175/100)*ROUND(Source!R44, 2), 2) -> 0 | V61: =ROUND((0/100)*ROUND(Source!R45, 2), 2) -> 0 | AC61: 5
C62: ВСЕГО по позиции: | H62: =I61+0 -> 31120.46 | J62: =K61+0 -> 235581.88 | O62: =I61+0 -> 31120.46 | P62: =K61+0 -> 235581.88
A64: 8 | B64: =Source!F46 -> КА, п.11 | C64: ОБОРУДОВАНИЕ:_x000D_ Приточная установка П7 (L=110 м3/ч, Pc=300 Па) 10 701,35 = [94 815 / 1,22 / 7,57] + 3% Трансп + 1,2% Заг.скл | D64: =Source!H46 -> ШТ | E64: =Source!I46 -> 1 | F64: =Source!AL46 -> 10701.35 | H64: =Source!AW47 -> 1 | I64: =Source!P46 -> 10701.35 | J64: =IF(Source!BC47<> 0, Source!BC47, 1) -> 7.57 | K64: =Source!P47 -> 81009.22 | Q64: =Source!X46 -> 0 | R64: =Source!X47 -> 0 | S64: =Source!Y46 -> 0 | T64: =Source!Y47 -> 0 | U64: =ROUND((175/100)*ROUND(Source!R46, 2), 2) -> 0 | V64: =ROUND((0/100)*ROUND(Source!R47, 2), 2) -> 0 | AC64: 5
C65: ВСЕГО по позиции: | H65: =I64+0 -> 10701.35 | J65: =K64+0 -> 81009.22 | O65: =I64+0 -> 10701.35 | P65: =K64+0 -> 81009.22
A67: 9 | B67: =Source!F48 -> КА, п.12 | C67: ОБОРУДОВАНИЕ:_x000D_ Приточная установка П8 (L=1540 м3/ч, Pc=400 Па) 34 249,11 = [303 450 / 1,22 / 7,57] + 3% Трансп + 1,2% Заг.скл | D67: =Source!H48 -> ШТ | E67: =Source!I48 -> 1 | F67: =Source!AL48 -> 34249.11 | H67: =Source!AW49 -> 1 | I67: =Source!P48 -> 34249.11 | J67: =IF(Source!BC49<> 0, Source!BC49, 1) -> 7.57 | K67: =Source!P49 -> 259265.76 | Q67: =Source!X48 -> 0 | R67: =Source!X49 -> 0 | S67: =Source!Y48 -> 0 | T67: =Source!Y49 -> 0 | U67: =ROUND((175/100)*ROUND(Source!R48, 2), 2) -> 0 | V67: =ROUND((0/100)*ROUND(Source!R49, 2), 2) -> 0 | AC67: 5
C68: ВСЕГО по позиции: | H68: =I67+0 -> 34249.11 | J68: =K67+0 -> 259265.76 | O68: =I67+0 -> 34249.11 | P68: =K67+0 -> 259265.76
A70: 10 | B70: =Source!F50 -> КА, п.14 | C70: ОБОРУДОВАНИЕ:_x000D_ Приточная установка П10 (L=4540 м3/ч, Pc=500 Па) 59 491,52 = [527 100 / 1,22 / 7,57] + 3% Трансп + 1,2% Заг.скл | D70: =Source!H50 -> ШТ | E70: =Source!I50 -> 1 | F70: =Source!AL50 -> 59491.52 | H70: =Source!AW51 -> 1 | I70: =Source!P50 -> 59491.52 | J70: =IF(Source!BC51<> 0, Source!BC51, 1) -> 7.57 | K70: =Source!P51 -> 450350.81 | Q70: =Source!X50 -> 0 | R70: =Source!X51 -> 0 | S70: =Source!Y50 -> 0 | T70: =Source!Y51 -> 0 | U70: =ROUND((175/100)*ROUND(Source!R50, 2), 2) -> 0 | V70: =ROUND((0/100)*ROUND(Source!R51, 2), 2) -> 0 | AC70: 5
C71: ВСЕГО по позиции: | H71: =I70+0 -> 59491.52 | J71: =K70+0 -> 450350.81 | O71: =I70+0 -> 59491.52 | P71: =K70+0 -> 450350.81
A73: 11 | B73: =Source!F52 -> КА, п.15 | C73: ОБОРУДОВАНИЕ:_x000D_ Приточная установка П11 (L=3800 м3/ч, Pc=700 Па) 57 476,86 = [509 250 / 1,22 / 7,57] + 3% Трансп + 1,2% Заг.скл | D73: =Source!H52 -> ШТ | E73: =Source!I52 -> 1 | F73: =Source!AL52 -> 57476.86 | H73: =Source!AW53 -> 1 | I73: =Source!P52 -> 57476.86 | J73: =IF(Source!BC53<> 0, Source!BC53, 1) -> 7.57 | K73: =Source!P53 -> 435099.83 | Q73: =Source!X52 -> 0 | R73: =Source!X53 -> 0 | S73: =Source!Y52 -> 0 | T73: =Source!Y53 -> 0 | U73: =ROUND((175/100)*ROUND(Source!R52, 2), 2) -> 0 | V73: =ROUND((0/100)*ROUND(Source!R53, 2), 2) -> 0 | AC73: 5
C74: ВСЕГО по позиции: | H74: =I73+0 -> 57476.86 | J74: =K73+0 -> 435099.83 | O74: =I73+0 -> 57476.86 | P74: =K73+0 -> 435099.83
A76: 12 | B76: =Source!F54 -> КА, п.16 | C76: ОБОРУДОВАНИЕ:_x000D_ Приточная установка П12 (L=3400 м3/ч, Pc=700 Па) 45 981,50 = [407 400 / 1,22 / 7,57] + 3% Трансп + 1,2% Заг.скл | D76: =Source!H54 -> ШТ | E76: =Source!I54 -> 1 | F76: =Source!AL54 -> 45981.5 | H76: =Source!AW55 -> 1 | I76: =Source!P54 -> 45981.5 | J76: =IF(Source!BC55<> 0, Source!BC55, 1) -> 7.57 | K76: =Source!P55 -> 348079.96 | Q76: =Source!X54 -> 0 | R76: =Source!X55 -> 0 | S76: =Source!Y54 -> 0 | T76: =Source!Y55 -> 0 | U76: =ROUND((175/100)*ROUND(Source!R54, 2), 2) -> 0 | V76: =ROUND((0/100)*ROUND(Source!R55, 2), 2) -> 0 | AC76: 5
C77: ВСЕГО по позиции: | H77: =I76+0 -> 45981.5 | J77: =K76+0 -> 348079.96 | O77: =I76+0 -> 45981.5 | P77: =K76+0 -> 348079.96
A79: 13 | B79: =Source!F56 -> КА, п.17 | C79: ОБОРУДОВАНИЕ:_x000D_ Приточная установка П13 (L=2000 м3/ч, Pc=500 Па) 39 842,72 = [353 010 / 1,22 / 7,57] + 3% Трансп + 1,2% Заг.скл | D79: =Source!H56 -> ШТ | E79: =Source!I56 -> 1 | F79: =Source!AL56 -> 39842.72 | H79: =Source!AW57 -> 1 | I79: =Source!P56 -> 39842.72 | J79: =IF(Source!BC57<> 0, Source!BC57, 1) -> 7.57 | K79: =Source!P57 -> 301609.39 | Q79: =Source!X56 -> 0 | R79: =Source!X57 -> 0 | S79: =Source!Y56 -> 0 | T79: =Source!Y57 -> 0 | U79: =ROUND((175/100)*ROUND(Source!R56, 2), 2) -> 0 | V79: =ROUND((0/100)*ROUND(Source!R57, 2), 2) -> 0 | AC79: 5
C80: ВСЕГО по позиции: | H80: =I79+0 -> 39842.72 | J80: =K79+0 -> 301609.39 | O80: =I79+0 -> 39842.72 | P80: =K79+0 -> 301609.39
A82: 14 | B82: =Source!F58 -> КА, п.18 | C82: ОБОРУДОВАНИЕ:_x000D_ Приточная установка КМО1 (L=1200 м3/ч, Pc=400 Па) 34 249,11 = [303 450 / 1,22 / 7,57] + 3% Трансп + 1,2% Заг.скл | D82: =Source!H58 -> ШТ | E82: =Source!I58 -> 1 | F82: =Source!AL58 -> 34249.11 | H82: =Source!AW59 -> 1 | I82: =Source!P58 -> 34249.11 | J82: =IF(Source!BC59<> 0, Source!BC59, 1) -> 7.57 | K82: =Source!P59 -> 259265.76 | Q82: =Source!X58 -> 0 | R82: =Source!X59 -> 0 | S82: =Source!Y58 -> 0 | T82: =Source!Y59 -> 0 | U82: =ROUND((175/100)*ROUND(Source!R58, 2), 2) -> 0 | V82: =ROUND((0/100)*ROUND(Source!R59, 2), 2) -> 0 | AC82: 5
C83: ВСЕГО по позиции: | H83: =I82+0 -> 34249.11 | J83: =K82+0 -> 259265.76 | O83: =I82+0 -> 34249.11 | P83: =K82+0 -> 259265.76
A85: 15 | B85: =Source!F60 -> КА, п.20 | C85: ОБОРУДОВАНИЕ:_x000D_ Приточная установка КМО2 (L=180 м3/ч, Pc=300 Па) 12 253,83 = [108 570 / 1,22 / 7,57] + 3% Трансп + 1,2% Заг.скл | D85: =Source!H60 -> ШТ | E85: =Source!I60 -> 1 | F85: =Source!AL60 -> 12253.83 | H85: =Source!AW61 -> 1 | I85: =Source!P60 -> 12253.83 | J85: =IF(Source!BC61<> 0, Source!BC61, 1) -> 7.57 | K85: =Source!P61 -> 92761.49 | Q85: =Source!X60 -> 0 | R85: =Source!X61 -> 0 | S85: =Source!Y60 -> 0 | T85: =Source!Y61 -> 0 | U85: =ROUND((175/100)*ROUND(Source!R60, 2), 2) -> 0 | V85: =ROUND((0/100)*ROUND(Source!R61, 2), 2) -> 0 | AC85: 5
C86: ВСЕГО по позиции: | H86: =I85+0 -> 12253.83 | J86: =K85+0 -> 92761.49 | O86: =I85+0 -> 12253.83 | P86: =K85+0 -> 92761.49
A88: 16 | B88: =Source!F62 -> КА, п.21 | C88: ОБОРУДОВАНИЕ:_x000D_ Приточная установка КМО3 (L=120 м3/ч, Pc=300 Па) 10 701,35 = [94 815 / 1,22 / 7,57] + 3% Трансп + 1,2% Заг.скл | D88: =Source!H62 -> ШТ | E88: =Source!I62 -> 1 | F88: =Source!AL62 -> 10701.35 | H88: =Source!AW63 -> 1 | I88: =Source!P62 -> 10701.35 | J88: =IF(Source!BC63<> 0, Source!BC63, 1) -> 7.57 | K88: =Source!P63 -> 81009.22 | Q88: =Source!X62 -> 0 | R88: =Source!X63 -> 0 | S88: =Source!Y62 -> 0 | T88: =Source!Y63 -> 0 | U88: =ROUND((175/100)*ROUND(Source!R62, 2), 2) -> 0 | V88: =ROUND((0/100)*ROUND(Source!R63, 2), 2) -> 0 | AC88: 5
C89: ВСЕГО по позиции: | H89: =I88+0 -> 10701.35 | J89: =K88+0 -> 81009.22 | O89: =I88+0 -> 10701.35 | P89: =K88+0 -> 81009.22
A91: 17 | B91: =Source!F64 -> КА, п.22 | C91: ОБОРУДОВАНИЕ:_x000D_ Приточная установка КМО4 (L=950 м3/ч, Pc=300 Па) 31 120,46 = [275 730 / 1,22 / 7,57] + 3% Трансп + 1,2% Заг.скл | D91: =Source!H64 -> ШТ | E91: =Source!I64 -> 1 | F91: =Source!AL64 -> 31120.46 | H91: =Source!AW65 -> 1 | I91: =Source!P64 -> 31120.46 | J91: =IF(Source!BC65<> 0, Source!BC65, 1) -> 7.57 | K91: =Source!P65 -> 235581.88 | Q91: =Source!X64 -> 0 | R91: =Source!X65 -> 0 | S91: =Source!Y64 -> 0 | T91: =Source!Y65 -> 0 | U91: =ROUND((175/100)*ROUND(Source!R64, 2), 2) -> 0 | V91: =ROUND((0/100)*ROUND(Source!R65, 2), 2) -> 0 | AC91: 5
C92: ВСЕГО по позиции: | H92: =I91+0 -> 31120.46 | J92: =K91+0 -> 235581.88 | O92: =I91+0 -> 31120.46 | P92: =K91+0 -> 235581.88
A94: 18 | B94: =Source!F66 -> 3.20-40-2 | C94: Установка камер приточных типовых и установок приточных без секции орошения производительностью до 20 тыс.м3/час | D94: =Source!H66 -> 1 КАМЕРА | E94: =Source!I66 -> 1 | Q94: =Source!X66 -> 1158.83 | R94: =Source!X67 -> 65300.27 | S94: =Source!Y66 -> 648.52 | T94: =Source!Y67 -> 36544.19 | U94: =ROUND((175/100)*ROUND(Source!R66, 2), 2) -> 44.29 | V94: =ROUND((0/100)*ROUND(Source!R67, 2), 2) -> 0 | AC94: 0
C95: ЗП | F95: =Source!AO66 -> 671.27 | G95: 1,05*1,15*1,2 | H95: =Source!AV67 -> 1.067 | I95: =Source!S66 -> 1037.84 | J95: =IF(Source!BA67<> 0, Source!BA67, 1) -> 56.35 | K95: =Source!S67 -> 58482.28
C96: ЭМ | F96: =Source!AM66 -> 143.96 | G96: 1,05*1,25*1,2 | H96: =Source!AV67 -> 1.067 | I96: =Source!Q66 -> 241.93 | J96: =IF(Source!BB67<> 0, Source!BB67, 1) -> 15.28 | K96: =Source!Q67 -> 3696.69
C97: в т.ч. ЗПМ | F97: =Source!AN66 -> 15.06 | G97: 1,05*1,25*1,2 | H97: =Source!AV67 -> 1.067 | I97: =Source!R66 -> 25.31 | J97: =IF(Source!BS67<> 0, Source!BS67, 1) -> 56.35 | K97: =Source!R67 -> 1426.22
C98: МР | F98: =Source!AL66 -> 372.01 | H98: =Source!AW67 -> 1 | I98: =Source!P66 -> 372.01 | J98: =IF(Source!BC67<> 0, Source!BC67, 1) -> 7.9 | K98: =Source!P67 -> 2938.88
C99: НР от ФОТ | D99: % | E99: =Source!BZ67 -> 109 | I99: =SUM(Q94:Q98) -> 1158.83 | J99: =Source!AT67 -> 109 | K99: =SUM(R94:R98) -> 65300.27
C100: СП от ФОТ | D100: % | E100: =Source!CA67 -> 61 | I100: =SUM(S94:S99) -> 648.52 | J100: =Source!AU67 -> 61 | K100: =SUM(T94:T99) -> 36544.19
C101: ЗТР | D101: чел-ч | E101: =Source!AQ66 -> 55.8 | G101: 1,05*1,15*1,2 | H101: =Source!AV67 -> 1.067 | I101: =Source!U66 -> 86.271431
C102: ВСЕГО работ по позиции: | H102: =I95+I96+I98+I99+I100+0-0-0 -> 3459.13 | J102: =K95+K96+K98+K99+K100+0-0-0 -> 166962.31
C103: ВСЕГО оборудование по позиции: | H103: =0+0 -> 0 | J103: =0+0 -> 0
C104: ВСЕГО по позиции: | H104: =I95+I96+I98+I99+I100+0 -> 3459.13 | J104: =K95+K96+K98+K99+K100+0 -> 166962.31 | O104: =I95+I96+I98+I99+I100+0 -> 3459.13 | P104: =K95+K96+K98+K99+K100+0 -> 166962.31
A106: 19 | B106: =Source!F68 -> КА, п.13 | C106: ОБОРУДОВАНИЕ:_x000D_ Приточная установка П9 (L=2045м3/ч, Pc=500 Па) 39 842,72 = [353 010 / 1,22 / 7,57] + 3% Трансп + 1,2% Заг.скл | D106: =Source!H68 -> ШТ | E106: =Source!I68 -> 1 | F106: =Source!AL68 -> 39842.72 | H106: =Source!AW69 -> 1 | I106: =Source!P68 -> 39842.72 | J106: =IF(Source!BC69<> 0, Source!BC69, 1) -> 7.57 | K106: =Source!P69 -> 301609.39 | Q106: =Source!X68 -> 0 | R106: =Source!X69 -> 0 | S106: =Source!Y68 -> 0 | T106: =Source!Y69 -> 0 | U106: =ROUND((175/100)*ROUND(Source!R68, 2), 2) -> 0 | V106: =ROUND((0/100)*ROUND(Source!R69, 2), 2) -> 0 | AC106: 5
C107: ВСЕГО по позиции: | H107: =I106+0 -> 39842.72 | J107: =K106+0 -> 301609.39 | O107: =I106+0 -> 39842.72 | P107: =K106+0 -> 301609.39
A110: =CONCATENATE("Итого по подразделу: ",IF(Source!G71<>"Новый подраздел", Source!G71, "")) -> Итого по подразделу: Приточные установки | H110: =SUM(O33:O109) -> 801004.59 | J110: =SUM(P33:P109) -> 7812357
A111: Итого по ТСН-2001.16 | I111: =SUM(W33:W110) -> 0 | J111: =SUM(X33:X110) -> 0
A112: Итого возвратных сумм | I112: =SUM(Y33:Y111) -> 0 | J112: =SUM(Z33:Z111) -> 0
A114: =CONCATENATE("Подраздел: ",IF(Source!G101<>"Новый подраздел", Source!G101, "")) -> Подраздел: Смесительный узел
A115: 20 | B115: =Source!F105 -> 3.20-52-1 | C115: Присоединение трубопроводов к оросительной системе блока тепломассобмена производительностью до 20 тыс.м3/час | D115: =Source!H105 -> 1 блок | E115: =Source!I105 -> 14 | Q115: =Source!X105 -> 725.56 | R115: =Source!X106 -> 40885.22 | S115: =Source!Y105 -> 406.05 | T115: =Source!Y106 -> 22880.72 | U115: =ROUND((175/100)*ROUND(Source!R105, 2), 2) -> 15.65 | V115: =ROUND((0/100)*ROUND(Source!R106, 2), 2) -> 0 | AC115: 0
C116: ="Объем: "&Source!I105&"=4+"&"5+"&"3+"&"1+"&"1" -> Объем: 14=4+5+3+1+1
C117: ЗП | F117: =Source!AO105 -> 30.34 | G117: 1,15*1,05*1,2 | H117: =Source!AV106 -> 1.067 | I117: =Source!S105 -> 656.71 | J117: =IF(Source!BA106<> 0, Source!BA106, 1) -> 56.35 | K117: =Source!S106 -> 37005.61
C118: ЭМ | F118: =Source!AM105 -> 4.77 | G118: 1,25*1,05*1,2 | H118: =Source!AV106 -> 1.067 | I118: =Source!Q105 -> 112.23 | J118: =IF(Source!BB106<> 0, Source!BB106, 1) -> 15.34 | K118: =Source!Q106 -> 1721.61
C119: в т.ч. ЗПМ | F119: =Source!AN105 -> 0.38 | G119: 1,25*1,05*1,2 | H119: =Source!AV106 -> 1.067 | I119: =Source!R105 -> 8.94 | J119: =IF(Source!BS106<> 0, Source!BS106, 1) -> 56.35 | K119: =Source!R106 -> 503.77
C120: МР | F120: =Source!AL105 -> 26.02 | H120: =Source!AW106 -> 1 | I120: =Source!P105 -> 364.28 | J120: =IF(Source!BC106<> 0, Source!BC106, 1) -> 7.99 | K120: =Source!P106 -> 2910.6
C121: НР от ФОТ | D121: % | E121: =Source!BZ106 -> 109 | I121: =SUM(Q115:Q120) -> 725.56 | J121: =Source!AT106 -> 109 | K121: =SUM(R115:R120) -> 40885.22
C122: СП от ФОТ | D122: % | E122: =Source!CA106 -> 61 | I122: =SUM(S115:S121) -> 406.05 | J122: =Source!AU106 -> 61 | K122: =SUM(T115:T121) -> 22880.72
C123: ЗТР | D123: чел-ч | E123: =Source!AQ105 -> 2.37 | G123: 1,15*1,05*1,2 | H123: =Source!AV106 -> 1.067 | I123: =Source!U105 -> 51.299034
C124: ВСЕГО работ по позиции: | H124: =I117+I118+I120+I121+I122+0-0-0 -> 2264.83 | J124: =K117+K118+K120+K121+K122+0-0-0 -> 105403.76
C125: ВСЕГО оборудование по позиции: | H125: =0+0 -> 0 | J125: =0+0 -> 0
C126: ВСЕГО по позиции: | H126: =I117+I118+I120+I121+I122+0 -> 2264.83 | J126: =K117+K118+K120+K121+K122+0 -> 105403.76 | O126: =I117+I118+I120+I121+I122+0 -> 2264.83 | P126: =K117+K118+K120+K121+K122+0 -> 105403.76
A128: 21 | B128: =Source!F107 -> КА, п.2 | C128: ОБОРУДОВАНИЕ:_x000D_ П1, П8, П9, П13 Смесительный узел SURP 40-2.5 5 042,27 = [44 675 / 1,22 / 7,57] + 3% Трансп + 1,2% Заг.скл | D128: =Source!H107 -> ШТ | E128: =Source!I107 -> 4 | F128: =Source!AL107 -> 5042.27 | H128: =Source!AW108 -> 1 | I128: =Source!P107 -> 20169.08 | J128: =IF(Source!BC108<> 0, Source!BC108, 1) -> 7.57 | K128: =Source!P108 -> 152679.94 | Q128: =Source!X107 -> 0 | R128: =Source!X108 -> 0 | S128: =Source!Y107 -> 0 | T128: =Source!Y108 -> 0 | U128: =ROUND((175/100)*ROUND(Source!R107, 2), 2) -> 0 | V128: =ROUND((0/100)*ROUND(Source!R108, 2), 2) -> 0 | AC128: 5
C129: ВСЕГО по позиции: | H129: =I128+0 -> 20169.08 | J129: =K128+0 -> 152679.94 | O129: =I128+0 -> 20169.08 | P129: =K128+0 -> 152679.94
A131: 22 | B131: =Source!F109 -> КА, п.4 | C131: ОБОРУДОВАНИЕ:_x000D_ П2, П4,П10, П11, П12 Смесительный узел SURP 80-6.3 7 900,60 = [70 000 / 1,22 / 7,57] + 3% Трансп + 1,2% Заг.скл | D131: =Source!H109 -> ШТ | E131: =Source!I109 -> 5 | F131: =Source!AL109 -> 7900.6 | H131: =Source!AW110 -> 1 | I131: =Source!P109 -> 39503 | J131: =IF(Source!BC110<> 0, Source!BC110, 1) -> 7.57 | K131: =Source!P110 -> 299037.71 | Q131: =Source!X109 -> 0 | R131: =Source!X110 -> 0 | S131: =Source!Y109 -> 0 | T131: =Source!Y110 -> 0 | U131: =ROUND((175/100)*ROUND(Source!R109, 2), 2) -> 0 | V131: =ROUND((0/100)*ROUND(Source!R110, 2), 2) -> 0 | AC131: 5
...

Sheet Source
A1: 0 | B1: Smeta.RU (495) 974-1589 | D1: _PS_ | F1: 0 | G1: 0 | H1: 0 | I1: Smeta.RU | K1: 1 | L1: 74598 | M1: 10 | N1: 12 | O1: 1 | P1: 0 | Q1: 5
A4: 1 | B4: 1 | C4: -1 | G4: Капитальный ремонт здания Государственного бюджетного общеобразовательного учреждения города Москвы «Школа №1574» по адресу: г. Москва, Старопименовский пер., д. №5 | EC4: 0
A5: 8 | B5: 1 | C5: -1 | G5: Капитальный ремонт здания Государственного бюджетного общеобразовательного учреждения города Москвы «Школа №1574» по адресу: г. Москва, Старопименовский пер., д. №5 | EC5: 0
A12: 1 | B12: 1577 | C12: 0 | D12: =ROW(A1536) -> 1536 | E12: 0 | F12: 02-01-07 | G12: 02-01-07 Вентиляция и кондиционирование воздуха | I12: 0 | J12: 2024-00375-01-0-ИОС4.2 | K12: 0 | L12: 0 | M12: 4098 | O12: 0 | P12: 0 | Q12: 0 | R12: 0 | S12: 0 | T12: 1 | U12: Капитальный ремонт здания Государственного бюджетного общеобразовательного учреждения города Москвы «Школа №1574» | V12: 2 | W12: г. Москва, Старопименовский переулок, д. 5. 1 этап | AB12: Гришечкина О.А. | AC12: Ведущий инженер сметчик | AD12: Феденко И.В. | AE12: Руководитель сметного отдела | BB12: 0 | BH12: Сметные нормы списания | BI12: Коды ОКП для ТСН-2001 МГЭ Дополнение 81 | BJ12: 1 | BK12: 1 | BL12: 0 | BM12: 0 | BN12: 1 | BO12: 0 | BP12: 6 | BQ12: 2 | BR12: 1 | BS12: 1 | BT12: 0 | BU12: 0 | BV12: 0 | BW12: 0 | BX12: 0 | BZ12: Типовой расчет для ТСН-2001 МГЭ, Дополнение 81, ремонт | CA12: Территориальные сметные нормативы для Москвы ТСН-2001 (МГЭ), дополнение 81 | CB12: Территориальные сметные нормативы для Москвы ТСН-2001 (МГЭ), дополнение 81 | CC12: Территориальные сметные нормативы для Москвы ТСН-2001 (МГЭ), дополнение 81 | CD12: Территориальные сметные нормативы для Москвы ТСН-2001 (МГЭ), дополнение 81 | CE12: Поправки для ТСН-2001 от 07.04.2026 г. доп.81 | CF12: 0 | CG12: 0 | CH12: 8200 | CK12: 82 | CQ12: Территориальные сметные нормативы для Москвы (ТСН-2001) | CR12: ТЕР | CS12: 41660 | CT12: 1 | CU12: 81 | CY12: 0 | EC12: 0
A15: 15 | B15: 1
A18: 52 | B18: =B1536 -> 1577 | C18: =C1536 -> 1 | D18: =D1536 -> 12 | E18: =E1536 -> 0 | F18: =F1536 -> 02-01-07 | G18: =G1536 -> 02-01-07 Вентиляция и кондиционирование воздуха | O18: =O1536 -> 5596900.2 | P18: =P1536 -> 5491642.6 | Q18: =Q1536 -> 12119.28 | R18: =R1536 -> 1450.29 | S18: =S1536 -> 93138.28 | T18: =T1536 -> 0 | U18: =U1536 -> 7684.5827 | V18: =V1536 -> 0 | ... GX18: =GX1536 -> 0
A20: 3 | B20: 1 | D20: =ROW(A1506) -> 1506 | F20: 02-01-07 | G20: Вентиляция и кондиционирование воздуха | I20: 0 | J20: 2024-00375-01-0-ИОС4.2 | K20: -1 | L20: 02-01-07 | S20: 0 | T20: 0 | V20: 2 | AB20: Гришечкина О.А. | AC20: Ведущий инженер сметчик | AD20: Феденко И.В. | AE20: Руководитель сметного отдела | BX20: 0 | CF20: 0 | CG20: 0
A22: 52 | B22: =B1506 -> 1 | C22: =C1506 -> 3 | D22: =D1506 -> 20 | E22: =E1506 -> 0 | F22: =F1506 -> 02-01-07 | G22: =G1506 -> Вентиляция и кондиционирование воздуха | O22: =O1506 -> 5596900.2 | P22: =P1506 -> 5491642.6 | Q22: =Q1506 -> 12119.28 | R22: =R1506 -> 1450.29 | S22: =S1506 -> 93138.28 | T22: =T1506 -> 0 | U22: =U1506 -> 7684.5827 | V22: =V1506 -> 0 | ... GX22: =GX1506 -> 0
A24: 4 | B24: 1 | D24: =ROW(A357) -> 357 | F24: Новый раздел | G24: Вентиляция | I24: 0 | K24: 0 | S24: 0 | T24: 0 | V24: 2 | BX24: 0 | CJ24: 0
A26: 52 | B26: =B357 -> 1 | C26: =C357 -> 4 | D26: =D357 -> 24 | E26: =E357 -> 0 | F26: =F357 -> Новый раздел | G26: =G357 -> Вентиляция | O26: =O357 -> 2190944.9 | P26: =P357 -> 2141975.3 | Q26: =Q357 -> 5775.02 | R26: =R357 -> 618.14 | S26: =S357 -> 43194.5 | T26: =T357 -> 0 | U26: =U357 -> 3548.3134 | V26: =V357 -> 0 | ... GX26: =GX357 -> 0
A28: 5 | B28: 1 | D28: =ROW(A71) -> 71 | F28: Новый подраздел | G28: Приточные установки | I28: 0 | K28: 0 | S28: 0 | T28: 0 | V28: 2 | BX28: 0 | CJ28: 0
A30: 52 | B30: =B71 -> 1 | C30: =C71 -> 5 | D30: =D71 -> 28 | E30: =E71 -> 0 | F30: =F71 -> Новый подраздел | G30: =G71 -> Приточные установки | O30: =O71 -> 778582.9 | P30: =P71 -> 763458.88 | Q30: =Q71 -> 2152.89 | R30: =R71 -> 218.1 | S30: =S71 -> 12971.13 | T30: =T71 -> 0 | U30: =U71 -> 1078.2383 | V30: =V71 -> 0 | ... GX30: =GX71 -> 0
A32: 17 | B32: 1 | C32: =ROW(SmtRes!A15) -> 15 | D32: =ROW(EtalonRes!A16) -> 16 | E32: 1 | F32: 3.20-40-1 | G32: Установка камер приточных типовых без секции орошения и установок приточных производительностью до 10 тыс.м3/час | H32: 1 КАМЕРА | I32: 16 | J32: 0 | K32: 16 | O32: =ROUND(CP32,2) -> 17418.81 | P32: =ROUND((ROUND((AC32*AW32*I32),2)*BC32),2) -> 3574.56 | Q32: =(ROUND((ROUND((((((ET32*1.2)*1.25)*1.05))*AV32*I32),2)*BB32),2)+ROUND((ROUND(((AE32-((((EU32*1.2)*1.25)*1.05)))*AV32*I32),2)*BS32),2)) -> 1910.96 | R32: =(ROUND((ROUND((((((EU32*1.2)*1.25)*1.05))*AV32*I32),2)*BS32),2)+ROUND((ROUND(((AE32-((((EU32*1.2)*1.25)*1.05)))*AV32*I32),2)*BS32),2)) -> 192.79 | S32: =ROUND((ROUND((AF32*AV32*I32),2)*BA32),2) -> 11933.29 | T32: =ROUND(CU32*I32,2) -> 0 | U32: =CV32*I32 -> 991.96685 | V32: =CW32*I32 -> 0 | W32: =ROUND(CX32*I32,2) -> 0 | X32: =(ROUND((((S32+ROUND((ROUND((((((EU32*1.2)*1.25)*1.05))*AV32*I32),2)*BS32),2))*AT32)/100),2)+ROUND(((ROUND((ROUND(((AE32-((((EU32*1.2)*1.25)*1.05)))*AV32*I32),2)*BS32),2)*AT32)/100),2)) -> 13217.43 | Y32: =(ROUND((((S32+ROUND((ROUND((((((EU32*1.2)*1.25)*1.05))*AV32*I32),2)*BS32),2))*AU32)/100),2)+ROUND(((ROUND((ROUND(((AE32-((((EU32*1.2)*1.25)*1.05)))*AV32*I32),2)*BS32),2)*AU32)/100),2)) -> 7396.91 | AA32: 56661434 | AB32: =ROUND((AC32+AD32+AF32),6) -> 1034.3428 | AC32: =ROUND((((ES32*1)*1)),6) -> 223.41 | AD32: =ROUND(((((((ET32*1.2)*1.25)*1.05))-((((EU32*1.2)*1.25)*1.05)))+AE32),6) -> 111.93525 | AE32: =ROUND(((((EU32*1.2)*1.25)*1.05)),6) -> 11.29275 | AF32: =ROUND(((((EV32*1.2)*1.15)*1.05)),6) -> 698.9976 | AG32: =ROUND((AP32),6) -> 0 | AH32: =((((EW32*1.2)*1.15)*1.05)) -> 58.1049 | AI32: =((((EX32*1.2)*1.25)*1.05)) -> 0 | AJ32: =(AS32) -> 0 | AK32: 776.88 | AL32: 223.41 | AM32: 71.07 | AN32: 7.17 | AO32: 482.4 | AP32: 0 | AQ32: 40.1 | AR32: 0 | AS32: 0 | AT32: 109 | AU32: 61 | AV32: 1.067 | AW32: 1 | AZ32: 1 | BA32: 1 | BB32: 1 | BC32: 1 | BH32: 0 | BI32: 1 | BJ32: ТСН-2001.3 Доп. 79, Сб. 20, т. 40, поз. 1 | BM32: 25 | BN32: 0 | BO32: 3.20-40-1 | BP32: 1 | BQ32: 30 | BR32: 0 | BS32: 1 | BT32: 1 | BU32: 1 | BV32: 1 | BW32: 1 | BX32: 1 | BZ32: 109 | CA32: 61 | CE32: 1566 | CF32: 0 | CG32: 0 | CM32: 0 | CN32: Поправка: Гл.12.Прил.8.п.8. 3_12.00.01.11.001 Наименование: При наличии напряженных и стесненных условий производства работ (стесненность, сложность складирования и транспортной логистики и т.п.) для объектов, расположенных в пределах круговой магистральной системы улиц "Садовое кольцо" города Москвы Поправка: Гл.6.Прил.2.2.п.2.2.6_06.00.01.07.001 Наименование: При выполнении при капитальном ремонте и реконструкции работ, аналогичных технологическим процессам, характерным для нового строительства, и отсутствующих в сборниках на ремонтно-строительные работы ТСН-2001.6 | CO32: 0 | CP32: =(P32+Q32+S32) -> 17418.81 | CQ32: =ROUND((ROUND((AC32*AW32*1),2)*BC32),2) -> 223.41 | CR32: =(ROUND((ROUND((((((ET32*1.2)*1.25)*1.05))*AV32*1),2)*BB32),2)+ROUND((ROUND(((AE32-((((EU32*1.2)*1.25)*1.05)))*AV32*1),2)*BS32),2)) -> 119.43 | CS32: =(ROUND((ROUND((((((EU32*1.2)*1.25)*1.05))*AV32*1),2)*BS32),2)+ROUND((ROUND(((AE32-((((EU32*1.2)*1.25)*1.05)))*AV32*1),2)*BS32),2)) -> 12.05 | CT32: =ROUND((ROUND((AF32*AV32*1),2)*BA32),2) -> 745.83 | CU32: =AG32 -> 0 | CV32: =(AH32*AV32) -> 61.997928 | CW32: =AI32 -> 0 | CX32: =AJ32 -> 0 | CY32: =(ROUND((((S32+ROUND((ROUND((((((EU32*1.2)*1.25)*1.05))*AV32*1),2)*BS32),2))*AT32)/100),2)+ROUND(((ROUND((ROUND(((AE32-((((EU32*1.2)*1.25)*1.05)))*AV32*1),2)*BS32),2)*AT32)/100),2)) -> 13020.42 | CZ32: =(ROUND((((S32+ROUND((ROUND((((((EU32*1.2)*1.25)*1.05))*AV32*1),2)*BS32),2))*AU32)/100),2)+ROUND(((ROUND((ROUND(((AE32-((((EU32*1.2)*1.25)*1.05)))*AV32*1),2)*BS32),2)*AU32)/100),2)) -> 7286.66 | DD32: *1)*1 | DE32: *1,2)*1,25)*1,05 | DF32: *1,2)*1,25)*1,05 | DG32: *1,2)*1,15)*1,05 | DI32: *1,2)*1,15)*1,05 | DJ32: *1,2)*1,25)*1,05 | DN32: 0 | DO32: 0 | DP32: 1 | DQ32: 1 | DU32: 1013 | DV32: 1 КАМЕРА | DW32: 1 КАМЕРА | DX32: 1 | EE32: 56938458 | EF32: 30 | EG32: Строительные работы | EH32: 0 | EJ32: 1 | EK32: 25 | EL32: ТСН-2001.3-20. Вентиляция и кондиционирование воздуха | EM32: ТСН-2001.3-20-1 | EO32: Поправка: Гл.12.Прил.8.п.8. 3_12.00.01.11.001 Поправка: Гл.6.Прил.2.2.п.2.2.6_06.00.01.07.001 | EQ32: 131072 | ER32: 776.88 | ES32: 223.41 | ET32: 71.07 | EU32: 7.17 | EV32: 482.4 | EW32: 40.1 | EX32: 0 | EY32: 0 | FQ32: 0 | FR32: 0 | FS32: 0 | FX32: 109 | FY32: 61 | GD32: 1 | GF32: -129762480 | GG32: 2 | GH32: 1 | GI32: 2 | GJ32: 0 | GK32: 0 | GL32: =ROUND(IF(AND(BH32=3,BI32=3,FS32<>0),P32,0),2) -> 0 | GM32: =ROUND(O32+X32+Y32,2)+GX32 -> 38033.15 | GN32: =IF(OR(BI32=0,BI32=1),GM32-GX32,0) -> 38033.15 | GO32: =IF(BI32=2,GM32-GX32,0) -> 0 | GP32: =IF(BI32=4,GM32-GX32,0) -> 0 | GR32: 0 | GS32: 3 | GT32: 0 | GV32: =ROUND((GT32),6) -> 0 | GW32: 1 | GX32: =ROUND(HC32*I32,2) -> 0 | HA32: 0 | HB32: 0 | HC32: =GV32*GW32 -> 0 | HS32: 0 | IK32: 0
A33: 17 | B33: 1 | C33: =ROW(SmtRes!A30) -> 30 | D33: =ROW(EtalonRes!A32) -> 32 | E33: 1 | F33: 3.20-40-1 | G33: Установка камер приточных типовых без секции орошения и установок приточных производительностью до 10 тыс.м3/час | H33: 1 КАМЕРА | I33: 16 | J33: 0 | K33: 16 | O33: =ROUND(CP33,2) -> 734268.67 | P33: =ROUND((ROUND((AC33*AW33*I33),2)*BC33),2) -> 32742.97 | Q33: =(ROUND((ROUND((((((ET33*1.2)*1.25)*1.05))*AV33*I33),2)*BB33),2)+ROUND((ROUND(((AE33-((((EU33*1.2)*1.25)*1.05)))*AV33*I33),2)*BS33),2)) -> 29084.81 | R33: =(ROUND((ROUND((((((EU33*1.2)*1.25)*1.05))*AV33*I33),2)*BS33),2)+ROUND((ROUND(((AE33-((((EU33*1.2)*1.25)*1.05)))*AV33*I33),2)*BS33),2)) -> 10863.72 | S33: =ROUND((ROUND((AF33*AV33*I33),2)*BA33),2) -> 672440.89 | T33: =ROUND(CU33*I33,2) -> 0 | U33: =CV33*I33 -> 991.96685 | V33: =CW33*I33 -> 0 | W33: =ROUND(CX33*I33,2) -> 0 | X33: =(ROUND((((S33+ROUND((ROUND((((((EU33*1.2)*1.25)*1.05))*AV33*I33),2)*BS33),2))*AT33)/100),2)+ROUND(((ROUND((ROUND(((AE33-((((EU33*1.2)*1.25)*1.05)))*AV33*I33),2)*BS33),2)*AT33)/100),2)) -> 744802.02 | Y33: =(ROUND((((S33+ROUND((ROUND((((((EU33*1.2)*1.25)*1.05))*AV33*I33),2)*BS33),2))*AU33)/100),2)+ROUND(((ROUND((ROUND(((AE33-((((EU33*1.2)*1.25)*1.05)))*AV33*I33),2)*BS33),2)*AU33)/100),2)) -> 416815.81 | AA33: 56661436 | AB33: =ROUND((AC33+AD33+AF33),6) -> 1034.3428 | AC33: =ROUND((((ES33*1)*1)),6) -> 223.41 | AD33: =ROUND(((((((ET33*1.2)*1.25)*1.05))-((((EU33*1.2)*1.25)*1.05)))+AE33),6) -> 111.93525 | AE33: =ROUND(((((EU33*1.2)*1.25)*1.05)),6) -> 11.29275 | AF33: =ROUND(((((EV33*1.2)*1.15)*1.05)),6) -> 698.9976 | AG33: =ROUND((AP33),6) -> 0 | AH33: =((((EW33*1.2)*1.15)*1.05)) -> 58.1049 | AI33: =((((EX33*1.2)*1.25)*1.05)) -> 0 | AJ33: =(AS33) -> 0 | AK33: 776.88 | AL33: 223.41 | AM33: 71.07 | AN33: 7.17 | AO33: 482.4 | AP33: 0 | AQ33: 40.1 | AR33: 0 | AS33: 0 | AT33: 109 | AU33: 61 | AV33: 1.067 | AW33: 1 | AZ33: 1 | BA33: 56.35 | BB33: 15.22 | BC33: 9.16 | BH33: 0 | BI33: 1 | BJ33: ТСН-2001.3 Доп. 79, Сб. 20, т. 40, поз. 1 | BM33: 25 | BN33: 0 | BO33: 3.20-40-1 | BP33: 1 | BQ33: 30 | BR33: 0 | BS33: 56.35 | BT33: 1 | BU33: 1 | BV33: 1 | BW33: 1 | BX33: 1 | BZ33: 109 | CA33: 61 | CE33: 1566 | CF33: 0 | CG33: 0 | CM33: 0 | CN33: Поправка: Гл.12.Прил.8.п.8. 3_12.00.01.11.001 Наименование: При наличии напряженных и стесненных условий производства работ (стесненность, сложность складирования и транспортной логистики и т.п.) для объектов, расположенных в пределах круговой магистральной системы улиц "Садовое кольцо" города Москвы Поправка: Гл.6.Прил.2.2.п.2.2.6_06.00.01.07.001 Наименование: При выполнении при капитальном ремонте и реконструкции работ, аналогичных технологическим процессам, характерным для нового строительства, и отсутствующих в сборниках на ремонтно-строительные работы ТСН-2001.6 | CO33: 0 | CP33: =(P33+Q33+S33) -> 734268.67 | CQ33: =ROUND((ROUND((AC33*AW33*1),2)*BC33),2) -> 2046.44 | CR33: =(ROUND((ROUND((((((ET33*1.2)*1.25)*1.05))*AV33*1),2)*BB33),2)+ROUND((ROUND(((AE33-((((EU33*1.2)*1.25)*1.05)))*AV33*1),2)*BS33),2)) -> 1817.72 | CS33: =(ROUND((ROUND((((((EU33*1.2)*1.25)*1.05))*AV33*1),2)*BS33),2)+ROUND((ROUND(((AE33-((((EU33*1.2)*1.25)*1.05)))*AV33*1),2)*BS33),2)) -> 679.02 | CT33: =ROUND((ROUND((AF33*AV33*1),2)*BA33),2) -> 42027.52 | CU33: =AG33 -> 0 | CV33: =(AH33*AV33) -> 61.997928 | CW33: =AI33 -> 0 | CX33: =AJ33 -> 0 | CY33: =(ROUND((((S33+ROUND((ROUND((((((EU33*1.2)*1.25)*1.05))*AV33*1),2)*BS33),2))*AT33)/100),2)+ROUND(((ROUND((ROUND(((AE33-((((EU33*1.2)*1.25)*1.05)))*AV33*1),2)*BS33),2)*AT33)/100),2)) -> 733700.7 | CZ33: =(ROUND((((S33+ROUND((ROUND((((((EU33*1.2)*1.25)*1.05))*AV33*1),2)*BS33),2))*AU33)/100),2)+ROUND(((ROUND((ROUND(((AE33-((((EU33*1.2)*1.25)*1.05)))*AV33*1),2)*BS33),2)*AU33)/100),2)) -> 410603.15 | DD33: *1)*1 | DE33: *1,2)*1,25)*1,05 | DF33: *1,2)*1,25)*1,05 | DG33: *1,2)*1,15)*1,05 | DI33: *1,2)*1,15)*1,05 | DJ33: *1,2)*1,25)*1,05 | DN33: 0 | DO33: 0 | DP33: 1 | DQ33: 1 | DU33: 1013 | DV33: 1 КАМЕРА | DW33: 1 КАМЕРА | DX33: 1 | EE33: 56938458 | EF33: 30 | EG33: Строительные работы | EH33: 0 | EJ33: 1 | EK33: 25 | EL33: ТСН-2001.3-20. Вентиляция и кондиционирование воздуха | EM33: ТСН-2001.3-20-1 | EO33: Поправка: Гл.12.Прил.8.п.8. 3_12.00.01.11.001 Поправка: Гл.6.Прил.2.2.п.2.2.6_06.00.01.07.001 | EQ33: 131072 | ER33: 776.88 | ES33: 223.41 | ET33: 71.07 | EU33: 7.17 | EV33: 482.4 | EW33: 40.1 | EX33: 0 | EY33: 0 | FQ33: 0 | FR33: 0 | FS33: 0 | FX33: 109 | FY33: 61 | GD33: 1 | GF33: -129762480 | GG33: 2 | GH33: 1 | GI33: 2 | GJ33: 0 | GK33: 0 | GL33: =ROUND(IF(AND(BH33=3,BI33=3,FS33<>0),P33,0),2) -> 0 | GM33: =ROUND(O33+X33+Y33,2)+GX33 -> 1895886.5 | GN33: =IF(OR(BI33=0,BI33=1),GM33-GX33,0) -> 1895886.5 | GO33: =IF(BI33=2,GM33-GX33,0) -> 0 | GP33: =IF(BI33=4,GM33-GX33,0) -> 0 | GR33: 0 | GS33: 3 | GT33: 0 | GV33: =ROUND((GT33),6) -> 0 | GW33: 1 | GX33: =ROUND(HC33*I33,2) -> 0 | HA33: 0 | HB33: 0 | HC33: =GV33*GW33 -> 0 | HS33: 0 | IK33: 0
A34: 17 | B34: 1 | E34: 2 | F34: КА, п.1 | G34: Приточная установка П1 (L=1890 м3/ч, Pc=500 Па) | H34: ШТ | I34: 1 | J34: 0 | K34: 1 | O34: =ROUND(CP34,2) -> 38705.03 | P34: =ROUND((ROUND((AC34*AW34*I34),2)*BC34),2) -> 38705.03 | Q34: =(ROUND((ROUND(((ET34)*AV34*I34),2)*BB34),2)+ROUND((ROUND(((AE34-(EU34))*AV34*I34),2)*BS34),2)) -> 0 | R34: =(ROUND((ROUND(((EU34)*AV34*I34),2)*BS34),2)+ROUND((ROUND(((AE34-(EU34))*AV34*I34),2)*BS34),2)) -> 0 | S34: =ROUND((ROUND((AF34*AV34*I34),2)*BA34),2) -> 0 | T34: =ROUND(CU34*I34,2) -> 0 | U34: =CV34*I34 -> 0 | V34: =CW34*I34 -> 0 | W34: =ROUND(CX34*I34,2) -> 0 | X34: =(ROUND((((S34+ROUND((ROUND(((EU34)*AV34*I34),2)*BS34),2))*AT34)/100),2)+ROUND(((ROUND((ROUND(((AE34-(EU34))*AV34*I34),2)*BS34),2)*AT34)/100),2)) -> 0 | Y34: =(ROUND((((S34+ROUND((ROUND(((EU34)*AV34*I34),2)*BS34),2))*AU34)/100),2)+ROUND(((ROUND((ROUND(((AE34-(EU34))*AV34*I34),2)*BS34),2)*AU34)/100),2)) -> 0 | AA34: 56661434 | AB34: =ROUND((AC34+AD34+AF34),6) -> 38705.03 | AC34: =ROUND((ES34),6) -> 38705.03 | AD34: =ROUND((((ET34)-(EU34))+AE34),6) -> 0 | AE34: =ROUND((EU34),6) -> 0 | AF34: =ROUND((EV34),6) -> 0 | AG34: =ROUND((AP34),6) -> 0 | AH34: =(EW34) -> 0 | AI34: =(EX34) -> 0 | AJ34: =(AS34) -> 0 | AK34: 38705.03 | AL34: 38705.03 | AM34: 0 | AN34: 0 | AO34: 0 | AP34: 0 | AQ34: 0 | AR34: 0 | AS34: 0 | AT34: 0 | AU34: 0 | AV34: 1 | AW34: 1 | AZ34: 1 | BA34: 1 | BB34: 1 | BC34: 1 | BH34: 3 | BI34: 3 | BJ34: КА, п.1 | BM34: 400007 | BN34: 0 | BP34: 0 | BQ34: 214 | BR34: 0 | BS34: 1 | BT34: 1 | BU34: 1 | BV34: 1 | BW34: 1 | BX34: 1 | BZ34: 0 | CA34: 0 | CE34: 1566 | CF34: 0 | CG34: 0 | CM34: 0 | CO34: 0 | CP34: =(P34+Q34+S34) -> 38705.03 | CQ34: =ROUND((ROUND((AC34*AW34*1),2)*BC34),2) -> 38705.03 | CR34: =(ROUND((ROUND(((ET34)*AV34*1),2)*BB34),2)+ROUND((ROUND(((AE34-(EU34))*AV34*1),2)*BS34),2)) -> 0 | CS34: =(ROUND((ROUND(((EU34)*AV34*1),2)*BS34),2)+ROUND((ROUND(((AE34-(EU34))*AV34*1),2)*BS34),2)) -> 0 | CT34: =ROUND((ROUND((AF34*AV34*1),2)*BA34),2) -> 0 | CU34: =AG34 -> 0 | CV34: =(AH34*AV34) -> 0 | CW34: =AI34 -> 0 | CX34: =AJ34 -> 0 | CY34: =(ROUND((((S34+ROUND((ROUND(((EU34)*AV34*1),2)*BS34),2))*AT34)/100),2)+ROUND(((ROUND((ROUND(((AE34-(EU34))*AV34*1),2)*BS34),2)*AT34)/100),2)) -> 0 | CZ34: =(ROUND((((S34+ROUND((ROUND(((EU34)*AV34*1),2)*BS34),2))*AU34)/100),2)+ROUND(((ROUND((ROUND(((AE34-(EU34))*AV34*1),2)*BS34),2)*AU34)/100),2)) -> 0 | DN34: 0 | DO34: 0 | DP34: 1 | DQ34: 1 | DU34: 1013 | DV34: ШТ | DW34: ШТ | DX34: 1 | EE34: 56938434 | EF34: 214 | EG34: Оборудование, отсутствующие в СНБ | EH34: 0 | EJ34: 3 | EK34: 400007 | EL34: Оборудование, отсутствующие в СНБ | EM34: Оборуд. КА | EQ34: 131088 | ER34: 0 | ES34: 38705.03 | ET34: 0 | EU34: 0 | EV34: 0 | EW34: 0 | EX34: 0 | EY34: 0 | FQ34: 0 | FR34: =P34 -> 38705.03 | FS34: 0 | FX34: 0 | FY34: 0 | GA34: [342 930 / 1,22 / 7,57] + 3% Трансп + 1,2% Заг.скл | GD34: 1 | GF34: 1914587062 | GG34: 2 | GH34: 4 | GI34: -2 | GJ34: 0 | GK34: 0 | GL34: =ROUND(IF(AND(BH34=3,BI34=3,FS34<>0),P34,0),2) -> 0 | GM34: =ROUND(O34+X34+Y34,2)+GX34 -> 38705.03 | GN34: =IF(OR(BI34=0,BI34=1),GM34-GX34,0) -> 0 | GO34: =IF(BI34=2,GM34-GX34,0) -> 0 | GP34: =IF(BI34=4,GM34-GX34,0) -> 0 | GR34: 1 | GS34: 2 | GT34: 0 | GV34: =ROUND((GT34),6) -> 0 | GW34: 1 | GX34: =ROUND(HC34*I34,2) -> 0 | HA34: 0 | HB34: 0 | HC34: =GV34*GW34 -> 0 | HE34: 3 | HF34: 1,2 | HS34: 0 | IK34: 0
A35: 17 | B35: 1 | E35: 2 | F35: КА, п.1 | G35: Приточная установка П1 (L=1890 м3/ч, Pc=500 Па) | H35: ШТ | I35: 1 | J35: 0 | K35: 1 | O35: =ROUND(CP35,2) -> 292997.08 | P35: =ROUND((ROUND((AC35*AW35*I35),2)*BC35),2) -> 292997.08 | Q35: =(ROUND((ROUND(((ET35)*AV35*I35),2)*BB35),2)+ROUND((ROUND(((AE35-(EU35))*AV35*I35),2)*BS35),2)) -> 0 | R35: =(ROUND((ROUND(((EU35)*AV35*I35),2)*BS35),2)+ROUND((ROUND(((AE35-(EU35))*AV35*I35),2)*BS35),2)) -> 0 | S35: =ROUND((ROUND((AF35*AV35*I35),2)*BA35),2) -> 0 | T35: =ROUND(CU35*I35,2) -> 0 | U35: =CV35*I35 -> 0 | V35: =CW35*I35 -> 0 | W35: =ROUND(CX35*I35,2) -> 0 | X35: =(ROUND((((S35+ROUND((ROUND(((EU35)*AV35*I35),2)*BS35),2))*AT35)/100),2)+ROUND(((ROUND((ROUND(((AE35-(EU35))*AV35*I35),2)*BS35),2)*AT35)/100),2)) -> 0 | Y35: =(ROUND((((S35+ROUND((ROUND(((EU35)*AV35*I35),2)*BS35),2))*AU35)/100),2)+ROUND(((ROUND((ROUND(((AE35-(EU35))*AV35*I35),2)*BS35),2)*AU35)/100),2)) -> 0 | AA35: 56661436 | AB35: =ROUND((AC35+AD35+AF35),6) -> 38705.03 | AC35: =ROUND((ES35),6) -> 38705.03 | AD35: =ROUND((((ET35)-(EU35))+AE35),6) -> 0 | AE35: =ROUND((EU35),6) -> 0 | AF35: =ROUND((EV35),6) -> 0 | AG35: =ROUND((AP35),6) -> 0 | AH35: =(EW35) -> 0 | AI35: =(EX35) -> 0 | AJ35: =(AS35) -> 0 | AK35: 38705.03 | AL35: 38705.03 | AM35: 0 | AN35: 0 | AO35: 0 | AP35: 0 | AQ35: 0 | AR35: 0 | AS35: 0 | AT35: 0 | AU35: 0 | AV35: 1 | AW35: 1 | AZ35: 1 | BA35: 1 | BB35: 1 | BC35: 7.57 | BH35: 3 | BI35: 3 | BJ35: КА, п.1 | BM35: 400007 | BN35: 0 | BP35: 0 | BQ35: 214 | BR35: 0 | BS35: 1 | BT35: 1 | BU35: 1 | BV35: 1 | BW35: 1 | BX35: 1 | BZ35: 0 | CA35: 0 | CE35: 1566 | CF35: 0 | CG35: 0 | CM35: 0 | CO35: 0 | CP35: =(P35+Q35+S35) -> 292997.08 | CQ35: =ROUND((ROUND((AC35*AW35*1),2)*BC35),2) -> 292997.08 | CR35: =(ROUND((ROUND(((ET35)*AV35*1),2)*BB35),2)+ROUND((ROUND(((AE35-(EU35))*AV35*1),2)*BS35),2)) -> 0 | CS35: =(ROUND((ROUND(((EU35)*AV35*1),2)*BS35),2)+ROUND((ROUND(((AE35-(EU35))*AV35*1),2)*BS35),2)) -> 0 | CT35: =ROUND((ROUND((AF35*AV35*1),2)*BA35),2) -> 0 | CU35: =AG35 -> 0 | CV35: =(AH35*AV35) -> 0 | CW35: =AI35 -> 0 | CX35: =AJ35 -> 0 | CY35: =(ROUND((((S35+ROUND((ROUND(((EU35)*AV35*1),2)*BS35),2))*AT35)/100),2)+ROUND(((ROUND((ROUND(((AE35-(EU35))*AV35*1),2)*BS35),2)*AT35)/100),2)) -> 0 | CZ35: =(ROUND((((S35+ROUND((ROUND(((EU35)*AV35*1),2)*BS35),2))*AU35)/100),2)+ROUND(((ROUND((ROUND(((AE35-(EU35))*AV35*1),2)*BS35),2)*AU35)/100),2)) -> 0 | DN35: 0 | DO35: 0 | DP35: 1 | DQ35: 1 | DU35: 1013 | DV35: ШТ | DW35: ШТ | DX35: 1 | EE35: 56938434 | EF35: 214 | EG35: Оборудование, отсутствующие в СНБ | EH35: 0 | EJ35: 3 | EK35: 400007 | EL35: Оборудование, отсутствующие в СНБ | EM35: Оборуд. КА | EQ35: 131088 | ER35: 0 | ES35: 38705.03 | ET35: 0 | EU35: 0 | EV35: 0 | EW35: 0 | EX35: 0 | EY35: 0 | EZ35: 5 | FC35: 1 | FD35: 18 | FF35: 342930 | FQ35: 0 | FR35: =P35 -> 292997.08 | FS35: 0 | FX35: 0 | FY35: 0 | GA35: [342 930 / 1,22 / 7,57] + 3% Трансп + 1,2% Заг.скл | GD35: 1 | GF35: 1914587062 | GG35: 2 | GH35: 3 | GI35: 3 | GJ35: 0 | GK35: 0 | GL35: =ROUND(IF(AND(BH35=3,BI35=3,FS35<>0),P35,0),2) -> 0 | GM35: =ROUND(O35+X35+Y35,2)+GX35 -> 292997.08 | GN35: =IF(OR(BI35=0,BI35=1),GM35-GX35,0) -> 0 | GO35: =IF(BI35=2,GM35-GX35,0) -> 0 | GP35: =IF(BI35=4,GM35-GX35,0) -> 0 | GR35: 1 | GS35: 1 | GT35: 0 | GV35: =ROUND((GT35),6) -> 0 | GW35: 1 | GX35: =ROUND(HC35*I35,2) -> 0 | HA35: 0 | HB35: 0 | HC35: =GV35*GW35 -> 0 | HE35: 3 | HF35: 1,2 | HS35: 0 | IK35: 0
A36: 17 | B36: 1 | E36: 3 | F36: КА, п.3 | G36: Приточная установка П2 (L=3600 м3/ч, Pc=500 Па) | H36: ШТ | I36: 1 | J36: 0 | K36: 1 | O36: =ROUND(CP36,2) -> 45981.5 | P36: =ROUND((ROUND((AC36*AW36*I36),2)*BC36),2) -> 45981.5 | Q36: =(ROUND((ROUND(((ET36)*AV36*I36),2)*BB36),2)+ROUND((ROUND(((AE36-(EU36))*AV36*I36),2)*BS36),2)) -> 0 | R36: =(ROUND((ROUND(((EU36)*AV36*I36),2)*BS36),2)+ROUND((ROUND(((AE36-(EU36))*AV36*I36),2)*BS36),2)) -> 0 | S36: =ROUND((ROUND((AF36*AV36*I36),2)*BA36),2) -> 0 | T36: =ROUND(CU36*I36,2) -> 0 | U36: =CV36*I36 -> 0 | V36: =CW36*I36 -> 0 | W36: =ROUND(CX36*I36,2) -> 0 | X36: =(ROUND((((S36+ROUND((ROUND(((EU36)*AV36*I36),2)*BS36),2))*AT36)/100),2)+ROUND(((ROUND((ROUND(((AE36-(EU36))*AV36*I36),2)*BS36),2)*AT36)/100),2)) -> 0 | Y36: =(ROUND((((S36+ROUND((ROUND(((EU36)*AV36*I36),2)*BS36),2))*AU36)/100),2)+ROUND(((ROUND((ROUND(((AE36-(EU36))*AV36*I36),2)*BS36),2)*AU36)/100),2)) -> 0 | AA36: 56661434 | AB36: =ROUND((AC36+AD36+AF36),6) -> 45981.5 | AC36: =ROUND((ES36),6) -> 45981.5 | AD36: =ROUND((((ET36)-(EU36))+AE36),6) -> 0 | AE36: =ROUND((EU36),6) -> 0 | AF36: =ROUND((EV36),6) -> 0 | AG36: =ROUND((AP36),6) -> 0 | AH36: =(EW36) -> 0 | AI36: =(EX36) -> 0 | AJ36: =(AS36) -> 0 | AK36: 45981.5 | AL36: 45981.5 | AM36: 0 | AN36: 0 | AO36: 0 | AP36: 0 | AQ36: 0 | AR36: 0 | AS36: 0 | AT36: 0 | AU36: 0 | AV36: 1 | AW36: 1 | AZ36: 1 | BA36: 1 | BB36: 1 | BC36: 1 | BH36: 3 | BI36: 3 | BJ36: КА, п.3 | BM36: 400007 | BN36: 0 | BP36: 0 | BQ36: 214 | BR36: 0 | BS36: 1 | BT36: 1 | BU36: 1 | BV36: 1 | BW36: 1 | BX36: 1 | BZ36: 0 | CA36: 0 | CE36: 1566 | CF36: 0 | CG36: 0 | CM36: 0 | CO36: 0 | CP36: =(P36+Q36+S36) -> 45981.5 | CQ36: =ROUND((ROUND((AC36*AW36*1),2)*BC36),2) -> 45981.5 | CR36: =(ROUND((ROUND(((ET36)*AV36*1),2)*BB36),2)+ROUND((ROUND(((AE36-(EU36))*AV36*1),2)*BS36),2)) -> 0 | CS36: =(ROUND((ROUND(((EU36)*AV36*1),2)*BS36),2)+ROUND((ROUND(((AE36-(EU36))*AV36*1),2)*BS36),2)) -> 0 | CT36: =ROUND((ROUND((AF36*AV36*1),2)*BA36),2) -> 0 | CU36: =AG36 -> 0 | CV36: =(AH36*AV36) -> 0 | CW36: =AI36 -> 0 | CX36: =AJ36 -> 0 | CY36: =(ROUND((((S36+ROUND((ROUND(((EU36)*AV36*1),2)*BS36),2))*AT36)/100),2)+ROUND(((ROUND((ROUND(((AE36-(EU36))*AV36*1),2)*BS36),2)*AT36)/100),2)) -> 0 | CZ36: =(ROUND((((S36+ROUND((ROUND(((EU36)*AV36*1),2)*BS36),2))*AU36)/100),2)+ROUND(((ROUND((ROUND(((AE36-(EU36))*AV36*1),2)*BS36),2)*AU36)/100),2)) -> 0 | DN36: 0 | DO36: 0 | DP36: 1 | DQ36: 1 | DU36: 1013 | DV36: ШТ | DW36: ШТ | DX36: 1 | EE36: 56938434 | EF36: 214 | EG36: Оборудование, отсутствующие в СНБ | EH36: 0 | EJ36: 3 | EK36: 400007 | EL36: Оборудование, отсутствующие в СНБ | EM36: Оборуд. КА | EQ36: 131088 | ER36: 0 | ES36: 45981.5 | ET36: 0 | EU36: 0 | EV36: 0 | EW36: 0 | EX36: 0 | EY36: 0 | FQ36: 0 | FR36: =P36 -> 45981.5 | FS36: 0 | FX36: 0 | FY36: 0 | GA36: [407 400 / 1,22 / 7,57] + 3% Трансп + 1,2% Заг.скл | GD36: 1 | GF36: 1539617914 | GG36: 2 | GH36: 4 | GI36: -2 | GJ36: 0 | GK36: 0 | GL36: =ROUND(IF(AND(BH36=3,BI36=3,FS36<>0),P36,0),2) -> 0 | GM36: =ROUND(O36+X36+Y36,2)+GX36 -> 45981.5 | GN36: =IF(OR(BI36=0,BI36=1),GM36-GX36,0) -> 0 | GO36: =IF(BI36=2,GM36-GX36,0) -> 0 | GP36: =IF(BI36=4,GM36-GX36,0) -> 0 | GR36: 1 | GS36: 2 | GT36: 0 | GV36: =ROUND((GT36),6) -> 0 | GW36: 1 | GX36: =ROUND(HC36*I36,2) -> 0 | HA36: 0 | HB36: 0 | HC36: =GV36*GW36 -> 0 | HE36: 3 | HF36: 1,2 | HS36: 0 | IK36: 0
A37: 17 | B37: 1 | E37: 3 | F37: КА, п.3 | G37: Приточная установка П2 (L=3600 м3/ч, Pc=500 Па) | H37: ШТ | I37: 1 | J37: 0 | K37: 1 | O37: =ROUND(CP37,2) -> 348079.96 | P37: =ROUND((ROUND((AC37*AW37*I37),2)*BC37),2) -> 348079.96 | Q37: =(ROUND((ROUND(((ET37)*AV37*I37),2)*BB37),2)+ROUND((ROUND(((AE37-(EU37))*AV37*I37),2)*BS37),2)) -> 0 | R37: =(ROUND((ROUND(((EU37)*AV37*I37),2)*BS37),2)+ROUND((ROUND(((AE37-(EU37))*AV37*I37),2)*BS37),2)) -> 0 | S37: =ROUND((ROUND((AF37*AV37*I37),2)*BA37),2) -> 0 | T37: =ROUND(CU37*I37,2) -> 0 | U37: =CV37*I37 -> 0 | V37: =CW37*I37 -> 0 | W37: =ROUND(CX37*I37,2) -> 0 | X37: =(ROUND((((S37+ROUND((ROUND(((EU37)*AV37*I37),2)*BS37),2))*AT37)/100),2)+ROUND(((ROUND((ROUND(((AE37-(EU37))*AV37*I37),2)*BS37),2)*AT37)/100),2)) -> 0 | Y37: =(ROUND((((S37+ROUND((ROUND(((EU37)*AV37*I37),2)*BS37),2))*AU37)/100),2)+ROUND(((ROUND((ROUND(((AE37-(EU37))*AV37*I37),2)*BS37),2)*AU37)/100),2)) -> 0 | AA37: 56661436 | AB37: =ROUND((AC37+AD37+AF37),6) -> 45981.5 | AC37: =ROUND((ES37),6) -> 45981.5 | AD37: =ROUND((((ET37)-(EU37))+AE37),6) -> 0 | AE37: =ROUND((EU37),6) -> 0 | AF37: =ROUND((EV37),6) -> 0 | AG37: =ROUND((AP37),6) -> 0 | AH37: =(EW37) -> 0 | AI37: =(EX37) -> 0 | AJ37: =(AS37) -> 0 | AK37: 45981.5 | AL37: 45981.5 | AM37: 0 | AN37: 0 | AO37: 0 | AP37: 0 | AQ37: 0 | AR37: 0 | AS37: 0 | AT37: 0 | AU37: 0 | AV37: 1 | AW37: 1 | AZ37: 1 | BA37: 1 | BB37: 1 | BC37: 7.57 | BH37: 3 | BI37: 3 | BJ37: КА, п.3 | BM37: 400007 | BN37: 0 | BP37: 0 | BQ37: 214 | BR37: 0 | BS37: 1 | BT37: 1 | BU37: 1 | BV37: 1 | BW37: 1 | BX37: 1 | BZ37: 0 | CA37: 0 | CE37: 1566 | CF37: 0 | CG37: 0 | CM37: 0 | CO37: 0 | CP37: =(P37+Q37+S37) -> 348079.96 | CQ37: =ROUND((ROUND((AC37*AW37*1),2)*BC37),2) -> 348079.96 | CR37: =(ROUND((ROUND(((ET37)*AV37*1),2)*BB37),2)+ROUND((ROUND(((AE37-(EU37))*AV37*1),2)*BS37),2)) -> 0 | CS37: =(ROUND((ROUND(((EU37)*AV37*1),2)*BS37),2)+ROUND((ROUND(((AE37-(EU37))*AV37*1),2)*BS37),2)) -> 0 | CT37: =ROUND((ROUND((AF37*AV37*1),2)*BA37),2) -> 0 | CU37: =AG37 -> 0 | CV37: =(AH37*AV37) -> 0 | CW37: =AI37 -> 0 | CX37: =AJ37 -> 0 | CY37: =(ROUND((((S37+ROUND((ROUND(((EU37)*AV37*1),2)*BS37),2))*AT37)/100),2)+ROUND(((ROUND((ROUND(((AE37-(EU37))*AV37*1),2)*BS37),2)*AT37)/100),2)) -> 0 | CZ37: =(ROUND((((S37+ROUND((ROUND(((EU37)*AV37*1),2)*BS37),2))*AU37)/100),2)+ROUND(((ROUND((ROUND(((AE37-(EU37))*AV37*1),2)*BS37),2)*AU37)/100),2)) -> 0 | DN37: 0 | DO37: 0 | DP37: 1 | DQ37: 1 | DU37: 1013 | DV37: ШТ | DW37: ШТ | DX37: 1 | EE37: 56938434 | EF37: 214 | EG37: Оборудование, отсутствующие в СНБ | EH37: 0 | EJ37: 3 | EK37: 400007 | EL37: Оборудование, отсутствующие в СНБ | EM37: Оборуд. КА | EQ37: 131088 | ER37: 0 | ES37: 45981.5 | ET37: 0 | EU37: 0 | EV37: 0 | EW37: 0 | EX37: 0 | EY37: 0 | EZ37: 5 | FC37: 1 | FD37: 18 | FF37: 407400 | FQ37: 0 | FR37: =P37 -> 348079.96 | FS37: 0 | FX37: 0 | FY37: 0 | GA37: [407 400 / 1,22 / 7,57] + 3% Трансп + 1,2% Заг.скл | GD37: 1 | GF37: 1539617914 | GG37: 2 | GH37: 3 | GI37: 3 | GJ37: 0 | GK37: 0 | GL37: =ROUND(IF(AND(BH37=3,BI37=3,FS37<>0),P37,0),2) -> 0 | GM37: =ROUND(O37+X37+Y37,2)+GX37 -> 348079.96 | GN37: =IF(OR(BI37=0,BI37=1),GM37-GX37,0) -> 0 | GO37: =IF(BI37=2,GM37-GX37,0) -> 0 | GP37: =IF(BI37=4,GM37-GX37,0) -> 0 | GR37: 1 | GS37: 1 | GT37: 0 | GV37: =ROUND((GT37),6) -> 0 | GW37: 1 | GX37: =ROUND(HC37*I37,2) -> 0 | HA37: 0 | HB37: 0 | HC37: =GV37*GW37 -> 0 | HE37: 3 | HF37: 1,2 | HS37: 0 | IK37: 0
A38: 17 | B38: 1 | E38: 4 | F38: КА, п.5 | G38: Приточная установка П3 (L=700 м3/ч, Pc=400 Па) | H38: ШТ | I38: 1 | J38: 0 | K38: 1 | O38: =ROUND(CP38,2) -> 64350.39 | P38: =ROUND((ROUND((AC38*AW38*I38),2)*BC38),2) -> 64350.39 | Q38: =(ROUND((ROUND(((ET38)*AV38*I38),2)*BB38),2)+ROUND((ROUND(((AE38-(EU38))*AV38*I38),2)*BS38),2)) -> 0 | R38: =(ROUND((ROUND(((EU38)*AV38*I38),2)*BS38),2)+ROUND((ROUND(((AE38-(EU38))*AV38*I38),2)*BS38),2)) -> 0 | S38: =ROUND((ROUND((AF38*AV38*I38),2)*BA38),2) -> 0 | T38: =ROUND(CU38*I38,2) -> 0 | U38: =CV38*I38 -> 0 | V38: =CW38*I38 -> 0 | W38: =ROUND(CX38*I38,2) -> 0 | X38: =(ROUND((((S38+ROUND((ROUND(((EU38)*AV38*I38),2)*BS38),2))*AT38)/100),2)+ROUND(((ROUND((ROUND(((AE38-(EU38))*AV38*I38),2)*BS38),2)*AT38)/100),2)) -> 0 | Y38: =(ROUND((((S38+ROUND((ROUND(((EU38)*AV38*I38),2)*BS38),2))*AU38)/100),2)+ROUND(((ROUND((ROUND(((AE38-(EU38))*AV38*I38),2)*BS38),2)*AU38)/100),2)) -> 0 | AA38: 56661434 | AB38: =ROUND((AC38+AD38+AF38),6) -> 64350.39 | AC38: =ROUND((ES38),6) -> 64350.39 | AD38: =ROUND((((ET38)-(EU38))+AE38),6) -> 0 | AE38: =ROUND((EU38),6) -> 0 | AF38: =ROUND((EV38),6) -> 0 | AG38: =ROUND((AP38),6) -> 0 | AH38: =(EW38) -> 0 | AI38: =(EX38) -> 0 | AJ38: =(AS38) -> 0 | AK38: 64350.39 | AL38: 64350.39 | AM38: 0 | AN38: 0 | AO38: 0 | AP38: 0 | AQ38: 0 | AR38: 0 | AS38: 0 | AT38: 0 | AU38: 0 | AV38: 1 | AW38: 1 | AZ38: 1 | BA38: 1 | BB38: 1 | BC38: 1 | BH38: 3 | BI38: 3 | BJ38: КА, п.5 | BM38: 400007 | BN38: 0 | BP38: 0 | BQ38: 214 | BR38: 0 | BS38: 1 | BT38: 1 | BU38: 1 | BV38: 1 | BW38: 1 | BX38: 1 | BZ38: 0 | CA38: 0 | CE38: 1566 | CF38: 0 | CG38: 0 | CM38: 0 | CO38: 0 | CP38: =(P38+Q38+S38) -> 64350.39 | CQ38: =ROUND((ROUND((AC38*AW38*1),2)*BC38),2) -> 64350.39 | CR38: =(ROUND((ROUND(((ET38)*AV38*1),2)*BB38),2)+ROUND((ROUND(((AE38-(EU38))*AV38*1),2)*BS38),2)) -> 0 | CS38: =(ROUND((ROUND(((EU38)*AV38*1),2)*BS38),2)+ROUND((ROUND(((AE38-(EU38))*AV38*1),2)*BS38),2)) -> 0 | CT38: =ROUND((ROUND((AF38*AV38*1),2)*BA38),2) -> 0 | CU38: =AG38 -> 0 | CV38: =(AH38*AV38) -> 0 | CW38: =AI38 -> 0 | CX38: =AJ38 -> 0 | CY38: =(ROUND((((S38+ROUND((ROUND(((EU38)*AV38*1),2)*BS38),2))*AT38)/100),2)+ROUND(((ROUND((ROUND(((AE38-(EU38))*AV38*1),2)*BS38),2)*AT38)/100),2)) -> 0 | CZ38: =(ROUND((((S38+ROUND((ROUND(((EU38)*AV38*1),2)*BS38),2))*AU38)/100),2)+ROUND(((ROUND((ROUND(((AE38-(EU38))*AV38*1),2)*BS38),2)*AU38)/100),2)) -> 0 | DN38: 0 | DO38: 0 | DP38: 1 | DQ38: 1 | DU38: 1013 | DV38: ШТ | DW38: ШТ | DX38: 1 | EE38: 56938434 | EF38: 214 | EG38: Оборудование, отсутствующие в СНБ | EH38: 0 | EJ38: 3 | EK38: 400007 | EL38: Оборудование, отсутствующие в СНБ | EM38: Оборуд. КА | EQ38: 131088 | ER38: 0 | ES38: 64350.39 | ET38: 0 | EU38: 0 | EV38: 0 | EW38: 0 | EX38: 0 | EY38: 0 | FQ38: 0 | FR38: =P38 -> 64350.39 | FS38: 0 | FX38: 0 | FY38: 0 | GA38: [570 150 / 1,22 / 7,57] + 3% Трансп + 1,2% Заг.скл | GD38: 1 | GF38: 125658678 | GG38: 2 | GH38: 4 | GI38: -2 | GJ38: 0 | GK38: 0 | GL38: =ROUND(IF(AND(BH38=3,BI38=3,FS38<>0),P38,0),2) -> 0 | GM38: =ROUND(O38+X38+Y38,2)+GX38 -> 64350.39 | GN38: =IF(OR(BI38=0,BI38=1),GM38-GX38,0) -> 0 | GO38: =IF(BI38=2,GM38-GX38,0) -> 0 | GP38: =IF(BI38=4,GM38-GX38,0) -> 0 | GR38: 1 | GS38: 2 | GT38: 0 | GV38: =ROUND((GT38),6) -> 0 | GW38: 1 | GX38: =ROUND(HC38*I38,2) -> 0 | HA38: 0 | HB38: 0 | HC38: =GV38*GW38 -> 0 | HE38: 3 | HF38: 1,2 | HS38: 0 | IK38: 0
A39: 17 | B39: 1 | E39: 4 | F39: КА, п.5 | G39: Приточная установка П3 (L=700 м3/ч, Pc=400 Па) | H39: ШТ | I39: 1 | J39: 0 | K39: 1 | O39: =ROUND(CP39,2) -> 487132.45 | P39: =ROUND((ROUND((AC39*AW39*I39),2)*BC39),2) -> 487132.45 | Q39: =(ROUND((ROUND(((ET39)*AV39*I39),2)*BB39),2)+ROUND((ROUND(((AE39-(EU39))*AV39*I39),2)*BS39),2)) -> 0 | R39: =(ROUND((ROUND(((EU39)*AV39*I39),2)*BS39),2)+ROUND((ROUND(((AE39-(EU39))*AV39*I39),2)*BS39),2)) -> 0 | S39: =ROUND((ROUND((AF39*AV39*I39),2)*BA39),2) -> 0 | T39: =ROUND(CU39*I39,2) -> 0 | U39: =CV39*I39 -> 0 | V39: =CW39*I39 -> 0 | W39: =ROUND(CX39*I39,2) -> 0 | X39: =(ROUND((((S39+ROUND((ROUND(((EU39)*AV39*I39),2)*BS39),2))*AT39)/100),2)+ROUND(((ROUND((ROUND(((AE39-(EU39))*AV39*I39),2)*BS39),2)*AT39)/100),2)) -> 0 | Y39: =(ROUND((((S39+ROUND((ROUND(((EU39)*AV39*I39),2)*BS39),2))*AU39)/100),2)+ROUND(((ROUND((ROUND(((AE39-(EU39))*AV39*I39),2)*BS39),2)*AU39)/100),2)) -> 0 | AA39: 56661436 | AB39: =ROUND((AC39+AD39+AF39),6) -> 64350.39 | AC39: =ROUND((ES39),6) -> 64350.39 | AD39: =ROUND((((ET39)-(EU39))+AE39),6) -> 0 | AE39: =ROUND((EU39),6) -> 0 | AF39: =ROUND((EV39),6) -> 0 | AG39: =ROUND((AP39),6) -> 0 | AH39: =(EW39) -> 0 | AI39: =(EX39) -> 0 | AJ39: =(AS39) -> 0 | AK39: 64350.39 | AL39: 64350.39 | AM39: 0 | AN39: 0 | AO39: 0 | AP39: 0 | AQ39: 0 | AR39: 0 | AS39: 0 | AT39: 0 | AU39: 0 | AV39: 1 | AW39: 1 | AZ39: 1 | BA39: 1 | BB39: 1 | BC39: 7.57 | BH39: 3 | BI39: 3 | BJ39: КА, п.5 | BM39: 400007 | BN39: 0 | BP39: 0 | BQ39: 214 | BR39: 0 | BS39: 1 | BT39: 1 | BU39: 1 | BV39: 1 | BW39: 1 | BX39: 1 | BZ39: 0 | CA39: 0 | CE39: 1566 | CF39: 0 | CG39: 0 | CM39: 0 | CO39: 0 | CP39: =(P39+Q39+S39) -> 487132.45 | CQ39: =ROUND((ROUND((AC39*AW39*1),2)*BC39),2) -> 487132.45 | CR39: =(ROUND((ROUND(((ET39)*AV39*1),2)*BB39),2)+ROUND((ROUND(((AE39-(EU39))*AV39*1),2)*BS39),2)) -> 0 | CS39: =(ROUND((ROUND(((EU39)*AV39*1),2)*BS39),2)+ROUND((ROUND(((AE39-(EU39))*AV39*1),2)*BS39),2)) -> 0 | CT39: =ROUND((ROUND((AF39*AV39*1),2)*BA39),2) -> 0 | CU39: =AG39 -> 0 | CV39: =(AH39*AV39) -> 0 | CW39: =AI39 -> 0 | CX39: =AJ39 -> 0 | CY39: =(ROUND((((S39+ROUND((ROUND(((EU39)*AV39*1),2)*BS39),2))*AT39)/100),2)+ROUND(((ROUND((ROUND(((AE39-(EU39))*AV39*1),2)*BS39),2)*AT39)/100),2)) -> 0 | CZ39: =(ROUND((((S39+ROUND((ROUND(((EU39)*AV39*1),2)*BS39),2))*AU39)/100),2)+ROUND(((ROUND((ROUND(((AE39-(EU39))*AV39*1),2)*BS39),2)*AU39)/100),2)) -> 0 | DN39: 0 | DO39: 0 | DP39: 1 | DQ39: 1 | DU39: 1013 | DV39: ШТ | DW39: ШТ | DX39: 1 | EE39: 56938434 | EF39: 214 | EG39: Оборудование, отсутствующие в СНБ | EH39: 0 | EJ39: 3 | EK39: 400007 | EL39: Оборудование, отсутствующие в СНБ | EM39: Оборуд. КА | EQ39: 131088 | ER39: 0 | ES39: 64350.39 | ET39: 0 | EU39: 0 | EV39: 0 | EW39: 0 | EX39: 0 | EY39: 0 | EZ39: 5 | FC39: 1 | FD39: 18 | FF39: 570150 | FQ39: 0 | FR39: =P39 -> 487132.45 | FS39: 0 | FX39: 0 | FY39: 0 | GA39: [570 150 / 1,22 / 7,57] + 3% Трансп + 1,2% Заг.скл | GD39: 1 | GF39: 125658678 | GG39: 2 | GH39: 3 | GI39: 3 | GJ39: 0 | GK39: 0 | GL39: =ROUND(IF(AND(BH39=3,BI39=3,FS39<>0),P39,0),2) -> 0 | GM39: =ROUND(O39+X39+Y39,2)+GX39 -> 487132.45 | GN39: =IF(OR(BI39=0,BI39=1),GM39-GX39,0) -> 0 | GO39: =IF(BI39=2,GM39-GX39,0) -> 0 | GP39: =IF(BI39=4,GM39-GX39,0) -> 0 | GR39: 1 | GS39: 1 | GT39: 0 | GV39: =ROUND((GT39),6) -> 0 | GW39: 1 | GX39: =ROUND(HC39*I39,2) -> 0 | HA39: 0 | HB39: 0 | HC39: =GV39*GW39 -> 0 | HE39: 3 | HF39: 1,2 | HS39: 0 | IK39: 0
A40: 17 | B40: 1 | E40: 5 | F40: КА, п.7 | G40: Приточная установка П4 (L=4970 м3/ч, Pc=500 Па) | H40: ШТ | I40: 1 | J40: 0 | K40: 1 | O40: =ROUND(CP40,2) -> 59491.52 | P40: =ROUND((ROUND((AC40*AW40*I40),2)*BC40),2) -> 59491.52 | Q40: =(ROUND((ROUND(((ET40)*AV40*I40),2)*BB40),2)+ROUND((ROUND(((AE40-(EU40))*AV40*I40),2)*BS40),2)) -> 0 | R40: =(ROUND((ROUND(((EU40)*AV40*I40),2)*BS40),2)+ROUND((ROUND(((AE40-(EU40))*AV40*I40),2)*BS40),2)) -> 0 | S40: =ROUND((ROUND((AF40*AV40*I40),2)*BA40),2) -> 0 | T40: =ROUND(CU40*I40,2) -> 0 | U40: =CV40*I40 -> 0 | V40: =CW40*I40 -> 0 | W40: =ROUND(CX40*I40,2) -> 0 | X40: =(ROUND((((S40+ROUND((ROUND(((EU40)*AV40*I40),2)*BS40),2))*AT40)/100),2)+ROUND(((ROUND((ROUND(((AE40-(EU40))*AV40*I40),2)*BS40),2)*AT40)/100),2)) -> 0 | Y40: =(ROUND((((S40+ROUND((ROUND(((EU40)*AV40*I40),2)*BS40),2))*AU40)/100),2)+ROUND(((ROUND((ROUND(((AE40-(EU40))*AV40*I40),2)*BS40),2)*AU40)/100),2)) -> 0 | AA40: 56661434 | AB40: =ROUND((AC40+AD40+AF40),6) -> 59491.52 | AC40: =ROUND((ES40),6) -> 59491.52 | AD40: =ROUND((((ET40)-(EU40))+AE40),6) -> 0 | AE40: =ROUND((EU40),6) -> 0 | AF40: =ROUND((EV40),6) -> 0 | AG40: =ROUND((AP40),6) -> 0 | AH40: =(EW40) -> 0 | AI40: =(EX40) -> 0 | AJ40: =(AS40) -> 0 | AK40: 59491.52 | AL40: 59491.52 | AM40: 0 | AN40: 0 | AO40: 0 | AP40: 0 | AQ40: 0 | AR40: 0 | AS40: 0 | AT40: 0 | AU40: 0 | AV40: 1 | AW40: 1 | AZ40: 1 | BA40: 1 | BB40: 1 | BC40: 1 | BH40: 3 | BI40: 3 | BJ40: КА, п.7 | BM40: 400007 | BN40: 0 | BP40: 0 | BQ40: 214 | BR40: 0 | BS40: 1 | BT40: 1 | BU40: 1 | BV40: 1 | BW40: 1 | BX40: 1 | BZ40: 0 | CA40: 0 | CE40: 1566 | CF40: 0 | CG40: 0 | CM40: 0 | CO40: 0 | CP40: =(P40+Q40+S40) -> 59491.52 | CQ40: =ROUND((ROUND((AC40*AW40*1),2)*BC40),2) -> 59491.52 | CR40: =(ROUND((ROUND(((ET40)*AV40*1),2)*BB40),2)+ROUND((ROUND(((AE40-(EU40))*AV40*1),2)*BS40),2)) -> 0 | CS40: =(ROUND((ROUND(((EU40)*AV40*1),2)*BS40),2)+ROUND((ROUND(((AE40-(EU40))*AV40*1),2)*BS40),2)) -> 0 | CT40: =ROUND((ROUND((AF40*AV40*1),2)*BA40),2) -> 0 | CU40: =AG40 -> 0 | CV40: =(AH40*AV40) -> 0 | CW40: =AI40 -> 0 | CX40: =AJ40 -> 0 | CY40: =(ROUND((((S40+ROUND((ROUND(((EU40)*AV40*1),2)*BS40),2))*AT40)/100),2)+ROUND(((ROUND((ROUND(((AE40-(EU40))*AV40*1),2)*BS40),2)*AT40)/100),2)) -> 0 | CZ40: =(ROUND((((S40+ROUND((ROUND(((EU40)*AV40*1),2)*BS40),2))*AU40)/100),2)+ROUND(((ROUND((ROUND(((AE40-(EU40))*AV40*1),2)*BS40),2)*AU40)/100),2)) -> 0 | DN40: 0 | DO40: 0 | DP40: 1 | DQ40: 1 | DU40: 1013 | DV40: ШТ | DW40: ШТ | DX40: 1 | EE40: 56938434 | EF40: 214 | EG40: Оборудование, отсутствующие в СНБ | EH40: 0 | EJ40: 3 | EK40: 400007 | EL40: Оборудование, отсутствующие в СНБ | EM40: Оборуд. КА | EQ40: 131088 | ER40: 0 | ES40: 59491.52 | ET40: 0 | EU40: 0 | EV40: 0 | EW40: 0 | EX40: 0 | EY40: 0 | FQ40: 0 | FR40: =P40 -> 59491.52 | FS40: 0 | FX40: 0 | FY40: 0 | GA40: [527 100 / 1,22 / 7,57] + 3% Трансп + 1,2% Заг.скл | GD40: 1 | GF40: -585811463 | GG40: 2 | GH40: 4 | GI40: -2 | GJ40: 0 | GK40: 0 | GL40: =ROUND(IF(AND(BH40=3,BI40=3,FS40<>0),P40,0),2) -> 0 | GM40: =ROUND(O40+X40+Y40,2)+GX40 -> 59491.52 | GN40: =IF(OR(BI40=0,BI40=1),GM40-GX40,0) -> 0 | GO40: =IF(BI40=2,GM40-GX40,0) -> 0 | GP40: =IF(BI40=4,GM40-GX40,0) -> 0 | GR40: 1 | GS40: 2 | GT40: 0 | GV40: =ROUND((GT40),6) -> 0 | GW40: 1 | GX40: =ROUND(HC40*I40,2) -> 0 | HA40: 0 | HB40: 0 | HC40: =GV40*GW40 -> 0 | HE40: 3 | HF40: 1,2 | HS40: 0 | IK40: 0
A41: 17 | B41: 1 | E41: 5 | F41: КА, п.7 | G41: Приточная установка П4 (L=4970 м3/ч, Pc=500 Па) | H41: ШТ | I41: 1 | J41: 0 | K41: 1 | O41: =ROUND(CP41,2) -> 450350.81 | P41: =ROUND((ROUND((AC41*AW41*I41),2)*BC41),2) -> 450350.81 | Q41: =(ROUND((ROUND(((ET41)*AV41*I41),2)*BB41),2)+ROUND((ROUND(((AE41-(EU41))*AV41*I41),2)*BS41),2)) -> 0 | R41: =(ROUND((ROUND(((EU41)*AV41*I41),2)*BS41),2)+ROUND((ROUND(((AE41-(EU41))*AV41*I41),2)*BS41),2)) -> 0 | S41: =ROUND((ROUND((AF41*AV41*I41),2)*BA41),2) -> 0 | T41: =ROUND(CU41*I41,2) -> 0 | U41: =CV41*I41 -> 0 | V41: =CW41*I41 -> 0 | W41: =ROUND(CX41*I41,2) -> 0 | X41: =(ROUND((((S41+ROUND((ROUND(((EU41)*AV41*I41),2)*BS41),2))*AT41)/100),2)+ROUND(((ROUND((ROUND(((AE41-(EU41))*AV41*I41),2)*BS41),2)*AT41)/100),2)) -> 0 | Y41: =(ROUND((((S41+ROUND((ROUND(((EU41)*AV41*I41),2)*BS41),2))*AU41)/100),2)+ROUND(((ROUND((ROUND(((AE41-(EU41))*AV41*I41),2)*BS41),2)*AU41)/100),2)) -> 0 | AA41: 56661436 | AB41: =ROUND((AC41+AD41+AF41),6) -> 59491.52 | AC41: =ROUND((ES41),6) -> 59491.52 | AD41: =ROUND((((ET41)-(EU41))+AE41),6) -> 0 | AE41: =ROUND((EU41),6) -> 0 | AF41: =ROUND((EV41),6) -> 0 | AG41: =ROUND((AP41),6) -> 0 | AH41: =(EW41) -> 0 | AI41: =(EX41) -> 0 | AJ41: =(AS41) -> 0 | AK41: 59491.52 | AL41: 59491.52 | AM41: 0 | AN41: 0 | AO41: 0 | AP41: 0 | AQ41: 0 | AR41: 0 | AS41: 0 | AT41: 0 | AU41: 0 | AV41: 1 | AW41: 1 | AZ41: 1 | BA41: 1 | BB41: 1 | BC41: 7.57 | BH41: 3 | BI41: 3 | BJ41: КА, п.7 | BM41: 400007 | BN41: 0 | BP41: 0 | BQ41: 214 | BR41: 0 | BS41: 1 | BT41: 1 | BU41: 1 | BV41: 1 | BW41: 1 | BX41: 1 | BZ41: 0 | CA41: 0 | CE41: 1566 | CF41: 0 | CG41: 0 | CM41: 0 | CO41: 0 | CP41: =(P41+Q41+S41) -> 450350.81 | CQ41: =ROUND((ROUND((AC41*AW41*1),2)*BC41),2) -> 450350.81 | CR41: =(ROUND((ROUND(((ET41)*AV41*1),2)*BB41),2)+ROUND((ROUND(((AE41-(EU41))*AV41*1),2)*BS41),2)) -> 0 | CS41: =(ROUND((ROUND(((EU41)*AV41*1),2)*BS41),2)+ROUND((ROUND(((AE41-(EU41))*AV41*1),2)*BS41),2)) -> 0 | CT41: =ROUND((ROUND((AF41*AV41*1),2)*BA41),2) -> 0 | CU41: =AG41 -> 0 | CV41: =(AH41*AV41) -> 0 | CW41: =AI41 -> 0 | CX41: =AJ41 -> 0 | CY41: =(ROUND((((S41+ROUND((ROUND(((EU41)*AV41*1),2)*BS41),2))*AT41)/100),2)+ROUND(((ROUND((ROUND(((AE41-(EU41))*AV41*1),2)*BS41),2)*AT41)/100),2)) -> 0 | CZ41: =(ROUND((((S41+ROUND((ROUND(((EU41)*AV41*1),2)*BS41),2))*AU41)/100),2)+ROUND(((ROUND((ROUND(((AE41-(EU41))*AV41*1),2)*BS41),2)*AU41)/100),2)) -> 0 | DN41: 0 | DO41: 0 | DP41: 1 | DQ41: 1 | DU41: 1013 | DV41: ШТ | DW41: ШТ | DX41: 1 | EE41: 56938434 | EF41: 214 | EG41: Оборудование, отсутствующие в СНБ | EH41: 0 | EJ41: 3 | EK41: 400007 | EL41: Оборудование, отсутствующие в СНБ | EM41: Оборуд. КА | EQ41: 131088 | ER41: 0 | ES41: 59491.52 | ET41: 0 | EU41: 0 | EV41: 0 | EW41: 0 | EX41: 0 | EY41: 0 | EZ41: 5 | FC41: 1 | FD41: 18 | FF41: 527100 | FQ41: 0 | FR41: =P41 -> 450350.81 | FS41: 0 | FX41: 0 | FY41: 0 | GA41: [527 100 / 1,22 / 7,57] + 3% Трансп + 1,2% Заг.скл | GD41: 1 | GF41: -585811463 | GG41: 2 | GH41: 3 | GI41: 3 | GJ41: 0 | GK41: 0 | GL41: =ROUND(IF(AND(BH41=3,BI41=3,FS41<>0),P41,0),2) -> 0 | GM41: =ROUND(O41+X41+Y41,2)+GX41 -> 450350.81 | GN41: =IF(OR(BI41=0,BI41=1),GM41-GX41,0) -> 0 | GO41: =IF(BI41=2,GM41-GX41,0) -> 0 | GP41: =IF(BI41=4,GM41-GX41,0) -> 0 | GR41: 1 | GS41: 1 | GT41: 0 | GV41: =ROUND((GT41),6) -> 0 | GW41: 1 | GX41: =ROUND(HC41*I41,2) -> 0 | HA41: 0 | HB41: 0 | HC41: =GV41*GW41 -> 0 | HE41: 3 | HF41: 1,2 | HS41: 0 | IK41: 0
A42: 17 | B42: 1 | E42: 6 | F42: КА, п.8 | G42: Приточная установка П5 (L=8010 м3/ч, Pc=700 Па) | H42: ШТ | I42: 1 | J42: 0 | K42: 1 | O42: =ROUND(CP42,2) -> 143952.88 | P42: =ROUND((ROUND((AC42*AW42*I42),2)*BC42),2) -> 143952.88 | Q42: =(ROUND((ROUND(((ET42)*AV42*I42),2)*BB42),2)+ROUND((ROUND(((AE42-(EU42))*AV42*I42),2)*BS42),2)) -> 0 | R42: =(ROUND((ROUND(((EU42)*AV42*I42),2)*BS42),2)+ROUND((ROUND(((AE42-(EU42))*AV42*I42),2)*BS42),2)) -> 0 | S42: =ROUND((ROUND((AF42*AV42*I42),2)*BA42),2) -> 0 | T42: =ROUND(CU42*I42,2) -> 0 | U42: =CV42*I42 -> 0 | V42: =CW42*I42 -> 0 | W42: =ROUND(CX42*I42,2) -> 0 | X42: =(ROUND((((S42+ROUND((ROUND(((EU42)*AV42*I42),2)*BS42),2))*AT42)/100),2)+ROUND(((ROUND((ROUND(((AE42-(EU42))*AV42*I42),2)*BS42),2)*AT42)/100),2)) -> 0 | Y42: =(ROUND((((S42+ROUND((ROUND(((EU42)*AV42*I42),2)*BS42),2))*AU42)/100),2)+ROUND(((ROUND((ROUND(((AE42-(EU42))*AV42*I42),2)*BS42),2)*AU42)/100),2)) -> 0 | AA42: 56661434 | AB42: =ROUND((AC42+AD42+AF42),6) -> 143952.88 | AC42: =ROUND((ES42),6) -> 143952.88 | AD42: =ROUND((((ET42)-(EU42))+AE42),6) -> 0 | AE42: =ROUND((EU42),6) -> 0 | AF42: =ROUND((EV42),6) -> 0 | AG42: =ROUND((AP42),6) -> 0 | AH42: =(EW42) -> 0 | AI42: =(EX42) -> 0 | AJ42: =(AS42) -> 0 | AK42: 143952.88 | AL42: 143952.88 | AM42: 0 | AN42: 0 | AO42: 0 | AP42: 0 | AQ42: 0 | AR42: 0 | AS42: 0 | AT42: 0 | AU42: 0 | AV42: 1 | AW42: 1 | AZ42: 1 | BA42: 1 | BB42: 1 | BC42: 1 | BH42: 3 | BI42: 3 | BJ42: КА, п.8 | BM42: 400007 | BN42: 0 | BP42: 0 | BQ42: 214 | BR42: 0 | BS42: 1 | BT42: 1 | BU42: 1 | BV42: 1 | BW42: 1 | BX42: 1 | BZ42: 0 | CA42: 0 | CE42: 1566 | CF42: 0 | CG42: 0 | CM42: 0 | CO42: 0 | CP42: =(P42+Q42+S42) -> 143952.88 | CQ42: =ROUND((ROUND((AC42*AW42*1),2)*BC42),2) -> 143952.88 | CR42: =(ROUND((ROUND(((ET42)*AV42*1),2)*BB42),2)+ROUND((ROUND(((AE42-(EU42))*AV42*1),2)*BS42),2)) -> 0 | CS42: =(ROUND((ROUND(((EU42)*AV42*1),2)*BS42),2)+ROUND((ROUND(((AE42-(EU42))*AV42*1),2)*BS42),2)) -> 0 | CT42: =ROUND((ROUND((AF42*AV42*1),2)*BA42),2) -> 0 | CU42: =AG42 -> 0 | CV42: =(AH42*AV42) -> 0 | CW42: =AI42 -> 0 | CX42: =AJ42 -> 0 | CY42: =(ROUND((((S42+ROUND((ROUND(((EU42)*AV42*1),2)*BS42),2))*AT42)/100),2)+ROUND(((ROUND((ROUND(((AE42-(EU42))*AV42*1),2)*BS42),2)*AT42)/100),2)) -> 0 | CZ42: =(ROUND((((S42+ROUND((ROUND(((EU42)*AV42*1),2)*BS42),2))*AU42)/100),2)+ROUND(((ROUND((ROUND(((AE42-(EU42))*AV42*1),2)*BS42),2)*AU42)/100),2)) -> 0 | DN42: 0 | DO42: 0 | DP42: 1 | DQ42: 1 | DU42: 1013 | DV42: ШТ | DW42: ШТ | DX42: 1 | EE42: 56938434 | EF42: 214 | EG42: Оборудование, отсутствующие в СНБ | EH42: 0 | EJ42: 3 | EK42: 400007 | EL42: Оборудование, отсутствующие в СНБ | EM42: Оборуд. КА | EQ42: 131088 | ER42: 0 | ES42: 143952.88 | ET42: 0 | EU42: 0 | EV42: 0 | EW42: 0 | EX42: 0 | EY42: 0 | FQ42: 0 | FR42: =P42 -> 143952.88 | FS42: 0 | FX42: 0 | FY42: 0 | GA42: [1 275 435 / 1,22 / 7,57] + 3% Трансп + 1,2% Заг.скл | GD42: 1 | GF42: 1510004595 | GG42: 2 | GH42: 4 | GI42: -2 | GJ42: 0 | GK42: 0 | GL42: =ROUND(IF(AND(BH42=3,BI42=3,FS42<>0),P42,0),2) -> 0 | GM42: =ROUND(O42+X42+Y42,2)+GX42 -> 143952.88 | GN42: =IF(OR(BI42=0,BI42=1),GM42-GX42,0) -> 0 | GO42: =IF(BI42=2,GM42-GX42,0) -> 0 | GP42: =IF(BI42=4,GM42-GX42,0) -> 0 | GR42: 1 | GS42: 2 | GT42: 0 | GV42: =ROUND((GT42),6) -> 0 | GW42: 1 | GX42: =ROUND(HC42*I42,2) -> 0 | HA42: 0 | HB42: 0 | HC42: =GV42*GW42 -> 0 | HE42: 3 | HF42: 1,2 | HS42: 0 | IK42: 0
A43: 17 | B43: 1 | E43: 6 | F43: КА, п.8 | G43: Приточная установка П5 (L=8010 м3/ч, Pc=700 Па) | H43: ШТ | I43: 1 | J43: 0 | K43: 1 | O43: =ROUND(CP43,2) -> 1089723.3 | P43: =ROUND((ROUND((AC43*AW43*I43),2)*BC43),2) -> 1089723.3 | Q43: =(ROUND((ROUND(((ET43)*AV43*I43),2)*BB43),2)+ROUND((ROUND(((AE43-(EU43))*AV43*I43),2)*BS43),2)) -> 0 | R43: =(ROUND((ROUND(((EU43)*AV43*I43),2)*BS43),2)+ROUND((ROUND(((AE43-(EU43))*AV43*I43),2)*BS43),2)) -> 0 | S43: =ROUND((ROUND((AF43*AV43*I43),2)*BA43),2) -> 0 | T43: =ROUND(CU43*I43,2) -> 0 | U43: =CV43*I43 -> 0 | V43: =CW43*I43 -> 0 | W43: =ROUND(CX43*I43,2) -> 0 | X43: =(ROUND((((S43+ROUND((ROUND(((EU43)*AV43*I43),2)*BS43),2))*AT43)/100),2)+ROUND(((ROUND((ROUND(((AE43-(EU43))*AV43*I43),2)*BS43),2)*AT43)/100),2)) -> 0 | Y43: =(ROUND((((S43+ROUND((ROUND(((EU43)*AV43*I43),2)*BS43),2))*AU43)/100),2)+ROUND(((ROUND((ROUND(((AE43-(EU43))*AV43*I43),2)*BS43),2)*AU43)/100),2)) -> 0 | AA43: 56661436 | AB43: =ROUND((AC43+AD43+AF43),6) -> 143952.88 | AC43: =ROUND((ES43),6) -> 143952.88 | AD43: =ROUND((((ET43)-(EU43))+AE43),6) -> 0 | AE43: =ROUND((EU43),6) -> 0 | AF43: =ROUND((EV43),6) -> 0 | AG43: =ROUND((AP43),6) -> 0 | AH43: =(EW43) -> 0 | AI43: =(EX43) -> 0 | AJ43: =(AS43) -> 0 | AK43: 143952.88 | AL43: 143952.88 | AM43: 0 | AN43: 0 | AO43: 0 | AP43: 0 | AQ43: 0 | AR43: 0 | AS43: 0 | AT43: 0 | AU43: 0 | AV43: 1 | AW43: 1 | AZ43: 1 | BA43: 1 | BB43: 1 | BC43: 7.57 | BH43: 3 | BI43: 3 | BJ43: КА, п.8 | BM43: 400007 | BN43: 0 | BP43: 0 | BQ43: 214 | BR43: 0 | BS43: 1 | BT43: 1 | BU43: 1 | BV43: 1 | BW43: 1 | BX43: 1 | BZ43: 0 | CA43: 0 | CE43: 1566 | CF43: 0 | CG43: 0 | CM43: 0 | CO43: 0 | CP43: =(P43+Q43+S43) -> 1089723.3 | CQ43: =ROUND((ROUND((AC43*AW43*1),2)*BC43),2) -> 1089723.3 | CR43: =(ROUND((ROUND(((ET43)*AV43*1),2)*BB43),2)+ROUND((ROUND(((AE43-(EU43))*AV43*1),2)*BS43),2)) -> 0 | CS43: =(ROUND((ROUND(((EU43)*AV43*1),2)*BS43),2)+ROUND((ROUND(((AE43-(EU43))*AV43*1),2)*BS43),2)) -> 0 | CT43: =ROUND((ROUND((AF43*AV43*1),2)*BA43),2) -> 0 | CU43: =AG43 -> 0 | CV43: =(AH43*AV43) -> 0 | CW43: =AI43 -> 0 | CX43: =AJ43 -> 0 | CY43: =(ROUND((((S43+ROUND((ROUND(((EU43)*AV43*1),2)*BS43),2))*AT43)/100),2)+ROUND(((ROUND((ROUND(((AE43-(EU43))*AV43*1),2)*BS43),2)*AT43)/100),2)) -> 0 | CZ43: =(ROUND((((S43+ROUND((ROUND(((EU43)*AV43*1),2)*BS43),2))*AU43)/100),2)+ROUND(((ROUND((ROUND(((AE43-(EU43))*AV43*1),2)*BS43),2)*AU43)/100),2)) -> 0 | DN43: 0 | DO43: 0 | DP43: 1 | DQ43: 1 | DU43: 1013 | DV43: ШТ | DW43: ШТ | DX43: 1 | EE43: 56938434 | EF43: 214 | EG43: Оборудование, отсутствующие в СНБ | EH43: 0 | EJ43: 3 | EK43: 400007 | EL43: Оборудование, отсутствующие в СНБ | EM43: Оборуд. КА | EQ43: 131088 | ER43: 0 | ES43: 143952.88 | ET43: 0 | EU43: 0 | EV43: 0 | EW43: 0 | EX43: 0 | EY43: 0 | EZ43: 5 | FC43: 1 | FD43: 18 | FF43: 1275435 | FQ43: 0 | FR43: =P43 -> 1089723.3 | FS43: 0 | FX43: 0 | FY43: 0 | GA43: [1 275 435 / 1,22 / 7,57] + 3% Трансп + 1,2% Заг.скл | GD43: 1 | GF43: 1510004595 | GG43: 2 | GH43: 3 | GI43: 3 | GJ43: 0 | GK43: 0 | GL43: =ROUND(IF(AND(BH43=3,BI43=3,FS43<>0),P43,0),2) -> 0 | GM43: =ROUND(O43+X43+Y43,2)+GX43 -> 1089723.3 | GN43: =IF(OR(BI43=0,BI43=1),GM43-GX43,0) -> 0 | GO43: =IF(BI43=2,GM43-GX43,0) -> 0 | GP43: =IF(BI43=4,GM43-GX43,0) -> 0 | GR43: 1 | GS43: 1 | GT43: 0 | GV43: =ROUND((GT43),6) -> 0 | GW43: 1 | GX43: =ROUND(HC43*I43,2) -> 0 | HA43: 0 | HB43: 0 | HC43: =GV43*GW43 -> 0 | HE43: 3 | HF43: 1,2 | HS43: 0 | IK43: 0
A44: 17 | B44: 1 | E44: 7 | F44: КА, п.10 | G44: Приточная установка П6 (L=620 м3/ч, Pc=400 Па) | H44: ШТ | I44: 1 | J44: 0 | K44: 1 | O44: =ROUND(CP44,2) -> 31120.46 | P44: =ROUND((ROUND((AC44*AW44*I44),2)*BC44),2) -> 31120.46 | Q44: =(ROUND((ROUND(((ET44)*AV44*I44),2)*BB44),2)+ROUND((ROUND(((AE44-(EU44))*AV44*I44),2)*BS44),2)) -> 0 | R44: =(ROUND((ROUND(((EU44)*AV44*I44),2)*BS44),2)+ROUND((ROUND(((AE44-(EU44))*AV44*I44),2)*BS44),2)) -> 0 | S44: =ROUND((ROUND((AF44*AV44*I44),2)*BA44),2) -> 0 | T44: =ROUND(CU44*I44,2) -> 0 | U44: =CV44*I44 -> 0 | V44: =CW44*I44 -> 0 | W44: =ROUND(CX44*I44,2) -> 0 | X44: =(ROUND((((S44+ROUND((ROUND(((EU44)*AV44*I44),2)*BS44),2))*AT44)/100),2)+ROUND(((ROUND((ROUND(((AE44-(EU44))*AV44*I44),2)*BS44),2)*AT44)/100),2)) -> 0 | Y44: =(ROUND((((S44+ROUND((ROUND(((EU44)*AV44*I44),2)*BS44),2))*AU44)/100),2)+ROUND(((ROUND((ROUND(((AE44-(EU44))*AV44*I44),2)*BS44),2)*AU44)/100),2)) -> 0 | AA44: 56661434 | AB44: =ROUND((AC44+AD44+AF44),6) -> 31120.46 | AC44: =ROUND((ES44),6) -> 31120.46 | AD44: =ROUND((((ET44)-(EU44))+AE44),6) -> 0 | AE44: =ROUND((EU44),6) -> 0 | AF44: =ROUND((EV44),6) -> 0 | AG44: =ROUND((AP44),6) -> 0 | AH44: =(EW44) -> 0 | AI44: =(EX44) -> 0 | AJ44: =(AS44) -> 0 | AK44: 31120.46 | AL44: 31120.46 | AM44: 0 | AN44: 0 | AO44: 0 | AP44: 0 | AQ44: 0 | AR44: 0 | AS44: 0 | AT44: 0 | AU44: 0 | AV44: 1 | AW44: 1 | AZ44: 1 | BA44: 1 | BB44: 1 | BC44: 1 | BH44: 3 | BI44: 3 | BJ44: КА, п.10 | BM44: 400007 | BN44: 0 | BP44: 0 | BQ44: 214 | BR44: 0 | BS44: 1 | BT44: 1 | BU44: 1 | BV44: 1 | BW44: 1 | BX44: 1 | BZ44: 0 | CA44: 0 | CE44: 1566 | CF44: 0 | CG44: 0 | CM44: 0 | CO44: 0 | CP44: =(P44+Q44+S44) -> 31120.46 | CQ44: =ROUND((ROUND((AC44*AW44*1),2)*BC44),2) -> 31120.46 | CR44: =(ROUND((ROUND(((ET44)*AV44*1),2)*BB44),2)+ROUND((ROUND(((AE44-(EU44))*AV44*1),2)*BS44),2)) -> 0 | CS44: =(ROUND((ROUND(((EU44)*AV44*1),2)*BS44),2)+ROUND((ROUND(((AE44-(EU44))*AV44*1),2)*BS44),2)) -> 0 | CT44: =ROUND((ROUND((AF44*AV44*1),2)*BA44),2) -> 0 | CU44: =AG44 -> 0 | CV44: =(AH44*AV44) -> 0 | CW44: =AI44 -> 0 | CX44: =AJ44 -> 0 | CY44: =(ROUND((((S44+ROUND((ROUND(((EU44)*AV44*1),2)*BS44),2))*AT44)/100),2)+ROUND(((ROUND((ROUND(((AE44-(EU44))*AV44*1),2)*BS44),2)*AT44)/100),2)) -> 0 | CZ44: =(ROUND((((S44+ROUND((ROUND(((EU44)*AV44*1),2)*BS44),2))*AU44)/100),2)+ROUND(((ROUND((ROUND(((AE44-(EU44))*AV44*1),2)*BS44),2)*AU44)/100),2)) -> 0 | DN44: 0 | DO44: 0 | DP44: 1 | DQ44: 1 | DU44: 1013 | DV44: ШТ | DW44: ШТ | DX44: 1 | EE44: 56938434 | EF44: 214 | EG44: Оборудование, отсутствующие в СНБ | EH44: 0 | EJ44: 3 | EK44: 400007 | EL44: Оборудование, отсутствующие в СНБ | EM44: Оборуд. КА | EQ44: 131088 | ER44: 0 | ES44: 31120.46 | ET44: 0 | EU44: 0 | EV44: 0 | EW44: 0 | EX44: 0 | EY44: 0 | FQ44: 0 | FR44: =P44 -> 31120.46 | FS44: 0 | FX44: 0 | FY44: 0 | GA44: [275 730 / 1,22 / 7,57] + 3% Трансп + 1,2% Заг.скл | GD44: 1 | GF44: -2046315333 | GG44: 2 | GH44: 4 | GI44: -2 | GJ44: 0 | GK44: 0 | GL44: =ROUND(IF(AND(BH44=3,BI44=3,FS44<>0),P44,0),2) -> 0 | GM44: =ROUND(O44+X44+Y44,2)+GX44 -> 31120.46 | GN44: =IF(OR(BI44=0,BI44=1),GM44-GX44,0) -> 0 | GO44: =IF(BI44=2,GM44-GX44,0) -> 0 | GP44: =IF(BI44=4,GM44-GX44,0) -> 0 | GR44: 1 | GS44: 2 | GT44: 0 | GV44: =ROUND((GT44),6) -> 0 | GW44: 1 | GX44: =ROUND(HC44*I44,2) -> 0 | HA44: 0 | HB44: 0 | HC44: =GV44*GW44 -> 0 | HE44: 3 | HF44: 1,2 | HS44: 0 | IK44: 0
A45: 17 | B45: 1 | E45: 7 | F45: КА, п.10 | G45: Приточная установка П6 (L=620 м3/ч, Pc=400 Па) | H45: ШТ | I45: 1 | J45: 0 | K45: 1 | O45: =ROUND(CP45,2) -> 235581.88 | P45: =ROUND((ROUND((AC45*AW45*I45),2)*BC45),2) -> 235581.88 | Q45: =(ROUND((ROUND(((ET45)*AV45*I45),2)*BB45),2)+ROUND((ROUND(((AE45-(EU45))*AV45*I45),2)*BS45),2)) -> 0 | R45: =(ROUND((ROUND(((EU45)*AV45*I45),2)*BS45),2)+ROUND((ROUND(((AE45-(EU45))*AV45*I45),2)*BS45),2)) -> 0 | S45: =ROUND((ROUND((AF45*AV45*I45),2)*BA45),2) -> 0 | T45: =ROUND(CU45*I45,2) -> 0 | U45: =CV45*I45 -> 0 | V45: =CW45*I45 -> 0 | W45: =ROUND(CX45*I45,2) -> 0 | X45: =(ROUND((((S45+ROUND((ROUND(((EU45)*AV45*I45),2)*BS45),2))*AT45)/100),2)+ROUND(((ROUND((ROUND(((AE45-(EU45))*AV45*I45),2)*BS45),2)*AT45)/100),2)) -> 0 | Y45: =(ROUND((((S45+ROUND((ROUND(((EU45)*AV45*I45),2)*BS45),2))*AU45)/100),2)+ROUND(((ROUND((ROUND(((AE45-(EU45))*AV45*I45),2)*BS45),2)*AU45)/100),2)) -> 0 | AA45: 56661436 | AB45: =ROUND((AC45+AD45+AF45),6) -> 31120.46 | AC45: =ROUND((ES45),6) -> 31120.46 | AD45: =ROUND((((ET45)-(EU45))+AE45),6) -> 0 | AE45: =ROUND((EU45),6) -> 0 | AF45: =ROUND((EV45),6) -> 0 | AG45: =ROUND((AP45),6) -> 0 | AH45: =(EW45) -> 0 | AI45: =(EX45) -> 0 | AJ45: =(AS45) -> 0 | AK45: 31120.46 | AL45: 31120.46 | AM45: 0 | AN45: 0 | AO45: 0 | AP45: 0 | AQ45: 0 | AR45: 0 | AS45: 0 | AT45: 0 | AU45: 0 | AV45: 1 | AW45: 1 | AZ45: 1 | BA45: 1 | BB45: 1 | BC45: 7.57 | BH45: 3 | BI45: 3 | BJ45: КА, п.10 | BM45: 400007 | BN45: 0 | BP45: 0 | BQ45: 214 | BR45: 0 | BS45: 1 | BT45: 1 | BU45: 1 | BV45: 1 | BW45: 1 | BX45: 1 | BZ45: 0 | CA45: 0 | CE45: 1566 | CF45: 0 | CG45: 0 | CM45: 0 | CO45: 0 | CP45: =(P45+Q45+S45) -> 235581.88 | CQ45: =ROUND((ROUND((AC45*AW45*1),2)*BC45),2) -> 235581.88 | CR45: =(ROUND((ROUND(((ET45)*AV45*1),2)*BB45),2)+ROUND((ROUND(((AE45-(EU45))*AV45*1),2)*BS45),2)) -> 0 | CS45: =(ROUND((ROUND(((EU45)*AV45*1),2)*BS45),2)+ROUND((ROUND(((AE45-(EU45))*AV45*1),2)*BS45),2)) -> 0 | CT45: =ROUND((ROUND((AF45*AV45*1),2)*BA45),2) -> 0 | CU45: =AG45 -> 0 | CV45: =(AH45*AV45) -> 0 | CW45: =AI45 -> 0 | CX45: =AJ45 -> 0 | CY45: =(ROUND((((S45+ROUND((ROUND(((EU45)*AV45*1),2)*BS45),2))*AT45)/100),2)+ROUND(((ROUND((ROUND(((AE45-(EU45))*AV45*1),2)*BS45),2)*AT45)/100),2)) -> 0 | CZ45: =(ROUND((((S45+ROUND((ROUND(((EU45)*AV45*1),2)*BS45),2))*AU45)/100),2)+ROUND(((ROUND((ROUND(((AE45-(EU45))*AV45*1),2)*BS45),2)*AU45)/100),2)) -> 0 | DN45: 0 | DO45: 0 | DP45: 1 | DQ45: 1 | DU45: 1013 | DV45: ШТ | DW45: ШТ | DX45: 1 | EE45: 56938434 | EF45: 214 | EG45: Оборудование, отсутствующие в СНБ | EH45: 0 | EJ45: 3 | EK45: 400007 | EL45: Оборудование, отсутствующие в СНБ | EM45: Оборуд. КА | EQ45: 131088 | ER45: 0 | ES45: 31120.46 | ET45: 0 | EU45: 0 | EV45: 0 | EW45: 0 | EX45: 0 | EY45: 0 | EZ45: 5 | FC45: 1 | FD45: 18 | FF45: 275730 | FQ45: 0 | FR45: =P45 -> 235581.88 | FS45: 0 | FX45: 0 | FY45: 0 | GA45: [275 730 / 1,22 / 7,57] + 3% Трансп + 1,2% Заг.скл | GD45: 1 | GF45: -2046315333 | GG45: 2 | GH45: 3 | GI45: 3 | GJ45: 0 | GK45: 0 | GL45: =ROUND(IF(AND(BH45=3,BI45=3,FS45<>0),P45,0),2) -> 0 | GM45: =ROUND(O45+X45+Y45,2)+GX45 -> 235581.88 | GN45: =IF(OR(BI45=0,BI45=1),GM45-GX45,0) -> 0 | GO45: =IF(BI45=2,GM45-GX45,0) -> 0 | GP45: =IF(BI45=4,GM45-GX45,0) -> 0 | GR45: 1 | GS45: 1 | GT45: 0 | GV45: =ROUND((GT45),6) -> 0 | GW45: 1 | GX45: =ROUND(HC45*I45,2) -> 0 | HA45: 0 | HB45: 0 | HC45: =GV45*GW45 -> 0 | HE45: 3 | HF45: 1,2 | HS45: 0 | IK45: 0
A46: 17 | B46: 1 | E46: 8 | F46: КА, п.11 | G46: Приточная установка П7 (L=110 м3/ч, Pc=300 Па) | H46: ШТ | I46: 1 | J46: 0 | K46: 1 | O46: =ROUND(CP46,2) -> 10701.35 | P46: =ROUND((ROUND((AC46*AW46*I46),2)*BC46),2) -> 10701.35 | Q46: =(ROUND((ROUND(((ET46)*AV46*I46),2)*BB46),2)+ROUND((ROUND(((AE46-(EU46))*AV46*I46),2)*BS46),2)) -> 0 | R46: =(ROUND((ROUND(((EU46)*AV46*I46),2)*BS46),2)+ROUND((ROUND(((AE46-(EU46))*AV46*I46),2)*BS46),2)) -> 0 | S46: =ROUND((ROUND((AF46*AV46*I46),2)*BA46),2) -> 0 | T46: =ROUND(CU46*I46,2) -> 0 | U46: =CV46*I46 -> 0 | V46: =CW46*I46 -> 0 | W46: =ROUND(CX46*I46,2) -> 0 | X46: =(ROUND((((S46+ROUND((ROUND(((EU46)*AV46*I46),2)*BS46),2))*AT46)/100),2)+ROUND(((ROUND((ROUND(((AE46-(EU46))*AV46*I46),2)*BS46),2)*AT46)/100),2)) -> 0 | Y46: =(ROUND((((S46+ROUND((ROUND(((EU46)*AV46*I46),2)*BS46),2))*AU46)/100),2)+ROUND(((ROUND((ROUND(((AE46-(EU46))*AV46*I46),2)*BS46),2)*AU46)/100),2)) -> 0 | AA46: 56661434 | AB46: =ROUND((AC46+AD46+AF46),6) -> 10701.35 | AC46: =ROUND((ES46),6) -> 10701.35 | AD46: =ROUND((((ET46)-(EU46))+AE46),6) -> 0 | AE46: =ROUND((EU46),6) -> 0 | AF46: =ROUND((EV46),6) -> 0 | AG46: =ROUND((AP46),6) -> 0 | AH46: =(EW46) -> 0 | AI46: =(EX46) -> 0 | AJ46: =(AS46) -> 0 | AK46: 10701.35 | AL46: 10701.35 | AM46: 0 | AN46: 0 | AO46: 0 | AP46: 0 | AQ46: 0 | AR46: 0 | AS46: 0 | AT46: 0 | AU46: 0 | AV46: 1 | AW46: 1 | AZ46: 1 | BA46: 1 | BB46: 1 | BC46: 1 | BH46: 3 | BI46: 3 | BJ46: КА, п.11 | BM46: 400007 | BN46: 0 | BP46: 0 | BQ46: 214 | BR46: 0 | BS46: 1 | BT46: 1 | BU46: 1 | BV46: 1 | BW46: 1 | BX46: 1 | BZ46: 0 | CA46: 0 | CE46: 1566 | CF46: 0 | CG46: 0 | CM46: 0 | CO46: 0 | CP46: =(P46+Q46+S46) -> 10701.35 | CQ46: =ROUND((ROUND((AC46*AW46*1),2)*BC46),2) -> 10701.35 | CR46: =(ROUND((ROUND(((ET46)*AV46*1),2)*BB46),2)+ROUND((ROUND(((AE46-(EU46))*AV46*1),2)*BS46),2)) -> 0 | CS46: =(ROUND((ROUND(((EU46)*AV46*1),2)*BS46),2)+ROUND((ROUND(((AE46-(EU46))*AV46*1),2)*BS46),2)) -> 0 | CT46: =ROUND((ROUND((AF46*AV46*1),2)*BA46),2) -> 0 | CU46: =AG46 -> 0 | CV46: =(AH46*AV46) -> 0 | CW46: =AI46 -> 0 | CX46: =AJ46 -> 0 | CY46: =(ROUND((((S46+ROUND((ROUND(((EU46)*AV46*1),2)*BS46),2))*AT46)/100),2)+ROUND(((ROUND((ROUND(((AE46-(EU46))*AV46*1),2)*BS46),2)*AT46)/100),2)) -> 0 | CZ46: =(ROUND((((S46+ROUND((ROUND(((EU46)*AV46*1),2)*BS46),2))*AU46)/100),2)+ROUND(((ROUND((ROUND(((AE46-(EU46))*AV46*1),2)*BS46),2)*AU46)/100),2)) -> 0 | DN46: 0 | DO46: 0 | DP46: 1 | DQ46: 1 | DU46: 1013 | DV46: ШТ | DW46: ШТ | DX46: 1 | EE46: 56938434 | EF46: 214 | EG46: Оборудование, отсутствующие в СНБ | EH46: 0 | EJ46: 3 | EK46: 400007 | EL46: Оборудование, отсутствующие в СНБ | EM46: Оборуд. КА | EQ46: 131088 | ER46: 0 | ES46: 10701.35 | ET46: 0 | EU46: 0 | EV46: 0 | EW46: 0 | EX46: 0 | EY46: 0 | FQ46: 0 | FR46: =P46 -> 10701.35 | FS46: 0 | FX46: 0 | FY46: 0 | GA46: [94 815 / 1,22 / 7,57] + 3% Трансп + 1,2% Заг.скл | GD46: 1 | GF46: -1635317556 | GG46: 2 | GH46: 4 | GI46: -2 | GJ46: 0 | GK46: 0 | GL46: =ROUND(IF(AND(BH46=3,BI46=3,FS46<>0),P46,0),2) -> 0 | GM46: =ROUND(O46+X46+Y46,2)+GX46 -> 10701.35 | GN46: =IF(OR(BI46=0,BI46=1),GM46-GX46,0) -> 0 | GO46: =IF(BI46=2,GM46-GX46,0) -> 0 | GP46: =IF(BI46=4,GM46-GX46,0) -> 0 | GR46: 1 | GS46: 2 | GT46: 0 | GV46: =ROUND((GT46),6) -> 0 | GW46: 1 | GX46: =ROUND(HC46*I46,2) -> 0 | HA46: 0 | HB46: 0 | HC46: =GV46*GW46 -> 0 | HE46: 3 | HF46: 1,2 | HS46: 0 | IK46: 0
A47: 17 | B47: 1 | E47: 8 | F47: КА, п.11 | G47: Приточная установка П7 (L=110 м3/ч, Pc=300 Па) | H47: ШТ | I47: 1 | J47: 0 | K47: 1 | O47: =ROUND(CP47,2) -> 81009.22 | P47: =ROUND((ROUND((AC47*AW47*I47),2)*BC47),2) -> 81009.22 | Q47: =(ROUND((ROUND(((ET47)*AV47*I47),2)*BB47),2)+ROUND((ROUND(((AE47-(EU47))*AV47*I47),2)*BS47),2)) -> 0 | R47: =(ROUND((ROUND(((EU47)*AV47*I47),2)*BS47),2)+ROUND((ROUND(((AE47-(EU47))*AV47*I47),2)*BS47),2)) -> 0 | S47: =ROUND((ROUND((AF47*AV47*I47),2)*BA47),2) -> 0 | T47: =ROUND(CU47*I47,2) -> 0 | U47: =CV47*I47 -> 0 | V47: =CW47*I47 -> 0 | W47: =ROUND(CX47*I47,2) -> 0 | X47: =(ROUND((((S47+ROUND((ROUND(((EU47)*AV47*I47),2)*BS47),2))*AT47)/100),2)+ROUND(((ROUND((ROUND(((AE47-(EU47))*AV47*I47),2)*BS47),2)*AT47)/100),2)) -> 0 | Y47: =(ROUND((((S47+ROUND((ROUND(((EU47)*AV47*I47),2)*BS47),2))*AU47)/100),2)+ROUND(((ROUND((ROUND(((AE47-(EU47))*AV47*I47),2)*BS47),2)*AU47)/100),2)) -> 0 | AA47: 56661436 | AB47: =ROUND((AC47+AD47+AF47),6) -> 10701.35 | AC47: =ROUND((ES47),6) -> 10701.35 | AD47: =ROUND((((ET47)-(EU47))+AE47),6) -> 0 | AE47: =ROUND((EU47),6) -> 0 | AF47: =ROUND((EV47),6) -> 0 | AG47: =ROUND((AP47),6) -> 0 | AH47: =(EW47) -> 0 | AI47: =(EX47) -> 0 | AJ47: =(AS47) -> 0 | AK47: 10701.35 | AL47: 10701.35 | AM47: 0 | AN47: 0 | AO47: 0 | AP47: 0 | AQ47: 0 | AR47: 0 | AS47: 0 | AT47: 0 | AU47: 0 | AV47: 1 | AW47: 1 | AZ47: 1 | BA47: 1 | BB47: 1 | BC47: 7.57 | BH47: 3 | BI47: 3 | BJ47: КА, п.11 | BM47: 400007 | BN47: 0 | BP47: 0 | BQ47: 214 | BR47: 0 | BS47: 1 | BT47: 1 | BU47: 1 | BV47: 1 | BW47: 1 | BX47: 1 | BZ47: 0 | CA47: 0 | CE47: 1566 | CF47: 0 | CG47: 0 | CM47: 0 | CO47: 0 | CP47: =(P47+Q47+S47) -> 81009.22 | CQ47: =ROUND((ROUND((AC47*AW47*1),2)*BC47),2) -> 81009.22 | CR47: =(ROUND((ROUND(((ET47)*AV47*1),2)*BB47),2)+ROUND((ROUND(((AE47-(EU47))*AV47*1),2)*BS47),2)) -> 0 | CS47: =(ROUND((ROUND(((EU47)*AV47*1),2)*BS47),2)+ROUND((ROUND(((AE47-(EU47))*AV47*1),2)*BS47),2)) -> 0 | CT47: =ROUND((ROUND((AF47*AV47*1),2)*BA47),2) -> 0 | CU47: =AG47 -> 0 | CV47: =(AH47*AV47) -> 0 | CW47: =AI47 -> 0 | CX47: =AJ47 -> 0 | CY47: =(ROUND((((S47+ROUND((ROUND(((EU47)*AV47*1),2)*BS47),2))*AT47)/100),2)+ROUND(((ROUND((ROUND(((AE47-(EU47))*AV47*1),2)*BS47),2)*AT47)/100),2)) -> 0 | CZ47: =(ROUND((((S47+ROUND((ROUND(((EU47)*AV47*1),2)*BS47),2))*AU47)/100),2)+ROUND(((ROUND((ROUND(((AE47-(EU47))*AV47*1),2)*BS47),2)*AU47)/100),2)) -> 0 | DN47: 0 | DO47: 0 | DP47: 1 | DQ47: 1 | DU47: 1013 | DV47: ШТ | DW47: ШТ | DX47: 1 | EE47: 56938434 | EF47: 214 | EG47: Оборудование, отсутствующие в СНБ | EH47: 0 | EJ47: 3 | EK47: 400007 | EL47: Оборудование, отсутствующие в СНБ | EM47: Оборуд. КА | EQ47: 131088 | ER47: 0 | ES47: 10701.35 | ET47: 0 | EU47: 0 | EV47: 0 | EW47: 0 | EX47: 0 | EY47: 0 | EZ47: 5 | FC47: 1 | FD47: 18 | FF47: 94815 | FQ47: 0 | FR47: =P47 -> 81009.22 | FS47: 0 | FX47: 0 | FY47: 0 | GA47: [94 815 / 1,22 / 7,57] + 3% Трансп + 1,2% Заг.скл | GD47: 1 | GF47: -1635317556 | GG47: 2 | GH47: 3 | GI47: 3 | GJ47: 0 | GK47: 0 | GL47: =ROUND(IF(AND(BH47=3,BI47=3,FS47<>0),P47,0),2) -> 0 | GM47: =ROUND(O47+X47+Y47,2)+GX47 -> 81009.22 | GN47: =IF(OR(BI47=0,BI47=1),GM47-GX47,0) -> 0 | GO47: =IF(BI47=2,GM47-GX47,0) -> 0 | GP47: =IF(BI47=4,GM47-GX47,0) -> 0 | GR47: 1 | GS47: 1 | GT47: 0 | GV47: =ROUND((GT47),6) -> 0 | GW47: 1 | GX47: =ROUND(HC47*I47,2) -> 0 | HA47: 0 | HB47: 0 | HC47: =GV47*GW47 -> 0 | HE47: 3 | HF47: 1,2 | HS47: 0 | IK47: 0
A48: 17 | B48: 1 | E48: 9 | F48: КА, п.12 | G48: Приточная установка П8 (L=1540 м3/ч, Pc=400 Па) | H48: ШТ | I48: 1 | J48: 0 | K48: 1 | O48: =ROUND(CP48,2) -> 34249.11 | P48: =ROUND((ROUND((AC48*AW48*I48),2)*BC48),2) -> 34249.11 | Q48: =(ROUND((ROUND(((ET48)*AV48*I48),2)*BB48),2)+ROUND((ROUND(((AE48-(EU48))*AV48*I48),2)*BS48),2)) -> 0 | R48: =(ROUND((ROUND(((EU48)*AV48*I48),2)*BS48),2)+ROUND((ROUND(((AE48-(EU48))*AV48*I48),2)*BS48),2)) -> 0 | S48: =ROUND((ROUND((AF48*AV48*I48),2)*BA48),2) -> 0 | T48: =ROUND(CU48*I48,2) -> 0 | U48: =CV48*I48 -> 0 | V48: =CW48*I48 -> 0 | W48: =ROUND(CX48*I48,2) -> 0 | X48: =(ROUND((((S48+ROUND((ROUND(((EU48)*AV48*I48),2)*BS48),2))*AT48)/100),2)+ROUND(((ROUND((ROUND(((AE48-(EU48))*AV48*I48),2)*BS48),2)*AT48)/100),2)) -> 0 | Y48: =(ROUND((((S48+ROUND((ROUND(((EU48)*AV48*I48),2)*BS48),2))*AU48)/100),2)+ROUND(((ROUND((ROUND(((AE48-(EU48))*AV48*I48),2)*BS48),2)*AU48)/100),2)) -> 0 | AA48: 56661434 | AB48: =ROUND((AC48+AD48+AF48),6) -> 34249.11 | AC48: =ROUND((ES48),6) -> 34249.11 | AD48: =ROUND((((ET48)-(EU48))+AE48),6) -> 0 | AE48: =ROUND((EU48),6) -> 0 | AF48: =ROUND((EV48),6) -> 0 | AG48: =ROUND((AP48),6) -> 0 | AH48: =(EW48) -> 0 | AI48: =(EX48) -> 0 | AJ48: =(AS48) -> 0 | AK48: 34249.11 | AL48: 34249.11 | AM48: 0 | AN48: 0 | AO48: 0 | AP48: 0 | AQ48: 0 | AR48: 0 | AS48: 0 | AT48: 0 | AU48: 0 | AV48: 1 | AW48: 1 | AZ48: 1 | BA48: 1 | BB48: 1 | BC48: 1 | BH48: 3 | BI48: 3 | BJ48: КА, п.12 | BM48: 400007 | BN48: 0 | BP48: 0 | BQ48: 214 | BR48: 0 | BS48: 1 | BT48: 1 | BU48: 1 | BV48: 1 | BW48: 1 | BX48: 1 | BZ48: 0 | CA48: 0 | CE48: 1566 | CF48: 0 | CG48: 0 | CM48: 0 | CO48: 0 | CP48: =(P48+Q48+S48) -> 34249.11 | CQ48: =ROUND((ROUND((AC48*AW48*1),2)*BC48),2) -> 34249.11 | CR48: =(ROUND((ROUND(((ET48)*AV48*1),2)*BB48),2)+ROUND((ROUND(((AE48-(EU48))*AV48*1),2)*BS48),2)) -> 0 | CS48: =(ROUND((ROUND(((EU48)*AV48*1),2)*BS48),2)+ROUND((ROUND(((AE48-(EU48))*AV48*1),2)*BS48),2)) -> 0 | CT48: =ROUND((ROUND((AF48*AV48*1),2)*BA48),2) -> 0 | CU48: =AG48 -> 0 | CV48: =(AH48*AV48) -> 0 | CW48: =AI48 -> 0 | CX48: =AJ48 -> 0 | CY48: =(ROUND((((S48+ROUND((ROUND(((EU48)*AV48*1),2)*BS48),2))*AT48)/100),2)+ROUND(((ROUND((ROUND(((AE48-(EU48))*AV48*1),2)*BS48),2)*AT48)/100),2)) -> 0 | CZ48: =(ROUND((((S48+ROUND((ROUND(((EU48)*AV48*1),2)*BS48),2))*AU48)/100),2)+ROUND(((ROUND((ROUND(((AE48-(EU48))*AV48*1),2)*BS48),2)*AU48)/100),2)) -> 0 | DN48: 0 | DO48: 0 | DP48: 1 | DQ48: 1 | DU48: 1013 | DV48: ШТ | DW48: ШТ | DX48: 1 | EE48: 56938434 | EF48: 214 | EG48: Оборудование, отсутствующие в СНБ | EH48: 0 | EJ48: 3 | EK48: 400007 | EL48: Оборудование, отсутствующие в СНБ | EM48: Оборуд. КА | EQ48: 131088 | ER48: 0 | ES48: 34249.11 | ET48: 0 | EU48: 0 | EV48: 0 | EW48: 0 | EX48: 0 | EY48: 0 | FQ48: 0 | FR48: =P48 -> 34249.11 | FS48: 0 | FX48: 0 | FY48: 0 | GA48: [303 450 / 1,22 / 7,57] + 3% Трансп + 1,2% Заг.скл | GD48: 1 | GF48: 597906176 | GG48: 2 | GH48: 4 | GI48: -2 | GJ48: 0 | GK48: 0 | GL48: =ROUND(IF(AND(BH48=3,BI48=3,FS48<>0),P48,0),2) -> 0 | GM48: =ROUND(O48+X48+Y48,2)+GX48 -> 34249.11 | GN48: =IF(OR(BI48=0,BI48=1),GM48-GX48,0) -> 0 | GO48: =IF(BI48=2,GM48-GX48,0) -> 0 | GP48: =IF(BI48=4,GM48-GX48,0) -> 0 | GR48: 1 | GS48: 2 | GT48: 0 | GV48: =ROUND((GT48),6) -> 0 | GW48: 1 | GX48: =ROUND(HC48*I48,2) -> 0 | HA48: 0 | HB48: 0 | HC48: =GV48*GW48 -> 0 | HE48: 3 | HF48: 1,2 | HS48: 0 | IK48: 0
A49: 17 | B49: 1 | E49: 9 | F49: КА, п.12 | G49: Приточная установка П8 (L=1540 м3/ч, Pc=400 Па) | H49: ШТ | I49: 1 | J49: 0 | K49: 1 | O49: =ROUND(CP49,2) -> 259265.76 | P49: =ROUND((ROUND((AC49*AW49*I49),2)*BC49),2) -> 259265.76 | Q49: =(ROUND((ROUND(((ET49)*AV49*I49),2)*BB49),2)+ROUND((ROUND(((AE49-(EU49))*AV49*I49),2)*BS49),2)) -> 0 | R49: =(ROUND((ROUND(((EU49)*AV49*I49),2)*BS49),2)+ROUND((ROUND(((AE49-(EU49))*AV49*I49),2)*BS49),2)) -> 0 | S49: =ROUND((ROUND((AF49*AV49*I49),2)*BA49),2) -> 0 | T49: =ROUND(CU49*I49,2) -> 0 | U49: =CV49*I49 -> 0 | V49: =CW49*I49 -> 0 | W49: =ROUND(CX49*I49,2) -> 0 | X49: =(ROUND((((S49+ROUND((ROUND(((EU49)*AV49*I49),2)*BS49),2))*AT49)/100),2)+ROUND(((ROUND((ROUND(((AE49-(EU49))*AV49*I49),2)*BS49),2)*AT49)/100),2)) -> 0 | Y49: =(ROUND((((S49+ROUND((ROUND(((EU49)*AV49*I49),2)*BS49),2))*AU49)/100),2)+ROUND(((ROUND((ROUND(((AE49-(EU49))*AV49*I49),2)*BS49),2)*AU49)/100),2)) -> 0 | AA49: 56661436 | AB49: =ROUND((AC49+AD49+AF49),6) -> 34249.11 | AC49: =ROUND((ES49),6) -> 34249.11 | AD49: =ROUND((((ET49)-(EU49))+AE49),6) -> 0 | AE49: =ROUND((EU49),6) -> 0 | AF49: =ROUND((EV49),6) -> 0 | AG49: =ROUND((AP49),6) -> 0 | AH49: =(EW49) -> 0 | AI49: =(EX49) -> 0 | AJ49: =(AS49) -> 0 | AK49: 34249.11 | AL49: 34249.11 | AM49: 0 | AN49: 0 | AO49: 0 | AP49: 0 | AQ49: 0 | AR49: 0 | AS49: 0 | AT49: 0 | AU49: 0 | AV49: 1 | AW49: 1 | AZ49: 1 | BA49: 1 | BB49: 1 | BC49: 7.57 | BH49: 3 | BI49: 3 | BJ49: КА, п.12 | BM49: 400007 | BN49: 0 | BP49: 0 | BQ49: 214 | BR49: 0 | BS49: 1 | BT49: 1 | BU49: 1 | BV49: 1 | BW49: 1 | BX49: 1 | BZ49: 0 | CA49: 0 | CE49: 1566 | CF49: 0 | CG49: 0 | CM49: 0 | CO49: 0 | CP49: =(P49+Q49+S49) -> 259265.76 | CQ49: =ROUND((ROUND((AC49*AW49*1),2)*BC49),2) -> 259265.76 | CR49: =(ROUND((ROUND(((ET49)*AV49*1),2)*BB49),2)+ROUND((ROUND(((AE49-(EU49))*AV49*1),2)*BS49),2)) -> 0 | CS49: =(ROUND((ROUND(((EU49)*AV49*1),2)*BS49),2)+ROUND((ROUND(((AE49-(EU49))*AV49*1),2)*BS49),2)) -> 0 | CT49: =ROUND((ROUND((AF49*AV49*1),2)*BA49),2) -> 0 | CU49: =AG49 -> 0 | CV49: =(AH49*AV49) -> 0 | CW49: =AI49 -> 0 | CX49: =AJ49 -> 0 | CY49: =(ROUND((((S49+ROUND((ROUND(((EU49)*AV49*1),2)*BS49),2))*AT49)/100),2)+ROUND(((ROUND((ROUND(((AE49-(EU49))*AV49*1),2)*BS49),2)*AT49)/100),2)) -> 0 | CZ49: =(ROUND((((S49+ROUND((ROUND(((EU49)*AV49*1),2)*BS49),2))*AU49)/100),2)+ROUND(((ROUND((ROUND(((AE49-(EU49))*AV49*1),2)*BS49),2)*AU49)/100),2)) -> 0 | DN49: 0 | DO49: 0 | DP49: 1 | DQ49: 1 | DU49: 1013 | DV49: ШТ | DW49: ШТ | DX49: 1 | EE49: 56938434 | EF49: 214 | EG49: Оборудование, отсутствующие в СНБ | EH49: 0 | EJ49: 3 | EK49: 400007 | EL49: Оборудование, отсутствующие в СНБ | EM49: Оборуд. КА | EQ49: 131088 | ER49: 0 | ES49: 34249.11 | ET49: 0 | EU49: 0 | EV49: 0 | EW49: 0 | EX49: 0 | EY49: 0 | EZ49: 5 | FC49: 1 | FD49: 18 | FF49: 303450 | FQ49: 0 | FR49: =P49 -> 259265.76 | FS49: 0 | FX49: 0 | FY49: 0 | GA49: [303 450 / 1,22 / 7,57] + 3% Трансп + 1,2% Заг.скл | GD49: 1 | GF49: 597906176 | GG49: 2 | GH49: 3 | GI49: 3 | GJ49: 0 | GK49: 0 | GL49: =ROUND(IF(AND(BH49=3,BI49=3,FS49<>0),P49,0),2) -> 0 | GM49: =ROUND(O49+X49+Y49,2)+GX49 -> 259265.76 | GN49: =IF(OR(BI49=0,BI49=1),GM49-GX49,0) -> 0 | GO49: =IF(BI49=2,GM49-GX49,0) -> 0 | GP49: =IF(BI49=4,GM49-GX49,0) -> 0 | GR49: 1 | GS49: 1 | GT49: 0 | GV49: =ROUND((GT49),6) -> 0 | GW49: 1 | GX49: =ROUND(HC49*I49,2) -> 0 | HA49: 0 | HB49: 0 | HC49: =GV49*GW49 -> 0 | HE49: 3 | HF49: 1,2 | HS49: 0 | IK49: 0
A50: 17 | B50: 1 | E50: 10 | F50: КА, п.14 | G50: Приточная установка П10 (L=4540 м3/ч, Pc=500 Па) | H50: ШТ | I50: 1 | J50: 0 | K50: 1 | O50: =ROUND(CP50,2) -> 59491.52 | P50: =ROUND((ROUND((AC50*AW50*I50),2)*BC50),2) -> 59491.52 | Q50: =(ROUND((ROUND(((ET50)*AV50*I50),2)*BB50),2)+ROUND((ROUND(((AE50-(EU50))*AV50*I50),2)*BS50),2)) -> 0 | R50: =(ROUND((ROUND(((EU50)*AV50*I50),2)*BS50),2)+ROUND((ROUND(((AE50-(EU50))*AV50*I50),2)*BS50),2)) -> 0 | S50: =ROUND((ROUND((AF50*AV50*I50),2)*BA50),2) -> 0 | T50: =ROUND(CU50*I50,2) -> 0 | U50: =CV50*I50 -> 0 | V50: =CW50*I50 -> 0 | W50: =ROUND(CX50*I50,2) -> 0 | X50: =(ROUND((((S50+ROUND((ROUND(((EU50)*AV50*I50),2)*BS50),2))*AT50)/100),2)+ROUND(((ROUND((ROUND(((AE50-(EU50))*AV50*I50),2)*BS50),2)*AT50)/100),2)) -> 0 | Y50: =(ROUND((((S50+ROUND((ROUND(((EU50)*AV50*I50),2)*BS50),2))*AU50)/100),2)+ROUND(((ROUND((ROUND(((AE50-(EU50))*AV50*I50),2)*BS50),2)*AU50)/100),2)) -> 0 | AA50: 56661434 | AB50: =ROUND((AC50+AD50+AF50),6) -> 59491.52 | AC50: =ROUND((ES50),6) -> 59491.52 | AD50: =ROUND((((ET50)-(EU50))+AE50),6) -> 0 | AE50: =ROUND((EU50),6) -> 0 | AF50: =ROUND((EV50),6) -> 0 | AG50: =ROUND((AP50),6) -> 0 | AH50: =(EW50) -> 0 | AI50: =(EX50) -> 0 | AJ50: =(AS50) -> 0 | AK50: 59491.52 | AL50: 59491.52 | AM50: 0 | AN50: 0 | AO50: 0 | AP50: 0 | AQ50: 0 | AR50: 0 | AS50: 0 | AT50: 0 | AU50: 0 | AV50: 1 | AW50: 1 | AZ50: 1 | BA50: 1 | BB50: 1 | BC50: 1 | BH50: 3 | BI50: 3 | BJ50: КА, п.14 | BM50: 400007 | BN50: 0 | BP50: 0 | BQ50: 214 | BR50: 0 | BS50: 1 | BT50: 1 | BU50: 1 | BV50: 1 | BW50: 1 | BX50: 1 | BZ50: 0 | CA50: 0 | CE50: 1566 | CF50: 0 | CG50: 0 | CM50: 0 | CO50: 0 | CP50: =(P50+Q50+S50) -> 59491.52 | CQ50: =ROUND((ROUND((AC50*AW50*1),2)*BC50),2) -> 59491.52 | CR50: =(ROUND((ROUND(((ET50)*AV50*1),2)*BB50),2)+ROUND((ROUND(((AE50-(EU50))*AV50*1),2)*BS50),2)) -> 0 | CS50: =(ROUND((ROUND(((EU50)*AV50*1),2)*BS50),2)+ROUND((ROUND(((AE50-(EU50))*AV50*1),2)*BS50),2)) -> 0 | CT50: =ROUND((ROUND((AF50*AV50*1),2)*BA50),2) -> 0 | CU50: =AG50 -> 0 | CV50: =(AH50*AV50) -> 0 | CW50: =AI50 -> 0 | CX50: =AJ50 -> 0 | CY50: =(ROUND((((S50+ROUND((ROUND(((EU50)*AV50*1),2)*BS50),2))*AT50)/100),2)+ROUND(((ROUND((ROUND(((AE50-(EU50))*AV50*1),2)*BS50),2)*AT50)/100),2)) -> 0 | CZ50: =(ROUND((((S50+ROUND((ROUND(((EU50)*AV50*1),2)*BS50),2))*AU50)/100),2)+ROUND(((ROUND((ROUND(((AE50-(EU50))*AV50*1),2)*BS50),2)*AU50)/100),2)) -> 0 | DN50: 0 | DO50: 0 | DP50: 1 | DQ50: 1 | DU50: 1013 | DV50: ШТ | DW50: ШТ | DX50: 1 | EE50: 56938434 | EF50: 214 | EG50: Оборудование, отсутствующие в СНБ | EH50: 0 | EJ50: 3 | EK50: 400007 | EL50: Оборудование, отсутствующие в СНБ | EM50: Оборуд. КА | EQ50: 131088 | ER50: 0 | ES50: 59491.52 | ET50: 0 | EU50: 0 | EV50: 0 | EW50: 0 | EX50: 0 | EY50: 0 | FQ50: 0 | FR50: =P50 -> 59491.52 | FS50: 0 | FX50: 0 | FY50: 0 | GA50: [527 100 / 1,22 / 7,57] + 3% Трансп + 1,2% Заг.скл | GD50: 1 | GF50: -466713147 | GG50: 2 | GH50: 4 | GI50: -2 | GJ50: 0 | GK50: 0 | GL50: =ROUND(IF(AND(BH50=3,BI50=3,FS50<>0),P50,0),2) -> 0 | GM50: =ROUND(O50+X50+Y50,2)+GX50 -> 59491.52 | GN50: =IF(OR(BI50=0,BI50=1),GM50-GX50,0) -> 0 | GO50: =IF(BI50=2,GM50-GX50,0) -> 0 | GP50: =IF(BI50=4,GM50-GX50,0) -> 0 | GR50: 1 | GS50: 2 | GT50: 0 | GV50: =ROUND((GT50),6) -> 0 | GW50: 1 | GX50: =ROUND(HC50*I50,2) -> 0 | HA50: 0 | HB50: 0 | HC50: =GV50*GW50 -> 0 | HE50: 3 | HF50: 1,2 | HS50: 0 | IK50: 0
A51: 17 | B51: 1 | E51: 10 | F51: КА, п.14 | G51: Приточная установка П10 (L=4540 м3/ч, Pc=500 Па) | H51: ШТ | I51: 1 | J51: 0 | K51: 1 | O51: =ROUND(CP51,2) -> 450350.81 | P51: =ROUND((ROUND((AC51*AW51*I51),2)*BC51),2) -> 450350.81 | Q51: =(ROUND((ROUND(((ET51)*AV51*I51),2)*BB51),2)+ROUND((ROUND(((AE51-(EU51))*AV51*I51),2)*BS51),2)) -> 0 | R51: =(ROUND((ROUND(((EU51)*AV51*I51),2)*BS51),2)+ROUND((ROUND(((AE51-(EU51))*AV51*I51),2)*BS51),2)) -> 0 | S51: =ROUND((ROUND((AF51*AV51*I51),2)*BA51),2) -> 0 | T51: =ROUND(CU51*I51,2) -> 0 | U51: =CV51*I51 -> 0 | V51: =CW51*I51 -> 0 | W51: =ROUND(CX51*I51,2) -> 0 | X51: =(ROUND((((S51+ROUND((ROUND(((EU51)*AV51*I51),2)*BS51),2))*AT51)/100),2)+ROUND(((ROUND((ROUND(((AE51-(EU51))*AV51*I51),2)*BS51),2)*AT51)/100),2)) -> 0 | Y51: =(ROUND((((S51+ROUND((ROUND(((EU51)*AV51*I51),2)*BS51),2))*AU51)/100),2)+ROUND(((ROUND((ROUND(((AE51-(EU51))*AV51*I51),2)*BS51),2)*AU51)/100),2)) -> 0 | AA51: 56661436 | AB51: =ROUND((AC51+AD51+AF51),6) -> 59491.52 | AC51: =ROUND((ES51),6) -> 59491.52 | AD51: =ROUND((((ET51)-(EU51))+AE51),6) -> 0 | AE51: =ROUND((EU51),6) -> 0 | AF51: =ROUND((EV51),6) -> 0 | AG51: =ROUND((AP51),6) -> 0 | AH51: =(EW51) -> 0 | AI51: =(EX51) -> 0 | AJ51: =(AS51) -> 0 | AK51: 59491.52 | AL51: 59491.52 | AM51: 0 | AN51: 0 | AO51: 0 | AP51: 0 | AQ51: 0 | AR51: 0 | AS51: 0 | AT51: 0 | AU51: 0 | AV51: 1 | AW51: 1 | AZ51: 1 | BA51: 1 | BB51: 1 | BC51: 7.57 | BH51: 3 | BI51: 3 | BJ51: КА, п.14 | BM51: 400007 | BN51: 0 | BP51: 0 | BQ51: 214 | BR51: 0 | BS51: 1 | BT51: 1 | BU51: 1 | BV51: 1 | BW51: 1 | BX51: 1 | BZ51: 0 | CA51: 0 | CE51: 1566 | CF51: 0 | CG51: 0 | CM51: 0 | CO51: 0 | CP51: =(P51+Q51+S51) -> 450350.81 | CQ51: =ROUND((ROUND((AC51*AW51*1),2)*BC51),2) -> 450350.81 | CR51: =(ROUND((ROUND(((ET51)*AV51*1),2)*BB51),2)+ROUND((ROUND(((AE51-(EU51))*AV51*1),2)*BS51),2)) -> 0 | CS51: =(ROUND((ROUND(((EU51)*AV51*1),2)*BS51),2)+ROUND((ROUND(((AE51-(EU51))*AV51*1),2)*BS51),2)) -> 0 | CT51: =ROUND((ROUND((AF51*AV51*1),2)*BA51),2) -> 0 | CU51: =AG51 -> 0 | CV51: =(AH51*AV51) -> 0 | CW51: =AI51 -> 0 | CX51: =AJ51 -> 0 | CY51: =(ROUND((((S51+ROUND((ROUND(((EU51)*AV51*1),2)*BS51),2))*AT51)/100),2)+ROUND(((ROUND((ROUND(((AE51-(EU51))*AV51*1),2)*BS51),2)*AT51)/100),2)) -> 0 | CZ51: =(ROUND((((S51+ROUND((ROUND(((EU51)*AV51*1),2)*BS51),2))*AU51)/100),2)+ROUND(((ROUND((ROUND(((AE51-(EU51))*AV51*1),2)*BS51),2)*AU51)/100),2)) -> 0 | DN51: 0 | DO51: 0 | DP51: 1 | DQ51: 1 | DU51: 1013 | DV51: ШТ | DW51: ШТ | DX51: 1 | EE51: 56938434 | EF51: 214 | EG51: Оборудование, отсутствующие в СНБ | EH51: 0 | EJ51: 3 | EK51: 400007 | EL51: Оборудование, отсутствующие в СНБ | EM51: Оборуд. КА | EQ51: 131088 | ER51: 0 | ES51: 59491.52 | ET51: 0 | EU51: 0 | EV51: 0 | EW51: 0 | EX51: 0 | EY51: 0 | EZ51: 5 | FC51: 1 | FD51: 18 | FF51: 527100 | FQ51: 0 | FR51: =P51 -> 450350.81 | FS51: 0 | FX51: 0 | FY51: 0 | GA51: [527 100 / 1,22 / 7,57] + 3% Трансп + 1,2% Заг.скл | GD51: 1 | GF51: -466713147 | GG51: 2 | GH51: 3 | GI51: 3 | GJ51: 0 | GK51: 0 | GL51: =ROUND(IF(AND(BH51=3,BI51=3,FS51<>0),P51,0),2) -> 0 | GM51: =ROUND(O51+X51+Y51,2)+GX51 -> 450350.81 | GN51: =IF(OR(BI51=0,BI51=1),GM51-GX51,0) -> 0 | GO51: =IF(BI51=2,GM51-GX51,0) -> 0 | GP51: =IF(BI51=4,GM51-GX51,0) -> 0 | GR51: 1 | GS51: 1 | GT51: 0 | GV51: =ROUND((GT51),6) -> 0 | GW51: 1 | GX51: =ROUND(HC51*I51,2) -> 0 | HA51: 0 | HB51: 0 | HC51: =GV51*GW51 -> 0 | HE51: 3 | HF51: 1,2 | HS51: 0 | IK51: 0
A52: 17 | B52: 1 | E52: 11 | F52: КА, п.15 | G52: Приточная установка П11 (L=3800 м3/ч, Pc=700 Па) | H52: ШТ | I52: 1 | J52: 0 | K52: 1 | O52: =ROUND(CP52,2) -> 57476.86 | P52: =ROUND((ROUND((AC52*AW52*I52),2)*BC52),2) -> 57476.86 | Q52: =(ROUND((ROUND(((ET52)*AV52*I52),2)*BB52),2)+ROUND((ROUND(((AE52-(EU52))*AV52*I52),2)*BS52),2)) -> 0 | R52: =(ROUND((ROUND(((EU52)*AV52*I52),2)*BS52),2)+ROUND((ROUND(((AE52-(EU52))*AV52*I52),2)*BS52),2)) -> 0 | S52: =ROUND((ROUND((AF52*AV52*I52),2)*BA52),2) -> 0 | T52: =ROUND(CU52*I52,2) -> 0 | U52: =CV52*I52 -> 0 | V52: =CW52*I52 -> 0 | W52: =ROUND(CX52*I52,2) -> 0 | X52: =(ROUND((((S52+ROUND((ROUND(((EU52)*AV52*I52),2)*BS52),2))*AT52)/100),2)+ROUND(((ROUND((ROUND(((AE52-(EU52))*AV52*I52),2)*BS52),2)*AT52)/100),2)) -> 0 | Y52: =(ROUND((((S52+ROUND((ROUND(((EU52)*AV52*I52),2)*BS52),2))*AU52)/100),2)+ROUND(((ROUND((ROUND(((AE52-(EU52))*AV52*I52),2)*BS52),2)*AU52)/100),2)) -> 0 | AA52: 56661434 | AB52: =ROUND((AC52+AD52+AF52),6) -> 57476.86 | AC52: =ROUND((ES52),6) -> 57476.86 | AD52: =ROUND((((ET52)-(EU52))+AE52),6) -> 0 | AE52: =ROUND((EU52),6) -> 0 | AF52: =ROUND((EV52),6) -> 0 | AG52: =ROUND((AP52),6) -> 0 | AH52: =(EW52) -> 0 | AI52: =(EX52) -> 0 | AJ52: =(AS52) -> 0 | AK52: 57476.86 | AL52: 57476.86 | AM52: 0 | AN52: 0 | AO52: 0 | AP52: 0 | AQ52: 0 | AR52: 0 | AS52: 0 | AT52: 0 | AU52: 0 | AV52: 1 | AW52: 1 | AZ52: 1 | BA52: 1 | BB52: 1 | BC52: 1 | BH52: 3 | BI52: 3 | BJ52: КА, п.15 | BM52: 400007 | BN52: 0 | BP52: 0 | BQ52: 214 | BR52: 0 | BS52: 1 | BT52: 1 | BU52: 1 | BV52: 1 | BW52: 1 | BX52: 1 | BZ52: 0 | CA52: 0 | CE52: 1566 | CF52: 0 | CG52: 0 | CM52: 0 | CO52: 0 | CP52: =(P52+Q52+S52) -> 57476.86 | CQ52: =ROUND((ROUND((AC52*AW52*1),2)*BC52),2) -> 57476.86 | CR52: =(ROUND((ROUND(((ET52)*AV52*1),2)*BB52),2)+ROUND((ROUND(((AE52-(EU52))*AV52*1),2)*BS52),2)) -> 0 | CS52: =(ROUND((ROUND(((EU52)*AV52*1),2)*BS52),2)+ROUND((ROUND(((AE52-(EU52))*AV52*1),2)*BS52),2)) -> 0 | CT52: =ROUND((ROUND((AF52*AV52*1),2)*BA52),2) -> 0 | CU52: =AG52 -> 0 | CV52: =(AH52*AV52) -> 0 | CW52: =AI52 -> 0 | CX52: =AJ52 -> 0 | CY52: =(ROUND((((S52+ROUND((ROUND(((EU52)*AV52*1),2)*BS52),2))*AT52)/100),2)+ROUND(((ROUND((ROUND(((AE52-(EU52))*AV52*1),2)*BS52),2)*AT52)/100),2)) -> 0 | CZ52: =(ROUND((((S52+ROUND((ROUND(((EU52)*AV52*1),2)*BS52),2))*AU52)/100),2)+ROUND(((ROUND((ROUND(((AE52-(EU52))*AV52*1),2)*BS52),2)*AU52)/100),2)) -> 0 | DN52: 0 | DO52: 0 | DP52: 1 | DQ52: 1 | DU52: 1013 | DV52: ШТ | DW52: ШТ | DX52: 1 | EE52: 56938434 | EF52: 214 | EG52: Оборудование, отсутствующие в СНБ | EH52: 0 | EJ52: 3 | EK52: 400007 | EL52: Оборудование, отсутствующие в СНБ | EM52: Оборуд. КА | EQ52: 131088 | ER52: 0 | ES52: 57476.86 | ET52: 0 | EU52: 0 | EV52: 0 | EW52: 0 | EX52: 0 | EY52: 0 | FQ52: 0 | FR52: =P52 -> 57476.86 | FS52: 0 | FX52: 0 | FY52: 0 | GA52: [509 250 / 1,22 / 7,57] + 3% Трансп + 1,2% Заг.скл | GD52: 1 | GF52: -1240450512 | GG52: 2 | GH52: 4 | GI52: -2 | GJ52: 0 | GK52: 0 | GL52: =ROUND(IF(AND(BH52=3,BI52=3,FS52<>0),P52,0),2) -> 0 | GM52: =ROUND(O52+X52+Y52,2)+GX52 -> 57476.86 | GN52: =IF(OR(BI52=0,BI52=1),GM52-GX52,0) -> 0 | GO52: =IF(BI52=2,GM52-GX52,0) -> 0 | GP52: =IF(BI52=4,GM52-GX52,0) -> 0 | GR52: 1 | GS52: 2 | GT52: 0 | GV52: =ROUND((GT52),6) -> 0 | GW52: 1 | GX52: =ROUND(HC52*I52,2) -> 0 | HA52: 0 | HB52: 0 | HC52: =GV52*GW52 -> 0 | HE52: 3 | HF52: 1,2 | HS52: 0 | IK52: 0
A53: 17 | B53: 1 | E53: 11 | F53: КА, п.15 | G53: Приточная установка П11 (L=3800 м3/ч, Pc=700 Па) | H53: ШТ | I53: 1 | J53: 0 | K53: 1 | O53: =ROUND(CP53,2) -> 435099.83 | P53: =ROUND((ROUND((AC53*AW53*I53),2)*BC53),2) -> 435099.83 | Q53: =(ROUND((ROUND(((ET53)*AV53*I53),2)*BB53),2)+ROUND((ROUND(((AE53-(EU53))*AV53*I53),2)*BS53),2)) -> 0 | R53: =(ROUND((ROUND(((EU53)*AV53*I53),2)*BS53),2)+ROUND((ROUND(((AE53-(EU53))*AV53*I53),2)*BS53),2)) -> 0 | S53: =ROUND((ROUND((AF53*AV53*I53),2)*BA53),2) -> 0 | T53: =ROUND(CU53*I53,2) -> 0 | U53: =CV53*I53 -> 0 | V53: =CW53*I53 -> 0 | W53: =ROUND(CX53*I53,2) -> 0 | X53: =(ROUND((((S53+ROUND((ROUND(((EU53)*AV53*I53),2)*BS53),2))*AT53)/100),2)+ROUND(((ROUND((ROUND(((AE53-(EU53))*AV53*I53),2)*BS53),2)*AT53)/100),2)) -> 0 | Y53: =(ROUND((((S53+ROUND((ROUND(((EU53)*AV53*I53),2)*BS53),2))*AU53)/100),2)+ROUND(((ROUND((ROUND(((AE53-(EU53))*AV53*I53),2)*BS53),2)*AU53)/100),2)) -> 0 | AA53: 56661436 | AB53: =ROUND((AC53+AD53+AF53),6) -> 57476.86 | AC53: =ROUND((ES53),6) -> 57476.86 | AD53: =ROUND((((ET53)-(EU53))+AE53),6) -> 0 | AE53: =ROUND((EU53),6) -> 0 | AF53: =ROUND((EV53),6) -> 0 | AG53: =ROUND((AP53),6) -> 0 | AH53: =(EW53) -> 0 | AI53: =(EX53) -> 0 | AJ53: =(AS53) -> 0 | AK53: 57476.86 | AL53: 57476.86 | AM53: 0 | AN53: 0 | AO53: 0 | AP53: 0 | AQ53: 0 | AR53: 0 | AS53: 0 | AT53: 0 | AU53: 0 | AV53: 1 | AW53: 1 | AZ53: 1 | BA53: 1 | BB53: 1 | BC53: 7.57 | BH53: 3 | BI53: 3 | BJ53: КА, п.15 | BM53: 400007 | BN53: 0 | BP53: 0 | BQ53: 214 | BR53: 0 | BS53: 1 | BT53: 1 | BU53: 1 | BV53: 1 | BW53: 1 | BX53: 1 | BZ53: 0 | CA53: 0 | CE53: 1566 | CF53: 0 | CG53: 0 | CM53: 0 | CO53: 0 | CP53: =(P53+Q53+S53) -> 435099.83 | CQ53: =ROUND((ROUND((AC53*AW53*1),2)*BC53),2) -> 435099.83 | CR53: =(ROUND((ROUND(((ET53)*AV53*1),2)*BB53),2)+ROUND((ROUND(((AE53-(EU53))*AV53*1),2)*BS53),2)) -> 0 | CS53: =(ROUND((ROUND(((EU53)*AV53*1),2)*BS53),2)+ROUND((ROUND(((AE53-(EU53))*AV53*1),2)*BS53),2)) -> 0 | CT53: =ROUND((ROUND((AF53*AV53*1),2)*BA53),2) -> 0 | CU53: =AG53 -> 0 | CV53: =(AH53*AV53) -> 0 | CW53: =AI53 -> 0 | CX53: =AJ53 -> 0 | CY53: =(ROUND((((S53+ROUND((ROUND(((EU53)*AV53*1),2)*BS53),2))*AT53)/100),2)+ROUND(((ROUND((ROUND(((AE53-(EU53))*AV53*1),2)*BS53),2)*AT53)/100),2)) -> 0 | CZ53: =(ROUND((((S53+ROUND((ROUND(((EU53)*AV53*1),2)*BS53),2))*AU53)/100),2)+ROUND(((ROUND((ROUND(((AE53-(EU53))*AV53*1),2)*BS53),2)*AU53)/100),2)) -> 0 | DN53: 0 | DO53: 0 | DP53: 1 | DQ53: 1 | DU53: 1013 | DV53: ШТ | DW53: ШТ | DX53: 1 | EE53: 56938434 | EF53: 214 | EG53: Оборудование, отсутствующие в СНБ | EH53: 0 | EJ53: 3 | EK53: 400007 | EL53: Оборудование, отсутствующие в СНБ | EM53: Оборуд. КА | EQ53: 131088 | ER53: 0 | ES53: 57476.86 | ET53: 0 | EU53: 0 | EV53: 0 | EW53: 0 | EX53: 0 | EY53: 0 | EZ53: 5 | FC53: 1 | FD53: 18 | FF53: 509250 | FQ53: 0 | FR53: =P53 -> 435099.83 | FS53: 0 | FX53: 0 | FY53: 0 | GA53: [509 250 / 1,22 / 7,57] + 3% Трансп + 1,2% Заг.скл | GD53: 1 | GF53: -1240450512 | GG53: 2 | GH53: 3 | GI53: 3 | GJ53: 0 | GK53: 0 | GL53: =ROUND(IF(AND(BH53=3,BI53=3,FS53<>0),P53,0),2) -> 0 | GM53: =ROUND(O53+X53+Y53,2)+GX53 -> 435099.83 | GN53: =IF(OR(BI53=0,BI53=1),GM53-GX53,0) -> 0 | GO53: =IF(BI53=2,GM53-GX53,0) -> 0 | GP53: =IF(BI53=4,GM53-GX53,0) -> 0 | GR53: 1 | GS53: 1 | GT53: 0 | GV53: =ROUND((GT53),6) -> 0 | GW53: 1 | GX53: =ROUND(HC53*I53,2) -> 0 | HA53: 0 | HB53: 0 | HC53: =GV53*GW53 -> 0 | HE53: 3 | HF53: 1,2 | HS53: 0 | IK53: 0
A54: 17 | B54: 1 | E54: 12 | F54: КА, п.16 | G54: Приточная установка П12 (L=3400 м3/ч, Pc=700 Па) | H54: ШТ | I54: 1 | J54: 0 | K54: 1 | O54: =ROUND(CP54,2) -> 45981.5 | P54: =ROUND((ROUND((AC54*AW54*I54),2)*BC54),2) -> 45981.5 | Q54: =(ROUND((ROUND(((ET54)*AV54*I54),2)*BB54),2)+ROUND((ROUND(((AE54-(EU54))*AV54*I54),2)*BS54),2)) -> 0 | R54: =(ROUND((ROUND(((EU54)*AV54*I54),2)*BS54),2)+ROUND((ROUND(((AE54-(EU54))*AV54*I54),2)*BS54),2)) -> 0 | S54: =ROUND((ROUND((AF54*AV54*I54),2)*BA54),2) -> 0 | T54: =ROUND(CU54*I54,2) -> 0 | U54: =CV54*I54 -> 0 | V54: =CW54*I54 -> 0 | W54: =ROUND(CX54*I54,2) -> 0 | X54: =(ROUND((((S54+ROUND((ROUND(((EU54)*AV54*I54),2)*BS54),2))*AT54)/100),2)+ROUND(((ROUND((ROUND(((AE54-(EU54))*AV54*I54),2)*BS54),2)*AT54)/100),2)) -> 0 | Y54: =(ROUND((((S54+ROUND((ROUND(((EU54)*AV54*I54),2)*BS54),2))*AU54)/100),2)+ROUND(((ROUND((ROUND(((AE54-(EU54))*AV54*I54),2)*BS54),2)*AU54)/100),2)) -> 0 | AA54: 56661434 | AB54: =ROUND((AC54+AD54+AF54),6) -> 45981.5 | AC54: =ROUND((ES54),6) -> 45981.5 | AD54: =ROUND((((ET54)-(EU54))+AE54),6) -> 0 | AE54: =ROUND((EU54),6) -> 0 | AF54: =ROUND((EV54),6) -> 0 | AG54: =ROUND((AP54),6) -> 0 | AH54: =(EW54) -> 0 | AI54: =(EX54) -> 0 | AJ54: =(AS54) -> 0 | AK54: 45981.5 | AL54: 45981.5 | AM54: 0 | AN54: 0 | AO54: 0 | AP54: 0 | AQ54: 0 | AR54: 0 | AS54: 0 | AT54: 0 | AU54: 0 | AV54: 1 | AW54: 1 | AZ54: 1 | BA54: 1 | BB54: 1 | BC54: 1 | BH54: 3 | BI54: 3 | BJ54: КА, п.16 | BM54: 400007 | BN54: 0 | BP54: 0 | BQ54: 214 | BR54: 0 | BS54: 1 | BT54: 1 | BU54: 1 | BV54: 1 | BW54: 1 | BX54: 1 | BZ54: 0 | CA54: 0 | CE54: 1566 | CF54: 0 | CG54: 0 | CM54: 0 | CO54: 0 | CP54: =(P54+Q54+S54) -> 45981.5 | CQ54: =ROUND((ROUND((AC54*AW54*1),2)*BC54),2) -> 45981.5 | CR54: =(ROUND((ROUND(((ET54)*AV54*1),2)*BB54),2)+ROUND((ROUND(((AE54-(EU54))*AV54*1),2)*BS54),2)) -> 0 | CS54: =(ROUND((ROUND(((EU54)*AV54*1),2)*BS54),2)+ROUND((ROUND(((AE54-(EU54))*AV54*1),2)*BS54),2)) -> 0 | CT54: =ROUND((ROUND((AF54*AV54*1),2)*BA54),2) -> 0 | CU54: =AG54 -> 0 | CV54: =(AH54*AV54) -> 0 | CW54: =AI54 -> 0 | CX54: =AJ54 -> 0 | CY54: =(ROUND((((S54+ROUND((ROUND(((EU54)*AV54*1),2)*BS54),2))*AT54)/100),2)+ROUND(((ROUND((ROUND(((AE54-(EU54))*AV54*1),2)*BS54),2)*AT54)/100),2)) -> 0 | CZ54: =(ROUND((((S54+ROUND((ROUND(((EU54)*AV54*1),2)*BS54),2))*AU54)/100),2)+ROUND(((ROUND((ROUND(((AE54-(EU54))*AV54*1),2)*BS54),2)*AU54)/100),2)) -> 0 | DN54: 0 | DO54: 0 | DP54: 1 | DQ54: 1 | DU54: 1013 | DV54: ШТ | DW54: ШТ | DX54: 1 | EE54: 56938434 | EF54: 214 | EG54: Оборудование, отсутствующие в СНБ | EH54: 0 | EJ54: 3 | EK54: 400007 | EL54: Оборудование, отсутствующие в СНБ | EM54: Оборуд. КА | EQ54: 131088 | ER54: 0 | ES54: 45981.5 | ET54: 0 | EU54: 0 | EV54: 0 | EW54: 0 | EX54: 0 | EY54: 0 | FQ54: 0 | FR54: =P54 -> 45981.5 | FS54: 0 | FX54: 0 | FY54: 0 | GA54: [407 400 / 1,22 / 7,57] + 3% Трансп + 1,2% Заг.скл | GD54: 1 | GF54: -1920684649 | GG54: 2 | GH54: 4 | GI54: -2 | GJ54: 0 | GK54: 0 | GL54: =ROUND(IF(AND(BH54=3,BI54=3,FS54<>0),P54,0),2) -> 0 | GM54: =ROUND(O54+X54+Y54,2)+GX54 -> 45981.5 | GN54: =IF(OR(BI54=0,BI54=1),GM54-GX54,0) -> 0 | GO54: =IF(BI54=2,GM54-GX54,0) -> 0 | GP54: =IF(BI54=4,GM54-GX54,0) -> 0 | GR54: 1 | GS54: 2 | GT54: 0 | GV54: =ROUND((GT54),6) -> 0 | GW54: 1 | GX54: =ROUND(HC54*I54,2) -> 0 | HA54: 0 | HB54: 0 | HC54: =GV54*GW54 -> 0 | HE54: 3 | HF54: 1,2 | HS54: 0 | IK54: 0
A55: 17 | B55: 1 | E55: 12 | F55: КА, п.16 | G55: Приточная установка П12 (L=3400 м3/ч, Pc=700 Па) | H55: ШТ | I55: 1 | J55: 0 | K55: 1 | O55: =ROUND(CP55,2) -> 348079.96 | P55: =ROUND((ROUND((AC55*AW55*I55),2)*BC55),2) -> 348079.96 | Q55: =(ROUND((ROUND(((ET55)*AV55*I55),2)*BB55),2)+ROUND((ROUND(((AE55-(EU55))*AV55*I55),2)*BS55),2)) -> 0 | R55: =(ROUND((ROUND(((EU55)*AV55*I55),2)*BS55),2)+ROUND((ROUND(((AE55-(EU55))*AV55*I55),2)*BS55),2)) -> 0 | S55: =ROUND((ROUND((AF55*AV55*I55),2)*BA55),2) -> 0 | T55: =ROUND(CU55*I55,2) -> 0 | U55: =CV55*I55 -> 0 | V55: =CW55*I55 -> 0 | W55: =ROUND(CX55*I55,2) -> 0 | X55: =(ROUND((((S55+ROUND((ROUND(((EU55)*AV55*I55),2)*BS55),2))*AT55)/100),2)+ROUND(((ROUND((ROUND(((AE55-(EU55))*AV55*I55),2)*BS55),2)*AT55)/100),2)) -> 0 | Y55: =(ROUND((((S55+ROUND((ROUND(((EU55)*AV55*I55),2)*BS55),2))*AU55)/100),2)+ROUND(((ROUND((ROUND(((AE55-(EU55))*AV55*I55),2)*BS55),2)*AU55)/100),2)) -> 0 | AA55: 56661436 | AB55: =ROUND((AC55+AD55+AF55),6) -> 45981.5 | AC55: =ROUND((ES55),6) -> 45981.5 | AD55: =ROUND((((ET55)-(EU55))+AE55),6) -> 0 | AE55: =ROUND((EU55),6) -> 0 | AF55: =ROUND((EV55),6) -> 0 | AG55: =ROUND((AP55),6) -> 0 | AH55: =(EW55) -> 0 | AI55: =(EX55) -> 0 | AJ55: =(AS55) -> 0 | AK55: 45981.5 | AL55: 45981.5 | AM55: 0 | AN55: 0 | AO55: 0 | AP55: 0 | AQ55: 0 | AR55: 0 | AS55: 0 | AT55: 0 | AU55: 0 | AV55: 1 | AW55: 1 | AZ55: 1 | BA55: 1 | BB55: 1 | BC55: 7.57 | BH55: 3 | BI55: 3 | BJ55: КА, п.16 | BM55: 400007 | BN55: 0 | BP55: 0 | BQ55: 214 | BR55: 0 | BS55: 1 | BT55: 1 | BU55: 1 | BV55: 1 | BW55: 1 | BX55: 1 | BZ55: 0 | CA55: 0 | CE55: 1566 | CF55: 0 | CG55: 0 | CM55: 0 | CO55: 0 | CP55: =(P55+Q55+S55) -> 348079.96 | CQ55: =ROUND((ROUND((AC55*AW55*1),2)*BC55),2) -> 348079.96 | CR55: =(ROUND((ROUND(((ET55)*AV55*1),2)*BB55),2)+ROUND((ROUND(((AE55-(EU55))*AV55*1),2)*BS55),2)) -> 0 | CS55: =(ROUND((ROUND(((EU55)*AV55*1),2)*BS55),2)+ROUND((ROUND(((AE55-(EU55))*AV55*1),2)*BS55),2)) -> 0 | CT55: =ROUND((ROUND((AF55*AV55*1),2)*BA55),2) -> 0 | CU55: =AG55 -> 0 | CV55: =(AH55*AV55) -> 0 | CW55: =AI55 -> 0 | CX55: =AJ55 -> 0 | CY55: =(ROUND((((S55+ROUND((ROUND(((EU55)*AV55*1),2)*BS55),2))*AT55)/100),2)+ROUND(((ROUND((ROUND(((AE55-(EU55))*AV55*1),2)*BS55),2)*AT55)/100),2)) -> 0 | CZ55: =(ROUND((((S55+ROUND((ROUND(((EU55)*AV55*1),2)*BS55),2))*AU55)/100),2)+ROUND(((ROUND((ROUND(((AE55-(EU55))*AV55*1),2)*BS55),2)*AU55)/100),2)) -> 0 | DN55: 0 | DO55: 0 | DP55: 1 | DQ55: 1 | DU55: 1013 | DV55: ШТ | DW55: ШТ | DX55: 1 | EE55: 56938434 | EF55: 214 | EG55: Оборудование, отсутствующие в СНБ | EH55: 0 | EJ55: 3 | EK55: 400007 | EL55: Оборудование, отсутствующие в СНБ | EM55: Оборуд. КА | EQ55: 131088 | ER55: 0 | ES55: 45981.5 | ET55: 0 | EU55: 0 | EV55: 0 | EW55: 0 | EX55: 0 | EY55: 0 | EZ55: 5 | FC55: 1 | FD55: 18 | FF55: 407400 | FQ55: 0 | FR55: =P55 -> 348079.96 | FS55: 0 | FX55: 0 | FY55: 0 | GA55: [407 400 / 1,22 / 7,57] + 3% Трансп + 1,2% Заг.скл | GD55: 1 | GF55: -1920684649 | GG55: 2 | GH55: 3 | GI55: 3 | GJ55: 0 | GK55: 0 | GL55: =ROUND(IF(AND(BH55=3,BI55=3,FS55<>0),P55,0),2) -> 0 | GM55: =ROUND(O55+X55+Y55,2)+GX55 -> 348079.96 | GN55: =IF(OR(BI55=0,BI55=1),GM55-GX55,0) -> 0 | GO55: =IF(BI55=2,GM55-GX55,0) -> 0 | GP55: =IF(BI55=4,GM55-GX55,0) -> 0 | GR55: 1 | GS55: 1 | GT55: 0 | GV55: =ROUND((GT55),6) -> 0 | GW55: 1 | GX55: =ROUND(HC55*I55,2) -> 0 | HA55: 0 | HB55: 0 | HC55: =GV55*GW55 -> 0 | HE55: 3 | HF55: 1,2 | HS55: 0 | IK55: 0
A56: 17 | B56: 1 | E56: 13 | F56: КА, п.17 | G56: Приточная установка П13 (L=2000 м3/ч, Pc=500 Па) | H56: ШТ | I56: 1 | J56: 0 | K56: 1 | O56: =ROUND(CP56,2) -> 39842.72 | P56: =ROUND((ROUND((AC56*AW56*I56),2)*BC56),2) -> 39842.72 | Q56: =(ROUND((ROUND(((ET56)*AV56*I56),2)*BB56),2)+ROUND((ROUND(((AE56-(EU56))*AV56*I56),2)*BS56),2)) -> 0 | R56: =(ROUND((ROUND(((EU56)*AV56*I56),2)*BS56),2)+ROUND((ROUND(((AE56-(EU56))*AV56*I56),2)*BS56),2)) -> 0 | S56: =ROUND((ROUND((AF56*AV56*I56),2)*BA56),2) -> 0 | T56: =ROUND(CU56*I56,2) -> 0 | U56: =CV56*I56 -> 0 | V56: =CW56*I56 -> 0 | W56: =ROUND(CX56*I56,2) -> 0 | X56: =(ROUND((((S56+ROUND((ROUND(((EU56)*AV56*I56),2)*BS56),2))*AT56)/100),2)+ROUND(((ROUND((ROUND(((AE56-(EU56))*AV56*I56),2)*BS56),2)*AT56)/100),2)) -> 0 | Y56: =(ROUND((((S56+ROUND((ROUND(((EU56)*AV56*I56),2)*BS56),2))*AU56)/100),2)+ROUND(((ROUND((ROUND(((AE56-(EU56))*AV56*I56),2)*BS56),2)*AU56)/100),2)) -> 0 | AA56: 56661434 | AB56: =ROUND((AC56+AD56+AF56),6) -> 39842.72 | AC56: =ROUND((ES56),6) -> 39842.72 | AD56: =ROUND((((ET56)-(EU56))+AE56),6) -> 0 | AE56: =ROUND((EU56),6) -> 0 | AF56: =ROUND((EV56),6) -> 0 | AG56: =ROUND((AP56),6) -> 0 | AH56: =(EW56) -> 0 | AI56: =(EX56) -> 0 | AJ56: =(AS56) -> 0 | AK56: 39842.72 | AL56: 39842.72 | AM56: 0 | AN56: 0 | AO56: 0 | AP56: 0 | AQ56: 0 | AR56: 0 | AS56: 0 | AT56: 0 | AU56: 0 | AV56: 1 | AW56: 1 | AZ56: 1 | BA56: 1 | BB56: 1 | BC56: 1 | BH56: 3 | BI56: 3 | BJ56: КА, п.17 | BM56: 400007 | BN56: 0 | BP56: 0 | BQ56: 214 | BR56: 0 | BS56: 1 | BT56: 1 | BU56: 1 | BV56: 1 | BW56: 1 | BX56: 1 | BZ56: 0 | CA56: 0 | CE56: 1566 | CF56: 0 | CG56: 0 | CM56: 0 | CO56: 0 | CP56: =(P56+Q56+S56) -> 39842.72 | CQ56: =ROUND((ROUND((AC56*AW56*1),2)*BC56),2) -> 39842.72 | CR56: =(ROUND((ROUND(((ET56)*AV56*1),2)*BB56),2)+ROUND((ROUND(((AE56-(EU56))*AV56*1),2)*BS56),2)) -> 0 | CS56: =(ROUND((ROUND(((EU56)*AV56*1),2)*BS56),2)+ROUND((ROUND(((AE56-(EU56))*AV56*1),2)*BS56),2)) -> 0 | CT56: =ROUND((ROUND((AF56*AV56*1),2)*BA56),2) -> 0 | CU56: =AG56 -> 0 | CV56: =(AH56*AV56) -> 0 | CW56: =AI56 -> 0 | CX56: =AJ56 -> 0 | CY56: =(ROUND((((S56+ROUND((ROUND(((EU56)*AV56*1),2)*BS56),2))*AT56)/100),2)+ROUND(((ROUND((ROUND(((AE56-(EU56))*AV56*1),2)*BS56),2)*AT56)/100),2)) -> 0 | CZ56: =(ROUND((((S56+ROUND((ROUND(((EU56)*AV56*1),2)*BS56),2))*AU56)/100),2)+ROUND(((ROUND((ROUND(((AE56-(EU56))*AV56*1),2)*BS56),2)*AU56)/100),2)) -> 0 | DN56: 0 | DO56: 0 | DP56: 1 | DQ56: 1 | DU56: 1013 | DV56: ШТ | DW56: ШТ | DX56: 1 | EE56: 56938434 | EF56: 214 | EG56: Оборудование, отсутствующие в СНБ | EH56: 0 | EJ56: 3 | EK56: 400007 | EL56: Оборудование, отсутствующие в СНБ | EM56: Оборуд. КА | EQ56: 131088 | ER56: 0 | ES56: 39842.72 | ET56: 0 | EU56: 0 | EV56: 0 | EW56: 0 | EX56: 0 | EY56: 0 | FQ56: 0 | FR56: =P56 -> 39842.72 | FS56: 0 | FX56: 0 | FY56: 0 | GA56: [353 010 / 1,22 / 7,57] + 3% Трансп + 1,2% Заг.скл | GD56: 1 | GF56: -510697344 | GG56: 2 | GH56: 4 | GI56: -2 | GJ56: 0 | GK56: 0 | GL56: =ROUND(IF(AND(BH56=3,BI56=3,FS56<>0),P56,0),2) -> 0 | GM56: =ROUND(O56+X56+Y56,2)+GX56 -> 39842.72 | GN56: =IF(OR(BI56=0,BI56=1),GM56-GX56,0) -> 0 | GO56: =IF(BI56=2,GM56-GX56,0) -> 0 | GP56: =IF(BI56=4,GM56-GX56,0) -> 0 | GR56: 1 | GS56: 2 | GT56: 0 | GV56: =ROUND((GT56),6) -> 0 | GW56: 1 | GX56: =ROUND(HC56*I56,2) -> 0 | HA56: 0 | HB56: 0 | HC56: =GV56*GW56 -> 0 | HE56: 3 | HF56: 1,2 | HS56: 0 | IK56: 0
A57: 17 | B57: 1 | E57: 13 | F57: КА, п.17 | G57: Приточная установка П13 (L=2000 м3/ч, Pc=500 Па) | H57: ШТ | I57: 1 | J57: 0 | K57: 1 | O57: =ROUND(CP57,2) -> 301609.39 | P57: =ROUND((ROUND((AC57*AW57*I57),2)*BC57),2) -> 301609.39 | Q57: =(ROUND((ROUND(((ET57)*AV57*I57),2)*BB57),2)+ROUND((ROUND(((AE57-(EU57))*AV57*I57),2)*BS57),2)) -> 0 | R57: =(ROUND((ROUND(((EU57)*AV57*I57),2)*BS57),2)+ROUND((ROUND(((AE57-(EU57))*AV57*I57),2)*BS57),2)) -> 0 | S57: =ROUND((ROUND((AF57*AV57*I57),2)*BA57),2) -> 0 | T57: =ROUND(CU57*I57,2) -> 0 | U57: =CV57*I57 -> 0 | V57: =CW57*I57 -> 0 | W57: =ROUND(CX57*I57,2) -> 0 | X57: =(ROUND((((S57+ROUND((ROUND(((EU57)*AV57*I57),2)*BS57),2))*AT57)/100),2)+ROUND(((ROUND((ROUND(((AE57-(EU57))*AV57*I57),2)*BS57),2)*AT57)/100),2)) -> 0 | Y57: =(ROUND((((S57+ROUND((ROUND(((EU57)*AV57*I57),2)*BS57),2))*AU57)/100),2)+ROUND(((ROUND((ROUND(((AE57-(EU57))*AV57*I57),2)*BS57),2)*AU57)/100),2)) -> 0 | AA57: 56661436 | AB57: =ROUND((AC57+AD57+AF57),6) -> 39842.72 | AC57: =ROUND((ES57),6) -> 39842.72 | AD57: =ROUND((((ET57)-(EU57))+AE57),6) -> 0 | AE57: =ROUND((EU57),6) -> 0 | AF57: =ROUND((EV57),6) -> 0 | AG57: =ROUND((AP57),6) -> 0 | AH57: =(EW57) -> 0 | AI57: =(EX57) -> 0 | AJ57: =(AS57) -> 0 | AK57: 39842.72 | AL57: 39842.72 | AM57: 0 | AN57: 0 | AO57: 0 | AP57: 0 | AQ57: 0 | AR57: 0 | AS57: 0 | AT57: 0 | AU57: 0 | AV57: 1 | AW57: 1 | AZ57: 1 | BA57: 1 | BB57: 1 | BC57: 7.57 | BH57: 3 | BI57: 3 | BJ57: КА, п.17 | BM57: 400007 | BN57: 0 | BP57: 0 | BQ57: 214 | BR57: 0 | BS57: 1 | BT57: 1 | BU57: 1 | BV57: 1 | BW57: 1 | BX57: 1 | BZ57: 0 | CA57: 0 | CE57: 1566 | CF57: 0 | CG57: 0 | CM57: 0 | CO57: 0 | CP57: =(P57+Q57+S57) -> 301609.39 | CQ57: =ROUND((ROUND((AC57*AW57*1),2)*BC57),2) -> 301609.39 | CR57: =(ROUND((ROUND(((ET57)*AV57*1),2)*BB57),2)+ROUND((ROUND(((AE57-(EU57))*AV57*1),2)*BS57),2)) -> 0 | CS57: =(ROUND((ROUND(((EU57)*AV57*1),2)*BS57),2)+ROUND((ROUND(((AE57-(EU57))*AV57*1),2)*BS57),2)) -> 0 | CT57: =ROUND((ROUND((AF57*AV57*1),2)*BA57),2) -> 0 | CU57: =AG57 -> 0 | CV57: =(AH57*AV57) -> 0 | CW57: =AI57 -> 0 | CX57: =AJ57 -> 0 | CY57: =(ROUND((((S57+ROUND((ROUND(((EU57)*AV57*1),2)*BS57),2))*AT57)/100),2)+ROUND(((ROUND((ROUND(((AE57-(EU57))*AV57*1),2)*BS57),2)*AT57)/100),2)) -> 0 | CZ57: =(ROUND((((S57+ROUND((ROUND(((EU57)*AV57*1),2)*BS57),2))*AU57)/100),2)+ROUND(((ROUND((ROUND(((AE57-(EU57))*AV57*1),2)*BS57),2)*AU57)/100),2)) -> 0 | DN57: 0 | DO57: 0 | DP57: 1 | DQ57: 1 | DU57: 1013 | DV57: ШТ | DW57: ШТ | DX57: 1 | EE57: 56938434 | EF57: 214 | EG57: Оборудование, отсутствующие в СНБ | EH57: 0 | EJ57: 3 | EK57: 400007 | EL57: Оборудование, отсутствующие в СНБ | EM57: Оборуд. КА | EQ57: 131088 | ER57: 0 | ES57: 39842.72 | ET57: 0 | EU57: 0 | EV57: 0 | EW57: 0 | EX57: 0 | EY57: 0 | EZ57: 5 | FC57: 1 | FD57: 18 | FF57: 353010 | FQ57: 0 | FR57: =P57 -> 301609.39 | FS57: 0 | FX57: 0 | FY57: 0 | GA57: [353 010 / 1,22 / 7,57] + 3% Трансп + 1,2% Заг.скл | GD57: 1 | GF57: -510697344 | GG57: 2 | GH57: 3 | GI57: 3 | GJ57: 0 | GK57: 0 | GL57: =ROUND(IF(AND(BH57=3,BI57=3,FS57<>0),P57,0),2) -> 0 | GM57: =ROUND(O57+X57+Y57,2)+GX57 -> 301609.39 | GN57: =IF(OR(BI57=0,BI57=1),GM57-GX57,0) -> 0 | GO57: =IF(BI57=2,GM57-GX57,0) -> 0 | GP57: =IF(BI57=4,GM57-GX57,0) -> 0 | GR57: 1 | GS57: 1 | GT57: 0 | GV57: =ROUND((GT57),6) -> 0 | GW57: 1 | GX57: =ROUND(HC57*I57,2) -> 0 | HA57: 0 | HB57: 0 | HC57: =GV57*GW57 -> 0 | HE57: 3 | HF57: 1,2 | HS57: 0 | IK57: 0
A58: 17 | B58: 1 | E58: 14 | F58: КА, п.18 | G58: Приточная установка КМО1 (L=1200 м3/ч, Pc=400 Па) | H58: ШТ | I58: 1 | J58: 0 | K58: 1 | O58: =ROUND(CP58,2) -> 34249.11 | P58: =ROUND((ROUND((AC58*AW58*I58),2)*BC58),2) -> 34249.11 | Q58: =(ROUND((ROUND(((ET58)*AV58*I58),2)*BB58),2)+ROUND((ROUND(((AE58-(EU58))*AV58*I58),2)*BS58),2)) -> 0 | R58: =(ROUND((ROUND(((EU58)*AV58*I58),2)*BS58),2)+ROUND((ROUND(((AE58-(EU58))*AV58*I58),2)*BS58),2)) -> 0 | S58: =ROUND((ROUND((AF58*AV58*I58),2)*BA58),2) -> 0 | T58: =ROUND(CU58*I58,2) -> 0 | U58: =CV58*I58 -> 0 | V58: =CW58*I58 -> 0 | W58: =ROUND(CX58*I58,2) -> 0 | X58: =(ROUND((((S58+ROUND((ROUND(((EU58)*AV58*I58),2)*BS58),2))*AT58)/100),2)+ROUND(((ROUND((ROUND(((AE58-(EU58))*AV58*I58),2)*BS58),2)*AT58)/100),2)) -> 0 | Y58: =(ROUND((((S58+ROUND((ROUND(((EU58)*AV58*I58),2)*BS58),2))*AU58)/100),2)+ROUND(((ROUND((ROUND(((AE58-(EU58))*AV58*I58),2)*BS58),2)*AU58)/100),2)) -> 0 | AA58: 56661434 | AB58: =ROUND((AC58+AD58+AF58),6) -> 34249.11 | AC58: =ROUND((ES58),6) -> 34249.11 | AD58: =ROUND((((ET58)-(EU58))+AE58),6) -> 0 | AE58: =ROUND((EU58),6) -> 0 | AF58: =ROUND((EV58),6) -> 0 | AG58: =ROUND((AP58),6) -> 0 | AH58: =(EW58) -> 0 | AI58: =(EX58) -> 0 | AJ58: =(AS58) -> 0 | AK58: 34249.11 | AL58: 34249.11 | AM58: 0 | AN58: 0 | AO58: 0 | AP58: 0 | AQ58: 0 | AR58: 0 | AS58: 0 | AT58: 0 | AU58: 0 | AV58: 1 | AW58: 1 | AZ58: 1 | BA58: 1 | BB58: 1 | BC58: 1 | BH58: 3 | BI58: 3 | BJ58: КА, п.18 | BM58: 400007 | BN58: 0 | BP58: 0 | BQ58: 214 | BR58: 0 | BS58: 1 | BT58: 1 | BU58: 1 | BV58: 1 | BW58: 1 | BX58: 1 | BZ58: 0 | CA58: 0 | CE58: 1566 | CF58: 0 | CG58: 0 | CM58: 0 | CO58: 0 | CP58: =(P58+Q58+S58) -> 34249.11 | CQ58: =ROUND((ROUND((AC58*AW58*1),2)*BC58),2) -> 34249.11 | CR58: =(ROUND((ROUND(((ET58)*AV58*1),2)*BB58),2)+ROUND((ROUND(((AE58-(EU58))*AV58*1),2)*BS58),2)) -> 0 | CS58: =(ROUND((ROUND(((EU58)*AV58*1),2)*BS58),2)+ROUND((ROUND(((AE58-(EU58))*AV58*1),2)*BS58),2)) -> 0 | CT58: =ROUND((ROUND((AF58*AV58*1),2)*BA58),2) -> 0 | CU58: =AG58 -> 0 | CV58: =(AH58*AV58) -> 0 | CW58: =AI58 -> 0 | CX58: =AJ58 -> 0 | CY58: =(ROUND((((S58+ROUND((ROUND(((EU58)*AV58*1),2)*BS58),2))*AT58)/100),2)+ROUND(((ROUND((ROUND(((AE58-(EU58))*AV58*1),2)*BS58),2)*AT58)/100),2)) -> 0 | CZ58: =(ROUND((((S58+ROUND((ROUND(((EU58)*AV58*1),2)*BS58),2))*AU58)/100),2)+ROUND(((ROUND((ROUND(((AE58-(EU58))*AV58*1),2)*BS58),2)*AU58)/100),2)) -> 0 | DN58: 0 | DO58: 0 | DP58: 1 | DQ58: 1 | DU58: 1013 | DV58: ШТ | DW58: ШТ | DX58: 1 | EE58: 56938434 | EF58: 214 | EG58: Оборудование, отсутствующие в СНБ | EH58: 0 | EJ58: 3 | EK58: 400007 | EL58: Оборудование, отсутствующие в СНБ | EM58: Оборуд. КА | EQ58: 131088 | ER58: 0 | ES58: 34249.11 | ET58: 0 | EU58: 0 | EV58: 0 | EW58: 0 | EX58: 0 | EY58: 0 | FQ58: 0 | FR58: =P58 -> 34249.11 | FS58: 0 | FX58: 0 | FY58: 0 | GA58: [303 450 / 1,22 / 7,57] + 3% Трансп + 1,2% Заг.скл | GD58: 1 | GF58: -1242068422 | GG58: 2 | GH58: 4 | GI58: -2 | GJ58: 0 | GK58: 0 | GL58: =ROUND(IF(AND(BH58=3,BI58=3,FS58<>0),P58,0),2) -> 0 | GM58: =ROUND(O58+X58+Y58,2)+GX58 -> 34249.11 | GN58: =IF(OR(BI58=0,BI58=1),GM58-GX58,0) -> 0 | GO58: =IF(BI58=2,GM58-GX58,0) -> 0 | GP58: =IF(BI58=4,GM58-GX58,0) -> 0 | GR58: 1 | GS58: 2 | GT58: 0 | GV58: =ROUND((GT58),6) -> 0 | GW58: 1 | GX58: =ROUND(HC58*I58,2) -> 0 | HA58: 0 | HB58: 0 | HC58: =GV58*GW58 -> 0 | HE58: 3 | HF58: 1,2 | HS58: 0 | IK58: 0
A59: 17 | B59: 1 | E59: 14 | F59: КА, п.18 | G59: Приточная установка КМО1 (L=1200 м3/ч, Pc=400 Па) | H59: ШТ | I59: 1 | J59: 0 | K59: 1 | O59: =ROUND(CP59,2) -> 259265.76 | P59: =ROUND((ROUND((AC59*AW59*I59),2)*BC59),2) -> 259265.76 | Q59: =(ROUND((ROUND(((ET59)*AV59*I59),2)*BB59),2)+ROUND((ROUND(((AE59-(EU59))*AV59*I59),2)*BS59),2)) -> 0 | R59: =(ROUND((ROUND(((EU59)*AV59*I59),2)*BS59),2)+ROUND((ROUND(((AE59-(EU59))*AV59*I59),2)*BS59),2)) -> 0 | S59: =ROUND((ROUND((AF59*AV59*I59),2)*BA59),2) -> 0 | T59: =ROUND(CU59*I59,2) -> 0 | U59: =CV59*I59 -> 0 | V59: =CW59*I59 -> 0 | W59: =ROUND(CX59*I59,2) -> 0 | X59: =(ROUND((((S59+ROUND((ROUND(((EU59)*AV59*I59),2)*BS59),2))*AT59)/100),2)+ROUND(((ROUND((ROUND(((AE59-(EU59))*AV59*I59),2)*BS59),2)*AT59)/100),2)) -> 0 | Y59: =(ROUND((((S59+ROUND((ROUND(((EU59)*AV59*I59),2)*BS59),2))*AU59)/100),2)+ROUND(((ROUND((ROUND(((AE59-(EU59))*AV59*I59),2)*BS59),2)*AU59)/100),2)) -> 0 | AA59: 56661436 | AB59: =ROUND((AC59+AD59+AF59),6) -> 34249.11 | AC59: =ROUND((ES59),6) -> 34249.11 | AD59: =ROUND((((ET59)-(EU59))+AE59),6) -> 0 | AE59: =ROUND((EU59),6) -> 0 | AF59: =ROUND((EV59),6) -> 0 | AG59: =ROUND((AP59),6) -> 0 | AH59: =(EW59) -> 0 | AI59: =(EX59) -> 0 | AJ59: =(AS59) -> 0 | AK59: 34249.11 | AL59: 34249.11 | AM59: 0 | AN59: 0 | AO59: 0 | AP59: 0 | AQ59: 0 | AR59: 0 | AS59: 0 | AT59: 0 | AU59: 0 | AV59: 1 | AW59: 1 | AZ59: 1 | BA59: 1 | BB59: 1 | BC59: 7.57 | BH59: 3 | BI59: 3 | BJ59: КА, п.18 | BM59: 400007 | BN59: 0 | BP59: 0 | BQ59: 214 | BR59: 0 | BS59: 1 | BT59: 1 | BU59: 1 | BV59: 1 | BW59: 1 | BX59: 1 | BZ59: 0 | CA59: 0 | CE59: 1566 | CF59: 0 | CG59: 0 | CM59: 0 | CO59: 0 | CP59: =(P59+Q59+S59) -> 259265.76 | CQ59: =ROUND((ROUND((AC59*AW59*1),2)*BC59),2) -> 259265.76 | CR59: =(ROUND((ROUND(((ET59)*AV59*1),2)*BB59),2)+ROUND((ROUND(((AE59-(EU59))*AV59*1),2)*BS59),2)) -> 0 | CS59: =(ROUND((ROUND(((EU59)*AV59*1),2)*BS59),2)+ROUND((ROUND(((AE59-(EU59))*AV59*1),2)*BS59),2)) -> 0 | CT59: =ROUND((ROUND((AF59*AV59*1),2)*BA59),2) -> 0 | CU59: =AG59 -> 0 | CV59: =(AH59*AV59) -> 0 | CW59: =AI59 -> 0 | CX59: =AJ59 -> 0 | CY59: =(ROUND((((S59+ROUND((ROUND(((EU59)*AV59*1),2)*BS59),2))*AT59)/100),2)+ROUND(((ROUND((ROUND(((AE59-(EU59))*AV59*1),2)*BS59),2)*AT59)/100),2)) -> 0 | CZ59: =(ROUND((((S59+ROUND((ROUND(((EU59)*AV59*1),2)*BS59),2))*AU59)/100),2)+ROUND(((ROUND((ROUND(((AE59-(EU59))*AV59*1),2)*BS59),2)*AU59)/100),2)) -> 0 | DN59: 0 | DO59: 0 | DP59: 1 | DQ59: 1 | DU59: 1013 | DV59: ШТ | DW59: ШТ | DX59: 1 | EE59: 56938434 | EF59: 214 | EG59: Оборудование, отсутствующие в СНБ | EH59: 0 | EJ59: 3 | EK59: 400007 | EL59: Оборудование, отсутствующие в СНБ | EM59: Оборуд. КА | EQ59: 131088 | ER59: 0 | ES59: 34249.11 | ET59: 0 | EU59: 0 | EV59: 0 | EW59: 0 | EX59: 0 | EY59: 0 | EZ59: 5 | FC59: 1 | FD59: 18 | FF59: 303450 | FQ59: 0 | FR59: =P59 -> 259265.76 | FS59: 0 | FX59: 0 | FY59: 0 | GA59: [303 450 / 1,22 / 7,57] + 3% Трансп + 1,2% Заг.скл | GD59: 1 | GF59: -1242068422 | GG59: 2 | GH59: 3 | GI59: 3 | GJ59: 0 | GK59: 0 | GL59: =ROUND(IF(AND(BH59=3,BI59=3,FS59<>0),P59,0),2) -> 0 | GM59: =ROUND(O59+X59+Y59,2)+GX59 -> 259265.76 | GN59: =IF(OR(BI59=0,BI59=1),GM59-GX59,0) -> 0 | GO59: =IF(BI59=2,GM59-GX59,0) -> 0 | GP59: =IF(BI59=4,GM59-GX59,0) -> 0 | GR59: 1 | GS59: 1 | GT59: 0 | GV59: =ROUND((GT59),6) -> 0 | GW59: 1 | GX59: =ROUND(HC59*I59,2) -> 0 | HA59: 0 | HB59: 0 | HC59: =GV59*GW59 -> 0 | HE59: 3 | HF59: 1,2 | HS59: 0 | IK59: 0
A60: 17 | B60: 1 | E60: 15 | F60: КА, п.20 | G60: Приточная установка КМО2 (L=180 м3/ч, Pc=300 Па) | H60: ШТ | I60: 1 | J60: 0 | K60: 1 | O60: =ROUND(CP60,2) -> 12253.83 | P60: =ROUND((ROUND((AC60*AW60*I60),2)*BC60),2) -> 12253.83 | Q60: =(ROUND((ROUND(((ET60)*AV60*I60),2)*BB60),2)+ROUND((ROUND(((AE60-(EU60))*AV60*I60),2)*BS60),2)) -> 0 | R60: =(ROUND((ROUND(((EU60)*AV60*I60),2)*BS60),2)+ROUND((ROUND(((AE60-(EU60))*AV60*I60),2)*BS60),2)) -> 0 | S60: =ROUND((ROUND((AF60*AV60*I60),2)*BA60),2) -> 0 | T60: =ROUND(CU60*I60,2) -> 0 | U60: =CV60*I60 -> 0 | V60: =CW60*I60 -> 0 | W60: =ROUND(CX60*I60,2) -> 0 | X60: =(ROUND((((S60+ROUND((ROUND(((EU60)*AV60*I60),2)*BS60),2))*AT60)/100),2)+ROUND(((ROUND((ROUND(((AE60-(EU60))*AV60*I60),2)*BS60),2)*AT60)/100),2)) -> 0 | Y60: =(ROUND((((S60+ROUND((ROUND(((EU60)*AV60*I60),2)*BS60),2))*AU60)/100),2)+ROUND(((ROUND((ROUND(((AE60-(EU60))*AV60*I60),2)*BS60),2)*AU60)/100),2)) -> 0 | AA60: 56661434 | AB60: =ROUND((AC60+AD60+AF60),6) -> 12253.83 | AC60: =ROUND((ES60),6) -> 12253.83 | AD60: =ROUND((((ET60)-(EU60))+AE60),6) -> 0 | AE60: =ROUND((EU60),6) -> 0 | AF60: =ROUND((EV60),6) -> 0 | AG60: =ROUND((AP60),6) -> 0 | AH60: =(EW60) -> 0 | AI60: =(EX60) -> 0 | AJ60: =(AS60) -> 0 | AK60: 12253.83 | AL60: 12253.83 | AM60: 0 | AN60: 0 | AO60: 0 | AP60: 0 | AQ60: 0 | AR60: 0 | AS60: 0 | AT60: 0 | AU60: 0 | AV60: 1 | AW60: 1 | AZ60: 1 | BA60: 1 | BB60: 1 | BC60: 1 | BH60: 3 | BI60: 3 | BJ60: КА, п.20 | BM60: 400007 | BN60: 0 | BP60: 0 | BQ60: 214 | BR60: 0 | BS60: 1 | BT60: 1 | BU60: 1 | BV60: 1 | BW60: 1 | BX60: 1 | BZ60: 0 | CA60: 0 | CE60: 1566 | CF60: 0 | CG60: 0 | CM60: 0 | CO60: 0 | CP60: =(P60+Q60+S60) -> 12253.83 | CQ60: =ROUND((ROUND((AC60*AW60*1),2)*BC60),2) -> 12253.83 | CR60: =(ROUND((ROUND(((ET60)*AV60*1),2)*BB60),2)+ROUND((ROUND(((AE60-(EU60))*AV60*1),2)*BS60),2)) -> 0 | CS60: =(ROUND((ROUND(((EU60)*AV60*1),2)*BS60),2)+ROUND((ROUND(((AE60-(EU60))*AV60*1),2)*BS60),2)) -> 0 | CT60: =ROUND((ROUND((AF60*AV60*1),2)*BA60),2) -> 0 | CU60: =AG60 -> 0 | CV60: =(AH60*AV60) -> 0 | CW60: =AI60 -> 0 | CX60: =AJ60 -> 0 | CY60: =(ROUND((((S60+ROUND((ROUND(((EU60)*AV60*1),2)*BS60),2))*AT60)/100),2)+ROUND(((ROUND((ROUND(((AE60-(EU60))*AV60*1),2)*BS60),2)*AT60)/100),2)) -> 0 | CZ60: =(ROUND((((S60+ROUND((ROUND(((EU60)*AV60*1),2)*BS60),2))*AU60)/100),2)+ROUND(((ROUND((ROUND(((AE60-(EU60))*AV60*1),2)*BS60),2)*AU60)/100),2)) -> 0 | DN60: 0 | DO60: 0 | DP60: 1 | DQ60: 1 | DU60: 1013 | DV60: ШТ | DW60: ШТ | DX60: 1 | EE60: 56938434 | EF60: 214 | EG60: Оборудование, отсутствующие в СНБ | EH60: 0 | EJ60: 3 | EK60: 400007 | EL60: Оборудование, отсутствующие в СНБ | EM60: Оборуд. КА | EQ60: 131088 | ER60: 0 | ES60: 12253.83 | ET60: 0 | EU60: 0 | EV60: 0 | EW60: 0 | EX60: 0 | EY60: 0 | FQ60: 0 | FR60: =P60 -> 12253.83 | FS60: 0 | FX60: 0 | FY60: 0 | GA60: [108 570 / 1,22 / 7,57] + 3% Трансп + 1,2% Заг.скл | GD60: 1 | GF60: 1407849693 | GG60: 2 | GH60: 4 | GI60: -2 | GJ60: 0 | GK60: 0 | GL60: =ROUND(IF(AND(BH60=3,BI60=3,FS60<>0),P60,0),2) -> 0 | GM60: =ROUND(O60+X60+Y60,2)+GX60 -> 12253.83 | GN60: =IF(OR(BI60=0,BI60=1),GM60-GX60,0) -> 0 | GO60: =IF(BI60=2,GM60-GX60,0) -> 0 | GP60: =IF(BI60=4,GM60-GX60,0) -> 0 | GR60: 1 | GS60: 2 | GT60: 0 | GV60: =ROUND((GT60),6) -> 0 | GW60: 1 | GX60: =ROUND(HC60*I60,2) -> 0 | HA60: 0 | HB60: 0 | HC60: =GV60*GW60 -> 0 | HE60: 3 | HF60: 1,2 | HS60: 0 | IK60: 0
A61: 17 | B61: 1 | E61: 15 | F61: КА, п.20 | G61: Приточная установка КМО2 (L=180 м3/ч, Pc=300 Па) | H61: ШТ | I61: 1 | J61: 0 | K61: 1 | O61: =ROUND(CP61,2) -> 92761.49 | P61: =ROUND((ROUND((AC61*AW61*I61),2)*BC61),2) -> 92761.49 | Q61: =(ROUND((ROUND(((ET61)*AV61*I61),2)*BB61),2)+ROUND((ROUND(((AE61-(EU61))*AV61*I61),2)*BS61),2)) -> 0 | R61: =(ROUND((ROUND(((EU61)*AV61*I61),2)*BS61),2)+ROUND((ROUND(((AE61-(EU61))*AV61*I61),2)*BS61),2)) -> 0 | S61: =ROUND((ROUND((AF61*AV61*I61),2)*BA61),2) -> 0 | T61: =ROUND(CU61*I61,2) -> 0 | U61: =CV61*I61 -> 0 | V61: =CW61*I61 -> 0 | W61: =ROUND(CX61*I61,2) -> 0 | X61: =(ROUND((((S61+ROUND((ROUND(((EU61)*AV61*I61),2)*BS61),2))*AT61)/100),2)+ROUND(((ROUND((ROUND(((AE61-(EU61))*AV61*I61),2)*BS61),2)*AT61)/100),2)) -> 0 | Y61: =(ROUND((((S61+ROUND((ROUND(((EU61)*AV61*I61),2)*BS61),2))*AU61)/100),2)+ROUND(((ROUND((ROUND(((AE61-(EU61))*AV61*I61),2)*BS61),2)*AU61)/100),2)) -> 0 | AA61: 56661436 | AB61: =ROUND((AC61+AD61+AF61),6) -> 12253.83 | AC61: =ROUND((ES61),6) -> 12253.83 | AD61: =ROUND((((ET61)-(EU61))+AE61),6) -> 0 | AE61: =ROUND((EU61),6) -> 0 | AF61: =ROUND((EV61),6) -> 0 | AG61: =ROUND((AP61),6) -> 0 | AH61: =(EW61) -> 0 | AI61: =(EX61) -> 0 | AJ61: =(AS61) -> 0 | AK61: 12253.83 | AL61: 12253.83 | AM61: 0 | AN61: 0 | AO61: 0 | AP61: 0 | AQ61: 0 | AR61: 0 | AS61: 0 | AT61: 0 | AU61: 0 | AV61: 1 | AW61: 1 | AZ61: 1 | BA61: 1 | BB61: 1 | BC61: 7.57 | BH61: 3 | BI61: 3 | BJ61: КА, п.20 | BM61: 400007 | BN61: 0 | BP61: 0 | BQ61: 214 | BR61: 0 | BS61: 1 | BT61: 1 | BU61: 1 | BV61: 1 | BW61: 1 | BX61: 1 | BZ61: 0 | CA61: 0 | CE61: 1566 | CF61: 0 | CG61: 0 | CM61: 0 | CO61: 0 | CP61: =(P61+Q61+S61) -> 92761.49 | CQ61: =ROUND((ROUND((AC61*AW61*1),2)*BC61),2) -> 92761.49 | CR61: =(ROUND((ROUND(((ET61)*AV61*1),2)*BB61),2)+ROUND((ROUND(((AE61-(EU61))*AV61*1),2)*BS61),2)) -> 0 | CS61: =(ROUND((ROUND(((EU61)*AV61*1),2)*BS61),2)+ROUND((ROUND(((AE61-(EU61))*AV61*1),2)*BS61),2)) -> 0 | CT61: =ROUND((ROUND((AF61*AV61*1),2)*BA61),2) -> 0 | CU61: =AG61 -> 0 | CV61: =(AH61*AV61) -> 0 | CW61: =AI61 -> 0 | CX61: =AJ61 -> 0 | CY61: =(ROUND((((S61+ROUND((ROUND(((EU61)*AV61*1),2)*BS61),2))*AT61)/100),2)+ROUND(((ROUND((ROUND(((AE61-(EU61))*AV61*1),2)*BS61),2)*AT61)/100),2)) -> 0 | CZ61: =(ROUND((((S61+ROUND((ROUND(((EU61)*AV61*1),2)*BS61),2))*AU61)/100),2)+ROUND(((ROUND((ROUND(((AE61-(EU61))*AV61*1),2)*BS61),2)*AU61)/100),2)) -> 0 | DN61: 0 | DO61: 0 | DP61: 1 | DQ61: 1 | DU61: 1013 | DV61: ШТ | DW61: ШТ | DX61: 1 | EE61: 56938434 | EF61: 214 | EG61: Оборудование, отсутствующие в СНБ | EH61: 0 | EJ61: 3 | EK61: 400007 | EL61: Оборудование, отсутствующие в СНБ | EM61: Оборуд. КА | EQ61: 131088 | ER61: 0 | ES61: 12253.83 | ET61: 0 | EU61: 0 | EV61: 0 | EW61: 0 | EX61: 0 | EY61: 0 | EZ61: 5 | FC61: 1 | FD61: 18 | FF61: 108570 | FQ61: 0 | FR61: =P61 -> 92761.49 | FS61: 0 | FX61: 0 | FY61: 0 | GA61: [108 570 / 1,22 / 7,57] + 3% Трансп + 1,2% Заг.скл | GD61: 1 | GF61: 1407849693 | GG61: 2 | GH61: 3 | GI61: 3 | GJ61: 0 | GK61: 0 | GL61: =ROUND(IF(AND(BH61=3,BI61=3,FS61<>0),P61,0),2) -> 0 | GM61: =ROUND(O61+X61+Y61,2)+GX61 -> 92761.49 | GN61: =IF(OR(BI61=0,BI61=1),GM61-GX61,0) -> 0 | GO61: =IF(BI61=2,GM61-GX61,0) -> 0 | GP61: =IF(BI61=4,GM61-GX61,0) -> 0 | GR61: 1 | GS61: 1 | GT61: 0 | GV61: =ROUND((GT61),6) -> 0 | GW61: 1 | GX61: =ROUND(HC61*I61,2) -> 0 | HA61: 0 | HB61: 0 | HC61: =GV61*GW61 -> 0 | HE61: 3 | HF61: 1,2 | HS61: 0 | IK61: 0
A62: 17 | B62: 1 | E62: 16 | F62: КА, п.21 | G62: Приточная установка КМО3 (L=120 м3/ч, Pc=300 Па) | H62: ШТ | I62: 1 | J62: 0 | K62: 1 | O62: =ROUND(CP62,2) -> 10701.35 | P62: =ROUND((ROUND((AC62*AW62*I62),2)*BC62),2) -> 10701.35 | Q62: =(ROUND((ROUND(((ET62)*AV62*I62),2)*BB62),2)+ROUND((ROUND(((AE62-(EU62))*AV62*I62),2)*BS62),2)) -> 0 | R62: =(ROUND((ROUND(((EU62)*AV62*I62),2)*BS62),2)+ROUND((ROUND(((AE62-(EU62))*AV62*I62),2)*BS62),2)) -> 0 | S62: =ROUND((ROUND((AF62*AV62*I62),2)*BA62),2) -> 0 | T62: =ROUND(CU62*I62,2) -> 0 | U62: =CV62*I62 -> 0 | V62: =CW62*I62 -> 0 | W62: =ROUND(CX62*I62,2) -> 0 | X62: =(ROUND((((S62+ROUND((ROUND(((EU62)*AV62*I62),2)*BS62),2))*AT62)/100),2)+ROUND(((ROUND((ROUND(((AE62-(EU62))*AV62*I62),2)*BS62),2)*AT62)/100),2)) -> 0 | Y62: =(ROUND((((S62+ROUND((ROUND(((EU62)*AV62*I62),2)*BS62),2))*AU62)/100),2)+ROUND(((ROUND((ROUND(((AE62-(EU62))*AV62*I62),2)*BS62),2)*AU62)/100),2)) -> 0 | AA62: 56661434 | AB62: =ROUND((AC62+AD62+AF62),6) -> 10701.35 | AC62: =ROUND((ES62),6) -> 10701.35 | AD62: =ROUND((((ET62)-(EU62))+AE62),6) -> 0 | AE62: =ROUND((EU62),6) -> 0 | AF62: =ROUND((EV62),6) -> 0 | AG62: =ROUND((AP62),6) -> 0 | AH62: =(EW62) -> 0 | AI62: =(EX62) -> 0 | AJ62: =(AS62) -> 0 | AK62: 10701.35 | AL62: 10701.35 | AM62: 0 | AN62: 0 | AO62: 0 | AP62: 0 | AQ62: 0 | AR62: 0 | AS62: 0 | AT62: 0 | AU62: 0 | AV62: 1 | AW62: 1 | AZ62: 1 | BA62: 1 | BB62: 1 | BC62: 1 | BH62: 3 | BI62: 3 | BJ62: КА, п.21 | BM62: 400007 | BN62: 0 | BP62: 0 | BQ62: 214 | BR62: 0 | BS62: 1 | BT62: 1 | BU62: 1 | BV62: 1 | BW62: 1 | BX62: 1 | BZ62: 0 | CA62: 0 | CE62: 1566 | CF62: 0 | CG62: 0 | CM62: 0 | CO62: 0 | CP62: =(P62+Q62+S62) -> 10701.35 | CQ62: =ROUND((ROUND((AC62*AW62*1),2)*BC62),2) -> 10701.35 | CR62: =(ROUND((ROUND(((ET62)*AV62*1),2)*BB62),2)+ROUND((ROUND(((AE62-(EU62))*AV62*1),2)*BS62),2)) -> 0 | CS62: =(ROUND((ROUND(((EU62)*AV62*1),2)*BS62),2)+ROUND((ROUND(((AE62-(EU62))*AV62*1),2)*BS62),2)) -> 0 | CT62: =ROUND((ROUND((AF62*AV62*1),2)*BA62),2) -> 0 | CU62: =AG62 -> 0 | CV62: =(AH62*AV62) -> 0 | CW62: =AI62 -> 0 | CX62: =AJ62 -> 0 | CY62: =(ROUND((((S62+ROUND((ROUND(((EU62)*AV62*1),2)*BS62),2))*AT62)/100),2)+ROUND(((ROUND((ROUND(((AE62-(EU62))*AV62*1),2)*BS62),2)*AT62)/100),2)) -> 0 | CZ62: =(ROUND((((S62+ROUND((ROUND(((EU62)*AV62*1),2)*BS62),2))*AU62)/100),2)+ROUND(((ROUND((ROUND(((AE62-(EU62))*AV62*1),2)*BS62),2)*AU62)/100),2)) -> 0 | DN62: 0 | DO62: 0 | DP62: 1 | DQ62: 1 | DU62: 1013 | DV62: ШТ | DW62: ШТ | DX62: 1 | EE62: 56938434 | EF62: 214 | EG62: Оборудование, отсутствующие в СНБ | EH62: 0 | EJ62: 3 | EK62: 400007 | EL62: Оборудование, отсутствующие в СНБ | EM62: Оборуд. КА | EQ62: 131088 | ER62: 0 | ES62: 10701.35 | ET62: 0 | EU62: 0 | EV62: 0 | EW62: 0 | EX62: 0 | EY62: 0 | FQ62: 0 | FR62: =P62 -> 10701.35 | FS62: 0 | FX62: 0 | FY62: 0 | GA62: [94 815 / 1,22 / 7,57] + 3% Трансп + 1,2% Заг.скл | GD62: 1 | GF62: -179790922 | GG62: 2 | GH62: 4 | GI62: -2 | GJ62: 0 | GK62: 0 | GL62: =ROUND(IF(AND(BH62=3,BI62=3,FS62<>0),P62,0),2) -> 0 | GM62: =ROUND(O62+X62+Y62,2)+GX62 -> 10701.35 | GN62: =IF(OR(BI62=0,BI62=1),GM62-GX62,0) -> 0 | GO62: =IF(BI62=2,GM62-GX62,0) -> 0 | GP62: =IF(BI62=4,GM62-GX62,0) -> 0 | GR62: 1 | GS62: 2 | GT62: 0 | GV62: =ROUND((GT62),6) -> 0 | GW62: 1 | GX62: =ROUND(HC62*I62,2) -> 0 | HA62: 0 | HB62: 0 | HC62: =GV62*GW62 -> 0 | HE62: 3 | HF62: 1,2 | HS62: 0 | IK62: 0
A63: 17 | B63: 1 | E63: 16 | F63: КА, п.21 | G63: Приточная установка КМО3 (L=120 м3/ч, Pc=300 Па) | H63: ШТ | I63: 1 | J63: 0 | K63: 1 | O63: =ROUND(CP63,2) -> 81009.22 | P63: =ROUND((ROUND((AC63*AW63*I63),2)*BC63),2) -> 81009.22 | Q63: =(ROUND((ROUND(((ET63)*AV63*I63),2)*BB63),2)+ROUND((ROUND(((AE63-(EU63))*AV63*I63),2)*BS63),2)) -> 0 | R63: =(ROUND((ROUND(((EU63)*AV63*I63),2)*BS63),2)+ROUND((ROUND(((AE63-(EU63))*AV63*I63),2)*BS63),2)) -> 0 | S63: =ROUND((ROUND((AF63*AV63*I63),2)*BA63),2) -> 0 | T63: =ROUND(CU63*I63,2) -> 0 | U63: =CV63*I63 -> 0 | V63: =CW63*I63 -> 0 | W63: =ROUND(CX63*I63,2) -> 0 | X63: =(ROUND((((S63+ROUND((ROUND(((EU63)*AV63*I63),2)*BS63),2))*AT63)/100),2)+ROUND(((ROUND((ROUND(((AE63-(EU63))*AV63*I63),2)*BS63),2)*AT63)/100),2)) -> 0 | Y63: =(ROUND((((S63+ROUND((ROUND(((EU63)*AV63*I63),2)*BS63),2))*AU63)/100),2)+ROUND(((ROUND((ROUND(((AE63-(EU63))*AV63*I63),2)*BS63),2)*AU63)/100),2)) -> 0 | AA63: 56661436 | AB63: =ROUND((AC63+AD63+AF63),6) -> 10701.35 | AC63: =ROUND((ES63),6) -> 10701.35 | AD63: =ROUND((((ET63)-(EU63))+AE63),6) -> 0 | AE63: =ROUND((EU63),6) -> 0 | AF63: =ROUND((EV63),6) -> 0 | AG63: =ROUND((AP63),6) -> 0 | AH63: =(EW63) -> 0 | AI63: =(EX63) -> 0 | AJ63: =(AS63) -> 0 | AK63: 10701.35 | AL63: 10701.35 | AM63: 0 | AN63: 0 | AO63: 0 | AP63: 0 | AQ63: 0 | AR63: 0 | AS63: 0 | AT63: 0 | AU63: 0 | AV63: 1 | AW63: 1 | AZ63: 1 | BA63: 1 | BB63: 1 | BC63: 7.57 | BH63: 3 | BI63: 3 | BJ63: КА, п.21 | BM63: 400007 | BN63: 0 | BP63: 0 | BQ63: 214 | BR63: 0 | BS63: 1 | BT63: 1 | BU63: 1 | BV63: 1 | BW63: 1 | BX63: 1 | BZ63: 0 | CA63: 0 | CE63: 1566 | CF63: 0 | CG63: 0 | CM63: 0 | CO63: 0 | CP63: =(P63+Q63+S63) -> 81009.22 | CQ63: =ROUND((ROUND((AC63*AW63*1),2)*BC63),2) -> 81009.22 | CR63: =(ROUND((ROUND(((ET63)*AV63*1),2)*BB63),2)+ROUND((ROUND(((AE63-(EU63))*AV63*1),2)*BS63),2)) -> 0 | CS63: =(ROUND((ROUND(((EU63)*AV63*1),2)*BS63),2)+ROUND((ROUND(((AE63-(EU63))*AV63*1),2)*BS63),2)) -> 0 | CT63: =ROUND((ROUND((AF63*AV63*1),2)*BA63),2) -> 0 | CU63: =AG63 -> 0 | CV63: =(AH63*AV63) -> 0 | CW63: =AI63 -> 0 | CX63: =AJ63 -> 0 | CY63: =(ROUND((((S63+ROUND((ROUND(((EU63)*AV63*1),2)*BS63),2))*AT63)/100),2)+ROUND(((ROUND((ROUND(((AE63-(EU63))*AV63*1),2)*BS63),2)*AT63)/100),2)) -> 0 | CZ63: =(ROUND((((S63+ROUND((ROUND(((EU63)*AV63*1),2)*BS63),2))*AU63)/100),2)+ROUND(((ROUND((ROUND(((AE63-(EU63))*AV63*1),2)*BS63),2)*AU63)/100),2)) -> 0 | DN63: 0 | DO63: 0 | DP63: 1 | DQ63: 1 | DU63: 1013 | DV63: ШТ | DW63: ШТ | DX63: 1 | EE63: 56938434 | EF63: 214 | EG63: Оборудование, отсутствующие в СНБ | EH63: 0 | EJ63: 3 | EK63: 400007 | EL63: Оборудование, отсутствующие в СНБ | EM63: Оборуд. КА | EQ63: 131088 | ER63: 0 | ES63: 10701.35 | ET63: 0 | EU63: 0 | EV63: 0 | EW63: 0 | EX63: 0 | EY63: 0 | EZ63: 5 | FC63: 1 | FD63: 18 | FF63: 94815 | FQ63: 0 | FR63: =P63 -> 81009.22 | FS63: 0 | FX63: 0 | FY63: 0 | GA63: [94 815 / 1,22 / 7,57] + 3% Трансп + 1,2% Заг.скл | GD63: 1 | GF63: -179790922 | GG63: 2 | GH63: 3 | GI63: 3 | GJ63: 0 | GK63: 0 | GL63: =ROUND(IF(AND(BH63=3,BI63=3,FS63<>0),P63,0),2) -> 0 | GM63: =ROUND(O63+X63+Y63,2)+GX63 -> 81009.22 | GN63: =IF(OR(BI63=0,BI63=1),GM63-GX63,0) -> 0 | GO63: =IF(BI63=2,GM63-GX63,0) -> 0 | GP63: =IF(BI63=4,GM63-GX63,0) -> 0 | GR63: 1 | GS63: 1 | GT63: 0 | GV63: =ROUND((GT63),6) -> 0 | GW63: 1 | GX63: =ROUND(HC63*I63,2) -> 0 | HA63: 0 | HB63: 0 | HC63: =GV63*GW63 -> 0 | HE63: 3 | HF63: 1,2 | HS63: 0 | IK63: 0
A64: 17 | B64: 1 | E64: 17 | F64: КА, п.22 | G64: Приточная установка КМО4 (L=950 м3/ч, Pc=300 Па) | H64: ШТ | I64: 1 | J64: 0 | K64: 1 | O64: =ROUND(CP64,2) -> 31120.46 | P64: =ROUND((ROUND((AC64*AW64*I64),2)*BC64),2) -> 31120.46 | Q64: =(ROUND((ROUND(((ET64)*AV64*I64),2)*BB64),2)+ROUND((ROUND(((AE64-(EU64))*AV64*I64),2)*BS64),2)) -> 0 | R64: =(ROUND((ROUND(((EU64)*AV64*I64),2)*BS64),2)+ROUND((ROUND(((AE64-(EU64))*AV64*I64),2)*BS64),2)) -> 0 | S64: =ROUND((ROUND((AF64*AV64*I64),2)*BA64),2) -> 0 | T64: =ROUND(CU64*I64,2) -> 0 | U64: =CV64*I64 -> 0 | V64: =CW64*I64 -> 0 | W64: =ROUND(CX64*I64,2) -> 0 | X64: =(ROUND((((S64+ROUND((ROUND(((EU64)*AV64*I64),2)*BS64),2))*AT64)/100),2)+ROUND(((ROUND((ROUND(((AE64-(EU64))*AV64*I64),2)*BS64),2)*AT64)/100),2)) -> 0 | Y64: =(ROUND((((S64+ROUND((ROUND(((EU64)*AV64*I64),2)*BS64),2))*AU64)/100),2)+ROUND(((ROUND((ROUND(((AE64-(EU64))*AV64*I64),2)*BS64),2)*AU64)/100),2)) -> 0 | AA64: 56661434 | AB64: =ROUND((AC64+AD64+AF64),6) -> 31120.46 | AC64: =ROUND((ES64),6) -> 31120.46 | AD64: =ROUND((((ET64)-(EU64))+AE64),6) -> 0 | AE64: =ROUND((EU64),6) -> 0 | AF64: =ROUND((EV64),6) -> 0 | AG64: =ROUND((AP64),6) -> 0 | AH64: =(EW64) -> 0 | AI64: =(EX64) -> 0 | AJ64: =(AS64) -> 0 | AK64: 31120.46 | AL64: 31120.46 | AM64: 0 | AN64: 0 | AO64: 0 | AP64: 0 | AQ64: 0 | AR64: 0 | AS64: 0 | AT64: 0 | AU64: 0 | AV64: 1 | AW64: 1 | AZ64: 1 | BA64: 1 | BB64: 1 | BC64: 1 | BH64: 3 | BI64: 3 | BJ64: КА, п.22 | BM64: 400007 | BN64: 0 | BP64: 0 | BQ64: 214 | BR64: 0 | BS64: 1 | BT64: 1 | BU64: 1 | BV64: 1 | BW64: 1 | BX64: 1 | BZ64: 0 | CA64: 0 | CE64: 1566 | CF64: 0 | CG64: 0 | CM64: 0 | CO64: 0 | CP64: =(P64+Q64+S64) -> 31120.46 | CQ64: =ROUND((ROUND((AC64*AW64*1),2)*BC64),2) -> 31120.46 | CR64: =(ROUND((ROUND(((ET64)*AV64*1),2)*BB64),2)+ROUND((ROUND(((AE64-(EU64))*AV64*1),2)*BS64),2)) -> 0 | CS64: =(ROUND((ROUND(((EU64)*AV64*1),2)*BS64),2)+ROUND((ROUND(((AE64-(EU64))*AV64*1),2)*BS64),2)) -> 0 | CT64: =ROUND((ROUND((AF64*AV64*1),2)*BA64),2) -> 0 | CU64: =AG64 -> 0 | CV64: =(AH64*AV64) -> 0 | CW64: =AI64 -> 0 | CX64: =AJ64 -> 0 | CY64: =(ROUND((((S64+ROUND((ROUND(((EU64)*AV64*1),2)*BS64),2))*AT64)/100),2)+ROUND(((ROUND((ROUND(((AE64-(EU64))*AV64*1),2)*BS64),2)*AT64)/100),2)) -> 0 | CZ64: =(ROUND((((S64+ROUND((ROUND(((EU64)*AV64*1),2)*BS64),2))*AU64)/100),2)+ROUND(((ROUND((ROUND(((AE64-(EU64))*AV64*1),2)*BS64),2)*AU64)/100),2)) -> 0 | DN64: 0 | DO64: 0 | DP64: 1 | DQ64: 1 | DU64: 1013 | DV64: ШТ | DW64: ШТ | DX64: 1 | EE64: 56938434 | EF64: 214 | EG64: Оборудование, отсутствующие в СНБ | EH64: 0 | EJ64: 3 | EK64: 400007 | EL64: Оборудование, отсутствующие в СНБ | EM64: Оборуд. КА | EQ64: 131088 | ER64: 0 | ES64: 31120.46 | ET64: 0 | EU64: 0 | EV64: 0 | EW64: 0 | EX64: 0 | EY64: 0 | FQ64: 0 | FR64: =P64 -> 31120.46 | FS64: 0 | FX64: 0 | FY64: 0 | GA64: [275 730 / 1,22 / 7,57] + 3% Трансп + 1,2% Заг.скл | GD64: 1 | GF64: 1271001187 | GG64: 2 | GH64: 4 | GI64: -2 | GJ64: 0 | GK64: 0 | GL64: =ROUND(IF(AND(BH64=3,BI64=3,FS64<>0),P64,0),2) -> 0 | GM64: =ROUND(O64+X64+Y64,2)+GX64 -> 31120.46 | GN64: =IF(OR(BI64=0,BI64=1),GM64-GX64,0) -> 0 | GO64: =IF(BI64=2,GM64-GX64,0) -> 0 | GP64: =IF(BI64=4,GM64-GX64,0) -> 0 | GR64: 1 | GS64: 2 | GT64: 0 | GV64: =ROUND((GT64),6) -> 0 | GW64: 1 | GX64: =ROUND(HC64*I64,2) -> 0 | HA64: 0 | HB64: 0 | HC64: =GV64*GW64 -> 0 | HE64: 3 | HF64: 1,2 | HS64: 0 | IK64: 0
A65: 17 | B65: 1 | E65: 17 | F65: КА, п.22 | G65: Приточная установка КМО4 (L=950 м3/ч, Pc=300 Па) | H65: ШТ | I65: 1 | J65: 0 | K65: 1 | O65: =ROUND(CP65,2) -> 235581.88 | P65: =ROUND((ROUND((AC65*AW65*I65),2)*BC65),2) -> 235581.88 | Q65: =(ROUND((ROUND(((ET65)*AV65*I65),2)*BB65),2)+ROUND((ROUND(((AE65-(EU65))*AV65*I65),2)*BS65),2)) -> 0 | R65: =(ROUND((ROUND(((EU65)*AV65*I65),2)*BS65),2)+ROUND((ROUND(((AE65-(EU65))*AV65*I65),2)*BS65),2)) -> 0 | S65: =ROUND((ROUND((AF65*AV65*I65),2)*BA65),2) -> 0 | T65: =ROUND(CU65*I65,2) -> 0 | U65: =CV65*I65 -> 0 | V65: =CW65*I65 -> 0 | W65: =ROUND(CX65*I65,2) -> 0 | X65: =(ROUND((((S65+ROUND((ROUND(((EU65)*AV65*I65),2)*BS65),2))*AT65)/100),2)+ROUND(((ROUND((ROUND(((AE65-(EU65))*AV65*I65),2)*BS65),2)*AT65)/100),2)) -> 0 | Y65: =(ROUND((((S65+ROUND((ROUND(((EU65)*AV65*I65),2)*BS65),2))*AU65)/100),2)+ROUND(((ROUND((ROUND(((AE65-(EU65))*AV65*I65),2)*BS65),2)*AU65)/100),2)) -> 0 | AA65: 56661436 | AB65: =ROUND((AC65+AD65+AF65),6) -> 31120.46 | AC65: =ROUND((ES65),6) -> 31120.46 | AD65: =ROUND((((ET65)-(EU65))+AE65),6) -> 0 | AE65: =ROUND((EU65),6) -> 0 | AF65: =ROUND((EV65),6) -> 0 | AG65: =ROUND((AP65),6) -> 0 | AH65: =(EW65) -> 0 | AI65: =(EX65) -> 0 | AJ65: =(AS65) -> 0 | AK65: 31120.46 | AL65: 31120.46 | AM65: 0 | AN65: 0 | AO65: 0 | AP65: 0 | AQ65: 0 | AR65: 0 | AS65: 0 | AT65: 0 | AU65: 0 | AV65: 1 | AW65: 1 | AZ65: 1 | BA65: 1 | BB65: 1 | BC65: 7.57 | BH65: 3 | BI65: 3 | BJ65: КА, п.22 | BM65: 400007 | BN65: 0 | BP65: 0 | BQ65: 214 | BR65: 0 | BS65: 1 | BT65: 1 | BU65: 1 | BV65: 1 | BW65: 1 | BX65: 1 | BZ65: 0 | CA65: 0 | CE65: 1566 | CF65: 0 | CG65: 0 | CM65: 0 | CO65: 0 | CP65: =(P65+Q65+S65) -> 235581.88 | CQ65: =ROUND((ROUND((AC65*AW65*1),2)*BC65),2) -> 235581.88 | CR65: =(ROUND((ROUND(((ET65)*AV65*1),2)*BB65),2)+ROUND((ROUND(((AE65-(EU65))*AV65*1),2)*BS65),2)) -> 0 | CS65: =(ROUND((ROUND(((EU65)*AV65*1),2)*BS65),2)+ROUND((ROUND(((AE65-(EU65))*AV65*1),2)*BS65),2)) -> 0 | CT65: =ROUND((ROUND((AF65*AV65*1),2)*BA65),2) -> 0 | CU65: =AG65 -> 0 | CV65: =(AH65*AV65) -> 0 | CW65: =AI65 -> 0 | CX65: =AJ65 -> 0 | CY65: =(ROUND((((S65+ROUND((ROUND(((EU65)*AV65*1),2)*BS65),2))*AT65)/100),2)+ROUND(((ROUND((ROUND(((AE65-(EU65))*AV65*1),2)*BS65),2)*AT65)/100),2)) -> 0 | CZ65: =(ROUND((((S65+ROUND((ROUND(((EU65)*AV65*1),2)*BS65),2))*AU65)/100),2)+ROUND(((ROUND((ROUND(((AE65-(EU65))*AV65*1),2)*BS65),2)*AU65)/100),2)) -> 0 | DN65: 0 | DO65: 0 | DP65: 1 | DQ65: 1 | DU65: 1013 | DV65: ШТ | DW65: ШТ | DX65: 1 | EE65: 56938434 | EF65: 214 | EG65: Оборудование, отсутствующие в СНБ | EH65: 0 | EJ65: 3 | EK65: 400007 | EL65: Оборудование, отсутствующие в СНБ | EM65: Оборуд. КА | EQ65: 131088 | ER65: 0 | ES65: 31120.46 | ET65: 0 | EU65: 0 | EV65: 0 | EW65: 0 | EX65: 0 | EY65: 0 | EZ65: 5 | FC65: 1 | FD65: 18 | FF65: 275730 | FQ65: 0 | FR65: =P65 -> 235581.88 | FS65: 0 | FX65: 0 | FY65: 0 | GA65: [275 730 / 1,22 / 7,57] + 3% Трансп + 1,2% Заг.скл | GD65: 1 | GF65: 1271001187 | GG65: 2 | GH65: 3 | GI65: 3 | GJ65: 0 | GK65: 0 | GL65: =ROUND(IF(AND(BH65=3,BI65=3,FS65<>0),P65,0),2) -> 0 | GM65: =ROUND(O65+X65+Y65,2)+GX65 -> 235581.88 | GN65: =IF(OR(BI65=0,BI65=1),GM65-GX65,0) -> 0 | GO65: =IF(BI65=2,GM65-GX65,0) -> 0 | GP65: =IF(BI65=4,GM65-GX65,0) -> 0 | GR65: 1 | GS65: 1 | GT65: 0 | GV65: =ROUND((GT65),6) -> 0 | GW65: 1 | GX65: =ROUND(HC65*I65,2) -> 0 | HA65: 0 | HB65: 0 | HC65: =GV65*GW65 -> 0 | HE65: 3 | HF65: 1,2 | HS65: 0 | IK65: 0
A66: 17 | B66: 1 | C66: =ROW(SmtRes!A45) -> 45 | D66: =ROW(EtalonRes!A48) -> 48 | E66: 18 | F66: 3.20-40-2 | G66: Установка камер приточных типовых и установок приточных без секции орошения производительностью до 20 тыс.м3/час | H66: 1 КАМЕРА | I66: 1 | J66: 0 | K66: 1 | O66: =ROUND(CP66,2) -> 1651.78 | P66: =ROUND((ROUND((AC66*AW66*I66),2)*BC66),2) -> 372.01 | Q66: =(ROUND((ROUND((((((ET66*1.05)*1.25)*1.2))*AV66*I66),2)*BB66),2)+ROUND((ROUND(((AE66-((((EU66*1.05)*1.25)*1.2)))*AV66*I66),2)*BS66),2)) -> 241.93 | R66: =(ROUND((ROUND((((((EU66*1.05)*1.25)*1.2))*AV66*I66),2)*BS66),2)+ROUND((ROUND(((AE66-((((EU66*1.05)*1.25)*1.2)))*AV66*I66),2)*BS66),2)) -> 25.31 | S66: =ROUND((ROUND((AF66*AV66*I66),2)*BA66),2) -> 1037.84 | T66: =ROUND(CU66*I66,2) -> 0 | U66: =CV66*I66 -> 86.271431 | V66: =CW66*I66 -> 0 | W66: =ROUND(CX66*I66,2) -> 0 | X66: =(ROUND((((S66+ROUND((ROUND((((((EU66*1.05)*1.25)*1.2))*AV66*I66),2)*BS66),2))*AT66)/100),2)+ROUND(((ROUND((ROUND(((AE66-((((EU66*1.05)*1.25)*1.2)))*AV66*I66),2)*BS66),2)*AT66)/100),2)) -> 1158.83 | Y66: =(ROUND((((S66+ROUND((ROUND((((((EU66*1.05)*1.25)*1.2))*AV66*I66),2)*BS66),2))*AU66)/100),2)+ROUND(((ROUND((ROUND(((AE66-((((EU66*1.05)*1.25)*1.2)))*AV66*I66),2)*BS66),2)*AU66)/100),2)) -> 648.52 | AA66: 56661434 | AB66: =ROUND((AC66+AD66+AF66),6) -> 1571.4172 | AC66: =ROUND(((((ES66*1)*1)*1)),6) -> 372.01 | AD66: =ROUND(((((((ET66*1.05)*1.25)*1.2))-((((EU66*1.05)*1.25)*1.2)))+AE66),6) -> 226.737 | AE66: =ROUND(((((EU66*1.05)*1.25)*1.2)),6) -> 23.7195 | AF66: =ROUND(((((EV66*1.05)*1.15)*1.2)),6) -> 972.67023 | AG66: =ROUND((AP66),6) -> 0 | AH66: =((((EW66*1.05)*1.15)*1.2)) -> 80.8542 | AI66: =((((EX66*1.05)*1.25)*1.2)) -> 0 | AJ66: =(AS66) -> 0 | AK66: 1187.24 | AL66: 372.01 | AM66: 143.96 | AN66: 15.06 | AO66: 671.27 | AP66: 0 | AQ66: 55.8 | AR66: 0 | AS66: 0 | AT66: 109 | AU66: 61 | AV66: 1.067 | AW66: 1 | AZ66: 1 | BA66: 1 | BB66: 1 | BC66: 1 | BH66: 0 | BI66: 1 | BJ66: ТСН-2001.3 Доп. 79, Сб. 20, т. 40, поз. 2 | BM66: 25 | BN66: 0 | BO66: 3.20-40-2 | BP66: 1 | BQ66: 30 | BR66: 0 | BS66: 1 | BT66: 1 | BU66: 1 | BV66: 1 | BW66: 1 | BX66: 1 | BZ66: 109 | CA66: 61 | CE66: 1566 | CF66: 0 | CG66: 0 | CM66: 0 | CN66: Поправка: 3-20. О.П. п.1.5 Наименование: Затраты на индивидуальные испытания систем вентиляции и кондиционирования воздуха Поправка: Гл.6.Прил.2.2.п.2.2.6_06.00.01.07.001 Наименование: При выполнении при капитальном ремонте и реконструкции работ, аналогичных технологическим процессам, характерным для нового строительства, и отсутствующих в сборниках на ремонтно-строительные работы ТСН-2001.6 Поправка: Гл.12.Прил.8.п.8. 3_12.00.01.11.001 Наименование: При наличии напряженных и стесненных условий производства работ (стесненность, сложность складирования и транспортной логистики и т.п.) для объектов, расположенных в пределах круговой магистральной системы улиц "Садовое кольцо" города Москвы | CO66: 0 | CP66: =(P66+Q66+S66) -> 1651.78 | CQ66: =ROUND((ROUND((AC66*AW66*1),2)*BC66),2) -> 372.01 | CR66: =(ROUND((ROUND((((((ET66*1.05)*1.25)*1.2))*AV66*1),2)*BB66),2)+ROUND((ROUND(((AE66-((((EU66*1.05)*1.25)*1.2)))*AV66*1),2)*BS66),2)) -> 241.93 | CS66: =(ROUND((ROUND((((((EU66*1.05)*1.25)*1.2))*AV66*1),2)*BS66),2)+ROUND((ROUND(((AE66-((((EU66*1.05)*1.25)*1.2)))*AV66*1),2)*BS66),2)) -> 25.31 | CT66: =ROUND((ROUND((AF66*AV66*1),2)*BA66),2) -> 1037.84 | CU66: =AG66 -> 0 | CV66: =(AH66*AV66) -> 86.271431 | CW66: =AI66 -> 0 | CX66: =AJ66 -> 0 | CY66: =(ROUND((((S66+ROUND((ROUND((((((EU66*1.05)*1.25)*1.2))*AV66*1),2)*BS66),2))*AT66)/100),2)+ROUND(((ROUND((ROUND(((AE66-((((EU66*1.05)*1.25)*1.2)))*AV66*1),2)*BS66),2)*AT66)/100),2)) -> 1158.83 | CZ66: =(ROUND((((S66+ROUND((ROUND((((((EU66*1.05)*1.25)*1.2))*AV66*1),2)*BS66),2))*AU66)/100),2)+ROUND(((ROUND((ROUND(((AE66-((((EU66*1.05)*1.25)*1.2)))*AV66*1),2)*BS66),2)*AU66)/100),2)) -> 648.52 | DB66: 1 | DD66: *1)*1)*1 | DE66: *1,05)*1,25)*1,2 | DF66: *1,05)*1,25)*1,2 | DG66: *1,05)*1,15)*1,2 | DI66: *1,05)*1,15)*1,2 | DJ66: *1,05)*1,25)*1,2 | DN66: 0 | DO66: 0 | DP66: 1 | DQ66: 1 | DU66: 1013 | DV66: 1 КАМЕРА | DW66: 1 КАМЕРА | DX66: 1 | EE66: 56938458 | EF66: 30 | EG66: Строительные работы | EH66: 0 | EJ66: 1 | EK66: 25 | EL66: ТСН-2001.3-20. Вентиляция и кондиционирование воздуха | EM66: ТСН-2001.3-20-1 | EO66: Поправка: 3-20. О.П. п.1.5 Поправка: Гл.6.Прил.2.2.п.2.2.6_06.00.01.07.001 Поправка: Гл.12.Прил.8.п.8. 3_12.00.01.11.001 | EQ66: 131072 | ER66: 1187.24 | ES66: 372.01 | ET66: 143.96 | EU66: 15.06 | EV66: 671.27 | EW66: 55.8 | EX66: 0 | EY66: 0 | FQ66: 0 | FR66: 0 | FS66: 0 | FX66: 109 | FY66: 61 | GD66: 1 | GF66: -592376583 | GG66: 2 | GH66: 1 | GI66: 2 | GJ66: 0 | GK66: 0 | GL66: =ROUND(IF(AND(BH66=3,BI66=3,FS66<>0),P66,0),2) -> 0 | GM66: =ROUND(O66+X66+Y66,2)+GX66 -> 3459.13 | GN66: =IF(OR(BI66=0,BI66=1),GM66-GX66,0) -> 3459.13 | GO66: =IF(BI66=2,GM66-GX66,0) -> 0 | GP66: =IF(BI66=4,GM66-GX66,0) -> 0 | GR66: 0 | GS66: 3 | GT66: 0 | GV66: =ROUND((GT66),6) -> 0 | GW66: 1 | GX66: =ROUND(HC66*I66,2) -> 0 | HA66: 0 | HB66: 0 | HC66: =GV66*GW66 -> 0 | HS66: 0 | IK66: 0
A67: 17 | B67: 1 | C67: =ROW(SmtRes!A60) -> 60 | D67: =ROW(EtalonRes!A64) -> 64 | E67: 18 | F67: 3.20-40-2 | G67: Установка камер приточных типовых и установок приточных без секции орошения производительностью до 20 тыс.м3/час | H67: 1 КАМЕРА | I67: 1 | J67: 0 | K67: 1 | O67: =ROUND(CP67,2) -> 65117.85 | P67: =ROUND((ROUND((AC67*AW67*I67),2)*BC67),2) -> 2938.88 | Q67: =(ROUND((ROUND((((((ET67*1.05)*1.25)*1.2))*AV67*I67),2)*BB67),2)+ROUND((ROUND(((AE67-((((EU67*1.05)*1.25)*1.2)))*AV67*I67),2)*BS67),2)) -> 3696.69 | R67: =(ROUND((ROUND((((((EU67*1.05)*1.25)*1.2))*AV67*I67),2)*BS67),2)+ROUND((ROUND(((AE67-((((EU67*1.05)*1.25)*1.2)))*AV67*I67),2)*BS67),2)) -> 1426.22 | S67: =ROUND((ROUND((AF67*AV67*I67),2)*BA67),2) -> 58482.28 | T67: =ROUND(CU67*I67,2) -> 0 | U67: =CV67*I67 -> 86.271431 | V67: =CW67*I67 -> 0 | W67: =ROUND(CX67*I67,2) -> 0 | X67: =(ROUND((((S67+ROUND((ROUND((((((EU67*1.05)*1.25)*1.2))*AV67*I67),2)*BS67),2))*AT67)/100),2)+ROUND(((ROUND((ROUND(((AE67-((((EU67*1.05)*1.25)*1.2)))*AV67*I67),2)*BS67),2)*AT67)/100),2)) -> 65300.27 | Y67: =(ROUND((((S67+ROUND((ROUND((((((EU67*1.05)*1.25)*1.2))*AV67*I67),2)*BS67),2))*AU67)/100),2)+ROUND(((ROUND((ROUND(((AE67-((((EU67*1.05)*1.25)*1.2)))*AV67*I67),2)*BS67),2)*AU67)/100),2)) -> 36544.19 | AA67: 56661436 | AB67: =ROUND((AC67+AD67+AF67),6) -> 1571.4172 | AC67: =ROUND(((((ES67*1)*1)*1)),6) -> 372.01 | AD67: =ROUND(((((((ET67*1.05)*1.25)*1.2))-((((EU67*1.05)*1.25)*1.2)))+AE67),6) -> 226.737 | AE67: =ROUND(((((EU67*1.05)*1.25)*1.2)),6) -> 23.7195 | AF67: =ROUND(((((EV67*1.05)*1.15)*1.2)),6) -> 972.67023 | AG67: =ROUND((AP67),6) -> 0 | AH67: =((((EW67*1.05)*1.15)*1.2)) -> 80.8542 | AI67: =((((EX67*1.05)*1.25)*1.2)) -> 0 | AJ67: =(AS67) -> 0 | AK67: 1187.24 | AL67: 372.01 | AM67: 143.96 | AN67: 15.06 | AO67: 671.27 | AP67: 0 | AQ67: 55.8 | AR67: 0 | AS67: 0 | AT67: 109 | AU67: 61 | AV67: 1.067 | AW67: 1 | AZ67: 1 | BA67: 56.35 | BB67: 15.28 | BC67: 7.9 | BH67: 0 | BI67: 1 | BJ67: ТСН-2001.3 Доп. 79, Сб. 20, т. 40, поз. 2 | BM67: 25 | BN67: 0 | BO67: 3.20-40-2 | BP67: 1 | BQ67: 30 | BR67: 0 | BS67: 56.35 | BT67: 1 | BU67: 1 | BV67: 1 | BW67: 1 | BX67: 1 | BZ67: 109 | CA67: 61 | CE67: 1566 | CF67: 0 | CG67: 0 | CM67: 0 | CN67: Поправка: 3-20. О.П. п.1.5 Наименование: Затраты на индивидуальные испытания систем вентиляции и кондиционирования воздуха Поправка: Гл.6.Прил.2.2.п.2.2.6_06.00.01.07.001 Наименование: При выполнении при капитальном ремонте и реконструкции работ, аналогичных технологическим процессам, характерным для нового строительства, и отсутствующих в сборниках на ремонтно-строительные работы ТСН-2001.6 Поправка: Гл.12.Прил.8.п.8. 3_12.00.01.11.001 Наименование: При наличии напряженных и стесненных условий производства работ (стесненность, сложность складирования и транспортной логистики и т.п.) для объектов, расположенных в пределах круговой магистральной системы улиц "Садовое кольцо" города Москвы | CO67: 0 | CP67: =(P67+Q67+S67) -> 65117.85 | CQ67: =ROUND((ROUND((AC67*AW67*1),2)*BC67),2) -> 2938.88 | CR67: =(ROUND((ROUND((((((ET67*1.05)*1.25)*1.2))*AV67*1),2)*BB67),2)+ROUND((ROUND(((AE67-((((EU67*1.05)*1.25)*1.2)))*AV67*1),2)*BS67),2)) -> 3696.69 | CS67: =(ROUND((ROUND((((((EU67*1.05)*1.25)*1.2))*AV67*1),2)*BS67),2)+ROUND((ROUND(((AE67-((((EU67*1.05)*1.25)*1.2)))*AV67*1),2)*BS67),2)) -> 1426.22 | CT67: =ROUND((ROUND((AF67*AV67*1),2)*BA67),2) -> 58482.28 | CU67: =AG67 -> 0 | CV67: =(AH67*AV67) -> 86.271431 | CW67: =AI67 -> 0 | CX67: =AJ67 -> 0 | CY67: =(ROUND((((S67+ROUND((ROUND((((((EU67*1.05)*1.25)*1.2))*AV67*1),2)*BS67),2))*AT67)/100),2)+ROUND(((ROUND((ROUND(((AE67-((((EU67*1.05)*1.25)*1.2)))*AV67*1),2)*BS67),2)*AT67)/100),2)) -> 65300.27 | CZ67: =(ROUND((((S67+ROUND((ROUND((((((EU67*1.05)*1.25)*1.2))*AV67*1),2)*BS67),2))*AU67)/100),2)+ROUND(((ROUND((ROUND(((AE67-((((EU67*1.05)*1.25)*1.2)))*AV67*1),2)*BS67),2)*AU67)/100),2)) -> 36544.19 | DB67: 4 | DD67: *1)*1)*1 | DE67: *1,05)*1,25)*1,2 | DF67: *1,05)*1,25)*1,2 | DG67: *1,05)*1,15)*1,2 | DI67: *1,05)*1,15)*1,2 | DJ67: *1,05)*1,25)*1,2 | DN67: 0 | DO67: 0 | DP67: 1 | DQ67: 1 | DU67: 1013 | DV67: 1 КАМЕРА | DW67: 1 КАМЕРА | DX67: 1 | EE67: 56938458 | EF67: 30 | EG67: Строительные работы | EH67: 0 | EJ67: 1 | EK67: 25 | EL67: ТСН-2001.3-20. Вентиляция и кондиционирование воздуха | EM67: ТСН-2001.3-20-1 | EO67: Поправка: 3-20. О.П. п.1.5 Поправка: Гл.6.Прил.2.2.п.2.2.6_06.00.01.07.001 Поправка: Гл.12.Прил.8.п.8. 3_12.00.01.11.001 | EQ67: 131072 | ER67: 1187.24 | ES67: 372.01 | ET67: 143.96 | EU67: 15.06 | EV67: 671.27 | EW67: 55.8 | EX67: 0 | EY67: 0 | FQ67: 0 | FR67: 0 | FS67: 0 | FX67: 109 | FY67: 61 | GD67: 1 | GF67: -592376583 | GG67: 2 | GH67: 1 | GI67: 2 | GJ67: 0 | GK67: 0 | GL67: =ROUND(IF(AND(BH67=3,BI67=3,FS67<>0),P67,0),2) -> 0 | GM67: =ROUND(O67+X67+Y67,2)+GX67 -> 166962.31 | GN67: =IF(OR(BI67=0,BI67=1),GM67-GX67,0) -> 166962.31 | GO67: =IF(BI67=2,GM67-GX67,0) -> 0 | GP67: =IF(BI67=4,GM67-GX67,0) -> 0 | GR67: 0 | GS67: 3 | GT67: 0 | GV67: =ROUND((GT67),6) -> 0 | GW67: 1 | GX67: =ROUND(HC67*I67,2) -> 0 | HA67: 0 | HB67: 0 | HC67: =GV67*GW67 -> 0 | HS67: 0 | IK67: 0
A68: 17 | B68: 1 | E68: 19 | F68: КА, п.13 | G68: Приточная установка П9 (L=2045м3/ч, Pc=500 Па) | H68: ШТ | I68: 1 | J68: 0 | K68: 1 | O68: =ROUND(CP68,2) -> 39842.72 | P68: =ROUND((ROUND((AC68*AW68*I68),2)*BC68),2) -> 39842.72 | Q68: =(ROUND((ROUND(((ET68)*AV68*I68),2)*BB68),2)+ROUND((ROUND(((AE68-(EU68))*AV68*I68),2)*BS68),2)) -> 0 | R68: =(ROUND((ROUND(((EU68)*AV68*I68),2)*BS68),2)+ROUND((ROUND(((AE68-(EU68))*AV68*I68),2)*BS68),2)) -> 0 | S68: =ROUND((ROUND((AF68*AV68*I68),2)*BA68),2) -> 0 | T68: =ROUND(CU68*I68,2) -> 0 | U68: =CV68*I68 -> 0 | V68: =CW68*I68 -> 0 | W68: =ROUND(CX68*I68,2) -> 0 | X68: =(ROUND((((S68+ROUND((ROUND(((EU68)*AV68*I68),2)*BS68),2))*AT68)/100),2)+ROUND(((ROUND((ROUND(((AE68-(EU68))*AV68*I68),2)*BS68),2)*AT68)/100),2)) -> 0 | Y68: =(ROUND((((S68+ROUND((ROUND(((EU68)*AV68*I68),2)*BS68),2))*AU68)/100),2)+ROUND(((ROUND((ROUND(((AE68-(EU68))*AV68*I68),2)*BS68),2)*AU68)/100),2)) -> 0 | AA68: 56661434 | AB68: =ROUND((AC68+AD68+AF68),6) -> 39842.72 | AC68: =ROUND((ES68),6) -> 39842.72 | AD68: =ROUND((((ET68)-(EU68))+AE68),6) -> 0 | AE68: =ROUND((EU68),6) -> 0 | AF68: =ROUND((EV68),6) -> 0 | AG68: =ROUND((AP68),6) -> 0 | AH68: =(EW68) -> 0 | AI68: =(EX68) -> 0 | AJ68: =(AS68) -> 0 | AK68: 39842.72 | AL68: 39842.72 | AM68: 0 | AN68: 0 | AO68: 0 | AP68: 0 | AQ68: 0 | AR68: 0 | AS68: 0 | AT68: 0 | AU68: 0 | AV68: 1 | AW68: 1 | AZ68: 1 | BA68: 1 | BB68: 1 | BC68: 1 | BH68: 3 | BI68: 3 | BJ68: КА, п.13 | BM68: 400007 | BN68: 0 | BP68: 0 | BQ68: 214 | BR68: 0 | BS68: 1 | BT68: 1 | BU68: 1 | BV68: 1 | BW68: 1 | BX68: 1 | BZ68: 0 | CA68: 0 | CE68: 1566 | CF68: 0 | CG68: 0 | CM68: 0 | CO68: 0 | CP68: =(P68+Q68+S68) -> 39842.72 | CQ68: =ROUND((ROUND((AC68*AW68*1),2)*BC68),2) -> 39842.72 | CR68: =(ROUND((ROUND(((ET68)*AV68*1),2)*BB68),2)+ROUND((ROUND(((AE68-(EU68))*AV68*1),2)*BS68),2)) -> 0 | CS68: =(ROUND((ROUND(((EU68)*AV68*1),2)*BS68),2)+ROUND((ROUND(((AE68-(EU68))*AV68*1),2)*BS68),2)) -> 0 | CT68: =ROUND((ROUND((AF68*AV68*1),2)*BA68),2) -> 0 | CU68: =AG68 -> 0 | CV68: =(AH68*AV68) -> 0 | CW68: =AI68 -> 0 | CX68: =AJ68 -> 0 | CY68: =(ROUND((((S68+ROUND((ROUND(((EU68)*AV68*1),2)*BS68),2))*AT68)/100),2)+ROUND(((ROUND((ROUND(((AE68-(EU68))*AV68*1),2)*BS68),2)*AT68)/100),2)) -> 0 | CZ68: =(ROUND((((S68+ROUND((ROUND(((EU68)*AV68*1),2)*BS68),2))*AU68)/100),2)+ROUND(((ROUND((ROUND(((AE68-(EU68))*AV68*1),2)*BS68),2)*AU68)/100),2)) -> 0 | DN68: 0 | DO68: 0 | DP68: 1 | DQ68: 1 | DU68: 1013 | DV68: ШТ | DW68: ШТ | DX68: 1 | EE68: 56938434 | EF68: 214 | EG68: Оборудование, отсутствующие в СНБ | EH68: 0 | EJ68: 3 | EK68: 400007 | EL68: Оборудование, отсутствующие в СНБ | EM68: Оборуд. КА | EQ68: 131088 | ER68: 0 | ES68: 39842.72 | ET68: 0 | EU68: 0 | EV68: 0 | EW68: 0 | EX68: 0 | EY68: 0 | FQ68: 0 | FR68: =P68 -> 39842.72 | FS68: 0 | FX68: 0 | FY68: 0 | GA68: [353 010 / 1,22 / 7,57] + 3% Трансп + 1,2% Заг.скл | GD68: 1 | GF68: 2119159757 | GG68: 2 | GH68: 4 | GI68: -2 | GJ68: 0 | GK68: 0 | GL68: =ROUND(IF(AND(BH68=3,BI68=3,FS68<>0),P68,0),2) -> 0 | GM68: =ROUND(O68+X68+Y68,2)+GX68 -> 39842.72 | GN68: =IF(OR(BI68=0,BI68=1),GM68-GX68,0) -> 0 | GO68: =IF(BI68=2,GM68-GX68,0) -> 0 | GP68: =IF(BI68=4,GM68-GX68,0) -> 0 | GR68: 1 | GS68: 2 | GT68: 0 | GV68: =ROUND((GT68),6) -> 0 | GW68: 1 | GX68: =ROUND(HC68*I68,2) -> 0 | HA68: 0 | HB68: 0 | HC68: =GV68*GW68 -> 0 | HE68: 3 | HF68: 1,2 | HS68: 0 | IK68: 0
A69: 17 | B69: 1 | E69: 19 | F69: КА, п.13 | G69: Приточная установка П9 (L=2045м3/ч, Pc=500 Па) | H69: ШТ | I69: 1 | J69: 0 | K69: 1 | O69: =ROUND(CP69,2) -> 301609.39 | P69: =ROUND((ROUND((AC69*AW69*I69),2)*BC69),2) -> 301609.39 | Q69: =(ROUND((ROUND(((ET69)*AV69*I69),2)*BB69),2)+ROUND((ROUND(((AE69-(EU69))*AV69*I69),2)*BS69),2)) -> 0 | R69: =(ROUND((ROUND(((EU69)*AV69*I69),2)*BS69),2)+ROUND((ROUND(((AE69-(EU69))*AV69*I69),2)*BS69),2)) -> 0 | S69: =ROUND((ROUND((AF69*AV69*I69),2)*BA69),2) -> 0 | T69: =ROUND(CU69*I69,2) -> 0 | U69: =CV69*I69 -> 0 | V69: =CW69*I69 -> 0 | W69: =ROUND(CX69*I69,2) -> 0 | X69: =(ROUND((((S69+ROUND((ROUND(((EU69)*AV69*I69),2)*BS69),2))*AT69)/100),2)+ROUND(((ROUND((ROUND(((AE69-(EU69))*AV69*I69),2)*BS69),2)*AT69)/100),2)) -> 0 | Y69: =(ROUND((((S69+ROUND((ROUND(((EU69)*AV69*I69),2)*BS69),2))*AU69)/100),2)+ROUND(((ROUND((ROUND(((AE69-(EU69))*AV69*I69),2)*BS69),2)*AU69)/100),2)) -> 0 | AA69: 56661436 | AB69: =ROUND((AC69+AD69+AF69),6) -> 39842.72 | AC69: =ROUND((ES69),6) -> 39842.72 | AD69: =ROUND((((ET69)-(EU69))+AE69),6) -> 0 | AE69: =ROUND((EU69),6) -> 0 | AF69: =ROUND((EV69),6) -> 0 | AG69: =ROUND((AP69),6) -> 0 | AH69: =(EW69) -> 0 | AI69: =(EX69) -> 0 | AJ69: =(AS69) -> 0 | AK69: 39842.72 | AL69: 39842.72 | AM69: 0 | AN69: 0 | AO69: 0 | AP69: 0 | AQ69: 0 | AR69: 0 | AS69: 0 | AT69: 0 | AU69: 0 | AV69: 1 | AW69: 1 | AZ69: 1 | BA69: 1 | BB69: 1 | BC69: 7.57 | BH69: 3 | BI69: 3 | BJ69: КА, п.13 | BM69: 400007 | BN69: 0 | BP69: 0 | BQ69: 214 | BR69: 0 | BS69: 1 | BT69: 1 | BU69: 1 | BV69: 1 | BW69: 1 | BX69: 1 | BZ69: 0 | CA69: 0 | CE69: 1566 | CF69: 0 | CG69: 0 | CM69: 0 | CO69: 0 | CP69: =(P69+Q69+S69) -> 301609.39 | CQ69: =ROUND((ROUND((AC69*AW69*1),2)*BC69),2) -> 301609.39 | CR69: =(ROUND((ROUND(((ET69)*AV69*1),2)*BB69),2)+ROUND((ROUND(((AE69-(EU69))*AV69*1),2)*BS69),2)) -> 0 | CS69: =(ROUND((ROUND(((EU69)*AV69*1),2)*BS69),2)+ROUND((ROUND(((AE69-(EU69))*AV69*1),2)*BS69),2)) -> 0 | CT69: =ROUND((ROUND((AF69*AV69*1),2)*BA69),2) -> 0 | CU69: =AG69 -> 0 | CV69: =(AH69*AV69) -> 0 | CW69: =AI69 -> 0 | CX69: =AJ69 -> 0 | CY69: =(ROUND((((S69+ROUND((ROUND(((EU69)*AV69*1),2)*BS69),2))*AT69)/100),2)+ROUND(((ROUND((ROUND(((AE69-(EU69))*AV69*1),2)*BS69),2)*AT69)/100),2)) -> 0 | CZ69: =(ROUND((((S69+ROUND((ROUND(((EU69)*AV69*1),2)*BS69),2))*AU69)/100),2)+ROUND(((ROUND((ROUND(((AE69-(EU69))*AV69*1),2)*BS69),2)*AU69)/100),2)) -> 0 | DN69: 0 | DO69: 0 | DP69: 1 | DQ69: 1 | DU69: 1013 | DV69: ШТ | DW69: ШТ | DX69: 1 | EE69: 56938434 | EF69: 214 | EG69: Оборудование, отсутствующие в СНБ | EH69: 0 | EJ69: 3 | EK69: 400007 | EL69: Оборудование, отсутствующие в СНБ | EM69: Оборуд. КА | EQ69: 131088 | ER69: 0 | ES69: 39842.72 | ET69: 0 | EU69: 0 | EV69: 0 | EW69: 0 | EX69: 0 | EY69: 0 | EZ69: 5 | FC69: 1 | FD69: 18 | FF69: 353010 | FQ69: 0 | FR69: =P69 -> 301609.39 | FS69: 0 | FX69: 0 | FY69: 0 | GA69: [353 010 / 1,22 / 7,57] + 3% Трансп + 1,2% Заг.скл | GD69: 1 | GF69: 2119159757 | GG69: 2 | GH69: 3 | GI69: 3 | GJ69: 0 | GK69: 0 | GL69: =ROUND(IF(AND(BH69=3,BI69=3,FS69<>0),P69,0),2) -> 0 | GM69: =ROUND(O69+X69+Y69,2)+GX69 -> 301609.39 | GN69: =IF(OR(BI69=0,BI69=1),GM69-GX69,0) -> 0 | GO69: =IF(BI69=2,GM69-GX69,0) -> 0 | GP69: =IF(BI69=4,GM69-GX69,0) -> 0 | GR69: 1 | GS69: 1 | GT69: 0 | GV69: =ROUND((GT69),6) -> 0 | GW69: 1 | GX69: =ROUND(HC69*I69,2) -> 0 | HA69: 0 | HB69: 0 | HC69: =GV69*GW69 -> 0 | HE69: 3 | HF69: 1,2 | HS69: 0 | IK69: 0
A71: 51 | B71: =B28 -> 1 | C71: =A28 -> 5 | D71: =ROW(A28) -> 28 | F71: =IF(F28<>"",F28,"") -> Новый подраздел | G71: =IF(G28<>"",G28,"") -> Приточные установки | H71: 0 | O71: =ROUND(AB71,2) -> 778582.9 | P71: =ROUND(AC71,2) -> 763458.88 | Q71: =ROUND(AD71,2) -> 2152.89 | R71: =ROUND(AE71,2) -> 218.1 | S71: =ROUND(AF71,2) -> 12971.13 | T71: =ROUND(AG71,2) -> 0 | U71: =AH71 -> 1078.2383 | V71: =AI71 -> 0 | W71: =ROUND(AJ71,2) -> 0 | X71: =ROUND(AK71,2) -> 14376.26 | Y71: =ROUND(AL71,2) -> 8045.43 | AB71: =ROUND(SUMIF(AA32:AA69,"=56661434",O32:O69),2) -> 778582.9 | AC71: =ROUND(SUMIF(AA32:AA69,"=56661434",P32:P69),2) -> 763458.88 | AD71: =ROUND(SUMIF(AA32:AA69,"=56661434",Q32:Q69),2) -> 2152.89 | AE71: =ROUND(SUMIF(AA32:AA69,"=56661434",R32:R69),2) -> 218.1 | AF71: =ROUND(SUMIF(AA32:AA69,"=56661434",S32:S69),2) -> 12971.13 | AG71: =ROUND(SUMIF(AA32:AA69,"=56661434",T32:T69),2) -> 0 | AH71: =SUMIF(AA32:AA69,"=56661434",U32:U69) -> 1078.2383 | AI71: =SUMIF(AA32:AA69,"=56661434",V32:V69) -> 0 | AJ71: =ROUND(SUMIF(AA32:AA69,"=56661434",W32:W69),2) -> 0 | AK71: =ROUND(SUMIF(AA32:AA69,"=56661434",X32:X69),2) -> 14376.26 | AL71: =ROUND(SUMIF(AA32:AA69,"=56661434",Y32:Y69),2) -> 8045.43 | AO71: =ROUND(BX71,2) -> 0 | AP71: =ROUND(BY71,2) -> 759512.31 | AQ71: =ROUND(BZ71,2) -> 0 | AR71: =ROUND(CA71,2) -> 801004.59 | AS71: =ROUND(CB71,2) -> 41492.28 | AT71: =ROUND(CC71,2) -> 0 | AU71: =ROUND(CD71,2) -> 0 | AV71: =ROUND(CE71,2) -> 763458.88 | ... BD71: =ROUND(CM71,2) -> 0 | BX71: =ROUND(SUMIF(AA32:AA69,"=56661434",FQ32:FQ69),2) -> 0 | BY71: =ROUND(SUMIF(AA32:AA69,"=56661434",FR32:FR69),2) -> 759512.31 | BZ71: =ROUND(SUMIF(AA32:AA69,"=56661434",GL32:GL69),2) -> 0 | CA71: =ROUND(SUMIF(AA32:AA69,"=56661434",GM32:GM69),2) -> 801004.59 | CB71: =ROUND(SUMIF(AA32:AA69,"=56661434",GN32:GN69),2) -> 41492.28 | CC71: =ROUND(SUMIF(AA32:AA69,"=56661434",GO32:GO69),2) -> 0 | CD71: =ROUND(SUMIF(AA32:AA69,"=56661434",GP32:GP69),2) -> 0 | CE71: =AC71-BX71 -> 763458.88 | CF71: =AC71-BY71 -> 3946.57 | CG71: =BX71-BZ71 -> 0 | CH71: =AC71-BX71-BY71+BZ71 -> 3946.57 | CI71: =BY71-BZ71 -> 759512.31 | CJ71: =ROUND(SUMIF(AA32:AA69,"=56661434",GX32:GX69),2) -> 0 | CK71: =ROUND(SUMIF(AA32:AA69,"=56661434",GY32:GY69),2) -> 0 | CL71: =ROUND(SUMIF(AA32:AA69,"=56661434",GZ32:GZ69),2) -> 0 | CM71: =ROUND(SUMIF(AA32:AA69,"=56661434",HD32:HD69),2) -> 0 | DG71: =ROUND(DT71,2) -> 6548894.7 | DH71: =ROUND(DU71,2) -> 5785190 | DI71: =ROUND(DV71,2) -> 32781.5 | DJ71: =ROUND(DW71,2) -> 12289.94 | DK71: =ROUND(DX71,2) -> 730923.17 | DL71: =ROUND(DY71,2) -> 0 | DM71: =DZ71 -> 1078.2383 | DN71: =EA71 -> 0 | DO71: =ROUND(EB71,2) -> 0 | DP71: =ROUND(EC71,2) -> 810102.29 | DQ71: =ROUND(ED71,2) -> 453360 | DT71: =ROUND(SUMIF(AA32:AA69,"=56661436",O32:O69),2) -> 6548894.7 | DU71: =ROUND(SUMIF(AA32:AA69,"=56661436",P32:P69),2) -> 5785190 | DV71: =ROUND(SUMIF(AA32:AA69,"=56661436",Q32:Q69),2) -> 32781.5 | DW71: =ROUND(SUMIF(AA32:AA69,"=56661436",R32:R69),2) -> 12289.94 | DX71: =ROUND(SUMIF(AA32:AA69,"=56661436",S32:S69),2) -> 730923.17 | DY71: =ROUND(SUMIF(AA32:AA69,"=56661436",T32:T69),2) -> 0 | DZ71: =SUMIF(AA32:AA69,"=56661436",U32:U69) -> 1078.2383 | EA71: =SUMIF(AA32:AA69,"=56661436",V32:V69) -> 0 | EB71: =ROUND(SUMIF(AA32:AA69,"=56661436",W32:W69),2) -> 0 | EC71: =ROUND(SUMIF(AA32:AA69,"=56661436",X32:X69),2) -> 810102.29 | ED71: =ROUND(SUMIF(AA32:AA69,"=56661436",Y32:Y69),2) -> 453360 | EG71: =ROUND(FP71,2) -> 0 | EH71: =ROUND(FQ71,2) -> 5749508.2 | EI71: =ROUND(FR71,2) -> 0 | EJ71: =ROUND(FS71,2) -> 7812357 | EK71: =ROUND(FT71,2) -> 2062848.8 | EL71: =ROUND(FU71,2) -> 0 | EM71: =ROUND(FV71,2) -> 0 | EN71: =ROUND(FW71,2) -> 5785190 | ... EV71: =ROUND(GE71,2) -> 0 | FP71: =ROUND(SUMIF(AA32:AA69,"=56661436",FQ32:FQ69),2) -> 0 | FQ71: =ROUND(SUMIF(AA32:AA69,"=56661436",FR32:FR69),2) -> 5749508.2 | FR71: =ROUND(SUMIF(AA32:AA69,"=56661436",GL32:GL69),2) -> 0 | FS71: =ROUND(SUMIF(AA32:AA69,"=56661436",GM32:GM69),2) -> 7812357 | FT71: =ROUND(SUMIF(AA32:AA69,"=56661436",GN32:GN69),2) -> 2062848.8 | FU71: =ROUND(SUMIF(AA32:AA69,"=56661436",GO32:GO69),2) -> 0 | FV71: =ROUND(SUMIF(AA32:AA69,"=56661436",GP32:GP69),2) -> 0 | FW71: =DU71-FP71 -> 5785190 | FX71: =DU71-FQ71 -> 35681.85 | FY71: =FP71-FR71 -> 0 | FZ71: =DU71-FP71-FQ71+FR71 -> 35681.85 | GA71: =FQ71-FR71 -> 5749508.2 | GB71: =ROUND(SUMIF(AA32:AA69,"=56661436",GX32:GX69),2) -> 0 | GC71: =ROUND(SUMIF(AA32:AA69,"=56661436",GY32:GY69),2) -> 0 | GD71: =ROUND(SUMIF(AA32:AA69,"=56661436",GZ32:GZ69),2) -> 0 | GE71: =ROUND(SUMIF(AA32:AA69,"=56661436",HD32:HD69),2) -> 0 | GX71: 0
A73: 50 | B73: 0 | C73: 0 | D73: 1 | E73: 201 | F73: =ROUND(Source!O71,O73) -> 778582.9 | G73: ПЗ | H73: Прямые затраты | K73: 201 | L73: 1 | M73: 3 | O73: 2 | P73: =ROUND(Source!DG71,O73) -> 6548894.7 | W73: 778582.9 | X73: 1 | Y73: 778582.9 | Z73: 6548894.7 | AA73: 1 | AB73: 6548894.7
A74: 50 | B74: 0 | C74: 0 | D74: 1 | E74: 202 | F74: =ROUND(Source!P71,O74) -> 763458.88 | G74: СтМатОб | H74: Стоимость материальных ресурсов (всего) | K74: 202 | L74: 2 | M74: 3 | O74: 2 | P74: =ROUND(Source!DH71,O74) -> 5785190 | W74: 763458.88 | X74: 1 | Y74: 763458.88 | Z74: 5785190 | AA74: 1 | AB74: 5785190
A75: 50 | B75: 0 | C75: 0 | D75: 1 | E75: 222 | F75: =ROUND(Source!AO71,O75) -> 0 | G75: СтМатОбЗак | H75: Стоимость материалов и оборудования заказчика | K75: 222 | L75: 3 | M75: 3 | O75: 2 | P75: =ROUND(Source!EG71,O75) -> 0 | W75: 0 | X75: 1 | Y75: 0 | Z75: 0 | AA75: 1 | AB75: 0
A76: 50 | B76: 0 | C76: 0 | D76: 1 | E76: 225 | F76: =ROUND(Source!AV71,O76) -> 763458.88 | G76: СтМатОбПод | H76: Стоимость материалов и оборудования подрядчика | K76: 225 | L76: 4 | M76: 3 | O76: 2 | P76: =ROUND(Source!EN71,O76) -> 5785190 | W76: 763458.88 | X76: 1 | Y76: 763458.88 | Z76: 5785190 | AA76: 1 | AB76: 5785190
A77: 50 | B77: 0 | C77: 0 | D77: 1 | E77: 226 | F77: =ROUND(Source!AW71,O77) -> 3946.57 | G77: СтМат | H77: Стоимость материалов (всего) | K77: 226 | L77: 5 | M77: 3 | O77: 2 | P77: =ROUND(Source!EO71,O77) -> 35681.85 | W77: 3946.57 | X77: 1 | Y77: 3946.57 | Z77: 35681.85 | AA77: 1 | AB77: 35681.85
A78: 50 | B78: 0 | C78: 0 | D78: 1 | E78: 227 | F78: =ROUND(Source!AX71,O78) -> 0 | G78: СтМатЗак | H78: Стоимость материалов заказчика | K78: 227 | L78: 6 | M78: 3 | O78: 2 | P78: =ROUND(Source!EP71,O78) -> 0 | W78: 0 | X78: 1 | Y78: 0 | Z78: 0 | AA78: 1 | AB78: 0
A79: 50 | B79: 0 | C79: 0 | D79: 1 | E79: 228 | F79: =ROUND(Source!AY71,O79) -> 3946.57 | G79: СтМатПод | H79: Стоимость материалов подрядчика | K79: 228 | L79: 7 | M79: 3 | O79: 2 | P79: =ROUND(Source!EQ71,O79) -> 35681.85 | W79: 3946.57 | X79: 1 | Y79: 3946.57 | Z79: 35681.85 | AA79: 1 | AB79: 35681.85
A80: 50 | B80: 0 | C80: 0 | D80: 1 | E80: 216 | F80: =ROUND(Source!AP71,O80) -> 759512.31 | G80: Оборуд | H80: Стоимость оборудования (всего) | K80: 216 | L80: 8 | M80: 3 | O80: 2 | P80: =ROUND(Source!EH71,O80) -> 5749508.2 | W80: 759512.31 | X80: 1 | Y80: 759512.31 | Z80: 5749508.2 | AA80: 1 | AB80: 5749508.2
A81: 50 | B81: 0 | C81: 0 | D81: 1 | E81: 223 | F81: =ROUND(Source!AQ71,O81) -> 0 | G81: ОборудЗак | H81: Стоимость оборудования заказчика | K81: 223 | L81: 9 | M81: 3 | O81: 2 | P81: =ROUND(Source!EI71,O81) -> 0 | W81: 0 | X81: 1 | Y81: 0 | Z81: 0 | AA81: 1 | AB81: 0
A82: 50 | B82: 0 | C82: 0 | D82: 1 | E82: 229 | F82: =ROUND(Source!AZ71,O82) -> 759512.31 | G82: ОборудПод | H82: Стоимость оборудования подрядчика | K82: 229 | L82: 10 | M82: 3 | O82: 2 | P82: =ROUND(Source!ER71,O82) -> 5749508.2 | W82: 759512.31 | X82: 1 | Y82: 759512.31 | Z82: 5749508.2 | AA82: 1 | AB82: 5749508.2
A83: 50 | B83: 0 | C83: 0 | D83: 1 | E83: 203 | F83: =ROUND(Source!Q71,O83) -> 2152.89 | G83: ЭММ | H83: Эксплуатация машин | K83: 203 | L83: 11 | M83: 3 | O83: 2 | P83: =ROUND(Source!DI71,O83) -> 32781.5 | W83: 2152.89 | X83: 1 | Y83: 2152.89 | Z83: 32781.5 | AA83: 1 | AB83: 32781.5
A84: 50 | B84: 0 | C84: 0 | D84: 1 | E84: 231 | F84: =ROUND(Source!BB71,O84) -> 0 | G84: ЭММсНРиСП | H84: Эксплуатация машин по ТСН-2001.16 | K84: 231 | L84: 12 | M84: 3 | O84: 2 | P84: =ROUND(Source!ET71,O84) -> 0 | W84: 0 | X84: 1 | Y84: 0 | Z84: 0 | AA84: 1 | AB84: 0
A85: 50 | B85: 0 | C85: 0 | D85: 1 | E85: 204 | F85: =ROUND(Source!R71,O85) -> 218.1 | G85: ЗПМ | H85: ЗП машинистов | K85: 204 | L85: 13 | M85: 3 | O85: 2 | P85: =ROUND(Source!DJ71,O85) -> 12289.94 | W85: 218.1 | X85: 1 | Y85: 218.1 | Z85: 12289.94 | AA85: 1 | AB85: 12289.94
A86: 50 | B86: 0 | C86: 0 | D86: 1 | E86: 205 | F86: =ROUND(Source!S71,O86) -> 12971.13 | G86: ОЗП | H86: Основная ЗП рабочих | K86: 205 | L86: 14 | M86: 3 | O86: 2 | P86: =ROUND(Source!DK71,O86) -> 730923.17 | W86: 12971.13 | X86: 1 | Y86: 12971.13 | Z86: 730923.17 | AA86: 1 | AB86: 730923.17
A87: 50 | B87: 0 | C87: 0 | D87: 1 | E87: 232 | F87: =ROUND(Source!BC71,O87) -> 0 | G87: ОЗПсНРиСП | H87: Основная ЗП рабочих по ТСН-2001.16 | K87: 232 | L87: 15 | M87: 3 | O87: 2 | P87: =ROUND(Source!EU71,O87) -> 0 | W87: 0 | X87: 1 | Y87: 0 | Z87: 0 | AA87: 1 | AB87: 0
A88: 50 | B88: 0 | C88: 0 | D88: 1 | E88: 214 | F88: =ROUND(Source!AS71,O88) -> 41492.28 | G88: Строит | H88: Строительные работы с НР и СП | K88: 214 | L88: 16 | M88: 3 | O88: 2 | P88: =ROUND(Source!EK71,O88) -> 2062848.8 | W88: 41492.28 | X88: 1 | Y88: 41492.28 | Z88: 2062848.8 | AA88: 1 | AB88: 2062848.8
A89: 50 | B89: 0 | C89: 0 | D89: 1 | E89: 215 | F89: =ROUND(Source!AT71,O89) -> 0 | G89: Монтаж | H89: Монтажные работы с НР и СП | K89: 215 | L89: 17 | M89: 3 | O89: 2 | P89: =ROUND(Source!EL71,O89) -> 0 | W89: 0 | X89: 1 | Y89: 0 | Z89: 0 | AA89: 1 | AB89: 0
A90: 50 | B90: 0 | C90: 0 | D90: 1 | E90: 217 | F90: =ROUND(Source!AU71,O90) -> 0 | G90: Прочие | H90: Прочие работы с НР и СП | K90: 217 | L90: 18 | M90: 3 | O90: 2 | P90: =ROUND(Source!EM71,O90) -> 0 | W90: 0 | X90: 1 | Y90: 0 | Z90: 0 | AA90: 1 | AB90: 0
A91: 50 | B91: 0 | C91: 0 | D91: 1 | E91: 230 | F91: =ROUND(Source!BA71,O91) -> 0 | G91: ПрочиеЗатр | H91: Прочие затраты по ТСН-2001.16 | K91: 230 | L91: 19 | M91: 3 | O91: 2 | P91: =ROUND(Source!ES71,O91) -> 0 | W91: 0 | X91: 1 | Y91: 0 | Z91: 0 | AA91: 1 | AB91: 0
A92: 50 | B92: 0 | C92: 0 | D92: 1 | E92: 206 | F92: =ROUND(Source!T71,O92) -> 0 | G92: ВозврМат | H92: Возврат материалов | K92: 206 | L92: 20 | M92: 3 | O92: 2 | P92: =ROUND(Source!DL71,O92) -> 0 | W92: 0 | X92: 1 | Y92: 0 | Z92: 0 | AA92: 1 | AB92: 0
A93: 50 | B93: 0 | C93: 0 | D93: 1 | E93: 207 | F93: =Source!U71 -> 1078.2383 | G93: ТрудСтр | H93: Трудозатраты строителей | K93: 207 | L93: 21 | M93: 3 | O93: -1 | P93: =Source!DM71 -> 1078.2383 | W93: 1078.2383 | X93: 1 | Y93: 1078.2383 | Z93: 1078.2383 | AA93: 1 | AB93: 1078.2383
A94: 50 | B94: 0 | C94: 0 | D94: 1 | E94: 208 | F94: =Source!V71 -> 0 | G94: ТрудМаш | H94: Трудозатраты машинистов | K94: 208 | L94: 22 | M94: 3 | O94: -1 | P94: =Source!DN71 -> 0 | W94: 0 | X94: 1 | Y94: 0 | Z94: 0 | AA94: 1 | AB94: 0
A95: 50 | B95: 0 | C95: 0 | D95: 1 | E95: 209 | F95: =ROUND(Source!W71,O95) -> 0 | G95: ТранспМат | H95: Транспорт материалов | K95: 209 | L95: 23 | M95: 3 | O95: 2 | P95: =ROUND(Source!DO71,O95) -> 0 | W95: 0 | X95: 1 | Y95: 0 | Z95: 0 | AA95: 1 | AB95: 0
A96: 50 | B96: 0 | C96: 0 | D96: 1 | E96: 233 | F96: =ROUND(Source!BD71,O96) -> 0 | G96: Перевозка | H96: Перевозка грузов | K96: 233 | L96: 24 | M96: 3 | O96: 2 | P96: =ROUND(Source!EV71,O96) -> 0 | W96: 0 | X96: 1 | Y96: 0 | Z96: 0 | AA96: 1 | AB96: 0
A97: 50 | B97: 0 | C97: 0 | D97: 1 | E97: 210 | F97: =ROUND(Source!X71,O97) -> 14376.26 | G97: НР | H97: Накладные расходы | K97: 210 | L97: 25 | M97: 3 | O97: 2 | P97: =ROUND(Source!DP71,O97) -> 810102.29 | W97: 14376.26 | X97: 1 | Y97: 14376.26 | Z97: 810102.29 | AA97: 1 | AB97: 810102.29
A98: 50 | B98: 0 | C98: 0 | D98: 1 | E98: 211 | F98: =ROUND(Source!Y71,O98) -> 8045.43 | G98: СмПриб | H98: Сметная прибыль | K98: 211 | L98: 26 | M98: 3 | O98: 2 | P98: =ROUND(Source!DQ71,O98) -> 453360 | W98: 8045.43 | X98: 1 | Y98: 8045.43 | Z98: 453360 | AA98: 1 | AB98: 453360
A99: 50 | B99: 0 | C99: 0 | D99: 1 | E99: 224 | F99: =ROUND(Source!AR71,O99) -> 801004.59 | G99: Всего | H99: Всего с НР и СП | K99: 224 | L99: 27 | M99: 3 | O99: 2 | P99: =ROUND(Source!EJ71,O99) -> 7812357 | W99: 801004.59 | X99: 1 | Y99: 801004.59 | Z99: 7812357 | AA99: 1 | AB99: 7812357
A101: 5 | B101: 1 | D101: =ROW(A118) -> 118 | F101: Новый подраздел | G101: Смесительный узел | I101: 0 | K101: -1 | S101: 0 | T101: 0 | V101: 2 | BX101: 0 | CJ101: 0
A103: 52 | B103: =B118 -> 1 | C103: =C118 -> 5 | D103: =D118 -> 101 | E103: =E118 -> 0 | F103: =F118 -> Новый подраздел | G103: =G118 -> Смесительный узел | O103: =O118 -> 86990.14 | P103: =P118 -> 86221.2 | Q103: =Q118 -> 112.23 | R103: =R118 -> 8.94 | S103: =S118 -> 656.71 | T103: =T118 -> 0 | U103: =U118 -> 51.299034 | V103: =V118 -> 0 | ... GX103: =GX118 -> 0
A105: 17 | B105: 1 | C105: =ROW(SmtRes!A69) -> 69 | D105: =ROW(EtalonRes!A74) -> 74 | E105: 20 | F105: 3.20-52-1 | G105: Присоединение трубопроводов к оросительной системе блока тепломассобмена производительностью до 20 тыс.м3/час | H105: 1 блок | I105: =ROUND(4+5+3+1+1,9) -> 14 | J105: 0 | K105: =ROUND(4+5+3+1+1,9) -> 14 | O105: =ROUND(CP105,2) -> 1133.22 | P105: =ROUND((ROUND((AC105*AW105*I105),2)*BC105),2) -> 364.28 | Q105: =(ROUND((ROUND((((((ET105*1.25)*1.05)*1.2))*AV105*I105),2)*BB105),2)+ROUND((ROUND(((AE105-((((EU105*1.25)*1.05)*1.2)))*AV105*I105),2)*BS105),2)) -> 112.23 | R105: =(ROUND((ROUND((((((EU105*1.25)*1.05)*1.2))*AV105*I105),2)*BS105),2)+ROUND((ROUND(((AE105-((((EU105*1.25)*1.05)*1.2)))*AV105*I105),2)*BS105),2)) -> 8.94 | S105: =ROUND((ROUND((AF105*AV105*I105),2)*BA105),2) -> 656.71 | T105: =ROUND(CU105*I105,2) -> 0 | U105: =CV105*I105 -> 51.299034 | V105: =CW105*I105 -> 0 | W105: =ROUND(CX105*I105,2) -> 0 | X105: =(ROUND((((S105+ROUND((ROUND((((((EU105*1.25)*1.05)*1.2))*AV105*I105),2)*BS105),2))*AT105)/100),2)+ROUND(((ROUND((ROUND(((AE105-((((EU105*1.25)*1.05)*1.2)))*AV105*I105),2)*BS105),2)*AT105)/100),2)) -> 725.56 | Y105: =(ROUND((((S105+ROUND((ROUND((((((EU105*1.25)*1.05)*1.2))*AV105*I105),2)*BS105),2))*AU105)/100),2)+ROUND(((ROUND((ROUND(((AE105-((((EU105*1.25)*1.05)*1.2)))*AV105*I105),2)*BS105),2)*AU105)/100),2)) -> 406.05 | AA105: 56661434 | AB105: =ROUND((AC105+AD105+AF105),6) -> 77.49541 | AC105: =ROUND(((((ES105*1)*1)*1)),6) -> 26.02 | AD105: =ROUND(((((((ET105*1.25)*1.05)*1.2))-((((EU105*1.25)*1.05)*1.2)))+AE105),6) -> 7.51275 | AE105: =ROUND(((((EU105*1.25)*1.05)*1.2)),6) -> 0.5985 | AF105: =ROUND(((((EV105*1.15)*1.05)*1.2)),6) -> 43.96266 | AG105: =ROUND((AP105),6) -> 0 | AH105: =((((EW105*1.15)*1.05)*1.2)) -> 3.43413 | AI105: =((((EX105*1.25)*1.05)*1.2)) -> 0 | AJ105: =(AS105) -> 0 | AK105: 61.13 | AL105: 26.02 | AM105: 4.77 | AN105: 0.38 | AO105: 30.34 | AP105: 0 | AQ105: 2.37 | AR105: 0 | AS105: 0 | AT105: 109 | AU105: 61 | AV105: 1.067 | AW105: 1 | AZ105: 1 | BA105: 1 | BB105: 1 | BC105: 1 | BH105: 0 | BI105: 1 | BJ105: ТСН-2001.3 Доп. 79, Сб. 20, т. 52, поз. 1 | BM105: 25 | BN105: 0 | BO105: 3.20-52-1 | BP105: 1 | BQ105: 30 | BR105: 0 | BS105: 1 | BT105: 1 | BU105: 1 | BV105: 1 | BW105: 1 | BX105: 1 | BZ105: 109 | CA105: 61 | CE105: 1566 | CF105: 0 | CG105: 0 | CM105: 0 | CN105: Поправка: Гл.6.Прил.2.2.п.2.2.6_06.00.01.07.001 Наименование: При выполнении при капитальном ремонте и реконструкции работ, аналогичных технологическим процессам, характерным для нового строительства, и отсутствующих в сборниках на ремонтно-строительные работы ТСН-2001.6 Поправка: 3-20. О.П. п.1.5 Наименование: Затраты на индивидуальные испытания систем вентиляции и кондиционирования воздуха Поправка: Гл.12.Прил.8.п.8. 3_12.00.01.11.001 Наименование: При наличии напряженных и стесненных условий производства работ (стесненность, сложность складирования и транспортной логистики и т.п.) для объектов, расположенных в пределах круговой магистральной системы улиц "Садовое кольцо" города Москвы | CO105: 0 | CP105: =(P105+Q105+S105) -> 1133.22 | CQ105: =ROUND((ROUND((AC105*AW105*1),2)*BC105),2) -> 26.02 | CR105: =(ROUND((ROUND((((((ET105*1.25)*1.05)*1.2))*AV105*1),2)*BB105),2)+ROUND((ROUND(((AE105-((((EU105*1.25)*1.05)*1.2)))*AV105*1),2)*BS105),2)) -> 8.02 | CS105: =(ROUND((ROUND((((((EU105*1.25)*1.05)*1.2))*AV105*1),2)*BS105),2)+ROUND((ROUND(((AE105-((((EU105*1.25)*1.05)*1.2)))*AV105*1),2)*BS105),2)) -> 0.64 | CT105: =ROUND((ROUND((AF105*AV105*1),2)*BA105),2) -> 46.91 | CU105: =AG105 -> 0 | CV105: =(AH105*AV105) -> 3.6642167 | CW105: =AI105 -> 0 | CX105: =AJ105 -> 0 | CY105: =(ROUND((((S105+ROUND((ROUND((((((EU105*1.25)*1.05)*1.2))*AV105*1),2)*BS105),2))*AT105)/100),2)+ROUND(((ROUND((ROUND(((AE105-((((EU105*1.25)*1.05)*1.2)))*AV105*1),2)*BS105),2)*AT105)/100),2)) -> 716.51 | CZ105: =(ROUND((((S105+ROUND((ROUND((((((EU105*1.25)*1.05)*1.2))*AV105*1),2)*BS105),2))*AU105)/100),2)+ROUND(((ROUND((ROUND(((AE105-((((EU105*1.25)*1.05)*1.2)))*AV105*1),2)*BS105),2)*AU105)/100),2)) -> 400.98 | DB105: 7 | DD105: *1)*1)*1 | DE105: *1,25)*1,05)*1,2 | DF105: *1,25)*1,05)*1,2 | DG105: *1,15)*1,05)*1,2 | DI105: *1,15)*1,05)*1,2 | DJ105: *1,25)*1,05)*1,2 | DN105: 0 | DO105: 0 | DP105: 1 | DQ105: 1 | DU105: 1013 | DV105: 1 блок | DW105: 1 блок | DX105: 1 | EE105: 56938458 | EF105: 30 | EG105: Строительные работы | EH105: 0 | EJ105: 1 | EK105: 25 | EL105: ТСН-2001.3-20. Вентиляция и кондиционирование воздуха | EM105: ТСН-2001.3-20-1 | EO105: Поправка: Гл.6.Прил.2.2.п.2.2.6_06.00.01.07.001 Поправка: 3-20. О.П. п.1.5 Поправка: Гл.12.Прил.8.п.8. 3_12.00.01.11.001 | EQ105: 131072 | ER105: 61.13 | ES105: 26.02 | ET105: 4.77 | EU105: 0.38 | EV105: 30.34 | EW105: 2.37 | EX105: 0 | EY105: 0 | FQ105: 0 | FR105: 0 | FS105: 0 | FX105: 109 | FY105: 61 | GD105: 1 | GF105: -685887764 | GG105: 2 | GH105: 1 | GI105: 2 | GJ105: 0 | GK105: 0 | GL105: =ROUND(IF(AND(BH105=3,BI105=3,FS105<>0),P105,0),2) -> 0 | GM105: =ROUND(O105+X105+Y105,2)+GX105 -> 2264.83 | GN105: =IF(OR(BI105=0,BI105=1),GM105-GX105,0) -> 2264.83 | GO105: =IF(BI105=2,GM105-GX105,0) -> 0 | GP105: =IF(BI105=4,GM105-GX105,0) -> 0 | GR105: 0 | GS105: 3 | GT105: 0 | GV105: =ROUND((GT105),6) -> 0 | GW105: 1 | GX105: =ROUND(HC105*I105,2) -> 0 | HA105: 0 | HB105: 0 | HC105: =GV105*GW105 -> 0 | HS105: 0 | IK105: 0
A106: 17 | B106: 1 | C106: =ROW(SmtRes!A78) -> 78 | D106: =ROW(EtalonRes!A84) -> 84 | E106: 20 | F106: 3.20-52-1 | G106: Присоединение трубопроводов к оросительной системе блока тепломассобмена производительностью до 20 тыс.м3/час | H106: 1 блок | I106: =ROUND(4+5+3+1+1,9) -> 14 | J106: 0 | K106: =ROUND(4+5+3+1+1,9) -> 14 | O106: =ROUND(CP106,2) -> 41637.82 | P106: =ROUND((ROUND((AC106*AW106*I106),2)*BC106),2) -> 2910.6 | Q106: =(ROUND((ROUND((((((ET106*1.25)*1.05)*1.2))*AV106*I106),2)*BB106),2)+ROUND((ROUND(((AE106-((((EU106*1.25)*1.05)*1.2)))*AV106*I106),2)*BS106),2)) -> 1721.61 | R106: =(ROUND((ROUND((((((EU106*1.25)*1.05)*1.2))*AV106*I106),2)*BS106),2)+ROUND((ROUND(((AE106-((((EU106*1.25)*1.05)*1.2)))*AV106*I106),2)*BS106),2)) -> 503.77 | S106: =ROUND((ROUND((AF106*AV106*I106),2)*BA106),2) -> 37005.61 | T106: =ROUND(CU106*I106,2) -> 0 | U106: =CV106*I106 -> 51.299034 | V106: =CW106*I106 -> 0 | W106: =ROUND(CX106*I106,2) -> 0 | X106: =(ROUND((((S106+ROUND((ROUND((((((EU106*1.25)*1.05)*1.2))*AV106*I106),2)*BS106),2))*AT106)/100),2)+ROUND(((ROUND((ROUND(((AE106-((((EU106*1.25)*1.05)*1.2)))*AV106*I106),2)*BS106),2)*AT106)/100),2)) -> 40885.22 | Y106: =(ROUND((((S106+ROUND((ROUND((((((EU106*1.25)*1.05)*1.2))*AV106*I106),2)*BS106),2))*AU106)/100),2)+ROUND(((ROUND((ROUND(((AE106-((((EU106*1.25)*1.05)*1.2)))*AV106*I106),2)*BS106),2)*AU106)/100),2)) -> 22880.72 | AA106: 56661436 | AB106: =ROUND((AC106+AD106+AF106),6) -> 77.49541 | AC106: =ROUND(((((ES106*1)*1)*1)),6) -> 26.02 | AD106: =ROUND(((((((ET106*1.25)*1.05)*1.2))-((((EU106*1.25)*1.05)*1.2)))+AE106),6) -> 7.51275 | AE106: =ROUND(((((EU106*1.25)*1.05)*1.2)),6) -> 0.5985 | AF106: =ROUND(((((EV106*1.15)*1.05)*1.2)),6) -> 43.96266 | AG106: =ROUND((AP106),6) -> 0 | AH106: =((((EW106*1.15)*1.05)*1.2)) -> 3.43413 | AI106: =((((EX106*1.25)*1.05)*1.2)) -> 0 | AJ106: =(AS106) -> 0 | AK106: 61.13 | AL106: 26.02 | AM106: 4.77 | AN106: 0.38 | AO106: 30.34 | AP106: 0 | AQ106: 2.37 | AR106: 0 | AS106: 0 | AT106: 109 | AU106: 61 | AV106: 1.067 | AW106: 1 | AZ106: 1 | BA106: 56.35 | BB106: 15.34 | BC106: 7.99 | BH106: 0 | BI106: 1 | BJ106: ТСН-2001.3 Доп. 79, Сб. 20, т. 52, поз. 1 | BM106: 25 | BN106: 0 | BO106: 3.20-52-1 | BP106: 1 | BQ106: 30 | BR106: 0 | BS106: 56.35 | BT106: 1 | BU106: 1 | BV106: 1 | BW106: 1 | BX106: 1 | BZ106: 109 | CA106: 61 | CE106: 1566 | CF106: 0 | CG106: 0 | CM106: 0 | CN106: Поправка: Гл.6.Прил.2.2.п.2.2.6_06.00.01.07.001 Наименование: При выполнении при капитальном ремонте и реконструкции работ, аналогичных технологическим процессам, характерным для нового строительства, и отсутствующих в сборниках на ремонтно-строительные работы ТСН-2001.6 Поправка: 3-20. О.П. п.1.5 Наименование: Затраты на индивидуальные испытания систем вентиляции и кондиционирования воздуха Поправка: Гл.12.Прил.8.п.8. 3_12.00.01.11.001 Наименование: При наличии напряженных и стесненных условий производства работ (стесненность, сложность складирования и транспортной логистики и т.п.) для объектов, расположенных в пределах круговой магистральной системы улиц "Садовое кольцо" города Москвы | CO106: 0 | CP106: =(P106+Q106+S106) -> 41637.82 | CQ106: =ROUND((ROUND((AC106*AW106*1),2)*BC106),2) -> 207.9 | CR106: =(ROUND((ROUND((((((ET106*1.25)*1.05)*1.2))*AV106*1),2)*BB106),2)+ROUND((ROUND(((AE106-((((EU106*1.25)*1.05)*1.2)))*AV106*1),2)*BS106),2)) -> 123.03 | CS106: =(ROUND((ROUND((((((EU106*1.25)*1.05)*1.2))*AV106*1),2)*BS106),2)+ROUND((ROUND(((AE106-((((EU106*1.25)*1.05)*1.2)))*AV106*1),2)*BS106),2)) -> 36.06 | CT106: =ROUND((ROUND((AF106*AV106*1),2)*BA106),2) -> 2643.38 | CU106: =AG106 -> 0 | CV106: =(AH106*AV106) -> 3.6642167 | CW106: =AI106 -> 0 | CX106: =AJ106 -> 0 | CY106: =(ROUND((((S106+ROUND((ROUND((((((EU106*1.25)*1.05)*1.2))*AV106*1),2)*BS106),2))*AT106)/100),2)+ROUND(((ROUND((ROUND(((AE106-((((EU106*1.25)*1.05)*1.2)))*AV106*1),2)*BS106),2)*AT106)/100),2)) -> 40375.42 | CZ106: =(ROUND((((S106+ROUND((ROUND((((((EU106*1.25)*1.05)*1.2))*AV106*1),2)*BS106),2))*AU106)/100),2)+ROUND(((ROUND((ROUND(((AE106-((((EU106*1.25)*1.05)*1.2)))*AV106*1),2)*BS106),2)*AU106)/100),2)) -> 22595.42 | DB106: 10 | DD106: *1)*1)*1 | DE106: *1,25)*1,05)*1,2 | DF106: *1,25)*1,05)*1,2 | DG106: *1,15)*1,05)*1,2 | DI106: *1,15)*1,05)*1,2 | DJ106: *1,25)*1,05)*1,2 | DN106: 0 | DO106: 0 | DP106: 1 | DQ106: 1 | DU106: 1013 | DV106: 1 блок | DW106: 1 блок | DX106: 1 | EE106: 56938458 | EF106: 30 | EG106: Строительные работы | EH106: 0 | EJ106: 1 | EK106: 25 | EL106: ТСН-2001.3-20. Вентиляция и кондиционирование воздуха | EM106: ТСН-2001.3-20-1 | EO106: Поправка: Гл.6.Прил.2.2.п.2.2.6_06.00.01.07.001 Поправка: 3-20. О.П. п.1.5 Поправка: Гл.12.Прил.8.п.8. 3_12.00.01.11.001 | EQ106: 131072 | ER106: 61.13 | ES106: 26.02 | ET106: 4.77 | EU106: 0.38 | EV106: 30.34 | EW106: 2.37 | EX106: 0 | EY106: 0 | FQ106: 0 | FR106: 0 | FS106: 0 | FX106: 109 | FY106: 61 | GD106: 1 | GF106: -685887764 | GG106: 2 | GH106: 1 | GI106: 2 | GJ106: 0 | GK106: 0 | GL106: =ROUND(IF(AND(BH106=3,BI106=3,FS106<>0),P106,0),2) -> 0 | GM106: =ROUND(O106+X106+Y106,2)+GX106 -> 105403.76 | GN106: =IF(OR(BI106=0,BI106=1),GM106-GX106,0) -> 105403.76 | GO106: =IF(BI106=2,GM106-GX106,0) -> 0 | GP106: =IF(BI106=4,GM106-GX106,0) -> 0 | GR106: 0 | GS106: 3 | GT106: 0 | GV106: =ROUND((GT106),6) -> 0 | GW106: 1 | GX106: =ROUND(HC106*I106,2) -> 0 | HA106: 0 | HB106: 0 | HC106: =GV106*GW106 -> 0 | HS106: 0 | IK106: 0
A107: 17 | B107: 1 | E107: 21 | F107: КА, п.2 | G107: П1, П8, П9, П13 Смесительный узел SURP 40-2.5 | H107: ШТ | I107: 4 | J107: 0 | K107: 4 | O107: =ROUND(CP107,2) -> 20169.08 | P107: =ROUND((ROUND((AC107*AW107*I107),2)*BC107),2) -> 20169.08 | Q107: =(ROUND((ROUND(((ET107)*AV107*I107),2)*BB107),2)+ROUND((ROUND(((AE107-(EU107))*AV107*I107),2)*BS107),2)) -> 0 | R107: =(ROUND((ROUND(((EU107)*AV107*I107),2)*BS107),2)+ROUND((ROUND(((AE107-(EU107))*AV107*I107),2)*BS107),2)) -> 0 | S107: =ROUND((ROUND((AF107*AV107*I107),2)*BA107),2) -> 0 | T107: =ROUND(CU107*I107,2) -> 0 | U107: =CV107*I107 -> 0 | V107: =CW107*I107 -> 0 | W107: =ROUND(CX107*I107,2) -> 0 | X107: =(ROUND((((S107+ROUND((ROUND(((EU107)*AV107*I107),2)*BS107),2))*AT107)/100),2)+ROUND(((ROUND((ROUND(((AE107-(EU107))*AV107*I107),2)*BS107),2)*AT107)/100),2)) -> 0 | Y107: =(ROUND((((S107+ROUND((ROUND(((EU107)*AV107*I107),2)*BS107),2))*AU107)/100),2)+ROUND(((ROUND((ROUND(((AE107-(EU107))*AV107*I107),2)*BS107),2)*AU107)/100),2)) -> 0 | AA107: 56661434 | AB107: =ROUND((AC107+AD107+AF107),6) -> 5042.27 | AC107: =ROUND((ES107),6) -> 5042.27 | AD107: =ROUND((((ET107)-(EU107))+AE107),6) -> 0 | AE107: =ROUND((EU107),6) -> 0 | AF107: =ROUND((EV107),6) -> 0 | AG107: =ROUND((AP107),6) -> 0 | AH107: =(EW107) -> 0 | AI107: =(EX107) -> 0 | AJ107: =(AS107) -> 0 | AK107: 5042.27 | AL107: 5042.27 | AM107: 0 | AN107: 0 | AO107: 0 | AP107: 0 | AQ107: 0 | AR107: 0 | AS107: 0 | AT107: 0 | AU107: 0 | AV107: 1 | AW107: 1 | AZ107: 1 | BA107: 1 | BB107: 1 | BC107: 1 | BH107: 3 | BI107: 3 | BJ107: КА, п.2 | BM107: 400007 | BN107: 0 | BP107: 0 | BQ107: 214 | BR107: 0 | BS107: 1 | BT107: 1 | BU107: 1 | BV107: 1 | BW107: 1 | BX107: 1 | BZ107: 0 | CA107: 0 | CE107: 1566 | CF107: 0 | CG107: 0 | CM107: 0 | CO107: 0 | CP107: =(P107+Q107+S107) -> 20169.08 | CQ107: =ROUND((ROUND((AC107*AW107*1),2)*BC107),2) -> 5042.27 | CR107: =(ROUND((ROUND(((ET107)*AV107*1),2)*BB107),2)+ROUND((ROUND(((AE107-(EU107))*AV107*1),2)*BS107),2)) -> 0 | CS107: =(ROUND((ROUND(((EU107)*AV107*1),2)*BS107),2)+ROUND((ROUND(((AE107-(EU107))*AV107*1),2)*BS107),2)) -> 0 | CT107: =ROUND((ROUND((AF107*AV107*1),2)*BA107),2) -> 0 | CU107: =AG107 -> 0 | CV107: =(AH107*AV107) -> 0 | CW107: =AI107 -> 0 | CX107: =AJ107 -> 0 | CY107: =(ROUND((((S107+ROUND((ROUND(((EU107)*AV107*1),2)*BS107),2))*AT107)/100),2)+ROUND(((ROUND((ROUND(((AE107-(EU107))*AV107*1),2)*BS107),2)*AT107)/100),2)) -> 0 | CZ107: =(ROUND((((S107+ROUND((ROUND(((EU107)*AV107*1),2)*BS107),2))*AU107)/100),2)+ROUND(((ROUND((ROUND(((AE107-(EU107))*AV107*1),2)*BS107),2)*AU107)/100),2)) -> 0 | DN107: 0 | DO107: 0 | DP107: 1 | DQ107: 1 | DU107: 1013 | DV107: ШТ | DW107: ШТ | DX107: 1 | EE107: 56938434 | EF107: 214 | EG107: Оборудование, отсутствующие в СНБ | EH107: 0 | EJ107: 3 | EK107: 400007 | EL107: Оборудование, отсутствующие в СНБ | EM107: Оборуд. КА | EQ107: 131088 | ER107: 0 | ES107: 5042.27 | ET107: 0 | EU107: 0 | EV107: 0 | EW107: 0 | EX107: 0 | EY107: 0 | FQ107: 0 | FR107: =P107 -> 20169.08 | FS107: 0 | FX107: 0 | FY107: 0 | GA107: [44 675 / 1,22 / 7,57] + 3% Трансп + 1,2% Заг.скл | GD107: 1 | GF107: 1243986182 | GG107: 2 | GH107: 4 | GI107: -2 | GJ107: 0 | GK107: 0 | GL107: =ROUND(IF(AND(BH107=3,BI107=3,FS107<>0),P107,0),2) -> 0 | GM107: =ROUND(O107+X107+Y107,2)+GX107 -> 20169.08 | GN107: =IF(OR(BI107=0,BI107=1),GM107-GX107,0) -> 0 | GO107: =IF(BI107=2,GM107-GX107,0) -> 0 | GP107: =IF(BI107=4,GM107-GX107,0) -> 0 | GR107: 1 | GS107: 2 | GT107: 0 | GV107: =ROUND((GT107),6) -> 0 | GW107: 1 | GX107: =ROUND(HC107*I107,2) -> 0 | HA107: 0 | HB107: 0 | HC107: =GV107*GW107 -> 0 | HE107: 3 | HF107: 1,2 | HS107: 0 | IK107: 0
A108: 17 | B108: 1 | E108: 21 | F108: КА, п.2 | G108: П1, П8, П9, П13 Смесительный узел SURP 40-2.5 | H108: ШТ | I108: 4 | J108: 0 | K108: 4 | O108: =ROUND(CP108,2) -> 152679.94 | P108: =ROUND((ROUND((AC108*AW108*I108),2)*BC108),2) -> 152679.94 | Q108: =(ROUND((ROUND(((ET108)*AV108*I108),2)*BB108),2)+ROUND((ROUND(((AE108-(EU108))*AV108*I108),2)*BS108),2)) -> 0 | R108: =(ROUND((ROUND(((EU108)*AV108*I108),2)*BS108),2)+ROUND((ROUND(((AE108-(EU108))*AV108*I108),2)*BS108),2)) -> 0 | S108: =ROUND((ROUND((AF108*AV108*I108),2)*BA108),2) -> 0 | T108: =ROUND(CU108*I108,2) -> 0 | U108: =CV108*I108 -> 0 | V108: =CW108*I108 -> 0 | W108: =ROUND(CX108*I108,2) -> 0 | X108: =(ROUND((((S108+ROUND((ROUND(((EU108)*AV108*I108),2)*BS108),2))*AT108)/100),2)+ROUND(((ROUND((ROUND(((AE108-(EU108))*AV108*I108),2)*BS108),2)*AT108)/100),2)) -> 0 | Y108: =(ROUND((((S108+ROUND((ROUND(((EU108)*AV108*I108),2)*BS108),2))*AU108)/100),2)+ROUND(((ROUND((ROUND(((AE108-(EU108))*AV108*I108),2)*BS108),2)*AU108)/100),2)) -> 0 | AA108: 56661436 | AB108: =ROUND((AC108+AD108+AF108),6) -> 5042.27 | AC108: =ROUND((ES108),6) -> 5042.27 | AD108: =ROUND((((ET108)-(EU108))+AE108),6) -> 0 | AE108: =ROUND((EU108),6) -> 0 | AF108: =ROUND((EV108),6) -> 0 | AG108: =ROUND((AP108),6) -> 0 | AH108: =(EW108) -> 0 | AI108: =(EX108) -> 0 | AJ108: =(AS108) -> 0 | AK108: 5042.27 | AL108: 5042.27 | AM108: 0 | AN108: 0 | AO108: 0 | AP108: 0 | AQ108: 0 | AR108: 0 | AS108: 0 | AT108: 0 | AU108: 0 | AV108: 1 | AW108: 1 | AZ108: 1 | BA108: 1 | BB108: 1 | BC108: 7.57 | BH108: 3 | BI108: 3 | BJ108: КА, п.2 | BM108: 400007 | BN108: 0 | BP108: 0 | BQ108: 214 | BR108: 0 | BS108: 1 | BT108: 1 | BU108: 1 | BV108: 1 | BW108: 1 | BX108: 1 | BZ108: 0 | CA108: 0 | CE108: 1566 | CF108: 0 | CG108: 0 | CM108: 0 | CO108: 0 | CP108: =(P108+Q108+S108) -> 152679.94 | CQ108: =ROUND((ROUND((AC108*AW108*1),2)*BC108),2) -> 38169.98 | CR108: =(ROUND((ROUND(((ET108)*AV108*1),2)*BB108),2)+ROUND((ROUND(((AE108-(EU108))*AV108*1),2)*BS108),2)) -> 0 | CS108: =(ROUND((ROUND(((EU108)*AV108*1),2)*BS108),2)+ROUND((ROUND(((AE108-(EU108))*AV108*1),2)*BS108),2)) -> 0 | CT108: =ROUND((ROUND((AF108*AV108*1),2)*BA108),2) -> 0 | CU108: =AG108 -> 0 | CV108: =(AH108*AV108) -> 0 | CW108: =AI108 -> 0 | CX108: =AJ108 -> 0 | CY108: =(ROUND((((S108+ROUND((ROUND(((EU108)*AV108*1),2)*BS108),2))*AT108)/100),2)+ROUND(((ROUND((ROUND(((AE108-(EU108))*AV108*1),2)*BS108),2)*AT108)/100),2)) -> 0 | CZ108: =(ROUND((((S108+ROUND((ROUND(((EU108)*AV108*1),2)*BS108),2))*AU108)/100),2)+ROUND(((ROUND((ROUND(((AE108-(EU108))*AV108*1),2)*BS108),2)*AU108)/100),2)) -> 0 | DN108: 0 | DO108: 0 | DP108: 1 | DQ108: 1 | DU108: 1013 | DV108: ШТ | DW108: ШТ | DX108: 1 | EE108: 56938434 | EF108: 214 | EG108: Оборудование, отсутствующие в СНБ | EH108: 0 | EJ108: 3 | EK108: 400007 | EL108: Оборудование, отсутствующие в СНБ | EM108: Оборуд. КА | EQ108: 131088 | ER108: 0 | ES108: 5042.27 | ET108: 0 | EU108: 0 | EV108: 0 | EW108: 0 | EX108: 0 | EY108: 0 | EZ108: 5 | FC108: 1 | FD108: 18 | FF108: 44675 | FQ108: 0 | FR108: =P108 -> 152679.94 | FS108: 0 | FX108: 0 | FY108: 0 | GA108: [44 675 / 1,22 / 7,57] + 3% Трансп + 1,2% Заг.скл | GD108: 1 | GF108: 1243986182 | GG108: 2 | GH108: 3 | GI108: 3 | GJ108: 0 | GK108: 0 | GL108: =ROUND(IF(AND(BH108=3,BI108=3,FS108<>0),P108,0),2) -> 0 | GM108: =ROUND(O108+X108+Y108,2)+GX108 -> 152679.94 | GN108: =IF(OR(BI108=0,BI108=1),GM108-GX108,0) -> 0 | GO108: =IF(BI108=2,GM108-GX108,0) -> 0 | GP108: =IF(BI108=4,GM108-GX108,0) -> 0 | GR108: 1 | GS108: 1 | GT108: 0 | GV108: =ROUND((GT108),6) -> 0 | GW108: 1 | GX108: =ROUND(HC108*I108,2) -> 0 | HA108: 0 | HB108: 0 | HC108: =GV108*GW108 -> 0 | HE108: 3 | HF108: 1,2 | HS108: 0 | IK108: 0
A109: 17 | B109: 1 | E109: 22 | F109: КА, п.4 | G109: П2, П4,П10, П11, П12 Смесительный узел SURP 80-6.3 | H109: ШТ | I109: 5 | J109: 0 | K109: 5 | O109: =ROUND(CP109,2) -> 39503 | P109: =ROUND((ROUND((AC109*AW109*I109),2)*BC109),2) -> 39503 | Q109: =(ROUND((ROUND(((ET109)*AV109*I109),2)*BB109),2)+ROUND((ROUND(((AE109-(EU109))*AV109*I109),2)*BS109),2)) -> 0 | R109: =(ROUND((ROUND(((EU109)*AV109*I109),2)*BS109),2)+ROUND((ROUND(((AE109-(EU109))*AV109*I109),2)*BS109),2)) -> 0 | S109: =ROUND((ROUND((AF109*AV109*I109),2)*BA109),2) -> 0 | T109: =ROUND(CU109*I109,2) -> 0 | U109: =CV109*I109 -> 0 | V109: =CW109*I109 -> 0 | W109: =ROUND(CX109*I109,2) -> 0 | X109: =(ROUND((((S109+ROUND((ROUND(((EU109)*AV109*I109),2)*BS109),2))*AT109)/100),2)+ROUND(((ROUND((ROUND(((AE109-(EU109))*AV109*I109),2)*BS109),2)*AT109)/100),2)) -> 0 | Y109: =(ROUND((((S109+ROUND((ROUND(((EU109)*AV109*I109),2)*BS109),2))*AU109)/100),2)+ROUND(((ROUND((ROUND(((AE109-(EU109))*AV109*I109),2)*BS109),2)*AU109)/100),2)) -> 0 | AA109: 56661434 | AB109: =ROUND((AC109+AD109+AF109),6) -> 7900.6 | AC109: =ROUND((ES109),6) -> 7900.6 | AD109: =ROUND((((ET109)-(EU109))+AE109),6) -> 0 | AE109: =ROUND((EU109),6) -> 0 | AF109: =ROUND((EV109),6) -> 0 | AG109: =ROUND((AP109),6) -> 0 | AH109: =(EW109) -> 0 | AI109: =(EX109) -> 0 | AJ109: =(AS109) -> 0 | AK109: 7900.6 | AL109: 7900.6 | AM109: 0 | AN109: 0 | AO109: 0 | AP109: 0 | AQ109: 0 | AR109: 0 | AS109: 0 | AT109: 0 | AU109: 0 | AV109: 1 | AW109: 1 | AZ109: 1 | BA109: 1 | BB109: 1 | BC109: 1 | BH109: 3 | BI109: 3 | BJ109: КА, п.4 | BM109: 400007 | BN109: 0 | BP109: 0 | BQ109: 214 | BR109: 0 | BS109: 1 | BT109: 1 | BU109: 1 | BV109: 1 | BW109: 1 | BX109: 1 | BZ109: 0 | CA109: 0 | CE109: 1566 | CF109: 0 | CG109: 0 | CM109: 0 | CO109: 0 | CP109: =(P109+Q109+S109) -> 39503 | CQ109: =ROUND((ROUND((AC109*AW109*1),2)*BC109),2) -> 7900.6 | CR109: =(ROUND((ROUND(((ET109)*AV109*1),2)*BB109),2)+ROUND((ROUND(((AE109-(EU109))*AV109*1),2)*BS109),2)) -> 0 | CS109: =(ROUND((ROUND(((EU109)*AV109*1),2)*BS109),2)+ROUND((ROUND(((AE109-(EU109))*AV109*1),2)*BS109),2)) -> 0 | CT109: =ROUND((ROUND((AF109*AV109*1),2)*BA109),2) -> 0 | CU109: =AG109 -> 0 | CV109: =(AH109*AV109) -> 0 | CW109: =AI109 -> 0 | CX109: =AJ109 -> 0 | CY109: =(ROUND((((S109+ROUND((ROUND(((EU109)*AV109*1),2)*BS109),2))*AT109)/100),2)+ROUND(((ROUND((ROUND(((AE109-(EU109))*AV109*1),2)*BS109),2)*AT109)/100),2)) -> 0 | CZ109: =(ROUND((((S109+ROUND((ROUND(((EU109)*AV109*1),2)*BS109),2))*AU109)/100),2)+ROUND(((ROUND((ROUND(((AE109-(EU109))*AV109*1),2)*BS109),2)*AU109)/100),2)) -> 0 | DN109: 0 | DO109: 0 | DP109: 1 | DQ109: 1 | DU109: 1013 | DV109: ШТ | DW109: ШТ | DX109: 1 | EE109: 56938434 | EF109: 214 | EG109: Оборудование, отсутствующие в СНБ | EH109: 0 | EJ109: 3 | EK109: 400007 | EL109: Оборудование, отсутствующие в СНБ | EM109: Оборуд. КА | EQ109: 131088 | ER109: 0 | ES109: 7900.6 | ET109: 0 | EU109: 0 | EV109: 0 | EW109: 0 | EX109: 0 | EY109: 0 | FQ109: 0 | FR109: =P109 -> 39503 | FS109: 0 | FX109: 0 | FY109: 0 | GA109: [70 000 / 1,22 / 7,57] + 3% Трансп + 1,2% Заг.скл | GD109: 1 | GF109: 1719198114 | GG109: 2 | GH109: 4 | GI109: -2 | GJ109: 0 | GK109: 0 | GL109: =ROUND(IF(AND(BH109=3,BI109=3,FS109<>0),P109,0),2) -> 0 | GM109: =ROUND(O109+X109+Y109,2)+GX109 -> 39503 | GN109: =IF(OR(BI109=0,BI109=1),GM109-GX109,0) -> 0 | GO109: =IF(BI109=2,GM109-GX109,0) -> 0 | GP109: =IF(BI109=4,GM109-GX109,0) -> 0 | GR109: 1 | GS109: 2 | GT109: 0 | GV109: =ROUND((GT109),6) -> 0 | GW109: 1 | GX109: =ROUND(HC109*I109,2) -> 0 | HA109: 0 | HB109: 0 | HC109: =GV109*GW109 -> 0 | HE109: 3 | HF109: 1,2 | HS109: 0 | IK109: 0
