Workbook

Sheet Смета по ТСН-2001(с доп.67
A1: =Source!B1 -> Smeta.RU (495) 974-1589
J2: Форма № 4б
B3: "СОГЛАСОВАНО" | G3: "УТВЕРЖДАЮ"
B6: =CONCATENATE("______________________ ", IF(Source!AL12<>"", Source!AL12, "")) -> ______________________ | G6: =CONCATENATE("______________________ ", IF(Source!AH12<>"", Source!AH12, "")) -> ______________________
B7: "_____"________________ 2026 г. | G7: "_____"________________ 2026 г.
A10: Капитальный ремонт здания Государственного бюджетного общеобразовательного учреждения города Москвы «Школа №1574», расположенного по адресу: г. Москва, Старопименовский переулок, д. 5. 1 этап. | AP10: Капитальный ремонт здания Государственного бюджетного общеобразовательного учреждения города Москвы «Школа №1574», расположенного по адресу: г. Москва, Старопименовский переулок, д. 5. 1 этап. 02-01-20 ОДИ 16.07.26
A11: (наименование стройки и/или объекта)
A13: =CONCATENATE( "ЛОКАЛЬНАЯ СМЕТА № ",IF(Source!F12<>"Новый объект", Source!F12, "")) -> ЛОКАЛЬНАЯ СМЕТА № 02-01-20
A15: =Source!G20 -> Мероприятия по обеспечению доступа инвалидов
A16: (наименование работ и затрат)
A18: =CONCATENATE( "Основание: чертежи № ", Source!J12) -> Основание: чертежи № 2024-00377-01-0-ОДИ.ВОР
I20: В базисном уровне цен | J20: В текущем уровне цен
E21: Сметная стоимость | I21: =I22+I23+I24+I25 -> 17.89 | J21: =J22+J23+J24+J25 -> 149.04 | K21: тыс.руб.
E22: Строительные работы | I22: =ROUND((Source!F351)/1000, 2) -> 5.06 | J22: =ROUND((Source!P351)/1000, 2) -> 80.24 | K22: тыс.руб.
E23: Работы по монтажу оборудования | I23: =ROUND((Source!F352)/1000, 2) -> 0 | J23: =ROUND((Source!P352)/1000, 2) -> 0 | K23: тыс.руб.
E24: Оборудование | I24: =ROUND((Source!F343)/1000, 2) -> 12.83 | J24: =ROUND((Source!P343)/1000, 2) -> 68.8 | K24: тыс.руб.
E25: Прочие работы и затраты | I25: =ROUND((Source!F353+Source!F354)/1000, 2) -> 0 | J25: =ROUND((Source!P353+Source!P354)/1000, 2) -> 0 | K25: тыс.руб.
E26: Средства на оплату труда | I26: =(Source!F349+ Source!F348)/1000 -> 0.32733 | J26: =((Source!P349 + Source!P348)/1000) -> 18.44505 | K26: тыс.руб.
E27: Затраты труда | I27: =Source!F356 -> 24.208651 | K27: чел.-ч.
E28: Кроме того:
E29: Возврат материалов | I29: =SUM(Y1:Y222)/1000 -> 0 | J29: =SUM(Z1:Z222)/1000 -> 0 | K29: тыс.руб.
A31: Составлен(а) по ТСН-2001 с учетом Дополнения №: 81
A32: № и период сборника коэффициентов (индексов) пересчета: Коэффициенты к ТСН-2001 МГЭ Дополнение 81, ремонт №219/81 I квартал 2026 года и Коэффициенты к ТСН-2001.13-2 Дополнение 47 №64/47 I квартал 2026 года | AP32: № и период сборника коэффициентов (индексов) пересчета: Коэффициенты к ТСН-2001 МГЭ Дополнение 81, ремонт №219/81 I квартал 2026 года и Коэффициенты к ТСН-2001.13-2 Дополнение 47 №64/47 I квартал 2026 года
A33: № п/п | B33: Шифр расценки и коды ресурсов | C33: Наименование работ и затрат | D33: Ед. изм. | E33: Кол-во единиц | F33: Цена на ед. изм., руб. | G33: Попра- вочные коэффи- циенты | H33: Коэффи- циенты зимних удорожа- ний | I33: Всего в ценах на январь 2000 года, руб. | J33: Коэффи- циенты (индек- сы) пере- счета, нормы НР и СП | K33: ВСЕГО затрат в текущем уровне цен, руб.
A34: 1 | B34: 2 | C34: 3 | D34: 4 | E34: 5 | F34: 6 | G34: 7 | H34: 8 | I34: 9 | J34: 10 | K34: 11
A36: =CONCATENATE("Локальная смета: ",IF(Source!G20<>"Новая локальная смета", Source!G20, "")) -> Локальная смета: Мероприятия по обеспечению доступа инвалидов
A38: =CONCATENATE("Раздел: ",IF(Source!G24<>"Новый раздел", Source!G24, "")) -> Раздел: Демонтажные работы (Письмо от АНО «РГТ» об утверждении объёмов демонтажных работ) | AP38: =CONCATENATE("Раздел: ",IF(Source!G24<>"Новый раздел", Source!G24, "")) -> Раздел: Демонтажные работы (Письмо от АНО «РГТ» об утверждении объёмов демонтажных работ)
A40: =CONCATENATE("Итого по разделу: ",IF(Source!G37<>"Новый раздел", Source!G37, "")) -> Итого по разделу: Демонтажные работы (Письмо от АНО «РГТ» об утверждении объёмов демонтажных работ) | H40: =SUM(O38:O39) -> 0 | J40: =SUM(P38:P39) -> 0 | AQ40: =CONCATENATE("Итого по разделу: ",IF(Source!G37<>"Новый раздел", Source!G37, "")) -> Итого по разделу: Демонтажные работы (Письмо от АНО «РГТ» об утверждении объёмов демонтажных работ)
A41: Итого по ТСН-2001.16 | I41: =SUM(W38:W40) -> 0 | J41: =SUM(X38:X40) -> 0
A42: Итого возвратных сумм | I42: =SUM(Y38:Y41) -> 0 | J42: =SUM(Z38:Z41) -> 0
A44: =CONCATENATE("Раздел: ",IF(Source!G67<>"Новый раздел", Source!G67, "")) -> Раздел: Оборудование санузла МГН (универсальная кабина)
A45: 1 | B45: =Source!F71 -> 3.17-2-14 | C45: Установка гарнитуры туалетной: поручней для ванн | D45: =Source!H71 -> 100 шт. | E45: =Source!I71 -> 0.06 | Q45: =Source!X71 -> 18.22 | R45: =Source!X72 -> 1026.97 | S45: =Source!Y71 -> 10.2 | T45: =Source!Y72 -> 574.72 | U45: =ROUND((175/100)*ROUND(Source!R71, 2), 2) -> 0.09 | V45: =ROUND((0/100)*ROUND(Source!R72, 2), 2) -> 0 | AC45: 0
C46: ="Объем: "&Source!I71&"=(1+"&"1+"&"2+"&"1+"&"1)/"&"100" -> Объем: 0,06=(1+1+2+1+1)/100
C47: ЗП | F47: =Source!AO71 -> 188.72 | G47: 1,15*1,2 | H47: =Source!AV72 -> 1.067 | I47: =Source!S71 -> 16.67 | J47: =IF(Source!BA72<> 0, Source!BA72, 1) -> 56.35 | K47: =Source!S72 -> 939.35
C48: ЭМ | F48: =Source!AM71 -> 7.54 | G48: 1,25*1,2 | H48: =Source!AV72 -> 1.067 | I48: =Source!Q71 -> 0.72 | J48: =IF(Source!BB72<> 0, Source!BB72, 1) -> 12.92 | K48: =Source!Q72 -> 9.3
C49: в т.ч. ЗПМ | F49: =Source!AN71 -> 0.5 | G49: 1,25*1,2 | H49: =Source!AV72 -> 1.067 | I49: =Source!R71 -> 0.05 | J49: =IF(Source!BS72<> 0, Source!BS72, 1) -> 56.35 | K49: =Source!R72 -> 2.82
C50: МР | F50: =Source!AL71 -> 5229.82 | H50: =Source!AW72 -> 1 | I50: =Source!P71 -> 313.79 | J50: =IF(Source!BC72<> 0, Source!BC72, 1) -> 0.71 | K50: =Source!P72 -> 222.79
C51: НР от ФОТ | D51: % | E51: =Source!BZ72 -> 109 | I51: =SUM(Q45:Q50) -> 18.22 | J51: =Source!AT72 -> 109 | K51: =SUM(R45:R50) -> 1026.97
C52: СП от ФОТ | D52: % | E52: =Source!CA72 -> 61 | I52: =SUM(S45:S51) -> 10.2 | J52: =Source!AU72 -> 61 | K52: =SUM(T45:T51) -> 574.72
C53: ЗТР | D53: чел-ч | E53: =Source!AQ71 -> 16.89 | G53: 1,15*1,2 | H53: =Source!AV72 -> 1.067 | I53: =Source!U71 -> 1.492191
C54: ВСЕГО работ по позиции: | H54: =I47+I48+I50+I51+I52+0-0-0 -> 359.6 | J54: =K47+K48+K50+K51+K52+0-0-0 -> 2773.13
C55: ВСЕГО оборудование по позиции: | H55: =0+0 -> 0 | J55: =0+0 -> 0
C56: ВСЕГО по позиции: | H56: =I47+I48+I50+I51+I52+0 -> 359.6 | J56: =K47+K48+K50+K51+K52+0 -> 2773.13 | O56: =I47+I48+I50+I51+I52+0 -> 359.6 | P56: =K47+K48+K50+K51+K52+0 -> 2773.13
A58: 2 | B58: =Source!F73 -> 3.17-2-13 | C58: Установка гарнитуры туалетной: вешалок, подстаканников, дозаторов настенных и т.п. | D58: =Source!H73 -> 100 шт. | E58: =Source!I73 -> 0.02 | Q58: =Source!X73 -> 3.11 | R58: =Source!X74 -> 175.05 | S58: =Source!Y73 -> 1.74 | T58: =Source!Y74 -> 97.97 | U58: =ROUND((175/100)*ROUND(Source!R73, 2), 2) -> 0.05 | V58: =ROUND((0/100)*ROUND(Source!R74, 2), 2) -> 0 | AC58: 0
C59: ="Объем: "&Source!I73&"=(1+"&"1)/"&"100" -> Объем: 0,02=(1+1)/100
C60: ЗП | F60: =Source!AO73 -> 95.59 | G60: 1,2*1,15 | H60: =Source!AV74 -> 1.067 | I60: =Source!S73 -> 2.82 | J60: =IF(Source!BA74<> 0, Source!BA74, 1) -> 56.35 | K60: =Source!S74 -> 158.91
C61: ЭМ | F61: =Source!AM73 -> 8.97 | G61: 1,2*1,25 | H61: =Source!AV74 -> 1.067 | I61: =Source!Q73 -> 0.29 | J61: =IF(Source!BB74<> 0, Source!BB74, 1) -> 15.15 | K61: =Source!Q74 -> 4.39
C62: в т.ч. ЗПМ | F62: =Source!AN73 -> 1.01 | G62: 1,2*1,25 | H62: =Source!AV74 -> 1.067 | I62: =Source!R73 -> 0.03 | J62: =IF(Source!BS74<> 0, Source!BS74, 1) -> 56.35 | K62: =Source!R74 -> 1.69
C63: МР | F63: =Source!AL73 -> 2202.04 | H63: =Source!AW74 -> 1 | I63: =Source!P73 -> 44.04 | J63: =IF(Source!BC74<> 0, Source!BC74, 1) -> 0.71 | K63: =Source!P74 -> 31.27
C64: НР от ФОТ | D64: % | E64: =Source!BZ74 -> 109 | I64: =SUM(Q58:Q63) -> 3.11 | J64: =Source!AT74 -> 109 | K64: =SUM(R58:R63) -> 175.05
C65: СП от ФОТ | D65: % | E65: =Source!CA74 -> 61 | I65: =SUM(S58:S64) -> 1.74 | J65: =Source!AU74 -> 61 | K65: =SUM(T58:T64) -> 97.97
C66: ЗТР | D66: чел-ч | E66: =Source!AQ73 -> 8.58 | G66: 1,2*1,15 | H66: =Source!AV74 -> 1.067 | I66: =Source!U73 -> 0.25267414
C67: ВСЕГО работ по позиции: | H67: =I60+I61+I63+I64+I65+0-0-0 -> 52 | J67: =K60+K61+K63+K64+K65+0-0-0 -> 467.59
C68: ВСЕГО оборудование по позиции: | H68: =0+0 -> 0 | J68: =0+0 -> 0
C69: ВСЕГО по позиции: | H69: =I60+I61+I63+I64+I65+0 -> 52 | J69: =K60+K61+K63+K64+K65+0 -> 467.59 | O69: =I60+I61+I63+I64+I65+0 -> 52 | P69: =K60+K61+K63+K64+K65+0 -> 467.59
A71: 3 | B71: =Source!F75 -> 3.70-61-2 | C71: Установка номерных табличек для этажа, подъезда | D71: =Source!H75 -> 1 ШТ. | E71: =Source!I75 -> 1 | Q71: =Source!X75 -> 9.82 | R71: =Source!X76 -> 553.33 | S71: =Source!Y75 -> 6.2 | T71: =Source!Y76 -> 349.13 | U71: =ROUND((175/100)*ROUND(Source!R75, 2), 2) -> 0 | V71: =ROUND((0/100)*ROUND(Source!R76, 2), 2) -> 0 | AC71: 0
C72: ЗП | F72: =Source!AO75 -> 7.79 | G72: 1,15*1,2 | H72: =Source!AV76 -> 1.087 | I72: =Source!S75 -> 11.69 | J72: =IF(Source!BA76<> 0, Source!BA76, 1) -> 56.35 | K72: =Source!S76 -> 658.73
C73: МР | F73: =Source!AL75 -> 0.5 | H73: =Source!AW76 -> 1 | I73: =Source!P75 -> 0.5 | J73: =IF(Source!BC76<> 0, Source!BC76, 1) -> 16.42 | K73: =Source!P76 -> 8.21
A74: 3,1 | B74: =Source!F77 -> КА, п.5 | C74: Тактильно-визуальный знак "Туалет для инвалидов" 136,79 = [1 610 / 1,22 / 9,84] + 2% Заг.скл | D74: =Source!H77 -> ШТ | E74: =Source!I77 -> 1 | F74: =Source!AK77 -> 136.79 | H74: =Source!AW78 -> 1 | I74: =Source!O77 -> 136.79 | J74: =IF(Source!BC78<> 0, Source!BC78, 1) -> 9.84 | K74: =Source!O78 -> 1346.01 | Q74: =Source!X77 -> 0 | R74: =Source!X78 -> 0 | S74: =Source!Y77 -> 0 | T74: =Source!Y78 -> 0 | U74: =ROUND((175/100)*ROUND(Source!R77, 2), 2) -> 0 | V74: =ROUND((0/100)*ROUND(Source!R78, 2), 2) -> 0 | AC74: 3
C75: НР от ФОТ | D75: % | E75: =Source!BZ76 -> 84 | I75: =SUM(Q71:Q74) -> 9.82 | J75: =Source!AT76 -> 84 | K75: =SUM(R71:R74) -> 553.33
C76: СП от ФОТ | D76: % | E76: =Source!CA76 -> 53 | I76: =SUM(S71:S75) -> 6.2 | J76: =Source!AU76 -> 53 | K76: =SUM(T71:T75) -> 349.13
C77: ЗТР | D77: чел-ч | E77: =Source!AQ75 -> 0.52 | G77: 1,15*1,2 | H77: =Source!AV76 -> 1.087 | I77: =Source!U75 -> 0.7800312
C78: ВСЕГО работ по позиции: | H78: =I72+I73+I75+I76+SUM(I74:I74)-SUMIF(AC74:AC74, 5, I74:I74)-SUMIF(AC74:AC74, 6, I74:I74) -> 165 | J78: =K72+K73+K75+K76+SUM(K74:K74)-SUMIF(AC74:AC74, 5, K74:K74)-SUMIF(AC74:AC74, 6, K74:K74) -> 2915.41
C79: ВСЕГО оборудование по позиции: | H79: =SUMIF(AC74:AC74, 5, I74:I74)+SUMIF(AC74:AC74, 6, I74:I74) -> 0 | J79: =SUMIF(AC74:AC74, 5, K74:K74)+SUMIF(AC74:AC74, 6, K74:K74) -> 0
C80: ВСЕГО по позиции: | H80: =I72+I73+I75+I76+SUM(I74:I74) -> 165 | J80: =K72+K73+K75+K76+SUM(K74:K74) -> 2915.41 | O80: =I72+I73+I75+I76+SUM(I74:I74) -> 165 | P80: =K72+K73+K75+K76+SUM(K74:K74) -> 2915.41
A83: =CONCATENATE("Итого по разделу: ",IF(Source!G80<>"Новый раздел", Source!G80, "")) -> Итого по разделу: Оборудование санузла МГН (универсальная кабина) | H83: =SUM(O44:O82) -> 576.6 | J83: =SUM(P44:P82) -> 6156.13 | AQ83: =CONCATENATE("Итого по разделу: ",IF(Source!G80<>"Новый раздел", Source!G80, "")) -> Итого по разделу: Оборудование санузла МГН (универсальная кабина)
A84: Итого по ТСН-2001.16 | I84: =SUM(W44:W83) -> 0 | J84: =SUM(X44:X83) -> 0
A85: Итого возвратных сумм | I85: =SUM(Y44:Y84) -> 0 | J85: =SUM(Z44:Z84) -> 0
A87: =CONCATENATE("Раздел: ",IF(Source!G110<>"Новый раздел", Source!G110, "")) -> Раздел: Оборудование не облагаемое НДС
A88: 4 | B88: =Source!F114 -> КА, п.1 | C88: ОБОРУДОВАНИЕ:_x000D_ Поручень откидной без бумагодержателя, 900х150 мм 1 532,56 = [11 130 / 7,57] + 3% Трансп + 1,2% Заг.скл | D88: =Source!H114 -> ШТ | E88: =Source!I114 -> 1 | F88: =Source!AL114 -> 1532.56 | H88: =Source!AW115 -> 1 | I88: =Source!P114 -> 1532.56 | J88: =IF(Source!BC115<> 0, Source!BC115, 1) -> 7.57 | K88: =Source!P115 -> 11601.48 | Q88: =Source!X114 -> 0 | R88: =Source!X115 -> 0 | S88: =Source!Y114 -> 0 | T88: =Source!Y115 -> 0 | U88: =ROUND((175/100)*ROUND(Source!R114, 2), 2) -> 0 | V88: =ROUND((0/100)*ROUND(Source!R115, 2), 2) -> 0 | AC88: 5
C89: ВСЕГО по позиции: | H89: =I88+0 -> 1532.56 | J89: =K88+0 -> 11601.48 | O89: =I88+0 -> 1532.56 | P89: =K88+0 -> 11601.48
A91: 5 | B91: =Source!F116 -> КА, п.2 | C91: ОБОРУДОВАНИЕ:_x000D_ Поручень для туалета напольный для инвалидов h-образный с бумагодержателем 900х750мм универсальный 1 069,90 = [7 770 / 7,57] + 3% Трансп + 1,2% Заг.скл | D91: =Source!H116 -> ШТ | E91: =Source!I116 -> 1 | F91: =Source!AL116 -> 1069.9 | H91: =Source!AW117 -> 1 | I91: =Source!P116 -> 1069.9 | J91: =IF(Source!BC117<> 0, Source!BC117, 1) -> 7.57 | K91: =Source!P117 -> 8099.14 | Q91: =Source!X116 -> 0 | R91: =Source!X117 -> 0 | S91: =Source!Y116 -> 0 | T91: =Source!Y117 -> 0 | U91: =ROUND((175/100)*ROUND(Source!R116, 2), 2) -> 0 | V91: =ROUND((0/100)*ROUND(Source!R117, 2), 2) -> 0 | AC91: 5
C92: ВСЕГО по позиции: | H92: =I91+0 -> 1069.9 | J92: =K91+0 -> 8099.14 | O92: =I91+0 -> 1069.9 | P92: =K91+0 -> 8099.14
A94: 6 | B94: =Source!F118 -> 13.3-11-80 | C94: ОБОРУДОВАНИЕ:_x000D_ Поручень реабилитационный односекционный, для установки около умывальника, габаритные размеры 700х260 мм. Материал сталь нержавеющая с полировкой, крепление к стене в двух точках, в комплекте: прокладки-амортизаторы резиновые, крепежные элементы | D94: =Source!H118 -> КОМПЛЕКТ | E94: =Source!I118 -> 2 | F94: =Source!AL118 -> 2345.31 | H94: =Source!AW119 -> 1 | I94: =Source!P118 -> 4690.62 | J94: =IF(Source!BC119<> 0, Source!BC119, 1) -> 3.89 | K94: =Source!P119 -> 18246.51 | Q94: =Source!X118 -> 0 | R94: =Source!X119 -> 0 | S94: =Source!Y118 -> 0 | T94: =Source!Y119 -> 0 | U94: =ROUND((175/100)*ROUND(Source!R118, 2), 2) -> 0 | V94: =ROUND((0/100)*ROUND(Source!R119, 2), 2) -> 0 | AC94: 5
C95: ВСЕГО по позиции: | H95: =I94+0 -> 4690.62 | J95: =K94+0 -> 18246.51 | O95: =I94+0 -> 4690.62 | P95: =K94+0 -> 18246.51
A97: 7 | B97: =Source!F120 -> 13.3-11-67 | C97: ОБОРУДОВАНИЕ:_x000D_ Крючок для подвески костылей, габаритные размеры 120х32 мм. Материал сталь нержавеющая с полировкой, крепление на стену, в комплекте: прокладки-амортизаторы резиновые, крепежные элементы | D97: =Source!H120 -> КОМПЛЕКТ | E97: =Source!I120 -> 1 | F97: =Source!AL120 -> 573.3 | H97: =Source!AW121 -> 1 | I97: =Source!P120 -> 573.3 | J97: =IF(Source!BC121<> 0, Source!BC121, 1) -> 3.36 | K97: =Source!P121 -> 1926.29 | Q97: =Source!X120 -> 0 | R97: =Source!X121 -> 0 | S97: =Source!Y120 -> 0 | T97: =Source!Y121 -> 0 | U97: =ROUND((175/100)*ROUND(Source!R120, 2), 2) -> 0 | V97: =ROUND((0/100)*ROUND(Source!R121, 2), 2) -> 0 | AC97: 5
C98: ВСЕГО по позиции: | H98: =I97+0 -> 573.3 | J98: =K97+0 -> 1926.29 | O98: =I97+0 -> 573.3 | P98: =K97+0 -> 1926.29
A100: 8 | B100: =Source!F122 -> 13.3-11-75 | C100: ОБОРУДОВАНИЕ:_x000D_ Поручень реабилитационный настенный, габаритные размеры 600х90 мм. Материал сталь нержавеющая с полировкой, крепление к стене в двух точках, в комплекте: прокладки-амортизаторы резиновые, крепежные элементы | D100: =Source!H122 -> КОМПЛЕКТ | E100: =Source!I122 -> 1 | F100: =Source!AL122 -> 2345.31 | H100: =Source!AW123 -> 1 | I100: =Source!P122 -> 2345.31 | J100: =IF(Source!BC123<> 0, Source!BC123, 1) -> 3.89 | K100: =Source!P123 -> 9123.26 | Q100: =Source!X122 -> 0 | R100: =Source!X123 -> 0 | S100: =Source!Y122 -> 0 | T100: =Source!Y123 -> 0 | U100: =ROUND((175/100)*ROUND(Source!R122, 2), 2) -> 0 | V100: =ROUND((0/100)*ROUND(Source!R123, 2), 2) -> 0 | AC100: 5
C101: ВСЕГО по позиции: | H101: =I100+0 -> 2345.31 | J101: =K100+0 -> 9123.26 | O101: =I100+0 -> 2345.31 | P101: =K100+0 -> 9123.26
A103: 9 | B103: =Source!F124 -> КА, п.3 | C103: ОБОРУДОВАНИЕ:_x000D_ Поручень - опора регулируемая с подушкой для спины в санитарно-гигиенические комнаты 250-370х650 1 404,49 = [10 200 / 7,57] + 3% Трансп + 1,2% Заг.скл | D103: =Source!H124 -> ШТ | E103: =Source!I124 -> 1 | F103: =Source!AL124 -> 1404.49 | H103: =Source!AW125 -> 1 | I103: =Source!P124 -> 1404.49 | J103: =IF(Source!BC125<> 0, Source!BC125, 1) -> 7.57 | K103: =Source!P125 -> 10631.99 | Q103: =Source!X124 -> 0 | R103: =Source!X125 -> 0 | S103: =Source!Y124 -> 0 | T103: =Source!Y125 -> 0 | U103: =ROUND((175/100)*ROUND(Source!R124, 2), 2) -> 0 | V103: =ROUND((0/100)*ROUND(Source!R125, 2), 2) -> 0 | AC103: 5
C104: ВСЕГО по позиции: | H104: =I103+0 -> 1404.49 | J104: =K103+0 -> 10631.99 | O104: =I103+0 -> 1404.49 | P104: =K103+0 -> 10631.99
A107: =CONCATENATE("Итого по разделу: ",IF(Source!G127<>"Новый раздел", Source!G127, "")) -> Итого по разделу: Оборудование не облагаемое НДС | H107: =SUM(O87:O106) -> 11616.18 | J107: =SUM(P87:P106) -> 59628.67
A108: Итого по ТСН-2001.16 | I108: =SUM(W87:W107) -> 0 | J108: =SUM(X87:X107) -> 0
A109: Итого возвратных сумм | I109: =SUM(Y87:Y108) -> 0 | J109: =SUM(Z87:Z108) -> 0
A111: =CONCATENATE("Раздел: ",IF(Source!G157<>"Новый раздел", Source!G157, "")) -> Раздел: Оборудование облагаемое НДС
A112: 10 | B112: =Source!F161 -> КА, п.4 | C112: ОБОРУДОВАНИЕ:_x000D_ Зеркало настенное поворотное, 600х400 мм 1 211,04 = [10 730 / 1,22 / 7,57] + 3% Трансп + 1,2% Заг.скл | D112: =Source!H161 -> ШТ | E112: =Source!I161 -> 1 | F112: =Source!AL161 -> 1211.04 | H112: =Source!AW162 -> 1 | I112: =Source!P161 -> 1211.04 | J112: =IF(Source!BC162<> 0, Source!BC162, 1) -> 7.57 | K112: =Source!P162 -> 9167.57 | Q112: =Source!X161 -> 0 | R112: =Source!X162 -> 0 | S112: =Source!Y161 -> 0 | T112: =Source!Y162 -> 0 | U112: =ROUND((175/100)*ROUND(Source!R161, 2), 2) -> 0 | V112: =ROUND((0/100)*ROUND(Source!R162, 2), 2) -> 0 | AC112: 5
C113: ВСЕГО по позиции: | H113: =I112+0 -> 1211.04 | J113: =K112+0 -> 9167.57 | O113: =I112+0 -> 1211.04 | P113: =K112+0 -> 9167.57
A116: =CONCATENATE("Итого по разделу: ",IF(Source!G164<>"Новый раздел", Source!G164, "")) -> Итого по разделу: Оборудование облагаемое НДС | H116: =SUM(O111:O115) -> 1211.04 | J116: =SUM(P111:P115) -> 9167.57
A117: Итого по ТСН-2001.16 | I117: =SUM(W111:W116) -> 0 | J117: =SUM(X111:X116) -> 0
A118: Итого возвратных сумм | I118: =SUM(Y111:Y117) -> 0 | J118: =SUM(Z111:Z117) -> 0
A120: =CONCATENATE("Раздел: ",IF(Source!G194<>"Новый раздел", Source!G194, "")) -> Раздел: Тактильные знаки, наклейки
A121: 11 | B121: =Source!F198 -> 3.70-61-2 | C121: Установка номерных табличек для этажа, подъезда | D121: =Source!H198 -> 1 ШТ. | E121: =Source!I198 -> 18 | Q121: =Source!X198 -> 176.69 | R121: =Source!X199 -> 9956.23 | S121: =Source!Y198 -> 111.48 | T121: =Source!Y199 -> 6281.91 | U121: =ROUND((175/100)*ROUND(Source!R198, 2), 2) -> 0 | V121: =ROUND((0/100)*ROUND(Source!R199, 2), 2) -> 0 | AC121: 0
C122: ="Объем: "&Source!I198&"=2+"&"2+"&"1+"&"1+"&"1+"&"1+"&"1+"&"1+"&"2+"&"1+"&"1+"&"1+"&"3" -> Объем: 18=2+2+1+1+1+1+1+1+2+1+1+1+3
C123: ЗП | F123: =Source!AO198 -> 7.79 | G123: 1,15*1,2 | H123: =Source!AV199 -> 1.087 | I123: =Source!S198 -> 210.34 | J123: =IF(Source!BA199<> 0, Source!BA199, 1) -> 56.35 | K123: =Source!S199 -> 11852.66
C124: МР | F124: =Source!AL198 -> 0.5 | H124: =Source!AW199 -> 1 | I124: =Source!P198 -> 9 | J124: =IF(Source!BC199<> 0, Source!BC199, 1) -> 16.42 | K124: =Source!P199 -> 147.78
C125: НР от ФОТ | D125: % | E125: =Source!BZ199 -> 84 | I125: =SUM(Q121:Q124) -> 176.69 | J125: =Source!AT199 -> 84 | K125: =SUM(R121:R124) -> 9956.23
C126: СП от ФОТ | D126: % | E126: =Source!CA199 -> 53 | I126: =SUM(S121:S125) -> 111.48 | J126: =Source!AU199 -> 53 | K126: =SUM(T121:T125) -> 6281.91
C127: ЗТР | D127: чел-ч | E127: =Source!AQ198 -> 0.52 | G127: 1,15*1,2 | H127: =Source!AV199 -> 1.087 | I127: =Source!U198 -> 14.040562
C128: ВСЕГО работ по позиции: | H128: =I123+I124+I125+I126+0-0-0 -> 507.51 | J128: =K123+K124+K125+K126+0-0-0 -> 28238.58
C129: ВСЕГО оборудование по позиции: | H129: =0+0 -> 0 | J129: =0+0 -> 0
...

Sheet Source
A1: 0 | B1: Smeta.RU (495) 974-1589 | D1: _PS_ | F1: 0 | G1: 0 | H1: 0 | I1: Smeta.RU | K1: 1 | L1: 74599 | M1: 10 | N1: 12 | O1: 1 | P1: 0 | Q1: 5
A4: 1 | B4: 1 | C4: -1 | G4: Капитальный ремонт здания Государственного бюджетного общеобразовательного учреждения города Москвы «Школа №1574», расположенного по адресу: г. Москва, Старопименовский переулок, д. 5. 1 этап | EC4: 0
A5: 8 | B5: 1 | C5: -1 | G5: Капитальный ремонт здания Государственного бюджетного общеобразовательного учреждения города Москвы «Школа №1574», расположенного по адресу: г. Москва, Старопименовский переулок, д. 5. 1 этап | EC5: 0
A12: 1 | B12: 375 | C12: 0 | D12: =ROW(A334) -> 334 | E12: 0 | F12: 02-01-20 | G12: 02-01-20 ОДИ 16.07.26 | I12: 0 | J12: 2024-00377-01-0-ОДИ.ВОР | K12: 0 | L12: 0 | M12: 4098 | O12: 0 | P12: 0 | Q12: 0 | R12: 0 | S12: 0 | T12: 1 | V12: 0 | AB12: О.А.Гришечкина | AC12: Ведущий инженер-сметчик | AD12: И.В.Феденко | AE12: Начальник отдела | BB12: 0 | BH12: Сметные нормы списания | BI12: Коды ОКП для ТСН-2001 МГЭ Дополнение 81 | BJ12: 1 | BK12: 1 | BL12: 0 | BM12: 0 | BN12: 1 | BO12: 0 | BP12: 6 | BQ12: 2 | BR12: 1 | BS12: 1 | BT12: 0 | BU12: 0 | BV12: 0 | BW12: 0 | BX12: 0 | BY12: ТСН-2001 (МГЭ) Доп 81 - Ремонт | BZ12: Типовой расчет для ТСН-2001 МГЭ, Дополнение 81, ремонт | CA12: Территориальные сметные нормативы для Москвы ТСН-2001 (МГЭ), дополнение 81 | CB12: Территориальные сметные нормативы для Москвы ТСН-2001 (МГЭ), дополнение 81 | CC12: Территориальные сметные нормативы для Москвы ТСН-2001 (МГЭ), дополнение 81 | CD12: Территориальные сметные нормативы для Москвы ТСН-2001 (МГЭ), дополнение 81 | CE12: Поправки для ТСН-2001 от 07.04.2026 г. доп.81 | CF12: 0 | CG12: 0 | CH12: 8200 | CK12: 82 | CQ12: Территориальные сметные нормативы для Москвы (ТСН-2001) | CR12: ТЕР | CS12: 41660 | CT12: 1 | CU12: 81 | CY12: 0 | EC12: 0
A15: 15 | B15: 1
A18: 52 | B18: =B334 -> 375 | C18: =C334 -> 1 | D18: =D334 -> 12 | E18: =E334 -> 0 | F18: =F334 -> 02-01-20 | G18: =G334 -> 02-01-20 ОДИ 16.07.26 | O18: =O334 -> 17437.48 | P18: =P334 -> 17109.22 | Q18: =Q334 -> 1.01 | R18: =R334 -> 0.08 | S18: =S334 -> 327.25 | T18: =T334 -> 0 | U18: =U334 -> 24.208651 | V18: =V334 -> 0 | ... GX18: =GX334 -> 0
A20: 3 | B20: 1 | D20: =ROW(A304) -> 304 | F20: 02-01-20 | G20: Мероприятия по обеспечению доступа инвалидов | I20: 0 | J20: 2024-00377-01-0-ОДИ.ВОР | K20: -1 | L20: 02-01-20 | S20: 0 | T20: 0 | V20: 0 | BX20: 0 | CF20: 0 | CG20: 0
A22: 52 | B22: =B304 -> 1 | C22: =C304 -> 3 | D22: =D304 -> 20 | E22: =E304 -> 0 | F22: =F304 -> 02-01-20 | G22: =G304 -> Мероприятия по обеспечению доступа инвалидов | O22: =O304 -> 17437.48 | P22: =P304 -> 17109.22 | Q22: =Q304 -> 1.01 | R22: =R304 -> 0.08 | S22: =S304 -> 327.25 | T22: =T304 -> 0 | U22: =U304 -> 24.208651 | V22: =V304 -> 0 | ... GX22: =GX304 -> 0
A24: 4 | B24: 1 | D24: =ROW(A37) -> 37 | F24: Новый раздел | G24: Демонтажные работы (Письмо от АНО «РГТ» об утверждении объёмов демонтажных работ) | I24: 0 | K24: -1 | S24: 0 | T24: 0 | V24: 0 | BX24: 0 | CJ24: 0
A26: 52 | B26: =B37 -> 1 | C26: =C37 -> 4 | D26: =D37 -> 24 | E26: =E37 -> 0 | F26: =F37 -> Новый раздел | G26: =G37 -> Демонтажные работы (Письмо от АНО «РГТ» об утверждении объёмов демонтажных работ) | O26: =O37 -> 0 | P26: =P37 -> 0 | Q26: =Q37 -> 0 | R26: =R37 -> 0 | S26: =S37 -> 0 | T26: =T37 -> 0 | U26: =U37 -> 0 | V26: =V37 -> 0 | ... GX26: =GX37 -> 0
A28: 17 | B28: 1 | C28: =ROW(SmtRes!A6) -> 6 | D28: =ROW(EtalonRes!A7) -> 7 | F28: 3.17-2-14 | G28: Установка гарнитуры туалетной: поручней для ванн / демонтаж поручней | H28: 100 шт. | I28: =ROUND((1+1+2+1+1)/100,9) -> 0.06 | J28: 0 | K28: =ROUND((1+1+2+1+1)/100,9) -> 0.06 | O28: =ROUND(CP28,2) -> 198.7 | P28: =ROUND((ROUND((AC28*AW28*I28),2)*BC28),2) -> 188.27 | Q28: =(ROUND((ROUND((((((ET28*1.25)*1.2)*0.6))*AV28*I28),2)*BB28),2)+ROUND((ROUND(((AE28-((((EU28*1.25)*1.2)*0.6)))*AV28*I28),2)*BS28),2)) -> 0.43 | R28: =(ROUND((ROUND((((((EU28*1.25)*1.2)*0.6))*AV28*I28),2)*BS28),2)+ROUND((ROUND(((AE28-((((EU28*1.25)*1.2)*0.6)))*AV28*I28),2)*BS28),2)) -> 0.03 | S28: =ROUND((ROUND((AF28*AV28*I28),2)*BA28),2) -> 10 | T28: =ROUND(CU28*I28,2) -> 0 | U28: =CV28*I28 -> 0.89531458 | V28: =CW28*I28 -> 0 | W28: =ROUND(CX28*I28,2) -> 0 | X28: =(ROUND((((S28+ROUND((ROUND((((((EU28*1.25)*1.2)*0.6))*AV28*I28),2)*BS28),2))*AT28)/100),2)+ROUND(((ROUND((ROUND(((AE28-((((EU28*1.25)*1.2)*0.6)))*AV28*I28),2)*BS28),2)*AT28)/100),2)) -> 10.93 | Y28: =(ROUND((((S28+ROUND((ROUND((((((EU28*1.25)*1.2)*0.6))*AV28*I28),2)*BS28),2))*AU28)/100),2)+ROUND(((ROUND((ROUND(((AE28-((((EU28*1.25)*1.2)*0.6)))*AV28*I28),2)*BS28),2)*AU28)/100),2)) -> 6.12 | AA28: -1 | AB28: =ROUND((AC28+AD28+AF28),6) -> 3300.9382 | AC28: =ROUND(((((ES28*1)*1)*0.6)),6) -> 3137.892 | AD28: =ROUND(((((((ET28*1.25)*1.2)*0.6))-((((EU28*1.25)*1.2)*0.6)))+AE28),6) -> 6.786 | AE28: =ROUND(((((EU28*1.25)*1.2)*0.6)),6) -> 0.45 | AF28: =ROUND(((((EV28*1.15)*1.2)*0.6)),6) -> 156.26016 | AG28: =ROUND((AP28),6) -> 0 | AH28: =((((EW28*1.15)*1.2)*0.6)) -> 13.98492 | AI28: =((((EX28*1.25)*1.2)*0.6)) -> 0 | AJ28: =(AS28) -> 0 | AK28: 5426.08 | AL28: 5229.82 | AM28: 7.54 | AN28: 0.5 | AO28: 188.72 | AP28: 0 | AQ28: 16.89 | AR28: 0 | AS28: 0 | AT28: 109 | AU28: 61 | AV28: 1.067 | AW28: 1 | AZ28: 1 | BA28: 1 | BB28: 1 | BC28: 1 | BH28: 0 | BI28: 1 | BJ28: ТСН-2001.3 Доп. 80, Сб. 17, т. 2, поз. 14 | BM28: 22 | BN28: 0 | BO28: 3.17-2-14 | BP28: 1 | BQ28: 30 | BR28: 0 | BS28: 1 | BT28: 1 | BU28: 1 | BV28: 1 | BW28: 1 | BX28: 1 | BZ28: 109 | CA28: 61 | CE28: 1566 | CF28: 0 | CG28: 0 | CM28: 0 | CN28: Поправка: Гл.6.Прил.2.2.п.2.2.6_06.00.01.07.001 Наименование: При выполнении при капитальном ремонте и реконструкции работ, аналогичных технологическим процессам, характерным для нового строительства, и отсутствующих в сборниках на ремонтно-строительные работы ТСН-2001.6 Поправка: Гл.12.Прил.8.п.8. 3_12.00.01.11.001 Наименование: При наличии напряженных и стесненных условий производства работ (стесненность, сложность складирования и транспортной логистики и т.п.) для объектов, расположенных в пределах круговой магистральной системы улиц "Садовое кольцо" города Москвы Поправка: Гл.6.Прил.2.2.п.2.2.16_06.00.01.35.006 Наименование: При демонтаже металлических конструкций (в т.ч. к стоимости вспомогательных материалов) | CO28: 0 | CP28: =(P28+Q28+S28) -> 198.7 | CQ28: =ROUND((ROUND((AC28*AW28*1),2)*BC28),2) -> 3137.89 | CR28: =(ROUND((ROUND((((((ET28*1.25)*1.2)*0.6))*AV28*1),2)*BB28),2)+ROUND((ROUND(((AE28-((((EU28*1.25)*1.2)*0.6)))*AV28*1),2)*BS28),2)) -> 7.24 | CS28: =(ROUND((ROUND((((((EU28*1.25)*1.2)*0.6))*AV28*1),2)*BS28),2)+ROUND((ROUND(((AE28-((((EU28*1.25)*1.2)*0.6)))*AV28*1),2)*BS28),2)) -> 0.48 | CT28: =ROUND((ROUND((AF28*AV28*1),2)*BA28),2) -> 166.73 | CU28: =AG28 -> 0 | CV28: =(AH28*AV28) -> 14.92191 | CW28: =AI28 -> 0 | CX28: =AJ28 -> 0 | CY28: =(ROUND((((S28+ROUND((ROUND((((((EU28*1.25)*1.2)*0.6))*AV28*1),2)*BS28),2))*AT28)/100),2)+ROUND(((ROUND((ROUND(((AE28-((((EU28*1.25)*1.2)*0.6)))*AV28*1),2)*BS28),2)*AT28)/100),2)) -> 11.42 | CZ28: =(ROUND((((S28+ROUND((ROUND((((((EU28*1.25)*1.2)*0.6))*AV28*1),2)*BS28),2))*AU28)/100),2)+ROUND(((ROUND((ROUND(((AE28-((((EU28*1.25)*1.2)*0.6)))*AV28*1),2)*BS28),2)*AU28)/100),2)) -> 6.39 | DB28: 1 | DD28: *1)*1)*0,6 | DE28: *1,25)*1,2)*0,6 | DF28: *1,25)*1,2)*0,6 | DG28: *1,15)*1,2)*0,6 | DI28: *1,15)*1,2)*0,6 | DJ28: *1,25)*1,2)*0,6 | DN28: 0 | DO28: 0 | DP28: 1 | DQ28: 1 | DU28: 1010 | DV28: 100 шт. | DW28: 100 шт. | DX28: 100 | EE28: 55393925 | EF28: 30 | EG28: Строительные работы | EH28: 0 | EJ28: 1 | EK28: 22 | EL28: ТСН-2001.3-17. Водопровод и канализация - внутренние устройства | EM28: ТСН-2001.3-17-1 | EO28: Поправка: Гл.6.Прил.2.2.п.2.2.6_06.00.01.07.001 Поправка: Гл.12.Прил.8.п.8. 3_12.00.01.11.001 Поправка: Гл.6.Прил.2.2.п.2.2.16_06.00.01.35.006 | EQ28: 1024 | ER28: 5426.08 | ES28: 5229.82 | ET28: 7.54 | EU28: 0.5 | EV28: 188.72 | EW28: 16.89 | EX28: 0 | EY28: 0 | FQ28: 0 | FR28: 0 | FS28: 0 | FX28: 109 | FY28: 61 | GD28: 1 | GF28: 981970529 | GG28: 2 | GH28: 1 | GI28: 2 | GJ28: 0 | GK28: 0 | GL28: =ROUND(IF(AND(BH28=3,BI28=3,FS28<>0),P28,0),2) -> 0 | GM28: =ROUND(O28+X28+Y28,2)+GX28 -> 215.75 | GN28: =IF(OR(BI28=0,BI28=1),GM28-GX28,0) -> 215.75 | GO28: =IF(BI28=2,GM28-GX28,0) -> 0 | GP28: =IF(BI28=4,GM28-GX28,0) -> 0 | GR28: 0 | GS28: 3 | GT28: 0 | GV28: =ROUND((GT28),6) -> 0 | GW28: 1 | GX28: =ROUND(HC28*I28,2) -> 0 | HA28: 0 | HB28: 0 | HC28: =GV28*GW28 -> 0 | HS28: 0 | IK28: 0
A29: 17 | B29: 1 | C29: =ROW(SmtRes!A12) -> 12 | D29: =ROW(EtalonRes!A14) -> 14 | F29: 3.17-2-14 | G29: Установка гарнитуры туалетной: поручней для ванн / демонтаж поручней | H29: 100 шт. | I29: =ROUND((1+1+2+1+1)/100,9) -> 0.06 | J29: 0 | K29: =ROUND((1+1+2+1+1)/100,9) -> 0.06 | O29: =ROUND(CP29,2) -> 702.73 | P29: =ROUND((ROUND((AC29*AW29*I29),2)*BC29),2) -> 133.67 | Q29: =(ROUND((ROUND((((((ET29*1.25)*1.2)*0.6))*AV29*I29),2)*BB29),2)+ROUND((ROUND(((AE29-((((EU29*1.25)*1.2)*0.6)))*AV29*I29),2)*BS29),2)) -> 5.56 | R29: =(ROUND((ROUND((((((EU29*1.25)*1.2)*0.6))*AV29*I29),2)*BS29),2)+ROUND((ROUND(((AE29-((((EU29*1.25)*1.2)*0.6)))*AV29*I29),2)*BS29),2)) -> 1.69 | S29: =ROUND((ROUND((AF29*AV29*I29),2)*BA29),2) -> 563.5 | T29: =ROUND(CU29*I29,2) -> 0 | U29: =CV29*I29 -> 0.89531458 | V29: =CW29*I29 -> 0 | W29: =ROUND(CX29*I29,2) -> 0 | X29: =(ROUND((((S29+ROUND((ROUND((((((EU29*1.25)*1.2)*0.6))*AV29*I29),2)*BS29),2))*AT29)/100),2)+ROUND(((ROUND((ROUND(((AE29-((((EU29*1.25)*1.2)*0.6)))*AV29*I29),2)*BS29),2)*AT29)/100),2)) -> 616.06 | Y29: =(ROUND((((S29+ROUND((ROUND((((((EU29*1.25)*1.2)*0.6))*AV29*I29),2)*BS29),2))*AU29)/100),2)+ROUND(((ROUND((ROUND(((AE29-((((EU29*1.25)*1.2)*0.6)))*AV29*I29),2)*BS29),2)*AU29)/100),2)) -> 344.77 | AA29: -1 | AB29: =ROUND((AC29+AD29+AF29),6) -> 3300.9382 | AC29: =ROUND(((((ES29*1)*1)*0.6)),6) -> 3137.892 | AD29: =ROUND(((((((ET29*1.25)*1.2)*0.6))-((((EU29*1.25)*1.2)*0.6)))+AE29),6) -> 6.786 | AE29: =ROUND(((((EU29*1.25)*1.2)*0.6)),6) -> 0.45 | AF29: =ROUND(((((EV29*1.15)*1.2)*0.6)),6) -> 156.26016 | AG29: =ROUND((AP29),6) -> 0 | AH29: =((((EW29*1.15)*1.2)*0.6)) -> 13.98492 | AI29: =((((EX29*1.25)*1.2)*0.6)) -> 0 | AJ29: =(AS29) -> 0 | AK29: 5426.08 | AL29: 5229.82 | AM29: 7.54 | AN29: 0.5 | AO29: 188.72 | AP29: 0 | AQ29: 16.89 | AR29: 0 | AS29: 0 | AT29: 109 | AU29: 61 | AV29: 1.067 | AW29: 1 | AZ29: 1 | BA29: 56.35 | BB29: 12.92 | BC29: 0.71 | BH29: 0 | BI29: 1 | BJ29: ТСН-2001.3 Доп. 80, Сб. 17, т. 2, поз. 14 | BM29: 22 | BN29: 0 | BO29: 3.17-2-14 | BP29: 1 | BQ29: 30 | BR29: 0 | BS29: 56.35 | BT29: 1 | BU29: 1 | BV29: 1 | BW29: 1 | BX29: 1 | BZ29: 109 | CA29: 61 | CE29: 1566 | CF29: 0 | CG29: 0 | CM29: 0 | CN29: Поправка: Гл.6.Прил.2.2.п.2.2.6_06.00.01.07.001 Наименование: При выполнении при капитальном ремонте и реконструкции работ, аналогичных технологическим процессам, характерным для нового строительства, и отсутствующих в сборниках на ремонтно-строительные работы ТСН-2001.6 Поправка: Гл.12.Прил.8.п.8. 3_12.00.01.11.001 Наименование: При наличии напряженных и стесненных условий производства работ (стесненность, сложность складирования и транспортной логистики и т.п.) для объектов, расположенных в пределах круговой магистральной системы улиц "Садовое кольцо" города Москвы Поправка: Гл.6.Прил.2.2.п.2.2.16_06.00.01.35.006 Наименование: При демонтаже металлических конструкций (в т.ч. к стоимости вспомогательных материалов) | CO29: 0 | CP29: =(P29+Q29+S29) -> 702.73 | CQ29: =ROUND((ROUND((AC29*AW29*1),2)*BC29),2) -> 2227.9 | CR29: =(ROUND((ROUND((((((ET29*1.25)*1.2)*0.6))*AV29*1),2)*BB29),2)+ROUND((ROUND(((AE29-((((EU29*1.25)*1.2)*0.6)))*AV29*1),2)*BS29),2)) -> 93.54 | CS29: =(ROUND((ROUND((((((EU29*1.25)*1.2)*0.6))*AV29*1),2)*BS29),2)+ROUND((ROUND(((AE29-((((EU29*1.25)*1.2)*0.6)))*AV29*1),2)*BS29),2)) -> 27.05 | CT29: =ROUND((ROUND((AF29*AV29*1),2)*BA29),2) -> 9395.24 | CU29: =AG29 -> 0 | CV29: =(AH29*AV29) -> 14.92191 | CW29: =AI29 -> 0 | CX29: =AJ29 -> 0 | CY29: =(ROUND((((S29+ROUND((ROUND((((((EU29*1.25)*1.2)*0.6))*AV29*1),2)*BS29),2))*AT29)/100),2)+ROUND(((ROUND((ROUND(((AE29-((((EU29*1.25)*1.2)*0.6)))*AV29*1),2)*BS29),2)*AT29)/100),2)) -> 643.7 | CZ29: =(ROUND((((S29+ROUND((ROUND((((((EU29*1.25)*1.2)*0.6))*AV29*1),2)*BS29),2))*AU29)/100),2)+ROUND(((ROUND((ROUND(((AE29-((((EU29*1.25)*1.2)*0.6)))*AV29*1),2)*BS29),2)*AU29)/100),2)) -> 360.24 | DB29: 4 | DD29: *1)*1)*0,6 | DE29: *1,25)*1,2)*0,6 | DF29: *1,25)*1,2)*0,6 | DG29: *1,15)*1,2)*0,6 | DI29: *1,15)*1,2)*0,6 | DJ29: *1,25)*1,2)*0,6 | DN29: 0 | DO29: 0 | DP29: 1 | DQ29: 1 | DU29: 1010 | DV29: 100 шт. | DW29: 100 шт. | DX29: 100 | EE29: 55393925 | EF29: 30 | EG29: Строительные работы | EH29: 0 | EJ29: 1 | EK29: 22 | EL29: ТСН-2001.3-17. Водопровод и канализация - внутренние устройства | EM29: ТСН-2001.3-17-1 | EO29: Поправка: Гл.6.Прил.2.2.п.2.2.6_06.00.01.07.001 Поправка: Гл.12.Прил.8.п.8. 3_12.00.01.11.001 Поправка: Гл.6.Прил.2.2.п.2.2.16_06.00.01.35.006 | EQ29: 1024 | ER29: 5426.08 | ES29: 5229.82 | ET29: 7.54 | EU29: 0.5 | EV29: 188.72 | EW29: 16.89 | EX29: 0 | EY29: 0 | FQ29: 0 | FR29: 0 | FS29: 0 | FX29: 109 | FY29: 61 | GD29: 1 | GF29: 981970529 | GG29: 2 | GH29: 1 | GI29: 2 | GJ29: 0 | GK29: 0 | GL29: =ROUND(IF(AND(BH29=3,BI29=3,FS29<>0),P29,0),2) -> 0 | GM29: =ROUND(O29+X29+Y29,2)+GX29 -> 1663.56 | GN29: =IF(OR(BI29=0,BI29=1),GM29-GX29,0) -> 1663.56 | GO29: =IF(BI29=2,GM29-GX29,0) -> 0 | GP29: =IF(BI29=4,GM29-GX29,0) -> 0 | GR29: 0 | GS29: 3 | GT29: 0 | GV29: =ROUND((GT29),6) -> 0 | GW29: 1 | GX29: =ROUND(HC29*I29,2) -> 0 | HA29: 0 | HB29: 0 | HC29: =GV29*GW29 -> 0 | HS29: 0 | IK29: 0
A30: 17 | B30: 1 | C30: =ROW(SmtRes!A18) -> 18 | D30: =ROW(EtalonRes!A21) -> 21 | F30: 3.17-2-13 | G30: Установка гарнитуры туалетной: вешалок, подстаканников, дозаторов настенных и т.п. / демонтаж зеркала и крючка для костылей | H30: 100 шт. | I30: =ROUND((1+1)/100,9) -> 0.02 | J30: 0 | K30: =ROUND((1+1)/100,9) -> 0.02 | O30: =ROUND(CP30,2) -> 28.28 | P30: =ROUND((ROUND((AC30*AW30*I30),2)*BC30),2) -> 26.42 | Q30: =(ROUND((ROUND((((((ET30*1.2)*1.25)*0.6))*AV30*I30),2)*BB30),2)+ROUND((ROUND(((AE30-((((EU30*1.2)*1.25)*0.6)))*AV30*I30),2)*BS30),2)) -> 0.17 | R30: =(ROUND((ROUND((((((EU30*1.2)*1.25)*0.6))*AV30*I30),2)*BS30),2)+ROUND((ROUND(((AE30-((((EU30*1.2)*1.25)*0.6)))*AV30*I30),2)*BS30),2)) -> 0.02 | S30: =ROUND((ROUND((AF30*AV30*I30),2)*BA30),2) -> 1.69 | T30: =ROUND(CU30*I30,2) -> 0 | U30: =CV30*I30 -> 0.15160448 | V30: =CW30*I30 -> 0 | W30: =ROUND(CX30*I30,2) -> 0 | X30: =(ROUND((((S30+ROUND((ROUND((((((EU30*1.2)*1.25)*0.6))*AV30*I30),2)*BS30),2))*AT30)/100),2)+ROUND(((ROUND((ROUND(((AE30-((((EU30*1.2)*1.25)*0.6)))*AV30*I30),2)*BS30),2)*AT30)/100),2)) -> 1.86 | Y30: =(ROUND((((S30+ROUND((ROUND((((((EU30*1.2)*1.25)*0.6))*AV30*I30),2)*BS30),2))*AU30)/100),2)+ROUND(((ROUND((ROUND(((AE30-((((EU30*1.2)*1.25)*0.6)))*AV30*I30),2)*BS30),2)*AU30)/100),2)) -> 1.04 | AA30: -1 | AB30: =ROUND((AC30+AD30+AF30),6) -> 1408.4455 | AC30: =ROUND(((((ES30*1)*1)*0.6)),6) -> 1321.224 | AD30: =ROUND(((((((ET30*1.2)*1.25)*0.6))-((((EU30*1.2)*1.25)*0.6)))+AE30),6) -> 8.073 | AE30: =ROUND(((((EU30*1.2)*1.25)*0.6)),6) -> 0.909 | AF30: =ROUND(((((EV30*1.2)*1.15)*0.6)),6) -> 79.14852 | AG30: =ROUND((AP30),6) -> 0 | AH30: =((((EW30*1.2)*1.15)*0.6)) -> 7.10424 | AI30: =((((EX30*1.2)*1.25)*0.6)) -> 0 | AJ30: =(AS30) -> 0 | AK30: 2306.6 | AL30: 2202.04 | AM30: 8.97 | AN30: 1.01 | AO30: 95.59 | AP30: 0 | AQ30: 8.58 | AR30: 0 | AS30: 0 | AT30: 109 | AU30: 61 | AV30: 1.067 | AW30: 1 | AZ30: 1 | BA30: 1 | BB30: 1 | BC30: 1 | BH30: 0 | BI30: 1 | BJ30: ТСН-2001.3 Доп. 80, Сб. 17, т. 2, поз. 13 | BM30: 22 | BN30: 0 | BO30: 3.17-2-13 | BP30: 1 | BQ30: 30 | BR30: 0 | BS30: 1 | BT30: 1 | BU30: 1 | BV30: 1 | BW30: 1 | BX30: 1 | BZ30: 109 | CA30: 61 | CE30: 1566 | CF30: 0 | CG30: 0 | CM30: 0 | CN30: Поправка: Гл.12.Прил.8.п.8. 3_12.00.01.11.001 Наименование: При наличии напряженных и стесненных условий производства работ (стесненность, сложность складирования и транспортной логистики и т.п.) для объектов, расположенных в пределах круговой магистральной системы улиц "Садовое кольцо" города Москвы Поправка: Гл.6.Прил.2.2.п.2.2.6_06.00.01.07.001 Наименование: При выполнении при капитальном ремонте и реконструкции работ, аналогичных технологическим процессам, характерным для нового строительства, и отсутствующих в сборниках на ремонтно-строительные работы ТСН-2001.6 Поправка: Гл.6.Прил.2.2.п.2.2.16_06.00.01.35.006 Наименование: При демонтаже металлических конструкций (в т.ч. к стоимости вспомогательных материалов) | CO30: 0 | CP30: =(P30+Q30+S30) -> 28.28 | CQ30: =ROUND((ROUND((AC30*AW30*1),2)*BC30),2) -> 1321.22 | CR30: =(ROUND((ROUND((((((ET30*1.2)*1.25)*0.6))*AV30*1),2)*BB30),2)+ROUND((ROUND(((AE30-((((EU30*1.2)*1.25)*0.6)))*AV30*1),2)*BS30),2)) -> 8.61 | CS30: =(ROUND((ROUND((((((EU30*1.2)*1.25)*0.6))*AV30*1),2)*BS30),2)+ROUND((ROUND(((AE30-((((EU30*1.2)*1.25)*0.6)))*AV30*1),2)*BS30),2)) -> 0.97 | CT30: =ROUND((ROUND((AF30*AV30*1),2)*BA30),2) -> 84.45 | CU30: =AG30 -> 0 | CV30: =(AH30*AV30) -> 7.5802241 | CW30: =AI30 -> 0 | CX30: =AJ30 -> 0 | CY30: =(ROUND((((S30+ROUND((ROUND((((((EU30*1.2)*1.25)*0.6))*AV30*1),2)*BS30),2))*AT30)/100),2)+ROUND(((ROUND((ROUND(((AE30-((((EU30*1.2)*1.25)*0.6)))*AV30*1),2)*BS30),2)*AT30)/100),2)) -> 2.9 | CZ30: =(ROUND((((S30+ROUND((ROUND((((((EU30*1.2)*1.25)*0.6))*AV30*1),2)*BS30),2))*AU30)/100),2)+ROUND(((ROUND((ROUND(((AE30-((((EU30*1.2)*1.25)*0.6)))*AV30*1),2)*BS30),2)*AU30)/100),2)) -> 1.62 | DB30: 7 | DD30: *1)*1)*0,6 | DE30: *1,2)*1,25)*0,6 | DF30: *1,2)*1,25)*0,6 | DG30: *1,2)*1,15)*0,6 | DI30: *1,2)*1,15)*0,6 | DJ30: *1,2)*1,25)*0,6 | DN30: 0 | DO30: 0 | DP30: 1 | DQ30: 1 | DU30: 1010 | DV30: 100 шт. | DW30: 100 шт. | DX30: 100 | EE30: 55393925 | EF30: 30 | EG30: Строительные работы | EH30: 0 | EJ30: 1 | EK30: 22 | EL30: ТСН-2001.3-17. Водопровод и канализация - внутренние устройства | EM30: ТСН-2001.3-17-1 | EO30: Поправка: Гл.12.Прил.8.п.8. 3_12.00.01.11.001 Поправка: Гл.6.Прил.2.2.п.2.2.6_06.00.01.07.001 Поправка: Гл.6.Прил.2.2.п.2.2.16_06.00.01.35.006 | EQ30: 1024 | ER30: 2306.6 | ES30: 2202.04 | ET30: 8.97 | EU30: 1.01 | EV30: 95.59 | EW30: 8.58 | EX30: 0 | EY30: 0 | FQ30: 0 | FR30: 0 | FS30: 0 | FX30: 109 | FY30: 61 | GD30: 1 | GF30: 2024075346 | GG30: 2 | GH30: 1 | GI30: 2 | GJ30: 0 | GK30: 0 | GL30: =ROUND(IF(AND(BH30=3,BI30=3,FS30<>0),P30,0),2) -> 0 | GM30: =ROUND(O30+X30+Y30,2)+GX30 -> 31.18 | GN30: =IF(OR(BI30=0,BI30=1),GM30-GX30,0) -> 31.18 | GO30: =IF(BI30=2,GM30-GX30,0) -> 0 | GP30: =IF(BI30=4,GM30-GX30,0) -> 0 | GR30: 0 | GS30: 3 | GT30: 0 | GV30: =ROUND((GT30),6) -> 0 | GW30: 1 | GX30: =ROUND(HC30*I30,2) -> 0 | HA30: 0 | HB30: 0 | HC30: =GV30*GW30 -> 0 | HS30: 0 | IK30: 0
A31: 17 | B31: 1 | C31: =ROW(SmtRes!A24) -> 24 | D31: =ROW(EtalonRes!A28) -> 28 | F31: 3.17-2-13 | G31: Установка гарнитуры туалетной: вешалок, подстаканников, дозаторов настенных и т.п. / демонтаж зеркала и крючка для костылей | H31: 100 шт. | I31: =ROUND((1+1)/100,9) -> 0.02 | J31: 0 | K31: =ROUND((1+1)/100,9) -> 0.02 | O31: =ROUND(CP31,2) -> 116.57 | P31: =ROUND((ROUND((AC31*AW31*I31),2)*BC31),2) -> 18.76 | Q31: =(ROUND((ROUND((((((ET31*1.2)*1.25)*0.6))*AV31*I31),2)*BB31),2)+ROUND((ROUND(((AE31-((((EU31*1.2)*1.25)*0.6)))*AV31*I31),2)*BS31),2)) -> 2.58 | R31: =(ROUND((ROUND((((((EU31*1.2)*1.25)*0.6))*AV31*I31),2)*BS31),2)+ROUND((ROUND(((AE31-((((EU31*1.2)*1.25)*0.6)))*AV31*I31),2)*BS31),2)) -> 1.13 | S31: =ROUND((ROUND((AF31*AV31*I31),2)*BA31),2) -> 95.23 | T31: =ROUND(CU31*I31,2) -> 0 | U31: =CV31*I31 -> 0.15160448 | V31: =CW31*I31 -> 0 | W31: =ROUND(CX31*I31,2) -> 0 | X31: =(ROUND((((S31+ROUND((ROUND((((((EU31*1.2)*1.25)*0.6))*AV31*I31),2)*BS31),2))*AT31)/100),2)+ROUND(((ROUND((ROUND(((AE31-((((EU31*1.2)*1.25)*0.6)))*AV31*I31),2)*BS31),2)*AT31)/100),2)) -> 105.03 | Y31: =(ROUND((((S31+ROUND((ROUND((((((EU31*1.2)*1.25)*0.6))*AV31*I31),2)*BS31),2))*AU31)/100),2)+ROUND(((ROUND((ROUND(((AE31-((((EU31*1.2)*1.25)*0.6)))*AV31*I31),2)*BS31),2)*AU31)/100),2)) -> 58.78 | AA31: -1 | AB31: =ROUND((AC31+AD31+AF31),6) -> 1408.4455 | AC31: =ROUND(((((ES31*1)*1)*0.6)),6) -> 1321.224 | AD31: =ROUND(((((((ET31*1.2)*1.25)*0.6))-((((EU31*1.2)*1.25)*0.6)))+AE31),6) -> 8.073 | AE31: =ROUND(((((EU31*1.2)*1.25)*0.6)),6) -> 0.909 | AF31: =ROUND(((((EV31*1.2)*1.15)*0.6)),6) -> 79.14852 | AG31: =ROUND((AP31),6) -> 0 | AH31: =((((EW31*1.2)*1.15)*0.6)) -> 7.10424 | AI31: =((((EX31*1.2)*1.25)*0.6)) -> 0 | AJ31: =(AS31) -> 0 | AK31: 2306.6 | AL31: 2202.04 | AM31: 8.97 | AN31: 1.01 | AO31: 95.59 | AP31: 0 | AQ31: 8.58 | AR31: 0 | AS31: 0 | AT31: 109 | AU31: 61 | AV31: 1.067 | AW31: 1 | AZ31: 1 | BA31: 56.35 | BB31: 15.15 | BC31: 0.71 | BH31: 0 | BI31: 1 | BJ31: ТСН-2001.3 Доп. 80, Сб. 17, т. 2, поз. 13 | BM31: 22 | BN31: 0 | BO31: 3.17-2-13 | BP31: 1 | BQ31: 30 | BR31: 0 | BS31: 56.35 | BT31: 1 | BU31: 1 | BV31: 1 | BW31: 1 | BX31: 1 | BZ31: 109 | CA31: 61 | CE31: 1566 | CF31: 0 | CG31: 0 | CM31: 0 | CN31: Поправка: Гл.12.Прил.8.п.8. 3_12.00.01.11.001 Наименование: При наличии напряженных и стесненных условий производства работ (стесненность, сложность складирования и транспортной логистики и т.п.) для объектов, расположенных в пределах круговой магистральной системы улиц "Садовое кольцо" города Москвы Поправка: Гл.6.Прил.2.2.п.2.2.6_06.00.01.07.001 Наименование: При выполнении при капитальном ремонте и реконструкции работ, аналогичных технологическим процессам, характерным для нового строительства, и отсутствующих в сборниках на ремонтно-строительные работы ТСН-2001.6 Поправка: Гл.6.Прил.2.2.п.2.2.16_06.00.01.35.006 Наименование: При демонтаже металлических конструкций (в т.ч. к стоимости вспомогательных материалов) | CO31: 0 | CP31: =(P31+Q31+S31) -> 116.57 | CQ31: =ROUND((ROUND((AC31*AW31*1),2)*BC31),2) -> 938.07 | CR31: =(ROUND((ROUND((((((ET31*1.2)*1.25)*0.6))*AV31*1),2)*BB31),2)+ROUND((ROUND(((AE31-((((EU31*1.2)*1.25)*0.6)))*AV31*1),2)*BS31),2)) -> 130.44 | CS31: =(ROUND((ROUND((((((EU31*1.2)*1.25)*0.6))*AV31*1),2)*BS31),2)+ROUND((ROUND(((AE31-((((EU31*1.2)*1.25)*0.6)))*AV31*1),2)*BS31),2)) -> 54.66 | CT31: =ROUND((ROUND((AF31*AV31*1),2)*BA31),2) -> 4758.76 | CU31: =AG31 -> 0 | CV31: =(AH31*AV31) -> 7.5802241 | CW31: =AI31 -> 0 | CX31: =AJ31 -> 0 | CY31: =(ROUND((((S31+ROUND((ROUND((((((EU31*1.2)*1.25)*0.6))*AV31*1),2)*BS31),2))*AT31)/100),2)+ROUND(((ROUND((ROUND(((AE31-((((EU31*1.2)*1.25)*0.6)))*AV31*1),2)*BS31),2)*AT31)/100),2)) -> 163.38 | CZ31: =(ROUND((((S31+ROUND((ROUND((((((EU31*1.2)*1.25)*0.6))*AV31*1),2)*BS31),2))*AU31)/100),2)+ROUND(((ROUND((ROUND(((AE31-((((EU31*1.2)*1.25)*0.6)))*AV31*1),2)*BS31),2)*AU31)/100),2)) -> 91.43 | DB31: 10 | DD31: *1)*1)*0,6 | DE31: *1,2)*1,25)*0,6 | DF31: *1,2)*1,25)*0,6 | DG31: *1,2)*1,15)*0,6 | DI31: *1,2)*1,15)*0,6 | DJ31: *1,2)*1,25)*0,6 | DN31: 0 | DO31: 0 | DP31: 1 | DQ31: 1 | DU31: 1010 | DV31: 100 шт. | DW31: 100 шт. | DX31: 100 | EE31: 55393925 | EF31: 30 | EG31: Строительные работы | EH31: 0 | EJ31: 1 | EK31: 22 | EL31: ТСН-2001.3-17. Водопровод и канализация - внутренние устройства | EM31: ТСН-2001.3-17-1 | EO31: Поправка: Гл.12.Прил.8.п.8. 3_12.00.01.11.001 Поправка: Гл.6.Прил.2.2.п.2.2.6_06.00.01.07.001 Поправка: Гл.6.Прил.2.2.п.2.2.16_06.00.01.35.006 | EQ31: 1024 | ER31: 2306.6 | ES31: 2202.04 | ET31: 8.97 | EU31: 1.01 | EV31: 95.59 | EW31: 8.58 | EX31: 0 | EY31: 0 | FQ31: 0 | FR31: 0 | FS31: 0 | FX31: 109 | FY31: 61 | GD31: 1 | GF31: 2024075346 | GG31: 2 | GH31: 1 | GI31: 2 | GJ31: 0 | GK31: 0 | GL31: =ROUND(IF(AND(BH31=3,BI31=3,FS31<>0),P31,0),2) -> 0 | GM31: =ROUND(O31+X31+Y31,2)+GX31 -> 280.38 | GN31: =IF(OR(BI31=0,BI31=1),GM31-GX31,0) -> 280.38 | GO31: =IF(BI31=2,GM31-GX31,0) -> 0 | GP31: =IF(BI31=4,GM31-GX31,0) -> 0 | GR31: 0 | GS31: 3 | GT31: 0 | GV31: =ROUND((GT31),6) -> 0 | GW31: 1 | GX31: =ROUND(HC31*I31,2) -> 0 | HA31: 0 | HB31: 0 | HC31: =GV31*GW31 -> 0 | HS31: 0 | IK31: 0
A32: 17 | B32: 1 | C32: =ROW(SmtRes!A26) -> 26 | D32: =ROW(EtalonRes!A31) -> 31 | F32: 3.70-61-2 | G32: Установка номерных табличек для этажа, подъезда / демонтаж знака "Туалет для инвалидов" | H32: 1 ШТ. | I32: 1 | J32: 0 | K32: 1 | O32: =ROUND(CP32,2) -> 9.35 | P32: =ROUND((ROUND((AC32*AW32*I32),2)*BC32),2) -> 0 | Q32: =(ROUND((ROUND((((((ET32*1.25)*1.2)*0.8))*AV32*I32),2)*BB32),2)+ROUND((ROUND(((AE32-((((EU32*1.25)*1.2)*0.8)))*AV32*I32),2)*BS32),2)) -> 0 | R32: =(ROUND((ROUND((((((EU32*1.25)*1.2)*0.8))*AV32*I32),2)*BS32),2)+ROUND((ROUND(((AE32-((((EU32*1.25)*1.2)*0.8)))*AV32*I32),2)*BS32),2)) -> 0 | S32: =ROUND((ROUND((AF32*AV32*I32),2)*BA32),2) -> 9.35 | T32: =ROUND(CU32*I32,2) -> 0 | U32: =CV32*I32 -> 0.62402496 | V32: =CW32*I32 -> 0 | W32: =ROUND(CX32*I32,2) -> 0 | X32: =(ROUND((((S32+ROUND((ROUND((((((EU32*1.25)*1.2)*0.8))*AV32*I32),2)*BS32),2))*AT32)/100),2)+ROUND(((ROUND((ROUND(((AE32-((((EU32*1.25)*1.2)*0.8)))*AV32*I32),2)*BS32),2)*AT32)/100),2)) -> 7.85 | Y32: =(ROUND((((S32+ROUND((ROUND((((((EU32*1.25)*1.2)*0.8))*AV32*I32),2)*BS32),2))*AU32)/100),2)+ROUND(((ROUND((ROUND(((AE32-((((EU32*1.25)*1.2)*0.8)))*AV32*I32),2)*BS32),2)*AU32)/100),2)) -> 4.96 | AA32: -1 | AB32: =ROUND((AC32+AD32+AF32),6) -> 8.60016 | AC32: =ROUND(((((ES32*1)*1)*0)),6) -> 0 | AD32: =ROUND(((((((ET32*1.25)*1.2)*0.8))-((((EU32*1.25)*1.2)*0.8)))+AE32),6) -> 0 | AE32: =ROUND(((((EU32*1.25)*1.2)*0.8)),6) -> 0 | AF32: =ROUND(((((EV32*1.15)*1.2)*0.8)),6) -> 8.60016 | AG32: =ROUND((AP32),6) -> 0 | AH32: =((((EW32*1.15)*1.2)*0.8)) -> 0.57408 | AI32: =((((EX32*1.25)*1.2)*0.8)) -> 0 | AJ32: =(AS32) -> 0 | AK32: 8.29 | AL32: 0.5 | AM32: 0 | AN32: 0 | AO32: 7.79 | AP32: 0 | AQ32: 0.52 | AR32: 0 | AS32: 0 | AT32: 84 | AU32: 53 | AV32: 1.087 | AW32: 1 | AZ32: 1 | BA32: 1 | BB32: 1 | BC32: 1 | BH32: 0 | BI32: 1 | BJ32: ТСН-2001.3 Доп. 78, Сб. 70, т. 61, поз. 2 | BM32: 55 | BN32: 0 | BO32: 3.70-61-2 | BP32: 1 | BQ32: 30 | BR32: 0 | BS32: 1 | BT32: 1 | BU32: 1 | BV32: 1 | BW32: 1 | BX32: 1 | BZ32: 84 | CA32: 53 | CE32: 1566 | CF32: 0 | CG32: 0 | CM32: 0 | CN32: Поправка: Гл.6.Прил.2.2.п.2.2.6_06.00.01.07.001 Наименование: При выполнении при капитальном ремонте и реконструкции работ, аналогичных технологическим процессам, характерным для нового строительства, и отсутствующих в сборниках на ремонтно-строительные работы ТСН-2001.6 Поправка: Гл.12.Прил.8.п.8. 3_12.00.01.11.001 Наименование: При наличии напряженных и стесненных условий производства работ (стесненность, сложность складирования и транспортной логистики и т.п.) для объектов, расположенных в пределах круговой магистральной системы улиц "Садовое кольцо" города Москвы Поправка: Гл.6.Прил.2.2.п.2.2.12_06.00.01.35.002 Наименование: При демонтаже сборных деревянных и пластмассовых конструкций | CO32: 0 | CP32: =(P32+Q32+S32) -> 9.35 | CQ32: =ROUND((ROUND((AC32*AW32*1),2)*BC32),2) -> 0 | CR32: =(ROUND((ROUND((((((ET32*1.25)*1.2)*0.8))*AV32*1),2)*BB32),2)+ROUND((ROUND(((AE32-((((EU32*1.25)*1.2)*0.8)))*AV32*1),2)*BS32),2)) -> 0 | CS32: =(ROUND((ROUND((((((EU32*1.25)*1.2)*0.8))*AV32*1),2)*BS32),2)+ROUND((ROUND(((AE32-((((EU32*1.25)*1.2)*0.8)))*AV32*1),2)*BS32),2)) -> 0 | CT32: =ROUND((ROUND((AF32*AV32*1),2)*BA32),2) -> 9.35 | CU32: =AG32 -> 0 | CV32: =(AH32*AV32) -> 0.62402496 | CW32: =AI32 -> 0 | CX32: =AJ32 -> 0 | CY32: =(ROUND((((S32+ROUND((ROUND((((((EU32*1.25)*1.2)*0.8))*AV32*1),2)*BS32),2))*AT32)/100),2)+ROUND(((ROUND((ROUND(((AE32-((((EU32*1.25)*1.2)*0.8)))*AV32*1),2)*BS32),2)*AT32)/100),2)) -> 7.85 | CZ32: =(ROUND((((S32+ROUND((ROUND((((((EU32*1.25)*1.2)*0.8))*AV32*1),2)*BS32),2))*AU32)/100),2)+ROUND(((ROUND((ROUND(((AE32-((((EU32*1.25)*1.2)*0.8)))*AV32*1),2)*BS32),2)*AU32)/100),2)) -> 4.96 | DB32: 13 | DD32: *1)*1)*0 | DE32: *1,25)*1,2)*0,8 | DF32: *1,25)*1,2)*0,8 | DG32: *1,15)*1,2)*0,8 | DI32: *1,15)*1,2)*0,8 | DJ32: *1,25)*1,2)*0,8 | DN32: 0 | DO32: 0 | DP32: 1 | DQ32: 1 | DU32: 1013 | DV32: 1 ШТ. | DW32: 1 ШТ. | DX32: 1 | EE32: 55393960 | EF32: 30 | EG32: Строительные работы | EH32: 0 | EJ32: 1 | EK32: 55 | EL32: ТСН-2001.3-70. Металлические конструкции | EM32: ТСН-2001.3-70-4 | EO32: Поправка: Гл.6.Прил.2.2.п.2.2.6_06.00.01.07.001 Поправка: Гл.12.Прил.8.п.8. 3_12.00.01.11.001 Поправка: Гл.6.Прил.2.2.п.2.2.12_06.00.01.35.002 | EQ32: 1024 | ER32: 8.29 | ES32: 0.5 | ET32: 0 | EU32: 0 | EV32: 7.79 | EW32: 0.52 | EX32: 0 | EY32: 0 | FQ32: 0 | FR32: 0 | FS32: 0 | FX32: 84 | FY32: 53 | GD32: 1 | GF32: 596051590 | GG32: 2 | GH32: 1 | GI32: 2 | GJ32: 0 | GK32: 0 | GL32: =ROUND(IF(AND(BH32=3,BI32=3,FS32<>0),P32,0),2) -> 0 | GM32: =ROUND(O32+X32+Y32,2)+GX32 -> 22.16 | GN32: =IF(OR(BI32=0,BI32=1),GM32-GX32,0) -> 22.16 | GO32: =IF(BI32=2,GM32-GX32,0) -> 0 | GP32: =IF(BI32=4,GM32-GX32,0) -> 0 | GR32: 0 | GS32: 3 | GT32: 0 | GV32: =ROUND((GT32),6) -> 0 | GW32: 1 | GX32: =ROUND(HC32*I32,2) -> 0 | HA32: 0 | HB32: 0 | HC32: =GV32*GW32 -> 0 | HS32: 0 | IK32: 0
A33: 17 | B33: 1 | C33: =ROW(SmtRes!A28) -> 28 | D33: =ROW(EtalonRes!A34) -> 34 | F33: 3.70-61-2 | G33: Установка номерных табличек для этажа, подъезда / демонтаж знака "Туалет для инвалидов" | H33: 1 ШТ. | I33: 1 | J33: 0 | K33: 1 | O33: =ROUND(CP33,2) -> 526.87 | P33: =ROUND((ROUND((AC33*AW33*I33),2)*BC33),2) -> 0 | Q33: =(ROUND((ROUND((((((ET33*1.25)*1.2)*0.8))*AV33*I33),2)*BB33),2)+ROUND((ROUND(((AE33-((((EU33*1.25)*1.2)*0.8)))*AV33*I33),2)*BS33),2)) -> 0 | R33: =(ROUND((ROUND((((((EU33*1.25)*1.2)*0.8))*AV33*I33),2)*BS33),2)+ROUND((ROUND(((AE33-((((EU33*1.25)*1.2)*0.8)))*AV33*I33),2)*BS33),2)) -> 0 | S33: =ROUND((ROUND((AF33*AV33*I33),2)*BA33),2) -> 526.87 | T33: =ROUND(CU33*I33,2) -> 0 | U33: =CV33*I33 -> 0.62402496 | V33: =CW33*I33 -> 0 | W33: =ROUND(CX33*I33,2) -> 0 | X33: =(ROUND((((S33+ROUND((ROUND((((((EU33*1.25)*1.2)*0.8))*AV33*I33),2)*BS33),2))*AT33)/100),2)+ROUND(((ROUND((ROUND(((AE33-((((EU33*1.25)*1.2)*0.8)))*AV33*I33),2)*BS33),2)*AT33)/100),2)) -> 442.57 | Y33: =(ROUND((((S33+ROUND((ROUND((((((EU33*1.25)*1.2)*0.8))*AV33*I33),2)*BS33),2))*AU33)/100),2)+ROUND(((ROUND((ROUND(((AE33-((((EU33*1.25)*1.2)*0.8)))*AV33*I33),2)*BS33),2)*AU33)/100),2)) -> 279.24 | AA33: -1 | AB33: =ROUND((AC33+AD33+AF33),6) -> 8.60016 | AC33: =ROUND(((((ES33*1)*1)*0)),6) -> 0 | AD33: =ROUND(((((((ET33*1.25)*1.2)*0.8))-((((EU33*1.25)*1.2)*0.8)))+AE33),6) -> 0 | AE33: =ROUND(((((EU33*1.25)*1.2)*0.8)),6) -> 0 | AF33: =ROUND(((((EV33*1.15)*1.2)*0.8)),6) -> 8.60016 | AG33: =ROUND((AP33),6) -> 0 | AH33: =((((EW33*1.15)*1.2)*0.8)) -> 0.57408 | AI33: =((((EX33*1.25)*1.2)*0.8)) -> 0 | AJ33: =(AS33) -> 0 | AK33: 8.29 | AL33: 0.5 | AM33: 0 | AN33: 0 | AO33: 7.79 | AP33: 0 | AQ33: 0.52 | AR33: 0 | AS33: 0 | AT33: 84 | AU33: 53 | AV33: 1.087 | AW33: 1 | AZ33: 1 | BA33: 56.35 | BB33: 1 | BC33: 16.42 | BH33: 0 | BI33: 1 | BJ33: ТСН-2001.3 Доп. 78, Сб. 70, т. 61, поз. 2 | BM33: 55 | BN33: 0 | BO33: 3.70-61-2 | BP33: 1 | BQ33: 30 | BR33: 0 | BS33: 56.35 | BT33: 1 | BU33: 1 | BV33: 1 | BW33: 1 | BX33: 1 | BZ33: 84 | CA33: 53 | CE33: 1566 | CF33: 0 | CG33: 0 | CM33: 0 | CN33: Поправка: Гл.6.Прил.2.2.п.2.2.6_06.00.01.07.001 Наименование: При выполнении при капитальном ремонте и реконструкции работ, аналогичных технологическим процессам, характерным для нового строительства, и отсутствующих в сборниках на ремонтно-строительные работы ТСН-2001.6 Поправка: Гл.12.Прил.8.п.8. 3_12.00.01.11.001 Наименование: При наличии напряженных и стесненных условий производства работ (стесненность, сложность складирования и транспортной логистики и т.п.) для объектов, расположенных в пределах круговой магистральной системы улиц "Садовое кольцо" города Москвы Поправка: Гл.6.Прил.2.2.п.2.2.12_06.00.01.35.002 Наименование: При демонтаже сборных деревянных и пластмассовых конструкций | CO33: 0 | CP33: =(P33+Q33+S33) -> 526.87 | CQ33: =ROUND((ROUND((AC33*AW33*1),2)*BC33),2) -> 0 | CR33: =(ROUND((ROUND((((((ET33*1.25)*1.2)*0.8))*AV33*1),2)*BB33),2)+ROUND((ROUND(((AE33-((((EU33*1.25)*1.2)*0.8)))*AV33*1),2)*BS33),2)) -> 0 | CS33: =(ROUND((ROUND((((((EU33*1.25)*1.2)*0.8))*AV33*1),2)*BS33),2)+ROUND((ROUND(((AE33-((((EU33*1.25)*1.2)*0.8)))*AV33*1),2)*BS33),2)) -> 0 | CT33: =ROUND((ROUND((AF33*AV33*1),2)*BA33),2) -> 526.87 | CU33: =AG33 -> 0 | CV33: =(AH33*AV33) -> 0.62402496 | CW33: =AI33 -> 0 | CX33: =AJ33 -> 0 | CY33: =(ROUND((((S33+ROUND((ROUND((((((EU33*1.25)*1.2)*0.8))*AV33*1),2)*BS33),2))*AT33)/100),2)+ROUND(((ROUND((ROUND(((AE33-((((EU33*1.25)*1.2)*0.8)))*AV33*1),2)*BS33),2)*AT33)/100),2)) -> 442.57 | CZ33: =(ROUND((((S33+ROUND((ROUND((((((EU33*1.25)*1.2)*0.8))*AV33*1),2)*BS33),2))*AU33)/100),2)+ROUND(((ROUND((ROUND(((AE33-((((EU33*1.25)*1.2)*0.8)))*AV33*1),2)*BS33),2)*AU33)/100),2)) -> 279.24 | DB33: 16 | DD33: *1)*1)*0 | DE33: *1,25)*1,2)*0,8 | DF33: *1,25)*1,2)*0,8 | DG33: *1,15)*1,2)*0,8 | DI33: *1,15)*1,2)*0,8 | DJ33: *1,25)*1,2)*0,8 | DN33: 0 | DO33: 0 | DP33: 1 | DQ33: 1 | DU33: 1013 | DV33: 1 ШТ. | DW33: 1 ШТ. | DX33: 1 | EE33: 55393960 | EF33: 30 | EG33: Строительные работы | EH33: 0 | EJ33: 1 | EK33: 55 | EL33: ТСН-2001.3-70. Металлические конструкции | EM33: ТСН-2001.3-70-4 | EO33: Поправка: Гл.6.Прил.2.2.п.2.2.6_06.00.01.07.001 Поправка: Гл.12.Прил.8.п.8. 3_12.00.01.11.001 Поправка: Гл.6.Прил.2.2.п.2.2.12_06.00.01.35.002 | EQ33: 1024 | ER33: 8.29 | ES33: 0.5 | ET33: 0 | EU33: 0 | EV33: 7.79 | EW33: 0.52 | EX33: 0 | EY33: 0 | FQ33: 0 | FR33: 0 | FS33: 0 | FX33: 84 | FY33: 53 | GD33: 1 | GF33: 596051590 | GG33: 2 | GH33: 1 | GI33: 2 | GJ33: 0 | GK33: 0 | GL33: =ROUND(IF(AND(BH33=3,BI33=3,FS33<>0),P33,0),2) -> 0 | GM33: =ROUND(O33+X33+Y33,2)+GX33 -> 1248.68 | GN33: =IF(OR(BI33=0,BI33=1),GM33-GX33,0) -> 1248.68 | GO33: =IF(BI33=2,GM33-GX33,0) -> 0 | GP33: =IF(BI33=4,GM33-GX33,0) -> 0 | GR33: 0 | GS33: 3 | GT33: 0 | GV33: =ROUND((GT33),6) -> 0 | GW33: 1 | GX33: =ROUND(HC33*I33,2) -> 0 | HA33: 0 | HB33: 0 | HC33: =GV33*GW33 -> 0 | HS33: 0 | IK33: 0
A34: 17 | B34: 1 | C34: =ROW(SmtRes!A30) -> 30 | D34: =ROW(EtalonRes!A37) -> 37 | F34: 3.70-61-2 | G34: Установка номерных табличек для этажа, подъезда / демонтаж информационных табличек | H34: 1 ШТ. | I34: =ROUND(2+2+1+1+1+1+1+1+2+1+1+1+3,9) -> 18 | J34: 0 | K34: =ROUND(2+2+1+1+1+1+1+1+2+1+1+1+3,9) -> 18 | O34: =ROUND(CP34,2) -> 168.27 | P34: =ROUND((ROUND((AC34*AW34*I34),2)*BC34),2) -> 0 | Q34: =(ROUND((ROUND((((((ET34*1.25)*1.2)*0.8))*AV34*I34),2)*BB34),2)+ROUND((ROUND(((AE34-((((EU34*1.25)*1.2)*0.8)))*AV34*I34),2)*BS34),2)) -> 0 | R34: =(ROUND((ROUND((((((EU34*1.25)*1.2)*0.8))*AV34*I34),2)*BS34),2)+ROUND((ROUND(((AE34-((((EU34*1.25)*1.2)*0.8)))*AV34*I34),2)*BS34),2)) -> 0 | S34: =ROUND((ROUND((AF34*AV34*I34),2)*BA34),2) -> 168.27 | T34: =ROUND(CU34*I34,2) -> 0 | U34: =CV34*I34 -> 11.232449 | V34: =CW34*I34 -> 0 | W34: =ROUND(CX34*I34,2) -> 0 | X34: =(ROUND((((S34+ROUND((ROUND((((((EU34*1.25)*1.2)*0.8))*AV34*I34),2)*BS34),2))*AT34)/100),2)+ROUND(((ROUND((ROUND(((AE34-((((EU34*1.25)*1.2)*0.8)))*AV34*I34),2)*BS34),2)*AT34)/100),2)) -> 141.35 | Y34: =(ROUND((((S34+ROUND((ROUND((((((EU34*1.25)*1.2)*0.8))*AV34*I34),2)*BS34),2))*AU34)/100),2)+ROUND(((ROUND((ROUND(((AE34-((((EU34*1.25)*1.2)*0.8)))*AV34*I34),2)*BS34),2)*AU34)/100),2)) -> 89.18 | AA34: -1 | AB34: =ROUND((AC34+AD34+AF34),6) -> 8.60016 | AC34: =ROUND(((((ES34*1)*1)*0)),6) -> 0 | AD34: =ROUND(((((((ET34*1.25)*1.2)*0.8))-((((EU34*1.25)*1.2)*0.8)))+AE34),6) -> 0 | AE34: =ROUND(((((EU34*1.25)*1.2)*0.8)),6) -> 0 | AF34: =ROUND(((((EV34*1.15)*1.2)*0.8)),6) -> 8.60016 | AG34: =ROUND((AP34),6) -> 0 | AH34: =((((EW34*1.15)*1.2)*0.8)) -> 0.57408 | AI34: =((((EX34*1.25)*1.2)*0.8)) -> 0 | AJ34: =(AS34) -> 0 | AK34: 8.29 | AL34: 0.5 | AM34: 0 | AN34: 0 | AO34: 7.79 | AP34: 0 | AQ34: 0.52 | AR34: 0 | AS34: 0 | AT34: 84 | AU34: 53 | AV34: 1.087 | AW34: 1 | AZ34: 1 | BA34: 1 | BB34: 1 | BC34: 1 | BH34: 0 | BI34: 1 | BJ34: ТСН-2001.3 Доп. 78, Сб. 70, т. 61, поз. 2 | BM34: 55 | BN34: 0 | BO34: 3.70-61-2 | BP34: 1 | BQ34: 30 | BR34: 0 | BS34: 1 | BT34: 1 | BU34: 1 | BV34: 1 | BW34: 1 | BX34: 1 | BZ34: 84 | CA34: 53 | CE34: 1566 | CF34: 0 | CG34: 0 | CM34: 0 | CN34: Поправка: Гл.6.Прил.2.2.п.2.2.6_06.00.01.07.001 Наименование: При выполнении при капитальном ремонте и реконструкции работ, аналогичных технологическим процессам, характерным для нового строительства, и отсутствующих в сборниках на ремонтно-строительные работы ТСН-2001.6 Поправка: Гл.12.Прил.8.п.8. 3_12.00.01.11.001 Наименование: При наличии напряженных и стесненных условий производства работ (стесненность, сложность складирования и транспортной логистики и т.п.) для объектов, расположенных в пределах круговой магистральной системы улиц "Садовое кольцо" города Москвы Поправка: Гл.6.Прил.2.2.п.2.2.12_06.00.01.35.002 Наименование: При демонтаже сборных деревянных и пластмассовых конструкций | CO34: 0 | CP34: =(P34+Q34+S34) -> 168.27 | CQ34: =ROUND((ROUND((AC34*AW34*1),2)*BC34),2) -> 0 | CR34: =(ROUND((ROUND((((((ET34*1.25)*1.2)*0.8))*AV34*1),2)*BB34),2)+ROUND((ROUND(((AE34-((((EU34*1.25)*1.2)*0.8)))*AV34*1),2)*BS34),2)) -> 0 | CS34: =(ROUND((ROUND((((((EU34*1.25)*1.2)*0.8))*AV34*1),2)*BS34),2)+ROUND((ROUND(((AE34-((((EU34*1.25)*1.2)*0.8)))*AV34*1),2)*BS34),2)) -> 0 | CT34: =ROUND((ROUND((AF34*AV34*1),2)*BA34),2) -> 9.35 | CU34: =AG34 -> 0 | CV34: =(AH34*AV34) -> 0.62402496 | CW34: =AI34 -> 0 | CX34: =AJ34 -> 0 | CY34: =(ROUND((((S34+ROUND((ROUND((((((EU34*1.25)*1.2)*0.8))*AV34*1),2)*BS34),2))*AT34)/100),2)+ROUND(((ROUND((ROUND(((AE34-((((EU34*1.25)*1.2)*0.8)))*AV34*1),2)*BS34),2)*AT34)/100),2)) -> 141.35 | CZ34: =(ROUND((((S34+ROUND((ROUND((((((EU34*1.25)*1.2)*0.8))*AV34*1),2)*BS34),2))*AU34)/100),2)+ROUND(((ROUND((ROUND(((AE34-((((EU34*1.25)*1.2)*0.8)))*AV34*1),2)*BS34),2)*AU34)/100),2)) -> 89.18 | DB34: 19 | DD34: *1)*1)*0 | DE34: *1,25)*1,2)*0,8 | DF34: *1,25)*1,2)*0,8 | DG34: *1,15)*1,2)*0,8 | DI34: *1,15)*1,2)*0,8 | DJ34: *1,25)*1,2)*0,8 | DN34: 0 | DO34: 0 | DP34: 1 | DQ34: 1 | DU34: 1013 | DV34: 1 ШТ. | DW34: 1 ШТ. | DX34: 1 | EE34: 55393960 | EF34: 30 | EG34: Строительные работы | EH34: 0 | EJ34: 1 | EK34: 55 | EL34: ТСН-2001.3-70. Металлические конструкции | EM34: ТСН-2001.3-70-4 | EO34: Поправка: Гл.6.Прил.2.2.п.2.2.6_06.00.01.07.001 Поправка: Гл.12.Прил.8.п.8. 3_12.00.01.11.001 Поправка: Гл.6.Прил.2.2.п.2.2.12_06.00.01.35.002 | EQ34: 1024 | ER34: 8.29 | ES34: 0.5 | ET34: 0 | EU34: 0 | EV34: 7.79 | EW34: 0.52 | EX34: 0 | EY34: 0 | FQ34: 0 | FR34: 0 | FS34: 0 | FX34: 84 | FY34: 53 | GD34: 1 | GF34: -349157379 | GG34: 2 | GH34: 1 | GI34: 2 | GJ34: 0 | GK34: 0 | GL34: =ROUND(IF(AND(BH34=3,BI34=3,FS34<>0),P34,0),2) -> 0 | GM34: =ROUND(O34+X34+Y34,2)+GX34 -> 398.8 | GN34: =IF(OR(BI34=0,BI34=1),GM34-GX34,0) -> 398.8 | GO34: =IF(BI34=2,GM34-GX34,0) -> 0 | GP34: =IF(BI34=4,GM34-GX34,0) -> 0 | GR34: 0 | GS34: 3 | GT34: 0 | GV34: =ROUND((GT34),6) -> 0 | GW34: 1 | GX34: =ROUND(HC34*I34,2) -> 0 | HA34: 0 | HB34: 0 | HC34: =GV34*GW34 -> 0 | HS34: 0 | IK34: 0
A35: 17 | B35: 1 | C35: =ROW(SmtRes!A32) -> 32 | D35: =ROW(EtalonRes!A40) -> 40 | F35: 3.70-61-2 | G35: Установка номерных табличек для этажа, подъезда / демонтаж информационных табличек | H35: 1 ШТ. | I35: =ROUND(2+2+1+1+1+1+1+1+2+1+1+1+3,9) -> 18 | J35: 0 | K35: =ROUND(2+2+1+1+1+1+1+1+2+1+1+1+3,9) -> 18 | O35: =ROUND(CP35,2) -> 9482.01 | P35: =ROUND((ROUND((AC35*AW35*I35),2)*BC35),2) -> 0 | Q35: =(ROUND((ROUND((((((ET35*1.25)*1.2)*0.8))*AV35*I35),2)*BB35),2)+ROUND((ROUND(((AE35-((((EU35*1.25)*1.2)*0.8)))*AV35*I35),2)*BS35),2)) -> 0 | R35: =(ROUND((ROUND((((((EU35*1.25)*1.2)*0.8))*AV35*I35),2)*BS35),2)+ROUND((ROUND(((AE35-((((EU35*1.25)*1.2)*0.8)))*AV35*I35),2)*BS35),2)) -> 0 | S35: =ROUND((ROUND((AF35*AV35*I35),2)*BA35),2) -> 9482.01 | T35: =ROUND(CU35*I35,2) -> 0 | U35: =CV35*I35 -> 11.232449 | V35: =CW35*I35 -> 0 | W35: =ROUND(CX35*I35,2) -> 0 | X35: =(ROUND((((S35+ROUND((ROUND((((((EU35*1.25)*1.2)*0.8))*AV35*I35),2)*BS35),2))*AT35)/100),2)+ROUND(((ROUND((ROUND(((AE35-((((EU35*1.25)*1.2)*0.8)))*AV35*I35),2)*BS35),2)*AT35)/100),2)) -> 7964.89 | Y35: =(ROUND((((S35+ROUND((ROUND((((((EU35*1.25)*1.2)*0.8))*AV35*I35),2)*BS35),2))*AU35)/100),2)+ROUND(((ROUND((ROUND(((AE35-((((EU35*1.25)*1.2)*0.8)))*AV35*I35),2)*BS35),2)*AU35)/100),2)) -> 5025.47 | AA35: -1 | AB35: =ROUND((AC35+AD35+AF35),6) -> 8.60016 | AC35: =ROUND(((((ES35*1)*1)*0)),6) -> 0 | AD35: =ROUND(((((((ET35*1.25)*1.2)*0.8))-((((EU35*1.25)*1.2)*0.8)))+AE35),6) -> 0 | AE35: =ROUND(((((EU35*1.25)*1.2)*0.8)),6) -> 0 | AF35: =ROUND(((((EV35*1.15)*1.2)*0.8)),6) -> 8.60016 | AG35: =ROUND((AP35),6) -> 0 | AH35: =((((EW35*1.15)*1.2)*0.8)) -> 0.57408 | AI35: =((((EX35*1.25)*1.2)*0.8)) -> 0 | AJ35: =(AS35) -> 0 | AK35: 8.29 | AL35: 0.5 | AM35: 0 | AN35: 0 | AO35: 7.79 | AP35: 0 | AQ35: 0.52 | AR35: 0 | AS35: 0 | AT35: 84 | AU35: 53 | AV35: 1.087 | AW35: 1 | AZ35: 1 | BA35: 56.35 | BB35: 1 | BC35: 16.42 | BH35: 0 | BI35: 1 | BJ35: ТСН-2001.3 Доп. 78, Сб. 70, т. 61, поз. 2 | BM35: 55 | BN35: 0 | BO35: 3.70-61-2 | BP35: 1 | BQ35: 30 | BR35: 0 | BS35: 56.35 | BT35: 1 | BU35: 1 | BV35: 1 | BW35: 1 | BX35: 1 | BZ35: 84 | CA35: 53 | CE35: 1566 | CF35: 0 | CG35: 0 | CM35: 0 | CN35: Поправка: Гл.6.Прил.2.2.п.2.2.6_06.00.01.07.001 Наименование: При выполнении при капитальном ремонте и реконструкции работ, аналогичных технологическим процессам, характерным для нового строительства, и отсутствующих в сборниках на ремонтно-строительные работы ТСН-2001.6 Поправка: Гл.12.Прил.8.п.8. 3_12.00.01.11.001 Наименование: При наличии напряженных и стесненных условий производства работ (стесненность, сложность складирования и транспортной логистики и т.п.) для объектов, расположенных в пределах круговой магистральной системы улиц "Садовое кольцо" города Москвы Поправка: Гл.6.Прил.2.2.п.2.2.12_06.00.01.35.002 Наименование: При демонтаже сборных деревянных и пластмассовых конструкций | CO35: 0 | CP35: =(P35+Q35+S35) -> 9482.01 | CQ35: =ROUND((ROUND((AC35*AW35*1),2)*BC35),2) -> 0 | CR35: =(ROUND((ROUND((((((ET35*1.25)*1.2)*0.8))*AV35*1),2)*BB35),2)+ROUND((ROUND(((AE35-((((EU35*1.25)*1.2)*0.8)))*AV35*1),2)*BS35),2)) -> 0 | CS35: =(ROUND((ROUND((((((EU35*1.25)*1.2)*0.8))*AV35*1),2)*BS35),2)+ROUND((ROUND(((AE35-((((EU35*1.25)*1.2)*0.8)))*AV35*1),2)*BS35),2)) -> 0 | CT35: =ROUND((ROUND((AF35*AV35*1),2)*BA35),2) -> 526.87 | CU35: =AG35 -> 0 | CV35: =(AH35*AV35) -> 0.62402496 | CW35: =AI35 -> 0 | CX35: =AJ35 -> 0 | CY35: =(ROUND((((S35+ROUND((ROUND((((((EU35*1.25)*1.2)*0.8))*AV35*1),2)*BS35),2))*AT35)/100),2)+ROUND(((ROUND((ROUND(((AE35-((((EU35*1.25)*1.2)*0.8)))*AV35*1),2)*BS35),2)*AT35)/100),2)) -> 7964.89 | CZ35: =(ROUND((((S35+ROUND((ROUND((((((EU35*1.25)*1.2)*0.8))*AV35*1),2)*BS35),2))*AU35)/100),2)+ROUND(((ROUND((ROUND(((AE35-((((EU35*1.25)*1.2)*0.8)))*AV35*1),2)*BS35),2)*AU35)/100),2)) -> 5025.47 | DB35: 22 | DD35: *1)*1)*0 | DE35: *1,25)*1,2)*0,8 | DF35: *1,25)*1,2)*0,8 | DG35: *1,15)*1,2)*0,8 | DI35: *1,15)*1,2)*0,8 | DJ35: *1,25)*1,2)*0,8 | DN35: 0 | DO35: 0 | DP35: 1 | DQ35: 1 | DU35: 1013 | DV35: 1 ШТ. | DW35: 1 ШТ. | DX35: 1 | EE35: 55393960 | EF35: 30 | EG35: Строительные работы | EH35: 0 | EJ35: 1 | EK35: 55 | EL35: ТСН-2001.3-70. Металлические конструкции | EM35: ТСН-2001.3-70-4 | EO35: Поправка: Гл.6.Прил.2.2.п.2.2.6_06.00.01.07.001 Поправка: Гл.12.Прил.8.п.8. 3_12.00.01.11.001 Поправка: Гл.6.Прил.2.2.п.2.2.12_06.00.01.35.002 | EQ35: 1024 | ER35: 8.29 | ES35: 0.5 | ET35: 0 | EU35: 0 | EV35: 7.79 | EW35: 0.52 | EX35: 0 | EY35: 0 | FQ35: 0 | FR35: 0 | FS35: 0 | FX35: 84 | FY35: 53 | GD35: 1 | GF35: -349157379 | GG35: 2 | GH35: 1 | GI35: 2 | GJ35: 0 | GK35: 0 | GL35: =ROUND(IF(AND(BH35=3,BI35=3,FS35<>0),P35,0),2) -> 0 | GM35: =ROUND(O35+X35+Y35,2)+GX35 -> 22472.37 | GN35: =IF(OR(BI35=0,BI35=1),GM35-GX35,0) -> 22472.37 | GO35: =IF(BI35=2,GM35-GX35,0) -> 0 | GP35: =IF(BI35=4,GM35-GX35,0) -> 0 | GR35: 0 | GS35: 3 | GT35: 0 | GV35: =ROUND((GT35),6) -> 0 | GW35: 1 | GX35: =ROUND(HC35*I35,2) -> 0 | HA35: 0 | HB35: 0 | HC35: =GV35*GW35 -> 0 | HS35: 0 | IK35: 0
A37: 51 | B37: =B24 -> 1 | C37: =A24 -> 4 | D37: =ROW(A24) -> 24 | F37: =IF(F24<>"",F24,"") -> Новый раздел | G37: =IF(G24<>"",G24,"") -> Демонтажные работы (Письмо от АНО «РГТ» об утверждении объёмов демонтажных работ) | H37: 0 | O37: =ROUND(AB37,2) -> 0 | P37: =ROUND(AC37,2) -> 0 | Q37: =ROUND(AD37,2) -> 0 | R37: =ROUND(AE37,2) -> 0 | S37: =ROUND(AF37,2) -> 0 | T37: =ROUND(AG37,2) -> 0 | U37: =AH37 -> 0 | V37: =AI37 -> 0 | W37: =ROUND(AJ37,2) -> 0 | X37: =ROUND(AK37,2) -> 0 | Y37: =ROUND(AL37,2) -> 0 | AB37: =ROUND(SUMIF(AA28:AA35,"=55938214",O28:O35),2) -> 0 | AC37: =ROUND(SUMIF(AA28:AA35,"=55938214",P28:P35),2) -> 0 | AD37: =ROUND(SUMIF(AA28:AA35,"=55938214",Q28:Q35),2) -> 0 | AE37: =ROUND(SUMIF(AA28:AA35,"=55938214",R28:R35),2) -> 0 | AF37: =ROUND(SUMIF(AA28:AA35,"=55938214",S28:S35),2) -> 0 | AG37: =ROUND(SUMIF(AA28:AA35,"=55938214",T28:T35),2) -> 0 | AH37: =SUMIF(AA28:AA35,"=55938214",U28:U35) -> 0 | AI37: =SUMIF(AA28:AA35,"=55938214",V28:V35) -> 0 | AJ37: =ROUND(SUMIF(AA28:AA35,"=55938214",W28:W35),2) -> 0 | AK37: =ROUND(SUMIF(AA28:AA35,"=55938214",X28:X35),2) -> 0 | AL37: =ROUND(SUMIF(AA28:AA35,"=55938214",Y28:Y35),2) -> 0 | AO37: =ROUND(BX37,2) -> 0 | AP37: =ROUND(BY37,2) -> 0 | AQ37: =ROUND(BZ37,2) -> 0 | AR37: =ROUND(CA37,2) -> 0 | AS37: =ROUND(CB37,2) -> 0 | AT37: =ROUND(CC37,2) -> 0 | AU37: =ROUND(CD37,2) -> 0 | AV37: =ROUND(CE37,2) -> 0 | ... BD37: =ROUND(CM37,2) -> 0 | BX37: =ROUND(SUMIF(AA28:AA35,"=55938214",FQ28:FQ35),2) -> 0 | BY37: =ROUND(SUMIF(AA28:AA35,"=55938214",FR28:FR35),2) -> 0 | BZ37: =ROUND(SUMIF(AA28:AA35,"=55938214",GL28:GL35),2) -> 0 | CA37: =ROUND(SUMIF(AA28:AA35,"=55938214",GM28:GM35),2) -> 0 | CB37: =ROUND(SUMIF(AA28:AA35,"=55938214",GN28:GN35),2) -> 0 | CC37: =ROUND(SUMIF(AA28:AA35,"=55938214",GO28:GO35),2) -> 0 | CD37: =ROUND(SUMIF(AA28:AA35,"=55938214",GP28:GP35),2) -> 0 | CE37: =AC37-BX37 -> 0 | CF37: =AC37-BY37 -> 0 | CG37: =BX37-BZ37 -> 0 | CH37: =AC37-BX37-BY37+BZ37 -> 0 | CI37: =BY37-BZ37 -> 0 | CJ37: =ROUND(SUMIF(AA28:AA35,"=55938214",GX28:GX35),2) -> 0 | CK37: =ROUND(SUMIF(AA28:AA35,"=55938214",GY28:GY35),2) -> 0 | CL37: =ROUND(SUMIF(AA28:AA35,"=55938214",GZ28:GZ35),2) -> 0 | CM37: =ROUND(SUMIF(AA28:AA35,"=55938214",HD28:HD35),2) -> 0 | DG37: =ROUND(DT37,2) -> 0 | DH37: =ROUND(DU37,2) -> 0 | DI37: =ROUND(DV37,2) -> 0 | DJ37: =ROUND(DW37,2) -> 0 | DK37: =ROUND(DX37,2) -> 0 | DL37: =ROUND(DY37,2) -> 0 | DM37: =DZ37 -> 0 | DN37: =EA37 -> 0 | DO37: =ROUND(EB37,2) -> 0 | DP37: =ROUND(EC37,2) -> 0 | DQ37: =ROUND(ED37,2) -> 0 | DT37: =ROUND(SUMIF(AA28:AA35,"=55938216",O28:O35),2) -> 0 | DU37: =ROUND(SUMIF(AA28:AA35,"=55938216",P28:P35),2) -> 0 | DV37: =ROUND(SUMIF(AA28:AA35,"=55938216",Q28:Q35),2) -> 0 | DW37: =ROUND(SUMIF(AA28:AA35,"=55938216",R28:R35),2) -> 0 | DX37: =ROUND(SUMIF(AA28:AA35,"=55938216",S28:S35),2) -> 0 | DY37: =ROUND(SUMIF(AA28:AA35,"=55938216",T28:T35),2) -> 0 | DZ37: =SUMIF(AA28:AA35,"=55938216",U28:U35) -> 0 | EA37: =SUMIF(AA28:AA35,"=55938216",V28:V35) -> 0 | EB37: =ROUND(SUMIF(AA28:AA35,"=55938216",W28:W35),2) -> 0 | EC37: =ROUND(SUMIF(AA28:AA35,"=55938216",X28:X35),2) -> 0 | ED37: =ROUND(SUMIF(AA28:AA35,"=55938216",Y28:Y35),2) -> 0 | EG37: =ROUND(FP37,2) -> 0 | EH37: =ROUND(FQ37,2) -> 0 | EI37: =ROUND(FR37,2) -> 0 | EJ37: =ROUND(FS37,2) -> 0 | EK37: =ROUND(FT37,2) -> 0 | EL37: =ROUND(FU37,2) -> 0 | EM37: =ROUND(FV37,2) -> 0 | EN37: =ROUND(FW37,2) -> 0 | ... EV37: =ROUND(GE37,2) -> 0 | FP37: =ROUND(SUMIF(AA28:AA35,"=55938216",FQ28:FQ35),2) -> 0 | FQ37: =ROUND(SUMIF(AA28:AA35,"=55938216",FR28:FR35),2) -> 0 | FR37: =ROUND(SUMIF(AA28:AA35,"=55938216",GL28:GL35),2) -> 0 | FS37: =ROUND(SUMIF(AA28:AA35,"=55938216",GM28:GM35),2) -> 0 | FT37: =ROUND(SUMIF(AA28:AA35,"=55938216",GN28:GN35),2) -> 0 | FU37: =ROUND(SUMIF(AA28:AA35,"=55938216",GO28:GO35),2) -> 0 | FV37: =ROUND(SUMIF(AA28:AA35,"=55938216",GP28:GP35),2) -> 0 | FW37: =DU37-FP37 -> 0 | FX37: =DU37-FQ37 -> 0 | FY37: =FP37-FR37 -> 0 | FZ37: =DU37-FP37-FQ37+FR37 -> 0 | GA37: =FQ37-FR37 -> 0 | GB37: =ROUND(SUMIF(AA28:AA35,"=55938216",GX28:GX35),2) -> 0 | GC37: =ROUND(SUMIF(AA28:AA35,"=55938216",GY28:GY35),2) -> 0 | GD37: =ROUND(SUMIF(AA28:AA35,"=55938216",GZ28:GZ35),2) -> 0 | GE37: =ROUND(SUMIF(AA28:AA35,"=55938216",HD28:HD35),2) -> 0 | GX37: 0
A39: 50 | B39: 0 | C39: 0 | D39: 1 | E39: 201 | F39: =ROUND(Source!O37,O39) -> 0 | G39: ПЗ | H39: Прямые затраты | K39: 201 | L39: 1 | M39: 3 | O39: 2 | P39: =ROUND(Source!DG37,O39) -> 0 | W39: 0 | X39: 1 | Y39: 0 | Z39: 0 | AA39: 1 | AB39: 0
A40: 50 | B40: 0 | C40: 0 | D40: 1 | E40: 202 | F40: =ROUND(Source!P37,O40) -> 0 | G40: СтМатОб | H40: Стоимость материальных ресурсов (всего) | K40: 202 | L40: 2 | M40: 3 | O40: 2 | P40: =ROUND(Source!DH37,O40) -> 0 | W40: 0 | X40: 1 | Y40: 0 | Z40: 0 | AA40: 1 | AB40: 0
A41: 50 | B41: 0 | C41: 0 | D41: 1 | E41: 222 | F41: =ROUND(Source!AO37,O41) -> 0 | G41: СтМатОбЗак | H41: Стоимость материалов и оборудования заказчика | K41: 222 | L41: 3 | M41: 3 | O41: 2 | P41: =ROUND(Source!EG37,O41) -> 0 | W41: 0 | X41: 1 | Y41: 0 | Z41: 0 | AA41: 1 | AB41: 0
A42: 50 | B42: 0 | C42: 0 | D42: 1 | E42: 225 | F42: =ROUND(Source!AV37,O42) -> 0 | G42: СтМатОбПод | H42: Стоимость материалов и оборудования подрядчика | K42: 225 | L42: 4 | M42: 3 | O42: 2 | P42: =ROUND(Source!EN37,O42) -> 0 | W42: 0 | X42: 1 | Y42: 0 | Z42: 0 | AA42: 1 | AB42: 0
A43: 50 | B43: 0 | C43: 0 | D43: 1 | E43: 226 | F43: =ROUND(Source!AW37,O43) -> 0 | G43: СтМат | H43: Стоимость материалов (всего) | K43: 226 | L43: 5 | M43: 3 | O43: 2 | P43: =ROUND(Source!EO37,O43) -> 0 | W43: 0 | X43: 1 | Y43: 0 | Z43: 0 | AA43: 1 | AB43: 0
A44: 50 | B44: 0 | C44: 0 | D44: 1 | E44: 227 | F44: =ROUND(Source!AX37,O44) -> 0 | G44: СтМатЗак | H44: Стоимость материалов заказчика | K44: 227 | L44: 6 | M44: 3 | O44: 2 | P44: =ROUND(Source!EP37,O44) -> 0 | W44: 0 | X44: 1 | Y44: 0 | Z44: 0 | AA44: 1 | AB44: 0
A45: 50 | B45: 0 | C45: 0 | D45: 1 | E45: 228 | F45: =ROUND(Source!AY37,O45) -> 0 | G45: СтМатПод | H45: Стоимость материалов подрядчика | K45: 228 | L45: 7 | M45: 3 | O45: 2 | P45: =ROUND(Source!EQ37,O45) -> 0 | W45: 0 | X45: 1 | Y45: 0 | Z45: 0 | AA45: 1 | AB45: 0
A46: 50 | B46: 0 | C46: 0 | D46: 1 | E46: 216 | F46: =ROUND(Source!AP37,O46) -> 0 | G46: Оборуд | H46: Стоимость оборудования (всего) | K46: 216 | L46: 8 | M46: 3 | O46: 2 | P46: =ROUND(Source!EH37,O46) -> 0 | W46: 0 | X46: 1 | Y46: 0 | Z46: 0 | AA46: 1 | AB46: 0
A47: 50 | B47: 0 | C47: 0 | D47: 1 | E47: 223 | F47: =ROUND(Source!AQ37,O47) -> 0 | G47: ОборудЗак | H47: Стоимость оборудования заказчика | K47: 223 | L47: 9 | M47: 3 | O47: 2 | P47: =ROUND(Source!EI37,O47) -> 0 | W47: 0 | X47: 1 | Y47: 0 | Z47: 0 | AA47: 1 | AB47: 0
A48: 50 | B48: 0 | C48: 0 | D48: 1 | E48: 229 | F48: =ROUND(Source!AZ37,O48) -> 0 | G48: ОборудПод | H48: Стоимость оборудования подрядчика | K48: 229 | L48: 10 | M48: 3 | O48: 2 | P48: =ROUND(Source!ER37,O48) -> 0 | W48: 0 | X48: 1 | Y48: 0 | Z48: 0 | AA48: 1 | AB48: 0
A49: 50 | B49: 0 | C49: 0 | D49: 1 | E49: 203 | F49: =ROUND(Source!Q37,O49) -> 0 | G49: ЭММ | H49: Эксплуатация машин | K49: 203 | L49: 11 | M49: 3 | O49: 2 | P49: =ROUND(Source!DI37,O49) -> 0 | W49: 0 | X49: 1 | Y49: 0 | Z49: 0 | AA49: 1 | AB49: 0
A50: 50 | B50: 0 | C50: 0 | D50: 1 | E50: 231 | F50: =ROUND(Source!BB37,O50) -> 0 | G50: ЭММсНРиСП | H50: Эксплуатация машин по ТСН-2001.16 | K50: 231 | L50: 12 | M50: 3 | O50: 2 | P50: =ROUND(Source!ET37,O50) -> 0 | W50: 0 | X50: 1 | Y50: 0 | Z50: 0 | AA50: 1 | AB50: 0
A51: 50 | B51: 0 | C51: 0 | D51: 1 | E51: 204 | F51: =ROUND(Source!R37,O51) -> 0 | G51: ЗПМ | H51: ЗП машинистов | K51: 204 | L51: 13 | M51: 3 | O51: 2 | P51: =ROUND(Source!DJ37,O51) -> 0 | W51: 0 | X51: 1 | Y51: 0 | Z51: 0 | AA51: 1 | AB51: 0
A52: 50 | B52: 0 | C52: 0 | D52: 1 | E52: 205 | F52: =ROUND(Source!S37,O52) -> 0 | G52: ОЗП | H52: Основная ЗП рабочих | K52: 205 | L52: 14 | M52: 3 | O52: 2 | P52: =ROUND(Source!DK37,O52) -> 0 | W52: 0 | X52: 1 | Y52: 0 | Z52: 0 | AA52: 1 | AB52: 0
A53: 50 | B53: 0 | C53: 0 | D53: 1 | E53: 232 | F53: =ROUND(Source!BC37,O53) -> 0 | G53: ОЗПсНРиСП | H53: Основная ЗП рабочих по ТСН-2001.16 | K53: 232 | L53: 15 | M53: 3 | O53: 2 | P53: =ROUND(Source!EU37,O53) -> 0 | W53: 0 | X53: 1 | Y53: 0 | Z53: 0 | AA53: 1 | AB53: 0
A54: 50 | B54: 0 | C54: 0 | D54: 1 | E54: 214 | F54: =ROUND(Source!AS37,O54) -> 0 | G54: Строит | H54: Строительные работы с НР и СП | K54: 214 | L54: 16 | M54: 3 | O54: 2 | P54: =ROUND(Source!EK37,O54) -> 0 | W54: 0 | X54: 1 | Y54: 0 | Z54: 0 | AA54: 1 | AB54: 0
A55: 50 | B55: 0 | C55: 0 | D55: 1 | E55: 215 | F55: =ROUND(Source!AT37,O55) -> 0 | G55: Монтаж | H55: Монтажные работы с НР и СП | K55: 215 | L55: 17 | M55: 3 | O55: 2 | P55: =ROUND(Source!EL37,O55) -> 0 | W55: 0 | X55: 1 | Y55: 0 | Z55: 0 | AA55: 1 | AB55: 0
A56: 50 | B56: 0 | C56: 0 | D56: 1 | E56: 217 | F56: =ROUND(Source!AU37,O56) -> 0 | G56: Прочие | H56: Прочие работы с НР и СП | K56: 217 | L56: 18 | M56: 3 | O56: 2 | P56: =ROUND(Source!EM37,O56) -> 0 | W56: 0 | X56: 1 | Y56: 0 | Z56: 0 | AA56: 1 | AB56: 0
A57: 50 | B57: 0 | C57: 0 | D57: 1 | E57: 230 | F57: =ROUND(Source!BA37,O57) -> 0 | G57: ПрочиеЗатр | H57: Прочие затраты по ТСН-2001.16 | K57: 230 | L57: 19 | M57: 3 | O57: 2 | P57: =ROUND(Source!ES37,O57) -> 0 | W57: 0 | X57: 1 | Y57: 0 | Z57: 0 | AA57: 1 | AB57: 0
A58: 50 | B58: 0 | C58: 0 | D58: 1 | E58: 206 | F58: =ROUND(Source!T37,O58) -> 0 | G58: ВозврМат | H58: Возврат материалов | K58: 206 | L58: 20 | M58: 3 | O58: 2 | P58: =ROUND(Source!DL37,O58) -> 0 | W58: 0 | X58: 1 | Y58: 0 | Z58: 0 | AA58: 1 | AB58: 0
A59: 50 | B59: 0 | C59: 0 | D59: 1 | E59: 207 | F59: =Source!U37 -> 0 | G59: ТрудСтр | H59: Трудозатраты строителей | K59: 207 | L59: 21 | M59: 3 | O59: -1 | P59: =Source!DM37 -> 0 | W59: 0 | X59: 1 | Y59: 0 | Z59: 0 | AA59: 1 | AB59: 0
A60: 50 | B60: 0 | C60: 0 | D60: 1 | E60: 208 | F60: =Source!V37 -> 0 | G60: ТрудМаш | H60: Трудозатраты машинистов | K60: 208 | L60: 22 | M60: 3 | O60: -1 | P60: =Source!DN37 -> 0 | W60: 0 | X60: 1 | Y60: 0 | Z60: 0 | AA60: 1 | AB60: 0
A61: 50 | B61: 0 | C61: 0 | D61: 1 | E61: 209 | F61: =ROUND(Source!W37,O61) -> 0 | G61: ТранспМат | H61: Транспорт материалов | K61: 209 | L61: 23 | M61: 3 | O61: 2 | P61: =ROUND(Source!DO37,O61) -> 0 | W61: 0 | X61: 1 | Y61: 0 | Z61: 0 | AA61: 1 | AB61: 0
A62: 50 | B62: 0 | C62: 0 | D62: 1 | E62: 233 | F62: =ROUND(Source!BD37,O62) -> 0 | G62: Перевозка | H62: Перевозка грузов | K62: 233 | L62: 24 | M62: 3 | O62: 2 | P62: =ROUND(Source!EV37,O62) -> 0 | W62: 0 | X62: 1 | Y62: 0 | Z62: 0 | AA62: 1 | AB62: 0
A63: 50 | B63: 0 | C63: 0 | D63: 1 | E63: 210 | F63: =ROUND(Source!X37,O63) -> 0 | G63: НР | H63: Накладные расходы | K63: 210 | L63: 25 | M63: 3 | O63: 2 | P63: =ROUND(Source!DP37,O63) -> 0 | W63: 0 | X63: 1 | Y63: 0 | Z63: 0 | AA63: 1 | AB63: 0
A64: 50 | B64: 0 | C64: 0 | D64: 1 | E64: 211 | F64: =ROUND(Source!Y37,O64) -> 0 | G64: СмПриб | H64: Сметная прибыль | K64: 211 | L64: 26 | M64: 3 | O64: 2 | P64: =ROUND(Source!DQ37,O64) -> 0 | W64: 0 | X64: 1 | Y64: 0 | Z64: 0 | AA64: 1 | AB64: 0
A65: 50 | B65: 0 | C65: 0 | D65: 1 | E65: 224 | F65: =ROUND(Source!AR37,O65) -> 0 | G65: Всего | H65: Всего с НР и СП | K65: 224 | L65: 27 | M65: 3 | O65: 2 | P65: =ROUND(Source!EJ37,O65) -> 0 | W65: 0 | X65: 1 | Y65: 0 | Z65: 0 | AA65: 1 | AB65: 0
A67: 4 | B67: 1 | D67: =ROW(A80) -> 80 | F67: 1 | G67: Оборудование санузла МГН (универсальная кабина) | I67: 0 | K67: -1 | S67: 0 | T67: 0 | V67: 0 | BX67: 0 | CJ67: 0
A69: 52 | B69: =B80 -> 1 | C69: =C80 -> 4 | D69: =D80 -> 67 | E69: =E80 -> 0 | F69: =F80 -> 1 | G69: =G80 -> Оборудование санузла МГН (универсальная кабина) | O69: =O80 -> 527.31 | P69: =P80 -> 495.12 | Q69: =Q80 -> 1.01 | R69: =R80 -> 0.08 | S69: =S80 -> 31.18 | T69: =T80 -> 0 | U69: =U80 -> 2.5248963 | V69: =V80 -> 0 | ... GX69: =GX80 -> 0
A71: 17 | B71: 1 | C71: =ROW(SmtRes!A38) -> 38 | D71: =ROW(EtalonRes!A47) -> 47 | E71: 1 | F71: 3.17-2-14 | G71: Установка гарнитуры туалетной: поручней для ванн | H71: 100 шт. | I71: =ROUND((1+1+2+1+1)/100,9) -> 0.06 | J71: 0 | K71: =ROUND((1+1+2+1+1)/100,9) -> 0.06 | O71: =ROUND(CP71,2) -> 331.18 | P71: =ROUND((ROUND((AC71*AW71*I71),2)*BC71),2) -> 313.79 | Q71: =(ROUND((ROUND(((((ET71*1.25)*1.2))*AV71*I71),2)*BB71),2)+ROUND((ROUND(((AE71-(((EU71*1.25)*1.2)))*AV71*I71),2)*BS71),2)) -> 0.72 | R71: =(ROUND((ROUND(((((EU71*1.25)*1.2))*AV71*I71),2)*BS71),2)+ROUND((ROUND(((AE71-(((EU71*1.25)*1.2)))*AV71*I71),2)*BS71),2)) -> 0.05 | S71: =ROUND((ROUND((AF71*AV71*I71),2)*BA71),2) -> 16.67 | T71: =ROUND(CU71*I71,2) -> 0 | U71: =CV71*I71 -> 1.492191 | V71: =CW71*I71 -> 0 | W71: =ROUND(CX71*I71,2) -> 0 | X71: =(ROUND((((S71+ROUND((ROUND(((((EU71*1.25)*1.2))*AV71*I71),2)*BS71),2))*AT71)/100),2)+ROUND(((ROUND((ROUND(((AE71-(((EU71*1.25)*1.2)))*AV71*I71),2)*BS71),2)*AT71)/100),2)) -> 18.22 | Y71: =(ROUND((((S71+ROUND((ROUND(((((EU71*1.25)*1.2))*AV71*I71),2)*BS71),2))*AU71)/100),2)+ROUND(((ROUND((ROUND(((AE71-(((EU71*1.25)*1.2)))*AV71*I71),2)*BS71),2)*AU71)/100),2)) -> 10.2 | AA71: 55938214 | AB71: =ROUND((AC71+AD71+AF71),6) -> 5501.5636 | AC71: =ROUND((((ES71*1)*1)),6) -> 5229.82 | AD71: =ROUND((((((ET71*1.25)*1.2))-(((EU71*1.25)*1.2)))+AE71),6) -> 11.31 | AE71: =ROUND((((EU71*1.25)*1.2)),6) -> 0.75 | AF71: =ROUND((((EV71*1.15)*1.2)),6) -> 260.4336 | AG71: =ROUND((AP71),6) -> 0 | AH71: =(((EW71*1.15)*1.2)) -> 23.3082 | AI71: =(((EX71*1.25)*1.2)) -> 0 | AJ71: =(AS71) -> 0 | AK71: 5426.08 | AL71: 5229.82 | AM71: 7.54 | AN71: 0.5 | AO71: 188.72 | AP71: 0 | AQ71: 16.89 | AR71: 0 | AS71: 0 | AT71: 109 | AU71: 61 | AV71: 1.067 | AW71: 1 | AZ71: 1 | BA71: 1 | BB71: 1 | BC71: 1 | BH71: 0 | BI71: 1 | BJ71: ТСН-2001.3 Доп. 80, Сб. 17, т. 2, поз. 14 | BM71: 22 | BN71: 0 | BO71: 3.17-2-14 | BP71: 1 | BQ71: 30 | BR71: 0 | BS71: 1 | BT71: 1 | BU71: 1 | BV71: 1 | BW71: 1 | BX71: 1 | BZ71: 109 | CA71: 61 | CE71: 1566 | CF71: 0 | CG71: 0 | CM71: 0 | CN71: Поправка: Гл.6.Прил.2.2.п.2.2.6_06.00.01.07.001 Наименование: При выполнении при капитальном ремонте и реконструкции работ, аналогичных технологическим процессам, характерным для нового строительства, и отсутствующих в сборниках на ремонтно-строительные работы ТСН-2001.6 Поправка: Гл.12.Прил.8.п.8. 3_12.00.01.11.001 Наименование: При наличии напряженных и стесненных условий производства работ (стесненность, сложность складирования и транспортной логистики и т.п.) для объектов, расположенных в пределах круговой магистральной системы улиц "Садовое кольцо" города Москвы | CO71: 0 | CP71: =(P71+Q71+S71) -> 331.18 | CQ71: =ROUND((ROUND((AC71*AW71*1),2)*BC71),2) -> 5229.82 | CR71: =(ROUND((ROUND(((((ET71*1.25)*1.2))*AV71*1),2)*BB71),2)+ROUND((ROUND(((AE71-(((EU71*1.25)*1.2)))*AV71*1),2)*BS71),2)) -> 12.07 | CS71: =(ROUND((ROUND(((((EU71*1.25)*1.2))*AV71*1),2)*BS71),2)+ROUND((ROUND(((AE71-(((EU71*1.25)*1.2)))*AV71*1),2)*BS71),2)) -> 0.8 | CT71: =ROUND((ROUND((AF71*AV71*1),2)*BA71),2) -> 277.88 | CU71: =AG71 -> 0 | CV71: =(AH71*AV71) -> 24.869849 | CW71: =AI71 -> 0 | CX71: =AJ71 -> 0 | CY71: =(ROUND((((S71+ROUND((ROUND(((((EU71*1.25)*1.2))*AV71*1),2)*BS71),2))*AT71)/100),2)+ROUND(((ROUND((ROUND(((AE71-(((EU71*1.25)*1.2)))*AV71*1),2)*BS71),2)*AT71)/100),2)) -> 19.04 | CZ71: =(ROUND((((S71+ROUND((ROUND(((((EU71*1.25)*1.2))*AV71*1),2)*BS71),2))*AU71)/100),2)+ROUND(((ROUND((ROUND(((AE71-(((EU71*1.25)*1.2)))*AV71*1),2)*BS71),2)*AU71)/100),2)) -> 10.66 | DB71: 25 | DD71: *1)*1 | DE71: *1,25)*1,2 | DF71: *1,25)*1,2 | DG71: *1,15)*1,2 | DI71: *1,15)*1,2 | DJ71: *1,25)*1,2 | DN71: 0 | DO71: 0 | DP71: 1 | DQ71: 1 | DU71: 1010 | DV71: 100 шт. | DW71: 100 шт. | DX71: 100 | EE71: 55393925 | EF71: 30 | EG71: Строительные работы | EH71: 0 | EJ71: 1 | EK71: 22 | EL71: ТСН-2001.3-17. Водопровод и канализация - внутренние устройства | EM71: ТСН-2001.3-17-1 | EO71: Поправка: Гл.6.Прил.2.2.п.2.2.6_06.00.01.07.001 Поправка: Гл.12.Прил.8.п.8. 3_12.00.01.11.001 | EQ71: 0 | ER71: 5426.08 | ES71: 5229.82 | ET71: 7.54 | EU71: 0.5 | EV71: 188.72 | EW71: 16.89 | EX71: 0 | EY71: 0 | FQ71: 0 | FR71: 0 | FS71: 0 | FX71: 109 | FY71: 61 | GD71: 1 | GF71: -972940482 | GG71: 2 | GH71: 1 | GI71: 2 | GJ71: 0 | GK71: 0 | GL71: =ROUND(IF(AND(BH71=3,BI71=3,FS71<>0),P71,0),2) -> 0 | GM71: =ROUND(O71+X71+Y71,2)+GX71 -> 359.6 | GN71: =IF(OR(BI71=0,BI71=1),GM71-GX71,0) -> 359.6 | GO71: =IF(BI71=2,GM71-GX71,0) -> 0 | GP71: =IF(BI71=4,GM71-GX71,0) -> 0 | GR71: 0 | GS71: 3 | GT71: 0 | GV71: =ROUND((GT71),6) -> 0 | GW71: 1 | GX71: =ROUND(HC71*I71,2) -> 0 | HA71: 0 | HB71: 0 | HC71: =GV71*GW71 -> 0 | HS71: 0 | IK71: 0
A72: 17 | B72: 1 | C72: =ROW(SmtRes!A44) -> 44 | D72: =ROW(EtalonRes!A54) -> 54 | E72: 1 | F72: 3.17-2-14 | G72: Установка гарнитуры туалетной: поручней для ванн | H72: 100 шт. | I72: =ROUND((1+1+2+1+1)/100,9) -> 0.06 | J72: 0 | K72: =ROUND((1+1+2+1+1)/100,9) -> 0.06 | O72: =ROUND(CP72,2) -> 1171.44 | P72: =ROUND((ROUND((AC72*AW72*I72),2)*BC72),2) -> 222.79 | Q72: =(ROUND((ROUND(((((ET72*1.25)*1.2))*AV72*I72),2)*BB72),2)+ROUND((ROUND(((AE72-(((EU72*1.25)*1.2)))*AV72*I72),2)*BS72),2)) -> 9.3 | R72: =(ROUND((ROUND(((((EU72*1.25)*1.2))*AV72*I72),2)*BS72),2)+ROUND((ROUND(((AE72-(((EU72*1.25)*1.2)))*AV72*I72),2)*BS72),2)) -> 2.82 | S72: =ROUND((ROUND((AF72*AV72*I72),2)*BA72),2) -> 939.35 | T72: =ROUND(CU72*I72,2) -> 0 | U72: =CV72*I72 -> 1.492191 | V72: =CW72*I72 -> 0 | W72: =ROUND(CX72*I72,2) -> 0 | X72: =(ROUND((((S72+ROUND((ROUND(((((EU72*1.25)*1.2))*AV72*I72),2)*BS72),2))*AT72)/100),2)+ROUND(((ROUND((ROUND(((AE72-(((EU72*1.25)*1.2)))*AV72*I72),2)*BS72),2)*AT72)/100),2)) -> 1026.97 | Y72: =(ROUND((((S72+ROUND((ROUND(((((EU72*1.25)*1.2))*AV72*I72),2)*BS72),2))*AU72)/100),2)+ROUND(((ROUND((ROUND(((AE72-(((EU72*1.25)*1.2)))*AV72*I72),2)*BS72),2)*AU72)/100),2)) -> 574.72 | AA72: 55938216 | AB72: =ROUND((AC72+AD72+AF72),6) -> 5501.5636 | AC72: =ROUND((((ES72*1)*1)),6) -> 5229.82 | AD72: =ROUND((((((ET72*1.25)*1.2))-(((EU72*1.25)*1.2)))+AE72),6) -> 11.31 | AE72: =ROUND((((EU72*1.25)*1.2)),6) -> 0.75 | AF72: =ROUND((((EV72*1.15)*1.2)),6) -> 260.4336 | AG72: =ROUND((AP72),6) -> 0 | AH72: =(((EW72*1.15)*1.2)) -> 23.3082 | AI72: =(((EX72*1.25)*1.2)) -> 0 | AJ72: =(AS72) -> 0 | AK72: 5426.08 | AL72: 5229.82 | AM72: 7.54 | AN72: 0.5 | AO72: 188.72 | AP72: 0 | AQ72: 16.89 | AR72: 0 | AS72: 0 | AT72: 109 | AU72: 61 | AV72: 1.067 | AW72: 1 | AZ72: 1 | BA72: 56.35 | BB72: 12.92 | BC72: 0.71 | BH72: 0 | BI72: 1 | BJ72: ТСН-2001.3 Доп. 80, Сб. 17, т. 2, поз. 14 | BM72: 22 | BN72: 0 | BO72: 3.17-2-14 | BP72: 1 | BQ72: 30 | BR72: 0 | BS72: 56.35 | BT72: 1 | BU72: 1 | BV72: 1 | BW72: 1 | BX72: 1 | BZ72: 109 | CA72: 61 | CE72: 1566 | CF72: 0 | CG72: 0 | CM72: 0 | CN72: Поправка: Гл.6.Прил.2.2.п.2.2.6_06.00.01.07.001 Наименование: При выполнении при капитальном ремонте и реконструкции работ, аналогичных технологическим процессам, характерным для нового строительства, и отсутствующих в сборниках на ремонтно-строительные работы ТСН-2001.6 Поправка: Гл.12.Прил.8.п.8. 3_12.00.01.11.001 Наименование: При наличии напряженных и стесненных условий производства работ (стесненность, сложность складирования и транспортной логистики и т.п.) для объектов, расположенных в пределах круговой магистральной системы улиц "Садовое кольцо" города Москвы | CO72: 0 | CP72: =(P72+Q72+S72) -> 1171.44 | CQ72: =ROUND((ROUND((AC72*AW72*1),2)*BC72),2) -> 3713.17 | CR72: =(ROUND((ROUND(((((ET72*1.25)*1.2))*AV72*1),2)*BB72),2)+ROUND((ROUND(((AE72-(((EU72*1.25)*1.2)))*AV72*1),2)*BS72),2)) -> 155.94 | CS72: =(ROUND((ROUND(((((EU72*1.25)*1.2))*AV72*1),2)*BS72),2)+ROUND((ROUND(((AE72-(((EU72*1.25)*1.2)))*AV72*1),2)*BS72),2)) -> 45.08 | CT72: =ROUND((ROUND((AF72*AV72*1),2)*BA72),2) -> 15658.54 | CU72: =AG72 -> 0 | CV72: =(AH72*AV72) -> 24.869849 | CW72: =AI72 -> 0 | CX72: =AJ72 -> 0 | CY72: =(ROUND((((S72+ROUND((ROUND(((((EU72*1.25)*1.2))*AV72*1),2)*BS72),2))*AT72)/100),2)+ROUND(((ROUND((ROUND(((AE72-(((EU72*1.25)*1.2)))*AV72*1),2)*BS72),2)*AT72)/100),2)) -> 1073.03 | CZ72: =(ROUND((((S72+ROUND((ROUND(((((EU72*1.25)*1.2))*AV72*1),2)*BS72),2))*AU72)/100),2)+ROUND(((ROUND((ROUND(((AE72-(((EU72*1.25)*1.2)))*AV72*1),2)*BS72),2)*AU72)/100),2)) -> 600.5 | DB72: 27 | DD72: *1)*1 | DE72: *1,25)*1,2 | DF72: *1,25)*1,2 | DG72: *1,15)*1,2 | DI72: *1,15)*1,2 | DJ72: *1,25)*1,2 | DN72: 0 | DO72: 0 | DP72: 1 | DQ72: 1 | DU72: 1010 | DV72: 100 шт. | DW72: 100 шт. | DX72: 100 | EE72: 55393925 | EF72: 30 | EG72: Строительные работы | EH72: 0 | EJ72: 1 | EK72: 22 | EL72: ТСН-2001.3-17. Водопровод и канализация - внутренние устройства | EM72: ТСН-2001.3-17-1 | EO72: Поправка: Гл.6.Прил.2.2.п.2.2.6_06.00.01.07.001 Поправка: Гл.12.Прил.8.п.8. 3_12.00.01.11.001 | EQ72: 0 | ER72: 5426.08 | ES72: 5229.82 | ET72: 7.54 | EU72: 0.5 | EV72: 188.72 | EW72: 16.89 | EX72: 0 | EY72: 0 | FQ72: 0 | FR72: 0 | FS72: 0 | FX72: 109 | FY72: 61 | GD72: 1 | GF72: -972940482 | GG72: 2 | GH72: 1 | GI72: 2 | GJ72: 0 | GK72: 0 | GL72: =ROUND(IF(AND(BH72=3,BI72=3,FS72<>0),P72,0),2) -> 0 | GM72: =ROUND(O72+X72+Y72,2)+GX72 -> 2773.13 | GN72: =IF(OR(BI72=0,BI72=1),GM72-GX72,0) -> 2773.13 | GO72: =IF(BI72=2,GM72-GX72,0) -> 0 | GP72: =IF(BI72=4,GM72-GX72,0) -> 0 | GR72: 0 | GS72: 3 | GT72: 0 | GV72: =ROUND((GT72),6) -> 0 | GW72: 1 | GX72: =ROUND(HC72*I72,2) -> 0 | HA72: 0 | HB72: 0 | HC72: =GV72*GW72 -> 0 | HS72: 0 | IK72: 0
A73: 17 | B73: 1 | C73: =ROW(SmtRes!A50) -> 50 | D73: =ROW(EtalonRes!A61) -> 61 | E73: 2 | F73: 3.17-2-13 | G73: Установка гарнитуры туалетной: вешалок, подстаканников, дозаторов настенных и т.п. | H73: 100 шт. | I73: =ROUND((1+1)/100,9) -> 0.02 | J73: 0 | K73: =ROUND((1+1)/100,9) -> 0.02 | O73: =ROUND(CP73,2) -> 47.15 | P73: =ROUND((ROUND((AC73*AW73*I73),2)*BC73),2) -> 44.04 | Q73: =(ROUND((ROUND(((((ET73*1.2)*1.25))*AV73*I73),2)*BB73),2)+ROUND((ROUND(((AE73-(((EU73*1.2)*1.25)))*AV73*I73),2)*BS73),2)) -> 0.29 | R73: =(ROUND((ROUND(((((EU73*1.2)*1.25))*AV73*I73),2)*BS73),2)+ROUND((ROUND(((AE73-(((EU73*1.2)*1.25)))*AV73*I73),2)*BS73),2)) -> 0.03 | S73: =ROUND((ROUND((AF73*AV73*I73),2)*BA73),2) -> 2.82 | T73: =ROUND(CU73*I73,2) -> 0 | U73: =CV73*I73 -> 0.25267414 | V73: =CW73*I73 -> 0 | W73: =ROUND(CX73*I73,2) -> 0 | X73: =(ROUND((((S73+ROUND((ROUND(((((EU73*1.2)*1.25))*AV73*I73),2)*BS73),2))*AT73)/100),2)+ROUND(((ROUND((ROUND(((AE73-(((EU73*1.2)*1.25)))*AV73*I73),2)*BS73),2)*AT73)/100),2)) -> 3.11 | Y73: =(ROUND((((S73+ROUND((ROUND(((((EU73*1.2)*1.25))*AV73*I73),2)*BS73),2))*AU73)/100),2)+ROUND(((ROUND((ROUND(((AE73-(((EU73*1.2)*1.25)))*AV73*I73),2)*BS73),2)*AU73)/100),2)) -> 1.74 | AA73: 55938214 | AB73: =ROUND((AC73+AD73+AF73),6) -> 2347.4092 | AC73: =ROUND((((ES73*1)*1)),6) -> 2202.04 | AD73: =ROUND((((((ET73*1.2)*1.25))-(((EU73*1.2)*1.25)))+AE73),6) -> 13.455 | AE73: =ROUND((((EU73*1.2)*1.25)),6) -> 1.515 | AF73: =ROUND((((EV73*1.2)*1.15)),6) -> 131.9142 | AG73: =ROUND((AP73),6) -> 0 | AH73: =(((EW73*1.2)*1.15)) -> 11.8404 | AI73: =(((EX73*1.2)*1.25)) -> 0 | AJ73: =(AS73) -> 0 | AK73: 2306.6 | AL73: 2202.04 | AM73: 8.97 | AN73: 1.01 | AO73: 95.59 | AP73: 0 | AQ73: 8.58 | AR73: 0 | AS73: 0 | AT73: 109 | AU73: 61 | AV73: 1.067 | AW73: 1 | AZ73: 1 | BA73: 1 | BB73: 1 | BC73: 1 | BH73: 0 | BI73: 1 | BJ73: ТСН-2001.3 Доп. 80, Сб. 17, т. 2, поз. 13 | BM73: 22 | BN73: 0 | BO73: 3.17-2-13 | BP73: 1 | BQ73: 30 | BR73: 0 | BS73: 1 | BT73: 1 | BU73: 1 | BV73: 1 | BW73: 1 | BX73: 1 | BZ73: 109 | CA73: 61 | CE73: 1566 | CF73: 0 | CG73: 0 | CM73: 0 | CN73: Поправка: Гл.12.Прил.8.п.8. 3_12.00.01.11.001 Наименование: При наличии напряженных и стесненных условий производства работ (стесненность, сложность складирования и транспортной логистики и т.п.) для объектов, расположенных в пределах круговой магистральной системы улиц "Садовое кольцо" города Москвы Поправка: Гл.6.Прил.2.2.п.2.2.6_06.00.01.07.001 Наименование: При выполнении при капитальном ремонте и реконструкции работ, аналогичных технологическим процессам, характерным для нового строительства, и отсутствующих в сборниках на ремонтно-строительные работы ТСН-2001.6 | CO73: 0 | CP73: =(P73+Q73+S73) -> 47.15 | CQ73: =ROUND((ROUND((AC73*AW73*1),2)*BC73),2) -> 2202.04 | CR73: =(ROUND((ROUND(((((ET73*1.2)*1.25))*AV73*1),2)*BB73),2)+ROUND((ROUND(((AE73-(((EU73*1.2)*1.25)))*AV73*1),2)*BS73),2)) -> 14.36 | CS73: =(ROUND((ROUND(((((EU73*1.2)*1.25))*AV73*1),2)*BS73),2)+ROUND((ROUND(((AE73-(((EU73*1.2)*1.25)))*AV73*1),2)*BS73),2)) -> 1.62 | CT73: =ROUND((ROUND((AF73*AV73*1),2)*BA73),2) -> 140.75 | CU73: =AG73 -> 0 | CV73: =(AH73*AV73) -> 12.633707 | CW73: =AI73 -> 0 | CX73: =AJ73 -> 0 | CY73: =(ROUND((((S73+ROUND((ROUND(((((EU73*1.2)*1.25))*AV73*1),2)*BS73),2))*AT73)/100),2)+ROUND(((ROUND((ROUND(((AE73-(((EU73*1.2)*1.25)))*AV73*1),2)*BS73),2)*AT73)/100),2)) -> 4.84 | CZ73: =(ROUND((((S73+ROUND((ROUND(((((EU73*1.2)*1.25))*AV73*1),2)*BS73),2))*AU73)/100),2)+ROUND(((ROUND((ROUND(((AE73-(((EU73*1.2)*1.25)))*AV73*1),2)*BS73),2)*AU73)/100),2)) -> 2.71 | DB73: 29 | DD73: *1)*1 | DE73: *1,2)*1,25 | DF73: *1,2)*1,25 | DG73: *1,2)*1,15 | DI73: *1,2)*1,15 | DJ73: *1,2)*1,25 | DN73: 0 | DO73: 0 | DP73: 1 | DQ73: 1 | DU73: 1010 | DV73: 100 шт. | DW73: 100 шт. | DX73: 100 | EE73: 55393925 | EF73: 30 | EG73: Строительные работы | EH73: 0 | EJ73: 1 | EK73: 22 | EL73: ТСН-2001.3-17. Водопровод и канализация - внутренние устройства | EM73: ТСН-2001.3-17-1 | EO73: Поправка: Гл.12.Прил.8.п.8. 3_12.00.01.11.001 Поправка: Гл.6.Прил.2.2.п.2.2.6_06.00.01.07.001 | EQ73: 0 | ER73: 2306.6 | ES73: 2202.04 | ET73: 8.97 | EU73: 1.01 | EV73: 95.59 | EW73: 8.58 | EX73: 0 | EY73: 0 | FQ73: 0 | FR73: 0 | FS73: 0 | FX73: 109 | FY73: 61 | GD73: 1 | GF73: -1875467598 | GG73: 2 | GH73: 1 | GI73: 2 | GJ73: 0 | GK73: 0 | GL73: =ROUND(IF(AND(BH73=3,BI73=3,FS73<>0),P73,0),2) -> 0 | GM73: =ROUND(O73+X73+Y73,2)+GX73 -> 52 | GN73: =IF(OR(BI73=0,BI73=1),GM73-GX73,0) -> 52 | GO73: =IF(BI73=2,GM73-GX73,0) -> 0 | GP73: =IF(BI73=4,GM73-GX73,0) -> 0 | GR73: 0 | GS73: 3 | GT73: 0 | GV73: =ROUND((GT73),6) -> 0 | GW73: 1 | GX73: =ROUND(HC73*I73,2) -> 0 | HA73: 0 | HB73: 0 | HC73: =GV73*GW73 -> 0 | HS73: 0 | IK73: 0
A74: 17 | B74: 1 | C74: =ROW(SmtRes!A56) -> 56 | D74: =ROW(EtalonRes!A68) -> 68 | E74: 2 | F74: 3.17-2-13 | G74: Установка гарнитуры туалетной: вешалок, подстаканников, дозаторов настенных и т.п. | H74: 100 шт. | I74: =ROUND((1+1)/100,9) -> 0.02 | J74: 0 | K74: =ROUND((1+1)/100,9) -> 0.02 | O74: =ROUND(CP74,2) -> 194.57 | P74: =ROUND((ROUND((AC74*AW74*I74),2)*BC74),2) -> 31.27 | Q74: =(ROUND((ROUND(((((ET74*1.2)*1.25))*AV74*I74),2)*BB74),2)+ROUND((ROUND(((AE74-(((EU74*1.2)*1.25)))*AV74*I74),2)*BS74),2)) -> 4.39 | R74: =(ROUND((ROUND(((((EU74*1.2)*1.25))*AV74*I74),2)*BS74),2)+ROUND((ROUND(((AE74-(((EU74*1.2)*1.25)))*AV74*I74),2)*BS74),2)) -> 1.69 | S74: =ROUND((ROUND((AF74*AV74*I74),2)*BA74),2) -> 158.91 | T74: =ROUND(CU74*I74,2) -> 0 | U74: =CV74*I74 -> 0.25267414 | V74: =CW74*I74 -> 0 | W74: =ROUND(CX74*I74,2) -> 0 | X74: =(ROUND((((S74+ROUND((ROUND(((((EU74*1.2)*1.25))*AV74*I74),2)*BS74),2))*AT74)/100),2)+ROUND(((ROUND((ROUND(((AE74-(((EU74*1.2)*1.25)))*AV74*I74),2)*BS74),2)*AT74)/100),2)) -> 175.05 | Y74: =(ROUND((((S74+ROUND((ROUND(((((EU74*1.2)*1.25))*AV74*I74),2)*BS74),2))*AU74)/100),2)+ROUND(((ROUND((ROUND(((AE74-(((EU74*1.2)*1.25)))*AV74*I74),2)*BS74),2)*AU74)/100),2)) -> 97.97 | AA74: 55938216 | AB74: =ROUND((AC74+AD74+AF74),6) -> 2347.4092 | AC74: =ROUND((((ES74*1)*1)),6) -> 2202.04 | AD74: =ROUND((((((ET74*1.2)*1.25))-(((EU74*1.2)*1.25)))+AE74),6) -> 13.455 | AE74: =ROUND((((EU74*1.2)*1.25)),6) -> 1.515 | AF74: =ROUND((((EV74*1.2)*1.15)),6) -> 131.9142 | AG74: =ROUND((AP74),6) -> 0 | AH74: =(((EW74*1.2)*1.15)) -> 11.8404 | AI74: =(((EX74*1.2)*1.25)) -> 0 | AJ74: =(AS74) -> 0 | AK74: 2306.6 | AL74: 2202.04 | AM74: 8.97 | AN74: 1.01 | AO74: 95.59 | AP74: 0 | AQ74: 8.58 | AR74: 0 | AS74: 0 | AT74: 109 | AU74: 61 | AV74: 1.067 | AW74: 1 | AZ74: 1 | BA74: 56.35 | BB74: 15.15 | BC74: 0.71 | BH74: 0 | BI74: 1 | BJ74: ТСН-2001.3 Доп. 80, Сб. 17, т. 2, поз. 13 | BM74: 22 | BN74: 0 | BO74: 3.17-2-13 | BP74: 1 | BQ74: 30 | BR74: 0 | BS74: 56.35 | BT74: 1 | BU74: 1 | BV74: 1 | BW74: 1 | BX74: 1 | BZ74: 109 | CA74: 61 | CE74: 1566 | CF74: 0 | CG74: 0 | CM74: 0 | CN74: Поправка: Гл.12.Прил.8.п.8. 3_12.00.01.11.001 Наименование: При наличии напряженных и стесненных условий производства работ (стесненность, сложность складирования и транспортной логистики и т.п.) для объектов, расположенных в пределах круговой магистральной системы улиц "Садовое кольцо" города Москвы Поправка: Гл.6.Прил.2.2.п.2.2.6_06.00.01.07.001 Наименование: При выполнении при капитальном ремонте и реконструкции работ, аналогичных технологическим процессам, характерным для нового строительства, и отсутствующих в сборниках на ремонтно-строительные работы ТСН-2001.6 | CO74: 0 | CP74: =(P74+Q74+S74) -> 194.57 | CQ74: =ROUND((ROUND((AC74*AW74*1),2)*BC74),2) -> 1563.45 | CR74: =(ROUND((ROUND(((((ET74*1.2)*1.25))*AV74*1),2)*BB74),2)+ROUND((ROUND(((AE74-(((EU74*1.2)*1.25)))*AV74*1),2)*BS74),2)) -> 217.55 | CS74: =(ROUND((ROUND(((((EU74*1.2)*1.25))*AV74*1),2)*BS74),2)+ROUND((ROUND(((AE74-(((EU74*1.2)*1.25)))*AV74*1),2)*BS74),2)) -> 91.29 | CT74: =ROUND((ROUND((AF74*AV74*1),2)*BA74),2) -> 7931.26 | CU74: =AG74 -> 0 | CV74: =(AH74*AV74) -> 12.633707 | CW74: =AI74 -> 0 | CX74: =AJ74 -> 0 | CY74: =(ROUND((((S74+ROUND((ROUND(((((EU74*1.2)*1.25))*AV74*1),2)*BS74),2))*AT74)/100),2)+ROUND(((ROUND((ROUND(((AE74-(((EU74*1.2)*1.25)))*AV74*1),2)*BS74),2)*AT74)/100),2)) -> 272.72 | CZ74: =(ROUND((((S74+ROUND((ROUND(((((EU74*1.2)*1.25))*AV74*1),2)*BS74),2))*AU74)/100),2)+ROUND(((ROUND((ROUND(((AE74-(((EU74*1.2)*1.25)))*AV74*1),2)*BS74),2)*AU74)/100),2)) -> 152.62 | DB74: 31 | DD74: *1)*1 | DE74: *1,2)*1,25 | DF74: *1,2)*1,25 | DG74: *1,2)*1,15 | DI74: *1,2)*1,15 | DJ74: *1,2)*1,25 | DN74: 0 | DO74: 0 | DP74: 1 | DQ74: 1 | DU74: 1010 | DV74: 100 шт. | DW74: 100 шт. | DX74: 100 | EE74: 55393925 | EF74: 30 | EG74: Строительные работы | EH74: 0 | EJ74: 1 | EK74: 22 | EL74: ТСН-2001.3-17. Водопровод и канализация - внутренние устройства | EM74: ТСН-2001.3-17-1 | EO74: Поправка: Гл.12.Прил.8.п.8. 3_12.00.01.11.001 Поправка: Гл.6.Прил.2.2.п.2.2.6_06.00.01.07.001 | EQ74: 0 | ER74: 2306.6 | ES74: 2202.04 | ET74: 8.97 | EU74: 1.01 | EV74: 95.59 | EW74: 8.58 | EX74: 0 | EY74: 0 | FQ74: 0 | FR74: 0 | FS74: 0 | FX74: 109 | FY74: 61 | GD74: 1 | GF74: -1875467598 | GG74: 2 | GH74: 1 | GI74: 2 | GJ74: 0 | GK74: 0 | GL74: =ROUND(IF(AND(BH74=3,BI74=3,FS74<>0),P74,0),2) -> 0 | GM74: =ROUND(O74+X74+Y74,2)+GX74 -> 467.59 | GN74: =IF(OR(BI74=0,BI74=1),GM74-GX74,0) -> 467.59 | GO74: =IF(BI74=2,GM74-GX74,0) -> 0 | GP74: =IF(BI74=4,GM74-GX74,0) -> 0 | GR74: 0 | GS74: 3 | GT74: 0 | GV74: =ROUND((GT74),6) -> 0 | GW74: 1 | GX74: =ROUND(HC74*I74,2) -> 0 | HA74: 0 | HB74: 0 | HC74: =GV74*GW74 -> 0 | HS74: 0 | IK74: 0
A75: 17 | B75: 1 | C75: =ROW(SmtRes!A59) -> 59 | D75: =ROW(EtalonRes!A71) -> 71 | E75: 3 | F75: 3.70-61-2 | G75: Установка номерных табличек для этажа, подъезда | H75: 1 ШТ. | I75: 1 | J75: 0 | K75: 1 | O75: =ROUND(CP75,2) -> 12.19 | P75: =ROUND((ROUND((AC75*AW75*I75),2)*BC75),2) -> 0.5 | Q75: =(ROUND((ROUND(((((ET75*1.25)*1.2))*AV75*I75),2)*BB75),2)+ROUND((ROUND(((AE75-(((EU75*1.25)*1.2)))*AV75*I75),2)*BS75),2)) -> 0 | R75: =(ROUND((ROUND(((((EU75*1.25)*1.2))*AV75*I75),2)*BS75),2)+ROUND((ROUND(((AE75-(((EU75*1.25)*1.2)))*AV75*I75),2)*BS75),2)) -> 0 | S75: =ROUND((ROUND((AF75*AV75*I75),2)*BA75),2) -> 11.69 | T75: =ROUND(CU75*I75,2) -> 0 | U75: =CV75*I75 -> 0.7800312 | V75: =CW75*I75 -> 0 | W75: =ROUND(CX75*I75,2) -> 0 | X75: =(ROUND((((S75+ROUND((ROUND(((((EU75*1.25)*1.2))*AV75*I75),2)*BS75),2))*AT75)/100),2)+ROUND(((ROUND((ROUND(((AE75-(((EU75*1.25)*1.2)))*AV75*I75),2)*BS75),2)*AT75)/100),2)) -> 9.82 | Y75: =(ROUND((((S75+ROUND((ROUND(((((EU75*1.25)*1.2))*AV75*I75),2)*BS75),2))*AU75)/100),2)+ROUND(((ROUND((ROUND(((AE75-(((EU75*1.25)*1.2)))*AV75*I75),2)*BS75),2)*AU75)/100),2)) -> 6.2 | AA75: 55938214 | AB75: =ROUND((AC75+AD75+AF75),6) -> 11.2502 | AC75: =ROUND((((ES75*1)*1)),6) -> 0.5 | AD75: =ROUND((((((ET75*1.25)*1.2))-(((EU75*1.25)*1.2)))+AE75),6) -> 0 | AE75: =ROUND((((EU75*1.25)*1.2)),6) -> 0 | AF75: =ROUND((((EV75*1.15)*1.2)),6) -> 10.7502 | AG75: =ROUND((AP75),6) -> 0 | AH75: =(((EW75*1.15)*1.2)) -> 0.7176 | AI75: =(((EX75*1.25)*1.2)) -> 0 | AJ75: =(AS75) -> 0 | AK75: 8.29 | AL75: 0.5 | AM75: 0 | AN75: 0 | AO75: 7.79 | AP75: 0 | AQ75: 0.52 | AR75: 0 | AS75: 0 | AT75: 84 | AU75: 53 | AV75: 1.087 | AW75: 1 | AZ75: 1 | BA75: 1 | BB75: 1 | BC75: 1 | BH75: 0 | BI75: 1 | BJ75: ТСН-2001.3 Доп. 78, Сб. 70, т. 61, поз. 2 | BM75: 55 | BN75: 0 | BO75: 3.70-61-2 | BP75: 1 | BQ75: 30 | BR75: 0 | BS75: 1 | BT75: 1 | BU75: 1 | BV75: 1 | BW75: 1 | BX75: 1 | BZ75: 84 | CA75: 53 | CE75: 1566 | CF75: 0 | CG75: 0 | CM75: 0 | CN75: Поправка: Гл.6.Прил.2.2.п.2.2.6_06.00.01.07.001 Наименование: При выполнении при капитальном ремонте и реконструкции работ, аналогичных технологическим процессам, характерным для нового строительства, и отсутствующих в сборниках на ремонтно-строительные работы ТСН-2001.6 Поправка: Гл.12.Прил.8.п.8. 3_12.00.01.11.001 Наименование: При наличии напряженных и стесненных условий производства работ (стесненность, сложность складирования и транспортной логистики и т.п.) для объектов, расположенных в пределах круговой магистральной системы улиц "Садовое кольцо" города Москвы | CO75: 0 | CP75: =(P75+Q75+S75) -> 12.19 | CQ75: =ROUND((ROUND((AC75*AW75*1),2)*BC75),2) -> 0.5 | CR75: =(ROUND((ROUND(((((ET75*1.25)*1.2))*AV75*1),2)*BB75),2)+ROUND((ROUND(((AE75-(((EU75*1.25)*1.2)))*AV75*1),2)*BS75),2)) -> 0 | CS75: =(ROUND((ROUND(((((EU75*1.25)*1.2))*AV75*1),2)*BS75),2)+ROUND((ROUND(((AE75-(((EU75*1.25)*1.2)))*AV75*1),2)*BS75),2)) -> 0 | CT75: =ROUND((ROUND((AF75*AV75*1),2)*BA75),2) -> 11.69 | CU75: =AG75 -> 0 | CV75: =(AH75*AV75) -> 0.7800312 | CW75: =AI75 -> 0 | CX75: =AJ75 -> 0 | CY75: =(ROUND((((S75+ROUND((ROUND(((((EU75*1.25)*1.2))*AV75*1),2)*BS75),2))*AT75)/100),2)+ROUND(((ROUND((ROUND(((AE75-(((EU75*1.25)*1.2)))*AV75*1),2)*BS75),2)*AT75)/100),2)) -> 9.82 | CZ75: =(ROUND((((S75+ROUND((ROUND(((((EU75*1.25)*1.2))*AV75*1),2)*BS75),2))*AU75)/100),2)+ROUND(((ROUND((ROUND(((AE75-(((EU75*1.25)*1.2)))*AV75*1),2)*BS75),2)*AU75)/100),2)) -> 6.2 | DB75: 33 | DD75: *1)*1 | DE75: *1,25)*1,2 | DF75: *1,25)*1,2 | DG75: *1,15)*1,2 | DI75: *1,15)*1,2 | DJ75: *1,25)*1,2 | DN75: 0 | DO75: 0 | DP75: 1 | DQ75: 1 | DU75: 1013 | DV75: 1 ШТ. | DW75: 1 ШТ. | DX75: 1 | EE75: 55393960 | EF75: 30 | EG75: Строительные работы | EH75: 0 | EJ75: 1 | EK75: 55 | EL75: ТСН-2001.3-70. Металлические конструкции | EM75: ТСН-2001.3-70-4 | EO75: Поправка: Гл.6.Прил.2.2.п.2.2.6_06.00.01.07.001 Поправка: Гл.12.Прил.8.п.8. 3_12.00.01.11.001 | EQ75: 0 | ER75: 8.29 | ES75: 0.5 | ET75: 0 | EU75: 0 | EV75: 7.79 | EW75: 0.52 | EX75: 0 | EY75: 0 | FQ75: 0 | FR75: 0 | FS75: 0 | FX75: 84 | FY75: 53 | GD75: 1 | GF75: 646576480 | GG75: 2 | GH75: 1 | GI75: 2 | GJ75: 0 | GK75: 0 | GL75: =ROUND(IF(AND(BH75=3,BI75=3,FS75<>0),P75,0),2) -> 0 | GM75: =ROUND(O75+X75+Y75,2)+GX75 -> 28.21 | GN75: =IF(OR(BI75=0,BI75=1),GM75-GX75,0) -> 28.21 | GO75: =IF(BI75=2,GM75-GX75,0) -> 0 | GP75: =IF(BI75=4,GM75-GX75,0) -> 0 | GR75: 0 | GS75: 3 | GT75: 0 | GV75: =ROUND((GT75),6) -> 0 | GW75: 1 | GX75: =ROUND(HC75*I75,2) -> 0 | HA75: 0 | HB75: 0 | HC75: =GV75*GW75 -> 0 | HS75: 0 | IK75: 0
A76: 17 | B76: 1 | C76: =ROW(SmtRes!A62) -> 62 | D76: =ROW(EtalonRes!A74) -> 74 | E76: 3 | F76: 3.70-61-2 | G76: Установка номерных табличек для этажа, подъезда | H76: 1 ШТ. | I76: 1 | J76: 0 | K76: 1 | O76: =ROUND(CP76,2) -> 666.94 | P76: =ROUND((ROUND((AC76*AW76*I76),2)*BC76),2) -> 8.21 | Q76: =(ROUND((ROUND(((((ET76*1.25)*1.2))*AV76*I76),2)*BB76),2)+ROUND((ROUND(((AE76-(((EU76*1.25)*1.2)))*AV76*I76),2)*BS76),2)) -> 0 | R76: =(ROUND((ROUND(((((EU76*1.25)*1.2))*AV76*I76),2)*BS76),2)+ROUND((ROUND(((AE76-(((EU76*1.25)*1.2)))*AV76*I76),2)*BS76),2)) -> 0 | S76: =ROUND((ROUND((AF76*AV76*I76),2)*BA76),2) -> 658.73 | T76: =ROUND(CU76*I76,2) -> 0 | U76: =CV76*I76 -> 0.7800312 | V76: =CW76*I76 -> 0 | W76: =ROUND(CX76*I76,2) -> 0 | X76: =(ROUND((((S76+ROUND((ROUND(((((EU76*1.25)*1.2))*AV76*I76),2)*BS76),2))*AT76)/100),2)+ROUND(((ROUND((ROUND(((AE76-(((EU76*1.25)*1.2)))*AV76*I76),2)*BS76),2)*AT76)/100),2)) -> 553.33 | Y76: =(ROUND((((S76+ROUND((ROUND(((((EU76*1.25)*1.2))*AV76*I76),2)*BS76),2))*AU76)/100),2)+ROUND(((ROUND((ROUND(((AE76-(((EU76*1.25)*1.2)))*AV76*I76),2)*BS76),2)*AU76)/100),2)) -> 349.13 | AA76: 55938216 | AB76: =ROUND((AC76+AD76+AF76),6) -> 11.2502 | AC76: =ROUND((((ES76*1)*1)),6) -> 0.5 | AD76: =ROUND((((((ET76*1.25)*1.2))-(((EU76*1.25)*1.2)))+AE76),6) -> 0 | AE76: =ROUND((((EU76*1.25)*1.2)),6) -> 0 | AF76: =ROUND((((EV76*1.15)*1.2)),6) -> 10.7502 | AG76: =ROUND((AP76),6) -> 0 | AH76: =(((EW76*1.15)*1.2)) -> 0.7176 | AI76: =(((EX76*1.25)*1.2)) -> 0 | AJ76: =(AS76) -> 0 | AK76: 8.29 | AL76: 0.5 | AM76: 0 | AN76: 0 | AO76: 7.79 | AP76: 0 | AQ76: 0.52 | AR76: 0 | AS76: 0 | AT76: 84 | AU76: 53 | AV76: 1.087 | AW76: 1 | AZ76: 1 | BA76: 56.35 | BB76: 1 | BC76: 16.42 | BH76: 0 | BI76: 1 | BJ76: ТСН-2001.3 Доп. 78, Сб. 70, т. 61, поз. 2 | BM76: 55 | BN76: 0 | BO76: 3.70-61-2 | BP76: 1 | BQ76: 30 | BR76: 0 | BS76: 56.35 | BT76: 1 | BU76: 1 | BV76: 1 | BW76: 1 | BX76: 1 | BZ76: 84 | CA76: 53 | CE76: 1566 | CF76: 0 | CG76: 0 | CM76: 0 | CN76: Поправка: Гл.6.Прил.2.2.п.2.2.6_06.00.01.07.001 Наименование: При выполнении при капитальном ремонте и реконструкции работ, аналогичных технологическим процессам, характерным для нового строительства, и отсутствующих в сборниках на ремонтно-строительные работы ТСН-2001.6 Поправка: Гл.12.Прил.8.п.8. 3_12.00.01.11.001 Наименование: При наличии напряженных и стесненных условий производства работ (стесненность, сложность складирования и транспортной логистики и т.п.) для объектов, расположенных в пределах круговой магистральной системы улиц "Садовое кольцо" города Москвы | CO76: 0 | CP76: =(P76+Q76+S76) -> 666.94 | CQ76: =ROUND((ROUND((AC76*AW76*1),2)*BC76),2) -> 8.21 | CR76: =(ROUND((ROUND(((((ET76*1.25)*1.2))*AV76*1),2)*BB76),2)+ROUND((ROUND(((AE76-(((EU76*1.25)*1.2)))*AV76*1),2)*BS76),2)) -> 0 | CS76: =(ROUND((ROUND(((((EU76*1.25)*1.2))*AV76*1),2)*BS76),2)+ROUND((ROUND(((AE76-(((EU76*1.25)*1.2)))*AV76*1),2)*BS76),2)) -> 0 | CT76: =ROUND((ROUND((AF76*AV76*1),2)*BA76),2) -> 658.73 | CU76: =AG76 -> 0 | CV76: =(AH76*AV76) -> 0.7800312 | CW76: =AI76 -> 0 | CX76: =AJ76 -> 0 | CY76: =(ROUND((((S76+ROUND((ROUND(((((EU76*1.25)*1.2))*AV76*1),2)*BS76),2))*AT76)/100),2)+ROUND(((ROUND((ROUND(((AE76-(((EU76*1.25)*1.2)))*AV76*1),2)*BS76),2)*AT76)/100),2)) -> 553.33 | CZ76: =(ROUND((((S76+ROUND((ROUND(((((EU76*1.25)*1.2))*AV76*1),2)*BS76),2))*AU76)/100),2)+ROUND(((ROUND((ROUND(((AE76-(((EU76*1.25)*1.2)))*AV76*1),2)*BS76),2)*AU76)/100),2)) -> 349.13 | DB76: 35 | DD76: *1)*1 | DE76: *1,25)*1,2 | DF76: *1,25)*1,2 | DG76: *1,15)*1,2 | DI76: *1,15)*1,2 | DJ76: *1,25)*1,2 | DN76: 0 | DO76: 0 | DP76: 1 | DQ76: 1 | DU76: 1013 | DV76: 1 ШТ. | DW76: 1 ШТ. | DX76: 1 | EE76: 55393960 | EF76: 30 | EG76: Строительные работы | EH76: 0 | EJ76: 1 | EK76: 55 | EL76: ТСН-2001.3-70. Металлические конструкции | EM76: ТСН-2001.3-70-4 | EO76: Поправка: Гл.6.Прил.2.2.п.2.2.6_06.00.01.07.001 Поправка: Гл.12.Прил.8.п.8. 3_12.00.01.11.001 | EQ76: 0 | ER76: 8.29 | ES76: 0.5 | ET76: 0 | EU76: 0 | EV76: 7.79 | EW76: 0.52 | EX76: 0 | EY76: 0 | FQ76: 0 | FR76: 0 | FS76: 0 | FX76: 84 | FY76: 53 | GD76: 1 | GF76: 646576480 | GG76: 2 | GH76: 1 | GI76: 2 | GJ76: 0 | GK76: 0 | GL76: =ROUND(IF(AND(BH76=3,BI76=3,FS76<>0),P76,0),2) -> 0 | GM76: =ROUND(O76+X76+Y76,2)+GX76 -> 1569.4 | GN76: =IF(OR(BI76=0,BI76=1),GM76-GX76,0) -> 1569.4 | GO76: =IF(BI76=2,GM76-GX76,0) -> 0 | GP76: =IF(BI76=4,GM76-GX76,0) -> 0 | GR76: 0 | GS76: 3 | GT76: 0 | GV76: =ROUND((GT76),6) -> 0 | GW76: 1 | GX76: =ROUND(HC76*I76,2) -> 0 | HA76: 0 | HB76: 0 | HC76: =GV76*GW76 -> 0 | HS76: 0 | IK76: 0
A77: 18 | B77: 1 | C77: 59 | E77: 3,1 | F77: КА, п.5 | G77: Тактильно-визуальный знак "Туалет для инвалидов" | H77: ШТ | I77: =I75*J77 -> 1 | J77: 1 | K77: 1 | O77: =ROUND(CP77,2) -> 136.79 | P77: =ROUND((ROUND((AC77*AW77*I77),2)*BC77),2) -> 136.79 | Q77: =(ROUND((ROUND(((ET77)*AV77*I77),2)*BB77),2)+ROUND((ROUND(((AE77-(EU77))*AV77*I77),2)*BS77),2)) -> 0 | R77: =(ROUND((ROUND(((EU77)*AV77*I77),2)*BS77),2)+ROUND((ROUND(((AE77-(EU77))*AV77*I77),2)*BS77),2)) -> 0 | S77: =ROUND((ROUND((AF77*AV77*I77),2)*BA77),2) -> 0 | T77: =ROUND(CU77*I77,2) -> 0 | U77: =CV77*I77 -> 0 | V77: =CW77*I77 -> 0 | W77: =ROUND(CX77*I77,2) -> 0 | X77: =(ROUND((((S77+ROUND((ROUND(((EU77)*AV77*I77),2)*BS77),2))*AT77)/100),2)+ROUND(((ROUND((ROUND(((AE77-(EU77))*AV77*I77),2)*BS77),2)*AT77)/100),2)) -> 0 | Y77: =(ROUND((((S77+ROUND((ROUND(((EU77)*AV77*I77),2)*BS77),2))*AU77)/100),2)+ROUND(((ROUND((ROUND(((AE77-(EU77))*AV77*I77),2)*BS77),2)*AU77)/100),2)) -> 0 | AA77: 55938214 | AB77: =ROUND((AC77+AD77+AF77),6) -> 136.79 | AC77: =ROUND((ES77),6) -> 136.79 | AD77: =ROUND((((ET77)-(EU77))+AE77),6) -> 0 | AE77: =ROUND((EU77),6) -> 0 | AF77: =ROUND((EV77),6) -> 0 | AG77: =ROUND((AP77),6) -> 0 | AH77: =(EW77) -> 0 | AI77: =(EX77) -> 0 | AJ77: =(AS77) -> 0 | AK77: 136.79 | AL77: 136.79 | AM77: 0 | AN77: 0 | AO77: 0 | AP77: 0 | AQ77: 0 | AR77: 0 | AS77: 0 | AT77: 0 | AU77: 0 | AV77: 1 | AW77: 1 | AZ77: 1 | BA77: 1 | BB77: 1 | BC77: 1 | BH77: 3 | BI77: 1 | BJ77: КА, п.5 | BM77: 400005 | BN77: 0 | BP77: 0 | BQ77: 213 | BR77: 0 | BS77: 1 | BT77: 1 | BU77: 1 | BV77: 1 | BW77: 1 | BX77: 1 | BZ77: 84 | CA77: 53 | CE77: 1566 | CF77: 0 | CG77: 0 | CM77: 0 | CO77: 0 | CP77: =(P77+Q77+S77) -> 136.79 | CQ77: =ROUND((ROUND((AC77*AW77*1),2)*BC77),2) -> 136.79 | CR77: =(ROUND((ROUND(((ET77)*AV77*1),2)*BB77),2)+ROUND((ROUND(((AE77-(EU77))*AV77*1),2)*BS77),2)) -> 0 | CS77: =(ROUND((ROUND(((EU77)*AV77*1),2)*BS77),2)+ROUND((ROUND(((AE77-(EU77))*AV77*1),2)*BS77),2)) -> 0 | CT77: =ROUND((ROUND((AF77*AV77*1),2)*BA77),2) -> 0 | CU77: =AG77 -> 0 | CV77: =(AH77*AV77) -> 0 | CW77: =AI77 -> 0 | CX77: =AJ77 -> 0 | CY77: =(ROUND((((S77+ROUND((ROUND(((EU77)*AV77*1),2)*BS77),2))*AT77)/100),2)+ROUND(((ROUND((ROUND(((AE77-(EU77))*AV77*1),2)*BS77),2)*AT77)/100),2)) -> 0 | CZ77: =(ROUND((((S77+ROUND((ROUND(((EU77)*AV77*1),2)*BS77),2))*AU77)/100),2)+ROUND(((ROUND((ROUND(((AE77-(EU77))*AV77*1),2)*BS77),2)*AU77)/100),2)) -> 0 | DN77: 0 | DO77: 0 | DP77: 1 | DQ77: 1 | DU77: 1013 | DV77: ШТ | DW77: ШТ | DX77: 1 | EE77: 55393902 | EF77: 213 | EG77: Материалы, отсутствующие в СНБ (Строительные) | EH77: 0 | EJ77: 1 | EK77: 400005 | EL77: Материалы, отсутствующие в СНБ (Строительные) | EM77: МР КА Строительные | EQ77: 16 | ER77: 0 | ES77: 136.79 | ET77: 0 | EU77: 0 | EV77: 0 | EW77: 0 | EX77: 0 | FQ77: 0 | FR77: 0 | FS77: 0 | FX77: 84 | FY77: 53 | GA77: [1 610 / 1,22 / 9,84] + 2% Заг.скл | GD77: 1 | GF77: -999068521 | GG77: 2 | GH77: 4 | GI77: -2 | GJ77: 0 | GK77: 0 | GL77: =ROUND(IF(AND(BH77=3,BI77=3,FS77<>0),P77,0),2) -> 0 | GM77: =ROUND(O77+X77+Y77,2)+GX77 -> 136.79 | GN77: =IF(OR(BI77=0,BI77=1),GM77-GX77,0) -> 136.79 | GO77: =IF(BI77=2,GM77-GX77,0) -> 0 | GP77: =IF(BI77=4,GM77-GX77,0) -> 0 | GR77: 1 | GS77: 2 | GT77: 0 | GV77: =ROUND((GT77),6) -> 0 | GW77: 1 | GX77: =ROUND(HC77*I77,2) -> 0 | HA77: 0 | HB77: 0 | HC77: =GV77*GW77 -> 0 | HE77: 0 | HF77: 2 | HS77: 0 | IK77: 0
A78: 18 | B78: 1 | C78: 62 | E78: 3,1 | F78: КА, п.5 | G78: Тактильно-визуальный знак "Туалет для инвалидов" | H78: ШТ | I78: =I76*J78 -> 1 | J78: 1 | K78: 1 | O78: =ROUND(CP78,2) -> 1346.01 | P78: =ROUND((ROUND((AC78*AW78*I78),2)*BC78),2) -> 1346.01 | Q78: =(ROUND((ROUND(((ET78)*AV78*I78),2)*BB78),2)+ROUND((ROUND(((AE78-(EU78))*AV78*I78),2)*BS78),2)) -> 0 | R78: =(ROUND((ROUND(((EU78)*AV78*I78),2)*BS78),2)+ROUND((ROUND(((AE78-(EU78))*AV78*I78),2)*BS78),2)) -> 0 | S78: =ROUND((ROUND((AF78*AV78*I78),2)*BA78),2) -> 0 | T78: =ROUND(CU78*I78,2) -> 0 | U78: =CV78*I78 -> 0 | V78: =CW78*I78 -> 0 | W78: =ROUND(CX78*I78,2) -> 0 | X78: =(ROUND((((S78+ROUND((ROUND(((EU78)*AV78*I78),2)*BS78),2))*AT78)/100),2)+ROUND(((ROUND((ROUND(((AE78-(EU78))*AV78*I78),2)*BS78),2)*AT78)/100),2)) -> 0 | Y78: =(ROUND((((S78+ROUND((ROUND(((EU78)*AV78*I78),2)*BS78),2))*AU78)/100),2)+ROUND(((ROUND((ROUND(((AE78-(EU78))*AV78*I78),2)*BS78),2)*AU78)/100),2)) -> 0 | AA78: 55938216 | AB78: =ROUND((AC78+AD78+AF78),6) -> 136.79 | AC78: =ROUND((ES78),6) -> 136.79 | AD78: =ROUND((((ET78)-(EU78))+AE78),6) -> 0 | AE78: =ROUND((EU78),6) -> 0 | AF78: =ROUND((EV78),6) -> 0 | AG78: =ROUND((AP78),6) -> 0 | AH78: =(EW78) -> 0 | AI78: =(EX78) -> 0 | AJ78: =(AS78) -> 0 | AK78: 136.79 | AL78: 136.79 | AM78: 0 | AN78: 0 | AO78: 0 | AP78: 0 | AQ78: 0 | AR78: 0 | AS78: 0 | AT78: 0 | AU78: 0 | AV78: 1 | AW78: 1 | AZ78: 1 | BA78: 1 | BB78: 1 | BC78: 9.84 | BH78: 3 | BI78: 1 | BJ78: КА, п.5 | BM78: 400005 | BN78: 0 | BP78: 0 | BQ78: 213 | BR78: 0 | BS78: 1 | BT78: 1 | BU78: 1 | BV78: 1 | BW78: 1 | BX78: 1 | BZ78: 84 | CA78: 53 | CE78: 1566 | CF78: 0 | CG78: 0 | CM78: 0 | CO78: 0 | CP78: =(P78+Q78+S78) -> 1346.01 | CQ78: =ROUND((ROUND((AC78*AW78*1),2)*BC78),2) -> 1346.01 | CR78: =(ROUND((ROUND(((ET78)*AV78*1),2)*BB78),2)+ROUND((ROUND(((AE78-(EU78))*AV78*1),2)*BS78),2)) -> 0 | CS78: =(ROUND((ROUND(((EU78)*AV78*1),2)*BS78),2)+ROUND((ROUND(((AE78-(EU78))*AV78*1),2)*BS78),2)) -> 0 | CT78: =ROUND((ROUND((AF78*AV78*1),2)*BA78),2) -> 0 | CU78: =AG78 -> 0 | CV78: =(AH78*AV78) -> 0 | CW78: =AI78 -> 0 | CX78: =AJ78 -> 0 | CY78: =(ROUND((((S78+ROUND((ROUND(((EU78)*AV78*1),2)*BS78),2))*AT78)/100),2)+ROUND(((ROUND((ROUND(((AE78-(EU78))*AV78*1),2)*BS78),2)*AT78)/100),2)) -> 0 | CZ78: =(ROUND((((S78+ROUND((ROUND(((EU78)*AV78*1),2)*BS78),2))*AU78)/100),2)+ROUND(((ROUND((ROUND(((AE78-(EU78))*AV78*1),2)*BS78),2)*AU78)/100),2)) -> 0 | DN78: 0 | DO78: 0 | DP78: 1 | DQ78: 1 | DU78: 1013 | DV78: ШТ | DW78: ШТ | DX78: 1 | EE78: 55393902 | EF78: 213 | EG78: Материалы, отсутствующие в СНБ (Строительные) | EH78: 0 | EJ78: 1 | EK78: 400005 | EL78: Материалы, отсутствующие в СНБ (Строительные) | EM78: МР КА Строительные | EQ78: 16 | ER78: 0 | ES78: 136.79 | ET78: 0 | EU78: 0 | EV78: 0 | EW78: 0 | EX78: 0 | EZ78: 5 | FC78: 1 | FD78: 18 | FF78: 1610 | FQ78: 0 | FR78: 0 | FS78: 0 | FX78: 84 | FY78: 53 | GA78: [1 610 / 1,22 / 9,84] + 2% Заг.скл | GD78: 1 | GF78: -999068521 | GG78: 2 | GH78: 3 | GI78: 5 | GJ78: 0 | GK78: 0 | GL78: =ROUND(IF(AND(BH78=3,BI78=3,FS78<>0),P78,0),2) -> 0 | GM78: =ROUND(O78+X78+Y78,2)+GX78 -> 1346.01 | GN78: =IF(OR(BI78=0,BI78=1),GM78-GX78,0) -> 1346.01 | GO78: =IF(BI78=2,GM78-GX78,0) -> 0 | GP78: =IF(BI78=4,GM78-GX78,0) -> 0 | GR78: 1 | GS78: 1 | GT78: 0 | GV78: =ROUND((GT78),6) -> 0 | GW78: 1 | GX78: =ROUND(HC78*I78,2) -> 0 | HA78: 0 | HB78: 0 | HC78: =GV78*GW78 -> 0 | HE78: 0 | HF78: 2 | HS78: 0 | IK78: 0
A80: 51 | B80: =B67 -> 1 | C80: =A67 -> 4 | D80: =ROW(A67) -> 67 | F80: =IF(F67<>"",F67,"") -> 1 | G80: =IF(G67<>"",G67,"") -> Оборудование санузла МГН (универсальная кабина) | H80: 0 | O80: =ROUND(AB80,2) -> 527.31 | P80: =ROUND(AC80,2) -> 495.12 | Q80: =ROUND(AD80,2) -> 1.01 | R80: =ROUND(AE80,2) -> 0.08 | S80: =ROUND(AF80,2) -> 31.18 | T80: =ROUND(AG80,2) -> 0 | U80: =AH80 -> 2.5248963 | V80: =AI80 -> 0 | W80: =ROUND(AJ80,2) -> 0 | X80: =ROUND(AK80,2) -> 31.15 | Y80: =ROUND(AL80,2) -> 18.14 | AB80: =ROUND(SUMIF(AA71:AA78,"=55938214",O71:O78),2) -> 527.31 | AC80: =ROUND(SUMIF(AA71:AA78,"=55938214",P71:P78),2) -> 495.12 | AD80: =ROUND(SUMIF(AA71:AA78,"=55938214",Q71:Q78),2) -> 1.01 | AE80: =ROUND(SUMIF(AA71:AA78,"=55938214",R71:R78),2) -> 0.08 | AF80: =ROUND(SUMIF(AA71:AA78,"=55938214",S71:S78),2) -> 31.18 | AG80: =ROUND(SUMIF(AA71:AA78,"=55938214",T71:T78),2) -> 0 | AH80: =SUMIF(AA71:AA78,"=55938214",U71:U78) -> 2.5248963 | AI80: =SUMIF(AA71:AA78,"=55938214",V71:V78) -> 0 | AJ80: =ROUND(SUMIF(AA71:AA78,"=55938214",W71:W78),2) -> 0 | AK80: =ROUND(SUMIF(AA71:AA78,"=55938214",X71:X78),2) -> 31.15 | AL80: =ROUND(SUMIF(AA71:AA78,"=55938214",Y71:Y78),2) -> 18.14 | AO80: =ROUND(BX80,2) -> 0 | AP80: =ROUND(BY80,2) -> 0 | AQ80: =ROUND(BZ80,2) -> 0 | AR80: =ROUND(CA80,2) -> 576.6 | AS80: =ROUND(CB80,2) -> 576.6 | AT80: =ROUND(CC80,2) -> 0 | AU80: =ROUND(CD80,2) -> 0 | AV80: =ROUND(CE80,2) -> 495.12 | ... BD80: =ROUND(CM80,2) -> 0 | BX80: =ROUND(SUMIF(AA71:AA78,"=55938214",FQ71:FQ78),2) -> 0 | BY80: =ROUND(SUMIF(AA71:AA78,"=55938214",FR71:FR78),2) -> 0 | BZ80: =ROUND(SUMIF(AA71:AA78,"=55938214",GL71:GL78),2) -> 0 | CA80: =ROUND(SUMIF(AA71:AA78,"=55938214",GM71:GM78),2) -> 576.6 | CB80: =ROUND(SUMIF(AA71:AA78,"=55938214",GN71:GN78),2) -> 576.6 | CC80: =ROUND(SUMIF(AA71:AA78,"=55938214",GO71:GO78),2) -> 0 | CD80: =ROUND(SUMIF(AA71:AA78,"=55938214",GP71:GP78),2) -> 0 | CE80: =AC80-BX80 -> 495.12 | CF80: =AC80-BY80 -> 495.12 | CG80: =BX80-BZ80 -> 0 | CH80: =AC80-BX80-BY80+BZ80 -> 495.12 | CI80: =BY80-BZ80 -> 0 | CJ80: =ROUND(SUMIF(AA71:AA78,"=55938214",GX71:GX78),2) -> 0 | CK80: =ROUND(SUMIF(AA71:AA78,"=55938214",GY71:GY78),2) -> 0 | CL80: =ROUND(SUMIF(AA71:AA78,"=55938214",GZ71:GZ78),2) -> 0 | CM80: =ROUND(SUMIF(AA71:AA78,"=55938214",HD71:HD78),2) -> 0 | DG80: =ROUND(DT80,2) -> 3378.96 | DH80: =ROUND(DU80,2) -> 1608.28 | DI80: =ROUND(DV80,2) -> 13.69 | DJ80: =ROUND(DW80,2) -> 4.51 | DK80: =ROUND(DX80,2) -> 1756.99 | DL80: =ROUND(DY80,2) -> 0 | DM80: =DZ80 -> 2.5248963 | DN80: =EA80 -> 0 | DO80: =ROUND(EB80,2) -> 0 | DP80: =ROUND(EC80,2) -> 1755.35 | DQ80: =ROUND(ED80,2) -> 1021.82 | DT80: =ROUND(SUMIF(AA71:AA78,"=55938216",O71:O78),2) -> 3378.96 | DU80: =ROUND(SUMIF(AA71:AA78,"=55938216",P71:P78),2) -> 1608.28 | DV80: =ROUND(SUMIF(AA71:AA78,"=55938216",Q71:Q78),2) -> 13.69 | DW80: =ROUND(SUMIF(AA71:AA78,"=55938216",R71:R78),2) -> 4.51 | DX80: =ROUND(SUMIF(AA71:AA78,"=55938216",S71:S78),2) -> 1756.99 | DY80: =ROUND(SUMIF(AA71:AA78,"=55938216",T71:T78),2) -> 0 | DZ80: =SUMIF(AA71:AA78,"=55938216",U71:U78) -> 2.5248963 | EA80: =SUMIF(AA71:AA78,"=55938216",V71:V78) -> 0 | EB80: =ROUND(SUMIF(AA71:AA78,"=55938216",W71:W78),2) -> 0 | EC80: =ROUND(SUMIF(AA71:AA78,"=55938216",X71:X78),2) -> 1755.35 | ED80: =ROUND(SUMIF(AA71:AA78,"=55938216",Y71:Y78),2) -> 1021.82 | EG80: =ROUND(FP80,2) -> 0 | EH80: =ROUND(FQ80,2) -> 0 | EI80: =ROUND(FR80,2) -> 0 | EJ80: =ROUND(FS80,2) -> 6156.13 | EK80: =ROUND(FT80,2) -> 6156.13 | EL80: =ROUND(FU80,2) -> 0 | EM80: =ROUND(FV80,2) -> 0 | EN80: =ROUND(FW80,2) -> 1608.28 | ... EV80: =ROUND(GE80,2) -> 0 | FP80: =ROUND(SUMIF(AA71:AA78,"=55938216",FQ71:FQ78),2) -> 0 | FQ80: =ROUND(SUMIF(AA71:AA78,"=55938216",FR71:FR78),2) -> 0 | FR80: =ROUND(SUMIF(AA71:AA78,"=55938216",GL71:GL78),2) -> 0 | FS80: =ROUND(SUMIF(AA71:AA78,"=55938216",GM71:GM78),2) -> 6156.13 | FT80: =ROUND(SUMIF(AA71:AA78,"=55938216",GN71:GN78),2) -> 6156.13 | FU80: =ROUND(SUMIF(AA71:AA78,"=55938216",GO71:GO78),2) -> 0 | FV80: =ROUND(SUMIF(AA71:AA78,"=55938216",GP71:GP78),2) -> 0 | FW80: =DU80-FP80 -> 1608.28 | FX80: =DU80-FQ80 -> 1608.28 | FY80: =FP80-FR80 -> 0 | FZ80: =DU80-FP80-FQ80+FR80 -> 1608.28 | GA80: =FQ80-FR80 -> 0 | GB80: =ROUND(SUMIF(AA71:AA78,"=55938216",GX71:GX78),2) -> 0 | GC80: =ROUND(SUMIF(AA71:AA78,"=55938216",GY71:GY78),2) -> 0 | GD80: =ROUND(SUMIF(AA71:AA78,"=55938216",GZ71:GZ78),2) -> 0 | GE80: =ROUND(SUMIF(AA71:AA78,"=55938216",HD71:HD78),2) -> 0 | GX80: 0
A82: 50 | B82: 0 | C82: 0 | D82: 1 | E82: 201 | F82: =ROUND(Source!O80,O82) -> 527.31 | G82: ПЗ | H82: Прямые затраты | K82: 201 | L82: 1 | M82: 3 | O82: 2 | P82: =ROUND(Source!DG80,O82) -> 3378.96 | W82: 527.31 | X82: 1 | Y82: 527.31 | Z82: 3378.96 | AA82: 1 | AB82: 3378.96
A83: 50 | B83: 0 | C83: 0 | D83: 1 | E83: 202 | F83: =ROUND(Source!P80,O83) -> 495.12 | G83: СтМатОб | H83: Стоимость материальных ресурсов (всего) | K83: 202 | L83: 2 | M83: 3 | O83: 2 | P83: =ROUND(Source!DH80,O83) -> 1608.28 | W83: 495.12 | X83: 1 | Y83: 495.12 | Z83: 1608.28 | AA83: 1 | AB83: 1608.28
A84: 50 | B84: 0 | C84: 0 | D84: 1 | E84: 222 | F84: =ROUND(Source!AO80,O84) -> 0 | G84: СтМатОбЗак | H84: Стоимость материалов и оборудования заказчика | K84: 222 | L84: 3 | M84: 3 | O84: 2 | P84: =ROUND(Source!EG80,O84) -> 0 | W84: 0 | X84: 1 | Y84: 0 | Z84: 0 | AA84: 1 | AB84: 0
A85: 50 | B85: 0 | C85: 0 | D85: 1 | E85: 225 | F85: =ROUND(Source!AV80,O85) -> 495.12 | G85: СтМатОбПод | H85: Стоимость материалов и оборудования подрядчика | K85: 225 | L85: 4 | M85: 3 | O85: 2 | P85: =ROUND(Source!EN80,O85) -> 1608.28 | W85: 495.12 | X85: 1 | Y85: 495.12 | Z85: 1608.28 | AA85: 1 | AB85: 1608.28
A86: 50 | B86: 0 | C86: 0 | D86: 1 | E86: 226 | F86: =ROUND(Source!AW80,O86) -> 495.12 | G86: СтМат | H86: Стоимость материалов (всего) | K86: 226 | L86: 5 | M86: 3 | O86: 2 | P86: =ROUND(Source!EO80,O86) -> 1608.28 | W86: 495.12 | X86: 1 | Y86: 495.12 | Z86: 1608.28 | AA86: 1 | AB86: 1608.28
A87: 50 | B87: 0 | C87: 0 | D87: 1 | E87: 227 | F87: =ROUND(Source!AX80,O87) -> 0 | G87: СтМатЗак | H87: Стоимость материалов заказчика | K87: 227 | L87: 6 | M87: 3 | O87: 2 | P87: =ROUND(Source!EP80,O87) -> 0 | W87: 0 | X87: 1 | Y87: 0 | Z87: 0 | AA87: 1 | AB87: 0
A88: 50 | B88: 0 | C88: 0 | D88: 1 | E88: 228 | F88: =ROUND(Source!AY80,O88) -> 495.12 | G88: СтМатПод | H88: Стоимость материалов подрядчика | K88: 228 | L88: 7 | M88: 3 | O88: 2 | P88: =ROUND(Source!EQ80,O88) -> 1608.28 | W88: 495.12 | X88: 1 | Y88: 495.12 | Z88: 1608.28 | AA88: 1 | AB88: 1608.28
A89: 50 | B89: 0 | C89: 0 | D89: 1 | E89: 216 | F89: =ROUND(Source!AP80,O89) -> 0 | G89: Оборуд | H89: Стоимость оборудования (всего) | K89: 216 | L89: 8 | M89: 3 | O89: 2 | P89: =ROUND(Source!EH80,O89) -> 0 | W89: 0 | X89: 1 | Y89: 0 | Z89: 0 | AA89: 1 | AB89: 0
A90: 50 | B90: 0 | C90: 0 | D90: 1 | E90: 223 | F90: =ROUND(Source!AQ80,O90) -> 0 | G90: ОборудЗак | H90: Стоимость оборудования заказчика | K90: 223 | L90: 9 | M90: 3 | O90: 2 | P90: =ROUND(Source!EI80,O90) -> 0 | W90: 0 | X90: 1 | Y90: 0 | Z90: 0 | AA90: 1 | AB90: 0
A91: 50 | B91: 0 | C91: 0 | D91: 1 | E91: 229 | F91: =ROUND(Source!AZ80,O91) -> 0 | G91: ОборудПод | H91: Стоимость оборудования подрядчика | K91: 229 | L91: 10 | M91: 3 | O91: 2 | P91: =ROUND(Source!ER80,O91) -> 0 | W91: 0 | X91: 1 | Y91: 0 | Z91: 0 | AA91: 1 | AB91: 0
A92: 50 | B92: 0 | C92: 0 | D92: 1 | E92: 203 | F92: =ROUND(Source!Q80,O92) -> 1.01 | G92: ЭММ | H92: Эксплуатация машин | K92: 203 | L92: 11 | M92: 3 | O92: 2 | P92: =ROUND(Source!DI80,O92) -> 13.69 | W92: 1.01 | X92: 1 | Y92: 1.01 | Z92: 13.69 | AA92: 1 | AB92: 13.69
A93: 50 | B93: 0 | C93: 0 | D93: 1 | E93: 231 | F93: =ROUND(Source!BB80,O93) -> 0 | G93: ЭММсНРиСП | H93: Эксплуатация машин по ТСН-2001.16 | K93: 231 | L93: 12 | M93: 3 | O93: 2 | P93: =ROUND(Source!ET80,O93) -> 0 | W93: 0 | X93: 1 | Y93: 0 | Z93: 0 | AA93: 1 | AB93: 0
A94: 50 | B94: 0 | C94: 0 | D94: 1 | E94: 204 | F94: =ROUND(Source!R80,O94) -> 0.08 | G94: ЗПМ | H94: ЗП машинистов | K94: 204 | L94: 13 | M94: 3 | O94: 2 | P94: =ROUND(Source!DJ80,O94) -> 4.51 | W94: 0.08 | X94: 1 | Y94: 0.08 | Z94: 4.51 | AA94: 1 | AB94: 4.51
A95: 50 | B95: 0 | C95: 0 | D95: 1 | E95: 205 | F95: =ROUND(Source!S80,O95) -> 31.18 | G95: ОЗП | H95: Основная ЗП рабочих | K95: 205 | L95: 14 | M95: 3 | O95: 2 | P95: =ROUND(Source!DK80,O95) -> 1756.99 | W95: 31.18 | X95: 1 | Y95: 31.18 | Z95: 1756.99 | AA95: 1 | AB95: 1756.99
A96: 50 | B96: 0 | C96: 0 | D96: 1 | E96: 232 | F96: =ROUND(Source!BC80,O96) -> 0 | G96: ОЗПсНРиСП | H96: Основная ЗП рабочих по ТСН-2001.16 | K96: 232 | L96: 15 | M96: 3 | O96: 2 | P96: =ROUND(Source!EU80,O96) -> 0 | W96: 0 | X96: 1 | Y96: 0 | Z96: 0 | AA96: 1 | AB96: 0
A97: 50 | B97: 0 | C97: 0 | D97: 1 | E97: 214 | F97: =ROUND(Source!AS80,O97) -> 576.6 | G97: Строит | H97: Строительные работы с НР и СП | K97: 214 | L97: 16 | M97: 3 | O97: 2 | P97: =ROUND(Source!EK80,O97) -> 6156.13 | W97: 576.6 | X97: 1 | Y97: 576.6 | Z97: 6156.13 | AA97: 1 | AB97: 6156.13
A98: 50 | B98: 0 | C98: 0 | D98: 1 | E98: 215 | F98: =ROUND(Source!AT80,O98) -> 0 | G98: Монтаж | H98: Монтажные работы с НР и СП | K98: 215 | L98: 17 | M98: 3 | O98: 2 | P98: =ROUND(Source!EL80,O98) -> 0 | W98: 0 | X98: 1 | Y98: 0 | Z98: 0 | AA98: 1 | AB98: 0
A99: 50 | B99: 0 | C99: 0 | D99: 1 | E99: 217 | F99: =ROUND(Source!AU80,O99) -> 0 | G99: Прочие | H99: Прочие работы с НР и СП | K99: 217 | L99: 18 | M99: 3 | O99: 2 | P99: =ROUND(Source!EM80,O99) -> 0 | W99: 0 | X99: 1 | Y99: 0 | Z99: 0 | AA99: 1 | AB99: 0
A100: 50 | B100: 0 | C100: 0 | D100: 1 | E100: 230 | F100: =ROUND(Source!BA80,O100) -> 0 | G100: ПрочиеЗатр | H100: Прочие затраты по ТСН-2001.16 | K100: 230 | L100: 19 | M100: 3 | O100: 2 | P100: =ROUND(Source!ES80,O100) -> 0 | W100: 0 | X100: 1 | Y100: 0 | Z100: 0 | AA100: 1 | AB100: 0
A101: 50 | B101: 0 | C101: 0 | D101: 1 | E101: 206 | F101: =ROUND(Source!T80,O101) -> 0 | G101: ВозврМат | H101: Возврат материалов | K101: 206 | L101: 20 | M101: 3 | O101: 2 | P101: =ROUND(Source!DL80,O101) -> 0 | W101: 0 | X101: 1 | Y101: 0 | Z101: 0 | AA101: 1 | AB101: 0
A102: 50 | B102: 0 | C102: 0 | D102: 1 | E102: 207 | F102: =Source!U80 -> 2.5248963 | G102: ТрудСтр | H102: Трудозатраты строителей | K102: 207 | L102: 21 | M102: 3 | O102: -1 | P102: =Source!DM80 -> 2.5248963 | W102: 2.5248963 | X102: 1 | Y102: 2.5248963 | Z102: 2.5248963 | AA102: 1 | AB102: 2.5248963
A103: 50 | B103: 0 | C103: 0 | D103: 1 | E103: 208 | F103: =Source!V80 -> 0 | G103: ТрудМаш | H103: Трудозатраты машинистов | K103: 208 | L103: 22 | M103: 3 | O103: -1 | P103: =Source!DN80 -> 0 | W103: 0 | X103: 1 | Y103: 0 | Z103: 0 | AA103: 1 | AB103: 0
A104: 50 | B104: 0 | C104: 0 | D104: 1 | E104: 209 | F104: =ROUND(Source!W80,O104) -> 0 | G104: ТранспМат | H104: Транспорт материалов | K104: 209 | L104: 23 | M104: 3 | O104: 2 | P104: =ROUND(Source!DO80,O104) -> 0 | W104: 0 | X104: 1 | Y104: 0 | Z104: 0 | AA104: 1 | AB104: 0
A105: 50 | B105: 0 | C105: 0 | D105: 1 | E105: 233 | F105: =ROUND(Source!BD80,O105) -> 0 | G105: Перевозка | H105: Перевозка грузов | K105: 233 | L105: 24 | M105: 3 | O105: 2 | P105: =ROUND(Source!EV80,O105) -> 0 | W105: 0 | X105: 1 | Y105: 0 | Z105: 0 | AA105: 1 | AB105: 0
A106: 50 | B106: 0 | C106: 0 | D106: 1 | E106: 210 | F106: =ROUND(Source!X80,O106) -> 31.15 | G106: НР | H106: Накладные расходы | K106: 210 | L106: 25 | M106: 3 | O106: 2 | P106: =ROUND(Source!DP80,O106) -> 1755.35 | W106: 31.15 | X106: 1 | Y106: 31.15 | Z106: 1755.35 | AA106: 1 | AB106: 1755.35
A107: 50 | B107: 0 | C107: 0 | D107: 1 | E107: 211 | F107: =ROUND(Source!Y80,O107) -> 18.14 | G107: СмПриб | H107: Сметная прибыль | K107: 211 | L107: 26 | M107: 3 | O107: 2 | P107: =ROUND(Source!DQ80,O107) -> 1021.82 | W107: 18.14 | X107: 1 | Y107: 18.14 | Z107: 1021.82 | AA107: 1 | AB107: 1021.82
A108: 50 | B108: 0 | C108: 0 | D108: 1 | E108: 224 | F108: =ROUND(Source!AR80,O108) -> 576.6 | G108: Всего | H108: Всего с НР и СП | K108: 224 | L108: 27 | M108: 3 | O108: 2 | P108: =ROUND(Source!EJ80,O108) -> 6156.13 | W108: 576.6 | X108: 1 | Y108: 576.6 | Z108: 6156.13 | AA108: 1 | AB108: 6156.13
A110: 4 | B110: 1 | D110: =ROW(A127) -> 127 | F110: 2 | G110: Оборудование не облагаемое НДС | I110: 0 | K110: -1 | S110: 0 | T110: 0 | V110: 0 | BX110: 0 | CJ110: 0
A112: 52 | B112: =B127 -> 1 | C112: =C127 -> 4 | D112: =D127 -> 110 | E112: =E127 -> 0 | F112: =F127 -> 2 | G112: =G127 -> Оборудование не облагаемое НДС | O112: =O127 -> 11616.18 | P112: =P127 -> 11616.18 | Q112: =Q127 -> 0 | R112: =R127 -> 0 | S112: =S127 -> 0 | T112: =T127 -> 0 | U112: =U127 -> 0 | V112: =V127 -> 0 | ... GX112: =GX127 -> 0
A114: 17 | B114: 1 | E114: 4 | F114: КА, п.1 | G114: Поручень откидной без бумагодержателя, 900х150 мм | H114: ШТ | I114: 1 | J114: 0 | K114: 1 | O114: =ROUND(CP114,2) -> 1532.56 | P114: =ROUND((ROUND((AC114*AW114*I114),2)*BC114),2) -> 1532.56 | Q114: =(ROUND((ROUND(((ET114)*AV114*I114),2)*BB114),2)+ROUND((ROUND(((AE114-(EU114))*AV114*I114),2)*BS114),2)) -> 0 | R114: =(ROUND((ROUND(((EU114)*AV114*I114),2)*BS114),2)+ROUND((ROUND(((AE114-(EU114))*AV114*I114),2)*BS114),2)) -> 0 | S114: =ROUND((ROUND((AF114*AV114*I114),2)*BA114),2) -> 0 | T114: =ROUND(CU114*I114,2) -> 0 | U114: =CV114*I114 -> 0 | V114: =CW114*I114 -> 0 | W114: =ROUND(CX114*I114,2) -> 0 | X114: =(ROUND((((S114+ROUND((ROUND(((EU114)*AV114*I114),2)*BS114),2))*AT114)/100),2)+ROUND(((ROUND((ROUND(((AE114-(EU114))*AV114*I114),2)*BS114),2)*AT114)/100),2)) -> 0 | Y114: =(ROUND((((S114+ROUND((ROUND(((EU114)*AV114*I114),2)*BS114),2))*AU114)/100),2)+ROUND(((ROUND((ROUND(((AE114-(EU114))*AV114*I114),2)*BS114),2)*AU114)/100),2)) -> 0 | AA114: 55938214 | AB114: =ROUND((AC114+AD114+AF114),6) -> 1532.56 | AC114: =ROUND((ES114),6) -> 1532.56 | AD114: =ROUND((((ET114)-(EU114))+AE114),6) -> 0 | AE114: =ROUND((EU114),6) -> 0 | AF114: =ROUND((EV114),6) -> 0 | AG114: =ROUND((AP114),6) -> 0 | AH114: =(EW114) -> 0 | AI114: =(EX114) -> 0 | AJ114: =(AS114) -> 0 | AK114: 1532.56 | AL114: 1532.56 | AM114: 0 | AN114: 0 | AO114: 0 | AP114: 0 | AQ114: 0 | AR114: 0 | AS114: 0 | AT114: 0 | AU114: 0 | AV114: 1 | AW114: 1 | AZ114: 1 | BA114: 1 | BB114: 1 | BC114: 1 | BH114: 3 | BI114: 3 | BJ114: КА, п.1 | BM114: 400007 | BN114: 0 | BP114: 0 | BQ114: 214 | BR114: 0 | BS114: 1 | BT114: 1 | BU114: 1 | BV114: 1 | BW114: 1 | BX114: 1 | BZ114: 0 | CA114: 0 | CE114: 1566 | CF114: 0 | CG114: 0 | CM114: 0 | CO114: 0 | CP114: =(P114+Q114+S114) -> 1532.56 | CQ114: =ROUND((ROUND((AC114*AW114*1),2)*BC114),2) -> 1532.56 | CR114: =(ROUND((ROUND(((ET114)*AV114*1),2)*BB114),2)+ROUND((ROUND(((AE114-(EU114))*AV114*1),2)*BS114),2)) -> 0 | CS114: =(ROUND((ROUND(((EU114)*AV114*1),2)*BS114),2)+ROUND((ROUND(((AE114-(EU114))*AV114*1),2)*BS114),2)) -> 0 | CT114: =ROUND((ROUND((AF114*AV114*1),2)*BA114),2) -> 0 | CU114: =AG114 -> 0 | CV114: =(AH114*AV114) -> 0 | CW114: =AI114 -> 0 | CX114: =AJ114 -> 0 | CY114: =(ROUND((((S114+ROUND((ROUND(((EU114)*AV114*1),2)*BS114),2))*AT114)/100),2)+ROUND(((ROUND((ROUND(((AE114-(EU114))*AV114*1),2)*BS114),2)*AT114)/100),2)) -> 0 | CZ114: =(ROUND((((S114+ROUND((ROUND(((EU114)*AV114*1),2)*BS114),2))*AU114)/100),2)+ROUND(((ROUND((ROUND(((AE114-(EU114))*AV114*1),2)*BS114),2)*AU114)/100),2)) -> 0 | DN114: 0 | DO114: 0 | DP114: 1 | DQ114: 1 | DU114: 1013 | DV114: ШТ | DW114: ШТ | DX114: 1 | EE114: 55393904 | EF114: 214 | EG114: Оборудование, отсутствующие в СНБ | EH114: 0 | EJ114: 3 | EK114: 400007 | EL114: Оборудование, отсутствующие в СНБ | EM114: Оборуд. КА | EQ114: 16 | ER114: 0 | ES114: 1532.56 | ET114: 0 | EU114: 0 | EV114: 0 | EW114: 0 | EX114: 0 | EY114: 0 | FQ114: 0 | FR114: =P114 -> 1532.56 | FS114: 0 | FX114: 0 | FY114: 0 | GA114: [11 130 / 7,57] + 3% Трансп + 1,2% Заг.скл | GD114: 1 | GF114: 296249389 | GG114: 2 | GH114: 4 | GI114: -2 | GJ114: 0 | GK114: 0 | GL114: =ROUND(IF(AND(BH114=3,BI114=3,FS114<>0),P114,0),2) -> 0 | GM114: =ROUND(O114+X114+Y114,2)+GX114 -> 1532.56 | GN114: =IF(OR(BI114=0,BI114=1),GM114-GX114,0) -> 0 | GO114: =IF(BI114=2,GM114-GX114,0) -> 0 | GP114: =IF(BI114=4,GM114-GX114,0) -> 0 | GR114: 0 | GS114: 2 | GT114: 0 | GV114: =ROUND((GT114),6) -> 0 | GW114: 1 | GX114: =ROUND(HC114*I114,2) -> 0 | HA114: 0 | HB114: 0 | HC114: =GV114*GW114 -> 0 | HE114: 3 | HF114: 1,2 | HS114: 0 | IK114: 0
A115: 17 | B115: 1 | E115: 4 | F115: КА, п.1 | G115: Поручень откидной без бумагодержателя, 900х150 мм | H115: ШТ | I115: 1 | J115: 0 | K115: 1 | O115: =ROUND(CP115,2) -> 11601.48 | P115: =ROUND((ROUND((AC115*AW115*I115),2)*BC115),2) -> 11601.48 | Q115: =(ROUND((ROUND(((ET115)*AV115*I115),2)*BB115),2)+ROUND((ROUND(((AE115-(EU115))*AV115*I115),2)*BS115),2)) -> 0 | R115: =(ROUND((ROUND(((EU115)*AV115*I115),2)*BS115),2)+ROUND((ROUND(((AE115-(EU115))*AV115*I115),2)*BS115),2)) -> 0 | S115: =ROUND((ROUND((AF115*AV115*I115),2)*BA115),2) -> 0 | T115: =ROUND(CU115*I115,2) -> 0 | U115: =CV115*I115 -> 0 | V115: =CW115*I115 -> 0 | W115: =ROUND(CX115*I115,2) -> 0 | X115: =(ROUND((((S115+ROUND((ROUND(((EU115)*AV115*I115),2)*BS115),2))*AT115)/100),2)+ROUND(((ROUND((ROUND(((AE115-(EU115))*AV115*I115),2)*BS115),2)*AT115)/100),2)) -> 0 | Y115: =(ROUND((((S115+ROUND((ROUND(((EU115)*AV115*I115),2)*BS115),2))*AU115)/100),2)+ROUND(((ROUND((ROUND(((AE115-(EU115))*AV115*I115),2)*BS115),2)*AU115)/100),2)) -> 0 | AA115: 55938216 | AB115: =ROUND((AC115+AD115+AF115),6) -> 1532.56 | AC115: =ROUND((ES115),6) -> 1532.56 | AD115: =ROUND((((ET115)-(EU115))+AE115),6) -> 0 | AE115: =ROUND((EU115),6) -> 0 | AF115: =ROUND((EV115),6) -> 0 | AG115: =ROUND((AP115),6) -> 0 | AH115: =(EW115) -> 0 | AI115: =(EX115) -> 0 | AJ115: =(AS115) -> 0 | AK115: 1532.56 | AL115: 1532.56 | AM115: 0 | AN115: 0 | AO115: 0 | AP115: 0 | AQ115: 0 | AR115: 0 | AS115: 0 | AT115: 0 | AU115: 0 | AV115: 1 | AW115: 1 | AZ115: 1 | BA115: 1 | BB115: 1 | BC115: 7.57 | BH115: 3 | BI115: 3 | BJ115: КА, п.1 | BM115: 400007 | BN115: 0 | BP115: 0 | BQ115: 214 | BR115: 0 | BS115: 1 | BT115: 1 | BU115: 1 | BV115: 1 | BW115: 1 | BX115: 1 | BZ115: 0 | CA115: 0 | CE115: 1566 | CF115: 0 | CG115: 0 | CM115: 0 | CO115: 0 | CP115: =(P115+Q115+S115) -> 11601.48 | CQ115: =ROUND((ROUND((AC115*AW115*1),2)*BC115),2) -> 11601.48 | CR115: =(ROUND((ROUND(((ET115)*AV115*1),2)*BB115),2)+ROUND((ROUND(((AE115-(EU115))*AV115*1),2)*BS115),2)) -> 0 | CS115: =(ROUND((ROUND(((EU115)*AV115*1),2)*BS115),2)+ROUND((ROUND(((AE115-(EU115))*AV115*1),2)*BS115),2)) -> 0 | CT115: =ROUND((ROUND((AF115*AV115*1),2)*BA115),2) -> 0 | CU115: =AG115 -> 0 | CV115: =(AH115*AV115) -> 0 | CW115: =AI115 -> 0 | CX115: =AJ115 -> 0 | CY115: =(ROUND((((S115+ROUND((ROUND(((EU115)*AV115*1),2)*BS115),2))*AT115)/100),2)+ROUND(((ROUND((ROUND(((AE115-(EU115))*AV115*1),2)*BS115),2)*AT115)/100),2)) -> 0 | CZ115: =(ROUND((((S115+ROUND((ROUND(((EU115)*AV115*1),2)*BS115),2))*AU115)/100),2)+ROUND(((ROUND((ROUND(((AE115-(EU115))*AV115*1),2)*BS115),2)*AU115)/100),2)) -> 0 | DN115: 0 | DO115: 0 | DP115: 1 | DQ115: 1 | DU115: 1013 | DV115: ШТ | DW115: ШТ | DX115: 1 | EE115: 55393904 | EF115: 214 | EG115: Оборудование, отсутствующие в СНБ | EH115: 0 | EJ115: 3 | EK115: 400007 | EL115: Оборудование, отсутствующие в СНБ | EM115: Оборуд. КА | EQ115: 16 | ER115: 1532.56 | ES115: 1532.56 | ET115: 0 | EU115: 0 | EV115: 0 | EW115: 0 | EX115: 0 | EY115: 0 | EZ115: 5 | FC115: 0 | FD115: 18 | FF115: 11130 | FQ115: 0 | FR115: =P115 -> 11601.48 | FS115: 0 | FX115: 0 | FY115: 0 | GA115: [11 130 / 7,57] + 3% Трансп + 1,2% Заг.скл | GD115: 1 | GF115: 296249389 | GG115: 2 | GH115: 3 | GI115: 5 | GJ115: 0 | GK115: 0 | GL115: =ROUND(IF(AND(BH115=3,BI115=3,FS115<>0),P115,0),2) -> 0 | GM115: =ROUND(O115+X115+Y115,2)+GX115 -> 11601.48 | GN115: =IF(OR(BI115=0,BI115=1),GM115-GX115,0) -> 0 | GO115: =IF(BI115=2,GM115-GX115,0) -> 0 | GP115: =IF(BI115=4,GM115-GX115,0) -> 0 | GR115: 1 | GS115: 1 | GT115: 0 | GV115: =ROUND((GT115),6) -> 0 | GW115: 1 | GX115: =ROUND(HC115*I115,2) -> 0 | HA115: 0 | HB115: 0 | HC115: =GV115*GW115 -> 0 | HE115: 3 | HF115: 1,2 | HS115: 0 | IK115: 0
A116: 17 | B116: 1 | E116: 5 | F116: КА, п.2 | G116: Поручень для туалета напольный для инвалидов h-образный с бумагодержателем 900х750мм универсальный | H116: ШТ | I116: 1 | J116: 0 | K116: 1 | O116: =ROUND(CP116,2) -> 1069.9 | P116: =ROUND((ROUND((AC116*AW116*I116),2)*BC116),2) -> 1069.9 | Q116: =(ROUND((ROUND(((ET116)*AV116*I116),2)*BB116),2)+ROUND((ROUND(((AE116-(EU116))*AV116*I116),2)*BS116),2)) -> 0 | R116: =(ROUND((ROUND(((EU116)*AV116*I116),2)*BS116),2)+ROUND((ROUND(((AE116-(EU116))*AV116*I116),2)*BS116),2)) -> 0 | S116: =ROUND((ROUND((AF116*AV116*I116),2)*BA116),2) -> 0 | T116: =ROUND(CU116*I116,2) -> 0 | U116: =CV116*I116 -> 0 | V116: =CW116*I116 -> 0 | W116: =ROUND(CX116*I116,2) -> 0 | X116: =(ROUND((((S116+ROUND((ROUND(((EU116)*AV116*I116),2)*BS116),2))*AT116)/100),2)+ROUND(((ROUND((ROUND(((AE116-(EU116))*AV116*I116),2)*BS116),2)*AT116)/100),2)) -> 0 | Y116: =(ROUND((((S116+ROUND((ROUND(((EU116)*AV116*I116),2)*BS116),2))*AU116)/100),2)+ROUND(((ROUND((ROUND(((AE116-(EU116))*AV116*I116),2)*BS116),2)*AU116)/100),2)) -> 0 | AA116: 55938214 | AB116: =ROUND((AC116+AD116+AF116),6) -> 1069.9 | AC116: =ROUND((ES116),6) -> 1069.9 | AD116: =ROUND((((ET116)-(EU116))+AE116),6) -> 0 | AE116: =ROUND((EU116),6) -> 0 | AF116: =ROUND((EV116),6) -> 0 | AG116: =ROUND((AP116),6) -> 0 | AH116: =(EW116) -> 0 | AI116: =(EX116) -> 0 | AJ116: =(AS116) -> 0 | AK116: 1069.9 | AL116: 1069.9 | AM116: 0 | AN116: 0 | AO116: 0 | AP116: 0 | AQ116: 0 | AR116: 0 | AS116: 0 | AT116: 0 | AU116: 0 | AV116: 1 | AW116: 1 | AZ116: 1 | BA116: 1 | BB116: 1 | BC116: 1 | BH116: 3 | BI116: 3 | BJ116: КА, п.2 | BM116: 400007 | BN116: 0 | BP116: 0 | BQ116: 214 | BR116: 0 | BS116: 1 | BT116: 1 | BU116: 1 | BV116: 1 | BW116: 1 | BX116: 1 | BZ116: 0 | CA116: 0 | CE116: 1566 | CF116: 0 | CG116: 0 | CM116: 0 | CO116: 0 | CP116: =(P116+Q116+S116) -> 1069.9 | CQ116: =ROUND((ROUND((AC116*AW116*1),2)*BC116),2) -> 1069.9 | CR116: =(ROUND((ROUND(((ET116)*AV116*1),2)*BB116),2)+ROUND((ROUND(((AE116-(EU116))*AV116*1),2)*BS116),2)) -> 0 | CS116: =(ROUND((ROUND(((EU116)*AV116*1),2)*BS116),2)+ROUND((ROUND(((AE116-(EU116))*AV116*1),2)*BS116),2)) -> 0 | CT116: =ROUND((ROUND((AF116*AV116*1),2)*BA116),2) -> 0 | CU116: =AG116 -> 0 | CV116: =(AH116*AV116) -> 0 | CW116: =AI116 -> 0 | CX116: =AJ116 -> 0 | CY116: =(ROUND((((S116+ROUND((ROUND(((EU116)*AV116*1),2)*BS116),2))*AT116)/100),2)+ROUND(((ROUND((ROUND(((AE116-(EU116))*AV116*1),2)*BS116),2)*AT116)/100),2)) -> 0 | CZ116: =(ROUND((((S116+ROUND((ROUND(((EU116)*AV116*1),2)*BS116),2))*AU116)/100),2)+ROUND(((ROUND((ROUND(((AE116-(EU116))*AV116*1),2)*BS116),2)*AU116)/100),2)) -> 0 | DN116: 0 | DO116: 0 | DP116: 1 | DQ116: 1 | DU116: 1013 | DV116: ШТ | DW116: ШТ | DX116: 1 | EE116: 55393904 | EF116: 214 | EG116: Оборудование, отсутствующие в СНБ | EH116: 0 | EJ116: 3 | EK116: 400007 | EL116: Оборудование, отсутствующие в СНБ | EM116: Оборуд. КА | EQ116: 16 | ER116: 0 | ES116: 1069.9 | ET116: 0 | EU116: 0 | EV116: 0 | EW116: 0 | EX116: 0 | EY116: 0 | FQ116: 0 | FR116: =P116 -> 1069.9 | FS116: 0 | FX116: 0 | FY116: 0 | GA116: [7 770 / 7,57] + 3% Трансп + 1,2% Заг.скл | GD116: 1 | GF116: 906605270 | GG116: 2 | GH116: 4 | GI116: -2 | GJ116: 0 | GK116: 0 | GL116: =ROUND(IF(AND(BH116=3,BI116=3,FS116<>0),P116,0),2) -> 0 | GM116: =ROUND(O116+X116+Y116,2)+GX116 -> 1069.9 | GN116: =IF(OR(BI116=0,BI116=1),GM116-GX116,0) -> 0 | GO116: =IF(BI116=2,GM116-GX116,0) -> 0 | GP116: =IF(BI116=4,GM116-GX116,0) -> 0 | GR116: 0 | GS116: 2 | GT116: 0 | GV116: =ROUND((GT116),6) -> 0 | GW116: 1 | GX116: =ROUND(HC116*I116,2) -> 0 | HA116: 0 | HB116: 0 | HC116: =GV116*GW116 -> 0 | HE116: 3 | HF116: 1,2 | HS116: 0 | IK116: 0
A117: 17 | B117: 1 | E117: 5 | F117: КА, п.2 | G117: Поручень для туалета напольный для инвалидов h-образный с бумагодержателем 900х750мм универсальный | H117: ШТ | I117: 1 | J117: 0 | K117: 1 | O117: =ROUND(CP117,2) -> 8099.14 | P117: =ROUND((ROUND((AC117*AW117*I117),2)*BC117),2) -> 8099.14 | Q117: =(ROUND((ROUND(((ET117)*AV117*I117),2)*BB117),2)+ROUND((ROUND(((AE117-(EU117))*AV117*I117),2)*BS117),2)) -> 0 | R117: =(ROUND((ROUND(((EU117)*AV117*I117),2)*BS117),2)+ROUND((ROUND(((AE117-(EU117))*AV117*I117),2)*BS117),2)) -> 0 | S117: =ROUND((ROUND((AF117*AV117*I117),2)*BA117),2) -> 0 | T117: =ROUND(CU117*I117,2) -> 0 | U117: =CV117*I117 -> 0 | V117: =CW117*I117 -> 0 | W117: =ROUND(CX117*I117,2) -> 0 | X117: =(ROUND((((S117+ROUND((ROUND(((EU117)*AV117*I117),2)*BS117),2))*AT117)/100),2)+ROUND(((ROUND((ROUND(((AE117-(EU117))*AV117*I117),2)*BS117),2)*AT117)/100),2)) -> 0 | Y117: =(ROUND((((S117+ROUND((ROUND(((EU117)*AV117*I117),2)*BS117),2))*AU117)/100),2)+ROUND(((ROUND((ROUND(((AE117-(EU117))*AV117*I117),2)*BS117),2)*AU117)/100),2)) -> 0 | AA117: 55938216 | AB117: =ROUND((AC117+AD117+AF117),6) -> 1069.9 | AC117: =ROUND((ES117),6) -> 1069.9 | AD117: =ROUND((((ET117)-(EU117))+AE117),6) -> 0 | AE117: =ROUND((EU117),6) -> 0 | AF117: =ROUND((EV117),6) -> 0 | AG117: =ROUND((AP117),6) -> 0 | AH117: =(EW117) -> 0 | AI117: =(EX117) -> 0 | AJ117: =(AS117) -> 0 | AK117: 1069.9 | AL117: 1069.9 | AM117: 0 | AN117: 0 | AO117: 0 | AP117: 0 | AQ117: 0 | AR117: 0 | AS117: 0 | AT117: 0 | AU117: 0 | AV117: 1 | AW117: 1 | AZ117: 1 | BA117: 1 | BB117: 1 | BC117: 7.57 | BH117: 3 | BI117: 3 | BJ117: КА, п.2 | BM117: 400007 | BN117: 0 | BP117: 0 | BQ117: 214 | BR117: 0 | BS117: 1 | BT117: 1 | BU117: 1 | BV117: 1 | BW117: 1 | BX117: 1 | BZ117: 0 | CA117: 0 | CE117: 1566 | CF117: 0 | CG117: 0 | CM117: 0 | CO117: 0 | CP117: =(P117+Q117+S117) -> 8099.14 | CQ117: =ROUND((ROUND((AC117*AW117*1),2)*BC117),2) -> 8099.14 | CR117: =(ROUND((ROUND(((ET117)*AV117*1),2)*BB117),2)+ROUND((ROUND(((AE117-(EU117))*AV117*1),2)*BS117),2)) -> 0 | CS117: =(ROUND((ROUND(((EU117)*AV117*1),2)*BS117),2)+ROUND((ROUND(((AE117-(EU117))*AV117*1),2)*BS117),2)) -> 0 | CT117: =ROUND((ROUND((AF117*AV117*1),2)*BA117),2) -> 0 | CU117: =AG117 -> 0 | CV117: =(AH117*AV117) -> 0 | CW117: =AI117 -> 0 | CX117: =AJ117 -> 0 | CY117: =(ROUND((((S117+ROUND((ROUND(((EU117)*AV117*1),2)*BS117),2))*AT117)/100),2)+ROUND(((ROUND((ROUND(((AE117-(EU117))*AV117*1),2)*BS117),2)*AT117)/100),2)) -> 0 | CZ117: =(ROUND((((S117+ROUND((ROUND(((EU117)*AV117*1),2)*BS117),2))*AU117)/100),2)+ROUND(((ROUND((ROUND(((AE117-(EU117))*AV117*1),2)*BS117),2)*AU117)/100),2)) -> 0 | DN117: 0 | DO117: 0 | DP117: 1 | DQ117: 1 | DU117: 1013 | DV117: ШТ | DW117: ШТ | DX117: 1 | EE117: 55393904 | EF117: 214 | EG117: Оборудование, отсутствующие в СНБ | EH117: 0 | EJ117: 3 | EK117: 400007 | EL117: Оборудование, отсутствующие в СНБ | EM117: Оборуд. КА | EQ117: 16 | ER117: 1069.9 | ES117: 1069.9 | ET117: 0 | EU117: 0 | EV117: 0 | EW117: 0 | EX117: 0 | EY117: 0 | EZ117: 5 | FC117: 0 | FD117: 18 | FF117: 7770 | FQ117: 0 | FR117: =P117 -> 8099.14 | FS117: 0 | FX117: 0 | FY117: 0 | GA117: [7 770 / 7,57] + 3% Трансп + 1,2% Заг.скл | GD117: 1 | GF117: 906605270 | GG117: 2 | GH117: 3 | GI117: 5 | GJ117: 0 | GK117: 0 | GL117: =ROUND(IF(AND(BH117=3,BI117=3,FS117<>0),P117,0),2) -> 0 | GM117: =ROUND(O117+X117+Y117,2)+GX117 -> 8099.14 | GN117: =IF(OR(BI117=0,BI117=1),GM117-GX117,0) -> 0 | GO117: =IF(BI117=2,GM117-GX117,0) -> 0 | GP117: =IF(BI117=4,GM117-GX117,0) -> 0 | GR117: 1 | GS117: 1 | GT117: 0 | GV117: =ROUND((GT117),6) -> 0 | GW117: 1 | GX117: =ROUND(HC117*I117,2) -> 0 | HA117: 0 | HB117: 0 | HC117: =GV117*GW117 -> 0 | HE117: 3 | HF117: 1,2 | HS117: 0 | IK117: 0
A118: 17 | B118: 1 | E118: 6 | F118: 13.3-11-80 | G118: Поручень реабилитационный односекционный, для установки около умывальника, габаритные размеры 700х260 мм. Материал сталь нержавеющая с полировкой, крепление к стене в двух точках, в комплекте: прокладки-амортизаторы резиновые, крепежные элементы | H118: КОМПЛЕКТ | I118: 2 | J118: 0 | K118: 2 | O118: =ROUND(CP118,2) -> 4690.62 | P118: =ROUND((ROUND((AC118*I118),2)*BC118),2) -> 4690.62 | Q118: =(ROUND((ROUND(((ET118)*AV118*I118),2)*BB118),2)+ROUND((ROUND(((AE118-(EU118))*AV118*I118),2)*BS118),2)) -> 0 | R118: =(ROUND((ROUND(((EU118)*AV118*I118),2)*BS118),2)+ROUND((ROUND(((AE118-(EU118))*AV118*I118),2)*BS118),2)) -> 0 | S118: =ROUND((ROUND((AF118*AV118*I118),2)*BA118),2) -> 0 | T118: =ROUND(CU118*I118,2) -> 0 | U118: =CV118*I118 -> 0 | V118: =CW118*I118 -> 0 | W118: =ROUND(CX118*I118,2) -> 0 | X118: =(ROUND((((S118+ROUND((ROUND(((EU118)*AV118*I118),2)*BS118),2))*AT118)/100),2)+ROUND(((ROUND((ROUND(((AE118-(EU118))*AV118*I118),2)*BS118),2)*AT118)/100),2)) -> 0 | Y118: =(ROUND((((S118+ROUND((ROUND(((EU118)*AV118*I118),2)*BS118),2))*AU118)/100),2)+ROUND(((ROUND((ROUND(((AE118-(EU118))*AV118*I118),2)*BS118),2)*AU118)/100),2)) -> 0 | AA118: 55938214 | AB118: =ROUND((AC118+AD118+AF118),6) -> 2345.31 | AC118: =ROUND((ES118),6) -> 2345.31 | AD118: =ROUND((((ET118)-(EU118))+AE118),6) -> 0 | AE118: =ROUND((EU118),6) -> 0 | AF118: =ROUND((EV118),6) -> 0 | AG118: =ROUND((AP118),6) -> 0 | AH118: =(EW118) -> 0 | AI118: =(EX118) -> 0 | AJ118: =(AS118) -> 0 | AK118: 2345.31 | AL118: 2345.31 | AM118: 0 | AN118: 0 | AO118: 0 | AP118: 0 | AQ118: 0 | AR118: 0 | AS118: 0 | AT118: 0 | AU118: 0 | AV118: 1 | AW118: 1 | AZ118: 1 | BA118: 1 | BB118: 1 | BC118: 1 | BH118: 3 | BI118: 3 | BJ118: ТСН-2001.13-2. Доп. 35. 13.3-11-80 | BM118: 746 | BN118: 0 | BP118: 0 | BQ118: 130 | BR118: 0 | BS118: 1 | BT118: 1 | BU118: 1 | BV118: 1 | BW118: 1 | BX118: 1 | BZ118: 0 | CA118: 0 | CE118: 1566 | CF118: 0 | CG118: 0 | CM118: 0 | CO118: 0 | CP118: =(P118+Q118+S118) -> 4690.62 | CQ118: =ROUND((ROUND((AC118*1),2)*BC118),2) -> 2345.31 | CR118: =(ROUND((ROUND(((ET118)*AV118*1),2)*BB118),2)+ROUND((ROUND(((AE118-(EU118))*AV118*1),2)*BS118),2)) -> 0 | CS118: =(ROUND((ROUND(((EU118)*AV118*1),2)*BS118),2)+ROUND((ROUND(((AE118-(EU118))*AV118*1),2)*BS118),2)) -> 0 | CT118: =ROUND((ROUND((AF118*AV118*1),2)*BA118),2) -> 0 | CU118: =AG118 -> 0 | CV118: =(AH118*AV118) -> 0 | CW118: =AI118 -> 0 | CX118: =AJ118 -> 0 | CY118: =(ROUND((((S118+ROUND((ROUND(((EU118)*AV118*1),2)*BS118),2))*AT118)/100),2)+ROUND(((ROUND((ROUND(((AE118-(EU118))*AV118*1),2)*BS118),2)*AT118)/100),2)) -> 0 | CZ118: =(ROUND((((S118+ROUND((ROUND(((EU118)*AV118*1),2)*BS118),2))*AU118)/100),2)+ROUND(((ROUND((ROUND(((AE118-(EU118))*AV118*1),2)*BS118),2)*AU118)/100),2)) -> 0 | DN118: 0 | DO118: 0 | DP118: 1 | DQ118: 1 | DU118: 1013 | DV118: КОМПЛЕКТ | DW118: КОМПЛЕКТ | DX118: 1 | EE118: 55393877 | EF118: 130 | EG118: Сметная стоимость оборудования | EH118: 0 | EJ118: 3 | EK118: 746 | EL118: ТСН-2001.13. Сметная стоимость оборудования | EM118: ТСН-2001.13 | EQ118: 0 | ER118: 2345.31 | ES118: 2345.31 | ET118: 0 | EU118: 0 | EV118: 0 | EW118: 0 | EX118: 0 | EY118: 0 | FQ118: 0 | FR118: =P118 -> 4690.62 | FS118: 0 | FX118: 0 | FY118: 0 | GD118: 1 | GF118: -1997495816 | GG118: 2 | GH118: 1 | GI118: -2 | GJ118: 0 | GK118: 0 | GL118: =ROUND(IF(AND(BH118=3,BI118=3,FS118<>0),P118,0),2) -> 0 | GM118: =ROUND(O118+X118+Y118,2)+GX118 -> 4690.62 | GN118: =IF(OR(BI118=0,BI118=1),GM118-GX118,0) -> 0 | GO118: =IF(BI118=2,GM118-GX118,0) -> 0 | GP118: =IF(BI118=4,GM118-GX118,0) -> 0 | GR118: 0 | GS118: 3 | GT118: 0 | GV118: =ROUND((GT118),6) -> 0 | GW118: 1 | GX118: =ROUND(HC118*I118,2) -> 0 | HA118: 0 | HB118: 0 | HC118: =GV118*GW118 -> 0 | HS118: 0 | IK118: 0
A119: 17 | B119: 1 | E119: 6 | F119: 13.3-11-80 | G119: Поручень реабилитационный односекционный, для установки около умывальника, габаритные размеры 700х260 мм. Материал сталь нержавеющая с полировкой, крепление к стене в двух точках, в комплекте: прокладки-амортизаторы резиновые, крепежные элементы | H119: КОМПЛЕКТ | I119: 2 | J119: 0 | K119: 2 | O119: =ROUND(CP119,2) -> 18246.51 | P119: =ROUND((ROUND((AC119*I119),2)*BC119),2) -> 18246.51 | Q119: =(ROUND((ROUND(((ET119)*AV119*I119),2)*BB119),2)+ROUND((ROUND(((AE119-(EU119))*AV119*I119),2)*BS119),2)) -> 0 | R119: =(ROUND((ROUND(((EU119)*AV119*I119),2)*BS119),2)+ROUND((ROUND(((AE119-(EU119))*AV119*I119),2)*BS119),2)) -> 0 | S119: =ROUND((ROUND((AF119*AV119*I119),2)*BA119),2) -> 0 | T119: =ROUND(CU119*I119,2) -> 0 | U119: =CV119*I119 -> 0 | V119: =CW119*I119 -> 0 | W119: =ROUND(CX119*I119,2) -> 0 | X119: =(ROUND((((S119+ROUND((ROUND(((EU119)*AV119*I119),2)*BS119),2))*AT119)/100),2)+ROUND(((ROUND((ROUND(((AE119-(EU119))*AV119*I119),2)*BS119),2)*AT119)/100),2)) -> 0 | Y119: =(ROUND((((S119+ROUND((ROUND(((EU119)*AV119*I119),2)*BS119),2))*AU119)/100),2)+ROUND(((ROUND((ROUND(((AE119-(EU119))*AV119*I119),2)*BS119),2)*AU119)/100),2)) -> 0 | AA119: 55938216 | AB119: =ROUND((AC119+AD119+AF119),6) -> 2345.31 | AC119: =ROUND((ES119),6) -> 2345.31 | AD119: =ROUND((((ET119)-(EU119))+AE119),6) -> 0 | AE119: =ROUND((EU119),6) -> 0 | AF119: =ROUND((EV119),6) -> 0 | AG119: =ROUND((AP119),6) -> 0 | AH119: =(EW119) -> 0 | AI119: =(EX119) -> 0 | AJ119: =(AS119) -> 0 | AK119: 2345.31 | AL119: 2345.31 | AM119: 0 | AN119: 0 | AO119: 0 | AP119: 0 | AQ119: 0 | AR119: 0 | AS119: 0 | AT119: 0 | AU119: 0 | AV119: 1 | AW119: 1 | AZ119: 1 | BA119: 1 | BB119: 1 | BC119: 3.89 | BH119: 3 | BI119: 3 | BJ119: ТСН-2001.13-2. Доп. 35. 13.3-11-80 | BM119: 746 | BN119: 0 | BP119: 0 | BQ119: 130 | BR119: 0 | BS119: 1 | BT119: 1 | BU119: 1 | BV119: 1 | BW119: 1 | BX119: 1 | BZ119: 0 | CA119: 0 | CE119: 1566 | CF119: 0 | CG119: 0 | CM119: 0 | CO119: 0 | CP119: =(P119+Q119+S119) -> 18246.51 | CQ119: =ROUND((ROUND((AC119*1),2)*BC119),2) -> 9123.26 | CR119: =(ROUND((ROUND(((ET119)*AV119*1),2)*BB119),2)+ROUND((ROUND(((AE119-(EU119))*AV119*1),2)*BS119),2)) -> 0 | CS119: =(ROUND((ROUND(((EU119)*AV119*1),2)*BS119),2)+ROUND((ROUND(((AE119-(EU119))*AV119*1),2)*BS119),2)) -> 0 | CT119: =ROUND((ROUND((AF119*AV119*1),2)*BA119),2) -> 0 | CU119: =AG119 -> 0 | CV119: =(AH119*AV119) -> 0 | CW119: =AI119 -> 0 | CX119: =AJ119 -> 0 | CY119: =(ROUND((((S119+ROUND((ROUND(((EU119)*AV119*1),2)*BS119),2))*AT119)/100),2)+ROUND(((ROUND((ROUND(((AE119-(EU119))*AV119*1),2)*BS119),2)*AT119)/100),2)) -> 0 | CZ119: =(ROUND((((S119+ROUND((ROUND(((EU119)*AV119*1),2)*BS119),2))*AU119)/100),2)+ROUND(((ROUND((ROUND(((AE119-(EU119))*AV119*1),2)*BS119),2)*AU119)/100),2)) -> 0 | DN119: 0 | DO119: 0 | DP119: 1 | DQ119: 1 | DU119: 1013 | DV119: КОМПЛЕКТ | DW119: КОМПЛЕКТ | DX119: 1 | EE119: 55393877 | EF119: 130 | EG119: Сметная стоимость оборудования | EH119: 0 | EJ119: 3 | EK119: 746 | EL119: ТСН-2001.13. Сметная стоимость оборудования | EM119: ТСН-2001.13 | EQ119: 0 | ER119: 2345.31 | ES119: 2345.31 | ET119: 0 | EU119: 0 | EV119: 0 | EW119: 0 | EX119: 0 | EY119: 0 | FQ119: 0 | FR119: =P119 -> 18246.51 | FS119: 0 | FX119: 0 | FY119: 0 | GD119: 1 | GF119: -1997495816 | GG119: 2 | GH119: 1 | GI119: 2 | GJ119: 0 | GK119: 0 | GL119: =ROUND(IF(AND(BH119=3,BI119=3,FS119<>0),P119,0),2) -> 0 | GM119: =ROUND(O119+X119+Y119,2)+GX119 -> 18246.51 | GN119: =IF(OR(BI119=0,BI119=1),GM119-GX119,0) -> 0 | GO119: =IF(BI119=2,GM119-GX119,0) -> 0 | GP119: =IF(BI119=4,GM119-GX119,0) -> 0 | GR119: 0 | GS119: 3 | GT119: 0 | GV119: =ROUND((GT119),6) -> 0 | GW119: 1 | GX119: =ROUND(HC119*I119,2) -> 0 | HA119: 0 | HB119: 0 | HC119: =GV119*GW119 -> 0 | HS119: 0 | IK119: 0
A120: 17 | B120: 1 | E120: 7 | F120: 13.3-11-67 | G120: Крючок для подвески костылей, габаритные размеры 120х32 мм. Материал сталь нержавеющая с полировкой, крепление на стену, в комплекте: прокладки-амортизаторы резиновые, крепежные элементы | H120: КОМПЛЕКТ | I120: 1 | J120: 0 | K120: 1 | O120: =ROUND(CP120,2) -> 573.3 | P120: =ROUND((ROUND((AC120*I120),2)*BC120),2) -> 573.3 | Q120: =(ROUND((ROUND(((ET120)*AV120*I120),2)*BB120),2)+ROUND((ROUND(((AE120-(EU120))*AV120*I120),2)*BS120),2)) -> 0 | R120: =(ROUND((ROUND(((EU120)*AV120*I120),2)*BS120),2)+ROUND((ROUND(((AE120-(EU120))*AV120*I120),2)*BS120),2)) -> 0 | S120: =ROUND((ROUND((AF120*AV120*I120),2)*BA120),2) -> 0 | T120: =ROUND(CU120*I120,2) -> 0 | U120: =CV120*I120 -> 0 | V120: =CW120*I120 -> 0 | W120: =ROUND(CX120*I120,2) -> 0 | X120: =(ROUND((((S120+ROUND((ROUND(((EU120)*AV120*I120),2)*BS120),2))*AT120)/100),2)+ROUND(((ROUND((ROUND(((AE120-(EU120))*AV120*I120),2)*BS120),2)*AT120)/100),2)) -> 0 | Y120: =(ROUND((((S120+ROUND((ROUND(((EU120)*AV120*I120),2)*BS120),2))*AU120)/100),2)+ROUND(((ROUND((ROUND(((AE120-(EU120))*AV120*I120),2)*BS120),2)*AU120)/100),2)) -> 0 | AA120: 55938214 | AB120: =ROUND((AC120+AD120+AF120),6) -> 573.3 | AC120: =ROUND((ES120),6) -> 573.3 | AD120: =ROUND((((ET120)-(EU120))+AE120),6) -> 0 | AE120: =ROUND((EU120),6) -> 0 | AF120: =ROUND((EV120),6) -> 0 | AG120: =ROUND((AP120),6) -> 0 | AH120: =(EW120) -> 0 | AI120: =(EX120) -> 0 | AJ120: =(AS120) -> 0 | AK120: 573.3 | AL120: 573.3 | AM120: 0 | AN120: 0 | AO120: 0 | AP120: 0 | AQ120: 0 | AR120: 0 | AS120: 0 | AT120: 0 | AU120: 0 | AV120: 1 | AW120: 1 | AZ120: 1 | BA120: 1 | BB120: 1 | BC120: 1 | BH120: 3 | BI120: 3 | BJ120: ТСН-2001.13-2. Доп. 35. 13.3-11-67 | BM120: 746 | BN120: 0 | BP120: 0 | BQ120: 130 | BR120: 0 | BS120: 1 | BT120: 1 | BU120: 1 | BV120: 1 | BW120: 1 | BX120: 1 | BZ120: 0 | CA120: 0 | CE120: 1566 | CF120: 0 | CG120: 0 | CM120: 0 | CO120: 0 | CP120: =(P120+Q120+S120) -> 573.3 | CQ120: =ROUND((ROUND((AC120*1),2)*BC120),2) -> 573.3 | CR120: =(ROUND((ROUND(((ET120)*AV120*1),2)*BB120),2)+ROUND((ROUND(((AE120-(EU120))*AV120*1),2)*BS120),2)) -> 0 | CS120: =(ROUND((ROUND(((EU120)*AV120*1),2)*BS120),2)+ROUND((ROUND(((AE120-(EU120))*AV120*1),2)*BS120),2)) -> 0 | CT120: =ROUND((ROUND((AF120*AV120*1),2)*BA120),2) -> 0 | CU120: =AG120 -> 0 | CV120: =(AH120*AV120) -> 0 | CW120: =AI120 -> 0 | CX120: =AJ120 -> 0 | CY120: =(ROUND((((S120+ROUND((ROUND(((EU120)*AV120*1),2)*BS120),2))*AT120)/100),2)+ROUND(((ROUND((ROUND(((AE120-(EU120))*AV120*1),2)*BS120),2)*AT120)/100),2)) -> 0 | CZ120: =(ROUND((((S120+ROUND((ROUND(((EU120)*AV120*1),2)*BS120),2))*AU120)/100),2)+ROUND(((ROUND((ROUND(((AE120-(EU120))*AV120*1),2)*BS120),2)*AU120)/100),2)) -> 0 | DN120: 0 | DO120: 0 | DP120: 1 | DQ120: 1 | DU120: 1013 | DV120: КОМПЛЕКТ | DW120: КОМПЛЕКТ | DX120: 1 | EE120: 55393877 | EF120: 130 | EG120: Сметная стоимость оборудования | EH120: 0 | EJ120: 3 | EK120: 746 | EL120: ТСН-2001.13. Сметная стоимость оборудования | EM120: ТСН-2001.13 | EQ120: 0 | ER120: 573.3 | ES120: 573.3 | ET120: 0 | EU120: 0 | EV120: 0 | EW120: 0 | EX120: 0 | EY120: 0 | FQ120: 0 | FR120: =P120 -> 573.3 | FS120: 0 | FX120: 0 | FY120: 0 | GD120: 1 | GF120: 1336540512 | GG120: 2 | GH120: 1 | GI120: -2 | GJ120: 0 | GK120: 0 | GL120: =ROUND(IF(AND(BH120=3,BI120=3,FS120<>0),P120,0),2) -> 0 | GM120: =ROUND(O120+X120+Y120,2)+GX120 -> 573.3 | GN120: =IF(OR(BI120=0,BI120=1),GM120-GX120,0) -> 0 | GO120: =IF(BI120=2,GM120-GX120,0) -> 0 | GP120: =IF(BI120=4,GM120-GX120,0) -> 0 | GR120: 0 | GS120: 3 | GT120: 0 | GV120: =ROUND((GT120),6) -> 0 | GW120: 1 | GX120: =ROUND(HC120*I120,2) -> 0 | HA120: 0 | HB120: 0 | HC120: =GV120*GW120 -> 0 | HS120: 0 | IK120: 0
A121: 17 | B121: 1 | E121: 7 | F121: 13.3-11-67 | G121: Крючок для подвески костылей, габаритные размеры 120х32 мм. Материал сталь нержавеющая с полировкой, крепление на стену, в комплекте: прокладки-амортизаторы резиновые, крепежные элементы | H121: КОМПЛЕКТ | I121: 1 | J121: 0 | K121: 1 | O121: =ROUND(CP121,2) -> 1926.29 | P121: =ROUND((ROUND((AC121*I121),2)*BC121),2) -> 1926.29 | Q121: =(ROUND((ROUND(((ET121)*AV121*I121),2)*BB121),2)+ROUND((ROUND(((AE121-(EU121))*AV121*I121),2)*BS121),2)) -> 0 | R121: =(ROUND((ROUND(((EU121)*AV121*I121),2)*BS121),2)+ROUND((ROUND(((AE121-(EU121))*AV121*I121),2)*BS121),2)) -> 0 | S121: =ROUND((ROUND((AF121*AV121*I121),2)*BA121),2) -> 0 | T121: =ROUND(CU121*I121,2) -> 0 | U121: =CV121*I121 -> 0 | V121: =CW121*I121 -> 0 | W121: =ROUND(CX121*I121,2) -> 0 | X121: =(ROUND((((S121+ROUND((ROUND(((EU121)*AV121*I121),2)*BS121),2))*AT121)/100),2)+ROUND(((ROUND((ROUND(((AE121-(EU121))*AV121*I121),2)*BS121),2)*AT121)/100),2)) -> 0 | Y121: =(ROUND((((S121+ROUND((ROUND(((EU121)*AV121*I121),2)*BS121),2))*AU121)/100),2)+ROUND(((ROUND((ROUND(((AE121-(EU121))*AV121*I121),2)*BS121),2)*AU121)/100),2)) -> 0 | AA121: 55938216 | AB121: =ROUND((AC121+AD121+AF121),6) -> 573.3 | AC121: =ROUND((ES121),6) -> 573.3 | AD121: =ROUND((((ET121)-(EU121))+AE121),6) -> 0 | AE121: =ROUND((EU121),6) -> 0 | AF121: =ROUND((EV121),6) -> 0 | AG121: =ROUND((AP121),6) -> 0 | AH121: =(EW121) -> 0 | AI121: =(EX121) -> 0 | AJ121: =(AS121) -> 0 | AK121: 573.3 | AL121: 573.3 | AM121: 0 | AN121: 0 | AO121: 0 | AP121: 0 | AQ121: 0 | AR121: 0 | AS121: 0 | AT121: 0 | AU121: 0 | AV121: 1 | AW121: 1 | AZ121: 1 | BA121: 1 | BB121: 1 | BC121: 3.36 | BH121: 3 | BI121: 3 | BJ121: ТСН-2001.13-2. Доп. 35. 13.3-11-67 | BM121: 746 | BN121: 0 | BP121: 0 | BQ121: 130 | BR121: 0 | BS121: 1 | BT121: 1 | BU121: 1 | BV121: 1 | BW121: 1 | BX121: 1 | BZ121: 0 | CA121: 0 | CE121: 1566 | CF121: 0 | CG121: 0 | CM121: 0 | CO121: 0 | CP121: =(P121+Q121+S121) -> 1926.29 | CQ121: =ROUND((ROUND((AC121*1),2)*BC121),2) -> 1926.29 | CR121: =(ROUND((ROUND(((ET121)*AV121*1),2)*BB121),2)+ROUND((ROUND(((AE121-(EU121))*AV121*1),2)*BS121),2)) -> 0 | CS121: =(ROUND((ROUND(((EU121)*AV121*1),2)*BS121),2)+ROUND((ROUND(((AE121-(EU121))*AV121*1),2)*BS121),2)) -> 0 | CT121: =ROUND((ROUND((AF121*AV121*1),2)*BA121),2) -> 0 | CU121: =AG121 -> 0 | CV121: =(AH121*AV121) -> 0 | CW121: =AI121 -> 0 | CX121: =AJ121 -> 0 | CY121: =(ROUND((((S121+ROUND((ROUND(((EU121)*AV121*1),2)*BS121),2))*AT121)/100),2)+ROUND(((ROUND((ROUND(((AE121-(EU121))*AV121*1),2)*BS121),2)*AT121)/100),2)) -> 0 | CZ121: =(ROUND((((S121+ROUND((ROUND(((EU121)*AV121*1),2)*BS121),2))*AU121)/100),2)+ROUND(((ROUND((ROUND(((AE121-(EU121))*AV121*1),2)*BS121),2)*AU121)/100),2)) -> 0 | DN121: 0 | DO121: 0 | DP121: 1 | DQ121: 1 | DU121: 1013 | DV121: КОМПЛЕКТ | DW121: КОМПЛЕКТ | DX121: 1 | EE121: 55393877 | EF121: 130 | EG121: Сметная стоимость оборудования | EH121: 0 | EJ121: 3 | EK121: 746 | EL121: ТСН-2001.13. Сметная стоимость оборудования | EM121: ТСН-2001.13 | EQ121: 0 | ER121: 573.3 | ES121: 573.3 | ET121: 0 | EU121: 0 | EV121: 0 | EW121: 0 | EX121: 0 | EY121: 0 | FQ121: 0 | FR121: =P121 -> 1926.29 | FS121: 0 | FX121: 0 | FY121: 0 | GD121: 1 | GF121: 1336540512 | GG121: 2 | GH121: 1 | GI121: 2 | GJ121: 0 | GK121: 0 | GL121: =ROUND(IF(AND(BH121=3,BI121=3,FS121<>0),P121,0),2) -> 0 | GM121: =ROUND(O121+X121+Y121,2)+GX121 -> 1926.29 | GN121: =IF(OR(BI121=0,BI121=1),GM121-GX121,0) -> 0 | GO121: =IF(BI121=2,GM121-GX121,0) -> 0 | GP121: =IF(BI121=4,GM121-GX121,0) -> 0 | GR121: 0 | GS121: 3 | GT121: 0 | GV121: =ROUND((GT121),6) -> 0 | GW121: 1 | GX121: =ROUND(HC121*I121,2) -> 0 | HA121: 0 | HB121: 0 | HC121: =GV121*GW121 -> 0 | HS121: 0 | IK121: 0
A122: 17 | B122: 1 | E122: 8 | F122: 13.3-11-75 | G122: Поручень реабилитационный настенный, габаритные размеры 600х90 мм. Материал сталь нержавеющая с полировкой, крепление к стене в двух точках, в комплекте: прокладки-амортизаторы резиновые, крепежные элементы | H122: КОМПЛЕКТ | I122: 1 | J122: 0 | K122: 1 | O122: =ROUND(CP122,2) -> 2345.31 | P122: =ROUND((ROUND((AC122*I122),2)*BC122),2) -> 2345.31 | Q122: =(ROUND((ROUND(((ET122)*AV122*I122),2)*BB122),2)+ROUND((ROUND(((AE122-(EU122))*AV122*I122),2)*BS122),2)) -> 0 | R122: =(ROUND((ROUND(((EU122)*AV122*I122),2)*BS122),2)+ROUND((ROUND(((AE122-(EU122))*AV122*I122),2)*BS122),2)) -> 0 | S122: =ROUND((ROUND((AF122*AV122*I122),2)*BA122),2) -> 0 | T122: =ROUND(CU122*I122,2) -> 0 | U122: =CV122*I122 -> 0 | V122: =CW122*I122 -> 0 | W122: =ROUND(CX122*I122,2) -> 0 | X122: =(ROUND((((S122+ROUND((ROUND(((EU122)*AV122*I122),2)*BS122),2))*AT122)/100),2)+ROUND(((ROUND((ROUND(((AE122-(EU122))*AV122*I122),2)*BS122),2)*AT122)/100),2)) -> 0 | Y122: =(ROUND((((S122+ROUND((ROUND(((EU122)*AV122*I122),2)*BS122),2))*AU122)/100),2)+ROUND(((ROUND((ROUND(((AE122-(EU122))*AV122*I122),2)*BS122),2)*AU122)/100),2)) -> 0 | AA122: 55938214 | AB122: =ROUND((AC122+AD122+AF122),6) -> 2345.31 | AC122: =ROUND((ES122),6) -> 2345.31 | AD122: =ROUND((((ET122)-(EU122))+AE122),6) -> 0 | AE122: =ROUND((EU122),6) -> 0 | AF122: =ROUND((EV122),6) -> 0 | AG122: =ROUND((AP122),6) -> 0 | AH122: =(EW122) -> 0 | AI122: =(EX122) -> 0 | AJ122: =(AS122) -> 0 | AK122: 2345.31 | AL122: 2345.31 | AM122: 0 | AN122: 0 | AO122: 0 | AP122: 0 | AQ122: 0 | AR122: 0 | AS122: 0 | AT122: 0 | AU122: 0 | AV122: 1 | AW122: 1 | AZ122: 1 | BA122: 1 | BB122: 1 | BC122: 1 | BH122: 3 | BI122: 3 | BJ122: ТСН-2001.13-2. Доп. 35. 13.3-11-75 | BM122: 746 | BN122: 0 | BP122: 0 | BQ122: 130 | BR122: 0 | BS122: 1 | BT122: 1 | BU122: 1 | BV122: 1 | BW122: 1 | BX122: 1 | BZ122: 0 | CA122: 0 | CE122: 1566 | CF122: 0 | CG122: 0 | CM122: 0 | CO122: 0 | CP122: =(P122+Q122+S122) -> 2345.31 | CQ122: =ROUND((ROUND((AC122*1),2)*BC122),2) -> 2345.31 | CR122: =(ROUND((ROUND(((ET122)*AV122*1),2)*BB122),2)+ROUND((ROUND(((AE122-(EU122))*AV122*1),2)*BS122),2)) -> 0 | CS122: =(ROUND((ROUND(((EU122)*AV122*1),2)*BS122),2)+ROUND((ROUND(((AE122-(EU122))*AV122*1),2)*BS122),2)) -> 0 | CT122: =ROUND((ROUND((AF122*AV122*1),2)*BA122),2) -> 0 | CU122: =AG122 -> 0 | CV122: =(AH122*AV122) -> 0 | CW122: =AI122 -> 0 | CX122: =AJ122 -> 0 | CY122: =(ROUND((((S122+ROUND((ROUND(((EU122)*AV122*1),2)*BS122),2))*AT122)/100),2)+ROUND(((ROUND((ROUND(((AE122-(EU122))*AV122*1),2)*BS122),2)*AT122)/100),2)) -> 0 | CZ122: =(ROUND((((S122+ROUND((ROUND(((EU122)*AV122*1),2)*BS122),2))*AU122)/100),2)+ROUND(((ROUND((ROUND(((AE122-(EU122))*AV122*1),2)*BS122),2)*AU122)/100),2)) -> 0 | DN122: 0 | DO122: 0 | DP122: 1 | DQ122: 1 | DU122: 1013 | DV122: КОМПЛЕКТ | DW122: КОМПЛЕКТ | DX122: 1 | EE122: 55393877 | EF122: 130 | EG122: Сметная стоимость оборудования | EH122: 0 | EJ122: 3 | EK122: 746 | EL122: ТСН-2001.13. Сметная стоимость оборудования | EM122: ТСН-2001.13 | EQ122: 0 | ER122: 2345.31 | ES122: 2345.31 | ET122: 0 | EU122: 0 | EV122: 0 | EW122: 0 | EX122: 0 | EY122: 0 | FQ122: 0 | FR122: =P122 -> 2345.31 | FS122: 0 | FX122: 0 | FY122: 0 | GD122: 1 | GF122: -1857083357 | GG122: 2 | GH122: 1 | GI122: -2 | GJ122: 0 | GK122: 0 | GL122: =ROUND(IF(AND(BH122=3,BI122=3,FS122<>0),P122,0),2) -> 0 | GM122: =ROUND(O122+X122+Y122,2)+GX122 -> 2345.31 | GN122: =IF(OR(BI122=0,BI122=1),GM122-GX122,0) -> 0 | GO122: =IF(BI122=2,GM122-GX122,0) -> 0 | GP122: =IF(BI122=4,GM122-GX122,0) -> 0 | GR122: 0 | GS122: 3 | GT122: 0 | GV122: =ROUND((GT122),6) -> 0 | GW122: 1 | GX122: =ROUND(HC122*I122,2) -> 0 | HA122: 0 | HB122: 0 | HC122: =GV122*GW122 -> 0 | HS122: 0 | IK122: 0
A123: 17 | B123: 1 | E123: 8 | F123: 13.3-11-75 | G123: Поручень реабилитационный настенный, габаритные размеры 600х90 мм. Материал сталь нержавеющая с полировкой, крепление к стене в двух точках, в комплекте: прокладки-амортизаторы резиновые, крепежные элементы | H123: КОМПЛЕКТ | I123: 1 | J123: 0 | K123: 1 | O123: =ROUND(CP123,2) -> 9123.26 | P123: =ROUND((ROUND((AC123*I123),2)*BC123),2) -> 9123.26 | Q123: =(ROUND((ROUND(((ET123)*AV123*I123),2)*BB123),2)+ROUND((ROUND(((AE123-(EU123))*AV123*I123),2)*BS123),2)) -> 0 | R123: =(ROUND((ROUND(((EU123)*AV123*I123),2)*BS123),2)+ROUND((ROUND(((AE123-(EU123))*AV123*I123),2)*BS123),2)) -> 0 | S123: =ROUND((ROUND((AF123*AV123*I123),2)*BA123),2) -> 0 | T123: =ROUND(CU123*I123,2) -> 0 | U123: =CV123*I123 -> 0 | V123: =CW123*I123 -> 0 | W123: =ROUND(CX123*I123,2) -> 0 | X123: =(ROUND((((S123+ROUND((ROUND(((EU123)*AV123*I123),2)*BS123),2))*AT123)/100),2)+ROUND(((ROUND((ROUND(((AE123-(EU123))*AV123*I123),2)*BS123),2)*AT123)/100),2)) -> 0 | Y123: =(ROUND((((S123+ROUND((ROUND(((EU123)*AV123*I123),2)*BS123),2))*AU123)/100),2)+ROUND(((ROUND((ROUND(((AE123-(EU123))*AV123*I123),2)*BS123),2)*AU123)/100),2)) -> 0 | AA123: 55938216 | AB123: =ROUND((AC123+AD123+AF123),6) -> 2345.31 | AC123: =ROUND((ES123),6) -> 2345.31 | AD123: =ROUND((((ET123)-(EU123))+AE123),6) -> 0 | AE123: =ROUND((EU123),6) -> 0 | AF123: =ROUND((EV123),6) -> 0 | AG123: =ROUND((AP123),6) -> 0 | AH123: =(EW123) -> 0 | AI123: =(EX123) -> 0 | AJ123: =(AS123) -> 0 | AK123: 2345.31 | AL123: 2345.31 | AM123: 0 | AN123: 0 | AO123: 0 | AP123: 0 | AQ123: 0 | AR123: 0 | AS123: 0 | AT123: 0 | AU123: 0 | AV123: 1 | AW123: 1 | AZ123: 1 | BA123: 1 | BB123: 1 | BC123: 3.89 | BH123: 3 | BI123: 3 | BJ123: ТСН-2001.13-2. Доп. 35. 13.3-11-75 | BM123: 746 | BN123: 0 | BP123: 0 | BQ123: 130 | BR123: 0 | BS123: 1 | BT123: 1 | BU123: 1 | BV123: 1 | BW123: 1 | BX123: 1 | BZ123: 0 | CA123: 0 | CE123: 1566 | CF123: 0 | CG123: 0 | CM123: 0 | CO123: 0 | CP123: =(P123+Q123+S123) -> 9123.26 | CQ123: =ROUND((ROUND((AC123*1),2)*BC123),2) -> 9123.26 | CR123: =(ROUND((ROUND(((ET123)*AV123*1),2)*BB123),2)+ROUND((ROUND(((AE123-(EU123))*AV123*1),2)*BS123),2)) -> 0 | CS123: =(ROUND((ROUND(((EU123)*AV123*1),2)*BS123),2)+ROUND((ROUND(((AE123-(EU123))*AV123*1),2)*BS123),2)) -> 0 | CT123: =ROUND((ROUND((AF123*AV123*1),2)*BA123),2) -> 0 | CU123: =AG123 -> 0 | CV123: =(AH123*AV123) -> 0 | CW123: =AI123 -> 0 | CX123: =AJ123 -> 0 | CY123: =(ROUND((((S123+ROUND((ROUND(((EU123)*AV123*1),2)*BS123),2))*AT123)/100),2)+ROUND(((ROUND((ROUND(((AE123-(EU123))*AV123*1),2)*BS123),2)*AT123)/100),2)) -> 0 | CZ123: =(ROUND((((S123+ROUND((ROUND(((EU123)*AV123*1),2)*BS123),2))*AU123)/100),2)+ROUND(((ROUND((ROUND(((AE123-(EU123))*AV123*1),2)*BS123),2)*AU123)/100),2)) -> 0 | DN123: 0 | DO123: 0 | DP123: 1 | DQ123: 1 | DU123: 1013 | DV123: КОМПЛЕКТ | DW123: КОМПЛЕКТ | DX123: 1 | EE123: 55393877 | EF123: 130 | EG123: Сметная стоимость оборудования | EH123: 0 | EJ123: 3 | EK123: 746 | EL123: ТСН-2001.13. Сметная стоимость оборудования | EM123: ТСН-2001.13 | EQ123: 0 | ER123: 2345.31 | ES123: 2345.31 | ET123: 0 | EU123: 0 | EV123: 0 | EW123: 0 | EX123: 0 | EY123: 0 | FQ123: 0 | FR123: =P123 -> 9123.26 | FS123: 0 | FX123: 0 | FY123: 0 | GD123: 1 | GF123: -1857083357 | GG123: 2 | GH123: 1 | GI123: 2 | GJ123: 0 | GK123: 0 | GL123: =ROUND(IF(AND(BH123=3,BI123=3,FS123<>0),P123,0),2) -> 0 | GM123: =ROUND(O123+X123+Y123,2)+GX123 -> 9123.26 | GN123: =IF(OR(BI123=0,BI123=1),GM123-GX123,0) -> 0 | GO123: =IF(BI123=2,GM123-GX123,0) -> 0 | GP123: =IF(BI123=4,GM123-GX123,0) -> 0 | GR123: 0 | GS123: 3 | GT123: 0 | GV123: =ROUND((GT123),6) -> 0 | GW123: 1 | GX123: =ROUND(HC123*I123,2) -> 0 | HA123: 0 | HB123: 0 | HC123: =GV123*GW123 -> 0 | HS123: 0 | IK123: 0
A124: 17 | B124: 1 | E124: 9 | F124: КА, п.3 | G124: Поручень - опора регулируемая с подушкой для спины в санитарно-гигиенические комнаты 250-370х650 | H124: ШТ | I124: 1 | J124: 0 | K124: 1 | O124: =ROUND(CP124,2) -> 1404.49 | P124: =ROUND((ROUND((AC124*AW124*I124),2)*BC124),2) -> 1404.49 | Q124: =(ROUND((ROUND(((ET124)*AV124*I124),2)*BB124),2)+ROUND((ROUND(((AE124-(EU124))*AV124*I124),2)*BS124),2)) -> 0 | R124: =(ROUND((ROUND(((EU124)*AV124*I124),2)*BS124),2)+ROUND((ROUND(((AE124-(EU124))*AV124*I124),2)*BS124),2)) -> 0 | S124: =ROUND((ROUND((AF124*AV124*I124),2)*BA124),2) -> 0 | T124: =ROUND(CU124*I124,2) -> 0 | U124: =CV124*I124 -> 0 | V124: =CW124*I124 -> 0 | W124: =ROUND(CX124*I124,2) -> 0 | X124: =(ROUND((((S124+ROUND((ROUND(((EU124)*AV124*I124),2)*BS124),2))*AT124)/100),2)+ROUND(((ROUND((ROUND(((AE124-(EU124))*AV124*I124),2)*BS124),2)*AT124)/100),2)) -> 0 | Y124: =(ROUND((((S124+ROUND((ROUND(((EU124)*AV124*I124),2)*BS124),2))*AU124)/100),2)+ROUND(((ROUND((ROUND(((AE124-(EU124))*AV124*I124),2)*BS124),2)*AU124)/100),2)) -> 0 | AA124: 55938214 | AB124: =ROUND((AC124+AD124+AF124),6) -> 1404.49 | AC124: =ROUND((ES124),6) -> 1404.49 | AD124: =ROUND((((ET124)-(EU124))+AE124),6) -> 0 | AE124: =ROUND((EU124),6) -> 0 | AF124: =ROUND((EV124),6) -> 0 | AG124: =ROUND((AP124),6) -> 0 | AH124: =(EW124) -> 0 | AI124: =(EX124) -> 0 | AJ124: =(AS124) -> 0 | AK124: 1404.49 | AL124: 1404.49 | AM124: 0 | AN124: 0 | AO124: 0 | AP124: 0 | AQ124: 0 | AR124: 0 | AS124: 0 | AT124: 0 | AU124: 0 | AV124: 1 | AW124: 1 | AZ124: 1 | BA124: 1 | BB124: 1 | BC124: 1 | BH124: 3 | BI124: 3 | BJ124: КА, п.3 | BM124: 400007 | BN124: 0 | BP124: 0 | BQ124: 214 | BR124: 0 | BS124: 1 | BT124: 1 | BU124: 1 | BV124: 1 | BW124: 1 | BX124: 1 | BZ124: 0 | CA124: 0 | CE124: 1566 | CF124: 0 | CG124: 0 | CM124: 0 | CO124: 0 | CP124: =(P124+Q124+S124) -> 1404.49 | CQ124: =ROUND((ROUND((AC124*AW124*1),2)*BC124),2) -> 1404.49 | CR124: =(ROUND((ROUND(((ET124)*AV124*1),2)*BB124),2)+ROUND((ROUND(((AE124-(EU124))*AV124*1),2)*BS124),2)) -> 0 | CS124: =(ROUND((ROUND(((EU124)*AV124*1),2)*BS124),2)+ROUND((ROUND(((AE124-(EU124))*AV124*1),2)*BS124),2)) -> 0 | CT124: =ROUND((ROUND((AF124*AV124*1),2)*BA124),2) -> 0 | CU124: =AG124 -> 0 | CV124: =(AH124*AV124) -> 0 | CW124: =AI124 -> 0 | CX124: =AJ124 -> 0 | CY124: =(ROUND((((S124+ROUND((ROUND(((EU124)*AV124*1),2)*BS124),2))*AT124)/100),2)+ROUND(((ROUND((ROUND(((AE124-(EU124))*AV124*1),2)*BS124),2)*AT124)/100),2)) -> 0 | CZ124: =(ROUND((((S124+ROUND((ROUND(((EU124)*AV124*1),2)*BS124),2))*AU124)/100),2)+ROUND(((ROUND((ROUND(((AE124-(EU124))*AV124*1),2)*BS124),2)*AU124)/100),2)) -> 0 | DN124: 0 | DO124: 0 | DP124: 1 | DQ124: 1 | DU124: 1013 | DV124: ШТ | DW124: ШТ | DX124: 1 | EE124: 55393904 | EF124: 214 | EG124: Оборудование, отсутствующие в СНБ | EH124: 0 | EJ124: 3 | EK124: 400007 | EL124: Оборудование, отсутствующие в СНБ | EM124: Оборуд. КА | EQ124: 16 | ER124: 0 | ES124: 1404.49 | ET124: 0 | EU124: 0 | EV124: 0 | EW124: 0 | EX124: 0 | EY124: 0 | FQ124: 0 | FR124: =P124 -> 1404.49 | FS124: 0 | FX124: 0 | FY124: 0 | GA124: [10 200 / 7,57] + 3% Трансп + 1,2% Заг.скл | GD124: 1 | GF124: 1465347277 | GG124: 2 | GH124: 4 | GI124: -2 | GJ124: 0 | GK124: 0 | GL124: =ROUND(IF(AND(BH124=3,BI124=3,FS124<>0),P124,0),2) -> 0 | GM124: =ROUND(O124+X124+Y124,2)+GX124 -> 1404.49 | GN124: =IF(OR(BI124=0,BI124=1),GM124-GX124,0) -> 0 | GO124: =IF(BI124=2,GM124-GX124,0) -> 0 | GP124: =IF(BI124=4,GM124-GX124,0) -> 0 | GR124: 0 | GS124: 2 | GT124: 0 | GV124: =ROUND((GT124),6) -> 0 | GW124: 1 | GX124: =ROUND(HC124*I124,2) -> 0 | HA124: 0 | HB124: 0 | HC124: =GV124*GW124 -> 0 | HE124: 3 | HF124: 1,2 | HS124: 0 | IK124: 0
A125: 17 | B125: 1 | E125: 9 | F125: КА, п.3 | G125: Поручень - опора регулируемая с подушкой для спины в санитарно-гигиенические комнаты 250-370х650 | H125: ШТ | I125: 1 | J125: 0 | K125: 1 | O125: =ROUND(CP125,2) -> 10631.99 | P125: =ROUND((ROUND((AC125*AW125*I125),2)*BC125),2) -> 10631.99 | Q125: =(ROUND((ROUND(((ET125)*AV125*I125),2)*BB125),2)+ROUND((ROUND(((AE125-(EU125))*AV125*I125),2)*BS125),2)) -> 0 | R125: =(ROUND((ROUND(((EU125)*AV125*I125),2)*BS125),2)+ROUND((ROUND(((AE125-(EU125))*AV125*I125),2)*BS125),2)) -> 0 | S125: =ROUND((ROUND((AF125*AV125*I125),2)*BA125),2) -> 0 | T125: =ROUND(CU125*I125,2) -> 0 | U125: =CV125*I125 -> 0 | V125: =CW125*I125 -> 0 | W125: =ROUND(CX125*I125,2) -> 0 | X125: =(ROUND((((S125+ROUND((ROUND(((EU125)*AV125*I125),2)*BS125),2))*AT125)/100),2)+ROUND(((ROUND((ROUND(((AE125-(EU125))*AV125*I125),2)*BS125),2)*AT125)/100),2)) -> 0 | Y125: =(ROUND((((S125+ROUND((ROUND(((EU125)*AV125*I125),2)*BS125),2))*AU125)/100),2)+ROUND(((ROUND((ROUND(((AE125-(EU125))*AV125*I125),2)*BS125),2)*AU125)/100),2)) -> 0 | AA125: 55938216 | AB125: =ROUND((AC125+AD125+AF125),6) -> 1404.49 | AC125: =ROUND((ES125),6) -> 1404.49 | AD125: =ROUND((((ET125)-(EU125))+AE125),6) -> 0 | AE125: =ROUND((EU125),6) -> 0 | AF125: =ROUND((EV125),6) -> 0 | AG125: =ROUND((AP125),6) -> 0 | AH125: =(EW125) -> 0 | AI125: =(EX125) -> 0 | AJ125: =(AS125) -> 0 | AK125: 1404.49 | AL125: 1404.49 | AM125: 0 | AN125: 0 | AO125: 0 | AP125: 0 | AQ125: 0 | AR125: 0 | AS125: 0 | AT125: 0 | AU125: 0 | AV125: 1 | AW125: 1 | AZ125: 1 | BA125: 1 | BB125: 1 | BC125: 7.57 | BH125: 3 | BI125: 3 | BJ125: КА, п.3 | BM125: 400007 | BN125: 0 | BP125: 0 | BQ125: 214 | BR125: 0 | BS125: 1 | BT125: 1 | BU125: 1 | BV125: 1 | BW125: 1 | BX125: 1 | BZ125: 0 | CA125: 0 | CE125: 1566 | CF125: 0 | CG125: 0 | CM125: 0 | CO125: 0 | CP125: =(P125+Q125+S125) -> 10631.99 | CQ125: =ROUND((ROUND((AC125*AW125*1),2)*BC125),2) -> 10631.99 | CR125: =(ROUND((ROUND(((ET125)*AV125*1),2)*BB125),2)+ROUND((ROUND(((AE125-(EU125))*AV125*1),2)*BS125),2)) -> 0 | CS125: =(ROUND((ROUND(((EU125)*AV125*1),2)*BS125),2)+ROUND((ROUND(((AE125-(EU125))*AV125*1),2)*BS125),2)) -> 0 | CT125: =ROUND((ROUND((AF125*AV125*1),2)*BA125),2) -> 0 | CU125: =AG125 -> 0 | CV125: =(AH125*AV125) -> 0 | CW125: =AI125 -> 0 | CX125: =AJ125 -> 0 | CY125: =(ROUND((((S125+ROUND((ROUND(((EU125)*AV125*1),2)*BS125),2))*AT125)/100),2)+ROUND(((ROUND((ROUND(((AE125-(EU125))*AV125*1),2)*BS125),2)*AT125)/100),2)) -> 0 | CZ125: =(ROUND((((S125+ROUND((ROUND(((EU125)*AV125*1),2)*BS125),2))*AU125)/100),2)+ROUND(((ROUND((ROUND(((AE125-(EU125))*AV125*1),2)*BS125),2)*AU125)/100),2)) -> 0 | DN125: 0 | DO125: 0 | DP125: 1 | DQ125: 1 | DU125: 1013 | DV125: ШТ | DW125: ШТ | DX125: 1 | EE125: 55393904 | EF125: 214 | EG125: Оборудование, отсутствующие в СНБ | EH125: 0 | EJ125: 3 | EK125: 400007 | EL125: Оборудование, отсутствующие в СНБ | EM125: Оборуд. КА | EQ125: 16 | ER125: 1404.49 | ES125: 1404.49 | ET125: 0 | EU125: 0 | EV125: 0 | EW125: 0 | EX125: 0 | EY125: 0 | EZ125: 5 | FC125: 0 | FD125: 18 | FF125: 10200 | FQ125: 0 | FR125: =P125 -> 10631.99 | FS125: 0 | FX125: 0 | FY125: 0 | GA125: [10 200 / 7,57] + 3% Трансп + 1,2% Заг.скл | GD125: 1 | GF125: 1465347277 | GG125: 2 | GH125: 3 | GI125: 5 | GJ125: 0 | GK125: 0 | GL125: =ROUND(IF(AND(BH125=3,BI125=3,FS125<>0),P125,0),2) -> 0 | GM125: =ROUND(O125+X125+Y125,2)+GX125 -> 10631.99 | GN125: =IF(OR(BI125=0,BI125=1),GM125-GX125,0) -> 0 | GO125: =IF(BI125=2,GM125-GX125,0) -> 0 | GP125: =IF(BI125=4,GM125-GX125,0) -> 0 | GR125: 1 | GS125: 1 | GT125: 0 | GV125: =ROUND((GT125),6) -> 0 | GW125: 1 | GX125: =ROUND(HC125*I125,2) -> 0 | HA125: 0 | HB125: 0 | HC125: =GV125*GW125 -> 0 | HE125: 3 | HF125: 1,2 | HS125: 0 | IK125: 0
A127: 51 | B127: =B110 -> 1 | C127: =A110 -> 4 | D127: =ROW(A110) -> 110 | F127: =IF(F110<>"",F110,"") -> 2 | G127: =IF(G110<>"",G110,"") -> Оборудование не облагаемое НДС | H127: 0 | O127: =ROUND(AB127,2) -> 11616.18 | P127: =ROUND(AC127,2) -> 11616.18 | Q127: =ROUND(AD127,2) -> 0 | R127: =ROUND(AE127,2) -> 0 | S127: =ROUND(AF127,2) -> 0 | T127: =ROUND(AG127,2) -> 0 | U127: =AH127 -> 0 | V127: =AI127 -> 0 | W127: =ROUND(AJ127,2) -> 0 | X127: =ROUND(AK127,2) -> 0 | Y127: =ROUND(AL127,2) -> 0 | AB127: =ROUND(SUMIF(AA114:AA125,"=55938214",O114:O125),2) -> 11616.18 | AC127: =ROUND(SUMIF(AA114:AA125,"=55938214",P114:P125),2) -> 11616.18 | AD127: =ROUND(SUMIF(AA114:AA125,"=55938214",Q114:Q125),2) -> 0 | AE127: =ROUND(SUMIF(AA114:AA125,"=55938214",R114:R125),2) -> 0 | AF127: =ROUND(SUMIF(AA114:AA125,"=55938214",S114:S125),2) -> 0 | AG127: =ROUND(SUMIF(AA114:AA125,"=55938214",T114:T125),2) -> 0 | AH127: =SUMIF(AA114:AA125,"=55938214",U114:U125) -> 0 | AI127: =SUMIF(AA114:AA125,"=55938214",V114:V125) -> 0 | AJ127: =ROUND(SUMIF(AA114:AA125,"=55938214",W114:W125),2) -> 0 | AK127: =ROUND(SUMIF(AA114:AA125,"=55938214",X114:X125),2) -> 0 | AL127: =ROUND(SUMIF(AA114:AA125,"=55938214",Y114:Y125),2) -> 0 | AO127: =ROUND(BX127,2) -> 0 | AP127: =ROUND(BY127,2) -> 11616.18 | AQ127: =ROUND(BZ127,2) -> 0 | AR127: =ROUND(CA127,2) -> 11616.18 | AS127: =ROUND(CB127,2) -> 0 | AT127: =ROUND(CC127,2) -> 0 | AU127: =ROUND(CD127,2) -> 0 | AV127: =ROUND(CE127,2) -> 11616.18 | ... BD127: =ROUND(CM127,2) -> 0 | BX127: =ROUND(SUMIF(AA114:AA125,"=55938214",FQ114:FQ125),2) -> 0 | BY127: =ROUND(SUMIF(AA114:AA125,"=55938214",FR114:FR125),2) -> 11616.18 | BZ127: =ROUND(SUMIF(AA114:AA125,"=55938214",GL114:GL125),2) -> 0 | CA127: =ROUND(SUMIF(AA114:AA125,"=55938214",GM114:GM125),2) -> 11616.18 | CB127: =ROUND(SUMIF(AA114:AA125,"=55938214",GN114:GN125),2) -> 0 | CC127: =ROUND(SUMIF(AA114:AA125,"=55938214",GO114:GO125),2) -> 0 | CD127: =ROUND(SUMIF(AA114:AA125,"=55938214",GP114:GP125),2) -> 0 | CE127: =AC127-BX127 -> 11616.18 | CF127: =AC127-BY127 -> 0 | CG127: =BX127-BZ127 -> 0 | CH127: =AC127-BX127-BY127+BZ127 -> 0 | CI127: =BY127-BZ127 -> 11616.18 | CJ127: =ROUND(SUMIF(AA114:AA125,"=55938214",GX114:GX125),2) -> 0 | CK127: =ROUND(SUMIF(AA114:AA125,"=55938214",GY114:GY125),2) -> 0 | CL127: =ROUND(SUMIF(AA114:AA125,"=55938214",GZ114:GZ125),2) -> 0 | CM127: =ROUND(SUMIF(AA114:AA125,"=55938214",HD114:HD125),2) -> 0 | DG127: =ROUND(DT127,2) -> 59628.67 | DH127: =ROUND(DU127,2) -> 59628.67 | DI127: =ROUND(DV127,2) -> 0 | DJ127: =ROUND(DW127,2) -> 0 | DK127: =ROUND(DX127,2) -> 0 | DL127: =ROUND(DY127,2) -> 0 | DM127: =DZ127 -> 0 | DN127: =EA127 -> 0 | DO127: =ROUND(EB127,2) -> 0 | DP127: =ROUND(EC127,2) -> 0 | DQ127: =ROUND(ED127,2) -> 0 | DT127: =ROUND(SUMIF(AA114:AA125,"=55938216",O114:O125),2) -> 59628.67 | DU127: =ROUND(SUMIF(AA114:AA125,"=55938216",P114:P125),2) -> 59628.67 | DV127: =ROUND(SUMIF(AA114:AA125,"=55938216",Q114:Q125),2) -> 0 | DW127: =ROUND(SUMIF(AA114:AA125,"=55938216",R114:R125),2) -> 0 | DX127: =ROUND(SUMIF(AA114:AA125,"=55938216",S114:S125),2) -> 0 | DY127: =ROUND(SUMIF(AA114:AA125,"=55938216",T114:T125),2) -> 0 | DZ127: =SUMIF(AA114:AA125,"=55938216",U114:U125) -> 0 | EA127: =SUMIF(AA114:AA125,"=55938216",V114:V125) -> 0 | EB127: =ROUND(SUMIF(AA114:AA125,"=55938216",W114:W125),2) -> 0 | EC127: =ROUND(SUMIF(AA114:AA125,"=55938216",X114:X125),2) -> 0 | ED127: =ROUND(SUMIF(AA114:AA125,"=55938216",Y114:Y125),2) -> 0 | EG127: =ROUND(FP127,2) -> 0 | EH127: =ROUND(FQ127,2) -> 59628.67 | EI127: =ROUND(FR127,2) -> 0 | EJ127: =ROUND(FS127,2) -> 59628.67 | EK127: =ROUND(FT127,2) -> 0 | EL127: =ROUND(FU127,2) -> 0 | EM127: =ROUND(FV127,2) -> 0 | EN127: =ROUND(FW127,2) -> 59628.67 | ... EV127: =ROUND(GE127,2) -> 0 | FP127: =ROUND(SUMIF(AA114:AA125,"=55938216",FQ114:FQ125),2) -> 0 | FQ127: =ROUND(SUMIF(AA114:AA125,"=55938216",FR114:FR125),2) -> 59628.67 | FR127: =ROUND(SUMIF(AA114:AA125,"=55938216",GL114:GL125),2) -> 0 | FS127: =ROUND(SUMIF(AA114:AA125,"=55938216",GM114:GM125),2) -> 59628.67 | FT127: =ROUND(SUMIF(AA114:AA125,"=55938216",GN114:GN125),2) -> 0 | FU127: =ROUND(SUMIF(AA114:AA125,"=55938216",GO114:GO125),2) -> 0 | FV127: =ROUND(SUMIF(AA114:AA125,"=55938216",GP114:GP125),2) -> 0 | FW127: =DU127-FP127 -> 59628.67 | FX127: =DU127-FQ127 -> 0 | FY127: =FP127-FR127 -> 0 | FZ127: =DU127-FP127-FQ127+FR127 -> 0 | GA127: =FQ127-FR127 -> 59628.67 | GB127: =ROUND(SUMIF(AA114:AA125,"=55938216",GX114:GX125),2) -> 0 | GC127: =ROUND(SUMIF(AA114:AA125,"=55938216",GY114:GY125),2) -> 0 | GD127: =ROUND(SUMIF(AA114:AA125,"=55938216",GZ114:GZ125),2) -> 0 | GE127: =ROUND(SUMIF(AA114:AA125,"=55938216",HD114:HD125),2) -> 0 | GX127: 0
A129: 50 | B129: 0 | C129: 0 | D129: 1 | E129: 201 | F129: =ROUND(Source!O127,O129) -> 11616.18 | G129: ПЗ | H129: Прямые затраты | K129: 201 | L129: 1 | M129: 3 | O129: 2 | P129: =ROUND(Source!DG127,O129) -> 59628.67 | W129: 11616.18 | X129: 1 | Y129: 11616.18 | Z129: 59628.67 | AA129: 1 | AB129: 59628.67
...

Sheet SourceObSm
A1: 0 | B1: Smeta.RU (495) 974-1589 | D1: _OBSM_ | F1: 0 | G1: 0 | H1: 0 | I1: Smeta.RU | K1: 1 | L1: 74599 | M1: 10 | N1: 12 | O1: 1 | P1: 0 | Q1: 5
A4: 1 | B4: 1 | C4: -1 | G4: Капитальный ремонт здания Государственного бюджетного общеобразовательного учреждения города Москвы «Школа №1574», расположенного по адресу: г. Москва, Старопименовский переулок, д. 5. 1 этап | EC4: 0
A5: 8 | B5: 1 | C5: -1 | G5: Капитальный ремонт здания Государственного бюджетного общеобразовательного учреждения города Москвы «Школа №1574», расположенного по адресу: г. Москва, Старопименовский переулок, д. 5. 1 этап | EC5: 0
A12: 1 | B12: 51 | C12: 0 | E12: 0 | F12: 02-01-20 | G12: 02-01-20 ОДИ 16.07.26 | I12: 0 | J12: 2024-00377-01-0-ОДИ.ВОР | K12: 0 | L12: 0 | M12: 4098 | O12: 0 | P12: 0 | Q12: 0 | R12: 0 | S12: 0 | T12: 1 | V12: 0 | AB12: О.А.Гришечкина | AC12: Ведущий инженер-сметчик | AD12: И.В.Феденко | AE12: Начальник отдела | BB12: 0 | BH12: Сметные нормы списания | BI12: Коды ОКП для ТСН-2001 МГЭ Дополнение 81 | BJ12: 1 | BK12: 1 | BL12: 0 | BM12: 0 | BN12: 1 | BO12: 0 | BP12: 6 | BQ12: 2 | BR12: 1 | BS12: 1 | BT12: 0 | BU12: 0 | BV12: 0 | BW12: 0 | BX12: 0 | BY12: ТСН-2001 (МГЭ) Доп 81 - Ремонт | BZ12: Типовой расчет для ТСН-2001 МГЭ, Дополнение 81, ремонт | CA12: Территориальные сметные нормативы для Москвы ТСН-2001 (МГЭ), дополнение 81 | CB12: Территориальные сметные нормативы для Москвы ТСН-2001 (МГЭ), дополнение 81 | CC12: Территориальные сметные нормативы для Москвы ТСН-2001 (МГЭ), дополнение 81 | CD12: Территориальные сметные нормативы для Москвы ТСН-2001 (МГЭ), дополнение 81 | CE12: Поправки для ТСН-2001 от 07.04.2026 г. доп.81 | CF12: 0 | CG12: 0 | CH12: 8200 | CK12: 82 | CQ12: Территориальные сметные нормативы для Москвы (ТСН-2001) | CR12: ТЕР | CS12: 41660 | CT12: 1 | CU12: 81 | CY12: 0 | EC12: 0
A14: 22 | B14: 1 | C14: 0 | D14: 55938214 | E14: 55938216 | F14: 2 | G14: 1
A16: 3 | B16: 1 | C16: 02-01-20 | D16: Мероприятия по обеспечению доступа инвалидов | E16: =ROUND((Source!F321)/1000,2) -> 5.06 | F16: =ROUND((Source!F322)/1000,2) -> 0 | G16: =ROUND((Source!F313)/1000,2) -> 12.83 | H16: =ROUND((Source!F323)/1000+(Source!F324)/1000,2) -> 0 | I16: =E16+F16+G16+H16 -> 17.89 | J16: =ROUND((Source!F319+Source!F318)/1000,2) -> 0.33 | K16: 34.55 | L16: 0 | M16: 0 | N16: =I16+L16+M16 -> 17.89 | T16: =ROUND((Source!P321)/1000,2) -> 80.24 | U16: =ROUND((Source!P322)/1000,2) -> 0 | V16: =ROUND((Source!P313)/1000,2) -> 68.8 | W16: =ROUND((Source!P323)/1000+(Source!P324)/1000,2) -> 0 | X16: =T16+U16+V16+W16 -> 149.04 | Y16: =ROUND((Source!P319+Source!P318)/1000,2) -> 18.45 | Z16: 228.38 | AA16: 0 | AB16: 0 | AC16: =X16+AA16+AB16 -> 149.04 | AI16: 0 | AJ16: -1 | AN16: 0 | AT16: 17437.48 | AU16: 17109.22 | AV16: 0 | AW16: 12827.22 | AX16: 0 | AY16: 1.01 | AZ16: 0.08 | BA16: 327.25 | BB16: 5064.87 | BC16: 0 | BD16: 0 | BE16: 0 | BF16: 24.208651 | BG16: 0 | BH16: 0 | BI16: 280.15 | BJ16: 174.46 | BK16: 17892.09 | BR16: 123418.39 | BS16: 104964.16 | BT16: 0 | BU16: 68796.24 | BV16: 0 | BW16: 13.69 | BX16: 4.51 | BY16: 18440.54 | BZ16: 80238.9 | CA16: 0 | CB16: 0 | CC16: 0 | CD16: 24.208651 | CE16: 0 | CF16: 0 | CG16: 15786.39 | CH16: 9830.36 | CI16: 149035.14
A18: 51 | E18: 5.06 | F18: 0 | G18: 12.83 | H18: 0 | I18: 17.89 | J18: 0.33 | K18: 34.55 | L18: 0 | M18: 0 | N18: 17.89 | T18: 80.24 | U18: 0 | V18: 68.8 | W18: 0 | X18: 149.04 | Y18: 18.45 | Z18: 228.38 | AA18: 0 | AB18: 0 | AC18: 149.04
A20: 50 | B20: 0 | C20: 0 | D20: 1 | E20: 201 | F20: 17437.48 | G20: ПЗ | H20: Прямые затраты | K20: 201 | L20: 1 | M20: 3 | O20: 2 | P20: 123418.39
A21: 50 | B21: 0 | C21: 0 | D21: 1 | E21: 202 | F21: 17109.22 | G21: СтМатОб | H21: Стоимость материальных ресурсов (всего) | K21: 202 | L21: 2 | M21: 3 | O21: 2 | P21: 104964.16
A22: 50 | B22: 0 | C22: 0 | D22: 1 | E22: 222 | F22: 0 | G22: СтМатОбЗак | H22: Стоимость материалов и оборудования заказчика | K22: 222 | L22: 3 | M22: 3 | O22: 2 | P22: 0
A23: 50 | B23: 0 | C23: 0 | D23: 1 | E23: 225 | F23: 17109.22 | G23: СтМатОбПод | H23: Стоимость материалов и оборудования подрядчика | K23: 225 | L23: 4 | M23: 3 | O23: 2 | P23: 104964.16
A24: 50 | B24: 0 | C24: 0 | D24: 1 | E24: 226 | F24: 4282 | G24: СтМат | H24: Стоимость материалов (всего) | K24: 226 | L24: 5 | M24: 3 | O24: 2 | P24: 36167.92
A25: 50 | B25: 0 | C25: 0 | D25: 1 | E25: 227 | F25: 0 | G25: СтМатЗак | H25: Стоимость материалов заказчика | K25: 227 | L25: 6 | M25: 3 | O25: 2 | P25: 0
A26: 50 | B26: 0 | C26: 0 | D26: 1 | E26: 228 | F26: 4282 | G26: СтМатПод | H26: Стоимость материалов подрядчика | K26: 228 | L26: 7 | M26: 3 | O26: 2 | P26: 36167.92
A27: 50 | B27: 0 | C27: 0 | D27: 1 | E27: 216 | F27: 12827.22 | G27: Оборуд | H27: Стоимость оборудования (всего) | K27: 216 | L27: 8 | M27: 3 | O27: 2 | P27: 68796.24
A28: 50 | B28: 0 | C28: 0 | D28: 1 | E28: 223 | F28: 0 | G28: ОборудЗак | H28: Стоимость оборудования заказчика | K28: 223 | L28: 9 | M28: 3 | O28: 2 | P28: 0
A29: 50 | B29: 0 | C29: 0 | D29: 1 | E29: 229 | F29: 12827.22 | G29: ОборудПод | H29: Стоимость оборудования подрядчика | K29: 229 | L29: 10 | M29: 3 | O29: 2 | P29: 68796.24
A30: 50 | B30: 0 | C30: 0 | D30: 1 | E30: 203 | F30: 1.01 | G30: ЭММ | H30: Эксплуатация машин | K30: 203 | L30: 11 | M30: 3 | O30: 2 | P30: 13.69
A31: 50 | B31: 0 | C31: 0 | D31: 1 | E31: 231 | F31: 0 | G31: ЭММсНРиСП | H31: Эксплуатация машин по ТСН-2001.16 | K31: 231 | L31: 12 | M31: 3 | O31: 2 | P31: 0
... A46: 50 | B46: 0 | C46: 0 | D46: 1 | E46: 224 | F46: 17892.09 | G46: Всего | H46: Всего с НР и СП | K46: 224 | L46: 27 | M46: 3 | O46: 2 | P46: 149035.14
A48: -1
A51: 75 | B51: Базовый уровень цен | C51: 2000 | D51: 0 | E51: 1 | F51: 0 | G51: 0 | H51: 1 | I51: 1 | J51: 3 | K51: 0 | L51: 0 | M51: 0 | N51: 55938214 | O51: 1
A52: 1 | B52: Сборник индексов | C52: Коэффициенты к ТСН-2001 МГЭ Дополнение 81, ремонт | D52: 2000 | E52: 1 | F52: 1 | G52: 1 | H52: 0 | I52: 2 | J52: 1 | K52: 1 | L52: 1 | M52: 1 | N52: 1 | O52: 1 | P52: 1 | Q52: 1 | AA52: 0 | AN52: 55938215
A53: 75 | B53: Текущий уровень цен | C53: 2026 | D53: 1 | E53: 0 | G53: 0 | H53: 1 | I53: 1 | J53: 1 | K53: 0 | L53: 0 | M53: 1 | N53: 55938216 | O53: 2
A54: 1 | B54: Сборник индексов | C54: Коэффициенты к ТСН-2001 МГЭ Дополнение 81, ремонт | D54: 2026 | E54: 1 | F54: 1 | G54: 1 | H54: 0 | I54: 2 | J54: 1 | K54: 9.84 | L54: 7.57 | M54: 1 | N54: 1 | O54: 9.84 | P54: 7.57 | Q54: 1 | AA54: 219/81 | AN54: 55938217
A55: 1 | B55: Сборник индексов | C55: Коэффициенты к ТСН-2001.13-2 Дополнение 47 | D55: 2026 | E55: 1 | F55: 1 | G55: 1 | H55: 0 | I55: 2 | J55: 1 | K55: 9.84 | L55: 7.57 | M55: 1 | N55: 1 | O55: 9.84 | P55: 7.57 | Q55: 1 | AA55: 64/47 | AN55: 55938218

Sheet SmtRes
A1: =ROW(Source!A28) -> 28 | B1: 55938214 | C1: 55986203 | D1: 55424304 | E1: 1081 | F1: 1 | G1: 1081 | H1: 1 | I1: 9999990008 | K1: Трудозатраты рабочих | L1: 1191 | N1: 1013 | O1: чел.-ч. | P1: чел.-ч. | Q1: 1 | W1: 0 | X1: 476480486 | Y1: =(((AT1*1.15)*1.2)*0.6) -> 13.98492 | AA1: 0 | AB1: 0 | AC1: 0 | AD1: 0 | AE1: 0 | AF1: 0 | AG1: 0 | AH1: 0 | AI1: 1 | AJ1: 1 | AK1: 1 | AL1: 1 | AM1: -2 | AN1: 0 | AO1: 1 | AP1: 1 | AQ1: 0 | AR1: 0 | AT1: 16.89 | AU1: *1,15)*1,2)*0,6 | AV1: 1 | AW1: 2 | AX1: 55986210 | AY1: 1 | AZ1: 0 | BA1: 1 | BB1: 0 | BC1: 0 | BD1: 0 | BE1: 0 | BF1: 0 | BG1: 0 | BH1: 0 | BI1: 0 | BJ1: 0 | BK1: 0 | BL1: 0 | BM1: 0 | BN1: 0 | BO1: 0 | BP1: 0 | BQ1: 0 | BR1: 0 | BS1: 0 | BT1: 0 | BU1: 0 | BV1: 0 | BW1: 0 | CU1: =ROUND(AT1*Source!I28*AH1*AL1,2) -> 0 | CV1: =ROUND(Y1*Source!I28,9) -> 0.8390952 | CW1: 0 | CX1: =ROUND(Y1*Source!I28,9) -> 0.8390952 | CY1: =AD1 -> 0 | CZ1: =AH1 -> 0 | DA1: =AL1 -> 1 | DB1: =ROUND((((ROUND(AT1*CZ1,2)*1.15)*1.2)*0.6),6) -> 0 | DC1: =ROUND((((ROUND(AT1*AG1,2)*1.15)*1.2)*0.6),6) -> 0 | DF1: =ROUND(ROUND(AE1,2)*CX1,2) -> 0 | DG1: =ROUND(ROUND(AF1,2)*CX1,2) -> 0 | DH1: =ROUND(ROUND(AG1,2)*CX1,2) -> 0 | DI1: =ROUND(ROUND(AH1,2)*CX1,2) -> 0 | DJ1: =DI1 -> 0 | DK1: 0 | DM1: 0 | DO1: 0
A2: =ROW(Source!A28) -> 28 | B2: 55938214 | C2: 55986203 | D2: 55490209 | E2: 1 | F2: 1 | G2: 1081 | H2: 2 | I2: 2.1-18-7 | J2: ТСН-2001.2. Доп. 68. п.1-18-7 (183001) | K2: Автомобили грузовые бортовые, грузоподъемность до 5 т | L2: 1368 | N2: 1011 | O2: маш.-ч | P2: маш.-ч | Q2: 1 | W2: 0 | X2: 874612079 | Y2: =(((AT2*1.25)*1.2)*0.6) -> 0.036 | AA2: 0 | AB2: 88.67 | AC2: 13.47 | AD2: 0 | AE2: 0 | AF2: 83.1 | AG2: 12.62 | AH2: 0 | AI2: 1 | AJ2: 1 | AK2: 1 | AL2: 1 | AM2: -2 | AN2: 0 | AO2: 1 | AP2: 1 | AQ2: 0 | AR2: 0 | AT2: 0.04 | AU2: *1,25)*1,2)*0,6 | AV2: 0 | AW2: 2 | AX2: 55986211 | AY2: 1 | AZ2: 0 | BA2: 2 | BB2: 0 | BC2: 0 | BD2: 0 | BE2: 0 | BF2: 0 | BG2: 0 | BH2: 0 | BI2: 0 | BJ2: 0 | BK2: 0 | BL2: 0 | BM2: 0 | BN2: 0 | BO2: 0 | BP2: 0 | BQ2: 0 | BR2: 0 | BS2: 0 | BT2: 0 | BU2: 0 | BV2: 0 | BW2: 0 | CV2: 0 | CW2: =ROUND(Y2*Source!I28*DO2,9) -> 0.0272592 | CX2: =ROUND(Y2*Source!I28,9) -> 0.00216 | CY2: =AB2 -> 88.67 | CZ2: =AF2 -> 83.1 | DA2: =AJ2 -> 1 | DB2: =ROUND((((ROUND(AT2*CZ2,2)*1.25)*1.2)*0.6),6) -> 2.988 | DC2: =ROUND((((ROUND(AT2*AG2,2)*1.25)*1.2)*0.6),6) -> 0.45 | DF2: =ROUND(ROUND(AE2,2)*CX2,2) -> 0 | DG2: =ROUND(ROUND(AF2,2)*CX2,2) -> 0.18 | DH2: =ROUND(ROUND(AG2,2)*CX2,2) -> 0.03 | DI2: =ROUND(ROUND(AH2,2)*CX2,2) -> 0 | DJ2: =DG2 -> 0.18 | DK2: 0 | DL2: 9999990009 | DM2: 0 | DN2: чел.-ч. | DO2: 12.62
A3: =ROW(Source!A28) -> 28 | B3: 55938214 | C3: 55986203 | D3: 55490263 | E3: 1 | F3: 1 | G3: 1081 | H3: 2 | I3: 2.1-30-10 | J3: ТСН-2001.2. Доп. 68. п.1-30-10 (304101) | K3: Перфораторы, мощность до 800 Вт | L3: 1368 | N3: 1011 | O3: маш.-ч | P3: маш.-ч | Q3: 1 | W3: 0 | X3: -1895752648 | Y3: =(((AT3*1.25)*1.2)*0.6) -> 1.233 | AA3: 0 | AB3: 0.82 | AC3: 0 | AD3: 0 | AE3: 0 | AF3: 0.77 | AG3: 0 | AH3: 0 | AI3: 1 | AJ3: 1 | AK3: 1 | AL3: 1 | AM3: -2 | AN3: 0 | AO3: 1 | AP3: 1 | AQ3: 0 | AR3: 0 | AT3: 1.37 | AU3: *1,25)*1,2)*0,6 | AV3: 0 | AW3: 2 | AX3: 55986212 | AY3: 1 | AZ3: 0 | BA3: 3 | BB3: 0 | BC3: 0 | BD3: 0 | BE3: 0 | BF3: 0 | BG3: 0 | BH3: 0 | BI3: 0 | BJ3: 0 | BK3: 0 | BL3: 0 | BM3: 0 | BN3: 0 | BO3: 0 | BP3: 0 | BQ3: 0 | BR3: 0 | BS3: 0 | BT3: 0 | BU3: 0 | BV3: 0 | BW3: 0 | CV3: 0 | CW3: =ROUND(Y3*Source!I28*DO3,9) -> 0 | CX3: =ROUND(Y3*Source!I28,9) -> 0.07398 | CY3: =AB3 -> 0.82 | CZ3: =AF3 -> 0.77 | DA3: =AJ3 -> 1 | DB3: =ROUND((((ROUND(AT3*CZ3,2)*1.25)*1.2)*0.6),6) -> 0.945 | DC3: =ROUND((((ROUND(AT3*AG3,2)*1.25)*1.2)*0.6),6) -> 0 | DF3: =ROUND(ROUND(AE3,2)*CX3,2) -> 0 | DG3: =ROUND(ROUND(AF3,2)*CX3,2) -> 0.06 | DH3: =ROUND(ROUND(AG3,2)*CX3,2) -> 0 | DI3: =ROUND(ROUND(AH3,2)*CX3,2) -> 0 | DJ3: =DG3 -> 0.06 | DK3: 0 | DM3: 0 | DO3: 0
A4: =ROW(Source!A28) -> 28 | B4: 55938214 | C4: 55986203 | D4: 55490296 | E4: 1 | F4: 1 | G4: 1081 | H4: 2 | I4: 2.1-30-56 | J4: ТСН-2001.2. Доп. 68. п.1-30-56 (309101) | K4: Шуруповерты | L4: 1368 | N4: 1011 | O4: маш.-ч | P4: маш.-ч | Q4: 1 | W4: 0 | X4: -643591644 | Y4: =(((AT4*1.25)*1.2)*0.6) -> 6.057 | AA4: 0 | AB4: 0.5 | AC4: 0 | AD4: 0 | AE4: 0 | AF4: 0.47 | AG4: 0 | AH4: 0 | AI4: 1 | AJ4: 1 | AK4: 1 | AL4: 1 | AM4: -2 | AN4: 0 | AO4: 1 | AP4: 1 | AQ4: 0 | AR4: 0 | AT4: 6.73 | AU4: *1,25)*1,2)*0,6 | AV4: 0 | AW4: 2 | AX4: 55986213 | AY4: 1 | AZ4: 0 | BA4: 4 | BB4: 0 | BC4: 0 | BD4: 0 | BE4: 0 | BF4: 0 | BG4: 0 | BH4: 0 | BI4: 0 | BJ4: 0 | BK4: 0 | BL4: 0 | BM4: 0 | BN4: 0 | BO4: 0 | BP4: 0 | BQ4: 0 | BR4: 0 | BS4: 0 | BT4: 0 | BU4: 0 | BV4: 0 | BW4: 0 | CV4: 0 | CW4: =ROUND(Y4*Source!I28*DO4,9) -> 0 | CX4: =ROUND(Y4*Source!I28,9) -> 0.36342 | CY4: =AB4 -> 0.5 | CZ4: =AF4 -> 0.47 | DA4: =AJ4 -> 1 | DB4: =ROUND((((ROUND(AT4*CZ4,2)*1.25)*1.2)*0.6),6) -> 2.844 | DC4: =ROUND((((ROUND(AT4*AG4,2)*1.25)*1.2)*0.6),6) -> 0 | DF4: =ROUND(ROUND(AE4,2)*CX4,2) -> 0 | DG4: =ROUND(ROUND(AF4,2)*CX4,2) -> 0.17 | DH4: =ROUND(ROUND(AG4,2)*CX4,2) -> 0 | DI4: =ROUND(ROUND(AH4,2)*CX4,2) -> 0 | DJ4: =DG4 -> 0.17 | DK4: 0 | DM4: 0 | DO4: 0
A5: =ROW(Source!A28) -> 28 | B5: 55938214 | C5: 55986203 | D5: 55469271 | E5: 1 | F5: 1 | G5: 1081 | H5: 3 | I5: 1.7-3-130 | J5: ТСН-2001.1 Доп. 65, Р. 7, о. 3, поз. 130 | K5: Бур с наконечником из твердого сплава, с хвостовиком SDS-plus, диаметр 6 мм, длина 210 мм | L5: 1354 | N5: 1010 | O5: шт. | P5: шт. | Q5: 1 | W5: 0 | X5: 1339646332 | Y5: =(((AT5*1)*1)*0.6) -> 0.38988 | AA5: 14.56 | AB5: 0 | AC5: 0 | AD5: 0 | AE5: 14.56 | AF5: 0 | AG5: 0 | AH5: 0 | AI5: 1 | AJ5: 1 | AK5: 1 | AL5: 1 | AM5: -2 | AN5: 0 | AO5: 1 | AP5: 1 | AQ5: 0 | AR5: 0 | AT5: 0.6498 | AU5: *1)*1)*0,6 | AV5: 0 | AW5: 2 | AX5: 55986214 | AY5: 1 | AZ5: 0 | BA5: 5 | BB5: 0 | BC5: 0 | BD5: 0 | BE5: 0 | BF5: 0 | BG5: 0 | BH5: 0 | BI5: 0 | BJ5: 0 | BK5: 0 | BL5: 0 | BM5: 0 | BN5: 0 | BO5: 0 | BP5: 0 | BQ5: 0 | BR5: 0 | BS5: 0 | BT5: 0 | BU5: 0 | BV5: 0 | BW5: 0 | CV5: 0 | CW5: 0 | CX5: =ROUND(Y5*Source!I28,9) -> 0.0233928 | CY5: =AA5 -> 14.56 | CZ5: =AE5 -> 14.56 | DA5: =AI5 -> 1 | DB5: =ROUND((((ROUND(AT5*CZ5,2)*1)*1)*0.6),6) -> 5.676 | DC5: =ROUND((((ROUND(AT5*AG5,2)*1)*1)*0.6),6) -> 0 | DF5: =ROUND(ROUND(AE5,2)*CX5,2) -> 0.34 | DG5: =ROUND(ROUND(AF5,2)*CX5,2) -> 0 | DH5: =ROUND(ROUND(AG5,2)*CX5,2) -> 0 | DI5: =ROUND(ROUND(AH5,2)*CX5,2) -> 0 | DJ5: =DF5 -> 0.34 | DK5: 0 | DM5: 0 | DO5: 0
A6: =ROW(Source!A28) -> 28 | B6: 55938214 | C6: 55986203 | D6: 55469182 | E6: 1 | F6: 1 | G6: 1081 | H6: 3 | I6: 1.7-3-3 | J6: ТСН-2001.1. Доп. 1-42. Р. 7, о. 3, поз. 3 | K6: Сверло с алмазным покрытием, диаметр 6 мм | L6: 1354 | N6: 1010 | O6: шт. | P6: шт. | Q6: 1 | W6: 0 | X6: -609213804 | Y6: =(((AT6*1)*1)*0.6) -> 15.16224 | AA6: 206.58 | AB6: 0 | AC6: 0 | AD6: 0 | AE6: 206.58 | AF6: 0 | AG6: 0 | AH6: 0 | AI6: 1 | AJ6: 1 | AK6: 1 | AL6: 1 | AM6: -2 | AN6: 0 | AO6: 1 | AP6: 1 | AQ6: 0 | AR6: 0 | AT6: 25.2704 | AU6: *1)*1)*0,6 | AV6: 0 | AW6: 2 | AX6: 55986215 | AY6: 1 | AZ6: 0 | BA6: 6 | BB6: 0 | BC6: 0 | BD6: 0 | BE6: 0 | BF6: 0 | BG6: 0 | BH6: 0 | BI6: 0 | BJ6: 0 | BK6: 0 | BL6: 0 | BM6: 0 | BN6: 0 | BO6: 0 | BP6: 0 | BQ6: 0 | BR6: 0 | BS6: 0 | BT6: 0 | BU6: 0 | BV6: 0 | BW6: 0 | CV6: 0 | CW6: 0 | CX6: =ROUND(Y6*Source!I28,9) -> 0.9097344 | CY6: =AA6 -> 206.58 | CZ6: =AE6 -> 206.58 | DA6: =AI6 -> 1 | DB6: =ROUND((((ROUND(AT6*CZ6,2)*1)*1)*0.6),6) -> 3132.216 | DC6: =ROUND((((ROUND(AT6*AG6,2)*1)*1)*0.6),6) -> 0 | DF6: =ROUND(ROUND(AE6,2)*CX6,2) -> 187.93 | DG6: =ROUND(ROUND(AF6,2)*CX6,2) -> 0 | DH6: =ROUND(ROUND(AG6,2)*CX6,2) -> 0 | DI6: =ROUND(ROUND(AH6,2)*CX6,2) -> 0 | DJ6: =DF6 -> 187.93 | DK6: 0 | DM6: 0 | DO6: 0
A7: =ROW(Source!A29) -> 29 | B7: 55938216 | C7: 55986203 | D7: 55424304 | E7: 1081 | F7: 1 | G7: 1081 | H7: 1 | I7: 9999990008 | K7: Трудозатраты рабочих | L7: 1191 | N7: 1013 | O7: чел.-ч. | P7: чел.-ч. | Q7: 1 | W7: 0 | X7: 476480486 | Y7: =(((AT7*1.15)*1.2)*0.6) -> 13.98492 | AA7: 0 | AB7: 0 | AC7: 0 | AD7: 0 | AE7: 0 | AF7: 0 | AG7: 0 | AH7: 0 | AI7: 1 | AJ7: 1 | AK7: 1 | AL7: 1 | AM7: 5 | AN7: 0 | AO7: 1 | AP7: 1 | AQ7: 0 | AR7: 0 | AT7: 16.89 | AU7: *1,15)*1,2)*0,6 | AV7: 1 | AW7: 2 | AX7: 55986210 | AY7: 1 | AZ7: 0 | BA7: 8 | BB7: 0 | BC7: 0 | BD7: 0 | BE7: 0 | BF7: 0 | BG7: 0 | BH7: 0 | BI7: 0 | BJ7: 0 | BK7: 0 | BL7: 0 | BM7: 0 | BN7: 0 | BO7: 0 | BP7: 0 | BQ7: 0 | BR7: 0 | BS7: 0 | BT7: 0 | BU7: 0 | BV7: 0 | BW7: 0 | CU7: =ROUND(AT7*Source!I29*AH7*AL7,2) -> 0 | CV7: =ROUND(Y7*Source!I29,9) -> 0.8390952 | CW7: 0 | CX7: =ROUND(Y7*Source!I29,9) -> 0.8390952 | CY7: =AD7 -> 0 | CZ7: =AH7 -> 0 | DA7: =AL7 -> 1 | DB7: =ROUND((((ROUND(AT7*CZ7,2)*1.15)*1.2)*0.6),6) -> 0 | DC7: =ROUND((((ROUND(AT7*AG7,2)*1.15)*1.2)*0.6),6) -> 0 | DF7: =ROUND(ROUND(AE7,2)*CX7,2) -> 0 | DG7: =ROUND(ROUND(AF7,2)*CX7,2) -> 0 | DH7: =ROUND(ROUND(AG7,2)*CX7,2) -> 0 | DI7: =ROUND(ROUND(AH7,2)*CX7,2) -> 0 | DJ7: =DI7 -> 0 | DK7: 0 | DM7: 0 | DO7: 0
A8: =ROW(Source!A29) -> 29 | B8: 55938216 | C8: 55986203 | D8: 55490209 | E8: 1 | F8: 1 | G8: 1081 | H8: 2 | I8: 2.1-18-7 | J8: ТСН-2001.2. Доп. 68. п.1-18-7 (183001) | K8: Автомобили грузовые бортовые, грузоподъемность до 5 т | L8: 1368 | N8: 1011 | O8: маш.-ч | P8: маш.-ч | Q8: 1 | W8: 0 | X8: 874612079 | Y8: =(((AT8*1.25)*1.2)*0.6) -> 0.036 | AA8: 0 | AB8: 1513.56 | AC8: 758.78 | AD8: 0 | AE8: 0 | AF8: 83.1 | AG8: 12.62 | AH8: 0 | AI8: 1 | AJ8: 17.07 | AK8: 56.35 | AL8: 1 | AM8: 2 | AN8: 0 | AO8: 1 | AP8: 1 | AQ8: 0 | AR8: 0 | AT8: 0.04 | AU8: *1,25)*1,2)*0,6 | AV8: 0 | AW8: 2 | AX8: 55986211 | AY8: 1 | AZ8: 0 | BA8: 9 | BB8: 0 | BC8: 0 | BD8: 0 | BE8: 0 | BF8: 0 | BG8: 0 | BH8: 0 | BI8: 0 | BJ8: 0 | BK8: 0 | BL8: 0 | BM8: 0 | BN8: 0 | BO8: 0 | BP8: 0 | BQ8: 0 | BR8: 0 | BS8: 0 | BT8: 0 | BU8: 0 | BV8: 0 | BW8: 0 | CV8: 0 | CW8: =ROUND(Y8*Source!I29*DO8,9) -> 0.0272592 | CX8: =ROUND(Y8*Source!I29,9) -> 0.00216 | CY8: =AB8 -> 1513.56 | CZ8: =AF8 -> 83.1 | DA8: =AJ8 -> 17.07 | DB8: =ROUND((((ROUND(AT8*CZ8,2)*1.25)*1.2)*0.6),6) -> 2.988 | DC8: =ROUND((((ROUND(AT8*AG8,2)*1.25)*1.2)*0.6),6) -> 0.45 | DF8: =ROUND(ROUND(AE8,2)*CX8,2) -> 0 | DG8: =ROUND(ROUND(AF8*AJ8,2)*CX8,2) -> 3.06 | DH8: =ROUND(ROUND(AG8*AK8,2)*CX8,2) -> 1.54 | DI8: =ROUND(ROUND(AH8,2)*CX8,2) -> 0 | DJ8: =DG8 -> 3.06 | DK8: 0 | DL8: 9999990009 | DM8: 0 | DN8: чел.-ч. | DO8: 12.62
A9: =ROW(Source!A29) -> 29 | B9: 55938216 | C9: 55986203 | D9: 55490263 | E9: 1 | F9: 1 | G9: 1081 | H9: 2 | I9: 2.1-30-10 | J9: ТСН-2001.2. Доп. 68. п.1-30-10 (304101) | K9: Перфораторы, мощность до 800 Вт | L9: 1368 | N9: 1011 | O9: маш.-ч | P9: маш.-ч | Q9: 1 | W9: 0 | X9: -1895752648 | Y9: =(((AT9*1.25)*1.2)*0.6) -> 1.233 | AA9: 0 | AB9: 7.85 | AC9: 0 | AD9: 0 | AE9: 0 | AF9: 0.77 | AG9: 0 | AH9: 0 | AI9: 1 | AJ9: 9.56 | AK9: 1 | AL9: 1 | AM9: 2 | AN9: 0 | AO9: 1 | AP9: 1 | AQ9: 0 | AR9: 0 | AT9: 1.37 | AU9: *1,25)*1,2)*0,6 | AV9: 0 | AW9: 2 | AX9: 55986212 | AY9: 1 | AZ9: 0 | BA9: 10 | BB9: 0 | BC9: 0 | BD9: 0 | BE9: 0 | BF9: 0 | BG9: 0 | BH9: 0 | BI9: 0 | BJ9: 0 | BK9: 0 | BL9: 0 | BM9: 0 | BN9: 0 | BO9: 0 | BP9: 0 | BQ9: 0 | BR9: 0 | BS9: 0 | BT9: 0 | BU9: 0 | BV9: 0 | BW9: 0 | CV9: 0 | CW9: =ROUND(Y9*Source!I29*DO9,9) -> 0 | CX9: =ROUND(Y9*Source!I29,9) -> 0.07398 | CY9: =AB9 -> 7.85 | CZ9: =AF9 -> 0.77 | DA9: =AJ9 -> 9.56 | DB9: =ROUND((((ROUND(AT9*CZ9,2)*1.25)*1.2)*0.6),6) -> 0.945 | DC9: =ROUND((((ROUND(AT9*AG9,2)*1.25)*1.2)*0.6),6) -> 0 | DF9: =ROUND(ROUND(AE9,2)*CX9,2) -> 0 | DG9: =ROUND(ROUND(AF9*AJ9,2)*CX9,2) -> 0.54 | DH9: =ROUND(ROUND(AG9,2)*CX9,2) -> 0 | DI9: =ROUND(ROUND(AH9,2)*CX9,2) -> 0 | DJ9: =DG9 -> 0.54 | DK9: 0 | DM9: 0 | DO9: 0
A10: =ROW(Source!A29) -> 29 | B10: 55938216 | C10: 55986203 | D10: 55490296 | E10: 1 | F10: 1 | G10: 1081 | H10: 2 | I10: 2.1-30-56 | J10: ТСН-2001.2. Доп. 68. п.1-30-56 (309101) | K10: Шуруповерты | L10: 1368 | N10: 1011 | O10: маш.-ч | P10: маш.-ч | Q10: 1 | W10: 0 | X10: -643591644 | Y10: =(((AT10*1.25)*1.2)*0.6) -> 6.057 | AA10: 0 | AB10: 4.84 | AC10: 0 | AD10: 0 | AE10: 0 | AF10: 0.47 | AG10: 0 | AH10: 0 | AI10: 1 | AJ10: 9.66 | AK10: 1 | AL10: 1 | AM10: 2 | AN10: 0 | AO10: 1 | AP10: 1 | AQ10: 0 | AR10: 0 | AT10: 6.73 | AU10: *1,25)*1,2)*0,6 | AV10: 0 | AW10: 2 | AX10: 55986213 | AY10: 1 | AZ10: 0 | BA10: 11 | BB10: 0 | BC10: 0 | BD10: 0 | BE10: 0 | BF10: 0 | BG10: 0 | BH10: 0 | BI10: 0 | BJ10: 0 | BK10: 0 | BL10: 0 | BM10: 0 | BN10: 0 | BO10: 0 | BP10: 0 | BQ10: 0 | BR10: 0 | BS10: 0 | BT10: 0 | BU10: 0 | BV10: 0 | BW10: 0 | CV10: 0 | CW10: =ROUND(Y10*Source!I29*DO10,9) -> 0 | CX10: =ROUND(Y10*Source!I29,9) -> 0.36342 | CY10: =AB10 -> 4.84 | CZ10: =AF10 -> 0.47 | DA10: =AJ10 -> 9.66 | DB10: =ROUND((((ROUND(AT10*CZ10,2)*1.25)*1.2)*0.6),6) -> 2.844 | DC10: =ROUND((((ROUND(AT10*AG10,2)*1.25)*1.2)*0.6),6) -> 0 | DF10: =ROUND(ROUND(AE10,2)*CX10,2) -> 0 | DG10: =ROUND(ROUND(AF10*AJ10,2)*CX10,2) -> 1.65 | DH10: =ROUND(ROUND(AG10,2)*CX10,2) -> 0 | DI10: =ROUND(ROUND(AH10,2)*CX10,2) -> 0 | DJ10: =DG10 -> 1.65 | DK10: 0 | DM10: 0 | DO10: 0
A11: =ROW(Source!A29) -> 29 | B11: 55938216 | C11: 55986203 | D11: 55469271 | E11: 1 | F11: 1 | G11: 1081 | H11: 3 | I11: 1.7-3-130 | J11: ТСН-2001.1 Доп. 65, Р. 7, о. 3, поз. 130 | K11: Бур с наконечником из твердого сплава, с хвостовиком SDS-plus, диаметр 6 мм, длина 210 мм | L11: 1354 | N11: 1010 | O11: шт. | P11: шт. | Q11: 1 | W11: 0 | X11: 1339646332 | Y11: =(((AT11*1)*1)*0.6) -> 0.38988 | AA11: 71.78 | AB11: 0 | AC11: 0 | AD11: 0 | AE11: 14.56 | AF11: 0 | AG11: 0 | AH11: 0 | AI11: 4.93 | AJ11: 1 | AK11: 1 | AL11: 1 | AM11: 2 | AN11: 0 | AO11: 1 | AP11: 1 | AQ11: 0 | AR11: 0 | AT11: 0.6498 | AU11: *1)*1)*0,6 | AV11: 0 | AW11: 2 | AX11: 55986214 | AY11: 1 | AZ11: 0 | BA11: 12 | BB11: 0 | BC11: 0 | BD11: 0 | BE11: 0 | BF11: 0 | BG11: 0 | BH11: 0 | BI11: 0 | BJ11: 0 | BK11: 0 | BL11: 0 | BM11: 0 | BN11: 0 | BO11: 0 | BP11: 0 | BQ11: 0 | BR11: 0 | BS11: 0 | BT11: 0 | BU11: 0 | BV11: 0 | BW11: 0 | CV11: 0 | CW11: 0 | CX11: =ROUND(Y11*Source!I29,9) -> 0.0233928 | CY11: =AA11 -> 71.78 | CZ11: =AE11 -> 14.56 | DA11: =AI11 -> 4.93 | DB11: =ROUND((((ROUND(AT11*CZ11,2)*1)*1)*0.6),6) -> 5.676 | DC11: =ROUND((((ROUND(AT11*AG11,2)*1)*1)*0.6),6) -> 0 | DF11: =ROUND(ROUND(AE11*AI11,2)*CX11,2) -> 1.68 | DG11: =ROUND(ROUND(AF11,2)*CX11,2) -> 0 | DH11: =ROUND(ROUND(AG11,2)*CX11,2) -> 0 | DI11: =ROUND(ROUND(AH11,2)*CX11,2) -> 0 | DJ11: =DF11 -> 1.68 | DK11: 0 | DM11: 0 | DO11: 0
A12: =ROW(Source!A29) -> 29 | B12: 55938216 | C12: 55986203 | D12: 55469182 | E12: 1 | F12: 1 | G12: 1081 | H12: 3 | I12: 1.7-3-3 | J12: ТСН-2001.1. Доп. 1-42. Р. 7, о. 3, поз. 3 | K12: Сверло с алмазным покрытием, диаметр 6 мм | L12: 1354 | N12: 1010 | O12: шт. | P12: шт. | Q12: 1 | W12: 0 | X12: -609213804 | Y12: =(((AT12*1)*1)*0.6) -> 15.16224 | AA12: 144.61 | AB12: 0 | AC12: 0 | AD12: 0 | AE12: 206.58 | AF12: 0 | AG12: 0 | AH12: 0 | AI12: 0.7 | AJ12: 1 | AK12: 1 | AL12: 1 | AM12: 2 | AN12: 0 | AO12: 1 | AP12: 1 | AQ12: 0 | AR12: 0 | AT12: 25.2704 | AU12: *1)*1)*0,6 | AV12: 0 | AW12: 2 | AX12: 55986215 | AY12: 1 | AZ12: 0 | BA12: 13 | BB12: 0 | BC12: 0 | BD12: 0 | BE12: 0 | BF12: 0 | BG12: 0 | BH12: 0 | BI12: 0 | BJ12: 0 | BK12: 0 | BL12: 0 | BM12: 0 | BN12: 0 | BO12: 0 | BP12: 0 | BQ12: 0 | BR12: 0 | BS12: 0 | BT12: 0 | BU12: 0 | BV12: 0 | BW12: 0 | CV12: 0 | CW12: 0 | CX12: =ROUND(Y12*Source!I29,9) -> 0.9097344 | CY12: =AA12 -> 144.61 | CZ12: =AE12 -> 206.58 | DA12: =AI12 -> 0.7 | DB12: =ROUND((((ROUND(AT12*CZ12,2)*1)*1)*0.6),6) -> 3132.216 | DC12: =ROUND((((ROUND(AT12*AG12,2)*1)*1)*0.6),6) -> 0 | DF12: =ROUND(ROUND(AE12*AI12,2)*CX12,2) -> 131.56 | DG12: =ROUND(ROUND(AF12,2)*CX12,2) -> 0 | DH12: =ROUND(ROUND(AG12,2)*CX12,2) -> 0 | DI12: =ROUND(ROUND(AH12,2)*CX12,2) -> 0 | DJ12: =DF12 -> 131.56 | DK12: 0 | DM12: 0 | DO12: 0
A13: =ROW(Source!A30) -> 30 | B13: 55938214 | C13: 55986217 | D13: 55424304 | E13: 1081 | F13: 1 | G13: 1081 | H13: 1 | I13: 9999990008 | K13: Трудозатраты рабочих | L13: 1191 | N13: 1013 | O13: чел.-ч. | P13: чел.-ч. | Q13: 1 | W13: 0 | X13: 476480486 | Y13: =(((AT13*1.2)*1.15)*0.6) -> 7.10424 | AA13: 0 | AB13: 0 | AC13: 0 | AD13: 0 | AE13: 0 | AF13: 0 | AG13: 0 | AH13: 0 | AI13: 1 | AJ13: 1 | AK13: 1 | AL13: 1 | AM13: -2 | AN13: 0 | AO13: 1 | AP13: 1 | AQ13: 0 | AR13: 0 | AT13: 8.58 | AU13: *1,2)*1,15)*0,6 | AV13: 1 | AW13: 2 | AX13: 55986224 | AY13: 1 | AZ13: 0 | BA13: 15 | BB13: 0 | BC13: 0 | BD13: 0 | BE13: 0 | BF13: 0 | BG13: 0 | BH13: 0 | BI13: 0 | BJ13: 0 | BK13: 0 | BL13: 0 | BM13: 0 | BN13: 0 | BO13: 0 | BP13: 0 | BQ13: 0 | BR13: 0 | BS13: 0 | BT13: 0 | BU13: 0 | BV13: 0 | BW13: 0 | CU13: =ROUND(AT13*Source!I30*AH13*AL13,2) -> 0 | CV13: =ROUND(Y13*Source!I30,9) -> 0.1420848 | CW13: 0 | CX13: =ROUND(Y13*Source!I30,9) -> 0.1420848 | CY13: =AD13 -> 0 | CZ13: =AH13 -> 0 | DA13: =AL13 -> 1 | DB13: =ROUND((((ROUND(AT13*CZ13,2)*1.2)*1.15)*0.6),6) -> 0 | DC13: =ROUND((((ROUND(AT13*AG13,2)*1.2)*1.15)*0.6),6) -> 0 | DF13: =ROUND(ROUND(AE13,2)*CX13,2) -> 0 | DG13: =ROUND(ROUND(AF13,2)*CX13,2) -> 0 | DH13: =ROUND(ROUND(AG13,2)*CX13,2) -> 0 | DI13: =ROUND(ROUND(AH13,2)*CX13,2) -> 0 | DJ13: =DI13 -> 0 | DK13: 0 | DM13: 0 | DO13: 0
A14: =ROW(Source!A30) -> 30 | B14: 55938214 | C14: 55986217 | D14: 55490209 | E14: 1 | F14: 1 | G14: 1081 | H14: 2 | I14: 2.1-18-7 | J14: ТСН-2001.2. Доп. 68. п.1-18-7 (183001) | K14: Автомобили грузовые бортовые, грузоподъемность до 5 т | L14: 1368 | N14: 1011 | O14: маш.-ч | P14: маш.-ч | Q14: 1 | W14: 0 | X14: 874612079 | Y14: =(((AT14*1.2)*1.25)*0.6) -> 0.072 | AA14: 0 | AB14: 88.67 | AC14: 13.47 | AD14: 0 | AE14: 0 | AF14: 83.1 | AG14: 12.62 | AH14: 0 | AI14: 1 | AJ14: 1 | AK14: 1 | AL14: 1 | AM14: -2 | AN14: 0 | AO14: 1 | AP14: 1 | AQ14: 0 | AR14: 0 | AT14: 0.08 | AU14: *1,2)*1,25)*0,6 | AV14: 0 | AW14: 2 | AX14: 55986225 | AY14: 1 | AZ14: 0 | BA14: 16 | BB14: 0 | BC14: 0 | BD14: 0 | BE14: 0 | BF14: 0 | BG14: 0 | BH14: 0 | BI14: 0 | BJ14: 0 | BK14: 0 | BL14: 0 | BM14: 0 | BN14: 0 | BO14: 0 | BP14: 0 | BQ14: 0 | BR14: 0 | BS14: 0 | BT14: 0 | BU14: 0 | BV14: 0 | BW14: 0 | CV14: 0 | CW14: =ROUND(Y14*Source!I30*DO14,9) -> 0.0181728 | CX14: =ROUND(Y14*Source!I30,9) -> 0.00144 | CY14: =AB14 -> 88.67 | CZ14: =AF14 -> 83.1 | DA14: =AJ14 -> 1 | DB14: =ROUND((((ROUND(AT14*CZ14,2)*1.2)*1.25)*0.6),6) -> 5.985 | DC14: =ROUND((((ROUND(AT14*AG14,2)*1.2)*1.25)*0.6),6) -> 0.909 | DF14: =ROUND(ROUND(AE14,2)*CX14,2) -> 0 | DG14: =ROUND(ROUND(AF14,2)*CX14,2) -> 0.12 | DH14: =ROUND(ROUND(AG14,2)*CX14,2) -> 0.02 | DI14: =ROUND(ROUND(AH14,2)*CX14,2) -> 0 | DJ14: =DG14 -> 0.12 | DK14: 0 | DL14: 9999990009 | DM14: 0 | DN14: чел.-ч. | DO14: 12.62
A15: =ROW(Source!A30) -> 30 | B15: 55938214 | C15: 55986217 | D15: 55490263 | E15: 1 | F15: 1 | G15: 1081 | H15: 2 | I15: 2.1-30-10 | J15: ТСН-2001.2. Доп. 68. п.1-30-10 (304101) | K15: Перфораторы, мощность до 800 Вт | L15: 1368 | N15: 1011 | O15: маш.-ч | P15: маш.-ч | Q15: 1 | W15: 0 | X15: -1895752648 | Y15: =(((AT15*1.2)*1.25)*0.6) -> 0.522 | AA15: 0 | AB15: 0.82 | AC15: 0 | AD15: 0 | AE15: 0 | AF15: 0.77 | AG15: 0 | AH15: 0 | AI15: 1 | AJ15: 1 | AK15: 1 | AL15: 1 | AM15: -2 | AN15: 0 | AO15: 1 | AP15: 1 | AQ15: 0 | AR15: 0 | AT15: 0.58 | AU15: *1,2)*1,25)*0,6 | AV15: 0 | AW15: 2 | AX15: 55986226 | AY15: 1 | AZ15: 0 | BA15: 17 | BB15: 0 | BC15: 0 | BD15: 0 | BE15: 0 | BF15: 0 | BG15: 0 | BH15: 0 | BI15: 0 | BJ15: 0 | BK15: 0 | BL15: 0 | BM15: 0 | BN15: 0 | BO15: 0 | BP15: 0 | BQ15: 0 | BR15: 0 | BS15: 0 | BT15: 0 | BU15: 0 | BV15: 0 | BW15: 0 | CV15: 0 | CW15: =ROUND(Y15*Source!I30*DO15,9) -> 0 | CX15: =ROUND(Y15*Source!I30,9) -> 0.01044 | CY15: =AB15 -> 0.82 | CZ15: =AF15 -> 0.77 | DA15: =AJ15 -> 1 | DB15: =ROUND((((ROUND(AT15*CZ15,2)*1.2)*1.25)*0.6),6) -> 0.405 | DC15: =ROUND((((ROUND(AT15*AG15,2)*1.2)*1.25)*0.6),6) -> 0 | DF15: =ROUND(ROUND(AE15,2)*CX15,2) -> 0 | DG15: =ROUND(ROUND(AF15,2)*CX15,2) -> 0.01 | DH15: =ROUND(ROUND(AG15,2)*CX15,2) -> 0 | DI15: =ROUND(ROUND(AH15,2)*CX15,2) -> 0 | DJ15: =DG15 -> 0.01 | DK15: 0 | DM15: 0 | DO15: 0
A16: =ROW(Source!A30) -> 30 | B16: 55938214 | C16: 55986217 | D16: 55490296 | E16: 1 | F16: 1 | G16: 1081 | H16: 2 | I16: 2.1-30-56 | J16: ТСН-2001.2. Доп. 68. п.1-30-56 (309101) | K16: Шуруповерты | L16: 1368 | N16: 1011 | O16: маш.-ч | P16: маш.-ч | Q16: 1 | W16: 0 | X16: -643591644 | Y16: =(((AT16*1.2)*1.25)*0.6) -> 3.591 | AA16: 0 | AB16: 0.5 | AC16: 0 | AD16: 0 | AE16: 0 | AF16: 0.47 | AG16: 0 | AH16: 0 | AI16: 1 | AJ16: 1 | AK16: 1 | AL16: 1 | AM16: -2 | AN16: 0 | AO16: 1 | AP16: 1 | AQ16: 0 | AR16: 0 | AT16: 3.99 | AU16: *1,2)*1,25)*0,6 | AV16: 0 | AW16: 2 | AX16: 55986227 | AY16: 1 | AZ16: 0 | BA16: 18 | BB16: 0 | BC16: 0 | BD16: 0 | BE16: 0 | BF16: 0 | BG16: 0 | BH16: 0 | BI16: 0 | BJ16: 0 | BK16: 0 | BL16: 0 | BM16: 0 | BN16: 0 | BO16: 0 | BP16: 0 | BQ16: 0 | BR16: 0 | BS16: 0 | BT16: 0 | BU16: 0 | BV16: 0 | BW16: 0 | CV16: 0 | CW16: =ROUND(Y16*Source!I30*DO16,9) -> 0 | CX16: =ROUND(Y16*Source!I30,9) -> 0.07182 | CY16: =AB16 -> 0.5 | CZ16: =AF16 -> 0.47 | DA16: =AJ16 -> 1 | DB16: =ROUND((((ROUND(AT16*CZ16,2)*1.2)*1.25)*0.6),6) -> 1.692 | DC16: =ROUND((((ROUND(AT16*AG16,2)*1.2)*1.25)*0.6),6) -> 0 | DF16: =ROUND(ROUND(AE16,2)*CX16,2) -> 0 | DG16: =ROUND(ROUND(AF16,2)*CX16,2) -> 0.03 | DH16: =ROUND(ROUND(AG16,2)*CX16,2) -> 0 | DI16: =ROUND(ROUND(AH16,2)*CX16,2) -> 0 | DJ16: =DG16 -> 0.03 | DK16: 0 | DM16: 0 | DO16: 0
