Workbook

Sheet Смета по ТСН-2001(с доп.67
A1: =Source!B1 -> Smeta.RU (495) 974-1589
J2: Форма № 4б
B3: "СОГЛАСОВАНО" | G3: "УТВЕРЖДАЮ"
B6: =CONCATENATE("______________________ ", IF(Source!AL12<>"", Source!AL12, "")) -> ______________________ | G6: =CONCATENATE("______________________ ", IF(Source!AH12<>"", Source!AH12, "")) -> ______________________
B7: "_____"________________ 2026 г. | G7: "_____"________________ 2026 г.
A10: Капитальный ремонт здания Государственного бюджетного общеобразовательного учреждения города Москвы «Школа №1574», расположенного по адресу: г. Москва, Старопименовский переулок, д. 5. 1 этап. | AP10: Капитальный ремонт здания Государственного бюджетного общеобразовательного учреждения города Москвы «Школа №1574», расположенного по адресу: г. Москва, Старопименовский переулок, д. 5. 1 этап. 02-01-14 СОТ 20.07
A11: (наименование стройки и/или объекта)
A13: =CONCATENATE( "ЛОКАЛЬНАЯ СМЕТА № ",IF(Source!F12<>"Новый объект", Source!F12, "")) -> ЛОКАЛЬНАЯ СМЕТА № 02-01-14
A15: =Source!G20 -> Система охранного телевидения
A16: (наименование работ и затрат)
A18: =CONCATENATE( "Основание: чертежи № ", Source!J12) -> Основание: чертежи № 2024-00375-00-ИОС5.7
I20: В базисном уровне цен | J20: В текущем уровне цен
E21: Сметная стоимость | I21: =I22+I23+I24+I25 -> 1061.16 | J21: =J22+J23+J24+J25 -> 8811.08 | K21: тыс.руб.
E22: Строительные работы | I22: =ROUND((Source!F279)/1000, 2) -> 0 | J22: =ROUND((Source!P279)/1000, 2) -> 0 | K22: тыс.руб.
E23: Работы по монтажу оборудования | I23: =ROUND((Source!F280)/1000, 2) -> 17.44 | J23: =ROUND((Source!P280)/1000, 2) -> 910.14 | K23: тыс.руб.
E24: Оборудование | I24: =ROUND((Source!F271)/1000, 2) -> 1043.72 | J24: =ROUND((Source!P271)/1000, 2) -> 7900.94 | K24: тыс.руб.
E25: Прочие работы и затраты | I25: =ROUND((Source!F281+Source!F282)/1000, 2) -> 0 | J25: =ROUND((Source!P281+Source!P282)/1000, 2) -> 0 | K25: тыс.руб.
E26: Средства на оплату труда | I26: =(Source!F277+ Source!F276)/1000 -> 6.74689 | J26: =((Source!P277 + Source!P276)/1000) -> 380.18726 | K26: тыс.руб.
E27: Затраты труда | I27: =Source!F284 -> 460.84551 | K27: чел.-ч.
E28: Кроме того:
E29: Возврат материалов | I29: =SUM(Y1:Y284)/1000 -> 0 | J29: =SUM(Z1:Z284)/1000 -> 0 | K29: тыс.руб.
A31: Составлен(а) по ТСН-2001 с учетом Дополнения №: 81
A32: № и период сборника коэффициентов (индексов) пересчета: Коэффициенты к ТСН-2001 МГЭ Дополнение 81, строительство №219/81 I квартал 2026 года и Коэффициенты к ТСН-2001.13-2 Дополнение 47 №64/47 I квартал 2026 года | AP32: № и период сборника коэффициентов (индексов) пересчета: Коэффициенты к ТСН-2001 МГЭ Дополнение 81, строительство №219/81 I квартал 2026 года и Коэффициенты к ТСН-2001.13-2 Дополнение 47 №64/47 I квартал 2026 года
A33: № п/п | B33: Шифр расценки и коды ресурсов | C33: Наименование работ и затрат | D33: Ед. изм. | E33: Кол-во единиц | F33: Цена на ед. изм., руб. | G33: Попра- вочные коэффи- циенты | H33: Коэффи- циенты зимних удорожа- ний | I33: Всего в ценах на январь 2000 года, руб. | J33: Коэффи- циенты (индек- сы) пере- счета, нормы НР и СП | K33: ВСЕГО затрат в текущем уровне цен, руб.
A34: 1 | B34: 2 | C34: 3 | D34: 4 | E34: 5 | F34: 6 | G34: 7 | H34: 8 | I34: 9 | J34: 10 | K34: 11
A36: =CONCATENATE("Локальная смета: ",IF(Source!G20<>"Новая локальная смета", Source!G20, "")) -> Локальная смета: Система охранного телевидения
A38: =CONCATENATE("Раздел: ",IF(Source!G24<>"Новый раздел", Source!G24, "")) -> Раздел: Демонтажные работы (Письмо от АНО «РГТ» об утверждении объёмов демонтажных работ) | AP38: =CONCATENATE("Раздел: ",IF(Source!G24<>"Новый раздел", Source!G24, "")) -> Раздел: Демонтажные работы (Письмо от АНО «РГТ» об утверждении объёмов демонтажных работ)
A39: 1 | B39: =Source!F28 -> 4.10-34-5 | C39: Монтаж коммутатора служебной связи / демонтаж Управляемого коммутатора | D39: =Source!H28 -> 1 ШТ. | E39: =Source!I28 -> 6 | Q39: =Source!X28 -> 165.68 | R39: =Source!X29 -> 9336.12 | S39: =Source!Y28 -> 84.68 | T39: =Source!Y29 -> 4771.8 | U39: =ROUND((175/100)*ROUND(Source!R28, 2), 2) -> 12.51 | V39: =ROUND((0/100)*ROUND(Source!R29, 2), 2) -> 0 | AC39: 0
C40: ="Объем: "&Source!I28&"=1+"&"1+"&"4" -> Объем: 6=1+1+4
C41: ЗП | F41: =Source!AO28 -> 78.24 | G41: 1,2*0,3 | H41: =Source!AV29 -> 1.047 | I41: =Source!S28 -> 176.94 | J41: =IF(Source!BA29<> 0, Source!BA29, 1) -> 56.35 | K41: =Source!S29 -> 9970.57
C42: ЭМ | F42: =Source!AM28 -> 28.71 | G42: 1,2*0,3 | H42: =Source!AV29 -> 1.047 | I42: =Source!Q28 -> 64.93 | J42: =IF(Source!BB29<> 0, Source!BB29, 1) -> 16.16 | K42: =Source!Q29 -> 1049.27
C43: в т.ч. ЗПМ | F43: =Source!AN28 -> 3.16 | G43: 1,2*0,3 | H43: =Source!AV29 -> 1.047 | I43: =Source!R28 -> 7.15 | J43: =IF(Source!BS29<> 0, Source!BS29, 1) -> 56.35 | K43: =Source!R29 -> 402.9
C44: НР от ФОТ | D44: % | E44: =Source!BZ29 -> 90 | I44: =SUM(Q39:Q43) -> 165.68 | J44: =Source!AT29 -> 90 | K44: =SUM(R39:R43) -> 9336.12
C45: СП от ФОТ | D45: % | E45: =Source!CA29 -> 46 | I45: =SUM(S39:S44) -> 84.68 | J45: =Source!AU29 -> 46 | K45: =SUM(T39:T44) -> 4771.8
C46: ЗТР | D46: чел-ч | E46: =Source!AQ28 -> 6.2 | G46: 1,2*0,3 | H46: =Source!AV29 -> 1.047 | I46: =Source!U28 -> 14.021424
C47: ВСЕГО работ по позиции: | H47: =I41+I42+I44+I45+0-0-0 -> 492.23 | J47: =K41+K42+K44+K45+0-0-0 -> 25127.76
C48: ВСЕГО оборудование по позиции: | H48: =0+0 -> 0 | J48: =0+0 -> 0
C49: ВСЕГО по позиции: | H49: =I41+I42+I44+I45+0 -> 492.23 | J49: =K41+K42+K44+K45+0 -> 25127.76 | O49: =I41+I42+I44+I45+0 -> 492.23 | P49: =K41+K42+K44+K45+0 -> 25127.76
A51: 2 | B51: =Source!F30 -> 4.10-72-14 | C51: Монтаж устройства цифровой регистрации / демонтаж сервера объектового контроля | D51: =Source!H30 -> 1 устройство | E51: =Source!I30 -> 1 | Q51: =Source!X30 -> 34.06 | R51: =Source!X31 -> 1919.14 | S51: =Source!Y30 -> 19 | T51: =Source!Y31 -> 1070.68 | U51: =ROUND((175/100)*ROUND(Source!R30, 2), 2) -> 0 | V51: =ROUND((0/100)*ROUND(Source!R31, 2), 2) -> 0 | AC51: 0
C52: ЗП | F52: =Source!AO30 -> 95.12 | G52: 1,2*0,3 | H52: =Source!AV31 -> 1.047 | I52: =Source!S30 -> 35.85 | J52: =IF(Source!BA31<> 0, Source!BA31, 1) -> 56.35 | K52: =Source!S31 -> 2020.15
C53: НР от ФОТ | D53: % | E53: =Source!BZ31 -> 95 | I53: =SUM(Q51:Q52) -> 34.06 | J53: =Source!AT31 -> 95 | K53: =SUM(R51:R52) -> 1919.14
C54: СП от ФОТ | D54: % | E54: =Source!CA31 -> 53 | I54: =SUM(S51:S53) -> 19 | J54: =Source!AU31 -> 53 | K54: =SUM(T51:T53) -> 1070.68
C55: ЗТР | D55: чел-ч | E55: =Source!AQ30 -> 8 | G55: 1,2*0,3 | H55: =Source!AV31 -> 1.047 | I55: =Source!U30 -> 3.01536
C56: ВСЕГО работ по позиции: | H56: =I52+I53+I54+0-0-0 -> 88.91 | J56: =K52+K53+K54+0-0-0 -> 5009.97
C57: ВСЕГО оборудование по позиции: | H57: =0+0 -> 0 | J57: =0+0 -> 0
C58: ВСЕГО по позиции: | H58: =I52+I53+I54+0 -> 88.91 | J58: =K52+K53+K54+0 -> 5009.97 | O58: =I52+I53+I54+0 -> 88.91 | P58: =K52+K53+K54+0 -> 5009.97
A60: 3 | B60: =Source!F32 -> 4.10-72-14 | C60: Монтаж устройства цифровой регистрации / демонтаж специализированной рабочей станции | D60: =Source!H32 -> 1 устройство | E60: =Source!I32 -> 1 | Q60: =Source!X32 -> 34.06 | R60: =Source!X33 -> 1919.14 | S60: =Source!Y32 -> 19 | T60: =Source!Y33 -> 1070.68 | U60: =ROUND((175/100)*ROUND(Source!R32, 2), 2) -> 0 | V60: =ROUND((0/100)*ROUND(Source!R33, 2), 2) -> 0 | AC60: 0
C61: ЗП | F61: =Source!AO32 -> 95.12 | G61: 1,2*0,3 | H61: =Source!AV33 -> 1.047 | I61: =Source!S32 -> 35.85 | J61: =IF(Source!BA33<> 0, Source!BA33, 1) -> 56.35 | K61: =Source!S33 -> 2020.15
C62: НР от ФОТ | D62: % | E62: =Source!BZ33 -> 95 | I62: =SUM(Q60:Q61) -> 34.06 | J62: =Source!AT33 -> 95 | K62: =SUM(R60:R61) -> 1919.14
C63: СП от ФОТ | D63: % | E63: =Source!CA33 -> 53 | I63: =SUM(S60:S62) -> 19 | J63: =Source!AU33 -> 53 | K63: =SUM(T60:T62) -> 1070.68
C64: ЗТР | D64: чел-ч | E64: =Source!AQ32 -> 8 | G64: 1,2*0,3 | H64: =Source!AV33 -> 1.047 | I64: =Source!U32 -> 3.01536
C65: ВСЕГО работ по позиции: | H65: =I61+I62+I63+0-0-0 -> 88.91 | J65: =K61+K62+K63+0-0-0 -> 5009.97
C66: ВСЕГО оборудование по позиции: | H66: =0+0 -> 0 | J66: =0+0 -> 0
C67: ВСЕГО по позиции: | H67: =I61+I62+I63+0 -> 88.91 | J67: =K61+K62+K63+0 -> 5009.97 | O67: =I61+I62+I63+0 -> 88.91 | P67: =K61+K62+K63+0 -> 5009.97
A69: 4 | B69: =Source!F34 -> 4.10-75-6 | C69: Монтаж аппаратуры настольной массой до 20 кг / демонтаж монитора | D69: =Source!H34 -> 1 ШТ. | E69: =Source!I34 -> 2 | Q69: =Source!X34 -> 63.26 | R69: =Source!X35 -> 3564.73 | S69: =Source!Y34 -> 35.29 | T69: =Source!Y35 -> 1988.75 | U69: =ROUND((175/100)*ROUND(Source!R34, 2), 2) -> 0 | V69: =ROUND((0/100)*ROUND(Source!R35, 2), 2) -> 0 | AC69: 0
C70: ЗП | F70: =Source!AO34 -> 88.34 | G70: 1,2*0,3 | H70: =Source!AV35 -> 1.047 | I70: =Source!S34 -> 66.59 | J70: =IF(Source!BA35<> 0, Source!BA35, 1) -> 56.35 | K70: =Source!S35 -> 3752.35
C71: НР от ФОТ | D71: % | E71: =Source!BZ35 -> 95 | I71: =SUM(Q69:Q70) -> 63.26 | J71: =Source!AT35 -> 95 | K71: =SUM(R69:R70) -> 3564.73
C72: СП от ФОТ | D72: % | E72: =Source!CA35 -> 53 | I72: =SUM(S69:S71) -> 35.29 | J72: =Source!AU35 -> 53 | K72: =SUM(T69:T71) -> 1988.75
C73: ЗТР | D73: чел-ч | E73: =Source!AQ34 -> 7 | G73: 1,2*0,3 | H73: =Source!AV35 -> 1.047 | I73: =Source!U34 -> 5.27688
C74: ВСЕГО работ по позиции: | H74: =I70+I71+I72+0-0-0 -> 165.14 | J74: =K70+K71+K72+0-0-0 -> 9305.83
C75: ВСЕГО оборудование по позиции: | H75: =0+0 -> 0 | J75: =0+0 -> 0
C76: ВСЕГО по позиции: | H76: =I70+I71+I72+0 -> 165.14 | J76: =K70+K71+K72+0 -> 9305.83 | O76: =I70+I71+I72+0 -> 165.14 | P76: =K70+K71+K72+0 -> 9305.83
A78: 5 | B78: =Source!F36 -> 4.10-21-5 | C78: Грозозащита для воздушных абонентских линий / демонтаж грозозащиты локальной вычислительной сети | D78: =Source!H36 -> 1 комплект | E78: =Source!I36 -> 1 | Q78: =Source!X36 -> 12.84 | R78: =Source!X37 -> 723.7 | S78: =Source!Y36 -> 6.56 | T78: =Source!Y37 -> 369.89 | U78: =ROUND((175/100)*ROUND(Source!R36, 2), 2) -> 0 | V78: =ROUND((0/100)*ROUND(Source!R37, 2), 2) -> 0 | AC78: 0
C79: ЗП | F79: =Source!AO36 -> 37.86 | G79: 1,2*0,3 | H79: =Source!AV37 -> 1.047 | I79: =Source!S36 -> 14.27 | J79: =IF(Source!BA37<> 0, Source!BA37, 1) -> 56.35 | K79: =Source!S37 -> 804.11
C80: НР от ФОТ | D80: % | E80: =Source!BZ37 -> 90 | I80: =SUM(Q78:Q79) -> 12.84 | J80: =Source!AT37 -> 90 | K80: =SUM(R78:R79) -> 723.7
C81: СП от ФОТ | D81: % | E81: =Source!CA37 -> 46 | I81: =SUM(S78:S80) -> 6.56 | J81: =Source!AU37 -> 46 | K81: =SUM(T78:T80) -> 369.89
C82: ЗТР | D82: чел-ч | E82: =Source!AQ36 -> 3 | G82: 1,2*0,3 | H82: =Source!AV37 -> 1.047 | I82: =Source!U36 -> 1.13076
C83: ВСЕГО работ по позиции: | H83: =I79+I80+I81+0-0-0 -> 33.67 | J83: =K79+K80+K81+0-0-0 -> 1897.7
C84: ВСЕГО оборудование по позиции: | H84: =0+0 -> 0 | J84: =0+0 -> 0
C85: ВСЕГО по позиции: | H85: =I79+I80+I81+0 -> 33.67 | J85: =K79+K80+K81+0 -> 1897.7 | O85: =I79+I80+I81+0 -> 33.67 | P85: =K79+K80+K81+0 -> 1897.7
A87: 6 | B87: =Source!F38 -> 4.10-21-5 | C87: Грозозащита для воздушных абонентских линий / демонтаж уличной грозозащиты локальной вычислительной сети | D87: =Source!H38 -> 1 комплект | E87: =Source!I38 -> 14 | Q87: =Source!X38 -> 179.8 | R87: =Source!X39 -> 10131.84 | S87: =Source!Y38 -> 91.9 | T87: =Source!Y39 -> 5178.5 | U87: =ROUND((175/100)*ROUND(Source!R38, 2), 2) -> 0 | V87: =ROUND((0/100)*ROUND(Source!R39, 2), 2) -> 0 | AC87: 0
C88: ЗП | F88: =Source!AO38 -> 37.86 | G88: 1,2*0,3 | H88: =Source!AV39 -> 1.047 | I88: =Source!S38 -> 199.78 | J88: =IF(Source!BA39<> 0, Source!BA39, 1) -> 56.35 | K88: =Source!S39 -> 11257.6
C89: НР от ФОТ | D89: % | E89: =Source!BZ39 -> 90 | I89: =SUM(Q87:Q88) -> 179.8 | J89: =Source!AT39 -> 90 | K89: =SUM(R87:R88) -> 10131.84
C90: СП от ФОТ | D90: % | E90: =Source!CA39 -> 46 | I90: =SUM(S87:S89) -> 91.9 | J90: =Source!AU39 -> 46 | K90: =SUM(T87:T89) -> 5178.5
C91: ЗТР | D91: чел-ч | E91: =Source!AQ38 -> 3 | G91: 1,2*0,3 | H91: =Source!AV39 -> 1.047 | I91: =Source!U38 -> 15.83064
C92: ВСЕГО работ по позиции: | H92: =I88+I89+I90+0-0-0 -> 471.48 | J92: =K88+K89+K90+0-0-0 -> 26567.94
C93: ВСЕГО оборудование по позиции: | H93: =0+0 -> 0 | J93: =0+0 -> 0
C94: ВСЕГО по позиции: | H94: =I88+I89+I90+0 -> 471.48 | J94: =K88+K89+K90+0 -> 26567.94 | O94: =I88+I89+I90+0 -> 471.48 | P94: =K88+K89+K90+0 -> 26567.94
A96: 7 | B96: =Source!F40 -> 4.10-174-1 | C96: Монтаж внутренней камеры видеонаблюдения / демонтаж видеокамер | D96: =Source!H40 -> 10 шт. | E96: =Source!I40 -> 8.1 | Q96: =Source!X40 -> 680.21 | R96: =Source!X41 -> 38329.89 | S96: =Source!Y40 -> 347.66 | T96: =Source!Y41 -> 19590.83 | U96: =ROUND((175/100)*ROUND(Source!R40, 2), 2) -> 0.7 | V96: =ROUND((0/100)*ROUND(Source!R41, 2), 2) -> 0 | AC96: 0
C97: ="Объем: "&Source!I40&"=81/"&"10" -> Объем: 8,1=81/10
C98: ЗП | F98: =Source!AO40 -> 247.42 | G98: 1,2*0,3 | H98: =Source!AV41 -> 1.047 | I98: =Source!S40 -> 755.39 | J98: =IF(Source!BA41<> 0, Source!BA41, 1) -> 56.35 | K98: =Source!S41 -> 42566.23
C99: ЭМ | F99: =Source!AM40 -> 2.36 | G99: 1,2*0,3 | H99: =Source!AV41 -> 1.047 | I99: =Source!Q40 -> 7.21 | J99: =IF(Source!BB41<> 0, Source!BB41, 1) -> 12.21 | K99: =Source!Q41 -> 88.03
C100: в т.ч. ЗПМ | F100: =Source!AN40 -> 0.13 | G100: 1,2*0,3 | H100: =Source!AV41 -> 1.047 | I100: =Source!R40 -> 0.4 | J100: =IF(Source!BS41<> 0, Source!BS41, 1) -> 56.35 | K100: =Source!R41 -> 22.54
C101: НР от ФОТ | D101: % | E101: =Source!BZ41 -> 90 | I101: =SUM(Q96:Q100) -> 680.21 | J101: =Source!AT41 -> 90 | K101: =SUM(R96:R100) -> 38329.89
C102: СП от ФОТ | D102: % | E102: =Source!CA41 -> 46 | I102: =SUM(S96:S101) -> 347.66 | J102: =Source!AU41 -> 46 | K102: =SUM(T96:T101) -> 19590.83
C103: ЗТР | D103: чел-ч | E103: =Source!AQ40 -> 15.54 | G103: 1,2*0,3 | H103: =Source!AV41 -> 1.047 | I103: =Source!U40 -> 47.444428
C104: ВСЕГО работ по позиции: | H104: =I98+I99+I101+I102+0-0-0 -> 1790.47 | J104: =K98+K99+K101+K102+0-0-0 -> 100574.98
C105: ВСЕГО оборудование по позиции: | H105: =0+0 -> 0 | J105: =0+0 -> 0
C106: ВСЕГО по позиции: | H106: =I98+I99+I101+I102+0 -> 1790.47 | J106: =K98+K99+K101+K102+0 -> 100574.98 | O106: =I98+I99+I101+I102+0 -> 1790.47 | P106: =K98+K99+K101+K102+0 -> 100574.98
A108: 8 | B108: =Source!F42 -> 4.10-174-2 | C108: Монтаж наружной камеры видеонаблюдения / демонтаж видеокамер | D108: =Source!H42 -> 10 шт. | E108: =Source!I42 -> 1.8 | Q108: =Source!X42 -> 245.1 | R108: =Source!X43 -> 13811.21 | S108: =Source!Y42 -> 125.27 | T108: =Source!Y43 -> 7059.06 | U108: =ROUND((175/100)*ROUND(Source!R42, 2), 2) -> 0.16 | V108: =ROUND((0/100)*ROUND(Source!R43, 2), 2) -> 0 | AC108: 0
C109: ="Объем: "&Source!I42&"=(14+"&"4)/"&"10" -> Объем: 1,8=(14+4)/10
C110: ЗП | F110: =Source!AO42 -> 401.27 | G110: 1,2*0,3 | H110: =Source!AV43 -> 1.047 | I110: =Source!S42 -> 272.24 | J110: =IF(Source!BA43<> 0, Source!BA43, 1) -> 56.35 | K110: =Source!S43 -> 15340.72
C111: ЭМ | F111: =Source!AM42 -> 2.36 | G111: 1,2*0,3 | H111: =Source!AV43 -> 1.047 | I111: =Source!Q42 -> 1.6 | J111: =IF(Source!BB43<> 0, Source!BB43, 1) -> 12.21 | K111: =Source!Q43 -> 19.54
C112: в т.ч. ЗПМ | F112: =Source!AN42 -> 0.13 | G112: 1,2*0,3 | H112: =Source!AV43 -> 1.047 | I112: =Source!R42 -> 0.09 | J112: =IF(Source!BS43<> 0, Source!BS43, 1) -> 56.35 | K112: =Source!R43 -> 5.07
C113: НР от ФОТ | D113: % | E113: =Source!BZ43 -> 90 | I113: =SUM(Q108:Q112) -> 245.1 | J113: =Source!AT43 -> 90 | K113: =SUM(R108:R112) -> 13811.21
C114: СП от ФОТ | D114: % | E114: =Source!CA43 -> 46 | I114: =SUM(S108:S113) -> 125.27 | J114: =Source!AU43 -> 46 | K114: =SUM(T108:T113) -> 7059.06
C115: ЗТР | D115: чел-ч | E115: =Source!AQ42 -> 25.33 | G115: 1,2*0,3 | H115: =Source!AV43 -> 1.047 | I115: =Source!U42 -> 17.18529
C116: ВСЕГО работ по позиции: | H116: =I110+I111+I113+I114+0-0-0 -> 644.21 | J116: =K110+K111+K113+K114+0-0-0 -> 36230.53
C117: ВСЕГО оборудование по позиции: | H117: =0+0 -> 0 | J117: =0+0 -> 0
C118: ВСЕГО по позиции: | H118: =I110+I111+I113+I114+0 -> 644.21 | J118: =K110+K111+K113+K114+0 -> 36230.53 | O118: =I110+I111+I113+I114+0 -> 644.21 | P118: =K110+K111+K113+K114+0 -> 36230.53
...

Sheet Source
A1: 0 | B1: Smeta.RU (495) 974-1589 | D1: _PS_ | F1: 0 | G1: 0 | H1: 0 | I1: Smeta.RU | K1: 1 | L1: 74599 | M1: 10 | N1: 12 | O1: 1 | P1: 0 | Q1: 5
A4: 1 | B4: 1 | C4: -1 | G4: Капитальный ремонт здания Государственного бюджетного общеобразовательного учреждения города Москвы «Школа №1574», расположенного по адресу: г. Москва, Старопименовский переулок, д. 5. 1 этап | EC4: 0
A5: 8 | B5: 1 | C5: -1 | G5: Капитальный ремонт здания Государственного бюджетного общеобразовательного учреждения города Москвы «Школа №1574», расположенного по адресу: г. Москва, Старопименовский переулок, д. 5. 1 этап | EC5: 0
A12: 1 | B12: 301 | C12: 0 | D12: =ROW(A262) -> 262 | E12: 0 | F12: 02-01-14 | G12: 02-01-14 СОТ 20.07 | I12: 0 | J12: 2024-00375-00-ИОС5.7 | K12: 0 | L12: 0 | M12: 4098 | O12: 0 | P12: 0 | Q12: 0 | R12: 0 | S12: 0 | T12: 1 | V12: 2 | AB12: О.А.Гришечкина | AC12: Ведущий инженер-сметчик | AD12: И.В.Феденко | AE12: Начальник отдела | BB12: 0 | BH12: Сметные нормы списания | BI12: Коды ОКП для ТСН-2001 МГЭ Дополнение 81 | BJ12: 1 | BK12: 1 | BL12: 0 | BM12: 0 | BN12: 1 | BO12: 0 | BP12: 6 | BQ12: 2 | BR12: 1 | BS12: 1 | BT12: 0 | BU12: 0 | BV12: 0 | BW12: 0 | BX12: 0 | BY12: ТСН-2001 (МГЭ) Доп 81 - Новое строительство | BZ12: Типовой расчет для ТСН-2001 МГЭ, Дополнение 81, строительство | CA12: Территориальные сметные нормативы для Москвы ТСН-2001 (МГЭ), дополнение 81 | CB12: Территориальные сметные нормативы для Москвы ТСН-2001 (МГЭ), дополнение 81 | CC12: Территориальные сметные нормативы для Москвы ТСН-2001 (МГЭ), дополнение 81 | CD12: Территориальные сметные нормативы для Москвы ТСН-2001 (МГЭ), дополнение 81 | CE12: Поправки для ТСН-2001 от 07.04.2026 г. доп.81 | CF12: 0 | CG12: 0 | CH12: 8200 | CK12: 82 | CQ12: Территориальные сметные нормативы для Москвы (ТСН-2001) | CR12: ТЕР | CS12: 41660 | CT12: 1 | CU12: 81 | CY12: 0 | EC12: 0
A15: 15 | B15: 1
A18: 52 | B18: =B262 -> 301 | C18: =C262 -> 1 | D18: =D262 -> 12 | E18: =E262 -> 0 | F18: =F262 -> 02-01-14 | G18: =G262 -> 02-01-14 СОТ 20.07 | O18: =O262 -> 1051915.2 | P18: =P262 -> 1044881.4 | Q18: =Q262 -> 320.15 | R18: =R262 -> 33.17 | S18: =S262 -> 6713.72 | T18: =T262 -> 0 | U18: =U262 -> 460.84551 | V18: =V262 -> 0 | ... GX18: =GX262 -> 0
A20: 3 | B20: 1 | D20: =ROW(A232) -> 232 | F20: 02-01-14 | G20: Система охранного телевидения | I20: 0 | J20: 2024-00375-00-ИОС5.7 | K20: -1 | L20: 02-01-14 | S20: 0 | T20: 0 | V20: 2 | BX20: 0 | CF20: 0 | CG20: 0
A22: 52 | B22: =B232 -> 1 | C22: =C232 -> 3 | D22: =D232 -> 20 | E22: =E232 -> 0 | F22: =F232 -> 02-01-14 | G22: =G232 -> Система охранного телевидения | O22: =O232 -> 1051915.2 | P22: =P232 -> 1044881.4 | Q22: =Q232 -> 320.15 | R22: =R232 -> 33.17 | S22: =S232 -> 6713.72 | T22: =T232 -> 0 | U22: =U232 -> 460.84551 | V22: =V232 -> 0 | ... GX22: =GX232 -> 0
A24: 4 | B24: 1 | D24: =ROW(A45) -> 45 | F24: Новый раздел | G24: Демонтажные работы (Письмо от АНО «РГТ» об утверждении объёмов демонтажных работ) | I24: 0 | K24: -1 | S24: 0 | T24: 0 | V24: 2 | BX24: 0 | CJ24: 0
A26: 52 | B26: =B45 -> 1 | C26: =C45 -> 4 | D26: =D45 -> 24 | E26: =E45 -> 0 | F26: =F45 -> Новый раздел | G26: =G45 -> Демонтажные работы (Письмо от АНО «РГТ» об утверждении объёмов демонтажных работ) | O26: =O45 -> 1630.65 | P26: =P45 -> 0 | Q26: =Q45 -> 73.74 | R26: =R45 -> 7.64 | S26: =S45 -> 1556.91 | T26: =T45 -> 0 | U26: =U45 -> 106.92014 | V26: =V45 -> 0 | ... GX26: =GX45 -> 0
A28: 17 | B28: 1 | C28: =ROW(SmtRes!A4) -> 4 | D28: =ROW(EtalonRes!A5) -> 5 | E28: 1 | F28: 4.10-34-5 | G28: Монтаж коммутатора служебной связи / демонтаж Управляемого коммутатора | H28: 1 ШТ. | I28: =ROUND(1+1+4,9) -> 6 | J28: 0 | K28: =ROUND(1+1+4,9) -> 6 | O28: =ROUND(CP28,2) -> 241.87 | P28: =ROUND((ROUND((AC28*AW28*I28),2)*BC28),2) -> 0 | Q28: =(ROUND((ROUND(((((ET28*1.2)*0.3))*AV28*I28),2)*BB28),2)+ROUND((ROUND(((AE28-(((EU28*1.2)*0.3)))*AV28*I28),2)*BS28),2)) -> 64.93 | R28: =(ROUND((ROUND(((((EU28*1.2)*0.3))*AV28*I28),2)*BS28),2)+ROUND((ROUND(((AE28-(((EU28*1.2)*0.3)))*AV28*I28),2)*BS28),2)) -> 7.15 | S28: =ROUND((ROUND((AF28*AV28*I28),2)*BA28),2) -> 176.94 | T28: =ROUND(CU28*I28,2) -> 0 | U28: =CV28*I28 -> 14.021424 | V28: =CW28*I28 -> 0 | W28: =ROUND(CX28*I28,2) -> 0 | X28: =(ROUND((((S28+ROUND((ROUND(((((EU28*1.2)*0.3))*AV28*I28),2)*BS28),2))*AT28)/100),2)+ROUND(((ROUND((ROUND(((AE28-(((EU28*1.2)*0.3)))*AV28*I28),2)*BS28),2)*AT28)/100),2)) -> 165.68 | Y28: =(ROUND((((S28+ROUND((ROUND(((((EU28*1.2)*0.3))*AV28*I28),2)*BS28),2))*AU28)/100),2)+ROUND(((ROUND((ROUND(((AE28-(((EU28*1.2)*0.3)))*AV28*I28),2)*BS28),2)*AU28)/100),2)) -> 84.68 | AA28: 55934355 | AB28: =ROUND((AC28+AD28+AF28),6) -> 38.502 | AC28: =ROUND((((ES28*1)*0)),6) -> 0 | AD28: =ROUND((((((ET28*1.2)*0.3))-(((EU28*1.2)*0.3)))+AE28),6) -> 10.3356 | AE28: =ROUND((((EU28*1.2)*0.3)),6) -> 1.1376 | AF28: =ROUND((((EV28*1.2)*0.3)),6) -> 28.1664 | AG28: =ROUND((AP28),6) -> 0 | AH28: =(((EW28*1.2)*0.3)) -> 2.232 | AI28: =(((EX28*1.2)*0.3)) -> 0 | AJ28: =(AS28) -> 0 | AK28: 119.3 | AL28: 12.35 | AM28: 28.71 | AN28: 3.16 | AO28: 78.24 | AP28: 0 | AQ28: 6.2 | AR28: 0 | AS28: 0 | AT28: 90 | AU28: 46 | AV28: 1.047 | AW28: 1 | AZ28: 1 | BA28: 1 | BB28: 1 | BC28: 1 | BH28: 0 | BI28: 2 | BJ28: ТСН-2001.4 Доп. 80, Сб. 10, т. 34, поз. 5 | BM28: 68 | BN28: 0 | BO28: 4.10-34-5 | BP28: 1 | BQ28: 40 | BR28: 0 | BS28: 1 | BT28: 1 | BU28: 1 | BV28: 1 | BW28: 1 | BX28: 1 | BZ28: 90 | CA28: 46 | CE28: 1566 | CF28: 0 | CG28: 0 | CM28: 0 | CN28: Поправка: Гл.12.Прил.8.п.8. 3_12.00.01.11.001 Наименование: При наличии напряженных и стесненных условий производства работ (стесненность, сложность складирования и транспортной логистики и т.п.) для объектов, расположенных в пределах круговой магистральной системы улиц "Садовое кольцо" города Москвы Поправка: Гл.4.Прил.2.2.п.2.2.29_04.00.01.35.003 Наименование: При демонтаже оборудования, предназначенного в лом | CO28: 0 | CP28: =(P28+Q28+S28) -> 241.87 | CQ28: =ROUND((ROUND((AC28*AW28*1),2)*BC28),2) -> 0 | CR28: =(ROUND((ROUND(((((ET28*1.2)*0.3))*AV28*1),2)*BB28),2)+ROUND((ROUND(((AE28-(((EU28*1.2)*0.3)))*AV28*1),2)*BS28),2)) -> 10.82 | CS28: =(ROUND((ROUND(((((EU28*1.2)*0.3))*AV28*1),2)*BS28),2)+ROUND((ROUND(((AE28-(((EU28*1.2)*0.3)))*AV28*1),2)*BS28),2)) -> 1.19 | CT28: =ROUND((ROUND((AF28*AV28*1),2)*BA28),2) -> 29.49 | CU28: =AG28 -> 0 | CV28: =(AH28*AV28) -> 2.336904 | CW28: =AI28 -> 0 | CX28: =AJ28 -> 0 | CY28: =(ROUND((((S28+ROUND((ROUND(((((EU28*1.2)*0.3))*AV28*1),2)*BS28),2))*AT28)/100),2)+ROUND(((ROUND((ROUND(((AE28-(((EU28*1.2)*0.3)))*AV28*1),2)*BS28),2)*AT28)/100),2)) -> 160.32 | CZ28: =(ROUND((((S28+ROUND((ROUND(((((EU28*1.2)*0.3))*AV28*1),2)*BS28),2))*AU28)/100),2)+ROUND(((ROUND((ROUND(((AE28-(((EU28*1.2)*0.3)))*AV28*1),2)*BS28),2)*AU28)/100),2)) -> 81.94 | DB28: 1 | DD28: *1)*0 | DE28: *1,2)*0,3 | DF28: *1,2)*0,3 | DG28: *1,2)*0,3 | DI28: *1,2)*0,3 | DJ28: *1,2)*0,3 | DN28: 0 | DO28: 0 | DP28: 1 | DQ28: 1 | DU28: 1013 | DV28: 1 ШТ. | DW28: 1 ШТ. | DX28: 1 | EE28: 57042958 | EF28: 40 | EG28: Монтаж оборудования | EH28: 0 | EJ28: 2 | EK28: 68 | EL28: ТСН-2001.4-10. Прокладка и монтаж сетей связи | EM28: ТСН-2001.4-10-1 | EO28: Поправка: Гл.12.Прил.8.п.8. 3_12.00.01.11.001 Поправка: Гл.4.Прил.2.2.п.2.2.29_04.00.01.35.003 | EQ28: 0 | ER28: 119.3 | ES28: 12.35 | ET28: 28.71 | EU28: 3.16 | EV28: 78.24 | EW28: 6.2 | EX28: 0 | EY28: 0 | FQ28: 0 | FR28: 0 | FS28: 0 | FX28: 90 | FY28: 46 | GD28: 1 | GF28: -523956322 | GG28: 2 | GH28: 1 | GI28: 2 | GJ28: 0 | GK28: 0 | GL28: =ROUND(IF(AND(BH28=3,BI28=3,FS28<>0),P28,0),2) -> 0 | GM28: =ROUND(O28+X28+Y28,2)+GX28 -> 492.23 | GN28: =IF(OR(BI28=0,BI28=1),GM28-GX28,0) -> 0 | GO28: =IF(BI28=2,GM28-GX28,0) -> 492.23 | GP28: =IF(BI28=4,GM28-GX28,0) -> 0 | GR28: 0 | GS28: 3 | GT28: 0 | GV28: =ROUND((GT28),6) -> 0 | GW28: 1 | GX28: =ROUND(HC28*I28,2) -> 0 | HA28: 0 | HB28: 0 | HC28: =GV28*GW28 -> 0 | HS28: 0 | IK28: 0
A29: 17 | B29: 1 | C29: =ROW(SmtRes!A8) -> 8 | D29: =ROW(EtalonRes!A10) -> 10 | E29: 1 | F29: 4.10-34-5 | G29: Монтаж коммутатора служебной связи / демонтаж Управляемого коммутатора | H29: 1 ШТ. | I29: =ROUND(1+1+4,9) -> 6 | J29: 0 | K29: =ROUND(1+1+4,9) -> 6 | O29: =ROUND(CP29,2) -> 11019.84 | P29: =ROUND((ROUND((AC29*AW29*I29),2)*BC29),2) -> 0 | Q29: =(ROUND((ROUND(((((ET29*1.2)*0.3))*AV29*I29),2)*BB29),2)+ROUND((ROUND(((AE29-(((EU29*1.2)*0.3)))*AV29*I29),2)*BS29),2)) -> 1049.27 | R29: =(ROUND((ROUND(((((EU29*1.2)*0.3))*AV29*I29),2)*BS29),2)+ROUND((ROUND(((AE29-(((EU29*1.2)*0.3)))*AV29*I29),2)*BS29),2)) -> 402.9 | S29: =ROUND((ROUND((AF29*AV29*I29),2)*BA29),2) -> 9970.57 | T29: =ROUND(CU29*I29,2) -> 0 | U29: =CV29*I29 -> 14.021424 | V29: =CW29*I29 -> 0 | W29: =ROUND(CX29*I29,2) -> 0 | X29: =(ROUND((((S29+ROUND((ROUND(((((EU29*1.2)*0.3))*AV29*I29),2)*BS29),2))*AT29)/100),2)+ROUND(((ROUND((ROUND(((AE29-(((EU29*1.2)*0.3)))*AV29*I29),2)*BS29),2)*AT29)/100),2)) -> 9336.12 | Y29: =(ROUND((((S29+ROUND((ROUND(((((EU29*1.2)*0.3))*AV29*I29),2)*BS29),2))*AU29)/100),2)+ROUND(((ROUND((ROUND(((AE29-(((EU29*1.2)*0.3)))*AV29*I29),2)*BS29),2)*AU29)/100),2)) -> 4771.8 | AA29: 55934357 | AB29: =ROUND((AC29+AD29+AF29),6) -> 38.502 | AC29: =ROUND((((ES29*1)*0)),6) -> 0 | AD29: =ROUND((((((ET29*1.2)*0.3))-(((EU29*1.2)*0.3)))+AE29),6) -> 10.3356 | AE29: =ROUND((((EU29*1.2)*0.3)),6) -> 1.1376 | AF29: =ROUND((((EV29*1.2)*0.3)),6) -> 28.1664 | AG29: =ROUND((AP29),6) -> 0 | AH29: =(((EW29*1.2)*0.3)) -> 2.232 | AI29: =(((EX29*1.2)*0.3)) -> 0 | AJ29: =(AS29) -> 0 | AK29: 119.3 | AL29: 12.35 | AM29: 28.71 | AN29: 3.16 | AO29: 78.24 | AP29: 0 | AQ29: 6.2 | AR29: 0 | AS29: 0 | AT29: 90 | AU29: 46 | AV29: 1.047 | AW29: 1 | AZ29: 1 | BA29: 56.35 | BB29: 16.16 | BC29: 14.7 | BH29: 0 | BI29: 2 | BJ29: ТСН-2001.4 Доп. 80, Сб. 10, т. 34, поз. 5 | BM29: 68 | BN29: 0 | BO29: 4.10-34-5 | BP29: 1 | BQ29: 40 | BR29: 0 | BS29: 56.35 | BT29: 1 | BU29: 1 | BV29: 1 | BW29: 1 | BX29: 1 | BZ29: 90 | CA29: 46 | CE29: 1566 | CF29: 0 | CG29: 0 | CM29: 0 | CN29: Поправка: Гл.12.Прил.8.п.8. 3_12.00.01.11.001 Наименование: При наличии напряженных и стесненных условий производства работ (стесненность, сложность складирования и транспортной логистики и т.п.) для объектов, расположенных в пределах круговой магистральной системы улиц "Садовое кольцо" города Москвы Поправка: Гл.4.Прил.2.2.п.2.2.29_04.00.01.35.003 Наименование: При демонтаже оборудования, предназначенного в лом | CO29: 0 | CP29: =(P29+Q29+S29) -> 11019.84 | CQ29: =ROUND((ROUND((AC29*AW29*1),2)*BC29),2) -> 0 | CR29: =(ROUND((ROUND(((((ET29*1.2)*0.3))*AV29*1),2)*BB29),2)+ROUND((ROUND(((AE29-(((EU29*1.2)*0.3)))*AV29*1),2)*BS29),2)) -> 174.85 | CS29: =(ROUND((ROUND(((((EU29*1.2)*0.3))*AV29*1),2)*BS29),2)+ROUND((ROUND(((AE29-(((EU29*1.2)*0.3)))*AV29*1),2)*BS29),2)) -> 67.06 | CT29: =ROUND((ROUND((AF29*AV29*1),2)*BA29),2) -> 1661.76 | CU29: =AG29 -> 0 | CV29: =(AH29*AV29) -> 2.336904 | CW29: =AI29 -> 0 | CX29: =AJ29 -> 0 | CY29: =(ROUND((((S29+ROUND((ROUND(((((EU29*1.2)*0.3))*AV29*1),2)*BS29),2))*AT29)/100),2)+ROUND(((ROUND((ROUND(((AE29-(((EU29*1.2)*0.3)))*AV29*1),2)*BS29),2)*AT29)/100),2)) -> 9033.87 | CZ29: =(ROUND((((S29+ROUND((ROUND(((((EU29*1.2)*0.3))*AV29*1),2)*BS29),2))*AU29)/100),2)+ROUND(((ROUND((ROUND(((AE29-(((EU29*1.2)*0.3)))*AV29*1),2)*BS29),2)*AU29)/100),2)) -> 4617.31 | DB29: 3 | DD29: *1)*0 | DE29: *1,2)*0,3 | DF29: *1,2)*0,3 | DG29: *1,2)*0,3 | DI29: *1,2)*0,3 | DJ29: *1,2)*0,3 | DN29: 0 | DO29: 0 | DP29: 1 | DQ29: 1 | DU29: 1013 | DV29: 1 ШТ. | DW29: 1 ШТ. | DX29: 1 | EE29: 57042958 | EF29: 40 | EG29: Монтаж оборудования | EH29: 0 | EJ29: 2 | EK29: 68 | EL29: ТСН-2001.4-10. Прокладка и монтаж сетей связи | EM29: ТСН-2001.4-10-1 | EO29: Поправка: Гл.12.Прил.8.п.8. 3_12.00.01.11.001 Поправка: Гл.4.Прил.2.2.п.2.2.29_04.00.01.35.003 | EQ29: 0 | ER29: 119.3 | ES29: 12.35 | ET29: 28.71 | EU29: 3.16 | EV29: 78.24 | EW29: 6.2 | EX29: 0 | EY29: 0 | FQ29: 0 | FR29: 0 | FS29: 0 | FX29: 90 | FY29: 46 | GD29: 1 | GF29: -523956322 | GG29: 2 | GH29: 1 | GI29: 2 | GJ29: 0 | GK29: 0 | GL29: =ROUND(IF(AND(BH29=3,BI29=3,FS29<>0),P29,0),2) -> 0 | GM29: =ROUND(O29+X29+Y29,2)+GX29 -> 25127.76 | GN29: =IF(OR(BI29=0,BI29=1),GM29-GX29,0) -> 0 | GO29: =IF(BI29=2,GM29-GX29,0) -> 25127.76 | GP29: =IF(BI29=4,GM29-GX29,0) -> 0 | GR29: 0 | GS29: 3 | GT29: 0 | GV29: =ROUND((GT29),6) -> 0 | GW29: 1 | GX29: =ROUND(HC29*I29,2) -> 0 | HA29: 0 | HB29: 0 | HC29: =GV29*GW29 -> 0 | HS29: 0 | IK29: 0
A30: 17 | B30: 1 | C30: =ROW(SmtRes!A13) -> 13 | D30: =ROW(EtalonRes!A17) -> 17 | E30: 2 | F30: 4.10-72-14 | G30: Монтаж устройства цифровой регистрации / демонтаж сервера объектового контроля | H30: 1 устройство | I30: 1 | J30: 0 | K30: 1 | O30: =ROUND(CP30,2) -> 35.85 | P30: =ROUND((ROUND((AC30*AW30*I30),2)*BC30),2) -> 0 | Q30: =(ROUND((ROUND(((((ET30*1.2)*0.3))*AV30*I30),2)*BB30),2)+ROUND((ROUND(((AE30-(((EU30*1.2)*0.3)))*AV30*I30),2)*BS30),2)) -> 0 | R30: =(ROUND((ROUND(((((EU30*1.2)*0.3))*AV30*I30),2)*BS30),2)+ROUND((ROUND(((AE30-(((EU30*1.2)*0.3)))*AV30*I30),2)*BS30),2)) -> 0 | S30: =ROUND((ROUND((AF30*AV30*I30),2)*BA30),2) -> 35.85 | T30: =ROUND(CU30*I30,2) -> 0 | U30: =CV30*I30 -> 3.01536 | V30: =CW30*I30 -> 0 | W30: =ROUND(CX30*I30,2) -> 0 | X30: =(ROUND((((S30+ROUND((ROUND(((((EU30*1.2)*0.3))*AV30*I30),2)*BS30),2))*AT30)/100),2)+ROUND(((ROUND((ROUND(((AE30-(((EU30*1.2)*0.3)))*AV30*I30),2)*BS30),2)*AT30)/100),2)) -> 34.06 | Y30: =(ROUND((((S30+ROUND((ROUND(((((EU30*1.2)*0.3))*AV30*I30),2)*BS30),2))*AU30)/100),2)+ROUND(((ROUND((ROUND(((AE30-(((EU30*1.2)*0.3)))*AV30*I30),2)*BS30),2)*AU30)/100),2)) -> 19 | AA30: 55934355 | AB30: =ROUND((AC30+AD30+AF30),6) -> 34.2432 | AC30: =ROUND((((ES30*1)*0)),6) -> 0 | AD30: =ROUND((((((ET30*1.2)*0.3))-(((EU30*1.2)*0.3)))+AE30),6) -> 0 | AE30: =ROUND((((EU30*1.2)*0.3)),6) -> 0 | AF30: =ROUND((((EV30*1.2)*0.3)),6) -> 34.2432 | AG30: =ROUND((AP30),6) -> 0 | AH30: =(((EW30*1.2)*0.3)) -> 2.88 | AI30: =(((EX30*1.2)*0.3)) -> 0 | AJ30: =(AS30) -> 0 | AK30: 96.22 | AL30: 1.1 | AM30: 0 | AN30: 0 | AO30: 95.12 | AP30: 0 | AQ30: 8 | AR30: 0 | AS30: 0 | AT30: 95 | AU30: 53 | AV30: 1.047 | AW30: 1 | AZ30: 1 | BA30: 1 | BB30: 1 | BC30: 1 | BH30: 0 | BI30: 2 | BJ30: ТСН-2001.4 Доп. 67, Сб. 10, т. 72, поз. 14 | BM30: 69 | BN30: 0 | BO30: 4.10-72-14 | BP30: 1 | BQ30: 40 | BR30: 0 | BS30: 1 | BT30: 1 | BU30: 1 | BV30: 1 | BW30: 1 | BX30: 1 | BZ30: 95 | CA30: 53 | CE30: 1566 | CF30: 0 | CG30: 0 | CM30: 0 | CN30: Поправка: Гл.12.Прил.8.п.8. 3_12.00.01.11.001 Наименование: При наличии напряженных и стесненных условий производства работ (стесненность, сложность складирования и транспортной логистики и т.п.) для объектов, расположенных в пределах круговой магистральной системы улиц "Садовое кольцо" города Москвы Поправка: Гл.4.Прил.2.2.п.2.2.29_04.00.01.35.003 Наименование: При демонтаже оборудования, предназначенного в лом | CO30: 0 | CP30: =(P30+Q30+S30) -> 35.85 | CQ30: =ROUND((ROUND((AC30*AW30*1),2)*BC30),2) -> 0 | CR30: =(ROUND((ROUND(((((ET30*1.2)*0.3))*AV30*1),2)*BB30),2)+ROUND((ROUND(((AE30-(((EU30*1.2)*0.3)))*AV30*1),2)*BS30),2)) -> 0 | CS30: =(ROUND((ROUND(((((EU30*1.2)*0.3))*AV30*1),2)*BS30),2)+ROUND((ROUND(((AE30-(((EU30*1.2)*0.3)))*AV30*1),2)*BS30),2)) -> 0 | CT30: =ROUND((ROUND((AF30*AV30*1),2)*BA30),2) -> 35.85 | CU30: =AG30 -> 0 | CV30: =(AH30*AV30) -> 3.01536 | CW30: =AI30 -> 0 | CX30: =AJ30 -> 0 | CY30: =(ROUND((((S30+ROUND((ROUND(((((EU30*1.2)*0.3))*AV30*1),2)*BS30),2))*AT30)/100),2)+ROUND(((ROUND((ROUND(((AE30-(((EU30*1.2)*0.3)))*AV30*1),2)*BS30),2)*AT30)/100),2)) -> 34.06 | CZ30: =(ROUND((((S30+ROUND((ROUND(((((EU30*1.2)*0.3))*AV30*1),2)*BS30),2))*AU30)/100),2)+ROUND(((ROUND((ROUND(((AE30-(((EU30*1.2)*0.3)))*AV30*1),2)*BS30),2)*AU30)/100),2)) -> 19 | DB30: 5 | DD30: *1)*0 | DE30: *1,2)*0,3 | DF30: *1,2)*0,3 | DG30: *1,2)*0,3 | DI30: *1,2)*0,3 | DJ30: *1,2)*0,3 | DN30: 0 | DO30: 0 | DP30: 1 | DQ30: 1 | DU30: 1013 | DV30: 1 устройство | DW30: 1 устройство | DX30: 1 | EE30: 57042959 | EF30: 40 | EG30: Монтаж оборудования | EH30: 0 | EJ30: 2 | EK30: 69 | EL30: ТСН-2001.4-10. Монтаж радиотелевизионного и электронного оборудования | EM30: ТСН-2001.4-10-2 | EO30: Поправка: Гл.12.Прил.8.п.8. 3_12.00.01.11.001 Поправка: Гл.4.Прил.2.2.п.2.2.29_04.00.01.35.003 | EQ30: 0 | ER30: 96.22 | ES30: 1.1 | ET30: 0 | EU30: 0 | EV30: 95.12 | EW30: 8 | EX30: 0 | EY30: 0 | FQ30: 0 | FR30: 0 | FS30: 0 | FX30: 95 | FY30: 53 | GD30: 1 | GF30: 275144487 | GG30: 2 | GH30: 1 | GI30: 2 | GJ30: 0 | GK30: 0 | GL30: =ROUND(IF(AND(BH30=3,BI30=3,FS30<>0),P30,0),2) -> 0 | GM30: =ROUND(O30+X30+Y30,2)+GX30 -> 88.91 | GN30: =IF(OR(BI30=0,BI30=1),GM30-GX30,0) -> 0 | GO30: =IF(BI30=2,GM30-GX30,0) -> 88.91 | GP30: =IF(BI30=4,GM30-GX30,0) -> 0 | GR30: 0 | GS30: 3 | GT30: 0 | GV30: =ROUND((GT30),6) -> 0 | GW30: 1 | GX30: =ROUND(HC30*I30,2) -> 0 | HA30: 0 | HB30: 0 | HC30: =GV30*GW30 -> 0 | HS30: 0 | IK30: 0
A31: 17 | B31: 1 | C31: =ROW(SmtRes!A18) -> 18 | D31: =ROW(EtalonRes!A24) -> 24 | E31: 2 | F31: 4.10-72-14 | G31: Монтаж устройства цифровой регистрации / демонтаж сервера объектового контроля | H31: 1 устройство | I31: 1 | J31: 0 | K31: 1 | O31: =ROUND(CP31,2) -> 2020.15 | P31: =ROUND((ROUND((AC31*AW31*I31),2)*BC31),2) -> 0 | Q31: =(ROUND((ROUND(((((ET31*1.2)*0.3))*AV31*I31),2)*BB31),2)+ROUND((ROUND(((AE31-(((EU31*1.2)*0.3)))*AV31*I31),2)*BS31),2)) -> 0 | R31: =(ROUND((ROUND(((((EU31*1.2)*0.3))*AV31*I31),2)*BS31),2)+ROUND((ROUND(((AE31-(((EU31*1.2)*0.3)))*AV31*I31),2)*BS31),2)) -> 0 | S31: =ROUND((ROUND((AF31*AV31*I31),2)*BA31),2) -> 2020.15 | T31: =ROUND(CU31*I31,2) -> 0 | U31: =CV31*I31 -> 3.01536 | V31: =CW31*I31 -> 0 | W31: =ROUND(CX31*I31,2) -> 0 | X31: =(ROUND((((S31+ROUND((ROUND(((((EU31*1.2)*0.3))*AV31*I31),2)*BS31),2))*AT31)/100),2)+ROUND(((ROUND((ROUND(((AE31-(((EU31*1.2)*0.3)))*AV31*I31),2)*BS31),2)*AT31)/100),2)) -> 1919.14 | Y31: =(ROUND((((S31+ROUND((ROUND(((((EU31*1.2)*0.3))*AV31*I31),2)*BS31),2))*AU31)/100),2)+ROUND(((ROUND((ROUND(((AE31-(((EU31*1.2)*0.3)))*AV31*I31),2)*BS31),2)*AU31)/100),2)) -> 1070.68 | AA31: 55934357 | AB31: =ROUND((AC31+AD31+AF31),6) -> 34.2432 | AC31: =ROUND((((ES31*1)*0)),6) -> 0 | AD31: =ROUND((((((ET31*1.2)*0.3))-(((EU31*1.2)*0.3)))+AE31),6) -> 0 | AE31: =ROUND((((EU31*1.2)*0.3)),6) -> 0 | AF31: =ROUND((((EV31*1.2)*0.3)),6) -> 34.2432 | AG31: =ROUND((AP31),6) -> 0 | AH31: =(((EW31*1.2)*0.3)) -> 2.88 | AI31: =(((EX31*1.2)*0.3)) -> 0 | AJ31: =(AS31) -> 0 | AK31: 96.22 | AL31: 1.1 | AM31: 0 | AN31: 0 | AO31: 95.12 | AP31: 0 | AQ31: 8 | AR31: 0 | AS31: 0 | AT31: 95 | AU31: 53 | AV31: 1.047 | AW31: 1 | AZ31: 1 | BA31: 56.35 | BB31: 1 | BC31: 16.59 | BH31: 0 | BI31: 2 | BJ31: ТСН-2001.4 Доп. 67, Сб. 10, т. 72, поз. 14 | BM31: 69 | BN31: 0 | BO31: 4.10-72-14 | BP31: 1 | BQ31: 40 | BR31: 0 | BS31: 56.35 | BT31: 1 | BU31: 1 | BV31: 1 | BW31: 1 | BX31: 1 | BZ31: 95 | CA31: 53 | CE31: 1566 | CF31: 0 | CG31: 0 | CM31: 0 | CN31: Поправка: Гл.12.Прил.8.п.8. 3_12.00.01.11.001 Наименование: При наличии напряженных и стесненных условий производства работ (стесненность, сложность складирования и транспортной логистики и т.п.) для объектов, расположенных в пределах круговой магистральной системы улиц "Садовое кольцо" города Москвы Поправка: Гл.4.Прил.2.2.п.2.2.29_04.00.01.35.003 Наименование: При демонтаже оборудования, предназначенного в лом | CO31: 0 | CP31: =(P31+Q31+S31) -> 2020.15 | CQ31: =ROUND((ROUND((AC31*AW31*1),2)*BC31),2) -> 0 | CR31: =(ROUND((ROUND(((((ET31*1.2)*0.3))*AV31*1),2)*BB31),2)+ROUND((ROUND(((AE31-(((EU31*1.2)*0.3)))*AV31*1),2)*BS31),2)) -> 0 | CS31: =(ROUND((ROUND(((((EU31*1.2)*0.3))*AV31*1),2)*BS31),2)+ROUND((ROUND(((AE31-(((EU31*1.2)*0.3)))*AV31*1),2)*BS31),2)) -> 0 | CT31: =ROUND((ROUND((AF31*AV31*1),2)*BA31),2) -> 2020.15 | CU31: =AG31 -> 0 | CV31: =(AH31*AV31) -> 3.01536 | CW31: =AI31 -> 0 | CX31: =AJ31 -> 0 | CY31: =(ROUND((((S31+ROUND((ROUND(((((EU31*1.2)*0.3))*AV31*1),2)*BS31),2))*AT31)/100),2)+ROUND(((ROUND((ROUND(((AE31-(((EU31*1.2)*0.3)))*AV31*1),2)*BS31),2)*AT31)/100),2)) -> 1919.14 | CZ31: =(ROUND((((S31+ROUND((ROUND(((((EU31*1.2)*0.3))*AV31*1),2)*BS31),2))*AU31)/100),2)+ROUND(((ROUND((ROUND(((AE31-(((EU31*1.2)*0.3)))*AV31*1),2)*BS31),2)*AU31)/100),2)) -> 1070.68 | DB31: 7 | DD31: *1)*0 | DE31: *1,2)*0,3 | DF31: *1,2)*0,3 | DG31: *1,2)*0,3 | DI31: *1,2)*0,3 | DJ31: *1,2)*0,3 | DN31: 0 | DO31: 0 | DP31: 1 | DQ31: 1 | DU31: 1013 | DV31: 1 устройство | DW31: 1 устройство | DX31: 1 | EE31: 57042959 | EF31: 40 | EG31: Монтаж оборудования | EH31: 0 | EJ31: 2 | EK31: 69 | EL31: ТСН-2001.4-10. Монтаж радиотелевизионного и электронного оборудования | EM31: ТСН-2001.4-10-2 | EO31: Поправка: Гл.12.Прил.8.п.8. 3_12.00.01.11.001 Поправка: Гл.4.Прил.2.2.п.2.2.29_04.00.01.35.003 | EQ31: 0 | ER31: 96.22 | ES31: 1.1 | ET31: 0 | EU31: 0 | EV31: 95.12 | EW31: 8 | EX31: 0 | EY31: 0 | FQ31: 0 | FR31: 0 | FS31: 0 | FX31: 95 | FY31: 53 | GD31: 1 | GF31: 275144487 | GG31: 2 | GH31: 1 | GI31: 2 | GJ31: 0 | GK31: 0 | GL31: =ROUND(IF(AND(BH31=3,BI31=3,FS31<>0),P31,0),2) -> 0 | GM31: =ROUND(O31+X31+Y31,2)+GX31 -> 5009.97 | GN31: =IF(OR(BI31=0,BI31=1),GM31-GX31,0) -> 0 | GO31: =IF(BI31=2,GM31-GX31,0) -> 5009.97 | GP31: =IF(BI31=4,GM31-GX31,0) -> 0 | GR31: 0 | GS31: 3 | GT31: 0 | GV31: =ROUND((GT31),6) -> 0 | GW31: 1 | GX31: =ROUND(HC31*I31,2) -> 0 | HA31: 0 | HB31: 0 | HC31: =GV31*GW31 -> 0 | HS31: 0 | IK31: 0
A32: 17 | B32: 1 | C32: =ROW(SmtRes!A23) -> 23 | D32: =ROW(EtalonRes!A31) -> 31 | E32: 3 | F32: 4.10-72-14 | G32: Монтаж устройства цифровой регистрации / демонтаж специализированной рабочей станции | H32: 1 устройство | I32: 1 | J32: 0 | K32: 1 | O32: =ROUND(CP32,2) -> 35.85 | P32: =ROUND((ROUND((AC32*AW32*I32),2)*BC32),2) -> 0 | Q32: =(ROUND((ROUND(((((ET32*1.2)*0.3))*AV32*I32),2)*BB32),2)+ROUND((ROUND(((AE32-(((EU32*1.2)*0.3)))*AV32*I32),2)*BS32),2)) -> 0 | R32: =(ROUND((ROUND(((((EU32*1.2)*0.3))*AV32*I32),2)*BS32),2)+ROUND((ROUND(((AE32-(((EU32*1.2)*0.3)))*AV32*I32),2)*BS32),2)) -> 0 | S32: =ROUND((ROUND((AF32*AV32*I32),2)*BA32),2) -> 35.85 | T32: =ROUND(CU32*I32,2) -> 0 | U32: =CV32*I32 -> 3.01536 | V32: =CW32*I32 -> 0 | W32: =ROUND(CX32*I32,2) -> 0 | X32: =(ROUND((((S32+ROUND((ROUND(((((EU32*1.2)*0.3))*AV32*I32),2)*BS32),2))*AT32)/100),2)+ROUND(((ROUND((ROUND(((AE32-(((EU32*1.2)*0.3)))*AV32*I32),2)*BS32),2)*AT32)/100),2)) -> 34.06 | Y32: =(ROUND((((S32+ROUND((ROUND(((((EU32*1.2)*0.3))*AV32*I32),2)*BS32),2))*AU32)/100),2)+ROUND(((ROUND((ROUND(((AE32-(((EU32*1.2)*0.3)))*AV32*I32),2)*BS32),2)*AU32)/100),2)) -> 19 | AA32: 55934355 | AB32: =ROUND((AC32+AD32+AF32),6) -> 34.2432 | AC32: =ROUND((((ES32*1)*0)),6) -> 0 | AD32: =ROUND((((((ET32*1.2)*0.3))-(((EU32*1.2)*0.3)))+AE32),6) -> 0 | AE32: =ROUND((((EU32*1.2)*0.3)),6) -> 0 | AF32: =ROUND((((EV32*1.2)*0.3)),6) -> 34.2432 | AG32: =ROUND((AP32),6) -> 0 | AH32: =(((EW32*1.2)*0.3)) -> 2.88 | AI32: =(((EX32*1.2)*0.3)) -> 0 | AJ32: =(AS32) -> 0 | AK32: 96.22 | AL32: 1.1 | AM32: 0 | AN32: 0 | AO32: 95.12 | AP32: 0 | AQ32: 8 | AR32: 0 | AS32: 0 | AT32: 95 | AU32: 53 | AV32: 1.047 | AW32: 1 | AZ32: 1 | BA32: 1 | BB32: 1 | BC32: 1 | BH32: 0 | BI32: 2 | BJ32: ТСН-2001.4 Доп. 67, Сб. 10, т. 72, поз. 14 | BM32: 69 | BN32: 0 | BO32: 4.10-72-14 | BP32: 1 | BQ32: 40 | BR32: 0 | BS32: 1 | BT32: 1 | BU32: 1 | BV32: 1 | BW32: 1 | BX32: 1 | BZ32: 95 | CA32: 53 | CE32: 1566 | CF32: 0 | CG32: 0 | CM32: 0 | CN32: Поправка: Гл.12.Прил.8.п.8. 3_12.00.01.11.001 Наименование: При наличии напряженных и стесненных условий производства работ (стесненность, сложность складирования и транспортной логистики и т.п.) для объектов, расположенных в пределах круговой магистральной системы улиц "Садовое кольцо" города Москвы Поправка: Гл.4.Прил.2.2.п.2.2.29_04.00.01.35.003 Наименование: При демонтаже оборудования, предназначенного в лом | CO32: 0 | CP32: =(P32+Q32+S32) -> 35.85 | CQ32: =ROUND((ROUND((AC32*AW32*1),2)*BC32),2) -> 0 | CR32: =(ROUND((ROUND(((((ET32*1.2)*0.3))*AV32*1),2)*BB32),2)+ROUND((ROUND(((AE32-(((EU32*1.2)*0.3)))*AV32*1),2)*BS32),2)) -> 0 | CS32: =(ROUND((ROUND(((((EU32*1.2)*0.3))*AV32*1),2)*BS32),2)+ROUND((ROUND(((AE32-(((EU32*1.2)*0.3)))*AV32*1),2)*BS32),2)) -> 0 | CT32: =ROUND((ROUND((AF32*AV32*1),2)*BA32),2) -> 35.85 | CU32: =AG32 -> 0 | CV32: =(AH32*AV32) -> 3.01536 | CW32: =AI32 -> 0 | CX32: =AJ32 -> 0 | CY32: =(ROUND((((S32+ROUND((ROUND(((((EU32*1.2)*0.3))*AV32*1),2)*BS32),2))*AT32)/100),2)+ROUND(((ROUND((ROUND(((AE32-(((EU32*1.2)*0.3)))*AV32*1),2)*BS32),2)*AT32)/100),2)) -> 34.06 | CZ32: =(ROUND((((S32+ROUND((ROUND(((((EU32*1.2)*0.3))*AV32*1),2)*BS32),2))*AU32)/100),2)+ROUND(((ROUND((ROUND(((AE32-(((EU32*1.2)*0.3)))*AV32*1),2)*BS32),2)*AU32)/100),2)) -> 19 | DB32: 9 | DD32: *1)*0 | DE32: *1,2)*0,3 | DF32: *1,2)*0,3 | DG32: *1,2)*0,3 | DI32: *1,2)*0,3 | DJ32: *1,2)*0,3 | DN32: 0 | DO32: 0 | DP32: 1 | DQ32: 1 | DU32: 1013 | DV32: 1 устройство | DW32: 1 устройство | DX32: 1 | EE32: 57042959 | EF32: 40 | EG32: Монтаж оборудования | EH32: 0 | EJ32: 2 | EK32: 69 | EL32: ТСН-2001.4-10. Монтаж радиотелевизионного и электронного оборудования | EM32: ТСН-2001.4-10-2 | EO32: Поправка: Гл.12.Прил.8.п.8. 3_12.00.01.11.001 Поправка: Гл.4.Прил.2.2.п.2.2.29_04.00.01.35.003 | EQ32: 0 | ER32: 96.22 | ES32: 1.1 | ET32: 0 | EU32: 0 | EV32: 95.12 | EW32: 8 | EX32: 0 | EY32: 0 | FQ32: 0 | FR32: 0 | FS32: 0 | FX32: 95 | FY32: 53 | GD32: 1 | GF32: -2098133405 | GG32: 2 | GH32: 1 | GI32: 2 | GJ32: 0 | GK32: 0 | GL32: =ROUND(IF(AND(BH32=3,BI32=3,FS32<>0),P32,0),2) -> 0 | GM32: =ROUND(O32+X32+Y32,2)+GX32 -> 88.91 | GN32: =IF(OR(BI32=0,BI32=1),GM32-GX32,0) -> 0 | GO32: =IF(BI32=2,GM32-GX32,0) -> 88.91 | GP32: =IF(BI32=4,GM32-GX32,0) -> 0 | GR32: 0 | GS32: 3 | GT32: 0 | GV32: =ROUND((GT32),6) -> 0 | GW32: 1 | GX32: =ROUND(HC32*I32,2) -> 0 | HA32: 0 | HB32: 0 | HC32: =GV32*GW32 -> 0 | HS32: 0 | IK32: 0
A33: 17 | B33: 1 | C33: =ROW(SmtRes!A28) -> 28 | D33: =ROW(EtalonRes!A38) -> 38 | E33: 3 | F33: 4.10-72-14 | G33: Монтаж устройства цифровой регистрации / демонтаж специализированной рабочей станции | H33: 1 устройство | I33: 1 | J33: 0 | K33: 1 | O33: =ROUND(CP33,2) -> 2020.15 | P33: =ROUND((ROUND((AC33*AW33*I33),2)*BC33),2) -> 0 | Q33: =(ROUND((ROUND(((((ET33*1.2)*0.3))*AV33*I33),2)*BB33),2)+ROUND((ROUND(((AE33-(((EU33*1.2)*0.3)))*AV33*I33),2)*BS33),2)) -> 0 | R33: =(ROUND((ROUND(((((EU33*1.2)*0.3))*AV33*I33),2)*BS33),2)+ROUND((ROUND(((AE33-(((EU33*1.2)*0.3)))*AV33*I33),2)*BS33),2)) -> 0 | S33: =ROUND((ROUND((AF33*AV33*I33),2)*BA33),2) -> 2020.15 | T33: =ROUND(CU33*I33,2) -> 0 | U33: =CV33*I33 -> 3.01536 | V33: =CW33*I33 -> 0 | W33: =ROUND(CX33*I33,2) -> 0 | X33: =(ROUND((((S33+ROUND((ROUND(((((EU33*1.2)*0.3))*AV33*I33),2)*BS33),2))*AT33)/100),2)+ROUND(((ROUND((ROUND(((AE33-(((EU33*1.2)*0.3)))*AV33*I33),2)*BS33),2)*AT33)/100),2)) -> 1919.14 | Y33: =(ROUND((((S33+ROUND((ROUND(((((EU33*1.2)*0.3))*AV33*I33),2)*BS33),2))*AU33)/100),2)+ROUND(((ROUND((ROUND(((AE33-(((EU33*1.2)*0.3)))*AV33*I33),2)*BS33),2)*AU33)/100),2)) -> 1070.68 | AA33: 55934357 | AB33: =ROUND((AC33+AD33+AF33),6) -> 34.2432 | AC33: =ROUND((((ES33*1)*0)),6) -> 0 | AD33: =ROUND((((((ET33*1.2)*0.3))-(((EU33*1.2)*0.3)))+AE33),6) -> 0 | AE33: =ROUND((((EU33*1.2)*0.3)),6) -> 0 | AF33: =ROUND((((EV33*1.2)*0.3)),6) -> 34.2432 | AG33: =ROUND((AP33),6) -> 0 | AH33: =(((EW33*1.2)*0.3)) -> 2.88 | AI33: =(((EX33*1.2)*0.3)) -> 0 | AJ33: =(AS33) -> 0 | AK33: 96.22 | AL33: 1.1 | AM33: 0 | AN33: 0 | AO33: 95.12 | AP33: 0 | AQ33: 8 | AR33: 0 | AS33: 0 | AT33: 95 | AU33: 53 | AV33: 1.047 | AW33: 1 | AZ33: 1 | BA33: 56.35 | BB33: 1 | BC33: 16.59 | BH33: 0 | BI33: 2 | BJ33: ТСН-2001.4 Доп. 67, Сб. 10, т. 72, поз. 14 | BM33: 69 | BN33: 0 | BO33: 4.10-72-14 | BP33: 1 | BQ33: 40 | BR33: 0 | BS33: 56.35 | BT33: 1 | BU33: 1 | BV33: 1 | BW33: 1 | BX33: 1 | BZ33: 95 | CA33: 53 | CE33: 1566 | CF33: 0 | CG33: 0 | CM33: 0 | CN33: Поправка: Гл.12.Прил.8.п.8. 3_12.00.01.11.001 Наименование: При наличии напряженных и стесненных условий производства работ (стесненность, сложность складирования и транспортной логистики и т.п.) для объектов, расположенных в пределах круговой магистральной системы улиц "Садовое кольцо" города Москвы Поправка: Гл.4.Прил.2.2.п.2.2.29_04.00.01.35.003 Наименование: При демонтаже оборудования, предназначенного в лом | CO33: 0 | CP33: =(P33+Q33+S33) -> 2020.15 | CQ33: =ROUND((ROUND((AC33*AW33*1),2)*BC33),2) -> 0 | CR33: =(ROUND((ROUND(((((ET33*1.2)*0.3))*AV33*1),2)*BB33),2)+ROUND((ROUND(((AE33-(((EU33*1.2)*0.3)))*AV33*1),2)*BS33),2)) -> 0 | CS33: =(ROUND((ROUND(((((EU33*1.2)*0.3))*AV33*1),2)*BS33),2)+ROUND((ROUND(((AE33-(((EU33*1.2)*0.3)))*AV33*1),2)*BS33),2)) -> 0 | CT33: =ROUND((ROUND((AF33*AV33*1),2)*BA33),2) -> 2020.15 | CU33: =AG33 -> 0 | CV33: =(AH33*AV33) -> 3.01536 | CW33: =AI33 -> 0 | CX33: =AJ33 -> 0 | CY33: =(ROUND((((S33+ROUND((ROUND(((((EU33*1.2)*0.3))*AV33*1),2)*BS33),2))*AT33)/100),2)+ROUND(((ROUND((ROUND(((AE33-(((EU33*1.2)*0.3)))*AV33*1),2)*BS33),2)*AT33)/100),2)) -> 1919.14 | CZ33: =(ROUND((((S33+ROUND((ROUND(((((EU33*1.2)*0.3))*AV33*1),2)*BS33),2))*AU33)/100),2)+ROUND(((ROUND((ROUND(((AE33-(((EU33*1.2)*0.3)))*AV33*1),2)*BS33),2)*AU33)/100),2)) -> 1070.68 | DB33: 11 | DD33: *1)*0 | DE33: *1,2)*0,3 | DF33: *1,2)*0,3 | DG33: *1,2)*0,3 | DI33: *1,2)*0,3 | DJ33: *1,2)*0,3 | DN33: 0 | DO33: 0 | DP33: 1 | DQ33: 1 | DU33: 1013 | DV33: 1 устройство | DW33: 1 устройство | DX33: 1 | EE33: 57042959 | EF33: 40 | EG33: Монтаж оборудования | EH33: 0 | EJ33: 2 | EK33: 69 | EL33: ТСН-2001.4-10. Монтаж радиотелевизионного и электронного оборудования | EM33: ТСН-2001.4-10-2 | EO33: Поправка: Гл.12.Прил.8.п.8. 3_12.00.01.11.001 Поправка: Гл.4.Прил.2.2.п.2.2.29_04.00.01.35.003 | EQ33: 0 | ER33: 96.22 | ES33: 1.1 | ET33: 0 | EU33: 0 | EV33: 95.12 | EW33: 8 | EX33: 0 | EY33: 0 | FQ33: 0 | FR33: 0 | FS33: 0 | FX33: 95 | FY33: 53 | GD33: 1 | GF33: -2098133405 | GG33: 2 | GH33: 1 | GI33: 2 | GJ33: 0 | GK33: 0 | GL33: =ROUND(IF(AND(BH33=3,BI33=3,FS33<>0),P33,0),2) -> 0 | GM33: =ROUND(O33+X33+Y33,2)+GX33 -> 5009.97 | GN33: =IF(OR(BI33=0,BI33=1),GM33-GX33,0) -> 0 | GO33: =IF(BI33=2,GM33-GX33,0) -> 5009.97 | GP33: =IF(BI33=4,GM33-GX33,0) -> 0 | GR33: 0 | GS33: 3 | GT33: 0 | GV33: =ROUND((GT33),6) -> 0 | GW33: 1 | GX33: =ROUND(HC33*I33,2) -> 0 | HA33: 0 | HB33: 0 | HC33: =GV33*GW33 -> 0 | HS33: 0 | IK33: 0
A34: 17 | B34: 1 | C34: =ROW(SmtRes!A33) -> 33 | D34: =ROW(EtalonRes!A45) -> 45 | E34: 4 | F34: 4.10-75-6 | G34: Монтаж аппаратуры настольной массой до 20 кг / демонтаж монитора | H34: 1 ШТ. | I34: 2 | J34: 0 | K34: 2 | O34: =ROUND(CP34,2) -> 66.59 | P34: =ROUND((ROUND((AC34*AW34*I34),2)*BC34),2) -> 0 | Q34: =(ROUND((ROUND(((((ET34*1.2)*0.3))*AV34*I34),2)*BB34),2)+ROUND((ROUND(((AE34-(((EU34*1.2)*0.3)))*AV34*I34),2)*BS34),2)) -> 0 | R34: =(ROUND((ROUND(((((EU34*1.2)*0.3))*AV34*I34),2)*BS34),2)+ROUND((ROUND(((AE34-(((EU34*1.2)*0.3)))*AV34*I34),2)*BS34),2)) -> 0 | S34: =ROUND((ROUND((AF34*AV34*I34),2)*BA34),2) -> 66.59 | T34: =ROUND(CU34*I34,2) -> 0 | U34: =CV34*I34 -> 5.27688 | V34: =CW34*I34 -> 0 | W34: =ROUND(CX34*I34,2) -> 0 | X34: =(ROUND((((S34+ROUND((ROUND(((((EU34*1.2)*0.3))*AV34*I34),2)*BS34),2))*AT34)/100),2)+ROUND(((ROUND((ROUND(((AE34-(((EU34*1.2)*0.3)))*AV34*I34),2)*BS34),2)*AT34)/100),2)) -> 63.26 | Y34: =(ROUND((((S34+ROUND((ROUND(((((EU34*1.2)*0.3))*AV34*I34),2)*BS34),2))*AU34)/100),2)+ROUND(((ROUND((ROUND(((AE34-(((EU34*1.2)*0.3)))*AV34*I34),2)*BS34),2)*AU34)/100),2)) -> 35.29 | AA34: 55934355 | AB34: =ROUND((AC34+AD34+AF34),6) -> 31.8024 | AC34: =ROUND((((ES34*1)*0)),6) -> 0 | AD34: =ROUND((((((ET34*1.2)*0.3))-(((EU34*1.2)*0.3)))+AE34),6) -> 0 | AE34: =ROUND((((EU34*1.2)*0.3)),6) -> 0 | AF34: =ROUND((((EV34*1.2)*0.3)),6) -> 31.8024 | AG34: =ROUND((AP34),6) -> 0 | AH34: =(((EW34*1.2)*0.3)) -> 2.52 | AI34: =(((EX34*1.2)*0.3)) -> 0 | AJ34: =(AS34) -> 0 | AK34: 123.21 | AL34: 34.87 | AM34: 0 | AN34: 0 | AO34: 88.34 | AP34: 0 | AQ34: 7 | AR34: 0 | AS34: 0 | AT34: 95 | AU34: 53 | AV34: 1.047 | AW34: 1 | AZ34: 1 | BA34: 1 | BB34: 1 | BC34: 1 | BH34: 0 | BI34: 2 | BJ34: ТСН-2001.4 Доп. 79, Сб. 10, т. 75, поз. 6 | BM34: 69 | BN34: 0 | BO34: 4.10-75-6 | BP34: 1 | BQ34: 40 | BR34: 0 | BS34: 1 | BT34: 1 | BU34: 1 | BV34: 1 | BW34: 1 | BX34: 1 | BZ34: 95 | CA34: 53 | CE34: 1566 | CF34: 0 | CG34: 0 | CM34: 0 | CN34: Поправка: Гл.12.Прил.8.п.8. 3_12.00.01.11.001 Наименование: При наличии напряженных и стесненных условий производства работ (стесненность, сложность складирования и транспортной логистики и т.п.) для объектов, расположенных в пределах круговой магистральной системы улиц "Садовое кольцо" города Москвы Поправка: Гл.4.Прил.2.2.п.2.2.29_04.00.01.35.003 Наименование: При демонтаже оборудования, предназначенного в лом | CO34: 0 | CP34: =(P34+Q34+S34) -> 66.59 | CQ34: =ROUND((ROUND((AC34*AW34*1),2)*BC34),2) -> 0 | CR34: =(ROUND((ROUND(((((ET34*1.2)*0.3))*AV34*1),2)*BB34),2)+ROUND((ROUND(((AE34-(((EU34*1.2)*0.3)))*AV34*1),2)*BS34),2)) -> 0 | CS34: =(ROUND((ROUND(((((EU34*1.2)*0.3))*AV34*1),2)*BS34),2)+ROUND((ROUND(((AE34-(((EU34*1.2)*0.3)))*AV34*1),2)*BS34),2)) -> 0 | CT34: =ROUND((ROUND((AF34*AV34*1),2)*BA34),2) -> 33.3 | CU34: =AG34 -> 0 | CV34: =(AH34*AV34) -> 2.63844 | CW34: =AI34 -> 0 | CX34: =AJ34 -> 0 | CY34: =(ROUND((((S34+ROUND((ROUND(((((EU34*1.2)*0.3))*AV34*1),2)*BS34),2))*AT34)/100),2)+ROUND(((ROUND((ROUND(((AE34-(((EU34*1.2)*0.3)))*AV34*1),2)*BS34),2)*AT34)/100),2)) -> 63.26 | CZ34: =(ROUND((((S34+ROUND((ROUND(((((EU34*1.2)*0.3))*AV34*1),2)*BS34),2))*AU34)/100),2)+ROUND(((ROUND((ROUND(((AE34-(((EU34*1.2)*0.3)))*AV34*1),2)*BS34),2)*AU34)/100),2)) -> 35.29 | DB34: 13 | DD34: *1)*0 | DE34: *1,2)*0,3 | DF34: *1,2)*0,3 | DG34: *1,2)*0,3 | DI34: *1,2)*0,3 | DJ34: *1,2)*0,3 | DN34: 0 | DO34: 0 | DP34: 1 | DQ34: 1 | DU34: 1013 | DV34: 1 ШТ. | DW34: 1 ШТ. | DX34: 1 | EE34: 57042959 | EF34: 40 | EG34: Монтаж оборудования | EH34: 0 | EJ34: 2 | EK34: 69 | EL34: ТСН-2001.4-10. Монтаж радиотелевизионного и электронного оборудования | EM34: ТСН-2001.4-10-2 | EO34: Поправка: Гл.12.Прил.8.п.8. 3_12.00.01.11.001 Поправка: Гл.4.Прил.2.2.п.2.2.29_04.00.01.35.003 | EQ34: 0 | ER34: 123.21 | ES34: 34.87 | ET34: 0 | EU34: 0 | EV34: 88.34 | EW34: 7 | EX34: 0 | EY34: 0 | FQ34: 0 | FR34: 0 | FS34: 0 | FX34: 95 | FY34: 53 | GD34: 1 | GF34: -876220620 | GG34: 2 | GH34: 1 | GI34: 2 | GJ34: 0 | GK34: 0 | GL34: =ROUND(IF(AND(BH34=3,BI34=3,FS34<>0),P34,0),2) -> 0 | GM34: =ROUND(O34+X34+Y34,2)+GX34 -> 165.14 | GN34: =IF(OR(BI34=0,BI34=1),GM34-GX34,0) -> 0 | GO34: =IF(BI34=2,GM34-GX34,0) -> 165.14 | GP34: =IF(BI34=4,GM34-GX34,0) -> 0 | GR34: 0 | GS34: 3 | GT34: 0 | GV34: =ROUND((GT34),6) -> 0 | GW34: 1 | GX34: =ROUND(HC34*I34,2) -> 0 | HA34: 0 | HB34: 0 | HC34: =GV34*GW34 -> 0 | HS34: 0 | IK34: 0
A35: 17 | B35: 1 | C35: =ROW(SmtRes!A38) -> 38 | D35: =ROW(EtalonRes!A52) -> 52 | E35: 4 | F35: 4.10-75-6 | G35: Монтаж аппаратуры настольной массой до 20 кг / демонтаж монитора | H35: 1 ШТ. | I35: 2 | J35: 0 | K35: 2 | O35: =ROUND(CP35,2) -> 3752.35 | P35: =ROUND((ROUND((AC35*AW35*I35),2)*BC35),2) -> 0 | Q35: =(ROUND((ROUND(((((ET35*1.2)*0.3))*AV35*I35),2)*BB35),2)+ROUND((ROUND(((AE35-(((EU35*1.2)*0.3)))*AV35*I35),2)*BS35),2)) -> 0 | R35: =(ROUND((ROUND(((((EU35*1.2)*0.3))*AV35*I35),2)*BS35),2)+ROUND((ROUND(((AE35-(((EU35*1.2)*0.3)))*AV35*I35),2)*BS35),2)) -> 0 | S35: =ROUND((ROUND((AF35*AV35*I35),2)*BA35),2) -> 3752.35 | T35: =ROUND(CU35*I35,2) -> 0 | U35: =CV35*I35 -> 5.27688 | V35: =CW35*I35 -> 0 | W35: =ROUND(CX35*I35,2) -> 0 | X35: =(ROUND((((S35+ROUND((ROUND(((((EU35*1.2)*0.3))*AV35*I35),2)*BS35),2))*AT35)/100),2)+ROUND(((ROUND((ROUND(((AE35-(((EU35*1.2)*0.3)))*AV35*I35),2)*BS35),2)*AT35)/100),2)) -> 3564.73 | Y35: =(ROUND((((S35+ROUND((ROUND(((((EU35*1.2)*0.3))*AV35*I35),2)*BS35),2))*AU35)/100),2)+ROUND(((ROUND((ROUND(((AE35-(((EU35*1.2)*0.3)))*AV35*I35),2)*BS35),2)*AU35)/100),2)) -> 1988.75 | AA35: 55934357 | AB35: =ROUND((AC35+AD35+AF35),6) -> 31.8024 | AC35: =ROUND((((ES35*1)*0)),6) -> 0 | AD35: =ROUND((((((ET35*1.2)*0.3))-(((EU35*1.2)*0.3)))+AE35),6) -> 0 | AE35: =ROUND((((EU35*1.2)*0.3)),6) -> 0 | AF35: =ROUND((((EV35*1.2)*0.3)),6) -> 31.8024 | AG35: =ROUND((AP35),6) -> 0 | AH35: =(((EW35*1.2)*0.3)) -> 2.52 | AI35: =(((EX35*1.2)*0.3)) -> 0 | AJ35: =(AS35) -> 0 | AK35: 123.21 | AL35: 34.87 | AM35: 0 | AN35: 0 | AO35: 88.34 | AP35: 0 | AQ35: 7 | AR35: 0 | AS35: 0 | AT35: 95 | AU35: 53 | AV35: 1.047 | AW35: 1 | AZ35: 1 | BA35: 56.35 | BB35: 1 | BC35: 10.28 | BH35: 0 | BI35: 2 | BJ35: ТСН-2001.4 Доп. 79, Сб. 10, т. 75, поз. 6 | BM35: 69 | BN35: 0 | BO35: 4.10-75-6 | BP35: 1 | BQ35: 40 | BR35: 0 | BS35: 56.35 | BT35: 1 | BU35: 1 | BV35: 1 | BW35: 1 | BX35: 1 | BZ35: 95 | CA35: 53 | CE35: 1566 | CF35: 0 | CG35: 0 | CM35: 0 | CN35: Поправка: Гл.12.Прил.8.п.8. 3_12.00.01.11.001 Наименование: При наличии напряженных и стесненных условий производства работ (стесненность, сложность складирования и транспортной логистики и т.п.) для объектов, расположенных в пределах круговой магистральной системы улиц "Садовое кольцо" города Москвы Поправка: Гл.4.Прил.2.2.п.2.2.29_04.00.01.35.003 Наименование: При демонтаже оборудования, предназначенного в лом | CO35: 0 | CP35: =(P35+Q35+S35) -> 3752.35 | CQ35: =ROUND((ROUND((AC35*AW35*1),2)*BC35),2) -> 0 | CR35: =(ROUND((ROUND(((((ET35*1.2)*0.3))*AV35*1),2)*BB35),2)+ROUND((ROUND(((AE35-(((EU35*1.2)*0.3)))*AV35*1),2)*BS35),2)) -> 0 | CS35: =(ROUND((ROUND(((((EU35*1.2)*0.3))*AV35*1),2)*BS35),2)+ROUND((ROUND(((AE35-(((EU35*1.2)*0.3)))*AV35*1),2)*BS35),2)) -> 0 | CT35: =ROUND((ROUND((AF35*AV35*1),2)*BA35),2) -> 1876.46 | CU35: =AG35 -> 0 | CV35: =(AH35*AV35) -> 2.63844 | CW35: =AI35 -> 0 | CX35: =AJ35 -> 0 | CY35: =(ROUND((((S35+ROUND((ROUND(((((EU35*1.2)*0.3))*AV35*1),2)*BS35),2))*AT35)/100),2)+ROUND(((ROUND((ROUND(((AE35-(((EU35*1.2)*0.3)))*AV35*1),2)*BS35),2)*AT35)/100),2)) -> 3564.73 | CZ35: =(ROUND((((S35+ROUND((ROUND(((((EU35*1.2)*0.3))*AV35*1),2)*BS35),2))*AU35)/100),2)+ROUND(((ROUND((ROUND(((AE35-(((EU35*1.2)*0.3)))*AV35*1),2)*BS35),2)*AU35)/100),2)) -> 1988.75 | DB35: 15 | DD35: *1)*0 | DE35: *1,2)*0,3 | DF35: *1,2)*0,3 | DG35: *1,2)*0,3 | DI35: *1,2)*0,3 | DJ35: *1,2)*0,3 | DN35: 0 | DO35: 0 | DP35: 1 | DQ35: 1 | DU35: 1013 | DV35: 1 ШТ. | DW35: 1 ШТ. | DX35: 1 | EE35: 57042959 | EF35: 40 | EG35: Монтаж оборудования | EH35: 0 | EJ35: 2 | EK35: 69 | EL35: ТСН-2001.4-10. Монтаж радиотелевизионного и электронного оборудования | EM35: ТСН-2001.4-10-2 | EO35: Поправка: Гл.12.Прил.8.п.8. 3_12.00.01.11.001 Поправка: Гл.4.Прил.2.2.п.2.2.29_04.00.01.35.003 | EQ35: 0 | ER35: 123.21 | ES35: 34.87 | ET35: 0 | EU35: 0 | EV35: 88.34 | EW35: 7 | EX35: 0 | EY35: 0 | FQ35: 0 | FR35: 0 | FS35: 0 | FX35: 95 | FY35: 53 | GD35: 1 | GF35: -876220620 | GG35: 2 | GH35: 1 | GI35: 2 | GJ35: 0 | GK35: 0 | GL35: =ROUND(IF(AND(BH35=3,BI35=3,FS35<>0),P35,0),2) -> 0 | GM35: =ROUND(O35+X35+Y35,2)+GX35 -> 9305.83 | GN35: =IF(OR(BI35=0,BI35=1),GM35-GX35,0) -> 0 | GO35: =IF(BI35=2,GM35-GX35,0) -> 9305.83 | GP35: =IF(BI35=4,GM35-GX35,0) -> 0 | GR35: 0 | GS35: 3 | GT35: 0 | GV35: =ROUND((GT35),6) -> 0 | GW35: 1 | GX35: =ROUND(HC35*I35,2) -> 0 | HA35: 0 | HB35: 0 | HC35: =GV35*GW35 -> 0 | HS35: 0 | IK35: 0
A36: 17 | B36: 1 | C36: =ROW(SmtRes!A53) -> 53 | D36: =ROW(EtalonRes!A69) -> 69 | E36: 5 | F36: 4.10-21-5 | G36: Грозозащита для воздушных абонентских линий / демонтаж грозозащиты локальной вычислительной сети | H36: 1 комплект | I36: 1 | J36: 0 | K36: 1 | O36: =ROUND(CP36,2) -> 14.27 | P36: =ROUND((ROUND((AC36*AW36*I36),2)*BC36),2) -> 0 | Q36: =(ROUND((ROUND(((((ET36*1.2)*0.3))*AV36*I36),2)*BB36),2)+ROUND((ROUND(((AE36-(((EU36*1.2)*0.3)))*AV36*I36),2)*BS36),2)) -> 0 | R36: =(ROUND((ROUND(((((EU36*1.2)*0.3))*AV36*I36),2)*BS36),2)+ROUND((ROUND(((AE36-(((EU36*1.2)*0.3)))*AV36*I36),2)*BS36),2)) -> 0 | S36: =ROUND((ROUND((AF36*AV36*I36),2)*BA36),2) -> 14.27 | T36: =ROUND(CU36*I36,2) -> 0 | U36: =CV36*I36 -> 1.13076 | V36: =CW36*I36 -> 0 | W36: =ROUND(CX36*I36,2) -> 0 | X36: =(ROUND((((S36+ROUND((ROUND(((((EU36*1.2)*0.3))*AV36*I36),2)*BS36),2))*AT36)/100),2)+ROUND(((ROUND((ROUND(((AE36-(((EU36*1.2)*0.3)))*AV36*I36),2)*BS36),2)*AT36)/100),2)) -> 12.84 | Y36: =(ROUND((((S36+ROUND((ROUND(((((EU36*1.2)*0.3))*AV36*I36),2)*BS36),2))*AU36)/100),2)+ROUND(((ROUND((ROUND(((AE36-(((EU36*1.2)*0.3)))*AV36*I36),2)*BS36),2)*AU36)/100),2)) -> 6.56 | AA36: 55934355 | AB36: =ROUND((AC36+AD36+AF36),6) -> 13.6296 | AC36: =ROUND((((ES36*1)*0)),6) -> 0 | AD36: =ROUND((((((ET36*1.2)*0.3))-(((EU36*1.2)*0.3)))+AE36),6) -> 0 | AE36: =ROUND((((EU36*1.2)*0.3)),6) -> 0 | AF36: =ROUND((((EV36*1.2)*0.3)),6) -> 13.6296 | AG36: =ROUND((AP36),6) -> 0 | AH36: =(((EW36*1.2)*0.3)) -> 1.08 | AI36: =(((EX36*1.2)*0.3)) -> 0 | AJ36: =(AS36) -> 0 | AK36: 80.47 | AL36: 42.61 | AM36: 0 | AN36: 0 | AO36: 37.86 | AP36: 0 | AQ36: 3 | AR36: 0 | AS36: 0 | AT36: 90 | AU36: 46 | AV36: 1.047 | AW36: 1 | AZ36: 1 | BA36: 1 | BB36: 1 | BC36: 1 | BH36: 0 | BI36: 2 | BJ36: ТСН-2001.4 Доп. 79, Сб. 10, т. 21, поз. 5 | BM36: 68 | BN36: 0 | BO36: 4.10-21-5 | BP36: 1 | BQ36: 40 | BR36: 0 | BS36: 1 | BT36: 1 | BU36: 1 | BV36: 1 | BW36: 1 | BX36: 1 | BZ36: 90 | CA36: 46 | CE36: 1566 | CF36: 0 | CG36: 0 | CM36: 0 | CN36: Поправка: Гл.12.Прил.8.п.8. 3_12.00.01.11.001 Наименование: При наличии напряженных и стесненных условий производства работ (стесненность, сложность складирования и транспортной логистики и т.п.) для объектов, расположенных в пределах круговой магистральной системы улиц "Садовое кольцо" города Москвы Поправка: Гл.4.Прил.2.2.п.2.2.29_04.00.01.35.003 Наименование: При демонтаже оборудования, предназначенного в лом | CO36: 0 | CP36: =(P36+Q36+S36) -> 14.27 | CQ36: =ROUND((ROUND((AC36*AW36*1),2)*BC36),2) -> 0 | CR36: =(ROUND((ROUND(((((ET36*1.2)*0.3))*AV36*1),2)*BB36),2)+ROUND((ROUND(((AE36-(((EU36*1.2)*0.3)))*AV36*1),2)*BS36),2)) -> 0 | CS36: =(ROUND((ROUND(((((EU36*1.2)*0.3))*AV36*1),2)*BS36),2)+ROUND((ROUND(((AE36-(((EU36*1.2)*0.3)))*AV36*1),2)*BS36),2)) -> 0 | CT36: =ROUND((ROUND((AF36*AV36*1),2)*BA36),2) -> 14.27 | CU36: =AG36 -> 0 | CV36: =(AH36*AV36) -> 1.13076 | CW36: =AI36 -> 0 | CX36: =AJ36 -> 0 | CY36: =(ROUND((((S36+ROUND((ROUND(((((EU36*1.2)*0.3))*AV36*1),2)*BS36),2))*AT36)/100),2)+ROUND(((ROUND((ROUND(((AE36-(((EU36*1.2)*0.3)))*AV36*1),2)*BS36),2)*AT36)/100),2)) -> 12.84 | CZ36: =(ROUND((((S36+ROUND((ROUND(((((EU36*1.2)*0.3))*AV36*1),2)*BS36),2))*AU36)/100),2)+ROUND(((ROUND((ROUND(((AE36-(((EU36*1.2)*0.3)))*AV36*1),2)*BS36),2)*AU36)/100),2)) -> 6.56 | DB36: 17 | DD36: *1)*0 | DE36: *1,2)*0,3 | DF36: *1,2)*0,3 | DG36: *1,2)*0,3 | DI36: *1,2)*0,3 | DJ36: *1,2)*0,3 | DN36: 0 | DO36: 0 | DP36: 1 | DQ36: 1 | DU36: 1013 | DV36: 1 комплект | DW36: 1 комплект | DX36: 1 | EE36: 57042958 | EF36: 40 | EG36: Монтаж оборудования | EH36: 0 | EJ36: 2 | EK36: 68 | EL36: ТСН-2001.4-10. Прокладка и монтаж сетей связи | EM36: ТСН-2001.4-10-1 | EO36: Поправка: Гл.12.Прил.8.п.8. 3_12.00.01.11.001 Поправка: Гл.4.Прил.2.2.п.2.2.29_04.00.01.35.003 | EQ36: 0 | ER36: 80.47 | ES36: 42.61 | ET36: 0 | EU36: 0 | EV36: 37.86 | EW36: 3 | EX36: 0 | EY36: 0 | FQ36: 0 | FR36: 0 | FS36: 0 | FX36: 90 | FY36: 46 | GD36: 1 | GF36: 1049768892 | GG36: 2 | GH36: 1 | GI36: 2 | GJ36: 0 | GK36: 0 | GL36: =ROUND(IF(AND(BH36=3,BI36=3,FS36<>0),P36,0),2) -> 0 | GM36: =ROUND(O36+X36+Y36,2)+GX36 -> 33.67 | GN36: =IF(OR(BI36=0,BI36=1),GM36-GX36,0) -> 0 | GO36: =IF(BI36=2,GM36-GX36,0) -> 33.67 | GP36: =IF(BI36=4,GM36-GX36,0) -> 0 | GR36: 0 | GS36: 3 | GT36: 0 | GV36: =ROUND((GT36),6) -> 0 | GW36: 1 | GX36: =ROUND(HC36*I36,2) -> 0 | HA36: 0 | HB36: 0 | HC36: =GV36*GW36 -> 0 | HS36: 0 | IK36: 0
A37: 17 | B37: 1 | C37: =ROW(SmtRes!A68) -> 68 | D37: =ROW(EtalonRes!A86) -> 86 | E37: 5 | F37: 4.10-21-5 | G37: Грозозащита для воздушных абонентских линий / демонтаж грозозащиты локальной вычислительной сети | H37: 1 комплект | I37: 1 | J37: 0 | K37: 1 | O37: =ROUND(CP37,2) -> 804.11 | P37: =ROUND((ROUND((AC37*AW37*I37),2)*BC37),2) -> 0 | Q37: =(ROUND((ROUND(((((ET37*1.2)*0.3))*AV37*I37),2)*BB37),2)+ROUND((ROUND(((AE37-(((EU37*1.2)*0.3)))*AV37*I37),2)*BS37),2)) -> 0 | R37: =(ROUND((ROUND(((((EU37*1.2)*0.3))*AV37*I37),2)*BS37),2)+ROUND((ROUND(((AE37-(((EU37*1.2)*0.3)))*AV37*I37),2)*BS37),2)) -> 0 | S37: =ROUND((ROUND((AF37*AV37*I37),2)*BA37),2) -> 804.11 | T37: =ROUND(CU37*I37,2) -> 0 | U37: =CV37*I37 -> 1.13076 | V37: =CW37*I37 -> 0 | W37: =ROUND(CX37*I37,2) -> 0 | X37: =(ROUND((((S37+ROUND((ROUND(((((EU37*1.2)*0.3))*AV37*I37),2)*BS37),2))*AT37)/100),2)+ROUND(((ROUND((ROUND(((AE37-(((EU37*1.2)*0.3)))*AV37*I37),2)*BS37),2)*AT37)/100),2)) -> 723.7 | Y37: =(ROUND((((S37+ROUND((ROUND(((((EU37*1.2)*0.3))*AV37*I37),2)*BS37),2))*AU37)/100),2)+ROUND(((ROUND((ROUND(((AE37-(((EU37*1.2)*0.3)))*AV37*I37),2)*BS37),2)*AU37)/100),2)) -> 369.89 | AA37: 55934357 | AB37: =ROUND((AC37+AD37+AF37),6) -> 13.6296 | AC37: =ROUND((((ES37*1)*0)),6) -> 0 | AD37: =ROUND((((((ET37*1.2)*0.3))-(((EU37*1.2)*0.3)))+AE37),6) -> 0 | AE37: =ROUND((((EU37*1.2)*0.3)),6) -> 0 | AF37: =ROUND((((EV37*1.2)*0.3)),6) -> 13.6296 | AG37: =ROUND((AP37),6) -> 0 | AH37: =(((EW37*1.2)*0.3)) -> 1.08 | AI37: =(((EX37*1.2)*0.3)) -> 0 | AJ37: =(AS37) -> 0 | AK37: 80.47 | AL37: 42.61 | AM37: 0 | AN37: 0 | AO37: 37.86 | AP37: 0 | AQ37: 3 | AR37: 0 | AS37: 0 | AT37: 90 | AU37: 46 | AV37: 1.047 | AW37: 1 | AZ37: 1 | BA37: 56.35 | BB37: 1 | BC37: 5.15 | BH37: 0 | BI37: 2 | BJ37: ТСН-2001.4 Доп. 79, Сб. 10, т. 21, поз. 5 | BM37: 68 | BN37: 0 | BO37: 4.10-21-5 | BP37: 1 | BQ37: 40 | BR37: 0 | BS37: 56.35 | BT37: 1 | BU37: 1 | BV37: 1 | BW37: 1 | BX37: 1 | BZ37: 90 | CA37: 46 | CE37: 1566 | CF37: 0 | CG37: 0 | CM37: 0 | CN37: Поправка: Гл.12.Прил.8.п.8. 3_12.00.01.11.001 Наименование: При наличии напряженных и стесненных условий производства работ (стесненность, сложность складирования и транспортной логистики и т.п.) для объектов, расположенных в пределах круговой магистральной системы улиц "Садовое кольцо" города Москвы Поправка: Гл.4.Прил.2.2.п.2.2.29_04.00.01.35.003 Наименование: При демонтаже оборудования, предназначенного в лом | CO37: 0 | CP37: =(P37+Q37+S37) -> 804.11 | CQ37: =ROUND((ROUND((AC37*AW37*1),2)*BC37),2) -> 0 | CR37: =(ROUND((ROUND(((((ET37*1.2)*0.3))*AV37*1),2)*BB37),2)+ROUND((ROUND(((AE37-(((EU37*1.2)*0.3)))*AV37*1),2)*BS37),2)) -> 0 | CS37: =(ROUND((ROUND(((((EU37*1.2)*0.3))*AV37*1),2)*BS37),2)+ROUND((ROUND(((AE37-(((EU37*1.2)*0.3)))*AV37*1),2)*BS37),2)) -> 0 | CT37: =ROUND((ROUND((AF37*AV37*1),2)*BA37),2) -> 804.11 | CU37: =AG37 -> 0 | CV37: =(AH37*AV37) -> 1.13076 | CW37: =AI37 -> 0 | CX37: =AJ37 -> 0 | CY37: =(ROUND((((S37+ROUND((ROUND(((((EU37*1.2)*0.3))*AV37*1),2)*BS37),2))*AT37)/100),2)+ROUND(((ROUND((ROUND(((AE37-(((EU37*1.2)*0.3)))*AV37*1),2)*BS37),2)*AT37)/100),2)) -> 723.7 | CZ37: =(ROUND((((S37+ROUND((ROUND(((((EU37*1.2)*0.3))*AV37*1),2)*BS37),2))*AU37)/100),2)+ROUND(((ROUND((ROUND(((AE37-(((EU37*1.2)*0.3)))*AV37*1),2)*BS37),2)*AU37)/100),2)) -> 369.89 | DB37: 19 | DD37: *1)*0 | DE37: *1,2)*0,3 | DF37: *1,2)*0,3 | DG37: *1,2)*0,3 | DI37: *1,2)*0,3 | DJ37: *1,2)*0,3 | DN37: 0 | DO37: 0 | DP37: 1 | DQ37: 1 | DU37: 1013 | DV37: 1 комплект | DW37: 1 комплект | DX37: 1 | EE37: 57042958 | EF37: 40 | EG37: Монтаж оборудования | EH37: 0 | EJ37: 2 | EK37: 68 | EL37: ТСН-2001.4-10. Прокладка и монтаж сетей связи | EM37: ТСН-2001.4-10-1 | EO37: Поправка: Гл.12.Прил.8.п.8. 3_12.00.01.11.001 Поправка: Гл.4.Прил.2.2.п.2.2.29_04.00.01.35.003 | EQ37: 0 | ER37: 80.47 | ES37: 42.61 | ET37: 0 | EU37: 0 | EV37: 37.86 | EW37: 3 | EX37: 0 | EY37: 0 | FQ37: 0 | FR37: 0 | FS37: 0 | FX37: 90 | FY37: 46 | GD37: 1 | GF37: 1049768892 | GG37: 2 | GH37: 1 | GI37: 2 | GJ37: 0 | GK37: 0 | GL37: =ROUND(IF(AND(BH37=3,BI37=3,FS37<>0),P37,0),2) -> 0 | GM37: =ROUND(O37+X37+Y37,2)+GX37 -> 1897.7 | GN37: =IF(OR(BI37=0,BI37=1),GM37-GX37,0) -> 0 | GO37: =IF(BI37=2,GM37-GX37,0) -> 1897.7 | GP37: =IF(BI37=4,GM37-GX37,0) -> 0 | GR37: 0 | GS37: 3 | GT37: 0 | GV37: =ROUND((GT37),6) -> 0 | GW37: 1 | GX37: =ROUND(HC37*I37,2) -> 0 | HA37: 0 | HB37: 0 | HC37: =GV37*GW37 -> 0 | HS37: 0 | IK37: 0
A38: 17 | B38: 1 | C38: =ROW(SmtRes!A83) -> 83 | D38: =ROW(EtalonRes!A103) -> 103 | E38: 6 | F38: 4.10-21-5 | G38: Грозозащита для воздушных абонентских линий / демонтаж уличной грозозащиты локальной вычислительной сети | H38: 1 комплект | I38: 14 | J38: 0 | K38: 14 | O38: =ROUND(CP38,2) -> 199.78 | P38: =ROUND((ROUND((AC38*AW38*I38),2)*BC38),2) -> 0 | Q38: =(ROUND((ROUND(((((ET38*1.2)*0.3))*AV38*I38),2)*BB38),2)+ROUND((ROUND(((AE38-(((EU38*1.2)*0.3)))*AV38*I38),2)*BS38),2)) -> 0 | R38: =(ROUND((ROUND(((((EU38*1.2)*0.3))*AV38*I38),2)*BS38),2)+ROUND((ROUND(((AE38-(((EU38*1.2)*0.3)))*AV38*I38),2)*BS38),2)) -> 0 | S38: =ROUND((ROUND((AF38*AV38*I38),2)*BA38),2) -> 199.78 | T38: =ROUND(CU38*I38,2) -> 0 | U38: =CV38*I38 -> 15.83064 | V38: =CW38*I38 -> 0 | W38: =ROUND(CX38*I38,2) -> 0 | X38: =(ROUND((((S38+ROUND((ROUND(((((EU38*1.2)*0.3))*AV38*I38),2)*BS38),2))*AT38)/100),2)+ROUND(((ROUND((ROUND(((AE38-(((EU38*1.2)*0.3)))*AV38*I38),2)*BS38),2)*AT38)/100),2)) -> 179.8 | Y38: =(ROUND((((S38+ROUND((ROUND(((((EU38*1.2)*0.3))*AV38*I38),2)*BS38),2))*AU38)/100),2)+ROUND(((ROUND((ROUND(((AE38-(((EU38*1.2)*0.3)))*AV38*I38),2)*BS38),2)*AU38)/100),2)) -> 91.9 | AA38: 55934355 | AB38: =ROUND((AC38+AD38+AF38),6) -> 13.6296 | AC38: =ROUND((((ES38*1)*0)),6) -> 0 | AD38: =ROUND((((((ET38*1.2)*0.3))-(((EU38*1.2)*0.3)))+AE38),6) -> 0 | AE38: =ROUND((((EU38*1.2)*0.3)),6) -> 0 | AF38: =ROUND((((EV38*1.2)*0.3)),6) -> 13.6296 | AG38: =ROUND((AP38),6) -> 0 | AH38: =(((EW38*1.2)*0.3)) -> 1.08 | AI38: =(((EX38*1.2)*0.3)) -> 0 | AJ38: =(AS38) -> 0 | AK38: 80.47 | AL38: 42.61 | AM38: 0 | AN38: 0 | AO38: 37.86 | AP38: 0 | AQ38: 3 | AR38: 0 | AS38: 0 | AT38: 90 | AU38: 46 | AV38: 1.047 | AW38: 1 | AZ38: 1 | BA38: 1 | BB38: 1 | BC38: 1 | BH38: 0 | BI38: 2 | BJ38: ТСН-2001.4 Доп. 79, Сб. 10, т. 21, поз. 5 | BM38: 68 | BN38: 0 | BO38: 4.10-21-5 | BP38: 1 | BQ38: 40 | BR38: 0 | BS38: 1 | BT38: 1 | BU38: 1 | BV38: 1 | BW38: 1 | BX38: 1 | BZ38: 90 | CA38: 46 | CE38: 1566 | CF38: 0 | CG38: 0 | CM38: 0 | CN38: Поправка: Гл.12.Прил.8.п.8. 3_12.00.01.11.001 Наименование: При наличии напряженных и стесненных условий производства работ (стесненность, сложность складирования и транспортной логистики и т.п.) для объектов, расположенных в пределах круговой магистральной системы улиц "Садовое кольцо" города Москвы Поправка: Гл.4.Прил.2.2.п.2.2.29_04.00.01.35.003 Наименование: При демонтаже оборудования, предназначенного в лом | CO38: 0 | CP38: =(P38+Q38+S38) -> 199.78 | CQ38: =ROUND((ROUND((AC38*AW38*1),2)*BC38),2) -> 0 | CR38: =(ROUND((ROUND(((((ET38*1.2)*0.3))*AV38*1),2)*BB38),2)+ROUND((ROUND(((AE38-(((EU38*1.2)*0.3)))*AV38*1),2)*BS38),2)) -> 0 | CS38: =(ROUND((ROUND(((((EU38*1.2)*0.3))*AV38*1),2)*BS38),2)+ROUND((ROUND(((AE38-(((EU38*1.2)*0.3)))*AV38*1),2)*BS38),2)) -> 0 | CT38: =ROUND((ROUND((AF38*AV38*1),2)*BA38),2) -> 14.27 | CU38: =AG38 -> 0 | CV38: =(AH38*AV38) -> 1.13076 | CW38: =AI38 -> 0 | CX38: =AJ38 -> 0 | CY38: =(ROUND((((S38+ROUND((ROUND(((((EU38*1.2)*0.3))*AV38*1),2)*BS38),2))*AT38)/100),2)+ROUND(((ROUND((ROUND(((AE38-(((EU38*1.2)*0.3)))*AV38*1),2)*BS38),2)*AT38)/100),2)) -> 179.8 | CZ38: =(ROUND((((S38+ROUND((ROUND(((((EU38*1.2)*0.3))*AV38*1),2)*BS38),2))*AU38)/100),2)+ROUND(((ROUND((ROUND(((AE38-(((EU38*1.2)*0.3)))*AV38*1),2)*BS38),2)*AU38)/100),2)) -> 91.9 | DB38: 21 | DD38: *1)*0 | DE38: *1,2)*0,3 | DF38: *1,2)*0,3 | DG38: *1,2)*0,3 | DI38: *1,2)*0,3 | DJ38: *1,2)*0,3 | DN38: 0 | DO38: 0 | DP38: 1 | DQ38: 1 | DU38: 1013 | DV38: 1 комплект | DW38: 1 комплект | DX38: 1 | EE38: 57042958 | EF38: 40 | EG38: Монтаж оборудования | EH38: 0 | EJ38: 2 | EK38: 68 | EL38: ТСН-2001.4-10. Прокладка и монтаж сетей связи | EM38: ТСН-2001.4-10-1 | EO38: Поправка: Гл.12.Прил.8.п.8. 3_12.00.01.11.001 Поправка: Гл.4.Прил.2.2.п.2.2.29_04.00.01.35.003 | EQ38: 0 | ER38: 80.47 | ES38: 42.61 | ET38: 0 | EU38: 0 | EV38: 37.86 | EW38: 3 | EX38: 0 | EY38: 0 | FQ38: 0 | FR38: 0 | FS38: 0 | FX38: 90 | FY38: 46 | GD38: 1 | GF38: -303373422 | GG38: 2 | GH38: 1 | GI38: 2 | GJ38: 0 | GK38: 0 | GL38: =ROUND(IF(AND(BH38=3,BI38=3,FS38<>0),P38,0),2) -> 0 | GM38: =ROUND(O38+X38+Y38,2)+GX38 -> 471.48 | GN38: =IF(OR(BI38=0,BI38=1),GM38-GX38,0) -> 0 | GO38: =IF(BI38=2,GM38-GX38,0) -> 471.48 | GP38: =IF(BI38=4,GM38-GX38,0) -> 0 | GR38: 0 | GS38: 3 | GT38: 0 | GV38: =ROUND((GT38),6) -> 0 | GW38: 1 | GX38: =ROUND(HC38*I38,2) -> 0 | HA38: 0 | HB38: 0 | HC38: =GV38*GW38 -> 0 | HS38: 0 | IK38: 0
A39: 17 | B39: 1 | C39: =ROW(SmtRes!A98) -> 98 | D39: =ROW(EtalonRes!A120) -> 120 | E39: 6 | F39: 4.10-21-5 | G39: Грозозащита для воздушных абонентских линий / демонтаж уличной грозозащиты локальной вычислительной сети | H39: 1 комплект | I39: 14 | J39: 0 | K39: 14 | O39: =ROUND(CP39,2) -> 11257.6 | P39: =ROUND((ROUND((AC39*AW39*I39),2)*BC39),2) -> 0 | Q39: =(ROUND((ROUND(((((ET39*1.2)*0.3))*AV39*I39),2)*BB39),2)+ROUND((ROUND(((AE39-(((EU39*1.2)*0.3)))*AV39*I39),2)*BS39),2)) -> 0 | R39: =(ROUND((ROUND(((((EU39*1.2)*0.3))*AV39*I39),2)*BS39),2)+ROUND((ROUND(((AE39-(((EU39*1.2)*0.3)))*AV39*I39),2)*BS39),2)) -> 0 | S39: =ROUND((ROUND((AF39*AV39*I39),2)*BA39),2) -> 11257.6 | T39: =ROUND(CU39*I39,2) -> 0 | U39: =CV39*I39 -> 15.83064 | V39: =CW39*I39 -> 0 | W39: =ROUND(CX39*I39,2) -> 0 | X39: =(ROUND((((S39+ROUND((ROUND(((((EU39*1.2)*0.3))*AV39*I39),2)*BS39),2))*AT39)/100),2)+ROUND(((ROUND((ROUND(((AE39-(((EU39*1.2)*0.3)))*AV39*I39),2)*BS39),2)*AT39)/100),2)) -> 10131.84 | Y39: =(ROUND((((S39+ROUND((ROUND(((((EU39*1.2)*0.3))*AV39*I39),2)*BS39),2))*AU39)/100),2)+ROUND(((ROUND((ROUND(((AE39-(((EU39*1.2)*0.3)))*AV39*I39),2)*BS39),2)*AU39)/100),2)) -> 5178.5 | AA39: 55934357 | AB39: =ROUND((AC39+AD39+AF39),6) -> 13.6296 | AC39: =ROUND((((ES39*1)*0)),6) -> 0 | AD39: =ROUND((((((ET39*1.2)*0.3))-(((EU39*1.2)*0.3)))+AE39),6) -> 0 | AE39: =ROUND((((EU39*1.2)*0.3)),6) -> 0 | AF39: =ROUND((((EV39*1.2)*0.3)),6) -> 13.6296 | AG39: =ROUND((AP39),6) -> 0 | AH39: =(((EW39*1.2)*0.3)) -> 1.08 | AI39: =(((EX39*1.2)*0.3)) -> 0 | AJ39: =(AS39) -> 0 | AK39: 80.47 | AL39: 42.61 | AM39: 0 | AN39: 0 | AO39: 37.86 | AP39: 0 | AQ39: 3 | AR39: 0 | AS39: 0 | AT39: 90 | AU39: 46 | AV39: 1.047 | AW39: 1 | AZ39: 1 | BA39: 56.35 | BB39: 1 | BC39: 5.15 | BH39: 0 | BI39: 2 | BJ39: ТСН-2001.4 Доп. 79, Сб. 10, т. 21, поз. 5 | BM39: 68 | BN39: 0 | BO39: 4.10-21-5 | BP39: 1 | BQ39: 40 | BR39: 0 | BS39: 56.35 | BT39: 1 | BU39: 1 | BV39: 1 | BW39: 1 | BX39: 1 | BZ39: 90 | CA39: 46 | CE39: 1566 | CF39: 0 | CG39: 0 | CM39: 0 | CN39: Поправка: Гл.12.Прил.8.п.8. 3_12.00.01.11.001 Наименование: При наличии напряженных и стесненных условий производства работ (стесненность, сложность складирования и транспортной логистики и т.п.) для объектов, расположенных в пределах круговой магистральной системы улиц "Садовое кольцо" города Москвы Поправка: Гл.4.Прил.2.2.п.2.2.29_04.00.01.35.003 Наименование: При демонтаже оборудования, предназначенного в лом | CO39: 0 | CP39: =(P39+Q39+S39) -> 11257.6 | CQ39: =ROUND((ROUND((AC39*AW39*1),2)*BC39),2) -> 0 | CR39: =(ROUND((ROUND(((((ET39*1.2)*0.3))*AV39*1),2)*BB39),2)+ROUND((ROUND(((AE39-(((EU39*1.2)*0.3)))*AV39*1),2)*BS39),2)) -> 0 | CS39: =(ROUND((ROUND(((((EU39*1.2)*0.3))*AV39*1),2)*BS39),2)+ROUND((ROUND(((AE39-(((EU39*1.2)*0.3)))*AV39*1),2)*BS39),2)) -> 0 | CT39: =ROUND((ROUND((AF39*AV39*1),2)*BA39),2) -> 804.11 | CU39: =AG39 -> 0 | CV39: =(AH39*AV39) -> 1.13076 | CW39: =AI39 -> 0 | CX39: =AJ39 -> 0 | CY39: =(ROUND((((S39+ROUND((ROUND(((((EU39*1.2)*0.3))*AV39*1),2)*BS39),2))*AT39)/100),2)+ROUND(((ROUND((ROUND(((AE39-(((EU39*1.2)*0.3)))*AV39*1),2)*BS39),2)*AT39)/100),2)) -> 10131.84 | CZ39: =(ROUND((((S39+ROUND((ROUND(((((EU39*1.2)*0.3))*AV39*1),2)*BS39),2))*AU39)/100),2)+ROUND(((ROUND((ROUND(((AE39-(((EU39*1.2)*0.3)))*AV39*1),2)*BS39),2)*AU39)/100),2)) -> 5178.5 | DB39: 23 | DD39: *1)*0 | DE39: *1,2)*0,3 | DF39: *1,2)*0,3 | DG39: *1,2)*0,3 | DI39: *1,2)*0,3 | DJ39: *1,2)*0,3 | DN39: 0 | DO39: 0 | DP39: 1 | DQ39: 1 | DU39: 1013 | DV39: 1 комплект | DW39: 1 комплект | DX39: 1 | EE39: 57042958 | EF39: 40 | EG39: Монтаж оборудования | EH39: 0 | EJ39: 2 | EK39: 68 | EL39: ТСН-2001.4-10. Прокладка и монтаж сетей связи | EM39: ТСН-2001.4-10-1 | EO39: Поправка: Гл.12.Прил.8.п.8. 3_12.00.01.11.001 Поправка: Гл.4.Прил.2.2.п.2.2.29_04.00.01.35.003 | EQ39: 0 | ER39: 80.47 | ES39: 42.61 | ET39: 0 | EU39: 0 | EV39: 37.86 | EW39: 3 | EX39: 0 | EY39: 0 | FQ39: 0 | FR39: 0 | FS39: 0 | FX39: 90 | FY39: 46 | GD39: 1 | GF39: -303373422 | GG39: 2 | GH39: 1 | GI39: 2 | GJ39: 0 | GK39: 0 | GL39: =ROUND(IF(AND(BH39=3,BI39=3,FS39<>0),P39,0),2) -> 0 | GM39: =ROUND(O39+X39+Y39,2)+GX39 -> 26567.94 | GN39: =IF(OR(BI39=0,BI39=1),GM39-GX39,0) -> 0 | GO39: =IF(BI39=2,GM39-GX39,0) -> 26567.94 | GP39: =IF(BI39=4,GM39-GX39,0) -> 0 | GR39: 0 | GS39: 3 | GT39: 0 | GV39: =ROUND((GT39),6) -> 0 | GW39: 1 | GX39: =ROUND(HC39*I39,2) -> 0 | HA39: 0 | HB39: 0 | HC39: =GV39*GW39 -> 0 | HS39: 0 | IK39: 0
A40: 17 | B40: 1 | C40: =ROW(SmtRes!A104) -> 104 | D40: =ROW(EtalonRes!A127) -> 127 | E40: 7 | F40: 4.10-174-1 | G40: Монтаж внутренней камеры видеонаблюдения / демонтаж видеокамер | H40: 10 шт. | I40: =ROUND(81/10,9) -> 8.1 | J40: 0 | K40: =ROUND(81/10,9) -> 8.1 | O40: =ROUND(CP40,2) -> 762.6 | P40: =ROUND((ROUND((AC40*AW40*I40),2)*BC40),2) -> 0 | Q40: =(ROUND((ROUND(((((ET40*1.2)*0.3))*AV40*I40),2)*BB40),2)+ROUND((ROUND(((AE40-(((EU40*1.2)*0.3)))*AV40*I40),2)*BS40),2)) -> 7.21 | R40: =(ROUND((ROUND(((((EU40*1.2)*0.3))*AV40*I40),2)*BS40),2)+ROUND((ROUND(((AE40-(((EU40*1.2)*0.3)))*AV40*I40),2)*BS40),2)) -> 0.4 | S40: =ROUND((ROUND((AF40*AV40*I40),2)*BA40),2) -> 755.39 | T40: =ROUND(CU40*I40,2) -> 0 | U40: =CV40*I40 -> 47.444428 | V40: =CW40*I40 -> 0 | W40: =ROUND(CX40*I40,2) -> 0 | X40: =(ROUND((((S40+ROUND((ROUND(((((EU40*1.2)*0.3))*AV40*I40),2)*BS40),2))*AT40)/100),2)+ROUND(((ROUND((ROUND(((AE40-(((EU40*1.2)*0.3)))*AV40*I40),2)*BS40),2)*AT40)/100),2)) -> 680.21 | Y40: =(ROUND((((S40+ROUND((ROUND(((((EU40*1.2)*0.3))*AV40*I40),2)*BS40),2))*AU40)/100),2)+ROUND(((ROUND((ROUND(((AE40-(((EU40*1.2)*0.3)))*AV40*I40),2)*BS40),2)*AU40)/100),2)) -> 347.66 | AA40: 55934355 | AB40: =ROUND((AC40+AD40+AF40),6) -> 89.9208 | AC40: =ROUND((((ES40*1)*0)),6) -> 0 | AD40: =ROUND((((((ET40*1.2)*0.3))-(((EU40*1.2)*0.3)))+AE40),6) -> 0.8496 | AE40: =ROUND((((EU40*1.2)*0.3)),6) -> 0.0468 | AF40: =ROUND((((EV40*1.2)*0.3)),6) -> 89.0712 | AG40: =ROUND((AP40),6) -> 0 | AH40: =(((EW40*1.2)*0.3)) -> 5.5944 | AI40: =(((EX40*1.2)*0.3)) -> 0 | AJ40: =(AS40) -> 0 | AK40: 292.29 | AL40: 42.51 | AM40: 2.36 | AN40: 0.13 | AO40: 247.42 | AP40: 0 | AQ40: 15.54 | AR40: 0 | AS40: 0 | AT40: 90 | AU40: 46 | AV40: 1.047 | AW40: 1 | AZ40: 1 | BA40: 1 | BB40: 1 | BC40: 1 | BH40: 0 | BI40: 2 | BJ40: ТСН-2001.4 Доп. 68, Сб. 10, т. 174, поз. 1 | BM40: 68 | BN40: 0 | BO40: 4.10-174-1 | BP40: 1 | BQ40: 40 | BR40: 0 | BS40: 1 | BT40: 1 | BU40: 1 | BV40: 1 | BW40: 1 | BX40: 1 | BZ40: 90 | CA40: 46 | CE40: 1566 | CF40: 0 | CG40: 0 | CM40: 0 | CN40: Поправка: Гл.12.Прил.8.п.8. 3_12.00.01.11.001 Наименование: При наличии напряженных и стесненных условий производства работ (стесненность, сложность складирования и транспортной логистики и т.п.) для объектов, расположенных в пределах круговой магистральной системы улиц "Садовое кольцо" города Москвы Поправка: Гл.4.Прил.2.2.п.2.2.29_04.00.01.35.003 Наименование: При демонтаже оборудования, предназначенного в лом | CO40: 0 | CP40: =(P40+Q40+S40) -> 762.6 | CQ40: =ROUND((ROUND((AC40*AW40*1),2)*BC40),2) -> 0 | CR40: =(ROUND((ROUND(((((ET40*1.2)*0.3))*AV40*1),2)*BB40),2)+ROUND((ROUND(((AE40-(((EU40*1.2)*0.3)))*AV40*1),2)*BS40),2)) -> 0.89 | CS40: =(ROUND((ROUND(((((EU40*1.2)*0.3))*AV40*1),2)*BS40),2)+ROUND((ROUND(((AE40-(((EU40*1.2)*0.3)))*AV40*1),2)*BS40),2)) -> 0.05 | CT40: =ROUND((ROUND((AF40*AV40*1),2)*BA40),2) -> 93.26 | CU40: =AG40 -> 0 | CV40: =(AH40*AV40) -> 5.8573368 | CW40: =AI40 -> 0 | CX40: =AJ40 -> 0 | CY40: =(ROUND((((S40+ROUND((ROUND(((((EU40*1.2)*0.3))*AV40*1),2)*BS40),2))*AT40)/100),2)+ROUND(((ROUND((ROUND(((AE40-(((EU40*1.2)*0.3)))*AV40*1),2)*BS40),2)*AT40)/100),2)) -> 679.9 | CZ40: =(ROUND((((S40+ROUND((ROUND(((((EU40*1.2)*0.3))*AV40*1),2)*BS40),2))*AU40)/100),2)+ROUND(((ROUND((ROUND(((AE40-(((EU40*1.2)*0.3)))*AV40*1),2)*BS40),2)*AU40)/100),2)) -> 347.5 | DB40: 25 | DD40: *1)*0 | DE40: *1,2)*0,3 | DF40: *1,2)*0,3 | DG40: *1,2)*0,3 | DI40: *1,2)*0,3 | DJ40: *1,2)*0,3 | DN40: 0 | DO40: 0 | DP40: 1 | DQ40: 1 | DU40: 1010 | DV40: 10 шт. | DW40: 10 шт. | DX40: 10 | EE40: 57042958 | EF40: 40 | EG40: Монтаж оборудования | EH40: 0 | EJ40: 2 | EK40: 68 | EL40: ТСН-2001.4-10. Прокладка и монтаж сетей связи | EM40: ТСН-2001.4-10-1 | EO40: Поправка: Гл.12.Прил.8.п.8. 3_12.00.01.11.001 Поправка: Гл.4.Прил.2.2.п.2.2.29_04.00.01.35.003 | EQ40: 0 | ER40: 292.29 | ES40: 42.51 | ET40: 2.36 | EU40: 0.13 | EV40: 247.42 | EW40: 15.54 | EX40: 0 | EY40: 0 | FQ40: 0 | FR40: 0 | FS40: 0 | FX40: 90 | FY40: 46 | GD40: 1 | GF40: 1565221849 | GG40: 2 | GH40: 1 | GI40: 2 | GJ40: 0 | GK40: 0 | GL40: =ROUND(IF(AND(BH40=3,BI40=3,FS40<>0),P40,0),2) -> 0 | GM40: =ROUND(O40+X40+Y40,2)+GX40 -> 1790.47 | GN40: =IF(OR(BI40=0,BI40=1),GM40-GX40,0) -> 0 | GO40: =IF(BI40=2,GM40-GX40,0) -> 1790.47 | GP40: =IF(BI40=4,GM40-GX40,0) -> 0 | GR40: 0 | GS40: 3 | GT40: 0 | GV40: =ROUND((GT40),6) -> 0 | GW40: 1 | GX40: =ROUND(HC40*I40,2) -> 0 | HA40: 0 | HB40: 0 | HC40: =GV40*GW40 -> 0 | HS40: 0 | IK40: 0
A41: 17 | B41: 1 | C41: =ROW(SmtRes!A110) -> 110 | D41: =ROW(EtalonRes!A134) -> 134 | E41: 7 | F41: 4.10-174-1 | G41: Монтаж внутренней камеры видеонаблюдения / демонтаж видеокамер | H41: 10 шт. | I41: =ROUND(81/10,9) -> 8.1 | J41: 0 | K41: =ROUND(81/10,9) -> 8.1 | O41: =ROUND(CP41,2) -> 42654.26 | P41: =ROUND((ROUND((AC41*AW41*I41),2)*BC41),2) -> 0 | Q41: =(ROUND((ROUND(((((ET41*1.2)*0.3))*AV41*I41),2)*BB41),2)+ROUND((ROUND(((AE41-(((EU41*1.2)*0.3)))*AV41*I41),2)*BS41),2)) -> 88.03 | R41: =(ROUND((ROUND(((((EU41*1.2)*0.3))*AV41*I41),2)*BS41),2)+ROUND((ROUND(((AE41-(((EU41*1.2)*0.3)))*AV41*I41),2)*BS41),2)) -> 22.54 | S41: =ROUND((ROUND((AF41*AV41*I41),2)*BA41),2) -> 42566.23 | T41: =ROUND(CU41*I41,2) -> 0 | U41: =CV41*I41 -> 47.444428 | V41: =CW41*I41 -> 0 | W41: =ROUND(CX41*I41,2) -> 0 | X41: =(ROUND((((S41+ROUND((ROUND(((((EU41*1.2)*0.3))*AV41*I41),2)*BS41),2))*AT41)/100),2)+ROUND(((ROUND((ROUND(((AE41-(((EU41*1.2)*0.3)))*AV41*I41),2)*BS41),2)*AT41)/100),2)) -> 38329.89 | Y41: =(ROUND((((S41+ROUND((ROUND(((((EU41*1.2)*0.3))*AV41*I41),2)*BS41),2))*AU41)/100),2)+ROUND(((ROUND((ROUND(((AE41-(((EU41*1.2)*0.3)))*AV41*I41),2)*BS41),2)*AU41)/100),2)) -> 19590.83 | AA41: 55934357 | AB41: =ROUND((AC41+AD41+AF41),6) -> 89.9208 | AC41: =ROUND((((ES41*1)*0)),6) -> 0 | AD41: =ROUND((((((ET41*1.2)*0.3))-(((EU41*1.2)*0.3)))+AE41),6) -> 0.8496 | AE41: =ROUND((((EU41*1.2)*0.3)),6) -> 0.0468 | AF41: =ROUND((((EV41*1.2)*0.3)),6) -> 89.0712 | AG41: =ROUND((AP41),6) -> 0 | AH41: =(((EW41*1.2)*0.3)) -> 5.5944 | AI41: =(((EX41*1.2)*0.3)) -> 0 | AJ41: =(AS41) -> 0 | AK41: 292.29 | AL41: 42.51 | AM41: 2.36 | AN41: 0.13 | AO41: 247.42 | AP41: 0 | AQ41: 15.54 | AR41: 0 | AS41: 0 | AT41: 90 | AU41: 46 | AV41: 1.047 | AW41: 1 | AZ41: 1 | BA41: 56.35 | BB41: 12.21 | BC41: 1.84 | BH41: 0 | BI41: 2 | BJ41: ТСН-2001.4 Доп. 68, Сб. 10, т. 174, поз. 1 | BM41: 68 | BN41: 0 | BO41: 4.10-174-1 | BP41: 1 | BQ41: 40 | BR41: 0 | BS41: 56.35 | BT41: 1 | BU41: 1 | BV41: 1 | BW41: 1 | BX41: 1 | BZ41: 90 | CA41: 46 | CE41: 1566 | CF41: 0 | CG41: 0 | CM41: 0 | CN41: Поправка: Гл.12.Прил.8.п.8. 3_12.00.01.11.001 Наименование: При наличии напряженных и стесненных условий производства работ (стесненность, сложность складирования и транспортной логистики и т.п.) для объектов, расположенных в пределах круговой магистральной системы улиц "Садовое кольцо" города Москвы Поправка: Гл.4.Прил.2.2.п.2.2.29_04.00.01.35.003 Наименование: При демонтаже оборудования, предназначенного в лом | CO41: 0 | CP41: =(P41+Q41+S41) -> 42654.26 | CQ41: =ROUND((ROUND((AC41*AW41*1),2)*BC41),2) -> 0 | CR41: =(ROUND((ROUND(((((ET41*1.2)*0.3))*AV41*1),2)*BB41),2)+ROUND((ROUND(((AE41-(((EU41*1.2)*0.3)))*AV41*1),2)*BS41),2)) -> 10.87 | CS41: =(ROUND((ROUND(((((EU41*1.2)*0.3))*AV41*1),2)*BS41),2)+ROUND((ROUND(((AE41-(((EU41*1.2)*0.3)))*AV41*1),2)*BS41),2)) -> 2.82 | CT41: =ROUND((ROUND((AF41*AV41*1),2)*BA41),2) -> 5255.2 | CU41: =AG41 -> 0 | CV41: =(AH41*AV41) -> 5.8573368 | CW41: =AI41 -> 0 | CX41: =AJ41 -> 0 | CY41: =(ROUND((((S41+ROUND((ROUND(((((EU41*1.2)*0.3))*AV41*1),2)*BS41),2))*AT41)/100),2)+ROUND(((ROUND((ROUND(((AE41-(((EU41*1.2)*0.3)))*AV41*1),2)*BS41),2)*AT41)/100),2)) -> 38312.15 | CZ41: =(ROUND((((S41+ROUND((ROUND(((((EU41*1.2)*0.3))*AV41*1),2)*BS41),2))*AU41)/100),2)+ROUND(((ROUND((ROUND(((AE41-(((EU41*1.2)*0.3)))*AV41*1),2)*BS41),2)*AU41)/100),2)) -> 19581.76 | DB41: 27 | DD41: *1)*0 | DE41: *1,2)*0,3 | DF41: *1,2)*0,3 | DG41: *1,2)*0,3 | DI41: *1,2)*0,3 | DJ41: *1,2)*0,3 | DN41: 0 | DO41: 0 | DP41: 1 | DQ41: 1 | DU41: 1010 | DV41: 10 шт. | DW41: 10 шт. | DX41: 10 | EE41: 57042958 | EF41: 40 | EG41: Монтаж оборудования | EH41: 0 | EJ41: 2 | EK41: 68 | EL41: ТСН-2001.4-10. Прокладка и монтаж сетей связи | EM41: ТСН-2001.4-10-1 | EO41: Поправка: Гл.12.Прил.8.п.8. 3_12.00.01.11.001 Поправка: Гл.4.Прил.2.2.п.2.2.29_04.00.01.35.003 | EQ41: 0 | ER41: 292.29 | ES41: 42.51 | ET41: 2.36 | EU41: 0.13 | EV41: 247.42 | EW41: 15.54 | EX41: 0 | EY41: 0 | FQ41: 0 | FR41: 0 | FS41: 0 | FX41: 90 | FY41: 46 | GD41: 1 | GF41: 1565221849 | GG41: 2 | GH41: 1 | GI41: 2 | GJ41: 0 | GK41: 0 | GL41: =ROUND(IF(AND(BH41=3,BI41=3,FS41<>0),P41,0),2) -> 0 | GM41: =ROUND(O41+X41+Y41,2)+GX41 -> 100574.98 | GN41: =IF(OR(BI41=0,BI41=1),GM41-GX41,0) -> 0 | GO41: =IF(BI41=2,GM41-GX41,0) -> 100574.98 | GP41: =IF(BI41=4,GM41-GX41,0) -> 0 | GR41: 0 | GS41: 3 | GT41: 0 | GV41: =ROUND((GT41),6) -> 0 | GW41: 1 | GX41: =ROUND(HC41*I41,2) -> 0 | HA41: 0 | HB41: 0 | HC41: =GV41*GW41 -> 0 | HS41: 0 | IK41: 0
A42: 17 | B42: 1 | C42: =ROW(SmtRes!A116) -> 116 | D42: =ROW(EtalonRes!A141) -> 141 | E42: 8 | F42: 4.10-174-2 | G42: Монтаж наружной камеры видеонаблюдения / демонтаж видеокамер | H42: 10 шт. | I42: =ROUND((14+4)/10,9) -> 1.8 | J42: 0 | K42: =ROUND((14+4)/10,9) -> 1.8 | O42: =ROUND(CP42,2) -> 273.84 | P42: =ROUND((ROUND((AC42*AW42*I42),2)*BC42),2) -> 0 | Q42: =(ROUND((ROUND(((((ET42*1.2)*0.3))*AV42*I42),2)*BB42),2)+ROUND((ROUND(((AE42-(((EU42*1.2)*0.3)))*AV42*I42),2)*BS42),2)) -> 1.6 | R42: =(ROUND((ROUND(((((EU42*1.2)*0.3))*AV42*I42),2)*BS42),2)+ROUND((ROUND(((AE42-(((EU42*1.2)*0.3)))*AV42*I42),2)*BS42),2)) -> 0.09 | S42: =ROUND((ROUND((AF42*AV42*I42),2)*BA42),2) -> 272.24 | T42: =ROUND(CU42*I42,2) -> 0 | U42: =CV42*I42 -> 17.18529 | V42: =CW42*I42 -> 0 | W42: =ROUND(CX42*I42,2) -> 0 | X42: =(ROUND((((S42+ROUND((ROUND(((((EU42*1.2)*0.3))*AV42*I42),2)*BS42),2))*AT42)/100),2)+ROUND(((ROUND((ROUND(((AE42-(((EU42*1.2)*0.3)))*AV42*I42),2)*BS42),2)*AT42)/100),2)) -> 245.1 | Y42: =(ROUND((((S42+ROUND((ROUND(((((EU42*1.2)*0.3))*AV42*I42),2)*BS42),2))*AU42)/100),2)+ROUND(((ROUND((ROUND(((AE42-(((EU42*1.2)*0.3)))*AV42*I42),2)*BS42),2)*AU42)/100),2)) -> 125.27 | AA42: 55934355 | AB42: =ROUND((AC42+AD42+AF42),6) -> 145.3068 | AC42: =ROUND((((ES42*1)*0)),6) -> 0 | AD42: =ROUND((((((ET42*1.2)*0.3))-(((EU42*1.2)*0.3)))+AE42),6) -> 0.8496 | AE42: =ROUND((((EU42*1.2)*0.3)),6) -> 0.0468 | AF42: =ROUND((((EV42*1.2)*0.3)),6) -> 144.4572 | AG42: =ROUND((AP42),6) -> 0 | AH42: =(((EW42*1.2)*0.3)) -> 9.1188 | AI42: =(((EX42*1.2)*0.3)) -> 0 | AJ42: =(AS42) -> 0 | AK42: 446.14 | AL42: 42.51 | AM42: 2.36 | AN42: 0.13 | AO42: 401.27 | AP42: 0 | AQ42: 25.33 | AR42: 0 | AS42: 0 | AT42: 90 | AU42: 46 | AV42: 1.047 | AW42: 1 | AZ42: 1 | BA42: 1 | BB42: 1 | BC42: 1 | BH42: 0 | BI42: 2 | BJ42: ТСН-2001.4 Доп. 68, Сб. 10, т. 174, поз. 2 | BM42: 68 | BN42: 0 | BO42: 4.10-174-2 | BP42: 1 | BQ42: 40 | BR42: 0 | BS42: 1 | BT42: 1 | BU42: 1 | BV42: 1 | BW42: 1 | BX42: 1 | BZ42: 90 | CA42: 46 | CE42: 1566 | CF42: 0 | CG42: 0 | CM42: 0 | CN42: Поправка: Гл.12.Прил.8.п.8. 3_12.00.01.11.001 Наименование: При наличии напряженных и стесненных условий производства работ (стесненность, сложность складирования и транспортной логистики и т.п.) для объектов, расположенных в пределах круговой магистральной системы улиц "Садовое кольцо" города Москвы Поправка: Гл.4.Прил.2.2.п.2.2.29_04.00.01.35.003 Наименование: При демонтаже оборудования, предназначенного в лом | CO42: 0 | CP42: =(P42+Q42+S42) -> 273.84 | CQ42: =ROUND((ROUND((AC42*AW42*1),2)*BC42),2) -> 0 | CR42: =(ROUND((ROUND(((((ET42*1.2)*0.3))*AV42*1),2)*BB42),2)+ROUND((ROUND(((AE42-(((EU42*1.2)*0.3)))*AV42*1),2)*BS42),2)) -> 0.89 | CS42: =(ROUND((ROUND(((((EU42*1.2)*0.3))*AV42*1),2)*BS42),2)+ROUND((ROUND(((AE42-(((EU42*1.2)*0.3)))*AV42*1),2)*BS42),2)) -> 0.05 | CT42: =ROUND((ROUND((AF42*AV42*1),2)*BA42),2) -> 151.25 | CU42: =AG42 -> 0 | CV42: =(AH42*AV42) -> 9.5473836 | CW42: =AI42 -> 0 | CX42: =AJ42 -> 0 | CY42: =(ROUND((((S42+ROUND((ROUND(((((EU42*1.2)*0.3))*AV42*1),2)*BS42),2))*AT42)/100),2)+ROUND(((ROUND((ROUND(((AE42-(((EU42*1.2)*0.3)))*AV42*1),2)*BS42),2)*AT42)/100),2)) -> 245.06 | CZ42: =(ROUND((((S42+ROUND((ROUND(((((EU42*1.2)*0.3))*AV42*1),2)*BS42),2))*AU42)/100),2)+ROUND(((ROUND((ROUND(((AE42-(((EU42*1.2)*0.3)))*AV42*1),2)*BS42),2)*AU42)/100),2)) -> 125.25 | DB42: 29 | DD42: *1)*0 | DE42: *1,2)*0,3 | DF42: *1,2)*0,3 | DG42: *1,2)*0,3 | DI42: *1,2)*0,3 | DJ42: *1,2)*0,3 | DN42: 0 | DO42: 0 | DP42: 1 | DQ42: 1 | DU42: 1010 | DV42: 10 шт. | DW42: 10 шт. | DX42: 10 | EE42: 57042958 | EF42: 40 | EG42: Монтаж оборудования | EH42: 0 | EJ42: 2 | EK42: 68 | EL42: ТСН-2001.4-10. Прокладка и монтаж сетей связи | EM42: ТСН-2001.4-10-1 | EO42: Поправка: Гл.12.Прил.8.п.8. 3_12.00.01.11.001 Поправка: Гл.4.Прил.2.2.п.2.2.29_04.00.01.35.003 | EQ42: 0 | ER42: 446.14 | ES42: 42.51 | ET42: 2.36 | EU42: 0.13 | EV42: 401.27 | EW42: 25.33 | EX42: 0 | EY42: 0 | FQ42: 0 | FR42: 0 | FS42: 0 | FX42: 90 | FY42: 46 | GD42: 1 | GF42: -1633559257 | GG42: 2 | GH42: 1 | GI42: 2 | GJ42: 0 | GK42: 0 | GL42: =ROUND(IF(AND(BH42=3,BI42=3,FS42<>0),P42,0),2) -> 0 | GM42: =ROUND(O42+X42+Y42,2)+GX42 -> 644.21 | GN42: =IF(OR(BI42=0,BI42=1),GM42-GX42,0) -> 0 | GO42: =IF(BI42=2,GM42-GX42,0) -> 644.21 | GP42: =IF(BI42=4,GM42-GX42,0) -> 0 | GR42: 0 | GS42: 3 | GT42: 0 | GV42: =ROUND((GT42),6) -> 0 | GW42: 1 | GX42: =ROUND(HC42*I42,2) -> 0 | HA42: 0 | HB42: 0 | HC42: =GV42*GW42 -> 0 | HS42: 0 | IK42: 0
A43: 17 | B43: 1 | C43: =ROW(SmtRes!A122) -> 122 | D43: =ROW(EtalonRes!A148) -> 148 | E43: 8 | F43: 4.10-174-2 | G43: Монтаж наружной камеры видеонаблюдения / демонтаж видеокамер | H43: 10 шт. | I43: =ROUND((14+4)/10,9) -> 1.8 | J43: 0 | K43: =ROUND((14+4)/10,9) -> 1.8 | O43: =ROUND(CP43,2) -> 15360.26 | P43: =ROUND((ROUND((AC43*AW43*I43),2)*BC43),2) -> 0 | Q43: =(ROUND((ROUND(((((ET43*1.2)*0.3))*AV43*I43),2)*BB43),2)+ROUND((ROUND(((AE43-(((EU43*1.2)*0.3)))*AV43*I43),2)*BS43),2)) -> 19.54 | R43: =(ROUND((ROUND(((((EU43*1.2)*0.3))*AV43*I43),2)*BS43),2)+ROUND((ROUND(((AE43-(((EU43*1.2)*0.3)))*AV43*I43),2)*BS43),2)) -> 5.07 | S43: =ROUND((ROUND((AF43*AV43*I43),2)*BA43),2) -> 15340.72 | T43: =ROUND(CU43*I43,2) -> 0 | U43: =CV43*I43 -> 17.18529 | V43: =CW43*I43 -> 0 | W43: =ROUND(CX43*I43,2) -> 0 | X43: =(ROUND((((S43+ROUND((ROUND(((((EU43*1.2)*0.3))*AV43*I43),2)*BS43),2))*AT43)/100),2)+ROUND(((ROUND((ROUND(((AE43-(((EU43*1.2)*0.3)))*AV43*I43),2)*BS43),2)*AT43)/100),2)) -> 13811.21 | Y43: =(ROUND((((S43+ROUND((ROUND(((((EU43*1.2)*0.3))*AV43*I43),2)*BS43),2))*AU43)/100),2)+ROUND(((ROUND((ROUND(((AE43-(((EU43*1.2)*0.3)))*AV43*I43),2)*BS43),2)*AU43)/100),2)) -> 7059.06 | AA43: 55934357 | AB43: =ROUND((AC43+AD43+AF43),6) -> 145.3068 | AC43: =ROUND((((ES43*1)*0)),6) -> 0 | AD43: =ROUND((((((ET43*1.2)*0.3))-(((EU43*1.2)*0.3)))+AE43),6) -> 0.8496 | AE43: =ROUND((((EU43*1.2)*0.3)),6) -> 0.0468 | AF43: =ROUND((((EV43*1.2)*0.3)),6) -> 144.4572 | AG43: =ROUND((AP43),6) -> 0 | AH43: =(((EW43*1.2)*0.3)) -> 9.1188 | AI43: =(((EX43*1.2)*0.3)) -> 0 | AJ43: =(AS43) -> 0 | AK43: 446.14 | AL43: 42.51 | AM43: 2.36 | AN43: 0.13 | AO43: 401.27 | AP43: 0 | AQ43: 25.33 | AR43: 0 | AS43: 0 | AT43: 90 | AU43: 46 | AV43: 1.047 | AW43: 1 | AZ43: 1 | BA43: 56.35 | BB43: 12.21 | BC43: 1.84 | BH43: 0 | BI43: 2 | BJ43: ТСН-2001.4 Доп. 68, Сб. 10, т. 174, поз. 2 | BM43: 68 | BN43: 0 | BO43: 4.10-174-2 | BP43: 1 | BQ43: 40 | BR43: 0 | BS43: 56.35 | BT43: 1 | BU43: 1 | BV43: 1 | BW43: 1 | BX43: 1 | BZ43: 90 | CA43: 46 | CE43: 1566 | CF43: 0 | CG43: 0 | CM43: 0 | CN43: Поправка: Гл.12.Прил.8.п.8. 3_12.00.01.11.001 Наименование: При наличии напряженных и стесненных условий производства работ (стесненность, сложность складирования и транспортной логистики и т.п.) для объектов, расположенных в пределах круговой магистральной системы улиц "Садовое кольцо" города Москвы Поправка: Гл.4.Прил.2.2.п.2.2.29_04.00.01.35.003 Наименование: При демонтаже оборудования, предназначенного в лом | CO43: 0 | CP43: =(P43+Q43+S43) -> 15360.26 | CQ43: =ROUND((ROUND((AC43*AW43*1),2)*BC43),2) -> 0 | CR43: =(ROUND((ROUND(((((ET43*1.2)*0.3))*AV43*1),2)*BB43),2)+ROUND((ROUND(((AE43-(((EU43*1.2)*0.3)))*AV43*1),2)*BS43),2)) -> 10.87 | CS43: =(ROUND((ROUND(((((EU43*1.2)*0.3))*AV43*1),2)*BS43),2)+ROUND((ROUND(((AE43-(((EU43*1.2)*0.3)))*AV43*1),2)*BS43),2)) -> 2.82 | CT43: =ROUND((ROUND((AF43*AV43*1),2)*BA43),2) -> 8522.94 | CU43: =AG43 -> 0 | CV43: =(AH43*AV43) -> 9.5473836 | CW43: =AI43 -> 0 | CX43: =AJ43 -> 0 | CY43: =(ROUND((((S43+ROUND((ROUND(((((EU43*1.2)*0.3))*AV43*1),2)*BS43),2))*AT43)/100),2)+ROUND(((ROUND((ROUND(((AE43-(((EU43*1.2)*0.3)))*AV43*1),2)*BS43),2)*AT43)/100),2)) -> 13809.19 | CZ43: =(ROUND((((S43+ROUND((ROUND(((((EU43*1.2)*0.3))*AV43*1),2)*BS43),2))*AU43)/100),2)+ROUND(((ROUND((ROUND(((AE43-(((EU43*1.2)*0.3)))*AV43*1),2)*BS43),2)*AU43)/100),2)) -> 7058.03 | DB43: 31 | DD43: *1)*0 | DE43: *1,2)*0,3 | DF43: *1,2)*0,3 | DG43: *1,2)*0,3 | DI43: *1,2)*0,3 | DJ43: *1,2)*0,3 | DN43: 0 | DO43: 0 | DP43: 1 | DQ43: 1 | DU43: 1010 | DV43: 10 шт. | DW43: 10 шт. | DX43: 10 | EE43: 57042958 | EF43: 40 | EG43: Монтаж оборудования | EH43: 0 | EJ43: 2 | EK43: 68 | EL43: ТСН-2001.4-10. Прокладка и монтаж сетей связи | EM43: ТСН-2001.4-10-1 | EO43: Поправка: Гл.12.Прил.8.п.8. 3_12.00.01.11.001 Поправка: Гл.4.Прил.2.2.п.2.2.29_04.00.01.35.003 | EQ43: 0 | ER43: 446.14 | ES43: 42.51 | ET43: 2.36 | EU43: 0.13 | EV43: 401.27 | EW43: 25.33 | EX43: 0 | EY43: 0 | FQ43: 0 | FR43: 0 | FS43: 0 | FX43: 90 | FY43: 46 | GD43: 1 | GF43: -1633559257 | GG43: 2 | GH43: 1 | GI43: 2 | GJ43: 0 | GK43: 0 | GL43: =ROUND(IF(AND(BH43=3,BI43=3,FS43<>0),P43,0),2) -> 0 | GM43: =ROUND(O43+X43+Y43,2)+GX43 -> 36230.53 | GN43: =IF(OR(BI43=0,BI43=1),GM43-GX43,0) -> 0 | GO43: =IF(BI43=2,GM43-GX43,0) -> 36230.53 | GP43: =IF(BI43=4,GM43-GX43,0) -> 0 | GR43: 0 | GS43: 3 | GT43: 0 | GV43: =ROUND((GT43),6) -> 0 | GW43: 1 | GX43: =ROUND(HC43*I43,2) -> 0 | HA43: 0 | HB43: 0 | HC43: =GV43*GW43 -> 0 | HS43: 0 | IK43: 0
A45: 51 | B45: =B24 -> 1 | C45: =A24 -> 4 | D45: =ROW(A24) -> 24 | F45: =IF(F24<>"",F24,"") -> Новый раздел | G45: =IF(G24<>"",G24,"") -> Демонтажные работы (Письмо от АНО «РГТ» об утверждении объёмов демонтажных работ) | H45: 0 | O45: =ROUND(AB45,2) -> 1630.65 | P45: =ROUND(AC45,2) -> 0 | Q45: =ROUND(AD45,2) -> 73.74 | R45: =ROUND(AE45,2) -> 7.64 | S45: =ROUND(AF45,2) -> 1556.91 | T45: =ROUND(AG45,2) -> 0 | U45: =AH45 -> 106.92014 | V45: =AI45 -> 0 | W45: =ROUND(AJ45,2) -> 0 | X45: =ROUND(AK45,2) -> 1415.01 | Y45: =ROUND(AL45,2) -> 729.36 | AB45: =ROUND(SUMIF(AA28:AA43,"=55934355",O28:O43),2) -> 1630.65 | AC45: =ROUND(SUMIF(AA28:AA43,"=55934355",P28:P43),2) -> 0 | AD45: =ROUND(SUMIF(AA28:AA43,"=55934355",Q28:Q43),2) -> 73.74 | AE45: =ROUND(SUMIF(AA28:AA43,"=55934355",R28:R43),2) -> 7.64 | AF45: =ROUND(SUMIF(AA28:AA43,"=55934355",S28:S43),2) -> 1556.91 | AG45: =ROUND(SUMIF(AA28:AA43,"=55934355",T28:T43),2) -> 0 | AH45: =SUMIF(AA28:AA43,"=55934355",U28:U43) -> 106.92014 | AI45: =SUMIF(AA28:AA43,"=55934355",V28:V43) -> 0 | AJ45: =ROUND(SUMIF(AA28:AA43,"=55934355",W28:W43),2) -> 0 | AK45: =ROUND(SUMIF(AA28:AA43,"=55934355",X28:X43),2) -> 1415.01 | AL45: =ROUND(SUMIF(AA28:AA43,"=55934355",Y28:Y43),2) -> 729.36 | AO45: =ROUND(BX45,2) -> 0 | AP45: =ROUND(BY45,2) -> 0 | AQ45: =ROUND(BZ45,2) -> 0 | AR45: =ROUND(CA45,2) -> 3775.02 | AS45: =ROUND(CB45,2) -> 0 | AT45: =ROUND(CC45,2) -> 3775.02 | AU45: =ROUND(CD45,2) -> 0 | AV45: =ROUND(CE45,2) -> 0 | ... BD45: =ROUND(CM45,2) -> 0 | BX45: =ROUND(SUMIF(AA28:AA43,"=55934355",FQ28:FQ43),2) -> 0 | BY45: =ROUND(SUMIF(AA28:AA43,"=55934355",FR28:FR43),2) -> 0 | BZ45: =ROUND(SUMIF(AA28:AA43,"=55934355",GL28:GL43),2) -> 0 | CA45: =ROUND(SUMIF(AA28:AA43,"=55934355",GM28:GM43),2) -> 3775.02 | CB45: =ROUND(SUMIF(AA28:AA43,"=55934355",GN28:GN43),2) -> 0 | CC45: =ROUND(SUMIF(AA28:AA43,"=55934355",GO28:GO43),2) -> 3775.02 | CD45: =ROUND(SUMIF(AA28:AA43,"=55934355",GP28:GP43),2) -> 0 | CE45: =AC45-BX45 -> 0 | CF45: =AC45-BY45 -> 0 | CG45: =BX45-BZ45 -> 0 | CH45: =AC45-BX45-BY45+BZ45 -> 0 | CI45: =BY45-BZ45 -> 0 | CJ45: =ROUND(SUMIF(AA28:AA43,"=55934355",GX28:GX43),2) -> 0 | CK45: =ROUND(SUMIF(AA28:AA43,"=55934355",GY28:GY43),2) -> 0 | CL45: =ROUND(SUMIF(AA28:AA43,"=55934355",GZ28:GZ43),2) -> 0 | CM45: =ROUND(SUMIF(AA28:AA43,"=55934355",HD28:HD43),2) -> 0 | DG45: =ROUND(DT45,2) -> 88888.72 | DH45: =ROUND(DU45,2) -> 0 | DI45: =ROUND(DV45,2) -> 1156.84 | DJ45: =ROUND(DW45,2) -> 430.51 | DK45: =ROUND(DX45,2) -> 87731.88 | DL45: =ROUND(DY45,2) -> 0 | DM45: =DZ45 -> 106.92014 | DN45: =EA45 -> 0 | DO45: =ROUND(EB45,2) -> 0 | DP45: =ROUND(EC45,2) -> 79735.77 | DQ45: =ROUND(ED45,2) -> 41100.19 | DT45: =ROUND(SUMIF(AA28:AA43,"=55934357",O28:O43),2) -> 88888.72 | DU45: =ROUND(SUMIF(AA28:AA43,"=55934357",P28:P43),2) -> 0 | DV45: =ROUND(SUMIF(AA28:AA43,"=55934357",Q28:Q43),2) -> 1156.84 | DW45: =ROUND(SUMIF(AA28:AA43,"=55934357",R28:R43),2) -> 430.51 | DX45: =ROUND(SUMIF(AA28:AA43,"=55934357",S28:S43),2) -> 87731.88 | DY45: =ROUND(SUMIF(AA28:AA43,"=55934357",T28:T43),2) -> 0 | DZ45: =SUMIF(AA28:AA43,"=55934357",U28:U43) -> 106.92014 | EA45: =SUMIF(AA28:AA43,"=55934357",V28:V43) -> 0 | EB45: =ROUND(SUMIF(AA28:AA43,"=55934357",W28:W43),2) -> 0 | EC45: =ROUND(SUMIF(AA28:AA43,"=55934357",X28:X43),2) -> 79735.77 | ED45: =ROUND(SUMIF(AA28:AA43,"=55934357",Y28:Y43),2) -> 41100.19 | EG45: =ROUND(FP45,2) -> 0 | EH45: =ROUND(FQ45,2) -> 0 | EI45: =ROUND(FR45,2) -> 0 | EJ45: =ROUND(FS45,2) -> 209724.68 | EK45: =ROUND(FT45,2) -> 0 | EL45: =ROUND(FU45,2) -> 209724.68 | EM45: =ROUND(FV45,2) -> 0 | EN45: =ROUND(FW45,2) -> 0 | ... EV45: =ROUND(GE45,2) -> 0 | FP45: =ROUND(SUMIF(AA28:AA43,"=55934357",FQ28:FQ43),2) -> 0 | FQ45: =ROUND(SUMIF(AA28:AA43,"=55934357",FR28:FR43),2) -> 0 | FR45: =ROUND(SUMIF(AA28:AA43,"=55934357",GL28:GL43),2) -> 0 | FS45: =ROUND(SUMIF(AA28:AA43,"=55934357",GM28:GM43),2) -> 209724.68 | FT45: =ROUND(SUMIF(AA28:AA43,"=55934357",GN28:GN43),2) -> 0 | FU45: =ROUND(SUMIF(AA28:AA43,"=55934357",GO28:GO43),2) -> 209724.68 | FV45: =ROUND(SUMIF(AA28:AA43,"=55934357",GP28:GP43),2) -> 0 | FW45: =DU45-FP45 -> 0 | FX45: =DU45-FQ45 -> 0 | FY45: =FP45-FR45 -> 0 | FZ45: =DU45-FP45-FQ45+FR45 -> 0 | GA45: =FQ45-FR45 -> 0 | GB45: =ROUND(SUMIF(AA28:AA43,"=55934357",GX28:GX43),2) -> 0 | GC45: =ROUND(SUMIF(AA28:AA43,"=55934357",GY28:GY43),2) -> 0 | GD45: =ROUND(SUMIF(AA28:AA43,"=55934357",GZ28:GZ43),2) -> 0 | GE45: =ROUND(SUMIF(AA28:AA43,"=55934357",HD28:HD43),2) -> 0 | GX45: 0
A47: 50 | B47: 0 | C47: 0 | D47: 1 | E47: 201 | F47: =ROUND(Source!O45,O47) -> 1630.65 | G47: ПЗ | H47: Прямые затраты | K47: 201 | L47: 1 | M47: 3 | O47: 2 | P47: =ROUND(Source!DG45,O47) -> 88888.72 | W47: 1630.65 | X47: 1 | Y47: 1630.65 | Z47: 88888.72 | AA47: 1 | AB47: 88888.72
A48: 50 | B48: 0 | C48: 0 | D48: 1 | E48: 202 | F48: =ROUND(Source!P45,O48) -> 0 | G48: СтМатОб | H48: Стоимость материальных ресурсов (всего) | K48: 202 | L48: 2 | M48: 3 | O48: 2 | P48: =ROUND(Source!DH45,O48) -> 0 | W48: 0 | X48: 1 | Y48: 0 | Z48: 0 | AA48: 1 | AB48: 0
A49: 50 | B49: 0 | C49: 0 | D49: 1 | E49: 222 | F49: =ROUND(Source!AO45,O49) -> 0 | G49: СтМатОбЗак | H49: Стоимость материалов и оборудования заказчика | K49: 222 | L49: 3 | M49: 3 | O49: 2 | P49: =ROUND(Source!EG45,O49) -> 0 | W49: 0 | X49: 1 | Y49: 0 | Z49: 0 | AA49: 1 | AB49: 0
A50: 50 | B50: 0 | C50: 0 | D50: 1 | E50: 225 | F50: =ROUND(Source!AV45,O50) -> 0 | G50: СтМатОбПод | H50: Стоимость материалов и оборудования подрядчика | K50: 225 | L50: 4 | M50: 3 | O50: 2 | P50: =ROUND(Source!EN45,O50) -> 0 | W50: 0 | X50: 1 | Y50: 0 | Z50: 0 | AA50: 1 | AB50: 0
A51: 50 | B51: 0 | C51: 0 | D51: 1 | E51: 226 | F51: =ROUND(Source!AW45,O51) -> 0 | G51: СтМат | H51: Стоимость материалов (всего) | K51: 226 | L51: 5 | M51: 3 | O51: 2 | P51: =ROUND(Source!EO45,O51) -> 0 | W51: 0 | X51: 1 | Y51: 0 | Z51: 0 | AA51: 1 | AB51: 0
A52: 50 | B52: 0 | C52: 0 | D52: 1 | E52: 227 | F52: =ROUND(Source!AX45,O52) -> 0 | G52: СтМатЗак | H52: Стоимость материалов заказчика | K52: 227 | L52: 6 | M52: 3 | O52: 2 | P52: =ROUND(Source!EP45,O52) -> 0 | W52: 0 | X52: 1 | Y52: 0 | Z52: 0 | AA52: 1 | AB52: 0
A53: 50 | B53: 0 | C53: 0 | D53: 1 | E53: 228 | F53: =ROUND(Source!AY45,O53) -> 0 | G53: СтМатПод | H53: Стоимость материалов подрядчика | K53: 228 | L53: 7 | M53: 3 | O53: 2 | P53: =ROUND(Source!EQ45,O53) -> 0 | W53: 0 | X53: 1 | Y53: 0 | Z53: 0 | AA53: 1 | AB53: 0
A54: 50 | B54: 0 | C54: 0 | D54: 1 | E54: 216 | F54: =ROUND(Source!AP45,O54) -> 0 | G54: Оборуд | H54: Стоимость оборудования (всего) | K54: 216 | L54: 8 | M54: 3 | O54: 2 | P54: =ROUND(Source!EH45,O54) -> 0 | W54: 0 | X54: 1 | Y54: 0 | Z54: 0 | AA54: 1 | AB54: 0
A55: 50 | B55: 0 | C55: 0 | D55: 1 | E55: 223 | F55: =ROUND(Source!AQ45,O55) -> 0 | G55: ОборудЗак | H55: Стоимость оборудования заказчика | K55: 223 | L55: 9 | M55: 3 | O55: 2 | P55: =ROUND(Source!EI45,O55) -> 0 | W55: 0 | X55: 1 | Y55: 0 | Z55: 0 | AA55: 1 | AB55: 0
A56: 50 | B56: 0 | C56: 0 | D56: 1 | E56: 229 | F56: =ROUND(Source!AZ45,O56) -> 0 | G56: ОборудПод | H56: Стоимость оборудования подрядчика | K56: 229 | L56: 10 | M56: 3 | O56: 2 | P56: =ROUND(Source!ER45,O56) -> 0 | W56: 0 | X56: 1 | Y56: 0 | Z56: 0 | AA56: 1 | AB56: 0
A57: 50 | B57: 0 | C57: 0 | D57: 1 | E57: 203 | F57: =ROUND(Source!Q45,O57) -> 73.74 | G57: ЭММ | H57: Эксплуатация машин | K57: 203 | L57: 11 | M57: 3 | O57: 2 | P57: =ROUND(Source!DI45,O57) -> 1156.84 | W57: 73.74 | X57: 1 | Y57: 73.74 | Z57: 1156.84 | AA57: 1 | AB57: 1156.84
A58: 50 | B58: 0 | C58: 0 | D58: 1 | E58: 231 | F58: =ROUND(Source!BB45,O58) -> 0 | G58: ЭММсНРиСП | H58: Эксплуатация машин по ТСН-2001.16 | K58: 231 | L58: 12 | M58: 3 | O58: 2 | P58: =ROUND(Source!ET45,O58) -> 0 | W58: 0 | X58: 1 | Y58: 0 | Z58: 0 | AA58: 1 | AB58: 0
A59: 50 | B59: 0 | C59: 0 | D59: 1 | E59: 204 | F59: =ROUND(Source!R45,O59) -> 7.64 | G59: ЗПМ | H59: ЗП машинистов | K59: 204 | L59: 13 | M59: 3 | O59: 2 | P59: =ROUND(Source!DJ45,O59) -> 430.51 | W59: 7.64 | X59: 1 | Y59: 7.64 | Z59: 430.51 | AA59: 1 | AB59: 430.51
A60: 50 | B60: 0 | C60: 0 | D60: 1 | E60: 205 | F60: =ROUND(Source!S45,O60) -> 1556.91 | G60: ОЗП | H60: Основная ЗП рабочих | K60: 205 | L60: 14 | M60: 3 | O60: 2 | P60: =ROUND(Source!DK45,O60) -> 87731.88 | W60: 1556.91 | X60: 1 | Y60: 1556.91 | Z60: 87731.88 | AA60: 1 | AB60: 87731.88
A61: 50 | B61: 0 | C61: 0 | D61: 1 | E61: 232 | F61: =ROUND(Source!BC45,O61) -> 0 | G61: ОЗПсНРиСП | H61: Основная ЗП рабочих по ТСН-2001.16 | K61: 232 | L61: 15 | M61: 3 | O61: 2 | P61: =ROUND(Source!EU45,O61) -> 0 | W61: 0 | X61: 1 | Y61: 0 | Z61: 0 | AA61: 1 | AB61: 0
A62: 50 | B62: 0 | C62: 0 | D62: 1 | E62: 214 | F62: =ROUND(Source!AS45,O62) -> 0 | G62: Строит | H62: Строительные работы с НР и СП | K62: 214 | L62: 16 | M62: 3 | O62: 2 | P62: =ROUND(Source!EK45,O62) -> 0 | W62: 0 | X62: 1 | Y62: 0 | Z62: 0 | AA62: 1 | AB62: 0
A63: 50 | B63: 0 | C63: 0 | D63: 1 | E63: 215 | F63: =ROUND(Source!AT45,O63) -> 3775.02 | G63: Монтаж | H63: Монтажные работы с НР и СП | K63: 215 | L63: 17 | M63: 3 | O63: 2 | P63: =ROUND(Source!EL45,O63) -> 209724.68 | W63: 3775.02 | X63: 1 | Y63: 3775.02 | Z63: 209724.68 | AA63: 1 | AB63: 209724.68
A64: 50 | B64: 0 | C64: 0 | D64: 1 | E64: 217 | F64: =ROUND(Source!AU45,O64) -> 0 | G64: Прочие | H64: Прочие работы с НР и СП | K64: 217 | L64: 18 | M64: 3 | O64: 2 | P64: =ROUND(Source!EM45,O64) -> 0 | W64: 0 | X64: 1 | Y64: 0 | Z64: 0 | AA64: 1 | AB64: 0
A65: 50 | B65: 0 | C65: 0 | D65: 1 | E65: 230 | F65: =ROUND(Source!BA45,O65) -> 0 | G65: ПрочиеЗатр | H65: Прочие затраты по ТСН-2001.16 | K65: 230 | L65: 19 | M65: 3 | O65: 2 | P65: =ROUND(Source!ES45,O65) -> 0 | W65: 0 | X65: 1 | Y65: 0 | Z65: 0 | AA65: 1 | AB65: 0
A66: 50 | B66: 0 | C66: 0 | D66: 1 | E66: 206 | F66: =ROUND(Source!T45,O66) -> 0 | G66: ВозврМат | H66: Возврат материалов | K66: 206 | L66: 20 | M66: 3 | O66: 2 | P66: =ROUND(Source!DL45,O66) -> 0 | W66: 0 | X66: 1 | Y66: 0 | Z66: 0 | AA66: 1 | AB66: 0
A67: 50 | B67: 0 | C67: 0 | D67: 1 | E67: 207 | F67: =Source!U45 -> 106.92014 | G67: ТрудСтр | H67: Трудозатраты строителей | K67: 207 | L67: 21 | M67: 3 | O67: -1 | P67: =Source!DM45 -> 106.92014 | W67: 106.92014 | X67: 1 | Y67: 106.92014 | Z67: 106.92014 | AA67: 1 | AB67: 106.92014
A68: 50 | B68: 0 | C68: 0 | D68: 1 | E68: 208 | F68: =Source!V45 -> 0 | G68: ТрудМаш | H68: Трудозатраты машинистов | K68: 208 | L68: 22 | M68: 3 | O68: -1 | P68: =Source!DN45 -> 0 | W68: 0 | X68: 1 | Y68: 0 | Z68: 0 | AA68: 1 | AB68: 0
A69: 50 | B69: 0 | C69: 0 | D69: 1 | E69: 209 | F69: =ROUND(Source!W45,O69) -> 0 | G69: ТранспМат | H69: Транспорт материалов | K69: 209 | L69: 23 | M69: 3 | O69: 2 | P69: =ROUND(Source!DO45,O69) -> 0 | W69: 0 | X69: 1 | Y69: 0 | Z69: 0 | AA69: 1 | AB69: 0
A70: 50 | B70: 0 | C70: 0 | D70: 1 | E70: 233 | F70: =ROUND(Source!BD45,O70) -> 0 | G70: Перевозка | H70: Перевозка грузов | K70: 233 | L70: 24 | M70: 3 | O70: 2 | P70: =ROUND(Source!EV45,O70) -> 0 | W70: 0 | X70: 1 | Y70: 0 | Z70: 0 | AA70: 1 | AB70: 0
A71: 50 | B71: 0 | C71: 0 | D71: 1 | E71: 210 | F71: =ROUND(Source!X45,O71) -> 1415.01 | G71: НР | H71: Накладные расходы | K71: 210 | L71: 25 | M71: 3 | O71: 2 | P71: =ROUND(Source!DP45,O71) -> 79735.77 | W71: 1415.01 | X71: 1 | Y71: 1415.01 | Z71: 79735.77 | AA71: 1 | AB71: 79735.77
A72: 50 | B72: 0 | C72: 0 | D72: 1 | E72: 211 | F72: =ROUND(Source!Y45,O72) -> 729.36 | G72: СмПриб | H72: Сметная прибыль | K72: 211 | L72: 26 | M72: 3 | O72: 2 | P72: =ROUND(Source!DQ45,O72) -> 41100.19 | W72: 729.36 | X72: 1 | Y72: 729.36 | Z72: 41100.19 | AA72: 1 | AB72: 41100.19
A73: 50 | B73: 0 | C73: 0 | D73: 1 | E73: 224 | F73: =ROUND(Source!AR45,O73) -> 3775.02 | G73: Всего | H73: Всего с НР и СП | K73: 224 | L73: 27 | M73: 3 | O73: 2 | P73: =ROUND(Source!EJ45,O73) -> 209724.68 | W73: 3775.02 | X73: 1 | Y73: 3775.02 | Z73: 209724.68 | AA73: 1 | AB73: 209724.68
A75: 4 | B75: 1 | D75: =ROW(A110) -> 110 | F75: 1 | G75: Сетевые приборы СОТ | I75: 0 | K75: -1 | S75: 0 | T75: 0 | V75: 2 | BX75: 0 | CJ75: 0
A77: 52 | B77: =B110 -> 1 | C77: =C110 -> 4 | D77: =D110 -> 75 | E77: =E110 -> 0 | F77: =F110 -> 1 | G77: =G110 -> Сетевые приборы СОТ | O77: =O110 -> 657551.84 | P77: =P110 -> 656284.62 | Q77: =Q110 -> 216.42 | R77: =R110 -> 23.82 | S77: =S110 -> 1050.8 | T77: =T110 -> 0 | U77: =U110 -> 84.43008 | V77: =V110 -> 0 | ... GX77: =GX110 -> 0
A79: 17 | B79: 1 | C79: =ROW(SmtRes!A127) -> 127 | D79: =ROW(EtalonRes!A153) -> 153 | E79: 9 | F79: 4.10-34-5 | G79: Монтаж коммутатора служебной связи | H79: 1 ШТ. | I79: 1 | J79: 0 | K79: 1 | O79: =ROUND(CP79,2) -> 146.72 | P79: =ROUND((ROUND((AC79*AW79*I79),2)*BC79),2) -> 12.35 | Q79: =(ROUND((ROUND((((ET79*1.2))*AV79*I79),2)*BB79),2)+ROUND((ROUND(((AE79-((EU79*1.2)))*AV79*I79),2)*BS79),2)) -> 36.07 | R79: =(ROUND((ROUND((((EU79*1.2))*AV79*I79),2)*BS79),2)+ROUND((ROUND(((AE79-((EU79*1.2)))*AV79*I79),2)*BS79),2)) -> 3.97 | S79: =ROUND((ROUND((AF79*AV79*I79),2)*BA79),2) -> 98.3 | T79: =ROUND(CU79*I79,2) -> 0 | U79: =CV79*I79 -> 7.78968 | V79: =CW79*I79 -> 0 | W79: =ROUND(CX79*I79,2) -> 0 | X79: =(ROUND((((S79+ROUND((ROUND((((EU79*1.2))*AV79*I79),2)*BS79),2))*AT79)/100),2)+ROUND(((ROUND((ROUND(((AE79-((EU79*1.2)))*AV79*I79),2)*BS79),2)*AT79)/100),2)) -> 92.04 | Y79: =(ROUND((((S79+ROUND((ROUND((((EU79*1.2))*AV79*I79),2)*BS79),2))*AU79)/100),2)+ROUND(((ROUND((ROUND(((AE79-((EU79*1.2)))*AV79*I79),2)*BS79),2)*AU79)/100),2)) -> 47.04 | AA79: 55934355 | AB79: =ROUND((AC79+AD79+AF79),6) -> 140.69 | AC79: =ROUND(((ES79*1)),6) -> 12.35 | AD79: =ROUND(((((ET79*1.2))-((EU79*1.2)))+AE79),6) -> 34.452 | AE79: =ROUND(((EU79*1.2)),6) -> 3.792 | AF79: =ROUND(((EV79*1.2)),6) -> 93.888 | AG79: =ROUND((AP79),6) -> 0 | AH79: =((EW79*1.2)) -> 7.44 | AI79: =((EX79*1.2)) -> 0 | AJ79: =(AS79) -> 0 | AK79: 119.3 | AL79: 12.35 | AM79: 28.71 | AN79: 3.16 | AO79: 78.24 | AP79: 0 | AQ79: 6.2 | AR79: 0 | AS79: 0 | AT79: 90 | AU79: 46 | AV79: 1.047 | AW79: 1 | AZ79: 1 | BA79: 1 | BB79: 1 | BC79: 1 | BH79: 0 | BI79: 2 | BJ79: ТСН-2001.4 Доп. 80, Сб. 10, т. 34, поз. 5 | BM79: 68 | BN79: 0 | BO79: 4.10-34-5 | BP79: 1 | BQ79: 40 | BR79: 0 | BS79: 1 | BT79: 1 | BU79: 1 | BV79: 1 | BW79: 1 | BX79: 1 | BZ79: 90 | CA79: 46 | CE79: 1566 | CF79: 0 | CG79: 0 | CM79: 0 | CN79: Поправка: Гл.12.Прил.8.п.8. 3_12.00.01.11.001 Наименование: При наличии напряженных и стесненных условий производства работ (стесненность, сложность складирования и транспортной логистики и т.п.) для объектов, расположенных в пределах круговой магистральной системы улиц "Садовое кольцо" города Москвы | CO79: 0 | CP79: =(P79+Q79+S79) -> 146.72 | CQ79: =ROUND((ROUND((AC79*AW79*1),2)*BC79),2) -> 12.35 | CR79: =(ROUND((ROUND((((ET79*1.2))*AV79*1),2)*BB79),2)+ROUND((ROUND(((AE79-((EU79*1.2)))*AV79*1),2)*BS79),2)) -> 36.07 | CS79: =(ROUND((ROUND((((EU79*1.2))*AV79*1),2)*BS79),2)+ROUND((ROUND(((AE79-((EU79*1.2)))*AV79*1),2)*BS79),2)) -> 3.97 | CT79: =ROUND((ROUND((AF79*AV79*1),2)*BA79),2) -> 98.3 | CU79: =AG79 -> 0 | CV79: =(AH79*AV79) -> 7.78968 | CW79: =AI79 -> 0 | CX79: =AJ79 -> 0 | CY79: =(ROUND((((S79+ROUND((ROUND((((EU79*1.2))*AV79*1),2)*BS79),2))*AT79)/100),2)+ROUND(((ROUND((ROUND(((AE79-((EU79*1.2)))*AV79*1),2)*BS79),2)*AT79)/100),2)) -> 92.04 | CZ79: =(ROUND((((S79+ROUND((ROUND((((EU79*1.2))*AV79*1),2)*BS79),2))*AU79)/100),2)+ROUND(((ROUND((ROUND(((AE79-((EU79*1.2)))*AV79*1),2)*BS79),2)*AU79)/100),2)) -> 47.04 | DB79: 33 | DD79: *1 | DE79: *1,2 | DF79: *1,2 | DG79: *1,2 | DI79: *1,2 | DJ79: *1,2 | DN79: 0 | DO79: 0 | DP79: 1 | DQ79: 1 | DU79: 1013 | DV79: 1 ШТ. | DW79: 1 ШТ. | DX79: 1 | EE79: 57042958 | EF79: 40 | EG79: Монтаж оборудования | EH79: 0 | EJ79: 2 | EK79: 68 | EL79: ТСН-2001.4-10. Прокладка и монтаж сетей связи | EM79: ТСН-2001.4-10-1 | EO79: Поправка: Гл.12.Прил.8.п.8. 3_12.00.01.11.001 | EQ79: 0 | ER79: 119.3 | ES79: 12.35 | ET79: 28.71 | EU79: 3.16 | EV79: 78.24 | EW79: 6.2 | EX79: 0 | EY79: 0 | FQ79: 0 | FR79: 0 | FS79: 0 | FX79: 90 | FY79: 46 | GD79: 1 | GF79: 982292204 | GG79: 2 | GH79: 1 | GI79: 2 | GJ79: 0 | GK79: 0 | GL79: =ROUND(IF(AND(BH79=3,BI79=3,FS79<>0),P79,0),2) -> 0 | GM79: =ROUND(O79+X79+Y79,2)+GX79 -> 285.8 | GN79: =IF(OR(BI79=0,BI79=1),GM79-GX79,0) -> 0 | GO79: =IF(BI79=2,GM79-GX79,0) -> 285.8 | GP79: =IF(BI79=4,GM79-GX79,0) -> 0 | GR79: 0 | GS79: 3 | GT79: 0 | GV79: =ROUND((GT79),6) -> 0 | GW79: 1 | GX79: =ROUND(HC79*I79,2) -> 0 | HA79: 0 | HB79: 0 | HC79: =GV79*GW79 -> 0 | HS79: 0 | IK79: 0
A80: 17 | B80: 1 | C80: =ROW(SmtRes!A132) -> 132 | D80: =ROW(EtalonRes!A158) -> 158 | E80: 9 | F80: 4.10-34-5 | G80: Монтаж коммутатора служебной связи | H80: 1 ШТ. | I80: 1 | J80: 0 | K80: 1 | O80: =ROUND(CP80,2) -> 6303.65 | P80: =ROUND((ROUND((AC80*AW80*I80),2)*BC80),2) -> 181.55 | Q80: =(ROUND((ROUND((((ET80*1.2))*AV80*I80),2)*BB80),2)+ROUND((ROUND(((AE80-((EU80*1.2)))*AV80*I80),2)*BS80),2)) -> 582.89 | R80: =(ROUND((ROUND((((EU80*1.2))*AV80*I80),2)*BS80),2)+ROUND((ROUND(((AE80-((EU80*1.2)))*AV80*I80),2)*BS80),2)) -> 223.71 | S80: =ROUND((ROUND((AF80*AV80*I80),2)*BA80),2) -> 5539.21 | T80: =ROUND(CU80*I80,2) -> 0 | U80: =CV80*I80 -> 7.78968 | V80: =CW80*I80 -> 0 | W80: =ROUND(CX80*I80,2) -> 0 | X80: =(ROUND((((S80+ROUND((ROUND((((EU80*1.2))*AV80*I80),2)*BS80),2))*AT80)/100),2)+ROUND(((ROUND((ROUND(((AE80-((EU80*1.2)))*AV80*I80),2)*BS80),2)*AT80)/100),2)) -> 5186.63 | Y80: =(ROUND((((S80+ROUND((ROUND((((EU80*1.2))*AV80*I80),2)*BS80),2))*AU80)/100),2)+ROUND(((ROUND((ROUND(((AE80-((EU80*1.2)))*AV80*I80),2)*BS80),2)*AU80)/100),2)) -> 2650.94 | AA80: 55934357 | AB80: =ROUND((AC80+AD80+AF80),6) -> 140.69 | AC80: =ROUND(((ES80*1)),6) -> 12.35 | AD80: =ROUND(((((ET80*1.2))-((EU80*1.2)))+AE80),6) -> 34.452 | AE80: =ROUND(((EU80*1.2)),6) -> 3.792 | AF80: =ROUND(((EV80*1.2)),6) -> 93.888 | AG80: =ROUND((AP80),6) -> 0 | AH80: =((EW80*1.2)) -> 7.44 | AI80: =((EX80*1.2)) -> 0 | AJ80: =(AS80) -> 0 | AK80: 119.3 | AL80: 12.35 | AM80: 28.71 | AN80: 3.16 | AO80: 78.24 | AP80: 0 | AQ80: 6.2 | AR80: 0 | AS80: 0 | AT80: 90 | AU80: 46 | AV80: 1.047 | AW80: 1 | AZ80: 1 | BA80: 56.35 | BB80: 16.16 | BC80: 14.7 | BH80: 0 | BI80: 2 | BJ80: ТСН-2001.4 Доп. 80, Сб. 10, т. 34, поз. 5 | BM80: 68 | BN80: 0 | BO80: 4.10-34-5 | BP80: 1 | BQ80: 40 | BR80: 0 | BS80: 56.35 | BT80: 1 | BU80: 1 | BV80: 1 | BW80: 1 | BX80: 1 | BZ80: 90 | CA80: 46 | CE80: 1566 | CF80: 0 | CG80: 0 | CM80: 0 | CN80: Поправка: Гл.12.Прил.8.п.8. 3_12.00.01.11.001 Наименование: При наличии напряженных и стесненных условий производства работ (стесненность, сложность складирования и транспортной логистики и т.п.) для объектов, расположенных в пределах круговой магистральной системы улиц "Садовое кольцо" города Москвы | CO80: 0 | CP80: =(P80+Q80+S80) -> 6303.65 | CQ80: =ROUND((ROUND((AC80*AW80*1),2)*BC80),2) -> 181.55 | CR80: =(ROUND((ROUND((((ET80*1.2))*AV80*1),2)*BB80),2)+ROUND((ROUND(((AE80-((EU80*1.2)))*AV80*1),2)*BS80),2)) -> 582.89 | CS80: =(ROUND((ROUND((((EU80*1.2))*AV80*1),2)*BS80),2)+ROUND((ROUND(((AE80-((EU80*1.2)))*AV80*1),2)*BS80),2)) -> 223.71 | CT80: =ROUND((ROUND((AF80*AV80*1),2)*BA80),2) -> 5539.21 | CU80: =AG80 -> 0 | CV80: =(AH80*AV80) -> 7.78968 | CW80: =AI80 -> 0 | CX80: =AJ80 -> 0 | CY80: =(ROUND((((S80+ROUND((ROUND((((EU80*1.2))*AV80*1),2)*BS80),2))*AT80)/100),2)+ROUND(((ROUND((ROUND(((AE80-((EU80*1.2)))*AV80*1),2)*BS80),2)*AT80)/100),2)) -> 5186.63 | CZ80: =(ROUND((((S80+ROUND((ROUND((((EU80*1.2))*AV80*1),2)*BS80),2))*AU80)/100),2)+ROUND(((ROUND((ROUND(((AE80-((EU80*1.2)))*AV80*1),2)*BS80),2)*AU80)/100),2)) -> 2650.94 | DB80: 34 | DD80: *1 | DE80: *1,2 | DF80: *1,2 | DG80: *1,2 | DI80: *1,2 | DJ80: *1,2 | DN80: 0 | DO80: 0 | DP80: 1 | DQ80: 1 | DU80: 1013 | DV80: 1 ШТ. | DW80: 1 ШТ. | DX80: 1 | EE80: 57042958 | EF80: 40 | EG80: Монтаж оборудования | EH80: 0 | EJ80: 2 | EK80: 68 | EL80: ТСН-2001.4-10. Прокладка и монтаж сетей связи | EM80: ТСН-2001.4-10-1 | EO80: Поправка: Гл.12.Прил.8.п.8. 3_12.00.01.11.001 | EQ80: 0 | ER80: 119.3 | ES80: 12.35 | ET80: 28.71 | EU80: 3.16 | EV80: 78.24 | EW80: 6.2 | EX80: 0 | EY80: 0 | FQ80: 0 | FR80: 0 | FS80: 0 | FX80: 90 | FY80: 46 | GD80: 1 | GF80: 982292204 | GG80: 2 | GH80: 1 | GI80: 2 | GJ80: 0 | GK80: 0 | GL80: =ROUND(IF(AND(BH80=3,BI80=3,FS80<>0),P80,0),2) -> 0 | GM80: =ROUND(O80+X80+Y80,2)+GX80 -> 14141.22 | GN80: =IF(OR(BI80=0,BI80=1),GM80-GX80,0) -> 0 | GO80: =IF(BI80=2,GM80-GX80,0) -> 14141.22 | GP80: =IF(BI80=4,GM80-GX80,0) -> 0 | GR80: 0 | GS80: 3 | GT80: 0 | GV80: =ROUND((GT80),6) -> 0 | GW80: 1 | GX80: =ROUND(HC80*I80,2) -> 0 | HA80: 0 | HB80: 0 | HC80: =GV80*GW80 -> 0 | HS80: 0 | IK80: 0
A81: 18 | B81: 1 | C81: 127 | E81: 9,1 | F81: КА, п.1 | G81: Управляемый коммутатор уровня L3:48х10/100/1000BASE-T (RJ-45) PoE/PoE+; 4х10G BASE-X(SFP) MES2348P | H81: ШТ | I81: =I79*J81 -> 1 | J81: 1 | K81: 1 | O81: =ROUND(CP81,2) -> 50603.12 | P81: =ROUND((ROUND((AC81*AW81*I81),2)*BC81),2) -> 50603.12 | Q81: =(ROUND((ROUND(((ET81)*AV81*I81),2)*BB81),2)+ROUND((ROUND(((AE81-(EU81))*AV81*I81),2)*BS81),2)) -> 0 | R81: =(ROUND((ROUND(((EU81)*AV81*I81),2)*BS81),2)+ROUND((ROUND(((AE81-(EU81))*AV81*I81),2)*BS81),2)) -> 0 | S81: =ROUND((ROUND((AF81*AV81*I81),2)*BA81),2) -> 0 | T81: =ROUND(CU81*I81,2) -> 0 | U81: =CV81*I81 -> 0 | V81: =CW81*I81 -> 0 | W81: =ROUND(CX81*I81,2) -> 0 | X81: =(ROUND((((S81+ROUND((ROUND(((EU81)*AV81*I81),2)*BS81),2))*AT81)/100),2)+ROUND(((ROUND((ROUND(((AE81-(EU81))*AV81*I81),2)*BS81),2)*AT81)/100),2)) -> 0 | Y81: =(ROUND((((S81+ROUND((ROUND(((EU81)*AV81*I81),2)*BS81),2))*AU81)/100),2)+ROUND(((ROUND((ROUND(((AE81-(EU81))*AV81*I81),2)*BS81),2)*AU81)/100),2)) -> 0 | AA81: 55934355 | AB81: =ROUND((AC81+AD81+AF81),6) -> 50603.12 | AC81: =ROUND((ES81),6) -> 50603.12 | AD81: =ROUND((((ET81)-(EU81))+AE81),6) -> 0 | AE81: =ROUND((EU81),6) -> 0 | AF81: =ROUND((EV81),6) -> 0 | AG81: =ROUND((AP81),6) -> 0 | AH81: =(EW81) -> 0 | AI81: =(EX81) -> 0 | AJ81: =(AS81) -> 0 | AK81: 50603.12 | AL81: 50603.12 | AM81: 0 | AN81: 0 | AO81: 0 | AP81: 0 | AQ81: 0 | AR81: 0 | AS81: 0 | AT81: 0 | AU81: 0 | AV81: 1 | AW81: 1 | AZ81: 1 | BA81: 1 | BB81: 1 | BC81: 1 | BH81: 3 | BI81: 3 | BJ81: КА, п.1 | BM81: 400007 | BN81: 0 | BP81: 0 | BQ81: 214 | BR81: 0 | BS81: 1 | BT81: 1 | BU81: 1 | BV81: 1 | BW81: 1 | BX81: 1 | BZ81: 90 | CA81: 46 | CE81: 1566 | CF81: 0 | CG81: 0 | CM81: 0 | CN81: Поправка: Гл.12.Прил.8.п.8. 3_12.00.01.11.001_x000D_ Наименование: При наличии напряженных и стесненных условий производства работ (стесненность, сложность складирования и транспортной логистики и т.п.) для объектов, расположенных в пределах круговой магистральной системы улиц "Садовое кольцо" города Москвы | CO81: 0 | CP81: =(P81+Q81+S81) -> 50603.12 | CQ81: =ROUND((ROUND((AC81*AW81*1),2)*BC81),2) -> 50603.12 | CR81: =(ROUND((ROUND(((ET81)*AV81*1),2)*BB81),2)+ROUND((ROUND(((AE81-(EU81))*AV81*1),2)*BS81),2)) -> 0 | CS81: =(ROUND((ROUND(((EU81)*AV81*1),2)*BS81),2)+ROUND((ROUND(((AE81-(EU81))*AV81*1),2)*BS81),2)) -> 0 | CT81: =ROUND((ROUND((AF81*AV81*1),2)*BA81),2) -> 0 | CU81: =AG81 -> 0 | CV81: =(AH81*AV81) -> 0 | CW81: =AI81 -> 0 | CX81: =AJ81 -> 0 | CY81: =(ROUND((((S81+ROUND((ROUND(((EU81)*AV81*1),2)*BS81),2))*AT81)/100),2)+ROUND(((ROUND((ROUND(((AE81-(EU81))*AV81*1),2)*BS81),2)*AT81)/100),2)) -> 0 | CZ81: =(ROUND((((S81+ROUND((ROUND(((EU81)*AV81*1),2)*BS81),2))*AU81)/100),2)+ROUND(((ROUND((ROUND(((AE81-(EU81))*AV81*1),2)*BS81),2)*AU81)/100),2)) -> 0 | DN81: 0 | DO81: 0 | DP81: 1 | DQ81: 1 | DU81: 1013 | DV81: ШТ | DW81: ШТ | DX81: 1 | EE81: 57042890 | EF81: 214 | EG81: Оборудование, отсутствующие в СНБ | EH81: 0 | EJ81: 3 | EK81: 400007 | EL81: Оборудование, отсутствующие в СНБ | EM81: Оборуд. КА | EO81: Поправка: Гл.12.Прил.8.п.8. 3_12.00.01.11.001 | EQ81: 16 | ER81: 0 | ES81: 50603.12 | ET81: 0 | EU81: 0 | EV81: 0 | EW81: 0 | EX81: 0 | FQ81: 0 | FR81: =P81 -> 50603.12 | FS81: 0 | FX81: 90 | FY81: 46 | GA81: [448 348 / 1,22 / 7,57] + 3% Трансп + 1,2% Заг.скл | GD81: 1 | GF81: 176370574 | GG81: 2 | GH81: 4 | GI81: -2 | GJ81: 0 | GK81: 0 | GL81: =ROUND(IF(AND(BH81=3,BI81=3,FS81<>0),P81,0),2) -> 0 | GM81: =ROUND(O81+X81+Y81,2)+GX81 -> 50603.12 | GN81: =IF(OR(BI81=0,BI81=1),GM81-GX81,0) -> 0 | GO81: =IF(BI81=2,GM81-GX81,0) -> 0 | GP81: =IF(BI81=4,GM81-GX81,0) -> 0 | GR81: 1 | GS81: 2 | GT81: 0 | GV81: =ROUND((GT81),6) -> 0 | GW81: 1 | GX81: =ROUND(HC81*I81,2) -> 0 | HA81: 0 | HB81: 0 | HC81: =GV81*GW81 -> 0 | HE81: 3 | HF81: 1,2 | HM81: *1 | HS81: 0 | IK81: 0
A82: 18 | B82: 1 | C82: 132 | E82: 9,1 | F82: КА, п.1 | G82: Управляемый коммутатор уровня L3:48х10/100/1000BASE-T (RJ-45) PoE/PoE+; 4х10G BASE-X(SFP) MES2348P | H82: ШТ | I82: =I80*J82 -> 1 | J82: 1 | K82: 1 | O82: =ROUND(CP82,2) -> 383065.62 | P82: =ROUND((ROUND((AC82*AW82*I82),2)*BC82),2) -> 383065.62 | Q82: =(ROUND((ROUND(((ET82)*AV82*I82),2)*BB82),2)+ROUND((ROUND(((AE82-(EU82))*AV82*I82),2)*BS82),2)) -> 0 | R82: =(ROUND((ROUND(((EU82)*AV82*I82),2)*BS82),2)+ROUND((ROUND(((AE82-(EU82))*AV82*I82),2)*BS82),2)) -> 0 | S82: =ROUND((ROUND((AF82*AV82*I82),2)*BA82),2) -> 0 | T82: =ROUND(CU82*I82,2) -> 0 | U82: =CV82*I82 -> 0 | V82: =CW82*I82 -> 0 | W82: =ROUND(CX82*I82,2) -> 0 | X82: =(ROUND((((S82+ROUND((ROUND(((EU82)*AV82*I82),2)*BS82),2))*AT82)/100),2)+ROUND(((ROUND((ROUND(((AE82-(EU82))*AV82*I82),2)*BS82),2)*AT82)/100),2)) -> 0 | Y82: =(ROUND((((S82+ROUND((ROUND(((EU82)*AV82*I82),2)*BS82),2))*AU82)/100),2)+ROUND(((ROUND((ROUND(((AE82-(EU82))*AV82*I82),2)*BS82),2)*AU82)/100),2)) -> 0 | AA82: 55934357 | AB82: =ROUND((AC82+AD82+AF82),6) -> 50603.12 | AC82: =ROUND((ES82),6) -> 50603.12 | AD82: =ROUND((((ET82)-(EU82))+AE82),6) -> 0 | AE82: =ROUND((EU82),6) -> 0 | AF82: =ROUND((EV82),6) -> 0 | AG82: =ROUND((AP82),6) -> 0 | AH82: =(EW82) -> 0 | AI82: =(EX82) -> 0 | AJ82: =(AS82) -> 0 | AK82: 50603.12 | AL82: 50603.12 | AM82: 0 | AN82: 0 | AO82: 0 | AP82: 0 | AQ82: 0 | AR82: 0 | AS82: 0 | AT82: 0 | AU82: 0 | AV82: 1 | AW82: 1 | AZ82: 1 | BA82: 1 | BB82: 1 | BC82: 7.57 | BH82: 3 | BI82: 3 | BJ82: КА, п.1 | BM82: 400007 | BN82: 0 | BP82: 0 | BQ82: 214 | BR82: 0 | BS82: 1 | BT82: 1 | BU82: 1 | BV82: 1 | BW82: 1 | BX82: 1 | BZ82: 90 | CA82: 46 | CE82: 1566 | CF82: 0 | CG82: 0 | CM82: 0 | CN82: Поправка: Гл.12.Прил.8.п.8. 3_12.00.01.11.001_x000D_ Наименование: При наличии напряженных и стесненных условий производства работ (стесненность, сложность складирования и транспортной логистики и т.п.) для объектов, расположенных в пределах круговой магистральной системы улиц "Садовое кольцо" города Москвы | CO82: 0 | CP82: =(P82+Q82+S82) -> 383065.62 | CQ82: =ROUND((ROUND((AC82*AW82*1),2)*BC82),2) -> 383065.62 | CR82: =(ROUND((ROUND(((ET82)*AV82*1),2)*BB82),2)+ROUND((ROUND(((AE82-(EU82))*AV82*1),2)*BS82),2)) -> 0 | CS82: =(ROUND((ROUND(((EU82)*AV82*1),2)*BS82),2)+ROUND((ROUND(((AE82-(EU82))*AV82*1),2)*BS82),2)) -> 0 | CT82: =ROUND((ROUND((AF82*AV82*1),2)*BA82),2) -> 0 | CU82: =AG82 -> 0 | CV82: =(AH82*AV82) -> 0 | CW82: =AI82 -> 0 | CX82: =AJ82 -> 0 | CY82: =(ROUND((((S82+ROUND((ROUND(((EU82)*AV82*1),2)*BS82),2))*AT82)/100),2)+ROUND(((ROUND((ROUND(((AE82-(EU82))*AV82*1),2)*BS82),2)*AT82)/100),2)) -> 0 | CZ82: =(ROUND((((S82+ROUND((ROUND(((EU82)*AV82*1),2)*BS82),2))*AU82)/100),2)+ROUND(((ROUND((ROUND(((AE82-(EU82))*AV82*1),2)*BS82),2)*AU82)/100),2)) -> 0 | DN82: 0 | DO82: 0 | DP82: 1 | DQ82: 1 | DU82: 1013 | DV82: ШТ | DW82: ШТ | DX82: 1 | EE82: 57042890 | EF82: 214 | EG82: Оборудование, отсутствующие в СНБ | EH82: 0 | EJ82: 3 | EK82: 400007 | EL82: Оборудование, отсутствующие в СНБ | EM82: Оборуд. КА | EO82: Поправка: Гл.12.Прил.8.п.8. 3_12.00.01.11.001 | EQ82: 16 | ER82: 0 | ES82: 50603.12 | ET82: 0 | EU82: 0 | EV82: 0 | EW82: 0 | EX82: 0 | EZ82: 5 | FC82: 1 | FD82: 18 | FF82: 448348 | FQ82: 0 | FR82: =P82 -> 383065.62 | FS82: 0 | FX82: 90 | FY82: 46 | GA82: [448 348 / 1,22 / 7,57] + 3% Трансп + 1,2% Заг.скл | GD82: 1 | GF82: 176370574 | GG82: 2 | GH82: 3 | GI82: 5 | GJ82: 0 | GK82: 0 | GL82: =ROUND(IF(AND(BH82=3,BI82=3,FS82<>0),P82,0),2) -> 0 | GM82: =ROUND(O82+X82+Y82,2)+GX82 -> 383065.62 | GN82: =IF(OR(BI82=0,BI82=1),GM82-GX82,0) -> 0 | GO82: =IF(BI82=2,GM82-GX82,0) -> 0 | GP82: =IF(BI82=4,GM82-GX82,0) -> 0 | GR82: 1 | GS82: 1 | GT82: 0 | GV82: =ROUND((GT82),6) -> 0 | GW82: 1 | GX82: =ROUND(HC82*I82,2) -> 0 | HA82: 0 | HB82: 0 | HC82: =GV82*GW82 -> 0 | HE82: 3 | HF82: 1,2 | HM82: *1 | HS82: 0 | IK82: 0
A83: 17 | B83: 1 | C83: =ROW(SmtRes!A133) -> 133 | D83: =ROW(EtalonRes!A159) -> 159 | F83: 4.10-35-2 | G83: Электрическая проверка и настройка коммутатора всех назначений, кроме междугородного | H83: 1 рабочее место | I83: 1 | J83: 0 | K83: 1 | O83: =ROUND(CP83,2) -> 420.17 | P83: =ROUND((ROUND((AC83*AW83*I83),2)*BC83),2) -> 0 | Q83: =(ROUND((ROUND((((ET83*1.2))*AV83*I83),2)*BB83),2)+ROUND((ROUND(((AE83-((EU83*1.2)))*AV83*I83),2)*BS83),2)) -> 0 | R83: =(ROUND((ROUND((((EU83*1.2))*AV83*I83),2)*BS83),2)+ROUND((ROUND(((AE83-((EU83*1.2)))*AV83*I83),2)*BS83),2)) -> 0 | S83: =ROUND((ROUND((AF83*AV83*I83),2)*BA83),2) -> 420.17 | T83: =ROUND(CU83*I83,2) -> 0 | U83: =CV83*I83 -> 28.8972 | V83: =CW83*I83 -> 0 | W83: =ROUND(CX83*I83,2) -> 0 | X83: =(ROUND((((S83+ROUND((ROUND((((EU83*1.2))*AV83*I83),2)*BS83),2))*AT83)/100),2)+ROUND(((ROUND((ROUND(((AE83-((EU83*1.2)))*AV83*I83),2)*BS83),2)*AT83)/100),2)) -> 378.15 | Y83: =(ROUND((((S83+ROUND((ROUND((((EU83*1.2))*AV83*I83),2)*BS83),2))*AU83)/100),2)+ROUND(((ROUND((ROUND(((AE83-((EU83*1.2)))*AV83*I83),2)*BS83),2)*AU83)/100),2)) -> 193.28 | AA83: -1 | AB83: =ROUND((AC83+AD83+AF83),6) -> 401.304 | AC83: =ROUND(((ES83*1)),6) -> 0 | AD83: =ROUND(((((ET83*1.2))-((EU83*1.2)))+AE83),6) -> 0 | AE83: =ROUND(((EU83*1.2)),6) -> 0 | AF83: =ROUND(((EV83*1.2)),6) -> 401.304 | AG83: =ROUND((AP83),6) -> 0 | AH83: =((EW83*1.2)) -> 27.6 | AI83: =((EX83*1.2)) -> 0 | AJ83: =(AS83) -> 0 | AK83: 334.42 | AL83: 0 | AM83: 0 | AN83: 0 | AO83: 334.42 | AP83: 0 | AQ83: 23 | AR83: 0 | AS83: 0 | AT83: 90 | AU83: 46 | AV83: 1.047 | AW83: 1 | AZ83: 1 | BA83: 1 | BB83: 1 | BC83: 1 | BH83: 0 | BI83: 2 | BJ83: ТСН-2001.4 Доп. 67, Сб. 10, т. 35, поз. 2 | BM83: 192 | BN83: 0 | BO83: 4.10-35-2 | BP83: 1 | BQ83: 40 | BR83: 0 | BS83: 1 | BT83: 1 | BU83: 1 | BV83: 1 | BW83: 1 | BX83: 1 | BZ83: 90 | CA83: 46 | CE83: 1566 | CF83: 0 | CG83: 0 | CM83: 0 | CN83: Поправка: Гл.12.Прил.8.п.8. 3_12.00.01.11.001 Наименование: При наличии напряженных и стесненных условий производства работ (стесненность, сложность складирования и транспортной логистики и т.п.) для объектов, расположенных в пределах круговой магистральной системы улиц "Садовое кольцо" города Москвы | CO83: 0 | CP83: =(P83+Q83+S83) -> 420.17 | CQ83: =ROUND((ROUND((AC83*AW83*1),2)*BC83),2) -> 0 | CR83: =(ROUND((ROUND((((ET83*1.2))*AV83*1),2)*BB83),2)+ROUND((ROUND(((AE83-((EU83*1.2)))*AV83*1),2)*BS83),2)) -> 0 | CS83: =(ROUND((ROUND((((EU83*1.2))*AV83*1),2)*BS83),2)+ROUND((ROUND(((AE83-((EU83*1.2)))*AV83*1),2)*BS83),2)) -> 0 | CT83: =ROUND((ROUND((AF83*AV83*1),2)*BA83),2) -> 420.17 | CU83: =AG83 -> 0 | CV83: =(AH83*AV83) -> 28.8972 | CW83: =AI83 -> 0 | CX83: =AJ83 -> 0 | CY83: =(ROUND((((S83+ROUND((ROUND((((EU83*1.2))*AV83*1),2)*BS83),2))*AT83)/100),2)+ROUND(((ROUND((ROUND(((AE83-((EU83*1.2)))*AV83*1),2)*BS83),2)*AT83)/100),2)) -> 378.15 | CZ83: =(ROUND((((S83+ROUND((ROUND((((EU83*1.2))*AV83*1),2)*BS83),2))*AU83)/100),2)+ROUND(((ROUND((ROUND(((AE83-((EU83*1.2)))*AV83*1),2)*BS83),2)*AU83)/100),2)) -> 193.28 | DB83: 35 | DD83: *1 | DE83: *1,2 | DF83: *1,2 | DG83: *1,2 | DI83: *1,2 | DJ83: *1,2 | DN83: 0 | DO83: 0 | DP83: 1 | DQ83: 1 | DU83: 1013 | DV83: 1 рабочее место | DW83: 1 рабочее место | DX83: 1 | EE83: 57043089 | EF83: 40 | EG83: Монтаж оборудования | EH83: 0 | EJ83: 2 | EK83: 192 | EL83: ТСН-2001.4-10. Прокладка и монтаж сетей связи | EM83: ТСН-2001.4-10-5 | EO83: Поправка: Гл.12.Прил.8.п.8. 3_12.00.01.11.001 | EQ83: 1024 | ER83: 334.42 | ES83: 0 | ET83: 0 | EU83: 0 | EV83: 334.42 | EW83: 23 | EX83: 0 | EY83: 0 | FQ83: 0 | FR83: 0 | FS83: 0 | FX83: 90 | FY83: 46 | GD83: 1 | GF83: 1839118886 | GG83: 2 | GH83: 1 | GI83: 2 | GJ83: 0 | GK83: 0 | GL83: =ROUND(IF(AND(BH83=3,BI83=3,FS83<>0),P83,0),2) -> 0 | GM83: =ROUND(O83+X83+Y83,2)+GX83 -> 991.6 | GN83: =IF(OR(BI83=0,BI83=1),GM83-GX83,0) -> 0 | GO83: =IF(BI83=2,GM83-GX83,0) -> 991.6 | GP83: =IF(BI83=4,GM83-GX83,0) -> 0 | GR83: 0 | GS83: 3 | GT83: 0 | GV83: =ROUND((GT83),6) -> 0 | GW83: 1 | GX83: =ROUND(HC83*I83,2) -> 0 | HA83: 0 | HB83: 0 | HC83: =GV83*GW83 -> 0 | HS83: 0 | IK83: 0
A84: 17 | B84: 1 | C84: =ROW(SmtRes!A134) -> 134 | D84: =ROW(EtalonRes!A160) -> 160 | F84: 4.10-35-2 | G84: Электрическая проверка и настройка коммутатора всех назначений, кроме междугородного | H84: 1 рабочее место | I84: 1 | J84: 0 | K84: 1 | O84: =ROUND(CP84,2) -> 23676.58 | P84: =ROUND((ROUND((AC84*AW84*I84),2)*BC84),2) -> 0 | Q84: =(ROUND((ROUND((((ET84*1.2))*AV84*I84),2)*BB84),2)+ROUND((ROUND(((AE84-((EU84*1.2)))*AV84*I84),2)*BS84),2)) -> 0 | R84: =(ROUND((ROUND((((EU84*1.2))*AV84*I84),2)*BS84),2)+ROUND((ROUND(((AE84-((EU84*1.2)))*AV84*I84),2)*BS84),2)) -> 0 | S84: =ROUND((ROUND((AF84*AV84*I84),2)*BA84),2) -> 23676.58 | T84: =ROUND(CU84*I84,2) -> 0 | U84: =CV84*I84 -> 28.8972 | V84: =CW84*I84 -> 0 | W84: =ROUND(CX84*I84,2) -> 0 | X84: =(ROUND((((S84+ROUND((ROUND((((EU84*1.2))*AV84*I84),2)*BS84),2))*AT84)/100),2)+ROUND(((ROUND((ROUND(((AE84-((EU84*1.2)))*AV84*I84),2)*BS84),2)*AT84)/100),2)) -> 21308.92 | Y84: =(ROUND((((S84+ROUND((ROUND((((EU84*1.2))*AV84*I84),2)*BS84),2))*AU84)/100),2)+ROUND(((ROUND((ROUND(((AE84-((EU84*1.2)))*AV84*I84),2)*BS84),2)*AU84)/100),2)) -> 10891.23 | AA84: -1 | AB84: =ROUND((AC84+AD84+AF84),6) -> 401.304 | AC84: =ROUND(((ES84*1)),6) -> 0 | AD84: =ROUND(((((ET84*1.2))-((EU84*1.2)))+AE84),6) -> 0 | AE84: =ROUND(((EU84*1.2)),6) -> 0 | AF84: =ROUND(((EV84*1.2)),6) -> 401.304 | AG84: =ROUND((AP84),6) -> 0 | AH84: =((EW84*1.2)) -> 27.6 | AI84: =((EX84*1.2)) -> 0 | AJ84: =(AS84) -> 0 | AK84: 334.42 | AL84: 0 | AM84: 0 | AN84: 0 | AO84: 334.42 | AP84: 0 | AQ84: 23 | AR84: 0 | AS84: 0 | AT84: 90 | AU84: 46 | AV84: 1.047 | AW84: 1 | AZ84: 1 | BA84: 56.35 | BB84: 1 | BC84: 1 | BH84: 0 | BI84: 2 | BJ84: ТСН-2001.4 Доп. 67, Сб. 10, т. 35, поз. 2 | BM84: 192 | BN84: 0 | BO84: 4.10-35-2 | BP84: 1 | BQ84: 40 | BR84: 0 | BS84: 56.35 | BT84: 1 | BU84: 1 | BV84: 1 | BW84: 1 | BX84: 1 | BZ84: 90 | CA84: 46 | CE84: 1566 | CF84: 0 | CG84: 0 | CM84: 0 | CN84: Поправка: Гл.12.Прил.8.п.8. 3_12.00.01.11.001 Наименование: При наличии напряженных и стесненных условий производства работ (стесненность, сложность складирования и транспортной логистики и т.п.) для объектов, расположенных в пределах круговой магистральной системы улиц "Садовое кольцо" города Москвы | CO84: 0 | CP84: =(P84+Q84+S84) -> 23676.58 | CQ84: =ROUND((ROUND((AC84*AW84*1),2)*BC84),2) -> 0 | CR84: =(ROUND((ROUND((((ET84*1.2))*AV84*1),2)*BB84),2)+ROUND((ROUND(((AE84-((EU84*1.2)))*AV84*1),2)*BS84),2)) -> 0 | CS84: =(ROUND((ROUND((((EU84*1.2))*AV84*1),2)*BS84),2)+ROUND((ROUND(((AE84-((EU84*1.2)))*AV84*1),2)*BS84),2)) -> 0 | CT84: =ROUND((ROUND((AF84*AV84*1),2)*BA84),2) -> 23676.58 | CU84: =AG84 -> 0 | CV84: =(AH84*AV84) -> 28.8972 | CW84: =AI84 -> 0 | CX84: =AJ84 -> 0 | CY84: =(ROUND((((S84+ROUND((ROUND((((EU84*1.2))*AV84*1),2)*BS84),2))*AT84)/100),2)+ROUND(((ROUND((ROUND(((AE84-((EU84*1.2)))*AV84*1),2)*BS84),2)*AT84)/100),2)) -> 21308.92 | CZ84: =(ROUND((((S84+ROUND((ROUND((((EU84*1.2))*AV84*1),2)*BS84),2))*AU84)/100),2)+ROUND(((ROUND((ROUND(((AE84-((EU84*1.2)))*AV84*1),2)*BS84),2)*AU84)/100),2)) -> 10891.23 | DB84: 36 | DD84: *1 | DE84: *1,2 | DF84: *1,2 | DG84: *1,2 | DI84: *1,2 | DJ84: *1,2 | DN84: 0 | DO84: 0 | DP84: 1 | DQ84: 1 | DU84: 1013 | DV84: 1 рабочее место | DW84: 1 рабочее место | DX84: 1 | EE84: 57043089 | EF84: 40 | EG84: Монтаж оборудования | EH84: 0 | EJ84: 2 | EK84: 192 | EL84: ТСН-2001.4-10. Прокладка и монтаж сетей связи | EM84: ТСН-2001.4-10-5 | EO84: Поправка: Гл.12.Прил.8.п.8. 3_12.00.01.11.001 | EQ84: 1024 | ER84: 334.42 | ES84: 0 | ET84: 0 | EU84: 0 | EV84: 334.42 | EW84: 23 | EX84: 0 | EY84: 0 | FQ84: 0 | FR84: 0 | FS84: 0 | FX84: 90 | FY84: 46 | GD84: 1 | GF84: 1839118886 | GG84: 2 | GH84: 1 | GI84: 2 | GJ84: 0 | GK84: 0 | GL84: =ROUND(IF(AND(BH84=3,BI84=3,FS84<>0),P84,0),2) -> 0 | GM84: =ROUND(O84+X84+Y84,2)+GX84 -> 55876.73 | GN84: =IF(OR(BI84=0,BI84=1),GM84-GX84,0) -> 0 | GO84: =IF(BI84=2,GM84-GX84,0) -> 55876.73 | GP84: =IF(BI84=4,GM84-GX84,0) -> 0 | GR84: 0 | GS84: 3 | GT84: 0 | GV84: =ROUND((GT84),6) -> 0 | GW84: 1 | GX84: =ROUND(HC84*I84,2) -> 0 | HA84: 0 | HB84: 0 | HC84: =GV84*GW84 -> 0 | HS84: 0 | IK84: 0
A85: 17 | B85: 1 | C85: =ROW(SmtRes!A139) -> 139 | D85: =ROW(EtalonRes!A167) -> 167 | E85: 10 | F85: 4.10-72-14 | G85: Монтаж устройства цифровой регистрации | H85: 1 устройство | I85: 1 | J85: 0 | K85: 1 | O85: =ROUND(CP85,2) -> 120.61 | P85: =ROUND((ROUND((AC85*AW85*I85),2)*BC85),2) -> 1.1 | Q85: =(ROUND((ROUND((((ET85*1.2))*AV85*I85),2)*BB85),2)+ROUND((ROUND(((AE85-((EU85*1.2)))*AV85*I85),2)*BS85),2)) -> 0 | R85: =(ROUND((ROUND((((EU85*1.2))*AV85*I85),2)*BS85),2)+ROUND((ROUND(((AE85-((EU85*1.2)))*AV85*I85),2)*BS85),2)) -> 0 | S85: =ROUND((ROUND((AF85*AV85*I85),2)*BA85),2) -> 119.51 | T85: =ROUND(CU85*I85,2) -> 0 | U85: =CV85*I85 -> 10.0512 | V85: =CW85*I85 -> 0 | W85: =ROUND(CX85*I85,2) -> 0 | X85: =(ROUND((((S85+ROUND((ROUND((((EU85*1.2))*AV85*I85),2)*BS85),2))*AT85)/100),2)+ROUND(((ROUND((ROUND(((AE85-((EU85*1.2)))*AV85*I85),2)*BS85),2)*AT85)/100),2)) -> 113.53 | Y85: =(ROUND((((S85+ROUND((ROUND((((EU85*1.2))*AV85*I85),2)*BS85),2))*AU85)/100),2)+ROUND(((ROUND((ROUND(((AE85-((EU85*1.2)))*AV85*I85),2)*BS85),2)*AU85)/100),2)) -> 63.34 | AA85: 55934355 | AB85: =ROUND((AC85+AD85+AF85),6) -> 115.244 | AC85: =ROUND(((ES85*1)),6) -> 1.1 | AD85: =ROUND(((((ET85*1.2))-((EU85*1.2)))+AE85),6) -> 0 | AE85: =ROUND(((EU85*1.2)),6) -> 0 | AF85: =ROUND(((EV85*1.2)),6) -> 114.144 | AG85: =ROUND((AP85),6) -> 0 | AH85: =((EW85*1.2)) -> 9.6 | AI85: =((EX85*1.2)) -> 0 | AJ85: =(AS85) -> 0 | AK85: 96.22 | AL85: 1.1 | AM85: 0 | AN85: 0 | AO85: 95.12 | AP85: 0 | AQ85: 8 | AR85: 0 | AS85: 0 | AT85: 95 | AU85: 53 | AV85: 1.047 | AW85: 1 | AZ85: 1 | BA85: 1 | BB85: 1 | BC85: 1 | BH85: 0 | BI85: 2 | BJ85: ТСН-2001.4 Доп. 67, Сб. 10, т. 72, поз. 14 | BM85: 69 | BN85: 0 | BO85: 4.10-72-14 | BP85: 1 | BQ85: 40 | BR85: 0 | BS85: 1 | BT85: 1 | BU85: 1 | BV85: 1 | BW85: 1 | BX85: 1 | BZ85: 95 | CA85: 53 | CE85: 1566 | CF85: 0 | CG85: 0 | CM85: 0 | CN85: Поправка: Гл.12.Прил.8.п.8. 3_12.00.01.11.001 Наименование: При наличии напряженных и стесненных условий производства работ (стесненность, сложность складирования и транспортной логистики и т.п.) для объектов, расположенных в пределах круговой магистральной системы улиц "Садовое кольцо" города Москвы | CO85: 0 | CP85: =(P85+Q85+S85) -> 120.61 | CQ85: =ROUND((ROUND((AC85*AW85*1),2)*BC85),2) -> 1.1 | CR85: =(ROUND((ROUND((((ET85*1.2))*AV85*1),2)*BB85),2)+ROUND((ROUND(((AE85-((EU85*1.2)))*AV85*1),2)*BS85),2)) -> 0 | CS85: =(ROUND((ROUND((((EU85*1.2))*AV85*1),2)*BS85),2)+ROUND((ROUND(((AE85-((EU85*1.2)))*AV85*1),2)*BS85),2)) -> 0 | CT85: =ROUND((ROUND((AF85*AV85*1),2)*BA85),2) -> 119.51 | CU85: =AG85 -> 0 | CV85: =(AH85*AV85) -> 10.0512 | CW85: =AI85 -> 0 | CX85: =AJ85 -> 0 | CY85: =(ROUND((((S85+ROUND((ROUND((((EU85*1.2))*AV85*1),2)*BS85),2))*AT85)/100),2)+ROUND(((ROUND((ROUND(((AE85-((EU85*1.2)))*AV85*1),2)*BS85),2)*AT85)/100),2)) -> 113.53 | CZ85: =(ROUND((((S85+ROUND((ROUND((((EU85*1.2))*AV85*1),2)*BS85),2))*AU85)/100),2)+ROUND(((ROUND((ROUND(((AE85-((EU85*1.2)))*AV85*1),2)*BS85),2)*AU85)/100),2)) -> 63.34 | DB85: 37 | DD85: *1 | DE85: *1,2 | DF85: *1,2 | DG85: *1,2 | DI85: *1,2 | DJ85: *1,2 | DN85: 0 | DO85: 0 | DP85: 1 | DQ85: 1 | DU85: 1013 | DV85: 1 устройство | DW85: 1 устройство | DX85: 1 | EE85: 57042959 | EF85: 40 | EG85: Монтаж оборудования | EH85: 0 | EJ85: 2 | EK85: 69 | EL85: ТСН-2001.4-10. Монтаж радиотелевизионного и электронного оборудования | EM85: ТСН-2001.4-10-2 | EO85: Поправка: Гл.12.Прил.8.п.8. 3_12.00.01.11.001 | EQ85: 0 | ER85: 96.22 | ES85: 1.1 | ET85: 0 | EU85: 0 | EV85: 95.12 | EW85: 8 | EX85: 0 | EY85: 0 | FQ85: 0 | FR85: 0 | FS85: 0 | FX85: 95 | FY85: 53 | GD85: 1 | GF85: -1819990670 | GG85: 2 | GH85: 1 | GI85: 2 | GJ85: 0 | GK85: 0 | GL85: =ROUND(IF(AND(BH85=3,BI85=3,FS85<>0),P85,0),2) -> 0 | GM85: =ROUND(O85+X85+Y85,2)+GX85 -> 297.48 | GN85: =IF(OR(BI85=0,BI85=1),GM85-GX85,0) -> 0 | GO85: =IF(BI85=2,GM85-GX85,0) -> 297.48 | GP85: =IF(BI85=4,GM85-GX85,0) -> 0 | GR85: 0 | GS85: 3 | GT85: 0 | GV85: =ROUND((GT85),6) -> 0 | GW85: 1 | GX85: =ROUND(HC85*I85,2) -> 0 | HA85: 0 | HB85: 0 | HC85: =GV85*GW85 -> 0 | HS85: 0 | IK85: 0
A86: 17 | B86: 1 | C86: =ROW(SmtRes!A144) -> 144 | D86: =ROW(EtalonRes!A174) -> 174 | E86: 10 | F86: 4.10-72-14 | G86: Монтаж устройства цифровой регистрации | H86: 1 устройство | I86: 1 | J86: 0 | K86: 1 | O86: =ROUND(CP86,2) -> 6752.64 | P86: =ROUND((ROUND((AC86*AW86*I86),2)*BC86),2) -> 18.25 | Q86: =(ROUND((ROUND((((ET86*1.2))*AV86*I86),2)*BB86),2)+ROUND((ROUND(((AE86-((EU86*1.2)))*AV86*I86),2)*BS86),2)) -> 0 | R86: =(ROUND((ROUND((((EU86*1.2))*AV86*I86),2)*BS86),2)+ROUND((ROUND(((AE86-((EU86*1.2)))*AV86*I86),2)*BS86),2)) -> 0 | S86: =ROUND((ROUND((AF86*AV86*I86),2)*BA86),2) -> 6734.39 | T86: =ROUND(CU86*I86,2) -> 0 | U86: =CV86*I86 -> 10.0512 | V86: =CW86*I86 -> 0 | W86: =ROUND(CX86*I86,2) -> 0 | X86: =(ROUND((((S86+ROUND((ROUND((((EU86*1.2))*AV86*I86),2)*BS86),2))*AT86)/100),2)+ROUND(((ROUND((ROUND(((AE86-((EU86*1.2)))*AV86*I86),2)*BS86),2)*AT86)/100),2)) -> 6397.67 | Y86: =(ROUND((((S86+ROUND((ROUND((((EU86*1.2))*AV86*I86),2)*BS86),2))*AU86)/100),2)+ROUND(((ROUND((ROUND(((AE86-((EU86*1.2)))*AV86*I86),2)*BS86),2)*AU86)/100),2)) -> 3569.23 | AA86: 55934357 | AB86: =ROUND((AC86+AD86+AF86),6) -> 115.244 | AC86: =ROUND(((ES86*1)),6) -> 1.1 | AD86: =ROUND(((((ET86*1.2))-((EU86*1.2)))+AE86),6) -> 0 | AE86: =ROUND(((EU86*1.2)),6) -> 0 | AF86: =ROUND(((EV86*1.2)),6) -> 114.144 | AG86: =ROUND((AP86),6) -> 0 | AH86: =((EW86*1.2)) -> 9.6 | AI86: =((EX86*1.2)) -> 0 | AJ86: =(AS86) -> 0 | AK86: 96.22 | AL86: 1.1 | AM86: 0 | AN86: 0 | AO86: 95.12 | AP86: 0 | AQ86: 8 | AR86: 0 | AS86: 0 | AT86: 95 | AU86: 53 | AV86: 1.047 | AW86: 1 | AZ86: 1 | BA86: 56.35 | BB86: 1 | BC86: 16.59 | BH86: 0 | BI86: 2 | BJ86: ТСН-2001.4 Доп. 67, Сб. 10, т. 72, поз. 14 | BM86: 69 | BN86: 0 | BO86: 4.10-72-14 | BP86: 1 | BQ86: 40 | BR86: 0 | BS86: 56.35 | BT86: 1 | BU86: 1 | BV86: 1 | BW86: 1 | BX86: 1 | BZ86: 95 | CA86: 53 | CE86: 1566 | CF86: 0 | CG86: 0 | CM86: 0 | CN86: Поправка: Гл.12.Прил.8.п.8. 3_12.00.01.11.001 Наименование: При наличии напряженных и стесненных условий производства работ (стесненность, сложность складирования и транспортной логистики и т.п.) для объектов, расположенных в пределах круговой магистральной системы улиц "Садовое кольцо" города Москвы | CO86: 0 | CP86: =(P86+Q86+S86) -> 6752.64 | CQ86: =ROUND((ROUND((AC86*AW86*1),2)*BC86),2) -> 18.25 | CR86: =(ROUND((ROUND((((ET86*1.2))*AV86*1),2)*BB86),2)+ROUND((ROUND(((AE86-((EU86*1.2)))*AV86*1),2)*BS86),2)) -> 0 | CS86: =(ROUND((ROUND((((EU86*1.2))*AV86*1),2)*BS86),2)+ROUND((ROUND(((AE86-((EU86*1.2)))*AV86*1),2)*BS86),2)) -> 0 | CT86: =ROUND((ROUND((AF86*AV86*1),2)*BA86),2) -> 6734.39 | CU86: =AG86 -> 0 | CV86: =(AH86*AV86) -> 10.0512 | CW86: =AI86 -> 0 | CX86: =AJ86 -> 0 | CY86: =(ROUND((((S86+ROUND((ROUND((((EU86*1.2))*AV86*1),2)*BS86),2))*AT86)/100),2)+ROUND(((ROUND((ROUND(((AE86-((EU86*1.2)))*AV86*1),2)*BS86),2)*AT86)/100),2)) -> 6397.67 | CZ86: =(ROUND((((S86+ROUND((ROUND((((EU86*1.2))*AV86*1),2)*BS86),2))*AU86)/100),2)+ROUND(((ROUND((ROUND(((AE86-((EU86*1.2)))*AV86*1),2)*BS86),2)*AU86)/100),2)) -> 3569.23 | DB86: 38 | DD86: *1 | DE86: *1,2 | DF86: *1,2 | DG86: *1,2 | DI86: *1,2 | DJ86: *1,2 | DN86: 0 | DO86: 0 | DP86: 1 | DQ86: 1 | DU86: 1013 | DV86: 1 устройство | DW86: 1 устройство | DX86: 1 | EE86: 57042959 | EF86: 40 | EG86: Монтаж оборудования | EH86: 0 | EJ86: 2 | EK86: 69 | EL86: ТСН-2001.4-10. Монтаж радиотелевизионного и электронного оборудования | EM86: ТСН-2001.4-10-2 | EO86: Поправка: Гл.12.Прил.8.п.8. 3_12.00.01.11.001 | EQ86: 0 | ER86: 96.22 | ES86: 1.1 | ET86: 0 | EU86: 0 | EV86: 95.12 | EW86: 8 | EX86: 0 | EY86: 0 | FQ86: 0 | FR86: 0 | FS86: 0 | FX86: 95 | FY86: 53 | GD86: 1 | GF86: -1819990670 | GG86: 2 | GH86: 1 | GI86: 2 | GJ86: 0 | GK86: 0 | GL86: =ROUND(IF(AND(BH86=3,BI86=3,FS86<>0),P86,0),2) -> 0 | GM86: =ROUND(O86+X86+Y86,2)+GX86 -> 16719.54 | GN86: =IF(OR(BI86=0,BI86=1),GM86-GX86,0) -> 0 | GO86: =IF(BI86=2,GM86-GX86,0) -> 16719.54 | GP86: =IF(BI86=4,GM86-GX86,0) -> 0 | GR86: 0 | GS86: 3 | GT86: 0 | GV86: =ROUND((GT86),6) -> 0 | GW86: 1 | GX86: =ROUND(HC86*I86,2) -> 0 | HA86: 0 | HB86: 0 | HC86: =GV86*GW86 -> 0 | HS86: 0 | IK86: 0
A87: 17 | B87: 1 | E87: 11 | F87: КА, п.2 | G87: SecurOS-IVS-NVRIndustrial( H.712)-AO.ASC7SP4HPX-99/1000- 180000R6-W Специализированный 99 канальный сервер объектового контроля / суммарный входящий видеопоток до 1000 Мбит/с / MJPEG, H.264, H.265 / удаленная работа с системой через LAN 4x1Gbit Ethernet / накопители под ОС SSD 480GB х 2 (Raid 1) / хранение видеоархива в течение 31 суток, поток ~ 5Мбит/с на канал, постоянная запись / отказоустойчивый дисковый массив объемом 180Тб HDD RAID6 в базовой комплектации/аппаратный RAID контроллер SAS/SATA, горячая замена дисков, вентиляторов и резервирование блоков питания, система самодиагностики / установка в 19"" стойку (рельсы/ручки в комплекте, высота не более 4U) / 220В, 50Гц / размещение в телекоммуникационных шкафах (стойках) глубиной не менее 1000мм / Максимальная потребляемая мощность 600Вт; USB-Ключ аппаратной защиты ""Guardant"" - 1шт / Предустановленная операционная система / В комплекте поставки: клавиатура + оптический манипулятор (""мышь""). Комплект предустановленного программного обеспечения, в составе: - SecurOS H.712 Premium - Ядро видеосервера версия 11.x - 1экз.; - SecurOS H.712 Premium - Подключение видеоканала - 95экз.; - SecurOS H.712 Premium - Трансляции видеоканала в ЕЦХД - 95экз.; - SecurOS H.712 Premium - Пользователь системы - 5экз.; - SecurOS H.712 Premium - Модуль интеграции ПО "FireSec" от компании ""RUBEZH" 1экз.;" | H87: ШТ | I87: 1 | J87: 0 | K87: 1 | O87: =ROUND(CP87,2) -> 465031.79 | P87: =ROUND((ROUND((AC87*AW87*I87),2)*BC87),2) -> 465031.79 | Q87: =(ROUND((ROUND(((ET87)*AV87*I87),2)*BB87),2)+ROUND((ROUND(((AE87-(EU87))*AV87*I87),2)*BS87),2)) -> 0 | R87: =(ROUND((ROUND(((EU87)*AV87*I87),2)*BS87),2)+ROUND((ROUND(((AE87-(EU87))*AV87*I87),2)*BS87),2)) -> 0 | S87: =ROUND((ROUND((AF87*AV87*I87),2)*BA87),2) -> 0 | T87: =ROUND(CU87*I87,2) -> 0 | U87: =CV87*I87 -> 0 | V87: =CW87*I87 -> 0 | W87: =ROUND(CX87*I87,2) -> 0 | X87: =(ROUND((((S87+ROUND((ROUND(((EU87)*AV87*I87),2)*BS87),2))*AT87)/100),2)+ROUND(((ROUND((ROUND(((AE87-(EU87))*AV87*I87),2)*BS87),2)*AT87)/100),2)) -> 0 | Y87: =(ROUND((((S87+ROUND((ROUND(((EU87)*AV87*I87),2)*BS87),2))*AU87)/100),2)+ROUND(((ROUND((ROUND(((AE87-(EU87))*AV87*I87),2)*BS87),2)*AU87)/100),2)) -> 0 | AA87: 55934355 | AB87: =ROUND((AC87+AD87+AF87),6) -> 465031.79 | AC87: =ROUND((ES87),6) -> 465031.79 | AD87: =ROUND((((ET87)-(EU87))+AE87),6) -> 0 | AE87: =ROUND((EU87),6) -> 0 | AF87: =ROUND((EV87),6) -> 0 | AG87: =ROUND((AP87),6) -> 0 | AH87: =(EW87) -> 0 | AI87: =(EX87) -> 0 | AJ87: =(AS87) -> 0 | AK87: 465031.79 | AL87: 465031.79 | AM87: 0 | AN87: 0 | AO87: 0 | AP87: 0 | AQ87: 0 | AR87: 0 | AS87: 0 | AT87: 0 | AU87: 0 | AV87: 1 | AW87: 1 | AZ87: 1 | BA87: 1 | BB87: 1 | BC87: 1 | BH87: 3 | BI87: 3 | BJ87: КА, п.2 | BM87: 400007 | BN87: 0 | BP87: 0 | BQ87: 214 | BR87: 0 | BS87: 1 | BT87: 1 | BU87: 1 | BV87: 1 | BW87: 1 | BX87: 1 | BZ87: 0 | CA87: 0 | CE87: 1566 | CF87: 0 | CG87: 0 | CM87: 0 | CO87: 0 | CP87: =(P87+Q87+S87) -> 465031.79 | CQ87: =ROUND((ROUND((AC87*AW87*1),2)*BC87),2) -> 465031.79 | CR87: =(ROUND((ROUND(((ET87)*AV87*1),2)*BB87),2)+ROUND((ROUND(((AE87-(EU87))*AV87*1),2)*BS87),2)) -> 0 | CS87: =(ROUND((ROUND(((EU87)*AV87*1),2)*BS87),2)+ROUND((ROUND(((AE87-(EU87))*AV87*1),2)*BS87),2)) -> 0 | CT87: =ROUND((ROUND((AF87*AV87*1),2)*BA87),2) -> 0 | CU87: =AG87 -> 0 | CV87: =(AH87*AV87) -> 0 | CW87: =AI87 -> 0 | CX87: =AJ87 -> 0 | CY87: =(ROUND((((S87+ROUND((ROUND(((EU87)*AV87*1),2)*BS87),2))*AT87)/100),2)+ROUND(((ROUND((ROUND(((AE87-(EU87))*AV87*1),2)*BS87),2)*AT87)/100),2)) -> 0 | CZ87: =(ROUND((((S87+ROUND((ROUND(((EU87)*AV87*1),2)*BS87),2))*AU87)/100),2)+ROUND(((ROUND((ROUND(((AE87-(EU87))*AV87*1),2)*BS87),2)*AU87)/100),2)) -> 0 | DN87: 0 | DO87: 0 | DP87: 1 | DQ87: 1 | DU87: 1013 | DV87: ШТ | DW87: ШТ | DX87: 1 | EE87: 57042890 | EF87: 214 | EG87: Оборудование, отсутствующие в СНБ | EH87: 0 | EJ87: 3 | EK87: 400007 | EL87: Оборудование, отсутствующие в СНБ | EM87: Оборуд. КА | EQ87: 16 | ER87: 0 | ES87: 465031.79 | ET87: 0 | EU87: 0 | EV87: 0 | EW87: 0 | EX87: 0 | EY87: 0 | FQ87: 0 | FR87: =P87 -> 465031.79 | FS87: 0 | FX87: 0 | FY87: 0 | GA87: [4 120 222 / 1,22 / 7,57] + 3% Трансп + 1,2% Заг.скл | GD87: 1 | GF87: -2107335193 | GG87: 2 | GH87: 4 | GI87: -2 | GJ87: 0 | GK87: 0 | GL87: =ROUND(IF(AND(BH87=3,BI87=3,FS87<>0),P87,0),2) -> 0 | GM87: =ROUND(O87+X87+Y87,2)+GX87 -> 465031.79 | GN87: =IF(OR(BI87=0,BI87=1),GM87-GX87,0) -> 0 | GO87: =IF(BI87=2,GM87-GX87,0) -> 0 | GP87: =IF(BI87=4,GM87-GX87,0) -> 0 | GR87: 1 | GS87: 2 | GT87: 0 | GV87: =ROUND((GT87),6) -> 0 | GW87: 1 | GX87: =ROUND(HC87*I87,2) -> 0 | HA87: 0 | HB87: 0 | HC87: =GV87*GW87 -> 0 | HE87: 3 | HF87: 1,2 | HS87: 0 | IK87: 0
A88: 17 | B88: 1 | E88: 11 | F88: КА, п.2 | G88: SecurOS-IVS-NVRIndustrial( H.712)-AO.ASC7SP4HPX-99/1000- 180000R6-W Специализированный 99 канальный сервер объектового контроля / суммарный входящий видеопоток до 1000 Мбит/с / MJPEG, H.264, H.265 / удаленная работа с системой через LAN 4x1Gbit Ethernet / накопители под ОС SSD 480GB х 2 (Raid 1) / хранение видеоархива в течение 31 суток, поток ~ 5Мбит/с на канал, постоянная запись / отказоустойчивый дисковый массив объемом 180Тб HDD RAID6 в базовой комплектации/аппаратный RAID контроллер SAS/SATA, горячая замена дисков, вентиляторов и резервирование блоков питания, система самодиагностики / установка в 19"" стойку (рельсы/ручки в комплекте, высота не более 4U) / 220В, 50Гц / размещение в телекоммуникационных шкафах (стойках) глубиной не менее 1000мм / Максимальная потребляемая мощность 600Вт; USB-Ключ аппаратной защиты ""Guardant"" - 1шт / Предустановленная операционная система / В комплекте поставки: клавиатура + оптический манипулятор (""мышь""). Комплект предустановленного программного обеспечения, в составе: - SecurOS H.712 Premium - Ядро видеосервера версия 11.x - 1экз.; - SecurOS H.712 Premium - Подключение видеоканала - 95экз.; - SecurOS H.712 Premium - Трансляции видеоканала в ЕЦХД - 95экз.; - SecurOS H.712 Premium - Пользователь системы - 5экз.; - SecurOS H.712 Premium - Модуль интеграции ПО "FireSec" от компании ""RUBEZH" 1экз.;" | H88: ШТ | I88: 1 | J88: 0 | K88: 1 | O88: =ROUND(CP88,2) -> 3520290.6 | P88: =ROUND((ROUND((AC88*AW88*I88),2)*BC88),2) -> 3520290.6 | Q88: =(ROUND((ROUND(((ET88)*AV88*I88),2)*BB88),2)+ROUND((ROUND(((AE88-(EU88))*AV88*I88),2)*BS88),2)) -> 0 | R88: =(ROUND((ROUND(((EU88)*AV88*I88),2)*BS88),2)+ROUND((ROUND(((AE88-(EU88))*AV88*I88),2)*BS88),2)) -> 0 | S88: =ROUND((ROUND((AF88*AV88*I88),2)*BA88),2) -> 0 | T88: =ROUND(CU88*I88,2) -> 0 | U88: =CV88*I88 -> 0 | V88: =CW88*I88 -> 0 | W88: =ROUND(CX88*I88,2) -> 0 | X88: =(ROUND((((S88+ROUND((ROUND(((EU88)*AV88*I88),2)*BS88),2))*AT88)/100),2)+ROUND(((ROUND((ROUND(((AE88-(EU88))*AV88*I88),2)*BS88),2)*AT88)/100),2)) -> 0 | Y88: =(ROUND((((S88+ROUND((ROUND(((EU88)*AV88*I88),2)*BS88),2))*AU88)/100),2)+ROUND(((ROUND((ROUND(((AE88-(EU88))*AV88*I88),2)*BS88),2)*AU88)/100),2)) -> 0 | AA88: 55934357 | AB88: =ROUND((AC88+AD88+AF88),6) -> 465031.79 | AC88: =ROUND((ES88),6) -> 465031.79 | AD88: =ROUND((((ET88)-(EU88))+AE88),6) -> 0 | AE88: =ROUND((EU88),6) -> 0 | AF88: =ROUND((EV88),6) -> 0 | AG88: =ROUND((AP88),6) -> 0 | AH88: =(EW88) -> 0 | AI88: =(EX88) -> 0 | AJ88: =(AS88) -> 0 | AK88: 465031.79 | AL88: 465031.79 | AM88: 0 | AN88: 0 | AO88: 0 | AP88: 0 | AQ88: 0 | AR88: 0 | AS88: 0 | AT88: 0 | AU88: 0 | AV88: 1 | AW88: 1 | AZ88: 1 | BA88: 1 | BB88: 1 | BC88: 7.57 | BH88: 3 | BI88: 3 | BJ88: КА, п.2 | BM88: 400007 | BN88: 0 | BP88: 0 | BQ88: 214 | BR88: 0 | BS88: 1 | BT88: 1 | BU88: 1 | BV88: 1 | BW88: 1 | BX88: 1 | BZ88: 0 | CA88: 0 | CE88: 1566 | CF88: 0 | CG88: 0 | CM88: 0 | CO88: 0 | CP88: =(P88+Q88+S88) -> 3520290.6 | CQ88: =ROUND((ROUND((AC88*AW88*1),2)*BC88),2) -> 3520290.6 | CR88: =(ROUND((ROUND(((ET88)*AV88*1),2)*BB88),2)+ROUND((ROUND(((AE88-(EU88))*AV88*1),2)*BS88),2)) -> 0 | CS88: =(ROUND((ROUND(((EU88)*AV88*1),2)*BS88),2)+ROUND((ROUND(((AE88-(EU88))*AV88*1),2)*BS88),2)) -> 0 | CT88: =ROUND((ROUND((AF88*AV88*1),2)*BA88),2) -> 0 | CU88: =AG88 -> 0 | CV88: =(AH88*AV88) -> 0 | CW88: =AI88 -> 0 | CX88: =AJ88 -> 0 | CY88: =(ROUND((((S88+ROUND((ROUND(((EU88)*AV88*1),2)*BS88),2))*AT88)/100),2)+ROUND(((ROUND((ROUND(((AE88-(EU88))*AV88*1),2)*BS88),2)*AT88)/100),2)) -> 0 | CZ88: =(ROUND((((S88+ROUND((ROUND(((EU88)*AV88*1),2)*BS88),2))*AU88)/100),2)+ROUND(((ROUND((ROUND(((AE88-(EU88))*AV88*1),2)*BS88),2)*AU88)/100),2)) -> 0 | DN88: 0 | DO88: 0 | DP88: 1 | DQ88: 1 | DU88: 1013 | DV88: ШТ | DW88: ШТ | DX88: 1 | EE88: 57042890 | EF88: 214 | EG88: Оборудование, отсутствующие в СНБ | EH88: 0 | EJ88: 3 | EK88: 400007 | EL88: Оборудование, отсутствующие в СНБ | EM88: Оборуд. КА | EQ88: 16 | ER88: 0 | ES88: 465031.79 | ET88: 0 | EU88: 0 | EV88: 0 | EW88: 0 | EX88: 0 | EY88: 0 | EZ88: 5 | FC88: 1 | FD88: 18 | FF88: 4120222 | FQ88: 0 | FR88: =P88 -> 3520290.6 | FS88: 0 | FX88: 0 | FY88: 0 | GA88: [4 120 222 / 1,22 / 7,57] + 3% Трансп + 1,2% Заг.скл | GD88: 1 | GF88: -2107335193 | GG88: 2 | GH88: 3 | GI88: 5 | GJ88: 0 | GK88: 0 | GL88: =ROUND(IF(AND(BH88=3,BI88=3,FS88<>0),P88,0),2) -> 0 | GM88: =ROUND(O88+X88+Y88,2)+GX88 -> 3520290.6 | GN88: =IF(OR(BI88=0,BI88=1),GM88-GX88,0) -> 0 | GO88: =IF(BI88=2,GM88-GX88,0) -> 0 | GP88: =IF(BI88=4,GM88-GX88,0) -> 0 | GR88: 1 | GS88: 1 | GT88: 0 | GV88: =ROUND((GT88),6) -> 0 | GW88: 1 | GX88: =ROUND(HC88*I88,2) -> 0 | HA88: 0 | HB88: 0 | HC88: =GV88*GW88 -> 0 | HE88: 3 | HF88: 1,2 | HS88: 0 | IK88: 0
A89: 17 | B89: 1 | F89: 13.1-2-668 | G89: Сервер видеонаблюдения для записи и хранения данных с IP камер, поддержка до 128 каналов. Установка до 8 жестких дисков, монтаж на стойку 19’ 2U, возможность горячей замены аппаратных компонентов, напряжение 220 В, мощность 560 Вт, ПО, в комплекте: салазки для крепления в стойку, мышь, клавиатура, кабель питания, диапазон рабочих температур от +5 °C до 45 °C, габаритные размеры 437х89х647 мм | H89: КОМПЛЕКТ | I89: 1 | J89: 0 | K89: 1 | O89: =ROUND(CP89,2) -> 38812.66 | P89: =ROUND((ROUND((AC89*I89),2)*BC89),2) -> 38812.66 | Q89: =(ROUND((ROUND(((ET89)*AV89*I89),2)*BB89),2)+ROUND((ROUND(((AE89-(EU89))*AV89*I89),2)*BS89),2)) -> 0 | R89: =(ROUND((ROUND(((EU89)*AV89*I89),2)*BS89),2)+ROUND((ROUND(((AE89-(EU89))*AV89*I89),2)*BS89),2)) -> 0 | S89: =ROUND((ROUND((AF89*AV89*I89),2)*BA89),2) -> 0 | T89: =ROUND(CU89*I89,2) -> 0 | U89: =CV89*I89 -> 0 | V89: =CW89*I89 -> 0 | W89: =ROUND(CX89*I89,2) -> 0 | X89: =(ROUND((((S89+ROUND((ROUND(((EU89)*AV89*I89),2)*BS89),2))*AT89)/100),2)+ROUND(((ROUND((ROUND(((AE89-(EU89))*AV89*I89),2)*BS89),2)*AT89)/100),2)) -> 0 | Y89: =(ROUND((((S89+ROUND((ROUND(((EU89)*AV89*I89),2)*BS89),2))*AU89)/100),2)+ROUND(((ROUND((ROUND(((AE89-(EU89))*AV89*I89),2)*BS89),2)*AU89)/100),2)) -> 0 | AA89: -1 | AB89: =ROUND((AC89+AD89+AF89),6) -> 38812.66 | AC89: =ROUND((ES89),6) -> 38812.66 | AD89: =ROUND((((ET89)-(EU89))+AE89),6) -> 0 | AE89: =ROUND((EU89),6) -> 0 | AF89: =ROUND((EV89),6) -> 0 | AG89: =ROUND((AP89),6) -> 0 | AH89: =(EW89) -> 0 | AI89: =(EX89) -> 0 | AJ89: =(AS89) -> 0 | AK89: 38812.66 | AL89: 38812.66 | AM89: 0 | AN89: 0 | AO89: 0 | AP89: 0 | AQ89: 0 | AR89: 0 | AS89: 0 | AT89: 0 | AU89: 0 | AV89: 1 | AW89: 1 | AZ89: 1 | BA89: 1 | BB89: 1 | BC89: 1 | BH89: 3 | BI89: 3 | BJ89: ТСН-2001.13-2. Доп. 47, Р. 1, о. 2, поз. 668 | BM89: 746 | BN89: 0 | BP89: 0 | BQ89: 130 | BR89: 0 | BS89: 1 | BT89: 1 | BU89: 1 | BV89: 1 | BW89: 1 | BX89: 1 | BZ89: 0 | CA89: 0 | CE89: 1566 | CF89: 0 | CG89: 0 | CM89: 0 | CO89: 0 | CP89: =(P89+Q89+S89) -> 38812.66 | CQ89: =ROUND((ROUND((AC89*1),2)*BC89),2) -> 38812.66 | CR89: =(ROUND((ROUND(((ET89)*AV89*1),2)*BB89),2)+ROUND((ROUND(((AE89-(EU89))*AV89*1),2)*BS89),2)) -> 0 | CS89: =(ROUND((ROUND(((EU89)*AV89*1),2)*BS89),2)+ROUND((ROUND(((AE89-(EU89))*AV89*1),2)*BS89),2)) -> 0 | CT89: =ROUND((ROUND((AF89*AV89*1),2)*BA89),2) -> 0 | CU89: =AG89 -> 0 | CV89: =(AH89*AV89) -> 0 | CW89: =AI89 -> 0 | CX89: =AJ89 -> 0 | CY89: =(ROUND((((S89+ROUND((ROUND(((EU89)*AV89*1),2)*BS89),2))*AT89)/100),2)+ROUND(((ROUND((ROUND(((AE89-(EU89))*AV89*1),2)*BS89),2)*AT89)/100),2)) -> 0 | CZ89: =(ROUND((((S89+ROUND((ROUND(((EU89)*AV89*1),2)*BS89),2))*AU89)/100),2)+ROUND(((ROUND((ROUND(((AE89-(EU89))*AV89*1),2)*BS89),2)*AU89)/100),2)) -> 0 | DN89: 0 | DO89: 0 | DP89: 1 | DQ89: 1 | DU89: 1013 | DV89: КОМПЛЕКТ | DW89: КОМПЛЕКТ | DX89: 1 | EE89: 57043064 | EF89: 130 | EG89: Сметная стоимость оборудования | EH89: 0 | EJ89: 3 | EK89: 746 | EL89: ТСН-2001.13. Сметная стоимость оборудования | EM89: ТСН-2001.13 | EQ89: 1024 | ER89: 38812.66 | ES89: 38812.66 | ET89: 0 | EU89: 0 | EV89: 0 | EW89: 0 | EX89: 0 | EY89: 0 | FQ89: 0 | FR89: =P89 -> 38812.66 | FS89: 0 | FX89: 0 | FY89: 0 | GD89: 1 | GF89: 1083781214 | GG89: 2 | GH89: 1 | GI89: -2 | GJ89: 0 | GK89: 0 | GL89: =ROUND(IF(AND(BH89=3,BI89=3,FS89<>0),P89,0),2) -> 0 | GM89: =ROUND(O89+X89+Y89,2)+GX89 -> 38812.66 | GN89: =IF(OR(BI89=0,BI89=1),GM89-GX89,0) -> 0 | GO89: =IF(BI89=2,GM89-GX89,0) -> 0 | GP89: =IF(BI89=4,GM89-GX89,0) -> 0 | GR89: 0 | GS89: 3 | GT89: 0 | GV89: =ROUND((GT89),6) -> 0 | GW89: 1 | GX89: =ROUND(HC89*I89,2) -> 0 | HA89: 0 | HB89: 0 | HC89: =GV89*GW89 -> 0 | HS89: 0 | IK89: 0
A90: 17 | B90: 1 | F90: 13.1-2-668 | G90: Сервер видеонаблюдения для записи и хранения данных с IP камер, поддержка до 128 каналов. Установка до 8 жестких дисков, монтаж на стойку 19’ 2U, возможность горячей замены аппаратных компонентов, напряжение 220 В, мощность 560 Вт, ПО, в комплекте: салазки для крепления в стойку, мышь, клавиатура, кабель питания, диапазон рабочих температур от +5 °C до 45 °C, габаритные размеры 437х89х647 мм | H90: КОМПЛЕКТ | I90: 1 | J90: 0 | K90: 1 | O90: =ROUND(CP90,2) -> 291094.95 | P90: =ROUND((ROUND((AC90*I90),2)*BC90),2) -> 291094.95 | Q90: =(ROUND((ROUND(((ET90)*AV90*I90),2)*BB90),2)+ROUND((ROUND(((AE90-(EU90))*AV90*I90),2)*BS90),2)) -> 0 | R90: =(ROUND((ROUND(((EU90)*AV90*I90),2)*BS90),2)+ROUND((ROUND(((AE90-(EU90))*AV90*I90),2)*BS90),2)) -> 0 | S90: =ROUND((ROUND((AF90*AV90*I90),2)*BA90),2) -> 0 | T90: =ROUND(CU90*I90,2) -> 0 | U90: =CV90*I90 -> 0 | V90: =CW90*I90 -> 0 | W90: =ROUND(CX90*I90,2) -> 0 | X90: =(ROUND((((S90+ROUND((ROUND(((EU90)*AV90*I90),2)*BS90),2))*AT90)/100),2)+ROUND(((ROUND((ROUND(((AE90-(EU90))*AV90*I90),2)*BS90),2)*AT90)/100),2)) -> 0 | Y90: =(ROUND((((S90+ROUND((ROUND(((EU90)*AV90*I90),2)*BS90),2))*AU90)/100),2)+ROUND(((ROUND((ROUND(((AE90-(EU90))*AV90*I90),2)*BS90),2)*AU90)/100),2)) -> 0 | AA90: -1 | AB90: =ROUND((AC90+AD90+AF90),6) -> 38812.66 | AC90: =ROUND((ES90),6) -> 38812.66 | AD90: =ROUND((((ET90)-(EU90))+AE90),6) -> 0 | AE90: =ROUND((EU90),6) -> 0 | AF90: =ROUND((EV90),6) -> 0 | AG90: =ROUND((AP90),6) -> 0 | AH90: =(EW90) -> 0 | AI90: =(EX90) -> 0 | AJ90: =(AS90) -> 0 | AK90: 38812.66 | AL90: 38812.66 | AM90: 0 | AN90: 0 | AO90: 0 | AP90: 0 | AQ90: 0 | AR90: 0 | AS90: 0 | AT90: 0 | AU90: 0 | AV90: 1 | AW90: 1 | AZ90: 1 | BA90: 1 | BB90: 1 | BC90: 7.5 | BH90: 3 | BI90: 3 | BJ90: ТСН-2001.13-2. Доп. 47, Р. 1, о. 2, поз. 668 | BM90: 746 | BN90: 0 | BP90: 0 | BQ90: 130 | BR90: 0 | BS90: 1 | BT90: 1 | BU90: 1 | BV90: 1 | BW90: 1 | BX90: 1 | BZ90: 0 | CA90: 0 | CE90: 1566 | CF90: 0 | CG90: 0 | CM90: 0 | CO90: 0 | CP90: =(P90+Q90+S90) -> 291094.95 | CQ90: =ROUND((ROUND((AC90*1),2)*BC90),2) -> 291094.95 | CR90: =(ROUND((ROUND(((ET90)*AV90*1),2)*BB90),2)+ROUND((ROUND(((AE90-(EU90))*AV90*1),2)*BS90),2)) -> 0 | CS90: =(ROUND((ROUND(((EU90)*AV90*1),2)*BS90),2)+ROUND((ROUND(((AE90-(EU90))*AV90*1),2)*BS90),2)) -> 0 | CT90: =ROUND((ROUND((AF90*AV90*1),2)*BA90),2) -> 0 | CU90: =AG90 -> 0 | CV90: =(AH90*AV90) -> 0 | CW90: =AI90 -> 0 | CX90: =AJ90 -> 0 | CY90: =(ROUND((((S90+ROUND((ROUND(((EU90)*AV90*1),2)*BS90),2))*AT90)/100),2)+ROUND(((ROUND((ROUND(((AE90-(EU90))*AV90*1),2)*BS90),2)*AT90)/100),2)) -> 0 | CZ90: =(ROUND((((S90+ROUND((ROUND(((EU90)*AV90*1),2)*BS90),2))*AU90)/100),2)+ROUND(((ROUND((ROUND(((AE90-(EU90))*AV90*1),2)*BS90),2)*AU90)/100),2)) -> 0 | DN90: 0 | DO90: 0 | DP90: 1 | DQ90: 1 | DU90: 1013 | DV90: КОМПЛЕКТ | DW90: КОМПЛЕКТ | DX90: 1 | EE90: 57043064 | EF90: 130 | EG90: Сметная стоимость оборудования | EH90: 0 | EJ90: 3 | EK90: 746 | EL90: ТСН-2001.13. Сметная стоимость оборудования | EM90: ТСН-2001.13 | EQ90: 1024 | ER90: 38812.66 | ES90: 38812.66 | ET90: 0 | EU90: 0 | EV90: 0 | EW90: 0 | EX90: 0 | EY90: 0 | FQ90: 0 | FR90: =P90 -> 291094.95 | FS90: 0 | FX90: 0 | FY90: 0 | GD90: 1 | GF90: 1083781214 | GG90: 2 | GH90: 1 | GI90: 2 | GJ90: 0 | GK90: 0 | GL90: =ROUND(IF(AND(BH90=3,BI90=3,FS90<>0),P90,0),2) -> 0 | GM90: =ROUND(O90+X90+Y90,2)+GX90 -> 291094.95 | GN90: =IF(OR(BI90=0,BI90=1),GM90-GX90,0) -> 0 | GO90: =IF(BI90=2,GM90-GX90,0) -> 0 | GP90: =IF(BI90=4,GM90-GX90,0) -> 0 | GR90: 0 | GS90: 3 | GT90: 0 | GV90: =ROUND((GT90),6) -> 0 | GW90: 1 | GX90: =ROUND(HC90*I90,2) -> 0 | HA90: 0 | HB90: 0 | HC90: =GV90*GW90 -> 0 | HS90: 0 | IK90: 0
A91: 17 | B91: 1 | C91: =ROW(SmtRes!A149) -> 149 | D91: =ROW(EtalonRes!A179) -> 179 | E91: 12 | F91: 4.10-34-5 | G91: Монтаж коммутатора служебной связи | H91: 1 ШТ. | I91: 1 | J91: 0 | K91: 1 | O91: =ROUND(CP91,2) -> 146.72 | P91: =ROUND((ROUND((AC91*AW91*I91),2)*BC91),2) -> 12.35 | Q91: =(ROUND((ROUND((((ET91*1.2))*AV91*I91),2)*BB91),2)+ROUND((ROUND(((AE91-((EU91*1.2)))*AV91*I91),2)*BS91),2)) -> 36.07 | R91: =(ROUND((ROUND((((EU91*1.2))*AV91*I91),2)*BS91),2)+ROUND((ROUND(((AE91-((EU91*1.2)))*AV91*I91),2)*BS91),2)) -> 3.97 | S91: =ROUND((ROUND((AF91*AV91*I91),2)*BA91),2) -> 98.3 | T91: =ROUND(CU91*I91,2) -> 0 | U91: =CV91*I91 -> 7.78968 | V91: =CW91*I91 -> 0 | W91: =ROUND(CX91*I91,2) -> 0 | X91: =(ROUND((((S91+ROUND((ROUND((((EU91*1.2))*AV91*I91),2)*BS91),2))*AT91)/100),2)+ROUND(((ROUND((ROUND(((AE91-((EU91*1.2)))*AV91*I91),2)*BS91),2)*AT91)/100),2)) -> 92.04 | Y91: =(ROUND((((S91+ROUND((ROUND((((EU91*1.2))*AV91*I91),2)*BS91),2))*AU91)/100),2)+ROUND(((ROUND((ROUND(((AE91-((EU91*1.2)))*AV91*I91),2)*BS91),2)*AU91)/100),2)) -> 47.04 | AA91: 55934355 | AB91: =ROUND((AC91+AD91+AF91),6) -> 140.69 | AC91: =ROUND(((ES91*1)),6) -> 12.35 | AD91: =ROUND(((((ET91*1.2))-((EU91*1.2)))+AE91),6) -> 34.452 | AE91: =ROUND(((EU91*1.2)),6) -> 3.792 | AF91: =ROUND(((EV91*1.2)),6) -> 93.888 | AG91: =ROUND((AP91),6) -> 0 | AH91: =((EW91*1.2)) -> 7.44 | AI91: =((EX91*1.2)) -> 0 | AJ91: =(AS91) -> 0 | AK91: 119.3 | AL91: 12.35 | AM91: 28.71 | AN91: 3.16 | AO91: 78.24 | AP91: 0 | AQ91: 6.2 | AR91: 0 | AS91: 0 | AT91: 90 | AU91: 46 | AV91: 1.047 | AW91: 1 | AZ91: 1 | BA91: 1 | BB91: 1 | BC91: 1 | BH91: 0 | BI91: 2 | BJ91: ТСН-2001.4 Доп. 80, Сб. 10, т. 34, поз. 5 | BM91: 68 | BN91: 0 | BO91: 4.10-34-5 | BP91: 1 | BQ91: 40 | BR91: 0 | BS91: 1 | BT91: 1 | BU91: 1 | BV91: 1 | BW91: 1 | BX91: 1 | BZ91: 90 | CA91: 46 | CE91: 1566 | CF91: 0 | CG91: 0 | CM91: 0 | CN91: Поправка: Гл.12.Прил.8.п.8. 3_12.00.01.11.001 Наименование: При наличии напряженных и стесненных условий производства работ (стесненность, сложность складирования и транспортной логистики и т.п.) для объектов, расположенных в пределах круговой магистральной системы улиц "Садовое кольцо" города Москвы | CO91: 0 | CP91: =(P91+Q91+S91) -> 146.72 | CQ91: =ROUND((ROUND((AC91*AW91*1),2)*BC91),2) -> 12.35 | CR91: =(ROUND((ROUND((((ET91*1.2))*AV91*1),2)*BB91),2)+ROUND((ROUND(((AE91-((EU91*1.2)))*AV91*1),2)*BS91),2)) -> 36.07 | CS91: =(ROUND((ROUND((((EU91*1.2))*AV91*1),2)*BS91),2)+ROUND((ROUND(((AE91-((EU91*1.2)))*AV91*1),2)*BS91),2)) -> 3.97 | CT91: =ROUND((ROUND((AF91*AV91*1),2)*BA91),2) -> 98.3 | CU91: =AG91 -> 0 | CV91: =(AH91*AV91) -> 7.78968 | CW91: =AI91 -> 0 | CX91: =AJ91 -> 0 | CY91: =(ROUND((((S91+ROUND((ROUND((((EU91*1.2))*AV91*1),2)*BS91),2))*AT91)/100),2)+ROUND(((ROUND((ROUND(((AE91-((EU91*1.2)))*AV91*1),2)*BS91),2)*AT91)/100),2)) -> 92.04 | CZ91: =(ROUND((((S91+ROUND((ROUND((((EU91*1.2))*AV91*1),2)*BS91),2))*AU91)/100),2)+ROUND(((ROUND((ROUND(((AE91-((EU91*1.2)))*AV91*1),2)*BS91),2)*AU91)/100),2)) -> 47.04 | DB91: 39 | DD91: *1 | DE91: *1,2 | DF91: *1,2 | DG91: *1,2 | DI91: *1,2 | DJ91: *1,2 | DN91: 0 | DO91: 0 | DP91: 1 | DQ91: 1 | DU91: 1013 | DV91: 1 ШТ. | DW91: 1 ШТ. | DX91: 1 | EE91: 57042958 | EF91: 40 | EG91: Монтаж оборудования | EH91: 0 | EJ91: 2 | EK91: 68 | EL91: ТСН-2001.4-10. Прокладка и монтаж сетей связи | EM91: ТСН-2001.4-10-1 | EO91: Поправка: Гл.12.Прил.8.п.8. 3_12.00.01.11.001 | EQ91: 0 | ER91: 119.3 | ES91: 12.35 | ET91: 28.71 | EU91: 3.16 | EV91: 78.24 | EW91: 6.2 | EX91: 0 | EY91: 0 | FQ91: 0 | FR91: 0 | FS91: 0 | FX91: 90 | FY91: 46 | GD91: 1 | GF91: 982292204 | GG91: 2 | GH91: 1 | GI91: 2 | GJ91: 0 | GK91: 0 | GL91: =ROUND(IF(AND(BH91=3,BI91=3,FS91<>0),P91,0),2) -> 0 | GM91: =ROUND(O91+X91+Y91,2)+GX91 -> 285.8 | GN91: =IF(OR(BI91=0,BI91=1),GM91-GX91,0) -> 0 | GO91: =IF(BI91=2,GM91-GX91,0) -> 285.8 | GP91: =IF(BI91=4,GM91-GX91,0) -> 0 | GR91: 0 | GS91: 3 | GT91: 0 | GV91: =ROUND((GT91),6) -> 0 | GW91: 1 | GX91: =ROUND(HC91*I91,2) -> 0 | HA91: 0 | HB91: 0 | HC91: =GV91*GW91 -> 0 | HS91: 0 | IK91: 0
A92: 17 | B92: 1 | C92: =ROW(SmtRes!A154) -> 154 | D92: =ROW(EtalonRes!A184) -> 184 | E92: 12 | F92: 4.10-34-5 | G92: Монтаж коммутатора служебной связи | H92: 1 ШТ. | I92: 1 | J92: 0 | K92: 1 | O92: =ROUND(CP92,2) -> 6303.65 | P92: =ROUND((ROUND((AC92*AW92*I92),2)*BC92),2) -> 181.55 | Q92: =(ROUND((ROUND((((ET92*1.2))*AV92*I92),2)*BB92),2)+ROUND((ROUND(((AE92-((EU92*1.2)))*AV92*I92),2)*BS92),2)) -> 582.89 | R92: =(ROUND((ROUND((((EU92*1.2))*AV92*I92),2)*BS92),2)+ROUND((ROUND(((AE92-((EU92*1.2)))*AV92*I92),2)*BS92),2)) -> 223.71 | S92: =ROUND((ROUND((AF92*AV92*I92),2)*BA92),2) -> 5539.21 | T92: =ROUND(CU92*I92,2) -> 0 | U92: =CV92*I92 -> 7.78968 | V92: =CW92*I92 -> 0 | W92: =ROUND(CX92*I92,2) -> 0 | X92: =(ROUND((((S92+ROUND((ROUND((((EU92*1.2))*AV92*I92),2)*BS92),2))*AT92)/100),2)+ROUND(((ROUND((ROUND(((AE92-((EU92*1.2)))*AV92*I92),2)*BS92),2)*AT92)/100),2)) -> 5186.63 | Y92: =(ROUND((((S92+ROUND((ROUND((((EU92*1.2))*AV92*I92),2)*BS92),2))*AU92)/100),2)+ROUND(((ROUND((ROUND(((AE92-((EU92*1.2)))*AV92*I92),2)*BS92),2)*AU92)/100),2)) -> 2650.94 | AA92: 55934357 | AB92: =ROUND((AC92+AD92+AF92),6) -> 140.69 | AC92: =ROUND(((ES92*1)),6) -> 12.35 | AD92: =ROUND(((((ET92*1.2))-((EU92*1.2)))+AE92),6) -> 34.452 | AE92: =ROUND(((EU92*1.2)),6) -> 3.792 | AF92: =ROUND(((EV92*1.2)),6) -> 93.888 | AG92: =ROUND((AP92),6) -> 0 | AH92: =((EW92*1.2)) -> 7.44 | AI92: =((EX92*1.2)) -> 0 | AJ92: =(AS92) -> 0 | AK92: 119.3 | AL92: 12.35 | AM92: 28.71 | AN92: 3.16 | AO92: 78.24 | AP92: 0 | AQ92: 6.2 | AR92: 0 | AS92: 0 | AT92: 90 | AU92: 46 | AV92: 1.047 | AW92: 1 | AZ92: 1 | BA92: 56.35 | BB92: 16.16 | BC92: 14.7 | BH92: 0 | BI92: 2 | BJ92: ТСН-2001.4 Доп. 80, Сб. 10, т. 34, поз. 5 | BM92: 68 | BN92: 0 | BO92: 4.10-34-5 | BP92: 1 | BQ92: 40 | BR92: 0 | BS92: 56.35 | BT92: 1 | BU92: 1 | BV92: 1 | BW92: 1 | BX92: 1 | BZ92: 90 | CA92: 46 | CE92: 1566 | CF92: 0 | CG92: 0 | CM92: 0 | CN92: Поправка: Гл.12.Прил.8.п.8. 3_12.00.01.11.001 Наименование: При наличии напряженных и стесненных условий производства работ (стесненность, сложность складирования и транспортной логистики и т.п.) для объектов, расположенных в пределах круговой магистральной системы улиц "Садовое кольцо" города Москвы | CO92: 0 | CP92: =(P92+Q92+S92) -> 6303.65 | CQ92: =ROUND((ROUND((AC92*AW92*1),2)*BC92),2) -> 181.55 | CR92: =(ROUND((ROUND((((ET92*1.2))*AV92*1),2)*BB92),2)+ROUND((ROUND(((AE92-((EU92*1.2)))*AV92*1),2)*BS92),2)) -> 582.89 | CS92: =(ROUND((ROUND((((EU92*1.2))*AV92*1),2)*BS92),2)+ROUND((ROUND(((AE92-((EU92*1.2)))*AV92*1),2)*BS92),2)) -> 223.71 | CT92: =ROUND((ROUND((AF92*AV92*1),2)*BA92),2) -> 5539.21 | CU92: =AG92 -> 0 | CV92: =(AH92*AV92) -> 7.78968 | CW92: =AI92 -> 0 | CX92: =AJ92 -> 0 | CY92: =(ROUND((((S92+ROUND((ROUND((((EU92*1.2))*AV92*1),2)*BS92),2))*AT92)/100),2)+ROUND(((ROUND((ROUND(((AE92-((EU92*1.2)))*AV92*1),2)*BS92),2)*AT92)/100),2)) -> 5186.63 | CZ92: =(ROUND((((S92+ROUND((ROUND((((EU92*1.2))*AV92*1),2)*BS92),2))*AU92)/100),2)+ROUND(((ROUND((ROUND(((AE92-((EU92*1.2)))*AV92*1),2)*BS92),2)*AU92)/100),2)) -> 2650.94 | DB92: 40 | DD92: *1 | DE92: *1,2 | DF92: *1,2 | DG92: *1,2 | DI92: *1,2 | DJ92: *1,2 | DN92: 0 | DO92: 0 | DP92: 1 | DQ92: 1 | DU92: 1013 | DV92: 1 ШТ. | DW92: 1 ШТ. | DX92: 1 | EE92: 57042958 | EF92: 40 | EG92: Монтаж оборудования | EH92: 0 | EJ92: 2 | EK92: 68 | EL92: ТСН-2001.4-10. Прокладка и монтаж сетей связи | EM92: ТСН-2001.4-10-1 | EO92: Поправка: Гл.12.Прил.8.п.8. 3_12.00.01.11.001 | EQ92: 0 | ER92: 119.3 | ES92: 12.35 | ET92: 28.71 | EU92: 3.16 | EV92: 78.24 | EW92: 6.2 | EX92: 0 | EY92: 0 | FQ92: 0 | FR92: 0 | FS92: 0 | FX92: 90 | FY92: 46 | GD92: 1 | GF92: 982292204 | GG92: 2 | GH92: 1 | GI92: 2 | GJ92: 0 | GK92: 0 | GL92: =ROUND(IF(AND(BH92=3,BI92=3,FS92<>0),P92,0),2) -> 0 | GM92: =ROUND(O92+X92+Y92,2)+GX92 -> 14141.22 | GN92: =IF(OR(BI92=0,BI92=1),GM92-GX92,0) -> 0 | GO92: =IF(BI92=2,GM92-GX92,0) -> 14141.22 | GP92: =IF(BI92=4,GM92-GX92,0) -> 0 | GR92: 0 | GS92: 3 | GT92: 0 | GV92: =ROUND((GT92),6) -> 0 | GW92: 1 | GX92: =ROUND(HC92*I92,2) -> 0 | HA92: 0 | HB92: 0 | HC92: =GV92*GW92 -> 0 | HS92: 0 | IK92: 0
A93: 18 | B93: 1 | C93: 149 | E93: 12,1 | F93: КА, п.3 | G93: Управляемый коммутатор уровня L3: 8х10/100/1000BASET (RJ-45) PoE/PoE+, 2х10/100/1000BASE-T (RJ-45), 2х1000BASE-X (SFP), RS-232/RJ-45 MES2308P | H93: ШТ | I93: =I91*J93 -> 1 | J93: 1 | K93: 1 | O93: =ROUND(CP93,2) -> 23932.38 | P93: =ROUND((ROUND((AC93*AW93*I93),2)*BC93),2) -> 23932.38 | Q93: =(ROUND((ROUND(((ET93)*AV93*I93),2)*BB93),2)+ROUND((ROUND(((AE93-(EU93))*AV93*I93),2)*BS93),2)) -> 0 | R93: =(ROUND((ROUND(((EU93)*AV93*I93),2)*BS93),2)+ROUND((ROUND(((AE93-(EU93))*AV93*I93),2)*BS93),2)) -> 0 | S93: =ROUND((ROUND((AF93*AV93*I93),2)*BA93),2) -> 0 | T93: =ROUND(CU93*I93,2) -> 0 | U93: =CV93*I93 -> 0 | V93: =CW93*I93 -> 0 | W93: =ROUND(CX93*I93,2) -> 0 | X93: =(ROUND((((S93+ROUND((ROUND(((EU93)*AV93*I93),2)*BS93),2))*AT93)/100),2)+ROUND(((ROUND((ROUND(((AE93-(EU93))*AV93*I93),2)*BS93),2)*AT93)/100),2)) -> 0 | Y93: =(ROUND((((S93+ROUND((ROUND(((EU93)*AV93*I93),2)*BS93),2))*AU93)/100),2)+ROUND(((ROUND((ROUND(((AE93-(EU93))*AV93*I93),2)*BS93),2)*AU93)/100),2)) -> 0 | AA93: 55934355 | AB93: =ROUND((AC93+AD93+AF93),6) -> 23932.38 | AC93: =ROUND((ES93),6) -> 23932.38 | AD93: =ROUND((((ET93)-(EU93))+AE93),6) -> 0 | AE93: =ROUND((EU93),6) -> 0 | AF93: =ROUND((EV93),6) -> 0 | AG93: =ROUND((AP93),6) -> 0 | AH93: =(EW93) -> 0 | AI93: =(EX93) -> 0 | AJ93: =(AS93) -> 0 | AK93: 23932.38 | AL93: 23932.38 | AM93: 0 | AN93: 0 | AO93: 0 | AP93: 0 | AQ93: 0 | AR93: 0 | AS93: 0 | AT93: 0 | AU93: 0 | AV93: 1 | AW93: 1 | AZ93: 1 | BA93: 1 | BB93: 1 | BC93: 1 | BH93: 3 | BI93: 3 | BJ93: КА, п.3 | BM93: 400007 | BN93: 0 | BP93: 0 | BQ93: 214 | BR93: 0 | BS93: 1 | BT93: 1 | BU93: 1 | BV93: 1 | BW93: 1 | BX93: 1 | BZ93: 90 | CA93: 46 | CE93: 1566 | CF93: 0 | CG93: 0 | CM93: 0 | CN93: Поправка: Гл.12.Прил.8.п.8. 3_12.00.01.11.001_x000D_ Наименование: При наличии напряженных и стесненных условий производства работ (стесненность, сложность складирования и транспортной логистики и т.п.) для объектов, расположенных в пределах круговой магистральной системы улиц "Садовое кольцо" города Москвы | CO93: 0 | CP93: =(P93+Q93+S93) -> 23932.38 | CQ93: =ROUND((ROUND((AC93*AW93*1),2)*BC93),2) -> 23932.38 | CR93: =(ROUND((ROUND(((ET93)*AV93*1),2)*BB93),2)+ROUND((ROUND(((AE93-(EU93))*AV93*1),2)*BS93),2)) -> 0 | CS93: =(ROUND((ROUND(((EU93)*AV93*1),2)*BS93),2)+ROUND((ROUND(((AE93-(EU93))*AV93*1),2)*BS93),2)) -> 0 | CT93: =ROUND((ROUND((AF93*AV93*1),2)*BA93),2) -> 0 | CU93: =AG93 -> 0 | CV93: =(AH93*AV93) -> 0 | CW93: =AI93 -> 0 | CX93: =AJ93 -> 0 | CY93: =(ROUND((((S93+ROUND((ROUND(((EU93)*AV93*1),2)*BS93),2))*AT93)/100),2)+ROUND(((ROUND((ROUND(((AE93-(EU93))*AV93*1),2)*BS93),2)*AT93)/100),2)) -> 0 | CZ93: =(ROUND((((S93+ROUND((ROUND(((EU93)*AV93*1),2)*BS93),2))*AU93)/100),2)+ROUND(((ROUND((ROUND(((AE93-(EU93))*AV93*1),2)*BS93),2)*AU93)/100),2)) -> 0 | DN93: 0 | DO93: 0 | DP93: 1 | DQ93: 1 | DU93: 1013 | DV93: ШТ | DW93: ШТ | DX93: 1 | EE93: 57042890 | EF93: 214 | EG93: Оборудование, отсутствующие в СНБ | EH93: 0 | EJ93: 3 | EK93: 400007 | EL93: Оборудование, отсутствующие в СНБ | EM93: Оборуд. КА | EO93: Поправка: Гл.12.Прил.8.п.8. 3_12.00.01.11.001 | EQ93: 16 | ER93: 0 | ES93: 23932.38 | ET93: 0 | EU93: 0 | EV93: 0 | EW93: 0 | EX93: 0 | FQ93: 0 | FR93: =P93 -> 23932.38 | FS93: 0 | FX93: 90 | FY93: 46 | GA93: [212 043 / 1,22 / 7,57] + 3% Трансп + 1,2% Заг.скл | GD93: 1 | GF93: 1942153840 | GG93: 2 | GH93: 4 | GI93: -2 | GJ93: 0 | GK93: 0 | GL93: =ROUND(IF(AND(BH93=3,BI93=3,FS93<>0),P93,0),2) -> 0 | GM93: =ROUND(O93+X93+Y93,2)+GX93 -> 23932.38 | GN93: =IF(OR(BI93=0,BI93=1),GM93-GX93,0) -> 0 | GO93: =IF(BI93=2,GM93-GX93,0) -> 0 | GP93: =IF(BI93=4,GM93-GX93,0) -> 0 | GR93: 1 | GS93: 2 | GT93: 0 | GV93: =ROUND((GT93),6) -> 0 | GW93: 1 | GX93: =ROUND(HC93*I93,2) -> 0 | HA93: 0 | HB93: 0 | HC93: =GV93*GW93 -> 0 | HE93: 3 | HF93: 1,2 | HM93: *1 | HS93: 0 | IK93: 0
A94: 18 | B94: 1 | C94: 154 | E94: 12,1 | F94: КА, п.3 | G94: Управляемый коммутатор уровня L3: 8х10/100/1000BASET (RJ-45) PoE/PoE+, 2х10/100/1000BASE-T (RJ-45), 2х1000BASE-X (SFP), RS-232/RJ-45 MES2308P | H94: ШТ | I94: =I92*J94 -> 1 | J94: 1 | K94: 1 | O94: =ROUND(CP94,2) -> 181168.12 | P94: =ROUND((ROUND((AC94*AW94*I94),2)*BC94),2) -> 181168.12 | Q94: =(ROUND((ROUND(((ET94)*AV94*I94),2)*BB94),2)+ROUND((ROUND(((AE94-(EU94))*AV94*I94),2)*BS94),2)) -> 0 | R94: =(ROUND((ROUND(((EU94)*AV94*I94),2)*BS94),2)+ROUND((ROUND(((AE94-(EU94))*AV94*I94),2)*BS94),2)) -> 0 | S94: =ROUND((ROUND((AF94*AV94*I94),2)*BA94),2) -> 0 | T94: =ROUND(CU94*I94,2) -> 0 | U94: =CV94*I94 -> 0 | V94: =CW94*I94 -> 0 | W94: =ROUND(CX94*I94,2) -> 0 | X94: =(ROUND((((S94+ROUND((ROUND(((EU94)*AV94*I94),2)*BS94),2))*AT94)/100),2)+ROUND(((ROUND((ROUND(((AE94-(EU94))*AV94*I94),2)*BS94),2)*AT94)/100),2)) -> 0 | Y94: =(ROUND((((S94+ROUND((ROUND(((EU94)*AV94*I94),2)*BS94),2))*AU94)/100),2)+ROUND(((ROUND((ROUND(((AE94-(EU94))*AV94*I94),2)*BS94),2)*AU94)/100),2)) -> 0 | AA94: 55934357 | AB94: =ROUND((AC94+AD94+AF94),6) -> 23932.38 | AC94: =ROUND((ES94),6) -> 23932.38 | AD94: =ROUND((((ET94)-(EU94))+AE94),6) -> 0 | AE94: =ROUND((EU94),6) -> 0 | AF94: =ROUND((EV94),6) -> 0 | AG94: =ROUND((AP94),6) -> 0 | AH94: =(EW94) -> 0 | AI94: =(EX94) -> 0 | AJ94: =(AS94) -> 0 | AK94: 23932.38 | AL94: 23932.38 | AM94: 0 | AN94: 0 | AO94: 0 | AP94: 0 | AQ94: 0 | AR94: 0 | AS94: 0 | AT94: 0 | AU94: 0 | AV94: 1 | AW94: 1 | AZ94: 1 | BA94: 1 | BB94: 1 | BC94: 7.57 | BH94: 3 | BI94: 3 | BJ94: КА, п.3 | BM94: 400007 | BN94: 0 | BP94: 0 | BQ94: 214 | BR94: 0 | BS94: 1 | BT94: 1 | BU94: 1 | BV94: 1 | BW94: 1 | BX94: 1 | BZ94: 90 | CA94: 46 | CE94: 1566 | CF94: 0 | CG94: 0 | CM94: 0 | CN94: Поправка: Гл.12.Прил.8.п.8. 3_12.00.01.11.001_x000D_ Наименование: При наличии напряженных и стесненных условий производства работ (стесненность, сложность складирования и транспортной логистики и т.п.) для объектов, расположенных в пределах круговой магистральной системы улиц "Садовое кольцо" города Москвы | CO94: 0 | CP94: =(P94+Q94+S94) -> 181168.12 | CQ94: =ROUND((ROUND((AC94*AW94*1),2)*BC94),2) -> 181168.12 | CR94: =(ROUND((ROUND(((ET94)*AV94*1),2)*BB94),2)+ROUND((ROUND(((AE94-(EU94))*AV94*1),2)*BS94),2)) -> 0 | CS94: =(ROUND((ROUND(((EU94)*AV94*1),2)*BS94),2)+ROUND((ROUND(((AE94-(EU94))*AV94*1),2)*BS94),2)) -> 0 | CT94: =ROUND((ROUND((AF94*AV94*1),2)*BA94),2) -> 0 | CU94: =AG94 -> 0 | CV94: =(AH94*AV94) -> 0 | CW94: =AI94 -> 0 | CX94: =AJ94 -> 0 | CY94: =(ROUND((((S94+ROUND((ROUND(((EU94)*AV94*1),2)*BS94),2))*AT94)/100),2)+ROUND(((ROUND((ROUND(((AE94-(EU94))*AV94*1),2)*BS94),2)*AT94)/100),2)) -> 0 | CZ94: =(ROUND((((S94+ROUND((ROUND(((EU94)*AV94*1),2)*BS94),2))*AU94)/100),2)+ROUND(((ROUND((ROUND(((AE94-(EU94))*AV94*1),2)*BS94),2)*AU94)/100),2)) -> 0 | DN94: 0 | DO94: 0 | DP94: 1 | DQ94: 1 | DU94: 1013 | DV94: ШТ | DW94: ШТ | DX94: 1 | EE94: 57042890 | EF94: 214 | EG94: Оборудование, отсутствующие в СНБ | EH94: 0 | EJ94: 3 | EK94: 400007 | EL94: Оборудование, отсутствующие в СНБ | EM94: Оборуд. КА | EO94: Поправка: Гл.12.Прил.8.п.8. 3_12.00.01.11.001 | EQ94: 16 | ER94: 0 | ES94: 23932.38 | ET94: 0 | EU94: 0 | EV94: 0 | EW94: 0 | EX94: 0 | EZ94: 5 | FC94: 1 | FD94: 18 | FF94: 212043 | FQ94: 0 | FR94: =P94 -> 181168.12 | FS94: 0 | FX94: 90 | FY94: 46 | GA94: [212 043 / 1,22 / 7,57] + 3% Трансп + 1,2% Заг.скл | GD94: 1 | GF94: 1942153840 | GG94: 2 | GH94: 3 | GI94: 5 | GJ94: 0 | GK94: 0 | GL94: =ROUND(IF(AND(BH94=3,BI94=3,FS94<>0),P94,0),2) -> 0 | GM94: =ROUND(O94+X94+Y94,2)+GX94 -> 181168.12 | GN94: =IF(OR(BI94=0,BI94=1),GM94-GX94,0) -> 0 | GO94: =IF(BI94=2,GM94-GX94,0) -> 0 | GP94: =IF(BI94=4,GM94-GX94,0) -> 0 | GR94: 1 | GS94: 1 | GT94: 0 | GV94: =ROUND((GT94),6) -> 0 | GW94: 1 | GX94: =ROUND(HC94*I94,2) -> 0 | HA94: 0 | HB94: 0 | HC94: =GV94*GW94 -> 0 | HE94: 3 | HF94: 1,2 | HM94: *1 | HS94: 0 | IK94: 0
A95: 17 | B95: 1 | C95: =ROW(SmtRes!A159) -> 159 | D95: =ROW(EtalonRes!A189) -> 189 | E95: 13 | F95: 4.10-34-5 | G95: Монтаж коммутатора служебной связи | H95: 1 ШТ. | I95: 4 | J95: 0 | K95: 4 | O95: =ROUND(CP95,2) -> 586.88 | P95: =ROUND((ROUND((AC95*AW95*I95),2)*BC95),2) -> 49.4 | Q95: =(ROUND((ROUND((((ET95*1.2))*AV95*I95),2)*BB95),2)+ROUND((ROUND(((AE95-((EU95*1.2)))*AV95*I95),2)*BS95),2)) -> 144.28 | R95: =(ROUND((ROUND((((EU95*1.2))*AV95*I95),2)*BS95),2)+ROUND((ROUND(((AE95-((EU95*1.2)))*AV95*I95),2)*BS95),2)) -> 15.88 | S95: =ROUND((ROUND((AF95*AV95*I95),2)*BA95),2) -> 393.2 | T95: =ROUND(CU95*I95,2) -> 0 | U95: =CV95*I95 -> 31.15872 | V95: =CW95*I95 -> 0 | W95: =ROUND(CX95*I95,2) -> 0 | X95: =(ROUND((((S95+ROUND((ROUND((((EU95*1.2))*AV95*I95),2)*BS95),2))*AT95)/100),2)+ROUND(((ROUND((ROUND(((AE95-((EU95*1.2)))*AV95*I95),2)*BS95),2)*AT95)/100),2)) -> 368.17 | Y95: =(ROUND((((S95+ROUND((ROUND((((EU95*1.2))*AV95*I95),2)*BS95),2))*AU95)/100),2)+ROUND(((ROUND((ROUND(((AE95-((EU95*1.2)))*AV95*I95),2)*BS95),2)*AU95)/100),2)) -> 188.18 | AA95: 55934355 | AB95: =ROUND((AC95+AD95+AF95),6) -> 140.69 | AC95: =ROUND(((ES95*1)),6) -> 12.35 | AD95: =ROUND(((((ET95*1.2))-((EU95*1.2)))+AE95),6) -> 34.452 | AE95: =ROUND(((EU95*1.2)),6) -> 3.792 | AF95: =ROUND(((EV95*1.2)),6) -> 93.888 | AG95: =ROUND((AP95),6) -> 0 | AH95: =((EW95*1.2)) -> 7.44 | AI95: =((EX95*1.2)) -> 0 | AJ95: =(AS95) -> 0 | AK95: 119.3 | AL95: 12.35 | AM95: 28.71 | AN95: 3.16 | AO95: 78.24 | AP95: 0 | AQ95: 6.2 | AR95: 0 | AS95: 0 | AT95: 90 | AU95: 46 | AV95: 1.047 | AW95: 1 | AZ95: 1 | BA95: 1 | BB95: 1 | BC95: 1 | BH95: 0 | BI95: 2 | BJ95: ТСН-2001.4 Доп. 80, Сб. 10, т. 34, поз. 5 | BM95: 68 | BN95: 0 | BO95: 4.10-34-5 | BP95: 1 | BQ95: 40 | BR95: 0 | BS95: 1 | BT95: 1 | BU95: 1 | BV95: 1 | BW95: 1 | BX95: 1 | BZ95: 90 | CA95: 46 | CE95: 1566 | CF95: 0 | CG95: 0 | CM95: 0 | CN95: Поправка: Гл.12.Прил.8.п.8. 3_12.00.01.11.001 Наименование: При наличии напряженных и стесненных условий производства работ (стесненность, сложность складирования и транспортной логистики и т.п.) для объектов, расположенных в пределах круговой магистральной системы улиц "Садовое кольцо" города Москвы | CO95: 0 | CP95: =(P95+Q95+S95) -> 586.88 | CQ95: =ROUND((ROUND((AC95*AW95*1),2)*BC95),2) -> 12.35 | CR95: =(ROUND((ROUND((((ET95*1.2))*AV95*1),2)*BB95),2)+ROUND((ROUND(((AE95-((EU95*1.2)))*AV95*1),2)*BS95),2)) -> 36.07 | CS95: =(ROUND((ROUND((((EU95*1.2))*AV95*1),2)*BS95),2)+ROUND((ROUND(((AE95-((EU95*1.2)))*AV95*1),2)*BS95),2)) -> 3.97 | CT95: =ROUND((ROUND((AF95*AV95*1),2)*BA95),2) -> 98.3 | CU95: =AG95 -> 0 | CV95: =(AH95*AV95) -> 7.78968 | CW95: =AI95 -> 0 | CX95: =AJ95 -> 0 | CY95: =(ROUND((((S95+ROUND((ROUND((((EU95*1.2))*AV95*1),2)*BS95),2))*AT95)/100),2)+ROUND(((ROUND((ROUND(((AE95-((EU95*1.2)))*AV95*1),2)*BS95),2)*AT95)/100),2)) -> 357.45 | CZ95: =(ROUND((((S95+ROUND((ROUND((((EU95*1.2))*AV95*1),2)*BS95),2))*AU95)/100),2)+ROUND(((ROUND((ROUND(((AE95-((EU95*1.2)))*AV95*1),2)*BS95),2)*AU95)/100),2)) -> 182.7 | DB95: 41 | DD95: *1 | DE95: *1,2 | DF95: *1,2 | DG95: *1,2 | DI95: *1,2 | DJ95: *1,2 | DN95: 0 | DO95: 0 | DP95: 1 | DQ95: 1 | DU95: 1013 | DV95: 1 ШТ. | DW95: 1 ШТ. | DX95: 1 | EE95: 57042958 | EF95: 40 | EG95: Монтаж оборудования | EH95: 0 | EJ95: 2 | EK95: 68 | EL95: ТСН-2001.4-10. Прокладка и монтаж сетей связи | EM95: ТСН-2001.4-10-1 | EO95: Поправка: Гл.12.Прил.8.п.8. 3_12.00.01.11.001 | EQ95: 0 | ER95: 119.3 | ES95: 12.35 | ET95: 28.71 | EU95: 3.16 | EV95: 78.24 | EW95: 6.2 | EX95: 0 | EY95: 0 | FQ95: 0 | FR95: 0 | FS95: 0 | FX95: 90 | FY95: 46 | GD95: 1 | GF95: 982292204 | GG95: 2 | GH95: 1 | GI95: 2 | GJ95: 0 | GK95: 0 | GL95: =ROUND(IF(AND(BH95=3,BI95=3,FS95<>0),P95,0),2) -> 0 | GM95: =ROUND(O95+X95+Y95,2)+GX95 -> 1143.23 | GN95: =IF(OR(BI95=0,BI95=1),GM95-GX95,0) -> 0 | GO95: =IF(BI95=2,GM95-GX95,0) -> 1143.23 | GP95: =IF(BI95=4,GM95-GX95,0) -> 0 | GR95: 0 | GS95: 3 | GT95: 0 | GV95: =ROUND((GT95),6) -> 0 | GW95: 1 | GX95: =ROUND(HC95*I95,2) -> 0 | HA95: 0 | HB95: 0 | HC95: =GV95*GW95 -> 0 | HS95: 0 | IK95: 0
A96: 17 | B96: 1 | C96: =ROW(SmtRes!A164) -> 164 | D96: =ROW(EtalonRes!A194) -> 194 | E96: 13 | F96: 4.10-34-5 | G96: Монтаж коммутатора служебной связи | H96: 1 ШТ. | I96: 4 | J96: 0 | K96: 4 | O96: =ROUND(CP96,2) -> 25214.56 | P96: =ROUND((ROUND((AC96*AW96*I96),2)*BC96),2) -> 726.18 | Q96: =(ROUND((ROUND((((ET96*1.2))*AV96*I96),2)*BB96),2)+ROUND((ROUND(((AE96-((EU96*1.2)))*AV96*I96),2)*BS96),2)) -> 2331.56 | R96: =(ROUND((ROUND((((EU96*1.2))*AV96*I96),2)*BS96),2)+ROUND((ROUND(((AE96-((EU96*1.2)))*AV96*I96),2)*BS96),2)) -> 894.84 | S96: =ROUND((ROUND((AF96*AV96*I96),2)*BA96),2) -> 22156.82 | T96: =ROUND(CU96*I96,2) -> 0 | U96: =CV96*I96 -> 31.15872 | V96: =CW96*I96 -> 0 | W96: =ROUND(CX96*I96,2) -> 0 | X96: =(ROUND((((S96+ROUND((ROUND((((EU96*1.2))*AV96*I96),2)*BS96),2))*AT96)/100),2)+ROUND(((ROUND((ROUND(((AE96-((EU96*1.2)))*AV96*I96),2)*BS96),2)*AT96)/100),2)) -> 20746.49 | Y96: =(ROUND((((S96+ROUND((ROUND((((EU96*1.2))*AV96*I96),2)*BS96),2))*AU96)/100),2)+ROUND(((ROUND((ROUND(((AE96-((EU96*1.2)))*AV96*I96),2)*BS96),2)*AU96)/100),2)) -> 10603.76 | AA96: 55934357 | AB96: =ROUND((AC96+AD96+AF96),6) -> 140.69 | AC96: =ROUND(((ES96*1)),6) -> 12.35 | AD96: =ROUND(((((ET96*1.2))-((EU96*1.2)))+AE96),6) -> 34.452 | AE96: =ROUND(((EU96*1.2)),6) -> 3.792 | AF96: =ROUND(((EV96*1.2)),6) -> 93.888 | AG96: =ROUND((AP96),6) -> 0 | AH96: =((EW96*1.2)) -> 7.44 | AI96: =((EX96*1.2)) -> 0 | AJ96: =(AS96) -> 0 | AK96: 119.3 | AL96: 12.35 | AM96: 28.71 | AN96: 3.16 | AO96: 78.24 | AP96: 0 | AQ96: 6.2 | AR96: 0 | AS96: 0 | AT96: 90 | AU96: 46 | AV96: 1.047 | AW96: 1 | AZ96: 1 | BA96: 56.35 | BB96: 16.16 | BC96: 14.7 | BH96: 0 | BI96: 2 | BJ96: ТСН-2001.4 Доп. 80, Сб. 10, т. 34, поз. 5 | BM96: 68 | BN96: 0 | BO96: 4.10-34-5 | BP96: 1 | BQ96: 40 | BR96: 0 | BS96: 56.35 | BT96: 1 | BU96: 1 | BV96: 1 | BW96: 1 | BX96: 1 | BZ96: 90 | CA96: 46 | CE96: 1566 | CF96: 0 | CG96: 0 | CM96: 0 | CN96: Поправка: Гл.12.Прил.8.п.8. 3_12.00.01.11.001 Наименование: При наличии напряженных и стесненных условий производства работ (стесненность, сложность складирования и транспортной логистики и т.п.) для объектов, расположенных в пределах круговой магистральной системы улиц "Садовое кольцо" города Москвы | CO96: 0 | CP96: =(P96+Q96+S96) -> 25214.56 | CQ96: =ROUND((ROUND((AC96*AW96*1),2)*BC96),2) -> 181.55 | CR96: =(ROUND((ROUND((((ET96*1.2))*AV96*1),2)*BB96),2)+ROUND((ROUND(((AE96-((EU96*1.2)))*AV96*1),2)*BS96),2)) -> 582.89 | CS96: =(ROUND((ROUND((((EU96*1.2))*AV96*1),2)*BS96),2)+ROUND((ROUND(((AE96-((EU96*1.2)))*AV96*1),2)*BS96),2)) -> 223.71 | CT96: =ROUND((ROUND((AF96*AV96*1),2)*BA96),2) -> 5539.21 | CU96: =AG96 -> 0 | CV96: =(AH96*AV96) -> 7.78968 | CW96: =AI96 -> 0 | CX96: =AJ96 -> 0 | CY96: =(ROUND((((S96+ROUND((ROUND((((EU96*1.2))*AV96*1),2)*BS96),2))*AT96)/100),2)+ROUND(((ROUND((ROUND(((AE96-((EU96*1.2)))*AV96*1),2)*BS96),2)*AT96)/100),2)) -> 20142.48 | CZ96: =(ROUND((((S96+ROUND((ROUND((((EU96*1.2))*AV96*1),2)*BS96),2))*AU96)/100),2)+ROUND(((ROUND((ROUND(((AE96-((EU96*1.2)))*AV96*1),2)*BS96),2)*AU96)/100),2)) -> 10295.04 | DB96: 42 | DD96: *1 | DE96: *1,2 | DF96: *1,2 | DG96: *1,2 | DI96: *1,2 | DJ96: *1,2 | DN96: 0 | DO96: 0 | DP96: 1 | DQ96: 1 | DU96: 1013 | DV96: 1 ШТ. | DW96: 1 ШТ. | DX96: 1 | EE96: 57042958 | EF96: 40 | EG96: Монтаж оборудования | EH96: 0 | EJ96: 2 | EK96: 68 | EL96: ТСН-2001.4-10. Прокладка и монтаж сетей связи | EM96: ТСН-2001.4-10-1 | EO96: Поправка: Гл.12.Прил.8.п.8. 3_12.00.01.11.001 | EQ96: 0 | ER96: 119.3 | ES96: 12.35 | ET96: 28.71 | EU96: 3.16 | EV96: 78.24 | EW96: 6.2 | EX96: 0 | EY96: 0 | FQ96: 0 | FR96: 0 | FS96: 0 | FX96: 90 | FY96: 46 | GD96: 1 | GF96: 982292204 | GG96: 2 | GH96: 1 | GI96: 2 | GJ96: 0 | GK96: 0 | GL96: =ROUND(IF(AND(BH96=3,BI96=3,FS96<>0),P96,0),2) -> 0 | GM96: =ROUND(O96+X96+Y96,2)+GX96 -> 56564.81 | GN96: =IF(OR(BI96=0,BI96=1),GM96-GX96,0) -> 0 | GO96: =IF(BI96=2,GM96-GX96,0) -> 56564.81 | GP96: =IF(BI96=4,GM96-GX96,0) -> 0 | GR96: 0 | GS96: 3 | GT96: 0 | GV96: =ROUND((GT96),6) -> 0 | GW96: 1 | GX96: =ROUND(HC96*I96,2) -> 0 | HA96: 0 | HB96: 0 | HC96: =GV96*GW96 -> 0 | HS96: 0 | IK96: 0
A97: 18 | B97: 1 | C97: 159 | E97: 13,1 | F97: КА, п.4 | G97: Управляемый коммутатор уровня L3:24х10/100/1000BASE-T (RJ-45) PoE/PoE+; 4х10G BASE-X(SFP) MES2324P | H97: ШТ | I97: =I95*J97 -> 4 | J97: 1 | K97: 1 | O97: =ROUND(CP97,2) -> 84607.72 | P97: =ROUND((ROUND((AC97*AW97*I97),2)*BC97),2) -> 84607.72 | Q97: =(ROUND((ROUND(((ET97)*AV97*I97),2)*BB97),2)+ROUND((ROUND(((AE97-(EU97))*AV97*I97),2)*BS97),2)) -> 0 | R97: =(ROUND((ROUND(((EU97)*AV97*I97),2)*BS97),2)+ROUND((ROUND(((AE97-(EU97))*AV97*I97),2)*BS97),2)) -> 0 | S97: =ROUND((ROUND((AF97*AV97*I97),2)*BA97),2) -> 0 | T97: =ROUND(CU97*I97,2) -> 0 | U97: =CV97*I97 -> 0 | V97: =CW97*I97 -> 0 | W97: =ROUND(CX97*I97,2) -> 0 | X97: =(ROUND((((S97+ROUND((ROUND(((EU97)*AV97*I97),2)*BS97),2))*AT97)/100),2)+ROUND(((ROUND((ROUND(((AE97-(EU97))*AV97*I97),2)*BS97),2)*AT97)/100),2)) -> 0 | Y97: =(ROUND((((S97+ROUND((ROUND(((EU97)*AV97*I97),2)*BS97),2))*AU97)/100),2)+ROUND(((ROUND((ROUND(((AE97-(EU97))*AV97*I97),2)*BS97),2)*AU97)/100),2)) -> 0 | AA97: 55934355 | AB97: =ROUND((AC97+AD97+AF97),6) -> 21151.93 | AC97: =ROUND((ES97),6) -> 21151.93 | AD97: =ROUND((((ET97)-(EU97))+AE97),6) -> 0 | AE97: =ROUND((EU97),6) -> 0 | AF97: =ROUND((EV97),6) -> 0 | AG97: =ROUND((AP97),6) -> 0 | AH97: =(EW97) -> 0 | AI97: =(EX97) -> 0 | AJ97: =(AS97) -> 0 | AK97: 21151.93 | AL97: 21151.93 | AM97: 0 | AN97: 0 | AO97: 0 | AP97: 0 | AQ97: 0 | AR97: 0 | AS97: 0 | AT97: 0 | AU97: 0 | AV97: 1 | AW97: 1 | AZ97: 1 | BA97: 1 | BB97: 1 | BC97: 1 | BH97: 3 | BI97: 3 | BJ97: КА, п.4 | BM97: 400007 | BN97: 0 | BP97: 0 | BQ97: 214 | BR97: 0 | BS97: 1 | BT97: 1 | BU97: 1 | BV97: 1 | BW97: 1 | BX97: 1 | BZ97: 90 | CA97: 46 | CE97: 1566 | CF97: 0 | CG97: 0 | CM97: 0 | CN97: Поправка: Гл.12.Прил.8.п.8. 3_12.00.01.11.001_x000D_ Наименование: При наличии напряженных и стесненных условий производства работ (стесненность, сложность складирования и транспортной логистики и т.п.) для объектов, расположенных в пределах круговой магистральной системы улиц "Садовое кольцо" города Москвы | CO97: 0 | CP97: =(P97+Q97+S97) -> 84607.72 | CQ97: =ROUND((ROUND((AC97*AW97*1),2)*BC97),2) -> 21151.93 | CR97: =(ROUND((ROUND(((ET97)*AV97*1),2)*BB97),2)+ROUND((ROUND(((AE97-(EU97))*AV97*1),2)*BS97),2)) -> 0 | CS97: =(ROUND((ROUND(((EU97)*AV97*1),2)*BS97),2)+ROUND((ROUND(((AE97-(EU97))*AV97*1),2)*BS97),2)) -> 0 | CT97: =ROUND((ROUND((AF97*AV97*1),2)*BA97),2) -> 0 | CU97: =AG97 -> 0 | CV97: =(AH97*AV97) -> 0 | CW97: =AI97 -> 0 | CX97: =AJ97 -> 0 | CY97: =(ROUND((((S97+ROUND((ROUND(((EU97)*AV97*1),2)*BS97),2))*AT97)/100),2)+ROUND(((ROUND((ROUND(((AE97-(EU97))*AV97*1),2)*BS97),2)*AT97)/100),2)) -> 0 | CZ97: =(ROUND((((S97+ROUND((ROUND(((EU97)*AV97*1),2)*BS97),2))*AU97)/100),2)+ROUND(((ROUND((ROUND(((AE97-(EU97))*AV97*1),2)*BS97),2)*AU97)/100),2)) -> 0 | DN97: 0 | DO97: 0 | DP97: 1 | DQ97: 1 | DU97: 1013 | DV97: ШТ | DW97: ШТ | DX97: 1 | EE97: 57042890 | EF97: 214 | EG97: Оборудование, отсутствующие в СНБ | EH97: 0 | EJ97: 3 | EK97: 400007 | EL97: Оборудование, отсутствующие в СНБ | EM97: Оборуд. КА | EO97: Поправка: Гл.12.Прил.8.п.8. 3_12.00.01.11.001 | EQ97: 16 | ER97: 0 | ES97: 21151.93 | ET97: 0 | EU97: 0 | EV97: 0 | EW97: 0 | EX97: 0 | FQ97: 0 | FR97: =P97 -> 84607.72 | FS97: 0 | FX97: 90 | FY97: 46 | GA97: [187 408 / 1,22 / 7,57] + 3% Трансп + 1,2% Заг.скл | GD97: 1 | GF97: -977076452 | GG97: 2 | GH97: 4 | GI97: -2 | GJ97: 0 | GK97: 0 | GL97: =ROUND(IF(AND(BH97=3,BI97=3,FS97<>0),P97,0),2) -> 0 | GM97: =ROUND(O97+X97+Y97,2)+GX97 -> 84607.72 | GN97: =IF(OR(BI97=0,BI97=1),GM97-GX97,0) -> 0 | GO97: =IF(BI97=2,GM97-GX97,0) -> 0 | GP97: =IF(BI97=4,GM97-GX97,0) -> 0 | GR97: 1 | GS97: 2 | GT97: 0 | GV97: =ROUND((GT97),6) -> 0 | GW97: 1 | GX97: =ROUND(HC97*I97,2) -> 0 | HA97: 0 | HB97: 0 | HC97: =GV97*GW97 -> 0 | HE97: 3 | HF97: 1,2 | HM97: *1 | HS97: 0 | IK97: 0
A98: 18 | B98: 1 | C98: 164 | E98: 13,1 | F98: КА, п.4 | G98: Управляемый коммутатор уровня L3:24х10/100/1000BASE-T (RJ-45) PoE/PoE+; 4х10G BASE-X(SFP) MES2324P | H98: ШТ | I98: =I96*J98 -> 4 | J98: 1 | K98: 1 | O98: =ROUND(CP98,2) -> 640480.44 | P98: =ROUND((ROUND((AC98*AW98*I98),2)*BC98),2) -> 640480.44 | Q98: =(ROUND((ROUND(((ET98)*AV98*I98),2)*BB98),2)+ROUND((ROUND(((AE98-(EU98))*AV98*I98),2)*BS98),2)) -> 0 | R98: =(ROUND((ROUND(((EU98)*AV98*I98),2)*BS98),2)+ROUND((ROUND(((AE98-(EU98))*AV98*I98),2)*BS98),2)) -> 0 | S98: =ROUND((ROUND((AF98*AV98*I98),2)*BA98),2) -> 0 | T98: =ROUND(CU98*I98,2) -> 0 | U98: =CV98*I98 -> 0 | V98: =CW98*I98 -> 0 | W98: =ROUND(CX98*I98,2) -> 0 | X98: =(ROUND((((S98+ROUND((ROUND(((EU98)*AV98*I98),2)*BS98),2))*AT98)/100),2)+ROUND(((ROUND((ROUND(((AE98-(EU98))*AV98*I98),2)*BS98),2)*AT98)/100),2)) -> 0 | Y98: =(ROUND((((S98+ROUND((ROUND(((EU98)*AV98*I98),2)*BS98),2))*AU98)/100),2)+ROUND(((ROUND((ROUND(((AE98-(EU98))*AV98*I98),2)*BS98),2)*AU98)/100),2)) -> 0 | AA98: 55934357 | AB98: =ROUND((AC98+AD98+AF98),6) -> 21151.93 | AC98: =ROUND((ES98),6) -> 21151.93 | AD98: =ROUND((((ET98)-(EU98))+AE98),6) -> 0 | AE98: =ROUND((EU98),6) -> 0 | AF98: =ROUND((EV98),6) -> 0 | AG98: =ROUND((AP98),6) -> 0 | AH98: =(EW98) -> 0 | AI98: =(EX98) -> 0 | AJ98: =(AS98) -> 0 | AK98: 21151.93 | AL98: 21151.93 | AM98: 0 | AN98: 0 | AO98: 0 | AP98: 0 | AQ98: 0 | AR98: 0 | AS98: 0 | AT98: 0 | AU98: 0 | AV98: 1 | AW98: 1 | AZ98: 1 | BA98: 1 | BB98: 1 | BC98: 7.57 | BH98: 3 | BI98: 3 | BJ98: КА, п.4 | BM98: 400007 | BN98: 0 | BP98: 0 | BQ98: 214 | BR98: 0 | BS98: 1 | BT98: 1 | BU98: 1 | BV98: 1 | BW98: 1 | BX98: 1 | BZ98: 90 | CA98: 46 | CE98: 1566 | CF98: 0 | CG98: 0 | CM98: 0 | CN98: Поправка: Гл.12.Прил.8.п.8. 3_12.00.01.11.001_x000D_ Наименование: При наличии напряженных и стесненных условий производства работ (стесненность, сложность складирования и транспортной логистики и т.п.) для объектов, расположенных в пределах круговой магистральной системы улиц "Садовое кольцо" города Москвы | CO98: 0 | CP98: =(P98+Q98+S98) -> 640480.44 | CQ98: =ROUND((ROUND((AC98*AW98*1),2)*BC98),2) -> 160120.11 | CR98: =(ROUND((ROUND(((ET98)*AV98*1),2)*BB98),2)+ROUND((ROUND(((AE98-(EU98))*AV98*1),2)*BS98),2)) -> 0 | CS98: =(ROUND((ROUND(((EU98)*AV98*1),2)*BS98),2)+ROUND((ROUND(((AE98-(EU98))*AV98*1),2)*BS98),2)) -> 0 | CT98: =ROUND((ROUND((AF98*AV98*1),2)*BA98),2) -> 0 | CU98: =AG98 -> 0 | CV98: =(AH98*AV98) -> 0 | CW98: =AI98 -> 0 | CX98: =AJ98 -> 0 | CY98: =(ROUND((((S98+ROUND((ROUND(((EU98)*AV98*1),2)*BS98),2))*AT98)/100),2)+ROUND(((ROUND((ROUND(((AE98-(EU98))*AV98*1),2)*BS98),2)*AT98)/100),2)) -> 0 | CZ98: =(ROUND((((S98+ROUND((ROUND(((EU98)*AV98*1),2)*BS98),2))*AU98)/100),2)+ROUND(((ROUND((ROUND(((AE98-(EU98))*AV98*1),2)*BS98),2)*AU98)/100),2)) -> 0 | DN98: 0 | DO98: 0 | DP98: 1 | DQ98: 1 | DU98: 1013 | DV98: ШТ | DW98: ШТ | DX98: 1 | EE98: 57042890 | EF98: 214 | EG98: Оборудование, отсутствующие в СНБ | EH98: 0 | EJ98: 3 | EK98: 400007 | EL98: Оборудование, отсутствующие в СНБ | EM98: Оборуд. КА | EO98: Поправка: Гл.12.Прил.8.п.8. 3_12.00.01.11.001 | EQ98: 16 | ER98: 0 | ES98: 21151.93 | ET98: 0 | EU98: 0 | EV98: 0 | EW98: 0 | EX98: 0 | EZ98: 5 | FC98: 1 | FD98: 18 | FF98: 187408 | FQ98: 0 | FR98: =P98 -> 640480.44 | FS98: 0 | FX98: 90 | FY98: 46 | GA98: [187 408 / 1,22 / 7,57] + 3% Трансп + 1,2% Заг.скл | GD98: 1 | GF98: -977076452 | GG98: 2 | GH98: 3 | GI98: 5 | GJ98: 0 | GK98: 0 | GL98: =ROUND(IF(AND(BH98=3,BI98=3,FS98<>0),P98,0),2) -> 0 | GM98: =ROUND(O98+X98+Y98,2)+GX98 -> 640480.44 | GN98: =IF(OR(BI98=0,BI98=1),GM98-GX98,0) -> 0 | GO98: =IF(BI98=2,GM98-GX98,0) -> 0 | GP98: =IF(BI98=4,GM98-GX98,0) -> 0 | GR98: 1 | GS98: 1 | GT98: 0 | GV98: =ROUND((GT98),6) -> 0 | GW98: 1 | GX98: =ROUND(HC98*I98,2) -> 0 | HA98: 0 | HB98: 0 | HC98: =GV98*GW98 -> 0 | HE98: 3 | HF98: 1,2 | HM98: *1 | HS98: 0 | IK98: 0
A99: 17 | B99: 1 | C99: =ROW(SmtRes!A165) -> 165 | D99: =ROW(EtalonRes!A195) -> 195 | F99: 4.10-35-2 | G99: Электрическая проверка и настройка коммутатора всех назначений, кроме междугородного | H99: 1 рабочее место | I99: =ROUND(1+4,9) -> 5 | J99: 0 | K99: =ROUND(1+4,9) -> 5 | O99: =ROUND(CP99,2) -> 2100.83 | P99: =ROUND((ROUND((AC99*AW99*I99),2)*BC99),2) -> 0 | Q99: =(ROUND((ROUND((((ET99*1.2))*AV99*I99),2)*BB99),2)+ROUND((ROUND(((AE99-((EU99*1.2)))*AV99*I99),2)*BS99),2)) -> 0 | R99: =(ROUND((ROUND((((EU99*1.2))*AV99*I99),2)*BS99),2)+ROUND((ROUND(((AE99-((EU99*1.2)))*AV99*I99),2)*BS99),2)) -> 0 | S99: =ROUND((ROUND((AF99*AV99*I99),2)*BA99),2) -> 2100.83 | T99: =ROUND(CU99*I99,2) -> 0 | U99: =CV99*I99 -> 144.486 | V99: =CW99*I99 -> 0 | W99: =ROUND(CX99*I99,2) -> 0 | X99: =(ROUND((((S99+ROUND((ROUND((((EU99*1.2))*AV99*I99),2)*BS99),2))*AT99)/100),2)+ROUND(((ROUND((ROUND(((AE99-((EU99*1.2)))*AV99*I99),2)*BS99),2)*AT99)/100),2)) -> 1890.75 | Y99: =(ROUND((((S99+ROUND((ROUND((((EU99*1.2))*AV99*I99),2)*BS99),2))*AU99)/100),2)+ROUND(((ROUND((ROUND(((AE99-((EU99*1.2)))*AV99*I99),2)*BS99),2)*AU99)/100),2)) -> 966.38 | AA99: -1 | AB99: =ROUND((AC99+AD99+AF99),6) -> 401.304 | AC99: =ROUND(((ES99*1)),6) -> 0 | AD99: =ROUND(((((ET99*1.2))-((EU99*1.2)))+AE99),6) -> 0 | AE99: =ROUND(((EU99*1.2)),6) -> 0 | AF99: =ROUND(((EV99*1.2)),6) -> 401.304 | AG99: =ROUND((AP99),6) -> 0 | AH99: =((EW99*1.2)) -> 27.6 | AI99: =((EX99*1.2)) -> 0 | AJ99: =(AS99) -> 0 | AK99: 334.42 | AL99: 0 | AM99: 0 | AN99: 0 | AO99: 334.42 | AP99: 0 | AQ99: 23 | AR99: 0 | AS99: 0 | AT99: 90 | AU99: 46 | AV99: 1.047 | AW99: 1 | AZ99: 1 | BA99: 1 | BB99: 1 | BC99: 1 | BH99: 0 | BI99: 2 | BJ99: ТСН-2001.4 Доп. 67, Сб. 10, т. 35, поз. 2 | BM99: 192 | BN99: 0 | BO99: 4.10-35-2 | BP99: 1 | BQ99: 40 | BR99: 0 | BS99: 1 | BT99: 1 | BU99: 1 | BV99: 1 | BW99: 1 | BX99: 1 | BZ99: 90 | CA99: 46 | CE99: 1566 | CF99: 0 | CG99: 0 | CM99: 0 | CN99: Поправка: Гл.12.Прил.8.п.8. 3_12.00.01.11.001 Наименование: При наличии напряженных и стесненных условий производства работ (стесненность, сложность складирования и транспортной логистики и т.п.) для объектов, расположенных в пределах круговой магистральной системы улиц "Садовое кольцо" города Москвы | CO99: 0 | CP99: =(P99+Q99+S99) -> 2100.83 | CQ99: =ROUND((ROUND((AC99*AW99*1),2)*BC99),2) -> 0 | CR99: =(ROUND((ROUND((((ET99*1.2))*AV99*1),2)*BB99),2)+ROUND((ROUND(((AE99-((EU99*1.2)))*AV99*1),2)*BS99),2)) -> 0 | CS99: =(ROUND((ROUND((((EU99*1.2))*AV99*1),2)*BS99),2)+ROUND((ROUND(((AE99-((EU99*1.2)))*AV99*1),2)*BS99),2)) -> 0 | CT99: =ROUND((ROUND((AF99*AV99*1),2)*BA99),2) -> 420.17 | CU99: =AG99 -> 0 | CV99: =(AH99*AV99) -> 28.8972 | CW99: =AI99 -> 0 | CX99: =AJ99 -> 0 | CY99: =(ROUND((((S99+ROUND((ROUND((((EU99*1.2))*AV99*1),2)*BS99),2))*AT99)/100),2)+ROUND(((ROUND((ROUND(((AE99-((EU99*1.2)))*AV99*1),2)*BS99),2)*AT99)/100),2)) -> 1890.75 | CZ99: =(ROUND((((S99+ROUND((ROUND((((EU99*1.2))*AV99*1),2)*BS99),2))*AU99)/100),2)+ROUND(((ROUND((ROUND(((AE99-((EU99*1.2)))*AV99*1),2)*BS99),2)*AU99)/100),2)) -> 966.38 | DB99: 43 | DD99: *1 | DE99: *1,2 | DF99: *1,2 | DG99: *1,2 | DI99: *1,2 | DJ99: *1,2 | DN99: 0 | DO99: 0 | DP99: 1 | DQ99: 1 | DU99: 1013 | DV99: 1 рабочее место | DW99: 1 рабочее место | DX99: 1 | EE99: 57043089 | EF99: 40 | EG99: Монтаж оборудования | EH99: 0 | EJ99: 2 | EK99: 192 | EL99: ТСН-2001.4-10. Прокладка и монтаж сетей связи | EM99: ТСН-2001.4-10-5 | EO99: Поправка: Гл.12.Прил.8.п.8. 3_12.00.01.11.001 | EQ99: 1024 | ER99: 334.42 | ES99: 0 | ET99: 0 | EU99: 0 | EV99: 334.42 | EW99: 23 | EX99: 0 | EY99: 0 | FQ99: 0 | FR99: 0 | FS99: 0 | FX99: 90 | FY99: 46 | GD99: 1 | GF99: 1839118886 | GG99: 2 | GH99: 1 | GI99: 2 | GJ99: 0 | GK99: 0 | GL99: =ROUND(IF(AND(BH99=3,BI99=3,FS99<>0),P99,0),2) -> 0 | GM99: =ROUND(O99+X99+Y99,2)+GX99 -> 4957.96 | GN99: =IF(OR(BI99=0,BI99=1),GM99-GX99,0) -> 0 | GO99: =IF(BI99=2,GM99-GX99,0) -> 4957.96 | GP99: =IF(BI99=4,GM99-GX99,0) -> 0 | GR99: 0 | GS99: 3 | GT99: 0 | GV99: =ROUND((GT99),6) -> 0 | GW99: 1 | GX99: =ROUND(HC99*I99,2) -> 0 | HA99: 0 | HB99: 0 | HC99: =GV99*GW99 -> 0 | HS99: 0 | IK99: 0
A100: 17 | B100: 1 | C100: =ROW(SmtRes!A166) -> 166 | D100: =ROW(EtalonRes!A196) -> 196 | F100: 4.10-35-2 | G100: Электрическая проверка и настройка коммутатора всех назначений, кроме междугородного | H100: 1 рабочее место | I100: =ROUND(1+4,9) -> 5 | J100: 0 | K100: =ROUND(1+4,9) -> 5 | O100: =ROUND(CP100,2) -> 118381.77 | P100: =ROUND((ROUND((AC100*AW100*I100),2)*BC100),2) -> 0 | Q100: =(ROUND((ROUND((((ET100*1.2))*AV100*I100),2)*BB100),2)+ROUND((ROUND(((AE100-((EU100*1.2)))*AV100*I100),2)*BS100),2)) -> 0 | R100: =(ROUND((ROUND((((EU100*1.2))*AV100*I100),2)*BS100),2)+ROUND((ROUND(((AE100-((EU100*1.2)))*AV100*I100),2)*BS100),2)) -> 0 | S100: =ROUND((ROUND((AF100*AV100*I100),2)*BA100),2) -> 118381.77 | T100: =ROUND(CU100*I100,2) -> 0 | U100: =CV100*I100 -> 144.486 | V100: =CW100*I100 -> 0 | W100: =ROUND(CX100*I100,2) -> 0 | X100: =(ROUND((((S100+ROUND((ROUND((((EU100*1.2))*AV100*I100),2)*BS100),2))*AT100)/100),2)+ROUND(((ROUND((ROUND(((AE100-((EU100*1.2)))*AV100*I100),2)*BS100),2)*AT100)/100),2)) -> 106543.59 | Y100: =(ROUND((((S100+ROUND((ROUND((((EU100*1.2))*AV100*I100),2)*BS100),2))*AU100)/100),2)+ROUND(((ROUND((ROUND(((AE100-((EU100*1.2)))*AV100*I100),2)*BS100),2)*AU100)/100),2)) -> 54455.61 | AA100: -1 | AB100: =ROUND((AC100+AD100+AF100),6) -> 401.304 | AC100: =ROUND(((ES100*1)),6) -> 0 | AD100: =ROUND(((((ET100*1.2))-((EU100*1.2)))+AE100),6) -> 0 | AE100: =ROUND(((EU100*1.2)),6) -> 0 | AF100: =ROUND(((EV100*1.2)),6) -> 401.304 | AG100: =ROUND((AP100),6) -> 0 | AH100: =((EW100*1.2)) -> 27.6 | AI100: =((EX100*1.2)) -> 0 | AJ100: =(AS100) -> 0 | AK100: 334.42 | AL100: 0 | AM100: 0 | AN100: 0 | AO100: 334.42 | AP100: 0 | AQ100: 23 | AR100: 0 | AS100: 0 | AT100: 90 | AU100: 46 | AV100: 1.047 | AW100: 1 | AZ100: 1 | BA100: 56.35 | BB100: 1 | BC100: 1 | BH100: 0 | BI100: 2 | BJ100: ТСН-2001.4 Доп. 67, Сб. 10, т. 35, поз. 2 | BM100: 192 | BN100: 0 | BO100: 4.10-35-2 | BP100: 1 | BQ100: 40 | BR100: 0 | BS100: 56.35 | BT100: 1 | BU100: 1 | BV100: 1 | BW100: 1 | BX100: 1 | BZ100: 90 | CA100: 46 | CE100: 1566 | CF100: 0 | CG100: 0 | CM100: 0 | CN100: Поправка: Гл.12.Прил.8.п.8. 3_12.00.01.11.001 Наименование: При наличии напряженных и стесненных условий производства работ (стесненность, сложность складирования и транспортной логистики и т.п.) для объектов, расположенных в пределах круговой магистральной системы улиц "Садовое кольцо" города Москвы | CO100: 0 | CP100: =(P100+Q100+S100) -> 118381.77 | CQ100: =ROUND((ROUND((AC100*AW100*1),2)*BC100),2) -> 0 | CR100: =(ROUND((ROUND((((ET100*1.2))*AV100*1),2)*BB100),2)+ROUND((ROUND(((AE100-((EU100*1.2)))*AV100*1),2)*BS100),2)) -> 0 | CS100: =(ROUND((ROUND((((EU100*1.2))*AV100*1),2)*BS100),2)+ROUND((ROUND(((AE100-((EU100*1.2)))*AV100*1),2)*BS100),2)) -> 0 | CT100: =ROUND((ROUND((AF100*AV100*1),2)*BA100),2) -> 23676.58 | CU100: =AG100 -> 0 | CV100: =(AH100*AV100) -> 28.8972 | CW100: =AI100 -> 0 | CX100: =AJ100 -> 0 | CY100: =(ROUND((((S100+ROUND((ROUND((((EU100*1.2))*AV100*1),2)*BS100),2))*AT100)/100),2)+ROUND(((ROUND((ROUND(((AE100-((EU100*1.2)))*AV100*1),2)*BS100),2)*AT100)/100),2)) -> 106543.59 | CZ100: =(ROUND((((S100+ROUND((ROUND((((EU100*1.2))*AV100*1),2)*BS100),2))*AU100)/100),2)+ROUND(((ROUND((ROUND(((AE100-((EU100*1.2)))*AV100*1),2)*BS100),2)*AU100)/100),2)) -> 54455.61 | DB100: 44 | DD100: *1 | DE100: *1,2 | DF100: *1,2 | DG100: *1,2 | DI100: *1,2 | DJ100: *1,2 | DN100: 0 | DO100: 0 | DP100: 1 | DQ100: 1 | DU100: 1013 | DV100: 1 рабочее место | DW100: 1 рабочее место | DX100: 1 | EE100: 57043089 | EF100: 40 | EG100: Монтаж оборудования | EH100: 0 | EJ100: 2 | EK100: 192 | EL100: ТСН-2001.4-10. Прокладка и монтаж сетей связи | EM100: ТСН-2001.4-10-5 | EO100: Поправка: Гл.12.Прил.8.п.8. 3_12.00.01.11.001 | EQ100: 1024 | ER100: 334.42 | ES100: 0 | ET100: 0 | EU100: 0 | EV100: 334.42 | EW100: 23 | EX100: 0 | EY100: 0 | FQ100: 0 | FR100: 0 | FS100: 0 | FX100: 90 | FY100: 46 | GD100: 1 | GF100: 1839118886 | GG100: 2 | GH100: 1 | GI100: 2 | GJ100: 0 | GK100: 0 | GL100: =ROUND(IF(AND(BH100=3,BI100=3,FS100<>0),P100,0),2) -> 0 | GM100: =ROUND(O100+X100+Y100,2)+GX100 -> 279380.97 | GN100: =IF(OR(BI100=0,BI100=1),GM100-GX100,0) -> 0 | GO100: =IF(BI100=2,GM100-GX100,0) -> 279380.97 | GP100: =IF(BI100=4,GM100-GX100,0) -> 0 | GR100: 0 | GS100: 3 | GT100: 0 | GV100: =ROUND((GT100),6) -> 0 | GW100: 1 | GX100: =ROUND(HC100*I100,2) -> 0 | HA100: 0 | HB100: 0 | HC100: =GV100*GW100 -> 0 | HS100: 0 | IK100: 0
A101: 17 | B101: 1 | C101: =ROW(SmtRes!A171) -> 171 | D101: =ROW(EtalonRes!A203) -> 203 | E101: 14 | F101: 4.10-72-14 | G101: Монтаж устройства цифровой регистрации | H101: 1 устройство | I101: 1 | J101: 0 | K101: 1 | O101: =ROUND(CP101,2) -> 120.61 | P101: =ROUND((ROUND((AC101*AW101*I101),2)*BC101),2) -> 1.1 | Q101: =(ROUND((ROUND((((ET101*1.2))*AV101*I101),2)*BB101),2)+ROUND((ROUND(((AE101-((EU101*1.2)))*AV101*I101),2)*BS101),2)) -> 0 | R101: =(ROUND((ROUND((((EU101*1.2))*AV101*I101),2)*BS101),2)+ROUND((ROUND(((AE101-((EU101*1.2)))*AV101*I101),2)*BS101),2)) -> 0 | S101: =ROUND((ROUND((AF101*AV101*I101),2)*BA101),2) -> 119.51 | T101: =ROUND(CU101*I101,2) -> 0 | U101: =CV101*I101 -> 10.0512 | V101: =CW101*I101 -> 0 | W101: =ROUND(CX101*I101,2) -> 0 | X101: =(ROUND((((S101+ROUND((ROUND((((EU101*1.2))*AV101*I101),2)*BS101),2))*AT101)/100),2)+ROUND(((ROUND((ROUND(((AE101-((EU101*1.2)))*AV101*I101),2)*BS101),2)*AT101)/100),2)) -> 113.53 | Y101: =(ROUND((((S101+ROUND((ROUND((((EU101*1.2))*AV101*I101),2)*BS101),2))*AU101)/100),2)+ROUND(((ROUND((ROUND(((AE101-((EU101*1.2)))*AV101*I101),2)*BS101),2)*AU101)/100),2)) -> 63.34 | AA101: 55934355 | AB101: =ROUND((AC101+AD101+AF101),6) -> 115.244 | AC101: =ROUND(((ES101*1)),6) -> 1.1 | AD101: =ROUND(((((ET101*1.2))-((EU101*1.2)))+AE101),6) -> 0 | AE101: =ROUND(((EU101*1.2)),6) -> 0 | AF101: =ROUND(((EV101*1.2)),6) -> 114.144 | AG101: =ROUND((AP101),6) -> 0 | AH101: =((EW101*1.2)) -> 9.6 | AI101: =((EX101*1.2)) -> 0 | AJ101: =(AS101) -> 0 | AK101: 96.22 | AL101: 1.1 | AM101: 0 | AN101: 0 | AO101: 95.12 | AP101: 0 | AQ101: 8 | AR101: 0 | AS101: 0 | AT101: 95 | AU101: 53 | AV101: 1.047 | AW101: 1 | AZ101: 1 | BA101: 1 | BB101: 1 | BC101: 1 | BH101: 0 | BI101: 2 | BJ101: ТСН-2001.4 Доп. 67, Сб. 10, т. 72, поз. 14 | BM101: 69 | BN101: 0 | BO101: 4.10-72-14 | BP101: 1 | BQ101: 40 | BR101: 0 | BS101: 1 | BT101: 1 | BU101: 1 | BV101: 1 | BW101: 1 | BX101: 1 | BZ101: 95 | CA101: 53 | CE101: 1566 | CF101: 0 | CG101: 0 | CM101: 0 | CN101: Поправка: Гл.12.Прил.8.п.8. 3_12.00.01.11.001 Наименование: При наличии напряженных и стесненных условий производства работ (стесненность, сложность складирования и транспортной логистики и т.п.) для объектов, расположенных в пределах круговой магистральной системы улиц "Садовое кольцо" города Москвы | CO101: 0 | CP101: =(P101+Q101+S101) -> 120.61 | CQ101: =ROUND((ROUND((AC101*AW101*1),2)*BC101),2) -> 1.1 | CR101: =(ROUND((ROUND((((ET101*1.2))*AV101*1),2)*BB101),2)+ROUND((ROUND(((AE101-((EU101*1.2)))*AV101*1),2)*BS101),2)) -> 0 | CS101: =(ROUND((ROUND((((EU101*1.2))*AV101*1),2)*BS101),2)+ROUND((ROUND(((AE101-((EU101*1.2)))*AV101*1),2)*BS101),2)) -> 0 | CT101: =ROUND((ROUND((AF101*AV101*1),2)*BA101),2) -> 119.51 | CU101: =AG101 -> 0 | CV101: =(AH101*AV101) -> 10.0512 | CW101: =AI101 -> 0 | CX101: =AJ101 -> 0 | CY101: =(ROUND((((S101+ROUND((ROUND((((EU101*1.2))*AV101*1),2)*BS101),2))*AT101)/100),2)+ROUND(((ROUND((ROUND(((AE101-((EU101*1.2)))*AV101*1),2)*BS101),2)*AT101)/100),2)) -> 113.53 | CZ101: =(ROUND((((S101+ROUND((ROUND((((EU101*1.2))*AV101*1),2)*BS101),2))*AU101)/100),2)+ROUND(((ROUND((ROUND(((AE101-((EU101*1.2)))*AV101*1),2)*BS101),2)*AU101)/100),2)) -> 63.34 | DB101: 45 | DD101: *1 | DE101: *1,2 | DF101: *1,2 | DG101: *1,2 | DI101: *1,2 | DJ101: *1,2 | DN101: 0 | DO101: 0 | DP101: 1 | DQ101: 1 | DU101: 1013 | DV101: 1 устройство | DW101: 1 устройство | DX101: 1 | EE101: 57042959 | EF101: 40 | EG101: Монтаж оборудования | EH101: 0 | EJ101: 2 | EK101: 69 | EL101: ТСН-2001.4-10. Монтаж радиотелевизионного и электронного оборудования | EM101: ТСН-2001.4-10-2 | EO101: Поправка: Гл.12.Прил.8.п.8. 3_12.00.01.11.001 | EQ101: 0 | ER101: 96.22 | ES101: 1.1 | ET101: 0 | EU101: 0 | EV101: 95.12 | EW101: 8 | EX101: 0 | EY101: 0 | FQ101: 0 | FR101: 0 | FS101: 0 | FX101: 95 | FY101: 53 | GD101: 1 | GF101: -1819990670 | GG101: 2 | GH101: 1 | GI101: 2 | GJ101: 0 | GK101: 0 | GL101: =ROUND(IF(AND(BH101=3,BI101=3,FS101<>0),P101,0),2) -> 0 | GM101: =ROUND(O101+X101+Y101,2)+GX101 -> 297.48 | GN101: =IF(OR(BI101=0,BI101=1),GM101-GX101,0) -> 0 | GO101: =IF(BI101=2,GM101-GX101,0) -> 297.48 | GP101: =IF(BI101=4,GM101-GX101,0) -> 0 | GR101: 0 | GS101: 3 | GT101: 0 | GV101: =ROUND((GT101),6) -> 0 | GW101: 1 | GX101: =ROUND(HC101*I101,2) -> 0 | HA101: 0 | HB101: 0 | HC101: =GV101*GW101 -> 0 | HS101: 0 | IK101: 0
