Workbook

Sheet Смета по ТСН-2001(с доп.67
A1: =Source!B1 -> Smeta.RU (495) 974-1589
J2: Форма № 4б
B3: "СОГЛАСОВАНО" | G3: "УТВЕРЖДАЮ"
B6: =CONCATENATE("______________________ ", IF(Source!AL12<>"", Source!AL12, "")) -> ______________________ | G6: =CONCATENATE("______________________ ", IF(Source!AH12<>"", Source!AH12, "")) -> ______________________
B7: "_____"________________ 2026 г. | G7: "_____"________________ 2026 г.
A10: Капитальный ремонт здания Государственного бюджетного общеобразовательного учреждения города Москвы «Школа №1574», расположенного по адресу: г. Москва, Старопименовский переулок, д. 5. 1 этап. 02-01-03 ЭОМ_27.07.26 | AP10: Капитальный ремонт здания Государственного бюджетного общеобразовательного учреждения города Москвы «Школа №1574», расположенного по адресу: г. Москва, Старопименовский переулок, д. 5. 1 этап. 02-01-03 ЭОМ_27.07.26
A11: (наименование стройки и/или объекта)
A13: =CONCATENATE( "ЛОКАЛЬНАЯ СМЕТА № ",IF(Source!F12<>"Новый объект", Source!F12, "")) -> ЛОКАЛЬНАЯ СМЕТА № 02-01-03
A16: (наименование работ и затрат)
A18: =CONCATENATE( "Основание: чертежи № ", Source!J12) -> Основание: чертежи № 2024-00375-01-0-ИОС1, 2024-00375-01-0-ООС2
I20: В базисном уровне цен | J20: В текущем уровне цен
E21: Сметная стоимость | I21: =I22+I23+I24+I25 -> 5734.48 | J21: =J22+J23+J24+J25 -> 78658.44 | K21: тыс.руб.
E22: Строительные работы | I22: =ROUND((Source!F1478)/1000, 2) -> 261.16 | J22: =ROUND((Source!P1478)/1000, 2) -> 14439.08 | K22: тыс.руб.
E23: Работы по монтажу оборудования | I23: =ROUND((Source!F1479)/1000, 2) -> 4377.25 | J23: =ROUND((Source!P1479)/1000, 2) -> 55954.02 | K23: тыс.руб.
E24: Оборудование | I24: =ROUND((Source!F1470)/1000, 2) -> 1096.07 | J24: =ROUND((Source!P1470)/1000, 2) -> 8265.34 | K24: тыс.руб.
E25: Прочие работы и затраты | I25: =ROUND((Source!F1480+Source!F1481)/1000, 2) -> 0 | J25: =ROUND((Source!P1480+Source!P1481)/1000, 2) -> 0 | K25: тыс.руб.
E26: Средства на оплату труда | I26: =(Source!F1476+ Source!F1475)/1000 -> 275.98458 | J26: =((Source!P1476 + Source!P1475)/1000) -> 15551.731 | K26: тыс.руб.
E27: Затраты труда | I27: =Source!F1483 -> 23259.425 | K27: чел.-ч.
E28: Кроме того:
E29: Возврат материалов | I29: =SUM(Y1:Y2291)/1000 -> 0 | J29: =SUM(Z1:Z2291)/1000 -> 0 | K29: тыс.руб.
A31: Составлен(а) по ТСН-2001 с учетом Дополнения №: 81
A32: № и период сборника коэффициентов (индексов) пересчета: Коэффициенты к ТСН-2001 МГЭ Дополнение 81, строительство №219/81 I квартал 2026 года и Коэффициенты к ТСН-2001.13-2 Дополнение 47 №64/47 I квартал 2026 года | AP32: № и период сборника коэффициентов (индексов) пересчета: Коэффициенты к ТСН-2001 МГЭ Дополнение 81, строительство №219/81 I квартал 2026 года и Коэффициенты к ТСН-2001.13-2 Дополнение 47 №64/47 I квартал 2026 года
A33: № п/п | B33: Шифр расценки и коды ресурсов | C33: Наименование работ и затрат | D33: Ед. изм. | E33: Кол-во единиц | F33: Цена на ед. изм., руб. | G33: Попра- вочные коэффи- циенты | H33: Коэффи- циенты зимних удорожа- ний | I33: Всего в ценах на январь 2000 года, руб. | J33: Коэффи- циенты (индек- сы) пере- счета, нормы НР и СП | K33: ВСЕГО затрат в текущем уровне цен, руб.
A34: 1 | B34: 2 | C34: 3 | D34: 4 | E34: 5 | F34: 6 | G34: 7 | H34: 8 | I34: 9 | J34: 10 | K34: 11
A36: =CONCATENATE("Локальная смета: ",IF(Source!G20<>"Новая локальная смета", Source!G20, "")) -> Локальная смета: Система электроснабжения
A38: =CONCATENATE("Раздел: ",IF(Source!G24<>"Новый раздел", Source!G24, "")) -> Раздел: Демонтажные работы (2024-00375-01-0-ООС2)
A39: 1 | B39: =Source!F28 -> 4.8-251-9 | C39: Монтаж щитка осветительного, устанавливаемого на стене распорными дюбелями, масса щитка до 6 кг / демонтаж | D39: =Source!H28 -> 1 ШТ. | E39: =Source!I28 -> 58 | Q39: =Source!X28 -> 801.57 | R39: =Source!X29 -> 45168.42 | S39: =Source!Y28 -> 421.44 | T39: =Source!Y29 -> 23748.34 | U39: =ROUND((175/100)*ROUND(Source!R28, 2), 2) -> 4.97 | V39: =ROUND((0/100)*ROUND(Source!R29, 2), 2) -> 0 | AC39: 0
C40: ЗП | F40: =Source!AO28 -> 37.67 | G40: 1,2*0,3 | H40: =Source!AV29 -> 1.047 | I40: =Source!S28 -> 823.52 | J40: =IF(Source!BA29<> 0, Source!BA29, 1) -> 56.35 | K40: =Source!S29 -> 46405.35
C41: ЭМ | F41: =Source!AM28 -> 1.32 | G41: 1,2*0,3 | H41: =Source!AV29 -> 1.047 | I41: =Source!Q28 -> 28.86 | J41: =IF(Source!BB29<> 0, Source!BB29, 1) -> 14.27 | K41: =Source!Q29 -> 411.83
C42: в т.ч. ЗПМ | F42: =Source!AN28 -> 0.13 | G42: 1,2*0,3 | H42: =Source!AV29 -> 1.047 | I42: =Source!R28 -> 2.84 | J42: =IF(Source!BS29<> 0, Source!BS29, 1) -> 56.35 | K42: =Source!R29 -> 160.03
C43: НР от ФОТ | D43: % | E43: =Source!BZ29 -> 97 | I43: =SUM(Q39:Q42) -> 801.57 | J43: =Source!AT29 -> 97 | K43: =SUM(R39:R42) -> 45168.42
C44: СП от ФОТ | D44: % | E44: =Source!CA29 -> 51 | I44: =SUM(S39:S43) -> 421.44 | J44: =Source!AU29 -> 51 | K44: =SUM(T39:T43) -> 23748.34
C45: ЗТР | D45: чел-ч | E45: =Source!AQ28 -> 2.9 | G45: 1,2*0,3 | H45: =Source!AV29 -> 1.047 | I45: =Source!U28 -> 63.397944
C46: ВСЕГО работ по позиции: | H46: =I40+I41+I43+I44+0-0-0 -> 2075.39 | J46: =K40+K41+K43+K44+0-0-0 -> 115733.94
C47: ВСЕГО оборудование по позиции: | H47: =0+0 -> 0 | J47: =0+0 -> 0
C48: ВСЕГО по позиции: | H48: =I40+I41+I43+I44+0 -> 2075.39 | J48: =K40+K41+K43+K44+0 -> 115733.94 | O48: =I40+I41+I43+I44+0 -> 2075.39 | P48: =K40+K41+K43+K44+0 -> 115733.94
A50: 2 | B50: =Source!F30 -> 6.67-7-5 | C50: Демонтаж осветительных приборов, светильник для люминесцентных ламп | D50: =Source!H30 -> 100 шт. | E50: =Source!I30 -> 12.44 | Q50: =Source!X30 -> 2676.76 | R50: =Source!X31 -> 150835.19 | S50: =Source!Y30 -> 1411.92 | T50: =Source!Y31 -> 79561.42 | U50: =ROUND((175/100)*ROUND(Source!R30, 2), 2) -> 0 | V50: =ROUND((0/100)*ROUND(Source!R31, 2), 2) -> 0 | AC50: 0
C51: ="Объем: "&Source!I30&"=1244/"&"100" -> Объем: 12,44=1244/100
C52: ЗП | F52: =Source!AO30 -> 188.2 | G52: 1,2 | H52: =Source!AV31 -> 1.047 | I52: =Source!S30 -> 2941.49 | J52: =IF(Source!BA31<> 0, Source!BA31, 1) -> 56.35 | K52: =Source!S31 -> 165752.96
C53: НР от ФОТ | D53: % | E53: =Source!BZ31 -> 91 | I53: =SUM(Q50:Q52) -> 2676.76 | J53: =Source!AT31 -> 91 | K53: =SUM(R50:R52) -> 150835.19
C54: СП от ФОТ | D54: % | E54: =Source!CA31 -> 48 | I54: =SUM(S50:S53) -> 1411.92 | J54: =Source!AU31 -> 48 | K54: =SUM(T50:T53) -> 79561.42
C55: ЗТР | D55: чел-ч | E55: =Source!AQ30 -> 17.89 | G55: 1,2 | H55: =Source!AV31 -> 1.047 | I55: =Source!U30 -> 279.61383
C56: ВСЕГО работ по позиции: | H56: =I52+I53+I54+0-0-0 -> 7030.17 | J56: =K52+K53+K54+0-0-0 -> 396149.57
C57: ВСЕГО оборудование по позиции: | H57: =0+0 -> 0 | J57: =0+0 -> 0
C58: ВСЕГО по позиции: | H58: =I52+I53+I54+0 -> 7030.17 | J58: =K52+K53+K54+0 -> 396149.57 | O58: =I52+I53+I54+0 -> 7030.17 | P58: =K52+K53+K54+0 -> 396149.57
A60: 3 | B60: =Source!F34 -> 6.67-7-1 | C60: Демонтаж осветительных приборов, выключатели, розетки | D60: =Source!H34 -> 100 шт. | E60: =Source!I34 -> 9.72 | Q60: =Source!X34 -> 663.23 | R60: =Source!X35 -> 37372.8 | S60: =Source!Y34 -> 349.83 | T60: =Source!Y35 -> 19713.12 | U60: =ROUND((175/100)*ROUND(Source!R34, 2), 2) -> 0 | V60: =ROUND((0/100)*ROUND(Source!R35, 2), 2) -> 0 | AC60: 0
C61: ="Объем: "&Source!I34&"=972/"&"100" -> Объем: 9,72=972/100
C62: ЗП | F62: =Source!AO34 -> 59.68 | G62: 1,2 | H62: =Source!AV35 -> 1.047 | I62: =Source!S34 -> 728.82 | J62: =IF(Source!BA35<> 0, Source!BA35, 1) -> 56.35 | K62: =Source!S35 -> 41069.01
C63: НР от ФОТ | D63: % | E63: =Source!BZ35 -> 91 | I63: =SUM(Q60:Q62) -> 663.23 | J63: =Source!AT35 -> 91 | K63: =SUM(R60:R62) -> 37372.8
C64: СП от ФОТ | D64: % | E64: =Source!CA35 -> 48 | I64: =SUM(S60:S63) -> 349.83 | J64: =Source!AU35 -> 48 | K64: =SUM(T60:T63) -> 19713.12
C65: ЗТР | D65: чел-ч | E65: =Source!AQ34 -> 5.84 | G65: 1,2 | H65: =Source!AV35 -> 1.047 | I65: =Source!U34 -> 71.319295
C66: ВСЕГО работ по позиции: | H66: =I62+I63+I64+0-0-0 -> 1741.88 | J66: =K62+K63+K64+0-0-0 -> 98154.93
C67: ВСЕГО оборудование по позиции: | H67: =0+0 -> 0 | J67: =0+0 -> 0
C68: ВСЕГО по позиции: | H68: =I62+I63+I64+0 -> 1741.88 | J68: =K62+K63+K64+0 -> 98154.93 | O68: =I62+I63+I64+0 -> 1741.88 | P68: =K62+K63+K64+0 -> 98154.93
A70: 4 | B70: =Source!F36 -> 6.67-6-1 | C70: Демонтаж кабеля | D70: =Source!H36 -> 100 м | E70: =Source!I36 -> 303.59 | Q70: =Source!X36 -> 34196.46 | R70: =Source!X37 -> 1926970.6 | S70: =Source!Y36 -> 18037.69 | T70: =Source!Y37 -> 1016424.1 | U70: =ROUND((175/100)*ROUND(Source!R36, 2), 2) -> 0 | V70: =ROUND((0/100)*ROUND(Source!R37, 2), 2) -> 0 | AC70: 0
C71: ="Объем: "&Source!I36&"=30359/"&"100" -> Объем: 303,59=30359/100
C72: ЗП | F72: =Source!AO36 -> 98.52 | G72: 1,2 | H72: =Source!AV37 -> 1.047 | I72: =Source!S36 -> 37578.53 | J72: =IF(Source!BA37<> 0, Source!BA37, 1) -> 56.35 | K72: =Source!S37 -> 2117550.2
C73: НР от ФОТ | D73: % | E73: =Source!BZ37 -> 91 | I73: =SUM(Q70:Q72) -> 34196.46 | J73: =Source!AT37 -> 91 | K73: =SUM(R70:R72) -> 1926970.6
C74: СП от ФОТ | D74: % | E74: =Source!CA37 -> 48 | I74: =SUM(S70:S73) -> 18037.69 | J74: =Source!AU37 -> 48 | K74: =SUM(T70:T73) -> 1016424.1
C75: ЗТР | D75: чел-ч | E75: =Source!AQ36 -> 9.64 | G75: 1,2 | H75: =Source!AV37 -> 1.047 | I75: =Source!U36 -> 3676.9898
C76: ВСЕГО работ по позиции: | H76: =I72+I73+I74+0-0-0 -> 89812.68 | J76: =K72+K73+K74+0-0-0 -> 5060944.9
C77: ВСЕГО оборудование по позиции: | H77: =0+0 -> 0 | J77: =0+0 -> 0
C78: ВСЕГО по позиции: | H78: =I72+I73+I74+0 -> 89812.68 | J78: =K72+K73+K74+0 -> 5060944.9 | O78: =I72+I73+I74+0 -> 89812.68 | P78: =K72+K73+K74+0 -> 5060944.9
A80: 5 | B80: =Source!F38 -> 6.67-5-13 | C80: Демонтаж трубных проводок, трубы в борозде диаметром 40 мм / стальных | D80: =Source!H38 -> 100 м | E80: =Source!I38 -> 5.5 | Q80: =Source!X38 -> 3450.69 | R80: =Source!X39 -> 194446.53 | S80: =Source!Y38 -> 1820.15 | T80: =Source!Y39 -> 102565.2 | U80: =ROUND((175/100)*ROUND(Source!R38, 2), 2) -> 0 | V80: =ROUND((0/100)*ROUND(Source!R39, 2), 2) -> 0 | AC80: 0
C81: ="Объем: "&Source!I38&"=(550)/"&"100" -> Объем: 5,5=(550)/100
C82: ЗП | F82: =Source!AO38 -> 548.75 | G82: 1,2 | H82: =Source!AV39 -> 1.047 | I82: =Source!S38 -> 3791.97 | J82: =IF(Source!BA39<> 0, Source!BA39, 1) -> 56.35 | K82: =Source!S39 -> 213677.51
C83: НР от ФОТ | D83: % | E83: =Source!BZ39 -> 91 | I83: =SUM(Q80:Q82) -> 3450.69 | J83: =Source!AT39 -> 91 | K83: =SUM(R80:R82) -> 194446.53
C84: СП от ФОТ | D84: % | E84: =Source!CA39 -> 48 | I84: =SUM(S80:S83) -> 1820.15 | J84: =Source!AU39 -> 48 | K84: =SUM(T80:T83) -> 102565.2
C85: ЗТР | D85: чел-ч | E85: =Source!AQ38 -> 50.39 | G85: 1,2 | H85: =Source!AV39 -> 1.047 | I85: =Source!U38 -> 348.20498
C86: ВСЕГО работ по позиции: | H86: =I82+I83+I84+0-0-0 -> 9062.81 | J86: =K82+K83+K84+0-0-0 -> 510689.24
C87: ВСЕГО оборудование по позиции: | H87: =0+0 -> 0 | J87: =0+0 -> 0
C88: ВСЕГО по позиции: | H88: =I82+I83+I84+0 -> 9062.81 | J88: =K82+K83+K84+0 -> 510689.24 | O88: =I82+I83+I84+0 -> 9062.81 | P88: =K82+K83+K84+0 -> 510689.24
A90: 6 | B90: =Source!F40 -> 6.67-5-12 | C90: Демонтаж трубных проводок, трубы в борозде диаметром 25 мм / ПВХ | D90: =Source!H40 -> 100 м | E90: =Source!I40 -> 149.2 | Q90: =Source!X40 -> 54626.1 | R90: =Source!X41 -> 3078180.7 | S90: =Source!Y40 -> 28813.77 | T90: =Source!Y41 -> 1623655.7 | U90: =ROUND((175/100)*ROUND(Source!R40, 2), 2) -> 0 | V90: =ROUND((0/100)*ROUND(Source!R41, 2), 2) -> 0 | AC90: 0
C91: ="Объем: "&Source!I40&"=(14920)/"&"100" -> Объем: 149,2=(14920)/100
C92: ЗП | F92: =Source!AO40 -> 320.23 | G92: 1,2 | H92: =Source!AV41 -> 1.047 | I92: =Source!S40 -> 60028.68 | J92: =IF(Source!BA41<> 0, Source!BA41, 1) -> 56.35 | K92: =Source!S41 -> 3382616.1
C93: НР от ФОТ | D93: % | E93: =Source!BZ41 -> 91 | I93: =SUM(Q90:Q92) -> 54626.1 | J93: =Source!AT41 -> 91 | K93: =SUM(R90:R92) -> 3078180.7
C94: СП от ФОТ | D94: % | E94: =Source!CA41 -> 48 | I94: =SUM(S90:S93) -> 28813.77 | J94: =Source!AU41 -> 48 | K94: =SUM(T90:T93) -> 1623655.7
C95: ЗТР | D95: чел-ч | E95: =Source!AQ40 -> 30.44 | G95: 1,2 | H95: =Source!AV41 -> 1.047 | I95: =Source!U40 -> 5706.1265
C96: ВСЕГО работ по позиции: | H96: =I92+I93+I94+0-0-0 -> 143468.55 | J96: =K92+K93+K94+0-0-0 -> 8084452.5
C97: ВСЕГО оборудование по позиции: | H97: =0+0 -> 0 | J97: =0+0 -> 0
C98: ВСЕГО по позиции: | H98: =I92+I93+I94+0 -> 143468.55 | J98: =K92+K93+K94+0 -> 8084452.5 | O98: =I92+I93+I94+0 -> 143468.55 | P98: =K92+K93+K94+0 -> 8084452.5
A100: 7 | B100: =Source!F43 -> 4.8-238-2 | C100: Монтаж щитов и стеллажей с блоками резисторов (ящиками сопротивлений) высотой свыше 1700 мм, щита, собираемого из отдельных панелей и блоков управления, однорядного или двухрядного, без блоков резисторов глубиной до 800 мм шкафного исполнения / демонтаж вводных панелей ВП1, ВП2 | D100: =Source!H43 -> 1 м ширины по фронту | E100: =Source!I43 -> 1.2 | Q100: =Source!X43 -> 122.49 | R100: =Source!X44 -> 6902.4 | S100: =Source!Y43 -> 64.4 | T100: =Source!Y44 -> 3629.1 | U100: =ROUND((175/100)*ROUND(Source!R43, 2), 2) -> 9.19 | V100: =ROUND((0/100)*ROUND(Source!R44, 2), 2) -> 0 | AC100: 0
C101: ="Объем: "&Source!I43&"=0,6*"&"2" -> Объем: 1,2=0,6*2
C102: ЗП | F102: =Source!AO43 -> 267.59 | G102: 1,2*0,3 | H102: =Source!AV44 -> 1.047 | I102: =Source!S43 -> 121.03 | J102: =IF(Source!BA44<> 0, Source!BA44, 1) -> 56.35 | K102: =Source!S44 -> 6820.04
C103: ЭМ | F103: =Source!AM43 -> 95.26 | G103: 1,2*0,3 | H103: =Source!AV44 -> 1.047 | I103: =Source!Q43 -> 43.09 | J103: =IF(Source!BB44<> 0, Source!BB44, 1) -> 16.32 | K103: =Source!Q44 -> 703.23
C104: в т.ч. ЗПМ | F104: =Source!AN43 -> 11.61 | G104: 1,2*0,3 | H104: =Source!AV44 -> 1.047 | I104: =Source!R43 -> 5.25 | J104: =IF(Source!BS44<> 0, Source!BS44, 1) -> 56.35 | K104: =Source!R44 -> 295.84
C105: НР от ФОТ | D105: % | E105: =Source!BZ44 -> 97 | I105: =SUM(Q100:Q104) -> 122.49 | J105: =Source!AT44 -> 97 | K105: =SUM(R100:R104) -> 6902.4
C106: СП от ФОТ | D106: % | E106: =Source!CA44 -> 51 | I106: =SUM(S100:S105) -> 64.4 | J106: =Source!AU44 -> 51 | K106: =SUM(T100:T105) -> 3629.1
C107: ЗТР | D107: чел-ч | E107: =Source!AQ43 -> 20.6 | G107: 1,2*0,3 | H107: =Source!AV44 -> 1.047 | I107: =Source!U43 -> 9.3174624
C108: ВСЕГО работ по позиции: | H108: =I102+I103+I105+I106+0-0-0 -> 351.01 | J108: =K102+K103+K105+K106+0-0-0 -> 18054.77
C109: ВСЕГО оборудование по позиции: | H109: =0+0 -> 0 | J109: =0+0 -> 0
C110: ВСЕГО по позиции: | H110: =I102+I103+I105+I106+0 -> 351.01 | J110: =K102+K103+K105+K106+0 -> 18054.77 | O110: =I102+I103+I105+I106+0 -> 351.01 | P110: =K102+K103+K105+K106+0 -> 18054.77
A112: 8 | B112: =Source!F45 -> 4.8-238-2 | C112: Монтаж щитов и стеллажей с блоками резисторов (ящиками сопротивлений) высотой свыше 1700 мм, щита, собираемого из отдельных панелей и блоков управления, однорядного или двухрядного, без блоков резисторов глубиной до 800 мм шкафного исполнения / демонтаж распределительных панелей РП1, РП2, РП3 | D112: =Source!H45 -> 1 м ширины по фронту | E112: =Source!I45 -> 1.8 | Q112: =Source!X45 -> 183.75 | R112: =Source!X46 -> 10354.15 | S112: =Source!Y45 -> 96.61 | T112: =Source!Y46 -> 5443.93 | U112: =ROUND((175/100)*ROUND(Source!R45, 2), 2) -> 13.79 | V112: =ROUND((0/100)*ROUND(Source!R46, 2), 2) -> 0 | AC112: 0
C113: ="Объем: "&Source!I45&"=0,6*"&"3" -> Объем: 1,8=0,6*3
C114: ЗП | F114: =Source!AO45 -> 267.59 | G114: 1,2*0,3 | H114: =Source!AV46 -> 1.047 | I114: =Source!S45 -> 181.55 | J114: =IF(Source!BA46<> 0, Source!BA46, 1) -> 56.35 | K114: =Source!S46 -> 10230.34
C115: ЭМ | F115: =Source!AM45 -> 95.26 | G115: 1,2*0,3 | H115: =Source!AV46 -> 1.047 | I115: =Source!Q45 -> 64.63 | J115: =IF(Source!BB46<> 0, Source!BB46, 1) -> 16.32 | K115: =Source!Q46 -> 1054.76
C116: в т.ч. ЗПМ | F116: =Source!AN45 -> 11.61 | G116: 1,2*0,3 | H116: =Source!AV46 -> 1.047 | I116: =Source!R45 -> 7.88 | J116: =IF(Source!BS46<> 0, Source!BS46, 1) -> 56.35 | K116: =Source!R46 -> 444.04
C117: НР от ФОТ | D117: % | E117: =Source!BZ46 -> 97 | I117: =SUM(Q112:Q116) -> 183.75 | J117: =Source!AT46 -> 97 | K117: =SUM(R112:R116) -> 10354.15
C118: СП от ФОТ | D118: % | E118: =Source!CA46 -> 51 | I118: =SUM(S112:S117) -> 96.61 | J118: =Source!AU46 -> 51 | K118: =SUM(T112:T117) -> 5443.93
C119: ЗТР | D119: чел-ч | E119: =Source!AQ45 -> 20.6 | G119: 1,2*0,3 | H119: =Source!AV46 -> 1.047 | I119: =Source!U45 -> 13.976194
...

Sheet Source
A1: 0 | B1: Smeta.RU (495) 974-1589 | D1: _PS_ | F1: 0 | G1: 0 | H1: 0 | I1: Smeta.RU | K1: 1 | L1: 74599 | M1: 10 | N1: 12 | O1: 1 | P1: 0 | Q1: 5
A4: 1 | B4: 1 | C4: -1 | G4: Капитальный ремонт здания Государственного бюджетного общеобразовательного учреждения города Москвы «Школа №1574», расположенного по адресу: г. Москва, Старопименовский переулок, д. 5. 1 этап | EC4: 0
A5: 8 | B5: 1 | C5: -1 | G5: Капитальный ремонт здания Государственного бюджетного общеобразовательного учреждения города Москвы «Школа №1574», расположенного по адресу: г. Москва, Старопименовский переулок, д. 5. 1 этап | EC5: 0
A12: 1 | B12: 1500 | C12: 0 | D12: =ROW(A1461) -> 1461 | E12: 0 | F12: 02-01-03 | G12: 02-01-03 ЭОМ_27.07.26 | I12: 0 | J12: 2024-00375-01-0-ИОС1, 2024-00375-01-0-ООС2 | K12: 0 | L12: 0 | M12: 4098 | O12: 0 | P12: 0 | Q12: 0 | R12: 0 | S12: 0 | T12: 1 | V12: 2 | AB12: О.А.Гришечкина | AC12: Ведущий инженер-сметччик | AD12: И.В.Феденко | AE12: Начальник отдела | BB12: 0 | BH12: Сметные нормы списания | BI12: Коды ОКП для ТСН-2001 МГЭ Дополнение 81 | BJ12: 1 | BK12: 1 | BL12: 0 | BM12: 0 | BN12: 1 | BO12: 0 | BP12: 6 | BQ12: 2 | BR12: 1 | BS12: 1 | BT12: 0 | BU12: 0 | BV12: 0 | BW12: 0 | BX12: 0 | BY12: ТСН-2001 (МГЭ) Доп 81 - Новое строительство | BZ12: Типовой расчет для ТСН-2001 МГЭ, Дополнение 81, строительство | CA12: Территориальные сметные нормативы для Москвы ТСН-2001 (МГЭ), дополнение 81 | CB12: Территориальные сметные нормативы для Москвы ТСН-2001 (МГЭ), дополнение 81 | CC12: Территориальные сметные нормативы для Москвы ТСН-2001 (МГЭ), дополнение 81 | CD12: Территориальные сметные нормативы для Москвы ТСН-2001 (МГЭ), дополнение 81 | CE12: Поправки для ТСН-2001 от 07.04.2026 г. доп.81 | CF12: 0 | CG12: 0 | CH12: 8200 | CK12: 82 | CQ12: Территориальные сметные нормативы для Москвы (ТСН-2001) | CR12: ТЕР | CS12: 41660 | CT12: 1 | CU12: 81 | CY12: 0 | EC12: 0
A15: 15 | B15: 1
A18: 52 | B18: =B1461 -> 1500 | C18: =C1461 -> 1 | D18: =D1461 -> 12 | E18: =E1461 -> 0 | F18: =F1461 -> 02-01-03 | G18: =G1461 -> 02-01-03 ЭОМ_27.07.26 | O18: =O1461 -> 5335739.8 | P18: =P1461 -> 5030939 | Q18: =Q1461 -> 34810 | R18: =R1461 -> 5993.71 | S18: =S1461 -> 269990.87 | T18: =T1461 -> 0 | U18: =U1461 -> 23259.425 | V18: =V1461 -> 0 | ... GX18: =GX1461 -> 0
A20: 3 | B20: 1 | D20: =ROW(A1431) -> 1431 | F20: 02-01-03 | G20: Система электроснабжения | I20: 0 | J20: 2024-00375-01-0-ИОС1, 2024-00375-01-0-ООС2 | K20: -1 | L20: 02-01-03 | S20: 0 | T20: 0 | V20: 2 | AB20: О.А.Гритшечкина | AD20: И.В.Феденко | AE20: Начальник отдела | BC20: *1 | BD20: *1,1 | BE20: *1,1 | BF20: *1,1 | BH20: *1,1 | BI20: *1,1 | BM20: *1 | BN20: *1,1 | BO20: Поправка: Гл.12.Прил.8.п.8. 5_12.00.01.11.003 Наименование: При наличии усложненных условий производства работ (стесненность, сложность складирования и транспортной логистики, наличие в зоне производства работ действующего технологического оборудования или движения технологического транспорта и т.п.) для объектов, расположенных за пределами территории круговой магистральной системы улиц "Садовое кольцо" и за пределами Третьего транспортного кольца города Москвы пунктов "а" и "б", но в пределах Московской кольцевой автомобильной дороги | BP20: Поправка: Гл.12.Прил.8.п.8. 5_12.00.01.11.003 | BX20: 0 | CF20: 0 | CG20: 0
A22: 52 | B22: =B1431 -> 1 | C22: =C1431 -> 3 | D22: =D1431 -> 20 | E22: =E1431 -> 0 | F22: =F1431 -> 02-01-03 | G22: =G1431 -> Система электроснабжения | O22: =O1431 -> 5335739.8 | P22: =P1431 -> 5030939 | Q22: =Q1431 -> 34810 | R22: =R1431 -> 5993.71 | S22: =S1431 -> 269990.87 | T22: =T1431 -> 0 | U22: =U1431 -> 23259.425 | V22: =V1431 -> 0 | ... GX22: =GX1431 -> 0
A24: 4 | B24: 1 | D24: =ROW(A93) -> 93 | F24: 1 | G24: Демонтажные работы (2024-00375-01-0-ООС2) | I24: 0 | K24: -1 | S24: 0 | T24: 0 | V24: 2 | BC24: *1 | BD24: *1,1 | BE24: *1,1 | BF24: *1,1 | BH24: *1,1 | BI24: *1,1 | BM24: *1 | BN24: *1,1 | BO24: Поправка: Гл.12.Прил.8.п.8. 5_12.00.01.11.003 Наименование: При наличии усложненных условий производства работ (стесненность, сложность складирования и транспортной логистики, наличие в зоне производства работ действующего технологического оборудования или движения технологического транспорта и т.п.) для объектов, расположенных за пределами территории круговой магистральной системы улиц "Садовое кольцо" и за пределами Третьего транспортного кольца города Москвы пунктов "а" и "б", но в пределах Московской кольцевой автомобильной дороги | BP24: Поправка: Гл.12.Прил.8.п.8. 5_12.00.01.11.003 | BX24: 0 | CJ24: 0
A26: 52 | B26: =B93 -> 1 | C26: =C93 -> 4 | D26: =D93 -> 24 | E26: =E93 -> 0 | F26: =F93 -> 1 | G26: =G93 -> Демонтажные работы (2024-00375-01-0-ООС2) | O26: =O93 -> 115163.54 | P26: =P93 -> 4.29 | Q26: =Q93 -> 857.45 | R26: =R93 -> 71.34 | S26: =S93 -> 114301.8 | T26: =T93 -> 0 | U26: =U93 -> 10822.647 | V26: =V93 -> 0 | ... GX26: =GX93 -> 0
A28: 17 | B28: 1 | C28: =ROW(SmtRes!A9) -> 9 | D28: =ROW(EtalonRes!A12) -> 12 | E28: 1 | F28: 4.8-251-9 | G28: Монтаж щитка осветительного, устанавливаемого на стене распорными дюбелями, масса щитка до 6 кг / демонтаж | H28: 1 ШТ. | I28: 58 | J28: 0 | K28: 58 | O28: =ROUND(CP28,2) -> 852.38 | P28: =ROUND((ROUND((AC28*AW28*I28),2)*BC28),2) -> 0 | Q28: =(ROUND((ROUND(((((ET28*1.2)*0.3))*AV28*I28),2)*BB28),2)+ROUND((ROUND(((AE28-(((EU28*1.2)*0.3)))*AV28*I28),2)*BS28),2)) -> 28.86 | R28: =(ROUND((ROUND(((((EU28*1.2)*0.3))*AV28*I28),2)*BS28),2)+ROUND((ROUND(((AE28-(((EU28*1.2)*0.3)))*AV28*I28),2)*BS28),2)) -> 2.84 | S28: =ROUND((ROUND((AF28*AV28*I28),2)*BA28),2) -> 823.52 | T28: =ROUND(CU28*I28,2) -> 0 | U28: =CV28*I28 -> 63.397944 | V28: =CW28*I28 -> 0 | W28: =ROUND(CX28*I28,2) -> 0 | X28: =(ROUND((((S28+ROUND((ROUND(((((EU28*1.2)*0.3))*AV28*I28),2)*BS28),2))*AT28)/100),2)+ROUND(((ROUND((ROUND(((AE28-(((EU28*1.2)*0.3)))*AV28*I28),2)*BS28),2)*AT28)/100),2)) -> 801.57 | Y28: =(ROUND((((S28+ROUND((ROUND(((((EU28*1.2)*0.3))*AV28*I28),2)*BS28),2))*AU28)/100),2)+ROUND(((ROUND((ROUND(((AE28-(((EU28*1.2)*0.3)))*AV28*I28),2)*BS28),2)*AU28)/100),2)) -> 421.44 | AA28: 54971259 | AB28: =ROUND((AC28+AD28+AF28),6) -> 14.0364 | AC28: =ROUND((((ES28*1)*0)),6) -> 0 | AD28: =ROUND((((((ET28*1.2)*0.3))-(((EU28*1.2)*0.3)))+AE28),6) -> 0.4752 | AE28: =ROUND((((EU28*1.2)*0.3)),6) -> 0.0468 | AF28: =ROUND((((EV28*1.2)*0.3)),6) -> 13.5612 | AG28: =ROUND((AP28),6) -> 0 | AH28: =(((EW28*1.2)*0.3)) -> 1.044 | AI28: =(((EX28*1.2)*0.3)) -> 0 | AJ28: =(AS28) -> 0 | AK28: 69.2 | AL28: 30.21 | AM28: 1.32 | AN28: 0.13 | AO28: 37.67 | AP28: 0 | AQ28: 2.9 | AR28: 0 | AS28: 0 | AT28: 97 | AU28: 51 | AV28: 1.047 | AW28: 1 | AZ28: 1 | BA28: 1 | BB28: 1 | BC28: 1 | BH28: 0 | BI28: 2 | BJ28: ТСН-2001.4 Доп. 80, Сб. 8, т. 251, поз. 9 | BM28: 67 | BN28: 0 | BO28: 4.8-251-9 | BP28: 1 | BQ28: 40 | BR28: 0 | BS28: 1 | BT28: 1 | BU28: 1 | BV28: 1 | BW28: 1 | BX28: 1 | BZ28: 97 | CA28: 51 | CE28: 1566 | CF28: 0 | CG28: 0 | CM28: 0 | CN28: Поправка: Гл.12.Прил.8.п.8. 3_12.00.01.11.001 Наименование: При наличии напряженных и стесненных условий производства работ (стесненность, сложность складирования и транспортной логистики и т.п.) для объектов, расположенных в пределах круговой магистральной системы улиц "Садовое кольцо" города Москвы Поправка: Гл.4.Прил.2.2.п.2.2.29_04.00.01.35.003 Наименование: При демонтаже оборудования, предназначенного в лом | CO28: 0 | CP28: =(P28+Q28+S28) -> 852.38 | CQ28: =ROUND((ROUND((AC28*AW28*1),2)*BC28),2) -> 0 | CR28: =(ROUND((ROUND(((((ET28*1.2)*0.3))*AV28*1),2)*BB28),2)+ROUND((ROUND(((AE28-(((EU28*1.2)*0.3)))*AV28*1),2)*BS28),2)) -> 0.5 | CS28: =(ROUND((ROUND(((((EU28*1.2)*0.3))*AV28*1),2)*BS28),2)+ROUND((ROUND(((AE28-(((EU28*1.2)*0.3)))*AV28*1),2)*BS28),2)) -> 0.05 | CT28: =ROUND((ROUND((AF28*AV28*1),2)*BA28),2) -> 14.2 | CU28: =AG28 -> 0 | CV28: =(AH28*AV28) -> 1.093068 | CW28: =AI28 -> 0 | CX28: =AJ28 -> 0 | CY28: =(ROUND((((S28+ROUND((ROUND(((((EU28*1.2)*0.3))*AV28*1),2)*BS28),2))*AT28)/100),2)+ROUND(((ROUND((ROUND(((AE28-(((EU28*1.2)*0.3)))*AV28*1),2)*BS28),2)*AT28)/100),2)) -> 798.86 | CZ28: =(ROUND((((S28+ROUND((ROUND(((((EU28*1.2)*0.3))*AV28*1),2)*BS28),2))*AU28)/100),2)+ROUND(((ROUND((ROUND(((AE28-(((EU28*1.2)*0.3)))*AV28*1),2)*BS28),2)*AU28)/100),2)) -> 420.02 | DB28: 1 | DD28: *1)*0 | DE28: *1,2)*0,3 | DF28: *1,2)*0,3 | DG28: *1,2)*0,3 | DI28: *1,2)*0,3 | DJ28: *1,2)*0,3 | DN28: 0 | DO28: 0 | DP28: 1 | DQ28: 1 | DU28: 1013 | DV28: 1 ШТ. | DW28: 1 ШТ. | DX28: 1 | EE28: 57042957 | EF28: 40 | EG28: Монтаж оборудования | EH28: 0 | EJ28: 2 | EK28: 67 | EL28: ТСН-2001.4-8. Электротехнические установки | EM28: ТСН-2001.4-8-1 | EO28: Поправка: Гл.12.Прил.8.п.8. 3_12.00.01.11.001 Поправка: Гл.4.Прил.2.2.п.2.2.29_04.00.01.35.003 | EQ28: 0 | ER28: 69.2 | ES28: 30.21 | ET28: 1.32 | EU28: 0.13 | EV28: 37.67 | EW28: 2.9 | EX28: 0 | EY28: 0 | FQ28: 0 | FR28: 0 | FS28: 0 | FX28: 97 | FY28: 51 | GD28: 1 | GF28: 1021264723 | GG28: 2 | GH28: 1 | GI28: 2 | GJ28: 0 | GK28: 0 | GL28: =ROUND(IF(AND(BH28=3,BI28=3,FS28<>0),P28,0),2) -> 0 | GM28: =ROUND(O28+X28+Y28,2)+GX28 -> 2075.39 | GN28: =IF(OR(BI28=0,BI28=1),GM28-GX28,0) -> 0 | GO28: =IF(BI28=2,GM28-GX28,0) -> 2075.39 | GP28: =IF(BI28=4,GM28-GX28,0) -> 0 | GR28: 0 | GS28: 3 | GT28: 0 | GV28: =ROUND((GT28),6) -> 0 | GW28: 1 | GX28: =ROUND(HC28*I28,2) -> 0 | HA28: 0 | HB28: 0 | HC28: =GV28*GW28 -> 0 | HS28: 0 | IK28: 0
A29: 17 | B29: 1 | C29: =ROW(SmtRes!A18) -> 18 | D29: =ROW(EtalonRes!A24) -> 24 | E29: 1 | F29: 4.8-251-9 | G29: Монтаж щитка осветительного, устанавливаемого на стене распорными дюбелями, масса щитка до 6 кг / демонтаж | H29: 1 ШТ. | I29: 58 | J29: 0 | K29: 58 | O29: =ROUND(CP29,2) -> 46817.18 | P29: =ROUND((ROUND((AC29*AW29*I29),2)*BC29),2) -> 0 | Q29: =(ROUND((ROUND(((((ET29*1.2)*0.3))*AV29*I29),2)*BB29),2)+ROUND((ROUND(((AE29-(((EU29*1.2)*0.3)))*AV29*I29),2)*BS29),2)) -> 411.83 | R29: =(ROUND((ROUND(((((EU29*1.2)*0.3))*AV29*I29),2)*BS29),2)+ROUND((ROUND(((AE29-(((EU29*1.2)*0.3)))*AV29*I29),2)*BS29),2)) -> 160.03 | S29: =ROUND((ROUND((AF29*AV29*I29),2)*BA29),2) -> 46405.35 | T29: =ROUND(CU29*I29,2) -> 0 | U29: =CV29*I29 -> 63.397944 | V29: =CW29*I29 -> 0 | W29: =ROUND(CX29*I29,2) -> 0 | X29: =(ROUND((((S29+ROUND((ROUND(((((EU29*1.2)*0.3))*AV29*I29),2)*BS29),2))*AT29)/100),2)+ROUND(((ROUND((ROUND(((AE29-(((EU29*1.2)*0.3)))*AV29*I29),2)*BS29),2)*AT29)/100),2)) -> 45168.42 | Y29: =(ROUND((((S29+ROUND((ROUND(((((EU29*1.2)*0.3))*AV29*I29),2)*BS29),2))*AU29)/100),2)+ROUND(((ROUND((ROUND(((AE29-(((EU29*1.2)*0.3)))*AV29*I29),2)*BS29),2)*AU29)/100),2)) -> 23748.34 | AA29: 55890823 | AB29: =ROUND((AC29+AD29+AF29),6) -> 14.0364 | AC29: =ROUND((((ES29*1)*0)),6) -> 0 | AD29: =ROUND((((((ET29*1.2)*0.3))-(((EU29*1.2)*0.3)))+AE29),6) -> 0.4752 | AE29: =ROUND((((EU29*1.2)*0.3)),6) -> 0.0468 | AF29: =ROUND((((EV29*1.2)*0.3)),6) -> 13.5612 | AG29: =ROUND((AP29),6) -> 0 | AH29: =(((EW29*1.2)*0.3)) -> 1.044 | AI29: =(((EX29*1.2)*0.3)) -> 0 | AJ29: =(AS29) -> 0 | AK29: 69.2 | AL29: 30.21 | AM29: 1.32 | AN29: 0.13 | AO29: 37.67 | AP29: 0 | AQ29: 2.9 | AR29: 0 | AS29: 0 | AT29: 97 | AU29: 51 | AV29: 1.047 | AW29: 1 | AZ29: 1 | BA29: 56.35 | BB29: 14.27 | BC29: 6.19 | BH29: 0 | BI29: 2 | BJ29: ТСН-2001.4 Доп. 80, Сб. 8, т. 251, поз. 9 | BM29: 67 | BN29: 0 | BO29: 4.8-251-9 | BP29: 1 | BQ29: 40 | BR29: 0 | BS29: 56.35 | BT29: 1 | BU29: 1 | BV29: 1 | BW29: 1 | BX29: 1 | BZ29: 97 | CA29: 51 | CE29: 1566 | CF29: 0 | CG29: 0 | CM29: 0 | CN29: Поправка: Гл.12.Прил.8.п.8. 3_12.00.01.11.001 Наименование: При наличии напряженных и стесненных условий производства работ (стесненность, сложность складирования и транспортной логистики и т.п.) для объектов, расположенных в пределах круговой магистральной системы улиц "Садовое кольцо" города Москвы Поправка: Гл.4.Прил.2.2.п.2.2.29_04.00.01.35.003 Наименование: При демонтаже оборудования, предназначенного в лом | CO29: 0 | CP29: =(P29+Q29+S29) -> 46817.18 | CQ29: =ROUND((ROUND((AC29*AW29*1),2)*BC29),2) -> 0 | CR29: =(ROUND((ROUND(((((ET29*1.2)*0.3))*AV29*1),2)*BB29),2)+ROUND((ROUND(((AE29-(((EU29*1.2)*0.3)))*AV29*1),2)*BS29),2)) -> 7.14 | CS29: =(ROUND((ROUND(((((EU29*1.2)*0.3))*AV29*1),2)*BS29),2)+ROUND((ROUND(((AE29-(((EU29*1.2)*0.3)))*AV29*1),2)*BS29),2)) -> 2.82 | CT29: =ROUND((ROUND((AF29*AV29*1),2)*BA29),2) -> 800.17 | CU29: =AG29 -> 0 | CV29: =(AH29*AV29) -> 1.093068 | CW29: =AI29 -> 0 | CX29: =AJ29 -> 0 | CY29: =(ROUND((((S29+ROUND((ROUND(((((EU29*1.2)*0.3))*AV29*1),2)*BS29),2))*AT29)/100),2)+ROUND(((ROUND((ROUND(((AE29-(((EU29*1.2)*0.3)))*AV29*1),2)*BS29),2)*AT29)/100),2)) -> 45015.92 | CZ29: =(ROUND((((S29+ROUND((ROUND(((((EU29*1.2)*0.3))*AV29*1),2)*BS29),2))*AU29)/100),2)+ROUND(((ROUND((ROUND(((AE29-(((EU29*1.2)*0.3)))*AV29*1),2)*BS29),2)*AU29)/100),2)) -> 23668.17 | DB29: 3 | DD29: *1)*0 | DE29: *1,2)*0,3 | DF29: *1,2)*0,3 | DG29: *1,2)*0,3 | DI29: *1,2)*0,3 | DJ29: *1,2)*0,3 | DN29: 0 | DO29: 0 | DP29: 1 | DQ29: 1 | DU29: 1013 | DV29: 1 ШТ. | DW29: 1 ШТ. | DX29: 1 | EE29: 57042957 | EF29: 40 | EG29: Монтаж оборудования | EH29: 0 | EJ29: 2 | EK29: 67 | EL29: ТСН-2001.4-8. Электротехнические установки | EM29: ТСН-2001.4-8-1 | EO29: Поправка: Гл.12.Прил.8.п.8. 3_12.00.01.11.001 Поправка: Гл.4.Прил.2.2.п.2.2.29_04.00.01.35.003 | EQ29: 0 | ER29: 69.2 | ES29: 30.21 | ET29: 1.32 | EU29: 0.13 | EV29: 37.67 | EW29: 2.9 | EX29: 0 | EY29: 0 | FQ29: 0 | FR29: 0 | FS29: 0 | FX29: 97 | FY29: 51 | GD29: 1 | GF29: 1021264723 | GG29: 2 | GH29: 1 | GI29: 2 | GJ29: 0 | GK29: 0 | GL29: =ROUND(IF(AND(BH29=3,BI29=3,FS29<>0),P29,0),2) -> 0 | GM29: =ROUND(O29+X29+Y29,2)+GX29 -> 115733.94 | GN29: =IF(OR(BI29=0,BI29=1),GM29-GX29,0) -> 0 | GO29: =IF(BI29=2,GM29-GX29,0) -> 115733.94 | GP29: =IF(BI29=4,GM29-GX29,0) -> 0 | GR29: 0 | GS29: 3 | GT29: 0 | GV29: =ROUND((GT29),6) -> 0 | GW29: 1 | GX29: =ROUND(HC29*I29,2) -> 0 | HA29: 0 | HB29: 0 | HC29: =GV29*GW29 -> 0 | HS29: 0 | IK29: 0
A30: 17 | B30: 1 | C30: =ROW(SmtRes!A19) -> 19 | D30: =ROW(EtalonRes!A25) -> 25 | E30: 2 | F30: 6.67-7-5 | G30: Демонтаж осветительных приборов, светильник для люминесцентных ламп | H30: 100 шт. | I30: =ROUND(1244/100,9) -> 12.44 | J30: 0 | K30: =ROUND(1244/100,9) -> 12.44 | O30: =ROUND(CP30,2) -> 2941.49 | P30: =ROUND((ROUND((AC30*AW30*I30),2)*BC30),2) -> 0 | Q30: =(ROUND((ROUND((((ET30*1.2))*AV30*I30),2)*BB30),2)+ROUND((ROUND(((AE30-((EU30*1.2)))*AV30*I30),2)*BS30),2)) -> 0 | R30: =(ROUND((ROUND((((EU30*1.2))*AV30*I30),2)*BS30),2)+ROUND((ROUND(((AE30-((EU30*1.2)))*AV30*I30),2)*BS30),2)) -> 0 | S30: =ROUND((ROUND((AF30*AV30*I30),2)*BA30),2) -> 2941.49 | T30: =ROUND(CU30*I30,2) -> 0 | U30: =CV30*I30 -> 279.61383 | V30: =CW30*I30 -> 0 | W30: =ROUND(CX30*I30,2) -> 0 | X30: =(ROUND((((S30+ROUND((ROUND((((EU30*1.2))*AV30*I30),2)*BS30),2))*AT30)/100),2)+ROUND(((ROUND((ROUND(((AE30-((EU30*1.2)))*AV30*I30),2)*BS30),2)*AT30)/100),2)) -> 2676.76 | Y30: =(ROUND((((S30+ROUND((ROUND((((EU30*1.2))*AV30*I30),2)*BS30),2))*AU30)/100),2)+ROUND(((ROUND((ROUND(((AE30-((EU30*1.2)))*AV30*I30),2)*BS30),2)*AU30)/100),2)) -> 1411.92 | AA30: 54971259 | AB30: =ROUND((AC30+AD30+AF30),6) -> 225.84 | AC30: =ROUND(((ES30*1)),6) -> 0 | AD30: =ROUND(((((ET30*1.2))-((EU30*1.2)))+AE30),6) -> 0 | AE30: =ROUND(((EU30*1.2)),6) -> 0 | AF30: =ROUND(((EV30*1.2)),6) -> 225.84 | AG30: =ROUND((AP30),6) -> 0 | AH30: =((EW30*1.2)) -> 21.468 | AI30: =((EX30*1.2)) -> 0 | AJ30: =(AS30) -> 0 | AK30: 188.2 | AL30: 0 | AM30: 0 | AN30: 0 | AO30: 188.2 | AP30: 0 | AQ30: 17.89 | AR30: 0 | AS30: 0 | AT30: 91 | AU30: 48 | AV30: 1.047 | AW30: 1 | AZ30: 1 | BA30: 1 | BB30: 1 | BC30: 1 | BH30: 0 | BI30: 1 | BJ30: ТСН-2001.6. Доп. 1-42. Сб. 67, т. 7, поз. 5 | BM30: 106 | BN30: 0 | BO30: 6.67-7-5 | BP30: 1 | BQ30: 60 | BR30: 0 | BS30: 1 | BT30: 1 | BU30: 1 | BV30: 1 | BW30: 1 | BX30: 1 | BZ30: 91 | CA30: 48 | CE30: 1566 | CF30: 0 | CG30: 0 | CM30: 0 | CN30: Поправка: Гл.12.Прил.8.п.8. 3_12.00.01.11.001 Наименование: При наличии напряженных и стесненных условий производства работ (стесненность, сложность складирования и транспортной логистики и т.п.) для объектов, расположенных в пределах круговой магистральной системы улиц "Садовое кольцо" города Москвы | CO30: 0 | CP30: =(P30+Q30+S30) -> 2941.49 | CQ30: =ROUND((ROUND((AC30*AW30*1),2)*BC30),2) -> 0 | CR30: =(ROUND((ROUND((((ET30*1.2))*AV30*1),2)*BB30),2)+ROUND((ROUND(((AE30-((EU30*1.2)))*AV30*1),2)*BS30),2)) -> 0 | CS30: =(ROUND((ROUND((((EU30*1.2))*AV30*1),2)*BS30),2)+ROUND((ROUND(((AE30-((EU30*1.2)))*AV30*1),2)*BS30),2)) -> 0 | CT30: =ROUND((ROUND((AF30*AV30*1),2)*BA30),2) -> 236.45 | CU30: =AG30 -> 0 | CV30: =(AH30*AV30) -> 22.476996 | CW30: =AI30 -> 0 | CX30: =AJ30 -> 0 | CY30: =(ROUND((((S30+ROUND((ROUND((((EU30*1.2))*AV30*1),2)*BS30),2))*AT30)/100),2)+ROUND(((ROUND((ROUND(((AE30-((EU30*1.2)))*AV30*1),2)*BS30),2)*AT30)/100),2)) -> 2676.76 | CZ30: =(ROUND((((S30+ROUND((ROUND((((EU30*1.2))*AV30*1),2)*BS30),2))*AU30)/100),2)+ROUND(((ROUND((ROUND(((AE30-((EU30*1.2)))*AV30*1),2)*BS30),2)*AU30)/100),2)) -> 1411.92 | DB30: 5 | DD30: *1 | DE30: *1,2 | DF30: *1,2 | DG30: *1,2 | DI30: *1,2 | DJ30: *1,2 | DN30: 0 | DO30: 0 | DP30: 1 | DQ30: 1 | DU30: 1010 | DV30: 100 шт. | DW30: 100 шт. | DX30: 100 | EE30: 57042996 | EF30: 60 | EG30: Ремонтно-строительные работы | EH30: 0 | EJ30: 1 | EK30: 106 | EL30: ТСН-2001.6-67. Электромонтажные работы | EM30: ТСН-2001.6-67-1 | EO30: Поправка: Гл.12.Прил.8.п.8. 3_12.00.01.11.001 | EQ30: 0 | ER30: 188.2 | ES30: 0 | ET30: 0 | EU30: 0 | EV30: 188.2 | EW30: 17.89 | EX30: 0 | EY30: 0 | FQ30: 0 | FR30: 0 | FS30: 0 | FX30: 91 | FY30: 48 | GD30: 1 | GF30: -651826134 | GG30: 2 | GH30: 1 | GI30: 2 | GJ30: 0 | GK30: 0 | GL30: =ROUND(IF(AND(BH30=3,BI30=3,FS30<>0),P30,0),2) -> 0 | GM30: =ROUND(O30+X30+Y30,2)+GX30 -> 7030.17 | GN30: =IF(OR(BI30=0,BI30=1),GM30-GX30,0) -> 7030.17 | GO30: =IF(BI30=2,GM30-GX30,0) -> 0 | GP30: =IF(BI30=4,GM30-GX30,0) -> 0 | GR30: 0 | GS30: 3 | GT30: 0 | GV30: =ROUND((GT30),6) -> 0 | GW30: 1 | GX30: =ROUND(HC30*I30,2) -> 0 | HA30: 0 | HB30: 0 | HC30: =GV30*GW30 -> 0 | HS30: 0 | IK30: 0
A31: 17 | B31: 1 | C31: =ROW(SmtRes!A20) -> 20 | D31: =ROW(EtalonRes!A26) -> 26 | E31: 2 | F31: 6.67-7-5 | G31: Демонтаж осветительных приборов, светильник для люминесцентных ламп | H31: 100 шт. | I31: =ROUND(1244/100,9) -> 12.44 | J31: 0 | K31: =ROUND(1244/100,9) -> 12.44 | O31: =ROUND(CP31,2) -> 165752.96 | P31: =ROUND((ROUND((AC31*AW31*I31),2)*BC31),2) -> 0 | Q31: =(ROUND((ROUND((((ET31*1.2))*AV31*I31),2)*BB31),2)+ROUND((ROUND(((AE31-((EU31*1.2)))*AV31*I31),2)*BS31),2)) -> 0 | R31: =(ROUND((ROUND((((EU31*1.2))*AV31*I31),2)*BS31),2)+ROUND((ROUND(((AE31-((EU31*1.2)))*AV31*I31),2)*BS31),2)) -> 0 | S31: =ROUND((ROUND((AF31*AV31*I31),2)*BA31),2) -> 165752.96 | T31: =ROUND(CU31*I31,2) -> 0 | U31: =CV31*I31 -> 279.61383 | V31: =CW31*I31 -> 0 | W31: =ROUND(CX31*I31,2) -> 0 | X31: =(ROUND((((S31+ROUND((ROUND((((EU31*1.2))*AV31*I31),2)*BS31),2))*AT31)/100),2)+ROUND(((ROUND((ROUND(((AE31-((EU31*1.2)))*AV31*I31),2)*BS31),2)*AT31)/100),2)) -> 150835.19 | Y31: =(ROUND((((S31+ROUND((ROUND((((EU31*1.2))*AV31*I31),2)*BS31),2))*AU31)/100),2)+ROUND(((ROUND((ROUND(((AE31-((EU31*1.2)))*AV31*I31),2)*BS31),2)*AU31)/100),2)) -> 79561.42 | AA31: 55890823 | AB31: =ROUND((AC31+AD31+AF31),6) -> 225.84 | AC31: =ROUND(((ES31*1)),6) -> 0 | AD31: =ROUND(((((ET31*1.2))-((EU31*1.2)))+AE31),6) -> 0 | AE31: =ROUND(((EU31*1.2)),6) -> 0 | AF31: =ROUND(((EV31*1.2)),6) -> 225.84 | AG31: =ROUND((AP31),6) -> 0 | AH31: =((EW31*1.2)) -> 21.468 | AI31: =((EX31*1.2)) -> 0 | AJ31: =(AS31) -> 0 | AK31: 188.2 | AL31: 0 | AM31: 0 | AN31: 0 | AO31: 188.2 | AP31: 0 | AQ31: 17.89 | AR31: 0 | AS31: 0 | AT31: 91 | AU31: 48 | AV31: 1.047 | AW31: 1 | AZ31: 1 | BA31: 56.35 | BB31: 1 | BC31: 1 | BH31: 0 | BI31: 1 | BJ31: ТСН-2001.6. Доп. 1-42. Сб. 67, т. 7, поз. 5 | BM31: 106 | BN31: 0 | BO31: 6.67-7-5 | BP31: 1 | BQ31: 60 | BR31: 0 | BS31: 56.35 | BT31: 1 | BU31: 1 | BV31: 1 | BW31: 1 | BX31: 1 | BZ31: 91 | CA31: 48 | CE31: 1566 | CF31: 0 | CG31: 0 | CM31: 0 | CN31: Поправка: Гл.12.Прил.8.п.8. 3_12.00.01.11.001 Наименование: При наличии напряженных и стесненных условий производства работ (стесненность, сложность складирования и транспортной логистики и т.п.) для объектов, расположенных в пределах круговой магистральной системы улиц "Садовое кольцо" города Москвы | CO31: 0 | CP31: =(P31+Q31+S31) -> 165752.96 | CQ31: =ROUND((ROUND((AC31*AW31*1),2)*BC31),2) -> 0 | CR31: =(ROUND((ROUND((((ET31*1.2))*AV31*1),2)*BB31),2)+ROUND((ROUND(((AE31-((EU31*1.2)))*AV31*1),2)*BS31),2)) -> 0 | CS31: =(ROUND((ROUND((((EU31*1.2))*AV31*1),2)*BS31),2)+ROUND((ROUND(((AE31-((EU31*1.2)))*AV31*1),2)*BS31),2)) -> 0 | CT31: =ROUND((ROUND((AF31*AV31*1),2)*BA31),2) -> 13323.96 | CU31: =AG31 -> 0 | CV31: =(AH31*AV31) -> 22.476996 | CW31: =AI31 -> 0 | CX31: =AJ31 -> 0 | CY31: =(ROUND((((S31+ROUND((ROUND((((EU31*1.2))*AV31*1),2)*BS31),2))*AT31)/100),2)+ROUND(((ROUND((ROUND(((AE31-((EU31*1.2)))*AV31*1),2)*BS31),2)*AT31)/100),2)) -> 150835.19 | CZ31: =(ROUND((((S31+ROUND((ROUND((((EU31*1.2))*AV31*1),2)*BS31),2))*AU31)/100),2)+ROUND(((ROUND((ROUND(((AE31-((EU31*1.2)))*AV31*1),2)*BS31),2)*AU31)/100),2)) -> 79561.42 | DB31: 6 | DD31: *1 | DE31: *1,2 | DF31: *1,2 | DG31: *1,2 | DI31: *1,2 | DJ31: *1,2 | DN31: 0 | DO31: 0 | DP31: 1 | DQ31: 1 | DU31: 1010 | DV31: 100 шт. | DW31: 100 шт. | DX31: 100 | EE31: 57042996 | EF31: 60 | EG31: Ремонтно-строительные работы | EH31: 0 | EJ31: 1 | EK31: 106 | EL31: ТСН-2001.6-67. Электромонтажные работы | EM31: ТСН-2001.6-67-1 | EO31: Поправка: Гл.12.Прил.8.п.8. 3_12.00.01.11.001 | EQ31: 0 | ER31: 188.2 | ES31: 0 | ET31: 0 | EU31: 0 | EV31: 188.2 | EW31: 17.89 | EX31: 0 | EY31: 0 | FQ31: 0 | FR31: 0 | FS31: 0 | FX31: 91 | FY31: 48 | GD31: 1 | GF31: -651826134 | GG31: 2 | GH31: 1 | GI31: 2 | GJ31: 0 | GK31: 0 | GL31: =ROUND(IF(AND(BH31=3,BI31=3,FS31<>0),P31,0),2) -> 0 | GM31: =ROUND(O31+X31+Y31,2)+GX31 -> 396149.57 | GN31: =IF(OR(BI31=0,BI31=1),GM31-GX31,0) -> 396149.57 | GO31: =IF(BI31=2,GM31-GX31,0) -> 0 | GP31: =IF(BI31=4,GM31-GX31,0) -> 0 | GR31: 0 | GS31: 3 | GT31: 0 | GV31: =ROUND((GT31),6) -> 0 | GW31: 1 | GX31: =ROUND(HC31*I31,2) -> 0 | HA31: 0 | HB31: 0 | HC31: =GV31*GW31 -> 0 | HS31: 0 | IK31: 0
A32: 17 | B32: 1 | C32: =ROW(SmtRes!A21) -> 21 | D32: =ROW(EtalonRes!A27) -> 27 | F32: 6.67-7-3 | G32: Демонтаж осветительных приборов, светильники с лампами накаливания | H32: 100 шт. | I32: =ROUND(1244/100,9) -> 12.44 | J32: 0 | K32: =ROUND(1244/100,9) -> 12.44 | O32: =ROUND(CP32,2) -> 1009.52 | P32: =ROUND((ROUND((AC32*AW32*I32),2)*BC32),2) -> 0 | Q32: =(ROUND((ROUND((((ET32*1.2))*AV32*I32),2)*BB32),2)+ROUND((ROUND(((AE32-((EU32*1.2)))*AV32*I32),2)*BS32),2)) -> 0 | R32: =(ROUND((ROUND((((EU32*1.2))*AV32*I32),2)*BS32),2)+ROUND((ROUND(((AE32-((EU32*1.2)))*AV32*I32),2)*BS32),2)) -> 0 | S32: =ROUND((ROUND((AF32*AV32*I32),2)*BA32),2) -> 1009.52 | T32: =ROUND(CU32*I32,2) -> 0 | U32: =CV32*I32 -> 98.779173 | V32: =CW32*I32 -> 0 | W32: =ROUND(CX32*I32,2) -> 0 | X32: =(ROUND((((S32+ROUND((ROUND((((EU32*1.2))*AV32*I32),2)*BS32),2))*AT32)/100),2)+ROUND(((ROUND((ROUND(((AE32-((EU32*1.2)))*AV32*I32),2)*BS32),2)*AT32)/100),2)) -> 918.66 | Y32: =(ROUND((((S32+ROUND((ROUND((((EU32*1.2))*AV32*I32),2)*BS32),2))*AU32)/100),2)+ROUND(((ROUND((ROUND(((AE32-((EU32*1.2)))*AV32*I32),2)*BS32),2)*AU32)/100),2)) -> 484.57 | AA32: -1 | AB32: =ROUND((AC32+AD32+AF32),6) -> 77.508 | AC32: =ROUND(((ES32*1)),6) -> 0 | AD32: =ROUND(((((ET32*1.2))-((EU32*1.2)))+AE32),6) -> 0 | AE32: =ROUND(((EU32*1.2)),6) -> 0 | AF32: =ROUND(((EV32*1.2)),6) -> 77.508 | AG32: =ROUND((AP32),6) -> 0 | AH32: =((EW32*1.2)) -> 7.584 | AI32: =((EX32*1.2)) -> 0 | AJ32: =(AS32) -> 0 | AK32: 64.59 | AL32: 0 | AM32: 0 | AN32: 0 | AO32: 64.59 | AP32: 0 | AQ32: 6.32 | AR32: 0 | AS32: 0 | AT32: 91 | AU32: 48 | AV32: 1.047 | AW32: 1 | AZ32: 1 | BA32: 1 | BB32: 1 | BC32: 1 | BH32: 0 | BI32: 1 | BJ32: ТСН-2001.6. Доп. 1-42. Сб. 67, т. 7, поз. 3 | BM32: 106 | BN32: 0 | BO32: 6.67-7-3 | BP32: 1 | BQ32: 60 | BR32: 0 | BS32: 1 | BT32: 1 | BU32: 1 | BV32: 1 | BW32: 1 | BX32: 1 | BZ32: 91 | CA32: 48 | CE32: 1566 | CF32: 0 | CG32: 0 | CM32: 0 | CN32: Поправка: Гл.12.Прил.8.п.8. 3_12.00.01.11.001 Наименование: При наличии напряженных и стесненных условий производства работ (стесненность, сложность складирования и транспортной логистики и т.п.) для объектов, расположенных в пределах круговой магистральной системы улиц "Садовое кольцо" города Москвы | CO32: 0 | CP32: =(P32+Q32+S32) -> 1009.52 | CQ32: =ROUND((ROUND((AC32*AW32*1),2)*BC32),2) -> 0 | CR32: =(ROUND((ROUND((((ET32*1.2))*AV32*1),2)*BB32),2)+ROUND((ROUND(((AE32-((EU32*1.2)))*AV32*1),2)*BS32),2)) -> 0 | CS32: =(ROUND((ROUND((((EU32*1.2))*AV32*1),2)*BS32),2)+ROUND((ROUND(((AE32-((EU32*1.2)))*AV32*1),2)*BS32),2)) -> 0 | CT32: =ROUND((ROUND((AF32*AV32*1),2)*BA32),2) -> 81.15 | CU32: =AG32 -> 0 | CV32: =(AH32*AV32) -> 7.940448 | CW32: =AI32 -> 0 | CX32: =AJ32 -> 0 | CY32: =(ROUND((((S32+ROUND((ROUND((((EU32*1.2))*AV32*1),2)*BS32),2))*AT32)/100),2)+ROUND(((ROUND((ROUND(((AE32-((EU32*1.2)))*AV32*1),2)*BS32),2)*AT32)/100),2)) -> 918.66 | CZ32: =(ROUND((((S32+ROUND((ROUND((((EU32*1.2))*AV32*1),2)*BS32),2))*AU32)/100),2)+ROUND(((ROUND((ROUND(((AE32-((EU32*1.2)))*AV32*1),2)*BS32),2)*AU32)/100),2)) -> 484.57 | DB32: 7 | DD32: *1 | DE32: *1,2 | DF32: *1,2 | DG32: *1,2 | DI32: *1,2 | DJ32: *1,2 | DN32: 0 | DO32: 0 | DP32: 1 | DQ32: 1 | DU32: 1010 | DV32: 100 шт. | DW32: 100 шт. | DX32: 100 | EE32: 57042996 | EF32: 60 | EG32: Ремонтно-строительные работы | EH32: 0 | EJ32: 1 | EK32: 106 | EL32: ТСН-2001.6-67. Электромонтажные работы | EM32: ТСН-2001.6-67-1 | EO32: Поправка: Гл.12.Прил.8.п.8. 3_12.00.01.11.001 | EQ32: 1024 | ER32: 64.59 | ES32: 0 | ET32: 0 | EU32: 0 | EV32: 64.59 | EW32: 6.32 | EX32: 0 | EY32: 0 | FQ32: 0 | FR32: 0 | FS32: 0 | FX32: 91 | FY32: 48 | GD32: 1 | GF32: 1397822307 | GG32: 2 | GH32: 1 | GI32: 2 | GJ32: 0 | GK32: 0 | GL32: =ROUND(IF(AND(BH32=3,BI32=3,FS32<>0),P32,0),2) -> 0 | GM32: =ROUND(O32+X32+Y32,2)+GX32 -> 2412.75 | GN32: =IF(OR(BI32=0,BI32=1),GM32-GX32,0) -> 2412.75 | GO32: =IF(BI32=2,GM32-GX32,0) -> 0 | GP32: =IF(BI32=4,GM32-GX32,0) -> 0 | GR32: 0 | GS32: 3 | GT32: 0 | GV32: =ROUND((GT32),6) -> 0 | GW32: 1 | GX32: =ROUND(HC32*I32,2) -> 0 | HA32: 0 | HB32: 0 | HC32: =GV32*GW32 -> 0 | HS32: 0 | IK32: 0
A33: 17 | B33: 1 | C33: =ROW(SmtRes!A22) -> 22 | D33: =ROW(EtalonRes!A28) -> 28 | F33: 6.67-7-3 | G33: Демонтаж осветительных приборов, светильники с лампами накаливания | H33: 100 шт. | I33: =ROUND(1244/100,9) -> 12.44 | J33: 0 | K33: =ROUND(1244/100,9) -> 12.44 | O33: =ROUND(CP33,2) -> 56886.45 | P33: =ROUND((ROUND((AC33*AW33*I33),2)*BC33),2) -> 0 | Q33: =(ROUND((ROUND((((ET33*1.2))*AV33*I33),2)*BB33),2)+ROUND((ROUND(((AE33-((EU33*1.2)))*AV33*I33),2)*BS33),2)) -> 0 | R33: =(ROUND((ROUND((((EU33*1.2))*AV33*I33),2)*BS33),2)+ROUND((ROUND(((AE33-((EU33*1.2)))*AV33*I33),2)*BS33),2)) -> 0 | S33: =ROUND((ROUND((AF33*AV33*I33),2)*BA33),2) -> 56886.45 | T33: =ROUND(CU33*I33,2) -> 0 | U33: =CV33*I33 -> 98.779173 | V33: =CW33*I33 -> 0 | W33: =ROUND(CX33*I33,2) -> 0 | X33: =(ROUND((((S33+ROUND((ROUND((((EU33*1.2))*AV33*I33),2)*BS33),2))*AT33)/100),2)+ROUND(((ROUND((ROUND(((AE33-((EU33*1.2)))*AV33*I33),2)*BS33),2)*AT33)/100),2)) -> 51766.67 | Y33: =(ROUND((((S33+ROUND((ROUND((((EU33*1.2))*AV33*I33),2)*BS33),2))*AU33)/100),2)+ROUND(((ROUND((ROUND(((AE33-((EU33*1.2)))*AV33*I33),2)*BS33),2)*AU33)/100),2)) -> 27305.5 | AA33: -1 | AB33: =ROUND((AC33+AD33+AF33),6) -> 77.508 | AC33: =ROUND(((ES33*1)),6) -> 0 | AD33: =ROUND(((((ET33*1.2))-((EU33*1.2)))+AE33),6) -> 0 | AE33: =ROUND(((EU33*1.2)),6) -> 0 | AF33: =ROUND(((EV33*1.2)),6) -> 77.508 | AG33: =ROUND((AP33),6) -> 0 | AH33: =((EW33*1.2)) -> 7.584 | AI33: =((EX33*1.2)) -> 0 | AJ33: =(AS33) -> 0 | AK33: 64.59 | AL33: 0 | AM33: 0 | AN33: 0 | AO33: 64.59 | AP33: 0 | AQ33: 6.32 | AR33: 0 | AS33: 0 | AT33: 91 | AU33: 48 | AV33: 1.047 | AW33: 1 | AZ33: 1 | BA33: 56.35 | BB33: 1 | BC33: 1 | BH33: 0 | BI33: 1 | BJ33: ТСН-2001.6. Доп. 1-42. Сб. 67, т. 7, поз. 3 | BM33: 106 | BN33: 0 | BO33: 6.67-7-3 | BP33: 1 | BQ33: 60 | BR33: 0 | BS33: 56.35 | BT33: 1 | BU33: 1 | BV33: 1 | BW33: 1 | BX33: 1 | BZ33: 91 | CA33: 48 | CE33: 1566 | CF33: 0 | CG33: 0 | CM33: 0 | CN33: Поправка: Гл.12.Прил.8.п.8. 3_12.00.01.11.001 Наименование: При наличии напряженных и стесненных условий производства работ (стесненность, сложность складирования и транспортной логистики и т.п.) для объектов, расположенных в пределах круговой магистральной системы улиц "Садовое кольцо" города Москвы | CO33: 0 | CP33: =(P33+Q33+S33) -> 56886.45 | CQ33: =ROUND((ROUND((AC33*AW33*1),2)*BC33),2) -> 0 | CR33: =(ROUND((ROUND((((ET33*1.2))*AV33*1),2)*BB33),2)+ROUND((ROUND(((AE33-((EU33*1.2)))*AV33*1),2)*BS33),2)) -> 0 | CS33: =(ROUND((ROUND((((EU33*1.2))*AV33*1),2)*BS33),2)+ROUND((ROUND(((AE33-((EU33*1.2)))*AV33*1),2)*BS33),2)) -> 0 | CT33: =ROUND((ROUND((AF33*AV33*1),2)*BA33),2) -> 4572.8 | CU33: =AG33 -> 0 | CV33: =(AH33*AV33) -> 7.940448 | CW33: =AI33 -> 0 | CX33: =AJ33 -> 0 | CY33: =(ROUND((((S33+ROUND((ROUND((((EU33*1.2))*AV33*1),2)*BS33),2))*AT33)/100),2)+ROUND(((ROUND((ROUND(((AE33-((EU33*1.2)))*AV33*1),2)*BS33),2)*AT33)/100),2)) -> 51766.67 | CZ33: =(ROUND((((S33+ROUND((ROUND((((EU33*1.2))*AV33*1),2)*BS33),2))*AU33)/100),2)+ROUND(((ROUND((ROUND(((AE33-((EU33*1.2)))*AV33*1),2)*BS33),2)*AU33)/100),2)) -> 27305.5 | DB33: 8 | DD33: *1 | DE33: *1,2 | DF33: *1,2 | DG33: *1,2 | DI33: *1,2 | DJ33: *1,2 | DN33: 0 | DO33: 0 | DP33: 1 | DQ33: 1 | DU33: 1010 | DV33: 100 шт. | DW33: 100 шт. | DX33: 100 | EE33: 57042996 | EF33: 60 | EG33: Ремонтно-строительные работы | EH33: 0 | EJ33: 1 | EK33: 106 | EL33: ТСН-2001.6-67. Электромонтажные работы | EM33: ТСН-2001.6-67-1 | EO33: Поправка: Гл.12.Прил.8.п.8. 3_12.00.01.11.001 | EQ33: 1024 | ER33: 64.59 | ES33: 0 | ET33: 0 | EU33: 0 | EV33: 64.59 | EW33: 6.32 | EX33: 0 | EY33: 0 | FQ33: 0 | FR33: 0 | FS33: 0 | FX33: 91 | FY33: 48 | GD33: 1 | GF33: 1397822307 | GG33: 2 | GH33: 1 | GI33: 2 | GJ33: 0 | GK33: 0 | GL33: =ROUND(IF(AND(BH33=3,BI33=3,FS33<>0),P33,0),2) -> 0 | GM33: =ROUND(O33+X33+Y33,2)+GX33 -> 135958.62 | GN33: =IF(OR(BI33=0,BI33=1),GM33-GX33,0) -> 135958.62 | GO33: =IF(BI33=2,GM33-GX33,0) -> 0 | GP33: =IF(BI33=4,GM33-GX33,0) -> 0 | GR33: 0 | GS33: 3 | GT33: 0 | GV33: =ROUND((GT33),6) -> 0 | GW33: 1 | GX33: =ROUND(HC33*I33,2) -> 0 | HA33: 0 | HB33: 0 | HC33: =GV33*GW33 -> 0 | HS33: 0 | IK33: 0
A34: 17 | B34: 1 | C34: =ROW(SmtRes!A23) -> 23 | D34: =ROW(EtalonRes!A29) -> 29 | E34: 3 | F34: 6.67-7-1 | G34: Демонтаж осветительных приборов, выключатели, розетки | H34: 100 шт. | I34: =ROUND(972/100,9) -> 9.72 | J34: 0 | K34: =ROUND(972/100,9) -> 9.72 | O34: =ROUND(CP34,2) -> 728.82 | P34: =ROUND((ROUND((AC34*AW34*I34),2)*BC34),2) -> 0 | Q34: =(ROUND((ROUND((((ET34*1.2))*AV34*I34),2)*BB34),2)+ROUND((ROUND(((AE34-((EU34*1.2)))*AV34*I34),2)*BS34),2)) -> 0 | R34: =(ROUND((ROUND((((EU34*1.2))*AV34*I34),2)*BS34),2)+ROUND((ROUND(((AE34-((EU34*1.2)))*AV34*I34),2)*BS34),2)) -> 0 | S34: =ROUND((ROUND((AF34*AV34*I34),2)*BA34),2) -> 728.82 | T34: =ROUND(CU34*I34,2) -> 0 | U34: =CV34*I34 -> 71.319295 | V34: =CW34*I34 -> 0 | W34: =ROUND(CX34*I34,2) -> 0 | X34: =(ROUND((((S34+ROUND((ROUND((((EU34*1.2))*AV34*I34),2)*BS34),2))*AT34)/100),2)+ROUND(((ROUND((ROUND(((AE34-((EU34*1.2)))*AV34*I34),2)*BS34),2)*AT34)/100),2)) -> 663.23 | Y34: =(ROUND((((S34+ROUND((ROUND((((EU34*1.2))*AV34*I34),2)*BS34),2))*AU34)/100),2)+ROUND(((ROUND((ROUND(((AE34-((EU34*1.2)))*AV34*I34),2)*BS34),2)*AU34)/100),2)) -> 349.83 | AA34: 54971259 | AB34: =ROUND((AC34+AD34+AF34),6) -> 71.616 | AC34: =ROUND(((ES34*1)),6) -> 0 | AD34: =ROUND(((((ET34*1.2))-((EU34*1.2)))+AE34),6) -> 0 | AE34: =ROUND(((EU34*1.2)),6) -> 0 | AF34: =ROUND(((EV34*1.2)),6) -> 71.616 | AG34: =ROUND((AP34),6) -> 0 | AH34: =((EW34*1.2)) -> 7.008 | AI34: =((EX34*1.2)) -> 0 | AJ34: =(AS34) -> 0 | AK34: 59.68 | AL34: 0 | AM34: 0 | AN34: 0 | AO34: 59.68 | AP34: 0 | AQ34: 5.84 | AR34: 0 | AS34: 0 | AT34: 91 | AU34: 48 | AV34: 1.047 | AW34: 1 | AZ34: 1 | BA34: 1 | BB34: 1 | BC34: 1 | BH34: 0 | BI34: 1 | BJ34: ТСН-2001.6. Доп. 1-42. Сб. 67, т. 7, поз. 1 | BM34: 106 | BN34: 0 | BO34: 6.67-7-1 | BP34: 1 | BQ34: 60 | BR34: 0 | BS34: 1 | BT34: 1 | BU34: 1 | BV34: 1 | BW34: 1 | BX34: 1 | BZ34: 91 | CA34: 48 | CE34: 1566 | CF34: 0 | CG34: 0 | CM34: 0 | CN34: Поправка: Гл.12.Прил.8.п.8. 3_12.00.01.11.001 Наименование: При наличии напряженных и стесненных условий производства работ (стесненность, сложность складирования и транспортной логистики и т.п.) для объектов, расположенных в пределах круговой магистральной системы улиц "Садовое кольцо" города Москвы | CO34: 0 | CP34: =(P34+Q34+S34) -> 728.82 | CQ34: =ROUND((ROUND((AC34*AW34*1),2)*BC34),2) -> 0 | CR34: =(ROUND((ROUND((((ET34*1.2))*AV34*1),2)*BB34),2)+ROUND((ROUND(((AE34-((EU34*1.2)))*AV34*1),2)*BS34),2)) -> 0 | CS34: =(ROUND((ROUND((((EU34*1.2))*AV34*1),2)*BS34),2)+ROUND((ROUND(((AE34-((EU34*1.2)))*AV34*1),2)*BS34),2)) -> 0 | CT34: =ROUND((ROUND((AF34*AV34*1),2)*BA34),2) -> 74.98 | CU34: =AG34 -> 0 | CV34: =(AH34*AV34) -> 7.337376 | CW34: =AI34 -> 0 | CX34: =AJ34 -> 0 | CY34: =(ROUND((((S34+ROUND((ROUND((((EU34*1.2))*AV34*1),2)*BS34),2))*AT34)/100),2)+ROUND(((ROUND((ROUND(((AE34-((EU34*1.2)))*AV34*1),2)*BS34),2)*AT34)/100),2)) -> 663.23 | CZ34: =(ROUND((((S34+ROUND((ROUND((((EU34*1.2))*AV34*1),2)*BS34),2))*AU34)/100),2)+ROUND(((ROUND((ROUND(((AE34-((EU34*1.2)))*AV34*1),2)*BS34),2)*AU34)/100),2)) -> 349.83 | DB34: 9 | DD34: *1 | DE34: *1,2 | DF34: *1,2 | DG34: *1,2 | DI34: *1,2 | DJ34: *1,2 | DN34: 0 | DO34: 0 | DP34: 1 | DQ34: 1 | DU34: 1010 | DV34: 100 шт. | DW34: 100 шт. | DX34: 100 | EE34: 57042996 | EF34: 60 | EG34: Ремонтно-строительные работы | EH34: 0 | EJ34: 1 | EK34: 106 | EL34: ТСН-2001.6-67. Электромонтажные работы | EM34: ТСН-2001.6-67-1 | EO34: Поправка: Гл.12.Прил.8.п.8. 3_12.00.01.11.001 | EQ34: 0 | ER34: 59.68 | ES34: 0 | ET34: 0 | EU34: 0 | EV34: 59.68 | EW34: 5.84 | EX34: 0 | EY34: 0 | FQ34: 0 | FR34: 0 | FS34: 0 | FX34: 91 | FY34: 48 | GD34: 1 | GF34: 1478850760 | GG34: 2 | GH34: 1 | GI34: 2 | GJ34: 0 | GK34: 0 | GL34: =ROUND(IF(AND(BH34=3,BI34=3,FS34<>0),P34,0),2) -> 0 | GM34: =ROUND(O34+X34+Y34,2)+GX34 -> 1741.88 | GN34: =IF(OR(BI34=0,BI34=1),GM34-GX34,0) -> 1741.88 | GO34: =IF(BI34=2,GM34-GX34,0) -> 0 | GP34: =IF(BI34=4,GM34-GX34,0) -> 0 | GR34: 0 | GS34: 3 | GT34: 0 | GV34: =ROUND((GT34),6) -> 0 | GW34: 1 | GX34: =ROUND(HC34*I34,2) -> 0 | HA34: 0 | HB34: 0 | HC34: =GV34*GW34 -> 0 | HS34: 0 | IK34: 0
A35: 17 | B35: 1 | C35: =ROW(SmtRes!A24) -> 24 | D35: =ROW(EtalonRes!A30) -> 30 | E35: 3 | F35: 6.67-7-1 | G35: Демонтаж осветительных приборов, выключатели, розетки | H35: 100 шт. | I35: =ROUND(972/100,9) -> 9.72 | J35: 0 | K35: =ROUND(972/100,9) -> 9.72 | O35: =ROUND(CP35,2) -> 41069.01 | P35: =ROUND((ROUND((AC35*AW35*I35),2)*BC35),2) -> 0 | Q35: =(ROUND((ROUND((((ET35*1.2))*AV35*I35),2)*BB35),2)+ROUND((ROUND(((AE35-((EU35*1.2)))*AV35*I35),2)*BS35),2)) -> 0 | R35: =(ROUND((ROUND((((EU35*1.2))*AV35*I35),2)*BS35),2)+ROUND((ROUND(((AE35-((EU35*1.2)))*AV35*I35),2)*BS35),2)) -> 0 | S35: =ROUND((ROUND((AF35*AV35*I35),2)*BA35),2) -> 41069.01 | T35: =ROUND(CU35*I35,2) -> 0 | U35: =CV35*I35 -> 71.319295 | V35: =CW35*I35 -> 0 | W35: =ROUND(CX35*I35,2) -> 0 | X35: =(ROUND((((S35+ROUND((ROUND((((EU35*1.2))*AV35*I35),2)*BS35),2))*AT35)/100),2)+ROUND(((ROUND((ROUND(((AE35-((EU35*1.2)))*AV35*I35),2)*BS35),2)*AT35)/100),2)) -> 37372.8 | Y35: =(ROUND((((S35+ROUND((ROUND((((EU35*1.2))*AV35*I35),2)*BS35),2))*AU35)/100),2)+ROUND(((ROUND((ROUND(((AE35-((EU35*1.2)))*AV35*I35),2)*BS35),2)*AU35)/100),2)) -> 19713.12 | AA35: 55890823 | AB35: =ROUND((AC35+AD35+AF35),6) -> 71.616 | AC35: =ROUND(((ES35*1)),6) -> 0 | AD35: =ROUND(((((ET35*1.2))-((EU35*1.2)))+AE35),6) -> 0 | AE35: =ROUND(((EU35*1.2)),6) -> 0 | AF35: =ROUND(((EV35*1.2)),6) -> 71.616 | AG35: =ROUND((AP35),6) -> 0 | AH35: =((EW35*1.2)) -> 7.008 | AI35: =((EX35*1.2)) -> 0 | AJ35: =(AS35) -> 0 | AK35: 59.68 | AL35: 0 | AM35: 0 | AN35: 0 | AO35: 59.68 | AP35: 0 | AQ35: 5.84 | AR35: 0 | AS35: 0 | AT35: 91 | AU35: 48 | AV35: 1.047 | AW35: 1 | AZ35: 1 | BA35: 56.35 | BB35: 1 | BC35: 1 | BH35: 0 | BI35: 1 | BJ35: ТСН-2001.6. Доп. 1-42. Сб. 67, т. 7, поз. 1 | BM35: 106 | BN35: 0 | BO35: 6.67-7-1 | BP35: 1 | BQ35: 60 | BR35: 0 | BS35: 56.35 | BT35: 1 | BU35: 1 | BV35: 1 | BW35: 1 | BX35: 1 | BZ35: 91 | CA35: 48 | CE35: 1566 | CF35: 0 | CG35: 0 | CM35: 0 | CN35: Поправка: Гл.12.Прил.8.п.8. 3_12.00.01.11.001 Наименование: При наличии напряженных и стесненных условий производства работ (стесненность, сложность складирования и транспортной логистики и т.п.) для объектов, расположенных в пределах круговой магистральной системы улиц "Садовое кольцо" города Москвы | CO35: 0 | CP35: =(P35+Q35+S35) -> 41069.01 | CQ35: =ROUND((ROUND((AC35*AW35*1),2)*BC35),2) -> 0 | CR35: =(ROUND((ROUND((((ET35*1.2))*AV35*1),2)*BB35),2)+ROUND((ROUND(((AE35-((EU35*1.2)))*AV35*1),2)*BS35),2)) -> 0 | CS35: =(ROUND((ROUND((((EU35*1.2))*AV35*1),2)*BS35),2)+ROUND((ROUND(((AE35-((EU35*1.2)))*AV35*1),2)*BS35),2)) -> 0 | CT35: =ROUND((ROUND((AF35*AV35*1),2)*BA35),2) -> 4225.12 | CU35: =AG35 -> 0 | CV35: =(AH35*AV35) -> 7.337376 | CW35: =AI35 -> 0 | CX35: =AJ35 -> 0 | CY35: =(ROUND((((S35+ROUND((ROUND((((EU35*1.2))*AV35*1),2)*BS35),2))*AT35)/100),2)+ROUND(((ROUND((ROUND(((AE35-((EU35*1.2)))*AV35*1),2)*BS35),2)*AT35)/100),2)) -> 37372.8 | CZ35: =(ROUND((((S35+ROUND((ROUND((((EU35*1.2))*AV35*1),2)*BS35),2))*AU35)/100),2)+ROUND(((ROUND((ROUND(((AE35-((EU35*1.2)))*AV35*1),2)*BS35),2)*AU35)/100),2)) -> 19713.12 | DB35: 10 | DD35: *1 | DE35: *1,2 | DF35: *1,2 | DG35: *1,2 | DI35: *1,2 | DJ35: *1,2 | DN35: 0 | DO35: 0 | DP35: 1 | DQ35: 1 | DU35: 1010 | DV35: 100 шт. | DW35: 100 шт. | DX35: 100 | EE35: 57042996 | EF35: 60 | EG35: Ремонтно-строительные работы | EH35: 0 | EJ35: 1 | EK35: 106 | EL35: ТСН-2001.6-67. Электромонтажные работы | EM35: ТСН-2001.6-67-1 | EO35: Поправка: Гл.12.Прил.8.п.8. 3_12.00.01.11.001 | EQ35: 0 | ER35: 59.68 | ES35: 0 | ET35: 0 | EU35: 0 | EV35: 59.68 | EW35: 5.84 | EX35: 0 | EY35: 0 | FQ35: 0 | FR35: 0 | FS35: 0 | FX35: 91 | FY35: 48 | GD35: 1 | GF35: 1478850760 | GG35: 2 | GH35: 1 | GI35: 2 | GJ35: 0 | GK35: 0 | GL35: =ROUND(IF(AND(BH35=3,BI35=3,FS35<>0),P35,0),2) -> 0 | GM35: =ROUND(O35+X35+Y35,2)+GX35 -> 98154.93 | GN35: =IF(OR(BI35=0,BI35=1),GM35-GX35,0) -> 98154.93 | GO35: =IF(BI35=2,GM35-GX35,0) -> 0 | GP35: =IF(BI35=4,GM35-GX35,0) -> 0 | GR35: 0 | GS35: 3 | GT35: 0 | GV35: =ROUND((GT35),6) -> 0 | GW35: 1 | GX35: =ROUND(HC35*I35,2) -> 0 | HA35: 0 | HB35: 0 | HC35: =GV35*GW35 -> 0 | HS35: 0 | IK35: 0
A36: 17 | B36: 1 | C36: =ROW(SmtRes!A25) -> 25 | D36: =ROW(EtalonRes!A31) -> 31 | E36: 4 | F36: 6.67-6-1 | G36: Демонтаж кабеля | H36: 100 м | I36: =ROUND(30359/100,9) -> 303.59 | J36: 0 | K36: =ROUND(30359/100,9) -> 303.59 | O36: =ROUND(CP36,2) -> 37578.53 | P36: =ROUND((ROUND((AC36*AW36*I36),2)*BC36),2) -> 0 | Q36: =(ROUND((ROUND((((ET36*1.2))*AV36*I36),2)*BB36),2)+ROUND((ROUND(((AE36-((EU36*1.2)))*AV36*I36),2)*BS36),2)) -> 0 | R36: =(ROUND((ROUND((((EU36*1.2))*AV36*I36),2)*BS36),2)+ROUND((ROUND(((AE36-((EU36*1.2)))*AV36*I36),2)*BS36),2)) -> 0 | S36: =ROUND((ROUND((AF36*AV36*I36),2)*BA36),2) -> 37578.53 | T36: =ROUND(CU36*I36,2) -> 0 | U36: =CV36*I36 -> 3676.9898 | V36: =CW36*I36 -> 0 | W36: =ROUND(CX36*I36,2) -> 0 | X36: =(ROUND((((S36+ROUND((ROUND((((EU36*1.2))*AV36*I36),2)*BS36),2))*AT36)/100),2)+ROUND(((ROUND((ROUND(((AE36-((EU36*1.2)))*AV36*I36),2)*BS36),2)*AT36)/100),2)) -> 34196.46 | Y36: =(ROUND((((S36+ROUND((ROUND((((EU36*1.2))*AV36*I36),2)*BS36),2))*AU36)/100),2)+ROUND(((ROUND((ROUND(((AE36-((EU36*1.2)))*AV36*I36),2)*BS36),2)*AU36)/100),2)) -> 18037.69 | AA36: 54971259 | AB36: =ROUND((AC36+AD36+AF36),6) -> 118.224 | AC36: =ROUND(((ES36*1)),6) -> 0 | AD36: =ROUND(((((ET36*1.2))-((EU36*1.2)))+AE36),6) -> 0 | AE36: =ROUND(((EU36*1.2)),6) -> 0 | AF36: =ROUND(((EV36*1.2)),6) -> 118.224 | AG36: =ROUND((AP36),6) -> 0 | AH36: =((EW36*1.2)) -> 11.568 | AI36: =((EX36*1.2)) -> 0 | AJ36: =(AS36) -> 0 | AK36: 98.52 | AL36: 0 | AM36: 0 | AN36: 0 | AO36: 98.52 | AP36: 0 | AQ36: 9.64 | AR36: 0 | AS36: 0 | AT36: 91 | AU36: 48 | AV36: 1.047 | AW36: 1 | AZ36: 1 | BA36: 1 | BB36: 1 | BC36: 1 | BH36: 0 | BI36: 1 | BJ36: ТСН-2001.6. Доп. 1-42. Сб. 67, т. 6, поз. 1 | BM36: 106 | BN36: 0 | BO36: 6.67-6-1 | BP36: 1 | BQ36: 60 | BR36: 0 | BS36: 1 | BT36: 1 | BU36: 1 | BV36: 1 | BW36: 1 | BX36: 1 | BZ36: 91 | CA36: 48 | CE36: 1566 | CF36: 0 | CG36: 0 | CM36: 0 | CN36: Поправка: Гл.12.Прил.8.п.8. 3_12.00.01.11.001 Наименование: При наличии напряженных и стесненных условий производства работ (стесненность, сложность складирования и транспортной логистики и т.п.) для объектов, расположенных в пределах круговой магистральной системы улиц "Садовое кольцо" города Москвы | CO36: 0 | CP36: =(P36+Q36+S36) -> 37578.53 | CQ36: =ROUND((ROUND((AC36*AW36*1),2)*BC36),2) -> 0 | CR36: =(ROUND((ROUND((((ET36*1.2))*AV36*1),2)*BB36),2)+ROUND((ROUND(((AE36-((EU36*1.2)))*AV36*1),2)*BS36),2)) -> 0 | CS36: =(ROUND((ROUND((((EU36*1.2))*AV36*1),2)*BS36),2)+ROUND((ROUND(((AE36-((EU36*1.2)))*AV36*1),2)*BS36),2)) -> 0 | CT36: =ROUND((ROUND((AF36*AV36*1),2)*BA36),2) -> 123.78 | CU36: =AG36 -> 0 | CV36: =(AH36*AV36) -> 12.111696 | CW36: =AI36 -> 0 | CX36: =AJ36 -> 0 | CY36: =(ROUND((((S36+ROUND((ROUND((((EU36*1.2))*AV36*1),2)*BS36),2))*AT36)/100),2)+ROUND(((ROUND((ROUND(((AE36-((EU36*1.2)))*AV36*1),2)*BS36),2)*AT36)/100),2)) -> 34196.46 | CZ36: =(ROUND((((S36+ROUND((ROUND((((EU36*1.2))*AV36*1),2)*BS36),2))*AU36)/100),2)+ROUND(((ROUND((ROUND(((AE36-((EU36*1.2)))*AV36*1),2)*BS36),2)*AU36)/100),2)) -> 18037.69 | DB36: 11 | DD36: *1 | DE36: *1,2 | DF36: *1,2 | DG36: *1,2 | DI36: *1,2 | DJ36: *1,2 | DN36: 0 | DO36: 0 | DP36: 1 | DQ36: 1 | DU36: 1003 | DV36: 100 м | DW36: 100 м | DX36: 100 | EE36: 57042996 | EF36: 60 | EG36: Ремонтно-строительные работы | EH36: 0 | EJ36: 1 | EK36: 106 | EL36: ТСН-2001.6-67. Электромонтажные работы | EM36: ТСН-2001.6-67-1 | EO36: Поправка: Гл.12.Прил.8.п.8. 3_12.00.01.11.001 | EQ36: 0 | ER36: 98.52 | ES36: 0 | ET36: 0 | EU36: 0 | EV36: 98.52 | EW36: 9.64 | EX36: 0 | EY36: 0 | FQ36: 0 | FR36: 0 | FS36: 0 | FX36: 91 | FY36: 48 | GD36: 1 | GF36: 1114236003 | GG36: 2 | GH36: 1 | GI36: 2 | GJ36: 0 | GK36: 0 | GL36: =ROUND(IF(AND(BH36=3,BI36=3,FS36<>0),P36,0),2) -> 0 | GM36: =ROUND(O36+X36+Y36,2)+GX36 -> 89812.68 | GN36: =IF(OR(BI36=0,BI36=1),GM36-GX36,0) -> 89812.68 | GO36: =IF(BI36=2,GM36-GX36,0) -> 0 | GP36: =IF(BI36=4,GM36-GX36,0) -> 0 | GR36: 0 | GS36: 3 | GT36: 0 | GV36: =ROUND((GT36),6) -> 0 | GW36: 1 | GX36: =ROUND(HC36*I36,2) -> 0 | HA36: 0 | HB36: 0 | HC36: =GV36*GW36 -> 0 | HS36: 0 | IK36: 0
A37: 17 | B37: 1 | C37: =ROW(SmtRes!A26) -> 26 | D37: =ROW(EtalonRes!A32) -> 32 | E37: 4 | F37: 6.67-6-1 | G37: Демонтаж кабеля | H37: 100 м | I37: =ROUND(30359/100,9) -> 303.59 | J37: 0 | K37: =ROUND(30359/100,9) -> 303.59 | O37: =ROUND(CP37,2) -> 2117550.2 | P37: =ROUND((ROUND((AC37*AW37*I37),2)*BC37),2) -> 0 | Q37: =(ROUND((ROUND((((ET37*1.2))*AV37*I37),2)*BB37),2)+ROUND((ROUND(((AE37-((EU37*1.2)))*AV37*I37),2)*BS37),2)) -> 0 | R37: =(ROUND((ROUND((((EU37*1.2))*AV37*I37),2)*BS37),2)+ROUND((ROUND(((AE37-((EU37*1.2)))*AV37*I37),2)*BS37),2)) -> 0 | S37: =ROUND((ROUND((AF37*AV37*I37),2)*BA37),2) -> 2117550.2 | T37: =ROUND(CU37*I37,2) -> 0 | U37: =CV37*I37 -> 3676.9898 | V37: =CW37*I37 -> 0 | W37: =ROUND(CX37*I37,2) -> 0 | X37: =(ROUND((((S37+ROUND((ROUND((((EU37*1.2))*AV37*I37),2)*BS37),2))*AT37)/100),2)+ROUND(((ROUND((ROUND(((AE37-((EU37*1.2)))*AV37*I37),2)*BS37),2)*AT37)/100),2)) -> 1926970.6 | Y37: =(ROUND((((S37+ROUND((ROUND((((EU37*1.2))*AV37*I37),2)*BS37),2))*AU37)/100),2)+ROUND(((ROUND((ROUND(((AE37-((EU37*1.2)))*AV37*I37),2)*BS37),2)*AU37)/100),2)) -> 1016424.1 | AA37: 55890823 | AB37: =ROUND((AC37+AD37+AF37),6) -> 118.224 | AC37: =ROUND(((ES37*1)),6) -> 0 | AD37: =ROUND(((((ET37*1.2))-((EU37*1.2)))+AE37),6) -> 0 | AE37: =ROUND(((EU37*1.2)),6) -> 0 | AF37: =ROUND(((EV37*1.2)),6) -> 118.224 | AG37: =ROUND((AP37),6) -> 0 | AH37: =((EW37*1.2)) -> 11.568 | AI37: =((EX37*1.2)) -> 0 | AJ37: =(AS37) -> 0 | AK37: 98.52 | AL37: 0 | AM37: 0 | AN37: 0 | AO37: 98.52 | AP37: 0 | AQ37: 9.64 | AR37: 0 | AS37: 0 | AT37: 91 | AU37: 48 | AV37: 1.047 | AW37: 1 | AZ37: 1 | BA37: 56.35 | BB37: 1 | BC37: 1 | BH37: 0 | BI37: 1 | BJ37: ТСН-2001.6. Доп. 1-42. Сб. 67, т. 6, поз. 1 | BM37: 106 | BN37: 0 | BO37: 6.67-6-1 | BP37: 1 | BQ37: 60 | BR37: 0 | BS37: 56.35 | BT37: 1 | BU37: 1 | BV37: 1 | BW37: 1 | BX37: 1 | BZ37: 91 | CA37: 48 | CE37: 1566 | CF37: 0 | CG37: 0 | CM37: 0 | CN37: Поправка: Гл.12.Прил.8.п.8. 3_12.00.01.11.001 Наименование: При наличии напряженных и стесненных условий производства работ (стесненность, сложность складирования и транспортной логистики и т.п.) для объектов, расположенных в пределах круговой магистральной системы улиц "Садовое кольцо" города Москвы | CO37: 0 | CP37: =(P37+Q37+S37) -> 2117550.2 | CQ37: =ROUND((ROUND((AC37*AW37*1),2)*BC37),2) -> 0 | CR37: =(ROUND((ROUND((((ET37*1.2))*AV37*1),2)*BB37),2)+ROUND((ROUND(((AE37-((EU37*1.2)))*AV37*1),2)*BS37),2)) -> 0 | CS37: =(ROUND((ROUND((((EU37*1.2))*AV37*1),2)*BS37),2)+ROUND((ROUND(((AE37-((EU37*1.2)))*AV37*1),2)*BS37),2)) -> 0 | CT37: =ROUND((ROUND((AF37*AV37*1),2)*BA37),2) -> 6975 | CU37: =AG37 -> 0 | CV37: =(AH37*AV37) -> 12.111696 | CW37: =AI37 -> 0 | CX37: =AJ37 -> 0 | CY37: =(ROUND((((S37+ROUND((ROUND((((EU37*1.2))*AV37*1),2)*BS37),2))*AT37)/100),2)+ROUND(((ROUND((ROUND(((AE37-((EU37*1.2)))*AV37*1),2)*BS37),2)*AT37)/100),2)) -> 1926970.6 | CZ37: =(ROUND((((S37+ROUND((ROUND((((EU37*1.2))*AV37*1),2)*BS37),2))*AU37)/100),2)+ROUND(((ROUND((ROUND(((AE37-((EU37*1.2)))*AV37*1),2)*BS37),2)*AU37)/100),2)) -> 1016424.1 | DB37: 12 | DD37: *1 | DE37: *1,2 | DF37: *1,2 | DG37: *1,2 | DI37: *1,2 | DJ37: *1,2 | DN37: 0 | DO37: 0 | DP37: 1 | DQ37: 1 | DU37: 1003 | DV37: 100 м | DW37: 100 м | DX37: 100 | EE37: 57042996 | EF37: 60 | EG37: Ремонтно-строительные работы | EH37: 0 | EJ37: 1 | EK37: 106 | EL37: ТСН-2001.6-67. Электромонтажные работы | EM37: ТСН-2001.6-67-1 | EO37: Поправка: Гл.12.Прил.8.п.8. 3_12.00.01.11.001 | EQ37: 0 | ER37: 98.52 | ES37: 0 | ET37: 0 | EU37: 0 | EV37: 98.52 | EW37: 9.64 | EX37: 0 | EY37: 0 | FQ37: 0 | FR37: 0 | FS37: 0 | FX37: 91 | FY37: 48 | GD37: 1 | GF37: 1114236003 | GG37: 2 | GH37: 1 | GI37: 2 | GJ37: 0 | GK37: 0 | GL37: =ROUND(IF(AND(BH37=3,BI37=3,FS37<>0),P37,0),2) -> 0 | GM37: =ROUND(O37+X37+Y37,2)+GX37 -> 5060944.9 | GN37: =IF(OR(BI37=0,BI37=1),GM37-GX37,0) -> 5060944.9 | GO37: =IF(BI37=2,GM37-GX37,0) -> 0 | GP37: =IF(BI37=4,GM37-GX37,0) -> 0 | GR37: 0 | GS37: 3 | GT37: 0 | GV37: =ROUND((GT37),6) -> 0 | GW37: 1 | GX37: =ROUND(HC37*I37,2) -> 0 | HA37: 0 | HB37: 0 | HC37: =GV37*GW37 -> 0 | HS37: 0 | IK37: 0
A38: 17 | B38: 1 | C38: =ROW(SmtRes!A28) -> 28 | D38: =ROW(EtalonRes!A34) -> 34 | E38: 5 | F38: 6.67-5-13 | G38: Демонтаж трубных проводок, трубы в борозде диаметром 40 мм / стальных | H38: 100 м | I38: =ROUND((550)/100,9) -> 5.5 | J38: 0 | K38: =ROUND((550)/100,9) -> 5.5 | O38: =ROUND(CP38,2) -> 3791.97 | P38: =ROUND((ROUND((AC38*AW38*I38),2)*BC38),2) -> 0 | Q38: =(ROUND((ROUND((((ET38*1.2))*AV38*I38),2)*BB38),2)+ROUND((ROUND(((AE38-((EU38*1.2)))*AV38*I38),2)*BS38),2)) -> 0 | R38: =(ROUND((ROUND((((EU38*1.2))*AV38*I38),2)*BS38),2)+ROUND((ROUND(((AE38-((EU38*1.2)))*AV38*I38),2)*BS38),2)) -> 0 | S38: =ROUND((ROUND((AF38*AV38*I38),2)*BA38),2) -> 3791.97 | T38: =ROUND(CU38*I38,2) -> 0 | U38: =CV38*I38 -> 348.20498 | V38: =CW38*I38 -> 0 | W38: =ROUND(CX38*I38,2) -> 0 | X38: =(ROUND((((S38+ROUND((ROUND((((EU38*1.2))*AV38*I38),2)*BS38),2))*AT38)/100),2)+ROUND(((ROUND((ROUND(((AE38-((EU38*1.2)))*AV38*I38),2)*BS38),2)*AT38)/100),2)) -> 3450.69 | Y38: =(ROUND((((S38+ROUND((ROUND((((EU38*1.2))*AV38*I38),2)*BS38),2))*AU38)/100),2)+ROUND(((ROUND((ROUND(((AE38-((EU38*1.2)))*AV38*I38),2)*BS38),2)*AU38)/100),2)) -> 1820.15 | AA38: 54971259 | AB38: =ROUND((AC38+AD38+AF38),6) -> 658.5 | AC38: =ROUND(((ES38*1)),6) -> 0 | AD38: =ROUND(((((ET38*1.2))-((EU38*1.2)))+AE38),6) -> 0 | AE38: =ROUND(((EU38*1.2)),6) -> 0 | AF38: =ROUND(((EV38*1.2)),6) -> 658.5 | AG38: =ROUND((AP38),6) -> 0 | AH38: =((EW38*1.2)) -> 60.468 | AI38: =((EX38*1.2)) -> 0 | AJ38: =(AS38) -> 0 | AK38: 548.75 | AL38: 0 | AM38: 0 | AN38: 0 | AO38: 548.75 | AP38: 0 | AQ38: 50.39 | AR38: 0 | AS38: 0 | AT38: 91 | AU38: 48 | AV38: 1.047 | AW38: 1 | AZ38: 1 | BA38: 1 | BB38: 1 | BC38: 1 | BH38: 0 | BI38: 1 | BJ38: ТСН-2001.6. Доп. 1-42. Сб. 67, т. 5, поз. 13 | BM38: 106 | BN38: 0 | BO38: 6.67-5-13 | BP38: 1 | BQ38: 60 | BR38: 0 | BS38: 1 | BT38: 1 | BU38: 1 | BV38: 1 | BW38: 1 | BX38: 1 | BZ38: 91 | CA38: 48 | CE38: 1566 | CF38: 0 | CG38: 0 | CM38: 0 | CN38: Поправка: Гл.12.Прил.8.п.8. 3_12.00.01.11.001 Наименование: При наличии напряженных и стесненных условий производства работ (стесненность, сложность складирования и транспортной логистики и т.п.) для объектов, расположенных в пределах круговой магистральной системы улиц "Садовое кольцо" города Москвы | CO38: 0 | CP38: =(P38+Q38+S38) -> 3791.97 | CQ38: =ROUND((ROUND((AC38*AW38*1),2)*BC38),2) -> 0 | CR38: =(ROUND((ROUND((((ET38*1.2))*AV38*1),2)*BB38),2)+ROUND((ROUND(((AE38-((EU38*1.2)))*AV38*1),2)*BS38),2)) -> 0 | CS38: =(ROUND((ROUND((((EU38*1.2))*AV38*1),2)*BS38),2)+ROUND((ROUND(((AE38-((EU38*1.2)))*AV38*1),2)*BS38),2)) -> 0 | CT38: =ROUND((ROUND((AF38*AV38*1),2)*BA38),2) -> 689.45 | CU38: =AG38 -> 0 | CV38: =(AH38*AV38) -> 63.309996 | CW38: =AI38 -> 0 | CX38: =AJ38 -> 0 | CY38: =(ROUND((((S38+ROUND((ROUND((((EU38*1.2))*AV38*1),2)*BS38),2))*AT38)/100),2)+ROUND(((ROUND((ROUND(((AE38-((EU38*1.2)))*AV38*1),2)*BS38),2)*AT38)/100),2)) -> 3450.69 | CZ38: =(ROUND((((S38+ROUND((ROUND((((EU38*1.2))*AV38*1),2)*BS38),2))*AU38)/100),2)+ROUND(((ROUND((ROUND(((AE38-((EU38*1.2)))*AV38*1),2)*BS38),2)*AU38)/100),2)) -> 1820.15 | DB38: 13 | DD38: *1 | DE38: *1,2 | DF38: *1,2 | DG38: *1,2 | DI38: *1,2 | DJ38: *1,2 | DN38: 0 | DO38: 0 | DP38: 1 | DQ38: 1 | DU38: 1003 | DV38: 100 м | DW38: 100 м | DX38: 100 | EE38: 57042996 | EF38: 60 | EG38: Ремонтно-строительные работы | EH38: 0 | EJ38: 1 | EK38: 106 | EL38: ТСН-2001.6-67. Электромонтажные работы | EM38: ТСН-2001.6-67-1 | EO38: Поправка: Гл.12.Прил.8.п.8. 3_12.00.01.11.001 | EQ38: 0 | ER38: 548.75 | ES38: 0 | ET38: 0 | EU38: 0 | EV38: 548.75 | EW38: 50.39 | EX38: 0 | EY38: 0 | FQ38: 0 | FR38: 0 | FS38: 0 | FX38: 91 | FY38: 48 | GD38: 1 | GF38: -1102157239 | GG38: 2 | GH38: 1 | GI38: 2 | GJ38: 0 | GK38: 0 | GL38: =ROUND(IF(AND(BH38=3,BI38=3,FS38<>0),P38,0),2) -> 0 | GM38: =ROUND(O38+X38+Y38,2)+GX38 -> 9062.81 | GN38: =IF(OR(BI38=0,BI38=1),GM38-GX38,0) -> 9062.81 | GO38: =IF(BI38=2,GM38-GX38,0) -> 0 | GP38: =IF(BI38=4,GM38-GX38,0) -> 0 | GR38: 0 | GS38: 3 | GT38: 0 | GV38: =ROUND((GT38),6) -> 0 | GW38: 1 | GX38: =ROUND(HC38*I38,2) -> 0 | HA38: 0 | HB38: 0 | HC38: =GV38*GW38 -> 0 | HS38: 0 | IK38: 0
A39: 17 | B39: 1 | C39: =ROW(SmtRes!A30) -> 30 | D39: =ROW(EtalonRes!A36) -> 36 | E39: 5 | F39: 6.67-5-13 | G39: Демонтаж трубных проводок, трубы в борозде диаметром 40 мм / стальных | H39: 100 м | I39: =ROUND((550)/100,9) -> 5.5 | J39: 0 | K39: =ROUND((550)/100,9) -> 5.5 | O39: =ROUND(CP39,2) -> 213677.51 | P39: =ROUND((ROUND((AC39*AW39*I39),2)*BC39),2) -> 0 | Q39: =(ROUND((ROUND((((ET39*1.2))*AV39*I39),2)*BB39),2)+ROUND((ROUND(((AE39-((EU39*1.2)))*AV39*I39),2)*BS39),2)) -> 0 | R39: =(ROUND((ROUND((((EU39*1.2))*AV39*I39),2)*BS39),2)+ROUND((ROUND(((AE39-((EU39*1.2)))*AV39*I39),2)*BS39),2)) -> 0 | S39: =ROUND((ROUND((AF39*AV39*I39),2)*BA39),2) -> 213677.51 | T39: =ROUND(CU39*I39,2) -> 0 | U39: =CV39*I39 -> 348.20498 | V39: =CW39*I39 -> 0 | W39: =ROUND(CX39*I39,2) -> 0 | X39: =(ROUND((((S39+ROUND((ROUND((((EU39*1.2))*AV39*I39),2)*BS39),2))*AT39)/100),2)+ROUND(((ROUND((ROUND(((AE39-((EU39*1.2)))*AV39*I39),2)*BS39),2)*AT39)/100),2)) -> 194446.53 | Y39: =(ROUND((((S39+ROUND((ROUND((((EU39*1.2))*AV39*I39),2)*BS39),2))*AU39)/100),2)+ROUND(((ROUND((ROUND(((AE39-((EU39*1.2)))*AV39*I39),2)*BS39),2)*AU39)/100),2)) -> 102565.2 | AA39: 55890823 | AB39: =ROUND((AC39+AD39+AF39),6) -> 658.5 | AC39: =ROUND(((ES39*1)),6) -> 0 | AD39: =ROUND(((((ET39*1.2))-((EU39*1.2)))+AE39),6) -> 0 | AE39: =ROUND(((EU39*1.2)),6) -> 0 | AF39: =ROUND(((EV39*1.2)),6) -> 658.5 | AG39: =ROUND((AP39),6) -> 0 | AH39: =((EW39*1.2)) -> 60.468 | AI39: =((EX39*1.2)) -> 0 | AJ39: =(AS39) -> 0 | AK39: 548.75 | AL39: 0 | AM39: 0 | AN39: 0 | AO39: 548.75 | AP39: 0 | AQ39: 50.39 | AR39: 0 | AS39: 0 | AT39: 91 | AU39: 48 | AV39: 1.047 | AW39: 1 | AZ39: 1 | BA39: 56.35 | BB39: 1 | BC39: 1 | BH39: 0 | BI39: 1 | BJ39: ТСН-2001.6. Доп. 1-42. Сб. 67, т. 5, поз. 13 | BM39: 106 | BN39: 0 | BO39: 6.67-5-13 | BP39: 1 | BQ39: 60 | BR39: 0 | BS39: 56.35 | BT39: 1 | BU39: 1 | BV39: 1 | BW39: 1 | BX39: 1 | BZ39: 91 | CA39: 48 | CE39: 1566 | CF39: 0 | CG39: 0 | CM39: 0 | CN39: Поправка: Гл.12.Прил.8.п.8. 3_12.00.01.11.001 Наименование: При наличии напряженных и стесненных условий производства работ (стесненность, сложность складирования и транспортной логистики и т.п.) для объектов, расположенных в пределах круговой магистральной системы улиц "Садовое кольцо" города Москвы | CO39: 0 | CP39: =(P39+Q39+S39) -> 213677.51 | CQ39: =ROUND((ROUND((AC39*AW39*1),2)*BC39),2) -> 0 | CR39: =(ROUND((ROUND((((ET39*1.2))*AV39*1),2)*BB39),2)+ROUND((ROUND(((AE39-((EU39*1.2)))*AV39*1),2)*BS39),2)) -> 0 | CS39: =(ROUND((ROUND((((EU39*1.2))*AV39*1),2)*BS39),2)+ROUND((ROUND(((AE39-((EU39*1.2)))*AV39*1),2)*BS39),2)) -> 0 | CT39: =ROUND((ROUND((AF39*AV39*1),2)*BA39),2) -> 38850.51 | CU39: =AG39 -> 0 | CV39: =(AH39*AV39) -> 63.309996 | CW39: =AI39 -> 0 | CX39: =AJ39 -> 0 | CY39: =(ROUND((((S39+ROUND((ROUND((((EU39*1.2))*AV39*1),2)*BS39),2))*AT39)/100),2)+ROUND(((ROUND((ROUND(((AE39-((EU39*1.2)))*AV39*1),2)*BS39),2)*AT39)/100),2)) -> 194446.53 | CZ39: =(ROUND((((S39+ROUND((ROUND((((EU39*1.2))*AV39*1),2)*BS39),2))*AU39)/100),2)+ROUND(((ROUND((ROUND(((AE39-((EU39*1.2)))*AV39*1),2)*BS39),2)*AU39)/100),2)) -> 102565.2 | DB39: 14 | DD39: *1 | DE39: *1,2 | DF39: *1,2 | DG39: *1,2 | DI39: *1,2 | DJ39: *1,2 | DN39: 0 | DO39: 0 | DP39: 1 | DQ39: 1 | DU39: 1003 | DV39: 100 м | DW39: 100 м | DX39: 100 | EE39: 57042996 | EF39: 60 | EG39: Ремонтно-строительные работы | EH39: 0 | EJ39: 1 | EK39: 106 | EL39: ТСН-2001.6-67. Электромонтажные работы | EM39: ТСН-2001.6-67-1 | EO39: Поправка: Гл.12.Прил.8.п.8. 3_12.00.01.11.001 | EQ39: 0 | ER39: 548.75 | ES39: 0 | ET39: 0 | EU39: 0 | EV39: 548.75 | EW39: 50.39 | EX39: 0 | EY39: 0 | FQ39: 0 | FR39: 0 | FS39: 0 | FX39: 91 | FY39: 48 | GD39: 1 | GF39: -1102157239 | GG39: 2 | GH39: 1 | GI39: 2 | GJ39: 0 | GK39: 0 | GL39: =ROUND(IF(AND(BH39=3,BI39=3,FS39<>0),P39,0),2) -> 0 | GM39: =ROUND(O39+X39+Y39,2)+GX39 -> 510689.24 | GN39: =IF(OR(BI39=0,BI39=1),GM39-GX39,0) -> 510689.24 | GO39: =IF(BI39=2,GM39-GX39,0) -> 0 | GP39: =IF(BI39=4,GM39-GX39,0) -> 0 | GR39: 0 | GS39: 3 | GT39: 0 | GV39: =ROUND((GT39),6) -> 0 | GW39: 1 | GX39: =ROUND(HC39*I39,2) -> 0 | HA39: 0 | HB39: 0 | HC39: =GV39*GW39 -> 0 | HS39: 0 | IK39: 0
A40: 17 | B40: 1 | C40: =ROW(SmtRes!A32) -> 32 | D40: =ROW(EtalonRes!A38) -> 38 | E40: 6 | F40: 6.67-5-12 | G40: Демонтаж трубных проводок, трубы в борозде диаметром 25 мм / ПВХ | H40: 100 м | I40: =ROUND((14920)/100,9) -> 149.2 | J40: 0 | K40: =ROUND((14920)/100,9) -> 149.2 | O40: =ROUND(CP40,2) -> 60028.68 | P40: =ROUND((ROUND((AC40*AW40*I40),2)*BC40),2) -> 0 | Q40: =(ROUND((ROUND((((ET40*1.2))*AV40*I40),2)*BB40),2)+ROUND((ROUND(((AE40-((EU40*1.2)))*AV40*I40),2)*BS40),2)) -> 0 | R40: =(ROUND((ROUND((((EU40*1.2))*AV40*I40),2)*BS40),2)+ROUND((ROUND(((AE40-((EU40*1.2)))*AV40*I40),2)*BS40),2)) -> 0 | S40: =ROUND((ROUND((AF40*AV40*I40),2)*BA40),2) -> 60028.68 | T40: =ROUND(CU40*I40,2) -> 0 | U40: =CV40*I40 -> 5706.1265 | V40: =CW40*I40 -> 0 | W40: =ROUND(CX40*I40,2) -> 0 | X40: =(ROUND((((S40+ROUND((ROUND((((EU40*1.2))*AV40*I40),2)*BS40),2))*AT40)/100),2)+ROUND(((ROUND((ROUND(((AE40-((EU40*1.2)))*AV40*I40),2)*BS40),2)*AT40)/100),2)) -> 54626.1 | Y40: =(ROUND((((S40+ROUND((ROUND((((EU40*1.2))*AV40*I40),2)*BS40),2))*AU40)/100),2)+ROUND(((ROUND((ROUND(((AE40-((EU40*1.2)))*AV40*I40),2)*BS40),2)*AU40)/100),2)) -> 28813.77 | AA40: 54971259 | AB40: =ROUND((AC40+AD40+AF40),6) -> 384.276 | AC40: =ROUND(((ES40*1)),6) -> 0 | AD40: =ROUND(((((ET40*1.2))-((EU40*1.2)))+AE40),6) -> 0 | AE40: =ROUND(((EU40*1.2)),6) -> 0 | AF40: =ROUND(((EV40*1.2)),6) -> 384.276 | AG40: =ROUND((AP40),6) -> 0 | AH40: =((EW40*1.2)) -> 36.528 | AI40: =((EX40*1.2)) -> 0 | AJ40: =(AS40) -> 0 | AK40: 320.23 | AL40: 0 | AM40: 0 | AN40: 0 | AO40: 320.23 | AP40: 0 | AQ40: 30.44 | AR40: 0 | AS40: 0 | AT40: 91 | AU40: 48 | AV40: 1.047 | AW40: 1 | AZ40: 1 | BA40: 1 | BB40: 1 | BC40: 1 | BH40: 0 | BI40: 1 | BJ40: ТСН-2001.6. Доп. 1-42. Сб. 67, т. 5, поз. 12 | BM40: 106 | BN40: 0 | BO40: 6.67-5-12 | BP40: 1 | BQ40: 60 | BR40: 0 | BS40: 1 | BT40: 1 | BU40: 1 | BV40: 1 | BW40: 1 | BX40: 1 | BZ40: 91 | CA40: 48 | CE40: 1566 | CF40: 0 | CG40: 0 | CM40: 0 | CN40: Поправка: Гл.12.Прил.8.п.8. 3_12.00.01.11.001 Наименование: При наличии напряженных и стесненных условий производства работ (стесненность, сложность складирования и транспортной логистики и т.п.) для объектов, расположенных в пределах круговой магистральной системы улиц "Садовое кольцо" города Москвы | CO40: 0 | CP40: =(P40+Q40+S40) -> 60028.68 | CQ40: =ROUND((ROUND((AC40*AW40*1),2)*BC40),2) -> 0 | CR40: =(ROUND((ROUND((((ET40*1.2))*AV40*1),2)*BB40),2)+ROUND((ROUND(((AE40-((EU40*1.2)))*AV40*1),2)*BS40),2)) -> 0 | CS40: =(ROUND((ROUND((((EU40*1.2))*AV40*1),2)*BS40),2)+ROUND((ROUND(((AE40-((EU40*1.2)))*AV40*1),2)*BS40),2)) -> 0 | CT40: =ROUND((ROUND((AF40*AV40*1),2)*BA40),2) -> 402.34 | CU40: =AG40 -> 0 | CV40: =(AH40*AV40) -> 38.244816 | CW40: =AI40 -> 0 | CX40: =AJ40 -> 0 | CY40: =(ROUND((((S40+ROUND((ROUND((((EU40*1.2))*AV40*1),2)*BS40),2))*AT40)/100),2)+ROUND(((ROUND((ROUND(((AE40-((EU40*1.2)))*AV40*1),2)*BS40),2)*AT40)/100),2)) -> 54626.1 | CZ40: =(ROUND((((S40+ROUND((ROUND((((EU40*1.2))*AV40*1),2)*BS40),2))*AU40)/100),2)+ROUND(((ROUND((ROUND(((AE40-((EU40*1.2)))*AV40*1),2)*BS40),2)*AU40)/100),2)) -> 28813.77 | DB40: 15 | DD40: *1 | DE40: *1,2 | DF40: *1,2 | DG40: *1,2 | DI40: *1,2 | DJ40: *1,2 | DN40: 0 | DO40: 0 | DP40: 1 | DQ40: 1 | DU40: 1003 | DV40: 100 м | DW40: 100 м | DX40: 100 | EE40: 57042996 | EF40: 60 | EG40: Ремонтно-строительные работы | EH40: 0 | EJ40: 1 | EK40: 106 | EL40: ТСН-2001.6-67. Электромонтажные работы | EM40: ТСН-2001.6-67-1 | EO40: Поправка: Гл.12.Прил.8.п.8. 3_12.00.01.11.001 | EQ40: 0 | ER40: 320.23 | ES40: 0 | ET40: 0 | EU40: 0 | EV40: 320.23 | EW40: 30.44 | EX40: 0 | EY40: 0 | FQ40: 0 | FR40: 0 | FS40: 0 | FX40: 91 | FY40: 48 | GD40: 1 | GF40: -1403822920 | GG40: 2 | GH40: 1 | GI40: 2 | GJ40: 0 | GK40: 0 | GL40: =ROUND(IF(AND(BH40=3,BI40=3,FS40<>0),P40,0),2) -> 0 | GM40: =ROUND(O40+X40+Y40,2)+GX40 -> 143468.55 | GN40: =IF(OR(BI40=0,BI40=1),GM40-GX40,0) -> 143468.55 | GO40: =IF(BI40=2,GM40-GX40,0) -> 0 | GP40: =IF(BI40=4,GM40-GX40,0) -> 0 | GR40: 0 | GS40: 3 | GT40: 0 | GV40: =ROUND((GT40),6) -> 0 | GW40: 1 | GX40: =ROUND(HC40*I40,2) -> 0 | HA40: 0 | HB40: 0 | HC40: =GV40*GW40 -> 0 | HS40: 0 | IK40: 0
A41: 17 | B41: 1 | C41: =ROW(SmtRes!A34) -> 34 | D41: =ROW(EtalonRes!A40) -> 40 | E41: 6 | F41: 6.67-5-12 | G41: Демонтаж трубных проводок, трубы в борозде диаметром 25 мм / ПВХ | H41: 100 м | I41: =ROUND((14920)/100,9) -> 149.2 | J41: 0 | K41: =ROUND((14920)/100,9) -> 149.2 | O41: =ROUND(CP41,2) -> 3382616.1 | P41: =ROUND((ROUND((AC41*AW41*I41),2)*BC41),2) -> 0 | Q41: =(ROUND((ROUND((((ET41*1.2))*AV41*I41),2)*BB41),2)+ROUND((ROUND(((AE41-((EU41*1.2)))*AV41*I41),2)*BS41),2)) -> 0 | R41: =(ROUND((ROUND((((EU41*1.2))*AV41*I41),2)*BS41),2)+ROUND((ROUND(((AE41-((EU41*1.2)))*AV41*I41),2)*BS41),2)) -> 0 | S41: =ROUND((ROUND((AF41*AV41*I41),2)*BA41),2) -> 3382616.1 | T41: =ROUND(CU41*I41,2) -> 0 | U41: =CV41*I41 -> 5706.1265 | V41: =CW41*I41 -> 0 | W41: =ROUND(CX41*I41,2) -> 0 | X41: =(ROUND((((S41+ROUND((ROUND((((EU41*1.2))*AV41*I41),2)*BS41),2))*AT41)/100),2)+ROUND(((ROUND((ROUND(((AE41-((EU41*1.2)))*AV41*I41),2)*BS41),2)*AT41)/100),2)) -> 3078180.7 | Y41: =(ROUND((((S41+ROUND((ROUND((((EU41*1.2))*AV41*I41),2)*BS41),2))*AU41)/100),2)+ROUND(((ROUND((ROUND(((AE41-((EU41*1.2)))*AV41*I41),2)*BS41),2)*AU41)/100),2)) -> 1623655.7 | AA41: 55890823 | AB41: =ROUND((AC41+AD41+AF41),6) -> 384.276 | AC41: =ROUND(((ES41*1)),6) -> 0 | AD41: =ROUND(((((ET41*1.2))-((EU41*1.2)))+AE41),6) -> 0 | AE41: =ROUND(((EU41*1.2)),6) -> 0 | AF41: =ROUND(((EV41*1.2)),6) -> 384.276 | AG41: =ROUND((AP41),6) -> 0 | AH41: =((EW41*1.2)) -> 36.528 | AI41: =((EX41*1.2)) -> 0 | AJ41: =(AS41) -> 0 | AK41: 320.23 | AL41: 0 | AM41: 0 | AN41: 0 | AO41: 320.23 | AP41: 0 | AQ41: 30.44 | AR41: 0 | AS41: 0 | AT41: 91 | AU41: 48 | AV41: 1.047 | AW41: 1 | AZ41: 1 | BA41: 56.35 | BB41: 1 | BC41: 1 | BH41: 0 | BI41: 1 | BJ41: ТСН-2001.6. Доп. 1-42. Сб. 67, т. 5, поз. 12 | BM41: 106 | BN41: 0 | BO41: 6.67-5-12 | BP41: 1 | BQ41: 60 | BR41: 0 | BS41: 56.35 | BT41: 1 | BU41: 1 | BV41: 1 | BW41: 1 | BX41: 1 | BZ41: 91 | CA41: 48 | CE41: 1566 | CF41: 0 | CG41: 0 | CM41: 0 | CN41: Поправка: Гл.12.Прил.8.п.8. 3_12.00.01.11.001 Наименование: При наличии напряженных и стесненных условий производства работ (стесненность, сложность складирования и транспортной логистики и т.п.) для объектов, расположенных в пределах круговой магистральной системы улиц "Садовое кольцо" города Москвы | CO41: 0 | CP41: =(P41+Q41+S41) -> 3382616.1 | CQ41: =ROUND((ROUND((AC41*AW41*1),2)*BC41),2) -> 0 | CR41: =(ROUND((ROUND((((ET41*1.2))*AV41*1),2)*BB41),2)+ROUND((ROUND(((AE41-((EU41*1.2)))*AV41*1),2)*BS41),2)) -> 0 | CS41: =(ROUND((ROUND((((EU41*1.2))*AV41*1),2)*BS41),2)+ROUND((ROUND(((AE41-((EU41*1.2)))*AV41*1),2)*BS41),2)) -> 0 | CT41: =ROUND((ROUND((AF41*AV41*1),2)*BA41),2) -> 22671.86 | CU41: =AG41 -> 0 | CV41: =(AH41*AV41) -> 38.244816 | CW41: =AI41 -> 0 | CX41: =AJ41 -> 0 | CY41: =(ROUND((((S41+ROUND((ROUND((((EU41*1.2))*AV41*1),2)*BS41),2))*AT41)/100),2)+ROUND(((ROUND((ROUND(((AE41-((EU41*1.2)))*AV41*1),2)*BS41),2)*AT41)/100),2)) -> 3078180.7 | CZ41: =(ROUND((((S41+ROUND((ROUND((((EU41*1.2))*AV41*1),2)*BS41),2))*AU41)/100),2)+ROUND(((ROUND((ROUND(((AE41-((EU41*1.2)))*AV41*1),2)*BS41),2)*AU41)/100),2)) -> 1623655.7 | DB41: 16 | DD41: *1 | DE41: *1,2 | DF41: *1,2 | DG41: *1,2 | DI41: *1,2 | DJ41: *1,2 | DN41: 0 | DO41: 0 | DP41: 1 | DQ41: 1 | DU41: 1003 | DV41: 100 м | DW41: 100 м | DX41: 100 | EE41: 57042996 | EF41: 60 | EG41: Ремонтно-строительные работы | EH41: 0 | EJ41: 1 | EK41: 106 | EL41: ТСН-2001.6-67. Электромонтажные работы | EM41: ТСН-2001.6-67-1 | EO41: Поправка: Гл.12.Прил.8.п.8. 3_12.00.01.11.001 | EQ41: 0 | ER41: 320.23 | ES41: 0 | ET41: 0 | EU41: 0 | EV41: 320.23 | EW41: 30.44 | EX41: 0 | EY41: 0 | FQ41: 0 | FR41: 0 | FS41: 0 | FX41: 91 | FY41: 48 | GD41: 1 | GF41: -1403822920 | GG41: 2 | GH41: 1 | GI41: 2 | GJ41: 0 | GK41: 0 | GL41: =ROUND(IF(AND(BH41=3,BI41=3,FS41<>0),P41,0),2) -> 0 | GM41: =ROUND(O41+X41+Y41,2)+GX41 -> 8084452.5 | GN41: =IF(OR(BI41=0,BI41=1),GM41-GX41,0) -> 8084452.5 | GO41: =IF(BI41=2,GM41-GX41,0) -> 0 | GP41: =IF(BI41=4,GM41-GX41,0) -> 0 | GR41: 0 | GS41: 3 | GT41: 0 | GV41: =ROUND((GT41),6) -> 0 | GW41: 1 | GX41: =ROUND(HC41*I41,2) -> 0 | HA41: 0 | HB41: 0 | HC41: =GV41*GW41 -> 0 | HS41: 0 | IK41: 0
A42: 19 | B42: 1 | G42: Демонтаж низковольтного оборудования | AA42: 1 | IK42: 0
A43: 17 | B43: 1 | C43: =ROW(SmtRes!A44) -> 44 | D43: =ROW(EtalonRes!A53) -> 53 | E43: 7 | F43: 4.8-238-2 | G43: Монтаж щитов и стеллажей с блоками резисторов (ящиками сопротивлений) высотой свыше 1700 мм, щита, собираемого из отдельных панелей и блоков управления, однорядного или двухрядного, без блоков резисторов глубиной до 800 мм шкафного исполнения / демонтаж вводных панелей ВП1, ВП2 | H43: 1 м ширины по фронту | I43: =ROUND(0.6*2,9) -> 1.2 | J43: 0 | K43: =ROUND(0.6*2,9) -> 1.2 | O43: =ROUND(CP43,2) -> 164.12 | P43: =ROUND((ROUND((AC43*AW43*I43),2)*BC43),2) -> 0 | Q43: =(ROUND((ROUND(((((ET43*1.2)*0.3))*AV43*I43),2)*BB43),2)+ROUND((ROUND(((AE43-(((EU43*1.2)*0.3)))*AV43*I43),2)*BS43),2)) -> 43.09 | R43: =(ROUND((ROUND(((((EU43*1.2)*0.3))*AV43*I43),2)*BS43),2)+ROUND((ROUND(((AE43-(((EU43*1.2)*0.3)))*AV43*I43),2)*BS43),2)) -> 5.25 | S43: =ROUND((ROUND((AF43*AV43*I43),2)*BA43),2) -> 121.03 | T43: =ROUND(CU43*I43,2) -> 0 | U43: =CV43*I43 -> 9.3174624 | V43: =CW43*I43 -> 0 | W43: =ROUND(CX43*I43,2) -> 0 | X43: =(ROUND((((S43+ROUND((ROUND(((((EU43*1.2)*0.3))*AV43*I43),2)*BS43),2))*AT43)/100),2)+ROUND(((ROUND((ROUND(((AE43-(((EU43*1.2)*0.3)))*AV43*I43),2)*BS43),2)*AT43)/100),2)) -> 122.49 | Y43: =(ROUND((((S43+ROUND((ROUND(((((EU43*1.2)*0.3))*AV43*I43),2)*BS43),2))*AU43)/100),2)+ROUND(((ROUND((ROUND(((AE43-(((EU43*1.2)*0.3)))*AV43*I43),2)*BS43),2)*AU43)/100),2)) -> 64.4 | AA43: 54971259 | AB43: =ROUND((AC43+AD43+AF43),6) -> 130.626 | AC43: =ROUND((((ES43*1)*0)),6) -> 0 | AD43: =ROUND((((((ET43*1.2)*0.3))-(((EU43*1.2)*0.3)))+AE43),6) -> 34.2936 | AE43: =ROUND((((EU43*1.2)*0.3)),6) -> 4.1796 | AF43: =ROUND((((EV43*1.2)*0.3)),6) -> 96.3324 | AG43: =ROUND((AP43),6) -> 0 | AH43: =(((EW43*1.2)*0.3)) -> 7.416 | AI43: =(((EX43*1.2)*0.3)) -> 0 | AJ43: =(AS43) -> 0 | AK43: 626.66 | AL43: 263.81 | AM43: 95.26 | AN43: 11.61 | AO43: 267.59 | AP43: 0 | AQ43: 20.6 | AR43: 0 | AS43: 0 | AT43: 97 | AU43: 51 | AV43: 1.047 | AW43: 1 | AZ43: 1 | BA43: 1 | BB43: 1 | BC43: 1 | BH43: 0 | BI43: 2 | BJ43: ТСН-2001.4 Доп. 80, Сб. 8, т. 238, поз. 2 | BM43: 67 | BN43: 0 | BO43: 4.8-238-2 | BP43: 1 | BQ43: 40 | BR43: 0 | BS43: 1 | BT43: 1 | BU43: 1 | BV43: 1 | BW43: 1 | BX43: 1 | BZ43: 97 | CA43: 51 | CE43: 1566 | CF43: 0 | CG43: 0 | CM43: 0 | CN43: Поправка: Гл.12.Прил.8.п.8. 3_12.00.01.11.001 Наименование: При наличии напряженных и стесненных условий производства работ (стесненность, сложность складирования и транспортной логистики и т.п.) для объектов, расположенных в пределах круговой магистральной системы улиц "Садовое кольцо" города Москвы Поправка: Гл.4.Прил.2.2.п.2.2.29_04.00.01.35.003 Наименование: При демонтаже оборудования, предназначенного в лом | CO43: 0 | CP43: =(P43+Q43+S43) -> 164.12 | CQ43: =ROUND((ROUND((AC43*AW43*1),2)*BC43),2) -> 0 | CR43: =(ROUND((ROUND(((((ET43*1.2)*0.3))*AV43*1),2)*BB43),2)+ROUND((ROUND(((AE43-(((EU43*1.2)*0.3)))*AV43*1),2)*BS43),2)) -> 35.91 | CS43: =(ROUND((ROUND(((((EU43*1.2)*0.3))*AV43*1),2)*BS43),2)+ROUND((ROUND(((AE43-(((EU43*1.2)*0.3)))*AV43*1),2)*BS43),2)) -> 4.38 | CT43: =ROUND((ROUND((AF43*AV43*1),2)*BA43),2) -> 100.86 | CU43: =AG43 -> 0 | CV43: =(AH43*AV43) -> 7.764552 | CW43: =AI43 -> 0 | CX43: =AJ43 -> 0 | CY43: =(ROUND((((S43+ROUND((ROUND(((((EU43*1.2)*0.3))*AV43*1),2)*BS43),2))*AT43)/100),2)+ROUND(((ROUND((ROUND(((AE43-(((EU43*1.2)*0.3)))*AV43*1),2)*BS43),2)*AT43)/100),2)) -> 121.65 | CZ43: =(ROUND((((S43+ROUND((ROUND(((((EU43*1.2)*0.3))*AV43*1),2)*BS43),2))*AU43)/100),2)+ROUND(((ROUND((ROUND(((AE43-(((EU43*1.2)*0.3)))*AV43*1),2)*BS43),2)*AU43)/100),2)) -> 63.96 | DB43: 17 | DD43: *1)*0 | DE43: *1,2)*0,3 | DF43: *1,2)*0,3 | DG43: *1,2)*0,3 | DI43: *1,2)*0,3 | DJ43: *1,2)*0,3 | DN43: 0 | DO43: 0 | DP43: 1 | DQ43: 1 | DU43: 1013 | DV43: 1 м ширины по фронту | DW43: 1 м ширины по фронту | DX43: 1 | EE43: 57042957 | EF43: 40 | EG43: Монтаж оборудования | EH43: 0 | EJ43: 2 | EK43: 67 | EL43: ТСН-2001.4-8. Электротехнические установки | EM43: ТСН-2001.4-8-1 | EO43: Поправка: Гл.12.Прил.8.п.8. 3_12.00.01.11.001 Поправка: Гл.4.Прил.2.2.п.2.2.29_04.00.01.35.003 | EQ43: 0 | ER43: 626.66 | ES43: 263.81 | ET43: 95.26 | EU43: 11.61 | EV43: 267.59 | EW43: 20.6 | EX43: 0 | EY43: 0 | FQ43: 0 | FR43: 0 | FS43: 0 | FX43: 97 | FY43: 51 | GD43: 1 | GF43: -1738033335 | GG43: 2 | GH43: 1 | GI43: 2 | GJ43: 0 | GK43: 0 | GL43: =ROUND(IF(AND(BH43=3,BI43=3,FS43<>0),P43,0),2) -> 0 | GM43: =ROUND(O43+X43+Y43,2)+GX43 -> 351.01 | GN43: =IF(OR(BI43=0,BI43=1),GM43-GX43,0) -> 0 | GO43: =IF(BI43=2,GM43-GX43,0) -> 351.01 | GP43: =IF(BI43=4,GM43-GX43,0) -> 0 | GR43: 0 | GS43: 3 | GT43: 0 | GV43: =ROUND((GT43),6) -> 0 | GW43: 1 | GX43: =ROUND(HC43*I43,2) -> 0 | HA43: 0 | HB43: 0 | HC43: =GV43*GW43 -> 0 | HS43: 0 | IK43: 0
A44: 17 | B44: 1 | C44: =ROW(SmtRes!A54) -> 54 | D44: =ROW(EtalonRes!A66) -> 66 | E44: 7 | F44: 4.8-238-2 | G44: Монтаж щитов и стеллажей с блоками резисторов (ящиками сопротивлений) высотой свыше 1700 мм, щита, собираемого из отдельных панелей и блоков управления, однорядного или двухрядного, без блоков резисторов глубиной до 800 мм шкафного исполнения / демонтаж вводных панелей ВП1, ВП2 | H44: 1 м ширины по фронту | I44: =ROUND(0.6*2,9) -> 1.2 | J44: 0 | K44: =ROUND(0.6*2,9) -> 1.2 | O44: =ROUND(CP44,2) -> 7523.27 | P44: =ROUND((ROUND((AC44*AW44*I44),2)*BC44),2) -> 0 | Q44: =(ROUND((ROUND(((((ET44*1.2)*0.3))*AV44*I44),2)*BB44),2)+ROUND((ROUND(((AE44-(((EU44*1.2)*0.3)))*AV44*I44),2)*BS44),2)) -> 703.23 | R44: =(ROUND((ROUND(((((EU44*1.2)*0.3))*AV44*I44),2)*BS44),2)+ROUND((ROUND(((AE44-(((EU44*1.2)*0.3)))*AV44*I44),2)*BS44),2)) -> 295.84 | S44: =ROUND((ROUND((AF44*AV44*I44),2)*BA44),2) -> 6820.04 | T44: =ROUND(CU44*I44,2) -> 0 | U44: =CV44*I44 -> 9.3174624 | V44: =CW44*I44 -> 0 | W44: =ROUND(CX44*I44,2) -> 0 | X44: =(ROUND((((S44+ROUND((ROUND(((((EU44*1.2)*0.3))*AV44*I44),2)*BS44),2))*AT44)/100),2)+ROUND(((ROUND((ROUND(((AE44-(((EU44*1.2)*0.3)))*AV44*I44),2)*BS44),2)*AT44)/100),2)) -> 6902.4 | Y44: =(ROUND((((S44+ROUND((ROUND(((((EU44*1.2)*0.3))*AV44*I44),2)*BS44),2))*AU44)/100),2)+ROUND(((ROUND((ROUND(((AE44-(((EU44*1.2)*0.3)))*AV44*I44),2)*BS44),2)*AU44)/100),2)) -> 3629.1 | AA44: 55890823 | AB44: =ROUND((AC44+AD44+AF44),6) -> 130.626 | AC44: =ROUND((((ES44*1)*0)),6) -> 0 | AD44: =ROUND((((((ET44*1.2)*0.3))-(((EU44*1.2)*0.3)))+AE44),6) -> 34.2936 | AE44: =ROUND((((EU44*1.2)*0.3)),6) -> 4.1796 | AF44: =ROUND((((EV44*1.2)*0.3)),6) -> 96.3324 | AG44: =ROUND((AP44),6) -> 0 | AH44: =(((EW44*1.2)*0.3)) -> 7.416 | AI44: =(((EX44*1.2)*0.3)) -> 0 | AJ44: =(AS44) -> 0 | AK44: 626.66 | AL44: 263.81 | AM44: 95.26 | AN44: 11.61 | AO44: 267.59 | AP44: 0 | AQ44: 20.6 | AR44: 0 | AS44: 0 | AT44: 97 | AU44: 51 | AV44: 1.047 | AW44: 1 | AZ44: 1 | BA44: 56.35 | BB44: 16.32 | BC44: 3.8 | BH44: 0 | BI44: 2 | BJ44: ТСН-2001.4 Доп. 80, Сб. 8, т. 238, поз. 2 | BM44: 67 | BN44: 0 | BO44: 4.8-238-2 | BP44: 1 | BQ44: 40 | BR44: 0 | BS44: 56.35 | BT44: 1 | BU44: 1 | BV44: 1 | BW44: 1 | BX44: 1 | BZ44: 97 | CA44: 51 | CE44: 1566 | CF44: 0 | CG44: 0 | CM44: 0 | CN44: Поправка: Гл.12.Прил.8.п.8. 3_12.00.01.11.001 Наименование: При наличии напряженных и стесненных условий производства работ (стесненность, сложность складирования и транспортной логистики и т.п.) для объектов, расположенных в пределах круговой магистральной системы улиц "Садовое кольцо" города Москвы Поправка: Гл.4.Прил.2.2.п.2.2.29_04.00.01.35.003 Наименование: При демонтаже оборудования, предназначенного в лом | CO44: 0 | CP44: =(P44+Q44+S44) -> 7523.27 | CQ44: =ROUND((ROUND((AC44*AW44*1),2)*BC44),2) -> 0 | CR44: =(ROUND((ROUND(((((ET44*1.2)*0.3))*AV44*1),2)*BB44),2)+ROUND((ROUND(((AE44-(((EU44*1.2)*0.3)))*AV44*1),2)*BS44),2)) -> 586.05 | CS44: =(ROUND((ROUND(((((EU44*1.2)*0.3))*AV44*1),2)*BS44),2)+ROUND((ROUND(((AE44-(((EU44*1.2)*0.3)))*AV44*1),2)*BS44),2)) -> 246.81 | CT44: =ROUND((ROUND((AF44*AV44*1),2)*BA44),2) -> 5683.46 | CU44: =AG44 -> 0 | CV44: =(AH44*AV44) -> 7.764552 | CW44: =AI44 -> 0 | CX44: =AJ44 -> 0 | CY44: =(ROUND((((S44+ROUND((ROUND(((((EU44*1.2)*0.3))*AV44*1),2)*BS44),2))*AT44)/100),2)+ROUND(((ROUND((ROUND(((AE44-(((EU44*1.2)*0.3)))*AV44*1),2)*BS44),2)*AT44)/100),2)) -> 6854.84 | CZ44: =(ROUND((((S44+ROUND((ROUND(((((EU44*1.2)*0.3))*AV44*1),2)*BS44),2))*AU44)/100),2)+ROUND(((ROUND((ROUND(((AE44-(((EU44*1.2)*0.3)))*AV44*1),2)*BS44),2)*AU44)/100),2)) -> 3604.09 | DB44: 19 | DD44: *1)*0 | DE44: *1,2)*0,3 | DF44: *1,2)*0,3 | DG44: *1,2)*0,3 | DI44: *1,2)*0,3 | DJ44: *1,2)*0,3 | DN44: 0 | DO44: 0 | DP44: 1 | DQ44: 1 | DU44: 1013 | DV44: 1 м ширины по фронту | DW44: 1 м ширины по фронту | DX44: 1 | EE44: 57042957 | EF44: 40 | EG44: Монтаж оборудования | EH44: 0 | EJ44: 2 | EK44: 67 | EL44: ТСН-2001.4-8. Электротехнические установки | EM44: ТСН-2001.4-8-1 | EO44: Поправка: Гл.12.Прил.8.п.8. 3_12.00.01.11.001 Поправка: Гл.4.Прил.2.2.п.2.2.29_04.00.01.35.003 | EQ44: 0 | ER44: 626.66 | ES44: 263.81 | ET44: 95.26 | EU44: 11.61 | EV44: 267.59 | EW44: 20.6 | EX44: 0 | EY44: 0 | FQ44: 0 | FR44: 0 | FS44: 0 | FX44: 97 | FY44: 51 | GD44: 1 | GF44: -1738033335 | GG44: 2 | GH44: 1 | GI44: 2 | GJ44: 0 | GK44: 0 | GL44: =ROUND(IF(AND(BH44=3,BI44=3,FS44<>0),P44,0),2) -> 0 | GM44: =ROUND(O44+X44+Y44,2)+GX44 -> 18054.77 | GN44: =IF(OR(BI44=0,BI44=1),GM44-GX44,0) -> 0 | GO44: =IF(BI44=2,GM44-GX44,0) -> 18054.77 | GP44: =IF(BI44=4,GM44-GX44,0) -> 0 | GR44: 0 | GS44: 0 | GT44: 0 | GV44: =ROUND((GT44),6) -> 0 | GW44: 1 | GX44: =ROUND(HC44*I44,2) -> 0 | HA44: 0 | HB44: 0 | HC44: =GV44*GW44 -> 0 | HS44: 0 | IK44: 0
A45: 17 | B45: 1 | E45: 8 | F45: 4.8-238-2 | G45: Монтаж щитов и стеллажей с блоками резисторов (ящиками сопротивлений) высотой свыше 1700 мм, щита, собираемого из отдельных панелей и блоков управления, однорядного или двухрядного, без блоков резисторов глубиной до 800 мм шкафного исполнения / демонтаж распределительных панелей РП1, РП2, РП3 | H45: 1 м ширины по фронту | I45: =ROUND(0.6*3,9) -> 1.8 | J45: 0 | K45: =ROUND(0.6*3,9) -> 1.8 | O45: =ROUND(CP45,2) -> 246.18 | P45: =ROUND((ROUND((AC45*AW45*I45),2)*BC45),2) -> 0 | Q45: =(ROUND((ROUND(((((ET45*1.2)*0.3))*AV45*I45),2)*BB45),2)+ROUND((ROUND(((AE45-(((EU45*1.2)*0.3)))*AV45*I45),2)*BS45),2)) -> 64.63 | R45: =(ROUND((ROUND(((((EU45*1.2)*0.3))*AV45*I45),2)*BS45),2)+ROUND((ROUND(((AE45-(((EU45*1.2)*0.3)))*AV45*I45),2)*BS45),2)) -> 7.88 | S45: =ROUND((ROUND((AF45*AV45*I45),2)*BA45),2) -> 181.55 | T45: =ROUND(CU45*I45,2) -> 0 | U45: =CV45*I45 -> 13.976194 | V45: =CW45*I45 -> 0 | W45: =ROUND(CX45*I45,2) -> 0 | X45: =(ROUND((((S45+ROUND((ROUND(((((EU45*1.2)*0.3))*AV45*I45),2)*BS45),2))*AT45)/100),2)+ROUND(((ROUND((ROUND(((AE45-(((EU45*1.2)*0.3)))*AV45*I45),2)*BS45),2)*AT45)/100),2)) -> 183.75 | Y45: =(ROUND((((S45+ROUND((ROUND(((((EU45*1.2)*0.3))*AV45*I45),2)*BS45),2))*AU45)/100),2)+ROUND(((ROUND((ROUND(((AE45-(((EU45*1.2)*0.3)))*AV45*I45),2)*BS45),2)*AU45)/100),2)) -> 96.61 | AA45: 54971259 | AB45: =ROUND((AC45+AD45+AF45),6) -> 130.626 | AC45: =ROUND((((ES45*1)*0)),6) -> 0 | AD45: =ROUND((((((ET45*1.2)*0.3))-(((EU45*1.2)*0.3)))+AE45),6) -> 34.2936 | AE45: =ROUND((((EU45*1.2)*0.3)),6) -> 4.1796 | AF45: =ROUND((((EV45*1.2)*0.3)),6) -> 96.3324 | AG45: =ROUND((AP45),6) -> 0 | AH45: =(((EW45*1.2)*0.3)) -> 7.416 | AI45: =(((EX45*1.2)*0.3)) -> 0 | AJ45: =(AS45) -> 0 | AK45: 626.66 | AL45: 263.81 | AM45: 95.26 | AN45: 11.61 | AO45: 267.59 | AP45: 0 | AQ45: 20.6 | AR45: 0 | AS45: 0 | AT45: 97 | AU45: 51 | AV45: 1.047 | AW45: 1 | AZ45: 1 | BA45: 1 | BB45: 1 | BC45: 1 | BH45: 0 | BI45: 2 | BJ45: ТСН-2001.4 Доп. 80, Сб. 8, т. 238, поз. 2 | BM45: 67 | BN45: 0 | BO45: 4.8-238-2 | BP45: 1 | BQ45: 40 | BR45: 0 | BS45: 1 | BT45: 1 | BU45: 1 | BV45: 1 | BW45: 1 | BX45: 1 | BZ45: 97 | CA45: 51 | CE45: 1566 | CF45: 0 | CG45: 0 | CM45: 0 | CN45: Поправка: Гл.12.Прил.8.п.8. 3_12.00.01.11.001 Наименование: При наличии усложненных условий производства работ (стесненность, сложность складирования и транспортной логистики, наличие в зоне производства работ действующего технологического оборудования или движения технологического транспорта и т.п.) для объектов, расположенных в пределах круговой магистральной системы улиц "Садовое кольцо" города Москвы Поправка: Гл.4.Прил.2.2.п.2.2.29_04.00.01.35.003 Наименование: При демонтаже оборудования, предназначенного в лом | CO45: 0 | CP45: =(P45+Q45+S45) -> 246.18 | CQ45: =ROUND((ROUND((AC45*AW45*1),2)*BC45),2) -> 0 | CR45: =(ROUND((ROUND(((((ET45*1.2)*0.3))*AV45*1),2)*BB45),2)+ROUND((ROUND(((AE45-(((EU45*1.2)*0.3)))*AV45*1),2)*BS45),2)) -> 35.91 | CS45: =(ROUND((ROUND(((((EU45*1.2)*0.3))*AV45*1),2)*BS45),2)+ROUND((ROUND(((AE45-(((EU45*1.2)*0.3)))*AV45*1),2)*BS45),2)) -> 4.38 | CT45: =ROUND((ROUND((AF45*AV45*1),2)*BA45),2) -> 100.86 | CU45: =AG45 -> 0 | CV45: =(AH45*AV45) -> 7.764552 | CW45: =AI45 -> 0 | CX45: =AJ45 -> 0 | CY45: =(ROUND((((S45+ROUND((ROUND(((((EU45*1.2)*0.3))*AV45*1),2)*BS45),2))*AT45)/100),2)+ROUND(((ROUND((ROUND(((AE45-(((EU45*1.2)*0.3)))*AV45*1),2)*BS45),2)*AT45)/100),2)) -> 180.35 | CZ45: =(ROUND((((S45+ROUND((ROUND(((((EU45*1.2)*0.3))*AV45*1),2)*BS45),2))*AU45)/100),2)+ROUND(((ROUND((ROUND(((AE45-(((EU45*1.2)*0.3)))*AV45*1),2)*BS45),2)*AU45)/100),2)) -> 94.82 | DB45: 21 | DD45: *1)*0 | DE45: *1,2)*0,3 | DF45: *1,2)*0,3 | DG45: *1,2)*0,3 | DI45: *1,2)*0,3 | DJ45: *1,2)*0,3 | DN45: 0 | DO45: 0 | DP45: 1 | DQ45: 1 | DU45: 1013 | DV45: 1 м ширины по фронту | DW45: 1 м ширины по фронту | DX45: 1 | EE45: 57042957 | EF45: 40 | EG45: Монтаж оборудования | EH45: 0 | EJ45: 2 | EK45: 67 | EL45: ТСН-2001.4-8. Электротехнические установки | EM45: ТСН-2001.4-8-1 | EO45: Поправка: Гл.12.Прил.8.п.8. 3_12.00.01.11.001 Поправка: Гл.4.Прил.2.2.п.2.2.29_04.00.01.35.003 | EQ45: 0 | ER45: 626.66 | ES45: 263.81 | ET45: 95.26 | EU45: 11.61 | EV45: 267.59 | EW45: 20.6 | EX45: 0 | EY45: 0 | FQ45: 0 | FR45: 0 | FS45: 0 | FX45: 97 | FY45: 51 | GD45: 1 | GF45: -38524377 | GG45: 2 | GH45: 1 | GI45: 2 | GJ45: 0 | GK45: 0 | GL45: =ROUND(IF(AND(BH45=3,BI45=3,FS45<>0),P45,0),2) -> 0 | GM45: =ROUND(O45+X45+Y45,2)+GX45 -> 526.54 | GN45: =IF(OR(BI45=0,BI45=1),GM45-GX45,0) -> 0 | GO45: =IF(BI45=2,GM45-GX45,0) -> 526.54 | GP45: =IF(BI45=4,GM45-GX45,0) -> 0 | GR45: 0 | GS45: 3 | GT45: 0 | GV45: =ROUND((GT45),6) -> 0 | GW45: 1 | GX45: =ROUND(HC45*I45,2) -> 0 | HA45: 0 | HB45: 0 | HC45: =GV45*GW45 -> 0 | HS45: 0 | IK45: 0
A46: 17 | B46: 1 | E46: 8 | F46: 4.8-238-2 | G46: Монтаж щитов и стеллажей с блоками резисторов (ящиками сопротивлений) высотой свыше 1700 мм, щита, собираемого из отдельных панелей и блоков управления, однорядного или двухрядного, без блоков резисторов глубиной до 800 мм шкафного исполнения / демонтаж распределительных панелей РП1, РП2, РП3 | H46: 1 м ширины по фронту | I46: =ROUND(0.6*3,9) -> 1.8 | J46: 0 | K46: =ROUND(0.6*3,9) -> 1.8 | O46: =ROUND(CP46,2) -> 11285.1 | P46: =ROUND((ROUND((AC46*AW46*I46),2)*BC46),2) -> 0 | Q46: =(ROUND((ROUND(((((ET46*1.2)*0.3))*AV46*I46),2)*BB46),2)+ROUND((ROUND(((AE46-(((EU46*1.2)*0.3)))*AV46*I46),2)*BS46),2)) -> 1054.76 | R46: =(ROUND((ROUND(((((EU46*1.2)*0.3))*AV46*I46),2)*BS46),2)+ROUND((ROUND(((AE46-(((EU46*1.2)*0.3)))*AV46*I46),2)*BS46),2)) -> 444.04 | S46: =ROUND((ROUND((AF46*AV46*I46),2)*BA46),2) -> 10230.34 | T46: =ROUND(CU46*I46,2) -> 0 | U46: =CV46*I46 -> 13.976194 | V46: =CW46*I46 -> 0 | W46: =ROUND(CX46*I46,2) -> 0 | X46: =(ROUND((((S46+ROUND((ROUND(((((EU46*1.2)*0.3))*AV46*I46),2)*BS46),2))*AT46)/100),2)+ROUND(((ROUND((ROUND(((AE46-(((EU46*1.2)*0.3)))*AV46*I46),2)*BS46),2)*AT46)/100),2)) -> 10354.15 | Y46: =(ROUND((((S46+ROUND((ROUND(((((EU46*1.2)*0.3))*AV46*I46),2)*BS46),2))*AU46)/100),2)+ROUND(((ROUND((ROUND(((AE46-(((EU46*1.2)*0.3)))*AV46*I46),2)*BS46),2)*AU46)/100),2)) -> 5443.93 | AA46: 55890823 | AB46: =ROUND((AC46+AD46+AF46),6) -> 130.626 | AC46: =ROUND((((ES46*1)*0)),6) -> 0 | AD46: =ROUND((((((ET46*1.2)*0.3))-(((EU46*1.2)*0.3)))+AE46),6) -> 34.2936 | AE46: =ROUND((((EU46*1.2)*0.3)),6) -> 4.1796 | AF46: =ROUND((((EV46*1.2)*0.3)),6) -> 96.3324 | AG46: =ROUND((AP46),6) -> 0 | AH46: =(((EW46*1.2)*0.3)) -> 7.416 | AI46: =(((EX46*1.2)*0.3)) -> 0 | AJ46: =(AS46) -> 0 | AK46: 626.66 | AL46: 263.81 | AM46: 95.26 | AN46: 11.61 | AO46: 267.59 | AP46: 0 | AQ46: 20.6 | AR46: 0 | AS46: 0 | AT46: 97 | AU46: 51 | AV46: 1.047 | AW46: 1 | AZ46: 1 | BA46: 56.35 | BB46: 16.32 | BC46: 3.8 | BH46: 0 | BI46: 2 | BJ46: ТСН-2001.4 Доп. 80, Сб. 8, т. 238, поз. 2 | BM46: 67 | BN46: 0 | BO46: 4.8-238-2 | BP46: 1 | BQ46: 40 | BR46: 0 | BS46: 56.35 | BT46: 1 | BU46: 1 | BV46: 1 | BW46: 1 | BX46: 1 | BZ46: 97 | CA46: 51 | CE46: 1566 | CF46: 0 | CG46: 0 | CM46: 0 | CN46: Поправка: Гл.12.Прил.8.п.8. 3_12.00.01.11.001 Наименование: При наличии усложненных условий производства работ (стесненность, сложность складирования и транспортной логистики, наличие в зоне производства работ действующего технологического оборудования или движения технологического транспорта и т.п.) для объектов, расположенных в пределах круговой магистральной системы улиц "Садовое кольцо" города Москвы Поправка: Гл.4.Прил.2.2.п.2.2.29_04.00.01.35.003 Наименование: При демонтаже оборудования, предназначенного в лом | CO46: 0 | CP46: =(P46+Q46+S46) -> 11285.1 | CQ46: =ROUND((ROUND((AC46*AW46*1),2)*BC46),2) -> 0 | CR46: =(ROUND((ROUND(((((ET46*1.2)*0.3))*AV46*1),2)*BB46),2)+ROUND((ROUND(((AE46-(((EU46*1.2)*0.3)))*AV46*1),2)*BS46),2)) -> 586.05 | CS46: =(ROUND((ROUND(((((EU46*1.2)*0.3))*AV46*1),2)*BS46),2)+ROUND((ROUND(((AE46-(((EU46*1.2)*0.3)))*AV46*1),2)*BS46),2)) -> 246.81 | CT46: =ROUND((ROUND((AF46*AV46*1),2)*BA46),2) -> 5683.46 | CU46: =AG46 -> 0 | CV46: =(AH46*AV46) -> 7.764552 | CW46: =AI46 -> 0 | CX46: =AJ46 -> 0 | CY46: =(ROUND((((S46+ROUND((ROUND(((((EU46*1.2)*0.3))*AV46*1),2)*BS46),2))*AT46)/100),2)+ROUND(((ROUND((ROUND(((AE46-(((EU46*1.2)*0.3)))*AV46*1),2)*BS46),2)*AT46)/100),2)) -> 10162.84 | CZ46: =(ROUND((((S46+ROUND((ROUND(((((EU46*1.2)*0.3))*AV46*1),2)*BS46),2))*AU46)/100),2)+ROUND(((ROUND((ROUND(((AE46-(((EU46*1.2)*0.3)))*AV46*1),2)*BS46),2)*AU46)/100),2)) -> 5343.35 | DB46: 23 | DD46: *1)*0 | DE46: *1,2)*0,3 | DF46: *1,2)*0,3 | DG46: *1,2)*0,3 | DI46: *1,2)*0,3 | DJ46: *1,2)*0,3 | DN46: 0 | DO46: 0 | DP46: 1 | DQ46: 1 | DU46: 1013 | DV46: 1 м ширины по фронту | DW46: 1 м ширины по фронту | DX46: 1 | EE46: 57042957 | EF46: 40 | EG46: Монтаж оборудования | EH46: 0 | EJ46: 2 | EK46: 67 | EL46: ТСН-2001.4-8. Электротехнические установки | EM46: ТСН-2001.4-8-1 | EO46: Поправка: Гл.12.Прил.8.п.8. 3_12.00.01.11.001 Поправка: Гл.4.Прил.2.2.п.2.2.29_04.00.01.35.003 | EQ46: 0 | ER46: 626.66 | ES46: 263.81 | ET46: 95.26 | EU46: 11.61 | EV46: 267.59 | EW46: 20.6 | EX46: 0 | EY46: 0 | FQ46: 0 | FR46: 0 | FS46: 0 | FX46: 97 | FY46: 51 | GD46: 1 | GF46: -38524377 | GG46: 2 | GH46: 1 | GI46: 2 | GJ46: 0 | GK46: 0 | GL46: =ROUND(IF(AND(BH46=3,BI46=3,FS46<>0),P46,0),2) -> 0 | GM46: =ROUND(O46+X46+Y46,2)+GX46 -> 27083.18 | GN46: =IF(OR(BI46=0,BI46=1),GM46-GX46,0) -> 0 | GO46: =IF(BI46=2,GM46-GX46,0) -> 27083.18 | GP46: =IF(BI46=4,GM46-GX46,0) -> 0 | GR46: 0 | GS46: 0 | GT46: 0 | GV46: =ROUND((GT46),6) -> 0 | GW46: 1 | GX46: =ROUND(HC46*I46,2) -> 0 | HA46: 0 | HB46: 0 | HC46: =GV46*GW46 -> 0 | HS46: 0 | IK46: 0
A47: 17 | B47: 1 | E47: 9 | F47: 4.8-238-2 | G47: Монтаж щитов и стеллажей с блоками резисторов (ящиками сопротивлений) высотой свыше 1700 мм, щита, собираемого из отдельных панелей и блоков управления, однорядного или двухрядного, без блоков резисторов глубиной до 800 мм шкафного исполнения / демонтаж ПЭСПЗ | H47: 1 м ширины по фронту | I47: =ROUND(0.6,9) -> 0.6 | J47: 0 | K47: =ROUND(0.6,9) -> 0.6 | O47: =ROUND(CP47,2) -> 82.06 | P47: =ROUND((ROUND((AC47*AW47*I47),2)*BC47),2) -> 0 | Q47: =(ROUND((ROUND(((((ET47*1.2)*0.3))*AV47*I47),2)*BB47),2)+ROUND((ROUND(((AE47-(((EU47*1.2)*0.3)))*AV47*I47),2)*BS47),2)) -> 21.54 | R47: =(ROUND((ROUND(((((EU47*1.2)*0.3))*AV47*I47),2)*BS47),2)+ROUND((ROUND(((AE47-(((EU47*1.2)*0.3)))*AV47*I47),2)*BS47),2)) -> 2.63 | S47: =ROUND((ROUND((AF47*AV47*I47),2)*BA47),2) -> 60.52 | T47: =ROUND(CU47*I47,2) -> 0 | U47: =CV47*I47 -> 4.6587312 | V47: =CW47*I47 -> 0 | W47: =ROUND(CX47*I47,2) -> 0 | X47: =(ROUND((((S47+ROUND((ROUND(((((EU47*1.2)*0.3))*AV47*I47),2)*BS47),2))*AT47)/100),2)+ROUND(((ROUND((ROUND(((AE47-(((EU47*1.2)*0.3)))*AV47*I47),2)*BS47),2)*AT47)/100),2)) -> 61.26 | Y47: =(ROUND((((S47+ROUND((ROUND(((((EU47*1.2)*0.3))*AV47*I47),2)*BS47),2))*AU47)/100),2)+ROUND(((ROUND((ROUND(((AE47-(((EU47*1.2)*0.3)))*AV47*I47),2)*BS47),2)*AU47)/100),2)) -> 32.21 | AA47: 54971259 | AB47: =ROUND((AC47+AD47+AF47),6) -> 130.626 | AC47: =ROUND((((ES47*1)*0)),6) -> 0 | AD47: =ROUND((((((ET47*1.2)*0.3))-(((EU47*1.2)*0.3)))+AE47),6) -> 34.2936 | AE47: =ROUND((((EU47*1.2)*0.3)),6) -> 4.1796 | AF47: =ROUND((((EV47*1.2)*0.3)),6) -> 96.3324 | AG47: =ROUND((AP47),6) -> 0 | AH47: =(((EW47*1.2)*0.3)) -> 7.416 | AI47: =(((EX47*1.2)*0.3)) -> 0 | AJ47: =(AS47) -> 0 | AK47: 626.66 | AL47: 263.81 | AM47: 95.26 | AN47: 11.61 | AO47: 267.59 | AP47: 0 | AQ47: 20.6 | AR47: 0 | AS47: 0 | AT47: 97 | AU47: 51 | AV47: 1.047 | AW47: 1 | AZ47: 1 | BA47: 1 | BB47: 1 | BC47: 1 | BH47: 0 | BI47: 2 | BJ47: ТСН-2001.4 Доп. 80, Сб. 8, т. 238, поз. 2 | BM47: 67 | BN47: 0 | BO47: 4.8-238-2 | BP47: 1 | BQ47: 40 | BR47: 0 | BS47: 1 | BT47: 1 | BU47: 1 | BV47: 1 | BW47: 1 | BX47: 1 | BZ47: 97 | CA47: 51 | CE47: 1566 | CF47: 0 | CG47: 0 | CM47: 0 | CN47: Поправка: Гл.12.Прил.8.п.8. 3_12.00.01.11.001 Наименование: При наличии усложненных условий производства работ (стесненность, сложность складирования и транспортной логистики, наличие в зоне производства работ действующего технологического оборудования или движения технологического транспорта и т.п.) для объектов, расположенных в пределах круговой магистральной системы улиц "Садовое кольцо" города Москвы Поправка: Гл.4.Прил.2.2.п.2.2.29_04.00.01.35.003 Наименование: При демонтаже оборудования, предназначенного в лом | CO47: 0 | CP47: =(P47+Q47+S47) -> 82.06 | CQ47: =ROUND((ROUND((AC47*AW47*1),2)*BC47),2) -> 0 | CR47: =(ROUND((ROUND(((((ET47*1.2)*0.3))*AV47*1),2)*BB47),2)+ROUND((ROUND(((AE47-(((EU47*1.2)*0.3)))*AV47*1),2)*BS47),2)) -> 35.91 | CS47: =(ROUND((ROUND(((((EU47*1.2)*0.3))*AV47*1),2)*BS47),2)+ROUND((ROUND(((AE47-(((EU47*1.2)*0.3)))*AV47*1),2)*BS47),2)) -> 4.38 | CT47: =ROUND((ROUND((AF47*AV47*1),2)*BA47),2) -> 100.86 | CU47: =AG47 -> 0 | CV47: =(AH47*AV47) -> 7.764552 | CW47: =AI47 -> 0 | CX47: =AJ47 -> 0 | CY47: =(ROUND((((S47+ROUND((ROUND(((((EU47*1.2)*0.3))*AV47*1),2)*BS47),2))*AT47)/100),2)+ROUND(((ROUND((ROUND(((AE47-(((EU47*1.2)*0.3)))*AV47*1),2)*BS47),2)*AT47)/100),2)) -> 62.95 | CZ47: =(ROUND((((S47+ROUND((ROUND(((((EU47*1.2)*0.3))*AV47*1),2)*BS47),2))*AU47)/100),2)+ROUND(((ROUND((ROUND(((AE47-(((EU47*1.2)*0.3)))*AV47*1),2)*BS47),2)*AU47)/100),2)) -> 33.1 | DB47: 25 | DD47: *1)*0 | DE47: *1,2)*0,3 | DF47: *1,2)*0,3 | DG47: *1,2)*0,3 | DI47: *1,2)*0,3 | DJ47: *1,2)*0,3 | DN47: 0 | DO47: 0 | DP47: 1 | DQ47: 1 | DU47: 1013 | DV47: 1 м ширины по фронту | DW47: 1 м ширины по фронту | DX47: 1 | EE47: 57042957 | EF47: 40 | EG47: Монтаж оборудования | EH47: 0 | EJ47: 2 | EK47: 67 | EL47: ТСН-2001.4-8. Электротехнические установки | EM47: ТСН-2001.4-8-1 | EO47: Поправка: Гл.12.Прил.8.п.8. 3_12.00.01.11.001 Поправка: Гл.4.Прил.2.2.п.2.2.29_04.00.01.35.003 | EQ47: 0 | ER47: 626.66 | ES47: 263.81 | ET47: 95.26 | EU47: 11.61 | EV47: 267.59 | EW47: 20.6 | EX47: 0 | EY47: 0 | FQ47: 0 | FR47: 0 | FS47: 0 | FX47: 97 | FY47: 51 | GD47: 1 | GF47: -1511028622 | GG47: 2 | GH47: 1 | GI47: 2 | GJ47: 0 | GK47: 0 | GL47: =ROUND(IF(AND(BH47=3,BI47=3,FS47<>0),P47,0),2) -> 0 | GM47: =ROUND(O47+X47+Y47,2)+GX47 -> 175.53 | GN47: =IF(OR(BI47=0,BI47=1),GM47-GX47,0) -> 0 | GO47: =IF(BI47=2,GM47-GX47,0) -> 175.53 | GP47: =IF(BI47=4,GM47-GX47,0) -> 0 | GR47: 0 | GS47: 3 | GT47: 0 | GV47: =ROUND((GT47),6) -> 0 | GW47: 1 | GX47: =ROUND(HC47*I47,2) -> 0 | HA47: 0 | HB47: 0 | HC47: =GV47*GW47 -> 0 | HS47: 0 | IK47: 0
A48: 17 | B48: 1 | E48: 9 | F48: 4.8-238-2 | G48: Монтаж щитов и стеллажей с блоками резисторов (ящиками сопротивлений) высотой свыше 1700 мм, щита, собираемого из отдельных панелей и блоков управления, однорядного или двухрядного, без блоков резисторов глубиной до 800 мм шкафного исполнения / демонтаж ПЭСПЗ | H48: 1 м ширины по фронту | I48: =ROUND(0.6,9) -> 0.6 | J48: 0 | K48: =ROUND(0.6,9) -> 0.6 | O48: =ROUND(CP48,2) -> 3761.83 | P48: =ROUND((ROUND((AC48*AW48*I48),2)*BC48),2) -> 0 | Q48: =(ROUND((ROUND(((((ET48*1.2)*0.3))*AV48*I48),2)*BB48),2)+ROUND((ROUND(((AE48-(((EU48*1.2)*0.3)))*AV48*I48),2)*BS48),2)) -> 351.53 | R48: =(ROUND((ROUND(((((EU48*1.2)*0.3))*AV48*I48),2)*BS48),2)+ROUND((ROUND(((AE48-(((EU48*1.2)*0.3)))*AV48*I48),2)*BS48),2)) -> 148.2 | S48: =ROUND((ROUND((AF48*AV48*I48),2)*BA48),2) -> 3410.3 | T48: =ROUND(CU48*I48,2) -> 0 | U48: =CV48*I48 -> 4.6587312 | V48: =CW48*I48 -> 0 | W48: =ROUND(CX48*I48,2) -> 0 | X48: =(ROUND((((S48+ROUND((ROUND(((((EU48*1.2)*0.3))*AV48*I48),2)*BS48),2))*AT48)/100),2)+ROUND(((ROUND((ROUND(((AE48-(((EU48*1.2)*0.3)))*AV48*I48),2)*BS48),2)*AT48)/100),2)) -> 3451.75 | Y48: =(ROUND((((S48+ROUND((ROUND(((((EU48*1.2)*0.3))*AV48*I48),2)*BS48),2))*AU48)/100),2)+ROUND(((ROUND((ROUND(((AE48-(((EU48*1.2)*0.3)))*AV48*I48),2)*BS48),2)*AU48)/100),2)) -> 1814.84 | AA48: 55890823 | AB48: =ROUND((AC48+AD48+AF48),6) -> 130.626 | AC48: =ROUND((((ES48*1)*0)),6) -> 0 | AD48: =ROUND((((((ET48*1.2)*0.3))-(((EU48*1.2)*0.3)))+AE48),6) -> 34.2936 | AE48: =ROUND((((EU48*1.2)*0.3)),6) -> 4.1796 | AF48: =ROUND((((EV48*1.2)*0.3)),6) -> 96.3324 | AG48: =ROUND((AP48),6) -> 0 | AH48: =(((EW48*1.2)*0.3)) -> 7.416 | AI48: =(((EX48*1.2)*0.3)) -> 0 | AJ48: =(AS48) -> 0 | AK48: 626.66 | AL48: 263.81 | AM48: 95.26 | AN48: 11.61 | AO48: 267.59 | AP48: 0 | AQ48: 20.6 | AR48: 0 | AS48: 0 | AT48: 97 | AU48: 51 | AV48: 1.047 | AW48: 1 | AZ48: 1 | BA48: 56.35 | BB48: 16.32 | BC48: 3.8 | BH48: 0 | BI48: 2 | BJ48: ТСН-2001.4 Доп. 80, Сб. 8, т. 238, поз. 2 | BM48: 67 | BN48: 0 | BO48: 4.8-238-2 | BP48: 1 | BQ48: 40 | BR48: 0 | BS48: 56.35 | BT48: 1 | BU48: 1 | BV48: 1 | BW48: 1 | BX48: 1 | BZ48: 97 | CA48: 51 | CE48: 1566 | CF48: 0 | CG48: 0 | CM48: 0 | CN48: Поправка: Гл.12.Прил.8.п.8. 3_12.00.01.11.001 Наименование: При наличии усложненных условий производства работ (стесненность, сложность складирования и транспортной логистики, наличие в зоне производства работ действующего технологического оборудования или движения технологического транспорта и т.п.) для объектов, расположенных в пределах круговой магистральной системы улиц "Садовое кольцо" города Москвы Поправка: Гл.4.Прил.2.2.п.2.2.29_04.00.01.35.003 Наименование: При демонтаже оборудования, предназначенного в лом | CO48: 0 | CP48: =(P48+Q48+S48) -> 3761.83 | CQ48: =ROUND((ROUND((AC48*AW48*1),2)*BC48),2) -> 0 | CR48: =(ROUND((ROUND(((((ET48*1.2)*0.3))*AV48*1),2)*BB48),2)+ROUND((ROUND(((AE48-(((EU48*1.2)*0.3)))*AV48*1),2)*BS48),2)) -> 586.05 | CS48: =(ROUND((ROUND(((((EU48*1.2)*0.3))*AV48*1),2)*BS48),2)+ROUND((ROUND(((AE48-(((EU48*1.2)*0.3)))*AV48*1),2)*BS48),2)) -> 246.81 | CT48: =ROUND((ROUND((AF48*AV48*1),2)*BA48),2) -> 5683.46 | CU48: =AG48 -> 0 | CV48: =(AH48*AV48) -> 7.764552 | CW48: =AI48 -> 0 | CX48: =AJ48 -> 0 | CY48: =(ROUND((((S48+ROUND((ROUND(((((EU48*1.2)*0.3))*AV48*1),2)*BS48),2))*AT48)/100),2)+ROUND(((ROUND((ROUND(((AE48-(((EU48*1.2)*0.3)))*AV48*1),2)*BS48),2)*AT48)/100),2)) -> 3547.4 | CZ48: =(ROUND((((S48+ROUND((ROUND(((((EU48*1.2)*0.3))*AV48*1),2)*BS48),2))*AU48)/100),2)+ROUND(((ROUND((ROUND(((AE48-(((EU48*1.2)*0.3)))*AV48*1),2)*BS48),2)*AU48)/100),2)) -> 1865.13 | DB48: 27 | DD48: *1)*0 | DE48: *1,2)*0,3 | DF48: *1,2)*0,3 | DG48: *1,2)*0,3 | DI48: *1,2)*0,3 | DJ48: *1,2)*0,3 | DN48: 0 | DO48: 0 | DP48: 1 | DQ48: 1 | DU48: 1013 | DV48: 1 м ширины по фронту | DW48: 1 м ширины по фронту | DX48: 1 | EE48: 57042957 | EF48: 40 | EG48: Монтаж оборудования | EH48: 0 | EJ48: 2 | EK48: 67 | EL48: ТСН-2001.4-8. Электротехнические установки | EM48: ТСН-2001.4-8-1 | EO48: Поправка: Гл.12.Прил.8.п.8. 3_12.00.01.11.001 Поправка: Гл.4.Прил.2.2.п.2.2.29_04.00.01.35.003 | EQ48: 0 | ER48: 626.66 | ES48: 263.81 | ET48: 95.26 | EU48: 11.61 | EV48: 267.59 | EW48: 20.6 | EX48: 0 | EY48: 0 | FQ48: 0 | FR48: 0 | FS48: 0 | FX48: 97 | FY48: 51 | GD48: 1 | GF48: -1511028622 | GG48: 2 | GH48: 1 | GI48: 2 | GJ48: 0 | GK48: 0 | GL48: =ROUND(IF(AND(BH48=3,BI48=3,FS48<>0),P48,0),2) -> 0 | GM48: =ROUND(O48+X48+Y48,2)+GX48 -> 9028.42 | GN48: =IF(OR(BI48=0,BI48=1),GM48-GX48,0) -> 0 | GO48: =IF(BI48=2,GM48-GX48,0) -> 9028.42 | GP48: =IF(BI48=4,GM48-GX48,0) -> 0 | GR48: 0 | GS48: 0 | GT48: 0 | GV48: =ROUND((GT48),6) -> 0 | GW48: 1 | GX48: =ROUND(HC48*I48,2) -> 0 | HA48: 0 | HB48: 0 | HC48: =GV48*GW48 -> 0 | HS48: 0 | IK48: 0
A49: 19 | B49: 1 | G49: Демонтаж световых указателей | AA49: 1 | IK49: 0
A50: 17 | B50: 1 | E50: 10 | F50: 4.8-245-10 | G50: Монтаж светильников с лампами накаливания, светового настенного указателя / демонтаж световых указателей | H50: 100 шт. | I50: =ROUND((7+4+4+32+11+2+8+1)/100,9) -> 0.69 | J50: 0 | K50: =ROUND((7+4+4+32+11+2+8+1)/100,9) -> 0.69 | O50: =ROUND(CP50,2) -> 310.32 | P50: =ROUND((ROUND((AC50*AW50*I50),2)*BC50),2) -> 0 | Q50: =(ROUND((ROUND(((((ET50*1.2)*0.3))*AV50*I50),2)*BB50),2)+ROUND((ROUND(((AE50-(((EU50*1.2)*0.3)))*AV50*I50),2)*BS50),2)) -> 24.27 | R50: =(ROUND((ROUND(((((EU50*1.2)*0.3))*AV50*I50),2)*BS50),2)+ROUND((ROUND(((AE50-(((EU50*1.2)*0.3)))*AV50*I50),2)*BS50),2)) -> 3.38 | S50: =ROUND((ROUND((AF50*AV50*I50),2)*BA50),2) -> 286.05 | T50: =ROUND(CU50*I50,2) -> 0 | U50: =CV50*I50 -> 22.020533 | V50: =CW50*I50 -> 0 | W50: =ROUND(CX50*I50,2) -> 0 | X50: =(ROUND((((S50+ROUND((ROUND(((((EU50*1.2)*0.3))*AV50*I50),2)*BS50),2))*AT50)/100),2)+ROUND(((ROUND((ROUND(((AE50-(((EU50*1.2)*0.3)))*AV50*I50),2)*BS50),2)*AT50)/100),2)) -> 280.75 | Y50: =(ROUND((((S50+ROUND((ROUND(((((EU50*1.2)*0.3))*AV50*I50),2)*BS50),2))*AU50)/100),2)+ROUND(((ROUND((ROUND(((AE50-(((EU50*1.2)*0.3)))*AV50*I50),2)*BS50),2)*AU50)/100),2)) -> 147.61 | AA50: 54971259 | AB50: =ROUND((AC50+AD50+AF50),6) -> 429.5448 | AC50: =ROUND((((ES50*1)*0)),6) -> 0 | AD50: =ROUND((((((ET50*1.2)*0.3))-(((EU50*1.2)*0.3)))+AE50),6) -> 33.5952 | AE50: =ROUND((((EU50*1.2)*0.3)),6) -> 4.68 | AF50: =ROUND((((EV50*1.2)*0.3)),6) -> 395.9496 | AG50: =ROUND((AP50),6) -> 0 | AH50: =(((EW50*1.2)*0.3)) -> 30.4812 | AI50: =(((EX50*1.2)*0.3)) -> 0 | AJ50: =(AS50) -> 0 | AK50: 1274.54 | AL50: 81.36 | AM50: 93.32 | AN50: 13 | AO50: 1099.86 | AP50: 0 | AQ50: 84.67 | AR50: 0 | AS50: 0 | AT50: 97 | AU50: 51 | AV50: 1.047 | AW50: 1 | AZ50: 1 | BA50: 1 | BB50: 1 | BC50: 1 | BH50: 0 | BI50: 2 | BJ50: ТСН-2001.4 Доп. 79, Сб. 8, т. 245, поз. 10 | BM50: 67 | BN50: 0 | BO50: 4.8-245-10 | BP50: 1 | BQ50: 40 | BR50: 0 | BS50: 1 | BT50: 1 | BU50: 1 | BV50: 1 | BW50: 1 | BX50: 1 | BZ50: 97 | CA50: 51 | CE50: 1566 | CF50: 0 | CG50: 0 | CM50: 0 | CN50: Поправка: Гл.12.Прил.8.п.8. 3_12.00.01.11.001 Наименование: При наличии усложненных условий производства работ (стесненность, сложность складирования и транспортной логистики, наличие в зоне производства работ действующего технологического оборудования или движения технологического транспорта и т.п.) для объектов, расположенных в пределах круговой магистральной системы улиц "Садовое кольцо" города Москвы Поправка: Гл.4.Прил.2.2.п.2.2.29_04.00.01.35.003 Наименование: При демонтаже оборудования, предназначенного в лом | CO50: 0 | CP50: =(P50+Q50+S50) -> 310.32 | CQ50: =ROUND((ROUND((AC50*AW50*1),2)*BC50),2) -> 0 | CR50: =(ROUND((ROUND(((((ET50*1.2)*0.3))*AV50*1),2)*BB50),2)+ROUND((ROUND(((AE50-(((EU50*1.2)*0.3)))*AV50*1),2)*BS50),2)) -> 35.17 | CS50: =(ROUND((ROUND(((((EU50*1.2)*0.3))*AV50*1),2)*BS50),2)+ROUND((ROUND(((AE50-(((EU50*1.2)*0.3)))*AV50*1),2)*BS50),2)) -> 4.9 | CT50: =ROUND((ROUND((AF50*AV50*1),2)*BA50),2) -> 414.56 | CU50: =AG50 -> 0 | CV50: =(AH50*AV50) -> 31.913816 | CW50: =AI50 -> 0 | CX50: =AJ50 -> 0 | CY50: =(ROUND((((S50+ROUND((ROUND(((((EU50*1.2)*0.3))*AV50*1),2)*BS50),2))*AT50)/100),2)+ROUND(((ROUND((ROUND(((AE50-(((EU50*1.2)*0.3)))*AV50*1),2)*BS50),2)*AT50)/100),2)) -> 282.22 | CZ50: =(ROUND((((S50+ROUND((ROUND(((((EU50*1.2)*0.3))*AV50*1),2)*BS50),2))*AU50)/100),2)+ROUND(((ROUND((ROUND(((AE50-(((EU50*1.2)*0.3)))*AV50*1),2)*BS50),2)*AU50)/100),2)) -> 148.38 | DB50: 29 | DD50: *1)*0 | DE50: *1,2)*0,3 | DF50: *1,2)*0,3 | DG50: *1,2)*0,3 | DI50: *1,2)*0,3 | DJ50: *1,2)*0,3 | DN50: 0 | DO50: 0 | DP50: 1 | DQ50: 1 | DU50: 1010 | DV50: 100 шт. | DW50: 100 шт. | DX50: 100 | EE50: 57042957 | EF50: 40 | EG50: Монтаж оборудования | EH50: 0 | EJ50: 2 | EK50: 67 | EL50: ТСН-2001.4-8. Электротехнические установки | EM50: ТСН-2001.4-8-1 | EO50: Поправка: Гл.12.Прил.8.п.8. 3_12.00.01.11.001 Поправка: Гл.4.Прил.2.2.п.2.2.29_04.00.01.35.003 | EQ50: 0 | ER50: 1274.54 | ES50: 81.36 | ET50: 93.32 | EU50: 13 | EV50: 1099.86 | EW50: 84.67 | EX50: 0 | EY50: 0 | FQ50: 0 | FR50: 0 | FS50: 0 | FX50: 97 | FY50: 51 | GD50: 1 | GF50: 904025482 | GG50: 2 | GH50: 1 | GI50: 2 | GJ50: 0 | GK50: 0 | GL50: =ROUND(IF(AND(BH50=3,BI50=3,FS50<>0),P50,0),2) -> 0 | GM50: =ROUND(O50+X50+Y50,2)+GX50 -> 738.68 | GN50: =IF(OR(BI50=0,BI50=1),GM50-GX50,0) -> 0 | GO50: =IF(BI50=2,GM50-GX50,0) -> 738.68 | GP50: =IF(BI50=4,GM50-GX50,0) -> 0 | GR50: 0 | GS50: 3 | GT50: 0 | GV50: =ROUND((GT50),6) -> 0 | GW50: 1 | GX50: =ROUND(HC50*I50,2) -> 0 | HA50: 0 | HB50: 0 | HC50: =GV50*GW50 -> 0 | HS50: 0 | IK50: 0
A51: 17 | B51: 1 | E51: 10 | F51: 4.8-245-10 | G51: Монтаж светильников с лампами накаливания, светового настенного указателя / демонтаж световых указателей | H51: 100 шт. | I51: =ROUND((7+4+4+32+11+2+8+1)/100,9) -> 0.69 | J51: 0 | K51: =ROUND((7+4+4+32+11+2+8+1)/100,9) -> 0.69 | O51: =ROUND(CP51,2) -> 16517.43 | P51: =ROUND((ROUND((AC51*AW51*I51),2)*BC51),2) -> 0 | Q51: =(ROUND((ROUND(((((ET51*1.2)*0.3))*AV51*I51),2)*BB51),2)+ROUND((ROUND(((AE51-(((EU51*1.2)*0.3)))*AV51*I51),2)*BS51),2)) -> 398.51 | R51: =(ROUND((ROUND(((((EU51*1.2)*0.3))*AV51*I51),2)*BS51),2)+ROUND((ROUND(((AE51-(((EU51*1.2)*0.3)))*AV51*I51),2)*BS51),2)) -> 190.46 | S51: =ROUND((ROUND((AF51*AV51*I51),2)*BA51),2) -> 16118.92 | T51: =ROUND(CU51*I51,2) -> 0 | U51: =CV51*I51 -> 22.020533 | V51: =CW51*I51 -> 0 | W51: =ROUND(CX51*I51,2) -> 0 | X51: =(ROUND((((S51+ROUND((ROUND(((((EU51*1.2)*0.3))*AV51*I51),2)*BS51),2))*AT51)/100),2)+ROUND(((ROUND((ROUND(((AE51-(((EU51*1.2)*0.3)))*AV51*I51),2)*BS51),2)*AT51)/100),2)) -> 15820.1 | Y51: =(ROUND((((S51+ROUND((ROUND(((((EU51*1.2)*0.3))*AV51*I51),2)*BS51),2))*AU51)/100),2)+ROUND(((ROUND((ROUND(((AE51-(((EU51*1.2)*0.3)))*AV51*I51),2)*BS51),2)*AU51)/100),2)) -> 8317.78 | AA51: 55890823 | AB51: =ROUND((AC51+AD51+AF51),6) -> 429.5448 | AC51: =ROUND((((ES51*1)*0)),6) -> 0 | AD51: =ROUND((((((ET51*1.2)*0.3))-(((EU51*1.2)*0.3)))+AE51),6) -> 33.5952 | AE51: =ROUND((((EU51*1.2)*0.3)),6) -> 4.68 | AF51: =ROUND((((EV51*1.2)*0.3)),6) -> 395.9496 | AG51: =ROUND((AP51),6) -> 0 | AH51: =(((EW51*1.2)*0.3)) -> 30.4812 | AI51: =(((EX51*1.2)*0.3)) -> 0 | AJ51: =(AS51) -> 0 | AK51: 1274.54 | AL51: 81.36 | AM51: 93.32 | AN51: 13 | AO51: 1099.86 | AP51: 0 | AQ51: 84.67 | AR51: 0 | AS51: 0 | AT51: 97 | AU51: 51 | AV51: 1.047 | AW51: 1 | AZ51: 1 | BA51: 56.35 | BB51: 16.42 | BC51: 10.65 | BH51: 0 | BI51: 2 | BJ51: ТСН-2001.4 Доп. 79, Сб. 8, т. 245, поз. 10 | BM51: 67 | BN51: 0 | BO51: 4.8-245-10 | BP51: 1 | BQ51: 40 | BR51: 0 | BS51: 56.35 | BT51: 1 | BU51: 1 | BV51: 1 | BW51: 1 | BX51: 1 | BZ51: 97 | CA51: 51 | CE51: 1566 | CF51: 0 | CG51: 0 | CM51: 0 | CN51: Поправка: Гл.12.Прил.8.п.8. 3_12.00.01.11.001 Наименование: При наличии усложненных условий производства работ (стесненность, сложность складирования и транспортной логистики, наличие в зоне производства работ действующего технологического оборудования или движения технологического транспорта и т.п.) для объектов, расположенных в пределах круговой магистральной системы улиц "Садовое кольцо" города Москвы Поправка: Гл.4.Прил.2.2.п.2.2.29_04.00.01.35.003 Наименование: При демонтаже оборудования, предназначенного в лом | CO51: 0 | CP51: =(P51+Q51+S51) -> 16517.43 | CQ51: =ROUND((ROUND((AC51*AW51*1),2)*BC51),2) -> 0 | CR51: =(ROUND((ROUND(((((ET51*1.2)*0.3))*AV51*1),2)*BB51),2)+ROUND((ROUND(((AE51-(((EU51*1.2)*0.3)))*AV51*1),2)*BS51),2)) -> 577.49 | CS51: =(ROUND((ROUND(((((EU51*1.2)*0.3))*AV51*1),2)*BS51),2)+ROUND((ROUND(((AE51-(((EU51*1.2)*0.3)))*AV51*1),2)*BS51),2)) -> 276.12 | CT51: =ROUND((ROUND((AF51*AV51*1),2)*BA51),2) -> 23360.46 | CU51: =AG51 -> 0 | CV51: =(AH51*AV51) -> 31.913816 | CW51: =AI51 -> 0 | CX51: =AJ51 -> 0 | CY51: =(ROUND((((S51+ROUND((ROUND(((((EU51*1.2)*0.3))*AV51*1),2)*BS51),2))*AT51)/100),2)+ROUND(((ROUND((ROUND(((AE51-(((EU51*1.2)*0.3)))*AV51*1),2)*BS51),2)*AT51)/100),2)) -> 15903.19 | CZ51: =(ROUND((((S51+ROUND((ROUND(((((EU51*1.2)*0.3))*AV51*1),2)*BS51),2))*AU51)/100),2)+ROUND(((ROUND((ROUND(((AE51-(((EU51*1.2)*0.3)))*AV51*1),2)*BS51),2)*AU51)/100),2)) -> 8361.47 | DB51: 31 | DD51: *1)*0 | DE51: *1,2)*0,3 | DF51: *1,2)*0,3 | DG51: *1,2)*0,3 | DI51: *1,2)*0,3 | DJ51: *1,2)*0,3 | DN51: 0 | DO51: 0 | DP51: 1 | DQ51: 1 | DU51: 1010 | DV51: 100 шт. | DW51: 100 шт. | DX51: 100 | EE51: 57042957 | EF51: 40 | EG51: Монтаж оборудования | EH51: 0 | EJ51: 2 | EK51: 67 | EL51: ТСН-2001.4-8. Электротехнические установки | EM51: ТСН-2001.4-8-1 | EO51: Поправка: Гл.12.Прил.8.п.8. 3_12.00.01.11.001 Поправка: Гл.4.Прил.2.2.п.2.2.29_04.00.01.35.003 | EQ51: 0 | ER51: 1274.54 | ES51: 81.36 | ET51: 93.32 | EU51: 13 | EV51: 1099.86 | EW51: 84.67 | EX51: 0 | EY51: 0 | FQ51: 0 | FR51: 0 | FS51: 0 | FX51: 97 | FY51: 51 | GD51: 1 | GF51: 904025482 | GG51: 2 | GH51: 1 | GI51: 2 | GJ51: 0 | GK51: 0 | GL51: =ROUND(IF(AND(BH51=3,BI51=3,FS51<>0),P51,0),2) -> 0 | GM51: =ROUND(O51+X51+Y51,2)+GX51 -> 40655.31 | GN51: =IF(OR(BI51=0,BI51=1),GM51-GX51,0) -> 0 | GO51: =IF(BI51=2,GM51-GX51,0) -> 40655.31 | GP51: =IF(BI51=4,GM51-GX51,0) -> 0 | GR51: 0 | GS51: 0 | GT51: 0 | GV51: =ROUND((GT51),6) -> 0 | GW51: 1 | GX51: =ROUND(HC51*I51,2) -> 0 | HA51: 0 | HB51: 0 | HC51: =GV51*GW51 -> 0 | HS51: 0 | IK51: 0
A52: 19 | B52: 1 | G52: Демонтаж электроустановочного оборудования | AA52: 1 | IK52: 0
A53: 17 | B53: 1 | E53: 11 | F53: 4.8-269-9 | G53: Монтаж лючка коробки сценической переходной и штепсельной типа ЛП-6 / демонтаж лючков | H53: 1 ШТ. | I53: =ROUND(8+77+56,9) -> 141 | J53: 0 | K53: =ROUND(8+77+56,9) -> 141 | O53: =ROUND(CP53,2) -> 723.31 | P53: =ROUND((ROUND((AC53*AW53*I53),2)*BC53),2) -> 0 | Q53: =(ROUND((ROUND(((((ET53*1.2)*0.3))*AV53*I53),2)*BB53),2)+ROUND((ROUND(((AE53-(((EU53*1.2)*0.3)))*AV53*I53),2)*BS53),2)) -> 41.45 | R53: =(ROUND((ROUND(((((EU53*1.2)*0.3))*AV53*I53),2)*BS53),2)+ROUND((ROUND(((AE53-(((EU53*1.2)*0.3)))*AV53*I53),2)*BS53),2)) -> 0 | S53: =ROUND((ROUND((AF53*AV53*I53),2)*BA53),2) -> 681.86 | T53: =ROUND(CU53*I53,2) -> 0 | U53: =CV53*I53 -> 54.740092 | V53: =CW53*I53 -> 0 | W53: =ROUND(CX53*I53,2) -> 0 | X53: =(ROUND((((S53+ROUND((ROUND(((((EU53*1.2)*0.3))*AV53*I53),2)*BS53),2))*AT53)/100),2)+ROUND(((ROUND((ROUND(((AE53-(((EU53*1.2)*0.3)))*AV53*I53),2)*BS53),2)*AT53)/100),2)) -> 661.4 | Y53: =(ROUND((((S53+ROUND((ROUND(((((EU53*1.2)*0.3))*AV53*I53),2)*BS53),2))*AU53)/100),2)+ROUND(((ROUND((ROUND(((AE53-(((EU53*1.2)*0.3)))*AV53*I53),2)*BS53),2)*AU53)/100),2)) -> 347.75 | AA53: 54971259 | AB53: =ROUND((AC53+AD53+AF53),6) -> 4.8996 | AC53: =ROUND((((ES53*1)*0)),6) -> 0 | AD53: =ROUND((((((ET53*1.2)*0.3))-(((EU53*1.2)*0.3)))+AE53),6) -> 0.2808 | AE53: =ROUND((((EU53*1.2)*0.3)),6) -> 0 | AF53: =ROUND((((EV53*1.2)*0.3)),6) -> 4.6188 | AG53: =ROUND((AP53),6) -> 0 | AH53: =(((EW53*1.2)*0.3)) -> 0.3708 | AI53: =(((EX53*1.2)*0.3)) -> 0 | AJ53: =(AS53) -> 0 | AK53: 213.09 | AL53: 199.48 | AM53: 0.78 | AN53: 0 | AO53: 12.83 | AP53: 0 | AQ53: 1.03 | AR53: 0 | AS53: 0 | AT53: 97 | AU53: 51 | AV53: 1.047 | AW53: 1 | AZ53: 1 | BA53: 1 | BB53: 1 | BC53: 1 | BH53: 0 | BI53: 2 | BJ53: ТСН-2001.4 Доп. 79, Сб. 8, т. 269, поз. 9 | BM53: 67 | BN53: 0 | BO53: 4.8-269-9 | BP53: 1 | BQ53: 40 | BR53: 0 | BS53: 1 | BT53: 1 | BU53: 1 | BV53: 1 | BW53: 1 | BX53: 1 | BZ53: 97 | CA53: 51 | CE53: 1566 | CF53: 0 | CG53: 0 | CM53: 0 | CN53: Поправка: Гл.12.Прил.8.п.8. 3_12.00.01.11.001 Наименование: При наличии напряженных и стесненных условий производства работ (стесненность, сложность складирования и транспортной логистики и т.п.) для объектов, расположенных в пределах круговой магистральной системы улиц "Садовое кольцо" города Москвы Поправка: Гл.4.Прил.2.2.п.2.2.29_04.00.01.35.003 Наименование: При демонтаже оборудования, предназначенного в лом | CO53: 0 | CP53: =(P53+Q53+S53) -> 723.31 | CQ53: =ROUND((ROUND((AC53*AW53*1),2)*BC53),2) -> 0 | CR53: =(ROUND((ROUND(((((ET53*1.2)*0.3))*AV53*1),2)*BB53),2)+ROUND((ROUND(((AE53-(((EU53*1.2)*0.3)))*AV53*1),2)*BS53),2)) -> 0.29 | CS53: =(ROUND((ROUND(((((EU53*1.2)*0.3))*AV53*1),2)*BS53),2)+ROUND((ROUND(((AE53-(((EU53*1.2)*0.3)))*AV53*1),2)*BS53),2)) -> 0 | CT53: =ROUND((ROUND((AF53*AV53*1),2)*BA53),2) -> 4.84 | CU53: =AG53 -> 0 | CV53: =(AH53*AV53) -> 0.3882276 | CW53: =AI53 -> 0 | CX53: =AJ53 -> 0 | CY53: =(ROUND((((S53+ROUND((ROUND(((((EU53*1.2)*0.3))*AV53*1),2)*BS53),2))*AT53)/100),2)+ROUND(((ROUND((ROUND(((AE53-(((EU53*1.2)*0.3)))*AV53*1),2)*BS53),2)*AT53)/100),2)) -> 661.4 | CZ53: =(ROUND((((S53+ROUND((ROUND(((((EU53*1.2)*0.3))*AV53*1),2)*BS53),2))*AU53)/100),2)+ROUND(((ROUND((ROUND(((AE53-(((EU53*1.2)*0.3)))*AV53*1),2)*BS53),2)*AU53)/100),2)) -> 347.75 | DB53: 33 | DD53: *1)*0 | DE53: *1,2)*0,3 | DF53: *1,2)*0,3 | DG53: *1,2)*0,3 | DI53: *1,2)*0,3 | DJ53: *1,2)*0,3 | DN53: 0 | DO53: 0 | DP53: 1 | DQ53: 1 | DU53: 1013 | DV53: 1 ШТ. | DW53: 1 ШТ. | DX53: 1 | EE53: 57042957 | EF53: 40 | EG53: Монтаж оборудования | EH53: 0 | EJ53: 2 | EK53: 67 | EL53: ТСН-2001.4-8. Электротехнические установки | EM53: ТСН-2001.4-8-1 | EO53: Поправка: Гл.12.Прил.8.п.8. 3_12.00.01.11.001 Поправка: Гл.4.Прил.2.2.п.2.2.29_04.00.01.35.003 | EQ53: 0 | ER53: 213.09 | ES53: 199.48 | ET53: 0.78 | EU53: 0 | EV53: 12.83 | EW53: 1.03 | EX53: 0 | EY53: 0 | FQ53: 0 | FR53: 0 | FS53: 0 | FX53: 97 | FY53: 51 | GD53: 1 | GF53: -1281564349 | GG53: 2 | GH53: 1 | GI53: 2 | GJ53: 0 | GK53: 0 | GL53: =ROUND(IF(AND(BH53=3,BI53=3,FS53<>0),P53,0),2) -> 0 | GM53: =ROUND(O53+X53+Y53,2)+GX53 -> 1732.46 | GN53: =IF(OR(BI53=0,BI53=1),GM53-GX53,0) -> 0 | GO53: =IF(BI53=2,GM53-GX53,0) -> 1732.46 | GP53: =IF(BI53=4,GM53-GX53,0) -> 0 | GR53: 0 | GS53: 3 | GT53: 0 | GV53: =ROUND((GT53),6) -> 0 | GW53: 1 | GX53: =ROUND(HC53*I53,2) -> 0 | HA53: 0 | HB53: 0 | HC53: =GV53*GW53 -> 0 | HS53: 0 | IK53: 0
A54: 17 | B54: 1 | E54: 11 | F54: 4.8-269-9 | G54: Монтаж лючка коробки сценической переходной и штепсельной типа ЛП-6 / демонтаж лючков | H54: 1 ШТ. | I54: =ROUND(8+77+56,9) -> 141 | J54: 0 | K54: =ROUND(8+77+56,9) -> 141 | O54: =ROUND(CP54,2) -> 38982.39 | P54: =ROUND((ROUND((AC54*AW54*I54),2)*BC54),2) -> 0 | Q54: =(ROUND((ROUND(((((ET54*1.2)*0.3))*AV54*I54),2)*BB54),2)+ROUND((ROUND(((AE54-(((EU54*1.2)*0.3)))*AV54*I54),2)*BS54),2)) -> 559.58 | R54: =(ROUND((ROUND(((((EU54*1.2)*0.3))*AV54*I54),2)*BS54),2)+ROUND((ROUND(((AE54-(((EU54*1.2)*0.3)))*AV54*I54),2)*BS54),2)) -> 0 | S54: =ROUND((ROUND((AF54*AV54*I54),2)*BA54),2) -> 38422.81 | T54: =ROUND(CU54*I54,2) -> 0 | U54: =CV54*I54 -> 54.740092 | V54: =CW54*I54 -> 0 | W54: =ROUND(CX54*I54,2) -> 0 | X54: =(ROUND((((S54+ROUND((ROUND(((((EU54*1.2)*0.3))*AV54*I54),2)*BS54),2))*AT54)/100),2)+ROUND(((ROUND((ROUND(((AE54-(((EU54*1.2)*0.3)))*AV54*I54),2)*BS54),2)*AT54)/100),2)) -> 37270.13 | Y54: =(ROUND((((S54+ROUND((ROUND(((((EU54*1.2)*0.3))*AV54*I54),2)*BS54),2))*AU54)/100),2)+ROUND(((ROUND((ROUND(((AE54-(((EU54*1.2)*0.3)))*AV54*I54),2)*BS54),2)*AU54)/100),2)) -> 19595.63 | AA54: 55890823 | AB54: =ROUND((AC54+AD54+AF54),6) -> 4.8996 | AC54: =ROUND((((ES54*1)*0)),6) -> 0 | AD54: =ROUND((((((ET54*1.2)*0.3))-(((EU54*1.2)*0.3)))+AE54),6) -> 0.2808 | AE54: =ROUND((((EU54*1.2)*0.3)),6) -> 0 | AF54: =ROUND((((EV54*1.2)*0.3)),6) -> 4.6188 | AG54: =ROUND((AP54),6) -> 0 | AH54: =(((EW54*1.2)*0.3)) -> 0.3708 | AI54: =(((EX54*1.2)*0.3)) -> 0 | AJ54: =(AS54) -> 0 | AK54: 213.09 | AL54: 199.48 | AM54: 0.78 | AN54: 0 | AO54: 12.83 | AP54: 0 | AQ54: 1.03 | AR54: 0 | AS54: 0 | AT54: 97 | AU54: 51 | AV54: 1.047 | AW54: 1 | AZ54: 1 | BA54: 56.35 | BB54: 13.5 | BC54: 5.01 | BH54: 0 | BI54: 2 | BJ54: ТСН-2001.4 Доп. 79, Сб. 8, т. 269, поз. 9 | BM54: 67 | BN54: 0 | BO54: 4.8-269-9 | BP54: 1 | BQ54: 40 | BR54: 0 | BS54: 56.35 | BT54: 1 | BU54: 1 | BV54: 1 | BW54: 1 | BX54: 1 | BZ54: 97 | CA54: 51 | CE54: 1566 | CF54: 0 | CG54: 0 | CM54: 0 | CN54: Поправка: Гл.12.Прил.8.п.8. 3_12.00.01.11.001 Наименование: При наличии напряженных и стесненных условий производства работ (стесненность, сложность складирования и транспортной логистики и т.п.) для объектов, расположенных в пределах круговой магистральной системы улиц "Садовое кольцо" города Москвы Поправка: Гл.4.Прил.2.2.п.2.2.29_04.00.01.35.003 Наименование: При демонтаже оборудования, предназначенного в лом | CO54: 0 | CP54: =(P54+Q54+S54) -> 38982.39 | CQ54: =ROUND((ROUND((AC54*AW54*1),2)*BC54),2) -> 0 | CR54: =(ROUND((ROUND(((((ET54*1.2)*0.3))*AV54*1),2)*BB54),2)+ROUND((ROUND(((AE54-(((EU54*1.2)*0.3)))*AV54*1),2)*BS54),2)) -> 3.92 | CS54: =(ROUND((ROUND(((((EU54*1.2)*0.3))*AV54*1),2)*BS54),2)+ROUND((ROUND(((AE54-(((EU54*1.2)*0.3)))*AV54*1),2)*BS54),2)) -> 0 | CT54: =ROUND((ROUND((AF54*AV54*1),2)*BA54),2) -> 272.73 | CU54: =AG54 -> 0 | CV54: =(AH54*AV54) -> 0.3882276 | CW54: =AI54 -> 0 | CX54: =AJ54 -> 0 | CY54: =(ROUND((((S54+ROUND((ROUND(((((EU54*1.2)*0.3))*AV54*1),2)*BS54),2))*AT54)/100),2)+ROUND(((ROUND((ROUND(((AE54-(((EU54*1.2)*0.3)))*AV54*1),2)*BS54),2)*AT54)/100),2)) -> 37270.13 | CZ54: =(ROUND((((S54+ROUND((ROUND(((((EU54*1.2)*0.3))*AV54*1),2)*BS54),2))*AU54)/100),2)+ROUND(((ROUND((ROUND(((AE54-(((EU54*1.2)*0.3)))*AV54*1),2)*BS54),2)*AU54)/100),2)) -> 19595.63 | DB54: 35 | DD54: *1)*0 | DE54: *1,2)*0,3 | DF54: *1,2)*0,3 | DG54: *1,2)*0,3 | DI54: *1,2)*0,3 | DJ54: *1,2)*0,3 | DN54: 0 | DO54: 0 | DP54: 1 | DQ54: 1 | DU54: 1013 | DV54: 1 ШТ. | DW54: 1 ШТ. | DX54: 1 | EE54: 57042957 | EF54: 40 | EG54: Монтаж оборудования | EH54: 0 | EJ54: 2 | EK54: 67 | EL54: ТСН-2001.4-8. Электротехнические установки | EM54: ТСН-2001.4-8-1 | EO54: Поправка: Гл.12.Прил.8.п.8. 3_12.00.01.11.001 Поправка: Гл.4.Прил.2.2.п.2.2.29_04.00.01.35.003 | EQ54: 0 | ER54: 213.09 | ES54: 199.48 | ET54: 0.78 | EU54: 0 | EV54: 12.83 | EW54: 1.03 | EX54: 0 | EY54: 0 | FQ54: 0 | FR54: 0 | FS54: 0 | FX54: 97 | FY54: 51 | GD54: 1 | GF54: -1281564349 | GG54: 2 | GH54: 1 | GI54: 2 | GJ54: 0 | GK54: 0 | GL54: =ROUND(IF(AND(BH54=3,BI54=3,FS54<>0),P54,0),2) -> 0 | GM54: =ROUND(O54+X54+Y54,2)+GX54 -> 95848.15 | GN54: =IF(OR(BI54=0,BI54=1),GM54-GX54,0) -> 0 | GO54: =IF(BI54=2,GM54-GX54,0) -> 95848.15 | GP54: =IF(BI54=4,GM54-GX54,0) -> 0 | GR54: 0 | GS54: 0 | GT54: 0 | GV54: =ROUND((GT54),6) -> 0 | GW54: 1 | GX54: =ROUND(HC54*I54,2) -> 0 | HA54: 0 | HB54: 0 | HC54: =GV54*GW54 -> 0 | HS54: 0 | IK54: 0
A55: 17 | B55: 1 | C55: =ROW(SmtRes!A60) -> 60 | D55: =ROW(EtalonRes!A73) -> 73 | E55: 12 | F55: 4.8-332-1 | G55: Монтаж установочной коробки скрытого типа / демонтаж коробок установочных | H55: 100 шт. | I55: =ROUND(402/100,9) -> 4.02 | J55: 0 | K55: =ROUND(402/100,9) -> 4.02 | O55: =ROUND(CP55,2) -> 543.94 | P55: =ROUND((ROUND((AC55*AW55*I55),2)*BC55),2) -> 0 | Q55: =(ROUND((ROUND(((((ET55*1.2)*0.3))*AV55*I55),2)*BB55),2)+ROUND((ROUND(((AE55-(((EU55*1.2)*0.3)))*AV55*I55),2)*BS55),2)) -> 22.99 | R55: =(ROUND((ROUND(((((EU55*1.2)*0.3))*AV55*I55),2)*BS55),2)+ROUND((ROUND(((AE55-(((EU55*1.2)*0.3)))*AV55*I55),2)*BS55),2)) -> 0.2 | S55: =ROUND((ROUND((AF55*AV55*I55),2)*BA55),2) -> 520.95 | T55: =ROUND(CU55*I55,2) -> 0 | U55: =CV55*I55 -> 46.592966 | V55: =CW55*I55 -> 0 | W55: =ROUND(CX55*I55,2) -> 0 | X55: =(ROUND((((S55+ROUND((ROUND(((((EU55*1.2)*0.3))*AV55*I55),2)*BS55),2))*AT55)/100),2)+ROUND(((ROUND((ROUND(((AE55-(((EU55*1.2)*0.3)))*AV55*I55),2)*BS55),2)*AT55)/100),2)) -> 505.52 | Y55: =(ROUND((((S55+ROUND((ROUND(((((EU55*1.2)*0.3))*AV55*I55),2)*BS55),2))*AU55)/100),2)+ROUND(((ROUND((ROUND(((AE55-(((EU55*1.2)*0.3)))*AV55*I55),2)*BS55),2)*AU55)/100),2)) -> 265.79 | AA55: 54971259 | AB55: =ROUND((AC55+AD55+AF55),6) -> 129.2328 | AC55: =ROUND((((ES55*1)*0)),6) -> 0 | AD55: =ROUND((((((ET55*1.2)*0.3))-(((EU55*1.2)*0.3)))+AE55),6) -> 5.4612 | AE55: =ROUND((((EU55*1.2)*0.3)),6) -> 0.0468 | AF55: =ROUND((((EV55*1.2)*0.3)),6) -> 123.7716 | AG55: =ROUND((AP55),6) -> 0 | AH55: =(((EW55*1.2)*0.3)) -> 11.07 | AI55: =(((EX55*1.2)*0.3)) -> 0 | AJ55: =(AS55) -> 0 | AK55: 1892.95 | AL55: 1533.97 | AM55: 15.17 | AN55: 0.13 | AO55: 343.81 | AP55: 0 | AQ55: 30.75 | AR55: 0 | AS55: 0 | AT55: 97 | AU55: 51 | AV55: 1.047 | AW55: 1 | AZ55: 1 | BA55: 1 | BB55: 1 | BC55: 1 | BH55: 0 | BI55: 2 | BJ55: ТСН-2001.4 Доп. 81, Сб. 8, т. 332, поз. 1 | BM55: 67 | BN55: 0 | BO55: 4.8-332-1 | BP55: 1 | BQ55: 40 | BR55: 0 | BS55: 1 | BT55: 1 | BU55: 1 | BV55: 1 | BW55: 1 | BX55: 1 | BZ55: 97 | CA55: 51 | CE55: 1566 | CF55: 0 | CG55: 0 | CM55: 0 | CN55: Поправка: Гл.12.Прил.8.п.8. 3_12.00.01.11.001 Наименование: При наличии напряженных и стесненных условий производства работ (стесненность, сложность складирования и транспортной логистики и т.п.) для объектов, расположенных в пределах круговой магистральной системы улиц "Садовое кольцо" города Москвы Поправка: Гл.4.Прил.2.2.п.2.2.29_04.00.01.35.003 Наименование: При демонтаже оборудования, предназначенного в лом | CO55: 0 | CP55: =(P55+Q55+S55) -> 543.94 | CQ55: =ROUND((ROUND((AC55*AW55*1),2)*BC55),2) -> 0 | CR55: =(ROUND((ROUND(((((ET55*1.2)*0.3))*AV55*1),2)*BB55),2)+ROUND((ROUND(((AE55-(((EU55*1.2)*0.3)))*AV55*1),2)*BS55),2)) -> 5.72 | CS55: =(ROUND((ROUND(((((EU55*1.2)*0.3))*AV55*1),2)*BS55),2)+ROUND((ROUND(((AE55-(((EU55*1.2)*0.3)))*AV55*1),2)*BS55),2)) -> 0.05 | CT55: =ROUND((ROUND((AF55*AV55*1),2)*BA55),2) -> 129.59 | CU55: =AG55 -> 0 | CV55: =(AH55*AV55) -> 11.59029 | CW55: =AI55 -> 0 | CX55: =AJ55 -> 0 | CY55: =(ROUND((((S55+ROUND((ROUND(((((EU55*1.2)*0.3))*AV55*1),2)*BS55),2))*AT55)/100),2)+ROUND(((ROUND((ROUND(((AE55-(((EU55*1.2)*0.3)))*AV55*1),2)*BS55),2)*AT55)/100),2)) -> 505.37 | CZ55: =(ROUND((((S55+ROUND((ROUND(((((EU55*1.2)*0.3))*AV55*1),2)*BS55),2))*AU55)/100),2)+ROUND(((ROUND((ROUND(((AE55-(((EU55*1.2)*0.3)))*AV55*1),2)*BS55),2)*AU55)/100),2)) -> 265.71 | DB55: 37 | DD55: *1)*0 | DE55: *1,2)*0,3 | DF55: *1,2)*0,3 | DG55: *1,2)*0,3 | DI55: *1,2)*0,3 | DJ55: *1,2)*0,3 | DN55: 0 | DO55: 0 | DP55: 1 | DQ55: 1 | DU55: 1010 | DV55: 100 шт. | DW55: 100 шт. | DX55: 100 | EE55: 57042957 | EF55: 40 | EG55: Монтаж оборудования | EH55: 0 | EJ55: 2 | EK55: 67 | EL55: ТСН-2001.4-8. Электротехнические установки | EM55: ТСН-2001.4-8-1 | EO55: Поправка: Гл.12.Прил.8.п.8. 3_12.00.01.11.001 Поправка: Гл.4.Прил.2.2.п.2.2.29_04.00.01.35.003 | EQ55: 0 | ER55: 1892.95 | ES55: 1533.97 | ET55: 15.17 | EU55: 0.13 | EV55: 343.81 | EW55: 30.75 | EX55: 0 | EY55: 0 | FQ55: 0 | FR55: 0 | FS55: 0 | FX55: 97 | FY55: 51 | GD55: 1 | GF55: -1219601191 | GG55: 2 | GH55: 1 | GI55: 2 | GJ55: 0 | GK55: 0 | GL55: =ROUND(IF(AND(BH55=3,BI55=3,FS55<>0),P55,0),2) -> 0 | GM55: =ROUND(O55+X55+Y55,2)+GX55 -> 1315.25 | GN55: =IF(OR(BI55=0,BI55=1),GM55-GX55,0) -> 0 | GO55: =IF(BI55=2,GM55-GX55,0) -> 1315.25 | GP55: =IF(BI55=4,GM55-GX55,0) -> 0 | GR55: 0 | GS55: 3 | GT55: 0 | GV55: =ROUND((GT55),6) -> 0 | GW55: 1 | GX55: =ROUND(HC55*I55,2) -> 0 | HA55: 0 | HB55: 0 | HC55: =GV55*GW55 -> 0 | HS55: 0 | IK55: 0
A56: 17 | B56: 1 | C56: =ROW(SmtRes!A66) -> 66 | D56: =ROW(EtalonRes!A80) -> 80 | E56: 12 | F56: 4.8-332-1 | G56: Монтаж установочной коробки скрытого типа / демонтаж коробок установочных | H56: 100 шт. | I56: =ROUND(402/100,9) -> 4.02 | J56: 0 | K56: =ROUND(402/100,9) -> 4.02 | O56: =ROUND(CP56,2) -> 29584.74 | P56: =ROUND((ROUND((AC56*AW56*I56),2)*BC56),2) -> 0 | Q56: =(ROUND((ROUND(((((ET56*1.2)*0.3))*AV56*I56),2)*BB56),2)+ROUND((ROUND(((AE56-(((EU56*1.2)*0.3)))*AV56*I56),2)*BS56),2)) -> 229.21 | R56: =(ROUND((ROUND(((((EU56*1.2)*0.3))*AV56*I56),2)*BS56),2)+ROUND((ROUND(((AE56-(((EU56*1.2)*0.3)))*AV56*I56),2)*BS56),2)) -> 11.27 | S56: =ROUND((ROUND((AF56*AV56*I56),2)*BA56),2) -> 29355.53 | T56: =ROUND(CU56*I56,2) -> 0 | U56: =CV56*I56 -> 46.592966 | V56: =CW56*I56 -> 0 | W56: =ROUND(CX56*I56,2) -> 0 | X56: =(ROUND((((S56+ROUND((ROUND(((((EU56*1.2)*0.3))*AV56*I56),2)*BS56),2))*AT56)/100),2)+ROUND(((ROUND((ROUND(((AE56-(((EU56*1.2)*0.3)))*AV56*I56),2)*BS56),2)*AT56)/100),2)) -> 28485.8 | Y56: =(ROUND((((S56+ROUND((ROUND(((((EU56*1.2)*0.3))*AV56*I56),2)*BS56),2))*AU56)/100),2)+ROUND(((ROUND((ROUND(((AE56-(((EU56*1.2)*0.3)))*AV56*I56),2)*BS56),2)*AU56)/100),2)) -> 14977.07 | AA56: 55890823 | AB56: =ROUND((AC56+AD56+AF56),6) -> 129.2328 | AC56: =ROUND((((ES56*1)*0)),6) -> 0 | AD56: =ROUND((((((ET56*1.2)*0.3))-(((EU56*1.2)*0.3)))+AE56),6) -> 5.4612 | AE56: =ROUND((((EU56*1.2)*0.3)),6) -> 0.0468 | AF56: =ROUND((((EV56*1.2)*0.3)),6) -> 123.7716 | AG56: =ROUND((AP56),6) -> 0 | AH56: =(((EW56*1.2)*0.3)) -> 11.07 | AI56: =(((EX56*1.2)*0.3)) -> 0 | AJ56: =(AS56) -> 0 | AK56: 1892.95 | AL56: 1533.97 | AM56: 15.17 | AN56: 0.13 | AO56: 343.81 | AP56: 0 | AQ56: 30.75 | AR56: 0 | AS56: 0 | AT56: 97 | AU56: 51 | AV56: 1.047 | AW56: 1 | AZ56: 1 | BA56: 56.35 | BB56: 9.97 | BC56: 2.84 | BH56: 0 | BI56: 2 | BJ56: ТСН-2001.4 Доп. 81, Сб. 8, т. 332, поз. 1 | BM56: 67 | BN56: 0 | BO56: 4.8-332-1 | BP56: 1 | BQ56: 40 | BR56: 0 | BS56: 56.35 | BT56: 1 | BU56: 1 | BV56: 1 | BW56: 1 | BX56: 1 | BZ56: 97 | CA56: 51 | CE56: 1566 | CF56: 0 | CG56: 0 | CM56: 0 | CN56: Поправка: Гл.12.Прил.8.п.8. 3_12.00.01.11.001 Наименование: При наличии напряженных и стесненных условий производства работ (стесненность, сложность складирования и транспортной логистики и т.п.) для объектов, расположенных в пределах круговой магистральной системы улиц "Садовое кольцо" города Москвы Поправка: Гл.4.Прил.2.2.п.2.2.29_04.00.01.35.003 Наименование: При демонтаже оборудования, предназначенного в лом | CO56: 0 | CP56: =(P56+Q56+S56) -> 29584.74 | CQ56: =ROUND((ROUND((AC56*AW56*1),2)*BC56),2) -> 0 | CR56: =(ROUND((ROUND(((((ET56*1.2)*0.3))*AV56*1),2)*BB56),2)+ROUND((ROUND(((AE56-(((EU56*1.2)*0.3)))*AV56*1),2)*BS56),2)) -> 57.03 | CS56: =(ROUND((ROUND(((((EU56*1.2)*0.3))*AV56*1),2)*BS56),2)+ROUND((ROUND(((AE56-(((EU56*1.2)*0.3)))*AV56*1),2)*BS56),2)) -> 2.82 | CT56: =ROUND((ROUND((AF56*AV56*1),2)*BA56),2) -> 7302.4 | CU56: =AG56 -> 0 | CV56: =(AH56*AV56) -> 11.59029 | CW56: =AI56 -> 0 | CX56: =AJ56 -> 0 | CY56: =(ROUND((((S56+ROUND((ROUND(((((EU56*1.2)*0.3))*AV56*1),2)*BS56),2))*AT56)/100),2)+ROUND(((ROUND((ROUND(((AE56-(((EU56*1.2)*0.3)))*AV56*1),2)*BS56),2)*AT56)/100),2)) -> 28477.6 | CZ56: =(ROUND((((S56+ROUND((ROUND(((((EU56*1.2)*0.3))*AV56*1),2)*BS56),2))*AU56)/100),2)+ROUND(((ROUND((ROUND(((AE56-(((EU56*1.2)*0.3)))*AV56*1),2)*BS56),2)*AU56)/100),2)) -> 14972.76 | DB56: 39 | DD56: *1)*0 | DE56: *1,2)*0,3 | DF56: *1,2)*0,3 | DG56: *1,2)*0,3 | DI56: *1,2)*0,3 | DJ56: *1,2)*0,3 | DN56: 0 | DO56: 0 | DP56: 1 | DQ56: 1 | DU56: 1010 | DV56: 100 шт. | DW56: 100 шт. | DX56: 100 | EE56: 57042957 | EF56: 40 | EG56: Монтаж оборудования | EH56: 0 | EJ56: 2 | EK56: 67 | EL56: ТСН-2001.4-8. Электротехнические установки | EM56: ТСН-2001.4-8-1 | EO56: Поправка: Гл.12.Прил.8.п.8. 3_12.00.01.11.001 Поправка: Гл.4.Прил.2.2.п.2.2.29_04.00.01.35.003 | EQ56: 0 | ER56: 1892.95 | ES56: 1533.97 | ET56: 15.17 | EU56: 0.13 | EV56: 343.81 | EW56: 30.75 | EX56: 0 | EY56: 0 | FQ56: 0 | FR56: 0 | FS56: 0 | FX56: 97 | FY56: 51 | GD56: 1 | GF56: -1219601191 | GG56: 2 | GH56: 1 | GI56: 2 | GJ56: 0 | GK56: 0 | GL56: =ROUND(IF(AND(BH56=3,BI56=3,FS56<>0),P56,0),2) -> 0 | GM56: =ROUND(O56+X56+Y56,2)+GX56 -> 73047.61 | GN56: =IF(OR(BI56=0,BI56=1),GM56-GX56,0) -> 0 | GO56: =IF(BI56=2,GM56-GX56,0) -> 73047.61 | GP56: =IF(BI56=4,GM56-GX56,0) -> 0 | GR56: 0 | GS56: 3 | GT56: 0 | GV56: =ROUND((GT56),6) -> 0 | GW56: 1 | GX56: =ROUND(HC56*I56,2) -> 0 | HA56: 0 | HB56: 0 | HC56: =GV56*GW56 -> 0 | HS56: 0 | IK56: 0
A57: 17 | B57: 1 | E57: 13 | F57: 4.8-328-4 | G57: Монтаж коробки ответвительной для кабельных линий / демонтаж коробок ответвительных | H57: 100 шт. | I57: =ROUND(200/100,9) -> 2 | J57: 0 | K57: =ROUND(200/100,9) -> 2 | O57: =ROUND(CP57,2) -> 1005.33 | P57: =ROUND((ROUND((AC57*AW57*I57),2)*BC57),2) -> 0 | Q57: =(ROUND((ROUND(((((ET57*1.2)*0.3))*AV57*I57),2)*BB57),2)+ROUND((ROUND(((AE57-(((EU57*1.2)*0.3)))*AV57*I57),2)*BS57),2)) -> 2.68 | R57: =(ROUND((ROUND(((((EU57*1.2)*0.3))*AV57*I57),2)*BS57),2)+ROUND((ROUND(((AE57-(((EU57*1.2)*0.3)))*AV57*I57),2)*BS57),2)) -> 0.19 | S57: =ROUND((ROUND((AF57*AV57*I57),2)*BA57),2) -> 1002.65 | T57: =ROUND(CU57*I57,2) -> 0 | U57: =CV57*I57 -> 71.531878 | V57: =CW57*I57 -> 0 | W57: =ROUND(CX57*I57,2) -> 0 | X57: =(ROUND((((S57+ROUND((ROUND(((((EU57*1.2)*0.3))*AV57*I57),2)*BS57),2))*AT57)/100),2)+ROUND(((ROUND((ROUND(((AE57-(((EU57*1.2)*0.3)))*AV57*I57),2)*BS57),2)*AT57)/100),2)) -> 972.75 | Y57: =(ROUND((((S57+ROUND((ROUND(((((EU57*1.2)*0.3))*AV57*I57),2)*BS57),2))*AU57)/100),2)+ROUND(((ROUND((ROUND(((AE57-(((EU57*1.2)*0.3)))*AV57*I57),2)*BS57),2)*AU57)/100),2)) -> 511.45 | AA57: 54971259 | AB57: =ROUND((AC57+AD57+AF57),6) -> 480.1032 | AC57: =ROUND((((ES57*1)*0)),6) -> 0 | AD57: =ROUND((((((ET57*1.2)*0.3))-(((EU57*1.2)*0.3)))+AE57),6) -> 1.2816 | AE57: =ROUND((((EU57*1.2)*0.3)),6) -> 0.09 | AF57: =ROUND((((EV57*1.2)*0.3)),6) -> 478.8216 | AG57: =ROUND((AP57),6) -> 0 | AH57: =(((EW57*1.2)*0.3)) -> 34.1604 | AI57: =(((EX57*1.2)*0.3)) -> 0 | AJ57: =(AS57) -> 0 | AK57: 1334.9 | AL57: 1.28 | AM57: 3.56 | AN57: 0.25 | AO57: 1330.06 | AP57: 0 | AQ57: 94.89 | AR57: 0 | AS57: 0 | AT57: 97 | AU57: 51 | AV57: 1.047 | AW57: 1 | AZ57: 1 | BA57: 1 | BB57: 1 | BC57: 1 | BH57: 0 | BI57: 2 | BJ57: ТСН-2001.4 Доп. 75, Сб. 8, т. 328, поз. 4 | BM57: 67 | BN57: 0 | BO57: 4.8-328-4 | BP57: 1 | BQ57: 40 | BR57: 0 | BS57: 1 | BT57: 1 | BU57: 1 | BV57: 1 | BW57: 1 | BX57: 1 | BZ57: 97 | CA57: 51 | CE57: 1566 | CF57: 0 | CG57: 0 | CM57: 0 | CN57: Поправка: Гл.12.Прил.8.п.8. 3_12.00.01.11.001 Наименование: При наличии напряженных и стесненных условий производства работ (стесненность, сложность складирования и транспортной логистики и т.п.) для объектов, расположенных в пределах круговой магистральной системы улиц "Садовое кольцо" города Москвы Поправка: Гл.4.Прил.2.2.п.2.2.29_04.00.01.35.003 Наименование: При демонтаже оборудования, предназначенного в лом | CO57: 0 | CP57: =(P57+Q57+S57) -> 1005.33 | CQ57: =ROUND((ROUND((AC57*AW57*1),2)*BC57),2) -> 0 | CR57: =(ROUND((ROUND(((((ET57*1.2)*0.3))*AV57*1),2)*BB57),2)+ROUND((ROUND(((AE57-(((EU57*1.2)*0.3)))*AV57*1),2)*BS57),2)) -> 1.34 | CS57: =(ROUND((ROUND(((((EU57*1.2)*0.3))*AV57*1),2)*BS57),2)+ROUND((ROUND(((AE57-(((EU57*1.2)*0.3)))*AV57*1),2)*BS57),2)) -> 0.09 | CT57: =ROUND((ROUND((AF57*AV57*1),2)*BA57),2) -> 501.33 | CU57: =AG57 -> 0 | CV57: =(AH57*AV57) -> 35.765939 | CW57: =AI57 -> 0 | CX57: =AJ57 -> 0 | CY57: =(ROUND((((S57+ROUND((ROUND(((((EU57*1.2)*0.3))*AV57*1),2)*BS57),2))*AT57)/100),2)+ROUND(((ROUND((ROUND(((AE57-(((EU57*1.2)*0.3)))*AV57*1),2)*BS57),2)*AT57)/100),2)) -> 972.66 | CZ57: =(ROUND((((S57+ROUND((ROUND(((((EU57*1.2)*0.3))*AV57*1),2)*BS57),2))*AU57)/100),2)+ROUND(((ROUND((ROUND(((AE57-(((EU57*1.2)*0.3)))*AV57*1),2)*BS57),2)*AU57)/100),2)) -> 511.4 | DB57: 41 | DD57: *1)*0 | DE57: *1,2)*0,3 | DF57: *1,2)*0,3 | DG57: *1,2)*0,3 | DI57: *1,2)*0,3 | DJ57: *1,2)*0,3 | DN57: 0 | DO57: 0 | DP57: 1 | DQ57: 1 | DU57: 1010 | DV57: 100 шт. | DW57: 100 шт. | DX57: 100 | EE57: 57042957 | EF57: 40 | EG57: Монтаж оборудования | EH57: 0 | EJ57: 2 | EK57: 67 | EL57: ТСН-2001.4-8. Электротехнические установки | EM57: ТСН-2001.4-8-1 | EO57: Поправка: Гл.12.Прил.8.п.8. 3_12.00.01.11.001 Поправка: Гл.4.Прил.2.2.п.2.2.29_04.00.01.35.003 | EQ57: 0 | ER57: 1334.9 | ES57: 1.28 | ET57: 3.56 | EU57: 0.25 | EV57: 1330.06 | EW57: 94.89 | EX57: 0 | EY57: 0 | FQ57: 0 | FR57: 0 | FS57: 0 | FX57: 97 | FY57: 51 | GD57: 1 | GF57: -505900781 | GG57: 2 | GH57: 1 | GI57: 2 | GJ57: 0 | GK57: 0 | GL57: =ROUND(IF(AND(BH57=3,BI57=3,FS57<>0),P57,0),2) -> 0 | GM57: =ROUND(O57+X57+Y57,2)+GX57 -> 2489.53 | GN57: =IF(OR(BI57=0,BI57=1),GM57-GX57,0) -> 0 | GO57: =IF(BI57=2,GM57-GX57,0) -> 2489.53 | GP57: =IF(BI57=4,GM57-GX57,0) -> 0 | GR57: 0 | GS57: 3 | GT57: 0 | GV57: =ROUND((GT57),6) -> 0 | GW57: 1 | GX57: =ROUND(HC57*I57,2) -> 0 | HA57: 0 | HB57: 0 | HC57: =GV57*GW57 -> 0 | HS57: 0 | IK57: 0
A58: 17 | B58: 1 | E58: 13 | F58: 4.8-328-4 | G58: Монтаж коробки ответвительной для кабельных линий / демонтаж коробок ответвительных | H58: 100 шт. | I58: =ROUND(200/100,9) -> 2 | J58: 0 | K58: =ROUND(200/100,9) -> 2 | O58: =ROUND(CP58,2) -> 56534.33 | P58: =ROUND((ROUND((AC58*AW58*I58),2)*BC58),2) -> 0 | Q58: =(ROUND((ROUND(((((ET58*1.2)*0.3))*AV58*I58),2)*BB58),2)+ROUND((ROUND(((AE58-(((EU58*1.2)*0.3)))*AV58*I58),2)*BS58),2)) -> 35 | R58: =(ROUND((ROUND(((((EU58*1.2)*0.3))*AV58*I58),2)*BS58),2)+ROUND((ROUND(((AE58-(((EU58*1.2)*0.3)))*AV58*I58),2)*BS58),2)) -> 10.71 | S58: =ROUND((ROUND((AF58*AV58*I58),2)*BA58),2) -> 56499.33 | T58: =ROUND(CU58*I58,2) -> 0 | U58: =CV58*I58 -> 71.531878 | V58: =CW58*I58 -> 0 | W58: =ROUND(CX58*I58,2) -> 0 | X58: =(ROUND((((S58+ROUND((ROUND(((((EU58*1.2)*0.3))*AV58*I58),2)*BS58),2))*AT58)/100),2)+ROUND(((ROUND((ROUND(((AE58-(((EU58*1.2)*0.3)))*AV58*I58),2)*BS58),2)*AT58)/100),2)) -> 54814.74 | Y58: =(ROUND((((S58+ROUND((ROUND(((((EU58*1.2)*0.3))*AV58*I58),2)*BS58),2))*AU58)/100),2)+ROUND(((ROUND((ROUND(((AE58-(((EU58*1.2)*0.3)))*AV58*I58),2)*BS58),2)*AU58)/100),2)) -> 28820.12 | AA58: 55890823 | AB58: =ROUND((AC58+AD58+AF58),6) -> 480.1032 | AC58: =ROUND((((ES58*1)*0)),6) -> 0 | AD58: =ROUND((((((ET58*1.2)*0.3))-(((EU58*1.2)*0.3)))+AE58),6) -> 1.2816 | AE58: =ROUND((((EU58*1.2)*0.3)),6) -> 0.09 | AF58: =ROUND((((EV58*1.2)*0.3)),6) -> 478.8216 | AG58: =ROUND((AP58),6) -> 0 | AH58: =(((EW58*1.2)*0.3)) -> 34.1604 | AI58: =(((EX58*1.2)*0.3)) -> 0 | AJ58: =(AS58) -> 0 | AK58: 1334.9 | AL58: 1.28 | AM58: 3.56 | AN58: 0.25 | AO58: 1330.06 | AP58: 0 | AQ58: 94.89 | AR58: 0 | AS58: 0 | AT58: 97 | AU58: 51 | AV58: 1.047 | AW58: 1 | AZ58: 1 | BA58: 56.35 | BB58: 13.06 | BC58: 4.94 | BH58: 0 | BI58: 2 | BJ58: ТСН-2001.4 Доп. 75, Сб. 8, т. 328, поз. 4 | BM58: 67 | BN58: 0 | BO58: 4.8-328-4 | BP58: 1 | BQ58: 40 | BR58: 0 | BS58: 56.35 | BT58: 1 | BU58: 1 | BV58: 1 | BW58: 1 | BX58: 1 | BZ58: 97 | CA58: 51 | CE58: 1566 | CF58: 0 | CG58: 0 | CM58: 0 | CN58: Поправка: Гл.12.Прил.8.п.8. 3_12.00.01.11.001 Наименование: При наличии напряженных и стесненных условий производства работ (стесненность, сложность складирования и транспортной логистики и т.п.) для объектов, расположенных в пределах круговой магистральной системы улиц "Садовое кольцо" города Москвы Поправка: Гл.4.Прил.2.2.п.2.2.29_04.00.01.35.003 Наименование: При демонтаже оборудования, предназначенного в лом | CO58: 0 | CP58: =(P58+Q58+S58) -> 56534.33 | CQ58: =ROUND((ROUND((AC58*AW58*1),2)*BC58),2) -> 0 | CR58: =(ROUND((ROUND(((((ET58*1.2)*0.3))*AV58*1),2)*BB58),2)+ROUND((ROUND(((AE58-(((EU58*1.2)*0.3)))*AV58*1),2)*BS58),2)) -> 17.5 | CS58: =(ROUND((ROUND(((((EU58*1.2)*0.3))*AV58*1),2)*BS58),2)+ROUND((ROUND(((AE58-(((EU58*1.2)*0.3)))*AV58*1),2)*BS58),2)) -> 5.07 | CT58: =ROUND((ROUND((AF58*AV58*1),2)*BA58),2) -> 28249.95 | CU58: =AG58 -> 0 | CV58: =(AH58*AV58) -> 35.765939 | CW58: =AI58 -> 0 | CX58: =AJ58 -> 0 | CY58: =(ROUND((((S58+ROUND((ROUND(((((EU58*1.2)*0.3))*AV58*1),2)*BS58),2))*AT58)/100),2)+ROUND(((ROUND((ROUND(((AE58-(((EU58*1.2)*0.3)))*AV58*1),2)*BS58),2)*AT58)/100),2)) -> 54809.27 | CZ58: =(ROUND((((S58+ROUND((ROUND(((((EU58*1.2)*0.3))*AV58*1),2)*BS58),2))*AU58)/100),2)+ROUND(((ROUND((ROUND(((AE58-(((EU58*1.2)*0.3)))*AV58*1),2)*BS58),2)*AU58)/100),2)) -> 28817.24 | DB58: 43 | DD58: *1)*0 | DE58: *1,2)*0,3 | DF58: *1,2)*0,3 | DG58: *1,2)*0,3 | DI58: *1,2)*0,3 | DJ58: *1,2)*0,3 | DN58: 0 | DO58: 0 | DP58: 1 | DQ58: 1 | DU58: 1010 | DV58: 100 шт. | DW58: 100 шт. | DX58: 100 | EE58: 57042957 | EF58: 40 | EG58: Монтаж оборудования | EH58: 0 | EJ58: 2 | EK58: 67 | EL58: ТСН-2001.4-8. Электротехнические установки | EM58: ТСН-2001.4-8-1 | EO58: Поправка: Гл.12.Прил.8.п.8. 3_12.00.01.11.001 Поправка: Гл.4.Прил.2.2.п.2.2.29_04.00.01.35.003 | EQ58: 0 | ER58: 1334.9 | ES58: 1.28 | ET58: 3.56 | EU58: 0.25 | EV58: 1330.06 | EW58: 94.89 | EX58: 0 | EY58: 0 | FQ58: 0 | FR58: 0 | FS58: 0 | FX58: 97 | FY58: 51 | GD58: 1 | GF58: -505900781 | GG58: 2 | GH58: 1 | GI58: 2 | GJ58: 0 | GK58: 0 | GL58: =ROUND(IF(AND(BH58=3,BI58=3,FS58<>0),P58,0),2) -> 0 | GM58: =ROUND(O58+X58+Y58,2)+GX58 -> 140169.19 | GN58: =IF(OR(BI58=0,BI58=1),GM58-GX58,0) -> 0 | GO58: =IF(BI58=2,GM58-GX58,0) -> 140169.19 | GP58: =IF(BI58=4,GM58-GX58,0) -> 0 | GR58: 0 | GS58: 0 | GT58: 0 | GV58: =ROUND((GT58),6) -> 0 | GW58: 1 | GX58: =ROUND(HC58*I58,2) -> 0 | HA58: 0 | HB58: 0 | HC58: =GV58*GW58 -> 0 | HS58: 0 | IK58: 0
A59: 17 | B59: 1 | E59: 14 | F59: 4.10-76-10 | G59: Монтаж ключа или кнопки на панели / демонтаж кнопок | H59: 1 ШТ. | I59: 8 | J59: 0 | K59: 8 | O59: =ROUND(CP59,2) -> 35.85 | P59: =ROUND((ROUND((AC59*AW59*I59),2)*BC59),2) -> 0 | Q59: =(ROUND((ROUND(((((ET59*1.2)*0.3))*AV59*I59),2)*BB59),2)+ROUND((ROUND(((AE59-(((EU59*1.2)*0.3)))*AV59*I59),2)*BS59),2)) -> 0 | R59: =(ROUND((ROUND(((((EU59*1.2)*0.3))*AV59*I59),2)*BS59),2)+ROUND((ROUND(((AE59-(((EU59*1.2)*0.3)))*AV59*I59),2)*BS59),2)) -> 0 | S59: =ROUND((ROUND((AF59*AV59*I59),2)*BA59),2) -> 35.85 | T59: =ROUND(CU59*I59,2) -> 0 | U59: =CV59*I59 -> 3.01536 | V59: =CW59*I59 -> 0 | W59: =ROUND(CX59*I59,2) -> 0 | X59: =(ROUND((((S59+ROUND((ROUND(((((EU59*1.2)*0.3))*AV59*I59),2)*BS59),2))*AT59)/100),2)+ROUND(((ROUND((ROUND(((AE59-(((EU59*1.2)*0.3)))*AV59*I59),2)*BS59),2)*AT59)/100),2)) -> 34.06 | Y59: =(ROUND((((S59+ROUND((ROUND(((((EU59*1.2)*0.3))*AV59*I59),2)*BS59),2))*AU59)/100),2)+ROUND(((ROUND((ROUND(((AE59-(((EU59*1.2)*0.3)))*AV59*I59),2)*BS59),2)*AU59)/100),2)) -> 19 | AA59: 54971259 | AB59: =ROUND((AC59+AD59+AF59),6) -> 4.2804 | AC59: =ROUND((((ES59*1)*0)),6) -> 0 | AD59: =ROUND((((((ET59*1.2)*0.3))-(((EU59*1.2)*0.3)))+AE59),6) -> 0 | AE59: =ROUND((((EU59*1.2)*0.3)),6) -> 0 | AF59: =ROUND((((EV59*1.2)*0.3)),6) -> 4.2804 | AG59: =ROUND((AP59),6) -> 0 | AH59: =(((EW59*1.2)*0.3)) -> 0.36 | AI59: =(((EX59*1.2)*0.3)) -> 0 | AJ59: =(AS59) -> 0 | AK59: 13.56 | AL59: 1.67 | AM59: 0 | AN59: 0 | AO59: 11.89 | AP59: 0 | AQ59: 1 | AR59: 0 | AS59: 0 | AT59: 95 | AU59: 53 | AV59: 1.047 | AW59: 1 | AZ59: 1 | BA59: 1 | BB59: 1 | BC59: 1 | BH59: 0 | BI59: 2 | BJ59: ТСН-2001.4 Доп. 79, Сб. 10, т. 76, поз. 10 | BM59: 69 | BN59: 0 | BO59: 4.10-76-10 | BP59: 1 | BQ59: 40 | BR59: 0 | BS59: 1 | BT59: 1 | BU59: 1 | BV59: 1 | BW59: 1 | BX59: 1 | BZ59: 95 | CA59: 53 | CE59: 1566 | CF59: 0 | CG59: 0 | CM59: 0 | CN59: Поправка: Гл.12.Прил.8.п.8. 3_12.00.01.11.001 Наименование: При наличии напряженных и стесненных условий производства работ (стесненность, сложность складирования и транспортной логистики и т.п.) для объектов, расположенных в пределах круговой магистральной системы улиц "Садовое кольцо" города Москвы Поправка: Гл.4.Прил.2.2.п.2.2.29_04.00.01.35.003 Наименование: При демонтаже оборудования, предназначенного в лом | CO59: 0 | CP59: =(P59+Q59+S59) -> 35.85 | CQ59: =ROUND((ROUND((AC59*AW59*1),2)*BC59),2) -> 0 | CR59: =(ROUND((ROUND(((((ET59*1.2)*0.3))*AV59*1),2)*BB59),2)+ROUND((ROUND(((AE59-(((EU59*1.2)*0.3)))*AV59*1),2)*BS59),2)) -> 0 | CS59: =(ROUND((ROUND(((((EU59*1.2)*0.3))*AV59*1),2)*BS59),2)+ROUND((ROUND(((AE59-(((EU59*1.2)*0.3)))*AV59*1),2)*BS59),2)) -> 0 | CT59: =ROUND((ROUND((AF59*AV59*1),2)*BA59),2) -> 4.48 | CU59: =AG59 -> 0 | CV59: =(AH59*AV59) -> 0.37692 | CW59: =AI59 -> 0 | CX59: =AJ59 -> 0 | CY59: =(ROUND((((S59+ROUND((ROUND(((((EU59*1.2)*0.3))*AV59*1),2)*BS59),2))*AT59)/100),2)+ROUND(((ROUND((ROUND(((AE59-(((EU59*1.2)*0.3)))*AV59*1),2)*BS59),2)*AT59)/100),2)) -> 34.06 | CZ59: =(ROUND((((S59+ROUND((ROUND(((((EU59*1.2)*0.3))*AV59*1),2)*BS59),2))*AU59)/100),2)+ROUND(((ROUND((ROUND(((AE59-(((EU59*1.2)*0.3)))*AV59*1),2)*BS59),2)*AU59)/100),2)) -> 19 | DB59: 45 | DD59: *1)*0 | DE59: *1,2)*0,3 | DF59: *1,2)*0,3 | DG59: *1,2)*0,3 | DI59: *1,2)*0,3 | DJ59: *1,2)*0,3 | DN59: 0 | DO59: 0 | DP59: 1 | DQ59: 1 | DU59: 1013 | DV59: 1 ШТ. | DW59: 1 ШТ. | DX59: 1 | EE59: 57042959 | EF59: 40 | EG59: Монтаж оборудования | EH59: 0 | EJ59: 2 | EK59: 69 | EL59: ТСН-2001.4-10. Монтаж радиотелевизионного и электронного оборудования | EM59: ТСН-2001.4-10-2 | EO59: Поправка: Гл.12.Прил.8.п.8. 3_12.00.01.11.001 Поправка: Гл.4.Прил.2.2.п.2.2.29_04.00.01.35.003 | EQ59: 0 | ER59: 13.56 | ES59: 1.67 | ET59: 0 | EU59: 0 | EV59: 11.89 | EW59: 1 | EX59: 0 | EY59: 0 | FQ59: 0 | FR59: 0 | FS59: 0 | FX59: 95 | FY59: 53 | GD59: 1 | GF59: -3566104 | GG59: 2 | GH59: 1 | GI59: 2 | GJ59: 0 | GK59: 0 | GL59: =ROUND(IF(AND(BH59=3,BI59=3,FS59<>0),P59,0),2) -> 0 | GM59: =ROUND(O59+X59+Y59,2)+GX59 -> 88.91 | GN59: =IF(OR(BI59=0,BI59=1),GM59-GX59,0) -> 0 | GO59: =IF(BI59=2,GM59-GX59,0) -> 88.91 | GP59: =IF(BI59=4,GM59-GX59,0) -> 0 | GR59: 0 | GS59: 3 | GT59: 0 | GV59: =ROUND((GT59),6) -> 0 | GW59: 1 | GX59: =ROUND(HC59*I59,2) -> 0 | HA59: 0 | HB59: 0 | HC59: =GV59*GW59 -> 0 | HS59: 0 | IK59: 0
A60: 17 | B60: 1 | E60: 14 | F60: 4.10-76-10 | G60: Монтаж ключа или кнопки на панели / демонтаж кнопок | H60: 1 ШТ. | I60: 8 | J60: 0 | K60: 8 | O60: =ROUND(CP60,2) -> 2020.15 | P60: =ROUND((ROUND((AC60*AW60*I60),2)*BC60),2) -> 0 | Q60: =(ROUND((ROUND(((((ET60*1.2)*0.3))*AV60*I60),2)*BB60),2)+ROUND((ROUND(((AE60-(((EU60*1.2)*0.3)))*AV60*I60),2)*BS60),2)) -> 0 | R60: =(ROUND((ROUND(((((EU60*1.2)*0.3))*AV60*I60),2)*BS60),2)+ROUND((ROUND(((AE60-(((EU60*1.2)*0.3)))*AV60*I60),2)*BS60),2)) -> 0 | S60: =ROUND((ROUND((AF60*AV60*I60),2)*BA60),2) -> 2020.15 | T60: =ROUND(CU60*I60,2) -> 0 | U60: =CV60*I60 -> 3.01536 | V60: =CW60*I60 -> 0 | W60: =ROUND(CX60*I60,2) -> 0 | X60: =(ROUND((((S60+ROUND((ROUND(((((EU60*1.2)*0.3))*AV60*I60),2)*BS60),2))*AT60)/100),2)+ROUND(((ROUND((ROUND(((AE60-(((EU60*1.2)*0.3)))*AV60*I60),2)*BS60),2)*AT60)/100),2)) -> 1919.14 | Y60: =(ROUND((((S60+ROUND((ROUND(((((EU60*1.2)*0.3))*AV60*I60),2)*BS60),2))*AU60)/100),2)+ROUND(((ROUND((ROUND(((AE60-(((EU60*1.2)*0.3)))*AV60*I60),2)*BS60),2)*AU60)/100),2)) -> 1070.68 | AA60: 55890823 | AB60: =ROUND((AC60+AD60+AF60),6) -> 4.2804 | AC60: =ROUND((((ES60*1)*0)),6) -> 0 | AD60: =ROUND((((((ET60*1.2)*0.3))-(((EU60*1.2)*0.3)))+AE60),6) -> 0 | AE60: =ROUND((((EU60*1.2)*0.3)),6) -> 0 | AF60: =ROUND((((EV60*1.2)*0.3)),6) -> 4.2804 | AG60: =ROUND((AP60),6) -> 0 | AH60: =(((EW60*1.2)*0.3)) -> 0.36 | AI60: =(((EX60*1.2)*0.3)) -> 0 | AJ60: =(AS60) -> 0 | AK60: 13.56 | AL60: 1.67 | AM60: 0 | AN60: 0 | AO60: 11.89 | AP60: 0 | AQ60: 1 | AR60: 0 | AS60: 0 | AT60: 95 | AU60: 53 | AV60: 1.047 | AW60: 1 | AZ60: 1 | BA60: 56.35 | BB60: 1 | BC60: 17.87 | BH60: 0 | BI60: 2 | BJ60: ТСН-2001.4 Доп. 79, Сб. 10, т. 76, поз. 10 | BM60: 69 | BN60: 0 | BO60: 4.10-76-10 | BP60: 1 | BQ60: 40 | BR60: 0 | BS60: 56.35 | BT60: 1 | BU60: 1 | BV60: 1 | BW60: 1 | BX60: 1 | BZ60: 95 | CA60: 53 | CE60: 1566 | CF60: 0 | CG60: 0 | CM60: 0 | CN60: Поправка: Гл.12.Прил.8.п.8. 3_12.00.01.11.001 Наименование: При наличии напряженных и стесненных условий производства работ (стесненность, сложность складирования и транспортной логистики и т.п.) для объектов, расположенных в пределах круговой магистральной системы улиц "Садовое кольцо" города Москвы Поправка: Гл.4.Прил.2.2.п.2.2.29_04.00.01.35.003 Наименование: При демонтаже оборудования, предназначенного в лом | CO60: 0 | CP60: =(P60+Q60+S60) -> 2020.15 | CQ60: =ROUND((ROUND((AC60*AW60*1),2)*BC60),2) -> 0 | CR60: =(ROUND((ROUND(((((ET60*1.2)*0.3))*AV60*1),2)*BB60),2)+ROUND((ROUND(((AE60-(((EU60*1.2)*0.3)))*AV60*1),2)*BS60),2)) -> 0 | CS60: =(ROUND((ROUND(((((EU60*1.2)*0.3))*AV60*1),2)*BS60),2)+ROUND((ROUND(((AE60-(((EU60*1.2)*0.3)))*AV60*1),2)*BS60),2)) -> 0 | CT60: =ROUND((ROUND((AF60*AV60*1),2)*BA60),2) -> 252.45 | CU60: =AG60 -> 0 | CV60: =(AH60*AV60) -> 0.37692 | CW60: =AI60 -> 0 | CX60: =AJ60 -> 0 | CY60: =(ROUND((((S60+ROUND((ROUND(((((EU60*1.2)*0.3))*AV60*1),2)*BS60),2))*AT60)/100),2)+ROUND(((ROUND((ROUND(((AE60-(((EU60*1.2)*0.3)))*AV60*1),2)*BS60),2)*AT60)/100),2)) -> 1919.14 | CZ60: =(ROUND((((S60+ROUND((ROUND(((((EU60*1.2)*0.3))*AV60*1),2)*BS60),2))*AU60)/100),2)+ROUND(((ROUND((ROUND(((AE60-(((EU60*1.2)*0.3)))*AV60*1),2)*BS60),2)*AU60)/100),2)) -> 1070.68 | DB60: 47 | DD60: *1)*0 | DE60: *1,2)*0,3 | DF60: *1,2)*0,3 | DG60: *1,2)*0,3 | DI60: *1,2)*0,3 | DJ60: *1,2)*0,3 | DN60: 0 | DO60: 0 | DP60: 1 | DQ60: 1 | DU60: 1013 | DV60: 1 ШТ. | DW60: 1 ШТ. | DX60: 1 | EE60: 57042959 | EF60: 40 | EG60: Монтаж оборудования | EH60: 0 | EJ60: 2 | EK60: 69 | EL60: ТСН-2001.4-10. Монтаж радиотелевизионного и электронного оборудования | EM60: ТСН-2001.4-10-2 | EO60: Поправка: Гл.12.Прил.8.п.8. 3_12.00.01.11.001 Поправка: Гл.4.Прил.2.2.п.2.2.29_04.00.01.35.003 | EQ60: 0 | ER60: 13.56 | ES60: 1.67 | ET60: 0 | EU60: 0 | EV60: 11.89 | EW60: 1 | EX60: 0 | EY60: 0 | FQ60: 0 | FR60: 0 | FS60: 0 | FX60: 95 | FY60: 53 | GD60: 1 | GF60: -3566104 | GG60: 2 | GH60: 1 | GI60: 2 | GJ60: 0 | GK60: 0 | GL60: =ROUND(IF(AND(BH60=3,BI60=3,FS60<>0),P60,0),2) -> 0 | GM60: =ROUND(O60+X60+Y60,2)+GX60 -> 5009.97 | GN60: =IF(OR(BI60=0,BI60=1),GM60-GX60,0) -> 0 | GO60: =IF(BI60=2,GM60-GX60,0) -> 5009.97 | GP60: =IF(BI60=4,GM60-GX60,0) -> 0 | GR60: 0 | GS60: 0 | GT60: 0 | GV60: =ROUND((GT60),6) -> 0 | GW60: 1 | GX60: =ROUND(HC60*I60,2) -> 0 | HA60: 0 | HB60: 0 | HC60: =GV60*GW60 -> 0 | HS60: 0 | IK60: 0
A61: 19 | B61: 1 | G61: Демонтаж кабеленесущих конструкций | AA61: 1 | IK61: 0
A62: 17 | B62: 1 | E62: 15 | F62: 4.8-174-1 | G62: Прокладка металлического рукава, наружный диаметр до 48 мм / демонтаж металлорукавов | H62: 100 м | I62: =ROUND((50+115)/100,9) -> 1.65 | J62: 0 | K62: =ROUND((50+115)/100,9) -> 1.65 | O62: =ROUND(CP62,2) -> 309.36 | P62: =ROUND((ROUND((AC62*AW62*I62),2)*BC62),2) -> 0 | Q62: =(ROUND((ROUND(((((ET62*1.2)*0.3))*AV62*I62),2)*BB62),2)+ROUND((ROUND(((AE62-(((EU62*1.2)*0.3)))*AV62*I62),2)*BS62),2)) -> 80.26 | R62: =(ROUND((ROUND(((((EU62*1.2)*0.3))*AV62*I62),2)*BS62),2)+ROUND((ROUND(((AE62-(((EU62*1.2)*0.3)))*AV62*I62),2)*BS62),2)) -> 1.57 | S62: =ROUND((ROUND((AF62*AV62*I62),2)*BA62),2) -> 229.1 | T62: =ROUND(CU62*I62,2) -> 0 | U62: =CV62*I62 -> 18.595348 | V62: =CW62*I62 -> 0 | W62: =ROUND(CX62*I62,2) -> 0 | X62: =(ROUND((((S62+ROUND((ROUND(((((EU62*1.2)*0.3))*AV62*I62),2)*BS62),2))*AT62)/100),2)+ROUND(((ROUND((ROUND(((AE62-(((EU62*1.2)*0.3)))*AV62*I62),2)*BS62),2)*AT62)/100),2)) -> 223.75 | Y62: =(ROUND((((S62+ROUND((ROUND(((((EU62*1.2)*0.3))*AV62*I62),2)*BS62),2))*AU62)/100),2)+ROUND(((ROUND((ROUND(((AE62-(((EU62*1.2)*0.3)))*AV62*I62),2)*BS62),2)*AU62)/100),2)) -> 117.64 | AA62: 54971259 | AB62: =ROUND((AC62+AD62+AF62),6) -> 179.0748 | AC62: =ROUND((((ES62*1)*0)),6) -> 0 | AD62: =ROUND((((((ET62*1.2)*0.3))-(((EU62*1.2)*0.3)))+AE62),6) -> 46.4616 | AE62: =ROUND((((EU62*1.2)*0.3)),6) -> 0.9072 | AF62: =ROUND((((EV62*1.2)*0.3)),6) -> 132.6132 | AG62: =ROUND((AP62),6) -> 0 | AH62: =(((EW62*1.2)*0.3)) -> 10.764 | AI62: =(((EX62*1.2)*0.3)) -> 0 | AJ62: =(AS62) -> 0 | AK62: 2261.17 | AL62: 1763.74 | AM62: 129.06 | AN62: 2.52 | AO62: 368.37 | AP62: 0 | AQ62: 29.9 | AR62: 0 | AS62: 0 | AT62: 97 | AU62: 51 | AV62: 1.047 | AW62: 1 | AZ62: 1 | BA62: 1 | BB62: 1 | BC62: 1 | BH62: 0 | BI62: 2 | BJ62: ТСН-2001.4 Доп. 80, Сб. 8, т. 174, поз. 1 | BM62: 67 | BN62: 0 | BO62: 4.8-174-1 | BP62: 1 | BQ62: 40 | BR62: 0 | BS62: 1 | BT62: 1 | BU62: 1 | BV62: 1 | BW62: 1 | BX62: 1 | BZ62: 97 | CA62: 51 | CE62: 1566 | CF62: 0 | CG62: 0 | CM62: 0 | CN62: Поправка: Гл.12.Прил.8.п.8. 3_12.00.01.11.001 Наименование: При наличии напряженных и стесненных условий производства работ (стесненность, сложность складирования и транспортной логистики и т.п.) для объектов, расположенных в пределах круговой магистральной системы улиц "Садовое кольцо" города Москвы Поправка: Гл.4.Прил.2.2.п.2.2.29_04.00.01.35.003 Наименование: При демонтаже оборудования, предназначенного в лом | CO62: 0 | CP62: =(P62+Q62+S62) -> 309.36 | CQ62: =ROUND((ROUND((AC62*AW62*1),2)*BC62),2) -> 0 | CR62: =(ROUND((ROUND(((((ET62*1.2)*0.3))*AV62*1),2)*BB62),2)+ROUND((ROUND(((AE62-(((EU62*1.2)*0.3)))*AV62*1),2)*BS62),2)) -> 48.65 | CS62: =(ROUND((ROUND(((((EU62*1.2)*0.3))*AV62*1),2)*BS62),2)+ROUND((ROUND(((AE62-(((EU62*1.2)*0.3)))*AV62*1),2)*BS62),2)) -> 0.95 | CT62: =ROUND((ROUND((AF62*AV62*1),2)*BA62),2) -> 138.85 | CU62: =AG62 -> 0 | CV62: =(AH62*AV62) -> 11.269908 | CW62: =AI62 -> 0 | CX62: =AJ62 -> 0 | CY62: =(ROUND((((S62+ROUND((ROUND(((((EU62*1.2)*0.3))*AV62*1),2)*BS62),2))*AT62)/100),2)+ROUND(((ROUND((ROUND(((AE62-(((EU62*1.2)*0.3)))*AV62*1),2)*BS62),2)*AT62)/100),2)) -> 223.15 | CZ62: =(ROUND((((S62+ROUND((ROUND(((((EU62*1.2)*0.3))*AV62*1),2)*BS62),2))*AU62)/100),2)+ROUND(((ROUND((ROUND(((AE62-(((EU62*1.2)*0.3)))*AV62*1),2)*BS62),2)*AU62)/100),2)) -> 117.33 | DB62: 49 | DD62: *1)*0 | DE62: *1,2)*0,3 | DF62: *1,2)*0,3 | DG62: *1,2)*0,3 | DI62: *1,2)*0,3 | DJ62: *1,2)*0,3 | DN62: 0 | DO62: 0 | DP62: 1 | DQ62: 1 | DU62: 1003 | DV62: 100 м | DW62: 100 м | DX62: 100 | EE62: 57042957 | EF62: 40 | EG62: Монтаж оборудования | EH62: 0 | EJ62: 2 | EK62: 67 | EL62: ТСН-2001.4-8. Электротехнические установки | EM62: ТСН-2001.4-8-1 | EO62: Поправка: Гл.12.Прил.8.п.8. 3_12.00.01.11.001 Поправка: Гл.4.Прил.2.2.п.2.2.29_04.00.01.35.003 | EQ62: 0 | ER62: 2261.17 | ES62: 1763.74 | ET62: 129.06 | EU62: 2.52 | EV62: 368.37 | EW62: 29.9 | EX62: 0 | EY62: 0 | FQ62: 0 | FR62: 0 | FS62: 0 | FX62: 97 | FY62: 51 | GD62: 1 | GF62: -1202354675 | GG62: 2 | GH62: 1 | GI62: 2 | GJ62: 0 | GK62: 0 | GL62: =ROUND(IF(AND(BH62=3,BI62=3,FS62<>0),P62,0),2) -> 0 | GM62: =ROUND(O62+X62+Y62,2)+GX62 -> 650.75 | GN62: =IF(OR(BI62=0,BI62=1),GM62-GX62,0) -> 0 | GO62: =IF(BI62=2,GM62-GX62,0) -> 650.75 | GP62: =IF(BI62=4,GM62-GX62,0) -> 0 | GR62: 0 | GS62: 3 | GT62: 0 | GV62: =ROUND((GT62),6) -> 0 | GW62: 1 | GX62: =ROUND(HC62*I62,2) -> 0 | HA62: 0 | HB62: 0 | HC62: =GV62*GW62 -> 0 | HS62: 0 | IK62: 0
A63: 17 | B63: 1 | E63: 15 | F63: 4.8-174-1 | G63: Прокладка металлического рукава, наружный диаметр до 48 мм / демонтаж металлорукавов | H63: 100 м | I63: =ROUND((50+115)/100,9) -> 1.65 | J63: 0 | K63: =ROUND((50+115)/100,9) -> 1.65 | O63: =ROUND(CP63,2) -> 14020.59 | P63: =ROUND((ROUND((AC63*AW63*I63),2)*BC63),2) -> 0 | Q63: =(ROUND((ROUND(((((ET63*1.2)*0.3))*AV63*I63),2)*BB63),2)+ROUND((ROUND(((AE63-(((EU63*1.2)*0.3)))*AV63*I63),2)*BS63),2)) -> 1110.8 | R63: =(ROUND((ROUND(((((EU63*1.2)*0.3))*AV63*I63),2)*BS63),2)+ROUND((ROUND(((AE63-(((EU63*1.2)*0.3)))*AV63*I63),2)*BS63),2)) -> 88.47 | S63: =ROUND((ROUND((AF63*AV63*I63),2)*BA63),2) -> 12909.79 | T63: =ROUND(CU63*I63,2) -> 0 | U63: =CV63*I63 -> 18.595348 | V63: =CW63*I63 -> 0 | W63: =ROUND(CX63*I63,2) -> 0 | X63: =(ROUND((((S63+ROUND((ROUND(((((EU63*1.2)*0.3))*AV63*I63),2)*BS63),2))*AT63)/100),2)+ROUND(((ROUND((ROUND(((AE63-(((EU63*1.2)*0.3)))*AV63*I63),2)*BS63),2)*AT63)/100),2)) -> 12608.31 | Y63: =(ROUND((((S63+ROUND((ROUND(((((EU63*1.2)*0.3))*AV63*I63),2)*BS63),2))*AU63)/100),2)+ROUND(((ROUND((ROUND(((AE63-(((EU63*1.2)*0.3)))*AV63*I63),2)*BS63),2)*AU63)/100),2)) -> 6629.11 | AA63: 55890823 | AB63: =ROUND((AC63+AD63+AF63),6) -> 179.0748 | AC63: =ROUND((((ES63*1)*0)),6) -> 0 | AD63: =ROUND((((((ET63*1.2)*0.3))-(((EU63*1.2)*0.3)))+AE63),6) -> 46.4616 | AE63: =ROUND((((EU63*1.2)*0.3)),6) -> 0.9072 | AF63: =ROUND((((EV63*1.2)*0.3)),6) -> 132.6132 | AG63: =ROUND((AP63),6) -> 0 | AH63: =(((EW63*1.2)*0.3)) -> 10.764 | AI63: =(((EX63*1.2)*0.3)) -> 0 | AJ63: =(AS63) -> 0 | AK63: 2261.17 | AL63: 1763.74 | AM63: 129.06 | AN63: 2.52 | AO63: 368.37 | AP63: 0 | AQ63: 29.9 | AR63: 0 | AS63: 0 | AT63: 97 | AU63: 51 | AV63: 1.047 | AW63: 1 | AZ63: 1 | BA63: 56.35 | BB63: 13.84 | BC63: 4.04 | BH63: 0 | BI63: 2 | BJ63: ТСН-2001.4 Доп. 80, Сб. 8, т. 174, поз. 1 | BM63: 67 | BN63: 0 | BO63: 4.8-174-1 | BP63: 1 | BQ63: 40 | BR63: 0 | BS63: 56.35 | BT63: 1 | BU63: 1 | BV63: 1 | BW63: 1 | BX63: 1 | BZ63: 97 | CA63: 51 | CE63: 1566 | CF63: 0 | CG63: 0 | CM63: 0 | CN63: Поправка: Гл.12.Прил.8.п.8. 3_12.00.01.11.001 Наименование: При наличии напряженных и стесненных условий производства работ (стесненность, сложность складирования и транспортной логистики и т.п.) для объектов, расположенных в пределах круговой магистральной системы улиц "Садовое кольцо" города Москвы Поправка: Гл.4.Прил.2.2.п.2.2.29_04.00.01.35.003 Наименование: При демонтаже оборудования, предназначенного в лом | CO63: 0 | CP63: =(P63+Q63+S63) -> 14020.59 | CQ63: =ROUND((ROUND((AC63*AW63*1),2)*BC63),2) -> 0 | CR63: =(ROUND((ROUND(((((ET63*1.2)*0.3))*AV63*1),2)*BB63),2)+ROUND((ROUND(((AE63-(((EU63*1.2)*0.3)))*AV63*1),2)*BS63),2)) -> 673.32 | CS63: =(ROUND((ROUND(((((EU63*1.2)*0.3))*AV63*1),2)*BS63),2)+ROUND((ROUND(((AE63-(((EU63*1.2)*0.3)))*AV63*1),2)*BS63),2)) -> 53.53 | CT63: =ROUND((ROUND((AF63*AV63*1),2)*BA63),2) -> 7824.2 | CU63: =AG63 -> 0 | CV63: =(AH63*AV63) -> 11.269908 | CW63: =AI63 -> 0 | CX63: =AJ63 -> 0 | CY63: =(ROUND((((S63+ROUND((ROUND(((((EU63*1.2)*0.3))*AV63*1),2)*BS63),2))*AT63)/100),2)+ROUND(((ROUND((ROUND(((AE63-(((EU63*1.2)*0.3)))*AV63*1),2)*BS63),2)*AT63)/100),2)) -> 12574.42 | CZ63: =(ROUND((((S63+ROUND((ROUND(((((EU63*1.2)*0.3))*AV63*1),2)*BS63),2))*AU63)/100),2)+ROUND(((ROUND((ROUND(((AE63-(((EU63*1.2)*0.3)))*AV63*1),2)*BS63),2)*AU63)/100),2)) -> 6611.29 | DB63: 51 | DD63: *1)*0 | DE63: *1,2)*0,3 | DF63: *1,2)*0,3 | DG63: *1,2)*0,3 | DI63: *1,2)*0,3 | DJ63: *1,2)*0,3 | DN63: 0 | DO63: 0 | DP63: 1 | DQ63: 1 | DU63: 1003 | DV63: 100 м | DW63: 100 м | DX63: 100 | EE63: 57042957 | EF63: 40 | EG63: Монтаж оборудования | EH63: 0 | EJ63: 2 | EK63: 67 | EL63: ТСН-2001.4-8. Электротехнические установки | EM63: ТСН-2001.4-8-1 | EO63: Поправка: Гл.12.Прил.8.п.8. 3_12.00.01.11.001 Поправка: Гл.4.Прил.2.2.п.2.2.29_04.00.01.35.003 | EQ63: 0 | ER63: 2261.17 | ES63: 1763.74 | ET63: 129.06 | EU63: 2.52 | EV63: 368.37 | EW63: 29.9 | EX63: 0 | EY63: 0 | FQ63: 0 | FR63: 0 | FS63: 0 | FX63: 97 | FY63: 51 | GD63: 1 | GF63: -1202354675 | GG63: 2 | GH63: 1 | GI63: 2 | GJ63: 0 | GK63: 0 | GL63: =ROUND(IF(AND(BH63=3,BI63=3,FS63<>0),P63,0),2) -> 0 | GM63: =ROUND(O63+X63+Y63,2)+GX63 -> 33258.01 | GN63: =IF(OR(BI63=0,BI63=1),GM63-GX63,0) -> 0 | GO63: =IF(BI63=2,GM63-GX63,0) -> 33258.01 | GP63: =IF(BI63=4,GM63-GX63,0) -> 0 | GR63: 0 | GS63: 0 | GT63: 0 | GV63: =ROUND((GT63),6) -> 0 | GW63: 1 | GX63: =ROUND(HC63*I63,2) -> 0 | HA63: 0 | HB63: 0 | HC63: =GV63*GW63 -> 0 | HS63: 0 | IK63: 0
A64: 17 | B64: 1 | E64: 16 | F64: 3.9-35-1 | G64: Монтаж мелких конструкций из стали различного профиля массой до 20 кг (проходка на кровлю Гусак) / демонтаж | H64: 1 Т | I64: =ROUND((6*18.6+4.1+3.3*2)/1000,9) -> 0.1223 | J64: 0 | K64: =ROUND((6*18.6+4.1+3.3*2)/1000,9) -> 0.1223 | O64: =ROUND(CP64,2) -> 155.89 | P64: =ROUND((ROUND((AC64*AW64*I64),2)*BC64),2) -> 4.29 | Q64: =(ROUND((ROUND(((((ET64*1.2)*0.6))*AV64*I64),2)*BB64),2)+ROUND((ROUND(((AE64-(((EU64*1.2)*0.6)))*AV64*I64),2)*BS64),2)) -> 5.04 | R64: =(ROUND((ROUND(((((EU64*1.2)*0.6))*AV64*I64),2)*BS64),2)+ROUND((ROUND(((AE64-(((EU64*1.2)*0.6)))*AV64*I64),2)*BS64),2)) -> 0 | S64: =ROUND((ROUND((AF64*AV64*I64),2)*BA64),2) -> 146.56 | T64: =ROUND(CU64*I64,2) -> 0 | U64: =CV64*I64 -> 11.103157 | V64: =CW64*I64 -> 0 | W64: =ROUND(CX64*I64,2) -> 0 | X64: =(ROUND((((S64+ROUND((ROUND(((((EU64*1.2)*0.6))*AV64*I64),2)*BS64),2))*AT64)/100),2)+ROUND(((ROUND((ROUND(((AE64-(((EU64*1.2)*0.6)))*AV64*I64),2)*BS64),2)*AT64)/100),2)) -> 136.3 | Y64: =(ROUND((((S64+ROUND((ROUND(((((EU64*1.2)*0.6))*AV64*I64),2)*BS64),2))*AU64)/100),2)+ROUND(((ROUND((ROUND(((AE64-(((EU64*1.2)*0.6)))*AV64*I64),2)*BS64),2)*AU64)/100),2)) -> 90.87 | AA64: 54971259 | AB64: =ROUND((AC64+AD64+AF64),6) -> 1175.4192 | AC64: =ROUND((((ES64*1)*0.6)),6) -> 35.04 | AD64: =ROUND((((((ET64*1.2)*0.6))-(((EU64*1.2)*0.6)))+AE64),6) -> 37.9152 | AE64: =ROUND((((EU64*1.2)*0.6)),6) -> 0 | AF64: =ROUND((((EV64*1.2)*0.6)),6) -> 1102.464 | AG64: =ROUND((AP64),6) -> 0 | AH64: =(((EW64*1.2)*0.6)) -> 83.52 | AI64: =(((EX64*1.2)*0.6)) -> 0 | AJ64: =(AS64) -> 0 | AK64: 1642.26 | AL64: 58.4 | AM64: 52.66 | AN64: 0 | AO64: 1531.2 | AP64: 0 | AQ64: 116 | AR64: 0 | AS64: 0 | AT64: 93 | AU64: 62 | AV64: 1.087 | AW64: 1 | AZ64: 1 | BA64: 1 | BB64: 1 | BC64: 1 | BH64: 0 | BI64: 1 | BJ64: ТСН-2001.3 Доп. 79, Сб. 9, т. 35, поз. 1 | BM64: 13 | BN64: 0 | BO64: 3.9-35-1 | BP64: 1 | BQ64: 30 | BR64: 0 | BS64: 1 | BT64: 1 | BU64: 1 | BV64: 1 | BW64: 1 | BX64: 1 | BZ64: 93 | CA64: 62 | CE64: 1566 | CF64: 0 | CG64: 0 | CM64: 0 | CN64: Поправка: Гл.12.Прил.8.п.8. 3_12.00.01.11.001 Наименование: При наличии напряженных и стесненных условий производства работ (стесненность, сложность складирования и транспортной логистики и т.п.) для объектов, расположенных в пределах круговой магистральной системы улиц "Садовое кольцо" города Москвы Поправка: Гл.6.Прил.2.2.п.2.2.16_06.00.01.35.006 Наименование: При демонтаже металлических конструкций (в т.ч. к стоимости вспомогательных материалов) | CO64: 0 | CP64: =(P64+Q64+S64) -> 155.89 | CQ64: =ROUND((ROUND((AC64*AW64*1),2)*BC64),2) -> 35.04 | CR64: =(ROUND((ROUND(((((ET64*1.2)*0.6))*AV64*1),2)*BB64),2)+ROUND((ROUND(((AE64-(((EU64*1.2)*0.6)))*AV64*1),2)*BS64),2)) -> 41.21 | CS64: =(ROUND((ROUND(((((EU64*1.2)*0.6))*AV64*1),2)*BS64),2)+ROUND((ROUND(((AE64-(((EU64*1.2)*0.6)))*AV64*1),2)*BS64),2)) -> 0 | CT64: =ROUND((ROUND((AF64*AV64*1),2)*BA64),2) -> 1198.38 | CU64: =AG64 -> 0 | CV64: =(AH64*AV64) -> 90.78624 | CW64: =AI64 -> 0 | CX64: =AJ64 -> 0 | CY64: =(ROUND((((S64+ROUND((ROUND(((((EU64*1.2)*0.6))*AV64*1),2)*BS64),2))*AT64)/100),2)+ROUND(((ROUND((ROUND(((AE64-(((EU64*1.2)*0.6)))*AV64*1),2)*BS64),2)*AT64)/100),2)) -> 136.3 | CZ64: =(ROUND((((S64+ROUND((ROUND(((((EU64*1.2)*0.6))*AV64*1),2)*BS64),2))*AU64)/100),2)+ROUND(((ROUND((ROUND(((AE64-(((EU64*1.2)*0.6)))*AV64*1),2)*BS64),2)*AU64)/100),2)) -> 90.87 | DB64: 53 | DD64: *1)*0,6 | DE64: *1,2)*0,6 | DF64: *1,2)*0,6 | DG64: *1,2)*0,6 | DI64: *1,2)*0,6 | DJ64: *1,2)*0,6 | DN64: 0 | DO64: 0 | DP64: 1 | DQ64: 1 | DU64: 1013 | DV64: 1 Т | DW64: 1 Т | DX64: 1 | EE64: 57042902 | EF64: 30 | EG64: Строительные работы | EH64: 0 | EJ64: 1 | EK64: 13 | EL64: ТСН-2001.3-9. Металлические конструкции | EM64: ТСН-2001.3-9-1 | EO64: Поправка: Гл.12.Прил.8.п.8. 3_12.00.01.11.001 Поправка: Гл.6.Прил.2.2.п.2.2.16_06.00.01.35.006 | EQ64: 0 | ER64: 1642.26 | ES64: 58.4 | ET64: 52.66 | EU64: 0 | EV64: 1531.2 | EW64: 116 | EX64: 0 | EY64: 0 | FQ64: 0 | FR64: 0 | FS64: 0 | FX64: 93 | FY64: 62 | GD64: 1 | GF64: -2000456464 | GG64: 2 | GH64: 1 | GI64: 2 | GJ64: 0 | GK64: 0 | GL64: =ROUND(IF(AND(BH64=3,BI64=3,FS64<>0),P64,0),2) -> 0 | GM64: =ROUND(O64+X64+Y64,2)+GX64 -> 383.06 | GN64: =IF(OR(BI64=0,BI64=1),GM64-GX64,0) -> 383.06 | GO64: =IF(BI64=2,GM64-GX64,0) -> 0 | GP64: =IF(BI64=4,GM64-GX64,0) -> 0 | GR64: 0 | GS64: 3 | GT64: 0 | GV64: =ROUND((GT64),6) -> 0 | GW64: 1 | GX64: =ROUND(HC64*I64,2) -> 0 | HA64: 0 | HB64: 0 | HC64: =GV64*GW64 -> 0 | HS64: 0 | IK64: 0
A65: 17 | B65: 1 | E65: 16 | F65: 3.9-35-1 | G65: Монтаж мелких конструкций из стали различного профиля массой до 20 кг (проходка на кровлю Гусак) / демонтаж | H65: 1 Т | I65: =ROUND((6*18.6+4.1+3.3*2)/1000,9) -> 0.1223 | J65: 0 | K65: =ROUND((6*18.6+4.1+3.3*2)/1000,9) -> 0.1223 | O65: =ROUND(CP65,2) -> 8356.8 | P65: =ROUND((ROUND((AC65*AW65*I65),2)*BC65),2) -> 46.98 | Q65: =(ROUND((ROUND(((((ET65*1.2)*0.6))*AV65*I65),2)*BB65),2)+ROUND((ROUND(((AE65-(((EU65*1.2)*0.6)))*AV65*I65),2)*BS65),2)) -> 51.16 | R65: =(ROUND((ROUND(((((EU65*1.2)*0.6))*AV65*I65),2)*BS65),2)+ROUND((ROUND(((AE65-(((EU65*1.2)*0.6)))*AV65*I65),2)*BS65),2)) -> 0 | S65: =ROUND((ROUND((AF65*AV65*I65),2)*BA65),2) -> 8258.66 | T65: =ROUND(CU65*I65,2) -> 0 | U65: =CV65*I65 -> 11.103157 | V65: =CW65*I65 -> 0 | W65: =ROUND(CX65*I65,2) -> 0 | X65: =(ROUND((((S65+ROUND((ROUND(((((EU65*1.2)*0.6))*AV65*I65),2)*BS65),2))*AT65)/100),2)+ROUND(((ROUND((ROUND(((AE65-(((EU65*1.2)*0.6)))*AV65*I65),2)*BS65),2)*AT65)/100),2)) -> 7680.55 | Y65: =(ROUND((((S65+ROUND((ROUND(((((EU65*1.2)*0.6))*AV65*I65),2)*BS65),2))*AU65)/100),2)+ROUND(((ROUND((ROUND(((AE65-(((EU65*1.2)*0.6)))*AV65*I65),2)*BS65),2)*AU65)/100),2)) -> 5120.37 | AA65: 55890823 | AB65: =ROUND((AC65+AD65+AF65),6) -> 1175.4192 | AC65: =ROUND((((ES65*1)*0.6)),6) -> 35.04 | AD65: =ROUND((((((ET65*1.2)*0.6))-(((EU65*1.2)*0.6)))+AE65),6) -> 37.9152 | AE65: =ROUND((((EU65*1.2)*0.6)),6) -> 0 | AF65: =ROUND((((EV65*1.2)*0.6)),6) -> 1102.464 | AG65: =ROUND((AP65),6) -> 0 | AH65: =(((EW65*1.2)*0.6)) -> 83.52 | AI65: =(((EX65*1.2)*0.6)) -> 0 | AJ65: =(AS65) -> 0 | AK65: 1642.26 | AL65: 58.4 | AM65: 52.66 | AN65: 0 | AO65: 1531.2 | AP65: 0 | AQ65: 116 | AR65: 0 | AS65: 0 | AT65: 93 | AU65: 62 | AV65: 1.087 | AW65: 1 | AZ65: 1 | BA65: 56.35 | BB65: 10.15 | BC65: 10.95 | BH65: 0 | BI65: 1 | BJ65: ТСН-2001.3 Доп. 79, Сб. 9, т. 35, поз. 1 | BM65: 13 | BN65: 0 | BO65: 3.9-35-1 | BP65: 1 | BQ65: 30 | BR65: 0 | BS65: 56.35 | BT65: 1 | BU65: 1 | BV65: 1 | BW65: 1 | BX65: 1 | BZ65: 93 | CA65: 62 | CE65: 1566 | CF65: 0 | CG65: 0 | CM65: 0 | CN65: Поправка: Гл.12.Прил.8.п.8. 3_12.00.01.11.001 Наименование: При наличии напряженных и стесненных условий производства работ (стесненность, сложность складирования и транспортной логистики и т.п.) для объектов, расположенных в пределах круговой магистральной системы улиц "Садовое кольцо" города Москвы Поправка: Гл.6.Прил.2.2.п.2.2.16_06.00.01.35.006 Наименование: При демонтаже металлических конструкций (в т.ч. к стоимости вспомогательных материалов) | CO65: 0 | CP65: =(P65+Q65+S65) -> 8356.8 | CQ65: =ROUND((ROUND((AC65*AW65*1),2)*BC65),2) -> 383.69 | CR65: =(ROUND((ROUND(((((ET65*1.2)*0.6))*AV65*1),2)*BB65),2)+ROUND((ROUND(((AE65-(((EU65*1.2)*0.6)))*AV65*1),2)*BS65),2)) -> 418.28 | CS65: =(ROUND((ROUND(((((EU65*1.2)*0.6))*AV65*1),2)*BS65),2)+ROUND((ROUND(((AE65-(((EU65*1.2)*0.6)))*AV65*1),2)*BS65),2)) -> 0 | CT65: =ROUND((ROUND((AF65*AV65*1),2)*BA65),2) -> 67528.71 | CU65: =AG65 -> 0 | CV65: =(AH65*AV65) -> 90.78624 | CW65: =AI65 -> 0 | CX65: =AJ65 -> 0 | CY65: =(ROUND((((S65+ROUND((ROUND(((((EU65*1.2)*0.6))*AV65*1),2)*BS65),2))*AT65)/100),2)+ROUND(((ROUND((ROUND(((AE65-(((EU65*1.2)*0.6)))*AV65*1),2)*BS65),2)*AT65)/100),2)) -> 7680.55 | CZ65: =(ROUND((((S65+ROUND((ROUND(((((EU65*1.2)*0.6))*AV65*1),2)*BS65),2))*AU65)/100),2)+ROUND(((ROUND((ROUND(((AE65-(((EU65*1.2)*0.6)))*AV65*1),2)*BS65),2)*AU65)/100),2)) -> 5120.37 | DB65: 55 | DD65: *1)*0,6 | DE65: *1,2)*0,6 | DF65: *1,2)*0,6 | DG65: *1,2)*0,6 | DI65: *1,2)*0,6 | DJ65: *1,2)*0,6 | DN65: 0 | DO65: 0 | DP65: 1 | DQ65: 1 | DU65: 1013 | DV65: 1 Т | DW65: 1 Т | DX65: 1 | EE65: 57042902 | EF65: 30 | EG65: Строительные работы | EH65: 0 | EJ65: 1 | EK65: 13 | EL65: ТСН-2001.3-9. Металлические конструкции | EM65: ТСН-2001.3-9-1 | EO65: Поправка: Гл.12.Прил.8.п.8. 3_12.00.01.11.001 Поправка: Гл.6.Прил.2.2.п.2.2.16_06.00.01.35.006 | EQ65: 0 | ER65: 1642.26 | ES65: 58.4 | ET65: 52.66 | EU65: 0 | EV65: 1531.2 | EW65: 116 | EX65: 0 | EY65: 0 | FQ65: 0 | FR65: 0 | FS65: 0 | FX65: 93 | FY65: 62 | GD65: 1 | GF65: -2000456464 | GG65: 2 | GH65: 1 | GI65: 2 | GJ65: 0 | GK65: 0 | GL65: =ROUND(IF(AND(BH65=3,BI65=3,FS65<>0),P65,0),2) -> 0 | GM65: =ROUND(O65+X65+Y65,2)+GX65 -> 21157.72 | GN65: =IF(OR(BI65=0,BI65=1),GM65-GX65,0) -> 21157.72 | GO65: =IF(BI65=2,GM65-GX65,0) -> 0 | GP65: =IF(BI65=4,GM65-GX65,0) -> 0 | GR65: 0 | GS65: 0 | GT65: 0 | GV65: =ROUND((GT65),6) -> 0 | GW65: 1 | GX65: =ROUND(HC65*I65,2) -> 0 | HA65: 0 | HB65: 0 | HC65: =GV65*GW65 -> 0 | HS65: 0 | IK65: 0
A66: 17 | B66: 1 | E66: 17 | F66: 4.8-331-2 | G66: Прокладка металлического перфорированного лотка по установленным конструкциям, массой погонного метра свыше 2 до 4 кг / демонтаж лотков | H66: 100 М ТРАССЫ | I66: =ROUND((78+69+55+447+513+46+99+32)/100,9) -> 13.39 | J66: 0 | K66: =ROUND((78+69+55+447+513+46+99+32)/100,9) -> 13.39 | O66: =ROUND(CP66,2) -> 1074.19 | P66: =ROUND((ROUND((AC66*AW66*I66),2)*BC66),2) -> 0 | Q66: =(ROUND((ROUND(((((ET66*1.2)*0.3))*AV66*I66),2)*BB66),2)+ROUND((ROUND(((AE66-(((EU66*1.2)*0.3)))*AV66*I66),2)*BS66),2)) -> 33.66 | R66: =(ROUND((ROUND(((((EU66*1.2)*0.3))*AV66*I66),2)*BS66),2)+ROUND((ROUND(((AE66-(((EU66*1.2)*0.3)))*AV66*I66),2)*BS66),2)) -> 6.06 | S66: =ROUND((ROUND((AF66*AV66*I66),2)*BA66),2) -> 1040.53 | T66: =ROUND(CU66*I66,2) -> 0 | U66: =CV66*I66 -> 91.551833 | V66: =CW66*I66 -> 0 | W66: =ROUND(CX66*I66,2) -> 0 | X66: =(ROUND((((S66+ROUND((ROUND(((((EU66*1.2)*0.3))*AV66*I66),2)*BS66),2))*AT66)/100),2)+ROUND(((ROUND((ROUND(((AE66-(((EU66*1.2)*0.3)))*AV66*I66),2)*BS66),2)*AT66)/100),2)) -> 1015.19 | Y66: =(ROUND((((S66+ROUND((ROUND(((((EU66*1.2)*0.3))*AV66*I66),2)*BS66),2))*AU66)/100),2)+ROUND(((ROUND((ROUND(((AE66-(((EU66*1.2)*0.3)))*AV66*I66),2)*BS66),2)*AU66)/100),2)) -> 533.76 | AA66: 54971259 | AB66: =ROUND((AC66+AD66+AF66),6) -> 76.6224 | AC66: =ROUND((((ES66*1)*0)),6) -> 0 | AD66: =ROUND((((((ET66*1.2)*0.3))-(((EU66*1.2)*0.3)))+AE66),6) -> 2.4012 | AE66: =ROUND((((EU66*1.2)*0.3)),6) -> 0.432 | AF66: =ROUND((((EV66*1.2)*0.3)),6) -> 74.2212 | AG66: =ROUND((AP66),6) -> 0 | AH66: =(((EW66*1.2)*0.3)) -> 6.5304 | AI66: =(((EX66*1.2)*0.3)) -> 0 | AJ66: =(AS66) -> 0 | AK66: 224.18 | AL66: 11.34 | AM66: 6.67 | AN66: 1.2 | AO66: 206.17 | AP66: 0 | AQ66: 18.14 | AR66: 0 | AS66: 0 | AT66: 97 | AU66: 51 | AV66: 1.047 | AW66: 1 | AZ66: 1 | BA66: 1 | BB66: 1 | BC66: 1 | BH66: 0 | BI66: 2 | BJ66: ТСН-2001.4 Доп. 79, Сб. 8, т. 331, поз. 2 | BM66: 67 | BN66: 0 | BO66: 4.8-331-2 | BP66: 1 | BQ66: 40 | BR66: 0 | BS66: 1 | BT66: 1 | BU66: 1 | BV66: 1 | BW66: 1 | BX66: 1 | BZ66: 97 | CA66: 51 | CE66: 1566 | CF66: 0 | CG66: 0 | CM66: 0 | CN66: Поправка: Гл.12.Прил.8.п.8. 3_12.00.01.11.001 Наименование: При наличии напряженных и стесненных условий производства работ (стесненность, сложность складирования и транспортной логистики и т.п.) для объектов, расположенных в пределах круговой магистральной системы улиц "Садовое кольцо" города Москвы Поправка: Гл.4.Прил.2.2.п.2.2.29_04.00.01.35.003 Наименование: При демонтаже оборудования, предназначенного в лом | CO66: 0 | CP66: =(P66+Q66+S66) -> 1074.19 | CQ66: =ROUND((ROUND((AC66*AW66*1),2)*BC66),2) -> 0 | CR66: =(ROUND((ROUND(((((ET66*1.2)*0.3))*AV66*1),2)*BB66),2)+ROUND((ROUND(((AE66-(((EU66*1.2)*0.3)))*AV66*1),2)*BS66),2)) -> 2.51 | CS66: =(ROUND((ROUND(((((EU66*1.2)*0.3))*AV66*1),2)*BS66),2)+ROUND((ROUND(((AE66-(((EU66*1.2)*0.3)))*AV66*1),2)*BS66),2)) -> 0.45 | CT66: =ROUND((ROUND((AF66*AV66*1),2)*BA66),2) -> 77.71 | CU66: =AG66 -> 0 | CV66: =(AH66*AV66) -> 6.8373288 | CW66: =AI66 -> 0 | CX66: =AJ66 -> 0 | CY66: =(ROUND((((S66+ROUND((ROUND(((((EU66*1.2)*0.3))*AV66*1),2)*BS66),2))*AT66)/100),2)+ROUND(((ROUND((ROUND(((AE66-(((EU66*1.2)*0.3)))*AV66*1),2)*BS66),2)*AT66)/100),2)) -> 1009.75 | CZ66: =(ROUND((((S66+ROUND((ROUND(((((EU66*1.2)*0.3))*AV66*1),2)*BS66),2))*AU66)/100),2)+ROUND(((ROUND((ROUND(((AE66-(((EU66*1.2)*0.3)))*AV66*1),2)*BS66),2)*AU66)/100),2)) -> 530.9 | DB66: 57 | DD66: *1)*0 | DE66: *1,2)*0,3 | DF66: *1,2)*0,3 | DG66: *1,2)*0,3 | DI66: *1,2)*0,3 | DJ66: *1,2)*0,3 | DN66: 0 | DO66: 0 | DP66: 1 | DQ66: 1 | DU66: 1013 | DV66: 100 М ТРАССЫ | DW66: 100 М ТРАССЫ | DX66: 1 | EE66: 57042957 | EF66: 40 | EG66: Монтаж оборудования | EH66: 0 | EJ66: 2 | EK66: 67 | EL66: ТСН-2001.4-8. Электротехнические установки | EM66: ТСН-2001.4-8-1 | EO66: Поправка: Гл.12.Прил.8.п.8. 3_12.00.01.11.001 Поправка: Гл.4.Прил.2.2.п.2.2.29_04.00.01.35.003 | EQ66: 0 | ER66: 224.18 | ES66: 11.34 | ET66: 6.67 | EU66: 1.2 | EV66: 206.17 | EW66: 18.14 | EX66: 0 | EY66: 0 | FQ66: 0 | FR66: 0 | FS66: 0 | FX66: 97 | FY66: 51 | GD66: 1 | GF66: -32704858 | GG66: 2 | GH66: 1 | GI66: 2 | GJ66: 0 | GK66: 0 | GL66: =ROUND(IF(AND(BH66=3,BI66=3,FS66<>0),P66,0),2) -> 0 | GM66: =ROUND(O66+X66+Y66,2)+GX66 -> 2623.14 | GN66: =IF(OR(BI66=0,BI66=1),GM66-GX66,0) -> 0 | GO66: =IF(BI66=2,GM66-GX66,0) -> 2623.14 | GP66: =IF(BI66=4,GM66-GX66,0) -> 0 | GR66: 0 | GS66: 3 | GT66: 0 | GV66: =ROUND((GT66),6) -> 0 | GW66: 1 | GX66: =ROUND(HC66*I66,2) -> 0 | HA66: 0 | HB66: 0 | HC66: =GV66*GW66 -> 0 | HS66: 0 | IK66: 0
A67: 17 | B67: 1 | E67: 17 | F67: 4.8-331-2 | G67: Прокладка металлического перфорированного лотка по установленным конструкциям, массой погонного метра свыше 2 до 4 кг / демонтаж лотков | H67: 100 М ТРАССЫ | I67: =ROUND((78+69+55+447+513+46+99+32)/100,9) -> 13.39 | J67: 0 | K67: =ROUND((78+69+55+447+513+46+99+32)/100,9) -> 13.39 | O67: =ROUND(CP67,2) -> 59272.06 | P67: =ROUND((ROUND((AC67*AW67*I67),2)*BC67),2) -> 0 | Q67: =(ROUND((ROUND(((((ET67*1.2)*0.3))*AV67*I67),2)*BB67),2)+ROUND((ROUND(((AE67-(((EU67*1.2)*0.3)))*AV67*I67),2)*BS67),2)) -> 638.19 | R67: =(ROUND((ROUND(((((EU67*1.2)*0.3))*AV67*I67),2)*BS67),2)+ROUND((ROUND(((AE67-(((EU67*1.2)*0.3)))*AV67*I67),2)*BS67),2)) -> 341.48 | S67: =ROUND((ROUND((AF67*AV67*I67),2)*BA67),2) -> 58633.87 | T67: =ROUND(CU67*I67,2) -> 0 | U67: =CV67*I67 -> 91.551833 | V67: =CW67*I67 -> 0 | W67: =ROUND(CX67*I67,2) -> 0 | X67: =(ROUND((((S67+ROUND((ROUND(((((EU67*1.2)*0.3))*AV67*I67),2)*BS67),2))*AT67)/100),2)+ROUND(((ROUND((ROUND(((AE67-(((EU67*1.2)*0.3)))*AV67*I67),2)*BS67),2)*AT67)/100),2)) -> 57206.09 | Y67: =(ROUND((((S67+ROUND((ROUND(((((EU67*1.2)*0.3))*AV67*I67),2)*BS67),2))*AU67)/100),2)+ROUND(((ROUND((ROUND(((AE67-(((EU67*1.2)*0.3)))*AV67*I67),2)*BS67),2)*AU67)/100),2)) -> 30077.43 | AA67: 55890823 | AB67: =ROUND((AC67+AD67+AF67),6) -> 76.6224 | AC67: =ROUND((((ES67*1)*0)),6) -> 0 | AD67: =ROUND((((((ET67*1.2)*0.3))-(((EU67*1.2)*0.3)))+AE67),6) -> 2.4012 | AE67: =ROUND((((EU67*1.2)*0.3)),6) -> 0.432 | AF67: =ROUND((((EV67*1.2)*0.3)),6) -> 74.2212 | AG67: =ROUND((AP67),6) -> 0 | AH67: =(((EW67*1.2)*0.3)) -> 6.5304 | AI67: =(((EX67*1.2)*0.3)) -> 0 | AJ67: =(AS67) -> 0 | AK67: 224.18 | AL67: 11.34 | AM67: 6.67 | AN67: 1.2 | AO67: 206.17 | AP67: 0 | AQ67: 18.14 | AR67: 0 | AS67: 0 | AT67: 97 | AU67: 51 | AV67: 1.047 | AW67: 1 | AZ67: 1 | BA67: 56.35 | BB67: 18.96 | BC67: 8.24 | BH67: 0 | BI67: 2 | BJ67: ТСН-2001.4 Доп. 79, Сб. 8, т. 331, поз. 2 | BM67: 67 | BN67: 0 | BO67: 4.8-331-2 | BP67: 1 | BQ67: 40 | BR67: 0 | BS67: 56.35 | BT67: 1 | BU67: 1 | BV67: 1 | BW67: 1 | BX67: 1 | BZ67: 97 | CA67: 51 | CE67: 1566 | CF67: 0 | CG67: 0 | CM67: 0 | CN67: Поправка: Гл.12.Прил.8.п.8. 3_12.00.01.11.001 Наименование: При наличии напряженных и стесненных условий производства работ (стесненность, сложность складирования и транспортной логистики и т.п.) для объектов, расположенных в пределах круговой магистральной системы улиц "Садовое кольцо" города Москвы Поправка: Гл.4.Прил.2.2.п.2.2.29_04.00.01.35.003 Наименование: При демонтаже оборудования, предназначенного в лом | CO67: 0 | CP67: =(P67+Q67+S67) -> 59272.06 | CQ67: =ROUND((ROUND((AC67*AW67*1),2)*BC67),2) -> 0 | CR67: =(ROUND((ROUND(((((ET67*1.2)*0.3))*AV67*1),2)*BB67),2)+ROUND((ROUND(((AE67-(((EU67*1.2)*0.3)))*AV67*1),2)*BS67),2)) -> 47.59 | CS67: =(ROUND((ROUND(((((EU67*1.2)*0.3))*AV67*1),2)*BS67),2)+ROUND((ROUND(((AE67-(((EU67*1.2)*0.3)))*AV67*1),2)*BS67),2)) -> 25.36 | CT67: =ROUND((ROUND((AF67*AV67*1),2)*BA67),2) -> 4378.96 | CU67: =AG67 -> 0 | CV67: =(AH67*AV67) -> 6.8373288 | CW67: =AI67 -> 0 | CX67: =AJ67 -> 0 | CY67: =(ROUND((((S67+ROUND((ROUND(((((EU67*1.2)*0.3))*AV67*1),2)*BS67),2))*AT67)/100),2)+ROUND(((ROUND((ROUND(((AE67-(((EU67*1.2)*0.3)))*AV67*1),2)*BS67),2)*AT67)/100),2)) -> 56899.45 | CZ67: =(ROUND((((S67+ROUND((ROUND(((((EU67*1.2)*0.3))*AV67*1),2)*BS67),2))*AU67)/100),2)+ROUND(((ROUND((ROUND(((AE67-(((EU67*1.2)*0.3)))*AV67*1),2)*BS67),2)*AU67)/100),2)) -> 29916.21 | DB67: 59 | DD67: *1)*0 | DE67: *1,2)*0,3 | DF67: *1,2)*0,3 | DG67: *1,2)*0,3 | DI67: *1,2)*0,3 | DJ67: *1,2)*0,3 | DN67: 0 | DO67: 0 | DP67: 1 | DQ67: 1 | DU67: 1013 | DV67: 100 М ТРАССЫ | DW67: 100 М ТРАССЫ | DX67: 1 | EE67: 57042957 | EF67: 40 | EG67: Монтаж оборудования | EH67: 0 | EJ67: 2 | EK67: 67 | EL67: ТСН-2001.4-8. Электротехнические установки | EM67: ТСН-2001.4-8-1 | EO67: Поправка: Гл.12.Прил.8.п.8. 3_12.00.01.11.001 Поправка: Гл.4.Прил.2.2.п.2.2.29_04.00.01.35.003 | EQ67: 0 | ER67: 224.18 | ES67: 11.34 | ET67: 6.67 | EU67: 1.2 | EV67: 206.17 | EW67: 18.14 | EX67: 0 | EY67: 0 | FQ67: 0 | FR67: 0 | FS67: 0 | FX67: 97 | FY67: 51 | GD67: 1 | GF67: -32704858 | GG67: 2 | GH67: 1 | GI67: 2 | GJ67: 0 | GK67: 0 | GL67: =ROUND(IF(AND(BH67=3,BI67=3,FS67<>0),P67,0),2) -> 0 | GM67: =ROUND(O67+X67+Y67,2)+GX67 -> 146555.58 | GN67: =IF(OR(BI67=0,BI67=1),GM67-GX67,0) -> 0 | GO67: =IF(BI67=2,GM67-GX67,0) -> 146555.58 | GP67: =IF(BI67=4,GM67-GX67,0) -> 0 | GR67: 0 | GS67: 0 | GT67: 0 | GV67: =ROUND((GT67),6) -> 0 | GW67: 1 | GX67: =ROUND(HC67*I67,2) -> 0 | HA67: 0 | HB67: 0 | HC67: =GV67*GW67 -> 0 | HS67: 0 | IK67: 0
A68: 17 | B68: 1 | E68: 18 | F68: 4.8-331-12 | G68: Установка крышек металлических на лотки металлические перфорированные и неперфорированные массой 1 м свыше 2 до 4 кг / демонтаж крышек лотков | H68: 100 М ТРАССЫ | I68: =ROUND(1339/100,9) -> 13.39 | J68: 0 | K68: =ROUND(1339/100,9) -> 13.39 | O68: =ROUND(CP68,2) -> 442.52 | P68: =ROUND((ROUND((AC68*AW68*I68),2)*BC68),2) -> 0 | Q68: =(ROUND((ROUND(((((ET68*1.2)*0.3))*AV68*I68),2)*BB68),2)+ROUND((ROUND(((AE68-(((EU68*1.2)*0.3)))*AV68*I68),2)*BS68),2)) -> 28.97 | R68: =(ROUND((ROUND(((((EU68*1.2)*0.3))*AV68*I68),2)*BS68),2)+ROUND((ROUND(((AE68-(((EU68*1.2)*0.3)))*AV68*I68),2)*BS68),2)) -> 5.3 | S68: =ROUND((ROUND((AF68*AV68*I68),2)*BA68),2) -> 413.55 | T68: =ROUND(CU68*I68,2) -> 0 | U68: =CV68*I68 -> 36.69139 | V68: =CW68*I68 -> 0 | W68: =ROUND(CX68*I68,2) -> 0 | X68: =(ROUND((((S68+ROUND((ROUND(((((EU68*1.2)*0.3))*AV68*I68),2)*BS68),2))*AT68)/100),2)+ROUND(((ROUND((ROUND(((AE68-(((EU68*1.2)*0.3)))*AV68*I68),2)*BS68),2)*AT68)/100),2)) -> 406.28 | Y68: =(ROUND((((S68+ROUND((ROUND(((((EU68*1.2)*0.3))*AV68*I68),2)*BS68),2))*AU68)/100),2)+ROUND(((ROUND((ROUND(((AE68-(((EU68*1.2)*0.3)))*AV68*I68),2)*BS68),2)*AU68)/100),2)) -> 213.61 | AA68: 54971259 | AB68: =ROUND((AC68+AD68+AF68),6) -> 31.5648 | AC68: =ROUND((((ES68*1)*0)),6) -> 0 | AD68: =ROUND((((((ET68*1.2)*0.3))-(((EU68*1.2)*0.3)))+AE68),6) -> 2.0664 | AE68: =ROUND((((EU68*1.2)*0.3)),6) -> 0.378 | AF68: =ROUND((((EV68*1.2)*0.3)),6) -> 29.4984 | AG68: =ROUND((AP68),6) -> 0 | AH68: =(((EW68*1.2)*0.3)) -> 2.6172 | AI68: =(((EX68*1.2)*0.3)) -> 0 | AJ68: =(AS68) -> 0 | AK68: 104.14 | AL68: 16.46 | AM68: 5.74 | AN68: 1.05 | AO68: 81.94 | AP68: 0 | AQ68: 7.27 | AR68: 0 | AS68: 0 | AT68: 97 | AU68: 51 | AV68: 1.047 | AW68: 1 | AZ68: 1 | BA68: 1 | BB68: 1 | BC68: 1 | BH68: 0 | BI68: 2 | BJ68: ТСН-2001.4 Доп. 80, Сб. 8, т. 331, поз. 12 | BM68: 67 | BN68: 0 | BO68: 4.8-331-12 | BP68: 1 | BQ68: 40 | BR68: 0 | BS68: 1 | BT68: 1 | BU68: 1 | BV68: 1 | BW68: 1 | BX68: 1 | BZ68: 97 | CA68: 51 | CE68: 1566 | CF68: 0 | CG68: 0 | CM68: 0 | CN68: Поправка: Гл.12.Прил.8.п.8. 3_12.00.01.11.001 Наименование: При наличии усложненных условий производства работ (стесненность, сложность складирования и транспортной логистики, наличие в зоне производства работ действующего технологического оборудования или движения технологического транспорта и т.п.) для объектов, расположенных в пределах круговой магистральной системы улиц "Садовое кольцо" города Москвы Поправка: Гл.4.Прил.2.2.п.2.2.29_04.00.01.35.003 Наименование: При демонтаже оборудования, предназначенного в лом | CO68: 0 | CP68: =(P68+Q68+S68) -> 442.52 | CQ68: =ROUND((ROUND((AC68*AW68*1),2)*BC68),2) -> 0 | CR68: =(ROUND((ROUND(((((ET68*1.2)*0.3))*AV68*1),2)*BB68),2)+ROUND((ROUND(((AE68-(((EU68*1.2)*0.3)))*AV68*1),2)*BS68),2)) -> 2.16 | CS68: =(ROUND((ROUND(((((EU68*1.2)*0.3))*AV68*1),2)*BS68),2)+ROUND((ROUND(((AE68-(((EU68*1.2)*0.3)))*AV68*1),2)*BS68),2)) -> 0.4 | CT68: =ROUND((ROUND((AF68*AV68*1),2)*BA68),2) -> 30.88 | CU68: =AG68 -> 0 | CV68: =(AH68*AV68) -> 2.7402084 | CW68: =AI68 -> 0 | CX68: =AJ68 -> 0 | CY68: =(ROUND((((S68+ROUND((ROUND(((((EU68*1.2)*0.3))*AV68*1),2)*BS68),2))*AT68)/100),2)+ROUND(((ROUND((ROUND(((AE68-(((EU68*1.2)*0.3)))*AV68*1),2)*BS68),2)*AT68)/100),2)) -> 401.53 | CZ68: =(ROUND((((S68+ROUND((ROUND(((((EU68*1.2)*0.3))*AV68*1),2)*BS68),2))*AU68)/100),2)+ROUND(((ROUND((ROUND(((AE68-(((EU68*1.2)*0.3)))*AV68*1),2)*BS68),2)*AU68)/100),2)) -> 211.11 | DB68: 61 | DD68: *1)*0 | DE68: *1,2)*0,3 | DF68: *1,2)*0,3 | DG68: *1,2)*0,3 | DI68: *1,2)*0,3 | DJ68: *1,2)*0,3 | DN68: 0 | DO68: 0 | DP68: 1 | DQ68: 1 | DU68: 1013 | DV68: 100 М ТРАССЫ | DW68: 100 М ТРАССЫ | DX68: 1 | EE68: 57042957 | EF68: 40 | EG68: Монтаж оборудования | EH68: 0 | EJ68: 2 | EK68: 67 | EL68: ТСН-2001.4-8. Электротехнические установки | EM68: ТСН-2001.4-8-1 | EO68: Поправка: Гл.12.Прил.8.п.8. 3_12.00.01.11.001 Поправка: Гл.4.Прил.2.2.п.2.2.29_04.00.01.35.003 | EQ68: 0 | ER68: 104.14 | ES68: 16.46 | ET68: 5.74 | EU68: 1.05 | EV68: 81.94 | EW68: 7.27 | EX68: 0 | EY68: 0 | FQ68: 0 | FR68: 0 | FS68: 0 | FX68: 97 | FY68: 51 | GD68: 1 | GF68: -554369069 | GG68: 2 | GH68: 1 | GI68: 2 | GJ68: 0 | GK68: 0 | GL68: =ROUND(IF(AND(BH68=3,BI68=3,FS68<>0),P68,0),2) -> 0 | GM68: =ROUND(O68+X68+Y68,2)+GX68 -> 1062.41 | GN68: =IF(OR(BI68=0,BI68=1),GM68-GX68,0) -> 0 | GO68: =IF(BI68=2,GM68-GX68,0) -> 1062.41 | GP68: =IF(BI68=4,GM68-GX68,0) -> 0 | GR68: 0 | GS68: 3 | GT68: 0 | GV68: =ROUND((GT68),6) -> 0 | GW68: 1 | GX68: =ROUND(HC68*I68,2) -> 0 | HA68: 0 | HB68: 0 | HC68: =GV68*GW68 -> 0 | HS68: 0 | IK68: 0
A69: 17 | B69: 1 | E69: 18 | F69: 4.8-331-12 | G69: Установка крышек металлических на лотки металлические перфорированные и неперфорированные массой 1 м свыше 2 до 4 кг / демонтаж крышек лотков | H69: 100 М ТРАССЫ | I69: =ROUND(1339/100,9) -> 13.39 | J69: 0 | K69: =ROUND(1339/100,9) -> 13.39 | O69: =ROUND(CP69,2) -> 23858.89 | P69: =ROUND((ROUND((AC69*AW69*I69),2)*BC69),2) -> 0 | Q69: =(ROUND((ROUND(((((ET69*1.2)*0.3))*AV69*I69),2)*BB69),2)+ROUND((ROUND(((AE69-(((EU69*1.2)*0.3)))*AV69*I69),2)*BS69),2)) -> 555.35 | R69: =(ROUND((ROUND(((((EU69*1.2)*0.3))*AV69*I69),2)*BS69),2)+ROUND((ROUND(((AE69-(((EU69*1.2)*0.3)))*AV69*I69),2)*BS69),2)) -> 298.66 | S69: =ROUND((ROUND((AF69*AV69*I69),2)*BA69),2) -> 23303.54 | T69: =ROUND(CU69*I69,2) -> 0 | U69: =CV69*I69 -> 36.69139 | V69: =CW69*I69 -> 0 | W69: =ROUND(CX69*I69,2) -> 0 | X69: =(ROUND((((S69+ROUND((ROUND(((((EU69*1.2)*0.3))*AV69*I69),2)*BS69),2))*AT69)/100),2)+ROUND(((ROUND((ROUND(((AE69-(((EU69*1.2)*0.3)))*AV69*I69),2)*BS69),2)*AT69)/100),2)) -> 22894.13 | Y69: =(ROUND((((S69+ROUND((ROUND(((((EU69*1.2)*0.3))*AV69*I69),2)*BS69),2))*AU69)/100),2)+ROUND(((ROUND((ROUND(((AE69-(((EU69*1.2)*0.3)))*AV69*I69),2)*BS69),2)*AU69)/100),2)) -> 12037.12 | AA69: 55890823 | AB69: =ROUND((AC69+AD69+AF69),6) -> 31.5648 | AC69: =ROUND((((ES69*1)*0)),6) -> 0 | AD69: =ROUND((((((ET69*1.2)*0.3))-(((EU69*1.2)*0.3)))+AE69),6) -> 2.0664 | AE69: =ROUND((((EU69*1.2)*0.3)),6) -> 0.378 | AF69: =ROUND((((EV69*1.2)*0.3)),6) -> 29.4984 | AG69: =ROUND((AP69),6) -> 0 | AH69: =(((EW69*1.2)*0.3)) -> 2.6172 | AI69: =(((EX69*1.2)*0.3)) -> 0 | AJ69: =(AS69) -> 0 | AK69: 104.14 | AL69: 16.46 | AM69: 5.74 | AN69: 1.05 | AO69: 81.94 | AP69: 0 | AQ69: 7.27 | AR69: 0 | AS69: 0 | AT69: 97 | AU69: 51 | AV69: 1.047 | AW69: 1 | AZ69: 1 | BA69: 56.35 | BB69: 19.17 | BC69: 7.31 | BH69: 0 | BI69: 2 | BJ69: ТСН-2001.4 Доп. 80, Сб. 8, т. 331, поз. 12 | BM69: 67 | BN69: 0 | BO69: 4.8-331-12 | BP69: 1 | BQ69: 40 | BR69: 0 | BS69: 56.35 | BT69: 1 | BU69: 1 | BV69: 1 | BW69: 1 | BX69: 1 | BZ69: 97 | CA69: 51 | CE69: 1566 | CF69: 0 | CG69: 0 | CM69: 0 | CN69: Поправка: Гл.12.Прил.8.п.8. 3_12.00.01.11.001 Наименование: При наличии усложненных условий производства работ (стесненность, сложность складирования и транспортной логистики, наличие в зоне производства работ действующего технологического оборудования или движения технологического транспорта и т.п.) для объектов, расположенных в пределах круговой магистральной системы улиц "Садовое кольцо" города Москвы Поправка: Гл.4.Прил.2.2.п.2.2.29_04.00.01.35.003 Наименование: При демонтаже оборудования, предназначенного в лом | CO69: 0 | CP69: =(P69+Q69+S69) -> 23858.89 | CQ69: =ROUND((ROUND((AC69*AW69*1),2)*BC69),2) -> 0 | CR69: =(ROUND((ROUND(((((ET69*1.2)*0.3))*AV69*1),2)*BB69),2)+ROUND((ROUND(((AE69-(((EU69*1.2)*0.3)))*AV69*1),2)*BS69),2)) -> 41.41 | CS69: =(ROUND((ROUND(((((EU69*1.2)*0.3))*AV69*1),2)*BS69),2)+ROUND((ROUND(((AE69-(((EU69*1.2)*0.3)))*AV69*1),2)*BS69),2)) -> 22.54 | CT69: =ROUND((ROUND((AF69*AV69*1),2)*BA69),2) -> 1740.09 | CU69: =AG69 -> 0 | CV69: =(AH69*AV69) -> 2.7402084 | CW69: =AI69 -> 0 | CX69: =AJ69 -> 0 | CY69: =(ROUND((((S69+ROUND((ROUND(((((EU69*1.2)*0.3))*AV69*1),2)*BS69),2))*AT69)/100),2)+ROUND(((ROUND((ROUND(((AE69-(((EU69*1.2)*0.3)))*AV69*1),2)*BS69),2)*AT69)/100),2)) -> 22626.3 | CZ69: =(ROUND((((S69+ROUND((ROUND(((((EU69*1.2)*0.3))*AV69*1),2)*BS69),2))*AU69)/100),2)+ROUND(((ROUND((ROUND(((AE69-(((EU69*1.2)*0.3)))*AV69*1),2)*BS69),2)*AU69)/100),2)) -> 11896.3 | DB69: 63 | DD69: *1)*0 | DE69: *1,2)*0,3 | DF69: *1,2)*0,3 | DG69: *1,2)*0,3 | DI69: *1,2)*0,3 | DJ69: *1,2)*0,3 | DN69: 0 | DO69: 0 | DP69: 1 | DQ69: 1 | DU69: 1013 | DV69: 100 М ТРАССЫ | DW69: 100 М ТРАССЫ | DX69: 1 | EE69: 57042957 | EF69: 40 | EG69: Монтаж оборудования | EH69: 0 | EJ69: 2 | EK69: 67 | EL69: ТСН-2001.4-8. Электротехнические установки | EM69: ТСН-2001.4-8-1 | EO69: Поправка: Гл.12.Прил.8.п.8. 3_12.00.01.11.001 Поправка: Гл.4.Прил.2.2.п.2.2.29_04.00.01.35.003 | EQ69: 0 | ER69: 104.14 | ES69: 16.46 | ET69: 5.74 | EU69: 1.05 | EV69: 81.94 | EW69: 7.27 | EX69: 0 | EY69: 0 | FQ69: 0 | FR69: 0 | FS69: 0 | FX69: 97 | FY69: 51 | GD69: 1 | GF69: -554369069 | GG69: 2 | GH69: 1 | GI69: 2 | GJ69: 0 | GK69: 0 | GL69: =ROUND(IF(AND(BH69=3,BI69=3,FS69<>0),P69,0),2) -> 0 | GM69: =ROUND(O69+X69+Y69,2)+GX69 -> 58790.14 | GN69: =IF(OR(BI69=0,BI69=1),GM69-GX69,0) -> 0 | GO69: =IF(BI69=2,GM69-GX69,0) -> 58790.14 | GP69: =IF(BI69=4,GM69-GX69,0) -> 0 | GR69: 0 | GS69: 0 | GT69: 0 | GV69: =ROUND((GT69),6) -> 0 | GW69: 1 | GX69: =ROUND(HC69*I69,2) -> 0 | HA69: 0 | HB69: 0 | HC69: =GV69*GW69 -> 0 | HS69: 0 | IK69: 0
A70: 17 | B70: 1 | E70: 19 | F70: 4.8-83-22 | G70: Установка конструкций металлических кабельных, кронштейна настенного крепления на анкерах массой до 15 кг / демонтаж кронштейнов | H70: 100 шт. кронштейнов | I70: =ROUND((198+24)/100,9) -> 2.22 | J70: 0 | K70: =ROUND((198+24)/100,9) -> 2.22 | O70: =ROUND(CP70,2) -> 457.53 | P70: =ROUND((ROUND((AC70*AW70*I70),2)*BC70),2) -> 0 | Q70: =(ROUND((ROUND(((((ET70*1.2)*0.3))*AV70*I70),2)*BB70),2)+ROUND((ROUND(((AE70-(((EU70*1.2)*0.3)))*AV70*I70),2)*BS70),2)) -> 20.28 | R70: =(ROUND((ROUND(((((EU70*1.2)*0.3))*AV70*I70),2)*BS70),2)+ROUND((ROUND(((AE70-(((EU70*1.2)*0.3)))*AV70*I70),2)*BS70),2)) -> 1.64 | S70: =ROUND((ROUND((AF70*AV70*I70),2)*BA70),2) -> 437.25 | T70: =ROUND(CU70*I70,2) -> 0 | U70: =CV70*I70 -> 33.915235 | V70: =CW70*I70 -> 0 | W70: =ROUND(CX70*I70,2) -> 0 | X70: =(ROUND((((S70+ROUND((ROUND(((((EU70*1.2)*0.3))*AV70*I70),2)*BS70),2))*AT70)/100),2)+ROUND(((ROUND((ROUND(((AE70-(((EU70*1.2)*0.3)))*AV70*I70),2)*BS70),2)*AT70)/100),2)) -> 425.72 | Y70: =(ROUND((((S70+ROUND((ROUND(((((EU70*1.2)*0.3))*AV70*I70),2)*BS70),2))*AU70)/100),2)+ROUND(((ROUND((ROUND(((AE70-(((EU70*1.2)*0.3)))*AV70*I70),2)*BS70),2)*AU70)/100),2)) -> 223.83 | AA70: 54971259 | AB70: =ROUND((AC70+AD70+AF70),6) -> 189.6012 | AC70: =ROUND((((ES70*1)*0)),6) -> 0 | AD70: =ROUND((((((ET70*1.2)*0.3))-(((EU70*1.2)*0.3)))+AE70),6) -> 8.406 | AE70: =ROUND((((EU70*1.2)*0.3)),6) -> 0.6804 | AF70: =ROUND((((EV70*1.2)*0.3)),6) -> 181.1952 | AG70: =ROUND((AP70),6) -> 0 | AH70: =(((EW70*1.2)*0.3)) -> 14.0544 | AI70: =(((EX70*1.2)*0.3)) -> 0 | AJ70: =(AS70) -> 0 | AK70: 5265.89 | AL70: 4739.22 | AM70: 23.35 | AN70: 1.89 | AO70: 503.32 | AP70: 0 | AQ70: 39.04 | AR70: 0 | AS70: 0 | AT70: 97 | AU70: 51 | AV70: 1.087 | AW70: 1 | AZ70: 1 | BA70: 1 | BB70: 1 | BC70: 1 | BH70: 0 | BI70: 2 | BJ70: ТСН-2001.4 Доп. 69, Сб. 8, т. 83, поз. 22 | BM70: 67 | BN70: 0 | BO70: 4.8-83-22 | BP70: 1 | BQ70: 40 | BR70: 0 | BS70: 1 | BT70: 1 | BU70: 1 | BV70: 1 | BW70: 1 | BX70: 1 | BZ70: 97 | CA70: 51 | CE70: 1566 | CF70: 0 | CG70: 0 | CM70: 0 | CN70: Поправка: Гл.12.Прил.8.п.8. 3_12.00.01.11.001 Наименование: При наличии напряженных и стесненных условий производства работ (стесненность, сложность складирования и транспортной логистики и т.п.) для объектов, расположенных в пределах круговой магистральной системы улиц "Садовое кольцо" города Москвы Поправка: Гл.4.Прил.2.2.п.2.2.29_04.00.01.35.003 Наименование: При демонтаже оборудования, предназначенного в лом | CO70: 0 | CP70: =(P70+Q70+S70) -> 457.53 | CQ70: =ROUND((ROUND((AC70*AW70*1),2)*BC70),2) -> 0 | CR70: =(ROUND((ROUND(((((ET70*1.2)*0.3))*AV70*1),2)*BB70),2)+ROUND((ROUND(((AE70-(((EU70*1.2)*0.3)))*AV70*1),2)*BS70),2)) -> 9.14 | CS70: =(ROUND((ROUND(((((EU70*1.2)*0.3))*AV70*1),2)*BS70),2)+ROUND((ROUND(((AE70-(((EU70*1.2)*0.3)))*AV70*1),2)*BS70),2)) -> 0.74 | CT70: =ROUND((ROUND((AF70*AV70*1),2)*BA70),2) -> 196.96 | CU70: =AG70 -> 0 | CV70: =(AH70*AV70) -> 15.277133 | CW70: =AI70 -> 0 | CX70: =AJ70 -> 0 | CY70: =(ROUND((((S70+ROUND((ROUND(((((EU70*1.2)*0.3))*AV70*1),2)*BS70),2))*AT70)/100),2)+ROUND(((ROUND((ROUND(((AE70-(((EU70*1.2)*0.3)))*AV70*1),2)*BS70),2)*AT70)/100),2)) -> 424.85 | CZ70: =(ROUND((((S70+ROUND((ROUND(((((EU70*1.2)*0.3))*AV70*1),2)*BS70),2))*AU70)/100),2)+ROUND(((ROUND((ROUND(((AE70-(((EU70*1.2)*0.3)))*AV70*1),2)*BS70),2)*AU70)/100),2)) -> 223.37 | DB70: 65 | DD70: *1)*0 | DE70: *1,2)*0,3 | DF70: *1,2)*0,3 | DG70: *1,2)*0,3 | DI70: *1,2)*0,3 | DJ70: *1,2)*0,3 | DN70: 0 | DO70: 0 | DP70: 1 | DQ70: 1 | DU70: 30517203 | DV70: 100 шт. кронштейнов | DW70: 100 шт. кронштейнов | DX70: 1 | EE70: 57042957 | EF70: 40 | EG70: Монтаж оборудования | EH70: 0 | EJ70: 2 | EK70: 67 | EL70: ТСН-2001.4-8. Электротехнические установки | EM70: ТСН-2001.4-8-1 | EO70: Поправка: Гл.12.Прил.8.п.8. 3_12.00.01.11.001 Поправка: Гл.4.Прил.2.2.п.2.2.29_04.00.01.35.003 | EQ70: 0 | ER70: 5265.89 | ES70: 4739.22 | ET70: 23.35 | EU70: 1.89 | EV70: 503.32 | EW70: 39.04 | EX70: 0 | EY70: 0 | FQ70: 0 | FR70: 0 | FS70: 0 | FX70: 97 | FY70: 51 | GD70: 1 | GF70: 1230429216 | GG70: 2 | GH70: 1 | GI70: 2 | GJ70: 0 | GK70: 0 | GL70: =ROUND(IF(AND(BH70=3,BI70=3,FS70<>0),P70,0),2) -> 0 | GM70: =ROUND(O70+X70+Y70,2)+GX70 -> 1107.08 | GN70: =IF(OR(BI70=0,BI70=1),GM70-GX70,0) -> 0 | GO70: =IF(BI70=2,GM70-GX70,0) -> 1107.08 | GP70: =IF(BI70=4,GM70-GX70,0) -> 0 | GR70: 0 | GS70: 3 | GT70: 0 | GV70: =ROUND((GT70),6) -> 0 | GW70: 1 | GX70: =ROUND(HC70*I70,2) -> 0 | HA70: 0 | HB70: 0 | HC70: =GV70*GW70 -> 0 | HS70: 0 | IK70: 0
A71: 17 | B71: 1 | E71: 19 | F71: 4.8-83-22 | G71: Установка конструкций металлических кабельных, кронштейна настенного крепления на анкерах массой до 15 кг / демонтаж кронштейнов | H71: 100 шт. кронштейнов | I71: =ROUND((198+24)/100,9) -> 2.22 | J71: 0 | K71: =ROUND((198+24)/100,9) -> 2.22 | O71: =ROUND(CP71,2) -> 24914.24 | P71: =ROUND((ROUND((AC71*AW71*I71),2)*BC71),2) -> 0 | Q71: =(ROUND((ROUND(((((ET71*1.2)*0.3))*AV71*I71),2)*BB71),2)+ROUND((ROUND(((AE71-(((EU71*1.2)*0.3)))*AV71*I71),2)*BS71),2)) -> 275.2 | R71: =(ROUND((ROUND(((((EU71*1.2)*0.3))*AV71*I71),2)*BS71),2)+ROUND((ROUND(((AE71-(((EU71*1.2)*0.3)))*AV71*I71),2)*BS71),2)) -> 92.41 | S71: =ROUND((ROUND((AF71*AV71*I71),2)*BA71),2) -> 24639.04 | T71: =ROUND(CU71*I71,2) -> 0 | U71: =CV71*I71 -> 33.915235 | V71: =CW71*I71 -> 0 | W71: =ROUND(CX71*I71,2) -> 0 | X71: =(ROUND((((S71+ROUND((ROUND(((((EU71*1.2)*0.3))*AV71*I71),2)*BS71),2))*AT71)/100),2)+ROUND(((ROUND((ROUND(((AE71-(((EU71*1.2)*0.3)))*AV71*I71),2)*BS71),2)*AT71)/100),2)) -> 23989.51 | Y71: =(ROUND((((S71+ROUND((ROUND(((((EU71*1.2)*0.3))*AV71*I71),2)*BS71),2))*AU71)/100),2)+ROUND(((ROUND((ROUND(((AE71-(((EU71*1.2)*0.3)))*AV71*I71),2)*BS71),2)*AU71)/100),2)) -> 12613.04 | AA71: 55890823 | AB71: =ROUND((AC71+AD71+AF71),6) -> 189.6012 | AC71: =ROUND((((ES71*1)*0)),6) -> 0 | AD71: =ROUND((((((ET71*1.2)*0.3))-(((EU71*1.2)*0.3)))+AE71),6) -> 8.406 | AE71: =ROUND((((EU71*1.2)*0.3)),6) -> 0.6804 | AF71: =ROUND((((EV71*1.2)*0.3)),6) -> 181.1952 | AG71: =ROUND((AP71),6) -> 0 | AH71: =(((EW71*1.2)*0.3)) -> 14.0544 | AI71: =(((EX71*1.2)*0.3)) -> 0 | AJ71: =(AS71) -> 0 | AK71: 5265.89 | AL71: 4739.22 | AM71: 23.35 | AN71: 1.89 | AO71: 503.32 | AP71: 0 | AQ71: 39.04 | AR71: 0 | AS71: 0 | AT71: 97 | AU71: 51 | AV71: 1.087 | AW71: 1 | AZ71: 1 | BA71: 56.35 | BB71: 13.57 | BC71: 17.48 | BH71: 0 | BI71: 2 | BJ71: ТСН-2001.4 Доп. 69, Сб. 8, т. 83, поз. 22 | BM71: 67 | BN71: 0 | BO71: 4.8-83-22 | BP71: 1 | BQ71: 40 | BR71: 0 | BS71: 56.35 | BT71: 1 | BU71: 1 | BV71: 1 | BW71: 1 | BX71: 1 | BZ71: 97 | CA71: 51 | CE71: 1566 | CF71: 0 | CG71: 0 | CM71: 0 | CN71: Поправка: Гл.12.Прил.8.п.8. 3_12.00.01.11.001 Наименование: При наличии напряженных и стесненных условий производства работ (стесненность, сложность складирования и транспортной логистики и т.п.) для объектов, расположенных в пределах круговой магистральной системы улиц "Садовое кольцо" города Москвы Поправка: Гл.4.Прил.2.2.п.2.2.29_04.00.01.35.003 Наименование: При демонтаже оборудования, предназначенного в лом | CO71: 0 | CP71: =(P71+Q71+S71) -> 24914.24 | CQ71: =ROUND((ROUND((AC71*AW71*1),2)*BC71),2) -> 0 | CR71: =(ROUND((ROUND(((((ET71*1.2)*0.3))*AV71*1),2)*BB71),2)+ROUND((ROUND(((AE71-(((EU71*1.2)*0.3)))*AV71*1),2)*BS71),2)) -> 124.03 | CS71: =(ROUND((ROUND(((((EU71*1.2)*0.3))*AV71*1),2)*BS71),2)+ROUND((ROUND(((AE71-(((EU71*1.2)*0.3)))*AV71*1),2)*BS71),2)) -> 41.7 | CT71: =ROUND((ROUND((AF71*AV71*1),2)*BA71),2) -> 11098.7 | CU71: =AG71 -> 0 | CV71: =(AH71*AV71) -> 15.277133 | CW71: =AI71 -> 0 | CX71: =AJ71 -> 0 | CY71: =(ROUND((((S71+ROUND((ROUND(((((EU71*1.2)*0.3))*AV71*1),2)*BS71),2))*AT71)/100),2)+ROUND(((ROUND((ROUND(((AE71-(((EU71*1.2)*0.3)))*AV71*1),2)*BS71),2)*AT71)/100),2)) -> 23940.32 | CZ71: =(ROUND((((S71+ROUND((ROUND(((((EU71*1.2)*0.3))*AV71*1),2)*BS71),2))*AU71)/100),2)+ROUND(((ROUND((ROUND(((AE71-(((EU71*1.2)*0.3)))*AV71*1),2)*BS71),2)*AU71)/100),2)) -> 12587.18 | DB71: 67 | DD71: *1)*0 | DE71: *1,2)*0,3 | DF71: *1,2)*0,3 | DG71: *1,2)*0,3 | DI71: *1,2)*0,3 | DJ71: *1,2)*0,3 | DN71: 0 | DO71: 0 | DP71: 1 | DQ71: 1 | DU71: 30517203 | DV71: 100 шт. кронштейнов | DW71: 100 шт. кронштейнов | DX71: 1 | EE71: 57042957 | EF71: 40 | EG71: Монтаж оборудования | EH71: 0 | EJ71: 2 | EK71: 67 | EL71: ТСН-2001.4-8. Электротехнические установки | EM71: ТСН-2001.4-8-1 | EO71: Поправка: Гл.12.Прил.8.п.8. 3_12.00.01.11.001 Поправка: Гл.4.Прил.2.2.п.2.2.29_04.00.01.35.003 | EQ71: 0 | ER71: 5265.89 | ES71: 4739.22 | ET71: 23.35 | EU71: 1.89 | EV71: 503.32 | EW71: 39.04 | EX71: 0 | EY71: 0 | FQ71: 0 | FR71: 0 | FS71: 0 | FX71: 97 | FY71: 51 | GD71: 1 | GF71: 1230429216 | GG71: 2 | GH71: 1 | GI71: 2 | GJ71: 0 | GK71: 0 | GL71: =ROUND(IF(AND(BH71=3,BI71=3,FS71<>0),P71,0),2) -> 0 | GM71: =ROUND(O71+X71+Y71,2)+GX71 -> 61516.79 | GN71: =IF(OR(BI71=0,BI71=1),GM71-GX71,0) -> 0 | GO71: =IF(BI71=2,GM71-GX71,0) -> 61516.79 | GP71: =IF(BI71=4,GM71-GX71,0) -> 0 | GR71: 0 | GS71: 0 | GT71: 0 | GV71: =ROUND((GT71),6) -> 0 | GW71: 1 | GX71: =ROUND(HC71*I71,2) -> 0 | HA71: 0 | HB71: 0 | HC71: =GV71*GW71 -> 0 | HS71: 0 | IK71: 0
A72: 19 | B72: 1 | G72: Демонтаж молниезащиты и заземления | AA72: 1 | IK72: 0
