Workbook

Sheet Смета по ТСН-2001(с доп.67
A1: =Source!B1 -> Smeta.RU (495) 974-1589
J2: Форма № 4б
A3: Капитальный ремонт здания Государственного бюджетного общеобразовательного учреждения города Москвы «Школа №1574» по адресу: г. Москва, Старопименовский пер., д. №5. | AP3: Капитальный ремонт здания Государственного бюджетного общеобразовательного учреждения города Москвы «Школа №1574» по адресу: г. Москва, Старопименовский пер., д. №5. 02-01-21 Спринклерное пожаротушение
A4: (наименование стройки и/или объекта)
A6: =CONCATENATE( "ЛОКАЛЬНАЯ СМЕТА № ",IF(Source!F12<>"Новый объект", Source!F12, "")) -> ЛОКАЛЬНАЯ СМЕТА № 02-01-21
A8: Спринклерное пожаротушение
A9: (наименование работ и затрат)
A11: =CONCATENATE( "Основание: чертежи № ", Source!J12) -> Основание: чертежи № 2024-00375-01-0-ИОС2.2
I13: В базисном уровне цен | J13: В текущем уровне цен
E14: Сметная стоимость | I14: =I15+I16+I17+I18 -> 754.65 | J14: =J15+J16+J17+J18 -> 15937.04 | K14: тыс.руб.
E15: Строительные работы | I15: =ROUND((Source!F368)/1000, 2) -> 17 | J15: =ROUND((Source!P368)/1000, 2) -> 410.92 | K15: тыс.руб.
E16: Работы по монтажу оборудования | I16: =ROUND((Source!F369)/1000, 2) -> 528.86 | J16: =ROUND((Source!P369)/1000, 2) -> 13945.56 | K16: тыс.руб.
E17: Оборудование | I17: =ROUND((Source!F360)/1000, 2) -> 208.79 | J17: =ROUND((Source!P360)/1000, 2) -> 1580.56 | K17: тыс.руб.
E18: Прочие работы и затраты | I18: =ROUND((Source!F370+Source!F371)/1000, 2) -> 0 | J18: =ROUND((Source!P370+Source!P371)/1000, 2) -> 0 | K18: тыс.руб.
E19: Средства на оплату труда | I19: =(Source!F366+ Source!F365)/1000 -> 79.48296 | J19: =((Source!P366 + Source!P365)/1000) -> 4478.8648 | K19: тыс.руб.
E20: Затраты труда | I20: =Source!F373 -> 6037.8927 | K20: чел.-ч.
E21: Кроме того:
E22: Возврат материалов | I22: =SUM(Y1:Y462)/1000 -> 0 | J22: =SUM(Z1:Z462)/1000 -> 0 | K22: тыс.руб.
A24: Составлен(а) по ТСН-2001 с учетом Дополнения №: 81
A25: № и период сборника коэффициентов (индексов) пересчета: Коэффициенты к ТСН-2001 МГЭ Дополнение 81, ремонт №219/81 I квартал 2026 года и Коэффициенты к ТСН-2001.13-2 Дополнение 47 №64/47 I квартал 2026 года | AP25: № и период сборника коэффициентов (индексов) пересчета: Коэффициенты к ТСН-2001 МГЭ Дополнение 81, ремонт №219/81 I квартал 2026 года и Коэффициенты к ТСН-2001.13-2 Дополнение 47 №64/47 I квартал 2026 года
A26: № п/п | B26: Шифр расценки и коды ресурсов | C26: Наименование работ и затрат | D26: Ед. изм. | E26: Кол-во единиц | F26: Цена на ед. изм., руб. | G26: Попра- вочные коэффи- циенты | H26: Коэффи- циенты зимних удорожа- ний | I26: Всего в ценах на январь 2000 года, руб. | J26: Коэффи- циенты (индек- сы) пере- счета, нормы НР и СП | K26: ВСЕГО затрат в текущем уровне цен, руб.
A27: 1 | B27: 2 | C27: 3 | D27: 4 | E27: 5 | F27: 6 | G27: 7 | H27: 8 | I27: 9 | J27: 10 | K27: 11
A29: =CONCATENATE("Локальная смета: ",IF(Source!G20<>"Новая локальная смета", Source!G20, "")) -> Локальная смета: Спринклерное пожаротушение.
A31: =CONCATENATE("Раздел: ",IF(Source!G24<>"Новый раздел", Source!G24, "")) -> Раздел: Насосная установка.
A32: 1 | B32: =Source!F30 -> 3.18-11-2 | C32: Установка насосов центробежных с электродвигателем массой агрегата до 0,2 т | D32: =Source!H30 -> 1 насос | E32: =Source!I30 -> 1 | Q32: =Source!X30 -> 356.79 | R32: =Source!X31 -> 20105.26 | S32: =Source!Y30 -> 212.31 | T32: =Source!Y31 -> 11963.46 | U32: =ROUND((175/100)*ROUND(Source!R30, 2), 2) -> 4.01 | V32: =ROUND((0/100)*ROUND(Source!R31, 2), 2) -> 0 | AC32: 0
C33: ЗП | F33: =Source!AO30 -> 198.7 | G33: 1,2*1,15 | H33: =Source!AV31 -> 1.067 | I33: =Source!S30 -> 292.58 | J33: =IF(Source!BA31<> 0, Source!BA31, 1) -> 56.35 | K33: =Source!S31 -> 16486.88
C34: ЭМ | F34: =Source!AM30 -> 15.92 | G34: 1,2*1,25 | H34: =Source!AV31 -> 1.067 | I34: =Source!Q30 -> 25.48 | J34: =IF(Source!BB31<> 0, Source!BB31, 1) -> 15.03 | K34: =Source!Q31 -> 382.96
C35: в т.ч. ЗПМ | F35: =Source!AN30 -> 1.43 | G35: 1,2*1,25 | H35: =Source!AV31 -> 1.067 | I35: =Source!R30 -> 2.29 | J35: =IF(Source!BS31<> 0, Source!BS31, 1) -> 56.35 | K35: =Source!R31 -> 129.04
C36: МР | F36: =Source!AL30 -> 172.01 | H36: =Source!AW31 -> 1 | I36: =Source!P30 -> 172.01 | J36: =IF(Source!BC31<> 0, Source!BC31, 1) -> 7.27 | K36: =Source!P31 -> 1250.51
C37: НР от ФОТ | D37: % | E37: =Source!BZ31 -> 121 | I37: =SUM(Q32:Q36) -> 356.79 | J37: =Source!AT31 -> 121 | K37: =SUM(R32:R36) -> 20105.26
C38: СП от ФОТ | D38: % | E38: =Source!CA31 -> 72 | I38: =SUM(S32:S37) -> 212.31 | J38: =Source!AU31 -> 72 | K38: =SUM(T32:T37) -> 11963.46
C39: ЗТР | D39: чел-ч | E39: =Source!AQ30 -> 16.3 | G39: 1,2*1,15 | H39: =Source!AV31 -> 1.067 | I39: =Source!U30 -> 24.001098
C40: ВСЕГО работ по позиции: | H40: =I33+I34+I36+I37+I38+0-0-0 -> 1059.17 | J40: =K33+K34+K36+K37+K38+0-0-0 -> 50189.07
C41: ВСЕГО оборудование по позиции: | H41: =0+0 -> 0 | J41: =0+0 -> 0
C42: ВСЕГО по позиции: | H42: =I33+I34+I36+I37+I38+0 -> 1059.17 | J42: =K33+K34+K36+K37+K38+0 -> 50189.07 | O42: =I33+I34+I36+I37+I38+0 -> 1059.17 | P42: =K33+K34+K36+K37+K38+0 -> 50189.07
A44: 2 | B44: =Source!F34 -> 3.17-10-1 | C44: Установка насосов погружных центробежных фекальных с электродвигателем производительностью 10 м3/час | D44: =Source!H34 -> 1 ШТ. | E44: =Source!I34 -> 1 | Q44: =Source!X34 -> 289.44 | R44: =Source!X35 -> 16310.18 | S44: =Source!Y34 -> 172.23 | T44: =Source!Y35 -> 9705.23 | U44: =ROUND((175/100)*ROUND(Source!R34, 2), 2) -> 0.84 | V44: =ROUND((0/100)*ROUND(Source!R35, 2), 2) -> 0 | AC44: 0
C45: ЗП | F45: =Source!AO34 -> 162.13 | G45: 1,2*1,15 | H45: =Source!AV35 -> 1.067 | I45: =Source!S34 -> 238.73 | J45: =IF(Source!BA35<> 0, Source!BA35, 1) -> 56.35 | K45: =Source!S35 -> 13452.44
C46: ЭМ | F46: =Source!AM34 -> 6.25 | G46: 1,2*1,25 | H46: =Source!AV35 -> 1.067 | I46: =Source!Q34 -> 10 | J46: =IF(Source!BB35<> 0, Source!BB35, 1) -> 14.22 | K46: =Source!Q35 -> 142.2
C47: в т.ч. ЗПМ | F47: =Source!AN34 -> 0.3 | G47: 1,2*1,25 | H47: =Source!AV35 -> 1.067 | I47: =Source!R34 -> 0.48 | J47: =IF(Source!BS35<> 0, Source!BS35, 1) -> 56.35 | K47: =Source!R35 -> 27.05
C48: МР | F48: =Source!AL34 -> 109.65 | H48: =Source!AW35 -> 1 | I48: =Source!P34 -> 109.65 | J48: =IF(Source!BC35<> 0, Source!BC35, 1) -> 7.21 | K48: =Source!P35 -> 790.58
C49: НР от ФОТ | D49: % | E49: =Source!BZ35 -> 121 | I49: =SUM(Q44:Q48) -> 289.44 | J49: =Source!AT35 -> 121 | K49: =SUM(R44:R48) -> 16310.18
C50: СП от ФОТ | D50: % | E50: =Source!CA35 -> 72 | I50: =SUM(S44:S49) -> 172.23 | J50: =Source!AU35 -> 72 | K50: =SUM(T44:T49) -> 9705.23
C51: ЗТР | D51: чел-ч | E51: =Source!AQ34 -> 13.3 | G51: 1,2*1,15 | H51: =Source!AV35 -> 1.067 | I51: =Source!U34 -> 19.583718
C52: ВСЕГО работ по позиции: | H52: =I45+I46+I48+I49+I50+0-0-0 -> 820.05 | J52: =K45+K46+K48+K49+K50+0-0-0 -> 40400.63
C53: ВСЕГО оборудование по позиции: | H53: =0+0 -> 0 | J53: =0+0 -> 0
C54: ВСЕГО по позиции: | H54: =I45+I46+I48+I49+I50+0 -> 820.05 | J54: =K45+K46+K48+K49+K50+0 -> 40400.63 | O54: =I45+I46+I48+I49+I50+0 -> 820.05 | P54: =K45+K46+K48+K49+K50+0 -> 40400.63
A56: 3 | B56: =Source!F42 -> 4.11-17-1 | C56: Монтаж щитов и пультов массой до 50кг | D56: =Source!H42 -> 1 ШТ. | E56: =Source!I42 -> 1 | Q56: =Source!X42 -> 68.04 | R56: =Source!X43 -> 3834.05 | S56: =Source!Y42 -> 34.78 | T56: =Source!Y43 -> 1959.63 | U56: =ROUND((175/100)*ROUND(Source!R42, 2), 2) -> 0.84 | V56: =ROUND((0/100)*ROUND(Source!R43, 2), 2) -> 0 | AC56: 0
C57: ЗП | F57: =Source!AO42 -> 59.79 | G57: 1,2 | H57: =Source!AV43 -> 1.047 | I57: =Source!S42 -> 75.12 | J57: =IF(Source!BA43<> 0, Source!BA43, 1) -> 56.35 | K57: =Source!S43 -> 4233.01
C58: ЭМ | F58: =Source!AM42 -> 4.27 | G58: 1,2 | H58: =Source!AV43 -> 1.047 | I58: =Source!Q42 -> 5.36 | J58: =IF(Source!BB43<> 0, Source!BB43, 1) -> 15.26 | K58: =Source!Q43 -> 81.79
C59: в т.ч. ЗПМ | F59: =Source!AN42 -> 0.38 | G59: 1,2 | H59: =Source!AV43 -> 1.047 | I59: =Source!R42 -> 0.48 | J59: =IF(Source!BS43<> 0, Source!BS43, 1) -> 56.35 | K59: =Source!R43 -> 27.05
C60: МР | F60: =Source!AL42 -> 89.36 | H60: =Source!AW43 -> 1 | I60: =Source!P42 -> 89.36 | J60: =IF(Source!BC43<> 0, Source!BC43, 1) -> 4.5 | K60: =Source!P43 -> 402.12
C61: НР от ФОТ | D61: % | E61: =Source!BZ43 -> 90 | I61: =SUM(Q56:Q60) -> 68.04 | J61: =Source!AT43 -> 90 | K61: =SUM(R56:R60) -> 3834.05
C62: СП от ФОТ | D62: % | E62: =Source!CA43 -> 46 | I62: =SUM(S56:S61) -> 34.78 | J62: =Source!AU43 -> 46 | K62: =SUM(T56:T61) -> 1959.63
C63: ЗТР | D63: чел-ч | E63: =Source!AQ42 -> 5.15 | G63: 1,2 | H63: =Source!AV43 -> 1.047 | I63: =Source!U42 -> 6.47046
C64: ВСЕГО работ по позиции: | H64: =I57+I58+I60+I61+I62+0-0-0 -> 272.66 | J64: =K57+K58+K60+K61+K62+0-0-0 -> 10510.6
C65: ВСЕГО оборудование по позиции: | H65: =0+0 -> 0 | J65: =0+0 -> 0
C66: ВСЕГО по позиции: | H66: =I57+I58+I60+I61+I62+0 -> 272.66 | J66: =K57+K58+K60+K61+K62+0 -> 10510.6 | O66: =I57+I58+I60+I61+I62+0 -> 272.66 | P66: =K57+K58+K60+K61+K62+0 -> 10510.6
A68: 4 | B68: =Source!F44 -> 4.11-3-1 | C68: Установка прибора массой до 5 кг на металлоконструкциях или щитах/ выносная панель ВПИ | D68: =Source!H44 -> 1 ШТ. | E68: =Source!I44 -> 1 | Q68: =Source!X44 -> 7.63 | R68: =Source!X45 -> 430.07 | S68: =Source!Y44 -> 3.9 | T68: =Source!Y45 -> 219.81 | U68: =ROUND((175/100)*ROUND(Source!R44, 2), 2) -> 0 | V68: =ROUND((0/100)*ROUND(Source!R45, 2), 2) -> 0 | AC68: 0
C69: ЗП | F69: =Source!AO44 -> 6.75 | G69: 1,2 | H69: =Source!AV45 -> 1.047 | I69: =Source!S44 -> 8.48 | J69: =IF(Source!BA45<> 0, Source!BA45, 1) -> 56.35 | K69: =Source!S45 -> 477.85
C70: НР от ФОТ | D70: % | E70: =Source!BZ45 -> 90 | I70: =SUM(Q68:Q69) -> 7.63 | J70: =Source!AT45 -> 90 | K70: =SUM(R68:R69) -> 430.07
C71: СП от ФОТ | D71: % | E71: =Source!CA45 -> 46 | I71: =SUM(S68:S70) -> 3.9 | J71: =Source!AU45 -> 46 | K71: =SUM(T68:T70) -> 219.81
C72: ЗТР | D72: чел-ч | E72: =Source!AQ44 -> 0.52 | G72: 1,2 | H72: =Source!AV45 -> 1.047 | I72: =Source!U44 -> 0.653328
C73: ВСЕГО работ по позиции: | H73: =I69+I70+I71+0-0-0 -> 20.01 | J73: =K69+K70+K71+0-0-0 -> 1127.73
C74: ВСЕГО оборудование по позиции: | H74: =0+0 -> 0 | J74: =0+0 -> 0
C75: ВСЕГО по позиции: | H75: =I69+I70+I71+0 -> 20.01 | J75: =K69+K70+K71+0 -> 1127.73 | O75: =I69+I70+I71+0 -> 20.01 | P75: =K69+K70+K71+0 -> 1127.73
A77: 5 | B77: =Source!F54 -> КА. п. 1 | C77: ОБОРУДОВАНИЕ:_x000D_ Насосная установка пожаротушения Q-66,38 (м3/ч), H- 25,0 м.в.ст., Жокей насос Q-3.0 (м3/ч),H- 30,0 м.в.ст., комплектно со шкафом автоматического управления ШУПН-3-С ОН/РН/ЖН-18,5/18,5/1,5-УПП/УПП/П-В и комплектно с выносной панелью индикации ВП 199 171,86 = [1 764 680 / 1,22 / 7,57] + 3% Трансп + 1,2% Заг.скл | D77: =Source!H54 -> компл. | E77: =Source!I54 -> 1 | F77: =Source!AL54 -> 199171.86 | H77: =Source!AW55 -> 1 | I77: =Source!P54 -> 199171.86 | J77: =IF(Source!BC55<> 0, Source!BC55, 1) -> 7.57 | K77: =Source!P55 -> 1507731 | Q77: =Source!X54 -> 0 | R77: =Source!X55 -> 0 | S77: =Source!Y54 -> 0 | T77: =Source!Y55 -> 0 | U77: =ROUND((175/100)*ROUND(Source!R54, 2), 2) -> 0 | V77: =ROUND((0/100)*ROUND(Source!R55, 2), 2) -> 0 | AC77: 5
C78: ВСЕГО по позиции: | H78: =I77+0 -> 199171.86 | J78: =K77+0 -> 1507731 | O78: =I77+0 -> 199171.86 | P78: =K77+0 -> 1507731
A80: 6 | B80: =Source!F56 -> 4.12-50-6 | C80: Монтаж арматуры фланцевой с электрическим приводом на номинальное давление до 4 МПа, номинальный диаметр прохода 100 мм | D80: =Source!H56 -> 1 ШТ. | E80: =Source!I56 -> 1 | Q80: =Source!X56 -> 81.3 | R80: =Source!X57 -> 4581.08 | S80: =Source!Y56 -> 41.55 | T80: =Source!Y57 -> 2341.44 | U80: =ROUND((175/100)*ROUND(Source!R56, 2), 2) -> 2.56 | V80: =ROUND((0/100)*ROUND(Source!R57, 2), 2) -> 0 | AC80: 0
C81: ЗП | F81: =Source!AO56 -> 69.41 | G81: 1,2 | H81: =Source!AV57 -> 1.067 | I81: =Source!S56 -> 88.87 | J81: =IF(Source!BA57<> 0, Source!BA57, 1) -> 56.35 | K81: =Source!S57 -> 5007.82
C82: ЭМ | F82: =Source!AM56 -> 7.48 | G82: 1,2 | H82: =Source!AV57 -> 1.067 | I82: =Source!Q56 -> 9.58 | J82: =IF(Source!BB57<> 0, Source!BB57, 1) -> 17.07 | K82: =Source!Q57 -> 163.53
C83: в т.ч. ЗПМ | F83: =Source!AN56 -> 1.14 | G83: 1,2 | H83: =Source!AV57 -> 1.067 | I83: =Source!R56 -> 1.46 | J83: =IF(Source!BS57<> 0, Source!BS57, 1) -> 56.35 | K83: =Source!R57 -> 82.27
C84: МР | F84: =Source!AL56 -> 3.93 | H84: =Source!AW57 -> 1.028 | I84: =Source!P56 -> 4.04 | J84: =IF(Source!BC57<> 0, Source!BC57, 1) -> 4.49 | K84: =Source!P57 -> 18.14
A85: 6,1 | B85: =Source!F58 -> КА. п. 2 | C85: ОБОРУДОВАНИЕ:_x000D_ Узел управления спринклерный водозаполненный УУ-С100/1,6В-ВФ.О4 Прямоточный-100 7 821,60 = [69 300 / 1,22 / 7,57] + 3% Трансп + 1,2% Заг.скл | D85: =Source!H58 -> шт. | E85: =Source!I58 -> 1 | F85: =Source!AK58 -> 7821.6 | H85: =Source!AW59 -> 1 | I85: =Source!O58 -> 7821.6 | J85: =IF(Source!BC59<> 0, Source!BC59, 1) -> 7.57 | K85: =Source!O59 -> 59209.51 | Q85: =Source!X58 -> 0 | R85: =Source!X59 -> 0 | S85: =Source!Y58 -> 0 | T85: =Source!Y59 -> 0 | U85: =ROUND((175/100)*ROUND(Source!R58, 2), 2) -> 0 | V85: =ROUND((0/100)*ROUND(Source!R59, 2), 2) -> 0 | AC85: 5
C86: НР от ФОТ | D86: % | E86: =Source!BZ57 -> 90 | I86: =SUM(Q80:Q85) -> 81.3 | J86: =Source!AT57 -> 90 | K86: =SUM(R80:R85) -> 4581.08
C87: СП от ФОТ | D87: % | E87: =Source!CA57 -> 46 | I87: =SUM(S80:S86) -> 41.55 | J87: =Source!AU57 -> 46 | K87: =SUM(T80:T86) -> 2341.44
C88: ЗТР | D88: чел-ч | E88: =Source!AQ56 -> 5.5 | G88: 1,2 | H88: =Source!AV57 -> 1.067 | I88: =Source!U56 -> 7.0422
C89: ВСЕГО работ по позиции: | H89: =I81+I82+I84+I86+I87+SUM(I85:I85)-SUMIF(AC85:AC85, 5, I85:I85)-SUMIF(AC85:AC85, 6, I85:I85) -> 225.34 | J89: =K81+K82+K84+K86+K87+SUM(K85:K85)-SUMIF(AC85:AC85, 5, K85:K85)-SUMIF(AC85:AC85, 6, K85:K85) -> 12112.01
C90: ВСЕГО оборудование по позиции: | H90: =SUMIF(AC85:AC85, 5, I85:I85)+SUMIF(AC85:AC85, 6, I85:I85) -> 7821.6 | J90: =SUMIF(AC85:AC85, 5, K85:K85)+SUMIF(AC85:AC85, 6, K85:K85) -> 59209.51
C91: ВСЕГО по позиции: | H91: =I81+I82+I84+I86+I87+SUM(I85:I85) -> 8046.94 | J91: =K81+K82+K84+K86+K87+SUM(K85:K85) -> 71321.52 | O91: =I81+I82+I84+I86+I87+SUM(I85:I85) -> 8046.94 | P91: =K81+K82+K84+K86+K87+SUM(K85:K85) -> 71321.52
A93: 7 | B93: =Source!F60 -> 4.12-48-10 | C93: Монтаж арматуры фланцевой с ручным приводом или без привода на номинальное давление до 4 МПа, номинальный диаметр прохода 100 мм | D93: =Source!H60 -> 1 ШТ. | E93: =Source!I60 -> 9 | Q93: =Source!X60 -> 540.55 | R93: =Source!X61 -> 30459.93 | S93: =Source!Y60 -> 276.28 | T93: =Source!Y61 -> 15568.41 | U93: =ROUND((175/100)*ROUND(Source!R60, 2), 2) -> 7.67 | V93: =ROUND((0/100)*ROUND(Source!R61, 2), 2) -> 0 | AC93: 0
C94: ЗП | F94: =Source!AO60 -> 51.74 | G94: 1,2 | H94: =Source!AV61 -> 1.067 | I94: =Source!S60 -> 596.23 | J94: =IF(Source!BA61<> 0, Source!BA61, 1) -> 56.35 | K94: =Source!S61 -> 33597.56
C95: ЭМ | F95: =Source!AM60 -> 2.49 | G95: 1,2 | H95: =Source!AV61 -> 1.067 | I95: =Source!Q60 -> 28.69 | J95: =IF(Source!BB61<> 0, Source!BB61, 1) -> 17.09 | K95: =Source!Q61 -> 490.31
C96: в т.ч. ЗПМ | F96: =Source!AN60 -> 0.38 | G96: 1,2 | H96: =Source!AV61 -> 1.067 | I96: =Source!R60 -> 4.38 | J96: =IF(Source!BS61<> 0, Source!BS61, 1) -> 56.35 | K96: =Source!R61 -> 246.81
C97: МР | F97: =Source!AL60 -> 3.93 | H97: =Source!AW61 -> 1.028 | I97: =Source!P60 -> 36.36 | J97: =IF(Source!BC61<> 0, Source!BC61, 1) -> 4.49 | K97: =Source!P61 -> 163.26
A98: 7,1 | B98: =Source!F62 -> 1.13-5-40 | C98: Затвор дисковый, поворотный, корпус из чугуна, диск из нержавеющей стали, с ручкой, номинальное давление PN 1,6 МПа, номинальный диаметр DN 100 мм | D98: =Source!H62 -> шт. | E98: =Source!I62 -> 9 | F98: =Source!AK62 -> 2177.93 | H98: =Source!AW63 -> 1 | I98: =Source!O62 -> 19601.37 | J98: =IF(Source!BC63<> 0, Source!BC63, 1) -> 3.11 | K98: =Source!O63 -> 60960.26 | Q98: =Source!X62 -> 0 | R98: =Source!X63 -> 0 | S98: =Source!Y62 -> 0 | T98: =Source!Y63 -> 0 | U98: =ROUND((175/100)*ROUND(Source!R62, 2), 2) -> 0 | V98: =ROUND((0/100)*ROUND(Source!R63, 2), 2) -> 0 | AC98: 3
C99: НР от ФОТ | D99: % | E99: =Source!BZ61 -> 90 | I99: =SUM(Q93:Q98) -> 540.55 | J99: =Source!AT61 -> 90 | K99: =SUM(R93:R98) -> 30459.93
C100: СП от ФОТ | D100: % | E100: =Source!CA61 -> 46 | I100: =SUM(S93:S99) -> 276.28 | J100: =Source!AU61 -> 46 | K100: =SUM(T93:T99) -> 15568.41
C101: ЗТР | D101: чел-ч | E101: =Source!AQ60 -> 4.1 | G101: 1,2 | H101: =Source!AV61 -> 1.067 | I101: =Source!U60 -> 47.24676
C102: ВСЕГО работ по позиции: | H102: =I94+I95+I97+I99+I100+SUM(I98:I98)-SUMIF(AC98:AC98, 5, I98:I98)-SUMIF(AC98:AC98, 6, I98:I98) -> 21079.48 | J102: =K94+K95+K97+K99+K100+SUM(K98:K98)-SUMIF(AC98:AC98, 5, K98:K98)-SUMIF(AC98:AC98, 6, K98:K98) -> 141239.73
C103: ВСЕГО оборудование по позиции: | H103: =SUMIF(AC98:AC98, 5, I98:I98)+SUMIF(AC98:AC98, 6, I98:I98) -> 0 | J103: =SUMIF(AC98:AC98, 5, K98:K98)+SUMIF(AC98:AC98, 6, K98:K98) -> 0
C104: ВСЕГО по позиции: | H104: =I94+I95+I97+I99+I100+SUM(I98:I98) -> 21079.48 | J104: =K94+K95+K97+K99+K100+SUM(K98:K98) -> 141239.73 | O104: =I94+I95+I97+I99+I100+SUM(I98:I98) -> 21079.48 | P104: =K94+K95+K97+K99+K100+SUM(K98:K98) -> 141239.73
A106: 8 | B106: =Source!F64 -> 1.12-9-21 | C106: Фланец стальной плоский приварной с соединительным выступом, ГОСТ 33259-2015, из стали Ст3сп, номинальное давление PN 1,6 МПа, номинальный диаметр DN 100 мм | D106: =Source!H64 -> шт. | E106: =Source!I64 -> 10 | F106: =Source!AL64 -> 107.23 | H106: =Source!AW65 -> 1 | I106: =Source!P64 -> 1072.3 | J106: =IF(Source!BC65<> 0, Source!BC65, 1) -> 6.94 | K106: =Source!P65 -> 7441.76 | Q106: =Source!X64 -> 0 | R106: =Source!X65 -> 0 | S106: =Source!Y64 -> 0 | T106: =Source!Y65 -> 0 | U106: =ROUND((175/100)*ROUND(Source!R64, 2), 2) -> 0 | V106: =ROUND((0/100)*ROUND(Source!R65, 2), 2) -> 0 | AC106: 3
C107: ВСЕГО по позиции: | H107: =I106+0 -> 1072.3 | J107: =K106+0 -> 7441.76 | O107: =I106+0 -> 1072.3 | P107: =K106+0 -> 7441.76
A109: 9 | B109: =Source!F66 -> 4.12-48-9 | C109: Монтаж арматуры фланцевой с ручным приводом или без привода на номинальное давление до 4 МПа, номинальный диаметр прохода 80 мм | D109: =Source!H66 -> 1 ШТ. | E109: =Source!I66 -> 8 | Q109: =Source!X66 -> 467.68 | R109: =Source!X67 -> 26353.55 | S109: =Source!Y66 -> 239.03 | T109: =Source!Y67 -> 13469.59 | U109: =ROUND((175/100)*ROUND(Source!R66, 2), 2) -> 4.48 | V109: =ROUND((0/100)*ROUND(Source!R67, 2), 2) -> 0 | AC109: 0
C110: ="Объем: "&Source!I66&"=4+"&"4" -> Объем: 8=4+4
C111: ЗП | F111: =Source!AO66 -> 50.48 | G111: 1,2 | H111: =Source!AV67 -> 1.067 | I111: =Source!S66 -> 517.08 | J111: =IF(Source!BA67<> 0, Source!BA67, 1) -> 56.35 | K111: =Source!S67 -> 29137.46
C112: ЭМ | F112: =Source!AM66 -> 1.66 | G112: 1,2 | H112: =Source!AV67 -> 1.067 | I112: =Source!Q66 -> 17 | J112: =IF(Source!BB67<> 0, Source!BB67, 1) -> 17.09 | K112: =Source!Q67 -> 290.53
C113: в т.ч. ЗПМ | F113: =Source!AN66 -> 0.25 | G113: 1,2 | H113: =Source!AV67 -> 1.067 | I113: =Source!R66 -> 2.56 | J113: =IF(Source!BS67<> 0, Source!BS67, 1) -> 56.35 | K113: =Source!R67 -> 144.26
C114: МР | F114: =Source!AL66 -> 2.77 | H114: =Source!AW67 -> 1.028 | I114: =Source!P66 -> 22.78 | J114: =IF(Source!BC67<> 0, Source!BC67, 1) -> 4.5 | K114: =Source!P67 -> 102.51
A115: 9,1 | B115: =Source!F68 -> 1.13-3-109 | C115: Клапан обратный, чугунный, фланцевый, температура рабочей среды от -10 до +100°С, условная пропускная способность 222 м3/ч, номинальное давление РN 1,6 МПа, номинальный диаметр DN 80 мм | D115: =Source!H68 -> шт. | E115: =Source!I68 -> 4 | F115: =Source!AK68 -> 3030.49 | H115: =Source!AW69 -> 1 | I115: =Source!O68 -> 12121.96 | J115: =IF(Source!BC69<> 0, Source!BC69, 1) -> 6.25 | K115: =Source!O69 -> 75762.25 | Q115: =Source!X68 -> 0 | R115: =Source!X69 -> 0 | S115: =Source!Y68 -> 0 | T115: =Source!Y69 -> 0 | U115: =ROUND((175/100)*ROUND(Source!R68, 2), 2) -> 0 | V115: =ROUND((0/100)*ROUND(Source!R69, 2), 2) -> 0 | AC115: 3
...

Sheet Source
A1: 0 | B1: Smeta.RU (495) 974-1589 | D1: _PS_ | F1: 0 | G1: 0 | H1: 0 | I1: Smeta.RU | K1: 1 | L1: 74598 | M1: 10 | N1: 12 | O1: 1 | P1: 0 | Q1: 5
A4: 1 | B4: 1 | C4: -1 | G4: Капитальный ремонт здания Государственного бюджетного общеобразовательного учреждения города Москвы «Школа №1574» по адресу: г. Москва, Старопименовский пер., д. №5 | EC4: 0
A5: 8 | B5: 1 | C5: -1 | G5: Капитальный ремонт здания Государственного бюджетного общеобразовательного учреждения города Москвы «Школа №1574» по адресу: г. Москва, Старопименовский пер., д. №5 | EC5: 0
A12: 1 | B12: 393 | C12: 0 | D12: =ROW(A351) -> 351 | E12: 0 | F12: 02-01-21 | G12: 02-01-21 Спринклерное пожаротушение | I12: 0 | J12: 2024-00375-01-0-ИОС2.2 | K12: 0 | L12: 0 | M12: 4098 | O12: 0 | P12: 0 | Q12: 0 | R12: 0 | S12: 0 | T12: 1 | V12: 2 | AB12: Гришечкина О.А. | AC12: Ведущий инженер-сметчик | AD12: Феденко И.В. | AE12: Руководитель сметного отдела | BB12: 0 | BH12: Сметные нормы списания | BI12: Коды ОКП для ТСН-2001 МГЭ Дополнение 81 | BJ12: 1 | BK12: 1 | BL12: 0 | BM12: 0 | BN12: 1 | BO12: 0 | BP12: 6 | BQ12: 2 | BR12: 1 | BS12: 1 | BT12: 0 | BU12: 0 | BV12: 0 | BW12: 0 | BX12: 0 | BY12: ТСН-2001 (МГЭ) Доп 81 - Новое строительство | BZ12: Типовой расчет для ТСН-2001 МГЭ, Дополнение 81, строительство | CA12: Территориальные сметные нормативы для Москвы ТСН-2001 (МГЭ), дополнение 81 | CB12: Территориальные сметные нормативы для Москвы ТСН-2001 (МГЭ), дополнение 81 | CC12: Территориальные сметные нормативы для Москвы ТСН-2001 (МГЭ), дополнение 81 | CD12: Территориальные сметные нормативы для Москвы ТСН-2001 (МГЭ), дополнение 81 | CE12: Поправки для ТСН-2001 от 07.04.2026 г. доп.81 | CF12: 0 | CG12: 0 | CH12: 8200 | CK12: 82 | CQ12: Территориальные сметные нормативы для Москвы (ТСН-2001) | CR12: ТЕР | CS12: 41660 | CT12: 1 | CU12: 81 | CY12: 0 | EC12: 0
A15: 15 | B15: 1
A18: 52 | B18: =B351 -> 393 | C18: =C351 -> 1 | D18: =D351 -> 12 | E18: =E351 -> 0 | F18: =F351 -> 02-01-21 | G18: =G351 -> 02-01-21 Спринклерное пожаротушение | O18: =O351 -> 645901.78 | P18: =P351 -> 549189.04 | Q18: =Q351 -> 21097.16 | R18: =R351 -> 3867.38 | S18: =S351 -> 75615.58 | T18: =T351 -> 0 | U18: =U351 -> 6037.8927 | V18: =V351 -> 0 | ... GX18: =GX351 -> 0
A20: 3 | B20: 1 | D20: =ROW(A318) -> 318 | F20: 02-01-21 | G20: Спринклерное пожаротушение. | I20: 0 | J20: 2024-00375-01-0-ИОС2.2 | K20: -1 | L20: 02-01-21 | S20: 0 | T20: 0 | V20: 2 | AB20: Гришечкина О.А. | AC20: Ведущий инженер-сметчик | AD20: Феденко И.В. | AE20: Руководитель сметного отдела | BX20: 0 | CF20: 0 | CG20: 0
A22: 52 | B22: =B318 -> 1 | C22: =C318 -> 3 | D22: =D318 -> 20 | E22: =E318 -> 0 | F22: =F318 -> 02-01-21 | G22: =G318 -> Спринклерное пожаротушение. | O22: =O318 -> 645901.78 | P22: =P318 -> 549189.04 | Q22: =Q318 -> 21097.16 | R22: =R318 -> 3867.38 | S22: =S318 -> 75615.58 | T22: =T318 -> 0 | U22: =U318 -> 6037.8927 | V22: =V318 -> 0 | ... GX22: =GX318 -> 0
A24: 4 | B24: 1 | D24: =ROW(A167) -> 167 | F24: Новый раздел | G24: Насосная установка. | I24: 0 | K24: 0 | S24: 0 | T24: 0 | V24: 2 | BX24: 0 | CJ24: 0
A26: 52 | B26: =B167 -> 1 | C26: =C167 -> 4 | D26: =D167 -> 24 | E26: =E167 -> 0 | F26: =F167 -> Новый раздел | G26: =G167 -> Насосная установка. | O26: =O167 -> 278528.64 | P26: =P167 -> 270042.49 | Q26: =Q167 -> 1757.79 | R26: =R167 -> 297.02 | S26: =S167 -> 6728.36 | T26: =T167 -> 0 | U26: =U167 -> 531.97169 | V26: =V167 -> 0 | ... GX26: =GX167 -> 0
A28: 17 | B28: 1 | C28: =ROW(SmtRes!A10) -> 10 | D28: =ROW(EtalonRes!A11) -> 11 | F28: 4.7-21-3 | G28: Монтаж насосного агрегата лопастного центробежного одноступенчатого, многоступенчатого объемного, вихревого, поршневого, приводного, роторного на общей фундаментной плите или моноблочный массой 0,425 т | H28: 1 ШТ. | I28: 2 | J28: 0 | K28: 2 | O28: =ROUND(CP28,2) -> 908.21 | P28: =ROUND((ROUND((AC28*AW28*I28),2)*BC28),2) -> 70.21 | Q28: =(ROUND((ROUND(((((ET28*0.75)*1.2))*AV28*I28),2)*BB28),2)+ROUND((ROUND(((AE28-(((EU28*0.75)*1.2)))*AV28*I28),2)*BS28),2)) -> 80.82 | R28: =(ROUND((ROUND(((((EU28*0.75)*1.2))*AV28*I28),2)*BS28),2)+ROUND((ROUND(((AE28-(((EU28*0.75)*1.2)))*AV28*I28),2)*BS28),2)) -> 5.57 | S28: =ROUND((ROUND((AF28*AV28*I28),2)*BA28),2) -> 757.18 | T28: =ROUND(CU28*I28,2) -> 0 | U28: =CV28*I28 -> 61.4592 | V28: =CW28*I28 -> 0 | W28: =ROUND(CX28*I28,2) -> 0 | X28: =(ROUND((((S28+ROUND((ROUND(((((EU28*0.75)*1.2))*AV28*I28),2)*BS28),2))*AT28)/100),2)+ROUND(((ROUND((ROUND(((AE28-(((EU28*0.75)*1.2)))*AV28*I28),2)*BS28),2)*AT28)/100),2)) -> 694.1 | Y28: =(ROUND((((S28+ROUND((ROUND(((((EU28*0.75)*1.2))*AV28*I28),2)*BS28),2))*AU28)/100),2)+ROUND(((ROUND((ROUND(((AE28-(((EU28*0.75)*1.2)))*AV28*I28),2)*BS28),2)*AU28)/100),2)) -> 358.49 | AA28: -1 | AB28: =ROUND((AC28+AD28+AF28),6) -> 426.8355 | AC28: =ROUND((((ES28*0.75)*1)),6) -> 34.1475 | AD28: =ROUND((((((ET28*0.75)*1.2))-(((EU28*0.75)*1.2)))+AE28),6) -> 37.872 | AE28: =ROUND((((EU28*0.75)*1.2)),6) -> 2.61 | AF28: =ROUND((((EV28*0.75)*1.2)),6) -> 354.816 | AG28: =ROUND((AP28),6) -> 0 | AH28: =(((EW28*0.75)*1.2)) -> 28.8 | AI28: =(((EX28*0.75)*1.2)) -> 0 | AJ28: =(AS28) -> 0 | AK28: 481.85 | AL28: 45.53 | AM28: 42.08 | AN28: 2.9 | AO28: 394.24 | AP28: 0 | AQ28: 32 | AR28: 0 | AS28: 0 | AT28: 91 | AU28: 47 | AV28: 1.067 | AW28: 1.028 | AZ28: 1 | BA28: 1 | BB28: 1 | BC28: 1 | BH28: 0 | BI28: 2 | BJ28: ТСН-2001.4 Доп. 80, Сб. 7, т. 21, поз. 3 | BM28: 66 | BN28: 0 | BO28: 4.7-21-3 | BP28: 1 | BQ28: 40 | BR28: 0 | BS28: 1 | BT28: 1 | BU28: 1 | BV28: 1 | BW28: 1 | BX28: 1 | BZ28: 91 | CA28: 47 | CE28: 1566 | CF28: 0 | CG28: 0 | CM28: 0 | CN28: Поправка: Гл.4.Прил.2.2.п.2.2.17_04.00.01.24.001 Наименование: При разнице в массе оборудования более 10% к норме и расценке ближайшего по массе оборудования при коэффициенте изменения массы оборудования до 0,5 т Поправка: Гл.12.Прил.8.п.8. 3_12.00.01.11.001 Наименование: При наличии напряженных и стесненных условий производства работ (стесненность, сложность складирования и транспортной логистики и т.п.) для объектов, расположенных в пределах круговой магистральной системы улиц "Садовое кольцо" города Москвы | CO28: 0 | CP28: =(P28+Q28+S28) -> 908.21 | CQ28: =ROUND((ROUND((AC28*AW28*1),2)*BC28),2) -> 35.1 | CR28: =(ROUND((ROUND(((((ET28*0.75)*1.2))*AV28*1),2)*BB28),2)+ROUND((ROUND(((AE28-(((EU28*0.75)*1.2)))*AV28*1),2)*BS28),2)) -> 40.41 | CS28: =(ROUND((ROUND(((((EU28*0.75)*1.2))*AV28*1),2)*BS28),2)+ROUND((ROUND(((AE28-(((EU28*0.75)*1.2)))*AV28*1),2)*BS28),2)) -> 2.78 | CT28: =ROUND((ROUND((AF28*AV28*1),2)*BA28),2) -> 378.59 | CU28: =AG28 -> 0 | CV28: =(AH28*AV28) -> 30.7296 | CW28: =AI28 -> 0 | CX28: =AJ28 -> 0 | CY28: =(ROUND((((S28+ROUND((ROUND(((((EU28*0.75)*1.2))*AV28*1),2)*BS28),2))*AT28)/100),2)+ROUND(((ROUND((ROUND(((AE28-(((EU28*0.75)*1.2)))*AV28*1),2)*BS28),2)*AT28)/100),2)) -> 691.56 | CZ28: =(ROUND((((S28+ROUND((ROUND(((((EU28*0.75)*1.2))*AV28*1),2)*BS28),2))*AU28)/100),2)+ROUND(((ROUND((ROUND(((AE28-(((EU28*0.75)*1.2)))*AV28*1),2)*BS28),2)*AU28)/100),2)) -> 357.18 | DB28: 1 | DD28: *0,75)*1 | DE28: *0,75)*1,2 | DF28: *0,75)*1,2 | DG28: *0,75)*1,2 | DI28: *0,75)*1,2 | DJ28: *0,75)*1,2 | DN28: 0 | DO28: 0 | DP28: 1 | DQ28: 1 | DU28: 1013 | DV28: 1 ШТ. | DW28: 1 ШТ. | DX28: 1 | EE28: 56938733 | EF28: 40 | EG28: Монтаж оборудования | EH28: 0 | EJ28: 2 | EK28: 66 | EL28: ТСН-2001.4-7. Компрессорные машины, насосы, вентиляторы | EM28: ТСН-2001.4-7-1 | EO28: Поправка: Гл.4.Прил.2.2.п.2.2.17_04.00.01.24.001 Поправка: Гл.12.Прил.8.п.8. 3_12.00.01.11.001 | EQ28: 132096 | ER28: 481.85 | ES28: 45.53 | ET28: 42.08 | EU28: 2.9 | EV28: 394.24 | EW28: 32 | EX28: 0 | EY28: 0 | FQ28: 0 | FR28: 0 | FS28: 2 | FX28: 91 | FY28: 47 | GD28: 1 | GF28: 2029985936 | GG28: 2 | GH28: 1 | GI28: 2 | GJ28: 0 | GK28: 0 | GL28: =ROUND(IF(AND(BH28=3,BI28=3,FS28<>0),P28,0),2) -> 0 | GM28: =ROUND(O28+X28+Y28,2)+GX28 -> 1960.8 | GN28: =IF(OR(BI28=0,BI28=1),GM28-GX28,0) -> 0 | GO28: =IF(BI28=2,GM28-GX28,0) -> 1960.8 | GP28: =IF(BI28=4,GM28-GX28,0) -> 0 | GR28: 0 | GS28: 3 | GT28: 0 | GV28: =ROUND((GT28),6) -> 0 | GW28: 1 | GX28: =ROUND(HC28*I28,2) -> 0 | HA28: 0 | HB28: 0 | HC28: =GV28*GW28 -> 0 | HS28: 0 | IK28: 0
A29: 17 | B29: 1 | C29: =ROW(SmtRes!A20) -> 20 | D29: =ROW(EtalonRes!A22) -> 22 | F29: 4.7-21-3 | G29: Монтаж насосного агрегата лопастного центробежного одноступенчатого, многоступенчатого объемного, вихревого, поршневого, приводного, роторного на общей фундаментной плите или моноблочный массой 0,425 т | H29: 1 ШТ. | I29: 2 | J29: 0 | K29: 2 | O29: =ROUND(CP29,2) -> 44699.5 | P29: =ROUND((ROUND((AC29*AW29*I29),2)*BC29),2) -> 841.12 | Q29: =(ROUND((ROUND(((((ET29*0.75)*1.2))*AV29*I29),2)*BB29),2)+ROUND((ROUND(((AE29-(((EU29*0.75)*1.2)))*AV29*I29),2)*BS29),2)) -> 1191.29 | R29: =(ROUND((ROUND(((((EU29*0.75)*1.2))*AV29*I29),2)*BS29),2)+ROUND((ROUND(((AE29-(((EU29*0.75)*1.2)))*AV29*I29),2)*BS29),2)) -> 313.87 | S29: =ROUND((ROUND((AF29*AV29*I29),2)*BA29),2) -> 42667.09 | T29: =ROUND(CU29*I29,2) -> 0 | U29: =CV29*I29 -> 61.4592 | V29: =CW29*I29 -> 0 | W29: =ROUND(CX29*I29,2) -> 0 | X29: =(ROUND((((S29+ROUND((ROUND(((((EU29*0.75)*1.2))*AV29*I29),2)*BS29),2))*AT29)/100),2)+ROUND(((ROUND((ROUND(((AE29-(((EU29*0.75)*1.2)))*AV29*I29),2)*BS29),2)*AT29)/100),2)) -> 39112.67 | Y29: =(ROUND((((S29+ROUND((ROUND(((((EU29*0.75)*1.2))*AV29*I29),2)*BS29),2))*AU29)/100),2)+ROUND(((ROUND((ROUND(((AE29-(((EU29*0.75)*1.2)))*AV29*I29),2)*BS29),2)*AU29)/100),2)) -> 20201.05 | AA29: -1 | AB29: =ROUND((AC29+AD29+AF29),6) -> 426.8355 | AC29: =ROUND((((ES29*0.75)*1)),6) -> 34.1475 | AD29: =ROUND((((((ET29*0.75)*1.2))-(((EU29*0.75)*1.2)))+AE29),6) -> 37.872 | AE29: =ROUND((((EU29*0.75)*1.2)),6) -> 2.61 | AF29: =ROUND((((EV29*0.75)*1.2)),6) -> 354.816 | AG29: =ROUND((AP29),6) -> 0 | AH29: =(((EW29*0.75)*1.2)) -> 28.8 | AI29: =(((EX29*0.75)*1.2)) -> 0 | AJ29: =(AS29) -> 0 | AK29: 481.85 | AL29: 45.53 | AM29: 42.08 | AN29: 2.9 | AO29: 394.24 | AP29: 0 | AQ29: 32 | AR29: 0 | AS29: 0 | AT29: 91 | AU29: 47 | AV29: 1.067 | AW29: 1.028 | AZ29: 1 | BA29: 56.35 | BB29: 14.74 | BC29: 11.98 | BH29: 0 | BI29: 2 | BJ29: ТСН-2001.4 Доп. 80, Сб. 7, т. 21, поз. 3 | BM29: 66 | BN29: 0 | BO29: 4.7-21-3 | BP29: 1 | BQ29: 40 | BR29: 0 | BS29: 56.35 | BT29: 1 | BU29: 1 | BV29: 1 | BW29: 1 | BX29: 1 | BZ29: 91 | CA29: 47 | CE29: 1566 | CF29: 0 | CG29: 0 | CM29: 0 | CN29: Поправка: Гл.4.Прил.2.2.п.2.2.17_04.00.01.24.001 Наименование: При разнице в массе оборудования более 10% к норме и расценке ближайшего по массе оборудования при коэффициенте изменения массы оборудования до 0,5 т Поправка: Гл.12.Прил.8.п.8. 3_12.00.01.11.001 Наименование: При наличии напряженных и стесненных условий производства работ (стесненность, сложность складирования и транспортной логистики и т.п.) для объектов, расположенных в пределах круговой магистральной системы улиц "Садовое кольцо" города Москвы | CO29: 0 | CP29: =(P29+Q29+S29) -> 44699.5 | CQ29: =ROUND((ROUND((AC29*AW29*1),2)*BC29),2) -> 420.5 | CR29: =(ROUND((ROUND(((((ET29*0.75)*1.2))*AV29*1),2)*BB29),2)+ROUND((ROUND(((AE29-(((EU29*0.75)*1.2)))*AV29*1),2)*BS29),2)) -> 595.64 | CS29: =(ROUND((ROUND(((((EU29*0.75)*1.2))*AV29*1),2)*BS29),2)+ROUND((ROUND(((AE29-(((EU29*0.75)*1.2)))*AV29*1),2)*BS29),2)) -> 156.65 | CT29: =ROUND((ROUND((AF29*AV29*1),2)*BA29),2) -> 21333.55 | CU29: =AG29 -> 0 | CV29: =(AH29*AV29) -> 30.7296 | CW29: =AI29 -> 0 | CX29: =AJ29 -> 0 | CY29: =(ROUND((((S29+ROUND((ROUND(((((EU29*0.75)*1.2))*AV29*1),2)*BS29),2))*AT29)/100),2)+ROUND(((ROUND((ROUND(((AE29-(((EU29*0.75)*1.2)))*AV29*1),2)*BS29),2)*AT29)/100),2)) -> 38969.6 | CZ29: =(ROUND((((S29+ROUND((ROUND(((((EU29*0.75)*1.2))*AV29*1),2)*BS29),2))*AU29)/100),2)+ROUND(((ROUND((ROUND(((AE29-(((EU29*0.75)*1.2)))*AV29*1),2)*BS29),2)*AU29)/100),2)) -> 20127.16 | DB29: 3 | DD29: *0,75)*1 | DE29: *0,75)*1,2 | DF29: *0,75)*1,2 | DG29: *0,75)*1,2 | DI29: *0,75)*1,2 | DJ29: *0,75)*1,2 | DN29: 0 | DO29: 0 | DP29: 1 | DQ29: 1 | DU29: 1013 | DV29: 1 ШТ. | DW29: 1 ШТ. | DX29: 1 | EE29: 56938733 | EF29: 40 | EG29: Монтаж оборудования | EH29: 0 | EJ29: 2 | EK29: 66 | EL29: ТСН-2001.4-7. Компрессорные машины, насосы, вентиляторы | EM29: ТСН-2001.4-7-1 | EO29: Поправка: Гл.4.Прил.2.2.п.2.2.17_04.00.01.24.001 Поправка: Гл.12.Прил.8.п.8. 3_12.00.01.11.001 | EQ29: 132096 | ER29: 481.85 | ES29: 45.53 | ET29: 42.08 | EU29: 2.9 | EV29: 394.24 | EW29: 32 | EX29: 0 | EY29: 0 | FQ29: 0 | FR29: 0 | FS29: 2 | FX29: 91 | FY29: 47 | GD29: 1 | GF29: 2029985936 | GG29: 2 | GH29: 1 | GI29: 2 | GJ29: 0 | GK29: 0 | GL29: =ROUND(IF(AND(BH29=3,BI29=3,FS29<>0),P29,0),2) -> 0 | GM29: =ROUND(O29+X29+Y29,2)+GX29 -> 104013.22 | GN29: =IF(OR(BI29=0,BI29=1),GM29-GX29,0) -> 0 | GO29: =IF(BI29=2,GM29-GX29,0) -> 104013.22 | GP29: =IF(BI29=4,GM29-GX29,0) -> 0 | GR29: 0 | GS29: 3 | GT29: 0 | GV29: =ROUND((GT29),6) -> 0 | GW29: 1 | GX29: =ROUND(HC29*I29,2) -> 0 | HA29: 0 | HB29: 0 | HC29: =GV29*GW29 -> 0 | HS29: 0 | IK29: 0
A30: 17 | B30: 1 | C30: =ROW(SmtRes!A29) -> 29 | D30: =ROW(EtalonRes!A34) -> 34 | E30: 1 | F30: 3.18-11-2 | G30: Установка насосов центробежных с электродвигателем массой агрегата до 0,2 т | H30: 1 насос | I30: 1 | J30: 0 | K30: 1 | O30: =ROUND(CP30,2) -> 490.07 | P30: =ROUND((ROUND((AC30*AW30*I30),2)*BC30),2) -> 172.01 | Q30: =(ROUND((ROUND(((((ET30*1.2)*1.25))*AV30*I30),2)*BB30),2)+ROUND((ROUND(((AE30-(((EU30*1.2)*1.25)))*AV30*I30),2)*BS30),2)) -> 25.48 | R30: =(ROUND((ROUND(((((EU30*1.2)*1.25))*AV30*I30),2)*BS30),2)+ROUND((ROUND(((AE30-(((EU30*1.2)*1.25)))*AV30*I30),2)*BS30),2)) -> 2.29 | S30: =ROUND((ROUND((AF30*AV30*I30),2)*BA30),2) -> 292.58 | T30: =ROUND(CU30*I30,2) -> 0 | U30: =CV30*I30 -> 24.001098 | V30: =CW30*I30 -> 0 | W30: =ROUND(CX30*I30,2) -> 0 | X30: =(ROUND((((S30+ROUND((ROUND(((((EU30*1.2)*1.25))*AV30*I30),2)*BS30),2))*AT30)/100),2)+ROUND(((ROUND((ROUND(((AE30-(((EU30*1.2)*1.25)))*AV30*I30),2)*BS30),2)*AT30)/100),2)) -> 356.79 | Y30: =(ROUND((((S30+ROUND((ROUND(((((EU30*1.2)*1.25))*AV30*I30),2)*BS30),2))*AU30)/100),2)+ROUND(((ROUND((ROUND(((AE30-(((EU30*1.2)*1.25)))*AV30*I30),2)*BS30),2)*AU30)/100),2)) -> 212.31 | AA30: 55747649 | AB30: =ROUND((AC30+AD30+AF30),6) -> 470.096 | AC30: =ROUND((((ES30*1)*1)),6) -> 172.01 | AD30: =ROUND((((((ET30*1.2)*1.25))-(((EU30*1.2)*1.25)))+AE30),6) -> 23.88 | AE30: =ROUND((((EU30*1.2)*1.25)),6) -> 2.145 | AF30: =ROUND((((EV30*1.2)*1.15)),6) -> 274.206 | AG30: =ROUND((AP30),6) -> 0 | AH30: =(((EW30*1.2)*1.15)) -> 22.494 | AI30: =(((EX30*1.2)*1.25)) -> 0 | AJ30: =(AS30) -> 0 | AK30: 386.63 | AL30: 172.01 | AM30: 15.92 | AN30: 1.43 | AO30: 198.7 | AP30: 0 | AQ30: 16.3 | AR30: 0 | AS30: 0 | AT30: 121 | AU30: 72 | AV30: 1.067 | AW30: 1 | AZ30: 1 | BA30: 1 | BB30: 1 | BC30: 1 | BH30: 0 | BI30: 1 | BJ30: ТСН-2001.3 Доп. 79, Сб. 18, т. 11, поз. 2 | BM30: 23 | BN30: 0 | BO30: 3.18-11-2 | BP30: 1 | BQ30: 30 | BR30: 0 | BS30: 1 | BT30: 1 | BU30: 1 | BV30: 1 | BW30: 1 | BX30: 1 | BZ30: 121 | CA30: 72 | CE30: 1566 | CF30: 0 | CG30: 0 | CM30: 0 | CN30: Поправка: Гл.12.Прил.8.п.8. 3_12.00.01.11.001 Наименование: При наличии напряженных и стесненных условий производства работ (стесненность, сложность складирования и транспортной логистики и т.п.) для объектов, расположенных в пределах круговой магистральной системы улиц "Садовое кольцо" города Москвы Поправка: Гл.6.Прил.2.2.п.2.2.6_06.00.01.07.001 Наименование: При выполнении при капитальном ремонте и реконструкции работ, аналогичных технологическим процессам, характерным для нового строительства, и отсутствующих в сборниках на ремонтно-строительные работы ТСН-2001.6 | CO30: 0 | CP30: =(P30+Q30+S30) -> 490.07 | CQ30: =ROUND((ROUND((AC30*AW30*1),2)*BC30),2) -> 172.01 | CR30: =(ROUND((ROUND(((((ET30*1.2)*1.25))*AV30*1),2)*BB30),2)+ROUND((ROUND(((AE30-(((EU30*1.2)*1.25)))*AV30*1),2)*BS30),2)) -> 25.48 | CS30: =(ROUND((ROUND(((((EU30*1.2)*1.25))*AV30*1),2)*BS30),2)+ROUND((ROUND(((AE30-(((EU30*1.2)*1.25)))*AV30*1),2)*BS30),2)) -> 2.29 | CT30: =ROUND((ROUND((AF30*AV30*1),2)*BA30),2) -> 292.58 | CU30: =AG30 -> 0 | CV30: =(AH30*AV30) -> 24.001098 | CW30: =AI30 -> 0 | CX30: =AJ30 -> 0 | CY30: =(ROUND((((S30+ROUND((ROUND(((((EU30*1.2)*1.25))*AV30*1),2)*BS30),2))*AT30)/100),2)+ROUND(((ROUND((ROUND(((AE30-(((EU30*1.2)*1.25)))*AV30*1),2)*BS30),2)*AT30)/100),2)) -> 356.79 | CZ30: =(ROUND((((S30+ROUND((ROUND(((((EU30*1.2)*1.25))*AV30*1),2)*BS30),2))*AU30)/100),2)+ROUND(((ROUND((ROUND(((AE30-(((EU30*1.2)*1.25)))*AV30*1),2)*BS30),2)*AU30)/100),2)) -> 212.31 | DB30: 5 | DD30: *1)*1 | DE30: *1,2)*1,25 | DF30: *1,2)*1,25 | DG30: *1,2)*1,15 | DI30: *1,2)*1,15 | DJ30: *1,2)*1,25 | DN30: 0 | DO30: 0 | DP30: 1 | DQ30: 1 | DU30: 1013 | DV30: 1 насос | DW30: 1 насос | DX30: 1 | EE30: 56938689 | EF30: 30 | EG30: Строительные работы | EH30: 0 | EJ30: 1 | EK30: 23 | EL30: ТСН-2001.3-18. Отопление - внутренние устройства | EM30: ТСН-2001.3-18-1 | EO30: Поправка: Гл.12.Прил.8.п.8. 3_12.00.01.11.001 Поправка: Гл.6.Прил.2.2.п.2.2.6_06.00.01.07.001 | EQ30: 0 | ER30: 386.63 | ES30: 172.01 | ET30: 15.92 | EU30: 1.43 | EV30: 198.7 | EW30: 16.3 | EX30: 0 | EY30: 0 | FQ30: 0 | FR30: 0 | FS30: 0 | FX30: 121 | FY30: 72 | GD30: 1 | GF30: 1996820590 | GG30: 2 | GH30: 1 | GI30: 2 | GJ30: 0 | GK30: 0 | GL30: =ROUND(IF(AND(BH30=3,BI30=3,FS30<>0),P30,0),2) -> 0 | GM30: =ROUND(O30+X30+Y30,2)+GX30 -> 1059.17 | GN30: =IF(OR(BI30=0,BI30=1),GM30-GX30,0) -> 1059.17 | GO30: =IF(BI30=2,GM30-GX30,0) -> 0 | GP30: =IF(BI30=4,GM30-GX30,0) -> 0 | GR30: 0 | GS30: 3 | GT30: 0 | GV30: =ROUND((GT30),6) -> 0 | GW30: 1 | GX30: =ROUND(HC30*I30,2) -> 0 | HA30: 0 | HB30: 0 | HC30: =GV30*GW30 -> 0 | HS30: 0 | IK30: 0
A31: 17 | B31: 1 | C31: =ROW(SmtRes!A38) -> 38 | D31: =ROW(EtalonRes!A46) -> 46 | E31: 1 | F31: 3.18-11-2 | G31: Установка насосов центробежных с электродвигателем массой агрегата до 0,2 т | H31: 1 насос | I31: 1 | J31: 0 | K31: 1 | O31: =ROUND(CP31,2) -> 18120.35 | P31: =ROUND((ROUND((AC31*AW31*I31),2)*BC31),2) -> 1250.51 | Q31: =(ROUND((ROUND(((((ET31*1.2)*1.25))*AV31*I31),2)*BB31),2)+ROUND((ROUND(((AE31-(((EU31*1.2)*1.25)))*AV31*I31),2)*BS31),2)) -> 382.96 | R31: =(ROUND((ROUND(((((EU31*1.2)*1.25))*AV31*I31),2)*BS31),2)+ROUND((ROUND(((AE31-(((EU31*1.2)*1.25)))*AV31*I31),2)*BS31),2)) -> 129.04 | S31: =ROUND((ROUND((AF31*AV31*I31),2)*BA31),2) -> 16486.88 | T31: =ROUND(CU31*I31,2) -> 0 | U31: =CV31*I31 -> 24.001098 | V31: =CW31*I31 -> 0 | W31: =ROUND(CX31*I31,2) -> 0 | X31: =(ROUND((((S31+ROUND((ROUND(((((EU31*1.2)*1.25))*AV31*I31),2)*BS31),2))*AT31)/100),2)+ROUND(((ROUND((ROUND(((AE31-(((EU31*1.2)*1.25)))*AV31*I31),2)*BS31),2)*AT31)/100),2)) -> 20105.26 | Y31: =(ROUND((((S31+ROUND((ROUND(((((EU31*1.2)*1.25))*AV31*I31),2)*BS31),2))*AU31)/100),2)+ROUND(((ROUND((ROUND(((AE31-(((EU31*1.2)*1.25)))*AV31*I31),2)*BS31),2)*AU31)/100),2)) -> 11963.46 | AA31: 55747651 | AB31: =ROUND((AC31+AD31+AF31),6) -> 470.096 | AC31: =ROUND((((ES31*1)*1)),6) -> 172.01 | AD31: =ROUND((((((ET31*1.2)*1.25))-(((EU31*1.2)*1.25)))+AE31),6) -> 23.88 | AE31: =ROUND((((EU31*1.2)*1.25)),6) -> 2.145 | AF31: =ROUND((((EV31*1.2)*1.15)),6) -> 274.206 | AG31: =ROUND((AP31),6) -> 0 | AH31: =(((EW31*1.2)*1.15)) -> 22.494 | AI31: =(((EX31*1.2)*1.25)) -> 0 | AJ31: =(AS31) -> 0 | AK31: 386.63 | AL31: 172.01 | AM31: 15.92 | AN31: 1.43 | AO31: 198.7 | AP31: 0 | AQ31: 16.3 | AR31: 0 | AS31: 0 | AT31: 121 | AU31: 72 | AV31: 1.067 | AW31: 1 | AZ31: 1 | BA31: 56.35 | BB31: 15.03 | BC31: 7.27 | BH31: 0 | BI31: 1 | BJ31: ТСН-2001.3 Доп. 79, Сб. 18, т. 11, поз. 2 | BM31: 23 | BN31: 0 | BO31: 3.18-11-2 | BP31: 1 | BQ31: 30 | BR31: 0 | BS31: 56.35 | BT31: 1 | BU31: 1 | BV31: 1 | BW31: 1 | BX31: 1 | BZ31: 121 | CA31: 72 | CE31: 1566 | CF31: 0 | CG31: 0 | CM31: 0 | CN31: Поправка: Гл.12.Прил.8.п.8. 3_12.00.01.11.001 Наименование: При наличии напряженных и стесненных условий производства работ (стесненность, сложность складирования и транспортной логистики и т.п.) для объектов, расположенных в пределах круговой магистральной системы улиц "Садовое кольцо" города Москвы Поправка: Гл.6.Прил.2.2.п.2.2.6_06.00.01.07.001 Наименование: При выполнении при капитальном ремонте и реконструкции работ, аналогичных технологическим процессам, характерным для нового строительства, и отсутствующих в сборниках на ремонтно-строительные работы ТСН-2001.6 | CO31: 0 | CP31: =(P31+Q31+S31) -> 18120.35 | CQ31: =ROUND((ROUND((AC31*AW31*1),2)*BC31),2) -> 1250.51 | CR31: =(ROUND((ROUND(((((ET31*1.2)*1.25))*AV31*1),2)*BB31),2)+ROUND((ROUND(((AE31-(((EU31*1.2)*1.25)))*AV31*1),2)*BS31),2)) -> 382.96 | CS31: =(ROUND((ROUND(((((EU31*1.2)*1.25))*AV31*1),2)*BS31),2)+ROUND((ROUND(((AE31-(((EU31*1.2)*1.25)))*AV31*1),2)*BS31),2)) -> 129.04 | CT31: =ROUND((ROUND((AF31*AV31*1),2)*BA31),2) -> 16486.88 | CU31: =AG31 -> 0 | CV31: =(AH31*AV31) -> 24.001098 | CW31: =AI31 -> 0 | CX31: =AJ31 -> 0 | CY31: =(ROUND((((S31+ROUND((ROUND(((((EU31*1.2)*1.25))*AV31*1),2)*BS31),2))*AT31)/100),2)+ROUND(((ROUND((ROUND(((AE31-(((EU31*1.2)*1.25)))*AV31*1),2)*BS31),2)*AT31)/100),2)) -> 20105.26 | CZ31: =(ROUND((((S31+ROUND((ROUND(((((EU31*1.2)*1.25))*AV31*1),2)*BS31),2))*AU31)/100),2)+ROUND(((ROUND((ROUND(((AE31-(((EU31*1.2)*1.25)))*AV31*1),2)*BS31),2)*AU31)/100),2)) -> 11963.46 | DB31: 7 | DD31: *1)*1 | DE31: *1,2)*1,25 | DF31: *1,2)*1,25 | DG31: *1,2)*1,15 | DI31: *1,2)*1,15 | DJ31: *1,2)*1,25 | DN31: 0 | DO31: 0 | DP31: 1 | DQ31: 1 | DU31: 1013 | DV31: 1 насос | DW31: 1 насос | DX31: 1 | EE31: 56938689 | EF31: 30 | EG31: Строительные работы | EH31: 0 | EJ31: 1 | EK31: 23 | EL31: ТСН-2001.3-18. Отопление - внутренние устройства | EM31: ТСН-2001.3-18-1 | EO31: Поправка: Гл.12.Прил.8.п.8. 3_12.00.01.11.001 Поправка: Гл.6.Прил.2.2.п.2.2.6_06.00.01.07.001 | EQ31: 0 | ER31: 386.63 | ES31: 172.01 | ET31: 15.92 | EU31: 1.43 | EV31: 198.7 | EW31: 16.3 | EX31: 0 | EY31: 0 | FQ31: 0 | FR31: 0 | FS31: 0 | FX31: 121 | FY31: 72 | GD31: 1 | GF31: 1996820590 | GG31: 2 | GH31: 1 | GI31: 2 | GJ31: 0 | GK31: 0 | GL31: =ROUND(IF(AND(BH31=3,BI31=3,FS31<>0),P31,0),2) -> 0 | GM31: =ROUND(O31+X31+Y31,2)+GX31 -> 50189.07 | GN31: =IF(OR(BI31=0,BI31=1),GM31-GX31,0) -> 50189.07 | GO31: =IF(BI31=2,GM31-GX31,0) -> 0 | GP31: =IF(BI31=4,GM31-GX31,0) -> 0 | GR31: 0 | GS31: 3 | GT31: 0 | GV31: =ROUND((GT31),6) -> 0 | GW31: 1 | GX31: =ROUND(HC31*I31,2) -> 0 | HA31: 0 | HB31: 0 | HC31: =GV31*GW31 -> 0 | HS31: 0 | IK31: 0
A32: 17 | B32: 1 | C32: =ROW(SmtRes!A48) -> 48 | D32: =ROW(EtalonRes!A57) -> 57 | F32: 4.7-21-1 | G32: Монтаж насосного агрегата лопастного центробежного одноступенчатого, многоступенчатого объемного, вихревого, поршневого, приводного, роторного на общей фундаментной плите или моноблочный массой 0,064 т | H32: 1 ШТ. | I32: =ROUND(1,9) -> 1 | J32: 0 | K32: =ROUND(1,9) -> 1 | O32: =ROUND(CP32,2) -> 513.44 | P32: =ROUND((ROUND((AC32*AW32*I32),2)*BC32),2) -> 43.53 | Q32: =(ROUND((ROUND((((ET32*1.2))*AV32*I32),2)*BB32),2)+ROUND((ROUND(((AE32-((EU32*1.2)))*AV32*I32),2)*BS32),2)) -> 31.37 | R32: =(ROUND((ROUND((((EU32*1.2))*AV32*I32),2)*BS32),2)+ROUND((ROUND(((AE32-((EU32*1.2)))*AV32*I32),2)*BS32),2)) -> 0.49 | S32: =ROUND((ROUND((AF32*AV32*I32),2)*BA32),2) -> 438.54 | T32: =ROUND(CU32*I32,2) -> 0 | U32: =CV32*I32 -> 35.59512 | V32: =CW32*I32 -> 0 | W32: =ROUND(CX32*I32,2) -> 0 | X32: =(ROUND((((S32+ROUND((ROUND((((EU32*1.2))*AV32*I32),2)*BS32),2))*AT32)/100),2)+ROUND(((ROUND((ROUND(((AE32-((EU32*1.2)))*AV32*I32),2)*BS32),2)*AT32)/100),2)) -> 399.52 | Y32: =(ROUND((((S32+ROUND((ROUND((((EU32*1.2))*AV32*I32),2)*BS32),2))*AU32)/100),2)+ROUND(((ROUND((ROUND(((AE32-((EU32*1.2)))*AV32*I32),2)*BS32),2)*AU32)/100),2)) -> 206.34 | AA32: -1 | AB32: =ROUND((AC32+AD32+AF32),6) -> 482.74 | AC32: =ROUND(((ES32*1)),6) -> 42.34 | AD32: =ROUND(((((ET32*1.2))-((EU32*1.2)))+AE32),6) -> 29.4 | AE32: =ROUND(((EU32*1.2)),6) -> 0.456 | AF32: =ROUND(((EV32*1.2)),6) -> 411 | AG32: =ROUND((AP32),6) -> 0 | AH32: =((EW32*1.2)) -> 33.36 | AI32: =((EX32*1.2)) -> 0 | AJ32: =(AS32) -> 0 | AK32: 409.34 | AL32: 42.34 | AM32: 24.5 | AN32: 0.38 | AO32: 342.5 | AP32: 0 | AQ32: 27.8 | AR32: 0 | AS32: 0 | AT32: 91 | AU32: 47 | AV32: 1.067 | AW32: 1.028 | AZ32: 1 | BA32: 1 | BB32: 1 | BC32: 1 | BH32: 0 | BI32: 2 | BJ32: ТСН-2001.4 Доп. 80, Сб. 7, т. 21, поз. 1 | BM32: 66 | BN32: 0 | BO32: 4.7-21-1 | BP32: 1 | BQ32: 40 | BR32: 0 | BS32: 1 | BT32: 1 | BU32: 1 | BV32: 1 | BW32: 1 | BX32: 1 | BZ32: 91 | CA32: 47 | CE32: 1566 | CF32: 0 | CG32: 0 | CM32: 0 | CN32: Поправка: Гл.12.Прил.8.п.8. 3_12.00.01.11.001 Наименование: При наличии напряженных и стесненных условий производства работ (стесненность, сложность складирования и транспортной логистики и т.п.) для объектов, расположенных в пределах круговой магистральной системы улиц "Садовое кольцо" города Москвы | CO32: 0 | CP32: =(P32+Q32+S32) -> 513.44 | CQ32: =ROUND((ROUND((AC32*AW32*1),2)*BC32),2) -> 43.53 | CR32: =(ROUND((ROUND((((ET32*1.2))*AV32*1),2)*BB32),2)+ROUND((ROUND(((AE32-((EU32*1.2)))*AV32*1),2)*BS32),2)) -> 31.37 | CS32: =(ROUND((ROUND((((EU32*1.2))*AV32*1),2)*BS32),2)+ROUND((ROUND(((AE32-((EU32*1.2)))*AV32*1),2)*BS32),2)) -> 0.49 | CT32: =ROUND((ROUND((AF32*AV32*1),2)*BA32),2) -> 438.54 | CU32: =AG32 -> 0 | CV32: =(AH32*AV32) -> 35.59512 | CW32: =AI32 -> 0 | CX32: =AJ32 -> 0 | CY32: =(ROUND((((S32+ROUND((ROUND((((EU32*1.2))*AV32*1),2)*BS32),2))*AT32)/100),2)+ROUND(((ROUND((ROUND(((AE32-((EU32*1.2)))*AV32*1),2)*BS32),2)*AT32)/100),2)) -> 399.52 | CZ32: =(ROUND((((S32+ROUND((ROUND((((EU32*1.2))*AV32*1),2)*BS32),2))*AU32)/100),2)+ROUND(((ROUND((ROUND(((AE32-((EU32*1.2)))*AV32*1),2)*BS32),2)*AU32)/100),2)) -> 206.34 | DB32: 9 | DD32: *1 | DE32: *1,2 | DF32: *1,2 | DG32: *1,2 | DI32: *1,2 | DJ32: *1,2 | DN32: 0 | DO32: 0 | DP32: 1 | DQ32: 1 | DU32: 1013 | DV32: 1 ШТ. | DW32: 1 ШТ. | DX32: 1 | EE32: 56938733 | EF32: 40 | EG32: Монтаж оборудования | EH32: 0 | EJ32: 2 | EK32: 66 | EL32: ТСН-2001.4-7. Компрессорные машины, насосы, вентиляторы | EM32: ТСН-2001.4-7-1 | EO32: Поправка: Гл.12.Прил.8.п.8. 3_12.00.01.11.001 | EQ32: 132096 | ER32: 409.34 | ES32: 42.34 | ET32: 24.5 | EU32: 0.38 | EV32: 342.5 | EW32: 27.8 | EX32: 0 | EY32: 0 | FQ32: 0 | FR32: 0 | FS32: 2 | FX32: 91 | FY32: 47 | GD32: 1 | GF32: -1722888311 | GG32: 2 | GH32: 1 | GI32: 2 | GJ32: 0 | GK32: 0 | GL32: =ROUND(IF(AND(BH32=3,BI32=3,FS32<>0),P32,0),2) -> 0 | GM32: =ROUND(O32+X32+Y32,2)+GX32 -> 1119.3 | GN32: =IF(OR(BI32=0,BI32=1),GM32-GX32,0) -> 0 | GO32: =IF(BI32=2,GM32-GX32,0) -> 1119.3 | GP32: =IF(BI32=4,GM32-GX32,0) -> 0 | GR32: 0 | GS32: 3 | GT32: 0 | GV32: =ROUND((GT32),6) -> 0 | GW32: 1 | GX32: =ROUND(HC32*I32,2) -> 0 | HA32: 0 | HB32: 0 | HC32: =GV32*GW32 -> 0 | HS32: 0 | IK32: 0
A33: 17 | B33: 1 | C33: =ROW(SmtRes!A58) -> 58 | D33: =ROW(EtalonRes!A68) -> 68 | F33: 4.7-21-1 | G33: Монтаж насосного агрегата лопастного центробежного одноступенчатого, многоступенчатого объемного, вихревого, поршневого, приводного, роторного на общей фундаментной плите или моноблочный массой 0,064 т | H33: 1 ШТ. | I33: =ROUND(1,9) -> 1 | J33: 0 | K33: =ROUND(1,9) -> 1 | O33: =ROUND(CP33,2) -> 25637.77 | P33: =ROUND((ROUND((AC33*AW33*I33),2)*BC33),2) -> 507.56 | Q33: =(ROUND((ROUND((((ET33*1.2))*AV33*I33),2)*BB33),2)+ROUND((ROUND(((AE33-((EU33*1.2)))*AV33*I33),2)*BS33),2)) -> 418.48 | R33: =(ROUND((ROUND((((EU33*1.2))*AV33*I33),2)*BS33),2)+ROUND((ROUND(((AE33-((EU33*1.2)))*AV33*I33),2)*BS33),2)) -> 27.61 | S33: =ROUND((ROUND((AF33*AV33*I33),2)*BA33),2) -> 24711.73 | T33: =ROUND(CU33*I33,2) -> 0 | U33: =CV33*I33 -> 35.59512 | V33: =CW33*I33 -> 0 | W33: =ROUND(CX33*I33,2) -> 0 | X33: =(ROUND((((S33+ROUND((ROUND((((EU33*1.2))*AV33*I33),2)*BS33),2))*AT33)/100),2)+ROUND(((ROUND((ROUND(((AE33-((EU33*1.2)))*AV33*I33),2)*BS33),2)*AT33)/100),2)) -> 22512.8 | Y33: =(ROUND((((S33+ROUND((ROUND((((EU33*1.2))*AV33*I33),2)*BS33),2))*AU33)/100),2)+ROUND(((ROUND((ROUND(((AE33-((EU33*1.2)))*AV33*I33),2)*BS33),2)*AU33)/100),2)) -> 11627.49 | AA33: -1 | AB33: =ROUND((AC33+AD33+AF33),6) -> 482.74 | AC33: =ROUND(((ES33*1)),6) -> 42.34 | AD33: =ROUND(((((ET33*1.2))-((EU33*1.2)))+AE33),6) -> 29.4 | AE33: =ROUND(((EU33*1.2)),6) -> 0.456 | AF33: =ROUND(((EV33*1.2)),6) -> 411 | AG33: =ROUND((AP33),6) -> 0 | AH33: =((EW33*1.2)) -> 33.36 | AI33: =((EX33*1.2)) -> 0 | AJ33: =(AS33) -> 0 | AK33: 409.34 | AL33: 42.34 | AM33: 24.5 | AN33: 0.38 | AO33: 342.5 | AP33: 0 | AQ33: 27.8 | AR33: 0 | AS33: 0 | AT33: 91 | AU33: 47 | AV33: 1.067 | AW33: 1.028 | AZ33: 1 | BA33: 56.35 | BB33: 13.34 | BC33: 11.66 | BH33: 0 | BI33: 2 | BJ33: ТСН-2001.4 Доп. 80, Сб. 7, т. 21, поз. 1 | BM33: 66 | BN33: 0 | BO33: 4.7-21-1 | BP33: 1 | BQ33: 40 | BR33: 0 | BS33: 56.35 | BT33: 1 | BU33: 1 | BV33: 1 | BW33: 1 | BX33: 1 | BZ33: 91 | CA33: 47 | CE33: 1566 | CF33: 0 | CG33: 0 | CM33: 0 | CN33: Поправка: Гл.12.Прил.8.п.8. 3_12.00.01.11.001 Наименование: При наличии напряженных и стесненных условий производства работ (стесненность, сложность складирования и транспортной логистики и т.п.) для объектов, расположенных в пределах круговой магистральной системы улиц "Садовое кольцо" города Москвы | CO33: 0 | CP33: =(P33+Q33+S33) -> 25637.77 | CQ33: =ROUND((ROUND((AC33*AW33*1),2)*BC33),2) -> 507.56 | CR33: =(ROUND((ROUND((((ET33*1.2))*AV33*1),2)*BB33),2)+ROUND((ROUND(((AE33-((EU33*1.2)))*AV33*1),2)*BS33),2)) -> 418.48 | CS33: =(ROUND((ROUND((((EU33*1.2))*AV33*1),2)*BS33),2)+ROUND((ROUND(((AE33-((EU33*1.2)))*AV33*1),2)*BS33),2)) -> 27.61 | CT33: =ROUND((ROUND((AF33*AV33*1),2)*BA33),2) -> 24711.73 | CU33: =AG33 -> 0 | CV33: =(AH33*AV33) -> 35.59512 | CW33: =AI33 -> 0 | CX33: =AJ33 -> 0 | CY33: =(ROUND((((S33+ROUND((ROUND((((EU33*1.2))*AV33*1),2)*BS33),2))*AT33)/100),2)+ROUND(((ROUND((ROUND(((AE33-((EU33*1.2)))*AV33*1),2)*BS33),2)*AT33)/100),2)) -> 22512.8 | CZ33: =(ROUND((((S33+ROUND((ROUND((((EU33*1.2))*AV33*1),2)*BS33),2))*AU33)/100),2)+ROUND(((ROUND((ROUND(((AE33-((EU33*1.2)))*AV33*1),2)*BS33),2)*AU33)/100),2)) -> 11627.49 | DB33: 10 | DD33: *1 | DE33: *1,2 | DF33: *1,2 | DG33: *1,2 | DI33: *1,2 | DJ33: *1,2 | DN33: 0 | DO33: 0 | DP33: 1 | DQ33: 1 | DU33: 1013 | DV33: 1 ШТ. | DW33: 1 ШТ. | DX33: 1 | EE33: 56938733 | EF33: 40 | EG33: Монтаж оборудования | EH33: 0 | EJ33: 2 | EK33: 66 | EL33: ТСН-2001.4-7. Компрессорные машины, насосы, вентиляторы | EM33: ТСН-2001.4-7-1 | EO33: Поправка: Гл.12.Прил.8.п.8. 3_12.00.01.11.001 | EQ33: 132096 | ER33: 409.34 | ES33: 42.34 | ET33: 24.5 | EU33: 0.38 | EV33: 342.5 | EW33: 27.8 | EX33: 0 | EY33: 0 | FQ33: 0 | FR33: 0 | FS33: 2 | FX33: 91 | FY33: 47 | GD33: 1 | GF33: -1722888311 | GG33: 2 | GH33: 1 | GI33: 2 | GJ33: 0 | GK33: 0 | GL33: =ROUND(IF(AND(BH33=3,BI33=3,FS33<>0),P33,0),2) -> 0 | GM33: =ROUND(O33+X33+Y33,2)+GX33 -> 59778.06 | GN33: =IF(OR(BI33=0,BI33=1),GM33-GX33,0) -> 0 | GO33: =IF(BI33=2,GM33-GX33,0) -> 59778.06 | GP33: =IF(BI33=4,GM33-GX33,0) -> 0 | GR33: 0 | GS33: 3 | GT33: 0 | GV33: =ROUND((GT33),6) -> 0 | GW33: 1 | GX33: =ROUND(HC33*I33,2) -> 0 | HA33: 0 | HB33: 0 | HC33: =GV33*GW33 -> 0 | HS33: 0 | IK33: 0
A34: 17 | B34: 1 | C34: =ROW(SmtRes!A67) -> 67 | D34: =ROW(EtalonRes!A78) -> 78 | E34: 2 | F34: 3.17-10-1 | G34: Установка насосов погружных центробежных фекальных с электродвигателем производительностью 10 м3/час | H34: 1 ШТ. | I34: 1 | J34: 0 | K34: 1 | O34: =ROUND(CP34,2) -> 358.38 | P34: =ROUND((ROUND((AC34*AW34*I34),2)*BC34),2) -> 109.65 | Q34: =(ROUND((ROUND(((((ET34*1.2)*1.25))*AV34*I34),2)*BB34),2)+ROUND((ROUND(((AE34-(((EU34*1.2)*1.25)))*AV34*I34),2)*BS34),2)) -> 10 | R34: =(ROUND((ROUND(((((EU34*1.2)*1.25))*AV34*I34),2)*BS34),2)+ROUND((ROUND(((AE34-(((EU34*1.2)*1.25)))*AV34*I34),2)*BS34),2)) -> 0.48 | S34: =ROUND((ROUND((AF34*AV34*I34),2)*BA34),2) -> 238.73 | T34: =ROUND(CU34*I34,2) -> 0 | U34: =CV34*I34 -> 19.583718 | V34: =CW34*I34 -> 0 | W34: =ROUND(CX34*I34,2) -> 0 | X34: =(ROUND((((S34+ROUND((ROUND(((((EU34*1.2)*1.25))*AV34*I34),2)*BS34),2))*AT34)/100),2)+ROUND(((ROUND((ROUND(((AE34-(((EU34*1.2)*1.25)))*AV34*I34),2)*BS34),2)*AT34)/100),2)) -> 289.44 | Y34: =(ROUND((((S34+ROUND((ROUND(((((EU34*1.2)*1.25))*AV34*I34),2)*BS34),2))*AU34)/100),2)+ROUND(((ROUND((ROUND(((AE34-(((EU34*1.2)*1.25)))*AV34*I34),2)*BS34),2)*AU34)/100),2)) -> 172.23 | AA34: 55747649 | AB34: =ROUND((AC34+AD34+AF34),6) -> 342.7644 | AC34: =ROUND((((ES34*1)*1)),6) -> 109.65 | AD34: =ROUND((((((ET34*1.2)*1.25))-(((EU34*1.2)*1.25)))+AE34),6) -> 9.375 | AE34: =ROUND((((EU34*1.2)*1.25)),6) -> 0.45 | AF34: =ROUND((((EV34*1.2)*1.15)),6) -> 223.7394 | AG34: =ROUND((AP34),6) -> 0 | AH34: =(((EW34*1.2)*1.15)) -> 18.354 | AI34: =(((EX34*1.2)*1.25)) -> 0 | AJ34: =(AS34) -> 0 | AK34: 278.03 | AL34: 109.65 | AM34: 6.25 | AN34: 0.3 | AO34: 162.13 | AP34: 0 | AQ34: 13.3 | AR34: 0 | AS34: 0 | AT34: 121 | AU34: 72 | AV34: 1.067 | AW34: 1 | AZ34: 1 | BA34: 1 | BB34: 1 | BC34: 1 | BH34: 0 | BI34: 1 | BJ34: ТСН-2001.3 Доп. 79, Сб. 17, т. 10, поз. 1 | BM34: 22 | BN34: 0 | BO34: 3.17-10-1 | BP34: 1 | BQ34: 30 | BR34: 0 | BS34: 1 | BT34: 1 | BU34: 1 | BV34: 1 | BW34: 1 | BX34: 1 | BZ34: 121 | CA34: 72 | CE34: 1566 | CF34: 0 | CG34: 0 | CM34: 0 | CN34: Поправка: Гл.12.Прил.8.п.8. 3_12.00.01.11.001 Наименование: При наличии напряженных и стесненных условий производства работ (стесненность, сложность складирования и транспортной логистики и т.п.) для объектов, расположенных в пределах круговой магистральной системы улиц "Садовое кольцо" города Москвы Поправка: Гл.6.Прил.2.2.п.2.2.6_06.00.01.07.001 Наименование: При выполнении при капитальном ремонте и реконструкции работ, аналогичных технологическим процессам, характерным для нового строительства, и отсутствующих в сборниках на ремонтно-строительные работы ТСН-2001.6 | CO34: 0 | CP34: =(P34+Q34+S34) -> 358.38 | CQ34: =ROUND((ROUND((AC34*AW34*1),2)*BC34),2) -> 109.65 | CR34: =(ROUND((ROUND(((((ET34*1.2)*1.25))*AV34*1),2)*BB34),2)+ROUND((ROUND(((AE34-(((EU34*1.2)*1.25)))*AV34*1),2)*BS34),2)) -> 10 | CS34: =(ROUND((ROUND(((((EU34*1.2)*1.25))*AV34*1),2)*BS34),2)+ROUND((ROUND(((AE34-(((EU34*1.2)*1.25)))*AV34*1),2)*BS34),2)) -> 0.48 | CT34: =ROUND((ROUND((AF34*AV34*1),2)*BA34),2) -> 238.73 | CU34: =AG34 -> 0 | CV34: =(AH34*AV34) -> 19.583718 | CW34: =AI34 -> 0 | CX34: =AJ34 -> 0 | CY34: =(ROUND((((S34+ROUND((ROUND(((((EU34*1.2)*1.25))*AV34*1),2)*BS34),2))*AT34)/100),2)+ROUND(((ROUND((ROUND(((AE34-(((EU34*1.2)*1.25)))*AV34*1),2)*BS34),2)*AT34)/100),2)) -> 289.44 | CZ34: =(ROUND((((S34+ROUND((ROUND(((((EU34*1.2)*1.25))*AV34*1),2)*BS34),2))*AU34)/100),2)+ROUND(((ROUND((ROUND(((AE34-(((EU34*1.2)*1.25)))*AV34*1),2)*BS34),2)*AU34)/100),2)) -> 172.23 | DB34: 11 | DD34: *1)*1 | DE34: *1,2)*1,25 | DF34: *1,2)*1,25 | DG34: *1,2)*1,15 | DI34: *1,2)*1,15 | DJ34: *1,2)*1,25 | DN34: 0 | DO34: 0 | DP34: 1 | DQ34: 1 | DU34: 1013 | DV34: 1 ШТ. | DW34: 1 ШТ. | DX34: 1 | EE34: 56938688 | EF34: 30 | EG34: Строительные работы | EH34: 0 | EJ34: 1 | EK34: 22 | EL34: ТСН-2001.3-17. Водопровод и канализация - внутренние устройства | EM34: ТСН-2001.3-17-1 | EO34: Поправка: Гл.12.Прил.8.п.8. 3_12.00.01.11.001 Поправка: Гл.6.Прил.2.2.п.2.2.6_06.00.01.07.001 | EQ34: 0 | ER34: 278.03 | ES34: 109.65 | ET34: 6.25 | EU34: 0.3 | EV34: 162.13 | EW34: 13.3 | EX34: 0 | EY34: 0 | FQ34: 0 | FR34: 0 | FS34: 0 | FX34: 121 | FY34: 72 | GD34: 1 | GF34: -257018826 | GG34: 2 | GH34: 1 | GI34: 2 | GJ34: 0 | GK34: 0 | GL34: =ROUND(IF(AND(BH34=3,BI34=3,FS34<>0),P34,0),2) -> 0 | GM34: =ROUND(O34+X34+Y34,2)+GX34 -> 820.05 | GN34: =IF(OR(BI34=0,BI34=1),GM34-GX34,0) -> 820.05 | GO34: =IF(BI34=2,GM34-GX34,0) -> 0 | GP34: =IF(BI34=4,GM34-GX34,0) -> 0 | GR34: 0 | GS34: 3 | GT34: 0 | GV34: =ROUND((GT34),6) -> 0 | GW34: 1 | GX34: =ROUND(HC34*I34,2) -> 0 | HA34: 0 | HB34: 0 | HC34: =GV34*GW34 -> 0 | HS34: 0 | IK34: 0
A35: 17 | B35: 1 | C35: =ROW(SmtRes!A76) -> 76 | D35: =ROW(EtalonRes!A88) -> 88 | E35: 2 | F35: 3.17-10-1 | G35: Установка насосов погружных центробежных фекальных с электродвигателем производительностью 10 м3/час | H35: 1 ШТ. | I35: 1 | J35: 0 | K35: 1 | O35: =ROUND(CP35,2) -> 14385.22 | P35: =ROUND((ROUND((AC35*AW35*I35),2)*BC35),2) -> 790.58 | Q35: =(ROUND((ROUND(((((ET35*1.2)*1.25))*AV35*I35),2)*BB35),2)+ROUND((ROUND(((AE35-(((EU35*1.2)*1.25)))*AV35*I35),2)*BS35),2)) -> 142.2 | R35: =(ROUND((ROUND(((((EU35*1.2)*1.25))*AV35*I35),2)*BS35),2)+ROUND((ROUND(((AE35-(((EU35*1.2)*1.25)))*AV35*I35),2)*BS35),2)) -> 27.05 | S35: =ROUND((ROUND((AF35*AV35*I35),2)*BA35),2) -> 13452.44 | T35: =ROUND(CU35*I35,2) -> 0 | U35: =CV35*I35 -> 19.583718 | V35: =CW35*I35 -> 0 | W35: =ROUND(CX35*I35,2) -> 0 | X35: =(ROUND((((S35+ROUND((ROUND(((((EU35*1.2)*1.25))*AV35*I35),2)*BS35),2))*AT35)/100),2)+ROUND(((ROUND((ROUND(((AE35-(((EU35*1.2)*1.25)))*AV35*I35),2)*BS35),2)*AT35)/100),2)) -> 16310.18 | Y35: =(ROUND((((S35+ROUND((ROUND(((((EU35*1.2)*1.25))*AV35*I35),2)*BS35),2))*AU35)/100),2)+ROUND(((ROUND((ROUND(((AE35-(((EU35*1.2)*1.25)))*AV35*I35),2)*BS35),2)*AU35)/100),2)) -> 9705.23 | AA35: 55747651 | AB35: =ROUND((AC35+AD35+AF35),6) -> 342.7644 | AC35: =ROUND((((ES35*1)*1)),6) -> 109.65 | AD35: =ROUND((((((ET35*1.2)*1.25))-(((EU35*1.2)*1.25)))+AE35),6) -> 9.375 | AE35: =ROUND((((EU35*1.2)*1.25)),6) -> 0.45 | AF35: =ROUND((((EV35*1.2)*1.15)),6) -> 223.7394 | AG35: =ROUND((AP35),6) -> 0 | AH35: =(((EW35*1.2)*1.15)) -> 18.354 | AI35: =(((EX35*1.2)*1.25)) -> 0 | AJ35: =(AS35) -> 0 | AK35: 278.03 | AL35: 109.65 | AM35: 6.25 | AN35: 0.3 | AO35: 162.13 | AP35: 0 | AQ35: 13.3 | AR35: 0 | AS35: 0 | AT35: 121 | AU35: 72 | AV35: 1.067 | AW35: 1 | AZ35: 1 | BA35: 56.35 | BB35: 14.22 | BC35: 7.21 | BH35: 0 | BI35: 1 | BJ35: ТСН-2001.3 Доп. 79, Сб. 17, т. 10, поз. 1 | BM35: 22 | BN35: 0 | BO35: 3.17-10-1 | BP35: 1 | BQ35: 30 | BR35: 0 | BS35: 56.35 | BT35: 1 | BU35: 1 | BV35: 1 | BW35: 1 | BX35: 1 | BZ35: 121 | CA35: 72 | CE35: 1566 | CF35: 0 | CG35: 0 | CM35: 0 | CN35: Поправка: Гл.12.Прил.8.п.8. 3_12.00.01.11.001 Наименование: При наличии напряженных и стесненных условий производства работ (стесненность, сложность складирования и транспортной логистики и т.п.) для объектов, расположенных в пределах круговой магистральной системы улиц "Садовое кольцо" города Москвы Поправка: Гл.6.Прил.2.2.п.2.2.6_06.00.01.07.001 Наименование: При выполнении при капитальном ремонте и реконструкции работ, аналогичных технологическим процессам, характерным для нового строительства, и отсутствующих в сборниках на ремонтно-строительные работы ТСН-2001.6 | CO35: 0 | CP35: =(P35+Q35+S35) -> 14385.22 | CQ35: =ROUND((ROUND((AC35*AW35*1),2)*BC35),2) -> 790.58 | CR35: =(ROUND((ROUND(((((ET35*1.2)*1.25))*AV35*1),2)*BB35),2)+ROUND((ROUND(((AE35-(((EU35*1.2)*1.25)))*AV35*1),2)*BS35),2)) -> 142.2 | CS35: =(ROUND((ROUND(((((EU35*1.2)*1.25))*AV35*1),2)*BS35),2)+ROUND((ROUND(((AE35-(((EU35*1.2)*1.25)))*AV35*1),2)*BS35),2)) -> 27.05 | CT35: =ROUND((ROUND((AF35*AV35*1),2)*BA35),2) -> 13452.44 | CU35: =AG35 -> 0 | CV35: =(AH35*AV35) -> 19.583718 | CW35: =AI35 -> 0 | CX35: =AJ35 -> 0 | CY35: =(ROUND((((S35+ROUND((ROUND(((((EU35*1.2)*1.25))*AV35*1),2)*BS35),2))*AT35)/100),2)+ROUND(((ROUND((ROUND(((AE35-(((EU35*1.2)*1.25)))*AV35*1),2)*BS35),2)*AT35)/100),2)) -> 16310.18 | CZ35: =(ROUND((((S35+ROUND((ROUND(((((EU35*1.2)*1.25))*AV35*1),2)*BS35),2))*AU35)/100),2)+ROUND(((ROUND((ROUND(((AE35-(((EU35*1.2)*1.25)))*AV35*1),2)*BS35),2)*AU35)/100),2)) -> 9705.23 | DB35: 13 | DD35: *1)*1 | DE35: *1,2)*1,25 | DF35: *1,2)*1,25 | DG35: *1,2)*1,15 | DI35: *1,2)*1,15 | DJ35: *1,2)*1,25 | DN35: 0 | DO35: 0 | DP35: 1 | DQ35: 1 | DU35: 1013 | DV35: 1 ШТ. | DW35: 1 ШТ. | DX35: 1 | EE35: 56938688 | EF35: 30 | EG35: Строительные работы | EH35: 0 | EJ35: 1 | EK35: 22 | EL35: ТСН-2001.3-17. Водопровод и канализация - внутренние устройства | EM35: ТСН-2001.3-17-1 | EO35: Поправка: Гл.12.Прил.8.п.8. 3_12.00.01.11.001 Поправка: Гл.6.Прил.2.2.п.2.2.6_06.00.01.07.001 | EQ35: 0 | ER35: 278.03 | ES35: 109.65 | ET35: 6.25 | EU35: 0.3 | EV35: 162.13 | EW35: 13.3 | EX35: 0 | EY35: 0 | FQ35: 0 | FR35: 0 | FS35: 0 | FX35: 121 | FY35: 72 | GD35: 1 | GF35: -257018826 | GG35: 2 | GH35: 1 | GI35: 2 | GJ35: 0 | GK35: 0 | GL35: =ROUND(IF(AND(BH35=3,BI35=3,FS35<>0),P35,0),2) -> 0 | GM35: =ROUND(O35+X35+Y35,2)+GX35 -> 40400.63 | GN35: =IF(OR(BI35=0,BI35=1),GM35-GX35,0) -> 40400.63 | GO35: =IF(BI35=2,GM35-GX35,0) -> 0 | GP35: =IF(BI35=4,GM35-GX35,0) -> 0 | GR35: 0 | GS35: 3 | GT35: 0 | GV35: =ROUND((GT35),6) -> 0 | GW35: 1 | GX35: =ROUND(HC35*I35,2) -> 0 | HA35: 0 | HB35: 0 | HC35: =GV35*GW35 -> 0 | HS35: 0 | IK35: 0
A36: 17 | B36: 1 | C36: =ROW(SmtRes!A77) -> 77 | D36: =ROW(EtalonRes!A89) -> 89 | F36: 4.6-48-4 | G36: Бак внутренней установки без давления цилиндрический вертикальный, вместимость 1,0 м3 (60 л.) | H36: 1 Т | I36: 0.009 | J36: 0 | K36: 0.009 | O36: =ROUND(CP36,2) -> 100.94 | P36: =ROUND((ROUND((AC36*AW36*I36),2)*BC36),2) -> 1.23 | Q36: =(ROUND((ROUND((((ET36*1.2))*AV36*I36),2)*BB36),2)+ROUND((ROUND(((AE36-((EU36*1.2)))*AV36*I36),2)*BS36),2)) -> 35.34 | R36: =(ROUND((ROUND((((EU36*1.2))*AV36*I36),2)*BS36),2)+ROUND((ROUND(((AE36-((EU36*1.2)))*AV36*I36),2)*BS36),2)) -> 10.63 | S36: =ROUND((ROUND((AF36*AV36*I36),2)*BA36),2) -> 64.37 | T36: =ROUND(CU36*I36,2) -> 0 | U36: =CV36*I36 -> 5.6119932 | V36: =CW36*I36 -> 0 | W36: =ROUND(CX36*I36,2) -> 0 | X36: =(ROUND((((S36+ROUND((ROUND((((EU36*1.2))*AV36*I36),2)*BS36),2))*AT36)/100),2)+ROUND(((ROUND((ROUND(((AE36-((EU36*1.2)))*AV36*I36),2)*BS36),2)*AT36)/100),2)) -> 66.75 | Y36: =(ROUND((((S36+ROUND((ROUND((((EU36*1.2))*AV36*I36),2)*BS36),2))*AU36)/100),2)+ROUND(((ROUND((ROUND(((AE36-((EU36*1.2)))*AV36*I36),2)*BS36),2)*AU36)/100),2)) -> 33.75 | AA36: -1 | AB36: =ROUND((AC36+AD36+AF36),6) -> 10515.652 | AC36: =ROUND(((ES36*1)),6) -> 133 | AD36: =ROUND(((((ET36*1.2))-((EU36*1.2)))+AE36),6) -> 3679.584 | AE36: =ROUND(((EU36*1.2)),6) -> 1107.072 | AF36: =ROUND(((EV36*1.2)),6) -> 6703.068 | AG36: =ROUND((AP36),6) -> 0 | AH36: =((EW36*1.2)) -> 584.4 | AI36: =((EX36*1.2)) -> 0 | AJ36: =(AS36) -> 0 | AK36: 8785.21 | AL36: 133 | AM36: 3066.32 | AN36: 922.56 | AO36: 5585.89 | AP36: 0 | AQ36: 487 | AR36: 0 | AS36: 0 | AT36: 89 | AU36: 45 | AV36: 1.067 | AW36: 1.028 | AZ36: 1 | BA36: 1 | BB36: 1 | BC36: 1 | BH36: 0 | BI36: 2 | BJ36: ТСН-2001.4. Доп. 1-42. Сб. 6, т. 48, поз. 4 | BM36: 65 | BN36: 0 | BO36: 4.6-48-4 | BP36: 1 | BQ36: 40 | BR36: 0 | BS36: 1 | BT36: 1 | BU36: 1 | BV36: 1 | BW36: 1 | BX36: 1 | BZ36: 89 | CA36: 45 | CE36: 1566 | CF36: 0 | CG36: 0 | CM36: 0 | CN36: Поправка: Гл.12.Прил.8.п.8. 3_12.00.01.11.001 Наименование: При наличии напряженных и стесненных условий производства работ (стесненность, сложность складирования и транспортной логистики и т.п.) для объектов, расположенных в пределах круговой магистральной системы улиц "Садовое кольцо" города Москвы | CO36: 0 | CP36: =(P36+Q36+S36) -> 100.94 | CQ36: =ROUND((ROUND((AC36*AW36*1),2)*BC36),2) -> 136.72 | CR36: =(ROUND((ROUND((((ET36*1.2))*AV36*1),2)*BB36),2)+ROUND((ROUND(((AE36-((EU36*1.2)))*AV36*1),2)*BS36),2)) -> 3926.12 | CS36: =(ROUND((ROUND((((EU36*1.2))*AV36*1),2)*BS36),2)+ROUND((ROUND(((AE36-((EU36*1.2)))*AV36*1),2)*BS36),2)) -> 1181.25 | CT36: =ROUND((ROUND((AF36*AV36*1),2)*BA36),2) -> 7152.17 | CU36: =AG36 -> 0 | CV36: =(AH36*AV36) -> 623.5548 | CW36: =AI36 -> 0 | CX36: =AJ36 -> 0 | CY36: =(ROUND((((S36+ROUND((ROUND((((EU36*1.2))*AV36*1),2)*BS36),2))*AT36)/100),2)+ROUND(((ROUND((ROUND(((AE36-((EU36*1.2)))*AV36*1),2)*BS36),2)*AT36)/100),2)) -> 1108.6 | CZ36: =(ROUND((((S36+ROUND((ROUND((((EU36*1.2))*AV36*1),2)*BS36),2))*AU36)/100),2)+ROUND(((ROUND((ROUND(((AE36-((EU36*1.2)))*AV36*1),2)*BS36),2)*AU36)/100),2)) -> 560.53 | DB36: 15 | DD36: *1 | DE36: *1,2 | DF36: *1,2 | DG36: *1,2 | DI36: *1,2 | DJ36: *1,2 | DN36: 0 | DO36: 0 | DP36: 1 | DQ36: 1 | DU36: 1013 | DV36: 1 Т | DW36: 1 Т | DX36: 1 | EE36: 56938732 | EF36: 40 | EG36: Монтаж оборудования | EH36: 0 | EJ36: 2 | EK36: 65 | EL36: ТСН-2001.4-6. Теплосиловое оборудование | EM36: ТСН-2001.4-6-1 | EO36: Поправка: Гл.12.Прил.8.п.8. 3_12.00.01.11.001 | EQ36: 132096 | ER36: 8785.21 | ES36: 133 | ET36: 3066.32 | EU36: 922.56 | EV36: 5585.89 | EW36: 487 | EX36: 0 | EY36: 0 | FQ36: 0 | FR36: 0 | FS36: 2 | FX36: 89 | FY36: 45 | GD36: 1 | GF36: -966979253 | GG36: 2 | GH36: 1 | GI36: 2 | GJ36: 0 | GK36: 0 | GL36: =ROUND(IF(AND(BH36=3,BI36=3,FS36<>0),P36,0),2) -> 0 | GM36: =ROUND(O36+X36+Y36,2)+GX36 -> 201.44 | GN36: =IF(OR(BI36=0,BI36=1),GM36-GX36,0) -> 0 | GO36: =IF(BI36=2,GM36-GX36,0) -> 201.44 | GP36: =IF(BI36=4,GM36-GX36,0) -> 0 | GR36: 0 | GS36: 3 | GT36: 0 | GV36: =ROUND((GT36),6) -> 0 | GW36: 1 | GX36: =ROUND(HC36*I36,2) -> 0 | HA36: 0 | HB36: 0 | HC36: =GV36*GW36 -> 0 | HS36: 0 | IK36: 0
A37: 17 | B37: 1 | C37: =ROW(SmtRes!A78) -> 78 | D37: =ROW(EtalonRes!A90) -> 90 | F37: 4.6-48-4 | G37: Бак внутренней установки без давления цилиндрический вертикальный, вместимость 1,0 м3 (60 л.) | H37: 1 Т | I37: 0.009 | J37: 0 | K37: 0.009 | O37: =ROUND(CP37,2) -> 4509.42 | P37: =ROUND((ROUND((AC37*AW37*I37),2)*BC37),2) -> 12.1 | Q37: =(ROUND((ROUND((((ET37*1.2))*AV37*I37),2)*BB37),2)+ROUND((ROUND(((AE37-((EU37*1.2)))*AV37*I37),2)*BS37),2)) -> 870.07 | R37: =(ROUND((ROUND((((EU37*1.2))*AV37*I37),2)*BS37),2)+ROUND((ROUND(((AE37-((EU37*1.2)))*AV37*I37),2)*BS37),2)) -> 599 | S37: =ROUND((ROUND((AF37*AV37*I37),2)*BA37),2) -> 3627.25 | T37: =ROUND(CU37*I37,2) -> 0 | U37: =CV37*I37 -> 5.6119932 | V37: =CW37*I37 -> 0 | W37: =ROUND(CX37*I37,2) -> 0 | X37: =(ROUND((((S37+ROUND((ROUND((((EU37*1.2))*AV37*I37),2)*BS37),2))*AT37)/100),2)+ROUND(((ROUND((ROUND(((AE37-((EU37*1.2)))*AV37*I37),2)*BS37),2)*AT37)/100),2)) -> 3761.36 | Y37: =(ROUND((((S37+ROUND((ROUND((((EU37*1.2))*AV37*I37),2)*BS37),2))*AU37)/100),2)+ROUND(((ROUND((ROUND(((AE37-((EU37*1.2)))*AV37*I37),2)*BS37),2)*AU37)/100),2)) -> 1901.81 | AA37: -1 | AB37: =ROUND((AC37+AD37+AF37),6) -> 10515.652 | AC37: =ROUND(((ES37*1)),6) -> 133 | AD37: =ROUND(((((ET37*1.2))-((EU37*1.2)))+AE37),6) -> 3679.584 | AE37: =ROUND(((EU37*1.2)),6) -> 1107.072 | AF37: =ROUND(((EV37*1.2)),6) -> 6703.068 | AG37: =ROUND((AP37),6) -> 0 | AH37: =((EW37*1.2)) -> 584.4 | AI37: =((EX37*1.2)) -> 0 | AJ37: =(AS37) -> 0 | AK37: 8785.21 | AL37: 133 | AM37: 3066.32 | AN37: 922.56 | AO37: 5585.89 | AP37: 0 | AQ37: 487 | AR37: 0 | AS37: 0 | AT37: 89 | AU37: 45 | AV37: 1.067 | AW37: 1.028 | AZ37: 1 | BA37: 56.35 | BB37: 24.62 | BC37: 9.84 | BH37: 0 | BI37: 2 | BJ37: ТСН-2001.4. Доп. 1-42. Сб. 6, т. 48, поз. 4 | BM37: 65 | BN37: 0 | BO37: 4.6-48-4 | BP37: 1 | BQ37: 40 | BR37: 0 | BS37: 56.35 | BT37: 1 | BU37: 1 | BV37: 1 | BW37: 1 | BX37: 1 | BZ37: 89 | CA37: 45 | CE37: 1566 | CF37: 0 | CG37: 0 | CM37: 0 | CN37: Поправка: Гл.12.Прил.8.п.8. 3_12.00.01.11.001 Наименование: При наличии напряженных и стесненных условий производства работ (стесненность, сложность складирования и транспортной логистики и т.п.) для объектов, расположенных в пределах круговой магистральной системы улиц "Садовое кольцо" города Москвы | CO37: 0 | CP37: =(P37+Q37+S37) -> 4509.42 | CQ37: =ROUND((ROUND((AC37*AW37*1),2)*BC37),2) -> 1345.32 | CR37: =(ROUND((ROUND((((ET37*1.2))*AV37*1),2)*BB37),2)+ROUND((ROUND(((AE37-((EU37*1.2)))*AV37*1),2)*BS37),2)) -> 96661.07 | CS37: =(ROUND((ROUND((((EU37*1.2))*AV37*1),2)*BS37),2)+ROUND((ROUND(((AE37-((EU37*1.2)))*AV37*1),2)*BS37),2)) -> 66563.44 | CT37: =ROUND((ROUND((AF37*AV37*1),2)*BA37),2) -> 403024.78 | CU37: =AG37 -> 0 | CV37: =(AH37*AV37) -> 623.5548 | CW37: =AI37 -> 0 | CX37: =AJ37 -> 0 | CY37: =(ROUND((((S37+ROUND((ROUND((((EU37*1.2))*AV37*1),2)*BS37),2))*AT37)/100),2)+ROUND(((ROUND((ROUND(((AE37-((EU37*1.2)))*AV37*1),2)*BS37),2)*AT37)/100),2)) -> 62469.71 | CZ37: =(ROUND((((S37+ROUND((ROUND((((EU37*1.2))*AV37*1),2)*BS37),2))*AU37)/100),2)+ROUND(((ROUND((ROUND(((AE37-((EU37*1.2)))*AV37*1),2)*BS37),2)*AU37)/100),2)) -> 31585.81 | DB37: 16 | DD37: *1 | DE37: *1,2 | DF37: *1,2 | DG37: *1,2 | DI37: *1,2 | DJ37: *1,2 | DN37: 0 | DO37: 0 | DP37: 1 | DQ37: 1 | DU37: 1013 | DV37: 1 Т | DW37: 1 Т | DX37: 1 | EE37: 56938732 | EF37: 40 | EG37: Монтаж оборудования | EH37: 0 | EJ37: 2 | EK37: 65 | EL37: ТСН-2001.4-6. Теплосиловое оборудование | EM37: ТСН-2001.4-6-1 | EO37: Поправка: Гл.12.Прил.8.п.8. 3_12.00.01.11.001 | EQ37: 132096 | ER37: 8785.21 | ES37: 133 | ET37: 3066.32 | EU37: 922.56 | EV37: 5585.89 | EW37: 487 | EX37: 0 | EY37: 0 | FQ37: 0 | FR37: 0 | FS37: 2 | FX37: 89 | FY37: 45 | GD37: 1 | GF37: -966979253 | GG37: 2 | GH37: 1 | GI37: 2 | GJ37: 0 | GK37: 0 | GL37: =ROUND(IF(AND(BH37=3,BI37=3,FS37<>0),P37,0),2) -> 0 | GM37: =ROUND(O37+X37+Y37,2)+GX37 -> 10172.59 | GN37: =IF(OR(BI37=0,BI37=1),GM37-GX37,0) -> 0 | GO37: =IF(BI37=2,GM37-GX37,0) -> 10172.59 | GP37: =IF(BI37=4,GM37-GX37,0) -> 0 | GR37: 0 | GS37: 3 | GT37: 0 | GV37: =ROUND((GT37),6) -> 0 | GW37: 1 | GX37: =ROUND(HC37*I37,2) -> 0 | HA37: 0 | HB37: 0 | HC37: =GV37*GW37 -> 0 | HS37: 0 | IK37: 0
A38: 17 | B38: 1 | C38: =ROW(SmtRes!A86) -> 86 | D38: =ROW(EtalonRes!A99) -> 99 | F38: 3.18-8-1 | G38: Установка баков расширительных круглых и прямоугольных вместимостью до 0,1 м3 (60 л.) | H38: 1 бак | I38: 1 | J38: 0 | K38: 1 | O38: =ROUND(CP38,2) -> 57.22 | P38: =ROUND((ROUND((AC38*AW38*I38),2)*BC38),2) -> 4.19 | Q38: =(ROUND((ROUND(((ET38)*AV38*I38),2)*BB38),2)+ROUND((ROUND(((AE38-(EU38))*AV38*I38),2)*BS38),2)) -> 8.07 | R38: =(ROUND((ROUND(((EU38)*AV38*I38),2)*BS38),2)+ROUND((ROUND(((AE38-(EU38))*AV38*I38),2)*BS38),2)) -> 0.63 | S38: =ROUND((ROUND((AF38*AV38*I38),2)*BA38),2) -> 44.96 | T38: =ROUND(CU38*I38,2) -> 0 | U38: =CV38*I38 -> 3.87321 | V38: =CW38*I38 -> 0 | W38: =ROUND(CX38*I38,2) -> 0 | X38: =(ROUND((((S38+ROUND((ROUND(((EU38)*AV38*I38),2)*BS38),2))*AT38)/100),2)+ROUND(((ROUND((ROUND(((AE38-(EU38))*AV38*I38),2)*BS38),2)*AT38)/100),2)) -> 55.16 | Y38: =(ROUND((((S38+ROUND((ROUND(((EU38)*AV38*I38),2)*BS38),2))*AU38)/100),2)+ROUND(((ROUND((ROUND(((AE38-(EU38))*AV38*I38),2)*BS38),2)*AU38)/100),2)) -> 32.82 | AA38: -1 | AB38: =ROUND((AC38+AD38+AF38),6) -> 53.89 | AC38: =ROUND((ES38),6) -> 4.19 | AD38: =ROUND((((ET38)-(EU38))+AE38),6) -> 7.56 | AE38: =ROUND((EU38),6) -> 0.59 | AF38: =ROUND((EV38),6) -> 42.14 | AG38: =ROUND((AP38),6) -> 0 | AH38: =(EW38) -> 3.63 | AI38: =(EX38) -> 0 | AJ38: =(AS38) -> 0 | AK38: 53.89 | AL38: 4.19 | AM38: 7.56 | AN38: 0.59 | AO38: 42.14 | AP38: 0 | AQ38: 3.63 | AR38: 0 | AS38: 0 | AT38: 121 | AU38: 72 | AV38: 1.067 | AW38: 1 | AZ38: 1 | BA38: 1 | BB38: 1 | BC38: 1 | BH38: 0 | BI38: 1 | BJ38: ТСН-2001.3 Доп. 72, Сб. 18, т. 8, поз. 1 | BM38: 23 | BN38: 0 | BO38: 3.18-8-1 | BP38: 1 | BQ38: 30 | BR38: 0 | BS38: 1 | BT38: 1 | BU38: 1 | BV38: 1 | BW38: 1 | BX38: 1 | BZ38: 121 | CA38: 72 | CE38: 1566 | CF38: 0 | CG38: 0 | CM38: 0 | CO38: 0 | CP38: =(P38+Q38+S38) -> 57.22 | CQ38: =ROUND((ROUND((AC38*AW38*1),2)*BC38),2) -> 4.19 | CR38: =(ROUND((ROUND(((ET38)*AV38*1),2)*BB38),2)+ROUND((ROUND(((AE38-(EU38))*AV38*1),2)*BS38),2)) -> 8.07 | CS38: =(ROUND((ROUND(((EU38)*AV38*1),2)*BS38),2)+ROUND((ROUND(((AE38-(EU38))*AV38*1),2)*BS38),2)) -> 0.63 | CT38: =ROUND((ROUND((AF38*AV38*1),2)*BA38),2) -> 44.96 | CU38: =AG38 -> 0 | CV38: =(AH38*AV38) -> 3.87321 | CW38: =AI38 -> 0 | CX38: =AJ38 -> 0 | CY38: =(ROUND((((S38+ROUND((ROUND(((EU38)*AV38*1),2)*BS38),2))*AT38)/100),2)+ROUND(((ROUND((ROUND(((AE38-(EU38))*AV38*1),2)*BS38),2)*AT38)/100),2)) -> 55.16 | CZ38: =(ROUND((((S38+ROUND((ROUND(((EU38)*AV38*1),2)*BS38),2))*AU38)/100),2)+ROUND(((ROUND((ROUND(((AE38-(EU38))*AV38*1),2)*BS38),2)*AU38)/100),2)) -> 32.82 | DN38: 0 | DO38: 0 | DP38: 1 | DQ38: 1 | DU38: 1013 | DV38: 1 бак | DW38: 1 бак | DX38: 1 | EE38: 56938689 | EF38: 30 | EG38: Строительные работы | EH38: 0 | EJ38: 1 | EK38: 23 | EL38: ТСН-2001.3-18. Отопление - внутренние устройства | EM38: ТСН-2001.3-18-1 | EQ38: 132096 | ER38: 53.89 | ES38: 4.19 | ET38: 7.56 | EU38: 0.59 | EV38: 42.14 | EW38: 3.63 | EX38: 0 | EY38: 0 | FQ38: 0 | FR38: 0 | FS38: 0 | FX38: 121 | FY38: 72 | GD38: 1 | GF38: 1630609332 | GG38: 2 | GH38: 1 | GI38: 2 | GJ38: 0 | GK38: 0 | GL38: =ROUND(IF(AND(BH38=3,BI38=3,FS38<>0),P38,0),2) -> 0 | GM38: =ROUND(O38+X38+Y38,2)+GX38 -> 145.2 | GN38: =IF(OR(BI38=0,BI38=1),GM38-GX38,0) -> 145.2 | GO38: =IF(BI38=2,GM38-GX38,0) -> 0 | GP38: =IF(BI38=4,GM38-GX38,0) -> 0 | GR38: 0 | GS38: 3 | GT38: 0 | GV38: =ROUND((GT38),6) -> 0 | GW38: 1 | GX38: =ROUND(HC38*I38,2) -> 0 | HA38: 0 | HB38: 0 | HC38: =GV38*GW38 -> 0 | HS38: 0 | IK38: 0
A39: 17 | B39: 1 | C39: =ROW(SmtRes!A94) -> 94 | D39: =ROW(EtalonRes!A108) -> 108 | F39: 3.18-8-1 | G39: Установка баков расширительных круглых и прямоугольных вместимостью до 0,1 м3 (60 л.) | H39: 1 бак | I39: 1 | J39: 0 | K39: 1 | O39: =ROUND(CP39,2) -> 2672.58 | P39: =ROUND((ROUND((AC39*AW39*I39),2)*BC39),2) -> 24.89 | Q39: =(ROUND((ROUND(((ET39)*AV39*I39),2)*BB39),2)+ROUND((ROUND(((AE39-(EU39))*AV39*I39),2)*BS39),2)) -> 114.19 | R39: =(ROUND((ROUND(((EU39)*AV39*I39),2)*BS39),2)+ROUND((ROUND(((AE39-(EU39))*AV39*I39),2)*BS39),2)) -> 35.5 | S39: =ROUND((ROUND((AF39*AV39*I39),2)*BA39),2) -> 2533.5 | T39: =ROUND(CU39*I39,2) -> 0 | U39: =CV39*I39 -> 3.87321 | V39: =CW39*I39 -> 0 | W39: =ROUND(CX39*I39,2) -> 0 | X39: =(ROUND((((S39+ROUND((ROUND(((EU39)*AV39*I39),2)*BS39),2))*AT39)/100),2)+ROUND(((ROUND((ROUND(((AE39-(EU39))*AV39*I39),2)*BS39),2)*AT39)/100),2)) -> 3108.49 | Y39: =(ROUND((((S39+ROUND((ROUND(((EU39)*AV39*I39),2)*BS39),2))*AU39)/100),2)+ROUND(((ROUND((ROUND(((AE39-(EU39))*AV39*I39),2)*BS39),2)*AU39)/100),2)) -> 1849.68 | AA39: -1 | AB39: =ROUND((AC39+AD39+AF39),6) -> 53.89 | AC39: =ROUND((ES39),6) -> 4.19 | AD39: =ROUND((((ET39)-(EU39))+AE39),6) -> 7.56 | AE39: =ROUND((EU39),6) -> 0.59 | AF39: =ROUND((EV39),6) -> 42.14 | AG39: =ROUND((AP39),6) -> 0 | AH39: =(EW39) -> 3.63 | AI39: =(EX39) -> 0 | AJ39: =(AS39) -> 0 | AK39: 53.89 | AL39: 4.19 | AM39: 7.56 | AN39: 0.59 | AO39: 42.14 | AP39: 0 | AQ39: 3.63 | AR39: 0 | AS39: 0 | AT39: 121 | AU39: 72 | AV39: 1.067 | AW39: 1 | AZ39: 1 | BA39: 56.35 | BB39: 14.15 | BC39: 5.94 | BH39: 0 | BI39: 1 | BJ39: ТСН-2001.3 Доп. 72, Сб. 18, т. 8, поз. 1 | BM39: 23 | BN39: 0 | BO39: 3.18-8-1 | BP39: 1 | BQ39: 30 | BR39: 0 | BS39: 56.35 | BT39: 1 | BU39: 1 | BV39: 1 | BW39: 1 | BX39: 1 | BZ39: 121 | CA39: 72 | CE39: 1566 | CF39: 0 | CG39: 0 | CM39: 0 | CO39: 0 | CP39: =(P39+Q39+S39) -> 2672.58 | CQ39: =ROUND((ROUND((AC39*AW39*1),2)*BC39),2) -> 24.89 | CR39: =(ROUND((ROUND(((ET39)*AV39*1),2)*BB39),2)+ROUND((ROUND(((AE39-(EU39))*AV39*1),2)*BS39),2)) -> 114.19 | CS39: =(ROUND((ROUND(((EU39)*AV39*1),2)*BS39),2)+ROUND((ROUND(((AE39-(EU39))*AV39*1),2)*BS39),2)) -> 35.5 | CT39: =ROUND((ROUND((AF39*AV39*1),2)*BA39),2) -> 2533.5 | CU39: =AG39 -> 0 | CV39: =(AH39*AV39) -> 3.87321 | CW39: =AI39 -> 0 | CX39: =AJ39 -> 0 | CY39: =(ROUND((((S39+ROUND((ROUND(((EU39)*AV39*1),2)*BS39),2))*AT39)/100),2)+ROUND(((ROUND((ROUND(((AE39-(EU39))*AV39*1),2)*BS39),2)*AT39)/100),2)) -> 3108.49 | CZ39: =(ROUND((((S39+ROUND((ROUND(((EU39)*AV39*1),2)*BS39),2))*AU39)/100),2)+ROUND(((ROUND((ROUND(((AE39-(EU39))*AV39*1),2)*BS39),2)*AU39)/100),2)) -> 1849.68 | DN39: 0 | DO39: 0 | DP39: 1 | DQ39: 1 | DU39: 1013 | DV39: 1 бак | DW39: 1 бак | DX39: 1 | EE39: 56938689 | EF39: 30 | EG39: Строительные работы | EH39: 0 | EJ39: 1 | EK39: 23 | EL39: ТСН-2001.3-18. Отопление - внутренние устройства | EM39: ТСН-2001.3-18-1 | EQ39: 132096 | ER39: 53.89 | ES39: 4.19 | ET39: 7.56 | EU39: 0.59 | EV39: 42.14 | EW39: 3.63 | EX39: 0 | EY39: 0 | FQ39: 0 | FR39: 0 | FS39: 0 | FX39: 121 | FY39: 72 | GD39: 1 | GF39: 1630609332 | GG39: 2 | GH39: 1 | GI39: 2 | GJ39: 0 | GK39: 0 | GL39: =ROUND(IF(AND(BH39=3,BI39=3,FS39<>0),P39,0),2) -> 0 | GM39: =ROUND(O39+X39+Y39,2)+GX39 -> 7630.75 | GN39: =IF(OR(BI39=0,BI39=1),GM39-GX39,0) -> 7630.75 | GO39: =IF(BI39=2,GM39-GX39,0) -> 0 | GP39: =IF(BI39=4,GM39-GX39,0) -> 0 | GR39: 0 | GS39: 3 | GT39: 0 | GV39: =ROUND((GT39),6) -> 0 | GW39: 1 | GX39: =ROUND(HC39*I39,2) -> 0 | HA39: 0 | HB39: 0 | HC39: =GV39*GW39 -> 0 | HS39: 0 | IK39: 0
A40: 17 | B40: 1 | C40: =ROW(SmtRes!A101) -> 101 | D40: =ROW(EtalonRes!A117) -> 117 | F40: 4.8-240-4 | G40: Монтаж пультов и шкафов управления, шкафа (пульта) управления навесного, высотой, шириной, глубиной до 600х600х350 мм | H40: 1 ШТ. | I40: 1 | J40: 0 | K40: 1 | O40: =ROUND(CP40,2) -> 56.97 | P40: =ROUND((ROUND((AC40*AW40*I40),2)*BC40),2) -> 1.46 | Q40: =(ROUND((ROUND((((ET40*1.2))*AV40*I40),2)*BB40),2)+ROUND((ROUND(((AE40-((EU40*1.2)))*AV40*I40),2)*BS40),2)) -> 21.89 | R40: =(ROUND((ROUND((((EU40*1.2))*AV40*I40),2)*BS40),2)+ROUND((ROUND(((AE40-((EU40*1.2)))*AV40*I40),2)*BS40),2)) -> 3.97 | S40: =ROUND((ROUND((AF40*AV40*I40),2)*BA40),2) -> 33.62 | T40: =ROUND(CU40*I40,2) -> 0 | U40: =CV40*I40 -> 2.588184 | V40: =CW40*I40 -> 0 | W40: =ROUND(CX40*I40,2) -> 0 | X40: =(ROUND((((S40+ROUND((ROUND((((EU40*1.2))*AV40*I40),2)*BS40),2))*AT40)/100),2)+ROUND(((ROUND((ROUND(((AE40-((EU40*1.2)))*AV40*I40),2)*BS40),2)*AT40)/100),2)) -> 36.46 | Y40: =(ROUND((((S40+ROUND((ROUND((((EU40*1.2))*AV40*I40),2)*BS40),2))*AU40)/100),2)+ROUND(((ROUND((ROUND(((AE40-((EU40*1.2)))*AV40*I40),2)*BS40),2)*AU40)/100),2)) -> 19.17 | AA40: -1 | AB40: =ROUND((AC40+AD40+AF40),6) -> 54.476 | AC40: =ROUND(((ES40*1)),6) -> 1.46 | AD40: =ROUND(((((ET40*1.2))-((EU40*1.2)))+AE40),6) -> 20.904 | AE40: =ROUND(((EU40*1.2)),6) -> 3.792 | AF40: =ROUND(((EV40*1.2)),6) -> 32.112 | AG40: =ROUND((AP40),6) -> 0 | AH40: =((EW40*1.2)) -> 2.472 | AI40: =((EX40*1.2)) -> 0 | AJ40: =(AS40) -> 0 | AK40: 45.64 | AL40: 1.46 | AM40: 17.42 | AN40: 3.16 | AO40: 26.76 | AP40: 0 | AQ40: 2.06 | AR40: 0 | AS40: 0 | AT40: 97 | AU40: 51 | AV40: 1.047 | AW40: 1 | AZ40: 1 | BA40: 1 | BB40: 1 | BC40: 1 | BH40: 0 | BI40: 2 | BJ40: ТСН-2001.4 Доп. 80, Сб. 8, т. 240, поз. 4 | BM40: 67 | BN40: 0 | BO40: 4.8-240-4 | BP40: 1 | BQ40: 40 | BR40: 0 | BS40: 1 | BT40: 1 | BU40: 1 | BV40: 1 | BW40: 1 | BX40: 1 | BZ40: 97 | CA40: 51 | CE40: 1566 | CF40: 0 | CG40: 0 | CM40: 0 | CN40: Поправка: Гл.12.Прил.8.п.8. 3_12.00.01.11.001 Наименование: При наличии напряженных и стесненных условий производства работ (стесненность, сложность складирования и транспортной логистики и т.п.) для объектов, расположенных в пределах круговой магистральной системы улиц "Садовое кольцо" города Москвы | CO40: 0 | CP40: =(P40+Q40+S40) -> 56.97 | CQ40: =ROUND((ROUND((AC40*AW40*1),2)*BC40),2) -> 1.46 | CR40: =(ROUND((ROUND((((ET40*1.2))*AV40*1),2)*BB40),2)+ROUND((ROUND(((AE40-((EU40*1.2)))*AV40*1),2)*BS40),2)) -> 21.89 | CS40: =(ROUND((ROUND((((EU40*1.2))*AV40*1),2)*BS40),2)+ROUND((ROUND(((AE40-((EU40*1.2)))*AV40*1),2)*BS40),2)) -> 3.97 | CT40: =ROUND((ROUND((AF40*AV40*1),2)*BA40),2) -> 33.62 | CU40: =AG40 -> 0 | CV40: =(AH40*AV40) -> 2.588184 | CW40: =AI40 -> 0 | CX40: =AJ40 -> 0 | CY40: =(ROUND((((S40+ROUND((ROUND((((EU40*1.2))*AV40*1),2)*BS40),2))*AT40)/100),2)+ROUND(((ROUND((ROUND(((AE40-((EU40*1.2)))*AV40*1),2)*BS40),2)*AT40)/100),2)) -> 36.46 | CZ40: =(ROUND((((S40+ROUND((ROUND((((EU40*1.2))*AV40*1),2)*BS40),2))*AU40)/100),2)+ROUND(((ROUND((ROUND(((AE40-((EU40*1.2)))*AV40*1),2)*BS40),2)*AU40)/100),2)) -> 19.17 | DB40: 17 | DD40: *1 | DE40: *1,2 | DF40: *1,2 | DG40: *1,2 | DI40: *1,2 | DJ40: *1,2 | DN40: 0 | DO40: 0 | DP40: 1 | DQ40: 1 | DU40: 1013 | DV40: 1 ШТ. | DW40: 1 ШТ. | DX40: 1 | EE40: 56938734 | EF40: 40 | EG40: Монтаж оборудования | EH40: 0 | EJ40: 2 | EK40: 67 | EL40: ТСН-2001.4-8. Электротехнические установки | EM40: ТСН-2001.4-8-1 | EO40: Поправка: Гл.12.Прил.8.п.8. 3_12.00.01.11.001 | EQ40: 132096 | ER40: 45.64 | ES40: 1.46 | ET40: 17.42 | EU40: 3.16 | EV40: 26.76 | EW40: 2.06 | EX40: 0 | EY40: 0 | FQ40: 0 | FR40: 0 | FS40: 0 | FX40: 97 | FY40: 51 | GD40: 1 | GF40: -1842782186 | GG40: 2 | GH40: 1 | GI40: 2 | GJ40: 0 | GK40: 0 | GL40: =ROUND(IF(AND(BH40=3,BI40=3,FS40<>0),P40,0),2) -> 0 | GM40: =ROUND(O40+X40+Y40,2)+GX40 -> 112.6 | GN40: =IF(OR(BI40=0,BI40=1),GM40-GX40,0) -> 0 | GO40: =IF(BI40=2,GM40-GX40,0) -> 112.6 | GP40: =IF(BI40=4,GM40-GX40,0) -> 0 | GR40: 0 | GS40: 3 | GT40: 0 | GV40: =ROUND((GT40),6) -> 0 | GW40: 1 | GX40: =ROUND(HC40*I40,2) -> 0 | HA40: 0 | HB40: 0 | HC40: =GV40*GW40 -> 0 | HS40: 0 | IK40: 0
A41: 17 | B41: 1 | C41: =ROW(SmtRes!A108) -> 108 | D41: =ROW(EtalonRes!A126) -> 126 | F41: 4.8-240-4 | G41: Монтаж пультов и шкафов управления, шкафа (пульта) управления навесного, высотой, шириной, глубиной до 600х600х350 мм | H41: 1 ШТ. | I41: 1 | J41: 0 | K41: 1 | O41: =ROUND(CP41,2) -> 2346.01 | P41: =ROUND((ROUND((AC41*AW41*I41),2)*BC41),2) -> 16.13 | Q41: =(ROUND((ROUND((((ET41*1.2))*AV41*I41),2)*BB41),2)+ROUND((ROUND(((AE41-((EU41*1.2)))*AV41*I41),2)*BS41),2)) -> 435.39 | R41: =(ROUND((ROUND((((EU41*1.2))*AV41*I41),2)*BS41),2)+ROUND((ROUND(((AE41-((EU41*1.2)))*AV41*I41),2)*BS41),2)) -> 223.71 | S41: =ROUND((ROUND((AF41*AV41*I41),2)*BA41),2) -> 1894.49 | T41: =ROUND(CU41*I41,2) -> 0 | U41: =CV41*I41 -> 2.588184 | V41: =CW41*I41 -> 0 | W41: =ROUND(CX41*I41,2) -> 0 | X41: =(ROUND((((S41+ROUND((ROUND((((EU41*1.2))*AV41*I41),2)*BS41),2))*AT41)/100),2)+ROUND(((ROUND((ROUND(((AE41-((EU41*1.2)))*AV41*I41),2)*BS41),2)*AT41)/100),2)) -> 2054.65 | Y41: =(ROUND((((S41+ROUND((ROUND((((EU41*1.2))*AV41*I41),2)*BS41),2))*AU41)/100),2)+ROUND(((ROUND((ROUND(((AE41-((EU41*1.2)))*AV41*I41),2)*BS41),2)*AU41)/100),2)) -> 1080.28 | AA41: -1 | AB41: =ROUND((AC41+AD41+AF41),6) -> 54.476 | AC41: =ROUND(((ES41*1)),6) -> 1.46 | AD41: =ROUND(((((ET41*1.2))-((EU41*1.2)))+AE41),6) -> 20.904 | AE41: =ROUND(((EU41*1.2)),6) -> 3.792 | AF41: =ROUND(((EV41*1.2)),6) -> 32.112 | AG41: =ROUND((AP41),6) -> 0 | AH41: =((EW41*1.2)) -> 2.472 | AI41: =((EX41*1.2)) -> 0 | AJ41: =(AS41) -> 0 | AK41: 45.64 | AL41: 1.46 | AM41: 17.42 | AN41: 3.16 | AO41: 26.76 | AP41: 0 | AQ41: 2.06 | AR41: 0 | AS41: 0 | AT41: 97 | AU41: 51 | AV41: 1.047 | AW41: 1 | AZ41: 1 | BA41: 56.35 | BB41: 19.89 | BC41: 11.05 | BH41: 0 | BI41: 2 | BJ41: ТСН-2001.4 Доп. 80, Сб. 8, т. 240, поз. 4 | BM41: 67 | BN41: 0 | BO41: 4.8-240-4 | BP41: 1 | BQ41: 40 | BR41: 0 | BS41: 56.35 | BT41: 1 | BU41: 1 | BV41: 1 | BW41: 1 | BX41: 1 | BZ41: 97 | CA41: 51 | CE41: 1566 | CF41: 0 | CG41: 0 | CM41: 0 | CN41: Поправка: Гл.12.Прил.8.п.8. 3_12.00.01.11.001 Наименование: При наличии напряженных и стесненных условий производства работ (стесненность, сложность складирования и транспортной логистики и т.п.) для объектов, расположенных в пределах круговой магистральной системы улиц "Садовое кольцо" города Москвы | CO41: 0 | CP41: =(P41+Q41+S41) -> 2346.01 | CQ41: =ROUND((ROUND((AC41*AW41*1),2)*BC41),2) -> 16.13 | CR41: =(ROUND((ROUND((((ET41*1.2))*AV41*1),2)*BB41),2)+ROUND((ROUND(((AE41-((EU41*1.2)))*AV41*1),2)*BS41),2)) -> 435.39 | CS41: =(ROUND((ROUND((((EU41*1.2))*AV41*1),2)*BS41),2)+ROUND((ROUND(((AE41-((EU41*1.2)))*AV41*1),2)*BS41),2)) -> 223.71 | CT41: =ROUND((ROUND((AF41*AV41*1),2)*BA41),2) -> 1894.49 | CU41: =AG41 -> 0 | CV41: =(AH41*AV41) -> 2.588184 | CW41: =AI41 -> 0 | CX41: =AJ41 -> 0 | CY41: =(ROUND((((S41+ROUND((ROUND((((EU41*1.2))*AV41*1),2)*BS41),2))*AT41)/100),2)+ROUND(((ROUND((ROUND(((AE41-((EU41*1.2)))*AV41*1),2)*BS41),2)*AT41)/100),2)) -> 2054.65 | CZ41: =(ROUND((((S41+ROUND((ROUND((((EU41*1.2))*AV41*1),2)*BS41),2))*AU41)/100),2)+ROUND(((ROUND((ROUND(((AE41-((EU41*1.2)))*AV41*1),2)*BS41),2)*AU41)/100),2)) -> 1080.28 | DB41: 18 | DD41: *1 | DE41: *1,2 | DF41: *1,2 | DG41: *1,2 | DI41: *1,2 | DJ41: *1,2 | DN41: 0 | DO41: 0 | DP41: 1 | DQ41: 1 | DU41: 1013 | DV41: 1 ШТ. | DW41: 1 ШТ. | DX41: 1 | EE41: 56938734 | EF41: 40 | EG41: Монтаж оборудования | EH41: 0 | EJ41: 2 | EK41: 67 | EL41: ТСН-2001.4-8. Электротехнические установки | EM41: ТСН-2001.4-8-1 | EO41: Поправка: Гл.12.Прил.8.п.8. 3_12.00.01.11.001 | EQ41: 132096 | ER41: 45.64 | ES41: 1.46 | ET41: 17.42 | EU41: 3.16 | EV41: 26.76 | EW41: 2.06 | EX41: 0 | EY41: 0 | FQ41: 0 | FR41: 0 | FS41: 0 | FX41: 97 | FY41: 51 | GD41: 1 | GF41: -1842782186 | GG41: 2 | GH41: 1 | GI41: 2 | GJ41: 0 | GK41: 0 | GL41: =ROUND(IF(AND(BH41=3,BI41=3,FS41<>0),P41,0),2) -> 0 | GM41: =ROUND(O41+X41+Y41,2)+GX41 -> 5480.94 | GN41: =IF(OR(BI41=0,BI41=1),GM41-GX41,0) -> 0 | GO41: =IF(BI41=2,GM41-GX41,0) -> 5480.94 | GP41: =IF(BI41=4,GM41-GX41,0) -> 0 | GR41: 0 | GS41: 3 | GT41: 0 | GV41: =ROUND((GT41),6) -> 0 | GW41: 1 | GX41: =ROUND(HC41*I41,2) -> 0 | HA41: 0 | HB41: 0 | HC41: =GV41*GW41 -> 0 | HS41: 0 | IK41: 0
A42: 17 | B42: 1 | C42: =ROW(SmtRes!A119) -> 119 | D42: =ROW(EtalonRes!A138) -> 138 | E42: 3 | F42: 4.11-17-1 | G42: Монтаж щитов и пультов массой до 50кг | H42: 1 ШТ. | I42: 1 | J42: 0 | K42: 1 | O42: =ROUND(CP42,2) -> 169.84 | P42: =ROUND((ROUND((AC42*AW42*I42),2)*BC42),2) -> 89.36 | Q42: =(ROUND((ROUND((((ET42*1.2))*AV42*I42),2)*BB42),2)+ROUND((ROUND(((AE42-((EU42*1.2)))*AV42*I42),2)*BS42),2)) -> 5.36 | R42: =(ROUND((ROUND((((EU42*1.2))*AV42*I42),2)*BS42),2)+ROUND((ROUND(((AE42-((EU42*1.2)))*AV42*I42),2)*BS42),2)) -> 0.48 | S42: =ROUND((ROUND((AF42*AV42*I42),2)*BA42),2) -> 75.12 | T42: =ROUND(CU42*I42,2) -> 0 | U42: =CV42*I42 -> 6.47046 | V42: =CW42*I42 -> 0 | W42: =ROUND(CX42*I42,2) -> 0 | X42: =(ROUND((((S42+ROUND((ROUND((((EU42*1.2))*AV42*I42),2)*BS42),2))*AT42)/100),2)+ROUND(((ROUND((ROUND(((AE42-((EU42*1.2)))*AV42*I42),2)*BS42),2)*AT42)/100),2)) -> 68.04 | Y42: =(ROUND((((S42+ROUND((ROUND((((EU42*1.2))*AV42*I42),2)*BS42),2))*AU42)/100),2)+ROUND(((ROUND((ROUND(((AE42-((EU42*1.2)))*AV42*I42),2)*BS42),2)*AU42)/100),2)) -> 34.78 | AA42: 55747649 | AB42: =ROUND((AC42+AD42+AF42),6) -> 166.232 | AC42: =ROUND(((ES42*1)),6) -> 89.36 | AD42: =ROUND(((((ET42*1.2))-((EU42*1.2)))+AE42),6) -> 5.124 | AE42: =ROUND(((EU42*1.2)),6) -> 0.456 | AF42: =ROUND(((EV42*1.2)),6) -> 71.748 | AG42: =ROUND((AP42),6) -> 0 | AH42: =((EW42*1.2)) -> 6.18 | AI42: =((EX42*1.2)) -> 0 | AJ42: =(AS42) -> 0 | AK42: 153.42 | AL42: 89.36 | AM42: 4.27 | AN42: 0.38 | AO42: 59.79 | AP42: 0 | AQ42: 5.15 | AR42: 0 | AS42: 0 | AT42: 90 | AU42: 46 | AV42: 1.047 | AW42: 1 | AZ42: 1 | BA42: 1 | BB42: 1 | BC42: 1 | BH42: 0 | BI42: 2 | BJ42: ТСН-2001.4 Доп. 80, Сб. 11, т. 17, поз. 1 | BM42: 72 | BN42: 0 | BO42: 4.11-17-1 | BP42: 1 | BQ42: 40 | BR42: 0 | BS42: 1 | BT42: 1 | BU42: 1 | BV42: 1 | BW42: 1 | BX42: 1 | BZ42: 90 | CA42: 46 | CE42: 1566 | CF42: 0 | CG42: 0 | CM42: 0 | CN42: Поправка: Гл.12.Прил.8.п.8. 3_12.00.01.11.001 Наименование: При наличии напряженных и стесненных условий производства работ (стесненность, сложность складирования и транспортной логистики и т.п.) для объектов, расположенных в пределах круговой магистральной системы улиц "Садовое кольцо" города Москвы | CO42: 0 | CP42: =(P42+Q42+S42) -> 169.84 | CQ42: =ROUND((ROUND((AC42*AW42*1),2)*BC42),2) -> 89.36 | CR42: =(ROUND((ROUND((((ET42*1.2))*AV42*1),2)*BB42),2)+ROUND((ROUND(((AE42-((EU42*1.2)))*AV42*1),2)*BS42),2)) -> 5.36 | CS42: =(ROUND((ROUND((((EU42*1.2))*AV42*1),2)*BS42),2)+ROUND((ROUND(((AE42-((EU42*1.2)))*AV42*1),2)*BS42),2)) -> 0.48 | CT42: =ROUND((ROUND((AF42*AV42*1),2)*BA42),2) -> 75.12 | CU42: =AG42 -> 0 | CV42: =(AH42*AV42) -> 6.47046 | CW42: =AI42 -> 0 | CX42: =AJ42 -> 0 | CY42: =(ROUND((((S42+ROUND((ROUND((((EU42*1.2))*AV42*1),2)*BS42),2))*AT42)/100),2)+ROUND(((ROUND((ROUND(((AE42-((EU42*1.2)))*AV42*1),2)*BS42),2)*AT42)/100),2)) -> 68.04 | CZ42: =(ROUND((((S42+ROUND((ROUND((((EU42*1.2))*AV42*1),2)*BS42),2))*AU42)/100),2)+ROUND(((ROUND((ROUND(((AE42-((EU42*1.2)))*AV42*1),2)*BS42),2)*AU42)/100),2)) -> 34.78 | DB42: 19 | DD42: *1 | DE42: *1,2 | DF42: *1,2 | DG42: *1,2 | DI42: *1,2 | DJ42: *1,2 | DN42: 0 | DO42: 0 | DP42: 1 | DQ42: 1 | DU42: 1013 | DV42: 1 ШТ. | DW42: 1 ШТ. | DX42: 1 | EE42: 56938739 | EF42: 40 | EG42: Монтаж оборудования | EH42: 0 | EJ42: 2 | EK42: 72 | EL42: ТСН-2001.4-11. Приборы и средства автоматизации и вычислительной техники | EM42: ТСН-2001.4-11-1 | EO42: Поправка: Гл.12.Прил.8.п.8. 3_12.00.01.11.001 | EQ42: 0 | ER42: 153.42 | ES42: 89.36 | ET42: 4.27 | EU42: 0.38 | EV42: 59.79 | EW42: 5.15 | EX42: 0 | EY42: 0 | FQ42: 0 | FR42: 0 | FS42: 0 | FX42: 90 | FY42: 46 | GD42: 1 | GF42: 69985007 | GG42: 2 | GH42: 1 | GI42: 2 | GJ42: 0 | GK42: 0 | GL42: =ROUND(IF(AND(BH42=3,BI42=3,FS42<>0),P42,0),2) -> 0 | GM42: =ROUND(O42+X42+Y42,2)+GX42 -> 272.66 | GN42: =IF(OR(BI42=0,BI42=1),GM42-GX42,0) -> 0 | GO42: =IF(BI42=2,GM42-GX42,0) -> 272.66 | GP42: =IF(BI42=4,GM42-GX42,0) -> 0 | GR42: 0 | GS42: 3 | GT42: 0 | GV42: =ROUND((GT42),6) -> 0 | GW42: 1 | GX42: =ROUND(HC42*I42,2) -> 0 | HA42: 0 | HB42: 0 | HC42: =GV42*GW42 -> 0 | HS42: 0 | IK42: 0
A43: 17 | B43: 1 | C43: =ROW(SmtRes!A130) -> 130 | D43: =ROW(EtalonRes!A150) -> 150 | E43: 3 | F43: 4.11-17-1 | G43: Монтаж щитов и пультов массой до 50кг | H43: 1 ШТ. | I43: 1 | J43: 0 | K43: 1 | O43: =ROUND(CP43,2) -> 4716.92 | P43: =ROUND((ROUND((AC43*AW43*I43),2)*BC43),2) -> 402.12 | Q43: =(ROUND((ROUND((((ET43*1.2))*AV43*I43),2)*BB43),2)+ROUND((ROUND(((AE43-((EU43*1.2)))*AV43*I43),2)*BS43),2)) -> 81.79 | R43: =(ROUND((ROUND((((EU43*1.2))*AV43*I43),2)*BS43),2)+ROUND((ROUND(((AE43-((EU43*1.2)))*AV43*I43),2)*BS43),2)) -> 27.05 | S43: =ROUND((ROUND((AF43*AV43*I43),2)*BA43),2) -> 4233.01 | T43: =ROUND(CU43*I43,2) -> 0 | U43: =CV43*I43 -> 6.47046 | V43: =CW43*I43 -> 0 | W43: =ROUND(CX43*I43,2) -> 0 | X43: =(ROUND((((S43+ROUND((ROUND((((EU43*1.2))*AV43*I43),2)*BS43),2))*AT43)/100),2)+ROUND(((ROUND((ROUND(((AE43-((EU43*1.2)))*AV43*I43),2)*BS43),2)*AT43)/100),2)) -> 3834.05 | Y43: =(ROUND((((S43+ROUND((ROUND((((EU43*1.2))*AV43*I43),2)*BS43),2))*AU43)/100),2)+ROUND(((ROUND((ROUND(((AE43-((EU43*1.2)))*AV43*I43),2)*BS43),2)*AU43)/100),2)) -> 1959.63 | AA43: 55747651 | AB43: =ROUND((AC43+AD43+AF43),6) -> 166.232 | AC43: =ROUND(((ES43*1)),6) -> 89.36 | AD43: =ROUND(((((ET43*1.2))-((EU43*1.2)))+AE43),6) -> 5.124 | AE43: =ROUND(((EU43*1.2)),6) -> 0.456 | AF43: =ROUND(((EV43*1.2)),6) -> 71.748 | AG43: =ROUND((AP43),6) -> 0 | AH43: =((EW43*1.2)) -> 6.18 | AI43: =((EX43*1.2)) -> 0 | AJ43: =(AS43) -> 0 | AK43: 153.42 | AL43: 89.36 | AM43: 4.27 | AN43: 0.38 | AO43: 59.79 | AP43: 0 | AQ43: 5.15 | AR43: 0 | AS43: 0 | AT43: 90 | AU43: 46 | AV43: 1.047 | AW43: 1 | AZ43: 1 | BA43: 56.35 | BB43: 15.26 | BC43: 4.5 | BH43: 0 | BI43: 2 | BJ43: ТСН-2001.4 Доп. 80, Сб. 11, т. 17, поз. 1 | BM43: 72 | BN43: 0 | BO43: 4.11-17-1 | BP43: 1 | BQ43: 40 | BR43: 0 | BS43: 56.35 | BT43: 1 | BU43: 1 | BV43: 1 | BW43: 1 | BX43: 1 | BZ43: 90 | CA43: 46 | CE43: 1566 | CF43: 0 | CG43: 0 | CM43: 0 | CN43: Поправка: Гл.12.Прил.8.п.8. 3_12.00.01.11.001 Наименование: При наличии напряженных и стесненных условий производства работ (стесненность, сложность складирования и транспортной логистики и т.п.) для объектов, расположенных в пределах круговой магистральной системы улиц "Садовое кольцо" города Москвы | CO43: 0 | CP43: =(P43+Q43+S43) -> 4716.92 | CQ43: =ROUND((ROUND((AC43*AW43*1),2)*BC43),2) -> 402.12 | CR43: =(ROUND((ROUND((((ET43*1.2))*AV43*1),2)*BB43),2)+ROUND((ROUND(((AE43-((EU43*1.2)))*AV43*1),2)*BS43),2)) -> 81.79 | CS43: =(ROUND((ROUND((((EU43*1.2))*AV43*1),2)*BS43),2)+ROUND((ROUND(((AE43-((EU43*1.2)))*AV43*1),2)*BS43),2)) -> 27.05 | CT43: =ROUND((ROUND((AF43*AV43*1),2)*BA43),2) -> 4233.01 | CU43: =AG43 -> 0 | CV43: =(AH43*AV43) -> 6.47046 | CW43: =AI43 -> 0 | CX43: =AJ43 -> 0 | CY43: =(ROUND((((S43+ROUND((ROUND((((EU43*1.2))*AV43*1),2)*BS43),2))*AT43)/100),2)+ROUND(((ROUND((ROUND(((AE43-((EU43*1.2)))*AV43*1),2)*BS43),2)*AT43)/100),2)) -> 3834.05 | CZ43: =(ROUND((((S43+ROUND((ROUND((((EU43*1.2))*AV43*1),2)*BS43),2))*AU43)/100),2)+ROUND(((ROUND((ROUND(((AE43-((EU43*1.2)))*AV43*1),2)*BS43),2)*AU43)/100),2)) -> 1959.63 | DB43: 20 | DD43: *1 | DE43: *1,2 | DF43: *1,2 | DG43: *1,2 | DI43: *1,2 | DJ43: *1,2 | DN43: 0 | DO43: 0 | DP43: 1 | DQ43: 1 | DU43: 1013 | DV43: 1 ШТ. | DW43: 1 ШТ. | DX43: 1 | EE43: 56938739 | EF43: 40 | EG43: Монтаж оборудования | EH43: 0 | EJ43: 2 | EK43: 72 | EL43: ТСН-2001.4-11. Приборы и средства автоматизации и вычислительной техники | EM43: ТСН-2001.4-11-1 | EO43: Поправка: Гл.12.Прил.8.п.8. 3_12.00.01.11.001 | EQ43: 0 | ER43: 153.42 | ES43: 89.36 | ET43: 4.27 | EU43: 0.38 | EV43: 59.79 | EW43: 5.15 | EX43: 0 | EY43: 0 | FQ43: 0 | FR43: 0 | FS43: 0 | FX43: 90 | FY43: 46 | GD43: 1 | GF43: 69985007 | GG43: 2 | GH43: 1 | GI43: 2 | GJ43: 0 | GK43: 0 | GL43: =ROUND(IF(AND(BH43=3,BI43=3,FS43<>0),P43,0),2) -> 0 | GM43: =ROUND(O43+X43+Y43,2)+GX43 -> 10510.6 | GN43: =IF(OR(BI43=0,BI43=1),GM43-GX43,0) -> 0 | GO43: =IF(BI43=2,GM43-GX43,0) -> 10510.6 | GP43: =IF(BI43=4,GM43-GX43,0) -> 0 | GR43: 0 | GS43: 3 | GT43: 0 | GV43: =ROUND((GT43),6) -> 0 | GW43: 1 | GX43: =ROUND(HC43*I43,2) -> 0 | HA43: 0 | HB43: 0 | HC43: =GV43*GW43 -> 0 | HS43: 0 | IK43: 0
A44: 17 | B44: 1 | C44: =ROW(SmtRes!A131) -> 131 | D44: =ROW(EtalonRes!A153) -> 153 | E44: 4 | F44: 4.11-3-1 | G44: Установка прибора массой до 5 кг на металлоконструкциях или щитах/ выносная панель ВПИ | H44: 1 ШТ. | I44: 1 | J44: 0 | K44: 1 | O44: =ROUND(CP44,2) -> 8.48 | P44: =ROUND((ROUND((AC44*AW44*I44),2)*BC44),2) -> 0 | Q44: =(ROUND((ROUND((((ET44*1.2))*AV44*I44),2)*BB44),2)+ROUND((ROUND(((AE44-((EU44*1.2)))*AV44*I44),2)*BS44),2)) -> 0 | R44: =(ROUND((ROUND((((EU44*1.2))*AV44*I44),2)*BS44),2)+ROUND((ROUND(((AE44-((EU44*1.2)))*AV44*I44),2)*BS44),2)) -> 0 | S44: =ROUND((ROUND((AF44*AV44*I44),2)*BA44),2) -> 8.48 | T44: =ROUND(CU44*I44,2) -> 0 | U44: =CV44*I44 -> 0.653328 | V44: =CW44*I44 -> 0 | W44: =ROUND(CX44*I44,2) -> 0 | X44: =(ROUND((((S44+ROUND((ROUND((((EU44*1.2))*AV44*I44),2)*BS44),2))*AT44)/100),2)+ROUND(((ROUND((ROUND(((AE44-((EU44*1.2)))*AV44*I44),2)*BS44),2)*AT44)/100),2)) -> 7.63 | Y44: =(ROUND((((S44+ROUND((ROUND((((EU44*1.2))*AV44*I44),2)*BS44),2))*AU44)/100),2)+ROUND(((ROUND((ROUND(((AE44-((EU44*1.2)))*AV44*I44),2)*BS44),2)*AU44)/100),2)) -> 3.9 | AA44: 55747649 | AB44: =ROUND((AC44+AD44+AF44),6) -> 8.1 | AC44: =ROUND(((ES44*1)),6) -> 0 | AD44: =ROUND(((((ET44*1.2))-((EU44*1.2)))+AE44),6) -> 0 | AE44: =ROUND(((EU44*1.2)),6) -> 0 | AF44: =ROUND(((EV44*1.2)),6) -> 8.1 | AG44: =ROUND((AP44),6) -> 0 | AH44: =((EW44*1.2)) -> 0.624 | AI44: =((EX44*1.2)) -> 0 | AJ44: =(AS44) -> 0 | AK44: 6.75 | AL44: 0 | AM44: 0 | AN44: 0 | AO44: 6.75 | AP44: 0 | AQ44: 0.52 | AR44: 0 | AS44: 0 | AT44: 90 | AU44: 46 | AV44: 1.047 | AW44: 1 | AZ44: 1 | BA44: 1 | BB44: 1 | BC44: 1 | BH44: 0 | BI44: 2 | BJ44: ТСН-2001.4 Доп. 67, Сб. 11, т. 3, поз. 1 | BM44: 72 | BN44: 0 | BO44: 4.11-3-1 | BP44: 1 | BQ44: 40 | BR44: 0 | BS44: 1 | BT44: 1 | BU44: 1 | BV44: 1 | BW44: 1 | BX44: 1 | BZ44: 90 | CA44: 46 | CE44: 1566 | CF44: 0 | CG44: 0 | CM44: 0 | CN44: Поправка: Гл.12.Прил.8.п.8. 3_12.00.01.11.001 Наименование: При наличии напряженных и стесненных условий производства работ (стесненность, сложность складирования и транспортной логистики и т.п.) для объектов, расположенных в пределах круговой магистральной системы улиц "Садовое кольцо" города Москвы | CO44: 0 | CP44: =(P44+Q44+S44) -> 8.48 | CQ44: =ROUND((ROUND((AC44*AW44*1),2)*BC44),2) -> 0 | CR44: =(ROUND((ROUND((((ET44*1.2))*AV44*1),2)*BB44),2)+ROUND((ROUND(((AE44-((EU44*1.2)))*AV44*1),2)*BS44),2)) -> 0 | CS44: =(ROUND((ROUND((((EU44*1.2))*AV44*1),2)*BS44),2)+ROUND((ROUND(((AE44-((EU44*1.2)))*AV44*1),2)*BS44),2)) -> 0 | CT44: =ROUND((ROUND((AF44*AV44*1),2)*BA44),2) -> 8.48 | CU44: =AG44 -> 0 | CV44: =(AH44*AV44) -> 0.653328 | CW44: =AI44 -> 0 | CX44: =AJ44 -> 0 | CY44: =(ROUND((((S44+ROUND((ROUND((((EU44*1.2))*AV44*1),2)*BS44),2))*AT44)/100),2)+ROUND(((ROUND((ROUND(((AE44-((EU44*1.2)))*AV44*1),2)*BS44),2)*AT44)/100),2)) -> 7.63 | CZ44: =(ROUND((((S44+ROUND((ROUND((((EU44*1.2))*AV44*1),2)*BS44),2))*AU44)/100),2)+ROUND(((ROUND((ROUND(((AE44-((EU44*1.2)))*AV44*1),2)*BS44),2)*AU44)/100),2)) -> 3.9 | DB44: 21 | DD44: *1 | DE44: *1,2 | DF44: *1,2 | DG44: *1,2 | DI44: *1,2 | DJ44: *1,2 | DN44: 0 | DO44: 0 | DP44: 1 | DQ44: 1 | DU44: 1013 | DV44: 1 ШТ. | DW44: 1 ШТ. | DX44: 1 | EE44: 56938739 | EF44: 40 | EG44: Монтаж оборудования | EH44: 0 | EJ44: 2 | EK44: 72 | EL44: ТСН-2001.4-11. Приборы и средства автоматизации и вычислительной техники | EM44: ТСН-2001.4-11-1 | EO44: Поправка: Гл.12.Прил.8.п.8. 3_12.00.01.11.001 | EQ44: 0 | ER44: 6.75 | ES44: 0 | ET44: 0 | EU44: 0 | EV44: 6.75 | EW44: 0.52 | EX44: 0 | EY44: 0 | FQ44: 0 | FR44: 0 | FS44: 0 | FX44: 90 | FY44: 46 | GD44: 1 | GF44: -1400951207 | GG44: 2 | GH44: 1 | GI44: 2 | GJ44: 0 | GK44: 0 | GL44: =ROUND(IF(AND(BH44=3,BI44=3,FS44<>0),P44,0),2) -> 0 | GM44: =ROUND(O44+X44+Y44,2)+GX44 -> 20.01 | GN44: =IF(OR(BI44=0,BI44=1),GM44-GX44,0) -> 0 | GO44: =IF(BI44=2,GM44-GX44,0) -> 20.01 | GP44: =IF(BI44=4,GM44-GX44,0) -> 0 | GR44: 0 | GS44: 3 | GT44: 0 | GV44: =ROUND((GT44),6) -> 0 | GW44: 1 | GX44: =ROUND(HC44*I44,2) -> 0 | HA44: 0 | HB44: 0 | HC44: =GV44*GW44 -> 0 | HS44: 0 | IK44: 0
A45: 17 | B45: 1 | C45: =ROW(SmtRes!A132) -> 132 | D45: =ROW(EtalonRes!A156) -> 156 | E45: 4 | F45: 4.11-3-1 | G45: Установка прибора массой до 5 кг на металлоконструкциях или щитах/ выносная панель ВПИ | H45: 1 ШТ. | I45: 1 | J45: 0 | K45: 1 | O45: =ROUND(CP45,2) -> 477.85 | P45: =ROUND((ROUND((AC45*AW45*I45),2)*BC45),2) -> 0 | Q45: =(ROUND((ROUND((((ET45*1.2))*AV45*I45),2)*BB45),2)+ROUND((ROUND(((AE45-((EU45*1.2)))*AV45*I45),2)*BS45),2)) -> 0 | R45: =(ROUND((ROUND((((EU45*1.2))*AV45*I45),2)*BS45),2)+ROUND((ROUND(((AE45-((EU45*1.2)))*AV45*I45),2)*BS45),2)) -> 0 | S45: =ROUND((ROUND((AF45*AV45*I45),2)*BA45),2) -> 477.85 | T45: =ROUND(CU45*I45,2) -> 0 | U45: =CV45*I45 -> 0.653328 | V45: =CW45*I45 -> 0 | W45: =ROUND(CX45*I45,2) -> 0 | X45: =(ROUND((((S45+ROUND((ROUND((((EU45*1.2))*AV45*I45),2)*BS45),2))*AT45)/100),2)+ROUND(((ROUND((ROUND(((AE45-((EU45*1.2)))*AV45*I45),2)*BS45),2)*AT45)/100),2)) -> 430.07 | Y45: =(ROUND((((S45+ROUND((ROUND((((EU45*1.2))*AV45*I45),2)*BS45),2))*AU45)/100),2)+ROUND(((ROUND((ROUND(((AE45-((EU45*1.2)))*AV45*I45),2)*BS45),2)*AU45)/100),2)) -> 219.81 | AA45: 55747651 | AB45: =ROUND((AC45+AD45+AF45),6) -> 8.1 | AC45: =ROUND(((ES45*1)),6) -> 0 | AD45: =ROUND(((((ET45*1.2))-((EU45*1.2)))+AE45),6) -> 0 | AE45: =ROUND(((EU45*1.2)),6) -> 0 | AF45: =ROUND(((EV45*1.2)),6) -> 8.1 | AG45: =ROUND((AP45),6) -> 0 | AH45: =((EW45*1.2)) -> 0.624 | AI45: =((EX45*1.2)) -> 0 | AJ45: =(AS45) -> 0 | AK45: 6.75 | AL45: 0 | AM45: 0 | AN45: 0 | AO45: 6.75 | AP45: 0 | AQ45: 0.52 | AR45: 0 | AS45: 0 | AT45: 90 | AU45: 46 | AV45: 1.047 | AW45: 1 | AZ45: 1 | BA45: 56.35 | BB45: 1 | BC45: 1 | BH45: 0 | BI45: 2 | BJ45: ТСН-2001.4 Доп. 67, Сб. 11, т. 3, поз. 1 | BM45: 72 | BN45: 0 | BO45: 4.11-3-1 | BP45: 1 | BQ45: 40 | BR45: 0 | BS45: 56.35 | BT45: 1 | BU45: 1 | BV45: 1 | BW45: 1 | BX45: 1 | BZ45: 90 | CA45: 46 | CE45: 1566 | CF45: 0 | CG45: 0 | CM45: 0 | CN45: Поправка: Гл.12.Прил.8.п.8. 3_12.00.01.11.001 Наименование: При наличии напряженных и стесненных условий производства работ (стесненность, сложность складирования и транспортной логистики и т.п.) для объектов, расположенных в пределах круговой магистральной системы улиц "Садовое кольцо" города Москвы | CO45: 0 | CP45: =(P45+Q45+S45) -> 477.85 | CQ45: =ROUND((ROUND((AC45*AW45*1),2)*BC45),2) -> 0 | CR45: =(ROUND((ROUND((((ET45*1.2))*AV45*1),2)*BB45),2)+ROUND((ROUND(((AE45-((EU45*1.2)))*AV45*1),2)*BS45),2)) -> 0 | CS45: =(ROUND((ROUND((((EU45*1.2))*AV45*1),2)*BS45),2)+ROUND((ROUND(((AE45-((EU45*1.2)))*AV45*1),2)*BS45),2)) -> 0 | CT45: =ROUND((ROUND((AF45*AV45*1),2)*BA45),2) -> 477.85 | CU45: =AG45 -> 0 | CV45: =(AH45*AV45) -> 0.653328 | CW45: =AI45 -> 0 | CX45: =AJ45 -> 0 | CY45: =(ROUND((((S45+ROUND((ROUND((((EU45*1.2))*AV45*1),2)*BS45),2))*AT45)/100),2)+ROUND(((ROUND((ROUND(((AE45-((EU45*1.2)))*AV45*1),2)*BS45),2)*AT45)/100),2)) -> 430.07 | CZ45: =(ROUND((((S45+ROUND((ROUND((((EU45*1.2))*AV45*1),2)*BS45),2))*AU45)/100),2)+ROUND(((ROUND((ROUND(((AE45-((EU45*1.2)))*AV45*1),2)*BS45),2)*AU45)/100),2)) -> 219.81 | DB45: 22 | DD45: *1 | DE45: *1,2 | DF45: *1,2 | DG45: *1,2 | DI45: *1,2 | DJ45: *1,2 | DN45: 0 | DO45: 0 | DP45: 1 | DQ45: 1 | DU45: 1013 | DV45: 1 ШТ. | DW45: 1 ШТ. | DX45: 1 | EE45: 56938739 | EF45: 40 | EG45: Монтаж оборудования | EH45: 0 | EJ45: 2 | EK45: 72 | EL45: ТСН-2001.4-11. Приборы и средства автоматизации и вычислительной техники | EM45: ТСН-2001.4-11-1 | EO45: Поправка: Гл.12.Прил.8.п.8. 3_12.00.01.11.001 | EQ45: 0 | ER45: 6.75 | ES45: 0 | ET45: 0 | EU45: 0 | EV45: 6.75 | EW45: 0.52 | EX45: 0 | EY45: 0 | FQ45: 0 | FR45: 0 | FS45: 0 | FX45: 90 | FY45: 46 | GD45: 1 | GF45: -1400951207 | GG45: 2 | GH45: 1 | GI45: 2 | GJ45: 0 | GK45: 0 | GL45: =ROUND(IF(AND(BH45=3,BI45=3,FS45<>0),P45,0),2) -> 0 | GM45: =ROUND(O45+X45+Y45,2)+GX45 -> 1127.73 | GN45: =IF(OR(BI45=0,BI45=1),GM45-GX45,0) -> 0 | GO45: =IF(BI45=2,GM45-GX45,0) -> 1127.73 | GP45: =IF(BI45=4,GM45-GX45,0) -> 0 | GR45: 0 | GS45: 3 | GT45: 0 | GV45: =ROUND((GT45),6) -> 0 | GW45: 1 | GX45: =ROUND(HC45*I45,2) -> 0 | HA45: 0 | HB45: 0 | HC45: =GV45*GW45 -> 0 | HS45: 0 | IK45: 0
A46: 17 | B46: 1 | C46: =ROW(SmtRes!A135) -> 135 | D46: =ROW(EtalonRes!A161) -> 161 | F46: 4.12-48-9 | G46: Монтаж арматуры фланцевой с ручным приводом или без привода на номинальное давление до 4 МПа, номинальный диаметр прохода 80 мм (обратный клапан, затвор поворотный) | H46: 1 ШТ. | I46: =ROUND(2+4,9) -> 6 | J46: 0 | K46: =ROUND(2+4,9) -> 6 | O46: =ROUND(CP46,2) -> 417.65 | P46: =ROUND((ROUND((AC46*AW46*I46),2)*BC46),2) -> 17.09 | Q46: =(ROUND((ROUND((((ET46*1.2))*AV46*I46),2)*BB46),2)+ROUND((ROUND(((AE46-((EU46*1.2)))*AV46*I46),2)*BS46),2)) -> 12.75 | R46: =(ROUND((ROUND((((EU46*1.2))*AV46*I46),2)*BS46),2)+ROUND((ROUND(((AE46-((EU46*1.2)))*AV46*I46),2)*BS46),2)) -> 1.92 | S46: =ROUND((ROUND((AF46*AV46*I46),2)*BA46),2) -> 387.81 | T46: =ROUND(CU46*I46,2) -> 0 | U46: =CV46*I46 -> 30.7296 | V46: =CW46*I46 -> 0 | W46: =ROUND(CX46*I46,2) -> 0 | X46: =(ROUND((((S46+ROUND((ROUND((((EU46*1.2))*AV46*I46),2)*BS46),2))*AT46)/100),2)+ROUND(((ROUND((ROUND(((AE46-((EU46*1.2)))*AV46*I46),2)*BS46),2)*AT46)/100),2)) -> 350.76 | Y46: =(ROUND((((S46+ROUND((ROUND((((EU46*1.2))*AV46*I46),2)*BS46),2))*AU46)/100),2)+ROUND(((ROUND((ROUND(((AE46-((EU46*1.2)))*AV46*I46),2)*BS46),2)*AU46)/100),2)) -> 179.28 | AA46: -1 | AB46: =ROUND((AC46+AD46+AF46),6) -> 65.338 | AC46: =ROUND(((ES46*1)),6) -> 2.77 | AD46: =ROUND(((((ET46*1.2))-((EU46*1.2)))+AE46),6) -> 1.992 | AE46: =ROUND(((EU46*1.2)),6) -> 0.3 | AF46: =ROUND(((EV46*1.2)),6) -> 60.576 | AG46: =ROUND((AP46),6) -> 0 | AH46: =((EW46*1.2)) -> 4.8 | AI46: =((EX46*1.2)) -> 0 | AJ46: =(AS46) -> 0 | AK46: 54.91 | AL46: 2.77 | AM46: 1.66 | AN46: 0.25 | AO46: 50.48 | AP46: 0 | AQ46: 4 | AR46: 0 | AS46: 0 | AT46: 90 | AU46: 46 | AV46: 1.067 | AW46: 1.028 | AZ46: 1 | BA46: 1 | BB46: 1 | BC46: 1 | BH46: 0 | BI46: 2 | BJ46: ТСН-2001.4 Доп. 68, Сб. 12, т. 48, поз. 9 | BM46: 73 | BN46: 0 | BO46: 4.12-48-9 | BP46: 1 | BQ46: 40 | BR46: 0 | BS46: 1 | BT46: 1 | BU46: 1 | BV46: 1 | BW46: 1 | BX46: 1 | BZ46: 90 | CA46: 46 | CE46: 1566 | CF46: 0 | CG46: 0 | CM46: 0 | CN46: Поправка: Гл.12.Прил.8.п.8. 3_12.00.01.11.001 Наименование: При наличии напряженных и стесненных условий производства работ (стесненность, сложность складирования и транспортной логистики и т.п.) для объектов, расположенных в пределах круговой магистральной системы улиц "Садовое кольцо" города Москвы | CO46: 0 | CP46: =(P46+Q46+S46) -> 417.65 | CQ46: =ROUND((ROUND((AC46*AW46*1),2)*BC46),2) -> 2.85 | CR46: =(ROUND((ROUND((((ET46*1.2))*AV46*1),2)*BB46),2)+ROUND((ROUND(((AE46-((EU46*1.2)))*AV46*1),2)*BS46),2)) -> 2.13 | CS46: =(ROUND((ROUND((((EU46*1.2))*AV46*1),2)*BS46),2)+ROUND((ROUND(((AE46-((EU46*1.2)))*AV46*1),2)*BS46),2)) -> 0.32 | CT46: =ROUND((ROUND((AF46*AV46*1),2)*BA46),2) -> 64.63 | CU46: =AG46 -> 0 | CV46: =(AH46*AV46) -> 5.1216 | CW46: =AI46 -> 0 | CX46: =AJ46 -> 0 | CY46: =(ROUND((((S46+ROUND((ROUND((((EU46*1.2))*AV46*1),2)*BS46),2))*AT46)/100),2)+ROUND(((ROUND((ROUND(((AE46-((EU46*1.2)))*AV46*1),2)*BS46),2)*AT46)/100),2)) -> 349.32 | CZ46: =(ROUND((((S46+ROUND((ROUND((((EU46*1.2))*AV46*1),2)*BS46),2))*AU46)/100),2)+ROUND(((ROUND((ROUND(((AE46-((EU46*1.2)))*AV46*1),2)*BS46),2)*AU46)/100),2)) -> 178.54 | DB46: 23 | DD46: *1 | DE46: *1,2 | DF46: *1,2 | DG46: *1,2 | DI46: *1,2 | DJ46: *1,2 | DN46: 0 | DO46: 0 | DP46: 1 | DQ46: 1 | DU46: 1013 | DV46: 1 ШТ. | DW46: 1 ШТ. | DX46: 1 | EE46: 56938740 | EF46: 40 | EG46: Монтаж оборудования | EH46: 0 | EJ46: 2 | EK46: 73 | EL46: ТСН-2001.4-12. Технологические трубопроводы | EM46: ТСН-2001.4-12-1 | EO46: Поправка: Гл.12.Прил.8.п.8. 3_12.00.01.11.001 | EQ46: 132096 | ER46: 54.91 | ES46: 2.77 | ET46: 1.66 | EU46: 0.25 | EV46: 50.48 | EW46: 4 | EX46: 0 | EY46: 0 | FQ46: 0 | FR46: 0 | FS46: 2 | FX46: 90 | FY46: 46 | GD46: 1 | GF46: 742127146 | GG46: 2 | GH46: 1 | GI46: 2 | GJ46: 0 | GK46: 0 | GL46: =ROUND(IF(AND(BH46=3,BI46=3,FS46<>0),P46,0),2) -> 0 | GM46: =ROUND(O46+X46+Y46,2)+GX46 -> 947.69 | GN46: =IF(OR(BI46=0,BI46=1),GM46-GX46,0) -> 0 | GO46: =IF(BI46=2,GM46-GX46,0) -> 947.69 | GP46: =IF(BI46=4,GM46-GX46,0) -> 0 | GR46: 0 | GS46: 3 | GT46: 0 | GV46: =ROUND((GT46),6) -> 0 | GW46: 1 | GX46: =ROUND(HC46*I46,2) -> 0 | HA46: 0 | HB46: 0 | HC46: =GV46*GW46 -> 0 | HS46: 0 | IK46: 0
A47: 17 | B47: 1 | C47: =ROW(SmtRes!A138) -> 138 | D47: =ROW(EtalonRes!A166) -> 166 | F47: 4.12-48-9 | G47: Монтаж арматуры фланцевой с ручным приводом или без привода на номинальное давление до 4 МПа, номинальный диаметр прохода 80 мм (обратный клапан, затвор поворотный) | H47: 1 ШТ. | I47: =ROUND(2+4,9) -> 6 | J47: 0 | K47: =ROUND(2+4,9) -> 6 | O47: =ROUND(CP47,2) -> 22147.9 | P47: =ROUND((ROUND((AC47*AW47*I47),2)*BC47),2) -> 76.91 | Q47: =(ROUND((ROUND((((ET47*1.2))*AV47*I47),2)*BB47),2)+ROUND((ROUND(((AE47-((EU47*1.2)))*AV47*I47),2)*BS47),2)) -> 217.9 | R47: =(ROUND((ROUND((((EU47*1.2))*AV47*I47),2)*BS47),2)+ROUND((ROUND(((AE47-((EU47*1.2)))*AV47*I47),2)*BS47),2)) -> 108.19 | S47: =ROUND((ROUND((AF47*AV47*I47),2)*BA47),2) -> 21853.09 | T47: =ROUND(CU47*I47,2) -> 0 | U47: =CV47*I47 -> 30.7296 | V47: =CW47*I47 -> 0 | W47: =ROUND(CX47*I47,2) -> 0 | X47: =(ROUND((((S47+ROUND((ROUND((((EU47*1.2))*AV47*I47),2)*BS47),2))*AT47)/100),2)+ROUND(((ROUND((ROUND(((AE47-((EU47*1.2)))*AV47*I47),2)*BS47),2)*AT47)/100),2)) -> 19765.15 | Y47: =(ROUND((((S47+ROUND((ROUND((((EU47*1.2))*AV47*I47),2)*BS47),2))*AU47)/100),2)+ROUND(((ROUND((ROUND(((AE47-((EU47*1.2)))*AV47*I47),2)*BS47),2)*AU47)/100),2)) -> 10102.19 | AA47: -1 | AB47: =ROUND((AC47+AD47+AF47),6) -> 65.338 | AC47: =ROUND(((ES47*1)),6) -> 2.77 | AD47: =ROUND(((((ET47*1.2))-((EU47*1.2)))+AE47),6) -> 1.992 | AE47: =ROUND(((EU47*1.2)),6) -> 0.3 | AF47: =ROUND(((EV47*1.2)),6) -> 60.576 | AG47: =ROUND((AP47),6) -> 0 | AH47: =((EW47*1.2)) -> 4.8 | AI47: =((EX47*1.2)) -> 0 | AJ47: =(AS47) -> 0 | AK47: 54.91 | AL47: 2.77 | AM47: 1.66 | AN47: 0.25 | AO47: 50.48 | AP47: 0 | AQ47: 4 | AR47: 0 | AS47: 0 | AT47: 90 | AU47: 46 | AV47: 1.067 | AW47: 1.028 | AZ47: 1 | BA47: 56.35 | BB47: 17.09 | BC47: 4.5 | BH47: 0 | BI47: 2 | BJ47: ТСН-2001.4 Доп. 68, Сб. 12, т. 48, поз. 9 | BM47: 73 | BN47: 0 | BO47: 4.12-48-9 | BP47: 1 | BQ47: 40 | BR47: 0 | BS47: 56.35 | BT47: 1 | BU47: 1 | BV47: 1 | BW47: 1 | BX47: 1 | BZ47: 90 | CA47: 46 | CE47: 1566 | CF47: 0 | CG47: 0 | CM47: 0 | CN47: Поправка: Гл.12.Прил.8.п.8. 3_12.00.01.11.001 Наименование: При наличии напряженных и стесненных условий производства работ (стесненность, сложность складирования и транспортной логистики и т.п.) для объектов, расположенных в пределах круговой магистральной системы улиц "Садовое кольцо" города Москвы | CO47: 0 | CP47: =(P47+Q47+S47) -> 22147.9 | CQ47: =ROUND((ROUND((AC47*AW47*1),2)*BC47),2) -> 12.83 | CR47: =(ROUND((ROUND((((ET47*1.2))*AV47*1),2)*BB47),2)+ROUND((ROUND(((AE47-((EU47*1.2)))*AV47*1),2)*BS47),2)) -> 36.4 | CS47: =(ROUND((ROUND((((EU47*1.2))*AV47*1),2)*BS47),2)+ROUND((ROUND(((AE47-((EU47*1.2)))*AV47*1),2)*BS47),2)) -> 18.03 | CT47: =ROUND((ROUND((AF47*AV47*1),2)*BA47),2) -> 3641.9 | CU47: =AG47 -> 0 | CV47: =(AH47*AV47) -> 5.1216 | CW47: =AI47 -> 0 | CX47: =AJ47 -> 0 | CY47: =(ROUND((((S47+ROUND((ROUND((((EU47*1.2))*AV47*1),2)*BS47),2))*AT47)/100),2)+ROUND(((ROUND((ROUND(((AE47-((EU47*1.2)))*AV47*1),2)*BS47),2)*AT47)/100),2)) -> 19684.01 | CZ47: =(ROUND((((S47+ROUND((ROUND((((EU47*1.2))*AV47*1),2)*BS47),2))*AU47)/100),2)+ROUND(((ROUND((ROUND(((AE47-((EU47*1.2)))*AV47*1),2)*BS47),2)*AU47)/100),2)) -> 10060.72 | DB47: 24 | DD47: *1 | DE47: *1,2 | DF47: *1,2 | DG47: *1,2 | DI47: *1,2 | DJ47: *1,2 | DN47: 0 | DO47: 0 | DP47: 1 | DQ47: 1 | DU47: 1013 | DV47: 1 ШТ. | DW47: 1 ШТ. | DX47: 1 | EE47: 56938740 | EF47: 40 | EG47: Монтаж оборудования | EH47: 0 | EJ47: 2 | EK47: 73 | EL47: ТСН-2001.4-12. Технологические трубопроводы | EM47: ТСН-2001.4-12-1 | EO47: Поправка: Гл.12.Прил.8.п.8. 3_12.00.01.11.001 | EQ47: 132096 | ER47: 54.91 | ES47: 2.77 | ET47: 1.66 | EU47: 0.25 | EV47: 50.48 | EW47: 4 | EX47: 0 | EY47: 0 | FQ47: 0 | FR47: 0 | FS47: 2 | FX47: 90 | FY47: 46 | GD47: 1 | GF47: 742127146 | GG47: 2 | GH47: 1 | GI47: 2 | GJ47: 0 | GK47: 0 | GL47: =ROUND(IF(AND(BH47=3,BI47=3,FS47<>0),P47,0),2) -> 0 | GM47: =ROUND(O47+X47+Y47,2)+GX47 -> 52015.24 | GN47: =IF(OR(BI47=0,BI47=1),GM47-GX47,0) -> 0 | GO47: =IF(BI47=2,GM47-GX47,0) -> 52015.24 | GP47: =IF(BI47=4,GM47-GX47,0) -> 0 | GR47: 0 | GS47: 3 | GT47: 0 | GV47: =ROUND((GT47),6) -> 0 | GW47: 1 | GX47: =ROUND(HC47*I47,2) -> 0 | HA47: 0 | HB47: 0 | HC47: =GV47*GW47 -> 0 | HS47: 0 | IK47: 0
A48: 17 | B48: 1 | C48: =ROW(SmtRes!A141) -> 141 | D48: =ROW(EtalonRes!A171) -> 171 | F48: 4.12-48-11 | G48: Монтаж арматуры фланцевой с ручным приводом или без привода на номинальное давление до 4 МПа, номинальный диаметр прохода 125 мм (затвор поворотный разделительный) | H48: 1 ШТ. | I48: =ROUND(2,9) -> 2 | J48: 0 | K48: =ROUND(2,9) -> 2 | O48: =ROUND(CP48,2) -> 191.1 | P48: =ROUND((ROUND((AC48*AW48*I48),2)*BC48),2) -> 8.08 | Q48: =(ROUND((ROUND((((ET48*1.2))*AV48*I48),2)*BB48),2)+ROUND((ROUND(((AE48-((EU48*1.2)))*AV48*I48),2)*BS48),2)) -> 8.5 | R48: =(ROUND((ROUND((((EU48*1.2))*AV48*I48),2)*BS48),2)+ROUND((ROUND(((AE48-((EU48*1.2)))*AV48*I48),2)*BS48),2)) -> 1.28 | S48: =ROUND((ROUND((AF48*AV48*I48),2)*BA48),2) -> 174.52 | T48: =ROUND(CU48*I48,2) -> 0 | U48: =CV48*I48 -> 13.82832 | V48: =CW48*I48 -> 0 | W48: =ROUND(CX48*I48,2) -> 0 | X48: =(ROUND((((S48+ROUND((ROUND((((EU48*1.2))*AV48*I48),2)*BS48),2))*AT48)/100),2)+ROUND(((ROUND((ROUND(((AE48-((EU48*1.2)))*AV48*I48),2)*BS48),2)*AT48)/100),2)) -> 158.22 | Y48: =(ROUND((((S48+ROUND((ROUND((((EU48*1.2))*AV48*I48),2)*BS48),2))*AU48)/100),2)+ROUND(((ROUND((ROUND(((AE48-((EU48*1.2)))*AV48*I48),2)*BS48),2)*AU48)/100),2)) -> 80.87 | AA48: -1 | AB48: =ROUND((AC48+AD48+AF48),6) -> 89.694 | AC48: =ROUND(((ES48*1)),6) -> 3.93 | AD48: =ROUND(((((ET48*1.2))-((EU48*1.2)))+AE48),6) -> 3.984 | AE48: =ROUND(((EU48*1.2)),6) -> 0.6 | AF48: =ROUND(((EV48*1.2)),6) -> 81.78 | AG48: =ROUND((AP48),6) -> 0 | AH48: =((EW48*1.2)) -> 6.48 | AI48: =((EX48*1.2)) -> 0 | AJ48: =(AS48) -> 0 | AK48: 75.4 | AL48: 3.93 | AM48: 3.32 | AN48: 0.5 | AO48: 68.15 | AP48: 0 | AQ48: 5.4 | AR48: 0 | AS48: 0 | AT48: 90 | AU48: 46 | AV48: 1.067 | AW48: 1.028 | AZ48: 1 | BA48: 1 | BB48: 1 | BC48: 1 | BH48: 0 | BI48: 2 | BJ48: ТСН-2001.4 Доп. 68, Сб. 12, т. 48, поз. 11 | BM48: 73 | BN48: 0 | BO48: 4.12-48-11 | BP48: 1 | BQ48: 40 | BR48: 0 | BS48: 1 | BT48: 1 | BU48: 1 | BV48: 1 | BW48: 1 | BX48: 1 | BZ48: 90 | CA48: 46 | CE48: 1566 | CF48: 0 | CG48: 0 | CM48: 0 | CN48: Поправка: Гл.12.Прил.8.п.8. 3_12.00.01.11.001 Наименование: При наличии напряженных и стесненных условий производства работ (стесненность, сложность складирования и транспортной логистики и т.п.) для объектов, расположенных в пределах круговой магистральной системы улиц "Садовое кольцо" города Москвы | CO48: 0 | CP48: =(P48+Q48+S48) -> 191.1 | CQ48: =ROUND((ROUND((AC48*AW48*1),2)*BC48),2) -> 4.04 | CR48: =(ROUND((ROUND((((ET48*1.2))*AV48*1),2)*BB48),2)+ROUND((ROUND(((AE48-((EU48*1.2)))*AV48*1),2)*BS48),2)) -> 4.25 | CS48: =(ROUND((ROUND((((EU48*1.2))*AV48*1),2)*BS48),2)+ROUND((ROUND(((AE48-((EU48*1.2)))*AV48*1),2)*BS48),2)) -> 0.64 | CT48: =ROUND((ROUND((AF48*AV48*1),2)*BA48),2) -> 87.26 | CU48: =AG48 -> 0 | CV48: =(AH48*AV48) -> 6.91416 | CW48: =AI48 -> 0 | CX48: =AJ48 -> 0 | CY48: =(ROUND((((S48+ROUND((ROUND((((EU48*1.2))*AV48*1),2)*BS48),2))*AT48)/100),2)+ROUND(((ROUND((ROUND(((AE48-((EU48*1.2)))*AV48*1),2)*BS48),2)*AT48)/100),2)) -> 157.64 | CZ48: =(ROUND((((S48+ROUND((ROUND((((EU48*1.2))*AV48*1),2)*BS48),2))*AU48)/100),2)+ROUND(((ROUND((ROUND(((AE48-((EU48*1.2)))*AV48*1),2)*BS48),2)*AU48)/100),2)) -> 80.57 | DB48: 25 | DD48: *1 | DE48: *1,2 | DF48: *1,2 | DG48: *1,2 | DI48: *1,2 | DJ48: *1,2 | DN48: 0 | DO48: 0 | DP48: 1 | DQ48: 1 | DU48: 1013 | DV48: 1 ШТ. | DW48: 1 ШТ. | DX48: 1 | EE48: 56938740 | EF48: 40 | EG48: Монтаж оборудования | EH48: 0 | EJ48: 2 | EK48: 73 | EL48: ТСН-2001.4-12. Технологические трубопроводы | EM48: ТСН-2001.4-12-1 | EO48: Поправка: Гл.12.Прил.8.п.8. 3_12.00.01.11.001 | EQ48: 132096 | ER48: 75.4 | ES48: 3.93 | ET48: 3.32 | EU48: 0.5 | EV48: 68.15 | EW48: 5.4 | EX48: 0 | EY48: 0 | FQ48: 0 | FR48: 0 | FS48: 2 | FX48: 90 | FY48: 46 | GD48: 1 | GF48: 434457661 | GG48: 2 | GH48: 1 | GI48: 2 | GJ48: 0 | GK48: 0 | GL48: =ROUND(IF(AND(BH48=3,BI48=3,FS48<>0),P48,0),2) -> 0 | GM48: =ROUND(O48+X48+Y48,2)+GX48 -> 430.19 | GN48: =IF(OR(BI48=0,BI48=1),GM48-GX48,0) -> 0 | GO48: =IF(BI48=2,GM48-GX48,0) -> 430.19 | GP48: =IF(BI48=4,GM48-GX48,0) -> 0 | GR48: 0 | GS48: 3 | GT48: 0 | GV48: =ROUND((GT48),6) -> 0 | GW48: 1 | GX48: =ROUND(HC48*I48,2) -> 0 | HA48: 0 | HB48: 0 | HC48: =GV48*GW48 -> 0 | HS48: 0 | IK48: 0
A49: 17 | B49: 1 | C49: =ROW(SmtRes!A144) -> 144 | D49: =ROW(EtalonRes!A176) -> 176 | F49: 4.12-48-11 | G49: Монтаж арматуры фланцевой с ручным приводом или без привода на номинальное давление до 4 МПа, номинальный диаметр прохода 125 мм (затвор поворотный разделительный) | H49: 1 ШТ. | I49: =ROUND(2,9) -> 2 | J49: 0 | K49: =ROUND(2,9) -> 2 | O49: =ROUND(CP49,2) -> 10015.75 | P49: =ROUND((ROUND((AC49*AW49*I49),2)*BC49),2) -> 36.28 | Q49: =(ROUND((ROUND((((ET49*1.2))*AV49*I49),2)*BB49),2)+ROUND((ROUND(((AE49-((EU49*1.2)))*AV49*I49),2)*BS49),2)) -> 145.27 | R49: =(ROUND((ROUND((((EU49*1.2))*AV49*I49),2)*BS49),2)+ROUND((ROUND(((AE49-((EU49*1.2)))*AV49*I49),2)*BS49),2)) -> 72.13 | S49: =ROUND((ROUND((AF49*AV49*I49),2)*BA49),2) -> 9834.2 | T49: =ROUND(CU49*I49,2) -> 0 | U49: =CV49*I49 -> 13.82832 | V49: =CW49*I49 -> 0 | W49: =ROUND(CX49*I49,2) -> 0 | X49: =(ROUND((((S49+ROUND((ROUND((((EU49*1.2))*AV49*I49),2)*BS49),2))*AT49)/100),2)+ROUND(((ROUND((ROUND(((AE49-((EU49*1.2)))*AV49*I49),2)*BS49),2)*AT49)/100),2)) -> 8915.7 | Y49: =(ROUND((((S49+ROUND((ROUND((((EU49*1.2))*AV49*I49),2)*BS49),2))*AU49)/100),2)+ROUND(((ROUND((ROUND(((AE49-((EU49*1.2)))*AV49*I49),2)*BS49),2)*AU49)/100),2)) -> 4556.91 | AA49: -1 | AB49: =ROUND((AC49+AD49+AF49),6) -> 89.694 | AC49: =ROUND(((ES49*1)),6) -> 3.93 | AD49: =ROUND(((((ET49*1.2))-((EU49*1.2)))+AE49),6) -> 3.984 | AE49: =ROUND(((EU49*1.2)),6) -> 0.6 | AF49: =ROUND(((EV49*1.2)),6) -> 81.78 | AG49: =ROUND((AP49),6) -> 0 | AH49: =((EW49*1.2)) -> 6.48 | AI49: =((EX49*1.2)) -> 0 | AJ49: =(AS49) -> 0 | AK49: 75.4 | AL49: 3.93 | AM49: 3.32 | AN49: 0.5 | AO49: 68.15 | AP49: 0 | AQ49: 5.4 | AR49: 0 | AS49: 0 | AT49: 90 | AU49: 46 | AV49: 1.067 | AW49: 1.028 | AZ49: 1 | BA49: 56.35 | BB49: 17.09 | BC49: 4.49 | BH49: 0 | BI49: 2 | BJ49: ТСН-2001.4 Доп. 68, Сб. 12, т. 48, поз. 11 | BM49: 73 | BN49: 0 | BO49: 4.12-48-11 | BP49: 1 | BQ49: 40 | BR49: 0 | BS49: 56.35 | BT49: 1 | BU49: 1 | BV49: 1 | BW49: 1 | BX49: 1 | BZ49: 90 | CA49: 46 | CE49: 1566 | CF49: 0 | CG49: 0 | CM49: 0 | CN49: Поправка: Гл.12.Прил.8.п.8. 3_12.00.01.11.001 Наименование: При наличии напряженных и стесненных условий производства работ (стесненность, сложность складирования и транспортной логистики и т.п.) для объектов, расположенных в пределах круговой магистральной системы улиц "Садовое кольцо" города Москвы | CO49: 0 | CP49: =(P49+Q49+S49) -> 10015.75 | CQ49: =ROUND((ROUND((AC49*AW49*1),2)*BC49),2) -> 18.14 | CR49: =(ROUND((ROUND((((ET49*1.2))*AV49*1),2)*BB49),2)+ROUND((ROUND(((AE49-((EU49*1.2)))*AV49*1),2)*BS49),2)) -> 72.63 | CS49: =(ROUND((ROUND((((EU49*1.2))*AV49*1),2)*BS49),2)+ROUND((ROUND(((AE49-((EU49*1.2)))*AV49*1),2)*BS49),2)) -> 36.06 | CT49: =ROUND((ROUND((AF49*AV49*1),2)*BA49),2) -> 4917.1 | CU49: =AG49 -> 0 | CV49: =(AH49*AV49) -> 6.91416 | CW49: =AI49 -> 0 | CX49: =AJ49 -> 0 | CY49: =(ROUND((((S49+ROUND((ROUND((((EU49*1.2))*AV49*1),2)*BS49),2))*AT49)/100),2)+ROUND(((ROUND((ROUND(((AE49-((EU49*1.2)))*AV49*1),2)*BS49),2)*AT49)/100),2)) -> 8883.23 | CZ49: =(ROUND((((S49+ROUND((ROUND((((EU49*1.2))*AV49*1),2)*BS49),2))*AU49)/100),2)+ROUND(((ROUND((ROUND(((AE49-((EU49*1.2)))*AV49*1),2)*BS49),2)*AU49)/100),2)) -> 4540.32 | DB49: 26 | DD49: *1 | DE49: *1,2 | DF49: *1,2 | DG49: *1,2 | DI49: *1,2 | DJ49: *1,2 | DN49: 0 | DO49: 0 | DP49: 1 | DQ49: 1 | DU49: 1013 | DV49: 1 ШТ. | DW49: 1 ШТ. | DX49: 1 | EE49: 56938740 | EF49: 40 | EG49: Монтаж оборудования | EH49: 0 | EJ49: 2 | EK49: 73 | EL49: ТСН-2001.4-12. Технологические трубопроводы | EM49: ТСН-2001.4-12-1 | EO49: Поправка: Гл.12.Прил.8.п.8. 3_12.00.01.11.001 | EQ49: 132096 | ER49: 75.4 | ES49: 3.93 | ET49: 3.32 | EU49: 0.5 | EV49: 68.15 | EW49: 5.4 | EX49: 0 | EY49: 0 | FQ49: 0 | FR49: 0 | FS49: 2 | FX49: 90 | FY49: 46 | GD49: 1 | GF49: 434457661 | GG49: 2 | GH49: 1 | GI49: 2 | GJ49: 0 | GK49: 0 | GL49: =ROUND(IF(AND(BH49=3,BI49=3,FS49<>0),P49,0),2) -> 0 | GM49: =ROUND(O49+X49+Y49,2)+GX49 -> 23488.36 | GN49: =IF(OR(BI49=0,BI49=1),GM49-GX49,0) -> 0 | GO49: =IF(BI49=2,GM49-GX49,0) -> 23488.36 | GP49: =IF(BI49=4,GM49-GX49,0) -> 0 | GR49: 0 | GS49: 3 | GT49: 0 | GV49: =ROUND((GT49),6) -> 0 | GW49: 1 | GX49: =ROUND(HC49*I49,2) -> 0 | HA49: 0 | HB49: 0 | HC49: =GV49*GW49 -> 0 | HS49: 0 | IK49: 0
A50: 17 | B50: 1 | C50: =ROW(SmtRes!A146) -> 146 | D50: =ROW(EtalonRes!A180) -> 180 | F50: 4.12-48-4 | G50: Монтаж арматуры фланцевой с ручным приводом или без привода на номинальное давление до 4 МПа, номинальный диаметр прохода 25 мм (обратный клапан, затвор поворотный для жокея) | H50: 1 ШТ. | I50: =ROUND(1+2,9) -> 3 | J50: 0 | K50: =ROUND(1+2,9) -> 3 | O50: =ROUND(CP50,2) -> 147.56 | P50: =ROUND((ROUND((AC50*AW50*I50),2)*BC50),2) -> 2.13 | Q50: =(ROUND((ROUND((((ET50*1.2))*AV50*I50),2)*BB50),2)+ROUND((ROUND(((AE50-((EU50*1.2)))*AV50*I50),2)*BS50),2)) -> 0 | R50: =(ROUND((ROUND((((EU50*1.2))*AV50*I50),2)*BS50),2)+ROUND((ROUND(((AE50-((EU50*1.2)))*AV50*I50),2)*BS50),2)) -> 0 | S50: =ROUND((ROUND((AF50*AV50*I50),2)*BA50),2) -> 145.43 | T50: =ROUND(CU50*I50,2) -> 0 | U50: =CV50*I50 -> 11.5236 | V50: =CW50*I50 -> 0 | W50: =ROUND(CX50*I50,2) -> 0 | X50: =(ROUND((((S50+ROUND((ROUND((((EU50*1.2))*AV50*I50),2)*BS50),2))*AT50)/100),2)+ROUND(((ROUND((ROUND(((AE50-((EU50*1.2)))*AV50*I50),2)*BS50),2)*AT50)/100),2)) -> 130.89 | Y50: =(ROUND((((S50+ROUND((ROUND((((EU50*1.2))*AV50*I50),2)*BS50),2))*AU50)/100),2)+ROUND(((ROUND((ROUND(((AE50-((EU50*1.2)))*AV50*I50),2)*BS50),2)*AU50)/100),2)) -> 66.9 | AA50: -1 | AB50: =ROUND((AC50+AD50+AF50),6) -> 46.122 | AC50: =ROUND(((ES50*1)),6) -> 0.69 | AD50: =ROUND(((((ET50*1.2))-((EU50*1.2)))+AE50),6) -> 0 | AE50: =ROUND(((EU50*1.2)),6) -> 0 | AF50: =ROUND(((EV50*1.2)),6) -> 45.432 | AG50: =ROUND((AP50),6) -> 0 | AH50: =((EW50*1.2)) -> 3.6 | AI50: =((EX50*1.2)) -> 0 | AJ50: =(AS50) -> 0 | AK50: 38.55 | AL50: 0.69 | AM50: 0 | AN50: 0 | AO50: 37.86 | AP50: 0 | AQ50: 3 | AR50: 0 | AS50: 0 | AT50: 90 | AU50: 46 | AV50: 1.067 | AW50: 1.028 | AZ50: 1 | BA50: 1 | BB50: 1 | BC50: 1 | BH50: 0 | BI50: 2 | BJ50: ТСН-2001.4 Доп. 67, Сб. 12, т. 48, поз. 4 | BM50: 73 | BN50: 0 | BO50: 4.12-48-4 | BP50: 1 | BQ50: 40 | BR50: 0 | BS50: 1 | BT50: 1 | BU50: 1 | BV50: 1 | BW50: 1 | BX50: 1 | BZ50: 90 | CA50: 46 | CE50: 1566 | CF50: 0 | CG50: 0 | CM50: 0 | CN50: Поправка: Гл.12.Прил.8.п.8. 3_12.00.01.11.001 Наименование: При наличии напряженных и стесненных условий производства работ (стесненность, сложность складирования и транспортной логистики и т.п.) для объектов, расположенных в пределах круговой магистральной системы улиц "Садовое кольцо" города Москвы | CO50: 0 | CP50: =(P50+Q50+S50) -> 147.56 | CQ50: =ROUND((ROUND((AC50*AW50*1),2)*BC50),2) -> 0.71 | CR50: =(ROUND((ROUND((((ET50*1.2))*AV50*1),2)*BB50),2)+ROUND((ROUND(((AE50-((EU50*1.2)))*AV50*1),2)*BS50),2)) -> 0 | CS50: =(ROUND((ROUND((((EU50*1.2))*AV50*1),2)*BS50),2)+ROUND((ROUND(((AE50-((EU50*1.2)))*AV50*1),2)*BS50),2)) -> 0 | CT50: =ROUND((ROUND((AF50*AV50*1),2)*BA50),2) -> 48.48 | CU50: =AG50 -> 0 | CV50: =(AH50*AV50) -> 3.8412 | CW50: =AI50 -> 0 | CX50: =AJ50 -> 0 | CY50: =(ROUND((((S50+ROUND((ROUND((((EU50*1.2))*AV50*1),2)*BS50),2))*AT50)/100),2)+ROUND(((ROUND((ROUND(((AE50-((EU50*1.2)))*AV50*1),2)*BS50),2)*AT50)/100),2)) -> 130.89 | CZ50: =(ROUND((((S50+ROUND((ROUND((((EU50*1.2))*AV50*1),2)*BS50),2))*AU50)/100),2)+ROUND(((ROUND((ROUND(((AE50-((EU50*1.2)))*AV50*1),2)*BS50),2)*AU50)/100),2)) -> 66.9 | DB50: 27 | DD50: *1 | DE50: *1,2 | DF50: *1,2 | DG50: *1,2 | DI50: *1,2 | DJ50: *1,2 | DN50: 0 | DO50: 0 | DP50: 1 | DQ50: 1 | DU50: 1013 | DV50: 1 ШТ. | DW50: 1 ШТ. | DX50: 1 | EE50: 56938740 | EF50: 40 | EG50: Монтаж оборудования | EH50: 0 | EJ50: 2 | EK50: 73 | EL50: ТСН-2001.4-12. Технологические трубопроводы | EM50: ТСН-2001.4-12-1 | EO50: Поправка: Гл.12.Прил.8.п.8. 3_12.00.01.11.001 | EQ50: 132096 | ER50: 38.55 | ES50: 0.69 | ET50: 0 | EU50: 0 | EV50: 37.86 | EW50: 3 | EX50: 0 | EY50: 0 | FQ50: 0 | FR50: 0 | FS50: 2 | FX50: 90 | FY50: 46 | GD50: 1 | GF50: 2121044303 | GG50: 2 | GH50: 1 | GI50: 2 | GJ50: 0 | GK50: 0 | GL50: =ROUND(IF(AND(BH50=3,BI50=3,FS50<>0),P50,0),2) -> 0 | GM50: =ROUND(O50+X50+Y50,2)+GX50 -> 345.35 | GN50: =IF(OR(BI50=0,BI50=1),GM50-GX50,0) -> 0 | GO50: =IF(BI50=2,GM50-GX50,0) -> 345.35 | GP50: =IF(BI50=4,GM50-GX50,0) -> 0 | GR50: 0 | GS50: 3 | GT50: 0 | GV50: =ROUND((GT50),6) -> 0 | GW50: 1 | GX50: =ROUND(HC50*I50,2) -> 0 | HA50: 0 | HB50: 0 | HC50: =GV50*GW50 -> 0 | HS50: 0 | IK50: 0
A51: 17 | B51: 1 | C51: =ROW(SmtRes!A148) -> 148 | D51: =ROW(EtalonRes!A184) -> 184 | F51: 4.12-48-4 | G51: Монтаж арматуры фланцевой с ручным приводом или без привода на номинальное давление до 4 МПа, номинальный диаметр прохода 25 мм (обратный клапан, затвор поворотный для жокея) | H51: 1 ШТ. | I51: =ROUND(1+2,9) -> 3 | J51: 0 | K51: =ROUND(1+2,9) -> 3 | O51: =ROUND(CP51,2) -> 8204.61 | P51: =ROUND((ROUND((AC51*AW51*I51),2)*BC51),2) -> 9.63 | Q51: =(ROUND((ROUND((((ET51*1.2))*AV51*I51),2)*BB51),2)+ROUND((ROUND(((AE51-((EU51*1.2)))*AV51*I51),2)*BS51),2)) -> 0 | R51: =(ROUND((ROUND((((EU51*1.2))*AV51*I51),2)*BS51),2)+ROUND((ROUND(((AE51-((EU51*1.2)))*AV51*I51),2)*BS51),2)) -> 0 | S51: =ROUND((ROUND((AF51*AV51*I51),2)*BA51),2) -> 8194.98 | T51: =ROUND(CU51*I51,2) -> 0 | U51: =CV51*I51 -> 11.5236 | V51: =CW51*I51 -> 0 | W51: =ROUND(CX51*I51,2) -> 0 | X51: =(ROUND((((S51+ROUND((ROUND((((EU51*1.2))*AV51*I51),2)*BS51),2))*AT51)/100),2)+ROUND(((ROUND((ROUND(((AE51-((EU51*1.2)))*AV51*I51),2)*BS51),2)*AT51)/100),2)) -> 7375.48 | Y51: =(ROUND((((S51+ROUND((ROUND((((EU51*1.2))*AV51*I51),2)*BS51),2))*AU51)/100),2)+ROUND(((ROUND((ROUND(((AE51-((EU51*1.2)))*AV51*I51),2)*BS51),2)*AU51)/100),2)) -> 3769.69 | AA51: -1 | AB51: =ROUND((AC51+AD51+AF51),6) -> 46.122 | AC51: =ROUND(((ES51*1)),6) -> 0.69 | AD51: =ROUND(((((ET51*1.2))-((EU51*1.2)))+AE51),6) -> 0 | AE51: =ROUND(((EU51*1.2)),6) -> 0 | AF51: =ROUND(((EV51*1.2)),6) -> 45.432 | AG51: =ROUND((AP51),6) -> 0 | AH51: =((EW51*1.2)) -> 3.6 | AI51: =((EX51*1.2)) -> 0 | AJ51: =(AS51) -> 0 | AK51: 38.55 | AL51: 0.69 | AM51: 0 | AN51: 0 | AO51: 37.86 | AP51: 0 | AQ51: 3 | AR51: 0 | AS51: 0 | AT51: 90 | AU51: 46 | AV51: 1.067 | AW51: 1.028 | AZ51: 1 | BA51: 56.35 | BB51: 1 | BC51: 4.52 | BH51: 0 | BI51: 2 | BJ51: ТСН-2001.4 Доп. 67, Сб. 12, т. 48, поз. 4 | BM51: 73 | BN51: 0 | BO51: 4.12-48-4 | BP51: 1 | BQ51: 40 | BR51: 0 | BS51: 56.35 | BT51: 1 | BU51: 1 | BV51: 1 | BW51: 1 | BX51: 1 | BZ51: 90 | CA51: 46 | CE51: 1566 | CF51: 0 | CG51: 0 | CM51: 0 | CN51: Поправка: Гл.12.Прил.8.п.8. 3_12.00.01.11.001 Наименование: При наличии напряженных и стесненных условий производства работ (стесненность, сложность складирования и транспортной логистики и т.п.) для объектов, расположенных в пределах круговой магистральной системы улиц "Садовое кольцо" города Москвы | CO51: 0 | CP51: =(P51+Q51+S51) -> 8204.61 | CQ51: =ROUND((ROUND((AC51*AW51*1),2)*BC51),2) -> 3.21 | CR51: =(ROUND((ROUND((((ET51*1.2))*AV51*1),2)*BB51),2)+ROUND((ROUND(((AE51-((EU51*1.2)))*AV51*1),2)*BS51),2)) -> 0 | CS51: =(ROUND((ROUND((((EU51*1.2))*AV51*1),2)*BS51),2)+ROUND((ROUND(((AE51-((EU51*1.2)))*AV51*1),2)*BS51),2)) -> 0 | CT51: =ROUND((ROUND((AF51*AV51*1),2)*BA51),2) -> 2731.85 | CU51: =AG51 -> 0 | CV51: =(AH51*AV51) -> 3.8412 | CW51: =AI51 -> 0 | CX51: =AJ51 -> 0 | CY51: =(ROUND((((S51+ROUND((ROUND((((EU51*1.2))*AV51*1),2)*BS51),2))*AT51)/100),2)+ROUND(((ROUND((ROUND(((AE51-((EU51*1.2)))*AV51*1),2)*BS51),2)*AT51)/100),2)) -> 7375.48 | CZ51: =(ROUND((((S51+ROUND((ROUND((((EU51*1.2))*AV51*1),2)*BS51),2))*AU51)/100),2)+ROUND(((ROUND((ROUND(((AE51-((EU51*1.2)))*AV51*1),2)*BS51),2)*AU51)/100),2)) -> 3769.69 | DB51: 28 | DD51: *1 | DE51: *1,2 | DF51: *1,2 | DG51: *1,2 | DI51: *1,2 | DJ51: *1,2 | DN51: 0 | DO51: 0 | DP51: 1 | DQ51: 1 | DU51: 1013 | DV51: 1 ШТ. | DW51: 1 ШТ. | DX51: 1 | EE51: 56938740 | EF51: 40 | EG51: Монтаж оборудования | EH51: 0 | EJ51: 2 | EK51: 73 | EL51: ТСН-2001.4-12. Технологические трубопроводы | EM51: ТСН-2001.4-12-1 | EO51: Поправка: Гл.12.Прил.8.п.8. 3_12.00.01.11.001 | EQ51: 132096 | ER51: 38.55 | ES51: 0.69 | ET51: 0 | EU51: 0 | EV51: 37.86 | EW51: 3 | EX51: 0 | EY51: 0 | FQ51: 0 | FR51: 0 | FS51: 2 | FX51: 90 | FY51: 46 | GD51: 1 | GF51: 2121044303 | GG51: 2 | GH51: 1 | GI51: 2 | GJ51: 0 | GK51: 0 | GL51: =ROUND(IF(AND(BH51=3,BI51=3,FS51<>0),P51,0),2) -> 0 | GM51: =ROUND(O51+X51+Y51,2)+GX51 -> 19349.78 | GN51: =IF(OR(BI51=0,BI51=1),GM51-GX51,0) -> 0 | GO51: =IF(BI51=2,GM51-GX51,0) -> 19349.78 | GP51: =IF(BI51=4,GM51-GX51,0) -> 0 | GR51: 0 | GS51: 3 | GT51: 0 | GV51: =ROUND((GT51),6) -> 0 | GW51: 1 | GX51: =ROUND(HC51*I51,2) -> 0 | HA51: 0 | HB51: 0 | HC51: =GV51*GW51 -> 0 | HS51: 0 | IK51: 0
A52: 17 | B52: 1 | C52: =ROW(SmtRes!A152) -> 152 | D52: =ROW(EtalonRes!A190) -> 190 | F52: 3.18-20-2 | G52: Установка манометров с трехходовым краном (реле давления, манометр) | H52: 1 комплект | I52: =ROUND(2+2+4,9) -> 8 | J52: 0 | K52: =ROUND(2+2+4,9) -> 8 | O52: =ROUND(CP52,2) -> 41.13 | P52: =ROUND((ROUND((AC52*AW52*I52),2)*BC52),2) -> 7.44 | Q52: =(ROUND((ROUND(((((ET52*1.25)*1.2))*AV52*I52),2)*BB52),2)+ROUND((ROUND(((AE52-(((EU52*1.25)*1.2)))*AV52*I52),2)*BS52),2)) -> 0 | R52: =(ROUND((ROUND(((((EU52*1.25)*1.2))*AV52*I52),2)*BS52),2)+ROUND((ROUND(((AE52-(((EU52*1.25)*1.2)))*AV52*I52),2)*BS52),2)) -> 0 | S52: =ROUND((ROUND((AF52*AV52*I52),2)*BA52),2) -> 33.69 | T52: =ROUND(CU52*I52,2) -> 0 | U52: =CV52*I52 -> 2.5915296 | V52: =CW52*I52 -> 0 | W52: =ROUND(CX52*I52,2) -> 0 | X52: =(ROUND((((S52+ROUND((ROUND(((((EU52*1.25)*1.2))*AV52*I52),2)*BS52),2))*AT52)/100),2)+ROUND(((ROUND((ROUND(((AE52-(((EU52*1.25)*1.2)))*AV52*I52),2)*BS52),2)*AT52)/100),2)) -> 40.76 | Y52: =(ROUND((((S52+ROUND((ROUND(((((EU52*1.25)*1.2))*AV52*I52),2)*BS52),2))*AU52)/100),2)+ROUND(((ROUND((ROUND(((AE52-(((EU52*1.25)*1.2)))*AV52*I52),2)*BS52),2)*AU52)/100),2)) -> 24.26 | AA52: -1 | AB52: =ROUND((AC52+AD52+AF52),6) -> 4.8768 | AC52: =ROUND((((ES52*1)*1)),6) -> 0.93 | AD52: =ROUND((((((ET52*1.25)*1.2))-(((EU52*1.25)*1.2)))+AE52),6) -> 0 | AE52: =ROUND((((EU52*1.25)*1.2)),6) -> 0 | AF52: =ROUND((((EV52*1.15)*1.2)),6) -> 3.9468 | AG52: =ROUND((AP52),6) -> 0 | AH52: =(((EW52*1.15)*1.2)) -> 0.3036 | AI52: =(((EX52*1.25)*1.2)) -> 0 | AJ52: =(AS52) -> 0 | AK52: 3.79 | AL52: 0.93 | AM52: 0 | AN52: 0 | AO52: 2.86 | AP52: 0 | AQ52: 0.22 | AR52: 0 | AS52: 0 | AT52: 121 | AU52: 72 | AV52: 1.067 | AW52: 1 | AZ52: 1 | BA52: 1 | BB52: 1 | BC52: 1 | BH52: 0 | BI52: 1 | BJ52: ТСН-2001.3. Доп. 1-42. Сб. 18, т. 20, поз. 2 | BM52: 23 | BN52: 0 | BO52: 3.18-20-2 | BP52: 1 | BQ52: 30 | BR52: 0 | BS52: 1 | BT52: 1 | BU52: 1 | BV52: 1 | BW52: 1 | BX52: 1 | BZ52: 121 | CA52: 72 | CE52: 1566 | CF52: 0 | CG52: 0 | CM52: 0 | CN52: Поправка: Гл.6.Прил.2.2.п.2.2.6_06.00.01.07.001 Наименование: При выполнении при капитальном ремонте и реконструкции работ, аналогичных технологическим процессам, характерным для нового строительства, и отсутствующих в сборниках на ремонтно-строительные работы ТСН-2001.6 Поправка: Гл.12.Прил.8.п.8. 3_12.00.01.11.001 Наименование: При наличии напряженных и стесненных условий производства работ (стесненность, сложность складирования и транспортной логистики и т.п.) для объектов, расположенных в пределах круговой магистральной системы улиц "Садовое кольцо" города Москвы | CO52: 0 | CP52: =(P52+Q52+S52) -> 41.13 | CQ52: =ROUND((ROUND((AC52*AW52*1),2)*BC52),2) -> 0.93 | CR52: =(ROUND((ROUND(((((ET52*1.25)*1.2))*AV52*1),2)*BB52),2)+ROUND((ROUND(((AE52-(((EU52*1.25)*1.2)))*AV52*1),2)*BS52),2)) -> 0 | CS52: =(ROUND((ROUND(((((EU52*1.25)*1.2))*AV52*1),2)*BS52),2)+ROUND((ROUND(((AE52-(((EU52*1.25)*1.2)))*AV52*1),2)*BS52),2)) -> 0 | CT52: =ROUND((ROUND((AF52*AV52*1),2)*BA52),2) -> 4.21 | CU52: =AG52 -> 0 | CV52: =(AH52*AV52) -> 0.3239412 | CW52: =AI52 -> 0 | CX52: =AJ52 -> 0 | CY52: =(ROUND((((S52+ROUND((ROUND(((((EU52*1.25)*1.2))*AV52*1),2)*BS52),2))*AT52)/100),2)+ROUND(((ROUND((ROUND(((AE52-(((EU52*1.25)*1.2)))*AV52*1),2)*BS52),2)*AT52)/100),2)) -> 40.76 | CZ52: =(ROUND((((S52+ROUND((ROUND(((((EU52*1.25)*1.2))*AV52*1),2)*BS52),2))*AU52)/100),2)+ROUND(((ROUND((ROUND(((AE52-(((EU52*1.25)*1.2)))*AV52*1),2)*BS52),2)*AU52)/100),2)) -> 24.26 | DB52: 29 | DD52: *1)*1 | DE52: *1,25)*1,2 | DF52: *1,25)*1,2 | DG52: *1,15)*1,2 | DI52: *1,15)*1,2 | DJ52: *1,25)*1,2 | DN52: 0 | DO52: 0 | DP52: 1 | DQ52: 1 | DU52: 1013 | DV52: 1 комплект | DW52: 1 комплект | DX52: 1 | EE52: 56938689 | EF52: 30 | EG52: Строительные работы | EH52: 0 | EJ52: 1 | EK52: 23 | EL52: ТСН-2001.3-18. Отопление - внутренние устройства | EM52: ТСН-2001.3-18-1 | EO52: Поправка: Гл.6.Прил.2.2.п.2.2.6_06.00.01.07.001 Поправка: Гл.12.Прил.8.п.8. 3_12.00.01.11.001 | EQ52: 132096 | ER52: 3.79 | ES52: 0.93 | ET52: 0 | EU52: 0 | EV52: 2.86 | EW52: 0.22 | EX52: 0 | EY52: 0 | FQ52: 0 | FR52: 0 | FS52: 0 | FX52: 121 | FY52: 72 | GD52: 1 | GF52: 2014171460 | GG52: 2 | GH52: 1 | GI52: 2 | GJ52: 0 | GK52: 0 | GL52: =ROUND(IF(AND(BH52=3,BI52=3,FS52<>0),P52,0),2) -> 0 | GM52: =ROUND(O52+X52+Y52,2)+GX52 -> 106.15 | GN52: =IF(OR(BI52=0,BI52=1),GM52-GX52,0) -> 106.15 | GO52: =IF(BI52=2,GM52-GX52,0) -> 0 | GP52: =IF(BI52=4,GM52-GX52,0) -> 0 | GR52: 0 | GS52: 3 | GT52: 0 | GV52: =ROUND((GT52),6) -> 0 | GW52: 1 | GX52: =ROUND(HC52*I52,2) -> 0 | HA52: 0 | HB52: 0 | HC52: =GV52*GW52 -> 0 | HS52: 0 | IK52: 0
A53: 17 | B53: 1 | C53: =ROW(SmtRes!A156) -> 156 | D53: =ROW(EtalonRes!A196) -> 196 | F53: 3.18-20-2 | G53: Установка манометров с трехходовым краном (реле давления, манометр) | H53: 1 комплект | I53: =ROUND(2+2+4,9) -> 8 | J53: 0 | K53: =ROUND(2+2+4,9) -> 8 | O53: =ROUND(CP53,2) -> 1939.13 | P53: =ROUND((ROUND((AC53*AW53*I53),2)*BC53),2) -> 40.7 | Q53: =(ROUND((ROUND(((((ET53*1.25)*1.2))*AV53*I53),2)*BB53),2)+ROUND((ROUND(((AE53-(((EU53*1.25)*1.2)))*AV53*I53),2)*BS53),2)) -> 0 | R53: =(ROUND((ROUND(((((EU53*1.25)*1.2))*AV53*I53),2)*BS53),2)+ROUND((ROUND(((AE53-(((EU53*1.25)*1.2)))*AV53*I53),2)*BS53),2)) -> 0 | S53: =ROUND((ROUND((AF53*AV53*I53),2)*BA53),2) -> 1898.43 | T53: =ROUND(CU53*I53,2) -> 0 | U53: =CV53*I53 -> 2.5915296 | V53: =CW53*I53 -> 0 | W53: =ROUND(CX53*I53,2) -> 0 | X53: =(ROUND((((S53+ROUND((ROUND(((((EU53*1.25)*1.2))*AV53*I53),2)*BS53),2))*AT53)/100),2)+ROUND(((ROUND((ROUND(((AE53-(((EU53*1.25)*1.2)))*AV53*I53),2)*BS53),2)*AT53)/100),2)) -> 2297.1 | Y53: =(ROUND((((S53+ROUND((ROUND(((((EU53*1.25)*1.2))*AV53*I53),2)*BS53),2))*AU53)/100),2)+ROUND(((ROUND((ROUND(((AE53-(((EU53*1.25)*1.2)))*AV53*I53),2)*BS53),2)*AU53)/100),2)) -> 1366.87 | AA53: -1 | AB53: =ROUND((AC53+AD53+AF53),6) -> 4.8768 | AC53: =ROUND((((ES53*1)*1)),6) -> 0.93 | AD53: =ROUND((((((ET53*1.25)*1.2))-(((EU53*1.25)*1.2)))+AE53),6) -> 0 | AE53: =ROUND((((EU53*1.25)*1.2)),6) -> 0 | AF53: =ROUND((((EV53*1.15)*1.2)),6) -> 3.9468 | AG53: =ROUND((AP53),6) -> 0 | AH53: =(((EW53*1.15)*1.2)) -> 0.3036 | AI53: =(((EX53*1.25)*1.2)) -> 0 | AJ53: =(AS53) -> 0 | AK53: 3.79 | AL53: 0.93 | AM53: 0 | AN53: 0 | AO53: 2.86 | AP53: 0 | AQ53: 0.22 | AR53: 0 | AS53: 0 | AT53: 121 | AU53: 72 | AV53: 1.067 | AW53: 1 | AZ53: 1 | BA53: 56.35 | BB53: 1 | BC53: 5.47 | BH53: 0 | BI53: 1 | BJ53: ТСН-2001.3. Доп. 1-42. Сб. 18, т. 20, поз. 2 | BM53: 23 | BN53: 0 | BO53: 3.18-20-2 | BP53: 1 | BQ53: 30 | BR53: 0 | BS53: 56.35 | BT53: 1 | BU53: 1 | BV53: 1 | BW53: 1 | BX53: 1 | BZ53: 121 | CA53: 72 | CE53: 1566 | CF53: 0 | CG53: 0 | CM53: 0 | CN53: Поправка: Гл.6.Прил.2.2.п.2.2.6_06.00.01.07.001 Наименование: При выполнении при капитальном ремонте и реконструкции работ, аналогичных технологическим процессам, характерным для нового строительства, и отсутствующих в сборниках на ремонтно-строительные работы ТСН-2001.6 Поправка: Гл.12.Прил.8.п.8. 3_12.00.01.11.001 Наименование: При наличии напряженных и стесненных условий производства работ (стесненность, сложность складирования и транспортной логистики и т.п.) для объектов, расположенных в пределах круговой магистральной системы улиц "Садовое кольцо" города Москвы | CO53: 0 | CP53: =(P53+Q53+S53) -> 1939.13 | CQ53: =ROUND((ROUND((AC53*AW53*1),2)*BC53),2) -> 5.09 | CR53: =(ROUND((ROUND(((((ET53*1.25)*1.2))*AV53*1),2)*BB53),2)+ROUND((ROUND(((AE53-(((EU53*1.25)*1.2)))*AV53*1),2)*BS53),2)) -> 0 | CS53: =(ROUND((ROUND(((((EU53*1.25)*1.2))*AV53*1),2)*BS53),2)+ROUND((ROUND(((AE53-(((EU53*1.25)*1.2)))*AV53*1),2)*BS53),2)) -> 0 | CT53: =ROUND((ROUND((AF53*AV53*1),2)*BA53),2) -> 237.23 | CU53: =AG53 -> 0 | CV53: =(AH53*AV53) -> 0.3239412 | CW53: =AI53 -> 0 | CX53: =AJ53 -> 0 | CY53: =(ROUND((((S53+ROUND((ROUND(((((EU53*1.25)*1.2))*AV53*1),2)*BS53),2))*AT53)/100),2)+ROUND(((ROUND((ROUND(((AE53-(((EU53*1.25)*1.2)))*AV53*1),2)*BS53),2)*AT53)/100),2)) -> 2297.1 | CZ53: =(ROUND((((S53+ROUND((ROUND(((((EU53*1.25)*1.2))*AV53*1),2)*BS53),2))*AU53)/100),2)+ROUND(((ROUND((ROUND(((AE53-(((EU53*1.25)*1.2)))*AV53*1),2)*BS53),2)*AU53)/100),2)) -> 1366.87 | DB53: 31 | DD53: *1)*1 | DE53: *1,25)*1,2 | DF53: *1,25)*1,2 | DG53: *1,15)*1,2 | DI53: *1,15)*1,2 | DJ53: *1,25)*1,2 | DN53: 0 | DO53: 0 | DP53: 1 | DQ53: 1 | DU53: 1013 | DV53: 1 комплект | DW53: 1 комплект | DX53: 1 | EE53: 56938689 | EF53: 30 | EG53: Строительные работы | EH53: 0 | EJ53: 1 | EK53: 23 | EL53: ТСН-2001.3-18. Отопление - внутренние устройства | EM53: ТСН-2001.3-18-1 | EO53: Поправка: Гл.6.Прил.2.2.п.2.2.6_06.00.01.07.001 Поправка: Гл.12.Прил.8.п.8. 3_12.00.01.11.001 | EQ53: 132096 | ER53: 3.79 | ES53: 0.93 | ET53: 0 | EU53: 0 | EV53: 2.86 | EW53: 0.22 | EX53: 0 | EY53: 0 | FQ53: 0 | FR53: 0 | FS53: 0 | FX53: 121 | FY53: 72 | GD53: 1 | GF53: 2014171460 | GG53: 2 | GH53: 1 | GI53: 2 | GJ53: 0 | GK53: 0 | GL53: =ROUND(IF(AND(BH53=3,BI53=3,FS53<>0),P53,0),2) -> 0 | GM53: =ROUND(O53+X53+Y53,2)+GX53 -> 5603.1 | GN53: =IF(OR(BI53=0,BI53=1),GM53-GX53,0) -> 5603.1 | GO53: =IF(BI53=2,GM53-GX53,0) -> 0 | GP53: =IF(BI53=4,GM53-GX53,0) -> 0 | GR53: 0 | GS53: 3 | GT53: 0 | GV53: =ROUND((GT53),6) -> 0 | GW53: 1 | GX53: =ROUND(HC53*I53,2) -> 0 | HA53: 0 | HB53: 0 | HC53: =GV53*GW53 -> 0 | HS53: 0 | IK53: 0
A54: 17 | B54: 1 | E54: 5 | F54: КА. п. 1 | G54: Насосная установка пожаротушения Q-66,38 (м3/ч), H- 25,0 м.в.ст., Жокей насос Q-3.0 (м3/ч),H- 30,0 м.в.ст., комплектно со шкафом автоматического управления ШУПН-3-С ОН/РН/ЖН-18,5/18,5/1,5-УПП/УПП/П-В и комплектно с выносной панелью индикации ВП | H54: компл. | I54: 1 | J54: 0 | K54: 1 | O54: =ROUND(CP54,2) -> 199171.86 | P54: =ROUND((ROUND((AC54*I54),2)*BC54),2) -> 199171.86 | Q54: =(ROUND((ROUND(((ET54)*AV54*I54),2)*BB54),2)+ROUND((ROUND(((AE54-(EU54))*AV54*I54),2)*BS54),2)) -> 0 | R54: =(ROUND((ROUND(((EU54)*AV54*I54),2)*BS54),2)+ROUND((ROUND(((AE54-(EU54))*AV54*I54),2)*BS54),2)) -> 0 | S54: =ROUND((ROUND((AF54*AV54*I54),2)*BA54),2) -> 0 | T54: =ROUND(CU54*I54,2) -> 0 | U54: =CV54*I54 -> 0 | V54: =CW54*I54 -> 0 | W54: =ROUND(CX54*I54,2) -> 0 | X54: =(ROUND((((S54+ROUND((ROUND(((EU54)*AV54*I54),2)*BS54),2))*AT54)/100),2)+ROUND(((ROUND((ROUND(((AE54-(EU54))*AV54*I54),2)*BS54),2)*AT54)/100),2)) -> 0 | Y54: =(ROUND((((S54+ROUND((ROUND(((EU54)*AV54*I54),2)*BS54),2))*AU54)/100),2)+ROUND(((ROUND((ROUND(((AE54-(EU54))*AV54*I54),2)*BS54),2)*AU54)/100),2)) -> 0 | AA54: 55747649 | AB54: =ROUND((AC54+AD54+AF54),6) -> 199171.86 | AC54: =ROUND((ES54),6) -> 199171.86 | AD54: =ROUND((((ET54)-(EU54))+AE54),6) -> 0 | AE54: =ROUND((EU54),6) -> 0 | AF54: =ROUND((EV54),6) -> 0 | AG54: =ROUND((AP54),6) -> 0 | AH54: =(EW54) -> 0 | AI54: =(EX54) -> 0 | AJ54: =(AS54) -> 0 | AK54: 199171.86 | AL54: 199171.86 | AM54: 0 | AN54: 0 | AO54: 0 | AP54: 0 | AQ54: 0 | AR54: 0 | AS54: 0 | AT54: 0 | AU54: 0 | AV54: 1 | AW54: 1 | AZ54: 1 | BA54: 1 | BB54: 1 | BC54: 1 | BH54: 3 | BI54: 3 | BM54: 746 | BN54: 0 | BP54: 0 | BQ54: 130 | BR54: 0 | BS54: 1 | BT54: 1 | BU54: 1 | BV54: 1 | BW54: 1 | BX54: 1 | BZ54: 0 | CA54: 0 | CE54: 1566 | CF54: 0 | CG54: 0 | CM54: 0 | CN54: Поправка: Гл.4.Прил.2.2.п.2.2.17_04.00.01.24.001_x000D_ Наименование: При разнице в массе оборудования более 10% к норме и расценке ближайшего по массе оборудования при коэффициенте изменения массы оборудования до 0,5 т | CO54: 0 | CP54: =(P54+Q54+S54) -> 199171.86 | CQ54: =ROUND((ROUND((AC54*1),2)*BC54),2) -> 199171.86 | CR54: =(ROUND((ROUND(((ET54)*AV54*1),2)*BB54),2)+ROUND((ROUND(((AE54-(EU54))*AV54*1),2)*BS54),2)) -> 0 | CS54: =(ROUND((ROUND(((EU54)*AV54*1),2)*BS54),2)+ROUND((ROUND(((AE54-(EU54))*AV54*1),2)*BS54),2)) -> 0 | CT54: =ROUND((ROUND((AF54*AV54*1),2)*BA54),2) -> 0 | CU54: =AG54 -> 0 | CV54: =(AH54*AV54) -> 0 | CW54: =AI54 -> 0 | CX54: =AJ54 -> 0 | CY54: =(ROUND((((S54+ROUND((ROUND(((EU54)*AV54*1),2)*BS54),2))*AT54)/100),2)+ROUND(((ROUND((ROUND(((AE54-(EU54))*AV54*1),2)*BS54),2)*AT54)/100),2)) -> 0 | CZ54: =(ROUND((((S54+ROUND((ROUND(((EU54)*AV54*1),2)*BS54),2))*AU54)/100),2)+ROUND(((ROUND((ROUND(((AE54-(EU54))*AV54*1),2)*BS54),2)*AU54)/100),2)) -> 0 | DN54: 0 | DO54: 0 | DP54: 1 | DQ54: 1 | DU54: 1013 | DV54: компл. | DW54: компл. | DX54: 1 | EE54: 56938841 | EF54: 130 | EG54: Сметная стоимость оборудования | EH54: 0 | EJ54: 3 | EK54: 746 | EL54: ТСН-2001.13. Сметная стоимость оборудования | EM54: ТСН-2001.13 | EO54: Поправка: Гл.4.Прил.2.2.п.2.2.17_04.00.01.24.001 | EQ54: 131072 | ER54: 0 | ES54: 199171.86 | ET54: 0 | EU54: 0 | EV54: 0 | EW54: 0 | EX54: 0 | EY54: 0 | FQ54: 0 | FR54: =P54 -> 199171.86 | FS54: 0 | FX54: 0 | FY54: 0 | GA54: [1 764 680 / 1,22 / 7,57] + 3% Трансп + 1,2% Заг.скл | GD54: 1 | GF54: -1036281574 | GG54: 2 | GH54: 4 | GI54: -2 | GJ54: 0 | GK54: 0 | GL54: =ROUND(IF(AND(BH54=3,BI54=3,FS54<>0),P54,0),2) -> 0 | GM54: =ROUND(O54+X54+Y54,2)+GX54 -> 199171.86 | GN54: =IF(OR(BI54=0,BI54=1),GM54-GX54,0) -> 0 | GO54: =IF(BI54=2,GM54-GX54,0) -> 0 | GP54: =IF(BI54=4,GM54-GX54,0) -> 0 | GR54: 0 | GS54: 2 | GT54: 0 | GV54: =ROUND((GT54),6) -> 0 | GW54: 1 | GX54: =ROUND(HC54*I54,2) -> 0 | HA54: 0 | HB54: 0 | HC54: =GV54*GW54 -> 0 | HE54: 3 | HF54: 1,2 | HS54: 0 | IK54: 0
A55: 17 | B55: 1 | E55: 5 | F55: КА. п. 1 | G55: Насосная установка пожаротушения Q-66,38 (м3/ч), H- 25,0 м.в.ст., Жокей насос Q-3.0 (м3/ч),H- 30,0 м.в.ст., комплектно со шкафом автоматического управления ШУПН-3-С ОН/РН/ЖН-18,5/18,5/1,5-УПП/УПП/П-В и комплектно с выносной панелью индикации ВП | H55: компл. | I55: 1 | J55: 0 | K55: 1 | O55: =ROUND(CP55,2) -> 1507731 | P55: =ROUND((ROUND((AC55*I55),2)*BC55),2) -> 1507731 | Q55: =(ROUND((ROUND(((ET55)*AV55*I55),2)*BB55),2)+ROUND((ROUND(((AE55-(EU55))*AV55*I55),2)*BS55),2)) -> 0 | R55: =(ROUND((ROUND(((EU55)*AV55*I55),2)*BS55),2)+ROUND((ROUND(((AE55-(EU55))*AV55*I55),2)*BS55),2)) -> 0 | S55: =ROUND((ROUND((AF55*AV55*I55),2)*BA55),2) -> 0 | T55: =ROUND(CU55*I55,2) -> 0 | U55: =CV55*I55 -> 0 | V55: =CW55*I55 -> 0 | W55: =ROUND(CX55*I55,2) -> 0 | X55: =(ROUND((((S55+ROUND((ROUND(((EU55)*AV55*I55),2)*BS55),2))*AT55)/100),2)+ROUND(((ROUND((ROUND(((AE55-(EU55))*AV55*I55),2)*BS55),2)*AT55)/100),2)) -> 0 | Y55: =(ROUND((((S55+ROUND((ROUND(((EU55)*AV55*I55),2)*BS55),2))*AU55)/100),2)+ROUND(((ROUND((ROUND(((AE55-(EU55))*AV55*I55),2)*BS55),2)*AU55)/100),2)) -> 0 | AA55: 55747651 | AB55: =ROUND((AC55+AD55+AF55),6) -> 199171.86 | AC55: =ROUND((ES55),6) -> 199171.86 | AD55: =ROUND((((ET55)-(EU55))+AE55),6) -> 0 | AE55: =ROUND((EU55),6) -> 0 | AF55: =ROUND((EV55),6) -> 0 | AG55: =ROUND((AP55),6) -> 0 | AH55: =(EW55) -> 0 | AI55: =(EX55) -> 0 | AJ55: =(AS55) -> 0 | AK55: 199171.86 | AL55: 199171.86 | AM55: 0 | AN55: 0 | AO55: 0 | AP55: 0 | AQ55: 0 | AR55: 0 | AS55: 0 | AT55: 0 | AU55: 0 | AV55: 1 | AW55: 1 | AZ55: 1 | BA55: 1 | BB55: 1 | BC55: 7.57 | BH55: 3 | BI55: 3 | BM55: 746 | BN55: 0 | BP55: 0 | BQ55: 130 | BR55: 0 | BS55: 1 | BT55: 1 | BU55: 1 | BV55: 1 | BW55: 1 | BX55: 1 | BZ55: 0 | CA55: 0 | CE55: 1566 | CF55: 0 | CG55: 0 | CM55: 0 | CN55: Поправка: Гл.4.Прил.2.2.п.2.2.17_04.00.01.24.001_x000D_ Наименование: При разнице в массе оборудования более 10% к норме и расценке ближайшего по массе оборудования при коэффициенте изменения массы оборудования до 0,5 т | CO55: 0 | CP55: =(P55+Q55+S55) -> 1507731 | CQ55: =ROUND((ROUND((AC55*1),2)*BC55),2) -> 1507731 | CR55: =(ROUND((ROUND(((ET55)*AV55*1),2)*BB55),2)+ROUND((ROUND(((AE55-(EU55))*AV55*1),2)*BS55),2)) -> 0 | CS55: =(ROUND((ROUND(((EU55)*AV55*1),2)*BS55),2)+ROUND((ROUND(((AE55-(EU55))*AV55*1),2)*BS55),2)) -> 0 | CT55: =ROUND((ROUND((AF55*AV55*1),2)*BA55),2) -> 0 | CU55: =AG55 -> 0 | CV55: =(AH55*AV55) -> 0 | CW55: =AI55 -> 0 | CX55: =AJ55 -> 0 | CY55: =(ROUND((((S55+ROUND((ROUND(((EU55)*AV55*1),2)*BS55),2))*AT55)/100),2)+ROUND(((ROUND((ROUND(((AE55-(EU55))*AV55*1),2)*BS55),2)*AT55)/100),2)) -> 0 | CZ55: =(ROUND((((S55+ROUND((ROUND(((EU55)*AV55*1),2)*BS55),2))*AU55)/100),2)+ROUND(((ROUND((ROUND(((AE55-(EU55))*AV55*1),2)*BS55),2)*AU55)/100),2)) -> 0 | DN55: 0 | DO55: 0 | DP55: 1 | DQ55: 1 | DU55: 1013 | DV55: компл. | DW55: компл. | DX55: 1 | EE55: 56938841 | EF55: 130 | EG55: Сметная стоимость оборудования | EH55: 0 | EJ55: 3 | EK55: 746 | EL55: ТСН-2001.13. Сметная стоимость оборудования | EM55: ТСН-2001.13 | EO55: Поправка: Гл.4.Прил.2.2.п.2.2.17_04.00.01.24.001 | EQ55: 131072 | ER55: 199171.86 | ES55: 199171.86 | ET55: 0 | EU55: 0 | EV55: 0 | EW55: 0 | EX55: 0 | EY55: 0 | EZ55: 5 | FC55: 1 | FD55: 18 | FF55: 1764680 | FQ55: 0 | FR55: =P55 -> 1507731 | FS55: 0 | FX55: 0 | FY55: 0 | GA55: [1 764 680 / 1,22 / 7,57] + 3% Трансп + 1,2% Заг.скл | GD55: 1 | GF55: -1036281574 | GG55: 2 | GH55: 3 | GI55: 5 | GJ55: 0 | GK55: 0 | GL55: =ROUND(IF(AND(BH55=3,BI55=3,FS55<>0),P55,0),2) -> 0 | GM55: =ROUND(O55+X55+Y55,2)+GX55 -> 1507731 | GN55: =IF(OR(BI55=0,BI55=1),GM55-GX55,0) -> 0 | GO55: =IF(BI55=2,GM55-GX55,0) -> 0 | GP55: =IF(BI55=4,GM55-GX55,0) -> 0 | GR55: 1 | GS55: 1 | GT55: 0 | GV55: =ROUND((GT55),6) -> 0 | GW55: 1 | GX55: =ROUND(HC55*I55,2) -> 0 | HA55: 0 | HB55: 0 | HC55: =GV55*GW55 -> 0 | HE55: 3 | HF55: 1,2 | HS55: 0 | IK55: 0
A56: 17 | B56: 1 | C56: =ROW(SmtRes!A160) -> 160 | D56: =ROW(EtalonRes!A201) -> 201 | E56: 6 | F56: 4.12-50-6 | G56: Монтаж арматуры фланцевой с электрическим приводом на номинальное давление до 4 МПа, номинальный диаметр прохода 100 мм | H56: 1 ШТ. | I56: 1 | J56: 0 | K56: 1 | O56: =ROUND(CP56,2) -> 102.49 | P56: =ROUND((ROUND((AC56*AW56*I56),2)*BC56),2) -> 4.04 | Q56: =(ROUND((ROUND((((ET56*1.2))*AV56*I56),2)*BB56),2)+ROUND((ROUND(((AE56-((EU56*1.2)))*AV56*I56),2)*BS56),2)) -> 9.58 | R56: =(ROUND((ROUND((((EU56*1.2))*AV56*I56),2)*BS56),2)+ROUND((ROUND(((AE56-((EU56*1.2)))*AV56*I56),2)*BS56),2)) -> 1.46 | S56: =ROUND((ROUND((AF56*AV56*I56),2)*BA56),2) -> 88.87 | T56: =ROUND(CU56*I56,2) -> 0 | U56: =CV56*I56 -> 7.0422 | V56: =CW56*I56 -> 0 | W56: =ROUND(CX56*I56,2) -> 0 | X56: =(ROUND((((S56+ROUND((ROUND((((EU56*1.2))*AV56*I56),2)*BS56),2))*AT56)/100),2)+ROUND(((ROUND((ROUND(((AE56-((EU56*1.2)))*AV56*I56),2)*BS56),2)*AT56)/100),2)) -> 81.3 | Y56: =(ROUND((((S56+ROUND((ROUND((((EU56*1.2))*AV56*I56),2)*BS56),2))*AU56)/100),2)+ROUND(((ROUND((ROUND(((AE56-((EU56*1.2)))*AV56*I56),2)*BS56),2)*AU56)/100),2)) -> 41.55 | AA56: 55747649 | AB56: =ROUND((AC56+AD56+AF56),6) -> 96.198 | AC56: =ROUND(((ES56*1)),6) -> 3.93 | AD56: =ROUND(((((ET56*1.2))-((EU56*1.2)))+AE56),6) -> 8.976 | AE56: =ROUND(((EU56*1.2)),6) -> 1.368 | AF56: =ROUND(((EV56*1.2)),6) -> 83.292 | AG56: =ROUND((AP56),6) -> 0 | AH56: =((EW56*1.2)) -> 6.6 | AI56: =((EX56*1.2)) -> 0 | AJ56: =(AS56) -> 0 | AK56: 80.82 | AL56: 3.93 | AM56: 7.48 | AN56: 1.14 | AO56: 69.41 | AP56: 0 | AQ56: 5.5 | AR56: 0 | AS56: 0 | AT56: 90 | AU56: 46 | AV56: 1.067 | AW56: 1.028 | AZ56: 1 | BA56: 1 | BB56: 1 | BC56: 1 | BH56: 0 | BI56: 2 | BJ56: ТСН-2001.4 Доп. 68, Сб. 12, т. 50, поз. 6 | BM56: 73 | BN56: 0 | BO56: 4.12-50-6 | BP56: 1 | BQ56: 40 | BR56: 0 | BS56: 1 | BT56: 1 | BU56: 1 | BV56: 1 | BW56: 1 | BX56: 1 | BZ56: 90 | CA56: 46 | CE56: 1566 | CF56: 0 | CG56: 0 | CM56: 0 | CN56: Поправка: Гл.12.Прил.8.п.8. 3_12.00.01.11.001 Наименование: При наличии напряженных и стесненных условий производства работ (стесненность, сложность складирования и транспортной логистики и т.п.) для объектов, расположенных в пределах круговой магистральной системы улиц "Садовое кольцо" города Москвы | CO56: 0 | CP56: =(P56+Q56+S56) -> 102.49 | CQ56: =ROUND((ROUND((AC56*AW56*1),2)*BC56),2) -> 4.04 | CR56: =(ROUND((ROUND((((ET56*1.2))*AV56*1),2)*BB56),2)+ROUND((ROUND(((AE56-((EU56*1.2)))*AV56*1),2)*BS56),2)) -> 9.58 | CS56: =(ROUND((ROUND((((EU56*1.2))*AV56*1),2)*BS56),2)+ROUND((ROUND(((AE56-((EU56*1.2)))*AV56*1),2)*BS56),2)) -> 1.46 | CT56: =ROUND((ROUND((AF56*AV56*1),2)*BA56),2) -> 88.87 | CU56: =AG56 -> 0 | CV56: =(AH56*AV56) -> 7.0422 | CW56: =AI56 -> 0 | CX56: =AJ56 -> 0 | CY56: =(ROUND((((S56+ROUND((ROUND((((EU56*1.2))*AV56*1),2)*BS56),2))*AT56)/100),2)+ROUND(((ROUND((ROUND(((AE56-((EU56*1.2)))*AV56*1),2)*BS56),2)*AT56)/100),2)) -> 81.3 | CZ56: =(ROUND((((S56+ROUND((ROUND((((EU56*1.2))*AV56*1),2)*BS56),2))*AU56)/100),2)+ROUND(((ROUND((ROUND(((AE56-((EU56*1.2)))*AV56*1),2)*BS56),2)*AU56)/100),2)) -> 41.55 | DB56: 33 | DD56: *1 | DE56: *1,2 | DF56: *1,2 | DG56: *1,2 | DI56: *1,2 | DJ56: *1,2 | DN56: 0 | DO56: 0 | DP56: 1 | DQ56: 1 | DU56: 1013 | DV56: 1 ШТ. | DW56: 1 ШТ. | DX56: 1 | EE56: 56938740 | EF56: 40 | EG56: Монтаж оборудования | EH56: 0 | EJ56: 2 | EK56: 73 | EL56: ТСН-2001.4-12. Технологические трубопроводы | EM56: ТСН-2001.4-12-1 | EO56: Поправка: Гл.12.Прил.8.п.8. 3_12.00.01.11.001 | EQ56: 131072 | ER56: 80.82 | ES56: 3.93 | ET56: 7.48 | EU56: 1.14 | EV56: 69.41 | EW56: 5.5 | EX56: 0 | EY56: 0 | FQ56: 0 | FR56: 0 | FS56: 2 | FX56: 90 | FY56: 46 | GD56: 1 | GF56: -355409604 | GG56: 2 | GH56: 1 | GI56: 2 | GJ56: 0 | GK56: 0 | GL56: =ROUND(IF(AND(BH56=3,BI56=3,FS56<>0),P56,0),2) -> 0 | GM56: =ROUND(O56+X56+Y56,2)+GX56 -> 225.34 | GN56: =IF(OR(BI56=0,BI56=1),GM56-GX56,0) -> 0 | GO56: =IF(BI56=2,GM56-GX56,0) -> 225.34 | GP56: =IF(BI56=4,GM56-GX56,0) -> 0 | GR56: 0 | GS56: 3 | GT56: 0 | GV56: =ROUND((GT56),6) -> 0 | GW56: 1 | GX56: =ROUND(HC56*I56,2) -> 0 | HA56: 0 | HB56: 0 | HC56: =GV56*GW56 -> 0 | HS56: 0 | IK56: 0
A57: 17 | B57: 1 | C57: =ROW(SmtRes!A164) -> 164 | D57: =ROW(EtalonRes!A206) -> 206 | E57: 6 | F57: 4.12-50-6 | G57: Монтаж арматуры фланцевой с электрическим приводом на номинальное давление до 4 МПа, номинальный диаметр прохода 100 мм | H57: 1 ШТ. | I57: 1 | J57: 0 | K57: 1 | O57: =ROUND(CP57,2) -> 5189.49 | P57: =ROUND((ROUND((AC57*AW57*I57),2)*BC57),2) -> 18.14 | Q57: =(ROUND((ROUND((((ET57*1.2))*AV57*I57),2)*BB57),2)+ROUND((ROUND(((AE57-((EU57*1.2)))*AV57*I57),2)*BS57),2)) -> 163.53 | R57: =(ROUND((ROUND((((EU57*1.2))*AV57*I57),2)*BS57),2)+ROUND((ROUND(((AE57-((EU57*1.2)))*AV57*I57),2)*BS57),2)) -> 82.27 | S57: =ROUND((ROUND((AF57*AV57*I57),2)*BA57),2) -> 5007.82 | T57: =ROUND(CU57*I57,2) -> 0 | U57: =CV57*I57 -> 7.0422 | V57: =CW57*I57 -> 0 | W57: =ROUND(CX57*I57,2) -> 0 | X57: =(ROUND((((S57+ROUND((ROUND((((EU57*1.2))*AV57*I57),2)*BS57),2))*AT57)/100),2)+ROUND(((ROUND((ROUND(((AE57-((EU57*1.2)))*AV57*I57),2)*BS57),2)*AT57)/100),2)) -> 4581.08 | Y57: =(ROUND((((S57+ROUND((ROUND((((EU57*1.2))*AV57*I57),2)*BS57),2))*AU57)/100),2)+ROUND(((ROUND((ROUND(((AE57-((EU57*1.2)))*AV57*I57),2)*BS57),2)*AU57)/100),2)) -> 2341.44 | AA57: 55747651 | AB57: =ROUND((AC57+AD57+AF57),6) -> 96.198 | AC57: =ROUND(((ES57*1)),6) -> 3.93 | AD57: =ROUND(((((ET57*1.2))-((EU57*1.2)))+AE57),6) -> 8.976 | AE57: =ROUND(((EU57*1.2)),6) -> 1.368 | AF57: =ROUND(((EV57*1.2)),6) -> 83.292 | AG57: =ROUND((AP57),6) -> 0 | AH57: =((EW57*1.2)) -> 6.6 | AI57: =((EX57*1.2)) -> 0 | AJ57: =(AS57) -> 0 | AK57: 80.82 | AL57: 3.93 | AM57: 7.48 | AN57: 1.14 | AO57: 69.41 | AP57: 0 | AQ57: 5.5 | AR57: 0 | AS57: 0 | AT57: 90 | AU57: 46 | AV57: 1.067 | AW57: 1.028 | AZ57: 1 | BA57: 56.35 | BB57: 17.07 | BC57: 4.49 | BH57: 0 | BI57: 2 | BJ57: ТСН-2001.4 Доп. 68, Сб. 12, т. 50, поз. 6 | BM57: 73 | BN57: 0 | BO57: 4.12-50-6 | BP57: 1 | BQ57: 40 | BR57: 0 | BS57: 56.35 | BT57: 1 | BU57: 1 | BV57: 1 | BW57: 1 | BX57: 1 | BZ57: 90 | CA57: 46 | CE57: 1566 | CF57: 0 | CG57: 0 | CM57: 0 | CN57: Поправка: Гл.12.Прил.8.п.8. 3_12.00.01.11.001 Наименование: При наличии напряженных и стесненных условий производства работ (стесненность, сложность складирования и транспортной логистики и т.п.) для объектов, расположенных в пределах круговой магистральной системы улиц "Садовое кольцо" города Москвы | CO57: 0 | CP57: =(P57+Q57+S57) -> 5189.49 | CQ57: =ROUND((ROUND((AC57*AW57*1),2)*BC57),2) -> 18.14 | CR57: =(ROUND((ROUND((((ET57*1.2))*AV57*1),2)*BB57),2)+ROUND((ROUND(((AE57-((EU57*1.2)))*AV57*1),2)*BS57),2)) -> 163.53 | CS57: =(ROUND((ROUND((((EU57*1.2))*AV57*1),2)*BS57),2)+ROUND((ROUND(((AE57-((EU57*1.2)))*AV57*1),2)*BS57),2)) -> 82.27 | CT57: =ROUND((ROUND((AF57*AV57*1),2)*BA57),2) -> 5007.82 | CU57: =AG57 -> 0 | CV57: =(AH57*AV57) -> 7.0422 | CW57: =AI57 -> 0 | CX57: =AJ57 -> 0 | CY57: =(ROUND((((S57+ROUND((ROUND((((EU57*1.2))*AV57*1),2)*BS57),2))*AT57)/100),2)+ROUND(((ROUND((ROUND(((AE57-((EU57*1.2)))*AV57*1),2)*BS57),2)*AT57)/100),2)) -> 4581.08 | CZ57: =(ROUND((((S57+ROUND((ROUND((((EU57*1.2))*AV57*1),2)*BS57),2))*AU57)/100),2)+ROUND(((ROUND((ROUND(((AE57-((EU57*1.2)))*AV57*1),2)*BS57),2)*AU57)/100),2)) -> 2341.44 | DB57: 34 | DD57: *1 | DE57: *1,2 | DF57: *1,2 | DG57: *1,2 | DI57: *1,2 | DJ57: *1,2 | DN57: 0 | DO57: 0 | DP57: 1 | DQ57: 1 | DU57: 1013 | DV57: 1 ШТ. | DW57: 1 ШТ. | DX57: 1 | EE57: 56938740 | EF57: 40 | EG57: Монтаж оборудования | EH57: 0 | EJ57: 2 | EK57: 73 | EL57: ТСН-2001.4-12. Технологические трубопроводы | EM57: ТСН-2001.4-12-1 | EO57: Поправка: Гл.12.Прил.8.п.8. 3_12.00.01.11.001 | EQ57: 131072 | ER57: 80.82 | ES57: 3.93 | ET57: 7.48 | EU57: 1.14 | EV57: 69.41 | EW57: 5.5 | EX57: 0 | EY57: 0 | FQ57: 0 | FR57: 0 | FS57: 2 | FX57: 90 | FY57: 46 | GD57: 1 | GF57: -355409604 | GG57: 2 | GH57: 1 | GI57: 2 | GJ57: 0 | GK57: 0 | GL57: =ROUND(IF(AND(BH57=3,BI57=3,FS57<>0),P57,0),2) -> 0 | GM57: =ROUND(O57+X57+Y57,2)+GX57 -> 12112.01 | GN57: =IF(OR(BI57=0,BI57=1),GM57-GX57,0) -> 0 | GO57: =IF(BI57=2,GM57-GX57,0) -> 12112.01 | GP57: =IF(BI57=4,GM57-GX57,0) -> 0 | GR57: 0 | GS57: 3 | GT57: 0 | GV57: =ROUND((GT57),6) -> 0 | GW57: 1 | GX57: =ROUND(HC57*I57,2) -> 0 | HA57: 0 | HB57: 0 | HC57: =GV57*GW57 -> 0 | HS57: 0 | IK57: 0
A58: 18 | B58: 1 | C58: 160 | E58: 6,1 | F58: КА. п. 2 | G58: Узел управления спринклерный водозаполненный УУ-С100/1,6В-ВФ.О4 Прямоточный-100 | H58: шт. | I58: =I56*J58 -> 1 | J58: 1 | K58: 1 | O58: =ROUND(CP58,2) -> 7821.6 | P58: =ROUND((ROUND((AC58*I58),2)*BC58),2) -> 7821.6 | Q58: =(ROUND((ROUND(((ET58)*AV58*I58),2)*BB58),2)+ROUND((ROUND(((AE58-(EU58))*AV58*I58),2)*BS58),2)) -> 0 | R58: =(ROUND((ROUND(((EU58)*AV58*I58),2)*BS58),2)+ROUND((ROUND(((AE58-(EU58))*AV58*I58),2)*BS58),2)) -> 0 | S58: =ROUND((ROUND((AF58*AV58*I58),2)*BA58),2) -> 0 | T58: =ROUND(CU58*I58,2) -> 0 | U58: =CV58*I58 -> 0 | V58: =CW58*I58 -> 0 | W58: =ROUND(CX58*I58,2) -> 0 | X58: =(ROUND((((S58+ROUND((ROUND(((EU58)*AV58*I58),2)*BS58),2))*AT58)/100),2)+ROUND(((ROUND((ROUND(((AE58-(EU58))*AV58*I58),2)*BS58),2)*AT58)/100),2)) -> 0 | Y58: =(ROUND((((S58+ROUND((ROUND(((EU58)*AV58*I58),2)*BS58),2))*AU58)/100),2)+ROUND(((ROUND((ROUND(((AE58-(EU58))*AV58*I58),2)*BS58),2)*AU58)/100),2)) -> 0 | AA58: 55747649 | AB58: =ROUND((AC58+AD58+AF58),6) -> 7821.6 | AC58: =ROUND((ES58),6) -> 7821.6 | AD58: =ROUND((((ET58)-(EU58))+AE58),6) -> 0 | AE58: =ROUND((EU58),6) -> 0 | AF58: =ROUND((EV58),6) -> 0 | AG58: =ROUND((AP58),6) -> 0 | AH58: =(EW58) -> 0 | AI58: =(EX58) -> 0 | AJ58: =(AS58) -> 0 | AK58: 7821.6 | AL58: 7821.6 | AM58: 0 | AN58: 0 | AO58: 0 | AP58: 0 | AQ58: 0 | AR58: 0 | AS58: 0 | AT58: 0 | AU58: 0 | AV58: 1 | AW58: 1 | AZ58: 1 | BA58: 1 | BB58: 1 | BC58: 1 | BH58: 3 | BI58: 3 | BM58: 746 | BN58: 0 | BP58: 0 | BQ58: 130 | BR58: 0 | BS58: 1 | BT58: 1 | BU58: 1 | BV58: 1 | BW58: 1 | BX58: 1 | BZ58: 90 | CA58: 46 | CE58: 1566 | CF58: 0 | CG58: 0 | CM58: 0 | CO58: 0 | CP58: =(P58+Q58+S58) -> 7821.6 | CQ58: =ROUND((ROUND((AC58*1),2)*BC58),2) -> 7821.6 | CR58: =(ROUND((ROUND(((ET58)*AV58*1),2)*BB58),2)+ROUND((ROUND(((AE58-(EU58))*AV58*1),2)*BS58),2)) -> 0 | CS58: =(ROUND((ROUND(((EU58)*AV58*1),2)*BS58),2)+ROUND((ROUND(((AE58-(EU58))*AV58*1),2)*BS58),2)) -> 0 | CT58: =ROUND((ROUND((AF58*AV58*1),2)*BA58),2) -> 0 | CU58: =AG58 -> 0 | CV58: =(AH58*AV58) -> 0 | CW58: =AI58 -> 0 | CX58: =AJ58 -> 0 | CY58: =(ROUND((((S58+ROUND((ROUND(((EU58)*AV58*1),2)*BS58),2))*AT58)/100),2)+ROUND(((ROUND((ROUND(((AE58-(EU58))*AV58*1),2)*BS58),2)*AT58)/100),2)) -> 0 | CZ58: =(ROUND((((S58+ROUND((ROUND(((EU58)*AV58*1),2)*BS58),2))*AU58)/100),2)+ROUND(((ROUND((ROUND(((AE58-(EU58))*AV58*1),2)*BS58),2)*AU58)/100),2)) -> 0 | DN58: 0 | DO58: 0 | DP58: 1 | DQ58: 1 | DU58: 1010 | DV58: шт. | DW58: шт. | DX58: 1 | EE58: 56938841 | EF58: 130 | EG58: Сметная стоимость оборудования | EH58: 0 | EJ58: 3 | EK58: 746 | EL58: ТСН-2001.13. Сметная стоимость оборудования | EM58: ТСН-2001.13 | EQ58: 0 | ER58: 0 | ES58: 7821.6 | ET58: 0 | EU58: 0 | EV58: 0 | EW58: 0 | EX58: 0 | FQ58: 0 | FR58: =P58 -> 7821.6 | FS58: 0 | FX58: 90 | FY58: 46 | GA58: [69 300 / 1,22 / 7,57] + 3% Трансп + 1,2% Заг.скл | GD58: 1 | GF58: -255262661 | GG58: 2 | GH58: 4 | GI58: -2 | GJ58: 0 | GK58: 0 | GL58: =ROUND(IF(AND(BH58=3,BI58=3,FS58<>0),P58,0),2) -> 0 | GM58: =ROUND(O58+X58+Y58,2)+GX58 -> 7821.6 | GN58: =IF(OR(BI58=0,BI58=1),GM58-GX58,0) -> 0 | GO58: =IF(BI58=2,GM58-GX58,0) -> 0 | GP58: =IF(BI58=4,GM58-GX58,0) -> 0 | GR58: 0 | GS58: 2 | GT58: 0 | GV58: =ROUND((GT58),6) -> 0 | GW58: 1 | GX58: =ROUND(HC58*I58,2) -> 0 | HA58: 0 | HB58: 0 | HC58: =GV58*GW58 -> 0 | HE58: 3 | HF58: 1,2 | HS58: 0 | IK58: 0
A59: 18 | B59: 1 | C59: 164 | E59: 6,1 | F59: КА. п. 2 | G59: Узел управления спринклерный водозаполненный УУ-С100/1,6В-ВФ.О4 Прямоточный-100 | H59: шт. | I59: =I57*J59 -> 1 | J59: 1 | K59: 1 | O59: =ROUND(CP59,2) -> 59209.51 | P59: =ROUND((ROUND((AC59*I59),2)*BC59),2) -> 59209.51 | Q59: =(ROUND((ROUND(((ET59)*AV59*I59),2)*BB59),2)+ROUND((ROUND(((AE59-(EU59))*AV59*I59),2)*BS59),2)) -> 0 | R59: =(ROUND((ROUND(((EU59)*AV59*I59),2)*BS59),2)+ROUND((ROUND(((AE59-(EU59))*AV59*I59),2)*BS59),2)) -> 0 | S59: =ROUND((ROUND((AF59*AV59*I59),2)*BA59),2) -> 0 | T59: =ROUND(CU59*I59,2) -> 0 | U59: =CV59*I59 -> 0 | V59: =CW59*I59 -> 0 | W59: =ROUND(CX59*I59,2) -> 0 | X59: =(ROUND((((S59+ROUND((ROUND(((EU59)*AV59*I59),2)*BS59),2))*AT59)/100),2)+ROUND(((ROUND((ROUND(((AE59-(EU59))*AV59*I59),2)*BS59),2)*AT59)/100),2)) -> 0 | Y59: =(ROUND((((S59+ROUND((ROUND(((EU59)*AV59*I59),2)*BS59),2))*AU59)/100),2)+ROUND(((ROUND((ROUND(((AE59-(EU59))*AV59*I59),2)*BS59),2)*AU59)/100),2)) -> 0 | AA59: 55747651 | AB59: =ROUND((AC59+AD59+AF59),6) -> 7821.6 | AC59: =ROUND((ES59),6) -> 7821.6 | AD59: =ROUND((((ET59)-(EU59))+AE59),6) -> 0 | AE59: =ROUND((EU59),6) -> 0 | AF59: =ROUND((EV59),6) -> 0 | AG59: =ROUND((AP59),6) -> 0 | AH59: =(EW59) -> 0 | AI59: =(EX59) -> 0 | AJ59: =(AS59) -> 0 | AK59: 7821.6 | AL59: 7821.6 | AM59: 0 | AN59: 0 | AO59: 0 | AP59: 0 | AQ59: 0 | AR59: 0 | AS59: 0 | AT59: 0 | AU59: 0 | AV59: 1 | AW59: 1 | AZ59: 1 | BA59: 1 | BB59: 1 | BC59: 7.57 | BH59: 3 | BI59: 3 | BM59: 746 | BN59: 0 | BP59: 0 | BQ59: 130 | BR59: 0 | BS59: 1 | BT59: 1 | BU59: 1 | BV59: 1 | BW59: 1 | BX59: 1 | BZ59: 90 | CA59: 46 | CE59: 1566 | CF59: 0 | CG59: 0 | CM59: 0 | CO59: 0 | CP59: =(P59+Q59+S59) -> 59209.51 | CQ59: =ROUND((ROUND((AC59*1),2)*BC59),2) -> 59209.51 | CR59: =(ROUND((ROUND(((ET59)*AV59*1),2)*BB59),2)+ROUND((ROUND(((AE59-(EU59))*AV59*1),2)*BS59),2)) -> 0 | CS59: =(ROUND((ROUND(((EU59)*AV59*1),2)*BS59),2)+ROUND((ROUND(((AE59-(EU59))*AV59*1),2)*BS59),2)) -> 0 | CT59: =ROUND((ROUND((AF59*AV59*1),2)*BA59),2) -> 0 | CU59: =AG59 -> 0 | CV59: =(AH59*AV59) -> 0 | CW59: =AI59 -> 0 | CX59: =AJ59 -> 0 | CY59: =(ROUND((((S59+ROUND((ROUND(((EU59)*AV59*1),2)*BS59),2))*AT59)/100),2)+ROUND(((ROUND((ROUND(((AE59-(EU59))*AV59*1),2)*BS59),2)*AT59)/100),2)) -> 0 | CZ59: =(ROUND((((S59+ROUND((ROUND(((EU59)*AV59*1),2)*BS59),2))*AU59)/100),2)+ROUND(((ROUND((ROUND(((AE59-(EU59))*AV59*1),2)*BS59),2)*AU59)/100),2)) -> 0 | DN59: 0 | DO59: 0 | DP59: 1 | DQ59: 1 | DU59: 1010 | DV59: шт. | DW59: шт. | DX59: 1 | EE59: 56938841 | EF59: 130 | EG59: Сметная стоимость оборудования | EH59: 0 | EJ59: 3 | EK59: 746 | EL59: ТСН-2001.13. Сметная стоимость оборудования | EM59: ТСН-2001.13 | EQ59: 0 | ER59: 7821.6 | ES59: 7821.6 | ET59: 0 | EU59: 0 | EV59: 0 | EW59: 0 | EX59: 0 | EZ59: 5 | FC59: 1 | FD59: 18 | FF59: 69300 | FQ59: 0 | FR59: =P59 -> 59209.51 | FS59: 0 | FX59: 90 | FY59: 46 | GA59: [69 300 / 1,22 / 7,57] + 3% Трансп + 1,2% Заг.скл | GD59: 1 | GF59: -255262661 | GG59: 2 | GH59: 3 | GI59: 5 | GJ59: 0 | GK59: 0 | GL59: =ROUND(IF(AND(BH59=3,BI59=3,FS59<>0),P59,0),2) -> 0 | GM59: =ROUND(O59+X59+Y59,2)+GX59 -> 59209.51 | GN59: =IF(OR(BI59=0,BI59=1),GM59-GX59,0) -> 0 | GO59: =IF(BI59=2,GM59-GX59,0) -> 0 | GP59: =IF(BI59=4,GM59-GX59,0) -> 0 | GR59: 1 | GS59: 1 | GT59: 0 | GV59: =ROUND((GT59),6) -> 0 | GW59: 1 | GX59: =ROUND(HC59*I59,2) -> 0 | HA59: 0 | HB59: 0 | HC59: =GV59*GW59 -> 0 | HE59: 3 | HF59: 1,2 | HS59: 0 | IK59: 0
A60: 17 | B60: 1 | C60: =ROW(SmtRes!A168) -> 168 | D60: =ROW(EtalonRes!A211) -> 211 | E60: 7 | F60: 4.12-48-10 | G60: Монтаж арматуры фланцевой с ручным приводом или без привода на номинальное давление до 4 МПа, номинальный диаметр прохода 100 мм | H60: 1 ШТ. | I60: =ROUND(9,9) -> 9 | J60: 0 | K60: =ROUND(9,9) -> 9 | O60: =ROUND(CP60,2) -> 661.28 | P60: =ROUND((ROUND((AC60*AW60*I60),2)*BC60),2) -> 36.36 | Q60: =(ROUND((ROUND((((ET60*1.2))*AV60*I60),2)*BB60),2)+ROUND((ROUND(((AE60-((EU60*1.2)))*AV60*I60),2)*BS60),2)) -> 28.69 | R60: =(ROUND((ROUND((((EU60*1.2))*AV60*I60),2)*BS60),2)+ROUND((ROUND(((AE60-((EU60*1.2)))*AV60*I60),2)*BS60),2)) -> 4.38 | S60: =ROUND((ROUND((AF60*AV60*I60),2)*BA60),2) -> 596.23 | T60: =ROUND(CU60*I60,2) -> 0 | U60: =CV60*I60 -> 47.24676 | V60: =CW60*I60 -> 0 | W60: =ROUND(CX60*I60,2) -> 0 | X60: =(ROUND((((S60+ROUND((ROUND((((EU60*1.2))*AV60*I60),2)*BS60),2))*AT60)/100),2)+ROUND(((ROUND((ROUND(((AE60-((EU60*1.2)))*AV60*I60),2)*BS60),2)*AT60)/100),2)) -> 540.55 | Y60: =(ROUND((((S60+ROUND((ROUND((((EU60*1.2))*AV60*I60),2)*BS60),2))*AU60)/100),2)+ROUND(((ROUND((ROUND(((AE60-((EU60*1.2)))*AV60*I60),2)*BS60),2)*AU60)/100),2)) -> 276.28 | AA60: 55747649 | AB60: =ROUND((AC60+AD60+AF60),6) -> 69.006 | AC60: =ROUND(((ES60*1)),6) -> 3.93 | AD60: =ROUND(((((ET60*1.2))-((EU60*1.2)))+AE60),6) -> 2.988 | AE60: =ROUND(((EU60*1.2)),6) -> 0.456 | AF60: =ROUND(((EV60*1.2)),6) -> 62.088 | AG60: =ROUND((AP60),6) -> 0 | AH60: =((EW60*1.2)) -> 4.92 | AI60: =((EX60*1.2)) -> 0 | AJ60: =(AS60) -> 0 | AK60: 58.16 | AL60: 3.93 | AM60: 2.49 | AN60: 0.38 | AO60: 51.74 | AP60: 0 | AQ60: 4.1 | AR60: 0 | AS60: 0 | AT60: 90 | AU60: 46 | AV60: 1.067 | AW60: 1.028 | AZ60: 1 | BA60: 1 | BB60: 1 | BC60: 1 | BH60: 0 | BI60: 2 | BJ60: ТСН-2001.4 Доп. 68, Сб. 12, т. 48, поз. 10 | BM60: 73 | BN60: 0 | BO60: 4.12-48-10 | BP60: 1 | BQ60: 40 | BR60: 0 | BS60: 1 | BT60: 1 | BU60: 1 | BV60: 1 | BW60: 1 | BX60: 1 | BZ60: 90 | CA60: 46 | CE60: 1566 | CF60: 0 | CG60: 0 | CM60: 0 | CN60: Поправка: Гл.12.Прил.8.п.8. 3_12.00.01.11.001 Наименование: При наличии напряженных и стесненных условий производства работ (стесненность, сложность складирования и транспортной логистики и т.п.) для объектов, расположенных в пределах круговой магистральной системы улиц "Садовое кольцо" города Москвы | CO60: 0 | CP60: =(P60+Q60+S60) -> 661.28 | CQ60: =ROUND((ROUND((AC60*AW60*1),2)*BC60),2) -> 4.04 | CR60: =(ROUND((ROUND((((ET60*1.2))*AV60*1),2)*BB60),2)+ROUND((ROUND(((AE60-((EU60*1.2)))*AV60*1),2)*BS60),2)) -> 3.19 | CS60: =(ROUND((ROUND((((EU60*1.2))*AV60*1),2)*BS60),2)+ROUND((ROUND(((AE60-((EU60*1.2)))*AV60*1),2)*BS60),2)) -> 0.49 | CT60: =ROUND((ROUND((AF60*AV60*1),2)*BA60),2) -> 66.25 | CU60: =AG60 -> 0 | CV60: =(AH60*AV60) -> 5.24964 | CW60: =AI60 -> 0 | CX60: =AJ60 -> 0 | CY60: =(ROUND((((S60+ROUND((ROUND((((EU60*1.2))*AV60*1),2)*BS60),2))*AT60)/100),2)+ROUND(((ROUND((ROUND(((AE60-((EU60*1.2)))*AV60*1),2)*BS60),2)*AT60)/100),2)) -> 537.05 | CZ60: =(ROUND((((S60+ROUND((ROUND((((EU60*1.2))*AV60*1),2)*BS60),2))*AU60)/100),2)+ROUND(((ROUND((ROUND(((AE60-((EU60*1.2)))*AV60*1),2)*BS60),2)*AU60)/100),2)) -> 274.49 | DB60: 35 | DD60: *1 | DE60: *1,2 | DF60: *1,2 | DG60: *1,2 | DI60: *1,2 | DJ60: *1,2 | DN60: 0 | DO60: 0 | DP60: 1 | DQ60: 1 | DU60: 1013 | DV60: 1 ШТ. | DW60: 1 ШТ. | DX60: 1 | EE60: 56938740 | EF60: 40 | EG60: Монтаж оборудования | EH60: 0 | EJ60: 2 | EK60: 73 | EL60: ТСН-2001.4-12. Технологические трубопроводы | EM60: ТСН-2001.4-12-1 | EO60: Поправка: Гл.12.Прил.8.п.8. 3_12.00.01.11.001 | EQ60: 131072 | ER60: 58.16 | ES60: 3.93 | ET60: 2.49 | EU60: 0.38 | EV60: 51.74 | EW60: 4.1 | EX60: 0 | EY60: 0 | FQ60: 0 | FR60: 0 | FS60: 2 | FX60: 90 | FY60: 46 | GD60: 1 | GF60: 1723816868 | GG60: 2 | GH60: 1 | GI60: 2 | GJ60: 0 | GK60: 0 | GL60: =ROUND(IF(AND(BH60=3,BI60=3,FS60<>0),P60,0),2) -> 0 | GM60: =ROUND(O60+X60+Y60,2)+GX60 -> 1478.11 | GN60: =IF(OR(BI60=0,BI60=1),GM60-GX60,0) -> 0 | GO60: =IF(BI60=2,GM60-GX60,0) -> 1478.11 | GP60: =IF(BI60=4,GM60-GX60,0) -> 0 | GR60: 0 | GS60: 3 | GT60: 0 | GV60: =ROUND((GT60),6) -> 0 | GW60: 1 | GX60: =ROUND(HC60*I60,2) -> 0 | HA60: 0 | HB60: 0 | HC60: =GV60*GW60 -> 0 | HS60: 0 | IK60: 0
A61: 17 | B61: 1 | C61: =ROW(SmtRes!A172) -> 172 | D61: =ROW(EtalonRes!A216) -> 216 | E61: 7 | F61: 4.12-48-10 | G61: Монтаж арматуры фланцевой с ручным приводом или без привода на номинальное давление до 4 МПа, номинальный диаметр прохода 100 мм | H61: 1 ШТ. | I61: =ROUND(9,9) -> 9 | J61: 0 | K61: =ROUND(9,9) -> 9 | O61: =ROUND(CP61,2) -> 34251.13 | P61: =ROUND((ROUND((AC61*AW61*I61),2)*BC61),2) -> 163.26 | Q61: =(ROUND((ROUND((((ET61*1.2))*AV61*I61),2)*BB61),2)+ROUND((ROUND(((AE61-((EU61*1.2)))*AV61*I61),2)*BS61),2)) -> 490.31 | R61: =(ROUND((ROUND((((EU61*1.2))*AV61*I61),2)*BS61),2)+ROUND((ROUND(((AE61-((EU61*1.2)))*AV61*I61),2)*BS61),2)) -> 246.81 | S61: =ROUND((ROUND((AF61*AV61*I61),2)*BA61),2) -> 33597.56 | T61: =ROUND(CU61*I61,2) -> 0 | U61: =CV61*I61 -> 47.24676 | V61: =CW61*I61 -> 0 | W61: =ROUND(CX61*I61,2) -> 0 | X61: =(ROUND((((S61+ROUND((ROUND((((EU61*1.2))*AV61*I61),2)*BS61),2))*AT61)/100),2)+ROUND(((ROUND((ROUND(((AE61-((EU61*1.2)))*AV61*I61),2)*BS61),2)*AT61)/100),2)) -> 30459.93 | Y61: =(ROUND((((S61+ROUND((ROUND((((EU61*1.2))*AV61*I61),2)*BS61),2))*AU61)/100),2)+ROUND(((ROUND((ROUND(((AE61-((EU61*1.2)))*AV61*I61),2)*BS61),2)*AU61)/100),2)) -> 15568.41 | AA61: 55747651 | AB61: =ROUND((AC61+AD61+AF61),6) -> 69.006 | AC61: =ROUND(((ES61*1)),6) -> 3.93 | AD61: =ROUND(((((ET61*1.2))-((EU61*1.2)))+AE61),6) -> 2.988 | AE61: =ROUND(((EU61*1.2)),6) -> 0.456 | AF61: =ROUND(((EV61*1.2)),6) -> 62.088 | AG61: =ROUND((AP61),6) -> 0 | AH61: =((EW61*1.2)) -> 4.92 | AI61: =((EX61*1.2)) -> 0 | AJ61: =(AS61) -> 0 | AK61: 58.16 | AL61: 3.93 | AM61: 2.49 | AN61: 0.38 | AO61: 51.74 | AP61: 0 | AQ61: 4.1 | AR61: 0 | AS61: 0 | AT61: 90 | AU61: 46 | AV61: 1.067 | AW61: 1.028 | AZ61: 1 | BA61: 56.35 | BB61: 17.09 | BC61: 4.49 | BH61: 0 | BI61: 2 | BJ61: ТСН-2001.4 Доп. 68, Сб. 12, т. 48, поз. 10 | BM61: 73 | BN61: 0 | BO61: 4.12-48-10 | BP61: 1 | BQ61: 40 | BR61: 0 | BS61: 56.35 | BT61: 1 | BU61: 1 | BV61: 1 | BW61: 1 | BX61: 1 | BZ61: 90 | CA61: 46 | CE61: 1566 | CF61: 0 | CG61: 0 | CM61: 0 | CN61: Поправка: Гл.12.Прил.8.п.8. 3_12.00.01.11.001 Наименование: При наличии напряженных и стесненных условий производства работ (стесненность, сложность складирования и транспортной логистики и т.п.) для объектов, расположенных в пределах круговой магистральной системы улиц "Садовое кольцо" города Москвы | CO61: 0 | CP61: =(P61+Q61+S61) -> 34251.13 | CQ61: =ROUND((ROUND((AC61*AW61*1),2)*BC61),2) -> 18.14 | CR61: =(ROUND((ROUND((((ET61*1.2))*AV61*1),2)*BB61),2)+ROUND((ROUND(((AE61-((EU61*1.2)))*AV61*1),2)*BS61),2)) -> 54.52 | CS61: =(ROUND((ROUND((((EU61*1.2))*AV61*1),2)*BS61),2)+ROUND((ROUND(((AE61-((EU61*1.2)))*AV61*1),2)*BS61),2)) -> 27.61 | CT61: =ROUND((ROUND((AF61*AV61*1),2)*BA61),2) -> 3733.19 | CU61: =AG61 -> 0 | CV61: =(AH61*AV61) -> 5.24964 | CW61: =AI61 -> 0 | CX61: =AJ61 -> 0 | CY61: =(ROUND((((S61+ROUND((ROUND((((EU61*1.2))*AV61*1),2)*BS61),2))*AT61)/100),2)+ROUND(((ROUND((ROUND(((AE61-((EU61*1.2)))*AV61*1),2)*BS61),2)*AT61)/100),2)) -> 30262.65 | CZ61: =(ROUND((((S61+ROUND((ROUND((((EU61*1.2))*AV61*1),2)*BS61),2))*AU61)/100),2)+ROUND(((ROUND((ROUND(((AE61-((EU61*1.2)))*AV61*1),2)*BS61),2)*AU61)/100),2)) -> 15467.58 | DB61: 36 | DD61: *1 | DE61: *1,2 | DF61: *1,2 | DG61: *1,2 | DI61: *1,2 | DJ61: *1,2 | DN61: 0 | DO61: 0 | DP61: 1 | DQ61: 1 | DU61: 1013 | DV61: 1 ШТ. | DW61: 1 ШТ. | DX61: 1 | EE61: 56938740 | EF61: 40 | EG61: Монтаж оборудования | EH61: 0 | EJ61: 2 | EK61: 73 | EL61: ТСН-2001.4-12. Технологические трубопроводы | EM61: ТСН-2001.4-12-1 | EO61: Поправка: Гл.12.Прил.8.п.8. 3_12.00.01.11.001 | EQ61: 131072 | ER61: 58.16 | ES61: 3.93 | ET61: 2.49 | EU61: 0.38 | EV61: 51.74 | EW61: 4.1 | EX61: 0 | EY61: 0 | FQ61: 0 | FR61: 0 | FS61: 2 | FX61: 90 | FY61: 46 | GD61: 1 | GF61: 1723816868 | GG61: 2 | GH61: 1 | GI61: 2 | GJ61: 0 | GK61: 0 | GL61: =ROUND(IF(AND(BH61=3,BI61=3,FS61<>0),P61,0),2) -> 0 | GM61: =ROUND(O61+X61+Y61,2)+GX61 -> 80279.47 | GN61: =IF(OR(BI61=0,BI61=1),GM61-GX61,0) -> 0 | GO61: =IF(BI61=2,GM61-GX61,0) -> 80279.47 | GP61: =IF(BI61=4,GM61-GX61,0) -> 0 | GR61: 0 | GS61: 3 | GT61: 0 | GV61: =ROUND((GT61),6) -> 0 | GW61: 1 | GX61: =ROUND(HC61*I61,2) -> 0 | HA61: 0 | HB61: 0 | HC61: =GV61*GW61 -> 0 | HS61: 0 | IK61: 0
A62: 18 | B62: 1 | C62: 168 | E62: 7,1 | F62: 1.13-5-40 | G62: Затвор дисковый, поворотный, корпус из чугуна, диск из нержавеющей стали, с ручкой, номинальное давление PN 1,6 МПа, номинальный диаметр DN 100 мм | H62: шт. | I62: =I60*J62 -> 9 | J62: 1 | K62: 1 | O62: =ROUND(CP62,2) -> 19601.37 | P62: =ROUND((ROUND((AC62*AW62*I62),2)*BC62),2) -> 19601.37 | Q62: =(ROUND((ROUND(((ET62)*AV62*I62),2)*BB62),2)+ROUND((ROUND(((AE62-(EU62))*AV62*I62),2)*BS62),2)) -> 0 | R62: =(ROUND((ROUND(((EU62)*AV62*I62),2)*BS62),2)+ROUND((ROUND(((AE62-(EU62))*AV62*I62),2)*BS62),2)) -> 0 | S62: =ROUND((ROUND((AF62*AV62*I62),2)*BA62),2) -> 0 | T62: =ROUND(CU62*I62,2) -> 0 | U62: =CV62*I62 -> 0 | V62: =CW62*I62 -> 0 | W62: =ROUND(CX62*I62,2) -> 0 | X62: =(ROUND((((S62+ROUND((ROUND(((EU62)*AV62*I62),2)*BS62),2))*AT62)/100),2)+ROUND(((ROUND((ROUND(((AE62-(EU62))*AV62*I62),2)*BS62),2)*AT62)/100),2)) -> 0 | Y62: =(ROUND((((S62+ROUND((ROUND(((EU62)*AV62*I62),2)*BS62),2))*AU62)/100),2)+ROUND(((ROUND((ROUND(((AE62-(EU62))*AV62*I62),2)*BS62),2)*AU62)/100),2)) -> 0 | AA62: 55747649 | AB62: =ROUND((AC62+AD62+AF62),6) -> 2177.93 | AC62: =ROUND((ES62),6) -> 2177.93 | AD62: =ROUND((((ET62)-(EU62))+AE62),6) -> 0 | AE62: =ROUND((EU62),6) -> 0 | AF62: =ROUND((EV62),6) -> 0 | AG62: =ROUND((AP62),6) -> 0 | AH62: =(EW62) -> 0 | AI62: =(EX62) -> 0 | AJ62: =(AS62) -> 0 | AK62: 2177.93 | AL62: 2177.93 | AM62: 0 | AN62: 0 | AO62: 0 | AP62: 0 | AQ62: 0 | AR62: 0 | AS62: 0 | AT62: 90 | AU62: 46 | AV62: 1 | AW62: 1 | AZ62: 1 | BA62: 1 | BB62: 1 | BC62: 1 | BH62: 3 | BI62: 2 | BJ62: ТСН-2001.1 Доп. 79, Р. 13, о. 5, поз. 40 | BM62: 73 | BN62: 0 | BP62: 0 | BQ62: 40 | BR62: 0 | BS62: 1 | BT62: 1 | BU62: 1 | BV62: 1 | BW62: 1 | BX62: 1 | BZ62: 90 | CA62: 46 | CE62: 1566 | CF62: 0 | CG62: 0 | CM62: 0 | CO62: 0 | CP62: =(P62+Q62+S62) -> 19601.37 | CQ62: =ROUND((ROUND((AC62*AW62*1),2)*BC62),2) -> 2177.93 | CR62: =(ROUND((ROUND(((ET62)*AV62*1),2)*BB62),2)+ROUND((ROUND(((AE62-(EU62))*AV62*1),2)*BS62),2)) -> 0 | CS62: =(ROUND((ROUND(((EU62)*AV62*1),2)*BS62),2)+ROUND((ROUND(((AE62-(EU62))*AV62*1),2)*BS62),2)) -> 0 | CT62: =ROUND((ROUND((AF62*AV62*1),2)*BA62),2) -> 0 | CU62: =AG62 -> 0 | CV62: =(AH62*AV62) -> 0 | CW62: =AI62 -> 0 | CX62: =AJ62 -> 0 | CY62: =(ROUND((((S62+ROUND((ROUND(((EU62)*AV62*1),2)*BS62),2))*AT62)/100),2)+ROUND(((ROUND((ROUND(((AE62-(EU62))*AV62*1),2)*BS62),2)*AT62)/100),2)) -> 0 | CZ62: =(ROUND((((S62+ROUND((ROUND(((EU62)*AV62*1),2)*BS62),2))*AU62)/100),2)+ROUND(((ROUND((ROUND(((AE62-(EU62))*AV62*1),2)*BS62),2)*AU62)/100),2)) -> 0 | DN62: 0 | DO62: 0 | DP62: 1 | DQ62: 1 | DU62: 1010 | DV62: шт. | DW62: шт. | DX62: 1 | EE62: 56938740 | EF62: 40 | EG62: Монтаж оборудования | EH62: 0 | EJ62: 2 | EK62: 73 | EL62: ТСН-2001.4-12. Технологические трубопроводы | EM62: ТСН-2001.4-12-1 | EQ62: 0 | ER62: 2177.93 | ES62: 2177.93 | ET62: 0 | EU62: 0 | EV62: 0 | EW62: 0 | EX62: 0 | FQ62: 0 | FR62: 0 | FS62: 0 | FX62: 90 | FY62: 46 | GD62: 1 | GF62: 873960273 | GG62: 2 | GH62: 1 | GI62: -2 | GJ62: 0 | GK62: 0 | GL62: =ROUND(IF(AND(BH62=3,BI62=3,FS62<>0),P62,0),2) -> 0 | GM62: =ROUND(O62+X62+Y62,2)+GX62 -> 19601.37 | GN62: =IF(OR(BI62=0,BI62=1),GM62-GX62,0) -> 0 | GO62: =IF(BI62=2,GM62-GX62,0) -> 19601.37 | GP62: =IF(BI62=4,GM62-GX62,0) -> 0 | GR62: 0 | GS62: 3 | GT62: 0 | GV62: =ROUND((GT62),6) -> 0 | GW62: 1 | GX62: =ROUND(HC62*I62,2) -> 0 | HA62: 0 | HB62: 0 | HC62: =GV62*GW62 -> 0 | HS62: 0 | IK62: 0
A63: 18 | B63: 1 | C63: 172 | E63: 7,1 | F63: 1.13-5-40 | G63: Затвор дисковый, поворотный, корпус из чугуна, диск из нержавеющей стали, с ручкой, номинальное давление PN 1,6 МПа, номинальный диаметр DN 100 мм | H63: шт. | I63: =I61*J63 -> 9 | J63: 1 | K63: 1 | O63: =ROUND(CP63,2) -> 60960.26 | P63: =ROUND((ROUND((AC63*AW63*I63),2)*BC63),2) -> 60960.26 | Q63: =(ROUND((ROUND(((ET63)*AV63*I63),2)*BB63),2)+ROUND((ROUND(((AE63-(EU63))*AV63*I63),2)*BS63),2)) -> 0 | R63: =(ROUND((ROUND(((EU63)*AV63*I63),2)*BS63),2)+ROUND((ROUND(((AE63-(EU63))*AV63*I63),2)*BS63),2)) -> 0 | S63: =ROUND((ROUND((AF63*AV63*I63),2)*BA63),2) -> 0 | T63: =ROUND(CU63*I63,2) -> 0 | U63: =CV63*I63 -> 0 | V63: =CW63*I63 -> 0 | W63: =ROUND(CX63*I63,2) -> 0 | X63: =(ROUND((((S63+ROUND((ROUND(((EU63)*AV63*I63),2)*BS63),2))*AT63)/100),2)+ROUND(((ROUND((ROUND(((AE63-(EU63))*AV63*I63),2)*BS63),2)*AT63)/100),2)) -> 0 | Y63: =(ROUND((((S63+ROUND((ROUND(((EU63)*AV63*I63),2)*BS63),2))*AU63)/100),2)+ROUND(((ROUND((ROUND(((AE63-(EU63))*AV63*I63),2)*BS63),2)*AU63)/100),2)) -> 0 | AA63: 55747651 | AB63: =ROUND((AC63+AD63+AF63),6) -> 2177.93 | AC63: =ROUND((ES63),6) -> 2177.93 | AD63: =ROUND((((ET63)-(EU63))+AE63),6) -> 0 | AE63: =ROUND((EU63),6) -> 0 | AF63: =ROUND((EV63),6) -> 0 | AG63: =ROUND((AP63),6) -> 0 | AH63: =(EW63) -> 0 | AI63: =(EX63) -> 0 | AJ63: =(AS63) -> 0 | AK63: 2177.93 | AL63: 2177.93 | AM63: 0 | AN63: 0 | AO63: 0 | AP63: 0 | AQ63: 0 | AR63: 0 | AS63: 0 | AT63: 90 | AU63: 46 | AV63: 1 | AW63: 1 | AZ63: 1 | BA63: 1 | BB63: 1 | BC63: 3.11 | BH63: 3 | BI63: 2 | BJ63: ТСН-2001.1 Доп. 79, Р. 13, о. 5, поз. 40 | BM63: 73 | BN63: 0 | BO63: 1.13-5-40 | BP63: 1 | BQ63: 40 | BR63: 0 | BS63: 1 | BT63: 1 | BU63: 1 | BV63: 1 | BW63: 1 | BX63: 1 | BZ63: 90 | CA63: 46 | CE63: 1566 | CF63: 0 | CG63: 0 | CM63: 0 | CO63: 0 | CP63: =(P63+Q63+S63) -> 60960.26 | CQ63: =ROUND((ROUND((AC63*AW63*1),2)*BC63),2) -> 6773.36 | CR63: =(ROUND((ROUND(((ET63)*AV63*1),2)*BB63),2)+ROUND((ROUND(((AE63-(EU63))*AV63*1),2)*BS63),2)) -> 0 | CS63: =(ROUND((ROUND(((EU63)*AV63*1),2)*BS63),2)+ROUND((ROUND(((AE63-(EU63))*AV63*1),2)*BS63),2)) -> 0 | CT63: =ROUND((ROUND((AF63*AV63*1),2)*BA63),2) -> 0 | CU63: =AG63 -> 0 | CV63: =(AH63*AV63) -> 0 | CW63: =AI63 -> 0 | CX63: =AJ63 -> 0 | CY63: =(ROUND((((S63+ROUND((ROUND(((EU63)*AV63*1),2)*BS63),2))*AT63)/100),2)+ROUND(((ROUND((ROUND(((AE63-(EU63))*AV63*1),2)*BS63),2)*AT63)/100),2)) -> 0 | CZ63: =(ROUND((((S63+ROUND((ROUND(((EU63)*AV63*1),2)*BS63),2))*AU63)/100),2)+ROUND(((ROUND((ROUND(((AE63-(EU63))*AV63*1),2)*BS63),2)*AU63)/100),2)) -> 0 | DN63: 0 | DO63: 0 | DP63: 1 | DQ63: 1 | DU63: 1010 | DV63: шт. | DW63: шт. | DX63: 1 | EE63: 56938740 | EF63: 40 | EG63: Монтаж оборудования | EH63: 0 | EJ63: 2 | EK63: 73 | EL63: ТСН-2001.4-12. Технологические трубопроводы | EM63: ТСН-2001.4-12-1 | EQ63: 0 | ER63: 2177.93 | ES63: 2177.93 | ET63: 0 | EU63: 0 | EV63: 0 | EW63: 0 | EX63: 0 | FQ63: 0 | FR63: 0 | FS63: 0 | FX63: 90 | FY63: 46 | GD63: 1 | GF63: 873960273 | GG63: 2 | GH63: 1 | GI63: 2 | GJ63: 0 | GK63: 0 | GL63: =ROUND(IF(AND(BH63=3,BI63=3,FS63<>0),P63,0),2) -> 0 | GM63: =ROUND(O63+X63+Y63,2)+GX63 -> 60960.26 | GN63: =IF(OR(BI63=0,BI63=1),GM63-GX63,0) -> 0 | GO63: =IF(BI63=2,GM63-GX63,0) -> 60960.26 | GP63: =IF(BI63=4,GM63-GX63,0) -> 0 | GR63: 0 | GS63: 3 | GT63: 0 | GV63: =ROUND((GT63),6) -> 0 | GW63: 1 | GX63: =ROUND(HC63*I63,2) -> 0 | HA63: 0 | HB63: 0 | HC63: =GV63*GW63 -> 0 | HS63: 0 | IK63: 0
A64: 17 | B64: 1 | E64: 8 | F64: 1.12-9-21 | G64: Фланец стальной плоский приварной с соединительным выступом, ГОСТ 33259-2015, из стали Ст3сп, номинальное давление PN 1,6 МПа, номинальный диаметр DN 100 мм | H64: шт. | I64: 10 | J64: 0 | K64: 10 | O64: =ROUND(CP64,2) -> 1072.3 | P64: =ROUND((ROUND((AC64*AW64*I64),2)*BC64),2) -> 1072.3 | Q64: =(ROUND((ROUND(((ET64)*AV64*I64),2)*BB64),2)+ROUND((ROUND(((AE64-(EU64))*AV64*I64),2)*BS64),2)) -> 0 | R64: =(ROUND((ROUND(((EU64)*AV64*I64),2)*BS64),2)+ROUND((ROUND(((AE64-(EU64))*AV64*I64),2)*BS64),2)) -> 0 | S64: =ROUND((ROUND((AF64*AV64*I64),2)*BA64),2) -> 0 | T64: =ROUND(CU64*I64,2) -> 0 | U64: =CV64*I64 -> 0 | V64: =CW64*I64 -> 0 | W64: =ROUND(CX64*I64,2) -> 0 | X64: =(ROUND((((S64+ROUND((ROUND(((EU64)*AV64*I64),2)*BS64),2))*AT64)/100),2)+ROUND(((ROUND((ROUND(((AE64-(EU64))*AV64*I64),2)*BS64),2)*AT64)/100),2)) -> 0 | Y64: =(ROUND((((S64+ROUND((ROUND(((EU64)*AV64*I64),2)*BS64),2))*AU64)/100),2)+ROUND(((ROUND((ROUND(((AE64-(EU64))*AV64*I64),2)*BS64),2)*AU64)/100),2)) -> 0 | AA64: 55747649 | AB64: =ROUND((AC64+AD64+AF64),6) -> 107.23 | AC64: =ROUND((ES64),6) -> 107.23 | AD64: =ROUND((((ET64)-(EU64))+AE64),6) -> 0 | AE64: =ROUND((EU64),6) -> 0 | AF64: =ROUND((EV64),6) -> 0 | AG64: =ROUND((AP64),6) -> 0 | AH64: =(EW64) -> 0 | AI64: =(EX64) -> 0 | AJ64: =(AS64) -> 0 | AK64: 107.23 | AL64: 107.23 | AM64: 0 | AN64: 0 | AO64: 0 | AP64: 0 | AQ64: 0 | AR64: 0 | AS64: 0 | AT64: 0 | AU64: 0 | AV64: 1 | AW64: 1 | AZ64: 1 | BA64: 1 | BB64: 1 | BC64: 1 | BH64: 3 | BI64: 1 | BJ64: ТСН-2001.1 Доп. 80, Р. 12, о. 9, поз. 21 | BM64: 1617 | BN64: 0 | BP64: 0 | BQ64: 200 | BR64: 0 | BS64: 1 | BT64: 1 | BU64: 1 | BV64: 1 | BW64: 1 | BX64: 1 | BZ64: 0 | CA64: 0 | CE64: 1566 | CF64: 0 | CG64: 0 | CM64: 0 | CO64: 0 | CP64: =(P64+Q64+S64) -> 1072.3 | CQ64: =ROUND((ROUND((AC64*AW64*1),2)*BC64),2) -> 107.23 | CR64: =(ROUND((ROUND(((ET64)*AV64*1),2)*BB64),2)+ROUND((ROUND(((AE64-(EU64))*AV64*1),2)*BS64),2)) -> 0 | CS64: =(ROUND((ROUND(((EU64)*AV64*1),2)*BS64),2)+ROUND((ROUND(((AE64-(EU64))*AV64*1),2)*BS64),2)) -> 0 | CT64: =ROUND((ROUND((AF64*AV64*1),2)*BA64),2) -> 0 | CU64: =AG64 -> 0 | CV64: =(AH64*AV64) -> 0 | CW64: =AI64 -> 0 | CX64: =AJ64 -> 0 | CY64: =(ROUND((((S64+ROUND((ROUND(((EU64)*AV64*1),2)*BS64),2))*AT64)/100),2)+ROUND(((ROUND((ROUND(((AE64-(EU64))*AV64*1),2)*BS64),2)*AT64)/100),2)) -> 0 | CZ64: =(ROUND((((S64+ROUND((ROUND(((EU64)*AV64*1),2)*BS64),2))*AU64)/100),2)+ROUND(((ROUND((ROUND(((AE64-(EU64))*AV64*1),2)*BS64),2)*AU64)/100),2)) -> 0 | DN64: 0 | DO64: 0 | DP64: 1 | DQ64: 1 | DU64: 1010 | DV64: шт. | DW64: шт. | DX64: 1 | EE64: 56938763 | EF64: 200 | EG64: Материалы строительные | EH64: 0 | EJ64: 1 | EK64: 1617 | EL64: ТСН-2001.1 Материалы строительные | EM64: ТСН-2001.1-1 | EQ64: 0 | ER64: 107.23 | ES64: 107.23 | ET64: 0 | EU64: 0 | EV64: 0 | EW64: 0 | EX64: 0 | EY64: 0 | FQ64: 0 | FR64: 0 | FS64: 0 | FX64: 0 | FY64: 0 | GD64: 1 | GF64: 235948314 | GG64: 2 | GH64: 1 | GI64: -2 | GJ64: 0 | GK64: 0 | GL64: =ROUND(IF(AND(BH64=3,BI64=3,FS64<>0),P64,0),2) -> 0 | GM64: =ROUND(O64+X64+Y64,2)+GX64 -> 1072.3 | GN64: =IF(OR(BI64=0,BI64=1),GM64-GX64,0) -> 1072.3 | GO64: =IF(BI64=2,GM64-GX64,0) -> 0 | GP64: =IF(BI64=4,GM64-GX64,0) -> 0 | GR64: 0 | GS64: 3 | GT64: 0 | GV64: =ROUND((GT64),6) -> 0 | GW64: 1 | GX64: =ROUND(HC64*I64,2) -> 0 | HA64: 0 | HB64: 0 | HC64: =GV64*GW64 -> 0 | HS64: 0 | IK64: 0
A65: 17 | B65: 1 | E65: 8 | F65: 1.12-9-21 | G65: Фланец стальной плоский приварной с соединительным выступом, ГОСТ 33259-2015, из стали Ст3сп, номинальное давление PN 1,6 МПа, номинальный диаметр DN 100 мм | H65: шт. | I65: 10 | J65: 0 | K65: 10 | O65: =ROUND(CP65,2) -> 7441.76 | P65: =ROUND((ROUND((AC65*AW65*I65),2)*BC65),2) -> 7441.76 | Q65: =(ROUND((ROUND(((ET65)*AV65*I65),2)*BB65),2)+ROUND((ROUND(((AE65-(EU65))*AV65*I65),2)*BS65),2)) -> 0 | R65: =(ROUND((ROUND(((EU65)*AV65*I65),2)*BS65),2)+ROUND((ROUND(((AE65-(EU65))*AV65*I65),2)*BS65),2)) -> 0 | S65: =ROUND((ROUND((AF65*AV65*I65),2)*BA65),2) -> 0 | T65: =ROUND(CU65*I65,2) -> 0 | U65: =CV65*I65 -> 0 | V65: =CW65*I65 -> 0 | W65: =ROUND(CX65*I65,2) -> 0 | X65: =(ROUND((((S65+ROUND((ROUND(((EU65)*AV65*I65),2)*BS65),2))*AT65)/100),2)+ROUND(((ROUND((ROUND(((AE65-(EU65))*AV65*I65),2)*BS65),2)*AT65)/100),2)) -> 0 | Y65: =(ROUND((((S65+ROUND((ROUND(((EU65)*AV65*I65),2)*BS65),2))*AU65)/100),2)+ROUND(((ROUND((ROUND(((AE65-(EU65))*AV65*I65),2)*BS65),2)*AU65)/100),2)) -> 0 | AA65: 55747651 | AB65: =ROUND((AC65+AD65+AF65),6) -> 107.23 | AC65: =ROUND((ES65),6) -> 107.23 | AD65: =ROUND((((ET65)-(EU65))+AE65),6) -> 0 | AE65: =ROUND((EU65),6) -> 0 | AF65: =ROUND((EV65),6) -> 0 | AG65: =ROUND((AP65),6) -> 0 | AH65: =(EW65) -> 0 | AI65: =(EX65) -> 0 | AJ65: =(AS65) -> 0 | AK65: 107.23 | AL65: 107.23 | AM65: 0 | AN65: 0 | AO65: 0 | AP65: 0 | AQ65: 0 | AR65: 0 | AS65: 0 | AT65: 0 | AU65: 0 | AV65: 1 | AW65: 1 | AZ65: 1 | BA65: 1 | BB65: 1 | BC65: 6.94 | BH65: 3 | BI65: 1 | BJ65: ТСН-2001.1 Доп. 80, Р. 12, о. 9, поз. 21 | BM65: 1617 | BN65: 0 | BO65: 1.12-9-21 | BP65: 1 | BQ65: 200 | BR65: 0 | BS65: 1 | BT65: 1 | BU65: 1 | BV65: 1 | BW65: 1 | BX65: 1 | BZ65: 0 | CA65: 0 | CE65: 1566 | CF65: 0 | CG65: 0 | CM65: 0 | CO65: 0 | CP65: =(P65+Q65+S65) -> 7441.76 | CQ65: =ROUND((ROUND((AC65*AW65*1),2)*BC65),2) -> 744.18 | CR65: =(ROUND((ROUND(((ET65)*AV65*1),2)*BB65),2)+ROUND((ROUND(((AE65-(EU65))*AV65*1),2)*BS65),2)) -> 0 | CS65: =(ROUND((ROUND(((EU65)*AV65*1),2)*BS65),2)+ROUND((ROUND(((AE65-(EU65))*AV65*1),2)*BS65),2)) -> 0 | CT65: =ROUND((ROUND((AF65*AV65*1),2)*BA65),2) -> 0 | CU65: =AG65 -> 0 | CV65: =(AH65*AV65) -> 0 | CW65: =AI65 -> 0 | CX65: =AJ65 -> 0 | CY65: =(ROUND((((S65+ROUND((ROUND(((EU65)*AV65*1),2)*BS65),2))*AT65)/100),2)+ROUND(((ROUND((ROUND(((AE65-(EU65))*AV65*1),2)*BS65),2)*AT65)/100),2)) -> 0 | CZ65: =(ROUND((((S65+ROUND((ROUND(((EU65)*AV65*1),2)*BS65),2))*AU65)/100),2)+ROUND(((ROUND((ROUND(((AE65-(EU65))*AV65*1),2)*BS65),2)*AU65)/100),2)) -> 0 | DN65: 0 | DO65: 0 | DP65: 1 | DQ65: 1 | DU65: 1010 | DV65: шт. | DW65: шт. | DX65: 1 | EE65: 56938763 | EF65: 200 | EG65: Материалы строительные | EH65: 0 | EJ65: 1 | EK65: 1617 | EL65: ТСН-2001.1 Материалы строительные | EM65: ТСН-2001.1-1 | EQ65: 0 | ER65: 107.23 | ES65: 107.23 | ET65: 0 | EU65: 0 | EV65: 0 | EW65: 0 | EX65: 0 | EY65: 0 | FQ65: 0 | FR65: 0 | FS65: 0 | FX65: 0 | FY65: 0 | GD65: 1 | GF65: 235948314 | GG65: 2 | GH65: 1 | GI65: 2 | GJ65: 0 | GK65: 0 | GL65: =ROUND(IF(AND(BH65=3,BI65=3,FS65<>0),P65,0),2) -> 0 | GM65: =ROUND(O65+X65+Y65,2)+GX65 -> 7441.76 | GN65: =IF(OR(BI65=0,BI65=1),GM65-GX65,0) -> 7441.76 | GO65: =IF(BI65=2,GM65-GX65,0) -> 0 | GP65: =IF(BI65=4,GM65-GX65,0) -> 0 | GR65: 0 | GS65: 3 | GT65: 0 | GV65: =ROUND((GT65),6) -> 0 | GW65: 1 | GX65: =ROUND(HC65*I65,2) -> 0 | HA65: 0 | HB65: 0 | HC65: =GV65*GW65 -> 0 | HS65: 0 | IK65: 0
A66: 17 | B66: 1 | C66: =ROW(SmtRes!A177) -> 177 | D66: =ROW(EtalonRes!A221) -> 221 | E66: 9 | F66: 4.12-48-9 | G66: Монтаж арматуры фланцевой с ручным приводом или без привода на номинальное давление до 4 МПа, номинальный диаметр прохода 80 мм | H66: 1 ШТ. | I66: =ROUND(4+4,9) -> 8 | J66: 0 | K66: =ROUND(4+4,9) -> 8 | O66: =ROUND(CP66,2) -> 556.86 | P66: =ROUND((ROUND((AC66*AW66*I66),2)*BC66),2) -> 22.78 | Q66: =(ROUND((ROUND((((ET66*1.2))*AV66*I66),2)*BB66),2)+ROUND((ROUND(((AE66-((EU66*1.2)))*AV66*I66),2)*BS66),2)) -> 17 | R66: =(ROUND((ROUND((((EU66*1.2))*AV66*I66),2)*BS66),2)+ROUND((ROUND(((AE66-((EU66*1.2)))*AV66*I66),2)*BS66),2)) -> 2.56 | S66: =ROUND((ROUND((AF66*AV66*I66),2)*BA66),2) -> 517.08 | T66: =ROUND(CU66*I66,2) -> 0 | U66: =CV66*I66 -> 40.9728 | V66: =CW66*I66 -> 0 | W66: =ROUND(CX66*I66,2) -> 0 | X66: =(ROUND((((S66+ROUND((ROUND((((EU66*1.2))*AV66*I66),2)*BS66),2))*AT66)/100),2)+ROUND(((ROUND((ROUND(((AE66-((EU66*1.2)))*AV66*I66),2)*BS66),2)*AT66)/100),2)) -> 467.68 | Y66: =(ROUND((((S66+ROUND((ROUND((((EU66*1.2))*AV66*I66),2)*BS66),2))*AU66)/100),2)+ROUND(((ROUND((ROUND(((AE66-((EU66*1.2)))*AV66*I66),2)*BS66),2)*AU66)/100),2)) -> 239.03 | AA66: 55747649 | AB66: =ROUND((AC66+AD66+AF66),6) -> 65.338 | AC66: =ROUND(((ES66*1)),6) -> 2.77 | AD66: =ROUND(((((ET66*1.2))-((EU66*1.2)))+AE66),6) -> 1.992 | AE66: =ROUND(((EU66*1.2)),6) -> 0.3 | AF66: =ROUND(((EV66*1.2)),6) -> 60.576 | AG66: =ROUND((AP66),6) -> 0 | AH66: =((EW66*1.2)) -> 4.8 | AI66: =((EX66*1.2)) -> 0 | AJ66: =(AS66) -> 0 | AK66: 54.91 | AL66: 2.77 | AM66: 1.66 | AN66: 0.25 | AO66: 50.48 | AP66: 0 | AQ66: 4 | AR66: 0 | AS66: 0 | AT66: 90 | AU66: 46 | AV66: 1.067 | AW66: 1.028 | AZ66: 1 | BA66: 1 | BB66: 1 | BC66: 1 | BH66: 0 | BI66: 2 | BJ66: ТСН-2001.4 Доп. 68, Сб. 12, т. 48, поз. 9 | BM66: 73 | BN66: 0 | BO66: 4.12-48-9 | BP66: 1 | BQ66: 40 | BR66: 0 | BS66: 1 | BT66: 1 | BU66: 1 | BV66: 1 | BW66: 1 | BX66: 1 | BZ66: 90 | CA66: 46 | CE66: 1566 | CF66: 0 | CG66: 0 | CM66: 0 | CN66: Поправка: Гл.12.Прил.8.п.8. 3_12.00.01.11.001 Наименование: При наличии напряженных и стесненных условий производства работ (стесненность, сложность складирования и транспортной логистики и т.п.) для объектов, расположенных в пределах круговой магистральной системы улиц "Садовое кольцо" города Москвы | CO66: 0 | CP66: =(P66+Q66+S66) -> 556.86 | CQ66: =ROUND((ROUND((AC66*AW66*1),2)*BC66),2) -> 2.85 | CR66: =(ROUND((ROUND((((ET66*1.2))*AV66*1),2)*BB66),2)+ROUND((ROUND(((AE66-((EU66*1.2)))*AV66*1),2)*BS66),2)) -> 2.13 | CS66: =(ROUND((ROUND((((EU66*1.2))*AV66*1),2)*BS66),2)+ROUND((ROUND(((AE66-((EU66*1.2)))*AV66*1),2)*BS66),2)) -> 0.32 | CT66: =ROUND((ROUND((AF66*AV66*1),2)*BA66),2) -> 64.63 | CU66: =AG66 -> 0 | CV66: =(AH66*AV66) -> 5.1216 | CW66: =AI66 -> 0 | CX66: =AJ66 -> 0 | CY66: =(ROUND((((S66+ROUND((ROUND((((EU66*1.2))*AV66*1),2)*BS66),2))*AT66)/100),2)+ROUND(((ROUND((ROUND(((AE66-((EU66*1.2)))*AV66*1),2)*BS66),2)*AT66)/100),2)) -> 465.66 | CZ66: =(ROUND((((S66+ROUND((ROUND((((EU66*1.2))*AV66*1),2)*BS66),2))*AU66)/100),2)+ROUND(((ROUND((ROUND(((AE66-((EU66*1.2)))*AV66*1),2)*BS66),2)*AU66)/100),2)) -> 238 | DB66: 37 | DD66: *1 | DE66: *1,2 | DF66: *1,2 | DG66: *1,2 | DI66: *1,2 | DJ66: *1,2 | DN66: 0 | DO66: 0 | DP66: 1 | DQ66: 1 | DU66: 1013 | DV66: 1 ШТ. | DW66: 1 ШТ. | DX66: 1 | EE66: 56938740 | EF66: 40 | EG66: Монтаж оборудования | EH66: 0 | EJ66: 2 | EK66: 73 | EL66: ТСН-2001.4-12. Технологические трубопроводы | EM66: ТСН-2001.4-12-1 | EO66: Поправка: Гл.12.Прил.8.п.8. 3_12.00.01.11.001 | EQ66: 131072 | ER66: 54.91 | ES66: 2.77 | ET66: 1.66 | EU66: 0.25 | EV66: 50.48 | EW66: 4 | EX66: 0 | EY66: 0 | FQ66: 0 | FR66: 0 | FS66: 2 | FX66: 90 | FY66: 46 | GD66: 1 | GF66: -202371068 | GG66: 2 | GH66: 1 | GI66: 2 | GJ66: 0 | GK66: 0 | GL66: =ROUND(IF(AND(BH66=3,BI66=3,FS66<>0),P66,0),2) -> 0 | GM66: =ROUND(O66+X66+Y66,2)+GX66 -> 1263.57 | GN66: =IF(OR(BI66=0,BI66=1),GM66-GX66,0) -> 0 | GO66: =IF(BI66=2,GM66-GX66,0) -> 1263.57 | GP66: =IF(BI66=4,GM66-GX66,0) -> 0 | GR66: 0 | GS66: 3 | GT66: 0 | GV66: =ROUND((GT66),6) -> 0 | GW66: 1 | GX66: =ROUND(HC66*I66,2) -> 0 | HA66: 0 | HB66: 0 | HC66: =GV66*GW66 -> 0 | HS66: 0 | IK66: 0
A67: 17 | B67: 1 | C67: =ROW(SmtRes!A182) -> 182 | D67: =ROW(EtalonRes!A226) -> 226 | E67: 9 | F67: 4.12-48-9 | G67: Монтаж арматуры фланцевой с ручным приводом или без привода на номинальное давление до 4 МПа, номинальный диаметр прохода 80 мм | H67: 1 ШТ. | I67: =ROUND(4+4,9) -> 8 | J67: 0 | K67: =ROUND(4+4,9) -> 8 | O67: =ROUND(CP67,2) -> 29530.5 | P67: =ROUND((ROUND((AC67*AW67*I67),2)*BC67),2) -> 102.51 | Q67: =(ROUND((ROUND((((ET67*1.2))*AV67*I67),2)*BB67),2)+ROUND((ROUND(((AE67-((EU67*1.2)))*AV67*I67),2)*BS67),2)) -> 290.53 | R67: =(ROUND((ROUND((((EU67*1.2))*AV67*I67),2)*BS67),2)+ROUND((ROUND(((AE67-((EU67*1.2)))*AV67*I67),2)*BS67),2)) -> 144.26 | S67: =ROUND((ROUND((AF67*AV67*I67),2)*BA67),2) -> 29137.46 | T67: =ROUND(CU67*I67,2) -> 0 | U67: =CV67*I67 -> 40.9728 | V67: =CW67*I67 -> 0 | W67: =ROUND(CX67*I67,2) -> 0 | X67: =(ROUND((((S67+ROUND((ROUND((((EU67*1.2))*AV67*I67),2)*BS67),2))*AT67)/100),2)+ROUND(((ROUND((ROUND(((AE67-((EU67*1.2)))*AV67*I67),2)*BS67),2)*AT67)/100),2)) -> 26353.55 | Y67: =(ROUND((((S67+ROUND((ROUND((((EU67*1.2))*AV67*I67),2)*BS67),2))*AU67)/100),2)+ROUND(((ROUND((ROUND(((AE67-((EU67*1.2)))*AV67*I67),2)*BS67),2)*AU67)/100),2)) -> 13469.59 | AA67: 55747651 | AB67: =ROUND((AC67+AD67+AF67),6) -> 65.338 | AC67: =ROUND(((ES67*1)),6) -> 2.77 | AD67: =ROUND(((((ET67*1.2))-((EU67*1.2)))+AE67),6) -> 1.992 | AE67: =ROUND(((EU67*1.2)),6) -> 0.3 | AF67: =ROUND(((EV67*1.2)),6) -> 60.576 | AG67: =ROUND((AP67),6) -> 0 | AH67: =((EW67*1.2)) -> 4.8 | AI67: =((EX67*1.2)) -> 0 | AJ67: =(AS67) -> 0 | AK67: 54.91 | AL67: 2.77 | AM67: 1.66 | AN67: 0.25 | AO67: 50.48 | AP67: 0 | AQ67: 4 | AR67: 0 | AS67: 0 | AT67: 90 | AU67: 46 | AV67: 1.067 | AW67: 1.028 | AZ67: 1 | BA67: 56.35 | BB67: 17.09 | BC67: 4.5 | BH67: 0 | BI67: 2 | BJ67: ТСН-2001.4 Доп. 68, Сб. 12, т. 48, поз. 9 | BM67: 73 | BN67: 0 | BO67: 4.12-48-9 | BP67: 1 | BQ67: 40 | BR67: 0 | BS67: 56.35 | BT67: 1 | BU67: 1 | BV67: 1 | BW67: 1 | BX67: 1 | BZ67: 90 | CA67: 46 | CE67: 1566 | CF67: 0 | CG67: 0 | CM67: 0 | CN67: Поправка: Гл.12.Прил.8.п.8. 3_12.00.01.11.001 Наименование: При наличии напряженных и стесненных условий производства работ (стесненность, сложность складирования и транспортной логистики и т.п.) для объектов, расположенных в пределах круговой магистральной системы улиц "Садовое кольцо" города Москвы | CO67: 0 | CP67: =(P67+Q67+S67) -> 29530.5 | CQ67: =ROUND((ROUND((AC67*AW67*1),2)*BC67),2) -> 12.83 | CR67: =(ROUND((ROUND((((ET67*1.2))*AV67*1),2)*BB67),2)+ROUND((ROUND(((AE67-((EU67*1.2)))*AV67*1),2)*BS67),2)) -> 36.4 | CS67: =(ROUND((ROUND((((EU67*1.2))*AV67*1),2)*BS67),2)+ROUND((ROUND(((AE67-((EU67*1.2)))*AV67*1),2)*BS67),2)) -> 18.03 | CT67: =ROUND((ROUND((AF67*AV67*1),2)*BA67),2) -> 3641.9 | CU67: =AG67 -> 0 | CV67: =(AH67*AV67) -> 5.1216 | CW67: =AI67 -> 0 | CX67: =AJ67 -> 0 | CY67: =(ROUND((((S67+ROUND((ROUND((((EU67*1.2))*AV67*1),2)*BS67),2))*AT67)/100),2)+ROUND(((ROUND((ROUND(((AE67-((EU67*1.2)))*AV67*1),2)*BS67),2)*AT67)/100),2)) -> 26239.94 | CZ67: =(ROUND((((S67+ROUND((ROUND((((EU67*1.2))*AV67*1),2)*BS67),2))*AU67)/100),2)+ROUND(((ROUND((ROUND(((AE67-((EU67*1.2)))*AV67*1),2)*BS67),2)*AU67)/100),2)) -> 13411.53 | DB67: 38 | DD67: *1 | DE67: *1,2 | DF67: *1,2 | DG67: *1,2 | DI67: *1,2 | DJ67: *1,2 | DN67: 0 | DO67: 0 | DP67: 1 | DQ67: 1 | DU67: 1013 | DV67: 1 ШТ. | DW67: 1 ШТ. | DX67: 1 | EE67: 56938740 | EF67: 40 | EG67: Монтаж оборудования | EH67: 0 | EJ67: 2 | EK67: 73 | EL67: ТСН-2001.4-12. Технологические трубопроводы | EM67: ТСН-2001.4-12-1 | EO67: Поправка: Гл.12.Прил.8.п.8. 3_12.00.01.11.001 | EQ67: 131072 | ER67: 54.91 | ES67: 2.77 | ET67: 1.66 | EU67: 0.25 | EV67: 50.48 | EW67: 4 | EX67: 0 | EY67: 0 | FQ67: 0 | FR67: 0 | FS67: 2 | FX67: 90 | FY67: 46 | GD67: 1 | GF67: -202371068 | GG67: 2 | GH67: 1 | GI67: 2 | GJ67: 0 | GK67: 0 | GL67: =ROUND(IF(AND(BH67=3,BI67=3,FS67<>0),P67,0),2) -> 0 | GM67: =ROUND(O67+X67+Y67,2)+GX67 -> 69353.64 | GN67: =IF(OR(BI67=0,BI67=1),GM67-GX67,0) -> 0 | GO67: =IF(BI67=2,GM67-GX67,0) -> 69353.64 | GP67: =IF(BI67=4,GM67-GX67,0) -> 0 | GR67: 0 | GS67: 3 | GT67: 0 | GV67: =ROUND((GT67),6) -> 0 | GW67: 1 | GX67: =ROUND(HC67*I67,2) -> 0 | HA67: 0 | HB67: 0 | HC67: =GV67*GW67 -> 0 | HS67: 0 | IK67: 0
A68: 18 | B68: 1 | C68: 176 | E68: 9,1 | F68: 1.13-3-109 | G68: Клапан обратный, чугунный, фланцевый, температура рабочей среды от -10 до +100°С, условная пропускная способность 222 м3/ч, номинальное давление РN 1,6 МПа, номинальный диаметр DN 80 мм | H68: шт. | I68: =I66*J68 -> 4 | J68: 0.5 | K68: 0.5 | O68: =ROUND(CP68,2) -> 12121.96 | P68: =ROUND((ROUND((AC68*AW68*I68),2)*BC68),2) -> 12121.96 | Q68: =(ROUND((ROUND(((ET68)*AV68*I68),2)*BB68),2)+ROUND((ROUND(((AE68-(EU68))*AV68*I68),2)*BS68),2)) -> 0 | R68: =(ROUND((ROUND(((EU68)*AV68*I68),2)*BS68),2)+ROUND((ROUND(((AE68-(EU68))*AV68*I68),2)*BS68),2)) -> 0 | S68: =ROUND((ROUND((AF68*AV68*I68),2)*BA68),2) -> 0 | T68: =ROUND(CU68*I68,2) -> 0 | U68: =CV68*I68 -> 0 | V68: =CW68*I68 -> 0 | W68: =ROUND(CX68*I68,2) -> 0 | X68: =(ROUND((((S68+ROUND((ROUND(((EU68)*AV68*I68),2)*BS68),2))*AT68)/100),2)+ROUND(((ROUND((ROUND(((AE68-(EU68))*AV68*I68),2)*BS68),2)*AT68)/100),2)) -> 0 | Y68: =(ROUND((((S68+ROUND((ROUND(((EU68)*AV68*I68),2)*BS68),2))*AU68)/100),2)+ROUND(((ROUND((ROUND(((AE68-(EU68))*AV68*I68),2)*BS68),2)*AU68)/100),2)) -> 0 | AA68: 55747649 | AB68: =ROUND((AC68+AD68+AF68),6) -> 3030.49 | AC68: =ROUND((ES68),6) -> 3030.49 | AD68: =ROUND((((ET68)-(EU68))+AE68),6) -> 0 | AE68: =ROUND((EU68),6) -> 0 | AF68: =ROUND((EV68),6) -> 0 | AG68: =ROUND((AP68),6) -> 0 | AH68: =(EW68) -> 0 | AI68: =(EX68) -> 0 | AJ68: =(AS68) -> 0 | AK68: 3030.49 | AL68: 3030.49 | AM68: 0 | AN68: 0 | AO68: 0 | AP68: 0 | AQ68: 0 | AR68: 0 | AS68: 0 | AT68: 90 | AU68: 46 | AV68: 1 | AW68: 1 | AZ68: 1 | BA68: 1 | BB68: 1 | BC68: 1 | BH68: 3 | BI68: 2 | BJ68: ТСН-2001.1 Доп. 79, Р. 13, о. 3, поз. 109 | BM68: 73 | BN68: 0 | BP68: 0 | BQ68: 40 | BR68: 0 | BS68: 1 | BT68: 1 | BU68: 1 | BV68: 1 | BW68: 1 | BX68: 1 | BZ68: 90 | CA68: 46 | CE68: 1566 | CF68: 0 | CG68: 0 | CM68: 0 | CO68: 0 | CP68: =(P68+Q68+S68) -> 12121.96 | CQ68: =ROUND((ROUND((AC68*AW68*1),2)*BC68),2) -> 3030.49 | CR68: =(ROUND((ROUND(((ET68)*AV68*1),2)*BB68),2)+ROUND((ROUND(((AE68-(EU68))*AV68*1),2)*BS68),2)) -> 0 | CS68: =(ROUND((ROUND(((EU68)*AV68*1),2)*BS68),2)+ROUND((ROUND(((AE68-(EU68))*AV68*1),2)*BS68),2)) -> 0 | CT68: =ROUND((ROUND((AF68*AV68*1),2)*BA68),2) -> 0 | CU68: =AG68 -> 0 | CV68: =(AH68*AV68) -> 0 | CW68: =AI68 -> 0 | CX68: =AJ68 -> 0 | CY68: =(ROUND((((S68+ROUND((ROUND(((EU68)*AV68*1),2)*BS68),2))*AT68)/100),2)+ROUND(((ROUND((ROUND(((AE68-(EU68))*AV68*1),2)*BS68),2)*AT68)/100),2)) -> 0 | CZ68: =(ROUND((((S68+ROUND((ROUND(((EU68)*AV68*1),2)*BS68),2))*AU68)/100),2)+ROUND(((ROUND((ROUND(((AE68-(EU68))*AV68*1),2)*BS68),2)*AU68)/100),2)) -> 0 | DN68: 0 | DO68: 0 | DP68: 1 | DQ68: 1 | DU68: 1010 | DV68: шт. | DW68: шт. | DX68: 1 | EE68: 56938740 | EF68: 40 | EG68: Монтаж оборудования | EH68: 0 | EJ68: 2 | EK68: 73 | EL68: ТСН-2001.4-12. Технологические трубопроводы | EM68: ТСН-2001.4-12-1 | EQ68: 0 | ER68: 3030.49 | ES68: 3030.49 | ET68: 0 | EU68: 0 | EV68: 0 | EW68: 0 | EX68: 0 | FQ68: 0 | FR68: 0 | FS68: 0 | FX68: 90 | FY68: 46 | GD68: 1 | GF68: -1962529768 | GG68: 2 | GH68: 1 | GI68: -2 | GJ68: 0 | GK68: 0 | GL68: =ROUND(IF(AND(BH68=3,BI68=3,FS68<>0),P68,0),2) -> 0 | GM68: =ROUND(O68+X68+Y68,2)+GX68 -> 12121.96 | GN68: =IF(OR(BI68=0,BI68=1),GM68-GX68,0) -> 0 | GO68: =IF(BI68=2,GM68-GX68,0) -> 12121.96 | GP68: =IF(BI68=4,GM68-GX68,0) -> 0 | GR68: 0 | GS68: 3 | GT68: 0 | GV68: =ROUND((GT68),6) -> 0 | GW68: 1 | GX68: =ROUND(HC68*I68,2) -> 0 | HA68: 0 | HB68: 0 | HC68: =GV68*GW68 -> 0 | HS68: 0 | IK68: 0
A69: 18 | B69: 1 | C69: 181 | E69: 9,1 | F69: 1.13-3-109 | G69: Клапан обратный, чугунный, фланцевый, температура рабочей среды от -10 до +100°С, условная пропускная способность 222 м3/ч, номинальное давление РN 1,6 МПа, номинальный диаметр DN 80 мм | H69: шт. | I69: =I67*J69 -> 4 | J69: 0.5 | K69: 0.5 | O69: =ROUND(CP69,2) -> 75762.25 | P69: =ROUND((ROUND((AC69*AW69*I69),2)*BC69),2) -> 75762.25 | Q69: =(ROUND((ROUND(((ET69)*AV69*I69),2)*BB69),2)+ROUND((ROUND(((AE69-(EU69))*AV69*I69),2)*BS69),2)) -> 0 | R69: =(ROUND((ROUND(((EU69)*AV69*I69),2)*BS69),2)+ROUND((ROUND(((AE69-(EU69))*AV69*I69),2)*BS69),2)) -> 0 | S69: =ROUND((ROUND((AF69*AV69*I69),2)*BA69),2) -> 0 | T69: =ROUND(CU69*I69,2) -> 0 | U69: =CV69*I69 -> 0 | V69: =CW69*I69 -> 0 | W69: =ROUND(CX69*I69,2) -> 0 | X69: =(ROUND((((S69+ROUND((ROUND(((EU69)*AV69*I69),2)*BS69),2))*AT69)/100),2)+ROUND(((ROUND((ROUND(((AE69-(EU69))*AV69*I69),2)*BS69),2)*AT69)/100),2)) -> 0 | Y69: =(ROUND((((S69+ROUND((ROUND(((EU69)*AV69*I69),2)*BS69),2))*AU69)/100),2)+ROUND(((ROUND((ROUND(((AE69-(EU69))*AV69*I69),2)*BS69),2)*AU69)/100),2)) -> 0 | AA69: 55747651 | AB69: =ROUND((AC69+AD69+AF69),6) -> 3030.49 | AC69: =ROUND((ES69),6) -> 3030.49 | AD69: =ROUND((((ET69)-(EU69))+AE69),6) -> 0 | AE69: =ROUND((EU69),6) -> 0 | AF69: =ROUND((EV69),6) -> 0 | AG69: =ROUND((AP69),6) -> 0 | AH69: =(EW69) -> 0 | AI69: =(EX69) -> 0 | AJ69: =(AS69) -> 0 | AK69: 3030.49 | AL69: 3030.49 | AM69: 0 | AN69: 0 | AO69: 0 | AP69: 0 | AQ69: 0 | AR69: 0 | AS69: 0 | AT69: 90 | AU69: 46 | AV69: 1 | AW69: 1 | AZ69: 1 | BA69: 1 | BB69: 1 | BC69: 6.25 | BH69: 3 | BI69: 2 | BJ69: ТСН-2001.1 Доп. 79, Р. 13, о. 3, поз. 109 | BM69: 73 | BN69: 0 | BO69: 1.13-3-109 | BP69: 1 | BQ69: 40 | BR69: 0 | BS69: 1 | BT69: 1 | BU69: 1 | BV69: 1 | BW69: 1 | BX69: 1 | BZ69: 90 | CA69: 46 | CE69: 1566 | CF69: 0 | CG69: 0 | CM69: 0 | CO69: 0 | CP69: =(P69+Q69+S69) -> 75762.25 | CQ69: =ROUND((ROUND((AC69*AW69*1),2)*BC69),2) -> 18940.56 | CR69: =(ROUND((ROUND(((ET69)*AV69*1),2)*BB69),2)+ROUND((ROUND(((AE69-(EU69))*AV69*1),2)*BS69),2)) -> 0 | CS69: =(ROUND((ROUND(((EU69)*AV69*1),2)*BS69),2)+ROUND((ROUND(((AE69-(EU69))*AV69*1),2)*BS69),2)) -> 0 | CT69: =ROUND((ROUND((AF69*AV69*1),2)*BA69),2) -> 0 | CU69: =AG69 -> 0 | CV69: =(AH69*AV69) -> 0 | CW69: =AI69 -> 0 | CX69: =AJ69 -> 0 | CY69: =(ROUND((((S69+ROUND((ROUND(((EU69)*AV69*1),2)*BS69),2))*AT69)/100),2)+ROUND(((ROUND((ROUND(((AE69-(EU69))*AV69*1),2)*BS69),2)*AT69)/100),2)) -> 0 | CZ69: =(ROUND((((S69+ROUND((ROUND(((EU69)*AV69*1),2)*BS69),2))*AU69)/100),2)+ROUND(((ROUND((ROUND(((AE69-(EU69))*AV69*1),2)*BS69),2)*AU69)/100),2)) -> 0 | DN69: 0 | DO69: 0 | DP69: 1 | DQ69: 1 | DU69: 1010 | DV69: шт. | DW69: шт. | DX69: 1 | EE69: 56938740 | EF69: 40 | EG69: Монтаж оборудования | EH69: 0 | EJ69: 2 | EK69: 73 | EL69: ТСН-2001.4-12. Технологические трубопроводы | EM69: ТСН-2001.4-12-1 | EQ69: 0 | ER69: 3030.49 | ES69: 3030.49 | ET69: 0 | EU69: 0 | EV69: 0 | EW69: 0 | EX69: 0 | FQ69: 0 | FR69: 0 | FS69: 0 | FX69: 90 | FY69: 46 | GD69: 1 | GF69: -1962529768 | GG69: 2 | GH69: 1 | GI69: 2 | GJ69: 0 | GK69: 0 | GL69: =ROUND(IF(AND(BH69=3,BI69=3,FS69<>0),P69,0),2) -> 0 | GM69: =ROUND(O69+X69+Y69,2)+GX69 -> 75762.25 | GN69: =IF(OR(BI69=0,BI69=1),GM69-GX69,0) -> 0 | GO69: =IF(BI69=2,GM69-GX69,0) -> 75762.25 | GP69: =IF(BI69=4,GM69-GX69,0) -> 0 | GR69: 0 | GS69: 3 | GT69: 0 | GV69: =ROUND((GT69),6) -> 0 | GW69: 1 | GX69: =ROUND(HC69*I69,2) -> 0 | HA69: 0 | HB69: 0 | HC69: =GV69*GW69 -> 0 | HS69: 0 | IK69: 0
A70: 18 | B70: 1 | C70: 177 | E70: 9,2 | F70: 1.13-5-39 | G70: Затвор дисковый, поворотный, корпус из чугуна, диск из нержавеющей стали, с ручкой, номинальное давление PN 1,6 МПа, номинальный диаметр DN 80 мм | H70: шт. | I70: =I66*J70 -> 4 | J70: 0.5 | K70: 0.5 | O70: =ROUND(CP70,2) -> 7897.72 | P70: =ROUND((ROUND((AC70*AW70*I70),2)*BC70),2) -> 7897.72 | Q70: =(ROUND((ROUND(((ET70)*AV70*I70),2)*BB70),2)+ROUND((ROUND(((AE70-(EU70))*AV70*I70),2)*BS70),2)) -> 0 | R70: =(ROUND((ROUND(((EU70)*AV70*I70),2)*BS70),2)+ROUND((ROUND(((AE70-(EU70))*AV70*I70),2)*BS70),2)) -> 0 | S70: =ROUND((ROUND((AF70*AV70*I70),2)*BA70),2) -> 0 | T70: =ROUND(CU70*I70,2) -> 0 | U70: =CV70*I70 -> 0 | V70: =CW70*I70 -> 0 | W70: =ROUND(CX70*I70,2) -> 0 | X70: =(ROUND((((S70+ROUND((ROUND(((EU70)*AV70*I70),2)*BS70),2))*AT70)/100),2)+ROUND(((ROUND((ROUND(((AE70-(EU70))*AV70*I70),2)*BS70),2)*AT70)/100),2)) -> 0 | Y70: =(ROUND((((S70+ROUND((ROUND(((EU70)*AV70*I70),2)*BS70),2))*AU70)/100),2)+ROUND(((ROUND((ROUND(((AE70-(EU70))*AV70*I70),2)*BS70),2)*AU70)/100),2)) -> 0 | AA70: 55747649 | AB70: =ROUND((AC70+AD70+AF70),6) -> 1974.43 | AC70: =ROUND((ES70),6) -> 1974.43 | AD70: =ROUND((((ET70)-(EU70))+AE70),6) -> 0 | AE70: =ROUND((EU70),6) -> 0 | AF70: =ROUND((EV70),6) -> 0 | AG70: =ROUND((AP70),6) -> 0 | AH70: =(EW70) -> 0 | AI70: =(EX70) -> 0 | AJ70: =(AS70) -> 0 | AK70: 1974.43 | AL70: 1974.43 | AM70: 0 | AN70: 0 | AO70: 0 | AP70: 0 | AQ70: 0 | AR70: 0 | AS70: 0 | AT70: 90 | AU70: 46 | AV70: 1 | AW70: 1 | AZ70: 1 | BA70: 1 | BB70: 1 | BC70: 1 | BH70: 3 | BI70: 2 | BJ70: ТСН-2001.1 Доп. 79, Р. 13, о. 5, поз. 39 | BM70: 73 | BN70: 0 | BP70: 0 | BQ70: 40 | BR70: 0 | BS70: 1 | BT70: 1 | BU70: 1 | BV70: 1 | BW70: 1 | BX70: 1 | BZ70: 90 | CA70: 46 | CE70: 1566 | CF70: 0 | CG70: 0 | CM70: 0 | CO70: 0 | CP70: =(P70+Q70+S70) -> 7897.72 | CQ70: =ROUND((ROUND((AC70*AW70*1),2)*BC70),2) -> 1974.43 | CR70: =(ROUND((ROUND(((ET70)*AV70*1),2)*BB70),2)+ROUND((ROUND(((AE70-(EU70))*AV70*1),2)*BS70),2)) -> 0 | CS70: =(ROUND((ROUND(((EU70)*AV70*1),2)*BS70),2)+ROUND((ROUND(((AE70-(EU70))*AV70*1),2)*BS70),2)) -> 0 | CT70: =ROUND((ROUND((AF70*AV70*1),2)*BA70),2) -> 0 | CU70: =AG70 -> 0 | CV70: =(AH70*AV70) -> 0 | CW70: =AI70 -> 0 | CX70: =AJ70 -> 0 | CY70: =(ROUND((((S70+ROUND((ROUND(((EU70)*AV70*1),2)*BS70),2))*AT70)/100),2)+ROUND(((ROUND((ROUND(((AE70-(EU70))*AV70*1),2)*BS70),2)*AT70)/100),2)) -> 0 | CZ70: =(ROUND((((S70+ROUND((ROUND(((EU70)*AV70*1),2)*BS70),2))*AU70)/100),2)+ROUND(((ROUND((ROUND(((AE70-(EU70))*AV70*1),2)*BS70),2)*AU70)/100),2)) -> 0 | DN70: 0 | DO70: 0 | DP70: 1 | DQ70: 1 | DU70: 1010 | DV70: шт. | DW70: шт. | DX70: 1 | EE70: 56938740 | EF70: 40 | EG70: Монтаж оборудования | EH70: 0 | EJ70: 2 | EK70: 73 | EL70: ТСН-2001.4-12. Технологические трубопроводы | EM70: ТСН-2001.4-12-1 | EQ70: 0 | ER70: 1974.43 | ES70: 1974.43 | ET70: 0 | EU70: 0 | EV70: 0 | EW70: 0 | EX70: 0 | FQ70: 0 | FR70: 0 | FS70: 0 | FX70: 90 | FY70: 46 | GD70: 1 | GF70: -2105799508 | GG70: 2 | GH70: 1 | GI70: -2 | GJ70: 0 | GK70: 0 | GL70: =ROUND(IF(AND(BH70=3,BI70=3,FS70<>0),P70,0),2) -> 0 | GM70: =ROUND(O70+X70+Y70,2)+GX70 -> 7897.72 | GN70: =IF(OR(BI70=0,BI70=1),GM70-GX70,0) -> 0 | GO70: =IF(BI70=2,GM70-GX70,0) -> 7897.72 | GP70: =IF(BI70=4,GM70-GX70,0) -> 0 | GR70: 0 | GS70: 3 | GT70: 0 | GV70: =ROUND((GT70),6) -> 0 | GW70: 1 | GX70: =ROUND(HC70*I70,2) -> 0 | HA70: 0 | HB70: 0 | HC70: =GV70*GW70 -> 0 | HS70: 0 | IK70: 0
