Workbook

Sheet Смета по ТСН-2001(с доп.67
A1: =Source!B1 -> Smeta.RU (495) 974-1589
J2: Форма № 4б
B3: "СОГЛАСОВАНО" | G3: "УТВЕРЖДАЮ"
B6: =CONCATENATE("______________________ ", IF(Source!AL12<>"", Source!AL12, "")) -> ______________________ | G6: =CONCATENATE("______________________ ", IF(Source!AH12<>"", Source!AH12, "")) -> ______________________
B7: "_____"________________ 2026 г. | G7: "_____"________________ 2026 г.
A10: Капитальный ремонт здания Государственного бюджетного общеобразовательного учреждения города Москвы «Школа №1574», расположенного по адресу: г. Москва, Старопименовский переулок, д. 5. 1 этап. 02-01-18 АДИС 16.07.26 | AP10: Капитальный ремонт здания Государственного бюджетного общеобразовательного учреждения города Москвы «Школа №1574», расположенного по адресу: г. Москва, Старопименовский переулок, д. 5. 1 этап. 02-01-18 АДИС 16.07.26
A11: (наименование стройки и/или объекта)
A13: =CONCATENATE( "ЛОКАЛЬНАЯ СМЕТА № ",IF(Source!F12<>"Новый объект", Source!F12, "")) -> ЛОКАЛЬНАЯ СМЕТА № 02-01-18
A15: =Source!G20 -> Автоматизация и диспетчеризация
A16: (наименование работ и затрат)
A18: =CONCATENATE( "Основание: чертежи № ", Source!J12) -> Основание: чертежи № 2024-00375-01-0-ИОС5.11
I20: В базисном уровне цен | J20: В текущем уровне цен
E21: Сметная стоимость | I21: =I22+I23+I24+I25 -> 3935.34 | J21: =J22+J23+J24+J25 -> 33787.95 | K21: тыс.руб.
E22: Строительные работы | I22: =ROUND((Source!F855)/1000, 2) -> 2.93 | J22: =ROUND((Source!P855)/1000, 2) -> 164.93 | K22: тыс.руб.
E23: Работы по монтажу оборудования | I23: =ROUND((Source!F856)/1000, 2) -> 224.94 | J23: =ROUND((Source!P856)/1000, 2) -> 5557.6 | K23: тыс.руб.
E24: Оборудование | I24: =ROUND((Source!F847)/1000, 2) -> 3707.47 | J24: =ROUND((Source!P847)/1000, 2) -> 28065.42 | K24: тыс.руб.
E25: Прочие работы и затраты | I25: =ROUND((Source!F857+Source!F858)/1000, 2) -> 0 | J25: =ROUND((Source!P857+Source!P858)/1000, 2) -> 0 | K25: тыс.руб.
E26: Средства на оплату труда | I26: =(Source!F853+ Source!F852)/1000 -> 33.06886 | J26: =((Source!P853 + Source!P852)/1000) -> 1863.4303 | K26: тыс.руб.
E27: Затраты труда | I27: =Source!F860 -> 2619.8285 | K27: чел.-ч.
E28: Кроме того:
E29: Возврат материалов | I29: =SUM(Y1:Y994)/1000 -> 0 | J29: =SUM(Z1:Z994)/1000 -> 0 | K29: тыс.руб.
A31: Составлен(а) по ТСН-2001 с учетом Дополнения №: 81
A32: № и период сборника коэффициентов (индексов) пересчета: Коэффициенты к ТСН-2001 МГЭ Дополнение 81, ремонт №219/81 I квартал 2026 года и Коэффициенты к ТСН-2001.13-2 Дополнение 47 №64/47 I квартал 2026 года | AP32: № и период сборника коэффициентов (индексов) пересчета: Коэффициенты к ТСН-2001 МГЭ Дополнение 81, ремонт №219/81 I квартал 2026 года и Коэффициенты к ТСН-2001.13-2 Дополнение 47 №64/47 I квартал 2026 года
A33: № п/п | B33: Шифр расценки и коды ресурсов | C33: Наименование работ и затрат | D33: Ед. изм. | E33: Кол-во единиц | F33: Цена на ед. изм., руб. | G33: Попра- вочные коэффи- циенты | H33: Коэффи- циенты зимних удорожа- ний | I33: Всего в ценах на январь 2000 года, руб. | J33: Коэффи- циенты (индек- сы) пере- счета, нормы НР и СП | K33: ВСЕГО затрат в текущем уровне цен, руб.
A34: 1 | B34: 2 | C34: 3 | D34: 4 | E34: 5 | F34: 6 | G34: 7 | H34: 8 | I34: 9 | J34: 10 | K34: 11
A36: =CONCATENATE("Локальная смета: ",IF(Source!G20<>"Новая локальная смета", Source!G20, "")) -> Локальная смета: Автоматизация и диспетчеризация
A38: =CONCATENATE("Раздел: ",IF(Source!G24<>"Новый раздел", Source!G24, "")) -> Раздел: Демонтажные работы (Письмо от АНО «РГТ» об утверждении объёмов демонтажных работ) | AP38: =CONCATENATE("Раздел: ",IF(Source!G24<>"Новый раздел", Source!G24, "")) -> Раздел: Демонтажные работы (Письмо от АНО «РГТ» об утверждении объёмов демонтажных работ)
A39: 1 | B39: =Source!F28 -> 4.11-3-1 | C39: Установка прибора массой до 5 кг на металлоконструкциях или щитах / демонтаж датчиков | D39: =Source!H28 -> 1 ШТ. | E39: =Source!I28 -> 113 | Q39: =Source!X28 -> 258.75 | R39: =Source!X29 -> 14580.57 | S39: =Source!Y28 -> 132.25 | T39: =Source!Y29 -> 7452.29 | U39: =ROUND((175/100)*ROUND(Source!R28, 2), 2) -> 0 | V39: =ROUND((0/100)*ROUND(Source!R29, 2), 2) -> 0 | AC39: 0
C40: ="Объем: "&Source!I28&"=17+"&"5+"&"14+"&"3+"&"14+"&"1+"&"30+"&"29" -> Объем: 113=17+5+14+3+14+1+30+29
C41: ЗП | F41: =Source!AO28 -> 6.75 | G41: 1,2*0,3 | H41: =Source!AV29 -> 1.047 | I41: =Source!S28 -> 287.5 | J41: =IF(Source!BA29<> 0, Source!BA29, 1) -> 56.35 | K41: =Source!S29 -> 16200.63
C42: НР от ФОТ | D42: % | E42: =Source!BZ29 -> 90 | I42: =SUM(Q39:Q41) -> 258.75 | J42: =Source!AT29 -> 90 | K42: =SUM(R39:R41) -> 14580.57
C43: СП от ФОТ | D43: % | E43: =Source!CA29 -> 46 | I43: =SUM(S39:S42) -> 132.25 | J43: =Source!AU29 -> 46 | K43: =SUM(T39:T42) -> 7452.29
C44: ЗТР | D44: чел-ч | E44: =Source!AQ28 -> 0.52 | G44: 1,2*0,3 | H44: =Source!AV29 -> 1.047 | I44: =Source!U28 -> 22.147819
C45: ВСЕГО работ по позиции: | H45: =I41+I42+I43+0-0-0 -> 678.5 | J45: =K41+K42+K43+0-0-0 -> 38233.49
C46: ВСЕГО оборудование по позиции: | H46: =0+0 -> 0 | J46: =0+0 -> 0
C47: ВСЕГО по позиции: | H47: =I41+I42+I43+0 -> 678.5 | J47: =K41+K42+K43+0 -> 38233.49 | O47: =I41+I42+I43+0 -> 678.5 | P47: =K41+K42+K43+0 -> 38233.49
A49: 2 | B49: =Source!F30 -> 4.11-3-1 | C49: Установка прибора массой до 5 кг на металлоконструкциях или щитах / демонтаж термостатов | D49: =Source!H30 -> 1 ШТ. | E49: =Source!I30 -> 14 | Q49: =Source!X30 -> 32.06 | R49: =Source!X31 -> 1806.47 | S49: =Source!Y30 -> 16.39 | T49: =Source!Y31 -> 923.31 | U49: =ROUND((175/100)*ROUND(Source!R30, 2), 2) -> 0 | V49: =ROUND((0/100)*ROUND(Source!R31, 2), 2) -> 0 | AC49: 0
C50: ="Объем: "&Source!I30&"=6+"&"8" -> Объем: 14=6+8
C51: ЗП | F51: =Source!AO30 -> 6.75 | G51: 1,2*0,3 | H51: =Source!AV31 -> 1.047 | I51: =Source!S30 -> 35.62 | J51: =IF(Source!BA31<> 0, Source!BA31, 1) -> 56.35 | K51: =Source!S31 -> 2007.19
C52: НР от ФОТ | D52: % | E52: =Source!BZ31 -> 90 | I52: =SUM(Q49:Q51) -> 32.06 | J52: =Source!AT31 -> 90 | K52: =SUM(R49:R51) -> 1806.47
C53: СП от ФОТ | D53: % | E53: =Source!CA31 -> 46 | I53: =SUM(S49:S52) -> 16.39 | J53: =Source!AU31 -> 46 | K53: =SUM(T49:T52) -> 923.31
C54: ЗТР | D54: чел-ч | E54: =Source!AQ30 -> 0.52 | G54: 1,2*0,3 | H54: =Source!AV31 -> 1.047 | I54: =Source!U30 -> 2.7439776
C55: ВСЕГО работ по позиции: | H55: =I51+I52+I53+0-0-0 -> 84.07 | J55: =K51+K52+K53+0-0-0 -> 4736.97
C56: ВСЕГО оборудование по позиции: | H56: =0+0 -> 0 | J56: =0+0 -> 0
C57: ВСЕГО по позиции: | H57: =I51+I52+I53+0 -> 84.07 | J57: =K51+K52+K53+0 -> 4736.97 | O57: =I51+I52+I53+0 -> 84.07 | P57: =K51+K52+K53+0 -> 4736.97
A59: 3 | B59: =Source!F32 -> 4.11-3-1 | C59: Установка прибора массой до 5 кг на металлоконструкциях или щитах / демонтаж электроприводов | D59: =Source!H32 -> 1 ШТ. | E59: =Source!I32 -> 65 | Q59: =Source!X32 -> 148.83 | R59: =Source!X33 -> 8386.74 | S59: =Source!Y32 -> 76.07 | T59: =Source!Y33 -> 4286.56 | U59: =ROUND((175/100)*ROUND(Source!R32, 2), 2) -> 0 | V59: =ROUND((0/100)*ROUND(Source!R33, 2), 2) -> 0 | AC59: 0
C60: ="Объем: "&Source!I32&"=24+"&"10+"&"31" -> Объем: 65=24+10+31
C61: ЗП | F61: =Source!AO32 -> 6.75 | G61: 1,2*0,3 | H61: =Source!AV33 -> 1.047 | I61: =Source!S32 -> 165.37 | J61: =IF(Source!BA33<> 0, Source!BA33, 1) -> 56.35 | K61: =Source!S33 -> 9318.6
C62: НР от ФОТ | D62: % | E62: =Source!BZ33 -> 90 | I62: =SUM(Q59:Q61) -> 148.83 | J62: =Source!AT33 -> 90 | K62: =SUM(R59:R61) -> 8386.74
C63: СП от ФОТ | D63: % | E63: =Source!CA33 -> 46 | I63: =SUM(S59:S62) -> 76.07 | J63: =Source!AU33 -> 46 | K63: =SUM(T59:T62) -> 4286.56
C64: ЗТР | D64: чел-ч | E64: =Source!AQ32 -> 0.52 | G64: 1,2*0,3 | H64: =Source!AV33 -> 1.047 | I64: =Source!U32 -> 12.739896
C65: ВСЕГО работ по позиции: | H65: =I61+I62+I63+0-0-0 -> 390.27 | J65: =K61+K62+K63+0-0-0 -> 21991.9
C66: ВСЕГО оборудование по позиции: | H66: =0+0 -> 0 | J66: =0+0 -> 0
C67: ВСЕГО по позиции: | H67: =I61+I62+I63+0 -> 390.27 | J67: =K61+K62+K63+0 -> 21991.9 | O67: =I61+I62+I63+0 -> 390.27 | P67: =K61+K62+K63+0 -> 21991.9
A69: 4 | B69: =Source!F34 -> 4.11-4-1 | C69: Монтаж уровнемера поплавкового с мерной лентой (типа УДУ) для резервуаров наземных / демонтаж подвесного датчика уровня | D69: =Source!H34 -> 1 комплект | E69: =Source!I34 -> 3 | Q69: =Source!X34 -> 133.19 | R69: =Source!X35 -> 7505.32 | S69: =Source!Y34 -> 68.08 | T69: =Source!Y35 -> 3836.05 | U69: =ROUND((175/100)*ROUND(Source!R34, 2), 2) -> 1.75 | V69: =ROUND((0/100)*ROUND(Source!R35, 2), 2) -> 0 | AC69: 0
C70: ЗП | F70: =Source!AO34 -> 129.99 | G70: 1,2*0,3 | H70: =Source!AV35 -> 1.047 | I70: =Source!S34 -> 146.99 | J70: =IF(Source!BA35<> 0, Source!BA35, 1) -> 56.35 | K70: =Source!S35 -> 8282.89
C71: ЭМ | F71: =Source!AM34 -> 11.29 | G71: 1,2*0,3 | H71: =Source!AV35 -> 1.047 | I71: =Source!Q34 -> 12.77 | J71: =IF(Source!BB35<> 0, Source!BB35, 1) -> 15.32 | K71: =Source!Q35 -> 195.64
C72: в т.ч. ЗПМ | F72: =Source!AN34 -> 0.88 | G72: 1,2*0,3 | H72: =Source!AV35 -> 1.047 | I72: =Source!R34 -> 1 | J72: =IF(Source!BS35<> 0, Source!BS35, 1) -> 56.35 | K72: =Source!R35 -> 56.35
C73: НР от ФОТ | D73: % | E73: =Source!BZ35 -> 90 | I73: =SUM(Q69:Q72) -> 133.19 | J73: =Source!AT35 -> 90 | K73: =SUM(R69:R72) -> 7505.32
C74: СП от ФОТ | D74: % | E74: =Source!CA35 -> 46 | I74: =SUM(S69:S73) -> 68.08 | J74: =Source!AU35 -> 46 | K74: =SUM(T69:T73) -> 3836.05
C75: ЗТР | D75: чел-ч | E75: =Source!AQ34 -> 10.3 | G75: 1,2*0,3 | H75: =Source!AV35 -> 1.047 | I75: =Source!U34 -> 11.646828
C76: ВСЕГО работ по позиции: | H76: =I70+I71+I73+I74+0-0-0 -> 361.03 | J76: =K70+K71+K73+K74+0-0-0 -> 19819.9
C77: ВСЕГО оборудование по позиции: | H77: =0+0 -> 0 | J77: =0+0 -> 0
C78: ВСЕГО по позиции: | H78: =I70+I71+I73+I74+0 -> 361.03 | J78: =K70+K71+K73+K74+0 -> 19819.9 | O78: =I70+I71+I73+I74+0 -> 361.03 | P78: =K70+K71+K73+K74+0 -> 19819.9
A80: 5 | B80: =Source!F36 -> 4.8-222-4 | C80: Монтаж пускателя магнитного общего назначения отдельностоящего, устанавливаемого на конструкции на стене или колонне, на ток до 40 А / демонтаж магнитного дверного контакта с реле задержки | D80: =Source!H36 -> 1 ШТ. | E80: =Source!I36 -> 4 | Q80: =Source!X36 -> 48.78 | R80: =Source!X37 -> 2748.82 | S80: =Source!Y36 -> 25.65 | T80: =Source!Y37 -> 1445.26 | U80: =ROUND((175/100)*ROUND(Source!R36, 2), 2) -> 0.35 | V80: =ROUND((0/100)*ROUND(Source!R37, 2), 2) -> 0 | AC80: 0
C81: ЗП | F81: =Source!AO36 -> 33.22 | G81: 1,2*0,3 | H81: =Source!AV37 -> 1.047 | I81: =Source!S36 -> 50.09 | J81: =IF(Source!BA37<> 0, Source!BA37, 1) -> 56.35 | K81: =Source!S37 -> 2822.57
C82: ЭМ | F82: =Source!AM36 -> 1.62 | G82: 1,2*0,3 | H82: =Source!AV37 -> 1.047 | I82: =Source!Q36 -> 2.44 | J82: =IF(Source!BB37<> 0, Source!BB37, 1) -> 15.31 | K82: =Source!Q37 -> 37.36
C83: в т.ч. ЗПМ | F83: =Source!AN36 -> 0.13 | G83: 1,2*0,3 | H83: =Source!AV37 -> 1.047 | I83: =Source!R36 -> 0.2 | J83: =IF(Source!BS37<> 0, Source!BS37, 1) -> 56.35 | K83: =Source!R37 -> 11.27
C84: НР от ФОТ | D84: % | E84: =Source!BZ37 -> 97 | I84: =SUM(Q80:Q83) -> 48.78 | J84: =Source!AT37 -> 97 | K84: =SUM(R80:R83) -> 2748.82
C85: СП от ФОТ | D85: % | E85: =Source!CA37 -> 51 | I85: =SUM(S80:S84) -> 25.65 | J85: =Source!AU37 -> 51 | K85: =SUM(T80:T84) -> 1445.26
C86: ЗТР | D86: чел-ч | E86: =Source!AQ36 -> 2.73 | G86: 1,2*0,3 | H86: =Source!AV37 -> 1.047 | I86: =Source!U36 -> 4.1159664
C87: ВСЕГО работ по позиции: | H87: =I81+I82+I84+I85+0-0-0 -> 126.96 | J87: =K81+K82+K84+K85+0-0-0 -> 7054.01
C88: ВСЕГО оборудование по позиции: | H88: =0+0 -> 0 | J88: =0+0 -> 0
C89: ВСЕГО по позиции: | H89: =I81+I82+I84+I85+0 -> 126.96 | J89: =K81+K82+K84+K85+0 -> 7054.01 | O89: =I81+I82+I84+I85+0 -> 126.96 | P89: =K81+K82+K84+K85+0 -> 7054.01
A91: 6 | B91: =Source!F38 -> 4.10-19-6 | C91: Монтаж отдельно устанавливаемого преобразователя или блока питания / демонтаж блока подключения | D91: =Source!H38 -> 1 ШТ. | E91: =Source!I38 -> 4 | Q91: =Source!X38 -> 190.33 | R91: =Source!X39 -> 10725.2 | S91: =Source!Y38 -> 97.28 | T91: =Source!Y39 -> 5481.77 | U91: =ROUND((175/100)*ROUND(Source!R38, 2), 2) -> 13.32 | V91: =ROUND((0/100)*ROUND(Source!R39, 2), 2) -> 0 | AC91: 0
C92: ЗП | F92: =Source!AO38 -> 135.22 | G92: 1,2*0,3 | H92: =Source!AV39 -> 1.047 | I92: =Source!S38 -> 203.87 | J92: =IF(Source!BA39<> 0, Source!BA39, 1) -> 56.35 | K92: =Source!S39 -> 11488.07
C93: ЭМ | F93: =Source!AM38 -> 45.93 | G93: 1,2*0,3 | H93: =Source!AV39 -> 1.047 | I93: =Source!Q38 -> 69.25 | J93: =IF(Source!BB39<> 0, Source!BB39, 1) -> 16.16 | K93: =Source!Q39 -> 1119.08
C94: в т.ч. ЗПМ | F94: =Source!AN38 -> 5.05 | G94: 1,2*0,3 | H94: =Source!AV39 -> 1.047 | I94: =Source!R38 -> 7.61 | J94: =IF(Source!BS39<> 0, Source!BS39, 1) -> 56.35 | K94: =Source!R39 -> 428.82
C95: НР от ФОТ | D95: % | E95: =Source!BZ39 -> 90 | I95: =SUM(Q91:Q94) -> 190.33 | J95: =Source!AT39 -> 90 | K95: =SUM(R91:R94) -> 10725.2
C96: СП от ФОТ | D96: % | E96: =Source!CA39 -> 46 | I96: =SUM(S91:S95) -> 97.28 | J96: =Source!AU39 -> 46 | K96: =SUM(T91:T95) -> 5481.77
C97: ЗТР | D97: чел-ч | E97: =Source!AQ38 -> 9.3 | G97: 1,2*0,3 | H97: =Source!AV39 -> 1.047 | I97: =Source!U38 -> 14.021424
C98: ВСЕГО работ по позиции: | H98: =I92+I93+I95+I96+0-0-0 -> 560.73 | J98: =K92+K93+K95+K96+0-0-0 -> 28814.12
C99: ВСЕГО оборудование по позиции: | H99: =0+0 -> 0 | J99: =0+0 -> 0
C100: ВСЕГО по позиции: | H100: =I92+I93+I95+I96+0 -> 560.73 | J100: =K92+K93+K95+K96+0 -> 28814.12 | O100: =I92+I93+I95+I96+0 -> 560.73 | P100: =K92+K93+K95+K96+0 -> 28814.12
A102: 7 | B102: =Source!F40 -> 4.11-8-1 | C102: Установка аппарата напольного массой до 0,2 т / демонтаж системного блока | D102: =Source!H40 -> 1 ШТ. | E102: =Source!I40 -> 1 | Q102: =Source!X40 -> 42.43 | R102: =Source!X41 -> 2390.7 | S102: =Source!Y40 -> 21.68 | T102: =Source!Y41 -> 1221.91 | U102: =ROUND((175/100)*ROUND(Source!R40, 2), 2) -> 3.62 | V102: =ROUND((0/100)*ROUND(Source!R41, 2), 2) -> 0 | AC102: 0
C103: ЗП | F103: =Source!AO40 -> 119.58 | G103: 1,2*0,3 | H103: =Source!AV41 -> 1.047 | I103: =Source!S40 -> 45.07 | J103: =IF(Source!BA41<> 0, Source!BA41, 1) -> 56.35 | K103: =Source!S41 -> 2539.69
C104: ЭМ | F104: =Source!AM40 -> 36.39 | G104: 1,2*0,3 | H104: =Source!AV41 -> 1.047 | I104: =Source!Q40 -> 13.72 | J104: =IF(Source!BB41<> 0, Source!BB41, 1) -> 17.01 | K104: =Source!Q41 -> 233.38
C105: в т.ч. ЗПМ | F105: =Source!AN40 -> 5.48 | G105: 1,2*0,3 | H105: =Source!AV41 -> 1.047 | I105: =Source!R40 -> 2.07 | J105: =IF(Source!BS41<> 0, Source!BS41, 1) -> 56.35 | K105: =Source!R41 -> 116.64
C106: НР от ФОТ | D106: % | E106: =Source!BZ41 -> 90 | I106: =SUM(Q102:Q105) -> 42.43 | J106: =Source!AT41 -> 90 | K106: =SUM(R102:R105) -> 2390.7
C107: СП от ФОТ | D107: % | E107: =Source!CA41 -> 46 | I107: =SUM(S102:S106) -> 21.68 | J107: =Source!AU41 -> 46 | K107: =SUM(T102:T106) -> 1221.91
C108: ЗТР | D108: чел-ч | E108: =Source!AQ40 -> 10.3 | G108: 1,2*0,3 | H108: =Source!AV41 -> 1.047 | I108: =Source!U40 -> 3.882276
C109: ВСЕГО работ по позиции: | H109: =I103+I104+I106+I107+0-0-0 -> 122.9 | J109: =K103+K104+K106+K107+0-0-0 -> 6385.68
C110: ВСЕГО оборудование по позиции: | H110: =0+0 -> 0 | J110: =0+0 -> 0
C111: ВСЕГО по позиции: | H111: =I103+I104+I106+I107+0 -> 122.9 | J111: =K103+K104+K106+K107+0 -> 6385.68 | O111: =I103+I104+I106+I107+0 -> 122.9 | P111: =K103+K104+K106+K107+0 -> 6385.68
A113: 8 | B113: =Source!F42 -> 4.11-7-2 | C113: Установка аппарата настольного массой до 0,03 т / демонтаж монитора | D113: =Source!H42 -> 1 ШТ. | E113: =Source!I42 -> 1 | Q113: =Source!X42 -> 13.09 | R113: =Source!X43 -> 737.4 | S113: =Source!Y42 -> 6.69 | T113: =Source!Y43 -> 376.89 | U113: =ROUND((175/100)*ROUND(Source!R42, 2), 2) -> 2.66 | V113: =ROUND((0/100)*ROUND(Source!R43, 2), 2) -> 0 | AC113: 0
C114: ЗП | F114: =Source!AO42 -> 34.55 | G114: 1,2*0,3 | H114: =Source!AV43 -> 1.047 | I114: =Source!S42 -> 13.02 | J114: =IF(Source!BA43<> 0, Source!BA43, 1) -> 56.35 | K114: =Source!S43 -> 733.68
C115: ЭМ | F115: =Source!AM42 -> 26.59 | G115: 1,2*0,3 | H115: =Source!AV43 -> 1.047 | I115: =Source!Q42 -> 10.02 | J115: =IF(Source!BB43<> 0, Source!BB43, 1) -> 17.07 | K115: =Source!Q43 -> 171.04
C116: в т.ч. ЗПМ | F116: =Source!AN42 -> 4.04 | G116: 1,2*0,3 | H116: =Source!AV43 -> 1.047 | I116: =Source!R42 -> 1.52 | J116: =IF(Source!BS43<> 0, Source!BS43, 1) -> 56.35 | K116: =Source!R43 -> 85.65
C117: НР от ФОТ | D117: % | E117: =Source!BZ43 -> 90 | I117: =SUM(Q113:Q116) -> 13.09 | J117: =Source!AT43 -> 90 | K117: =SUM(R113:R116) -> 737.4
C118: СП от ФОТ | D118: % | E118: =Source!CA43 -> 46 | I118: =SUM(S113:S117) -> 6.69 | J118: =Source!AU43 -> 46 | K118: =SUM(T113:T117) -> 376.89
...

Sheet Source
A1: 0 | B1: Smeta.RU (495) 974-1589 | D1: _PS_ | F1: 0 | G1: 0 | H1: 0 | I1: Smeta.RU | K1: 1 | L1: 74599 | M1: 10 | N1: 12 | O1: 1 | P1: 0 | Q1: 5
A4: 1 | B4: 1 | C4: -1 | G4: Капитальный ремонт здания Государственного бюджетного общеобразовательного учреждения города Москвы «Школа №1574», расположенного по адресу: г. Москва, Старопименовский переулок, д. 5. 1 этап | EC4: 0
A5: 8 | B5: 1 | C5: -1 | G5: Капитальный ремонт здания Государственного бюджетного общеобразовательного учреждения города Москвы «Школа №1574», расположенного по адресу: г. Москва, Старопименовский переулок, д. 5. 1 этап | EC5: 0
A12: 1 | B12: 880 | C12: 0 | D12: =ROW(A838) -> 838 | E12: 0 | F12: 02-01-18 | G12: 02-01-18 АДИС 16.07.26 | I12: 0 | J12: 2024-00375-01-0-ИОС5.11 | K12: 0 | L12: 0 | M12: 4098 | O12: 0 | P12: 0 | Q12: 0 | R12: 0 | S12: 0 | T12: 1 | U12: Капитальный ремонт здания Государственного бюджетного общеобразовательного учреждения города Москвы «Школа №1574» | V12: 2 | W12: г. Москва, Старопименовский переулок, д. 5. 1 этап | AB12: О.А.Гришечкина | AC12: Ведущий инженер-сметчик | AD12: И.В.Феденко | AE12: Начальник отдела | BB12: 0 | BH12: Сметные нормы списания | BI12: Коды ОКП для ТСН-2001 МГЭ Дополнение 81 | BJ12: 1 | BK12: 1 | BL12: 0 | BM12: 0 | BN12: 1 | BO12: 0 | BP12: 6 | BQ12: 2 | BR12: 1 | BS12: 1 | BT12: 0 | BU12: 0 | BV12: 0 | BW12: 0 | BX12: 0 | BZ12: Типовой расчет для ТСН-2001 МГЭ, Дополнение 81, ремонт | CA12: Территориальные сметные нормативы для Москвы ТСН-2001 (МГЭ), дополнение 81 | CB12: Территориальные сметные нормативы для Москвы ТСН-2001 (МГЭ), дополнение 81 | CC12: Территориальные сметные нормативы для Москвы ТСН-2001 (МГЭ), дополнение 81 | CD12: Территориальные сметные нормативы для Москвы ТСН-2001 (МГЭ), дополнение 81 | CE12: Поправки для ТСН-2001 от 07.04.2026 г. доп.81 | CF12: 0 | CG12: 0 | CH12: 8200 | CK12: 82 | CQ12: Территориальные сметные нормативы для Москвы (ТСН-2001) | CR12: ТЕР | CS12: 41660 | CT12: 1 | CU12: 81 | CY12: 0 | EC12: 0
A15: 15 | B15: 1
A18: 52 | B18: =B838 -> 880 | C18: =C838 -> 1 | D18: =D838 -> 12 | E18: =E838 -> 0 | F18: =F838 -> 02-01-18 | G18: =G838 -> 02-01-18 АДИС 16.07.26 | O18: =O838 -> 3887861.5 | P18: =P838 -> 3850190.2 | Q18: =Q838 -> 5352.17 | R18: =R838 -> 749.69 | S18: =S838 -> 32319.17 | T18: =T838 -> 0 | U18: =U838 -> 2619.8285 | V18: =V838 -> 0 | ... GX18: =GX838 -> 0
A20: 3 | B20: 1 | D20: =ROW(A805) -> 805 | F20: 02-01-18 | G20: Автоматизация и диспетчеризация | I20: 0 | J20: 2024-00375-01-0-ИОС5.11 | K20: -1 | L20: 02-01-18 | S20: 0 | T20: 0 | V20: 2 | BX20: 0 | CF20: 0 | CG20: 0
A22: 52 | B22: =B805 -> 1 | C22: =C805 -> 3 | D22: =D805 -> 20 | E22: =E805 -> 0 | F22: =F805 -> 02-01-18 | G22: =G805 -> Автоматизация и диспетчеризация | O22: =O805 -> 3887861.5 | P22: =P805 -> 3850190.2 | Q22: =Q805 -> 5352.17 | R22: =R805 -> 749.69 | S22: =S805 -> 32319.17 | T22: =T805 -> 0 | U22: =U805 -> 2619.8285 | V22: =V805 -> 0 | ... GX22: =GX805 -> 0
A24: 4 | B24: 1 | D24: =ROW(A87) -> 87 | F24: Новый раздел | G24: Демонтажные работы (Письмо от АНО «РГТ» об утверждении объёмов демонтажных работ) | I24: 0 | K24: -1 | S24: 0 | T24: 0 | V24: 2 | BX24: 0 | CJ24: 0
A26: 52 | B26: =B87 -> 1 | C26: =C87 -> 4 | D26: =D87 -> 24 | E26: =E87 -> 0 | F26: =F87 -> Новый раздел | G26: =G87 -> Демонтажные работы (Письмо от АНО «РГТ» об утверждении объёмов демонтажных работ) | O26: =O87 -> 8811.58 | P26: =P87 -> 0 | Q26: =Q87 -> 1253.57 | R26: =R87 -> 211.26 | S26: =S87 -> 7558.01 | T26: =T87 -> 0 | U26: =U87 -> 607.88738 | V26: =V87 -> 0 | ... GX26: =GX87 -> 0
A28: 17 | B28: 1 | C28: =ROW(SmtRes!A1) -> 1 | D28: =ROW(EtalonRes!A3) -> 3 | E28: 1 | F28: 4.11-3-1 | G28: Установка прибора массой до 5 кг на металлоконструкциях или щитах / демонтаж датчиков | H28: 1 ШТ. | I28: =ROUND(17+5+14+3+14+1+30+29,9) -> 113 | J28: 0 | K28: =ROUND(17+5+14+3+14+1+30+29,9) -> 113 | O28: =ROUND(CP28,2) -> 287.5 | P28: =ROUND((ROUND((AC28*AW28*I28),2)*BC28),2) -> 0 | Q28: =(ROUND((ROUND(((((ET28*1.2)*0.3))*AV28*I28),2)*BB28),2)+ROUND((ROUND(((AE28-(((EU28*1.2)*0.3)))*AV28*I28),2)*BS28),2)) -> 0 | R28: =(ROUND((ROUND(((((EU28*1.2)*0.3))*AV28*I28),2)*BS28),2)+ROUND((ROUND(((AE28-(((EU28*1.2)*0.3)))*AV28*I28),2)*BS28),2)) -> 0 | S28: =ROUND((ROUND((AF28*AV28*I28),2)*BA28),2) -> 287.5 | T28: =ROUND(CU28*I28,2) -> 0 | U28: =CV28*I28 -> 22.147819 | V28: =CW28*I28 -> 0 | W28: =ROUND(CX28*I28,2) -> 0 | X28: =(ROUND((((S28+ROUND((ROUND(((((EU28*1.2)*0.3))*AV28*I28),2)*BS28),2))*AT28)/100),2)+ROUND(((ROUND((ROUND(((AE28-(((EU28*1.2)*0.3)))*AV28*I28),2)*BS28),2)*AT28)/100),2)) -> 258.75 | Y28: =(ROUND((((S28+ROUND((ROUND(((((EU28*1.2)*0.3))*AV28*I28),2)*BS28),2))*AU28)/100),2)+ROUND(((ROUND((ROUND(((AE28-(((EU28*1.2)*0.3)))*AV28*I28),2)*BS28),2)*AU28)/100),2)) -> 132.25 | AA28: 55944368 | AB28: =ROUND((AC28+AD28+AF28),6) -> 2.43 | AC28: =ROUND((((ES28*1)*0)),6) -> 0 | AD28: =ROUND((((((ET28*1.2)*0.3))-(((EU28*1.2)*0.3)))+AE28),6) -> 0 | AE28: =ROUND((((EU28*1.2)*0.3)),6) -> 0 | AF28: =ROUND((((EV28*1.2)*0.3)),6) -> 2.43 | AG28: =ROUND((AP28),6) -> 0 | AH28: =(((EW28*1.2)*0.3)) -> 0.1872 | AI28: =(((EX28*1.2)*0.3)) -> 0 | AJ28: =(AS28) -> 0 | AK28: 6.75 | AL28: 0 | AM28: 0 | AN28: 0 | AO28: 6.75 | AP28: 0 | AQ28: 0.52 | AR28: 0 | AS28: 0 | AT28: 90 | AU28: 46 | AV28: 1.047 | AW28: 1 | AZ28: 1 | BA28: 1 | BB28: 1 | BC28: 1 | BH28: 0 | BI28: 2 | BJ28: ТСН-2001.4 Доп. 67, Сб. 11, т. 3, поз. 1 | BM28: 72 | BN28: 0 | BO28: 4.11-3-1 | BP28: 1 | BQ28: 40 | BR28: 0 | BS28: 1 | BT28: 1 | BU28: 1 | BV28: 1 | BW28: 1 | BX28: 1 | BZ28: 90 | CA28: 46 | CE28: 1566 | CF28: 0 | CG28: 0 | CM28: 0 | CN28: Поправка: Гл.12.Прил.8.п.8. 3_12.00.01.11.001 Наименование: При наличии напряженных и стесненных условий производства работ (стесненность, сложность складирования и транспортной логистики и т.п.) для объектов, расположенных в пределах круговой магистральной системы улиц "Садовое кольцо" города Москвы Поправка: Гл.4.Прил.2.2.п.2.2.29_04.00.01.35.003 Наименование: При демонтаже оборудования, предназначенного в лом | CO28: 0 | CP28: =(P28+Q28+S28) -> 287.5 | CQ28: =ROUND((ROUND((AC28*AW28*1),2)*BC28),2) -> 0 | CR28: =(ROUND((ROUND(((((ET28*1.2)*0.3))*AV28*1),2)*BB28),2)+ROUND((ROUND(((AE28-(((EU28*1.2)*0.3)))*AV28*1),2)*BS28),2)) -> 0 | CS28: =(ROUND((ROUND(((((EU28*1.2)*0.3))*AV28*1),2)*BS28),2)+ROUND((ROUND(((AE28-(((EU28*1.2)*0.3)))*AV28*1),2)*BS28),2)) -> 0 | CT28: =ROUND((ROUND((AF28*AV28*1),2)*BA28),2) -> 2.54 | CU28: =AG28 -> 0 | CV28: =(AH28*AV28) -> 0.1959984 | CW28: =AI28 -> 0 | CX28: =AJ28 -> 0 | CY28: =(ROUND((((S28+ROUND((ROUND(((((EU28*1.2)*0.3))*AV28*1),2)*BS28),2))*AT28)/100),2)+ROUND(((ROUND((ROUND(((AE28-(((EU28*1.2)*0.3)))*AV28*1),2)*BS28),2)*AT28)/100),2)) -> 258.75 | CZ28: =(ROUND((((S28+ROUND((ROUND(((((EU28*1.2)*0.3))*AV28*1),2)*BS28),2))*AU28)/100),2)+ROUND(((ROUND((ROUND(((AE28-(((EU28*1.2)*0.3)))*AV28*1),2)*BS28),2)*AU28)/100),2)) -> 132.25 | DB28: 1 | DD28: *1)*0 | DE28: *1,2)*0,3 | DF28: *1,2)*0,3 | DG28: *1,2)*0,3 | DI28: *1,2)*0,3 | DJ28: *1,2)*0,3 | DN28: 0 | DO28: 0 | DP28: 1 | DQ28: 1 | DU28: 1013 | DV28: 1 ШТ. | DW28: 1 ШТ. | DX28: 1 | EE28: 55393976 | EF28: 40 | EG28: Монтаж оборудования | EH28: 0 | EJ28: 2 | EK28: 72 | EL28: ТСН-2001.4-11. Приборы и средства автоматизации и вычислительной техники | EM28: ТСН-2001.4-11-1 | EO28: Поправка: Гл.12.Прил.8.п.8. 3_12.00.01.11.001 Поправка: Гл.4.Прил.2.2.п.2.2.29_04.00.01.35.003 | EQ28: 0 | ER28: 6.75 | ES28: 0 | ET28: 0 | EU28: 0 | EV28: 6.75 | EW28: 0.52 | EX28: 0 | EY28: 0 | FQ28: 0 | FR28: 0 | FS28: 0 | FX28: 90 | FY28: 46 | GD28: 1 | GF28: 1988963433 | GG28: 2 | GH28: 1 | GI28: 2 | GJ28: 0 | GK28: 0 | GL28: =ROUND(IF(AND(BH28=3,BI28=3,FS28<>0),P28,0),2) -> 0 | GM28: =ROUND(O28+X28+Y28,2)+GX28 -> 678.5 | GN28: =IF(OR(BI28=0,BI28=1),GM28-GX28,0) -> 0 | GO28: =IF(BI28=2,GM28-GX28,0) -> 678.5 | GP28: =IF(BI28=4,GM28-GX28,0) -> 0 | GR28: 0 | GS28: 3 | GT28: 0 | GV28: =ROUND((GT28),6) -> 0 | GW28: 1 | GX28: =ROUND(HC28*I28,2) -> 0 | HA28: 0 | HB28: 0 | HC28: =GV28*GW28 -> 0 | HS28: 0 | IK28: 0
A29: 17 | B29: 1 | C29: =ROW(SmtRes!A2) -> 2 | D29: =ROW(EtalonRes!A6) -> 6 | E29: 1 | F29: 4.11-3-1 | G29: Установка прибора массой до 5 кг на металлоконструкциях или щитах / демонтаж датчиков | H29: 1 ШТ. | I29: =ROUND(17+5+14+3+14+1+30+29,9) -> 113 | J29: 0 | K29: =ROUND(17+5+14+3+14+1+30+29,9) -> 113 | O29: =ROUND(CP29,2) -> 16200.63 | P29: =ROUND((ROUND((AC29*AW29*I29),2)*BC29),2) -> 0 | Q29: =(ROUND((ROUND(((((ET29*1.2)*0.3))*AV29*I29),2)*BB29),2)+ROUND((ROUND(((AE29-(((EU29*1.2)*0.3)))*AV29*I29),2)*BS29),2)) -> 0 | R29: =(ROUND((ROUND(((((EU29*1.2)*0.3))*AV29*I29),2)*BS29),2)+ROUND((ROUND(((AE29-(((EU29*1.2)*0.3)))*AV29*I29),2)*BS29),2)) -> 0 | S29: =ROUND((ROUND((AF29*AV29*I29),2)*BA29),2) -> 16200.63 | T29: =ROUND(CU29*I29,2) -> 0 | U29: =CV29*I29 -> 22.147819 | V29: =CW29*I29 -> 0 | W29: =ROUND(CX29*I29,2) -> 0 | X29: =(ROUND((((S29+ROUND((ROUND(((((EU29*1.2)*0.3))*AV29*I29),2)*BS29),2))*AT29)/100),2)+ROUND(((ROUND((ROUND(((AE29-(((EU29*1.2)*0.3)))*AV29*I29),2)*BS29),2)*AT29)/100),2)) -> 14580.57 | Y29: =(ROUND((((S29+ROUND((ROUND(((((EU29*1.2)*0.3))*AV29*I29),2)*BS29),2))*AU29)/100),2)+ROUND(((ROUND((ROUND(((AE29-(((EU29*1.2)*0.3)))*AV29*I29),2)*BS29),2)*AU29)/100),2)) -> 7452.29 | AA29: 55944370 | AB29: =ROUND((AC29+AD29+AF29),6) -> 2.43 | AC29: =ROUND((((ES29*1)*0)),6) -> 0 | AD29: =ROUND((((((ET29*1.2)*0.3))-(((EU29*1.2)*0.3)))+AE29),6) -> 0 | AE29: =ROUND((((EU29*1.2)*0.3)),6) -> 0 | AF29: =ROUND((((EV29*1.2)*0.3)),6) -> 2.43 | AG29: =ROUND((AP29),6) -> 0 | AH29: =(((EW29*1.2)*0.3)) -> 0.1872 | AI29: =(((EX29*1.2)*0.3)) -> 0 | AJ29: =(AS29) -> 0 | AK29: 6.75 | AL29: 0 | AM29: 0 | AN29: 0 | AO29: 6.75 | AP29: 0 | AQ29: 0.52 | AR29: 0 | AS29: 0 | AT29: 90 | AU29: 46 | AV29: 1.047 | AW29: 1 | AZ29: 1 | BA29: 56.35 | BB29: 1 | BC29: 1 | BH29: 0 | BI29: 2 | BJ29: ТСН-2001.4 Доп. 67, Сб. 11, т. 3, поз. 1 | BM29: 72 | BN29: 0 | BO29: 4.11-3-1 | BP29: 1 | BQ29: 40 | BR29: 0 | BS29: 56.35 | BT29: 1 | BU29: 1 | BV29: 1 | BW29: 1 | BX29: 1 | BZ29: 90 | CA29: 46 | CE29: 1566 | CF29: 0 | CG29: 0 | CM29: 0 | CN29: Поправка: Гл.12.Прил.8.п.8. 3_12.00.01.11.001 Наименование: При наличии напряженных и стесненных условий производства работ (стесненность, сложность складирования и транспортной логистики и т.п.) для объектов, расположенных в пределах круговой магистральной системы улиц "Садовое кольцо" города Москвы Поправка: Гл.4.Прил.2.2.п.2.2.29_04.00.01.35.003 Наименование: При демонтаже оборудования, предназначенного в лом | CO29: 0 | CP29: =(P29+Q29+S29) -> 16200.63 | CQ29: =ROUND((ROUND((AC29*AW29*1),2)*BC29),2) -> 0 | CR29: =(ROUND((ROUND(((((ET29*1.2)*0.3))*AV29*1),2)*BB29),2)+ROUND((ROUND(((AE29-(((EU29*1.2)*0.3)))*AV29*1),2)*BS29),2)) -> 0 | CS29: =(ROUND((ROUND(((((EU29*1.2)*0.3))*AV29*1),2)*BS29),2)+ROUND((ROUND(((AE29-(((EU29*1.2)*0.3)))*AV29*1),2)*BS29),2)) -> 0 | CT29: =ROUND((ROUND((AF29*AV29*1),2)*BA29),2) -> 143.13 | CU29: =AG29 -> 0 | CV29: =(AH29*AV29) -> 0.1959984 | CW29: =AI29 -> 0 | CX29: =AJ29 -> 0 | CY29: =(ROUND((((S29+ROUND((ROUND(((((EU29*1.2)*0.3))*AV29*1),2)*BS29),2))*AT29)/100),2)+ROUND(((ROUND((ROUND(((AE29-(((EU29*1.2)*0.3)))*AV29*1),2)*BS29),2)*AT29)/100),2)) -> 14580.57 | CZ29: =(ROUND((((S29+ROUND((ROUND(((((EU29*1.2)*0.3))*AV29*1),2)*BS29),2))*AU29)/100),2)+ROUND(((ROUND((ROUND(((AE29-(((EU29*1.2)*0.3)))*AV29*1),2)*BS29),2)*AU29)/100),2)) -> 7452.29 | DB29: 3 | DD29: *1)*0 | DE29: *1,2)*0,3 | DF29: *1,2)*0,3 | DG29: *1,2)*0,3 | DI29: *1,2)*0,3 | DJ29: *1,2)*0,3 | DN29: 0 | DO29: 0 | DP29: 1 | DQ29: 1 | DU29: 1013 | DV29: 1 ШТ. | DW29: 1 ШТ. | DX29: 1 | EE29: 55393976 | EF29: 40 | EG29: Монтаж оборудования | EH29: 0 | EJ29: 2 | EK29: 72 | EL29: ТСН-2001.4-11. Приборы и средства автоматизации и вычислительной техники | EM29: ТСН-2001.4-11-1 | EO29: Поправка: Гл.12.Прил.8.п.8. 3_12.00.01.11.001 Поправка: Гл.4.Прил.2.2.п.2.2.29_04.00.01.35.003 | EQ29: 0 | ER29: 6.75 | ES29: 0 | ET29: 0 | EU29: 0 | EV29: 6.75 | EW29: 0.52 | EX29: 0 | EY29: 0 | FQ29: 0 | FR29: 0 | FS29: 0 | FX29: 90 | FY29: 46 | GD29: 1 | GF29: 1988963433 | GG29: 2 | GH29: 1 | GI29: 2 | GJ29: 0 | GK29: 0 | GL29: =ROUND(IF(AND(BH29=3,BI29=3,FS29<>0),P29,0),2) -> 0 | GM29: =ROUND(O29+X29+Y29,2)+GX29 -> 38233.49 | GN29: =IF(OR(BI29=0,BI29=1),GM29-GX29,0) -> 0 | GO29: =IF(BI29=2,GM29-GX29,0) -> 38233.49 | GP29: =IF(BI29=4,GM29-GX29,0) -> 0 | GR29: 0 | GS29: 3 | GT29: 0 | GV29: =ROUND((GT29),6) -> 0 | GW29: 1 | GX29: =ROUND(HC29*I29,2) -> 0 | HA29: 0 | HB29: 0 | HC29: =GV29*GW29 -> 0 | HS29: 0 | IK29: 0
A30: 17 | B30: 1 | C30: =ROW(SmtRes!A3) -> 3 | D30: =ROW(EtalonRes!A9) -> 9 | E30: 2 | F30: 4.11-3-1 | G30: Установка прибора массой до 5 кг на металлоконструкциях или щитах / демонтаж термостатов | H30: 1 ШТ. | I30: =ROUND(6+8,9) -> 14 | J30: 0 | K30: =ROUND(6+8,9) -> 14 | O30: =ROUND(CP30,2) -> 35.62 | P30: =ROUND((ROUND((AC30*AW30*I30),2)*BC30),2) -> 0 | Q30: =(ROUND((ROUND(((((ET30*1.2)*0.3))*AV30*I30),2)*BB30),2)+ROUND((ROUND(((AE30-(((EU30*1.2)*0.3)))*AV30*I30),2)*BS30),2)) -> 0 | R30: =(ROUND((ROUND(((((EU30*1.2)*0.3))*AV30*I30),2)*BS30),2)+ROUND((ROUND(((AE30-(((EU30*1.2)*0.3)))*AV30*I30),2)*BS30),2)) -> 0 | S30: =ROUND((ROUND((AF30*AV30*I30),2)*BA30),2) -> 35.62 | T30: =ROUND(CU30*I30,2) -> 0 | U30: =CV30*I30 -> 2.7439776 | V30: =CW30*I30 -> 0 | W30: =ROUND(CX30*I30,2) -> 0 | X30: =(ROUND((((S30+ROUND((ROUND(((((EU30*1.2)*0.3))*AV30*I30),2)*BS30),2))*AT30)/100),2)+ROUND(((ROUND((ROUND(((AE30-(((EU30*1.2)*0.3)))*AV30*I30),2)*BS30),2)*AT30)/100),2)) -> 32.06 | Y30: =(ROUND((((S30+ROUND((ROUND(((((EU30*1.2)*0.3))*AV30*I30),2)*BS30),2))*AU30)/100),2)+ROUND(((ROUND((ROUND(((AE30-(((EU30*1.2)*0.3)))*AV30*I30),2)*BS30),2)*AU30)/100),2)) -> 16.39 | AA30: 55944368 | AB30: =ROUND((AC30+AD30+AF30),6) -> 2.43 | AC30: =ROUND((((ES30*1)*0)),6) -> 0 | AD30: =ROUND((((((ET30*1.2)*0.3))-(((EU30*1.2)*0.3)))+AE30),6) -> 0 | AE30: =ROUND((((EU30*1.2)*0.3)),6) -> 0 | AF30: =ROUND((((EV30*1.2)*0.3)),6) -> 2.43 | AG30: =ROUND((AP30),6) -> 0 | AH30: =(((EW30*1.2)*0.3)) -> 0.1872 | AI30: =(((EX30*1.2)*0.3)) -> 0 | AJ30: =(AS30) -> 0 | AK30: 6.75 | AL30: 0 | AM30: 0 | AN30: 0 | AO30: 6.75 | AP30: 0 | AQ30: 0.52 | AR30: 0 | AS30: 0 | AT30: 90 | AU30: 46 | AV30: 1.047 | AW30: 1 | AZ30: 1 | BA30: 1 | BB30: 1 | BC30: 1 | BH30: 0 | BI30: 2 | BJ30: ТСН-2001.4 Доп. 67, Сб. 11, т. 3, поз. 1 | BM30: 72 | BN30: 0 | BO30: 4.11-3-1 | BP30: 1 | BQ30: 40 | BR30: 0 | BS30: 1 | BT30: 1 | BU30: 1 | BV30: 1 | BW30: 1 | BX30: 1 | BZ30: 90 | CA30: 46 | CE30: 1566 | CF30: 0 | CG30: 0 | CM30: 0 | CN30: Поправка: Гл.12.Прил.8.п.8. 3_12.00.01.11.001 Наименование: При наличии напряженных и стесненных условий производства работ (стесненность, сложность складирования и транспортной логистики и т.п.) для объектов, расположенных в пределах круговой магистральной системы улиц "Садовое кольцо" города Москвы Поправка: Гл.4.Прил.2.2.п.2.2.29_04.00.01.35.003 Наименование: При демонтаже оборудования, предназначенного в лом | CO30: 0 | CP30: =(P30+Q30+S30) -> 35.62 | CQ30: =ROUND((ROUND((AC30*AW30*1),2)*BC30),2) -> 0 | CR30: =(ROUND((ROUND(((((ET30*1.2)*0.3))*AV30*1),2)*BB30),2)+ROUND((ROUND(((AE30-(((EU30*1.2)*0.3)))*AV30*1),2)*BS30),2)) -> 0 | CS30: =(ROUND((ROUND(((((EU30*1.2)*0.3))*AV30*1),2)*BS30),2)+ROUND((ROUND(((AE30-(((EU30*1.2)*0.3)))*AV30*1),2)*BS30),2)) -> 0 | CT30: =ROUND((ROUND((AF30*AV30*1),2)*BA30),2) -> 2.54 | CU30: =AG30 -> 0 | CV30: =(AH30*AV30) -> 0.1959984 | CW30: =AI30 -> 0 | CX30: =AJ30 -> 0 | CY30: =(ROUND((((S30+ROUND((ROUND(((((EU30*1.2)*0.3))*AV30*1),2)*BS30),2))*AT30)/100),2)+ROUND(((ROUND((ROUND(((AE30-(((EU30*1.2)*0.3)))*AV30*1),2)*BS30),2)*AT30)/100),2)) -> 32.06 | CZ30: =(ROUND((((S30+ROUND((ROUND(((((EU30*1.2)*0.3))*AV30*1),2)*BS30),2))*AU30)/100),2)+ROUND(((ROUND((ROUND(((AE30-(((EU30*1.2)*0.3)))*AV30*1),2)*BS30),2)*AU30)/100),2)) -> 16.39 | DB30: 5 | DD30: *1)*0 | DE30: *1,2)*0,3 | DF30: *1,2)*0,3 | DG30: *1,2)*0,3 | DI30: *1,2)*0,3 | DJ30: *1,2)*0,3 | DN30: 0 | DO30: 0 | DP30: 1 | DQ30: 1 | DU30: 1013 | DV30: 1 ШТ. | DW30: 1 ШТ. | DX30: 1 | EE30: 55393976 | EF30: 40 | EG30: Монтаж оборудования | EH30: 0 | EJ30: 2 | EK30: 72 | EL30: ТСН-2001.4-11. Приборы и средства автоматизации и вычислительной техники | EM30: ТСН-2001.4-11-1 | EO30: Поправка: Гл.12.Прил.8.п.8. 3_12.00.01.11.001 Поправка: Гл.4.Прил.2.2.п.2.2.29_04.00.01.35.003 | EQ30: 0 | ER30: 6.75 | ES30: 0 | ET30: 0 | EU30: 0 | EV30: 6.75 | EW30: 0.52 | EX30: 0 | EY30: 0 | FQ30: 0 | FR30: 0 | FS30: 0 | FX30: 90 | FY30: 46 | GD30: 1 | GF30: -615345603 | GG30: 2 | GH30: 1 | GI30: 2 | GJ30: 0 | GK30: 0 | GL30: =ROUND(IF(AND(BH30=3,BI30=3,FS30<>0),P30,0),2) -> 0 | GM30: =ROUND(O30+X30+Y30,2)+GX30 -> 84.07 | GN30: =IF(OR(BI30=0,BI30=1),GM30-GX30,0) -> 0 | GO30: =IF(BI30=2,GM30-GX30,0) -> 84.07 | GP30: =IF(BI30=4,GM30-GX30,0) -> 0 | GR30: 0 | GS30: 3 | GT30: 0 | GV30: =ROUND((GT30),6) -> 0 | GW30: 1 | GX30: =ROUND(HC30*I30,2) -> 0 | HA30: 0 | HB30: 0 | HC30: =GV30*GW30 -> 0 | HS30: 0 | IK30: 0
A31: 17 | B31: 1 | C31: =ROW(SmtRes!A4) -> 4 | D31: =ROW(EtalonRes!A12) -> 12 | E31: 2 | F31: 4.11-3-1 | G31: Установка прибора массой до 5 кг на металлоконструкциях или щитах / демонтаж термостатов | H31: 1 ШТ. | I31: =ROUND(6+8,9) -> 14 | J31: 0 | K31: =ROUND(6+8,9) -> 14 | O31: =ROUND(CP31,2) -> 2007.19 | P31: =ROUND((ROUND((AC31*AW31*I31),2)*BC31),2) -> 0 | Q31: =(ROUND((ROUND(((((ET31*1.2)*0.3))*AV31*I31),2)*BB31),2)+ROUND((ROUND(((AE31-(((EU31*1.2)*0.3)))*AV31*I31),2)*BS31),2)) -> 0 | R31: =(ROUND((ROUND(((((EU31*1.2)*0.3))*AV31*I31),2)*BS31),2)+ROUND((ROUND(((AE31-(((EU31*1.2)*0.3)))*AV31*I31),2)*BS31),2)) -> 0 | S31: =ROUND((ROUND((AF31*AV31*I31),2)*BA31),2) -> 2007.19 | T31: =ROUND(CU31*I31,2) -> 0 | U31: =CV31*I31 -> 2.7439776 | V31: =CW31*I31 -> 0 | W31: =ROUND(CX31*I31,2) -> 0 | X31: =(ROUND((((S31+ROUND((ROUND(((((EU31*1.2)*0.3))*AV31*I31),2)*BS31),2))*AT31)/100),2)+ROUND(((ROUND((ROUND(((AE31-(((EU31*1.2)*0.3)))*AV31*I31),2)*BS31),2)*AT31)/100),2)) -> 1806.47 | Y31: =(ROUND((((S31+ROUND((ROUND(((((EU31*1.2)*0.3))*AV31*I31),2)*BS31),2))*AU31)/100),2)+ROUND(((ROUND((ROUND(((AE31-(((EU31*1.2)*0.3)))*AV31*I31),2)*BS31),2)*AU31)/100),2)) -> 923.31 | AA31: 55944370 | AB31: =ROUND((AC31+AD31+AF31),6) -> 2.43 | AC31: =ROUND((((ES31*1)*0)),6) -> 0 | AD31: =ROUND((((((ET31*1.2)*0.3))-(((EU31*1.2)*0.3)))+AE31),6) -> 0 | AE31: =ROUND((((EU31*1.2)*0.3)),6) -> 0 | AF31: =ROUND((((EV31*1.2)*0.3)),6) -> 2.43 | AG31: =ROUND((AP31),6) -> 0 | AH31: =(((EW31*1.2)*0.3)) -> 0.1872 | AI31: =(((EX31*1.2)*0.3)) -> 0 | AJ31: =(AS31) -> 0 | AK31: 6.75 | AL31: 0 | AM31: 0 | AN31: 0 | AO31: 6.75 | AP31: 0 | AQ31: 0.52 | AR31: 0 | AS31: 0 | AT31: 90 | AU31: 46 | AV31: 1.047 | AW31: 1 | AZ31: 1 | BA31: 56.35 | BB31: 1 | BC31: 1 | BH31: 0 | BI31: 2 | BJ31: ТСН-2001.4 Доп. 67, Сб. 11, т. 3, поз. 1 | BM31: 72 | BN31: 0 | BO31: 4.11-3-1 | BP31: 1 | BQ31: 40 | BR31: 0 | BS31: 56.35 | BT31: 1 | BU31: 1 | BV31: 1 | BW31: 1 | BX31: 1 | BZ31: 90 | CA31: 46 | CE31: 1566 | CF31: 0 | CG31: 0 | CM31: 0 | CN31: Поправка: Гл.12.Прил.8.п.8. 3_12.00.01.11.001 Наименование: При наличии напряженных и стесненных условий производства работ (стесненность, сложность складирования и транспортной логистики и т.п.) для объектов, расположенных в пределах круговой магистральной системы улиц "Садовое кольцо" города Москвы Поправка: Гл.4.Прил.2.2.п.2.2.29_04.00.01.35.003 Наименование: При демонтаже оборудования, предназначенного в лом | CO31: 0 | CP31: =(P31+Q31+S31) -> 2007.19 | CQ31: =ROUND((ROUND((AC31*AW31*1),2)*BC31),2) -> 0 | CR31: =(ROUND((ROUND(((((ET31*1.2)*0.3))*AV31*1),2)*BB31),2)+ROUND((ROUND(((AE31-(((EU31*1.2)*0.3)))*AV31*1),2)*BS31),2)) -> 0 | CS31: =(ROUND((ROUND(((((EU31*1.2)*0.3))*AV31*1),2)*BS31),2)+ROUND((ROUND(((AE31-(((EU31*1.2)*0.3)))*AV31*1),2)*BS31),2)) -> 0 | CT31: =ROUND((ROUND((AF31*AV31*1),2)*BA31),2) -> 143.13 | CU31: =AG31 -> 0 | CV31: =(AH31*AV31) -> 0.1959984 | CW31: =AI31 -> 0 | CX31: =AJ31 -> 0 | CY31: =(ROUND((((S31+ROUND((ROUND(((((EU31*1.2)*0.3))*AV31*1),2)*BS31),2))*AT31)/100),2)+ROUND(((ROUND((ROUND(((AE31-(((EU31*1.2)*0.3)))*AV31*1),2)*BS31),2)*AT31)/100),2)) -> 1806.47 | CZ31: =(ROUND((((S31+ROUND((ROUND(((((EU31*1.2)*0.3))*AV31*1),2)*BS31),2))*AU31)/100),2)+ROUND(((ROUND((ROUND(((AE31-(((EU31*1.2)*0.3)))*AV31*1),2)*BS31),2)*AU31)/100),2)) -> 923.31 | DB31: 7 | DD31: *1)*0 | DE31: *1,2)*0,3 | DF31: *1,2)*0,3 | DG31: *1,2)*0,3 | DI31: *1,2)*0,3 | DJ31: *1,2)*0,3 | DN31: 0 | DO31: 0 | DP31: 1 | DQ31: 1 | DU31: 1013 | DV31: 1 ШТ. | DW31: 1 ШТ. | DX31: 1 | EE31: 55393976 | EF31: 40 | EG31: Монтаж оборудования | EH31: 0 | EJ31: 2 | EK31: 72 | EL31: ТСН-2001.4-11. Приборы и средства автоматизации и вычислительной техники | EM31: ТСН-2001.4-11-1 | EO31: Поправка: Гл.12.Прил.8.п.8. 3_12.00.01.11.001 Поправка: Гл.4.Прил.2.2.п.2.2.29_04.00.01.35.003 | EQ31: 0 | ER31: 6.75 | ES31: 0 | ET31: 0 | EU31: 0 | EV31: 6.75 | EW31: 0.52 | EX31: 0 | EY31: 0 | FQ31: 0 | FR31: 0 | FS31: 0 | FX31: 90 | FY31: 46 | GD31: 1 | GF31: -615345603 | GG31: 2 | GH31: 1 | GI31: 2 | GJ31: 0 | GK31: 0 | GL31: =ROUND(IF(AND(BH31=3,BI31=3,FS31<>0),P31,0),2) -> 0 | GM31: =ROUND(O31+X31+Y31,2)+GX31 -> 4736.97 | GN31: =IF(OR(BI31=0,BI31=1),GM31-GX31,0) -> 0 | GO31: =IF(BI31=2,GM31-GX31,0) -> 4736.97 | GP31: =IF(BI31=4,GM31-GX31,0) -> 0 | GR31: 0 | GS31: 3 | GT31: 0 | GV31: =ROUND((GT31),6) -> 0 | GW31: 1 | GX31: =ROUND(HC31*I31,2) -> 0 | HA31: 0 | HB31: 0 | HC31: =GV31*GW31 -> 0 | HS31: 0 | IK31: 0
A32: 17 | B32: 1 | C32: =ROW(SmtRes!A5) -> 5 | D32: =ROW(EtalonRes!A15) -> 15 | E32: 3 | F32: 4.11-3-1 | G32: Установка прибора массой до 5 кг на металлоконструкциях или щитах / демонтаж электроприводов | H32: 1 ШТ. | I32: =ROUND(24+10+31,9) -> 65 | J32: 0 | K32: =ROUND(24+10+31,9) -> 65 | O32: =ROUND(CP32,2) -> 165.37 | P32: =ROUND((ROUND((AC32*AW32*I32),2)*BC32),2) -> 0 | Q32: =(ROUND((ROUND(((((ET32*1.2)*0.3))*AV32*I32),2)*BB32),2)+ROUND((ROUND(((AE32-(((EU32*1.2)*0.3)))*AV32*I32),2)*BS32),2)) -> 0 | R32: =(ROUND((ROUND(((((EU32*1.2)*0.3))*AV32*I32),2)*BS32),2)+ROUND((ROUND(((AE32-(((EU32*1.2)*0.3)))*AV32*I32),2)*BS32),2)) -> 0 | S32: =ROUND((ROUND((AF32*AV32*I32),2)*BA32),2) -> 165.37 | T32: =ROUND(CU32*I32,2) -> 0 | U32: =CV32*I32 -> 12.739896 | V32: =CW32*I32 -> 0 | W32: =ROUND(CX32*I32,2) -> 0 | X32: =(ROUND((((S32+ROUND((ROUND(((((EU32*1.2)*0.3))*AV32*I32),2)*BS32),2))*AT32)/100),2)+ROUND(((ROUND((ROUND(((AE32-(((EU32*1.2)*0.3)))*AV32*I32),2)*BS32),2)*AT32)/100),2)) -> 148.83 | Y32: =(ROUND((((S32+ROUND((ROUND(((((EU32*1.2)*0.3))*AV32*I32),2)*BS32),2))*AU32)/100),2)+ROUND(((ROUND((ROUND(((AE32-(((EU32*1.2)*0.3)))*AV32*I32),2)*BS32),2)*AU32)/100),2)) -> 76.07 | AA32: 55944368 | AB32: =ROUND((AC32+AD32+AF32),6) -> 2.43 | AC32: =ROUND((((ES32*1)*0)),6) -> 0 | AD32: =ROUND((((((ET32*1.2)*0.3))-(((EU32*1.2)*0.3)))+AE32),6) -> 0 | AE32: =ROUND((((EU32*1.2)*0.3)),6) -> 0 | AF32: =ROUND((((EV32*1.2)*0.3)),6) -> 2.43 | AG32: =ROUND((AP32),6) -> 0 | AH32: =(((EW32*1.2)*0.3)) -> 0.1872 | AI32: =(((EX32*1.2)*0.3)) -> 0 | AJ32: =(AS32) -> 0 | AK32: 6.75 | AL32: 0 | AM32: 0 | AN32: 0 | AO32: 6.75 | AP32: 0 | AQ32: 0.52 | AR32: 0 | AS32: 0 | AT32: 90 | AU32: 46 | AV32: 1.047 | AW32: 1 | AZ32: 1 | BA32: 1 | BB32: 1 | BC32: 1 | BH32: 0 | BI32: 2 | BJ32: ТСН-2001.4 Доп. 67, Сб. 11, т. 3, поз. 1 | BM32: 72 | BN32: 0 | BO32: 4.11-3-1 | BP32: 1 | BQ32: 40 | BR32: 0 | BS32: 1 | BT32: 1 | BU32: 1 | BV32: 1 | BW32: 1 | BX32: 1 | BZ32: 90 | CA32: 46 | CE32: 1566 | CF32: 0 | CG32: 0 | CM32: 0 | CN32: Поправка: Гл.12.Прил.8.п.8. 3_12.00.01.11.001 Наименование: При наличии напряженных и стесненных условий производства работ (стесненность, сложность складирования и транспортной логистики и т.п.) для объектов, расположенных в пределах круговой магистральной системы улиц "Садовое кольцо" города Москвы Поправка: Гл.4.Прил.2.2.п.2.2.29_04.00.01.35.003 Наименование: При демонтаже оборудования, предназначенного в лом | CO32: 0 | CP32: =(P32+Q32+S32) -> 165.37 | CQ32: =ROUND((ROUND((AC32*AW32*1),2)*BC32),2) -> 0 | CR32: =(ROUND((ROUND(((((ET32*1.2)*0.3))*AV32*1),2)*BB32),2)+ROUND((ROUND(((AE32-(((EU32*1.2)*0.3)))*AV32*1),2)*BS32),2)) -> 0 | CS32: =(ROUND((ROUND(((((EU32*1.2)*0.3))*AV32*1),2)*BS32),2)+ROUND((ROUND(((AE32-(((EU32*1.2)*0.3)))*AV32*1),2)*BS32),2)) -> 0 | CT32: =ROUND((ROUND((AF32*AV32*1),2)*BA32),2) -> 2.54 | CU32: =AG32 -> 0 | CV32: =(AH32*AV32) -> 0.1959984 | CW32: =AI32 -> 0 | CX32: =AJ32 -> 0 | CY32: =(ROUND((((S32+ROUND((ROUND(((((EU32*1.2)*0.3))*AV32*1),2)*BS32),2))*AT32)/100),2)+ROUND(((ROUND((ROUND(((AE32-(((EU32*1.2)*0.3)))*AV32*1),2)*BS32),2)*AT32)/100),2)) -> 148.83 | CZ32: =(ROUND((((S32+ROUND((ROUND(((((EU32*1.2)*0.3))*AV32*1),2)*BS32),2))*AU32)/100),2)+ROUND(((ROUND((ROUND(((AE32-(((EU32*1.2)*0.3)))*AV32*1),2)*BS32),2)*AU32)/100),2)) -> 76.07 | DB32: 9 | DD32: *1)*0 | DE32: *1,2)*0,3 | DF32: *1,2)*0,3 | DG32: *1,2)*0,3 | DI32: *1,2)*0,3 | DJ32: *1,2)*0,3 | DN32: 0 | DO32: 0 | DP32: 1 | DQ32: 1 | DU32: 1013 | DV32: 1 ШТ. | DW32: 1 ШТ. | DX32: 1 | EE32: 55393976 | EF32: 40 | EG32: Монтаж оборудования | EH32: 0 | EJ32: 2 | EK32: 72 | EL32: ТСН-2001.4-11. Приборы и средства автоматизации и вычислительной техники | EM32: ТСН-2001.4-11-1 | EO32: Поправка: Гл.12.Прил.8.п.8. 3_12.00.01.11.001 Поправка: Гл.4.Прил.2.2.п.2.2.29_04.00.01.35.003 | EQ32: 0 | ER32: 6.75 | ES32: 0 | ET32: 0 | EU32: 0 | EV32: 6.75 | EW32: 0.52 | EX32: 0 | EY32: 0 | FQ32: 0 | FR32: 0 | FS32: 0 | FX32: 90 | FY32: 46 | GD32: 1 | GF32: -490469543 | GG32: 2 | GH32: 1 | GI32: 2 | GJ32: 0 | GK32: 0 | GL32: =ROUND(IF(AND(BH32=3,BI32=3,FS32<>0),P32,0),2) -> 0 | GM32: =ROUND(O32+X32+Y32,2)+GX32 -> 390.27 | GN32: =IF(OR(BI32=0,BI32=1),GM32-GX32,0) -> 0 | GO32: =IF(BI32=2,GM32-GX32,0) -> 390.27 | GP32: =IF(BI32=4,GM32-GX32,0) -> 0 | GR32: 0 | GS32: 3 | GT32: 0 | GV32: =ROUND((GT32),6) -> 0 | GW32: 1 | GX32: =ROUND(HC32*I32,2) -> 0 | HA32: 0 | HB32: 0 | HC32: =GV32*GW32 -> 0 | HS32: 0 | IK32: 0
A33: 17 | B33: 1 | C33: =ROW(SmtRes!A6) -> 6 | D33: =ROW(EtalonRes!A18) -> 18 | E33: 3 | F33: 4.11-3-1 | G33: Установка прибора массой до 5 кг на металлоконструкциях или щитах / демонтаж электроприводов | H33: 1 ШТ. | I33: =ROUND(24+10+31,9) -> 65 | J33: 0 | K33: =ROUND(24+10+31,9) -> 65 | O33: =ROUND(CP33,2) -> 9318.6 | P33: =ROUND((ROUND((AC33*AW33*I33),2)*BC33),2) -> 0 | Q33: =(ROUND((ROUND(((((ET33*1.2)*0.3))*AV33*I33),2)*BB33),2)+ROUND((ROUND(((AE33-(((EU33*1.2)*0.3)))*AV33*I33),2)*BS33),2)) -> 0 | R33: =(ROUND((ROUND(((((EU33*1.2)*0.3))*AV33*I33),2)*BS33),2)+ROUND((ROUND(((AE33-(((EU33*1.2)*0.3)))*AV33*I33),2)*BS33),2)) -> 0 | S33: =ROUND((ROUND((AF33*AV33*I33),2)*BA33),2) -> 9318.6 | T33: =ROUND(CU33*I33,2) -> 0 | U33: =CV33*I33 -> 12.739896 | V33: =CW33*I33 -> 0 | W33: =ROUND(CX33*I33,2) -> 0 | X33: =(ROUND((((S33+ROUND((ROUND(((((EU33*1.2)*0.3))*AV33*I33),2)*BS33),2))*AT33)/100),2)+ROUND(((ROUND((ROUND(((AE33-(((EU33*1.2)*0.3)))*AV33*I33),2)*BS33),2)*AT33)/100),2)) -> 8386.74 | Y33: =(ROUND((((S33+ROUND((ROUND(((((EU33*1.2)*0.3))*AV33*I33),2)*BS33),2))*AU33)/100),2)+ROUND(((ROUND((ROUND(((AE33-(((EU33*1.2)*0.3)))*AV33*I33),2)*BS33),2)*AU33)/100),2)) -> 4286.56 | AA33: 55944370 | AB33: =ROUND((AC33+AD33+AF33),6) -> 2.43 | AC33: =ROUND((((ES33*1)*0)),6) -> 0 | AD33: =ROUND((((((ET33*1.2)*0.3))-(((EU33*1.2)*0.3)))+AE33),6) -> 0 | AE33: =ROUND((((EU33*1.2)*0.3)),6) -> 0 | AF33: =ROUND((((EV33*1.2)*0.3)),6) -> 2.43 | AG33: =ROUND((AP33),6) -> 0 | AH33: =(((EW33*1.2)*0.3)) -> 0.1872 | AI33: =(((EX33*1.2)*0.3)) -> 0 | AJ33: =(AS33) -> 0 | AK33: 6.75 | AL33: 0 | AM33: 0 | AN33: 0 | AO33: 6.75 | AP33: 0 | AQ33: 0.52 | AR33: 0 | AS33: 0 | AT33: 90 | AU33: 46 | AV33: 1.047 | AW33: 1 | AZ33: 1 | BA33: 56.35 | BB33: 1 | BC33: 1 | BH33: 0 | BI33: 2 | BJ33: ТСН-2001.4 Доп. 67, Сб. 11, т. 3, поз. 1 | BM33: 72 | BN33: 0 | BO33: 4.11-3-1 | BP33: 1 | BQ33: 40 | BR33: 0 | BS33: 56.35 | BT33: 1 | BU33: 1 | BV33: 1 | BW33: 1 | BX33: 1 | BZ33: 90 | CA33: 46 | CE33: 1566 | CF33: 0 | CG33: 0 | CM33: 0 | CN33: Поправка: Гл.12.Прил.8.п.8. 3_12.00.01.11.001 Наименование: При наличии напряженных и стесненных условий производства работ (стесненность, сложность складирования и транспортной логистики и т.п.) для объектов, расположенных в пределах круговой магистральной системы улиц "Садовое кольцо" города Москвы Поправка: Гл.4.Прил.2.2.п.2.2.29_04.00.01.35.003 Наименование: При демонтаже оборудования, предназначенного в лом | CO33: 0 | CP33: =(P33+Q33+S33) -> 9318.6 | CQ33: =ROUND((ROUND((AC33*AW33*1),2)*BC33),2) -> 0 | CR33: =(ROUND((ROUND(((((ET33*1.2)*0.3))*AV33*1),2)*BB33),2)+ROUND((ROUND(((AE33-(((EU33*1.2)*0.3)))*AV33*1),2)*BS33),2)) -> 0 | CS33: =(ROUND((ROUND(((((EU33*1.2)*0.3))*AV33*1),2)*BS33),2)+ROUND((ROUND(((AE33-(((EU33*1.2)*0.3)))*AV33*1),2)*BS33),2)) -> 0 | CT33: =ROUND((ROUND((AF33*AV33*1),2)*BA33),2) -> 143.13 | CU33: =AG33 -> 0 | CV33: =(AH33*AV33) -> 0.1959984 | CW33: =AI33 -> 0 | CX33: =AJ33 -> 0 | CY33: =(ROUND((((S33+ROUND((ROUND(((((EU33*1.2)*0.3))*AV33*1),2)*BS33),2))*AT33)/100),2)+ROUND(((ROUND((ROUND(((AE33-(((EU33*1.2)*0.3)))*AV33*1),2)*BS33),2)*AT33)/100),2)) -> 8386.74 | CZ33: =(ROUND((((S33+ROUND((ROUND(((((EU33*1.2)*0.3))*AV33*1),2)*BS33),2))*AU33)/100),2)+ROUND(((ROUND((ROUND(((AE33-(((EU33*1.2)*0.3)))*AV33*1),2)*BS33),2)*AU33)/100),2)) -> 4286.56 | DB33: 11 | DD33: *1)*0 | DE33: *1,2)*0,3 | DF33: *1,2)*0,3 | DG33: *1,2)*0,3 | DI33: *1,2)*0,3 | DJ33: *1,2)*0,3 | DN33: 0 | DO33: 0 | DP33: 1 | DQ33: 1 | DU33: 1013 | DV33: 1 ШТ. | DW33: 1 ШТ. | DX33: 1 | EE33: 55393976 | EF33: 40 | EG33: Монтаж оборудования | EH33: 0 | EJ33: 2 | EK33: 72 | EL33: ТСН-2001.4-11. Приборы и средства автоматизации и вычислительной техники | EM33: ТСН-2001.4-11-1 | EO33: Поправка: Гл.12.Прил.8.п.8. 3_12.00.01.11.001 Поправка: Гл.4.Прил.2.2.п.2.2.29_04.00.01.35.003 | EQ33: 0 | ER33: 6.75 | ES33: 0 | ET33: 0 | EU33: 0 | EV33: 6.75 | EW33: 0.52 | EX33: 0 | EY33: 0 | FQ33: 0 | FR33: 0 | FS33: 0 | FX33: 90 | FY33: 46 | GD33: 1 | GF33: -490469543 | GG33: 2 | GH33: 1 | GI33: 2 | GJ33: 0 | GK33: 0 | GL33: =ROUND(IF(AND(BH33=3,BI33=3,FS33<>0),P33,0),2) -> 0 | GM33: =ROUND(O33+X33+Y33,2)+GX33 -> 21991.9 | GN33: =IF(OR(BI33=0,BI33=1),GM33-GX33,0) -> 0 | GO33: =IF(BI33=2,GM33-GX33,0) -> 21991.9 | GP33: =IF(BI33=4,GM33-GX33,0) -> 0 | GR33: 0 | GS33: 3 | GT33: 0 | GV33: =ROUND((GT33),6) -> 0 | GW33: 1 | GX33: =ROUND(HC33*I33,2) -> 0 | HA33: 0 | HB33: 0 | HC33: =GV33*GW33 -> 0 | HS33: 0 | IK33: 0
A34: 17 | B34: 1 | C34: =ROW(SmtRes!A15) -> 15 | D34: =ROW(EtalonRes!A28) -> 28 | E34: 4 | F34: 4.11-4-1 | G34: Монтаж уровнемера поплавкового с мерной лентой (типа УДУ) для резервуаров наземных / демонтаж подвесного датчика уровня | H34: 1 комплект | I34: 3 | J34: 0 | K34: 3 | O34: =ROUND(CP34,2) -> 159.76 | P34: =ROUND((ROUND((AC34*AW34*I34),2)*BC34),2) -> 0 | Q34: =(ROUND((ROUND(((((ET34*1.2)*0.3))*AV34*I34),2)*BB34),2)+ROUND((ROUND(((AE34-(((EU34*1.2)*0.3)))*AV34*I34),2)*BS34),2)) -> 12.77 | R34: =(ROUND((ROUND(((((EU34*1.2)*0.3))*AV34*I34),2)*BS34),2)+ROUND((ROUND(((AE34-(((EU34*1.2)*0.3)))*AV34*I34),2)*BS34),2)) -> 1 | S34: =ROUND((ROUND((AF34*AV34*I34),2)*BA34),2) -> 146.99 | T34: =ROUND(CU34*I34,2) -> 0 | U34: =CV34*I34 -> 11.646828 | V34: =CW34*I34 -> 0 | W34: =ROUND(CX34*I34,2) -> 0 | X34: =(ROUND((((S34+ROUND((ROUND(((((EU34*1.2)*0.3))*AV34*I34),2)*BS34),2))*AT34)/100),2)+ROUND(((ROUND((ROUND(((AE34-(((EU34*1.2)*0.3)))*AV34*I34),2)*BS34),2)*AT34)/100),2)) -> 133.19 | Y34: =(ROUND((((S34+ROUND((ROUND(((((EU34*1.2)*0.3))*AV34*I34),2)*BS34),2))*AU34)/100),2)+ROUND(((ROUND((ROUND(((AE34-(((EU34*1.2)*0.3)))*AV34*I34),2)*BS34),2)*AU34)/100),2)) -> 68.08 | AA34: 55944368 | AB34: =ROUND((AC34+AD34+AF34),6) -> 50.8608 | AC34: =ROUND((((ES34*1)*0)),6) -> 0 | AD34: =ROUND((((((ET34*1.2)*0.3))-(((EU34*1.2)*0.3)))+AE34),6) -> 4.0644 | AE34: =ROUND((((EU34*1.2)*0.3)),6) -> 0.3168 | AF34: =ROUND((((EV34*1.2)*0.3)),6) -> 46.7964 | AG34: =ROUND((AP34),6) -> 0 | AH34: =(((EW34*1.2)*0.3)) -> 3.708 | AI34: =(((EX34*1.2)*0.3)) -> 0 | AJ34: =(AS34) -> 0 | AK34: 368.94 | AL34: 227.66 | AM34: 11.29 | AN34: 0.88 | AO34: 129.99 | AP34: 0 | AQ34: 10.3 | AR34: 0 | AS34: 0 | AT34: 90 | AU34: 46 | AV34: 1.047 | AW34: 1 | AZ34: 1 | BA34: 1 | BB34: 1 | BC34: 1 | BH34: 0 | BI34: 2 | BJ34: ТСН-2001.4 Доп. 80, Сб. 11, т. 4, поз. 1 | BM34: 72 | BN34: 0 | BO34: 4.11-4-1 | BP34: 1 | BQ34: 40 | BR34: 0 | BS34: 1 | BT34: 1 | BU34: 1 | BV34: 1 | BW34: 1 | BX34: 1 | BZ34: 90 | CA34: 46 | CE34: 1566 | CF34: 0 | CG34: 0 | CM34: 0 | CN34: Поправка: Гл.12.Прил.8.п.8. 3_12.00.01.11.001 Наименование: При наличии напряженных и стесненных условий производства работ (стесненность, сложность складирования и транспортной логистики и т.п.) для объектов, расположенных в пределах круговой магистральной системы улиц "Садовое кольцо" города Москвы Поправка: Гл.4.Прил.2.2.п.2.2.29_04.00.01.35.003 Наименование: При демонтаже оборудования, предназначенного в лом | CO34: 0 | CP34: =(P34+Q34+S34) -> 159.76 | CQ34: =ROUND((ROUND((AC34*AW34*1),2)*BC34),2) -> 0 | CR34: =(ROUND((ROUND(((((ET34*1.2)*0.3))*AV34*1),2)*BB34),2)+ROUND((ROUND(((AE34-(((EU34*1.2)*0.3)))*AV34*1),2)*BS34),2)) -> 4.26 | CS34: =(ROUND((ROUND(((((EU34*1.2)*0.3))*AV34*1),2)*BS34),2)+ROUND((ROUND(((AE34-(((EU34*1.2)*0.3)))*AV34*1),2)*BS34),2)) -> 0.33 | CT34: =ROUND((ROUND((AF34*AV34*1),2)*BA34),2) -> 49 | CU34: =AG34 -> 0 | CV34: =(AH34*AV34) -> 3.882276 | CW34: =AI34 -> 0 | CX34: =AJ34 -> 0 | CY34: =(ROUND((((S34+ROUND((ROUND(((((EU34*1.2)*0.3))*AV34*1),2)*BS34),2))*AT34)/100),2)+ROUND(((ROUND((ROUND(((AE34-(((EU34*1.2)*0.3)))*AV34*1),2)*BS34),2)*AT34)/100),2)) -> 132.59 | CZ34: =(ROUND((((S34+ROUND((ROUND(((((EU34*1.2)*0.3))*AV34*1),2)*BS34),2))*AU34)/100),2)+ROUND(((ROUND((ROUND(((AE34-(((EU34*1.2)*0.3)))*AV34*1),2)*BS34),2)*AU34)/100),2)) -> 67.77 | DB34: 13 | DD34: *1)*0 | DE34: *1,2)*0,3 | DF34: *1,2)*0,3 | DG34: *1,2)*0,3 | DI34: *1,2)*0,3 | DJ34: *1,2)*0,3 | DN34: 0 | DO34: 0 | DP34: 1 | DQ34: 1 | DU34: 1013 | DV34: 1 комплект | DW34: 1 комплект | DX34: 1 | EE34: 55393976 | EF34: 40 | EG34: Монтаж оборудования | EH34: 0 | EJ34: 2 | EK34: 72 | EL34: ТСН-2001.4-11. Приборы и средства автоматизации и вычислительной техники | EM34: ТСН-2001.4-11-1 | EO34: Поправка: Гл.12.Прил.8.п.8. 3_12.00.01.11.001 Поправка: Гл.4.Прил.2.2.п.2.2.29_04.00.01.35.003 | EQ34: 0 | ER34: 368.94 | ES34: 227.66 | ET34: 11.29 | EU34: 0.88 | EV34: 129.99 | EW34: 10.3 | EX34: 0 | EY34: 0 | FQ34: 0 | FR34: 0 | FS34: 0 | FX34: 90 | FY34: 46 | GD34: 1 | GF34: -130358486 | GG34: 2 | GH34: 1 | GI34: 2 | GJ34: 0 | GK34: 0 | GL34: =ROUND(IF(AND(BH34=3,BI34=3,FS34<>0),P34,0),2) -> 0 | GM34: =ROUND(O34+X34+Y34,2)+GX34 -> 361.03 | GN34: =IF(OR(BI34=0,BI34=1),GM34-GX34,0) -> 0 | GO34: =IF(BI34=2,GM34-GX34,0) -> 361.03 | GP34: =IF(BI34=4,GM34-GX34,0) -> 0 | GR34: 0 | GS34: 3 | GT34: 0 | GV34: =ROUND((GT34),6) -> 0 | GW34: 1 | GX34: =ROUND(HC34*I34,2) -> 0 | HA34: 0 | HB34: 0 | HC34: =GV34*GW34 -> 0 | HS34: 0 | IK34: 0
A35: 17 | B35: 1 | C35: =ROW(SmtRes!A24) -> 24 | D35: =ROW(EtalonRes!A38) -> 38 | E35: 4 | F35: 4.11-4-1 | G35: Монтаж уровнемера поплавкового с мерной лентой (типа УДУ) для резервуаров наземных / демонтаж подвесного датчика уровня | H35: 1 комплект | I35: 3 | J35: 0 | K35: 3 | O35: =ROUND(CP35,2) -> 8478.53 | P35: =ROUND((ROUND((AC35*AW35*I35),2)*BC35),2) -> 0 | Q35: =(ROUND((ROUND(((((ET35*1.2)*0.3))*AV35*I35),2)*BB35),2)+ROUND((ROUND(((AE35-(((EU35*1.2)*0.3)))*AV35*I35),2)*BS35),2)) -> 195.64 | R35: =(ROUND((ROUND(((((EU35*1.2)*0.3))*AV35*I35),2)*BS35),2)+ROUND((ROUND(((AE35-(((EU35*1.2)*0.3)))*AV35*I35),2)*BS35),2)) -> 56.35 | S35: =ROUND((ROUND((AF35*AV35*I35),2)*BA35),2) -> 8282.89 | T35: =ROUND(CU35*I35,2) -> 0 | U35: =CV35*I35 -> 11.646828 | V35: =CW35*I35 -> 0 | W35: =ROUND(CX35*I35,2) -> 0 | X35: =(ROUND((((S35+ROUND((ROUND(((((EU35*1.2)*0.3))*AV35*I35),2)*BS35),2))*AT35)/100),2)+ROUND(((ROUND((ROUND(((AE35-(((EU35*1.2)*0.3)))*AV35*I35),2)*BS35),2)*AT35)/100),2)) -> 7505.32 | Y35: =(ROUND((((S35+ROUND((ROUND(((((EU35*1.2)*0.3))*AV35*I35),2)*BS35),2))*AU35)/100),2)+ROUND(((ROUND((ROUND(((AE35-(((EU35*1.2)*0.3)))*AV35*I35),2)*BS35),2)*AU35)/100),2)) -> 3836.05 | AA35: 55944370 | AB35: =ROUND((AC35+AD35+AF35),6) -> 50.8608 | AC35: =ROUND((((ES35*1)*0)),6) -> 0 | AD35: =ROUND((((((ET35*1.2)*0.3))-(((EU35*1.2)*0.3)))+AE35),6) -> 4.0644 | AE35: =ROUND((((EU35*1.2)*0.3)),6) -> 0.3168 | AF35: =ROUND((((EV35*1.2)*0.3)),6) -> 46.7964 | AG35: =ROUND((AP35),6) -> 0 | AH35: =(((EW35*1.2)*0.3)) -> 3.708 | AI35: =(((EX35*1.2)*0.3)) -> 0 | AJ35: =(AS35) -> 0 | AK35: 368.94 | AL35: 227.66 | AM35: 11.29 | AN35: 0.88 | AO35: 129.99 | AP35: 0 | AQ35: 10.3 | AR35: 0 | AS35: 0 | AT35: 90 | AU35: 46 | AV35: 1.047 | AW35: 1 | AZ35: 1 | BA35: 56.35 | BB35: 15.32 | BC35: 7.63 | BH35: 0 | BI35: 2 | BJ35: ТСН-2001.4 Доп. 80, Сб. 11, т. 4, поз. 1 | BM35: 72 | BN35: 0 | BO35: 4.11-4-1 | BP35: 1 | BQ35: 40 | BR35: 0 | BS35: 56.35 | BT35: 1 | BU35: 1 | BV35: 1 | BW35: 1 | BX35: 1 | BZ35: 90 | CA35: 46 | CE35: 1566 | CF35: 0 | CG35: 0 | CM35: 0 | CN35: Поправка: Гл.12.Прил.8.п.8. 3_12.00.01.11.001 Наименование: При наличии напряженных и стесненных условий производства работ (стесненность, сложность складирования и транспортной логистики и т.п.) для объектов, расположенных в пределах круговой магистральной системы улиц "Садовое кольцо" города Москвы Поправка: Гл.4.Прил.2.2.п.2.2.29_04.00.01.35.003 Наименование: При демонтаже оборудования, предназначенного в лом | CO35: 0 | CP35: =(P35+Q35+S35) -> 8478.53 | CQ35: =ROUND((ROUND((AC35*AW35*1),2)*BC35),2) -> 0 | CR35: =(ROUND((ROUND(((((ET35*1.2)*0.3))*AV35*1),2)*BB35),2)+ROUND((ROUND(((AE35-(((EU35*1.2)*0.3)))*AV35*1),2)*BS35),2)) -> 65.26 | CS35: =(ROUND((ROUND(((((EU35*1.2)*0.3))*AV35*1),2)*BS35),2)+ROUND((ROUND(((AE35-(((EU35*1.2)*0.3)))*AV35*1),2)*BS35),2)) -> 18.6 | CT35: =ROUND((ROUND((AF35*AV35*1),2)*BA35),2) -> 2761.15 | CU35: =AG35 -> 0 | CV35: =(AH35*AV35) -> 3.882276 | CW35: =AI35 -> 0 | CX35: =AJ35 -> 0 | CY35: =(ROUND((((S35+ROUND((ROUND(((((EU35*1.2)*0.3))*AV35*1),2)*BS35),2))*AT35)/100),2)+ROUND(((ROUND((ROUND(((AE35-(((EU35*1.2)*0.3)))*AV35*1),2)*BS35),2)*AT35)/100),2)) -> 7471.34 | CZ35: =(ROUND((((S35+ROUND((ROUND(((((EU35*1.2)*0.3))*AV35*1),2)*BS35),2))*AU35)/100),2)+ROUND(((ROUND((ROUND(((AE35-(((EU35*1.2)*0.3)))*AV35*1),2)*BS35),2)*AU35)/100),2)) -> 3818.69 | DB35: 15 | DD35: *1)*0 | DE35: *1,2)*0,3 | DF35: *1,2)*0,3 | DG35: *1,2)*0,3 | DI35: *1,2)*0,3 | DJ35: *1,2)*0,3 | DN35: 0 | DO35: 0 | DP35: 1 | DQ35: 1 | DU35: 1013 | DV35: 1 комплект | DW35: 1 комплект | DX35: 1 | EE35: 55393976 | EF35: 40 | EG35: Монтаж оборудования | EH35: 0 | EJ35: 2 | EK35: 72 | EL35: ТСН-2001.4-11. Приборы и средства автоматизации и вычислительной техники | EM35: ТСН-2001.4-11-1 | EO35: Поправка: Гл.12.Прил.8.п.8. 3_12.00.01.11.001 Поправка: Гл.4.Прил.2.2.п.2.2.29_04.00.01.35.003 | EQ35: 0 | ER35: 368.94 | ES35: 227.66 | ET35: 11.29 | EU35: 0.88 | EV35: 129.99 | EW35: 10.3 | EX35: 0 | EY35: 0 | FQ35: 0 | FR35: 0 | FS35: 0 | FX35: 90 | FY35: 46 | GD35: 1 | GF35: -130358486 | GG35: 2 | GH35: 1 | GI35: 2 | GJ35: 0 | GK35: 0 | GL35: =ROUND(IF(AND(BH35=3,BI35=3,FS35<>0),P35,0),2) -> 0 | GM35: =ROUND(O35+X35+Y35,2)+GX35 -> 19819.9 | GN35: =IF(OR(BI35=0,BI35=1),GM35-GX35,0) -> 0 | GO35: =IF(BI35=2,GM35-GX35,0) -> 19819.9 | GP35: =IF(BI35=4,GM35-GX35,0) -> 0 | GR35: 0 | GS35: 3 | GT35: 0 | GV35: =ROUND((GT35),6) -> 0 | GW35: 1 | GX35: =ROUND(HC35*I35,2) -> 0 | HA35: 0 | HB35: 0 | HC35: =GV35*GW35 -> 0 | HS35: 0 | IK35: 0
A36: 17 | B36: 1 | C36: =ROW(SmtRes!A39) -> 39 | D36: =ROW(EtalonRes!A57) -> 57 | E36: 5 | F36: 4.8-222-4 | G36: Монтаж пускателя магнитного общего назначения отдельностоящего, устанавливаемого на конструкции на стене или колонне, на ток до 40 А / демонтаж магнитного дверного контакта с реле задержки | H36: 1 ШТ. | I36: 4 | J36: 0 | K36: 4 | O36: =ROUND(CP36,2) -> 52.53 | P36: =ROUND((ROUND((AC36*AW36*I36),2)*BC36),2) -> 0 | Q36: =(ROUND((ROUND(((((ET36*1.2)*0.3))*AV36*I36),2)*BB36),2)+ROUND((ROUND(((AE36-(((EU36*1.2)*0.3)))*AV36*I36),2)*BS36),2)) -> 2.44 | R36: =(ROUND((ROUND(((((EU36*1.2)*0.3))*AV36*I36),2)*BS36),2)+ROUND((ROUND(((AE36-(((EU36*1.2)*0.3)))*AV36*I36),2)*BS36),2)) -> 0.2 | S36: =ROUND((ROUND((AF36*AV36*I36),2)*BA36),2) -> 50.09 | T36: =ROUND(CU36*I36,2) -> 0 | U36: =CV36*I36 -> 4.1159664 | V36: =CW36*I36 -> 0 | W36: =ROUND(CX36*I36,2) -> 0 | X36: =(ROUND((((S36+ROUND((ROUND(((((EU36*1.2)*0.3))*AV36*I36),2)*BS36),2))*AT36)/100),2)+ROUND(((ROUND((ROUND(((AE36-(((EU36*1.2)*0.3)))*AV36*I36),2)*BS36),2)*AT36)/100),2)) -> 48.78 | Y36: =(ROUND((((S36+ROUND((ROUND(((((EU36*1.2)*0.3))*AV36*I36),2)*BS36),2))*AU36)/100),2)+ROUND(((ROUND((ROUND(((AE36-(((EU36*1.2)*0.3)))*AV36*I36),2)*BS36),2)*AU36)/100),2)) -> 25.65 | AA36: 55944368 | AB36: =ROUND((AC36+AD36+AF36),6) -> 12.5424 | AC36: =ROUND((((ES36*1)*0)),6) -> 0 | AD36: =ROUND((((((ET36*1.2)*0.3))-(((EU36*1.2)*0.3)))+AE36),6) -> 0.5832 | AE36: =ROUND((((EU36*1.2)*0.3)),6) -> 0.0468 | AF36: =ROUND((((EV36*1.2)*0.3)),6) -> 11.9592 | AG36: =ROUND((AP36),6) -> 0 | AH36: =(((EW36*1.2)*0.3)) -> 0.9828 | AI36: =(((EX36*1.2)*0.3)) -> 0 | AJ36: =(AS36) -> 0 | AK36: 62.5 | AL36: 27.66 | AM36: 1.62 | AN36: 0.13 | AO36: 33.22 | AP36: 0 | AQ36: 2.73 | AR36: 0 | AS36: 0 | AT36: 97 | AU36: 51 | AV36: 1.047 | AW36: 1 | AZ36: 1 | BA36: 1 | BB36: 1 | BC36: 1 | BH36: 0 | BI36: 2 | BJ36: ТСН-2001.4 Доп. 80, Сб. 8, т. 222, поз. 4 | BM36: 67 | BN36: 0 | BO36: 4.8-222-4 | BP36: 1 | BQ36: 40 | BR36: 0 | BS36: 1 | BT36: 1 | BU36: 1 | BV36: 1 | BW36: 1 | BX36: 1 | BZ36: 97 | CA36: 51 | CE36: 1566 | CF36: 0 | CG36: 0 | CM36: 0 | CN36: Поправка: Гл.12.Прил.8.п.8. 3_12.00.01.11.001 Наименование: При наличии напряженных и стесненных условий производства работ (стесненность, сложность складирования и транспортной логистики и т.п.) для объектов, расположенных в пределах круговой магистральной системы улиц "Садовое кольцо" города Москвы Поправка: Гл.4.Прил.2.2.п.2.2.29_04.00.01.35.003 Наименование: При демонтаже оборудования, предназначенного в лом | CO36: 0 | CP36: =(P36+Q36+S36) -> 52.53 | CQ36: =ROUND((ROUND((AC36*AW36*1),2)*BC36),2) -> 0 | CR36: =(ROUND((ROUND(((((ET36*1.2)*0.3))*AV36*1),2)*BB36),2)+ROUND((ROUND(((AE36-(((EU36*1.2)*0.3)))*AV36*1),2)*BS36),2)) -> 0.61 | CS36: =(ROUND((ROUND(((((EU36*1.2)*0.3))*AV36*1),2)*BS36),2)+ROUND((ROUND(((AE36-(((EU36*1.2)*0.3)))*AV36*1),2)*BS36),2)) -> 0.05 | CT36: =ROUND((ROUND((AF36*AV36*1),2)*BA36),2) -> 12.52 | CU36: =AG36 -> 0 | CV36: =(AH36*AV36) -> 1.0289916 | CW36: =AI36 -> 0 | CX36: =AJ36 -> 0 | CY36: =(ROUND((((S36+ROUND((ROUND(((((EU36*1.2)*0.3))*AV36*1),2)*BS36),2))*AT36)/100),2)+ROUND(((ROUND((ROUND(((AE36-(((EU36*1.2)*0.3)))*AV36*1),2)*BS36),2)*AT36)/100),2)) -> 48.64 | CZ36: =(ROUND((((S36+ROUND((ROUND(((((EU36*1.2)*0.3))*AV36*1),2)*BS36),2))*AU36)/100),2)+ROUND(((ROUND((ROUND(((AE36-(((EU36*1.2)*0.3)))*AV36*1),2)*BS36),2)*AU36)/100),2)) -> 25.57 | DB36: 17 | DD36: *1)*0 | DE36: *1,2)*0,3 | DF36: *1,2)*0,3 | DG36: *1,2)*0,3 | DI36: *1,2)*0,3 | DJ36: *1,2)*0,3 | DN36: 0 | DO36: 0 | DP36: 1 | DQ36: 1 | DU36: 1013 | DV36: 1 ШТ. | DW36: 1 ШТ. | DX36: 1 | EE36: 55393971 | EF36: 40 | EG36: Монтаж оборудования | EH36: 0 | EJ36: 2 | EK36: 67 | EL36: ТСН-2001.4-8. Электротехнические установки | EM36: ТСН-2001.4-8-1 | EO36: Поправка: Гл.12.Прил.8.п.8. 3_12.00.01.11.001 Поправка: Гл.4.Прил.2.2.п.2.2.29_04.00.01.35.003 | EQ36: 0 | ER36: 62.5 | ES36: 27.66 | ET36: 1.62 | EU36: 0.13 | EV36: 33.22 | EW36: 2.73 | EX36: 0 | EY36: 0 | FQ36: 0 | FR36: 0 | FS36: 0 | FX36: 97 | FY36: 51 | GD36: 1 | GF36: 1911795638 | GG36: 2 | GH36: 1 | GI36: 2 | GJ36: 0 | GK36: 0 | GL36: =ROUND(IF(AND(BH36=3,BI36=3,FS36<>0),P36,0),2) -> 0 | GM36: =ROUND(O36+X36+Y36,2)+GX36 -> 126.96 | GN36: =IF(OR(BI36=0,BI36=1),GM36-GX36,0) -> 0 | GO36: =IF(BI36=2,GM36-GX36,0) -> 126.96 | GP36: =IF(BI36=4,GM36-GX36,0) -> 0 | GR36: 0 | GS36: 3 | GT36: 0 | GV36: =ROUND((GT36),6) -> 0 | GW36: 1 | GX36: =ROUND(HC36*I36,2) -> 0 | HA36: 0 | HB36: 0 | HC36: =GV36*GW36 -> 0 | HS36: 0 | IK36: 0
A37: 17 | B37: 1 | C37: =ROW(SmtRes!A54) -> 54 | D37: =ROW(EtalonRes!A76) -> 76 | E37: 5 | F37: 4.8-222-4 | G37: Монтаж пускателя магнитного общего назначения отдельностоящего, устанавливаемого на конструкции на стене или колонне, на ток до 40 А / демонтаж магнитного дверного контакта с реле задержки | H37: 1 ШТ. | I37: 4 | J37: 0 | K37: 4 | O37: =ROUND(CP37,2) -> 2859.93 | P37: =ROUND((ROUND((AC37*AW37*I37),2)*BC37),2) -> 0 | Q37: =(ROUND((ROUND(((((ET37*1.2)*0.3))*AV37*I37),2)*BB37),2)+ROUND((ROUND(((AE37-(((EU37*1.2)*0.3)))*AV37*I37),2)*BS37),2)) -> 37.36 | R37: =(ROUND((ROUND(((((EU37*1.2)*0.3))*AV37*I37),2)*BS37),2)+ROUND((ROUND(((AE37-(((EU37*1.2)*0.3)))*AV37*I37),2)*BS37),2)) -> 11.27 | S37: =ROUND((ROUND((AF37*AV37*I37),2)*BA37),2) -> 2822.57 | T37: =ROUND(CU37*I37,2) -> 0 | U37: =CV37*I37 -> 4.1159664 | V37: =CW37*I37 -> 0 | W37: =ROUND(CX37*I37,2) -> 0 | X37: =(ROUND((((S37+ROUND((ROUND(((((EU37*1.2)*0.3))*AV37*I37),2)*BS37),2))*AT37)/100),2)+ROUND(((ROUND((ROUND(((AE37-(((EU37*1.2)*0.3)))*AV37*I37),2)*BS37),2)*AT37)/100),2)) -> 2748.82 | Y37: =(ROUND((((S37+ROUND((ROUND(((((EU37*1.2)*0.3))*AV37*I37),2)*BS37),2))*AU37)/100),2)+ROUND(((ROUND((ROUND(((AE37-(((EU37*1.2)*0.3)))*AV37*I37),2)*BS37),2)*AU37)/100),2)) -> 1445.26 | AA37: 55944370 | AB37: =ROUND((AC37+AD37+AF37),6) -> 12.5424 | AC37: =ROUND((((ES37*1)*0)),6) -> 0 | AD37: =ROUND((((((ET37*1.2)*0.3))-(((EU37*1.2)*0.3)))+AE37),6) -> 0.5832 | AE37: =ROUND((((EU37*1.2)*0.3)),6) -> 0.0468 | AF37: =ROUND((((EV37*1.2)*0.3)),6) -> 11.9592 | AG37: =ROUND((AP37),6) -> 0 | AH37: =(((EW37*1.2)*0.3)) -> 0.9828 | AI37: =(((EX37*1.2)*0.3)) -> 0 | AJ37: =(AS37) -> 0 | AK37: 62.5 | AL37: 27.66 | AM37: 1.62 | AN37: 0.13 | AO37: 33.22 | AP37: 0 | AQ37: 2.73 | AR37: 0 | AS37: 0 | AT37: 97 | AU37: 51 | AV37: 1.047 | AW37: 1 | AZ37: 1 | BA37: 56.35 | BB37: 15.31 | BC37: 5.98 | BH37: 0 | BI37: 2 | BJ37: ТСН-2001.4 Доп. 80, Сб. 8, т. 222, поз. 4 | BM37: 67 | BN37: 0 | BO37: 4.8-222-4 | BP37: 1 | BQ37: 40 | BR37: 0 | BS37: 56.35 | BT37: 1 | BU37: 1 | BV37: 1 | BW37: 1 | BX37: 1 | BZ37: 97 | CA37: 51 | CE37: 1566 | CF37: 0 | CG37: 0 | CM37: 0 | CN37: Поправка: Гл.12.Прил.8.п.8. 3_12.00.01.11.001 Наименование: При наличии напряженных и стесненных условий производства работ (стесненность, сложность складирования и транспортной логистики и т.п.) для объектов, расположенных в пределах круговой магистральной системы улиц "Садовое кольцо" города Москвы Поправка: Гл.4.Прил.2.2.п.2.2.29_04.00.01.35.003 Наименование: При демонтаже оборудования, предназначенного в лом | CO37: 0 | CP37: =(P37+Q37+S37) -> 2859.93 | CQ37: =ROUND((ROUND((AC37*AW37*1),2)*BC37),2) -> 0 | CR37: =(ROUND((ROUND(((((ET37*1.2)*0.3))*AV37*1),2)*BB37),2)+ROUND((ROUND(((AE37-(((EU37*1.2)*0.3)))*AV37*1),2)*BS37),2)) -> 9.34 | CS37: =(ROUND((ROUND(((((EU37*1.2)*0.3))*AV37*1),2)*BS37),2)+ROUND((ROUND(((AE37-(((EU37*1.2)*0.3)))*AV37*1),2)*BS37),2)) -> 2.82 | CT37: =ROUND((ROUND((AF37*AV37*1),2)*BA37),2) -> 705.5 | CU37: =AG37 -> 0 | CV37: =(AH37*AV37) -> 1.0289916 | CW37: =AI37 -> 0 | CX37: =AJ37 -> 0 | CY37: =(ROUND((((S37+ROUND((ROUND(((((EU37*1.2)*0.3))*AV37*1),2)*BS37),2))*AT37)/100),2)+ROUND(((ROUND((ROUND(((AE37-(((EU37*1.2)*0.3)))*AV37*1),2)*BS37),2)*AT37)/100),2)) -> 2740.63 | CZ37: =(ROUND((((S37+ROUND((ROUND(((((EU37*1.2)*0.3))*AV37*1),2)*BS37),2))*AU37)/100),2)+ROUND(((ROUND((ROUND(((AE37-(((EU37*1.2)*0.3)))*AV37*1),2)*BS37),2)*AU37)/100),2)) -> 1440.95 | DB37: 19 | DD37: *1)*0 | DE37: *1,2)*0,3 | DF37: *1,2)*0,3 | DG37: *1,2)*0,3 | DI37: *1,2)*0,3 | DJ37: *1,2)*0,3 | DN37: 0 | DO37: 0 | DP37: 1 | DQ37: 1 | DU37: 1013 | DV37: 1 ШТ. | DW37: 1 ШТ. | DX37: 1 | EE37: 55393971 | EF37: 40 | EG37: Монтаж оборудования | EH37: 0 | EJ37: 2 | EK37: 67 | EL37: ТСН-2001.4-8. Электротехнические установки | EM37: ТСН-2001.4-8-1 | EO37: Поправка: Гл.12.Прил.8.п.8. 3_12.00.01.11.001 Поправка: Гл.4.Прил.2.2.п.2.2.29_04.00.01.35.003 | EQ37: 0 | ER37: 62.5 | ES37: 27.66 | ET37: 1.62 | EU37: 0.13 | EV37: 33.22 | EW37: 2.73 | EX37: 0 | EY37: 0 | FQ37: 0 | FR37: 0 | FS37: 0 | FX37: 97 | FY37: 51 | GD37: 1 | GF37: 1911795638 | GG37: 2 | GH37: 1 | GI37: 2 | GJ37: 0 | GK37: 0 | GL37: =ROUND(IF(AND(BH37=3,BI37=3,FS37<>0),P37,0),2) -> 0 | GM37: =ROUND(O37+X37+Y37,2)+GX37 -> 7054.01 | GN37: =IF(OR(BI37=0,BI37=1),GM37-GX37,0) -> 0 | GO37: =IF(BI37=2,GM37-GX37,0) -> 7054.01 | GP37: =IF(BI37=4,GM37-GX37,0) -> 0 | GR37: 0 | GS37: 3 | GT37: 0 | GV37: =ROUND((GT37),6) -> 0 | GW37: 1 | GX37: =ROUND(HC37*I37,2) -> 0 | HA37: 0 | HB37: 0 | HC37: =GV37*GW37 -> 0 | HS37: 0 | IK37: 0
A38: 17 | B38: 1 | C38: =ROW(SmtRes!A67) -> 67 | D38: =ROW(EtalonRes!A92) -> 92 | E38: 6 | F38: 4.10-19-6 | G38: Монтаж отдельно устанавливаемого преобразователя или блока питания / демонтаж блока подключения | H38: 1 ШТ. | I38: 4 | J38: 0 | K38: 4 | O38: =ROUND(CP38,2) -> 273.12 | P38: =ROUND((ROUND((AC38*AW38*I38),2)*BC38),2) -> 0 | Q38: =(ROUND((ROUND(((((ET38*1.2)*0.3))*AV38*I38),2)*BB38),2)+ROUND((ROUND(((AE38-(((EU38*1.2)*0.3)))*AV38*I38),2)*BS38),2)) -> 69.25 | R38: =(ROUND((ROUND(((((EU38*1.2)*0.3))*AV38*I38),2)*BS38),2)+ROUND((ROUND(((AE38-(((EU38*1.2)*0.3)))*AV38*I38),2)*BS38),2)) -> 7.61 | S38: =ROUND((ROUND((AF38*AV38*I38),2)*BA38),2) -> 203.87 | T38: =ROUND(CU38*I38,2) -> 0 | U38: =CV38*I38 -> 14.021424 | V38: =CW38*I38 -> 0 | W38: =ROUND(CX38*I38,2) -> 0 | X38: =(ROUND((((S38+ROUND((ROUND(((((EU38*1.2)*0.3))*AV38*I38),2)*BS38),2))*AT38)/100),2)+ROUND(((ROUND((ROUND(((AE38-(((EU38*1.2)*0.3)))*AV38*I38),2)*BS38),2)*AT38)/100),2)) -> 190.33 | Y38: =(ROUND((((S38+ROUND((ROUND(((((EU38*1.2)*0.3))*AV38*I38),2)*BS38),2))*AU38)/100),2)+ROUND(((ROUND((ROUND(((AE38-(((EU38*1.2)*0.3)))*AV38*I38),2)*BS38),2)*AU38)/100),2)) -> 97.28 | AA38: 55944368 | AB38: =ROUND((AC38+AD38+AF38),6) -> 65.214 | AC38: =ROUND((((ES38*1)*0)),6) -> 0 | AD38: =ROUND((((((ET38*1.2)*0.3))-(((EU38*1.2)*0.3)))+AE38),6) -> 16.5348 | AE38: =ROUND((((EU38*1.2)*0.3)),6) -> 1.818 | AF38: =ROUND((((EV38*1.2)*0.3)),6) -> 48.6792 | AG38: =ROUND((AP38),6) -> 0 | AH38: =(((EW38*1.2)*0.3)) -> 3.348 | AI38: =(((EX38*1.2)*0.3)) -> 0 | AJ38: =(AS38) -> 0 | AK38: 236.95 | AL38: 55.8 | AM38: 45.93 | AN38: 5.05 | AO38: 135.22 | AP38: 0 | AQ38: 9.3 | AR38: 0 | AS38: 0 | AT38: 90 | AU38: 46 | AV38: 1.047 | AW38: 1 | AZ38: 1 | BA38: 1 | BB38: 1 | BC38: 1 | BH38: 0 | BI38: 2 | BJ38: ТСН-2001.4 Доп. 70, Сб. 10, т. 19, поз. 6 | BM38: 68 | BN38: 0 | BO38: 4.10-19-6 | BP38: 1 | BQ38: 40 | BR38: 0 | BS38: 1 | BT38: 1 | BU38: 1 | BV38: 1 | BW38: 1 | BX38: 1 | BZ38: 90 | CA38: 46 | CE38: 1566 | CF38: 0 | CG38: 0 | CM38: 0 | CN38: Поправка: Гл.12.Прил.8.п.8. 3_12.00.01.11.001 Наименование: При наличии напряженных и стесненных условий производства работ (стесненность, сложность складирования и транспортной логистики и т.п.) для объектов, расположенных в пределах круговой магистральной системы улиц "Садовое кольцо" города Москвы Поправка: Гл.4.Прил.2.2.п.2.2.29_04.00.01.35.003 Наименование: При демонтаже оборудования, предназначенного в лом | CO38: 0 | CP38: =(P38+Q38+S38) -> 273.12 | CQ38: =ROUND((ROUND((AC38*AW38*1),2)*BC38),2) -> 0 | CR38: =(ROUND((ROUND(((((ET38*1.2)*0.3))*AV38*1),2)*BB38),2)+ROUND((ROUND(((AE38-(((EU38*1.2)*0.3)))*AV38*1),2)*BS38),2)) -> 17.31 | CS38: =(ROUND((ROUND(((((EU38*1.2)*0.3))*AV38*1),2)*BS38),2)+ROUND((ROUND(((AE38-(((EU38*1.2)*0.3)))*AV38*1),2)*BS38),2)) -> 1.9 | CT38: =ROUND((ROUND((AF38*AV38*1),2)*BA38),2) -> 50.97 | CU38: =AG38 -> 0 | CV38: =(AH38*AV38) -> 3.505356 | CW38: =AI38 -> 0 | CX38: =AJ38 -> 0 | CY38: =(ROUND((((S38+ROUND((ROUND(((((EU38*1.2)*0.3))*AV38*1),2)*BS38),2))*AT38)/100),2)+ROUND(((ROUND((ROUND(((AE38-(((EU38*1.2)*0.3)))*AV38*1),2)*BS38),2)*AT38)/100),2)) -> 185.19 | CZ38: =(ROUND((((S38+ROUND((ROUND(((((EU38*1.2)*0.3))*AV38*1),2)*BS38),2))*AU38)/100),2)+ROUND(((ROUND((ROUND(((AE38-(((EU38*1.2)*0.3)))*AV38*1),2)*BS38),2)*AU38)/100),2)) -> 94.65 | DB38: 21 | DD38: *1)*0 | DE38: *1,2)*0,3 | DF38: *1,2)*0,3 | DG38: *1,2)*0,3 | DI38: *1,2)*0,3 | DJ38: *1,2)*0,3 | DN38: 0 | DO38: 0 | DP38: 1 | DQ38: 1 | DU38: 1013 | DV38: 1 ШТ. | DW38: 1 ШТ. | DX38: 1 | EE38: 55393972 | EF38: 40 | EG38: Монтаж оборудования | EH38: 0 | EJ38: 2 | EK38: 68 | EL38: ТСН-2001.4-10. Прокладка и монтаж сетей связи | EM38: ТСН-2001.4-10-1 | EO38: Поправка: Гл.12.Прил.8.п.8. 3_12.00.01.11.001 Поправка: Гл.4.Прил.2.2.п.2.2.29_04.00.01.35.003 | EQ38: 0 | ER38: 236.95 | ES38: 55.8 | ET38: 45.93 | EU38: 5.05 | EV38: 135.22 | EW38: 9.3 | EX38: 0 | EY38: 0 | FQ38: 0 | FR38: 0 | FS38: 0 | FX38: 90 | FY38: 46 | GD38: 1 | GF38: 1139241847 | GG38: 2 | GH38: 1 | GI38: 2 | GJ38: 0 | GK38: 0 | GL38: =ROUND(IF(AND(BH38=3,BI38=3,FS38<>0),P38,0),2) -> 0 | GM38: =ROUND(O38+X38+Y38,2)+GX38 -> 560.73 | GN38: =IF(OR(BI38=0,BI38=1),GM38-GX38,0) -> 0 | GO38: =IF(BI38=2,GM38-GX38,0) -> 560.73 | GP38: =IF(BI38=4,GM38-GX38,0) -> 0 | GR38: 0 | GS38: 3 | GT38: 0 | GV38: =ROUND((GT38),6) -> 0 | GW38: 1 | GX38: =ROUND(HC38*I38,2) -> 0 | HA38: 0 | HB38: 0 | HC38: =GV38*GW38 -> 0 | HS38: 0 | IK38: 0
A39: 17 | B39: 1 | C39: =ROW(SmtRes!A80) -> 80 | D39: =ROW(EtalonRes!A108) -> 108 | E39: 6 | F39: 4.10-19-6 | G39: Монтаж отдельно устанавливаемого преобразователя или блока питания / демонтаж блока подключения | H39: 1 ШТ. | I39: 4 | J39: 0 | K39: 4 | O39: =ROUND(CP39,2) -> 12607.15 | P39: =ROUND((ROUND((AC39*AW39*I39),2)*BC39),2) -> 0 | Q39: =(ROUND((ROUND(((((ET39*1.2)*0.3))*AV39*I39),2)*BB39),2)+ROUND((ROUND(((AE39-(((EU39*1.2)*0.3)))*AV39*I39),2)*BS39),2)) -> 1119.08 | R39: =(ROUND((ROUND(((((EU39*1.2)*0.3))*AV39*I39),2)*BS39),2)+ROUND((ROUND(((AE39-(((EU39*1.2)*0.3)))*AV39*I39),2)*BS39),2)) -> 428.82 | S39: =ROUND((ROUND((AF39*AV39*I39),2)*BA39),2) -> 11488.07 | T39: =ROUND(CU39*I39,2) -> 0 | U39: =CV39*I39 -> 14.021424 | V39: =CW39*I39 -> 0 | W39: =ROUND(CX39*I39,2) -> 0 | X39: =(ROUND((((S39+ROUND((ROUND(((((EU39*1.2)*0.3))*AV39*I39),2)*BS39),2))*AT39)/100),2)+ROUND(((ROUND((ROUND(((AE39-(((EU39*1.2)*0.3)))*AV39*I39),2)*BS39),2)*AT39)/100),2)) -> 10725.2 | Y39: =(ROUND((((S39+ROUND((ROUND(((((EU39*1.2)*0.3))*AV39*I39),2)*BS39),2))*AU39)/100),2)+ROUND(((ROUND((ROUND(((AE39-(((EU39*1.2)*0.3)))*AV39*I39),2)*BS39),2)*AU39)/100),2)) -> 5481.77 | AA39: 55944370 | AB39: =ROUND((AC39+AD39+AF39),6) -> 65.214 | AC39: =ROUND((((ES39*1)*0)),6) -> 0 | AD39: =ROUND((((((ET39*1.2)*0.3))-(((EU39*1.2)*0.3)))+AE39),6) -> 16.5348 | AE39: =ROUND((((EU39*1.2)*0.3)),6) -> 1.818 | AF39: =ROUND((((EV39*1.2)*0.3)),6) -> 48.6792 | AG39: =ROUND((AP39),6) -> 0 | AH39: =(((EW39*1.2)*0.3)) -> 3.348 | AI39: =(((EX39*1.2)*0.3)) -> 0 | AJ39: =(AS39) -> 0 | AK39: 236.95 | AL39: 55.8 | AM39: 45.93 | AN39: 5.05 | AO39: 135.22 | AP39: 0 | AQ39: 9.3 | AR39: 0 | AS39: 0 | AT39: 90 | AU39: 46 | AV39: 1.047 | AW39: 1 | AZ39: 1 | BA39: 56.35 | BB39: 16.16 | BC39: 10.51 | BH39: 0 | BI39: 2 | BJ39: ТСН-2001.4 Доп. 70, Сб. 10, т. 19, поз. 6 | BM39: 68 | BN39: 0 | BO39: 4.10-19-6 | BP39: 1 | BQ39: 40 | BR39: 0 | BS39: 56.35 | BT39: 1 | BU39: 1 | BV39: 1 | BW39: 1 | BX39: 1 | BZ39: 90 | CA39: 46 | CE39: 1566 | CF39: 0 | CG39: 0 | CM39: 0 | CN39: Поправка: Гл.12.Прил.8.п.8. 3_12.00.01.11.001 Наименование: При наличии напряженных и стесненных условий производства работ (стесненность, сложность складирования и транспортной логистики и т.п.) для объектов, расположенных в пределах круговой магистральной системы улиц "Садовое кольцо" города Москвы Поправка: Гл.4.Прил.2.2.п.2.2.29_04.00.01.35.003 Наименование: При демонтаже оборудования, предназначенного в лом | CO39: 0 | CP39: =(P39+Q39+S39) -> 12607.15 | CQ39: =ROUND((ROUND((AC39*AW39*1),2)*BC39),2) -> 0 | CR39: =(ROUND((ROUND(((((ET39*1.2)*0.3))*AV39*1),2)*BB39),2)+ROUND((ROUND(((AE39-(((EU39*1.2)*0.3)))*AV39*1),2)*BS39),2)) -> 279.73 | CS39: =(ROUND((ROUND(((((EU39*1.2)*0.3))*AV39*1),2)*BS39),2)+ROUND((ROUND(((AE39-(((EU39*1.2)*0.3)))*AV39*1),2)*BS39),2)) -> 107.07 | CT39: =ROUND((ROUND((AF39*AV39*1),2)*BA39),2) -> 2872.16 | CU39: =AG39 -> 0 | CV39: =(AH39*AV39) -> 3.505356 | CW39: =AI39 -> 0 | CX39: =AJ39 -> 0 | CY39: =(ROUND((((S39+ROUND((ROUND(((((EU39*1.2)*0.3))*AV39*1),2)*BS39),2))*AT39)/100),2)+ROUND(((ROUND((ROUND(((AE39-(((EU39*1.2)*0.3)))*AV39*1),2)*BS39),2)*AT39)/100),2)) -> 10435.63 | CZ39: =(ROUND((((S39+ROUND((ROUND(((((EU39*1.2)*0.3))*AV39*1),2)*BS39),2))*AU39)/100),2)+ROUND(((ROUND((ROUND(((AE39-(((EU39*1.2)*0.3)))*AV39*1),2)*BS39),2)*AU39)/100),2)) -> 5333.76 | DB39: 23 | DD39: *1)*0 | DE39: *1,2)*0,3 | DF39: *1,2)*0,3 | DG39: *1,2)*0,3 | DI39: *1,2)*0,3 | DJ39: *1,2)*0,3 | DN39: 0 | DO39: 0 | DP39: 1 | DQ39: 1 | DU39: 1013 | DV39: 1 ШТ. | DW39: 1 ШТ. | DX39: 1 | EE39: 55393972 | EF39: 40 | EG39: Монтаж оборудования | EH39: 0 | EJ39: 2 | EK39: 68 | EL39: ТСН-2001.4-10. Прокладка и монтаж сетей связи | EM39: ТСН-2001.4-10-1 | EO39: Поправка: Гл.12.Прил.8.п.8. 3_12.00.01.11.001 Поправка: Гл.4.Прил.2.2.п.2.2.29_04.00.01.35.003 | EQ39: 0 | ER39: 236.95 | ES39: 55.8 | ET39: 45.93 | EU39: 5.05 | EV39: 135.22 | EW39: 9.3 | EX39: 0 | EY39: 0 | FQ39: 0 | FR39: 0 | FS39: 0 | FX39: 90 | FY39: 46 | GD39: 1 | GF39: 1139241847 | GG39: 2 | GH39: 1 | GI39: 2 | GJ39: 0 | GK39: 0 | GL39: =ROUND(IF(AND(BH39=3,BI39=3,FS39<>0),P39,0),2) -> 0 | GM39: =ROUND(O39+X39+Y39,2)+GX39 -> 28814.12 | GN39: =IF(OR(BI39=0,BI39=1),GM39-GX39,0) -> 0 | GO39: =IF(BI39=2,GM39-GX39,0) -> 28814.12 | GP39: =IF(BI39=4,GM39-GX39,0) -> 0 | GR39: 0 | GS39: 3 | GT39: 0 | GV39: =ROUND((GT39),6) -> 0 | GW39: 1 | GX39: =ROUND(HC39*I39,2) -> 0 | HA39: 0 | HB39: 0 | HC39: =GV39*GW39 -> 0 | HS39: 0 | IK39: 0
A40: 17 | B40: 1 | C40: =ROW(SmtRes!A86) -> 86 | D40: =ROW(EtalonRes!A116) -> 116 | E40: 7 | F40: 4.11-8-1 | G40: Установка аппарата напольного массой до 0,2 т / демонтаж системного блока | H40: 1 ШТ. | I40: 1 | J40: 0 | K40: 1 | O40: =ROUND(CP40,2) -> 58.79 | P40: =ROUND((ROUND((AC40*AW40*I40),2)*BC40),2) -> 0 | Q40: =(ROUND((ROUND(((((ET40*1.2)*0.3))*AV40*I40),2)*BB40),2)+ROUND((ROUND(((AE40-(((EU40*1.2)*0.3)))*AV40*I40),2)*BS40),2)) -> 13.72 | R40: =(ROUND((ROUND(((((EU40*1.2)*0.3))*AV40*I40),2)*BS40),2)+ROUND((ROUND(((AE40-(((EU40*1.2)*0.3)))*AV40*I40),2)*BS40),2)) -> 2.07 | S40: =ROUND((ROUND((AF40*AV40*I40),2)*BA40),2) -> 45.07 | T40: =ROUND(CU40*I40,2) -> 0 | U40: =CV40*I40 -> 3.882276 | V40: =CW40*I40 -> 0 | W40: =ROUND(CX40*I40,2) -> 0 | X40: =(ROUND((((S40+ROUND((ROUND(((((EU40*1.2)*0.3))*AV40*I40),2)*BS40),2))*AT40)/100),2)+ROUND(((ROUND((ROUND(((AE40-(((EU40*1.2)*0.3)))*AV40*I40),2)*BS40),2)*AT40)/100),2)) -> 42.43 | Y40: =(ROUND((((S40+ROUND((ROUND(((((EU40*1.2)*0.3))*AV40*I40),2)*BS40),2))*AU40)/100),2)+ROUND(((ROUND((ROUND(((AE40-(((EU40*1.2)*0.3)))*AV40*I40),2)*BS40),2)*AU40)/100),2)) -> 21.68 | AA40: 55944368 | AB40: =ROUND((AC40+AD40+AF40),6) -> 56.1492 | AC40: =ROUND((((ES40*1)*0)),6) -> 0 | AD40: =ROUND((((((ET40*1.2)*0.3))-(((EU40*1.2)*0.3)))+AE40),6) -> 13.1004 | AE40: =ROUND((((EU40*1.2)*0.3)),6) -> 1.9728 | AF40: =ROUND((((EV40*1.2)*0.3)),6) -> 43.0488 | AG40: =ROUND((AP40),6) -> 0 | AH40: =(((EW40*1.2)*0.3)) -> 3.708 | AI40: =(((EX40*1.2)*0.3)) -> 0 | AJ40: =(AS40) -> 0 | AK40: 161.07 | AL40: 5.1 | AM40: 36.39 | AN40: 5.48 | AO40: 119.58 | AP40: 0 | AQ40: 10.3 | AR40: 0 | AS40: 0 | AT40: 90 | AU40: 46 | AV40: 1.047 | AW40: 1 | AZ40: 1 | BA40: 1 | BB40: 1 | BC40: 1 | BH40: 0 | BI40: 2 | BJ40: ТСН-2001.4 Доп. 80, Сб. 11, т. 8, поз. 1 | BM40: 72 | BN40: 0 | BO40: 4.11-8-1 | BP40: 1 | BQ40: 40 | BR40: 0 | BS40: 1 | BT40: 1 | BU40: 1 | BV40: 1 | BW40: 1 | BX40: 1 | BZ40: 90 | CA40: 46 | CE40: 1566 | CF40: 0 | CG40: 0 | CM40: 0 | CN40: Поправка: Гл.12.Прил.8.п.8. 3_12.00.01.11.001 Наименование: При наличии напряженных и стесненных условий производства работ (стесненность, сложность складирования и транспортной логистики и т.п.) для объектов, расположенных в пределах круговой магистральной системы улиц "Садовое кольцо" города Москвы Поправка: Гл.4.Прил.2.2.п.2.2.29_04.00.01.35.003 Наименование: При демонтаже оборудования, предназначенного в лом | CO40: 0 | CP40: =(P40+Q40+S40) -> 58.79 | CQ40: =ROUND((ROUND((AC40*AW40*1),2)*BC40),2) -> 0 | CR40: =(ROUND((ROUND(((((ET40*1.2)*0.3))*AV40*1),2)*BB40),2)+ROUND((ROUND(((AE40-(((EU40*1.2)*0.3)))*AV40*1),2)*BS40),2)) -> 13.72 | CS40: =(ROUND((ROUND(((((EU40*1.2)*0.3))*AV40*1),2)*BS40),2)+ROUND((ROUND(((AE40-(((EU40*1.2)*0.3)))*AV40*1),2)*BS40),2)) -> 2.07 | CT40: =ROUND((ROUND((AF40*AV40*1),2)*BA40),2) -> 45.07 | CU40: =AG40 -> 0 | CV40: =(AH40*AV40) -> 3.882276 | CW40: =AI40 -> 0 | CX40: =AJ40 -> 0 | CY40: =(ROUND((((S40+ROUND((ROUND(((((EU40*1.2)*0.3))*AV40*1),2)*BS40),2))*AT40)/100),2)+ROUND(((ROUND((ROUND(((AE40-(((EU40*1.2)*0.3)))*AV40*1),2)*BS40),2)*AT40)/100),2)) -> 42.43 | CZ40: =(ROUND((((S40+ROUND((ROUND(((((EU40*1.2)*0.3))*AV40*1),2)*BS40),2))*AU40)/100),2)+ROUND(((ROUND((ROUND(((AE40-(((EU40*1.2)*0.3)))*AV40*1),2)*BS40),2)*AU40)/100),2)) -> 21.68 | DB40: 25 | DD40: *1)*0 | DE40: *1,2)*0,3 | DF40: *1,2)*0,3 | DG40: *1,2)*0,3 | DI40: *1,2)*0,3 | DJ40: *1,2)*0,3 | DN40: 0 | DO40: 0 | DP40: 1 | DQ40: 1 | DU40: 1013 | DV40: 1 ШТ. | DW40: 1 ШТ. | DX40: 1 | EE40: 55393976 | EF40: 40 | EG40: Монтаж оборудования | EH40: 0 | EJ40: 2 | EK40: 72 | EL40: ТСН-2001.4-11. Приборы и средства автоматизации и вычислительной техники | EM40: ТСН-2001.4-11-1 | EO40: Поправка: Гл.12.Прил.8.п.8. 3_12.00.01.11.001 Поправка: Гл.4.Прил.2.2.п.2.2.29_04.00.01.35.003 | EQ40: 0 | ER40: 161.07 | ES40: 5.1 | ET40: 36.39 | EU40: 5.48 | EV40: 119.58 | EW40: 10.3 | EX40: 0 | EY40: 0 | FQ40: 0 | FR40: 0 | FS40: 0 | FX40: 90 | FY40: 46 | GD40: 1 | GF40: -400545562 | GG40: 2 | GH40: 1 | GI40: 2 | GJ40: 0 | GK40: 0 | GL40: =ROUND(IF(AND(BH40=3,BI40=3,FS40<>0),P40,0),2) -> 0 | GM40: =ROUND(O40+X40+Y40,2)+GX40 -> 122.9 | GN40: =IF(OR(BI40=0,BI40=1),GM40-GX40,0) -> 0 | GO40: =IF(BI40=2,GM40-GX40,0) -> 122.9 | GP40: =IF(BI40=4,GM40-GX40,0) -> 0 | GR40: 0 | GS40: 3 | GT40: 0 | GV40: =ROUND((GT40),6) -> 0 | GW40: 1 | GX40: =ROUND(HC40*I40,2) -> 0 | HA40: 0 | HB40: 0 | HC40: =GV40*GW40 -> 0 | HS40: 0 | IK40: 0
A41: 17 | B41: 1 | C41: =ROW(SmtRes!A92) -> 92 | D41: =ROW(EtalonRes!A124) -> 124 | E41: 7 | F41: 4.11-8-1 | G41: Установка аппарата напольного массой до 0,2 т / демонтаж системного блока | H41: 1 ШТ. | I41: 1 | J41: 0 | K41: 1 | O41: =ROUND(CP41,2) -> 2773.07 | P41: =ROUND((ROUND((AC41*AW41*I41),2)*BC41),2) -> 0 | Q41: =(ROUND((ROUND(((((ET41*1.2)*0.3))*AV41*I41),2)*BB41),2)+ROUND((ROUND(((AE41-(((EU41*1.2)*0.3)))*AV41*I41),2)*BS41),2)) -> 233.38 | R41: =(ROUND((ROUND(((((EU41*1.2)*0.3))*AV41*I41),2)*BS41),2)+ROUND((ROUND(((AE41-(((EU41*1.2)*0.3)))*AV41*I41),2)*BS41),2)) -> 116.64 | S41: =ROUND((ROUND((AF41*AV41*I41),2)*BA41),2) -> 2539.69 | T41: =ROUND(CU41*I41,2) -> 0 | U41: =CV41*I41 -> 3.882276 | V41: =CW41*I41 -> 0 | W41: =ROUND(CX41*I41,2) -> 0 | X41: =(ROUND((((S41+ROUND((ROUND(((((EU41*1.2)*0.3))*AV41*I41),2)*BS41),2))*AT41)/100),2)+ROUND(((ROUND((ROUND(((AE41-(((EU41*1.2)*0.3)))*AV41*I41),2)*BS41),2)*AT41)/100),2)) -> 2390.7 | Y41: =(ROUND((((S41+ROUND((ROUND(((((EU41*1.2)*0.3))*AV41*I41),2)*BS41),2))*AU41)/100),2)+ROUND(((ROUND((ROUND(((AE41-(((EU41*1.2)*0.3)))*AV41*I41),2)*BS41),2)*AU41)/100),2)) -> 1221.91 | AA41: 55944370 | AB41: =ROUND((AC41+AD41+AF41),6) -> 56.1492 | AC41: =ROUND((((ES41*1)*0)),6) -> 0 | AD41: =ROUND((((((ET41*1.2)*0.3))-(((EU41*1.2)*0.3)))+AE41),6) -> 13.1004 | AE41: =ROUND((((EU41*1.2)*0.3)),6) -> 1.9728 | AF41: =ROUND((((EV41*1.2)*0.3)),6) -> 43.0488 | AG41: =ROUND((AP41),6) -> 0 | AH41: =(((EW41*1.2)*0.3)) -> 3.708 | AI41: =(((EX41*1.2)*0.3)) -> 0 | AJ41: =(AS41) -> 0 | AK41: 161.07 | AL41: 5.1 | AM41: 36.39 | AN41: 5.48 | AO41: 119.58 | AP41: 0 | AQ41: 10.3 | AR41: 0 | AS41: 0 | AT41: 90 | AU41: 46 | AV41: 1.047 | AW41: 1 | AZ41: 1 | BA41: 56.35 | BB41: 17.01 | BC41: 5.86 | BH41: 0 | BI41: 2 | BJ41: ТСН-2001.4 Доп. 80, Сб. 11, т. 8, поз. 1 | BM41: 72 | BN41: 0 | BO41: 4.11-8-1 | BP41: 1 | BQ41: 40 | BR41: 0 | BS41: 56.35 | BT41: 1 | BU41: 1 | BV41: 1 | BW41: 1 | BX41: 1 | BZ41: 90 | CA41: 46 | CE41: 1566 | CF41: 0 | CG41: 0 | CM41: 0 | CN41: Поправка: Гл.12.Прил.8.п.8. 3_12.00.01.11.001 Наименование: При наличии напряженных и стесненных условий производства работ (стесненность, сложность складирования и транспортной логистики и т.п.) для объектов, расположенных в пределах круговой магистральной системы улиц "Садовое кольцо" города Москвы Поправка: Гл.4.Прил.2.2.п.2.2.29_04.00.01.35.003 Наименование: При демонтаже оборудования, предназначенного в лом | CO41: 0 | CP41: =(P41+Q41+S41) -> 2773.07 | CQ41: =ROUND((ROUND((AC41*AW41*1),2)*BC41),2) -> 0 | CR41: =(ROUND((ROUND(((((ET41*1.2)*0.3))*AV41*1),2)*BB41),2)+ROUND((ROUND(((AE41-(((EU41*1.2)*0.3)))*AV41*1),2)*BS41),2)) -> 233.38 | CS41: =(ROUND((ROUND(((((EU41*1.2)*0.3))*AV41*1),2)*BS41),2)+ROUND((ROUND(((AE41-(((EU41*1.2)*0.3)))*AV41*1),2)*BS41),2)) -> 116.64 | CT41: =ROUND((ROUND((AF41*AV41*1),2)*BA41),2) -> 2539.69 | CU41: =AG41 -> 0 | CV41: =(AH41*AV41) -> 3.882276 | CW41: =AI41 -> 0 | CX41: =AJ41 -> 0 | CY41: =(ROUND((((S41+ROUND((ROUND(((((EU41*1.2)*0.3))*AV41*1),2)*BS41),2))*AT41)/100),2)+ROUND(((ROUND((ROUND(((AE41-(((EU41*1.2)*0.3)))*AV41*1),2)*BS41),2)*AT41)/100),2)) -> 2390.7 | CZ41: =(ROUND((((S41+ROUND((ROUND(((((EU41*1.2)*0.3))*AV41*1),2)*BS41),2))*AU41)/100),2)+ROUND(((ROUND((ROUND(((AE41-(((EU41*1.2)*0.3)))*AV41*1),2)*BS41),2)*AU41)/100),2)) -> 1221.91 | DB41: 27 | DD41: *1)*0 | DE41: *1,2)*0,3 | DF41: *1,2)*0,3 | DG41: *1,2)*0,3 | DI41: *1,2)*0,3 | DJ41: *1,2)*0,3 | DN41: 0 | DO41: 0 | DP41: 1 | DQ41: 1 | DU41: 1013 | DV41: 1 ШТ. | DW41: 1 ШТ. | DX41: 1 | EE41: 55393976 | EF41: 40 | EG41: Монтаж оборудования | EH41: 0 | EJ41: 2 | EK41: 72 | EL41: ТСН-2001.4-11. Приборы и средства автоматизации и вычислительной техники | EM41: ТСН-2001.4-11-1 | EO41: Поправка: Гл.12.Прил.8.п.8. 3_12.00.01.11.001 Поправка: Гл.4.Прил.2.2.п.2.2.29_04.00.01.35.003 | EQ41: 0 | ER41: 161.07 | ES41: 5.1 | ET41: 36.39 | EU41: 5.48 | EV41: 119.58 | EW41: 10.3 | EX41: 0 | EY41: 0 | FQ41: 0 | FR41: 0 | FS41: 0 | FX41: 90 | FY41: 46 | GD41: 1 | GF41: -400545562 | GG41: 2 | GH41: 1 | GI41: 2 | GJ41: 0 | GK41: 0 | GL41: =ROUND(IF(AND(BH41=3,BI41=3,FS41<>0),P41,0),2) -> 0 | GM41: =ROUND(O41+X41+Y41,2)+GX41 -> 6385.68 | GN41: =IF(OR(BI41=0,BI41=1),GM41-GX41,0) -> 0 | GO41: =IF(BI41=2,GM41-GX41,0) -> 6385.68 | GP41: =IF(BI41=4,GM41-GX41,0) -> 0 | GR41: 0 | GS41: 3 | GT41: 0 | GV41: =ROUND((GT41),6) -> 0 | GW41: 1 | GX41: =ROUND(HC41*I41,2) -> 0 | HA41: 0 | HB41: 0 | HC41: =GV41*GW41 -> 0 | HS41: 0 | IK41: 0
A42: 17 | B42: 1 | C42: =ROW(SmtRes!A94) -> 94 | D42: =ROW(EtalonRes!A127) -> 127 | E42: 8 | F42: 4.11-7-2 | G42: Установка аппарата настольного массой до 0,03 т / демонтаж монитора | H42: 1 ШТ. | I42: 1 | J42: 0 | K42: 1 | O42: =ROUND(CP42,2) -> 23.04 | P42: =ROUND((ROUND((AC42*AW42*I42),2)*BC42),2) -> 0 | Q42: =(ROUND((ROUND(((((ET42*1.2)*0.3))*AV42*I42),2)*BB42),2)+ROUND((ROUND(((AE42-(((EU42*1.2)*0.3)))*AV42*I42),2)*BS42),2)) -> 10.02 | R42: =(ROUND((ROUND(((((EU42*1.2)*0.3))*AV42*I42),2)*BS42),2)+ROUND((ROUND(((AE42-(((EU42*1.2)*0.3)))*AV42*I42),2)*BS42),2)) -> 1.52 | S42: =ROUND((ROUND((AF42*AV42*I42),2)*BA42),2) -> 13.02 | T42: =ROUND(CU42*I42,2) -> 0 | U42: =CV42*I42 -> 1.1646828 | V42: =CW42*I42 -> 0 | W42: =ROUND(CX42*I42,2) -> 0 | X42: =(ROUND((((S42+ROUND((ROUND(((((EU42*1.2)*0.3))*AV42*I42),2)*BS42),2))*AT42)/100),2)+ROUND(((ROUND((ROUND(((AE42-(((EU42*1.2)*0.3)))*AV42*I42),2)*BS42),2)*AT42)/100),2)) -> 13.09 | Y42: =(ROUND((((S42+ROUND((ROUND(((((EU42*1.2)*0.3))*AV42*I42),2)*BS42),2))*AU42)/100),2)+ROUND(((ROUND((ROUND(((AE42-(((EU42*1.2)*0.3)))*AV42*I42),2)*BS42),2)*AU42)/100),2)) -> 6.69 | AA42: 55944368 | AB42: =ROUND((AC42+AD42+AF42),6) -> 22.0104 | AC42: =ROUND((((ES42*1)*0)),6) -> 0 | AD42: =ROUND((((((ET42*1.2)*0.3))-(((EU42*1.2)*0.3)))+AE42),6) -> 9.5724 | AE42: =ROUND((((EU42*1.2)*0.3)),6) -> 1.4544 | AF42: =ROUND((((EV42*1.2)*0.3)),6) -> 12.438 | AG42: =ROUND((AP42),6) -> 0 | AH42: =(((EW42*1.2)*0.3)) -> 1.1124 | AI42: =(((EX42*1.2)*0.3)) -> 0 | AJ42: =(AS42) -> 0 | AK42: 61.14 | AL42: 0 | AM42: 26.59 | AN42: 4.04 | AO42: 34.55 | AP42: 0 | AQ42: 3.09 | AR42: 0 | AS42: 0 | AT42: 90 | AU42: 46 | AV42: 1.047 | AW42: 1 | AZ42: 1 | BA42: 1 | BB42: 1 | BC42: 1 | BH42: 0 | BI42: 2 | BJ42: ТСН-2001.4 Доп. 68, Сб. 11, т. 7, поз. 2 | BM42: 72 | BN42: 0 | BO42: 4.11-7-2 | BP42: 1 | BQ42: 40 | BR42: 0 | BS42: 1 | BT42: 1 | BU42: 1 | BV42: 1 | BW42: 1 | BX42: 1 | BZ42: 90 | CA42: 46 | CE42: 1566 | CF42: 0 | CG42: 0 | CM42: 0 | CN42: Поправка: Гл.12.Прил.8.п.8. 3_12.00.01.11.001 Наименование: При наличии напряженных и стесненных условий производства работ (стесненность, сложность складирования и транспортной логистики и т.п.) для объектов, расположенных в пределах круговой магистральной системы улиц "Садовое кольцо" города Москвы Поправка: Гл.4.Прил.2.2.п.2.2.29_04.00.01.35.003 Наименование: При демонтаже оборудования, предназначенного в лом | CO42: 0 | CP42: =(P42+Q42+S42) -> 23.04 | CQ42: =ROUND((ROUND((AC42*AW42*1),2)*BC42),2) -> 0 | CR42: =(ROUND((ROUND(((((ET42*1.2)*0.3))*AV42*1),2)*BB42),2)+ROUND((ROUND(((AE42-(((EU42*1.2)*0.3)))*AV42*1),2)*BS42),2)) -> 10.02 | CS42: =(ROUND((ROUND(((((EU42*1.2)*0.3))*AV42*1),2)*BS42),2)+ROUND((ROUND(((AE42-(((EU42*1.2)*0.3)))*AV42*1),2)*BS42),2)) -> 1.52 | CT42: =ROUND((ROUND((AF42*AV42*1),2)*BA42),2) -> 13.02 | CU42: =AG42 -> 0 | CV42: =(AH42*AV42) -> 1.1646828 | CW42: =AI42 -> 0 | CX42: =AJ42 -> 0 | CY42: =(ROUND((((S42+ROUND((ROUND(((((EU42*1.2)*0.3))*AV42*1),2)*BS42),2))*AT42)/100),2)+ROUND(((ROUND((ROUND(((AE42-(((EU42*1.2)*0.3)))*AV42*1),2)*BS42),2)*AT42)/100),2)) -> 13.09 | CZ42: =(ROUND((((S42+ROUND((ROUND(((((EU42*1.2)*0.3))*AV42*1),2)*BS42),2))*AU42)/100),2)+ROUND(((ROUND((ROUND(((AE42-(((EU42*1.2)*0.3)))*AV42*1),2)*BS42),2)*AU42)/100),2)) -> 6.69 | DB42: 29 | DD42: *1)*0 | DE42: *1,2)*0,3 | DF42: *1,2)*0,3 | DG42: *1,2)*0,3 | DI42: *1,2)*0,3 | DJ42: *1,2)*0,3 | DN42: 0 | DO42: 0 | DP42: 1 | DQ42: 1 | DU42: 1013 | DV42: 1 ШТ. | DW42: 1 ШТ. | DX42: 1 | EE42: 55393976 | EF42: 40 | EG42: Монтаж оборудования | EH42: 0 | EJ42: 2 | EK42: 72 | EL42: ТСН-2001.4-11. Приборы и средства автоматизации и вычислительной техники | EM42: ТСН-2001.4-11-1 | EO42: Поправка: Гл.12.Прил.8.п.8. 3_12.00.01.11.001 Поправка: Гл.4.Прил.2.2.п.2.2.29_04.00.01.35.003 | EQ42: 0 | ER42: 61.14 | ES42: 0 | ET42: 26.59 | EU42: 4.04 | EV42: 34.55 | EW42: 3.09 | EX42: 0 | EY42: 0 | FQ42: 0 | FR42: 0 | FS42: 0 | FX42: 90 | FY42: 46 | GD42: 1 | GF42: -1651993029 | GG42: 2 | GH42: 1 | GI42: 2 | GJ42: 0 | GK42: 0 | GL42: =ROUND(IF(AND(BH42=3,BI42=3,FS42<>0),P42,0),2) -> 0 | GM42: =ROUND(O42+X42+Y42,2)+GX42 -> 42.82 | GN42: =IF(OR(BI42=0,BI42=1),GM42-GX42,0) -> 0 | GO42: =IF(BI42=2,GM42-GX42,0) -> 42.82 | GP42: =IF(BI42=4,GM42-GX42,0) -> 0 | GR42: 0 | GS42: 3 | GT42: 0 | GV42: =ROUND((GT42),6) -> 0 | GW42: 1 | GX42: =ROUND(HC42*I42,2) -> 0 | HA42: 0 | HB42: 0 | HC42: =GV42*GW42 -> 0 | HS42: 0 | IK42: 0
A43: 17 | B43: 1 | C43: =ROW(SmtRes!A96) -> 96 | D43: =ROW(EtalonRes!A130) -> 130 | E43: 8 | F43: 4.11-7-2 | G43: Установка аппарата настольного массой до 0,03 т / демонтаж монитора | H43: 1 ШТ. | I43: 1 | J43: 0 | K43: 1 | O43: =ROUND(CP43,2) -> 904.72 | P43: =ROUND((ROUND((AC43*AW43*I43),2)*BC43),2) -> 0 | Q43: =(ROUND((ROUND(((((ET43*1.2)*0.3))*AV43*I43),2)*BB43),2)+ROUND((ROUND(((AE43-(((EU43*1.2)*0.3)))*AV43*I43),2)*BS43),2)) -> 171.04 | R43: =(ROUND((ROUND(((((EU43*1.2)*0.3))*AV43*I43),2)*BS43),2)+ROUND((ROUND(((AE43-(((EU43*1.2)*0.3)))*AV43*I43),2)*BS43),2)) -> 85.65 | S43: =ROUND((ROUND((AF43*AV43*I43),2)*BA43),2) -> 733.68 | T43: =ROUND(CU43*I43,2) -> 0 | U43: =CV43*I43 -> 1.1646828 | V43: =CW43*I43 -> 0 | W43: =ROUND(CX43*I43,2) -> 0 | X43: =(ROUND((((S43+ROUND((ROUND(((((EU43*1.2)*0.3))*AV43*I43),2)*BS43),2))*AT43)/100),2)+ROUND(((ROUND((ROUND(((AE43-(((EU43*1.2)*0.3)))*AV43*I43),2)*BS43),2)*AT43)/100),2)) -> 737.4 | Y43: =(ROUND((((S43+ROUND((ROUND(((((EU43*1.2)*0.3))*AV43*I43),2)*BS43),2))*AU43)/100),2)+ROUND(((ROUND((ROUND(((AE43-(((EU43*1.2)*0.3)))*AV43*I43),2)*BS43),2)*AU43)/100),2)) -> 376.89 | AA43: 55944370 | AB43: =ROUND((AC43+AD43+AF43),6) -> 22.0104 | AC43: =ROUND((((ES43*1)*0)),6) -> 0 | AD43: =ROUND((((((ET43*1.2)*0.3))-(((EU43*1.2)*0.3)))+AE43),6) -> 9.5724 | AE43: =ROUND((((EU43*1.2)*0.3)),6) -> 1.4544 | AF43: =ROUND((((EV43*1.2)*0.3)),6) -> 12.438 | AG43: =ROUND((AP43),6) -> 0 | AH43: =(((EW43*1.2)*0.3)) -> 1.1124 | AI43: =(((EX43*1.2)*0.3)) -> 0 | AJ43: =(AS43) -> 0 | AK43: 61.14 | AL43: 0 | AM43: 26.59 | AN43: 4.04 | AO43: 34.55 | AP43: 0 | AQ43: 3.09 | AR43: 0 | AS43: 0 | AT43: 90 | AU43: 46 | AV43: 1.047 | AW43: 1 | AZ43: 1 | BA43: 56.35 | BB43: 17.07 | BC43: 1 | BH43: 0 | BI43: 2 | BJ43: ТСН-2001.4 Доп. 68, Сб. 11, т. 7, поз. 2 | BM43: 72 | BN43: 0 | BO43: 4.11-7-2 | BP43: 1 | BQ43: 40 | BR43: 0 | BS43: 56.35 | BT43: 1 | BU43: 1 | BV43: 1 | BW43: 1 | BX43: 1 | BZ43: 90 | CA43: 46 | CE43: 1566 | CF43: 0 | CG43: 0 | CM43: 0 | CN43: Поправка: Гл.12.Прил.8.п.8. 3_12.00.01.11.001 Наименование: При наличии напряженных и стесненных условий производства работ (стесненность, сложность складирования и транспортной логистики и т.п.) для объектов, расположенных в пределах круговой магистральной системы улиц "Садовое кольцо" города Москвы Поправка: Гл.4.Прил.2.2.п.2.2.29_04.00.01.35.003 Наименование: При демонтаже оборудования, предназначенного в лом | CO43: 0 | CP43: =(P43+Q43+S43) -> 904.72 | CQ43: =ROUND((ROUND((AC43*AW43*1),2)*BC43),2) -> 0 | CR43: =(ROUND((ROUND(((((ET43*1.2)*0.3))*AV43*1),2)*BB43),2)+ROUND((ROUND(((AE43-(((EU43*1.2)*0.3)))*AV43*1),2)*BS43),2)) -> 171.04 | CS43: =(ROUND((ROUND(((((EU43*1.2)*0.3))*AV43*1),2)*BS43),2)+ROUND((ROUND(((AE43-(((EU43*1.2)*0.3)))*AV43*1),2)*BS43),2)) -> 85.65 | CT43: =ROUND((ROUND((AF43*AV43*1),2)*BA43),2) -> 733.68 | CU43: =AG43 -> 0 | CV43: =(AH43*AV43) -> 1.1646828 | CW43: =AI43 -> 0 | CX43: =AJ43 -> 0 | CY43: =(ROUND((((S43+ROUND((ROUND(((((EU43*1.2)*0.3))*AV43*1),2)*BS43),2))*AT43)/100),2)+ROUND(((ROUND((ROUND(((AE43-(((EU43*1.2)*0.3)))*AV43*1),2)*BS43),2)*AT43)/100),2)) -> 737.4 | CZ43: =(ROUND((((S43+ROUND((ROUND(((((EU43*1.2)*0.3))*AV43*1),2)*BS43),2))*AU43)/100),2)+ROUND(((ROUND((ROUND(((AE43-(((EU43*1.2)*0.3)))*AV43*1),2)*BS43),2)*AU43)/100),2)) -> 376.89 | DB43: 31 | DD43: *1)*0 | DE43: *1,2)*0,3 | DF43: *1,2)*0,3 | DG43: *1,2)*0,3 | DI43: *1,2)*0,3 | DJ43: *1,2)*0,3 | DN43: 0 | DO43: 0 | DP43: 1 | DQ43: 1 | DU43: 1013 | DV43: 1 ШТ. | DW43: 1 ШТ. | DX43: 1 | EE43: 55393976 | EF43: 40 | EG43: Монтаж оборудования | EH43: 0 | EJ43: 2 | EK43: 72 | EL43: ТСН-2001.4-11. Приборы и средства автоматизации и вычислительной техники | EM43: ТСН-2001.4-11-1 | EO43: Поправка: Гл.12.Прил.8.п.8. 3_12.00.01.11.001 Поправка: Гл.4.Прил.2.2.п.2.2.29_04.00.01.35.003 | EQ43: 0 | ER43: 61.14 | ES43: 0 | ET43: 26.59 | EU43: 4.04 | EV43: 34.55 | EW43: 3.09 | EX43: 0 | EY43: 0 | FQ43: 0 | FR43: 0 | FS43: 0 | FX43: 90 | FY43: 46 | GD43: 1 | GF43: -1651993029 | GG43: 2 | GH43: 1 | GI43: 2 | GJ43: 0 | GK43: 0 | GL43: =ROUND(IF(AND(BH43=3,BI43=3,FS43<>0),P43,0),2) -> 0 | GM43: =ROUND(O43+X43+Y43,2)+GX43 -> 2019.01 | GN43: =IF(OR(BI43=0,BI43=1),GM43-GX43,0) -> 0 | GO43: =IF(BI43=2,GM43-GX43,0) -> 2019.01 | GP43: =IF(BI43=4,GM43-GX43,0) -> 0 | GR43: 0 | GS43: 3 | GT43: 0 | GV43: =ROUND((GT43),6) -> 0 | GW43: 1 | GX43: =ROUND(HC43*I43,2) -> 0 | HA43: 0 | HB43: 0 | HC43: =GV43*GW43 -> 0 | HS43: 0 | IK43: 0
A44: 17 | B44: 1 | C44: =ROW(SmtRes!A102) -> 102 | D44: =ROW(EtalonRes!A137) -> 137 | E44: 9 | F44: 4.10-167-1 | G44: Монтаж блока питания сети (БПС) в диспетчерской / демонтаж ИБП | H44: 1 ШТ. | I44: 1 | J44: 0 | K44: 1 | O44: =ROUND(CP44,2) -> 7.15 | P44: =ROUND((ROUND((AC44*AW44*I44),2)*BC44),2) -> 0 | Q44: =(ROUND((ROUND(((((ET44*1.2)*0.3))*AV44*I44),2)*BB44),2)+ROUND((ROUND(((AE44-(((EU44*1.2)*0.3)))*AV44*I44),2)*BS44),2)) -> 0.01 | R44: =(ROUND((ROUND(((((EU44*1.2)*0.3))*AV44*I44),2)*BS44),2)+ROUND((ROUND(((AE44-(((EU44*1.2)*0.3)))*AV44*I44),2)*BS44),2)) -> 0 | S44: =ROUND((ROUND((AF44*AV44*I44),2)*BA44),2) -> 7.14 | T44: =ROUND(CU44*I44,2) -> 0 | U44: =CV44*I44 -> 0.5126112 | V44: =CW44*I44 -> 0 | W44: =ROUND(CX44*I44,2) -> 0 | X44: =(ROUND((((S44+ROUND((ROUND(((((EU44*1.2)*0.3))*AV44*I44),2)*BS44),2))*AT44)/100),2)+ROUND(((ROUND((ROUND(((AE44-(((EU44*1.2)*0.3)))*AV44*I44),2)*BS44),2)*AT44)/100),2)) -> 6.43 | Y44: =(ROUND((((S44+ROUND((ROUND(((((EU44*1.2)*0.3))*AV44*I44),2)*BS44),2))*AU44)/100),2)+ROUND(((ROUND((ROUND(((AE44-(((EU44*1.2)*0.3)))*AV44*I44),2)*BS44),2)*AU44)/100),2)) -> 3.28 | AA44: 55944368 | AB44: =ROUND((AC44+AD44+AF44),6) -> 6.8256 | AC44: =ROUND((((ES44*1)*0)),6) -> 0 | AD44: =ROUND((((((ET44*1.2)*0.3))-(((EU44*1.2)*0.3)))+AE44),6) -> 0.0072 | AE44: =ROUND((((EU44*1.2)*0.3)),6) -> 0 | AF44: =ROUND((((EV44*1.2)*0.3)),6) -> 6.8184 | AG44: =ROUND((AP44),6) -> 0 | AH44: =(((EW44*1.2)*0.3)) -> 0.4896 | AI44: =(((EX44*1.2)*0.3)) -> 0 | AJ44: =(AS44) -> 0 | AK44: 21.3 | AL44: 2.34 | AM44: 0.02 | AN44: 0 | AO44: 18.94 | AP44: 0 | AQ44: 1.36 | AR44: 0 | AS44: 0 | AT44: 90 | AU44: 46 | AV44: 1.047 | AW44: 1 | AZ44: 1 | BA44: 1 | BB44: 1 | BC44: 1 | BH44: 0 | BI44: 2 | BJ44: ТСН-2001.4 Доп. 69, Сб. 10, т. 167, поз. 1 | BM44: 68 | BN44: 0 | BO44: 4.10-167-1 | BP44: 1 | BQ44: 40 | BR44: 0 | BS44: 1 | BT44: 1 | BU44: 1 | BV44: 1 | BW44: 1 | BX44: 1 | BZ44: 90 | CA44: 46 | CE44: 1566 | CF44: 0 | CG44: 0 | CM44: 0 | CN44: Поправка: Гл.12.Прил.8.п.8. 3_12.00.01.11.001 Наименование: При наличии напряженных и стесненных условий производства работ (стесненность, сложность складирования и транспортной логистики и т.п.) для объектов, расположенных в пределах круговой магистральной системы улиц "Садовое кольцо" города Москвы Поправка: Гл.4.Прил.2.2.п.2.2.29_04.00.01.35.003 Наименование: При демонтаже оборудования, предназначенного в лом | CO44: 0 | CP44: =(P44+Q44+S44) -> 7.15 | CQ44: =ROUND((ROUND((AC44*AW44*1),2)*BC44),2) -> 0 | CR44: =(ROUND((ROUND(((((ET44*1.2)*0.3))*AV44*1),2)*BB44),2)+ROUND((ROUND(((AE44-(((EU44*1.2)*0.3)))*AV44*1),2)*BS44),2)) -> 0.01 | CS44: =(ROUND((ROUND(((((EU44*1.2)*0.3))*AV44*1),2)*BS44),2)+ROUND((ROUND(((AE44-(((EU44*1.2)*0.3)))*AV44*1),2)*BS44),2)) -> 0 | CT44: =ROUND((ROUND((AF44*AV44*1),2)*BA44),2) -> 7.14 | CU44: =AG44 -> 0 | CV44: =(AH44*AV44) -> 0.5126112 | CW44: =AI44 -> 0 | CX44: =AJ44 -> 0 | CY44: =(ROUND((((S44+ROUND((ROUND(((((EU44*1.2)*0.3))*AV44*1),2)*BS44),2))*AT44)/100),2)+ROUND(((ROUND((ROUND(((AE44-(((EU44*1.2)*0.3)))*AV44*1),2)*BS44),2)*AT44)/100),2)) -> 6.43 | CZ44: =(ROUND((((S44+ROUND((ROUND(((((EU44*1.2)*0.3))*AV44*1),2)*BS44),2))*AU44)/100),2)+ROUND(((ROUND((ROUND(((AE44-(((EU44*1.2)*0.3)))*AV44*1),2)*BS44),2)*AU44)/100),2)) -> 3.28 | DB44: 33 | DD44: *1)*0 | DE44: *1,2)*0,3 | DF44: *1,2)*0,3 | DG44: *1,2)*0,3 | DI44: *1,2)*0,3 | DJ44: *1,2)*0,3 | DN44: 0 | DO44: 0 | DP44: 1 | DQ44: 1 | DU44: 1013 | DV44: 1 ШТ. | DW44: 1 ШТ. | DX44: 1 | EE44: 55393972 | EF44: 40 | EG44: Монтаж оборудования | EH44: 0 | EJ44: 2 | EK44: 68 | EL44: ТСН-2001.4-10. Прокладка и монтаж сетей связи | EM44: ТСН-2001.4-10-1 | EO44: Поправка: Гл.12.Прил.8.п.8. 3_12.00.01.11.001 Поправка: Гл.4.Прил.2.2.п.2.2.29_04.00.01.35.003 | EQ44: 0 | ER44: 21.3 | ES44: 2.34 | ET44: 0.02 | EU44: 0 | EV44: 18.94 | EW44: 1.36 | EX44: 0 | EY44: 0 | FQ44: 0 | FR44: 0 | FS44: 0 | FX44: 90 | FY44: 46 | GD44: 1 | GF44: 1815428302 | GG44: 2 | GH44: 1 | GI44: 2 | GJ44: 0 | GK44: 0 | GL44: =ROUND(IF(AND(BH44=3,BI44=3,FS44<>0),P44,0),2) -> 0 | GM44: =ROUND(O44+X44+Y44,2)+GX44 -> 16.86 | GN44: =IF(OR(BI44=0,BI44=1),GM44-GX44,0) -> 0 | GO44: =IF(BI44=2,GM44-GX44,0) -> 16.86 | GP44: =IF(BI44=4,GM44-GX44,0) -> 0 | GR44: 0 | GS44: 3 | GT44: 0 | GV44: =ROUND((GT44),6) -> 0 | GW44: 1 | GX44: =ROUND(HC44*I44,2) -> 0 | HA44: 0 | HB44: 0 | HC44: =GV44*GW44 -> 0 | HS44: 0 | IK44: 0
A45: 17 | B45: 1 | C45: =ROW(SmtRes!A108) -> 108 | D45: =ROW(EtalonRes!A144) -> 144 | E45: 9 | F45: 4.10-167-1 | G45: Монтаж блока питания сети (БПС) в диспетчерской / демонтаж ИБП | H45: 1 ШТ. | I45: 1 | J45: 0 | K45: 1 | O45: =ROUND(CP45,2) -> 402.45 | P45: =ROUND((ROUND((AC45*AW45*I45),2)*BC45),2) -> 0 | Q45: =(ROUND((ROUND(((((ET45*1.2)*0.3))*AV45*I45),2)*BB45),2)+ROUND((ROUND(((AE45-(((EU45*1.2)*0.3)))*AV45*I45),2)*BS45),2)) -> 0.11 | R45: =(ROUND((ROUND(((((EU45*1.2)*0.3))*AV45*I45),2)*BS45),2)+ROUND((ROUND(((AE45-(((EU45*1.2)*0.3)))*AV45*I45),2)*BS45),2)) -> 0 | S45: =ROUND((ROUND((AF45*AV45*I45),2)*BA45),2) -> 402.34 | T45: =ROUND(CU45*I45,2) -> 0 | U45: =CV45*I45 -> 0.5126112 | V45: =CW45*I45 -> 0 | W45: =ROUND(CX45*I45,2) -> 0 | X45: =(ROUND((((S45+ROUND((ROUND(((((EU45*1.2)*0.3))*AV45*I45),2)*BS45),2))*AT45)/100),2)+ROUND(((ROUND((ROUND(((AE45-(((EU45*1.2)*0.3)))*AV45*I45),2)*BS45),2)*AT45)/100),2)) -> 362.11 | Y45: =(ROUND((((S45+ROUND((ROUND(((((EU45*1.2)*0.3))*AV45*I45),2)*BS45),2))*AU45)/100),2)+ROUND(((ROUND((ROUND(((AE45-(((EU45*1.2)*0.3)))*AV45*I45),2)*BS45),2)*AU45)/100),2)) -> 185.08 | AA45: 55944370 | AB45: =ROUND((AC45+AD45+AF45),6) -> 6.8256 | AC45: =ROUND((((ES45*1)*0)),6) -> 0 | AD45: =ROUND((((((ET45*1.2)*0.3))-(((EU45*1.2)*0.3)))+AE45),6) -> 0.0072 | AE45: =ROUND((((EU45*1.2)*0.3)),6) -> 0 | AF45: =ROUND((((EV45*1.2)*0.3)),6) -> 6.8184 | AG45: =ROUND((AP45),6) -> 0 | AH45: =(((EW45*1.2)*0.3)) -> 0.4896 | AI45: =(((EX45*1.2)*0.3)) -> 0 | AJ45: =(AS45) -> 0 | AK45: 21.3 | AL45: 2.34 | AM45: 0.02 | AN45: 0 | AO45: 18.94 | AP45: 0 | AQ45: 1.36 | AR45: 0 | AS45: 0 | AT45: 90 | AU45: 46 | AV45: 1.047 | AW45: 1 | AZ45: 1 | BA45: 56.35 | BB45: 11 | BC45: 10.24 | BH45: 0 | BI45: 2 | BJ45: ТСН-2001.4 Доп. 69, Сб. 10, т. 167, поз. 1 | BM45: 68 | BN45: 0 | BO45: 4.10-167-1 | BP45: 1 | BQ45: 40 | BR45: 0 | BS45: 56.35 | BT45: 1 | BU45: 1 | BV45: 1 | BW45: 1 | BX45: 1 | BZ45: 90 | CA45: 46 | CE45: 1566 | CF45: 0 | CG45: 0 | CM45: 0 | CN45: Поправка: Гл.12.Прил.8.п.8. 3_12.00.01.11.001 Наименование: При наличии напряженных и стесненных условий производства работ (стесненность, сложность складирования и транспортной логистики и т.п.) для объектов, расположенных в пределах круговой магистральной системы улиц "Садовое кольцо" города Москвы Поправка: Гл.4.Прил.2.2.п.2.2.29_04.00.01.35.003 Наименование: При демонтаже оборудования, предназначенного в лом | CO45: 0 | CP45: =(P45+Q45+S45) -> 402.45 | CQ45: =ROUND((ROUND((AC45*AW45*1),2)*BC45),2) -> 0 | CR45: =(ROUND((ROUND(((((ET45*1.2)*0.3))*AV45*1),2)*BB45),2)+ROUND((ROUND(((AE45-(((EU45*1.2)*0.3)))*AV45*1),2)*BS45),2)) -> 0.11 | CS45: =(ROUND((ROUND(((((EU45*1.2)*0.3))*AV45*1),2)*BS45),2)+ROUND((ROUND(((AE45-(((EU45*1.2)*0.3)))*AV45*1),2)*BS45),2)) -> 0 | CT45: =ROUND((ROUND((AF45*AV45*1),2)*BA45),2) -> 402.34 | CU45: =AG45 -> 0 | CV45: =(AH45*AV45) -> 0.5126112 | CW45: =AI45 -> 0 | CX45: =AJ45 -> 0 | CY45: =(ROUND((((S45+ROUND((ROUND(((((EU45*1.2)*0.3))*AV45*1),2)*BS45),2))*AT45)/100),2)+ROUND(((ROUND((ROUND(((AE45-(((EU45*1.2)*0.3)))*AV45*1),2)*BS45),2)*AT45)/100),2)) -> 362.11 | CZ45: =(ROUND((((S45+ROUND((ROUND(((((EU45*1.2)*0.3))*AV45*1),2)*BS45),2))*AU45)/100),2)+ROUND(((ROUND((ROUND(((AE45-(((EU45*1.2)*0.3)))*AV45*1),2)*BS45),2)*AU45)/100),2)) -> 185.08 | DB45: 35 | DD45: *1)*0 | DE45: *1,2)*0,3 | DF45: *1,2)*0,3 | DG45: *1,2)*0,3 | DI45: *1,2)*0,3 | DJ45: *1,2)*0,3 | DN45: 0 | DO45: 0 | DP45: 1 | DQ45: 1 | DU45: 1013 | DV45: 1 ШТ. | DW45: 1 ШТ. | DX45: 1 | EE45: 55393972 | EF45: 40 | EG45: Монтаж оборудования | EH45: 0 | EJ45: 2 | EK45: 68 | EL45: ТСН-2001.4-10. Прокладка и монтаж сетей связи | EM45: ТСН-2001.4-10-1 | EO45: Поправка: Гл.12.Прил.8.п.8. 3_12.00.01.11.001 Поправка: Гл.4.Прил.2.2.п.2.2.29_04.00.01.35.003 | EQ45: 0 | ER45: 21.3 | ES45: 2.34 | ET45: 0.02 | EU45: 0 | EV45: 18.94 | EW45: 1.36 | EX45: 0 | EY45: 0 | FQ45: 0 | FR45: 0 | FS45: 0 | FX45: 90 | FY45: 46 | GD45: 1 | GF45: 1815428302 | GG45: 2 | GH45: 1 | GI45: 2 | GJ45: 0 | GK45: 0 | GL45: =ROUND(IF(AND(BH45=3,BI45=3,FS45<>0),P45,0),2) -> 0 | GM45: =ROUND(O45+X45+Y45,2)+GX45 -> 949.64 | GN45: =IF(OR(BI45=0,BI45=1),GM45-GX45,0) -> 0 | GO45: =IF(BI45=2,GM45-GX45,0) -> 949.64 | GP45: =IF(BI45=4,GM45-GX45,0) -> 0 | GR45: 0 | GS45: 3 | GT45: 0 | GV45: =ROUND((GT45),6) -> 0 | GW45: 1 | GX45: =ROUND(HC45*I45,2) -> 0 | HA45: 0 | HB45: 0 | HC45: =GV45*GW45 -> 0 | HS45: 0 | IK45: 0
A46: 17 | B46: 1 | C46: =ROW(SmtRes!A116) -> 116 | D46: =ROW(EtalonRes!A153) -> 153 | E46: 10 | F46: 4.8-240-4 | G46: Монтаж пультов и шкафов управления, шкафа (пульта) управления навесного, высотой, шириной, глубиной до 600х600х350 мм / демонтаж щитов | H46: 1 ШТ. | I46: =ROUND(1+1+4+2+1+2+2+43+1+8+20+1+1+1+2+1+3,9) -> 94 | J46: 0 | K46: =ROUND(1+1+4+2+1+2+2+43+1+8+20+1+1+1+2+1+3,9) -> 94 | O46: =ROUND(CP46,2) -> 1565.32 | P46: =ROUND((ROUND((AC46*AW46*I46),2)*BC46),2) -> 0 | Q46: =(ROUND((ROUND(((((ET46*1.2)*0.3))*AV46*I46),2)*BB46),2)+ROUND((ROUND(((AE46-(((EU46*1.2)*0.3)))*AV46*I46),2)*BS46),2)) -> 617.2 | R46: =(ROUND((ROUND(((((EU46*1.2)*0.3))*AV46*I46),2)*BS46),2)+ROUND((ROUND(((AE46-(((EU46*1.2)*0.3)))*AV46*I46),2)*BS46),2)) -> 111.96 | S46: =ROUND((ROUND((AF46*AV46*I46),2)*BA46),2) -> 948.12 | T46: =ROUND(CU46*I46,2) -> 0 | U46: =CV46*I46 -> 72.986789 | V46: =CW46*I46 -> 0 | W46: =ROUND(CX46*I46,2) -> 0 | X46: =(ROUND((((S46+ROUND((ROUND(((((EU46*1.2)*0.3))*AV46*I46),2)*BS46),2))*AT46)/100),2)+ROUND(((ROUND((ROUND(((AE46-(((EU46*1.2)*0.3)))*AV46*I46),2)*BS46),2)*AT46)/100),2)) -> 1028.28 | Y46: =(ROUND((((S46+ROUND((ROUND(((((EU46*1.2)*0.3))*AV46*I46),2)*BS46),2))*AU46)/100),2)+ROUND(((ROUND((ROUND(((AE46-(((EU46*1.2)*0.3)))*AV46*I46),2)*BS46),2)*AU46)/100),2)) -> 540.64 | AA46: 55944368 | AB46: =ROUND((AC46+AD46+AF46),6) -> 15.9048 | AC46: =ROUND((((ES46*1)*0)),6) -> 0 | AD46: =ROUND((((((ET46*1.2)*0.3))-(((EU46*1.2)*0.3)))+AE46),6) -> 6.2712 | AE46: =ROUND((((EU46*1.2)*0.3)),6) -> 1.1376 | AF46: =ROUND((((EV46*1.2)*0.3)),6) -> 9.6336 | AG46: =ROUND((AP46),6) -> 0 | AH46: =(((EW46*1.2)*0.3)) -> 0.7416 | AI46: =(((EX46*1.2)*0.3)) -> 0 | AJ46: =(AS46) -> 0 | AK46: 45.64 | AL46: 1.46 | AM46: 17.42 | AN46: 3.16 | AO46: 26.76 | AP46: 0 | AQ46: 2.06 | AR46: 0 | AS46: 0 | AT46: 97 | AU46: 51 | AV46: 1.047 | AW46: 1 | AZ46: 1 | BA46: 1 | BB46: 1 | BC46: 1 | BH46: 0 | BI46: 2 | BJ46: ТСН-2001.4 Доп. 80, Сб. 8, т. 240, поз. 4 | BM46: 67 | BN46: 0 | BO46: 4.8-240-4 | BP46: 1 | BQ46: 40 | BR46: 0 | BS46: 1 | BT46: 1 | BU46: 1 | BV46: 1 | BW46: 1 | BX46: 1 | BZ46: 97 | CA46: 51 | CE46: 1566 | CF46: 0 | CG46: 0 | CM46: 0 | CN46: Поправка: Гл.12.Прил.8.п.8. 3_12.00.01.11.001 Наименование: При наличии напряженных и стесненных условий производства работ (стесненность, сложность складирования и транспортной логистики и т.п.) для объектов, расположенных в пределах круговой магистральной системы улиц "Садовое кольцо" города Москвы Поправка: Гл.4.Прил.2.2.п.2.2.29_04.00.01.35.003 Наименование: При демонтаже оборудования, предназначенного в лом | CO46: 0 | CP46: =(P46+Q46+S46) -> 1565.32 | CQ46: =ROUND((ROUND((AC46*AW46*1),2)*BC46),2) -> 0 | CR46: =(ROUND((ROUND(((((ET46*1.2)*0.3))*AV46*1),2)*BB46),2)+ROUND((ROUND(((AE46-(((EU46*1.2)*0.3)))*AV46*1),2)*BS46),2)) -> 6.57 | CS46: =(ROUND((ROUND(((((EU46*1.2)*0.3))*AV46*1),2)*BS46),2)+ROUND((ROUND(((AE46-(((EU46*1.2)*0.3)))*AV46*1),2)*BS46),2)) -> 1.19 | CT46: =ROUND((ROUND((AF46*AV46*1),2)*BA46),2) -> 10.09 | CU46: =AG46 -> 0 | CV46: =(AH46*AV46) -> 0.7764552 | CW46: =AI46 -> 0 | CX46: =AJ46 -> 0 | CY46: =(ROUND((((S46+ROUND((ROUND(((((EU46*1.2)*0.3))*AV46*1),2)*BS46),2))*AT46)/100),2)+ROUND(((ROUND((ROUND(((AE46-(((EU46*1.2)*0.3)))*AV46*1),2)*BS46),2)*AT46)/100),2)) -> 920.83 | CZ46: =(ROUND((((S46+ROUND((ROUND(((((EU46*1.2)*0.3))*AV46*1),2)*BS46),2))*AU46)/100),2)+ROUND(((ROUND((ROUND(((AE46-(((EU46*1.2)*0.3)))*AV46*1),2)*BS46),2)*AU46)/100),2)) -> 484.15 | DB46: 37 | DD46: *1)*0 | DE46: *1,2)*0,3 | DF46: *1,2)*0,3 | DG46: *1,2)*0,3 | DI46: *1,2)*0,3 | DJ46: *1,2)*0,3 | DN46: 0 | DO46: 0 | DP46: 1 | DQ46: 1 | DU46: 1013 | DV46: 1 ШТ. | DW46: 1 ШТ. | DX46: 1 | EE46: 55393971 | EF46: 40 | EG46: Монтаж оборудования | EH46: 0 | EJ46: 2 | EK46: 67 | EL46: ТСН-2001.4-8. Электротехнические установки | EM46: ТСН-2001.4-8-1 | EO46: Поправка: Гл.12.Прил.8.п.8. 3_12.00.01.11.001 Поправка: Гл.4.Прил.2.2.п.2.2.29_04.00.01.35.003 | EQ46: 0 | ER46: 45.64 | ES46: 1.46 | ET46: 17.42 | EU46: 3.16 | EV46: 26.76 | EW46: 2.06 | EX46: 0 | EY46: 0 | FQ46: 0 | FR46: 0 | FS46: 0 | FX46: 97 | FY46: 51 | GD46: 1 | GF46: 1181136527 | GG46: 2 | GH46: 1 | GI46: 2 | GJ46: 0 | GK46: 0 | GL46: =ROUND(IF(AND(BH46=3,BI46=3,FS46<>0),P46,0),2) -> 0 | GM46: =ROUND(O46+X46+Y46,2)+GX46 -> 3134.24 | GN46: =IF(OR(BI46=0,BI46=1),GM46-GX46,0) -> 0 | GO46: =IF(BI46=2,GM46-GX46,0) -> 3134.24 | GP46: =IF(BI46=4,GM46-GX46,0) -> 0 | GR46: 0 | GS46: 3 | GT46: 0 | GV46: =ROUND((GT46),6) -> 0 | GW46: 1 | GX46: =ROUND(HC46*I46,2) -> 0 | HA46: 0 | HB46: 0 | HC46: =GV46*GW46 -> 0 | HS46: 0 | IK46: 0
A47: 17 | B47: 1 | C47: =ROW(SmtRes!A124) -> 124 | D47: =ROW(EtalonRes!A162) -> 162 | E47: 10 | F47: 4.8-240-4 | G47: Монтаж пультов и шкафов управления, шкафа (пульта) управления навесного, высотой, шириной, глубиной до 600х600х350 мм / демонтаж щитов | H47: 1 ШТ. | I47: =ROUND(1+1+4+2+1+2+2+43+1+8+20+1+1+1+2+1+3,9) -> 94 | J47: 0 | K47: =ROUND(1+1+4+2+1+2+2+43+1+8+20+1+1+1+2+1+3,9) -> 94 | O47: =ROUND(CP47,2) -> 65702.67 | P47: =ROUND((ROUND((AC47*AW47*I47),2)*BC47),2) -> 0 | Q47: =(ROUND((ROUND(((((ET47*1.2)*0.3))*AV47*I47),2)*BB47),2)+ROUND((ROUND(((AE47-(((EU47*1.2)*0.3)))*AV47*I47),2)*BS47),2)) -> 12276.11 | R47: =(ROUND((ROUND(((((EU47*1.2)*0.3))*AV47*I47),2)*BS47),2)+ROUND((ROUND(((AE47-(((EU47*1.2)*0.3)))*AV47*I47),2)*BS47),2)) -> 6308.95 | S47: =ROUND((ROUND((AF47*AV47*I47),2)*BA47),2) -> 53426.56 | T47: =ROUND(CU47*I47,2) -> 0 | U47: =CV47*I47 -> 72.986789 | V47: =CW47*I47 -> 0 | W47: =ROUND(CX47*I47,2) -> 0 | X47: =(ROUND((((S47+ROUND((ROUND(((((EU47*1.2)*0.3))*AV47*I47),2)*BS47),2))*AT47)/100),2)+ROUND(((ROUND((ROUND(((AE47-(((EU47*1.2)*0.3)))*AV47*I47),2)*BS47),2)*AT47)/100),2)) -> 57943.44 | Y47: =(ROUND((((S47+ROUND((ROUND(((((EU47*1.2)*0.3))*AV47*I47),2)*BS47),2))*AU47)/100),2)+ROUND(((ROUND((ROUND(((AE47-(((EU47*1.2)*0.3)))*AV47*I47),2)*BS47),2)*AU47)/100),2)) -> 30465.11 | AA47: 55944370 | AB47: =ROUND((AC47+AD47+AF47),6) -> 15.9048 | AC47: =ROUND((((ES47*1)*0)),6) -> 0 | AD47: =ROUND((((((ET47*1.2)*0.3))-(((EU47*1.2)*0.3)))+AE47),6) -> 6.2712 | AE47: =ROUND((((EU47*1.2)*0.3)),6) -> 1.1376 | AF47: =ROUND((((EV47*1.2)*0.3)),6) -> 9.6336 | AG47: =ROUND((AP47),6) -> 0 | AH47: =(((EW47*1.2)*0.3)) -> 0.7416 | AI47: =(((EX47*1.2)*0.3)) -> 0 | AJ47: =(AS47) -> 0 | AK47: 45.64 | AL47: 1.46 | AM47: 17.42 | AN47: 3.16 | AO47: 26.76 | AP47: 0 | AQ47: 2.06 | AR47: 0 | AS47: 0 | AT47: 97 | AU47: 51 | AV47: 1.047 | AW47: 1 | AZ47: 1 | BA47: 56.35 | BB47: 19.89 | BC47: 11.05 | BH47: 0 | BI47: 2 | BJ47: ТСН-2001.4 Доп. 80, Сб. 8, т. 240, поз. 4 | BM47: 67 | BN47: 0 | BO47: 4.8-240-4 | BP47: 1 | BQ47: 40 | BR47: 0 | BS47: 56.35 | BT47: 1 | BU47: 1 | BV47: 1 | BW47: 1 | BX47: 1 | BZ47: 97 | CA47: 51 | CE47: 1566 | CF47: 0 | CG47: 0 | CM47: 0 | CN47: Поправка: Гл.12.Прил.8.п.8. 3_12.00.01.11.001 Наименование: При наличии напряженных и стесненных условий производства работ (стесненность, сложность складирования и транспортной логистики и т.п.) для объектов, расположенных в пределах круговой магистральной системы улиц "Садовое кольцо" города Москвы Поправка: Гл.4.Прил.2.2.п.2.2.29_04.00.01.35.003 Наименование: При демонтаже оборудования, предназначенного в лом | CO47: 0 | CP47: =(P47+Q47+S47) -> 65702.67 | CQ47: =ROUND((ROUND((AC47*AW47*1),2)*BC47),2) -> 0 | CR47: =(ROUND((ROUND(((((ET47*1.2)*0.3))*AV47*1),2)*BB47),2)+ROUND((ROUND(((AE47-(((EU47*1.2)*0.3)))*AV47*1),2)*BS47),2)) -> 130.68 | CS47: =(ROUND((ROUND(((((EU47*1.2)*0.3))*AV47*1),2)*BS47),2)+ROUND((ROUND(((AE47-(((EU47*1.2)*0.3)))*AV47*1),2)*BS47),2)) -> 67.06 | CT47: =ROUND((ROUND((AF47*AV47*1),2)*BA47),2) -> 568.57 | CU47: =AG47 -> 0 | CV47: =(AH47*AV47) -> 0.7764552 | CW47: =AI47 -> 0 | CX47: =AJ47 -> 0 | CY47: =(ROUND((((S47+ROUND((ROUND(((((EU47*1.2)*0.3))*AV47*1),2)*BS47),2))*AT47)/100),2)+ROUND(((ROUND((ROUND(((AE47-(((EU47*1.2)*0.3)))*AV47*1),2)*BS47),2)*AT47)/100),2)) -> 51888.81 | CZ47: =(ROUND((((S47+ROUND((ROUND(((((EU47*1.2)*0.3))*AV47*1),2)*BS47),2))*AU47)/100),2)+ROUND(((ROUND((ROUND(((AE47-(((EU47*1.2)*0.3)))*AV47*1),2)*BS47),2)*AU47)/100),2)) -> 27281.75 | DB47: 39 | DD47: *1)*0 | DE47: *1,2)*0,3 | DF47: *1,2)*0,3 | DG47: *1,2)*0,3 | DI47: *1,2)*0,3 | DJ47: *1,2)*0,3 | DN47: 0 | DO47: 0 | DP47: 1 | DQ47: 1 | DU47: 1013 | DV47: 1 ШТ. | DW47: 1 ШТ. | DX47: 1 | EE47: 55393971 | EF47: 40 | EG47: Монтаж оборудования | EH47: 0 | EJ47: 2 | EK47: 67 | EL47: ТСН-2001.4-8. Электротехнические установки | EM47: ТСН-2001.4-8-1 | EO47: Поправка: Гл.12.Прил.8.п.8. 3_12.00.01.11.001 Поправка: Гл.4.Прил.2.2.п.2.2.29_04.00.01.35.003 | EQ47: 0 | ER47: 45.64 | ES47: 1.46 | ET47: 17.42 | EU47: 3.16 | EV47: 26.76 | EW47: 2.06 | EX47: 0 | EY47: 0 | FQ47: 0 | FR47: 0 | FS47: 0 | FX47: 97 | FY47: 51 | GD47: 1 | GF47: 1181136527 | GG47: 2 | GH47: 1 | GI47: 2 | GJ47: 0 | GK47: 0 | GL47: =ROUND(IF(AND(BH47=3,BI47=3,FS47<>0),P47,0),2) -> 0 | GM47: =ROUND(O47+X47+Y47,2)+GX47 -> 154111.22 | GN47: =IF(OR(BI47=0,BI47=1),GM47-GX47,0) -> 0 | GO47: =IF(BI47=2,GM47-GX47,0) -> 154111.22 | GP47: =IF(BI47=4,GM47-GX47,0) -> 0 | GR47: 0 | GS47: 3 | GT47: 0 | GV47: =ROUND((GT47),6) -> 0 | GW47: 1 | GX47: =ROUND(HC47*I47,2) -> 0 | HA47: 0 | HB47: 0 | HC47: =GV47*GW47 -> 0 | HS47: 0 | IK47: 0
A48: 17 | B48: 1 | C48: =ROW(SmtRes!A125) -> 125 | D48: =ROW(EtalonRes!A163) -> 163 | E48: 11 | F48: 4.10-80-3 | G48: Аппараты приемные, приборы ПС приемно-контрольные, пусковые, концентратор, блок линейный / демонтаж оборудования управления освещением | H48: 10 лучей | I48: =ROUND(6*20/10,9) -> 12 | J48: 0 | K48: =ROUND(6*20/10,9) -> 12 | O48: =ROUND(CP48,2) -> 317.79 | P48: =ROUND((ROUND((AC48*AW48*I48),2)*BC48),2) -> 0 | Q48: =(ROUND((ROUND(((((ET48*1.2)*0.3))*AV48*I48),2)*BB48),2)+ROUND((ROUND(((AE48-(((EU48*1.2)*0.3)))*AV48*I48),2)*BS48),2)) -> 0.27 | R48: =(ROUND((ROUND(((((EU48*1.2)*0.3))*AV48*I48),2)*BS48),2)+ROUND((ROUND(((AE48-(((EU48*1.2)*0.3)))*AV48*I48),2)*BS48),2)) -> 0.05 | S48: =ROUND((ROUND((AF48*AV48*I48),2)*BA48),2) -> 317.52 | T48: =ROUND(CU48*I48,2) -> 0 | U48: =CV48*I48 -> 24.424416 | V48: =CW48*I48 -> 0 | W48: =ROUND(CX48*I48,2) -> 0 | X48: =(ROUND((((S48+ROUND((ROUND(((((EU48*1.2)*0.3))*AV48*I48),2)*BS48),2))*AT48)/100),2)+ROUND(((ROUND((ROUND(((AE48-(((EU48*1.2)*0.3)))*AV48*I48),2)*BS48),2)*AT48)/100),2)) -> 285.81 | Y48: =(ROUND((((S48+ROUND((ROUND(((((EU48*1.2)*0.3))*AV48*I48),2)*BS48),2))*AU48)/100),2)+ROUND(((ROUND((ROUND(((AE48-(((EU48*1.2)*0.3)))*AV48*I48),2)*BS48),2)*AU48)/100),2)) -> 146.08 | AA48: 55944368 | AB48: =ROUND((AC48+AD48+AF48),6) -> 25.2936 | AC48: =ROUND((((ES48*1)*0)),6) -> 0 | AD48: =ROUND((((((ET48*1.2)*0.3))-(((EU48*1.2)*0.3)))+AE48),6) -> 0.0216 | AE48: =ROUND((((EU48*1.2)*0.3)),6) -> 0.0036 | AF48: =ROUND((((EV48*1.2)*0.3)),6) -> 25.272 | AG48: =ROUND((AP48),6) -> 0 | AH48: =(((EW48*1.2)*0.3)) -> 1.944 | AI48: =(((EX48*1.2)*0.3)) -> 0 | AJ48: =(AS48) -> 0 | AK48: 79.29 | AL48: 9.03 | AM48: 0.06 | AN48: 0.01 | AO48: 70.2 | AP48: 0 | AQ48: 5.4 | AR48: 0 | AS48: 0 | AT48: 90 | AU48: 46 | AV48: 1.047 | AW48: 1 | AZ48: 1 | BA48: 1 | BB48: 1 | BC48: 1 | BH48: 0 | BI48: 2 | BJ48: ТСН-2001.4 Доп. 68, Сб. 10, т. 80, поз. 3 | BM48: 68 | BN48: 0 | BO48: 4.10-80-3 | BP48: 1 | BQ48: 40 | BR48: 0 | BS48: 1 | BT48: 1 | BU48: 1 | BV48: 1 | BW48: 1 | BX48: 1 | BZ48: 90 | CA48: 46 | CE48: 1566 | CF48: 0 | CG48: 0 | CM48: 0 | CN48: Поправка: Гл.12.Прил.8.п.8. 3_12.00.01.11.001 Наименование: При наличии напряженных и стесненных условий производства работ (стесненность, сложность складирования и транспортной логистики и т.п.) для объектов, расположенных в пределах круговой магистральной системы улиц "Садовое кольцо" города Москвы Поправка: Гл.4.Прил.2.2.п.2.2.29_04.00.01.35.003 Наименование: При демонтаже оборудования, предназначенного в лом | CO48: 0 | CP48: =(P48+Q48+S48) -> 317.79 | CQ48: =ROUND((ROUND((AC48*AW48*1),2)*BC48),2) -> 0 | CR48: =(ROUND((ROUND(((((ET48*1.2)*0.3))*AV48*1),2)*BB48),2)+ROUND((ROUND(((AE48-(((EU48*1.2)*0.3)))*AV48*1),2)*BS48),2)) -> 0.02 | CS48: =(ROUND((ROUND(((((EU48*1.2)*0.3))*AV48*1),2)*BS48),2)+ROUND((ROUND(((AE48-(((EU48*1.2)*0.3)))*AV48*1),2)*BS48),2)) -> 0 | CT48: =ROUND((ROUND((AF48*AV48*1),2)*BA48),2) -> 26.46 | CU48: =AG48 -> 0 | CV48: =(AH48*AV48) -> 2.035368 | CW48: =AI48 -> 0 | CX48: =AJ48 -> 0 | CY48: =(ROUND((((S48+ROUND((ROUND(((((EU48*1.2)*0.3))*AV48*1),2)*BS48),2))*AT48)/100),2)+ROUND(((ROUND((ROUND(((AE48-(((EU48*1.2)*0.3)))*AV48*1),2)*BS48),2)*AT48)/100),2)) -> 285.77 | CZ48: =(ROUND((((S48+ROUND((ROUND(((((EU48*1.2)*0.3))*AV48*1),2)*BS48),2))*AU48)/100),2)+ROUND(((ROUND((ROUND(((AE48-(((EU48*1.2)*0.3)))*AV48*1),2)*BS48),2)*AU48)/100),2)) -> 146.06 | DB48: 41 | DD48: *1)*0 | DE48: *1,2)*0,3 | DF48: *1,2)*0,3 | DG48: *1,2)*0,3 | DI48: *1,2)*0,3 | DJ48: *1,2)*0,3 | DN48: 0 | DO48: 0 | DP48: 1 | DQ48: 1 | DU48: 1013 | DV48: 10 лучей | DW48: 10 лучей | DX48: 1 | EE48: 55393972 | EF48: 40 | EG48: Монтаж оборудования | EH48: 0 | EJ48: 2 | EK48: 68 | EL48: ТСН-2001.4-10. Прокладка и монтаж сетей связи | EM48: ТСН-2001.4-10-1 | EO48: Поправка: Гл.12.Прил.8.п.8. 3_12.00.01.11.001 Поправка: Гл.4.Прил.2.2.п.2.2.29_04.00.01.35.003 | EQ48: 0 | ER48: 79.29 | ES48: 9.03 | ET48: 0.06 | EU48: 0.01 | EV48: 70.2 | EW48: 5.4 | EX48: 0 | EY48: 0 | FQ48: 0 | FR48: 0 | FS48: 0 | FX48: 90 | FY48: 46 | GD48: 1 | GF48: 916812127 | GG48: 2 | GH48: 1 | GI48: 2 | GJ48: 0 | GK48: 0 | GL48: =ROUND(IF(AND(BH48=3,BI48=3,FS48<>0),P48,0),2) -> 0 | GM48: =ROUND(O48+X48+Y48,2)+GX48 -> 749.68 | GN48: =IF(OR(BI48=0,BI48=1),GM48-GX48,0) -> 0 | GO48: =IF(BI48=2,GM48-GX48,0) -> 749.68 | GP48: =IF(BI48=4,GM48-GX48,0) -> 0 | GR48: 0 | GS48: 3 | GT48: 0 | GV48: =ROUND((GT48),6) -> 0 | GW48: 1 | GX48: =ROUND(HC48*I48,2) -> 0 | HA48: 0 | HB48: 0 | HC48: =GV48*GW48 -> 0 | HS48: 0 | IK48: 0
A49: 17 | B49: 1 | C49: =ROW(SmtRes!A126) -> 126 | D49: =ROW(EtalonRes!A164) -> 164 | E49: 11 | F49: 4.10-80-3 | G49: Аппараты приемные, приборы ПС приемно-контрольные, пусковые, концентратор, блок линейный / демонтаж оборудования управления освещением | H49: 10 лучей | I49: =ROUND(6*20/10,9) -> 12 | J49: 0 | K49: =ROUND(6*20/10,9) -> 12 | O49: =ROUND(CP49,2) -> 17897.25 | P49: =ROUND((ROUND((AC49*AW49*I49),2)*BC49),2) -> 0 | Q49: =(ROUND((ROUND(((((ET49*1.2)*0.3))*AV49*I49),2)*BB49),2)+ROUND((ROUND(((AE49-(((EU49*1.2)*0.3)))*AV49*I49),2)*BS49),2)) -> 5 | R49: =(ROUND((ROUND(((((EU49*1.2)*0.3))*AV49*I49),2)*BS49),2)+ROUND((ROUND(((AE49-(((EU49*1.2)*0.3)))*AV49*I49),2)*BS49),2)) -> 2.82 | S49: =ROUND((ROUND((AF49*AV49*I49),2)*BA49),2) -> 17892.25 | T49: =ROUND(CU49*I49,2) -> 0 | U49: =CV49*I49 -> 24.424416 | V49: =CW49*I49 -> 0 | W49: =ROUND(CX49*I49,2) -> 0 | X49: =(ROUND((((S49+ROUND((ROUND(((((EU49*1.2)*0.3))*AV49*I49),2)*BS49),2))*AT49)/100),2)+ROUND(((ROUND((ROUND(((AE49-(((EU49*1.2)*0.3)))*AV49*I49),2)*BS49),2)*AT49)/100),2)) -> 16105.56 | Y49: =(ROUND((((S49+ROUND((ROUND(((((EU49*1.2)*0.3))*AV49*I49),2)*BS49),2))*AU49)/100),2)+ROUND(((ROUND((ROUND(((AE49-(((EU49*1.2)*0.3)))*AV49*I49),2)*BS49),2)*AU49)/100),2)) -> 8231.73 | AA49: 55944370 | AB49: =ROUND((AC49+AD49+AF49),6) -> 25.2936 | AC49: =ROUND((((ES49*1)*0)),6) -> 0 | AD49: =ROUND((((((ET49*1.2)*0.3))-(((EU49*1.2)*0.3)))+AE49),6) -> 0.0216 | AE49: =ROUND((((EU49*1.2)*0.3)),6) -> 0.0036 | AF49: =ROUND((((EV49*1.2)*0.3)),6) -> 25.272 | AG49: =ROUND((AP49),6) -> 0 | AH49: =(((EW49*1.2)*0.3)) -> 1.944 | AI49: =(((EX49*1.2)*0.3)) -> 0 | AJ49: =(AS49) -> 0 | AK49: 79.29 | AL49: 9.03 | AM49: 0.06 | AN49: 0.01 | AO49: 70.2 | AP49: 0 | AQ49: 5.4 | AR49: 0 | AS49: 0 | AT49: 90 | AU49: 46 | AV49: 1.047 | AW49: 1 | AZ49: 1 | BA49: 56.35 | BB49: 18.5 | BC49: 9.84 | BH49: 0 | BI49: 2 | BJ49: ТСН-2001.4 Доп. 68, Сб. 10, т. 80, поз. 3 | BM49: 68 | BN49: 0 | BO49: 4.10-80-3 | BP49: 1 | BQ49: 40 | BR49: 0 | BS49: 56.35 | BT49: 1 | BU49: 1 | BV49: 1 | BW49: 1 | BX49: 1 | BZ49: 90 | CA49: 46 | CE49: 1566 | CF49: 0 | CG49: 0 | CM49: 0 | CN49: Поправка: Гл.12.Прил.8.п.8. 3_12.00.01.11.001 Наименование: При наличии напряженных и стесненных условий производства работ (стесненность, сложность складирования и транспортной логистики и т.п.) для объектов, расположенных в пределах круговой магистральной системы улиц "Садовое кольцо" города Москвы Поправка: Гл.4.Прил.2.2.п.2.2.29_04.00.01.35.003 Наименование: При демонтаже оборудования, предназначенного в лом | CO49: 0 | CP49: =(P49+Q49+S49) -> 17897.25 | CQ49: =ROUND((ROUND((AC49*AW49*1),2)*BC49),2) -> 0 | CR49: =(ROUND((ROUND(((((ET49*1.2)*0.3))*AV49*1),2)*BB49),2)+ROUND((ROUND(((AE49-(((EU49*1.2)*0.3)))*AV49*1),2)*BS49),2)) -> 0.37 | CS49: =(ROUND((ROUND(((((EU49*1.2)*0.3))*AV49*1),2)*BS49),2)+ROUND((ROUND(((AE49-(((EU49*1.2)*0.3)))*AV49*1),2)*BS49),2)) -> 0 | CT49: =ROUND((ROUND((AF49*AV49*1),2)*BA49),2) -> 1491.02 | CU49: =AG49 -> 0 | CV49: =(AH49*AV49) -> 2.035368 | CW49: =AI49 -> 0 | CX49: =AJ49 -> 0 | CY49: =(ROUND((((S49+ROUND((ROUND(((((EU49*1.2)*0.3))*AV49*1),2)*BS49),2))*AT49)/100),2)+ROUND(((ROUND((ROUND(((AE49-(((EU49*1.2)*0.3)))*AV49*1),2)*BS49),2)*AT49)/100),2)) -> 16103.03 | CZ49: =(ROUND((((S49+ROUND((ROUND(((((EU49*1.2)*0.3))*AV49*1),2)*BS49),2))*AU49)/100),2)+ROUND(((ROUND((ROUND(((AE49-(((EU49*1.2)*0.3)))*AV49*1),2)*BS49),2)*AU49)/100),2)) -> 8230.44 | DB49: 43 | DD49: *1)*0 | DE49: *1,2)*0,3 | DF49: *1,2)*0,3 | DG49: *1,2)*0,3 | DI49: *1,2)*0,3 | DJ49: *1,2)*0,3 | DN49: 0 | DO49: 0 | DP49: 1 | DQ49: 1 | DU49: 1013 | DV49: 10 лучей | DW49: 10 лучей | DX49: 1 | EE49: 55393972 | EF49: 40 | EG49: Монтаж оборудования | EH49: 0 | EJ49: 2 | EK49: 68 | EL49: ТСН-2001.4-10. Прокладка и монтаж сетей связи | EM49: ТСН-2001.4-10-1 | EO49: Поправка: Гл.12.Прил.8.п.8. 3_12.00.01.11.001 Поправка: Гл.4.Прил.2.2.п.2.2.29_04.00.01.35.003 | EQ49: 0 | ER49: 79.29 | ES49: 9.03 | ET49: 0.06 | EU49: 0.01 | EV49: 70.2 | EW49: 5.4 | EX49: 0 | EY49: 0 | FQ49: 0 | FR49: 0 | FS49: 0 | FX49: 90 | FY49: 46 | GD49: 1 | GF49: 916812127 | GG49: 2 | GH49: 1 | GI49: 2 | GJ49: 0 | GK49: 0 | GL49: =ROUND(IF(AND(BH49=3,BI49=3,FS49<>0),P49,0),2) -> 0 | GM49: =ROUND(O49+X49+Y49,2)+GX49 -> 42234.54 | GN49: =IF(OR(BI49=0,BI49=1),GM49-GX49,0) -> 0 | GO49: =IF(BI49=2,GM49-GX49,0) -> 42234.54 | GP49: =IF(BI49=4,GM49-GX49,0) -> 0 | GR49: 0 | GS49: 3 | GT49: 0 | GV49: =ROUND((GT49),6) -> 0 | GW49: 1 | GX49: =ROUND(HC49*I49,2) -> 0 | HA49: 0 | HB49: 0 | HC49: =GV49*GW49 -> 0 | HS49: 0 | IK49: 0
A50: 17 | B50: 1 | C50: =ROW(SmtRes!A127) -> 127 | D50: =ROW(EtalonRes!A165) -> 165 | E50: 12 | F50: 6.67-7-1 | G50: Демонтаж осветительных приборов, выключатели, розетки | H50: 100 шт. | I50: =ROUND(2/100,9) -> 0.02 | J50: 0 | K50: =ROUND(2/100,9) -> 0.02 | O50: =ROUND(CP50,2) -> 1.5 | P50: =ROUND((ROUND((AC50*AW50*I50),2)*BC50),2) -> 0 | Q50: =(ROUND((ROUND((((ET50*1.2))*AV50*I50),2)*BB50),2)+ROUND((ROUND(((AE50-((EU50*1.2)))*AV50*I50),2)*BS50),2)) -> 0 | R50: =(ROUND((ROUND((((EU50*1.2))*AV50*I50),2)*BS50),2)+ROUND((ROUND(((AE50-((EU50*1.2)))*AV50*I50),2)*BS50),2)) -> 0 | S50: =ROUND((ROUND((AF50*AV50*I50),2)*BA50),2) -> 1.5 | T50: =ROUND(CU50*I50,2) -> 0 | U50: =CV50*I50 -> 0.14674752 | V50: =CW50*I50 -> 0 | W50: =ROUND(CX50*I50,2) -> 0 | X50: =(ROUND((((S50+ROUND((ROUND((((EU50*1.2))*AV50*I50),2)*BS50),2))*AT50)/100),2)+ROUND(((ROUND((ROUND(((AE50-((EU50*1.2)))*AV50*I50),2)*BS50),2)*AT50)/100),2)) -> 1.37 | Y50: =(ROUND((((S50+ROUND((ROUND((((EU50*1.2))*AV50*I50),2)*BS50),2))*AU50)/100),2)+ROUND(((ROUND((ROUND(((AE50-((EU50*1.2)))*AV50*I50),2)*BS50),2)*AU50)/100),2)) -> 0.72 | AA50: 55944368 | AB50: =ROUND((AC50+AD50+AF50),6) -> 71.616 | AC50: =ROUND(((ES50*1)),6) -> 0 | AD50: =ROUND(((((ET50*1.2))-((EU50*1.2)))+AE50),6) -> 0 | AE50: =ROUND(((EU50*1.2)),6) -> 0 | AF50: =ROUND(((EV50*1.2)),6) -> 71.616 | AG50: =ROUND((AP50),6) -> 0 | AH50: =((EW50*1.2)) -> 7.008 | AI50: =((EX50*1.2)) -> 0 | AJ50: =(AS50) -> 0 | AK50: 59.68 | AL50: 0 | AM50: 0 | AN50: 0 | AO50: 59.68 | AP50: 0 | AQ50: 5.84 | AR50: 0 | AS50: 0 | AT50: 91 | AU50: 48 | AV50: 1.047 | AW50: 1 | AZ50: 1 | BA50: 1 | BB50: 1 | BC50: 1 | BH50: 0 | BI50: 1 | BJ50: ТСН-2001.6. Доп. 1-42. Сб. 67, т. 7, поз. 1 | BM50: 106 | BN50: 0 | BO50: 6.67-7-1 | BP50: 1 | BQ50: 60 | BR50: 0 | BS50: 1 | BT50: 1 | BU50: 1 | BV50: 1 | BW50: 1 | BX50: 1 | BZ50: 91 | CA50: 48 | CE50: 1566 | CF50: 0 | CG50: 0 | CM50: 0 | CN50: Поправка: Гл.12.Прил.8.п.8. 3_12.00.01.11.001 Наименование: При наличии напряженных и стесненных условий производства работ (стесненность, сложность складирования и транспортной логистики и т.п.) для объектов, расположенных в пределах круговой магистральной системы улиц "Садовое кольцо" города Москвы | CO50: 0 | CP50: =(P50+Q50+S50) -> 1.5 | CQ50: =ROUND((ROUND((AC50*AW50*1),2)*BC50),2) -> 0 | CR50: =(ROUND((ROUND((((ET50*1.2))*AV50*1),2)*BB50),2)+ROUND((ROUND(((AE50-((EU50*1.2)))*AV50*1),2)*BS50),2)) -> 0 | CS50: =(ROUND((ROUND((((EU50*1.2))*AV50*1),2)*BS50),2)+ROUND((ROUND(((AE50-((EU50*1.2)))*AV50*1),2)*BS50),2)) -> 0 | CT50: =ROUND((ROUND((AF50*AV50*1),2)*BA50),2) -> 74.98 | CU50: =AG50 -> 0 | CV50: =(AH50*AV50) -> 7.337376 | CW50: =AI50 -> 0 | CX50: =AJ50 -> 0 | CY50: =(ROUND((((S50+ROUND((ROUND((((EU50*1.2))*AV50*1),2)*BS50),2))*AT50)/100),2)+ROUND(((ROUND((ROUND(((AE50-((EU50*1.2)))*AV50*1),2)*BS50),2)*AT50)/100),2)) -> 1.37 | CZ50: =(ROUND((((S50+ROUND((ROUND((((EU50*1.2))*AV50*1),2)*BS50),2))*AU50)/100),2)+ROUND(((ROUND((ROUND(((AE50-((EU50*1.2)))*AV50*1),2)*BS50),2)*AU50)/100),2)) -> 0.72 | DB50: 45 | DD50: *1 | DE50: *1,2 | DF50: *1,2 | DG50: *1,2 | DI50: *1,2 | DJ50: *1,2 | DN50: 0 | DO50: 0 | DP50: 1 | DQ50: 1 | DU50: 1010 | DV50: 100 шт. | DW50: 100 шт. | DX50: 100 | EE50: 55394010 | EF50: 60 | EG50: Ремонтно-строительные работы | EH50: 0 | EJ50: 1 | EK50: 106 | EL50: ТСН-2001.6-67. Электромонтажные работы | EM50: ТСН-2001.6-67-1 | EO50: Поправка: Гл.12.Прил.8.п.8. 3_12.00.01.11.001 | EQ50: 0 | ER50: 59.68 | ES50: 0 | ET50: 0 | EU50: 0 | EV50: 59.68 | EW50: 5.84 | EX50: 0 | EY50: 0 | FQ50: 0 | FR50: 0 | FS50: 0 | FX50: 91 | FY50: 48 | GD50: 1 | GF50: 1478850760 | GG50: 2 | GH50: 1 | GI50: 2 | GJ50: 0 | GK50: 0 | GL50: =ROUND(IF(AND(BH50=3,BI50=3,FS50<>0),P50,0),2) -> 0 | GM50: =ROUND(O50+X50+Y50,2)+GX50 -> 3.59 | GN50: =IF(OR(BI50=0,BI50=1),GM50-GX50,0) -> 3.59 | GO50: =IF(BI50=2,GM50-GX50,0) -> 0 | GP50: =IF(BI50=4,GM50-GX50,0) -> 0 | GR50: 0 | GS50: 3 | GT50: 0 | GV50: =ROUND((GT50),6) -> 0 | GW50: 1 | GX50: =ROUND(HC50*I50,2) -> 0 | HA50: 0 | HB50: 0 | HC50: =GV50*GW50 -> 0 | HS50: 0 | IK50: 0
A51: 17 | B51: 1 | C51: =ROW(SmtRes!A128) -> 128 | D51: =ROW(EtalonRes!A166) -> 166 | E51: 12 | F51: 6.67-7-1 | G51: Демонтаж осветительных приборов, выключатели, розетки | H51: 100 шт. | I51: =ROUND(2/100,9) -> 0.02 | J51: 0 | K51: =ROUND(2/100,9) -> 0.02 | O51: =ROUND(CP51,2) -> 84.53 | P51: =ROUND((ROUND((AC51*AW51*I51),2)*BC51),2) -> 0 | Q51: =(ROUND((ROUND((((ET51*1.2))*AV51*I51),2)*BB51),2)+ROUND((ROUND(((AE51-((EU51*1.2)))*AV51*I51),2)*BS51),2)) -> 0 | R51: =(ROUND((ROUND((((EU51*1.2))*AV51*I51),2)*BS51),2)+ROUND((ROUND(((AE51-((EU51*1.2)))*AV51*I51),2)*BS51),2)) -> 0 | S51: =ROUND((ROUND((AF51*AV51*I51),2)*BA51),2) -> 84.53 | T51: =ROUND(CU51*I51,2) -> 0 | U51: =CV51*I51 -> 0.14674752 | V51: =CW51*I51 -> 0 | W51: =ROUND(CX51*I51,2) -> 0 | X51: =(ROUND((((S51+ROUND((ROUND((((EU51*1.2))*AV51*I51),2)*BS51),2))*AT51)/100),2)+ROUND(((ROUND((ROUND(((AE51-((EU51*1.2)))*AV51*I51),2)*BS51),2)*AT51)/100),2)) -> 76.92 | Y51: =(ROUND((((S51+ROUND((ROUND((((EU51*1.2))*AV51*I51),2)*BS51),2))*AU51)/100),2)+ROUND(((ROUND((ROUND(((AE51-((EU51*1.2)))*AV51*I51),2)*BS51),2)*AU51)/100),2)) -> 40.57 | AA51: 55944370 | AB51: =ROUND((AC51+AD51+AF51),6) -> 71.616 | AC51: =ROUND(((ES51*1)),6) -> 0 | AD51: =ROUND(((((ET51*1.2))-((EU51*1.2)))+AE51),6) -> 0 | AE51: =ROUND(((EU51*1.2)),6) -> 0 | AF51: =ROUND(((EV51*1.2)),6) -> 71.616 | AG51: =ROUND((AP51),6) -> 0 | AH51: =((EW51*1.2)) -> 7.008 | AI51: =((EX51*1.2)) -> 0 | AJ51: =(AS51) -> 0 | AK51: 59.68 | AL51: 0 | AM51: 0 | AN51: 0 | AO51: 59.68 | AP51: 0 | AQ51: 5.84 | AR51: 0 | AS51: 0 | AT51: 91 | AU51: 48 | AV51: 1.047 | AW51: 1 | AZ51: 1 | BA51: 56.35 | BB51: 1 | BC51: 1 | BH51: 0 | BI51: 1 | BJ51: ТСН-2001.6. Доп. 1-42. Сб. 67, т. 7, поз. 1 | BM51: 106 | BN51: 0 | BO51: 6.67-7-1 | BP51: 1 | BQ51: 60 | BR51: 0 | BS51: 56.35 | BT51: 1 | BU51: 1 | BV51: 1 | BW51: 1 | BX51: 1 | BZ51: 91 | CA51: 48 | CE51: 1566 | CF51: 0 | CG51: 0 | CM51: 0 | CN51: Поправка: Гл.12.Прил.8.п.8. 3_12.00.01.11.001 Наименование: При наличии напряженных и стесненных условий производства работ (стесненность, сложность складирования и транспортной логистики и т.п.) для объектов, расположенных в пределах круговой магистральной системы улиц "Садовое кольцо" города Москвы | CO51: 0 | CP51: =(P51+Q51+S51) -> 84.53 | CQ51: =ROUND((ROUND((AC51*AW51*1),2)*BC51),2) -> 0 | CR51: =(ROUND((ROUND((((ET51*1.2))*AV51*1),2)*BB51),2)+ROUND((ROUND(((AE51-((EU51*1.2)))*AV51*1),2)*BS51),2)) -> 0 | CS51: =(ROUND((ROUND((((EU51*1.2))*AV51*1),2)*BS51),2)+ROUND((ROUND(((AE51-((EU51*1.2)))*AV51*1),2)*BS51),2)) -> 0 | CT51: =ROUND((ROUND((AF51*AV51*1),2)*BA51),2) -> 4225.12 | CU51: =AG51 -> 0 | CV51: =(AH51*AV51) -> 7.337376 | CW51: =AI51 -> 0 | CX51: =AJ51 -> 0 | CY51: =(ROUND((((S51+ROUND((ROUND((((EU51*1.2))*AV51*1),2)*BS51),2))*AT51)/100),2)+ROUND(((ROUND((ROUND(((AE51-((EU51*1.2)))*AV51*1),2)*BS51),2)*AT51)/100),2)) -> 76.92 | CZ51: =(ROUND((((S51+ROUND((ROUND((((EU51*1.2))*AV51*1),2)*BS51),2))*AU51)/100),2)+ROUND(((ROUND((ROUND(((AE51-((EU51*1.2)))*AV51*1),2)*BS51),2)*AU51)/100),2)) -> 40.57 | DB51: 46 | DD51: *1 | DE51: *1,2 | DF51: *1,2 | DG51: *1,2 | DI51: *1,2 | DJ51: *1,2 | DN51: 0 | DO51: 0 | DP51: 1 | DQ51: 1 | DU51: 1010 | DV51: 100 шт. | DW51: 100 шт. | DX51: 100 | EE51: 55394010 | EF51: 60 | EG51: Ремонтно-строительные работы | EH51: 0 | EJ51: 1 | EK51: 106 | EL51: ТСН-2001.6-67. Электромонтажные работы | EM51: ТСН-2001.6-67-1 | EO51: Поправка: Гл.12.Прил.8.п.8. 3_12.00.01.11.001 | EQ51: 0 | ER51: 59.68 | ES51: 0 | ET51: 0 | EU51: 0 | EV51: 59.68 | EW51: 5.84 | EX51: 0 | EY51: 0 | FQ51: 0 | FR51: 0 | FS51: 0 | FX51: 91 | FY51: 48 | GD51: 1 | GF51: 1478850760 | GG51: 2 | GH51: 1 | GI51: 2 | GJ51: 0 | GK51: 0 | GL51: =ROUND(IF(AND(BH51=3,BI51=3,FS51<>0),P51,0),2) -> 0 | GM51: =ROUND(O51+X51+Y51,2)+GX51 -> 202.02 | GN51: =IF(OR(BI51=0,BI51=1),GM51-GX51,0) -> 202.02 | GO51: =IF(BI51=2,GM51-GX51,0) -> 0 | GP51: =IF(BI51=4,GM51-GX51,0) -> 0 | GR51: 0 | GS51: 3 | GT51: 0 | GV51: =ROUND((GT51),6) -> 0 | GW51: 1 | GX51: =ROUND(HC51*I51,2) -> 0 | HA51: 0 | HB51: 0 | HC51: =GV51*GW51 -> 0 | HS51: 0 | IK51: 0
A52: 17 | B52: 1 | C52: =ROW(SmtRes!A130) -> 130 | D52: =ROW(EtalonRes!A170) -> 170 | E52: 13 | F52: 4.11-2-3 | G52: Установка преобразователя электрического многозонного / демонтаж частотных преобразователей | H52: 1 ШТ. | I52: =ROUND(11+5+7+1,9) -> 24 | J52: 0 | K52: =ROUND(11+5+7+1,9) -> 24 | O52: =ROUND(CP52,2) -> 242.07 | P52: =ROUND((ROUND((AC52*AW52*I52),2)*BC52),2) -> 0 | Q52: =(ROUND((ROUND(((((ET52*1.2)*0.3))*AV52*I52),2)*BB52),2)+ROUND((ROUND(((AE52-(((EU52*1.2)*0.3)))*AV52*I52),2)*BS52),2)) -> 0 | R52: =(ROUND((ROUND(((((EU52*1.2)*0.3))*AV52*I52),2)*BS52),2)+ROUND((ROUND(((AE52-(((EU52*1.2)*0.3)))*AV52*I52),2)*BS52),2)) -> 0 | S52: =ROUND((ROUND((AF52*AV52*I52),2)*BA52),2) -> 242.07 | T52: =ROUND(CU52*I52,2) -> 0 | U52: =CV52*I52 -> 18.634925 | V52: =CW52*I52 -> 0 | W52: =ROUND(CX52*I52,2) -> 0 | X52: =(ROUND((((S52+ROUND((ROUND(((((EU52*1.2)*0.3))*AV52*I52),2)*BS52),2))*AT52)/100),2)+ROUND(((ROUND((ROUND(((AE52-(((EU52*1.2)*0.3)))*AV52*I52),2)*BS52),2)*AT52)/100),2)) -> 217.86 | Y52: =(ROUND((((S52+ROUND((ROUND(((((EU52*1.2)*0.3))*AV52*I52),2)*BS52),2))*AU52)/100),2)+ROUND(((ROUND((ROUND(((AE52-(((EU52*1.2)*0.3)))*AV52*I52),2)*BS52),2)*AU52)/100),2)) -> 111.35 | AA52: 55944368 | AB52: =ROUND((AC52+AD52+AF52),6) -> 9.6336 | AC52: =ROUND((((ES52*1)*0)),6) -> 0 | AD52: =ROUND((((((ET52*1.2)*0.3))-(((EU52*1.2)*0.3)))+AE52),6) -> 0 | AE52: =ROUND((((EU52*1.2)*0.3)),6) -> 0 | AF52: =ROUND((((EV52*1.2)*0.3)),6) -> 9.6336 | AG52: =ROUND((AP52),6) -> 0 | AH52: =(((EW52*1.2)*0.3)) -> 0.7416 | AI52: =(((EX52*1.2)*0.3)) -> 0 | AJ52: =(AS52) -> 0 | AK52: 26.76 | AL52: 0 | AM52: 0 | AN52: 0 | AO52: 26.76 | AP52: 0 | AQ52: 2.06 | AR52: 0 | AS52: 0 | AT52: 90 | AU52: 46 | AV52: 1.047 | AW52: 1 | AZ52: 1 | BA52: 1 | BB52: 1 | BC52: 1 | BH52: 0 | BI52: 2 | BJ52: ТСН-2001.4 Доп. 67, Сб. 11, т. 2, поз. 3 | BM52: 72 | BN52: 0 | BO52: 4.11-2-3 | BP52: 1 | BQ52: 40 | BR52: 0 | BS52: 1 | BT52: 1 | BU52: 1 | BV52: 1 | BW52: 1 | BX52: 1 | BZ52: 90 | CA52: 46 | CE52: 1566 | CF52: 0 | CG52: 0 | CM52: 0 | CN52: Поправка: Гл.12.Прил.8.п.8. 3_12.00.01.11.001 Наименование: При наличии напряженных и стесненных условий производства работ (стесненность, сложность складирования и транспортной логистики и т.п.) для объектов, расположенных в пределах круговой магистральной системы улиц "Садовое кольцо" города Москвы Поправка: Гл.4.Прил.2.2.п.2.2.29_04.00.01.35.003 Наименование: При демонтаже оборудования, предназначенного в лом | CO52: 0 | CP52: =(P52+Q52+S52) -> 242.07 | CQ52: =ROUND((ROUND((AC52*AW52*1),2)*BC52),2) -> 0 | CR52: =(ROUND((ROUND(((((ET52*1.2)*0.3))*AV52*1),2)*BB52),2)+ROUND((ROUND(((AE52-(((EU52*1.2)*0.3)))*AV52*1),2)*BS52),2)) -> 0 | CS52: =(ROUND((ROUND(((((EU52*1.2)*0.3))*AV52*1),2)*BS52),2)+ROUND((ROUND(((AE52-(((EU52*1.2)*0.3)))*AV52*1),2)*BS52),2)) -> 0 | CT52: =ROUND((ROUND((AF52*AV52*1),2)*BA52),2) -> 10.09 | CU52: =AG52 -> 0 | CV52: =(AH52*AV52) -> 0.7764552 | CW52: =AI52 -> 0 | CX52: =AJ52 -> 0 | CY52: =(ROUND((((S52+ROUND((ROUND(((((EU52*1.2)*0.3))*AV52*1),2)*BS52),2))*AT52)/100),2)+ROUND(((ROUND((ROUND(((AE52-(((EU52*1.2)*0.3)))*AV52*1),2)*BS52),2)*AT52)/100),2)) -> 217.86 | CZ52: =(ROUND((((S52+ROUND((ROUND(((((EU52*1.2)*0.3))*AV52*1),2)*BS52),2))*AU52)/100),2)+ROUND(((ROUND((ROUND(((AE52-(((EU52*1.2)*0.3)))*AV52*1),2)*BS52),2)*AU52)/100),2)) -> 111.35 | DB52: 47 | DD52: *1)*0 | DE52: *1,2)*0,3 | DF52: *1,2)*0,3 | DG52: *1,2)*0,3 | DI52: *1,2)*0,3 | DJ52: *1,2)*0,3 | DN52: 0 | DO52: 0 | DP52: 1 | DQ52: 1 | DU52: 1013 | DV52: 1 ШТ. | DW52: 1 ШТ. | DX52: 1 | EE52: 55393976 | EF52: 40 | EG52: Монтаж оборудования | EH52: 0 | EJ52: 2 | EK52: 72 | EL52: ТСН-2001.4-11. Приборы и средства автоматизации и вычислительной техники | EM52: ТСН-2001.4-11-1 | EO52: Поправка: Гл.12.Прил.8.п.8. 3_12.00.01.11.001 Поправка: Гл.4.Прил.2.2.п.2.2.29_04.00.01.35.003 | EQ52: 0 | ER52: 26.76 | ES52: 0 | ET52: 0 | EU52: 0 | EV52: 26.76 | EW52: 2.06 | EX52: 0 | EY52: 0 | FQ52: 0 | FR52: 0 | FS52: 0 | FX52: 90 | FY52: 46 | GD52: 1 | GF52: 511010036 | GG52: 2 | GH52: 1 | GI52: 2 | GJ52: 0 | GK52: 0 | GL52: =ROUND(IF(AND(BH52=3,BI52=3,FS52<>0),P52,0),2) -> 0 | GM52: =ROUND(O52+X52+Y52,2)+GX52 -> 571.28 | GN52: =IF(OR(BI52=0,BI52=1),GM52-GX52,0) -> 0 | GO52: =IF(BI52=2,GM52-GX52,0) -> 571.28 | GP52: =IF(BI52=4,GM52-GX52,0) -> 0 | GR52: 0 | GS52: 3 | GT52: 0 | GV52: =ROUND((GT52),6) -> 0 | GW52: 1 | GX52: =ROUND(HC52*I52,2) -> 0 | HA52: 0 | HB52: 0 | HC52: =GV52*GW52 -> 0 | HS52: 0 | IK52: 0
A53: 17 | B53: 1 | C53: =ROW(SmtRes!A132) -> 132 | D53: =ROW(EtalonRes!A174) -> 174 | E53: 13 | F53: 4.11-2-3 | G53: Установка преобразователя электрического многозонного / демонтаж частотных преобразователей | H53: 1 ШТ. | I53: =ROUND(11+5+7+1,9) -> 24 | J53: 0 | K53: =ROUND(11+5+7+1,9) -> 24 | O53: =ROUND(CP53,2) -> 13640.64 | P53: =ROUND((ROUND((AC53*AW53*I53),2)*BC53),2) -> 0 | Q53: =(ROUND((ROUND(((((ET53*1.2)*0.3))*AV53*I53),2)*BB53),2)+ROUND((ROUND(((AE53-(((EU53*1.2)*0.3)))*AV53*I53),2)*BS53),2)) -> 0 | R53: =(ROUND((ROUND(((((EU53*1.2)*0.3))*AV53*I53),2)*BS53),2)+ROUND((ROUND(((AE53-(((EU53*1.2)*0.3)))*AV53*I53),2)*BS53),2)) -> 0 | S53: =ROUND((ROUND((AF53*AV53*I53),2)*BA53),2) -> 13640.64 | T53: =ROUND(CU53*I53,2) -> 0 | U53: =CV53*I53 -> 18.634925 | V53: =CW53*I53 -> 0 | W53: =ROUND(CX53*I53,2) -> 0 | X53: =(ROUND((((S53+ROUND((ROUND(((((EU53*1.2)*0.3))*AV53*I53),2)*BS53),2))*AT53)/100),2)+ROUND(((ROUND((ROUND(((AE53-(((EU53*1.2)*0.3)))*AV53*I53),2)*BS53),2)*AT53)/100),2)) -> 12276.58 | Y53: =(ROUND((((S53+ROUND((ROUND(((((EU53*1.2)*0.3))*AV53*I53),2)*BS53),2))*AU53)/100),2)+ROUND(((ROUND((ROUND(((AE53-(((EU53*1.2)*0.3)))*AV53*I53),2)*BS53),2)*AU53)/100),2)) -> 6274.69 | AA53: 55944370 | AB53: =ROUND((AC53+AD53+AF53),6) -> 9.6336 | AC53: =ROUND((((ES53*1)*0)),6) -> 0 | AD53: =ROUND((((((ET53*1.2)*0.3))-(((EU53*1.2)*0.3)))+AE53),6) -> 0 | AE53: =ROUND((((EU53*1.2)*0.3)),6) -> 0 | AF53: =ROUND((((EV53*1.2)*0.3)),6) -> 9.6336 | AG53: =ROUND((AP53),6) -> 0 | AH53: =(((EW53*1.2)*0.3)) -> 0.7416 | AI53: =(((EX53*1.2)*0.3)) -> 0 | AJ53: =(AS53) -> 0 | AK53: 26.76 | AL53: 0 | AM53: 0 | AN53: 0 | AO53: 26.76 | AP53: 0 | AQ53: 2.06 | AR53: 0 | AS53: 0 | AT53: 90 | AU53: 46 | AV53: 1.047 | AW53: 1 | AZ53: 1 | BA53: 56.35 | BB53: 1 | BC53: 1 | BH53: 0 | BI53: 2 | BJ53: ТСН-2001.4 Доп. 67, Сб. 11, т. 2, поз. 3 | BM53: 72 | BN53: 0 | BO53: 4.11-2-3 | BP53: 1 | BQ53: 40 | BR53: 0 | BS53: 56.35 | BT53: 1 | BU53: 1 | BV53: 1 | BW53: 1 | BX53: 1 | BZ53: 90 | CA53: 46 | CE53: 1566 | CF53: 0 | CG53: 0 | CM53: 0 | CN53: Поправка: Гл.12.Прил.8.п.8. 3_12.00.01.11.001 Наименование: При наличии напряженных и стесненных условий производства работ (стесненность, сложность складирования и транспортной логистики и т.п.) для объектов, расположенных в пределах круговой магистральной системы улиц "Садовое кольцо" города Москвы Поправка: Гл.4.Прил.2.2.п.2.2.29_04.00.01.35.003 Наименование: При демонтаже оборудования, предназначенного в лом | CO53: 0 | CP53: =(P53+Q53+S53) -> 13640.64 | CQ53: =ROUND((ROUND((AC53*AW53*1),2)*BC53),2) -> 0 | CR53: =(ROUND((ROUND(((((ET53*1.2)*0.3))*AV53*1),2)*BB53),2)+ROUND((ROUND(((AE53-(((EU53*1.2)*0.3)))*AV53*1),2)*BS53),2)) -> 0 | CS53: =(ROUND((ROUND(((((EU53*1.2)*0.3))*AV53*1),2)*BS53),2)+ROUND((ROUND(((AE53-(((EU53*1.2)*0.3)))*AV53*1),2)*BS53),2)) -> 0 | CT53: =ROUND((ROUND((AF53*AV53*1),2)*BA53),2) -> 568.57 | CU53: =AG53 -> 0 | CV53: =(AH53*AV53) -> 0.7764552 | CW53: =AI53 -> 0 | CX53: =AJ53 -> 0 | CY53: =(ROUND((((S53+ROUND((ROUND(((((EU53*1.2)*0.3))*AV53*1),2)*BS53),2))*AT53)/100),2)+ROUND(((ROUND((ROUND(((AE53-(((EU53*1.2)*0.3)))*AV53*1),2)*BS53),2)*AT53)/100),2)) -> 12276.58 | CZ53: =(ROUND((((S53+ROUND((ROUND(((((EU53*1.2)*0.3))*AV53*1),2)*BS53),2))*AU53)/100),2)+ROUND(((ROUND((ROUND(((AE53-(((EU53*1.2)*0.3)))*AV53*1),2)*BS53),2)*AU53)/100),2)) -> 6274.69 | DB53: 49 | DD53: *1)*0 | DE53: *1,2)*0,3 | DF53: *1,2)*0,3 | DG53: *1,2)*0,3 | DI53: *1,2)*0,3 | DJ53: *1,2)*0,3 | DN53: 0 | DO53: 0 | DP53: 1 | DQ53: 1 | DU53: 1013 | DV53: 1 ШТ. | DW53: 1 ШТ. | DX53: 1 | EE53: 55393976 | EF53: 40 | EG53: Монтаж оборудования | EH53: 0 | EJ53: 2 | EK53: 72 | EL53: ТСН-2001.4-11. Приборы и средства автоматизации и вычислительной техники | EM53: ТСН-2001.4-11-1 | EO53: Поправка: Гл.12.Прил.8.п.8. 3_12.00.01.11.001 Поправка: Гл.4.Прил.2.2.п.2.2.29_04.00.01.35.003 | EQ53: 0 | ER53: 26.76 | ES53: 0 | ET53: 0 | EU53: 0 | EV53: 26.76 | EW53: 2.06 | EX53: 0 | EY53: 0 | FQ53: 0 | FR53: 0 | FS53: 0 | FX53: 90 | FY53: 46 | GD53: 1 | GF53: 511010036 | GG53: 2 | GH53: 1 | GI53: 2 | GJ53: 0 | GK53: 0 | GL53: =ROUND(IF(AND(BH53=3,BI53=3,FS53<>0),P53,0),2) -> 0 | GM53: =ROUND(O53+X53+Y53,2)+GX53 -> 32191.91 | GN53: =IF(OR(BI53=0,BI53=1),GM53-GX53,0) -> 0 | GO53: =IF(BI53=2,GM53-GX53,0) -> 32191.91 | GP53: =IF(BI53=4,GM53-GX53,0) -> 0 | GR53: 0 | GS53: 3 | GT53: 0 | GV53: =ROUND((GT53),6) -> 0 | GW53: 1 | GX53: =ROUND(HC53*I53,2) -> 0 | HA53: 0 | HB53: 0 | HC53: =GV53*GW53 -> 0 | HS53: 0 | IK53: 0
A54: 17 | B54: 1 | C54: =ROW(SmtRes!A133) -> 133 | D54: =ROW(EtalonRes!A177) -> 177 | E54: 14 | F54: 4.11-3-1 | G54: Установка прибора массой до 5 кг на металлоконструкциях или щитах / демонтаж регуляторов скорости и выносных пультов | H54: 1 ШТ. | I54: 30 | J54: 0 | K54: 30 | O54: =ROUND(CP54,2) -> 76.33 | P54: =ROUND((ROUND((AC54*AW54*I54),2)*BC54),2) -> 0 | Q54: =(ROUND((ROUND(((((ET54*1.2)*0.3))*AV54*I54),2)*BB54),2)+ROUND((ROUND(((AE54-(((EU54*1.2)*0.3)))*AV54*I54),2)*BS54),2)) -> 0 | R54: =(ROUND((ROUND(((((EU54*1.2)*0.3))*AV54*I54),2)*BS54),2)+ROUND((ROUND(((AE54-(((EU54*1.2)*0.3)))*AV54*I54),2)*BS54),2)) -> 0 | S54: =ROUND((ROUND((AF54*AV54*I54),2)*BA54),2) -> 76.33 | T54: =ROUND(CU54*I54,2) -> 0 | U54: =CV54*I54 -> 5.879952 | V54: =CW54*I54 -> 0 | W54: =ROUND(CX54*I54,2) -> 0 | X54: =(ROUND((((S54+ROUND((ROUND(((((EU54*1.2)*0.3))*AV54*I54),2)*BS54),2))*AT54)/100),2)+ROUND(((ROUND((ROUND(((AE54-(((EU54*1.2)*0.3)))*AV54*I54),2)*BS54),2)*AT54)/100),2)) -> 68.7 | Y54: =(ROUND((((S54+ROUND((ROUND(((((EU54*1.2)*0.3))*AV54*I54),2)*BS54),2))*AU54)/100),2)+ROUND(((ROUND((ROUND(((AE54-(((EU54*1.2)*0.3)))*AV54*I54),2)*BS54),2)*AU54)/100),2)) -> 35.11 | AA54: 55944368 | AB54: =ROUND((AC54+AD54+AF54),6) -> 2.43 | AC54: =ROUND((((ES54*1)*0)),6) -> 0 | AD54: =ROUND((((((ET54*1.2)*0.3))-(((EU54*1.2)*0.3)))+AE54),6) -> 0 | AE54: =ROUND((((EU54*1.2)*0.3)),6) -> 0 | AF54: =ROUND((((EV54*1.2)*0.3)),6) -> 2.43 | AG54: =ROUND((AP54),6) -> 0 | AH54: =(((EW54*1.2)*0.3)) -> 0.1872 | AI54: =(((EX54*1.2)*0.3)) -> 0 | AJ54: =(AS54) -> 0 | AK54: 6.75 | AL54: 0 | AM54: 0 | AN54: 0 | AO54: 6.75 | AP54: 0 | AQ54: 0.52 | AR54: 0 | AS54: 0 | AT54: 90 | AU54: 46 | AV54: 1.047 | AW54: 1 | AZ54: 1 | BA54: 1 | BB54: 1 | BC54: 1 | BH54: 0 | BI54: 2 | BJ54: ТСН-2001.4 Доп. 67, Сб. 11, т. 3, поз. 1 | BM54: 72 | BN54: 0 | BO54: 4.11-3-1 | BP54: 1 | BQ54: 40 | BR54: 0 | BS54: 1 | BT54: 1 | BU54: 1 | BV54: 1 | BW54: 1 | BX54: 1 | BZ54: 90 | CA54: 46 | CE54: 1566 | CF54: 0 | CG54: 0 | CM54: 0 | CN54: Поправка: Гл.12.Прил.8.п.8. 3_12.00.01.11.001 Наименование: При наличии напряженных и стесненных условий производства работ (стесненность, сложность складирования и транспортной логистики и т.п.) для объектов, расположенных в пределах круговой магистральной системы улиц "Садовое кольцо" города Москвы Поправка: Гл.4.Прил.2.2.п.2.2.29_04.00.01.35.003 Наименование: При демонтаже оборудования, предназначенного в лом | CO54: 0 | CP54: =(P54+Q54+S54) -> 76.33 | CQ54: =ROUND((ROUND((AC54*AW54*1),2)*BC54),2) -> 0 | CR54: =(ROUND((ROUND(((((ET54*1.2)*0.3))*AV54*1),2)*BB54),2)+ROUND((ROUND(((AE54-(((EU54*1.2)*0.3)))*AV54*1),2)*BS54),2)) -> 0 | CS54: =(ROUND((ROUND(((((EU54*1.2)*0.3))*AV54*1),2)*BS54),2)+ROUND((ROUND(((AE54-(((EU54*1.2)*0.3)))*AV54*1),2)*BS54),2)) -> 0 | CT54: =ROUND((ROUND((AF54*AV54*1),2)*BA54),2) -> 2.54 | CU54: =AG54 -> 0 | CV54: =(AH54*AV54) -> 0.1959984 | CW54: =AI54 -> 0 | CX54: =AJ54 -> 0 | CY54: =(ROUND((((S54+ROUND((ROUND(((((EU54*1.2)*0.3))*AV54*1),2)*BS54),2))*AT54)/100),2)+ROUND(((ROUND((ROUND(((AE54-(((EU54*1.2)*0.3)))*AV54*1),2)*BS54),2)*AT54)/100),2)) -> 68.7 | CZ54: =(ROUND((((S54+ROUND((ROUND(((((EU54*1.2)*0.3))*AV54*1),2)*BS54),2))*AU54)/100),2)+ROUND(((ROUND((ROUND(((AE54-(((EU54*1.2)*0.3)))*AV54*1),2)*BS54),2)*AU54)/100),2)) -> 35.11 | DB54: 51 | DD54: *1)*0 | DE54: *1,2)*0,3 | DF54: *1,2)*0,3 | DG54: *1,2)*0,3 | DI54: *1,2)*0,3 | DJ54: *1,2)*0,3 | DN54: 0 | DO54: 0 | DP54: 1 | DQ54: 1 | DU54: 1013 | DV54: 1 ШТ. | DW54: 1 ШТ. | DX54: 1 | EE54: 55393976 | EF54: 40 | EG54: Монтаж оборудования | EH54: 0 | EJ54: 2 | EK54: 72 | EL54: ТСН-2001.4-11. Приборы и средства автоматизации и вычислительной техники | EM54: ТСН-2001.4-11-1 | EO54: Поправка: Гл.12.Прил.8.п.8. 3_12.00.01.11.001 Поправка: Гл.4.Прил.2.2.п.2.2.29_04.00.01.35.003 | EQ54: 0 | ER54: 6.75 | ES54: 0 | ET54: 0 | EU54: 0 | EV54: 6.75 | EW54: 0.52 | EX54: 0 | EY54: 0 | FQ54: 0 | FR54: 0 | FS54: 0 | FX54: 90 | FY54: 46 | GD54: 1 | GF54: 662794709 | GG54: 2 | GH54: 1 | GI54: 2 | GJ54: 0 | GK54: 0 | GL54: =ROUND(IF(AND(BH54=3,BI54=3,FS54<>0),P54,0),2) -> 0 | GM54: =ROUND(O54+X54+Y54,2)+GX54 -> 180.14 | GN54: =IF(OR(BI54=0,BI54=1),GM54-GX54,0) -> 0 | GO54: =IF(BI54=2,GM54-GX54,0) -> 180.14 | GP54: =IF(BI54=4,GM54-GX54,0) -> 0 | GR54: 0 | GS54: 3 | GT54: 0 | GV54: =ROUND((GT54),6) -> 0 | GW54: 1 | GX54: =ROUND(HC54*I54,2) -> 0 | HA54: 0 | HB54: 0 | HC54: =GV54*GW54 -> 0 | HS54: 0 | IK54: 0
A55: 17 | B55: 1 | C55: =ROW(SmtRes!A134) -> 134 | D55: =ROW(EtalonRes!A180) -> 180 | E55: 14 | F55: 4.11-3-1 | G55: Установка прибора массой до 5 кг на металлоконструкциях или щитах / демонтаж регуляторов скорости и выносных пультов | H55: 1 ШТ. | I55: 30 | J55: 0 | K55: 30 | O55: =ROUND(CP55,2) -> 4301.2 | P55: =ROUND((ROUND((AC55*AW55*I55),2)*BC55),2) -> 0 | Q55: =(ROUND((ROUND(((((ET55*1.2)*0.3))*AV55*I55),2)*BB55),2)+ROUND((ROUND(((AE55-(((EU55*1.2)*0.3)))*AV55*I55),2)*BS55),2)) -> 0 | R55: =(ROUND((ROUND(((((EU55*1.2)*0.3))*AV55*I55),2)*BS55),2)+ROUND((ROUND(((AE55-(((EU55*1.2)*0.3)))*AV55*I55),2)*BS55),2)) -> 0 | S55: =ROUND((ROUND((AF55*AV55*I55),2)*BA55),2) -> 4301.2 | T55: =ROUND(CU55*I55,2) -> 0 | U55: =CV55*I55 -> 5.879952 | V55: =CW55*I55 -> 0 | W55: =ROUND(CX55*I55,2) -> 0 | X55: =(ROUND((((S55+ROUND((ROUND(((((EU55*1.2)*0.3))*AV55*I55),2)*BS55),2))*AT55)/100),2)+ROUND(((ROUND((ROUND(((AE55-(((EU55*1.2)*0.3)))*AV55*I55),2)*BS55),2)*AT55)/100),2)) -> 3871.08 | Y55: =(ROUND((((S55+ROUND((ROUND(((((EU55*1.2)*0.3))*AV55*I55),2)*BS55),2))*AU55)/100),2)+ROUND(((ROUND((ROUND(((AE55-(((EU55*1.2)*0.3)))*AV55*I55),2)*BS55),2)*AU55)/100),2)) -> 1978.55 | AA55: 55944370 | AB55: =ROUND((AC55+AD55+AF55),6) -> 2.43 | AC55: =ROUND((((ES55*1)*0)),6) -> 0 | AD55: =ROUND((((((ET55*1.2)*0.3))-(((EU55*1.2)*0.3)))+AE55),6) -> 0 | AE55: =ROUND((((EU55*1.2)*0.3)),6) -> 0 | AF55: =ROUND((((EV55*1.2)*0.3)),6) -> 2.43 | AG55: =ROUND((AP55),6) -> 0 | AH55: =(((EW55*1.2)*0.3)) -> 0.1872 | AI55: =(((EX55*1.2)*0.3)) -> 0 | AJ55: =(AS55) -> 0 | AK55: 6.75 | AL55: 0 | AM55: 0 | AN55: 0 | AO55: 6.75 | AP55: 0 | AQ55: 0.52 | AR55: 0 | AS55: 0 | AT55: 90 | AU55: 46 | AV55: 1.047 | AW55: 1 | AZ55: 1 | BA55: 56.35 | BB55: 1 | BC55: 1 | BH55: 0 | BI55: 2 | BJ55: ТСН-2001.4 Доп. 67, Сб. 11, т. 3, поз. 1 | BM55: 72 | BN55: 0 | BO55: 4.11-3-1 | BP55: 1 | BQ55: 40 | BR55: 0 | BS55: 56.35 | BT55: 1 | BU55: 1 | BV55: 1 | BW55: 1 | BX55: 1 | BZ55: 90 | CA55: 46 | CE55: 1566 | CF55: 0 | CG55: 0 | CM55: 0 | CN55: Поправка: Гл.12.Прил.8.п.8. 3_12.00.01.11.001 Наименование: При наличии напряженных и стесненных условий производства работ (стесненность, сложность складирования и транспортной логистики и т.п.) для объектов, расположенных в пределах круговой магистральной системы улиц "Садовое кольцо" города Москвы Поправка: Гл.4.Прил.2.2.п.2.2.29_04.00.01.35.003 Наименование: При демонтаже оборудования, предназначенного в лом | CO55: 0 | CP55: =(P55+Q55+S55) -> 4301.2 | CQ55: =ROUND((ROUND((AC55*AW55*1),2)*BC55),2) -> 0 | CR55: =(ROUND((ROUND(((((ET55*1.2)*0.3))*AV55*1),2)*BB55),2)+ROUND((ROUND(((AE55-(((EU55*1.2)*0.3)))*AV55*1),2)*BS55),2)) -> 0 | CS55: =(ROUND((ROUND(((((EU55*1.2)*0.3))*AV55*1),2)*BS55),2)+ROUND((ROUND(((AE55-(((EU55*1.2)*0.3)))*AV55*1),2)*BS55),2)) -> 0 | CT55: =ROUND((ROUND((AF55*AV55*1),2)*BA55),2) -> 143.13 | CU55: =AG55 -> 0 | CV55: =(AH55*AV55) -> 0.1959984 | CW55: =AI55 -> 0 | CX55: =AJ55 -> 0 | CY55: =(ROUND((((S55+ROUND((ROUND(((((EU55*1.2)*0.3))*AV55*1),2)*BS55),2))*AT55)/100),2)+ROUND(((ROUND((ROUND(((AE55-(((EU55*1.2)*0.3)))*AV55*1),2)*BS55),2)*AT55)/100),2)) -> 3871.08 | CZ55: =(ROUND((((S55+ROUND((ROUND(((((EU55*1.2)*0.3))*AV55*1),2)*BS55),2))*AU55)/100),2)+ROUND(((ROUND((ROUND(((AE55-(((EU55*1.2)*0.3)))*AV55*1),2)*BS55),2)*AU55)/100),2)) -> 1978.55 | DB55: 53 | DD55: *1)*0 | DE55: *1,2)*0,3 | DF55: *1,2)*0,3 | DG55: *1,2)*0,3 | DI55: *1,2)*0,3 | DJ55: *1,2)*0,3 | DN55: 0 | DO55: 0 | DP55: 1 | DQ55: 1 | DU55: 1013 | DV55: 1 ШТ. | DW55: 1 ШТ. | DX55: 1 | EE55: 55393976 | EF55: 40 | EG55: Монтаж оборудования | EH55: 0 | EJ55: 2 | EK55: 72 | EL55: ТСН-2001.4-11. Приборы и средства автоматизации и вычислительной техники | EM55: ТСН-2001.4-11-1 | EO55: Поправка: Гл.12.Прил.8.п.8. 3_12.00.01.11.001 Поправка: Гл.4.Прил.2.2.п.2.2.29_04.00.01.35.003 | EQ55: 0 | ER55: 6.75 | ES55: 0 | ET55: 0 | EU55: 0 | EV55: 6.75 | EW55: 0.52 | EX55: 0 | EY55: 0 | FQ55: 0 | FR55: 0 | FS55: 0 | FX55: 90 | FY55: 46 | GD55: 1 | GF55: 662794709 | GG55: 2 | GH55: 1 | GI55: 2 | GJ55: 0 | GK55: 0 | GL55: =ROUND(IF(AND(BH55=3,BI55=3,FS55<>0),P55,0),2) -> 0 | GM55: =ROUND(O55+X55+Y55,2)+GX55 -> 10150.83 | GN55: =IF(OR(BI55=0,BI55=1),GM55-GX55,0) -> 0 | GO55: =IF(BI55=2,GM55-GX55,0) -> 10150.83 | GP55: =IF(BI55=4,GM55-GX55,0) -> 0 | GR55: 0 | GS55: 3 | GT55: 0 | GV55: =ROUND((GT55),6) -> 0 | GW55: 1 | GX55: =ROUND(HC55*I55,2) -> 0 | HA55: 0 | HB55: 0 | HC55: =GV55*GW55 -> 0 | HS55: 0 | IK55: 0
A56: 17 | B56: 1 | C56: =ROW(SmtRes!A146) -> 146 | D56: =ROW(EtalonRes!A195) -> 195 | F56: 4.8-261-1 | G56: Монтаж пульта регулирования регулятора электрического с количеством ручек до 24 / демонтаж регуляторов скорости и выносных пультов | H56: 1 ШТ. | I56: =ROUND(24+6,9) -> 30 | J56: 0 | K56: =ROUND(24+6,9) -> 30 | O56: =ROUND(CP56,2) -> 6743.51 | P56: =ROUND((ROUND((AC56*AW56*I56),2)*BC56),2) -> 0 | Q56: =(ROUND((ROUND(((((ET56*1.2)*0.3))*AV56*I56),2)*BB56),2)+ROUND((ROUND(((AE56-(((EU56*1.2)*0.3)))*AV56*I56),2)*BS56),2)) -> 8.82 | R56: =(ROUND((ROUND(((((EU56*1.2)*0.3))*AV56*I56),2)*BS56),2)+ROUND((ROUND(((AE56-(((EU56*1.2)*0.3)))*AV56*I56),2)*BS56),2)) -> 0 | S56: =ROUND((ROUND((AF56*AV56*I56),2)*BA56),2) -> 6734.69 | T56: =ROUND(CU56*I56,2) -> 0 | U56: =CV56*I56 -> 540.50328 | V56: =CW56*I56 -> 0 | W56: =ROUND(CX56*I56,2) -> 0 | X56: =(ROUND((((S56+ROUND((ROUND(((((EU56*1.2)*0.3))*AV56*I56),2)*BS56),2))*AT56)/100),2)+ROUND(((ROUND((ROUND(((AE56-(((EU56*1.2)*0.3)))*AV56*I56),2)*BS56),2)*AT56)/100),2)) -> 6532.65 | Y56: =(ROUND((((S56+ROUND((ROUND(((((EU56*1.2)*0.3))*AV56*I56),2)*BS56),2))*AU56)/100),2)+ROUND(((ROUND((ROUND(((AE56-(((EU56*1.2)*0.3)))*AV56*I56),2)*BS56),2)*AU56)/100),2)) -> 3434.69 | AA56: -1 | AB56: =ROUND((AC56+AD56+AF56),6) -> 214.6932 | AC56: =ROUND((((ES56*1)*0)),6) -> 0 | AD56: =ROUND((((((ET56*1.2)*0.3))-(((EU56*1.2)*0.3)))+AE56),6) -> 0.2808 | AE56: =ROUND((((EU56*1.2)*0.3)),6) -> 0 | AF56: =ROUND((((EV56*1.2)*0.3)),6) -> 214.4124 | AG56: =ROUND((AP56),6) -> 0 | AH56: =(((EW56*1.2)*0.3)) -> 17.208 | AI56: =(((EX56*1.2)*0.3)) -> 0 | AJ56: =(AS56) -> 0 | AK56: 891.97 | AL56: 295.6 | AM56: 0.78 | AN56: 0 | AO56: 595.59 | AP56: 0 | AQ56: 47.8 | AR56: 0 | AS56: 0 | AT56: 97 | AU56: 51 | AV56: 1.047 | AW56: 1 | AZ56: 1 | BA56: 1 | BB56: 1 | BC56: 1 | BH56: 0 | BI56: 2 | BJ56: ТСН-2001.4 Доп. 79, Сб. 8, т. 261, поз. 1 | BM56: 67 | BN56: 0 | BO56: 4.8-261-1 | BP56: 1 | BQ56: 40 | BR56: 0 | BS56: 1 | BT56: 1 | BU56: 1 | BV56: 1 | BW56: 1 | BX56: 1 | BZ56: 97 | CA56: 51 | CE56: 1566 | CF56: 0 | CG56: 0 | CM56: 0 | CN56: Поправка: Гл.12.Прил.8.п.8. 3_12.00.01.11.001 Наименование: При наличии напряженных и стесненных условий производства работ (стесненность, сложность складирования и транспортной логистики и т.п.) для объектов, расположенных в пределах круговой магистральной системы улиц "Садовое кольцо" города Москвы Поправка: Гл.4.Прил.2.2.п.2.2.29_04.00.01.35.003 Наименование: При демонтаже оборудования, предназначенного в лом | CO56: 0 | CP56: =(P56+Q56+S56) -> 6743.51 | CQ56: =ROUND((ROUND((AC56*AW56*1),2)*BC56),2) -> 0 | CR56: =(ROUND((ROUND(((((ET56*1.2)*0.3))*AV56*1),2)*BB56),2)+ROUND((ROUND(((AE56-(((EU56*1.2)*0.3)))*AV56*1),2)*BS56),2)) -> 0.29 | CS56: =(ROUND((ROUND(((((EU56*1.2)*0.3))*AV56*1),2)*BS56),2)+ROUND((ROUND(((AE56-(((EU56*1.2)*0.3)))*AV56*1),2)*BS56),2)) -> 0 | CT56: =ROUND((ROUND((AF56*AV56*1),2)*BA56),2) -> 224.49 | CU56: =AG56 -> 0 | CV56: =(AH56*AV56) -> 18.016776 | CW56: =AI56 -> 0 | CX56: =AJ56 -> 0 | CY56: =(ROUND((((S56+ROUND((ROUND(((((EU56*1.2)*0.3))*AV56*1),2)*BS56),2))*AT56)/100),2)+ROUND(((ROUND((ROUND(((AE56-(((EU56*1.2)*0.3)))*AV56*1),2)*BS56),2)*AT56)/100),2)) -> 6532.65 | CZ56: =(ROUND((((S56+ROUND((ROUND(((((EU56*1.2)*0.3))*AV56*1),2)*BS56),2))*AU56)/100),2)+ROUND(((ROUND((ROUND(((AE56-(((EU56*1.2)*0.3)))*AV56*1),2)*BS56),2)*AU56)/100),2)) -> 3434.69 | DB56: 55 | DD56: *1)*0 | DE56: *1,2)*0,3 | DF56: *1,2)*0,3 | DG56: *1,2)*0,3 | DI56: *1,2)*0,3 | DJ56: *1,2)*0,3 | DN56: 0 | DO56: 0 | DP56: 1 | DQ56: 1 | DU56: 1013 | DV56: 1 ШТ. | DW56: 1 ШТ. | DX56: 1 | EE56: 55393971 | EF56: 40 | EG56: Монтаж оборудования | EH56: 0 | EJ56: 2 | EK56: 67 | EL56: ТСН-2001.4-8. Электротехнические установки | EM56: ТСН-2001.4-8-1 | EO56: Поправка: Гл.12.Прил.8.п.8. 3_12.00.01.11.001 Поправка: Гл.4.Прил.2.2.п.2.2.29_04.00.01.35.003 | EQ56: 1024 | ER56: 891.97 | ES56: 295.6 | ET56: 0.78 | EU56: 0 | EV56: 595.59 | EW56: 47.8 | EX56: 0 | EY56: 0 | FQ56: 0 | FR56: 0 | FS56: 0 | FX56: 97 | FY56: 51 | GD56: 1 | GF56: 147134040 | GG56: 2 | GH56: 1 | GI56: 2 | GJ56: 0 | GK56: 0 | GL56: =ROUND(IF(AND(BH56=3,BI56=3,FS56<>0),P56,0),2) -> 0 | GM56: =ROUND(O56+X56+Y56,2)+GX56 -> 16710.85 | GN56: =IF(OR(BI56=0,BI56=1),GM56-GX56,0) -> 0 | GO56: =IF(BI56=2,GM56-GX56,0) -> 16710.85 | GP56: =IF(BI56=4,GM56-GX56,0) -> 0 | GR56: 0 | GS56: 3 | GT56: 0 | GV56: =ROUND((GT56),6) -> 0 | GW56: 1 | GX56: =ROUND(HC56*I56,2) -> 0 | HA56: 0 | HB56: 0 | HC56: =GV56*GW56 -> 0 | HS56: 0 | IK56: 0
A57: 17 | B57: 1 | C57: =ROW(SmtRes!A158) -> 158 | D57: =ROW(EtalonRes!A210) -> 210 | F57: 4.8-261-1 | G57: Монтаж пульта регулирования регулятора электрического с количеством ручек до 24 / демонтаж регуляторов скорости и выносных пультов | H57: 1 ШТ. | I57: =ROUND(24+6,9) -> 30 | J57: 0 | K57: =ROUND(24+6,9) -> 30 | O57: =ROUND(CP57,2) -> 379618.85 | P57: =ROUND((ROUND((AC57*AW57*I57),2)*BC57),2) -> 0 | Q57: =(ROUND((ROUND(((((ET57*1.2)*0.3))*AV57*I57),2)*BB57),2)+ROUND((ROUND(((AE57-(((EU57*1.2)*0.3)))*AV57*I57),2)*BS57),2)) -> 119.07 | R57: =(ROUND((ROUND(((((EU57*1.2)*0.3))*AV57*I57),2)*BS57),2)+ROUND((ROUND(((AE57-(((EU57*1.2)*0.3)))*AV57*I57),2)*BS57),2)) -> 0 | S57: =ROUND((ROUND((AF57*AV57*I57),2)*BA57),2) -> 379499.78 | T57: =ROUND(CU57*I57,2) -> 0 | U57: =CV57*I57 -> 540.50328 | V57: =CW57*I57 -> 0 | W57: =ROUND(CX57*I57,2) -> 0 | X57: =(ROUND((((S57+ROUND((ROUND(((((EU57*1.2)*0.3))*AV57*I57),2)*BS57),2))*AT57)/100),2)+ROUND(((ROUND((ROUND(((AE57-(((EU57*1.2)*0.3)))*AV57*I57),2)*BS57),2)*AT57)/100),2)) -> 368114.79 | Y57: =(ROUND((((S57+ROUND((ROUND(((((EU57*1.2)*0.3))*AV57*I57),2)*BS57),2))*AU57)/100),2)+ROUND(((ROUND((ROUND(((AE57-(((EU57*1.2)*0.3)))*AV57*I57),2)*BS57),2)*AU57)/100),2)) -> 193544.89 | AA57: -1 | AB57: =ROUND((AC57+AD57+AF57),6) -> 214.6932 | AC57: =ROUND((((ES57*1)*0)),6) -> 0 | AD57: =ROUND((((((ET57*1.2)*0.3))-(((EU57*1.2)*0.3)))+AE57),6) -> 0.2808 | AE57: =ROUND((((EU57*1.2)*0.3)),6) -> 0 | AF57: =ROUND((((EV57*1.2)*0.3)),6) -> 214.4124 | AG57: =ROUND((AP57),6) -> 0 | AH57: =(((EW57*1.2)*0.3)) -> 17.208 | AI57: =(((EX57*1.2)*0.3)) -> 0 | AJ57: =(AS57) -> 0 | AK57: 891.97 | AL57: 295.6 | AM57: 0.78 | AN57: 0 | AO57: 595.59 | AP57: 0 | AQ57: 47.8 | AR57: 0 | AS57: 0 | AT57: 97 | AU57: 51 | AV57: 1.047 | AW57: 1 | AZ57: 1 | BA57: 56.35 | BB57: 13.5 | BC57: 6.82 | BH57: 0 | BI57: 2 | BJ57: ТСН-2001.4 Доп. 79, Сб. 8, т. 261, поз. 1 | BM57: 67 | BN57: 0 | BO57: 4.8-261-1 | BP57: 1 | BQ57: 40 | BR57: 0 | BS57: 56.35 | BT57: 1 | BU57: 1 | BV57: 1 | BW57: 1 | BX57: 1 | BZ57: 97 | CA57: 51 | CE57: 1566 | CF57: 0 | CG57: 0 | CM57: 0 | CN57: Поправка: Гл.12.Прил.8.п.8. 3_12.00.01.11.001 Наименование: При наличии напряженных и стесненных условий производства работ (стесненность, сложность складирования и транспортной логистики и т.п.) для объектов, расположенных в пределах круговой магистральной системы улиц "Садовое кольцо" города Москвы Поправка: Гл.4.Прил.2.2.п.2.2.29_04.00.01.35.003 Наименование: При демонтаже оборудования, предназначенного в лом | CO57: 0 | CP57: =(P57+Q57+S57) -> 379618.85 | CQ57: =ROUND((ROUND((AC57*AW57*1),2)*BC57),2) -> 0 | CR57: =(ROUND((ROUND(((((ET57*1.2)*0.3))*AV57*1),2)*BB57),2)+ROUND((ROUND(((AE57-(((EU57*1.2)*0.3)))*AV57*1),2)*BS57),2)) -> 3.92 | CS57: =(ROUND((ROUND(((((EU57*1.2)*0.3))*AV57*1),2)*BS57),2)+ROUND((ROUND(((AE57-(((EU57*1.2)*0.3)))*AV57*1),2)*BS57),2)) -> 0 | CT57: =ROUND((ROUND((AF57*AV57*1),2)*BA57),2) -> 12650.01 | CU57: =AG57 -> 0 | CV57: =(AH57*AV57) -> 18.016776 | CW57: =AI57 -> 0 | CX57: =AJ57 -> 0 | CY57: =(ROUND((((S57+ROUND((ROUND(((((EU57*1.2)*0.3))*AV57*1),2)*BS57),2))*AT57)/100),2)+ROUND(((ROUND((ROUND(((AE57-(((EU57*1.2)*0.3)))*AV57*1),2)*BS57),2)*AT57)/100),2)) -> 368114.79 | CZ57: =(ROUND((((S57+ROUND((ROUND(((((EU57*1.2)*0.3))*AV57*1),2)*BS57),2))*AU57)/100),2)+ROUND(((ROUND((ROUND(((AE57-(((EU57*1.2)*0.3)))*AV57*1),2)*BS57),2)*AU57)/100),2)) -> 193544.89 | DB57: 57 | DD57: *1)*0 | DE57: *1,2)*0,3 | DF57: *1,2)*0,3 | DG57: *1,2)*0,3 | DI57: *1,2)*0,3 | DJ57: *1,2)*0,3 | DN57: 0 | DO57: 0 | DP57: 1 | DQ57: 1 | DU57: 1013 | DV57: 1 ШТ. | DW57: 1 ШТ. | DX57: 1 | EE57: 55393971 | EF57: 40 | EG57: Монтаж оборудования | EH57: 0 | EJ57: 2 | EK57: 67 | EL57: ТСН-2001.4-8. Электротехнические установки | EM57: ТСН-2001.4-8-1 | EO57: Поправка: Гл.12.Прил.8.п.8. 3_12.00.01.11.001 Поправка: Гл.4.Прил.2.2.п.2.2.29_04.00.01.35.003 | EQ57: 1024 | ER57: 891.97 | ES57: 295.6 | ET57: 0.78 | EU57: 0 | EV57: 595.59 | EW57: 47.8 | EX57: 0 | EY57: 0 | FQ57: 0 | FR57: 0 | FS57: 0 | FX57: 97 | FY57: 51 | GD57: 1 | GF57: 147134040 | GG57: 2 | GH57: 1 | GI57: 2 | GJ57: 0 | GK57: 0 | GL57: =ROUND(IF(AND(BH57=3,BI57=3,FS57<>0),P57,0),2) -> 0 | GM57: =ROUND(O57+X57+Y57,2)+GX57 -> 941278.53 | GN57: =IF(OR(BI57=0,BI57=1),GM57-GX57,0) -> 0 | GO57: =IF(BI57=2,GM57-GX57,0) -> 941278.53 | GP57: =IF(BI57=4,GM57-GX57,0) -> 0 | GR57: 0 | GS57: 3 | GT57: 0 | GV57: =ROUND((GT57),6) -> 0 | GW57: 1 | GX57: =ROUND(HC57*I57,2) -> 0 | HA57: 0 | HB57: 0 | HC57: =GV57*GW57 -> 0 | HS57: 0 | IK57: 0
A58: 17 | B58: 1 | C58: =ROW(SmtRes!A160) -> 160 | D58: =ROW(EtalonRes!A212) -> 212 | E58: 15 | F58: 6.67-5-1 | G58: Демонтаж трубных проводок, первого провода сечением 6 мм2 | H58: 100 м | I58: =ROUND(3750/100,9) -> 37.5 | J58: 0 | K58: =ROUND(3750/100,9) -> 37.5 | O58: =ROUND(CP58,2) -> 1134.06 | P58: =ROUND((ROUND((AC58*AW58*I58),2)*BC58),2) -> 0 | Q58: =(ROUND((ROUND((((ET58*1.2))*AV58*I58),2)*BB58),2)+ROUND((ROUND(((AE58-((EU58*1.2)))*AV58*I58),2)*BS58),2)) -> 0 | R58: =(ROUND((ROUND((((EU58*1.2))*AV58*I58),2)*BS58),2)+ROUND((ROUND(((AE58-((EU58*1.2)))*AV58*I58),2)*BS58),2)) -> 0 | S58: =ROUND((ROUND((AF58*AV58*I58),2)*BA58),2) -> 1134.06 | T58: =ROUND(CU58*I58,2) -> 0 | U58: =CV58*I58 -> 106.00875 | V58: =CW58*I58 -> 0 | W58: =ROUND(CX58*I58,2) -> 0 | X58: =(ROUND((((S58+ROUND((ROUND((((EU58*1.2))*AV58*I58),2)*BS58),2))*AT58)/100),2)+ROUND(((ROUND((ROUND(((AE58-((EU58*1.2)))*AV58*I58),2)*BS58),2)*AT58)/100),2)) -> 1031.99 | Y58: =(ROUND((((S58+ROUND((ROUND((((EU58*1.2))*AV58*I58),2)*BS58),2))*AU58)/100),2)+ROUND(((ROUND((ROUND(((AE58-((EU58*1.2)))*AV58*I58),2)*BS58),2)*AU58)/100),2)) -> 544.35 | AA58: 55944368 | AB58: =ROUND((AC58+AD58+AF58),6) -> 28.884 | AC58: =ROUND(((ES58*1)),6) -> 0 | AD58: =ROUND(((((ET58*1.2))-((EU58*1.2)))+AE58),6) -> 0 | AE58: =ROUND(((EU58*1.2)),6) -> 0 | AF58: =ROUND(((EV58*1.2)),6) -> 28.884 | AG58: =ROUND((AP58),6) -> 0 | AH58: =((EW58*1.2)) -> 2.7 | AI58: =((EX58*1.2)) -> 0 | AJ58: =(AS58) -> 0 | AK58: 24.07 | AL58: 0 | AM58: 0 | AN58: 0 | AO58: 24.07 | AP58: 0 | AQ58: 2.25 | AR58: 0 | AS58: 0 | AT58: 91 | AU58: 48 | AV58: 1.047 | AW58: 1 | AZ58: 1 | BA58: 1 | BB58: 1 | BC58: 1 | BH58: 0 | BI58: 1 | BJ58: ТСН-2001.6. Доп. 1-42. Сб. 67, т. 5, поз. 1 | BM58: 106 | BN58: 0 | BO58: 6.67-5-1 | BP58: 1 | BQ58: 60 | BR58: 0 | BS58: 1 | BT58: 1 | BU58: 1 | BV58: 1 | BW58: 1 | BX58: 1 | BZ58: 91 | CA58: 48 | CE58: 1566 | CF58: 0 | CG58: 0 | CM58: 0 | CN58: Поправка: Гл.12.Прил.8.п.8. 3_12.00.01.11.001 Наименование: При наличии напряженных и стесненных условий производства работ (стесненность, сложность складирования и транспортной логистики и т.п.) для объектов, расположенных в пределах круговой магистральной системы улиц "Садовое кольцо" города Москвы | CO58: 0 | CP58: =(P58+Q58+S58) -> 1134.06 | CQ58: =ROUND((ROUND((AC58*AW58*1),2)*BC58),2) -> 0 | CR58: =(ROUND((ROUND((((ET58*1.2))*AV58*1),2)*BB58),2)+ROUND((ROUND(((AE58-((EU58*1.2)))*AV58*1),2)*BS58),2)) -> 0 | CS58: =(ROUND((ROUND((((EU58*1.2))*AV58*1),2)*BS58),2)+ROUND((ROUND(((AE58-((EU58*1.2)))*AV58*1),2)*BS58),2)) -> 0 | CT58: =ROUND((ROUND((AF58*AV58*1),2)*BA58),2) -> 30.24 | CU58: =AG58 -> 0 | CV58: =(AH58*AV58) -> 2.8269 | CW58: =AI58 -> 0 | CX58: =AJ58 -> 0 | CY58: =(ROUND((((S58+ROUND((ROUND((((EU58*1.2))*AV58*1),2)*BS58),2))*AT58)/100),2)+ROUND(((ROUND((ROUND(((AE58-((EU58*1.2)))*AV58*1),2)*BS58),2)*AT58)/100),2)) -> 1031.99 | CZ58: =(ROUND((((S58+ROUND((ROUND((((EU58*1.2))*AV58*1),2)*BS58),2))*AU58)/100),2)+ROUND(((ROUND((ROUND(((AE58-((EU58*1.2)))*AV58*1),2)*BS58),2)*AU58)/100),2)) -> 544.35 | DB58: 59 | DD58: *1 | DE58: *1,2 | DF58: *1,2 | DG58: *1,2 | DI58: *1,2 | DJ58: *1,2 | DN58: 0 | DO58: 0 | DP58: 1 | DQ58: 1 | DU58: 1003 | DV58: 100 м | DW58: 100 м | DX58: 100 | EE58: 55394010 | EF58: 60 | EG58: Ремонтно-строительные работы | EH58: 0 | EJ58: 1 | EK58: 106 | EL58: ТСН-2001.6-67. Электромонтажные работы | EM58: ТСН-2001.6-67-1 | EO58: Поправка: Гл.12.Прил.8.п.8. 3_12.00.01.11.001 | EQ58: 0 | ER58: 24.07 | ES58: 0 | ET58: 0 | EU58: 0 | EV58: 24.07 | EW58: 2.25 | EX58: 0 | EY58: 0 | FQ58: 0 | FR58: 0 | FS58: 0 | FX58: 91 | FY58: 48 | GD58: 1 | GF58: -1911321142 | GG58: 2 | GH58: 1 | GI58: 2 | GJ58: 0 | GK58: 0 | GL58: =ROUND(IF(AND(BH58=3,BI58=3,FS58<>0),P58,0),2) -> 0 | GM58: =ROUND(O58+X58+Y58,2)+GX58 -> 2710.4 | GN58: =IF(OR(BI58=0,BI58=1),GM58-GX58,0) -> 2710.4 | GO58: =IF(BI58=2,GM58-GX58,0) -> 0 | GP58: =IF(BI58=4,GM58-GX58,0) -> 0 | GR58: 0 | GS58: 3 | GT58: 0 | GV58: =ROUND((GT58),6) -> 0 | GW58: 1 | GX58: =ROUND(HC58*I58,2) -> 0 | HA58: 0 | HB58: 0 | HC58: =GV58*GW58 -> 0 | HS58: 0 | IK58: 0
A59: 17 | B59: 1 | C59: =ROW(SmtRes!A162) -> 162 | D59: =ROW(EtalonRes!A214) -> 214 | E59: 15 | F59: 6.67-5-1 | G59: Демонтаж трубных проводок, первого провода сечением 6 мм2 | H59: 100 м | I59: =ROUND(3750/100,9) -> 37.5 | J59: 0 | K59: =ROUND(3750/100,9) -> 37.5 | O59: =ROUND(CP59,2) -> 63904.28 | P59: =ROUND((ROUND((AC59*AW59*I59),2)*BC59),2) -> 0 | Q59: =(ROUND((ROUND((((ET59*1.2))*AV59*I59),2)*BB59),2)+ROUND((ROUND(((AE59-((EU59*1.2)))*AV59*I59),2)*BS59),2)) -> 0 | R59: =(ROUND((ROUND((((EU59*1.2))*AV59*I59),2)*BS59),2)+ROUND((ROUND(((AE59-((EU59*1.2)))*AV59*I59),2)*BS59),2)) -> 0 | S59: =ROUND((ROUND((AF59*AV59*I59),2)*BA59),2) -> 63904.28 | T59: =ROUND(CU59*I59,2) -> 0 | U59: =CV59*I59 -> 106.00875 | V59: =CW59*I59 -> 0 | W59: =ROUND(CX59*I59,2) -> 0 | X59: =(ROUND((((S59+ROUND((ROUND((((EU59*1.2))*AV59*I59),2)*BS59),2))*AT59)/100),2)+ROUND(((ROUND((ROUND(((AE59-((EU59*1.2)))*AV59*I59),2)*BS59),2)*AT59)/100),2)) -> 58152.89 | Y59: =(ROUND((((S59+ROUND((ROUND((((EU59*1.2))*AV59*I59),2)*BS59),2))*AU59)/100),2)+ROUND(((ROUND((ROUND(((AE59-((EU59*1.2)))*AV59*I59),2)*BS59),2)*AU59)/100),2)) -> 30674.05 | AA59: 55944370 | AB59: =ROUND((AC59+AD59+AF59),6) -> 28.884 | AC59: =ROUND(((ES59*1)),6) -> 0 | AD59: =ROUND(((((ET59*1.2))-((EU59*1.2)))+AE59),6) -> 0 | AE59: =ROUND(((EU59*1.2)),6) -> 0 | AF59: =ROUND(((EV59*1.2)),6) -> 28.884 | AG59: =ROUND((AP59),6) -> 0 | AH59: =((EW59*1.2)) -> 2.7 | AI59: =((EX59*1.2)) -> 0 | AJ59: =(AS59) -> 0 | AK59: 24.07 | AL59: 0 | AM59: 0 | AN59: 0 | AO59: 24.07 | AP59: 0 | AQ59: 2.25 | AR59: 0 | AS59: 0 | AT59: 91 | AU59: 48 | AV59: 1.047 | AW59: 1 | AZ59: 1 | BA59: 56.35 | BB59: 1 | BC59: 1 | BH59: 0 | BI59: 1 | BJ59: ТСН-2001.6. Доп. 1-42. Сб. 67, т. 5, поз. 1 | BM59: 106 | BN59: 0 | BO59: 6.67-5-1 | BP59: 1 | BQ59: 60 | BR59: 0 | BS59: 56.35 | BT59: 1 | BU59: 1 | BV59: 1 | BW59: 1 | BX59: 1 | BZ59: 91 | CA59: 48 | CE59: 1566 | CF59: 0 | CG59: 0 | CM59: 0 | CN59: Поправка: Гл.12.Прил.8.п.8. 3_12.00.01.11.001 Наименование: При наличии напряженных и стесненных условий производства работ (стесненность, сложность складирования и транспортной логистики и т.п.) для объектов, расположенных в пределах круговой магистральной системы улиц "Садовое кольцо" города Москвы | CO59: 0 | CP59: =(P59+Q59+S59) -> 63904.28 | CQ59: =ROUND((ROUND((AC59*AW59*1),2)*BC59),2) -> 0 | CR59: =(ROUND((ROUND((((ET59*1.2))*AV59*1),2)*BB59),2)+ROUND((ROUND(((AE59-((EU59*1.2)))*AV59*1),2)*BS59),2)) -> 0 | CS59: =(ROUND((ROUND((((EU59*1.2))*AV59*1),2)*BS59),2)+ROUND((ROUND(((AE59-((EU59*1.2)))*AV59*1),2)*BS59),2)) -> 0 | CT59: =ROUND((ROUND((AF59*AV59*1),2)*BA59),2) -> 1704.02 | CU59: =AG59 -> 0 | CV59: =(AH59*AV59) -> 2.8269 | CW59: =AI59 -> 0 | CX59: =AJ59 -> 0 | CY59: =(ROUND((((S59+ROUND((ROUND((((EU59*1.2))*AV59*1),2)*BS59),2))*AT59)/100),2)+ROUND(((ROUND((ROUND(((AE59-((EU59*1.2)))*AV59*1),2)*BS59),2)*AT59)/100),2)) -> 58152.89 | CZ59: =(ROUND((((S59+ROUND((ROUND((((EU59*1.2))*AV59*1),2)*BS59),2))*AU59)/100),2)+ROUND(((ROUND((ROUND(((AE59-((EU59*1.2)))*AV59*1),2)*BS59),2)*AU59)/100),2)) -> 30674.05 | DB59: 60 | DD59: *1 | DE59: *1,2 | DF59: *1,2 | DG59: *1,2 | DI59: *1,2 | DJ59: *1,2 | DN59: 0 | DO59: 0 | DP59: 1 | DQ59: 1 | DU59: 1003 | DV59: 100 м | DW59: 100 м | DX59: 100 | EE59: 55394010 | EF59: 60 | EG59: Ремонтно-строительные работы | EH59: 0 | EJ59: 1 | EK59: 106 | EL59: ТСН-2001.6-67. Электромонтажные работы | EM59: ТСН-2001.6-67-1 | EO59: Поправка: Гл.12.Прил.8.п.8. 3_12.00.01.11.001 | EQ59: 0 | ER59: 24.07 | ES59: 0 | ET59: 0 | EU59: 0 | EV59: 24.07 | EW59: 2.25 | EX59: 0 | EY59: 0 | FQ59: 0 | FR59: 0 | FS59: 0 | FX59: 91 | FY59: 48 | GD59: 1 | GF59: -1911321142 | GG59: 2 | GH59: 1 | GI59: 2 | GJ59: 0 | GK59: 0 | GL59: =ROUND(IF(AND(BH59=3,BI59=3,FS59<>0),P59,0),2) -> 0 | GM59: =ROUND(O59+X59+Y59,2)+GX59 -> 152731.22 | GN59: =IF(OR(BI59=0,BI59=1),GM59-GX59,0) -> 152731.22 | GO59: =IF(BI59=2,GM59-GX59,0) -> 0 | GP59: =IF(BI59=4,GM59-GX59,0) -> 0 | GR59: 0 | GS59: 3 | GT59: 0 | GV59: =ROUND((GT59),6) -> 0 | GW59: 1 | GX59: =ROUND(HC59*I59,2) -> 0 | HA59: 0 | HB59: 0 | HC59: =GV59*GW59 -> 0 | HS59: 0 | IK59: 0
A60: 17 | B60: 1 | C60: =ROW(SmtRes!A167) -> 167 | D60: =ROW(EtalonRes!A220) -> 220 | E60: 16 | F60: 4.8-328-1 | G60: Прокладка кабельного изделия по установленным конструкциям и лоткам, при массе 1 м кабельного изделия до 0,5 кг на высоте до 5 м / демонтаж | H60: 100 м | I60: =ROUND(4280/100,9) -> 42.8 | J60: 0 | K60: =ROUND(4280/100,9) -> 42.8 | O60: =ROUND(CP60,2) -> 1100.54 | P60: =ROUND((ROUND((AC60*AW60*I60),2)*BC60),2) -> 0 | Q60: =(ROUND((ROUND(((((ET60*1.2)*0.3))*AV60*I60),2)*BB60),2)+ROUND((ROUND(((AE60-(((EU60*1.2)*0.3)))*AV60*I60),2)*BS60),2)) -> 42.27 | R60: =(ROUND((ROUND(((((EU60*1.2)*0.3))*AV60*I60),2)*BS60),2)+ROUND((ROUND(((AE60-(((EU60*1.2)*0.3)))*AV60*I60),2)*BS60),2)) -> 4.84 | S60: =ROUND((ROUND((AF60*AV60*I60),2)*BA60),2) -> 1058.27 | T60: =ROUND(CU60*I60,2) -> 0 | U60: =CV60*I60 -> 85.339211 | V60: =CW60*I60 -> 0 | W60: =ROUND(CX60*I60,2) -> 0 | X60: =(ROUND((((S60+ROUND((ROUND(((((EU60*1.2)*0.3))*AV60*I60),2)*BS60),2))*AT60)/100),2)+ROUND(((ROUND((ROUND(((AE60-(((EU60*1.2)*0.3)))*AV60*I60),2)*BS60),2)*AT60)/100),2)) -> 1031.22 | Y60: =(ROUND((((S60+ROUND((ROUND(((((EU60*1.2)*0.3))*AV60*I60),2)*BS60),2))*AU60)/100),2)+ROUND(((ROUND((ROUND(((AE60-(((EU60*1.2)*0.3)))*AV60*I60),2)*BS60),2)*AU60)/100),2)) -> 542.19 | AA60: 55944368 | AB60: =ROUND((AC60+AD60+AF60),6) -> 24.5592 | AC60: =ROUND((((ES60*1)*0)),6) -> 0 | AD60: =ROUND((((((ET60*1.2)*0.3))-(((EU60*1.2)*0.3)))+AE60),6) -> 0.9432 | AE60: =ROUND((((EU60*1.2)*0.3)),6) -> 0.108 | AF60: =ROUND((((EV60*1.2)*0.3)),6) -> 23.616 | AG60: =ROUND((AP60),6) -> 0 | AH60: =(((EW60*1.2)*0.3)) -> 1.9044 | AI60: =(((EX60*1.2)*0.3)) -> 0 | AJ60: =(AS60) -> 0 | AK60: 194.05 | AL60: 125.83 | AM60: 2.62 | AN60: 0.3 | AO60: 65.6 | AP60: 0 | AQ60: 5.29 | AR60: 0 | AS60: 0 | AT60: 97 | AU60: 51 | AV60: 1.047 | AW60: 1 | AZ60: 1 | BA60: 1 | BB60: 1 | BC60: 1 | BH60: 0 | BI60: 2 | BJ60: ТСН-2001.4 Доп. 75, Сб. 8, т. 328, поз. 1 | BM60: 67 | BN60: 0 | BO60: 4.8-328-1 | BP60: 1 | BQ60: 40 | BR60: 0 | BS60: 1 | BT60: 1 | BU60: 1 | BV60: 1 | BW60: 1 | BX60: 1 | BZ60: 97 | CA60: 51 | CE60: 1566 | CF60: 0 | CG60: 0 | CM60: 0 | CN60: Поправка: Гл.12.Прил.8.п.8. 3_12.00.01.11.001 Наименование: При наличии напряженных и стесненных условий производства работ (стесненность, сложность складирования и транспортной логистики и т.п.) для объектов, расположенных в пределах круговой магистральной системы улиц "Садовое кольцо" города Москвы Поправка: Гл.4.Прил.2.2.п.2.2.29_04.00.01.35.003 Наименование: При демонтаже оборудования, предназначенного в лом | CO60: 0 | CP60: =(P60+Q60+S60) -> 1100.54 | CQ60: =ROUND((ROUND((AC60*AW60*1),2)*BC60),2) -> 0 | CR60: =(ROUND((ROUND(((((ET60*1.2)*0.3))*AV60*1),2)*BB60),2)+ROUND((ROUND(((AE60-(((EU60*1.2)*0.3)))*AV60*1),2)*BS60),2)) -> 0.99 | CS60: =(ROUND((ROUND(((((EU60*1.2)*0.3))*AV60*1),2)*BS60),2)+ROUND((ROUND(((AE60-(((EU60*1.2)*0.3)))*AV60*1),2)*BS60),2)) -> 0.11 | CT60: =ROUND((ROUND((AF60*AV60*1),2)*BA60),2) -> 24.73 | CU60: =AG60 -> 0 | CV60: =(AH60*AV60) -> 1.9939068 | CW60: =AI60 -> 0 | CX60: =AJ60 -> 0 | CY60: =(ROUND((((S60+ROUND((ROUND(((((EU60*1.2)*0.3))*AV60*1),2)*BS60),2))*AT60)/100),2)+ROUND(((ROUND((ROUND(((AE60-(((EU60*1.2)*0.3)))*AV60*1),2)*BS60),2)*AT60)/100),2)) -> 1026.63 | CZ60: =(ROUND((((S60+ROUND((ROUND(((((EU60*1.2)*0.3))*AV60*1),2)*BS60),2))*AU60)/100),2)+ROUND(((ROUND((ROUND(((AE60-(((EU60*1.2)*0.3)))*AV60*1),2)*BS60),2)*AU60)/100),2)) -> 539.77 | DB60: 61 | DD60: *1)*0 | DE60: *1,2)*0,3 | DF60: *1,2)*0,3 | DG60: *1,2)*0,3 | DI60: *1,2)*0,3 | DJ60: *1,2)*0,3 | DN60: 0 | DO60: 0 | DP60: 1 | DQ60: 1 | DU60: 1003 | DV60: 100 м | DW60: 100 м | DX60: 100 | EE60: 55393971 | EF60: 40 | EG60: Монтаж оборудования | EH60: 0 | EJ60: 2 | EK60: 67 | EL60: ТСН-2001.4-8. Электротехнические установки | EM60: ТСН-2001.4-8-1 | EO60: Поправка: Гл.12.Прил.8.п.8. 3_12.00.01.11.001 Поправка: Гл.4.Прил.2.2.п.2.2.29_04.00.01.35.003 | EQ60: 0 | ER60: 194.05 | ES60: 125.83 | ET60: 2.62 | EU60: 0.3 | EV60: 65.6 | EW60: 5.29 | EX60: 0 | EY60: 0 | FQ60: 0 | FR60: 0 | FS60: 0 | FX60: 97 | FY60: 51 | GD60: 1 | GF60: 1117165266 | GG60: 2 | GH60: 1 | GI60: 2 | GJ60: 0 | GK60: 0 | GL60: =ROUND(IF(AND(BH60=3,BI60=3,FS60<>0),P60,0),2) -> 0 | GM60: =ROUND(O60+X60+Y60,2)+GX60 -> 2673.95 | GN60: =IF(OR(BI60=0,BI60=1),GM60-GX60,0) -> 0 | GO60: =IF(BI60=2,GM60-GX60,0) -> 2673.95 | GP60: =IF(BI60=4,GM60-GX60,0) -> 0 | GR60: 0 | GS60: 3 | GT60: 0 | GV60: =ROUND((GT60),6) -> 0 | GW60: 1 | GX60: =ROUND(HC60*I60,2) -> 0 | HA60: 0 | HB60: 0 | HC60: =GV60*GW60 -> 0 | HS60: 0 | IK60: 0
A61: 17 | B61: 1 | C61: =ROW(SmtRes!A172) -> 172 | D61: =ROW(EtalonRes!A226) -> 226 | E61: 16 | F61: 4.8-328-1 | G61: Прокладка кабельного изделия по установленным конструкциям и лоткам, при массе 1 м кабельного изделия до 0,5 кг на высоте до 5 м / демонтаж | H61: 100 м | I61: =ROUND(4280/100,9) -> 42.8 | J61: 0 | K61: =ROUND(4280/100,9) -> 42.8 | O61: =ROUND(CP61,2) -> 60279.4 | P61: =ROUND((ROUND((AC61*AW61*I61),2)*BC61),2) -> 0 | Q61: =(ROUND((ROUND(((((ET61*1.2)*0.3))*AV61*I61),2)*BB61),2)+ROUND((ROUND(((AE61-(((EU61*1.2)*0.3)))*AV61*I61),2)*BS61),2)) -> 645.89 | R61: =(ROUND((ROUND(((((EU61*1.2)*0.3))*AV61*I61),2)*BS61),2)+ROUND((ROUND(((AE61-(((EU61*1.2)*0.3)))*AV61*I61),2)*BS61),2)) -> 272.73 | S61: =ROUND((ROUND((AF61*AV61*I61),2)*BA61),2) -> 59633.51 | T61: =ROUND(CU61*I61,2) -> 0 | U61: =CV61*I61 -> 85.339211 | V61: =CW61*I61 -> 0 | W61: =ROUND(CX61*I61,2) -> 0 | X61: =(ROUND((((S61+ROUND((ROUND(((((EU61*1.2)*0.3))*AV61*I61),2)*BS61),2))*AT61)/100),2)+ROUND(((ROUND((ROUND(((AE61-(((EU61*1.2)*0.3)))*AV61*I61),2)*BS61),2)*AT61)/100),2)) -> 58109.05 | Y61: =(ROUND((((S61+ROUND((ROUND(((((EU61*1.2)*0.3))*AV61*I61),2)*BS61),2))*AU61)/100),2)+ROUND(((ROUND((ROUND(((AE61-(((EU61*1.2)*0.3)))*AV61*I61),2)*BS61),2)*AU61)/100),2)) -> 30552.18 | AA61: 55944370 | AB61: =ROUND((AC61+AD61+AF61),6) -> 24.5592 | AC61: =ROUND((((ES61*1)*0)),6) -> 0 | AD61: =ROUND((((((ET61*1.2)*0.3))-(((EU61*1.2)*0.3)))+AE61),6) -> 0.9432 | AE61: =ROUND((((EU61*1.2)*0.3)),6) -> 0.108 | AF61: =ROUND((((EV61*1.2)*0.3)),6) -> 23.616 | AG61: =ROUND((AP61),6) -> 0 | AH61: =(((EW61*1.2)*0.3)) -> 1.9044 | AI61: =(((EX61*1.2)*0.3)) -> 0 | AJ61: =(AS61) -> 0 | AK61: 194.05 | AL61: 125.83 | AM61: 2.62 | AN61: 0.3 | AO61: 65.6 | AP61: 0 | AQ61: 5.29 | AR61: 0 | AS61: 0 | AT61: 97 | AU61: 51 | AV61: 1.047 | AW61: 1 | AZ61: 1 | BA61: 56.35 | BB61: 15.28 | BC61: 3.78 | BH61: 0 | BI61: 2 | BJ61: ТСН-2001.4 Доп. 75, Сб. 8, т. 328, поз. 1 | BM61: 67 | BN61: 0 | BO61: 4.8-328-1 | BP61: 1 | BQ61: 40 | BR61: 0 | BS61: 56.35 | BT61: 1 | BU61: 1 | BV61: 1 | BW61: 1 | BX61: 1 | BZ61: 97 | CA61: 51 | CE61: 1566 | CF61: 0 | CG61: 0 | CM61: 0 | CN61: Поправка: Гл.12.Прил.8.п.8. 3_12.00.01.11.001 Наименование: При наличии напряженных и стесненных условий производства работ (стесненность, сложность складирования и транспортной логистики и т.п.) для объектов, расположенных в пределах круговой магистральной системы улиц "Садовое кольцо" города Москвы Поправка: Гл.4.Прил.2.2.п.2.2.29_04.00.01.35.003 Наименование: При демонтаже оборудования, предназначенного в лом | CO61: 0 | CP61: =(P61+Q61+S61) -> 60279.4 | CQ61: =ROUND((ROUND((AC61*AW61*1),2)*BC61),2) -> 0 | CR61: =(ROUND((ROUND(((((ET61*1.2)*0.3))*AV61*1),2)*BB61),2)+ROUND((ROUND(((AE61-(((EU61*1.2)*0.3)))*AV61*1),2)*BS61),2)) -> 15.13 | CS61: =(ROUND((ROUND(((((EU61*1.2)*0.3))*AV61*1),2)*BS61),2)+ROUND((ROUND(((AE61-(((EU61*1.2)*0.3)))*AV61*1),2)*BS61),2)) -> 6.2 | CT61: =ROUND((ROUND((AF61*AV61*1),2)*BA61),2) -> 1393.54 | CU61: =AG61 -> 0 | CV61: =(AH61*AV61) -> 1.9939068 | CW61: =AI61 -> 0 | CX61: =AJ61 -> 0 | CY61: =(ROUND((((S61+ROUND((ROUND(((((EU61*1.2)*0.3))*AV61*1),2)*BS61),2))*AT61)/100),2)+ROUND(((ROUND((ROUND(((AE61-(((EU61*1.2)*0.3)))*AV61*1),2)*BS61),2)*AT61)/100),2)) -> 57850.52 | CZ61: =(ROUND((((S61+ROUND((ROUND(((((EU61*1.2)*0.3))*AV61*1),2)*BS61),2))*AU61)/100),2)+ROUND(((ROUND((ROUND(((AE61-(((EU61*1.2)*0.3)))*AV61*1),2)*BS61),2)*AU61)/100),2)) -> 30416.25 | DB61: 63 | DD61: *1)*0 | DE61: *1,2)*0,3 | DF61: *1,2)*0,3 | DG61: *1,2)*0,3 | DI61: *1,2)*0,3 | DJ61: *1,2)*0,3 | DN61: 0 | DO61: 0 | DP61: 1 | DQ61: 1 | DU61: 1003 | DV61: 100 м | DW61: 100 м | DX61: 100 | EE61: 55393971 | EF61: 40 | EG61: Монтаж оборудования | EH61: 0 | EJ61: 2 | EK61: 67 | EL61: ТСН-2001.4-8. Электротехнические установки | EM61: ТСН-2001.4-8-1 | EO61: Поправка: Гл.12.Прил.8.п.8. 3_12.00.01.11.001 Поправка: Гл.4.Прил.2.2.п.2.2.29_04.00.01.35.003 | EQ61: 0 | ER61: 194.05 | ES61: 125.83 | ET61: 2.62 | EU61: 0.3 | EV61: 65.6 | EW61: 5.29 | EX61: 0 | EY61: 0 | FQ61: 0 | FR61: 0 | FS61: 0 | FX61: 97 | FY61: 51 | GD61: 1 | GF61: 1117165266 | GG61: 2 | GH61: 1 | GI61: 2 | GJ61: 0 | GK61: 0 | GL61: =ROUND(IF(AND(BH61=3,BI61=3,FS61<>0),P61,0),2) -> 0 | GM61: =ROUND(O61+X61+Y61,2)+GX61 -> 148940.63 | GN61: =IF(OR(BI61=0,BI61=1),GM61-GX61,0) -> 0 | GO61: =IF(BI61=2,GM61-GX61,0) -> 148940.63 | GP61: =IF(BI61=4,GM61-GX61,0) -> 0 | GR61: 0 | GS61: 3 | GT61: 0 | GV61: =ROUND((GT61),6) -> 0 | GW61: 1 | GX61: =ROUND(HC61*I61,2) -> 0 | HA61: 0 | HB61: 0 | HC61: =GV61*GW61 -> 0 | HS61: 0 | IK61: 0
A62: 17 | B62: 1 | C62: =ROW(SmtRes!A173) -> 173 | D62: =ROW(EtalonRes!A227) -> 227 | F62: 6.67-6-1 | G62: Демонтаж кабеля | H62: 100 м | I62: =ROUND((550+180+80+20+550+180+80+20+3500+280+340+900+150+850+350)/100,9) -> 80.3 | J62: 0 | K62: =ROUND((550+180+80+20+550+180+80+20+3500+280+340+900+150+850+350)/100,9) -> 80.3 | O62: =ROUND(CP62,2) -> 9939.58 | P62: =ROUND((ROUND((AC62*AW62*I62),2)*BC62),2) -> 0 | Q62: =(ROUND((ROUND((((ET62*1.2))*AV62*I62),2)*BB62),2)+ROUND((ROUND(((AE62-((EU62*1.2)))*AV62*I62),2)*BS62),2)) -> 0 | R62: =(ROUND((ROUND((((EU62*1.2))*AV62*I62),2)*BS62),2)+ROUND((ROUND(((AE62-((EU62*1.2)))*AV62*I62),2)*BS62),2)) -> 0 | S62: =ROUND((ROUND((AF62*AV62*I62),2)*BA62),2) -> 9939.58 | T62: =ROUND(CU62*I62,2) -> 0 | U62: =CV62*I62 -> 972.56919 | V62: =CW62*I62 -> 0 | W62: =ROUND(CX62*I62,2) -> 0 | X62: =(ROUND((((S62+ROUND((ROUND((((EU62*1.2))*AV62*I62),2)*BS62),2))*AT62)/100),2)+ROUND(((ROUND((ROUND(((AE62-((EU62*1.2)))*AV62*I62),2)*BS62),2)*AT62)/100),2)) -> 9045.02 | Y62: =(ROUND((((S62+ROUND((ROUND((((EU62*1.2))*AV62*I62),2)*BS62),2))*AU62)/100),2)+ROUND(((ROUND((ROUND(((AE62-((EU62*1.2)))*AV62*I62),2)*BS62),2)*AU62)/100),2)) -> 4771 | AA62: -1 | AB62: =ROUND((AC62+AD62+AF62),6) -> 118.224 | AC62: =ROUND(((ES62*1)),6) -> 0 | AD62: =ROUND(((((ET62*1.2))-((EU62*1.2)))+AE62),6) -> 0 | AE62: =ROUND(((EU62*1.2)),6) -> 0 | AF62: =ROUND(((EV62*1.2)),6) -> 118.224 | AG62: =ROUND((AP62),6) -> 0 | AH62: =((EW62*1.2)) -> 11.568 | AI62: =((EX62*1.2)) -> 0 | AJ62: =(AS62) -> 0 | AK62: 98.52 | AL62: 0 | AM62: 0 | AN62: 0 | AO62: 98.52 | AP62: 0 | AQ62: 9.64 | AR62: 0 | AS62: 0 | AT62: 91 | AU62: 48 | AV62: 1.047 | AW62: 1 | AZ62: 1 | BA62: 1 | BB62: 1 | BC62: 1 | BH62: 0 | BI62: 1 | BJ62: ТСН-2001.6. Доп. 1-42. Сб. 67, т. 6, поз. 1 | BM62: 106 | BN62: 0 | BO62: 6.67-6-1 | BP62: 1 | BQ62: 60 | BR62: 0 | BS62: 1 | BT62: 1 | BU62: 1 | BV62: 1 | BW62: 1 | BX62: 1 | BZ62: 91 | CA62: 48 | CE62: 1566 | CF62: 0 | CG62: 0 | CM62: 0 | CN62: Поправка: Гл.12.Прил.8.п.8. 3_12.00.01.11.001 Наименование: При наличии напряженных и стесненных условий производства работ (стесненность, сложность складирования и транспортной логистики и т.п.) для объектов, расположенных в пределах круговой магистральной системы улиц "Садовое кольцо" города Москвы | CO62: 0 | CP62: =(P62+Q62+S62) -> 9939.58 | CQ62: =ROUND((ROUND((AC62*AW62*1),2)*BC62),2) -> 0 | CR62: =(ROUND((ROUND((((ET62*1.2))*AV62*1),2)*BB62),2)+ROUND((ROUND(((AE62-((EU62*1.2)))*AV62*1),2)*BS62),2)) -> 0 | CS62: =(ROUND((ROUND((((EU62*1.2))*AV62*1),2)*BS62),2)+ROUND((ROUND(((AE62-((EU62*1.2)))*AV62*1),2)*BS62),2)) -> 0 | CT62: =ROUND((ROUND((AF62*AV62*1),2)*BA62),2) -> 123.78 | CU62: =AG62 -> 0 | CV62: =(AH62*AV62) -> 12.111696 | CW62: =AI62 -> 0 | CX62: =AJ62 -> 0 | CY62: =(ROUND((((S62+ROUND((ROUND((((EU62*1.2))*AV62*1),2)*BS62),2))*AT62)/100),2)+ROUND(((ROUND((ROUND(((AE62-((EU62*1.2)))*AV62*1),2)*BS62),2)*AT62)/100),2)) -> 9045.02 | CZ62: =(ROUND((((S62+ROUND((ROUND((((EU62*1.2))*AV62*1),2)*BS62),2))*AU62)/100),2)+ROUND(((ROUND((ROUND(((AE62-((EU62*1.2)))*AV62*1),2)*BS62),2)*AU62)/100),2)) -> 4771 | DB62: 65 | DD62: *1 | DE62: *1,2 | DF62: *1,2 | DG62: *1,2 | DI62: *1,2 | DJ62: *1,2 | DN62: 0 | DO62: 0 | DP62: 1 | DQ62: 1 | DU62: 1003 | DV62: 100 м | DW62: 100 м | DX62: 100 | EE62: 55394010 | EF62: 60 | EG62: Ремонтно-строительные работы | EH62: 0 | EJ62: 1 | EK62: 106 | EL62: ТСН-2001.6-67. Электромонтажные работы | EM62: ТСН-2001.6-67-1 | EO62: Поправка: Гл.12.Прил.8.п.8. 3_12.00.01.11.001 | EQ62: 1024 | ER62: 98.52 | ES62: 0 | ET62: 0 | EU62: 0 | EV62: 98.52 | EW62: 9.64 | EX62: 0 | EY62: 0 | FQ62: 0 | FR62: 0 | FS62: 0 | FX62: 91 | FY62: 48 | GD62: 1 | GF62: 1114236003 | GG62: 2 | GH62: 1 | GI62: 2 | GJ62: 0 | GK62: 0 | GL62: =ROUND(IF(AND(BH62=3,BI62=3,FS62<>0),P62,0),2) -> 0 | GM62: =ROUND(O62+X62+Y62,2)+GX62 -> 23755.6 | GN62: =IF(OR(BI62=0,BI62=1),GM62-GX62,0) -> 23755.6 | GO62: =IF(BI62=2,GM62-GX62,0) -> 0 | GP62: =IF(BI62=4,GM62-GX62,0) -> 0 | GR62: 0 | GS62: 3 | GT62: 0 | GV62: =ROUND((GT62),6) -> 0 | GW62: 1 | GX62: =ROUND(HC62*I62,2) -> 0 | HA62: 0 | HB62: 0 | HC62: =GV62*GW62 -> 0 | HS62: 0 | IK62: 0
A63: 17 | B63: 1 | C63: =ROW(SmtRes!A174) -> 174 | D63: =ROW(EtalonRes!A228) -> 228 | F63: 6.67-6-1 | G63: Демонтаж кабеля | H63: 100 м | I63: =ROUND((550+180+80+20+550+180+80+20+3500+280+340+900+150+850+350)/100,9) -> 80.3 | J63: 0 | K63: =ROUND((550+180+80+20+550+180+80+20+3500+280+340+900+150+850+350)/100,9) -> 80.3 | O63: =ROUND(CP63,2) -> 560095.33 | P63: =ROUND((ROUND((AC63*AW63*I63),2)*BC63),2) -> 0 | Q63: =(ROUND((ROUND((((ET63*1.2))*AV63*I63),2)*BB63),2)+ROUND((ROUND(((AE63-((EU63*1.2)))*AV63*I63),2)*BS63),2)) -> 0 | R63: =(ROUND((ROUND((((EU63*1.2))*AV63*I63),2)*BS63),2)+ROUND((ROUND(((AE63-((EU63*1.2)))*AV63*I63),2)*BS63),2)) -> 0 | S63: =ROUND((ROUND((AF63*AV63*I63),2)*BA63),2) -> 560095.33 | T63: =ROUND(CU63*I63,2) -> 0 | U63: =CV63*I63 -> 972.56919 | V63: =CW63*I63 -> 0 | W63: =ROUND(CX63*I63,2) -> 0 | X63: =(ROUND((((S63+ROUND((ROUND((((EU63*1.2))*AV63*I63),2)*BS63),2))*AT63)/100),2)+ROUND(((ROUND((ROUND(((AE63-((EU63*1.2)))*AV63*I63),2)*BS63),2)*AT63)/100),2)) -> 509686.75 | Y63: =(ROUND((((S63+ROUND((ROUND((((EU63*1.2))*AV63*I63),2)*BS63),2))*AU63)/100),2)+ROUND(((ROUND((ROUND(((AE63-((EU63*1.2)))*AV63*I63),2)*BS63),2)*AU63)/100),2)) -> 268845.76 | AA63: -1 | AB63: =ROUND((AC63+AD63+AF63),6) -> 118.224 | AC63: =ROUND(((ES63*1)),6) -> 0 | AD63: =ROUND(((((ET63*1.2))-((EU63*1.2)))+AE63),6) -> 0 | AE63: =ROUND(((EU63*1.2)),6) -> 0 | AF63: =ROUND(((EV63*1.2)),6) -> 118.224 | AG63: =ROUND((AP63),6) -> 0 | AH63: =((EW63*1.2)) -> 11.568 | AI63: =((EX63*1.2)) -> 0 | AJ63: =(AS63) -> 0 | AK63: 98.52 | AL63: 0 | AM63: 0 | AN63: 0 | AO63: 98.52 | AP63: 0 | AQ63: 9.64 | AR63: 0 | AS63: 0 | AT63: 91 | AU63: 48 | AV63: 1.047 | AW63: 1 | AZ63: 1 | BA63: 56.35 | BB63: 1 | BC63: 1 | BH63: 0 | BI63: 1 | BJ63: ТСН-2001.6. Доп. 1-42. Сб. 67, т. 6, поз. 1 | BM63: 106 | BN63: 0 | BO63: 6.67-6-1 | BP63: 1 | BQ63: 60 | BR63: 0 | BS63: 56.35 | BT63: 1 | BU63: 1 | BV63: 1 | BW63: 1 | BX63: 1 | BZ63: 91 | CA63: 48 | CE63: 1566 | CF63: 0 | CG63: 0 | CM63: 0 | CN63: Поправка: Гл.12.Прил.8.п.8. 3_12.00.01.11.001 Наименование: При наличии напряженных и стесненных условий производства работ (стесненность, сложность складирования и транспортной логистики и т.п.) для объектов, расположенных в пределах круговой магистральной системы улиц "Садовое кольцо" города Москвы | CO63: 0 | CP63: =(P63+Q63+S63) -> 560095.33 | CQ63: =ROUND((ROUND((AC63*AW63*1),2)*BC63),2) -> 0 | CR63: =(ROUND((ROUND((((ET63*1.2))*AV63*1),2)*BB63),2)+ROUND((ROUND(((AE63-((EU63*1.2)))*AV63*1),2)*BS63),2)) -> 0 | CS63: =(ROUND((ROUND((((EU63*1.2))*AV63*1),2)*BS63),2)+ROUND((ROUND(((AE63-((EU63*1.2)))*AV63*1),2)*BS63),2)) -> 0 | CT63: =ROUND((ROUND((AF63*AV63*1),2)*BA63),2) -> 6975 | CU63: =AG63 -> 0 | CV63: =(AH63*AV63) -> 12.111696 | CW63: =AI63 -> 0 | CX63: =AJ63 -> 0 | CY63: =(ROUND((((S63+ROUND((ROUND((((EU63*1.2))*AV63*1),2)*BS63),2))*AT63)/100),2)+ROUND(((ROUND((ROUND(((AE63-((EU63*1.2)))*AV63*1),2)*BS63),2)*AT63)/100),2)) -> 509686.75 | CZ63: =(ROUND((((S63+ROUND((ROUND((((EU63*1.2))*AV63*1),2)*BS63),2))*AU63)/100),2)+ROUND(((ROUND((ROUND(((AE63-((EU63*1.2)))*AV63*1),2)*BS63),2)*AU63)/100),2)) -> 268845.76 | DB63: 66 | DD63: *1 | DE63: *1,2 | DF63: *1,2 | DG63: *1,2 | DI63: *1,2 | DJ63: *1,2 | DN63: 0 | DO63: 0 | DP63: 1 | DQ63: 1 | DU63: 1003 | DV63: 100 м | DW63: 100 м | DX63: 100 | EE63: 55394010 | EF63: 60 | EG63: Ремонтно-строительные работы | EH63: 0 | EJ63: 1 | EK63: 106 | EL63: ТСН-2001.6-67. Электромонтажные работы | EM63: ТСН-2001.6-67-1 | EO63: Поправка: Гл.12.Прил.8.п.8. 3_12.00.01.11.001 | EQ63: 1024 | ER63: 98.52 | ES63: 0 | ET63: 0 | EU63: 0 | EV63: 98.52 | EW63: 9.64 | EX63: 0 | EY63: 0 | FQ63: 0 | FR63: 0 | FS63: 0 | FX63: 91 | FY63: 48 | GD63: 1 | GF63: 1114236003 | GG63: 2 | GH63: 1 | GI63: 2 | GJ63: 0 | GK63: 0 | GL63: =ROUND(IF(AND(BH63=3,BI63=3,FS63<>0),P63,0),2) -> 0 | GM63: =ROUND(O63+X63+Y63,2)+GX63 -> 1338627.8 | GN63: =IF(OR(BI63=0,BI63=1),GM63-GX63,0) -> 1338627.8 | GO63: =IF(BI63=2,GM63-GX63,0) -> 0 | GP63: =IF(BI63=4,GM63-GX63,0) -> 0 | GR63: 0 | GS63: 3 | GT63: 0 | GV63: =ROUND((GT63),6) -> 0 | GW63: 1 | GX63: =ROUND(HC63*I63,2) -> 0 | HA63: 0 | HB63: 0 | HC63: =GV63*GW63 -> 0 | HS63: 0 | IK63: 0
A64: 17 | B64: 1 | C64: =ROW(SmtRes!A182) -> 182 | D64: =ROW(EtalonRes!A241) -> 241 | E64: 17 | F64: 4.8-331-2 | G64: Прокладка металлического перфорированного лотка по установленным конструкциям, массой погонного метра до 4 кг / демонтаж лотков | H64: 100 М ТРАССЫ | I64: =ROUND(24/100,9) -> 0.24 | J64: 0 | K64: =ROUND(24/100,9) -> 0.24 | O64: =ROUND(CP64,2) -> 19.25 | P64: =ROUND((ROUND((AC64*AW64*I64),2)*BC64),2) -> 0 | Q64: =(ROUND((ROUND(((((ET64*1.2)*0.3))*AV64*I64),2)*BB64),2)+ROUND((ROUND(((AE64-(((EU64*1.2)*0.3)))*AV64*I64),2)*BS64),2)) -> 0.6 | R64: =(ROUND((ROUND(((((EU64*1.2)*0.3))*AV64*I64),2)*BS64),2)+ROUND((ROUND(((AE64-(((EU64*1.2)*0.3)))*AV64*I64),2)*BS64),2)) -> 0.11 | S64: =ROUND((ROUND((AF64*AV64*I64),2)*BA64),2) -> 18.65 | T64: =ROUND(CU64*I64,2) -> 0 | U64: =CV64*I64 -> 1.6409589 | V64: =CW64*I64 -> 0 | W64: =ROUND(CX64*I64,2) -> 0 | X64: =(ROUND((((S64+ROUND((ROUND(((((EU64*1.2)*0.3))*AV64*I64),2)*BS64),2))*AT64)/100),2)+ROUND(((ROUND((ROUND(((AE64-(((EU64*1.2)*0.3)))*AV64*I64),2)*BS64),2)*AT64)/100),2)) -> 18.2 | Y64: =(ROUND((((S64+ROUND((ROUND(((((EU64*1.2)*0.3))*AV64*I64),2)*BS64),2))*AU64)/100),2)+ROUND(((ROUND((ROUND(((AE64-(((EU64*1.2)*0.3)))*AV64*I64),2)*BS64),2)*AU64)/100),2)) -> 9.57 | AA64: 55944368 | AB64: =ROUND((AC64+AD64+AF64),6) -> 76.6224 | AC64: =ROUND((((ES64*1)*0)),6) -> 0 | AD64: =ROUND((((((ET64*1.2)*0.3))-(((EU64*1.2)*0.3)))+AE64),6) -> 2.4012 | AE64: =ROUND((((EU64*1.2)*0.3)),6) -> 0.432 | AF64: =ROUND((((EV64*1.2)*0.3)),6) -> 74.2212 | AG64: =ROUND((AP64),6) -> 0 | AH64: =(((EW64*1.2)*0.3)) -> 6.5304 | AI64: =(((EX64*1.2)*0.3)) -> 0 | AJ64: =(AS64) -> 0 | AK64: 224.18 | AL64: 11.34 | AM64: 6.67 | AN64: 1.2 | AO64: 206.17 | AP64: 0 | AQ64: 18.14 | AR64: 0 | AS64: 0 | AT64: 97 | AU64: 51 | AV64: 1.047 | AW64: 1 | AZ64: 1 | BA64: 1 | BB64: 1 | BC64: 1 | BH64: 0 | BI64: 2 | BJ64: ТСН-2001.4 Доп. 81, Сб. 8, т. 331, поз. 2 | BM64: 67 | BN64: 0 | BO64: 4.8-331-2 | BP64: 1 | BQ64: 40 | BR64: 0 | BS64: 1 | BT64: 1 | BU64: 1 | BV64: 1 | BW64: 1 | BX64: 1 | BZ64: 97 | CA64: 51 | CE64: 1566 | CF64: 0 | CG64: 0 | CM64: 0 | CN64: Поправка: Гл.12.Прил.8.п.8. 3_12.00.01.11.001 Наименование: При наличии напряженных и стесненных условий производства работ (стесненность, сложность складирования и транспортной логистики и т.п.) для объектов, расположенных в пределах круговой магистральной системы улиц "Садовое кольцо" города Москвы Поправка: Гл.4.Прил.2.2.п.2.2.29_04.00.01.35.003 Наименование: При демонтаже оборудования, предназначенного в лом | CO64: 0 | CP64: =(P64+Q64+S64) -> 19.25 | CQ64: =ROUND((ROUND((AC64*AW64*1),2)*BC64),2) -> 0 | CR64: =(ROUND((ROUND(((((ET64*1.2)*0.3))*AV64*1),2)*BB64),2)+ROUND((ROUND(((AE64-(((EU64*1.2)*0.3)))*AV64*1),2)*BS64),2)) -> 2.51 | CS64: =(ROUND((ROUND(((((EU64*1.2)*0.3))*AV64*1),2)*BS64),2)+ROUND((ROUND(((AE64-(((EU64*1.2)*0.3)))*AV64*1),2)*BS64),2)) -> 0.45 | CT64: =ROUND((ROUND((AF64*AV64*1),2)*BA64),2) -> 77.71 | CU64: =AG64 -> 0 | CV64: =(AH64*AV64) -> 6.8373288 | CW64: =AI64 -> 0 | CX64: =AJ64 -> 0 | CY64: =(ROUND((((S64+ROUND((ROUND(((((EU64*1.2)*0.3))*AV64*1),2)*BS64),2))*AT64)/100),2)+ROUND(((ROUND((ROUND(((AE64-(((EU64*1.2)*0.3)))*AV64*1),2)*BS64),2)*AT64)/100),2)) -> 18.53 | CZ64: =(ROUND((((S64+ROUND((ROUND(((((EU64*1.2)*0.3))*AV64*1),2)*BS64),2))*AU64)/100),2)+ROUND(((ROUND((ROUND(((AE64-(((EU64*1.2)*0.3)))*AV64*1),2)*BS64),2)*AU64)/100),2)) -> 9.74 | DB64: 67 | DD64: *1)*0 | DE64: *1,2)*0,3 | DF64: *1,2)*0,3 | DG64: *1,2)*0,3 | DI64: *1,2)*0,3 | DJ64: *1,2)*0,3 | DN64: 0 | DO64: 0 | DP64: 1 | DQ64: 1 | DU64: 1013 | DV64: 100 М ТРАССЫ | DW64: 100 М ТРАССЫ | DX64: 1 | EE64: 55393971 | EF64: 40 | EG64: Монтаж оборудования | EH64: 0 | EJ64: 2 | EK64: 67 | EL64: ТСН-2001.4-8. Электротехнические установки | EM64: ТСН-2001.4-8-1 | EO64: Поправка: Гл.12.Прил.8.п.8. 3_12.00.01.11.001 Поправка: Гл.4.Прил.2.2.п.2.2.29_04.00.01.35.003 | EQ64: 0 | ER64: 224.18 | ES64: 11.34 | ET64: 6.67 | EU64: 1.2 | EV64: 206.17 | EW64: 18.14 | EX64: 0 | EY64: 0 | FQ64: 0 | FR64: 0 | FS64: 0 | FX64: 97 | FY64: 51 | GD64: 1 | GF64: 1878904797 | GG64: 2 | GH64: 1 | GI64: 2 | GJ64: 0 | GK64: 0 | GL64: =ROUND(IF(AND(BH64=3,BI64=3,FS64<>0),P64,0),2) -> 0 | GM64: =ROUND(O64+X64+Y64,2)+GX64 -> 47.02 | GN64: =IF(OR(BI64=0,BI64=1),GM64-GX64,0) -> 0 | GO64: =IF(BI64=2,GM64-GX64,0) -> 47.02 | GP64: =IF(BI64=4,GM64-GX64,0) -> 0 | GR64: 0 | GS64: 3 | GT64: 0 | GV64: =ROUND((GT64),6) -> 0 | GW64: 1 | GX64: =ROUND(HC64*I64,2) -> 0 | HA64: 0 | HB64: 0 | HC64: =GV64*GW64 -> 0 | HS64: 0 | IK64: 0
A65: 17 | B65: 1 | C65: =ROW(SmtRes!A190) -> 190 | D65: =ROW(EtalonRes!A254) -> 254 | E65: 17 | F65: 4.8-331-2 | G65: Прокладка металлического перфорированного лотка по установленным конструкциям, массой погонного метра до 4 кг / демонтаж лотков | H65: 100 М ТРАССЫ | I65: =ROUND(24/100,9) -> 0.24 | J65: 0 | K65: =ROUND(24/100,9) -> 0.24 | O65: =ROUND(CP65,2) -> 1062.31 | P65: =ROUND((ROUND((AC65*AW65*I65),2)*BC65),2) -> 0 | Q65: =(ROUND((ROUND(((((ET65*1.2)*0.3))*AV65*I65),2)*BB65),2)+ROUND((ROUND(((AE65-(((EU65*1.2)*0.3)))*AV65*I65),2)*BS65),2)) -> 11.38 | R65: =(ROUND((ROUND(((((EU65*1.2)*0.3))*AV65*I65),2)*BS65),2)+ROUND((ROUND(((AE65-(((EU65*1.2)*0.3)))*AV65*I65),2)*BS65),2)) -> 6.2 | S65: =ROUND((ROUND((AF65*AV65*I65),2)*BA65),2) -> 1050.93 | T65: =ROUND(CU65*I65,2) -> 0 | U65: =CV65*I65 -> 1.6409589 | V65: =CW65*I65 -> 0 | W65: =ROUND(CX65*I65,2) -> 0 | X65: =(ROUND((((S65+ROUND((ROUND(((((EU65*1.2)*0.3))*AV65*I65),2)*BS65),2))*AT65)/100),2)+ROUND(((ROUND((ROUND(((AE65-(((EU65*1.2)*0.3)))*AV65*I65),2)*BS65),2)*AT65)/100),2)) -> 1025.42 | Y65: =(ROUND((((S65+ROUND((ROUND(((((EU65*1.2)*0.3))*AV65*I65),2)*BS65),2))*AU65)/100),2)+ROUND(((ROUND((ROUND(((AE65-(((EU65*1.2)*0.3)))*AV65*I65),2)*BS65),2)*AU65)/100),2)) -> 539.14 | AA65: 55944370 | AB65: =ROUND((AC65+AD65+AF65),6) -> 76.6224 | AC65: =ROUND((((ES65*1)*0)),6) -> 0 | AD65: =ROUND((((((ET65*1.2)*0.3))-(((EU65*1.2)*0.3)))+AE65),6) -> 2.4012 | AE65: =ROUND((((EU65*1.2)*0.3)),6) -> 0.432 | AF65: =ROUND((((EV65*1.2)*0.3)),6) -> 74.2212 | AG65: =ROUND((AP65),6) -> 0 | AH65: =(((EW65*1.2)*0.3)) -> 6.5304 | AI65: =(((EX65*1.2)*0.3)) -> 0 | AJ65: =(AS65) -> 0 | AK65: 224.18 | AL65: 11.34 | AM65: 6.67 | AN65: 1.2 | AO65: 206.17 | AP65: 0 | AQ65: 18.14 | AR65: 0 | AS65: 0 | AT65: 97 | AU65: 51 | AV65: 1.047 | AW65: 1 | AZ65: 1 | BA65: 56.35 | BB65: 18.96 | BC65: 8.24 | BH65: 0 | BI65: 2 | BJ65: ТСН-2001.4 Доп. 81, Сб. 8, т. 331, поз. 2 | BM65: 67 | BN65: 0 | BO65: 4.8-331-2 | BP65: 1 | BQ65: 40 | BR65: 0 | BS65: 56.35 | BT65: 1 | BU65: 1 | BV65: 1 | BW65: 1 | BX65: 1 | BZ65: 97 | CA65: 51 | CE65: 1566 | CF65: 0 | CG65: 0 | CM65: 0 | CN65: Поправка: Гл.12.Прил.8.п.8. 3_12.00.01.11.001 Наименование: При наличии напряженных и стесненных условий производства работ (стесненность, сложность складирования и транспортной логистики и т.п.) для объектов, расположенных в пределах круговой магистральной системы улиц "Садовое кольцо" города Москвы Поправка: Гл.4.Прил.2.2.п.2.2.29_04.00.01.35.003 Наименование: При демонтаже оборудования, предназначенного в лом | CO65: 0 | CP65: =(P65+Q65+S65) -> 1062.31 | CQ65: =ROUND((ROUND((AC65*AW65*1),2)*BC65),2) -> 0 | CR65: =(ROUND((ROUND(((((ET65*1.2)*0.3))*AV65*1),2)*BB65),2)+ROUND((ROUND(((AE65-(((EU65*1.2)*0.3)))*AV65*1),2)*BS65),2)) -> 47.59 | CS65: =(ROUND((ROUND(((((EU65*1.2)*0.3))*AV65*1),2)*BS65),2)+ROUND((ROUND(((AE65-(((EU65*1.2)*0.3)))*AV65*1),2)*BS65),2)) -> 25.36 | CT65: =ROUND((ROUND((AF65*AV65*1),2)*BA65),2) -> 4378.96 | CU65: =AG65 -> 0 | CV65: =(AH65*AV65) -> 6.8373288 | CW65: =AI65 -> 0 | CX65: =AJ65 -> 0 | CY65: =(ROUND((((S65+ROUND((ROUND(((((EU65*1.2)*0.3))*AV65*1),2)*BS65),2))*AT65)/100),2)+ROUND(((ROUND((ROUND(((AE65-(((EU65*1.2)*0.3)))*AV65*1),2)*BS65),2)*AT65)/100),2)) -> 1044 | CZ65: =(ROUND((((S65+ROUND((ROUND(((((EU65*1.2)*0.3))*AV65*1),2)*BS65),2))*AU65)/100),2)+ROUND(((ROUND((ROUND(((AE65-(((EU65*1.2)*0.3)))*AV65*1),2)*BS65),2)*AU65)/100),2)) -> 548.91 | DB65: 69 | DD65: *1)*0 | DE65: *1,2)*0,3 | DF65: *1,2)*0,3 | DG65: *1,2)*0,3 | DI65: *1,2)*0,3 | DJ65: *1,2)*0,3 | DN65: 0 | DO65: 0 | DP65: 1 | DQ65: 1 | DU65: 1013 | DV65: 100 М ТРАССЫ | DW65: 100 М ТРАССЫ | DX65: 1 | EE65: 55393971 | EF65: 40 | EG65: Монтаж оборудования | EH65: 0 | EJ65: 2 | EK65: 67 | EL65: ТСН-2001.4-8. Электротехнические установки | EM65: ТСН-2001.4-8-1 | EO65: Поправка: Гл.12.Прил.8.п.8. 3_12.00.01.11.001 Поправка: Гл.4.Прил.2.2.п.2.2.29_04.00.01.35.003 | EQ65: 0 | ER65: 224.18 | ES65: 11.34 | ET65: 6.67 | EU65: 1.2 | EV65: 206.17 | EW65: 18.14 | EX65: 0 | EY65: 0 | FQ65: 0 | FR65: 0 | FS65: 0 | FX65: 97 | FY65: 51 | GD65: 1 | GF65: 1878904797 | GG65: 2 | GH65: 1 | GI65: 2 | GJ65: 0 | GK65: 0 | GL65: =ROUND(IF(AND(BH65=3,BI65=3,FS65<>0),P65,0),2) -> 0 | GM65: =ROUND(O65+X65+Y65,2)+GX65 -> 2626.87 | GN65: =IF(OR(BI65=0,BI65=1),GM65-GX65,0) -> 0 | GO65: =IF(BI65=2,GM65-GX65,0) -> 2626.87 | GP65: =IF(BI65=4,GM65-GX65,0) -> 0 | GR65: 0 | GS65: 3 | GT65: 0 | GV65: =ROUND((GT65),6) -> 0 | GW65: 1 | GX65: =ROUND(HC65*I65,2) -> 0 | HA65: 0 | HB65: 0 | HC65: =GV65*GW65 -> 0 | HS65: 0 | IK65: 0
A66: 17 | B66: 1 | C66: =ROW(SmtRes!A200) -> 200 | D66: =ROW(EtalonRes!A268) -> 268 | E66: 18 | F66: 4.8-331-12 | G66: Установка крышек металлических на лотки металлические перфорированные и неперфорированные массой 1 м свыше 2 до 4 кг / демонтаж крышек лотков | H66: 100 М ТРАССЫ | I66: =ROUND(24/100,9) -> 0.24 | J66: 0 | K66: =ROUND(24/100,9) -> 0.24 | O66: =ROUND(CP66,2) -> 7.93 | P66: =ROUND((ROUND((AC66*AW66*I66),2)*BC66),2) -> 0 | Q66: =(ROUND((ROUND(((((ET66*1.2)*0.3))*AV66*I66),2)*BB66),2)+ROUND((ROUND(((AE66-(((EU66*1.2)*0.3)))*AV66*I66),2)*BS66),2)) -> 0.52 | R66: =(ROUND((ROUND(((((EU66*1.2)*0.3))*AV66*I66),2)*BS66),2)+ROUND((ROUND(((AE66-(((EU66*1.2)*0.3)))*AV66*I66),2)*BS66),2)) -> 0.09 | S66: =ROUND((ROUND((AF66*AV66*I66),2)*BA66),2) -> 7.41 | T66: =ROUND(CU66*I66,2) -> 0 | U66: =CV66*I66 -> 0.65765002 | V66: =CW66*I66 -> 0 | W66: =ROUND(CX66*I66,2) -> 0 | X66: =(ROUND((((S66+ROUND((ROUND(((((EU66*1.2)*0.3))*AV66*I66),2)*BS66),2))*AT66)/100),2)+ROUND(((ROUND((ROUND(((AE66-(((EU66*1.2)*0.3)))*AV66*I66),2)*BS66),2)*AT66)/100),2)) -> 7.28 | Y66: =(ROUND((((S66+ROUND((ROUND(((((EU66*1.2)*0.3))*AV66*I66),2)*BS66),2))*AU66)/100),2)+ROUND(((ROUND((ROUND(((AE66-(((EU66*1.2)*0.3)))*AV66*I66),2)*BS66),2)*AU66)/100),2)) -> 3.83 | AA66: 55944368 | AB66: =ROUND((AC66+AD66+AF66),6) -> 31.5648 | AC66: =ROUND((((ES66*1)*0)),6) -> 0 | AD66: =ROUND((((((ET66*1.2)*0.3))-(((EU66*1.2)*0.3)))+AE66),6) -> 2.0664 | AE66: =ROUND((((EU66*1.2)*0.3)),6) -> 0.378 | AF66: =ROUND((((EV66*1.2)*0.3)),6) -> 29.4984 | AG66: =ROUND((AP66),6) -> 0 | AH66: =(((EW66*1.2)*0.3)) -> 2.6172 | AI66: =(((EX66*1.2)*0.3)) -> 0 | AJ66: =(AS66) -> 0 | AK66: 104.14 | AL66: 16.46 | AM66: 5.74 | AN66: 1.05 | AO66: 81.94 | AP66: 0 | AQ66: 7.27 | AR66: 0 | AS66: 0 | AT66: 97 | AU66: 51 | AV66: 1.047 | AW66: 1 | AZ66: 1 | BA66: 1 | BB66: 1 | BC66: 1 | BH66: 0 | BI66: 2 | BJ66: ТСН-2001.4 Доп. 80, Сб. 8, т. 331, поз. 12 | BM66: 67 | BN66: 0 | BO66: 4.8-331-12 | BP66: 1 | BQ66: 40 | BR66: 0 | BS66: 1 | BT66: 1 | BU66: 1 | BV66: 1 | BW66: 1 | BX66: 1 | BZ66: 97 | CA66: 51 | CE66: 1566 | CF66: 0 | CG66: 0 | CM66: 0 | CN66: Поправка: Гл.12.Прил.8.п.8. 3_12.00.01.11.001 Наименование: При наличии напряженных и стесненных условий производства работ (стесненность, сложность складирования и транспортной логистики и т.п.) для объектов, расположенных в пределах круговой магистральной системы улиц "Садовое кольцо" города Москвы Поправка: Гл.4.Прил.2.2.п.2.2.29_04.00.01.35.003 Наименование: При демонтаже оборудования, предназначенного в лом | CO66: 0 | CP66: =(P66+Q66+S66) -> 7.93 | CQ66: =ROUND((ROUND((AC66*AW66*1),2)*BC66),2) -> 0 | CR66: =(ROUND((ROUND(((((ET66*1.2)*0.3))*AV66*1),2)*BB66),2)+ROUND((ROUND(((AE66-(((EU66*1.2)*0.3)))*AV66*1),2)*BS66),2)) -> 2.16 | CS66: =(ROUND((ROUND(((((EU66*1.2)*0.3))*AV66*1),2)*BS66),2)+ROUND((ROUND(((AE66-(((EU66*1.2)*0.3)))*AV66*1),2)*BS66),2)) -> 0.4 | CT66: =ROUND((ROUND((AF66*AV66*1),2)*BA66),2) -> 30.88 | CU66: =AG66 -> 0 | CV66: =(AH66*AV66) -> 2.7402084 | CW66: =AI66 -> 0 | CX66: =AJ66 -> 0 | CY66: =(ROUND((((S66+ROUND((ROUND(((((EU66*1.2)*0.3))*AV66*1),2)*BS66),2))*AT66)/100),2)+ROUND(((ROUND((ROUND(((AE66-(((EU66*1.2)*0.3)))*AV66*1),2)*BS66),2)*AT66)/100),2)) -> 7.58 | CZ66: =(ROUND((((S66+ROUND((ROUND(((((EU66*1.2)*0.3))*AV66*1),2)*BS66),2))*AU66)/100),2)+ROUND(((ROUND((ROUND(((AE66-(((EU66*1.2)*0.3)))*AV66*1),2)*BS66),2)*AU66)/100),2)) -> 3.98 | DB66: 71 | DD66: *1)*0 | DE66: *1,2)*0,3 | DF66: *1,2)*0,3 | DG66: *1,2)*0,3 | DI66: *1,2)*0,3 | DJ66: *1,2)*0,3 | DN66: 0 | DO66: 0 | DP66: 1 | DQ66: 1 | DU66: 1013 | DV66: 100 М ТРАССЫ | DW66: 100 М ТРАССЫ | DX66: 1 | EE66: 55393971 | EF66: 40 | EG66: Монтаж оборудования | EH66: 0 | EJ66: 2 | EK66: 67 | EL66: ТСН-2001.4-8. Электротехнические установки | EM66: ТСН-2001.4-8-1 | EO66: Поправка: Гл.12.Прил.8.п.8. 3_12.00.01.11.001 Поправка: Гл.4.Прил.2.2.п.2.2.29_04.00.01.35.003 | EQ66: 0 | ER66: 104.14 | ES66: 16.46 | ET66: 5.74 | EU66: 1.05 | EV66: 81.94 | EW66: 7.27 | EX66: 0 | EY66: 0 | FQ66: 0 | FR66: 0 | FS66: 0 | FX66: 97 | FY66: 51 | GD66: 1 | GF66: -1382004924 | GG66: 2 | GH66: 1 | GI66: 2 | GJ66: 0 | GK66: 0 | GL66: =ROUND(IF(AND(BH66=3,BI66=3,FS66<>0),P66,0),2) -> 0 | GM66: =ROUND(O66+X66+Y66,2)+GX66 -> 19.04 | GN66: =IF(OR(BI66=0,BI66=1),GM66-GX66,0) -> 0 | GO66: =IF(BI66=2,GM66-GX66,0) -> 19.04 | GP66: =IF(BI66=4,GM66-GX66,0) -> 0 | GR66: 0 | GS66: 3 | GT66: 0 | GV66: =ROUND((GT66),6) -> 0 | GW66: 1 | GX66: =ROUND(HC66*I66,2) -> 0 | HA66: 0 | HB66: 0 | HC66: =GV66*GW66 -> 0 | HS66: 0 | IK66: 0
A67: 17 | B67: 1 | C67: =ROW(SmtRes!A210) -> 210 | D67: =ROW(EtalonRes!A282) -> 282 | E67: 18 | F67: 4.8-331-12 | G67: Установка крышек металлических на лотки металлические перфорированные и неперфорированные массой 1 м свыше 2 до 4 кг / демонтаж крышек лотков | H67: 100 М ТРАССЫ | I67: =ROUND(24/100,9) -> 0.24 | J67: 0 | K67: =ROUND(24/100,9) -> 0.24 | O67: =ROUND(CP67,2) -> 427.52 | P67: =ROUND((ROUND((AC67*AW67*I67),2)*BC67),2) -> 0 | Q67: =(ROUND((ROUND(((((ET67*1.2)*0.3))*AV67*I67),2)*BB67),2)+ROUND((ROUND(((AE67-(((EU67*1.2)*0.3)))*AV67*I67),2)*BS67),2)) -> 9.97 | R67: =(ROUND((ROUND(((((EU67*1.2)*0.3))*AV67*I67),2)*BS67),2)+ROUND((ROUND(((AE67-(((EU67*1.2)*0.3)))*AV67*I67),2)*BS67),2)) -> 5.07 | S67: =ROUND((ROUND((AF67*AV67*I67),2)*BA67),2) -> 417.55 | T67: =ROUND(CU67*I67,2) -> 0 | U67: =CV67*I67 -> 0.65765002 | V67: =CW67*I67 -> 0 | W67: =ROUND(CX67*I67,2) -> 0 | X67: =(ROUND((((S67+ROUND((ROUND(((((EU67*1.2)*0.3))*AV67*I67),2)*BS67),2))*AT67)/100),2)+ROUND(((ROUND((ROUND(((AE67-(((EU67*1.2)*0.3)))*AV67*I67),2)*BS67),2)*AT67)/100),2)) -> 409.94 | Y67: =(ROUND((((S67+ROUND((ROUND(((((EU67*1.2)*0.3))*AV67*I67),2)*BS67),2))*AU67)/100),2)+ROUND(((ROUND((ROUND(((AE67-(((EU67*1.2)*0.3)))*AV67*I67),2)*BS67),2)*AU67)/100),2)) -> 215.54 | AA67: 55944370 | AB67: =ROUND((AC67+AD67+AF67),6) -> 31.5648 | AC67: =ROUND((((ES67*1)*0)),6) -> 0 | AD67: =ROUND((((((ET67*1.2)*0.3))-(((EU67*1.2)*0.3)))+AE67),6) -> 2.0664 | AE67: =ROUND((((EU67*1.2)*0.3)),6) -> 0.378 | AF67: =ROUND((((EV67*1.2)*0.3)),6) -> 29.4984 | AG67: =ROUND((AP67),6) -> 0 | AH67: =(((EW67*1.2)*0.3)) -> 2.6172 | AI67: =(((EX67*1.2)*0.3)) -> 0 | AJ67: =(AS67) -> 0 | AK67: 104.14 | AL67: 16.46 | AM67: 5.74 | AN67: 1.05 | AO67: 81.94 | AP67: 0 | AQ67: 7.27 | AR67: 0 | AS67: 0 | AT67: 97 | AU67: 51 | AV67: 1.047 | AW67: 1 | AZ67: 1 | BA67: 56.35 | BB67: 19.17 | BC67: 7.31 | BH67: 0 | BI67: 2 | BJ67: ТСН-2001.4 Доп. 80, Сб. 8, т. 331, поз. 12 | BM67: 67 | BN67: 0 | BO67: 4.8-331-12 | BP67: 1 | BQ67: 40 | BR67: 0 | BS67: 56.35 | BT67: 1 | BU67: 1 | BV67: 1 | BW67: 1 | BX67: 1 | BZ67: 97 | CA67: 51 | CE67: 1566 | CF67: 0 | CG67: 0 | CM67: 0 | CN67: Поправка: Гл.12.Прил.8.п.8. 3_12.00.01.11.001 Наименование: При наличии напряженных и стесненных условий производства работ (стесненность, сложность складирования и транспортной логистики и т.п.) для объектов, расположенных в пределах круговой магистральной системы улиц "Садовое кольцо" города Москвы Поправка: Гл.4.Прил.2.2.п.2.2.29_04.00.01.35.003 Наименование: При демонтаже оборудования, предназначенного в лом | CO67: 0 | CP67: =(P67+Q67+S67) -> 427.52 | CQ67: =ROUND((ROUND((AC67*AW67*1),2)*BC67),2) -> 0 | CR67: =(ROUND((ROUND(((((ET67*1.2)*0.3))*AV67*1),2)*BB67),2)+ROUND((ROUND(((AE67-(((EU67*1.2)*0.3)))*AV67*1),2)*BS67),2)) -> 41.41 | CS67: =(ROUND((ROUND(((((EU67*1.2)*0.3))*AV67*1),2)*BS67),2)+ROUND((ROUND(((AE67-(((EU67*1.2)*0.3)))*AV67*1),2)*BS67),2)) -> 22.54 | CT67: =ROUND((ROUND((AF67*AV67*1),2)*BA67),2) -> 1740.09 | CU67: =AG67 -> 0 | CV67: =(AH67*AV67) -> 2.7402084 | CW67: =AI67 -> 0 | CX67: =AJ67 -> 0 | CY67: =(ROUND((((S67+ROUND((ROUND(((((EU67*1.2)*0.3))*AV67*1),2)*BS67),2))*AT67)/100),2)+ROUND(((ROUND((ROUND(((AE67-(((EU67*1.2)*0.3)))*AV67*1),2)*BS67),2)*AT67)/100),2)) -> 426.89 | CZ67: =(ROUND((((S67+ROUND((ROUND(((((EU67*1.2)*0.3))*AV67*1),2)*BS67),2))*AU67)/100),2)+ROUND(((ROUND((ROUND(((AE67-(((EU67*1.2)*0.3)))*AV67*1),2)*BS67),2)*AU67)/100),2)) -> 224.45 | DB67: 73 | DD67: *1)*0 | DE67: *1,2)*0,3 | DF67: *1,2)*0,3 | DG67: *1,2)*0,3 | DI67: *1,2)*0,3 | DJ67: *1,2)*0,3 | DN67: 0 | DO67: 0 | DP67: 1 | DQ67: 1 | DU67: 1013 | DV67: 100 М ТРАССЫ | DW67: 100 М ТРАССЫ | DX67: 1 | EE67: 55393971 | EF67: 40 | EG67: Монтаж оборудования | EH67: 0 | EJ67: 2 | EK67: 67 | EL67: ТСН-2001.4-8. Электротехнические установки | EM67: ТСН-2001.4-8-1 | EO67: Поправка: Гл.12.Прил.8.п.8. 3_12.00.01.11.001 Поправка: Гл.4.Прил.2.2.п.2.2.29_04.00.01.35.003 | EQ67: 0 | ER67: 104.14 | ES67: 16.46 | ET67: 5.74 | EU67: 1.05 | EV67: 81.94 | EW67: 7.27 | EX67: 0 | EY67: 0 | FQ67: 0 | FR67: 0 | FS67: 0 | FX67: 97 | FY67: 51 | GD67: 1 | GF67: -1382004924 | GG67: 2 | GH67: 1 | GI67: 2 | GJ67: 0 | GK67: 0 | GL67: =ROUND(IF(AND(BH67=3,BI67=3,FS67<>0),P67,0),2) -> 0 | GM67: =ROUND(O67+X67+Y67,2)+GX67 -> 1053 | GN67: =IF(OR(BI67=0,BI67=1),GM67-GX67,0) -> 0 | GO67: =IF(BI67=2,GM67-GX67,0) -> 1053 | GP67: =IF(BI67=4,GM67-GX67,0) -> 0 | GR67: 0 | GS67: 3 | GT67: 0 | GV67: =ROUND((GT67),6) -> 0 | GW67: 1 | GX67: =ROUND(HC67*I67,2) -> 0 | HA67: 0 | HB67: 0 | HC67: =GV67*GW67 -> 0 | HS67: 0 | IK67: 0
