Workbook

Sheet Смета по ТСН-2001(с доп.67
A1: =Source!B1 -> Smeta.RU (495) 974-1589
J2: Форма № 4б
B3: "СОГЛАСОВАНО" | G3: "УТВЕРЖДАЮ"
B6: =CONCATENATE("______________________ ", IF(Source!AL12<>"", Source!AL12, "")) -> ______________________ | G6: =CONCATENATE("______________________ ", IF(Source!AH12<>"", Source!AH12, "")) -> ______________________
B7: "_____"________________ 2026 г. | G7: "_____"________________ 2026 г.
A10: Капитальный ремонт здания Государственного бюджетного общеобразовательного учреждения города Москвы «Школа №1574», расположенного по адресу: г. Москва, Старопименовский переулок, д. 5. 1 этап. | AP10: Капитальный ремонт здания Государственного бюджетного общеобразовательного учреждения города Москвы «Школа №1574», расположенного по адресу: г. Москва, Старопименовский переулок, д. 5. 1 этап. 02-01-09 СОУЭ 20.07
A11: (наименование стройки и/или объекта)
A13: =CONCATENATE( "ЛОКАЛЬНАЯ СМЕТА № ",IF(Source!F12<>"Новый объект", Source!F12, "")) -> ЛОКАЛЬНАЯ СМЕТА № 02-01-09
A15: =Source!G20 -> Система оповещения и управления эвакуацией
A16: (наименование работ и затрат)
A18: =CONCATENATE( "Основание: чертежи № ", Source!J12) -> Основание: чертежи № 2024-00375-01-0-ИОС5.2.
I20: В базисном уровне цен | J20: В текущем уровне цен
E21: Сметная стоимость | I21: =I22+I23+I24+I25 -> 410.23 | J21: =J22+J23+J24+J25 -> 8624.83 | K21: тыс.руб.
E22: Строительные работы | I22: =ROUND((Source!F406)/1000, 2) -> 0.88 | J22: =ROUND((Source!P406)/1000, 2) -> 12.92 | K22: тыс.руб.
E23: Работы по монтажу оборудования | I23: =ROUND((Source!F407)/1000, 2) -> 232.84 | J23: =ROUND((Source!P407)/1000, 2) -> 7294.27 | K23: тыс.руб.
E24: Оборудование | I24: =ROUND((Source!F398)/1000, 2) -> 176.51 | J24: =ROUND((Source!P398)/1000, 2) -> 1317.64 | K24: тыс.руб.
E25: Прочие работы и затраты | I25: =ROUND((Source!F408+Source!F409)/1000, 2) -> 0 | J25: =ROUND((Source!P408+Source!P409)/1000, 2) -> 0 | K25: тыс.руб.
E26: Средства на оплату труда | I26: =(Source!F404+ Source!F403)/1000 -> 41.67934 | J26: =((Source!P404 + Source!P403)/1000) -> 2348.6308 | K26: тыс.руб.
E27: Затраты труда | I27: =Source!F411 -> 3479.8297 | K27: чел.-ч.
E28: Кроме того:
E29: Возврат материалов | I29: =SUM(Y1:Y447)/1000 -> 0 | J29: =SUM(Z1:Z447)/1000 -> 0 | K29: тыс.руб.
A31: Составлен(а) по ТСН-2001 с учетом Дополнения №: 81
A32: № и период сборника коэффициентов (индексов) пересчета: Коэффициенты к ТСН-2001 МГЭ Дополнение 81, строительство №219/81 I квартал 2026 года и Коэффициенты к ТСН-2001.13-2 Дополнение 47 №64/47 I квартал 2026 года | AP32: № и период сборника коэффициентов (индексов) пересчета: Коэффициенты к ТСН-2001 МГЭ Дополнение 81, строительство №219/81 I квартал 2026 года и Коэффициенты к ТСН-2001.13-2 Дополнение 47 №64/47 I квартал 2026 года
A33: № п/п | B33: Шифр расценки и коды ресурсов | C33: Наименование работ и затрат | D33: Ед. изм. | E33: Кол-во единиц | F33: Цена на ед. изм., руб. | G33: Попра- вочные коэффи- циенты | H33: Коэффи- циенты зимних удорожа- ний | I33: Всего в ценах на январь 2000 года, руб. | J33: Коэффи- циенты (индек- сы) пере- счета, нормы НР и СП | K33: ВСЕГО затрат в текущем уровне цен, руб.
A34: 1 | B34: 2 | C34: 3 | D34: 4 | E34: 5 | F34: 6 | G34: 7 | H34: 8 | I34: 9 | J34: 10 | K34: 11
A36: =CONCATENATE("Локальная смета: ",IF(Source!G20<>"Новая локальная смета", Source!G20, "")) -> Локальная смета: Система оповещения и управления эвакуацией
A38: =CONCATENATE("Раздел: ",IF(Source!G24<>"Новый раздел", Source!G24, "")) -> Раздел: Демонтажные работы (письмо от АНО «РГТ» об утверждении объёмов демонтажных работ) | AP38: =CONCATENATE("Раздел: ",IF(Source!G24<>"Новый раздел", Source!G24, "")) -> Раздел: Демонтажные работы (письмо от АНО «РГТ» об утверждении объёмов демонтажных работ)
A39: 1 | B39: =Source!F28 -> 4.10-32-2 | C39: Монтаж стойки, полустойки, каркаса стойки или шкафа массой до 300 кг / демонтаж шкафа управления оповещения и эвакуацией пожарного | D39: =Source!H28 -> 1 ШТ. | E39: =Source!I28 -> 1 | Q39: =Source!X28 -> 53.14 | R39: =Source!X29 -> 2994.21 | S39: =Source!Y28 -> 27.16 | T39: =Source!Y29 -> 1530.37 | U39: =ROUND((175/100)*ROUND(Source!R28, 2), 2) -> 4.5 | V39: =ROUND((0/100)*ROUND(Source!R29, 2), 2) -> 0 | AC39: 0
C40: ЗП | F40: =Source!AO28 -> 149.81 | G40: 1,2*0,3 | H40: =Source!AV29 -> 1.047 | I40: =Source!S28 -> 56.47 | J40: =IF(Source!BA29<> 0, Source!BA29, 1) -> 56.35 | K40: =Source!S29 -> 3182.08
C41: ЭМ | F41: =Source!AM28 -> 63.24 | G41: 1,2*0,3 | H41: =Source!AV29 -> 1.047 | I41: =Source!Q28 -> 23.84 | J41: =IF(Source!BB29<> 0, Source!BB29, 1) -> 16.04 | K41: =Source!Q29 -> 382.39
C42: в т.ч. ЗПМ | F42: =Source!AN28 -> 6.81 | G42: 1,2*0,3 | H42: =Source!AV29 -> 1.047 | I42: =Source!R28 -> 2.57 | J42: =IF(Source!BS29<> 0, Source!BS29, 1) -> 56.35 | K42: =Source!R29 -> 144.82
C43: НР от ФОТ | D43: % | E43: =Source!BZ29 -> 90 | I43: =SUM(Q39:Q42) -> 53.14 | J43: =Source!AT29 -> 90 | K43: =SUM(R39:R42) -> 2994.21
C44: СП от ФОТ | D44: % | E44: =Source!CA29 -> 46 | I44: =SUM(S39:S43) -> 27.16 | J44: =Source!AU29 -> 46 | K44: =SUM(T39:T43) -> 1530.37
C45: ЗТР | D45: чел-ч | E45: =Source!AQ28 -> 13.4 | G45: 1,2*0,3 | H45: =Source!AV29 -> 1.047 | I45: =Source!U28 -> 5.050728
C46: ВСЕГО работ по позиции: | H46: =I40+I41+I43+I44+0-0-0 -> 160.61 | J46: =K40+K41+K43+K44+0-0-0 -> 8089.05
C47: ВСЕГО оборудование по позиции: | H47: =0+0 -> 0 | J47: =0+0 -> 0
C48: ВСЕГО по позиции: | H48: =I40+I41+I43+I44+0 -> 160.61 | J48: =K40+K41+K43+K44+0 -> 8089.05 | O48: =I40+I41+I43+I44+0 -> 160.61 | P48: =K40+K41+K43+K44+0 -> 8089.05
A50: 2 | B50: =Source!F30 -> 4.10-151-4 | C50: Установка пульта или табло вызывной сигнализации с количеством сигналов до 20 / демонтаж пульта микрофонного | D50: =Source!H30 -> 1 ШТ. | E50: =Source!I30 -> 1 | Q50: =Source!X30 -> 35.44 | R50: =Source!X31 -> 1997.15 | S50: =Source!Y30 -> 18.11 | T50: =Source!Y31 -> 1020.77 | U50: =ROUND((175/100)*ROUND(Source!R30, 2), 2) -> 0 | V50: =ROUND((0/100)*ROUND(Source!R31, 2), 2) -> 0 | AC50: 0
C51: ЗП | F51: =Source!AO30 -> 104.49 | G51: 1,2*0,3 | H51: =Source!AV31 -> 1.047 | I51: =Source!S30 -> 39.38 | J51: =IF(Source!BA31<> 0, Source!BA31, 1) -> 56.35 | K51: =Source!S31 -> 2219.06
C52: ЭМ | F52: =Source!AM30 -> 0.18 | G52: 1,2*0,3 | H52: =Source!AV31 -> 1.047 | I52: =Source!Q30 -> 0.07 | J52: =IF(Source!BB31<> 0, Source!BB31, 1) -> 9.28 | K52: =Source!Q31 -> 0.65
C53: НР от ФОТ | D53: % | E53: =Source!BZ31 -> 90 | I53: =SUM(Q50:Q52) -> 35.44 | J53: =Source!AT31 -> 90 | K53: =SUM(R50:R52) -> 1997.15
C54: СП от ФОТ | D54: % | E54: =Source!CA31 -> 46 | I54: =SUM(S50:S53) -> 18.11 | J54: =Source!AU31 -> 46 | K54: =SUM(T50:T53) -> 1020.77
C55: ЗТР | D55: чел-ч | E55: =Source!AQ30 -> 9 | G55: 1,2*0,3 | H55: =Source!AV31 -> 1.047 | I55: =Source!U30 -> 3.39228
C56: ВСЕГО работ по позиции: | H56: =I51+I52+I53+I54+0-0-0 -> 93 | J56: =K51+K52+K53+K54+0-0-0 -> 5237.63
C57: ВСЕГО оборудование по позиции: | H57: =0+0 -> 0 | J57: =0+0 -> 0
C58: ВСЕГО по позиции: | H58: =I51+I52+I53+I54+0 -> 93 | J58: =K51+K52+K53+K54+0 -> 5237.63 | O58: =I51+I52+I53+I54+0 -> 93 | P58: =K51+K52+K53+K54+0 -> 5237.63
A60: 3 | B60: =Source!F32 -> 4.10-80-2 | C60: Аппараты приемные, приборы ПС приемно-контрольные, пусковые, концентратор, блок базовый на 20 лучей / демонтаж Прибор приемно-контрольный и управления охранно-пожарный | D60: =Source!H32 -> 1 ШТ. | E60: =Source!I32 -> 2 | Q60: =Source!X32 -> 104.79 | R60: =Source!X33 -> 5904.75 | S60: =Source!Y32 -> 53.56 | T60: =Source!Y33 -> 3017.98 | U60: =ROUND((175/100)*ROUND(Source!R32, 2), 2) -> 0.02 | V60: =ROUND((0/100)*ROUND(Source!R33, 2), 2) -> 0 | AC60: 0
C61: ЗП | F61: =Source!AO32 -> 154.44 | G61: 1,2*0,3 | H61: =Source!AV33 -> 1.047 | I61: =Source!S32 -> 116.42 | J61: =IF(Source!BA33<> 0, Source!BA33, 1) -> 56.35 | K61: =Source!S33 -> 6560.27
C62: ЭМ | F62: =Source!AM32 -> 0.06 | G62: 1,2*0,3 | H62: =Source!AV33 -> 1.047 | I62: =Source!Q32 -> 0.05 | J62: =IF(Source!BB33<> 0, Source!BB33, 1) -> 18.5 | K62: =Source!Q33 -> 0.93
C63: в т.ч. ЗПМ | F63: =Source!AN32 -> 0.01 | G63: 1,2*0,3 | H63: =Source!AV33 -> 1.047 | I63: =Source!R32 -> 0.01 | J63: =IF(Source!BS33<> 0, Source!BS33, 1) -> 56.35 | K63: =Source!R33 -> 0.56
C64: НР от ФОТ | D64: % | E64: =Source!BZ33 -> 90 | I64: =SUM(Q60:Q63) -> 104.79 | J64: =Source!AT33 -> 90 | K64: =SUM(R60:R63) -> 5904.75
C65: СП от ФОТ | D65: % | E65: =Source!CA33 -> 46 | I65: =SUM(S60:S64) -> 53.56 | J65: =Source!AU33 -> 46 | K65: =SUM(T60:T64) -> 3017.98
C66: ЗТР | D66: чел-ч | E66: =Source!AQ32 -> 11.7 | G66: 1,2*0,3 | H66: =Source!AV33 -> 1.047 | I66: =Source!U32 -> 8.819928
C67: ВСЕГО работ по позиции: | H67: =I61+I62+I64+I65+0-0-0 -> 274.82 | J67: =K61+K62+K64+K65+0-0-0 -> 15483.93
C68: ВСЕГО оборудование по позиции: | H68: =0+0 -> 0 | J68: =0+0 -> 0
C69: ВСЕГО по позиции: | H69: =I61+I62+I64+I65+0 -> 274.82 | J69: =K61+K62+K64+K65+0 -> 15483.93 | O69: =I61+I62+I64+I65+0 -> 274.82 | P69: =K61+K62+K64+K65+0 -> 15483.93
A71: 4 | B71: =Source!F34 -> 4.10-34-5 | C71: Монтаж коммутатора служебной связи / демонтаж модуля речевых сообщений | D71: =Source!H34 -> 1 ШТ. | E71: =Source!I34 -> 1 | Q71: =Source!X34 -> 27.61 | R71: =Source!X35 -> 1555.94 | S71: =Source!Y34 -> 14.11 | T71: =Source!Y35 -> 795.26 | U71: =ROUND((175/100)*ROUND(Source!R34, 2), 2) -> 2.08 | V71: =ROUND((0/100)*ROUND(Source!R35, 2), 2) -> 0 | AC71: 0
C72: ЗП | F72: =Source!AO34 -> 78.24 | G72: 1,2*0,3 | H72: =Source!AV35 -> 1.047 | I72: =Source!S34 -> 29.49 | J72: =IF(Source!BA35<> 0, Source!BA35, 1) -> 56.35 | K72: =Source!S35 -> 1661.76
C73: ЭМ | F73: =Source!AM34 -> 28.71 | G73: 1,2*0,3 | H73: =Source!AV35 -> 1.047 | I73: =Source!Q34 -> 10.82 | J73: =IF(Source!BB35<> 0, Source!BB35, 1) -> 16.16 | K73: =Source!Q35 -> 174.85
C74: в т.ч. ЗПМ | F74: =Source!AN34 -> 3.16 | G74: 1,2*0,3 | H74: =Source!AV35 -> 1.047 | I74: =Source!R34 -> 1.19 | J74: =IF(Source!BS35<> 0, Source!BS35, 1) -> 56.35 | K74: =Source!R35 -> 67.06
C75: НР от ФОТ | D75: % | E75: =Source!BZ35 -> 90 | I75: =SUM(Q71:Q74) -> 27.61 | J75: =Source!AT35 -> 90 | K75: =SUM(R71:R74) -> 1555.94
C76: СП от ФОТ | D76: % | E76: =Source!CA35 -> 46 | I76: =SUM(S71:S75) -> 14.11 | J76: =Source!AU35 -> 46 | K76: =SUM(T71:T75) -> 795.26
C77: ЗТР | D77: чел-ч | E77: =Source!AQ34 -> 6.2 | G77: 1,2*0,3 | H77: =Source!AV35 -> 1.047 | I77: =Source!U34 -> 2.336904
C78: ВСЕГО работ по позиции: | H78: =I72+I73+I75+I76+0-0-0 -> 82.03 | J78: =K72+K73+K75+K76+0-0-0 -> 4187.81
C79: ВСЕГО оборудование по позиции: | H79: =0+0 -> 0 | J79: =0+0 -> 0
C80: ВСЕГО по позиции: | H80: =I72+I73+I75+I76+0 -> 82.03 | J80: =K72+K73+K75+K76+0 -> 4187.81 | O80: =I72+I73+I75+I76+0 -> 82.03 | P80: =K72+K73+K75+K76+0 -> 4187.81
A82: 5 | B82: =Source!F36 -> 4.10-167-1 | C82: Монтаж блока питания сети (БПС) в диспетчерской / демонтаж блоков электропитания | D82: =Source!H36 -> 1 ШТ. | E82: =Source!I36 -> 12 | Q82: =Source!X36 -> 77.1 | R82: =Source!X37 -> 4344.75 | S82: =Source!Y36 -> 39.41 | T82: =Source!Y37 -> 2220.65 | U82: =ROUND((175/100)*ROUND(Source!R36, 2), 2) -> 0 | V82: =ROUND((0/100)*ROUND(Source!R37, 2), 2) -> 0 | AC82: 0
C83: ="Объем: "&Source!I36&"=2+"&"2+"&"4+"&"4" -> Объем: 12=2+2+4+4
C84: ЗП | F84: =Source!AO36 -> 18.94 | G84: 1,2*0,3 | H84: =Source!AV37 -> 1.047 | I84: =Source!S36 -> 85.67 | J84: =IF(Source!BA37<> 0, Source!BA37, 1) -> 56.35 | K84: =Source!S37 -> 4827.5
C85: ЭМ | F85: =Source!AM36 -> 0.02 | G85: 1,2*0,3 | H85: =Source!AV37 -> 1.047 | I85: =Source!Q36 -> 0.09 | J85: =IF(Source!BB37<> 0, Source!BB37, 1) -> 11 | K85: =Source!Q37 -> 0.99
C86: НР от ФОТ | D86: % | E86: =Source!BZ37 -> 90 | I86: =SUM(Q82:Q85) -> 77.1 | J86: =Source!AT37 -> 90 | K86: =SUM(R82:R85) -> 4344.75
C87: СП от ФОТ | D87: % | E87: =Source!CA37 -> 46 | I87: =SUM(S82:S86) -> 39.41 | J87: =Source!AU37 -> 46 | K87: =SUM(T82:T86) -> 2220.65
C88: ЗТР | D88: чел-ч | E88: =Source!AQ36 -> 1.36 | G88: 1,2*0,3 | H88: =Source!AV37 -> 1.047 | I88: =Source!U36 -> 6.1513344
C89: ВСЕГО работ по позиции: | H89: =I84+I85+I86+I87+0-0-0 -> 202.27 | J89: =K84+K85+K86+K87+0-0-0 -> 11393.89
C90: ВСЕГО оборудование по позиции: | H90: =0+0 -> 0 | J90: =0+0 -> 0
C91: ВСЕГО по позиции: | H91: =I84+I85+I86+I87+0 -> 202.27 | J91: =K84+K85+K86+K87+0 -> 11393.89 | O91: =I84+I85+I86+I87+0 -> 202.27 | P91: =K84+K85+K86+K87+0 -> 11393.89
A93: 6 | B93: =Source!F38 -> 4.10-81-2 | C93: Извещатели ПС автоматические, дымовой, фотоэлектрический, радиоизотопный, световой в нормальном исполнении / демонтаж оповещателей | D93: =Source!H38 -> 1 ШТ. | E93: =Source!I38 -> 116 | Q93: =Source!X38 -> 834.62 | R93: =Source!X39 -> 47031.06 | S93: =Source!Y38 -> 426.59 | T93: =Source!Y39 -> 24038.1 | U93: =ROUND((175/100)*ROUND(Source!R38, 2), 2) -> 0.77 | V93: =ROUND((0/100)*ROUND(Source!R39, 2), 2) -> 0 | AC93: 0
C94: ="Объем: "&Source!I38&"=12+"&"18+"&"2+"&"4+"&"1+"&"1+"&"1+"&"63+"&"1+"&"10+"&"2+"&"1" -> Объем: 116=12+18+2+4+1+1+1+63+1+10+2+1
C95: ЗП | F95: =Source!AO38 -> 21.2 | G95: 1,2*0,3 | H95: =Source!AV39 -> 1.047 | I95: =Source!S38 -> 926.92 | J95: =IF(Source!BA39<> 0, Source!BA39, 1) -> 56.35 | K95: =Source!S39 -> 52231.94
C96: ЭМ | F96: =Source!AM38 -> 0.06 | G96: 1,2*0,3 | H96: =Source!AV39 -> 1.047 | I96: =Source!Q38 -> 2.62 | J96: =IF(Source!BB39<> 0, Source!BB39, 1) -> 18.5 | K96: =Source!Q39 -> 48.47
C97: в т.ч. ЗПМ | F97: =Source!AN38 -> 0.01 | G97: 1,2*0,3 | H97: =Source!AV39 -> 1.047 | I97: =Source!R38 -> 0.44 | J97: =IF(Source!BS39<> 0, Source!BS39, 1) -> 56.35 | K97: =Source!R39 -> 24.79
C98: НР от ФОТ | D98: % | E98: =Source!BZ39 -> 90 | I98: =SUM(Q93:Q97) -> 834.62 | J98: =Source!AT39 -> 90 | K98: =SUM(R93:R97) -> 47031.06
C99: СП от ФОТ | D99: % | E99: =Source!CA39 -> 46 | I99: =SUM(S93:S98) -> 426.59 | J99: =Source!AU39 -> 46 | K99: =SUM(T93:T98) -> 24038.1
C100: ЗТР | D100: чел-ч | E100: =Source!AQ38 -> 1.68 | G100: 1,2*0,3 | H100: =Source!AV39 -> 1.047 | I100: =Source!U38 -> 73.45417
C101: ВСЕГО работ по позиции: | H101: =I95+I96+I98+I99+0-0-0 -> 2190.75 | J101: =K95+K96+K98+K99+0-0-0 -> 123349.57
C102: ВСЕГО оборудование по позиции: | H102: =0+0 -> 0 | J102: =0+0 -> 0
C103: ВСЕГО по позиции: | H103: =I95+I96+I98+I99+0 -> 2190.75 | J103: =K95+K96+K98+K99+0 -> 123349.57 | O103: =I95+I96+I98+I99+0 -> 2190.75 | P103: =K95+K96+K98+K99+0 -> 123349.57
A105: 7 | B105: =Source!F40 -> 4.10-76-7 | C105: Монтаж громкоговорителя или звуковой колонки в помещении / демонтаж громкоговорителей | D105: =Source!H40 -> 1 ШТ. | E105: =Source!I40 -> 186 | Q105: =Source!X40 -> 1583.79 | R105: =Source!X41 -> 89246.71 | S105: =Source!Y40 -> 883.59 | T105: =Source!Y41 -> 49790.27 | U105: =ROUND((175/100)*ROUND(Source!R40, 2), 2) -> 0 | V105: =ROUND((0/100)*ROUND(Source!R41, 2), 2) -> 0 | AC105: 0
C106: ="Объем: "&Source!I40&"=144+"&"42" -> Объем: 186=144+42
C107: ЗП | F107: =Source!AO40 -> 23.78 | G107: 1,2*0,3 | H107: =Source!AV41 -> 1.047 | I107: =Source!S40 -> 1667.15 | J107: =IF(Source!BA41<> 0, Source!BA41, 1) -> 56.35 | K107: =Source!S41 -> 93943.9
C108: НР от ФОТ | D108: % | E108: =Source!BZ41 -> 95 | I108: =SUM(Q105:Q107) -> 1583.79 | J108: =Source!AT41 -> 95 | K108: =SUM(R105:R107) -> 89246.71
C109: СП от ФОТ | D109: % | E109: =Source!CA41 -> 53 | I109: =SUM(S105:S108) -> 883.59 | J109: =Source!AU41 -> 53 | K109: =SUM(T105:T108) -> 49790.27
C110: ЗТР | D110: чел-ч | E110: =Source!AQ40 -> 2 | G110: 1,2*0,3 | H110: =Source!AV41 -> 1.047 | I110: =Source!U40 -> 140.21424
C111: ВСЕГО работ по позиции: | H111: =I107+I108+I109+0-0-0 -> 4134.53 | J111: =K107+K108+K109+0-0-0 -> 232980.88
C112: ВСЕГО оборудование по позиции: | H112: =0+0 -> 0 | J112: =0+0 -> 0
C113: ВСЕГО по позиции: | H113: =I107+I108+I109+0 -> 4134.53 | J113: =K107+K108+K109+0 -> 232980.88 | O113: =I107+I108+I109+0 -> 4134.53 | P113: =K107+K108+K109+0 -> 232980.88
A115: 8 | B115: =Source!F42 -> 4.10-118-12 | C115: Установка для трубных проводок коробки оконечной / демонтаж фильтра оконечного | D115: =Source!H42 -> 100 шт. | E115: =Source!I42 -> 0.07 | Q115: =Source!X42 -> 6.62 | R115: =Source!X43 -> 372.75 | S115: =Source!Y42 -> 3.38 | T115: =Source!Y43 -> 190.52 | U115: =ROUND((175/100)*ROUND(Source!R42, 2), 2) -> 0 | V115: =ROUND((0/100)*ROUND(Source!R43, 2), 2) -> 0 | AC115: 0
C116: ="Объем: "&Source!I42&"=7/"&"100" -> Объем: 0,07=7/100
C117: ЗП | F117: =Source!AO42 -> 278.64 | G117: 1,2*0,3 | H117: =Source!AV43 -> 1.047 | I117: =Source!S42 -> 7.35 | J117: =IF(Source!BA43<> 0, Source!BA43, 1) -> 56.35 | K117: =Source!S43 -> 414.17
C118: НР от ФОТ | D118: % | E118: =Source!BZ43 -> 90 | I118: =SUM(Q115:Q117) -> 6.62 | J118: =Source!AT43 -> 90 | K118: =SUM(R115:R117) -> 372.75
...

Sheet Source
A1: 0 | B1: Smeta.RU (495) 974-1589 | D1: _PS_ | F1: 0 | G1: 0 | H1: 0 | I1: Smeta.RU | K1: 1 | L1: 74599 | M1: 10 | N1: 12 | O1: 1 | P1: 0 | Q1: 5
A4: 1 | B4: 1 | C4: -1 | G4: Капитальный ремонт здания Государственного бюджетного общеобразовательного учреждения города Москвы «Школа №1574», расположенного по адресу: г. Москва, Старопименовский переулок, д. 5. 1 этап | EC4: 0
A5: 8 | B5: 1 | C5: -1 | G5: Капитальный ремонт здания Государственного бюджетного общеобразовательного учреждения города Москвы «Школа №1574», расположенного по адресу: г. Москва, Старопименовский переулок, д. 5. 1 этап | EC5: 0
A12: 1 | B12: 428 | C12: 0 | D12: =ROW(A389) -> 389 | E12: 0 | F12: 02-01-09 | G12: 02-01-09 СОУЭ 20.07 | I12: 0 | J12: 2024-00375-01-0-ИОС5.2. | K12: 0 | L12: 0 | M12: 4098 | O12: 0 | P12: 0 | Q12: 0 | R12: 0 | S12: 0 | T12: 1 | V12: 2 | AB12: О.А.Гришечкина | AC12: Ведущий инженер-сметчик | AD12: И.В.Феденко | AE12: Начальник отдела | BB12: 0 | BH12: Сметные нормы списания | BI12: Коды ОКП для ТСН-2001 МГЭ Дополнение 81 | BJ12: 1 | BK12: 1 | BL12: 0 | BM12: 0 | BN12: 1 | BO12: 0 | BP12: 6 | BQ12: 2 | BR12: 1 | BS12: 1 | BT12: 0 | BU12: 0 | BV12: 0 | BW12: 0 | BX12: 0 | BY12: ТСН-2001 (МГЭ) Доп 81 - Новое строительство | BZ12: Типовой расчет для ТСН-2001 МГЭ, Дополнение 81, строительство | CA12: Территориальные сметные нормативы для Москвы ТСН-2001 (МГЭ), дополнение 81 | CB12: Территориальные сметные нормативы для Москвы ТСН-2001 (МГЭ), дополнение 81 | CC12: Территориальные сметные нормативы для Москвы ТСН-2001 (МГЭ), дополнение 81 | CD12: Территориальные сметные нормативы для Москвы ТСН-2001 (МГЭ), дополнение 81 | CE12: Поправки для ТСН-2001 от 07.04.2026 г. доп.81 | CF12: 0 | CG12: 0 | CH12: 8200 | CK12: 82 | CQ12: Территориальные сметные нормативы для Москвы (ТСН-2001) | CR12: ТЕР | CS12: 41660 | CT12: 1 | CU12: 81 | CY12: 0 | EC12: 0
A15: 15 | B15: 1
A18: 52 | B18: =B389 -> 428 | C18: =C389 -> 1 | D18: =D389 -> 12 | E18: =E389 -> 0 | F18: =F389 -> 02-01-09 | G18: =G389 -> 02-01-09 СОУЭ 20.07 | O18: =O389 -> 352494.46 | P18: =P389 -> 309995.38 | Q18: =Q389 -> 857.25 | R18: =R389 -> 37.51 | S18: =S389 -> 41641.83 | T18: =T389 -> 0 | U18: =U389 -> 3479.8297 | V18: =V389 -> 0 | ... GX18: =GX389 -> 0
A20: 3 | B20: 1 | D20: =ROW(A359) -> 359 | F20: 02-01-09 | G20: Система оповещения и управления эвакуацией | I20: 0 | J20: 2024-00375-01-0-ИОС5.2 | K20: -1 | L20: 02-01-09 | S20: 0 | T20: 0 | V20: 2 | BX20: 0 | CF20: 0 | CG20: 0
A22: 52 | B22: =B359 -> 1 | C22: =C359 -> 3 | D22: =D359 -> 20 | E22: =E359 -> 0 | F22: =F359 -> 02-01-09 | G22: =G359 -> Система оповещения и управления эвакуацией | O22: =O359 -> 352494.46 | P22: =P359 -> 309995.38 | Q22: =Q359 -> 857.25 | R22: =R359 -> 37.51 | S22: =S359 -> 41641.83 | T22: =T359 -> 0 | U22: =U359 -> 3479.8297 | V22: =V359 -> 0 | ... GX22: =GX359 -> 0
A24: 4 | B24: 1 | D24: =ROW(A53) -> 53 | F24: Новый раздел | G24: Демонтажные работы (письмо от АНО «РГТ» об утверждении объёмов демонтажных работ) | I24: 0 | K24: -1 | S24: 0 | T24: 0 | V24: 2 | BX24: 0 | CJ24: 0
A26: 52 | B26: =B53 -> 1 | C26: =C53 -> 4 | D26: =D53 -> 24 | E26: =E53 -> 0 | F26: =F53 -> Новый раздел | G26: =G53 -> Демонтажные работы (письмо от АНО «РГТ» об утверждении объёмов демонтажных работ) | O26: =O53 -> 10173.78 | P26: =P53 -> 0 | Q26: =Q53 -> 158.25 | R26: =R53 -> 4.24 | S26: =S53 -> 10015.53 | T26: =T53 -> 0 | U26: =U53 -> 836.40381 | V26: =V53 -> 0 | ... GX26: =GX53 -> 0
A28: 17 | B28: 1 | C28: =ROW(SmtRes!A5) -> 5 | D28: =ROW(EtalonRes!A6) -> 6 | E28: 1 | F28: 4.10-32-2 | G28: Монтаж стойки, полустойки, каркаса стойки или шкафа массой до 300 кг / демонтаж шкафа управления оповещения и эвакуацией пожарного | H28: 1 ШТ. | I28: 1 | J28: 0 | K28: 1 | O28: =ROUND(CP28,2) -> 80.31 | P28: =ROUND((ROUND((AC28*AW28*I28),2)*BC28),2) -> 0 | Q28: =(ROUND((ROUND(((((ET28*1.2)*0.3))*AV28*I28),2)*BB28),2)+ROUND((ROUND(((AE28-(((EU28*1.2)*0.3)))*AV28*I28),2)*BS28),2)) -> 23.84 | R28: =(ROUND((ROUND(((((EU28*1.2)*0.3))*AV28*I28),2)*BS28),2)+ROUND((ROUND(((AE28-(((EU28*1.2)*0.3)))*AV28*I28),2)*BS28),2)) -> 2.57 | S28: =ROUND((ROUND((AF28*AV28*I28),2)*BA28),2) -> 56.47 | T28: =ROUND(CU28*I28,2) -> 0 | U28: =CV28*I28 -> 5.050728 | V28: =CW28*I28 -> 0 | W28: =ROUND(CX28*I28,2) -> 0 | X28: =(ROUND((((S28+ROUND((ROUND(((((EU28*1.2)*0.3))*AV28*I28),2)*BS28),2))*AT28)/100),2)+ROUND(((ROUND((ROUND(((AE28-(((EU28*1.2)*0.3)))*AV28*I28),2)*BS28),2)*AT28)/100),2)) -> 53.14 | Y28: =(ROUND((((S28+ROUND((ROUND(((((EU28*1.2)*0.3))*AV28*I28),2)*BS28),2))*AU28)/100),2)+ROUND(((ROUND((ROUND(((AE28-(((EU28*1.2)*0.3)))*AV28*I28),2)*BS28),2)*AU28)/100),2)) -> 27.16 | AA28: 57014138 | AB28: =ROUND((AC28+AD28+AF28),6) -> 76.698 | AC28: =ROUND((((ES28*1)*0)),6) -> 0 | AD28: =ROUND((((((ET28*1.2)*0.3))-(((EU28*1.2)*0.3)))+AE28),6) -> 22.7664 | AE28: =ROUND((((EU28*1.2)*0.3)),6) -> 2.4516 | AF28: =ROUND((((EV28*1.2)*0.3)),6) -> 53.9316 | AG28: =ROUND((AP28),6) -> 0 | AH28: =(((EW28*1.2)*0.3)) -> 4.824 | AI28: =(((EX28*1.2)*0.3)) -> 0 | AJ28: =(AS28) -> 0 | AK28: 216.97 | AL28: 3.92 | AM28: 63.24 | AN28: 6.81 | AO28: 149.81 | AP28: 0 | AQ28: 13.4 | AR28: 0 | AS28: 0 | AT28: 90 | AU28: 46 | AV28: 1.047 | AW28: 1 | AZ28: 1 | BA28: 1 | BB28: 1 | BC28: 1 | BH28: 0 | BI28: 2 | BJ28: ТСН-2001.4 Доп. 80, Сб. 10, т. 32, поз. 2 | BM28: 68 | BN28: 0 | BO28: 4.10-32-2 | BP28: 1 | BQ28: 40 | BR28: 0 | BS28: 1 | BT28: 1 | BU28: 1 | BV28: 1 | BW28: 1 | BX28: 1 | BZ28: 90 | CA28: 46 | CE28: 1566 | CF28: 0 | CG28: 0 | CM28: 0 | CN28: Поправка: Гл.12.Прил.8.п.8. 3_12.00.01.11.001 Наименование: При наличии напряженных и стесненных условий производства работ (стесненность, сложность складирования и транспортной логистики и т.п.) для объектов, расположенных в пределах круговой магистральной системы улиц "Садовое кольцо" города Москвы Поправка: Гл.4.Прил.2.2.п.2.2.29_04.00.01.35.003 Наименование: При демонтаже оборудования, предназначенного в лом | CO28: 0 | CP28: =(P28+Q28+S28) -> 80.31 | CQ28: =ROUND((ROUND((AC28*AW28*1),2)*BC28),2) -> 0 | CR28: =(ROUND((ROUND(((((ET28*1.2)*0.3))*AV28*1),2)*BB28),2)+ROUND((ROUND(((AE28-(((EU28*1.2)*0.3)))*AV28*1),2)*BS28),2)) -> 23.84 | CS28: =(ROUND((ROUND(((((EU28*1.2)*0.3))*AV28*1),2)*BS28),2)+ROUND((ROUND(((AE28-(((EU28*1.2)*0.3)))*AV28*1),2)*BS28),2)) -> 2.57 | CT28: =ROUND((ROUND((AF28*AV28*1),2)*BA28),2) -> 56.47 | CU28: =AG28 -> 0 | CV28: =(AH28*AV28) -> 5.050728 | CW28: =AI28 -> 0 | CX28: =AJ28 -> 0 | CY28: =(ROUND((((S28+ROUND((ROUND(((((EU28*1.2)*0.3))*AV28*1),2)*BS28),2))*AT28)/100),2)+ROUND(((ROUND((ROUND(((AE28-(((EU28*1.2)*0.3)))*AV28*1),2)*BS28),2)*AT28)/100),2)) -> 53.14 | CZ28: =(ROUND((((S28+ROUND((ROUND(((((EU28*1.2)*0.3))*AV28*1),2)*BS28),2))*AU28)/100),2)+ROUND(((ROUND((ROUND(((AE28-(((EU28*1.2)*0.3)))*AV28*1),2)*BS28),2)*AU28)/100),2)) -> 27.16 | DB28: 1 | DD28: *1)*0 | DE28: *1,2)*0,3 | DF28: *1,2)*0,3 | DG28: *1,2)*0,3 | DI28: *1,2)*0,3 | DJ28: *1,2)*0,3 | DN28: 0 | DO28: 0 | DP28: 1 | DQ28: 1 | DU28: 1013 | DV28: 1 ШТ. | DW28: 1 ШТ. | DX28: 1 | EE28: 57042958 | EF28: 40 | EG28: Монтаж оборудования | EH28: 0 | EJ28: 2 | EK28: 68 | EL28: ТСН-2001.4-10. Прокладка и монтаж сетей связи | EM28: ТСН-2001.4-10-1 | EO28: Поправка: Гл.12.Прил.8.п.8. 3_12.00.01.11.001 Поправка: Гл.4.Прил.2.2.п.2.2.29_04.00.01.35.003 | EQ28: 0 | ER28: 216.97 | ES28: 3.92 | ET28: 63.24 | EU28: 6.81 | EV28: 149.81 | EW28: 13.4 | EX28: 0 | EY28: 0 | FQ28: 0 | FR28: 0 | FS28: 0 | FX28: 90 | FY28: 46 | GD28: 1 | GF28: 1360940533 | GG28: 2 | GH28: 1 | GI28: 2 | GJ28: 0 | GK28: 0 | GL28: =ROUND(IF(AND(BH28=3,BI28=3,FS28<>0),P28,0),2) -> 0 | GM28: =ROUND(O28+X28+Y28,2)+GX28 -> 160.61 | GN28: =IF(OR(BI28=0,BI28=1),GM28-GX28,0) -> 0 | GO28: =IF(BI28=2,GM28-GX28,0) -> 160.61 | GP28: =IF(BI28=4,GM28-GX28,0) -> 0 | GR28: 0 | GS28: 3 | GT28: 0 | GV28: =ROUND((GT28),6) -> 0 | GW28: 1 | GX28: =ROUND(HC28*I28,2) -> 0 | HA28: 0 | HB28: 0 | HC28: =GV28*GW28 -> 0 | HS28: 0 | IK28: 0
A29: 17 | B29: 1 | C29: =ROW(SmtRes!A10) -> 10 | D29: =ROW(EtalonRes!A12) -> 12 | E29: 1 | F29: 4.10-32-2 | G29: Монтаж стойки, полустойки, каркаса стойки или шкафа массой до 300 кг / демонтаж шкафа управления оповещения и эвакуацией пожарного | H29: 1 ШТ. | I29: 1 | J29: 0 | K29: 1 | O29: =ROUND(CP29,2) -> 3564.47 | P29: =ROUND((ROUND((AC29*AW29*I29),2)*BC29),2) -> 0 | Q29: =(ROUND((ROUND(((((ET29*1.2)*0.3))*AV29*I29),2)*BB29),2)+ROUND((ROUND(((AE29-(((EU29*1.2)*0.3)))*AV29*I29),2)*BS29),2)) -> 382.39 | R29: =(ROUND((ROUND(((((EU29*1.2)*0.3))*AV29*I29),2)*BS29),2)+ROUND((ROUND(((AE29-(((EU29*1.2)*0.3)))*AV29*I29),2)*BS29),2)) -> 144.82 | S29: =ROUND((ROUND((AF29*AV29*I29),2)*BA29),2) -> 3182.08 | T29: =ROUND(CU29*I29,2) -> 0 | U29: =CV29*I29 -> 5.050728 | V29: =CW29*I29 -> 0 | W29: =ROUND(CX29*I29,2) -> 0 | X29: =(ROUND((((S29+ROUND((ROUND(((((EU29*1.2)*0.3))*AV29*I29),2)*BS29),2))*AT29)/100),2)+ROUND(((ROUND((ROUND(((AE29-(((EU29*1.2)*0.3)))*AV29*I29),2)*BS29),2)*AT29)/100),2)) -> 2994.21 | Y29: =(ROUND((((S29+ROUND((ROUND(((((EU29*1.2)*0.3))*AV29*I29),2)*BS29),2))*AU29)/100),2)+ROUND(((ROUND((ROUND(((AE29-(((EU29*1.2)*0.3)))*AV29*I29),2)*BS29),2)*AU29)/100),2)) -> 1530.37 | AA29: 57014140 | AB29: =ROUND((AC29+AD29+AF29),6) -> 76.698 | AC29: =ROUND((((ES29*1)*0)),6) -> 0 | AD29: =ROUND((((((ET29*1.2)*0.3))-(((EU29*1.2)*0.3)))+AE29),6) -> 22.7664 | AE29: =ROUND((((EU29*1.2)*0.3)),6) -> 2.4516 | AF29: =ROUND((((EV29*1.2)*0.3)),6) -> 53.9316 | AG29: =ROUND((AP29),6) -> 0 | AH29: =(((EW29*1.2)*0.3)) -> 4.824 | AI29: =(((EX29*1.2)*0.3)) -> 0 | AJ29: =(AS29) -> 0 | AK29: 216.97 | AL29: 3.92 | AM29: 63.24 | AN29: 6.81 | AO29: 149.81 | AP29: 0 | AQ29: 13.4 | AR29: 0 | AS29: 0 | AT29: 90 | AU29: 46 | AV29: 1.047 | AW29: 1 | AZ29: 1 | BA29: 56.35 | BB29: 16.04 | BC29: 7.12 | BH29: 0 | BI29: 2 | BJ29: ТСН-2001.4 Доп. 80, Сб. 10, т. 32, поз. 2 | BM29: 68 | BN29: 0 | BO29: 4.10-32-2 | BP29: 1 | BQ29: 40 | BR29: 0 | BS29: 56.35 | BT29: 1 | BU29: 1 | BV29: 1 | BW29: 1 | BX29: 1 | BZ29: 90 | CA29: 46 | CE29: 1566 | CF29: 0 | CG29: 0 | CM29: 0 | CN29: Поправка: Гл.12.Прил.8.п.8. 3_12.00.01.11.001 Наименование: При наличии напряженных и стесненных условий производства работ (стесненность, сложность складирования и транспортной логистики и т.п.) для объектов, расположенных в пределах круговой магистральной системы улиц "Садовое кольцо" города Москвы Поправка: Гл.4.Прил.2.2.п.2.2.29_04.00.01.35.003 Наименование: При демонтаже оборудования, предназначенного в лом | CO29: 0 | CP29: =(P29+Q29+S29) -> 3564.47 | CQ29: =ROUND((ROUND((AC29*AW29*1),2)*BC29),2) -> 0 | CR29: =(ROUND((ROUND(((((ET29*1.2)*0.3))*AV29*1),2)*BB29),2)+ROUND((ROUND(((AE29-(((EU29*1.2)*0.3)))*AV29*1),2)*BS29),2)) -> 382.39 | CS29: =(ROUND((ROUND(((((EU29*1.2)*0.3))*AV29*1),2)*BS29),2)+ROUND((ROUND(((AE29-(((EU29*1.2)*0.3)))*AV29*1),2)*BS29),2)) -> 144.82 | CT29: =ROUND((ROUND((AF29*AV29*1),2)*BA29),2) -> 3182.08 | CU29: =AG29 -> 0 | CV29: =(AH29*AV29) -> 5.050728 | CW29: =AI29 -> 0 | CX29: =AJ29 -> 0 | CY29: =(ROUND((((S29+ROUND((ROUND(((((EU29*1.2)*0.3))*AV29*1),2)*BS29),2))*AT29)/100),2)+ROUND(((ROUND((ROUND(((AE29-(((EU29*1.2)*0.3)))*AV29*1),2)*BS29),2)*AT29)/100),2)) -> 2994.21 | CZ29: =(ROUND((((S29+ROUND((ROUND(((((EU29*1.2)*0.3))*AV29*1),2)*BS29),2))*AU29)/100),2)+ROUND(((ROUND((ROUND(((AE29-(((EU29*1.2)*0.3)))*AV29*1),2)*BS29),2)*AU29)/100),2)) -> 1530.37 | DB29: 3 | DD29: *1)*0 | DE29: *1,2)*0,3 | DF29: *1,2)*0,3 | DG29: *1,2)*0,3 | DI29: *1,2)*0,3 | DJ29: *1,2)*0,3 | DN29: 0 | DO29: 0 | DP29: 1 | DQ29: 1 | DU29: 1013 | DV29: 1 ШТ. | DW29: 1 ШТ. | DX29: 1 | EE29: 57042958 | EF29: 40 | EG29: Монтаж оборудования | EH29: 0 | EJ29: 2 | EK29: 68 | EL29: ТСН-2001.4-10. Прокладка и монтаж сетей связи | EM29: ТСН-2001.4-10-1 | EO29: Поправка: Гл.12.Прил.8.п.8. 3_12.00.01.11.001 Поправка: Гл.4.Прил.2.2.п.2.2.29_04.00.01.35.003 | EQ29: 0 | ER29: 216.97 | ES29: 3.92 | ET29: 63.24 | EU29: 6.81 | EV29: 149.81 | EW29: 13.4 | EX29: 0 | EY29: 0 | FQ29: 0 | FR29: 0 | FS29: 0 | FX29: 90 | FY29: 46 | GD29: 1 | GF29: 1360940533 | GG29: 2 | GH29: 1 | GI29: 2 | GJ29: 0 | GK29: 0 | GL29: =ROUND(IF(AND(BH29=3,BI29=3,FS29<>0),P29,0),2) -> 0 | GM29: =ROUND(O29+X29+Y29,2)+GX29 -> 8089.05 | GN29: =IF(OR(BI29=0,BI29=1),GM29-GX29,0) -> 0 | GO29: =IF(BI29=2,GM29-GX29,0) -> 8089.05 | GP29: =IF(BI29=4,GM29-GX29,0) -> 0 | GR29: 0 | GS29: 3 | GT29: 0 | GV29: =ROUND((GT29),6) -> 0 | GW29: 1 | GX29: =ROUND(HC29*I29,2) -> 0 | HA29: 0 | HB29: 0 | HC29: =GV29*GW29 -> 0 | HS29: 0 | IK29: 0
A30: 17 | B30: 1 | C30: =ROW(SmtRes!A13) -> 13 | D30: =ROW(EtalonRes!A16) -> 16 | E30: 2 | F30: 4.10-151-4 | G30: Установка пульта или табло вызывной сигнализации с количеством сигналов до 20 / демонтаж пульта микрофонного | H30: 1 ШТ. | I30: 1 | J30: 0 | K30: 1 | O30: =ROUND(CP30,2) -> 39.45 | P30: =ROUND((ROUND((AC30*AW30*I30),2)*BC30),2) -> 0 | Q30: =(ROUND((ROUND(((((ET30*1.2)*0.3))*AV30*I30),2)*BB30),2)+ROUND((ROUND(((AE30-(((EU30*1.2)*0.3)))*AV30*I30),2)*BS30),2)) -> 0.07 | R30: =(ROUND((ROUND(((((EU30*1.2)*0.3))*AV30*I30),2)*BS30),2)+ROUND((ROUND(((AE30-(((EU30*1.2)*0.3)))*AV30*I30),2)*BS30),2)) -> 0 | S30: =ROUND((ROUND((AF30*AV30*I30),2)*BA30),2) -> 39.38 | T30: =ROUND(CU30*I30,2) -> 0 | U30: =CV30*I30 -> 3.39228 | V30: =CW30*I30 -> 0 | W30: =ROUND(CX30*I30,2) -> 0 | X30: =(ROUND((((S30+ROUND((ROUND(((((EU30*1.2)*0.3))*AV30*I30),2)*BS30),2))*AT30)/100),2)+ROUND(((ROUND((ROUND(((AE30-(((EU30*1.2)*0.3)))*AV30*I30),2)*BS30),2)*AT30)/100),2)) -> 35.44 | Y30: =(ROUND((((S30+ROUND((ROUND(((((EU30*1.2)*0.3))*AV30*I30),2)*BS30),2))*AU30)/100),2)+ROUND(((ROUND((ROUND(((AE30-(((EU30*1.2)*0.3)))*AV30*I30),2)*BS30),2)*AU30)/100),2)) -> 18.11 | AA30: 57014138 | AB30: =ROUND((AC30+AD30+AF30),6) -> 37.6812 | AC30: =ROUND((((ES30*1)*0)),6) -> 0 | AD30: =ROUND((((((ET30*1.2)*0.3))-(((EU30*1.2)*0.3)))+AE30),6) -> 0.0648 | AE30: =ROUND((((EU30*1.2)*0.3)),6) -> 0 | AF30: =ROUND((((EV30*1.2)*0.3)),6) -> 37.6164 | AG30: =ROUND((AP30),6) -> 0 | AH30: =(((EW30*1.2)*0.3)) -> 3.24 | AI30: =(((EX30*1.2)*0.3)) -> 0 | AJ30: =(AS30) -> 0 | AK30: 109.12 | AL30: 4.45 | AM30: 0.18 | AN30: 0 | AO30: 104.49 | AP30: 0 | AQ30: 9 | AR30: 0 | AS30: 0 | AT30: 90 | AU30: 46 | AV30: 1.047 | AW30: 1 | AZ30: 1 | BA30: 1 | BB30: 1 | BC30: 1 | BH30: 0 | BI30: 2 | BJ30: ТСН-2001.4 Доп. 68, Сб. 10, т. 151, поз. 4 | BM30: 68 | BN30: 0 | BO30: 4.10-151-4 | BP30: 1 | BQ30: 40 | BR30: 0 | BS30: 1 | BT30: 1 | BU30: 1 | BV30: 1 | BW30: 1 | BX30: 1 | BZ30: 90 | CA30: 46 | CE30: 1566 | CF30: 0 | CG30: 0 | CM30: 0 | CN30: Поправка: Гл.12.Прил.8.п.8. 3_12.00.01.11.001 Наименование: При наличии напряженных и стесненных условий производства работ (стесненность, сложность складирования и транспортной логистики и т.п.) для объектов, расположенных в пределах круговой магистральной системы улиц "Садовое кольцо" города Москвы Поправка: Гл.4.Прил.2.2.п.2.2.29_04.00.01.35.003 Наименование: При демонтаже оборудования, предназначенного в лом | CO30: 0 | CP30: =(P30+Q30+S30) -> 39.45 | CQ30: =ROUND((ROUND((AC30*AW30*1),2)*BC30),2) -> 0 | CR30: =(ROUND((ROUND(((((ET30*1.2)*0.3))*AV30*1),2)*BB30),2)+ROUND((ROUND(((AE30-(((EU30*1.2)*0.3)))*AV30*1),2)*BS30),2)) -> 0.07 | CS30: =(ROUND((ROUND(((((EU30*1.2)*0.3))*AV30*1),2)*BS30),2)+ROUND((ROUND(((AE30-(((EU30*1.2)*0.3)))*AV30*1),2)*BS30),2)) -> 0 | CT30: =ROUND((ROUND((AF30*AV30*1),2)*BA30),2) -> 39.38 | CU30: =AG30 -> 0 | CV30: =(AH30*AV30) -> 3.39228 | CW30: =AI30 -> 0 | CX30: =AJ30 -> 0 | CY30: =(ROUND((((S30+ROUND((ROUND(((((EU30*1.2)*0.3))*AV30*1),2)*BS30),2))*AT30)/100),2)+ROUND(((ROUND((ROUND(((AE30-(((EU30*1.2)*0.3)))*AV30*1),2)*BS30),2)*AT30)/100),2)) -> 35.44 | CZ30: =(ROUND((((S30+ROUND((ROUND(((((EU30*1.2)*0.3))*AV30*1),2)*BS30),2))*AU30)/100),2)+ROUND(((ROUND((ROUND(((AE30-(((EU30*1.2)*0.3)))*AV30*1),2)*BS30),2)*AU30)/100),2)) -> 18.11 | DB30: 5 | DD30: *1)*0 | DE30: *1,2)*0,3 | DF30: *1,2)*0,3 | DG30: *1,2)*0,3 | DI30: *1,2)*0,3 | DJ30: *1,2)*0,3 | DN30: 0 | DO30: 0 | DP30: 1 | DQ30: 1 | DU30: 1013 | DV30: 1 ШТ. | DW30: 1 ШТ. | DX30: 1 | EE30: 57042958 | EF30: 40 | EG30: Монтаж оборудования | EH30: 0 | EJ30: 2 | EK30: 68 | EL30: ТСН-2001.4-10. Прокладка и монтаж сетей связи | EM30: ТСН-2001.4-10-1 | EO30: Поправка: Гл.12.Прил.8.п.8. 3_12.00.01.11.001 Поправка: Гл.4.Прил.2.2.п.2.2.29_04.00.01.35.003 | EQ30: 0 | ER30: 109.12 | ES30: 4.45 | ET30: 0.18 | EU30: 0 | EV30: 104.49 | EW30: 9 | EX30: 0 | EY30: 0 | FQ30: 0 | FR30: 0 | FS30: 0 | FX30: 90 | FY30: 46 | GD30: 1 | GF30: 717714156 | GG30: 2 | GH30: 1 | GI30: 2 | GJ30: 0 | GK30: 0 | GL30: =ROUND(IF(AND(BH30=3,BI30=3,FS30<>0),P30,0),2) -> 0 | GM30: =ROUND(O30+X30+Y30,2)+GX30 -> 93 | GN30: =IF(OR(BI30=0,BI30=1),GM30-GX30,0) -> 0 | GO30: =IF(BI30=2,GM30-GX30,0) -> 93 | GP30: =IF(BI30=4,GM30-GX30,0) -> 0 | GR30: 0 | GS30: 3 | GT30: 0 | GV30: =ROUND((GT30),6) -> 0 | GW30: 1 | GX30: =ROUND(HC30*I30,2) -> 0 | HA30: 0 | HB30: 0 | HC30: =GV30*GW30 -> 0 | HS30: 0 | IK30: 0
A31: 17 | B31: 1 | C31: =ROW(SmtRes!A16) -> 16 | D31: =ROW(EtalonRes!A20) -> 20 | E31: 2 | F31: 4.10-151-4 | G31: Установка пульта или табло вызывной сигнализации с количеством сигналов до 20 / демонтаж пульта микрофонного | H31: 1 ШТ. | I31: 1 | J31: 0 | K31: 1 | O31: =ROUND(CP31,2) -> 2219.71 | P31: =ROUND((ROUND((AC31*AW31*I31),2)*BC31),2) -> 0 | Q31: =(ROUND((ROUND(((((ET31*1.2)*0.3))*AV31*I31),2)*BB31),2)+ROUND((ROUND(((AE31-(((EU31*1.2)*0.3)))*AV31*I31),2)*BS31),2)) -> 0.65 | R31: =(ROUND((ROUND(((((EU31*1.2)*0.3))*AV31*I31),2)*BS31),2)+ROUND((ROUND(((AE31-(((EU31*1.2)*0.3)))*AV31*I31),2)*BS31),2)) -> 0 | S31: =ROUND((ROUND((AF31*AV31*I31),2)*BA31),2) -> 2219.06 | T31: =ROUND(CU31*I31,2) -> 0 | U31: =CV31*I31 -> 3.39228 | V31: =CW31*I31 -> 0 | W31: =ROUND(CX31*I31,2) -> 0 | X31: =(ROUND((((S31+ROUND((ROUND(((((EU31*1.2)*0.3))*AV31*I31),2)*BS31),2))*AT31)/100),2)+ROUND(((ROUND((ROUND(((AE31-(((EU31*1.2)*0.3)))*AV31*I31),2)*BS31),2)*AT31)/100),2)) -> 1997.15 | Y31: =(ROUND((((S31+ROUND((ROUND(((((EU31*1.2)*0.3))*AV31*I31),2)*BS31),2))*AU31)/100),2)+ROUND(((ROUND((ROUND(((AE31-(((EU31*1.2)*0.3)))*AV31*I31),2)*BS31),2)*AU31)/100),2)) -> 1020.77 | AA31: 57014140 | AB31: =ROUND((AC31+AD31+AF31),6) -> 37.6812 | AC31: =ROUND((((ES31*1)*0)),6) -> 0 | AD31: =ROUND((((((ET31*1.2)*0.3))-(((EU31*1.2)*0.3)))+AE31),6) -> 0.0648 | AE31: =ROUND((((EU31*1.2)*0.3)),6) -> 0 | AF31: =ROUND((((EV31*1.2)*0.3)),6) -> 37.6164 | AG31: =ROUND((AP31),6) -> 0 | AH31: =(((EW31*1.2)*0.3)) -> 3.24 | AI31: =(((EX31*1.2)*0.3)) -> 0 | AJ31: =(AS31) -> 0 | AK31: 109.12 | AL31: 4.45 | AM31: 0.18 | AN31: 0 | AO31: 104.49 | AP31: 0 | AQ31: 9 | AR31: 0 | AS31: 0 | AT31: 90 | AU31: 46 | AV31: 1.047 | AW31: 1 | AZ31: 1 | BA31: 56.35 | BB31: 9.28 | BC31: 0.93 | BH31: 0 | BI31: 2 | BJ31: ТСН-2001.4 Доп. 68, Сб. 10, т. 151, поз. 4 | BM31: 68 | BN31: 0 | BO31: 4.10-151-4 | BP31: 1 | BQ31: 40 | BR31: 0 | BS31: 56.35 | BT31: 1 | BU31: 1 | BV31: 1 | BW31: 1 | BX31: 1 | BZ31: 90 | CA31: 46 | CE31: 1566 | CF31: 0 | CG31: 0 | CM31: 0 | CN31: Поправка: Гл.12.Прил.8.п.8. 3_12.00.01.11.001 Наименование: При наличии напряженных и стесненных условий производства работ (стесненность, сложность складирования и транспортной логистики и т.п.) для объектов, расположенных в пределах круговой магистральной системы улиц "Садовое кольцо" города Москвы Поправка: Гл.4.Прил.2.2.п.2.2.29_04.00.01.35.003 Наименование: При демонтаже оборудования, предназначенного в лом | CO31: 0 | CP31: =(P31+Q31+S31) -> 2219.71 | CQ31: =ROUND((ROUND((AC31*AW31*1),2)*BC31),2) -> 0 | CR31: =(ROUND((ROUND(((((ET31*1.2)*0.3))*AV31*1),2)*BB31),2)+ROUND((ROUND(((AE31-(((EU31*1.2)*0.3)))*AV31*1),2)*BS31),2)) -> 0.65 | CS31: =(ROUND((ROUND(((((EU31*1.2)*0.3))*AV31*1),2)*BS31),2)+ROUND((ROUND(((AE31-(((EU31*1.2)*0.3)))*AV31*1),2)*BS31),2)) -> 0 | CT31: =ROUND((ROUND((AF31*AV31*1),2)*BA31),2) -> 2219.06 | CU31: =AG31 -> 0 | CV31: =(AH31*AV31) -> 3.39228 | CW31: =AI31 -> 0 | CX31: =AJ31 -> 0 | CY31: =(ROUND((((S31+ROUND((ROUND(((((EU31*1.2)*0.3))*AV31*1),2)*BS31),2))*AT31)/100),2)+ROUND(((ROUND((ROUND(((AE31-(((EU31*1.2)*0.3)))*AV31*1),2)*BS31),2)*AT31)/100),2)) -> 1997.15 | CZ31: =(ROUND((((S31+ROUND((ROUND(((((EU31*1.2)*0.3))*AV31*1),2)*BS31),2))*AU31)/100),2)+ROUND(((ROUND((ROUND(((AE31-(((EU31*1.2)*0.3)))*AV31*1),2)*BS31),2)*AU31)/100),2)) -> 1020.77 | DB31: 7 | DD31: *1)*0 | DE31: *1,2)*0,3 | DF31: *1,2)*0,3 | DG31: *1,2)*0,3 | DI31: *1,2)*0,3 | DJ31: *1,2)*0,3 | DN31: 0 | DO31: 0 | DP31: 1 | DQ31: 1 | DU31: 1013 | DV31: 1 ШТ. | DW31: 1 ШТ. | DX31: 1 | EE31: 57042958 | EF31: 40 | EG31: Монтаж оборудования | EH31: 0 | EJ31: 2 | EK31: 68 | EL31: ТСН-2001.4-10. Прокладка и монтаж сетей связи | EM31: ТСН-2001.4-10-1 | EO31: Поправка: Гл.12.Прил.8.п.8. 3_12.00.01.11.001 Поправка: Гл.4.Прил.2.2.п.2.2.29_04.00.01.35.003 | EQ31: 0 | ER31: 109.12 | ES31: 4.45 | ET31: 0.18 | EU31: 0 | EV31: 104.49 | EW31: 9 | EX31: 0 | EY31: 0 | FQ31: 0 | FR31: 0 | FS31: 0 | FX31: 90 | FY31: 46 | GD31: 1 | GF31: 717714156 | GG31: 2 | GH31: 1 | GI31: 2 | GJ31: 0 | GK31: 0 | GL31: =ROUND(IF(AND(BH31=3,BI31=3,FS31<>0),P31,0),2) -> 0 | GM31: =ROUND(O31+X31+Y31,2)+GX31 -> 5237.63 | GN31: =IF(OR(BI31=0,BI31=1),GM31-GX31,0) -> 0 | GO31: =IF(BI31=2,GM31-GX31,0) -> 5237.63 | GP31: =IF(BI31=4,GM31-GX31,0) -> 0 | GR31: 0 | GS31: 3 | GT31: 0 | GV31: =ROUND((GT31),6) -> 0 | GW31: 1 | GX31: =ROUND(HC31*I31,2) -> 0 | HA31: 0 | HB31: 0 | HC31: =GV31*GW31 -> 0 | HS31: 0 | IK31: 0
A32: 17 | B32: 1 | C32: =ROW(SmtRes!A17) -> 17 | D32: =ROW(EtalonRes!A21) -> 21 | E32: 3 | F32: 4.10-80-2 | G32: Аппараты приемные, приборы ПС приемно-контрольные, пусковые, концентратор, блок базовый на 20 лучей / демонтаж Прибор приемно-контрольный и управления охранно-пожарный | H32: 1 ШТ. | I32: 2 | J32: 0 | K32: 2 | O32: =ROUND(CP32,2) -> 116.47 | P32: =ROUND((ROUND((AC32*AW32*I32),2)*BC32),2) -> 0 | Q32: =(ROUND((ROUND(((((ET32*1.2)*0.3))*AV32*I32),2)*BB32),2)+ROUND((ROUND(((AE32-(((EU32*1.2)*0.3)))*AV32*I32),2)*BS32),2)) -> 0.05 | R32: =(ROUND((ROUND(((((EU32*1.2)*0.3))*AV32*I32),2)*BS32),2)+ROUND((ROUND(((AE32-(((EU32*1.2)*0.3)))*AV32*I32),2)*BS32),2)) -> 0.01 | S32: =ROUND((ROUND((AF32*AV32*I32),2)*BA32),2) -> 116.42 | T32: =ROUND(CU32*I32,2) -> 0 | U32: =CV32*I32 -> 8.819928 | V32: =CW32*I32 -> 0 | W32: =ROUND(CX32*I32,2) -> 0 | X32: =(ROUND((((S32+ROUND((ROUND(((((EU32*1.2)*0.3))*AV32*I32),2)*BS32),2))*AT32)/100),2)+ROUND(((ROUND((ROUND(((AE32-(((EU32*1.2)*0.3)))*AV32*I32),2)*BS32),2)*AT32)/100),2)) -> 104.79 | Y32: =(ROUND((((S32+ROUND((ROUND(((((EU32*1.2)*0.3))*AV32*I32),2)*BS32),2))*AU32)/100),2)+ROUND(((ROUND((ROUND(((AE32-(((EU32*1.2)*0.3)))*AV32*I32),2)*BS32),2)*AU32)/100),2)) -> 53.56 | AA32: 57014138 | AB32: =ROUND((AC32+AD32+AF32),6) -> 55.62 | AC32: =ROUND((((ES32*1)*0)),6) -> 0 | AD32: =ROUND((((((ET32*1.2)*0.3))-(((EU32*1.2)*0.3)))+AE32),6) -> 0.0216 | AE32: =ROUND((((EU32*1.2)*0.3)),6) -> 0.0036 | AF32: =ROUND((((EV32*1.2)*0.3)),6) -> 55.5984 | AG32: =ROUND((AP32),6) -> 0 | AH32: =(((EW32*1.2)*0.3)) -> 4.212 | AI32: =(((EX32*1.2)*0.3)) -> 0 | AJ32: =(AS32) -> 0 | AK32: 175.43 | AL32: 20.93 | AM32: 0.06 | AN32: 0.01 | AO32: 154.44 | AP32: 0 | AQ32: 11.7 | AR32: 0 | AS32: 0 | AT32: 90 | AU32: 46 | AV32: 1.047 | AW32: 1 | AZ32: 1 | BA32: 1 | BB32: 1 | BC32: 1 | BH32: 0 | BI32: 2 | BJ32: ТСН-2001.4 Доп. 68, Сб. 10, т. 80, поз. 2 | BM32: 68 | BN32: 0 | BO32: 4.10-80-2 | BP32: 1 | BQ32: 40 | BR32: 0 | BS32: 1 | BT32: 1 | BU32: 1 | BV32: 1 | BW32: 1 | BX32: 1 | BZ32: 90 | CA32: 46 | CE32: 1566 | CF32: 0 | CG32: 0 | CM32: 0 | CN32: Поправка: Гл.12.Прил.8.п.8. 3_12.00.01.11.001 Наименование: При наличии напряженных и стесненных условий производства работ (стесненность, сложность складирования и транспортной логистики и т.п.) для объектов, расположенных в пределах круговой магистральной системы улиц "Садовое кольцо" города Москвы Поправка: Гл.4.Прил.2.2.п.2.2.29_04.00.01.35.003 Наименование: При демонтаже оборудования, предназначенного в лом | CO32: 0 | CP32: =(P32+Q32+S32) -> 116.47 | CQ32: =ROUND((ROUND((AC32*AW32*1),2)*BC32),2) -> 0 | CR32: =(ROUND((ROUND(((((ET32*1.2)*0.3))*AV32*1),2)*BB32),2)+ROUND((ROUND(((AE32-(((EU32*1.2)*0.3)))*AV32*1),2)*BS32),2)) -> 0.02 | CS32: =(ROUND((ROUND(((((EU32*1.2)*0.3))*AV32*1),2)*BS32),2)+ROUND((ROUND(((AE32-(((EU32*1.2)*0.3)))*AV32*1),2)*BS32),2)) -> 0 | CT32: =ROUND((ROUND((AF32*AV32*1),2)*BA32),2) -> 58.21 | CU32: =AG32 -> 0 | CV32: =(AH32*AV32) -> 4.409964 | CW32: =AI32 -> 0 | CX32: =AJ32 -> 0 | CY32: =(ROUND((((S32+ROUND((ROUND(((((EU32*1.2)*0.3))*AV32*1),2)*BS32),2))*AT32)/100),2)+ROUND(((ROUND((ROUND(((AE32-(((EU32*1.2)*0.3)))*AV32*1),2)*BS32),2)*AT32)/100),2)) -> 104.78 | CZ32: =(ROUND((((S32+ROUND((ROUND(((((EU32*1.2)*0.3))*AV32*1),2)*BS32),2))*AU32)/100),2)+ROUND(((ROUND((ROUND(((AE32-(((EU32*1.2)*0.3)))*AV32*1),2)*BS32),2)*AU32)/100),2)) -> 53.55 | DB32: 9 | DD32: *1)*0 | DE32: *1,2)*0,3 | DF32: *1,2)*0,3 | DG32: *1,2)*0,3 | DI32: *1,2)*0,3 | DJ32: *1,2)*0,3 | DN32: 0 | DO32: 0 | DP32: 1 | DQ32: 1 | DU32: 1013 | DV32: 1 ШТ. | DW32: 1 ШТ. | DX32: 1 | EE32: 57042958 | EF32: 40 | EG32: Монтаж оборудования | EH32: 0 | EJ32: 2 | EK32: 68 | EL32: ТСН-2001.4-10. Прокладка и монтаж сетей связи | EM32: ТСН-2001.4-10-1 | EO32: Поправка: Гл.12.Прил.8.п.8. 3_12.00.01.11.001 Поправка: Гл.4.Прил.2.2.п.2.2.29_04.00.01.35.003 | EQ32: 0 | ER32: 175.43 | ES32: 20.93 | ET32: 0.06 | EU32: 0.01 | EV32: 154.44 | EW32: 11.7 | EX32: 0 | EY32: 0 | FQ32: 0 | FR32: 0 | FS32: 0 | FX32: 90 | FY32: 46 | GD32: 1 | GF32: -616531060 | GG32: 2 | GH32: 1 | GI32: 2 | GJ32: 0 | GK32: 0 | GL32: =ROUND(IF(AND(BH32=3,BI32=3,FS32<>0),P32,0),2) -> 0 | GM32: =ROUND(O32+X32+Y32,2)+GX32 -> 274.82 | GN32: =IF(OR(BI32=0,BI32=1),GM32-GX32,0) -> 0 | GO32: =IF(BI32=2,GM32-GX32,0) -> 274.82 | GP32: =IF(BI32=4,GM32-GX32,0) -> 0 | GR32: 0 | GS32: 3 | GT32: 0 | GV32: =ROUND((GT32),6) -> 0 | GW32: 1 | GX32: =ROUND(HC32*I32,2) -> 0 | HA32: 0 | HB32: 0 | HC32: =GV32*GW32 -> 0 | HS32: 0 | IK32: 0
A33: 17 | B33: 1 | C33: =ROW(SmtRes!A18) -> 18 | D33: =ROW(EtalonRes!A22) -> 22 | E33: 3 | F33: 4.10-80-2 | G33: Аппараты приемные, приборы ПС приемно-контрольные, пусковые, концентратор, блок базовый на 20 лучей / демонтаж Прибор приемно-контрольный и управления охранно-пожарный | H33: 1 ШТ. | I33: 2 | J33: 0 | K33: 2 | O33: =ROUND(CP33,2) -> 6561.2 | P33: =ROUND((ROUND((AC33*AW33*I33),2)*BC33),2) -> 0 | Q33: =(ROUND((ROUND(((((ET33*1.2)*0.3))*AV33*I33),2)*BB33),2)+ROUND((ROUND(((AE33-(((EU33*1.2)*0.3)))*AV33*I33),2)*BS33),2)) -> 0.93 | R33: =(ROUND((ROUND(((((EU33*1.2)*0.3))*AV33*I33),2)*BS33),2)+ROUND((ROUND(((AE33-(((EU33*1.2)*0.3)))*AV33*I33),2)*BS33),2)) -> 0.56 | S33: =ROUND((ROUND((AF33*AV33*I33),2)*BA33),2) -> 6560.27 | T33: =ROUND(CU33*I33,2) -> 0 | U33: =CV33*I33 -> 8.819928 | V33: =CW33*I33 -> 0 | W33: =ROUND(CX33*I33,2) -> 0 | X33: =(ROUND((((S33+ROUND((ROUND(((((EU33*1.2)*0.3))*AV33*I33),2)*BS33),2))*AT33)/100),2)+ROUND(((ROUND((ROUND(((AE33-(((EU33*1.2)*0.3)))*AV33*I33),2)*BS33),2)*AT33)/100),2)) -> 5904.75 | Y33: =(ROUND((((S33+ROUND((ROUND(((((EU33*1.2)*0.3))*AV33*I33),2)*BS33),2))*AU33)/100),2)+ROUND(((ROUND((ROUND(((AE33-(((EU33*1.2)*0.3)))*AV33*I33),2)*BS33),2)*AU33)/100),2)) -> 3017.98 | AA33: 57014140 | AB33: =ROUND((AC33+AD33+AF33),6) -> 55.62 | AC33: =ROUND((((ES33*1)*0)),6) -> 0 | AD33: =ROUND((((((ET33*1.2)*0.3))-(((EU33*1.2)*0.3)))+AE33),6) -> 0.0216 | AE33: =ROUND((((EU33*1.2)*0.3)),6) -> 0.0036 | AF33: =ROUND((((EV33*1.2)*0.3)),6) -> 55.5984 | AG33: =ROUND((AP33),6) -> 0 | AH33: =(((EW33*1.2)*0.3)) -> 4.212 | AI33: =(((EX33*1.2)*0.3)) -> 0 | AJ33: =(AS33) -> 0 | AK33: 175.43 | AL33: 20.93 | AM33: 0.06 | AN33: 0.01 | AO33: 154.44 | AP33: 0 | AQ33: 11.7 | AR33: 0 | AS33: 0 | AT33: 90 | AU33: 46 | AV33: 1.047 | AW33: 1 | AZ33: 1 | BA33: 56.35 | BB33: 18.5 | BC33: 9.84 | BH33: 0 | BI33: 2 | BJ33: ТСН-2001.4 Доп. 68, Сб. 10, т. 80, поз. 2 | BM33: 68 | BN33: 0 | BO33: 4.10-80-2 | BP33: 1 | BQ33: 40 | BR33: 0 | BS33: 56.35 | BT33: 1 | BU33: 1 | BV33: 1 | BW33: 1 | BX33: 1 | BZ33: 90 | CA33: 46 | CE33: 1566 | CF33: 0 | CG33: 0 | CM33: 0 | CN33: Поправка: Гл.12.Прил.8.п.8. 3_12.00.01.11.001 Наименование: При наличии напряженных и стесненных условий производства работ (стесненность, сложность складирования и транспортной логистики и т.п.) для объектов, расположенных в пределах круговой магистральной системы улиц "Садовое кольцо" города Москвы Поправка: Гл.4.Прил.2.2.п.2.2.29_04.00.01.35.003 Наименование: При демонтаже оборудования, предназначенного в лом | CO33: 0 | CP33: =(P33+Q33+S33) -> 6561.2 | CQ33: =ROUND((ROUND((AC33*AW33*1),2)*BC33),2) -> 0 | CR33: =(ROUND((ROUND(((((ET33*1.2)*0.3))*AV33*1),2)*BB33),2)+ROUND((ROUND(((AE33-(((EU33*1.2)*0.3)))*AV33*1),2)*BS33),2)) -> 0.37 | CS33: =(ROUND((ROUND(((((EU33*1.2)*0.3))*AV33*1),2)*BS33),2)+ROUND((ROUND(((AE33-(((EU33*1.2)*0.3)))*AV33*1),2)*BS33),2)) -> 0 | CT33: =ROUND((ROUND((AF33*AV33*1),2)*BA33),2) -> 3280.13 | CU33: =AG33 -> 0 | CV33: =(AH33*AV33) -> 4.409964 | CW33: =AI33 -> 0 | CX33: =AJ33 -> 0 | CY33: =(ROUND((((S33+ROUND((ROUND(((((EU33*1.2)*0.3))*AV33*1),2)*BS33),2))*AT33)/100),2)+ROUND(((ROUND((ROUND(((AE33-(((EU33*1.2)*0.3)))*AV33*1),2)*BS33),2)*AT33)/100),2)) -> 5904.24 | CZ33: =(ROUND((((S33+ROUND((ROUND(((((EU33*1.2)*0.3))*AV33*1),2)*BS33),2))*AU33)/100),2)+ROUND(((ROUND((ROUND(((AE33-(((EU33*1.2)*0.3)))*AV33*1),2)*BS33),2)*AU33)/100),2)) -> 3017.72 | DB33: 11 | DD33: *1)*0 | DE33: *1,2)*0,3 | DF33: *1,2)*0,3 | DG33: *1,2)*0,3 | DI33: *1,2)*0,3 | DJ33: *1,2)*0,3 | DN33: 0 | DO33: 0 | DP33: 1 | DQ33: 1 | DU33: 1013 | DV33: 1 ШТ. | DW33: 1 ШТ. | DX33: 1 | EE33: 57042958 | EF33: 40 | EG33: Монтаж оборудования | EH33: 0 | EJ33: 2 | EK33: 68 | EL33: ТСН-2001.4-10. Прокладка и монтаж сетей связи | EM33: ТСН-2001.4-10-1 | EO33: Поправка: Гл.12.Прил.8.п.8. 3_12.00.01.11.001 Поправка: Гл.4.Прил.2.2.п.2.2.29_04.00.01.35.003 | EQ33: 0 | ER33: 175.43 | ES33: 20.93 | ET33: 0.06 | EU33: 0.01 | EV33: 154.44 | EW33: 11.7 | EX33: 0 | EY33: 0 | FQ33: 0 | FR33: 0 | FS33: 0 | FX33: 90 | FY33: 46 | GD33: 1 | GF33: -616531060 | GG33: 2 | GH33: 1 | GI33: 2 | GJ33: 0 | GK33: 0 | GL33: =ROUND(IF(AND(BH33=3,BI33=3,FS33<>0),P33,0),2) -> 0 | GM33: =ROUND(O33+X33+Y33,2)+GX33 -> 15483.93 | GN33: =IF(OR(BI33=0,BI33=1),GM33-GX33,0) -> 0 | GO33: =IF(BI33=2,GM33-GX33,0) -> 15483.93 | GP33: =IF(BI33=4,GM33-GX33,0) -> 0 | GR33: 0 | GS33: 3 | GT33: 0 | GV33: =ROUND((GT33),6) -> 0 | GW33: 1 | GX33: =ROUND(HC33*I33,2) -> 0 | HA33: 0 | HB33: 0 | HC33: =GV33*GW33 -> 0 | HS33: 0 | IK33: 0
A34: 17 | B34: 1 | C34: =ROW(SmtRes!A22) -> 22 | D34: =ROW(EtalonRes!A27) -> 27 | E34: 4 | F34: 4.10-34-5 | G34: Монтаж коммутатора служебной связи / демонтаж модуля речевых сообщений | H34: 1 ШТ. | I34: 1 | J34: 0 | K34: 1 | O34: =ROUND(CP34,2) -> 40.31 | P34: =ROUND((ROUND((AC34*AW34*I34),2)*BC34),2) -> 0 | Q34: =(ROUND((ROUND(((((ET34*1.2)*0.3))*AV34*I34),2)*BB34),2)+ROUND((ROUND(((AE34-(((EU34*1.2)*0.3)))*AV34*I34),2)*BS34),2)) -> 10.82 | R34: =(ROUND((ROUND(((((EU34*1.2)*0.3))*AV34*I34),2)*BS34),2)+ROUND((ROUND(((AE34-(((EU34*1.2)*0.3)))*AV34*I34),2)*BS34),2)) -> 1.19 | S34: =ROUND((ROUND((AF34*AV34*I34),2)*BA34),2) -> 29.49 | T34: =ROUND(CU34*I34,2) -> 0 | U34: =CV34*I34 -> 2.336904 | V34: =CW34*I34 -> 0 | W34: =ROUND(CX34*I34,2) -> 0 | X34: =(ROUND((((S34+ROUND((ROUND(((((EU34*1.2)*0.3))*AV34*I34),2)*BS34),2))*AT34)/100),2)+ROUND(((ROUND((ROUND(((AE34-(((EU34*1.2)*0.3)))*AV34*I34),2)*BS34),2)*AT34)/100),2)) -> 27.61 | Y34: =(ROUND((((S34+ROUND((ROUND(((((EU34*1.2)*0.3))*AV34*I34),2)*BS34),2))*AU34)/100),2)+ROUND(((ROUND((ROUND(((AE34-(((EU34*1.2)*0.3)))*AV34*I34),2)*BS34),2)*AU34)/100),2)) -> 14.11 | AA34: 57014138 | AB34: =ROUND((AC34+AD34+AF34),6) -> 38.502 | AC34: =ROUND((((ES34*1)*0)),6) -> 0 | AD34: =ROUND((((((ET34*1.2)*0.3))-(((EU34*1.2)*0.3)))+AE34),6) -> 10.3356 | AE34: =ROUND((((EU34*1.2)*0.3)),6) -> 1.1376 | AF34: =ROUND((((EV34*1.2)*0.3)),6) -> 28.1664 | AG34: =ROUND((AP34),6) -> 0 | AH34: =(((EW34*1.2)*0.3)) -> 2.232 | AI34: =(((EX34*1.2)*0.3)) -> 0 | AJ34: =(AS34) -> 0 | AK34: 119.3 | AL34: 12.35 | AM34: 28.71 | AN34: 3.16 | AO34: 78.24 | AP34: 0 | AQ34: 6.2 | AR34: 0 | AS34: 0 | AT34: 90 | AU34: 46 | AV34: 1.047 | AW34: 1 | AZ34: 1 | BA34: 1 | BB34: 1 | BC34: 1 | BH34: 0 | BI34: 2 | BJ34: ТСН-2001.4 Доп. 80, Сб. 10, т. 34, поз. 5 | BM34: 68 | BN34: 0 | BO34: 4.10-34-5 | BP34: 1 | BQ34: 40 | BR34: 0 | BS34: 1 | BT34: 1 | BU34: 1 | BV34: 1 | BW34: 1 | BX34: 1 | BZ34: 90 | CA34: 46 | CE34: 1566 | CF34: 0 | CG34: 0 | CM34: 0 | CN34: Поправка: Гл.12.Прил.8.п.8. 3_12.00.01.11.001 Наименование: При наличии напряженных и стесненных условий производства работ (стесненность, сложность складирования и транспортной логистики и т.п.) для объектов, расположенных в пределах круговой магистральной системы улиц "Садовое кольцо" города Москвы Поправка: Гл.4.Прил.2.2.п.2.2.29_04.00.01.35.003 Наименование: При демонтаже оборудования, предназначенного в лом | CO34: 0 | CP34: =(P34+Q34+S34) -> 40.31 | CQ34: =ROUND((ROUND((AC34*AW34*1),2)*BC34),2) -> 0 | CR34: =(ROUND((ROUND(((((ET34*1.2)*0.3))*AV34*1),2)*BB34),2)+ROUND((ROUND(((AE34-(((EU34*1.2)*0.3)))*AV34*1),2)*BS34),2)) -> 10.82 | CS34: =(ROUND((ROUND(((((EU34*1.2)*0.3))*AV34*1),2)*BS34),2)+ROUND((ROUND(((AE34-(((EU34*1.2)*0.3)))*AV34*1),2)*BS34),2)) -> 1.19 | CT34: =ROUND((ROUND((AF34*AV34*1),2)*BA34),2) -> 29.49 | CU34: =AG34 -> 0 | CV34: =(AH34*AV34) -> 2.336904 | CW34: =AI34 -> 0 | CX34: =AJ34 -> 0 | CY34: =(ROUND((((S34+ROUND((ROUND(((((EU34*1.2)*0.3))*AV34*1),2)*BS34),2))*AT34)/100),2)+ROUND(((ROUND((ROUND(((AE34-(((EU34*1.2)*0.3)))*AV34*1),2)*BS34),2)*AT34)/100),2)) -> 27.61 | CZ34: =(ROUND((((S34+ROUND((ROUND(((((EU34*1.2)*0.3))*AV34*1),2)*BS34),2))*AU34)/100),2)+ROUND(((ROUND((ROUND(((AE34-(((EU34*1.2)*0.3)))*AV34*1),2)*BS34),2)*AU34)/100),2)) -> 14.11 | DB34: 13 | DD34: *1)*0 | DE34: *1,2)*0,3 | DF34: *1,2)*0,3 | DG34: *1,2)*0,3 | DI34: *1,2)*0,3 | DJ34: *1,2)*0,3 | DN34: 0 | DO34: 0 | DP34: 1 | DQ34: 1 | DU34: 1013 | DV34: 1 ШТ. | DW34: 1 ШТ. | DX34: 1 | EE34: 57042958 | EF34: 40 | EG34: Монтаж оборудования | EH34: 0 | EJ34: 2 | EK34: 68 | EL34: ТСН-2001.4-10. Прокладка и монтаж сетей связи | EM34: ТСН-2001.4-10-1 | EO34: Поправка: Гл.12.Прил.8.п.8. 3_12.00.01.11.001 Поправка: Гл.4.Прил.2.2.п.2.2.29_04.00.01.35.003 | EQ34: 0 | ER34: 119.3 | ES34: 12.35 | ET34: 28.71 | EU34: 3.16 | EV34: 78.24 | EW34: 6.2 | EX34: 0 | EY34: 0 | FQ34: 0 | FR34: 0 | FS34: 0 | FX34: 90 | FY34: 46 | GD34: 1 | GF34: -1352779689 | GG34: 2 | GH34: 1 | GI34: 2 | GJ34: 0 | GK34: 0 | GL34: =ROUND(IF(AND(BH34=3,BI34=3,FS34<>0),P34,0),2) -> 0 | GM34: =ROUND(O34+X34+Y34,2)+GX34 -> 82.03 | GN34: =IF(OR(BI34=0,BI34=1),GM34-GX34,0) -> 0 | GO34: =IF(BI34=2,GM34-GX34,0) -> 82.03 | GP34: =IF(BI34=4,GM34-GX34,0) -> 0 | GR34: 0 | GS34: 3 | GT34: 0 | GV34: =ROUND((GT34),6) -> 0 | GW34: 1 | GX34: =ROUND(HC34*I34,2) -> 0 | HA34: 0 | HB34: 0 | HC34: =GV34*GW34 -> 0 | HS34: 0 | IK34: 0
A35: 17 | B35: 1 | C35: =ROW(SmtRes!A26) -> 26 | D35: =ROW(EtalonRes!A32) -> 32 | E35: 4 | F35: 4.10-34-5 | G35: Монтаж коммутатора служебной связи / демонтаж модуля речевых сообщений | H35: 1 ШТ. | I35: 1 | J35: 0 | K35: 1 | O35: =ROUND(CP35,2) -> 1836.61 | P35: =ROUND((ROUND((AC35*AW35*I35),2)*BC35),2) -> 0 | Q35: =(ROUND((ROUND(((((ET35*1.2)*0.3))*AV35*I35),2)*BB35),2)+ROUND((ROUND(((AE35-(((EU35*1.2)*0.3)))*AV35*I35),2)*BS35),2)) -> 174.85 | R35: =(ROUND((ROUND(((((EU35*1.2)*0.3))*AV35*I35),2)*BS35),2)+ROUND((ROUND(((AE35-(((EU35*1.2)*0.3)))*AV35*I35),2)*BS35),2)) -> 67.06 | S35: =ROUND((ROUND((AF35*AV35*I35),2)*BA35),2) -> 1661.76 | T35: =ROUND(CU35*I35,2) -> 0 | U35: =CV35*I35 -> 2.336904 | V35: =CW35*I35 -> 0 | W35: =ROUND(CX35*I35,2) -> 0 | X35: =(ROUND((((S35+ROUND((ROUND(((((EU35*1.2)*0.3))*AV35*I35),2)*BS35),2))*AT35)/100),2)+ROUND(((ROUND((ROUND(((AE35-(((EU35*1.2)*0.3)))*AV35*I35),2)*BS35),2)*AT35)/100),2)) -> 1555.94 | Y35: =(ROUND((((S35+ROUND((ROUND(((((EU35*1.2)*0.3))*AV35*I35),2)*BS35),2))*AU35)/100),2)+ROUND(((ROUND((ROUND(((AE35-(((EU35*1.2)*0.3)))*AV35*I35),2)*BS35),2)*AU35)/100),2)) -> 795.26 | AA35: 57014140 | AB35: =ROUND((AC35+AD35+AF35),6) -> 38.502 | AC35: =ROUND((((ES35*1)*0)),6) -> 0 | AD35: =ROUND((((((ET35*1.2)*0.3))-(((EU35*1.2)*0.3)))+AE35),6) -> 10.3356 | AE35: =ROUND((((EU35*1.2)*0.3)),6) -> 1.1376 | AF35: =ROUND((((EV35*1.2)*0.3)),6) -> 28.1664 | AG35: =ROUND((AP35),6) -> 0 | AH35: =(((EW35*1.2)*0.3)) -> 2.232 | AI35: =(((EX35*1.2)*0.3)) -> 0 | AJ35: =(AS35) -> 0 | AK35: 119.3 | AL35: 12.35 | AM35: 28.71 | AN35: 3.16 | AO35: 78.24 | AP35: 0 | AQ35: 6.2 | AR35: 0 | AS35: 0 | AT35: 90 | AU35: 46 | AV35: 1.047 | AW35: 1 | AZ35: 1 | BA35: 56.35 | BB35: 16.16 | BC35: 14.7 | BH35: 0 | BI35: 2 | BJ35: ТСН-2001.4 Доп. 80, Сб. 10, т. 34, поз. 5 | BM35: 68 | BN35: 0 | BO35: 4.10-34-5 | BP35: 1 | BQ35: 40 | BR35: 0 | BS35: 56.35 | BT35: 1 | BU35: 1 | BV35: 1 | BW35: 1 | BX35: 1 | BZ35: 90 | CA35: 46 | CE35: 1566 | CF35: 0 | CG35: 0 | CM35: 0 | CN35: Поправка: Гл.12.Прил.8.п.8. 3_12.00.01.11.001 Наименование: При наличии напряженных и стесненных условий производства работ (стесненность, сложность складирования и транспортной логистики и т.п.) для объектов, расположенных в пределах круговой магистральной системы улиц "Садовое кольцо" города Москвы Поправка: Гл.4.Прил.2.2.п.2.2.29_04.00.01.35.003 Наименование: При демонтаже оборудования, предназначенного в лом | CO35: 0 | CP35: =(P35+Q35+S35) -> 1836.61 | CQ35: =ROUND((ROUND((AC35*AW35*1),2)*BC35),2) -> 0 | CR35: =(ROUND((ROUND(((((ET35*1.2)*0.3))*AV35*1),2)*BB35),2)+ROUND((ROUND(((AE35-(((EU35*1.2)*0.3)))*AV35*1),2)*BS35),2)) -> 174.85 | CS35: =(ROUND((ROUND(((((EU35*1.2)*0.3))*AV35*1),2)*BS35),2)+ROUND((ROUND(((AE35-(((EU35*1.2)*0.3)))*AV35*1),2)*BS35),2)) -> 67.06 | CT35: =ROUND((ROUND((AF35*AV35*1),2)*BA35),2) -> 1661.76 | CU35: =AG35 -> 0 | CV35: =(AH35*AV35) -> 2.336904 | CW35: =AI35 -> 0 | CX35: =AJ35 -> 0 | CY35: =(ROUND((((S35+ROUND((ROUND(((((EU35*1.2)*0.3))*AV35*1),2)*BS35),2))*AT35)/100),2)+ROUND(((ROUND((ROUND(((AE35-(((EU35*1.2)*0.3)))*AV35*1),2)*BS35),2)*AT35)/100),2)) -> 1555.94 | CZ35: =(ROUND((((S35+ROUND((ROUND(((((EU35*1.2)*0.3))*AV35*1),2)*BS35),2))*AU35)/100),2)+ROUND(((ROUND((ROUND(((AE35-(((EU35*1.2)*0.3)))*AV35*1),2)*BS35),2)*AU35)/100),2)) -> 795.26 | DB35: 15 | DD35: *1)*0 | DE35: *1,2)*0,3 | DF35: *1,2)*0,3 | DG35: *1,2)*0,3 | DI35: *1,2)*0,3 | DJ35: *1,2)*0,3 | DN35: 0 | DO35: 0 | DP35: 1 | DQ35: 1 | DU35: 1013 | DV35: 1 ШТ. | DW35: 1 ШТ. | DX35: 1 | EE35: 57042958 | EF35: 40 | EG35: Монтаж оборудования | EH35: 0 | EJ35: 2 | EK35: 68 | EL35: ТСН-2001.4-10. Прокладка и монтаж сетей связи | EM35: ТСН-2001.4-10-1 | EO35: Поправка: Гл.12.Прил.8.п.8. 3_12.00.01.11.001 Поправка: Гл.4.Прил.2.2.п.2.2.29_04.00.01.35.003 | EQ35: 0 | ER35: 119.3 | ES35: 12.35 | ET35: 28.71 | EU35: 3.16 | EV35: 78.24 | EW35: 6.2 | EX35: 0 | EY35: 0 | FQ35: 0 | FR35: 0 | FS35: 0 | FX35: 90 | FY35: 46 | GD35: 1 | GF35: -1352779689 | GG35: 2 | GH35: 1 | GI35: 2 | GJ35: 0 | GK35: 0 | GL35: =ROUND(IF(AND(BH35=3,BI35=3,FS35<>0),P35,0),2) -> 0 | GM35: =ROUND(O35+X35+Y35,2)+GX35 -> 4187.81 | GN35: =IF(OR(BI35=0,BI35=1),GM35-GX35,0) -> 0 | GO35: =IF(BI35=2,GM35-GX35,0) -> 4187.81 | GP35: =IF(BI35=4,GM35-GX35,0) -> 0 | GR35: 0 | GS35: 3 | GT35: 0 | GV35: =ROUND((GT35),6) -> 0 | GW35: 1 | GX35: =ROUND(HC35*I35,2) -> 0 | HA35: 0 | HB35: 0 | HC35: =GV35*GW35 -> 0 | HS35: 0 | IK35: 0
A36: 17 | B36: 1 | C36: =ROW(SmtRes!A32) -> 32 | D36: =ROW(EtalonRes!A39) -> 39 | E36: 5 | F36: 4.10-167-1 | G36: Монтаж блока питания сети (БПС) в диспетчерской / демонтаж блоков электропитания | H36: 1 ШТ. | I36: =ROUND(2+2+4+4,9) -> 12 | J36: 0 | K36: =ROUND(2+2+4+4,9) -> 12 | O36: =ROUND(CP36,2) -> 85.76 | P36: =ROUND((ROUND((AC36*AW36*I36),2)*BC36),2) -> 0 | Q36: =(ROUND((ROUND(((((ET36*1.2)*0.3))*AV36*I36),2)*BB36),2)+ROUND((ROUND(((AE36-(((EU36*1.2)*0.3)))*AV36*I36),2)*BS36),2)) -> 0.09 | R36: =(ROUND((ROUND(((((EU36*1.2)*0.3))*AV36*I36),2)*BS36),2)+ROUND((ROUND(((AE36-(((EU36*1.2)*0.3)))*AV36*I36),2)*BS36),2)) -> 0 | S36: =ROUND((ROUND((AF36*AV36*I36),2)*BA36),2) -> 85.67 | T36: =ROUND(CU36*I36,2) -> 0 | U36: =CV36*I36 -> 6.1513344 | V36: =CW36*I36 -> 0 | W36: =ROUND(CX36*I36,2) -> 0 | X36: =(ROUND((((S36+ROUND((ROUND(((((EU36*1.2)*0.3))*AV36*I36),2)*BS36),2))*AT36)/100),2)+ROUND(((ROUND((ROUND(((AE36-(((EU36*1.2)*0.3)))*AV36*I36),2)*BS36),2)*AT36)/100),2)) -> 77.1 | Y36: =(ROUND((((S36+ROUND((ROUND(((((EU36*1.2)*0.3))*AV36*I36),2)*BS36),2))*AU36)/100),2)+ROUND(((ROUND((ROUND(((AE36-(((EU36*1.2)*0.3)))*AV36*I36),2)*BS36),2)*AU36)/100),2)) -> 39.41 | AA36: 57014138 | AB36: =ROUND((AC36+AD36+AF36),6) -> 6.8256 | AC36: =ROUND((((ES36*1)*0)),6) -> 0 | AD36: =ROUND((((((ET36*1.2)*0.3))-(((EU36*1.2)*0.3)))+AE36),6) -> 0.0072 | AE36: =ROUND((((EU36*1.2)*0.3)),6) -> 0 | AF36: =ROUND((((EV36*1.2)*0.3)),6) -> 6.8184 | AG36: =ROUND((AP36),6) -> 0 | AH36: =(((EW36*1.2)*0.3)) -> 0.4896 | AI36: =(((EX36*1.2)*0.3)) -> 0 | AJ36: =(AS36) -> 0 | AK36: 21.3 | AL36: 2.34 | AM36: 0.02 | AN36: 0 | AO36: 18.94 | AP36: 0 | AQ36: 1.36 | AR36: 0 | AS36: 0 | AT36: 90 | AU36: 46 | AV36: 1.047 | AW36: 1 | AZ36: 1 | BA36: 1 | BB36: 1 | BC36: 1 | BH36: 0 | BI36: 2 | BJ36: ТСН-2001.4 Доп. 69, Сб. 10, т. 167, поз. 1 | BM36: 68 | BN36: 0 | BO36: 4.10-167-1 | BP36: 1 | BQ36: 40 | BR36: 0 | BS36: 1 | BT36: 1 | BU36: 1 | BV36: 1 | BW36: 1 | BX36: 1 | BZ36: 90 | CA36: 46 | CE36: 1566 | CF36: 0 | CG36: 0 | CM36: 0 | CN36: Поправка: Гл.12.Прил.8.п.8. 3_12.00.01.11.001 Наименование: При наличии напряженных и стесненных условий производства работ (стесненность, сложность складирования и транспортной логистики и т.п.) для объектов, расположенных в пределах круговой магистральной системы улиц "Садовое кольцо" города Москвы Поправка: Гл.4.Прил.2.2.п.2.2.29_04.00.01.35.003 Наименование: При демонтаже оборудования, предназначенного в лом | CO36: 0 | CP36: =(P36+Q36+S36) -> 85.76 | CQ36: =ROUND((ROUND((AC36*AW36*1),2)*BC36),2) -> 0 | CR36: =(ROUND((ROUND(((((ET36*1.2)*0.3))*AV36*1),2)*BB36),2)+ROUND((ROUND(((AE36-(((EU36*1.2)*0.3)))*AV36*1),2)*BS36),2)) -> 0.01 | CS36: =(ROUND((ROUND(((((EU36*1.2)*0.3))*AV36*1),2)*BS36),2)+ROUND((ROUND(((AE36-(((EU36*1.2)*0.3)))*AV36*1),2)*BS36),2)) -> 0 | CT36: =ROUND((ROUND((AF36*AV36*1),2)*BA36),2) -> 7.14 | CU36: =AG36 -> 0 | CV36: =(AH36*AV36) -> 0.5126112 | CW36: =AI36 -> 0 | CX36: =AJ36 -> 0 | CY36: =(ROUND((((S36+ROUND((ROUND(((((EU36*1.2)*0.3))*AV36*1),2)*BS36),2))*AT36)/100),2)+ROUND(((ROUND((ROUND(((AE36-(((EU36*1.2)*0.3)))*AV36*1),2)*BS36),2)*AT36)/100),2)) -> 77.1 | CZ36: =(ROUND((((S36+ROUND((ROUND(((((EU36*1.2)*0.3))*AV36*1),2)*BS36),2))*AU36)/100),2)+ROUND(((ROUND((ROUND(((AE36-(((EU36*1.2)*0.3)))*AV36*1),2)*BS36),2)*AU36)/100),2)) -> 39.41 | DB36: 17 | DD36: *1)*0 | DE36: *1,2)*0,3 | DF36: *1,2)*0,3 | DG36: *1,2)*0,3 | DI36: *1,2)*0,3 | DJ36: *1,2)*0,3 | DN36: 0 | DO36: 0 | DP36: 1 | DQ36: 1 | DU36: 1013 | DV36: 1 ШТ. | DW36: 1 ШТ. | DX36: 1 | EE36: 57042958 | EF36: 40 | EG36: Монтаж оборудования | EH36: 0 | EJ36: 2 | EK36: 68 | EL36: ТСН-2001.4-10. Прокладка и монтаж сетей связи | EM36: ТСН-2001.4-10-1 | EO36: Поправка: Гл.12.Прил.8.п.8. 3_12.00.01.11.001 Поправка: Гл.4.Прил.2.2.п.2.2.29_04.00.01.35.003 | EQ36: 0 | ER36: 21.3 | ES36: 2.34 | ET36: 0.02 | EU36: 0 | EV36: 18.94 | EW36: 1.36 | EX36: 0 | EY36: 0 | FQ36: 0 | FR36: 0 | FS36: 0 | FX36: 90 | FY36: 46 | GD36: 1 | GF36: -1291988825 | GG36: 2 | GH36: 1 | GI36: 2 | GJ36: 0 | GK36: 0 | GL36: =ROUND(IF(AND(BH36=3,BI36=3,FS36<>0),P36,0),2) -> 0 | GM36: =ROUND(O36+X36+Y36,2)+GX36 -> 202.27 | GN36: =IF(OR(BI36=0,BI36=1),GM36-GX36,0) -> 0 | GO36: =IF(BI36=2,GM36-GX36,0) -> 202.27 | GP36: =IF(BI36=4,GM36-GX36,0) -> 0 | GR36: 0 | GS36: 3 | GT36: 0 | GV36: =ROUND((GT36),6) -> 0 | GW36: 1 | GX36: =ROUND(HC36*I36,2) -> 0 | HA36: 0 | HB36: 0 | HC36: =GV36*GW36 -> 0 | HS36: 0 | IK36: 0
A37: 17 | B37: 1 | C37: =ROW(SmtRes!A38) -> 38 | D37: =ROW(EtalonRes!A46) -> 46 | E37: 5 | F37: 4.10-167-1 | G37: Монтаж блока питания сети (БПС) в диспетчерской / демонтаж блоков электропитания | H37: 1 ШТ. | I37: =ROUND(2+2+4+4,9) -> 12 | J37: 0 | K37: =ROUND(2+2+4+4,9) -> 12 | O37: =ROUND(CP37,2) -> 4828.49 | P37: =ROUND((ROUND((AC37*AW37*I37),2)*BC37),2) -> 0 | Q37: =(ROUND((ROUND(((((ET37*1.2)*0.3))*AV37*I37),2)*BB37),2)+ROUND((ROUND(((AE37-(((EU37*1.2)*0.3)))*AV37*I37),2)*BS37),2)) -> 0.99 | R37: =(ROUND((ROUND(((((EU37*1.2)*0.3))*AV37*I37),2)*BS37),2)+ROUND((ROUND(((AE37-(((EU37*1.2)*0.3)))*AV37*I37),2)*BS37),2)) -> 0 | S37: =ROUND((ROUND((AF37*AV37*I37),2)*BA37),2) -> 4827.5 | T37: =ROUND(CU37*I37,2) -> 0 | U37: =CV37*I37 -> 6.1513344 | V37: =CW37*I37 -> 0 | W37: =ROUND(CX37*I37,2) -> 0 | X37: =(ROUND((((S37+ROUND((ROUND(((((EU37*1.2)*0.3))*AV37*I37),2)*BS37),2))*AT37)/100),2)+ROUND(((ROUND((ROUND(((AE37-(((EU37*1.2)*0.3)))*AV37*I37),2)*BS37),2)*AT37)/100),2)) -> 4344.75 | Y37: =(ROUND((((S37+ROUND((ROUND(((((EU37*1.2)*0.3))*AV37*I37),2)*BS37),2))*AU37)/100),2)+ROUND(((ROUND((ROUND(((AE37-(((EU37*1.2)*0.3)))*AV37*I37),2)*BS37),2)*AU37)/100),2)) -> 2220.65 | AA37: 57014140 | AB37: =ROUND((AC37+AD37+AF37),6) -> 6.8256 | AC37: =ROUND((((ES37*1)*0)),6) -> 0 | AD37: =ROUND((((((ET37*1.2)*0.3))-(((EU37*1.2)*0.3)))+AE37),6) -> 0.0072 | AE37: =ROUND((((EU37*1.2)*0.3)),6) -> 0 | AF37: =ROUND((((EV37*1.2)*0.3)),6) -> 6.8184 | AG37: =ROUND((AP37),6) -> 0 | AH37: =(((EW37*1.2)*0.3)) -> 0.4896 | AI37: =(((EX37*1.2)*0.3)) -> 0 | AJ37: =(AS37) -> 0 | AK37: 21.3 | AL37: 2.34 | AM37: 0.02 | AN37: 0 | AO37: 18.94 | AP37: 0 | AQ37: 1.36 | AR37: 0 | AS37: 0 | AT37: 90 | AU37: 46 | AV37: 1.047 | AW37: 1 | AZ37: 1 | BA37: 56.35 | BB37: 11 | BC37: 10.24 | BH37: 0 | BI37: 2 | BJ37: ТСН-2001.4 Доп. 69, Сб. 10, т. 167, поз. 1 | BM37: 68 | BN37: 0 | BO37: 4.10-167-1 | BP37: 1 | BQ37: 40 | BR37: 0 | BS37: 56.35 | BT37: 1 | BU37: 1 | BV37: 1 | BW37: 1 | BX37: 1 | BZ37: 90 | CA37: 46 | CE37: 1566 | CF37: 0 | CG37: 0 | CM37: 0 | CN37: Поправка: Гл.12.Прил.8.п.8. 3_12.00.01.11.001 Наименование: При наличии напряженных и стесненных условий производства работ (стесненность, сложность складирования и транспортной логистики и т.п.) для объектов, расположенных в пределах круговой магистральной системы улиц "Садовое кольцо" города Москвы Поправка: Гл.4.Прил.2.2.п.2.2.29_04.00.01.35.003 Наименование: При демонтаже оборудования, предназначенного в лом | CO37: 0 | CP37: =(P37+Q37+S37) -> 4828.49 | CQ37: =ROUND((ROUND((AC37*AW37*1),2)*BC37),2) -> 0 | CR37: =(ROUND((ROUND(((((ET37*1.2)*0.3))*AV37*1),2)*BB37),2)+ROUND((ROUND(((AE37-(((EU37*1.2)*0.3)))*AV37*1),2)*BS37),2)) -> 0.11 | CS37: =(ROUND((ROUND(((((EU37*1.2)*0.3))*AV37*1),2)*BS37),2)+ROUND((ROUND(((AE37-(((EU37*1.2)*0.3)))*AV37*1),2)*BS37),2)) -> 0 | CT37: =ROUND((ROUND((AF37*AV37*1),2)*BA37),2) -> 402.34 | CU37: =AG37 -> 0 | CV37: =(AH37*AV37) -> 0.5126112 | CW37: =AI37 -> 0 | CX37: =AJ37 -> 0 | CY37: =(ROUND((((S37+ROUND((ROUND(((((EU37*1.2)*0.3))*AV37*1),2)*BS37),2))*AT37)/100),2)+ROUND(((ROUND((ROUND(((AE37-(((EU37*1.2)*0.3)))*AV37*1),2)*BS37),2)*AT37)/100),2)) -> 4344.75 | CZ37: =(ROUND((((S37+ROUND((ROUND(((((EU37*1.2)*0.3))*AV37*1),2)*BS37),2))*AU37)/100),2)+ROUND(((ROUND((ROUND(((AE37-(((EU37*1.2)*0.3)))*AV37*1),2)*BS37),2)*AU37)/100),2)) -> 2220.65 | DB37: 19 | DD37: *1)*0 | DE37: *1,2)*0,3 | DF37: *1,2)*0,3 | DG37: *1,2)*0,3 | DI37: *1,2)*0,3 | DJ37: *1,2)*0,3 | DN37: 0 | DO37: 0 | DP37: 1 | DQ37: 1 | DU37: 1013 | DV37: 1 ШТ. | DW37: 1 ШТ. | DX37: 1 | EE37: 57042958 | EF37: 40 | EG37: Монтаж оборудования | EH37: 0 | EJ37: 2 | EK37: 68 | EL37: ТСН-2001.4-10. Прокладка и монтаж сетей связи | EM37: ТСН-2001.4-10-1 | EO37: Поправка: Гл.12.Прил.8.п.8. 3_12.00.01.11.001 Поправка: Гл.4.Прил.2.2.п.2.2.29_04.00.01.35.003 | EQ37: 0 | ER37: 21.3 | ES37: 2.34 | ET37: 0.02 | EU37: 0 | EV37: 18.94 | EW37: 1.36 | EX37: 0 | EY37: 0 | FQ37: 0 | FR37: 0 | FS37: 0 | FX37: 90 | FY37: 46 | GD37: 1 | GF37: -1291988825 | GG37: 2 | GH37: 1 | GI37: 2 | GJ37: 0 | GK37: 0 | GL37: =ROUND(IF(AND(BH37=3,BI37=3,FS37<>0),P37,0),2) -> 0 | GM37: =ROUND(O37+X37+Y37,2)+GX37 -> 11393.89 | GN37: =IF(OR(BI37=0,BI37=1),GM37-GX37,0) -> 0 | GO37: =IF(BI37=2,GM37-GX37,0) -> 11393.89 | GP37: =IF(BI37=4,GM37-GX37,0) -> 0 | GR37: 0 | GS37: 3 | GT37: 0 | GV37: =ROUND((GT37),6) -> 0 | GW37: 1 | GX37: =ROUND(HC37*I37,2) -> 0 | HA37: 0 | HB37: 0 | HC37: =GV37*GW37 -> 0 | HS37: 0 | IK37: 0
A38: 17 | B38: 1 | C38: =ROW(SmtRes!A39) -> 39 | D38: =ROW(EtalonRes!A47) -> 47 | E38: 6 | F38: 4.10-81-2 | G38: Извещатели ПС автоматические, дымовой, фотоэлектрический, радиоизотопный, световой в нормальном исполнении / демонтаж оповещателей | H38: 1 ШТ. | I38: =ROUND(12+18+2+4+1+1+1+63+1+10+2+1,9) -> 116 | J38: 0 | K38: =ROUND(12+18+2+4+1+1+1+63+1+10+2+1,9) -> 116 | O38: =ROUND(CP38,2) -> 929.54 | P38: =ROUND((ROUND((AC38*AW38*I38),2)*BC38),2) -> 0 | Q38: =(ROUND((ROUND(((((ET38*1.2)*0.3))*AV38*I38),2)*BB38),2)+ROUND((ROUND(((AE38-(((EU38*1.2)*0.3)))*AV38*I38),2)*BS38),2)) -> 2.62 | R38: =(ROUND((ROUND(((((EU38*1.2)*0.3))*AV38*I38),2)*BS38),2)+ROUND((ROUND(((AE38-(((EU38*1.2)*0.3)))*AV38*I38),2)*BS38),2)) -> 0.44 | S38: =ROUND((ROUND((AF38*AV38*I38),2)*BA38),2) -> 926.92 | T38: =ROUND(CU38*I38,2) -> 0 | U38: =CV38*I38 -> 73.45417 | V38: =CW38*I38 -> 0 | W38: =ROUND(CX38*I38,2) -> 0 | X38: =(ROUND((((S38+ROUND((ROUND(((((EU38*1.2)*0.3))*AV38*I38),2)*BS38),2))*AT38)/100),2)+ROUND(((ROUND((ROUND(((AE38-(((EU38*1.2)*0.3)))*AV38*I38),2)*BS38),2)*AT38)/100),2)) -> 834.62 | Y38: =(ROUND((((S38+ROUND((ROUND(((((EU38*1.2)*0.3))*AV38*I38),2)*BS38),2))*AU38)/100),2)+ROUND(((ROUND((ROUND(((AE38-(((EU38*1.2)*0.3)))*AV38*I38),2)*BS38),2)*AU38)/100),2)) -> 426.59 | AA38: 57014138 | AB38: =ROUND((AC38+AD38+AF38),6) -> 7.6536 | AC38: =ROUND((((ES38*1)*0)),6) -> 0 | AD38: =ROUND((((((ET38*1.2)*0.3))-(((EU38*1.2)*0.3)))+AE38),6) -> 0.0216 | AE38: =ROUND((((EU38*1.2)*0.3)),6) -> 0.0036 | AF38: =ROUND((((EV38*1.2)*0.3)),6) -> 7.632 | AG38: =ROUND((AP38),6) -> 0 | AH38: =(((EW38*1.2)*0.3)) -> 0.6048 | AI38: =(((EX38*1.2)*0.3)) -> 0 | AJ38: =(AS38) -> 0 | AK38: 22.52 | AL38: 1.26 | AM38: 0.06 | AN38: 0.01 | AO38: 21.2 | AP38: 0 | AQ38: 1.68 | AR38: 0 | AS38: 0 | AT38: 90 | AU38: 46 | AV38: 1.047 | AW38: 1 | AZ38: 1 | BA38: 1 | BB38: 1 | BC38: 1 | BH38: 0 | BI38: 2 | BJ38: ТСН-2001.4. Доп. 1-42. Сб. 10, т. 81, поз. 2 | BM38: 68 | BN38: 0 | BO38: 4.10-81-2 | BP38: 1 | BQ38: 40 | BR38: 0 | BS38: 1 | BT38: 1 | BU38: 1 | BV38: 1 | BW38: 1 | BX38: 1 | BZ38: 90 | CA38: 46 | CE38: 1566 | CF38: 0 | CG38: 0 | CM38: 0 | CN38: Поправка: Гл.12.Прил.8.п.8. 3_12.00.01.11.001 Наименование: При наличии напряженных и стесненных условий производства работ (стесненность, сложность складирования и транспортной логистики и т.п.) для объектов, расположенных в пределах круговой магистральной системы улиц "Садовое кольцо" города Москвы Поправка: Гл.4.Прил.2.2.п.2.2.29_04.00.01.35.003 Наименование: При демонтаже оборудования, предназначенного в лом | CO38: 0 | CP38: =(P38+Q38+S38) -> 929.54 | CQ38: =ROUND((ROUND((AC38*AW38*1),2)*BC38),2) -> 0 | CR38: =(ROUND((ROUND(((((ET38*1.2)*0.3))*AV38*1),2)*BB38),2)+ROUND((ROUND(((AE38-(((EU38*1.2)*0.3)))*AV38*1),2)*BS38),2)) -> 0.02 | CS38: =(ROUND((ROUND(((((EU38*1.2)*0.3))*AV38*1),2)*BS38),2)+ROUND((ROUND(((AE38-(((EU38*1.2)*0.3)))*AV38*1),2)*BS38),2)) -> 0 | CT38: =ROUND((ROUND((AF38*AV38*1),2)*BA38),2) -> 7.99 | CU38: =AG38 -> 0 | CV38: =(AH38*AV38) -> 0.6332256 | CW38: =AI38 -> 0 | CX38: =AJ38 -> 0 | CY38: =(ROUND((((S38+ROUND((ROUND(((((EU38*1.2)*0.3))*AV38*1),2)*BS38),2))*AT38)/100),2)+ROUND(((ROUND((ROUND(((AE38-(((EU38*1.2)*0.3)))*AV38*1),2)*BS38),2)*AT38)/100),2)) -> 834.23 | CZ38: =(ROUND((((S38+ROUND((ROUND(((((EU38*1.2)*0.3))*AV38*1),2)*BS38),2))*AU38)/100),2)+ROUND(((ROUND((ROUND(((AE38-(((EU38*1.2)*0.3)))*AV38*1),2)*BS38),2)*AU38)/100),2)) -> 426.38 | DB38: 21 | DD38: *1)*0 | DE38: *1,2)*0,3 | DF38: *1,2)*0,3 | DG38: *1,2)*0,3 | DI38: *1,2)*0,3 | DJ38: *1,2)*0,3 | DN38: 0 | DO38: 0 | DP38: 1 | DQ38: 1 | DU38: 1013 | DV38: 1 ШТ. | DW38: 1 ШТ. | DX38: 1 | EE38: 57042958 | EF38: 40 | EG38: Монтаж оборудования | EH38: 0 | EJ38: 2 | EK38: 68 | EL38: ТСН-2001.4-10. Прокладка и монтаж сетей связи | EM38: ТСН-2001.4-10-1 | EO38: Поправка: Гл.12.Прил.8.п.8. 3_12.00.01.11.001 Поправка: Гл.4.Прил.2.2.п.2.2.29_04.00.01.35.003 | EQ38: 0 | ER38: 22.52 | ES38: 1.26 | ET38: 0.06 | EU38: 0.01 | EV38: 21.2 | EW38: 1.68 | EX38: 0 | EY38: 0 | FQ38: 0 | FR38: 0 | FS38: 0 | FX38: 90 | FY38: 46 | GD38: 1 | GF38: -324079866 | GG38: 2 | GH38: 1 | GI38: 2 | GJ38: 0 | GK38: 0 | GL38: =ROUND(IF(AND(BH38=3,BI38=3,FS38<>0),P38,0),2) -> 0 | GM38: =ROUND(O38+X38+Y38,2)+GX38 -> 2190.75 | GN38: =IF(OR(BI38=0,BI38=1),GM38-GX38,0) -> 0 | GO38: =IF(BI38=2,GM38-GX38,0) -> 2190.75 | GP38: =IF(BI38=4,GM38-GX38,0) -> 0 | GR38: 0 | GS38: 3 | GT38: 0 | GV38: =ROUND((GT38),6) -> 0 | GW38: 1 | GX38: =ROUND(HC38*I38,2) -> 0 | HA38: 0 | HB38: 0 | HC38: =GV38*GW38 -> 0 | HS38: 0 | IK38: 0
A39: 17 | B39: 1 | C39: =ROW(SmtRes!A40) -> 40 | D39: =ROW(EtalonRes!A48) -> 48 | E39: 6 | F39: 4.10-81-2 | G39: Извещатели ПС автоматические, дымовой, фотоэлектрический, радиоизотопный, световой в нормальном исполнении / демонтаж оповещателей | H39: 1 ШТ. | I39: =ROUND(12+18+2+4+1+1+1+63+1+10+2+1,9) -> 116 | J39: 0 | K39: =ROUND(12+18+2+4+1+1+1+63+1+10+2+1,9) -> 116 | O39: =ROUND(CP39,2) -> 52280.41 | P39: =ROUND((ROUND((AC39*AW39*I39),2)*BC39),2) -> 0 | Q39: =(ROUND((ROUND(((((ET39*1.2)*0.3))*AV39*I39),2)*BB39),2)+ROUND((ROUND(((AE39-(((EU39*1.2)*0.3)))*AV39*I39),2)*BS39),2)) -> 48.47 | R39: =(ROUND((ROUND(((((EU39*1.2)*0.3))*AV39*I39),2)*BS39),2)+ROUND((ROUND(((AE39-(((EU39*1.2)*0.3)))*AV39*I39),2)*BS39),2)) -> 24.79 | S39: =ROUND((ROUND((AF39*AV39*I39),2)*BA39),2) -> 52231.94 | T39: =ROUND(CU39*I39,2) -> 0 | U39: =CV39*I39 -> 73.45417 | V39: =CW39*I39 -> 0 | W39: =ROUND(CX39*I39,2) -> 0 | X39: =(ROUND((((S39+ROUND((ROUND(((((EU39*1.2)*0.3))*AV39*I39),2)*BS39),2))*AT39)/100),2)+ROUND(((ROUND((ROUND(((AE39-(((EU39*1.2)*0.3)))*AV39*I39),2)*BS39),2)*AT39)/100),2)) -> 47031.06 | Y39: =(ROUND((((S39+ROUND((ROUND(((((EU39*1.2)*0.3))*AV39*I39),2)*BS39),2))*AU39)/100),2)+ROUND(((ROUND((ROUND(((AE39-(((EU39*1.2)*0.3)))*AV39*I39),2)*BS39),2)*AU39)/100),2)) -> 24038.1 | AA39: 57014140 | AB39: =ROUND((AC39+AD39+AF39),6) -> 7.6536 | AC39: =ROUND((((ES39*1)*0)),6) -> 0 | AD39: =ROUND((((((ET39*1.2)*0.3))-(((EU39*1.2)*0.3)))+AE39),6) -> 0.0216 | AE39: =ROUND((((EU39*1.2)*0.3)),6) -> 0.0036 | AF39: =ROUND((((EV39*1.2)*0.3)),6) -> 7.632 | AG39: =ROUND((AP39),6) -> 0 | AH39: =(((EW39*1.2)*0.3)) -> 0.6048 | AI39: =(((EX39*1.2)*0.3)) -> 0 | AJ39: =(AS39) -> 0 | AK39: 22.52 | AL39: 1.26 | AM39: 0.06 | AN39: 0.01 | AO39: 21.2 | AP39: 0 | AQ39: 1.68 | AR39: 0 | AS39: 0 | AT39: 90 | AU39: 46 | AV39: 1.047 | AW39: 1 | AZ39: 1 | BA39: 56.35 | BB39: 18.5 | BC39: 9.84 | BH39: 0 | BI39: 2 | BJ39: ТСН-2001.4. Доп. 1-42. Сб. 10, т. 81, поз. 2 | BM39: 68 | BN39: 0 | BO39: 4.10-81-2 | BP39: 1 | BQ39: 40 | BR39: 0 | BS39: 56.35 | BT39: 1 | BU39: 1 | BV39: 1 | BW39: 1 | BX39: 1 | BZ39: 90 | CA39: 46 | CE39: 1566 | CF39: 0 | CG39: 0 | CM39: 0 | CN39: Поправка: Гл.12.Прил.8.п.8. 3_12.00.01.11.001 Наименование: При наличии напряженных и стесненных условий производства работ (стесненность, сложность складирования и транспортной логистики и т.п.) для объектов, расположенных в пределах круговой магистральной системы улиц "Садовое кольцо" города Москвы Поправка: Гл.4.Прил.2.2.п.2.2.29_04.00.01.35.003 Наименование: При демонтаже оборудования, предназначенного в лом | CO39: 0 | CP39: =(P39+Q39+S39) -> 52280.41 | CQ39: =ROUND((ROUND((AC39*AW39*1),2)*BC39),2) -> 0 | CR39: =(ROUND((ROUND(((((ET39*1.2)*0.3))*AV39*1),2)*BB39),2)+ROUND((ROUND(((AE39-(((EU39*1.2)*0.3)))*AV39*1),2)*BS39),2)) -> 0.37 | CS39: =(ROUND((ROUND(((((EU39*1.2)*0.3))*AV39*1),2)*BS39),2)+ROUND((ROUND(((AE39-(((EU39*1.2)*0.3)))*AV39*1),2)*BS39),2)) -> 0 | CT39: =ROUND((ROUND((AF39*AV39*1),2)*BA39),2) -> 450.24 | CU39: =AG39 -> 0 | CV39: =(AH39*AV39) -> 0.6332256 | CW39: =AI39 -> 0 | CX39: =AJ39 -> 0 | CY39: =(ROUND((((S39+ROUND((ROUND(((((EU39*1.2)*0.3))*AV39*1),2)*BS39),2))*AT39)/100),2)+ROUND(((ROUND((ROUND(((AE39-(((EU39*1.2)*0.3)))*AV39*1),2)*BS39),2)*AT39)/100),2)) -> 47008.75 | CZ39: =(ROUND((((S39+ROUND((ROUND(((((EU39*1.2)*0.3))*AV39*1),2)*BS39),2))*AU39)/100),2)+ROUND(((ROUND((ROUND(((AE39-(((EU39*1.2)*0.3)))*AV39*1),2)*BS39),2)*AU39)/100),2)) -> 24026.69 | DB39: 23 | DD39: *1)*0 | DE39: *1,2)*0,3 | DF39: *1,2)*0,3 | DG39: *1,2)*0,3 | DI39: *1,2)*0,3 | DJ39: *1,2)*0,3 | DN39: 0 | DO39: 0 | DP39: 1 | DQ39: 1 | DU39: 1013 | DV39: 1 ШТ. | DW39: 1 ШТ. | DX39: 1 | EE39: 57042958 | EF39: 40 | EG39: Монтаж оборудования | EH39: 0 | EJ39: 2 | EK39: 68 | EL39: ТСН-2001.4-10. Прокладка и монтаж сетей связи | EM39: ТСН-2001.4-10-1 | EO39: Поправка: Гл.12.Прил.8.п.8. 3_12.00.01.11.001 Поправка: Гл.4.Прил.2.2.п.2.2.29_04.00.01.35.003 | EQ39: 0 | ER39: 22.52 | ES39: 1.26 | ET39: 0.06 | EU39: 0.01 | EV39: 21.2 | EW39: 1.68 | EX39: 0 | EY39: 0 | FQ39: 0 | FR39: 0 | FS39: 0 | FX39: 90 | FY39: 46 | GD39: 1 | GF39: -324079866 | GG39: 2 | GH39: 1 | GI39: 2 | GJ39: 0 | GK39: 0 | GL39: =ROUND(IF(AND(BH39=3,BI39=3,FS39<>0),P39,0),2) -> 0 | GM39: =ROUND(O39+X39+Y39,2)+GX39 -> 123349.57 | GN39: =IF(OR(BI39=0,BI39=1),GM39-GX39,0) -> 0 | GO39: =IF(BI39=2,GM39-GX39,0) -> 123349.57 | GP39: =IF(BI39=4,GM39-GX39,0) -> 0 | GR39: 0 | GS39: 3 | GT39: 0 | GV39: =ROUND((GT39),6) -> 0 | GW39: 1 | GX39: =ROUND(HC39*I39,2) -> 0 | HA39: 0 | HB39: 0 | HC39: =GV39*GW39 -> 0 | HS39: 0 | IK39: 0
A40: 17 | B40: 1 | C40: =ROW(SmtRes!A44) -> 44 | D40: =ROW(EtalonRes!A53) -> 53 | E40: 7 | F40: 4.10-76-7 | G40: Монтаж громкоговорителя или звуковой колонки в помещении / демонтаж громкоговорителей | H40: 1 ШТ. | I40: =ROUND(144+42,9) -> 186 | J40: 0 | K40: =ROUND(144+42,9) -> 186 | O40: =ROUND(CP40,2) -> 1667.15 | P40: =ROUND((ROUND((AC40*AW40*I40),2)*BC40),2) -> 0 | Q40: =(ROUND((ROUND(((((ET40*1.2)*0.3))*AV40*I40),2)*BB40),2)+ROUND((ROUND(((AE40-(((EU40*1.2)*0.3)))*AV40*I40),2)*BS40),2)) -> 0 | R40: =(ROUND((ROUND(((((EU40*1.2)*0.3))*AV40*I40),2)*BS40),2)+ROUND((ROUND(((AE40-(((EU40*1.2)*0.3)))*AV40*I40),2)*BS40),2)) -> 0 | S40: =ROUND((ROUND((AF40*AV40*I40),2)*BA40),2) -> 1667.15 | T40: =ROUND(CU40*I40,2) -> 0 | U40: =CV40*I40 -> 140.21424 | V40: =CW40*I40 -> 0 | W40: =ROUND(CX40*I40,2) -> 0 | X40: =(ROUND((((S40+ROUND((ROUND(((((EU40*1.2)*0.3))*AV40*I40),2)*BS40),2))*AT40)/100),2)+ROUND(((ROUND((ROUND(((AE40-(((EU40*1.2)*0.3)))*AV40*I40),2)*BS40),2)*AT40)/100),2)) -> 1583.79 | Y40: =(ROUND((((S40+ROUND((ROUND(((((EU40*1.2)*0.3))*AV40*I40),2)*BS40),2))*AU40)/100),2)+ROUND(((ROUND((ROUND(((AE40-(((EU40*1.2)*0.3)))*AV40*I40),2)*BS40),2)*AU40)/100),2)) -> 883.59 | AA40: 57014138 | AB40: =ROUND((AC40+AD40+AF40),6) -> 8.5608 | AC40: =ROUND((((ES40*1)*0)),6) -> 0 | AD40: =ROUND((((((ET40*1.2)*0.3))-(((EU40*1.2)*0.3)))+AE40),6) -> 0 | AE40: =ROUND((((EU40*1.2)*0.3)),6) -> 0 | AF40: =ROUND((((EV40*1.2)*0.3)),6) -> 8.5608 | AG40: =ROUND((AP40),6) -> 0 | AH40: =(((EW40*1.2)*0.3)) -> 0.72 | AI40: =(((EX40*1.2)*0.3)) -> 0 | AJ40: =(AS40) -> 0 | AK40: 48.24 | AL40: 24.46 | AM40: 0 | AN40: 0 | AO40: 23.78 | AP40: 0 | AQ40: 2 | AR40: 0 | AS40: 0 | AT40: 95 | AU40: 53 | AV40: 1.047 | AW40: 1 | AZ40: 1 | BA40: 1 | BB40: 1 | BC40: 1 | BH40: 0 | BI40: 2 | BJ40: ТСН-2001.4 Доп. 67, Сб. 10, т. 76, поз. 7 | BM40: 69 | BN40: 0 | BO40: 4.10-76-7 | BP40: 1 | BQ40: 40 | BR40: 0 | BS40: 1 | BT40: 1 | BU40: 1 | BV40: 1 | BW40: 1 | BX40: 1 | BZ40: 95 | CA40: 53 | CE40: 1566 | CF40: 0 | CG40: 0 | CM40: 0 | CN40: Поправка: Гл.12.Прил.8.п.8. 3_12.00.01.11.001 Наименование: При наличии напряженных и стесненных условий производства работ (стесненность, сложность складирования и транспортной логистики и т.п.) для объектов, расположенных в пределах круговой магистральной системы улиц "Садовое кольцо" города Москвы Поправка: Гл.4.Прил.2.2.п.2.2.29_04.00.01.35.003 Наименование: При демонтаже оборудования, предназначенного в лом | CO40: 0 | CP40: =(P40+Q40+S40) -> 1667.15 | CQ40: =ROUND((ROUND((AC40*AW40*1),2)*BC40),2) -> 0 | CR40: =(ROUND((ROUND(((((ET40*1.2)*0.3))*AV40*1),2)*BB40),2)+ROUND((ROUND(((AE40-(((EU40*1.2)*0.3)))*AV40*1),2)*BS40),2)) -> 0 | CS40: =(ROUND((ROUND(((((EU40*1.2)*0.3))*AV40*1),2)*BS40),2)+ROUND((ROUND(((AE40-(((EU40*1.2)*0.3)))*AV40*1),2)*BS40),2)) -> 0 | CT40: =ROUND((ROUND((AF40*AV40*1),2)*BA40),2) -> 8.96 | CU40: =AG40 -> 0 | CV40: =(AH40*AV40) -> 0.75384 | CW40: =AI40 -> 0 | CX40: =AJ40 -> 0 | CY40: =(ROUND((((S40+ROUND((ROUND(((((EU40*1.2)*0.3))*AV40*1),2)*BS40),2))*AT40)/100),2)+ROUND(((ROUND((ROUND(((AE40-(((EU40*1.2)*0.3)))*AV40*1),2)*BS40),2)*AT40)/100),2)) -> 1583.79 | CZ40: =(ROUND((((S40+ROUND((ROUND(((((EU40*1.2)*0.3))*AV40*1),2)*BS40),2))*AU40)/100),2)+ROUND(((ROUND((ROUND(((AE40-(((EU40*1.2)*0.3)))*AV40*1),2)*BS40),2)*AU40)/100),2)) -> 883.59 | DB40: 25 | DD40: *1)*0 | DE40: *1,2)*0,3 | DF40: *1,2)*0,3 | DG40: *1,2)*0,3 | DI40: *1,2)*0,3 | DJ40: *1,2)*0,3 | DN40: 0 | DO40: 0 | DP40: 1 | DQ40: 1 | DU40: 1013 | DV40: 1 ШТ. | DW40: 1 ШТ. | DX40: 1 | EE40: 57042959 | EF40: 40 | EG40: Монтаж оборудования | EH40: 0 | EJ40: 2 | EK40: 69 | EL40: ТСН-2001.4-10. Монтаж радиотелевизионного и электронного оборудования | EM40: ТСН-2001.4-10-2 | EO40: Поправка: Гл.12.Прил.8.п.8. 3_12.00.01.11.001 Поправка: Гл.4.Прил.2.2.п.2.2.29_04.00.01.35.003 | EQ40: 0 | ER40: 48.24 | ES40: 24.46 | ET40: 0 | EU40: 0 | EV40: 23.78 | EW40: 2 | EX40: 0 | EY40: 0 | FQ40: 0 | FR40: 0 | FS40: 0 | FX40: 95 | FY40: 53 | GD40: 1 | GF40: 35820931 | GG40: 2 | GH40: 1 | GI40: 2 | GJ40: 0 | GK40: 0 | GL40: =ROUND(IF(AND(BH40=3,BI40=3,FS40<>0),P40,0),2) -> 0 | GM40: =ROUND(O40+X40+Y40,2)+GX40 -> 4134.53 | GN40: =IF(OR(BI40=0,BI40=1),GM40-GX40,0) -> 0 | GO40: =IF(BI40=2,GM40-GX40,0) -> 4134.53 | GP40: =IF(BI40=4,GM40-GX40,0) -> 0 | GR40: 0 | GS40: 3 | GT40: 0 | GV40: =ROUND((GT40),6) -> 0 | GW40: 1 | GX40: =ROUND(HC40*I40,2) -> 0 | HA40: 0 | HB40: 0 | HC40: =GV40*GW40 -> 0 | HS40: 0 | IK40: 0
A41: 17 | B41: 1 | C41: =ROW(SmtRes!A48) -> 48 | D41: =ROW(EtalonRes!A58) -> 58 | E41: 7 | F41: 4.10-76-7 | G41: Монтаж громкоговорителя или звуковой колонки в помещении / демонтаж громкоговорителей | H41: 1 ШТ. | I41: =ROUND(144+42,9) -> 186 | J41: 0 | K41: =ROUND(144+42,9) -> 186 | O41: =ROUND(CP41,2) -> 93943.9 | P41: =ROUND((ROUND((AC41*AW41*I41),2)*BC41),2) -> 0 | Q41: =(ROUND((ROUND(((((ET41*1.2)*0.3))*AV41*I41),2)*BB41),2)+ROUND((ROUND(((AE41-(((EU41*1.2)*0.3)))*AV41*I41),2)*BS41),2)) -> 0 | R41: =(ROUND((ROUND(((((EU41*1.2)*0.3))*AV41*I41),2)*BS41),2)+ROUND((ROUND(((AE41-(((EU41*1.2)*0.3)))*AV41*I41),2)*BS41),2)) -> 0 | S41: =ROUND((ROUND((AF41*AV41*I41),2)*BA41),2) -> 93943.9 | T41: =ROUND(CU41*I41,2) -> 0 | U41: =CV41*I41 -> 140.21424 | V41: =CW41*I41 -> 0 | W41: =ROUND(CX41*I41,2) -> 0 | X41: =(ROUND((((S41+ROUND((ROUND(((((EU41*1.2)*0.3))*AV41*I41),2)*BS41),2))*AT41)/100),2)+ROUND(((ROUND((ROUND(((AE41-(((EU41*1.2)*0.3)))*AV41*I41),2)*BS41),2)*AT41)/100),2)) -> 89246.71 | Y41: =(ROUND((((S41+ROUND((ROUND(((((EU41*1.2)*0.3))*AV41*I41),2)*BS41),2))*AU41)/100),2)+ROUND(((ROUND((ROUND(((AE41-(((EU41*1.2)*0.3)))*AV41*I41),2)*BS41),2)*AU41)/100),2)) -> 49790.27 | AA41: 57014140 | AB41: =ROUND((AC41+AD41+AF41),6) -> 8.5608 | AC41: =ROUND((((ES41*1)*0)),6) -> 0 | AD41: =ROUND((((((ET41*1.2)*0.3))-(((EU41*1.2)*0.3)))+AE41),6) -> 0 | AE41: =ROUND((((EU41*1.2)*0.3)),6) -> 0 | AF41: =ROUND((((EV41*1.2)*0.3)),6) -> 8.5608 | AG41: =ROUND((AP41),6) -> 0 | AH41: =(((EW41*1.2)*0.3)) -> 0.72 | AI41: =(((EX41*1.2)*0.3)) -> 0 | AJ41: =(AS41) -> 0 | AK41: 48.24 | AL41: 24.46 | AM41: 0 | AN41: 0 | AO41: 23.78 | AP41: 0 | AQ41: 2 | AR41: 0 | AS41: 0 | AT41: 95 | AU41: 53 | AV41: 1.047 | AW41: 1 | AZ41: 1 | BA41: 56.35 | BB41: 1 | BC41: 11.11 | BH41: 0 | BI41: 2 | BJ41: ТСН-2001.4 Доп. 67, Сб. 10, т. 76, поз. 7 | BM41: 69 | BN41: 0 | BO41: 4.10-76-7 | BP41: 1 | BQ41: 40 | BR41: 0 | BS41: 56.35 | BT41: 1 | BU41: 1 | BV41: 1 | BW41: 1 | BX41: 1 | BZ41: 95 | CA41: 53 | CE41: 1566 | CF41: 0 | CG41: 0 | CM41: 0 | CN41: Поправка: Гл.12.Прил.8.п.8. 3_12.00.01.11.001 Наименование: При наличии напряженных и стесненных условий производства работ (стесненность, сложность складирования и транспортной логистики и т.п.) для объектов, расположенных в пределах круговой магистральной системы улиц "Садовое кольцо" города Москвы Поправка: Гл.4.Прил.2.2.п.2.2.29_04.00.01.35.003 Наименование: При демонтаже оборудования, предназначенного в лом | CO41: 0 | CP41: =(P41+Q41+S41) -> 93943.9 | CQ41: =ROUND((ROUND((AC41*AW41*1),2)*BC41),2) -> 0 | CR41: =(ROUND((ROUND(((((ET41*1.2)*0.3))*AV41*1),2)*BB41),2)+ROUND((ROUND(((AE41-(((EU41*1.2)*0.3)))*AV41*1),2)*BS41),2)) -> 0 | CS41: =(ROUND((ROUND(((((EU41*1.2)*0.3))*AV41*1),2)*BS41),2)+ROUND((ROUND(((AE41-(((EU41*1.2)*0.3)))*AV41*1),2)*BS41),2)) -> 0 | CT41: =ROUND((ROUND((AF41*AV41*1),2)*BA41),2) -> 504.9 | CU41: =AG41 -> 0 | CV41: =(AH41*AV41) -> 0.75384 | CW41: =AI41 -> 0 | CX41: =AJ41 -> 0 | CY41: =(ROUND((((S41+ROUND((ROUND(((((EU41*1.2)*0.3))*AV41*1),2)*BS41),2))*AT41)/100),2)+ROUND(((ROUND((ROUND(((AE41-(((EU41*1.2)*0.3)))*AV41*1),2)*BS41),2)*AT41)/100),2)) -> 89246.71 | CZ41: =(ROUND((((S41+ROUND((ROUND(((((EU41*1.2)*0.3))*AV41*1),2)*BS41),2))*AU41)/100),2)+ROUND(((ROUND((ROUND(((AE41-(((EU41*1.2)*0.3)))*AV41*1),2)*BS41),2)*AU41)/100),2)) -> 49790.27 | DB41: 27 | DD41: *1)*0 | DE41: *1,2)*0,3 | DF41: *1,2)*0,3 | DG41: *1,2)*0,3 | DI41: *1,2)*0,3 | DJ41: *1,2)*0,3 | DN41: 0 | DO41: 0 | DP41: 1 | DQ41: 1 | DU41: 1013 | DV41: 1 ШТ. | DW41: 1 ШТ. | DX41: 1 | EE41: 57042959 | EF41: 40 | EG41: Монтаж оборудования | EH41: 0 | EJ41: 2 | EK41: 69 | EL41: ТСН-2001.4-10. Монтаж радиотелевизионного и электронного оборудования | EM41: ТСН-2001.4-10-2 | EO41: Поправка: Гл.12.Прил.8.п.8. 3_12.00.01.11.001 Поправка: Гл.4.Прил.2.2.п.2.2.29_04.00.01.35.003 | EQ41: 0 | ER41: 48.24 | ES41: 24.46 | ET41: 0 | EU41: 0 | EV41: 23.78 | EW41: 2 | EX41: 0 | EY41: 0 | FQ41: 0 | FR41: 0 | FS41: 0 | FX41: 95 | FY41: 53 | GD41: 1 | GF41: 35820931 | GG41: 2 | GH41: 1 | GI41: 2 | GJ41: 0 | GK41: 0 | GL41: =ROUND(IF(AND(BH41=3,BI41=3,FS41<>0),P41,0),2) -> 0 | GM41: =ROUND(O41+X41+Y41,2)+GX41 -> 232980.88 | GN41: =IF(OR(BI41=0,BI41=1),GM41-GX41,0) -> 0 | GO41: =IF(BI41=2,GM41-GX41,0) -> 232980.88 | GP41: =IF(BI41=4,GM41-GX41,0) -> 0 | GR41: 0 | GS41: 3 | GT41: 0 | GV41: =ROUND((GT41),6) -> 0 | GW41: 1 | GX41: =ROUND(HC41*I41,2) -> 0 | HA41: 0 | HB41: 0 | HC41: =GV41*GW41 -> 0 | HS41: 0 | IK41: 0
A42: 17 | B42: 1 | C42: =ROW(SmtRes!A53) -> 53 | D42: =ROW(EtalonRes!A64) -> 64 | E42: 8 | F42: 4.10-118-12 | G42: Установка для трубных проводок коробки оконечной / демонтаж фильтра оконечного | H42: 100 шт. | I42: =ROUND(7/100,9) -> 0.07 | J42: 0 | K42: =ROUND(7/100,9) -> 0.07 | O42: =ROUND(CP42,2) -> 7.35 | P42: =ROUND((ROUND((AC42*AW42*I42),2)*BC42),2) -> 0 | Q42: =(ROUND((ROUND(((((ET42*1.2)*0.3))*AV42*I42),2)*BB42),2)+ROUND((ROUND(((AE42-(((EU42*1.2)*0.3)))*AV42*I42),2)*BS42),2)) -> 0 | R42: =(ROUND((ROUND(((((EU42*1.2)*0.3))*AV42*I42),2)*BS42),2)+ROUND((ROUND(((AE42-(((EU42*1.2)*0.3)))*AV42*I42),2)*BS42),2)) -> 0 | S42: =ROUND((ROUND((AF42*AV42*I42),2)*BA42),2) -> 7.35 | T42: =ROUND(CU42*I42,2) -> 0 | U42: =CV42*I42 -> 0.6332256 | V42: =CW42*I42 -> 0 | W42: =ROUND(CX42*I42,2) -> 0 | X42: =(ROUND((((S42+ROUND((ROUND(((((EU42*1.2)*0.3))*AV42*I42),2)*BS42),2))*AT42)/100),2)+ROUND(((ROUND((ROUND(((AE42-(((EU42*1.2)*0.3)))*AV42*I42),2)*BS42),2)*AT42)/100),2)) -> 6.62 | Y42: =(ROUND((((S42+ROUND((ROUND(((((EU42*1.2)*0.3))*AV42*I42),2)*BS42),2))*AU42)/100),2)+ROUND(((ROUND((ROUND(((AE42-(((EU42*1.2)*0.3)))*AV42*I42),2)*BS42),2)*AU42)/100),2)) -> 3.38 | AA42: 57014138 | AB42: =ROUND((AC42+AD42+AF42),6) -> 100.3104 | AC42: =ROUND((((ES42*1)*0)),6) -> 0 | AD42: =ROUND((((((ET42*1.2)*0.3))-(((EU42*1.2)*0.3)))+AE42),6) -> 0 | AE42: =ROUND((((EU42*1.2)*0.3)),6) -> 0 | AF42: =ROUND((((EV42*1.2)*0.3)),6) -> 100.3104 | AG42: =ROUND((AP42),6) -> 0 | AH42: =(((EW42*1.2)*0.3)) -> 8.64 | AI42: =(((EX42*1.2)*0.3)) -> 0 | AJ42: =(AS42) -> 0 | AK42: 364.24 | AL42: 85.6 | AM42: 0 | AN42: 0 | AO42: 278.64 | AP42: 0 | AQ42: 24 | AR42: 0 | AS42: 0 | AT42: 90 | AU42: 46 | AV42: 1.047 | AW42: 1 | AZ42: 1 | BA42: 1 | BB42: 1 | BC42: 1 | BH42: 0 | BI42: 2 | BJ42: ТСН-2001.4 Доп. 79, Сб. 10, т. 118, поз. 12 | BM42: 68 | BN42: 0 | BO42: 4.10-118-12 | BP42: 1 | BQ42: 40 | BR42: 0 | BS42: 1 | BT42: 1 | BU42: 1 | BV42: 1 | BW42: 1 | BX42: 1 | BZ42: 90 | CA42: 46 | CE42: 1566 | CF42: 0 | CG42: 0 | CM42: 0 | CN42: Поправка: Гл.12.Прил.8.п.8. 3_12.00.01.11.001 Наименование: При наличии напряженных и стесненных условий производства работ (стесненность, сложность складирования и транспортной логистики и т.п.) для объектов, расположенных в пределах круговой магистральной системы улиц "Садовое кольцо" города Москвы Поправка: Гл.4.Прил.2.2.п.2.2.29_04.00.01.35.003 Наименование: При демонтаже оборудования, предназначенного в лом | CO42: 0 | CP42: =(P42+Q42+S42) -> 7.35 | CQ42: =ROUND((ROUND((AC42*AW42*1),2)*BC42),2) -> 0 | CR42: =(ROUND((ROUND(((((ET42*1.2)*0.3))*AV42*1),2)*BB42),2)+ROUND((ROUND(((AE42-(((EU42*1.2)*0.3)))*AV42*1),2)*BS42),2)) -> 0 | CS42: =(ROUND((ROUND(((((EU42*1.2)*0.3))*AV42*1),2)*BS42),2)+ROUND((ROUND(((AE42-(((EU42*1.2)*0.3)))*AV42*1),2)*BS42),2)) -> 0 | CT42: =ROUND((ROUND((AF42*AV42*1),2)*BA42),2) -> 105.02 | CU42: =AG42 -> 0 | CV42: =(AH42*AV42) -> 9.04608 | CW42: =AI42 -> 0 | CX42: =AJ42 -> 0 | CY42: =(ROUND((((S42+ROUND((ROUND(((((EU42*1.2)*0.3))*AV42*1),2)*BS42),2))*AT42)/100),2)+ROUND(((ROUND((ROUND(((AE42-(((EU42*1.2)*0.3)))*AV42*1),2)*BS42),2)*AT42)/100),2)) -> 6.62 | CZ42: =(ROUND((((S42+ROUND((ROUND(((((EU42*1.2)*0.3))*AV42*1),2)*BS42),2))*AU42)/100),2)+ROUND(((ROUND((ROUND(((AE42-(((EU42*1.2)*0.3)))*AV42*1),2)*BS42),2)*AU42)/100),2)) -> 3.38 | DB42: 29 | DD42: *1)*0 | DE42: *1,2)*0,3 | DF42: *1,2)*0,3 | DG42: *1,2)*0,3 | DI42: *1,2)*0,3 | DJ42: *1,2)*0,3 | DN42: 0 | DO42: 0 | DP42: 1 | DQ42: 1 | DU42: 1010 | DV42: 100 шт. | DW42: 100 шт. | DX42: 100 | EE42: 57042958 | EF42: 40 | EG42: Монтаж оборудования | EH42: 0 | EJ42: 2 | EK42: 68 | EL42: ТСН-2001.4-10. Прокладка и монтаж сетей связи | EM42: ТСН-2001.4-10-1 | EO42: Поправка: Гл.12.Прил.8.п.8. 3_12.00.01.11.001 Поправка: Гл.4.Прил.2.2.п.2.2.29_04.00.01.35.003 | EQ42: 0 | ER42: 364.24 | ES42: 85.6 | ET42: 0 | EU42: 0 | EV42: 278.64 | EW42: 24 | EX42: 0 | EY42: 0 | FQ42: 0 | FR42: 0 | FS42: 0 | FX42: 90 | FY42: 46 | GD42: 1 | GF42: 990274235 | GG42: 2 | GH42: 1 | GI42: 2 | GJ42: 0 | GK42: 0 | GL42: =ROUND(IF(AND(BH42=3,BI42=3,FS42<>0),P42,0),2) -> 0 | GM42: =ROUND(O42+X42+Y42,2)+GX42 -> 17.35 | GN42: =IF(OR(BI42=0,BI42=1),GM42-GX42,0) -> 0 | GO42: =IF(BI42=2,GM42-GX42,0) -> 17.35 | GP42: =IF(BI42=4,GM42-GX42,0) -> 0 | GR42: 0 | GS42: 3 | GT42: 0 | GV42: =ROUND((GT42),6) -> 0 | GW42: 1 | GX42: =ROUND(HC42*I42,2) -> 0 | HA42: 0 | HB42: 0 | HC42: =GV42*GW42 -> 0 | HS42: 0 | IK42: 0
A43: 17 | B43: 1 | C43: =ROW(SmtRes!A58) -> 58 | D43: =ROW(EtalonRes!A70) -> 70 | E43: 8 | F43: 4.10-118-12 | G43: Установка для трубных проводок коробки оконечной / демонтаж фильтра оконечного | H43: 100 шт. | I43: =ROUND(7/100,9) -> 0.07 | J43: 0 | K43: =ROUND(7/100,9) -> 0.07 | O43: =ROUND(CP43,2) -> 414.17 | P43: =ROUND((ROUND((AC43*AW43*I43),2)*BC43),2) -> 0 | Q43: =(ROUND((ROUND(((((ET43*1.2)*0.3))*AV43*I43),2)*BB43),2)+ROUND((ROUND(((AE43-(((EU43*1.2)*0.3)))*AV43*I43),2)*BS43),2)) -> 0 | R43: =(ROUND((ROUND(((((EU43*1.2)*0.3))*AV43*I43),2)*BS43),2)+ROUND((ROUND(((AE43-(((EU43*1.2)*0.3)))*AV43*I43),2)*BS43),2)) -> 0 | S43: =ROUND((ROUND((AF43*AV43*I43),2)*BA43),2) -> 414.17 | T43: =ROUND(CU43*I43,2) -> 0 | U43: =CV43*I43 -> 0.6332256 | V43: =CW43*I43 -> 0 | W43: =ROUND(CX43*I43,2) -> 0 | X43: =(ROUND((((S43+ROUND((ROUND(((((EU43*1.2)*0.3))*AV43*I43),2)*BS43),2))*AT43)/100),2)+ROUND(((ROUND((ROUND(((AE43-(((EU43*1.2)*0.3)))*AV43*I43),2)*BS43),2)*AT43)/100),2)) -> 372.75 | Y43: =(ROUND((((S43+ROUND((ROUND(((((EU43*1.2)*0.3))*AV43*I43),2)*BS43),2))*AU43)/100),2)+ROUND(((ROUND((ROUND(((AE43-(((EU43*1.2)*0.3)))*AV43*I43),2)*BS43),2)*AU43)/100),2)) -> 190.52 | AA43: 57014140 | AB43: =ROUND((AC43+AD43+AF43),6) -> 100.3104 | AC43: =ROUND((((ES43*1)*0)),6) -> 0 | AD43: =ROUND((((((ET43*1.2)*0.3))-(((EU43*1.2)*0.3)))+AE43),6) -> 0 | AE43: =ROUND((((EU43*1.2)*0.3)),6) -> 0 | AF43: =ROUND((((EV43*1.2)*0.3)),6) -> 100.3104 | AG43: =ROUND((AP43),6) -> 0 | AH43: =(((EW43*1.2)*0.3)) -> 8.64 | AI43: =(((EX43*1.2)*0.3)) -> 0 | AJ43: =(AS43) -> 0 | AK43: 364.24 | AL43: 85.6 | AM43: 0 | AN43: 0 | AO43: 278.64 | AP43: 0 | AQ43: 24 | AR43: 0 | AS43: 0 | AT43: 90 | AU43: 46 | AV43: 1.047 | AW43: 1 | AZ43: 1 | BA43: 56.35 | BB43: 1 | BC43: 5.06 | BH43: 0 | BI43: 2 | BJ43: ТСН-2001.4 Доп. 79, Сб. 10, т. 118, поз. 12 | BM43: 68 | BN43: 0 | BO43: 4.10-118-12 | BP43: 1 | BQ43: 40 | BR43: 0 | BS43: 56.35 | BT43: 1 | BU43: 1 | BV43: 1 | BW43: 1 | BX43: 1 | BZ43: 90 | CA43: 46 | CE43: 1566 | CF43: 0 | CG43: 0 | CM43: 0 | CN43: Поправка: Гл.12.Прил.8.п.8. 3_12.00.01.11.001 Наименование: При наличии напряженных и стесненных условий производства работ (стесненность, сложность складирования и транспортной логистики и т.п.) для объектов, расположенных в пределах круговой магистральной системы улиц "Садовое кольцо" города Москвы Поправка: Гл.4.Прил.2.2.п.2.2.29_04.00.01.35.003 Наименование: При демонтаже оборудования, предназначенного в лом | CO43: 0 | CP43: =(P43+Q43+S43) -> 414.17 | CQ43: =ROUND((ROUND((AC43*AW43*1),2)*BC43),2) -> 0 | CR43: =(ROUND((ROUND(((((ET43*1.2)*0.3))*AV43*1),2)*BB43),2)+ROUND((ROUND(((AE43-(((EU43*1.2)*0.3)))*AV43*1),2)*BS43),2)) -> 0 | CS43: =(ROUND((ROUND(((((EU43*1.2)*0.3))*AV43*1),2)*BS43),2)+ROUND((ROUND(((AE43-(((EU43*1.2)*0.3)))*AV43*1),2)*BS43),2)) -> 0 | CT43: =ROUND((ROUND((AF43*AV43*1),2)*BA43),2) -> 5917.88 | CU43: =AG43 -> 0 | CV43: =(AH43*AV43) -> 9.04608 | CW43: =AI43 -> 0 | CX43: =AJ43 -> 0 | CY43: =(ROUND((((S43+ROUND((ROUND(((((EU43*1.2)*0.3))*AV43*1),2)*BS43),2))*AT43)/100),2)+ROUND(((ROUND((ROUND(((AE43-(((EU43*1.2)*0.3)))*AV43*1),2)*BS43),2)*AT43)/100),2)) -> 372.75 | CZ43: =(ROUND((((S43+ROUND((ROUND(((((EU43*1.2)*0.3))*AV43*1),2)*BS43),2))*AU43)/100),2)+ROUND(((ROUND((ROUND(((AE43-(((EU43*1.2)*0.3)))*AV43*1),2)*BS43),2)*AU43)/100),2)) -> 190.52 | DB43: 31 | DD43: *1)*0 | DE43: *1,2)*0,3 | DF43: *1,2)*0,3 | DG43: *1,2)*0,3 | DI43: *1,2)*0,3 | DJ43: *1,2)*0,3 | DN43: 0 | DO43: 0 | DP43: 1 | DQ43: 1 | DU43: 1010 | DV43: 100 шт. | DW43: 100 шт. | DX43: 100 | EE43: 57042958 | EF43: 40 | EG43: Монтаж оборудования | EH43: 0 | EJ43: 2 | EK43: 68 | EL43: ТСН-2001.4-10. Прокладка и монтаж сетей связи | EM43: ТСН-2001.4-10-1 | EO43: Поправка: Гл.12.Прил.8.п.8. 3_12.00.01.11.001 Поправка: Гл.4.Прил.2.2.п.2.2.29_04.00.01.35.003 | EQ43: 0 | ER43: 364.24 | ES43: 85.6 | ET43: 0 | EU43: 0 | EV43: 278.64 | EW43: 24 | EX43: 0 | EY43: 0 | FQ43: 0 | FR43: 0 | FS43: 0 | FX43: 90 | FY43: 46 | GD43: 1 | GF43: 990274235 | GG43: 2 | GH43: 1 | GI43: 2 | GJ43: 0 | GK43: 0 | GL43: =ROUND(IF(AND(BH43=3,BI43=3,FS43<>0),P43,0),2) -> 0 | GM43: =ROUND(O43+X43+Y43,2)+GX43 -> 977.44 | GN43: =IF(OR(BI43=0,BI43=1),GM43-GX43,0) -> 0 | GO43: =IF(BI43=2,GM43-GX43,0) -> 977.44 | GP43: =IF(BI43=4,GM43-GX43,0) -> 0 | GR43: 0 | GS43: 3 | GT43: 0 | GV43: =ROUND((GT43),6) -> 0 | GW43: 1 | GX43: =ROUND(HC43*I43,2) -> 0 | HA43: 0 | HB43: 0 | HC43: =GV43*GW43 -> 0 | HS43: 0 | IK43: 0
A44: 17 | B44: 1 | C44: =ROW(SmtRes!A59) -> 59 | D44: =ROW(EtalonRes!A71) -> 71 | F44: 6.67-6-1 | G44: Демонтаж кабеля | H44: 100 м | I44: =ROUND((4500+50)/100,9) -> 45.5 | J44: 0 | K44: =ROUND((4500+50)/100,9) -> 45.5 | O44: =ROUND(CP44,2) -> 5632.01 | P44: =ROUND((ROUND((AC44*AW44*I44),2)*BC44),2) -> 0 | Q44: =(ROUND((ROUND((((ET44*1.2))*AV44*I44),2)*BB44),2)+ROUND((ROUND(((AE44-((EU44*1.2)))*AV44*I44),2)*BS44),2)) -> 0 | R44: =(ROUND((ROUND((((EU44*1.2))*AV44*I44),2)*BS44),2)+ROUND((ROUND(((AE44-((EU44*1.2)))*AV44*I44),2)*BS44),2)) -> 0 | S44: =ROUND((ROUND((AF44*AV44*I44),2)*BA44),2) -> 5632.01 | T44: =ROUND(CU44*I44,2) -> 0 | U44: =CV44*I44 -> 551.08217 | V44: =CW44*I44 -> 0 | W44: =ROUND(CX44*I44,2) -> 0 | X44: =(ROUND((((S44+ROUND((ROUND((((EU44*1.2))*AV44*I44),2)*BS44),2))*AT44)/100),2)+ROUND(((ROUND((ROUND(((AE44-((EU44*1.2)))*AV44*I44),2)*BS44),2)*AT44)/100),2)) -> 5125.13 | Y44: =(ROUND((((S44+ROUND((ROUND((((EU44*1.2))*AV44*I44),2)*BS44),2))*AU44)/100),2)+ROUND(((ROUND((ROUND(((AE44-((EU44*1.2)))*AV44*I44),2)*BS44),2)*AU44)/100),2)) -> 2703.36 | AA44: -1 | AB44: =ROUND((AC44+AD44+AF44),6) -> 118.224 | AC44: =ROUND(((ES44*1)),6) -> 0 | AD44: =ROUND(((((ET44*1.2))-((EU44*1.2)))+AE44),6) -> 0 | AE44: =ROUND(((EU44*1.2)),6) -> 0 | AF44: =ROUND(((EV44*1.2)),6) -> 118.224 | AG44: =ROUND((AP44),6) -> 0 | AH44: =((EW44*1.2)) -> 11.568 | AI44: =((EX44*1.2)) -> 0 | AJ44: =(AS44) -> 0 | AK44: 98.52 | AL44: 0 | AM44: 0 | AN44: 0 | AO44: 98.52 | AP44: 0 | AQ44: 9.64 | AR44: 0 | AS44: 0 | AT44: 91 | AU44: 48 | AV44: 1.047 | AW44: 1 | AZ44: 1 | BA44: 1 | BB44: 1 | BC44: 1 | BH44: 0 | BI44: 1 | BJ44: ТСН-2001.6. Доп. 1-42. Сб. 67, т. 6, поз. 1 | BM44: 106 | BN44: 0 | BO44: 6.67-6-1 | BP44: 1 | BQ44: 60 | BR44: 0 | BS44: 1 | BT44: 1 | BU44: 1 | BV44: 1 | BW44: 1 | BX44: 1 | BZ44: 91 | CA44: 48 | CE44: 1566 | CF44: 0 | CG44: 0 | CM44: 0 | CN44: Поправка: Гл.12.Прил.8.п.8. 3_12.00.01.11.001 Наименование: При наличии напряженных и стесненных условий производства работ (стесненность, сложность складирования и транспортной логистики и т.п.) для объектов, расположенных в пределах круговой магистральной системы улиц "Садовое кольцо" города Москвы | CO44: 0 | CP44: =(P44+Q44+S44) -> 5632.01 | CQ44: =ROUND((ROUND((AC44*AW44*1),2)*BC44),2) -> 0 | CR44: =(ROUND((ROUND((((ET44*1.2))*AV44*1),2)*BB44),2)+ROUND((ROUND(((AE44-((EU44*1.2)))*AV44*1),2)*BS44),2)) -> 0 | CS44: =(ROUND((ROUND((((EU44*1.2))*AV44*1),2)*BS44),2)+ROUND((ROUND(((AE44-((EU44*1.2)))*AV44*1),2)*BS44),2)) -> 0 | CT44: =ROUND((ROUND((AF44*AV44*1),2)*BA44),2) -> 123.78 | CU44: =AG44 -> 0 | CV44: =(AH44*AV44) -> 12.111696 | CW44: =AI44 -> 0 | CX44: =AJ44 -> 0 | CY44: =(ROUND((((S44+ROUND((ROUND((((EU44*1.2))*AV44*1),2)*BS44),2))*AT44)/100),2)+ROUND(((ROUND((ROUND(((AE44-((EU44*1.2)))*AV44*1),2)*BS44),2)*AT44)/100),2)) -> 5125.13 | CZ44: =(ROUND((((S44+ROUND((ROUND((((EU44*1.2))*AV44*1),2)*BS44),2))*AU44)/100),2)+ROUND(((ROUND((ROUND(((AE44-((EU44*1.2)))*AV44*1),2)*BS44),2)*AU44)/100),2)) -> 2703.36 | DB44: 33 | DD44: *1 | DE44: *1,2 | DF44: *1,2 | DG44: *1,2 | DI44: *1,2 | DJ44: *1,2 | DN44: 0 | DO44: 0 | DP44: 1 | DQ44: 1 | DU44: 1003 | DV44: 100 м | DW44: 100 м | DX44: 100 | EE44: 57042996 | EF44: 60 | EG44: Ремонтно-строительные работы | EH44: 0 | EJ44: 1 | EK44: 106 | EL44: ТСН-2001.6-67. Электромонтажные работы | EM44: ТСН-2001.6-67-1 | EO44: Поправка: Гл.12.Прил.8.п.8. 3_12.00.01.11.001 | EQ44: 1024 | ER44: 98.52 | ES44: 0 | ET44: 0 | EU44: 0 | EV44: 98.52 | EW44: 9.64 | EX44: 0 | EY44: 0 | FQ44: 0 | FR44: 0 | FS44: 0 | FX44: 91 | FY44: 48 | GD44: 1 | GF44: 1114236003 | GG44: 2 | GH44: 1 | GI44: 2 | GJ44: 0 | GK44: 0 | GL44: =ROUND(IF(AND(BH44=3,BI44=3,FS44<>0),P44,0),2) -> 0 | GM44: =ROUND(O44+X44+Y44,2)+GX44 -> 13460.5 | GN44: =IF(OR(BI44=0,BI44=1),GM44-GX44,0) -> 13460.5 | GO44: =IF(BI44=2,GM44-GX44,0) -> 0 | GP44: =IF(BI44=4,GM44-GX44,0) -> 0 | GR44: 0 | GS44: 3 | GT44: 0 | GV44: =ROUND((GT44),6) -> 0 | GW44: 1 | GX44: =ROUND(HC44*I44,2) -> 0 | HA44: 0 | HB44: 0 | HC44: =GV44*GW44 -> 0 | HS44: 0 | IK44: 0
A45: 17 | B45: 1 | C45: =ROW(SmtRes!A60) -> 60 | D45: =ROW(EtalonRes!A72) -> 72 | F45: 6.67-6-1 | G45: Демонтаж кабеля | H45: 100 м | I45: =ROUND((4500+50)/100,9) -> 45.5 | J45: 0 | K45: =ROUND((4500+50)/100,9) -> 45.5 | O45: =ROUND(CP45,2) -> 317363.76 | P45: =ROUND((ROUND((AC45*AW45*I45),2)*BC45),2) -> 0 | Q45: =(ROUND((ROUND((((ET45*1.2))*AV45*I45),2)*BB45),2)+ROUND((ROUND(((AE45-((EU45*1.2)))*AV45*I45),2)*BS45),2)) -> 0 | R45: =(ROUND((ROUND((((EU45*1.2))*AV45*I45),2)*BS45),2)+ROUND((ROUND(((AE45-((EU45*1.2)))*AV45*I45),2)*BS45),2)) -> 0 | S45: =ROUND((ROUND((AF45*AV45*I45),2)*BA45),2) -> 317363.76 | T45: =ROUND(CU45*I45,2) -> 0 | U45: =CV45*I45 -> 551.08217 | V45: =CW45*I45 -> 0 | W45: =ROUND(CX45*I45,2) -> 0 | X45: =(ROUND((((S45+ROUND((ROUND((((EU45*1.2))*AV45*I45),2)*BS45),2))*AT45)/100),2)+ROUND(((ROUND((ROUND(((AE45-((EU45*1.2)))*AV45*I45),2)*BS45),2)*AT45)/100),2)) -> 288801.02 | Y45: =(ROUND((((S45+ROUND((ROUND((((EU45*1.2))*AV45*I45),2)*BS45),2))*AU45)/100),2)+ROUND(((ROUND((ROUND(((AE45-((EU45*1.2)))*AV45*I45),2)*BS45),2)*AU45)/100),2)) -> 152334.6 | AA45: -1 | AB45: =ROUND((AC45+AD45+AF45),6) -> 118.224 | AC45: =ROUND(((ES45*1)),6) -> 0 | AD45: =ROUND(((((ET45*1.2))-((EU45*1.2)))+AE45),6) -> 0 | AE45: =ROUND(((EU45*1.2)),6) -> 0 | AF45: =ROUND(((EV45*1.2)),6) -> 118.224 | AG45: =ROUND((AP45),6) -> 0 | AH45: =((EW45*1.2)) -> 11.568 | AI45: =((EX45*1.2)) -> 0 | AJ45: =(AS45) -> 0 | AK45: 98.52 | AL45: 0 | AM45: 0 | AN45: 0 | AO45: 98.52 | AP45: 0 | AQ45: 9.64 | AR45: 0 | AS45: 0 | AT45: 91 | AU45: 48 | AV45: 1.047 | AW45: 1 | AZ45: 1 | BA45: 56.35 | BB45: 1 | BC45: 1 | BH45: 0 | BI45: 1 | BJ45: ТСН-2001.6. Доп. 1-42. Сб. 67, т. 6, поз. 1 | BM45: 106 | BN45: 0 | BO45: 6.67-6-1 | BP45: 1 | BQ45: 60 | BR45: 0 | BS45: 56.35 | BT45: 1 | BU45: 1 | BV45: 1 | BW45: 1 | BX45: 1 | BZ45: 91 | CA45: 48 | CE45: 1566 | CF45: 0 | CG45: 0 | CM45: 0 | CN45: Поправка: Гл.12.Прил.8.п.8. 3_12.00.01.11.001 Наименование: При наличии напряженных и стесненных условий производства работ (стесненность, сложность складирования и транспортной логистики и т.п.) для объектов, расположенных в пределах круговой магистральной системы улиц "Садовое кольцо" города Москвы | CO45: 0 | CP45: =(P45+Q45+S45) -> 317363.76 | CQ45: =ROUND((ROUND((AC45*AW45*1),2)*BC45),2) -> 0 | CR45: =(ROUND((ROUND((((ET45*1.2))*AV45*1),2)*BB45),2)+ROUND((ROUND(((AE45-((EU45*1.2)))*AV45*1),2)*BS45),2)) -> 0 | CS45: =(ROUND((ROUND((((EU45*1.2))*AV45*1),2)*BS45),2)+ROUND((ROUND(((AE45-((EU45*1.2)))*AV45*1),2)*BS45),2)) -> 0 | CT45: =ROUND((ROUND((AF45*AV45*1),2)*BA45),2) -> 6975 | CU45: =AG45 -> 0 | CV45: =(AH45*AV45) -> 12.111696 | CW45: =AI45 -> 0 | CX45: =AJ45 -> 0 | CY45: =(ROUND((((S45+ROUND((ROUND((((EU45*1.2))*AV45*1),2)*BS45),2))*AT45)/100),2)+ROUND(((ROUND((ROUND(((AE45-((EU45*1.2)))*AV45*1),2)*BS45),2)*AT45)/100),2)) -> 288801.02 | CZ45: =(ROUND((((S45+ROUND((ROUND((((EU45*1.2))*AV45*1),2)*BS45),2))*AU45)/100),2)+ROUND(((ROUND((ROUND(((AE45-((EU45*1.2)))*AV45*1),2)*BS45),2)*AU45)/100),2)) -> 152334.6 | DB45: 34 | DD45: *1 | DE45: *1,2 | DF45: *1,2 | DG45: *1,2 | DI45: *1,2 | DJ45: *1,2 | DN45: 0 | DO45: 0 | DP45: 1 | DQ45: 1 | DU45: 1003 | DV45: 100 м | DW45: 100 м | DX45: 100 | EE45: 57042996 | EF45: 60 | EG45: Ремонтно-строительные работы | EH45: 0 | EJ45: 1 | EK45: 106 | EL45: ТСН-2001.6-67. Электромонтажные работы | EM45: ТСН-2001.6-67-1 | EO45: Поправка: Гл.12.Прил.8.п.8. 3_12.00.01.11.001 | EQ45: 1024 | ER45: 98.52 | ES45: 0 | ET45: 0 | EU45: 0 | EV45: 98.52 | EW45: 9.64 | EX45: 0 | EY45: 0 | FQ45: 0 | FR45: 0 | FS45: 0 | FX45: 91 | FY45: 48 | GD45: 1 | GF45: 1114236003 | GG45: 2 | GH45: 1 | GI45: 2 | GJ45: 0 | GK45: 0 | GL45: =ROUND(IF(AND(BH45=3,BI45=3,FS45<>0),P45,0),2) -> 0 | GM45: =ROUND(O45+X45+Y45,2)+GX45 -> 758499.38 | GN45: =IF(OR(BI45=0,BI45=1),GM45-GX45,0) -> 758499.38 | GO45: =IF(BI45=2,GM45-GX45,0) -> 0 | GP45: =IF(BI45=4,GM45-GX45,0) -> 0 | GR45: 0 | GS45: 3 | GT45: 0 | GV45: =ROUND((GT45),6) -> 0 | GW45: 1 | GX45: =ROUND(HC45*I45,2) -> 0 | HA45: 0 | HB45: 0 | HC45: =GV45*GW45 -> 0 | HS45: 0 | IK45: 0
A46: 17 | B46: 1 | C46: =ROW(SmtRes!A66) -> 66 | D46: =ROW(EtalonRes!A82) -> 82 | E46: 9 | F46: 4.10-185-8 | G46: Прокладка кабеля связи огнестойкого в трубах гофрированных с использованием скобы СМД: по бетонным поверхностям | H46: 100 м | I46: =ROUND((4500+50)/100,9) -> 45.5 | J46: 0 | K46: =ROUND((4500+50)/100,9) -> 45.5 | O46: =ROUND(CP46,2) -> 7175.33 | P46: =ROUND((ROUND((AC46*AW46*I46),2)*BC46),2) -> 0 | Q46: =(ROUND((ROUND(((((ET46*1.2)*0.3))*AV46*I46),2)*BB46),2)+ROUND((ROUND(((AE46-(((EU46*1.2)*0.3)))*AV46*I46),2)*BS46),2)) -> 119.88 | R46: =(ROUND((ROUND(((((EU46*1.2)*0.3))*AV46*I46),2)*BS46),2)+ROUND((ROUND(((AE46-(((EU46*1.2)*0.3)))*AV46*I46),2)*BS46),2)) -> 0 | S46: =ROUND((ROUND((AF46*AV46*I46),2)*BA46),2) -> 7055.45 | T46: =ROUND(CU46*I46,2) -> 0 | U46: =CV46*I46 -> 593.55665 | V46: =CW46*I46 -> 0 | W46: =ROUND(CX46*I46,2) -> 0 | X46: =(ROUND((((S46+ROUND((ROUND(((((EU46*1.2)*0.3))*AV46*I46),2)*BS46),2))*AT46)/100),2)+ROUND(((ROUND((ROUND(((AE46-(((EU46*1.2)*0.3)))*AV46*I46),2)*BS46),2)*AT46)/100),2)) -> 6349.91 | Y46: =(ROUND((((S46+ROUND((ROUND(((((EU46*1.2)*0.3))*AV46*I46),2)*BS46),2))*AU46)/100),2)+ROUND(((ROUND((ROUND(((AE46-(((EU46*1.2)*0.3)))*AV46*I46),2)*BS46),2)*AU46)/100),2)) -> 3245.51 | AA46: 57014138 | AB46: =ROUND((AC46+AD46+AF46),6) -> 150.6204 | AC46: =ROUND((((ES46*1)*0)),6) -> 0 | AD46: =ROUND((((((ET46*1.2)*0.3))-(((EU46*1.2)*0.3)))+AE46),6) -> 2.5164 | AE46: =ROUND((((EU46*1.2)*0.3)),6) -> 0 | AF46: =ROUND((((EV46*1.2)*0.3)),6) -> 148.104 | AG46: =ROUND((AP46),6) -> 0 | AH46: =(((EW46*1.2)*0.3)) -> 12.4596 | AI46: =(((EX46*1.2)*0.3)) -> 0 | AJ46: =(AS46) -> 0 | AK46: 441.78 | AL46: 23.39 | AM46: 6.99 | AN46: 0 | AO46: 411.4 | AP46: 0 | AQ46: 34.61 | AR46: 0 | AS46: 0 | AT46: 90 | AU46: 46 | AV46: 1.047 | AW46: 1 | AZ46: 1 | BA46: 1 | BB46: 1 | BC46: 1 | BH46: 0 | BI46: 2 | BJ46: ТСН-2001.4 Доп. 80, Сб. 10, т. 185, поз. 8 | BM46: 68 | BN46: 0 | BO46: 4.10-185-8 | BP46: 1 | BQ46: 40 | BR46: 0 | BS46: 1 | BT46: 1 | BU46: 1 | BV46: 1 | BW46: 1 | BX46: 1 | BZ46: 90 | CA46: 46 | CE46: 1566 | CF46: 0 | CG46: 0 | CM46: 0 | CN46: Поправка: Гл.12.Прил.8.п.8. 3_12.00.01.11.001 Наименование: При наличии напряженных и стесненных условий производства работ (стесненность, сложность складирования и транспортной логистики и т.п.) для объектов, расположенных в пределах круговой магистральной системы улиц "Садовое кольцо" города Москвы Поправка: Гл.4.Прил.2.2.п.2.2.29_04.00.01.35.003 Наименование: При демонтаже оборудования, предназначенного в лом | CO46: 0 | CP46: =(P46+Q46+S46) -> 7175.33 | CQ46: =ROUND((ROUND((AC46*AW46*1),2)*BC46),2) -> 0 | CR46: =(ROUND((ROUND(((((ET46*1.2)*0.3))*AV46*1),2)*BB46),2)+ROUND((ROUND(((AE46-(((EU46*1.2)*0.3)))*AV46*1),2)*BS46),2)) -> 2.63 | CS46: =(ROUND((ROUND(((((EU46*1.2)*0.3))*AV46*1),2)*BS46),2)+ROUND((ROUND(((AE46-(((EU46*1.2)*0.3)))*AV46*1),2)*BS46),2)) -> 0 | CT46: =ROUND((ROUND((AF46*AV46*1),2)*BA46),2) -> 155.06 | CU46: =AG46 -> 0 | CV46: =(AH46*AV46) -> 13.045201 | CW46: =AI46 -> 0 | CX46: =AJ46 -> 0 | CY46: =(ROUND((((S46+ROUND((ROUND(((((EU46*1.2)*0.3))*AV46*1),2)*BS46),2))*AT46)/100),2)+ROUND(((ROUND((ROUND(((AE46-(((EU46*1.2)*0.3)))*AV46*1),2)*BS46),2)*AT46)/100),2)) -> 6349.91 | CZ46: =(ROUND((((S46+ROUND((ROUND(((((EU46*1.2)*0.3))*AV46*1),2)*BS46),2))*AU46)/100),2)+ROUND(((ROUND((ROUND(((AE46-(((EU46*1.2)*0.3)))*AV46*1),2)*BS46),2)*AU46)/100),2)) -> 3245.51 | DB46: 35 | DD46: *1)*0 | DE46: *1,2)*0,3 | DF46: *1,2)*0,3 | DG46: *1,2)*0,3 | DI46: *1,2)*0,3 | DJ46: *1,2)*0,3 | DN46: 0 | DO46: 0 | DP46: 1 | DQ46: 1 | DU46: 1003 | DV46: 100 м | DW46: 100 м | DX46: 100 | EE46: 57042958 | EF46: 40 | EG46: Монтаж оборудования | EH46: 0 | EJ46: 2 | EK46: 68 | EL46: ТСН-2001.4-10. Прокладка и монтаж сетей связи | EM46: ТСН-2001.4-10-1 | EO46: Поправка: Гл.12.Прил.8.п.8. 3_12.00.01.11.001 Поправка: Гл.4.Прил.2.2.п.2.2.29_04.00.01.35.003 | EQ46: 0 | ER46: 441.78 | ES46: 23.39 | ET46: 6.99 | EU46: 0 | EV46: 411.4 | EW46: 34.61 | EX46: 0 | EY46: 0 | FQ46: 0 | FR46: 0 | FS46: 0 | FX46: 90 | FY46: 46 | GD46: 1 | GF46: -63843540 | GG46: 2 | GH46: 1 | GI46: 2 | GJ46: 0 | GK46: 0 | GL46: =ROUND(IF(AND(BH46=3,BI46=3,FS46<>0),P46,0),2) -> 0 | GM46: =ROUND(O46+X46+Y46,2)+GX46 -> 16770.75 | GN46: =IF(OR(BI46=0,BI46=1),GM46-GX46,0) -> 0 | GO46: =IF(BI46=2,GM46-GX46,0) -> 16770.75 | GP46: =IF(BI46=4,GM46-GX46,0) -> 0 | GR46: 0 | GS46: 3 | GT46: 0 | GV46: =ROUND((GT46),6) -> 0 | GW46: 1 | GX46: =ROUND(HC46*I46,2) -> 0 | HA46: 0 | HB46: 0 | HC46: =GV46*GW46 -> 0 | HS46: 0 | IK46: 0
A47: 17 | B47: 1 | C47: =ROW(SmtRes!A72) -> 72 | D47: =ROW(EtalonRes!A92) -> 92 | E47: 9 | F47: 4.10-185-8 | G47: Прокладка кабеля связи огнестойкого в трубах гофрированных с использованием скобы СМД: по бетонным поверхностям | H47: 100 м | I47: =ROUND((4500+50)/100,9) -> 45.5 | J47: 0 | K47: =ROUND((4500+50)/100,9) -> 45.5 | O47: =ROUND(CP47,2) -> 398725.46 | P47: =ROUND((ROUND((AC47*AW47*I47),2)*BC47),2) -> 0 | Q47: =(ROUND((ROUND(((((ET47*1.2)*0.3))*AV47*I47),2)*BB47),2)+ROUND((ROUND(((AE47-(((EU47*1.2)*0.3)))*AV47*I47),2)*BS47),2)) -> 1150.85 | R47: =(ROUND((ROUND(((((EU47*1.2)*0.3))*AV47*I47),2)*BS47),2)+ROUND((ROUND(((AE47-(((EU47*1.2)*0.3)))*AV47*I47),2)*BS47),2)) -> 0 | S47: =ROUND((ROUND((AF47*AV47*I47),2)*BA47),2) -> 397574.61 | T47: =ROUND(CU47*I47,2) -> 0 | U47: =CV47*I47 -> 593.55665 | V47: =CW47*I47 -> 0 | W47: =ROUND(CX47*I47,2) -> 0 | X47: =(ROUND((((S47+ROUND((ROUND(((((EU47*1.2)*0.3))*AV47*I47),2)*BS47),2))*AT47)/100),2)+ROUND(((ROUND((ROUND(((AE47-(((EU47*1.2)*0.3)))*AV47*I47),2)*BS47),2)*AT47)/100),2)) -> 357817.15 | Y47: =(ROUND((((S47+ROUND((ROUND(((((EU47*1.2)*0.3))*AV47*I47),2)*BS47),2))*AU47)/100),2)+ROUND(((ROUND((ROUND(((AE47-(((EU47*1.2)*0.3)))*AV47*I47),2)*BS47),2)*AU47)/100),2)) -> 182884.32 | AA47: 57014140 | AB47: =ROUND((AC47+AD47+AF47),6) -> 150.6204 | AC47: =ROUND((((ES47*1)*0)),6) -> 0 | AD47: =ROUND((((((ET47*1.2)*0.3))-(((EU47*1.2)*0.3)))+AE47),6) -> 2.5164 | AE47: =ROUND((((EU47*1.2)*0.3)),6) -> 0 | AF47: =ROUND((((EV47*1.2)*0.3)),6) -> 148.104 | AG47: =ROUND((AP47),6) -> 0 | AH47: =(((EW47*1.2)*0.3)) -> 12.4596 | AI47: =(((EX47*1.2)*0.3)) -> 0 | AJ47: =(AS47) -> 0 | AK47: 441.78 | AL47: 23.39 | AM47: 6.99 | AN47: 0 | AO47: 411.4 | AP47: 0 | AQ47: 34.61 | AR47: 0 | AS47: 0 | AT47: 90 | AU47: 46 | AV47: 1.047 | AW47: 1 | AZ47: 1 | BA47: 56.35 | BB47: 9.6 | BC47: 7.41 | BH47: 0 | BI47: 2 | BJ47: ТСН-2001.4 Доп. 80, Сб. 10, т. 185, поз. 8 | BM47: 68 | BN47: 0 | BO47: 4.10-185-8 | BP47: 1 | BQ47: 40 | BR47: 0 | BS47: 56.35 | BT47: 1 | BU47: 1 | BV47: 1 | BW47: 1 | BX47: 1 | BZ47: 90 | CA47: 46 | CE47: 1566 | CF47: 0 | CG47: 0 | CM47: 0 | CN47: Поправка: Гл.12.Прил.8.п.8. 3_12.00.01.11.001 Наименование: При наличии напряженных и стесненных условий производства работ (стесненность, сложность складирования и транспортной логистики и т.п.) для объектов, расположенных в пределах круговой магистральной системы улиц "Садовое кольцо" города Москвы Поправка: Гл.4.Прил.2.2.п.2.2.29_04.00.01.35.003 Наименование: При демонтаже оборудования, предназначенного в лом | CO47: 0 | CP47: =(P47+Q47+S47) -> 398725.46 | CQ47: =ROUND((ROUND((AC47*AW47*1),2)*BC47),2) -> 0 | CR47: =(ROUND((ROUND(((((ET47*1.2)*0.3))*AV47*1),2)*BB47),2)+ROUND((ROUND(((AE47-(((EU47*1.2)*0.3)))*AV47*1),2)*BS47),2)) -> 25.25 | CS47: =(ROUND((ROUND(((((EU47*1.2)*0.3))*AV47*1),2)*BS47),2)+ROUND((ROUND(((AE47-(((EU47*1.2)*0.3)))*AV47*1),2)*BS47),2)) -> 0 | CT47: =ROUND((ROUND((AF47*AV47*1),2)*BA47),2) -> 8737.63 | CU47: =AG47 -> 0 | CV47: =(AH47*AV47) -> 13.045201 | CW47: =AI47 -> 0 | CX47: =AJ47 -> 0 | CY47: =(ROUND((((S47+ROUND((ROUND(((((EU47*1.2)*0.3))*AV47*1),2)*BS47),2))*AT47)/100),2)+ROUND(((ROUND((ROUND(((AE47-(((EU47*1.2)*0.3)))*AV47*1),2)*BS47),2)*AT47)/100),2)) -> 357817.15 | CZ47: =(ROUND((((S47+ROUND((ROUND(((((EU47*1.2)*0.3))*AV47*1),2)*BS47),2))*AU47)/100),2)+ROUND(((ROUND((ROUND(((AE47-(((EU47*1.2)*0.3)))*AV47*1),2)*BS47),2)*AU47)/100),2)) -> 182884.32 | DB47: 37 | DD47: *1)*0 | DE47: *1,2)*0,3 | DF47: *1,2)*0,3 | DG47: *1,2)*0,3 | DI47: *1,2)*0,3 | DJ47: *1,2)*0,3 | DN47: 0 | DO47: 0 | DP47: 1 | DQ47: 1 | DU47: 1003 | DV47: 100 м | DW47: 100 м | DX47: 100 | EE47: 57042958 | EF47: 40 | EG47: Монтаж оборудования | EH47: 0 | EJ47: 2 | EK47: 68 | EL47: ТСН-2001.4-10. Прокладка и монтаж сетей связи | EM47: ТСН-2001.4-10-1 | EO47: Поправка: Гл.12.Прил.8.п.8. 3_12.00.01.11.001 Поправка: Гл.4.Прил.2.2.п.2.2.29_04.00.01.35.003 | EQ47: 0 | ER47: 441.78 | ES47: 23.39 | ET47: 6.99 | EU47: 0 | EV47: 411.4 | EW47: 34.61 | EX47: 0 | EY47: 0 | FQ47: 0 | FR47: 0 | FS47: 0 | FX47: 90 | FY47: 46 | GD47: 1 | GF47: -63843540 | GG47: 2 | GH47: 1 | GI47: 2 | GJ47: 0 | GK47: 0 | GL47: =ROUND(IF(AND(BH47=3,BI47=3,FS47<>0),P47,0),2) -> 0 | GM47: =ROUND(O47+X47+Y47,2)+GX47 -> 939426.93 | GN47: =IF(OR(BI47=0,BI47=1),GM47-GX47,0) -> 0 | GO47: =IF(BI47=2,GM47-GX47,0) -> 939426.93 | GP47: =IF(BI47=4,GM47-GX47,0) -> 0 | GR47: 0 | GS47: 3 | GT47: 0 | GV47: =ROUND((GT47),6) -> 0 | GW47: 1 | GX47: =ROUND(HC47*I47,2) -> 0 | HA47: 0 | HB47: 0 | HC47: =GV47*GW47 -> 0 | HS47: 0 | IK47: 0
A48: 17 | B48: 1 | C48: =ROW(SmtRes!A74) -> 74 | D48: =ROW(EtalonRes!A94) -> 94 | F48: 6.67-5-12 | G48: Демонтаж трубных проводок, трубы в борозде диаметром 25 мм / ПВХ | H48: 100 м | I48: =ROUND(4550/100,9) -> 45.5 | J48: 0 | K48: =ROUND(4550/100,9) -> 45.5 | O48: =ROUND(CP48,2) -> 18306.33 | P48: =ROUND((ROUND((AC48*AW48*I48),2)*BC48),2) -> 0 | Q48: =(ROUND((ROUND((((ET48*1.2))*AV48*I48),2)*BB48),2)+ROUND((ROUND(((AE48-((EU48*1.2)))*AV48*I48),2)*BS48),2)) -> 0 | R48: =(ROUND((ROUND((((EU48*1.2))*AV48*I48),2)*BS48),2)+ROUND((ROUND(((AE48-((EU48*1.2)))*AV48*I48),2)*BS48),2)) -> 0 | S48: =ROUND((ROUND((AF48*AV48*I48),2)*BA48),2) -> 18306.33 | T48: =ROUND(CU48*I48,2) -> 0 | U48: =CV48*I48 -> 1740.1391 | V48: =CW48*I48 -> 0 | W48: =ROUND(CX48*I48,2) -> 0 | X48: =(ROUND((((S48+ROUND((ROUND((((EU48*1.2))*AV48*I48),2)*BS48),2))*AT48)/100),2)+ROUND(((ROUND((ROUND(((AE48-((EU48*1.2)))*AV48*I48),2)*BS48),2)*AT48)/100),2)) -> 16658.76 | Y48: =(ROUND((((S48+ROUND((ROUND((((EU48*1.2))*AV48*I48),2)*BS48),2))*AU48)/100),2)+ROUND(((ROUND((ROUND(((AE48-((EU48*1.2)))*AV48*I48),2)*BS48),2)*AU48)/100),2)) -> 8787.04 | AA48: -1 | AB48: =ROUND((AC48+AD48+AF48),6) -> 384.276 | AC48: =ROUND(((ES48*1)),6) -> 0 | AD48: =ROUND(((((ET48*1.2))-((EU48*1.2)))+AE48),6) -> 0 | AE48: =ROUND(((EU48*1.2)),6) -> 0 | AF48: =ROUND(((EV48*1.2)),6) -> 384.276 | AG48: =ROUND((AP48),6) -> 0 | AH48: =((EW48*1.2)) -> 36.528 | AI48: =((EX48*1.2)) -> 0 | AJ48: =(AS48) -> 0 | AK48: 320.23 | AL48: 0 | AM48: 0 | AN48: 0 | AO48: 320.23 | AP48: 0 | AQ48: 30.44 | AR48: 0 | AS48: 0 | AT48: 91 | AU48: 48 | AV48: 1.047 | AW48: 1 | AZ48: 1 | BA48: 1 | BB48: 1 | BC48: 1 | BH48: 0 | BI48: 1 | BJ48: ТСН-2001.6. Доп. 1-42. Сб. 67, т. 5, поз. 12 | BM48: 106 | BN48: 0 | BO48: 6.67-5-12 | BP48: 1 | BQ48: 60 | BR48: 0 | BS48: 1 | BT48: 1 | BU48: 1 | BV48: 1 | BW48: 1 | BX48: 1 | BZ48: 91 | CA48: 48 | CE48: 1566 | CF48: 0 | CG48: 0 | CM48: 0 | CN48: Поправка: Гл.12.Прил.8.п.8. 3_12.00.01.11.001 Наименование: При наличии напряженных и стесненных условий производства работ (стесненность, сложность складирования и транспортной логистики и т.п.) для объектов, расположенных в пределах круговой магистральной системы улиц "Садовое кольцо" города Москвы | CO48: 0 | CP48: =(P48+Q48+S48) -> 18306.33 | CQ48: =ROUND((ROUND((AC48*AW48*1),2)*BC48),2) -> 0 | CR48: =(ROUND((ROUND((((ET48*1.2))*AV48*1),2)*BB48),2)+ROUND((ROUND(((AE48-((EU48*1.2)))*AV48*1),2)*BS48),2)) -> 0 | CS48: =(ROUND((ROUND((((EU48*1.2))*AV48*1),2)*BS48),2)+ROUND((ROUND(((AE48-((EU48*1.2)))*AV48*1),2)*BS48),2)) -> 0 | CT48: =ROUND((ROUND((AF48*AV48*1),2)*BA48),2) -> 402.34 | CU48: =AG48 -> 0 | CV48: =(AH48*AV48) -> 38.244816 | CW48: =AI48 -> 0 | CX48: =AJ48 -> 0 | CY48: =(ROUND((((S48+ROUND((ROUND((((EU48*1.2))*AV48*1),2)*BS48),2))*AT48)/100),2)+ROUND(((ROUND((ROUND(((AE48-((EU48*1.2)))*AV48*1),2)*BS48),2)*AT48)/100),2)) -> 16658.76 | CZ48: =(ROUND((((S48+ROUND((ROUND((((EU48*1.2))*AV48*1),2)*BS48),2))*AU48)/100),2)+ROUND(((ROUND((ROUND(((AE48-((EU48*1.2)))*AV48*1),2)*BS48),2)*AU48)/100),2)) -> 8787.04 | DB48: 39 | DD48: *1 | DE48: *1,2 | DF48: *1,2 | DG48: *1,2 | DI48: *1,2 | DJ48: *1,2 | DN48: 0 | DO48: 0 | DP48: 1 | DQ48: 1 | DU48: 1003 | DV48: 100 м | DW48: 100 м | DX48: 100 | EE48: 57042996 | EF48: 60 | EG48: Ремонтно-строительные работы | EH48: 0 | EJ48: 1 | EK48: 106 | EL48: ТСН-2001.6-67. Электромонтажные работы | EM48: ТСН-2001.6-67-1 | EO48: Поправка: Гл.12.Прил.8.п.8. 3_12.00.01.11.001 | EQ48: 1024 | ER48: 320.23 | ES48: 0 | ET48: 0 | EU48: 0 | EV48: 320.23 | EW48: 30.44 | EX48: 0 | EY48: 0 | FQ48: 0 | FR48: 0 | FS48: 0 | FX48: 91 | FY48: 48 | GD48: 1 | GF48: -1403822920 | GG48: 2 | GH48: 1 | GI48: 2 | GJ48: 0 | GK48: 0 | GL48: =ROUND(IF(AND(BH48=3,BI48=3,FS48<>0),P48,0),2) -> 0 | GM48: =ROUND(O48+X48+Y48,2)+GX48 -> 43752.13 | GN48: =IF(OR(BI48=0,BI48=1),GM48-GX48,0) -> 43752.13 | GO48: =IF(BI48=2,GM48-GX48,0) -> 0 | GP48: =IF(BI48=4,GM48-GX48,0) -> 0 | GR48: 0 | GS48: 3 | GT48: 0 | GV48: =ROUND((GT48),6) -> 0 | GW48: 1 | GX48: =ROUND(HC48*I48,2) -> 0 | HA48: 0 | HB48: 0 | HC48: =GV48*GW48 -> 0 | HS48: 0 | IK48: 0
A49: 17 | B49: 1 | C49: =ROW(SmtRes!A76) -> 76 | D49: =ROW(EtalonRes!A96) -> 96 | F49: 6.67-5-12 | G49: Демонтаж трубных проводок, трубы в борозде диаметром 25 мм / ПВХ | H49: 100 м | I49: =ROUND(4550/100,9) -> 45.5 | J49: 0 | K49: =ROUND(4550/100,9) -> 45.5 | O49: =ROUND(CP49,2) -> 1031561.7 | P49: =ROUND((ROUND((AC49*AW49*I49),2)*BC49),2) -> 0 | Q49: =(ROUND((ROUND((((ET49*1.2))*AV49*I49),2)*BB49),2)+ROUND((ROUND(((AE49-((EU49*1.2)))*AV49*I49),2)*BS49),2)) -> 0 | R49: =(ROUND((ROUND((((EU49*1.2))*AV49*I49),2)*BS49),2)+ROUND((ROUND(((AE49-((EU49*1.2)))*AV49*I49),2)*BS49),2)) -> 0 | S49: =ROUND((ROUND((AF49*AV49*I49),2)*BA49),2) -> 1031561.7 | T49: =ROUND(CU49*I49,2) -> 0 | U49: =CV49*I49 -> 1740.1391 | V49: =CW49*I49 -> 0 | W49: =ROUND(CX49*I49,2) -> 0 | X49: =(ROUND((((S49+ROUND((ROUND((((EU49*1.2))*AV49*I49),2)*BS49),2))*AT49)/100),2)+ROUND(((ROUND((ROUND(((AE49-((EU49*1.2)))*AV49*I49),2)*BS49),2)*AT49)/100),2)) -> 938721.15 | Y49: =(ROUND((((S49+ROUND((ROUND((((EU49*1.2))*AV49*I49),2)*BS49),2))*AU49)/100),2)+ROUND(((ROUND((ROUND(((AE49-((EU49*1.2)))*AV49*I49),2)*BS49),2)*AU49)/100),2)) -> 495149.62 | AA49: -1 | AB49: =ROUND((AC49+AD49+AF49),6) -> 384.276 | AC49: =ROUND(((ES49*1)),6) -> 0 | AD49: =ROUND(((((ET49*1.2))-((EU49*1.2)))+AE49),6) -> 0 | AE49: =ROUND(((EU49*1.2)),6) -> 0 | AF49: =ROUND(((EV49*1.2)),6) -> 384.276 | AG49: =ROUND((AP49),6) -> 0 | AH49: =((EW49*1.2)) -> 36.528 | AI49: =((EX49*1.2)) -> 0 | AJ49: =(AS49) -> 0 | AK49: 320.23 | AL49: 0 | AM49: 0 | AN49: 0 | AO49: 320.23 | AP49: 0 | AQ49: 30.44 | AR49: 0 | AS49: 0 | AT49: 91 | AU49: 48 | AV49: 1.047 | AW49: 1 | AZ49: 1 | BA49: 56.35 | BB49: 1 | BC49: 1 | BH49: 0 | BI49: 1 | BJ49: ТСН-2001.6. Доп. 1-42. Сб. 67, т. 5, поз. 12 | BM49: 106 | BN49: 0 | BO49: 6.67-5-12 | BP49: 1 | BQ49: 60 | BR49: 0 | BS49: 56.35 | BT49: 1 | BU49: 1 | BV49: 1 | BW49: 1 | BX49: 1 | BZ49: 91 | CA49: 48 | CE49: 1566 | CF49: 0 | CG49: 0 | CM49: 0 | CN49: Поправка: Гл.12.Прил.8.п.8. 3_12.00.01.11.001 Наименование: При наличии напряженных и стесненных условий производства работ (стесненность, сложность складирования и транспортной логистики и т.п.) для объектов, расположенных в пределах круговой магистральной системы улиц "Садовое кольцо" города Москвы | CO49: 0 | CP49: =(P49+Q49+S49) -> 1031561.7 | CQ49: =ROUND((ROUND((AC49*AW49*1),2)*BC49),2) -> 0 | CR49: =(ROUND((ROUND((((ET49*1.2))*AV49*1),2)*BB49),2)+ROUND((ROUND(((AE49-((EU49*1.2)))*AV49*1),2)*BS49),2)) -> 0 | CS49: =(ROUND((ROUND((((EU49*1.2))*AV49*1),2)*BS49),2)+ROUND((ROUND(((AE49-((EU49*1.2)))*AV49*1),2)*BS49),2)) -> 0 | CT49: =ROUND((ROUND((AF49*AV49*1),2)*BA49),2) -> 22671.86 | CU49: =AG49 -> 0 | CV49: =(AH49*AV49) -> 38.244816 | CW49: =AI49 -> 0 | CX49: =AJ49 -> 0 | CY49: =(ROUND((((S49+ROUND((ROUND((((EU49*1.2))*AV49*1),2)*BS49),2))*AT49)/100),2)+ROUND(((ROUND((ROUND(((AE49-((EU49*1.2)))*AV49*1),2)*BS49),2)*AT49)/100),2)) -> 938721.15 | CZ49: =(ROUND((((S49+ROUND((ROUND((((EU49*1.2))*AV49*1),2)*BS49),2))*AU49)/100),2)+ROUND(((ROUND((ROUND(((AE49-((EU49*1.2)))*AV49*1),2)*BS49),2)*AU49)/100),2)) -> 495149.62 | DB49: 40 | DD49: *1 | DE49: *1,2 | DF49: *1,2 | DG49: *1,2 | DI49: *1,2 | DJ49: *1,2 | DN49: 0 | DO49: 0 | DP49: 1 | DQ49: 1 | DU49: 1003 | DV49: 100 м | DW49: 100 м | DX49: 100 | EE49: 57042996 | EF49: 60 | EG49: Ремонтно-строительные работы | EH49: 0 | EJ49: 1 | EK49: 106 | EL49: ТСН-2001.6-67. Электромонтажные работы | EM49: ТСН-2001.6-67-1 | EO49: Поправка: Гл.12.Прил.8.п.8. 3_12.00.01.11.001 | EQ49: 1024 | ER49: 320.23 | ES49: 0 | ET49: 0 | EU49: 0 | EV49: 320.23 | EW49: 30.44 | EX49: 0 | EY49: 0 | FQ49: 0 | FR49: 0 | FS49: 0 | FX49: 91 | FY49: 48 | GD49: 1 | GF49: -1403822920 | GG49: 2 | GH49: 1 | GI49: 2 | GJ49: 0 | GK49: 0 | GL49: =ROUND(IF(AND(BH49=3,BI49=3,FS49<>0),P49,0),2) -> 0 | GM49: =ROUND(O49+X49+Y49,2)+GX49 -> 2465432.5 | GN49: =IF(OR(BI49=0,BI49=1),GM49-GX49,0) -> 2465432.5 | GO49: =IF(BI49=2,GM49-GX49,0) -> 0 | GP49: =IF(BI49=4,GM49-GX49,0) -> 0 | GR49: 0 | GS49: 3 | GT49: 0 | GV49: =ROUND((GT49),6) -> 0 | GW49: 1 | GX49: =ROUND(HC49*I49,2) -> 0 | HA49: 0 | HB49: 0 | HC49: =GV49*GW49 -> 0 | HS49: 0 | IK49: 0
A50: 17 | B50: 1 | C50: =ROW(SmtRes!A81) -> 81 | D50: =ROW(EtalonRes!A103) -> 103 | E50: 10 | F50: 3.17-12-1 | G50: Установка вентиляционных решеток площадью в свету до 0,05 м2 / демонтаж защитного кожуха | H50: 100 шт. | I50: =ROUND((6+1+4)/100,9) -> 0.11 | J50: 0 | K50: =ROUND((6+1+4)/100,9) -> 0.11 | O50: =ROUND(CP50,2) -> 32.11 | P50: =ROUND((ROUND((AC50*AW50*I50),2)*BC50),2) -> 0 | Q50: =(ROUND((ROUND(((((ET50*1.2)*0.8))*AV50*I50),2)*BB50),2)+ROUND((ROUND(((AE50-(((EU50*1.2)*0.8)))*AV50*I50),2)*BS50),2)) -> 0.88 | R50: =(ROUND((ROUND(((((EU50*1.2)*0.8))*AV50*I50),2)*BS50),2)+ROUND((ROUND(((AE50-(((EU50*1.2)*0.8)))*AV50*I50),2)*BS50),2)) -> 0.03 | S50: =ROUND((ROUND((AF50*AV50*I50),2)*BA50),2) -> 31.23 | T50: =ROUND(CU50*I50,2) -> 0 | U50: =CV50*I50 -> 2.794345 | V50: =CW50*I50 -> 0 | W50: =ROUND(CX50*I50,2) -> 0 | X50: =(ROUND((((S50+ROUND((ROUND(((((EU50*1.2)*0.8))*AV50*I50),2)*BS50),2))*AT50)/100),2)+ROUND(((ROUND((ROUND(((AE50-(((EU50*1.2)*0.8)))*AV50*I50),2)*BS50),2)*AT50)/100),2)) -> 37.82 | Y50: =(ROUND((((S50+ROUND((ROUND(((((EU50*1.2)*0.8))*AV50*I50),2)*BS50),2))*AU50)/100),2)+ROUND(((ROUND((ROUND(((AE50-(((EU50*1.2)*0.8)))*AV50*I50),2)*BS50),2)*AU50)/100),2)) -> 22.51 | AA50: 57014138 | AB50: =ROUND((AC50+AD50+AF50),6) -> 273.6288 | AC50: =ROUND((((ES50*1)*0)),6) -> 0 | AD50: =ROUND((((((ET50*1.2)*0.8))-(((EU50*1.2)*0.8)))+AE50),6) -> 7.5072 | AE50: =ROUND((((EU50*1.2)*0.8)),6) -> 0.24 | AF50: =ROUND((((EV50*1.2)*0.8)),6) -> 266.1216 | AG50: =ROUND((AP50),6) -> 0 | AH50: =(((EW50*1.2)*0.8)) -> 23.808 | AI50: =(((EX50*1.2)*0.8)) -> 0 | AJ50: =(AS50) -> 0 | AK50: 641.07 | AL50: 356.04 | AM50: 7.82 | AN50: 0.25 | AO50: 277.21 | AP50: 0 | AQ50: 24.8 | AR50: 0 | AS50: 0 | AT50: 121 | AU50: 72 | AV50: 1.067 | AW50: 1 | AZ50: 1 | BA50: 1 | BB50: 1 | BC50: 1 | BH50: 0 | BI50: 1 | BJ50: ТСН-2001.3 Доп. 79, Сб. 17, т. 12, поз. 1 | BM50: 22 | BN50: 0 | BO50: 3.17-12-1 | BP50: 1 | BQ50: 30 | BR50: 0 | BS50: 1 | BT50: 1 | BU50: 1 | BV50: 1 | BW50: 1 | BX50: 1 | BZ50: 121 | CA50: 72 | CE50: 1566 | CF50: 0 | CG50: 0 | CM50: 0 | CN50: Поправка: Гл.12.Прил.8.п.8. 3_12.00.01.11.001 Наименование: При наличии напряженных и стесненных условий производства работ (стесненность, сложность складирования и транспортной логистики и т.п.) для объектов, расположенных в пределах круговой магистральной системы улиц "Садовое кольцо" города Москвы Поправка: Гл.6.Прил.2.2.п.2.2.12_06.00.01.35.002 Наименование: При демонтаже сборных деревянных и пластмассовых конструкций | CO50: 0 | CP50: =(P50+Q50+S50) -> 32.11 | CQ50: =ROUND((ROUND((AC50*AW50*1),2)*BC50),2) -> 0 | CR50: =(ROUND((ROUND(((((ET50*1.2)*0.8))*AV50*1),2)*BB50),2)+ROUND((ROUND(((AE50-(((EU50*1.2)*0.8)))*AV50*1),2)*BS50),2)) -> 8.01 | CS50: =(ROUND((ROUND(((((EU50*1.2)*0.8))*AV50*1),2)*BS50),2)+ROUND((ROUND(((AE50-(((EU50*1.2)*0.8)))*AV50*1),2)*BS50),2)) -> 0.26 | CT50: =ROUND((ROUND((AF50*AV50*1),2)*BA50),2) -> 283.95 | CU50: =AG50 -> 0 | CV50: =(AH50*AV50) -> 25.403136 | CW50: =AI50 -> 0 | CX50: =AJ50 -> 0 | CY50: =(ROUND((((S50+ROUND((ROUND(((((EU50*1.2)*0.8))*AV50*1),2)*BS50),2))*AT50)/100),2)+ROUND(((ROUND((ROUND(((AE50-(((EU50*1.2)*0.8)))*AV50*1),2)*BS50),2)*AT50)/100),2)) -> 38.1 | CZ50: =(ROUND((((S50+ROUND((ROUND(((((EU50*1.2)*0.8))*AV50*1),2)*BS50),2))*AU50)/100),2)+ROUND(((ROUND((ROUND(((AE50-(((EU50*1.2)*0.8)))*AV50*1),2)*BS50),2)*AU50)/100),2)) -> 22.67 | DB50: 41 | DD50: *1)*0 | DE50: *1,2)*0,8 | DF50: *1,2)*0,8 | DG50: *1,2)*0,8 | DI50: *1,2)*0,8 | DJ50: *1,2)*0,8 | DN50: 0 | DO50: 0 | DP50: 1 | DQ50: 1 | DU50: 1010 | DV50: 100 шт. | DW50: 100 шт. | DX50: 100 | EE50: 57042911 | EF50: 30 | EG50: Строительные работы | EH50: 0 | EJ50: 1 | EK50: 22 | EL50: ТСН-2001.3-17. Водопровод и канализация - внутренние устройства | EM50: ТСН-2001.3-17-1 | EO50: Поправка: Гл.12.Прил.8.п.8. 3_12.00.01.11.001 Поправка: Гл.6.Прил.2.2.п.2.2.12_06.00.01.35.002 | EQ50: 0 | ER50: 641.07 | ES50: 356.04 | ET50: 7.82 | EU50: 0.25 | EV50: 277.21 | EW50: 24.8 | EX50: 0 | EY50: 0 | FQ50: 0 | FR50: 0 | FS50: 0 | FX50: 121 | FY50: 72 | GD50: 1 | GF50: 1356411474 | GG50: 2 | GH50: 1 | GI50: 2 | GJ50: 0 | GK50: 0 | GL50: =ROUND(IF(AND(BH50=3,BI50=3,FS50<>0),P50,0),2) -> 0 | GM50: =ROUND(O50+X50+Y50,2)+GX50 -> 92.44 | GN50: =IF(OR(BI50=0,BI50=1),GM50-GX50,0) -> 92.44 | GO50: =IF(BI50=2,GM50-GX50,0) -> 0 | GP50: =IF(BI50=4,GM50-GX50,0) -> 0 | GR50: 0 | GS50: 3 | GT50: 0 | GV50: =ROUND((GT50),6) -> 0 | GW50: 1 | GX50: =ROUND(HC50*I50,2) -> 0 | HA50: 0 | HB50: 0 | HC50: =GV50*GW50 -> 0 | HS50: 0 | IK50: 0
A51: 17 | B51: 1 | C51: =ROW(SmtRes!A86) -> 86 | D51: =ROW(EtalonRes!A110) -> 110 | E51: 10 | F51: 3.17-12-1 | G51: Установка вентиляционных решеток площадью в свету до 0,05 м2 / демонтаж защитного кожуха | H51: 100 шт. | I51: =ROUND((6+1+4)/100,9) -> 0.11 | J51: 0 | K51: =ROUND((6+1+4)/100,9) -> 0.11 | O51: =ROUND(CP51,2) -> 1769.63 | P51: =ROUND((ROUND((AC51*AW51*I51),2)*BC51),2) -> 0 | Q51: =(ROUND((ROUND(((((ET51*1.2)*0.8))*AV51*I51),2)*BB51),2)+ROUND((ROUND(((AE51-(((EU51*1.2)*0.8)))*AV51*I51),2)*BS51),2)) -> 9.82 | R51: =(ROUND((ROUND(((((EU51*1.2)*0.8))*AV51*I51),2)*BS51),2)+ROUND((ROUND(((AE51-(((EU51*1.2)*0.8)))*AV51*I51),2)*BS51),2)) -> 1.69 | S51: =ROUND((ROUND((AF51*AV51*I51),2)*BA51),2) -> 1759.81 | T51: =ROUND(CU51*I51,2) -> 0 | U51: =CV51*I51 -> 2.794345 | V51: =CW51*I51 -> 0 | W51: =ROUND(CX51*I51,2) -> 0 | X51: =(ROUND((((S51+ROUND((ROUND(((((EU51*1.2)*0.8))*AV51*I51),2)*BS51),2))*AT51)/100),2)+ROUND(((ROUND((ROUND(((AE51-(((EU51*1.2)*0.8)))*AV51*I51),2)*BS51),2)*AT51)/100),2)) -> 2131.42 | Y51: =(ROUND((((S51+ROUND((ROUND(((((EU51*1.2)*0.8))*AV51*I51),2)*BS51),2))*AU51)/100),2)+ROUND(((ROUND((ROUND(((AE51-(((EU51*1.2)*0.8)))*AV51*I51),2)*BS51),2)*AU51)/100),2)) -> 1268.28 | AA51: 57014140 | AB51: =ROUND((AC51+AD51+AF51),6) -> 273.6288 | AC51: =ROUND((((ES51*1)*0)),6) -> 0 | AD51: =ROUND((((((ET51*1.2)*0.8))-(((EU51*1.2)*0.8)))+AE51),6) -> 7.5072 | AE51: =ROUND((((EU51*1.2)*0.8)),6) -> 0.24 | AF51: =ROUND((((EV51*1.2)*0.8)),6) -> 266.1216 | AG51: =ROUND((AP51),6) -> 0 | AH51: =(((EW51*1.2)*0.8)) -> 23.808 | AI51: =(((EX51*1.2)*0.8)) -> 0 | AJ51: =(AS51) -> 0 | AK51: 641.07 | AL51: 356.04 | AM51: 7.82 | AN51: 0.25 | AO51: 277.21 | AP51: 0 | AQ51: 24.8 | AR51: 0 | AS51: 0 | AT51: 121 | AU51: 72 | AV51: 1.067 | AW51: 1 | AZ51: 1 | BA51: 56.35 | BB51: 11.16 | BC51: 3.42 | BH51: 0 | BI51: 1 | BJ51: ТСН-2001.3 Доп. 79, Сб. 17, т. 12, поз. 1 | BM51: 22 | BN51: 0 | BO51: 3.17-12-1 | BP51: 1 | BQ51: 30 | BR51: 0 | BS51: 56.35 | BT51: 1 | BU51: 1 | BV51: 1 | BW51: 1 | BX51: 1 | BZ51: 121 | CA51: 72 | CE51: 1566 | CF51: 0 | CG51: 0 | CM51: 0 | CN51: Поправка: Гл.12.Прил.8.п.8. 3_12.00.01.11.001 Наименование: При наличии напряженных и стесненных условий производства работ (стесненность, сложность складирования и транспортной логистики и т.п.) для объектов, расположенных в пределах круговой магистральной системы улиц "Садовое кольцо" города Москвы Поправка: Гл.6.Прил.2.2.п.2.2.12_06.00.01.35.002 Наименование: При демонтаже сборных деревянных и пластмассовых конструкций | CO51: 0 | CP51: =(P51+Q51+S51) -> 1769.63 | CQ51: =ROUND((ROUND((AC51*AW51*1),2)*BC51),2) -> 0 | CR51: =(ROUND((ROUND(((((ET51*1.2)*0.8))*AV51*1),2)*BB51),2)+ROUND((ROUND(((AE51-(((EU51*1.2)*0.8)))*AV51*1),2)*BS51),2)) -> 89.39 | CS51: =(ROUND((ROUND(((((EU51*1.2)*0.8))*AV51*1),2)*BS51),2)+ROUND((ROUND(((AE51-(((EU51*1.2)*0.8)))*AV51*1),2)*BS51),2)) -> 14.65 | CT51: =ROUND((ROUND((AF51*AV51*1),2)*BA51),2) -> 16000.58 | CU51: =AG51 -> 0 | CV51: =(AH51*AV51) -> 25.403136 | CW51: =AI51 -> 0 | CX51: =AJ51 -> 0 | CY51: =(ROUND((((S51+ROUND((ROUND(((((EU51*1.2)*0.8))*AV51*1),2)*BS51),2))*AT51)/100),2)+ROUND(((ROUND((ROUND(((AE51-(((EU51*1.2)*0.8)))*AV51*1),2)*BS51),2)*AT51)/100),2)) -> 2147.1 | CZ51: =(ROUND((((S51+ROUND((ROUND(((((EU51*1.2)*0.8))*AV51*1),2)*BS51),2))*AU51)/100),2)+ROUND(((ROUND((ROUND(((AE51-(((EU51*1.2)*0.8)))*AV51*1),2)*BS51),2)*AU51)/100),2)) -> 1277.61 | DB51: 43 | DD51: *1)*0 | DE51: *1,2)*0,8 | DF51: *1,2)*0,8 | DG51: *1,2)*0,8 | DI51: *1,2)*0,8 | DJ51: *1,2)*0,8 | DN51: 0 | DO51: 0 | DP51: 1 | DQ51: 1 | DU51: 1010 | DV51: 100 шт. | DW51: 100 шт. | DX51: 100 | EE51: 57042911 | EF51: 30 | EG51: Строительные работы | EH51: 0 | EJ51: 1 | EK51: 22 | EL51: ТСН-2001.3-17. Водопровод и канализация - внутренние устройства | EM51: ТСН-2001.3-17-1 | EO51: Поправка: Гл.12.Прил.8.п.8. 3_12.00.01.11.001 Поправка: Гл.6.Прил.2.2.п.2.2.12_06.00.01.35.002 | EQ51: 0 | ER51: 641.07 | ES51: 356.04 | ET51: 7.82 | EU51: 0.25 | EV51: 277.21 | EW51: 24.8 | EX51: 0 | EY51: 0 | FQ51: 0 | FR51: 0 | FS51: 0 | FX51: 121 | FY51: 72 | GD51: 1 | GF51: 1356411474 | GG51: 2 | GH51: 1 | GI51: 2 | GJ51: 0 | GK51: 0 | GL51: =ROUND(IF(AND(BH51=3,BI51=3,FS51<>0),P51,0),2) -> 0 | GM51: =ROUND(O51+X51+Y51,2)+GX51 -> 5169.33 | GN51: =IF(OR(BI51=0,BI51=1),GM51-GX51,0) -> 5169.33 | GO51: =IF(BI51=2,GM51-GX51,0) -> 0 | GP51: =IF(BI51=4,GM51-GX51,0) -> 0 | GR51: 0 | GS51: 3 | GT51: 0 | GV51: =ROUND((GT51),6) -> 0 | GW51: 1 | GX51: =ROUND(HC51*I51,2) -> 0 | HA51: 0 | HB51: 0 | HC51: =GV51*GW51 -> 0 | HS51: 0 | IK51: 0
A53: 51 | B53: =B24 -> 1 | C53: =A24 -> 4 | D53: =ROW(A24) -> 24 | F53: =IF(F24<>"",F24,"") -> Новый раздел | G53: =IF(G24<>"",G24,"") -> Демонтажные работы (письмо от АНО «РГТ» об утверждении объёмов демонтажных работ) | H53: 0 | O53: =ROUND(AB53,2) -> 10173.78 | P53: =ROUND(AC53,2) -> 0 | Q53: =ROUND(AD53,2) -> 158.25 | R53: =ROUND(AE53,2) -> 4.24 | S53: =ROUND(AF53,2) -> 10015.53 | T53: =ROUND(AG53,2) -> 0 | U53: =AH53 -> 836.40381 | V53: =AI53 -> 0 | W53: =ROUND(AJ53,2) -> 0 | X53: =ROUND(AK53,2) -> 9110.84 | Y53: =ROUND(AL53,2) -> 4733.93 | AB53: =ROUND(SUMIF(AA28:AA51,"=57014138",O28:O51),2) -> 10173.78 | AC53: =ROUND(SUMIF(AA28:AA51,"=57014138",P28:P51),2) -> 0 | AD53: =ROUND(SUMIF(AA28:AA51,"=57014138",Q28:Q51),2) -> 158.25 | AE53: =ROUND(SUMIF(AA28:AA51,"=57014138",R28:R51),2) -> 4.24 | AF53: =ROUND(SUMIF(AA28:AA51,"=57014138",S28:S51),2) -> 10015.53 | AG53: =ROUND(SUMIF(AA28:AA51,"=57014138",T28:T51),2) -> 0 | AH53: =SUMIF(AA28:AA51,"=57014138",U28:U51) -> 836.40381 | AI53: =SUMIF(AA28:AA51,"=57014138",V28:V51) -> 0 | AJ53: =ROUND(SUMIF(AA28:AA51,"=57014138",W28:W51),2) -> 0 | AK53: =ROUND(SUMIF(AA28:AA51,"=57014138",X28:X51),2) -> 9110.84 | AL53: =ROUND(SUMIF(AA28:AA51,"=57014138",Y28:Y51),2) -> 4733.93 | AO53: =ROUND(BX53,2) -> 0 | AP53: =ROUND(BY53,2) -> 0 | AQ53: =ROUND(BZ53,2) -> 0 | AR53: =ROUND(CA53,2) -> 24018.55 | AS53: =ROUND(CB53,2) -> 92.44 | AT53: =ROUND(CC53,2) -> 23926.11 | AU53: =ROUND(CD53,2) -> 0 | AV53: =ROUND(CE53,2) -> 0 | ... BD53: =ROUND(CM53,2) -> 0 | BX53: =ROUND(SUMIF(AA28:AA51,"=57014138",FQ28:FQ51),2) -> 0 | BY53: =ROUND(SUMIF(AA28:AA51,"=57014138",FR28:FR51),2) -> 0 | BZ53: =ROUND(SUMIF(AA28:AA51,"=57014138",GL28:GL51),2) -> 0 | CA53: =ROUND(SUMIF(AA28:AA51,"=57014138",GM28:GM51),2) -> 24018.55 | CB53: =ROUND(SUMIF(AA28:AA51,"=57014138",GN28:GN51),2) -> 92.44 | CC53: =ROUND(SUMIF(AA28:AA51,"=57014138",GO28:GO51),2) -> 23926.11 | CD53: =ROUND(SUMIF(AA28:AA51,"=57014138",GP28:GP51),2) -> 0 | CE53: =AC53-BX53 -> 0 | CF53: =AC53-BY53 -> 0 | CG53: =BX53-BZ53 -> 0 | CH53: =AC53-BX53-BY53+BZ53 -> 0 | CI53: =BY53-BZ53 -> 0 | CJ53: =ROUND(SUMIF(AA28:AA51,"=57014138",GX28:GX51),2) -> 0 | CK53: =ROUND(SUMIF(AA28:AA51,"=57014138",GY28:GY51),2) -> 0 | CL53: =ROUND(SUMIF(AA28:AA51,"=57014138",GZ28:GZ51),2) -> 0 | CM53: =ROUND(SUMIF(AA28:AA51,"=57014138",HD28:HD51),2) -> 0 | DG53: =ROUND(DT53,2) -> 566144.05 | DH53: =ROUND(DU53,2) -> 0 | DI53: =ROUND(DV53,2) -> 1768.95 | DJ53: =ROUND(DW53,2) -> 238.92 | DK53: =ROUND(DX53,2) -> 564375.1 | DL53: =ROUND(DY53,2) -> 0 | DM53: =DZ53 -> 836.40381 | DN53: =EA53 -> 0 | DO53: =ROUND(EB53,2) -> 0 | DP53: =ROUND(EC53,2) -> 513395.89 | DQ53: =ROUND(ED53,2) -> 266756.52 | DT53: =ROUND(SUMIF(AA28:AA51,"=57014140",O28:O51),2) -> 566144.05 | DU53: =ROUND(SUMIF(AA28:AA51,"=57014140",P28:P51),2) -> 0 | DV53: =ROUND(SUMIF(AA28:AA51,"=57014140",Q28:Q51),2) -> 1768.95 | DW53: =ROUND(SUMIF(AA28:AA51,"=57014140",R28:R51),2) -> 238.92 | DX53: =ROUND(SUMIF(AA28:AA51,"=57014140",S28:S51),2) -> 564375.1 | DY53: =ROUND(SUMIF(AA28:AA51,"=57014140",T28:T51),2) -> 0 | DZ53: =SUMIF(AA28:AA51,"=57014140",U28:U51) -> 836.40381 | EA53: =SUMIF(AA28:AA51,"=57014140",V28:V51) -> 0 | EB53: =ROUND(SUMIF(AA28:AA51,"=57014140",W28:W51),2) -> 0 | EC53: =ROUND(SUMIF(AA28:AA51,"=57014140",X28:X51),2) -> 513395.89 | ED53: =ROUND(SUMIF(AA28:AA51,"=57014140",Y28:Y51),2) -> 266756.52 | EG53: =ROUND(FP53,2) -> 0 | EH53: =ROUND(FQ53,2) -> 0 | EI53: =ROUND(FR53,2) -> 0 | EJ53: =ROUND(FS53,2) -> 1346296.5 | EK53: =ROUND(FT53,2) -> 5169.33 | EL53: =ROUND(FU53,2) -> 1341127.1 | EM53: =ROUND(FV53,2) -> 0 | EN53: =ROUND(FW53,2) -> 0 | ... EV53: =ROUND(GE53,2) -> 0 | FP53: =ROUND(SUMIF(AA28:AA51,"=57014140",FQ28:FQ51),2) -> 0 | FQ53: =ROUND(SUMIF(AA28:AA51,"=57014140",FR28:FR51),2) -> 0 | FR53: =ROUND(SUMIF(AA28:AA51,"=57014140",GL28:GL51),2) -> 0 | FS53: =ROUND(SUMIF(AA28:AA51,"=57014140",GM28:GM51),2) -> 1346296.5 | FT53: =ROUND(SUMIF(AA28:AA51,"=57014140",GN28:GN51),2) -> 5169.33 | FU53: =ROUND(SUMIF(AA28:AA51,"=57014140",GO28:GO51),2) -> 1341127.1 | FV53: =ROUND(SUMIF(AA28:AA51,"=57014140",GP28:GP51),2) -> 0 | FW53: =DU53-FP53 -> 0 | FX53: =DU53-FQ53 -> 0 | FY53: =FP53-FR53 -> 0 | FZ53: =DU53-FP53-FQ53+FR53 -> 0 | GA53: =FQ53-FR53 -> 0 | GB53: =ROUND(SUMIF(AA28:AA51,"=57014140",GX28:GX51),2) -> 0 | GC53: =ROUND(SUMIF(AA28:AA51,"=57014140",GY28:GY51),2) -> 0 | GD53: =ROUND(SUMIF(AA28:AA51,"=57014140",GZ28:GZ51),2) -> 0 | GE53: =ROUND(SUMIF(AA28:AA51,"=57014140",HD28:HD51),2) -> 0 | GX53: 0
A55: 50 | B55: 0 | C55: 0 | D55: 1 | E55: 201 | F55: =ROUND(Source!O53,O55) -> 10173.78 | G55: ПЗ | H55: Прямые затраты | K55: 201 | L55: 1 | M55: 3 | O55: 2 | P55: =ROUND(Source!DG53,O55) -> 566144.05 | W55: 10173.78 | X55: 1 | Y55: 10173.78 | Z55: 566144.05 | AA55: 1 | AB55: 566144.05
A56: 50 | B56: 0 | C56: 0 | D56: 1 | E56: 202 | F56: =ROUND(Source!P53,O56) -> 0 | G56: СтМатОб | H56: Стоимость материальных ресурсов (всего) | K56: 202 | L56: 2 | M56: 3 | O56: 2 | P56: =ROUND(Source!DH53,O56) -> 0 | W56: 0 | X56: 1 | Y56: 0 | Z56: 0 | AA56: 1 | AB56: 0
A57: 50 | B57: 0 | C57: 0 | D57: 1 | E57: 222 | F57: =ROUND(Source!AO53,O57) -> 0 | G57: СтМатОбЗак | H57: Стоимость материалов и оборудования заказчика | K57: 222 | L57: 3 | M57: 3 | O57: 2 | P57: =ROUND(Source!EG53,O57) -> 0 | W57: 0 | X57: 1 | Y57: 0 | Z57: 0 | AA57: 1 | AB57: 0
A58: 50 | B58: 0 | C58: 0 | D58: 1 | E58: 225 | F58: =ROUND(Source!AV53,O58) -> 0 | G58: СтМатОбПод | H58: Стоимость материалов и оборудования подрядчика | K58: 225 | L58: 4 | M58: 3 | O58: 2 | P58: =ROUND(Source!EN53,O58) -> 0 | W58: 0 | X58: 1 | Y58: 0 | Z58: 0 | AA58: 1 | AB58: 0
A59: 50 | B59: 0 | C59: 0 | D59: 1 | E59: 226 | F59: =ROUND(Source!AW53,O59) -> 0 | G59: СтМат | H59: Стоимость материалов (всего) | K59: 226 | L59: 5 | M59: 3 | O59: 2 | P59: =ROUND(Source!EO53,O59) -> 0 | W59: 0 | X59: 1 | Y59: 0 | Z59: 0 | AA59: 1 | AB59: 0
A60: 50 | B60: 0 | C60: 0 | D60: 1 | E60: 227 | F60: =ROUND(Source!AX53,O60) -> 0 | G60: СтМатЗак | H60: Стоимость материалов заказчика | K60: 227 | L60: 6 | M60: 3 | O60: 2 | P60: =ROUND(Source!EP53,O60) -> 0 | W60: 0 | X60: 1 | Y60: 0 | Z60: 0 | AA60: 1 | AB60: 0
A61: 50 | B61: 0 | C61: 0 | D61: 1 | E61: 228 | F61: =ROUND(Source!AY53,O61) -> 0 | G61: СтМатПод | H61: Стоимость материалов подрядчика | K61: 228 | L61: 7 | M61: 3 | O61: 2 | P61: =ROUND(Source!EQ53,O61) -> 0 | W61: 0 | X61: 1 | Y61: 0 | Z61: 0 | AA61: 1 | AB61: 0
A62: 50 | B62: 0 | C62: 0 | D62: 1 | E62: 216 | F62: =ROUND(Source!AP53,O62) -> 0 | G62: Оборуд | H62: Стоимость оборудования (всего) | K62: 216 | L62: 8 | M62: 3 | O62: 2 | P62: =ROUND(Source!EH53,O62) -> 0 | W62: 0 | X62: 1 | Y62: 0 | Z62: 0 | AA62: 1 | AB62: 0
A63: 50 | B63: 0 | C63: 0 | D63: 1 | E63: 223 | F63: =ROUND(Source!AQ53,O63) -> 0 | G63: ОборудЗак | H63: Стоимость оборудования заказчика | K63: 223 | L63: 9 | M63: 3 | O63: 2 | P63: =ROUND(Source!EI53,O63) -> 0 | W63: 0 | X63: 1 | Y63: 0 | Z63: 0 | AA63: 1 | AB63: 0
A64: 50 | B64: 0 | C64: 0 | D64: 1 | E64: 229 | F64: =ROUND(Source!AZ53,O64) -> 0 | G64: ОборудПод | H64: Стоимость оборудования подрядчика | K64: 229 | L64: 10 | M64: 3 | O64: 2 | P64: =ROUND(Source!ER53,O64) -> 0 | W64: 0 | X64: 1 | Y64: 0 | Z64: 0 | AA64: 1 | AB64: 0
A65: 50 | B65: 0 | C65: 0 | D65: 1 | E65: 203 | F65: =ROUND(Source!Q53,O65) -> 158.25 | G65: ЭММ | H65: Эксплуатация машин | K65: 203 | L65: 11 | M65: 3 | O65: 2 | P65: =ROUND(Source!DI53,O65) -> 1768.95 | W65: 158.25 | X65: 1 | Y65: 158.25 | Z65: 1768.95 | AA65: 1 | AB65: 1768.95
A66: 50 | B66: 0 | C66: 0 | D66: 1 | E66: 231 | F66: =ROUND(Source!BB53,O66) -> 0 | G66: ЭММсНРиСП | H66: Эксплуатация машин по ТСН-2001.16 | K66: 231 | L66: 12 | M66: 3 | O66: 2 | P66: =ROUND(Source!ET53,O66) -> 0 | W66: 0 | X66: 1 | Y66: 0 | Z66: 0 | AA66: 1 | AB66: 0
A67: 50 | B67: 0 | C67: 0 | D67: 1 | E67: 204 | F67: =ROUND(Source!R53,O67) -> 4.24 | G67: ЗПМ | H67: ЗП машинистов | K67: 204 | L67: 13 | M67: 3 | O67: 2 | P67: =ROUND(Source!DJ53,O67) -> 238.92 | W67: 4.24 | X67: 1 | Y67: 4.24 | Z67: 238.92 | AA67: 1 | AB67: 238.92
A68: 50 | B68: 0 | C68: 0 | D68: 1 | E68: 205 | F68: =ROUND(Source!S53,O68) -> 10015.53 | G68: ОЗП | H68: Основная ЗП рабочих | K68: 205 | L68: 14 | M68: 3 | O68: 2 | P68: =ROUND(Source!DK53,O68) -> 564375.1 | W68: 10015.53 | X68: 1 | Y68: 10015.53 | Z68: 564375.1 | AA68: 1 | AB68: 564375.1
A69: 50 | B69: 0 | C69: 0 | D69: 1 | E69: 232 | F69: =ROUND(Source!BC53,O69) -> 0 | G69: ОЗПсНРиСП | H69: Основная ЗП рабочих по ТСН-2001.16 | K69: 232 | L69: 15 | M69: 3 | O69: 2 | P69: =ROUND(Source!EU53,O69) -> 0 | W69: 0 | X69: 1 | Y69: 0 | Z69: 0 | AA69: 1 | AB69: 0
A70: 50 | B70: 0 | C70: 0 | D70: 1 | E70: 214 | F70: =ROUND(Source!AS53,O70) -> 92.44 | G70: Строит | H70: Строительные работы с НР и СП | K70: 214 | L70: 16 | M70: 3 | O70: 2 | P70: =ROUND(Source!EK53,O70) -> 5169.33 | W70: 92.44 | X70: 1 | Y70: 92.44 | Z70: 5169.33 | AA70: 1 | AB70: 5169.33
A71: 50 | B71: 0 | C71: 0 | D71: 1 | E71: 215 | F71: =ROUND(Source!AT53,O71) -> 23926.11 | G71: Монтаж | H71: Монтажные работы с НР и СП | K71: 215 | L71: 17 | M71: 3 | O71: 2 | P71: =ROUND(Source!EL53,O71) -> 1341127.1 | W71: 23926.11 | X71: 1 | Y71: 23926.11 | Z71: 1341127.1 | AA71: 1 | AB71: 1341127.1
A72: 50 | B72: 0 | C72: 0 | D72: 1 | E72: 217 | F72: =ROUND(Source!AU53,O72) -> 0 | G72: Прочие | H72: Прочие работы с НР и СП | K72: 217 | L72: 18 | M72: 3 | O72: 2 | P72: =ROUND(Source!EM53,O72) -> 0 | W72: 0 | X72: 1 | Y72: 0 | Z72: 0 | AA72: 1 | AB72: 0
A73: 50 | B73: 0 | C73: 0 | D73: 1 | E73: 230 | F73: =ROUND(Source!BA53,O73) -> 0 | G73: ПрочиеЗатр | H73: Прочие затраты по ТСН-2001.16 | K73: 230 | L73: 19 | M73: 3 | O73: 2 | P73: =ROUND(Source!ES53,O73) -> 0 | W73: 0 | X73: 1 | Y73: 0 | Z73: 0 | AA73: 1 | AB73: 0
A74: 50 | B74: 0 | C74: 0 | D74: 1 | E74: 206 | F74: =ROUND(Source!T53,O74) -> 0 | G74: ВозврМат | H74: Возврат материалов | K74: 206 | L74: 20 | M74: 3 | O74: 2 | P74: =ROUND(Source!DL53,O74) -> 0 | W74: 0 | X74: 1 | Y74: 0 | Z74: 0 | AA74: 1 | AB74: 0
A75: 50 | B75: 0 | C75: 0 | D75: 1 | E75: 207 | F75: =Source!U53 -> 836.40381 | G75: ТрудСтр | H75: Трудозатраты строителей | K75: 207 | L75: 21 | M75: 3 | O75: -1 | P75: =Source!DM53 -> 836.40381 | W75: 836.40381 | X75: 1 | Y75: 836.40381 | Z75: 836.40381 | AA75: 1 | AB75: 836.40381
A76: 50 | B76: 0 | C76: 0 | D76: 1 | E76: 208 | F76: =Source!V53 -> 0 | G76: ТрудМаш | H76: Трудозатраты машинистов | K76: 208 | L76: 22 | M76: 3 | O76: -1 | P76: =Source!DN53 -> 0 | W76: 0 | X76: 1 | Y76: 0 | Z76: 0 | AA76: 1 | AB76: 0
A77: 50 | B77: 0 | C77: 0 | D77: 1 | E77: 209 | F77: =ROUND(Source!W53,O77) -> 0 | G77: ТранспМат | H77: Транспорт материалов | K77: 209 | L77: 23 | M77: 3 | O77: 2 | P77: =ROUND(Source!DO53,O77) -> 0 | W77: 0 | X77: 1 | Y77: 0 | Z77: 0 | AA77: 1 | AB77: 0
A78: 50 | B78: 0 | C78: 0 | D78: 1 | E78: 233 | F78: =ROUND(Source!BD53,O78) -> 0 | G78: Перевозка | H78: Перевозка грузов | K78: 233 | L78: 24 | M78: 3 | O78: 2 | P78: =ROUND(Source!EV53,O78) -> 0 | W78: 0 | X78: 1 | Y78: 0 | Z78: 0 | AA78: 1 | AB78: 0
A79: 50 | B79: 0 | C79: 0 | D79: 1 | E79: 210 | F79: =ROUND(Source!X53,O79) -> 9110.84 | G79: НР | H79: Накладные расходы | K79: 210 | L79: 25 | M79: 3 | O79: 2 | P79: =ROUND(Source!DP53,O79) -> 513395.89 | W79: 9110.84 | X79: 1 | Y79: 9110.84 | Z79: 513395.89 | AA79: 1 | AB79: 513395.89
A80: 50 | B80: 0 | C80: 0 | D80: 1 | E80: 211 | F80: =ROUND(Source!Y53,O80) -> 4733.93 | G80: СмПриб | H80: Сметная прибыль | K80: 211 | L80: 26 | M80: 3 | O80: 2 | P80: =ROUND(Source!DQ53,O80) -> 266756.52 | W80: 4733.93 | X80: 1 | Y80: 4733.93 | Z80: 266756.52 | AA80: 1 | AB80: 266756.52
A81: 50 | B81: 0 | C81: 0 | D81: 1 | E81: 224 | F81: =ROUND(Source!AR53,O81) -> 24018.55 | G81: Всего | H81: Всего с НР и СП | K81: 224 | L81: 27 | M81: 3 | O81: 2 | P81: =ROUND(Source!EJ53,O81) -> 1346296.5 | W81: 24018.55 | X81: 1 | Y81: 24018.55 | Z81: 1346296.5 | AA81: 1 | AB81: 1346296.5
A83: 4 | B83: 1 | D83: =ROW(A152) -> 152 | G83: Центральное оборудование системы | I83: 0 | K83: -1 | S83: 0 | T83: 0 | V83: 2 | BX83: 0 | CJ83: 0
A85: 52 | B85: =B152 -> 1 | C85: =C152 -> 4 | D85: =D152 -> 83 | E85: =E152 -> 0 | F85: =F152 | G85: =G152 -> Центральное оборудование системы | O85: =O152 -> 109193.04 | P85: =P152 -> 108372.57 | Q85: =Q152 -> 115.9 | R85: =R152 -> 12.56 | S85: =S152 -> 704.57 | T85: =T152 -> 0 | U85: =U152 -> 55.834416 | V85: =V152 -> 0 | ... GX85: =GX152 -> 0
A87: 17 | B87: 1 | C87: =ROW(SmtRes!A91) -> 91 | D87: =ROW(EtalonRes!A116) -> 116 | E87: 11 | F87: 4.10-32-2 | G87: Монтаж стойки, полустойки, каркаса стойки или шкафа массой до 300 кг | H87: 1 ШТ. | I87: 1 | J87: 0 | K87: 1 | O87: =ROUND(CP87,2) -> 271.59 | P87: =ROUND((ROUND((AC87*AW87*I87),2)*BC87),2) -> 3.92 | Q87: =(ROUND((ROUND((((ET87*1.2))*AV87*I87),2)*BB87),2)+ROUND((ROUND(((AE87-((EU87*1.2)))*AV87*I87),2)*BS87),2)) -> 79.45 | R87: =(ROUND((ROUND((((EU87*1.2))*AV87*I87),2)*BS87),2)+ROUND((ROUND(((AE87-((EU87*1.2)))*AV87*I87),2)*BS87),2)) -> 8.56 | S87: =ROUND((ROUND((AF87*AV87*I87),2)*BA87),2) -> 188.22 | T87: =ROUND(CU87*I87,2) -> 0 | U87: =CV87*I87 -> 16.83576 | V87: =CW87*I87 -> 0 | W87: =ROUND(CX87*I87,2) -> 0 | X87: =(ROUND((((S87+ROUND((ROUND((((EU87*1.2))*AV87*I87),2)*BS87),2))*AT87)/100),2)+ROUND(((ROUND((ROUND(((AE87-((EU87*1.2)))*AV87*I87),2)*BS87),2)*AT87)/100),2)) -> 177.1 | Y87: =(ROUND((((S87+ROUND((ROUND((((EU87*1.2))*AV87*I87),2)*BS87),2))*AU87)/100),2)+ROUND(((ROUND((ROUND(((AE87-((EU87*1.2)))*AV87*I87),2)*BS87),2)*AU87)/100),2)) -> 90.52 | AA87: 57014138 | AB87: =ROUND((AC87+AD87+AF87),6) -> 259.58 | AC87: =ROUND(((ES87*1)),6) -> 3.92 | AD87: =ROUND(((((ET87*1.2))-((EU87*1.2)))+AE87),6) -> 75.888 | AE87: =ROUND(((EU87*1.2)),6) -> 8.172 | AF87: =ROUND(((EV87*1.2)),6) -> 179.772 | AG87: =ROUND((AP87),6) -> 0 | AH87: =((EW87*1.2)) -> 16.08 | AI87: =((EX87*1.2)) -> 0 | AJ87: =(AS87) -> 0 | AK87: 216.97 | AL87: 3.92 | AM87: 63.24 | AN87: 6.81 | AO87: 149.81 | AP87: 0 | AQ87: 13.4 | AR87: 0 | AS87: 0 | AT87: 90 | AU87: 46 | AV87: 1.047 | AW87: 1 | AZ87: 1 | BA87: 1 | BB87: 1 | BC87: 1 | BH87: 0 | BI87: 2 | BJ87: ТСН-2001.4 Доп. 80, Сб. 10, т. 32, поз. 2 | BM87: 68 | BN87: 0 | BO87: 4.10-32-2 | BP87: 1 | BQ87: 40 | BR87: 0 | BS87: 1 | BT87: 1 | BU87: 1 | BV87: 1 | BW87: 1 | BX87: 1 | BZ87: 90 | CA87: 46 | CE87: 1566 | CF87: 0 | CG87: 0 | CM87: 0 | CN87: Поправка: Гл.12.Прил.8.п.8. 3_12.00.01.11.001 Наименование: При наличии напряженных и стесненных условий производства работ (стесненность, сложность складирования и транспортной логистики и т.п.) для объектов, расположенных в пределах круговой магистральной системы улиц "Садовое кольцо" города Москвы | CO87: 0 | CP87: =(P87+Q87+S87) -> 271.59 | CQ87: =ROUND((ROUND((AC87*AW87*1),2)*BC87),2) -> 3.92 | CR87: =(ROUND((ROUND((((ET87*1.2))*AV87*1),2)*BB87),2)+ROUND((ROUND(((AE87-((EU87*1.2)))*AV87*1),2)*BS87),2)) -> 79.45 | CS87: =(ROUND((ROUND((((EU87*1.2))*AV87*1),2)*BS87),2)+ROUND((ROUND(((AE87-((EU87*1.2)))*AV87*1),2)*BS87),2)) -> 8.56 | CT87: =ROUND((ROUND((AF87*AV87*1),2)*BA87),2) -> 188.22 | CU87: =AG87 -> 0 | CV87: =(AH87*AV87) -> 16.83576 | CW87: =AI87 -> 0 | CX87: =AJ87 -> 0 | CY87: =(ROUND((((S87+ROUND((ROUND((((EU87*1.2))*AV87*1),2)*BS87),2))*AT87)/100),2)+ROUND(((ROUND((ROUND(((AE87-((EU87*1.2)))*AV87*1),2)*BS87),2)*AT87)/100),2)) -> 177.1 | CZ87: =(ROUND((((S87+ROUND((ROUND((((EU87*1.2))*AV87*1),2)*BS87),2))*AU87)/100),2)+ROUND(((ROUND((ROUND(((AE87-((EU87*1.2)))*AV87*1),2)*BS87),2)*AU87)/100),2)) -> 90.52 | DB87: 45 | DD87: *1 | DE87: *1,2 | DF87: *1,2 | DG87: *1,2 | DI87: *1,2 | DJ87: *1,2 | DN87: 0 | DO87: 0 | DP87: 1 | DQ87: 1 | DU87: 1013 | DV87: 1 ШТ. | DW87: 1 ШТ. | DX87: 1 | EE87: 57042958 | EF87: 40 | EG87: Монтаж оборудования | EH87: 0 | EJ87: 2 | EK87: 68 | EL87: ТСН-2001.4-10. Прокладка и монтаж сетей связи | EM87: ТСН-2001.4-10-1 | EO87: Поправка: Гл.12.Прил.8.п.8. 3_12.00.01.11.001 | EQ87: 0 | ER87: 216.97 | ES87: 3.92 | ET87: 63.24 | EU87: 6.81 | EV87: 149.81 | EW87: 13.4 | EX87: 0 | EY87: 0 | FQ87: 0 | FR87: 0 | FS87: 0 | FX87: 90 | FY87: 46 | GD87: 1 | GF87: -1495082032 | GG87: 2 | GH87: 1 | GI87: 2 | GJ87: 0 | GK87: 0 | GL87: =ROUND(IF(AND(BH87=3,BI87=3,FS87<>0),P87,0),2) -> 0 | GM87: =ROUND(O87+X87+Y87,2)+GX87 -> 539.21 | GN87: =IF(OR(BI87=0,BI87=1),GM87-GX87,0) -> 0 | GO87: =IF(BI87=2,GM87-GX87,0) -> 539.21 | GP87: =IF(BI87=4,GM87-GX87,0) -> 0 | GR87: 0 | GS87: 3 | GT87: 0 | GV87: =ROUND((GT87),6) -> 0 | GW87: 1 | GX87: =ROUND(HC87*I87,2) -> 0 | HA87: 0 | HB87: 0 | HC87: =GV87*GW87 -> 0 | HS87: 0 | IK87: 0
A88: 17 | B88: 1 | C88: =ROW(SmtRes!A96) -> 96 | D88: =ROW(EtalonRes!A122) -> 122 | E88: 11 | F88: 4.10-32-2 | G88: Монтаж стойки, полустойки, каркаса стойки или шкафа массой до 300 кг | H88: 1 ШТ. | I88: 1 | J88: 0 | K88: 1 | O88: =ROUND(CP88,2) -> 11908.49 | P88: =ROUND((ROUND((AC88*AW88*I88),2)*BC88),2) -> 27.91 | Q88: =(ROUND((ROUND((((ET88*1.2))*AV88*I88),2)*BB88),2)+ROUND((ROUND(((AE88-((EU88*1.2)))*AV88*I88),2)*BS88),2)) -> 1274.38 | R88: =(ROUND((ROUND((((EU88*1.2))*AV88*I88),2)*BS88),2)+ROUND((ROUND(((AE88-((EU88*1.2)))*AV88*I88),2)*BS88),2)) -> 482.36 | S88: =ROUND((ROUND((AF88*AV88*I88),2)*BA88),2) -> 10606.2 | T88: =ROUND(CU88*I88,2) -> 0 | U88: =CV88*I88 -> 16.83576 | V88: =CW88*I88 -> 0 | W88: =ROUND(CX88*I88,2) -> 0 | X88: =(ROUND((((S88+ROUND((ROUND((((EU88*1.2))*AV88*I88),2)*BS88),2))*AT88)/100),2)+ROUND(((ROUND((ROUND(((AE88-((EU88*1.2)))*AV88*I88),2)*BS88),2)*AT88)/100),2)) -> 9979.7 | Y88: =(ROUND((((S88+ROUND((ROUND((((EU88*1.2))*AV88*I88),2)*BS88),2))*AU88)/100),2)+ROUND(((ROUND((ROUND(((AE88-((EU88*1.2)))*AV88*I88),2)*BS88),2)*AU88)/100),2)) -> 5100.74 | AA88: 57014140 | AB88: =ROUND((AC88+AD88+AF88),6) -> 259.58 | AC88: =ROUND(((ES88*1)),6) -> 3.92 | AD88: =ROUND(((((ET88*1.2))-((EU88*1.2)))+AE88),6) -> 75.888 | AE88: =ROUND(((EU88*1.2)),6) -> 8.172 | AF88: =ROUND(((EV88*1.2)),6) -> 179.772 | AG88: =ROUND((AP88),6) -> 0 | AH88: =((EW88*1.2)) -> 16.08 | AI88: =((EX88*1.2)) -> 0 | AJ88: =(AS88) -> 0 | AK88: 216.97 | AL88: 3.92 | AM88: 63.24 | AN88: 6.81 | AO88: 149.81 | AP88: 0 | AQ88: 13.4 | AR88: 0 | AS88: 0 | AT88: 90 | AU88: 46 | AV88: 1.047 | AW88: 1 | AZ88: 1 | BA88: 56.35 | BB88: 16.04 | BC88: 7.12 | BH88: 0 | BI88: 2 | BJ88: ТСН-2001.4 Доп. 80, Сб. 10, т. 32, поз. 2 | BM88: 68 | BN88: 0 | BO88: 4.10-32-2 | BP88: 1 | BQ88: 40 | BR88: 0 | BS88: 56.35 | BT88: 1 | BU88: 1 | BV88: 1 | BW88: 1 | BX88: 1 | BZ88: 90 | CA88: 46 | CE88: 1566 | CF88: 0 | CG88: 0 | CM88: 0 | CN88: Поправка: Гл.12.Прил.8.п.8. 3_12.00.01.11.001 Наименование: При наличии напряженных и стесненных условий производства работ (стесненность, сложность складирования и транспортной логистики и т.п.) для объектов, расположенных в пределах круговой магистральной системы улиц "Садовое кольцо" города Москвы | CO88: 0 | CP88: =(P88+Q88+S88) -> 11908.49 | CQ88: =ROUND((ROUND((AC88*AW88*1),2)*BC88),2) -> 27.91 | CR88: =(ROUND((ROUND((((ET88*1.2))*AV88*1),2)*BB88),2)+ROUND((ROUND(((AE88-((EU88*1.2)))*AV88*1),2)*BS88),2)) -> 1274.38 | CS88: =(ROUND((ROUND((((EU88*1.2))*AV88*1),2)*BS88),2)+ROUND((ROUND(((AE88-((EU88*1.2)))*AV88*1),2)*BS88),2)) -> 482.36 | CT88: =ROUND((ROUND((AF88*AV88*1),2)*BA88),2) -> 10606.2 | CU88: =AG88 -> 0 | CV88: =(AH88*AV88) -> 16.83576 | CW88: =AI88 -> 0 | CX88: =AJ88 -> 0 | CY88: =(ROUND((((S88+ROUND((ROUND((((EU88*1.2))*AV88*1),2)*BS88),2))*AT88)/100),2)+ROUND(((ROUND((ROUND(((AE88-((EU88*1.2)))*AV88*1),2)*BS88),2)*AT88)/100),2)) -> 9979.7 | CZ88: =(ROUND((((S88+ROUND((ROUND((((EU88*1.2))*AV88*1),2)*BS88),2))*AU88)/100),2)+ROUND(((ROUND((ROUND(((AE88-((EU88*1.2)))*AV88*1),2)*BS88),2)*AU88)/100),2)) -> 5100.74 | DB88: 46 | DD88: *1 | DE88: *1,2 | DF88: *1,2 | DG88: *1,2 | DI88: *1,2 | DJ88: *1,2 | DN88: 0 | DO88: 0 | DP88: 1 | DQ88: 1 | DU88: 1013 | DV88: 1 ШТ. | DW88: 1 ШТ. | DX88: 1 | EE88: 57042958 | EF88: 40 | EG88: Монтаж оборудования | EH88: 0 | EJ88: 2 | EK88: 68 | EL88: ТСН-2001.4-10. Прокладка и монтаж сетей связи | EM88: ТСН-2001.4-10-1 | EO88: Поправка: Гл.12.Прил.8.п.8. 3_12.00.01.11.001 | EQ88: 0 | ER88: 216.97 | ES88: 3.92 | ET88: 63.24 | EU88: 6.81 | EV88: 149.81 | EW88: 13.4 | EX88: 0 | EY88: 0 | FQ88: 0 | FR88: 0 | FS88: 0 | FX88: 90 | FY88: 46 | GD88: 1 | GF88: -1495082032 | GG88: 2 | GH88: 1 | GI88: 2 | GJ88: 0 | GK88: 0 | GL88: =ROUND(IF(AND(BH88=3,BI88=3,FS88<>0),P88,0),2) -> 0 | GM88: =ROUND(O88+X88+Y88,2)+GX88 -> 26988.93 | GN88: =IF(OR(BI88=0,BI88=1),GM88-GX88,0) -> 0 | GO88: =IF(BI88=2,GM88-GX88,0) -> 26988.93 | GP88: =IF(BI88=4,GM88-GX88,0) -> 0 | GR88: 0 | GS88: 3 | GT88: 0 | GV88: =ROUND((GT88),6) -> 0 | GW88: 1 | GX88: =ROUND(HC88*I88,2) -> 0 | HA88: 0 | HB88: 0 | HC88: =GV88*GW88 -> 0 | HS88: 0 | IK88: 0
A89: 17 | B89: 1 | E89: 12 | F89: КА, п.1 | G89: Шкаф управления оповещения и эвакуацией пожарный SONAR RACK SPM 16U Ш-18-0425 | H89: ШТ | I89: 1 | J89: 0 | K89: 1 | O89: =ROUND(CP89,2) -> 82560.19 | P89: =ROUND((ROUND((AC89*AW89*I89),2)*BC89),2) -> 82560.19 | Q89: =(ROUND((ROUND(((ET89)*AV89*I89),2)*BB89),2)+ROUND((ROUND(((AE89-(EU89))*AV89*I89),2)*BS89),2)) -> 0 | R89: =(ROUND((ROUND(((EU89)*AV89*I89),2)*BS89),2)+ROUND((ROUND(((AE89-(EU89))*AV89*I89),2)*BS89),2)) -> 0 | S89: =ROUND((ROUND((AF89*AV89*I89),2)*BA89),2) -> 0 | T89: =ROUND(CU89*I89,2) -> 0 | U89: =CV89*I89 -> 0 | V89: =CW89*I89 -> 0 | W89: =ROUND(CX89*I89,2) -> 0 | X89: =(ROUND((((S89+ROUND((ROUND(((EU89)*AV89*I89),2)*BS89),2))*AT89)/100),2)+ROUND(((ROUND((ROUND(((AE89-(EU89))*AV89*I89),2)*BS89),2)*AT89)/100),2)) -> 0 | Y89: =(ROUND((((S89+ROUND((ROUND(((EU89)*AV89*I89),2)*BS89),2))*AU89)/100),2)+ROUND(((ROUND((ROUND(((AE89-(EU89))*AV89*I89),2)*BS89),2)*AU89)/100),2)) -> 0 | AA89: 57014138 | AB89: =ROUND((AC89+AD89+AF89),6) -> 82560.19 | AC89: =ROUND((ES89),6) -> 82560.19 | AD89: =ROUND((((ET89)-(EU89))+AE89),6) -> 0 | AE89: =ROUND((EU89),6) -> 0 | AF89: =ROUND((EV89),6) -> 0 | AG89: =ROUND((AP89),6) -> 0 | AH89: =(EW89) -> 0 | AI89: =(EX89) -> 0 | AJ89: =(AS89) -> 0 | AK89: 82560.19 | AL89: 82560.19 | AM89: 0 | AN89: 0 | AO89: 0 | AP89: 0 | AQ89: 0 | AR89: 0 | AS89: 0 | AT89: 0 | AU89: 0 | AV89: 1 | AW89: 1 | AZ89: 1 | BA89: 1 | BB89: 1 | BC89: 1 | BH89: 3 | BI89: 3 | BJ89: КА, п.1 | BM89: 400007 | BN89: 0 | BP89: 0 | BQ89: 214 | BR89: 0 | BS89: 1 | BT89: 1 | BU89: 1 | BV89: 1 | BW89: 1 | BX89: 1 | BZ89: 0 | CA89: 0 | CE89: 1566 | CF89: 0 | CG89: 0 | CM89: 0 | CO89: 0 | CP89: =(P89+Q89+S89) -> 82560.19 | CQ89: =ROUND((ROUND((AC89*AW89*1),2)*BC89),2) -> 82560.19 | CR89: =(ROUND((ROUND(((ET89)*AV89*1),2)*BB89),2)+ROUND((ROUND(((AE89-(EU89))*AV89*1),2)*BS89),2)) -> 0 | CS89: =(ROUND((ROUND(((EU89)*AV89*1),2)*BS89),2)+ROUND((ROUND(((AE89-(EU89))*AV89*1),2)*BS89),2)) -> 0 | CT89: =ROUND((ROUND((AF89*AV89*1),2)*BA89),2) -> 0 | CU89: =AG89 -> 0 | CV89: =(AH89*AV89) -> 0 | CW89: =AI89 -> 0 | CX89: =AJ89 -> 0 | CY89: =(ROUND((((S89+ROUND((ROUND(((EU89)*AV89*1),2)*BS89),2))*AT89)/100),2)+ROUND(((ROUND((ROUND(((AE89-(EU89))*AV89*1),2)*BS89),2)*AT89)/100),2)) -> 0 | CZ89: =(ROUND((((S89+ROUND((ROUND(((EU89)*AV89*1),2)*BS89),2))*AU89)/100),2)+ROUND(((ROUND((ROUND(((AE89-(EU89))*AV89*1),2)*BS89),2)*AU89)/100),2)) -> 0 | DN89: 0 | DO89: 0 | DP89: 1 | DQ89: 1 | DU89: 1013 | DV89: ШТ | DW89: ШТ | DX89: 1 | EE89: 57042890 | EF89: 214 | EG89: Оборудование, отсутствующие в СНБ | EH89: 0 | EJ89: 3 | EK89: 400007 | EL89: Оборудование, отсутствующие в СНБ | EM89: Оборуд. КА | EQ89: 16 | ER89: 0 | ES89: 82560.19 | ET89: 0 | EU89: 0 | EV89: 0 | EW89: 0 | EX89: 0 | EY89: 0 | FQ89: 0 | FR89: =P89 -> 82560.19 | FS89: 0 | FX89: 0 | FY89: 0 | GA89: [731 490,5 / 1,22 / 7,57] + 3% Трансп + 1,2% Заг.скл | GD89: 1 | GF89: 2033696216 | GG89: 2 | GH89: 4 | GI89: -2 | GJ89: 0 | GK89: 0 | GL89: =ROUND(IF(AND(BH89=3,BI89=3,FS89<>0),P89,0),2) -> 0 | GM89: =ROUND(O89+X89+Y89,2)+GX89 -> 82560.19 | GN89: =IF(OR(BI89=0,BI89=1),GM89-GX89,0) -> 0 | GO89: =IF(BI89=2,GM89-GX89,0) -> 0 | GP89: =IF(BI89=4,GM89-GX89,0) -> 0 | GR89: 1 | GS89: 2 | GT89: 0 | GV89: =ROUND((GT89),6) -> 0 | GW89: 1 | GX89: =ROUND(HC89*I89,2) -> 0 | HA89: 0 | HB89: 0 | HC89: =GV89*GW89 -> 0 | HE89: 3 | HF89: 1,2 | HS89: 0 | IK89: 0
A90: 17 | B90: 1 | E90: 12 | F90: КА, п.1 | G90: Шкаф управления оповещения и эвакуацией пожарный SONAR RACK SPM 16U Ш-18-0425 | H90: ШТ | I90: 1 | J90: 0 | K90: 1 | O90: =ROUND(CP90,2) -> 624980.64 | P90: =ROUND((ROUND((AC90*AW90*I90),2)*BC90),2) -> 624980.64 | Q90: =(ROUND((ROUND(((ET90)*AV90*I90),2)*BB90),2)+ROUND((ROUND(((AE90-(EU90))*AV90*I90),2)*BS90),2)) -> 0 | R90: =(ROUND((ROUND(((EU90)*AV90*I90),2)*BS90),2)+ROUND((ROUND(((AE90-(EU90))*AV90*I90),2)*BS90),2)) -> 0 | S90: =ROUND((ROUND((AF90*AV90*I90),2)*BA90),2) -> 0 | T90: =ROUND(CU90*I90,2) -> 0 | U90: =CV90*I90 -> 0 | V90: =CW90*I90 -> 0 | W90: =ROUND(CX90*I90,2) -> 0 | X90: =(ROUND((((S90+ROUND((ROUND(((EU90)*AV90*I90),2)*BS90),2))*AT90)/100),2)+ROUND(((ROUND((ROUND(((AE90-(EU90))*AV90*I90),2)*BS90),2)*AT90)/100),2)) -> 0 | Y90: =(ROUND((((S90+ROUND((ROUND(((EU90)*AV90*I90),2)*BS90),2))*AU90)/100),2)+ROUND(((ROUND((ROUND(((AE90-(EU90))*AV90*I90),2)*BS90),2)*AU90)/100),2)) -> 0 | AA90: 57014140 | AB90: =ROUND((AC90+AD90+AF90),6) -> 82560.19 | AC90: =ROUND((ES90),6) -> 82560.19 | AD90: =ROUND((((ET90)-(EU90))+AE90),6) -> 0 | AE90: =ROUND((EU90),6) -> 0 | AF90: =ROUND((EV90),6) -> 0 | AG90: =ROUND((AP90),6) -> 0 | AH90: =(EW90) -> 0 | AI90: =(EX90) -> 0 | AJ90: =(AS90) -> 0 | AK90: 82560.19 | AL90: 82560.19 | AM90: 0 | AN90: 0 | AO90: 0 | AP90: 0 | AQ90: 0 | AR90: 0 | AS90: 0 | AT90: 0 | AU90: 0 | AV90: 1 | AW90: 1 | AZ90: 1 | BA90: 1 | BB90: 1 | BC90: 7.57 | BH90: 3 | BI90: 3 | BJ90: КА, п.1 | BM90: 400007 | BN90: 0 | BP90: 0 | BQ90: 214 | BR90: 0 | BS90: 1 | BT90: 1 | BU90: 1 | BV90: 1 | BW90: 1 | BX90: 1 | BZ90: 0 | CA90: 0 | CE90: 1566 | CF90: 0 | CG90: 0 | CM90: 0 | CO90: 0 | CP90: =(P90+Q90+S90) -> 624980.64 | CQ90: =ROUND((ROUND((AC90*AW90*1),2)*BC90),2) -> 624980.64 | CR90: =(ROUND((ROUND(((ET90)*AV90*1),2)*BB90),2)+ROUND((ROUND(((AE90-(EU90))*AV90*1),2)*BS90),2)) -> 0 | CS90: =(ROUND((ROUND(((EU90)*AV90*1),2)*BS90),2)+ROUND((ROUND(((AE90-(EU90))*AV90*1),2)*BS90),2)) -> 0 | CT90: =ROUND((ROUND((AF90*AV90*1),2)*BA90),2) -> 0 | CU90: =AG90 -> 0 | CV90: =(AH90*AV90) -> 0 | CW90: =AI90 -> 0 | CX90: =AJ90 -> 0 | CY90: =(ROUND((((S90+ROUND((ROUND(((EU90)*AV90*1),2)*BS90),2))*AT90)/100),2)+ROUND(((ROUND((ROUND(((AE90-(EU90))*AV90*1),2)*BS90),2)*AT90)/100),2)) -> 0 | CZ90: =(ROUND((((S90+ROUND((ROUND(((EU90)*AV90*1),2)*BS90),2))*AU90)/100),2)+ROUND(((ROUND((ROUND(((AE90-(EU90))*AV90*1),2)*BS90),2)*AU90)/100),2)) -> 0 | DN90: 0 | DO90: 0 | DP90: 1 | DQ90: 1 | DU90: 1013 | DV90: ШТ | DW90: ШТ | DX90: 1 | EE90: 57042890 | EF90: 214 | EG90: Оборудование, отсутствующие в СНБ | EH90: 0 | EJ90: 3 | EK90: 400007 | EL90: Оборудование, отсутствующие в СНБ | EM90: Оборуд. КА | EQ90: 16 | ER90: 0 | ES90: 82560.19 | ET90: 0 | EU90: 0 | EV90: 0 | EW90: 0 | EX90: 0 | EY90: 0 | EZ90: 5 | FC90: 1 | FD90: 18 | FF90: 731490.5 | FQ90: 0 | FR90: =P90 -> 624980.64 | FS90: 0 | FX90: 0 | FY90: 0 | GA90: [731 490,5 / 1,22 / 7,57] + 3% Трансп + 1,2% Заг.скл | GD90: 1 | GF90: 2033696216 | GG90: 2 | GH90: 3 | GI90: 5 | GJ90: 0 | GK90: 0 | GL90: =ROUND(IF(AND(BH90=3,BI90=3,FS90<>0),P90,0),2) -> 0 | GM90: =ROUND(O90+X90+Y90,2)+GX90 -> 624980.64 | GN90: =IF(OR(BI90=0,BI90=1),GM90-GX90,0) -> 0 | GO90: =IF(BI90=2,GM90-GX90,0) -> 0 | GP90: =IF(BI90=4,GM90-GX90,0) -> 0 | GR90: 1 | GS90: 1 | GT90: 0 | GV90: =ROUND((GT90),6) -> 0 | GW90: 1 | GX90: =ROUND(HC90*I90,2) -> 0 | HA90: 0 | HB90: 0 | HC90: =GV90*GW90 -> 0 | HE90: 3 | HF90: 1,2 | HS90: 0 | IK90: 0
A91: 17 | B91: 1 | F91: КА, п.2 | G91: Sonar RD-8 (вилка) - Блок розеток 1U, 8 розеток, 16A, Максимальная мощность потребления 3,5 кВт. Шнур с вилкой SCHUKO Sonar RD-8 (вилка) (Калибр+) ЗС000077190 | H91: ШТ | I91: 1 | J91: 0 | K91: 1 | O91: =ROUND(CP91,2) -> 651.18 | P91: =ROUND((ROUND((AC91*AW91*I91),2)*BC91),2) -> 651.18 | Q91: =(ROUND((ROUND(((ET91)*AV91*I91),2)*BB91),2)+ROUND((ROUND(((AE91-(EU91))*AV91*I91),2)*BS91),2)) -> 0 | R91: =(ROUND((ROUND(((EU91)*AV91*I91),2)*BS91),2)+ROUND((ROUND(((AE91-(EU91))*AV91*I91),2)*BS91),2)) -> 0 | S91: =ROUND((ROUND((AF91*AV91*I91),2)*BA91),2) -> 0 | T91: =ROUND(CU91*I91,2) -> 0 | U91: =CV91*I91 -> 0 | V91: =CW91*I91 -> 0 | W91: =ROUND(CX91*I91,2) -> 0 | X91: =(ROUND((((S91+ROUND((ROUND(((EU91)*AV91*I91),2)*BS91),2))*AT91)/100),2)+ROUND(((ROUND((ROUND(((AE91-(EU91))*AV91*I91),2)*BS91),2)*AT91)/100),2)) -> 0 | Y91: =(ROUND((((S91+ROUND((ROUND(((EU91)*AV91*I91),2)*BS91),2))*AU91)/100),2)+ROUND(((ROUND((ROUND(((AE91-(EU91))*AV91*I91),2)*BS91),2)*AU91)/100),2)) -> 0 | AA91: -1 | AB91: =ROUND((AC91+AD91+AF91),6) -> 651.18 | AC91: =ROUND((ES91),6) -> 651.18 | AD91: =ROUND((((ET91)-(EU91))+AE91),6) -> 0 | AE91: =ROUND((EU91),6) -> 0 | AF91: =ROUND((EV91),6) -> 0 | AG91: =ROUND((AP91),6) -> 0 | AH91: =(EW91) -> 0 | AI91: =(EX91) -> 0 | AJ91: =(AS91) -> 0 | AK91: 651.18 | AL91: 651.18 | AM91: 0 | AN91: 0 | AO91: 0 | AP91: 0 | AQ91: 0 | AR91: 0 | AS91: 0 | AT91: 0 | AU91: 0 | AV91: 1 | AW91: 1 | AZ91: 1 | BA91: 1 | BB91: 1 | BC91: 1 | BH91: 3 | BI91: 2 | BJ91: КА, п.2 | BM91: 400005 | BN91: 0 | BP91: 0 | BQ91: 213 | BR91: 0 | BS91: 1 | BT91: 1 | BU91: 1 | BV91: 1 | BW91: 1 | BX91: 1 | BZ91: 0 | CA91: 0 | CE91: 1566 | CF91: 0 | CG91: 0 | CM91: 0 | CO91: 0 | CP91: =(P91+Q91+S91) -> 651.18 | CQ91: =ROUND((ROUND((AC91*AW91*1),2)*BC91),2) -> 651.18 | CR91: =(ROUND((ROUND(((ET91)*AV91*1),2)*BB91),2)+ROUND((ROUND(((AE91-(EU91))*AV91*1),2)*BS91),2)) -> 0 | CS91: =(ROUND((ROUND(((EU91)*AV91*1),2)*BS91),2)+ROUND((ROUND(((AE91-(EU91))*AV91*1),2)*BS91),2)) -> 0 | CT91: =ROUND((ROUND((AF91*AV91*1),2)*BA91),2) -> 0 | CU91: =AG91 -> 0 | CV91: =(AH91*AV91) -> 0 | CW91: =AI91 -> 0 | CX91: =AJ91 -> 0 | CY91: =(ROUND((((S91+ROUND((ROUND(((EU91)*AV91*1),2)*BS91),2))*AT91)/100),2)+ROUND(((ROUND((ROUND(((AE91-(EU91))*AV91*1),2)*BS91),2)*AT91)/100),2)) -> 0 | CZ91: =(ROUND((((S91+ROUND((ROUND(((EU91)*AV91*1),2)*BS91),2))*AU91)/100),2)+ROUND(((ROUND((ROUND(((AE91-(EU91))*AV91*1),2)*BS91),2)*AU91)/100),2)) -> 0 | DN91: 0 | DO91: 0 | DP91: 1 | DQ91: 1 | DU91: 1013 | DV91: ШТ | DW91: ШТ | DX91: 1 | EE91: 57042888 | EF91: 213 | EG91: Материалы, отсутствующие в СНБ (Строительные) | EH91: 0 | EJ91: 1 | EK91: 400005 | EL91: Материалы, отсутствующие в СНБ (Строительные) | EM91: МР КА Строительные | EQ91: 1040 | ER91: 0 | ES91: 651.18 | ET91: 0 | EU91: 0 | EV91: 0 | EW91: 0 | EX91: 0 | EY91: 0 | FQ91: 0 | FR91: 0 | FS91: 0 | FX91: 0 | FY91: 0 | GA91: [7 664 / 1,22 / 9,84] + 2% Заг.скл | GD91: 1 | GF91: -1870089525 | GG91: 2 | GH91: 4 | GI91: -2 | GJ91: 0 | GK91: 0 | GL91: =ROUND(IF(AND(BH91=3,BI91=3,FS91<>0),P91,0),2) -> 0 | GM91: =ROUND(O91+X91+Y91,2)+GX91 -> 651.18 | GN91: =IF(OR(BI91=0,BI91=1),GM91-GX91,0) -> 0 | GO91: =IF(BI91=2,GM91-GX91,0) -> 651.18 | GP91: =IF(BI91=4,GM91-GX91,0) -> 0 | GR91: 1 | GS91: 2 | GT91: 0 | GV91: =ROUND((GT91),6) -> 0 | GW91: 1 | GX91: =ROUND(HC91*I91,2) -> 0 | HA91: 0 | HB91: 0 | HC91: =GV91*GW91 -> 0 | HE91: 0 | HF91: 2 | HS91: 0 | IK91: 0
A92: 17 | B92: 1 | F92: КА, п.2 | G92: Sonar RD-8 (вилка) - Блок розеток 1U, 8 розеток, 16A, Максимальная мощность потребления 3,5 кВт. Шнур с вилкой SCHUKO Sonar RD-8 (вилка) (Калибр+) ЗС000077190 | H92: ШТ | I92: 1 | J92: 0 | K92: 1 | O92: =ROUND(CP92,2) -> 6407.61 | P92: =ROUND((ROUND((AC92*AW92*I92),2)*BC92),2) -> 6407.61 | Q92: =(ROUND((ROUND(((ET92)*AV92*I92),2)*BB92),2)+ROUND((ROUND(((AE92-(EU92))*AV92*I92),2)*BS92),2)) -> 0 | R92: =(ROUND((ROUND(((EU92)*AV92*I92),2)*BS92),2)+ROUND((ROUND(((AE92-(EU92))*AV92*I92),2)*BS92),2)) -> 0 | S92: =ROUND((ROUND((AF92*AV92*I92),2)*BA92),2) -> 0 | T92: =ROUND(CU92*I92,2) -> 0 | U92: =CV92*I92 -> 0 | V92: =CW92*I92 -> 0 | W92: =ROUND(CX92*I92,2) -> 0 | X92: =(ROUND((((S92+ROUND((ROUND(((EU92)*AV92*I92),2)*BS92),2))*AT92)/100),2)+ROUND(((ROUND((ROUND(((AE92-(EU92))*AV92*I92),2)*BS92),2)*AT92)/100),2)) -> 0 | Y92: =(ROUND((((S92+ROUND((ROUND(((EU92)*AV92*I92),2)*BS92),2))*AU92)/100),2)+ROUND(((ROUND((ROUND(((AE92-(EU92))*AV92*I92),2)*BS92),2)*AU92)/100),2)) -> 0 | AA92: -1 | AB92: =ROUND((AC92+AD92+AF92),6) -> 651.18 | AC92: =ROUND((ES92),6) -> 651.18 | AD92: =ROUND((((ET92)-(EU92))+AE92),6) -> 0 | AE92: =ROUND((EU92),6) -> 0 | AF92: =ROUND((EV92),6) -> 0 | AG92: =ROUND((AP92),6) -> 0 | AH92: =(EW92) -> 0 | AI92: =(EX92) -> 0 | AJ92: =(AS92) -> 0 | AK92: 651.18 | AL92: 651.18 | AM92: 0 | AN92: 0 | AO92: 0 | AP92: 0 | AQ92: 0 | AR92: 0 | AS92: 0 | AT92: 0 | AU92: 0 | AV92: 1 | AW92: 1 | AZ92: 1 | BA92: 1 | BB92: 1 | BC92: 9.84 | BH92: 3 | BI92: 2 | BJ92: КА, п.2 | BM92: 400005 | BN92: 0 | BP92: 0 | BQ92: 213 | BR92: 0 | BS92: 1 | BT92: 1 | BU92: 1 | BV92: 1 | BW92: 1 | BX92: 1 | BZ92: 0 | CA92: 0 | CE92: 1566 | CF92: 0 | CG92: 0 | CM92: 0 | CO92: 0 | CP92: =(P92+Q92+S92) -> 6407.61 | CQ92: =ROUND((ROUND((AC92*AW92*1),2)*BC92),2) -> 6407.61 | CR92: =(ROUND((ROUND(((ET92)*AV92*1),2)*BB92),2)+ROUND((ROUND(((AE92-(EU92))*AV92*1),2)*BS92),2)) -> 0 | CS92: =(ROUND((ROUND(((EU92)*AV92*1),2)*BS92),2)+ROUND((ROUND(((AE92-(EU92))*AV92*1),2)*BS92),2)) -> 0 | CT92: =ROUND((ROUND((AF92*AV92*1),2)*BA92),2) -> 0 | CU92: =AG92 -> 0 | CV92: =(AH92*AV92) -> 0 | CW92: =AI92 -> 0 | CX92: =AJ92 -> 0 | CY92: =(ROUND((((S92+ROUND((ROUND(((EU92)*AV92*1),2)*BS92),2))*AT92)/100),2)+ROUND(((ROUND((ROUND(((AE92-(EU92))*AV92*1),2)*BS92),2)*AT92)/100),2)) -> 0 | CZ92: =(ROUND((((S92+ROUND((ROUND(((EU92)*AV92*1),2)*BS92),2))*AU92)/100),2)+ROUND(((ROUND((ROUND(((AE92-(EU92))*AV92*1),2)*BS92),2)*AU92)/100),2)) -> 0 | DN92: 0 | DO92: 0 | DP92: 1 | DQ92: 1 | DU92: 1013 | DV92: ШТ | DW92: ШТ | DX92: 1 | EE92: 57042888 | EF92: 213 | EG92: Материалы, отсутствующие в СНБ (Строительные) | EH92: 0 | EJ92: 1 | EK92: 400005 | EL92: Материалы, отсутствующие в СНБ (Строительные) | EM92: МР КА Строительные | EQ92: 1040 | ER92: 0 | ES92: 651.18 | ET92: 0 | EU92: 0 | EV92: 0 | EW92: 0 | EX92: 0 | EY92: 0 | EZ92: 5 | FC92: 1 | FD92: 18 | FF92: 7664 | FQ92: 0 | FR92: 0 | FS92: 0 | FX92: 0 | FY92: 0 | GA92: [7 664 / 1,22 / 9,84] + 2% Заг.скл | GD92: 1 | GF92: -1870089525 | GG92: 2 | GH92: 3 | GI92: 5 | GJ92: 0 | GK92: 0 | GL92: =ROUND(IF(AND(BH92=3,BI92=3,FS92<>0),P92,0),2) -> 0 | GM92: =ROUND(O92+X92+Y92,2)+GX92 -> 6407.61 | GN92: =IF(OR(BI92=0,BI92=1),GM92-GX92,0) -> 0 | GO92: =IF(BI92=2,GM92-GX92,0) -> 6407.61 | GP92: =IF(BI92=4,GM92-GX92,0) -> 0 | GR92: 1 | GS92: 1 | GT92: 0 | GV92: =ROUND((GT92),6) -> 0 | GW92: 1 | GX92: =ROUND(HC92*I92,2) -> 0 | HA92: 0 | HB92: 0 | HC92: =GV92*GW92 -> 0 | HE92: 0 | HF92: 2 | HS92: 0 | IK92: 0
A93: 17 | B93: 1 | C93: =ROW(SmtRes!A98) -> 98 | D93: =ROW(EtalonRes!A125) -> 125 | F93: 4.11-12-1 | G93: Установка съемных и выдвижных блоков (модулей, ячеек, ТЭЗ) массой до 5 кг | H93: 1 ШТ. | I93: 1 | J93: 0 | K93: 1 | O93: =ROUND(CP93,2) -> 15.27 | P93: =ROUND((ROUND((AC93*AW93*I93),2)*BC93),2) -> 0 | Q93: =(ROUND((ROUND((((ET93*1.2))*AV93*I93),2)*BB93),2)+ROUND((ROUND(((AE93-((EU93*1.2)))*AV93*I93),2)*BS93),2)) -> 0.63 | R93: =(ROUND((ROUND((((EU93*1.2))*AV93*I93),2)*BS93),2)+ROUND((ROUND(((AE93-((EU93*1.2)))*AV93*I93),2)*BS93),2)) -> 0.1 | S93: =ROUND((ROUND((AF93*AV93*I93),2)*BA93),2) -> 14.64 | T93: =ROUND(CU93*I93,2) -> 0 | U93: =CV93*I93 -> 1.294092 | V93: =CW93*I93 -> 0 | W93: =ROUND(CX93*I93,2) -> 0 | X93: =(ROUND((((S93+ROUND((ROUND((((EU93*1.2))*AV93*I93),2)*BS93),2))*AT93)/100),2)+ROUND(((ROUND((ROUND(((AE93-((EU93*1.2)))*AV93*I93),2)*BS93),2)*AT93)/100),2)) -> 13.27 | Y93: =(ROUND((((S93+ROUND((ROUND((((EU93*1.2))*AV93*I93),2)*BS93),2))*AU93)/100),2)+ROUND(((ROUND((ROUND(((AE93-((EU93*1.2)))*AV93*I93),2)*BS93),2)*AU93)/100),2)) -> 6.78 | AA93: -1 | AB93: =ROUND((AC93+AD93+AF93),6) -> 14.58 | AC93: =ROUND(((ES93*1)),6) -> 0 | AD93: =ROUND(((((ET93*1.2))-((EU93*1.2)))+AE93),6) -> 0.6 | AE93: =ROUND(((EU93*1.2)),6) -> 0.096 | AF93: =ROUND(((EV93*1.2)),6) -> 13.98 | AG93: =ROUND((AP93),6) -> 0 | AH93: =((EW93*1.2)) -> 1.236 | AI93: =((EX93*1.2)) -> 0 | AJ93: =(AS93) -> 0 | AK93: 12.15 | AL93: 0 | AM93: 0.5 | AN93: 0.08 | AO93: 11.65 | AP93: 0 | AQ93: 1.03 | AR93: 0 | AS93: 0 | AT93: 90 | AU93: 46 | AV93: 1.047 | AW93: 1 | AZ93: 1 | BA93: 1 | BB93: 1 | BC93: 1 | BH93: 0 | BI93: 2 | BJ93: ТСН-2001.4 Доп. 68, Сб. 11, т. 12, поз. 1 | BM93: 72 | BN93: 0 | BO93: 4.11-12-1 | BP93: 1 | BQ93: 40 | BR93: 0 | BS93: 1 | BT93: 1 | BU93: 1 | BV93: 1 | BW93: 1 | BX93: 1 | BZ93: 90 | CA93: 46 | CE93: 1566 | CF93: 0 | CG93: 0 | CM93: 0 | CN93: Поправка: Гл.12.Прил.8.п.8. 3_12.00.01.11.001 Наименование: При наличии напряженных и стесненных условий производства работ (стесненность, сложность складирования и транспортной логистики и т.п.) для объектов, расположенных в пределах круговой магистральной системы улиц "Садовое кольцо" города Москвы | CO93: 0 | CP93: =(P93+Q93+S93) -> 15.27 | CQ93: =ROUND((ROUND((AC93*AW93*1),2)*BC93),2) -> 0 | CR93: =(ROUND((ROUND((((ET93*1.2))*AV93*1),2)*BB93),2)+ROUND((ROUND(((AE93-((EU93*1.2)))*AV93*1),2)*BS93),2)) -> 0.63 | CS93: =(ROUND((ROUND((((EU93*1.2))*AV93*1),2)*BS93),2)+ROUND((ROUND(((AE93-((EU93*1.2)))*AV93*1),2)*BS93),2)) -> 0.1 | CT93: =ROUND((ROUND((AF93*AV93*1),2)*BA93),2) -> 14.64 | CU93: =AG93 -> 0 | CV93: =(AH93*AV93) -> 1.294092 | CW93: =AI93 -> 0 | CX93: =AJ93 -> 0 | CY93: =(ROUND((((S93+ROUND((ROUND((((EU93*1.2))*AV93*1),2)*BS93),2))*AT93)/100),2)+ROUND(((ROUND((ROUND(((AE93-((EU93*1.2)))*AV93*1),2)*BS93),2)*AT93)/100),2)) -> 13.27 | CZ93: =(ROUND((((S93+ROUND((ROUND((((EU93*1.2))*AV93*1),2)*BS93),2))*AU93)/100),2)+ROUND(((ROUND((ROUND(((AE93-((EU93*1.2)))*AV93*1),2)*BS93),2)*AU93)/100),2)) -> 6.78 | DB93: 47 | DD93: *1 | DE93: *1,2 | DF93: *1,2 | DG93: *1,2 | DI93: *1,2 | DJ93: *1,2 | DN93: 0 | DO93: 0 | DP93: 1 | DQ93: 1 | DU93: 1013 | DV93: 1 ШТ. | DW93: 1 ШТ. | DX93: 1 | EE93: 57042962 | EF93: 40 | EG93: Монтаж оборудования | EH93: 0 | EJ93: 2 | EK93: 72 | EL93: ТСН-2001.4-11. Приборы и средства автоматизации и вычислительной техники | EM93: ТСН-2001.4-11-1 | EO93: Поправка: Гл.12.Прил.8.п.8. 3_12.00.01.11.001 | EQ93: 1024 | ER93: 12.15 | ES93: 0 | ET93: 0.5 | EU93: 0.08 | EV93: 11.65 | EW93: 1.03 | EX93: 0 | EY93: 0 | FQ93: 0 | FR93: 0 | FS93: 0 | FX93: 90 | FY93: 46 | GD93: 1 | GF93: -920792427 | GG93: 2 | GH93: 1 | GI93: 2 | GJ93: 0 | GK93: 0 | GL93: =ROUND(IF(AND(BH93=3,BI93=3,FS93<>0),P93,0),2) -> 0 | GM93: =ROUND(O93+X93+Y93,2)+GX93 -> 35.32 | GN93: =IF(OR(BI93=0,BI93=1),GM93-GX93,0) -> 0 | GO93: =IF(BI93=2,GM93-GX93,0) -> 35.32 | GP93: =IF(BI93=4,GM93-GX93,0) -> 0 | GR93: 0 | GS93: 3 | GT93: 0 | GV93: =ROUND((GT93),6) -> 0 | GW93: 1 | GX93: =ROUND(HC93*I93,2) -> 0 | HA93: 0 | HB93: 0 | HC93: =GV93*GW93 -> 0 | HS93: 0 | IK93: 0
A94: 17 | B94: 1 | C94: =ROW(SmtRes!A100) -> 100 | D94: =ROW(EtalonRes!A128) -> 128 | F94: 4.11-12-1 | G94: Установка съемных и выдвижных блоков (модулей, ячеек, ТЭЗ) массой до 5 кг | H94: 1 ШТ. | I94: 1 | J94: 0 | K94: 1 | O94: =ROUND(CP94,2) -> 835.68 | P94: =ROUND((ROUND((AC94*AW94*I94),2)*BC94),2) -> 0 | Q94: =(ROUND((ROUND((((ET94*1.2))*AV94*I94),2)*BB94),2)+ROUND((ROUND(((AE94-((EU94*1.2)))*AV94*I94),2)*BS94),2)) -> 10.72 | R94: =(ROUND((ROUND((((EU94*1.2))*AV94*I94),2)*BS94),2)+ROUND((ROUND(((AE94-((EU94*1.2)))*AV94*I94),2)*BS94),2)) -> 5.64 | S94: =ROUND((ROUND((AF94*AV94*I94),2)*BA94),2) -> 824.96 | T94: =ROUND(CU94*I94,2) -> 0 | U94: =CV94*I94 -> 1.294092 | V94: =CW94*I94 -> 0 | W94: =ROUND(CX94*I94,2) -> 0 | X94: =(ROUND((((S94+ROUND((ROUND((((EU94*1.2))*AV94*I94),2)*BS94),2))*AT94)/100),2)+ROUND(((ROUND((ROUND(((AE94-((EU94*1.2)))*AV94*I94),2)*BS94),2)*AT94)/100),2)) -> 747.54 | Y94: =(ROUND((((S94+ROUND((ROUND((((EU94*1.2))*AV94*I94),2)*BS94),2))*AU94)/100),2)+ROUND(((ROUND((ROUND(((AE94-((EU94*1.2)))*AV94*I94),2)*BS94),2)*AU94)/100),2)) -> 382.08 | AA94: -1 | AB94: =ROUND((AC94+AD94+AF94),6) -> 14.58 | AC94: =ROUND(((ES94*1)),6) -> 0 | AD94: =ROUND(((((ET94*1.2))-((EU94*1.2)))+AE94),6) -> 0.6 | AE94: =ROUND(((EU94*1.2)),6) -> 0.096 | AF94: =ROUND(((EV94*1.2)),6) -> 13.98 | AG94: =ROUND((AP94),6) -> 0 | AH94: =((EW94*1.2)) -> 1.236 | AI94: =((EX94*1.2)) -> 0 | AJ94: =(AS94) -> 0 | AK94: 12.15 | AL94: 0 | AM94: 0.5 | AN94: 0.08 | AO94: 11.65 | AP94: 0 | AQ94: 1.03 | AR94: 0 | AS94: 0 | AT94: 90 | AU94: 46 | AV94: 1.047 | AW94: 1 | AZ94: 1 | BA94: 56.35 | BB94: 17.02 | BC94: 1 | BH94: 0 | BI94: 2 | BJ94: ТСН-2001.4 Доп. 68, Сб. 11, т. 12, поз. 1 | BM94: 72 | BN94: 0 | BO94: 4.11-12-1 | BP94: 1 | BQ94: 40 | BR94: 0 | BS94: 56.35 | BT94: 1 | BU94: 1 | BV94: 1 | BW94: 1 | BX94: 1 | BZ94: 90 | CA94: 46 | CE94: 1566 | CF94: 0 | CG94: 0 | CM94: 0 | CN94: Поправка: Гл.12.Прил.8.п.8. 3_12.00.01.11.001 Наименование: При наличии напряженных и стесненных условий производства работ (стесненность, сложность складирования и транспортной логистики и т.п.) для объектов, расположенных в пределах круговой магистральной системы улиц "Садовое кольцо" города Москвы | CO94: 0 | CP94: =(P94+Q94+S94) -> 835.68 | CQ94: =ROUND((ROUND((AC94*AW94*1),2)*BC94),2) -> 0 | CR94: =(ROUND((ROUND((((ET94*1.2))*AV94*1),2)*BB94),2)+ROUND((ROUND(((AE94-((EU94*1.2)))*AV94*1),2)*BS94),2)) -> 10.72 | CS94: =(ROUND((ROUND((((EU94*1.2))*AV94*1),2)*BS94),2)+ROUND((ROUND(((AE94-((EU94*1.2)))*AV94*1),2)*BS94),2)) -> 5.64 | CT94: =ROUND((ROUND((AF94*AV94*1),2)*BA94),2) -> 824.96 | CU94: =AG94 -> 0 | CV94: =(AH94*AV94) -> 1.294092 | CW94: =AI94 -> 0 | CX94: =AJ94 -> 0 | CY94: =(ROUND((((S94+ROUND((ROUND((((EU94*1.2))*AV94*1),2)*BS94),2))*AT94)/100),2)+ROUND(((ROUND((ROUND(((AE94-((EU94*1.2)))*AV94*1),2)*BS94),2)*AT94)/100),2)) -> 747.54 | CZ94: =(ROUND((((S94+ROUND((ROUND((((EU94*1.2))*AV94*1),2)*BS94),2))*AU94)/100),2)+ROUND(((ROUND((ROUND(((AE94-((EU94*1.2)))*AV94*1),2)*BS94),2)*AU94)/100),2)) -> 382.08 | DB94: 48 | DD94: *1 | DE94: *1,2 | DF94: *1,2 | DG94: *1,2 | DI94: *1,2 | DJ94: *1,2 | DN94: 0 | DO94: 0 | DP94: 1 | DQ94: 1 | DU94: 1013 | DV94: 1 ШТ. | DW94: 1 ШТ. | DX94: 1 | EE94: 57042962 | EF94: 40 | EG94: Монтаж оборудования | EH94: 0 | EJ94: 2 | EK94: 72 | EL94: ТСН-2001.4-11. Приборы и средства автоматизации и вычислительной техники | EM94: ТСН-2001.4-11-1 | EO94: Поправка: Гл.12.Прил.8.п.8. 3_12.00.01.11.001 | EQ94: 1024 | ER94: 12.15 | ES94: 0 | ET94: 0.5 | EU94: 0.08 | EV94: 11.65 | EW94: 1.03 | EX94: 0 | EY94: 0 | FQ94: 0 | FR94: 0 | FS94: 0 | FX94: 90 | FY94: 46 | GD94: 1 | GF94: -920792427 | GG94: 2 | GH94: 1 | GI94: 2 | GJ94: 0 | GK94: 0 | GL94: =ROUND(IF(AND(BH94=3,BI94=3,FS94<>0),P94,0),2) -> 0 | GM94: =ROUND(O94+X94+Y94,2)+GX94 -> 1965.3 | GN94: =IF(OR(BI94=0,BI94=1),GM94-GX94,0) -> 0 | GO94: =IF(BI94=2,GM94-GX94,0) -> 1965.3 | GP94: =IF(BI94=4,GM94-GX94,0) -> 0 | GR94: 0 | GS94: 3 | GT94: 0 | GV94: =ROUND((GT94),6) -> 0 | GW94: 1 | GX94: =ROUND(HC94*I94,2) -> 0 | HA94: 0 | HB94: 0 | HC94: =GV94*GW94 -> 0 | HS94: 0 | IK94: 0
A95: 17 | B95: 1 | C95: =ROW(SmtRes!A104) -> 104 | D95: =ROW(EtalonRes!A133) -> 133 | F95: 4.10-170-2 | G95: Монтаж блока информационно-управляющего (БИУ) в диспетчерской | H95: 1 ШТ. | I95: 1 | J95: 0 | K95: 1 | O95: =ROUND(CP95,2) -> 44.39 | P95: =ROUND((ROUND((AC95*AW95*I95),2)*BC95),2) -> 2.34 | Q95: =(ROUND((ROUND((((ET95*1.2))*AV95*I95),2)*BB95),2)+ROUND((ROUND(((AE95-((EU95*1.2)))*AV95*I95),2)*BS95),2)) -> 0 | R95: =(ROUND((ROUND((((EU95*1.2))*AV95*I95),2)*BS95),2)+ROUND((ROUND(((AE95-((EU95*1.2)))*AV95*I95),2)*BS95),2)) -> 0 | S95: =ROUND((ROUND((AF95*AV95*I95),2)*BA95),2) -> 42.05 | T95: =ROUND(CU95*I95,2) -> 0 | U95: =CV95*I95 -> 3.32946 | V95: =CW95*I95 -> 0 | W95: =ROUND(CX95*I95,2) -> 0 | X95: =(ROUND((((S95+ROUND((ROUND((((EU95*1.2))*AV95*I95),2)*BS95),2))*AT95)/100),2)+ROUND(((ROUND((ROUND(((AE95-((EU95*1.2)))*AV95*I95),2)*BS95),2)*AT95)/100),2)) -> 37.85 | Y95: =(ROUND((((S95+ROUND((ROUND((((EU95*1.2))*AV95*I95),2)*BS95),2))*AU95)/100),2)+ROUND(((ROUND((ROUND(((AE95-((EU95*1.2)))*AV95*I95),2)*BS95),2)*AU95)/100),2)) -> 19.34 | AA95: -1 | AB95: =ROUND((AC95+AD95+AF95),6) -> 42.504 | AC95: =ROUND(((ES95*1)),6) -> 2.34 | AD95: =ROUND(((((ET95*1.2))-((EU95*1.2)))+AE95),6) -> 0 | AE95: =ROUND(((EU95*1.2)),6) -> 0 | AF95: =ROUND(((EV95*1.2)),6) -> 40.164 | AG95: =ROUND((AP95),6) -> 0 | AH95: =((EW95*1.2)) -> 3.18 | AI95: =((EX95*1.2)) -> 0 | AJ95: =(AS95) -> 0 | AK95: 35.81 | AL95: 2.34 | AM95: 0 | AN95: 0 | AO95: 33.47 | AP95: 0 | AQ95: 2.65 | AR95: 0 | AS95: 0 | AT95: 90 | AU95: 46 | AV95: 1.047 | AW95: 1 | AZ95: 1 | BA95: 1 | BB95: 1 | BC95: 1 | BH95: 0 | BI95: 2 | BJ95: ТСН-2001.4 Доп. 67, Сб. 10, т. 170, поз. 2 | BM95: 68 | BN95: 0 | BO95: 4.10-170-2 | BP95: 1 | BQ95: 40 | BR95: 0 | BS95: 1 | BT95: 1 | BU95: 1 | BV95: 1 | BW95: 1 | BX95: 1 | BZ95: 90 | CA95: 46 | CE95: 1566 | CF95: 0 | CG95: 0 | CM95: 0 | CN95: Поправка: Гл.12.Прил.8.п.8. 3_12.00.01.11.001 Наименование: При наличии напряженных и стесненных условий производства работ (стесненность, сложность складирования и транспортной логистики и т.п.) для объектов, расположенных в пределах круговой магистральной системы улиц "Садовое кольцо" города Москвы | CO95: 0 | CP95: =(P95+Q95+S95) -> 44.39 | CQ95: =ROUND((ROUND((AC95*AW95*1),2)*BC95),2) -> 2.34 | CR95: =(ROUND((ROUND((((ET95*1.2))*AV95*1),2)*BB95),2)+ROUND((ROUND(((AE95-((EU95*1.2)))*AV95*1),2)*BS95),2)) -> 0 | CS95: =(ROUND((ROUND((((EU95*1.2))*AV95*1),2)*BS95),2)+ROUND((ROUND(((AE95-((EU95*1.2)))*AV95*1),2)*BS95),2)) -> 0 | CT95: =ROUND((ROUND((AF95*AV95*1),2)*BA95),2) -> 42.05 | CU95: =AG95 -> 0 | CV95: =(AH95*AV95) -> 3.32946 | CW95: =AI95 -> 0 | CX95: =AJ95 -> 0 | CY95: =(ROUND((((S95+ROUND((ROUND((((EU95*1.2))*AV95*1),2)*BS95),2))*AT95)/100),2)+ROUND(((ROUND((ROUND(((AE95-((EU95*1.2)))*AV95*1),2)*BS95),2)*AT95)/100),2)) -> 37.85 | CZ95: =(ROUND((((S95+ROUND((ROUND((((EU95*1.2))*AV95*1),2)*BS95),2))*AU95)/100),2)+ROUND(((ROUND((ROUND(((AE95-((EU95*1.2)))*AV95*1),2)*BS95),2)*AU95)/100),2)) -> 19.34 | DB95: 49 | DD95: *1 | DE95: *1,2 | DF95: *1,2 | DG95: *1,2 | DI95: *1,2 | DJ95: *1,2 | DN95: 0 | DO95: 0 | DP95: 1 | DQ95: 1 | DU95: 1013 | DV95: 1 ШТ. | DW95: 1 ШТ. | DX95: 1 | EE95: 57042958 | EF95: 40 | EG95: Монтаж оборудования | EH95: 0 | EJ95: 2 | EK95: 68 | EL95: ТСН-2001.4-10. Прокладка и монтаж сетей связи | EM95: ТСН-2001.4-10-1 | EO95: Поправка: Гл.12.Прил.8.п.8. 3_12.00.01.11.001 | EQ95: 1024 | ER95: 35.81 | ES95: 2.34 | ET95: 0 | EU95: 0 | EV95: 33.47 | EW95: 2.65 | EX95: 0 | EY95: 0 | FQ95: 0 | FR95: 0 | FS95: 0 | FX95: 90 | FY95: 46 | GD95: 1 | GF95: 1558984384 | GG95: 2 | GH95: 1 | GI95: 2 | GJ95: 0 | GK95: 0 | GL95: =ROUND(IF(AND(BH95=3,BI95=3,FS95<>0),P95,0),2) -> 0 | GM95: =ROUND(O95+X95+Y95,2)+GX95 -> 101.58 | GN95: =IF(OR(BI95=0,BI95=1),GM95-GX95,0) -> 0 | GO95: =IF(BI95=2,GM95-GX95,0) -> 101.58 | GP95: =IF(BI95=4,GM95-GX95,0) -> 0 | GR95: 0 | GS95: 3 | GT95: 0 | GV95: =ROUND((GT95),6) -> 0 | GW95: 1 | GX95: =ROUND(HC95*I95,2) -> 0 | HA95: 0 | HB95: 0 | HC95: =GV95*GW95 -> 0 | HS95: 0 | IK95: 0
A96: 17 | B96: 1 | C96: =ROW(SmtRes!A108) -> 108 | D96: =ROW(EtalonRes!A138) -> 138 | F96: 4.10-170-2 | G96: Монтаж блока информационно-управляющего (БИУ) в диспетчерской | H96: 1 ШТ. | I96: 1 | J96: 0 | K96: 1 | O96: =ROUND(CP96,2) -> 2393.48 | P96: =ROUND((ROUND((AC96*AW96*I96),2)*BC96),2) -> 23.96 | Q96: =(ROUND((ROUND((((ET96*1.2))*AV96*I96),2)*BB96),2)+ROUND((ROUND(((AE96-((EU96*1.2)))*AV96*I96),2)*BS96),2)) -> 0 | R96: =(ROUND((ROUND((((EU96*1.2))*AV96*I96),2)*BS96),2)+ROUND((ROUND(((AE96-((EU96*1.2)))*AV96*I96),2)*BS96),2)) -> 0 | S96: =ROUND((ROUND((AF96*AV96*I96),2)*BA96),2) -> 2369.52 | T96: =ROUND(CU96*I96,2) -> 0 | U96: =CV96*I96 -> 3.32946 | V96: =CW96*I96 -> 0 | W96: =ROUND(CX96*I96,2) -> 0 | X96: =(ROUND((((S96+ROUND((ROUND((((EU96*1.2))*AV96*I96),2)*BS96),2))*AT96)/100),2)+ROUND(((ROUND((ROUND(((AE96-((EU96*1.2)))*AV96*I96),2)*BS96),2)*AT96)/100),2)) -> 2132.57 | Y96: =(ROUND((((S96+ROUND((ROUND((((EU96*1.2))*AV96*I96),2)*BS96),2))*AU96)/100),2)+ROUND(((ROUND((ROUND(((AE96-((EU96*1.2)))*AV96*I96),2)*BS96),2)*AU96)/100),2)) -> 1089.98 | AA96: -1 | AB96: =ROUND((AC96+AD96+AF96),6) -> 42.504 | AC96: =ROUND(((ES96*1)),6) -> 2.34 | AD96: =ROUND(((((ET96*1.2))-((EU96*1.2)))+AE96),6) -> 0 | AE96: =ROUND(((EU96*1.2)),6) -> 0 | AF96: =ROUND(((EV96*1.2)),6) -> 40.164 | AG96: =ROUND((AP96),6) -> 0 | AH96: =((EW96*1.2)) -> 3.18 | AI96: =((EX96*1.2)) -> 0 | AJ96: =(AS96) -> 0 | AK96: 35.81 | AL96: 2.34 | AM96: 0 | AN96: 0 | AO96: 33.47 | AP96: 0 | AQ96: 2.65 | AR96: 0 | AS96: 0 | AT96: 90 | AU96: 46 | AV96: 1.047 | AW96: 1 | AZ96: 1 | BA96: 56.35 | BB96: 1 | BC96: 10.24 | BH96: 0 | BI96: 2 | BJ96: ТСН-2001.4 Доп. 67, Сб. 10, т. 170, поз. 2 | BM96: 68 | BN96: 0 | BO96: 4.10-170-2 | BP96: 1 | BQ96: 40 | BR96: 0 | BS96: 56.35 | BT96: 1 | BU96: 1 | BV96: 1 | BW96: 1 | BX96: 1 | BZ96: 90 | CA96: 46 | CE96: 1566 | CF96: 0 | CG96: 0 | CM96: 0 | CN96: Поправка: Гл.12.Прил.8.п.8. 3_12.00.01.11.001 Наименование: При наличии напряженных и стесненных условий производства работ (стесненность, сложность складирования и транспортной логистики и т.п.) для объектов, расположенных в пределах круговой магистральной системы улиц "Садовое кольцо" города Москвы | CO96: 0 | CP96: =(P96+Q96+S96) -> 2393.48 | CQ96: =ROUND((ROUND((AC96*AW96*1),2)*BC96),2) -> 23.96 | CR96: =(ROUND((ROUND((((ET96*1.2))*AV96*1),2)*BB96),2)+ROUND((ROUND(((AE96-((EU96*1.2)))*AV96*1),2)*BS96),2)) -> 0 | CS96: =(ROUND((ROUND((((EU96*1.2))*AV96*1),2)*BS96),2)+ROUND((ROUND(((AE96-((EU96*1.2)))*AV96*1),2)*BS96),2)) -> 0 | CT96: =ROUND((ROUND((AF96*AV96*1),2)*BA96),2) -> 2369.52 | CU96: =AG96 -> 0 | CV96: =(AH96*AV96) -> 3.32946 | CW96: =AI96 -> 0 | CX96: =AJ96 -> 0 | CY96: =(ROUND((((S96+ROUND((ROUND((((EU96*1.2))*AV96*1),2)*BS96),2))*AT96)/100),2)+ROUND(((ROUND((ROUND(((AE96-((EU96*1.2)))*AV96*1),2)*BS96),2)*AT96)/100),2)) -> 2132.57 | CZ96: =(ROUND((((S96+ROUND((ROUND((((EU96*1.2))*AV96*1),2)*BS96),2))*AU96)/100),2)+ROUND(((ROUND((ROUND(((AE96-((EU96*1.2)))*AV96*1),2)*BS96),2)*AU96)/100),2)) -> 1089.98 | DB96: 50 | DD96: *1 | DE96: *1,2 | DF96: *1,2 | DG96: *1,2 | DI96: *1,2 | DJ96: *1,2 | DN96: 0 | DO96: 0 | DP96: 1 | DQ96: 1 | DU96: 1013 | DV96: 1 ШТ. | DW96: 1 ШТ. | DX96: 1 | EE96: 57042958 | EF96: 40 | EG96: Монтаж оборудования | EH96: 0 | EJ96: 2 | EK96: 68 | EL96: ТСН-2001.4-10. Прокладка и монтаж сетей связи | EM96: ТСН-2001.4-10-1 | EO96: Поправка: Гл.12.Прил.8.п.8. 3_12.00.01.11.001 | EQ96: 1024 | ER96: 35.81 | ES96: 2.34 | ET96: 0 | EU96: 0 | EV96: 33.47 | EW96: 2.65 | EX96: 0 | EY96: 0 | FQ96: 0 | FR96: 0 | FS96: 0 | FX96: 90 | FY96: 46 | GD96: 1 | GF96: 1558984384 | GG96: 2 | GH96: 1 | GI96: 2 | GJ96: 0 | GK96: 0 | GL96: =ROUND(IF(AND(BH96=3,BI96=3,FS96<>0),P96,0),2) -> 0 | GM96: =ROUND(O96+X96+Y96,2)+GX96 -> 5616.03 | GN96: =IF(OR(BI96=0,BI96=1),GM96-GX96,0) -> 0 | GO96: =IF(BI96=2,GM96-GX96,0) -> 5616.03 | GP96: =IF(BI96=4,GM96-GX96,0) -> 0 | GR96: 0 | GS96: 3 | GT96: 0 | GV96: =ROUND((GT96),6) -> 0 | GW96: 1 | GX96: =ROUND(HC96*I96,2) -> 0 | HA96: 0 | HB96: 0 | HC96: =GV96*GW96 -> 0 | HS96: 0 | IK96: 0
A97: 17 | B97: 1 | F97: КА, п.3 | G97: Конвертер DAP-IP Sonar SNCA-8002 | H97: ШТ | I97: 1 | J97: 0 | K97: 1 | O97: =ROUND(CP97,2) -> 6828.38 | P97: =ROUND((ROUND((AC97*AW97*I97),2)*BC97),2) -> 6828.38 | Q97: =(ROUND((ROUND(((ET97)*AV97*I97),2)*BB97),2)+ROUND((ROUND(((AE97-(EU97))*AV97*I97),2)*BS97),2)) -> 0 | R97: =(ROUND((ROUND(((EU97)*AV97*I97),2)*BS97),2)+ROUND((ROUND(((AE97-(EU97))*AV97*I97),2)*BS97),2)) -> 0 | S97: =ROUND((ROUND((AF97*AV97*I97),2)*BA97),2) -> 0 | T97: =ROUND(CU97*I97,2) -> 0 | U97: =CV97*I97 -> 0 | V97: =CW97*I97 -> 0 | W97: =ROUND(CX97*I97,2) -> 0 | X97: =(ROUND((((S97+ROUND((ROUND(((EU97)*AV97*I97),2)*BS97),2))*AT97)/100),2)+ROUND(((ROUND((ROUND(((AE97-(EU97))*AV97*I97),2)*BS97),2)*AT97)/100),2)) -> 0 | Y97: =(ROUND((((S97+ROUND((ROUND(((EU97)*AV97*I97),2)*BS97),2))*AU97)/100),2)+ROUND(((ROUND((ROUND(((AE97-(EU97))*AV97*I97),2)*BS97),2)*AU97)/100),2)) -> 0 | AA97: -1 | AB97: =ROUND((AC97+AD97+AF97),6) -> 6828.38 | AC97: =ROUND((ES97),6) -> 6828.38 | AD97: =ROUND((((ET97)-(EU97))+AE97),6) -> 0 | AE97: =ROUND((EU97),6) -> 0 | AF97: =ROUND((EV97),6) -> 0 | AG97: =ROUND((AP97),6) -> 0 | AH97: =(EW97) -> 0 | AI97: =(EX97) -> 0 | AJ97: =(AS97) -> 0 | AK97: 6828.38 | AL97: 6828.38 | AM97: 0 | AN97: 0 | AO97: 0 | AP97: 0 | AQ97: 0 | AR97: 0 | AS97: 0 | AT97: 0 | AU97: 0 | AV97: 1 | AW97: 1 | AZ97: 1 | BA97: 1 | BB97: 1 | BC97: 1 | BH97: 3 | BI97: 3 | BJ97: КА, п.3 | BM97: 400007 | BN97: 0 | BP97: 0 | BQ97: 214 | BR97: 0 | BS97: 1 | BT97: 1 | BU97: 1 | BV97: 1 | BW97: 1 | BX97: 1 | BZ97: 0 | CA97: 0 | CE97: 1566 | CF97: 0 | CG97: 0 | CM97: 0 | CO97: 0 | CP97: =(P97+Q97+S97) -> 6828.38 | CQ97: =ROUND((ROUND((AC97*AW97*1),2)*BC97),2) -> 6828.38 | CR97: =(ROUND((ROUND(((ET97)*AV97*1),2)*BB97),2)+ROUND((ROUND(((AE97-(EU97))*AV97*1),2)*BS97),2)) -> 0 | CS97: =(ROUND((ROUND(((EU97)*AV97*1),2)*BS97),2)+ROUND((ROUND(((AE97-(EU97))*AV97*1),2)*BS97),2)) -> 0 | CT97: =ROUND((ROUND((AF97*AV97*1),2)*BA97),2) -> 0 | CU97: =AG97 -> 0 | CV97: =(AH97*AV97) -> 0 | CW97: =AI97 -> 0 | CX97: =AJ97 -> 0 | CY97: =(ROUND((((S97+ROUND((ROUND(((EU97)*AV97*1),2)*BS97),2))*AT97)/100),2)+ROUND(((ROUND((ROUND(((AE97-(EU97))*AV97*1),2)*BS97),2)*AT97)/100),2)) -> 0 | CZ97: =(ROUND((((S97+ROUND((ROUND(((EU97)*AV97*1),2)*BS97),2))*AU97)/100),2)+ROUND(((ROUND((ROUND(((AE97-(EU97))*AV97*1),2)*BS97),2)*AU97)/100),2)) -> 0 | DN97: 0 | DO97: 0 | DP97: 1 | DQ97: 1 | DU97: 1013 | DV97: ШТ | DW97: ШТ | DX97: 1 | EE97: 57042890 | EF97: 214 | EG97: Оборудование, отсутствующие в СНБ | EH97: 0 | EJ97: 3 | EK97: 400007 | EL97: Оборудование, отсутствующие в СНБ | EM97: Оборуд. КА | EQ97: 1040 | ER97: 0 | ES97: 6828.38 | ET97: 0 | EU97: 0 | EV97: 0 | EW97: 0 | EX97: 0 | EY97: 0 | FQ97: 0 | FR97: =P97 -> 6828.38 | FS97: 0 | FX97: 0 | FY97: 0 | GA97: [60 500 / 1,22 / 7,57] + 3% Трансп + 1,2% Заг.скл | GD97: 1 | GF97: 609121864 | GG97: 2 | GH97: 4 | GI97: -2 | GJ97: 0 | GK97: 0 | GL97: =ROUND(IF(AND(BH97=3,BI97=3,FS97<>0),P97,0),2) -> 0 | GM97: =ROUND(O97+X97+Y97,2)+GX97 -> 6828.38 | GN97: =IF(OR(BI97=0,BI97=1),GM97-GX97,0) -> 0 | GO97: =IF(BI97=2,GM97-GX97,0) -> 0 | GP97: =IF(BI97=4,GM97-GX97,0) -> 0 | GR97: 1 | GS97: 2 | GT97: 0 | GV97: =ROUND((GT97),6) -> 0 | GW97: 1 | GX97: =ROUND(HC97*I97,2) -> 0 | HA97: 0 | HB97: 0 | HC97: =GV97*GW97 -> 0 | HE97: 3 | HF97: 1,2 | HS97: 0 | IK97: 0
A98: 17 | B98: 1 | F98: КА, п.3 | G98: Конвертер DAP-IP Sonar SNCA-8002 | H98: ШТ | I98: 1 | J98: 0 | K98: 1 | O98: =ROUND(CP98,2) -> 51690.84 | P98: =ROUND((ROUND((AC98*AW98*I98),2)*BC98),2) -> 51690.84 | Q98: =(ROUND((ROUND(((ET98)*AV98*I98),2)*BB98),2)+ROUND((ROUND(((AE98-(EU98))*AV98*I98),2)*BS98),2)) -> 0 | R98: =(ROUND((ROUND(((EU98)*AV98*I98),2)*BS98),2)+ROUND((ROUND(((AE98-(EU98))*AV98*I98),2)*BS98),2)) -> 0 | S98: =ROUND((ROUND((AF98*AV98*I98),2)*BA98),2) -> 0 | T98: =ROUND(CU98*I98,2) -> 0 | U98: =CV98*I98 -> 0 | V98: =CW98*I98 -> 0 | W98: =ROUND(CX98*I98,2) -> 0 | X98: =(ROUND((((S98+ROUND((ROUND(((EU98)*AV98*I98),2)*BS98),2))*AT98)/100),2)+ROUND(((ROUND((ROUND(((AE98-(EU98))*AV98*I98),2)*BS98),2)*AT98)/100),2)) -> 0 | Y98: =(ROUND((((S98+ROUND((ROUND(((EU98)*AV98*I98),2)*BS98),2))*AU98)/100),2)+ROUND(((ROUND((ROUND(((AE98-(EU98))*AV98*I98),2)*BS98),2)*AU98)/100),2)) -> 0 | AA98: -1 | AB98: =ROUND((AC98+AD98+AF98),6) -> 6828.38 | AC98: =ROUND((ES98),6) -> 6828.38 | AD98: =ROUND((((ET98)-(EU98))+AE98),6) -> 0 | AE98: =ROUND((EU98),6) -> 0 | AF98: =ROUND((EV98),6) -> 0 | AG98: =ROUND((AP98),6) -> 0 | AH98: =(EW98) -> 0 | AI98: =(EX98) -> 0 | AJ98: =(AS98) -> 0 | AK98: 6828.38 | AL98: 6828.38 | AM98: 0 | AN98: 0 | AO98: 0 | AP98: 0 | AQ98: 0 | AR98: 0 | AS98: 0 | AT98: 0 | AU98: 0 | AV98: 1 | AW98: 1 | AZ98: 1 | BA98: 1 | BB98: 1 | BC98: 7.57 | BH98: 3 | BI98: 3 | BJ98: КА, п.3 | BM98: 400007 | BN98: 0 | BP98: 0 | BQ98: 214 | BR98: 0 | BS98: 1 | BT98: 1 | BU98: 1 | BV98: 1 | BW98: 1 | BX98: 1 | BZ98: 0 | CA98: 0 | CE98: 1566 | CF98: 0 | CG98: 0 | CM98: 0 | CO98: 0 | CP98: =(P98+Q98+S98) -> 51690.84 | CQ98: =ROUND((ROUND((AC98*AW98*1),2)*BC98),2) -> 51690.84 | CR98: =(ROUND((ROUND(((ET98)*AV98*1),2)*BB98),2)+ROUND((ROUND(((AE98-(EU98))*AV98*1),2)*BS98),2)) -> 0 | CS98: =(ROUND((ROUND(((EU98)*AV98*1),2)*BS98),2)+ROUND((ROUND(((AE98-(EU98))*AV98*1),2)*BS98),2)) -> 0 | CT98: =ROUND((ROUND((AF98*AV98*1),2)*BA98),2) -> 0 | CU98: =AG98 -> 0 | CV98: =(AH98*AV98) -> 0 | CW98: =AI98 -> 0 | CX98: =AJ98 -> 0 | CY98: =(ROUND((((S98+ROUND((ROUND(((EU98)*AV98*1),2)*BS98),2))*AT98)/100),2)+ROUND(((ROUND((ROUND(((AE98-(EU98))*AV98*1),2)*BS98),2)*AT98)/100),2)) -> 0 | CZ98: =(ROUND((((S98+ROUND((ROUND(((EU98)*AV98*1),2)*BS98),2))*AU98)/100),2)+ROUND(((ROUND((ROUND(((AE98-(EU98))*AV98*1),2)*BS98),2)*AU98)/100),2)) -> 0 | DN98: 0 | DO98: 0 | DP98: 1 | DQ98: 1 | DU98: 1013 | DV98: ШТ | DW98: ШТ | DX98: 1 | EE98: 57042890 | EF98: 214 | EG98: Оборудование, отсутствующие в СНБ | EH98: 0 | EJ98: 3 | EK98: 400007 | EL98: Оборудование, отсутствующие в СНБ | EM98: Оборуд. КА | EQ98: 1040 | ER98: 0 | ES98: 6828.38 | ET98: 0 | EU98: 0 | EV98: 0 | EW98: 0 | EX98: 0 | EY98: 0 | EZ98: 5 | FC98: 1 | FD98: 18 | FF98: 60500 | FQ98: 0 | FR98: =P98 -> 51690.84 | FS98: 0 | FX98: 0 | FY98: 0 | GA98: [60 500 / 1,22 / 7,57] + 3% Трансп + 1,2% Заг.скл | GD98: 1 | GF98: 609121864 | GG98: 2 | GH98: 3 | GI98: 5 | GJ98: 0 | GK98: 0 | GL98: =ROUND(IF(AND(BH98=3,BI98=3,FS98<>0),P98,0),2) -> 0 | GM98: =ROUND(O98+X98+Y98,2)+GX98 -> 51690.84 | GN98: =IF(OR(BI98=0,BI98=1),GM98-GX98,0) -> 0 | GO98: =IF(BI98=2,GM98-GX98,0) -> 0 | GP98: =IF(BI98=4,GM98-GX98,0) -> 0 | GR98: 1 | GS98: 1 | GT98: 0 | GV98: =ROUND((GT98),6) -> 0 | GW98: 1 | GX98: =ROUND(HC98*I98,2) -> 0 | HA98: 0 | HB98: 0 | HC98: =GV98*GW98 -> 0 | HE98: 3 | HF98: 1,2 | HS98: 0 | IK98: 0
A99: 17 | B99: 1 | C99: =ROW(SmtRes!A110) -> 110 | D99: =ROW(EtalonRes!A141) -> 141 | F99: 4.11-12-3 | G99: Установка съемных и выдвижных блоков (модулей, ячеек, ТЭЗ) массой до 20 кг | H99: 1 ШТ. | I99: 1 | J99: 0 | K99: 1 | O99: =ROUND(CP99,2) -> 46.31 | P99: =ROUND((ROUND((AC99*AW99*I99),2)*BC99),2) -> 0 | Q99: =(ROUND((ROUND((((ET99*1.2))*AV99*I99),2)*BB99),2)+ROUND((ROUND(((AE99-((EU99*1.2)))*AV99*I99),2)*BS99),2)) -> 2.4 | R99: =(ROUND((ROUND((((EU99*1.2))*AV99*I99),2)*BS99),2)+ROUND((ROUND(((AE99-((EU99*1.2)))*AV99*I99),2)*BS99),2)) -> 0.36 | S99: =ROUND((ROUND((AF99*AV99*I99),2)*BA99),2) -> 43.91 | T99: =ROUND(CU99*I99,2) -> 0 | U99: =CV99*I99 -> 3.882276 | V99: =CW99*I99 -> 0 | W99: =ROUND(CX99*I99,2) -> 0 | X99: =(ROUND((((S99+ROUND((ROUND((((EU99*1.2))*AV99*I99),2)*BS99),2))*AT99)/100),2)+ROUND(((ROUND((ROUND(((AE99-((EU99*1.2)))*AV99*I99),2)*BS99),2)*AT99)/100),2)) -> 39.84 | Y99: =(ROUND((((S99+ROUND((ROUND((((EU99*1.2))*AV99*I99),2)*BS99),2))*AU99)/100),2)+ROUND(((ROUND((ROUND(((AE99-((EU99*1.2)))*AV99*I99),2)*BS99),2)*AU99)/100),2)) -> 20.36 | AA99: -1 | AB99: =ROUND((AC99+AD99+AF99),6) -> 44.232 | AC99: =ROUND(((ES99*1)),6) -> 0 | AD99: =ROUND(((((ET99*1.2))-((EU99*1.2)))+AE99),6) -> 2.292 | AE99: =ROUND(((EU99*1.2)),6) -> 0.348 | AF99: =ROUND(((EV99*1.2)),6) -> 41.94 | AG99: =ROUND((AP99),6) -> 0 | AH99: =((EW99*1.2)) -> 3.708 | AI99: =((EX99*1.2)) -> 0 | AJ99: =(AS99) -> 0 | AK99: 36.86 | AL99: 0 | AM99: 1.91 | AN99: 0.29 | AO99: 34.95 | AP99: 0 | AQ99: 3.09 | AR99: 0 | AS99: 0 | AT99: 90 | AU99: 46 | AV99: 1.047 | AW99: 1 | AZ99: 1 | BA99: 1 | BB99: 1 | BC99: 1 | BH99: 0 | BI99: 2 | BJ99: ТСН-2001.4 Доп. 68, Сб. 11, т. 12, поз. 3 | BM99: 72 | BN99: 0 | BO99: 4.11-12-3 | BP99: 1 | BQ99: 40 | BR99: 0 | BS99: 1 | BT99: 1 | BU99: 1 | BV99: 1 | BW99: 1 | BX99: 1 | BZ99: 90 | CA99: 46 | CE99: 1566 | CF99: 0 | CG99: 0 | CM99: 0 | CN99: Поправка: Гл.12.Прил.8.п.8. 3_12.00.01.11.001 Наименование: При наличии напряженных и стесненных условий производства работ (стесненность, сложность складирования и транспортной логистики и т.п.) для объектов, расположенных в пределах круговой магистральной системы улиц "Садовое кольцо" города Москвы | CO99: 0 | CP99: =(P99+Q99+S99) -> 46.31 | CQ99: =ROUND((ROUND((AC99*AW99*1),2)*BC99),2) -> 0 | CR99: =(ROUND((ROUND((((ET99*1.2))*AV99*1),2)*BB99),2)+ROUND((ROUND(((AE99-((EU99*1.2)))*AV99*1),2)*BS99),2)) -> 2.4 | CS99: =(ROUND((ROUND((((EU99*1.2))*AV99*1),2)*BS99),2)+ROUND((ROUND(((AE99-((EU99*1.2)))*AV99*1),2)*BS99),2)) -> 0.36 | CT99: =ROUND((ROUND((AF99*AV99*1),2)*BA99),2) -> 43.91 | CU99: =AG99 -> 0 | CV99: =(AH99*AV99) -> 3.882276 | CW99: =AI99 -> 0 | CX99: =AJ99 -> 0 | CY99: =(ROUND((((S99+ROUND((ROUND((((EU99*1.2))*AV99*1),2)*BS99),2))*AT99)/100),2)+ROUND(((ROUND((ROUND(((AE99-((EU99*1.2)))*AV99*1),2)*BS99),2)*AT99)/100),2)) -> 39.84 | CZ99: =(ROUND((((S99+ROUND((ROUND((((EU99*1.2))*AV99*1),2)*BS99),2))*AU99)/100),2)+ROUND(((ROUND((ROUND(((AE99-((EU99*1.2)))*AV99*1),2)*BS99),2)*AU99)/100),2)) -> 20.36 | DB99: 51 | DD99: *1 | DE99: *1,2 | DF99: *1,2 | DG99: *1,2 | DI99: *1,2 | DJ99: *1,2 | DN99: 0 | DO99: 0 | DP99: 1 | DQ99: 1 | DU99: 1013 | DV99: 1 ШТ. | DW99: 1 ШТ. | DX99: 1 | EE99: 57042962 | EF99: 40 | EG99: Монтаж оборудования | EH99: 0 | EJ99: 2 | EK99: 72 | EL99: ТСН-2001.4-11. Приборы и средства автоматизации и вычислительной техники | EM99: ТСН-2001.4-11-1 | EO99: Поправка: Гл.12.Прил.8.п.8. 3_12.00.01.11.001 | EQ99: 1024 | ER99: 36.86 | ES99: 0 | ET99: 1.91 | EU99: 0.29 | EV99: 34.95 | EW99: 3.09 | EX99: 0 | EY99: 0 | FQ99: 0 | FR99: 0 | FS99: 0 | FX99: 90 | FY99: 46 | GD99: 1 | GF99: 1451808283 | GG99: 2 | GH99: 1 | GI99: 2 | GJ99: 0 | GK99: 0 | GL99: =ROUND(IF(AND(BH99=3,BI99=3,FS99<>0),P99,0),2) -> 0 | GM99: =ROUND(O99+X99+Y99,2)+GX99 -> 106.51 | GN99: =IF(OR(BI99=0,BI99=1),GM99-GX99,0) -> 0 | GO99: =IF(BI99=2,GM99-GX99,0) -> 106.51 | GP99: =IF(BI99=4,GM99-GX99,0) -> 0 | GR99: 0 | GS99: 3 | GT99: 0 | GV99: =ROUND((GT99),6) -> 0 | GW99: 1 | GX99: =ROUND(HC99*I99,2) -> 0 | HA99: 0 | HB99: 0 | HC99: =GV99*GW99 -> 0 | HS99: 0 | IK99: 0
A100: 17 | B100: 1 | C100: =ROW(SmtRes!A112) -> 112 | D100: =ROW(EtalonRes!A144) -> 144 | F100: 4.11-12-3 | G100: Установка съемных и выдвижных блоков (модулей, ячеек, ТЭЗ) массой до 20 кг | H100: 1 ШТ. | I100: 1 | J100: 0 | K100: 1 | O100: =ROUND(CP100,2) -> 2515.32 | P100: =ROUND((ROUND((AC100*AW100*I100),2)*BC100),2) -> 0 | Q100: =(ROUND((ROUND((((ET100*1.2))*AV100*I100),2)*BB100),2)+ROUND((ROUND(((AE100-((EU100*1.2)))*AV100*I100),2)*BS100),2)) -> 40.99 | R100: =(ROUND((ROUND((((EU100*1.2))*AV100*I100),2)*BS100),2)+ROUND((ROUND(((AE100-((EU100*1.2)))*AV100*I100),2)*BS100),2)) -> 20.29 | S100: =ROUND((ROUND((AF100*AV100*I100),2)*BA100),2) -> 2474.33 | T100: =ROUND(CU100*I100,2) -> 0 | U100: =CV100*I100 -> 3.882276 | V100: =CW100*I100 -> 0 | W100: =ROUND(CX100*I100,2) -> 0 | X100: =(ROUND((((S100+ROUND((ROUND((((EU100*1.2))*AV100*I100),2)*BS100),2))*AT100)/100),2)+ROUND(((ROUND((ROUND(((AE100-((EU100*1.2)))*AV100*I100),2)*BS100),2)*AT100)/100),2)) -> 2245.16 | Y100: =(ROUND((((S100+ROUND((ROUND((((EU100*1.2))*AV100*I100),2)*BS100),2))*AU100)/100),2)+ROUND(((ROUND((ROUND(((AE100-((EU100*1.2)))*AV100*I100),2)*BS100),2)*AU100)/100),2)) -> 1147.53 | AA100: -1 | AB100: =ROUND((AC100+AD100+AF100),6) -> 44.232 | AC100: =ROUND(((ES100*1)),6) -> 0 | AD100: =ROUND(((((ET100*1.2))-((EU100*1.2)))+AE100),6) -> 2.292 | AE100: =ROUND(((EU100*1.2)),6) -> 0.348 | AF100: =ROUND(((EV100*1.2)),6) -> 41.94 | AG100: =ROUND((AP100),6) -> 0 | AH100: =((EW100*1.2)) -> 3.708 | AI100: =((EX100*1.2)) -> 0 | AJ100: =(AS100) -> 0 | AK100: 36.86 | AL100: 0 | AM100: 1.91 | AN100: 0.29 | AO100: 34.95 | AP100: 0 | AQ100: 3.09 | AR100: 0 | AS100: 0 | AT100: 90 | AU100: 46 | AV100: 1.047 | AW100: 1 | AZ100: 1 | BA100: 56.35 | BB100: 17.08 | BC100: 1 | BH100: 0 | BI100: 2 | BJ100: ТСН-2001.4 Доп. 68, Сб. 11, т. 12, поз. 3 | BM100: 72 | BN100: 0 | BO100: 4.11-12-3 | BP100: 1 | BQ100: 40 | BR100: 0 | BS100: 56.35 | BT100: 1 | BU100: 1 | BV100: 1 | BW100: 1 | BX100: 1 | BZ100: 90 | CA100: 46 | CE100: 1566 | CF100: 0 | CG100: 0 | CM100: 0 | CN100: Поправка: Гл.12.Прил.8.п.8. 3_12.00.01.11.001 Наименование: При наличии напряженных и стесненных условий производства работ (стесненность, сложность складирования и транспортной логистики и т.п.) для объектов, расположенных в пределах круговой магистральной системы улиц "Садовое кольцо" города Москвы | CO100: 0 | CP100: =(P100+Q100+S100) -> 2515.32 | CQ100: =ROUND((ROUND((AC100*AW100*1),2)*BC100),2) -> 0 | CR100: =(ROUND((ROUND((((ET100*1.2))*AV100*1),2)*BB100),2)+ROUND((ROUND(((AE100-((EU100*1.2)))*AV100*1),2)*BS100),2)) -> 40.99 | CS100: =(ROUND((ROUND((((EU100*1.2))*AV100*1),2)*BS100),2)+ROUND((ROUND(((AE100-((EU100*1.2)))*AV100*1),2)*BS100),2)) -> 20.29 | CT100: =ROUND((ROUND((AF100*AV100*1),2)*BA100),2) -> 2474.33 | CU100: =AG100 -> 0 | CV100: =(AH100*AV100) -> 3.882276 | CW100: =AI100 -> 0 | CX100: =AJ100 -> 0 | CY100: =(ROUND((((S100+ROUND((ROUND((((EU100*1.2))*AV100*1),2)*BS100),2))*AT100)/100),2)+ROUND(((ROUND((ROUND(((AE100-((EU100*1.2)))*AV100*1),2)*BS100),2)*AT100)/100),2)) -> 2245.16 | CZ100: =(ROUND((((S100+ROUND((ROUND((((EU100*1.2))*AV100*1),2)*BS100),2))*AU100)/100),2)+ROUND(((ROUND((ROUND(((AE100-((EU100*1.2)))*AV100*1),2)*BS100),2)*AU100)/100),2)) -> 1147.53 | DB100: 52 | DD100: *1 | DE100: *1,2 | DF100: *1,2 | DG100: *1,2 | DI100: *1,2 | DJ100: *1,2 | DN100: 0 | DO100: 0 | DP100: 1 | DQ100: 1 | DU100: 1013 | DV100: 1 ШТ. | DW100: 1 ШТ. | DX100: 1 | EE100: 57042962 | EF100: 40 | EG100: Монтаж оборудования | EH100: 0 | EJ100: 2 | EK100: 72 | EL100: ТСН-2001.4-11. Приборы и средства автоматизации и вычислительной техники | EM100: ТСН-2001.4-11-1 | EO100: Поправка: Гл.12.Прил.8.п.8. 3_12.00.01.11.001 | EQ100: 1024 | ER100: 36.86 | ES100: 0 | ET100: 1.91 | EU100: 0.29 | EV100: 34.95 | EW100: 3.09 | EX100: 0 | EY100: 0 | FQ100: 0 | FR100: 0 | FS100: 0 | FX100: 90 | FY100: 46 | GD100: 1 | GF100: 1451808283 | GG100: 2 | GH100: 1 | GI100: 2 | GJ100: 0 | GK100: 0 | GL100: =ROUND(IF(AND(BH100=3,BI100=3,FS100<>0),P100,0),2) -> 0 | GM100: =ROUND(O100+X100+Y100,2)+GX100 -> 5908.01 | GN100: =IF(OR(BI100=0,BI100=1),GM100-GX100,0) -> 0 | GO100: =IF(BI100=2,GM100-GX100,0) -> 5908.01 | GP100: =IF(BI100=4,GM100-GX100,0) -> 0 | GR100: 0 | GS100: 3 | GT100: 0 | GV100: =ROUND((GT100),6) -> 0 | GW100: 1 | GX100: =ROUND(HC100*I100,2) -> 0 | HA100: 0 | HB100: 0 | HC100: =GV100*GW100 -> 0 | HS100: 0 | IK100: 0
A101: 17 | B101: 1 | C101: =ROW(SmtRes!A113) -> 113 | D101: =ROW(EtalonRes!A145) -> 145 | F101: 4.10-80-1 | G101: Аппараты приемные, приборы ПС приемно-контрольные, пусковые, концентратор, блок базовый на 10 лучей | H101: 1 ШТ. | I101: 1 | J101: 0 | K101: 1 | O101: =ROUND(CP101,2) -> 132.02 | P101: =ROUND((ROUND((AC101*AW101*I101),2)*BC101),2) -> 12.53 | Q101: =(ROUND((ROUND((((ET101*1.2))*AV101*I101),2)*BB101),2)+ROUND((ROUND(((AE101-((EU101*1.2)))*AV101*I101),2)*BS101),2)) -> 0.08 | R101: =(ROUND((ROUND((((EU101*1.2))*AV101*I101),2)*BS101),2)+ROUND((ROUND(((AE101-((EU101*1.2)))*AV101*I101),2)*BS101),2)) -> 0.01 | S101: =ROUND((ROUND((AF101*AV101*I101),2)*BA101),2) -> 119.41 | T101: =ROUND(CU101*I101,2) -> 0 | U101: =CV101*I101 -> 9.04608 | V101: =CW101*I101 -> 0 | W101: =ROUND(CX101*I101,2) -> 0 | X101: =(ROUND((((S101+ROUND((ROUND((((EU101*1.2))*AV101*I101),2)*BS101),2))*AT101)/100),2)+ROUND(((ROUND((ROUND(((AE101-((EU101*1.2)))*AV101*I101),2)*BS101),2)*AT101)/100),2)) -> 107.48 | Y101: =(ROUND((((S101+ROUND((ROUND((((EU101*1.2))*AV101*I101),2)*BS101),2))*AU101)/100),2)+ROUND(((ROUND((ROUND(((AE101-((EU101*1.2)))*AV101*I101),2)*BS101),2)*AU101)/100),2)) -> 54.93 | AA101: -1 | AB101: =ROUND((AC101+AD101+AF101),6) -> 126.65 | AC101: =ROUND(((ES101*1)),6) -> 12.53 | AD101: =ROUND(((((ET101*1.2))-((EU101*1.2)))+AE101),6) -> 0.072 | AE101: =ROUND(((EU101*1.2)),6) -> 0.012 | AF101: =ROUND(((EV101*1.2)),6) -> 114.048 | AG101: =ROUND((AP101),6) -> 0 | AH101: =((EW101*1.2)) -> 8.64 | AI101: =((EX101*1.2)) -> 0 | AJ101: =(AS101) -> 0 | AK101: 107.63 | AL101: 12.53 | AM101: 0.06 | AN101: 0.01 | AO101: 95.04 | AP101: 0 | AQ101: 7.2 | AR101: 0 | AS101: 0 | AT101: 90 | AU101: 46 | AV101: 1.047 | AW101: 1 | AZ101: 1 | BA101: 1 | BB101: 1 | BC101: 1 | BH101: 0 | BI101: 2 | BJ101: ТСН-2001.4 Доп. 68, Сб. 10, т. 80, поз. 1 | BM101: 68 | BN101: 0 | BO101: 4.10-80-1 | BP101: 1 | BQ101: 40 | BR101: 0 | BS101: 1 | BT101: 1 | BU101: 1 | BV101: 1 | BW101: 1 | BX101: 1 | BZ101: 90 | CA101: 46 | CE101: 1566 | CF101: 0 | CG101: 0 | CM101: 0 | CN101: Поправка: Гл.12.Прил.8.п.8. 3_12.00.01.11.001 Наименование: При наличии напряженных и стесненных условий производства работ (стесненность, сложность складирования и транспортной логистики и т.п.) для объектов, расположенных в пределах круговой магистральной системы улиц "Садовое кольцо" города Москвы | CO101: 0 | CP101: =(P101+Q101+S101) -> 132.02 | CQ101: =ROUND((ROUND((AC101*AW101*1),2)*BC101),2) -> 12.53 | CR101: =(ROUND((ROUND((((ET101*1.2))*AV101*1),2)*BB101),2)+ROUND((ROUND(((AE101-((EU101*1.2)))*AV101*1),2)*BS101),2)) -> 0.08 | CS101: =(ROUND((ROUND((((EU101*1.2))*AV101*1),2)*BS101),2)+ROUND((ROUND(((AE101-((EU101*1.2)))*AV101*1),2)*BS101),2)) -> 0.01 | CT101: =ROUND((ROUND((AF101*AV101*1),2)*BA101),2) -> 119.41 | CU101: =AG101 -> 0 | CV101: =(AH101*AV101) -> 9.04608 | CW101: =AI101 -> 0 | CX101: =AJ101 -> 0 | CY101: =(ROUND((((S101+ROUND((ROUND((((EU101*1.2))*AV101*1),2)*BS101),2))*AT101)/100),2)+ROUND(((ROUND((ROUND(((AE101-((EU101*1.2)))*AV101*1),2)*BS101),2)*AT101)/100),2)) -> 107.48 | CZ101: =(ROUND((((S101+ROUND((ROUND((((EU101*1.2))*AV101*1),2)*BS101),2))*AU101)/100),2)+ROUND(((ROUND((ROUND(((AE101-((EU101*1.2)))*AV101*1),2)*BS101),2)*AU101)/100),2)) -> 54.93 | DB101: 53 | DD101: *1 | DE101: *1,2 | DF101: *1,2 | DG101: *1,2 | DI101: *1,2 | DJ101: *1,2 | DN101: 0 | DO101: 0 | DP101: 1 | DQ101: 1 | DU101: 1013 | DV101: 1 ШТ. | DW101: 1 ШТ. | DX101: 1 | EE101: 57042958 | EF101: 40 | EG101: Монтаж оборудования | EH101: 0 | EJ101: 2 | EK101: 68 | EL101: ТСН-2001.4-10. Прокладка и монтаж сетей связи | EM101: ТСН-2001.4-10-1 | EO101: Поправка: Гл.12.Прил.8.п.8. 3_12.00.01.11.001 | EQ101: 1024 | ER101: 107.63 | ES101: 12.53 | ET101: 0.06 | EU101: 0.01 | EV101: 95.04 | EW101: 7.2 | EX101: 0 | EY101: 0 | FQ101: 0 | FR101: 0 | FS101: 0 | FX101: 90 | FY101: 46 | GD101: 1 | GF101: -488197810 | GG101: 2 | GH101: 1 | GI101: 2 | GJ101: 0 | GK101: 0 | GL101: =ROUND(IF(AND(BH101=3,BI101=3,FS101<>0),P101,0),2) -> 0 | GM101: =ROUND(O101+X101+Y101,2)+GX101 -> 294.43 | GN101: =IF(OR(BI101=0,BI101=1),GM101-GX101,0) -> 0 | GO101: =IF(BI101=2,GM101-GX101,0) -> 294.43 | GP101: =IF(BI101=4,GM101-GX101,0) -> 0 | GR101: 0 | GS101: 3 | GT101: 0 | GV101: =ROUND((GT101),6) -> 0 | GW101: 1 | GX101: =ROUND(HC101*I101,2) -> 0 | HA101: 0 | HB101: 0 | HC101: =GV101*GW101 -> 0 | HS101: 0 | IK101: 0
