Workbook

Sheet Смета по ТСН-2001(с доп.67
A1: =Source!B1 -> Smeta.RU (495) 974-1589
J2: Форма № 4б
B3: "СОГЛАСОВАНО" | G3: "УТВЕРЖДАЮ"
B6: =CONCATENATE("______________________ ", IF(Source!AL12<>"", Source!AL12, "")) -> ______________________ | G6: =CONCATENATE("______________________ ", IF(Source!AH12<>"", Source!AH12, "")) -> ______________________
B7: "_____"________________ 2026 г. | G7: "_____"________________ 2026 г.
A10: Капитальный ремонт здания Государственного бюджетного общеобразовательного учреждения города Москвы «Школа №1574», расположенного по адресу: г. Москва, Старопименовский переулок, д. 5. 1 этап. | AP10: Капитальный ремонт здания Государственного бюджетного общеобразовательного учреждения города Москвы «Школа №1574», расположенного по адресу: г. Москва, Старопименовский переулок, д. 5. 1 этап. 02-01-11 РТС
A11: (наименование стройки и/или объекта)
A13: =CONCATENATE( "ЛОКАЛЬНАЯ СМЕТА № ",IF(Source!F12<>"Новый объект", Source!F12, "")) -> ЛОКАЛЬНАЯ СМЕТА № 02-01-11
A15: =Source!G20 -> Радиотрансляционная сеть
A16: (наименование работ и затрат)
A18: =CONCATENATE( "Основание: чертежи № ", Source!J12) -> Основание: чертежи № 2024-00375-01-0-ИОС5.4
I20: В базисном уровне цен | J20: В текущем уровне цен
E21: Сметная стоимость | I21: =I22+I23+I24+I25 -> 243.21 | J21: =J22+J23+J24+J25 -> 2138.84 | K21: тыс.руб.
E22: Строительные работы | I22: =ROUND((Source!F360)/1000, 2) -> 1.45 | J22: =ROUND((Source!P360)/1000, 2) -> 81.46 | K22: тыс.руб.
E23: Работы по монтажу оборудования | I23: =ROUND((Source!F361)/1000, 2) -> 65.01 | J23: =ROUND((Source!P361)/1000, 2) -> 715.11 | K23: тыс.руб.
E24: Оборудование | I24: =ROUND((Source!F352)/1000, 2) -> 176.75 | J24: =ROUND((Source!P352)/1000, 2) -> 1342.27 | K24: тыс.руб.
E25: Прочие работы и затраты | I25: =ROUND((Source!F362+Source!F363)/1000, 2) -> 0 | J25: =ROUND((Source!P362+Source!P363)/1000, 2) -> 0 | K25: тыс.руб.
E26: Средства на оплату труда | I26: =(Source!F358+ Source!F357)/1000 -> 4.49723 | J26: =((Source!P358 + Source!P357)/1000) -> 253.41891 | K26: тыс.руб.
E27: Затраты труда | I27: =Source!F365 -> 366.44694 | K27: чел.-ч.
E28: Кроме того:
E29: Возврат материалов | I29: =SUM(Y1:Y456)/1000 -> 0 | J29: =SUM(Z1:Z456)/1000 -> 0 | K29: тыс.руб.
A31: Составлен(а) по ТСН-2001 с учетом Дополнения №: 81
A32: № и период сборника коэффициентов (индексов) пересчета: Коэффициенты к ТСН-2001 МГЭ Дополнение 81, строительство №219/81 I квартал 2026 года и Коэффициенты к ТСН-2001.13-2 Дополнение 47 №64/47 I квартал 2026 года | AP32: № и период сборника коэффициентов (индексов) пересчета: Коэффициенты к ТСН-2001 МГЭ Дополнение 81, строительство №219/81 I квартал 2026 года и Коэффициенты к ТСН-2001.13-2 Дополнение 47 №64/47 I квартал 2026 года
A33: № п/п | B33: Шифр расценки и коды ресурсов | C33: Наименование работ и затрат | D33: Ед. изм. | E33: Кол-во единиц | F33: Цена на ед. изм., руб. | G33: Попра- вочные коэффи- циенты | H33: Коэффи- циенты зимних удорожа- ний | I33: Всего в ценах на январь 2000 года, руб. | J33: Коэффи- циенты (индек- сы) пере- счета, нормы НР и СП | K33: ВСЕГО затрат в текущем уровне цен, руб.
A34: 1 | B34: 2 | C34: 3 | D34: 4 | E34: 5 | F34: 6 | G34: 7 | H34: 8 | I34: 9 | J34: 10 | K34: 11
A36: =CONCATENATE("Локальная смета: ",IF(Source!G20<>"Новая локальная смета", Source!G20, "")) -> Локальная смета: Радиотрансляционная сеть
A38: =CONCATENATE("Раздел: ",IF(Source!G24<>"Новый раздел", Source!G24, "")) -> Раздел: Демонтажные работы
A39: 1 | B39: =Source!F28 -> 4.10-73-1 | C39: Монтаж радиостанции УКВ связи абонентской мощностью до 15 Вт стационарной / демонтаж устройства подачи программ вещания | D39: =Source!H28 -> 1 комплект | E39: =Source!I28 -> 1 | Q39: =Source!X28 -> 45.19 | R39: =Source!X29 -> 2546.54 | S39: =Source!Y28 -> 25.21 | T39: =Source!Y29 -> 1420.7 | U39: =ROUND((175/100)*ROUND(Source!R28, 2), 2) -> 0 | V39: =ROUND((0/100)*ROUND(Source!R29, 2), 2) -> 0 | AC39: 0
C40: ЗП | F40: =Source!AO28 -> 126.2 | G40: 1,2*0,3 | H40: =Source!AV29 -> 1.047 | I40: =Source!S28 -> 47.57 | J40: =IF(Source!BA29<> 0, Source!BA29, 1) -> 56.35 | K40: =Source!S29 -> 2680.57
C41: НР от ФОТ | D41: % | E41: =Source!BZ29 -> 95 | I41: =SUM(Q39:Q40) -> 45.19 | J41: =Source!AT29 -> 95 | K41: =SUM(R39:R40) -> 2546.54
C42: СП от ФОТ | D42: % | E42: =Source!CA29 -> 53 | I42: =SUM(S39:S41) -> 25.21 | J42: =Source!AU29 -> 53 | K42: =SUM(T39:T41) -> 1420.7
C43: ЗТР | D43: чел-ч | E43: =Source!AQ28 -> 10 | G43: 1,2*0,3 | H43: =Source!AV29 -> 1.047 | I43: =Source!U28 -> 3.7692
C44: ВСЕГО работ по позиции: | H44: =I40+I41+I42+0-0-0 -> 117.97 | J44: =K40+K41+K42+0-0-0 -> 6647.81
C45: ВСЕГО оборудование по позиции: | H45: =0+0 -> 0 | J45: =0+0 -> 0
C46: ВСЕГО по позиции: | H46: =I40+I41+I42+0 -> 117.97 | J46: =K40+K41+K42+0 -> 6647.81 | O46: =I40+I41+I42+0 -> 117.97 | P46: =K40+K41+K42+0 -> 6647.81
A48: 2 | B48: =Source!F30 -> 4.10-32-4 | C48: Монтаж платы дополнительной, устанавливаемой на готовом месте стойки / демонтаж модуля для приема интернет вещания радиостанции | D48: =Source!H30 -> 1 ШТ. | E48: =Source!I30 -> 1 | Q48: =Source!X30 -> 8.31 | R48: =Source!X31 -> 468.1 | S48: =Source!Y30 -> 4.25 | T48: =Source!Y31 -> 239.25 | U48: =ROUND((175/100)*ROUND(Source!R30, 2), 2) -> 0.67 | V48: =ROUND((0/100)*ROUND(Source!R31, 2), 2) -> 0 | AC48: 0
C49: ЗП | F49: =Source!AO30 -> 23.48 | G49: 1,2*0,3 | H49: =Source!AV31 -> 1.047 | I49: =Source!S30 -> 8.85 | J49: =IF(Source!BA31<> 0, Source!BA31, 1) -> 56.35 | K49: =Source!S31 -> 498.7
C50: ЭМ | F50: =Source!AM30 -> 9.19 | G50: 1,2*0,3 | H50: =Source!AV31 -> 1.047 | I50: =Source!Q30 -> 3.46 | J50: =IF(Source!BB31<> 0, Source!BB31, 1) -> 16.15 | K50: =Source!Q31 -> 55.88
C51: в т.ч. ЗПМ | F51: =Source!AN30 -> 1.01 | G51: 1,2*0,3 | H51: =Source!AV31 -> 1.047 | I51: =Source!R30 -> 0.38 | J51: =IF(Source!BS31<> 0, Source!BS31, 1) -> 56.35 | K51: =Source!R31 -> 21.41
C52: НР от ФОТ | D52: % | E52: =Source!BZ31 -> 90 | I52: =SUM(Q48:Q51) -> 8.31 | J52: =Source!AT31 -> 90 | K52: =SUM(R48:R51) -> 468.1
C53: СП от ФОТ | D53: % | E53: =Source!CA31 -> 46 | I53: =SUM(S48:S52) -> 4.25 | J53: =Source!AU31 -> 46 | K53: =SUM(T48:T52) -> 239.25
C54: ЗТР | D54: чел-ч | E54: =Source!AQ30 -> 2.1 | G54: 1,2*0,3 | H54: =Source!AV31 -> 1.047 | I54: =Source!U30 -> 0.791532
C55: ВСЕГО работ по позиции: | H55: =I49+I50+I52+I53+0-0-0 -> 24.87 | J55: =K49+K50+K52+K53+0-0-0 -> 1261.93
C56: ВСЕГО оборудование по позиции: | H56: =0+0 -> 0 | J56: =0+0 -> 0
C57: ВСЕГО по позиции: | H57: =I49+I50+I52+I53+0 -> 24.87 | J57: =K49+K50+K52+K53+0 -> 1261.93 | O57: =I49+I50+I52+I53+0 -> 24.87 | P57: =K49+K50+K52+K53+0 -> 1261.93
A59: 3 | B59: =Source!F32 -> 4.10-134-4 | C59: Монтаж антенны коллективной для приема ТВ на антенной опоре высотой до 9 м с одним ярусом оттяжек / демонтаж антенны | D59: =Source!H32 -> 1 антенна | E59: =Source!I32 -> 1 | Q59: =Source!X32 -> 28.31 | R59: =Source!X33 -> 1595.27 | S59: =Source!Y32 -> 15.79 | T59: =Source!Y33 -> 889.99 | U59: =ROUND((175/100)*ROUND(Source!R32, 2), 2) -> 0 | V59: =ROUND((0/100)*ROUND(Source!R33, 2), 2) -> 0 | AC59: 0
C60: ЗП | F60: =Source!AO32 -> 76.15 | G60: 1,2*0,3 | H60: =Source!AV33 -> 1.087 | I60: =Source!S32 -> 29.8 | J60: =IF(Source!BA33<> 0, Source!BA33, 1) -> 56.35 | K60: =Source!S33 -> 1679.23
C61: НР от ФОТ | D61: % | E61: =Source!BZ33 -> 95 | I61: =SUM(Q59:Q60) -> 28.31 | J61: =Source!AT33 -> 95 | K61: =SUM(R59:R60) -> 1595.27
C62: СП от ФОТ | D62: % | E62: =Source!CA33 -> 53 | I62: =SUM(S59:S61) -> 15.79 | J62: =Source!AU33 -> 53 | K62: =SUM(T59:T61) -> 889.99
C63: ЗТР | D63: чел-ч | E63: =Source!AQ32 -> 5.37 | G63: 1,2*0,3 | H63: =Source!AV33 -> 1.087 | I63: =Source!U32 -> 2.1013884
C64: ВСЕГО работ по позиции: | H64: =I60+I61+I62+0-0-0 -> 73.9 | J64: =K60+K61+K62+0-0-0 -> 4164.49
C65: ВСЕГО оборудование по позиции: | H65: =0+0 -> 0 | J65: =0+0 -> 0
C66: ВСЕГО по позиции: | H66: =I60+I61+I62+0 -> 73.9 | J66: =K60+K61+K62+0 -> 4164.49 | O66: =I60+I61+I62+0 -> 73.9 | P66: =K60+K61+K62+0 -> 4164.49
A68: 4 | B68: =Source!F34 -> 4.10-21-5 | C68: Грозозащита для воздушных абонентских линий / демонтаж грозозащиты | D68: =Source!H34 -> 1 комплект | E68: =Source!I34 -> 1 | Q68: =Source!X34 -> 12.84 | R68: =Source!X35 -> 723.7 | S68: =Source!Y34 -> 6.56 | T68: =Source!Y35 -> 369.89 | U68: =ROUND((175/100)*ROUND(Source!R34, 2), 2) -> 0 | V68: =ROUND((0/100)*ROUND(Source!R35, 2), 2) -> 0 | AC68: 0
C69: ЗП | F69: =Source!AO34 -> 37.86 | G69: 1,2*0,3 | H69: =Source!AV35 -> 1.047 | I69: =Source!S34 -> 14.27 | J69: =IF(Source!BA35<> 0, Source!BA35, 1) -> 56.35 | K69: =Source!S35 -> 804.11
C70: НР от ФОТ | D70: % | E70: =Source!BZ35 -> 90 | I70: =SUM(Q68:Q69) -> 12.84 | J70: =Source!AT35 -> 90 | K70: =SUM(R68:R69) -> 723.7
C71: СП от ФОТ | D71: % | E71: =Source!CA35 -> 46 | I71: =SUM(S68:S70) -> 6.56 | J71: =Source!AU35 -> 46 | K71: =SUM(T68:T70) -> 369.89
C72: ЗТР | D72: чел-ч | E72: =Source!AQ34 -> 3 | G72: 1,2*0,3 | H72: =Source!AV35 -> 1.047 | I72: =Source!U34 -> 1.13076
C73: ВСЕГО работ по позиции: | H73: =I69+I70+I71+0-0-0 -> 33.67 | J73: =K69+K70+K71+0-0-0 -> 1897.7
C74: ВСЕГО оборудование по позиции: | H74: =0+0 -> 0 | J74: =0+0 -> 0
C75: ВСЕГО по позиции: | H75: =I69+I70+I71+0 -> 33.67 | J75: =K69+K70+K71+0 -> 1897.7 | O75: =I69+I70+I71+0 -> 33.67 | P75: =K69+K70+K71+0 -> 1897.7
A77: 5 | B77: =Source!F36 -> 4.10-118-12 | C77: Установка для трубных проводок коробки оконечной / демонтаж | D77: =Source!H36 -> 100 шт. | E77: =Source!I36 -> 0.07 | Q77: =Source!X36 -> 6.62 | R77: =Source!X37 -> 372.75 | S77: =Source!Y36 -> 3.38 | T77: =Source!Y37 -> 190.52 | U77: =ROUND((175/100)*ROUND(Source!R36, 2), 2) -> 0 | V77: =ROUND((0/100)*ROUND(Source!R37, 2), 2) -> 0 | AC77: 0
C78: ="Объем: "&Source!I36&"=7/"&"100" -> Объем: 0,07=7/100
C79: ЗП | F79: =Source!AO36 -> 278.64 | G79: 1,2*0,3 | H79: =Source!AV37 -> 1.047 | I79: =Source!S36 -> 7.35 | J79: =IF(Source!BA37<> 0, Source!BA37, 1) -> 56.35 | K79: =Source!S37 -> 414.17
C80: НР от ФОТ | D80: % | E80: =Source!BZ37 -> 90 | I80: =SUM(Q77:Q79) -> 6.62 | J80: =Source!AT37 -> 90 | K80: =SUM(R77:R79) -> 372.75
C81: СП от ФОТ | D81: % | E81: =Source!CA37 -> 46 | I81: =SUM(S77:S80) -> 3.38 | J81: =Source!AU37 -> 46 | K81: =SUM(T77:T80) -> 190.52
C82: ЗТР | D82: чел-ч | E82: =Source!AQ36 -> 24 | G82: 1,2*0,3 | H82: =Source!AV37 -> 1.047 | I82: =Source!U36 -> 0.6332256
C83: ВСЕГО работ по позиции: | H83: =I79+I80+I81+0-0-0 -> 17.35 | J83: =K79+K80+K81+0-0-0 -> 977.44
C84: ВСЕГО оборудование по позиции: | H84: =0+0 -> 0 | J84: =0+0 -> 0
C85: ВСЕГО по позиции: | H85: =I79+I80+I81+0 -> 17.35 | J85: =K79+K80+K81+0 -> 977.44 | O85: =I79+I80+I81+0 -> 17.35 | P85: =K79+K80+K81+0 -> 977.44
A87: 6 | B87: =Source!F38 -> 6.67-7-1 | C87: Демонтаж осветительных приборов, выключатели, розетки | D87: =Source!H38 -> 100 шт. | E87: =Source!I38 -> 0.06 | Q87: =Source!X38 -> 4.1 | R87: =Source!X39 -> 230.76 | S87: =Source!Y38 -> 2.16 | T87: =Source!Y39 -> 121.72 | U87: =ROUND((175/100)*ROUND(Source!R38, 2), 2) -> 0 | V87: =ROUND((0/100)*ROUND(Source!R39, 2), 2) -> 0 | AC87: 0
C88: ="Объем: "&Source!I38&"=6/"&"100" -> Объем: 0,06=6/100
C89: ЗП | F89: =Source!AO38 -> 59.68 | G89: 1,2 | H89: =Source!AV39 -> 1.047 | I89: =Source!S38 -> 4.5 | J89: =IF(Source!BA39<> 0, Source!BA39, 1) -> 56.35 | K89: =Source!S39 -> 253.58
C90: НР от ФОТ | D90: % | E90: =Source!BZ39 -> 91 | I90: =SUM(Q87:Q89) -> 4.1 | J90: =Source!AT39 -> 91 | K90: =SUM(R87:R89) -> 230.76
C91: СП от ФОТ | D91: % | E91: =Source!CA39 -> 48 | I91: =SUM(S87:S90) -> 2.16 | J91: =Source!AU39 -> 48 | K91: =SUM(T87:T90) -> 121.72
C92: ЗТР | D92: чел-ч | E92: =Source!AQ38 -> 5.84 | G92: 1,2 | H92: =Source!AV39 -> 1.047 | I92: =Source!U38 -> 0.44024256
C93: ВСЕГО работ по позиции: | H93: =I89+I90+I91+0-0-0 -> 10.76 | J93: =K89+K90+K91+0-0-0 -> 606.06
C94: ВСЕГО оборудование по позиции: | H94: =0+0 -> 0 | J94: =0+0 -> 0
C95: ВСЕГО по позиции: | H95: =I89+I90+I91+0 -> 10.76 | J95: =K89+K90+K91+0 -> 606.06 | O95: =I89+I90+I91+0 -> 10.76 | P95: =K89+K90+K91+0 -> 606.06
A97: 7 | B97: =Source!F40 -> 4.11-7-1 | C97: Установка аппарата настольного массой до 0,015 т / демонтаж приёмника | D97: =Source!H40 -> 1 ШТ. | E97: =Source!I40 -> 6 | Q97: =Source!X40 -> 27.56 | R97: =Source!X41 -> 1552.9 | S97: =Source!Y40 -> 14.09 | T97: =Source!Y41 -> 793.7 | U97: =ROUND((175/100)*ROUND(Source!R40, 2), 2) -> 8 | V97: =ROUND((0/100)*ROUND(Source!R41, 2), 2) -> 0 | AC97: 0
C98: ЗП | F98: =Source!AO40 -> 11.52 | G98: 1,2*0,3 | H98: =Source!AV41 -> 1.047 | I98: =Source!S40 -> 26.05 | J98: =IF(Source!BA41<> 0, Source!BA41, 1) -> 56.35 | K98: =Source!S41 -> 1467.92
C99: ЭМ | F99: =Source!AM40 -> 13.3 | G99: 1,2*0,3 | H99: =Source!AV41 -> 1.047 | I99: =Source!Q40 -> 30.08 | J99: =IF(Source!BB41<> 0, Source!BB41, 1) -> 17.06 | K99: =Source!Q41 -> 513.16
C100: в т.ч. ЗПМ | F100: =Source!AN40 -> 2.02 | G100: 1,2*0,3 | H100: =Source!AV41 -> 1.047 | I100: =Source!R40 -> 4.57 | J100: =IF(Source!BS41<> 0, Source!BS41, 1) -> 56.35 | K100: =Source!R41 -> 257.52
C101: НР от ФОТ | D101: % | E101: =Source!BZ41 -> 90 | I101: =SUM(Q97:Q100) -> 27.56 | J101: =Source!AT41 -> 90 | K101: =SUM(R97:R100) -> 1552.9
C102: СП от ФОТ | D102: % | E102: =Source!CA41 -> 46 | I102: =SUM(S97:S101) -> 14.09 | J102: =Source!AU41 -> 46 | K102: =SUM(T97:T101) -> 793.7
C103: ЗТР | D103: чел-ч | E103: =Source!AQ40 -> 1.03 | G103: 1,2*0,3 | H103: =Source!AV41 -> 1.047 | I103: =Source!U40 -> 2.3293656
C104: ВСЕГО работ по позиции: | H104: =I98+I99+I101+I102+0-0-0 -> 97.78 | J104: =K98+K99+K101+K102+0-0-0 -> 4327.68
C105: ВСЕГО оборудование по позиции: | H105: =0+0 -> 0 | J105: =0+0 -> 0
C106: ВСЕГО по позиции: | H106: =I98+I99+I101+I102+0 -> 97.78 | J106: =K98+K99+K101+K102+0 -> 4327.68 | O106: =I98+I99+I101+I102+0 -> 97.78 | P106: =K98+K99+K101+K102+0 -> 4327.68
A108: 8 | B108: =Source!F42 -> 4.10-69-3 | C108: Монтаж щита распределительного настенного типа / демонтаж шкафа с объектовой станцией | D108: =Source!H42 -> 1 ШТ. | E108: =Source!I42 -> 1 | Q108: =Source!X42 -> 160.23 | R108: =Source!X43 -> 9028.79 | S108: =Source!Y42 -> 89.39 | T108: =Source!Y43 -> 5037.11 | U108: =ROUND((175/100)*ROUND(Source!R42, 2), 2) -> 0 | V108: =ROUND((0/100)*ROUND(Source!R43, 2), 2) -> 0 | AC108: 0
C109: ЗП | F109: =Source!AO42 -> 447.48 | G109: 1,2*0,3 | H109: =Source!AV43 -> 1.047 | I109: =Source!S42 -> 168.66 | J109: =IF(Source!BA43<> 0, Source!BA43, 1) -> 56.35 | K109: =Source!S43 -> 9503.99
C110: НР от ФОТ | D110: % | E110: =Source!BZ43 -> 95 | I110: =SUM(Q108:Q109) -> 160.23 | J110: =Source!AT43 -> 95 | K110: =SUM(R108:R109) -> 9028.79
C111: СП от ФОТ | D111: % | E111: =Source!CA43 -> 53 | I111: =SUM(S108:S110) -> 89.39 | J111: =Source!AU43 -> 53 | K111: =SUM(T108:T110) -> 5037.11
C112: ЗТР | D112: чел-ч | E112: =Source!AQ42 -> 33 | G112: 1,2*0,3 | H112: =Source!AV43 -> 1.047 | I112: =Source!U42 -> 12.43836
C113: ВСЕГО работ по позиции: | H113: =I109+I110+I111+0-0-0 -> 418.28 | J113: =K109+K110+K111+0-0-0 -> 23569.89
C114: ВСЕГО оборудование по позиции: | H114: =0+0 -> 0 | J114: =0+0 -> 0
C115: ВСЕГО по позиции: | H115: =I109+I110+I111+0 -> 418.28 | J115: =K109+K110+K111+0 -> 23569.89 | O115: =I109+I110+I111+0 -> 418.28 | P115: =K109+K110+K111+0 -> 23569.89
A117: 9 | B117: =Source!F44 -> 4.10-73-1 | C117: Монтаж радиостанции УКВ связи абонентской мощностью до 15 Вт стационарной / демонтаж устройства сопряжения с РСО | D117: =Source!H44 -> 1 комплект | E117: =Source!I44 -> 1 | Q117: =Source!X44 -> 45.19 | R117: =Source!X45 -> 2546.54 | S117: =Source!Y44 -> 25.21 | T117: =Source!Y45 -> 1420.7 | U117: =ROUND((175/100)*ROUND(Source!R44, 2), 2) -> 0 | V117: =ROUND((0/100)*ROUND(Source!R45, 2), 2) -> 0 | AC117: 0
C118: ЗП | F118: =Source!AO44 -> 126.2 | G118: 1,2*0,3 | H118: =Source!AV45 -> 1.047 | I118: =Source!S44 -> 47.57 | J118: =IF(Source!BA45<> 0, Source!BA45, 1) -> 56.35 | K118: =Source!S45 -> 2680.57
C119: НР от ФОТ | D119: % | E119: =Source!BZ45 -> 95 | I119: =SUM(Q117:Q118) -> 45.19 | J119: =Source!AT45 -> 95 | K119: =SUM(R117:R118) -> 2546.54
...

Sheet Source
A1: 0 | B1: Smeta.RU (495) 974-1589 | D1: _PS_ | F1: 0 | G1: 0 | H1: 0 | I1: Smeta.RU | K1: 1 | L1: 74599 | M1: 10 | N1: 12 | O1: 1 | P1: 0 | Q1: 5
A4: 1 | B4: 1 | C4: -1 | G4: Капитальный ремонт здания Государственного бюджетного общеобразовательного учреждения города Москвы «Школа №1574», расположенного по адресу: г. Москва, Старопименовский переулок, д. 5. 1 этап | EC4: 0
A5: 8 | B5: 1 | C5: -1 | G5: Капитальный ремонт здания Государственного бюджетного общеобразовательного учреждения города Москвы «Школа №1574», расположенного по адресу: г. Москва, Старопименовский переулок, д. 5. 1 этап | EC5: 0
A12: 1 | B12: 382 | C12: 0 | D12: =ROW(A343) -> 343 | E12: 0 | F12: 02-01-11 | G12: 02-01-11 РТС | I12: 0 | J12: 2024-00375-01-0-ИОС5.4 | K12: 0 | L12: 0 | M12: 4098 | O12: 0 | P12: 0 | Q12: 0 | R12: 0 | S12: 0 | T12: 1 | V12: 0 | BB12: 0 | BH12: Сметные нормы списания | BI12: Коды ОКП для ТСН-2001 МГЭ Дополнение 81 | BJ12: 1 | BK12: 1 | BL12: 0 | BM12: 0 | BN12: 1 | BO12: 0 | BP12: 6 | BQ12: 2 | BR12: 1 | BS12: 1 | BT12: 0 | BU12: 0 | BV12: 0 | BW12: 0 | BX12: 0 | BY12: ТСН-2001 (МГЭ) Доп 81 - Новое строительство | BZ12: Типовой расчет для ТСН-2001 МГЭ, Дополнение 81, строительство | CA12: Территориальные сметные нормативы для Москвы ТСН-2001 (МГЭ), дополнение 81 | CB12: Территориальные сметные нормативы для Москвы ТСН-2001 (МГЭ), дополнение 81 | CC12: Территориальные сметные нормативы для Москвы ТСН-2001 (МГЭ), дополнение 81 | CD12: Территориальные сметные нормативы для Москвы ТСН-2001 (МГЭ), дополнение 81 | CE12: Поправки для ТСН-2001 от 07.04.2026 г. доп.81 | CF12: 0 | CG12: 0 | CH12: 8200 | CK12: 81 | CQ12: Территориальные сметные нормативы для Москвы (ТСН-2001) | CR12: ТЕР | CS12: 41660 | CT12: 1 | CU12: 81 | CY12: 0 | EC12: 0
A15: 15 | B15: 1
A18: 52 | B18: =B343 -> 382 | C18: =C343 -> 1 | D18: =D343 -> 12 | E18: =E343 -> 0 | F18: =F343 -> 02-01-11 | G18: =G343 -> 02-01-11 РТС | O18: =O343 -> 236689.87 | P18: =P343 -> 231819.9 | Q18: =Q343 -> 406.41 | R18: =R343 -> 33.67 | S18: =S343 -> 4463.56 | T18: =T343 -> 0 | U18: =U343 -> 366.44694 | V18: =V343 -> 0 | ... GX18: =GX343 -> 0
A20: 3 | B20: 1 | D20: =ROW(A313) -> 313 | F20: 02-01-11 | G20: Радиотрансляционная сеть | I20: 0 | J20: 2024-00375-01-0-ИОС5.4 | K20: -1 | L20: 02-01-11 | S20: 0 | T20: 0 | V20: 0 | BX20: 0 | CF20: 0 | CG20: 0
A22: 52 | B22: =B313 -> 1 | C22: =C313 -> 3 | D22: =D313 -> 20 | E22: =E313 -> 0 | F22: =F313 -> 02-01-11 | G22: =G313 -> Радиотрансляционная сеть | O22: =O313 -> 236689.87 | P22: =P313 -> 231819.9 | Q22: =Q313 -> 406.41 | R22: =R313 -> 33.67 | S22: =S313 -> 4463.56 | T22: =T313 -> 0 | U22: =U313 -> 366.44694 | V22: =V313 -> 0 | ... GX22: =GX313 -> 0
A24: 4 | B24: 1 | D24: =ROW(A55) -> 55 | F24: Новый раздел | G24: Демонтажные работы | I24: 0 | K24: 0 | S24: 0 | T24: 0 | V24: 0 | BX24: 0 | CJ24: 0
A26: 52 | B26: =B55 -> 1 | C26: =C55 -> 4 | D26: =D55 -> 24 | E26: =E55 -> 0 | F26: =F55 -> Новый раздел | G26: =G55 -> Демонтажные работы | O26: =O55 -> 1019.76 | P26: =P55 -> 0 | Q26: =Q55 -> 33.55 | R26: =R55 -> 4.95 | S26: =S55 -> 986.21 | T26: =T55 -> 0 | U26: =U55 -> 88.462399 | V26: =V55 -> 0 | ... GX26: =GX55 -> 0
A28: 17 | B28: 1 | C28: =ROW(SmtRes!A11) -> 11 | D28: =ROW(EtalonRes!A12) -> 12 | E28: 1 | F28: 4.10-73-1 | G28: Монтаж радиостанции УКВ связи абонентской мощностью до 15 Вт стационарной / демонтаж устройства подачи программ вещания | H28: 1 комплект | I28: 1 | J28: 0 | K28: 1 | O28: =ROUND(CP28,2) -> 47.57 | P28: =ROUND((ROUND((AC28*AW28*I28),2)*BC28),2) -> 0 | Q28: =(ROUND((ROUND(((((ET28*1.2)*0.3))*AV28*I28),2)*BB28),2)+ROUND((ROUND(((AE28-(((EU28*1.2)*0.3)))*AV28*I28),2)*BS28),2)) -> 0 | R28: =(ROUND((ROUND(((((EU28*1.2)*0.3))*AV28*I28),2)*BS28),2)+ROUND((ROUND(((AE28-(((EU28*1.2)*0.3)))*AV28*I28),2)*BS28),2)) -> 0 | S28: =ROUND((ROUND((AF28*AV28*I28),2)*BA28),2) -> 47.57 | T28: =ROUND(CU28*I28,2) -> 0 | U28: =CV28*I28 -> 3.7692 | V28: =CW28*I28 -> 0 | W28: =ROUND(CX28*I28,2) -> 0 | X28: =(ROUND((((S28+ROUND((ROUND(((((EU28*1.2)*0.3))*AV28*I28),2)*BS28),2))*AT28)/100),2)+ROUND(((ROUND((ROUND(((AE28-(((EU28*1.2)*0.3)))*AV28*I28),2)*BS28),2)*AT28)/100),2)) -> 45.19 | Y28: =(ROUND((((S28+ROUND((ROUND(((((EU28*1.2)*0.3))*AV28*I28),2)*BS28),2))*AU28)/100),2)+ROUND(((ROUND((ROUND(((AE28-(((EU28*1.2)*0.3)))*AV28*I28),2)*BS28),2)*AU28)/100),2)) -> 25.21 | AA28: 55917797 | AB28: =ROUND((AC28+AD28+AF28),6) -> 45.432 | AC28: =ROUND((((ES28*1)*0)),6) -> 0 | AD28: =ROUND((((((ET28*1.2)*0.3))-(((EU28*1.2)*0.3)))+AE28),6) -> 0 | AE28: =ROUND((((EU28*1.2)*0.3)),6) -> 0 | AF28: =ROUND((((EV28*1.2)*0.3)),6) -> 45.432 | AG28: =ROUND((AP28),6) -> 0 | AH28: =(((EW28*1.2)*0.3)) -> 3.6 | AI28: =(((EX28*1.2)*0.3)) -> 0 | AJ28: =(AS28) -> 0 | AK28: 201.88 | AL28: 75.68 | AM28: 0 | AN28: 0 | AO28: 126.2 | AP28: 0 | AQ28: 10 | AR28: 0 | AS28: 0 | AT28: 95 | AU28: 53 | AV28: 1.047 | AW28: 1 | AZ28: 1 | BA28: 1 | BB28: 1 | BC28: 1 | BH28: 0 | BI28: 2 | BJ28: ТСН-2001.4 Доп. 80, Сб. 10, т. 73, поз. 1 | BM28: 69 | BN28: 0 | BO28: 4.10-73-1 | BP28: 1 | BQ28: 40 | BR28: 0 | BS28: 1 | BT28: 1 | BU28: 1 | BV28: 1 | BW28: 1 | BX28: 1 | BZ28: 95 | CA28: 53 | CE28: 1566 | CF28: 0 | CG28: 0 | CM28: 0 | CN28: Поправка: Гл.12.Прил.8.п.8. 3_12.00.01.11.001 Наименование: При наличии напряженных и стесненных условий производства работ (стесненность, сложность складирования и транспортной логистики и т.п.) для объектов, расположенных в пределах круговой магистральной системы улиц "Садовое кольцо" города Москвы Поправка: Гл.4.Прил.2.2.п.2.2.29_04.00.01.35.003 Наименование: При демонтаже оборудования, предназначенного в лом | CO28: 0 | CP28: =(P28+Q28+S28) -> 47.57 | CQ28: =ROUND((ROUND((AC28*AW28*1),2)*BC28),2) -> 0 | CR28: =(ROUND((ROUND(((((ET28*1.2)*0.3))*AV28*1),2)*BB28),2)+ROUND((ROUND(((AE28-(((EU28*1.2)*0.3)))*AV28*1),2)*BS28),2)) -> 0 | CS28: =(ROUND((ROUND(((((EU28*1.2)*0.3))*AV28*1),2)*BS28),2)+ROUND((ROUND(((AE28-(((EU28*1.2)*0.3)))*AV28*1),2)*BS28),2)) -> 0 | CT28: =ROUND((ROUND((AF28*AV28*1),2)*BA28),2) -> 47.57 | CU28: =AG28 -> 0 | CV28: =(AH28*AV28) -> 3.7692 | CW28: =AI28 -> 0 | CX28: =AJ28 -> 0 | CY28: =(ROUND((((S28+ROUND((ROUND(((((EU28*1.2)*0.3))*AV28*1),2)*BS28),2))*AT28)/100),2)+ROUND(((ROUND((ROUND(((AE28-(((EU28*1.2)*0.3)))*AV28*1),2)*BS28),2)*AT28)/100),2)) -> 45.19 | CZ28: =(ROUND((((S28+ROUND((ROUND(((((EU28*1.2)*0.3))*AV28*1),2)*BS28),2))*AU28)/100),2)+ROUND(((ROUND((ROUND(((AE28-(((EU28*1.2)*0.3)))*AV28*1),2)*BS28),2)*AU28)/100),2)) -> 25.21 | DB28: 1 | DD28: *1)*0 | DE28: *1,2)*0,3 | DF28: *1,2)*0,3 | DG28: *1,2)*0,3 | DI28: *1,2)*0,3 | DJ28: *1,2)*0,3 | DN28: 0 | DO28: 0 | DP28: 1 | DQ28: 1 | DU28: 1013 | DV28: 1 комплект | DW28: 1 комплект | DX28: 1 | EE28: 55393701 | EF28: 40 | EG28: Монтаж оборудования | EH28: 0 | EJ28: 2 | EK28: 69 | EL28: ТСН-2001.4-10. Монтаж радиотелевизионного и электронного оборудования | EM28: ТСН-2001.4-10-2 | EO28: Поправка: Гл.12.Прил.8.п.8. 3_12.00.01.11.001 Поправка: Гл.4.Прил.2.2.п.2.2.29_04.00.01.35.003 | EQ28: 0 | ER28: 201.88 | ES28: 75.68 | ET28: 0 | EU28: 0 | EV28: 126.2 | EW28: 10 | EX28: 0 | EY28: 0 | FQ28: 0 | FR28: 0 | FS28: 0 | FX28: 95 | FY28: 53 | GD28: 1 | GF28: 446669827 | GG28: 2 | GH28: 1 | GI28: 2 | GJ28: 0 | GK28: 0 | GL28: =ROUND(IF(AND(BH28=3,BI28=3,FS28<>0),P28,0),2) -> 0 | GM28: =ROUND(O28+X28+Y28,2)+GX28 -> 117.97 | GN28: =IF(OR(BI28=0,BI28=1),GM28-GX28,0) -> 0 | GO28: =IF(BI28=2,GM28-GX28,0) -> 117.97 | GP28: =IF(BI28=4,GM28-GX28,0) -> 0 | GR28: 0 | GS28: 3 | GT28: 0 | GV28: =ROUND((GT28),6) -> 0 | GW28: 1 | GX28: =ROUND(HC28*I28,2) -> 0 | HA28: 0 | HB28: 0 | HC28: =GV28*GW28 -> 0 | HS28: 0 | IK28: 0
A29: 17 | B29: 1 | C29: =ROW(SmtRes!A22) -> 22 | D29: =ROW(EtalonRes!A24) -> 24 | E29: 1 | F29: 4.10-73-1 | G29: Монтаж радиостанции УКВ связи абонентской мощностью до 15 Вт стационарной / демонтаж устройства подачи программ вещания | H29: 1 комплект | I29: 1 | J29: 0 | K29: 1 | O29: =ROUND(CP29,2) -> 2680.57 | P29: =ROUND((ROUND((AC29*AW29*I29),2)*BC29),2) -> 0 | Q29: =(ROUND((ROUND(((((ET29*1.2)*0.3))*AV29*I29),2)*BB29),2)+ROUND((ROUND(((AE29-(((EU29*1.2)*0.3)))*AV29*I29),2)*BS29),2)) -> 0 | R29: =(ROUND((ROUND(((((EU29*1.2)*0.3))*AV29*I29),2)*BS29),2)+ROUND((ROUND(((AE29-(((EU29*1.2)*0.3)))*AV29*I29),2)*BS29),2)) -> 0 | S29: =ROUND((ROUND((AF29*AV29*I29),2)*BA29),2) -> 2680.57 | T29: =ROUND(CU29*I29,2) -> 0 | U29: =CV29*I29 -> 3.7692 | V29: =CW29*I29 -> 0 | W29: =ROUND(CX29*I29,2) -> 0 | X29: =(ROUND((((S29+ROUND((ROUND(((((EU29*1.2)*0.3))*AV29*I29),2)*BS29),2))*AT29)/100),2)+ROUND(((ROUND((ROUND(((AE29-(((EU29*1.2)*0.3)))*AV29*I29),2)*BS29),2)*AT29)/100),2)) -> 2546.54 | Y29: =(ROUND((((S29+ROUND((ROUND(((((EU29*1.2)*0.3))*AV29*I29),2)*BS29),2))*AU29)/100),2)+ROUND(((ROUND((ROUND(((AE29-(((EU29*1.2)*0.3)))*AV29*I29),2)*BS29),2)*AU29)/100),2)) -> 1420.7 | AA29: 55917799 | AB29: =ROUND((AC29+AD29+AF29),6) -> 45.432 | AC29: =ROUND((((ES29*1)*0)),6) -> 0 | AD29: =ROUND((((((ET29*1.2)*0.3))-(((EU29*1.2)*0.3)))+AE29),6) -> 0 | AE29: =ROUND((((EU29*1.2)*0.3)),6) -> 0 | AF29: =ROUND((((EV29*1.2)*0.3)),6) -> 45.432 | AG29: =ROUND((AP29),6) -> 0 | AH29: =(((EW29*1.2)*0.3)) -> 3.6 | AI29: =(((EX29*1.2)*0.3)) -> 0 | AJ29: =(AS29) -> 0 | AK29: 201.88 | AL29: 75.68 | AM29: 0 | AN29: 0 | AO29: 126.2 | AP29: 0 | AQ29: 10 | AR29: 0 | AS29: 0 | AT29: 95 | AU29: 53 | AV29: 1.047 | AW29: 1 | AZ29: 1 | BA29: 56.35 | BB29: 1 | BC29: 9.58 | BH29: 0 | BI29: 2 | BJ29: ТСН-2001.4 Доп. 80, Сб. 10, т. 73, поз. 1 | BM29: 69 | BN29: 0 | BO29: 4.10-73-1 | BP29: 1 | BQ29: 40 | BR29: 0 | BS29: 56.35 | BT29: 1 | BU29: 1 | BV29: 1 | BW29: 1 | BX29: 1 | BZ29: 95 | CA29: 53 | CE29: 1566 | CF29: 0 | CG29: 0 | CM29: 0 | CN29: Поправка: Гл.12.Прил.8.п.8. 3_12.00.01.11.001 Наименование: При наличии напряженных и стесненных условий производства работ (стесненность, сложность складирования и транспортной логистики и т.п.) для объектов, расположенных в пределах круговой магистральной системы улиц "Садовое кольцо" города Москвы Поправка: Гл.4.Прил.2.2.п.2.2.29_04.00.01.35.003 Наименование: При демонтаже оборудования, предназначенного в лом | CO29: 0 | CP29: =(P29+Q29+S29) -> 2680.57 | CQ29: =ROUND((ROUND((AC29*AW29*1),2)*BC29),2) -> 0 | CR29: =(ROUND((ROUND(((((ET29*1.2)*0.3))*AV29*1),2)*BB29),2)+ROUND((ROUND(((AE29-(((EU29*1.2)*0.3)))*AV29*1),2)*BS29),2)) -> 0 | CS29: =(ROUND((ROUND(((((EU29*1.2)*0.3))*AV29*1),2)*BS29),2)+ROUND((ROUND(((AE29-(((EU29*1.2)*0.3)))*AV29*1),2)*BS29),2)) -> 0 | CT29: =ROUND((ROUND((AF29*AV29*1),2)*BA29),2) -> 2680.57 | CU29: =AG29 -> 0 | CV29: =(AH29*AV29) -> 3.7692 | CW29: =AI29 -> 0 | CX29: =AJ29 -> 0 | CY29: =(ROUND((((S29+ROUND((ROUND(((((EU29*1.2)*0.3))*AV29*1),2)*BS29),2))*AT29)/100),2)+ROUND(((ROUND((ROUND(((AE29-(((EU29*1.2)*0.3)))*AV29*1),2)*BS29),2)*AT29)/100),2)) -> 2546.54 | CZ29: =(ROUND((((S29+ROUND((ROUND(((((EU29*1.2)*0.3))*AV29*1),2)*BS29),2))*AU29)/100),2)+ROUND(((ROUND((ROUND(((AE29-(((EU29*1.2)*0.3)))*AV29*1),2)*BS29),2)*AU29)/100),2)) -> 1420.7 | DB29: 3 | DD29: *1)*0 | DE29: *1,2)*0,3 | DF29: *1,2)*0,3 | DG29: *1,2)*0,3 | DI29: *1,2)*0,3 | DJ29: *1,2)*0,3 | DN29: 0 | DO29: 0 | DP29: 1 | DQ29: 1 | DU29: 1013 | DV29: 1 комплект | DW29: 1 комплект | DX29: 1 | EE29: 55393701 | EF29: 40 | EG29: Монтаж оборудования | EH29: 0 | EJ29: 2 | EK29: 69 | EL29: ТСН-2001.4-10. Монтаж радиотелевизионного и электронного оборудования | EM29: ТСН-2001.4-10-2 | EO29: Поправка: Гл.12.Прил.8.п.8. 3_12.00.01.11.001 Поправка: Гл.4.Прил.2.2.п.2.2.29_04.00.01.35.003 | EQ29: 0 | ER29: 201.88 | ES29: 75.68 | ET29: 0 | EU29: 0 | EV29: 126.2 | EW29: 10 | EX29: 0 | EY29: 0 | FQ29: 0 | FR29: 0 | FS29: 0 | FX29: 95 | FY29: 53 | GD29: 1 | GF29: 446669827 | GG29: 2 | GH29: 1 | GI29: 2 | GJ29: 0 | GK29: 0 | GL29: =ROUND(IF(AND(BH29=3,BI29=3,FS29<>0),P29,0),2) -> 0 | GM29: =ROUND(O29+X29+Y29,2)+GX29 -> 6647.81 | GN29: =IF(OR(BI29=0,BI29=1),GM29-GX29,0) -> 0 | GO29: =IF(BI29=2,GM29-GX29,0) -> 6647.81 | GP29: =IF(BI29=4,GM29-GX29,0) -> 0 | GR29: 0 | GS29: 3 | GT29: 0 | GV29: =ROUND((GT29),6) -> 0 | GW29: 1 | GX29: =ROUND(HC29*I29,2) -> 0 | HA29: 0 | HB29: 0 | HC29: =GV29*GW29 -> 0 | HS29: 0 | IK29: 0
A30: 17 | B30: 1 | C30: =ROW(SmtRes!A24) -> 24 | D30: =ROW(EtalonRes!A27) -> 27 | E30: 2 | F30: 4.10-32-4 | G30: Монтаж платы дополнительной, устанавливаемой на готовом месте стойки / демонтаж модуля для приема интернет вещания радиостанции | H30: 1 ШТ. | I30: 1 | J30: 0 | K30: 1 | O30: =ROUND(CP30,2) -> 12.31 | P30: =ROUND((ROUND((AC30*AW30*I30),2)*BC30),2) -> 0 | Q30: =(ROUND((ROUND(((((ET30*1.2)*0.3))*AV30*I30),2)*BB30),2)+ROUND((ROUND(((AE30-(((EU30*1.2)*0.3)))*AV30*I30),2)*BS30),2)) -> 3.46 | R30: =(ROUND((ROUND(((((EU30*1.2)*0.3))*AV30*I30),2)*BS30),2)+ROUND((ROUND(((AE30-(((EU30*1.2)*0.3)))*AV30*I30),2)*BS30),2)) -> 0.38 | S30: =ROUND((ROUND((AF30*AV30*I30),2)*BA30),2) -> 8.85 | T30: =ROUND(CU30*I30,2) -> 0 | U30: =CV30*I30 -> 0.791532 | V30: =CW30*I30 -> 0 | W30: =ROUND(CX30*I30,2) -> 0 | X30: =(ROUND((((S30+ROUND((ROUND(((((EU30*1.2)*0.3))*AV30*I30),2)*BS30),2))*AT30)/100),2)+ROUND(((ROUND((ROUND(((AE30-(((EU30*1.2)*0.3)))*AV30*I30),2)*BS30),2)*AT30)/100),2)) -> 8.31 | Y30: =(ROUND((((S30+ROUND((ROUND(((((EU30*1.2)*0.3))*AV30*I30),2)*BS30),2))*AU30)/100),2)+ROUND(((ROUND((ROUND(((AE30-(((EU30*1.2)*0.3)))*AV30*I30),2)*BS30),2)*AU30)/100),2)) -> 4.25 | AA30: 55917797 | AB30: =ROUND((AC30+AD30+AF30),6) -> 11.7612 | AC30: =ROUND((((ES30*1)*0)),6) -> 0 | AD30: =ROUND((((((ET30*1.2)*0.3))-(((EU30*1.2)*0.3)))+AE30),6) -> 3.3084 | AE30: =ROUND((((EU30*1.2)*0.3)),6) -> 0.3636 | AF30: =ROUND((((EV30*1.2)*0.3)),6) -> 8.4528 | AG30: =ROUND((AP30),6) -> 0 | AH30: =(((EW30*1.2)*0.3)) -> 0.756 | AI30: =(((EX30*1.2)*0.3)) -> 0 | AJ30: =(AS30) -> 0 | AK30: 32.67 | AL30: 0 | AM30: 9.19 | AN30: 1.01 | AO30: 23.48 | AP30: 0 | AQ30: 2.1 | AR30: 0 | AS30: 0 | AT30: 90 | AU30: 46 | AV30: 1.047 | AW30: 1 | AZ30: 1 | BA30: 1 | BB30: 1 | BC30: 1 | BH30: 0 | BI30: 2 | BJ30: ТСН-2001.4 Доп. 68, Сб. 10, т. 32, поз. 4 | BM30: 68 | BN30: 0 | BO30: 4.10-32-4 | BP30: 1 | BQ30: 40 | BR30: 0 | BS30: 1 | BT30: 1 | BU30: 1 | BV30: 1 | BW30: 1 | BX30: 1 | BZ30: 90 | CA30: 46 | CE30: 1566 | CF30: 0 | CG30: 0 | CM30: 0 | CN30: Поправка: Гл.12.Прил.8.п.8. 3_12.00.01.11.001 Наименование: При наличии напряженных и стесненных условий производства работ (стесненность, сложность складирования и транспортной логистики и т.п.) для объектов, расположенных в пределах круговой магистральной системы улиц "Садовое кольцо" города Москвы Поправка: Гл.4.Прил.2.2.п.2.2.29_04.00.01.35.003 Наименование: При демонтаже оборудования, предназначенного в лом | CO30: 0 | CP30: =(P30+Q30+S30) -> 12.31 | CQ30: =ROUND((ROUND((AC30*AW30*1),2)*BC30),2) -> 0 | CR30: =(ROUND((ROUND(((((ET30*1.2)*0.3))*AV30*1),2)*BB30),2)+ROUND((ROUND(((AE30-(((EU30*1.2)*0.3)))*AV30*1),2)*BS30),2)) -> 3.46 | CS30: =(ROUND((ROUND(((((EU30*1.2)*0.3))*AV30*1),2)*BS30),2)+ROUND((ROUND(((AE30-(((EU30*1.2)*0.3)))*AV30*1),2)*BS30),2)) -> 0.38 | CT30: =ROUND((ROUND((AF30*AV30*1),2)*BA30),2) -> 8.85 | CU30: =AG30 -> 0 | CV30: =(AH30*AV30) -> 0.791532 | CW30: =AI30 -> 0 | CX30: =AJ30 -> 0 | CY30: =(ROUND((((S30+ROUND((ROUND(((((EU30*1.2)*0.3))*AV30*1),2)*BS30),2))*AT30)/100),2)+ROUND(((ROUND((ROUND(((AE30-(((EU30*1.2)*0.3)))*AV30*1),2)*BS30),2)*AT30)/100),2)) -> 8.31 | CZ30: =(ROUND((((S30+ROUND((ROUND(((((EU30*1.2)*0.3))*AV30*1),2)*BS30),2))*AU30)/100),2)+ROUND(((ROUND((ROUND(((AE30-(((EU30*1.2)*0.3)))*AV30*1),2)*BS30),2)*AU30)/100),2)) -> 4.25 | DB30: 5 | DD30: *1)*0 | DE30: *1,2)*0,3 | DF30: *1,2)*0,3 | DG30: *1,2)*0,3 | DI30: *1,2)*0,3 | DJ30: *1,2)*0,3 | DN30: 0 | DO30: 0 | DP30: 1 | DQ30: 1 | DU30: 1013 | DV30: 1 ШТ. | DW30: 1 ШТ. | DX30: 1 | EE30: 55393700 | EF30: 40 | EG30: Монтаж оборудования | EH30: 0 | EJ30: 2 | EK30: 68 | EL30: ТСН-2001.4-10. Прокладка и монтаж сетей связи | EM30: ТСН-2001.4-10-1 | EO30: Поправка: Гл.12.Прил.8.п.8. 3_12.00.01.11.001 Поправка: Гл.4.Прил.2.2.п.2.2.29_04.00.01.35.003 | EQ30: 0 | ER30: 32.67 | ES30: 0 | ET30: 9.19 | EU30: 1.01 | EV30: 23.48 | EW30: 2.1 | EX30: 0 | EY30: 0 | FQ30: 0 | FR30: 0 | FS30: 0 | FX30: 90 | FY30: 46 | GD30: 1 | GF30: 553809513 | GG30: 2 | GH30: 1 | GI30: 2 | GJ30: 0 | GK30: 0 | GL30: =ROUND(IF(AND(BH30=3,BI30=3,FS30<>0),P30,0),2) -> 0 | GM30: =ROUND(O30+X30+Y30,2)+GX30 -> 24.87 | GN30: =IF(OR(BI30=0,BI30=1),GM30-GX30,0) -> 0 | GO30: =IF(BI30=2,GM30-GX30,0) -> 24.87 | GP30: =IF(BI30=4,GM30-GX30,0) -> 0 | GR30: 0 | GS30: 3 | GT30: 0 | GV30: =ROUND((GT30),6) -> 0 | GW30: 1 | GX30: =ROUND(HC30*I30,2) -> 0 | HA30: 0 | HB30: 0 | HC30: =GV30*GW30 -> 0 | HS30: 0 | IK30: 0
A31: 17 | B31: 1 | C31: =ROW(SmtRes!A26) -> 26 | D31: =ROW(EtalonRes!A30) -> 30 | E31: 2 | F31: 4.10-32-4 | G31: Монтаж платы дополнительной, устанавливаемой на готовом месте стойки / демонтаж модуля для приема интернет вещания радиостанции | H31: 1 ШТ. | I31: 1 | J31: 0 | K31: 1 | O31: =ROUND(CP31,2) -> 554.58 | P31: =ROUND((ROUND((AC31*AW31*I31),2)*BC31),2) -> 0 | Q31: =(ROUND((ROUND(((((ET31*1.2)*0.3))*AV31*I31),2)*BB31),2)+ROUND((ROUND(((AE31-(((EU31*1.2)*0.3)))*AV31*I31),2)*BS31),2)) -> 55.88 | R31: =(ROUND((ROUND(((((EU31*1.2)*0.3))*AV31*I31),2)*BS31),2)+ROUND((ROUND(((AE31-(((EU31*1.2)*0.3)))*AV31*I31),2)*BS31),2)) -> 21.41 | S31: =ROUND((ROUND((AF31*AV31*I31),2)*BA31),2) -> 498.7 | T31: =ROUND(CU31*I31,2) -> 0 | U31: =CV31*I31 -> 0.791532 | V31: =CW31*I31 -> 0 | W31: =ROUND(CX31*I31,2) -> 0 | X31: =(ROUND((((S31+ROUND((ROUND(((((EU31*1.2)*0.3))*AV31*I31),2)*BS31),2))*AT31)/100),2)+ROUND(((ROUND((ROUND(((AE31-(((EU31*1.2)*0.3)))*AV31*I31),2)*BS31),2)*AT31)/100),2)) -> 468.1 | Y31: =(ROUND((((S31+ROUND((ROUND(((((EU31*1.2)*0.3))*AV31*I31),2)*BS31),2))*AU31)/100),2)+ROUND(((ROUND((ROUND(((AE31-(((EU31*1.2)*0.3)))*AV31*I31),2)*BS31),2)*AU31)/100),2)) -> 239.25 | AA31: 55917799 | AB31: =ROUND((AC31+AD31+AF31),6) -> 11.7612 | AC31: =ROUND((((ES31*1)*0)),6) -> 0 | AD31: =ROUND((((((ET31*1.2)*0.3))-(((EU31*1.2)*0.3)))+AE31),6) -> 3.3084 | AE31: =ROUND((((EU31*1.2)*0.3)),6) -> 0.3636 | AF31: =ROUND((((EV31*1.2)*0.3)),6) -> 8.4528 | AG31: =ROUND((AP31),6) -> 0 | AH31: =(((EW31*1.2)*0.3)) -> 0.756 | AI31: =(((EX31*1.2)*0.3)) -> 0 | AJ31: =(AS31) -> 0 | AK31: 32.67 | AL31: 0 | AM31: 9.19 | AN31: 1.01 | AO31: 23.48 | AP31: 0 | AQ31: 2.1 | AR31: 0 | AS31: 0 | AT31: 90 | AU31: 46 | AV31: 1.047 | AW31: 1 | AZ31: 1 | BA31: 56.35 | BB31: 16.15 | BC31: 1 | BH31: 0 | BI31: 2 | BJ31: ТСН-2001.4 Доп. 68, Сб. 10, т. 32, поз. 4 | BM31: 68 | BN31: 0 | BO31: 4.10-32-4 | BP31: 1 | BQ31: 40 | BR31: 0 | BS31: 56.35 | BT31: 1 | BU31: 1 | BV31: 1 | BW31: 1 | BX31: 1 | BZ31: 90 | CA31: 46 | CE31: 1566 | CF31: 0 | CG31: 0 | CM31: 0 | CN31: Поправка: Гл.12.Прил.8.п.8. 3_12.00.01.11.001 Наименование: При наличии напряженных и стесненных условий производства работ (стесненность, сложность складирования и транспортной логистики и т.п.) для объектов, расположенных в пределах круговой магистральной системы улиц "Садовое кольцо" города Москвы Поправка: Гл.4.Прил.2.2.п.2.2.29_04.00.01.35.003 Наименование: При демонтаже оборудования, предназначенного в лом | CO31: 0 | CP31: =(P31+Q31+S31) -> 554.58 | CQ31: =ROUND((ROUND((AC31*AW31*1),2)*BC31),2) -> 0 | CR31: =(ROUND((ROUND(((((ET31*1.2)*0.3))*AV31*1),2)*BB31),2)+ROUND((ROUND(((AE31-(((EU31*1.2)*0.3)))*AV31*1),2)*BS31),2)) -> 55.88 | CS31: =(ROUND((ROUND(((((EU31*1.2)*0.3))*AV31*1),2)*BS31),2)+ROUND((ROUND(((AE31-(((EU31*1.2)*0.3)))*AV31*1),2)*BS31),2)) -> 21.41 | CT31: =ROUND((ROUND((AF31*AV31*1),2)*BA31),2) -> 498.7 | CU31: =AG31 -> 0 | CV31: =(AH31*AV31) -> 0.791532 | CW31: =AI31 -> 0 | CX31: =AJ31 -> 0 | CY31: =(ROUND((((S31+ROUND((ROUND(((((EU31*1.2)*0.3))*AV31*1),2)*BS31),2))*AT31)/100),2)+ROUND(((ROUND((ROUND(((AE31-(((EU31*1.2)*0.3)))*AV31*1),2)*BS31),2)*AT31)/100),2)) -> 468.1 | CZ31: =(ROUND((((S31+ROUND((ROUND(((((EU31*1.2)*0.3))*AV31*1),2)*BS31),2))*AU31)/100),2)+ROUND(((ROUND((ROUND(((AE31-(((EU31*1.2)*0.3)))*AV31*1),2)*BS31),2)*AU31)/100),2)) -> 239.25 | DB31: 7 | DD31: *1)*0 | DE31: *1,2)*0,3 | DF31: *1,2)*0,3 | DG31: *1,2)*0,3 | DI31: *1,2)*0,3 | DJ31: *1,2)*0,3 | DN31: 0 | DO31: 0 | DP31: 1 | DQ31: 1 | DU31: 1013 | DV31: 1 ШТ. | DW31: 1 ШТ. | DX31: 1 | EE31: 55393700 | EF31: 40 | EG31: Монтаж оборудования | EH31: 0 | EJ31: 2 | EK31: 68 | EL31: ТСН-2001.4-10. Прокладка и монтаж сетей связи | EM31: ТСН-2001.4-10-1 | EO31: Поправка: Гл.12.Прил.8.п.8. 3_12.00.01.11.001 Поправка: Гл.4.Прил.2.2.п.2.2.29_04.00.01.35.003 | EQ31: 0 | ER31: 32.67 | ES31: 0 | ET31: 9.19 | EU31: 1.01 | EV31: 23.48 | EW31: 2.1 | EX31: 0 | EY31: 0 | FQ31: 0 | FR31: 0 | FS31: 0 | FX31: 90 | FY31: 46 | GD31: 1 | GF31: 553809513 | GG31: 2 | GH31: 1 | GI31: 2 | GJ31: 0 | GK31: 0 | GL31: =ROUND(IF(AND(BH31=3,BI31=3,FS31<>0),P31,0),2) -> 0 | GM31: =ROUND(O31+X31+Y31,2)+GX31 -> 1261.93 | GN31: =IF(OR(BI31=0,BI31=1),GM31-GX31,0) -> 0 | GO31: =IF(BI31=2,GM31-GX31,0) -> 1261.93 | GP31: =IF(BI31=4,GM31-GX31,0) -> 0 | GR31: 0 | GS31: 3 | GT31: 0 | GV31: =ROUND((GT31),6) -> 0 | GW31: 1 | GX31: =ROUND(HC31*I31,2) -> 0 | HA31: 0 | HB31: 0 | HC31: =GV31*GW31 -> 0 | HS31: 0 | IK31: 0
A32: 17 | B32: 1 | C32: =ROW(SmtRes!A28) -> 28 | D32: =ROW(EtalonRes!A32) -> 32 | E32: 3 | F32: 4.10-134-4 | G32: Монтаж антенны коллективной для приема ТВ на антенной опоре высотой до 9 м с одним ярусом оттяжек / демонтаж антенны | H32: 1 антенна | I32: 1 | J32: 0 | K32: 1 | O32: =ROUND(CP32,2) -> 29.8 | P32: =ROUND((ROUND((AC32*AW32*I32),2)*BC32),2) -> 0 | Q32: =(ROUND((ROUND(((((ET32*1.2)*0.3))*AV32*I32),2)*BB32),2)+ROUND((ROUND(((AE32-(((EU32*1.2)*0.3)))*AV32*I32),2)*BS32),2)) -> 0 | R32: =(ROUND((ROUND(((((EU32*1.2)*0.3))*AV32*I32),2)*BS32),2)+ROUND((ROUND(((AE32-(((EU32*1.2)*0.3)))*AV32*I32),2)*BS32),2)) -> 0 | S32: =ROUND((ROUND((AF32*AV32*I32),2)*BA32),2) -> 29.8 | T32: =ROUND(CU32*I32,2) -> 0 | U32: =CV32*I32 -> 2.1013884 | V32: =CW32*I32 -> 0 | W32: =ROUND(CX32*I32,2) -> 0 | X32: =(ROUND((((S32+ROUND((ROUND(((((EU32*1.2)*0.3))*AV32*I32),2)*BS32),2))*AT32)/100),2)+ROUND(((ROUND((ROUND(((AE32-(((EU32*1.2)*0.3)))*AV32*I32),2)*BS32),2)*AT32)/100),2)) -> 28.31 | Y32: =(ROUND((((S32+ROUND((ROUND(((((EU32*1.2)*0.3))*AV32*I32),2)*BS32),2))*AU32)/100),2)+ROUND(((ROUND((ROUND(((AE32-(((EU32*1.2)*0.3)))*AV32*I32),2)*BS32),2)*AU32)/100),2)) -> 15.79 | AA32: 55917797 | AB32: =ROUND((AC32+AD32+AF32),6) -> 27.414 | AC32: =ROUND((((ES32*1)*0)),6) -> 0 | AD32: =ROUND((((((ET32*1.2)*0.3))-(((EU32*1.2)*0.3)))+AE32),6) -> 0 | AE32: =ROUND((((EU32*1.2)*0.3)),6) -> 0 | AF32: =ROUND((((EV32*1.2)*0.3)),6) -> 27.414 | AG32: =ROUND((AP32),6) -> 0 | AH32: =(((EW32*1.2)*0.3)) -> 1.9332 | AI32: =(((EX32*1.2)*0.3)) -> 0 | AJ32: =(AS32) -> 0 | AK32: 76.52 | AL32: 0.37 | AM32: 0 | AN32: 0 | AO32: 76.15 | AP32: 0 | AQ32: 5.37 | AR32: 0 | AS32: 0 | AT32: 95 | AU32: 53 | AV32: 1.087 | AW32: 1 | AZ32: 1 | BA32: 1 | BB32: 1 | BC32: 1 | BH32: 0 | BI32: 2 | BJ32: ТСН-2001.4 Доп. 81, Сб. 10, т. 134, поз. 4 | BM32: 69 | BN32: 0 | BO32: 4.10-134-4 | BP32: 1 | BQ32: 40 | BR32: 0 | BS32: 1 | BT32: 1 | BU32: 1 | BV32: 1 | BW32: 1 | BX32: 1 | BZ32: 95 | CA32: 53 | CE32: 1566 | CF32: 0 | CG32: 0 | CM32: 0 | CN32: Поправка: Гл.12.Прил.8.п.8. 3_12.00.01.11.001 Наименование: При наличии напряженных и стесненных условий производства работ (стесненность, сложность складирования и транспортной логистики и т.п.) для объектов, расположенных в пределах круговой магистральной системы улиц "Садовое кольцо" города Москвы Поправка: Гл.4.Прил.2.2.п.2.2.29_04.00.01.35.003 Наименование: При демонтаже оборудования, предназначенного в лом | CO32: 0 | CP32: =(P32+Q32+S32) -> 29.8 | CQ32: =ROUND((ROUND((AC32*AW32*1),2)*BC32),2) -> 0 | CR32: =(ROUND((ROUND(((((ET32*1.2)*0.3))*AV32*1),2)*BB32),2)+ROUND((ROUND(((AE32-(((EU32*1.2)*0.3)))*AV32*1),2)*BS32),2)) -> 0 | CS32: =(ROUND((ROUND(((((EU32*1.2)*0.3))*AV32*1),2)*BS32),2)+ROUND((ROUND(((AE32-(((EU32*1.2)*0.3)))*AV32*1),2)*BS32),2)) -> 0 | CT32: =ROUND((ROUND((AF32*AV32*1),2)*BA32),2) -> 29.8 | CU32: =AG32 -> 0 | CV32: =(AH32*AV32) -> 2.1013884 | CW32: =AI32 -> 0 | CX32: =AJ32 -> 0 | CY32: =(ROUND((((S32+ROUND((ROUND(((((EU32*1.2)*0.3))*AV32*1),2)*BS32),2))*AT32)/100),2)+ROUND(((ROUND((ROUND(((AE32-(((EU32*1.2)*0.3)))*AV32*1),2)*BS32),2)*AT32)/100),2)) -> 28.31 | CZ32: =(ROUND((((S32+ROUND((ROUND(((((EU32*1.2)*0.3))*AV32*1),2)*BS32),2))*AU32)/100),2)+ROUND(((ROUND((ROUND(((AE32-(((EU32*1.2)*0.3)))*AV32*1),2)*BS32),2)*AU32)/100),2)) -> 15.79 | DB32: 9 | DD32: *1)*0 | DE32: *1,2)*0,3 | DF32: *1,2)*0,3 | DG32: *1,2)*0,3 | DI32: *1,2)*0,3 | DJ32: *1,2)*0,3 | DN32: 0 | DO32: 0 | DP32: 1 | DQ32: 1 | DU32: 1013 | DV32: 1 антенна | DW32: 1 антенна | DX32: 1 | EE32: 55393701 | EF32: 40 | EG32: Монтаж оборудования | EH32: 0 | EJ32: 2 | EK32: 69 | EL32: ТСН-2001.4-10. Монтаж радиотелевизионного и электронного оборудования | EM32: ТСН-2001.4-10-2 | EO32: Поправка: Гл.12.Прил.8.п.8. 3_12.00.01.11.001 Поправка: Гл.4.Прил.2.2.п.2.2.29_04.00.01.35.003 | EQ32: 0 | ER32: 76.52 | ES32: 0.37 | ET32: 0 | EU32: 0 | EV32: 76.15 | EW32: 5.37 | EX32: 0 | EY32: 0 | FQ32: 0 | FR32: 0 | FS32: 0 | FX32: 95 | FY32: 53 | GD32: 1 | GF32: 82209368 | GG32: 2 | GH32: 1 | GI32: 2 | GJ32: 0 | GK32: 0 | GL32: =ROUND(IF(AND(BH32=3,BI32=3,FS32<>0),P32,0),2) -> 0 | GM32: =ROUND(O32+X32+Y32,2)+GX32 -> 73.9 | GN32: =IF(OR(BI32=0,BI32=1),GM32-GX32,0) -> 0 | GO32: =IF(BI32=2,GM32-GX32,0) -> 73.9 | GP32: =IF(BI32=4,GM32-GX32,0) -> 0 | GR32: 0 | GS32: 3 | GT32: 0 | GV32: =ROUND((GT32),6) -> 0 | GW32: 1 | GX32: =ROUND(HC32*I32,2) -> 0 | HA32: 0 | HB32: 0 | HC32: =GV32*GW32 -> 0 | HS32: 0 | IK32: 0
A33: 17 | B33: 1 | C33: =ROW(SmtRes!A30) -> 30 | D33: =ROW(EtalonRes!A34) -> 34 | E33: 3 | F33: 4.10-134-4 | G33: Монтаж антенны коллективной для приема ТВ на антенной опоре высотой до 9 м с одним ярусом оттяжек / демонтаж антенны | H33: 1 антенна | I33: 1 | J33: 0 | K33: 1 | O33: =ROUND(CP33,2) -> 1679.23 | P33: =ROUND((ROUND((AC33*AW33*I33),2)*BC33),2) -> 0 | Q33: =(ROUND((ROUND(((((ET33*1.2)*0.3))*AV33*I33),2)*BB33),2)+ROUND((ROUND(((AE33-(((EU33*1.2)*0.3)))*AV33*I33),2)*BS33),2)) -> 0 | R33: =(ROUND((ROUND(((((EU33*1.2)*0.3))*AV33*I33),2)*BS33),2)+ROUND((ROUND(((AE33-(((EU33*1.2)*0.3)))*AV33*I33),2)*BS33),2)) -> 0 | S33: =ROUND((ROUND((AF33*AV33*I33),2)*BA33),2) -> 1679.23 | T33: =ROUND(CU33*I33,2) -> 0 | U33: =CV33*I33 -> 2.1013884 | V33: =CW33*I33 -> 0 | W33: =ROUND(CX33*I33,2) -> 0 | X33: =(ROUND((((S33+ROUND((ROUND(((((EU33*1.2)*0.3))*AV33*I33),2)*BS33),2))*AT33)/100),2)+ROUND(((ROUND((ROUND(((AE33-(((EU33*1.2)*0.3)))*AV33*I33),2)*BS33),2)*AT33)/100),2)) -> 1595.27 | Y33: =(ROUND((((S33+ROUND((ROUND(((((EU33*1.2)*0.3))*AV33*I33),2)*BS33),2))*AU33)/100),2)+ROUND(((ROUND((ROUND(((AE33-(((EU33*1.2)*0.3)))*AV33*I33),2)*BS33),2)*AU33)/100),2)) -> 889.99 | AA33: 55917799 | AB33: =ROUND((AC33+AD33+AF33),6) -> 27.414 | AC33: =ROUND((((ES33*1)*0)),6) -> 0 | AD33: =ROUND((((((ET33*1.2)*0.3))-(((EU33*1.2)*0.3)))+AE33),6) -> 0 | AE33: =ROUND((((EU33*1.2)*0.3)),6) -> 0 | AF33: =ROUND((((EV33*1.2)*0.3)),6) -> 27.414 | AG33: =ROUND((AP33),6) -> 0 | AH33: =(((EW33*1.2)*0.3)) -> 1.9332 | AI33: =(((EX33*1.2)*0.3)) -> 0 | AJ33: =(AS33) -> 0 | AK33: 76.52 | AL33: 0.37 | AM33: 0 | AN33: 0 | AO33: 76.15 | AP33: 0 | AQ33: 5.37 | AR33: 0 | AS33: 0 | AT33: 95 | AU33: 53 | AV33: 1.087 | AW33: 1 | AZ33: 1 | BA33: 56.35 | BB33: 1 | BC33: 5.46 | BH33: 0 | BI33: 2 | BJ33: ТСН-2001.4 Доп. 81, Сб. 10, т. 134, поз. 4 | BM33: 69 | BN33: 0 | BO33: 4.10-134-4 | BP33: 1 | BQ33: 40 | BR33: 0 | BS33: 56.35 | BT33: 1 | BU33: 1 | BV33: 1 | BW33: 1 | BX33: 1 | BZ33: 95 | CA33: 53 | CE33: 1566 | CF33: 0 | CG33: 0 | CM33: 0 | CN33: Поправка: Гл.12.Прил.8.п.8. 3_12.00.01.11.001 Наименование: При наличии напряженных и стесненных условий производства работ (стесненность, сложность складирования и транспортной логистики и т.п.) для объектов, расположенных в пределах круговой магистральной системы улиц "Садовое кольцо" города Москвы Поправка: Гл.4.Прил.2.2.п.2.2.29_04.00.01.35.003 Наименование: При демонтаже оборудования, предназначенного в лом | CO33: 0 | CP33: =(P33+Q33+S33) -> 1679.23 | CQ33: =ROUND((ROUND((AC33*AW33*1),2)*BC33),2) -> 0 | CR33: =(ROUND((ROUND(((((ET33*1.2)*0.3))*AV33*1),2)*BB33),2)+ROUND((ROUND(((AE33-(((EU33*1.2)*0.3)))*AV33*1),2)*BS33),2)) -> 0 | CS33: =(ROUND((ROUND(((((EU33*1.2)*0.3))*AV33*1),2)*BS33),2)+ROUND((ROUND(((AE33-(((EU33*1.2)*0.3)))*AV33*1),2)*BS33),2)) -> 0 | CT33: =ROUND((ROUND((AF33*AV33*1),2)*BA33),2) -> 1679.23 | CU33: =AG33 -> 0 | CV33: =(AH33*AV33) -> 2.1013884 | CW33: =AI33 -> 0 | CX33: =AJ33 -> 0 | CY33: =(ROUND((((S33+ROUND((ROUND(((((EU33*1.2)*0.3))*AV33*1),2)*BS33),2))*AT33)/100),2)+ROUND(((ROUND((ROUND(((AE33-(((EU33*1.2)*0.3)))*AV33*1),2)*BS33),2)*AT33)/100),2)) -> 1595.27 | CZ33: =(ROUND((((S33+ROUND((ROUND(((((EU33*1.2)*0.3))*AV33*1),2)*BS33),2))*AU33)/100),2)+ROUND(((ROUND((ROUND(((AE33-(((EU33*1.2)*0.3)))*AV33*1),2)*BS33),2)*AU33)/100),2)) -> 889.99 | DB33: 11 | DD33: *1)*0 | DE33: *1,2)*0,3 | DF33: *1,2)*0,3 | DG33: *1,2)*0,3 | DI33: *1,2)*0,3 | DJ33: *1,2)*0,3 | DN33: 0 | DO33: 0 | DP33: 1 | DQ33: 1 | DU33: 1013 | DV33: 1 антенна | DW33: 1 антенна | DX33: 1 | EE33: 55393701 | EF33: 40 | EG33: Монтаж оборудования | EH33: 0 | EJ33: 2 | EK33: 69 | EL33: ТСН-2001.4-10. Монтаж радиотелевизионного и электронного оборудования | EM33: ТСН-2001.4-10-2 | EO33: Поправка: Гл.12.Прил.8.п.8. 3_12.00.01.11.001 Поправка: Гл.4.Прил.2.2.п.2.2.29_04.00.01.35.003 | EQ33: 0 | ER33: 76.52 | ES33: 0.37 | ET33: 0 | EU33: 0 | EV33: 76.15 | EW33: 5.37 | EX33: 0 | EY33: 0 | FQ33: 0 | FR33: 0 | FS33: 0 | FX33: 95 | FY33: 53 | GD33: 1 | GF33: 82209368 | GG33: 2 | GH33: 1 | GI33: 2 | GJ33: 0 | GK33: 0 | GL33: =ROUND(IF(AND(BH33=3,BI33=3,FS33<>0),P33,0),2) -> 0 | GM33: =ROUND(O33+X33+Y33,2)+GX33 -> 4164.49 | GN33: =IF(OR(BI33=0,BI33=1),GM33-GX33,0) -> 0 | GO33: =IF(BI33=2,GM33-GX33,0) -> 4164.49 | GP33: =IF(BI33=4,GM33-GX33,0) -> 0 | GR33: 0 | GS33: 3 | GT33: 0 | GV33: =ROUND((GT33),6) -> 0 | GW33: 1 | GX33: =ROUND(HC33*I33,2) -> 0 | HA33: 0 | HB33: 0 | HC33: =GV33*GW33 -> 0 | HS33: 0 | IK33: 0
A34: 17 | B34: 1 | C34: =ROW(SmtRes!A45) -> 45 | D34: =ROW(EtalonRes!A51) -> 51 | E34: 4 | F34: 4.10-21-5 | G34: Грозозащита для воздушных абонентских линий / демонтаж грозозащиты | H34: 1 комплект | I34: 1 | J34: 0 | K34: 1 | O34: =ROUND(CP34,2) -> 14.27 | P34: =ROUND((ROUND((AC34*AW34*I34),2)*BC34),2) -> 0 | Q34: =(ROUND((ROUND(((((ET34*1.2)*0.3))*AV34*I34),2)*BB34),2)+ROUND((ROUND(((AE34-(((EU34*1.2)*0.3)))*AV34*I34),2)*BS34),2)) -> 0 | R34: =(ROUND((ROUND(((((EU34*1.2)*0.3))*AV34*I34),2)*BS34),2)+ROUND((ROUND(((AE34-(((EU34*1.2)*0.3)))*AV34*I34),2)*BS34),2)) -> 0 | S34: =ROUND((ROUND((AF34*AV34*I34),2)*BA34),2) -> 14.27 | T34: =ROUND(CU34*I34,2) -> 0 | U34: =CV34*I34 -> 1.13076 | V34: =CW34*I34 -> 0 | W34: =ROUND(CX34*I34,2) -> 0 | X34: =(ROUND((((S34+ROUND((ROUND(((((EU34*1.2)*0.3))*AV34*I34),2)*BS34),2))*AT34)/100),2)+ROUND(((ROUND((ROUND(((AE34-(((EU34*1.2)*0.3)))*AV34*I34),2)*BS34),2)*AT34)/100),2)) -> 12.84 | Y34: =(ROUND((((S34+ROUND((ROUND(((((EU34*1.2)*0.3))*AV34*I34),2)*BS34),2))*AU34)/100),2)+ROUND(((ROUND((ROUND(((AE34-(((EU34*1.2)*0.3)))*AV34*I34),2)*BS34),2)*AU34)/100),2)) -> 6.56 | AA34: 55917797 | AB34: =ROUND((AC34+AD34+AF34),6) -> 13.6296 | AC34: =ROUND((((ES34*1)*0)),6) -> 0 | AD34: =ROUND((((((ET34*1.2)*0.3))-(((EU34*1.2)*0.3)))+AE34),6) -> 0 | AE34: =ROUND((((EU34*1.2)*0.3)),6) -> 0 | AF34: =ROUND((((EV34*1.2)*0.3)),6) -> 13.6296 | AG34: =ROUND((AP34),6) -> 0 | AH34: =(((EW34*1.2)*0.3)) -> 1.08 | AI34: =(((EX34*1.2)*0.3)) -> 0 | AJ34: =(AS34) -> 0 | AK34: 80.47 | AL34: 42.61 | AM34: 0 | AN34: 0 | AO34: 37.86 | AP34: 0 | AQ34: 3 | AR34: 0 | AS34: 0 | AT34: 90 | AU34: 46 | AV34: 1.047 | AW34: 1 | AZ34: 1 | BA34: 1 | BB34: 1 | BC34: 1 | BH34: 0 | BI34: 2 | BJ34: ТСН-2001.4 Доп. 79, Сб. 10, т. 21, поз. 5 | BM34: 68 | BN34: 0 | BO34: 4.10-21-5 | BP34: 1 | BQ34: 40 | BR34: 0 | BS34: 1 | BT34: 1 | BU34: 1 | BV34: 1 | BW34: 1 | BX34: 1 | BZ34: 90 | CA34: 46 | CE34: 1566 | CF34: 0 | CG34: 0 | CM34: 0 | CN34: Поправка: Гл.12.Прил.8.п.8. 3_12.00.01.11.001 Наименование: При наличии напряженных и стесненных условий производства работ (стесненность, сложность складирования и транспортной логистики и т.п.) для объектов, расположенных в пределах круговой магистральной системы улиц "Садовое кольцо" города Москвы Поправка: Гл.4.Прил.2.2.п.2.2.29_04.00.01.35.003 Наименование: При демонтаже оборудования, предназначенного в лом | CO34: 0 | CP34: =(P34+Q34+S34) -> 14.27 | CQ34: =ROUND((ROUND((AC34*AW34*1),2)*BC34),2) -> 0 | CR34: =(ROUND((ROUND(((((ET34*1.2)*0.3))*AV34*1),2)*BB34),2)+ROUND((ROUND(((AE34-(((EU34*1.2)*0.3)))*AV34*1),2)*BS34),2)) -> 0 | CS34: =(ROUND((ROUND(((((EU34*1.2)*0.3))*AV34*1),2)*BS34),2)+ROUND((ROUND(((AE34-(((EU34*1.2)*0.3)))*AV34*1),2)*BS34),2)) -> 0 | CT34: =ROUND((ROUND((AF34*AV34*1),2)*BA34),2) -> 14.27 | CU34: =AG34 -> 0 | CV34: =(AH34*AV34) -> 1.13076 | CW34: =AI34 -> 0 | CX34: =AJ34 -> 0 | CY34: =(ROUND((((S34+ROUND((ROUND(((((EU34*1.2)*0.3))*AV34*1),2)*BS34),2))*AT34)/100),2)+ROUND(((ROUND((ROUND(((AE34-(((EU34*1.2)*0.3)))*AV34*1),2)*BS34),2)*AT34)/100),2)) -> 12.84 | CZ34: =(ROUND((((S34+ROUND((ROUND(((((EU34*1.2)*0.3))*AV34*1),2)*BS34),2))*AU34)/100),2)+ROUND(((ROUND((ROUND(((AE34-(((EU34*1.2)*0.3)))*AV34*1),2)*BS34),2)*AU34)/100),2)) -> 6.56 | DB34: 13 | DD34: *1)*0 | DE34: *1,2)*0,3 | DF34: *1,2)*0,3 | DG34: *1,2)*0,3 | DI34: *1,2)*0,3 | DJ34: *1,2)*0,3 | DN34: 0 | DO34: 0 | DP34: 1 | DQ34: 1 | DU34: 1013 | DV34: 1 комплект | DW34: 1 комплект | DX34: 1 | EE34: 55393700 | EF34: 40 | EG34: Монтаж оборудования | EH34: 0 | EJ34: 2 | EK34: 68 | EL34: ТСН-2001.4-10. Прокладка и монтаж сетей связи | EM34: ТСН-2001.4-10-1 | EO34: Поправка: Гл.12.Прил.8.п.8. 3_12.00.01.11.001 Поправка: Гл.4.Прил.2.2.п.2.2.29_04.00.01.35.003 | EQ34: 0 | ER34: 80.47 | ES34: 42.61 | ET34: 0 | EU34: 0 | EV34: 37.86 | EW34: 3 | EX34: 0 | EY34: 0 | FQ34: 0 | FR34: 0 | FS34: 0 | FX34: 90 | FY34: 46 | GD34: 1 | GF34: -1588285181 | GG34: 2 | GH34: 1 | GI34: 2 | GJ34: 0 | GK34: 0 | GL34: =ROUND(IF(AND(BH34=3,BI34=3,FS34<>0),P34,0),2) -> 0 | GM34: =ROUND(O34+X34+Y34,2)+GX34 -> 33.67 | GN34: =IF(OR(BI34=0,BI34=1),GM34-GX34,0) -> 0 | GO34: =IF(BI34=2,GM34-GX34,0) -> 33.67 | GP34: =IF(BI34=4,GM34-GX34,0) -> 0 | GR34: 0 | GS34: 3 | GT34: 0 | GV34: =ROUND((GT34),6) -> 0 | GW34: 1 | GX34: =ROUND(HC34*I34,2) -> 0 | HA34: 0 | HB34: 0 | HC34: =GV34*GW34 -> 0 | HS34: 0 | IK34: 0
A35: 17 | B35: 1 | C35: =ROW(SmtRes!A60) -> 60 | D35: =ROW(EtalonRes!A68) -> 68 | E35: 4 | F35: 4.10-21-5 | G35: Грозозащита для воздушных абонентских линий / демонтаж грозозащиты | H35: 1 комплект | I35: 1 | J35: 0 | K35: 1 | O35: =ROUND(CP35,2) -> 804.11 | P35: =ROUND((ROUND((AC35*AW35*I35),2)*BC35),2) -> 0 | Q35: =(ROUND((ROUND(((((ET35*1.2)*0.3))*AV35*I35),2)*BB35),2)+ROUND((ROUND(((AE35-(((EU35*1.2)*0.3)))*AV35*I35),2)*BS35),2)) -> 0 | R35: =(ROUND((ROUND(((((EU35*1.2)*0.3))*AV35*I35),2)*BS35),2)+ROUND((ROUND(((AE35-(((EU35*1.2)*0.3)))*AV35*I35),2)*BS35),2)) -> 0 | S35: =ROUND((ROUND((AF35*AV35*I35),2)*BA35),2) -> 804.11 | T35: =ROUND(CU35*I35,2) -> 0 | U35: =CV35*I35 -> 1.13076 | V35: =CW35*I35 -> 0 | W35: =ROUND(CX35*I35,2) -> 0 | X35: =(ROUND((((S35+ROUND((ROUND(((((EU35*1.2)*0.3))*AV35*I35),2)*BS35),2))*AT35)/100),2)+ROUND(((ROUND((ROUND(((AE35-(((EU35*1.2)*0.3)))*AV35*I35),2)*BS35),2)*AT35)/100),2)) -> 723.7 | Y35: =(ROUND((((S35+ROUND((ROUND(((((EU35*1.2)*0.3))*AV35*I35),2)*BS35),2))*AU35)/100),2)+ROUND(((ROUND((ROUND(((AE35-(((EU35*1.2)*0.3)))*AV35*I35),2)*BS35),2)*AU35)/100),2)) -> 369.89 | AA35: 55917799 | AB35: =ROUND((AC35+AD35+AF35),6) -> 13.6296 | AC35: =ROUND((((ES35*1)*0)),6) -> 0 | AD35: =ROUND((((((ET35*1.2)*0.3))-(((EU35*1.2)*0.3)))+AE35),6) -> 0 | AE35: =ROUND((((EU35*1.2)*0.3)),6) -> 0 | AF35: =ROUND((((EV35*1.2)*0.3)),6) -> 13.6296 | AG35: =ROUND((AP35),6) -> 0 | AH35: =(((EW35*1.2)*0.3)) -> 1.08 | AI35: =(((EX35*1.2)*0.3)) -> 0 | AJ35: =(AS35) -> 0 | AK35: 80.47 | AL35: 42.61 | AM35: 0 | AN35: 0 | AO35: 37.86 | AP35: 0 | AQ35: 3 | AR35: 0 | AS35: 0 | AT35: 90 | AU35: 46 | AV35: 1.047 | AW35: 1 | AZ35: 1 | BA35: 56.35 | BB35: 1 | BC35: 5.15 | BH35: 0 | BI35: 2 | BJ35: ТСН-2001.4 Доп. 79, Сб. 10, т. 21, поз. 5 | BM35: 68 | BN35: 0 | BO35: 4.10-21-5 | BP35: 1 | BQ35: 40 | BR35: 0 | BS35: 56.35 | BT35: 1 | BU35: 1 | BV35: 1 | BW35: 1 | BX35: 1 | BZ35: 90 | CA35: 46 | CE35: 1566 | CF35: 0 | CG35: 0 | CM35: 0 | CN35: Поправка: Гл.12.Прил.8.п.8. 3_12.00.01.11.001 Наименование: При наличии напряженных и стесненных условий производства работ (стесненность, сложность складирования и транспортной логистики и т.п.) для объектов, расположенных в пределах круговой магистральной системы улиц "Садовое кольцо" города Москвы Поправка: Гл.4.Прил.2.2.п.2.2.29_04.00.01.35.003 Наименование: При демонтаже оборудования, предназначенного в лом | CO35: 0 | CP35: =(P35+Q35+S35) -> 804.11 | CQ35: =ROUND((ROUND((AC35*AW35*1),2)*BC35),2) -> 0 | CR35: =(ROUND((ROUND(((((ET35*1.2)*0.3))*AV35*1),2)*BB35),2)+ROUND((ROUND(((AE35-(((EU35*1.2)*0.3)))*AV35*1),2)*BS35),2)) -> 0 | CS35: =(ROUND((ROUND(((((EU35*1.2)*0.3))*AV35*1),2)*BS35),2)+ROUND((ROUND(((AE35-(((EU35*1.2)*0.3)))*AV35*1),2)*BS35),2)) -> 0 | CT35: =ROUND((ROUND((AF35*AV35*1),2)*BA35),2) -> 804.11 | CU35: =AG35 -> 0 | CV35: =(AH35*AV35) -> 1.13076 | CW35: =AI35 -> 0 | CX35: =AJ35 -> 0 | CY35: =(ROUND((((S35+ROUND((ROUND(((((EU35*1.2)*0.3))*AV35*1),2)*BS35),2))*AT35)/100),2)+ROUND(((ROUND((ROUND(((AE35-(((EU35*1.2)*0.3)))*AV35*1),2)*BS35),2)*AT35)/100),2)) -> 723.7 | CZ35: =(ROUND((((S35+ROUND((ROUND(((((EU35*1.2)*0.3))*AV35*1),2)*BS35),2))*AU35)/100),2)+ROUND(((ROUND((ROUND(((AE35-(((EU35*1.2)*0.3)))*AV35*1),2)*BS35),2)*AU35)/100),2)) -> 369.89 | DB35: 15 | DD35: *1)*0 | DE35: *1,2)*0,3 | DF35: *1,2)*0,3 | DG35: *1,2)*0,3 | DI35: *1,2)*0,3 | DJ35: *1,2)*0,3 | DN35: 0 | DO35: 0 | DP35: 1 | DQ35: 1 | DU35: 1013 | DV35: 1 комплект | DW35: 1 комплект | DX35: 1 | EE35: 55393700 | EF35: 40 | EG35: Монтаж оборудования | EH35: 0 | EJ35: 2 | EK35: 68 | EL35: ТСН-2001.4-10. Прокладка и монтаж сетей связи | EM35: ТСН-2001.4-10-1 | EO35: Поправка: Гл.12.Прил.8.п.8. 3_12.00.01.11.001 Поправка: Гл.4.Прил.2.2.п.2.2.29_04.00.01.35.003 | EQ35: 0 | ER35: 80.47 | ES35: 42.61 | ET35: 0 | EU35: 0 | EV35: 37.86 | EW35: 3 | EX35: 0 | EY35: 0 | FQ35: 0 | FR35: 0 | FS35: 0 | FX35: 90 | FY35: 46 | GD35: 1 | GF35: -1588285181 | GG35: 2 | GH35: 1 | GI35: 2 | GJ35: 0 | GK35: 0 | GL35: =ROUND(IF(AND(BH35=3,BI35=3,FS35<>0),P35,0),2) -> 0 | GM35: =ROUND(O35+X35+Y35,2)+GX35 -> 1897.7 | GN35: =IF(OR(BI35=0,BI35=1),GM35-GX35,0) -> 0 | GO35: =IF(BI35=2,GM35-GX35,0) -> 1897.7 | GP35: =IF(BI35=4,GM35-GX35,0) -> 0 | GR35: 0 | GS35: 3 | GT35: 0 | GV35: =ROUND((GT35),6) -> 0 | GW35: 1 | GX35: =ROUND(HC35*I35,2) -> 0 | HA35: 0 | HB35: 0 | HC35: =GV35*GW35 -> 0 | HS35: 0 | IK35: 0
A36: 17 | B36: 1 | C36: =ROW(SmtRes!A65) -> 65 | D36: =ROW(EtalonRes!A74) -> 74 | E36: 5 | F36: 4.10-118-12 | G36: Установка для трубных проводок коробки оконечной / демонтаж | H36: 100 шт. | I36: =ROUND(7/100,9) -> 0.07 | J36: 0 | K36: =ROUND(7/100,9) -> 0.07 | O36: =ROUND(CP36,2) -> 7.35 | P36: =ROUND((ROUND((AC36*AW36*I36),2)*BC36),2) -> 0 | Q36: =(ROUND((ROUND(((((ET36*1.2)*0.3))*AV36*I36),2)*BB36),2)+ROUND((ROUND(((AE36-(((EU36*1.2)*0.3)))*AV36*I36),2)*BS36),2)) -> 0 | R36: =(ROUND((ROUND(((((EU36*1.2)*0.3))*AV36*I36),2)*BS36),2)+ROUND((ROUND(((AE36-(((EU36*1.2)*0.3)))*AV36*I36),2)*BS36),2)) -> 0 | S36: =ROUND((ROUND((AF36*AV36*I36),2)*BA36),2) -> 7.35 | T36: =ROUND(CU36*I36,2) -> 0 | U36: =CV36*I36 -> 0.6332256 | V36: =CW36*I36 -> 0 | W36: =ROUND(CX36*I36,2) -> 0 | X36: =(ROUND((((S36+ROUND((ROUND(((((EU36*1.2)*0.3))*AV36*I36),2)*BS36),2))*AT36)/100),2)+ROUND(((ROUND((ROUND(((AE36-(((EU36*1.2)*0.3)))*AV36*I36),2)*BS36),2)*AT36)/100),2)) -> 6.62 | Y36: =(ROUND((((S36+ROUND((ROUND(((((EU36*1.2)*0.3))*AV36*I36),2)*BS36),2))*AU36)/100),2)+ROUND(((ROUND((ROUND(((AE36-(((EU36*1.2)*0.3)))*AV36*I36),2)*BS36),2)*AU36)/100),2)) -> 3.38 | AA36: 55917797 | AB36: =ROUND((AC36+AD36+AF36),6) -> 100.3104 | AC36: =ROUND((((ES36*1)*0)),6) -> 0 | AD36: =ROUND((((((ET36*1.2)*0.3))-(((EU36*1.2)*0.3)))+AE36),6) -> 0 | AE36: =ROUND((((EU36*1.2)*0.3)),6) -> 0 | AF36: =ROUND((((EV36*1.2)*0.3)),6) -> 100.3104 | AG36: =ROUND((AP36),6) -> 0 | AH36: =(((EW36*1.2)*0.3)) -> 8.64 | AI36: =(((EX36*1.2)*0.3)) -> 0 | AJ36: =(AS36) -> 0 | AK36: 364.24 | AL36: 85.6 | AM36: 0 | AN36: 0 | AO36: 278.64 | AP36: 0 | AQ36: 24 | AR36: 0 | AS36: 0 | AT36: 90 | AU36: 46 | AV36: 1.047 | AW36: 1 | AZ36: 1 | BA36: 1 | BB36: 1 | BC36: 1 | BH36: 0 | BI36: 2 | BJ36: ТСН-2001.4 Доп. 79, Сб. 10, т. 118, поз. 12 | BM36: 68 | BN36: 0 | BO36: 4.10-118-12 | BP36: 1 | BQ36: 40 | BR36: 0 | BS36: 1 | BT36: 1 | BU36: 1 | BV36: 1 | BW36: 1 | BX36: 1 | BZ36: 90 | CA36: 46 | CE36: 1566 | CF36: 0 | CG36: 0 | CM36: 0 | CN36: Поправка: Гл.12.Прил.8.п.8. 3_12.00.01.11.001 Наименование: При наличии напряженных и стесненных условий производства работ (стесненность, сложность складирования и транспортной логистики и т.п.) для объектов, расположенных в пределах круговой магистральной системы улиц "Садовое кольцо" города Москвы Поправка: Гл.4.Прил.2.2.п.2.2.29_04.00.01.35.003 Наименование: При демонтаже оборудования, предназначенного в лом | CO36: 0 | CP36: =(P36+Q36+S36) -> 7.35 | CQ36: =ROUND((ROUND((AC36*AW36*1),2)*BC36),2) -> 0 | CR36: =(ROUND((ROUND(((((ET36*1.2)*0.3))*AV36*1),2)*BB36),2)+ROUND((ROUND(((AE36-(((EU36*1.2)*0.3)))*AV36*1),2)*BS36),2)) -> 0 | CS36: =(ROUND((ROUND(((((EU36*1.2)*0.3))*AV36*1),2)*BS36),2)+ROUND((ROUND(((AE36-(((EU36*1.2)*0.3)))*AV36*1),2)*BS36),2)) -> 0 | CT36: =ROUND((ROUND((AF36*AV36*1),2)*BA36),2) -> 105.02 | CU36: =AG36 -> 0 | CV36: =(AH36*AV36) -> 9.04608 | CW36: =AI36 -> 0 | CX36: =AJ36 -> 0 | CY36: =(ROUND((((S36+ROUND((ROUND(((((EU36*1.2)*0.3))*AV36*1),2)*BS36),2))*AT36)/100),2)+ROUND(((ROUND((ROUND(((AE36-(((EU36*1.2)*0.3)))*AV36*1),2)*BS36),2)*AT36)/100),2)) -> 6.62 | CZ36: =(ROUND((((S36+ROUND((ROUND(((((EU36*1.2)*0.3))*AV36*1),2)*BS36),2))*AU36)/100),2)+ROUND(((ROUND((ROUND(((AE36-(((EU36*1.2)*0.3)))*AV36*1),2)*BS36),2)*AU36)/100),2)) -> 3.38 | DB36: 17 | DD36: *1)*0 | DE36: *1,2)*0,3 | DF36: *1,2)*0,3 | DG36: *1,2)*0,3 | DI36: *1,2)*0,3 | DJ36: *1,2)*0,3 | DN36: 0 | DO36: 0 | DP36: 1 | DQ36: 1 | DU36: 1010 | DV36: 100 шт. | DW36: 100 шт. | DX36: 100 | EE36: 55393700 | EF36: 40 | EG36: Монтаж оборудования | EH36: 0 | EJ36: 2 | EK36: 68 | EL36: ТСН-2001.4-10. Прокладка и монтаж сетей связи | EM36: ТСН-2001.4-10-1 | EO36: Поправка: Гл.12.Прил.8.п.8. 3_12.00.01.11.001 Поправка: Гл.4.Прил.2.2.п.2.2.29_04.00.01.35.003 | EQ36: 0 | ER36: 364.24 | ES36: 85.6 | ET36: 0 | EU36: 0 | EV36: 278.64 | EW36: 24 | EX36: 0 | EY36: 0 | FQ36: 0 | FR36: 0 | FS36: 0 | FX36: 90 | FY36: 46 | GD36: 1 | GF36: -1053927933 | GG36: 2 | GH36: 1 | GI36: 2 | GJ36: 0 | GK36: 0 | GL36: =ROUND(IF(AND(BH36=3,BI36=3,FS36<>0),P36,0),2) -> 0 | GM36: =ROUND(O36+X36+Y36,2)+GX36 -> 17.35 | GN36: =IF(OR(BI36=0,BI36=1),GM36-GX36,0) -> 0 | GO36: =IF(BI36=2,GM36-GX36,0) -> 17.35 | GP36: =IF(BI36=4,GM36-GX36,0) -> 0 | GR36: 0 | GS36: 3 | GT36: 0 | GV36: =ROUND((GT36),6) -> 0 | GW36: 1 | GX36: =ROUND(HC36*I36,2) -> 0 | HA36: 0 | HB36: 0 | HC36: =GV36*GW36 -> 0 | HS36: 0 | IK36: 0
A37: 17 | B37: 1 | C37: =ROW(SmtRes!A70) -> 70 | D37: =ROW(EtalonRes!A80) -> 80 | E37: 5 | F37: 4.10-118-12 | G37: Установка для трубных проводок коробки оконечной / демонтаж | H37: 100 шт. | I37: =ROUND(7/100,9) -> 0.07 | J37: 0 | K37: =ROUND(7/100,9) -> 0.07 | O37: =ROUND(CP37,2) -> 414.17 | P37: =ROUND((ROUND((AC37*AW37*I37),2)*BC37),2) -> 0 | Q37: =(ROUND((ROUND(((((ET37*1.2)*0.3))*AV37*I37),2)*BB37),2)+ROUND((ROUND(((AE37-(((EU37*1.2)*0.3)))*AV37*I37),2)*BS37),2)) -> 0 | R37: =(ROUND((ROUND(((((EU37*1.2)*0.3))*AV37*I37),2)*BS37),2)+ROUND((ROUND(((AE37-(((EU37*1.2)*0.3)))*AV37*I37),2)*BS37),2)) -> 0 | S37: =ROUND((ROUND((AF37*AV37*I37),2)*BA37),2) -> 414.17 | T37: =ROUND(CU37*I37,2) -> 0 | U37: =CV37*I37 -> 0.6332256 | V37: =CW37*I37 -> 0 | W37: =ROUND(CX37*I37,2) -> 0 | X37: =(ROUND((((S37+ROUND((ROUND(((((EU37*1.2)*0.3))*AV37*I37),2)*BS37),2))*AT37)/100),2)+ROUND(((ROUND((ROUND(((AE37-(((EU37*1.2)*0.3)))*AV37*I37),2)*BS37),2)*AT37)/100),2)) -> 372.75 | Y37: =(ROUND((((S37+ROUND((ROUND(((((EU37*1.2)*0.3))*AV37*I37),2)*BS37),2))*AU37)/100),2)+ROUND(((ROUND((ROUND(((AE37-(((EU37*1.2)*0.3)))*AV37*I37),2)*BS37),2)*AU37)/100),2)) -> 190.52 | AA37: 55917799 | AB37: =ROUND((AC37+AD37+AF37),6) -> 100.3104 | AC37: =ROUND((((ES37*1)*0)),6) -> 0 | AD37: =ROUND((((((ET37*1.2)*0.3))-(((EU37*1.2)*0.3)))+AE37),6) -> 0 | AE37: =ROUND((((EU37*1.2)*0.3)),6) -> 0 | AF37: =ROUND((((EV37*1.2)*0.3)),6) -> 100.3104 | AG37: =ROUND((AP37),6) -> 0 | AH37: =(((EW37*1.2)*0.3)) -> 8.64 | AI37: =(((EX37*1.2)*0.3)) -> 0 | AJ37: =(AS37) -> 0 | AK37: 364.24 | AL37: 85.6 | AM37: 0 | AN37: 0 | AO37: 278.64 | AP37: 0 | AQ37: 24 | AR37: 0 | AS37: 0 | AT37: 90 | AU37: 46 | AV37: 1.047 | AW37: 1 | AZ37: 1 | BA37: 56.35 | BB37: 1 | BC37: 5.06 | BH37: 0 | BI37: 2 | BJ37: ТСН-2001.4 Доп. 79, Сб. 10, т. 118, поз. 12 | BM37: 68 | BN37: 0 | BO37: 4.10-118-12 | BP37: 1 | BQ37: 40 | BR37: 0 | BS37: 56.35 | BT37: 1 | BU37: 1 | BV37: 1 | BW37: 1 | BX37: 1 | BZ37: 90 | CA37: 46 | CE37: 1566 | CF37: 0 | CG37: 0 | CM37: 0 | CN37: Поправка: Гл.12.Прил.8.п.8. 3_12.00.01.11.001 Наименование: При наличии напряженных и стесненных условий производства работ (стесненность, сложность складирования и транспортной логистики и т.п.) для объектов, расположенных в пределах круговой магистральной системы улиц "Садовое кольцо" города Москвы Поправка: Гл.4.Прил.2.2.п.2.2.29_04.00.01.35.003 Наименование: При демонтаже оборудования, предназначенного в лом | CO37: 0 | CP37: =(P37+Q37+S37) -> 414.17 | CQ37: =ROUND((ROUND((AC37*AW37*1),2)*BC37),2) -> 0 | CR37: =(ROUND((ROUND(((((ET37*1.2)*0.3))*AV37*1),2)*BB37),2)+ROUND((ROUND(((AE37-(((EU37*1.2)*0.3)))*AV37*1),2)*BS37),2)) -> 0 | CS37: =(ROUND((ROUND(((((EU37*1.2)*0.3))*AV37*1),2)*BS37),2)+ROUND((ROUND(((AE37-(((EU37*1.2)*0.3)))*AV37*1),2)*BS37),2)) -> 0 | CT37: =ROUND((ROUND((AF37*AV37*1),2)*BA37),2) -> 5917.88 | CU37: =AG37 -> 0 | CV37: =(AH37*AV37) -> 9.04608 | CW37: =AI37 -> 0 | CX37: =AJ37 -> 0 | CY37: =(ROUND((((S37+ROUND((ROUND(((((EU37*1.2)*0.3))*AV37*1),2)*BS37),2))*AT37)/100),2)+ROUND(((ROUND((ROUND(((AE37-(((EU37*1.2)*0.3)))*AV37*1),2)*BS37),2)*AT37)/100),2)) -> 372.75 | CZ37: =(ROUND((((S37+ROUND((ROUND(((((EU37*1.2)*0.3))*AV37*1),2)*BS37),2))*AU37)/100),2)+ROUND(((ROUND((ROUND(((AE37-(((EU37*1.2)*0.3)))*AV37*1),2)*BS37),2)*AU37)/100),2)) -> 190.52 | DB37: 19 | DD37: *1)*0 | DE37: *1,2)*0,3 | DF37: *1,2)*0,3 | DG37: *1,2)*0,3 | DI37: *1,2)*0,3 | DJ37: *1,2)*0,3 | DN37: 0 | DO37: 0 | DP37: 1 | DQ37: 1 | DU37: 1010 | DV37: 100 шт. | DW37: 100 шт. | DX37: 100 | EE37: 55393700 | EF37: 40 | EG37: Монтаж оборудования | EH37: 0 | EJ37: 2 | EK37: 68 | EL37: ТСН-2001.4-10. Прокладка и монтаж сетей связи | EM37: ТСН-2001.4-10-1 | EO37: Поправка: Гл.12.Прил.8.п.8. 3_12.00.01.11.001 Поправка: Гл.4.Прил.2.2.п.2.2.29_04.00.01.35.003 | EQ37: 0 | ER37: 364.24 | ES37: 85.6 | ET37: 0 | EU37: 0 | EV37: 278.64 | EW37: 24 | EX37: 0 | EY37: 0 | FQ37: 0 | FR37: 0 | FS37: 0 | FX37: 90 | FY37: 46 | GD37: 1 | GF37: -1053927933 | GG37: 2 | GH37: 1 | GI37: 2 | GJ37: 0 | GK37: 0 | GL37: =ROUND(IF(AND(BH37=3,BI37=3,FS37<>0),P37,0),2) -> 0 | GM37: =ROUND(O37+X37+Y37,2)+GX37 -> 977.44 | GN37: =IF(OR(BI37=0,BI37=1),GM37-GX37,0) -> 0 | GO37: =IF(BI37=2,GM37-GX37,0) -> 977.44 | GP37: =IF(BI37=4,GM37-GX37,0) -> 0 | GR37: 0 | GS37: 3 | GT37: 0 | GV37: =ROUND((GT37),6) -> 0 | GW37: 1 | GX37: =ROUND(HC37*I37,2) -> 0 | HA37: 0 | HB37: 0 | HC37: =GV37*GW37 -> 0 | HS37: 0 | IK37: 0
A38: 17 | B38: 1 | C38: =ROW(SmtRes!A71) -> 71 | D38: =ROW(EtalonRes!A81) -> 81 | E38: 6 | F38: 6.67-7-1 | G38: Демонтаж осветительных приборов, выключатели, розетки | H38: 100 шт. | I38: =ROUND(6/100,9) -> 0.06 | J38: 0 | K38: =ROUND(6/100,9) -> 0.06 | O38: =ROUND(CP38,2) -> 4.5 | P38: =ROUND((ROUND((AC38*AW38*I38),2)*BC38),2) -> 0 | Q38: =(ROUND((ROUND((((ET38*1.2))*AV38*I38),2)*BB38),2)+ROUND((ROUND(((AE38-((EU38*1.2)))*AV38*I38),2)*BS38),2)) -> 0 | R38: =(ROUND((ROUND((((EU38*1.2))*AV38*I38),2)*BS38),2)+ROUND((ROUND(((AE38-((EU38*1.2)))*AV38*I38),2)*BS38),2)) -> 0 | S38: =ROUND((ROUND((AF38*AV38*I38),2)*BA38),2) -> 4.5 | T38: =ROUND(CU38*I38,2) -> 0 | U38: =CV38*I38 -> 0.44024256 | V38: =CW38*I38 -> 0 | W38: =ROUND(CX38*I38,2) -> 0 | X38: =(ROUND((((S38+ROUND((ROUND((((EU38*1.2))*AV38*I38),2)*BS38),2))*AT38)/100),2)+ROUND(((ROUND((ROUND(((AE38-((EU38*1.2)))*AV38*I38),2)*BS38),2)*AT38)/100),2)) -> 4.1 | Y38: =(ROUND((((S38+ROUND((ROUND((((EU38*1.2))*AV38*I38),2)*BS38),2))*AU38)/100),2)+ROUND(((ROUND((ROUND(((AE38-((EU38*1.2)))*AV38*I38),2)*BS38),2)*AU38)/100),2)) -> 2.16 | AA38: 55917797 | AB38: =ROUND((AC38+AD38+AF38),6) -> 71.616 | AC38: =ROUND(((ES38*1)),6) -> 0 | AD38: =ROUND(((((ET38*1.2))-((EU38*1.2)))+AE38),6) -> 0 | AE38: =ROUND(((EU38*1.2)),6) -> 0 | AF38: =ROUND(((EV38*1.2)),6) -> 71.616 | AG38: =ROUND((AP38),6) -> 0 | AH38: =((EW38*1.2)) -> 7.008 | AI38: =((EX38*1.2)) -> 0 | AJ38: =(AS38) -> 0 | AK38: 59.68 | AL38: 0 | AM38: 0 | AN38: 0 | AO38: 59.68 | AP38: 0 | AQ38: 5.84 | AR38: 0 | AS38: 0 | AT38: 91 | AU38: 48 | AV38: 1.047 | AW38: 1 | AZ38: 1 | BA38: 1 | BB38: 1 | BC38: 1 | BH38: 0 | BI38: 1 | BJ38: ТСН-2001.6. Доп. 1-42. Сб. 67, т. 7, поз. 1 | BM38: 106 | BN38: 0 | BO38: 6.67-7-1 | BP38: 1 | BQ38: 60 | BR38: 0 | BS38: 1 | BT38: 1 | BU38: 1 | BV38: 1 | BW38: 1 | BX38: 1 | BZ38: 91 | CA38: 48 | CE38: 1566 | CF38: 0 | CG38: 0 | CM38: 0 | CN38: Поправка: Гл.12.Прил.8.п.8. 3_12.00.01.11.001 Наименование: При наличии напряженных и стесненных условий производства работ (стесненность, сложность складирования и транспортной логистики и т.п.) для объектов, расположенных в пределах круговой магистральной системы улиц "Садовое кольцо" города Москвы | CO38: 0 | CP38: =(P38+Q38+S38) -> 4.5 | CQ38: =ROUND((ROUND((AC38*AW38*1),2)*BC38),2) -> 0 | CR38: =(ROUND((ROUND((((ET38*1.2))*AV38*1),2)*BB38),2)+ROUND((ROUND(((AE38-((EU38*1.2)))*AV38*1),2)*BS38),2)) -> 0 | CS38: =(ROUND((ROUND((((EU38*1.2))*AV38*1),2)*BS38),2)+ROUND((ROUND(((AE38-((EU38*1.2)))*AV38*1),2)*BS38),2)) -> 0 | CT38: =ROUND((ROUND((AF38*AV38*1),2)*BA38),2) -> 74.98 | CU38: =AG38 -> 0 | CV38: =(AH38*AV38) -> 7.337376 | CW38: =AI38 -> 0 | CX38: =AJ38 -> 0 | CY38: =(ROUND((((S38+ROUND((ROUND((((EU38*1.2))*AV38*1),2)*BS38),2))*AT38)/100),2)+ROUND(((ROUND((ROUND(((AE38-((EU38*1.2)))*AV38*1),2)*BS38),2)*AT38)/100),2)) -> 4.1 | CZ38: =(ROUND((((S38+ROUND((ROUND((((EU38*1.2))*AV38*1),2)*BS38),2))*AU38)/100),2)+ROUND(((ROUND((ROUND(((AE38-((EU38*1.2)))*AV38*1),2)*BS38),2)*AU38)/100),2)) -> 2.16 | DB38: 21 | DD38: *1 | DE38: *1,2 | DF38: *1,2 | DG38: *1,2 | DI38: *1,2 | DJ38: *1,2 | DN38: 0 | DO38: 0 | DP38: 1 | DQ38: 1 | DU38: 1010 | DV38: 100 шт. | DW38: 100 шт. | DX38: 100 | EE38: 55393738 | EF38: 60 | EG38: Ремонтно-строительные работы | EH38: 0 | EJ38: 1 | EK38: 106 | EL38: ТСН-2001.6-67. Электромонтажные работы | EM38: ТСН-2001.6-67-1 | EO38: Поправка: Гл.12.Прил.8.п.8. 3_12.00.01.11.001 | EQ38: 0 | ER38: 59.68 | ES38: 0 | ET38: 0 | EU38: 0 | EV38: 59.68 | EW38: 5.84 | EX38: 0 | EY38: 0 | FQ38: 0 | FR38: 0 | FS38: 0 | FX38: 91 | FY38: 48 | GD38: 1 | GF38: 1478850760 | GG38: 2 | GH38: 1 | GI38: 2 | GJ38: 0 | GK38: 0 | GL38: =ROUND(IF(AND(BH38=3,BI38=3,FS38<>0),P38,0),2) -> 0 | GM38: =ROUND(O38+X38+Y38,2)+GX38 -> 10.76 | GN38: =IF(OR(BI38=0,BI38=1),GM38-GX38,0) -> 10.76 | GO38: =IF(BI38=2,GM38-GX38,0) -> 0 | GP38: =IF(BI38=4,GM38-GX38,0) -> 0 | GR38: 0 | GS38: 3 | GT38: 0 | GV38: =ROUND((GT38),6) -> 0 | GW38: 1 | GX38: =ROUND(HC38*I38,2) -> 0 | HA38: 0 | HB38: 0 | HC38: =GV38*GW38 -> 0 | HS38: 0 | IK38: 0
A39: 17 | B39: 1 | C39: =ROW(SmtRes!A72) -> 72 | D39: =ROW(EtalonRes!A82) -> 82 | E39: 6 | F39: 6.67-7-1 | G39: Демонтаж осветительных приборов, выключатели, розетки | H39: 100 шт. | I39: =ROUND(6/100,9) -> 0.06 | J39: 0 | K39: =ROUND(6/100,9) -> 0.06 | O39: =ROUND(CP39,2) -> 253.58 | P39: =ROUND((ROUND((AC39*AW39*I39),2)*BC39),2) -> 0 | Q39: =(ROUND((ROUND((((ET39*1.2))*AV39*I39),2)*BB39),2)+ROUND((ROUND(((AE39-((EU39*1.2)))*AV39*I39),2)*BS39),2)) -> 0 | R39: =(ROUND((ROUND((((EU39*1.2))*AV39*I39),2)*BS39),2)+ROUND((ROUND(((AE39-((EU39*1.2)))*AV39*I39),2)*BS39),2)) -> 0 | S39: =ROUND((ROUND((AF39*AV39*I39),2)*BA39),2) -> 253.58 | T39: =ROUND(CU39*I39,2) -> 0 | U39: =CV39*I39 -> 0.44024256 | V39: =CW39*I39 -> 0 | W39: =ROUND(CX39*I39,2) -> 0 | X39: =(ROUND((((S39+ROUND((ROUND((((EU39*1.2))*AV39*I39),2)*BS39),2))*AT39)/100),2)+ROUND(((ROUND((ROUND(((AE39-((EU39*1.2)))*AV39*I39),2)*BS39),2)*AT39)/100),2)) -> 230.76 | Y39: =(ROUND((((S39+ROUND((ROUND((((EU39*1.2))*AV39*I39),2)*BS39),2))*AU39)/100),2)+ROUND(((ROUND((ROUND(((AE39-((EU39*1.2)))*AV39*I39),2)*BS39),2)*AU39)/100),2)) -> 121.72 | AA39: 55917799 | AB39: =ROUND((AC39+AD39+AF39),6) -> 71.616 | AC39: =ROUND(((ES39*1)),6) -> 0 | AD39: =ROUND(((((ET39*1.2))-((EU39*1.2)))+AE39),6) -> 0 | AE39: =ROUND(((EU39*1.2)),6) -> 0 | AF39: =ROUND(((EV39*1.2)),6) -> 71.616 | AG39: =ROUND((AP39),6) -> 0 | AH39: =((EW39*1.2)) -> 7.008 | AI39: =((EX39*1.2)) -> 0 | AJ39: =(AS39) -> 0 | AK39: 59.68 | AL39: 0 | AM39: 0 | AN39: 0 | AO39: 59.68 | AP39: 0 | AQ39: 5.84 | AR39: 0 | AS39: 0 | AT39: 91 | AU39: 48 | AV39: 1.047 | AW39: 1 | AZ39: 1 | BA39: 56.35 | BB39: 1 | BC39: 1 | BH39: 0 | BI39: 1 | BJ39: ТСН-2001.6. Доп. 1-42. Сб. 67, т. 7, поз. 1 | BM39: 106 | BN39: 0 | BO39: 6.67-7-1 | BP39: 1 | BQ39: 60 | BR39: 0 | BS39: 56.35 | BT39: 1 | BU39: 1 | BV39: 1 | BW39: 1 | BX39: 1 | BZ39: 91 | CA39: 48 | CE39: 1566 | CF39: 0 | CG39: 0 | CM39: 0 | CN39: Поправка: Гл.12.Прил.8.п.8. 3_12.00.01.11.001 Наименование: При наличии напряженных и стесненных условий производства работ (стесненность, сложность складирования и транспортной логистики и т.п.) для объектов, расположенных в пределах круговой магистральной системы улиц "Садовое кольцо" города Москвы | CO39: 0 | CP39: =(P39+Q39+S39) -> 253.58 | CQ39: =ROUND((ROUND((AC39*AW39*1),2)*BC39),2) -> 0 | CR39: =(ROUND((ROUND((((ET39*1.2))*AV39*1),2)*BB39),2)+ROUND((ROUND(((AE39-((EU39*1.2)))*AV39*1),2)*BS39),2)) -> 0 | CS39: =(ROUND((ROUND((((EU39*1.2))*AV39*1),2)*BS39),2)+ROUND((ROUND(((AE39-((EU39*1.2)))*AV39*1),2)*BS39),2)) -> 0 | CT39: =ROUND((ROUND((AF39*AV39*1),2)*BA39),2) -> 4225.12 | CU39: =AG39 -> 0 | CV39: =(AH39*AV39) -> 7.337376 | CW39: =AI39 -> 0 | CX39: =AJ39 -> 0 | CY39: =(ROUND((((S39+ROUND((ROUND((((EU39*1.2))*AV39*1),2)*BS39),2))*AT39)/100),2)+ROUND(((ROUND((ROUND(((AE39-((EU39*1.2)))*AV39*1),2)*BS39),2)*AT39)/100),2)) -> 230.76 | CZ39: =(ROUND((((S39+ROUND((ROUND((((EU39*1.2))*AV39*1),2)*BS39),2))*AU39)/100),2)+ROUND(((ROUND((ROUND(((AE39-((EU39*1.2)))*AV39*1),2)*BS39),2)*AU39)/100),2)) -> 121.72 | DB39: 22 | DD39: *1 | DE39: *1,2 | DF39: *1,2 | DG39: *1,2 | DI39: *1,2 | DJ39: *1,2 | DN39: 0 | DO39: 0 | DP39: 1 | DQ39: 1 | DU39: 1010 | DV39: 100 шт. | DW39: 100 шт. | DX39: 100 | EE39: 55393738 | EF39: 60 | EG39: Ремонтно-строительные работы | EH39: 0 | EJ39: 1 | EK39: 106 | EL39: ТСН-2001.6-67. Электромонтажные работы | EM39: ТСН-2001.6-67-1 | EO39: Поправка: Гл.12.Прил.8.п.8. 3_12.00.01.11.001 | EQ39: 0 | ER39: 59.68 | ES39: 0 | ET39: 0 | EU39: 0 | EV39: 59.68 | EW39: 5.84 | EX39: 0 | EY39: 0 | FQ39: 0 | FR39: 0 | FS39: 0 | FX39: 91 | FY39: 48 | GD39: 1 | GF39: 1478850760 | GG39: 2 | GH39: 1 | GI39: 2 | GJ39: 0 | GK39: 0 | GL39: =ROUND(IF(AND(BH39=3,BI39=3,FS39<>0),P39,0),2) -> 0 | GM39: =ROUND(O39+X39+Y39,2)+GX39 -> 606.06 | GN39: =IF(OR(BI39=0,BI39=1),GM39-GX39,0) -> 606.06 | GO39: =IF(BI39=2,GM39-GX39,0) -> 0 | GP39: =IF(BI39=4,GM39-GX39,0) -> 0 | GR39: 0 | GS39: 3 | GT39: 0 | GV39: =ROUND((GT39),6) -> 0 | GW39: 1 | GX39: =ROUND(HC39*I39,2) -> 0 | HA39: 0 | HB39: 0 | HC39: =GV39*GW39 -> 0 | HS39: 0 | IK39: 0
A40: 17 | B40: 1 | C40: =ROW(SmtRes!A74) -> 74 | D40: =ROW(EtalonRes!A85) -> 85 | E40: 7 | F40: 4.11-7-1 | G40: Установка аппарата настольного массой до 0,015 т / демонтаж приёмника | H40: 1 ШТ. | I40: 6 | J40: 0 | K40: 6 | O40: =ROUND(CP40,2) -> 56.13 | P40: =ROUND((ROUND((AC40*AW40*I40),2)*BC40),2) -> 0 | Q40: =(ROUND((ROUND(((((ET40*1.2)*0.3))*AV40*I40),2)*BB40),2)+ROUND((ROUND(((AE40-(((EU40*1.2)*0.3)))*AV40*I40),2)*BS40),2)) -> 30.08 | R40: =(ROUND((ROUND(((((EU40*1.2)*0.3))*AV40*I40),2)*BS40),2)+ROUND((ROUND(((AE40-(((EU40*1.2)*0.3)))*AV40*I40),2)*BS40),2)) -> 4.57 | S40: =ROUND((ROUND((AF40*AV40*I40),2)*BA40),2) -> 26.05 | T40: =ROUND(CU40*I40,2) -> 0 | U40: =CV40*I40 -> 2.3293656 | V40: =CW40*I40 -> 0 | W40: =ROUND(CX40*I40,2) -> 0 | X40: =(ROUND((((S40+ROUND((ROUND(((((EU40*1.2)*0.3))*AV40*I40),2)*BS40),2))*AT40)/100),2)+ROUND(((ROUND((ROUND(((AE40-(((EU40*1.2)*0.3)))*AV40*I40),2)*BS40),2)*AT40)/100),2)) -> 27.56 | Y40: =(ROUND((((S40+ROUND((ROUND(((((EU40*1.2)*0.3))*AV40*I40),2)*BS40),2))*AU40)/100),2)+ROUND(((ROUND((ROUND(((AE40-(((EU40*1.2)*0.3)))*AV40*I40),2)*BS40),2)*AU40)/100),2)) -> 14.09 | AA40: 55917797 | AB40: =ROUND((AC40+AD40+AF40),6) -> 8.9352 | AC40: =ROUND((((ES40*1)*0)),6) -> 0 | AD40: =ROUND((((((ET40*1.2)*0.3))-(((EU40*1.2)*0.3)))+AE40),6) -> 4.788 | AE40: =ROUND((((EU40*1.2)*0.3)),6) -> 0.7272 | AF40: =ROUND((((EV40*1.2)*0.3)),6) -> 4.1472 | AG40: =ROUND((AP40),6) -> 0 | AH40: =(((EW40*1.2)*0.3)) -> 0.3708 | AI40: =(((EX40*1.2)*0.3)) -> 0 | AJ40: =(AS40) -> 0 | AK40: 24.82 | AL40: 0 | AM40: 13.3 | AN40: 2.02 | AO40: 11.52 | AP40: 0 | AQ40: 1.03 | AR40: 0 | AS40: 0 | AT40: 90 | AU40: 46 | AV40: 1.047 | AW40: 1 | AZ40: 1 | BA40: 1 | BB40: 1 | BC40: 1 | BH40: 0 | BI40: 2 | BJ40: ТСН-2001.4 Доп. 68, Сб. 11, т. 7, поз. 1 | BM40: 72 | BN40: 0 | BO40: 4.11-7-1 | BP40: 1 | BQ40: 40 | BR40: 0 | BS40: 1 | BT40: 1 | BU40: 1 | BV40: 1 | BW40: 1 | BX40: 1 | BZ40: 90 | CA40: 46 | CE40: 1566 | CF40: 0 | CG40: 0 | CM40: 0 | CN40: Поправка: Гл.12.Прил.8.п.8. 3_12.00.01.11.001 Наименование: При наличии напряженных и стесненных условий производства работ (стесненность, сложность складирования и транспортной логистики и т.п.) для объектов, расположенных в пределах круговой магистральной системы улиц "Садовое кольцо" города Москвы Поправка: Гл.4.Прил.2.2.п.2.2.29_04.00.01.35.003 Наименование: При демонтаже оборудования, предназначенного в лом | CO40: 0 | CP40: =(P40+Q40+S40) -> 56.13 | CQ40: =ROUND((ROUND((AC40*AW40*1),2)*BC40),2) -> 0 | CR40: =(ROUND((ROUND(((((ET40*1.2)*0.3))*AV40*1),2)*BB40),2)+ROUND((ROUND(((AE40-(((EU40*1.2)*0.3)))*AV40*1),2)*BS40),2)) -> 5.01 | CS40: =(ROUND((ROUND(((((EU40*1.2)*0.3))*AV40*1),2)*BS40),2)+ROUND((ROUND(((AE40-(((EU40*1.2)*0.3)))*AV40*1),2)*BS40),2)) -> 0.76 | CT40: =ROUND((ROUND((AF40*AV40*1),2)*BA40),2) -> 4.34 | CU40: =AG40 -> 0 | CV40: =(AH40*AV40) -> 0.3882276 | CW40: =AI40 -> 0 | CX40: =AJ40 -> 0 | CY40: =(ROUND((((S40+ROUND((ROUND(((((EU40*1.2)*0.3))*AV40*1),2)*BS40),2))*AT40)/100),2)+ROUND(((ROUND((ROUND(((AE40-(((EU40*1.2)*0.3)))*AV40*1),2)*BS40),2)*AT40)/100),2)) -> 24.13 | CZ40: =(ROUND((((S40+ROUND((ROUND(((((EU40*1.2)*0.3))*AV40*1),2)*BS40),2))*AU40)/100),2)+ROUND(((ROUND((ROUND(((AE40-(((EU40*1.2)*0.3)))*AV40*1),2)*BS40),2)*AU40)/100),2)) -> 12.33 | DB40: 23 | DD40: *1)*0 | DE40: *1,2)*0,3 | DF40: *1,2)*0,3 | DG40: *1,2)*0,3 | DI40: *1,2)*0,3 | DJ40: *1,2)*0,3 | DN40: 0 | DO40: 0 | DP40: 1 | DQ40: 1 | DU40: 1013 | DV40: 1 ШТ. | DW40: 1 ШТ. | DX40: 1 | EE40: 55393704 | EF40: 40 | EG40: Монтаж оборудования | EH40: 0 | EJ40: 2 | EK40: 72 | EL40: ТСН-2001.4-11. Приборы и средства автоматизации и вычислительной техники | EM40: ТСН-2001.4-11-1 | EO40: Поправка: Гл.12.Прил.8.п.8. 3_12.00.01.11.001 Поправка: Гл.4.Прил.2.2.п.2.2.29_04.00.01.35.003 | EQ40: 0 | ER40: 24.82 | ES40: 0 | ET40: 13.3 | EU40: 2.02 | EV40: 11.52 | EW40: 1.03 | EX40: 0 | EY40: 0 | FQ40: 0 | FR40: 0 | FS40: 0 | FX40: 90 | FY40: 46 | GD40: 1 | GF40: 381958606 | GG40: 2 | GH40: 1 | GI40: 2 | GJ40: 0 | GK40: 0 | GL40: =ROUND(IF(AND(BH40=3,BI40=3,FS40<>0),P40,0),2) -> 0 | GM40: =ROUND(O40+X40+Y40,2)+GX40 -> 97.78 | GN40: =IF(OR(BI40=0,BI40=1),GM40-GX40,0) -> 0 | GO40: =IF(BI40=2,GM40-GX40,0) -> 97.78 | GP40: =IF(BI40=4,GM40-GX40,0) -> 0 | GR40: 0 | GS40: 3 | GT40: 0 | GV40: =ROUND((GT40),6) -> 0 | GW40: 1 | GX40: =ROUND(HC40*I40,2) -> 0 | HA40: 0 | HB40: 0 | HC40: =GV40*GW40 -> 0 | HS40: 0 | IK40: 0
A41: 17 | B41: 1 | C41: =ROW(SmtRes!A76) -> 76 | D41: =ROW(EtalonRes!A88) -> 88 | E41: 7 | F41: 4.11-7-1 | G41: Установка аппарата настольного массой до 0,015 т / демонтаж приёмника | H41: 1 ШТ. | I41: 6 | J41: 0 | K41: 6 | O41: =ROUND(CP41,2) -> 1981.08 | P41: =ROUND((ROUND((AC41*AW41*I41),2)*BC41),2) -> 0 | Q41: =(ROUND((ROUND(((((ET41*1.2)*0.3))*AV41*I41),2)*BB41),2)+ROUND((ROUND(((AE41-(((EU41*1.2)*0.3)))*AV41*I41),2)*BS41),2)) -> 513.16 | R41: =(ROUND((ROUND(((((EU41*1.2)*0.3))*AV41*I41),2)*BS41),2)+ROUND((ROUND(((AE41-(((EU41*1.2)*0.3)))*AV41*I41),2)*BS41),2)) -> 257.52 | S41: =ROUND((ROUND((AF41*AV41*I41),2)*BA41),2) -> 1467.92 | T41: =ROUND(CU41*I41,2) -> 0 | U41: =CV41*I41 -> 2.3293656 | V41: =CW41*I41 -> 0 | W41: =ROUND(CX41*I41,2) -> 0 | X41: =(ROUND((((S41+ROUND((ROUND(((((EU41*1.2)*0.3))*AV41*I41),2)*BS41),2))*AT41)/100),2)+ROUND(((ROUND((ROUND(((AE41-(((EU41*1.2)*0.3)))*AV41*I41),2)*BS41),2)*AT41)/100),2)) -> 1552.9 | Y41: =(ROUND((((S41+ROUND((ROUND(((((EU41*1.2)*0.3))*AV41*I41),2)*BS41),2))*AU41)/100),2)+ROUND(((ROUND((ROUND(((AE41-(((EU41*1.2)*0.3)))*AV41*I41),2)*BS41),2)*AU41)/100),2)) -> 793.7 | AA41: 55917799 | AB41: =ROUND((AC41+AD41+AF41),6) -> 8.9352 | AC41: =ROUND((((ES41*1)*0)),6) -> 0 | AD41: =ROUND((((((ET41*1.2)*0.3))-(((EU41*1.2)*0.3)))+AE41),6) -> 4.788 | AE41: =ROUND((((EU41*1.2)*0.3)),6) -> 0.7272 | AF41: =ROUND((((EV41*1.2)*0.3)),6) -> 4.1472 | AG41: =ROUND((AP41),6) -> 0 | AH41: =(((EW41*1.2)*0.3)) -> 0.3708 | AI41: =(((EX41*1.2)*0.3)) -> 0 | AJ41: =(AS41) -> 0 | AK41: 24.82 | AL41: 0 | AM41: 13.3 | AN41: 2.02 | AO41: 11.52 | AP41: 0 | AQ41: 1.03 | AR41: 0 | AS41: 0 | AT41: 90 | AU41: 46 | AV41: 1.047 | AW41: 1 | AZ41: 1 | BA41: 56.35 | BB41: 17.06 | BC41: 1 | BH41: 0 | BI41: 2 | BJ41: ТСН-2001.4 Доп. 68, Сб. 11, т. 7, поз. 1 | BM41: 72 | BN41: 0 | BO41: 4.11-7-1 | BP41: 1 | BQ41: 40 | BR41: 0 | BS41: 56.35 | BT41: 1 | BU41: 1 | BV41: 1 | BW41: 1 | BX41: 1 | BZ41: 90 | CA41: 46 | CE41: 1566 | CF41: 0 | CG41: 0 | CM41: 0 | CN41: Поправка: Гл.12.Прил.8.п.8. 3_12.00.01.11.001 Наименование: При наличии напряженных и стесненных условий производства работ (стесненность, сложность складирования и транспортной логистики и т.п.) для объектов, расположенных в пределах круговой магистральной системы улиц "Садовое кольцо" города Москвы Поправка: Гл.4.Прил.2.2.п.2.2.29_04.00.01.35.003 Наименование: При демонтаже оборудования, предназначенного в лом | CO41: 0 | CP41: =(P41+Q41+S41) -> 1981.08 | CQ41: =ROUND((ROUND((AC41*AW41*1),2)*BC41),2) -> 0 | CR41: =(ROUND((ROUND(((((ET41*1.2)*0.3))*AV41*1),2)*BB41),2)+ROUND((ROUND(((AE41-(((EU41*1.2)*0.3)))*AV41*1),2)*BS41),2)) -> 85.47 | CS41: =(ROUND((ROUND(((((EU41*1.2)*0.3))*AV41*1),2)*BS41),2)+ROUND((ROUND(((AE41-(((EU41*1.2)*0.3)))*AV41*1),2)*BS41),2)) -> 42.83 | CT41: =ROUND((ROUND((AF41*AV41*1),2)*BA41),2) -> 244.56 | CU41: =AG41 -> 0 | CV41: =(AH41*AV41) -> 0.3882276 | CW41: =AI41 -> 0 | CX41: =AJ41 -> 0 | CY41: =(ROUND((((S41+ROUND((ROUND(((((EU41*1.2)*0.3))*AV41*1),2)*BS41),2))*AT41)/100),2)+ROUND(((ROUND((ROUND(((AE41-(((EU41*1.2)*0.3)))*AV41*1),2)*BS41),2)*AT41)/100),2)) -> 1359.68 | CZ41: =(ROUND((((S41+ROUND((ROUND(((((EU41*1.2)*0.3))*AV41*1),2)*BS41),2))*AU41)/100),2)+ROUND(((ROUND((ROUND(((AE41-(((EU41*1.2)*0.3)))*AV41*1),2)*BS41),2)*AU41)/100),2)) -> 694.95 | DB41: 25 | DD41: *1)*0 | DE41: *1,2)*0,3 | DF41: *1,2)*0,3 | DG41: *1,2)*0,3 | DI41: *1,2)*0,3 | DJ41: *1,2)*0,3 | DN41: 0 | DO41: 0 | DP41: 1 | DQ41: 1 | DU41: 1013 | DV41: 1 ШТ. | DW41: 1 ШТ. | DX41: 1 | EE41: 55393704 | EF41: 40 | EG41: Монтаж оборудования | EH41: 0 | EJ41: 2 | EK41: 72 | EL41: ТСН-2001.4-11. Приборы и средства автоматизации и вычислительной техники | EM41: ТСН-2001.4-11-1 | EO41: Поправка: Гл.12.Прил.8.п.8. 3_12.00.01.11.001 Поправка: Гл.4.Прил.2.2.п.2.2.29_04.00.01.35.003 | EQ41: 0 | ER41: 24.82 | ES41: 0 | ET41: 13.3 | EU41: 2.02 | EV41: 11.52 | EW41: 1.03 | EX41: 0 | EY41: 0 | FQ41: 0 | FR41: 0 | FS41: 0 | FX41: 90 | FY41: 46 | GD41: 1 | GF41: 381958606 | GG41: 2 | GH41: 1 | GI41: 2 | GJ41: 0 | GK41: 0 | GL41: =ROUND(IF(AND(BH41=3,BI41=3,FS41<>0),P41,0),2) -> 0 | GM41: =ROUND(O41+X41+Y41,2)+GX41 -> 4327.68 | GN41: =IF(OR(BI41=0,BI41=1),GM41-GX41,0) -> 0 | GO41: =IF(BI41=2,GM41-GX41,0) -> 4327.68 | GP41: =IF(BI41=4,GM41-GX41,0) -> 0 | GR41: 0 | GS41: 3 | GT41: 0 | GV41: =ROUND((GT41),6) -> 0 | GW41: 1 | GX41: =ROUND(HC41*I41,2) -> 0 | HA41: 0 | HB41: 0 | HC41: =GV41*GW41 -> 0 | HS41: 0 | IK41: 0
A42: 17 | B42: 1 | C42: =ROW(SmtRes!A83) -> 83 | D42: =ROW(EtalonRes!A96) -> 96 | E42: 8 | F42: 4.10-69-3 | G42: Монтаж щита распределительного настенного типа / демонтаж шкафа с объектовой станцией | H42: 1 ШТ. | I42: 1 | J42: 0 | K42: 1 | O42: =ROUND(CP42,2) -> 168.66 | P42: =ROUND((ROUND((AC42*AW42*I42),2)*BC42),2) -> 0 | Q42: =(ROUND((ROUND(((((ET42*1.2)*0.3))*AV42*I42),2)*BB42),2)+ROUND((ROUND(((AE42-(((EU42*1.2)*0.3)))*AV42*I42),2)*BS42),2)) -> 0 | R42: =(ROUND((ROUND(((((EU42*1.2)*0.3))*AV42*I42),2)*BS42),2)+ROUND((ROUND(((AE42-(((EU42*1.2)*0.3)))*AV42*I42),2)*BS42),2)) -> 0 | S42: =ROUND((ROUND((AF42*AV42*I42),2)*BA42),2) -> 168.66 | T42: =ROUND(CU42*I42,2) -> 0 | U42: =CV42*I42 -> 12.43836 | V42: =CW42*I42 -> 0 | W42: =ROUND(CX42*I42,2) -> 0 | X42: =(ROUND((((S42+ROUND((ROUND(((((EU42*1.2)*0.3))*AV42*I42),2)*BS42),2))*AT42)/100),2)+ROUND(((ROUND((ROUND(((AE42-(((EU42*1.2)*0.3)))*AV42*I42),2)*BS42),2)*AT42)/100),2)) -> 160.23 | Y42: =(ROUND((((S42+ROUND((ROUND(((((EU42*1.2)*0.3))*AV42*I42),2)*BS42),2))*AU42)/100),2)+ROUND(((ROUND((ROUND(((AE42-(((EU42*1.2)*0.3)))*AV42*I42),2)*BS42),2)*AU42)/100),2)) -> 89.39 | AA42: 55917797 | AB42: =ROUND((AC42+AD42+AF42),6) -> 161.0928 | AC42: =ROUND((((ES42*1)*0)),6) -> 0 | AD42: =ROUND((((((ET42*1.2)*0.3))-(((EU42*1.2)*0.3)))+AE42),6) -> 0 | AE42: =ROUND((((EU42*1.2)*0.3)),6) -> 0 | AF42: =ROUND((((EV42*1.2)*0.3)),6) -> 161.0928 | AG42: =ROUND((AP42),6) -> 0 | AH42: =(((EW42*1.2)*0.3)) -> 11.88 | AI42: =(((EX42*1.2)*0.3)) -> 0 | AJ42: =(AS42) -> 0 | AK42: 524.23 | AL42: 76.75 | AM42: 0 | AN42: 0 | AO42: 447.48 | AP42: 0 | AQ42: 33 | AR42: 0 | AS42: 0 | AT42: 95 | AU42: 53 | AV42: 1.047 | AW42: 1 | AZ42: 1 | BA42: 1 | BB42: 1 | BC42: 1 | BH42: 0 | BI42: 2 | BJ42: ТСН-2001.4 Доп. 67, Сб. 10, т. 69, поз. 3 | BM42: 69 | BN42: 0 | BO42: 4.10-69-3 | BP42: 1 | BQ42: 40 | BR42: 0 | BS42: 1 | BT42: 1 | BU42: 1 | BV42: 1 | BW42: 1 | BX42: 1 | BZ42: 95 | CA42: 53 | CE42: 1566 | CF42: 0 | CG42: 0 | CM42: 0 | CN42: Поправка: Гл.12.Прил.8.п.8. 3_12.00.01.11.001 Наименование: При наличии напряженных и стесненных условий производства работ (стесненность, сложность складирования и транспортной логистики и т.п.) для объектов, расположенных в пределах круговой магистральной системы улиц "Садовое кольцо" города Москвы Поправка: Гл.4.Прил.2.2.п.2.2.29_04.00.01.35.003 Наименование: При демонтаже оборудования, предназначенного в лом | CO42: 0 | CP42: =(P42+Q42+S42) -> 168.66 | CQ42: =ROUND((ROUND((AC42*AW42*1),2)*BC42),2) -> 0 | CR42: =(ROUND((ROUND(((((ET42*1.2)*0.3))*AV42*1),2)*BB42),2)+ROUND((ROUND(((AE42-(((EU42*1.2)*0.3)))*AV42*1),2)*BS42),2)) -> 0 | CS42: =(ROUND((ROUND(((((EU42*1.2)*0.3))*AV42*1),2)*BS42),2)+ROUND((ROUND(((AE42-(((EU42*1.2)*0.3)))*AV42*1),2)*BS42),2)) -> 0 | CT42: =ROUND((ROUND((AF42*AV42*1),2)*BA42),2) -> 168.66 | CU42: =AG42 -> 0 | CV42: =(AH42*AV42) -> 12.43836 | CW42: =AI42 -> 0 | CX42: =AJ42 -> 0 | CY42: =(ROUND((((S42+ROUND((ROUND(((((EU42*1.2)*0.3))*AV42*1),2)*BS42),2))*AT42)/100),2)+ROUND(((ROUND((ROUND(((AE42-(((EU42*1.2)*0.3)))*AV42*1),2)*BS42),2)*AT42)/100),2)) -> 160.23 | CZ42: =(ROUND((((S42+ROUND((ROUND(((((EU42*1.2)*0.3))*AV42*1),2)*BS42),2))*AU42)/100),2)+ROUND(((ROUND((ROUND(((AE42-(((EU42*1.2)*0.3)))*AV42*1),2)*BS42),2)*AU42)/100),2)) -> 89.39 | DB42: 27 | DD42: *1)*0 | DE42: *1,2)*0,3 | DF42: *1,2)*0,3 | DG42: *1,2)*0,3 | DI42: *1,2)*0,3 | DJ42: *1,2)*0,3 | DN42: 0 | DO42: 0 | DP42: 1 | DQ42: 1 | DU42: 1013 | DV42: 1 ШТ. | DW42: 1 ШТ. | DX42: 1 | EE42: 55393701 | EF42: 40 | EG42: Монтаж оборудования | EH42: 0 | EJ42: 2 | EK42: 69 | EL42: ТСН-2001.4-10. Монтаж радиотелевизионного и электронного оборудования | EM42: ТСН-2001.4-10-2 | EO42: Поправка: Гл.12.Прил.8.п.8. 3_12.00.01.11.001 Поправка: Гл.4.Прил.2.2.п.2.2.29_04.00.01.35.003 | EQ42: 0 | ER42: 524.23 | ES42: 76.75 | ET42: 0 | EU42: 0 | EV42: 447.48 | EW42: 33 | EX42: 0 | EY42: 0 | FQ42: 0 | FR42: 0 | FS42: 0 | FX42: 95 | FY42: 53 | GD42: 1 | GF42: -1787952050 | GG42: 2 | GH42: 1 | GI42: 2 | GJ42: 0 | GK42: 0 | GL42: =ROUND(IF(AND(BH42=3,BI42=3,FS42<>0),P42,0),2) -> 0 | GM42: =ROUND(O42+X42+Y42,2)+GX42 -> 418.28 | GN42: =IF(OR(BI42=0,BI42=1),GM42-GX42,0) -> 0 | GO42: =IF(BI42=2,GM42-GX42,0) -> 418.28 | GP42: =IF(BI42=4,GM42-GX42,0) -> 0 | GR42: 0 | GS42: 3 | GT42: 0 | GV42: =ROUND((GT42),6) -> 0 | GW42: 1 | GX42: =ROUND(HC42*I42,2) -> 0 | HA42: 0 | HB42: 0 | HC42: =GV42*GW42 -> 0 | HS42: 0 | IK42: 0
A43: 17 | B43: 1 | C43: =ROW(SmtRes!A90) -> 90 | D43: =ROW(EtalonRes!A104) -> 104 | E43: 8 | F43: 4.10-69-3 | G43: Монтаж щита распределительного настенного типа / демонтаж шкафа с объектовой станцией | H43: 1 ШТ. | I43: 1 | J43: 0 | K43: 1 | O43: =ROUND(CP43,2) -> 9503.99 | P43: =ROUND((ROUND((AC43*AW43*I43),2)*BC43),2) -> 0 | Q43: =(ROUND((ROUND(((((ET43*1.2)*0.3))*AV43*I43),2)*BB43),2)+ROUND((ROUND(((AE43-(((EU43*1.2)*0.3)))*AV43*I43),2)*BS43),2)) -> 0 | R43: =(ROUND((ROUND(((((EU43*1.2)*0.3))*AV43*I43),2)*BS43),2)+ROUND((ROUND(((AE43-(((EU43*1.2)*0.3)))*AV43*I43),2)*BS43),2)) -> 0 | S43: =ROUND((ROUND((AF43*AV43*I43),2)*BA43),2) -> 9503.99 | T43: =ROUND(CU43*I43,2) -> 0 | U43: =CV43*I43 -> 12.43836 | V43: =CW43*I43 -> 0 | W43: =ROUND(CX43*I43,2) -> 0 | X43: =(ROUND((((S43+ROUND((ROUND(((((EU43*1.2)*0.3))*AV43*I43),2)*BS43),2))*AT43)/100),2)+ROUND(((ROUND((ROUND(((AE43-(((EU43*1.2)*0.3)))*AV43*I43),2)*BS43),2)*AT43)/100),2)) -> 9028.79 | Y43: =(ROUND((((S43+ROUND((ROUND(((((EU43*1.2)*0.3))*AV43*I43),2)*BS43),2))*AU43)/100),2)+ROUND(((ROUND((ROUND(((AE43-(((EU43*1.2)*0.3)))*AV43*I43),2)*BS43),2)*AU43)/100),2)) -> 5037.11 | AA43: 55917799 | AB43: =ROUND((AC43+AD43+AF43),6) -> 161.0928 | AC43: =ROUND((((ES43*1)*0)),6) -> 0 | AD43: =ROUND((((((ET43*1.2)*0.3))-(((EU43*1.2)*0.3)))+AE43),6) -> 0 | AE43: =ROUND((((EU43*1.2)*0.3)),6) -> 0 | AF43: =ROUND((((EV43*1.2)*0.3)),6) -> 161.0928 | AG43: =ROUND((AP43),6) -> 0 | AH43: =(((EW43*1.2)*0.3)) -> 11.88 | AI43: =(((EX43*1.2)*0.3)) -> 0 | AJ43: =(AS43) -> 0 | AK43: 524.23 | AL43: 76.75 | AM43: 0 | AN43: 0 | AO43: 447.48 | AP43: 0 | AQ43: 33 | AR43: 0 | AS43: 0 | AT43: 95 | AU43: 53 | AV43: 1.047 | AW43: 1 | AZ43: 1 | BA43: 56.35 | BB43: 1 | BC43: 9.08 | BH43: 0 | BI43: 2 | BJ43: ТСН-2001.4 Доп. 67, Сб. 10, т. 69, поз. 3 | BM43: 69 | BN43: 0 | BO43: 4.10-69-3 | BP43: 1 | BQ43: 40 | BR43: 0 | BS43: 56.35 | BT43: 1 | BU43: 1 | BV43: 1 | BW43: 1 | BX43: 1 | BZ43: 95 | CA43: 53 | CE43: 1566 | CF43: 0 | CG43: 0 | CM43: 0 | CN43: Поправка: Гл.12.Прил.8.п.8. 3_12.00.01.11.001 Наименование: При наличии напряженных и стесненных условий производства работ (стесненность, сложность складирования и транспортной логистики и т.п.) для объектов, расположенных в пределах круговой магистральной системы улиц "Садовое кольцо" города Москвы Поправка: Гл.4.Прил.2.2.п.2.2.29_04.00.01.35.003 Наименование: При демонтаже оборудования, предназначенного в лом | CO43: 0 | CP43: =(P43+Q43+S43) -> 9503.99 | CQ43: =ROUND((ROUND((AC43*AW43*1),2)*BC43),2) -> 0 | CR43: =(ROUND((ROUND(((((ET43*1.2)*0.3))*AV43*1),2)*BB43),2)+ROUND((ROUND(((AE43-(((EU43*1.2)*0.3)))*AV43*1),2)*BS43),2)) -> 0 | CS43: =(ROUND((ROUND(((((EU43*1.2)*0.3))*AV43*1),2)*BS43),2)+ROUND((ROUND(((AE43-(((EU43*1.2)*0.3)))*AV43*1),2)*BS43),2)) -> 0 | CT43: =ROUND((ROUND((AF43*AV43*1),2)*BA43),2) -> 9503.99 | CU43: =AG43 -> 0 | CV43: =(AH43*AV43) -> 12.43836 | CW43: =AI43 -> 0 | CX43: =AJ43 -> 0 | CY43: =(ROUND((((S43+ROUND((ROUND(((((EU43*1.2)*0.3))*AV43*1),2)*BS43),2))*AT43)/100),2)+ROUND(((ROUND((ROUND(((AE43-(((EU43*1.2)*0.3)))*AV43*1),2)*BS43),2)*AT43)/100),2)) -> 9028.79 | CZ43: =(ROUND((((S43+ROUND((ROUND(((((EU43*1.2)*0.3))*AV43*1),2)*BS43),2))*AU43)/100),2)+ROUND(((ROUND((ROUND(((AE43-(((EU43*1.2)*0.3)))*AV43*1),2)*BS43),2)*AU43)/100),2)) -> 5037.11 | DB43: 29 | DD43: *1)*0 | DE43: *1,2)*0,3 | DF43: *1,2)*0,3 | DG43: *1,2)*0,3 | DI43: *1,2)*0,3 | DJ43: *1,2)*0,3 | DN43: 0 | DO43: 0 | DP43: 1 | DQ43: 1 | DU43: 1013 | DV43: 1 ШТ. | DW43: 1 ШТ. | DX43: 1 | EE43: 55393701 | EF43: 40 | EG43: Монтаж оборудования | EH43: 0 | EJ43: 2 | EK43: 69 | EL43: ТСН-2001.4-10. Монтаж радиотелевизионного и электронного оборудования | EM43: ТСН-2001.4-10-2 | EO43: Поправка: Гл.12.Прил.8.п.8. 3_12.00.01.11.001 Поправка: Гл.4.Прил.2.2.п.2.2.29_04.00.01.35.003 | EQ43: 0 | ER43: 524.23 | ES43: 76.75 | ET43: 0 | EU43: 0 | EV43: 447.48 | EW43: 33 | EX43: 0 | EY43: 0 | FQ43: 0 | FR43: 0 | FS43: 0 | FX43: 95 | FY43: 53 | GD43: 1 | GF43: -1787952050 | GG43: 2 | GH43: 1 | GI43: 2 | GJ43: 0 | GK43: 0 | GL43: =ROUND(IF(AND(BH43=3,BI43=3,FS43<>0),P43,0),2) -> 0 | GM43: =ROUND(O43+X43+Y43,2)+GX43 -> 23569.89 | GN43: =IF(OR(BI43=0,BI43=1),GM43-GX43,0) -> 0 | GO43: =IF(BI43=2,GM43-GX43,0) -> 23569.89 | GP43: =IF(BI43=4,GM43-GX43,0) -> 0 | GR43: 0 | GS43: 3 | GT43: 0 | GV43: =ROUND((GT43),6) -> 0 | GW43: 1 | GX43: =ROUND(HC43*I43,2) -> 0 | HA43: 0 | HB43: 0 | HC43: =GV43*GW43 -> 0 | HS43: 0 | IK43: 0
A44: 17 | B44: 1 | C44: =ROW(SmtRes!A101) -> 101 | D44: =ROW(EtalonRes!A116) -> 116 | E44: 9 | F44: 4.10-73-1 | G44: Монтаж радиостанции УКВ связи абонентской мощностью до 15 Вт стационарной / демонтаж устройства сопряжения с РСО | H44: 1 комплект | I44: 1 | J44: 0 | K44: 1 | O44: =ROUND(CP44,2) -> 47.57 | P44: =ROUND((ROUND((AC44*AW44*I44),2)*BC44),2) -> 0 | Q44: =(ROUND((ROUND(((((ET44*1.2)*0.3))*AV44*I44),2)*BB44),2)+ROUND((ROUND(((AE44-(((EU44*1.2)*0.3)))*AV44*I44),2)*BS44),2)) -> 0 | R44: =(ROUND((ROUND(((((EU44*1.2)*0.3))*AV44*I44),2)*BS44),2)+ROUND((ROUND(((AE44-(((EU44*1.2)*0.3)))*AV44*I44),2)*BS44),2)) -> 0 | S44: =ROUND((ROUND((AF44*AV44*I44),2)*BA44),2) -> 47.57 | T44: =ROUND(CU44*I44,2) -> 0 | U44: =CV44*I44 -> 3.7692 | V44: =CW44*I44 -> 0 | W44: =ROUND(CX44*I44,2) -> 0 | X44: =(ROUND((((S44+ROUND((ROUND(((((EU44*1.2)*0.3))*AV44*I44),2)*BS44),2))*AT44)/100),2)+ROUND(((ROUND((ROUND(((AE44-(((EU44*1.2)*0.3)))*AV44*I44),2)*BS44),2)*AT44)/100),2)) -> 45.19 | Y44: =(ROUND((((S44+ROUND((ROUND(((((EU44*1.2)*0.3))*AV44*I44),2)*BS44),2))*AU44)/100),2)+ROUND(((ROUND((ROUND(((AE44-(((EU44*1.2)*0.3)))*AV44*I44),2)*BS44),2)*AU44)/100),2)) -> 25.21 | AA44: 55917797 | AB44: =ROUND((AC44+AD44+AF44),6) -> 45.432 | AC44: =ROUND((((ES44*1)*0)),6) -> 0 | AD44: =ROUND((((((ET44*1.2)*0.3))-(((EU44*1.2)*0.3)))+AE44),6) -> 0 | AE44: =ROUND((((EU44*1.2)*0.3)),6) -> 0 | AF44: =ROUND((((EV44*1.2)*0.3)),6) -> 45.432 | AG44: =ROUND((AP44),6) -> 0 | AH44: =(((EW44*1.2)*0.3)) -> 3.6 | AI44: =(((EX44*1.2)*0.3)) -> 0 | AJ44: =(AS44) -> 0 | AK44: 201.88 | AL44: 75.68 | AM44: 0 | AN44: 0 | AO44: 126.2 | AP44: 0 | AQ44: 10 | AR44: 0 | AS44: 0 | AT44: 95 | AU44: 53 | AV44: 1.047 | AW44: 1 | AZ44: 1 | BA44: 1 | BB44: 1 | BC44: 1 | BH44: 0 | BI44: 2 | BJ44: ТСН-2001.4 Доп. 80, Сб. 10, т. 73, поз. 1 | BM44: 69 | BN44: 0 | BO44: 4.10-73-1 | BP44: 1 | BQ44: 40 | BR44: 0 | BS44: 1 | BT44: 1 | BU44: 1 | BV44: 1 | BW44: 1 | BX44: 1 | BZ44: 95 | CA44: 53 | CE44: 1566 | CF44: 0 | CG44: 0 | CM44: 0 | CN44: Поправка: Гл.12.Прил.8.п.8. 3_12.00.01.11.001 Наименование: При наличии напряженных и стесненных условий производства работ (стесненность, сложность складирования и транспортной логистики и т.п.) для объектов, расположенных в пределах круговой магистральной системы улиц "Садовое кольцо" города Москвы Поправка: Гл.4.Прил.2.2.п.2.2.29_04.00.01.35.003 Наименование: При демонтаже оборудования, предназначенного в лом | CO44: 0 | CP44: =(P44+Q44+S44) -> 47.57 | CQ44: =ROUND((ROUND((AC44*AW44*1),2)*BC44),2) -> 0 | CR44: =(ROUND((ROUND(((((ET44*1.2)*0.3))*AV44*1),2)*BB44),2)+ROUND((ROUND(((AE44-(((EU44*1.2)*0.3)))*AV44*1),2)*BS44),2)) -> 0 | CS44: =(ROUND((ROUND(((((EU44*1.2)*0.3))*AV44*1),2)*BS44),2)+ROUND((ROUND(((AE44-(((EU44*1.2)*0.3)))*AV44*1),2)*BS44),2)) -> 0 | CT44: =ROUND((ROUND((AF44*AV44*1),2)*BA44),2) -> 47.57 | CU44: =AG44 -> 0 | CV44: =(AH44*AV44) -> 3.7692 | CW44: =AI44 -> 0 | CX44: =AJ44 -> 0 | CY44: =(ROUND((((S44+ROUND((ROUND(((((EU44*1.2)*0.3))*AV44*1),2)*BS44),2))*AT44)/100),2)+ROUND(((ROUND((ROUND(((AE44-(((EU44*1.2)*0.3)))*AV44*1),2)*BS44),2)*AT44)/100),2)) -> 45.19 | CZ44: =(ROUND((((S44+ROUND((ROUND(((((EU44*1.2)*0.3))*AV44*1),2)*BS44),2))*AU44)/100),2)+ROUND(((ROUND((ROUND(((AE44-(((EU44*1.2)*0.3)))*AV44*1),2)*BS44),2)*AU44)/100),2)) -> 25.21 | DB44: 31 | DD44: *1)*0 | DE44: *1,2)*0,3 | DF44: *1,2)*0,3 | DG44: *1,2)*0,3 | DI44: *1,2)*0,3 | DJ44: *1,2)*0,3 | DN44: 0 | DO44: 0 | DP44: 1 | DQ44: 1 | DU44: 1013 | DV44: 1 комплект | DW44: 1 комплект | DX44: 1 | EE44: 55393701 | EF44: 40 | EG44: Монтаж оборудования | EH44: 0 | EJ44: 2 | EK44: 69 | EL44: ТСН-2001.4-10. Монтаж радиотелевизионного и электронного оборудования | EM44: ТСН-2001.4-10-2 | EO44: Поправка: Гл.12.Прил.8.п.8. 3_12.00.01.11.001 Поправка: Гл.4.Прил.2.2.п.2.2.29_04.00.01.35.003 | EQ44: 0 | ER44: 201.88 | ES44: 75.68 | ET44: 0 | EU44: 0 | EV44: 126.2 | EW44: 10 | EX44: 0 | EY44: 0 | FQ44: 0 | FR44: 0 | FS44: 0 | FX44: 95 | FY44: 53 | GD44: 1 | GF44: 99576978 | GG44: 2 | GH44: 1 | GI44: 2 | GJ44: 0 | GK44: 0 | GL44: =ROUND(IF(AND(BH44=3,BI44=3,FS44<>0),P44,0),2) -> 0 | GM44: =ROUND(O44+X44+Y44,2)+GX44 -> 117.97 | GN44: =IF(OR(BI44=0,BI44=1),GM44-GX44,0) -> 0 | GO44: =IF(BI44=2,GM44-GX44,0) -> 117.97 | GP44: =IF(BI44=4,GM44-GX44,0) -> 0 | GR44: 0 | GS44: 3 | GT44: 0 | GV44: =ROUND((GT44),6) -> 0 | GW44: 1 | GX44: =ROUND(HC44*I44,2) -> 0 | HA44: 0 | HB44: 0 | HC44: =GV44*GW44 -> 0 | HS44: 0 | IK44: 0
A45: 17 | B45: 1 | C45: =ROW(SmtRes!A112) -> 112 | D45: =ROW(EtalonRes!A128) -> 128 | E45: 9 | F45: 4.10-73-1 | G45: Монтаж радиостанции УКВ связи абонентской мощностью до 15 Вт стационарной / демонтаж устройства сопряжения с РСО | H45: 1 комплект | I45: 1 | J45: 0 | K45: 1 | O45: =ROUND(CP45,2) -> 2680.57 | P45: =ROUND((ROUND((AC45*AW45*I45),2)*BC45),2) -> 0 | Q45: =(ROUND((ROUND(((((ET45*1.2)*0.3))*AV45*I45),2)*BB45),2)+ROUND((ROUND(((AE45-(((EU45*1.2)*0.3)))*AV45*I45),2)*BS45),2)) -> 0 | R45: =(ROUND((ROUND(((((EU45*1.2)*0.3))*AV45*I45),2)*BS45),2)+ROUND((ROUND(((AE45-(((EU45*1.2)*0.3)))*AV45*I45),2)*BS45),2)) -> 0 | S45: =ROUND((ROUND((AF45*AV45*I45),2)*BA45),2) -> 2680.57 | T45: =ROUND(CU45*I45,2) -> 0 | U45: =CV45*I45 -> 3.7692 | V45: =CW45*I45 -> 0 | W45: =ROUND(CX45*I45,2) -> 0 | X45: =(ROUND((((S45+ROUND((ROUND(((((EU45*1.2)*0.3))*AV45*I45),2)*BS45),2))*AT45)/100),2)+ROUND(((ROUND((ROUND(((AE45-(((EU45*1.2)*0.3)))*AV45*I45),2)*BS45),2)*AT45)/100),2)) -> 2546.54 | Y45: =(ROUND((((S45+ROUND((ROUND(((((EU45*1.2)*0.3))*AV45*I45),2)*BS45),2))*AU45)/100),2)+ROUND(((ROUND((ROUND(((AE45-(((EU45*1.2)*0.3)))*AV45*I45),2)*BS45),2)*AU45)/100),2)) -> 1420.7 | AA45: 55917799 | AB45: =ROUND((AC45+AD45+AF45),6) -> 45.432 | AC45: =ROUND((((ES45*1)*0)),6) -> 0 | AD45: =ROUND((((((ET45*1.2)*0.3))-(((EU45*1.2)*0.3)))+AE45),6) -> 0 | AE45: =ROUND((((EU45*1.2)*0.3)),6) -> 0 | AF45: =ROUND((((EV45*1.2)*0.3)),6) -> 45.432 | AG45: =ROUND((AP45),6) -> 0 | AH45: =(((EW45*1.2)*0.3)) -> 3.6 | AI45: =(((EX45*1.2)*0.3)) -> 0 | AJ45: =(AS45) -> 0 | AK45: 201.88 | AL45: 75.68 | AM45: 0 | AN45: 0 | AO45: 126.2 | AP45: 0 | AQ45: 10 | AR45: 0 | AS45: 0 | AT45: 95 | AU45: 53 | AV45: 1.047 | AW45: 1 | AZ45: 1 | BA45: 56.35 | BB45: 1 | BC45: 9.58 | BH45: 0 | BI45: 2 | BJ45: ТСН-2001.4 Доп. 80, Сб. 10, т. 73, поз. 1 | BM45: 69 | BN45: 0 | BO45: 4.10-73-1 | BP45: 1 | BQ45: 40 | BR45: 0 | BS45: 56.35 | BT45: 1 | BU45: 1 | BV45: 1 | BW45: 1 | BX45: 1 | BZ45: 95 | CA45: 53 | CE45: 1566 | CF45: 0 | CG45: 0 | CM45: 0 | CN45: Поправка: Гл.12.Прил.8.п.8. 3_12.00.01.11.001 Наименование: При наличии напряженных и стесненных условий производства работ (стесненность, сложность складирования и транспортной логистики и т.п.) для объектов, расположенных в пределах круговой магистральной системы улиц "Садовое кольцо" города Москвы Поправка: Гл.4.Прил.2.2.п.2.2.29_04.00.01.35.003 Наименование: При демонтаже оборудования, предназначенного в лом | CO45: 0 | CP45: =(P45+Q45+S45) -> 2680.57 | CQ45: =ROUND((ROUND((AC45*AW45*1),2)*BC45),2) -> 0 | CR45: =(ROUND((ROUND(((((ET45*1.2)*0.3))*AV45*1),2)*BB45),2)+ROUND((ROUND(((AE45-(((EU45*1.2)*0.3)))*AV45*1),2)*BS45),2)) -> 0 | CS45: =(ROUND((ROUND(((((EU45*1.2)*0.3))*AV45*1),2)*BS45),2)+ROUND((ROUND(((AE45-(((EU45*1.2)*0.3)))*AV45*1),2)*BS45),2)) -> 0 | CT45: =ROUND((ROUND((AF45*AV45*1),2)*BA45),2) -> 2680.57 | CU45: =AG45 -> 0 | CV45: =(AH45*AV45) -> 3.7692 | CW45: =AI45 -> 0 | CX45: =AJ45 -> 0 | CY45: =(ROUND((((S45+ROUND((ROUND(((((EU45*1.2)*0.3))*AV45*1),2)*BS45),2))*AT45)/100),2)+ROUND(((ROUND((ROUND(((AE45-(((EU45*1.2)*0.3)))*AV45*1),2)*BS45),2)*AT45)/100),2)) -> 2546.54 | CZ45: =(ROUND((((S45+ROUND((ROUND(((((EU45*1.2)*0.3))*AV45*1),2)*BS45),2))*AU45)/100),2)+ROUND(((ROUND((ROUND(((AE45-(((EU45*1.2)*0.3)))*AV45*1),2)*BS45),2)*AU45)/100),2)) -> 1420.7 | DB45: 33 | DD45: *1)*0 | DE45: *1,2)*0,3 | DF45: *1,2)*0,3 | DG45: *1,2)*0,3 | DI45: *1,2)*0,3 | DJ45: *1,2)*0,3 | DN45: 0 | DO45: 0 | DP45: 1 | DQ45: 1 | DU45: 1013 | DV45: 1 комплект | DW45: 1 комплект | DX45: 1 | EE45: 55393701 | EF45: 40 | EG45: Монтаж оборудования | EH45: 0 | EJ45: 2 | EK45: 69 | EL45: ТСН-2001.4-10. Монтаж радиотелевизионного и электронного оборудования | EM45: ТСН-2001.4-10-2 | EO45: Поправка: Гл.12.Прил.8.п.8. 3_12.00.01.11.001 Поправка: Гл.4.Прил.2.2.п.2.2.29_04.00.01.35.003 | EQ45: 0 | ER45: 201.88 | ES45: 75.68 | ET45: 0 | EU45: 0 | EV45: 126.2 | EW45: 10 | EX45: 0 | EY45: 0 | FQ45: 0 | FR45: 0 | FS45: 0 | FX45: 95 | FY45: 53 | GD45: 1 | GF45: 99576978 | GG45: 2 | GH45: 1 | GI45: 2 | GJ45: 0 | GK45: 0 | GL45: =ROUND(IF(AND(BH45=3,BI45=3,FS45<>0),P45,0),2) -> 0 | GM45: =ROUND(O45+X45+Y45,2)+GX45 -> 6647.81 | GN45: =IF(OR(BI45=0,BI45=1),GM45-GX45,0) -> 0 | GO45: =IF(BI45=2,GM45-GX45,0) -> 6647.81 | GP45: =IF(BI45=4,GM45-GX45,0) -> 0 | GR45: 0 | GS45: 3 | GT45: 0 | GV45: =ROUND((GT45),6) -> 0 | GW45: 1 | GX45: =ROUND(HC45*I45,2) -> 0 | HA45: 0 | HB45: 0 | HC45: =GV45*GW45 -> 0 | HS45: 0 | IK45: 0
A46: 17 | B46: 1 | C46: =ROW(SmtRes!A114) -> 114 | D46: =ROW(EtalonRes!A130) -> 130 | E46: 10 | F46: 4.10-134-7 | G46: Монтаж антенны дополнительной для приема ТВ на ранее установленной опоре, с действующими ТВ антеннами / демонтаж антенны | H46: 1 антенна | I46: 1 | J46: 0 | K46: 1 | O46: =ROUND(CP46,2) -> 15.59 | P46: =ROUND((ROUND((AC46*AW46*I46),2)*BC46),2) -> 0 | Q46: =(ROUND((ROUND(((((ET46*1.2)*0.3))*AV46*I46),2)*BB46),2)+ROUND((ROUND(((AE46-(((EU46*1.2)*0.3)))*AV46*I46),2)*BS46),2)) -> 0 | R46: =(ROUND((ROUND(((((EU46*1.2)*0.3))*AV46*I46),2)*BS46),2)+ROUND((ROUND(((AE46-(((EU46*1.2)*0.3)))*AV46*I46),2)*BS46),2)) -> 0 | S46: =ROUND((ROUND((AF46*AV46*I46),2)*BA46),2) -> 15.59 | T46: =ROUND(CU46*I46,2) -> 0 | U46: =CV46*I46 -> 1.0839564 | V46: =CW46*I46 -> 0 | W46: =ROUND(CX46*I46,2) -> 0 | X46: =(ROUND((((S46+ROUND((ROUND(((((EU46*1.2)*0.3))*AV46*I46),2)*BS46),2))*AT46)/100),2)+ROUND(((ROUND((ROUND(((AE46-(((EU46*1.2)*0.3)))*AV46*I46),2)*BS46),2)*AT46)/100),2)) -> 14.81 | Y46: =(ROUND((((S46+ROUND((ROUND(((((EU46*1.2)*0.3))*AV46*I46),2)*BS46),2))*AU46)/100),2)+ROUND(((ROUND((ROUND(((AE46-(((EU46*1.2)*0.3)))*AV46*I46),2)*BS46),2)*AU46)/100),2)) -> 8.26 | AA46: 55917797 | AB46: =ROUND((AC46+AD46+AF46),6) -> 14.346 | AC46: =ROUND((((ES46*1)*0)),6) -> 0 | AD46: =ROUND((((((ET46*1.2)*0.3))-(((EU46*1.2)*0.3)))+AE46),6) -> 0 | AE46: =ROUND((((EU46*1.2)*0.3)),6) -> 0 | AF46: =ROUND((((EV46*1.2)*0.3)),6) -> 14.346 | AG46: =ROUND((AP46),6) -> 0 | AH46: =(((EW46*1.2)*0.3)) -> 0.9972 | AI46: =(((EX46*1.2)*0.3)) -> 0 | AJ46: =(AS46) -> 0 | AK46: 40.03 | AL46: 0.18 | AM46: 0 | AN46: 0 | AO46: 39.85 | AP46: 0 | AQ46: 2.77 | AR46: 0 | AS46: 0 | AT46: 95 | AU46: 53 | AV46: 1.087 | AW46: 1 | AZ46: 1 | BA46: 1 | BB46: 1 | BC46: 1 | BH46: 0 | BI46: 2 | BJ46: ТСН-2001.4 Доп. 81, Сб. 10, т. 134, поз. 7 | BM46: 69 | BN46: 0 | BO46: 4.10-134-7 | BP46: 1 | BQ46: 40 | BR46: 0 | BS46: 1 | BT46: 1 | BU46: 1 | BV46: 1 | BW46: 1 | BX46: 1 | BZ46: 95 | CA46: 53 | CE46: 1566 | CF46: 0 | CG46: 0 | CM46: 0 | CN46: Поправка: Гл.12.Прил.8.п.8. 3_12.00.01.11.001 Наименование: При наличии напряженных и стесненных условий производства работ (стесненность, сложность складирования и транспортной логистики и т.п.) для объектов, расположенных в пределах круговой магистральной системы улиц "Садовое кольцо" города Москвы Поправка: Гл.4.Прил.2.2.п.2.2.29_04.00.01.35.003 Наименование: При демонтаже оборудования, предназначенного в лом | CO46: 0 | CP46: =(P46+Q46+S46) -> 15.59 | CQ46: =ROUND((ROUND((AC46*AW46*1),2)*BC46),2) -> 0 | CR46: =(ROUND((ROUND(((((ET46*1.2)*0.3))*AV46*1),2)*BB46),2)+ROUND((ROUND(((AE46-(((EU46*1.2)*0.3)))*AV46*1),2)*BS46),2)) -> 0 | CS46: =(ROUND((ROUND(((((EU46*1.2)*0.3))*AV46*1),2)*BS46),2)+ROUND((ROUND(((AE46-(((EU46*1.2)*0.3)))*AV46*1),2)*BS46),2)) -> 0 | CT46: =ROUND((ROUND((AF46*AV46*1),2)*BA46),2) -> 15.59 | CU46: =AG46 -> 0 | CV46: =(AH46*AV46) -> 1.0839564 | CW46: =AI46 -> 0 | CX46: =AJ46 -> 0 | CY46: =(ROUND((((S46+ROUND((ROUND(((((EU46*1.2)*0.3))*AV46*1),2)*BS46),2))*AT46)/100),2)+ROUND(((ROUND((ROUND(((AE46-(((EU46*1.2)*0.3)))*AV46*1),2)*BS46),2)*AT46)/100),2)) -> 14.81 | CZ46: =(ROUND((((S46+ROUND((ROUND(((((EU46*1.2)*0.3))*AV46*1),2)*BS46),2))*AU46)/100),2)+ROUND(((ROUND((ROUND(((AE46-(((EU46*1.2)*0.3)))*AV46*1),2)*BS46),2)*AU46)/100),2)) -> 8.26 | DB46: 35 | DD46: *1)*0 | DE46: *1,2)*0,3 | DF46: *1,2)*0,3 | DG46: *1,2)*0,3 | DI46: *1,2)*0,3 | DJ46: *1,2)*0,3 | DN46: 0 | DO46: 0 | DP46: 1 | DQ46: 1 | DU46: 1013 | DV46: 1 антенна | DW46: 1 антенна | DX46: 1 | EE46: 55393701 | EF46: 40 | EG46: Монтаж оборудования | EH46: 0 | EJ46: 2 | EK46: 69 | EL46: ТСН-2001.4-10. Монтаж радиотелевизионного и электронного оборудования | EM46: ТСН-2001.4-10-2 | EO46: Поправка: Гл.12.Прил.8.п.8. 3_12.00.01.11.001 Поправка: Гл.4.Прил.2.2.п.2.2.29_04.00.01.35.003 | EQ46: 0 | ER46: 40.03 | ES46: 0.18 | ET46: 0 | EU46: 0 | EV46: 39.85 | EW46: 2.77 | EX46: 0 | EY46: 0 | FQ46: 0 | FR46: 0 | FS46: 0 | FX46: 95 | FY46: 53 | GD46: 1 | GF46: 668601792 | GG46: 2 | GH46: 1 | GI46: 2 | GJ46: 0 | GK46: 0 | GL46: =ROUND(IF(AND(BH46=3,BI46=3,FS46<>0),P46,0),2) -> 0 | GM46: =ROUND(O46+X46+Y46,2)+GX46 -> 38.66 | GN46: =IF(OR(BI46=0,BI46=1),GM46-GX46,0) -> 0 | GO46: =IF(BI46=2,GM46-GX46,0) -> 38.66 | GP46: =IF(BI46=4,GM46-GX46,0) -> 0 | GR46: 0 | GS46: 3 | GT46: 0 | GV46: =ROUND((GT46),6) -> 0 | GW46: 1 | GX46: =ROUND(HC46*I46,2) -> 0 | HA46: 0 | HB46: 0 | HC46: =GV46*GW46 -> 0 | HS46: 0 | IK46: 0
A47: 17 | B47: 1 | C47: =ROW(SmtRes!A116) -> 116 | D47: =ROW(EtalonRes!A132) -> 132 | E47: 10 | F47: 4.10-134-7 | G47: Монтаж антенны дополнительной для приема ТВ на ранее установленной опоре, с действующими ТВ антеннами / демонтаж антенны | H47: 1 антенна | I47: 1 | J47: 0 | K47: 1 | O47: =ROUND(CP47,2) -> 878.5 | P47: =ROUND((ROUND((AC47*AW47*I47),2)*BC47),2) -> 0 | Q47: =(ROUND((ROUND(((((ET47*1.2)*0.3))*AV47*I47),2)*BB47),2)+ROUND((ROUND(((AE47-(((EU47*1.2)*0.3)))*AV47*I47),2)*BS47),2)) -> 0 | R47: =(ROUND((ROUND(((((EU47*1.2)*0.3))*AV47*I47),2)*BS47),2)+ROUND((ROUND(((AE47-(((EU47*1.2)*0.3)))*AV47*I47),2)*BS47),2)) -> 0 | S47: =ROUND((ROUND((AF47*AV47*I47),2)*BA47),2) -> 878.5 | T47: =ROUND(CU47*I47,2) -> 0 | U47: =CV47*I47 -> 1.0839564 | V47: =CW47*I47 -> 0 | W47: =ROUND(CX47*I47,2) -> 0 | X47: =(ROUND((((S47+ROUND((ROUND(((((EU47*1.2)*0.3))*AV47*I47),2)*BS47),2))*AT47)/100),2)+ROUND(((ROUND((ROUND(((AE47-(((EU47*1.2)*0.3)))*AV47*I47),2)*BS47),2)*AT47)/100),2)) -> 834.58 | Y47: =(ROUND((((S47+ROUND((ROUND(((((EU47*1.2)*0.3))*AV47*I47),2)*BS47),2))*AU47)/100),2)+ROUND(((ROUND((ROUND(((AE47-(((EU47*1.2)*0.3)))*AV47*I47),2)*BS47),2)*AU47)/100),2)) -> 465.61 | AA47: 55917799 | AB47: =ROUND((AC47+AD47+AF47),6) -> 14.346 | AC47: =ROUND((((ES47*1)*0)),6) -> 0 | AD47: =ROUND((((((ET47*1.2)*0.3))-(((EU47*1.2)*0.3)))+AE47),6) -> 0 | AE47: =ROUND((((EU47*1.2)*0.3)),6) -> 0 | AF47: =ROUND((((EV47*1.2)*0.3)),6) -> 14.346 | AG47: =ROUND((AP47),6) -> 0 | AH47: =(((EW47*1.2)*0.3)) -> 0.9972 | AI47: =(((EX47*1.2)*0.3)) -> 0 | AJ47: =(AS47) -> 0 | AK47: 40.03 | AL47: 0.18 | AM47: 0 | AN47: 0 | AO47: 39.85 | AP47: 0 | AQ47: 2.77 | AR47: 0 | AS47: 0 | AT47: 95 | AU47: 53 | AV47: 1.087 | AW47: 1 | AZ47: 1 | BA47: 56.35 | BB47: 1 | BC47: 5.61 | BH47: 0 | BI47: 2 | BJ47: ТСН-2001.4 Доп. 81, Сб. 10, т. 134, поз. 7 | BM47: 69 | BN47: 0 | BO47: 4.10-134-7 | BP47: 1 | BQ47: 40 | BR47: 0 | BS47: 56.35 | BT47: 1 | BU47: 1 | BV47: 1 | BW47: 1 | BX47: 1 | BZ47: 95 | CA47: 53 | CE47: 1566 | CF47: 0 | CG47: 0 | CM47: 0 | CN47: Поправка: Гл.12.Прил.8.п.8. 3_12.00.01.11.001 Наименование: При наличии напряженных и стесненных условий производства работ (стесненность, сложность складирования и транспортной логистики и т.п.) для объектов, расположенных в пределах круговой магистральной системы улиц "Садовое кольцо" города Москвы Поправка: Гл.4.Прил.2.2.п.2.2.29_04.00.01.35.003 Наименование: При демонтаже оборудования, предназначенного в лом | CO47: 0 | CP47: =(P47+Q47+S47) -> 878.5 | CQ47: =ROUND((ROUND((AC47*AW47*1),2)*BC47),2) -> 0 | CR47: =(ROUND((ROUND(((((ET47*1.2)*0.3))*AV47*1),2)*BB47),2)+ROUND((ROUND(((AE47-(((EU47*1.2)*0.3)))*AV47*1),2)*BS47),2)) -> 0 | CS47: =(ROUND((ROUND(((((EU47*1.2)*0.3))*AV47*1),2)*BS47),2)+ROUND((ROUND(((AE47-(((EU47*1.2)*0.3)))*AV47*1),2)*BS47),2)) -> 0 | CT47: =ROUND((ROUND((AF47*AV47*1),2)*BA47),2) -> 878.5 | CU47: =AG47 -> 0 | CV47: =(AH47*AV47) -> 1.0839564 | CW47: =AI47 -> 0 | CX47: =AJ47 -> 0 | CY47: =(ROUND((((S47+ROUND((ROUND(((((EU47*1.2)*0.3))*AV47*1),2)*BS47),2))*AT47)/100),2)+ROUND(((ROUND((ROUND(((AE47-(((EU47*1.2)*0.3)))*AV47*1),2)*BS47),2)*AT47)/100),2)) -> 834.58 | CZ47: =(ROUND((((S47+ROUND((ROUND(((((EU47*1.2)*0.3))*AV47*1),2)*BS47),2))*AU47)/100),2)+ROUND(((ROUND((ROUND(((AE47-(((EU47*1.2)*0.3)))*AV47*1),2)*BS47),2)*AU47)/100),2)) -> 465.61 | DB47: 37 | DD47: *1)*0 | DE47: *1,2)*0,3 | DF47: *1,2)*0,3 | DG47: *1,2)*0,3 | DI47: *1,2)*0,3 | DJ47: *1,2)*0,3 | DN47: 0 | DO47: 0 | DP47: 1 | DQ47: 1 | DU47: 1013 | DV47: 1 антенна | DW47: 1 антенна | DX47: 1 | EE47: 55393701 | EF47: 40 | EG47: Монтаж оборудования | EH47: 0 | EJ47: 2 | EK47: 69 | EL47: ТСН-2001.4-10. Монтаж радиотелевизионного и электронного оборудования | EM47: ТСН-2001.4-10-2 | EO47: Поправка: Гл.12.Прил.8.п.8. 3_12.00.01.11.001 Поправка: Гл.4.Прил.2.2.п.2.2.29_04.00.01.35.003 | EQ47: 0 | ER47: 40.03 | ES47: 0.18 | ET47: 0 | EU47: 0 | EV47: 39.85 | EW47: 2.77 | EX47: 0 | EY47: 0 | FQ47: 0 | FR47: 0 | FS47: 0 | FX47: 95 | FY47: 53 | GD47: 1 | GF47: 668601792 | GG47: 2 | GH47: 1 | GI47: 2 | GJ47: 0 | GK47: 0 | GL47: =ROUND(IF(AND(BH47=3,BI47=3,FS47<>0),P47,0),2) -> 0 | GM47: =ROUND(O47+X47+Y47,2)+GX47 -> 2178.69 | GN47: =IF(OR(BI47=0,BI47=1),GM47-GX47,0) -> 0 | GO47: =IF(BI47=2,GM47-GX47,0) -> 2178.69 | GP47: =IF(BI47=4,GM47-GX47,0) -> 0 | GR47: 0 | GS47: 3 | GT47: 0 | GV47: =ROUND((GT47),6) -> 0 | GW47: 1 | GX47: =ROUND(HC47*I47,2) -> 0 | HA47: 0 | HB47: 0 | HC47: =GV47*GW47 -> 0 | HS47: 0 | IK47: 0
A48: 17 | B48: 1 | C48: =ROW(SmtRes!A131) -> 131 | D48: =ROW(EtalonRes!A149) -> 149 | E48: 11 | F48: 4.10-21-5 | G48: Грозозащита для воздушных абонентских линий / демонтаж грозозащиты | H48: 1 комплект | I48: 1 | J48: 0 | K48: 1 | O48: =ROUND(CP48,2) -> 14.27 | P48: =ROUND((ROUND((AC48*AW48*I48),2)*BC48),2) -> 0 | Q48: =(ROUND((ROUND(((((ET48*1.2)*0.3))*AV48*I48),2)*BB48),2)+ROUND((ROUND(((AE48-(((EU48*1.2)*0.3)))*AV48*I48),2)*BS48),2)) -> 0 | R48: =(ROUND((ROUND(((((EU48*1.2)*0.3))*AV48*I48),2)*BS48),2)+ROUND((ROUND(((AE48-(((EU48*1.2)*0.3)))*AV48*I48),2)*BS48),2)) -> 0 | S48: =ROUND((ROUND((AF48*AV48*I48),2)*BA48),2) -> 14.27 | T48: =ROUND(CU48*I48,2) -> 0 | U48: =CV48*I48 -> 1.13076 | V48: =CW48*I48 -> 0 | W48: =ROUND(CX48*I48,2) -> 0 | X48: =(ROUND((((S48+ROUND((ROUND(((((EU48*1.2)*0.3))*AV48*I48),2)*BS48),2))*AT48)/100),2)+ROUND(((ROUND((ROUND(((AE48-(((EU48*1.2)*0.3)))*AV48*I48),2)*BS48),2)*AT48)/100),2)) -> 12.84 | Y48: =(ROUND((((S48+ROUND((ROUND(((((EU48*1.2)*0.3))*AV48*I48),2)*BS48),2))*AU48)/100),2)+ROUND(((ROUND((ROUND(((AE48-(((EU48*1.2)*0.3)))*AV48*I48),2)*BS48),2)*AU48)/100),2)) -> 6.56 | AA48: 55917797 | AB48: =ROUND((AC48+AD48+AF48),6) -> 13.6296 | AC48: =ROUND((((ES48*1)*0)),6) -> 0 | AD48: =ROUND((((((ET48*1.2)*0.3))-(((EU48*1.2)*0.3)))+AE48),6) -> 0 | AE48: =ROUND((((EU48*1.2)*0.3)),6) -> 0 | AF48: =ROUND((((EV48*1.2)*0.3)),6) -> 13.6296 | AG48: =ROUND((AP48),6) -> 0 | AH48: =(((EW48*1.2)*0.3)) -> 1.08 | AI48: =(((EX48*1.2)*0.3)) -> 0 | AJ48: =(AS48) -> 0 | AK48: 80.47 | AL48: 42.61 | AM48: 0 | AN48: 0 | AO48: 37.86 | AP48: 0 | AQ48: 3 | AR48: 0 | AS48: 0 | AT48: 90 | AU48: 46 | AV48: 1.047 | AW48: 1 | AZ48: 1 | BA48: 1 | BB48: 1 | BC48: 1 | BH48: 0 | BI48: 2 | BJ48: ТСН-2001.4 Доп. 79, Сб. 10, т. 21, поз. 5 | BM48: 68 | BN48: 0 | BO48: 4.10-21-5 | BP48: 1 | BQ48: 40 | BR48: 0 | BS48: 1 | BT48: 1 | BU48: 1 | BV48: 1 | BW48: 1 | BX48: 1 | BZ48: 90 | CA48: 46 | CE48: 1566 | CF48: 0 | CG48: 0 | CM48: 0 | CN48: Поправка: Гл.12.Прил.8.п.8. 3_12.00.01.11.001 Наименование: При наличии напряженных и стесненных условий производства работ (стесненность, сложность складирования и транспортной логистики и т.п.) для объектов, расположенных в пределах круговой магистральной системы улиц "Садовое кольцо" города Москвы Поправка: Гл.4.Прил.2.2.п.2.2.29_04.00.01.35.003 Наименование: При демонтаже оборудования, предназначенного в лом | CO48: 0 | CP48: =(P48+Q48+S48) -> 14.27 | CQ48: =ROUND((ROUND((AC48*AW48*1),2)*BC48),2) -> 0 | CR48: =(ROUND((ROUND(((((ET48*1.2)*0.3))*AV48*1),2)*BB48),2)+ROUND((ROUND(((AE48-(((EU48*1.2)*0.3)))*AV48*1),2)*BS48),2)) -> 0 | CS48: =(ROUND((ROUND(((((EU48*1.2)*0.3))*AV48*1),2)*BS48),2)+ROUND((ROUND(((AE48-(((EU48*1.2)*0.3)))*AV48*1),2)*BS48),2)) -> 0 | CT48: =ROUND((ROUND((AF48*AV48*1),2)*BA48),2) -> 14.27 | CU48: =AG48 -> 0 | CV48: =(AH48*AV48) -> 1.13076 | CW48: =AI48 -> 0 | CX48: =AJ48 -> 0 | CY48: =(ROUND((((S48+ROUND((ROUND(((((EU48*1.2)*0.3))*AV48*1),2)*BS48),2))*AT48)/100),2)+ROUND(((ROUND((ROUND(((AE48-(((EU48*1.2)*0.3)))*AV48*1),2)*BS48),2)*AT48)/100),2)) -> 12.84 | CZ48: =(ROUND((((S48+ROUND((ROUND(((((EU48*1.2)*0.3))*AV48*1),2)*BS48),2))*AU48)/100),2)+ROUND(((ROUND((ROUND(((AE48-(((EU48*1.2)*0.3)))*AV48*1),2)*BS48),2)*AU48)/100),2)) -> 6.56 | DB48: 39 | DD48: *1)*0 | DE48: *1,2)*0,3 | DF48: *1,2)*0,3 | DG48: *1,2)*0,3 | DI48: *1,2)*0,3 | DJ48: *1,2)*0,3 | DN48: 0 | DO48: 0 | DP48: 1 | DQ48: 1 | DU48: 1013 | DV48: 1 комплект | DW48: 1 комплект | DX48: 1 | EE48: 55393700 | EF48: 40 | EG48: Монтаж оборудования | EH48: 0 | EJ48: 2 | EK48: 68 | EL48: ТСН-2001.4-10. Прокладка и монтаж сетей связи | EM48: ТСН-2001.4-10-1 | EO48: Поправка: Гл.12.Прил.8.п.8. 3_12.00.01.11.001 Поправка: Гл.4.Прил.2.2.п.2.2.29_04.00.01.35.003 | EQ48: 0 | ER48: 80.47 | ES48: 42.61 | ET48: 0 | EU48: 0 | EV48: 37.86 | EW48: 3 | EX48: 0 | EY48: 0 | FQ48: 0 | FR48: 0 | FS48: 0 | FX48: 90 | FY48: 46 | GD48: 1 | GF48: -1588285181 | GG48: 2 | GH48: 1 | GI48: 2 | GJ48: 0 | GK48: 0 | GL48: =ROUND(IF(AND(BH48=3,BI48=3,FS48<>0),P48,0),2) -> 0 | GM48: =ROUND(O48+X48+Y48,2)+GX48 -> 33.67 | GN48: =IF(OR(BI48=0,BI48=1),GM48-GX48,0) -> 0 | GO48: =IF(BI48=2,GM48-GX48,0) -> 33.67 | GP48: =IF(BI48=4,GM48-GX48,0) -> 0 | GR48: 0 | GS48: 3 | GT48: 0 | GV48: =ROUND((GT48),6) -> 0 | GW48: 1 | GX48: =ROUND(HC48*I48,2) -> 0 | HA48: 0 | HB48: 0 | HC48: =GV48*GW48 -> 0 | HS48: 0 | IK48: 0
A49: 17 | B49: 1 | C49: =ROW(SmtRes!A146) -> 146 | D49: =ROW(EtalonRes!A166) -> 166 | E49: 11 | F49: 4.10-21-5 | G49: Грозозащита для воздушных абонентских линий / демонтаж грозозащиты | H49: 1 комплект | I49: 1 | J49: 0 | K49: 1 | O49: =ROUND(CP49,2) -> 804.11 | P49: =ROUND((ROUND((AC49*AW49*I49),2)*BC49),2) -> 0 | Q49: =(ROUND((ROUND(((((ET49*1.2)*0.3))*AV49*I49),2)*BB49),2)+ROUND((ROUND(((AE49-(((EU49*1.2)*0.3)))*AV49*I49),2)*BS49),2)) -> 0 | R49: =(ROUND((ROUND(((((EU49*1.2)*0.3))*AV49*I49),2)*BS49),2)+ROUND((ROUND(((AE49-(((EU49*1.2)*0.3)))*AV49*I49),2)*BS49),2)) -> 0 | S49: =ROUND((ROUND((AF49*AV49*I49),2)*BA49),2) -> 804.11 | T49: =ROUND(CU49*I49,2) -> 0 | U49: =CV49*I49 -> 1.13076 | V49: =CW49*I49 -> 0 | W49: =ROUND(CX49*I49,2) -> 0 | X49: =(ROUND((((S49+ROUND((ROUND(((((EU49*1.2)*0.3))*AV49*I49),2)*BS49),2))*AT49)/100),2)+ROUND(((ROUND((ROUND(((AE49-(((EU49*1.2)*0.3)))*AV49*I49),2)*BS49),2)*AT49)/100),2)) -> 723.7 | Y49: =(ROUND((((S49+ROUND((ROUND(((((EU49*1.2)*0.3))*AV49*I49),2)*BS49),2))*AU49)/100),2)+ROUND(((ROUND((ROUND(((AE49-(((EU49*1.2)*0.3)))*AV49*I49),2)*BS49),2)*AU49)/100),2)) -> 369.89 | AA49: 55917799 | AB49: =ROUND((AC49+AD49+AF49),6) -> 13.6296 | AC49: =ROUND((((ES49*1)*0)),6) -> 0 | AD49: =ROUND((((((ET49*1.2)*0.3))-(((EU49*1.2)*0.3)))+AE49),6) -> 0 | AE49: =ROUND((((EU49*1.2)*0.3)),6) -> 0 | AF49: =ROUND((((EV49*1.2)*0.3)),6) -> 13.6296 | AG49: =ROUND((AP49),6) -> 0 | AH49: =(((EW49*1.2)*0.3)) -> 1.08 | AI49: =(((EX49*1.2)*0.3)) -> 0 | AJ49: =(AS49) -> 0 | AK49: 80.47 | AL49: 42.61 | AM49: 0 | AN49: 0 | AO49: 37.86 | AP49: 0 | AQ49: 3 | AR49: 0 | AS49: 0 | AT49: 90 | AU49: 46 | AV49: 1.047 | AW49: 1 | AZ49: 1 | BA49: 56.35 | BB49: 1 | BC49: 5.15 | BH49: 0 | BI49: 2 | BJ49: ТСН-2001.4 Доп. 79, Сб. 10, т. 21, поз. 5 | BM49: 68 | BN49: 0 | BO49: 4.10-21-5 | BP49: 1 | BQ49: 40 | BR49: 0 | BS49: 56.35 | BT49: 1 | BU49: 1 | BV49: 1 | BW49: 1 | BX49: 1 | BZ49: 90 | CA49: 46 | CE49: 1566 | CF49: 0 | CG49: 0 | CM49: 0 | CN49: Поправка: Гл.12.Прил.8.п.8. 3_12.00.01.11.001 Наименование: При наличии напряженных и стесненных условий производства работ (стесненность, сложность складирования и транспортной логистики и т.п.) для объектов, расположенных в пределах круговой магистральной системы улиц "Садовое кольцо" города Москвы Поправка: Гл.4.Прил.2.2.п.2.2.29_04.00.01.35.003 Наименование: При демонтаже оборудования, предназначенного в лом | CO49: 0 | CP49: =(P49+Q49+S49) -> 804.11 | CQ49: =ROUND((ROUND((AC49*AW49*1),2)*BC49),2) -> 0 | CR49: =(ROUND((ROUND(((((ET49*1.2)*0.3))*AV49*1),2)*BB49),2)+ROUND((ROUND(((AE49-(((EU49*1.2)*0.3)))*AV49*1),2)*BS49),2)) -> 0 | CS49: =(ROUND((ROUND(((((EU49*1.2)*0.3))*AV49*1),2)*BS49),2)+ROUND((ROUND(((AE49-(((EU49*1.2)*0.3)))*AV49*1),2)*BS49),2)) -> 0 | CT49: =ROUND((ROUND((AF49*AV49*1),2)*BA49),2) -> 804.11 | CU49: =AG49 -> 0 | CV49: =(AH49*AV49) -> 1.13076 | CW49: =AI49 -> 0 | CX49: =AJ49 -> 0 | CY49: =(ROUND((((S49+ROUND((ROUND(((((EU49*1.2)*0.3))*AV49*1),2)*BS49),2))*AT49)/100),2)+ROUND(((ROUND((ROUND(((AE49-(((EU49*1.2)*0.3)))*AV49*1),2)*BS49),2)*AT49)/100),2)) -> 723.7 | CZ49: =(ROUND((((S49+ROUND((ROUND(((((EU49*1.2)*0.3))*AV49*1),2)*BS49),2))*AU49)/100),2)+ROUND(((ROUND((ROUND(((AE49-(((EU49*1.2)*0.3)))*AV49*1),2)*BS49),2)*AU49)/100),2)) -> 369.89 | DB49: 41 | DD49: *1)*0 | DE49: *1,2)*0,3 | DF49: *1,2)*0,3 | DG49: *1,2)*0,3 | DI49: *1,2)*0,3 | DJ49: *1,2)*0,3 | DN49: 0 | DO49: 0 | DP49: 1 | DQ49: 1 | DU49: 1013 | DV49: 1 комплект | DW49: 1 комплект | DX49: 1 | EE49: 55393700 | EF49: 40 | EG49: Монтаж оборудования | EH49: 0 | EJ49: 2 | EK49: 68 | EL49: ТСН-2001.4-10. Прокладка и монтаж сетей связи | EM49: ТСН-2001.4-10-1 | EO49: Поправка: Гл.12.Прил.8.п.8. 3_12.00.01.11.001 Поправка: Гл.4.Прил.2.2.п.2.2.29_04.00.01.35.003 | EQ49: 0 | ER49: 80.47 | ES49: 42.61 | ET49: 0 | EU49: 0 | EV49: 37.86 | EW49: 3 | EX49: 0 | EY49: 0 | FQ49: 0 | FR49: 0 | FS49: 0 | FX49: 90 | FY49: 46 | GD49: 1 | GF49: -1588285181 | GG49: 2 | GH49: 1 | GI49: 2 | GJ49: 0 | GK49: 0 | GL49: =ROUND(IF(AND(BH49=3,BI49=3,FS49<>0),P49,0),2) -> 0 | GM49: =ROUND(O49+X49+Y49,2)+GX49 -> 1897.7 | GN49: =IF(OR(BI49=0,BI49=1),GM49-GX49,0) -> 0 | GO49: =IF(BI49=2,GM49-GX49,0) -> 1897.7 | GP49: =IF(BI49=4,GM49-GX49,0) -> 0 | GR49: 0 | GS49: 3 | GT49: 0 | GV49: =ROUND((GT49),6) -> 0 | GW49: 1 | GX49: =ROUND(HC49*I49,2) -> 0 | HA49: 0 | HB49: 0 | HC49: =GV49*GW49 -> 0 | HS49: 0 | IK49: 0
A50: 17 | B50: 1 | C50: =ROW(SmtRes!A150) -> 150 | D50: =ROW(EtalonRes!A170) -> 170 | E50: 12 | F50: 4.10-134-3 | G50: Монтаж металлоконструкций для телевизионных антенн / демонтаж мачты антенной | H50: 1 Т | I50: =ROUND((5.1+3.1)/1000,9) -> 0.0082 | J50: 0 | K50: =ROUND((5.1+3.1)/1000,9) -> 0.0082 | O50: =ROUND(CP50,2) -> 1.4 | P50: =ROUND((ROUND((AC50*AW50*I50),2)*BC50),2) -> 0 | Q50: =(ROUND((ROUND(((((ET50*1.2)*0.3))*AV50*I50),2)*BB50),2)+ROUND((ROUND(((AE50-(((EU50*1.2)*0.3)))*AV50*I50),2)*BS50),2)) -> 0.01 | R50: =(ROUND((ROUND(((((EU50*1.2)*0.3))*AV50*I50),2)*BS50),2)+ROUND((ROUND(((AE50-(((EU50*1.2)*0.3)))*AV50*I50),2)*BS50),2)) -> 0 | S50: =ROUND((ROUND((AF50*AV50*I50),2)*BA50),2) -> 1.39 | T50: =ROUND(CU50*I50,2) -> 0 | U50: =CV50*I50 -> 0.10268237 | V50: =CW50*I50 -> 0 | W50: =ROUND(CX50*I50,2) -> 0 | X50: =(ROUND((((S50+ROUND((ROUND(((((EU50*1.2)*0.3))*AV50*I50),2)*BS50),2))*AT50)/100),2)+ROUND(((ROUND((ROUND(((AE50-(((EU50*1.2)*0.3)))*AV50*I50),2)*BS50),2)*AT50)/100),2)) -> 1.32 | Y50: =(ROUND((((S50+ROUND((ROUND(((((EU50*1.2)*0.3))*AV50*I50),2)*BS50),2))*AU50)/100),2)+ROUND(((ROUND((ROUND(((AE50-(((EU50*1.2)*0.3)))*AV50*I50),2)*BS50),2)*AU50)/100),2)) -> 0.74 | AA50: 55917797 | AB50: =ROUND((AC50+AD50+AF50),6) -> 157.0248 | AC50: =ROUND((((ES50*1)*0)),6) -> 0 | AD50: =ROUND((((((ET50*1.2)*0.3))-(((EU50*1.2)*0.3)))+AE50),6) -> 0.6984 | AE50: =ROUND((((EU50*1.2)*0.3)),6) -> 0 | AF50: =ROUND((((EV50*1.2)*0.3)),6) -> 156.3264 | AG50: =ROUND((AP50),6) -> 0 | AH50: =(((EW50*1.2)*0.3)) -> 11.52 | AI50: =(((EX50*1.2)*0.3)) -> 0 | AJ50: =(AS50) -> 0 | AK50: 545.15 | AL50: 108.97 | AM50: 1.94 | AN50: 0 | AO50: 434.24 | AP50: 0 | AQ50: 32 | AR50: 0 | AS50: 0 | AT50: 95 | AU50: 53 | AV50: 1.087 | AW50: 1 | AZ50: 1 | BA50: 1 | BB50: 1 | BC50: 1 | BH50: 0 | BI50: 2 | BJ50: ТСН-2001.4 Доп. 81, Сб. 10, т. 134, поз. 3 | BM50: 69 | BN50: 0 | BO50: 4.10-134-3 | BP50: 1 | BQ50: 40 | BR50: 0 | BS50: 1 | BT50: 1 | BU50: 1 | BV50: 1 | BW50: 1 | BX50: 1 | BZ50: 95 | CA50: 53 | CE50: 1566 | CF50: 0 | CG50: 0 | CM50: 0 | CN50: Поправка: Гл.12.Прил.8.п.8. 3_12.00.01.11.001 Наименование: При наличии напряженных и стесненных условий производства работ (стесненность, сложность складирования и транспортной логистики и т.п.) для объектов, расположенных в пределах круговой магистральной системы улиц "Садовое кольцо" города Москвы Поправка: Гл.4.Прил.2.2.п.2.2.29_04.00.01.35.003 Наименование: При демонтаже оборудования, предназначенного в лом | CO50: 0 | CP50: =(P50+Q50+S50) -> 1.4 | CQ50: =ROUND((ROUND((AC50*AW50*1),2)*BC50),2) -> 0 | CR50: =(ROUND((ROUND(((((ET50*1.2)*0.3))*AV50*1),2)*BB50),2)+ROUND((ROUND(((AE50-(((EU50*1.2)*0.3)))*AV50*1),2)*BS50),2)) -> 0.76 | CS50: =(ROUND((ROUND(((((EU50*1.2)*0.3))*AV50*1),2)*BS50),2)+ROUND((ROUND(((AE50-(((EU50*1.2)*0.3)))*AV50*1),2)*BS50),2)) -> 0 | CT50: =ROUND((ROUND((AF50*AV50*1),2)*BA50),2) -> 169.93 | CU50: =AG50 -> 0 | CV50: =(AH50*AV50) -> 12.52224 | CW50: =AI50 -> 0 | CX50: =AJ50 -> 0 | CY50: =(ROUND((((S50+ROUND((ROUND(((((EU50*1.2)*0.3))*AV50*1),2)*BS50),2))*AT50)/100),2)+ROUND(((ROUND((ROUND(((AE50-(((EU50*1.2)*0.3)))*AV50*1),2)*BS50),2)*AT50)/100),2)) -> 1.32 | CZ50: =(ROUND((((S50+ROUND((ROUND(((((EU50*1.2)*0.3))*AV50*1),2)*BS50),2))*AU50)/100),2)+ROUND(((ROUND((ROUND(((AE50-(((EU50*1.2)*0.3)))*AV50*1),2)*BS50),2)*AU50)/100),2)) -> 0.74 | DB50: 43 | DD50: *1)*0 | DE50: *1,2)*0,3 | DF50: *1,2)*0,3 | DG50: *1,2)*0,3 | DI50: *1,2)*0,3 | DJ50: *1,2)*0,3 | DN50: 0 | DO50: 0 | DP50: 1 | DQ50: 1 | DU50: 1013 | DV50: 1 Т | DW50: 1 Т | DX50: 1 | EE50: 55393701 | EF50: 40 | EG50: Монтаж оборудования | EH50: 0 | EJ50: 2 | EK50: 69 | EL50: ТСН-2001.4-10. Монтаж радиотелевизионного и электронного оборудования | EM50: ТСН-2001.4-10-2 | EO50: Поправка: Гл.12.Прил.8.п.8. 3_12.00.01.11.001 Поправка: Гл.4.Прил.2.2.п.2.2.29_04.00.01.35.003 | EQ50: 0 | ER50: 545.15 | ES50: 108.97 | ET50: 1.94 | EU50: 0 | EV50: 434.24 | EW50: 32 | EX50: 0 | EY50: 0 | FQ50: 0 | FR50: 0 | FS50: 0 | FX50: 95 | FY50: 53 | GD50: 1 | GF50: -1460753722 | GG50: 2 | GH50: 1 | GI50: 2 | GJ50: 0 | GK50: 0 | GL50: =ROUND(IF(AND(BH50=3,BI50=3,FS50<>0),P50,0),2) -> 0 | GM50: =ROUND(O50+X50+Y50,2)+GX50 -> 3.46 | GN50: =IF(OR(BI50=0,BI50=1),GM50-GX50,0) -> 0 | GO50: =IF(BI50=2,GM50-GX50,0) -> 3.46 | GP50: =IF(BI50=4,GM50-GX50,0) -> 0 | GR50: 0 | GS50: 3 | GT50: 0 | GV50: =ROUND((GT50),6) -> 0 | GW50: 1 | GX50: =ROUND(HC50*I50,2) -> 0 | HA50: 0 | HB50: 0 | HC50: =GV50*GW50 -> 0 | HS50: 0 | IK50: 0
A51: 17 | B51: 1 | C51: =ROW(SmtRes!A154) -> 154 | D51: =ROW(EtalonRes!A174) -> 174 | E51: 12 | F51: 4.10-134-3 | G51: Монтаж металлоконструкций для телевизионных антенн / демонтаж мачты антенной | H51: 1 Т | I51: =ROUND((5.1+3.1)/1000,9) -> 0.0082 | J51: 0 | K51: =ROUND((5.1+3.1)/1000,9) -> 0.0082 | O51: =ROUND(CP51,2) -> 78.43 | P51: =ROUND((ROUND((AC51*AW51*I51),2)*BC51),2) -> 0 | Q51: =(ROUND((ROUND(((((ET51*1.2)*0.3))*AV51*I51),2)*BB51),2)+ROUND((ROUND(((AE51-(((EU51*1.2)*0.3)))*AV51*I51),2)*BS51),2)) -> 0.1 | R51: =(ROUND((ROUND(((((EU51*1.2)*0.3))*AV51*I51),2)*BS51),2)+ROUND((ROUND(((AE51-(((EU51*1.2)*0.3)))*AV51*I51),2)*BS51),2)) -> 0 | S51: =ROUND((ROUND((AF51*AV51*I51),2)*BA51),2) -> 78.33 | T51: =ROUND(CU51*I51,2) -> 0 | U51: =CV51*I51 -> 0.10268237 | V51: =CW51*I51 -> 0 | W51: =ROUND(CX51*I51,2) -> 0 | X51: =(ROUND((((S51+ROUND((ROUND(((((EU51*1.2)*0.3))*AV51*I51),2)*BS51),2))*AT51)/100),2)+ROUND(((ROUND((ROUND(((AE51-(((EU51*1.2)*0.3)))*AV51*I51),2)*BS51),2)*AT51)/100),2)) -> 74.41 | Y51: =(ROUND((((S51+ROUND((ROUND(((((EU51*1.2)*0.3))*AV51*I51),2)*BS51),2))*AU51)/100),2)+ROUND(((ROUND((ROUND(((AE51-(((EU51*1.2)*0.3)))*AV51*I51),2)*BS51),2)*AU51)/100),2)) -> 41.51 | AA51: 55917799 | AB51: =ROUND((AC51+AD51+AF51),6) -> 157.0248 | AC51: =ROUND((((ES51*1)*0)),6) -> 0 | AD51: =ROUND((((((ET51*1.2)*0.3))-(((EU51*1.2)*0.3)))+AE51),6) -> 0.6984 | AE51: =ROUND((((EU51*1.2)*0.3)),6) -> 0 | AF51: =ROUND((((EV51*1.2)*0.3)),6) -> 156.3264 | AG51: =ROUND((AP51),6) -> 0 | AH51: =(((EW51*1.2)*0.3)) -> 11.52 | AI51: =(((EX51*1.2)*0.3)) -> 0 | AJ51: =(AS51) -> 0 | AK51: 545.15 | AL51: 108.97 | AM51: 1.94 | AN51: 0 | AO51: 434.24 | AP51: 0 | AQ51: 32 | AR51: 0 | AS51: 0 | AT51: 95 | AU51: 53 | AV51: 1.087 | AW51: 1 | AZ51: 1 | BA51: 56.35 | BB51: 9.97 | BC51: 4.46 | BH51: 0 | BI51: 2 | BJ51: ТСН-2001.4 Доп. 81, Сб. 10, т. 134, поз. 3 | BM51: 69 | BN51: 0 | BO51: 4.10-134-3 | BP51: 1 | BQ51: 40 | BR51: 0 | BS51: 56.35 | BT51: 1 | BU51: 1 | BV51: 1 | BW51: 1 | BX51: 1 | BZ51: 95 | CA51: 53 | CE51: 1566 | CF51: 0 | CG51: 0 | CM51: 0 | CN51: Поправка: Гл.12.Прил.8.п.8. 3_12.00.01.11.001 Наименование: При наличии напряженных и стесненных условий производства работ (стесненность, сложность складирования и транспортной логистики и т.п.) для объектов, расположенных в пределах круговой магистральной системы улиц "Садовое кольцо" города Москвы Поправка: Гл.4.Прил.2.2.п.2.2.29_04.00.01.35.003 Наименование: При демонтаже оборудования, предназначенного в лом | CO51: 0 | CP51: =(P51+Q51+S51) -> 78.43 | CQ51: =ROUND((ROUND((AC51*AW51*1),2)*BC51),2) -> 0 | CR51: =(ROUND((ROUND(((((ET51*1.2)*0.3))*AV51*1),2)*BB51),2)+ROUND((ROUND(((AE51-(((EU51*1.2)*0.3)))*AV51*1),2)*BS51),2)) -> 7.58 | CS51: =(ROUND((ROUND(((((EU51*1.2)*0.3))*AV51*1),2)*BS51),2)+ROUND((ROUND(((AE51-(((EU51*1.2)*0.3)))*AV51*1),2)*BS51),2)) -> 0 | CT51: =ROUND((ROUND((AF51*AV51*1),2)*BA51),2) -> 9575.56 | CU51: =AG51 -> 0 | CV51: =(AH51*AV51) -> 12.52224 | CW51: =AI51 -> 0 | CX51: =AJ51 -> 0 | CY51: =(ROUND((((S51+ROUND((ROUND(((((EU51*1.2)*0.3))*AV51*1),2)*BS51),2))*AT51)/100),2)+ROUND(((ROUND((ROUND(((AE51-(((EU51*1.2)*0.3)))*AV51*1),2)*BS51),2)*AT51)/100),2)) -> 74.41 | CZ51: =(ROUND((((S51+ROUND((ROUND(((((EU51*1.2)*0.3))*AV51*1),2)*BS51),2))*AU51)/100),2)+ROUND(((ROUND((ROUND(((AE51-(((EU51*1.2)*0.3)))*AV51*1),2)*BS51),2)*AU51)/100),2)) -> 41.51 | DB51: 45 | DD51: *1)*0 | DE51: *1,2)*0,3 | DF51: *1,2)*0,3 | DG51: *1,2)*0,3 | DI51: *1,2)*0,3 | DJ51: *1,2)*0,3 | DN51: 0 | DO51: 0 | DP51: 1 | DQ51: 1 | DU51: 1013 | DV51: 1 Т | DW51: 1 Т | DX51: 1 | EE51: 55393701 | EF51: 40 | EG51: Монтаж оборудования | EH51: 0 | EJ51: 2 | EK51: 69 | EL51: ТСН-2001.4-10. Монтаж радиотелевизионного и электронного оборудования | EM51: ТСН-2001.4-10-2 | EO51: Поправка: Гл.12.Прил.8.п.8. 3_12.00.01.11.001 Поправка: Гл.4.Прил.2.2.п.2.2.29_04.00.01.35.003 | EQ51: 0 | ER51: 545.15 | ES51: 108.97 | ET51: 1.94 | EU51: 0 | EV51: 434.24 | EW51: 32 | EX51: 0 | EY51: 0 | FQ51: 0 | FR51: 0 | FS51: 0 | FX51: 95 | FY51: 53 | GD51: 1 | GF51: -1460753722 | GG51: 2 | GH51: 1 | GI51: 2 | GJ51: 0 | GK51: 0 | GL51: =ROUND(IF(AND(BH51=3,BI51=3,FS51<>0),P51,0),2) -> 0 | GM51: =ROUND(O51+X51+Y51,2)+GX51 -> 194.35 | GN51: =IF(OR(BI51=0,BI51=1),GM51-GX51,0) -> 0 | GO51: =IF(BI51=2,GM51-GX51,0) -> 194.35 | GP51: =IF(BI51=4,GM51-GX51,0) -> 0 | GR51: 0 | GS51: 3 | GT51: 0 | GV51: =ROUND((GT51),6) -> 0 | GW51: 1 | GX51: =ROUND(HC51*I51,2) -> 0 | HA51: 0 | HB51: 0 | HC51: =GV51*GW51 -> 0 | HS51: 0 | IK51: 0
A52: 17 | B52: 1 | C52: =ROW(SmtRes!A155) -> 155 | D52: =ROW(EtalonRes!A175) -> 175 | E52: 13 | F52: 6.67-6-1 | G52: Демонтаж кабеля | H52: 100 м | I52: =ROUND((50+50+50+300+20+15)/100,9) -> 4.85 | J52: 0 | K52: =ROUND((50+50+50+300+20+15)/100,9) -> 4.85 | O52: =ROUND(CP52,2) -> 600.34 | P52: =ROUND((ROUND((AC52*AW52*I52),2)*BC52),2) -> 0 | Q52: =(ROUND((ROUND((((ET52*1.2))*AV52*I52),2)*BB52),2)+ROUND((ROUND(((AE52-((EU52*1.2)))*AV52*I52),2)*BS52),2)) -> 0 | R52: =(ROUND((ROUND((((EU52*1.2))*AV52*I52),2)*BS52),2)+ROUND((ROUND(((AE52-((EU52*1.2)))*AV52*I52),2)*BS52),2)) -> 0 | S52: =ROUND((ROUND((AF52*AV52*I52),2)*BA52),2) -> 600.34 | T52: =ROUND(CU52*I52,2) -> 0 | U52: =CV52*I52 -> 58.741726 | V52: =CW52*I52 -> 0 | W52: =ROUND(CX52*I52,2) -> 0 | X52: =(ROUND((((S52+ROUND((ROUND((((EU52*1.2))*AV52*I52),2)*BS52),2))*AT52)/100),2)+ROUND(((ROUND((ROUND(((AE52-((EU52*1.2)))*AV52*I52),2)*BS52),2)*AT52)/100),2)) -> 546.31 | Y52: =(ROUND((((S52+ROUND((ROUND((((EU52*1.2))*AV52*I52),2)*BS52),2))*AU52)/100),2)+ROUND(((ROUND((ROUND(((AE52-((EU52*1.2)))*AV52*I52),2)*BS52),2)*AU52)/100),2)) -> 288.16 | AA52: 55917797 | AB52: =ROUND((AC52+AD52+AF52),6) -> 118.224 | AC52: =ROUND(((ES52*1)),6) -> 0 | AD52: =ROUND(((((ET52*1.2))-((EU52*1.2)))+AE52),6) -> 0 | AE52: =ROUND(((EU52*1.2)),6) -> 0 | AF52: =ROUND(((EV52*1.2)),6) -> 118.224 | AG52: =ROUND((AP52),6) -> 0 | AH52: =((EW52*1.2)) -> 11.568 | AI52: =((EX52*1.2)) -> 0 | AJ52: =(AS52) -> 0 | AK52: 98.52 | AL52: 0 | AM52: 0 | AN52: 0 | AO52: 98.52 | AP52: 0 | AQ52: 9.64 | AR52: 0 | AS52: 0 | AT52: 91 | AU52: 48 | AV52: 1.047 | AW52: 1 | AZ52: 1 | BA52: 1 | BB52: 1 | BC52: 1 | BH52: 0 | BI52: 1 | BJ52: ТСН-2001.6. Доп. 1-42. Сб. 67, т. 6, поз. 1 | BM52: 106 | BN52: 0 | BO52: 6.67-6-1 | BP52: 1 | BQ52: 60 | BR52: 0 | BS52: 1 | BT52: 1 | BU52: 1 | BV52: 1 | BW52: 1 | BX52: 1 | BZ52: 91 | CA52: 48 | CE52: 1566 | CF52: 0 | CG52: 0 | CM52: 0 | CN52: Поправка: Гл.12.Прил.8.п.8. 3_12.00.01.11.001 Наименование: При наличии напряженных и стесненных условий производства работ (стесненность, сложность складирования и транспортной логистики и т.п.) для объектов, расположенных в пределах круговой магистральной системы улиц "Садовое кольцо" города Москвы | CO52: 0 | CP52: =(P52+Q52+S52) -> 600.34 | CQ52: =ROUND((ROUND((AC52*AW52*1),2)*BC52),2) -> 0 | CR52: =(ROUND((ROUND((((ET52*1.2))*AV52*1),2)*BB52),2)+ROUND((ROUND(((AE52-((EU52*1.2)))*AV52*1),2)*BS52),2)) -> 0 | CS52: =(ROUND((ROUND((((EU52*1.2))*AV52*1),2)*BS52),2)+ROUND((ROUND(((AE52-((EU52*1.2)))*AV52*1),2)*BS52),2)) -> 0 | CT52: =ROUND((ROUND((AF52*AV52*1),2)*BA52),2) -> 123.78 | CU52: =AG52 -> 0 | CV52: =(AH52*AV52) -> 12.111696 | CW52: =AI52 -> 0 | CX52: =AJ52 -> 0 | CY52: =(ROUND((((S52+ROUND((ROUND((((EU52*1.2))*AV52*1),2)*BS52),2))*AT52)/100),2)+ROUND(((ROUND((ROUND(((AE52-((EU52*1.2)))*AV52*1),2)*BS52),2)*AT52)/100),2)) -> 546.31 | CZ52: =(ROUND((((S52+ROUND((ROUND((((EU52*1.2))*AV52*1),2)*BS52),2))*AU52)/100),2)+ROUND(((ROUND((ROUND(((AE52-((EU52*1.2)))*AV52*1),2)*BS52),2)*AU52)/100),2)) -> 288.16 | DB52: 47 | DD52: *1 | DE52: *1,2 | DF52: *1,2 | DG52: *1,2 | DI52: *1,2 | DJ52: *1,2 | DN52: 0 | DO52: 0 | DP52: 1 | DQ52: 1 | DU52: 1003 | DV52: 100 м | DW52: 100 м | DX52: 100 | EE52: 55393738 | EF52: 60 | EG52: Ремонтно-строительные работы | EH52: 0 | EJ52: 1 | EK52: 106 | EL52: ТСН-2001.6-67. Электромонтажные работы | EM52: ТСН-2001.6-67-1 | EO52: Поправка: Гл.12.Прил.8.п.8. 3_12.00.01.11.001 | EQ52: 0 | ER52: 98.52 | ES52: 0 | ET52: 0 | EU52: 0 | EV52: 98.52 | EW52: 9.64 | EX52: 0 | EY52: 0 | FQ52: 0 | FR52: 0 | FS52: 0 | FX52: 91 | FY52: 48 | GD52: 1 | GF52: 1114236003 | GG52: 2 | GH52: 1 | GI52: 2 | GJ52: 0 | GK52: 0 | GL52: =ROUND(IF(AND(BH52=3,BI52=3,FS52<>0),P52,0),2) -> 0 | GM52: =ROUND(O52+X52+Y52,2)+GX52 -> 1434.81 | GN52: =IF(OR(BI52=0,BI52=1),GM52-GX52,0) -> 1434.81 | GO52: =IF(BI52=2,GM52-GX52,0) -> 0 | GP52: =IF(BI52=4,GM52-GX52,0) -> 0 | GR52: 0 | GS52: 3 | GT52: 0 | GV52: =ROUND((GT52),6) -> 0 | GW52: 1 | GX52: =ROUND(HC52*I52,2) -> 0 | HA52: 0 | HB52: 0 | HC52: =GV52*GW52 -> 0 | HS52: 0 | IK52: 0
A53: 17 | B53: 1 | C53: =ROW(SmtRes!A156) -> 156 | D53: =ROW(EtalonRes!A176) -> 176 | E53: 13 | F53: 6.67-6-1 | G53: Демонтаж кабеля | H53: 100 м | I53: =ROUND((50+50+50+300+20+15)/100,9) -> 4.85 | J53: 0 | K53: =ROUND((50+50+50+300+20+15)/100,9) -> 4.85 | O53: =ROUND(CP53,2) -> 33829.16 | P53: =ROUND((ROUND((AC53*AW53*I53),2)*BC53),2) -> 0 | Q53: =(ROUND((ROUND((((ET53*1.2))*AV53*I53),2)*BB53),2)+ROUND((ROUND(((AE53-((EU53*1.2)))*AV53*I53),2)*BS53),2)) -> 0 | R53: =(ROUND((ROUND((((EU53*1.2))*AV53*I53),2)*BS53),2)+ROUND((ROUND(((AE53-((EU53*1.2)))*AV53*I53),2)*BS53),2)) -> 0 | S53: =ROUND((ROUND((AF53*AV53*I53),2)*BA53),2) -> 33829.16 | T53: =ROUND(CU53*I53,2) -> 0 | U53: =CV53*I53 -> 58.741726 | V53: =CW53*I53 -> 0 | W53: =ROUND(CX53*I53,2) -> 0 | X53: =(ROUND((((S53+ROUND((ROUND((((EU53*1.2))*AV53*I53),2)*BS53),2))*AT53)/100),2)+ROUND(((ROUND((ROUND(((AE53-((EU53*1.2)))*AV53*I53),2)*BS53),2)*AT53)/100),2)) -> 30784.54 | Y53: =(ROUND((((S53+ROUND((ROUND((((EU53*1.2))*AV53*I53),2)*BS53),2))*AU53)/100),2)+ROUND(((ROUND((ROUND(((AE53-((EU53*1.2)))*AV53*I53),2)*BS53),2)*AU53)/100),2)) -> 16238 | AA53: 55917799 | AB53: =ROUND((AC53+AD53+AF53),6) -> 118.224 | AC53: =ROUND(((ES53*1)),6) -> 0 | AD53: =ROUND(((((ET53*1.2))-((EU53*1.2)))+AE53),6) -> 0 | AE53: =ROUND(((EU53*1.2)),6) -> 0 | AF53: =ROUND(((EV53*1.2)),6) -> 118.224 | AG53: =ROUND((AP53),6) -> 0 | AH53: =((EW53*1.2)) -> 11.568 | AI53: =((EX53*1.2)) -> 0 | AJ53: =(AS53) -> 0 | AK53: 98.52 | AL53: 0 | AM53: 0 | AN53: 0 | AO53: 98.52 | AP53: 0 | AQ53: 9.64 | AR53: 0 | AS53: 0 | AT53: 91 | AU53: 48 | AV53: 1.047 | AW53: 1 | AZ53: 1 | BA53: 56.35 | BB53: 1 | BC53: 1 | BH53: 0 | BI53: 1 | BJ53: ТСН-2001.6. Доп. 1-42. Сб. 67, т. 6, поз. 1 | BM53: 106 | BN53: 0 | BO53: 6.67-6-1 | BP53: 1 | BQ53: 60 | BR53: 0 | BS53: 56.35 | BT53: 1 | BU53: 1 | BV53: 1 | BW53: 1 | BX53: 1 | BZ53: 91 | CA53: 48 | CE53: 1566 | CF53: 0 | CG53: 0 | CM53: 0 | CN53: Поправка: Гл.12.Прил.8.п.8. 3_12.00.01.11.001 Наименование: При наличии напряженных и стесненных условий производства работ (стесненность, сложность складирования и транспортной логистики и т.п.) для объектов, расположенных в пределах круговой магистральной системы улиц "Садовое кольцо" города Москвы | CO53: 0 | CP53: =(P53+Q53+S53) -> 33829.16 | CQ53: =ROUND((ROUND((AC53*AW53*1),2)*BC53),2) -> 0 | CR53: =(ROUND((ROUND((((ET53*1.2))*AV53*1),2)*BB53),2)+ROUND((ROUND(((AE53-((EU53*1.2)))*AV53*1),2)*BS53),2)) -> 0 | CS53: =(ROUND((ROUND((((EU53*1.2))*AV53*1),2)*BS53),2)+ROUND((ROUND(((AE53-((EU53*1.2)))*AV53*1),2)*BS53),2)) -> 0 | CT53: =ROUND((ROUND((AF53*AV53*1),2)*BA53),2) -> 6975 | CU53: =AG53 -> 0 | CV53: =(AH53*AV53) -> 12.111696 | CW53: =AI53 -> 0 | CX53: =AJ53 -> 0 | CY53: =(ROUND((((S53+ROUND((ROUND((((EU53*1.2))*AV53*1),2)*BS53),2))*AT53)/100),2)+ROUND(((ROUND((ROUND(((AE53-((EU53*1.2)))*AV53*1),2)*BS53),2)*AT53)/100),2)) -> 30784.54 | CZ53: =(ROUND((((S53+ROUND((ROUND((((EU53*1.2))*AV53*1),2)*BS53),2))*AU53)/100),2)+ROUND(((ROUND((ROUND(((AE53-((EU53*1.2)))*AV53*1),2)*BS53),2)*AU53)/100),2)) -> 16238 | DB53: 48 | DD53: *1 | DE53: *1,2 | DF53: *1,2 | DG53: *1,2 | DI53: *1,2 | DJ53: *1,2 | DN53: 0 | DO53: 0 | DP53: 1 | DQ53: 1 | DU53: 1003 | DV53: 100 м | DW53: 100 м | DX53: 100 | EE53: 55393738 | EF53: 60 | EG53: Ремонтно-строительные работы | EH53: 0 | EJ53: 1 | EK53: 106 | EL53: ТСН-2001.6-67. Электромонтажные работы | EM53: ТСН-2001.6-67-1 | EO53: Поправка: Гл.12.Прил.8.п.8. 3_12.00.01.11.001 | EQ53: 0 | ER53: 98.52 | ES53: 0 | ET53: 0 | EU53: 0 | EV53: 98.52 | EW53: 9.64 | EX53: 0 | EY53: 0 | FQ53: 0 | FR53: 0 | FS53: 0 | FX53: 91 | FY53: 48 | GD53: 1 | GF53: 1114236003 | GG53: 2 | GH53: 1 | GI53: 2 | GJ53: 0 | GK53: 0 | GL53: =ROUND(IF(AND(BH53=3,BI53=3,FS53<>0),P53,0),2) -> 0 | GM53: =ROUND(O53+X53+Y53,2)+GX53 -> 80851.7 | GN53: =IF(OR(BI53=0,BI53=1),GM53-GX53,0) -> 80851.7 | GO53: =IF(BI53=2,GM53-GX53,0) -> 0 | GP53: =IF(BI53=4,GM53-GX53,0) -> 0 | GR53: 0 | GS53: 3 | GT53: 0 | GV53: =ROUND((GT53),6) -> 0 | GW53: 1 | GX53: =ROUND(HC53*I53,2) -> 0 | HA53: 0 | HB53: 0 | HC53: =GV53*GW53 -> 0 | HS53: 0 | IK53: 0
A55: 51 | B55: =B24 -> 1 | C55: =A24 -> 4 | D55: =ROW(A24) -> 24 | F55: =IF(F24<>"",F24,"") -> Новый раздел | G55: =IF(G24<>"",G24,"") -> Демонтажные работы | H55: 0 | O55: =ROUND(AB55,2) -> 1019.76 | P55: =ROUND(AC55,2) -> 0 | Q55: =ROUND(AD55,2) -> 33.55 | R55: =ROUND(AE55,2) -> 4.95 | S55: =ROUND(AF55,2) -> 986.21 | T55: =ROUND(AG55,2) -> 0 | U55: =AH55 -> 88.462399 | V55: =AI55 -> 0 | W55: =ROUND(AJ55,2) -> 0 | X55: =ROUND(AK55,2) -> 913.63 | Y55: =ROUND(AL55,2) -> 489.76 | AB55: =ROUND(SUMIF(AA28:AA53,"=55917797",O28:O53),2) -> 1019.76 | AC55: =ROUND(SUMIF(AA28:AA53,"=55917797",P28:P53),2) -> 0 | AD55: =ROUND(SUMIF(AA28:AA53,"=55917797",Q28:Q53),2) -> 33.55 | AE55: =ROUND(SUMIF(AA28:AA53,"=55917797",R28:R53),2) -> 4.95 | AF55: =ROUND(SUMIF(AA28:AA53,"=55917797",S28:S53),2) -> 986.21 | AG55: =ROUND(SUMIF(AA28:AA53,"=55917797",T28:T53),2) -> 0 | AH55: =SUMIF(AA28:AA53,"=55917797",U28:U53) -> 88.462399 | AI55: =SUMIF(AA28:AA53,"=55917797",V28:V53) -> 0 | AJ55: =ROUND(SUMIF(AA28:AA53,"=55917797",W28:W53),2) -> 0 | AK55: =ROUND(SUMIF(AA28:AA53,"=55917797",X28:X53),2) -> 913.63 | AL55: =ROUND(SUMIF(AA28:AA53,"=55917797",Y28:Y53),2) -> 489.76 | AO55: =ROUND(BX55,2) -> 0 | AP55: =ROUND(BY55,2) -> 0 | AQ55: =ROUND(BZ55,2) -> 0 | AR55: =ROUND(CA55,2) -> 2423.15 | AS55: =ROUND(CB55,2) -> 1445.57 | AT55: =ROUND(CC55,2) -> 977.58 | AU55: =ROUND(CD55,2) -> 0 | AV55: =ROUND(CE55,2) -> 0 | ... BD55: =ROUND(CM55,2) -> 0 | BX55: =ROUND(SUMIF(AA28:AA53,"=55917797",FQ28:FQ53),2) -> 0 | BY55: =ROUND(SUMIF(AA28:AA53,"=55917797",FR28:FR53),2) -> 0 | BZ55: =ROUND(SUMIF(AA28:AA53,"=55917797",GL28:GL53),2) -> 0 | CA55: =ROUND(SUMIF(AA28:AA53,"=55917797",GM28:GM53),2) -> 2423.15 | CB55: =ROUND(SUMIF(AA28:AA53,"=55917797",GN28:GN53),2) -> 1445.57 | CC55: =ROUND(SUMIF(AA28:AA53,"=55917797",GO28:GO53),2) -> 977.58 | CD55: =ROUND(SUMIF(AA28:AA53,"=55917797",GP28:GP53),2) -> 0 | CE55: =AC55-BX55 -> 0 | CF55: =AC55-BY55 -> 0 | CG55: =BX55-BZ55 -> 0 | CH55: =AC55-BX55-BY55+BZ55 -> 0 | CI55: =BY55-BZ55 -> 0 | CJ55: =ROUND(SUMIF(AA28:AA53,"=55917797",GX28:GX53),2) -> 0 | CK55: =ROUND(SUMIF(AA28:AA53,"=55917797",GY28:GY53),2) -> 0 | CL55: =ROUND(SUMIF(AA28:AA53,"=55917797",GZ28:GZ53),2) -> 0 | CM55: =ROUND(SUMIF(AA28:AA53,"=55917797",HD28:HD53),2) -> 0 | DG55: =ROUND(DT55,2) -> 56142.08 | DH55: =ROUND(DU55,2) -> 0 | DI55: =ROUND(DV55,2) -> 569.14 | DJ55: =ROUND(DW55,2) -> 278.93 | DK55: =ROUND(DX55,2) -> 55572.94 | DL55: =ROUND(DY55,2) -> 0 | DM55: =DZ55 -> 88.462399 | DN55: =EA55 -> 0 | DO55: =ROUND(EB55,2) -> 0 | DP55: =ROUND(EC55,2) -> 51482.58 | DQ55: =ROUND(ED55,2) -> 27598.59 | DT55: =ROUND(SUMIF(AA28:AA53,"=55917799",O28:O53),2) -> 56142.08 | DU55: =ROUND(SUMIF(AA28:AA53,"=55917799",P28:P53),2) -> 0 | DV55: =ROUND(SUMIF(AA28:AA53,"=55917799",Q28:Q53),2) -> 569.14 | DW55: =ROUND(SUMIF(AA28:AA53,"=55917799",R28:R53),2) -> 278.93 | DX55: =ROUND(SUMIF(AA28:AA53,"=55917799",S28:S53),2) -> 55572.94 | DY55: =ROUND(SUMIF(AA28:AA53,"=55917799",T28:T53),2) -> 0 | DZ55: =SUMIF(AA28:AA53,"=55917799",U28:U53) -> 88.462399 | EA55: =SUMIF(AA28:AA53,"=55917799",V28:V53) -> 0 | EB55: =ROUND(SUMIF(AA28:AA53,"=55917799",W28:W53),2) -> 0 | EC55: =ROUND(SUMIF(AA28:AA53,"=55917799",X28:X53),2) -> 51482.58 | ED55: =ROUND(SUMIF(AA28:AA53,"=55917799",Y28:Y53),2) -> 27598.59 | EG55: =ROUND(FP55,2) -> 0 | EH55: =ROUND(FQ55,2) -> 0 | EI55: =ROUND(FR55,2) -> 0 | EJ55: =ROUND(FS55,2) -> 135223.25 | EK55: =ROUND(FT55,2) -> 81457.76 | EL55: =ROUND(FU55,2) -> 53765.49 | EM55: =ROUND(FV55,2) -> 0 | EN55: =ROUND(FW55,2) -> 0 | ... EV55: =ROUND(GE55,2) -> 0 | FP55: =ROUND(SUMIF(AA28:AA53,"=55917799",FQ28:FQ53),2) -> 0 | FQ55: =ROUND(SUMIF(AA28:AA53,"=55917799",FR28:FR53),2) -> 0 | FR55: =ROUND(SUMIF(AA28:AA53,"=55917799",GL28:GL53),2) -> 0 | FS55: =ROUND(SUMIF(AA28:AA53,"=55917799",GM28:GM53),2) -> 135223.25 | FT55: =ROUND(SUMIF(AA28:AA53,"=55917799",GN28:GN53),2) -> 81457.76 | FU55: =ROUND(SUMIF(AA28:AA53,"=55917799",GO28:GO53),2) -> 53765.49 | FV55: =ROUND(SUMIF(AA28:AA53,"=55917799",GP28:GP53),2) -> 0 | FW55: =DU55-FP55 -> 0 | FX55: =DU55-FQ55 -> 0 | FY55: =FP55-FR55 -> 0 | FZ55: =DU55-FP55-FQ55+FR55 -> 0 | GA55: =FQ55-FR55 -> 0 | GB55: =ROUND(SUMIF(AA28:AA53,"=55917799",GX28:GX53),2) -> 0 | GC55: =ROUND(SUMIF(AA28:AA53,"=55917799",GY28:GY53),2) -> 0 | GD55: =ROUND(SUMIF(AA28:AA53,"=55917799",GZ28:GZ53),2) -> 0 | GE55: =ROUND(SUMIF(AA28:AA53,"=55917799",HD28:HD53),2) -> 0 | GX55: 0
A57: 50 | B57: 0 | C57: 0 | D57: 1 | E57: 201 | F57: =ROUND(Source!O55,O57) -> 1019.76 | G57: ПЗ | H57: Прямые затраты | K57: 201 | L57: 1 | M57: 3 | O57: 2 | P57: =ROUND(Source!DG55,O57) -> 56142.08 | W57: 1019.76 | X57: 1 | Y57: 1019.76 | Z57: 56142.08 | AA57: 1 | AB57: 56142.08
A58: 50 | B58: 0 | C58: 0 | D58: 1 | E58: 202 | F58: =ROUND(Source!P55,O58) -> 0 | G58: СтМатОб | H58: Стоимость материальных ресурсов (всего) | K58: 202 | L58: 2 | M58: 3 | O58: 2 | P58: =ROUND(Source!DH55,O58) -> 0 | W58: 0 | X58: 1 | Y58: 0 | Z58: 0 | AA58: 1 | AB58: 0
A59: 50 | B59: 0 | C59: 0 | D59: 1 | E59: 222 | F59: =ROUND(Source!AO55,O59) -> 0 | G59: СтМатОбЗак | H59: Стоимость материалов и оборудования заказчика | K59: 222 | L59: 3 | M59: 3 | O59: 2 | P59: =ROUND(Source!EG55,O59) -> 0 | W59: 0 | X59: 1 | Y59: 0 | Z59: 0 | AA59: 1 | AB59: 0
A60: 50 | B60: 0 | C60: 0 | D60: 1 | E60: 225 | F60: =ROUND(Source!AV55,O60) -> 0 | G60: СтМатОбПод | H60: Стоимость материалов и оборудования подрядчика | K60: 225 | L60: 4 | M60: 3 | O60: 2 | P60: =ROUND(Source!EN55,O60) -> 0 | W60: 0 | X60: 1 | Y60: 0 | Z60: 0 | AA60: 1 | AB60: 0
A61: 50 | B61: 0 | C61: 0 | D61: 1 | E61: 226 | F61: =ROUND(Source!AW55,O61) -> 0 | G61: СтМат | H61: Стоимость материалов (всего) | K61: 226 | L61: 5 | M61: 3 | O61: 2 | P61: =ROUND(Source!EO55,O61) -> 0 | W61: 0 | X61: 1 | Y61: 0 | Z61: 0 | AA61: 1 | AB61: 0
A62: 50 | B62: 0 | C62: 0 | D62: 1 | E62: 227 | F62: =ROUND(Source!AX55,O62) -> 0 | G62: СтМатЗак | H62: Стоимость материалов заказчика | K62: 227 | L62: 6 | M62: 3 | O62: 2 | P62: =ROUND(Source!EP55,O62) -> 0 | W62: 0 | X62: 1 | Y62: 0 | Z62: 0 | AA62: 1 | AB62: 0
A63: 50 | B63: 0 | C63: 0 | D63: 1 | E63: 228 | F63: =ROUND(Source!AY55,O63) -> 0 | G63: СтМатПод | H63: Стоимость материалов подрядчика | K63: 228 | L63: 7 | M63: 3 | O63: 2 | P63: =ROUND(Source!EQ55,O63) -> 0 | W63: 0 | X63: 1 | Y63: 0 | Z63: 0 | AA63: 1 | AB63: 0
A64: 50 | B64: 0 | C64: 0 | D64: 1 | E64: 216 | F64: =ROUND(Source!AP55,O64) -> 0 | G64: Оборуд | H64: Стоимость оборудования (всего) | K64: 216 | L64: 8 | M64: 3 | O64: 2 | P64: =ROUND(Source!EH55,O64) -> 0 | W64: 0 | X64: 1 | Y64: 0 | Z64: 0 | AA64: 1 | AB64: 0
A65: 50 | B65: 0 | C65: 0 | D65: 1 | E65: 223 | F65: =ROUND(Source!AQ55,O65) -> 0 | G65: ОборудЗак | H65: Стоимость оборудования заказчика | K65: 223 | L65: 9 | M65: 3 | O65: 2 | P65: =ROUND(Source!EI55,O65) -> 0 | W65: 0 | X65: 1 | Y65: 0 | Z65: 0 | AA65: 1 | AB65: 0
A66: 50 | B66: 0 | C66: 0 | D66: 1 | E66: 229 | F66: =ROUND(Source!AZ55,O66) -> 0 | G66: ОборудПод | H66: Стоимость оборудования подрядчика | K66: 229 | L66: 10 | M66: 3 | O66: 2 | P66: =ROUND(Source!ER55,O66) -> 0 | W66: 0 | X66: 1 | Y66: 0 | Z66: 0 | AA66: 1 | AB66: 0
A67: 50 | B67: 0 | C67: 0 | D67: 1 | E67: 203 | F67: =ROUND(Source!Q55,O67) -> 33.55 | G67: ЭММ | H67: Эксплуатация машин | K67: 203 | L67: 11 | M67: 3 | O67: 2 | P67: =ROUND(Source!DI55,O67) -> 569.14 | W67: 33.55 | X67: 1 | Y67: 33.55 | Z67: 569.14 | AA67: 1 | AB67: 569.14
A68: 50 | B68: 0 | C68: 0 | D68: 1 | E68: 231 | F68: =ROUND(Source!BB55,O68) -> 0 | G68: ЭММсНРиСП | H68: Эксплуатация машин по ТСН-2001.16 | K68: 231 | L68: 12 | M68: 3 | O68: 2 | P68: =ROUND(Source!ET55,O68) -> 0 | W68: 0 | X68: 1 | Y68: 0 | Z68: 0 | AA68: 1 | AB68: 0
A69: 50 | B69: 0 | C69: 0 | D69: 1 | E69: 204 | F69: =ROUND(Source!R55,O69) -> 4.95 | G69: ЗПМ | H69: ЗП машинистов | K69: 204 | L69: 13 | M69: 3 | O69: 2 | P69: =ROUND(Source!DJ55,O69) -> 278.93 | W69: 4.95 | X69: 1 | Y69: 4.95 | Z69: 278.93 | AA69: 1 | AB69: 278.93
A70: 50 | B70: 0 | C70: 0 | D70: 1 | E70: 205 | F70: =ROUND(Source!S55,O70) -> 986.21 | G70: ОЗП | H70: Основная ЗП рабочих | K70: 205 | L70: 14 | M70: 3 | O70: 2 | P70: =ROUND(Source!DK55,O70) -> 55572.94 | W70: 986.21 | X70: 1 | Y70: 986.21 | Z70: 55572.94 | AA70: 1 | AB70: 55572.94
A71: 50 | B71: 0 | C71: 0 | D71: 1 | E71: 232 | F71: =ROUND(Source!BC55,O71) -> 0 | G71: ОЗПсНРиСП | H71: Основная ЗП рабочих по ТСН-2001.16 | K71: 232 | L71: 15 | M71: 3 | O71: 2 | P71: =ROUND(Source!EU55,O71) -> 0 | W71: 0 | X71: 1 | Y71: 0 | Z71: 0 | AA71: 1 | AB71: 0
A72: 50 | B72: 0 | C72: 0 | D72: 1 | E72: 214 | F72: =ROUND(Source!AS55,O72) -> 1445.57 | G72: Строит | H72: Строительные работы с НР и СП | K72: 214 | L72: 16 | M72: 3 | O72: 2 | P72: =ROUND(Source!EK55,O72) -> 81457.76 | W72: 1445.57 | X72: 1 | Y72: 1445.57 | Z72: 81457.76 | AA72: 1 | AB72: 81457.76
A73: 50 | B73: 0 | C73: 0 | D73: 1 | E73: 215 | F73: =ROUND(Source!AT55,O73) -> 977.58 | G73: Монтаж | H73: Монтажные работы с НР и СП | K73: 215 | L73: 17 | M73: 3 | O73: 2 | P73: =ROUND(Source!EL55,O73) -> 53765.49 | W73: 977.58 | X73: 1 | Y73: 977.58 | Z73: 53765.49 | AA73: 1 | AB73: 53765.49
A74: 50 | B74: 0 | C74: 0 | D74: 1 | E74: 217 | F74: =ROUND(Source!AU55,O74) -> 0 | G74: Прочие | H74: Прочие работы с НР и СП | K74: 217 | L74: 18 | M74: 3 | O74: 2 | P74: =ROUND(Source!EM55,O74) -> 0 | W74: 0 | X74: 1 | Y74: 0 | Z74: 0 | AA74: 1 | AB74: 0
A75: 50 | B75: 0 | C75: 0 | D75: 1 | E75: 230 | F75: =ROUND(Source!BA55,O75) -> 0 | G75: ПрочиеЗатр | H75: Прочие затраты по ТСН-2001.16 | K75: 230 | L75: 19 | M75: 3 | O75: 2 | P75: =ROUND(Source!ES55,O75) -> 0 | W75: 0 | X75: 1 | Y75: 0 | Z75: 0 | AA75: 1 | AB75: 0
A76: 50 | B76: 0 | C76: 0 | D76: 1 | E76: 206 | F76: =ROUND(Source!T55,O76) -> 0 | G76: ВозврМат | H76: Возврат материалов | K76: 206 | L76: 20 | M76: 3 | O76: 2 | P76: =ROUND(Source!DL55,O76) -> 0 | W76: 0 | X76: 1 | Y76: 0 | Z76: 0 | AA76: 1 | AB76: 0
A77: 50 | B77: 0 | C77: 0 | D77: 1 | E77: 207 | F77: =Source!U55 -> 88.462399 | G77: ТрудСтр | H77: Трудозатраты строителей | K77: 207 | L77: 21 | M77: 3 | O77: -1 | P77: =Source!DM55 -> 88.462399 | W77: 88.462399 | X77: 1 | Y77: 88.462399 | Z77: 88.462399 | AA77: 1 | AB77: 88.462399
A78: 50 | B78: 0 | C78: 0 | D78: 1 | E78: 208 | F78: =Source!V55 -> 0 | G78: ТрудМаш | H78: Трудозатраты машинистов | K78: 208 | L78: 22 | M78: 3 | O78: -1 | P78: =Source!DN55 -> 0 | W78: 0 | X78: 1 | Y78: 0 | Z78: 0 | AA78: 1 | AB78: 0
A79: 50 | B79: 0 | C79: 0 | D79: 1 | E79: 209 | F79: =ROUND(Source!W55,O79) -> 0 | G79: ТранспМат | H79: Транспорт материалов | K79: 209 | L79: 23 | M79: 3 | O79: 2 | P79: =ROUND(Source!DO55,O79) -> 0 | W79: 0 | X79: 1 | Y79: 0 | Z79: 0 | AA79: 1 | AB79: 0
A80: 50 | B80: 0 | C80: 0 | D80: 1 | E80: 233 | F80: =ROUND(Source!BD55,O80) -> 0 | G80: Перевозка | H80: Перевозка грузов | K80: 233 | L80: 24 | M80: 3 | O80: 2 | P80: =ROUND(Source!EV55,O80) -> 0 | W80: 0 | X80: 1 | Y80: 0 | Z80: 0 | AA80: 1 | AB80: 0
A81: 50 | B81: 0 | C81: 0 | D81: 1 | E81: 210 | F81: =ROUND(Source!X55,O81) -> 913.63 | G81: НР | H81: Накладные расходы | K81: 210 | L81: 25 | M81: 3 | O81: 2 | P81: =ROUND(Source!DP55,O81) -> 51482.58 | W81: 913.63 | X81: 1 | Y81: 913.63 | Z81: 51482.58 | AA81: 1 | AB81: 51482.58
A82: 50 | B82: 0 | C82: 0 | D82: 1 | E82: 211 | F82: =ROUND(Source!Y55,O82) -> 489.76 | G82: СмПриб | H82: Сметная прибыль | K82: 211 | L82: 26 | M82: 3 | O82: 2 | P82: =ROUND(Source!DQ55,O82) -> 27598.59 | W82: 489.76 | X82: 1 | Y82: 489.76 | Z82: 27598.59 | AA82: 1 | AB82: 27598.59
A83: 50 | B83: 0 | C83: 0 | D83: 1 | E83: 224 | F83: =ROUND(Source!AR55,O83) -> 2423.15 | G83: Всего | H83: Всего с НР и СП | K83: 224 | L83: 27 | M83: 3 | O83: 2 | P83: =ROUND(Source!EJ55,O83) -> 135223.25 | W83: 2423.15 | X83: 1 | Y83: 2423.15 | Z83: 135223.25 | AA83: 1 | AB83: 135223.25
A85: 4 | B85: 1 | D85: =ROW(A120) -> 120 | F85: 1 | G85: Комплект основного оборудования (радиофикация) | I85: 0 | K85: -1 | S85: 0 | T85: 0 | V85: 0 | BX85: 0 | CJ85: 0
A87: 52 | B87: =B120 -> 1 | C87: =C120 -> 4 | D87: =D120 -> 85 | E87: =E120 -> 0 | F87: =F120 -> 1 | G87: =G120 -> Комплект основного оборудования (радиофикация) | O87: =O120 -> 68109.38 | P87: =P120 -> 67535.33 | Q87: =Q120 -> 111.87 | R87: =R120 -> 16.51 | S87: =S120 -> 462.18 | T87: =T120 -> 0 | U87: =U120 -> 37.271807 | V87: =V120 -> 0 | ... GX87: =GX120 -> 0
A89: 17 | B89: 1 | C89: =ROW(SmtRes!A167) -> 167 | D89: =ROW(EtalonRes!A188) -> 188 | E89: 14 | F89: 4.10-73-1 | G89: Монтаж радиостанции УКВ связи абонентской мощностью до 15 Вт стационарной | H89: 1 комплект | I89: 1 | J89: 0 | K89: 1 | O89: =ROUND(CP89,2) -> 234.24 | P89: =ROUND((ROUND((AC89*AW89*I89),2)*BC89),2) -> 75.68 | Q89: =(ROUND((ROUND((((ET89*1.2))*AV89*I89),2)*BB89),2)+ROUND((ROUND(((AE89-((EU89*1.2)))*AV89*I89),2)*BS89),2)) -> 0 | R89: =(ROUND((ROUND((((EU89*1.2))*AV89*I89),2)*BS89),2)+ROUND((ROUND(((AE89-((EU89*1.2)))*AV89*I89),2)*BS89),2)) -> 0 | S89: =ROUND((ROUND((AF89*AV89*I89),2)*BA89),2) -> 158.56 | T89: =ROUND(CU89*I89,2) -> 0 | U89: =CV89*I89 -> 12.564 | V89: =CW89*I89 -> 0 | W89: =ROUND(CX89*I89,2) -> 0 | X89: =(ROUND((((S89+ROUND((ROUND((((EU89*1.2))*AV89*I89),2)*BS89),2))*AT89)/100),2)+ROUND(((ROUND((ROUND(((AE89-((EU89*1.2)))*AV89*I89),2)*BS89),2)*AT89)/100),2)) -> 150.63 | Y89: =(ROUND((((S89+ROUND((ROUND((((EU89*1.2))*AV89*I89),2)*BS89),2))*AU89)/100),2)+ROUND(((ROUND((ROUND(((AE89-((EU89*1.2)))*AV89*I89),2)*BS89),2)*AU89)/100),2)) -> 84.04 | AA89: 55917797 | AB89: =ROUND((AC89+AD89+AF89),6) -> 227.12 | AC89: =ROUND(((ES89*1)),6) -> 75.68 | AD89: =ROUND(((((ET89*1.2))-((EU89*1.2)))+AE89),6) -> 0 | AE89: =ROUND(((EU89*1.2)),6) -> 0 | AF89: =ROUND(((EV89*1.2)),6) -> 151.44 | AG89: =ROUND((AP89),6) -> 0 | AH89: =((EW89*1.2)) -> 12 | AI89: =((EX89*1.2)) -> 0 | AJ89: =(AS89) -> 0 | AK89: 201.88 | AL89: 75.68 | AM89: 0 | AN89: 0 | AO89: 126.2 | AP89: 0 | AQ89: 10 | AR89: 0 | AS89: 0 | AT89: 95 | AU89: 53 | AV89: 1.047 | AW89: 1 | AZ89: 1 | BA89: 1 | BB89: 1 | BC89: 1 | BH89: 0 | BI89: 2 | BJ89: ТСН-2001.4 Доп. 80, Сб. 10, т. 73, поз. 1 | BM89: 69 | BN89: 0 | BO89: 4.10-73-1 | BP89: 1 | BQ89: 40 | BR89: 0 | BS89: 1 | BT89: 1 | BU89: 1 | BV89: 1 | BW89: 1 | BX89: 1 | BZ89: 95 | CA89: 53 | CE89: 1566 | CF89: 0 | CG89: 0 | CM89: 0 | CN89: Поправка: Гл.12.Прил.8.п.8. 3_12.00.01.11.001 Наименование: При наличии напряженных и стесненных условий производства работ (стесненность, сложность складирования и транспортной логистики и т.п.) для объектов, расположенных в пределах круговой магистральной системы улиц "Садовое кольцо" города Москвы | CO89: 0 | CP89: =(P89+Q89+S89) -> 234.24 | CQ89: =ROUND((ROUND((AC89*AW89*1),2)*BC89),2) -> 75.68 | CR89: =(ROUND((ROUND((((ET89*1.2))*AV89*1),2)*BB89),2)+ROUND((ROUND(((AE89-((EU89*1.2)))*AV89*1),2)*BS89),2)) -> 0 | CS89: =(ROUND((ROUND((((EU89*1.2))*AV89*1),2)*BS89),2)+ROUND((ROUND(((AE89-((EU89*1.2)))*AV89*1),2)*BS89),2)) -> 0 | CT89: =ROUND((ROUND((AF89*AV89*1),2)*BA89),2) -> 158.56 | CU89: =AG89 -> 0 | CV89: =(AH89*AV89) -> 12.564 | CW89: =AI89 -> 0 | CX89: =AJ89 -> 0 | CY89: =(ROUND((((S89+ROUND((ROUND((((EU89*1.2))*AV89*1),2)*BS89),2))*AT89)/100),2)+ROUND(((ROUND((ROUND(((AE89-((EU89*1.2)))*AV89*1),2)*BS89),2)*AT89)/100),2)) -> 150.63 | CZ89: =(ROUND((((S89+ROUND((ROUND((((EU89*1.2))*AV89*1),2)*BS89),2))*AU89)/100),2)+ROUND(((ROUND((ROUND(((AE89-((EU89*1.2)))*AV89*1),2)*BS89),2)*AU89)/100),2)) -> 84.04 | DB89: 49 | DD89: *1 | DE89: *1,2 | DF89: *1,2 | DG89: *1,2 | DI89: *1,2 | DJ89: *1,2 | DN89: 0 | DO89: 0 | DP89: 1 | DQ89: 1 | DU89: 1013 | DV89: 1 комплект | DW89: 1 комплект | DX89: 1 | EE89: 55393701 | EF89: 40 | EG89: Монтаж оборудования | EH89: 0 | EJ89: 2 | EK89: 69 | EL89: ТСН-2001.4-10. Монтаж радиотелевизионного и электронного оборудования | EM89: ТСН-2001.4-10-2 | EO89: Поправка: Гл.12.Прил.8.п.8. 3_12.00.01.11.001 | EQ89: 0 | ER89: 201.88 | ES89: 75.68 | ET89: 0 | EU89: 0 | EV89: 126.2 | EW89: 10 | EX89: 0 | EY89: 0 | FQ89: 0 | FR89: 0 | FS89: 0 | FX89: 95 | FY89: 53 | GD89: 1 | GF89: -542777880 | GG89: 2 | GH89: 1 | GI89: 2 | GJ89: 0 | GK89: 0 | GL89: =ROUND(IF(AND(BH89=3,BI89=3,FS89<>0),P89,0),2) -> 0 | GM89: =ROUND(O89+X89+Y89,2)+GX89 -> 468.91 | GN89: =IF(OR(BI89=0,BI89=1),GM89-GX89,0) -> 0 | GO89: =IF(BI89=2,GM89-GX89,0) -> 468.91 | GP89: =IF(BI89=4,GM89-GX89,0) -> 0 | GR89: 0 | GS89: 3 | GT89: 0 | GV89: =ROUND((GT89),6) -> 0 | GW89: 1 | GX89: =ROUND(HC89*I89,2) -> 0 | HA89: 0 | HB89: 0 | HC89: =GV89*GW89 -> 0 | HS89: 0 | IK89: 0
A90: 17 | B90: 1 | C90: =ROW(SmtRes!A178) -> 178 | D90: =ROW(EtalonRes!A200) -> 200 | E90: 14 | F90: 4.10-73-1 | G90: Монтаж радиостанции УКВ связи абонентской мощностью до 15 Вт стационарной | H90: 1 комплект | I90: 1 | J90: 0 | K90: 1 | O90: =ROUND(CP90,2) -> 9659.87 | P90: =ROUND((ROUND((AC90*AW90*I90),2)*BC90),2) -> 725.01 | Q90: =(ROUND((ROUND((((ET90*1.2))*AV90*I90),2)*BB90),2)+ROUND((ROUND(((AE90-((EU90*1.2)))*AV90*I90),2)*BS90),2)) -> 0 | R90: =(ROUND((ROUND((((EU90*1.2))*AV90*I90),2)*BS90),2)+ROUND((ROUND(((AE90-((EU90*1.2)))*AV90*I90),2)*BS90),2)) -> 0 | S90: =ROUND((ROUND((AF90*AV90*I90),2)*BA90),2) -> 8934.86 | T90: =ROUND(CU90*I90,2) -> 0 | U90: =CV90*I90 -> 12.564 | V90: =CW90*I90 -> 0 | W90: =ROUND(CX90*I90,2) -> 0 | X90: =(ROUND((((S90+ROUND((ROUND((((EU90*1.2))*AV90*I90),2)*BS90),2))*AT90)/100),2)+ROUND(((ROUND((ROUND(((AE90-((EU90*1.2)))*AV90*I90),2)*BS90),2)*AT90)/100),2)) -> 8488.12 | Y90: =(ROUND((((S90+ROUND((ROUND((((EU90*1.2))*AV90*I90),2)*BS90),2))*AU90)/100),2)+ROUND(((ROUND((ROUND(((AE90-((EU90*1.2)))*AV90*I90),2)*BS90),2)*AU90)/100),2)) -> 4735.48 | AA90: 55917799 | AB90: =ROUND((AC90+AD90+AF90),6) -> 227.12 | AC90: =ROUND(((ES90*1)),6) -> 75.68 | AD90: =ROUND(((((ET90*1.2))-((EU90*1.2)))+AE90),6) -> 0 | AE90: =ROUND(((EU90*1.2)),6) -> 0 | AF90: =ROUND(((EV90*1.2)),6) -> 151.44 | AG90: =ROUND((AP90),6) -> 0 | AH90: =((EW90*1.2)) -> 12 | AI90: =((EX90*1.2)) -> 0 | AJ90: =(AS90) -> 0 | AK90: 201.88 | AL90: 75.68 | AM90: 0 | AN90: 0 | AO90: 126.2 | AP90: 0 | AQ90: 10 | AR90: 0 | AS90: 0 | AT90: 95 | AU90: 53 | AV90: 1.047 | AW90: 1 | AZ90: 1 | BA90: 56.35 | BB90: 1 | BC90: 9.58 | BH90: 0 | BI90: 2 | BJ90: ТСН-2001.4 Доп. 80, Сб. 10, т. 73, поз. 1 | BM90: 69 | BN90: 0 | BO90: 4.10-73-1 | BP90: 1 | BQ90: 40 | BR90: 0 | BS90: 56.35 | BT90: 1 | BU90: 1 | BV90: 1 | BW90: 1 | BX90: 1 | BZ90: 95 | CA90: 53 | CE90: 1566 | CF90: 0 | CG90: 0 | CM90: 0 | CN90: Поправка: Гл.12.Прил.8.п.8. 3_12.00.01.11.001 Наименование: При наличии напряженных и стесненных условий производства работ (стесненность, сложность складирования и транспортной логистики и т.п.) для объектов, расположенных в пределах круговой магистральной системы улиц "Садовое кольцо" города Москвы | CO90: 0 | CP90: =(P90+Q90+S90) -> 9659.87 | CQ90: =ROUND((ROUND((AC90*AW90*1),2)*BC90),2) -> 725.01 | CR90: =(ROUND((ROUND((((ET90*1.2))*AV90*1),2)*BB90),2)+ROUND((ROUND(((AE90-((EU90*1.2)))*AV90*1),2)*BS90),2)) -> 0 | CS90: =(ROUND((ROUND((((EU90*1.2))*AV90*1),2)*BS90),2)+ROUND((ROUND(((AE90-((EU90*1.2)))*AV90*1),2)*BS90),2)) -> 0 | CT90: =ROUND((ROUND((AF90*AV90*1),2)*BA90),2) -> 8934.86 | CU90: =AG90 -> 0 | CV90: =(AH90*AV90) -> 12.564 | CW90: =AI90 -> 0 | CX90: =AJ90 -> 0 | CY90: =(ROUND((((S90+ROUND((ROUND((((EU90*1.2))*AV90*1),2)*BS90),2))*AT90)/100),2)+ROUND(((ROUND((ROUND(((AE90-((EU90*1.2)))*AV90*1),2)*BS90),2)*AT90)/100),2)) -> 8488.12 | CZ90: =(ROUND((((S90+ROUND((ROUND((((EU90*1.2))*AV90*1),2)*BS90),2))*AU90)/100),2)+ROUND(((ROUND((ROUND(((AE90-((EU90*1.2)))*AV90*1),2)*BS90),2)*AU90)/100),2)) -> 4735.48 | DB90: 50 | DD90: *1 | DE90: *1,2 | DF90: *1,2 | DG90: *1,2 | DI90: *1,2 | DJ90: *1,2 | DN90: 0 | DO90: 0 | DP90: 1 | DQ90: 1 | DU90: 1013 | DV90: 1 комплект | DW90: 1 комплект | DX90: 1 | EE90: 55393701 | EF90: 40 | EG90: Монтаж оборудования | EH90: 0 | EJ90: 2 | EK90: 69 | EL90: ТСН-2001.4-10. Монтаж радиотелевизионного и электронного оборудования | EM90: ТСН-2001.4-10-2 | EO90: Поправка: Гл.12.Прил.8.п.8. 3_12.00.01.11.001 | EQ90: 0 | ER90: 201.88 | ES90: 75.68 | ET90: 0 | EU90: 0 | EV90: 126.2 | EW90: 10 | EX90: 0 | EY90: 0 | FQ90: 0 | FR90: 0 | FS90: 0 | FX90: 95 | FY90: 53 | GD90: 1 | GF90: -542777880 | GG90: 2 | GH90: 1 | GI90: 2 | GJ90: 0 | GK90: 0 | GL90: =ROUND(IF(AND(BH90=3,BI90=3,FS90<>0),P90,0),2) -> 0 | GM90: =ROUND(O90+X90+Y90,2)+GX90 -> 22883.47 | GN90: =IF(OR(BI90=0,BI90=1),GM90-GX90,0) -> 0 | GO90: =IF(BI90=2,GM90-GX90,0) -> 22883.47 | GP90: =IF(BI90=4,GM90-GX90,0) -> 0 | GR90: 0 | GS90: 3 | GT90: 0 | GV90: =ROUND((GT90),6) -> 0 | GW90: 1 | GX90: =ROUND(HC90*I90,2) -> 0 | HA90: 0 | HB90: 0 | HC90: =GV90*GW90 -> 0 | HS90: 0 | IK90: 0
A91: 17 | B91: 1 | E91: 15 | F91: КА, п.1 | G91: Устройство подачи программ вещания УППВ 1918 М1 исп. У | H91: ШТ | I91: 1 | J91: 0 | K91: 1 | O91: =ROUND(CP91,2) -> 58238.71 | P91: =ROUND((ROUND((AC91*AW91*I91),2)*BC91),2) -> 58238.71 | Q91: =(ROUND((ROUND(((ET91)*AV91*I91),2)*BB91),2)+ROUND((ROUND(((AE91-(EU91))*AV91*I91),2)*BS91),2)) -> 0 | R91: =(ROUND((ROUND(((EU91)*AV91*I91),2)*BS91),2)+ROUND((ROUND(((AE91-(EU91))*AV91*I91),2)*BS91),2)) -> 0 | S91: =ROUND((ROUND((AF91*AV91*I91),2)*BA91),2) -> 0 | T91: =ROUND(CU91*I91,2) -> 0 | U91: =CV91*I91 -> 0 | V91: =CW91*I91 -> 0 | W91: =ROUND(CX91*I91,2) -> 0 | X91: =(ROUND((((S91+ROUND((ROUND(((EU91)*AV91*I91),2)*BS91),2))*AT91)/100),2)+ROUND(((ROUND((ROUND(((AE91-(EU91))*AV91*I91),2)*BS91),2)*AT91)/100),2)) -> 0 | Y91: =(ROUND((((S91+ROUND((ROUND(((EU91)*AV91*I91),2)*BS91),2))*AU91)/100),2)+ROUND(((ROUND((ROUND(((AE91-(EU91))*AV91*I91),2)*BS91),2)*AU91)/100),2)) -> 0 | AA91: 55917797 | AB91: =ROUND((AC91+AD91+AF91),6) -> 58238.71 | AC91: =ROUND((ES91),6) -> 58238.71 | AD91: =ROUND((((ET91)-(EU91))+AE91),6) -> 0 | AE91: =ROUND((EU91),6) -> 0 | AF91: =ROUND((EV91),6) -> 0 | AG91: =ROUND((AP91),6) -> 0 | AH91: =(EW91) -> 0 | AI91: =(EX91) -> 0 | AJ91: =(AS91) -> 0 | AK91: 58238.71 | AL91: 58238.71 | AM91: 0 | AN91: 0 | AO91: 0 | AP91: 0 | AQ91: 0 | AR91: 0 | AS91: 0 | AT91: 0 | AU91: 0 | AV91: 1 | AW91: 1 | AZ91: 1 | BA91: 1 | BB91: 1 | BC91: 1 | BH91: 3 | BI91: 3 | BJ91: КА, п.1 | BM91: 400007 | BN91: 0 | BP91: 0 | BQ91: 214 | BR91: 0 | BS91: 1 | BT91: 1 | BU91: 1 | BV91: 1 | BW91: 1 | BX91: 1 | BZ91: 0 | CA91: 0 | CE91: 1566 | CF91: 0 | CG91: 0 | CM91: 0 | CO91: 0 | CP91: =(P91+Q91+S91) -> 58238.71 | CQ91: =ROUND((ROUND((AC91*AW91*1),2)*BC91),2) -> 58238.71 | CR91: =(ROUND((ROUND(((ET91)*AV91*1),2)*BB91),2)+ROUND((ROUND(((AE91-(EU91))*AV91*1),2)*BS91),2)) -> 0 | CS91: =(ROUND((ROUND(((EU91)*AV91*1),2)*BS91),2)+ROUND((ROUND(((AE91-(EU91))*AV91*1),2)*BS91),2)) -> 0 | CT91: =ROUND((ROUND((AF91*AV91*1),2)*BA91),2) -> 0 | CU91: =AG91 -> 0 | CV91: =(AH91*AV91) -> 0 | CW91: =AI91 -> 0 | CX91: =AJ91 -> 0 | CY91: =(ROUND((((S91+ROUND((ROUND(((EU91)*AV91*1),2)*BS91),2))*AT91)/100),2)+ROUND(((ROUND((ROUND(((AE91-(EU91))*AV91*1),2)*BS91),2)*AT91)/100),2)) -> 0 | CZ91: =(ROUND((((S91+ROUND((ROUND(((EU91)*AV91*1),2)*BS91),2))*AU91)/100),2)+ROUND(((ROUND((ROUND(((AE91-(EU91))*AV91*1),2)*BS91),2)*AU91)/100),2)) -> 0 | DN91: 0 | DO91: 0 | DP91: 1 | DQ91: 1 | DU91: 1013 | DV91: ШТ | DW91: ШТ | DX91: 1 | EE91: 55393630 | EF91: 214 | EG91: Оборудование, отсутствующие в СНБ | EH91: 0 | EJ91: 3 | EK91: 400007 | EL91: Оборудование, отсутствующие в СНБ | EM91: Оборуд. КА | EQ91: 16 | ER91: 0 | ES91: 58238.71 | ET91: 0 | EU91: 0 | EV91: 0 | EW91: 0 | EX91: 0 | EY91: 0 | FQ91: 0 | FR91: =P91 -> 58238.71 | FS91: 0 | FX91: 0 | FY91: 0 | GA91: [516 000 / 1,22 / 7,57] + 3% Трансп + 1,2% Заг.скл | GD91: 1 | GF91: 1695877574 | GG91: 2 | GH91: 4 | GI91: -2 | GJ91: 0 | GK91: 0 | GL91: =ROUND(IF(AND(BH91=3,BI91=3,FS91<>0),P91,0),2) -> 0 | GM91: =ROUND(O91+X91+Y91,2)+GX91 -> 58238.71 | GN91: =IF(OR(BI91=0,BI91=1),GM91-GX91,0) -> 0 | GO91: =IF(BI91=2,GM91-GX91,0) -> 0 | GP91: =IF(BI91=4,GM91-GX91,0) -> 0 | GR91: 1 | GS91: 2 | GT91: 0 | GV91: =ROUND((GT91),6) -> 0 | GW91: 1 | GX91: =ROUND(HC91*I91,2) -> 0 | HA91: 0 | HB91: 0 | HC91: =GV91*GW91 -> 0 | HE91: 3 | HF91: 1,2 | HS91: 0 | IK91: 0
A92: 17 | B92: 1 | E92: 15 | F92: КА, п.1 | G92: Устройство подачи программ вещания УППВ 1918 М1 исп. У | H92: ШТ | I92: 1 | J92: 0 | K92: 1 | O92: =ROUND(CP92,2) -> 440867.03 | P92: =ROUND((ROUND((AC92*AW92*I92),2)*BC92),2) -> 440867.03 | Q92: =(ROUND((ROUND(((ET92)*AV92*I92),2)*BB92),2)+ROUND((ROUND(((AE92-(EU92))*AV92*I92),2)*BS92),2)) -> 0 | R92: =(ROUND((ROUND(((EU92)*AV92*I92),2)*BS92),2)+ROUND((ROUND(((AE92-(EU92))*AV92*I92),2)*BS92),2)) -> 0 | S92: =ROUND((ROUND((AF92*AV92*I92),2)*BA92),2) -> 0 | T92: =ROUND(CU92*I92,2) -> 0 | U92: =CV92*I92 -> 0 | V92: =CW92*I92 -> 0 | W92: =ROUND(CX92*I92,2) -> 0 | X92: =(ROUND((((S92+ROUND((ROUND(((EU92)*AV92*I92),2)*BS92),2))*AT92)/100),2)+ROUND(((ROUND((ROUND(((AE92-(EU92))*AV92*I92),2)*BS92),2)*AT92)/100),2)) -> 0 | Y92: =(ROUND((((S92+ROUND((ROUND(((EU92)*AV92*I92),2)*BS92),2))*AU92)/100),2)+ROUND(((ROUND((ROUND(((AE92-(EU92))*AV92*I92),2)*BS92),2)*AU92)/100),2)) -> 0 | AA92: 55917799 | AB92: =ROUND((AC92+AD92+AF92),6) -> 58238.71 | AC92: =ROUND((ES92),6) -> 58238.71 | AD92: =ROUND((((ET92)-(EU92))+AE92),6) -> 0 | AE92: =ROUND((EU92),6) -> 0 | AF92: =ROUND((EV92),6) -> 0 | AG92: =ROUND((AP92),6) -> 0 | AH92: =(EW92) -> 0 | AI92: =(EX92) -> 0 | AJ92: =(AS92) -> 0 | AK92: 58238.71 | AL92: 58238.71 | AM92: 0 | AN92: 0 | AO92: 0 | AP92: 0 | AQ92: 0 | AR92: 0 | AS92: 0 | AT92: 0 | AU92: 0 | AV92: 1 | AW92: 1 | AZ92: 1 | BA92: 1 | BB92: 1 | BC92: 7.57 | BH92: 3 | BI92: 3 | BJ92: КА, п.1 | BM92: 400007 | BN92: 0 | BP92: 0 | BQ92: 214 | BR92: 0 | BS92: 1 | BT92: 1 | BU92: 1 | BV92: 1 | BW92: 1 | BX92: 1 | BZ92: 0 | CA92: 0 | CE92: 1566 | CF92: 0 | CG92: 0 | CM92: 0 | CO92: 0 | CP92: =(P92+Q92+S92) -> 440867.03 | CQ92: =ROUND((ROUND((AC92*AW92*1),2)*BC92),2) -> 440867.03 | CR92: =(ROUND((ROUND(((ET92)*AV92*1),2)*BB92),2)+ROUND((ROUND(((AE92-(EU92))*AV92*1),2)*BS92),2)) -> 0 | CS92: =(ROUND((ROUND(((EU92)*AV92*1),2)*BS92),2)+ROUND((ROUND(((AE92-(EU92))*AV92*1),2)*BS92),2)) -> 0 | CT92: =ROUND((ROUND((AF92*AV92*1),2)*BA92),2) -> 0 | CU92: =AG92 -> 0 | CV92: =(AH92*AV92) -> 0 | CW92: =AI92 -> 0 | CX92: =AJ92 -> 0 | CY92: =(ROUND((((S92+ROUND((ROUND(((EU92)*AV92*1),2)*BS92),2))*AT92)/100),2)+ROUND(((ROUND((ROUND(((AE92-(EU92))*AV92*1),2)*BS92),2)*AT92)/100),2)) -> 0 | CZ92: =(ROUND((((S92+ROUND((ROUND(((EU92)*AV92*1),2)*BS92),2))*AU92)/100),2)+ROUND(((ROUND((ROUND(((AE92-(EU92))*AV92*1),2)*BS92),2)*AU92)/100),2)) -> 0 | DN92: 0 | DO92: 0 | DP92: 1 | DQ92: 1 | DU92: 1013 | DV92: ШТ | DW92: ШТ | DX92: 1 | EE92: 55393630 | EF92: 214 | EG92: Оборудование, отсутствующие в СНБ | EH92: 0 | EJ92: 3 | EK92: 400007 | EL92: Оборудование, отсутствующие в СНБ | EM92: Оборуд. КА | EQ92: 16 | ER92: 0 | ES92: 58238.71 | ET92: 0 | EU92: 0 | EV92: 0 | EW92: 0 | EX92: 0 | EY92: 0 | EZ92: 5 | FC92: 1 | FD92: 18 | FF92: 516000 | FQ92: 0 | FR92: =P92 -> 440867.03 | FS92: 0 | FX92: 0 | FY92: 0 | GA92: [516 000 / 1,22 / 7,57] + 3% Трансп + 1,2% Заг.скл | GD92: 1 | GF92: 1695877574 | GG92: 2 | GH92: 3 | GI92: 5 | GJ92: 0 | GK92: 0 | GL92: =ROUND(IF(AND(BH92=3,BI92=3,FS92<>0),P92,0),2) -> 0 | GM92: =ROUND(O92+X92+Y92,2)+GX92 -> 440867.03 | GN92: =IF(OR(BI92=0,BI92=1),GM92-GX92,0) -> 0 | GO92: =IF(BI92=2,GM92-GX92,0) -> 0 | GP92: =IF(BI92=4,GM92-GX92,0) -> 0 | GR92: 1 | GS92: 1 | GT92: 0 | GV92: =ROUND((GT92),6) -> 0 | GW92: 1 | GX92: =ROUND(HC92*I92,2) -> 0 | HA92: 0 | HB92: 0 | HC92: =GV92*GW92 -> 0 | HE92: 3 | HF92: 1,2 | HS92: 0 | IK92: 0
A93: 17 | B93: 1 | C93: =ROW(SmtRes!A180) -> 180 | D93: =ROW(EtalonRes!A203) -> 203 | E93: 16 | F93: 4.10-32-4 | G93: Монтаж платы дополнительной, устанавливаемой на готовом месте стойки | H93: 1 ШТ. | I93: 1 | J93: 0 | K93: 1 | O93: =ROUND(CP93,2) -> 41.05 | P93: =ROUND((ROUND((AC93*AW93*I93),2)*BC93),2) -> 0 | Q93: =(ROUND((ROUND((((ET93*1.2))*AV93*I93),2)*BB93),2)+ROUND((ROUND(((AE93-((EU93*1.2)))*AV93*I93),2)*BS93),2)) -> 11.55 | R93: =(ROUND((ROUND((((EU93*1.2))*AV93*I93),2)*BS93),2)+ROUND((ROUND(((AE93-((EU93*1.2)))*AV93*I93),2)*BS93),2)) -> 1.27 | S93: =ROUND((ROUND((AF93*AV93*I93),2)*BA93),2) -> 29.5 | T93: =ROUND(CU93*I93,2) -> 0 | U93: =CV93*I93 -> 2.63844 | V93: =CW93*I93 -> 0 | W93: =ROUND(CX93*I93,2) -> 0 | X93: =(ROUND((((S93+ROUND((ROUND((((EU93*1.2))*AV93*I93),2)*BS93),2))*AT93)/100),2)+ROUND(((ROUND((ROUND(((AE93-((EU93*1.2)))*AV93*I93),2)*BS93),2)*AT93)/100),2)) -> 27.69 | Y93: =(ROUND((((S93+ROUND((ROUND((((EU93*1.2))*AV93*I93),2)*BS93),2))*AU93)/100),2)+ROUND(((ROUND((ROUND(((AE93-((EU93*1.2)))*AV93*I93),2)*BS93),2)*AU93)/100),2)) -> 14.15 | AA93: 55917797 | AB93: =ROUND((AC93+AD93+AF93),6) -> 39.204 | AC93: =ROUND(((ES93*1)),6) -> 0 | AD93: =ROUND(((((ET93*1.2))-((EU93*1.2)))+AE93),6) -> 11.028 | AE93: =ROUND(((EU93*1.2)),6) -> 1.212 | AF93: =ROUND(((EV93*1.2)),6) -> 28.176 | AG93: =ROUND((AP93),6) -> 0 | AH93: =((EW93*1.2)) -> 2.52 | AI93: =((EX93*1.2)) -> 0 | AJ93: =(AS93) -> 0 | AK93: 32.67 | AL93: 0 | AM93: 9.19 | AN93: 1.01 | AO93: 23.48 | AP93: 0 | AQ93: 2.1 | AR93: 0 | AS93: 0 | AT93: 90 | AU93: 46 | AV93: 1.047 | AW93: 1 | AZ93: 1 | BA93: 1 | BB93: 1 | BC93: 1 | BH93: 0 | BI93: 2 | BJ93: ТСН-2001.4 Доп. 68, Сб. 10, т. 32, поз. 4 | BM93: 68 | BN93: 0 | BO93: 4.10-32-4 | BP93: 1 | BQ93: 40 | BR93: 0 | BS93: 1 | BT93: 1 | BU93: 1 | BV93: 1 | BW93: 1 | BX93: 1 | BZ93: 90 | CA93: 46 | CE93: 1566 | CF93: 0 | CG93: 0 | CM93: 0 | CN93: Поправка: Гл.12.Прил.8.п.8. 3_12.00.01.11.001 Наименование: При наличии напряженных и стесненных условий производства работ (стесненность, сложность складирования и транспортной логистики и т.п.) для объектов, расположенных в пределах круговой магистральной системы улиц "Садовое кольцо" города Москвы | CO93: 0 | CP93: =(P93+Q93+S93) -> 41.05 | CQ93: =ROUND((ROUND((AC93*AW93*1),2)*BC93),2) -> 0 | CR93: =(ROUND((ROUND((((ET93*1.2))*AV93*1),2)*BB93),2)+ROUND((ROUND(((AE93-((EU93*1.2)))*AV93*1),2)*BS93),2)) -> 11.55 | CS93: =(ROUND((ROUND((((EU93*1.2))*AV93*1),2)*BS93),2)+ROUND((ROUND(((AE93-((EU93*1.2)))*AV93*1),2)*BS93),2)) -> 1.27 | CT93: =ROUND((ROUND((AF93*AV93*1),2)*BA93),2) -> 29.5 | CU93: =AG93 -> 0 | CV93: =(AH93*AV93) -> 2.63844 | CW93: =AI93 -> 0 | CX93: =AJ93 -> 0 | CY93: =(ROUND((((S93+ROUND((ROUND((((EU93*1.2))*AV93*1),2)*BS93),2))*AT93)/100),2)+ROUND(((ROUND((ROUND(((AE93-((EU93*1.2)))*AV93*1),2)*BS93),2)*AT93)/100),2)) -> 27.69 | CZ93: =(ROUND((((S93+ROUND((ROUND((((EU93*1.2))*AV93*1),2)*BS93),2))*AU93)/100),2)+ROUND(((ROUND((ROUND(((AE93-((EU93*1.2)))*AV93*1),2)*BS93),2)*AU93)/100),2)) -> 14.15 | DB93: 51 | DD93: *1 | DE93: *1,2 | DF93: *1,2 | DG93: *1,2 | DI93: *1,2 | DJ93: *1,2 | DN93: 0 | DO93: 0 | DP93: 1 | DQ93: 1 | DU93: 1013 | DV93: 1 ШТ. | DW93: 1 ШТ. | DX93: 1 | EE93: 55393700 | EF93: 40 | EG93: Монтаж оборудования | EH93: 0 | EJ93: 2 | EK93: 68 | EL93: ТСН-2001.4-10. Прокладка и монтаж сетей связи | EM93: ТСН-2001.4-10-1 | EO93: Поправка: Гл.12.Прил.8.п.8. 3_12.00.01.11.001 | EQ93: 0 | ER93: 32.67 | ES93: 0 | ET93: 9.19 | EU93: 1.01 | EV93: 23.48 | EW93: 2.1 | EX93: 0 | EY93: 0 | FQ93: 0 | FR93: 0 | FS93: 0 | FX93: 90 | FY93: 46 | GD93: 1 | GF93: 1604197288 | GG93: 2 | GH93: 1 | GI93: 2 | GJ93: 0 | GK93: 0 | GL93: =ROUND(IF(AND(BH93=3,BI93=3,FS93<>0),P93,0),2) -> 0 | GM93: =ROUND(O93+X93+Y93,2)+GX93 -> 82.89 | GN93: =IF(OR(BI93=0,BI93=1),GM93-GX93,0) -> 0 | GO93: =IF(BI93=2,GM93-GX93,0) -> 82.89 | GP93: =IF(BI93=4,GM93-GX93,0) -> 0 | GR93: 0 | GS93: 3 | GT93: 0 | GV93: =ROUND((GT93),6) -> 0 | GW93: 1 | GX93: =ROUND(HC93*I93,2) -> 0 | HA93: 0 | HB93: 0 | HC93: =GV93*GW93 -> 0 | HS93: 0 | IK93: 0
A94: 17 | B94: 1 | C94: =ROW(SmtRes!A182) -> 182 | D94: =ROW(EtalonRes!A206) -> 206 | E94: 16 | F94: 4.10-32-4 | G94: Монтаж платы дополнительной, устанавливаемой на готовом месте стойки | H94: 1 ШТ. | I94: 1 | J94: 0 | K94: 1 | O94: =ROUND(CP94,2) -> 1848.86 | P94: =ROUND((ROUND((AC94*AW94*I94),2)*BC94),2) -> 0 | Q94: =(ROUND((ROUND((((ET94*1.2))*AV94*I94),2)*BB94),2)+ROUND((ROUND(((AE94-((EU94*1.2)))*AV94*I94),2)*BS94),2)) -> 186.53 | R94: =(ROUND((ROUND((((EU94*1.2))*AV94*I94),2)*BS94),2)+ROUND((ROUND(((AE94-((EU94*1.2)))*AV94*I94),2)*BS94),2)) -> 71.56 | S94: =ROUND((ROUND((AF94*AV94*I94),2)*BA94),2) -> 1662.33 | T94: =ROUND(CU94*I94,2) -> 0 | U94: =CV94*I94 -> 2.63844 | V94: =CW94*I94 -> 0 | W94: =ROUND(CX94*I94,2) -> 0 | X94: =(ROUND((((S94+ROUND((ROUND((((EU94*1.2))*AV94*I94),2)*BS94),2))*AT94)/100),2)+ROUND(((ROUND((ROUND(((AE94-((EU94*1.2)))*AV94*I94),2)*BS94),2)*AT94)/100),2)) -> 1560.5 | Y94: =(ROUND((((S94+ROUND((ROUND((((EU94*1.2))*AV94*I94),2)*BS94),2))*AU94)/100),2)+ROUND(((ROUND((ROUND(((AE94-((EU94*1.2)))*AV94*I94),2)*BS94),2)*AU94)/100),2)) -> 797.59 | AA94: 55917799 | AB94: =ROUND((AC94+AD94+AF94),6) -> 39.204 | AC94: =ROUND(((ES94*1)),6) -> 0 | AD94: =ROUND(((((ET94*1.2))-((EU94*1.2)))+AE94),6) -> 11.028 | AE94: =ROUND(((EU94*1.2)),6) -> 1.212 | AF94: =ROUND(((EV94*1.2)),6) -> 28.176 | AG94: =ROUND((AP94),6) -> 0 | AH94: =((EW94*1.2)) -> 2.52 | AI94: =((EX94*1.2)) -> 0 | AJ94: =(AS94) -> 0 | AK94: 32.67 | AL94: 0 | AM94: 9.19 | AN94: 1.01 | AO94: 23.48 | AP94: 0 | AQ94: 2.1 | AR94: 0 | AS94: 0 | AT94: 90 | AU94: 46 | AV94: 1.047 | AW94: 1 | AZ94: 1 | BA94: 56.35 | BB94: 16.15 | BC94: 1 | BH94: 0 | BI94: 2 | BJ94: ТСН-2001.4 Доп. 68, Сб. 10, т. 32, поз. 4 | BM94: 68 | BN94: 0 | BO94: 4.10-32-4 | BP94: 1 | BQ94: 40 | BR94: 0 | BS94: 56.35 | BT94: 1 | BU94: 1 | BV94: 1 | BW94: 1 | BX94: 1 | BZ94: 90 | CA94: 46 | CE94: 1566 | CF94: 0 | CG94: 0 | CM94: 0 | CN94: Поправка: Гл.12.Прил.8.п.8. 3_12.00.01.11.001 Наименование: При наличии напряженных и стесненных условий производства работ (стесненность, сложность складирования и транспортной логистики и т.п.) для объектов, расположенных в пределах круговой магистральной системы улиц "Садовое кольцо" города Москвы | CO94: 0 | CP94: =(P94+Q94+S94) -> 1848.86 | CQ94: =ROUND((ROUND((AC94*AW94*1),2)*BC94),2) -> 0 | CR94: =(ROUND((ROUND((((ET94*1.2))*AV94*1),2)*BB94),2)+ROUND((ROUND(((AE94-((EU94*1.2)))*AV94*1),2)*BS94),2)) -> 186.53 | CS94: =(ROUND((ROUND((((EU94*1.2))*AV94*1),2)*BS94),2)+ROUND((ROUND(((AE94-((EU94*1.2)))*AV94*1),2)*BS94),2)) -> 71.56 | CT94: =ROUND((ROUND((AF94*AV94*1),2)*BA94),2) -> 1662.33 | CU94: =AG94 -> 0 | CV94: =(AH94*AV94) -> 2.63844 | CW94: =AI94 -> 0 | CX94: =AJ94 -> 0 | CY94: =(ROUND((((S94+ROUND((ROUND((((EU94*1.2))*AV94*1),2)*BS94),2))*AT94)/100),2)+ROUND(((ROUND((ROUND(((AE94-((EU94*1.2)))*AV94*1),2)*BS94),2)*AT94)/100),2)) -> 1560.5 | CZ94: =(ROUND((((S94+ROUND((ROUND((((EU94*1.2))*AV94*1),2)*BS94),2))*AU94)/100),2)+ROUND(((ROUND((ROUND(((AE94-((EU94*1.2)))*AV94*1),2)*BS94),2)*AU94)/100),2)) -> 797.59 | DB94: 52 | DD94: *1 | DE94: *1,2 | DF94: *1,2 | DG94: *1,2 | DI94: *1,2 | DJ94: *1,2 | DN94: 0 | DO94: 0 | DP94: 1 | DQ94: 1 | DU94: 1013 | DV94: 1 ШТ. | DW94: 1 ШТ. | DX94: 1 | EE94: 55393700 | EF94: 40 | EG94: Монтаж оборудования | EH94: 0 | EJ94: 2 | EK94: 68 | EL94: ТСН-2001.4-10. Прокладка и монтаж сетей связи | EM94: ТСН-2001.4-10-1 | EO94: Поправка: Гл.12.Прил.8.п.8. 3_12.00.01.11.001 | EQ94: 0 | ER94: 32.67 | ES94: 0 | ET94: 9.19 | EU94: 1.01 | EV94: 23.48 | EW94: 2.1 | EX94: 0 | EY94: 0 | FQ94: 0 | FR94: 0 | FS94: 0 | FX94: 90 | FY94: 46 | GD94: 1 | GF94: 1604197288 | GG94: 2 | GH94: 1 | GI94: 2 | GJ94: 0 | GK94: 0 | GL94: =ROUND(IF(AND(BH94=3,BI94=3,FS94<>0),P94,0),2) -> 0 | GM94: =ROUND(O94+X94+Y94,2)+GX94 -> 4206.95 | GN94: =IF(OR(BI94=0,BI94=1),GM94-GX94,0) -> 0 | GO94: =IF(BI94=2,GM94-GX94,0) -> 4206.95 | GP94: =IF(BI94=4,GM94-GX94,0) -> 0 | GR94: 0 | GS94: 3 | GT94: 0 | GV94: =ROUND((GT94),6) -> 0 | GW94: 1 | GX94: =ROUND(HC94*I94,2) -> 0 | HA94: 0 | HB94: 0 | HC94: =GV94*GW94 -> 0 | HS94: 0 | IK94: 0
A95: 17 | B95: 1 | E95: 17 | F95: КА, п.2 | G95: Модуль для приема интернет вещания радиостанции "Радио Москвы" для установки в БИП-03 | H95: ШТ | I95: 1 | J95: 0 | K95: 1 | O95: =ROUND(CP95,2) -> 3453.69 | P95: =ROUND((ROUND((AC95*AW95*I95),2)*BC95),2) -> 3453.69 | Q95: =(ROUND((ROUND(((ET95)*AV95*I95),2)*BB95),2)+ROUND((ROUND(((AE95-(EU95))*AV95*I95),2)*BS95),2)) -> 0 | R95: =(ROUND((ROUND(((EU95)*AV95*I95),2)*BS95),2)+ROUND((ROUND(((AE95-(EU95))*AV95*I95),2)*BS95),2)) -> 0 | S95: =ROUND((ROUND((AF95*AV95*I95),2)*BA95),2) -> 0 | T95: =ROUND(CU95*I95,2) -> 0 | U95: =CV95*I95 -> 0 | V95: =CW95*I95 -> 0 | W95: =ROUND(CX95*I95,2) -> 0 | X95: =(ROUND((((S95+ROUND((ROUND(((EU95)*AV95*I95),2)*BS95),2))*AT95)/100),2)+ROUND(((ROUND((ROUND(((AE95-(EU95))*AV95*I95),2)*BS95),2)*AT95)/100),2)) -> 0 | Y95: =(ROUND((((S95+ROUND((ROUND(((EU95)*AV95*I95),2)*BS95),2))*AU95)/100),2)+ROUND(((ROUND((ROUND(((AE95-(EU95))*AV95*I95),2)*BS95),2)*AU95)/100),2)) -> 0 | AA95: 55917797 | AB95: =ROUND((AC95+AD95+AF95),6) -> 3453.69 | AC95: =ROUND((ES95),6) -> 3453.69 | AD95: =ROUND((((ET95)-(EU95))+AE95),6) -> 0 | AE95: =ROUND((EU95),6) -> 0 | AF95: =ROUND((EV95),6) -> 0 | AG95: =ROUND((AP95),6) -> 0 | AH95: =(EW95) -> 0 | AI95: =(EX95) -> 0 | AJ95: =(AS95) -> 0 | AK95: 3453.69 | AL95: 3453.69 | AM95: 0 | AN95: 0 | AO95: 0 | AP95: 0 | AQ95: 0 | AR95: 0 | AS95: 0 | AT95: 0 | AU95: 0 | AV95: 1 | AW95: 1 | AZ95: 1 | BA95: 1 | BB95: 1 | BC95: 1 | BH95: 3 | BI95: 3 | BJ95: КА, п.2 | BM95: 400007 | BN95: 0 | BP95: 0 | BQ95: 214 | BR95: 0 | BS95: 1 | BT95: 1 | BU95: 1 | BV95: 1 | BW95: 1 | BX95: 1 | BZ95: 0 | CA95: 0 | CE95: 1566 | CF95: 0 | CG95: 0 | CM95: 0 | CO95: 0 | CP95: =(P95+Q95+S95) -> 3453.69 | CQ95: =ROUND((ROUND((AC95*AW95*1),2)*BC95),2) -> 3453.69 | CR95: =(ROUND((ROUND(((ET95)*AV95*1),2)*BB95),2)+ROUND((ROUND(((AE95-(EU95))*AV95*1),2)*BS95),2)) -> 0 | CS95: =(ROUND((ROUND(((EU95)*AV95*1),2)*BS95),2)+ROUND((ROUND(((AE95-(EU95))*AV95*1),2)*BS95),2)) -> 0 | CT95: =ROUND((ROUND((AF95*AV95*1),2)*BA95),2) -> 0 | CU95: =AG95 -> 0 | CV95: =(AH95*AV95) -> 0 | CW95: =AI95 -> 0 | CX95: =AJ95 -> 0 | CY95: =(ROUND((((S95+ROUND((ROUND(((EU95)*AV95*1),2)*BS95),2))*AT95)/100),2)+ROUND(((ROUND((ROUND(((AE95-(EU95))*AV95*1),2)*BS95),2)*AT95)/100),2)) -> 0 | CZ95: =(ROUND((((S95+ROUND((ROUND(((EU95)*AV95*1),2)*BS95),2))*AU95)/100),2)+ROUND(((ROUND((ROUND(((AE95-(EU95))*AV95*1),2)*BS95),2)*AU95)/100),2)) -> 0 | DN95: 0 | DO95: 0 | DP95: 1 | DQ95: 1 | DU95: 1013 | DV95: ШТ | DW95: ШТ | DX95: 1 | EE95: 55393630 | EF95: 214 | EG95: Оборудование, отсутствующие в СНБ | EH95: 0 | EJ95: 3 | EK95: 400007 | EL95: Оборудование, отсутствующие в СНБ | EM95: Оборуд. КА | EQ95: 16 | ER95: 0 | ES95: 3453.69 | ET95: 0 | EU95: 0 | EV95: 0 | EW95: 0 | EX95: 0 | EY95: 0 | FQ95: 0 | FR95: =P95 -> 3453.69 | FS95: 0 | FX95: 0 | FY95: 0 | GA95: [30 600 / 1,22 / 7,57] + 3% Трансп + 1,2% Заг.скл | GD95: 1 | GF95: 1552324280 | GG95: 2 | GH95: 4 | GI95: -2 | GJ95: 0 | GK95: 0 | GL95: =ROUND(IF(AND(BH95=3,BI95=3,FS95<>0),P95,0),2) -> 0 | GM95: =ROUND(O95+X95+Y95,2)+GX95 -> 3453.69 | GN95: =IF(OR(BI95=0,BI95=1),GM95-GX95,0) -> 0 | GO95: =IF(BI95=2,GM95-GX95,0) -> 0 | GP95: =IF(BI95=4,GM95-GX95,0) -> 0 | GR95: 1 | GS95: 2 | GT95: 0 | GV95: =ROUND((GT95),6) -> 0 | GW95: 1 | GX95: =ROUND(HC95*I95,2) -> 0 | HA95: 0 | HB95: 0 | HC95: =GV95*GW95 -> 0 | HE95: 3 | HF95: 1,2 | HS95: 0 | IK95: 0
A96: 17 | B96: 1 | E96: 17 | F96: КА, п.2 | G96: Модуль для приема интернет вещания радиостанции "Радио Москвы" для установки в БИП-03 | H96: ШТ | I96: 1 | J96: 0 | K96: 1 | O96: =ROUND(CP96,2) -> 26144.43 | P96: =ROUND((ROUND((AC96*AW96*I96),2)*BC96),2) -> 26144.43 | Q96: =(ROUND((ROUND(((ET96)*AV96*I96),2)*BB96),2)+ROUND((ROUND(((AE96-(EU96))*AV96*I96),2)*BS96),2)) -> 0 | R96: =(ROUND((ROUND(((EU96)*AV96*I96),2)*BS96),2)+ROUND((ROUND(((AE96-(EU96))*AV96*I96),2)*BS96),2)) -> 0 | S96: =ROUND((ROUND((AF96*AV96*I96),2)*BA96),2) -> 0 | T96: =ROUND(CU96*I96,2) -> 0 | U96: =CV96*I96 -> 0 | V96: =CW96*I96 -> 0 | W96: =ROUND(CX96*I96,2) -> 0 | X96: =(ROUND((((S96+ROUND((ROUND(((EU96)*AV96*I96),2)*BS96),2))*AT96)/100),2)+ROUND(((ROUND((ROUND(((AE96-(EU96))*AV96*I96),2)*BS96),2)*AT96)/100),2)) -> 0 | Y96: =(ROUND((((S96+ROUND((ROUND(((EU96)*AV96*I96),2)*BS96),2))*AU96)/100),2)+ROUND(((ROUND((ROUND(((AE96-(EU96))*AV96*I96),2)*BS96),2)*AU96)/100),2)) -> 0 | AA96: 55917799 | AB96: =ROUND((AC96+AD96+AF96),6) -> 3453.69 | AC96: =ROUND((ES96),6) -> 3453.69 | AD96: =ROUND((((ET96)-(EU96))+AE96),6) -> 0 | AE96: =ROUND((EU96),6) -> 0 | AF96: =ROUND((EV96),6) -> 0 | AG96: =ROUND((AP96),6) -> 0 | AH96: =(EW96) -> 0 | AI96: =(EX96) -> 0 | AJ96: =(AS96) -> 0 | AK96: 3453.69 | AL96: 3453.69 | AM96: 0 | AN96: 0 | AO96: 0 | AP96: 0 | AQ96: 0 | AR96: 0 | AS96: 0 | AT96: 0 | AU96: 0 | AV96: 1 | AW96: 1 | AZ96: 1 | BA96: 1 | BB96: 1 | BC96: 7.57 | BH96: 3 | BI96: 3 | BJ96: КА, п.2 | BM96: 400007 | BN96: 0 | BP96: 0 | BQ96: 214 | BR96: 0 | BS96: 1 | BT96: 1 | BU96: 1 | BV96: 1 | BW96: 1 | BX96: 1 | BZ96: 0 | CA96: 0 | CE96: 1566 | CF96: 0 | CG96: 0 | CM96: 0 | CO96: 0 | CP96: =(P96+Q96+S96) -> 26144.43 | CQ96: =ROUND((ROUND((AC96*AW96*1),2)*BC96),2) -> 26144.43 | CR96: =(ROUND((ROUND(((ET96)*AV96*1),2)*BB96),2)+ROUND((ROUND(((AE96-(EU96))*AV96*1),2)*BS96),2)) -> 0 | CS96: =(ROUND((ROUND(((EU96)*AV96*1),2)*BS96),2)+ROUND((ROUND(((AE96-(EU96))*AV96*1),2)*BS96),2)) -> 0 | CT96: =ROUND((ROUND((AF96*AV96*1),2)*BA96),2) -> 0 | CU96: =AG96 -> 0 | CV96: =(AH96*AV96) -> 0 | CW96: =AI96 -> 0 | CX96: =AJ96 -> 0 | CY96: =(ROUND((((S96+ROUND((ROUND(((EU96)*AV96*1),2)*BS96),2))*AT96)/100),2)+ROUND(((ROUND((ROUND(((AE96-(EU96))*AV96*1),2)*BS96),2)*AT96)/100),2)) -> 0 | CZ96: =(ROUND((((S96+ROUND((ROUND(((EU96)*AV96*1),2)*BS96),2))*AU96)/100),2)+ROUND(((ROUND((ROUND(((AE96-(EU96))*AV96*1),2)*BS96),2)*AU96)/100),2)) -> 0 | DN96: 0 | DO96: 0 | DP96: 1 | DQ96: 1 | DU96: 1013 | DV96: ШТ | DW96: ШТ | DX96: 1 | EE96: 55393630 | EF96: 214 | EG96: Оборудование, отсутствующие в СНБ | EH96: 0 | EJ96: 3 | EK96: 400007 | EL96: Оборудование, отсутствующие в СНБ | EM96: Оборуд. КА | EQ96: 16 | ER96: 0 | ES96: 3453.69 | ET96: 0 | EU96: 0 | EV96: 0 | EW96: 0 | EX96: 0 | EY96: 0 | EZ96: 5 | FC96: 1 | FD96: 18 | FF96: 30600 | FQ96: 0 | FR96: =P96 -> 26144.43 | FS96: 0 | FX96: 0 | FY96: 0 | GA96: [30 600 / 1,22 / 7,57] + 3% Трансп + 1,2% Заг.скл | GD96: 1 | GF96: 1552324280 | GG96: 2 | GH96: 3 | GI96: 5 | GJ96: 0 | GK96: 0 | GL96: =ROUND(IF(AND(BH96=3,BI96=3,FS96<>0),P96,0),2) -> 0 | GM96: =ROUND(O96+X96+Y96,2)+GX96 -> 26144.43 | GN96: =IF(OR(BI96=0,BI96=1),GM96-GX96,0) -> 0 | GO96: =IF(BI96=2,GM96-GX96,0) -> 0 | GP96: =IF(BI96=4,GM96-GX96,0) -> 0 | GR96: 1 | GS96: 1 | GT96: 0 | GV96: =ROUND((GT96),6) -> 0 | GW96: 1 | GX96: =ROUND(HC96*I96,2) -> 0 | HA96: 0 | HB96: 0 | HC96: =GV96*GW96 -> 0 | HE96: 3 | HF96: 1,2 | HS96: 0 | IK96: 0
A97: 17 | B97: 1 | C97: =ROW(SmtRes!A184) -> 184 | D97: =ROW(EtalonRes!A208) -> 208 | E97: 18 | F97: 4.10-134-4 | G97: Монтаж антенны коллективной для приема ТВ на антенной опоре высотой до 9 м с одним ярусом оттяжек | H97: 1 антенна | I97: 1 | J97: 0 | K97: 1 | O97: =ROUND(CP97,2) -> 99.7 | P97: =ROUND((ROUND((AC97*AW97*I97),2)*BC97),2) -> 0.37 | Q97: =(ROUND((ROUND((((ET97*1.2))*AV97*I97),2)*BB97),2)+ROUND((ROUND(((AE97-((EU97*1.2)))*AV97*I97),2)*BS97),2)) -> 0 | R97: =(ROUND((ROUND((((EU97*1.2))*AV97*I97),2)*BS97),2)+ROUND((ROUND(((AE97-((EU97*1.2)))*AV97*I97),2)*BS97),2)) -> 0 | S97: =ROUND((ROUND((AF97*AV97*I97),2)*BA97),2) -> 99.33 | T97: =ROUND(CU97*I97,2) -> 0 | U97: =CV97*I97 -> 7.004628 | V97: =CW97*I97 -> 0 | W97: =ROUND(CX97*I97,2) -> 0 | X97: =(ROUND((((S97+ROUND((ROUND((((EU97*1.2))*AV97*I97),2)*BS97),2))*AT97)/100),2)+ROUND(((ROUND((ROUND(((AE97-((EU97*1.2)))*AV97*I97),2)*BS97),2)*AT97)/100),2)) -> 94.36 | Y97: =(ROUND((((S97+ROUND((ROUND((((EU97*1.2))*AV97*I97),2)*BS97),2))*AU97)/100),2)+ROUND(((ROUND((ROUND(((AE97-((EU97*1.2)))*AV97*I97),2)*BS97),2)*AU97)/100),2)) -> 52.64 | AA97: 55917797 | AB97: =ROUND((AC97+AD97+AF97),6) -> 91.75 | AC97: =ROUND(((ES97*1)),6) -> 0.37 | AD97: =ROUND(((((ET97*1.2))-((EU97*1.2)))+AE97),6) -> 0 | AE97: =ROUND(((EU97*1.2)),6) -> 0 | AF97: =ROUND(((EV97*1.2)),6) -> 91.38 | AG97: =ROUND((AP97),6) -> 0 | AH97: =((EW97*1.2)) -> 6.444 | AI97: =((EX97*1.2)) -> 0 | AJ97: =(AS97) -> 0 | AK97: 76.52 | AL97: 0.37 | AM97: 0 | AN97: 0 | AO97: 76.15 | AP97: 0 | AQ97: 5.37 | AR97: 0 | AS97: 0 | AT97: 95 | AU97: 53 | AV97: 1.087 | AW97: 1 | AZ97: 1 | BA97: 1 | BB97: 1 | BC97: 1 | BH97: 0 | BI97: 2 | BJ97: ТСН-2001.4 Доп. 81, Сб. 10, т. 134, поз. 4 | BM97: 69 | BN97: 0 | BO97: 4.10-134-4 | BP97: 1 | BQ97: 40 | BR97: 0 | BS97: 1 | BT97: 1 | BU97: 1 | BV97: 1 | BW97: 1 | BX97: 1 | BZ97: 95 | CA97: 53 | CE97: 1566 | CF97: 0 | CG97: 0 | CM97: 0 | CN97: Поправка: Гл.12.Прил.8.п.8. 3_12.00.01.11.001 Наименование: При наличии напряженных и стесненных условий производства работ (стесненность, сложность складирования и транспортной логистики и т.п.) для объектов, расположенных в пределах круговой магистральной системы улиц "Садовое кольцо" города Москвы | CO97: 0 | CP97: =(P97+Q97+S97) -> 99.7 | CQ97: =ROUND((ROUND((AC97*AW97*1),2)*BC97),2) -> 0.37 | CR97: =(ROUND((ROUND((((ET97*1.2))*AV97*1),2)*BB97),2)+ROUND((ROUND(((AE97-((EU97*1.2)))*AV97*1),2)*BS97),2)) -> 0 | CS97: =(ROUND((ROUND((((EU97*1.2))*AV97*1),2)*BS97),2)+ROUND((ROUND(((AE97-((EU97*1.2)))*AV97*1),2)*BS97),2)) -> 0 | CT97: =ROUND((ROUND((AF97*AV97*1),2)*BA97),2) -> 99.33 | CU97: =AG97 -> 0 | CV97: =(AH97*AV97) -> 7.004628 | CW97: =AI97 -> 0 | CX97: =AJ97 -> 0 | CY97: =(ROUND((((S97+ROUND((ROUND((((EU97*1.2))*AV97*1),2)*BS97),2))*AT97)/100),2)+ROUND(((ROUND((ROUND(((AE97-((EU97*1.2)))*AV97*1),2)*BS97),2)*AT97)/100),2)) -> 94.36 | CZ97: =(ROUND((((S97+ROUND((ROUND((((EU97*1.2))*AV97*1),2)*BS97),2))*AU97)/100),2)+ROUND(((ROUND((ROUND(((AE97-((EU97*1.2)))*AV97*1),2)*BS97),2)*AU97)/100),2)) -> 52.64 | DB97: 53 | DD97: *1 | DE97: *1,2 | DF97: *1,2 | DG97: *1,2 | DI97: *1,2 | DJ97: *1,2 | DN97: 0 | DO97: 0 | DP97: 1 | DQ97: 1 | DU97: 1013 | DV97: 1 антенна | DW97: 1 антенна | DX97: 1 | EE97: 55393701 | EF97: 40 | EG97: Монтаж оборудования | EH97: 0 | EJ97: 2 | EK97: 69 | EL97: ТСН-2001.4-10. Монтаж радиотелевизионного и электронного оборудования | EM97: ТСН-2001.4-10-2 | EO97: Поправка: Гл.12.Прил.8.п.8. 3_12.00.01.11.001 | EQ97: 0 | ER97: 76.52 | ES97: 0.37 | ET97: 0 | EU97: 0 | EV97: 76.15 | EW97: 5.37 | EX97: 0 | EY97: 0 | FQ97: 0 | FR97: 0 | FS97: 0 | FX97: 95 | FY97: 53 | GD97: 1 | GF97: 1760566508 | GG97: 2 | GH97: 1 | GI97: 2 | GJ97: 0 | GK97: 0 | GL97: =ROUND(IF(AND(BH97=3,BI97=3,FS97<>0),P97,0),2) -> 0 | GM97: =ROUND(O97+X97+Y97,2)+GX97 -> 246.7 | GN97: =IF(OR(BI97=0,BI97=1),GM97-GX97,0) -> 0 | GO97: =IF(BI97=2,GM97-GX97,0) -> 246.7 | GP97: =IF(BI97=4,GM97-GX97,0) -> 0 | GR97: 0 | GS97: 3 | GT97: 0 | GV97: =ROUND((GT97),6) -> 0 | GW97: 1 | GX97: =ROUND(HC97*I97,2) -> 0 | HA97: 0 | HB97: 0 | HC97: =GV97*GW97 -> 0 | HS97: 0 | IK97: 0
A98: 17 | B98: 1 | C98: =ROW(SmtRes!A186) -> 186 | D98: =ROW(EtalonRes!A210) -> 210 | E98: 18 | F98: 4.10-134-4 | G98: Монтаж антенны коллективной для приема ТВ на антенной опоре высотой до 9 м с одним ярусом оттяжек | H98: 1 антенна | I98: 1 | J98: 0 | K98: 1 | O98: =ROUND(CP98,2) -> 5599.27 | P98: =ROUND((ROUND((AC98*AW98*I98),2)*BC98),2) -> 2.02 | Q98: =(ROUND((ROUND((((ET98*1.2))*AV98*I98),2)*BB98),2)+ROUND((ROUND(((AE98-((EU98*1.2)))*AV98*I98),2)*BS98),2)) -> 0 | R98: =(ROUND((ROUND((((EU98*1.2))*AV98*I98),2)*BS98),2)+ROUND((ROUND(((AE98-((EU98*1.2)))*AV98*I98),2)*BS98),2)) -> 0 | S98: =ROUND((ROUND((AF98*AV98*I98),2)*BA98),2) -> 5597.25 | T98: =ROUND(CU98*I98,2) -> 0 | U98: =CV98*I98 -> 7.004628 | V98: =CW98*I98 -> 0 | W98: =ROUND(CX98*I98,2) -> 0 | X98: =(ROUND((((S98+ROUND((ROUND((((EU98*1.2))*AV98*I98),2)*BS98),2))*AT98)/100),2)+ROUND(((ROUND((ROUND(((AE98-((EU98*1.2)))*AV98*I98),2)*BS98),2)*AT98)/100),2)) -> 5317.39 | Y98: =(ROUND((((S98+ROUND((ROUND((((EU98*1.2))*AV98*I98),2)*BS98),2))*AU98)/100),2)+ROUND(((ROUND((ROUND(((AE98-((EU98*1.2)))*AV98*I98),2)*BS98),2)*AU98)/100),2)) -> 2966.54 | AA98: 55917799 | AB98: =ROUND((AC98+AD98+AF98),6) -> 91.75 | AC98: =ROUND(((ES98*1)),6) -> 0.37 | AD98: =ROUND(((((ET98*1.2))-((EU98*1.2)))+AE98),6) -> 0 | AE98: =ROUND(((EU98*1.2)),6) -> 0 | AF98: =ROUND(((EV98*1.2)),6) -> 91.38 | AG98: =ROUND((AP98),6) -> 0 | AH98: =((EW98*1.2)) -> 6.444 | AI98: =((EX98*1.2)) -> 0 | AJ98: =(AS98) -> 0 | AK98: 76.52 | AL98: 0.37 | AM98: 0 | AN98: 0 | AO98: 76.15 | AP98: 0 | AQ98: 5.37 | AR98: 0 | AS98: 0 | AT98: 95 | AU98: 53 | AV98: 1.087 | AW98: 1 | AZ98: 1 | BA98: 56.35 | BB98: 1 | BC98: 5.46 | BH98: 0 | BI98: 2 | BJ98: ТСН-2001.4 Доп. 81, Сб. 10, т. 134, поз. 4 | BM98: 69 | BN98: 0 | BO98: 4.10-134-4 | BP98: 1 | BQ98: 40 | BR98: 0 | BS98: 56.35 | BT98: 1 | BU98: 1 | BV98: 1 | BW98: 1 | BX98: 1 | BZ98: 95 | CA98: 53 | CE98: 1566 | CF98: 0 | CG98: 0 | CM98: 0 | CN98: Поправка: Гл.12.Прил.8.п.8. 3_12.00.01.11.001 Наименование: При наличии напряженных и стесненных условий производства работ (стесненность, сложность складирования и транспортной логистики и т.п.) для объектов, расположенных в пределах круговой магистральной системы улиц "Садовое кольцо" города Москвы | CO98: 0 | CP98: =(P98+Q98+S98) -> 5599.27 | CQ98: =ROUND((ROUND((AC98*AW98*1),2)*BC98),2) -> 2.02 | CR98: =(ROUND((ROUND((((ET98*1.2))*AV98*1),2)*BB98),2)+ROUND((ROUND(((AE98-((EU98*1.2)))*AV98*1),2)*BS98),2)) -> 0 | CS98: =(ROUND((ROUND((((EU98*1.2))*AV98*1),2)*BS98),2)+ROUND((ROUND(((AE98-((EU98*1.2)))*AV98*1),2)*BS98),2)) -> 0 | CT98: =ROUND((ROUND((AF98*AV98*1),2)*BA98),2) -> 5597.25 | CU98: =AG98 -> 0 | CV98: =(AH98*AV98) -> 7.004628 | CW98: =AI98 -> 0 | CX98: =AJ98 -> 0 | CY98: =(ROUND((((S98+ROUND((ROUND((((EU98*1.2))*AV98*1),2)*BS98),2))*AT98)/100),2)+ROUND(((ROUND((ROUND(((AE98-((EU98*1.2)))*AV98*1),2)*BS98),2)*AT98)/100),2)) -> 5317.39 | CZ98: =(ROUND((((S98+ROUND((ROUND((((EU98*1.2))*AV98*1),2)*BS98),2))*AU98)/100),2)+ROUND(((ROUND((ROUND(((AE98-((EU98*1.2)))*AV98*1),2)*BS98),2)*AU98)/100),2)) -> 2966.54 | DB98: 54 | DD98: *1 | DE98: *1,2 | DF98: *1,2 | DG98: *1,2 | DI98: *1,2 | DJ98: *1,2 | DN98: 0 | DO98: 0 | DP98: 1 | DQ98: 1 | DU98: 1013 | DV98: 1 антенна | DW98: 1 антенна | DX98: 1 | EE98: 55393701 | EF98: 40 | EG98: Монтаж оборудования | EH98: 0 | EJ98: 2 | EK98: 69 | EL98: ТСН-2001.4-10. Монтаж радиотелевизионного и электронного оборудования | EM98: ТСН-2001.4-10-2 | EO98: Поправка: Гл.12.Прил.8.п.8. 3_12.00.01.11.001 | EQ98: 0 | ER98: 76.52 | ES98: 0.37 | ET98: 0 | EU98: 0 | EV98: 76.15 | EW98: 5.37 | EX98: 0 | EY98: 0 | FQ98: 0 | FR98: 0 | FS98: 0 | FX98: 95 | FY98: 53 | GD98: 1 | GF98: 1760566508 | GG98: 2 | GH98: 1 | GI98: 2 | GJ98: 0 | GK98: 0 | GL98: =ROUND(IF(AND(BH98=3,BI98=3,FS98<>0),P98,0),2) -> 0 | GM98: =ROUND(O98+X98+Y98,2)+GX98 -> 13883.2 | GN98: =IF(OR(BI98=0,BI98=1),GM98-GX98,0) -> 0 | GO98: =IF(BI98=2,GM98-GX98,0) -> 13883.2 | GP98: =IF(BI98=4,GM98-GX98,0) -> 0 | GR98: 0 | GS98: 3 | GT98: 0 | GV98: =ROUND((GT98),6) -> 0 | GW98: 1 | GX98: =ROUND(HC98*I98,2) -> 0 | HA98: 0 | HB98: 0 | HC98: =GV98*GW98 -> 0 | HS98: 0 | IK98: 0
A99: 17 | B99: 1 | E99: 19 | F99: 13.1-2-587 | G99: Антенна эфирная UNF, частотный диапазон от 470 до 790 MHz, коэффициент усиления антенны от 14 до 16 дБ, каналы от 21 до 60. Габаритные размеры 450х2356x400 мм | H99: шт. | I99: 1 | J99: 0 | K99: 1 | O99: =ROUND(CP99,2) -> 699.69 | P99: =ROUND((ROUND((AC99*I99),2)*BC99),2) -> 699.69 | Q99: =(ROUND((ROUND(((ET99)*AV99*I99),2)*BB99),2)+ROUND((ROUND(((AE99-(EU99))*AV99*I99),2)*BS99),2)) -> 0 | R99: =(ROUND((ROUND(((EU99)*AV99*I99),2)*BS99),2)+ROUND((ROUND(((AE99-(EU99))*AV99*I99),2)*BS99),2)) -> 0 | S99: =ROUND((ROUND((AF99*AV99*I99),2)*BA99),2) -> 0 | T99: =ROUND(CU99*I99,2) -> 0 | U99: =CV99*I99 -> 0 | V99: =CW99*I99 -> 0 | W99: =ROUND(CX99*I99,2) -> 0 | X99: =(ROUND((((S99+ROUND((ROUND(((EU99)*AV99*I99),2)*BS99),2))*AT99)/100),2)+ROUND(((ROUND((ROUND(((AE99-(EU99))*AV99*I99),2)*BS99),2)*AT99)/100),2)) -> 0 | Y99: =(ROUND((((S99+ROUND((ROUND(((EU99)*AV99*I99),2)*BS99),2))*AU99)/100),2)+ROUND(((ROUND((ROUND(((AE99-(EU99))*AV99*I99),2)*BS99),2)*AU99)/100),2)) -> 0 | AA99: 55917797 | AB99: =ROUND((AC99+AD99+AF99),6) -> 699.69 | AC99: =ROUND((ES99),6) -> 699.69 | AD99: =ROUND((((ET99)-(EU99))+AE99),6) -> 0 | AE99: =ROUND((EU99),6) -> 0 | AF99: =ROUND((EV99),6) -> 0 | AG99: =ROUND((AP99),6) -> 0 | AH99: =(EW99) -> 0 | AI99: =(EX99) -> 0 | AJ99: =(AS99) -> 0 | AK99: 699.69 | AL99: 699.69 | AM99: 0 | AN99: 0 | AO99: 0 | AP99: 0 | AQ99: 0 | AR99: 0 | AS99: 0 | AT99: 0 | AU99: 0 | AV99: 1 | AW99: 1 | AZ99: 1 | BA99: 1 | BB99: 1 | BC99: 1 | BH99: 3 | BI99: 3 | BJ99: ТСН-2001.13-2. Доп. 36. 13.1-2-587 | BM99: 746 | BN99: 0 | BP99: 0 | BQ99: 130 | BR99: 0 | BS99: 1 | BT99: 1 | BU99: 1 | BV99: 1 | BW99: 1 | BX99: 1 | BZ99: 0 | CA99: 0 | CE99: 1566 | CF99: 0 | CG99: 0 | CM99: 0 | CO99: 0 | CP99: =(P99+Q99+S99) -> 699.69 | CQ99: =ROUND((ROUND((AC99*1),2)*BC99),2) -> 699.69 | CR99: =(ROUND((ROUND(((ET99)*AV99*1),2)*BB99),2)+ROUND((ROUND(((AE99-(EU99))*AV99*1),2)*BS99),2)) -> 0 | CS99: =(ROUND((ROUND(((EU99)*AV99*1),2)*BS99),2)+ROUND((ROUND(((AE99-(EU99))*AV99*1),2)*BS99),2)) -> 0 | CT99: =ROUND((ROUND((AF99*AV99*1),2)*BA99),2) -> 0 | CU99: =AG99 -> 0 | CV99: =(AH99*AV99) -> 0 | CW99: =AI99 -> 0 | CX99: =AJ99 -> 0 | CY99: =(ROUND((((S99+ROUND((ROUND(((EU99)*AV99*1),2)*BS99),2))*AT99)/100),2)+ROUND(((ROUND((ROUND(((AE99-(EU99))*AV99*1),2)*BS99),2)*AT99)/100),2)) -> 0 | CZ99: =(ROUND((((S99+ROUND((ROUND(((EU99)*AV99*1),2)*BS99),2))*AU99)/100),2)+ROUND(((ROUND((ROUND(((AE99-(EU99))*AV99*1),2)*BS99),2)*AU99)/100),2)) -> 0 | DN99: 0 | DO99: 0 | DP99: 1 | DQ99: 1 | DU99: 1010 | DV99: шт. | DW99: шт. | DX99: 1 | EE99: 55393806 | EF99: 130 | EG99: Сметная стоимость оборудования | EH99: 0 | EJ99: 3 | EK99: 746 | EL99: ТСН-2001.13. Сметная стоимость оборудования | EM99: ТСН-2001.13 | EQ99: 0 | ER99: 699.69 | ES99: 699.69 | ET99: 0 | EU99: 0 | EV99: 0 | EW99: 0 | EX99: 0 | EY99: 0 | FQ99: 0 | FR99: =P99 -> 699.69 | FS99: 0 | FX99: 0 | FY99: 0 | GD99: 1 | GF99: 539505184 | GG99: 2 | GH99: 1 | GI99: -2 | GJ99: 0 | GK99: 0 | GL99: =ROUND(IF(AND(BH99=3,BI99=3,FS99<>0),P99,0),2) -> 0 | GM99: =ROUND(O99+X99+Y99,2)+GX99 -> 699.69 | GN99: =IF(OR(BI99=0,BI99=1),GM99-GX99,0) -> 0 | GO99: =IF(BI99=2,GM99-GX99,0) -> 0 | GP99: =IF(BI99=4,GM99-GX99,0) -> 0 | GR99: 0 | GS99: 3 | GT99: 0 | GV99: =ROUND((GT99),6) -> 0 | GW99: 1 | GX99: =ROUND(HC99*I99,2) -> 0 | HA99: 0 | HB99: 0 | HC99: =GV99*GW99 -> 0 | HS99: 0 | IK99: 0
A100: 17 | B100: 1 | E100: 19 | F100: 13.1-2-587 | G100: Антенна эфирная UNF, частотный диапазон от 470 до 790 MHz, коэффициент усиления антенны от 14 до 16 дБ, каналы от 21 до 60. Габаритные размеры 450х2356x400 мм | H100: шт. | I100: 1 | J100: 0 | K100: 1 | O100: =ROUND(CP100,2) -> 7381.73 | P100: =ROUND((ROUND((AC100*I100),2)*BC100),2) -> 7381.73 | Q100: =(ROUND((ROUND(((ET100)*AV100*I100),2)*BB100),2)+ROUND((ROUND(((AE100-(EU100))*AV100*I100),2)*BS100),2)) -> 0 | R100: =(ROUND((ROUND(((EU100)*AV100*I100),2)*BS100),2)+ROUND((ROUND(((AE100-(EU100))*AV100*I100),2)*BS100),2)) -> 0 | S100: =ROUND((ROUND((AF100*AV100*I100),2)*BA100),2) -> 0 | T100: =ROUND(CU100*I100,2) -> 0 | U100: =CV100*I100 -> 0 | V100: =CW100*I100 -> 0 | W100: =ROUND(CX100*I100,2) -> 0 | X100: =(ROUND((((S100+ROUND((ROUND(((EU100)*AV100*I100),2)*BS100),2))*AT100)/100),2)+ROUND(((ROUND((ROUND(((AE100-(EU100))*AV100*I100),2)*BS100),2)*AT100)/100),2)) -> 0 | Y100: =(ROUND((((S100+ROUND((ROUND(((EU100)*AV100*I100),2)*BS100),2))*AU100)/100),2)+ROUND(((ROUND((ROUND(((AE100-(EU100))*AV100*I100),2)*BS100),2)*AU100)/100),2)) -> 0 | AA100: 55917799 | AB100: =ROUND((AC100+AD100+AF100),6) -> 699.69 | AC100: =ROUND((ES100),6) -> 699.69 | AD100: =ROUND((((ET100)-(EU100))+AE100),6) -> 0 | AE100: =ROUND((EU100),6) -> 0 | AF100: =ROUND((EV100),6) -> 0 | AG100: =ROUND((AP100),6) -> 0 | AH100: =(EW100) -> 0 | AI100: =(EX100) -> 0 | AJ100: =(AS100) -> 0 | AK100: 699.69 | AL100: 699.69 | AM100: 0 | AN100: 0 | AO100: 0 | AP100: 0 | AQ100: 0 | AR100: 0 | AS100: 0 | AT100: 0 | AU100: 0 | AV100: 1 | AW100: 1 | AZ100: 1 | BA100: 1 | BB100: 1 | BC100: 10.55 | BH100: 3 | BI100: 3 | BJ100: ТСН-2001.13-2. Доп. 36. 13.1-2-587 | BM100: 746 | BN100: 0 | BP100: 0 | BQ100: 130 | BR100: 0 | BS100: 1 | BT100: 1 | BU100: 1 | BV100: 1 | BW100: 1 | BX100: 1 | BZ100: 0 | CA100: 0 | CE100: 1566 | CF100: 0 | CG100: 0 | CM100: 0 | CO100: 0 | CP100: =(P100+Q100+S100) -> 7381.73 | CQ100: =ROUND((ROUND((AC100*1),2)*BC100),2) -> 7381.73 | CR100: =(ROUND((ROUND(((ET100)*AV100*1),2)*BB100),2)+ROUND((ROUND(((AE100-(EU100))*AV100*1),2)*BS100),2)) -> 0 | CS100: =(ROUND((ROUND(((EU100)*AV100*1),2)*BS100),2)+ROUND((ROUND(((AE100-(EU100))*AV100*1),2)*BS100),2)) -> 0 | CT100: =ROUND((ROUND((AF100*AV100*1),2)*BA100),2) -> 0 | CU100: =AG100 -> 0 | CV100: =(AH100*AV100) -> 0 | CW100: =AI100 -> 0 | CX100: =AJ100 -> 0 | CY100: =(ROUND((((S100+ROUND((ROUND(((EU100)*AV100*1),2)*BS100),2))*AT100)/100),2)+ROUND(((ROUND((ROUND(((AE100-(EU100))*AV100*1),2)*BS100),2)*AT100)/100),2)) -> 0 | CZ100: =(ROUND((((S100+ROUND((ROUND(((EU100)*AV100*1),2)*BS100),2))*AU100)/100),2)+ROUND(((ROUND((ROUND(((AE100-(EU100))*AV100*1),2)*BS100),2)*AU100)/100),2)) -> 0 | DN100: 0 | DO100: 0 | DP100: 1 | DQ100: 1 | DU100: 1010 | DV100: шт. | DW100: шт. | DX100: 1 | EE100: 55393806 | EF100: 130 | EG100: Сметная стоимость оборудования | EH100: 0 | EJ100: 3 | EK100: 746 | EL100: ТСН-2001.13. Сметная стоимость оборудования | EM100: ТСН-2001.13 | EQ100: 0 | ER100: 699.69 | ES100: 699.69 | ET100: 0 | EU100: 0 | EV100: 0 | EW100: 0 | EX100: 0 | EY100: 0 | FQ100: 0 | FR100: =P100 -> 7381.73 | FS100: 0 | FX100: 0 | FY100: 0 | GD100: 1 | GF100: 539505184 | GG100: 2 | GH100: 1 | GI100: 2 | GJ100: 0 | GK100: 0 | GL100: =ROUND(IF(AND(BH100=3,BI100=3,FS100<>0),P100,0),2) -> 0 | GM100: =ROUND(O100+X100+Y100,2)+GX100 -> 7381.73 | GN100: =IF(OR(BI100=0,BI100=1),GM100-GX100,0) -> 0 | GO100: =IF(BI100=2,GM100-GX100,0) -> 0 | GP100: =IF(BI100=4,GM100-GX100,0) -> 0 | GR100: 0 | GS100: 3 | GT100: 0 | GV100: =ROUND((GT100),6) -> 0 | GW100: 1 | GX100: =ROUND(HC100*I100,2) -> 0 | HA100: 0 | HB100: 0 | HC100: =GV100*GW100 -> 0 | HS100: 0 | IK100: 0
A101: 17 | B101: 1 | C101: =ROW(SmtRes!A201) -> 201 | D101: =ROW(EtalonRes!A227) -> 227 | E101: 20 | F101: 4.10-21-5 | G101: Грозозащита для воздушных абонентских линий | H101: 1 комплект | I101: 1 | J101: 0 | K101: 1 | O101: =ROUND(CP101,2) -> 90.18 | P101: =ROUND((ROUND((AC101*AW101*I101),2)*BC101),2) -> 42.61 | Q101: =(ROUND((ROUND((((ET101*1.2))*AV101*I101),2)*BB101),2)+ROUND((ROUND(((AE101-((EU101*1.2)))*AV101*I101),2)*BS101),2)) -> 0 | R101: =(ROUND((ROUND((((EU101*1.2))*AV101*I101),2)*BS101),2)+ROUND((ROUND(((AE101-((EU101*1.2)))*AV101*I101),2)*BS101),2)) -> 0 | S101: =ROUND((ROUND((AF101*AV101*I101),2)*BA101),2) -> 47.57 | T101: =ROUND(CU101*I101,2) -> 0 | U101: =CV101*I101 -> 3.7692 | V101: =CW101*I101 -> 0 | W101: =ROUND(CX101*I101,2) -> 0 | X101: =(ROUND((((S101+ROUND((ROUND((((EU101*1.2))*AV101*I101),2)*BS101),2))*AT101)/100),2)+ROUND(((ROUND((ROUND(((AE101-((EU101*1.2)))*AV101*I101),2)*BS101),2)*AT101)/100),2)) -> 42.81 | Y101: =(ROUND((((S101+ROUND((ROUND((((EU101*1.2))*AV101*I101),2)*BS101),2))*AU101)/100),2)+ROUND(((ROUND((ROUND(((AE101-((EU101*1.2)))*AV101*I101),2)*BS101),2)*AU101)/100),2)) -> 21.88 | AA101: 55917797 | AB101: =ROUND((AC101+AD101+AF101),6) -> 88.042 | AC101: =ROUND(((ES101*1)),6) -> 42.61 | AD101: =ROUND(((((ET101*1.2))-((EU101*1.2)))+AE101),6) -> 0 | AE101: =ROUND(((EU101*1.2)),6) -> 0 | AF101: =ROUND(((EV101*1.2)),6) -> 45.432 | AG101: =ROUND((AP101),6) -> 0 | AH101: =((EW101*1.2)) -> 3.6 | AI101: =((EX101*1.2)) -> 0 | AJ101: =(AS101) -> 0 | AK101: 80.47 | AL101: 42.61 | AM101: 0 | AN101: 0 | AO101: 37.86 | AP101: 0 | AQ101: 3 | AR101: 0 | AS101: 0 | AT101: 90 | AU101: 46 | AV101: 1.047 | AW101: 1 | AZ101: 1 | BA101: 1 | BB101: 1 | BC101: 1 | BH101: 0 | BI101: 2 | BJ101: ТСН-2001.4 Доп. 79, Сб. 10, т. 21, поз. 5 | BM101: 68 | BN101: 0 | BO101: 4.10-21-5 | BP101: 1 | BQ101: 40 | BR101: 0 | BS101: 1 | BT101: 1 | BU101: 1 | BV101: 1 | BW101: 1 | BX101: 1 | BZ101: 90 | CA101: 46 | CE101: 1566 | CF101: 0 | CG101: 0 | CM101: 0 | CN101: Поправка: Гл.12.Прил.8.п.8. 3_12.00.01.11.001 Наименование: При наличии напряженных и стесненных условий производства работ (стесненность, сложность складирования и транспортной логистики и т.п.) для объектов, расположенных в пределах круговой магистральной системы улиц "Садовое кольцо" города Москвы | CO101: 0 | CP101: =(P101+Q101+S101) -> 90.18 | CQ101: =ROUND((ROUND((AC101*AW101*1),2)*BC101),2) -> 42.61 | CR101: =(ROUND((ROUND((((ET101*1.2))*AV101*1),2)*BB101),2)+ROUND((ROUND(((AE101-((EU101*1.2)))*AV101*1),2)*BS101),2)) -> 0 | CS101: =(ROUND((ROUND((((EU101*1.2))*AV101*1),2)*BS101),2)+ROUND((ROUND(((AE101-((EU101*1.2)))*AV101*1),2)*BS101),2)) -> 0 | CT101: =ROUND((ROUND((AF101*AV101*1),2)*BA101),2) -> 47.57 | CU101: =AG101 -> 0 | CV101: =(AH101*AV101) -> 3.7692 | CW101: =AI101 -> 0 | CX101: =AJ101 -> 0 | CY101: =(ROUND((((S101+ROUND((ROUND((((EU101*1.2))*AV101*1),2)*BS101),2))*AT101)/100),2)+ROUND(((ROUND((ROUND(((AE101-((EU101*1.2)))*AV101*1),2)*BS101),2)*AT101)/100),2)) -> 42.81 | CZ101: =(ROUND((((S101+ROUND((ROUND((((EU101*1.2))*AV101*1),2)*BS101),2))*AU101)/100),2)+ROUND(((ROUND((ROUND(((AE101-((EU101*1.2)))*AV101*1),2)*BS101),2)*AU101)/100),2)) -> 21.88 | DB101: 55 | DD101: *1 | DE101: *1,2 | DF101: *1,2 | DG101: *1,2 | DI101: *1,2 | DJ101: *1,2 | DN101: 0 | DO101: 0 | DP101: 1 | DQ101: 1 | DU101: 1013 | DV101: 1 комплект | DW101: 1 комплект | DX101: 1 | EE101: 55393700 | EF101: 40 | EG101: Монтаж оборудования | EH101: 0 | EJ101: 2 | EK101: 68 | EL101: ТСН-2001.4-10. Прокладка и монтаж сетей связи | EM101: ТСН-2001.4-10-1 | EO101: Поправка: Гл.12.Прил.8.п.8. 3_12.00.01.11.001 | EQ101: 0 | ER101: 80.47 | ES101: 42.61 | ET101: 0 | EU101: 0 | EV101: 37.86 | EW101: 3 | EX101: 0 | EY101: 0 | FQ101: 0 | FR101: 0 | FS101: 0 | FX101: 90 | FY101: 46 | GD101: 1 | GF101: -1785550083 | GG101: 2 | GH101: 1 | GI101: 2 | GJ101: 0 | GK101: 0 | GL101: =ROUND(IF(AND(BH101=3,BI101=3,FS101<>0),P101,0),2) -> 0 | GM101: =ROUND(O101+X101+Y101,2)+GX101 -> 154.87 | GN101: =IF(OR(BI101=0,BI101=1),GM101-GX101,0) -> 0 | GO101: =IF(BI101=2,GM101-GX101,0) -> 154.87 | GP101: =IF(BI101=4,GM101-GX101,0) -> 0 | GR101: 0 | GS101: 3 | GT101: 0 | GV101: =ROUND((GT101),6) -> 0 | GW101: 1 | GX101: =ROUND(HC101*I101,2) -> 0 | HA101: 0 | HB101: 0 | HC101: =GV101*GW101 -> 0 | HS101: 0 | IK101: 0
A102: 17 | B102: 1 | C102: =ROW(SmtRes!A216) -> 216 | D102: =ROW(EtalonRes!A244) -> 244 | E102: 20 | F102: 4.10-21-5 | G102: Грозозащита для воздушных абонентских линий | H102: 1 комплект | I102: 1 | J102: 0 | K102: 1 | O102: =ROUND(CP102,2) -> 2900.01 | P102: =ROUND((ROUND((AC102*AW102*I102),2)*BC102),2) -> 219.44 | Q102: =(ROUND((ROUND((((ET102*1.2))*AV102*I102),2)*BB102),2)+ROUND((ROUND(((AE102-((EU102*1.2)))*AV102*I102),2)*BS102),2)) -> 0 | R102: =(ROUND((ROUND((((EU102*1.2))*AV102*I102),2)*BS102),2)+ROUND((ROUND(((AE102-((EU102*1.2)))*AV102*I102),2)*BS102),2)) -> 0 | S102: =ROUND((ROUND((AF102*AV102*I102),2)*BA102),2) -> 2680.57 | T102: =ROUND(CU102*I102,2) -> 0 | U102: =CV102*I102 -> 3.7692 | V102: =CW102*I102 -> 0 | W102: =ROUND(CX102*I102,2) -> 0 | X102: =(ROUND((((S102+ROUND((ROUND((((EU102*1.2))*AV102*I102),2)*BS102),2))*AT102)/100),2)+ROUND(((ROUND((ROUND(((AE102-((EU102*1.2)))*AV102*I102),2)*BS102),2)*AT102)/100),2)) -> 2412.51 | Y102: =(ROUND((((S102+ROUND((ROUND((((EU102*1.2))*AV102*I102),2)*BS102),2))*AU102)/100),2)+ROUND(((ROUND((ROUND(((AE102-((EU102*1.2)))*AV102*I102),2)*BS102),2)*AU102)/100),2)) -> 1233.06 | AA102: 55917799 | AB102: =ROUND((AC102+AD102+AF102),6) -> 88.042 | AC102: =ROUND(((ES102*1)),6) -> 42.61 | AD102: =ROUND(((((ET102*1.2))-((EU102*1.2)))+AE102),6) -> 0 | AE102: =ROUND(((EU102*1.2)),6) -> 0 | AF102: =ROUND(((EV102*1.2)),6) -> 45.432 | AG102: =ROUND((AP102),6) -> 0 | AH102: =((EW102*1.2)) -> 3.6 | AI102: =((EX102*1.2)) -> 0 | AJ102: =(AS102) -> 0 | AK102: 80.47 | AL102: 42.61 | AM102: 0 | AN102: 0 | AO102: 37.86 | AP102: 0 | AQ102: 3 | AR102: 0 | AS102: 0 | AT102: 90 | AU102: 46 | AV102: 1.047 | AW102: 1 | AZ102: 1 | BA102: 56.35 | BB102: 1 | BC102: 5.15 | BH102: 0 | BI102: 2 | BJ102: ТСН-2001.4 Доп. 79, Сб. 10, т. 21, поз. 5 | BM102: 68 | BN102: 0 | BO102: 4.10-21-5 | BP102: 1 | BQ102: 40 | BR102: 0 | BS102: 56.35 | BT102: 1 | BU102: 1 | BV102: 1 | BW102: 1 | BX102: 1 | BZ102: 90 | CA102: 46 | CE102: 1566 | CF102: 0 | CG102: 0 | CM102: 0 | CN102: Поправка: Гл.12.Прил.8.п.8. 3_12.00.01.11.001 Наименование: При наличии напряженных и стесненных условий производства работ (стесненность, сложность складирования и транспортной логистики и т.п.) для объектов, расположенных в пределах круговой магистральной системы улиц "Садовое кольцо" города Москвы | CO102: 0 | CP102: =(P102+Q102+S102) -> 2900.01 | CQ102: =ROUND((ROUND((AC102*AW102*1),2)*BC102),2) -> 219.44 | CR102: =(ROUND((ROUND((((ET102*1.2))*AV102*1),2)*BB102),2)+ROUND((ROUND(((AE102-((EU102*1.2)))*AV102*1),2)*BS102),2)) -> 0 | CS102: =(ROUND((ROUND((((EU102*1.2))*AV102*1),2)*BS102),2)+ROUND((ROUND(((AE102-((EU102*1.2)))*AV102*1),2)*BS102),2)) -> 0 | CT102: =ROUND((ROUND((AF102*AV102*1),2)*BA102),2) -> 2680.57 | CU102: =AG102 -> 0 | CV102: =(AH102*AV102) -> 3.7692 | CW102: =AI102 -> 0 | CX102: =AJ102 -> 0 | CY102: =(ROUND((((S102+ROUND((ROUND((((EU102*1.2))*AV102*1),2)*BS102),2))*AT102)/100),2)+ROUND(((ROUND((ROUND(((AE102-((EU102*1.2)))*AV102*1),2)*BS102),2)*AT102)/100),2)) -> 2412.51 | CZ102: =(ROUND((((S102+ROUND((ROUND((((EU102*1.2))*AV102*1),2)*BS102),2))*AU102)/100),2)+ROUND(((ROUND((ROUND(((AE102-((EU102*1.2)))*AV102*1),2)*BS102),2)*AU102)/100),2)) -> 1233.06 | DB102: 56 | DD102: *1 | DE102: *1,2 | DF102: *1,2 | DG102: *1,2 | DI102: *1,2 | DJ102: *1,2 | DN102: 0 | DO102: 0 | DP102: 1 | DQ102: 1 | DU102: 1013 | DV102: 1 комплект | DW102: 1 комплект | DX102: 1 | EE102: 55393700 | EF102: 40 | EG102: Монтаж оборудования | EH102: 0 | EJ102: 2 | EK102: 68 | EL102: ТСН-2001.4-10. Прокладка и монтаж сетей связи | EM102: ТСН-2001.4-10-1 | EO102: Поправка: Гл.12.Прил.8.п.8. 3_12.00.01.11.001 | EQ102: 0 | ER102: 80.47 | ES102: 42.61 | ET102: 0 | EU102: 0 | EV102: 37.86 | EW102: 3 | EX102: 0 | EY102: 0 | FQ102: 0 | FR102: 0 | FS102: 0 | FX102: 90 | FY102: 46 | GD102: 1 | GF102: -1785550083 | GG102: 2 | GH102: 1 | GI102: 2 | GJ102: 0 | GK102: 0 | GL102: =ROUND(IF(AND(BH102=3,BI102=3,FS102<>0),P102,0),2) -> 0 | GM102: =ROUND(O102+X102+Y102,2)+GX102 -> 6545.58 | GN102: =IF(OR(BI102=0,BI102=1),GM102-GX102,0) -> 0 | GO102: =IF(BI102=2,GM102-GX102,0) -> 6545.58 | GP102: =IF(BI102=4,GM102-GX102,0) -> 0 | GR102: 0 | GS102: 3 | GT102: 0 | GV102: =ROUND((GT102),6) -> 0 | GW102: 1 | GX102: =ROUND(HC102*I102,2) -> 0 | HA102: 0 | HB102: 0 | HC102: =GV102*GW102 -> 0 | HS102: 0 | IK102: 0
