Workbook

Sheet Смета по ТСН-2001(с доп.67
A1: =Source!B1 -> Smeta.RU (495) 974-1589
J2: Форма № 4б
B3: "СОГЛАСОВАНО" | G3: "УТВЕРЖДАЮ"
B6: =CONCATENATE("______________________ ", IF(Source!AL12<>"", Source!AL12, "")) -> ______________________ | G6: =CONCATENATE("______________________ ", IF(Source!AH12<>"", Source!AH12, "")) -> ______________________
B7: "_____"________________ 2026 г. | G7: "_____"________________ 2026 г.
A10: Капитальный ремонт здания Государственного бюджетного общеобразовательного учреждения города Москвы «Школа №1574», расположенного по адресу: г. Москва, Старопименовский переулок, д. 5. 1 этап. | AP10: Капитальный ремонт здания Государственного бюджетного общеобразовательного учреждения города Москвы «Школа №1574», расположенного по адресу: г. Москва, Старопименовский переулок, д. 5. 1 этап. 02-01-16 Электрочасофикация 15.07
A11: (наименование стройки и/или объекта)
A13: =CONCATENATE( "ЛОКАЛЬНАЯ СМЕТА № ",IF(Source!F12<>"Новый объект", Source!F12, "")) -> ЛОКАЛЬНАЯ СМЕТА № 02-01-16
A15: =Source!G20 -> Электрочасофикация
A16: (наименование работ и затрат)
A18: =CONCATENATE( "Основание: чертежи № ", Source!J12) -> Основание: чертежи № 2024-00375-01-0-ИОС5.9
I20: В базисном уровне цен | J20: В текущем уровне цен
E21: Сметная стоимость | I21: =I22+I23+I24+I25 -> 135.22 | J21: =J22+J23+J24+J25 -> 1054.65 | K21: тыс.руб.
E22: Строительные работы | I22: =ROUND((Source!F247)/1000, 2) -> 0 | J22: =ROUND((Source!P247)/1000, 2) -> 0 | K22: тыс.руб.
E23: Работы по монтажу оборудования | I23: =ROUND((Source!F248)/1000, 2) -> 0.74 | J23: =ROUND((Source!P248)/1000, 2) -> 36.65 | K23: тыс.руб.
E24: Оборудование | I24: =ROUND((Source!F239)/1000, 2) -> 134.48 | J24: =ROUND((Source!P239)/1000, 2) -> 1018 | K24: тыс.руб.
E25: Прочие работы и затраты | I25: =ROUND((Source!F249+Source!F250)/1000, 2) -> 0 | J25: =ROUND((Source!P249+Source!P250)/1000, 2) -> 0 | K25: тыс.руб.
E26: Средства на оплату труда | I26: =(Source!F245+ Source!F244)/1000 -> 0.26827 | J26: =((Source!P245 + Source!P244)/1000) -> 15.11703 | K26: тыс.руб.
E27: Затраты труда | I27: =Source!F252 -> 21.315978 | K27: чел.-ч.
E28: Кроме того:
E29: Возврат материалов | I29: =SUM(Y1:Y173)/1000 -> 0 | J29: =SUM(Z1:Z173)/1000 -> 0 | K29: тыс.руб.
A31: Составлен(а) по ТСН-2001 с учетом Дополнения №: 81
A32: № и период сборника коэффициентов (индексов) пересчета: Коэффициенты к ТСН-2001 МГЭ Дополнение 81, ремонт №219/81 I квартал 2026 года и Коэффициенты к ТСН-2001.13-2 Дополнение 47 №64/47 I квартал 2026 года | AP32: № и период сборника коэффициентов (индексов) пересчета: Коэффициенты к ТСН-2001 МГЭ Дополнение 81, ремонт №219/81 I квартал 2026 года и Коэффициенты к ТСН-2001.13-2 Дополнение 47 №64/47 I квартал 2026 года
A33: № п/п | B33: Шифр расценки и коды ресурсов | C33: Наименование работ и затрат | D33: Ед. изм. | E33: Кол-во единиц | F33: Цена на ед. изм., руб. | G33: Попра- вочные коэффи- циенты | H33: Коэффи- циенты зимних удорожа- ний | I33: Всего в ценах на январь 2000 года, руб. | J33: Коэффи- циенты (индек- сы) пере- счета, нормы НР и СП | K33: ВСЕГО затрат в текущем уровне цен, руб.
A34: 1 | B34: 2 | C34: 3 | D34: 4 | E34: 5 | F34: 6 | G34: 7 | H34: 8 | I34: 9 | J34: 10 | K34: 11
A36: =CONCATENATE("Локальная смета: ",IF(Source!G20<>"Новая локальная смета", Source!G20, "")) -> Локальная смета: Электрочасофикация
A38: =CONCATENATE("Раздел: ",IF(Source!G24<>"Новый раздел", Source!G24, "")) -> Раздел: Демонтажные работы (Письмо от АНО «РГТ» об утверждении объёмов демонтажных работ) | AP38: =CONCATENATE("Раздел: ",IF(Source!G24<>"Новый раздел", Source!G24, "")) -> Раздел: Демонтажные работы (Письмо от АНО «РГТ» об утверждении объёмов демонтажных работ)
A39: 1 | B39: =Source!F28 -> 4.10-85-1 | C39: Монтаж часов первичных электрических показывающих кварцевых типа ПКЧЗ-2-РИ-Р24-Р6-1 / демонтаж часовой станции | D39: =Source!H28 -> 1 ШТ. | E39: =Source!I28 -> 1 | Q39: =Source!X28 -> 14.01 | R39: =Source!X29 -> 789.63 | S39: =Source!Y28 -> 7.16 | T39: =Source!Y29 -> 403.59 | U39: =ROUND((175/100)*ROUND(Source!R28, 2), 2) -> 0 | V39: =ROUND((0/100)*ROUND(Source!R29, 2), 2) -> 0 | AC39: 0
C40: ЗП | F40: =Source!AO28 -> 41.31 | G40: 1,2*0,3 | H40: =Source!AV29 -> 1.047 | I40: =Source!S28 -> 15.57 | J40: =IF(Source!BA29<> 0, Source!BA29, 1) -> 56.35 | K40: =Source!S29 -> 877.37
C41: НР от ФОТ | D41: % | E41: =Source!BZ29 -> 90 | I41: =SUM(Q39:Q40) -> 14.01 | J41: =Source!AT29 -> 90 | K41: =SUM(R39:R40) -> 789.63
C42: СП от ФОТ | D42: % | E42: =Source!CA29 -> 46 | I42: =SUM(S39:S41) -> 7.16 | J42: =Source!AU29 -> 46 | K42: =SUM(T39:T41) -> 403.59
C43: ЗТР | D43: чел-ч | E43: =Source!AQ28 -> 3 | G43: 1,2*0,3 | H43: =Source!AV29 -> 1.047 | I43: =Source!U28 -> 1.13076
C44: ВСЕГО работ по позиции: | H44: =I40+I41+I42+0-0-0 -> 36.74 | J44: =K40+K41+K42+0-0-0 -> 2070.59
C45: ВСЕГО оборудование по позиции: | H45: =0+0 -> 0 | J45: =0+0 -> 0
C46: ВСЕГО по позиции: | H46: =I40+I41+I42+0 -> 36.74 | J46: =K40+K41+K42+0 -> 2070.59 | O46: =I40+I41+I42+0 -> 36.74 | P46: =K40+K41+K42+0 -> 2070.59
A48: 2 | B48: =Source!F30 -> 4.10-134-7 | C48: Монтаж антенны дополнительной для приема ТВ на ранее установленной опоре, с действующими ТВ антеннами / демонтаж антенны | D48: =Source!H30 -> 1 антенна | E48: =Source!I30 -> 1 | Q48: =Source!X30 -> 14.81 | R48: =Source!X31 -> 834.58 | S48: =Source!Y30 -> 8.26 | T48: =Source!Y31 -> 465.61 | U48: =ROUND((175/100)*ROUND(Source!R30, 2), 2) -> 0 | V48: =ROUND((0/100)*ROUND(Source!R31, 2), 2) -> 0 | AC48: 0
C49: ЗП | F49: =Source!AO30 -> 39.85 | G49: 1,2*0,3 | H49: =Source!AV31 -> 1.087 | I49: =Source!S30 -> 15.59 | J49: =IF(Source!BA31<> 0, Source!BA31, 1) -> 56.35 | K49: =Source!S31 -> 878.5
C50: НР от ФОТ | D50: % | E50: =Source!BZ31 -> 95 | I50: =SUM(Q48:Q49) -> 14.81 | J50: =Source!AT31 -> 95 | K50: =SUM(R48:R49) -> 834.58
C51: СП от ФОТ | D51: % | E51: =Source!CA31 -> 53 | I51: =SUM(S48:S50) -> 8.26 | J51: =Source!AU31 -> 53 | K51: =SUM(T48:T50) -> 465.61
C52: ЗТР | D52: чел-ч | E52: =Source!AQ30 -> 2.77 | G52: 1,2*0,3 | H52: =Source!AV31 -> 1.087 | I52: =Source!U30 -> 1.0839564
C53: ВСЕГО работ по позиции: | H53: =I49+I50+I51+0-0-0 -> 38.66 | J53: =K49+K50+K51+0-0-0 -> 2178.69
C54: ВСЕГО оборудование по позиции: | H54: =0+0 -> 0 | J54: =0+0 -> 0
C55: ВСЕГО по позиции: | H55: =I49+I50+I51+0 -> 38.66 | J55: =K49+K50+K51+0 -> 2178.69 | O55: =I49+I50+I51+0 -> 38.66 | P55: =K49+K50+K51+0 -> 2178.69
A57: 3 | B57: =Source!F32 -> 4.10-136-1 | C57: Монтаж коробки телевизионной (ответвители, разветвители магистральные, домовые, абонентские), УСС, / демонтаж модуля грозозащиты для антенны | D57: =Source!H32 -> 1 ШТ. | E57: =Source!I32 -> 1 | Q57: =Source!X32 -> 4.09 | R57: =Source!X33 -> 230.73 | S57: =Source!Y32 -> 2.28 | T57: =Source!Y33 -> 128.72 | U57: =ROUND((175/100)*ROUND(Source!R32, 2), 2) -> 0 | V57: =ROUND((0/100)*ROUND(Source!R33, 2), 2) -> 0 | AC57: 0
C58: ЗП | F58: =Source!AO32 -> 11.02 | G58: 1,2*0,3 | H58: =Source!AV33 -> 1.087 | I58: =Source!S32 -> 4.31 | J58: =IF(Source!BA33<> 0, Source!BA33, 1) -> 56.35 | K58: =Source!S33 -> 242.87
C59: НР от ФОТ | D59: % | E59: =Source!BZ33 -> 95 | I59: =SUM(Q57:Q58) -> 4.09 | J59: =Source!AT33 -> 95 | K59: =SUM(R57:R58) -> 230.73
C60: СП от ФОТ | D60: % | E60: =Source!CA33 -> 53 | I60: =SUM(S57:S59) -> 2.28 | J60: =Source!AU33 -> 53 | K60: =SUM(T57:T59) -> 128.72
C61: ЗТР | D61: чел-ч | E61: =Source!AQ32 -> 0.8 | G61: 1,2*0,3 | H61: =Source!AV33 -> 1.087 | I61: =Source!U32 -> 0.313056
C62: ВСЕГО работ по позиции: | H62: =I58+I59+I60+0-0-0 -> 10.68 | J62: =K58+K59+K60+0-0-0 -> 602.32
C63: ВСЕГО оборудование по позиции: | H63: =0+0 -> 0 | J63: =0+0 -> 0
C64: ВСЕГО по позиции: | H64: =I58+I59+I60+0 -> 10.68 | J64: =K58+K59+K60+0 -> 602.32 | O64: =I58+I59+I60+0 -> 10.68 | P64: =K58+K59+K60+0 -> 602.32
A66: 4 | B66: =Source!F34 -> 4.10-86-1 | C66: Монтаж электрочасов вторичных для помещений односторонних на стене / демонтаж часов повторителей | D66: =Source!H34 -> 1 ШТ. | E66: =Source!I34 -> 3 | Q66: =Source!X34 -> 24.22 | R66: =Source!X35 -> 1364.74 | S66: =Source!Y34 -> 12.38 | T66: =Source!Y35 -> 697.53 | U66: =ROUND((175/100)*ROUND(Source!R34, 2), 2) -> 0 | V66: =ROUND((0/100)*ROUND(Source!R35, 2), 2) -> 0 | AC66: 0
C67: ЗП | F67: =Source!AO34 -> 23.8 | G67: 1,2*0,3 | H67: =Source!AV35 -> 1.047 | I67: =Source!S34 -> 26.91 | J67: =IF(Source!BA35<> 0, Source!BA35, 1) -> 56.35 | K67: =Source!S35 -> 1516.38
C68: НР от ФОТ | D68: % | E68: =Source!BZ35 -> 90 | I68: =SUM(Q66:Q67) -> 24.22 | J68: =Source!AT35 -> 90 | K68: =SUM(R66:R67) -> 1364.74
C69: СП от ФОТ | D69: % | E69: =Source!CA35 -> 46 | I69: =SUM(S66:S68) -> 12.38 | J69: =Source!AU35 -> 46 | K69: =SUM(T66:T68) -> 697.53
C70: ЗТР | D70: чел-ч | E70: =Source!AQ34 -> 2 | G70: 1,2*0,3 | H70: =Source!AV35 -> 1.047 | I70: =Source!U34 -> 2.26152
C71: ВСЕГО работ по позиции: | H71: =I67+I68+I69+0-0-0 -> 63.51 | J71: =K67+K68+K69+0-0-0 -> 3578.65
C72: ВСЕГО оборудование по позиции: | H72: =0+0 -> 0 | J72: =0+0 -> 0
C73: ВСЕГО по позиции: | H73: =I67+I68+I69+0 -> 63.51 | J73: =K67+K68+K69+0 -> 3578.65 | O73: =I67+I68+I69+0 -> 63.51 | P73: =K67+K68+K69+0 -> 3578.65
A76: =CONCATENATE("Итого по разделу: ",IF(Source!G37<>"Новый раздел", Source!G37, "")) -> Итого по разделу: Демонтажные работы (Письмо от АНО «РГТ» об утверждении объёмов демонтажных работ) | H76: =SUM(O38:O75) -> 149.59 | J76: =SUM(P38:P75) -> 8430.25 | AQ76: =CONCATENATE("Итого по разделу: ",IF(Source!G37<>"Новый раздел", Source!G37, "")) -> Итого по разделу: Демонтажные работы (Письмо от АНО «РГТ» об утверждении объёмов демонтажных работ)
A77: Итого по ТСН-2001.16 | I77: =SUM(W38:W76) -> 0 | J77: =SUM(X38:X76) -> 0
A78: Итого возвратных сумм | I78: =SUM(Y38:Y77) -> 0 | J78: =SUM(Z38:Z77) -> 0
A80: =CONCATENATE("Раздел: ",IF(Source!G67<>"Новый раздел", Source!G67, "")) -> Раздел: Комплект основного оборудования
A81: 5 | B81: =Source!F71 -> 4.10-85-1 | C81: Монтаж часов первичных электрических показывающих кварцевых типа ПКЧЗ-2-РИ-Р24-Р6-1 | D81: =Source!H71 -> 1 ШТ. | E81: =Source!I71 -> 1 | Q81: =Source!X71 -> 46.71 | R81: =Source!X72 -> 2632.11 | S81: =Source!Y71 -> 23.87 | T81: =Source!Y72 -> 1345.3 | U81: =ROUND((175/100)*ROUND(Source!R71, 2), 2) -> 0 | V81: =ROUND((0/100)*ROUND(Source!R72, 2), 2) -> 0 | AC81: 0
C82: ЗП | F82: =Source!AO71 -> 41.31 | G82: 1,2 | H82: =Source!AV72 -> 1.047 | I82: =Source!S71 -> 51.9 | J82: =IF(Source!BA72<> 0, Source!BA72, 1) -> 56.35 | K82: =Source!S72 -> 2924.57
C83: МР | F83: =Source!AL71 -> 0.46 | H83: =Source!AW72 -> 1 | I83: =Source!P71 -> 0.46 | J83: =IF(Source!BC72<> 0, Source!BC72, 1) -> 6.83 | K83: =Source!P72 -> 3.14
C84: НР от ФОТ | D84: % | E84: =Source!BZ72 -> 90 | I84: =SUM(Q81:Q83) -> 46.71 | J84: =Source!AT72 -> 90 | K84: =SUM(R81:R83) -> 2632.11
C85: СП от ФОТ | D85: % | E85: =Source!CA72 -> 46 | I85: =SUM(S81:S84) -> 23.87 | J85: =Source!AU72 -> 46 | K85: =SUM(T81:T84) -> 1345.3
C86: ЗТР | D86: чел-ч | E86: =Source!AQ71 -> 3 | G86: 1,2 | H86: =Source!AV72 -> 1.047 | I86: =Source!U71 -> 3.7692
C87: ВСЕГО работ по позиции: | H87: =I82+I83+I84+I85+0-0-0 -> 122.94 | J87: =K82+K83+K84+K85+0-0-0 -> 6905.12
C88: ВСЕГО оборудование по позиции: | H88: =0+0 -> 0 | J88: =0+0 -> 0
C89: ВСЕГО по позиции: | H89: =I82+I83+I84+I85+0 -> 122.94 | J89: =K82+K83+K84+K85+0 -> 6905.12 | O89: =I82+I83+I84+I85+0 -> 122.94 | P89: =K82+K83+K84+K85+0 -> 6905.12
A91: 6 | B91: =Source!F73 -> КА1 | C91: ОБОРУДОВАНИЕ:_x000D_ КОНТУР - часовая станция, сервер времени, стоечное исполнение, NTP (тип. SC KMWP-IP-A0124) 72 464,18 = [642 038,95 / 1,22 / 7,57] + 3% Трансп + 1,2% Заг.скл | D91: =Source!H73 -> шт. | E91: =Source!I73 -> 1 | F91: =Source!AL73 -> 72464.18 | H91: =Source!AW74 -> 1 | I91: =Source!P73 -> 72464.18 | J91: =IF(Source!BC74<> 0, Source!BC74, 1) -> 7.57 | K91: =Source!P74 -> 548553.84 | Q91: =Source!X73 -> 0 | R91: =Source!X74 -> 0 | S91: =Source!Y73 -> 0 | T91: =Source!Y74 -> 0 | U91: =ROUND((175/100)*ROUND(Source!R73, 2), 2) -> 0 | V91: =ROUND((0/100)*ROUND(Source!R74, 2), 2) -> 0 | AC91: 5
C92: ВСЕГО по позиции: | H92: =I91+0 -> 72464.18 | J92: =K91+0 -> 548553.84 | O92: =I91+0 -> 72464.18 | P92: =K91+0 -> 548553.84
A94: 7 | B94: =Source!F75 -> 4.11-12-1 | C94: Установка съемных и выдвижных блоков (модулей, ячеек, ТЭЗ) массой до 5 кг | D94: =Source!H75 -> 1 ШТ. | E94: =Source!I75 -> 1 | Q94: =Source!X75 -> 13.27 | R94: =Source!X76 -> 747.54 | S94: =Source!Y75 -> 6.78 | T94: =Source!Y76 -> 382.08 | U94: =ROUND((175/100)*ROUND(Source!R75, 2), 2) -> 0.18 | V94: =ROUND((0/100)*ROUND(Source!R76, 2), 2) -> 0 | AC94: 0
C95: ЗП | F95: =Source!AO75 -> 11.65 | G95: 1,2 | H95: =Source!AV76 -> 1.047 | I95: =Source!S75 -> 14.64 | J95: =IF(Source!BA76<> 0, Source!BA76, 1) -> 56.35 | K95: =Source!S76 -> 824.96
C96: ЭМ | F96: =Source!AM75 -> 0.5 | G96: 1,2 | H96: =Source!AV76 -> 1.047 | I96: =Source!Q75 -> 0.63 | J96: =IF(Source!BB76<> 0, Source!BB76, 1) -> 17.02 | K96: =Source!Q76 -> 10.72
C97: в т.ч. ЗПМ | F97: =Source!AN75 -> 0.08 | G97: 1,2 | H97: =Source!AV76 -> 1.047 | I97: =Source!R75 -> 0.1 | J97: =IF(Source!BS76<> 0, Source!BS76, 1) -> 56.35 | K97: =Source!R76 -> 5.64
C98: НР от ФОТ | D98: % | E98: =Source!BZ76 -> 90 | I98: =SUM(Q94:Q97) -> 13.27 | J98: =Source!AT76 -> 90 | K98: =SUM(R94:R97) -> 747.54
C99: СП от ФОТ | D99: % | E99: =Source!CA76 -> 46 | I99: =SUM(S94:S98) -> 6.78 | J99: =Source!AU76 -> 46 | K99: =SUM(T94:T98) -> 382.08
C100: ЗТР | D100: чел-ч | E100: =Source!AQ75 -> 1.03 | G100: 1,2 | H100: =Source!AV76 -> 1.047 | I100: =Source!U75 -> 1.294092
C101: ВСЕГО работ по позиции: | H101: =I95+I96+I98+I99+0-0-0 -> 35.32 | J101: =K95+K96+K98+K99+0-0-0 -> 1965.3
C102: ВСЕГО оборудование по позиции: | H102: =0+0 -> 0 | J102: =0+0 -> 0
C103: ВСЕГО по позиции: | H103: =I95+I96+I98+I99+0 -> 35.32 | J103: =K95+K96+K98+K99+0 -> 1965.3 | O103: =I95+I96+I98+I99+0 -> 35.32 | P103: =K95+K96+K98+K99+0 -> 1965.3
A105: 8 | B105: =Source!F79 -> КА2 | C105: ОБОРУДОВАНИЕ:_x000D_ Модуль часовой станции GPS / ГЛОНАСС Антенна (тип. SC GPS/GLO) 9тип SC GPS/GLO-A042 4) 12 282,39 = [108 823 / 1,22 / 7,57] + 3% Трансп + 1,2% Заг.скл | D105: =Source!H79 -> шт. | E105: =Source!I79 -> 1 | F105: =Source!AL79 -> 12282.39 | H105: =Source!AW80 -> 1 | I105: =Source!P79 -> 12282.39 | J105: =IF(Source!BC80<> 0, Source!BC80, 1) -> 7.57 | K105: =Source!P80 -> 92977.69 | Q105: =Source!X79 -> 0 | R105: =Source!X80 -> 0 | S105: =Source!Y79 -> 0 | T105: =Source!Y80 -> 0 | U105: =ROUND((175/100)*ROUND(Source!R79, 2), 2) -> 0 | V105: =ROUND((0/100)*ROUND(Source!R80, 2), 2) -> 0 | AC105: 5
C106: ВСЕГО по позиции: | H106: =I105+0 -> 12282.39 | J106: =K105+0 -> 92977.69 | O106: =I105+0 -> 12282.39 | P106: =K105+0 -> 92977.69
A108: 9 | B108: =Source!F81 -> 4.10-21-5 | C108: Грозозащита для воздушных абонентских линий | D108: =Source!H81 -> 1 комплект | E108: =Source!I81 -> 1 | Q108: =Source!X81 -> 42.81 | R108: =Source!X82 -> 2412.51 | S108: =Source!Y81 -> 21.88 | T108: =Source!Y82 -> 1233.06 | U108: =ROUND((175/100)*ROUND(Source!R81, 2), 2) -> 0 | V108: =ROUND((0/100)*ROUND(Source!R82, 2), 2) -> 0 | AC108: 0
C109: ЗП | F109: =Source!AO81 -> 37.86 | G109: 1,2 | H109: =Source!AV82 -> 1.047 | I109: =Source!S81 -> 47.57 | J109: =IF(Source!BA82<> 0, Source!BA82, 1) -> 56.35 | K109: =Source!S82 -> 2680.57
C110: МР | F110: =Source!AL81 -> 42.61 | H110: =Source!AW82 -> 1 | I110: =Source!P81 -> 42.61 | J110: =IF(Source!BC82<> 0, Source!BC82, 1) -> 5.15 | K110: =Source!P82 -> 219.44
C111: НР от ФОТ | D111: % | E111: =Source!BZ82 -> 90 | I111: =SUM(Q108:Q110) -> 42.81 | J111: =Source!AT82 -> 90 | K111: =SUM(R108:R110) -> 2412.51
C112: СП от ФОТ | D112: % | E112: =Source!CA82 -> 46 | I112: =SUM(S108:S111) -> 21.88 | J112: =Source!AU82 -> 46 | K112: =SUM(T108:T111) -> 1233.06
C113: ЗТР | D113: чел-ч | E113: =Source!AQ81 -> 3 | G113: 1,2 | H113: =Source!AV82 -> 1.047 | I113: =Source!U81 -> 3.7692
C114: ВСЕГО работ по позиции: | H114: =I109+I110+I111+I112+0-0-0 -> 154.87 | J114: =K109+K110+K111+K112+0-0-0 -> 6545.58
C115: ВСЕГО оборудование по позиции: | H115: =0+0 -> 0 | J115: =0+0 -> 0
C116: ВСЕГО по позиции: | H116: =I109+I110+I111+I112+0 -> 154.87 | J116: =K109+K110+K111+K112+0 -> 6545.58 | O116: =I109+I110+I111+I112+0 -> 154.87 | P116: =K109+K110+K111+K112+0 -> 6545.58
A118: 10 | B118: =Source!F85 -> КА3 | C118: ОБОРУДОВАНИЕ:_x000D_ Модуль грозозащиты для антенны (тип. SC PTR) SC PTR-A0424 12 258,35 = [108 610 / 1,22 / 7,57] + 3% Трансп + 1,2% Заг.скл | D118: =Source!H85 -> шт. | E118: =Source!I85 -> 1 | F118: =Source!AL85 -> 12258.35 | H118: =Source!AW86 -> 1 | I118: =Source!P85 -> 12258.35 | J118: =IF(Source!BC86<> 0, Source!BC86, 1) -> 7.57 | K118: =Source!P86 -> 92795.71 | Q118: =Source!X85 -> 0 | R118: =Source!X86 -> 0 | S118: =Source!Y85 -> 0 | T118: =Source!Y86 -> 0 | U118: =ROUND((175/100)*ROUND(Source!R85, 2), 2) -> 0 | V118: =ROUND((0/100)*ROUND(Source!R86, 2), 2) -> 0 | AC118: 5
C119: ВСЕГО по позиции: | H119: =I118+0 -> 12258.35 | J119: =K118+0 -> 92795.71 | O119: =I118+0 -> 12258.35 | P119: =K118+0 -> 92795.71
A122: =CONCATENATE("Итого по разделу: ",IF(Source!G88<>"Новый раздел", Source!G88, "")) -> Итого по разделу: Комплект основного оборудования | H122: =SUM(O80:O121) -> 97318.05 | J122: =SUM(P80:P121) -> 749743.24
A123: Итого по ТСН-2001.16 | I123: =SUM(W80:W122) -> 0 | J123: =SUM(X80:X122) -> 0
A124: Итого возвратных сумм | I124: =SUM(Y80:Y123) -> 0 | J124: =SUM(Z80:Z123) -> 0
...

Sheet Source
A1: 0 | B1: Smeta.RU (495) 974-1589 | D1: _PS_ | F1: 0 | G1: 0 | H1: 0 | I1: Smeta.RU | K1: 1 | L1: 74599 | M1: 10 | N1: 12 | O1: 1 | P1: 0 | Q1: 5
A4: 1 | B4: 1 | C4: -1 | G4: Капитальный ремонт здания Государственного бюджетного общеобразовательного учреждения города Москвы «Школа №1574», расположенного по адресу: г. Москва, Старопименовский переулок, д. 5. 1 этап | EC4: 0
A5: 8 | B5: 1 | C5: -1 | G5: Капитальный ремонт здания Государственного бюджетного общеобразовательного учреждения города Москвы «Школа №1574», расположенного по адресу: г. Москва, Старопименовский переулок, д. 5. 1 этап | EC5: 0
A12: 1 | B12: 271 | C12: 0 | D12: =ROW(A230) -> 230 | E12: 0 | F12: 02-01-16 | G12: 02-01-16 Электрочасофикация 15.07 | I12: 0 | J12: 2024-00375-01-0-ИОС5.9 | K12: 0 | L12: 0 | M12: 4097 | O12: 0 | P12: 0 | Q12: 0 | R12: 0 | S12: 0 | T12: 1 | U12: Капитальный ремонт здания Государственного бюджетного общеобразовательного учреждения города Москвы «Школа №1574», | V12: 2 | W12: г. Москва, Старопименовский переулок, д. 5. 1 этап | AB12: О.А.Гришечкина | AC12: Ведущий инженер-сметчик | AD12: И.В.Феденко | AE12: Начальник отдела | BB12: 0 | BH12: Сметные нормы списания | BI12: Коды ОКП для ТСН-2001 МГЭ Дополнение 81 | BJ12: 1 | BK12: 1 | BL12: 0 | BM12: 0 | BN12: 1 | BO12: 0 | BP12: 6 | BQ12: 2 | BR12: 1 | BS12: 1 | BT12: 0 | BU12: 0 | BV12: 0 | BW12: 0 | BX12: 0 | BY12: ТСН-2001 (МГЭ) Доп 81 - Ремонт | BZ12: Типовой расчет для ТСН-2001 МГЭ, Дополнение 81, ремонт | CA12: Территориальные сметные нормативы для Москвы ТСН-2001 (МГЭ), дополнение 81 | CB12: Территориальные сметные нормативы для Москвы ТСН-2001 (МГЭ), дополнение 81 | CC12: Территориальные сметные нормативы для Москвы ТСН-2001 (МГЭ), дополнение 81 | CD12: Территориальные сметные нормативы для Москвы ТСН-2001 (МГЭ), дополнение 81 | CE12: Поправки для ТСН-2001 от 07.04.2026 г. доп.81 | CF12: 0 | CG12: 0 | CH12: 8 | CK12: 82 | CQ12: Территориальные сметные нормативы для Москвы (ТСН-2001) | CR12: ТЕР | CS12: 41660 | CT12: 1 | CU12: 81 | CY12: 0 | EC12: 0
A15: 15 | B15: 1
A18: 52 | B18: =B230 -> 271 | C18: =C230 -> 1 | D18: =D230 -> 12 | E18: =E230 -> 0 | F18: =F230 -> 02-01-16 | G18: =G230 -> 02-01-16 Электрочасофикация 15.07 | O18: =O230 -> 134852.23 | P18: =P230 -> 134583.43 | Q18: =Q230 -> 0.63 | R18: =R230 -> 0.1 | S18: =S230 -> 268.17 | T18: =T230 -> 0 | U18: =U230 -> 21.315978 | V18: =V230 -> 0 | ... GX18: =GX230 -> 0
A20: 3 | B20: 1 | D20: =ROW(A200) -> 200 | F20: 02-01-16 | G20: Электрочасофикация | I20: 0 | J20: 2024-00375-01-0-ИОС5.9 | K20: -1 | L20: 02-01-16 | S20: 0 | T20: 0 | V20: 2 | BX20: 0 | CF20: 0 | CG20: 0
A22: 52 | B22: =B200 -> 1 | C22: =C200 -> 3 | D22: =D200 -> 20 | E22: =E200 -> 0 | F22: =F200 -> 02-01-16 | G22: =G200 -> Электрочасофикация | O22: =O200 -> 134852.23 | P22: =P200 -> 134583.43 | Q22: =Q200 -> 0.63 | R22: =R200 -> 0.1 | S22: =S200 -> 268.17 | T22: =T200 -> 0 | U22: =U200 -> 21.315978 | V22: =V200 -> 0 | ... GX22: =GX200 -> 0
A24: 4 | B24: 1 | D24: =ROW(A37) -> 37 | F24: Новый раздел | G24: Демонтажные работы (Письмо от АНО «РГТ» об утверждении объёмов демонтажных работ) | I24: 0 | K24: -1 | S24: 0 | T24: 0 | V24: 2 | BX24: 0 | CJ24: 0
A26: 52 | B26: =B37 -> 1 | C26: =C37 -> 4 | D26: =D37 -> 24 | E26: =E37 -> 0 | F26: =F37 -> Новый раздел | G26: =G37 -> Демонтажные работы (Письмо от АНО «РГТ» об утверждении объёмов демонтажных работ) | O26: =O37 -> 62.38 | P26: =P37 -> 0 | Q26: =Q37 -> 0 | R26: =R37 -> 0 | S26: =S37 -> 62.38 | T26: =T37 -> 0 | U26: =U37 -> 4.7892924 | V26: =V37 -> 0 | ... GX26: =GX37 -> 0
A28: 17 | B28: 1 | C28: =ROW(SmtRes!A3) -> 3 | D28: =ROW(EtalonRes!A3) -> 3 | E28: 1 | F28: 4.10-85-1 | G28: Монтаж часов первичных электрических показывающих кварцевых типа ПКЧЗ-2-РИ-Р24-Р6-1 / демонтаж часовой станции | H28: 1 ШТ. | I28: 1 | J28: 0 | K28: 1 | O28: =ROUND(CP28,2) -> 15.57 | P28: =ROUND((ROUND((AC28*AW28*I28),2)*BC28),2) -> 0 | Q28: =(ROUND((ROUND(((((ET28*1.2)*0.3))*AV28*I28),2)*BB28),2)+ROUND((ROUND(((AE28-(((EU28*1.2)*0.3)))*AV28*I28),2)*BS28),2)) -> 0 | R28: =(ROUND((ROUND(((((EU28*1.2)*0.3))*AV28*I28),2)*BS28),2)+ROUND((ROUND(((AE28-(((EU28*1.2)*0.3)))*AV28*I28),2)*BS28),2)) -> 0 | S28: =ROUND((ROUND((AF28*AV28*I28),2)*BA28),2) -> 15.57 | T28: =ROUND(CU28*I28,2) -> 0 | U28: =CV28*I28 -> 1.13076 | V28: =CW28*I28 -> 0 | W28: =ROUND(CX28*I28,2) -> 0 | X28: =(ROUND((((S28+ROUND((ROUND(((((EU28*1.2)*0.3))*AV28*I28),2)*BS28),2))*AT28)/100),2)+ROUND(((ROUND((ROUND(((AE28-(((EU28*1.2)*0.3)))*AV28*I28),2)*BS28),2)*AT28)/100),2)) -> 14.01 | Y28: =(ROUND((((S28+ROUND((ROUND(((((EU28*1.2)*0.3))*AV28*I28),2)*BS28),2))*AU28)/100),2)+ROUND(((ROUND((ROUND(((AE28-(((EU28*1.2)*0.3)))*AV28*I28),2)*BS28),2)*AU28)/100),2)) -> 7.16 | AA28: 55942966 | AB28: =ROUND((AC28+AD28+AF28),6) -> 14.8716 | AC28: =ROUND((((ES28*1)*0)),6) -> 0 | AD28: =ROUND((((((ET28*1.2)*0.3))-(((EU28*1.2)*0.3)))+AE28),6) -> 0 | AE28: =ROUND((((EU28*1.2)*0.3)),6) -> 0 | AF28: =ROUND((((EV28*1.2)*0.3)),6) -> 14.8716 | AG28: =ROUND((AP28),6) -> 0 | AH28: =(((EW28*1.2)*0.3)) -> 1.08 | AI28: =(((EX28*1.2)*0.3)) -> 0 | AJ28: =(AS28) -> 0 | AK28: 41.77 | AL28: 0.46 | AM28: 0 | AN28: 0 | AO28: 41.31 | AP28: 0 | AQ28: 3 | AR28: 0 | AS28: 0 | AT28: 90 | AU28: 46 | AV28: 1.047 | AW28: 1 | AZ28: 1 | BA28: 1 | BB28: 1 | BC28: 1 | BH28: 0 | BI28: 2 | BJ28: ТСН-2001.4 Доп. 81, Сб. 10, т. 85, поз. 1 | BM28: 68 | BN28: 0 | BO28: 4.10-85-1 | BP28: 1 | BQ28: 40 | BR28: 0 | BS28: 1 | BT28: 1 | BU28: 1 | BV28: 1 | BW28: 1 | BX28: 1 | BZ28: 90 | CA28: 46 | CE28: 1566 | CF28: 0 | CG28: 0 | CM28: 0 | CN28: Поправка: Гл.12.Прил.8.п.8. 3_12.00.01.11.001 Наименование: При наличии напряженных и стесненных условий производства работ (стесненность, сложность складирования и транспортной логистики и т.п.) для объектов, расположенных в пределах круговой магистральной системы улиц "Садовое кольцо" города Москвы Поправка: Гл.4.Прил.2.2.п.2.2.29_04.00.01.35.003 Наименование: При демонтаже оборудования, предназначенного в лом | CO28: 0 | CP28: =(P28+Q28+S28) -> 15.57 | CQ28: =ROUND((ROUND((AC28*AW28*1),2)*BC28),2) -> 0 | CR28: =(ROUND((ROUND(((((ET28*1.2)*0.3))*AV28*1),2)*BB28),2)+ROUND((ROUND(((AE28-(((EU28*1.2)*0.3)))*AV28*1),2)*BS28),2)) -> 0 | CS28: =(ROUND((ROUND(((((EU28*1.2)*0.3))*AV28*1),2)*BS28),2)+ROUND((ROUND(((AE28-(((EU28*1.2)*0.3)))*AV28*1),2)*BS28),2)) -> 0 | CT28: =ROUND((ROUND((AF28*AV28*1),2)*BA28),2) -> 15.57 | CU28: =AG28 -> 0 | CV28: =(AH28*AV28) -> 1.13076 | CW28: =AI28 -> 0 | CX28: =AJ28 -> 0 | CY28: =(ROUND((((S28+ROUND((ROUND(((((EU28*1.2)*0.3))*AV28*1),2)*BS28),2))*AT28)/100),2)+ROUND(((ROUND((ROUND(((AE28-(((EU28*1.2)*0.3)))*AV28*1),2)*BS28),2)*AT28)/100),2)) -> 14.01 | CZ28: =(ROUND((((S28+ROUND((ROUND(((((EU28*1.2)*0.3))*AV28*1),2)*BS28),2))*AU28)/100),2)+ROUND(((ROUND((ROUND(((AE28-(((EU28*1.2)*0.3)))*AV28*1),2)*BS28),2)*AU28)/100),2)) -> 7.16 | DB28: 1 | DD28: *1)*0 | DE28: *1,2)*0,3 | DF28: *1,2)*0,3 | DG28: *1,2)*0,3 | DI28: *1,2)*0,3 | DJ28: *1,2)*0,3 | DN28: 0 | DO28: 0 | DP28: 1 | DQ28: 1 | DU28: 1013 | DV28: 1 ШТ. | DW28: 1 ШТ. | DX28: 1 | EE28: 55393972 | EF28: 40 | EG28: Монтаж оборудования | EH28: 0 | EJ28: 2 | EK28: 68 | EL28: ТСН-2001.4-10. Прокладка и монтаж сетей связи | EM28: ТСН-2001.4-10-1 | EO28: Поправка: Гл.12.Прил.8.п.8. 3_12.00.01.11.001 Поправка: Гл.4.Прил.2.2.п.2.2.29_04.00.01.35.003 | EQ28: 0 | ER28: 41.77 | ES28: 0.46 | ET28: 0 | EU28: 0 | EV28: 41.31 | EW28: 3 | EX28: 0 | EY28: 0 | FQ28: 0 | FR28: 0 | FS28: 0 | FX28: 90 | FY28: 46 | GD28: 1 | GF28: 1212227501 | GG28: 2 | GH28: 1 | GI28: 2 | GJ28: 0 | GK28: 0 | GL28: =ROUND(IF(AND(BH28=3,BI28=3,FS28<>0),P28,0),2) -> 0 | GM28: =ROUND(O28+X28+Y28,2)+GX28 -> 36.74 | GN28: =IF(OR(BI28=0,BI28=1),GM28-GX28,0) -> 0 | GO28: =IF(BI28=2,GM28-GX28,0) -> 36.74 | GP28: =IF(BI28=4,GM28-GX28,0) -> 0 | GR28: 0 | GS28: 3 | GT28: 0 | GV28: =ROUND((GT28),6) -> 0 | GW28: 1 | GX28: =ROUND(HC28*I28,2) -> 0 | HA28: 0 | HB28: 0 | HC28: =GV28*GW28 -> 0 | HS28: 0 | IK28: 0
A29: 17 | B29: 1 | C29: =ROW(SmtRes!A6) -> 6 | D29: =ROW(EtalonRes!A6) -> 6 | E29: 1 | F29: 4.10-85-1 | G29: Монтаж часов первичных электрических показывающих кварцевых типа ПКЧЗ-2-РИ-Р24-Р6-1 / демонтаж часовой станции | H29: 1 ШТ. | I29: 1 | J29: 0 | K29: 1 | O29: =ROUND(CP29,2) -> 877.37 | P29: =ROUND((ROUND((AC29*AW29*I29),2)*BC29),2) -> 0 | Q29: =(ROUND((ROUND(((((ET29*1.2)*0.3))*AV29*I29),2)*BB29),2)+ROUND((ROUND(((AE29-(((EU29*1.2)*0.3)))*AV29*I29),2)*BS29),2)) -> 0 | R29: =(ROUND((ROUND(((((EU29*1.2)*0.3))*AV29*I29),2)*BS29),2)+ROUND((ROUND(((AE29-(((EU29*1.2)*0.3)))*AV29*I29),2)*BS29),2)) -> 0 | S29: =ROUND((ROUND((AF29*AV29*I29),2)*BA29),2) -> 877.37 | T29: =ROUND(CU29*I29,2) -> 0 | U29: =CV29*I29 -> 1.13076 | V29: =CW29*I29 -> 0 | W29: =ROUND(CX29*I29,2) -> 0 | X29: =(ROUND((((S29+ROUND((ROUND(((((EU29*1.2)*0.3))*AV29*I29),2)*BS29),2))*AT29)/100),2)+ROUND(((ROUND((ROUND(((AE29-(((EU29*1.2)*0.3)))*AV29*I29),2)*BS29),2)*AT29)/100),2)) -> 789.63 | Y29: =(ROUND((((S29+ROUND((ROUND(((((EU29*1.2)*0.3))*AV29*I29),2)*BS29),2))*AU29)/100),2)+ROUND(((ROUND((ROUND(((AE29-(((EU29*1.2)*0.3)))*AV29*I29),2)*BS29),2)*AU29)/100),2)) -> 403.59 | AA29: 55942968 | AB29: =ROUND((AC29+AD29+AF29),6) -> 14.8716 | AC29: =ROUND((((ES29*1)*0)),6) -> 0 | AD29: =ROUND((((((ET29*1.2)*0.3))-(((EU29*1.2)*0.3)))+AE29),6) -> 0 | AE29: =ROUND((((EU29*1.2)*0.3)),6) -> 0 | AF29: =ROUND((((EV29*1.2)*0.3)),6) -> 14.8716 | AG29: =ROUND((AP29),6) -> 0 | AH29: =(((EW29*1.2)*0.3)) -> 1.08 | AI29: =(((EX29*1.2)*0.3)) -> 0 | AJ29: =(AS29) -> 0 | AK29: 41.77 | AL29: 0.46 | AM29: 0 | AN29: 0 | AO29: 41.31 | AP29: 0 | AQ29: 3 | AR29: 0 | AS29: 0 | AT29: 90 | AU29: 46 | AV29: 1.047 | AW29: 1 | AZ29: 1 | BA29: 56.35 | BB29: 1 | BC29: 6.83 | BH29: 0 | BI29: 2 | BJ29: ТСН-2001.4 Доп. 81, Сб. 10, т. 85, поз. 1 | BM29: 68 | BN29: 0 | BO29: 4.10-85-1 | BP29: 1 | BQ29: 40 | BR29: 0 | BS29: 56.35 | BT29: 1 | BU29: 1 | BV29: 1 | BW29: 1 | BX29: 1 | BZ29: 90 | CA29: 46 | CE29: 1566 | CF29: 0 | CG29: 0 | CM29: 0 | CN29: Поправка: Гл.12.Прил.8.п.8. 3_12.00.01.11.001 Наименование: При наличии напряженных и стесненных условий производства работ (стесненность, сложность складирования и транспортной логистики и т.п.) для объектов, расположенных в пределах круговой магистральной системы улиц "Садовое кольцо" города Москвы Поправка: Гл.4.Прил.2.2.п.2.2.29_04.00.01.35.003 Наименование: При демонтаже оборудования, предназначенного в лом | CO29: 0 | CP29: =(P29+Q29+S29) -> 877.37 | CQ29: =ROUND((ROUND((AC29*AW29*1),2)*BC29),2) -> 0 | CR29: =(ROUND((ROUND(((((ET29*1.2)*0.3))*AV29*1),2)*BB29),2)+ROUND((ROUND(((AE29-(((EU29*1.2)*0.3)))*AV29*1),2)*BS29),2)) -> 0 | CS29: =(ROUND((ROUND(((((EU29*1.2)*0.3))*AV29*1),2)*BS29),2)+ROUND((ROUND(((AE29-(((EU29*1.2)*0.3)))*AV29*1),2)*BS29),2)) -> 0 | CT29: =ROUND((ROUND((AF29*AV29*1),2)*BA29),2) -> 877.37 | CU29: =AG29 -> 0 | CV29: =(AH29*AV29) -> 1.13076 | CW29: =AI29 -> 0 | CX29: =AJ29 -> 0 | CY29: =(ROUND((((S29+ROUND((ROUND(((((EU29*1.2)*0.3))*AV29*1),2)*BS29),2))*AT29)/100),2)+ROUND(((ROUND((ROUND(((AE29-(((EU29*1.2)*0.3)))*AV29*1),2)*BS29),2)*AT29)/100),2)) -> 789.63 | CZ29: =(ROUND((((S29+ROUND((ROUND(((((EU29*1.2)*0.3))*AV29*1),2)*BS29),2))*AU29)/100),2)+ROUND(((ROUND((ROUND(((AE29-(((EU29*1.2)*0.3)))*AV29*1),2)*BS29),2)*AU29)/100),2)) -> 403.59 | DB29: 3 | DD29: *1)*0 | DE29: *1,2)*0,3 | DF29: *1,2)*0,3 | DG29: *1,2)*0,3 | DI29: *1,2)*0,3 | DJ29: *1,2)*0,3 | DN29: 0 | DO29: 0 | DP29: 1 | DQ29: 1 | DU29: 1013 | DV29: 1 ШТ. | DW29: 1 ШТ. | DX29: 1 | EE29: 55393972 | EF29: 40 | EG29: Монтаж оборудования | EH29: 0 | EJ29: 2 | EK29: 68 | EL29: ТСН-2001.4-10. Прокладка и монтаж сетей связи | EM29: ТСН-2001.4-10-1 | EO29: Поправка: Гл.12.Прил.8.п.8. 3_12.00.01.11.001 Поправка: Гл.4.Прил.2.2.п.2.2.29_04.00.01.35.003 | EQ29: 0 | ER29: 41.77 | ES29: 0.46 | ET29: 0 | EU29: 0 | EV29: 41.31 | EW29: 3 | EX29: 0 | EY29: 0 | FQ29: 0 | FR29: 0 | FS29: 0 | FX29: 90 | FY29: 46 | GD29: 1 | GF29: 1212227501 | GG29: 2 | GH29: 1 | GI29: 2 | GJ29: 0 | GK29: 0 | GL29: =ROUND(IF(AND(BH29=3,BI29=3,FS29<>0),P29,0),2) -> 0 | GM29: =ROUND(O29+X29+Y29,2)+GX29 -> 2070.59 | GN29: =IF(OR(BI29=0,BI29=1),GM29-GX29,0) -> 0 | GO29: =IF(BI29=2,GM29-GX29,0) -> 2070.59 | GP29: =IF(BI29=4,GM29-GX29,0) -> 0 | GR29: 0 | GS29: 3 | GT29: 0 | GV29: =ROUND((GT29),6) -> 0 | GW29: 1 | GX29: =ROUND(HC29*I29,2) -> 0 | HA29: 0 | HB29: 0 | HC29: =GV29*GW29 -> 0 | HS29: 0 | IK29: 0
A30: 17 | B30: 1 | C30: =ROW(SmtRes!A8) -> 8 | D30: =ROW(EtalonRes!A8) -> 8 | E30: 2 | F30: 4.10-134-7 | G30: Монтаж антенны дополнительной для приема ТВ на ранее установленной опоре, с действующими ТВ антеннами / демонтаж антенны | H30: 1 антенна | I30: 1 | J30: 0 | K30: 1 | O30: =ROUND(CP30,2) -> 15.59 | P30: =ROUND((ROUND((AC30*AW30*I30),2)*BC30),2) -> 0 | Q30: =(ROUND((ROUND(((((ET30*1.2)*0.3))*AV30*I30),2)*BB30),2)+ROUND((ROUND(((AE30-(((EU30*1.2)*0.3)))*AV30*I30),2)*BS30),2)) -> 0 | R30: =(ROUND((ROUND(((((EU30*1.2)*0.3))*AV30*I30),2)*BS30),2)+ROUND((ROUND(((AE30-(((EU30*1.2)*0.3)))*AV30*I30),2)*BS30),2)) -> 0 | S30: =ROUND((ROUND((AF30*AV30*I30),2)*BA30),2) -> 15.59 | T30: =ROUND(CU30*I30,2) -> 0 | U30: =CV30*I30 -> 1.0839564 | V30: =CW30*I30 -> 0 | W30: =ROUND(CX30*I30,2) -> 0 | X30: =(ROUND((((S30+ROUND((ROUND(((((EU30*1.2)*0.3))*AV30*I30),2)*BS30),2))*AT30)/100),2)+ROUND(((ROUND((ROUND(((AE30-(((EU30*1.2)*0.3)))*AV30*I30),2)*BS30),2)*AT30)/100),2)) -> 14.81 | Y30: =(ROUND((((S30+ROUND((ROUND(((((EU30*1.2)*0.3))*AV30*I30),2)*BS30),2))*AU30)/100),2)+ROUND(((ROUND((ROUND(((AE30-(((EU30*1.2)*0.3)))*AV30*I30),2)*BS30),2)*AU30)/100),2)) -> 8.26 | AA30: 55942966 | AB30: =ROUND((AC30+AD30+AF30),6) -> 14.346 | AC30: =ROUND((((ES30*1)*0)),6) -> 0 | AD30: =ROUND((((((ET30*1.2)*0.3))-(((EU30*1.2)*0.3)))+AE30),6) -> 0 | AE30: =ROUND((((EU30*1.2)*0.3)),6) -> 0 | AF30: =ROUND((((EV30*1.2)*0.3)),6) -> 14.346 | AG30: =ROUND((AP30),6) -> 0 | AH30: =(((EW30*1.2)*0.3)) -> 0.9972 | AI30: =(((EX30*1.2)*0.3)) -> 0 | AJ30: =(AS30) -> 0 | AK30: 40.03 | AL30: 0.18 | AM30: 0 | AN30: 0 | AO30: 39.85 | AP30: 0 | AQ30: 2.77 | AR30: 0 | AS30: 0 | AT30: 95 | AU30: 53 | AV30: 1.087 | AW30: 1 | AZ30: 1 | BA30: 1 | BB30: 1 | BC30: 1 | BH30: 0 | BI30: 2 | BJ30: ТСН-2001.4 Доп. 81, Сб. 10, т. 134, поз. 7 | BM30: 69 | BN30: 0 | BO30: 4.10-134-7 | BP30: 1 | BQ30: 40 | BR30: 0 | BS30: 1 | BT30: 1 | BU30: 1 | BV30: 1 | BW30: 1 | BX30: 1 | BZ30: 95 | CA30: 53 | CE30: 1566 | CF30: 0 | CG30: 0 | CM30: 0 | CN30: Поправка: Гл.12.Прил.8.п.8. 3_12.00.01.11.001 Наименование: При наличии напряженных и стесненных условий производства работ (стесненность, сложность складирования и транспортной логистики и т.п.) для объектов, расположенных в пределах круговой магистральной системы улиц "Садовое кольцо" города Москвы Поправка: Гл.4.Прил.2.2.п.2.2.29_04.00.01.35.003 Наименование: При демонтаже оборудования, предназначенного в лом | CO30: 0 | CP30: =(P30+Q30+S30) -> 15.59 | CQ30: =ROUND((ROUND((AC30*AW30*1),2)*BC30),2) -> 0 | CR30: =(ROUND((ROUND(((((ET30*1.2)*0.3))*AV30*1),2)*BB30),2)+ROUND((ROUND(((AE30-(((EU30*1.2)*0.3)))*AV30*1),2)*BS30),2)) -> 0 | CS30: =(ROUND((ROUND(((((EU30*1.2)*0.3))*AV30*1),2)*BS30),2)+ROUND((ROUND(((AE30-(((EU30*1.2)*0.3)))*AV30*1),2)*BS30),2)) -> 0 | CT30: =ROUND((ROUND((AF30*AV30*1),2)*BA30),2) -> 15.59 | CU30: =AG30 -> 0 | CV30: =(AH30*AV30) -> 1.0839564 | CW30: =AI30 -> 0 | CX30: =AJ30 -> 0 | CY30: =(ROUND((((S30+ROUND((ROUND(((((EU30*1.2)*0.3))*AV30*1),2)*BS30),2))*AT30)/100),2)+ROUND(((ROUND((ROUND(((AE30-(((EU30*1.2)*0.3)))*AV30*1),2)*BS30),2)*AT30)/100),2)) -> 14.81 | CZ30: =(ROUND((((S30+ROUND((ROUND(((((EU30*1.2)*0.3))*AV30*1),2)*BS30),2))*AU30)/100),2)+ROUND(((ROUND((ROUND(((AE30-(((EU30*1.2)*0.3)))*AV30*1),2)*BS30),2)*AU30)/100),2)) -> 8.26 | DB30: 5 | DD30: *1)*0 | DE30: *1,2)*0,3 | DF30: *1,2)*0,3 | DG30: *1,2)*0,3 | DI30: *1,2)*0,3 | DJ30: *1,2)*0,3 | DN30: 0 | DO30: 0 | DP30: 1 | DQ30: 1 | DU30: 1013 | DV30: 1 антенна | DW30: 1 антенна | DX30: 1 | EE30: 55393973 | EF30: 40 | EG30: Монтаж оборудования | EH30: 0 | EJ30: 2 | EK30: 69 | EL30: ТСН-2001.4-10. Монтаж радиотелевизионного и электронного оборудования | EM30: ТСН-2001.4-10-2 | EO30: Поправка: Гл.12.Прил.8.п.8. 3_12.00.01.11.001 Поправка: Гл.4.Прил.2.2.п.2.2.29_04.00.01.35.003 | EQ30: 0 | ER30: 40.03 | ES30: 0.18 | ET30: 0 | EU30: 0 | EV30: 39.85 | EW30: 2.77 | EX30: 0 | EY30: 0 | FQ30: 0 | FR30: 0 | FS30: 0 | FX30: 95 | FY30: 53 | GD30: 1 | GF30: 338733022 | GG30: 2 | GH30: 1 | GI30: 2 | GJ30: 0 | GK30: 0 | GL30: =ROUND(IF(AND(BH30=3,BI30=3,FS30<>0),P30,0),2) -> 0 | GM30: =ROUND(O30+X30+Y30,2)+GX30 -> 38.66 | GN30: =IF(OR(BI30=0,BI30=1),GM30-GX30,0) -> 0 | GO30: =IF(BI30=2,GM30-GX30,0) -> 38.66 | GP30: =IF(BI30=4,GM30-GX30,0) -> 0 | GR30: 0 | GS30: 3 | GT30: 0 | GV30: =ROUND((GT30),6) -> 0 | GW30: 1 | GX30: =ROUND(HC30*I30,2) -> 0 | HA30: 0 | HB30: 0 | HC30: =GV30*GW30 -> 0 | HS30: 0 | IK30: 0
A31: 17 | B31: 1 | C31: =ROW(SmtRes!A10) -> 10 | D31: =ROW(EtalonRes!A10) -> 10 | E31: 2 | F31: 4.10-134-7 | G31: Монтаж антенны дополнительной для приема ТВ на ранее установленной опоре, с действующими ТВ антеннами / демонтаж антенны | H31: 1 антенна | I31: 1 | J31: 0 | K31: 1 | O31: =ROUND(CP31,2) -> 878.5 | P31: =ROUND((ROUND((AC31*AW31*I31),2)*BC31),2) -> 0 | Q31: =(ROUND((ROUND(((((ET31*1.2)*0.3))*AV31*I31),2)*BB31),2)+ROUND((ROUND(((AE31-(((EU31*1.2)*0.3)))*AV31*I31),2)*BS31),2)) -> 0 | R31: =(ROUND((ROUND(((((EU31*1.2)*0.3))*AV31*I31),2)*BS31),2)+ROUND((ROUND(((AE31-(((EU31*1.2)*0.3)))*AV31*I31),2)*BS31),2)) -> 0 | S31: =ROUND((ROUND((AF31*AV31*I31),2)*BA31),2) -> 878.5 | T31: =ROUND(CU31*I31,2) -> 0 | U31: =CV31*I31 -> 1.0839564 | V31: =CW31*I31 -> 0 | W31: =ROUND(CX31*I31,2) -> 0 | X31: =(ROUND((((S31+ROUND((ROUND(((((EU31*1.2)*0.3))*AV31*I31),2)*BS31),2))*AT31)/100),2)+ROUND(((ROUND((ROUND(((AE31-(((EU31*1.2)*0.3)))*AV31*I31),2)*BS31),2)*AT31)/100),2)) -> 834.58 | Y31: =(ROUND((((S31+ROUND((ROUND(((((EU31*1.2)*0.3))*AV31*I31),2)*BS31),2))*AU31)/100),2)+ROUND(((ROUND((ROUND(((AE31-(((EU31*1.2)*0.3)))*AV31*I31),2)*BS31),2)*AU31)/100),2)) -> 465.61 | AA31: 55942968 | AB31: =ROUND((AC31+AD31+AF31),6) -> 14.346 | AC31: =ROUND((((ES31*1)*0)),6) -> 0 | AD31: =ROUND((((((ET31*1.2)*0.3))-(((EU31*1.2)*0.3)))+AE31),6) -> 0 | AE31: =ROUND((((EU31*1.2)*0.3)),6) -> 0 | AF31: =ROUND((((EV31*1.2)*0.3)),6) -> 14.346 | AG31: =ROUND((AP31),6) -> 0 | AH31: =(((EW31*1.2)*0.3)) -> 0.9972 | AI31: =(((EX31*1.2)*0.3)) -> 0 | AJ31: =(AS31) -> 0 | AK31: 40.03 | AL31: 0.18 | AM31: 0 | AN31: 0 | AO31: 39.85 | AP31: 0 | AQ31: 2.77 | AR31: 0 | AS31: 0 | AT31: 95 | AU31: 53 | AV31: 1.087 | AW31: 1 | AZ31: 1 | BA31: 56.35 | BB31: 1 | BC31: 5.61 | BH31: 0 | BI31: 2 | BJ31: ТСН-2001.4 Доп. 81, Сб. 10, т. 134, поз. 7 | BM31: 69 | BN31: 0 | BO31: 4.10-134-7 | BP31: 1 | BQ31: 40 | BR31: 0 | BS31: 56.35 | BT31: 1 | BU31: 1 | BV31: 1 | BW31: 1 | BX31: 1 | BZ31: 95 | CA31: 53 | CE31: 1566 | CF31: 0 | CG31: 0 | CM31: 0 | CN31: Поправка: Гл.12.Прил.8.п.8. 3_12.00.01.11.001 Наименование: При наличии напряженных и стесненных условий производства работ (стесненность, сложность складирования и транспортной логистики и т.п.) для объектов, расположенных в пределах круговой магистральной системы улиц "Садовое кольцо" города Москвы Поправка: Гл.4.Прил.2.2.п.2.2.29_04.00.01.35.003 Наименование: При демонтаже оборудования, предназначенного в лом | CO31: 0 | CP31: =(P31+Q31+S31) -> 878.5 | CQ31: =ROUND((ROUND((AC31*AW31*1),2)*BC31),2) -> 0 | CR31: =(ROUND((ROUND(((((ET31*1.2)*0.3))*AV31*1),2)*BB31),2)+ROUND((ROUND(((AE31-(((EU31*1.2)*0.3)))*AV31*1),2)*BS31),2)) -> 0 | CS31: =(ROUND((ROUND(((((EU31*1.2)*0.3))*AV31*1),2)*BS31),2)+ROUND((ROUND(((AE31-(((EU31*1.2)*0.3)))*AV31*1),2)*BS31),2)) -> 0 | CT31: =ROUND((ROUND((AF31*AV31*1),2)*BA31),2) -> 878.5 | CU31: =AG31 -> 0 | CV31: =(AH31*AV31) -> 1.0839564 | CW31: =AI31 -> 0 | CX31: =AJ31 -> 0 | CY31: =(ROUND((((S31+ROUND((ROUND(((((EU31*1.2)*0.3))*AV31*1),2)*BS31),2))*AT31)/100),2)+ROUND(((ROUND((ROUND(((AE31-(((EU31*1.2)*0.3)))*AV31*1),2)*BS31),2)*AT31)/100),2)) -> 834.58 | CZ31: =(ROUND((((S31+ROUND((ROUND(((((EU31*1.2)*0.3))*AV31*1),2)*BS31),2))*AU31)/100),2)+ROUND(((ROUND((ROUND(((AE31-(((EU31*1.2)*0.3)))*AV31*1),2)*BS31),2)*AU31)/100),2)) -> 465.61 | DB31: 7 | DD31: *1)*0 | DE31: *1,2)*0,3 | DF31: *1,2)*0,3 | DG31: *1,2)*0,3 | DI31: *1,2)*0,3 | DJ31: *1,2)*0,3 | DN31: 0 | DO31: 0 | DP31: 1 | DQ31: 1 | DU31: 1013 | DV31: 1 антенна | DW31: 1 антенна | DX31: 1 | EE31: 55393973 | EF31: 40 | EG31: Монтаж оборудования | EH31: 0 | EJ31: 2 | EK31: 69 | EL31: ТСН-2001.4-10. Монтаж радиотелевизионного и электронного оборудования | EM31: ТСН-2001.4-10-2 | EO31: Поправка: Гл.12.Прил.8.п.8. 3_12.00.01.11.001 Поправка: Гл.4.Прил.2.2.п.2.2.29_04.00.01.35.003 | EQ31: 0 | ER31: 40.03 | ES31: 0.18 | ET31: 0 | EU31: 0 | EV31: 39.85 | EW31: 2.77 | EX31: 0 | EY31: 0 | FQ31: 0 | FR31: 0 | FS31: 0 | FX31: 95 | FY31: 53 | GD31: 1 | GF31: 338733022 | GG31: 2 | GH31: 1 | GI31: 2 | GJ31: 0 | GK31: 0 | GL31: =ROUND(IF(AND(BH31=3,BI31=3,FS31<>0),P31,0),2) -> 0 | GM31: =ROUND(O31+X31+Y31,2)+GX31 -> 2178.69 | GN31: =IF(OR(BI31=0,BI31=1),GM31-GX31,0) -> 0 | GO31: =IF(BI31=2,GM31-GX31,0) -> 2178.69 | GP31: =IF(BI31=4,GM31-GX31,0) -> 0 | GR31: 0 | GS31: 3 | GT31: 0 | GV31: =ROUND((GT31),6) -> 0 | GW31: 1 | GX31: =ROUND(HC31*I31,2) -> 0 | HA31: 0 | HB31: 0 | HC31: =GV31*GW31 -> 0 | HS31: 0 | IK31: 0
A32: 17 | B32: 1 | C32: =ROW(SmtRes!A12) -> 12 | D32: =ROW(EtalonRes!A12) -> 12 | E32: 3 | F32: 4.10-136-1 | G32: Монтаж коробки телевизионной (ответвители, разветвители магистральные, домовые, абонентские), УСС, / демонтаж модуля грозозащиты для антенны | H32: 1 ШТ. | I32: 1 | J32: 0 | K32: 1 | O32: =ROUND(CP32,2) -> 4.31 | P32: =ROUND((ROUND((AC32*AW32*I32),2)*BC32),2) -> 0 | Q32: =(ROUND((ROUND(((((ET32*1.2)*0.3))*AV32*I32),2)*BB32),2)+ROUND((ROUND(((AE32-(((EU32*1.2)*0.3)))*AV32*I32),2)*BS32),2)) -> 0 | R32: =(ROUND((ROUND(((((EU32*1.2)*0.3))*AV32*I32),2)*BS32),2)+ROUND((ROUND(((AE32-(((EU32*1.2)*0.3)))*AV32*I32),2)*BS32),2)) -> 0 | S32: =ROUND((ROUND((AF32*AV32*I32),2)*BA32),2) -> 4.31 | T32: =ROUND(CU32*I32,2) -> 0 | U32: =CV32*I32 -> 0.313056 | V32: =CW32*I32 -> 0 | W32: =ROUND(CX32*I32,2) -> 0 | X32: =(ROUND((((S32+ROUND((ROUND(((((EU32*1.2)*0.3))*AV32*I32),2)*BS32),2))*AT32)/100),2)+ROUND(((ROUND((ROUND(((AE32-(((EU32*1.2)*0.3)))*AV32*I32),2)*BS32),2)*AT32)/100),2)) -> 4.09 | Y32: =(ROUND((((S32+ROUND((ROUND(((((EU32*1.2)*0.3))*AV32*I32),2)*BS32),2))*AU32)/100),2)+ROUND(((ROUND((ROUND(((AE32-(((EU32*1.2)*0.3)))*AV32*I32),2)*BS32),2)*AU32)/100),2)) -> 2.28 | AA32: 55942966 | AB32: =ROUND((AC32+AD32+AF32),6) -> 3.9672 | AC32: =ROUND((((ES32*1)*0)),6) -> 0 | AD32: =ROUND((((((ET32*1.2)*0.3))-(((EU32*1.2)*0.3)))+AE32),6) -> 0 | AE32: =ROUND((((EU32*1.2)*0.3)),6) -> 0 | AF32: =ROUND((((EV32*1.2)*0.3)),6) -> 3.9672 | AG32: =ROUND((AP32),6) -> 0 | AH32: =(((EW32*1.2)*0.3)) -> 0.288 | AI32: =(((EX32*1.2)*0.3)) -> 0 | AJ32: =(AS32) -> 0 | AK32: 11.32 | AL32: 0.3 | AM32: 0 | AN32: 0 | AO32: 11.02 | AP32: 0 | AQ32: 0.8 | AR32: 0 | AS32: 0 | AT32: 95 | AU32: 53 | AV32: 1.087 | AW32: 1 | AZ32: 1 | BA32: 1 | BB32: 1 | BC32: 1 | BH32: 0 | BI32: 2 | BJ32: ТСН-2001.4 Доп. 81, Сб. 10, т. 136, поз. 1 | BM32: 69 | BN32: 0 | BO32: 4.10-136-1 | BP32: 1 | BQ32: 40 | BR32: 0 | BS32: 1 | BT32: 1 | BU32: 1 | BV32: 1 | BW32: 1 | BX32: 1 | BZ32: 95 | CA32: 53 | CE32: 1566 | CF32: 0 | CG32: 0 | CM32: 0 | CN32: Поправка: Гл.12.Прил.8.п.8. 3_12.00.01.11.001 Наименование: При наличии напряженных и стесненных условий производства работ (стесненность, сложность складирования и транспортной логистики и т.п.) для объектов, расположенных в пределах круговой магистральной системы улиц "Садовое кольцо" города Москвы Поправка: Гл.4.Прил.2.2.п.2.2.29_04.00.01.35.003 Наименование: При демонтаже оборудования, предназначенного в лом | CO32: 0 | CP32: =(P32+Q32+S32) -> 4.31 | CQ32: =ROUND((ROUND((AC32*AW32*1),2)*BC32),2) -> 0 | CR32: =(ROUND((ROUND(((((ET32*1.2)*0.3))*AV32*1),2)*BB32),2)+ROUND((ROUND(((AE32-(((EU32*1.2)*0.3)))*AV32*1),2)*BS32),2)) -> 0 | CS32: =(ROUND((ROUND(((((EU32*1.2)*0.3))*AV32*1),2)*BS32),2)+ROUND((ROUND(((AE32-(((EU32*1.2)*0.3)))*AV32*1),2)*BS32),2)) -> 0 | CT32: =ROUND((ROUND((AF32*AV32*1),2)*BA32),2) -> 4.31 | CU32: =AG32 -> 0 | CV32: =(AH32*AV32) -> 0.313056 | CW32: =AI32 -> 0 | CX32: =AJ32 -> 0 | CY32: =(ROUND((((S32+ROUND((ROUND(((((EU32*1.2)*0.3))*AV32*1),2)*BS32),2))*AT32)/100),2)+ROUND(((ROUND((ROUND(((AE32-(((EU32*1.2)*0.3)))*AV32*1),2)*BS32),2)*AT32)/100),2)) -> 4.09 | CZ32: =(ROUND((((S32+ROUND((ROUND(((((EU32*1.2)*0.3))*AV32*1),2)*BS32),2))*AU32)/100),2)+ROUND(((ROUND((ROUND(((AE32-(((EU32*1.2)*0.3)))*AV32*1),2)*BS32),2)*AU32)/100),2)) -> 2.28 | DB32: 9 | DD32: *1)*0 | DE32: *1,2)*0,3 | DF32: *1,2)*0,3 | DG32: *1,2)*0,3 | DI32: *1,2)*0,3 | DJ32: *1,2)*0,3 | DN32: 0 | DO32: 0 | DP32: 1 | DQ32: 1 | DU32: 1013 | DV32: 1 ШТ. | DW32: 1 ШТ. | DX32: 1 | EE32: 55393973 | EF32: 40 | EG32: Монтаж оборудования | EH32: 0 | EJ32: 2 | EK32: 69 | EL32: ТСН-2001.4-10. Монтаж радиотелевизионного и электронного оборудования | EM32: ТСН-2001.4-10-2 | EO32: Поправка: Гл.12.Прил.8.п.8. 3_12.00.01.11.001 Поправка: Гл.4.Прил.2.2.п.2.2.29_04.00.01.35.003 | EQ32: 0 | ER32: 11.32 | ES32: 0.3 | ET32: 0 | EU32: 0 | EV32: 11.02 | EW32: 0.8 | EX32: 0 | EY32: 0 | FQ32: 0 | FR32: 0 | FS32: 0 | FX32: 95 | FY32: 53 | GD32: 1 | GF32: -1909085749 | GG32: 2 | GH32: 1 | GI32: 2 | GJ32: 0 | GK32: 0 | GL32: =ROUND(IF(AND(BH32=3,BI32=3,FS32<>0),P32,0),2) -> 0 | GM32: =ROUND(O32+X32+Y32,2)+GX32 -> 10.68 | GN32: =IF(OR(BI32=0,BI32=1),GM32-GX32,0) -> 0 | GO32: =IF(BI32=2,GM32-GX32,0) -> 10.68 | GP32: =IF(BI32=4,GM32-GX32,0) -> 0 | GR32: 0 | GS32: 3 | GT32: 0 | GV32: =ROUND((GT32),6) -> 0 | GW32: 1 | GX32: =ROUND(HC32*I32,2) -> 0 | HA32: 0 | HB32: 0 | HC32: =GV32*GW32 -> 0 | HS32: 0 | IK32: 0
A33: 17 | B33: 1 | C33: =ROW(SmtRes!A14) -> 14 | D33: =ROW(EtalonRes!A14) -> 14 | E33: 3 | F33: 4.10-136-1 | G33: Монтаж коробки телевизионной (ответвители, разветвители магистральные, домовые, абонентские), УСС, / демонтаж модуля грозозащиты для антенны | H33: 1 ШТ. | I33: 1 | J33: 0 | K33: 1 | O33: =ROUND(CP33,2) -> 242.87 | P33: =ROUND((ROUND((AC33*AW33*I33),2)*BC33),2) -> 0 | Q33: =(ROUND((ROUND(((((ET33*1.2)*0.3))*AV33*I33),2)*BB33),2)+ROUND((ROUND(((AE33-(((EU33*1.2)*0.3)))*AV33*I33),2)*BS33),2)) -> 0 | R33: =(ROUND((ROUND(((((EU33*1.2)*0.3))*AV33*I33),2)*BS33),2)+ROUND((ROUND(((AE33-(((EU33*1.2)*0.3)))*AV33*I33),2)*BS33),2)) -> 0 | S33: =ROUND((ROUND((AF33*AV33*I33),2)*BA33),2) -> 242.87 | T33: =ROUND(CU33*I33,2) -> 0 | U33: =CV33*I33 -> 0.313056 | V33: =CW33*I33 -> 0 | W33: =ROUND(CX33*I33,2) -> 0 | X33: =(ROUND((((S33+ROUND((ROUND(((((EU33*1.2)*0.3))*AV33*I33),2)*BS33),2))*AT33)/100),2)+ROUND(((ROUND((ROUND(((AE33-(((EU33*1.2)*0.3)))*AV33*I33),2)*BS33),2)*AT33)/100),2)) -> 230.73 | Y33: =(ROUND((((S33+ROUND((ROUND(((((EU33*1.2)*0.3))*AV33*I33),2)*BS33),2))*AU33)/100),2)+ROUND(((ROUND((ROUND(((AE33-(((EU33*1.2)*0.3)))*AV33*I33),2)*BS33),2)*AU33)/100),2)) -> 128.72 | AA33: 55942968 | AB33: =ROUND((AC33+AD33+AF33),6) -> 3.9672 | AC33: =ROUND((((ES33*1)*0)),6) -> 0 | AD33: =ROUND((((((ET33*1.2)*0.3))-(((EU33*1.2)*0.3)))+AE33),6) -> 0 | AE33: =ROUND((((EU33*1.2)*0.3)),6) -> 0 | AF33: =ROUND((((EV33*1.2)*0.3)),6) -> 3.9672 | AG33: =ROUND((AP33),6) -> 0 | AH33: =(((EW33*1.2)*0.3)) -> 0.288 | AI33: =(((EX33*1.2)*0.3)) -> 0 | AJ33: =(AS33) -> 0 | AK33: 11.32 | AL33: 0.3 | AM33: 0 | AN33: 0 | AO33: 11.02 | AP33: 0 | AQ33: 0.8 | AR33: 0 | AS33: 0 | AT33: 95 | AU33: 53 | AV33: 1.087 | AW33: 1 | AZ33: 1 | BA33: 56.35 | BB33: 1 | BC33: 7.37 | BH33: 0 | BI33: 2 | BJ33: ТСН-2001.4 Доп. 81, Сб. 10, т. 136, поз. 1 | BM33: 69 | BN33: 0 | BO33: 4.10-136-1 | BP33: 1 | BQ33: 40 | BR33: 0 | BS33: 56.35 | BT33: 1 | BU33: 1 | BV33: 1 | BW33: 1 | BX33: 1 | BZ33: 95 | CA33: 53 | CE33: 1566 | CF33: 0 | CG33: 0 | CM33: 0 | CN33: Поправка: Гл.12.Прил.8.п.8. 3_12.00.01.11.001 Наименование: При наличии напряженных и стесненных условий производства работ (стесненность, сложность складирования и транспортной логистики и т.п.) для объектов, расположенных в пределах круговой магистральной системы улиц "Садовое кольцо" города Москвы Поправка: Гл.4.Прил.2.2.п.2.2.29_04.00.01.35.003 Наименование: При демонтаже оборудования, предназначенного в лом | CO33: 0 | CP33: =(P33+Q33+S33) -> 242.87 | CQ33: =ROUND((ROUND((AC33*AW33*1),2)*BC33),2) -> 0 | CR33: =(ROUND((ROUND(((((ET33*1.2)*0.3))*AV33*1),2)*BB33),2)+ROUND((ROUND(((AE33-(((EU33*1.2)*0.3)))*AV33*1),2)*BS33),2)) -> 0 | CS33: =(ROUND((ROUND(((((EU33*1.2)*0.3))*AV33*1),2)*BS33),2)+ROUND((ROUND(((AE33-(((EU33*1.2)*0.3)))*AV33*1),2)*BS33),2)) -> 0 | CT33: =ROUND((ROUND((AF33*AV33*1),2)*BA33),2) -> 242.87 | CU33: =AG33 -> 0 | CV33: =(AH33*AV33) -> 0.313056 | CW33: =AI33 -> 0 | CX33: =AJ33 -> 0 | CY33: =(ROUND((((S33+ROUND((ROUND(((((EU33*1.2)*0.3))*AV33*1),2)*BS33),2))*AT33)/100),2)+ROUND(((ROUND((ROUND(((AE33-(((EU33*1.2)*0.3)))*AV33*1),2)*BS33),2)*AT33)/100),2)) -> 230.73 | CZ33: =(ROUND((((S33+ROUND((ROUND(((((EU33*1.2)*0.3))*AV33*1),2)*BS33),2))*AU33)/100),2)+ROUND(((ROUND((ROUND(((AE33-(((EU33*1.2)*0.3)))*AV33*1),2)*BS33),2)*AU33)/100),2)) -> 128.72 | DB33: 11 | DD33: *1)*0 | DE33: *1,2)*0,3 | DF33: *1,2)*0,3 | DG33: *1,2)*0,3 | DI33: *1,2)*0,3 | DJ33: *1,2)*0,3 | DN33: 0 | DO33: 0 | DP33: 1 | DQ33: 1 | DU33: 1013 | DV33: 1 ШТ. | DW33: 1 ШТ. | DX33: 1 | EE33: 55393973 | EF33: 40 | EG33: Монтаж оборудования | EH33: 0 | EJ33: 2 | EK33: 69 | EL33: ТСН-2001.4-10. Монтаж радиотелевизионного и электронного оборудования | EM33: ТСН-2001.4-10-2 | EO33: Поправка: Гл.12.Прил.8.п.8. 3_12.00.01.11.001 Поправка: Гл.4.Прил.2.2.п.2.2.29_04.00.01.35.003 | EQ33: 0 | ER33: 11.32 | ES33: 0.3 | ET33: 0 | EU33: 0 | EV33: 11.02 | EW33: 0.8 | EX33: 0 | EY33: 0 | FQ33: 0 | FR33: 0 | FS33: 0 | FX33: 95 | FY33: 53 | GD33: 1 | GF33: -1909085749 | GG33: 2 | GH33: 1 | GI33: 2 | GJ33: 0 | GK33: 0 | GL33: =ROUND(IF(AND(BH33=3,BI33=3,FS33<>0),P33,0),2) -> 0 | GM33: =ROUND(O33+X33+Y33,2)+GX33 -> 602.32 | GN33: =IF(OR(BI33=0,BI33=1),GM33-GX33,0) -> 0 | GO33: =IF(BI33=2,GM33-GX33,0) -> 602.32 | GP33: =IF(BI33=4,GM33-GX33,0) -> 0 | GR33: 0 | GS33: 3 | GT33: 0 | GV33: =ROUND((GT33),6) -> 0 | GW33: 1 | GX33: =ROUND(HC33*I33,2) -> 0 | HA33: 0 | HB33: 0 | HC33: =GV33*GW33 -> 0 | HS33: 0 | IK33: 0
A34: 17 | B34: 1 | C34: =ROW(SmtRes!A18) -> 18 | D34: =ROW(EtalonRes!A18) -> 18 | E34: 4 | F34: 4.10-86-1 | G34: Монтаж электрочасов вторичных для помещений односторонних на стене / демонтаж часов повторителей | H34: 1 ШТ. | I34: 3 | J34: 0 | K34: 3 | O34: =ROUND(CP34,2) -> 26.91 | P34: =ROUND((ROUND((AC34*AW34*I34),2)*BC34),2) -> 0 | Q34: =(ROUND((ROUND(((((ET34*1.2)*0.3))*AV34*I34),2)*BB34),2)+ROUND((ROUND(((AE34-(((EU34*1.2)*0.3)))*AV34*I34),2)*BS34),2)) -> 0 | R34: =(ROUND((ROUND(((((EU34*1.2)*0.3))*AV34*I34),2)*BS34),2)+ROUND((ROUND(((AE34-(((EU34*1.2)*0.3)))*AV34*I34),2)*BS34),2)) -> 0 | S34: =ROUND((ROUND((AF34*AV34*I34),2)*BA34),2) -> 26.91 | T34: =ROUND(CU34*I34,2) -> 0 | U34: =CV34*I34 -> 2.26152 | V34: =CW34*I34 -> 0 | W34: =ROUND(CX34*I34,2) -> 0 | X34: =(ROUND((((S34+ROUND((ROUND(((((EU34*1.2)*0.3))*AV34*I34),2)*BS34),2))*AT34)/100),2)+ROUND(((ROUND((ROUND(((AE34-(((EU34*1.2)*0.3)))*AV34*I34),2)*BS34),2)*AT34)/100),2)) -> 24.22 | Y34: =(ROUND((((S34+ROUND((ROUND(((((EU34*1.2)*0.3))*AV34*I34),2)*BS34),2))*AU34)/100),2)+ROUND(((ROUND((ROUND(((AE34-(((EU34*1.2)*0.3)))*AV34*I34),2)*BS34),2)*AU34)/100),2)) -> 12.38 | AA34: 55942966 | AB34: =ROUND((AC34+AD34+AF34),6) -> 8.568 | AC34: =ROUND((((ES34*1)*0)),6) -> 0 | AD34: =ROUND((((((ET34*1.2)*0.3))-(((EU34*1.2)*0.3)))+AE34),6) -> 0 | AE34: =ROUND((((EU34*1.2)*0.3)),6) -> 0 | AF34: =ROUND((((EV34*1.2)*0.3)),6) -> 8.568 | AG34: =ROUND((AP34),6) -> 0 | AH34: =(((EW34*1.2)*0.3)) -> 0.72 | AI34: =(((EX34*1.2)*0.3)) -> 0 | AJ34: =(AS34) -> 0 | AK34: 24.38 | AL34: 0.58 | AM34: 0 | AN34: 0 | AO34: 23.8 | AP34: 0 | AQ34: 2 | AR34: 0 | AS34: 0 | AT34: 90 | AU34: 46 | AV34: 1.047 | AW34: 1 | AZ34: 1 | BA34: 1 | BB34: 1 | BC34: 1 | BH34: 0 | BI34: 2 | BJ34: ТСН-2001.4 Доп. 81, Сб. 10, т. 86, поз. 1 | BM34: 68 | BN34: 0 | BO34: 4.10-86-1 | BP34: 1 | BQ34: 40 | BR34: 0 | BS34: 1 | BT34: 1 | BU34: 1 | BV34: 1 | BW34: 1 | BX34: 1 | BZ34: 90 | CA34: 46 | CE34: 1566 | CF34: 0 | CG34: 0 | CM34: 0 | CN34: Поправка: Гл.12.Прил.8.п.8. 3_12.00.01.11.001 Наименование: При наличии напряженных и стесненных условий производства работ (стесненность, сложность складирования и транспортной логистики и т.п.) для объектов, расположенных в пределах круговой магистральной системы улиц "Садовое кольцо" города Москвы Поправка: Гл.4.Прил.2.2.п.2.2.29_04.00.01.35.003 Наименование: При демонтаже оборудования, предназначенного в лом | CO34: 0 | CP34: =(P34+Q34+S34) -> 26.91 | CQ34: =ROUND((ROUND((AC34*AW34*1),2)*BC34),2) -> 0 | CR34: =(ROUND((ROUND(((((ET34*1.2)*0.3))*AV34*1),2)*BB34),2)+ROUND((ROUND(((AE34-(((EU34*1.2)*0.3)))*AV34*1),2)*BS34),2)) -> 0 | CS34: =(ROUND((ROUND(((((EU34*1.2)*0.3))*AV34*1),2)*BS34),2)+ROUND((ROUND(((AE34-(((EU34*1.2)*0.3)))*AV34*1),2)*BS34),2)) -> 0 | CT34: =ROUND((ROUND((AF34*AV34*1),2)*BA34),2) -> 8.97 | CU34: =AG34 -> 0 | CV34: =(AH34*AV34) -> 0.75384 | CW34: =AI34 -> 0 | CX34: =AJ34 -> 0 | CY34: =(ROUND((((S34+ROUND((ROUND(((((EU34*1.2)*0.3))*AV34*1),2)*BS34),2))*AT34)/100),2)+ROUND(((ROUND((ROUND(((AE34-(((EU34*1.2)*0.3)))*AV34*1),2)*BS34),2)*AT34)/100),2)) -> 24.22 | CZ34: =(ROUND((((S34+ROUND((ROUND(((((EU34*1.2)*0.3))*AV34*1),2)*BS34),2))*AU34)/100),2)+ROUND(((ROUND((ROUND(((AE34-(((EU34*1.2)*0.3)))*AV34*1),2)*BS34),2)*AU34)/100),2)) -> 12.38 | DB34: 13 | DD34: *1)*0 | DE34: *1,2)*0,3 | DF34: *1,2)*0,3 | DG34: *1,2)*0,3 | DI34: *1,2)*0,3 | DJ34: *1,2)*0,3 | DN34: 0 | DO34: 0 | DP34: 1 | DQ34: 1 | DU34: 1013 | DV34: 1 ШТ. | DW34: 1 ШТ. | DX34: 1 | EE34: 55393972 | EF34: 40 | EG34: Монтаж оборудования | EH34: 0 | EJ34: 2 | EK34: 68 | EL34: ТСН-2001.4-10. Прокладка и монтаж сетей связи | EM34: ТСН-2001.4-10-1 | EO34: Поправка: Гл.12.Прил.8.п.8. 3_12.00.01.11.001 Поправка: Гл.4.Прил.2.2.п.2.2.29_04.00.01.35.003 | EQ34: 0 | ER34: 24.38 | ES34: 0.58 | ET34: 0 | EU34: 0 | EV34: 23.8 | EW34: 2 | EX34: 0 | EY34: 0 | FQ34: 0 | FR34: 0 | FS34: 0 | FX34: 90 | FY34: 46 | GD34: 1 | GF34: -1108641318 | GG34: 2 | GH34: 1 | GI34: 2 | GJ34: 0 | GK34: 0 | GL34: =ROUND(IF(AND(BH34=3,BI34=3,FS34<>0),P34,0),2) -> 0 | GM34: =ROUND(O34+X34+Y34,2)+GX34 -> 63.51 | GN34: =IF(OR(BI34=0,BI34=1),GM34-GX34,0) -> 0 | GO34: =IF(BI34=2,GM34-GX34,0) -> 63.51 | GP34: =IF(BI34=4,GM34-GX34,0) -> 0 | GR34: 0 | GS34: 3 | GT34: 0 | GV34: =ROUND((GT34),6) -> 0 | GW34: 1 | GX34: =ROUND(HC34*I34,2) -> 0 | HA34: 0 | HB34: 0 | HC34: =GV34*GW34 -> 0 | HS34: 0 | IK34: 0
A35: 17 | B35: 1 | C35: =ROW(SmtRes!A22) -> 22 | D35: =ROW(EtalonRes!A22) -> 22 | E35: 4 | F35: 4.10-86-1 | G35: Монтаж электрочасов вторичных для помещений односторонних на стене / демонтаж часов повторителей | H35: 1 ШТ. | I35: 3 | J35: 0 | K35: 3 | O35: =ROUND(CP35,2) -> 1516.38 | P35: =ROUND((ROUND((AC35*AW35*I35),2)*BC35),2) -> 0 | Q35: =(ROUND((ROUND(((((ET35*1.2)*0.3))*AV35*I35),2)*BB35),2)+ROUND((ROUND(((AE35-(((EU35*1.2)*0.3)))*AV35*I35),2)*BS35),2)) -> 0 | R35: =(ROUND((ROUND(((((EU35*1.2)*0.3))*AV35*I35),2)*BS35),2)+ROUND((ROUND(((AE35-(((EU35*1.2)*0.3)))*AV35*I35),2)*BS35),2)) -> 0 | S35: =ROUND((ROUND((AF35*AV35*I35),2)*BA35),2) -> 1516.38 | T35: =ROUND(CU35*I35,2) -> 0 | U35: =CV35*I35 -> 2.26152 | V35: =CW35*I35 -> 0 | W35: =ROUND(CX35*I35,2) -> 0 | X35: =(ROUND((((S35+ROUND((ROUND(((((EU35*1.2)*0.3))*AV35*I35),2)*BS35),2))*AT35)/100),2)+ROUND(((ROUND((ROUND(((AE35-(((EU35*1.2)*0.3)))*AV35*I35),2)*BS35),2)*AT35)/100),2)) -> 1364.74 | Y35: =(ROUND((((S35+ROUND((ROUND(((((EU35*1.2)*0.3))*AV35*I35),2)*BS35),2))*AU35)/100),2)+ROUND(((ROUND((ROUND(((AE35-(((EU35*1.2)*0.3)))*AV35*I35),2)*BS35),2)*AU35)/100),2)) -> 697.53 | AA35: 55942968 | AB35: =ROUND((AC35+AD35+AF35),6) -> 8.568 | AC35: =ROUND((((ES35*1)*0)),6) -> 0 | AD35: =ROUND((((((ET35*1.2)*0.3))-(((EU35*1.2)*0.3)))+AE35),6) -> 0 | AE35: =ROUND((((EU35*1.2)*0.3)),6) -> 0 | AF35: =ROUND((((EV35*1.2)*0.3)),6) -> 8.568 | AG35: =ROUND((AP35),6) -> 0 | AH35: =(((EW35*1.2)*0.3)) -> 0.72 | AI35: =(((EX35*1.2)*0.3)) -> 0 | AJ35: =(AS35) -> 0 | AK35: 24.38 | AL35: 0.58 | AM35: 0 | AN35: 0 | AO35: 23.8 | AP35: 0 | AQ35: 2 | AR35: 0 | AS35: 0 | AT35: 90 | AU35: 46 | AV35: 1.047 | AW35: 1 | AZ35: 1 | BA35: 56.35 | BB35: 1 | BC35: 7.03 | BH35: 0 | BI35: 2 | BJ35: ТСН-2001.4 Доп. 81, Сб. 10, т. 86, поз. 1 | BM35: 68 | BN35: 0 | BO35: 4.10-86-1 | BP35: 1 | BQ35: 40 | BR35: 0 | BS35: 56.35 | BT35: 1 | BU35: 1 | BV35: 1 | BW35: 1 | BX35: 1 | BZ35: 90 | CA35: 46 | CE35: 1566 | CF35: 0 | CG35: 0 | CM35: 0 | CN35: Поправка: Гл.12.Прил.8.п.8. 3_12.00.01.11.001 Наименование: При наличии напряженных и стесненных условий производства работ (стесненность, сложность складирования и транспортной логистики и т.п.) для объектов, расположенных в пределах круговой магистральной системы улиц "Садовое кольцо" города Москвы Поправка: Гл.4.Прил.2.2.п.2.2.29_04.00.01.35.003 Наименование: При демонтаже оборудования, предназначенного в лом | CO35: 0 | CP35: =(P35+Q35+S35) -> 1516.38 | CQ35: =ROUND((ROUND((AC35*AW35*1),2)*BC35),2) -> 0 | CR35: =(ROUND((ROUND(((((ET35*1.2)*0.3))*AV35*1),2)*BB35),2)+ROUND((ROUND(((AE35-(((EU35*1.2)*0.3)))*AV35*1),2)*BS35),2)) -> 0 | CS35: =(ROUND((ROUND(((((EU35*1.2)*0.3))*AV35*1),2)*BS35),2)+ROUND((ROUND(((AE35-(((EU35*1.2)*0.3)))*AV35*1),2)*BS35),2)) -> 0 | CT35: =ROUND((ROUND((AF35*AV35*1),2)*BA35),2) -> 505.46 | CU35: =AG35 -> 0 | CV35: =(AH35*AV35) -> 0.75384 | CW35: =AI35 -> 0 | CX35: =AJ35 -> 0 | CY35: =(ROUND((((S35+ROUND((ROUND(((((EU35*1.2)*0.3))*AV35*1),2)*BS35),2))*AT35)/100),2)+ROUND(((ROUND((ROUND(((AE35-(((EU35*1.2)*0.3)))*AV35*1),2)*BS35),2)*AT35)/100),2)) -> 1364.74 | CZ35: =(ROUND((((S35+ROUND((ROUND(((((EU35*1.2)*0.3))*AV35*1),2)*BS35),2))*AU35)/100),2)+ROUND(((ROUND((ROUND(((AE35-(((EU35*1.2)*0.3)))*AV35*1),2)*BS35),2)*AU35)/100),2)) -> 697.53 | DB35: 15 | DD35: *1)*0 | DE35: *1,2)*0,3 | DF35: *1,2)*0,3 | DG35: *1,2)*0,3 | DI35: *1,2)*0,3 | DJ35: *1,2)*0,3 | DN35: 0 | DO35: 0 | DP35: 1 | DQ35: 1 | DU35: 1013 | DV35: 1 ШТ. | DW35: 1 ШТ. | DX35: 1 | EE35: 55393972 | EF35: 40 | EG35: Монтаж оборудования | EH35: 0 | EJ35: 2 | EK35: 68 | EL35: ТСН-2001.4-10. Прокладка и монтаж сетей связи | EM35: ТСН-2001.4-10-1 | EO35: Поправка: Гл.12.Прил.8.п.8. 3_12.00.01.11.001 Поправка: Гл.4.Прил.2.2.п.2.2.29_04.00.01.35.003 | EQ35: 0 | ER35: 24.38 | ES35: 0.58 | ET35: 0 | EU35: 0 | EV35: 23.8 | EW35: 2 | EX35: 0 | EY35: 0 | FQ35: 0 | FR35: 0 | FS35: 0 | FX35: 90 | FY35: 46 | GD35: 1 | GF35: -1108641318 | GG35: 2 | GH35: 1 | GI35: 2 | GJ35: 0 | GK35: 0 | GL35: =ROUND(IF(AND(BH35=3,BI35=3,FS35<>0),P35,0),2) -> 0 | GM35: =ROUND(O35+X35+Y35,2)+GX35 -> 3578.65 | GN35: =IF(OR(BI35=0,BI35=1),GM35-GX35,0) -> 0 | GO35: =IF(BI35=2,GM35-GX35,0) -> 3578.65 | GP35: =IF(BI35=4,GM35-GX35,0) -> 0 | GR35: 0 | GS35: 3 | GT35: 0 | GV35: =ROUND((GT35),6) -> 0 | GW35: 1 | GX35: =ROUND(HC35*I35,2) -> 0 | HA35: 0 | HB35: 0 | HC35: =GV35*GW35 -> 0 | HS35: 0 | IK35: 0
A37: 51 | B37: =B24 -> 1 | C37: =A24 -> 4 | D37: =ROW(A24) -> 24 | F37: =IF(F24<>"",F24,"") -> Новый раздел | G37: =IF(G24<>"",G24,"") -> Демонтажные работы (Письмо от АНО «РГТ» об утверждении объёмов демонтажных работ) | H37: 0 | O37: =ROUND(AB37,2) -> 62.38 | P37: =ROUND(AC37,2) -> 0 | Q37: =ROUND(AD37,2) -> 0 | R37: =ROUND(AE37,2) -> 0 | S37: =ROUND(AF37,2) -> 62.38 | T37: =ROUND(AG37,2) -> 0 | U37: =AH37 -> 4.7892924 | V37: =AI37 -> 0 | W37: =ROUND(AJ37,2) -> 0 | X37: =ROUND(AK37,2) -> 57.13 | Y37: =ROUND(AL37,2) -> 30.08 | AB37: =ROUND(SUMIF(AA28:AA35,"=55942966",O28:O35),2) -> 62.38 | AC37: =ROUND(SUMIF(AA28:AA35,"=55942966",P28:P35),2) -> 0 | AD37: =ROUND(SUMIF(AA28:AA35,"=55942966",Q28:Q35),2) -> 0 | AE37: =ROUND(SUMIF(AA28:AA35,"=55942966",R28:R35),2) -> 0 | AF37: =ROUND(SUMIF(AA28:AA35,"=55942966",S28:S35),2) -> 62.38 | AG37: =ROUND(SUMIF(AA28:AA35,"=55942966",T28:T35),2) -> 0 | AH37: =SUMIF(AA28:AA35,"=55942966",U28:U35) -> 4.7892924 | AI37: =SUMIF(AA28:AA35,"=55942966",V28:V35) -> 0 | AJ37: =ROUND(SUMIF(AA28:AA35,"=55942966",W28:W35),2) -> 0 | AK37: =ROUND(SUMIF(AA28:AA35,"=55942966",X28:X35),2) -> 57.13 | AL37: =ROUND(SUMIF(AA28:AA35,"=55942966",Y28:Y35),2) -> 30.08 | AO37: =ROUND(BX37,2) -> 0 | AP37: =ROUND(BY37,2) -> 0 | AQ37: =ROUND(BZ37,2) -> 0 | AR37: =ROUND(CA37,2) -> 149.59 | AS37: =ROUND(CB37,2) -> 0 | AT37: =ROUND(CC37,2) -> 149.59 | AU37: =ROUND(CD37,2) -> 0 | AV37: =ROUND(CE37,2) -> 0 | ... BD37: =ROUND(CM37,2) -> 0 | BX37: =ROUND(SUMIF(AA28:AA35,"=55942966",FQ28:FQ35),2) -> 0 | BY37: =ROUND(SUMIF(AA28:AA35,"=55942966",FR28:FR35),2) -> 0 | BZ37: =ROUND(SUMIF(AA28:AA35,"=55942966",GL28:GL35),2) -> 0 | CA37: =ROUND(SUMIF(AA28:AA35,"=55942966",GM28:GM35),2) -> 149.59 | CB37: =ROUND(SUMIF(AA28:AA35,"=55942966",GN28:GN35),2) -> 0 | CC37: =ROUND(SUMIF(AA28:AA35,"=55942966",GO28:GO35),2) -> 149.59 | CD37: =ROUND(SUMIF(AA28:AA35,"=55942966",GP28:GP35),2) -> 0 | CE37: =AC37-BX37 -> 0 | CF37: =AC37-BY37 -> 0 | CG37: =BX37-BZ37 -> 0 | CH37: =AC37-BX37-BY37+BZ37 -> 0 | CI37: =BY37-BZ37 -> 0 | CJ37: =ROUND(SUMIF(AA28:AA35,"=55942966",GX28:GX35),2) -> 0 | CK37: =ROUND(SUMIF(AA28:AA35,"=55942966",GY28:GY35),2) -> 0 | CL37: =ROUND(SUMIF(AA28:AA35,"=55942966",GZ28:GZ35),2) -> 0 | CM37: =ROUND(SUMIF(AA28:AA35,"=55942966",HD28:HD35),2) -> 0 | DG37: =ROUND(DT37,2) -> 3515.12 | DH37: =ROUND(DU37,2) -> 0 | DI37: =ROUND(DV37,2) -> 0 | DJ37: =ROUND(DW37,2) -> 0 | DK37: =ROUND(DX37,2) -> 3515.12 | DL37: =ROUND(DY37,2) -> 0 | DM37: =DZ37 -> 4.7892924 | DN37: =EA37 -> 0 | DO37: =ROUND(EB37,2) -> 0 | DP37: =ROUND(EC37,2) -> 3219.68 | DQ37: =ROUND(ED37,2) -> 1695.45 | DT37: =ROUND(SUMIF(AA28:AA35,"=55942968",O28:O35),2) -> 3515.12 | DU37: =ROUND(SUMIF(AA28:AA35,"=55942968",P28:P35),2) -> 0 | DV37: =ROUND(SUMIF(AA28:AA35,"=55942968",Q28:Q35),2) -> 0 | DW37: =ROUND(SUMIF(AA28:AA35,"=55942968",R28:R35),2) -> 0 | DX37: =ROUND(SUMIF(AA28:AA35,"=55942968",S28:S35),2) -> 3515.12 | DY37: =ROUND(SUMIF(AA28:AA35,"=55942968",T28:T35),2) -> 0 | DZ37: =SUMIF(AA28:AA35,"=55942968",U28:U35) -> 4.7892924 | EA37: =SUMIF(AA28:AA35,"=55942968",V28:V35) -> 0 | EB37: =ROUND(SUMIF(AA28:AA35,"=55942968",W28:W35),2) -> 0 | EC37: =ROUND(SUMIF(AA28:AA35,"=55942968",X28:X35),2) -> 3219.68 | ED37: =ROUND(SUMIF(AA28:AA35,"=55942968",Y28:Y35),2) -> 1695.45 | EG37: =ROUND(FP37,2) -> 0 | EH37: =ROUND(FQ37,2) -> 0 | EI37: =ROUND(FR37,2) -> 0 | EJ37: =ROUND(FS37,2) -> 8430.25 | EK37: =ROUND(FT37,2) -> 0 | EL37: =ROUND(FU37,2) -> 8430.25 | EM37: =ROUND(FV37,2) -> 0 | EN37: =ROUND(FW37,2) -> 0 | ... EV37: =ROUND(GE37,2) -> 0 | FP37: =ROUND(SUMIF(AA28:AA35,"=55942968",FQ28:FQ35),2) -> 0 | FQ37: =ROUND(SUMIF(AA28:AA35,"=55942968",FR28:FR35),2) -> 0 | FR37: =ROUND(SUMIF(AA28:AA35,"=55942968",GL28:GL35),2) -> 0 | FS37: =ROUND(SUMIF(AA28:AA35,"=55942968",GM28:GM35),2) -> 8430.25 | FT37: =ROUND(SUMIF(AA28:AA35,"=55942968",GN28:GN35),2) -> 0 | FU37: =ROUND(SUMIF(AA28:AA35,"=55942968",GO28:GO35),2) -> 8430.25 | FV37: =ROUND(SUMIF(AA28:AA35,"=55942968",GP28:GP35),2) -> 0 | FW37: =DU37-FP37 -> 0 | FX37: =DU37-FQ37 -> 0 | FY37: =FP37-FR37 -> 0 | FZ37: =DU37-FP37-FQ37+FR37 -> 0 | GA37: =FQ37-FR37 -> 0 | GB37: =ROUND(SUMIF(AA28:AA35,"=55942968",GX28:GX35),2) -> 0 | GC37: =ROUND(SUMIF(AA28:AA35,"=55942968",GY28:GY35),2) -> 0 | GD37: =ROUND(SUMIF(AA28:AA35,"=55942968",GZ28:GZ35),2) -> 0 | GE37: =ROUND(SUMIF(AA28:AA35,"=55942968",HD28:HD35),2) -> 0 | GX37: 0
A39: 50 | B39: 0 | C39: 0 | D39: 1 | E39: 201 | F39: =ROUND(Source!O37,O39) -> 62.38 | G39: ПЗ | H39: Прямые затраты | K39: 201 | L39: 1 | M39: 3 | O39: 2 | P39: =ROUND(Source!DG37,O39) -> 3515.12 | W39: 62.38 | X39: 1 | Y39: 62.38 | Z39: 3515.12 | AA39: 1 | AB39: 3515.12
A40: 50 | B40: 0 | C40: 0 | D40: 1 | E40: 202 | F40: =ROUND(Source!P37,O40) -> 0 | G40: СтМатОб | H40: Стоимость материальных ресурсов (всего) | K40: 202 | L40: 2 | M40: 3 | O40: 2 | P40: =ROUND(Source!DH37,O40) -> 0 | W40: 0 | X40: 1 | Y40: 0 | Z40: 0 | AA40: 1 | AB40: 0
A41: 50 | B41: 0 | C41: 0 | D41: 1 | E41: 222 | F41: =ROUND(Source!AO37,O41) -> 0 | G41: СтМатОбЗак | H41: Стоимость материалов и оборудования заказчика | K41: 222 | L41: 3 | M41: 3 | O41: 2 | P41: =ROUND(Source!EG37,O41) -> 0 | W41: 0 | X41: 1 | Y41: 0 | Z41: 0 | AA41: 1 | AB41: 0
A42: 50 | B42: 0 | C42: 0 | D42: 1 | E42: 225 | F42: =ROUND(Source!AV37,O42) -> 0 | G42: СтМатОбПод | H42: Стоимость материалов и оборудования подрядчика | K42: 225 | L42: 4 | M42: 3 | O42: 2 | P42: =ROUND(Source!EN37,O42) -> 0 | W42: 0 | X42: 1 | Y42: 0 | Z42: 0 | AA42: 1 | AB42: 0
A43: 50 | B43: 0 | C43: 0 | D43: 1 | E43: 226 | F43: =ROUND(Source!AW37,O43) -> 0 | G43: СтМат | H43: Стоимость материалов (всего) | K43: 226 | L43: 5 | M43: 3 | O43: 2 | P43: =ROUND(Source!EO37,O43) -> 0 | W43: 0 | X43: 1 | Y43: 0 | Z43: 0 | AA43: 1 | AB43: 0
A44: 50 | B44: 0 | C44: 0 | D44: 1 | E44: 227 | F44: =ROUND(Source!AX37,O44) -> 0 | G44: СтМатЗак | H44: Стоимость материалов заказчика | K44: 227 | L44: 6 | M44: 3 | O44: 2 | P44: =ROUND(Source!EP37,O44) -> 0 | W44: 0 | X44: 1 | Y44: 0 | Z44: 0 | AA44: 1 | AB44: 0
A45: 50 | B45: 0 | C45: 0 | D45: 1 | E45: 228 | F45: =ROUND(Source!AY37,O45) -> 0 | G45: СтМатПод | H45: Стоимость материалов подрядчика | K45: 228 | L45: 7 | M45: 3 | O45: 2 | P45: =ROUND(Source!EQ37,O45) -> 0 | W45: 0 | X45: 1 | Y45: 0 | Z45: 0 | AA45: 1 | AB45: 0
A46: 50 | B46: 0 | C46: 0 | D46: 1 | E46: 216 | F46: =ROUND(Source!AP37,O46) -> 0 | G46: Оборуд | H46: Стоимость оборудования (всего) | K46: 216 | L46: 8 | M46: 3 | O46: 2 | P46: =ROUND(Source!EH37,O46) -> 0 | W46: 0 | X46: 1 | Y46: 0 | Z46: 0 | AA46: 1 | AB46: 0
A47: 50 | B47: 0 | C47: 0 | D47: 1 | E47: 223 | F47: =ROUND(Source!AQ37,O47) -> 0 | G47: ОборудЗак | H47: Стоимость оборудования заказчика | K47: 223 | L47: 9 | M47: 3 | O47: 2 | P47: =ROUND(Source!EI37,O47) -> 0 | W47: 0 | X47: 1 | Y47: 0 | Z47: 0 | AA47: 1 | AB47: 0
A48: 50 | B48: 0 | C48: 0 | D48: 1 | E48: 229 | F48: =ROUND(Source!AZ37,O48) -> 0 | G48: ОборудПод | H48: Стоимость оборудования подрядчика | K48: 229 | L48: 10 | M48: 3 | O48: 2 | P48: =ROUND(Source!ER37,O48) -> 0 | W48: 0 | X48: 1 | Y48: 0 | Z48: 0 | AA48: 1 | AB48: 0
A49: 50 | B49: 0 | C49: 0 | D49: 1 | E49: 203 | F49: =ROUND(Source!Q37,O49) -> 0 | G49: ЭММ | H49: Эксплуатация машин | K49: 203 | L49: 11 | M49: 3 | O49: 2 | P49: =ROUND(Source!DI37,O49) -> 0 | W49: 0 | X49: 1 | Y49: 0 | Z49: 0 | AA49: 1 | AB49: 0
A50: 50 | B50: 0 | C50: 0 | D50: 1 | E50: 231 | F50: =ROUND(Source!BB37,O50) -> 0 | G50: ЭММсНРиСП | H50: Эксплуатация машин по ТСН-2001.16 | K50: 231 | L50: 12 | M50: 3 | O50: 2 | P50: =ROUND(Source!ET37,O50) -> 0 | W50: 0 | X50: 1 | Y50: 0 | Z50: 0 | AA50: 1 | AB50: 0
A51: 50 | B51: 0 | C51: 0 | D51: 1 | E51: 204 | F51: =ROUND(Source!R37,O51) -> 0 | G51: ЗПМ | H51: ЗП машинистов | K51: 204 | L51: 13 | M51: 3 | O51: 2 | P51: =ROUND(Source!DJ37,O51) -> 0 | W51: 0 | X51: 1 | Y51: 0 | Z51: 0 | AA51: 1 | AB51: 0
A52: 50 | B52: 0 | C52: 0 | D52: 1 | E52: 205 | F52: =ROUND(Source!S37,O52) -> 62.38 | G52: ОЗП | H52: Основная ЗП рабочих | K52: 205 | L52: 14 | M52: 3 | O52: 2 | P52: =ROUND(Source!DK37,O52) -> 3515.12 | W52: 62.38 | X52: 1 | Y52: 62.38 | Z52: 3515.12 | AA52: 1 | AB52: 3515.12
A53: 50 | B53: 0 | C53: 0 | D53: 1 | E53: 232 | F53: =ROUND(Source!BC37,O53) -> 0 | G53: ОЗПсНРиСП | H53: Основная ЗП рабочих по ТСН-2001.16 | K53: 232 | L53: 15 | M53: 3 | O53: 2 | P53: =ROUND(Source!EU37,O53) -> 0 | W53: 0 | X53: 1 | Y53: 0 | Z53: 0 | AA53: 1 | AB53: 0
A54: 50 | B54: 0 | C54: 0 | D54: 1 | E54: 214 | F54: =ROUND(Source!AS37,O54) -> 0 | G54: Строит | H54: Строительные работы с НР и СП | K54: 214 | L54: 16 | M54: 3 | O54: 2 | P54: =ROUND(Source!EK37,O54) -> 0 | W54: 0 | X54: 1 | Y54: 0 | Z54: 0 | AA54: 1 | AB54: 0
A55: 50 | B55: 0 | C55: 0 | D55: 1 | E55: 215 | F55: =ROUND(Source!AT37,O55) -> 149.59 | G55: Монтаж | H55: Монтажные работы с НР и СП | K55: 215 | L55: 17 | M55: 3 | O55: 2 | P55: =ROUND(Source!EL37,O55) -> 8430.25 | W55: 149.59 | X55: 1 | Y55: 149.59 | Z55: 8430.25 | AA55: 1 | AB55: 8430.25
A56: 50 | B56: 0 | C56: 0 | D56: 1 | E56: 217 | F56: =ROUND(Source!AU37,O56) -> 0 | G56: Прочие | H56: Прочие работы с НР и СП | K56: 217 | L56: 18 | M56: 3 | O56: 2 | P56: =ROUND(Source!EM37,O56) -> 0 | W56: 0 | X56: 1 | Y56: 0 | Z56: 0 | AA56: 1 | AB56: 0
A57: 50 | B57: 0 | C57: 0 | D57: 1 | E57: 230 | F57: =ROUND(Source!BA37,O57) -> 0 | G57: ПрочиеЗатр | H57: Прочие затраты по ТСН-2001.16 | K57: 230 | L57: 19 | M57: 3 | O57: 2 | P57: =ROUND(Source!ES37,O57) -> 0 | W57: 0 | X57: 1 | Y57: 0 | Z57: 0 | AA57: 1 | AB57: 0
A58: 50 | B58: 0 | C58: 0 | D58: 1 | E58: 206 | F58: =ROUND(Source!T37,O58) -> 0 | G58: ВозврМат | H58: Возврат материалов | K58: 206 | L58: 20 | M58: 3 | O58: 2 | P58: =ROUND(Source!DL37,O58) -> 0 | W58: 0 | X58: 1 | Y58: 0 | Z58: 0 | AA58: 1 | AB58: 0
A59: 50 | B59: 0 | C59: 0 | D59: 1 | E59: 207 | F59: =Source!U37 -> 4.7892924 | G59: ТрудСтр | H59: Трудозатраты строителей | K59: 207 | L59: 21 | M59: 3 | O59: -1 | P59: =Source!DM37 -> 4.7892924 | W59: 4.7892924 | X59: 1 | Y59: 4.7892924 | Z59: 4.7892924 | AA59: 1 | AB59: 4.7892924
A60: 50 | B60: 0 | C60: 0 | D60: 1 | E60: 208 | F60: =Source!V37 -> 0 | G60: ТрудМаш | H60: Трудозатраты машинистов | K60: 208 | L60: 22 | M60: 3 | O60: -1 | P60: =Source!DN37 -> 0 | W60: 0 | X60: 1 | Y60: 0 | Z60: 0 | AA60: 1 | AB60: 0
A61: 50 | B61: 0 | C61: 0 | D61: 1 | E61: 209 | F61: =ROUND(Source!W37,O61) -> 0 | G61: ТранспМат | H61: Транспорт материалов | K61: 209 | L61: 23 | M61: 3 | O61: 2 | P61: =ROUND(Source!DO37,O61) -> 0 | W61: 0 | X61: 1 | Y61: 0 | Z61: 0 | AA61: 1 | AB61: 0
A62: 50 | B62: 0 | C62: 0 | D62: 1 | E62: 233 | F62: =ROUND(Source!BD37,O62) -> 0 | G62: Перевозка | H62: Перевозка грузов | K62: 233 | L62: 24 | M62: 3 | O62: 2 | P62: =ROUND(Source!EV37,O62) -> 0 | W62: 0 | X62: 1 | Y62: 0 | Z62: 0 | AA62: 1 | AB62: 0
A63: 50 | B63: 0 | C63: 0 | D63: 1 | E63: 210 | F63: =ROUND(Source!X37,O63) -> 57.13 | G63: НР | H63: Накладные расходы | K63: 210 | L63: 25 | M63: 3 | O63: 2 | P63: =ROUND(Source!DP37,O63) -> 3219.68 | W63: 57.13 | X63: 1 | Y63: 57.13 | Z63: 3219.68 | AA63: 1 | AB63: 3219.68
A64: 50 | B64: 0 | C64: 0 | D64: 1 | E64: 211 | F64: =ROUND(Source!Y37,O64) -> 30.08 | G64: СмПриб | H64: Сметная прибыль | K64: 211 | L64: 26 | M64: 3 | O64: 2 | P64: =ROUND(Source!DQ37,O64) -> 1695.45 | W64: 30.08 | X64: 1 | Y64: 30.08 | Z64: 1695.45 | AA64: 1 | AB64: 1695.45
A65: 50 | B65: 0 | C65: 0 | D65: 1 | E65: 224 | F65: =ROUND(Source!AR37,O65) -> 149.59 | G65: Всего | H65: Всего с НР и СП | K65: 224 | L65: 27 | M65: 3 | O65: 2 | P65: =ROUND(Source!EJ37,O65) -> 8430.25 | W65: 149.59 | X65: 1 | Y65: 149.59 | Z65: 8430.25 | AA65: 1 | AB65: 8430.25
A67: 4 | B67: 1 | D67: =ROW(A88) -> 88 | F67: Новый раздел | G67: Комплект основного оборудования | I67: 0 | K67: 0 | S67: 0 | T67: 0 | V67: 0 | BX67: 0 | CJ67: 0
A69: 52 | B69: =B88 -> 1 | C69: =C88 -> 4 | D69: =D88 -> 67 | E69: =E88 -> 0 | F69: =F88 -> Новый раздел | G69: =G88 -> Комплект основного оборудования | O69: =O88 -> 97162.73 | P69: =P88 -> 97047.99 | Q69: =Q88 -> 0.63 | R69: =R88 -> 0.1 | S69: =S88 -> 114.11 | T69: =T88 -> 0 | U69: =U88 -> 8.832492 | V69: =V88 -> 0 | ... GX69: =GX88 -> 0
A71: 17 | B71: 1 | C71: =ROW(SmtRes!A25) -> 25 | D71: =ROW(EtalonRes!A25) -> 25 | E71: 5 | F71: 4.10-85-1 | G71: Монтаж часов первичных электрических показывающих кварцевых типа ПКЧЗ-2-РИ-Р24-Р6-1 | H71: 1 ШТ. | I71: 1 | J71: 0 | K71: 1 | O71: =ROUND(CP71,2) -> 52.36 | P71: =ROUND((ROUND((AC71*AW71*I71),2)*BC71),2) -> 0.46 | Q71: =(ROUND((ROUND((((ET71*1.2))*AV71*I71),2)*BB71),2)+ROUND((ROUND(((AE71-((EU71*1.2)))*AV71*I71),2)*BS71),2)) -> 0 | R71: =(ROUND((ROUND((((EU71*1.2))*AV71*I71),2)*BS71),2)+ROUND((ROUND(((AE71-((EU71*1.2)))*AV71*I71),2)*BS71),2)) -> 0 | S71: =ROUND((ROUND((AF71*AV71*I71),2)*BA71),2) -> 51.9 | T71: =ROUND(CU71*I71,2) -> 0 | U71: =CV71*I71 -> 3.7692 | V71: =CW71*I71 -> 0 | W71: =ROUND(CX71*I71,2) -> 0 | X71: =(ROUND((((S71+ROUND((ROUND((((EU71*1.2))*AV71*I71),2)*BS71),2))*AT71)/100),2)+ROUND(((ROUND((ROUND(((AE71-((EU71*1.2)))*AV71*I71),2)*BS71),2)*AT71)/100),2)) -> 46.71 | Y71: =(ROUND((((S71+ROUND((ROUND((((EU71*1.2))*AV71*I71),2)*BS71),2))*AU71)/100),2)+ROUND(((ROUND((ROUND(((AE71-((EU71*1.2)))*AV71*I71),2)*BS71),2)*AU71)/100),2)) -> 23.87 | AA71: 55942966 | AB71: =ROUND((AC71+AD71+AF71),6) -> 50.032 | AC71: =ROUND(((ES71*1)),6) -> 0.46 | AD71: =ROUND(((((ET71*1.2))-((EU71*1.2)))+AE71),6) -> 0 | AE71: =ROUND(((EU71*1.2)),6) -> 0 | AF71: =ROUND(((EV71*1.2)),6) -> 49.572 | AG71: =ROUND((AP71),6) -> 0 | AH71: =((EW71*1.2)) -> 3.6 | AI71: =((EX71*1.2)) -> 0 | AJ71: =(AS71) -> 0 | AK71: 41.77 | AL71: 0.46 | AM71: 0 | AN71: 0 | AO71: 41.31 | AP71: 0 | AQ71: 3 | AR71: 0 | AS71: 0 | AT71: 90 | AU71: 46 | AV71: 1.047 | AW71: 1 | AZ71: 1 | BA71: 1 | BB71: 1 | BC71: 1 | BH71: 0 | BI71: 2 | BJ71: ТСН-2001.4 Доп. 81, Сб. 10, т. 85, поз. 1 | BM71: 68 | BN71: 0 | BO71: 4.10-85-1 | BP71: 1 | BQ71: 40 | BR71: 0 | BS71: 1 | BT71: 1 | BU71: 1 | BV71: 1 | BW71: 1 | BX71: 1 | BZ71: 90 | CA71: 46 | CE71: 1566 | CF71: 0 | CG71: 0 | CM71: 0 | CN71: Поправка: Гл.12.Прил.8.п.8. 3_12.00.01.11.001 Наименование: При наличии напряженных и стесненных условий производства работ (стесненность, сложность складирования и транспортной логистики и т.п.) для объектов, расположенных в пределах круговой магистральной системы улиц "Садовое кольцо" города Москвы | CO71: 0 | CP71: =(P71+Q71+S71) -> 52.36 | CQ71: =ROUND((ROUND((AC71*AW71*1),2)*BC71),2) -> 0.46 | CR71: =(ROUND((ROUND((((ET71*1.2))*AV71*1),2)*BB71),2)+ROUND((ROUND(((AE71-((EU71*1.2)))*AV71*1),2)*BS71),2)) -> 0 | CS71: =(ROUND((ROUND((((EU71*1.2))*AV71*1),2)*BS71),2)+ROUND((ROUND(((AE71-((EU71*1.2)))*AV71*1),2)*BS71),2)) -> 0 | CT71: =ROUND((ROUND((AF71*AV71*1),2)*BA71),2) -> 51.9 | CU71: =AG71 -> 0 | CV71: =(AH71*AV71) -> 3.7692 | CW71: =AI71 -> 0 | CX71: =AJ71 -> 0 | CY71: =(ROUND((((S71+ROUND((ROUND((((EU71*1.2))*AV71*1),2)*BS71),2))*AT71)/100),2)+ROUND(((ROUND((ROUND(((AE71-((EU71*1.2)))*AV71*1),2)*BS71),2)*AT71)/100),2)) -> 46.71 | CZ71: =(ROUND((((S71+ROUND((ROUND((((EU71*1.2))*AV71*1),2)*BS71),2))*AU71)/100),2)+ROUND(((ROUND((ROUND(((AE71-((EU71*1.2)))*AV71*1),2)*BS71),2)*AU71)/100),2)) -> 23.87 | DB71: 17 | DD71: *1 | DE71: *1,2 | DF71: *1,2 | DG71: *1,2 | DI71: *1,2 | DJ71: *1,2 | DN71: 0 | DO71: 0 | DP71: 1 | DQ71: 1 | DU71: 1013 | DV71: 1 ШТ. | DW71: 1 ШТ. | DX71: 1 | EE71: 55393972 | EF71: 40 | EG71: Монтаж оборудования | EH71: 0 | EJ71: 2 | EK71: 68 | EL71: ТСН-2001.4-10. Прокладка и монтаж сетей связи | EM71: ТСН-2001.4-10-1 | EO71: Поправка: Гл.12.Прил.8.п.8. 3_12.00.01.11.001 | EQ71: 131072 | ER71: 41.77 | ES71: 0.46 | ET71: 0 | EU71: 0 | EV71: 41.31 | EW71: 3 | EX71: 0 | EY71: 0 | FQ71: 0 | FR71: 0 | FS71: 0 | FX71: 90 | FY71: 46 | GD71: 1 | GF71: -401276944 | GG71: 2 | GH71: 1 | GI71: 2 | GJ71: 0 | GK71: 0 | GL71: =ROUND(IF(AND(BH71=3,BI71=3,FS71<>0),P71,0),2) -> 0 | GM71: =ROUND(O71+X71+Y71,2)+GX71 -> 122.94 | GN71: =IF(OR(BI71=0,BI71=1),GM71-GX71,0) -> 0 | GO71: =IF(BI71=2,GM71-GX71,0) -> 122.94 | GP71: =IF(BI71=4,GM71-GX71,0) -> 0 | GR71: 0 | GS71: 3 | GT71: 0 | GV71: =ROUND((GT71),6) -> 0 | GW71: 1 | GX71: =ROUND(HC71*I71,2) -> 0 | HA71: 0 | HB71: 0 | HC71: =GV71*GW71 -> 0 | HS71: 0 | IK71: 0
A72: 17 | B72: 1 | C72: =ROW(SmtRes!A28) -> 28 | D72: =ROW(EtalonRes!A28) -> 28 | E72: 5 | F72: 4.10-85-1 | G72: Монтаж часов первичных электрических показывающих кварцевых типа ПКЧЗ-2-РИ-Р24-Р6-1 | H72: 1 ШТ. | I72: 1 | J72: 0 | K72: 1 | O72: =ROUND(CP72,2) -> 2927.71 | P72: =ROUND((ROUND((AC72*AW72*I72),2)*BC72),2) -> 3.14 | Q72: =(ROUND((ROUND((((ET72*1.2))*AV72*I72),2)*BB72),2)+ROUND((ROUND(((AE72-((EU72*1.2)))*AV72*I72),2)*BS72),2)) -> 0 | R72: =(ROUND((ROUND((((EU72*1.2))*AV72*I72),2)*BS72),2)+ROUND((ROUND(((AE72-((EU72*1.2)))*AV72*I72),2)*BS72),2)) -> 0 | S72: =ROUND((ROUND((AF72*AV72*I72),2)*BA72),2) -> 2924.57 | T72: =ROUND(CU72*I72,2) -> 0 | U72: =CV72*I72 -> 3.7692 | V72: =CW72*I72 -> 0 | W72: =ROUND(CX72*I72,2) -> 0 | X72: =(ROUND((((S72+ROUND((ROUND((((EU72*1.2))*AV72*I72),2)*BS72),2))*AT72)/100),2)+ROUND(((ROUND((ROUND(((AE72-((EU72*1.2)))*AV72*I72),2)*BS72),2)*AT72)/100),2)) -> 2632.11 | Y72: =(ROUND((((S72+ROUND((ROUND((((EU72*1.2))*AV72*I72),2)*BS72),2))*AU72)/100),2)+ROUND(((ROUND((ROUND(((AE72-((EU72*1.2)))*AV72*I72),2)*BS72),2)*AU72)/100),2)) -> 1345.3 | AA72: 55942968 | AB72: =ROUND((AC72+AD72+AF72),6) -> 50.032 | AC72: =ROUND(((ES72*1)),6) -> 0.46 | AD72: =ROUND(((((ET72*1.2))-((EU72*1.2)))+AE72),6) -> 0 | AE72: =ROUND(((EU72*1.2)),6) -> 0 | AF72: =ROUND(((EV72*1.2)),6) -> 49.572 | AG72: =ROUND((AP72),6) -> 0 | AH72: =((EW72*1.2)) -> 3.6 | AI72: =((EX72*1.2)) -> 0 | AJ72: =(AS72) -> 0 | AK72: 41.77 | AL72: 0.46 | AM72: 0 | AN72: 0 | AO72: 41.31 | AP72: 0 | AQ72: 3 | AR72: 0 | AS72: 0 | AT72: 90 | AU72: 46 | AV72: 1.047 | AW72: 1 | AZ72: 1 | BA72: 56.35 | BB72: 1 | BC72: 6.83 | BH72: 0 | BI72: 2 | BJ72: ТСН-2001.4 Доп. 81, Сб. 10, т. 85, поз. 1 | BM72: 68 | BN72: 0 | BO72: 4.10-85-1 | BP72: 1 | BQ72: 40 | BR72: 0 | BS72: 56.35 | BT72: 1 | BU72: 1 | BV72: 1 | BW72: 1 | BX72: 1 | BZ72: 90 | CA72: 46 | CE72: 1566 | CF72: 0 | CG72: 0 | CM72: 0 | CN72: Поправка: Гл.12.Прил.8.п.8. 3_12.00.01.11.001 Наименование: При наличии напряженных и стесненных условий производства работ (стесненность, сложность складирования и транспортной логистики и т.п.) для объектов, расположенных в пределах круговой магистральной системы улиц "Садовое кольцо" города Москвы | CO72: 0 | CP72: =(P72+Q72+S72) -> 2927.71 | CQ72: =ROUND((ROUND((AC72*AW72*1),2)*BC72),2) -> 3.14 | CR72: =(ROUND((ROUND((((ET72*1.2))*AV72*1),2)*BB72),2)+ROUND((ROUND(((AE72-((EU72*1.2)))*AV72*1),2)*BS72),2)) -> 0 | CS72: =(ROUND((ROUND((((EU72*1.2))*AV72*1),2)*BS72),2)+ROUND((ROUND(((AE72-((EU72*1.2)))*AV72*1),2)*BS72),2)) -> 0 | CT72: =ROUND((ROUND((AF72*AV72*1),2)*BA72),2) -> 2924.57 | CU72: =AG72 -> 0 | CV72: =(AH72*AV72) -> 3.7692 | CW72: =AI72 -> 0 | CX72: =AJ72 -> 0 | CY72: =(ROUND((((S72+ROUND((ROUND((((EU72*1.2))*AV72*1),2)*BS72),2))*AT72)/100),2)+ROUND(((ROUND((ROUND(((AE72-((EU72*1.2)))*AV72*1),2)*BS72),2)*AT72)/100),2)) -> 2632.11 | CZ72: =(ROUND((((S72+ROUND((ROUND((((EU72*1.2))*AV72*1),2)*BS72),2))*AU72)/100),2)+ROUND(((ROUND((ROUND(((AE72-((EU72*1.2)))*AV72*1),2)*BS72),2)*AU72)/100),2)) -> 1345.3 | DB72: 18 | DD72: *1 | DE72: *1,2 | DF72: *1,2 | DG72: *1,2 | DI72: *1,2 | DJ72: *1,2 | DN72: 0 | DO72: 0 | DP72: 1 | DQ72: 1 | DU72: 1013 | DV72: 1 ШТ. | DW72: 1 ШТ. | DX72: 1 | EE72: 55393972 | EF72: 40 | EG72: Монтаж оборудования | EH72: 0 | EJ72: 2 | EK72: 68 | EL72: ТСН-2001.4-10. Прокладка и монтаж сетей связи | EM72: ТСН-2001.4-10-1 | EO72: Поправка: Гл.12.Прил.8.п.8. 3_12.00.01.11.001 | EQ72: 131072 | ER72: 41.77 | ES72: 0.46 | ET72: 0 | EU72: 0 | EV72: 41.31 | EW72: 3 | EX72: 0 | EY72: 0 | FQ72: 0 | FR72: 0 | FS72: 0 | FX72: 90 | FY72: 46 | GD72: 1 | GF72: -401276944 | GG72: 2 | GH72: 1 | GI72: 2 | GJ72: 0 | GK72: 0 | GL72: =ROUND(IF(AND(BH72=3,BI72=3,FS72<>0),P72,0),2) -> 0 | GM72: =ROUND(O72+X72+Y72,2)+GX72 -> 6905.12 | GN72: =IF(OR(BI72=0,BI72=1),GM72-GX72,0) -> 0 | GO72: =IF(BI72=2,GM72-GX72,0) -> 6905.12 | GP72: =IF(BI72=4,GM72-GX72,0) -> 0 | GR72: 0 | GS72: 3 | GT72: 0 | GV72: =ROUND((GT72),6) -> 0 | GW72: 1 | GX72: =ROUND(HC72*I72,2) -> 0 | HA72: 0 | HB72: 0 | HC72: =GV72*GW72 -> 0 | HS72: 0 | IK72: 0
A73: 17 | B73: 1 | E73: 6 | F73: КА1 | G73: КОНТУР - часовая станция, сервер времени, стоечное исполнение, NTP (тип. SC KMWP-IP-A0124) | H73: шт. | I73: 1 | J73: 0 | K73: 1 | O73: =ROUND(CP73,2) -> 72464.18 | P73: =ROUND((ROUND((AC73*I73),2)*BC73),2) -> 72464.18 | Q73: =(ROUND((ROUND(((ET73)*AV73*I73),2)*BB73),2)+ROUND((ROUND(((AE73-(EU73))*AV73*I73),2)*BS73),2)) -> 0 | R73: =(ROUND((ROUND(((EU73)*AV73*I73),2)*BS73),2)+ROUND((ROUND(((AE73-(EU73))*AV73*I73),2)*BS73),2)) -> 0 | S73: =ROUND((ROUND((AF73*AV73*I73),2)*BA73),2) -> 0 | T73: =ROUND(CU73*I73,2) -> 0 | U73: =CV73*I73 -> 0 | V73: =CW73*I73 -> 0 | W73: =ROUND(CX73*I73,2) -> 0 | X73: =(ROUND((((S73+ROUND((ROUND(((EU73)*AV73*I73),2)*BS73),2))*AT73)/100),2)+ROUND(((ROUND((ROUND(((AE73-(EU73))*AV73*I73),2)*BS73),2)*AT73)/100),2)) -> 0 | Y73: =(ROUND((((S73+ROUND((ROUND(((EU73)*AV73*I73),2)*BS73),2))*AU73)/100),2)+ROUND(((ROUND((ROUND(((AE73-(EU73))*AV73*I73),2)*BS73),2)*AU73)/100),2)) -> 0 | AA73: 55942966 | AB73: =ROUND((AC73+AD73+AF73),6) -> 72464.18 | AC73: =ROUND((ES73),6) -> 72464.18 | AD73: =ROUND((((ET73)-(EU73))+AE73),6) -> 0 | AE73: =ROUND((EU73),6) -> 0 | AF73: =ROUND((EV73),6) -> 0 | AG73: =ROUND((AP73),6) -> 0 | AH73: =(EW73) -> 0 | AI73: =(EX73) -> 0 | AJ73: =(AS73) -> 0 | AK73: 72464.18 | AL73: 72464.18 | AM73: 0 | AN73: 0 | AO73: 0 | AP73: 0 | AQ73: 0 | AR73: 0 | AS73: 0 | AT73: 0 | AU73: 0 | AV73: 1 | AW73: 1 | AZ73: 1 | BA73: 1 | BB73: 1 | BC73: 1 | BH73: 3 | BI73: 3 | BM73: 746 | BN73: 0 | BP73: 0 | BQ73: 130 | BR73: 0 | BS73: 1 | BT73: 1 | BU73: 1 | BV73: 1 | BW73: 1 | BX73: 1 | BZ73: 0 | CA73: 0 | CE73: 1566 | CF73: 0 | CG73: 0 | CM73: 0 | CO73: 0 | CP73: =(P73+Q73+S73) -> 72464.18 | CQ73: =ROUND((ROUND((AC73*1),2)*BC73),2) -> 72464.18 | CR73: =(ROUND((ROUND(((ET73)*AV73*1),2)*BB73),2)+ROUND((ROUND(((AE73-(EU73))*AV73*1),2)*BS73),2)) -> 0 | CS73: =(ROUND((ROUND(((EU73)*AV73*1),2)*BS73),2)+ROUND((ROUND(((AE73-(EU73))*AV73*1),2)*BS73),2)) -> 0 | CT73: =ROUND((ROUND((AF73*AV73*1),2)*BA73),2) -> 0 | CU73: =AG73 -> 0 | CV73: =(AH73*AV73) -> 0 | CW73: =AI73 -> 0 | CX73: =AJ73 -> 0 | CY73: =(ROUND((((S73+ROUND((ROUND(((EU73)*AV73*1),2)*BS73),2))*AT73)/100),2)+ROUND(((ROUND((ROUND(((AE73-(EU73))*AV73*1),2)*BS73),2)*AT73)/100),2)) -> 0 | CZ73: =(ROUND((((S73+ROUND((ROUND(((EU73)*AV73*1),2)*BS73),2))*AU73)/100),2)+ROUND(((ROUND((ROUND(((AE73-(EU73))*AV73*1),2)*BS73),2)*AU73)/100),2)) -> 0 | DN73: 0 | DO73: 0 | DP73: 1 | DQ73: 1 | DU73: 1010 | DV73: шт. | DW73: шт. | DX73: 1 | EE73: 55393877 | EF73: 130 | EG73: Сметная стоимость оборудования | EH73: 0 | EJ73: 3 | EK73: 746 | EL73: ТСН-2001.13. Сметная стоимость оборудования | EM73: ТСН-2001.13 | EQ73: 131072 | ER73: 0 | ES73: 72464.18 | ET73: 0 | EU73: 0 | EV73: 0 | EW73: 0 | EX73: 0 | EY73: 0 | FQ73: 0 | FR73: =P73 -> 72464.18 | FS73: 0 | FX73: 0 | FY73: 0 | GA73: [642 038,95 / 1,22 / 7,57] + 3% Трансп + 1,2% Заг.скл | GD73: 1 | GF73: -1161085270 | GG73: 2 | GH73: 4 | GI73: -2 | GJ73: 0 | GK73: 0 | GL73: =ROUND(IF(AND(BH73=3,BI73=3,FS73<>0),P73,0),2) -> 0 | GM73: =ROUND(O73+X73+Y73,2)+GX73 -> 72464.18 | GN73: =IF(OR(BI73=0,BI73=1),GM73-GX73,0) -> 0 | GO73: =IF(BI73=2,GM73-GX73,0) -> 0 | GP73: =IF(BI73=4,GM73-GX73,0) -> 0 | GR73: 0 | GS73: 2 | GT73: 0 | GV73: =ROUND((GT73),6) -> 0 | GW73: 1 | GX73: =ROUND(HC73*I73,2) -> 0 | HA73: 0 | HB73: 0 | HC73: =GV73*GW73 -> 0 | HE73: 3 | HF73: 1,2 | HS73: 0 | IK73: 0
A74: 17 | B74: 1 | E74: 6 | F74: КА1 | G74: КОНТУР - часовая станция, сервер времени, стоечное исполнение, NTP (тип. SC KMWP-IP-A0124) | H74: шт. | I74: 1 | J74: 0 | K74: 1 | O74: =ROUND(CP74,2) -> 548553.84 | P74: =ROUND((ROUND((AC74*I74),2)*BC74),2) -> 548553.84 | Q74: =(ROUND((ROUND(((ET74)*AV74*I74),2)*BB74),2)+ROUND((ROUND(((AE74-(EU74))*AV74*I74),2)*BS74),2)) -> 0 | R74: =(ROUND((ROUND(((EU74)*AV74*I74),2)*BS74),2)+ROUND((ROUND(((AE74-(EU74))*AV74*I74),2)*BS74),2)) -> 0 | S74: =ROUND((ROUND((AF74*AV74*I74),2)*BA74),2) -> 0 | T74: =ROUND(CU74*I74,2) -> 0 | U74: =CV74*I74 -> 0 | V74: =CW74*I74 -> 0 | W74: =ROUND(CX74*I74,2) -> 0 | X74: =(ROUND((((S74+ROUND((ROUND(((EU74)*AV74*I74),2)*BS74),2))*AT74)/100),2)+ROUND(((ROUND((ROUND(((AE74-(EU74))*AV74*I74),2)*BS74),2)*AT74)/100),2)) -> 0 | Y74: =(ROUND((((S74+ROUND((ROUND(((EU74)*AV74*I74),2)*BS74),2))*AU74)/100),2)+ROUND(((ROUND((ROUND(((AE74-(EU74))*AV74*I74),2)*BS74),2)*AU74)/100),2)) -> 0 | AA74: 55942968 | AB74: =ROUND((AC74+AD74+AF74),6) -> 72464.18 | AC74: =ROUND((ES74),6) -> 72464.18 | AD74: =ROUND((((ET74)-(EU74))+AE74),6) -> 0 | AE74: =ROUND((EU74),6) -> 0 | AF74: =ROUND((EV74),6) -> 0 | AG74: =ROUND((AP74),6) -> 0 | AH74: =(EW74) -> 0 | AI74: =(EX74) -> 0 | AJ74: =(AS74) -> 0 | AK74: 72464.18 | AL74: 72464.18 | AM74: 0 | AN74: 0 | AO74: 0 | AP74: 0 | AQ74: 0 | AR74: 0 | AS74: 0 | AT74: 0 | AU74: 0 | AV74: 1 | AW74: 1 | AZ74: 1 | BA74: 1 | BB74: 1 | BC74: 7.57 | BH74: 3 | BI74: 3 | BM74: 746 | BN74: 0 | BP74: 0 | BQ74: 130 | BR74: 0 | BS74: 1 | BT74: 1 | BU74: 1 | BV74: 1 | BW74: 1 | BX74: 1 | BZ74: 0 | CA74: 0 | CE74: 1566 | CF74: 0 | CG74: 0 | CM74: 0 | CO74: 0 | CP74: =(P74+Q74+S74) -> 548553.84 | CQ74: =ROUND((ROUND((AC74*1),2)*BC74),2) -> 548553.84 | CR74: =(ROUND((ROUND(((ET74)*AV74*1),2)*BB74),2)+ROUND((ROUND(((AE74-(EU74))*AV74*1),2)*BS74),2)) -> 0 | CS74: =(ROUND((ROUND(((EU74)*AV74*1),2)*BS74),2)+ROUND((ROUND(((AE74-(EU74))*AV74*1),2)*BS74),2)) -> 0 | CT74: =ROUND((ROUND((AF74*AV74*1),2)*BA74),2) -> 0 | CU74: =AG74 -> 0 | CV74: =(AH74*AV74) -> 0 | CW74: =AI74 -> 0 | CX74: =AJ74 -> 0 | CY74: =(ROUND((((S74+ROUND((ROUND(((EU74)*AV74*1),2)*BS74),2))*AT74)/100),2)+ROUND(((ROUND((ROUND(((AE74-(EU74))*AV74*1),2)*BS74),2)*AT74)/100),2)) -> 0 | CZ74: =(ROUND((((S74+ROUND((ROUND(((EU74)*AV74*1),2)*BS74),2))*AU74)/100),2)+ROUND(((ROUND((ROUND(((AE74-(EU74))*AV74*1),2)*BS74),2)*AU74)/100),2)) -> 0 | DN74: 0 | DO74: 0 | DP74: 1 | DQ74: 1 | DU74: 1010 | DV74: шт. | DW74: шт. | DX74: 1 | EE74: 55393877 | EF74: 130 | EG74: Сметная стоимость оборудования | EH74: 0 | EJ74: 3 | EK74: 746 | EL74: ТСН-2001.13. Сметная стоимость оборудования | EM74: ТСН-2001.13 | EQ74: 131072 | ER74: 72464.18 | ES74: 72464.18 | ET74: 0 | EU74: 0 | EV74: 0 | EW74: 0 | EX74: 0 | EY74: 0 | EZ74: 5 | FC74: 1 | FD74: 18 | FF74: 642038.95 | FQ74: 0 | FR74: =P74 -> 548553.84 | FS74: 0 | FX74: 0 | FY74: 0 | GA74: [642 038,95 / 1,22 / 7,57] + 3% Трансп + 1,2% Заг.скл | GD74: 1 | GF74: -1161085270 | GG74: 2 | GH74: 3 | GI74: 3 | GJ74: 0 | GK74: 0 | GL74: =ROUND(IF(AND(BH74=3,BI74=3,FS74<>0),P74,0),2) -> 0 | GM74: =ROUND(O74+X74+Y74,2)+GX74 -> 548553.84 | GN74: =IF(OR(BI74=0,BI74=1),GM74-GX74,0) -> 0 | GO74: =IF(BI74=2,GM74-GX74,0) -> 0 | GP74: =IF(BI74=4,GM74-GX74,0) -> 0 | GR74: 1 | GS74: 1 | GT74: 0 | GV74: =ROUND((GT74),6) -> 0 | GW74: 1 | GX74: =ROUND(HC74*I74,2) -> 0 | HA74: 0 | HB74: 0 | HC74: =GV74*GW74 -> 0 | HE74: 3 | HF74: 1,2 | HS74: 0 | IK74: 0
A75: 17 | B75: 1 | C75: =ROW(SmtRes!A30) -> 30 | D75: =ROW(EtalonRes!A31) -> 31 | E75: 7 | F75: 4.11-12-1 | G75: Установка съемных и выдвижных блоков (модулей, ячеек, ТЭЗ) массой до 5 кг | H75: 1 ШТ. | I75: 1 | J75: 0 | K75: 1 | O75: =ROUND(CP75,2) -> 15.27 | P75: =ROUND((ROUND((AC75*AW75*I75),2)*BC75),2) -> 0 | Q75: =(ROUND((ROUND((((ET75*1.2))*AV75*I75),2)*BB75),2)+ROUND((ROUND(((AE75-((EU75*1.2)))*AV75*I75),2)*BS75),2)) -> 0.63 | R75: =(ROUND((ROUND((((EU75*1.2))*AV75*I75),2)*BS75),2)+ROUND((ROUND(((AE75-((EU75*1.2)))*AV75*I75),2)*BS75),2)) -> 0.1 | S75: =ROUND((ROUND((AF75*AV75*I75),2)*BA75),2) -> 14.64 | T75: =ROUND(CU75*I75,2) -> 0 | U75: =CV75*I75 -> 1.294092 | V75: =CW75*I75 -> 0 | W75: =ROUND(CX75*I75,2) -> 0 | X75: =(ROUND((((S75+ROUND((ROUND((((EU75*1.2))*AV75*I75),2)*BS75),2))*AT75)/100),2)+ROUND(((ROUND((ROUND(((AE75-((EU75*1.2)))*AV75*I75),2)*BS75),2)*AT75)/100),2)) -> 13.27 | Y75: =(ROUND((((S75+ROUND((ROUND((((EU75*1.2))*AV75*I75),2)*BS75),2))*AU75)/100),2)+ROUND(((ROUND((ROUND(((AE75-((EU75*1.2)))*AV75*I75),2)*BS75),2)*AU75)/100),2)) -> 6.78 | AA75: 55942966 | AB75: =ROUND((AC75+AD75+AF75),6) -> 14.58 | AC75: =ROUND(((ES75*1)),6) -> 0 | AD75: =ROUND(((((ET75*1.2))-((EU75*1.2)))+AE75),6) -> 0.6 | AE75: =ROUND(((EU75*1.2)),6) -> 0.096 | AF75: =ROUND(((EV75*1.2)),6) -> 13.98 | AG75: =ROUND((AP75),6) -> 0 | AH75: =((EW75*1.2)) -> 1.236 | AI75: =((EX75*1.2)) -> 0 | AJ75: =(AS75) -> 0 | AK75: 12.15 | AL75: 0 | AM75: 0.5 | AN75: 0.08 | AO75: 11.65 | AP75: 0 | AQ75: 1.03 | AR75: 0 | AS75: 0 | AT75: 90 | AU75: 46 | AV75: 1.047 | AW75: 1 | AZ75: 1 | BA75: 1 | BB75: 1 | BC75: 1 | BH75: 0 | BI75: 2 | BJ75: ТСН-2001.4 Доп. 68, Сб. 11, т. 12, поз. 1 | BM75: 72 | BN75: 0 | BO75: 4.11-12-1 | BP75: 1 | BQ75: 40 | BR75: 0 | BS75: 1 | BT75: 1 | BU75: 1 | BV75: 1 | BW75: 1 | BX75: 1 | BZ75: 90 | CA75: 46 | CE75: 1566 | CF75: 0 | CG75: 0 | CM75: 0 | CN75: Поправка: Гл.12.Прил.8.п.8. 3_12.00.01.11.001 Наименование: При наличии напряженных и стесненных условий производства работ (стесненность, сложность складирования и транспортной логистики и т.п.) для объектов, расположенных в пределах круговой магистральной системы улиц "Садовое кольцо" города Москвы | CO75: 0 | CP75: =(P75+Q75+S75) -> 15.27 | CQ75: =ROUND((ROUND((AC75*AW75*1),2)*BC75),2) -> 0 | CR75: =(ROUND((ROUND((((ET75*1.2))*AV75*1),2)*BB75),2)+ROUND((ROUND(((AE75-((EU75*1.2)))*AV75*1),2)*BS75),2)) -> 0.63 | CS75: =(ROUND((ROUND((((EU75*1.2))*AV75*1),2)*BS75),2)+ROUND((ROUND(((AE75-((EU75*1.2)))*AV75*1),2)*BS75),2)) -> 0.1 | CT75: =ROUND((ROUND((AF75*AV75*1),2)*BA75),2) -> 14.64 | CU75: =AG75 -> 0 | CV75: =(AH75*AV75) -> 1.294092 | CW75: =AI75 -> 0 | CX75: =AJ75 -> 0 | CY75: =(ROUND((((S75+ROUND((ROUND((((EU75*1.2))*AV75*1),2)*BS75),2))*AT75)/100),2)+ROUND(((ROUND((ROUND(((AE75-((EU75*1.2)))*AV75*1),2)*BS75),2)*AT75)/100),2)) -> 13.27 | CZ75: =(ROUND((((S75+ROUND((ROUND((((EU75*1.2))*AV75*1),2)*BS75),2))*AU75)/100),2)+ROUND(((ROUND((ROUND(((AE75-((EU75*1.2)))*AV75*1),2)*BS75),2)*AU75)/100),2)) -> 6.78 | DB75: 19 | DD75: *1 | DE75: *1,2 | DF75: *1,2 | DG75: *1,2 | DI75: *1,2 | DJ75: *1,2 | DN75: 0 | DO75: 0 | DP75: 1 | DQ75: 1 | DU75: 1013 | DV75: 1 ШТ. | DW75: 1 ШТ. | DX75: 1 | EE75: 55393976 | EF75: 40 | EG75: Монтаж оборудования | EH75: 0 | EJ75: 2 | EK75: 72 | EL75: ТСН-2001.4-11. Приборы и средства автоматизации и вычислительной техники | EM75: ТСН-2001.4-11-1 | EO75: Поправка: Гл.12.Прил.8.п.8. 3_12.00.01.11.001 | EQ75: 0 | ER75: 12.15 | ES75: 0 | ET75: 0.5 | EU75: 0.08 | EV75: 11.65 | EW75: 1.03 | EX75: 0 | EY75: 0 | FQ75: 0 | FR75: 0 | FS75: 0 | FX75: 90 | FY75: 46 | GD75: 1 | GF75: -920792427 | GG75: 2 | GH75: 1 | GI75: 2 | GJ75: 0 | GK75: 0 | GL75: =ROUND(IF(AND(BH75=3,BI75=3,FS75<>0),P75,0),2) -> 0 | GM75: =ROUND(O75+X75+Y75,2)+GX75 -> 35.32 | GN75: =IF(OR(BI75=0,BI75=1),GM75-GX75,0) -> 0 | GO75: =IF(BI75=2,GM75-GX75,0) -> 35.32 | GP75: =IF(BI75=4,GM75-GX75,0) -> 0 | GR75: 0 | GS75: 3 | GT75: 0 | GV75: =ROUND((GT75),6) -> 0 | GW75: 1 | GX75: =ROUND(HC75*I75,2) -> 0 | HA75: 0 | HB75: 0 | HC75: =GV75*GW75 -> 0 | HS75: 0 | IK75: 0
A76: 17 | B76: 1 | C76: =ROW(SmtRes!A32) -> 32 | D76: =ROW(EtalonRes!A34) -> 34 | E76: 7 | F76: 4.11-12-1 | G76: Установка съемных и выдвижных блоков (модулей, ячеек, ТЭЗ) массой до 5 кг | H76: 1 ШТ. | I76: 1 | J76: 0 | K76: 1 | O76: =ROUND(CP76,2) -> 835.68 | P76: =ROUND((ROUND((AC76*AW76*I76),2)*BC76),2) -> 0 | Q76: =(ROUND((ROUND((((ET76*1.2))*AV76*I76),2)*BB76),2)+ROUND((ROUND(((AE76-((EU76*1.2)))*AV76*I76),2)*BS76),2)) -> 10.72 | R76: =(ROUND((ROUND((((EU76*1.2))*AV76*I76),2)*BS76),2)+ROUND((ROUND(((AE76-((EU76*1.2)))*AV76*I76),2)*BS76),2)) -> 5.64 | S76: =ROUND((ROUND((AF76*AV76*I76),2)*BA76),2) -> 824.96 | T76: =ROUND(CU76*I76,2) -> 0 | U76: =CV76*I76 -> 1.294092 | V76: =CW76*I76 -> 0 | W76: =ROUND(CX76*I76,2) -> 0 | X76: =(ROUND((((S76+ROUND((ROUND((((EU76*1.2))*AV76*I76),2)*BS76),2))*AT76)/100),2)+ROUND(((ROUND((ROUND(((AE76-((EU76*1.2)))*AV76*I76),2)*BS76),2)*AT76)/100),2)) -> 747.54 | Y76: =(ROUND((((S76+ROUND((ROUND((((EU76*1.2))*AV76*I76),2)*BS76),2))*AU76)/100),2)+ROUND(((ROUND((ROUND(((AE76-((EU76*1.2)))*AV76*I76),2)*BS76),2)*AU76)/100),2)) -> 382.08 | AA76: 55942968 | AB76: =ROUND((AC76+AD76+AF76),6) -> 14.58 | AC76: =ROUND(((ES76*1)),6) -> 0 | AD76: =ROUND(((((ET76*1.2))-((EU76*1.2)))+AE76),6) -> 0.6 | AE76: =ROUND(((EU76*1.2)),6) -> 0.096 | AF76: =ROUND(((EV76*1.2)),6) -> 13.98 | AG76: =ROUND((AP76),6) -> 0 | AH76: =((EW76*1.2)) -> 1.236 | AI76: =((EX76*1.2)) -> 0 | AJ76: =(AS76) -> 0 | AK76: 12.15 | AL76: 0 | AM76: 0.5 | AN76: 0.08 | AO76: 11.65 | AP76: 0 | AQ76: 1.03 | AR76: 0 | AS76: 0 | AT76: 90 | AU76: 46 | AV76: 1.047 | AW76: 1 | AZ76: 1 | BA76: 56.35 | BB76: 17.02 | BC76: 1 | BH76: 0 | BI76: 2 | BJ76: ТСН-2001.4 Доп. 68, Сб. 11, т. 12, поз. 1 | BM76: 72 | BN76: 0 | BO76: 4.11-12-1 | BP76: 1 | BQ76: 40 | BR76: 0 | BS76: 56.35 | BT76: 1 | BU76: 1 | BV76: 1 | BW76: 1 | BX76: 1 | BZ76: 90 | CA76: 46 | CE76: 1566 | CF76: 0 | CG76: 0 | CM76: 0 | CN76: Поправка: Гл.12.Прил.8.п.8. 3_12.00.01.11.001 Наименование: При наличии напряженных и стесненных условий производства работ (стесненность, сложность складирования и транспортной логистики и т.п.) для объектов, расположенных в пределах круговой магистральной системы улиц "Садовое кольцо" города Москвы | CO76: 0 | CP76: =(P76+Q76+S76) -> 835.68 | CQ76: =ROUND((ROUND((AC76*AW76*1),2)*BC76),2) -> 0 | CR76: =(ROUND((ROUND((((ET76*1.2))*AV76*1),2)*BB76),2)+ROUND((ROUND(((AE76-((EU76*1.2)))*AV76*1),2)*BS76),2)) -> 10.72 | CS76: =(ROUND((ROUND((((EU76*1.2))*AV76*1),2)*BS76),2)+ROUND((ROUND(((AE76-((EU76*1.2)))*AV76*1),2)*BS76),2)) -> 5.64 | CT76: =ROUND((ROUND((AF76*AV76*1),2)*BA76),2) -> 824.96 | CU76: =AG76 -> 0 | CV76: =(AH76*AV76) -> 1.294092 | CW76: =AI76 -> 0 | CX76: =AJ76 -> 0 | CY76: =(ROUND((((S76+ROUND((ROUND((((EU76*1.2))*AV76*1),2)*BS76),2))*AT76)/100),2)+ROUND(((ROUND((ROUND(((AE76-((EU76*1.2)))*AV76*1),2)*BS76),2)*AT76)/100),2)) -> 747.54 | CZ76: =(ROUND((((S76+ROUND((ROUND((((EU76*1.2))*AV76*1),2)*BS76),2))*AU76)/100),2)+ROUND(((ROUND((ROUND(((AE76-((EU76*1.2)))*AV76*1),2)*BS76),2)*AU76)/100),2)) -> 382.08 | DB76: 20 | DD76: *1 | DE76: *1,2 | DF76: *1,2 | DG76: *1,2 | DI76: *1,2 | DJ76: *1,2 | DN76: 0 | DO76: 0 | DP76: 1 | DQ76: 1 | DU76: 1013 | DV76: 1 ШТ. | DW76: 1 ШТ. | DX76: 1 | EE76: 55393976 | EF76: 40 | EG76: Монтаж оборудования | EH76: 0 | EJ76: 2 | EK76: 72 | EL76: ТСН-2001.4-11. Приборы и средства автоматизации и вычислительной техники | EM76: ТСН-2001.4-11-1 | EO76: Поправка: Гл.12.Прил.8.п.8. 3_12.00.01.11.001 | EQ76: 0 | ER76: 12.15 | ES76: 0 | ET76: 0.5 | EU76: 0.08 | EV76: 11.65 | EW76: 1.03 | EX76: 0 | EY76: 0 | FQ76: 0 | FR76: 0 | FS76: 0 | FX76: 90 | FY76: 46 | GD76: 1 | GF76: -920792427 | GG76: 2 | GH76: 1 | GI76: 2 | GJ76: 0 | GK76: 0 | GL76: =ROUND(IF(AND(BH76=3,BI76=3,FS76<>0),P76,0),2) -> 0 | GM76: =ROUND(O76+X76+Y76,2)+GX76 -> 1965.3 | GN76: =IF(OR(BI76=0,BI76=1),GM76-GX76,0) -> 0 | GO76: =IF(BI76=2,GM76-GX76,0) -> 1965.3 | GP76: =IF(BI76=4,GM76-GX76,0) -> 0 | GR76: 0 | GS76: 3 | GT76: 0 | GV76: =ROUND((GT76),6) -> 0 | GW76: 1 | GX76: =ROUND(HC76*I76,2) -> 0 | HA76: 0 | HB76: 0 | HC76: =GV76*GW76 -> 0 | HS76: 0 | IK76: 0
A77: 17 | B77: 1 | C77: =ROW(SmtRes!A34) -> 34 | D77: =ROW(EtalonRes!A36) -> 36 | F77: 4.10-134-7 | G77: Монтаж антенны дополнительной для приема ТВ на ранее установленной опоре, с действующими ТВ антеннами | H77: 1 антенна | I77: 1 | J77: 0 | K77: 1 | O77: =ROUND(CP77,2) -> 52.16 | P77: =ROUND((ROUND((AC77*AW77*I77),2)*BC77),2) -> 0.18 | Q77: =(ROUND((ROUND((((ET77*1.2))*AV77*I77),2)*BB77),2)+ROUND((ROUND(((AE77-((EU77*1.2)))*AV77*I77),2)*BS77),2)) -> 0 | R77: =(ROUND((ROUND((((EU77*1.2))*AV77*I77),2)*BS77),2)+ROUND((ROUND(((AE77-((EU77*1.2)))*AV77*I77),2)*BS77),2)) -> 0 | S77: =ROUND((ROUND((AF77*AV77*I77),2)*BA77),2) -> 51.98 | T77: =ROUND(CU77*I77,2) -> 0 | U77: =CV77*I77 -> 3.613188 | V77: =CW77*I77 -> 0 | W77: =ROUND(CX77*I77,2) -> 0 | X77: =(ROUND((((S77+ROUND((ROUND((((EU77*1.2))*AV77*I77),2)*BS77),2))*AT77)/100),2)+ROUND(((ROUND((ROUND(((AE77-((EU77*1.2)))*AV77*I77),2)*BS77),2)*AT77)/100),2)) -> 49.38 | Y77: =(ROUND((((S77+ROUND((ROUND((((EU77*1.2))*AV77*I77),2)*BS77),2))*AU77)/100),2)+ROUND(((ROUND((ROUND(((AE77-((EU77*1.2)))*AV77*I77),2)*BS77),2)*AU77)/100),2)) -> 27.55 | AA77: -1 | AB77: =ROUND((AC77+AD77+AF77),6) -> 48 | AC77: =ROUND(((ES77*1)),6) -> 0.18 | AD77: =ROUND(((((ET77*1.2))-((EU77*1.2)))+AE77),6) -> 0 | AE77: =ROUND(((EU77*1.2)),6) -> 0 | AF77: =ROUND(((EV77*1.2)),6) -> 47.82 | AG77: =ROUND((AP77),6) -> 0 | AH77: =((EW77*1.2)) -> 3.324 | AI77: =((EX77*1.2)) -> 0 | AJ77: =(AS77) -> 0 | AK77: 40.03 | AL77: 0.18 | AM77: 0 | AN77: 0 | AO77: 39.85 | AP77: 0 | AQ77: 2.77 | AR77: 0 | AS77: 0 | AT77: 95 | AU77: 53 | AV77: 1.087 | AW77: 1 | AZ77: 1 | BA77: 1 | BB77: 1 | BC77: 1 | BH77: 0 | BI77: 2 | BJ77: ТСН-2001.4 Доп. 81, Сб. 10, т. 134, поз. 7 | BM77: 69 | BN77: 0 | BO77: 4.10-134-7 | BP77: 1 | BQ77: 40 | BR77: 0 | BS77: 1 | BT77: 1 | BU77: 1 | BV77: 1 | BW77: 1 | BX77: 1 | BZ77: 95 | CA77: 53 | CE77: 1566 | CF77: 0 | CG77: 0 | CM77: 0 | CN77: Поправка: Гл.12.Прил.8.п.8. 3_12.00.01.11.001 Наименование: При наличии напряженных и стесненных условий производства работ (стесненность, сложность складирования и транспортной логистики и т.п.) для объектов, расположенных в пределах круговой магистральной системы улиц "Садовое кольцо" города Москвы | CO77: 0 | CP77: =(P77+Q77+S77) -> 52.16 | CQ77: =ROUND((ROUND((AC77*AW77*1),2)*BC77),2) -> 0.18 | CR77: =(ROUND((ROUND((((ET77*1.2))*AV77*1),2)*BB77),2)+ROUND((ROUND(((AE77-((EU77*1.2)))*AV77*1),2)*BS77),2)) -> 0 | CS77: =(ROUND((ROUND((((EU77*1.2))*AV77*1),2)*BS77),2)+ROUND((ROUND(((AE77-((EU77*1.2)))*AV77*1),2)*BS77),2)) -> 0 | CT77: =ROUND((ROUND((AF77*AV77*1),2)*BA77),2) -> 51.98 | CU77: =AG77 -> 0 | CV77: =(AH77*AV77) -> 3.613188 | CW77: =AI77 -> 0 | CX77: =AJ77 -> 0 | CY77: =(ROUND((((S77+ROUND((ROUND((((EU77*1.2))*AV77*1),2)*BS77),2))*AT77)/100),2)+ROUND(((ROUND((ROUND(((AE77-((EU77*1.2)))*AV77*1),2)*BS77),2)*AT77)/100),2)) -> 49.38 | CZ77: =(ROUND((((S77+ROUND((ROUND((((EU77*1.2))*AV77*1),2)*BS77),2))*AU77)/100),2)+ROUND(((ROUND((ROUND(((AE77-((EU77*1.2)))*AV77*1),2)*BS77),2)*AU77)/100),2)) -> 27.55 | DB77: 21 | DD77: *1 | DE77: *1,2 | DF77: *1,2 | DG77: *1,2 | DI77: *1,2 | DJ77: *1,2 | DN77: 0 | DO77: 0 | DP77: 1 | DQ77: 1 | DU77: 1013 | DV77: 1 антенна | DW77: 1 антенна | DX77: 1 | EE77: 55393973 | EF77: 40 | EG77: Монтаж оборудования | EH77: 0 | EJ77: 2 | EK77: 69 | EL77: ТСН-2001.4-10. Монтаж радиотелевизионного и электронного оборудования | EM77: ТСН-2001.4-10-2 | EO77: Поправка: Гл.12.Прил.8.п.8. 3_12.00.01.11.001 | EQ77: 132096 | ER77: 40.03 | ES77: 0.18 | ET77: 0 | EU77: 0 | EV77: 39.85 | EW77: 2.77 | EX77: 0 | EY77: 0 | FQ77: 0 | FR77: 0 | FS77: 0 | FX77: 95 | FY77: 53 | GD77: 1 | GF77: 2002393274 | GG77: 2 | GH77: 1 | GI77: 2 | GJ77: 0 | GK77: 0 | GL77: =ROUND(IF(AND(BH77=3,BI77=3,FS77<>0),P77,0),2) -> 0 | GM77: =ROUND(O77+X77+Y77,2)+GX77 -> 129.09 | GN77: =IF(OR(BI77=0,BI77=1),GM77-GX77,0) -> 0 | GO77: =IF(BI77=2,GM77-GX77,0) -> 129.09 | GP77: =IF(BI77=4,GM77-GX77,0) -> 0 | GR77: 0 | GS77: 3 | GT77: 0 | GV77: =ROUND((GT77),6) -> 0 | GW77: 1 | GX77: =ROUND(HC77*I77,2) -> 0 | HA77: 0 | HB77: 0 | HC77: =GV77*GW77 -> 0 | HS77: 0 | IK77: 0
A78: 17 | B78: 1 | C78: =ROW(SmtRes!A36) -> 36 | D78: =ROW(EtalonRes!A38) -> 38 | F78: 4.10-134-7 | G78: Монтаж антенны дополнительной для приема ТВ на ранее установленной опоре, с действующими ТВ антеннами | H78: 1 антенна | I78: 1 | J78: 0 | K78: 1 | O78: =ROUND(CP78,2) -> 2930.08 | P78: =ROUND((ROUND((AC78*AW78*I78),2)*BC78),2) -> 1.01 | Q78: =(ROUND((ROUND((((ET78*1.2))*AV78*I78),2)*BB78),2)+ROUND((ROUND(((AE78-((EU78*1.2)))*AV78*I78),2)*BS78),2)) -> 0 | R78: =(ROUND((ROUND((((EU78*1.2))*AV78*I78),2)*BS78),2)+ROUND((ROUND(((AE78-((EU78*1.2)))*AV78*I78),2)*BS78),2)) -> 0 | S78: =ROUND((ROUND((AF78*AV78*I78),2)*BA78),2) -> 2929.07 | T78: =ROUND(CU78*I78,2) -> 0 | U78: =CV78*I78 -> 3.613188 | V78: =CW78*I78 -> 0 | W78: =ROUND(CX78*I78,2) -> 0 | X78: =(ROUND((((S78+ROUND((ROUND((((EU78*1.2))*AV78*I78),2)*BS78),2))*AT78)/100),2)+ROUND(((ROUND((ROUND(((AE78-((EU78*1.2)))*AV78*I78),2)*BS78),2)*AT78)/100),2)) -> 2782.62 | Y78: =(ROUND((((S78+ROUND((ROUND((((EU78*1.2))*AV78*I78),2)*BS78),2))*AU78)/100),2)+ROUND(((ROUND((ROUND(((AE78-((EU78*1.2)))*AV78*I78),2)*BS78),2)*AU78)/100),2)) -> 1552.41 | AA78: -1 | AB78: =ROUND((AC78+AD78+AF78),6) -> 48 | AC78: =ROUND(((ES78*1)),6) -> 0.18 | AD78: =ROUND(((((ET78*1.2))-((EU78*1.2)))+AE78),6) -> 0 | AE78: =ROUND(((EU78*1.2)),6) -> 0 | AF78: =ROUND(((EV78*1.2)),6) -> 47.82 | AG78: =ROUND((AP78),6) -> 0 | AH78: =((EW78*1.2)) -> 3.324 | AI78: =((EX78*1.2)) -> 0 | AJ78: =(AS78) -> 0 | AK78: 40.03 | AL78: 0.18 | AM78: 0 | AN78: 0 | AO78: 39.85 | AP78: 0 | AQ78: 2.77 | AR78: 0 | AS78: 0 | AT78: 95 | AU78: 53 | AV78: 1.087 | AW78: 1 | AZ78: 1 | BA78: 56.35 | BB78: 1 | BC78: 5.61 | BH78: 0 | BI78: 2 | BJ78: ТСН-2001.4 Доп. 81, Сб. 10, т. 134, поз. 7 | BM78: 69 | BN78: 0 | BO78: 4.10-134-7 | BP78: 1 | BQ78: 40 | BR78: 0 | BS78: 56.35 | BT78: 1 | BU78: 1 | BV78: 1 | BW78: 1 | BX78: 1 | BZ78: 95 | CA78: 53 | CE78: 1566 | CF78: 0 | CG78: 0 | CM78: 0 | CN78: Поправка: Гл.12.Прил.8.п.8. 3_12.00.01.11.001 Наименование: При наличии напряженных и стесненных условий производства работ (стесненность, сложность складирования и транспортной логистики и т.п.) для объектов, расположенных в пределах круговой магистральной системы улиц "Садовое кольцо" города Москвы | CO78: 0 | CP78: =(P78+Q78+S78) -> 2930.08 | CQ78: =ROUND((ROUND((AC78*AW78*1),2)*BC78),2) -> 1.01 | CR78: =(ROUND((ROUND((((ET78*1.2))*AV78*1),2)*BB78),2)+ROUND((ROUND(((AE78-((EU78*1.2)))*AV78*1),2)*BS78),2)) -> 0 | CS78: =(ROUND((ROUND((((EU78*1.2))*AV78*1),2)*BS78),2)+ROUND((ROUND(((AE78-((EU78*1.2)))*AV78*1),2)*BS78),2)) -> 0 | CT78: =ROUND((ROUND((AF78*AV78*1),2)*BA78),2) -> 2929.07 | CU78: =AG78 -> 0 | CV78: =(AH78*AV78) -> 3.613188 | CW78: =AI78 -> 0 | CX78: =AJ78 -> 0 | CY78: =(ROUND((((S78+ROUND((ROUND((((EU78*1.2))*AV78*1),2)*BS78),2))*AT78)/100),2)+ROUND(((ROUND((ROUND(((AE78-((EU78*1.2)))*AV78*1),2)*BS78),2)*AT78)/100),2)) -> 2782.62 | CZ78: =(ROUND((((S78+ROUND((ROUND((((EU78*1.2))*AV78*1),2)*BS78),2))*AU78)/100),2)+ROUND(((ROUND((ROUND(((AE78-((EU78*1.2)))*AV78*1),2)*BS78),2)*AU78)/100),2)) -> 1552.41 | DB78: 22 | DD78: *1 | DE78: *1,2 | DF78: *1,2 | DG78: *1,2 | DI78: *1,2 | DJ78: *1,2 | DN78: 0 | DO78: 0 | DP78: 1 | DQ78: 1 | DU78: 1013 | DV78: 1 антенна | DW78: 1 антенна | DX78: 1 | EE78: 55393973 | EF78: 40 | EG78: Монтаж оборудования | EH78: 0 | EJ78: 2 | EK78: 69 | EL78: ТСН-2001.4-10. Монтаж радиотелевизионного и электронного оборудования | EM78: ТСН-2001.4-10-2 | EO78: Поправка: Гл.12.Прил.8.п.8. 3_12.00.01.11.001 | EQ78: 132096 | ER78: 40.03 | ES78: 0.18 | ET78: 0 | EU78: 0 | EV78: 39.85 | EW78: 2.77 | EX78: 0 | EY78: 0 | FQ78: 0 | FR78: 0 | FS78: 0 | FX78: 95 | FY78: 53 | GD78: 1 | GF78: 2002393274 | GG78: 2 | GH78: 1 | GI78: 2 | GJ78: 0 | GK78: 0 | GL78: =ROUND(IF(AND(BH78=3,BI78=3,FS78<>0),P78,0),2) -> 0 | GM78: =ROUND(O78+X78+Y78,2)+GX78 -> 7265.11 | GN78: =IF(OR(BI78=0,BI78=1),GM78-GX78,0) -> 0 | GO78: =IF(BI78=2,GM78-GX78,0) -> 7265.11 | GP78: =IF(BI78=4,GM78-GX78,0) -> 0 | GR78: 0 | GS78: 3 | GT78: 0 | GV78: =ROUND((GT78),6) -> 0 | GW78: 1 | GX78: =ROUND(HC78*I78,2) -> 0 | HA78: 0 | HB78: 0 | HC78: =GV78*GW78 -> 0 | HS78: 0 | IK78: 0
A79: 17 | B79: 1 | E79: 8 | F79: КА2 | G79: Модуль часовой станции GPS / ГЛОНАСС Антенна (тип. SC GPS/GLO) 9тип SC GPS/GLO-A042 4) | H79: шт. | I79: 1 | J79: 0 | K79: 1 | O79: =ROUND(CP79,2) -> 12282.39 | P79: =ROUND((ROUND((AC79*I79),2)*BC79),2) -> 12282.39 | Q79: =(ROUND((ROUND(((ET79)*AV79*I79),2)*BB79),2)+ROUND((ROUND(((AE79-(EU79))*AV79*I79),2)*BS79),2)) -> 0 | R79: =(ROUND((ROUND(((EU79)*AV79*I79),2)*BS79),2)+ROUND((ROUND(((AE79-(EU79))*AV79*I79),2)*BS79),2)) -> 0 | S79: =ROUND((ROUND((AF79*AV79*I79),2)*BA79),2) -> 0 | T79: =ROUND(CU79*I79,2) -> 0 | U79: =CV79*I79 -> 0 | V79: =CW79*I79 -> 0 | W79: =ROUND(CX79*I79,2) -> 0 | X79: =(ROUND((((S79+ROUND((ROUND(((EU79)*AV79*I79),2)*BS79),2))*AT79)/100),2)+ROUND(((ROUND((ROUND(((AE79-(EU79))*AV79*I79),2)*BS79),2)*AT79)/100),2)) -> 0 | Y79: =(ROUND((((S79+ROUND((ROUND(((EU79)*AV79*I79),2)*BS79),2))*AU79)/100),2)+ROUND(((ROUND((ROUND(((AE79-(EU79))*AV79*I79),2)*BS79),2)*AU79)/100),2)) -> 0 | AA79: 55942966 | AB79: =ROUND((AC79+AD79+AF79),6) -> 12282.39 | AC79: =ROUND((ES79),6) -> 12282.39 | AD79: =ROUND((((ET79)-(EU79))+AE79),6) -> 0 | AE79: =ROUND((EU79),6) -> 0 | AF79: =ROUND((EV79),6) -> 0 | AG79: =ROUND((AP79),6) -> 0 | AH79: =(EW79) -> 0 | AI79: =(EX79) -> 0 | AJ79: =(AS79) -> 0 | AK79: 12282.39 | AL79: 12282.39 | AM79: 0 | AN79: 0 | AO79: 0 | AP79: 0 | AQ79: 0 | AR79: 0 | AS79: 0 | AT79: 0 | AU79: 0 | AV79: 1 | AW79: 1 | AZ79: 1 | BA79: 1 | BB79: 1 | BC79: 1 | BH79: 3 | BI79: 3 | BM79: 746 | BN79: 0 | BP79: 0 | BQ79: 130 | BR79: 0 | BS79: 1 | BT79: 1 | BU79: 1 | BV79: 1 | BW79: 1 | BX79: 1 | BZ79: 0 | CA79: 0 | CE79: 1566 | CF79: 0 | CG79: 0 | CM79: 0 | CO79: 0 | CP79: =(P79+Q79+S79) -> 12282.39 | CQ79: =ROUND((ROUND((AC79*1),2)*BC79),2) -> 12282.39 | CR79: =(ROUND((ROUND(((ET79)*AV79*1),2)*BB79),2)+ROUND((ROUND(((AE79-(EU79))*AV79*1),2)*BS79),2)) -> 0 | CS79: =(ROUND((ROUND(((EU79)*AV79*1),2)*BS79),2)+ROUND((ROUND(((AE79-(EU79))*AV79*1),2)*BS79),2)) -> 0 | CT79: =ROUND((ROUND((AF79*AV79*1),2)*BA79),2) -> 0 | CU79: =AG79 -> 0 | CV79: =(AH79*AV79) -> 0 | CW79: =AI79 -> 0 | CX79: =AJ79 -> 0 | CY79: =(ROUND((((S79+ROUND((ROUND(((EU79)*AV79*1),2)*BS79),2))*AT79)/100),2)+ROUND(((ROUND((ROUND(((AE79-(EU79))*AV79*1),2)*BS79),2)*AT79)/100),2)) -> 0 | CZ79: =(ROUND((((S79+ROUND((ROUND(((EU79)*AV79*1),2)*BS79),2))*AU79)/100),2)+ROUND(((ROUND((ROUND(((AE79-(EU79))*AV79*1),2)*BS79),2)*AU79)/100),2)) -> 0 | DN79: 0 | DO79: 0 | DP79: 1 | DQ79: 1 | DU79: 1010 | DV79: шт. | DW79: шт. | DX79: 1 | EE79: 55393877 | EF79: 130 | EG79: Сметная стоимость оборудования | EH79: 0 | EJ79: 3 | EK79: 746 | EL79: ТСН-2001.13. Сметная стоимость оборудования | EM79: ТСН-2001.13 | EQ79: 131072 | ER79: 0 | ES79: 12282.39 | ET79: 0 | EU79: 0 | EV79: 0 | EW79: 0 | EX79: 0 | EY79: 0 | FQ79: 0 | FR79: =P79 -> 12282.39 | FS79: 0 | FX79: 0 | FY79: 0 | GA79: [108 823 / 1,22 / 7,57] + 3% Трансп + 1,2% Заг.скл | GD79: 1 | GF79: 1166323966 | GG79: 2 | GH79: 4 | GI79: -2 | GJ79: 0 | GK79: 0 | GL79: =ROUND(IF(AND(BH79=3,BI79=3,FS79<>0),P79,0),2) -> 0 | GM79: =ROUND(O79+X79+Y79,2)+GX79 -> 12282.39 | GN79: =IF(OR(BI79=0,BI79=1),GM79-GX79,0) -> 0 | GO79: =IF(BI79=2,GM79-GX79,0) -> 0 | GP79: =IF(BI79=4,GM79-GX79,0) -> 0 | GR79: 0 | GS79: 2 | GT79: 0 | GV79: =ROUND((GT79),6) -> 0 | GW79: 1 | GX79: =ROUND(HC79*I79,2) -> 0 | HA79: 0 | HB79: 0 | HC79: =GV79*GW79 -> 0 | HE79: 3 | HF79: 1,2 | HS79: 0 | IK79: 0
A80: 17 | B80: 1 | E80: 8 | F80: КА2 | G80: Модуль часовой станции GPS / ГЛОНАСС Антенна (тип. SC GPS/GLO) 9тип SC GPS/GLO-A042 4) | H80: шт. | I80: 1 | J80: 0 | K80: 1 | O80: =ROUND(CP80,2) -> 92977.69 | P80: =ROUND((ROUND((AC80*I80),2)*BC80),2) -> 92977.69 | Q80: =(ROUND((ROUND(((ET80)*AV80*I80),2)*BB80),2)+ROUND((ROUND(((AE80-(EU80))*AV80*I80),2)*BS80),2)) -> 0 | R80: =(ROUND((ROUND(((EU80)*AV80*I80),2)*BS80),2)+ROUND((ROUND(((AE80-(EU80))*AV80*I80),2)*BS80),2)) -> 0 | S80: =ROUND((ROUND((AF80*AV80*I80),2)*BA80),2) -> 0 | T80: =ROUND(CU80*I80,2) -> 0 | U80: =CV80*I80 -> 0 | V80: =CW80*I80 -> 0 | W80: =ROUND(CX80*I80,2) -> 0 | X80: =(ROUND((((S80+ROUND((ROUND(((EU80)*AV80*I80),2)*BS80),2))*AT80)/100),2)+ROUND(((ROUND((ROUND(((AE80-(EU80))*AV80*I80),2)*BS80),2)*AT80)/100),2)) -> 0 | Y80: =(ROUND((((S80+ROUND((ROUND(((EU80)*AV80*I80),2)*BS80),2))*AU80)/100),2)+ROUND(((ROUND((ROUND(((AE80-(EU80))*AV80*I80),2)*BS80),2)*AU80)/100),2)) -> 0 | AA80: 55942968 | AB80: =ROUND((AC80+AD80+AF80),6) -> 12282.39 | AC80: =ROUND((ES80),6) -> 12282.39 | AD80: =ROUND((((ET80)-(EU80))+AE80),6) -> 0 | AE80: =ROUND((EU80),6) -> 0 | AF80: =ROUND((EV80),6) -> 0 | AG80: =ROUND((AP80),6) -> 0 | AH80: =(EW80) -> 0 | AI80: =(EX80) -> 0 | AJ80: =(AS80) -> 0 | AK80: 12282.39 | AL80: 12282.39 | AM80: 0 | AN80: 0 | AO80: 0 | AP80: 0 | AQ80: 0 | AR80: 0 | AS80: 0 | AT80: 0 | AU80: 0 | AV80: 1 | AW80: 1 | AZ80: 1 | BA80: 1 | BB80: 1 | BC80: 7.57 | BH80: 3 | BI80: 3 | BM80: 746 | BN80: 0 | BP80: 0 | BQ80: 130 | BR80: 0 | BS80: 1 | BT80: 1 | BU80: 1 | BV80: 1 | BW80: 1 | BX80: 1 | BZ80: 0 | CA80: 0 | CE80: 1566 | CF80: 0 | CG80: 0 | CM80: 0 | CO80: 0 | CP80: =(P80+Q80+S80) -> 92977.69 | CQ80: =ROUND((ROUND((AC80*1),2)*BC80),2) -> 92977.69 | CR80: =(ROUND((ROUND(((ET80)*AV80*1),2)*BB80),2)+ROUND((ROUND(((AE80-(EU80))*AV80*1),2)*BS80),2)) -> 0 | CS80: =(ROUND((ROUND(((EU80)*AV80*1),2)*BS80),2)+ROUND((ROUND(((AE80-(EU80))*AV80*1),2)*BS80),2)) -> 0 | CT80: =ROUND((ROUND((AF80*AV80*1),2)*BA80),2) -> 0 | CU80: =AG80 -> 0 | CV80: =(AH80*AV80) -> 0 | CW80: =AI80 -> 0 | CX80: =AJ80 -> 0 | CY80: =(ROUND((((S80+ROUND((ROUND(((EU80)*AV80*1),2)*BS80),2))*AT80)/100),2)+ROUND(((ROUND((ROUND(((AE80-(EU80))*AV80*1),2)*BS80),2)*AT80)/100),2)) -> 0 | CZ80: =(ROUND((((S80+ROUND((ROUND(((EU80)*AV80*1),2)*BS80),2))*AU80)/100),2)+ROUND(((ROUND((ROUND(((AE80-(EU80))*AV80*1),2)*BS80),2)*AU80)/100),2)) -> 0 | DN80: 0 | DO80: 0 | DP80: 1 | DQ80: 1 | DU80: 1010 | DV80: шт. | DW80: шт. | DX80: 1 | EE80: 55393877 | EF80: 130 | EG80: Сметная стоимость оборудования | EH80: 0 | EJ80: 3 | EK80: 746 | EL80: ТСН-2001.13. Сметная стоимость оборудования | EM80: ТСН-2001.13 | EQ80: 131072 | ER80: 12282.39 | ES80: 12282.39 | ET80: 0 | EU80: 0 | EV80: 0 | EW80: 0 | EX80: 0 | EY80: 0 | EZ80: 5 | FC80: 1 | FD80: 18 | FF80: 108823 | FQ80: 0 | FR80: =P80 -> 92977.69 | FS80: 0 | FX80: 0 | FY80: 0 | GA80: [108 823 / 1,22 / 7,57] + 3% Трансп + 1,2% Заг.скл | GD80: 1 | GF80: 1166323966 | GG80: 2 | GH80: 3 | GI80: 3 | GJ80: 0 | GK80: 0 | GL80: =ROUND(IF(AND(BH80=3,BI80=3,FS80<>0),P80,0),2) -> 0 | GM80: =ROUND(O80+X80+Y80,2)+GX80 -> 92977.69 | GN80: =IF(OR(BI80=0,BI80=1),GM80-GX80,0) -> 0 | GO80: =IF(BI80=2,GM80-GX80,0) -> 0 | GP80: =IF(BI80=4,GM80-GX80,0) -> 0 | GR80: 1 | GS80: 1 | GT80: 0 | GV80: =ROUND((GT80),6) -> 0 | GW80: 1 | GX80: =ROUND(HC80*I80,2) -> 0 | HA80: 0 | HB80: 0 | HC80: =GV80*GW80 -> 0 | HE80: 3 | HF80: 1,2 | HS80: 0 | IK80: 0
A81: 17 | B81: 1 | C81: =ROW(SmtRes!A51) -> 51 | D81: =ROW(EtalonRes!A55) -> 55 | E81: 9 | F81: 4.10-21-5 | G81: Грозозащита для воздушных абонентских линий | H81: 1 комплект | I81: 1 | J81: 0 | K81: 1 | O81: =ROUND(CP81,2) -> 90.18 | P81: =ROUND((ROUND((AC81*AW81*I81),2)*BC81),2) -> 42.61 | Q81: =(ROUND((ROUND((((ET81*1.2))*AV81*I81),2)*BB81),2)+ROUND((ROUND(((AE81-((EU81*1.2)))*AV81*I81),2)*BS81),2)) -> 0 | R81: =(ROUND((ROUND((((EU81*1.2))*AV81*I81),2)*BS81),2)+ROUND((ROUND(((AE81-((EU81*1.2)))*AV81*I81),2)*BS81),2)) -> 0 | S81: =ROUND((ROUND((AF81*AV81*I81),2)*BA81),2) -> 47.57 | T81: =ROUND(CU81*I81,2) -> 0 | U81: =CV81*I81 -> 3.7692 | V81: =CW81*I81 -> 0 | W81: =ROUND(CX81*I81,2) -> 0 | X81: =(ROUND((((S81+ROUND((ROUND((((EU81*1.2))*AV81*I81),2)*BS81),2))*AT81)/100),2)+ROUND(((ROUND((ROUND(((AE81-((EU81*1.2)))*AV81*I81),2)*BS81),2)*AT81)/100),2)) -> 42.81 | Y81: =(ROUND((((S81+ROUND((ROUND((((EU81*1.2))*AV81*I81),2)*BS81),2))*AU81)/100),2)+ROUND(((ROUND((ROUND(((AE81-((EU81*1.2)))*AV81*I81),2)*BS81),2)*AU81)/100),2)) -> 21.88 | AA81: 55942966 | AB81: =ROUND((AC81+AD81+AF81),6) -> 88.042 | AC81: =ROUND(((ES81*1)),6) -> 42.61 | AD81: =ROUND(((((ET81*1.2))-((EU81*1.2)))+AE81),6) -> 0 | AE81: =ROUND(((EU81*1.2)),6) -> 0 | AF81: =ROUND(((EV81*1.2)),6) -> 45.432 | AG81: =ROUND((AP81),6) -> 0 | AH81: =((EW81*1.2)) -> 3.6 | AI81: =((EX81*1.2)) -> 0 | AJ81: =(AS81) -> 0 | AK81: 80.47 | AL81: 42.61 | AM81: 0 | AN81: 0 | AO81: 37.86 | AP81: 0 | AQ81: 3 | AR81: 0 | AS81: 0 | AT81: 90 | AU81: 46 | AV81: 1.047 | AW81: 1 | AZ81: 1 | BA81: 1 | BB81: 1 | BC81: 1 | BH81: 0 | BI81: 2 | BJ81: ТСН-2001.4 Доп. 79, Сб. 10, т. 21, поз. 5 | BM81: 68 | BN81: 0 | BO81: 4.10-21-5 | BP81: 1 | BQ81: 40 | BR81: 0 | BS81: 1 | BT81: 1 | BU81: 1 | BV81: 1 | BW81: 1 | BX81: 1 | BZ81: 90 | CA81: 46 | CE81: 1566 | CF81: 0 | CG81: 0 | CM81: 0 | CN81: Поправка: Гл.12.Прил.8.п.8. 3_12.00.01.11.001 Наименование: При наличии напряженных и стесненных условий производства работ (стесненность, сложность складирования и транспортной логистики и т.п.) для объектов, расположенных в пределах круговой магистральной системы улиц "Садовое кольцо" города Москвы | CO81: 0 | CP81: =(P81+Q81+S81) -> 90.18 | CQ81: =ROUND((ROUND((AC81*AW81*1),2)*BC81),2) -> 42.61 | CR81: =(ROUND((ROUND((((ET81*1.2))*AV81*1),2)*BB81),2)+ROUND((ROUND(((AE81-((EU81*1.2)))*AV81*1),2)*BS81),2)) -> 0 | CS81: =(ROUND((ROUND((((EU81*1.2))*AV81*1),2)*BS81),2)+ROUND((ROUND(((AE81-((EU81*1.2)))*AV81*1),2)*BS81),2)) -> 0 | CT81: =ROUND((ROUND((AF81*AV81*1),2)*BA81),2) -> 47.57 | CU81: =AG81 -> 0 | CV81: =(AH81*AV81) -> 3.7692 | CW81: =AI81 -> 0 | CX81: =AJ81 -> 0 | CY81: =(ROUND((((S81+ROUND((ROUND((((EU81*1.2))*AV81*1),2)*BS81),2))*AT81)/100),2)+ROUND(((ROUND((ROUND(((AE81-((EU81*1.2)))*AV81*1),2)*BS81),2)*AT81)/100),2)) -> 42.81 | CZ81: =(ROUND((((S81+ROUND((ROUND((((EU81*1.2))*AV81*1),2)*BS81),2))*AU81)/100),2)+ROUND(((ROUND((ROUND(((AE81-((EU81*1.2)))*AV81*1),2)*BS81),2)*AU81)/100),2)) -> 21.88 | DB81: 23 | DD81: *1 | DE81: *1,2 | DF81: *1,2 | DG81: *1,2 | DI81: *1,2 | DJ81: *1,2 | DN81: 0 | DO81: 0 | DP81: 1 | DQ81: 1 | DU81: 1013 | DV81: 1 комплект | DW81: 1 комплект | DX81: 1 | EE81: 55393972 | EF81: 40 | EG81: Монтаж оборудования | EH81: 0 | EJ81: 2 | EK81: 68 | EL81: ТСН-2001.4-10. Прокладка и монтаж сетей связи | EM81: ТСН-2001.4-10-1 | EO81: Поправка: Гл.12.Прил.8.п.8. 3_12.00.01.11.001 | EQ81: 0 | ER81: 80.47 | ES81: 42.61 | ET81: 0 | EU81: 0 | EV81: 37.86 | EW81: 3 | EX81: 0 | EY81: 0 | FQ81: 0 | FR81: 0 | FS81: 0 | FX81: 90 | FY81: 46 | GD81: 1 | GF81: -1785550083 | GG81: 2 | GH81: 1 | GI81: 2 | GJ81: 0 | GK81: 0 | GL81: =ROUND(IF(AND(BH81=3,BI81=3,FS81<>0),P81,0),2) -> 0 | GM81: =ROUND(O81+X81+Y81,2)+GX81 -> 154.87 | GN81: =IF(OR(BI81=0,BI81=1),GM81-GX81,0) -> 0 | GO81: =IF(BI81=2,GM81-GX81,0) -> 154.87 | GP81: =IF(BI81=4,GM81-GX81,0) -> 0 | GR81: 0 | GS81: 3 | GT81: 0 | GV81: =ROUND((GT81),6) -> 0 | GW81: 1 | GX81: =ROUND(HC81*I81,2) -> 0 | HA81: 0 | HB81: 0 | HC81: =GV81*GW81 -> 0 | HS81: 0 | IK81: 0
A82: 17 | B82: 1 | C82: =ROW(SmtRes!A66) -> 66 | D82: =ROW(EtalonRes!A72) -> 72 | E82: 9 | F82: 4.10-21-5 | G82: Грозозащита для воздушных абонентских линий | H82: 1 комплект | I82: 1 | J82: 0 | K82: 1 | O82: =ROUND(CP82,2) -> 2900.01 | P82: =ROUND((ROUND((AC82*AW82*I82),2)*BC82),2) -> 219.44 | Q82: =(ROUND((ROUND((((ET82*1.2))*AV82*I82),2)*BB82),2)+ROUND((ROUND(((AE82-((EU82*1.2)))*AV82*I82),2)*BS82),2)) -> 0 | R82: =(ROUND((ROUND((((EU82*1.2))*AV82*I82),2)*BS82),2)+ROUND((ROUND(((AE82-((EU82*1.2)))*AV82*I82),2)*BS82),2)) -> 0 | S82: =ROUND((ROUND((AF82*AV82*I82),2)*BA82),2) -> 2680.57 | T82: =ROUND(CU82*I82,2) -> 0 | U82: =CV82*I82 -> 3.7692 | V82: =CW82*I82 -> 0 | W82: =ROUND(CX82*I82,2) -> 0 | X82: =(ROUND((((S82+ROUND((ROUND((((EU82*1.2))*AV82*I82),2)*BS82),2))*AT82)/100),2)+ROUND(((ROUND((ROUND(((AE82-((EU82*1.2)))*AV82*I82),2)*BS82),2)*AT82)/100),2)) -> 2412.51 | Y82: =(ROUND((((S82+ROUND((ROUND((((EU82*1.2))*AV82*I82),2)*BS82),2))*AU82)/100),2)+ROUND(((ROUND((ROUND(((AE82-((EU82*1.2)))*AV82*I82),2)*BS82),2)*AU82)/100),2)) -> 1233.06 | AA82: 55942968 | AB82: =ROUND((AC82+AD82+AF82),6) -> 88.042 | AC82: =ROUND(((ES82*1)),6) -> 42.61 | AD82: =ROUND(((((ET82*1.2))-((EU82*1.2)))+AE82),6) -> 0 | AE82: =ROUND(((EU82*1.2)),6) -> 0 | AF82: =ROUND(((EV82*1.2)),6) -> 45.432 | AG82: =ROUND((AP82),6) -> 0 | AH82: =((EW82*1.2)) -> 3.6 | AI82: =((EX82*1.2)) -> 0 | AJ82: =(AS82) -> 0 | AK82: 80.47 | AL82: 42.61 | AM82: 0 | AN82: 0 | AO82: 37.86 | AP82: 0 | AQ82: 3 | AR82: 0 | AS82: 0 | AT82: 90 | AU82: 46 | AV82: 1.047 | AW82: 1 | AZ82: 1 | BA82: 56.35 | BB82: 1 | BC82: 5.15 | BH82: 0 | BI82: 2 | BJ82: ТСН-2001.4 Доп. 79, Сб. 10, т. 21, поз. 5 | BM82: 68 | BN82: 0 | BO82: 4.10-21-5 | BP82: 1 | BQ82: 40 | BR82: 0 | BS82: 56.35 | BT82: 1 | BU82: 1 | BV82: 1 | BW82: 1 | BX82: 1 | BZ82: 90 | CA82: 46 | CE82: 1566 | CF82: 0 | CG82: 0 | CM82: 0 | CN82: Поправка: Гл.12.Прил.8.п.8. 3_12.00.01.11.001 Наименование: При наличии напряженных и стесненных условий производства работ (стесненность, сложность складирования и транспортной логистики и т.п.) для объектов, расположенных в пределах круговой магистральной системы улиц "Садовое кольцо" города Москвы | CO82: 0 | CP82: =(P82+Q82+S82) -> 2900.01 | CQ82: =ROUND((ROUND((AC82*AW82*1),2)*BC82),2) -> 219.44 | CR82: =(ROUND((ROUND((((ET82*1.2))*AV82*1),2)*BB82),2)+ROUND((ROUND(((AE82-((EU82*1.2)))*AV82*1),2)*BS82),2)) -> 0 | CS82: =(ROUND((ROUND((((EU82*1.2))*AV82*1),2)*BS82),2)+ROUND((ROUND(((AE82-((EU82*1.2)))*AV82*1),2)*BS82),2)) -> 0 | CT82: =ROUND((ROUND((AF82*AV82*1),2)*BA82),2) -> 2680.57 | CU82: =AG82 -> 0 | CV82: =(AH82*AV82) -> 3.7692 | CW82: =AI82 -> 0 | CX82: =AJ82 -> 0 | CY82: =(ROUND((((S82+ROUND((ROUND((((EU82*1.2))*AV82*1),2)*BS82),2))*AT82)/100),2)+ROUND(((ROUND((ROUND(((AE82-((EU82*1.2)))*AV82*1),2)*BS82),2)*AT82)/100),2)) -> 2412.51 | CZ82: =(ROUND((((S82+ROUND((ROUND((((EU82*1.2))*AV82*1),2)*BS82),2))*AU82)/100),2)+ROUND(((ROUND((ROUND(((AE82-((EU82*1.2)))*AV82*1),2)*BS82),2)*AU82)/100),2)) -> 1233.06 | DB82: 24 | DD82: *1 | DE82: *1,2 | DF82: *1,2 | DG82: *1,2 | DI82: *1,2 | DJ82: *1,2 | DN82: 0 | DO82: 0 | DP82: 1 | DQ82: 1 | DU82: 1013 | DV82: 1 комплект | DW82: 1 комплект | DX82: 1 | EE82: 55393972 | EF82: 40 | EG82: Монтаж оборудования | EH82: 0 | EJ82: 2 | EK82: 68 | EL82: ТСН-2001.4-10. Прокладка и монтаж сетей связи | EM82: ТСН-2001.4-10-1 | EO82: Поправка: Гл.12.Прил.8.п.8. 3_12.00.01.11.001 | EQ82: 0 | ER82: 80.47 | ES82: 42.61 | ET82: 0 | EU82: 0 | EV82: 37.86 | EW82: 3 | EX82: 0 | EY82: 0 | FQ82: 0 | FR82: 0 | FS82: 0 | FX82: 90 | FY82: 46 | GD82: 1 | GF82: -1785550083 | GG82: 2 | GH82: 1 | GI82: 2 | GJ82: 0 | GK82: 0 | GL82: =ROUND(IF(AND(BH82=3,BI82=3,FS82<>0),P82,0),2) -> 0 | GM82: =ROUND(O82+X82+Y82,2)+GX82 -> 6545.58 | GN82: =IF(OR(BI82=0,BI82=1),GM82-GX82,0) -> 0 | GO82: =IF(BI82=2,GM82-GX82,0) -> 6545.58 | GP82: =IF(BI82=4,GM82-GX82,0) -> 0 | GR82: 0 | GS82: 3 | GT82: 0 | GV82: =ROUND((GT82),6) -> 0 | GW82: 1 | GX82: =ROUND(HC82*I82,2) -> 0 | HA82: 0 | HB82: 0 | HC82: =GV82*GW82 -> 0 | HS82: 0 | IK82: 0
A83: 17 | B83: 1 | C83: =ROW(SmtRes!A68) -> 68 | D83: =ROW(EtalonRes!A74) -> 74 | F83: 4.10-136-1 | G83: Монтаж коробки телевизионной (ответвители, разветвители магистральные, домовые, абонентские), УСС, БФТК | H83: 1 ШТ. | I83: 1 | J83: 0 | K83: 1 | O83: =ROUND(CP83,2) -> 14.67 | P83: =ROUND((ROUND((AC83*AW83*I83),2)*BC83),2) -> 0.3 | Q83: =(ROUND((ROUND((((ET83*1.2))*AV83*I83),2)*BB83),2)+ROUND((ROUND(((AE83-((EU83*1.2)))*AV83*I83),2)*BS83),2)) -> 0 | R83: =(ROUND((ROUND((((EU83*1.2))*AV83*I83),2)*BS83),2)+ROUND((ROUND(((AE83-((EU83*1.2)))*AV83*I83),2)*BS83),2)) -> 0 | S83: =ROUND((ROUND((AF83*AV83*I83),2)*BA83),2) -> 14.37 | T83: =ROUND(CU83*I83,2) -> 0 | U83: =CV83*I83 -> 1.04352 | V83: =CW83*I83 -> 0 | W83: =ROUND(CX83*I83,2) -> 0 | X83: =(ROUND((((S83+ROUND((ROUND((((EU83*1.2))*AV83*I83),2)*BS83),2))*AT83)/100),2)+ROUND(((ROUND((ROUND(((AE83-((EU83*1.2)))*AV83*I83),2)*BS83),2)*AT83)/100),2)) -> 13.65 | Y83: =(ROUND((((S83+ROUND((ROUND((((EU83*1.2))*AV83*I83),2)*BS83),2))*AU83)/100),2)+ROUND(((ROUND((ROUND(((AE83-((EU83*1.2)))*AV83*I83),2)*BS83),2)*AU83)/100),2)) -> 7.62 | AA83: -1 | AB83: =ROUND((AC83+AD83+AF83),6) -> 13.524 | AC83: =ROUND(((ES83*1)),6) -> 0.3 | AD83: =ROUND(((((ET83*1.2))-((EU83*1.2)))+AE83),6) -> 0 | AE83: =ROUND(((EU83*1.2)),6) -> 0 | AF83: =ROUND(((EV83*1.2)),6) -> 13.224 | AG83: =ROUND((AP83),6) -> 0 | AH83: =((EW83*1.2)) -> 0.96 | AI83: =((EX83*1.2)) -> 0 | AJ83: =(AS83) -> 0 | AK83: 11.32 | AL83: 0.3 | AM83: 0 | AN83: 0 | AO83: 11.02 | AP83: 0 | AQ83: 0.8 | AR83: 0 | AS83: 0 | AT83: 95 | AU83: 53 | AV83: 1.087 | AW83: 1 | AZ83: 1 | BA83: 1 | BB83: 1 | BC83: 1 | BH83: 0 | BI83: 2 | BJ83: ТСН-2001.4 Доп. 81, Сб. 10, т. 136, поз. 1 | BM83: 69 | BN83: 0 | BO83: 4.10-136-1 | BP83: 1 | BQ83: 40 | BR83: 0 | BS83: 1 | BT83: 1 | BU83: 1 | BV83: 1 | BW83: 1 | BX83: 1 | BZ83: 95 | CA83: 53 | CE83: 1566 | CF83: 0 | CG83: 0 | CM83: 0 | CN83: Поправка: Гл.12.Прил.8.п.8. 3_12.00.01.11.001 Наименование: При наличии напряженных и стесненных условий производства работ (стесненность, сложность складирования и транспортной логистики и т.п.) для объектов, расположенных в пределах круговой магистральной системы улиц "Садовое кольцо" города Москвы | CO83: 0 | CP83: =(P83+Q83+S83) -> 14.67 | CQ83: =ROUND((ROUND((AC83*AW83*1),2)*BC83),2) -> 0.3 | CR83: =(ROUND((ROUND((((ET83*1.2))*AV83*1),2)*BB83),2)+ROUND((ROUND(((AE83-((EU83*1.2)))*AV83*1),2)*BS83),2)) -> 0 | CS83: =(ROUND((ROUND((((EU83*1.2))*AV83*1),2)*BS83),2)+ROUND((ROUND(((AE83-((EU83*1.2)))*AV83*1),2)*BS83),2)) -> 0 | CT83: =ROUND((ROUND((AF83*AV83*1),2)*BA83),2) -> 14.37 | CU83: =AG83 -> 0 | CV83: =(AH83*AV83) -> 1.04352 | CW83: =AI83 -> 0 | CX83: =AJ83 -> 0 | CY83: =(ROUND((((S83+ROUND((ROUND((((EU83*1.2))*AV83*1),2)*BS83),2))*AT83)/100),2)+ROUND(((ROUND((ROUND(((AE83-((EU83*1.2)))*AV83*1),2)*BS83),2)*AT83)/100),2)) -> 13.65 | CZ83: =(ROUND((((S83+ROUND((ROUND((((EU83*1.2))*AV83*1),2)*BS83),2))*AU83)/100),2)+ROUND(((ROUND((ROUND(((AE83-((EU83*1.2)))*AV83*1),2)*BS83),2)*AU83)/100),2)) -> 7.62 | DB83: 25 | DD83: *1 | DE83: *1,2 | DF83: *1,2 | DG83: *1,2 | DI83: *1,2 | DJ83: *1,2 | DN83: 0 | DO83: 0 | DP83: 1 | DQ83: 1 | DU83: 1013 | DV83: 1 ШТ. | DW83: 1 ШТ. | DX83: 1 | EE83: 55393973 | EF83: 40 | EG83: Монтаж оборудования | EH83: 0 | EJ83: 2 | EK83: 69 | EL83: ТСН-2001.4-10. Монтаж радиотелевизионного и электронного оборудования | EM83: ТСН-2001.4-10-2 | EO83: Поправка: Гл.12.Прил.8.п.8. 3_12.00.01.11.001 | EQ83: 132096 | ER83: 11.32 | ES83: 0.3 | ET83: 0 | EU83: 0 | EV83: 11.02 | EW83: 0.8 | EX83: 0 | EY83: 0 | FQ83: 0 | FR83: 0 | FS83: 0 | FX83: 95 | FY83: 53 | GD83: 1 | GF83: 765090221 | GG83: 2 | GH83: 1 | GI83: 2 | GJ83: 0 | GK83: 0 | GL83: =ROUND(IF(AND(BH83=3,BI83=3,FS83<>0),P83,0),2) -> 0 | GM83: =ROUND(O83+X83+Y83,2)+GX83 -> 35.94 | GN83: =IF(OR(BI83=0,BI83=1),GM83-GX83,0) -> 0 | GO83: =IF(BI83=2,GM83-GX83,0) -> 35.94 | GP83: =IF(BI83=4,GM83-GX83,0) -> 0 | GR83: 0 | GS83: 3 | GT83: 0 | GV83: =ROUND((GT83),6) -> 0 | GW83: 1 | GX83: =ROUND(HC83*I83,2) -> 0 | HA83: 0 | HB83: 0 | HC83: =GV83*GW83 -> 0 | HS83: 0 | IK83: 0
A84: 17 | B84: 1 | C84: =ROW(SmtRes!A70) -> 70 | D84: =ROW(EtalonRes!A76) -> 76 | F84: 4.10-136-1 | G84: Монтаж коробки телевизионной (ответвители, разветвители магистральные, домовые, абонентские), УСС, БФТК | H84: 1 ШТ. | I84: 1 | J84: 0 | K84: 1 | O84: =ROUND(CP84,2) -> 811.96 | P84: =ROUND((ROUND((AC84*AW84*I84),2)*BC84),2) -> 2.21 | Q84: =(ROUND((ROUND((((ET84*1.2))*AV84*I84),2)*BB84),2)+ROUND((ROUND(((AE84-((EU84*1.2)))*AV84*I84),2)*BS84),2)) -> 0 | R84: =(ROUND((ROUND((((EU84*1.2))*AV84*I84),2)*BS84),2)+ROUND((ROUND(((AE84-((EU84*1.2)))*AV84*I84),2)*BS84),2)) -> 0 | S84: =ROUND((ROUND((AF84*AV84*I84),2)*BA84),2) -> 809.75 | T84: =ROUND(CU84*I84,2) -> 0 | U84: =CV84*I84 -> 1.04352 | V84: =CW84*I84 -> 0 | W84: =ROUND(CX84*I84,2) -> 0 | X84: =(ROUND((((S84+ROUND((ROUND((((EU84*1.2))*AV84*I84),2)*BS84),2))*AT84)/100),2)+ROUND(((ROUND((ROUND(((AE84-((EU84*1.2)))*AV84*I84),2)*BS84),2)*AT84)/100),2)) -> 769.26 | Y84: =(ROUND((((S84+ROUND((ROUND((((EU84*1.2))*AV84*I84),2)*BS84),2))*AU84)/100),2)+ROUND(((ROUND((ROUND(((AE84-((EU84*1.2)))*AV84*I84),2)*BS84),2)*AU84)/100),2)) -> 429.17 | AA84: -1 | AB84: =ROUND((AC84+AD84+AF84),6) -> 13.524 | AC84: =ROUND(((ES84*1)),6) -> 0.3 | AD84: =ROUND(((((ET84*1.2))-((EU84*1.2)))+AE84),6) -> 0 | AE84: =ROUND(((EU84*1.2)),6) -> 0 | AF84: =ROUND(((EV84*1.2)),6) -> 13.224 | AG84: =ROUND((AP84),6) -> 0 | AH84: =((EW84*1.2)) -> 0.96 | AI84: =((EX84*1.2)) -> 0 | AJ84: =(AS84) -> 0 | AK84: 11.32 | AL84: 0.3 | AM84: 0 | AN84: 0 | AO84: 11.02 | AP84: 0 | AQ84: 0.8 | AR84: 0 | AS84: 0 | AT84: 95 | AU84: 53 | AV84: 1.087 | AW84: 1 | AZ84: 1 | BA84: 56.35 | BB84: 1 | BC84: 7.37 | BH84: 0 | BI84: 2 | BJ84: ТСН-2001.4 Доп. 81, Сб. 10, т. 136, поз. 1 | BM84: 69 | BN84: 0 | BO84: 4.10-136-1 | BP84: 1 | BQ84: 40 | BR84: 0 | BS84: 56.35 | BT84: 1 | BU84: 1 | BV84: 1 | BW84: 1 | BX84: 1 | BZ84: 95 | CA84: 53 | CE84: 1566 | CF84: 0 | CG84: 0 | CM84: 0 | CN84: Поправка: Гл.12.Прил.8.п.8. 3_12.00.01.11.001 Наименование: При наличии напряженных и стесненных условий производства работ (стесненность, сложность складирования и транспортной логистики и т.п.) для объектов, расположенных в пределах круговой магистральной системы улиц "Садовое кольцо" города Москвы | CO84: 0 | CP84: =(P84+Q84+S84) -> 811.96 | CQ84: =ROUND((ROUND((AC84*AW84*1),2)*BC84),2) -> 2.21 | CR84: =(ROUND((ROUND((((ET84*1.2))*AV84*1),2)*BB84),2)+ROUND((ROUND(((AE84-((EU84*1.2)))*AV84*1),2)*BS84),2)) -> 0 | CS84: =(ROUND((ROUND((((EU84*1.2))*AV84*1),2)*BS84),2)+ROUND((ROUND(((AE84-((EU84*1.2)))*AV84*1),2)*BS84),2)) -> 0 | CT84: =ROUND((ROUND((AF84*AV84*1),2)*BA84),2) -> 809.75 | CU84: =AG84 -> 0 | CV84: =(AH84*AV84) -> 1.04352 | CW84: =AI84 -> 0 | CX84: =AJ84 -> 0 | CY84: =(ROUND((((S84+ROUND((ROUND((((EU84*1.2))*AV84*1),2)*BS84),2))*AT84)/100),2)+ROUND(((ROUND((ROUND(((AE84-((EU84*1.2)))*AV84*1),2)*BS84),2)*AT84)/100),2)) -> 769.26 | CZ84: =(ROUND((((S84+ROUND((ROUND((((EU84*1.2))*AV84*1),2)*BS84),2))*AU84)/100),2)+ROUND(((ROUND((ROUND(((AE84-((EU84*1.2)))*AV84*1),2)*BS84),2)*AU84)/100),2)) -> 429.17 | DB84: 26 | DD84: *1 | DE84: *1,2 | DF84: *1,2 | DG84: *1,2 | DI84: *1,2 | DJ84: *1,2 | DN84: 0 | DO84: 0 | DP84: 1 | DQ84: 1 | DU84: 1013 | DV84: 1 ШТ. | DW84: 1 ШТ. | DX84: 1 | EE84: 55393973 | EF84: 40 | EG84: Монтаж оборудования | EH84: 0 | EJ84: 2 | EK84: 69 | EL84: ТСН-2001.4-10. Монтаж радиотелевизионного и электронного оборудования | EM84: ТСН-2001.4-10-2 | EO84: Поправка: Гл.12.Прил.8.п.8. 3_12.00.01.11.001 | EQ84: 132096 | ER84: 11.32 | ES84: 0.3 | ET84: 0 | EU84: 0 | EV84: 11.02 | EW84: 0.8 | EX84: 0 | EY84: 0 | FQ84: 0 | FR84: 0 | FS84: 0 | FX84: 95 | FY84: 53 | GD84: 1 | GF84: 765090221 | GG84: 2 | GH84: 1 | GI84: 2 | GJ84: 0 | GK84: 0 | GL84: =ROUND(IF(AND(BH84=3,BI84=3,FS84<>0),P84,0),2) -> 0 | GM84: =ROUND(O84+X84+Y84,2)+GX84 -> 2010.39 | GN84: =IF(OR(BI84=0,BI84=1),GM84-GX84,0) -> 0 | GO84: =IF(BI84=2,GM84-GX84,0) -> 2010.39 | GP84: =IF(BI84=4,GM84-GX84,0) -> 0 | GR84: 0 | GS84: 3 | GT84: 0 | GV84: =ROUND((GT84),6) -> 0 | GW84: 1 | GX84: =ROUND(HC84*I84,2) -> 0 | HA84: 0 | HB84: 0 | HC84: =GV84*GW84 -> 0 | HS84: 0 | IK84: 0
A85: 17 | B85: 1 | E85: 10 | F85: КА3 | G85: Модуль грозозащиты для антенны (тип. SC PTR) SC PTR-A0424 | H85: шт. | I85: 1 | J85: 0 | K85: 1 | O85: =ROUND(CP85,2) -> 12258.35 | P85: =ROUND((ROUND((AC85*I85),2)*BC85),2) -> 12258.35 | Q85: =(ROUND((ROUND(((ET85)*AV85*I85),2)*BB85),2)+ROUND((ROUND(((AE85-(EU85))*AV85*I85),2)*BS85),2)) -> 0 | R85: =(ROUND((ROUND(((EU85)*AV85*I85),2)*BS85),2)+ROUND((ROUND(((AE85-(EU85))*AV85*I85),2)*BS85),2)) -> 0 | S85: =ROUND((ROUND((AF85*AV85*I85),2)*BA85),2) -> 0 | T85: =ROUND(CU85*I85,2) -> 0 | U85: =CV85*I85 -> 0 | V85: =CW85*I85 -> 0 | W85: =ROUND(CX85*I85,2) -> 0 | X85: =(ROUND((((S85+ROUND((ROUND(((EU85)*AV85*I85),2)*BS85),2))*AT85)/100),2)+ROUND(((ROUND((ROUND(((AE85-(EU85))*AV85*I85),2)*BS85),2)*AT85)/100),2)) -> 0 | Y85: =(ROUND((((S85+ROUND((ROUND(((EU85)*AV85*I85),2)*BS85),2))*AU85)/100),2)+ROUND(((ROUND((ROUND(((AE85-(EU85))*AV85*I85),2)*BS85),2)*AU85)/100),2)) -> 0 | AA85: 55942966 | AB85: =ROUND((AC85+AD85+AF85),6) -> 12258.35 | AC85: =ROUND((ES85),6) -> 12258.35 | AD85: =ROUND((((ET85)-(EU85))+AE85),6) -> 0 | AE85: =ROUND((EU85),6) -> 0 | AF85: =ROUND((EV85),6) -> 0 | AG85: =ROUND((AP85),6) -> 0 | AH85: =(EW85) -> 0 | AI85: =(EX85) -> 0 | AJ85: =(AS85) -> 0 | AK85: 12258.35 | AL85: 12258.35 | AM85: 0 | AN85: 0 | AO85: 0 | AP85: 0 | AQ85: 0 | AR85: 0 | AS85: 0 | AT85: 0 | AU85: 0 | AV85: 1 | AW85: 1 | AZ85: 1 | BA85: 1 | BB85: 1 | BC85: 1 | BH85: 3 | BI85: 3 | BM85: 746 | BN85: 0 | BP85: 0 | BQ85: 130 | BR85: 0 | BS85: 1 | BT85: 1 | BU85: 1 | BV85: 1 | BW85: 1 | BX85: 1 | BZ85: 95 | CA85: 53 | CE85: 1566 | CF85: 0 | CG85: 0 | CM85: 0 | CO85: 0 | CP85: =(P85+Q85+S85) -> 12258.35 | CQ85: =ROUND((ROUND((AC85*1),2)*BC85),2) -> 12258.35 | CR85: =(ROUND((ROUND(((ET85)*AV85*1),2)*BB85),2)+ROUND((ROUND(((AE85-(EU85))*AV85*1),2)*BS85),2)) -> 0 | CS85: =(ROUND((ROUND(((EU85)*AV85*1),2)*BS85),2)+ROUND((ROUND(((AE85-(EU85))*AV85*1),2)*BS85),2)) -> 0 | CT85: =ROUND((ROUND((AF85*AV85*1),2)*BA85),2) -> 0 | CU85: =AG85 -> 0 | CV85: =(AH85*AV85) -> 0 | CW85: =AI85 -> 0 | CX85: =AJ85 -> 0 | CY85: =(ROUND((((S85+ROUND((ROUND(((EU85)*AV85*1),2)*BS85),2))*AT85)/100),2)+ROUND(((ROUND((ROUND(((AE85-(EU85))*AV85*1),2)*BS85),2)*AT85)/100),2)) -> 0 | CZ85: =(ROUND((((S85+ROUND((ROUND(((EU85)*AV85*1),2)*BS85),2))*AU85)/100),2)+ROUND(((ROUND((ROUND(((AE85-(EU85))*AV85*1),2)*BS85),2)*AU85)/100),2)) -> 0 | DN85: 0 | DO85: 0 | DP85: 1 | DQ85: 1 | DU85: 1010 | DV85: шт. | DW85: шт. | DX85: 1 | EE85: 55393877 | EF85: 130 | EG85: Сметная стоимость оборудования | EH85: 0 | EJ85: 3 | EK85: 746 | EL85: ТСН-2001.13. Сметная стоимость оборудования | EM85: ТСН-2001.13 | EQ85: 0 | ER85: 0 | ES85: 12258.35 | ET85: 0 | EU85: 0 | EV85: 0 | EW85: 0 | EX85: 0 | EY85: 0 | FQ85: 0 | FR85: =P85 -> 12258.35 | FS85: 0 | FX85: 95 | FY85: 53 | GA85: [108 610 / 1,22 / 7,57] + 3% Трансп + 1,2% Заг.скл | GD85: 1 | GF85: 253220946 | GG85: 2 | GH85: 4 | GI85: -2 | GJ85: 0 | GK85: 0 | GL85: =ROUND(IF(AND(BH85=3,BI85=3,FS85<>0),P85,0),2) -> 0 | GM85: =ROUND(O85+X85+Y85,2)+GX85 -> 12258.35 | GN85: =IF(OR(BI85=0,BI85=1),GM85-GX85,0) -> 0 | GO85: =IF(BI85=2,GM85-GX85,0) -> 0 | GP85: =IF(BI85=4,GM85-GX85,0) -> 0 | GR85: 0 | GS85: 2 | GT85: 0 | GV85: =ROUND((GT85),6) -> 0 | GW85: 1 | GX85: =ROUND(HC85*I85,2) -> 0 | HA85: 0 | HB85: 0 | HC85: =GV85*GW85 -> 0 | HE85: 3 | HF85: 1,2 | HS85: 0 | IK85: 0
A86: 17 | B86: 1 | E86: 10 | F86: КА3 | G86: Модуль грозозащиты для антенны (тип. SC PTR) SC PTR-A0424 | H86: шт. | I86: 1 | J86: 0 | K86: 1 | O86: =ROUND(CP86,2) -> 92795.71 | P86: =ROUND((ROUND((AC86*I86),2)*BC86),2) -> 92795.71 | Q86: =(ROUND((ROUND(((ET86)*AV86*I86),2)*BB86),2)+ROUND((ROUND(((AE86-(EU86))*AV86*I86),2)*BS86),2)) -> 0 | R86: =(ROUND((ROUND(((EU86)*AV86*I86),2)*BS86),2)+ROUND((ROUND(((AE86-(EU86))*AV86*I86),2)*BS86),2)) -> 0 | S86: =ROUND((ROUND((AF86*AV86*I86),2)*BA86),2) -> 0 | T86: =ROUND(CU86*I86,2) -> 0 | U86: =CV86*I86 -> 0 | V86: =CW86*I86 -> 0 | W86: =ROUND(CX86*I86,2) -> 0 | X86: =(ROUND((((S86+ROUND((ROUND(((EU86)*AV86*I86),2)*BS86),2))*AT86)/100),2)+ROUND(((ROUND((ROUND(((AE86-(EU86))*AV86*I86),2)*BS86),2)*AT86)/100),2)) -> 0 | Y86: =(ROUND((((S86+ROUND((ROUND(((EU86)*AV86*I86),2)*BS86),2))*AU86)/100),2)+ROUND(((ROUND((ROUND(((AE86-(EU86))*AV86*I86),2)*BS86),2)*AU86)/100),2)) -> 0 | AA86: 55942968 | AB86: =ROUND((AC86+AD86+AF86),6) -> 12258.35 | AC86: =ROUND((ES86),6) -> 12258.35 | AD86: =ROUND((((ET86)-(EU86))+AE86),6) -> 0 | AE86: =ROUND((EU86),6) -> 0 | AF86: =ROUND((EV86),6) -> 0 | AG86: =ROUND((AP86),6) -> 0 | AH86: =(EW86) -> 0 | AI86: =(EX86) -> 0 | AJ86: =(AS86) -> 0 | AK86: 12258.35 | AL86: 12258.35 | AM86: 0 | AN86: 0 | AO86: 0 | AP86: 0 | AQ86: 0 | AR86: 0 | AS86: 0 | AT86: 0 | AU86: 0 | AV86: 1 | AW86: 1 | AZ86: 1 | BA86: 1 | BB86: 1 | BC86: 7.57 | BH86: 3 | BI86: 3 | BM86: 746 | BN86: 0 | BP86: 0 | BQ86: 130 | BR86: 0 | BS86: 1 | BT86: 1 | BU86: 1 | BV86: 1 | BW86: 1 | BX86: 1 | BZ86: 95 | CA86: 53 | CE86: 1566 | CF86: 0 | CG86: 0 | CM86: 0 | CO86: 0 | CP86: =(P86+Q86+S86) -> 92795.71 | CQ86: =ROUND((ROUND((AC86*1),2)*BC86),2) -> 92795.71 | CR86: =(ROUND((ROUND(((ET86)*AV86*1),2)*BB86),2)+ROUND((ROUND(((AE86-(EU86))*AV86*1),2)*BS86),2)) -> 0 | CS86: =(ROUND((ROUND(((EU86)*AV86*1),2)*BS86),2)+ROUND((ROUND(((AE86-(EU86))*AV86*1),2)*BS86),2)) -> 0 | CT86: =ROUND((ROUND((AF86*AV86*1),2)*BA86),2) -> 0 | CU86: =AG86 -> 0 | CV86: =(AH86*AV86) -> 0 | CW86: =AI86 -> 0 | CX86: =AJ86 -> 0 | CY86: =(ROUND((((S86+ROUND((ROUND(((EU86)*AV86*1),2)*BS86),2))*AT86)/100),2)+ROUND(((ROUND((ROUND(((AE86-(EU86))*AV86*1),2)*BS86),2)*AT86)/100),2)) -> 0 | CZ86: =(ROUND((((S86+ROUND((ROUND(((EU86)*AV86*1),2)*BS86),2))*AU86)/100),2)+ROUND(((ROUND((ROUND(((AE86-(EU86))*AV86*1),2)*BS86),2)*AU86)/100),2)) -> 0 | DN86: 0 | DO86: 0 | DP86: 1 | DQ86: 1 | DU86: 1010 | DV86: шт. | DW86: шт. | DX86: 1 | EE86: 55393877 | EF86: 130 | EG86: Сметная стоимость оборудования | EH86: 0 | EJ86: 3 | EK86: 746 | EL86: ТСН-2001.13. Сметная стоимость оборудования | EM86: ТСН-2001.13 | EQ86: 0 | ER86: 12258.35 | ES86: 12258.35 | ET86: 0 | EU86: 0 | EV86: 0 | EW86: 0 | EX86: 0 | EY86: 0 | EZ86: 5 | FC86: 1 | FD86: 18 | FF86: 108610 | FQ86: 0 | FR86: =P86 -> 92795.71 | FS86: 0 | FX86: 95 | FY86: 53 | GA86: [108 610 / 1,22 / 7,57] + 3% Трансп + 1,2% Заг.скл | GD86: 1 | GF86: 253220946 | GG86: 2 | GH86: 3 | GI86: 3 | GJ86: 0 | GK86: 0 | GL86: =ROUND(IF(AND(BH86=3,BI86=3,FS86<>0),P86,0),2) -> 0 | GM86: =ROUND(O86+X86+Y86,2)+GX86 -> 92795.71 | GN86: =IF(OR(BI86=0,BI86=1),GM86-GX86,0) -> 0 | GO86: =IF(BI86=2,GM86-GX86,0) -> 0 | GP86: =IF(BI86=4,GM86-GX86,0) -> 0 | GR86: 1 | GS86: 1 | GT86: 0 | GV86: =ROUND((GT86),6) -> 0 | GW86: 1 | GX86: =ROUND(HC86*I86,2) -> 0 | HA86: 0 | HB86: 0 | HC86: =GV86*GW86 -> 0 | HE86: 3 | HF86: 1,2 | HS86: 0 | IK86: 0
A88: 51 | B88: =B67 -> 1 | C88: =A67 -> 4 | D88: =ROW(A67) -> 67 | F88: =IF(F67<>"",F67,"") -> Новый раздел | G88: =IF(G67<>"",G67,"") -> Комплект основного оборудования | H88: 0 | O88: =ROUND(AB88,2) -> 97162.73 | P88: =ROUND(AC88,2) -> 97047.99 | Q88: =ROUND(AD88,2) -> 0.63 | R88: =ROUND(AE88,2) -> 0.1 | S88: =ROUND(AF88,2) -> 114.11 | T88: =ROUND(AG88,2) -> 0 | U88: =AH88 -> 8.832492 | V88: =AI88 -> 0 | W88: =ROUND(AJ88,2) -> 0 | X88: =ROUND(AK88,2) -> 102.79 | Y88: =ROUND(AL88,2) -> 52.53 | AB88: =ROUND(SUMIF(AA71:AA86,"=55942966",O71:O86),2) -> 97162.73 | AC88: =ROUND(SUMIF(AA71:AA86,"=55942966",P71:P86),2) -> 97047.99 | AD88: =ROUND(SUMIF(AA71:AA86,"=55942966",Q71:Q86),2) -> 0.63 | AE88: =ROUND(SUMIF(AA71:AA86,"=55942966",R71:R86),2) -> 0.1 | AF88: =ROUND(SUMIF(AA71:AA86,"=55942966",S71:S86),2) -> 114.11 | AG88: =ROUND(SUMIF(AA71:AA86,"=55942966",T71:T86),2) -> 0 | AH88: =SUMIF(AA71:AA86,"=55942966",U71:U86) -> 8.832492 | AI88: =SUMIF(AA71:AA86,"=55942966",V71:V86) -> 0 | AJ88: =ROUND(SUMIF(AA71:AA86,"=55942966",W71:W86),2) -> 0 | AK88: =ROUND(SUMIF(AA71:AA86,"=55942966",X71:X86),2) -> 102.79 | AL88: =ROUND(SUMIF(AA71:AA86,"=55942966",Y71:Y86),2) -> 52.53 | AO88: =ROUND(BX88,2) -> 0 | AP88: =ROUND(BY88,2) -> 97004.92 | AQ88: =ROUND(BZ88,2) -> 0 | AR88: =ROUND(CA88,2) -> 97318.05 | AS88: =ROUND(CB88,2) -> 0 | AT88: =ROUND(CC88,2) -> 313.13 | AU88: =ROUND(CD88,2) -> 0 | AV88: =ROUND(CE88,2) -> 97047.99 | ... BD88: =ROUND(CM88,2) -> 0 | BX88: =ROUND(SUMIF(AA71:AA86,"=55942966",FQ71:FQ86),2) -> 0 | BY88: =ROUND(SUMIF(AA71:AA86,"=55942966",FR71:FR86),2) -> 97004.92 | BZ88: =ROUND(SUMIF(AA71:AA86,"=55942966",GL71:GL86),2) -> 0 | CA88: =ROUND(SUMIF(AA71:AA86,"=55942966",GM71:GM86),2) -> 97318.05 | CB88: =ROUND(SUMIF(AA71:AA86,"=55942966",GN71:GN86),2) -> 0 | CC88: =ROUND(SUMIF(AA71:AA86,"=55942966",GO71:GO86),2) -> 313.13 | CD88: =ROUND(SUMIF(AA71:AA86,"=55942966",GP71:GP86),2) -> 0 | CE88: =AC88-BX88 -> 97047.99 | CF88: =AC88-BY88 -> 43.07 | CG88: =BX88-BZ88 -> 0 | CH88: =AC88-BX88-BY88+BZ88 -> 43.07 | CI88: =BY88-BZ88 -> 97004.92 | CJ88: =ROUND(SUMIF(AA71:AA86,"=55942966",GX71:GX86),2) -> 0 | CK88: =ROUND(SUMIF(AA71:AA86,"=55942966",GY71:GY86),2) -> 0 | CL88: =ROUND(SUMIF(AA71:AA86,"=55942966",GZ71:GZ86),2) -> 0 | CM88: =ROUND(SUMIF(AA71:AA86,"=55942966",HD71:HD86),2) -> 0 | DG88: =ROUND(DT88,2) -> 740990.64 | DH88: =ROUND(DU88,2) -> 734549.82 | DI88: =ROUND(DV88,2) -> 10.72 | DJ88: =ROUND(DW88,2) -> 5.64 | DK88: =ROUND(DX88,2) -> 6430.1 | DL88: =ROUND(DY88,2) -> 0 | DM88: =DZ88 -> 8.832492 | DN88: =EA88 -> 0 | DO88: =ROUND(EB88,2) -> 0 | DP88: =ROUND(EC88,2) -> 5792.16 | DQ88: =ROUND(ED88,2) -> 2960.44 | DT88: =ROUND(SUMIF(AA71:AA86,"=55942968",O71:O86),2) -> 740990.64 | DU88: =ROUND(SUMIF(AA71:AA86,"=55942968",P71:P86),2) -> 734549.82 | DV88: =ROUND(SUMIF(AA71:AA86,"=55942968",Q71:Q86),2) -> 10.72 | DW88: =ROUND(SUMIF(AA71:AA86,"=55942968",R71:R86),2) -> 5.64 | DX88: =ROUND(SUMIF(AA71:AA86,"=55942968",S71:S86),2) -> 6430.1 | DY88: =ROUND(SUMIF(AA71:AA86,"=55942968",T71:T86),2) -> 0 | DZ88: =SUMIF(AA71:AA86,"=55942968",U71:U86) -> 8.832492 | EA88: =SUMIF(AA71:AA86,"=55942968",V71:V86) -> 0 | EB88: =ROUND(SUMIF(AA71:AA86,"=55942968",W71:W86),2) -> 0 | EC88: =ROUND(SUMIF(AA71:AA86,"=55942968",X71:X86),2) -> 5792.16 | ED88: =ROUND(SUMIF(AA71:AA86,"=55942968",Y71:Y86),2) -> 2960.44 | EG88: =ROUND(FP88,2) -> 0 | EH88: =ROUND(FQ88,2) -> 734327.24 | EI88: =ROUND(FR88,2) -> 0 | EJ88: =ROUND(FS88,2) -> 749743.24 | EK88: =ROUND(FT88,2) -> 0 | EL88: =ROUND(FU88,2) -> 15416 | EM88: =ROUND(FV88,2) -> 0 | EN88: =ROUND(FW88,2) -> 734549.82 | ... EV88: =ROUND(GE88,2) -> 0 | FP88: =ROUND(SUMIF(AA71:AA86,"=55942968",FQ71:FQ86),2) -> 0 | FQ88: =ROUND(SUMIF(AA71:AA86,"=55942968",FR71:FR86),2) -> 734327.24 | FR88: =ROUND(SUMIF(AA71:AA86,"=55942968",GL71:GL86),2) -> 0 | FS88: =ROUND(SUMIF(AA71:AA86,"=55942968",GM71:GM86),2) -> 749743.24 | FT88: =ROUND(SUMIF(AA71:AA86,"=55942968",GN71:GN86),2) -> 0 | FU88: =ROUND(SUMIF(AA71:AA86,"=55942968",GO71:GO86),2) -> 15416 | FV88: =ROUND(SUMIF(AA71:AA86,"=55942968",GP71:GP86),2) -> 0 | FW88: =DU88-FP88 -> 734549.82 | FX88: =DU88-FQ88 -> 222.58 | FY88: =FP88-FR88 -> 0 | FZ88: =DU88-FP88-FQ88+FR88 -> 222.58 | GA88: =FQ88-FR88 -> 734327.24 | GB88: =ROUND(SUMIF(AA71:AA86,"=55942968",GX71:GX86),2) -> 0 | GC88: =ROUND(SUMIF(AA71:AA86,"=55942968",GY71:GY86),2) -> 0 | GD88: =ROUND(SUMIF(AA71:AA86,"=55942968",GZ71:GZ86),2) -> 0 | GE88: =ROUND(SUMIF(AA71:AA86,"=55942968",HD71:HD86),2) -> 0 | GX88: 0
A90: 50 | B90: 0 | C90: 0 | D90: 1 | E90: 201 | F90: =ROUND(Source!O88,O90) -> 97162.73 | G90: ПЗ | H90: Прямые затраты | K90: 201 | L90: 1 | M90: 3 | O90: 2 | P90: =ROUND(Source!DG88,O90) -> 740990.64 | W90: 97162.73 | X90: 1 | Y90: 97162.73 | Z90: 740990.64 | AA90: 1 | AB90: 740990.64
A91: 50 | B91: 0 | C91: 0 | D91: 1 | E91: 202 | F91: =ROUND(Source!P88,O91) -> 97047.99 | G91: СтМатОб | H91: Стоимость материальных ресурсов (всего) | K91: 202 | L91: 2 | M91: 3 | O91: 2 | P91: =ROUND(Source!DH88,O91) -> 734549.82 | W91: 97047.99 | X91: 1 | Y91: 97047.99 | Z91: 734549.82 | AA91: 1 | AB91: 734549.82
A92: 50 | B92: 0 | C92: 0 | D92: 1 | E92: 222 | F92: =ROUND(Source!AO88,O92) -> 0 | G92: СтМатОбЗак | H92: Стоимость материалов и оборудования заказчика | K92: 222 | L92: 3 | M92: 3 | O92: 2 | P92: =ROUND(Source!EG88,O92) -> 0 | W92: 0 | X92: 1 | Y92: 0 | Z92: 0 | AA92: 1 | AB92: 0
A93: 50 | B93: 0 | C93: 0 | D93: 1 | E93: 225 | F93: =ROUND(Source!AV88,O93) -> 97047.99 | G93: СтМатОбПод | H93: Стоимость материалов и оборудования подрядчика | K93: 225 | L93: 4 | M93: 3 | O93: 2 | P93: =ROUND(Source!EN88,O93) -> 734549.82 | W93: 97047.99 | X93: 1 | Y93: 97047.99 | Z93: 734549.82 | AA93: 1 | AB93: 734549.82
A94: 50 | B94: 0 | C94: 0 | D94: 1 | E94: 226 | F94: =ROUND(Source!AW88,O94) -> 43.07 | G94: СтМат | H94: Стоимость материалов (всего) | K94: 226 | L94: 5 | M94: 3 | O94: 2 | P94: =ROUND(Source!EO88,O94) -> 222.58 | W94: 43.07 | X94: 1 | Y94: 43.07 | Z94: 222.58 | AA94: 1 | AB94: 222.58
A95: 50 | B95: 0 | C95: 0 | D95: 1 | E95: 227 | F95: =ROUND(Source!AX88,O95) -> 0 | G95: СтМатЗак | H95: Стоимость материалов заказчика | K95: 227 | L95: 6 | M95: 3 | O95: 2 | P95: =ROUND(Source!EP88,O95) -> 0 | W95: 0 | X95: 1 | Y95: 0 | Z95: 0 | AA95: 1 | AB95: 0
A96: 50 | B96: 0 | C96: 0 | D96: 1 | E96: 228 | F96: =ROUND(Source!AY88,O96) -> 43.07 | G96: СтМатПод | H96: Стоимость материалов подрядчика | K96: 228 | L96: 7 | M96: 3 | O96: 2 | P96: =ROUND(Source!EQ88,O96) -> 222.58 | W96: 43.07 | X96: 1 | Y96: 43.07 | Z96: 222.58 | AA96: 1 | AB96: 222.58
A97: 50 | B97: 0 | C97: 0 | D97: 1 | E97: 216 | F97: =ROUND(Source!AP88,O97) -> 97004.92 | G97: Оборуд | H97: Стоимость оборудования (всего) | K97: 216 | L97: 8 | M97: 3 | O97: 2 | P97: =ROUND(Source!EH88,O97) -> 734327.24 | W97: 97004.92 | X97: 1 | Y97: 97004.92 | Z97: 734327.24 | AA97: 1 | AB97: 734327.24
A98: 50 | B98: 0 | C98: 0 | D98: 1 | E98: 223 | F98: =ROUND(Source!AQ88,O98) -> 0 | G98: ОборудЗак | H98: Стоимость оборудования заказчика | K98: 223 | L98: 9 | M98: 3 | O98: 2 | P98: =ROUND(Source!EI88,O98) -> 0 | W98: 0 | X98: 1 | Y98: 0 | Z98: 0 | AA98: 1 | AB98: 0
A99: 50 | B99: 0 | C99: 0 | D99: 1 | E99: 229 | F99: =ROUND(Source!AZ88,O99) -> 97004.92 | G99: ОборудПод | H99: Стоимость оборудования подрядчика | K99: 229 | L99: 10 | M99: 3 | O99: 2 | P99: =ROUND(Source!ER88,O99) -> 734327.24 | W99: 97004.92 | X99: 1 | Y99: 97004.92 | Z99: 734327.24 | AA99: 1 | AB99: 734327.24
A100: 50 | B100: 0 | C100: 0 | D100: 1 | E100: 203 | F100: =ROUND(Source!Q88,O100) -> 0.63 | G100: ЭММ | H100: Эксплуатация машин | K100: 203 | L100: 11 | M100: 3 | O100: 2 | P100: =ROUND(Source!DI88,O100) -> 10.72 | W100: 0.63 | X100: 1 | Y100: 0.63 | Z100: 10.72 | AA100: 1 | AB100: 10.72
A101: 50 | B101: 0 | C101: 0 | D101: 1 | E101: 231 | F101: =ROUND(Source!BB88,O101) -> 0 | G101: ЭММсНРиСП | H101: Эксплуатация машин по ТСН-2001.16 | K101: 231 | L101: 12 | M101: 3 | O101: 2 | P101: =ROUND(Source!ET88,O101) -> 0 | W101: 0 | X101: 1 | Y101: 0 | Z101: 0 | AA101: 1 | AB101: 0
A102: 50 | B102: 0 | C102: 0 | D102: 1 | E102: 204 | F102: =ROUND(Source!R88,O102) -> 0.1 | G102: ЗПМ | H102: ЗП машинистов | K102: 204 | L102: 13 | M102: 3 | O102: 2 | P102: =ROUND(Source!DJ88,O102) -> 5.64 | W102: 0.1 | X102: 1 | Y102: 0.1 | Z102: 5.64 | AA102: 1 | AB102: 5.64
A103: 50 | B103: 0 | C103: 0 | D103: 1 | E103: 205 | F103: =ROUND(Source!S88,O103) -> 114.11 | G103: ОЗП | H103: Основная ЗП рабочих | K103: 205 | L103: 14 | M103: 3 | O103: 2 | P103: =ROUND(Source!DK88,O103) -> 6430.1 | W103: 114.11 | X103: 1 | Y103: 114.11 | Z103: 6430.1 | AA103: 1 | AB103: 6430.1
A104: 50 | B104: 0 | C104: 0 | D104: 1 | E104: 232 | F104: =ROUND(Source!BC88,O104) -> 0 | G104: ОЗПсНРиСП | H104: Основная ЗП рабочих по ТСН-2001.16 | K104: 232 | L104: 15 | M104: 3 | O104: 2 | P104: =ROUND(Source!EU88,O104) -> 0 | W104: 0 | X104: 1 | Y104: 0 | Z104: 0 | AA104: 1 | AB104: 0
A105: 50 | B105: 0 | C105: 0 | D105: 1 | E105: 214 | F105: =ROUND(Source!AS88,O105) -> 0 | G105: Строит | H105: Строительные работы с НР и СП | K105: 214 | L105: 16 | M105: 3 | O105: 2 | P105: =ROUND(Source!EK88,O105) -> 0 | W105: 0 | X105: 1 | Y105: 0 | Z105: 0 | AA105: 1 | AB105: 0
A106: 50 | B106: 0 | C106: 0 | D106: 1 | E106: 215 | F106: =ROUND(Source!AT88,O106) -> 313.13 | G106: Монтаж | H106: Монтажные работы с НР и СП | K106: 215 | L106: 17 | M106: 3 | O106: 2 | P106: =ROUND(Source!EL88,O106) -> 15416 | W106: 313.13 | X106: 1 | Y106: 313.13 | Z106: 15416 | AA106: 1 | AB106: 15416
A107: 50 | B107: 0 | C107: 0 | D107: 1 | E107: 217 | F107: =ROUND(Source!AU88,O107) -> 0 | G107: Прочие | H107: Прочие работы с НР и СП | K107: 217 | L107: 18 | M107: 3 | O107: 2 | P107: =ROUND(Source!EM88,O107) -> 0 | W107: 0 | X107: 1 | Y107: 0 | Z107: 0 | AA107: 1 | AB107: 0
A108: 50 | B108: 0 | C108: 0 | D108: 1 | E108: 230 | F108: =ROUND(Source!BA88,O108) -> 0 | G108: ПрочиеЗатр | H108: Прочие затраты по ТСН-2001.16 | K108: 230 | L108: 19 | M108: 3 | O108: 2 | P108: =ROUND(Source!ES88,O108) -> 0 | W108: 0 | X108: 1 | Y108: 0 | Z108: 0 | AA108: 1 | AB108: 0
A109: 50 | B109: 0 | C109: 0 | D109: 1 | E109: 206 | F109: =ROUND(Source!T88,O109) -> 0 | G109: ВозврМат | H109: Возврат материалов | K109: 206 | L109: 20 | M109: 3 | O109: 2 | P109: =ROUND(Source!DL88,O109) -> 0 | W109: 0 | X109: 1 | Y109: 0 | Z109: 0 | AA109: 1 | AB109: 0
A110: 50 | B110: 0 | C110: 0 | D110: 1 | E110: 207 | F110: =Source!U88 -> 8.832492 | G110: ТрудСтр | H110: Трудозатраты строителей | K110: 207 | L110: 21 | M110: 3 | O110: -1 | P110: =Source!DM88 -> 8.832492 | W110: 8.832492 | X110: 1 | Y110: 8.832492 | Z110: 8.832492 | AA110: 1 | AB110: 8.832492
A111: 50 | B111: 0 | C111: 0 | D111: 1 | E111: 208 | F111: =Source!V88 -> 0 | G111: ТрудМаш | H111: Трудозатраты машинистов | K111: 208 | L111: 22 | M111: 3 | O111: -1 | P111: =Source!DN88 -> 0 | W111: 0 | X111: 1 | Y111: 0 | Z111: 0 | AA111: 1 | AB111: 0
A112: 50 | B112: 0 | C112: 0 | D112: 1 | E112: 209 | F112: =ROUND(Source!W88,O112) -> 0 | G112: ТранспМат | H112: Транспорт материалов | K112: 209 | L112: 23 | M112: 3 | O112: 2 | P112: =ROUND(Source!DO88,O112) -> 0 | W112: 0 | X112: 1 | Y112: 0 | Z112: 0 | AA112: 1 | AB112: 0
A113: 50 | B113: 0 | C113: 0 | D113: 1 | E113: 233 | F113: =ROUND(Source!BD88,O113) -> 0 | G113: Перевозка | H113: Перевозка грузов | K113: 233 | L113: 24 | M113: 3 | O113: 2 | P113: =ROUND(Source!EV88,O113) -> 0 | W113: 0 | X113: 1 | Y113: 0 | Z113: 0 | AA113: 1 | AB113: 0
A114: 50 | B114: 0 | C114: 0 | D114: 1 | E114: 210 | F114: =ROUND(Source!X88,O114) -> 102.79 | G114: НР | H114: Накладные расходы | K114: 210 | L114: 25 | M114: 3 | O114: 2 | P114: =ROUND(Source!DP88,O114) -> 5792.16 | W114: 102.79 | X114: 1 | Y114: 102.79 | Z114: 5792.16 | AA114: 1 | AB114: 5792.16
A115: 50 | B115: 0 | C115: 0 | D115: 1 | E115: 211 | F115: =ROUND(Source!Y88,O115) -> 52.53 | G115: СмПриб | H115: Сметная прибыль | K115: 211 | L115: 26 | M115: 3 | O115: 2 | P115: =ROUND(Source!DQ88,O115) -> 2960.44 | W115: 52.53 | X115: 1 | Y115: 52.53 | Z115: 2960.44 | AA115: 1 | AB115: 2960.44
A116: 50 | B116: 0 | C116: 0 | D116: 1 | E116: 224 | F116: =ROUND(Source!AR88,O116) -> 97318.05 | G116: Всего | H116: Всего с НР и СП | K116: 224 | L116: 27 | M116: 3 | O116: 2 | P116: =ROUND(Source!EJ88,O116) -> 749743.24 | W116: 97318.05 | X116: 1 | Y116: 97318.05 | Z116: 749743.24 | AA116: 1 | AB116: 749743.24
A118: 4 | B118: 1 | D118: =ROW(A127) -> 127 | F118: Новый раздел | G118: Оборудование устанавливаемое по месту | I118: 0 | K118: 0 | S118: 0 | T118: 0 | V118: 0 | BX118: 0 | CJ118: 0
A120: 52 | B120: =B127 -> 1 | C120: =C127 -> 4 | D120: =D127 -> 118 | E120: =E127 -> 0 | F120: =F127 -> Новый раздел | G120: =G127 -> Оборудование устанавливаемое по месту | O120: =O127 -> 37564.33 | P120: =P127 -> 37474.62 | Q120: =Q127 -> 0 | R120: =R127 -> 0 | S120: =S127 -> 89.71 | T120: =T127 -> 0 | U120: =U127 -> 7.5384 | V120: =V127 -> 0 | ... GX120: =GX127 -> 0
A122: 17 | B122: 1 | C122: =ROW(SmtRes!A74) -> 74 | D122: =ROW(EtalonRes!A80) -> 80 | E122: 11 | F122: 4.10-86-1 | G122: Монтаж электрочасов вторичных для помещений односторонних на стене | H122: 1 ШТ. | I122: 3 | J122: 0 | K122: 3 | O122: =ROUND(CP122,2) -> 91.45 | P122: =ROUND((ROUND((AC122*AW122*I122),2)*BC122),2) -> 1.74 | Q122: =(ROUND((ROUND((((ET122*1.2))*AV122*I122),2)*BB122),2)+ROUND((ROUND(((AE122-((EU122*1.2)))*AV122*I122),2)*BS122),2)) -> 0 | R122: =(ROUND((ROUND((((EU122*1.2))*AV122*I122),2)*BS122),2)+ROUND((ROUND(((AE122-((EU122*1.2)))*AV122*I122),2)*BS122),2)) -> 0 | S122: =ROUND((ROUND((AF122*AV122*I122),2)*BA122),2) -> 89.71 | T122: =ROUND(CU122*I122,2) -> 0 | U122: =CV122*I122 -> 7.5384 | V122: =CW122*I122 -> 0 | W122: =ROUND(CX122*I122,2) -> 0 | X122: =(ROUND((((S122+ROUND((ROUND((((EU122*1.2))*AV122*I122),2)*BS122),2))*AT122)/100),2)+ROUND(((ROUND((ROUND(((AE122-((EU122*1.2)))*AV122*I122),2)*BS122),2)*AT122)/100),2)) -> 80.74 | Y122: =(ROUND((((S122+ROUND((ROUND((((EU122*1.2))*AV122*I122),2)*BS122),2))*AU122)/100),2)+ROUND(((ROUND((ROUND(((AE122-((EU122*1.2)))*AV122*I122),2)*BS122),2)*AU122)/100),2)) -> 41.27 | AA122: 55942966 | AB122: =ROUND((AC122+AD122+AF122),6) -> 29.14 | AC122: =ROUND(((ES122*1)),6) -> 0.58 | AD122: =ROUND(((((ET122*1.2))-((EU122*1.2)))+AE122),6) -> 0 | AE122: =ROUND(((EU122*1.2)),6) -> 0 | AF122: =ROUND(((EV122*1.2)),6) -> 28.56 | AG122: =ROUND((AP122),6) -> 0 | AH122: =((EW122*1.2)) -> 2.4 | AI122: =((EX122*1.2)) -> 0 | AJ122: =(AS122) -> 0 | AK122: 24.38 | AL122: 0.58 | AM122: 0 | AN122: 0 | AO122: 23.8 | AP122: 0 | AQ122: 2 | AR122: 0 | AS122: 0 | AT122: 90 | AU122: 46 | AV122: 1.047 | AW122: 1 | AZ122: 1 | BA122: 1 | BB122: 1 | BC122: 1 | BH122: 0 | BI122: 2 | BJ122: ТСН-2001.4 Доп. 81, Сб. 10, т. 86, поз. 1 | BM122: 68 | BN122: 0 | BO122: 4.10-86-1 | BP122: 1 | BQ122: 40 | BR122: 0 | BS122: 1 | BT122: 1 | BU122: 1 | BV122: 1 | BW122: 1 | BX122: 1 | BZ122: 90 | CA122: 46 | CE122: 1566 | CF122: 0 | CG122: 0 | CM122: 0 | CN122: Поправка: Гл.12.Прил.8.п.8. 3_12.00.01.11.001 Наименование: При наличии напряженных и стесненных условий производства работ (стесненность, сложность складирования и транспортной логистики и т.п.) для объектов, расположенных в пределах круговой магистральной системы улиц "Садовое кольцо" города Москвы | CO122: 0 | CP122: =(P122+Q122+S122) -> 91.45 | CQ122: =ROUND((ROUND((AC122*AW122*1),2)*BC122),2) -> 0.58 | CR122: =(ROUND((ROUND((((ET122*1.2))*AV122*1),2)*BB122),2)+ROUND((ROUND(((AE122-((EU122*1.2)))*AV122*1),2)*BS122),2)) -> 0 | CS122: =(ROUND((ROUND((((EU122*1.2))*AV122*1),2)*BS122),2)+ROUND((ROUND(((AE122-((EU122*1.2)))*AV122*1),2)*BS122),2)) -> 0 | CT122: =ROUND((ROUND((AF122*AV122*1),2)*BA122),2) -> 29.9 | CU122: =AG122 -> 0 | CV122: =(AH122*AV122) -> 2.5128 | CW122: =AI122 -> 0 | CX122: =AJ122 -> 0 | CY122: =(ROUND((((S122+ROUND((ROUND((((EU122*1.2))*AV122*1),2)*BS122),2))*AT122)/100),2)+ROUND(((ROUND((ROUND(((AE122-((EU122*1.2)))*AV122*1),2)*BS122),2)*AT122)/100),2)) -> 80.74 | CZ122: =(ROUND((((S122+ROUND((ROUND((((EU122*1.2))*AV122*1),2)*BS122),2))*AU122)/100),2)+ROUND(((ROUND((ROUND(((AE122-((EU122*1.2)))*AV122*1),2)*BS122),2)*AU122)/100),2)) -> 41.27 | DB122: 27 | DD122: *1 | DE122: *1,2 | DF122: *1,2 | DG122: *1,2 | DI122: *1,2 | DJ122: *1,2 | DN122: 0 | DO122: 0 | DP122: 1 | DQ122: 1 | DU122: 1013 | DV122: 1 ШТ. | DW122: 1 ШТ. | DX122: 1 | EE122: 55393972 | EF122: 40 | EG122: Монтаж оборудования | EH122: 0 | EJ122: 2 | EK122: 68 | EL122: ТСН-2001.4-10. Прокладка и монтаж сетей связи | EM122: ТСН-2001.4-10-1 | EO122: Поправка: Гл.12.Прил.8.п.8. 3_12.00.01.11.001 | EQ122: 131072 | ER122: 24.38 | ES122: 0.58 | ET122: 0 | EU122: 0 | EV122: 23.8 | EW122: 2 | EX122: 0 | EY122: 0 | FQ122: 0 | FR122: 0 | FS122: 0 | FX122: 90 | FY122: 46 | GD122: 1 | GF122: 1819152192 | GG122: 2 | GH122: 1 | GI122: 2 | GJ122: 0 | GK122: 0 | GL122: =ROUND(IF(AND(BH122=3,BI122=3,FS122<>0),P122,0),2) -> 0 | GM122: =ROUND(O122+X122+Y122,2)+GX122 -> 213.46 | GN122: =IF(OR(BI122=0,BI122=1),GM122-GX122,0) -> 0 | GO122: =IF(BI122=2,GM122-GX122,0) -> 213.46 | GP122: =IF(BI122=4,GM122-GX122,0) -> 0 | GR122: 0 | GS122: 3 | GT122: 0 | GV122: =ROUND((GT122),6) -> 0 | GW122: 1 | GX122: =ROUND(HC122*I122,2) -> 0 | HA122: 0 | HB122: 0 | HC122: =GV122*GW122 -> 0 | HS122: 0 | IK122: 0
A123: 17 | B123: 1 | C123: =ROW(SmtRes!A78) -> 78 | D123: =ROW(EtalonRes!A84) -> 84 | E123: 11 | F123: 4.10-86-1 | G123: Монтаж электрочасов вторичных для помещений односторонних на стене | H123: 1 ШТ. | I123: 3 | J123: 0 | K123: 3 | O123: =ROUND(CP123,2) -> 5067.39 | P123: =ROUND((ROUND((AC123*AW123*I123),2)*BC123),2) -> 12.23 | Q123: =(ROUND((ROUND((((ET123*1.2))*AV123*I123),2)*BB123),2)+ROUND((ROUND(((AE123-((EU123*1.2)))*AV123*I123),2)*BS123),2)) -> 0 | R123: =(ROUND((ROUND((((EU123*1.2))*AV123*I123),2)*BS123),2)+ROUND((ROUND(((AE123-((EU123*1.2)))*AV123*I123),2)*BS123),2)) -> 0 | S123: =ROUND((ROUND((AF123*AV123*I123),2)*BA123),2) -> 5055.16 | T123: =ROUND(CU123*I123,2) -> 0 | U123: =CV123*I123 -> 7.5384 | V123: =CW123*I123 -> 0 | W123: =ROUND(CX123*I123,2) -> 0 | X123: =(ROUND((((S123+ROUND((ROUND((((EU123*1.2))*AV123*I123),2)*BS123),2))*AT123)/100),2)+ROUND(((ROUND((ROUND(((AE123-((EU123*1.2)))*AV123*I123),2)*BS123),2)*AT123)/100),2)) -> 4549.64 | Y123: =(ROUND((((S123+ROUND((ROUND((((EU123*1.2))*AV123*I123),2)*BS123),2))*AU123)/100),2)+ROUND(((ROUND((ROUND(((AE123-((EU123*1.2)))*AV123*I123),2)*BS123),2)*AU123)/100),2)) -> 2325.37 | AA123: 55942968 | AB123: =ROUND((AC123+AD123+AF123),6) -> 29.14 | AC123: =ROUND(((ES123*1)),6) -> 0.58 | AD123: =ROUND(((((ET123*1.2))-((EU123*1.2)))+AE123),6) -> 0 | AE123: =ROUND(((EU123*1.2)),6) -> 0 | AF123: =ROUND(((EV123*1.2)),6) -> 28.56 | AG123: =ROUND((AP123),6) -> 0 | AH123: =((EW123*1.2)) -> 2.4 | AI123: =((EX123*1.2)) -> 0 | AJ123: =(AS123) -> 0 | AK123: 24.38 | AL123: 0.58 | AM123: 0 | AN123: 0 | AO123: 23.8 | AP123: 0 | AQ123: 2 | AR123: 0 | AS123: 0 | AT123: 90 | AU123: 46 | AV123: 1.047 | AW123: 1 | AZ123: 1 | BA123: 56.35 | BB123: 1 | BC123: 7.03 | BH123: 0 | BI123: 2 | BJ123: ТСН-2001.4 Доп. 81, Сб. 10, т. 86, поз. 1 | BM123: 68 | BN123: 0 | BO123: 4.10-86-1 | BP123: 1 | BQ123: 40 | BR123: 0 | BS123: 56.35 | BT123: 1 | BU123: 1 | BV123: 1 | BW123: 1 | BX123: 1 | BZ123: 90 | CA123: 46 | CE123: 1566 | CF123: 0 | CG123: 0 | CM123: 0 | CN123: Поправка: Гл.12.Прил.8.п.8. 3_12.00.01.11.001 Наименование: При наличии напряженных и стесненных условий производства работ (стесненность, сложность складирования и транспортной логистики и т.п.) для объектов, расположенных в пределах круговой магистральной системы улиц "Садовое кольцо" города Москвы | CO123: 0 | CP123: =(P123+Q123+S123) -> 5067.39 | CQ123: =ROUND((ROUND((AC123*AW123*1),2)*BC123),2) -> 4.08 | CR123: =(ROUND((ROUND((((ET123*1.2))*AV123*1),2)*BB123),2)+ROUND((ROUND(((AE123-((EU123*1.2)))*AV123*1),2)*BS123),2)) -> 0 | CS123: =(ROUND((ROUND((((EU123*1.2))*AV123*1),2)*BS123),2)+ROUND((ROUND(((AE123-((EU123*1.2)))*AV123*1),2)*BS123),2)) -> 0 | CT123: =ROUND((ROUND((AF123*AV123*1),2)*BA123),2) -> 1684.87 | CU123: =AG123 -> 0 | CV123: =(AH123*AV123) -> 2.5128 | CW123: =AI123 -> 0 | CX123: =AJ123 -> 0 | CY123: =(ROUND((((S123+ROUND((ROUND((((EU123*1.2))*AV123*1),2)*BS123),2))*AT123)/100),2)+ROUND(((ROUND((ROUND(((AE123-((EU123*1.2)))*AV123*1),2)*BS123),2)*AT123)/100),2)) -> 4549.64 | CZ123: =(ROUND((((S123+ROUND((ROUND((((EU123*1.2))*AV123*1),2)*BS123),2))*AU123)/100),2)+ROUND(((ROUND((ROUND(((AE123-((EU123*1.2)))*AV123*1),2)*BS123),2)*AU123)/100),2)) -> 2325.37 | DB123: 28 | DD123: *1 | DE123: *1,2 | DF123: *1,2 | DG123: *1,2 | DI123: *1,2 | DJ123: *1,2 | DN123: 0 | DO123: 0 | DP123: 1 | DQ123: 1 | DU123: 1013 | DV123: 1 ШТ. | DW123: 1 ШТ. | DX123: 1 | EE123: 55393972 | EF123: 40 | EG123: Монтаж оборудования | EH123: 0 | EJ123: 2 | EK123: 68 | EL123: ТСН-2001.4-10. Прокладка и монтаж сетей связи | EM123: ТСН-2001.4-10-1 | EO123: Поправка: Гл.12.Прил.8.п.8. 3_12.00.01.11.001 | EQ123: 131072 | ER123: 24.38 | ES123: 0.58 | ET123: 0 | EU123: 0 | EV123: 23.8 | EW123: 2 | EX123: 0 | EY123: 0 | FQ123: 0 | FR123: 0 | FS123: 0 | FX123: 90 | FY123: 46 | GD123: 1 | GF123: 1819152192 | GG123: 2 | GH123: 1 | GI123: 2 | GJ123: 0 | GK123: 0 | GL123: =ROUND(IF(AND(BH123=3,BI123=3,FS123<>0),P123,0),2) -> 0 | GM123: =ROUND(O123+X123+Y123,2)+GX123 -> 11942.4 | GN123: =IF(OR(BI123=0,BI123=1),GM123-GX123,0) -> 0 | GO123: =IF(BI123=2,GM123-GX123,0) -> 11942.4 | GP123: =IF(BI123=4,GM123-GX123,0) -> 0 | GR123: 0 | GS123: 3 | GT123: 0 | GV123: =ROUND((GT123),6) -> 0 | GW123: 1 | GX123: =ROUND(HC123*I123,2) -> 0 | HA123: 0 | HB123: 0 | HC123: =GV123*GW123 -> 0 | HS123: 0 | IK123: 0
A124: 17 | B124: 1 | E124: 12 | F124: КА4 | G124: КОНТУР D - часы повторители, цифровое LED табло, цифры высотой 10 мм, часы/минуты/секунды, цвет зеленый, односторонние (тип. SC KDG 10Gs) SC KDG 10Gs-IP-A0124 | H124: шт. | I124: 3 | J124: 0 | K124: 3 | O124: =ROUND(CP124,2) -> 37472.88 | P124: =ROUND((ROUND((AC124*I124),2)*BC124),2) -> 37472.88 | Q124: =(ROUND((ROUND(((ET124)*AV124*I124),2)*BB124),2)+ROUND((ROUND(((AE124-(EU124))*AV124*I124),2)*BS124),2)) -> 0 | R124: =(ROUND((ROUND(((EU124)*AV124*I124),2)*BS124),2)+ROUND((ROUND(((AE124-(EU124))*AV124*I124),2)*BS124),2)) -> 0 | S124: =ROUND((ROUND((AF124*AV124*I124),2)*BA124),2) -> 0 | T124: =ROUND(CU124*I124,2) -> 0 | U124: =CV124*I124 -> 0 | V124: =CW124*I124 -> 0 | W124: =ROUND(CX124*I124,2) -> 0 | X124: =(ROUND((((S124+ROUND((ROUND(((EU124)*AV124*I124),2)*BS124),2))*AT124)/100),2)+ROUND(((ROUND((ROUND(((AE124-(EU124))*AV124*I124),2)*BS124),2)*AT124)/100),2)) -> 0 | Y124: =(ROUND((((S124+ROUND((ROUND(((EU124)*AV124*I124),2)*BS124),2))*AU124)/100),2)+ROUND(((ROUND((ROUND(((AE124-(EU124))*AV124*I124),2)*BS124),2)*AU124)/100),2)) -> 0 | AA124: 55942966 | AB124: =ROUND((AC124+AD124+AF124),6) -> 12490.96 | AC124: =ROUND((ES124),6) -> 12490.96 | AD124: =ROUND((((ET124)-(EU124))+AE124),6) -> 0 | AE124: =ROUND((EU124),6) -> 0 | AF124: =ROUND((EV124),6) -> 0 | AG124: =ROUND((AP124),6) -> 0 | AH124: =(EW124) -> 0 | AI124: =(EX124) -> 0 | AJ124: =(AS124) -> 0 | AK124: 12490.96 | AL124: 12490.96 | AM124: 0 | AN124: 0 | AO124: 0 | AP124: 0 | AQ124: 0 | AR124: 0 | AS124: 0 | AT124: 0 | AU124: 0 | AV124: 1 | AW124: 1 | AZ124: 1 | BA124: 1 | BB124: 1 | BC124: 1 | BH124: 3 | BI124: 3 | BM124: 746 | BN124: 0 | BP124: 0 | BQ124: 130 | BR124: 0 | BS124: 1 | BT124: 1 | BU124: 1 | BV124: 1 | BW124: 1 | BX124: 1 | BZ124: 0 | CA124: 0 | CE124: 1566 | CF124: 0 | CG124: 0 | CM124: 0 | CO124: 0 | CP124: =(P124+Q124+S124) -> 37472.88 | CQ124: =ROUND((ROUND((AC124*1),2)*BC124),2) -> 12490.96 | CR124: =(ROUND((ROUND(((ET124)*AV124*1),2)*BB124),2)+ROUND((ROUND(((AE124-(EU124))*AV124*1),2)*BS124),2)) -> 0 | CS124: =(ROUND((ROUND(((EU124)*AV124*1),2)*BS124),2)+ROUND((ROUND(((AE124-(EU124))*AV124*1),2)*BS124),2)) -> 0 | CT124: =ROUND((ROUND((AF124*AV124*1),2)*BA124),2) -> 0 | CU124: =AG124 -> 0 | CV124: =(AH124*AV124) -> 0 | CW124: =AI124 -> 0 | CX124: =AJ124 -> 0 | CY124: =(ROUND((((S124+ROUND((ROUND(((EU124)*AV124*1),2)*BS124),2))*AT124)/100),2)+ROUND(((ROUND((ROUND(((AE124-(EU124))*AV124*1),2)*BS124),2)*AT124)/100),2)) -> 0 | CZ124: =(ROUND((((S124+ROUND((ROUND(((EU124)*AV124*1),2)*BS124),2))*AU124)/100),2)+ROUND(((ROUND((ROUND(((AE124-(EU124))*AV124*1),2)*BS124),2)*AU124)/100),2)) -> 0 | DN124: 0 | DO124: 0 | DP124: 1 | DQ124: 1 | DU124: 1010 | DV124: шт. | DW124: шт. | DX124: 1 | EE124: 55393877 | EF124: 130 | EG124: Сметная стоимость оборудования | EH124: 0 | EJ124: 3 | EK124: 746 | EL124: ТСН-2001.13. Сметная стоимость оборудования | EM124: ТСН-2001.13 | EQ124: 131072 | ER124: 0 | ES124: 12490.96 | ET124: 0 | EU124: 0 | EV124: 0 | EW124: 0 | EX124: 0 | EY124: 0 | FQ124: 0 | FR124: =P124 -> 37472.88 | FS124: 0 | FX124: 0 | FY124: 0 | GA124: [110 671 / 1,22 / 7,57] + 3% Трансп + 1,2% Заг.скл | GD124: 1 | GF124: 313033476 | GG124: 2 | GH124: 4 | GI124: -2 | GJ124: 0 | GK124: 0 | GL124: =ROUND(IF(AND(BH124=3,BI124=3,FS124<>0),P124,0),2) -> 0 | GM124: =ROUND(O124+X124+Y124,2)+GX124 -> 37472.88 | GN124: =IF(OR(BI124=0,BI124=1),GM124-GX124,0) -> 0 | GO124: =IF(BI124=2,GM124-GX124,0) -> 0 | GP124: =IF(BI124=4,GM124-GX124,0) -> 0 | GR124: 0 | GS124: 2 | GT124: 0 | GV124: =ROUND((GT124),6) -> 0 | GW124: 1 | GX124: =ROUND(HC124*I124,2) -> 0 | HA124: 0 | HB124: 0 | HC124: =GV124*GW124 -> 0 | HE124: 3 | HF124: 1,2 | HS124: 0 | IK124: 0
A125: 17 | B125: 1 | E125: 12 | F125: КА4 | G125: КОНТУР D - часы повторители, цифровое LED табло, цифры высотой 10 мм, часы/минуты/секунды, цвет зеленый, односторонние (тип. SC KDG 10Gs) SC KDG 10Gs-IP-A0124 | H125: шт. | I125: 3 | J125: 0 | K125: 3 | O125: =ROUND(CP125,2) -> 283669.7 | P125: =ROUND((ROUND((AC125*I125),2)*BC125),2) -> 283669.7 | Q125: =(ROUND((ROUND(((ET125)*AV125*I125),2)*BB125),2)+ROUND((ROUND(((AE125-(EU125))*AV125*I125),2)*BS125),2)) -> 0 | R125: =(ROUND((ROUND(((EU125)*AV125*I125),2)*BS125),2)+ROUND((ROUND(((AE125-(EU125))*AV125*I125),2)*BS125),2)) -> 0 | S125: =ROUND((ROUND((AF125*AV125*I125),2)*BA125),2) -> 0 | T125: =ROUND(CU125*I125,2) -> 0 | U125: =CV125*I125 -> 0 | V125: =CW125*I125 -> 0 | W125: =ROUND(CX125*I125,2) -> 0 | X125: =(ROUND((((S125+ROUND((ROUND(((EU125)*AV125*I125),2)*BS125),2))*AT125)/100),2)+ROUND(((ROUND((ROUND(((AE125-(EU125))*AV125*I125),2)*BS125),2)*AT125)/100),2)) -> 0 | Y125: =(ROUND((((S125+ROUND((ROUND(((EU125)*AV125*I125),2)*BS125),2))*AU125)/100),2)+ROUND(((ROUND((ROUND(((AE125-(EU125))*AV125*I125),2)*BS125),2)*AU125)/100),2)) -> 0 | AA125: 55942968 | AB125: =ROUND((AC125+AD125+AF125),6) -> 12490.96 | AC125: =ROUND((ES125),6) -> 12490.96 | AD125: =ROUND((((ET125)-(EU125))+AE125),6) -> 0 | AE125: =ROUND((EU125),6) -> 0 | AF125: =ROUND((EV125),6) -> 0 | AG125: =ROUND((AP125),6) -> 0 | AH125: =(EW125) -> 0 | AI125: =(EX125) -> 0 | AJ125: =(AS125) -> 0 | AK125: 12490.96 | AL125: 12490.96 | AM125: 0 | AN125: 0 | AO125: 0 | AP125: 0 | AQ125: 0 | AR125: 0 | AS125: 0 | AT125: 0 | AU125: 0 | AV125: 1 | AW125: 1 | AZ125: 1 | BA125: 1 | BB125: 1 | BC125: 7.57 | BH125: 3 | BI125: 3 | BM125: 746 | BN125: 0 | BP125: 0 | BQ125: 130 | BR125: 0 | BS125: 1 | BT125: 1 | BU125: 1 | BV125: 1 | BW125: 1 | BX125: 1 | BZ125: 0 | CA125: 0 | CE125: 1566 | CF125: 0 | CG125: 0 | CM125: 0 | CO125: 0 | CP125: =(P125+Q125+S125) -> 283669.7 | CQ125: =ROUND((ROUND((AC125*1),2)*BC125),2) -> 94556.57 | CR125: =(ROUND((ROUND(((ET125)*AV125*1),2)*BB125),2)+ROUND((ROUND(((AE125-(EU125))*AV125*1),2)*BS125),2)) -> 0 | CS125: =(ROUND((ROUND(((EU125)*AV125*1),2)*BS125),2)+ROUND((ROUND(((AE125-(EU125))*AV125*1),2)*BS125),2)) -> 0 | CT125: =ROUND((ROUND((AF125*AV125*1),2)*BA125),2) -> 0 | CU125: =AG125 -> 0 | CV125: =(AH125*AV125) -> 0 | CW125: =AI125 -> 0 | CX125: =AJ125 -> 0 | CY125: =(ROUND((((S125+ROUND((ROUND(((EU125)*AV125*1),2)*BS125),2))*AT125)/100),2)+ROUND(((ROUND((ROUND(((AE125-(EU125))*AV125*1),2)*BS125),2)*AT125)/100),2)) -> 0 | CZ125: =(ROUND((((S125+ROUND((ROUND(((EU125)*AV125*1),2)*BS125),2))*AU125)/100),2)+ROUND(((ROUND((ROUND(((AE125-(EU125))*AV125*1),2)*BS125),2)*AU125)/100),2)) -> 0 | DN125: 0 | DO125: 0 | DP125: 1 | DQ125: 1 | DU125: 1010 | DV125: шт. | DW125: шт. | DX125: 1 | EE125: 55393877 | EF125: 130 | EG125: Сметная стоимость оборудования | EH125: 0 | EJ125: 3 | EK125: 746 | EL125: ТСН-2001.13. Сметная стоимость оборудования | EM125: ТСН-2001.13 | EQ125: 131072 | ER125: 12490.96 | ES125: 12490.96 | ET125: 0 | EU125: 0 | EV125: 0 | EW125: 0 | EX125: 0 | EY125: 0 | EZ125: 5 | FC125: 1 | FD125: 18 | FF125: 110671 | FQ125: 0 | FR125: =P125 -> 283669.7 | FS125: 0 | FX125: 0 | FY125: 0 | GA125: [110 671 / 1,22 / 7,57] + 3% Трансп + 1,2% Заг.скл | GD125: 1 | GF125: 313033476 | GG125: 2 | GH125: 3 | GI125: 3 | GJ125: 0 | GK125: 0 | GL125: =ROUND(IF(AND(BH125=3,BI125=3,FS125<>0),P125,0),2) -> 0 | GM125: =ROUND(O125+X125+Y125,2)+GX125 -> 283669.7 | GN125: =IF(OR(BI125=0,BI125=1),GM125-GX125,0) -> 0 | GO125: =IF(BI125=2,GM125-GX125,0) -> 0 | GP125: =IF(BI125=4,GM125-GX125,0) -> 0 | GR125: 1 | GS125: 1 | GT125: 0 | GV125: =ROUND((GT125),6) -> 0 | GW125: 1 | GX125: =ROUND(HC125*I125,2) -> 0 | HA125: 0 | HB125: 0 | HC125: =GV125*GW125 -> 0 | HE125: 3 | HF125: 1,2 | HS125: 0 | IK125: 0
A127: 51 | B127: =B118 -> 1 | C127: =A118 -> 4 | D127: =ROW(A118) -> 118 | F127: =IF(F118<>"",F118,"") -> Новый раздел | G127: =IF(G118<>"",G118,"") -> Оборудование устанавливаемое по месту | H127: 0 | O127: =ROUND(AB127,2) -> 37564.33 | P127: =ROUND(AC127,2) -> 37474.62 | Q127: =ROUND(AD127,2) -> 0 | R127: =ROUND(AE127,2) -> 0 | S127: =ROUND(AF127,2) -> 89.71 | T127: =ROUND(AG127,2) -> 0 | U127: =AH127 -> 7.5384 | V127: =AI127 -> 0 | W127: =ROUND(AJ127,2) -> 0 | X127: =ROUND(AK127,2) -> 80.74 | Y127: =ROUND(AL127,2) -> 41.27 | AB127: =ROUND(SUMIF(AA122:AA125,"=55942966",O122:O125),2) -> 37564.33 | AC127: =ROUND(SUMIF(AA122:AA125,"=55942966",P122:P125),2) -> 37474.62 | AD127: =ROUND(SUMIF(AA122:AA125,"=55942966",Q122:Q125),2) -> 0 | AE127: =ROUND(SUMIF(AA122:AA125,"=55942966",R122:R125),2) -> 0 | AF127: =ROUND(SUMIF(AA122:AA125,"=55942966",S122:S125),2) -> 89.71 | AG127: =ROUND(SUMIF(AA122:AA125,"=55942966",T122:T125),2) -> 0 | AH127: =SUMIF(AA122:AA125,"=55942966",U122:U125) -> 7.5384 | AI127: =SUMIF(AA122:AA125,"=55942966",V122:V125) -> 0 | AJ127: =ROUND(SUMIF(AA122:AA125,"=55942966",W122:W125),2) -> 0 | AK127: =ROUND(SUMIF(AA122:AA125,"=55942966",X122:X125),2) -> 80.74 | AL127: =ROUND(SUMIF(AA122:AA125,"=55942966",Y122:Y125),2) -> 41.27 | AO127: =ROUND(BX127,2) -> 0 | AP127: =ROUND(BY127,2) -> 37472.88 | AQ127: =ROUND(BZ127,2) -> 0 | AR127: =ROUND(CA127,2) -> 37686.34 | AS127: =ROUND(CB127,2) -> 0 | AT127: =ROUND(CC127,2) -> 213.46 | AU127: =ROUND(CD127,2) -> 0 | AV127: =ROUND(CE127,2) -> 37474.62 | ... BD127: =ROUND(CM127,2) -> 0 | BX127: =ROUND(SUMIF(AA122:AA125,"=55942966",FQ122:FQ125),2) -> 0 | BY127: =ROUND(SUMIF(AA122:AA125,"=55942966",FR122:FR125),2) -> 37472.88 | BZ127: =ROUND(SUMIF(AA122:AA125,"=55942966",GL122:GL125),2) -> 0 | CA127: =ROUND(SUMIF(AA122:AA125,"=55942966",GM122:GM125),2) -> 37686.34 | CB127: =ROUND(SUMIF(AA122:AA125,"=55942966",GN122:GN125),2) -> 0 | CC127: =ROUND(SUMIF(AA122:AA125,"=55942966",GO122:GO125),2) -> 213.46 | CD127: =ROUND(SUMIF(AA122:AA125,"=55942966",GP122:GP125),2) -> 0 | CE127: =AC127-BX127 -> 37474.62 | CF127: =AC127-BY127 -> 1.74 | CG127: =BX127-BZ127 -> 0 | CH127: =AC127-BX127-BY127+BZ127 -> 1.74 | CI127: =BY127-BZ127 -> 37472.88 | CJ127: =ROUND(SUMIF(AA122:AA125,"=55942966",GX122:GX125),2) -> 0 | CK127: =ROUND(SUMIF(AA122:AA125,"=55942966",GY122:GY125),2) -> 0 | CL127: =ROUND(SUMIF(AA122:AA125,"=55942966",GZ122:GZ125),2) -> 0 | CM127: =ROUND(SUMIF(AA122:AA125,"=55942966",HD122:HD125),2) -> 0 | DG127: =ROUND(DT127,2) -> 288737.09 | DH127: =ROUND(DU127,2) -> 283681.93 | DI127: =ROUND(DV127,2) -> 0 | DJ127: =ROUND(DW127,2) -> 0 | DK127: =ROUND(DX127,2) -> 5055.16 | DL127: =ROUND(DY127,2) -> 0 | DM127: =DZ127 -> 7.5384 | DN127: =EA127 -> 0 | DO127: =ROUND(EB127,2) -> 0 | DP127: =ROUND(EC127,2) -> 4549.64 | DQ127: =ROUND(ED127,2) -> 2325.37 | DT127: =ROUND(SUMIF(AA122:AA125,"=55942968",O122:O125),2) -> 288737.09 | DU127: =ROUND(SUMIF(AA122:AA125,"=55942968",P122:P125),2) -> 283681.93 | DV127: =ROUND(SUMIF(AA122:AA125,"=55942968",Q122:Q125),2) -> 0 | DW127: =ROUND(SUMIF(AA122:AA125,"=55942968",R122:R125),2) -> 0 | DX127: =ROUND(SUMIF(AA122:AA125,"=55942968",S122:S125),2) -> 5055.16 | DY127: =ROUND(SUMIF(AA122:AA125,"=55942968",T122:T125),2) -> 0 | DZ127: =SUMIF(AA122:AA125,"=55942968",U122:U125) -> 7.5384 | EA127: =SUMIF(AA122:AA125,"=55942968",V122:V125) -> 0 | EB127: =ROUND(SUMIF(AA122:AA125,"=55942968",W122:W125),2) -> 0 | EC127: =ROUND(SUMIF(AA122:AA125,"=55942968",X122:X125),2) -> 4549.64 | ED127: =ROUND(SUMIF(AA122:AA125,"=55942968",Y122:Y125),2) -> 2325.37 | EG127: =ROUND(FP127,2) -> 0 | EH127: =ROUND(FQ127,2) -> 283669.7 | EI127: =ROUND(FR127,2) -> 0 | EJ127: =ROUND(FS127,2) -> 295612.1 | EK127: =ROUND(FT127,2) -> 0 | EL127: =ROUND(FU127,2) -> 11942.4 | EM127: =ROUND(FV127,2) -> 0 | EN127: =ROUND(FW127,2) -> 283681.93 | ... EV127: =ROUND(GE127,2) -> 0 | FP127: =ROUND(SUMIF(AA122:AA125,"=55942968",FQ122:FQ125),2) -> 0 | FQ127: =ROUND(SUMIF(AA122:AA125,"=55942968",FR122:FR125),2) -> 283669.7 | FR127: =ROUND(SUMIF(AA122:AA125,"=55942968",GL122:GL125),2) -> 0 | FS127: =ROUND(SUMIF(AA122:AA125,"=55942968",GM122:GM125),2) -> 295612.1 | FT127: =ROUND(SUMIF(AA122:AA125,"=55942968",GN122:GN125),2) -> 0 | FU127: =ROUND(SUMIF(AA122:AA125,"=55942968",GO122:GO125),2) -> 11942.4 | FV127: =ROUND(SUMIF(AA122:AA125,"=55942968",GP122:GP125),2) -> 0 | FW127: =DU127-FP127 -> 283681.93 | FX127: =DU127-FQ127 -> 12.23 | FY127: =FP127-FR127 -> 0 | FZ127: =DU127-FP127-FQ127+FR127 -> 12.23 | GA127: =FQ127-FR127 -> 283669.7 | GB127: =ROUND(SUMIF(AA122:AA125,"=55942968",GX122:GX125),2) -> 0 | GC127: =ROUND(SUMIF(AA122:AA125,"=55942968",GY122:GY125),2) -> 0 | GD127: =ROUND(SUMIF(AA122:AA125,"=55942968",GZ122:GZ125),2) -> 0 | GE127: =ROUND(SUMIF(AA122:AA125,"=55942968",HD122:HD125),2) -> 0 | GX127: 0
A129: 50 | B129: 0 | C129: 0 | D129: 1 | E129: 201 | F129: =ROUND(Source!O127,O129) -> 37564.33 | G129: ПЗ | H129: Прямые затраты | K129: 201 | L129: 1 | M129: 3 | O129: 2 | P129: =ROUND(Source!DG127,O129) -> 288737.09 | W129: 37564.33 | X129: 1 | Y129: 37564.33 | Z129: 288737.09 | AA129: 1 | AB129: 288737.09
...

Sheet SourceObSm
A1: 0 | B1: Smeta.RU (495) 974-1589 | D1: _OBSM_ | F1: 0 | G1: 0 | H1: 0 | I1: Smeta.RU | K1: 1 | L1: 74599 | M1: 10 | N1: 12 | O1: 1 | P1: 0 | Q1: 5
A4: 1 | B4: 1 | C4: -1 | G4: Капитальный ремонт здания Государственного бюджетного общеобразовательного учреждения города Москвы «Школа №1574», расположенного по адресу: г. Москва, Старопименовский переулок, д. 5. 1 этап | EC4: 0
A5: 8 | B5: 1 | C5: -1 | G5: Капитальный ремонт здания Государственного бюджетного общеобразовательного учреждения города Москвы «Школа №1574», расположенного по адресу: г. Москва, Старопименовский переулок, д. 5. 1 этап | EC5: 0
A12: 1 | B12: 51 | C12: 0 | E12: 0 | F12: 02-01-16 | G12: 02-01-16 Электрочасофикация 15.07 | I12: 0 | J12: 2024-00375-01-0-ИОС5.9 | K12: 0 | L12: 0 | M12: 4097 | O12: 0 | P12: 0 | Q12: 0 | R12: 0 | S12: 0 | T12: 1 | U12: Капитальный ремонт здания Государственного бюджетного общеобразовательного учреждения города Москвы «Школа №1574», | V12: 2 | W12: г. Москва, Старопименовский переулок, д. 5. 1 этап | AB12: О.А.Гришечкина | AC12: Ведущий инженер-сметчик | AD12: И.В.Феденко | AE12: Начальник отдела | BB12: 0 | BH12: Сметные нормы списания | BI12: Коды ОКП для ТСН-2001 МГЭ Дополнение 81 | BJ12: 1 | BK12: 1 | BL12: 0 | BM12: 0 | BN12: 1 | BO12: 0 | BP12: 6 | BQ12: 2 | BR12: 1 | BS12: 1 | BT12: 0 | BU12: 0 | BV12: 0 | BW12: 0 | BX12: 0 | BY12: ТСН-2001 (МГЭ) Доп 81 - Ремонт | BZ12: Типовой расчет для ТСН-2001 МГЭ, Дополнение 81, ремонт | CA12: Территориальные сметные нормативы для Москвы ТСН-2001 (МГЭ), дополнение 81 | CB12: Территориальные сметные нормативы для Москвы ТСН-2001 (МГЭ), дополнение 81 | CC12: Территориальные сметные нормативы для Москвы ТСН-2001 (МГЭ), дополнение 81 | CD12: Территориальные сметные нормативы для Москвы ТСН-2001 (МГЭ), дополнение 81 | CE12: Поправки для ТСН-2001 от 07.04.2026 г. доп.81 | CF12: 0 | CG12: 0 | CH12: 8 | CK12: 82 | CQ12: Территориальные сметные нормативы для Москвы (ТСН-2001) | CR12: ТЕР | CS12: 41660 | CT12: 1 | CU12: 81 | CY12: 0 | EC12: 0
A14: 22 | B14: 1 | C14: 0 | D14: 55942968 | E14: 55942966 | F14: 2 | G14: 1
A16: 3 | B16: 1 | C16: 02-01-16 | D16: Электрочасофикация | E16: =ROUND((Source!P217)/1000,2) -> 0 | F16: =ROUND((Source!P218)/1000,2) -> 36.65 | G16: =ROUND((Source!P209)/1000,2) -> 1018 | H16: =ROUND((Source!P219)/1000+(Source!P220)/1000,2) -> 0 | I16: =E16+F16+G16+H16 -> 1054.65 | J16: =ROUND((Source!P215+Source!P214)/1000,2) -> 15.12 | K16: 2052.78 | L16: 0 | M16: 0 | N16: =I16+L16+M16 -> 1054.65 | T16: =ROUND((Source!F217)/1000,2) -> 0 | U16: =ROUND((Source!F218)/1000,2) -> 0.74 | V16: =ROUND((Source!F209)/1000,2) -> 134.48 | W16: =ROUND((Source!F219)/1000+(Source!F220)/1000,2) -> 0 | X16: =T16+U16+V16+W16 -> 135.22 | Y16: =ROUND((Source!F215+Source!F214)/1000,2) -> 0.27 | Z16: 269.44 | AA16: 0 | AB16: 0 | AC16: =X16+AA16+AB16 -> 135.22 | AI16: 2 | AJ16: -1 | AN16: 0 | AT16: 1033952.3 | AU16: 1018830.2 | AV16: 0 | AW16: 1017996.9 | AX16: 0 | AY16: 10.72 | AZ16: 5.64 | BA16: 15111.39 | BB16: 0 | BC16: 36649.09 | BD16: 0 | BE16: 0 | BF16: 21.315978 | BG16: 0 | BH16: 0 | BI16: 13661.39 | BJ16: 7032.32 | BK16: 1054646 | BR16: 134852.23 | BS16: 134583.43 | BT16: 0 | BU16: 134477.8 | BV16: 0 | BW16: 0.63 | BX16: 0.1 | BY16: 268.17 | BZ16: 0 | CA16: 741.65 | CB16: 0 | CC16: 0 | CD16: 21.315978 | CE16: 0 | CF16: 0 | CG16: 242.43 | CH16: 124.79 | CI16: 135219.45
A18: 51 | E18: 0 | F18: 36.65 | G18: 1018 | H18: 0 | I18: 1054.65 | J18: 15.12 | K18: 2052.78 | L18: 0 | M18: 0 | N18: 1054.65 | T18: 0 | U18: 0.74 | V18: 134.48 | W18: 0 | X18: 135.22 | Y18: 0.27 | Z18: 269.44 | AA18: 0 | AB18: 0 | AC18: 135.22
A20: 50 | B20: 0 | C20: 0 | D20: 1 | E20: 201 | F20: 1033952.3 | G20: ПЗ | H20: Прямые затраты | K20: 201 | L20: 1 | M20: 3 | O20: 2 | P20: 134852.23
A21: 50 | B21: 0 | C21: 0 | D21: 1 | E21: 202 | F21: 1018830.2 | G21: СтМатОб | H21: Стоимость материальных ресурсов (всего) | K21: 202 | L21: 2 | M21: 3 | O21: 2 | P21: 134583.43
A22: 50 | B22: 0 | C22: 0 | D22: 1 | E22: 222 | F22: 0 | G22: СтМатОбЗак | H22: Стоимость материалов и оборудования заказчика | K22: 222 | L22: 3 | M22: 3 | O22: 2 | P22: 0
A23: 50 | B23: 0 | C23: 0 | D23: 1 | E23: 225 | F23: 1018830.2 | G23: СтМатОбПод | H23: Стоимость материалов и оборудования подрядчика | K23: 225 | L23: 4 | M23: 3 | O23: 2 | P23: 134583.43
A24: 50 | B24: 0 | C24: 0 | D24: 1 | E24: 226 | F24: 833.27 | G24: СтМат | H24: Стоимость материалов (всего) | K24: 226 | L24: 5 | M24: 3 | O24: 2 | P24: 105.63
A25: 50 | B25: 0 | C25: 0 | D25: 1 | E25: 227 | F25: 0 | G25: СтМатЗак | H25: Стоимость материалов заказчика | K25: 227 | L25: 6 | M25: 3 | O25: 2 | P25: 0
A26: 50 | B26: 0 | C26: 0 | D26: 1 | E26: 228 | F26: 833.27 | G26: СтМатПод | H26: Стоимость материалов подрядчика | K26: 228 | L26: 7 | M26: 3 | O26: 2 | P26: 105.63
A27: 50 | B27: 0 | C27: 0 | D27: 1 | E27: 216 | F27: 1017996.9 | G27: Оборуд | H27: Стоимость оборудования (всего) | K27: 216 | L27: 8 | M27: 3 | O27: 2 | P27: 134477.8
A28: 50 | B28: 0 | C28: 0 | D28: 1 | E28: 223 | F28: 0 | G28: ОборудЗак | H28: Стоимость оборудования заказчика | K28: 223 | L28: 9 | M28: 3 | O28: 2 | P28: 0
A29: 50 | B29: 0 | C29: 0 | D29: 1 | E29: 229 | F29: 1017996.9 | G29: ОборудПод | H29: Стоимость оборудования подрядчика | K29: 229 | L29: 10 | M29: 3 | O29: 2 | P29: 134477.8
A30: 50 | B30: 0 | C30: 0 | D30: 1 | E30: 203 | F30: 10.72 | G30: ЭММ | H30: Эксплуатация машин | K30: 203 | L30: 11 | M30: 3 | O30: 2 | P30: 0.63
A31: 50 | B31: 0 | C31: 0 | D31: 1 | E31: 231 | F31: 0 | G31: ЭММсНРиСП | H31: Эксплуатация машин по ТСН-2001.16 | K31: 231 | L31: 12 | M31: 3 | O31: 2 | P31: 0
... A46: 50 | B46: 0 | C46: 0 | D46: 1 | E46: 224 | F46: 1054646 | G46: Всего | H46: Всего с НР и СП | K46: 224 | L46: 27 | M46: 3 | O46: 2 | P46: 135219.45
A48: -1
A51: 75 | B51: Текущий уровень цен | C51: 2026 | D51: 1 | E51: 0 | G51: 0 | H51: 1 | I51: 1 | J51: 1 | K51: 0 | L51: 0 | M51: 1 | N51: 55942968 | O51: 1
A52: 1 | B52: Сборник индексов | C52: Коэффициенты к ТСН-2001 МГЭ Дополнение 81, ремонт | D52: 2026 | E52: 1 | F52: 1 | G52: 1 | H52: 0 | I52: 2 | J52: 1 | K52: 9.84 | L52: 7.57 | M52: 1 | N52: 1 | O52: 9.84 | P52: 7.57 | Q52: 1 | AA52: 219/81 | AN52: 55942969
A53: 1 | B53: Сборник индексов | C53: Коэффициенты к ТСН-2001.13-2 Дополнение 47 | D53: 2026 | E53: 1 | F53: 1 | G53: 1 | H53: 0 | I53: 2 | J53: 1 | K53: 9.84 | L53: 7.57 | M53: 1 | N53: 1 | O53: 9.84 | P53: 7.57 | Q53: 1 | AA53: 64/47 | AN53: 55942970
A54: 75 | B54: Базовый уровень цен | C54: 2000 | D54: 0 | E54: 1 | F54: 0 | G54: 0 | H54: 1 | I54: 1 | J54: 3 | K54: 0 | L54: 0 | M54: 0 | N54: 55942966 | O54: 2
A55: 1 | B55: Сборник индексов | C55: Коэффициенты к ТСН-2001 МГЭ Дополнение 81, ремонт | D55: 2000 | E55: 1 | F55: 1 | G55: 1 | H55: 0 | I55: 2 | J55: 1 | K55: 1 | L55: 1 | M55: 1 | N55: 1 | O55: 1 | P55: 1 | Q55: 1 | AA55: 0 | AN55: 55942967

Sheet SmtRes
A1: =ROW(Source!A28) -> 28 | B1: 55942966 | C1: 55984400 | D1: 55424304 | E1: 1081 | F1: 1 | G1: 1081 | H1: 1 | I1: 9999990008 | K1: Трудозатраты рабочих | L1: 1191 | N1: 1013 | O1: чел.-ч. | P1: чел.-ч. | Q1: 1 | W1: 0 | X1: 476480486 | Y1: =((AT1*1.2)*0.3) -> 1.08 | AA1: 0 | AB1: 0 | AC1: 0 | AD1: 0 | AE1: 0 | AF1: 0 | AG1: 0 | AH1: 0 | AI1: 1 | AJ1: 1 | AK1: 1 | AL1: 1 | AM1: -2 | AN1: 0 | AO1: 1 | AP1: 1 | AQ1: 0 | AR1: 0 | AT1: 3 | AU1: *1,2)*0,3 | AV1: 1 | AW1: 2 | AX1: 55985162 | AY1: 1 | AZ1: 0 | BA1: 1 | BB1: 0 | BC1: 0 | BD1: 0 | BE1: 0 | BF1: 0 | BG1: 0 | BH1: 0 | BI1: 0 | BJ1: 0 | BK1: 0 | BL1: 0 | BM1: 0 | BN1: 0 | BO1: 0 | BP1: 0 | BQ1: 0 | BR1: 0 | BS1: 0 | BT1: 0 | BU1: 0 | BV1: 0 | BW1: 0 | CU1: =ROUND(AT1*Source!I28*AH1*AL1,2) -> 0 | CV1: =ROUND(Y1*Source!I28,9) -> 1.08 | CW1: 0 | CX1: =ROUND(Y1*Source!I28,9) -> 1.08 | CY1: =AD1 -> 0 | CZ1: =AH1 -> 0 | DA1: =AL1 -> 1 | DB1: =ROUND(((ROUND(AT1*CZ1,2)*1.2)*0.3),6) -> 0 | DC1: =ROUND(((ROUND(AT1*AG1,2)*1.2)*0.3),6) -> 0 | DF1: =ROUND(ROUND(AE1,2)*CX1,2) -> 0 | DG1: =ROUND(ROUND(AF1,2)*CX1,2) -> 0 | DH1: =ROUND(ROUND(AG1,2)*CX1,2) -> 0 | DI1: =ROUND(ROUND(AH1,2)*CX1,2) -> 0 | DJ1: =DI1 -> 0 | DK1: 0 | DM1: 0 | DO1: 0
A2: =ROW(Source!A28) -> 28 | B2: 55942966 | C2: 55984400 | D2: 55459261 | E2: 1 | F2: 1 | G2: 1081 | H2: 3 | I2: 1.1-1-146 | J2: ТСН-2001.1 Доп. 79, Р. 1, о. 1, поз. 146 | K2: Гипс строительный | L2: 1348 | N2: 1009 | O2: т | P2: т | Q2: 1000 | W2: 0 | X2: -2092697376 | Y2: =((AT2*1)*0) -> 0 | AA2: 1219.68 | AB2: 0 | AC2: 0 | AD2: 0 | AE2: 1219.68 | AF2: 0 | AG2: 0 | AH2: 0 | AI2: 1 | AJ2: 1 | AK2: 1 | AL2: 1 | AM2: -2 | AN2: 0 | AO2: 1 | AP2: 1 | AQ2: 0 | AR2: 0 | AT2: 0.0001 | AU2: *1)*0 | AV2: 0 | AW2: 2 | AX2: 55985163 | AY2: 1 | AZ2: 0 | BA2: 2 | BB2: 0 | BC2: 0 | BD2: 0 | BE2: 0 | BF2: 0 | BG2: 0 | BH2: 0 | BI2: 0 | BJ2: 0 | BK2: 0 | BL2: 0 | BM2: 0 | BN2: 0 | BO2: 0 | BP2: 0 | BQ2: 0 | BR2: 0 | BS2: 0 | BT2: 0 | BU2: 0 | BV2: 0 | BW2: 0 | CV2: 0 | CW2: 0 | CX2: =ROUND(Y2*Source!I28,9) -> 0 | CY2: =AA2 -> 1219.68 | CZ2: =AE2 -> 1219.68 | DA2: =AI2 -> 1 | DB2: =ROUND(((ROUND(AT2*CZ2,2)*1)*0),6) -> 0 | DC2: =ROUND(((ROUND(AT2*AG2,2)*1)*0),6) -> 0 | DF2: =ROUND(ROUND(AE2,2)*CX2,2) -> 0 | DG2: =ROUND(ROUND(AF2,2)*CX2,2) -> 0 | DH2: =ROUND(ROUND(AG2,2)*CX2,2) -> 0 | DI2: =ROUND(ROUND(AH2,2)*CX2,2) -> 0 | DJ2: =DF2 -> 0 | DK2: 0 | DM2: 0 | DO2: 0
A3: =ROW(Source!A28) -> 28 | B3: 55942966 | C3: 55984400 | D3: 55461880 | E3: 1 | F3: 1 | G3: 1081 | H3: 3 | I3: 1.1-1-3805 | J3: ТСН-2001.1 Доп. 79, Р. 1, о. 1, поз. 3805 | K3: Шуруп-саморез с потайной головкой, универсальный, оцинкованный, диаметр 5 мм, длина 70 мм | L3: 1355 | N3: 1010 | O3: 100 шт. | P3: 100 шт. | Q3: 100 | W3: 0 | X3: 1440323189 | Y3: =((AT3*1)*0) -> 0 | AA3: 10.89 | AB3: 0 | AC3: 0 | AD3: 0 | AE3: 10.89 | AF3: 0 | AG3: 0 | AH3: 0 | AI3: 1 | AJ3: 1 | AK3: 1 | AL3: 1 | AM3: -2 | AN3: 0 | AO3: 1 | AP3: 1 | AQ3: 0 | AR3: 0 | AT3: 0.0307 | AU3: *1)*0 | AV3: 0 | AW3: 2 | AX3: 55985164 | AY3: 1 | AZ3: 0 | BA3: 3 | BB3: 0 | BC3: 0 | BD3: 0 | BE3: 0 | BF3: 0 | BG3: 0 | BH3: 0 | BI3: 0 | BJ3: 0 | BK3: 0 | BL3: 0 | BM3: 0 | BN3: 0 | BO3: 0 | BP3: 0 | BQ3: 0 | BR3: 0 | BS3: 0 | BT3: 0 | BU3: 0 | BV3: 0 | BW3: 0 | CV3: 0 | CW3: 0 | CX3: =ROUND(Y3*Source!I28,9) -> 0 | CY3: =AA3 -> 10.89 | CZ3: =AE3 -> 10.89 | DA3: =AI3 -> 1 | DB3: =ROUND(((ROUND(AT3*CZ3,2)*1)*0),6) -> 0 | DC3: =ROUND(((ROUND(AT3*AG3,2)*1)*0),6) -> 0 | DF3: =ROUND(ROUND(AE3,2)*CX3,2) -> 0 | DG3: =ROUND(ROUND(AF3,2)*CX3,2) -> 0 | DH3: =ROUND(ROUND(AG3,2)*CX3,2) -> 0 | DI3: =ROUND(ROUND(AH3,2)*CX3,2) -> 0 | DJ3: =DF3 -> 0 | DK3: 0 | DM3: 0 | DO3: 0
A4: =ROW(Source!A29) -> 29 | B4: 55942968 | C4: 55984400 | D4: 55424304 | E4: 1081 | F4: 1 | G4: 1081 | H4: 1 | I4: 9999990008 | K4: Трудозатраты рабочих | L4: 1191 | N4: 1013 | O4: чел.-ч. | P4: чел.-ч. | Q4: 1 | W4: 0 | X4: 476480486 | Y4: =((AT4*1.2)*0.3) -> 1.08 | AA4: 0 | AB4: 0 | AC4: 0 | AD4: 0 | AE4: 0 | AF4: 0 | AG4: 0 | AH4: 0 | AI4: 1 | AJ4: 1 | AK4: 1 | AL4: 1 | AM4: 5 | AN4: 0 | AO4: 1 | AP4: 1 | AQ4: 0 | AR4: 0 | AT4: 3 | AU4: *1,2)*0,3 | AV4: 1 | AW4: 2 | AX4: 55985162 | AY4: 1 | AZ4: 0 | BA4: 4 | BB4: 0 | BC4: 0 | BD4: 0 | BE4: 0 | BF4: 0 | BG4: 0 | BH4: 0 | BI4: 0 | BJ4: 0 | BK4: 0 | BL4: 0 | BM4: 0 | BN4: 0 | BO4: 0 | BP4: 0 | BQ4: 0 | BR4: 0 | BS4: 0 | BT4: 0 | BU4: 0 | BV4: 0 | BW4: 0 | CU4: =ROUND(AT4*Source!I29*AH4*AL4,2) -> 0 | CV4: =ROUND(Y4*Source!I29,9) -> 1.08 | CW4: 0 | CX4: =ROUND(Y4*Source!I29,9) -> 1.08 | CY4: =AD4 -> 0 | CZ4: =AH4 -> 0 | DA4: =AL4 -> 1 | DB4: =ROUND(((ROUND(AT4*CZ4,2)*1.2)*0.3),6) -> 0 | DC4: =ROUND(((ROUND(AT4*AG4,2)*1.2)*0.3),6) -> 0 | DF4: =ROUND(ROUND(AE4,2)*CX4,2) -> 0 | DG4: =ROUND(ROUND(AF4,2)*CX4,2) -> 0 | DH4: =ROUND(ROUND(AG4,2)*CX4,2) -> 0 | DI4: =ROUND(ROUND(AH4,2)*CX4,2) -> 0 | DJ4: =DI4 -> 0 | DK4: 0 | DM4: 0 | DO4: 0
A5: =ROW(Source!A29) -> 29 | B5: 55942968 | C5: 55984400 | D5: 55459261 | E5: 1 | F5: 1 | G5: 1081 | H5: 3 | I5: 1.1-1-146 | J5: ТСН-2001.1 Доп. 79, Р. 1, о. 1, поз. 146 | K5: Гипс строительный | L5: 1348 | N5: 1009 | O5: т | P5: т | Q5: 1000 | W5: 0 | X5: -2092697376 | Y5: =((AT5*1)*0) -> 0 | AA5: 7305.88 | AB5: 0 | AC5: 0 | AD5: 0 | AE5: 1219.68 | AF5: 0 | AG5: 0 | AH5: 0 | AI5: 5.99 | AJ5: 1 | AK5: 1 | AL5: 1 | AM5: 2 | AN5: 0 | AO5: 1 | AP5: 1 | AQ5: 0 | AR5: 0 | AT5: 0.0001 | AU5: *1)*0 | AV5: 0 | AW5: 2 | AX5: 55985163 | AY5: 1 | AZ5: 0 | BA5: 5 | BB5: 0 | BC5: 0 | BD5: 0 | BE5: 0 | BF5: 0 | BG5: 0 | BH5: 0 | BI5: 0 | BJ5: 0 | BK5: 0 | BL5: 0 | BM5: 0 | BN5: 0 | BO5: 0 | BP5: 0 | BQ5: 0 | BR5: 0 | BS5: 0 | BT5: 0 | BU5: 0 | BV5: 0 | BW5: 0 | CV5: 0 | CW5: 0 | CX5: =ROUND(Y5*Source!I29,9) -> 0 | CY5: =AA5 -> 7305.88 | CZ5: =AE5 -> 1219.68 | DA5: =AI5 -> 5.99 | DB5: =ROUND(((ROUND(AT5*CZ5,2)*1)*0),6) -> 0 | DC5: =ROUND(((ROUND(AT5*AG5,2)*1)*0),6) -> 0 | DF5: =ROUND(ROUND(AE5*AI5,2)*CX5,2) -> 0 | DG5: =ROUND(ROUND(AF5,2)*CX5,2) -> 0 | DH5: =ROUND(ROUND(AG5,2)*CX5,2) -> 0 | DI5: =ROUND(ROUND(AH5,2)*CX5,2) -> 0 | DJ5: =DF5 -> 0 | DK5: 0 | DM5: 0 | DO5: 0
A6: =ROW(Source!A29) -> 29 | B6: 55942968 | C6: 55984400 | D6: 55461880 | E6: 1 | F6: 1 | G6: 1081 | H6: 3 | I6: 1.1-1-3805 | J6: ТСН-2001.1 Доп. 79, Р. 1, о. 1, поз. 3805 | K6: Шуруп-саморез с потайной головкой, универсальный, оцинкованный, диаметр 5 мм, длина 70 мм | L6: 1355 | N6: 1010 | O6: 100 шт. | P6: 100 шт. | Q6: 100 | W6: 0 | X6: 1440323189 | Y6: =((AT6*1)*0) -> 0 | AA6: 78.52 | AB6: 0 | AC6: 0 | AD6: 0 | AE6: 10.89 | AF6: 0 | AG6: 0 | AH6: 0 | AI6: 7.21 | AJ6: 1 | AK6: 1 | AL6: 1 | AM6: 2 | AN6: 0 | AO6: 1 | AP6: 1 | AQ6: 0 | AR6: 0 | AT6: 0.0307 | AU6: *1)*0 | AV6: 0 | AW6: 2 | AX6: 55985164 | AY6: 1 | AZ6: 0 | BA6: 6 | BB6: 0 | BC6: 0 | BD6: 0 | BE6: 0 | BF6: 0 | BG6: 0 | BH6: 0 | BI6: 0 | BJ6: 0 | BK6: 0 | BL6: 0 | BM6: 0 | BN6: 0 | BO6: 0 | BP6: 0 | BQ6: 0 | BR6: 0 | BS6: 0 | BT6: 0 | BU6: 0 | BV6: 0 | BW6: 0 | CV6: 0 | CW6: 0 | CX6: =ROUND(Y6*Source!I29,9) -> 0 | CY6: =AA6 -> 78.52 | CZ6: =AE6 -> 10.89 | DA6: =AI6 -> 7.21 | DB6: =ROUND(((ROUND(AT6*CZ6,2)*1)*0),6) -> 0 | DC6: =ROUND(((ROUND(AT6*AG6,2)*1)*0),6) -> 0 | DF6: =ROUND(ROUND(AE6*AI6,2)*CX6,2) -> 0 | DG6: =ROUND(ROUND(AF6,2)*CX6,2) -> 0 | DH6: =ROUND(ROUND(AG6,2)*CX6,2) -> 0 | DI6: =ROUND(ROUND(AH6,2)*CX6,2) -> 0 | DJ6: =DF6 -> 0 | DK6: 0 | DM6: 0 | DO6: 0
A7: =ROW(Source!A30) -> 30 | B7: 55942966 | C7: 55984401 | D7: 55424304 | E7: 1081 | F7: 1 | G7: 1081 | H7: 1 | I7: 9999990008 | K7: Трудозатраты рабочих | L7: 1191 | N7: 1013 | O7: чел.-ч. | P7: чел.-ч. | Q7: 1 | W7: 0 | X7: 476480486 | Y7: =((AT7*1.2)*0.3) -> 0.9972 | AA7: 0 | AB7: 0 | AC7: 0 | AD7: 0 | AE7: 0 | AF7: 0 | AG7: 0 | AH7: 0 | AI7: 1 | AJ7: 1 | AK7: 1 | AL7: 1 | AM7: -2 | AN7: 0 | AO7: 1 | AP7: 1 | AQ7: 0 | AR7: 0 | AT7: 2.77 | AU7: *1,2)*0,3 | AV7: 1 | AW7: 2 | AX7: 55985166 | AY7: 1 | AZ7: 0 | BA7: 7 | BB7: 0 | BC7: 0 | BD7: 0 | BE7: 0 | BF7: 0 | BG7: 0 | BH7: 0 | BI7: 0 | BJ7: 0 | BK7: 0 | BL7: 0 | BM7: 0 | BN7: 0 | BO7: 0 | BP7: 0 | BQ7: 0 | BR7: 0 | BS7: 0 | BT7: 0 | BU7: 0 | BV7: 0 | BW7: 0 | CU7: =ROUND(AT7*Source!I30*AH7*AL7,2) -> 0 | CV7: =ROUND(Y7*Source!I30,9) -> 0.9972 | CW7: 0 | CX7: =ROUND(Y7*Source!I30,9) -> 0.9972 | CY7: =AD7 -> 0 | CZ7: =AH7 -> 0 | DA7: =AL7 -> 1 | DB7: =ROUND(((ROUND(AT7*CZ7,2)*1.2)*0.3),6) -> 0 | DC7: =ROUND(((ROUND(AT7*AG7,2)*1.2)*0.3),6) -> 0 | DF7: =ROUND(ROUND(AE7,2)*CX7,2) -> 0 | DG7: =ROUND(ROUND(AF7,2)*CX7,2) -> 0 | DH7: =ROUND(ROUND(AG7,2)*CX7,2) -> 0 | DI7: =ROUND(ROUND(AH7,2)*CX7,2) -> 0 | DJ7: =DI7 -> 0 | DK7: 0 | DM7: 0 | DO7: 0
A8: =ROW(Source!A30) -> 30 | B8: 55942966 | C8: 55984401 | D8: 55459873 | E8: 1 | F8: 1 | G8: 1081 | H8: 3 | I8: 1.1-1-1051 | J8: ТСН-2001.1 Доп. 79, Р. 1, о. 1, поз. 1051 | K8: Солидол жировой | L8: 1348 | N8: 1009 | O8: т | P8: т | Q8: 1000 | W8: 0 | X8: -1448251497 | Y8: =((AT8*1)*0) -> 0 | AA8: 18495.41 | AB8: 0 | AC8: 0 | AD8: 0 | AE8: 18495.41 | AF8: 0 | AG8: 0 | AH8: 0 | AI8: 1 | AJ8: 1 | AK8: 1 | AL8: 1 | AM8: -2 | AN8: 0 | AO8: 1 | AP8: 1 | AQ8: 0 | AR8: 0 | AT8: 1e-05 | AU8: *1)*0 | AV8: 0 | AW8: 2 | AX8: 55985167 | AY8: 1 | AZ8: 0 | BA8: 8 | BB8: 0 | BC8: 0 | BD8: 0 | BE8: 0 | BF8: 0 | BG8: 0 | BH8: 0 | BI8: 0 | BJ8: 0 | BK8: 0 | BL8: 0 | BM8: 0 | BN8: 0 | BO8: 0 | BP8: 0 | BQ8: 0 | BR8: 0 | BS8: 0 | BT8: 0 | BU8: 0 | BV8: 0 | BW8: 0 | CV8: 0 | CW8: 0 | CX8: =ROUND(Y8*Source!I30,9) -> 0 | CY8: =AA8 -> 18495.41 | CZ8: =AE8 -> 18495.41 | DA8: =AI8 -> 1 | DB8: =ROUND(((ROUND(AT8*CZ8,2)*1)*0),6) -> 0 | DC8: =ROUND(((ROUND(AT8*AG8,2)*1)*0),6) -> 0 | DF8: =ROUND(ROUND(AE8,2)*CX8,2) -> 0 | DG8: =ROUND(ROUND(AF8,2)*CX8,2) -> 0 | DH8: =ROUND(ROUND(AG8,2)*CX8,2) -> 0 | DI8: =ROUND(ROUND(AH8,2)*CX8,2) -> 0 | DJ8: =DF8 -> 0 | DK8: 0 | DM8: 0 | DO8: 0
A9: =ROW(Source!A31) -> 31 | B9: 55942968 | C9: 55984401 | D9: 55424304 | E9: 1081 | F9: 1 | G9: 1081 | H9: 1 | I9: 9999990008 | K9: Трудозатраты рабочих | L9: 1191 | N9: 1013 | O9: чел.-ч. | P9: чел.-ч. | Q9: 1 | W9: 0 | X9: 476480486 | Y9: =((AT9*1.2)*0.3) -> 0.9972 | AA9: 0 | AB9: 0 | AC9: 0 | AD9: 0 | AE9: 0 | AF9: 0 | AG9: 0 | AH9: 0 | AI9: 1 | AJ9: 1 | AK9: 1 | AL9: 1 | AM9: 5 | AN9: 0 | AO9: 1 | AP9: 1 | AQ9: 0 | AR9: 0 | AT9: 2.77 | AU9: *1,2)*0,3 | AV9: 1 | AW9: 2 | AX9: 55985166 | AY9: 1 | AZ9: 0 | BA9: 9 | BB9: 0 | BC9: 0 | BD9: 0 | BE9: 0 | BF9: 0 | BG9: 0 | BH9: 0 | BI9: 0 | BJ9: 0 | BK9: 0 | BL9: 0 | BM9: 0 | BN9: 0 | BO9: 0 | BP9: 0 | BQ9: 0 | BR9: 0 | BS9: 0 | BT9: 0 | BU9: 0 | BV9: 0 | BW9: 0 | CU9: =ROUND(AT9*Source!I31*AH9*AL9,2) -> 0 | CV9: =ROUND(Y9*Source!I31,9) -> 0.9972 | CW9: 0 | CX9: =ROUND(Y9*Source!I31,9) -> 0.9972 | CY9: =AD9 -> 0 | CZ9: =AH9 -> 0 | DA9: =AL9 -> 1 | DB9: =ROUND(((ROUND(AT9*CZ9,2)*1.2)*0.3),6) -> 0 | DC9: =ROUND(((ROUND(AT9*AG9,2)*1.2)*0.3),6) -> 0 | DF9: =ROUND(ROUND(AE9,2)*CX9,2) -> 0 | DG9: =ROUND(ROUND(AF9,2)*CX9,2) -> 0 | DH9: =ROUND(ROUND(AG9,2)*CX9,2) -> 0 | DI9: =ROUND(ROUND(AH9,2)*CX9,2) -> 0 | DJ9: =DI9 -> 0 | DK9: 0 | DM9: 0 | DO9: 0
A10: =ROW(Source!A31) -> 31 | B10: 55942968 | C10: 55984401 | D10: 55459873 | E10: 1 | F10: 1 | G10: 1081 | H10: 3 | I10: 1.1-1-1051 | J10: ТСН-2001.1 Доп. 79, Р. 1, о. 1, поз. 1051 | K10: Солидол жировой | L10: 1348 | N10: 1009 | O10: т | P10: т | Q10: 1000 | W10: 0 | X10: -1448251497 | Y10: =((AT10*1)*0) -> 0 | AA10: 101169.89 | AB10: 0 | AC10: 0 | AD10: 0 | AE10: 18495.41 | AF10: 0 | AG10: 0 | AH10: 0 | AI10: 5.47 | AJ10: 1 | AK10: 1 | AL10: 1 | AM10: 2 | AN10: 0 | AO10: 1 | AP10: 1 | AQ10: 0 | AR10: 0 | AT10: 1e-05 | AU10: *1)*0 | AV10: 0 | AW10: 2 | AX10: 55985167 | AY10: 1 | AZ10: 0 | BA10: 10 | BB10: 0 | BC10: 0 | BD10: 0 | BE10: 0 | BF10: 0 | BG10: 0 | BH10: 0 | BI10: 0 | BJ10: 0 | BK10: 0 | BL10: 0 | BM10: 0 | BN10: 0 | BO10: 0 | BP10: 0 | BQ10: 0 | BR10: 0 | BS10: 0 | BT10: 0 | BU10: 0 | BV10: 0 | BW10: 0 | CV10: 0 | CW10: 0 | CX10: =ROUND(Y10*Source!I31,9) -> 0 | CY10: =AA10 -> 101169.89 | CZ10: =AE10 -> 18495.41 | DA10: =AI10 -> 5.47 | DB10: =ROUND(((ROUND(AT10*CZ10,2)*1)*0),6) -> 0 | DC10: =ROUND(((ROUND(AT10*AG10,2)*1)*0),6) -> 0 | DF10: =ROUND(ROUND(AE10*AI10,2)*CX10,2) -> 0 | DG10: =ROUND(ROUND(AF10,2)*CX10,2) -> 0 | DH10: =ROUND(ROUND(AG10,2)*CX10,2) -> 0 | DI10: =ROUND(ROUND(AH10,2)*CX10,2) -> 0 | DJ10: =DF10 -> 0 | DK10: 0 | DM10: 0 | DO10: 0
A11: =ROW(Source!A32) -> 32 | B11: 55942966 | C11: 55984402 | D11: 55424304 | E11: 1081 | F11: 1 | G11: 1081 | H11: 1 | I11: 9999990008 | K11: Трудозатраты рабочих | L11: 1191 | N11: 1013 | O11: чел.-ч. | P11: чел.-ч. | Q11: 1 | W11: 0 | X11: 476480486 | Y11: =((AT11*1.2)*0.3) -> 0.288 | AA11: 0 | AB11: 0 | AC11: 0 | AD11: 0 | AE11: 0 | AF11: 0 | AG11: 0 | AH11: 0 | AI11: 1 | AJ11: 1 | AK11: 1 | AL11: 1 | AM11: -2 | AN11: 0 | AO11: 1 | AP11: 1 | AQ11: 0 | AR11: 0 | AT11: 0.8 | AU11: *1,2)*0,3 | AV11: 1 | AW11: 2 | AX11: 55985169 | AY11: 1 | AZ11: 0 | BA11: 11 | BB11: 0 | BC11: 0 | BD11: 0 | BE11: 0 | BF11: 0 | BG11: 0 | BH11: 0 | BI11: 0 | BJ11: 0 | BK11: 0 | BL11: 0 | BM11: 0 | BN11: 0 | BO11: 0 | BP11: 0 | BQ11: 0 | BR11: 0 | BS11: 0 | BT11: 0 | BU11: 0 | BV11: 0 | BW11: 0 | CU11: =ROUND(AT11*Source!I32*AH11*AL11,2) -> 0 | CV11: =ROUND(Y11*Source!I32,9) -> 0.288 | CW11: 0 | CX11: =ROUND(Y11*Source!I32,9) -> 0.288 | CY11: =AD11 -> 0 | CZ11: =AH11 -> 0 | DA11: =AL11 -> 1 | DB11: =ROUND(((ROUND(AT11*CZ11,2)*1.2)*0.3),6) -> 0 | DC11: =ROUND(((ROUND(AT11*AG11,2)*1.2)*0.3),6) -> 0 | DF11: =ROUND(ROUND(AE11,2)*CX11,2) -> 0 | DG11: =ROUND(ROUND(AF11,2)*CX11,2) -> 0 | DH11: =ROUND(ROUND(AG11,2)*CX11,2) -> 0 | DI11: =ROUND(ROUND(AH11,2)*CX11,2) -> 0 | DJ11: =DI11 -> 0 | DK11: 0 | DM11: 0 | DO11: 0
A12: =ROW(Source!A32) -> 32 | B12: 55942966 | C12: 55984402 | D12: 55460239 | E12: 1 | F12: 1 | G12: 1081 | H12: 3 | I12: 1.1-1-1501 | J12: ТСН-2001.1 Доп. 79, Р. 1, о. 1, поз. 1501 | K12: Шурупы с потайной головкой, черные, диаметр 5 мм, длина 70 мм | L12: 1348 | N12: 1009 | O12: т | P12: т | Q12: 1000 | W12: 0 | X12: -1843244094 | Y12: =((AT12*1)*0) -> 0 | AA12: 12416.13 | AB12: 0 | AC12: 0 | AD12: 0 | AE12: 12416.13 | AF12: 0 | AG12: 0 | AH12: 0 | AI12: 1 | AJ12: 1 | AK12: 1 | AL12: 1 | AM12: -2 | AN12: 0 | AO12: 1 | AP12: 1 | AQ12: 0 | AR12: 0 | AT12: 2.4e-05 | AU12: *1)*0 | AV12: 0 | AW12: 2 | AX12: 55985170 | AY12: 1 | AZ12: 0 | BA12: 12 | BB12: 0 | BC12: 0 | BD12: 0 | BE12: 0 | BF12: 0 | BG12: 0 | BH12: 0 | BI12: 0 | BJ12: 0 | BK12: 0 | BL12: 0 | BM12: 0 | BN12: 0 | BO12: 0 | BP12: 0 | BQ12: 0 | BR12: 0 | BS12: 0 | BT12: 0 | BU12: 0 | BV12: 0 | BW12: 0 | CV12: 0 | CW12: 0 | CX12: =ROUND(Y12*Source!I32,9) -> 0 | CY12: =AA12 -> 12416.13 | CZ12: =AE12 -> 12416.13 | DA12: =AI12 -> 1 | DB12: =ROUND(((ROUND(AT12*CZ12,2)*1)*0),6) -> 0 | DC12: =ROUND(((ROUND(AT12*AG12,2)*1)*0),6) -> 0 | DF12: =ROUND(ROUND(AE12,2)*CX12,2) -> 0 | DG12: =ROUND(ROUND(AF12,2)*CX12,2) -> 0 | DH12: =ROUND(ROUND(AG12,2)*CX12,2) -> 0 | DI12: =ROUND(ROUND(AH12,2)*CX12,2) -> 0 | DJ12: =DF12 -> 0 | DK12: 0 | DM12: 0 | DO12: 0
A13: =ROW(Source!A33) -> 33 | B13: 55942968 | C13: 55984402 | D13: 55424304 | E13: 1081 | F13: 1 | G13: 1081 | H13: 1 | I13: 9999990008 | K13: Трудозатраты рабочих | L13: 1191 | N13: 1013 | O13: чел.-ч. | P13: чел.-ч. | Q13: 1 | W13: 0 | X13: 476480486 | Y13: =((AT13*1.2)*0.3) -> 0.288 | AA13: 0 | AB13: 0 | AC13: 0 | AD13: 0 | AE13: 0 | AF13: 0 | AG13: 0 | AH13: 0 | AI13: 1 | AJ13: 1 | AK13: 1 | AL13: 1 | AM13: 5 | AN13: 0 | AO13: 1 | AP13: 1 | AQ13: 0 | AR13: 0 | AT13: 0.8 | AU13: *1,2)*0,3 | AV13: 1 | AW13: 2 | AX13: 55985169 | AY13: 1 | AZ13: 0 | BA13: 13 | BB13: 0 | BC13: 0 | BD13: 0 | BE13: 0 | BF13: 0 | BG13: 0 | BH13: 0 | BI13: 0 | BJ13: 0 | BK13: 0 | BL13: 0 | BM13: 0 | BN13: 0 | BO13: 0 | BP13: 0 | BQ13: 0 | BR13: 0 | BS13: 0 | BT13: 0 | BU13: 0 | BV13: 0 | BW13: 0 | CU13: =ROUND(AT13*Source!I33*AH13*AL13,2) -> 0 | CV13: =ROUND(Y13*Source!I33,9) -> 0.288 | CW13: 0 | CX13: =ROUND(Y13*Source!I33,9) -> 0.288 | CY13: =AD13 -> 0 | CZ13: =AH13 -> 0 | DA13: =AL13 -> 1 | DB13: =ROUND(((ROUND(AT13*CZ13,2)*1.2)*0.3),6) -> 0 | DC13: =ROUND(((ROUND(AT13*AG13,2)*1.2)*0.3),6) -> 0 | DF13: =ROUND(ROUND(AE13,2)*CX13,2) -> 0 | DG13: =ROUND(ROUND(AF13,2)*CX13,2) -> 0 | DH13: =ROUND(ROUND(AG13,2)*CX13,2) -> 0 | DI13: =ROUND(ROUND(AH13,2)*CX13,2) -> 0 | DJ13: =DI13 -> 0 | DK13: 0 | DM13: 0 | DO13: 0
A14: =ROW(Source!A33) -> 33 | B14: 55942968 | C14: 55984402 | D14: 55460239 | E14: 1 | F14: 1 | G14: 1081 | H14: 3 | I14: 1.1-1-1501 | J14: ТСН-2001.1 Доп. 79, Р. 1, о. 1, поз. 1501 | K14: Шурупы с потайной головкой, черные, диаметр 5 мм, длина 70 мм | L14: 1348 | N14: 1009 | O14: т | P14: т | Q14: 1000 | W14: 0 | X14: -1843244094 | Y14: =((AT14*1)*0) -> 0 | AA14: 91879.36 | AB14: 0 | AC14: 0 | AD14: 0 | AE14: 12416.13 | AF14: 0 | AG14: 0 | AH14: 0 | AI14: 7.4 | AJ14: 1 | AK14: 1 | AL14: 1 | AM14: 2 | AN14: 0 | AO14: 1 | AP14: 1 | AQ14: 0 | AR14: 0 | AT14: 2.4e-05 | AU14: *1)*0 | AV14: 0 | AW14: 2 | AX14: 55985170 | AY14: 1 | AZ14: 0 | BA14: 14 | BB14: 0 | BC14: 0 | BD14: 0 | BE14: 0 | BF14: 0 | BG14: 0 | BH14: 0 | BI14: 0 | BJ14: 0 | BK14: 0 | BL14: 0 | BM14: 0 | BN14: 0 | BO14: 0 | BP14: 0 | BQ14: 0 | BR14: 0 | BS14: 0 | BT14: 0 | BU14: 0 | BV14: 0 | BW14: 0 | CV14: 0 | CW14: 0 | CX14: =ROUND(Y14*Source!I33,9) -> 0 | CY14: =AA14 -> 91879.36 | CZ14: =AE14 -> 12416.13 | DA14: =AI14 -> 7.4 | DB14: =ROUND(((ROUND(AT14*CZ14,2)*1)*0),6) -> 0 | DC14: =ROUND(((ROUND(AT14*AG14,2)*1)*0),6) -> 0 | DF14: =ROUND(ROUND(AE14*AI14,2)*CX14,2) -> 0 | DG14: =ROUND(ROUND(AF14,2)*CX14,2) -> 0 | DH14: =ROUND(ROUND(AG14,2)*CX14,2) -> 0 | DI14: =ROUND(ROUND(AH14,2)*CX14,2) -> 0 | DJ14: =DF14 -> 0 | DK14: 0 | DM14: 0 | DO14: 0
A15: =ROW(Source!A34) -> 34 | B15: 55942966 | C15: 55984403 | D15: 55424304 | E15: 1081 | F15: 1 | G15: 1081 | H15: 1 | I15: 9999990008 | K15: Трудозатраты рабочих | L15: 1191 | N15: 1013 | O15: чел.-ч. | P15: чел.-ч. | Q15: 1 | W15: 0 | X15: 476480486 | Y15: =((AT15*1.2)*0.3) -> 0.72 | AA15: 0 | AB15: 0 | AC15: 0 | AD15: 0 | AE15: 0 | AF15: 0 | AG15: 0 | AH15: 0 | AI15: 1 | AJ15: 1 | AK15: 1 | AL15: 1 | AM15: -2 | AN15: 0 | AO15: 1 | AP15: 1 | AQ15: 0 | AR15: 0 | AT15: 2 | AU15: *1,2)*0,3 | AV15: 1 | AW15: 2 | AX15: 55985172 | AY15: 1 | AZ15: 0 | BA15: 15 | BB15: 0 | BC15: 0 | BD15: 0 | BE15: 0 | BF15: 0 | BG15: 0 | BH15: 0 | BI15: 0 | BJ15: 0 | BK15: 0 | BL15: 0 | BM15: 0 | BN15: 0 | BO15: 0 | BP15: 0 | BQ15: 0 | BR15: 0 | BS15: 0 | BT15: 0 | BU15: 0 | BV15: 0 | BW15: 0 | CU15: =ROUND(AT15*Source!I34*AH15*AL15,2) -> 0 | CV15: =ROUND(Y15*Source!I34,9) -> 2.16 | CW15: 0 | CX15: =ROUND(Y15*Source!I34,9) -> 2.16 | CY15: =AD15 -> 0 | CZ15: =AH15 -> 0 | DA15: =AL15 -> 1 | DB15: =ROUND(((ROUND(AT15*CZ15,2)*1.2)*0.3),6) -> 0 | DC15: =ROUND(((ROUND(AT15*AG15,2)*1.2)*0.3),6) -> 0 | DF15: =ROUND(ROUND(AE15,2)*CX15,2) -> 0 | DG15: =ROUND(ROUND(AF15,2)*CX15,2) -> 0 | DH15: =ROUND(ROUND(AG15,2)*CX15,2) -> 0 | DI15: =ROUND(ROUND(AH15,2)*CX15,2) -> 0 | DJ15: =DI15 -> 0 | DK15: 0 | DM15: 0 | DO15: 0
A16: =ROW(Source!A34) -> 34 | B16: 55942966 | C16: 55984403 | D16: 55459261 | E16: 1 | F16: 1 | G16: 1081 | H16: 3 | I16: 1.1-1-146 | J16: ТСН-2001.1 Доп. 79, Р. 1, о. 1, поз. 146 | K16: Гипс строительный | L16: 1348 | N16: 1009 | O16: т | P16: т | Q16: 1000 | W16: 0 | X16: -2092697376 | Y16: =((AT16*1)*0) -> 0 | AA16: 1219.68 | AB16: 0 | AC16: 0 | AD16: 0 | AE16: 1219.68 | AF16: 0 | AG16: 0 | AH16: 0 | AI16: 1 | AJ16: 1 | AK16: 1 | AL16: 1 | AM16: -2 | AN16: 0 | AO16: 1 | AP16: 1 | AQ16: 0 | AR16: 0 | AT16: 0.0001 | AU16: *1)*0 | AV16: 0 | AW16: 2 | AX16: 55985173 | AY16: 1 | AZ16: 0 | BA16: 16 | BB16: 0 | BC16: 0 | BD16: 0 | BE16: 0 | BF16: 0 | BG16: 0 | BH16: 0 | BI16: 0 | BJ16: 0 | BK16: 0 | BL16: 0 | BM16: 0 | BN16: 0 | BO16: 0 | BP16: 0 | BQ16: 0 | BR16: 0 | BS16: 0 | BT16: 0 | BU16: 0 | BV16: 0 | BW16: 0 | CV16: 0 | CW16: 0 | CX16: =ROUND(Y16*Source!I34,9) -> 0 | CY16: =AA16 -> 1219.68 | CZ16: =AE16 -> 1219.68 | DA16: =AI16 -> 1 | DB16: =ROUND(((ROUND(AT16*CZ16,2)*1)*0),6) -> 0 | DC16: =ROUND(((ROUND(AT16*AG16,2)*1)*0),6) -> 0 | DF16: =ROUND(ROUND(AE16,2)*CX16,2) -> 0 | DG16: =ROUND(ROUND(AF16,2)*CX16,2) -> 0 | DH16: =ROUND(ROUND(AG16,2)*CX16,2) -> 0 | DI16: =ROUND(ROUND(AH16,2)*CX16,2) -> 0 | DJ16: =DF16 -> 0 | DK16: 0 | DM16: 0 | DO16: 0
A17: =ROW(Source!A34) -> 34 | B17: 55942966 | C17: 55984403 | D17: 55461880 | E17: 1 | F17: 1 | G17: 1081 | H17: 3 | I17: 1.1-1-3805 | J17: ТСН-2001.1 Доп. 79, Р. 1, о. 1, поз. 3805 | K17: Шуруп-саморез с потайной головкой, универсальный, оцинкованный, диаметр 5 мм, длина 70 мм | L17: 1355 | N17: 1010 | O17: 100 шт. | P17: 100 шт. | Q17: 100 | W17: 0 | X17: 1440323189 | Y17: =((AT17*1)*0) -> 0 | AA17: 10.89 | AB17: 0 | AC17: 0 | AD17: 0 | AE17: 10.89 | AF17: 0 | AG17: 0 | AH17: 0 | AI17: 1 | AJ17: 1 | AK17: 1 | AL17: 1 | AM17: -2 | AN17: 0 | AO17: 1 | AP17: 1 | AQ17: 0 | AR17: 0 | AT17: 0.0345 | AU17: *1)*0 | AV17: 0 | AW17: 2 | AX17: 55985174 | AY17: 1 | AZ17: 0 | BA17: 17 | BB17: 0 | BC17: 0 | BD17: 0 | BE17: 0 | BF17: 0 | BG17: 0 | BH17: 0 | BI17: 0 | BJ17: 0 | BK17: 0 | BL17: 0 | BM17: 0 | BN17: 0 | BO17: 0 | BP17: 0 | BQ17: 0 | BR17: 0 | BS17: 0 | BT17: 0 | BU17: 0 | BV17: 0 | BW17: 0 | CV17: 0 | CW17: 0 | CX17: =ROUND(Y17*Source!I34,9) -> 0 | CY17: =AA17 -> 10.89 | CZ17: =AE17 -> 10.89 | DA17: =AI17 -> 1 | DB17: =ROUND(((ROUND(AT17*CZ17,2)*1)*0),6) -> 0 | DC17: =ROUND(((ROUND(AT17*AG17,2)*1)*0),6) -> 0 | DF17: =ROUND(ROUND(AE17,2)*CX17,2) -> 0 | DG17: =ROUND(ROUND(AF17,2)*CX17,2) -> 0 | DH17: =ROUND(ROUND(AG17,2)*CX17,2) -> 0 | DI17: =ROUND(ROUND(AH17,2)*CX17,2) -> 0 | DJ17: =DF17 -> 0 | DK17: 0 | DM17: 0 | DO17: 0
A18: =ROW(Source!A34) -> 34 | B18: 55942966 | C18: 55984403 | D18: 55459811 | E18: 1 | F18: 1 | G18: 1081 | H18: 3 | I18: 1.1-1-963 | J18: ТСН-2001.1 Доп. 79, Р. 1, о. 1, поз. 963 | K18: Проволока стальная низкоуглеродистая общего назначения, диаметр от 1,6 до 3,0 мм | L18: 1348 | N18: 1009 | O18: т | P18: т | Q18: 1000 | W18: 0 | X18: -572924193 | Y18: =((AT18*1)*0) -> 0 | AA18: 8054.6 | AB18: 0 | AC18: 0 | AD18: 0 | AE18: 8054.6 | AF18: 0 | AG18: 0 | AH18: 0 | AI18: 1 | AJ18: 1 | AK18: 1 | AL18: 1 | AM18: -2 | AN18: 0 | AO18: 1 | AP18: 1 | AQ18: 0 | AR18: 0 | AT18: 1e-05 | AU18: *1)*0 | AV18: 0 | AW18: 2 | AX18: 55985175 | AY18: 1 | AZ18: 0 | BA18: 18 | BB18: 0 | BC18: 0 | BD18: 0 | BE18: 0 | BF18: 0 | BG18: 0 | BH18: 0 | BI18: 0 | BJ18: 0 | BK18: 0 | BL18: 0 | BM18: 0 | BN18: 0 | BO18: 0 | BP18: 0 | BQ18: 0 | BR18: 0 | BS18: 0 | BT18: 0 | BU18: 0 | BV18: 0 | BW18: 0 | CV18: 0 | CW18: 0 | CX18: =ROUND(Y18*Source!I34,9) -> 0 | CY18: =AA18 -> 8054.6 | CZ18: =AE18 -> 8054.6 | DA18: =AI18 -> 1 | DB18: =ROUND(((ROUND(AT18*CZ18,2)*1)*0),6) -> 0 | DC18: =ROUND(((ROUND(AT18*AG18,2)*1)*0),6) -> 0 | DF18: =ROUND(ROUND(AE18,2)*CX18,2) -> 0 | DG18: =ROUND(ROUND(AF18,2)*CX18,2) -> 0 | DH18: =ROUND(ROUND(AG18,2)*CX18,2) -> 0 | DI18: =ROUND(ROUND(AH18,2)*CX18,2) -> 0 | DJ18: =DF18 -> 0 | DK18: 0 | DM18: 0 | DO18: 0
A19: =ROW(Source!A35) -> 35 | B19: 55942968 | C19: 55984403 | D19: 55424304 | E19: 1081 | F19: 1 | G19: 1081 | H19: 1 | I19: 9999990008 | K19: Трудозатраты рабочих | L19: 1191 | N19: 1013 | O19: чел.-ч. | P19: чел.-ч. | Q19: 1 | W19: 0 | X19: 476480486 | Y19: =((AT19*1.2)*0.3) -> 0.72 | AA19: 0 | AB19: 0 | AC19: 0 | AD19: 0 | AE19: 0 | AF19: 0 | AG19: 0 | AH19: 0 | AI19: 1 | AJ19: 1 | AK19: 1 | AL19: 1 | AM19: 5 | AN19: 0 | AO19: 1 | AP19: 1 | AQ19: 0 | AR19: 0 | AT19: 2 | AU19: *1,2)*0,3 | AV19: 1 | AW19: 2 | AX19: 55985172 | AY19: 1 | AZ19: 0 | BA19: 19 | BB19: 0 | BC19: 0 | BD19: 0 | BE19: 0 | BF19: 0 | BG19: 0 | BH19: 0 | BI19: 0 | BJ19: 0 | BK19: 0 | BL19: 0 | BM19: 0 | BN19: 0 | BO19: 0 | BP19: 0 | BQ19: 0 | BR19: 0 | BS19: 0 | BT19: 0 | BU19: 0 | BV19: 0 | BW19: 0 | CU19: =ROUND(AT19*Source!I35*AH19*AL19,2) -> 0 | CV19: =ROUND(Y19*Source!I35,9) -> 2.16 | CW19: 0 | CX19: =ROUND(Y19*Source!I35,9) -> 2.16 | CY19: =AD19 -> 0 | CZ19: =AH19 -> 0 | DA19: =AL19 -> 1 | DB19: =ROUND(((ROUND(AT19*CZ19,2)*1.2)*0.3),6) -> 0 | DC19: =ROUND(((ROUND(AT19*AG19,2)*1.2)*0.3),6) -> 0 | DF19: =ROUND(ROUND(AE19,2)*CX19,2) -> 0 | DG19: =ROUND(ROUND(AF19,2)*CX19,2) -> 0 | DH19: =ROUND(ROUND(AG19,2)*CX19,2) -> 0 | DI19: =ROUND(ROUND(AH19,2)*CX19,2) -> 0 | DJ19: =DI19 -> 0 | DK19: 0 | DM19: 0 | DO19: 0
A20: =ROW(Source!A35) -> 35 | B20: 55942968 | C20: 55984403 | D20: 55459261 | E20: 1 | F20: 1 | G20: 1081 | H20: 3 | I20: 1.1-1-146 | J20: ТСН-2001.1 Доп. 79, Р. 1, о. 1, поз. 146 | K20: Гипс строительный | L20: 1348 | N20: 1009 | O20: т | P20: т | Q20: 1000 | W20: 0 | X20: -2092697376 | Y20: =((AT20*1)*0) -> 0 | AA20: 7305.88 | AB20: 0 | AC20: 0 | AD20: 0 | AE20: 1219.68 | AF20: 0 | AG20: 0 | AH20: 0 | AI20: 5.99 | AJ20: 1 | AK20: 1 | AL20: 1 | AM20: 2 | AN20: 0 | AO20: 1 | AP20: 1 | AQ20: 0 | AR20: 0 | AT20: 0.0001 | AU20: *1)*0 | AV20: 0 | AW20: 2 | AX20: 55985173 | AY20: 1 | AZ20: 0 | BA20: 20 | BB20: 0 | BC20: 0 | BD20: 0 | BE20: 0 | BF20: 0 | BG20: 0 | BH20: 0 | BI20: 0 | BJ20: 0 | BK20: 0 | BL20: 0 | BM20: 0 | BN20: 0 | BO20: 0 | BP20: 0 | BQ20: 0 | BR20: 0 | BS20: 0 | BT20: 0 | BU20: 0 | BV20: 0 | BW20: 0 | CV20: 0 | CW20: 0 | CX20: =ROUND(Y20*Source!I35,9) -> 0 | CY20: =AA20 -> 7305.88 | CZ20: =AE20 -> 1219.68 | DA20: =AI20 -> 5.99 | DB20: =ROUND(((ROUND(AT20*CZ20,2)*1)*0),6) -> 0 | DC20: =ROUND(((ROUND(AT20*AG20,2)*1)*0),6) -> 0 | DF20: =ROUND(ROUND(AE20*AI20,2)*CX20,2) -> 0 | DG20: =ROUND(ROUND(AF20,2)*CX20,2) -> 0 | DH20: =ROUND(ROUND(AG20,2)*CX20,2) -> 0 | DI20: =ROUND(ROUND(AH20,2)*CX20,2) -> 0 | DJ20: =DF20 -> 0 | DK20: 0 | DM20: 0 | DO20: 0
A21: =ROW(Source!A35) -> 35 | B21: 55942968 | C21: 55984403 | D21: 55461880 | E21: 1 | F21: 1 | G21: 1081 | H21: 3 | I21: 1.1-1-3805 | J21: ТСН-2001.1 Доп. 79, Р. 1, о. 1, поз. 3805 | K21: Шуруп-саморез с потайной головкой, универсальный, оцинкованный, диаметр 5 мм, длина 70 мм | L21: 1355 | N21: 1010 | O21: 100 шт. | P21: 100 шт. | Q21: 100 | W21: 0 | X21: 1440323189 | Y21: =((AT21*1)*0) -> 0 | AA21: 78.52 | AB21: 0 | AC21: 0 | AD21: 0 | AE21: 10.89 | AF21: 0 | AG21: 0 | AH21: 0 | AI21: 7.21 | AJ21: 1 | AK21: 1 | AL21: 1 | AM21: 2 | AN21: 0 | AO21: 1 | AP21: 1 | AQ21: 0 | AR21: 0 | AT21: 0.0345 | AU21: *1)*0 | AV21: 0 | AW21: 2 | AX21: 55985174 | AY21: 1 | AZ21: 0 | BA21: 21 | BB21: 0 | BC21: 0 | BD21: 0 | BE21: 0 | BF21: 0 | BG21: 0 | BH21: 0 | BI21: 0 | BJ21: 0 | BK21: 0 | BL21: 0 | BM21: 0 | BN21: 0 | BO21: 0 | BP21: 0 | BQ21: 0 | BR21: 0 | BS21: 0 | BT21: 0 | BU21: 0 | BV21: 0 | BW21: 0 | CV21: 0 | CW21: 0 | CX21: =ROUND(Y21*Source!I35,9) -> 0 | CY21: =AA21 -> 78.52 | CZ21: =AE21 -> 10.89 | DA21: =AI21 -> 7.21 | DB21: =ROUND(((ROUND(AT21*CZ21,2)*1)*0),6) -> 0 | DC21: =ROUND(((ROUND(AT21*AG21,2)*1)*0),6) -> 0 | DF21: =ROUND(ROUND(AE21*AI21,2)*CX21,2) -> 0 | DG21: =ROUND(ROUND(AF21,2)*CX21,2) -> 0 | DH21: =ROUND(ROUND(AG21,2)*CX21,2) -> 0 | DI21: =ROUND(ROUND(AH21,2)*CX21,2) -> 0 | DJ21: =DF21 -> 0 | DK21: 0 | DM21: 0 | DO21: 0
A22: =ROW(Source!A35) -> 35 | B22: 55942968 | C22: 55984403 | D22: 55459811 | E22: 1 | F22: 1 | G22: 1081 | H22: 3 | I22: 1.1-1-963 | J22: ТСН-2001.1 Доп. 79, Р. 1, о. 1, поз. 963 | K22: Проволока стальная низкоуглеродистая общего назначения, диаметр от 1,6 до 3,0 мм | L22: 1348 | N22: 1009 | O22: т | P22: т | Q22: 1000 | W22: 0 | X22: -572924193 | Y22: =((AT22*1)*0) -> 0 | AA22: 64597.89 | AB22: 0 | AC22: 0 | AD22: 0 | AE22: 8054.6 | AF22: 0 | AG22: 0 | AH22: 0 | AI22: 8.02 | AJ22: 1 | AK22: 1 | AL22: 1 | AM22: 2 | AN22: 0 | AO22: 1 | AP22: 1 | AQ22: 0 | AR22: 0 | AT22: 1e-05 | AU22: *1)*0 | AV22: 0 | AW22: 2 | AX22: 55985175 | AY22: 1 | AZ22: 0 | BA22: 22 | BB22: 0 | BC22: 0 | BD22: 0 | BE22: 0 | BF22: 0 | BG22: 0 | BH22: 0 | BI22: 0 | BJ22: 0 | BK22: 0 | BL22: 0 | BM22: 0 | BN22: 0 | BO22: 0 | BP22: 0 | BQ22: 0 | BR22: 0 | BS22: 0 | BT22: 0 | BU22: 0 | BV22: 0 | BW22: 0 | CV22: 0 | CW22: 0 | CX22: =ROUND(Y22*Source!I35,9) -> 0 | CY22: =AA22 -> 64597.89 | CZ22: =AE22 -> 8054.6 | DA22: =AI22 -> 8.02 | DB22: =ROUND(((ROUND(AT22*CZ22,2)*1)*0),6) -> 0 | DC22: =ROUND(((ROUND(AT22*AG22,2)*1)*0),6) -> 0 | DF22: =ROUND(ROUND(AE22*AI22,2)*CX22,2) -> 0 | DG22: =ROUND(ROUND(AF22,2)*CX22,2) -> 0 | DH22: =ROUND(ROUND(AG22,2)*CX22,2) -> 0 | DI22: =ROUND(ROUND(AH22,2)*CX22,2) -> 0 | DJ22: =DF22 -> 0 | DK22: 0 | DM22: 0 | DO22: 0
A23: =ROW(Source!A71) -> 71 | B23: 55942966 | C23: 55943207 | D23: 55424304 | E23: 1081 | F23: 1 | G23: 1081 | H23: 1 | I23: 9999990008 | K23: Трудозатраты рабочих | L23: 1191 | N23: 1013 | O23: чел.-ч. | P23: чел.-ч. | Q23: 1 | W23: 0 | X23: 476480486 | Y23: =(AT23*1.2) -> 3.6 | AA23: 0 | AB23: 0 | AC23: 0 | AD23: 0 | AE23: 0 | AF23: 0 | AG23: 0 | AH23: 0 | AI23: 1 | AJ23: 1 | AK23: 1 | AL23: 1 | AM23: -2 | AN23: 0 | AO23: 1 | AP23: 1 | AQ23: 0 | AR23: 0 | AT23: 3 | AU23: *1,2 | AV23: 1 | AW23: 2 | AX23: 55984434 | AY23: 1 | AZ23: 0 | BA23: 23 | BB23: 0 | BC23: 0 | BD23: 0 | BE23: 0 | BF23: 0 | BG23: 0 | BH23: 0 | BI23: 0 | BJ23: 0 | BK23: 0 | BL23: 0 | BM23: 0 | BN23: 0 | BO23: 0 | BP23: 0 | BQ23: 0 | BR23: 0 | BS23: 0 | BT23: 0 | BU23: 0 | BV23: 0 | BW23: 0 | CU23: =ROUND(AT23*Source!I71*AH23*AL23,2) -> 0 | CV23: =ROUND(Y23*Source!I71,9) -> 3.6 | CW23: 0 | CX23: =ROUND(Y23*Source!I71,9) -> 3.6 | CY23: =AD23 -> 0 | CZ23: =AH23 -> 0 | DA23: =AL23 -> 1 | DB23: =ROUND((ROUND(AT23*CZ23,2)*1.2),6) -> 0 | DC23: =ROUND((ROUND(AT23*AG23,2)*1.2),6) -> 0 | DF23: =ROUND(ROUND(AE23,2)*CX23,2) -> 0 | DG23: =ROUND(ROUND(AF23,2)*CX23,2) -> 0 | DH23: =ROUND(ROUND(AG23,2)*CX23,2) -> 0 | DI23: =ROUND(ROUND(AH23,2)*CX23,2) -> 0 | DJ23: =DI23 -> 0 | DK23: 0 | DM23: 0 | DO23: 0
