Workbook

Sheet Смета по ТСН-2001(с доп.67
A1: =Source!B1 -> Smeta.RU (495) 974-1589
J2: Форма № 4б
A3: Капитальный ремонт здания Государственного бюджетного общеобразовательного учреждения города Москвы «Школа №1574», расположенного по адресу: г. Москва, Старопименовский переулок, д. 5. 1 этап. | AP3: Капитальный ремонт здания Государственного бюджетного общеобразовательного учреждения города Москвы «Школа №1574», расположенного по адресу: г. Москва, Старопименовский переулок, д. 5. 1 этап.
A4: (наименование стройки и/или объекта)
A6: =CONCATENATE( "ЛОКАЛЬНАЯ СМЕТА № ",IF(Source!F12<>"Новый объект", Source!F12, "")) -> ЛОКАЛЬНАЯ СМЕТА № 02-01-06.
A8: Отопление.
A9: (наименование работ и затрат)
A11: =CONCATENATE( "Основание: чертежи № ", Source!J12) -> Основание: чертежи № 2024-00375-01-0-ИОС4.1
I13: В базисном уровне цен | J13: В текущем уровне цен
E14: Сметная стоимость | I14: =I15+I16+I17+I18 -> 1411.49 | J14: =J15+J16+J17+J18 -> 19902.93 | K14: тыс.руб.
E15: Строительные работы | I15: =ROUND((Source!F675)/1000, 2) -> 1379.86 | J15: =ROUND((Source!P675)/1000, 2) -> 19683.43 | K15: тыс.руб.
E16: Работы по монтажу оборудования | I16: =ROUND((Source!F676)/1000, 2) -> 0.17 | J16: =ROUND((Source!P676)/1000, 2) -> 9.46 | K16: тыс.руб.
E17: Оборудование | I17: =ROUND((Source!F667)/1000, 2) -> 31.46 | J17: =ROUND((Source!P667)/1000, 2) -> 210.04 | K17: тыс.руб.
E18: Прочие работы и затраты | I18: =ROUND((Source!F677+Source!F678)/1000, 2) -> 0 | J18: =ROUND((Source!P677+Source!P678)/1000, 2) -> 0 | K18: тыс.руб.
E19: Средства на оплату труда | I19: =(Source!F673+ Source!F672)/1000 -> 57.03786 | J19: =((Source!P673 + Source!P672)/1000) -> 3214.0835 | K19: тыс.руб.
E20: Затраты труда | I20: =Source!F680 -> 4400.9578 | K20: чел.-ч.
E21: Кроме того:
E22: Возврат материалов | I22: =SUM(Y1:Y842)/1000 -> 0 | J22: =SUM(Z1:Z842)/1000 -> 0 | K22: тыс.руб.
A24: Составлен(а) по ТСН-2001 с учетом Дополнения №: 81
A25: № и период сборника коэффициентов (индексов) пересчета: Коэффициенты к ТСН-2001 МГЭ Дополнение 81, ремонт №219/81 I квартал 2026 года и Коэффициенты к ТСН-2001.13-2 Дополнение 47 №64/47 I квартал 2026 года | AP25: № и период сборника коэффициентов (индексов) пересчета: Коэффициенты к ТСН-2001 МГЭ Дополнение 81, ремонт №219/81 I квартал 2026 года и Коэффициенты к ТСН-2001.13-2 Дополнение 47 №64/47 I квартал 2026 года
A26: № п/п | B26: Шифр расценки и коды ресурсов | C26: Наименование работ и затрат | D26: Ед. изм. | E26: Кол-во единиц | F26: Цена на ед. изм., руб. | G26: Попра- вочные коэффи- циенты | H26: Коэффи- циенты зимних удорожа- ний | I26: Всего в ценах на январь 2000 года, руб. | J26: Коэффи- циенты (индек- сы) пере- счета, нормы НР и СП | K26: ВСЕГО затрат в текущем уровне цен, руб.
A27: 1 | B27: 2 | C27: 3 | D27: 4 | E27: 5 | F27: 6 | G27: 7 | H27: 8 | I27: 9 | J27: 10 | K27: 11
A29: =CONCATENATE("Локальная смета: ",IF(Source!G20<>"Новая локальная смета", Source!G20, "")) -> Локальная смета: Отопление.
A31: =CONCATENATE("Раздел: ",IF(Source!G24<>"Новый раздел", Source!G24, "")) -> Раздел: Отопительные приборы.
A32: 1 | B32: =Source!F28 -> 3.18-25-1 | C32: Установка радиаторов стальных панельных однорядных с креплением к стене длиной до 1600 мм (вентиль справа) | D32: =Source!H28 -> 100 шт. | E32: =Source!I28 -> 1.33 | Q32: =Source!X28 -> 2039.9 | R32: =Source!X29 -> 114948.49 | S32: =Source!Y28 -> 1141.6 | T32: =Source!Y29 -> 64328.97 | U32: =ROUND((175/100)*ROUND(Source!R28, 2), 2) -> 39.52 | V32: =ROUND((0/100)*ROUND(Source!R29, 2), 2) -> 0 | AC32: 0
C33: ="Объем: "&Source!I28&"=(1+"&"9+"&"11+"&"13+"&"23+"&"2+"&"10+"&"13+"&"18+"&"6+"&"17+"&"2+"&"8)/"&"100" -> Объем: 1,33=(1+9+11+13+23+2+10+13+18+6+17+2+8)/100
C34: ЗП | F34: =Source!AO28 -> 916.6 | G34: 1,03*1,15*1,2 | H34: =Source!AV29 -> 1.067 | I34: =Source!S28 -> 1848.89 | J34: =IF(Source!BA29<> 0, Source!BA29, 1) -> 56.35 | K34: =Source!S29 -> 104184.95
C35: ЭМ | F35: =Source!AM28 -> 95.35 | G35: 1,03*1,25*1,2 | H35: =Source!AV29 -> 1.067 | I35: =Source!Q28 -> 209.06 | J35: =IF(Source!BB29<> 0, Source!BB29, 1) -> 15.04 | K35: =Source!Q29 -> 3144.26
C36: в т.ч. ЗПМ | F36: =Source!AN28 -> 10.3 | G36: 1,03*1,25*1,2 | H36: =Source!AV29 -> 1.067 | I36: =Source!R28 -> 22.58 | J36: =IF(Source!BS29<> 0, Source!BS29, 1) -> 56.35 | K36: =Source!R29 -> 1272.38
C37: МР | F37: =Source!AL28 -> 2078.86 | H37: =Source!AW29 -> 1 | I37: =Source!P28 -> 2764.88 | J37: =IF(Source!BC29<> 0, Source!BC29, 1) -> 20.83 | K37: =Source!P29 -> 57592.45
A38: 1,1 | B38: =Source!F30 -> КА. п. 1 | C38: Сmальной nанельный paguamop PRADO Classic, mun 20, Bыcoma Н = 500 мм, PRADO Classic-20-500-400 373,26 = [4 393 / 1,22 / 9,84] + 2% Заг.скл | D38: =Source!H30 -> шт. | E38: =Source!I30 -> 1 | F38: =Source!AK30 -> 373.26 | H38: =Source!AW31 -> 1 | I38: =Source!O30 -> 373.26 | J38: =IF(Source!BC31<> 0, Source!BC31, 1) -> 9.84 | K38: =Source!O31 -> 3672.88 | Q38: =Source!X30 -> 0 | R38: =Source!X31 -> 0 | S38: =Source!Y30 -> 0 | T38: =Source!Y31 -> 0 | U38: =ROUND((175/100)*ROUND(Source!R30, 2), 2) -> 0 | V38: =ROUND((0/100)*ROUND(Source!R31, 2), 2) -> 0 | AC38: 3
A39: 1,2 | B39: =Source!F32 -> КА. п. 2 | C39: Сmальной nанельный paguamop PRADO Classic, mun 20, Bыcoma Н = 500 мм, PRADO Classic-20-500-500 431,97 = [5 084 / 1,22 / 9,84] + 2% Заг.скл | D39: =Source!H32 | E39: =Source!I32 -> 9 | F39: =Source!AK32 -> 431.97 | H39: =Source!AW33 -> 1 | I39: =Source!O32 -> 3887.73 | J39: =IF(Source!BC33<> 0, Source!BC33, 1) -> 9.84 | K39: =Source!O33 -> 38255.26 | Q39: =Source!X32 -> 0 | R39: =Source!X33 -> 0 | S39: =Source!Y32 -> 0 | T39: =Source!Y33 -> 0 | U39: =ROUND((175/100)*ROUND(Source!R32, 2), 2) -> 0 | V39: =ROUND((0/100)*ROUND(Source!R33, 2), 2) -> 0 | AC39: 3
A40: 1,3 | B40: =Source!F34 -> КА. п. 3 | C40: Сmальной nанельный paguamop PRADO Classic, mun 20, Bыcoma Н = 500 мм, PRADO Classic-20-500-600 494,25 = [5 817 / 1,22 / 9,84] + 2% Заг.скл | D40: =Source!H34 | E40: =Source!I34 -> 11 | F40: =Source!AK34 -> 494.25 | H40: =Source!AW35 -> 1 | I40: =Source!O34 -> 5436.75 | J40: =IF(Source!BC35<> 0, Source!BC35, 1) -> 9.84 | K40: =Source!O35 -> 53497.62 | Q40: =Source!X34 -> 0 | R40: =Source!X35 -> 0 | S40: =Source!Y34 -> 0 | T40: =Source!Y35 -> 0 | U40: =ROUND((175/100)*ROUND(Source!R34, 2), 2) -> 0 | V40: =ROUND((0/100)*ROUND(Source!R35, 2), 2) -> 0 | AC40: 3
A41: 1,4 | B41: =Source!F36 -> КА. п. 4 | C41: Сmальной nанельный paguamop PRADO Classic, mun 20, Bыcoma Н = 500 мм, PRADO Classic-20-500-700 545,65 = [6 422 / 1,22 / 9,84] + 2% Заг.скл | D41: =Source!H36 | E41: =Source!I36 -> 13 | F41: =Source!AK36 -> 545.65 | H41: =Source!AW37 -> 1 | I41: =Source!O36 -> 7093.45 | J41: =IF(Source!BC37<> 0, Source!BC37, 1) -> 9.84 | K41: =Source!O37 -> 69799.55 | Q41: =Source!X36 -> 0 | R41: =Source!X37 -> 0 | S41: =Source!Y36 -> 0 | T41: =Source!Y37 -> 0 | U41: =ROUND((175/100)*ROUND(Source!R36, 2), 2) -> 0 | V41: =ROUND((0/100)*ROUND(Source!R37, 2), 2) -> 0 | AC41: 3
A42: 1,5 | B42: =Source!F38 -> КА. п. 5 | C42: Сmальной nанельный paguamop PRADO Classic, mun 20, Bыcoma Н = 500 мм, PRADO Classic-20-500-800 601,47 = [7 079 / 1,22 / 9,84] + 2% Заг.скл | D42: =Source!H38 | E42: =Source!I38 -> 23 | F42: =Source!AK38 -> 601.47 | H42: =Source!AW39 -> 1 | I42: =Source!O38 -> 13833.81 | J42: =IF(Source!BC39<> 0, Source!BC39, 1) -> 9.84 | K42: =Source!O39 -> 136124.69 | Q42: =Source!X38 -> 0 | R42: =Source!X39 -> 0 | S42: =Source!Y38 -> 0 | T42: =Source!Y39 -> 0 | U42: =ROUND((175/100)*ROUND(Source!R38, 2), 2) -> 0 | V42: =ROUND((0/100)*ROUND(Source!R39, 2), 2) -> 0 | AC42: 3
A43: 1,6 | B43: =Source!F40 -> КА. п. 6 | C43: Сmальной nанельный paguamop PRADO Classic, mun 20, Bыcoma Н = 500 мм, PRADO Classic-20-500-900 660,10 = [7 769 / 1,22 / 9,84] + 2% Заг.скл | D43: =Source!H40 | E43: =Source!I40 -> 2 | F43: =Source!AK40 -> 660.1 | H43: =Source!AW41 -> 1 | I43: =Source!O40 -> 1320.2 | J43: =IF(Source!BC41<> 0, Source!BC41, 1) -> 9.84 | K43: =Source!O41 -> 12990.77 | Q43: =Source!X40 -> 0 | R43: =Source!X41 -> 0 | S43: =Source!Y40 -> 0 | T43: =Source!Y41 -> 0 | U43: =ROUND((175/100)*ROUND(Source!R40, 2), 2) -> 0 | V43: =ROUND((0/100)*ROUND(Source!R41, 2), 2) -> 0 | AC43: 3
A44: 1,7 | B44: =Source!F42 -> КА. п. 7 | C44: Сmальной nанельный paguamop PRADO Classic, mun 20, Bыcoma Н = 500 мм, PRADO Classic-20-500-1000 726,04 = [8 545 / 1,22 / 9,84] + 2% Заг.скл | D44: =Source!H42 | E44: =Source!I42 -> 10 | F44: =Source!AK42 -> 726.04 | H44: =Source!AW43 -> 1 | I44: =Source!O42 -> 7260.4 | J44: =IF(Source!BC43<> 0, Source!BC43, 1) -> 9.84 | K44: =Source!O43 -> 71442.34 | Q44: =Source!X42 -> 0 | R44: =Source!X43 -> 0 | S44: =Source!Y42 -> 0 | T44: =Source!Y43 -> 0 | U44: =ROUND((175/100)*ROUND(Source!R42, 2), 2) -> 0 | V44: =ROUND((0/100)*ROUND(Source!R43, 2), 2) -> 0 | AC44: 3
A45: 1,8 | B45: =Source!F44 -> КА. п. 8 | C45: Сmальной nанельный paguamop PRADO Classic, mun 20, Bыcoma Н = 500 мм, PRADO Classic-20-500-1100 781,86 = [9 202 / 1,22 / 9,84] + 2% Заг.скл | D45: =Source!H44 | E45: =Source!I44 -> 13 | F45: =Source!AK44 -> 781.86 | H45: =Source!AW45 -> 1 | I45: =Source!O44 -> 10164.18 | J45: =IF(Source!BC45<> 0, Source!BC45, 1) -> 9.84 | K45: =Source!O45 -> 100015.53 | Q45: =Source!X44 -> 0 | R45: =Source!X45 -> 0 | S45: =Source!Y44 -> 0 | T45: =Source!Y45 -> 0 | U45: =ROUND((175/100)*ROUND(Source!R44, 2), 2) -> 0 | V45: =ROUND((0/100)*ROUND(Source!R45, 2), 2) -> 0 | AC45: 3
A46: 1,9 | B46: =Source!F46 -> КА. п. 9 | C46: Сmальной nанельный paguamop PRADO Classic, mun 20, Bыcoma Н = 500 мм, PRADO Classic-20-500-1200 837,85 = [9 861 / 1,22 / 9,84] + 2% Заг.скл | D46: =Source!H46 | E46: =Source!I46 -> 18 | F46: =Source!AK46 -> 837.85 | H46: =Source!AW47 -> 1 | I46: =Source!O46 -> 15081.3 | J46: =IF(Source!BC47<> 0, Source!BC47, 1) -> 9.84 | K46: =Source!O47 -> 148399.99 | Q46: =Source!X46 -> 0 | R46: =Source!X47 -> 0 | S46: =Source!Y46 -> 0 | T46: =Source!Y47 -> 0 | U46: =ROUND((175/100)*ROUND(Source!R46, 2), 2) -> 0 | V46: =ROUND((0/100)*ROUND(Source!R47, 2), 2) -> 0 | AC46: 3
A47: 1,10 | B47: =Source!F48 -> КА. п. 10 | C47: Сmальной nанельный paguamop PRADO Classic, mun 20, Bыcoma Н = 500 мм, PRADO Classic-20-500-1300 848,72 = [9 989 / 1,22 / 9,84] + 2% Заг.скл | D47: =Source!H48 | E47: =Source!I48 -> 6 | F47: =Source!AK48 -> 848.72 | H47: =Source!AW49 -> 1 | I47: =Source!O48 -> 5092.32 | J47: =IF(Source!BC49<> 0, Source!BC49, 1) -> 9.84 | K47: =Source!O49 -> 50108.43 | Q47: =Source!X48 -> 0 | R47: =Source!X49 -> 0 | S47: =Source!Y48 -> 0 | T47: =Source!Y49 -> 0 | U47: =ROUND((175/100)*ROUND(Source!R48, 2), 2) -> 0 | V47: =ROUND((0/100)*ROUND(Source!R49, 2), 2) -> 0 | AC47: 3
A48: 1,11 | B48: =Source!F50 -> КА. п. 11 | C48: Сmальной nанельный paguamop PRADO Classic, mun 20, Bыcoma Н = 500 мм, PRADO Classic-20-500-1400 956,80 = [11 261 / 1,22 / 9,84] + 2% Заг.скл | D48: =Source!H50 | E48: =Source!I50 -> 17 | F48: =Source!AK50 -> 956.8 | H48: =Source!AW51 -> 1 | I48: =Source!O50 -> 16265.6 | J48: =IF(Source!BC51<> 0, Source!BC51, 1) -> 9.84 | K48: =Source!O51 -> 160053.5 | Q48: =Source!X50 -> 0 | R48: =Source!X51 -> 0 | S48: =Source!Y50 -> 0 | T48: =Source!Y51 -> 0 | U48: =ROUND((175/100)*ROUND(Source!R50, 2), 2) -> 0 | V48: =ROUND((0/100)*ROUND(Source!R51, 2), 2) -> 0 | AC48: 3
A49: 1,12 | B49: =Source!F52 -> КА. п. 12 | C49: Сmальной nанельный paguamop PRADO Classic, mun 20, Bыcoma Н = 500 мм, PRADO Classic-20-500-1500 963,69 = [11 342 / 1,22 / 9,84] + 2% Заг.скл | D49: =Source!H52 | E49: =Source!I52 -> 2 | F49: =Source!AK52 -> 963.69 | H49: =Source!AW53 -> 1 | I49: =Source!O52 -> 1927.38 | J49: =IF(Source!BC53<> 0, Source!BC53, 1) -> 9.84 | K49: =Source!O53 -> 18965.42 | Q49: =Source!X52 -> 0 | R49: =Source!X53 -> 0 | S49: =Source!Y52 -> 0 | T49: =Source!Y53 -> 0 | U49: =ROUND((175/100)*ROUND(Source!R52, 2), 2) -> 0 | V49: =ROUND((0/100)*ROUND(Source!R53, 2), 2) -> 0 | AC49: 3
A50: 1,13 | B50: =Source!F54 -> КА. п. 13 | C50: Сmальной nанельный paguamop PRADO Classic, mun 20, Bыcoma Н = 500 мм, PRADO Classic-20-500-1600 1 071,34 = [12 609 / 1,22 / 9,84] + 2% Заг.скл | D50: =Source!H54 | E50: =Source!I54 -> 8 | F50: =Source!AK54 -> 1071.34 | H50: =Source!AW55 -> 1 | I50: =Source!O54 -> 8570.72 | J50: =IF(Source!BC55<> 0, Source!BC55, 1) -> 9.84 | K50: =Source!O55 -> 84335.88 | Q50: =Source!X54 -> 0 | R50: =Source!X55 -> 0 | S50: =Source!Y54 -> 0 | T50: =Source!Y55 -> 0 | U50: =ROUND((175/100)*ROUND(Source!R54, 2), 2) -> 0 | V50: =ROUND((0/100)*ROUND(Source!R55, 2), 2) -> 0 | AC50: 3
C51: НР от ФОТ | D51: % | E51: =Source!BZ29 -> 109 | I51: =SUM(Q32:Q50) -> 2039.9 | J51: =Source!AT29 -> 109 | K51: =SUM(R32:R50) -> 114948.49
C52: СП от ФОТ | D52: % | E52: =Source!CA29 -> 61 | I52: =SUM(S32:S51) -> 1141.6 | J52: =Source!AU29 -> 61 | K52: =SUM(T32:T51) -> 64328.97
C53: ЗТР | D53: чел-ч | E53: =Source!AQ28 -> 74.7 | G53: 1,03*1,15*1,2 | H53: =Source!AV29 -> 1.067 | I53: =Source!U28 -> 150.67908
C54: ВСЕГО работ по позиции: | H54: =I34+I35+I37+I51+I52+SUM(I38:I50)-SUMIF(AC38:AC50, 5, I38:I50)-SUMIF(AC38:AC50, 6, I38:I50) -> 104311.43 | J54: =K34+K35+K37+K51+K52+SUM(K38:K50)-SUMIF(AC38:AC50, 5, K38:K50)-SUMIF(AC38:AC50, 6, K38:K50) -> 1291861
C55: ВСЕГО оборудование по позиции: | H55: =SUMIF(AC38:AC50, 5, I38:I50)+SUMIF(AC38:AC50, 6, I38:I50) -> 0 | J55: =SUMIF(AC38:AC50, 5, K38:K50)+SUMIF(AC38:AC50, 6, K38:K50) -> 0
C56: ВСЕГО по позиции: | H56: =I34+I35+I37+I51+I52+SUM(I38:I50) -> 104311.43 | J56: =K34+K35+K37+K51+K52+SUM(K38:K50) -> 1291861 | O56: =I34+I35+I37+I51+I52+SUM(I38:I50) -> 104311.43 | P56: =K34+K35+K37+K51+K52+SUM(K38:K50) -> 1291861
A58: 2 | B58: =Source!F56 -> 3.18-25-2 | C58: Установка радиаторов стальных панельных однорядных с креплением к стене длиной свыше 1600 до 2000 мм (вентиль справа) | D58: =Source!H56 -> 100 шт. | E58: =Source!I56 -> 0.02 | Q58: =Source!X56 -> 40.2 | R58: =Source!X57 -> 2265.23 | S58: =Source!Y56 -> 22.5 | T58: =Source!Y57 -> 1267.7 | U58: =ROUND((175/100)*ROUND(Source!R56, 2), 2) -> 1.05 | V58: =ROUND((0/100)*ROUND(Source!R57, 2), 2) -> 0 | AC58: 0
C59: ="Объем: "&Source!I56&"=(1+"&"1)/"&"100" -> Объем: 0,02=(1+1)/100
C60: ЗП | F60: =Source!AO56 -> 1196.19 | G60: 1,03*1,15*1,2 | H60: =Source!AV57 -> 1.067 | I60: =Source!S56 -> 36.28 | J60: =IF(Source!BA57<> 0, Source!BA57, 1) -> 56.35 | K60: =Source!S57 -> 2044.38
C61: ЭМ | F61: =Source!AM56 -> 166.7 | G61: 1,03*1,25*1,2 | H61: =Source!AV57 -> 1.067 | I61: =Source!Q56 -> 5.5 | J61: =IF(Source!BB57<> 0, Source!BB57, 1) -> 15.06 | K61: =Source!Q57 -> 82.83
C62: в т.ч. ЗПМ | F62: =Source!AN56 -> 18.07 | G62: 1,03*1,25*1,2 | H62: =Source!AV57 -> 1.067 | I62: =Source!R56 -> 0.6 | J62: =IF(Source!BS57<> 0, Source!BS57, 1) -> 56.35 | K62: =Source!R57 -> 33.81
C63: МР | F63: =Source!AL56 -> 3119.05 | H63: =Source!AW57 -> 1 | I63: =Source!P56 -> 62.38 | J63: =IF(Source!BC57<> 0, Source!BC57, 1) -> 20.83 | K63: =Source!P57 -> 1299.38
A64: 2,1 | B64: =Source!F58 -> КА. п. 14 | C64: Сmальной nанельный paguamop PRADO Classic, mun 20, Bыcoma Н = 500 мм, PRADO Classic-20-500-1900 1 190,46 = [14 011 / 1,22 / 9,84] + 2% Заг.скл | D64: =Source!H58 -> шт. | E64: =Source!I58 -> 1 | F64: =Source!AK58 -> 1190.46 | H64: =Source!AW59 -> 1 | I64: =Source!O58 -> 1190.46 | J64: =IF(Source!BC59<> 0, Source!BC59, 1) -> 9.84 | K64: =Source!O59 -> 11714.13 | Q64: =Source!X58 -> 0 | R64: =Source!X59 -> 0 | S64: =Source!Y58 -> 0 | T64: =Source!Y59 -> 0 | U64: =ROUND((175/100)*ROUND(Source!R58, 2), 2) -> 0 | V64: =ROUND((0/100)*ROUND(Source!R59, 2), 2) -> 0 | AC64: 3
A65: 2,2 | B65: =Source!F60 -> КА. п. 15 | C65: Сmальной nанельный paguamop PRADO Classic, mun 20, Bыcoma Н = 500 мм, PRADO Classic-20-500-2000 1 322,07 = [15 560 / 1,22 / 9,84] + 2% Заг.скл | D65: =Source!H60 -> шт. | E65: =Source!I60 -> 1 | F65: =Source!AK60 -> 1322.07 | H65: =Source!AW61 -> 1 | I65: =Source!O60 -> 1322.07 | J65: =IF(Source!BC61<> 0, Source!BC61, 1) -> 9.84 | K65: =Source!O61 -> 13009.17 | Q65: =Source!X60 -> 0 | R65: =Source!X61 -> 0 | S65: =Source!Y60 -> 0 | T65: =Source!Y61 -> 0 | U65: =ROUND((175/100)*ROUND(Source!R60, 2), 2) -> 0 | V65: =ROUND((0/100)*ROUND(Source!R61, 2), 2) -> 0 | AC65: 3
C66: НР от ФОТ | D66: % | E66: =Source!BZ57 -> 109 | I66: =SUM(Q58:Q65) -> 40.2 | J66: =Source!AT57 -> 109 | K66: =SUM(R58:R65) -> 2265.23
C67: СП от ФОТ | D67: % | E67: =Source!CA57 -> 61 | I67: =SUM(S58:S66) -> 22.5 | J67: =Source!AU57 -> 61 | K67: =SUM(T58:T66) -> 1267.7
C68: ЗТР | D68: чел-ч | E68: =Source!AQ56 -> 97.55 | G68: 1,03*1,15*1,2 | H68: =Source!AV57 -> 1.067 | I68: =Source!U56 -> 2.9589525
C69: ВСЕГО работ по позиции: | H69: =I60+I61+I63+I66+I67+SUM(I64:I65)-SUMIF(AC64:AC65, 5, I64:I65)-SUMIF(AC64:AC65, 6, I64:I65) -> 2679.39 | J69: =K60+K61+K63+K66+K67+SUM(K64:K65)-SUMIF(AC64:AC65, 5, K64:K65)-SUMIF(AC64:AC65, 6, K64:K65) -> 31682.82
C70: ВСЕГО оборудование по позиции: | H70: =SUMIF(AC64:AC65, 5, I64:I65)+SUMIF(AC64:AC65, 6, I64:I65) -> 0 | J70: =SUMIF(AC64:AC65, 5, K64:K65)+SUMIF(AC64:AC65, 6, K64:K65) -> 0
C71: ВСЕГО по позиции: | H71: =I60+I61+I63+I66+I67+SUM(I64:I65) -> 2679.39 | J71: =K60+K61+K63+K66+K67+SUM(K64:K65) -> 31682.82 | O71: =I60+I61+I63+I66+I67+SUM(I64:I65) -> 2679.39 | P71: =K60+K61+K63+K66+K67+SUM(K64:K65) -> 31682.82
A73: 3 | B73: =Source!F62 -> 3.18-25-1 | C73: Установка радиаторов стальных панельных однорядных с креплением к стене длиной до 1600 мм (вентиль слева) | D73: =Source!H62 -> 100 шт. | E73: =Source!I62 -> 1.52 | Q73: =Source!X62 -> 2331.32 | R73: =Source!X63 -> 131370.15 | S73: =Source!Y62 -> 1304.69 | T73: =Source!Y63 -> 73519.07 | U73: =ROUND((175/100)*ROUND(Source!R62, 2), 2) -> 45.17 | V73: =ROUND((0/100)*ROUND(Source!R63, 2), 2) -> 0 | AC73: 0
C74: ="Объем: "&Source!I62&"=(9+"&"13+"&"15+"&"25+"&"3+"&"20+"&"13+"&"15+"&"3+"&"24+"&"2+"&"10)/"&"100" -> Объем: 1,52=(9+13+15+25+3+20+13+15+3+24+2+10)/100
C75: ЗП | F75: =Source!AO62 -> 916.6 | G75: 1,03*1,15*1,2 | H75: =Source!AV63 -> 1.067 | I75: =Source!S62 -> 2113.02 | J75: =IF(Source!BA63<> 0, Source!BA63, 1) -> 56.35 | K75: =Source!S63 -> 119068.68
C76: ЭМ | F76: =Source!AM62 -> 95.35 | G76: 1,03*1,25*1,2 | H76: =Source!AV63 -> 1.067 | I76: =Source!Q62 -> 238.92 | J76: =IF(Source!BB63<> 0, Source!BB63, 1) -> 15.04 | K76: =Source!Q63 -> 3593.36
C77: в т.ч. ЗПМ | F77: =Source!AN62 -> 10.3 | G77: 1,03*1,25*1,2 | H77: =Source!AV63 -> 1.067 | I77: =Source!R62 -> 25.81 | J77: =IF(Source!BS63<> 0, Source!BS63, 1) -> 56.35 | K77: =Source!R63 -> 1454.39
C78: МР | F78: =Source!AL62 -> 2078.86 | H78: =Source!AW63 -> 1 | I78: =Source!P62 -> 3159.87 | J78: =IF(Source!BC63<> 0, Source!BC63, 1) -> 20.83 | K78: =Source!P63 -> 65820.09
A79: 3,1 | B79: =Source!F64 -> КА. п. 2 | C79: Сmальной nанельный paguamop PRADO Classic, mun 20, Bыcoma Н = 500 мм, PRADO Classic-20-500-500 431,97 = [5 084 / 1,22 / 9,84] + 2% Заг.скл | D79: =Source!H64 | E79: =Source!I64 -> 9 | F79: =Source!AK64 -> 431.97 | H79: =Source!AW65 -> 1 | I79: =Source!O64 -> 3887.73 | J79: =IF(Source!BC65<> 0, Source!BC65, 1) -> 9.84 | K79: =Source!O65 -> 38255.26 | Q79: =Source!X64 -> 0 | R79: =Source!X65 -> 0 | S79: =Source!Y64 -> 0 | T79: =Source!Y65 -> 0 | U79: =ROUND((175/100)*ROUND(Source!R64, 2), 2) -> 0 | V79: =ROUND((0/100)*ROUND(Source!R65, 2), 2) -> 0 | AC79: 3
A80: 3,2 | B80: =Source!F66 -> КА. п. 3 | C80: Сmальной nанельный paguamop PRADO Classic, mun 20, Bыcoma Н = 500 мм, PRADO Classic-20-500-600 494,25 = [5 817 / 1,22 / 9,84] + 2% Заг.скл | D80: =Source!H66 | E80: =Source!I66 -> 13 | F80: =Source!AK66 -> 494.25 | H80: =Source!AW67 -> 1 | I80: =Source!O66 -> 6425.25 | J80: =IF(Source!BC67<> 0, Source!BC67, 1) -> 9.84 | K80: =Source!O67 -> 63224.46 | Q80: =Source!X66 -> 0 | R80: =Source!X67 -> 0 | S80: =Source!Y66 -> 0 | T80: =Source!Y67 -> 0 | U80: =ROUND((175/100)*ROUND(Source!R66, 2), 2) -> 0 | V80: =ROUND((0/100)*ROUND(Source!R67, 2), 2) -> 0 | AC80: 3
A81: 3,3 | B81: =Source!F68 -> КА. п. 4 | C81: Сmальной nанельный paguamop PRADO Classic, mun 20, Bыcoma Н = 500 мм, PRADO Classic-20-500-700 545,65 = [6 422 / 1,22 / 9,84] + 2% Заг.скл | D81: =Source!H68 | E81: =Source!I68 -> 15 | F81: =Source!AK68 -> 545.65 | H81: =Source!AW69 -> 1 | I81: =Source!O68 -> 8184.75 | J81: =IF(Source!BC69<> 0, Source!BC69, 1) -> 9.84 | K81: =Source!O69 -> 80537.94 | Q81: =Source!X68 -> 0 | R81: =Source!X69 -> 0 | S81: =Source!Y68 -> 0 | T81: =Source!Y69 -> 0 | U81: =ROUND((175/100)*ROUND(Source!R68, 2), 2) -> 0 | V81: =ROUND((0/100)*ROUND(Source!R69, 2), 2) -> 0 | AC81: 3
A82: 3,4 | B82: =Source!F70 -> КА. п. 5 | C82: Сmальной nанельный paguamop PRADO Classic, mun 20, Bыcoma Н = 500 мм, PRADO Classic-20-500-800 601,47 = [7 079 / 1,22 / 9,84] + 2% Заг.скл | D82: =Source!H70 | E82: =Source!I70 -> 25 | F82: =Source!AK70 -> 601.47 | H82: =Source!AW71 -> 1 | I82: =Source!O70 -> 15036.75 | J82: =IF(Source!BC71<> 0, Source!BC71, 1) -> 9.84 | K82: =Source!O71 -> 147961.62 | Q82: =Source!X70 -> 0 | R82: =Source!X71 -> 0 | S82: =Source!Y70 -> 0 | T82: =Source!Y71 -> 0 | U82: =ROUND((175/100)*ROUND(Source!R70, 2), 2) -> 0 | V82: =ROUND((0/100)*ROUND(Source!R71, 2), 2) -> 0 | AC82: 3
A83: 3,5 | B83: =Source!F72 -> КА. п. 6 | C83: Сmальной nанельный paguamop PRADO Classic, mun 20, Bыcoma Н = 500 мм, PRADO Classic-20-500-900 660,10 = [7 769 / 1,22 / 9,84] + 2% Заг.скл | D83: =Source!H72 | E83: =Source!I72 -> 3 | F83: =Source!AK72 -> 660.1 | H83: =Source!AW73 -> 1 | I83: =Source!O72 -> 1980.3 | J83: =IF(Source!BC73<> 0, Source!BC73, 1) -> 9.84 | K83: =Source!O73 -> 19486.15 | Q83: =Source!X72 -> 0 | R83: =Source!X73 -> 0 | S83: =Source!Y72 -> 0 | T83: =Source!Y73 -> 0 | U83: =ROUND((175/100)*ROUND(Source!R72, 2), 2) -> 0 | V83: =ROUND((0/100)*ROUND(Source!R73, 2), 2) -> 0 | AC83: 3
A84: 3,6 | B84: =Source!F74 -> КА. п. 7 | C84: Сmальной nанельный paguamop PRADO Classic, mun 20, Bыcoma Н = 500 мм, PRADO Classic-20-500-1000 726,04 = [8 545 / 1,22 / 9,84] + 2% Заг.скл | D84: =Source!H74 | E84: =Source!I74 -> 20 | F84: =Source!AK74 -> 726.04 | H84: =Source!AW75 -> 1 | I84: =Source!O74 -> 14520.8 | J84: =IF(Source!BC75<> 0, Source!BC75, 1) -> 9.84 | K84: =Source!O75 -> 142884.67 | Q84: =Source!X74 -> 0 | R84: =Source!X75 -> 0 | S84: =Source!Y74 -> 0 | T84: =Source!Y75 -> 0 | U84: =ROUND((175/100)*ROUND(Source!R74, 2), 2) -> 0 | V84: =ROUND((0/100)*ROUND(Source!R75, 2), 2) -> 0 | AC84: 3
A85: 3,7 | B85: =Source!F76 -> КА. п. 8 | C85: Сmальной nанельный paguamop PRADO Classic, mun 20, Bыcoma Н = 500 мм, PRADO Classic-20-500-1100 781,86 = [9 202 / 1,22 / 9,84] + 2% Заг.скл | D85: =Source!H76 | E85: =Source!I76 -> 13 | F85: =Source!AK76 -> 781.86 | H85: =Source!AW77 -> 1 | I85: =Source!O76 -> 10164.18 | J85: =IF(Source!BC77<> 0, Source!BC77, 1) -> 9.84 | K85: =Source!O77 -> 100015.53 | Q85: =Source!X76 -> 0 | R85: =Source!X77 -> 0 | S85: =Source!Y76 -> 0 | T85: =Source!Y77 -> 0 | U85: =ROUND((175/100)*ROUND(Source!R76, 2), 2) -> 0 | V85: =ROUND((0/100)*ROUND(Source!R77, 2), 2) -> 0 | AC85: 3
A86: 3,8 | B86: =Source!F78 -> КА. п. 9 | C86: Сmальной nанельный paguamop PRADO Classic, mun 20, Bыcoma Н = 500 мм, PRADO Classic-20-500-1200 837,85 = [9 861 / 1,22 / 9,84] + 2% Заг.скл | D86: =Source!H78 | E86: =Source!I78 -> 15 | F86: =Source!AK78 -> 837.85 | H86: =Source!AW79 -> 1 | I86: =Source!O78 -> 12567.75 | J86: =IF(Source!BC79<> 0, Source!BC79, 1) -> 9.84 | K86: =Source!O79 -> 123666.66 | Q86: =Source!X78 -> 0 | R86: =Source!X79 -> 0 | S86: =Source!Y78 -> 0 | T86: =Source!Y79 -> 0 | U86: =ROUND((175/100)*ROUND(Source!R78, 2), 2) -> 0 | V86: =ROUND((0/100)*ROUND(Source!R79, 2), 2) -> 0 | AC86: 3
A87: 3,9 | B87: =Source!F80 -> КА. п. 10 | C87: Сmальной nанельный paguamop PRADO Classic, mun 20, Bыcoma Н = 500 мм, PRADO Classic-20-500-1300 848,72 = [9 989 / 1,22 / 9,84] + 2% Заг.скл | D87: =Source!H80 | E87: =Source!I80 -> 3 | F87: =Source!AK80 -> 848.72 | H87: =Source!AW81 -> 1 | I87: =Source!O80 -> 2546.16 | J87: =IF(Source!BC81<> 0, Source!BC81, 1) -> 9.84 | K87: =Source!O81 -> 25054.21 | Q87: =Source!X80 -> 0 | R87: =Source!X81 -> 0 | S87: =Source!Y80 -> 0 | T87: =Source!Y81 -> 0 | U87: =ROUND((175/100)*ROUND(Source!R80, 2), 2) -> 0 | V87: =ROUND((0/100)*ROUND(Source!R81, 2), 2) -> 0 | AC87: 3
A88: 3,10 | B88: =Source!F82 -> КА. п. 11 | C88: Сmальной nанельный paguamop PRADO Classic, mun 20, Bыcoma Н = 500 мм, PRADO Classic-20-500-1400 956,80 = [11 261 / 1,22 / 9,84] + 2% Заг.скл | D88: =Source!H82 | E88: =Source!I82 -> 24 | F88: =Source!AK82 -> 956.8 | H88: =Source!AW83 -> 1 | I88: =Source!O82 -> 22963.2 | J88: =IF(Source!BC83<> 0, Source!BC83, 1) -> 9.84 | K88: =Source!O83 -> 225957.89 | Q88: =Source!X82 -> 0 | R88: =Source!X83 -> 0 | S88: =Source!Y82 -> 0 | T88: =Source!Y83 -> 0 | U88: =ROUND((175/100)*ROUND(Source!R82, 2), 2) -> 0 | V88: =ROUND((0/100)*ROUND(Source!R83, 2), 2) -> 0 | AC88: 3
A89: 3,11 | B89: =Source!F84 -> КА. п. 12 | C89: Сmальной nанельный paguamop PRADO Classic, mun 20, Bыcoma Н = 500 мм, PRADO Classic-20-500-1500 963,69 = [11 342 / 1,22 / 9,84] + 2% Заг.скл | D89: =Source!H84 | E89: =Source!I84 -> 2 | F89: =Source!AK84 -> 963.69 | H89: =Source!AW85 -> 1 | I89: =Source!O84 -> 1927.38 | J89: =IF(Source!BC85<> 0, Source!BC85, 1) -> 9.84 | K89: =Source!O85 -> 18965.42 | Q89: =Source!X84 -> 0 | R89: =Source!X85 -> 0 | S89: =Source!Y84 -> 0 | T89: =Source!Y85 -> 0 | U89: =ROUND((175/100)*ROUND(Source!R84, 2), 2) -> 0 | V89: =ROUND((0/100)*ROUND(Source!R85, 2), 2) -> 0 | AC89: 3
A90: 3,12 | B90: =Source!F86 -> КА. п. 13 | C90: Сmальной nанельный paguamop PRADO Classic, mun 20, Bыcoma Н = 500 мм, PRADO Classic-20-500-1600 1 071,34 = [12 609 / 1,22 / 9,84] + 2% Заг.скл | D90: =Source!H86 | E90: =Source!I86 -> 10 | F90: =Source!AK86 -> 1071.34 | H90: =Source!AW87 -> 1 | I90: =Source!O86 -> 10713.4 | J90: =IF(Source!BC87<> 0, Source!BC87, 1) -> 9.84 | K90: =Source!O87 -> 105419.86 | Q90: =Source!X86 -> 0 | R90: =Source!X87 -> 0 | S90: =Source!Y86 -> 0 | T90: =Source!Y87 -> 0 | U90: =ROUND((175/100)*ROUND(Source!R86, 2), 2) -> 0 | V90: =ROUND((0/100)*ROUND(Source!R87, 2), 2) -> 0 | AC90: 3
C91: НР от ФОТ | D91: % | E91: =Source!BZ63 -> 109 | I91: =SUM(Q73:Q90) -> 2331.32 | J91: =Source!AT63 -> 109 | K91: =SUM(R73:R90) -> 131370.15
C92: СП от ФОТ | D92: % | E92: =Source!CA63 -> 61 | I92: =SUM(S73:S91) -> 1304.69 | J92: =Source!AU63 -> 61 | K92: =SUM(T73:T91) -> 73519.07
C93: ЗТР | D93: чел-ч | E93: =Source!AQ62 -> 74.7 | G93: 1,03*1,15*1,2 | H93: =Source!AV63 -> 1.067 | I93: =Source!U62 -> 172.20467
C94: ВСЕГО работ по позиции: | H94: =I75+I76+I78+I91+I92+SUM(I79:I90)-SUMIF(AC79:AC90, 5, I79:I90)-SUMIF(AC79:AC90, 6, I79:I90) -> 120065.47 | J94: =K75+K76+K78+K91+K92+SUM(K79:K90)-SUMIF(AC79:AC90, 5, K79:K90)-SUMIF(AC79:AC90, 6, K79:K90) -> 1484801
C95: ВСЕГО оборудование по позиции: | H95: =SUMIF(AC79:AC90, 5, I79:I90)+SUMIF(AC79:AC90, 6, I79:I90) -> 0 | J95: =SUMIF(AC79:AC90, 5, K79:K90)+SUMIF(AC79:AC90, 6, K79:K90) -> 0
C96: ВСЕГО по позиции: | H96: =I75+I76+I78+I91+I92+SUM(I79:I90) -> 120065.47 | J96: =K75+K76+K78+K91+K92+SUM(K79:K90) -> 1484801 | O96: =I75+I76+I78+I91+I92+SUM(I79:I90) -> 120065.47 | P96: =K75+K76+K78+K91+K92+SUM(K79:K90) -> 1484801
A98: 4 | B98: =Source!F88 -> 3.18-25-1 | C98: Установка радиаторов стальных панельных однорядных с креплением к стене длиной до 1600 мм (вентиль слева) | D98: =Source!H88 -> 100 шт. | E98: =Source!I88 -> 0.01 | Q98: =Source!X88 -> 15.34 | R98: =Source!X89 -> 864.21 | S98: =Source!Y88 -> 8.58 | T98: =Source!Y89 -> 483.64 | U98: =ROUND((175/100)*ROUND(Source!R88, 2), 2) -> 0.3 | V98: =ROUND((0/100)*ROUND(Source!R89, 2), 2) -> 0 | AC98: 0
C99: ="Объем: "&Source!I88&"=(1)/"&"100" -> Объем: 0,01=(1)/100
C100: ЗП | F100: =Source!AO88 -> 916.6 | G100: 1,03*1,15*1,2 | H100: =Source!AV89 -> 1.067 | I100: =Source!S88 -> 13.9 | J100: =IF(Source!BA89<> 0, Source!BA89, 1) -> 56.35 | K100: =Source!S89 -> 783.27
C101: ЭМ | F101: =Source!AM88 -> 95.35 | G101: 1,03*1,25*1,2 | H101: =Source!AV89 -> 1.067 | I101: =Source!Q88 -> 1.57 | J101: =IF(Source!BB89<> 0, Source!BB89, 1) -> 15.04 | K101: =Source!Q89 -> 23.61
C102: в т.ч. ЗПМ | F102: =Source!AN88 -> 10.3 | G102: 1,03*1,25*1,2 | H102: =Source!AV89 -> 1.067 | I102: =Source!R88 -> 0.17 | J102: =IF(Source!BS89<> 0, Source!BS89, 1) -> 56.35 | K102: =Source!R89 -> 9.58
C103: МР | F103: =Source!AL88 -> 2078.86 | H103: =Source!AW89 -> 1 | I103: =Source!P88 -> 20.79 | J103: =IF(Source!BC89<> 0, Source!BC89, 1) -> 20.83 | K103: =Source!P89 -> 433.06
A104: 4,1 | B104: =Source!F90 -> КА. п. 16 | C104: Сmальной nанельный paguamop PRADO Classic, mun 20, Bыcoma Н = 300 мм, PRADO Classic-20-300-400 342,75 = [4 034 / 1,22 / 9,84] + 2% Заг.скл | D104: =Source!H90 -> шт. | E104: =Source!I90 -> 1 | F104: =Source!AK90 -> 342.75 | H104: =Source!AW91 -> 1 | I104: =Source!O90 -> 342.75 | J104: =IF(Source!BC91<> 0, Source!BC91, 1) -> 9.84 | K104: =Source!O91 -> 3372.66 | Q104: =Source!X90 -> 0 | R104: =Source!X91 -> 0 | S104: =Source!Y90 -> 0 | T104: =Source!Y91 -> 0 | U104: =ROUND((175/100)*ROUND(Source!R90, 2), 2) -> 0 | V104: =ROUND((0/100)*ROUND(Source!R91, 2), 2) -> 0 | AC104: 3
C105: НР от ФОТ | D105: % | E105: =Source!BZ89 -> 109 | I105: =SUM(Q98:Q104) -> 15.34 | J105: =Source!AT89 -> 109 | K105: =SUM(R98:R104) -> 864.21
C106: СП от ФОТ | D106: % | E106: =Source!CA89 -> 61 | I106: =SUM(S98:S105) -> 8.58 | J106: =Source!AU89 -> 61 | K106: =SUM(T98:T105) -> 483.64
C107: ЗТР | D107: чел-ч | E107: =Source!AQ88 -> 74.7 | G107: 1,03*1,15*1,2 | H107: =Source!AV89 -> 1.067 | I107: =Source!U88 -> 1.1329254
C108: ВСЕГО работ по позиции: | H108: =I100+I101+I103+I105+I106+SUM(I104:I104)-SUMIF(AC104:AC104, 5, I104:I104)-SUMIF(AC104:AC104, 6, I104:I104) -> 402.93 | J108: =K100+K101+K103+K105+K106+SUM(K104:K104)-SUMIF(AC104:AC104, 5, K104:K104)-SUMIF(AC104:AC104, 6, K104:K104) -> 5960.45
C109: ВСЕГО оборудование по позиции: | H109: =SUMIF(AC104:AC104, 5, I104:I104)+SUMIF(AC104:AC104, 6, I104:I104) -> 0 | J109: =SUMIF(AC104:AC104, 5, K104:K104)+SUMIF(AC104:AC104, 6, K104:K104) -> 0
C110: ВСЕГО по позиции: | H110: =I100+I101+I103+I105+I106+SUM(I104:I104) -> 402.93 | J110: =K100+K101+K103+K105+K106+SUM(K104:K104) -> 5960.45 | O110: =I100+I101+I103+I105+I106+SUM(I104:I104) -> 402.93 | P110: =K100+K101+K103+K105+K106+SUM(K104:K104) -> 5960.45
...

Sheet Source
A1: 0 | B1: Smeta.RU (495) 974-1589 | D1: _PS_ | F1: 0 | G1: 0 | H1: 0 | I1: Smeta.RU | K1: 1 | L1: 74603 | M1: 10 | N1: 12 | O1: 1 | P1: 0 | Q1: 4
A4: 8 | B4: 1 | C4: -1 | F4: Новый проект | G4: Капитальный ремонт здания Государственного бюджетного общеобразовательного учреждения города Москвы «Школа №1574», расположенного по адресу: г. Москва, Старопименовский переулок, д. 5. 1 этап | EC4: 0
A12: 1 | B12: 699 | C12: 0 | D12: =ROW(A658) -> 658 | E12: 0 | F12: 02-01-06. | I12: 0 | J12: 2024-00375-01-0-ИОС4.1 | K12: 0 | L12: 0 | M12: 4098 | O12: 0 | P12: 0 | Q12: 0 | R12: 0 | S12: 0 | T12: 1 | V12: 2 | BB12: 0 | BH12: Сметные нормы списания | BI12: Коды ОКП для ТСН-2001 МГЭ Дополнение 81 | BJ12: 1 | BK12: 1 | BL12: 0 | BM12: 0 | BN12: 1 | BO12: 0 | BP12: 6 | BQ12: 2 | BR12: 1 | BS12: 1 | BT12: 0 | BU12: 0 | BV12: 0 | BW12: 0 | BX12: 0 | BY12: ТСН-2001 (МГЭ) Доп 81 - Ремонт | BZ12: Типовой расчет для ТСН-2001 МГЭ, Дополнение 81, ремонт | CA12: Территориальные сметные нормативы для Москвы ТСН-2001 (МГЭ), дополнение 81 | CB12: Территориальные сметные нормативы для Москвы ТСН-2001 (МГЭ), дополнение 81 | CC12: Территориальные сметные нормативы для Москвы ТСН-2001 (МГЭ), дополнение 81 | CD12: Территориальные сметные нормативы для Москвы ТСН-2001 (МГЭ), дополнение 81 | CE12: Поправки для ТСН-2001 от 07.04.2026 г. доп.81 | CF12: 0 | CG12: 0 | CH12: 8200 | CK12: 81 | CQ12: Территориальные сметные нормативы для Москвы (ТСН-2001) | CR12: ТЕР | CS12: 41660 | CT12: 1 | CU12: 81 | CY12: 0 | EC12: 0
A15: 15 | B15: 1
A18: 52 | B18: =B658 -> 699 | C18: =C658 -> 1 | D18: =D658 -> 12 | E18: =E658 -> 0 | F18: =F658 -> 02-01-06. | G18: =G658 | O18: =O658 -> 1320813.7 | P18: =P658 -> 1259642.9 | Q18: =Q658 -> 4678.66 | R18: =R658 -> 545.75 | S18: =S658 -> 56492.11 | T18: =T658 -> 0 | U18: =U658 -> 4400.9578 | V18: =V658 -> 0 | ... GX18: =GX658 -> 0
A20: 3 | B20: 1 | D20: =ROW(A625) -> 625 | F20: 02-01-06 | G20: Отопление. | I20: 0 | J20: 2024-00375-01-0-ИОС4.1 | K20: -1 | L20: 02-01-06 | S20: 0 | T20: 0 | V20: 2 | BX20: 0 | CF20: 0 | CG20: 0
A22: 52 | B22: =B625 -> 1 | C22: =C625 -> 3 | D22: =D625 -> 20 | E22: =E625 -> 0 | F22: =F625 -> 02-01-06 | G22: =G625 -> Отопление. | O22: =O625 -> 1320813.7 | P22: =P625 -> 1259642.9 | Q22: =Q625 -> 4678.66 | R22: =R625 -> 545.75 | S22: =S625 -> 56492.11 | T22: =T625 -> 0 | U22: =U625 -> 4400.9578 | V22: =V625 -> 0 | ... GX22: =GX625 -> 0
A24: 4 | B24: 1 | D24: =ROW(A261) -> 261 | F24: Новый раздел | G24: Отопительные приборы. | I24: 0 | K24: 0 | S24: 0 | T24: 0 | V24: 2 | BX24: 0 | CJ24: 0
A26: 52 | B26: =B261 -> 1 | C26: =C261 -> 4 | D26: =D261 -> 24 | E26: =E261 -> 0 | F26: =F261 -> Новый раздел | G26: =G261 -> Отопительные приборы. | O26: =O261 -> 832307.31 | P26: =P261 -> 821022.42 | Q26: =Q261 -> 707.04 | R26: =R261 -> 74.21 | S26: =S261 -> 10577.85 | T26: =T261 -> 0 | U26: =U261 -> 873.42104 | V26: =V261 -> 0 | ... GX26: =GX261 -> 0
A28: 17 | B28: 1 | C28: =ROW(SmtRes!A22) -> 22 | D28: =ROW(EtalonRes!A10) -> 10 | E28: 1 | F28: 3.18-25-1 | G28: Установка радиаторов стальных панельных однорядных с креплением к стене длиной до 1600 мм (вентиль справа) | H28: 100 шт. | I28: =ROUND((1+9+11+13+23+2+10+13+18+6+17+2+8)/100,9) -> 1.33 | J28: 0 | K28: =ROUND((1+9+11+13+23+2+10+13+18+6+17+2+8)/100,9) -> 1.33 | O28: =ROUND(CP28,2) -> 4822.83 | P28: =ROUND((ROUND((AC28*AW28*I28),2)*BC28),2) -> 2764.88 | Q28: =(ROUND((ROUND((((((ET28*1.03)*1.25)*1.2))*AV28*I28),2)*BB28),2)+ROUND((ROUND(((AE28-((((EU28*1.03)*1.25)*1.2)))*AV28*I28),2)*BS28),2)) -> 209.06 | R28: =(ROUND((ROUND((((((EU28*1.03)*1.25)*1.2))*AV28*I28),2)*BS28),2)+ROUND((ROUND(((AE28-((((EU28*1.03)*1.25)*1.2)))*AV28*I28),2)*BS28),2)) -> 22.58 | S28: =ROUND((ROUND((AF28*AV28*I28),2)*BA28),2) -> 1848.89 | T28: =ROUND(CU28*I28,2) -> 0 | U28: =CV28*I28 -> 150.67908 | V28: =CW28*I28 -> 0 | W28: =ROUND(CX28*I28,2) -> 0 | X28: =(ROUND((((S28+ROUND((ROUND((((((EU28*1.03)*1.25)*1.2))*AV28*I28),2)*BS28),2))*AT28)/100),2)+ROUND(((ROUND((ROUND(((AE28-((((EU28*1.03)*1.25)*1.2)))*AV28*I28),2)*BS28),2)*AT28)/100),2)) -> 2039.9 | Y28: =(ROUND((((S28+ROUND((ROUND((((((EU28*1.03)*1.25)*1.2))*AV28*I28),2)*BS28),2))*AU28)/100),2)+ROUND(((ROUND((ROUND(((AE28-((((EU28*1.03)*1.25)*1.2)))*AV28*I28),2)*BS28),2)*AU28)/100),2)) -> 1141.6 | AA28: 86551701 | AB28: =ROUND((AC28+AD28+AF28),6) -> 3529.031 | AC28: =ROUND(((((ES28*1)*1)*1)),6) -> 2078.86 | AD28: =ROUND(((((((ET28*1.03)*1.25)*1.2))-((((EU28*1.03)*1.25)*1.2)))+AE28),6) -> 147.31575 | AE28: =ROUND(((((EU28*1.03)*1.25)*1.2)),6) -> 15.9135 | AF28: =ROUND(((((EV28*1.03)*1.15)*1.2)),6) -> 1302.8552 | AG28: =ROUND((AP28),6) -> 0 | AH28: =((((EW28*1.03)*1.15)*1.2)) -> 106.17858 | AI28: =((((EX28*1.03)*1.25)*1.2)) -> 0 | AJ28: =(AS28) -> 0 | AK28: 3090.81 | AL28: 2078.86 | AM28: 95.35 | AN28: 10.3 | AO28: 916.6 | AP28: 0 | AQ28: 74.7 | AR28: 0 | AS28: 0 | AT28: 109 | AU28: 61 | AV28: 1.067 | AW28: 1 | AZ28: 1 | BA28: 1 | BB28: 1 | BC28: 1 | BH28: 0 | BI28: 1 | BJ28: ТСН-2001.3 Доп. 81, Сб. 18, т. 25, поз. 1 | BM28: 23 | BN28: 0 | BO28: 3.18-25-1 | BP28: 1 | BQ28: 30 | BR28: 0 | BS28: 1 | BT28: 1 | BU28: 1 | BV28: 1 | BW28: 1 | BX28: 1 | BZ28: 109 | CA28: 61 | CE28: 1566 | CF28: 0 | CG28: 0 | CM28: 0 | CN28: Поправка: 3-18. О.П. п.1.8 Наименование: Затраты на тепловое испытание систем отопления с проверкой равномерности прогрева отопительных приборов Поправка: Гл.6.Прил.2.2.п.2.2.6_06.00.01.07.001 Наименование: При выполнении при капитальном ремонте и реконструкции работ, аналогичных технологическим процессам, характерным для нового строительства, и отсутствующих в сборниках на ремонтно-строительные работы ТСН-2001.6 Поправка: Гл.12.Прил.8.п.8. 3_12.00.01.11.001 Наименование: При наличии напряженных и стесненных условий производства работ (стесненность, сложность складирования и транспортной логистики и т.п.) для объектов, расположенных в пределах круговой магистральной системы улиц "Садовое кольцо" города Москвы | CO28: 0 | CP28: =(P28+Q28+S28) -> 4822.83 | CQ28: =ROUND((ROUND((AC28*AW28*1),2)*BC28),2) -> 2078.86 | CR28: =(ROUND((ROUND((((((ET28*1.03)*1.25)*1.2))*AV28*1),2)*BB28),2)+ROUND((ROUND(((AE28-((((EU28*1.03)*1.25)*1.2)))*AV28*1),2)*BS28),2)) -> 157.19 | CS28: =(ROUND((ROUND((((((EU28*1.03)*1.25)*1.2))*AV28*1),2)*BS28),2)+ROUND((ROUND(((AE28-((((EU28*1.03)*1.25)*1.2)))*AV28*1),2)*BS28),2)) -> 16.98 | CT28: =ROUND((ROUND((AF28*AV28*1),2)*BA28),2) -> 1390.15 | CU28: =AG28 -> 0 | CV28: =(AH28*AV28) -> 113.29254 | CW28: =AI28 -> 0 | CX28: =AJ28 -> 0 | CY28: =(ROUND((((S28+ROUND((ROUND((((((EU28*1.03)*1.25)*1.2))*AV28*1),2)*BS28),2))*AT28)/100),2)+ROUND(((ROUND((ROUND(((AE28-((((EU28*1.03)*1.25)*1.2)))*AV28*1),2)*BS28),2)*AT28)/100),2)) -> 2033.8 | CZ28: =(ROUND((((S28+ROUND((ROUND((((((EU28*1.03)*1.25)*1.2))*AV28*1),2)*BS28),2))*AU28)/100),2)+ROUND(((ROUND((ROUND(((AE28-((((EU28*1.03)*1.25)*1.2)))*AV28*1),2)*BS28),2)*AU28)/100),2)) -> 1138.18 | DB28: 1 | DD28: *1)*1)*1 | DE28: *1,03)*1,25)*1,2 | DF28: *1,03)*1,25)*1,2 | DG28: *1,03)*1,15)*1,2 | DI28: *1,03)*1,15)*1,2 | DJ28: *1,03)*1,25)*1,2 | DN28: 0 | DO28: 0 | DP28: 1 | DQ28: 1 | DU28: 1010 | DV28: 100 шт. | DW28: 100 шт. | DX28: 100 | EE28: 85635395 | EF28: 30 | EG28: Строительные работы | EH28: 0 | EJ28: 1 | EK28: 23 | EL28: ТСН-2001.3-18. Отопление - внутренние устройства | EM28: ТСН-2001.3-18-1 | EO28: Поправка: 3-18. О.П. п.1.8 Поправка: Гл.6.Прил.2.2.п.2.2.6_06.00.01.07.001 Поправка: Гл.12.Прил.8.п.8. 3_12.00.01.11.001 | EQ28: 131072 | ER28: 3090.81 | ES28: 2078.86 | ET28: 95.35 | EU28: 10.3 | EV28: 916.6 | EW28: 74.7 | EX28: 0 | EY28: 0 | FQ28: 0 | FR28: 0 | FS28: 0 | FX28: 109 | FY28: 61 | GD28: 1 | GF28: -468095277 | GG28: 2 | GH28: 1 | GI28: 2 | GJ28: 0 | GK28: 0 | GL28: =ROUND(IF(AND(BH28=3,BI28=3,FS28<>0),P28,0),2) -> 0 | GM28: =ROUND(O28+X28+Y28,2)+GX28 -> 8004.33 | GN28: =IF(OR(BI28=0,BI28=1),GM28-GX28,0) -> 8004.33 | GO28: =IF(BI28=2,GM28-GX28,0) -> 0 | GP28: =IF(BI28=4,GM28-GX28,0) -> 0 | GR28: 0 | GS28: 3 | GT28: 0 | GV28: =ROUND((GT28),6) -> 0 | GW28: 1 | GX28: =ROUND(HC28*I28,2) -> 0 | HA28: 0 | HB28: 0 | HC28: =GV28*GW28 -> 0 | HS28: 0 | IK28: 0
A29: 17 | B29: 1 | C29: =ROW(SmtRes!A44) -> 44 | D29: =ROW(EtalonRes!A20) -> 20 | E29: 1 | F29: 3.18-25-1 | G29: Установка радиаторов стальных панельных однорядных с креплением к стене длиной до 1600 мм (вентиль справа) | H29: 100 шт. | I29: =ROUND((1+9+11+13+23+2+10+13+18+6+17+2+8)/100,9) -> 1.33 | J29: 0 | K29: =ROUND((1+9+11+13+23+2+10+13+18+6+17+2+8)/100,9) -> 1.33 | O29: =ROUND(CP29,2) -> 164921.66 | P29: =ROUND((ROUND((AC29*AW29*I29),2)*BC29),2) -> 57592.45 | Q29: =(ROUND((ROUND((((((ET29*1.03)*1.25)*1.2))*AV29*I29),2)*BB29),2)+ROUND((ROUND(((AE29-((((EU29*1.03)*1.25)*1.2)))*AV29*I29),2)*BS29),2)) -> 3144.26 | R29: =(ROUND((ROUND((((((EU29*1.03)*1.25)*1.2))*AV29*I29),2)*BS29),2)+ROUND((ROUND(((AE29-((((EU29*1.03)*1.25)*1.2)))*AV29*I29),2)*BS29),2)) -> 1272.38 | S29: =ROUND((ROUND((AF29*AV29*I29),2)*BA29),2) -> 104184.95 | T29: =ROUND(CU29*I29,2) -> 0 | U29: =CV29*I29 -> 150.67908 | V29: =CW29*I29 -> 0 | W29: =ROUND(CX29*I29,2) -> 0 | X29: =(ROUND((((S29+ROUND((ROUND((((((EU29*1.03)*1.25)*1.2))*AV29*I29),2)*BS29),2))*AT29)/100),2)+ROUND(((ROUND((ROUND(((AE29-((((EU29*1.03)*1.25)*1.2)))*AV29*I29),2)*BS29),2)*AT29)/100),2)) -> 114948.49 | Y29: =(ROUND((((S29+ROUND((ROUND((((((EU29*1.03)*1.25)*1.2))*AV29*I29),2)*BS29),2))*AU29)/100),2)+ROUND(((ROUND((ROUND(((AE29-((((EU29*1.03)*1.25)*1.2)))*AV29*I29),2)*BS29),2)*AU29)/100),2)) -> 64328.97 | AA29: 86551703 | AB29: =ROUND((AC29+AD29+AF29),6) -> 3529.031 | AC29: =ROUND(((((ES29*1)*1)*1)),6) -> 2078.86 | AD29: =ROUND(((((((ET29*1.03)*1.25)*1.2))-((((EU29*1.03)*1.25)*1.2)))+AE29),6) -> 147.31575 | AE29: =ROUND(((((EU29*1.03)*1.25)*1.2)),6) -> 15.9135 | AF29: =ROUND(((((EV29*1.03)*1.15)*1.2)),6) -> 1302.8552 | AG29: =ROUND((AP29),6) -> 0 | AH29: =((((EW29*1.03)*1.15)*1.2)) -> 106.17858 | AI29: =((((EX29*1.03)*1.25)*1.2)) -> 0 | AJ29: =(AS29) -> 0 | AK29: 3090.81 | AL29: 2078.86 | AM29: 95.35 | AN29: 10.3 | AO29: 916.6 | AP29: 0 | AQ29: 74.7 | AR29: 0 | AS29: 0 | AT29: 109 | AU29: 61 | AV29: 1.067 | AW29: 1 | AZ29: 1 | BA29: 56.35 | BB29: 15.04 | BC29: 20.83 | BH29: 0 | BI29: 1 | BJ29: ТСН-2001.3 Доп. 81, Сб. 18, т. 25, поз. 1 | BM29: 23 | BN29: 0 | BO29: 3.18-25-1 | BP29: 1 | BQ29: 30 | BR29: 0 | BS29: 56.35 | BT29: 1 | BU29: 1 | BV29: 1 | BW29: 1 | BX29: 1 | BZ29: 109 | CA29: 61 | CE29: 1566 | CF29: 0 | CG29: 0 | CM29: 0 | CN29: Поправка: 3-18. О.П. п.1.8 Наименование: Затраты на тепловое испытание систем отопления с проверкой равномерности прогрева отопительных приборов Поправка: Гл.6.Прил.2.2.п.2.2.6_06.00.01.07.001 Наименование: При выполнении при капитальном ремонте и реконструкции работ, аналогичных технологическим процессам, характерным для нового строительства, и отсутствующих в сборниках на ремонтно-строительные работы ТСН-2001.6 Поправка: Гл.12.Прил.8.п.8. 3_12.00.01.11.001 Наименование: При наличии напряженных и стесненных условий производства работ (стесненность, сложность складирования и транспортной логистики и т.п.) для объектов, расположенных в пределах круговой магистральной системы улиц "Садовое кольцо" города Москвы | CO29: 0 | CP29: =(P29+Q29+S29) -> 164921.66 | CQ29: =ROUND((ROUND((AC29*AW29*1),2)*BC29),2) -> 43302.65 | CR29: =(ROUND((ROUND((((((ET29*1.03)*1.25)*1.2))*AV29*1),2)*BB29),2)+ROUND((ROUND(((AE29-((((EU29*1.03)*1.25)*1.2)))*AV29*1),2)*BS29),2)) -> 2364.14 | CS29: =(ROUND((ROUND((((((EU29*1.03)*1.25)*1.2))*AV29*1),2)*BS29),2)+ROUND((ROUND(((AE29-((((EU29*1.03)*1.25)*1.2)))*AV29*1),2)*BS29),2)) -> 956.82 | CT29: =ROUND((ROUND((AF29*AV29*1),2)*BA29),2) -> 78334.95 | CU29: =AG29 -> 0 | CV29: =(AH29*AV29) -> 113.29254 | CW29: =AI29 -> 0 | CX29: =AJ29 -> 0 | CY29: =(ROUND((((S29+ROUND((ROUND((((((EU29*1.03)*1.25)*1.2))*AV29*1),2)*BS29),2))*AT29)/100),2)+ROUND(((ROUND((ROUND(((AE29-((((EU29*1.03)*1.25)*1.2)))*AV29*1),2)*BS29),2)*AT29)/100),2)) -> 114604.53 | CZ29: =(ROUND((((S29+ROUND((ROUND((((((EU29*1.03)*1.25)*1.2))*AV29*1),2)*BS29),2))*AU29)/100),2)+ROUND(((ROUND((ROUND(((AE29-((((EU29*1.03)*1.25)*1.2)))*AV29*1),2)*BS29),2)*AU29)/100),2)) -> 64136.48 | DB29: 4 | DD29: *1)*1)*1 | DE29: *1,03)*1,25)*1,2 | DF29: *1,03)*1,25)*1,2 | DG29: *1,03)*1,15)*1,2 | DI29: *1,03)*1,15)*1,2 | DJ29: *1,03)*1,25)*1,2 | DN29: 0 | DO29: 0 | DP29: 1 | DQ29: 1 | DU29: 1010 | DV29: 100 шт. | DW29: 100 шт. | DX29: 100 | EE29: 85635395 | EF29: 30 | EG29: Строительные работы | EH29: 0 | EJ29: 1 | EK29: 23 | EL29: ТСН-2001.3-18. Отопление - внутренние устройства | EM29: ТСН-2001.3-18-1 | EO29: Поправка: 3-18. О.П. п.1.8 Поправка: Гл.6.Прил.2.2.п.2.2.6_06.00.01.07.001 Поправка: Гл.12.Прил.8.п.8. 3_12.00.01.11.001 | EQ29: 131072 | ER29: 3090.81 | ES29: 2078.86 | ET29: 95.35 | EU29: 10.3 | EV29: 916.6 | EW29: 74.7 | EX29: 0 | EY29: 0 | FQ29: 0 | FR29: 0 | FS29: 0 | FX29: 109 | FY29: 61 | GD29: 1 | GF29: -468095277 | GG29: 2 | GH29: 1 | GI29: 2 | GJ29: 0 | GK29: 0 | GL29: =ROUND(IF(AND(BH29=3,BI29=3,FS29<>0),P29,0),2) -> 0 | GM29: =ROUND(O29+X29+Y29,2)+GX29 -> 344199.12 | GN29: =IF(OR(BI29=0,BI29=1),GM29-GX29,0) -> 344199.12 | GO29: =IF(BI29=2,GM29-GX29,0) -> 0 | GP29: =IF(BI29=4,GM29-GX29,0) -> 0 | GR29: 0 | GS29: 3 | GT29: 0 | GV29: =ROUND((GT29),6) -> 0 | GW29: 1 | GX29: =ROUND(HC29*I29,2) -> 0 | HA29: 0 | HB29: 0 | HC29: =GV29*GW29 -> 0 | HS29: 0 | IK29: 0
A30: 18 | B30: 1 | C30: 10 | E30: 1,1 | F30: КА. п. 1 | G30: Сmальной nанельный paguamop PRADO Classic, mun 20, Bыcoma Н = 500 мм, PRADO Classic-20-500-400 | H30: шт. | I30: =I28*J30 -> 1 | J30: 0.7518797 | K30: 0.75188 | O30: =ROUND(CP30,2) -> 373.26 | P30: =ROUND((ROUND((AC30*AW30*I30),2)*BC30),2) -> 373.26 | Q30: =(ROUND((ROUND(((ET30)*AV30*I30),2)*BB30),2)+ROUND((ROUND(((AE30-(EU30))*AV30*I30),2)*BS30),2)) -> 0 | R30: =(ROUND((ROUND(((EU30)*AV30*I30),2)*BS30),2)+ROUND((ROUND(((AE30-(EU30))*AV30*I30),2)*BS30),2)) -> 0 | S30: =ROUND((ROUND((AF30*AV30*I30),2)*BA30),2) -> 0 | T30: =ROUND(CU30*I30,2) -> 0 | U30: =CV30*I30 -> 0 | V30: =CW30*I30 -> 0 | W30: =ROUND(CX30*I30,2) -> 0 | X30: =(ROUND((((S30+ROUND((ROUND(((EU30)*AV30*I30),2)*BS30),2))*AT30)/100),2)+ROUND(((ROUND((ROUND(((AE30-(EU30))*AV30*I30),2)*BS30),2)*AT30)/100),2)) -> 0 | Y30: =(ROUND((((S30+ROUND((ROUND(((EU30)*AV30*I30),2)*BS30),2))*AU30)/100),2)+ROUND(((ROUND((ROUND(((AE30-(EU30))*AV30*I30),2)*BS30),2)*AU30)/100),2)) -> 0 | AA30: 86551701 | AB30: =ROUND((AC30+AD30+AF30),6) -> 373.26 | AC30: =ROUND((ES30),6) -> 373.26 | AD30: =ROUND((((ET30)-(EU30))+AE30),6) -> 0 | AE30: =ROUND((EU30),6) -> 0 | AF30: =ROUND((EV30),6) -> 0 | AG30: =ROUND((AP30),6) -> 0 | AH30: =(EW30) -> 0 | AI30: =(EX30) -> 0 | AJ30: =(AS30) -> 0 | AK30: 373.26 | AL30: 373.26 | AM30: 0 | AN30: 0 | AO30: 0 | AP30: 0 | AQ30: 0 | AR30: 0 | AS30: 0 | AT30: 109 | AU30: 61 | AV30: 1 | AW30: 1 | AZ30: 1 | BA30: 1 | BB30: 1 | BC30: 1 | BH30: 3 | BI30: 1 | BM30: 23 | BN30: 0 | BP30: 0 | BQ30: 30 | BR30: 0 | BS30: 1 | BT30: 1 | BU30: 1 | BV30: 1 | BW30: 1 | BX30: 1 | BZ30: 109 | CA30: 61 | CE30: 1566 | CF30: 0 | CG30: 0 | CM30: 0 | CO30: 0 | CP30: =(P30+Q30+S30) -> 373.26 | CQ30: =ROUND((ROUND((AC30*AW30*1),2)*BC30),2) -> 373.26 | CR30: =(ROUND((ROUND(((ET30)*AV30*1),2)*BB30),2)+ROUND((ROUND(((AE30-(EU30))*AV30*1),2)*BS30),2)) -> 0 | CS30: =(ROUND((ROUND(((EU30)*AV30*1),2)*BS30),2)+ROUND((ROUND(((AE30-(EU30))*AV30*1),2)*BS30),2)) -> 0 | CT30: =ROUND((ROUND((AF30*AV30*1),2)*BA30),2) -> 0 | CU30: =AG30 -> 0 | CV30: =(AH30*AV30) -> 0 | CW30: =AI30 -> 0 | CX30: =AJ30 -> 0 | CY30: =(ROUND((((S30+ROUND((ROUND(((EU30)*AV30*1),2)*BS30),2))*AT30)/100),2)+ROUND(((ROUND((ROUND(((AE30-(EU30))*AV30*1),2)*BS30),2)*AT30)/100),2)) -> 0 | CZ30: =(ROUND((((S30+ROUND((ROUND(((EU30)*AV30*1),2)*BS30),2))*AU30)/100),2)+ROUND(((ROUND((ROUND(((AE30-(EU30))*AV30*1),2)*BS30),2)*AU30)/100),2)) -> 0 | DN30: 0 | DO30: 0 | DP30: 1 | DQ30: 1 | DU30: 1010 | DV30: шт. | DW30: шт. | DX30: 1 | EE30: 85635395 | EF30: 30 | EG30: Строительные работы | EH30: 0 | EJ30: 1 | EK30: 23 | EL30: ТСН-2001.3-18. Отопление - внутренние устройства | EM30: ТСН-2001.3-18-1 | EQ30: 0 | ER30: 0 | ES30: 373.26 | ET30: 0 | EU30: 0 | EV30: 0 | EW30: 0 | EX30: 0 | FQ30: 0 | FR30: 0 | FS30: 0 | FX30: 109 | FY30: 61 | GA30: [4 393 / 1,22 / 9,84] + 2% Заг.скл | GD30: 1 | GF30: 2083950908 | GG30: 2 | GH30: 4 | GI30: -2 | GJ30: 0 | GK30: 0 | GL30: =ROUND(IF(AND(BH30=3,BI30=3,FS30<>0),P30,0),2) -> 0 | GM30: =ROUND(O30+X30+Y30,2)+GX30 -> 373.26 | GN30: =IF(OR(BI30=0,BI30=1),GM30-GX30,0) -> 373.26 | GO30: =IF(BI30=2,GM30-GX30,0) -> 0 | GP30: =IF(BI30=4,GM30-GX30,0) -> 0 | GR30: 0 | GS30: 2 | GT30: 0 | GV30: =ROUND((GT30),6) -> 0 | GW30: 1 | GX30: =ROUND(HC30*I30,2) -> 0 | HA30: 0 | HB30: 0 | HC30: =GV30*GW30 -> 0 | HE30: 0 | HF30: 2 | HS30: 0 | IK30: 0
A31: 18 | B31: 1 | C31: 32 | E31: 1,1 | F31: КА. п. 1 | G31: Сmальной nанельный paguamop PRADO Classic, mun 20, Bыcoma Н = 500 мм, PRADO Classic-20-500-400 | H31: шт. | I31: =I29*J31 -> 1 | J31: 0.7518797 | K31: 0.75188 | O31: =ROUND(CP31,2) -> 3672.88 | P31: =ROUND((ROUND((AC31*AW31*I31),2)*BC31),2) -> 3672.88 | Q31: =(ROUND((ROUND(((ET31)*AV31*I31),2)*BB31),2)+ROUND((ROUND(((AE31-(EU31))*AV31*I31),2)*BS31),2)) -> 0 | R31: =(ROUND((ROUND(((EU31)*AV31*I31),2)*BS31),2)+ROUND((ROUND(((AE31-(EU31))*AV31*I31),2)*BS31),2)) -> 0 | S31: =ROUND((ROUND((AF31*AV31*I31),2)*BA31),2) -> 0 | T31: =ROUND(CU31*I31,2) -> 0 | U31: =CV31*I31 -> 0 | V31: =CW31*I31 -> 0 | W31: =ROUND(CX31*I31,2) -> 0 | X31: =(ROUND((((S31+ROUND((ROUND(((EU31)*AV31*I31),2)*BS31),2))*AT31)/100),2)+ROUND(((ROUND((ROUND(((AE31-(EU31))*AV31*I31),2)*BS31),2)*AT31)/100),2)) -> 0 | Y31: =(ROUND((((S31+ROUND((ROUND(((EU31)*AV31*I31),2)*BS31),2))*AU31)/100),2)+ROUND(((ROUND((ROUND(((AE31-(EU31))*AV31*I31),2)*BS31),2)*AU31)/100),2)) -> 0 | AA31: 86551703 | AB31: =ROUND((AC31+AD31+AF31),6) -> 373.26 | AC31: =ROUND((ES31),6) -> 373.26 | AD31: =ROUND((((ET31)-(EU31))+AE31),6) -> 0 | AE31: =ROUND((EU31),6) -> 0 | AF31: =ROUND((EV31),6) -> 0 | AG31: =ROUND((AP31),6) -> 0 | AH31: =(EW31) -> 0 | AI31: =(EX31) -> 0 | AJ31: =(AS31) -> 0 | AK31: 373.26 | AL31: 373.26 | AM31: 0 | AN31: 0 | AO31: 0 | AP31: 0 | AQ31: 0 | AR31: 0 | AS31: 0 | AT31: 109 | AU31: 61 | AV31: 1 | AW31: 1 | AZ31: 1 | BA31: 1 | BB31: 1 | BC31: 9.84 | BH31: 3 | BI31: 1 | BM31: 23 | BN31: 0 | BP31: 0 | BQ31: 30 | BR31: 0 | BS31: 1 | BT31: 1 | BU31: 1 | BV31: 1 | BW31: 1 | BX31: 1 | BZ31: 109 | CA31: 61 | CE31: 1566 | CF31: 0 | CG31: 0 | CM31: 0 | CO31: 0 | CP31: =(P31+Q31+S31) -> 3672.88 | CQ31: =ROUND((ROUND((AC31*AW31*1),2)*BC31),2) -> 3672.88 | CR31: =(ROUND((ROUND(((ET31)*AV31*1),2)*BB31),2)+ROUND((ROUND(((AE31-(EU31))*AV31*1),2)*BS31),2)) -> 0 | CS31: =(ROUND((ROUND(((EU31)*AV31*1),2)*BS31),2)+ROUND((ROUND(((AE31-(EU31))*AV31*1),2)*BS31),2)) -> 0 | CT31: =ROUND((ROUND((AF31*AV31*1),2)*BA31),2) -> 0 | CU31: =AG31 -> 0 | CV31: =(AH31*AV31) -> 0 | CW31: =AI31 -> 0 | CX31: =AJ31 -> 0 | CY31: =(ROUND((((S31+ROUND((ROUND(((EU31)*AV31*1),2)*BS31),2))*AT31)/100),2)+ROUND(((ROUND((ROUND(((AE31-(EU31))*AV31*1),2)*BS31),2)*AT31)/100),2)) -> 0 | CZ31: =(ROUND((((S31+ROUND((ROUND(((EU31)*AV31*1),2)*BS31),2))*AU31)/100),2)+ROUND(((ROUND((ROUND(((AE31-(EU31))*AV31*1),2)*BS31),2)*AU31)/100),2)) -> 0 | DN31: 0 | DO31: 0 | DP31: 1 | DQ31: 1 | DU31: 1010 | DV31: шт. | DW31: шт. | DX31: 1 | EE31: 85635395 | EF31: 30 | EG31: Строительные работы | EH31: 0 | EJ31: 1 | EK31: 23 | EL31: ТСН-2001.3-18. Отопление - внутренние устройства | EM31: ТСН-2001.3-18-1 | EQ31: 0 | ER31: 373.26 | ES31: 373.26 | ET31: 0 | EU31: 0 | EV31: 0 | EW31: 0 | EX31: 0 | EZ31: 5 | FC31: 1 | FD31: 18 | FF31: 4393 | FQ31: 0 | FR31: 0 | FS31: 0 | FX31: 109 | FY31: 61 | GA31: [4 393 / 1,22 / 9,84] + 2% Заг.скл | GD31: 1 | GF31: 2083950908 | GG31: 2 | GH31: 3 | GI31: 5 | GJ31: 0 | GK31: 0 | GL31: =ROUND(IF(AND(BH31=3,BI31=3,FS31<>0),P31,0),2) -> 0 | GM31: =ROUND(O31+X31+Y31,2)+GX31 -> 3672.88 | GN31: =IF(OR(BI31=0,BI31=1),GM31-GX31,0) -> 3672.88 | GO31: =IF(BI31=2,GM31-GX31,0) -> 0 | GP31: =IF(BI31=4,GM31-GX31,0) -> 0 | GR31: 1 | GS31: 1 | GT31: 0 | GV31: =ROUND((GT31),6) -> 0 | GW31: 1 | GX31: =ROUND(HC31*I31,2) -> 0 | HA31: 0 | HB31: 0 | HC31: =GV31*GW31 -> 0 | HE31: 0 | HF31: 2 | HS31: 0 | IK31: 0
A32: 18 | B32: 1 | C32: 15 | E32: 1,2 | F32: КА. п. 2 | G32: Сmальной nанельный paguamop PRADO Classic, mun 20, Bыcoma Н = 500 мм, PRADO Classic-20-500-500 | I32: =I28*J32 -> 9 | J32: 6.7669173 | K32: 6.766917 | O32: =ROUND(CP32,2) -> 3887.73 | P32: =ROUND((ROUND((AC32*AW32*I32),2)*BC32),2) -> 3887.73 | Q32: =(ROUND((ROUND(((ET32)*AV32*I32),2)*BB32),2)+ROUND((ROUND(((AE32-(EU32))*AV32*I32),2)*BS32),2)) -> 0 | R32: =(ROUND((ROUND(((EU32)*AV32*I32),2)*BS32),2)+ROUND((ROUND(((AE32-(EU32))*AV32*I32),2)*BS32),2)) -> 0 | S32: =ROUND((ROUND((AF32*AV32*I32),2)*BA32),2) -> 0 | T32: =ROUND(CU32*I32,2) -> 0 | U32: =CV32*I32 -> 0 | V32: =CW32*I32 -> 0 | W32: =ROUND(CX32*I32,2) -> 0 | X32: =(ROUND((((S32+ROUND((ROUND(((EU32)*AV32*I32),2)*BS32),2))*AT32)/100),2)+ROUND(((ROUND((ROUND(((AE32-(EU32))*AV32*I32),2)*BS32),2)*AT32)/100),2)) -> 0 | Y32: =(ROUND((((S32+ROUND((ROUND(((EU32)*AV32*I32),2)*BS32),2))*AU32)/100),2)+ROUND(((ROUND((ROUND(((AE32-(EU32))*AV32*I32),2)*BS32),2)*AU32)/100),2)) -> 0 | AA32: 86551701 | AB32: =ROUND((AC32+AD32+AF32),6) -> 431.97 | AC32: =ROUND((ES32),6) -> 431.97 | AD32: =ROUND((((ET32)-(EU32))+AE32),6) -> 0 | AE32: =ROUND((EU32),6) -> 0 | AF32: =ROUND((EV32),6) -> 0 | AG32: =ROUND((AP32),6) -> 0 | AH32: =(EW32) -> 0 | AI32: =(EX32) -> 0 | AJ32: =(AS32) -> 0 | AK32: 431.97 | AL32: 431.97 | AM32: 0 | AN32: 0 | AO32: 0 | AP32: 0 | AQ32: 0 | AR32: 0 | AS32: 0 | AT32: 109 | AU32: 61 | AV32: 1 | AW32: 1 | AZ32: 1 | BA32: 1 | BB32: 1 | BC32: 1 | BH32: 3 | BI32: 1 | BM32: 23 | BN32: 0 | BP32: 0 | BQ32: 30 | BR32: 0 | BS32: 1 | BT32: 1 | BU32: 1 | BV32: 1 | BW32: 1 | BX32: 1 | BZ32: 109 | CA32: 61 | CE32: 1566 | CF32: 0 | CG32: 0 | CM32: 0 | CO32: 0 | CP32: =(P32+Q32+S32) -> 3887.73 | CQ32: =ROUND((ROUND((AC32*AW32*1),2)*BC32),2) -> 431.97 | CR32: =(ROUND((ROUND(((ET32)*AV32*1),2)*BB32),2)+ROUND((ROUND(((AE32-(EU32))*AV32*1),2)*BS32),2)) -> 0 | CS32: =(ROUND((ROUND(((EU32)*AV32*1),2)*BS32),2)+ROUND((ROUND(((AE32-(EU32))*AV32*1),2)*BS32),2)) -> 0 | CT32: =ROUND((ROUND((AF32*AV32*1),2)*BA32),2) -> 0 | CU32: =AG32 -> 0 | CV32: =(AH32*AV32) -> 0 | CW32: =AI32 -> 0 | CX32: =AJ32 -> 0 | CY32: =(ROUND((((S32+ROUND((ROUND(((EU32)*AV32*1),2)*BS32),2))*AT32)/100),2)+ROUND(((ROUND((ROUND(((AE32-(EU32))*AV32*1),2)*BS32),2)*AT32)/100),2)) -> 0 | CZ32: =(ROUND((((S32+ROUND((ROUND(((EU32)*AV32*1),2)*BS32),2))*AU32)/100),2)+ROUND(((ROUND((ROUND(((AE32-(EU32))*AV32*1),2)*BS32),2)*AU32)/100),2)) -> 0 | DN32: 0 | DO32: 0 | DP32: 1 | DQ32: 1 | EE32: 85635395 | EF32: 30 | EG32: Строительные работы | EH32: 0 | EJ32: 1 | EK32: 23 | EL32: ТСН-2001.3-18. Отопление - внутренние устройства | EM32: ТСН-2001.3-18-1 | EQ32: 0 | ER32: 0 | ES32: 431.97 | ET32: 0 | EU32: 0 | EV32: 0 | EW32: 0 | EX32: 0 | FQ32: 0 | FR32: 0 | FS32: 0 | FX32: 109 | FY32: 61 | GA32: [5 084 / 1,22 / 9,84] + 2% Заг.скл | GD32: 1 | GF32: -401967197 | GG32: 2 | GH32: 4 | GI32: -2 | GJ32: 0 | GK32: 0 | GL32: =ROUND(IF(AND(BH32=3,BI32=3,FS32<>0),P32,0),2) -> 0 | GM32: =ROUND(O32+X32+Y32,2)+GX32 -> 3887.73 | GN32: =IF(OR(BI32=0,BI32=1),GM32-GX32,0) -> 3887.73 | GO32: =IF(BI32=2,GM32-GX32,0) -> 0 | GP32: =IF(BI32=4,GM32-GX32,0) -> 0 | GR32: 0 | GS32: 2 | GT32: 0 | GV32: =ROUND((GT32),6) -> 0 | GW32: 1 | GX32: =ROUND(HC32*I32,2) -> 0 | HA32: 0 | HB32: 0 | HC32: =GV32*GW32 -> 0 | HE32: 0 | HF32: 2 | HS32: 0 | IK32: 0
A33: 18 | B33: 1 | C33: 37 | E33: 1,2 | F33: КА. п. 2 | G33: Сmальной nанельный paguamop PRADO Classic, mun 20, Bыcoma Н = 500 мм, PRADO Classic-20-500-500 | I33: =I29*J33 -> 9 | J33: 6.7669173 | K33: 6.766917 | O33: =ROUND(CP33,2) -> 38255.26 | P33: =ROUND((ROUND((AC33*AW33*I33),2)*BC33),2) -> 38255.26 | Q33: =(ROUND((ROUND(((ET33)*AV33*I33),2)*BB33),2)+ROUND((ROUND(((AE33-(EU33))*AV33*I33),2)*BS33),2)) -> 0 | R33: =(ROUND((ROUND(((EU33)*AV33*I33),2)*BS33),2)+ROUND((ROUND(((AE33-(EU33))*AV33*I33),2)*BS33),2)) -> 0 | S33: =ROUND((ROUND((AF33*AV33*I33),2)*BA33),2) -> 0 | T33: =ROUND(CU33*I33,2) -> 0 | U33: =CV33*I33 -> 0 | V33: =CW33*I33 -> 0 | W33: =ROUND(CX33*I33,2) -> 0 | X33: =(ROUND((((S33+ROUND((ROUND(((EU33)*AV33*I33),2)*BS33),2))*AT33)/100),2)+ROUND(((ROUND((ROUND(((AE33-(EU33))*AV33*I33),2)*BS33),2)*AT33)/100),2)) -> 0 | Y33: =(ROUND((((S33+ROUND((ROUND(((EU33)*AV33*I33),2)*BS33),2))*AU33)/100),2)+ROUND(((ROUND((ROUND(((AE33-(EU33))*AV33*I33),2)*BS33),2)*AU33)/100),2)) -> 0 | AA33: 86551703 | AB33: =ROUND((AC33+AD33+AF33),6) -> 431.97 | AC33: =ROUND((ES33),6) -> 431.97 | AD33: =ROUND((((ET33)-(EU33))+AE33),6) -> 0 | AE33: =ROUND((EU33),6) -> 0 | AF33: =ROUND((EV33),6) -> 0 | AG33: =ROUND((AP33),6) -> 0 | AH33: =(EW33) -> 0 | AI33: =(EX33) -> 0 | AJ33: =(AS33) -> 0 | AK33: 431.97 | AL33: 431.97 | AM33: 0 | AN33: 0 | AO33: 0 | AP33: 0 | AQ33: 0 | AR33: 0 | AS33: 0 | AT33: 109 | AU33: 61 | AV33: 1 | AW33: 1 | AZ33: 1 | BA33: 1 | BB33: 1 | BC33: 9.84 | BH33: 3 | BI33: 1 | BM33: 23 | BN33: 0 | BP33: 0 | BQ33: 30 | BR33: 0 | BS33: 1 | BT33: 1 | BU33: 1 | BV33: 1 | BW33: 1 | BX33: 1 | BZ33: 109 | CA33: 61 | CE33: 1566 | CF33: 0 | CG33: 0 | CM33: 0 | CO33: 0 | CP33: =(P33+Q33+S33) -> 38255.26 | CQ33: =ROUND((ROUND((AC33*AW33*1),2)*BC33),2) -> 4250.58 | CR33: =(ROUND((ROUND(((ET33)*AV33*1),2)*BB33),2)+ROUND((ROUND(((AE33-(EU33))*AV33*1),2)*BS33),2)) -> 0 | CS33: =(ROUND((ROUND(((EU33)*AV33*1),2)*BS33),2)+ROUND((ROUND(((AE33-(EU33))*AV33*1),2)*BS33),2)) -> 0 | CT33: =ROUND((ROUND((AF33*AV33*1),2)*BA33),2) -> 0 | CU33: =AG33 -> 0 | CV33: =(AH33*AV33) -> 0 | CW33: =AI33 -> 0 | CX33: =AJ33 -> 0 | CY33: =(ROUND((((S33+ROUND((ROUND(((EU33)*AV33*1),2)*BS33),2))*AT33)/100),2)+ROUND(((ROUND((ROUND(((AE33-(EU33))*AV33*1),2)*BS33),2)*AT33)/100),2)) -> 0 | CZ33: =(ROUND((((S33+ROUND((ROUND(((EU33)*AV33*1),2)*BS33),2))*AU33)/100),2)+ROUND(((ROUND((ROUND(((AE33-(EU33))*AV33*1),2)*BS33),2)*AU33)/100),2)) -> 0 | DN33: 0 | DO33: 0 | DP33: 1 | DQ33: 1 | EE33: 85635395 | EF33: 30 | EG33: Строительные работы | EH33: 0 | EJ33: 1 | EK33: 23 | EL33: ТСН-2001.3-18. Отопление - внутренние устройства | EM33: ТСН-2001.3-18-1 | EQ33: 0 | ER33: 431.97 | ES33: 431.97 | ET33: 0 | EU33: 0 | EV33: 0 | EW33: 0 | EX33: 0 | EZ33: 5 | FC33: 1 | FD33: 18 | FF33: 5084 | FQ33: 0 | FR33: 0 | FS33: 0 | FX33: 109 | FY33: 61 | GA33: [5 084 / 1,22 / 9,84] + 2% Заг.скл | GD33: 1 | GF33: -401967197 | GG33: 2 | GH33: 3 | GI33: 5 | GJ33: 0 | GK33: 0 | GL33: =ROUND(IF(AND(BH33=3,BI33=3,FS33<>0),P33,0),2) -> 0 | GM33: =ROUND(O33+X33+Y33,2)+GX33 -> 38255.26 | GN33: =IF(OR(BI33=0,BI33=1),GM33-GX33,0) -> 38255.26 | GO33: =IF(BI33=2,GM33-GX33,0) -> 0 | GP33: =IF(BI33=4,GM33-GX33,0) -> 0 | GR33: 1 | GS33: 1 | GT33: 0 | GV33: =ROUND((GT33),6) -> 0 | GW33: 1 | GX33: =ROUND(HC33*I33,2) -> 0 | HA33: 0 | HB33: 0 | HC33: =GV33*GW33 -> 0 | HE33: 0 | HF33: 2 | HS33: 0 | IK33: 0
A34: 18 | B34: 1 | C34: 16 | E34: 1,3 | F34: КА. п. 3 | G34: Сmальной nанельный paguamop PRADO Classic, mun 20, Bыcoma Н = 500 мм, PRADO Classic-20-500-600 | I34: =I28*J34 -> 11 | J34: 8.2706767 | K34: 8.270677 | O34: =ROUND(CP34,2) -> 5436.75 | P34: =ROUND((ROUND((AC34*AW34*I34),2)*BC34),2) -> 5436.75 | Q34: =(ROUND((ROUND(((ET34)*AV34*I34),2)*BB34),2)+ROUND((ROUND(((AE34-(EU34))*AV34*I34),2)*BS34),2)) -> 0 | R34: =(ROUND((ROUND(((EU34)*AV34*I34),2)*BS34),2)+ROUND((ROUND(((AE34-(EU34))*AV34*I34),2)*BS34),2)) -> 0 | S34: =ROUND((ROUND((AF34*AV34*I34),2)*BA34),2) -> 0 | T34: =ROUND(CU34*I34,2) -> 0 | U34: =CV34*I34 -> 0 | V34: =CW34*I34 -> 0 | W34: =ROUND(CX34*I34,2) -> 0 | X34: =(ROUND((((S34+ROUND((ROUND(((EU34)*AV34*I34),2)*BS34),2))*AT34)/100),2)+ROUND(((ROUND((ROUND(((AE34-(EU34))*AV34*I34),2)*BS34),2)*AT34)/100),2)) -> 0 | Y34: =(ROUND((((S34+ROUND((ROUND(((EU34)*AV34*I34),2)*BS34),2))*AU34)/100),2)+ROUND(((ROUND((ROUND(((AE34-(EU34))*AV34*I34),2)*BS34),2)*AU34)/100),2)) -> 0 | AA34: 86551701 | AB34: =ROUND((AC34+AD34+AF34),6) -> 494.25 | AC34: =ROUND((ES34),6) -> 494.25 | AD34: =ROUND((((ET34)-(EU34))+AE34),6) -> 0 | AE34: =ROUND((EU34),6) -> 0 | AF34: =ROUND((EV34),6) -> 0 | AG34: =ROUND((AP34),6) -> 0 | AH34: =(EW34) -> 0 | AI34: =(EX34) -> 0 | AJ34: =(AS34) -> 0 | AK34: 494.25 | AL34: 494.25 | AM34: 0 | AN34: 0 | AO34: 0 | AP34: 0 | AQ34: 0 | AR34: 0 | AS34: 0 | AT34: 109 | AU34: 61 | AV34: 1 | AW34: 1 | AZ34: 1 | BA34: 1 | BB34: 1 | BC34: 1 | BH34: 3 | BI34: 1 | BM34: 23 | BN34: 0 | BP34: 0 | BQ34: 30 | BR34: 0 | BS34: 1 | BT34: 1 | BU34: 1 | BV34: 1 | BW34: 1 | BX34: 1 | BZ34: 109 | CA34: 61 | CE34: 1566 | CF34: 0 | CG34: 0 | CM34: 0 | CO34: 0 | CP34: =(P34+Q34+S34) -> 5436.75 | CQ34: =ROUND((ROUND((AC34*AW34*1),2)*BC34),2) -> 494.25 | CR34: =(ROUND((ROUND(((ET34)*AV34*1),2)*BB34),2)+ROUND((ROUND(((AE34-(EU34))*AV34*1),2)*BS34),2)) -> 0 | CS34: =(ROUND((ROUND(((EU34)*AV34*1),2)*BS34),2)+ROUND((ROUND(((AE34-(EU34))*AV34*1),2)*BS34),2)) -> 0 | CT34: =ROUND((ROUND((AF34*AV34*1),2)*BA34),2) -> 0 | CU34: =AG34 -> 0 | CV34: =(AH34*AV34) -> 0 | CW34: =AI34 -> 0 | CX34: =AJ34 -> 0 | CY34: =(ROUND((((S34+ROUND((ROUND(((EU34)*AV34*1),2)*BS34),2))*AT34)/100),2)+ROUND(((ROUND((ROUND(((AE34-(EU34))*AV34*1),2)*BS34),2)*AT34)/100),2)) -> 0 | CZ34: =(ROUND((((S34+ROUND((ROUND(((EU34)*AV34*1),2)*BS34),2))*AU34)/100),2)+ROUND(((ROUND((ROUND(((AE34-(EU34))*AV34*1),2)*BS34),2)*AU34)/100),2)) -> 0 | DN34: 0 | DO34: 0 | DP34: 1 | DQ34: 1 | EE34: 85635395 | EF34: 30 | EG34: Строительные работы | EH34: 0 | EJ34: 1 | EK34: 23 | EL34: ТСН-2001.3-18. Отопление - внутренние устройства | EM34: ТСН-2001.3-18-1 | EQ34: 0 | ER34: 0 | ES34: 494.25 | ET34: 0 | EU34: 0 | EV34: 0 | EW34: 0 | EX34: 0 | FQ34: 0 | FR34: 0 | FS34: 0 | FX34: 109 | FY34: 61 | GA34: [5 817 / 1,22 / 9,84] + 2% Заг.скл | GD34: 1 | GF34: 1290624388 | GG34: 2 | GH34: 4 | GI34: -2 | GJ34: 0 | GK34: 0 | GL34: =ROUND(IF(AND(BH34=3,BI34=3,FS34<>0),P34,0),2) -> 0 | GM34: =ROUND(O34+X34+Y34,2)+GX34 -> 5436.75 | GN34: =IF(OR(BI34=0,BI34=1),GM34-GX34,0) -> 5436.75 | GO34: =IF(BI34=2,GM34-GX34,0) -> 0 | GP34: =IF(BI34=4,GM34-GX34,0) -> 0 | GR34: 0 | GS34: 2 | GT34: 0 | GV34: =ROUND((GT34),6) -> 0 | GW34: 1 | GX34: =ROUND(HC34*I34,2) -> 0 | HA34: 0 | HB34: 0 | HC34: =GV34*GW34 -> 0 | HE34: 0 | HF34: 2 | HS34: 0 | IK34: 0
A35: 18 | B35: 1 | C35: 38 | E35: 1,3 | F35: КА. п. 3 | G35: Сmальной nанельный paguamop PRADO Classic, mun 20, Bыcoma Н = 500 мм, PRADO Classic-20-500-600 | I35: =I29*J35 -> 11 | J35: 8.2706767 | K35: 8.270677 | O35: =ROUND(CP35,2) -> 53497.62 | P35: =ROUND((ROUND((AC35*AW35*I35),2)*BC35),2) -> 53497.62 | Q35: =(ROUND((ROUND(((ET35)*AV35*I35),2)*BB35),2)+ROUND((ROUND(((AE35-(EU35))*AV35*I35),2)*BS35),2)) -> 0 | R35: =(ROUND((ROUND(((EU35)*AV35*I35),2)*BS35),2)+ROUND((ROUND(((AE35-(EU35))*AV35*I35),2)*BS35),2)) -> 0 | S35: =ROUND((ROUND((AF35*AV35*I35),2)*BA35),2) -> 0 | T35: =ROUND(CU35*I35,2) -> 0 | U35: =CV35*I35 -> 0 | V35: =CW35*I35 -> 0 | W35: =ROUND(CX35*I35,2) -> 0 | X35: =(ROUND((((S35+ROUND((ROUND(((EU35)*AV35*I35),2)*BS35),2))*AT35)/100),2)+ROUND(((ROUND((ROUND(((AE35-(EU35))*AV35*I35),2)*BS35),2)*AT35)/100),2)) -> 0 | Y35: =(ROUND((((S35+ROUND((ROUND(((EU35)*AV35*I35),2)*BS35),2))*AU35)/100),2)+ROUND(((ROUND((ROUND(((AE35-(EU35))*AV35*I35),2)*BS35),2)*AU35)/100),2)) -> 0 | AA35: 86551703 | AB35: =ROUND((AC35+AD35+AF35),6) -> 494.25 | AC35: =ROUND((ES35),6) -> 494.25 | AD35: =ROUND((((ET35)-(EU35))+AE35),6) -> 0 | AE35: =ROUND((EU35),6) -> 0 | AF35: =ROUND((EV35),6) -> 0 | AG35: =ROUND((AP35),6) -> 0 | AH35: =(EW35) -> 0 | AI35: =(EX35) -> 0 | AJ35: =(AS35) -> 0 | AK35: 494.25 | AL35: 494.25 | AM35: 0 | AN35: 0 | AO35: 0 | AP35: 0 | AQ35: 0 | AR35: 0 | AS35: 0 | AT35: 109 | AU35: 61 | AV35: 1 | AW35: 1 | AZ35: 1 | BA35: 1 | BB35: 1 | BC35: 9.84 | BH35: 3 | BI35: 1 | BM35: 23 | BN35: 0 | BP35: 0 | BQ35: 30 | BR35: 0 | BS35: 1 | BT35: 1 | BU35: 1 | BV35: 1 | BW35: 1 | BX35: 1 | BZ35: 109 | CA35: 61 | CE35: 1566 | CF35: 0 | CG35: 0 | CM35: 0 | CO35: 0 | CP35: =(P35+Q35+S35) -> 53497.62 | CQ35: =ROUND((ROUND((AC35*AW35*1),2)*BC35),2) -> 4863.42 | CR35: =(ROUND((ROUND(((ET35)*AV35*1),2)*BB35),2)+ROUND((ROUND(((AE35-(EU35))*AV35*1),2)*BS35),2)) -> 0 | CS35: =(ROUND((ROUND(((EU35)*AV35*1),2)*BS35),2)+ROUND((ROUND(((AE35-(EU35))*AV35*1),2)*BS35),2)) -> 0 | CT35: =ROUND((ROUND((AF35*AV35*1),2)*BA35),2) -> 0 | CU35: =AG35 -> 0 | CV35: =(AH35*AV35) -> 0 | CW35: =AI35 -> 0 | CX35: =AJ35 -> 0 | CY35: =(ROUND((((S35+ROUND((ROUND(((EU35)*AV35*1),2)*BS35),2))*AT35)/100),2)+ROUND(((ROUND((ROUND(((AE35-(EU35))*AV35*1),2)*BS35),2)*AT35)/100),2)) -> 0 | CZ35: =(ROUND((((S35+ROUND((ROUND(((EU35)*AV35*1),2)*BS35),2))*AU35)/100),2)+ROUND(((ROUND((ROUND(((AE35-(EU35))*AV35*1),2)*BS35),2)*AU35)/100),2)) -> 0 | DN35: 0 | DO35: 0 | DP35: 1 | DQ35: 1 | EE35: 85635395 | EF35: 30 | EG35: Строительные работы | EH35: 0 | EJ35: 1 | EK35: 23 | EL35: ТСН-2001.3-18. Отопление - внутренние устройства | EM35: ТСН-2001.3-18-1 | EQ35: 0 | ER35: 494.25 | ES35: 494.25 | ET35: 0 | EU35: 0 | EV35: 0 | EW35: 0 | EX35: 0 | EZ35: 5 | FC35: 1 | FD35: 18 | FF35: 5817 | FQ35: 0 | FR35: 0 | FS35: 0 | FX35: 109 | FY35: 61 | GA35: [5 817 / 1,22 / 9,84] + 2% Заг.скл | GD35: 1 | GF35: 1290624388 | GG35: 2 | GH35: 3 | GI35: 5 | GJ35: 0 | GK35: 0 | GL35: =ROUND(IF(AND(BH35=3,BI35=3,FS35<>0),P35,0),2) -> 0 | GM35: =ROUND(O35+X35+Y35,2)+GX35 -> 53497.62 | GN35: =IF(OR(BI35=0,BI35=1),GM35-GX35,0) -> 53497.62 | GO35: =IF(BI35=2,GM35-GX35,0) -> 0 | GP35: =IF(BI35=4,GM35-GX35,0) -> 0 | GR35: 1 | GS35: 1 | GT35: 0 | GV35: =ROUND((GT35),6) -> 0 | GW35: 1 | GX35: =ROUND(HC35*I35,2) -> 0 | HA35: 0 | HB35: 0 | HC35: =GV35*GW35 -> 0 | HE35: 0 | HF35: 2 | HS35: 0 | IK35: 0
A36: 18 | B36: 1 | C36: 17 | E36: 1,4 | F36: КА. п. 4 | G36: Сmальной nанельный paguamop PRADO Classic, mun 20, Bыcoma Н = 500 мм, PRADO Classic-20-500-700 | I36: =I28*J36 -> 13 | J36: 9.7744361 | K36: 9.774436 | O36: =ROUND(CP36,2) -> 7093.45 | P36: =ROUND((ROUND((AC36*AW36*I36),2)*BC36),2) -> 7093.45 | Q36: =(ROUND((ROUND(((ET36)*AV36*I36),2)*BB36),2)+ROUND((ROUND(((AE36-(EU36))*AV36*I36),2)*BS36),2)) -> 0 | R36: =(ROUND((ROUND(((EU36)*AV36*I36),2)*BS36),2)+ROUND((ROUND(((AE36-(EU36))*AV36*I36),2)*BS36),2)) -> 0 | S36: =ROUND((ROUND((AF36*AV36*I36),2)*BA36),2) -> 0 | T36: =ROUND(CU36*I36,2) -> 0 | U36: =CV36*I36 -> 0 | V36: =CW36*I36 -> 0 | W36: =ROUND(CX36*I36,2) -> 0 | X36: =(ROUND((((S36+ROUND((ROUND(((EU36)*AV36*I36),2)*BS36),2))*AT36)/100),2)+ROUND(((ROUND((ROUND(((AE36-(EU36))*AV36*I36),2)*BS36),2)*AT36)/100),2)) -> 0 | Y36: =(ROUND((((S36+ROUND((ROUND(((EU36)*AV36*I36),2)*BS36),2))*AU36)/100),2)+ROUND(((ROUND((ROUND(((AE36-(EU36))*AV36*I36),2)*BS36),2)*AU36)/100),2)) -> 0 | AA36: 86551701 | AB36: =ROUND((AC36+AD36+AF36),6) -> 545.65 | AC36: =ROUND((ES36),6) -> 545.65 | AD36: =ROUND((((ET36)-(EU36))+AE36),6) -> 0 | AE36: =ROUND((EU36),6) -> 0 | AF36: =ROUND((EV36),6) -> 0 | AG36: =ROUND((AP36),6) -> 0 | AH36: =(EW36) -> 0 | AI36: =(EX36) -> 0 | AJ36: =(AS36) -> 0 | AK36: 545.65 | AL36: 545.65 | AM36: 0 | AN36: 0 | AO36: 0 | AP36: 0 | AQ36: 0 | AR36: 0 | AS36: 0 | AT36: 109 | AU36: 61 | AV36: 1 | AW36: 1 | AZ36: 1 | BA36: 1 | BB36: 1 | BC36: 1 | BH36: 3 | BI36: 1 | BM36: 23 | BN36: 0 | BP36: 0 | BQ36: 30 | BR36: 0 | BS36: 1 | BT36: 1 | BU36: 1 | BV36: 1 | BW36: 1 | BX36: 1 | BZ36: 109 | CA36: 61 | CE36: 1566 | CF36: 0 | CG36: 0 | CM36: 0 | CO36: 0 | CP36: =(P36+Q36+S36) -> 7093.45 | CQ36: =ROUND((ROUND((AC36*AW36*1),2)*BC36),2) -> 545.65 | CR36: =(ROUND((ROUND(((ET36)*AV36*1),2)*BB36),2)+ROUND((ROUND(((AE36-(EU36))*AV36*1),2)*BS36),2)) -> 0 | CS36: =(ROUND((ROUND(((EU36)*AV36*1),2)*BS36),2)+ROUND((ROUND(((AE36-(EU36))*AV36*1),2)*BS36),2)) -> 0 | CT36: =ROUND((ROUND((AF36*AV36*1),2)*BA36),2) -> 0 | CU36: =AG36 -> 0 | CV36: =(AH36*AV36) -> 0 | CW36: =AI36 -> 0 | CX36: =AJ36 -> 0 | CY36: =(ROUND((((S36+ROUND((ROUND(((EU36)*AV36*1),2)*BS36),2))*AT36)/100),2)+ROUND(((ROUND((ROUND(((AE36-(EU36))*AV36*1),2)*BS36),2)*AT36)/100),2)) -> 0 | CZ36: =(ROUND((((S36+ROUND((ROUND(((EU36)*AV36*1),2)*BS36),2))*AU36)/100),2)+ROUND(((ROUND((ROUND(((AE36-(EU36))*AV36*1),2)*BS36),2)*AU36)/100),2)) -> 0 | DN36: 0 | DO36: 0 | DP36: 1 | DQ36: 1 | EE36: 85635395 | EF36: 30 | EG36: Строительные работы | EH36: 0 | EJ36: 1 | EK36: 23 | EL36: ТСН-2001.3-18. Отопление - внутренние устройства | EM36: ТСН-2001.3-18-1 | EQ36: 0 | ER36: 0 | ES36: 545.65 | ET36: 0 | EU36: 0 | EV36: 0 | EW36: 0 | EX36: 0 | FQ36: 0 | FR36: 0 | FS36: 0 | FX36: 109 | FY36: 61 | GA36: [6 422 / 1,22 / 9,84] + 2% Заг.скл | GD36: 1 | GF36: 752976982 | GG36: 2 | GH36: 4 | GI36: -2 | GJ36: 0 | GK36: 0 | GL36: =ROUND(IF(AND(BH36=3,BI36=3,FS36<>0),P36,0),2) -> 0 | GM36: =ROUND(O36+X36+Y36,2)+GX36 -> 7093.45 | GN36: =IF(OR(BI36=0,BI36=1),GM36-GX36,0) -> 7093.45 | GO36: =IF(BI36=2,GM36-GX36,0) -> 0 | GP36: =IF(BI36=4,GM36-GX36,0) -> 0 | GR36: 0 | GS36: 2 | GT36: 0 | GV36: =ROUND((GT36),6) -> 0 | GW36: 1 | GX36: =ROUND(HC36*I36,2) -> 0 | HA36: 0 | HB36: 0 | HC36: =GV36*GW36 -> 0 | HE36: 0 | HF36: 2 | HS36: 0 | IK36: 0
A37: 18 | B37: 1 | C37: 39 | E37: 1,4 | F37: КА. п. 4 | G37: Сmальной nанельный paguamop PRADO Classic, mun 20, Bыcoma Н = 500 мм, PRADO Classic-20-500-700 | I37: =I29*J37 -> 13 | J37: 9.7744361 | K37: 9.774436 | O37: =ROUND(CP37,2) -> 69799.55 | P37: =ROUND((ROUND((AC37*AW37*I37),2)*BC37),2) -> 69799.55 | Q37: =(ROUND((ROUND(((ET37)*AV37*I37),2)*BB37),2)+ROUND((ROUND(((AE37-(EU37))*AV37*I37),2)*BS37),2)) -> 0 | R37: =(ROUND((ROUND(((EU37)*AV37*I37),2)*BS37),2)+ROUND((ROUND(((AE37-(EU37))*AV37*I37),2)*BS37),2)) -> 0 | S37: =ROUND((ROUND((AF37*AV37*I37),2)*BA37),2) -> 0 | T37: =ROUND(CU37*I37,2) -> 0 | U37: =CV37*I37 -> 0 | V37: =CW37*I37 -> 0 | W37: =ROUND(CX37*I37,2) -> 0 | X37: =(ROUND((((S37+ROUND((ROUND(((EU37)*AV37*I37),2)*BS37),2))*AT37)/100),2)+ROUND(((ROUND((ROUND(((AE37-(EU37))*AV37*I37),2)*BS37),2)*AT37)/100),2)) -> 0 | Y37: =(ROUND((((S37+ROUND((ROUND(((EU37)*AV37*I37),2)*BS37),2))*AU37)/100),2)+ROUND(((ROUND((ROUND(((AE37-(EU37))*AV37*I37),2)*BS37),2)*AU37)/100),2)) -> 0 | AA37: 86551703 | AB37: =ROUND((AC37+AD37+AF37),6) -> 545.65 | AC37: =ROUND((ES37),6) -> 545.65 | AD37: =ROUND((((ET37)-(EU37))+AE37),6) -> 0 | AE37: =ROUND((EU37),6) -> 0 | AF37: =ROUND((EV37),6) -> 0 | AG37: =ROUND((AP37),6) -> 0 | AH37: =(EW37) -> 0 | AI37: =(EX37) -> 0 | AJ37: =(AS37) -> 0 | AK37: 545.65 | AL37: 545.65 | AM37: 0 | AN37: 0 | AO37: 0 | AP37: 0 | AQ37: 0 | AR37: 0 | AS37: 0 | AT37: 109 | AU37: 61 | AV37: 1 | AW37: 1 | AZ37: 1 | BA37: 1 | BB37: 1 | BC37: 9.84 | BH37: 3 | BI37: 1 | BM37: 23 | BN37: 0 | BP37: 0 | BQ37: 30 | BR37: 0 | BS37: 1 | BT37: 1 | BU37: 1 | BV37: 1 | BW37: 1 | BX37: 1 | BZ37: 109 | CA37: 61 | CE37: 1566 | CF37: 0 | CG37: 0 | CM37: 0 | CO37: 0 | CP37: =(P37+Q37+S37) -> 69799.55 | CQ37: =ROUND((ROUND((AC37*AW37*1),2)*BC37),2) -> 5369.2 | CR37: =(ROUND((ROUND(((ET37)*AV37*1),2)*BB37),2)+ROUND((ROUND(((AE37-(EU37))*AV37*1),2)*BS37),2)) -> 0 | CS37: =(ROUND((ROUND(((EU37)*AV37*1),2)*BS37),2)+ROUND((ROUND(((AE37-(EU37))*AV37*1),2)*BS37),2)) -> 0 | CT37: =ROUND((ROUND((AF37*AV37*1),2)*BA37),2) -> 0 | CU37: =AG37 -> 0 | CV37: =(AH37*AV37) -> 0 | CW37: =AI37 -> 0 | CX37: =AJ37 -> 0 | CY37: =(ROUND((((S37+ROUND((ROUND(((EU37)*AV37*1),2)*BS37),2))*AT37)/100),2)+ROUND(((ROUND((ROUND(((AE37-(EU37))*AV37*1),2)*BS37),2)*AT37)/100),2)) -> 0 | CZ37: =(ROUND((((S37+ROUND((ROUND(((EU37)*AV37*1),2)*BS37),2))*AU37)/100),2)+ROUND(((ROUND((ROUND(((AE37-(EU37))*AV37*1),2)*BS37),2)*AU37)/100),2)) -> 0 | DN37: 0 | DO37: 0 | DP37: 1 | DQ37: 1 | EE37: 85635395 | EF37: 30 | EG37: Строительные работы | EH37: 0 | EJ37: 1 | EK37: 23 | EL37: ТСН-2001.3-18. Отопление - внутренние устройства | EM37: ТСН-2001.3-18-1 | EQ37: 0 | ER37: 545.65 | ES37: 545.65 | ET37: 0 | EU37: 0 | EV37: 0 | EW37: 0 | EX37: 0 | EZ37: 5 | FC37: 1 | FD37: 18 | FF37: 6422 | FQ37: 0 | FR37: 0 | FS37: 0 | FX37: 109 | FY37: 61 | GA37: [6 422 / 1,22 / 9,84] + 2% Заг.скл | GD37: 1 | GF37: 752976982 | GG37: 2 | GH37: 3 | GI37: 5 | GJ37: 0 | GK37: 0 | GL37: =ROUND(IF(AND(BH37=3,BI37=3,FS37<>0),P37,0),2) -> 0 | GM37: =ROUND(O37+X37+Y37,2)+GX37 -> 69799.55 | GN37: =IF(OR(BI37=0,BI37=1),GM37-GX37,0) -> 69799.55 | GO37: =IF(BI37=2,GM37-GX37,0) -> 0 | GP37: =IF(BI37=4,GM37-GX37,0) -> 0 | GR37: 1 | GS37: 1 | GT37: 0 | GV37: =ROUND((GT37),6) -> 0 | GW37: 1 | GX37: =ROUND(HC37*I37,2) -> 0 | HA37: 0 | HB37: 0 | HC37: =GV37*GW37 -> 0 | HE37: 0 | HF37: 2 | HS37: 0 | IK37: 0
A38: 18 | B38: 1 | C38: 18 | E38: 1,5 | F38: КА. п. 5 | G38: Сmальной nанельный paguamop PRADO Classic, mun 20, Bыcoma Н = 500 мм, PRADO Classic-20-500-800 | I38: =I28*J38 -> 23 | J38: 17.293233 | K38: 17.293233 | O38: =ROUND(CP38,2) -> 13833.81 | P38: =ROUND((ROUND((AC38*AW38*I38),2)*BC38),2) -> 13833.81 | Q38: =(ROUND((ROUND(((ET38)*AV38*I38),2)*BB38),2)+ROUND((ROUND(((AE38-(EU38))*AV38*I38),2)*BS38),2)) -> 0 | R38: =(ROUND((ROUND(((EU38)*AV38*I38),2)*BS38),2)+ROUND((ROUND(((AE38-(EU38))*AV38*I38),2)*BS38),2)) -> 0 | S38: =ROUND((ROUND((AF38*AV38*I38),2)*BA38),2) -> 0 | T38: =ROUND(CU38*I38,2) -> 0 | U38: =CV38*I38 -> 0 | V38: =CW38*I38 -> 0 | W38: =ROUND(CX38*I38,2) -> 0 | X38: =(ROUND((((S38+ROUND((ROUND(((EU38)*AV38*I38),2)*BS38),2))*AT38)/100),2)+ROUND(((ROUND((ROUND(((AE38-(EU38))*AV38*I38),2)*BS38),2)*AT38)/100),2)) -> 0 | Y38: =(ROUND((((S38+ROUND((ROUND(((EU38)*AV38*I38),2)*BS38),2))*AU38)/100),2)+ROUND(((ROUND((ROUND(((AE38-(EU38))*AV38*I38),2)*BS38),2)*AU38)/100),2)) -> 0 | AA38: 86551701 | AB38: =ROUND((AC38+AD38+AF38),6) -> 601.47 | AC38: =ROUND((ES38),6) -> 601.47 | AD38: =ROUND((((ET38)-(EU38))+AE38),6) -> 0 | AE38: =ROUND((EU38),6) -> 0 | AF38: =ROUND((EV38),6) -> 0 | AG38: =ROUND((AP38),6) -> 0 | AH38: =(EW38) -> 0 | AI38: =(EX38) -> 0 | AJ38: =(AS38) -> 0 | AK38: 601.47 | AL38: 601.47 | AM38: 0 | AN38: 0 | AO38: 0 | AP38: 0 | AQ38: 0 | AR38: 0 | AS38: 0 | AT38: 109 | AU38: 61 | AV38: 1 | AW38: 1 | AZ38: 1 | BA38: 1 | BB38: 1 | BC38: 1 | BH38: 3 | BI38: 1 | BM38: 23 | BN38: 0 | BP38: 0 | BQ38: 30 | BR38: 0 | BS38: 1 | BT38: 1 | BU38: 1 | BV38: 1 | BW38: 1 | BX38: 1 | BZ38: 109 | CA38: 61 | CE38: 1566 | CF38: 0 | CG38: 0 | CM38: 0 | CO38: 0 | CP38: =(P38+Q38+S38) -> 13833.81 | CQ38: =ROUND((ROUND((AC38*AW38*1),2)*BC38),2) -> 601.47 | CR38: =(ROUND((ROUND(((ET38)*AV38*1),2)*BB38),2)+ROUND((ROUND(((AE38-(EU38))*AV38*1),2)*BS38),2)) -> 0 | CS38: =(ROUND((ROUND(((EU38)*AV38*1),2)*BS38),2)+ROUND((ROUND(((AE38-(EU38))*AV38*1),2)*BS38),2)) -> 0 | CT38: =ROUND((ROUND((AF38*AV38*1),2)*BA38),2) -> 0 | CU38: =AG38 -> 0 | CV38: =(AH38*AV38) -> 0 | CW38: =AI38 -> 0 | CX38: =AJ38 -> 0 | CY38: =(ROUND((((S38+ROUND((ROUND(((EU38)*AV38*1),2)*BS38),2))*AT38)/100),2)+ROUND(((ROUND((ROUND(((AE38-(EU38))*AV38*1),2)*BS38),2)*AT38)/100),2)) -> 0 | CZ38: =(ROUND((((S38+ROUND((ROUND(((EU38)*AV38*1),2)*BS38),2))*AU38)/100),2)+ROUND(((ROUND((ROUND(((AE38-(EU38))*AV38*1),2)*BS38),2)*AU38)/100),2)) -> 0 | DN38: 0 | DO38: 0 | DP38: 1 | DQ38: 1 | EE38: 85635395 | EF38: 30 | EG38: Строительные работы | EH38: 0 | EJ38: 1 | EK38: 23 | EL38: ТСН-2001.3-18. Отопление - внутренние устройства | EM38: ТСН-2001.3-18-1 | EQ38: 0 | ER38: 0 | ES38: 601.47 | ET38: 0 | EU38: 0 | EV38: 0 | EW38: 0 | EX38: 0 | FQ38: 0 | FR38: 0 | FS38: 0 | FX38: 109 | FY38: 61 | GA38: [7 079 / 1,22 / 9,84] + 2% Заг.скл | GD38: 1 | GF38: 566747535 | GG38: 2 | GH38: 4 | GI38: -2 | GJ38: 0 | GK38: 0 | GL38: =ROUND(IF(AND(BH38=3,BI38=3,FS38<>0),P38,0),2) -> 0 | GM38: =ROUND(O38+X38+Y38,2)+GX38 -> 13833.81 | GN38: =IF(OR(BI38=0,BI38=1),GM38-GX38,0) -> 13833.81 | GO38: =IF(BI38=2,GM38-GX38,0) -> 0 | GP38: =IF(BI38=4,GM38-GX38,0) -> 0 | GR38: 0 | GS38: 2 | GT38: 0 | GV38: =ROUND((GT38),6) -> 0 | GW38: 1 | GX38: =ROUND(HC38*I38,2) -> 0 | HA38: 0 | HB38: 0 | HC38: =GV38*GW38 -> 0 | HE38: 0 | HF38: 2 | HS38: 0 | IK38: 0
A39: 18 | B39: 1 | C39: 40 | E39: 1,5 | F39: КА. п. 5 | G39: Сmальной nанельный paguamop PRADO Classic, mun 20, Bыcoma Н = 500 мм, PRADO Classic-20-500-800 | I39: =I29*J39 -> 23 | J39: 17.293233 | K39: 17.293233 | O39: =ROUND(CP39,2) -> 136124.69 | P39: =ROUND((ROUND((AC39*AW39*I39),2)*BC39),2) -> 136124.69 | Q39: =(ROUND((ROUND(((ET39)*AV39*I39),2)*BB39),2)+ROUND((ROUND(((AE39-(EU39))*AV39*I39),2)*BS39),2)) -> 0 | R39: =(ROUND((ROUND(((EU39)*AV39*I39),2)*BS39),2)+ROUND((ROUND(((AE39-(EU39))*AV39*I39),2)*BS39),2)) -> 0 | S39: =ROUND((ROUND((AF39*AV39*I39),2)*BA39),2) -> 0 | T39: =ROUND(CU39*I39,2) -> 0 | U39: =CV39*I39 -> 0 | V39: =CW39*I39 -> 0 | W39: =ROUND(CX39*I39,2) -> 0 | X39: =(ROUND((((S39+ROUND((ROUND(((EU39)*AV39*I39),2)*BS39),2))*AT39)/100),2)+ROUND(((ROUND((ROUND(((AE39-(EU39))*AV39*I39),2)*BS39),2)*AT39)/100),2)) -> 0 | Y39: =(ROUND((((S39+ROUND((ROUND(((EU39)*AV39*I39),2)*BS39),2))*AU39)/100),2)+ROUND(((ROUND((ROUND(((AE39-(EU39))*AV39*I39),2)*BS39),2)*AU39)/100),2)) -> 0 | AA39: 86551703 | AB39: =ROUND((AC39+AD39+AF39),6) -> 601.47 | AC39: =ROUND((ES39),6) -> 601.47 | AD39: =ROUND((((ET39)-(EU39))+AE39),6) -> 0 | AE39: =ROUND((EU39),6) -> 0 | AF39: =ROUND((EV39),6) -> 0 | AG39: =ROUND((AP39),6) -> 0 | AH39: =(EW39) -> 0 | AI39: =(EX39) -> 0 | AJ39: =(AS39) -> 0 | AK39: 601.47 | AL39: 601.47 | AM39: 0 | AN39: 0 | AO39: 0 | AP39: 0 | AQ39: 0 | AR39: 0 | AS39: 0 | AT39: 109 | AU39: 61 | AV39: 1 | AW39: 1 | AZ39: 1 | BA39: 1 | BB39: 1 | BC39: 9.84 | BH39: 3 | BI39: 1 | BM39: 23 | BN39: 0 | BP39: 0 | BQ39: 30 | BR39: 0 | BS39: 1 | BT39: 1 | BU39: 1 | BV39: 1 | BW39: 1 | BX39: 1 | BZ39: 109 | CA39: 61 | CE39: 1566 | CF39: 0 | CG39: 0 | CM39: 0 | CO39: 0 | CP39: =(P39+Q39+S39) -> 136124.69 | CQ39: =ROUND((ROUND((AC39*AW39*1),2)*BC39),2) -> 5918.46 | CR39: =(ROUND((ROUND(((ET39)*AV39*1),2)*BB39),2)+ROUND((ROUND(((AE39-(EU39))*AV39*1),2)*BS39),2)) -> 0 | CS39: =(ROUND((ROUND(((EU39)*AV39*1),2)*BS39),2)+ROUND((ROUND(((AE39-(EU39))*AV39*1),2)*BS39),2)) -> 0 | CT39: =ROUND((ROUND((AF39*AV39*1),2)*BA39),2) -> 0 | CU39: =AG39 -> 0 | CV39: =(AH39*AV39) -> 0 | CW39: =AI39 -> 0 | CX39: =AJ39 -> 0 | CY39: =(ROUND((((S39+ROUND((ROUND(((EU39)*AV39*1),2)*BS39),2))*AT39)/100),2)+ROUND(((ROUND((ROUND(((AE39-(EU39))*AV39*1),2)*BS39),2)*AT39)/100),2)) -> 0 | CZ39: =(ROUND((((S39+ROUND((ROUND(((EU39)*AV39*1),2)*BS39),2))*AU39)/100),2)+ROUND(((ROUND((ROUND(((AE39-(EU39))*AV39*1),2)*BS39),2)*AU39)/100),2)) -> 0 | DN39: 0 | DO39: 0 | DP39: 1 | DQ39: 1 | EE39: 85635395 | EF39: 30 | EG39: Строительные работы | EH39: 0 | EJ39: 1 | EK39: 23 | EL39: ТСН-2001.3-18. Отопление - внутренние устройства | EM39: ТСН-2001.3-18-1 | EQ39: 0 | ER39: 601.47 | ES39: 601.47 | ET39: 0 | EU39: 0 | EV39: 0 | EW39: 0 | EX39: 0 | EZ39: 5 | FC39: 1 | FD39: 18 | FF39: 7079 | FQ39: 0 | FR39: 0 | FS39: 0 | FX39: 109 | FY39: 61 | GA39: [7 079 / 1,22 / 9,84] + 2% Заг.скл | GD39: 1 | GF39: 566747535 | GG39: 2 | GH39: 3 | GI39: 5 | GJ39: 0 | GK39: 0 | GL39: =ROUND(IF(AND(BH39=3,BI39=3,FS39<>0),P39,0),2) -> 0 | GM39: =ROUND(O39+X39+Y39,2)+GX39 -> 136124.69 | GN39: =IF(OR(BI39=0,BI39=1),GM39-GX39,0) -> 136124.69 | GO39: =IF(BI39=2,GM39-GX39,0) -> 0 | GP39: =IF(BI39=4,GM39-GX39,0) -> 0 | GR39: 1 | GS39: 1 | GT39: 0 | GV39: =ROUND((GT39),6) -> 0 | GW39: 1 | GX39: =ROUND(HC39*I39,2) -> 0 | HA39: 0 | HB39: 0 | HC39: =GV39*GW39 -> 0 | HE39: 0 | HF39: 2 | HS39: 0 | IK39: 0
A40: 18 | B40: 1 | C40: 19 | E40: 1,6 | F40: КА. п. 6 | G40: Сmальной nанельный paguamop PRADO Classic, mun 20, Bыcoma Н = 500 мм, PRADO Classic-20-500-900 | I40: =I28*J40 -> 2 | J40: 1.5037594 | K40: 1.5037594 | O40: =ROUND(CP40,2) -> 1320.2 | P40: =ROUND((ROUND((AC40*AW40*I40),2)*BC40),2) -> 1320.2 | Q40: =(ROUND((ROUND(((ET40)*AV40*I40),2)*BB40),2)+ROUND((ROUND(((AE40-(EU40))*AV40*I40),2)*BS40),2)) -> 0 | R40: =(ROUND((ROUND(((EU40)*AV40*I40),2)*BS40),2)+ROUND((ROUND(((AE40-(EU40))*AV40*I40),2)*BS40),2)) -> 0 | S40: =ROUND((ROUND((AF40*AV40*I40),2)*BA40),2) -> 0 | T40: =ROUND(CU40*I40,2) -> 0 | U40: =CV40*I40 -> 0 | V40: =CW40*I40 -> 0 | W40: =ROUND(CX40*I40,2) -> 0 | X40: =(ROUND((((S40+ROUND((ROUND(((EU40)*AV40*I40),2)*BS40),2))*AT40)/100),2)+ROUND(((ROUND((ROUND(((AE40-(EU40))*AV40*I40),2)*BS40),2)*AT40)/100),2)) -> 0 | Y40: =(ROUND((((S40+ROUND((ROUND(((EU40)*AV40*I40),2)*BS40),2))*AU40)/100),2)+ROUND(((ROUND((ROUND(((AE40-(EU40))*AV40*I40),2)*BS40),2)*AU40)/100),2)) -> 0 | AA40: 86551701 | AB40: =ROUND((AC40+AD40+AF40),6) -> 660.1 | AC40: =ROUND((ES40),6) -> 660.1 | AD40: =ROUND((((ET40)-(EU40))+AE40),6) -> 0 | AE40: =ROUND((EU40),6) -> 0 | AF40: =ROUND((EV40),6) -> 0 | AG40: =ROUND((AP40),6) -> 0 | AH40: =(EW40) -> 0 | AI40: =(EX40) -> 0 | AJ40: =(AS40) -> 0 | AK40: 660.1 | AL40: 660.1 | AM40: 0 | AN40: 0 | AO40: 0 | AP40: 0 | AQ40: 0 | AR40: 0 | AS40: 0 | AT40: 109 | AU40: 61 | AV40: 1 | AW40: 1 | AZ40: 1 | BA40: 1 | BB40: 1 | BC40: 1 | BH40: 3 | BI40: 1 | BM40: 23 | BN40: 0 | BP40: 0 | BQ40: 30 | BR40: 0 | BS40: 1 | BT40: 1 | BU40: 1 | BV40: 1 | BW40: 1 | BX40: 1 | BZ40: 109 | CA40: 61 | CE40: 1566 | CF40: 0 | CG40: 0 | CM40: 0 | CO40: 0 | CP40: =(P40+Q40+S40) -> 1320.2 | CQ40: =ROUND((ROUND((AC40*AW40*1),2)*BC40),2) -> 660.1 | CR40: =(ROUND((ROUND(((ET40)*AV40*1),2)*BB40),2)+ROUND((ROUND(((AE40-(EU40))*AV40*1),2)*BS40),2)) -> 0 | CS40: =(ROUND((ROUND(((EU40)*AV40*1),2)*BS40),2)+ROUND((ROUND(((AE40-(EU40))*AV40*1),2)*BS40),2)) -> 0 | CT40: =ROUND((ROUND((AF40*AV40*1),2)*BA40),2) -> 0 | CU40: =AG40 -> 0 | CV40: =(AH40*AV40) -> 0 | CW40: =AI40 -> 0 | CX40: =AJ40 -> 0 | CY40: =(ROUND((((S40+ROUND((ROUND(((EU40)*AV40*1),2)*BS40),2))*AT40)/100),2)+ROUND(((ROUND((ROUND(((AE40-(EU40))*AV40*1),2)*BS40),2)*AT40)/100),2)) -> 0 | CZ40: =(ROUND((((S40+ROUND((ROUND(((EU40)*AV40*1),2)*BS40),2))*AU40)/100),2)+ROUND(((ROUND((ROUND(((AE40-(EU40))*AV40*1),2)*BS40),2)*AU40)/100),2)) -> 0 | DN40: 0 | DO40: 0 | DP40: 1 | DQ40: 1 | EE40: 85635395 | EF40: 30 | EG40: Строительные работы | EH40: 0 | EJ40: 1 | EK40: 23 | EL40: ТСН-2001.3-18. Отопление - внутренние устройства | EM40: ТСН-2001.3-18-1 | EQ40: 0 | ER40: 0 | ES40: 660.1 | ET40: 0 | EU40: 0 | EV40: 0 | EW40: 0 | EX40: 0 | FQ40: 0 | FR40: 0 | FS40: 0 | FX40: 109 | FY40: 61 | GA40: [7 769 / 1,22 / 9,84] + 2% Заг.скл | GD40: 1 | GF40: 1036536234 | GG40: 2 | GH40: 4 | GI40: -2 | GJ40: 0 | GK40: 0 | GL40: =ROUND(IF(AND(BH40=3,BI40=3,FS40<>0),P40,0),2) -> 0 | GM40: =ROUND(O40+X40+Y40,2)+GX40 -> 1320.2 | GN40: =IF(OR(BI40=0,BI40=1),GM40-GX40,0) -> 1320.2 | GO40: =IF(BI40=2,GM40-GX40,0) -> 0 | GP40: =IF(BI40=4,GM40-GX40,0) -> 0 | GR40: 0 | GS40: 2 | GT40: 0 | GV40: =ROUND((GT40),6) -> 0 | GW40: 1 | GX40: =ROUND(HC40*I40,2) -> 0 | HA40: 0 | HB40: 0 | HC40: =GV40*GW40 -> 0 | HE40: 0 | HF40: 2 | HS40: 0 | IK40: 0
A41: 18 | B41: 1 | C41: 41 | E41: 1,6 | F41: КА. п. 6 | G41: Сmальной nанельный paguamop PRADO Classic, mun 20, Bыcoma Н = 500 мм, PRADO Classic-20-500-900 | I41: =I29*J41 -> 2 | J41: 1.5037594 | K41: 1.5037594 | O41: =ROUND(CP41,2) -> 12990.77 | P41: =ROUND((ROUND((AC41*AW41*I41),2)*BC41),2) -> 12990.77 | Q41: =(ROUND((ROUND(((ET41)*AV41*I41),2)*BB41),2)+ROUND((ROUND(((AE41-(EU41))*AV41*I41),2)*BS41),2)) -> 0 | R41: =(ROUND((ROUND(((EU41)*AV41*I41),2)*BS41),2)+ROUND((ROUND(((AE41-(EU41))*AV41*I41),2)*BS41),2)) -> 0 | S41: =ROUND((ROUND((AF41*AV41*I41),2)*BA41),2) -> 0 | T41: =ROUND(CU41*I41,2) -> 0 | U41: =CV41*I41 -> 0 | V41: =CW41*I41 -> 0 | W41: =ROUND(CX41*I41,2) -> 0 | X41: =(ROUND((((S41+ROUND((ROUND(((EU41)*AV41*I41),2)*BS41),2))*AT41)/100),2)+ROUND(((ROUND((ROUND(((AE41-(EU41))*AV41*I41),2)*BS41),2)*AT41)/100),2)) -> 0 | Y41: =(ROUND((((S41+ROUND((ROUND(((EU41)*AV41*I41),2)*BS41),2))*AU41)/100),2)+ROUND(((ROUND((ROUND(((AE41-(EU41))*AV41*I41),2)*BS41),2)*AU41)/100),2)) -> 0 | AA41: 86551703 | AB41: =ROUND((AC41+AD41+AF41),6) -> 660.1 | AC41: =ROUND((ES41),6) -> 660.1 | AD41: =ROUND((((ET41)-(EU41))+AE41),6) -> 0 | AE41: =ROUND((EU41),6) -> 0 | AF41: =ROUND((EV41),6) -> 0 | AG41: =ROUND((AP41),6) -> 0 | AH41: =(EW41) -> 0 | AI41: =(EX41) -> 0 | AJ41: =(AS41) -> 0 | AK41: 660.1 | AL41: 660.1 | AM41: 0 | AN41: 0 | AO41: 0 | AP41: 0 | AQ41: 0 | AR41: 0 | AS41: 0 | AT41: 109 | AU41: 61 | AV41: 1 | AW41: 1 | AZ41: 1 | BA41: 1 | BB41: 1 | BC41: 9.84 | BH41: 3 | BI41: 1 | BM41: 23 | BN41: 0 | BP41: 0 | BQ41: 30 | BR41: 0 | BS41: 1 | BT41: 1 | BU41: 1 | BV41: 1 | BW41: 1 | BX41: 1 | BZ41: 109 | CA41: 61 | CE41: 1566 | CF41: 0 | CG41: 0 | CM41: 0 | CO41: 0 | CP41: =(P41+Q41+S41) -> 12990.77 | CQ41: =ROUND((ROUND((AC41*AW41*1),2)*BC41),2) -> 6495.38 | CR41: =(ROUND((ROUND(((ET41)*AV41*1),2)*BB41),2)+ROUND((ROUND(((AE41-(EU41))*AV41*1),2)*BS41),2)) -> 0 | CS41: =(ROUND((ROUND(((EU41)*AV41*1),2)*BS41),2)+ROUND((ROUND(((AE41-(EU41))*AV41*1),2)*BS41),2)) -> 0 | CT41: =ROUND((ROUND((AF41*AV41*1),2)*BA41),2) -> 0 | CU41: =AG41 -> 0 | CV41: =(AH41*AV41) -> 0 | CW41: =AI41 -> 0 | CX41: =AJ41 -> 0 | CY41: =(ROUND((((S41+ROUND((ROUND(((EU41)*AV41*1),2)*BS41),2))*AT41)/100),2)+ROUND(((ROUND((ROUND(((AE41-(EU41))*AV41*1),2)*BS41),2)*AT41)/100),2)) -> 0 | CZ41: =(ROUND((((S41+ROUND((ROUND(((EU41)*AV41*1),2)*BS41),2))*AU41)/100),2)+ROUND(((ROUND((ROUND(((AE41-(EU41))*AV41*1),2)*BS41),2)*AU41)/100),2)) -> 0 | DN41: 0 | DO41: 0 | DP41: 1 | DQ41: 1 | EE41: 85635395 | EF41: 30 | EG41: Строительные работы | EH41: 0 | EJ41: 1 | EK41: 23 | EL41: ТСН-2001.3-18. Отопление - внутренние устройства | EM41: ТСН-2001.3-18-1 | EQ41: 0 | ER41: 660.1 | ES41: 660.1 | ET41: 0 | EU41: 0 | EV41: 0 | EW41: 0 | EX41: 0 | EZ41: 5 | FC41: 1 | FD41: 18 | FF41: 7769 | FQ41: 0 | FR41: 0 | FS41: 0 | FX41: 109 | FY41: 61 | GA41: [7 769 / 1,22 / 9,84] + 2% Заг.скл | GD41: 1 | GF41: 1036536234 | GG41: 2 | GH41: 3 | GI41: 5 | GJ41: 0 | GK41: 0 | GL41: =ROUND(IF(AND(BH41=3,BI41=3,FS41<>0),P41,0),2) -> 0 | GM41: =ROUND(O41+X41+Y41,2)+GX41 -> 12990.77 | GN41: =IF(OR(BI41=0,BI41=1),GM41-GX41,0) -> 12990.77 | GO41: =IF(BI41=2,GM41-GX41,0) -> 0 | GP41: =IF(BI41=4,GM41-GX41,0) -> 0 | GR41: 1 | GS41: 1 | GT41: 0 | GV41: =ROUND((GT41),6) -> 0 | GW41: 1 | GX41: =ROUND(HC41*I41,2) -> 0 | HA41: 0 | HB41: 0 | HC41: =GV41*GW41 -> 0 | HE41: 0 | HF41: 2 | HS41: 0 | IK41: 0
A42: 18 | B42: 1 | C42: 20 | E42: 1,7 | F42: КА. п. 7 | G42: Сmальной nанельный paguamop PRADO Classic, mun 20, Bыcoma Н = 500 мм, PRADO Classic-20-500-1000 | I42: =I28*J42 -> 10 | J42: 7.518797 | K42: 7.518797 | O42: =ROUND(CP42,2) -> 7260.4 | P42: =ROUND((ROUND((AC42*AW42*I42),2)*BC42),2) -> 7260.4 | Q42: =(ROUND((ROUND(((ET42)*AV42*I42),2)*BB42),2)+ROUND((ROUND(((AE42-(EU42))*AV42*I42),2)*BS42),2)) -> 0 | R42: =(ROUND((ROUND(((EU42)*AV42*I42),2)*BS42),2)+ROUND((ROUND(((AE42-(EU42))*AV42*I42),2)*BS42),2)) -> 0 | S42: =ROUND((ROUND((AF42*AV42*I42),2)*BA42),2) -> 0 | T42: =ROUND(CU42*I42,2) -> 0 | U42: =CV42*I42 -> 0 | V42: =CW42*I42 -> 0 | W42: =ROUND(CX42*I42,2) -> 0 | X42: =(ROUND((((S42+ROUND((ROUND(((EU42)*AV42*I42),2)*BS42),2))*AT42)/100),2)+ROUND(((ROUND((ROUND(((AE42-(EU42))*AV42*I42),2)*BS42),2)*AT42)/100),2)) -> 0 | Y42: =(ROUND((((S42+ROUND((ROUND(((EU42)*AV42*I42),2)*BS42),2))*AU42)/100),2)+ROUND(((ROUND((ROUND(((AE42-(EU42))*AV42*I42),2)*BS42),2)*AU42)/100),2)) -> 0 | AA42: 86551701 | AB42: =ROUND((AC42+AD42+AF42),6) -> 726.04 | AC42: =ROUND((ES42),6) -> 726.04 | AD42: =ROUND((((ET42)-(EU42))+AE42),6) -> 0 | AE42: =ROUND((EU42),6) -> 0 | AF42: =ROUND((EV42),6) -> 0 | AG42: =ROUND((AP42),6) -> 0 | AH42: =(EW42) -> 0 | AI42: =(EX42) -> 0 | AJ42: =(AS42) -> 0 | AK42: 726.04 | AL42: 726.04 | AM42: 0 | AN42: 0 | AO42: 0 | AP42: 0 | AQ42: 0 | AR42: 0 | AS42: 0 | AT42: 109 | AU42: 61 | AV42: 1 | AW42: 1 | AZ42: 1 | BA42: 1 | BB42: 1 | BC42: 1 | BH42: 3 | BI42: 1 | BM42: 23 | BN42: 0 | BP42: 0 | BQ42: 30 | BR42: 0 | BS42: 1 | BT42: 1 | BU42: 1 | BV42: 1 | BW42: 1 | BX42: 1 | BZ42: 109 | CA42: 61 | CE42: 1566 | CF42: 0 | CG42: 0 | CM42: 0 | CO42: 0 | CP42: =(P42+Q42+S42) -> 7260.4 | CQ42: =ROUND((ROUND((AC42*AW42*1),2)*BC42),2) -> 726.04 | CR42: =(ROUND((ROUND(((ET42)*AV42*1),2)*BB42),2)+ROUND((ROUND(((AE42-(EU42))*AV42*1),2)*BS42),2)) -> 0 | CS42: =(ROUND((ROUND(((EU42)*AV42*1),2)*BS42),2)+ROUND((ROUND(((AE42-(EU42))*AV42*1),2)*BS42),2)) -> 0 | CT42: =ROUND((ROUND((AF42*AV42*1),2)*BA42),2) -> 0 | CU42: =AG42 -> 0 | CV42: =(AH42*AV42) -> 0 | CW42: =AI42 -> 0 | CX42: =AJ42 -> 0 | CY42: =(ROUND((((S42+ROUND((ROUND(((EU42)*AV42*1),2)*BS42),2))*AT42)/100),2)+ROUND(((ROUND((ROUND(((AE42-(EU42))*AV42*1),2)*BS42),2)*AT42)/100),2)) -> 0 | CZ42: =(ROUND((((S42+ROUND((ROUND(((EU42)*AV42*1),2)*BS42),2))*AU42)/100),2)+ROUND(((ROUND((ROUND(((AE42-(EU42))*AV42*1),2)*BS42),2)*AU42)/100),2)) -> 0 | DN42: 0 | DO42: 0 | DP42: 1 | DQ42: 1 | EE42: 85635395 | EF42: 30 | EG42: Строительные работы | EH42: 0 | EJ42: 1 | EK42: 23 | EL42: ТСН-2001.3-18. Отопление - внутренние устройства | EM42: ТСН-2001.3-18-1 | EQ42: 0 | ER42: 0 | ES42: 726.04 | ET42: 0 | EU42: 0 | EV42: 0 | EW42: 0 | EX42: 0 | FQ42: 0 | FR42: 0 | FS42: 0 | FX42: 109 | FY42: 61 | GA42: [8 545 / 1,22 / 9,84] + 2% Заг.скл | GD42: 1 | GF42: -1830095872 | GG42: 2 | GH42: 4 | GI42: -2 | GJ42: 0 | GK42: 0 | GL42: =ROUND(IF(AND(BH42=3,BI42=3,FS42<>0),P42,0),2) -> 0 | GM42: =ROUND(O42+X42+Y42,2)+GX42 -> 7260.4 | GN42: =IF(OR(BI42=0,BI42=1),GM42-GX42,0) -> 7260.4 | GO42: =IF(BI42=2,GM42-GX42,0) -> 0 | GP42: =IF(BI42=4,GM42-GX42,0) -> 0 | GR42: 0 | GS42: 2 | GT42: 0 | GV42: =ROUND((GT42),6) -> 0 | GW42: 1 | GX42: =ROUND(HC42*I42,2) -> 0 | HA42: 0 | HB42: 0 | HC42: =GV42*GW42 -> 0 | HE42: 0 | HF42: 2 | HS42: 0 | IK42: 0
A43: 18 | B43: 1 | C43: 42 | E43: 1,7 | F43: КА. п. 7 | G43: Сmальной nанельный paguamop PRADO Classic, mun 20, Bыcoma Н = 500 мм, PRADO Classic-20-500-1000 | I43: =I29*J43 -> 10 | J43: 7.518797 | K43: 7.518797 | O43: =ROUND(CP43,2) -> 71442.34 | P43: =ROUND((ROUND((AC43*AW43*I43),2)*BC43),2) -> 71442.34 | Q43: =(ROUND((ROUND(((ET43)*AV43*I43),2)*BB43),2)+ROUND((ROUND(((AE43-(EU43))*AV43*I43),2)*BS43),2)) -> 0 | R43: =(ROUND((ROUND(((EU43)*AV43*I43),2)*BS43),2)+ROUND((ROUND(((AE43-(EU43))*AV43*I43),2)*BS43),2)) -> 0 | S43: =ROUND((ROUND((AF43*AV43*I43),2)*BA43),2) -> 0 | T43: =ROUND(CU43*I43,2) -> 0 | U43: =CV43*I43 -> 0 | V43: =CW43*I43 -> 0 | W43: =ROUND(CX43*I43,2) -> 0 | X43: =(ROUND((((S43+ROUND((ROUND(((EU43)*AV43*I43),2)*BS43),2))*AT43)/100),2)+ROUND(((ROUND((ROUND(((AE43-(EU43))*AV43*I43),2)*BS43),2)*AT43)/100),2)) -> 0 | Y43: =(ROUND((((S43+ROUND((ROUND(((EU43)*AV43*I43),2)*BS43),2))*AU43)/100),2)+ROUND(((ROUND((ROUND(((AE43-(EU43))*AV43*I43),2)*BS43),2)*AU43)/100),2)) -> 0 | AA43: 86551703 | AB43: =ROUND((AC43+AD43+AF43),6) -> 726.04 | AC43: =ROUND((ES43),6) -> 726.04 | AD43: =ROUND((((ET43)-(EU43))+AE43),6) -> 0 | AE43: =ROUND((EU43),6) -> 0 | AF43: =ROUND((EV43),6) -> 0 | AG43: =ROUND((AP43),6) -> 0 | AH43: =(EW43) -> 0 | AI43: =(EX43) -> 0 | AJ43: =(AS43) -> 0 | AK43: 726.04 | AL43: 726.04 | AM43: 0 | AN43: 0 | AO43: 0 | AP43: 0 | AQ43: 0 | AR43: 0 | AS43: 0 | AT43: 109 | AU43: 61 | AV43: 1 | AW43: 1 | AZ43: 1 | BA43: 1 | BB43: 1 | BC43: 9.84 | BH43: 3 | BI43: 1 | BM43: 23 | BN43: 0 | BP43: 0 | BQ43: 30 | BR43: 0 | BS43: 1 | BT43: 1 | BU43: 1 | BV43: 1 | BW43: 1 | BX43: 1 | BZ43: 109 | CA43: 61 | CE43: 1566 | CF43: 0 | CG43: 0 | CM43: 0 | CO43: 0 | CP43: =(P43+Q43+S43) -> 71442.34 | CQ43: =ROUND((ROUND((AC43*AW43*1),2)*BC43),2) -> 7144.23 | CR43: =(ROUND((ROUND(((ET43)*AV43*1),2)*BB43),2)+ROUND((ROUND(((AE43-(EU43))*AV43*1),2)*BS43),2)) -> 0 | CS43: =(ROUND((ROUND(((EU43)*AV43*1),2)*BS43),2)+ROUND((ROUND(((AE43-(EU43))*AV43*1),2)*BS43),2)) -> 0 | CT43: =ROUND((ROUND((AF43*AV43*1),2)*BA43),2) -> 0 | CU43: =AG43 -> 0 | CV43: =(AH43*AV43) -> 0 | CW43: =AI43 -> 0 | CX43: =AJ43 -> 0 | CY43: =(ROUND((((S43+ROUND((ROUND(((EU43)*AV43*1),2)*BS43),2))*AT43)/100),2)+ROUND(((ROUND((ROUND(((AE43-(EU43))*AV43*1),2)*BS43),2)*AT43)/100),2)) -> 0 | CZ43: =(ROUND((((S43+ROUND((ROUND(((EU43)*AV43*1),2)*BS43),2))*AU43)/100),2)+ROUND(((ROUND((ROUND(((AE43-(EU43))*AV43*1),2)*BS43),2)*AU43)/100),2)) -> 0 | DN43: 0 | DO43: 0 | DP43: 1 | DQ43: 1 | EE43: 85635395 | EF43: 30 | EG43: Строительные работы | EH43: 0 | EJ43: 1 | EK43: 23 | EL43: ТСН-2001.3-18. Отопление - внутренние устройства | EM43: ТСН-2001.3-18-1 | EQ43: 0 | ER43: 726.04 | ES43: 726.04 | ET43: 0 | EU43: 0 | EV43: 0 | EW43: 0 | EX43: 0 | EZ43: 5 | FC43: 1 | FD43: 18 | FF43: 8545 | FQ43: 0 | FR43: 0 | FS43: 0 | FX43: 109 | FY43: 61 | GA43: [8 545 / 1,22 / 9,84] + 2% Заг.скл | GD43: 1 | GF43: -1830095872 | GG43: 2 | GH43: 3 | GI43: 5 | GJ43: 0 | GK43: 0 | GL43: =ROUND(IF(AND(BH43=3,BI43=3,FS43<>0),P43,0),2) -> 0 | GM43: =ROUND(O43+X43+Y43,2)+GX43 -> 71442.34 | GN43: =IF(OR(BI43=0,BI43=1),GM43-GX43,0) -> 71442.34 | GO43: =IF(BI43=2,GM43-GX43,0) -> 0 | GP43: =IF(BI43=4,GM43-GX43,0) -> 0 | GR43: 1 | GS43: 1 | GT43: 0 | GV43: =ROUND((GT43),6) -> 0 | GW43: 1 | GX43: =ROUND(HC43*I43,2) -> 0 | HA43: 0 | HB43: 0 | HC43: =GV43*GW43 -> 0 | HE43: 0 | HF43: 2 | HS43: 0 | IK43: 0
A44: 18 | B44: 1 | C44: 21 | E44: 1,8 | F44: КА. п. 8 | G44: Сmальной nанельный paguamop PRADO Classic, mun 20, Bыcoma Н = 500 мм, PRADO Classic-20-500-1100 | I44: =I28*J44 -> 13 | J44: 9.7744361 | K44: 9.774436 | O44: =ROUND(CP44,2) -> 10164.18 | P44: =ROUND((ROUND((AC44*AW44*I44),2)*BC44),2) -> 10164.18 | Q44: =(ROUND((ROUND(((ET44)*AV44*I44),2)*BB44),2)+ROUND((ROUND(((AE44-(EU44))*AV44*I44),2)*BS44),2)) -> 0 | R44: =(ROUND((ROUND(((EU44)*AV44*I44),2)*BS44),2)+ROUND((ROUND(((AE44-(EU44))*AV44*I44),2)*BS44),2)) -> 0 | S44: =ROUND((ROUND((AF44*AV44*I44),2)*BA44),2) -> 0 | T44: =ROUND(CU44*I44,2) -> 0 | U44: =CV44*I44 -> 0 | V44: =CW44*I44 -> 0 | W44: =ROUND(CX44*I44,2) -> 0 | X44: =(ROUND((((S44+ROUND((ROUND(((EU44)*AV44*I44),2)*BS44),2))*AT44)/100),2)+ROUND(((ROUND((ROUND(((AE44-(EU44))*AV44*I44),2)*BS44),2)*AT44)/100),2)) -> 0 | Y44: =(ROUND((((S44+ROUND((ROUND(((EU44)*AV44*I44),2)*BS44),2))*AU44)/100),2)+ROUND(((ROUND((ROUND(((AE44-(EU44))*AV44*I44),2)*BS44),2)*AU44)/100),2)) -> 0 | AA44: 86551701 | AB44: =ROUND((AC44+AD44+AF44),6) -> 781.86 | AC44: =ROUND((ES44),6) -> 781.86 | AD44: =ROUND((((ET44)-(EU44))+AE44),6) -> 0 | AE44: =ROUND((EU44),6) -> 0 | AF44: =ROUND((EV44),6) -> 0 | AG44: =ROUND((AP44),6) -> 0 | AH44: =(EW44) -> 0 | AI44: =(EX44) -> 0 | AJ44: =(AS44) -> 0 | AK44: 781.86 | AL44: 781.86 | AM44: 0 | AN44: 0 | AO44: 0 | AP44: 0 | AQ44: 0 | AR44: 0 | AS44: 0 | AT44: 109 | AU44: 61 | AV44: 1 | AW44: 1 | AZ44: 1 | BA44: 1 | BB44: 1 | BC44: 1 | BH44: 3 | BI44: 1 | BM44: 23 | BN44: 0 | BP44: 0 | BQ44: 30 | BR44: 0 | BS44: 1 | BT44: 1 | BU44: 1 | BV44: 1 | BW44: 1 | BX44: 1 | BZ44: 109 | CA44: 61 | CE44: 1566 | CF44: 0 | CG44: 0 | CM44: 0 | CO44: 0 | CP44: =(P44+Q44+S44) -> 10164.18 | CQ44: =ROUND((ROUND((AC44*AW44*1),2)*BC44),2) -> 781.86 | CR44: =(ROUND((ROUND(((ET44)*AV44*1),2)*BB44),2)+ROUND((ROUND(((AE44-(EU44))*AV44*1),2)*BS44),2)) -> 0 | CS44: =(ROUND((ROUND(((EU44)*AV44*1),2)*BS44),2)+ROUND((ROUND(((AE44-(EU44))*AV44*1),2)*BS44),2)) -> 0 | CT44: =ROUND((ROUND((AF44*AV44*1),2)*BA44),2) -> 0 | CU44: =AG44 -> 0 | CV44: =(AH44*AV44) -> 0 | CW44: =AI44 -> 0 | CX44: =AJ44 -> 0 | CY44: =(ROUND((((S44+ROUND((ROUND(((EU44)*AV44*1),2)*BS44),2))*AT44)/100),2)+ROUND(((ROUND((ROUND(((AE44-(EU44))*AV44*1),2)*BS44),2)*AT44)/100),2)) -> 0 | CZ44: =(ROUND((((S44+ROUND((ROUND(((EU44)*AV44*1),2)*BS44),2))*AU44)/100),2)+ROUND(((ROUND((ROUND(((AE44-(EU44))*AV44*1),2)*BS44),2)*AU44)/100),2)) -> 0 | DN44: 0 | DO44: 0 | DP44: 1 | DQ44: 1 | EE44: 85635395 | EF44: 30 | EG44: Строительные работы | EH44: 0 | EJ44: 1 | EK44: 23 | EL44: ТСН-2001.3-18. Отопление - внутренние устройства | EM44: ТСН-2001.3-18-1 | EQ44: 0 | ER44: 0 | ES44: 781.86 | ET44: 0 | EU44: 0 | EV44: 0 | EW44: 0 | EX44: 0 | FQ44: 0 | FR44: 0 | FS44: 0 | FX44: 109 | FY44: 61 | GA44: [9 202 / 1,22 / 9,84] + 2% Заг.скл | GD44: 1 | GF44: -1794134594 | GG44: 2 | GH44: 4 | GI44: -2 | GJ44: 0 | GK44: 0 | GL44: =ROUND(IF(AND(BH44=3,BI44=3,FS44<>0),P44,0),2) -> 0 | GM44: =ROUND(O44+X44+Y44,2)+GX44 -> 10164.18 | GN44: =IF(OR(BI44=0,BI44=1),GM44-GX44,0) -> 10164.18 | GO44: =IF(BI44=2,GM44-GX44,0) -> 0 | GP44: =IF(BI44=4,GM44-GX44,0) -> 0 | GR44: 0 | GS44: 2 | GT44: 0 | GV44: =ROUND((GT44),6) -> 0 | GW44: 1 | GX44: =ROUND(HC44*I44,2) -> 0 | HA44: 0 | HB44: 0 | HC44: =GV44*GW44 -> 0 | HE44: 0 | HF44: 2 | HS44: 0 | IK44: 0
A45: 18 | B45: 1 | C45: 43 | E45: 1,8 | F45: КА. п. 8 | G45: Сmальной nанельный paguamop PRADO Classic, mun 20, Bыcoma Н = 500 мм, PRADO Classic-20-500-1100 | I45: =I29*J45 -> 13 | J45: 9.7744361 | K45: 9.774436 | O45: =ROUND(CP45,2) -> 100015.53 | P45: =ROUND((ROUND((AC45*AW45*I45),2)*BC45),2) -> 100015.53 | Q45: =(ROUND((ROUND(((ET45)*AV45*I45),2)*BB45),2)+ROUND((ROUND(((AE45-(EU45))*AV45*I45),2)*BS45),2)) -> 0 | R45: =(ROUND((ROUND(((EU45)*AV45*I45),2)*BS45),2)+ROUND((ROUND(((AE45-(EU45))*AV45*I45),2)*BS45),2)) -> 0 | S45: =ROUND((ROUND((AF45*AV45*I45),2)*BA45),2) -> 0 | T45: =ROUND(CU45*I45,2) -> 0 | U45: =CV45*I45 -> 0 | V45: =CW45*I45 -> 0 | W45: =ROUND(CX45*I45,2) -> 0 | X45: =(ROUND((((S45+ROUND((ROUND(((EU45)*AV45*I45),2)*BS45),2))*AT45)/100),2)+ROUND(((ROUND((ROUND(((AE45-(EU45))*AV45*I45),2)*BS45),2)*AT45)/100),2)) -> 0 | Y45: =(ROUND((((S45+ROUND((ROUND(((EU45)*AV45*I45),2)*BS45),2))*AU45)/100),2)+ROUND(((ROUND((ROUND(((AE45-(EU45))*AV45*I45),2)*BS45),2)*AU45)/100),2)) -> 0 | AA45: 86551703 | AB45: =ROUND((AC45+AD45+AF45),6) -> 781.86 | AC45: =ROUND((ES45),6) -> 781.86 | AD45: =ROUND((((ET45)-(EU45))+AE45),6) -> 0 | AE45: =ROUND((EU45),6) -> 0 | AF45: =ROUND((EV45),6) -> 0 | AG45: =ROUND((AP45),6) -> 0 | AH45: =(EW45) -> 0 | AI45: =(EX45) -> 0 | AJ45: =(AS45) -> 0 | AK45: 781.86 | AL45: 781.86 | AM45: 0 | AN45: 0 | AO45: 0 | AP45: 0 | AQ45: 0 | AR45: 0 | AS45: 0 | AT45: 109 | AU45: 61 | AV45: 1 | AW45: 1 | AZ45: 1 | BA45: 1 | BB45: 1 | BC45: 9.84 | BH45: 3 | BI45: 1 | BM45: 23 | BN45: 0 | BP45: 0 | BQ45: 30 | BR45: 0 | BS45: 1 | BT45: 1 | BU45: 1 | BV45: 1 | BW45: 1 | BX45: 1 | BZ45: 109 | CA45: 61 | CE45: 1566 | CF45: 0 | CG45: 0 | CM45: 0 | CO45: 0 | CP45: =(P45+Q45+S45) -> 100015.53 | CQ45: =ROUND((ROUND((AC45*AW45*1),2)*BC45),2) -> 7693.5 | CR45: =(ROUND((ROUND(((ET45)*AV45*1),2)*BB45),2)+ROUND((ROUND(((AE45-(EU45))*AV45*1),2)*BS45),2)) -> 0 | CS45: =(ROUND((ROUND(((EU45)*AV45*1),2)*BS45),2)+ROUND((ROUND(((AE45-(EU45))*AV45*1),2)*BS45),2)) -> 0 | CT45: =ROUND((ROUND((AF45*AV45*1),2)*BA45),2) -> 0 | CU45: =AG45 -> 0 | CV45: =(AH45*AV45) -> 0 | CW45: =AI45 -> 0 | CX45: =AJ45 -> 0 | CY45: =(ROUND((((S45+ROUND((ROUND(((EU45)*AV45*1),2)*BS45),2))*AT45)/100),2)+ROUND(((ROUND((ROUND(((AE45-(EU45))*AV45*1),2)*BS45),2)*AT45)/100),2)) -> 0 | CZ45: =(ROUND((((S45+ROUND((ROUND(((EU45)*AV45*1),2)*BS45),2))*AU45)/100),2)+ROUND(((ROUND((ROUND(((AE45-(EU45))*AV45*1),2)*BS45),2)*AU45)/100),2)) -> 0 | DN45: 0 | DO45: 0 | DP45: 1 | DQ45: 1 | EE45: 85635395 | EF45: 30 | EG45: Строительные работы | EH45: 0 | EJ45: 1 | EK45: 23 | EL45: ТСН-2001.3-18. Отопление - внутренние устройства | EM45: ТСН-2001.3-18-1 | EQ45: 0 | ER45: 781.86 | ES45: 781.86 | ET45: 0 | EU45: 0 | EV45: 0 | EW45: 0 | EX45: 0 | EZ45: 5 | FC45: 1 | FD45: 18 | FF45: 9202 | FQ45: 0 | FR45: 0 | FS45: 0 | FX45: 109 | FY45: 61 | GA45: [9 202 / 1,22 / 9,84] + 2% Заг.скл | GD45: 1 | GF45: -1794134594 | GG45: 2 | GH45: 3 | GI45: 5 | GJ45: 0 | GK45: 0 | GL45: =ROUND(IF(AND(BH45=3,BI45=3,FS45<>0),P45,0),2) -> 0 | GM45: =ROUND(O45+X45+Y45,2)+GX45 -> 100015.53 | GN45: =IF(OR(BI45=0,BI45=1),GM45-GX45,0) -> 100015.53 | GO45: =IF(BI45=2,GM45-GX45,0) -> 0 | GP45: =IF(BI45=4,GM45-GX45,0) -> 0 | GR45: 1 | GS45: 1 | GT45: 0 | GV45: =ROUND((GT45),6) -> 0 | GW45: 1 | GX45: =ROUND(HC45*I45,2) -> 0 | HA45: 0 | HB45: 0 | HC45: =GV45*GW45 -> 0 | HE45: 0 | HF45: 2 | HS45: 0 | IK45: 0
A46: 18 | B46: 1 | C46: 22 | E46: 1,9 | F46: КА. п. 9 | G46: Сmальной nанельный paguamop PRADO Classic, mun 20, Bыcoma Н = 500 мм, PRADO Classic-20-500-1200 | I46: =I28*J46 -> 18 | J46: 13.533835 | K46: 13.533835 | O46: =ROUND(CP46,2) -> 15081.3 | P46: =ROUND((ROUND((AC46*AW46*I46),2)*BC46),2) -> 15081.3 | Q46: =(ROUND((ROUND(((ET46)*AV46*I46),2)*BB46),2)+ROUND((ROUND(((AE46-(EU46))*AV46*I46),2)*BS46),2)) -> 0 | R46: =(ROUND((ROUND(((EU46)*AV46*I46),2)*BS46),2)+ROUND((ROUND(((AE46-(EU46))*AV46*I46),2)*BS46),2)) -> 0 | S46: =ROUND((ROUND((AF46*AV46*I46),2)*BA46),2) -> 0 | T46: =ROUND(CU46*I46,2) -> 0 | U46: =CV46*I46 -> 0 | V46: =CW46*I46 -> 0 | W46: =ROUND(CX46*I46,2) -> 0 | X46: =(ROUND((((S46+ROUND((ROUND(((EU46)*AV46*I46),2)*BS46),2))*AT46)/100),2)+ROUND(((ROUND((ROUND(((AE46-(EU46))*AV46*I46),2)*BS46),2)*AT46)/100),2)) -> 0 | Y46: =(ROUND((((S46+ROUND((ROUND(((EU46)*AV46*I46),2)*BS46),2))*AU46)/100),2)+ROUND(((ROUND((ROUND(((AE46-(EU46))*AV46*I46),2)*BS46),2)*AU46)/100),2)) -> 0 | AA46: 86551701 | AB46: =ROUND((AC46+AD46+AF46),6) -> 837.85 | AC46: =ROUND((ES46),6) -> 837.85 | AD46: =ROUND((((ET46)-(EU46))+AE46),6) -> 0 | AE46: =ROUND((EU46),6) -> 0 | AF46: =ROUND((EV46),6) -> 0 | AG46: =ROUND((AP46),6) -> 0 | AH46: =(EW46) -> 0 | AI46: =(EX46) -> 0 | AJ46: =(AS46) -> 0 | AK46: 837.85 | AL46: 837.85 | AM46: 0 | AN46: 0 | AO46: 0 | AP46: 0 | AQ46: 0 | AR46: 0 | AS46: 0 | AT46: 109 | AU46: 61 | AV46: 1 | AW46: 1 | AZ46: 1 | BA46: 1 | BB46: 1 | BC46: 1 | BH46: 3 | BI46: 1 | BM46: 23 | BN46: 0 | BP46: 0 | BQ46: 30 | BR46: 0 | BS46: 1 | BT46: 1 | BU46: 1 | BV46: 1 | BW46: 1 | BX46: 1 | BZ46: 109 | CA46: 61 | CE46: 1566 | CF46: 0 | CG46: 0 | CM46: 0 | CO46: 0 | CP46: =(P46+Q46+S46) -> 15081.3 | CQ46: =ROUND((ROUND((AC46*AW46*1),2)*BC46),2) -> 837.85 | CR46: =(ROUND((ROUND(((ET46)*AV46*1),2)*BB46),2)+ROUND((ROUND(((AE46-(EU46))*AV46*1),2)*BS46),2)) -> 0 | CS46: =(ROUND((ROUND(((EU46)*AV46*1),2)*BS46),2)+ROUND((ROUND(((AE46-(EU46))*AV46*1),2)*BS46),2)) -> 0 | CT46: =ROUND((ROUND((AF46*AV46*1),2)*BA46),2) -> 0 | CU46: =AG46 -> 0 | CV46: =(AH46*AV46) -> 0 | CW46: =AI46 -> 0 | CX46: =AJ46 -> 0 | CY46: =(ROUND((((S46+ROUND((ROUND(((EU46)*AV46*1),2)*BS46),2))*AT46)/100),2)+ROUND(((ROUND((ROUND(((AE46-(EU46))*AV46*1),2)*BS46),2)*AT46)/100),2)) -> 0 | CZ46: =(ROUND((((S46+ROUND((ROUND(((EU46)*AV46*1),2)*BS46),2))*AU46)/100),2)+ROUND(((ROUND((ROUND(((AE46-(EU46))*AV46*1),2)*BS46),2)*AU46)/100),2)) -> 0 | DN46: 0 | DO46: 0 | DP46: 1 | DQ46: 1 | EE46: 85635395 | EF46: 30 | EG46: Строительные работы | EH46: 0 | EJ46: 1 | EK46: 23 | EL46: ТСН-2001.3-18. Отопление - внутренние устройства | EM46: ТСН-2001.3-18-1 | EQ46: 0 | ER46: 0 | ES46: 837.85 | ET46: 0 | EU46: 0 | EV46: 0 | EW46: 0 | EX46: 0 | FQ46: 0 | FR46: 0 | FS46: 0 | FX46: 109 | FY46: 61 | GA46: [9 861 / 1,22 / 9,84] + 2% Заг.скл | GD46: 1 | GF46: 708020071 | GG46: 2 | GH46: 4 | GI46: -2 | GJ46: 0 | GK46: 0 | GL46: =ROUND(IF(AND(BH46=3,BI46=3,FS46<>0),P46,0),2) -> 0 | GM46: =ROUND(O46+X46+Y46,2)+GX46 -> 15081.3 | GN46: =IF(OR(BI46=0,BI46=1),GM46-GX46,0) -> 15081.3 | GO46: =IF(BI46=2,GM46-GX46,0) -> 0 | GP46: =IF(BI46=4,GM46-GX46,0) -> 0 | GR46: 0 | GS46: 2 | GT46: 0 | GV46: =ROUND((GT46),6) -> 0 | GW46: 1 | GX46: =ROUND(HC46*I46,2) -> 0 | HA46: 0 | HB46: 0 | HC46: =GV46*GW46 -> 0 | HE46: 0 | HF46: 2 | HS46: 0 | IK46: 0
A47: 18 | B47: 1 | C47: 44 | E47: 1,9 | F47: КА. п. 9 | G47: Сmальной nанельный paguamop PRADO Classic, mun 20, Bыcoma Н = 500 мм, PRADO Classic-20-500-1200 | I47: =I29*J47 -> 18 | J47: 13.533835 | K47: 13.533835 | O47: =ROUND(CP47,2) -> 148399.99 | P47: =ROUND((ROUND((AC47*AW47*I47),2)*BC47),2) -> 148399.99 | Q47: =(ROUND((ROUND(((ET47)*AV47*I47),2)*BB47),2)+ROUND((ROUND(((AE47-(EU47))*AV47*I47),2)*BS47),2)) -> 0 | R47: =(ROUND((ROUND(((EU47)*AV47*I47),2)*BS47),2)+ROUND((ROUND(((AE47-(EU47))*AV47*I47),2)*BS47),2)) -> 0 | S47: =ROUND((ROUND((AF47*AV47*I47),2)*BA47),2) -> 0 | T47: =ROUND(CU47*I47,2) -> 0 | U47: =CV47*I47 -> 0 | V47: =CW47*I47 -> 0 | W47: =ROUND(CX47*I47,2) -> 0 | X47: =(ROUND((((S47+ROUND((ROUND(((EU47)*AV47*I47),2)*BS47),2))*AT47)/100),2)+ROUND(((ROUND((ROUND(((AE47-(EU47))*AV47*I47),2)*BS47),2)*AT47)/100),2)) -> 0 | Y47: =(ROUND((((S47+ROUND((ROUND(((EU47)*AV47*I47),2)*BS47),2))*AU47)/100),2)+ROUND(((ROUND((ROUND(((AE47-(EU47))*AV47*I47),2)*BS47),2)*AU47)/100),2)) -> 0 | AA47: 86551703 | AB47: =ROUND((AC47+AD47+AF47),6) -> 837.85 | AC47: =ROUND((ES47),6) -> 837.85 | AD47: =ROUND((((ET47)-(EU47))+AE47),6) -> 0 | AE47: =ROUND((EU47),6) -> 0 | AF47: =ROUND((EV47),6) -> 0 | AG47: =ROUND((AP47),6) -> 0 | AH47: =(EW47) -> 0 | AI47: =(EX47) -> 0 | AJ47: =(AS47) -> 0 | AK47: 837.85 | AL47: 837.85 | AM47: 0 | AN47: 0 | AO47: 0 | AP47: 0 | AQ47: 0 | AR47: 0 | AS47: 0 | AT47: 109 | AU47: 61 | AV47: 1 | AW47: 1 | AZ47: 1 | BA47: 1 | BB47: 1 | BC47: 9.84 | BH47: 3 | BI47: 1 | BM47: 23 | BN47: 0 | BP47: 0 | BQ47: 30 | BR47: 0 | BS47: 1 | BT47: 1 | BU47: 1 | BV47: 1 | BW47: 1 | BX47: 1 | BZ47: 109 | CA47: 61 | CE47: 1566 | CF47: 0 | CG47: 0 | CM47: 0 | CO47: 0 | CP47: =(P47+Q47+S47) -> 148399.99 | CQ47: =ROUND((ROUND((AC47*AW47*1),2)*BC47),2) -> 8244.44 | CR47: =(ROUND((ROUND(((ET47)*AV47*1),2)*BB47),2)+ROUND((ROUND(((AE47-(EU47))*AV47*1),2)*BS47),2)) -> 0 | CS47: =(ROUND((ROUND(((EU47)*AV47*1),2)*BS47),2)+ROUND((ROUND(((AE47-(EU47))*AV47*1),2)*BS47),2)) -> 0 | CT47: =ROUND((ROUND((AF47*AV47*1),2)*BA47),2) -> 0 | CU47: =AG47 -> 0 | CV47: =(AH47*AV47) -> 0 | CW47: =AI47 -> 0 | CX47: =AJ47 -> 0 | CY47: =(ROUND((((S47+ROUND((ROUND(((EU47)*AV47*1),2)*BS47),2))*AT47)/100),2)+ROUND(((ROUND((ROUND(((AE47-(EU47))*AV47*1),2)*BS47),2)*AT47)/100),2)) -> 0 | CZ47: =(ROUND((((S47+ROUND((ROUND(((EU47)*AV47*1),2)*BS47),2))*AU47)/100),2)+ROUND(((ROUND((ROUND(((AE47-(EU47))*AV47*1),2)*BS47),2)*AU47)/100),2)) -> 0 | DN47: 0 | DO47: 0 | DP47: 1 | DQ47: 1 | EE47: 85635395 | EF47: 30 | EG47: Строительные работы | EH47: 0 | EJ47: 1 | EK47: 23 | EL47: ТСН-2001.3-18. Отопление - внутренние устройства | EM47: ТСН-2001.3-18-1 | EQ47: 0 | ER47: 837.85 | ES47: 837.85 | ET47: 0 | EU47: 0 | EV47: 0 | EW47: 0 | EX47: 0 | EZ47: 5 | FC47: 1 | FD47: 18 | FF47: 9861 | FQ47: 0 | FR47: 0 | FS47: 0 | FX47: 109 | FY47: 61 | GA47: [9 861 / 1,22 / 9,84] + 2% Заг.скл | GD47: 1 | GF47: 708020071 | GG47: 2 | GH47: 3 | GI47: 5 | GJ47: 0 | GK47: 0 | GL47: =ROUND(IF(AND(BH47=3,BI47=3,FS47<>0),P47,0),2) -> 0 | GM47: =ROUND(O47+X47+Y47,2)+GX47 -> 148399.99 | GN47: =IF(OR(BI47=0,BI47=1),GM47-GX47,0) -> 148399.99 | GO47: =IF(BI47=2,GM47-GX47,0) -> 0 | GP47: =IF(BI47=4,GM47-GX47,0) -> 0 | GR47: 1 | GS47: 1 | GT47: 0 | GV47: =ROUND((GT47),6) -> 0 | GW47: 1 | GX47: =ROUND(HC47*I47,2) -> 0 | HA47: 0 | HB47: 0 | HC47: =GV47*GW47 -> 0 | HE47: 0 | HF47: 2 | HS47: 0 | IK47: 0
A48: 18 | B48: 1 | C48: 11 | E48: 1,10 | F48: КА. п. 10 | G48: Сmальной nанельный paguamop PRADO Classic, mun 20, Bыcoma Н = 500 мм, PRADO Classic-20-500-1300 | I48: =I28*J48 -> 6 | J48: 4.5112782 | K48: 4.511278 | O48: =ROUND(CP48,2) -> 5092.32 | P48: =ROUND((ROUND((AC48*AW48*I48),2)*BC48),2) -> 5092.32 | Q48: =(ROUND((ROUND(((ET48)*AV48*I48),2)*BB48),2)+ROUND((ROUND(((AE48-(EU48))*AV48*I48),2)*BS48),2)) -> 0 | R48: =(ROUND((ROUND(((EU48)*AV48*I48),2)*BS48),2)+ROUND((ROUND(((AE48-(EU48))*AV48*I48),2)*BS48),2)) -> 0 | S48: =ROUND((ROUND((AF48*AV48*I48),2)*BA48),2) -> 0 | T48: =ROUND(CU48*I48,2) -> 0 | U48: =CV48*I48 -> 0 | V48: =CW48*I48 -> 0 | W48: =ROUND(CX48*I48,2) -> 0 | X48: =(ROUND((((S48+ROUND((ROUND(((EU48)*AV48*I48),2)*BS48),2))*AT48)/100),2)+ROUND(((ROUND((ROUND(((AE48-(EU48))*AV48*I48),2)*BS48),2)*AT48)/100),2)) -> 0 | Y48: =(ROUND((((S48+ROUND((ROUND(((EU48)*AV48*I48),2)*BS48),2))*AU48)/100),2)+ROUND(((ROUND((ROUND(((AE48-(EU48))*AV48*I48),2)*BS48),2)*AU48)/100),2)) -> 0 | AA48: 86551701 | AB48: =ROUND((AC48+AD48+AF48),6) -> 848.72 | AC48: =ROUND((ES48),6) -> 848.72 | AD48: =ROUND((((ET48)-(EU48))+AE48),6) -> 0 | AE48: =ROUND((EU48),6) -> 0 | AF48: =ROUND((EV48),6) -> 0 | AG48: =ROUND((AP48),6) -> 0 | AH48: =(EW48) -> 0 | AI48: =(EX48) -> 0 | AJ48: =(AS48) -> 0 | AK48: 848.72 | AL48: 848.72 | AM48: 0 | AN48: 0 | AO48: 0 | AP48: 0 | AQ48: 0 | AR48: 0 | AS48: 0 | AT48: 109 | AU48: 61 | AV48: 1 | AW48: 1 | AZ48: 1 | BA48: 1 | BB48: 1 | BC48: 1 | BH48: 3 | BI48: 1 | BM48: 23 | BN48: 0 | BP48: 0 | BQ48: 30 | BR48: 0 | BS48: 1 | BT48: 1 | BU48: 1 | BV48: 1 | BW48: 1 | BX48: 1 | BZ48: 109 | CA48: 61 | CE48: 1566 | CF48: 0 | CG48: 0 | CM48: 0 | CO48: 0 | CP48: =(P48+Q48+S48) -> 5092.32 | CQ48: =ROUND((ROUND((AC48*AW48*1),2)*BC48),2) -> 848.72 | CR48: =(ROUND((ROUND(((ET48)*AV48*1),2)*BB48),2)+ROUND((ROUND(((AE48-(EU48))*AV48*1),2)*BS48),2)) -> 0 | CS48: =(ROUND((ROUND(((EU48)*AV48*1),2)*BS48),2)+ROUND((ROUND(((AE48-(EU48))*AV48*1),2)*BS48),2)) -> 0 | CT48: =ROUND((ROUND((AF48*AV48*1),2)*BA48),2) -> 0 | CU48: =AG48 -> 0 | CV48: =(AH48*AV48) -> 0 | CW48: =AI48 -> 0 | CX48: =AJ48 -> 0 | CY48: =(ROUND((((S48+ROUND((ROUND(((EU48)*AV48*1),2)*BS48),2))*AT48)/100),2)+ROUND(((ROUND((ROUND(((AE48-(EU48))*AV48*1),2)*BS48),2)*AT48)/100),2)) -> 0 | CZ48: =(ROUND((((S48+ROUND((ROUND(((EU48)*AV48*1),2)*BS48),2))*AU48)/100),2)+ROUND(((ROUND((ROUND(((AE48-(EU48))*AV48*1),2)*BS48),2)*AU48)/100),2)) -> 0 | DN48: 0 | DO48: 0 | DP48: 1 | DQ48: 1 | EE48: 85635395 | EF48: 30 | EG48: Строительные работы | EH48: 0 | EJ48: 1 | EK48: 23 | EL48: ТСН-2001.3-18. Отопление - внутренние устройства | EM48: ТСН-2001.3-18-1 | EQ48: 0 | ER48: 0 | ES48: 848.72 | ET48: 0 | EU48: 0 | EV48: 0 | EW48: 0 | EX48: 0 | FQ48: 0 | FR48: 0 | FS48: 0 | FX48: 109 | FY48: 61 | GA48: [9 989 / 1,22 / 9,84] + 2% Заг.скл | GD48: 1 | GF48: -823927281 | GG48: 2 | GH48: 4 | GI48: -2 | GJ48: 0 | GK48: 0 | GL48: =ROUND(IF(AND(BH48=3,BI48=3,FS48<>0),P48,0),2) -> 0 | GM48: =ROUND(O48+X48+Y48,2)+GX48 -> 5092.32 | GN48: =IF(OR(BI48=0,BI48=1),GM48-GX48,0) -> 5092.32 | GO48: =IF(BI48=2,GM48-GX48,0) -> 0 | GP48: =IF(BI48=4,GM48-GX48,0) -> 0 | GR48: 0 | GS48: 2 | GT48: 0 | GV48: =ROUND((GT48),6) -> 0 | GW48: 1 | GX48: =ROUND(HC48*I48,2) -> 0 | HA48: 0 | HB48: 0 | HC48: =GV48*GW48 -> 0 | HE48: 0 | HF48: 2 | HS48: 0 | IK48: 0
A49: 18 | B49: 1 | C49: 33 | E49: 1,10 | F49: КА. п. 10 | G49: Сmальной nанельный paguamop PRADO Classic, mun 20, Bыcoma Н = 500 мм, PRADO Classic-20-500-1300 | I49: =I29*J49 -> 6 | J49: 4.5112782 | K49: 4.511278 | O49: =ROUND(CP49,2) -> 50108.43 | P49: =ROUND((ROUND((AC49*AW49*I49),2)*BC49),2) -> 50108.43 | Q49: =(ROUND((ROUND(((ET49)*AV49*I49),2)*BB49),2)+ROUND((ROUND(((AE49-(EU49))*AV49*I49),2)*BS49),2)) -> 0 | R49: =(ROUND((ROUND(((EU49)*AV49*I49),2)*BS49),2)+ROUND((ROUND(((AE49-(EU49))*AV49*I49),2)*BS49),2)) -> 0 | S49: =ROUND((ROUND((AF49*AV49*I49),2)*BA49),2) -> 0 | T49: =ROUND(CU49*I49,2) -> 0 | U49: =CV49*I49 -> 0 | V49: =CW49*I49 -> 0 | W49: =ROUND(CX49*I49,2) -> 0 | X49: =(ROUND((((S49+ROUND((ROUND(((EU49)*AV49*I49),2)*BS49),2))*AT49)/100),2)+ROUND(((ROUND((ROUND(((AE49-(EU49))*AV49*I49),2)*BS49),2)*AT49)/100),2)) -> 0 | Y49: =(ROUND((((S49+ROUND((ROUND(((EU49)*AV49*I49),2)*BS49),2))*AU49)/100),2)+ROUND(((ROUND((ROUND(((AE49-(EU49))*AV49*I49),2)*BS49),2)*AU49)/100),2)) -> 0 | AA49: 86551703 | AB49: =ROUND((AC49+AD49+AF49),6) -> 848.72 | AC49: =ROUND((ES49),6) -> 848.72 | AD49: =ROUND((((ET49)-(EU49))+AE49),6) -> 0 | AE49: =ROUND((EU49),6) -> 0 | AF49: =ROUND((EV49),6) -> 0 | AG49: =ROUND((AP49),6) -> 0 | AH49: =(EW49) -> 0 | AI49: =(EX49) -> 0 | AJ49: =(AS49) -> 0 | AK49: 848.72 | AL49: 848.72 | AM49: 0 | AN49: 0 | AO49: 0 | AP49: 0 | AQ49: 0 | AR49: 0 | AS49: 0 | AT49: 109 | AU49: 61 | AV49: 1 | AW49: 1 | AZ49: 1 | BA49: 1 | BB49: 1 | BC49: 9.84 | BH49: 3 | BI49: 1 | BM49: 23 | BN49: 0 | BP49: 0 | BQ49: 30 | BR49: 0 | BS49: 1 | BT49: 1 | BU49: 1 | BV49: 1 | BW49: 1 | BX49: 1 | BZ49: 109 | CA49: 61 | CE49: 1566 | CF49: 0 | CG49: 0 | CM49: 0 | CO49: 0 | CP49: =(P49+Q49+S49) -> 50108.43 | CQ49: =ROUND((ROUND((AC49*AW49*1),2)*BC49),2) -> 8351.4 | CR49: =(ROUND((ROUND(((ET49)*AV49*1),2)*BB49),2)+ROUND((ROUND(((AE49-(EU49))*AV49*1),2)*BS49),2)) -> 0 | CS49: =(ROUND((ROUND(((EU49)*AV49*1),2)*BS49),2)+ROUND((ROUND(((AE49-(EU49))*AV49*1),2)*BS49),2)) -> 0 | CT49: =ROUND((ROUND((AF49*AV49*1),2)*BA49),2) -> 0 | CU49: =AG49 -> 0 | CV49: =(AH49*AV49) -> 0 | CW49: =AI49 -> 0 | CX49: =AJ49 -> 0 | CY49: =(ROUND((((S49+ROUND((ROUND(((EU49)*AV49*1),2)*BS49),2))*AT49)/100),2)+ROUND(((ROUND((ROUND(((AE49-(EU49))*AV49*1),2)*BS49),2)*AT49)/100),2)) -> 0 | CZ49: =(ROUND((((S49+ROUND((ROUND(((EU49)*AV49*1),2)*BS49),2))*AU49)/100),2)+ROUND(((ROUND((ROUND(((AE49-(EU49))*AV49*1),2)*BS49),2)*AU49)/100),2)) -> 0 | DN49: 0 | DO49: 0 | DP49: 1 | DQ49: 1 | EE49: 85635395 | EF49: 30 | EG49: Строительные работы | EH49: 0 | EJ49: 1 | EK49: 23 | EL49: ТСН-2001.3-18. Отопление - внутренние устройства | EM49: ТСН-2001.3-18-1 | EQ49: 0 | ER49: 848.72 | ES49: 848.72 | ET49: 0 | EU49: 0 | EV49: 0 | EW49: 0 | EX49: 0 | EZ49: 5 | FC49: 1 | FD49: 18 | FF49: 9989 | FQ49: 0 | FR49: 0 | FS49: 0 | FX49: 109 | FY49: 61 | GA49: [9 989 / 1,22 / 9,84] + 2% Заг.скл | GD49: 1 | GF49: -823927281 | GG49: 2 | GH49: 3 | GI49: 5 | GJ49: 0 | GK49: 0 | GL49: =ROUND(IF(AND(BH49=3,BI49=3,FS49<>0),P49,0),2) -> 0 | GM49: =ROUND(O49+X49+Y49,2)+GX49 -> 50108.43 | GN49: =IF(OR(BI49=0,BI49=1),GM49-GX49,0) -> 50108.43 | GO49: =IF(BI49=2,GM49-GX49,0) -> 0 | GP49: =IF(BI49=4,GM49-GX49,0) -> 0 | GR49: 1 | GS49: 1 | GT49: 0 | GV49: =ROUND((GT49),6) -> 0 | GW49: 1 | GX49: =ROUND(HC49*I49,2) -> 0 | HA49: 0 | HB49: 0 | HC49: =GV49*GW49 -> 0 | HE49: 0 | HF49: 2 | HS49: 0 | IK49: 0
A50: 18 | B50: 1 | C50: 12 | E50: 1,11 | F50: КА. п. 11 | G50: Сmальной nанельный paguamop PRADO Classic, mun 20, Bыcoma Н = 500 мм, PRADO Classic-20-500-1400 | I50: =I28*J50 -> 17 | J50: 12.781955 | K50: 12.781955 | O50: =ROUND(CP50,2) -> 16265.6 | P50: =ROUND((ROUND((AC50*AW50*I50),2)*BC50),2) -> 16265.6 | Q50: =(ROUND((ROUND(((ET50)*AV50*I50),2)*BB50),2)+ROUND((ROUND(((AE50-(EU50))*AV50*I50),2)*BS50),2)) -> 0 | R50: =(ROUND((ROUND(((EU50)*AV50*I50),2)*BS50),2)+ROUND((ROUND(((AE50-(EU50))*AV50*I50),2)*BS50),2)) -> 0 | S50: =ROUND((ROUND((AF50*AV50*I50),2)*BA50),2) -> 0 | T50: =ROUND(CU50*I50,2) -> 0 | U50: =CV50*I50 -> 0 | V50: =CW50*I50 -> 0 | W50: =ROUND(CX50*I50,2) -> 0 | X50: =(ROUND((((S50+ROUND((ROUND(((EU50)*AV50*I50),2)*BS50),2))*AT50)/100),2)+ROUND(((ROUND((ROUND(((AE50-(EU50))*AV50*I50),2)*BS50),2)*AT50)/100),2)) -> 0 | Y50: =(ROUND((((S50+ROUND((ROUND(((EU50)*AV50*I50),2)*BS50),2))*AU50)/100),2)+ROUND(((ROUND((ROUND(((AE50-(EU50))*AV50*I50),2)*BS50),2)*AU50)/100),2)) -> 0 | AA50: 86551701 | AB50: =ROUND((AC50+AD50+AF50),6) -> 956.8 | AC50: =ROUND((ES50),6) -> 956.8 | AD50: =ROUND((((ET50)-(EU50))+AE50),6) -> 0 | AE50: =ROUND((EU50),6) -> 0 | AF50: =ROUND((EV50),6) -> 0 | AG50: =ROUND((AP50),6) -> 0 | AH50: =(EW50) -> 0 | AI50: =(EX50) -> 0 | AJ50: =(AS50) -> 0 | AK50: 956.8 | AL50: 956.8 | AM50: 0 | AN50: 0 | AO50: 0 | AP50: 0 | AQ50: 0 | AR50: 0 | AS50: 0 | AT50: 109 | AU50: 61 | AV50: 1 | AW50: 1 | AZ50: 1 | BA50: 1 | BB50: 1 | BC50: 1 | BH50: 3 | BI50: 1 | BM50: 23 | BN50: 0 | BP50: 0 | BQ50: 30 | BR50: 0 | BS50: 1 | BT50: 1 | BU50: 1 | BV50: 1 | BW50: 1 | BX50: 1 | BZ50: 109 | CA50: 61 | CE50: 1566 | CF50: 0 | CG50: 0 | CM50: 0 | CO50: 0 | CP50: =(P50+Q50+S50) -> 16265.6 | CQ50: =ROUND((ROUND((AC50*AW50*1),2)*BC50),2) -> 956.8 | CR50: =(ROUND((ROUND(((ET50)*AV50*1),2)*BB50),2)+ROUND((ROUND(((AE50-(EU50))*AV50*1),2)*BS50),2)) -> 0 | CS50: =(ROUND((ROUND(((EU50)*AV50*1),2)*BS50),2)+ROUND((ROUND(((AE50-(EU50))*AV50*1),2)*BS50),2)) -> 0 | CT50: =ROUND((ROUND((AF50*AV50*1),2)*BA50),2) -> 0 | CU50: =AG50 -> 0 | CV50: =(AH50*AV50) -> 0 | CW50: =AI50 -> 0 | CX50: =AJ50 -> 0 | CY50: =(ROUND((((S50+ROUND((ROUND(((EU50)*AV50*1),2)*BS50),2))*AT50)/100),2)+ROUND(((ROUND((ROUND(((AE50-(EU50))*AV50*1),2)*BS50),2)*AT50)/100),2)) -> 0 | CZ50: =(ROUND((((S50+ROUND((ROUND(((EU50)*AV50*1),2)*BS50),2))*AU50)/100),2)+ROUND(((ROUND((ROUND(((AE50-(EU50))*AV50*1),2)*BS50),2)*AU50)/100),2)) -> 0 | DN50: 0 | DO50: 0 | DP50: 1 | DQ50: 1 | EE50: 85635395 | EF50: 30 | EG50: Строительные работы | EH50: 0 | EJ50: 1 | EK50: 23 | EL50: ТСН-2001.3-18. Отопление - внутренние устройства | EM50: ТСН-2001.3-18-1 | EQ50: 0 | ER50: 0 | ES50: 956.8 | ET50: 0 | EU50: 0 | EV50: 0 | EW50: 0 | EX50: 0 | FQ50: 0 | FR50: 0 | FS50: 0 | FX50: 109 | FY50: 61 | GA50: [11 261 / 1,22 / 9,84] + 2% Заг.скл | GD50: 1 | GF50: 540672148 | GG50: 2 | GH50: 4 | GI50: -2 | GJ50: 0 | GK50: 0 | GL50: =ROUND(IF(AND(BH50=3,BI50=3,FS50<>0),P50,0),2) -> 0 | GM50: =ROUND(O50+X50+Y50,2)+GX50 -> 16265.6 | GN50: =IF(OR(BI50=0,BI50=1),GM50-GX50,0) -> 16265.6 | GO50: =IF(BI50=2,GM50-GX50,0) -> 0 | GP50: =IF(BI50=4,GM50-GX50,0) -> 0 | GR50: 0 | GS50: 2 | GT50: 0 | GV50: =ROUND((GT50),6) -> 0 | GW50: 1 | GX50: =ROUND(HC50*I50,2) -> 0 | HA50: 0 | HB50: 0 | HC50: =GV50*GW50 -> 0 | HE50: 0 | HF50: 2 | HS50: 0 | IK50: 0
A51: 18 | B51: 1 | C51: 34 | E51: 1,11 | F51: КА. п. 11 | G51: Сmальной nанельный paguamop PRADO Classic, mun 20, Bыcoma Н = 500 мм, PRADO Classic-20-500-1400 | I51: =I29*J51 -> 17 | J51: 12.781955 | K51: 12.781955 | O51: =ROUND(CP51,2) -> 160053.5 | P51: =ROUND((ROUND((AC51*AW51*I51),2)*BC51),2) -> 160053.5 | Q51: =(ROUND((ROUND(((ET51)*AV51*I51),2)*BB51),2)+ROUND((ROUND(((AE51-(EU51))*AV51*I51),2)*BS51),2)) -> 0 | R51: =(ROUND((ROUND(((EU51)*AV51*I51),2)*BS51),2)+ROUND((ROUND(((AE51-(EU51))*AV51*I51),2)*BS51),2)) -> 0 | S51: =ROUND((ROUND((AF51*AV51*I51),2)*BA51),2) -> 0 | T51: =ROUND(CU51*I51,2) -> 0 | U51: =CV51*I51 -> 0 | V51: =CW51*I51 -> 0 | W51: =ROUND(CX51*I51,2) -> 0 | X51: =(ROUND((((S51+ROUND((ROUND(((EU51)*AV51*I51),2)*BS51),2))*AT51)/100),2)+ROUND(((ROUND((ROUND(((AE51-(EU51))*AV51*I51),2)*BS51),2)*AT51)/100),2)) -> 0 | Y51: =(ROUND((((S51+ROUND((ROUND(((EU51)*AV51*I51),2)*BS51),2))*AU51)/100),2)+ROUND(((ROUND((ROUND(((AE51-(EU51))*AV51*I51),2)*BS51),2)*AU51)/100),2)) -> 0 | AA51: 86551703 | AB51: =ROUND((AC51+AD51+AF51),6) -> 956.8 | AC51: =ROUND((ES51),6) -> 956.8 | AD51: =ROUND((((ET51)-(EU51))+AE51),6) -> 0 | AE51: =ROUND((EU51),6) -> 0 | AF51: =ROUND((EV51),6) -> 0 | AG51: =ROUND((AP51),6) -> 0 | AH51: =(EW51) -> 0 | AI51: =(EX51) -> 0 | AJ51: =(AS51) -> 0 | AK51: 956.8 | AL51: 956.8 | AM51: 0 | AN51: 0 | AO51: 0 | AP51: 0 | AQ51: 0 | AR51: 0 | AS51: 0 | AT51: 109 | AU51: 61 | AV51: 1 | AW51: 1 | AZ51: 1 | BA51: 1 | BB51: 1 | BC51: 9.84 | BH51: 3 | BI51: 1 | BM51: 23 | BN51: 0 | BP51: 0 | BQ51: 30 | BR51: 0 | BS51: 1 | BT51: 1 | BU51: 1 | BV51: 1 | BW51: 1 | BX51: 1 | BZ51: 109 | CA51: 61 | CE51: 1566 | CF51: 0 | CG51: 0 | CM51: 0 | CO51: 0 | CP51: =(P51+Q51+S51) -> 160053.5 | CQ51: =ROUND((ROUND((AC51*AW51*1),2)*BC51),2) -> 9414.91 | CR51: =(ROUND((ROUND(((ET51)*AV51*1),2)*BB51),2)+ROUND((ROUND(((AE51-(EU51))*AV51*1),2)*BS51),2)) -> 0 | CS51: =(ROUND((ROUND(((EU51)*AV51*1),2)*BS51),2)+ROUND((ROUND(((AE51-(EU51))*AV51*1),2)*BS51),2)) -> 0 | CT51: =ROUND((ROUND((AF51*AV51*1),2)*BA51),2) -> 0 | CU51: =AG51 -> 0 | CV51: =(AH51*AV51) -> 0 | CW51: =AI51 -> 0 | CX51: =AJ51 -> 0 | CY51: =(ROUND((((S51+ROUND((ROUND(((EU51)*AV51*1),2)*BS51),2))*AT51)/100),2)+ROUND(((ROUND((ROUND(((AE51-(EU51))*AV51*1),2)*BS51),2)*AT51)/100),2)) -> 0 | CZ51: =(ROUND((((S51+ROUND((ROUND(((EU51)*AV51*1),2)*BS51),2))*AU51)/100),2)+ROUND(((ROUND((ROUND(((AE51-(EU51))*AV51*1),2)*BS51),2)*AU51)/100),2)) -> 0 | DN51: 0 | DO51: 0 | DP51: 1 | DQ51: 1 | EE51: 85635395 | EF51: 30 | EG51: Строительные работы | EH51: 0 | EJ51: 1 | EK51: 23 | EL51: ТСН-2001.3-18. Отопление - внутренние устройства | EM51: ТСН-2001.3-18-1 | EQ51: 0 | ER51: 956.8 | ES51: 956.8 | ET51: 0 | EU51: 0 | EV51: 0 | EW51: 0 | EX51: 0 | EZ51: 5 | FC51: 1 | FD51: 18 | FF51: 11261 | FQ51: 0 | FR51: 0 | FS51: 0 | FX51: 109 | FY51: 61 | GA51: [11 261 / 1,22 / 9,84] + 2% Заг.скл | GD51: 1 | GF51: 540672148 | GG51: 2 | GH51: 3 | GI51: 5 | GJ51: 0 | GK51: 0 | GL51: =ROUND(IF(AND(BH51=3,BI51=3,FS51<>0),P51,0),2) -> 0 | GM51: =ROUND(O51+X51+Y51,2)+GX51 -> 160053.5 | GN51: =IF(OR(BI51=0,BI51=1),GM51-GX51,0) -> 160053.5 | GO51: =IF(BI51=2,GM51-GX51,0) -> 0 | GP51: =IF(BI51=4,GM51-GX51,0) -> 0 | GR51: 1 | GS51: 1 | GT51: 0 | GV51: =ROUND((GT51),6) -> 0 | GW51: 1 | GX51: =ROUND(HC51*I51,2) -> 0 | HA51: 0 | HB51: 0 | HC51: =GV51*GW51 -> 0 | HE51: 0 | HF51: 2 | HS51: 0 | IK51: 0
A52: 18 | B52: 1 | C52: 13 | E52: 1,12 | F52: КА. п. 12 | G52: Сmальной nанельный paguamop PRADO Classic, mun 20, Bыcoma Н = 500 мм, PRADO Classic-20-500-1500 | I52: =I28*J52 -> 2 | J52: 1.5037594 | K52: 1.5037594 | O52: =ROUND(CP52,2) -> 1927.38 | P52: =ROUND((ROUND((AC52*AW52*I52),2)*BC52),2) -> 1927.38 | Q52: =(ROUND((ROUND(((ET52)*AV52*I52),2)*BB52),2)+ROUND((ROUND(((AE52-(EU52))*AV52*I52),2)*BS52),2)) -> 0 | R52: =(ROUND((ROUND(((EU52)*AV52*I52),2)*BS52),2)+ROUND((ROUND(((AE52-(EU52))*AV52*I52),2)*BS52),2)) -> 0 | S52: =ROUND((ROUND((AF52*AV52*I52),2)*BA52),2) -> 0 | T52: =ROUND(CU52*I52,2) -> 0 | U52: =CV52*I52 -> 0 | V52: =CW52*I52 -> 0 | W52: =ROUND(CX52*I52,2) -> 0 | X52: =(ROUND((((S52+ROUND((ROUND(((EU52)*AV52*I52),2)*BS52),2))*AT52)/100),2)+ROUND(((ROUND((ROUND(((AE52-(EU52))*AV52*I52),2)*BS52),2)*AT52)/100),2)) -> 0 | Y52: =(ROUND((((S52+ROUND((ROUND(((EU52)*AV52*I52),2)*BS52),2))*AU52)/100),2)+ROUND(((ROUND((ROUND(((AE52-(EU52))*AV52*I52),2)*BS52),2)*AU52)/100),2)) -> 0 | AA52: 86551701 | AB52: =ROUND((AC52+AD52+AF52),6) -> 963.69 | AC52: =ROUND((ES52),6) -> 963.69 | AD52: =ROUND((((ET52)-(EU52))+AE52),6) -> 0 | AE52: =ROUND((EU52),6) -> 0 | AF52: =ROUND((EV52),6) -> 0 | AG52: =ROUND((AP52),6) -> 0 | AH52: =(EW52) -> 0 | AI52: =(EX52) -> 0 | AJ52: =(AS52) -> 0 | AK52: 963.69 | AL52: 963.69 | AM52: 0 | AN52: 0 | AO52: 0 | AP52: 0 | AQ52: 0 | AR52: 0 | AS52: 0 | AT52: 109 | AU52: 61 | AV52: 1 | AW52: 1 | AZ52: 1 | BA52: 1 | BB52: 1 | BC52: 1 | BH52: 3 | BI52: 1 | BM52: 23 | BN52: 0 | BP52: 0 | BQ52: 30 | BR52: 0 | BS52: 1 | BT52: 1 | BU52: 1 | BV52: 1 | BW52: 1 | BX52: 1 | BZ52: 109 | CA52: 61 | CE52: 1566 | CF52: 0 | CG52: 0 | CM52: 0 | CO52: 0 | CP52: =(P52+Q52+S52) -> 1927.38 | CQ52: =ROUND((ROUND((AC52*AW52*1),2)*BC52),2) -> 963.69 | CR52: =(ROUND((ROUND(((ET52)*AV52*1),2)*BB52),2)+ROUND((ROUND(((AE52-(EU52))*AV52*1),2)*BS52),2)) -> 0 | CS52: =(ROUND((ROUND(((EU52)*AV52*1),2)*BS52),2)+ROUND((ROUND(((AE52-(EU52))*AV52*1),2)*BS52),2)) -> 0 | CT52: =ROUND((ROUND((AF52*AV52*1),2)*BA52),2) -> 0 | CU52: =AG52 -> 0 | CV52: =(AH52*AV52) -> 0 | CW52: =AI52 -> 0 | CX52: =AJ52 -> 0 | CY52: =(ROUND((((S52+ROUND((ROUND(((EU52)*AV52*1),2)*BS52),2))*AT52)/100),2)+ROUND(((ROUND((ROUND(((AE52-(EU52))*AV52*1),2)*BS52),2)*AT52)/100),2)) -> 0 | CZ52: =(ROUND((((S52+ROUND((ROUND(((EU52)*AV52*1),2)*BS52),2))*AU52)/100),2)+ROUND(((ROUND((ROUND(((AE52-(EU52))*AV52*1),2)*BS52),2)*AU52)/100),2)) -> 0 | DN52: 0 | DO52: 0 | DP52: 1 | DQ52: 1 | EE52: 85635395 | EF52: 30 | EG52: Строительные работы | EH52: 0 | EJ52: 1 | EK52: 23 | EL52: ТСН-2001.3-18. Отопление - внутренние устройства | EM52: ТСН-2001.3-18-1 | EQ52: 0 | ER52: 0 | ES52: 963.69 | ET52: 0 | EU52: 0 | EV52: 0 | EW52: 0 | EX52: 0 | FQ52: 0 | FR52: 0 | FS52: 0 | FX52: 109 | FY52: 61 | GA52: [11 342 / 1,22 / 9,84] + 2% Заг.скл | GD52: 1 | GF52: 1679109804 | GG52: 2 | GH52: 4 | GI52: -2 | GJ52: 0 | GK52: 0 | GL52: =ROUND(IF(AND(BH52=3,BI52=3,FS52<>0),P52,0),2) -> 0 | GM52: =ROUND(O52+X52+Y52,2)+GX52 -> 1927.38 | GN52: =IF(OR(BI52=0,BI52=1),GM52-GX52,0) -> 1927.38 | GO52: =IF(BI52=2,GM52-GX52,0) -> 0 | GP52: =IF(BI52=4,GM52-GX52,0) -> 0 | GR52: 0 | GS52: 2 | GT52: 0 | GV52: =ROUND((GT52),6) -> 0 | GW52: 1 | GX52: =ROUND(HC52*I52,2) -> 0 | HA52: 0 | HB52: 0 | HC52: =GV52*GW52 -> 0 | HE52: 0 | HF52: 2 | HS52: 0 | IK52: 0
A53: 18 | B53: 1 | C53: 35 | E53: 1,12 | F53: КА. п. 12 | G53: Сmальной nанельный paguamop PRADO Classic, mun 20, Bыcoma Н = 500 мм, PRADO Classic-20-500-1500 | I53: =I29*J53 -> 2 | J53: 1.5037594 | K53: 1.5037594 | O53: =ROUND(CP53,2) -> 18965.42 | P53: =ROUND((ROUND((AC53*AW53*I53),2)*BC53),2) -> 18965.42 | Q53: =(ROUND((ROUND(((ET53)*AV53*I53),2)*BB53),2)+ROUND((ROUND(((AE53-(EU53))*AV53*I53),2)*BS53),2)) -> 0 | R53: =(ROUND((ROUND(((EU53)*AV53*I53),2)*BS53),2)+ROUND((ROUND(((AE53-(EU53))*AV53*I53),2)*BS53),2)) -> 0 | S53: =ROUND((ROUND((AF53*AV53*I53),2)*BA53),2) -> 0 | T53: =ROUND(CU53*I53,2) -> 0 | U53: =CV53*I53 -> 0 | V53: =CW53*I53 -> 0 | W53: =ROUND(CX53*I53,2) -> 0 | X53: =(ROUND((((S53+ROUND((ROUND(((EU53)*AV53*I53),2)*BS53),2))*AT53)/100),2)+ROUND(((ROUND((ROUND(((AE53-(EU53))*AV53*I53),2)*BS53),2)*AT53)/100),2)) -> 0 | Y53: =(ROUND((((S53+ROUND((ROUND(((EU53)*AV53*I53),2)*BS53),2))*AU53)/100),2)+ROUND(((ROUND((ROUND(((AE53-(EU53))*AV53*I53),2)*BS53),2)*AU53)/100),2)) -> 0 | AA53: 86551703 | AB53: =ROUND((AC53+AD53+AF53),6) -> 963.69 | AC53: =ROUND((ES53),6) -> 963.69 | AD53: =ROUND((((ET53)-(EU53))+AE53),6) -> 0 | AE53: =ROUND((EU53),6) -> 0 | AF53: =ROUND((EV53),6) -> 0 | AG53: =ROUND((AP53),6) -> 0 | AH53: =(EW53) -> 0 | AI53: =(EX53) -> 0 | AJ53: =(AS53) -> 0 | AK53: 963.69 | AL53: 963.69 | AM53: 0 | AN53: 0 | AO53: 0 | AP53: 0 | AQ53: 0 | AR53: 0 | AS53: 0 | AT53: 109 | AU53: 61 | AV53: 1 | AW53: 1 | AZ53: 1 | BA53: 1 | BB53: 1 | BC53: 9.84 | BH53: 3 | BI53: 1 | BM53: 23 | BN53: 0 | BP53: 0 | BQ53: 30 | BR53: 0 | BS53: 1 | BT53: 1 | BU53: 1 | BV53: 1 | BW53: 1 | BX53: 1 | BZ53: 109 | CA53: 61 | CE53: 1566 | CF53: 0 | CG53: 0 | CM53: 0 | CO53: 0 | CP53: =(P53+Q53+S53) -> 18965.42 | CQ53: =ROUND((ROUND((AC53*AW53*1),2)*BC53),2) -> 9482.71 | CR53: =(ROUND((ROUND(((ET53)*AV53*1),2)*BB53),2)+ROUND((ROUND(((AE53-(EU53))*AV53*1),2)*BS53),2)) -> 0 | CS53: =(ROUND((ROUND(((EU53)*AV53*1),2)*BS53),2)+ROUND((ROUND(((AE53-(EU53))*AV53*1),2)*BS53),2)) -> 0 | CT53: =ROUND((ROUND((AF53*AV53*1),2)*BA53),2) -> 0 | CU53: =AG53 -> 0 | CV53: =(AH53*AV53) -> 0 | CW53: =AI53 -> 0 | CX53: =AJ53 -> 0 | CY53: =(ROUND((((S53+ROUND((ROUND(((EU53)*AV53*1),2)*BS53),2))*AT53)/100),2)+ROUND(((ROUND((ROUND(((AE53-(EU53))*AV53*1),2)*BS53),2)*AT53)/100),2)) -> 0 | CZ53: =(ROUND((((S53+ROUND((ROUND(((EU53)*AV53*1),2)*BS53),2))*AU53)/100),2)+ROUND(((ROUND((ROUND(((AE53-(EU53))*AV53*1),2)*BS53),2)*AU53)/100),2)) -> 0 | DN53: 0 | DO53: 0 | DP53: 1 | DQ53: 1 | EE53: 85635395 | EF53: 30 | EG53: Строительные работы | EH53: 0 | EJ53: 1 | EK53: 23 | EL53: ТСН-2001.3-18. Отопление - внутренние устройства | EM53: ТСН-2001.3-18-1 | EQ53: 0 | ER53: 963.69 | ES53: 963.69 | ET53: 0 | EU53: 0 | EV53: 0 | EW53: 0 | EX53: 0 | EZ53: 5 | FC53: 1 | FD53: 18 | FF53: 11342 | FQ53: 0 | FR53: 0 | FS53: 0 | FX53: 109 | FY53: 61 | GA53: [11 342 / 1,22 / 9,84] + 2% Заг.скл | GD53: 1 | GF53: 1679109804 | GG53: 2 | GH53: 3 | GI53: 5 | GJ53: 0 | GK53: 0 | GL53: =ROUND(IF(AND(BH53=3,BI53=3,FS53<>0),P53,0),2) -> 0 | GM53: =ROUND(O53+X53+Y53,2)+GX53 -> 18965.42 | GN53: =IF(OR(BI53=0,BI53=1),GM53-GX53,0) -> 18965.42 | GO53: =IF(BI53=2,GM53-GX53,0) -> 0 | GP53: =IF(BI53=4,GM53-GX53,0) -> 0 | GR53: 1 | GS53: 1 | GT53: 0 | GV53: =ROUND((GT53),6) -> 0 | GW53: 1 | GX53: =ROUND(HC53*I53,2) -> 0 | HA53: 0 | HB53: 0 | HC53: =GV53*GW53 -> 0 | HE53: 0 | HF53: 2 | HS53: 0 | IK53: 0
A54: 18 | B54: 1 | C54: 14 | E54: 1,13 | F54: КА. п. 13 | G54: Сmальной nанельный paguamop PRADO Classic, mun 20, Bыcoma Н = 500 мм, PRADO Classic-20-500-1600 | I54: =I28*J54 -> 8 | J54: 6.0150376 | K54: 6.0150376 | O54: =ROUND(CP54,2) -> 8570.72 | P54: =ROUND((ROUND((AC54*AW54*I54),2)*BC54),2) -> 8570.72 | Q54: =(ROUND((ROUND(((ET54)*AV54*I54),2)*BB54),2)+ROUND((ROUND(((AE54-(EU54))*AV54*I54),2)*BS54),2)) -> 0 | R54: =(ROUND((ROUND(((EU54)*AV54*I54),2)*BS54),2)+ROUND((ROUND(((AE54-(EU54))*AV54*I54),2)*BS54),2)) -> 0 | S54: =ROUND((ROUND((AF54*AV54*I54),2)*BA54),2) -> 0 | T54: =ROUND(CU54*I54,2) -> 0 | U54: =CV54*I54 -> 0 | V54: =CW54*I54 -> 0 | W54: =ROUND(CX54*I54,2) -> 0 | X54: =(ROUND((((S54+ROUND((ROUND(((EU54)*AV54*I54),2)*BS54),2))*AT54)/100),2)+ROUND(((ROUND((ROUND(((AE54-(EU54))*AV54*I54),2)*BS54),2)*AT54)/100),2)) -> 0 | Y54: =(ROUND((((S54+ROUND((ROUND(((EU54)*AV54*I54),2)*BS54),2))*AU54)/100),2)+ROUND(((ROUND((ROUND(((AE54-(EU54))*AV54*I54),2)*BS54),2)*AU54)/100),2)) -> 0 | AA54: 86551701 | AB54: =ROUND((AC54+AD54+AF54),6) -> 1071.34 | AC54: =ROUND((ES54),6) -> 1071.34 | AD54: =ROUND((((ET54)-(EU54))+AE54),6) -> 0 | AE54: =ROUND((EU54),6) -> 0 | AF54: =ROUND((EV54),6) -> 0 | AG54: =ROUND((AP54),6) -> 0 | AH54: =(EW54) -> 0 | AI54: =(EX54) -> 0 | AJ54: =(AS54) -> 0 | AK54: 1071.34 | AL54: 1071.34 | AM54: 0 | AN54: 0 | AO54: 0 | AP54: 0 | AQ54: 0 | AR54: 0 | AS54: 0 | AT54: 109 | AU54: 61 | AV54: 1 | AW54: 1 | AZ54: 1 | BA54: 1 | BB54: 1 | BC54: 1 | BH54: 3 | BI54: 1 | BM54: 23 | BN54: 0 | BP54: 0 | BQ54: 30 | BR54: 0 | BS54: 1 | BT54: 1 | BU54: 1 | BV54: 1 | BW54: 1 | BX54: 1 | BZ54: 109 | CA54: 61 | CE54: 1566 | CF54: 0 | CG54: 0 | CM54: 0 | CO54: 0 | CP54: =(P54+Q54+S54) -> 8570.72 | CQ54: =ROUND((ROUND((AC54*AW54*1),2)*BC54),2) -> 1071.34 | CR54: =(ROUND((ROUND(((ET54)*AV54*1),2)*BB54),2)+ROUND((ROUND(((AE54-(EU54))*AV54*1),2)*BS54),2)) -> 0 | CS54: =(ROUND((ROUND(((EU54)*AV54*1),2)*BS54),2)+ROUND((ROUND(((AE54-(EU54))*AV54*1),2)*BS54),2)) -> 0 | CT54: =ROUND((ROUND((AF54*AV54*1),2)*BA54),2) -> 0 | CU54: =AG54 -> 0 | CV54: =(AH54*AV54) -> 0 | CW54: =AI54 -> 0 | CX54: =AJ54 -> 0 | CY54: =(ROUND((((S54+ROUND((ROUND(((EU54)*AV54*1),2)*BS54),2))*AT54)/100),2)+ROUND(((ROUND((ROUND(((AE54-(EU54))*AV54*1),2)*BS54),2)*AT54)/100),2)) -> 0 | CZ54: =(ROUND((((S54+ROUND((ROUND(((EU54)*AV54*1),2)*BS54),2))*AU54)/100),2)+ROUND(((ROUND((ROUND(((AE54-(EU54))*AV54*1),2)*BS54),2)*AU54)/100),2)) -> 0 | DN54: 0 | DO54: 0 | DP54: 1 | DQ54: 1 | EE54: 85635395 | EF54: 30 | EG54: Строительные работы | EH54: 0 | EJ54: 1 | EK54: 23 | EL54: ТСН-2001.3-18. Отопление - внутренние устройства | EM54: ТСН-2001.3-18-1 | EQ54: 0 | ER54: 0 | ES54: 1071.34 | ET54: 0 | EU54: 0 | EV54: 0 | EW54: 0 | EX54: 0 | FQ54: 0 | FR54: 0 | FS54: 0 | FX54: 109 | FY54: 61 | GA54: [12 609 / 1,22 / 9,84] + 2% Заг.скл | GD54: 1 | GF54: -444911970 | GG54: 2 | GH54: 4 | GI54: -2 | GJ54: 0 | GK54: 0 | GL54: =ROUND(IF(AND(BH54=3,BI54=3,FS54<>0),P54,0),2) -> 0 | GM54: =ROUND(O54+X54+Y54,2)+GX54 -> 8570.72 | GN54: =IF(OR(BI54=0,BI54=1),GM54-GX54,0) -> 8570.72 | GO54: =IF(BI54=2,GM54-GX54,0) -> 0 | GP54: =IF(BI54=4,GM54-GX54,0) -> 0 | GR54: 0 | GS54: 2 | GT54: 0 | GV54: =ROUND((GT54),6) -> 0 | GW54: 1 | GX54: =ROUND(HC54*I54,2) -> 0 | HA54: 0 | HB54: 0 | HC54: =GV54*GW54 -> 0 | HE54: 0 | HF54: 2 | HS54: 0 | IK54: 0
A55: 18 | B55: 1 | C55: 36 | E55: 1,13 | F55: КА. п. 13 | G55: Сmальной nанельный paguamop PRADO Classic, mun 20, Bыcoma Н = 500 мм, PRADO Classic-20-500-1600 | I55: =I29*J55 -> 8 | J55: 6.0150376 | K55: 6.0150376 | O55: =ROUND(CP55,2) -> 84335.88 | P55: =ROUND((ROUND((AC55*AW55*I55),2)*BC55),2) -> 84335.88 | Q55: =(ROUND((ROUND(((ET55)*AV55*I55),2)*BB55),2)+ROUND((ROUND(((AE55-(EU55))*AV55*I55),2)*BS55),2)) -> 0 | R55: =(ROUND((ROUND(((EU55)*AV55*I55),2)*BS55),2)+ROUND((ROUND(((AE55-(EU55))*AV55*I55),2)*BS55),2)) -> 0 | S55: =ROUND((ROUND((AF55*AV55*I55),2)*BA55),2) -> 0 | T55: =ROUND(CU55*I55,2) -> 0 | U55: =CV55*I55 -> 0 | V55: =CW55*I55 -> 0 | W55: =ROUND(CX55*I55,2) -> 0 | X55: =(ROUND((((S55+ROUND((ROUND(((EU55)*AV55*I55),2)*BS55),2))*AT55)/100),2)+ROUND(((ROUND((ROUND(((AE55-(EU55))*AV55*I55),2)*BS55),2)*AT55)/100),2)) -> 0 | Y55: =(ROUND((((S55+ROUND((ROUND(((EU55)*AV55*I55),2)*BS55),2))*AU55)/100),2)+ROUND(((ROUND((ROUND(((AE55-(EU55))*AV55*I55),2)*BS55),2)*AU55)/100),2)) -> 0 | AA55: 86551703 | AB55: =ROUND((AC55+AD55+AF55),6) -> 1071.34 | AC55: =ROUND((ES55),6) -> 1071.34 | AD55: =ROUND((((ET55)-(EU55))+AE55),6) -> 0 | AE55: =ROUND((EU55),6) -> 0 | AF55: =ROUND((EV55),6) -> 0 | AG55: =ROUND((AP55),6) -> 0 | AH55: =(EW55) -> 0 | AI55: =(EX55) -> 0 | AJ55: =(AS55) -> 0 | AK55: 1071.34 | AL55: 1071.34 | AM55: 0 | AN55: 0 | AO55: 0 | AP55: 0 | AQ55: 0 | AR55: 0 | AS55: 0 | AT55: 109 | AU55: 61 | AV55: 1 | AW55: 1 | AZ55: 1 | BA55: 1 | BB55: 1 | BC55: 9.84 | BH55: 3 | BI55: 1 | BM55: 23 | BN55: 0 | BP55: 0 | BQ55: 30 | BR55: 0 | BS55: 1 | BT55: 1 | BU55: 1 | BV55: 1 | BW55: 1 | BX55: 1 | BZ55: 109 | CA55: 61 | CE55: 1566 | CF55: 0 | CG55: 0 | CM55: 0 | CO55: 0 | CP55: =(P55+Q55+S55) -> 84335.88 | CQ55: =ROUND((ROUND((AC55*AW55*1),2)*BC55),2) -> 10541.99 | CR55: =(ROUND((ROUND(((ET55)*AV55*1),2)*BB55),2)+ROUND((ROUND(((AE55-(EU55))*AV55*1),2)*BS55),2)) -> 0 | CS55: =(ROUND((ROUND(((EU55)*AV55*1),2)*BS55),2)+ROUND((ROUND(((AE55-(EU55))*AV55*1),2)*BS55),2)) -> 0 | CT55: =ROUND((ROUND((AF55*AV55*1),2)*BA55),2) -> 0 | CU55: =AG55 -> 0 | CV55: =(AH55*AV55) -> 0 | CW55: =AI55 -> 0 | CX55: =AJ55 -> 0 | CY55: =(ROUND((((S55+ROUND((ROUND(((EU55)*AV55*1),2)*BS55),2))*AT55)/100),2)+ROUND(((ROUND((ROUND(((AE55-(EU55))*AV55*1),2)*BS55),2)*AT55)/100),2)) -> 0 | CZ55: =(ROUND((((S55+ROUND((ROUND(((EU55)*AV55*1),2)*BS55),2))*AU55)/100),2)+ROUND(((ROUND((ROUND(((AE55-(EU55))*AV55*1),2)*BS55),2)*AU55)/100),2)) -> 0 | DN55: 0 | DO55: 0 | DP55: 1 | DQ55: 1 | EE55: 85635395 | EF55: 30 | EG55: Строительные работы | EH55: 0 | EJ55: 1 | EK55: 23 | EL55: ТСН-2001.3-18. Отопление - внутренние устройства | EM55: ТСН-2001.3-18-1 | EQ55: 0 | ER55: 1071.34 | ES55: 1071.34 | ET55: 0 | EU55: 0 | EV55: 0 | EW55: 0 | EX55: 0 | EZ55: 5 | FC55: 1 | FD55: 18 | FF55: 12609 | FQ55: 0 | FR55: 0 | FS55: 0 | FX55: 109 | FY55: 61 | GA55: [12 609 / 1,22 / 9,84] + 2% Заг.скл | GD55: 1 | GF55: -444911970 | GG55: 2 | GH55: 3 | GI55: 5 | GJ55: 0 | GK55: 0 | GL55: =ROUND(IF(AND(BH55=3,BI55=3,FS55<>0),P55,0),2) -> 0 | GM55: =ROUND(O55+X55+Y55,2)+GX55 -> 84335.88 | GN55: =IF(OR(BI55=0,BI55=1),GM55-GX55,0) -> 84335.88 | GO55: =IF(BI55=2,GM55-GX55,0) -> 0 | GP55: =IF(BI55=4,GM55-GX55,0) -> 0 | GR55: 1 | GS55: 1 | GT55: 0 | GV55: =ROUND((GT55),6) -> 0 | GW55: 1 | GX55: =ROUND(HC55*I55,2) -> 0 | HA55: 0 | HB55: 0 | HC55: =GV55*GW55 -> 0 | HE55: 0 | HF55: 2 | HS55: 0 | IK55: 0
A56: 17 | B56: 1 | C56: =ROW(SmtRes!A55) -> 55 | D56: =ROW(EtalonRes!A30) -> 30 | E56: 2 | F56: 3.18-25-2 | G56: Установка радиаторов стальных панельных однорядных с креплением к стене длиной свыше 1600 до 2000 мм (вентиль справа) | H56: 100 шт. | I56: =ROUND((1+1)/100,9) -> 0.02 | J56: 0 | K56: =ROUND((1+1)/100,9) -> 0.02 | O56: =ROUND(CP56,2) -> 104.16 | P56: =ROUND((ROUND((AC56*AW56*I56),2)*BC56),2) -> 62.38 | Q56: =(ROUND((ROUND((((((ET56*1.03)*1.25)*1.2))*AV56*I56),2)*BB56),2)+ROUND((ROUND(((AE56-((((EU56*1.03)*1.25)*1.2)))*AV56*I56),2)*BS56),2)) -> 5.5 | R56: =(ROUND((ROUND((((((EU56*1.03)*1.25)*1.2))*AV56*I56),2)*BS56),2)+ROUND((ROUND(((AE56-((((EU56*1.03)*1.25)*1.2)))*AV56*I56),2)*BS56),2)) -> 0.6 | S56: =ROUND((ROUND((AF56*AV56*I56),2)*BA56),2) -> 36.28 | T56: =ROUND(CU56*I56,2) -> 0 | U56: =CV56*I56 -> 2.9589525 | V56: =CW56*I56 -> 0 | W56: =ROUND(CX56*I56,2) -> 0 | X56: =(ROUND((((S56+ROUND((ROUND((((((EU56*1.03)*1.25)*1.2))*AV56*I56),2)*BS56),2))*AT56)/100),2)+ROUND(((ROUND((ROUND(((AE56-((((EU56*1.03)*1.25)*1.2)))*AV56*I56),2)*BS56),2)*AT56)/100),2)) -> 40.2 | Y56: =(ROUND((((S56+ROUND((ROUND((((((EU56*1.03)*1.25)*1.2))*AV56*I56),2)*BS56),2))*AU56)/100),2)+ROUND(((ROUND((ROUND(((AE56-((((EU56*1.03)*1.25)*1.2)))*AV56*I56),2)*BS56),2)*AU56)/100),2)) -> 22.5 | AA56: 86551701 | AB56: =ROUND((AC56+AD56+AF56),6) -> 5076.866 | AC56: =ROUND(((((ES56*1)*1)*1)),6) -> 3119.05 | AD56: =ROUND(((((((ET56*1.03)*1.25)*1.2))-((((EU56*1.03)*1.25)*1.2)))+AE56),6) -> 257.5515 | AE56: =ROUND(((((EU56*1.03)*1.25)*1.2)),6) -> 27.91815 | AF56: =ROUND(((((EV56*1.03)*1.15)*1.2)),6) -> 1700.2645 | AG56: =ROUND((AP56),6) -> 0 | AH56: =((((EW56*1.03)*1.15)*1.2)) -> 138.65757 | AI56: =((((EX56*1.03)*1.25)*1.2)) -> 0 | AJ56: =(AS56) -> 0 | AK56: 4481.94 | AL56: 3119.05 | AM56: 166.7 | AN56: 18.07 | AO56: 1196.19 | AP56: 0 | AQ56: 97.55 | AR56: 0 | AS56: 0 | AT56: 109 | AU56: 61 | AV56: 1.067 | AW56: 1 | AZ56: 1 | BA56: 1 | BB56: 1 | BC56: 1 | BH56: 0 | BI56: 1 | BJ56: ТСН-2001.3 Доп. 81, Сб. 18, т. 25, поз. 2 | BM56: 23 | BN56: 0 | BO56: 3.18-25-2 | BP56: 1 | BQ56: 30 | BR56: 0 | BS56: 1 | BT56: 1 | BU56: 1 | BV56: 1 | BW56: 1 | BX56: 1 | BZ56: 109 | CA56: 61 | CE56: 1566 | CF56: 0 | CG56: 0 | CM56: 0 | CN56: Поправка: 3-18. О.П. п.1.8 Наименование: Затраты на тепловое испытание систем отопления с проверкой равномерности прогрева отопительных приборов Поправка: Гл.6.Прил.2.2.п.2.2.6_06.00.01.07.001 Наименование: При выполнении при капитальном ремонте и реконструкции работ, аналогичных технологическим процессам, характерным для нового строительства, и отсутствующих в сборниках на ремонтно-строительные работы ТСН-2001.6 Поправка: Гл.12.Прил.8.п.8. 3_12.00.01.11.001 Наименование: При наличии напряженных и стесненных условий производства работ (стесненность, сложность складирования и транспортной логистики и т.п.) для объектов, расположенных в пределах круговой магистральной системы улиц "Садовое кольцо" города Москвы | CO56: 0 | CP56: =(P56+Q56+S56) -> 104.16 | CQ56: =ROUND((ROUND((AC56*AW56*1),2)*BC56),2) -> 3119.05 | CR56: =(ROUND((ROUND((((((ET56*1.03)*1.25)*1.2))*AV56*1),2)*BB56),2)+ROUND((ROUND(((AE56-((((EU56*1.03)*1.25)*1.2)))*AV56*1),2)*BS56),2)) -> 274.81 | CS56: =(ROUND((ROUND((((((EU56*1.03)*1.25)*1.2))*AV56*1),2)*BS56),2)+ROUND((ROUND(((AE56-((((EU56*1.03)*1.25)*1.2)))*AV56*1),2)*BS56),2)) -> 29.79 | CT56: =ROUND((ROUND((AF56*AV56*1),2)*BA56),2) -> 1814.18 | CU56: =AG56 -> 0 | CV56: =(AH56*AV56) -> 147.94763 | CW56: =AI56 -> 0 | CX56: =AJ56 -> 0 | CY56: =(ROUND((((S56+ROUND((ROUND((((((EU56*1.03)*1.25)*1.2))*AV56*1),2)*BS56),2))*AT56)/100),2)+ROUND(((ROUND((ROUND(((AE56-((((EU56*1.03)*1.25)*1.2)))*AV56*1),2)*BS56),2)*AT56)/100),2)) -> 72.02 | CZ56: =(ROUND((((S56+ROUND((ROUND((((((EU56*1.03)*1.25)*1.2))*AV56*1),2)*BS56),2))*AU56)/100),2)+ROUND(((ROUND((ROUND(((AE56-((((EU56*1.03)*1.25)*1.2)))*AV56*1),2)*BS56),2)*AU56)/100),2)) -> 40.3 | DB56: 7 | DD56: *1)*1)*1 | DE56: *1,03)*1,25)*1,2 | DF56: *1,03)*1,25)*1,2 | DG56: *1,03)*1,15)*1,2 | DI56: *1,03)*1,15)*1,2 | DJ56: *1,03)*1,25)*1,2 | DN56: 0 | DO56: 0 | DP56: 1 | DQ56: 1 | DU56: 1010 | DV56: 100 шт. | DW56: 100 шт. | DX56: 100 | EE56: 85635395 | EF56: 30 | EG56: Строительные работы | EH56: 0 | EJ56: 1 | EK56: 23 | EL56: ТСН-2001.3-18. Отопление - внутренние устройства | EM56: ТСН-2001.3-18-1 | EO56: Поправка: 3-18. О.П. п.1.8 Поправка: Гл.6.Прил.2.2.п.2.2.6_06.00.01.07.001 Поправка: Гл.12.Прил.8.п.8. 3_12.00.01.11.001 | EQ56: 131072 | ER56: 4481.94 | ES56: 3119.05 | ET56: 166.7 | EU56: 18.07 | EV56: 1196.19 | EW56: 97.55 | EX56: 0 | EY56: 0 | FQ56: 0 | FR56: 0 | FS56: 0 | FX56: 109 | FY56: 61 | GD56: 1 | GF56: -1208879943 | GG56: 2 | GH56: 1 | GI56: 2 | GJ56: 0 | GK56: 0 | GL56: =ROUND(IF(AND(BH56=3,BI56=3,FS56<>0),P56,0),2) -> 0 | GM56: =ROUND(O56+X56+Y56,2)+GX56 -> 166.86 | GN56: =IF(OR(BI56=0,BI56=1),GM56-GX56,0) -> 166.86 | GO56: =IF(BI56=2,GM56-GX56,0) -> 0 | GP56: =IF(BI56=4,GM56-GX56,0) -> 0 | GR56: 0 | GS56: 3 | GT56: 0 | GV56: =ROUND((GT56),6) -> 0 | GW56: 1 | GX56: =ROUND(HC56*I56,2) -> 0 | HA56: 0 | HB56: 0 | HC56: =GV56*GW56 -> 0 | HS56: 0 | IK56: 0
A57: 17 | B57: 1 | C57: =ROW(SmtRes!A66) -> 66 | D57: =ROW(EtalonRes!A40) -> 40 | E57: 2 | F57: 3.18-25-2 | G57: Установка радиаторов стальных панельных однорядных с креплением к стене длиной свыше 1600 до 2000 мм (вентиль справа) | H57: 100 шт. | I57: =ROUND((1+1)/100,9) -> 0.02 | J57: 0 | K57: =ROUND((1+1)/100,9) -> 0.02 | O57: =ROUND(CP57,2) -> 3426.59 | P57: =ROUND((ROUND((AC57*AW57*I57),2)*BC57),2) -> 1299.38 | Q57: =(ROUND((ROUND((((((ET57*1.03)*1.25)*1.2))*AV57*I57),2)*BB57),2)+ROUND((ROUND(((AE57-((((EU57*1.03)*1.25)*1.2)))*AV57*I57),2)*BS57),2)) -> 82.83 | R57: =(ROUND((ROUND((((((EU57*1.03)*1.25)*1.2))*AV57*I57),2)*BS57),2)+ROUND((ROUND(((AE57-((((EU57*1.03)*1.25)*1.2)))*AV57*I57),2)*BS57),2)) -> 33.81 | S57: =ROUND((ROUND((AF57*AV57*I57),2)*BA57),2) -> 2044.38 | T57: =ROUND(CU57*I57,2) -> 0 | U57: =CV57*I57 -> 2.9589525 | V57: =CW57*I57 -> 0 | W57: =ROUND(CX57*I57,2) -> 0 | X57: =(ROUND((((S57+ROUND((ROUND((((((EU57*1.03)*1.25)*1.2))*AV57*I57),2)*BS57),2))*AT57)/100),2)+ROUND(((ROUND((ROUND(((AE57-((((EU57*1.03)*1.25)*1.2)))*AV57*I57),2)*BS57),2)*AT57)/100),2)) -> 2265.23 | Y57: =(ROUND((((S57+ROUND((ROUND((((((EU57*1.03)*1.25)*1.2))*AV57*I57),2)*BS57),2))*AU57)/100),2)+ROUND(((ROUND((ROUND(((AE57-((((EU57*1.03)*1.25)*1.2)))*AV57*I57),2)*BS57),2)*AU57)/100),2)) -> 1267.7 | AA57: 86551703 | AB57: =ROUND((AC57+AD57+AF57),6) -> 5076.866 | AC57: =ROUND(((((ES57*1)*1)*1)),6) -> 3119.05 | AD57: =ROUND(((((((ET57*1.03)*1.25)*1.2))-((((EU57*1.03)*1.25)*1.2)))+AE57),6) -> 257.5515 | AE57: =ROUND(((((EU57*1.03)*1.25)*1.2)),6) -> 27.91815 | AF57: =ROUND(((((EV57*1.03)*1.15)*1.2)),6) -> 1700.2645 | AG57: =ROUND((AP57),6) -> 0 | AH57: =((((EW57*1.03)*1.15)*1.2)) -> 138.65757 | AI57: =((((EX57*1.03)*1.25)*1.2)) -> 0 | AJ57: =(AS57) -> 0 | AK57: 4481.94 | AL57: 3119.05 | AM57: 166.7 | AN57: 18.07 | AO57: 1196.19 | AP57: 0 | AQ57: 97.55 | AR57: 0 | AS57: 0 | AT57: 109 | AU57: 61 | AV57: 1.067 | AW57: 1 | AZ57: 1 | BA57: 56.35 | BB57: 15.06 | BC57: 20.83 | BH57: 0 | BI57: 1 | BJ57: ТСН-2001.3 Доп. 81, Сб. 18, т. 25, поз. 2 | BM57: 23 | BN57: 0 | BO57: 3.18-25-2 | BP57: 1 | BQ57: 30 | BR57: 0 | BS57: 56.35 | BT57: 1 | BU57: 1 | BV57: 1 | BW57: 1 | BX57: 1 | BZ57: 109 | CA57: 61 | CE57: 1566 | CF57: 0 | CG57: 0 | CM57: 0 | CN57: Поправка: 3-18. О.П. п.1.8 Наименование: Затраты на тепловое испытание систем отопления с проверкой равномерности прогрева отопительных приборов Поправка: Гл.6.Прил.2.2.п.2.2.6_06.00.01.07.001 Наименование: При выполнении при капитальном ремонте и реконструкции работ, аналогичных технологическим процессам, характерным для нового строительства, и отсутствующих в сборниках на ремонтно-строительные работы ТСН-2001.6 Поправка: Гл.12.Прил.8.п.8. 3_12.00.01.11.001 Наименование: При наличии напряженных и стесненных условий производства работ (стесненность, сложность складирования и транспортной логистики и т.п.) для объектов, расположенных в пределах круговой магистральной системы улиц "Садовое кольцо" города Москвы | CO57: 0 | CP57: =(P57+Q57+S57) -> 3426.59 | CQ57: =ROUND((ROUND((AC57*AW57*1),2)*BC57),2) -> 64969.81 | CR57: =(ROUND((ROUND((((((ET57*1.03)*1.25)*1.2))*AV57*1),2)*BB57),2)+ROUND((ROUND(((AE57-((((EU57*1.03)*1.25)*1.2)))*AV57*1),2)*BS57),2)) -> 4138.64 | CS57: =(ROUND((ROUND((((((EU57*1.03)*1.25)*1.2))*AV57*1),2)*BS57),2)+ROUND((ROUND(((AE57-((((EU57*1.03)*1.25)*1.2)))*AV57*1),2)*BS57),2)) -> 1678.67 | CT57: =ROUND((ROUND((AF57*AV57*1),2)*BA57),2) -> 102229.04 | CU57: =AG57 -> 0 | CV57: =(AH57*AV57) -> 147.94763 | CW57: =AI57 -> 0 | CX57: =AJ57 -> 0 | CY57: =(ROUND((((S57+ROUND((ROUND((((((EU57*1.03)*1.25)*1.2))*AV57*1),2)*BS57),2))*AT57)/100),2)+ROUND(((ROUND((ROUND(((AE57-((((EU57*1.03)*1.25)*1.2)))*AV57*1),2)*BS57),2)*AT57)/100),2)) -> 4058.12 | CZ57: =(ROUND((((S57+ROUND((ROUND((((((EU57*1.03)*1.25)*1.2))*AV57*1),2)*BS57),2))*AU57)/100),2)+ROUND(((ROUND((ROUND(((AE57-((((EU57*1.03)*1.25)*1.2)))*AV57*1),2)*BS57),2)*AU57)/100),2)) -> 2271.06 | DB57: 10 | DD57: *1)*1)*1 | DE57: *1,03)*1,25)*1,2 | DF57: *1,03)*1,25)*1,2 | DG57: *1,03)*1,15)*1,2 | DI57: *1,03)*1,15)*1,2 | DJ57: *1,03)*1,25)*1,2 | DN57: 0 | DO57: 0 | DP57: 1 | DQ57: 1 | DU57: 1010 | DV57: 100 шт. | DW57: 100 шт. | DX57: 100 | EE57: 85635395 | EF57: 30 | EG57: Строительные работы | EH57: 0 | EJ57: 1 | EK57: 23 | EL57: ТСН-2001.3-18. Отопление - внутренние устройства | EM57: ТСН-2001.3-18-1 | EO57: Поправка: 3-18. О.П. п.1.8 Поправка: Гл.6.Прил.2.2.п.2.2.6_06.00.01.07.001 Поправка: Гл.12.Прил.8.п.8. 3_12.00.01.11.001 | EQ57: 131072 | ER57: 4481.94 | ES57: 3119.05 | ET57: 166.7 | EU57: 18.07 | EV57: 1196.19 | EW57: 97.55 | EX57: 0 | EY57: 0 | FQ57: 0 | FR57: 0 | FS57: 0 | FX57: 109 | FY57: 61 | GD57: 1 | GF57: -1208879943 | GG57: 2 | GH57: 1 | GI57: 2 | GJ57: 0 | GK57: 0 | GL57: =ROUND(IF(AND(BH57=3,BI57=3,FS57<>0),P57,0),2) -> 0 | GM57: =ROUND(O57+X57+Y57,2)+GX57 -> 6959.52 | GN57: =IF(OR(BI57=0,BI57=1),GM57-GX57,0) -> 6959.52 | GO57: =IF(BI57=2,GM57-GX57,0) -> 0 | GP57: =IF(BI57=4,GM57-GX57,0) -> 0 | GR57: 0 | GS57: 3 | GT57: 0 | GV57: =ROUND((GT57),6) -> 0 | GW57: 1 | GX57: =ROUND(HC57*I57,2) -> 0 | HA57: 0 | HB57: 0 | HC57: =GV57*GW57 -> 0 | HS57: 0 | IK57: 0
A58: 18 | B58: 1 | C58: 54 | E58: 2,1 | F58: КА. п. 14 | G58: Сmальной nанельный paguamop PRADO Classic, mun 20, Bыcoma Н = 500 мм, PRADO Classic-20-500-1900 | H58: шт. | I58: =I56*J58 -> 1 | J58: 50 | K58: 50 | O58: =ROUND(CP58,2) -> 1190.46 | P58: =ROUND((ROUND((AC58*AW58*I58),2)*BC58),2) -> 1190.46 | Q58: =(ROUND((ROUND(((ET58)*AV58*I58),2)*BB58),2)+ROUND((ROUND(((AE58-(EU58))*AV58*I58),2)*BS58),2)) -> 0 | R58: =(ROUND((ROUND(((EU58)*AV58*I58),2)*BS58),2)+ROUND((ROUND(((AE58-(EU58))*AV58*I58),2)*BS58),2)) -> 0 | S58: =ROUND((ROUND((AF58*AV58*I58),2)*BA58),2) -> 0 | T58: =ROUND(CU58*I58,2) -> 0 | U58: =CV58*I58 -> 0 | V58: =CW58*I58 -> 0 | W58: =ROUND(CX58*I58,2) -> 0 | X58: =(ROUND((((S58+ROUND((ROUND(((EU58)*AV58*I58),2)*BS58),2))*AT58)/100),2)+ROUND(((ROUND((ROUND(((AE58-(EU58))*AV58*I58),2)*BS58),2)*AT58)/100),2)) -> 0 | Y58: =(ROUND((((S58+ROUND((ROUND(((EU58)*AV58*I58),2)*BS58),2))*AU58)/100),2)+ROUND(((ROUND((ROUND(((AE58-(EU58))*AV58*I58),2)*BS58),2)*AU58)/100),2)) -> 0 | AA58: 86551701 | AB58: =ROUND((AC58+AD58+AF58),6) -> 1190.46 | AC58: =ROUND((ES58),6) -> 1190.46 | AD58: =ROUND((((ET58)-(EU58))+AE58),6) -> 0 | AE58: =ROUND((EU58),6) -> 0 | AF58: =ROUND((EV58),6) -> 0 | AG58: =ROUND((AP58),6) -> 0 | AH58: =(EW58) -> 0 | AI58: =(EX58) -> 0 | AJ58: =(AS58) -> 0 | AK58: 1190.46 | AL58: 1190.46 | AM58: 0 | AN58: 0 | AO58: 0 | AP58: 0 | AQ58: 0 | AR58: 0 | AS58: 0 | AT58: 109 | AU58: 61 | AV58: 1 | AW58: 1 | AZ58: 1 | BA58: 1 | BB58: 1 | BC58: 1 | BH58: 3 | BI58: 1 | BM58: 23 | BN58: 0 | BP58: 0 | BQ58: 30 | BR58: 0 | BS58: 1 | BT58: 1 | BU58: 1 | BV58: 1 | BW58: 1 | BX58: 1 | BZ58: 109 | CA58: 61 | CE58: 1566 | CF58: 0 | CG58: 0 | CM58: 0 | CO58: 0 | CP58: =(P58+Q58+S58) -> 1190.46 | CQ58: =ROUND((ROUND((AC58*AW58*1),2)*BC58),2) -> 1190.46 | CR58: =(ROUND((ROUND(((ET58)*AV58*1),2)*BB58),2)+ROUND((ROUND(((AE58-(EU58))*AV58*1),2)*BS58),2)) -> 0 | CS58: =(ROUND((ROUND(((EU58)*AV58*1),2)*BS58),2)+ROUND((ROUND(((AE58-(EU58))*AV58*1),2)*BS58),2)) -> 0 | CT58: =ROUND((ROUND((AF58*AV58*1),2)*BA58),2) -> 0 | CU58: =AG58 -> 0 | CV58: =(AH58*AV58) -> 0 | CW58: =AI58 -> 0 | CX58: =AJ58 -> 0 | CY58: =(ROUND((((S58+ROUND((ROUND(((EU58)*AV58*1),2)*BS58),2))*AT58)/100),2)+ROUND(((ROUND((ROUND(((AE58-(EU58))*AV58*1),2)*BS58),2)*AT58)/100),2)) -> 0 | CZ58: =(ROUND((((S58+ROUND((ROUND(((EU58)*AV58*1),2)*BS58),2))*AU58)/100),2)+ROUND(((ROUND((ROUND(((AE58-(EU58))*AV58*1),2)*BS58),2)*AU58)/100),2)) -> 0 | DN58: 0 | DO58: 0 | DP58: 1 | DQ58: 1 | DU58: 1010 | DV58: шт. | DW58: шт. | DX58: 1 | EE58: 85635395 | EF58: 30 | EG58: Строительные работы | EH58: 0 | EJ58: 1 | EK58: 23 | EL58: ТСН-2001.3-18. Отопление - внутренние устройства | EM58: ТСН-2001.3-18-1 | EQ58: 0 | ER58: 0 | ES58: 1190.46 | ET58: 0 | EU58: 0 | EV58: 0 | EW58: 0 | EX58: 0 | FQ58: 0 | FR58: 0 | FS58: 0 | FX58: 109 | FY58: 61 | GA58: [14 011 / 1,22 / 9,84] + 2% Заг.скл | GD58: 1 | GF58: -965078020 | GG58: 2 | GH58: 4 | GI58: -2 | GJ58: 0 | GK58: 0 | GL58: =ROUND(IF(AND(BH58=3,BI58=3,FS58<>0),P58,0),2) -> 0 | GM58: =ROUND(O58+X58+Y58,2)+GX58 -> 1190.46 | GN58: =IF(OR(BI58=0,BI58=1),GM58-GX58,0) -> 1190.46 | GO58: =IF(BI58=2,GM58-GX58,0) -> 0 | GP58: =IF(BI58=4,GM58-GX58,0) -> 0 | GR58: 0 | GS58: 2 | GT58: 0 | GV58: =ROUND((GT58),6) -> 0 | GW58: 1 | GX58: =ROUND(HC58*I58,2) -> 0 | HA58: 0 | HB58: 0 | HC58: =GV58*GW58 -> 0 | HE58: 0 | HF58: 2 | HS58: 0 | IK58: 0
A59: 18 | B59: 1 | C59: 65 | E59: 2,1 | F59: КА. п. 14 | G59: Сmальной nанельный paguamop PRADO Classic, mun 20, Bыcoma Н = 500 мм, PRADO Classic-20-500-1900 | H59: шт. | I59: =I57*J59 -> 1 | J59: 50 | K59: 50 | O59: =ROUND(CP59,2) -> 11714.13 | P59: =ROUND((ROUND((AC59*AW59*I59),2)*BC59),2) -> 11714.13 | Q59: =(ROUND((ROUND(((ET59)*AV59*I59),2)*BB59),2)+ROUND((ROUND(((AE59-(EU59))*AV59*I59),2)*BS59),2)) -> 0 | R59: =(ROUND((ROUND(((EU59)*AV59*I59),2)*BS59),2)+ROUND((ROUND(((AE59-(EU59))*AV59*I59),2)*BS59),2)) -> 0 | S59: =ROUND((ROUND((AF59*AV59*I59),2)*BA59),2) -> 0 | T59: =ROUND(CU59*I59,2) -> 0 | U59: =CV59*I59 -> 0 | V59: =CW59*I59 -> 0 | W59: =ROUND(CX59*I59,2) -> 0 | X59: =(ROUND((((S59+ROUND((ROUND(((EU59)*AV59*I59),2)*BS59),2))*AT59)/100),2)+ROUND(((ROUND((ROUND(((AE59-(EU59))*AV59*I59),2)*BS59),2)*AT59)/100),2)) -> 0 | Y59: =(ROUND((((S59+ROUND((ROUND(((EU59)*AV59*I59),2)*BS59),2))*AU59)/100),2)+ROUND(((ROUND((ROUND(((AE59-(EU59))*AV59*I59),2)*BS59),2)*AU59)/100),2)) -> 0 | AA59: 86551703 | AB59: =ROUND((AC59+AD59+AF59),6) -> 1190.46 | AC59: =ROUND((ES59),6) -> 1190.46 | AD59: =ROUND((((ET59)-(EU59))+AE59),6) -> 0 | AE59: =ROUND((EU59),6) -> 0 | AF59: =ROUND((EV59),6) -> 0 | AG59: =ROUND((AP59),6) -> 0 | AH59: =(EW59) -> 0 | AI59: =(EX59) -> 0 | AJ59: =(AS59) -> 0 | AK59: 1190.46 | AL59: 1190.46 | AM59: 0 | AN59: 0 | AO59: 0 | AP59: 0 | AQ59: 0 | AR59: 0 | AS59: 0 | AT59: 109 | AU59: 61 | AV59: 1 | AW59: 1 | AZ59: 1 | BA59: 1 | BB59: 1 | BC59: 9.84 | BH59: 3 | BI59: 1 | BM59: 23 | BN59: 0 | BP59: 0 | BQ59: 30 | BR59: 0 | BS59: 1 | BT59: 1 | BU59: 1 | BV59: 1 | BW59: 1 | BX59: 1 | BZ59: 109 | CA59: 61 | CE59: 1566 | CF59: 0 | CG59: 0 | CM59: 0 | CO59: 0 | CP59: =(P59+Q59+S59) -> 11714.13 | CQ59: =ROUND((ROUND((AC59*AW59*1),2)*BC59),2) -> 11714.13 | CR59: =(ROUND((ROUND(((ET59)*AV59*1),2)*BB59),2)+ROUND((ROUND(((AE59-(EU59))*AV59*1),2)*BS59),2)) -> 0 | CS59: =(ROUND((ROUND(((EU59)*AV59*1),2)*BS59),2)+ROUND((ROUND(((AE59-(EU59))*AV59*1),2)*BS59),2)) -> 0 | CT59: =ROUND((ROUND((AF59*AV59*1),2)*BA59),2) -> 0 | CU59: =AG59 -> 0 | CV59: =(AH59*AV59) -> 0 | CW59: =AI59 -> 0 | CX59: =AJ59 -> 0 | CY59: =(ROUND((((S59+ROUND((ROUND(((EU59)*AV59*1),2)*BS59),2))*AT59)/100),2)+ROUND(((ROUND((ROUND(((AE59-(EU59))*AV59*1),2)*BS59),2)*AT59)/100),2)) -> 0 | CZ59: =(ROUND((((S59+ROUND((ROUND(((EU59)*AV59*1),2)*BS59),2))*AU59)/100),2)+ROUND(((ROUND((ROUND(((AE59-(EU59))*AV59*1),2)*BS59),2)*AU59)/100),2)) -> 0 | DN59: 0 | DO59: 0 | DP59: 1 | DQ59: 1 | DU59: 1010 | DV59: шт. | DW59: шт. | DX59: 1 | EE59: 85635395 | EF59: 30 | EG59: Строительные работы | EH59: 0 | EJ59: 1 | EK59: 23 | EL59: ТСН-2001.3-18. Отопление - внутренние устройства | EM59: ТСН-2001.3-18-1 | EQ59: 0 | ER59: 1190.46 | ES59: 1190.46 | ET59: 0 | EU59: 0 | EV59: 0 | EW59: 0 | EX59: 0 | EZ59: 5 | FC59: 1 | FD59: 18 | FF59: 14011 | FQ59: 0 | FR59: 0 | FS59: 0 | FX59: 109 | FY59: 61 | GA59: [14 011 / 1,22 / 9,84] + 2% Заг.скл | GD59: 1 | GF59: -965078020 | GG59: 2 | GH59: 3 | GI59: 5 | GJ59: 0 | GK59: 0 | GL59: =ROUND(IF(AND(BH59=3,BI59=3,FS59<>0),P59,0),2) -> 0 | GM59: =ROUND(O59+X59+Y59,2)+GX59 -> 11714.13 | GN59: =IF(OR(BI59=0,BI59=1),GM59-GX59,0) -> 11714.13 | GO59: =IF(BI59=2,GM59-GX59,0) -> 0 | GP59: =IF(BI59=4,GM59-GX59,0) -> 0 | GR59: 1 | GS59: 1 | GT59: 0 | GV59: =ROUND((GT59),6) -> 0 | GW59: 1 | GX59: =ROUND(HC59*I59,2) -> 0 | HA59: 0 | HB59: 0 | HC59: =GV59*GW59 -> 0 | HE59: 0 | HF59: 2 | HS59: 0 | IK59: 0
A60: 18 | B60: 1 | C60: 55 | E60: 2,2 | F60: КА. п. 15 | G60: Сmальной nанельный paguamop PRADO Classic, mun 20, Bыcoma Н = 500 мм, PRADO Classic-20-500-2000 | H60: шт. | I60: =I56*J60 -> 1 | J60: 50 | K60: 50 | O60: =ROUND(CP60,2) -> 1322.07 | P60: =ROUND((ROUND((AC60*AW60*I60),2)*BC60),2) -> 1322.07 | Q60: =(ROUND((ROUND(((ET60)*AV60*I60),2)*BB60),2)+ROUND((ROUND(((AE60-(EU60))*AV60*I60),2)*BS60),2)) -> 0 | R60: =(ROUND((ROUND(((EU60)*AV60*I60),2)*BS60),2)+ROUND((ROUND(((AE60-(EU60))*AV60*I60),2)*BS60),2)) -> 0 | S60: =ROUND((ROUND((AF60*AV60*I60),2)*BA60),2) -> 0 | T60: =ROUND(CU60*I60,2) -> 0 | U60: =CV60*I60 -> 0 | V60: =CW60*I60 -> 0 | W60: =ROUND(CX60*I60,2) -> 0 | X60: =(ROUND((((S60+ROUND((ROUND(((EU60)*AV60*I60),2)*BS60),2))*AT60)/100),2)+ROUND(((ROUND((ROUND(((AE60-(EU60))*AV60*I60),2)*BS60),2)*AT60)/100),2)) -> 0 | Y60: =(ROUND((((S60+ROUND((ROUND(((EU60)*AV60*I60),2)*BS60),2))*AU60)/100),2)+ROUND(((ROUND((ROUND(((AE60-(EU60))*AV60*I60),2)*BS60),2)*AU60)/100),2)) -> 0 | AA60: 86551701 | AB60: =ROUND((AC60+AD60+AF60),6) -> 1322.07 | AC60: =ROUND((ES60),6) -> 1322.07 | AD60: =ROUND((((ET60)-(EU60))+AE60),6) -> 0 | AE60: =ROUND((EU60),6) -> 0 | AF60: =ROUND((EV60),6) -> 0 | AG60: =ROUND((AP60),6) -> 0 | AH60: =(EW60) -> 0 | AI60: =(EX60) -> 0 | AJ60: =(AS60) -> 0 | AK60: 1322.07 | AL60: 1322.07 | AM60: 0 | AN60: 0 | AO60: 0 | AP60: 0 | AQ60: 0 | AR60: 0 | AS60: 0 | AT60: 109 | AU60: 61 | AV60: 1 | AW60: 1 | AZ60: 1 | BA60: 1 | BB60: 1 | BC60: 1 | BH60: 3 | BI60: 1 | BM60: 23 | BN60: 0 | BP60: 0 | BQ60: 30 | BR60: 0 | BS60: 1 | BT60: 1 | BU60: 1 | BV60: 1 | BW60: 1 | BX60: 1 | BZ60: 109 | CA60: 61 | CE60: 1566 | CF60: 0 | CG60: 0 | CM60: 0 | CO60: 0 | CP60: =(P60+Q60+S60) -> 1322.07 | CQ60: =ROUND((ROUND((AC60*AW60*1),2)*BC60),2) -> 1322.07 | CR60: =(ROUND((ROUND(((ET60)*AV60*1),2)*BB60),2)+ROUND((ROUND(((AE60-(EU60))*AV60*1),2)*BS60),2)) -> 0 | CS60: =(ROUND((ROUND(((EU60)*AV60*1),2)*BS60),2)+ROUND((ROUND(((AE60-(EU60))*AV60*1),2)*BS60),2)) -> 0 | CT60: =ROUND((ROUND((AF60*AV60*1),2)*BA60),2) -> 0 | CU60: =AG60 -> 0 | CV60: =(AH60*AV60) -> 0 | CW60: =AI60 -> 0 | CX60: =AJ60 -> 0 | CY60: =(ROUND((((S60+ROUND((ROUND(((EU60)*AV60*1),2)*BS60),2))*AT60)/100),2)+ROUND(((ROUND((ROUND(((AE60-(EU60))*AV60*1),2)*BS60),2)*AT60)/100),2)) -> 0 | CZ60: =(ROUND((((S60+ROUND((ROUND(((EU60)*AV60*1),2)*BS60),2))*AU60)/100),2)+ROUND(((ROUND((ROUND(((AE60-(EU60))*AV60*1),2)*BS60),2)*AU60)/100),2)) -> 0 | DN60: 0 | DO60: 0 | DP60: 1 | DQ60: 1 | DU60: 1010 | DV60: шт. | DW60: шт. | DX60: 1 | EE60: 85635395 | EF60: 30 | EG60: Строительные работы | EH60: 0 | EJ60: 1 | EK60: 23 | EL60: ТСН-2001.3-18. Отопление - внутренние устройства | EM60: ТСН-2001.3-18-1 | EQ60: 0 | ER60: 0 | ES60: 1322.07 | ET60: 0 | EU60: 0 | EV60: 0 | EW60: 0 | EX60: 0 | FQ60: 0 | FR60: 0 | FS60: 0 | FX60: 109 | FY60: 61 | GA60: [15 560 / 1,22 / 9,84] + 2% Заг.скл | GD60: 1 | GF60: 1104844905 | GG60: 2 | GH60: 4 | GI60: -2 | GJ60: 0 | GK60: 0 | GL60: =ROUND(IF(AND(BH60=3,BI60=3,FS60<>0),P60,0),2) -> 0 | GM60: =ROUND(O60+X60+Y60,2)+GX60 -> 1322.07 | GN60: =IF(OR(BI60=0,BI60=1),GM60-GX60,0) -> 1322.07 | GO60: =IF(BI60=2,GM60-GX60,0) -> 0 | GP60: =IF(BI60=4,GM60-GX60,0) -> 0 | GR60: 0 | GS60: 2 | GT60: 0 | GV60: =ROUND((GT60),6) -> 0 | GW60: 1 | GX60: =ROUND(HC60*I60,2) -> 0 | HA60: 0 | HB60: 0 | HC60: =GV60*GW60 -> 0 | HE60: 0 | HF60: 2 | HS60: 0 | IK60: 0
A61: 18 | B61: 1 | C61: 66 | E61: 2,2 | F61: КА. п. 15 | G61: Сmальной nанельный paguamop PRADO Classic, mun 20, Bыcoma Н = 500 мм, PRADO Classic-20-500-2000 | H61: шт. | I61: =I57*J61 -> 1 | J61: 50 | K61: 50 | O61: =ROUND(CP61,2) -> 13009.17 | P61: =ROUND((ROUND((AC61*AW61*I61),2)*BC61),2) -> 13009.17 | Q61: =(ROUND((ROUND(((ET61)*AV61*I61),2)*BB61),2)+ROUND((ROUND(((AE61-(EU61))*AV61*I61),2)*BS61),2)) -> 0 | R61: =(ROUND((ROUND(((EU61)*AV61*I61),2)*BS61),2)+ROUND((ROUND(((AE61-(EU61))*AV61*I61),2)*BS61),2)) -> 0 | S61: =ROUND((ROUND((AF61*AV61*I61),2)*BA61),2) -> 0 | T61: =ROUND(CU61*I61,2) -> 0 | U61: =CV61*I61 -> 0 | V61: =CW61*I61 -> 0 | W61: =ROUND(CX61*I61,2) -> 0 | X61: =(ROUND((((S61+ROUND((ROUND(((EU61)*AV61*I61),2)*BS61),2))*AT61)/100),2)+ROUND(((ROUND((ROUND(((AE61-(EU61))*AV61*I61),2)*BS61),2)*AT61)/100),2)) -> 0 | Y61: =(ROUND((((S61+ROUND((ROUND(((EU61)*AV61*I61),2)*BS61),2))*AU61)/100),2)+ROUND(((ROUND((ROUND(((AE61-(EU61))*AV61*I61),2)*BS61),2)*AU61)/100),2)) -> 0 | AA61: 86551703 | AB61: =ROUND((AC61+AD61+AF61),6) -> 1322.07 | AC61: =ROUND((ES61),6) -> 1322.07 | AD61: =ROUND((((ET61)-(EU61))+AE61),6) -> 0 | AE61: =ROUND((EU61),6) -> 0 | AF61: =ROUND((EV61),6) -> 0 | AG61: =ROUND((AP61),6) -> 0 | AH61: =(EW61) -> 0 | AI61: =(EX61) -> 0 | AJ61: =(AS61) -> 0 | AK61: 1322.07 | AL61: 1322.07 | AM61: 0 | AN61: 0 | AO61: 0 | AP61: 0 | AQ61: 0 | AR61: 0 | AS61: 0 | AT61: 109 | AU61: 61 | AV61: 1 | AW61: 1 | AZ61: 1 | BA61: 1 | BB61: 1 | BC61: 9.84 | BH61: 3 | BI61: 1 | BM61: 23 | BN61: 0 | BP61: 0 | BQ61: 30 | BR61: 0 | BS61: 1 | BT61: 1 | BU61: 1 | BV61: 1 | BW61: 1 | BX61: 1 | BZ61: 109 | CA61: 61 | CE61: 1566 | CF61: 0 | CG61: 0 | CM61: 0 | CO61: 0 | CP61: =(P61+Q61+S61) -> 13009.17 | CQ61: =ROUND((ROUND((AC61*AW61*1),2)*BC61),2) -> 13009.17 | CR61: =(ROUND((ROUND(((ET61)*AV61*1),2)*BB61),2)+ROUND((ROUND(((AE61-(EU61))*AV61*1),2)*BS61),2)) -> 0 | CS61: =(ROUND((ROUND(((EU61)*AV61*1),2)*BS61),2)+ROUND((ROUND(((AE61-(EU61))*AV61*1),2)*BS61),2)) -> 0 | CT61: =ROUND((ROUND((AF61*AV61*1),2)*BA61),2) -> 0 | CU61: =AG61 -> 0 | CV61: =(AH61*AV61) -> 0 | CW61: =AI61 -> 0 | CX61: =AJ61 -> 0 | CY61: =(ROUND((((S61+ROUND((ROUND(((EU61)*AV61*1),2)*BS61),2))*AT61)/100),2)+ROUND(((ROUND((ROUND(((AE61-(EU61))*AV61*1),2)*BS61),2)*AT61)/100),2)) -> 0 | CZ61: =(ROUND((((S61+ROUND((ROUND(((EU61)*AV61*1),2)*BS61),2))*AU61)/100),2)+ROUND(((ROUND((ROUND(((AE61-(EU61))*AV61*1),2)*BS61),2)*AU61)/100),2)) -> 0 | DN61: 0 | DO61: 0 | DP61: 1 | DQ61: 1 | DU61: 1010 | DV61: шт. | DW61: шт. | DX61: 1 | EE61: 85635395 | EF61: 30 | EG61: Строительные работы | EH61: 0 | EJ61: 1 | EK61: 23 | EL61: ТСН-2001.3-18. Отопление - внутренние устройства | EM61: ТСН-2001.3-18-1 | EQ61: 0 | ER61: 1322.07 | ES61: 1322.07 | ET61: 0 | EU61: 0 | EV61: 0 | EW61: 0 | EX61: 0 | EZ61: 5 | FC61: 1 | FD61: 18 | FF61: 15560 | FQ61: 0 | FR61: 0 | FS61: 0 | FX61: 109 | FY61: 61 | GA61: [15 560 / 1,22 / 9,84] + 2% Заг.скл | GD61: 1 | GF61: 1104844905 | GG61: 2 | GH61: 3 | GI61: 5 | GJ61: 0 | GK61: 0 | GL61: =ROUND(IF(AND(BH61=3,BI61=3,FS61<>0),P61,0),2) -> 0 | GM61: =ROUND(O61+X61+Y61,2)+GX61 -> 13009.17 | GN61: =IF(OR(BI61=0,BI61=1),GM61-GX61,0) -> 13009.17 | GO61: =IF(BI61=2,GM61-GX61,0) -> 0 | GP61: =IF(BI61=4,GM61-GX61,0) -> 0 | GR61: 1 | GS61: 1 | GT61: 0 | GV61: =ROUND((GT61),6) -> 0 | GW61: 1 | GX61: =ROUND(HC61*I61,2) -> 0 | HA61: 0 | HB61: 0 | HC61: =GV61*GW61 -> 0 | HE61: 0 | HF61: 2 | HS61: 0 | IK61: 0
A62: 17 | B62: 1 | C62: =ROW(SmtRes!A87) -> 87 | D62: =ROW(EtalonRes!A50) -> 50 | E62: 3 | F62: 3.18-25-1 | G62: Установка радиаторов стальных панельных однорядных с креплением к стене длиной до 1600 мм (вентиль слева) | H62: 100 шт. | I62: =ROUND((9+13+15+25+3+20+13+15+3+24+2+10)/100,9) -> 1.52 | J62: 0 | K62: =ROUND((9+13+15+25+3+20+13+15+3+24+2+10)/100,9) -> 1.52 | O62: =ROUND(CP62,2) -> 5511.81 | P62: =ROUND((ROUND((AC62*AW62*I62),2)*BC62),2) -> 3159.87 | Q62: =(ROUND((ROUND((((((ET62*1.03)*1.25)*1.2))*AV62*I62),2)*BB62),2)+ROUND((ROUND(((AE62-((((EU62*1.03)*1.25)*1.2)))*AV62*I62),2)*BS62),2)) -> 238.92 | R62: =(ROUND((ROUND((((((EU62*1.03)*1.25)*1.2))*AV62*I62),2)*BS62),2)+ROUND((ROUND(((AE62-((((EU62*1.03)*1.25)*1.2)))*AV62*I62),2)*BS62),2)) -> 25.81 | S62: =ROUND((ROUND((AF62*AV62*I62),2)*BA62),2) -> 2113.02 | T62: =ROUND(CU62*I62,2) -> 0 | U62: =CV62*I62 -> 172.20467 | V62: =CW62*I62 -> 0 | W62: =ROUND(CX62*I62,2) -> 0 | X62: =(ROUND((((S62+ROUND((ROUND((((((EU62*1.03)*1.25)*1.2))*AV62*I62),2)*BS62),2))*AT62)/100),2)+ROUND(((ROUND((ROUND(((AE62-((((EU62*1.03)*1.25)*1.2)))*AV62*I62),2)*BS62),2)*AT62)/100),2)) -> 2331.32 | Y62: =(ROUND((((S62+ROUND((ROUND((((((EU62*1.03)*1.25)*1.2))*AV62*I62),2)*BS62),2))*AU62)/100),2)+ROUND(((ROUND((ROUND(((AE62-((((EU62*1.03)*1.25)*1.2)))*AV62*I62),2)*BS62),2)*AU62)/100),2)) -> 1304.69 | AA62: 86551701 | AB62: =ROUND((AC62+AD62+AF62),6) -> 3529.031 | AC62: =ROUND(((((ES62*1)*1)*1)),6) -> 2078.86 | AD62: =ROUND(((((((ET62*1.03)*1.25)*1.2))-((((EU62*1.03)*1.25)*1.2)))+AE62),6) -> 147.31575 | AE62: =ROUND(((((EU62*1.03)*1.25)*1.2)),6) -> 15.9135 | AF62: =ROUND(((((EV62*1.03)*1.15)*1.2)),6) -> 1302.8552 | AG62: =ROUND((AP62),6) -> 0 | AH62: =((((EW62*1.03)*1.15)*1.2)) -> 106.17858 | AI62: =((((EX62*1.03)*1.25)*1.2)) -> 0 | AJ62: =(AS62) -> 0 | AK62: 3090.81 | AL62: 2078.86 | AM62: 95.35 | AN62: 10.3 | AO62: 916.6 | AP62: 0 | AQ62: 74.7 | AR62: 0 | AS62: 0 | AT62: 109 | AU62: 61 | AV62: 1.067 | AW62: 1 | AZ62: 1 | BA62: 1 | BB62: 1 | BC62: 1 | BH62: 0 | BI62: 1 | BJ62: ТСН-2001.3 Доп. 81, Сб. 18, т. 25, поз. 1 | BM62: 23 | BN62: 0 | BO62: 3.18-25-1 | BP62: 1 | BQ62: 30 | BR62: 0 | BS62: 1 | BT62: 1 | BU62: 1 | BV62: 1 | BW62: 1 | BX62: 1 | BZ62: 109 | CA62: 61 | CE62: 1566 | CF62: 0 | CG62: 0 | CM62: 0 | CN62: Поправка: 3-18. О.П. п.1.8 Наименование: Затраты на тепловое испытание систем отопления с проверкой равномерности прогрева отопительных приборов Поправка: Гл.6.Прил.2.2.п.2.2.6_06.00.01.07.001 Наименование: При выполнении при капитальном ремонте и реконструкции работ, аналогичных технологическим процессам, характерным для нового строительства, и отсутствующих в сборниках на ремонтно-строительные работы ТСН-2001.6 Поправка: Гл.12.Прил.8.п.8. 3_12.00.01.11.001 Наименование: При наличии напряженных и стесненных условий производства работ (стесненность, сложность складирования и транспортной логистики и т.п.) для объектов, расположенных в пределах круговой магистральной системы улиц "Садовое кольцо" города Москвы | CO62: 0 | CP62: =(P62+Q62+S62) -> 5511.81 | CQ62: =ROUND((ROUND((AC62*AW62*1),2)*BC62),2) -> 2078.86 | CR62: =(ROUND((ROUND((((((ET62*1.03)*1.25)*1.2))*AV62*1),2)*BB62),2)+ROUND((ROUND(((AE62-((((EU62*1.03)*1.25)*1.2)))*AV62*1),2)*BS62),2)) -> 157.19 | CS62: =(ROUND((ROUND((((((EU62*1.03)*1.25)*1.2))*AV62*1),2)*BS62),2)+ROUND((ROUND(((AE62-((((EU62*1.03)*1.25)*1.2)))*AV62*1),2)*BS62),2)) -> 16.98 | CT62: =ROUND((ROUND((AF62*AV62*1),2)*BA62),2) -> 1390.15 | CU62: =AG62 -> 0 | CV62: =(AH62*AV62) -> 113.29254 | CW62: =AI62 -> 0 | CX62: =AJ62 -> 0 | CY62: =(ROUND((((S62+ROUND((ROUND((((((EU62*1.03)*1.25)*1.2))*AV62*1),2)*BS62),2))*AT62)/100),2)+ROUND(((ROUND((ROUND(((AE62-((((EU62*1.03)*1.25)*1.2)))*AV62*1),2)*BS62),2)*AT62)/100),2)) -> 2321.7 | CZ62: =(ROUND((((S62+ROUND((ROUND((((((EU62*1.03)*1.25)*1.2))*AV62*1),2)*BS62),2))*AU62)/100),2)+ROUND(((ROUND((ROUND(((AE62-((((EU62*1.03)*1.25)*1.2)))*AV62*1),2)*BS62),2)*AU62)/100),2)) -> 1299.3 | DB62: 13 | DD62: *1)*1)*1 | DE62: *1,03)*1,25)*1,2 | DF62: *1,03)*1,25)*1,2 | DG62: *1,03)*1,15)*1,2 | DI62: *1,03)*1,15)*1,2 | DJ62: *1,03)*1,25)*1,2 | DN62: 0 | DO62: 0 | DP62: 1 | DQ62: 1 | DU62: 1010 | DV62: 100 шт. | DW62: 100 шт. | DX62: 100 | EE62: 85635395 | EF62: 30 | EG62: Строительные работы | EH62: 0 | EJ62: 1 | EK62: 23 | EL62: ТСН-2001.3-18. Отопление - внутренние устройства | EM62: ТСН-2001.3-18-1 | EO62: Поправка: 3-18. О.П. п.1.8 Поправка: Гл.6.Прил.2.2.п.2.2.6_06.00.01.07.001 Поправка: Гл.12.Прил.8.п.8. 3_12.00.01.11.001 | EQ62: 131072 | ER62: 3090.81 | ES62: 2078.86 | ET62: 95.35 | EU62: 10.3 | EV62: 916.6 | EW62: 74.7 | EX62: 0 | EY62: 0 | FQ62: 0 | FR62: 0 | FS62: 0 | FX62: 109 | FY62: 61 | GD62: 1 | GF62: -1088987177 | GG62: 2 | GH62: 1 | GI62: 2 | GJ62: 0 | GK62: 0 | GL62: =ROUND(IF(AND(BH62=3,BI62=3,FS62<>0),P62,0),2) -> 0 | GM62: =ROUND(O62+X62+Y62,2)+GX62 -> 9147.82 | GN62: =IF(OR(BI62=0,BI62=1),GM62-GX62,0) -> 9147.82 | GO62: =IF(BI62=2,GM62-GX62,0) -> 0 | GP62: =IF(BI62=4,GM62-GX62,0) -> 0 | GR62: 0 | GS62: 3 | GT62: 0 | GV62: =ROUND((GT62),6) -> 0 | GW62: 1 | GX62: =ROUND(HC62*I62,2) -> 0 | HA62: 0 | HB62: 0 | HC62: =GV62*GW62 -> 0 | HS62: 0 | IK62: 0
A63: 17 | B63: 1 | C63: =ROW(SmtRes!A108) -> 108 | D63: =ROW(EtalonRes!A60) -> 60 | E63: 3 | F63: 3.18-25-1 | G63: Установка радиаторов стальных панельных однорядных с креплением к стене длиной до 1600 мм (вентиль слева) | H63: 100 шт. | I63: =ROUND((9+13+15+25+3+20+13+15+3+24+2+10)/100,9) -> 1.52 | J63: 0 | K63: =ROUND((9+13+15+25+3+20+13+15+3+24+2+10)/100,9) -> 1.52 | O63: =ROUND(CP63,2) -> 188482.13 | P63: =ROUND((ROUND((AC63*AW63*I63),2)*BC63),2) -> 65820.09 | Q63: =(ROUND((ROUND((((((ET63*1.03)*1.25)*1.2))*AV63*I63),2)*BB63),2)+ROUND((ROUND(((AE63-((((EU63*1.03)*1.25)*1.2)))*AV63*I63),2)*BS63),2)) -> 3593.36 | R63: =(ROUND((ROUND((((((EU63*1.03)*1.25)*1.2))*AV63*I63),2)*BS63),2)+ROUND((ROUND(((AE63-((((EU63*1.03)*1.25)*1.2)))*AV63*I63),2)*BS63),2)) -> 1454.39 | S63: =ROUND((ROUND((AF63*AV63*I63),2)*BA63),2) -> 119068.68 | T63: =ROUND(CU63*I63,2) -> 0 | U63: =CV63*I63 -> 172.20467 | V63: =CW63*I63 -> 0 | W63: =ROUND(CX63*I63,2) -> 0 | X63: =(ROUND((((S63+ROUND((ROUND((((((EU63*1.03)*1.25)*1.2))*AV63*I63),2)*BS63),2))*AT63)/100),2)+ROUND(((ROUND((ROUND(((AE63-((((EU63*1.03)*1.25)*1.2)))*AV63*I63),2)*BS63),2)*AT63)/100),2)) -> 131370.15 | Y63: =(ROUND((((S63+ROUND((ROUND((((((EU63*1.03)*1.25)*1.2))*AV63*I63),2)*BS63),2))*AU63)/100),2)+ROUND(((ROUND((ROUND(((AE63-((((EU63*1.03)*1.25)*1.2)))*AV63*I63),2)*BS63),2)*AU63)/100),2)) -> 73519.07 | AA63: 86551703 | AB63: =ROUND((AC63+AD63+AF63),6) -> 3529.031 | AC63: =ROUND(((((ES63*1)*1)*1)),6) -> 2078.86 | AD63: =ROUND(((((((ET63*1.03)*1.25)*1.2))-((((EU63*1.03)*1.25)*1.2)))+AE63),6) -> 147.31575 | AE63: =ROUND(((((EU63*1.03)*1.25)*1.2)),6) -> 15.9135 | AF63: =ROUND(((((EV63*1.03)*1.15)*1.2)),6) -> 1302.8552 | AG63: =ROUND((AP63),6) -> 0 | AH63: =((((EW63*1.03)*1.15)*1.2)) -> 106.17858 | AI63: =((((EX63*1.03)*1.25)*1.2)) -> 0 | AJ63: =(AS63) -> 0 | AK63: 3090.81 | AL63: 2078.86 | AM63: 95.35 | AN63: 10.3 | AO63: 916.6 | AP63: 0 | AQ63: 74.7 | AR63: 0 | AS63: 0 | AT63: 109 | AU63: 61 | AV63: 1.067 | AW63: 1 | AZ63: 1 | BA63: 56.35 | BB63: 15.04 | BC63: 20.83 | BH63: 0 | BI63: 1 | BJ63: ТСН-2001.3 Доп. 81, Сб. 18, т. 25, поз. 1 | BM63: 23 | BN63: 0 | BO63: 3.18-25-1 | BP63: 1 | BQ63: 30 | BR63: 0 | BS63: 56.35 | BT63: 1 | BU63: 1 | BV63: 1 | BW63: 1 | BX63: 1 | BZ63: 109 | CA63: 61 | CE63: 1566 | CF63: 0 | CG63: 0 | CM63: 0 | CN63: Поправка: 3-18. О.П. п.1.8 Наименование: Затраты на тепловое испытание систем отопления с проверкой равномерности прогрева отопительных приборов Поправка: Гл.6.Прил.2.2.п.2.2.6_06.00.01.07.001 Наименование: При выполнении при капитальном ремонте и реконструкции работ, аналогичных технологическим процессам, характерным для нового строительства, и отсутствующих в сборниках на ремонтно-строительные работы ТСН-2001.6 Поправка: Гл.12.Прил.8.п.8. 3_12.00.01.11.001 Наименование: При наличии напряженных и стесненных условий производства работ (стесненность, сложность складирования и транспортной логистики и т.п.) для объектов, расположенных в пределах круговой магистральной системы улиц "Садовое кольцо" города Москвы | CO63: 0 | CP63: =(P63+Q63+S63) -> 188482.13 | CQ63: =ROUND((ROUND((AC63*AW63*1),2)*BC63),2) -> 43302.65 | CR63: =(ROUND((ROUND((((((ET63*1.03)*1.25)*1.2))*AV63*1),2)*BB63),2)+ROUND((ROUND(((AE63-((((EU63*1.03)*1.25)*1.2)))*AV63*1),2)*BS63),2)) -> 2364.14 | CS63: =(ROUND((ROUND((((((EU63*1.03)*1.25)*1.2))*AV63*1),2)*BS63),2)+ROUND((ROUND(((AE63-((((EU63*1.03)*1.25)*1.2)))*AV63*1),2)*BS63),2)) -> 956.82 | CT63: =ROUND((ROUND((AF63*AV63*1),2)*BA63),2) -> 78334.95 | CU63: =AG63 -> 0 | CV63: =(AH63*AV63) -> 113.29254 | CW63: =AI63 -> 0 | CX63: =AJ63 -> 0 | CY63: =(ROUND((((S63+ROUND((ROUND((((((EU63*1.03)*1.25)*1.2))*AV63*1),2)*BS63),2))*AT63)/100),2)+ROUND(((ROUND((ROUND(((AE63-((((EU63*1.03)*1.25)*1.2)))*AV63*1),2)*BS63),2)*AT63)/100),2)) -> 130827.8 | CZ63: =(ROUND((((S63+ROUND((ROUND((((((EU63*1.03)*1.25)*1.2))*AV63*1),2)*BS63),2))*AU63)/100),2)+ROUND(((ROUND((ROUND(((AE63-((((EU63*1.03)*1.25)*1.2)))*AV63*1),2)*BS63),2)*AU63)/100),2)) -> 73215.56 | DB63: 16 | DD63: *1)*1)*1 | DE63: *1,03)*1,25)*1,2 | DF63: *1,03)*1,25)*1,2 | DG63: *1,03)*1,15)*1,2 | DI63: *1,03)*1,15)*1,2 | DJ63: *1,03)*1,25)*1,2 | DN63: 0 | DO63: 0 | DP63: 1 | DQ63: 1 | DU63: 1010 | DV63: 100 шт. | DW63: 100 шт. | DX63: 100 | EE63: 85635395 | EF63: 30 | EG63: Строительные работы | EH63: 0 | EJ63: 1 | EK63: 23 | EL63: ТСН-2001.3-18. Отопление - внутренние устройства | EM63: ТСН-2001.3-18-1 | EO63: Поправка: 3-18. О.П. п.1.8 Поправка: Гл.6.Прил.2.2.п.2.2.6_06.00.01.07.001 Поправка: Гл.12.Прил.8.п.8. 3_12.00.01.11.001 | EQ63: 131072 | ER63: 3090.81 | ES63: 2078.86 | ET63: 95.35 | EU63: 10.3 | EV63: 916.6 | EW63: 74.7 | EX63: 0 | EY63: 0 | FQ63: 0 | FR63: 0 | FS63: 0 | FX63: 109 | FY63: 61 | GD63: 1 | GF63: -1088987177 | GG63: 2 | GH63: 1 | GI63: 2 | GJ63: 0 | GK63: 0 | GL63: =ROUND(IF(AND(BH63=3,BI63=3,FS63<>0),P63,0),2) -> 0 | GM63: =ROUND(O63+X63+Y63,2)+GX63 -> 393371.35 | GN63: =IF(OR(BI63=0,BI63=1),GM63-GX63,0) -> 393371.35 | GO63: =IF(BI63=2,GM63-GX63,0) -> 0 | GP63: =IF(BI63=4,GM63-GX63,0) -> 0 | GR63: 0 | GS63: 3 | GT63: 0 | GV63: =ROUND((GT63),6) -> 0 | GW63: 1 | GX63: =ROUND(HC63*I63,2) -> 0 | HA63: 0 | HB63: 0 | HC63: =GV63*GW63 -> 0 | HS63: 0 | IK63: 0
A64: 18 | B64: 1 | C64: 80 | E64: 3,1 | F64: КА. п. 2 | G64: Сmальной nанельный paguamop PRADO Classic, mun 20, Bыcoma Н = 500 мм, PRADO Classic-20-500-500 | I64: =I62*J64 -> 9 | J64: 5.9210526 | K64: 5.9210526 | O64: =ROUND(CP64,2) -> 3887.73 | P64: =ROUND((ROUND((AC64*AW64*I64),2)*BC64),2) -> 3887.73 | Q64: =(ROUND((ROUND(((ET64)*AV64*I64),2)*BB64),2)+ROUND((ROUND(((AE64-(EU64))*AV64*I64),2)*BS64),2)) -> 0 | R64: =(ROUND((ROUND(((EU64)*AV64*I64),2)*BS64),2)+ROUND((ROUND(((AE64-(EU64))*AV64*I64),2)*BS64),2)) -> 0 | S64: =ROUND((ROUND((AF64*AV64*I64),2)*BA64),2) -> 0 | T64: =ROUND(CU64*I64,2) -> 0 | U64: =CV64*I64 -> 0 | V64: =CW64*I64 -> 0 | W64: =ROUND(CX64*I64,2) -> 0 | X64: =(ROUND((((S64+ROUND((ROUND(((EU64)*AV64*I64),2)*BS64),2))*AT64)/100),2)+ROUND(((ROUND((ROUND(((AE64-(EU64))*AV64*I64),2)*BS64),2)*AT64)/100),2)) -> 0 | Y64: =(ROUND((((S64+ROUND((ROUND(((EU64)*AV64*I64),2)*BS64),2))*AU64)/100),2)+ROUND(((ROUND((ROUND(((AE64-(EU64))*AV64*I64),2)*BS64),2)*AU64)/100),2)) -> 0 | AA64: 86551701 | AB64: =ROUND((AC64+AD64+AF64),6) -> 431.97 | AC64: =ROUND((ES64),6) -> 431.97 | AD64: =ROUND((((ET64)-(EU64))+AE64),6) -> 0 | AE64: =ROUND((EU64),6) -> 0 | AF64: =ROUND((EV64),6) -> 0 | AG64: =ROUND((AP64),6) -> 0 | AH64: =(EW64) -> 0 | AI64: =(EX64) -> 0 | AJ64: =(AS64) -> 0 | AK64: 431.97 | AL64: 431.97 | AM64: 0 | AN64: 0 | AO64: 0 | AP64: 0 | AQ64: 0 | AR64: 0 | AS64: 0 | AT64: 109 | AU64: 61 | AV64: 1 | AW64: 1 | AZ64: 1 | BA64: 1 | BB64: 1 | BC64: 1 | BH64: 3 | BI64: 1 | BM64: 23 | BN64: 0 | BP64: 0 | BQ64: 30 | BR64: 0 | BS64: 1 | BT64: 1 | BU64: 1 | BV64: 1 | BW64: 1 | BX64: 1 | BZ64: 109 | CA64: 61 | CE64: 1566 | CF64: 0 | CG64: 0 | CM64: 0 | CO64: 0 | CP64: =(P64+Q64+S64) -> 3887.73 | CQ64: =ROUND((ROUND((AC64*AW64*1),2)*BC64),2) -> 431.97 | CR64: =(ROUND((ROUND(((ET64)*AV64*1),2)*BB64),2)+ROUND((ROUND(((AE64-(EU64))*AV64*1),2)*BS64),2)) -> 0 | CS64: =(ROUND((ROUND(((EU64)*AV64*1),2)*BS64),2)+ROUND((ROUND(((AE64-(EU64))*AV64*1),2)*BS64),2)) -> 0 | CT64: =ROUND((ROUND((AF64*AV64*1),2)*BA64),2) -> 0 | CU64: =AG64 -> 0 | CV64: =(AH64*AV64) -> 0 | CW64: =AI64 -> 0 | CX64: =AJ64 -> 0 | CY64: =(ROUND((((S64+ROUND((ROUND(((EU64)*AV64*1),2)*BS64),2))*AT64)/100),2)+ROUND(((ROUND((ROUND(((AE64-(EU64))*AV64*1),2)*BS64),2)*AT64)/100),2)) -> 0 | CZ64: =(ROUND((((S64+ROUND((ROUND(((EU64)*AV64*1),2)*BS64),2))*AU64)/100),2)+ROUND(((ROUND((ROUND(((AE64-(EU64))*AV64*1),2)*BS64),2)*AU64)/100),2)) -> 0 | DN64: 0 | DO64: 0 | DP64: 1 | DQ64: 1 | EE64: 85635395 | EF64: 30 | EG64: Строительные работы | EH64: 0 | EJ64: 1 | EK64: 23 | EL64: ТСН-2001.3-18. Отопление - внутренние устройства | EM64: ТСН-2001.3-18-1 | EQ64: 0 | ER64: 0 | ES64: 431.97 | ET64: 0 | EU64: 0 | EV64: 0 | EW64: 0 | EX64: 0 | FQ64: 0 | FR64: 0 | FS64: 0 | FX64: 109 | FY64: 61 | GA64: [5 084 / 1,22 / 9,84] + 2% Заг.скл | GD64: 1 | GF64: -401967197 | GG64: 2 | GH64: 4 | GI64: -2 | GJ64: 0 | GK64: 0 | GL64: =ROUND(IF(AND(BH64=3,BI64=3,FS64<>0),P64,0),2) -> 0 | GM64: =ROUND(O64+X64+Y64,2)+GX64 -> 3887.73 | GN64: =IF(OR(BI64=0,BI64=1),GM64-GX64,0) -> 3887.73 | GO64: =IF(BI64=2,GM64-GX64,0) -> 0 | GP64: =IF(BI64=4,GM64-GX64,0) -> 0 | GR64: 0 | GS64: 2 | GT64: 0 | GV64: =ROUND((GT64),6) -> 0 | GW64: 1 | GX64: =ROUND(HC64*I64,2) -> 0 | HA64: 0 | HB64: 0 | HC64: =GV64*GW64 -> 0 | HE64: 0 | HF64: 2 | HS64: 0 | IK64: 0
A65: 18 | B65: 1 | C65: 101 | E65: 3,1 | F65: КА. п. 2 | G65: Сmальной nанельный paguamop PRADO Classic, mun 20, Bыcoma Н = 500 мм, PRADO Classic-20-500-500 | I65: =I63*J65 -> 9 | J65: 5.9210526 | K65: 5.9210526 | O65: =ROUND(CP65,2) -> 38255.26 | P65: =ROUND((ROUND((AC65*AW65*I65),2)*BC65),2) -> 38255.26 | Q65: =(ROUND((ROUND(((ET65)*AV65*I65),2)*BB65),2)+ROUND((ROUND(((AE65-(EU65))*AV65*I65),2)*BS65),2)) -> 0 | R65: =(ROUND((ROUND(((EU65)*AV65*I65),2)*BS65),2)+ROUND((ROUND(((AE65-(EU65))*AV65*I65),2)*BS65),2)) -> 0 | S65: =ROUND((ROUND((AF65*AV65*I65),2)*BA65),2) -> 0 | T65: =ROUND(CU65*I65,2) -> 0 | U65: =CV65*I65 -> 0 | V65: =CW65*I65 -> 0 | W65: =ROUND(CX65*I65,2) -> 0 | X65: =(ROUND((((S65+ROUND((ROUND(((EU65)*AV65*I65),2)*BS65),2))*AT65)/100),2)+ROUND(((ROUND((ROUND(((AE65-(EU65))*AV65*I65),2)*BS65),2)*AT65)/100),2)) -> 0 | Y65: =(ROUND((((S65+ROUND((ROUND(((EU65)*AV65*I65),2)*BS65),2))*AU65)/100),2)+ROUND(((ROUND((ROUND(((AE65-(EU65))*AV65*I65),2)*BS65),2)*AU65)/100),2)) -> 0 | AA65: 86551703 | AB65: =ROUND((AC65+AD65+AF65),6) -> 431.97 | AC65: =ROUND((ES65),6) -> 431.97 | AD65: =ROUND((((ET65)-(EU65))+AE65),6) -> 0 | AE65: =ROUND((EU65),6) -> 0 | AF65: =ROUND((EV65),6) -> 0 | AG65: =ROUND((AP65),6) -> 0 | AH65: =(EW65) -> 0 | AI65: =(EX65) -> 0 | AJ65: =(AS65) -> 0 | AK65: 431.97 | AL65: 431.97 | AM65: 0 | AN65: 0 | AO65: 0 | AP65: 0 | AQ65: 0 | AR65: 0 | AS65: 0 | AT65: 109 | AU65: 61 | AV65: 1 | AW65: 1 | AZ65: 1 | BA65: 1 | BB65: 1 | BC65: 9.84 | BH65: 3 | BI65: 1 | BM65: 23 | BN65: 0 | BP65: 0 | BQ65: 30 | BR65: 0 | BS65: 1 | BT65: 1 | BU65: 1 | BV65: 1 | BW65: 1 | BX65: 1 | BZ65: 109 | CA65: 61 | CE65: 1566 | CF65: 0 | CG65: 0 | CM65: 0 | CO65: 0 | CP65: =(P65+Q65+S65) -> 38255.26 | CQ65: =ROUND((ROUND((AC65*AW65*1),2)*BC65),2) -> 4250.58 | CR65: =(ROUND((ROUND(((ET65)*AV65*1),2)*BB65),2)+ROUND((ROUND(((AE65-(EU65))*AV65*1),2)*BS65),2)) -> 0 | CS65: =(ROUND((ROUND(((EU65)*AV65*1),2)*BS65),2)+ROUND((ROUND(((AE65-(EU65))*AV65*1),2)*BS65),2)) -> 0 | CT65: =ROUND((ROUND((AF65*AV65*1),2)*BA65),2) -> 0 | CU65: =AG65 -> 0 | CV65: =(AH65*AV65) -> 0 | CW65: =AI65 -> 0 | CX65: =AJ65 -> 0 | CY65: =(ROUND((((S65+ROUND((ROUND(((EU65)*AV65*1),2)*BS65),2))*AT65)/100),2)+ROUND(((ROUND((ROUND(((AE65-(EU65))*AV65*1),2)*BS65),2)*AT65)/100),2)) -> 0 | CZ65: =(ROUND((((S65+ROUND((ROUND(((EU65)*AV65*1),2)*BS65),2))*AU65)/100),2)+ROUND(((ROUND((ROUND(((AE65-(EU65))*AV65*1),2)*BS65),2)*AU65)/100),2)) -> 0 | DN65: 0 | DO65: 0 | DP65: 1 | DQ65: 1 | EE65: 85635395 | EF65: 30 | EG65: Строительные работы | EH65: 0 | EJ65: 1 | EK65: 23 | EL65: ТСН-2001.3-18. Отопление - внутренние устройства | EM65: ТСН-2001.3-18-1 | EQ65: 0 | ER65: 431.97 | ES65: 431.97 | ET65: 0 | EU65: 0 | EV65: 0 | EW65: 0 | EX65: 0 | EZ65: 5 | FC65: 1 | FD65: 18 | FF65: 5084 | FQ65: 0 | FR65: 0 | FS65: 0 | FX65: 109 | FY65: 61 | GA65: [5 084 / 1,22 / 9,84] + 2% Заг.скл | GD65: 1 | GF65: -401967197 | GG65: 2 | GH65: 3 | GI65: 5 | GJ65: 0 | GK65: 0 | GL65: =ROUND(IF(AND(BH65=3,BI65=3,FS65<>0),P65,0),2) -> 0 | GM65: =ROUND(O65+X65+Y65,2)+GX65 -> 38255.26 | GN65: =IF(OR(BI65=0,BI65=1),GM65-GX65,0) -> 38255.26 | GO65: =IF(BI65=2,GM65-GX65,0) -> 0 | GP65: =IF(BI65=4,GM65-GX65,0) -> 0 | GR65: 1 | GS65: 1 | GT65: 0 | GV65: =ROUND((GT65),6) -> 0 | GW65: 1 | GX65: =ROUND(HC65*I65,2) -> 0 | HA65: 0 | HB65: 0 | HC65: =GV65*GW65 -> 0 | HE65: 0 | HF65: 2 | HS65: 0 | IK65: 0
A66: 18 | B66: 1 | C66: 81 | E66: 3,2 | F66: КА. п. 3 | G66: Сmальной nанельный paguamop PRADO Classic, mun 20, Bыcoma Н = 500 мм, PRADO Classic-20-500-600 | I66: =I62*J66 -> 13 | J66: 8.5526316 | K66: 8.5526316 | O66: =ROUND(CP66,2) -> 6425.25 | P66: =ROUND((ROUND((AC66*AW66*I66),2)*BC66),2) -> 6425.25 | Q66: =(ROUND((ROUND(((ET66)*AV66*I66),2)*BB66),2)+ROUND((ROUND(((AE66-(EU66))*AV66*I66),2)*BS66),2)) -> 0 | R66: =(ROUND((ROUND(((EU66)*AV66*I66),2)*BS66),2)+ROUND((ROUND(((AE66-(EU66))*AV66*I66),2)*BS66),2)) -> 0 | S66: =ROUND((ROUND((AF66*AV66*I66),2)*BA66),2) -> 0 | T66: =ROUND(CU66*I66,2) -> 0 | U66: =CV66*I66 -> 0 | V66: =CW66*I66 -> 0 | W66: =ROUND(CX66*I66,2) -> 0 | X66: =(ROUND((((S66+ROUND((ROUND(((EU66)*AV66*I66),2)*BS66),2))*AT66)/100),2)+ROUND(((ROUND((ROUND(((AE66-(EU66))*AV66*I66),2)*BS66),2)*AT66)/100),2)) -> 0 | Y66: =(ROUND((((S66+ROUND((ROUND(((EU66)*AV66*I66),2)*BS66),2))*AU66)/100),2)+ROUND(((ROUND((ROUND(((AE66-(EU66))*AV66*I66),2)*BS66),2)*AU66)/100),2)) -> 0 | AA66: 86551701 | AB66: =ROUND((AC66+AD66+AF66),6) -> 494.25 | AC66: =ROUND((ES66),6) -> 494.25 | AD66: =ROUND((((ET66)-(EU66))+AE66),6) -> 0 | AE66: =ROUND((EU66),6) -> 0 | AF66: =ROUND((EV66),6) -> 0 | AG66: =ROUND((AP66),6) -> 0 | AH66: =(EW66) -> 0 | AI66: =(EX66) -> 0 | AJ66: =(AS66) -> 0 | AK66: 494.25 | AL66: 494.25 | AM66: 0 | AN66: 0 | AO66: 0 | AP66: 0 | AQ66: 0 | AR66: 0 | AS66: 0 | AT66: 109 | AU66: 61 | AV66: 1 | AW66: 1 | AZ66: 1 | BA66: 1 | BB66: 1 | BC66: 1 | BH66: 3 | BI66: 1 | BM66: 23 | BN66: 0 | BP66: 0 | BQ66: 30 | BR66: 0 | BS66: 1 | BT66: 1 | BU66: 1 | BV66: 1 | BW66: 1 | BX66: 1 | BZ66: 109 | CA66: 61 | CE66: 1566 | CF66: 0 | CG66: 0 | CM66: 0 | CO66: 0 | CP66: =(P66+Q66+S66) -> 6425.25 | CQ66: =ROUND((ROUND((AC66*AW66*1),2)*BC66),2) -> 494.25 | CR66: =(ROUND((ROUND(((ET66)*AV66*1),2)*BB66),2)+ROUND((ROUND(((AE66-(EU66))*AV66*1),2)*BS66),2)) -> 0 | CS66: =(ROUND((ROUND(((EU66)*AV66*1),2)*BS66),2)+ROUND((ROUND(((AE66-(EU66))*AV66*1),2)*BS66),2)) -> 0 | CT66: =ROUND((ROUND((AF66*AV66*1),2)*BA66),2) -> 0 | CU66: =AG66 -> 0 | CV66: =(AH66*AV66) -> 0 | CW66: =AI66 -> 0 | CX66: =AJ66 -> 0 | CY66: =(ROUND((((S66+ROUND((ROUND(((EU66)*AV66*1),2)*BS66),2))*AT66)/100),2)+ROUND(((ROUND((ROUND(((AE66-(EU66))*AV66*1),2)*BS66),2)*AT66)/100),2)) -> 0 | CZ66: =(ROUND((((S66+ROUND((ROUND(((EU66)*AV66*1),2)*BS66),2))*AU66)/100),2)+ROUND(((ROUND((ROUND(((AE66-(EU66))*AV66*1),2)*BS66),2)*AU66)/100),2)) -> 0 | DN66: 0 | DO66: 0 | DP66: 1 | DQ66: 1 | EE66: 85635395 | EF66: 30 | EG66: Строительные работы | EH66: 0 | EJ66: 1 | EK66: 23 | EL66: ТСН-2001.3-18. Отопление - внутренние устройства | EM66: ТСН-2001.3-18-1 | EQ66: 0 | ER66: 0 | ES66: 494.25 | ET66: 0 | EU66: 0 | EV66: 0 | EW66: 0 | EX66: 0 | FQ66: 0 | FR66: 0 | FS66: 0 | FX66: 109 | FY66: 61 | GA66: [5 817 / 1,22 / 9,84] + 2% Заг.скл | GD66: 1 | GF66: 1290624388 | GG66: 2 | GH66: 4 | GI66: -2 | GJ66: 0 | GK66: 0 | GL66: =ROUND(IF(AND(BH66=3,BI66=3,FS66<>0),P66,0),2) -> 0 | GM66: =ROUND(O66+X66+Y66,2)+GX66 -> 6425.25 | GN66: =IF(OR(BI66=0,BI66=1),GM66-GX66,0) -> 6425.25 | GO66: =IF(BI66=2,GM66-GX66,0) -> 0 | GP66: =IF(BI66=4,GM66-GX66,0) -> 0 | GR66: 0 | GS66: 2 | GT66: 0 | GV66: =ROUND((GT66),6) -> 0 | GW66: 1 | GX66: =ROUND(HC66*I66,2) -> 0 | HA66: 0 | HB66: 0 | HC66: =GV66*GW66 -> 0 | HE66: 0 | HF66: 2 | HS66: 0 | IK66: 0
A67: 18 | B67: 1 | C67: 102 | E67: 3,2 | F67: КА. п. 3 | G67: Сmальной nанельный paguamop PRADO Classic, mun 20, Bыcoma Н = 500 мм, PRADO Classic-20-500-600 | I67: =I63*J67 -> 13 | J67: 8.5526316 | K67: 8.5526316 | O67: =ROUND(CP67,2) -> 63224.46 | P67: =ROUND((ROUND((AC67*AW67*I67),2)*BC67),2) -> 63224.46 | Q67: =(ROUND((ROUND(((ET67)*AV67*I67),2)*BB67),2)+ROUND((ROUND(((AE67-(EU67))*AV67*I67),2)*BS67),2)) -> 0 | R67: =(ROUND((ROUND(((EU67)*AV67*I67),2)*BS67),2)+ROUND((ROUND(((AE67-(EU67))*AV67*I67),2)*BS67),2)) -> 0 | S67: =ROUND((ROUND((AF67*AV67*I67),2)*BA67),2) -> 0 | T67: =ROUND(CU67*I67,2) -> 0 | U67: =CV67*I67 -> 0 | V67: =CW67*I67 -> 0 | W67: =ROUND(CX67*I67,2) -> 0 | X67: =(ROUND((((S67+ROUND((ROUND(((EU67)*AV67*I67),2)*BS67),2))*AT67)/100),2)+ROUND(((ROUND((ROUND(((AE67-(EU67))*AV67*I67),2)*BS67),2)*AT67)/100),2)) -> 0 | Y67: =(ROUND((((S67+ROUND((ROUND(((EU67)*AV67*I67),2)*BS67),2))*AU67)/100),2)+ROUND(((ROUND((ROUND(((AE67-(EU67))*AV67*I67),2)*BS67),2)*AU67)/100),2)) -> 0 | AA67: 86551703 | AB67: =ROUND((AC67+AD67+AF67),6) -> 494.25 | AC67: =ROUND((ES67),6) -> 494.25 | AD67: =ROUND((((ET67)-(EU67))+AE67),6) -> 0 | AE67: =ROUND((EU67),6) -> 0 | AF67: =ROUND((EV67),6) -> 0 | AG67: =ROUND((AP67),6) -> 0 | AH67: =(EW67) -> 0 | AI67: =(EX67) -> 0 | AJ67: =(AS67) -> 0 | AK67: 494.25 | AL67: 494.25 | AM67: 0 | AN67: 0 | AO67: 0 | AP67: 0 | AQ67: 0 | AR67: 0 | AS67: 0 | AT67: 109 | AU67: 61 | AV67: 1 | AW67: 1 | AZ67: 1 | BA67: 1 | BB67: 1 | BC67: 9.84 | BH67: 3 | BI67: 1 | BM67: 23 | BN67: 0 | BP67: 0 | BQ67: 30 | BR67: 0 | BS67: 1 | BT67: 1 | BU67: 1 | BV67: 1 | BW67: 1 | BX67: 1 | BZ67: 109 | CA67: 61 | CE67: 1566 | CF67: 0 | CG67: 0 | CM67: 0 | CO67: 0 | CP67: =(P67+Q67+S67) -> 63224.46 | CQ67: =ROUND((ROUND((AC67*AW67*1),2)*BC67),2) -> 4863.42 | CR67: =(ROUND((ROUND(((ET67)*AV67*1),2)*BB67),2)+ROUND((ROUND(((AE67-(EU67))*AV67*1),2)*BS67),2)) -> 0 | CS67: =(ROUND((ROUND(((EU67)*AV67*1),2)*BS67),2)+ROUND((ROUND(((AE67-(EU67))*AV67*1),2)*BS67),2)) -> 0 | CT67: =ROUND((ROUND((AF67*AV67*1),2)*BA67),2) -> 0 | CU67: =AG67 -> 0 | CV67: =(AH67*AV67) -> 0 | CW67: =AI67 -> 0 | CX67: =AJ67 -> 0 | CY67: =(ROUND((((S67+ROUND((ROUND(((EU67)*AV67*1),2)*BS67),2))*AT67)/100),2)+ROUND(((ROUND((ROUND(((AE67-(EU67))*AV67*1),2)*BS67),2)*AT67)/100),2)) -> 0 | CZ67: =(ROUND((((S67+ROUND((ROUND(((EU67)*AV67*1),2)*BS67),2))*AU67)/100),2)+ROUND(((ROUND((ROUND(((AE67-(EU67))*AV67*1),2)*BS67),2)*AU67)/100),2)) -> 0 | DN67: 0 | DO67: 0 | DP67: 1 | DQ67: 1 | EE67: 85635395 | EF67: 30 | EG67: Строительные работы | EH67: 0 | EJ67: 1 | EK67: 23 | EL67: ТСН-2001.3-18. Отопление - внутренние устройства | EM67: ТСН-2001.3-18-1 | EQ67: 0 | ER67: 494.25 | ES67: 494.25 | ET67: 0 | EU67: 0 | EV67: 0 | EW67: 0 | EX67: 0 | EZ67: 5 | FC67: 1 | FD67: 18 | FF67: 5817 | FQ67: 0 | FR67: 0 | FS67: 0 | FX67: 109 | FY67: 61 | GA67: [5 817 / 1,22 / 9,84] + 2% Заг.скл | GD67: 1 | GF67: 1290624388 | GG67: 2 | GH67: 3 | GI67: 5 | GJ67: 0 | GK67: 0 | GL67: =ROUND(IF(AND(BH67=3,BI67=3,FS67<>0),P67,0),2) -> 0 | GM67: =ROUND(O67+X67+Y67,2)+GX67 -> 63224.46 | GN67: =IF(OR(BI67=0,BI67=1),GM67-GX67,0) -> 63224.46 | GO67: =IF(BI67=2,GM67-GX67,0) -> 0 | GP67: =IF(BI67=4,GM67-GX67,0) -> 0 | GR67: 1 | GS67: 1 | GT67: 0 | GV67: =ROUND((GT67),6) -> 0 | GW67: 1 | GX67: =ROUND(HC67*I67,2) -> 0 | HA67: 0 | HB67: 0 | HC67: =GV67*GW67 -> 0 | HE67: 0 | HF67: 2 | HS67: 0 | IK67: 0
A68: 18 | B68: 1 | C68: 82 | E68: 3,3 | F68: КА. п. 4 | G68: Сmальной nанельный paguamop PRADO Classic, mun 20, Bыcoma Н = 500 мм, PRADO Classic-20-500-700 | I68: =I62*J68 -> 15 | J68: 9.8684211 | K68: 9.868421 | O68: =ROUND(CP68,2) -> 8184.75 | P68: =ROUND((ROUND((AC68*AW68*I68),2)*BC68),2) -> 8184.75 | Q68: =(ROUND((ROUND(((ET68)*AV68*I68),2)*BB68),2)+ROUND((ROUND(((AE68-(EU68))*AV68*I68),2)*BS68),2)) -> 0 | R68: =(ROUND((ROUND(((EU68)*AV68*I68),2)*BS68),2)+ROUND((ROUND(((AE68-(EU68))*AV68*I68),2)*BS68),2)) -> 0 | S68: =ROUND((ROUND((AF68*AV68*I68),2)*BA68),2) -> 0 | T68: =ROUND(CU68*I68,2) -> 0 | U68: =CV68*I68 -> 0 | V68: =CW68*I68 -> 0 | W68: =ROUND(CX68*I68,2) -> 0 | X68: =(ROUND((((S68+ROUND((ROUND(((EU68)*AV68*I68),2)*BS68),2))*AT68)/100),2)+ROUND(((ROUND((ROUND(((AE68-(EU68))*AV68*I68),2)*BS68),2)*AT68)/100),2)) -> 0 | Y68: =(ROUND((((S68+ROUND((ROUND(((EU68)*AV68*I68),2)*BS68),2))*AU68)/100),2)+ROUND(((ROUND((ROUND(((AE68-(EU68))*AV68*I68),2)*BS68),2)*AU68)/100),2)) -> 0 | AA68: 86551701 | AB68: =ROUND((AC68+AD68+AF68),6) -> 545.65 | AC68: =ROUND((ES68),6) -> 545.65 | AD68: =ROUND((((ET68)-(EU68))+AE68),6) -> 0 | AE68: =ROUND((EU68),6) -> 0 | AF68: =ROUND((EV68),6) -> 0 | AG68: =ROUND((AP68),6) -> 0 | AH68: =(EW68) -> 0 | AI68: =(EX68) -> 0 | AJ68: =(AS68) -> 0 | AK68: 545.65 | AL68: 545.65 | AM68: 0 | AN68: 0 | AO68: 0 | AP68: 0 | AQ68: 0 | AR68: 0 | AS68: 0 | AT68: 109 | AU68: 61 | AV68: 1 | AW68: 1 | AZ68: 1 | BA68: 1 | BB68: 1 | BC68: 1 | BH68: 3 | BI68: 1 | BM68: 23 | BN68: 0 | BP68: 0 | BQ68: 30 | BR68: 0 | BS68: 1 | BT68: 1 | BU68: 1 | BV68: 1 | BW68: 1 | BX68: 1 | BZ68: 109 | CA68: 61 | CE68: 1566 | CF68: 0 | CG68: 0 | CM68: 0 | CO68: 0 | CP68: =(P68+Q68+S68) -> 8184.75 | CQ68: =ROUND((ROUND((AC68*AW68*1),2)*BC68),2) -> 545.65 | CR68: =(ROUND((ROUND(((ET68)*AV68*1),2)*BB68),2)+ROUND((ROUND(((AE68-(EU68))*AV68*1),2)*BS68),2)) -> 0 | CS68: =(ROUND((ROUND(((EU68)*AV68*1),2)*BS68),2)+ROUND((ROUND(((AE68-(EU68))*AV68*1),2)*BS68),2)) -> 0 | CT68: =ROUND((ROUND((AF68*AV68*1),2)*BA68),2) -> 0 | CU68: =AG68 -> 0 | CV68: =(AH68*AV68) -> 0 | CW68: =AI68 -> 0 | CX68: =AJ68 -> 0 | CY68: =(ROUND((((S68+ROUND((ROUND(((EU68)*AV68*1),2)*BS68),2))*AT68)/100),2)+ROUND(((ROUND((ROUND(((AE68-(EU68))*AV68*1),2)*BS68),2)*AT68)/100),2)) -> 0 | CZ68: =(ROUND((((S68+ROUND((ROUND(((EU68)*AV68*1),2)*BS68),2))*AU68)/100),2)+ROUND(((ROUND((ROUND(((AE68-(EU68))*AV68*1),2)*BS68),2)*AU68)/100),2)) -> 0 | DN68: 0 | DO68: 0 | DP68: 1 | DQ68: 1 | EE68: 85635395 | EF68: 30 | EG68: Строительные работы | EH68: 0 | EJ68: 1 | EK68: 23 | EL68: ТСН-2001.3-18. Отопление - внутренние устройства | EM68: ТСН-2001.3-18-1 | EQ68: 0 | ER68: 0 | ES68: 545.65 | ET68: 0 | EU68: 0 | EV68: 0 | EW68: 0 | EX68: 0 | FQ68: 0 | FR68: 0 | FS68: 0 | FX68: 109 | FY68: 61 | GA68: [6 422 / 1,22 / 9,84] + 2% Заг.скл | GD68: 1 | GF68: 752976982 | GG68: 2 | GH68: 4 | GI68: -2 | GJ68: 0 | GK68: 0 | GL68: =ROUND(IF(AND(BH68=3,BI68=3,FS68<>0),P68,0),2) -> 0 | GM68: =ROUND(O68+X68+Y68,2)+GX68 -> 8184.75 | GN68: =IF(OR(BI68=0,BI68=1),GM68-GX68,0) -> 8184.75 | GO68: =IF(BI68=2,GM68-GX68,0) -> 0 | GP68: =IF(BI68=4,GM68-GX68,0) -> 0 | GR68: 0 | GS68: 2 | GT68: 0 | GV68: =ROUND((GT68),6) -> 0 | GW68: 1 | GX68: =ROUND(HC68*I68,2) -> 0 | HA68: 0 | HB68: 0 | HC68: =GV68*GW68 -> 0 | HE68: 0 | HF68: 2 | HS68: 0 | IK68: 0
A69: 18 | B69: 1 | C69: 103 | E69: 3,3 | F69: КА. п. 4 | G69: Сmальной nанельный paguamop PRADO Classic, mun 20, Bыcoma Н = 500 мм, PRADO Classic-20-500-700 | I69: =I63*J69 -> 15 | J69: 9.8684211 | K69: 9.868421 | O69: =ROUND(CP69,2) -> 80537.94 | P69: =ROUND((ROUND((AC69*AW69*I69),2)*BC69),2) -> 80537.94 | Q69: =(ROUND((ROUND(((ET69)*AV69*I69),2)*BB69),2)+ROUND((ROUND(((AE69-(EU69))*AV69*I69),2)*BS69),2)) -> 0 | R69: =(ROUND((ROUND(((EU69)*AV69*I69),2)*BS69),2)+ROUND((ROUND(((AE69-(EU69))*AV69*I69),2)*BS69),2)) -> 0 | S69: =ROUND((ROUND((AF69*AV69*I69),2)*BA69),2) -> 0 | T69: =ROUND(CU69*I69,2) -> 0 | U69: =CV69*I69 -> 0 | V69: =CW69*I69 -> 0 | W69: =ROUND(CX69*I69,2) -> 0 | X69: =(ROUND((((S69+ROUND((ROUND(((EU69)*AV69*I69),2)*BS69),2))*AT69)/100),2)+ROUND(((ROUND((ROUND(((AE69-(EU69))*AV69*I69),2)*BS69),2)*AT69)/100),2)) -> 0 | Y69: =(ROUND((((S69+ROUND((ROUND(((EU69)*AV69*I69),2)*BS69),2))*AU69)/100),2)+ROUND(((ROUND((ROUND(((AE69-(EU69))*AV69*I69),2)*BS69),2)*AU69)/100),2)) -> 0 | AA69: 86551703 | AB69: =ROUND((AC69+AD69+AF69),6) -> 545.65 | AC69: =ROUND((ES69),6) -> 545.65 | AD69: =ROUND((((ET69)-(EU69))+AE69),6) -> 0 | AE69: =ROUND((EU69),6) -> 0 | AF69: =ROUND((EV69),6) -> 0 | AG69: =ROUND((AP69),6) -> 0 | AH69: =(EW69) -> 0 | AI69: =(EX69) -> 0 | AJ69: =(AS69) -> 0 | AK69: 545.65 | AL69: 545.65 | AM69: 0 | AN69: 0 | AO69: 0 | AP69: 0 | AQ69: 0 | AR69: 0 | AS69: 0 | AT69: 109 | AU69: 61 | AV69: 1 | AW69: 1 | AZ69: 1 | BA69: 1 | BB69: 1 | BC69: 9.84 | BH69: 3 | BI69: 1 | BM69: 23 | BN69: 0 | BP69: 0 | BQ69: 30 | BR69: 0 | BS69: 1 | BT69: 1 | BU69: 1 | BV69: 1 | BW69: 1 | BX69: 1 | BZ69: 109 | CA69: 61 | CE69: 1566 | CF69: 0 | CG69: 0 | CM69: 0 | CO69: 0 | CP69: =(P69+Q69+S69) -> 80537.94 | CQ69: =ROUND((ROUND((AC69*AW69*1),2)*BC69),2) -> 5369.2 | CR69: =(ROUND((ROUND(((ET69)*AV69*1),2)*BB69),2)+ROUND((ROUND(((AE69-(EU69))*AV69*1),2)*BS69),2)) -> 0 | CS69: =(ROUND((ROUND(((EU69)*AV69*1),2)*BS69),2)+ROUND((ROUND(((AE69-(EU69))*AV69*1),2)*BS69),2)) -> 0 | CT69: =ROUND((ROUND((AF69*AV69*1),2)*BA69),2) -> 0 | CU69: =AG69 -> 0 | CV69: =(AH69*AV69) -> 0 | CW69: =AI69 -> 0 | CX69: =AJ69 -> 0 | CY69: =(ROUND((((S69+ROUND((ROUND(((EU69)*AV69*1),2)*BS69),2))*AT69)/100),2)+ROUND(((ROUND((ROUND(((AE69-(EU69))*AV69*1),2)*BS69),2)*AT69)/100),2)) -> 0 | CZ69: =(ROUND((((S69+ROUND((ROUND(((EU69)*AV69*1),2)*BS69),2))*AU69)/100),2)+ROUND(((ROUND((ROUND(((AE69-(EU69))*AV69*1),2)*BS69),2)*AU69)/100),2)) -> 0 | DN69: 0 | DO69: 0 | DP69: 1 | DQ69: 1 | EE69: 85635395 | EF69: 30 | EG69: Строительные работы | EH69: 0 | EJ69: 1 | EK69: 23 | EL69: ТСН-2001.3-18. Отопление - внутренние устройства | EM69: ТСН-2001.3-18-1 | EQ69: 0 | ER69: 545.65 | ES69: 545.65 | ET69: 0 | EU69: 0 | EV69: 0 | EW69: 0 | EX69: 0 | EZ69: 5 | FC69: 1 | FD69: 18 | FF69: 6422 | FQ69: 0 | FR69: 0 | FS69: 0 | FX69: 109 | FY69: 61 | GA69: [6 422 / 1,22 / 9,84] + 2% Заг.скл | GD69: 1 | GF69: 752976982 | GG69: 2 | GH69: 3 | GI69: 5 | GJ69: 0 | GK69: 0 | GL69: =ROUND(IF(AND(BH69=3,BI69=3,FS69<>0),P69,0),2) -> 0 | GM69: =ROUND(O69+X69+Y69,2)+GX69 -> 80537.94 | GN69: =IF(OR(BI69=0,BI69=1),GM69-GX69,0) -> 80537.94 | GO69: =IF(BI69=2,GM69-GX69,0) -> 0 | GP69: =IF(BI69=4,GM69-GX69,0) -> 0 | GR69: 1 | GS69: 1 | GT69: 0 | GV69: =ROUND((GT69),6) -> 0 | GW69: 1 | GX69: =ROUND(HC69*I69,2) -> 0 | HA69: 0 | HB69: 0 | HC69: =GV69*GW69 -> 0 | HE69: 0 | HF69: 2 | HS69: 0 | IK69: 0
A70: 18 | B70: 1 | C70: 83 | E70: 3,4 | F70: КА. п. 5 | G70: Сmальной nанельный paguamop PRADO Classic, mun 20, Bыcoma Н = 500 мм, PRADO Classic-20-500-800 | I70: =I62*J70 -> 25 | J70: 16.447368 | K70: 16.447368 | O70: =ROUND(CP70,2) -> 15036.75 | P70: =ROUND((ROUND((AC70*AW70*I70),2)*BC70),2) -> 15036.75 | Q70: =(ROUND((ROUND(((ET70)*AV70*I70),2)*BB70),2)+ROUND((ROUND(((AE70-(EU70))*AV70*I70),2)*BS70),2)) -> 0 | R70: =(ROUND((ROUND(((EU70)*AV70*I70),2)*BS70),2)+ROUND((ROUND(((AE70-(EU70))*AV70*I70),2)*BS70),2)) -> 0 | S70: =ROUND((ROUND((AF70*AV70*I70),2)*BA70),2) -> 0 | T70: =ROUND(CU70*I70,2) -> 0 | U70: =CV70*I70 -> 0 | V70: =CW70*I70 -> 0 | W70: =ROUND(CX70*I70,2) -> 0 | X70: =(ROUND((((S70+ROUND((ROUND(((EU70)*AV70*I70),2)*BS70),2))*AT70)/100),2)+ROUND(((ROUND((ROUND(((AE70-(EU70))*AV70*I70),2)*BS70),2)*AT70)/100),2)) -> 0 | Y70: =(ROUND((((S70+ROUND((ROUND(((EU70)*AV70*I70),2)*BS70),2))*AU70)/100),2)+ROUND(((ROUND((ROUND(((AE70-(EU70))*AV70*I70),2)*BS70),2)*AU70)/100),2)) -> 0 | AA70: 86551701 | AB70: =ROUND((AC70+AD70+AF70),6) -> 601.47 | AC70: =ROUND((ES70),6) -> 601.47 | AD70: =ROUND((((ET70)-(EU70))+AE70),6) -> 0 | AE70: =ROUND((EU70),6) -> 0 | AF70: =ROUND((EV70),6) -> 0 | AG70: =ROUND((AP70),6) -> 0 | AH70: =(EW70) -> 0 | AI70: =(EX70) -> 0 | AJ70: =(AS70) -> 0 | AK70: 601.47 | AL70: 601.47 | AM70: 0 | AN70: 0 | AO70: 0 | AP70: 0 | AQ70: 0 | AR70: 0 | AS70: 0 | AT70: 109 | AU70: 61 | AV70: 1 | AW70: 1 | AZ70: 1 | BA70: 1 | BB70: 1 | BC70: 1 | BH70: 3 | BI70: 1 | BM70: 23 | BN70: 0 | BP70: 0 | BQ70: 30 | BR70: 0 | BS70: 1 | BT70: 1 | BU70: 1 | BV70: 1 | BW70: 1 | BX70: 1 | BZ70: 109 | CA70: 61 | CE70: 1566 | CF70: 0 | CG70: 0 | CM70: 0 | CO70: 0 | CP70: =(P70+Q70+S70) -> 15036.75 | CQ70: =ROUND((ROUND((AC70*AW70*1),2)*BC70),2) -> 601.47 | CR70: =(ROUND((ROUND(((ET70)*AV70*1),2)*BB70),2)+ROUND((ROUND(((AE70-(EU70))*AV70*1),2)*BS70),2)) -> 0 | CS70: =(ROUND((ROUND(((EU70)*AV70*1),2)*BS70),2)+ROUND((ROUND(((AE70-(EU70))*AV70*1),2)*BS70),2)) -> 0 | CT70: =ROUND((ROUND((AF70*AV70*1),2)*BA70),2) -> 0 | CU70: =AG70 -> 0 | CV70: =(AH70*AV70) -> 0 | CW70: =AI70 -> 0 | CX70: =AJ70 -> 0 | CY70: =(ROUND((((S70+ROUND((ROUND(((EU70)*AV70*1),2)*BS70),2))*AT70)/100),2)+ROUND(((ROUND((ROUND(((AE70-(EU70))*AV70*1),2)*BS70),2)*AT70)/100),2)) -> 0 | CZ70: =(ROUND((((S70+ROUND((ROUND(((EU70)*AV70*1),2)*BS70),2))*AU70)/100),2)+ROUND(((ROUND((ROUND(((AE70-(EU70))*AV70*1),2)*BS70),2)*AU70)/100),2)) -> 0 | DN70: 0 | DO70: 0 | DP70: 1 | DQ70: 1 | EE70: 85635395 | EF70: 30 | EG70: Строительные работы | EH70: 0 | EJ70: 1 | EK70: 23 | EL70: ТСН-2001.3-18. Отопление - внутренние устройства | EM70: ТСН-2001.3-18-1 | EQ70: 0 | ER70: 0 | ES70: 601.47 | ET70: 0 | EU70: 0 | EV70: 0 | EW70: 0 | EX70: 0 | FQ70: 0 | FR70: 0 | FS70: 0 | FX70: 109 | FY70: 61 | GA70: [7 079 / 1,22 / 9,84] + 2% Заг.скл | GD70: 1 | GF70: 566747535 | GG70: 2 | GH70: 4 | GI70: -2 | GJ70: 0 | GK70: 0 | GL70: =ROUND(IF(AND(BH70=3,BI70=3,FS70<>0),P70,0),2) -> 0 | GM70: =ROUND(O70+X70+Y70,2)+GX70 -> 15036.75 | GN70: =IF(OR(BI70=0,BI70=1),GM70-GX70,0) -> 15036.75 | GO70: =IF(BI70=2,GM70-GX70,0) -> 0 | GP70: =IF(BI70=4,GM70-GX70,0) -> 0 | GR70: 0 | GS70: 2 | GT70: 0 | GV70: =ROUND((GT70),6) -> 0 | GW70: 1 | GX70: =ROUND(HC70*I70,2) -> 0 | HA70: 0 | HB70: 0 | HC70: =GV70*GW70 -> 0 | HE70: 0 | HF70: 2 | HS70: 0 | IK70: 0
A71: 18 | B71: 1 | C71: 104 | E71: 3,4 | F71: КА. п. 5 | G71: Сmальной nанельный paguamop PRADO Classic, mun 20, Bыcoma Н = 500 мм, PRADO Classic-20-500-800 | I71: =I63*J71 -> 25 | J71: 16.447368 | K71: 16.447368 | O71: =ROUND(CP71,2) -> 147961.62 | P71: =ROUND((ROUND((AC71*AW71*I71),2)*BC71),2) -> 147961.62 | Q71: =(ROUND((ROUND(((ET71)*AV71*I71),2)*BB71),2)+ROUND((ROUND(((AE71-(EU71))*AV71*I71),2)*BS71),2)) -> 0 | R71: =(ROUND((ROUND(((EU71)*AV71*I71),2)*BS71),2)+ROUND((ROUND(((AE71-(EU71))*AV71*I71),2)*BS71),2)) -> 0 | S71: =ROUND((ROUND((AF71*AV71*I71),2)*BA71),2) -> 0 | T71: =ROUND(CU71*I71,2) -> 0 | U71: =CV71*I71 -> 0 | V71: =CW71*I71 -> 0 | W71: =ROUND(CX71*I71,2) -> 0 | X71: =(ROUND((((S71+ROUND((ROUND(((EU71)*AV71*I71),2)*BS71),2))*AT71)/100),2)+ROUND(((ROUND((ROUND(((AE71-(EU71))*AV71*I71),2)*BS71),2)*AT71)/100),2)) -> 0 | Y71: =(ROUND((((S71+ROUND((ROUND(((EU71)*AV71*I71),2)*BS71),2))*AU71)/100),2)+ROUND(((ROUND((ROUND(((AE71-(EU71))*AV71*I71),2)*BS71),2)*AU71)/100),2)) -> 0 | AA71: 86551703 | AB71: =ROUND((AC71+AD71+AF71),6) -> 601.47 | AC71: =ROUND((ES71),6) -> 601.47 | AD71: =ROUND((((ET71)-(EU71))+AE71),6) -> 0 | AE71: =ROUND((EU71),6) -> 0 | AF71: =ROUND((EV71),6) -> 0 | AG71: =ROUND((AP71),6) -> 0 | AH71: =(EW71) -> 0 | AI71: =(EX71) -> 0 | AJ71: =(AS71) -> 0 | AK71: 601.47 | AL71: 601.47 | AM71: 0 | AN71: 0 | AO71: 0 | AP71: 0 | AQ71: 0 | AR71: 0 | AS71: 0 | AT71: 109 | AU71: 61 | AV71: 1 | AW71: 1 | AZ71: 1 | BA71: 1 | BB71: 1 | BC71: 9.84 | BH71: 3 | BI71: 1 | BM71: 23 | BN71: 0 | BP71: 0 | BQ71: 30 | BR71: 0 | BS71: 1 | BT71: 1 | BU71: 1 | BV71: 1 | BW71: 1 | BX71: 1 | BZ71: 109 | CA71: 61 | CE71: 1566 | CF71: 0 | CG71: 0 | CM71: 0 | CO71: 0 | CP71: =(P71+Q71+S71) -> 147961.62 | CQ71: =ROUND((ROUND((AC71*AW71*1),2)*BC71),2) -> 5918.46 | CR71: =(ROUND((ROUND(((ET71)*AV71*1),2)*BB71),2)+ROUND((ROUND(((AE71-(EU71))*AV71*1),2)*BS71),2)) -> 0 | CS71: =(ROUND((ROUND(((EU71)*AV71*1),2)*BS71),2)+ROUND((ROUND(((AE71-(EU71))*AV71*1),2)*BS71),2)) -> 0 | CT71: =ROUND((ROUND((AF71*AV71*1),2)*BA71),2) -> 0 | CU71: =AG71 -> 0 | CV71: =(AH71*AV71) -> 0 | CW71: =AI71 -> 0 | CX71: =AJ71 -> 0 | CY71: =(ROUND((((S71+ROUND((ROUND(((EU71)*AV71*1),2)*BS71),2))*AT71)/100),2)+ROUND(((ROUND((ROUND(((AE71-(EU71))*AV71*1),2)*BS71),2)*AT71)/100),2)) -> 0 | CZ71: =(ROUND((((S71+ROUND((ROUND(((EU71)*AV71*1),2)*BS71),2))*AU71)/100),2)+ROUND(((ROUND((ROUND(((AE71-(EU71))*AV71*1),2)*BS71),2)*AU71)/100),2)) -> 0 | DN71: 0 | DO71: 0 | DP71: 1 | DQ71: 1 | EE71: 85635395 | EF71: 30 | EG71: Строительные работы | EH71: 0 | EJ71: 1 | EK71: 23 | EL71: ТСН-2001.3-18. Отопление - внутренние устройства | EM71: ТСН-2001.3-18-1 | EQ71: 0 | ER71: 601.47 | ES71: 601.47 | ET71: 0 | EU71: 0 | EV71: 0 | EW71: 0 | EX71: 0 | EZ71: 5 | FC71: 1 | FD71: 18 | FF71: 7079 | FQ71: 0 | FR71: 0 | FS71: 0 | FX71: 109 | FY71: 61 | GA71: [7 079 / 1,22 / 9,84] + 2% Заг.скл | GD71: 1 | GF71: 566747535 | GG71: 2 | GH71: 3 | GI71: 5 | GJ71: 0 | GK71: 0 | GL71: =ROUND(IF(AND(BH71=3,BI71=3,FS71<>0),P71,0),2) -> 0 | GM71: =ROUND(O71+X71+Y71,2)+GX71 -> 147961.62 | GN71: =IF(OR(BI71=0,BI71=1),GM71-GX71,0) -> 147961.62 | GO71: =IF(BI71=2,GM71-GX71,0) -> 0 | GP71: =IF(BI71=4,GM71-GX71,0) -> 0 | GR71: 1 | GS71: 1 | GT71: 0 | GV71: =ROUND((GT71),6) -> 0 | GW71: 1 | GX71: =ROUND(HC71*I71,2) -> 0 | HA71: 0 | HB71: 0 | HC71: =GV71*GW71 -> 0 | HE71: 0 | HF71: 2 | HS71: 0 | IK71: 0
A72: 18 | B72: 1 | C72: 84 | E72: 3,5 | F72: КА. п. 6 | G72: Сmальной nанельный paguamop PRADO Classic, mun 20, Bыcoma Н = 500 мм, PRADO Classic-20-500-900 | I72: =I62*J72 -> 3 | J72: 1.9736842 | K72: 1.973684 | O72: =ROUND(CP72,2) -> 1980.3 | P72: =ROUND((ROUND((AC72*AW72*I72),2)*BC72),2) -> 1980.3 | Q72: =(ROUND((ROUND(((ET72)*AV72*I72),2)*BB72),2)+ROUND((ROUND(((AE72-(EU72))*AV72*I72),2)*BS72),2)) -> 0 | R72: =(ROUND((ROUND(((EU72)*AV72*I72),2)*BS72),2)+ROUND((ROUND(((AE72-(EU72))*AV72*I72),2)*BS72),2)) -> 0 | S72: =ROUND((ROUND((AF72*AV72*I72),2)*BA72),2) -> 0 | T72: =ROUND(CU72*I72,2) -> 0 | U72: =CV72*I72 -> 0 | V72: =CW72*I72 -> 0 | W72: =ROUND(CX72*I72,2) -> 0 | X72: =(ROUND((((S72+ROUND((ROUND(((EU72)*AV72*I72),2)*BS72),2))*AT72)/100),2)+ROUND(((ROUND((ROUND(((AE72-(EU72))*AV72*I72),2)*BS72),2)*AT72)/100),2)) -> 0 | Y72: =(ROUND((((S72+ROUND((ROUND(((EU72)*AV72*I72),2)*BS72),2))*AU72)/100),2)+ROUND(((ROUND((ROUND(((AE72-(EU72))*AV72*I72),2)*BS72),2)*AU72)/100),2)) -> 0 | AA72: 86551701 | AB72: =ROUND((AC72+AD72+AF72),6) -> 660.1 | AC72: =ROUND((ES72),6) -> 660.1 | AD72: =ROUND((((ET72)-(EU72))+AE72),6) -> 0 | AE72: =ROUND((EU72),6) -> 0 | AF72: =ROUND((EV72),6) -> 0 | AG72: =ROUND((AP72),6) -> 0 | AH72: =(EW72) -> 0 | AI72: =(EX72) -> 0 | AJ72: =(AS72) -> 0 | AK72: 660.1 | AL72: 660.1 | AM72: 0 | AN72: 0 | AO72: 0 | AP72: 0 | AQ72: 0 | AR72: 0 | AS72: 0 | AT72: 109 | AU72: 61 | AV72: 1 | AW72: 1 | AZ72: 1 | BA72: 1 | BB72: 1 | BC72: 1 | BH72: 3 | BI72: 1 | BM72: 23 | BN72: 0 | BP72: 0 | BQ72: 30 | BR72: 0 | BS72: 1 | BT72: 1 | BU72: 1 | BV72: 1 | BW72: 1 | BX72: 1 | BZ72: 109 | CA72: 61 | CE72: 1566 | CF72: 0 | CG72: 0 | CM72: 0 | CO72: 0 | CP72: =(P72+Q72+S72) -> 1980.3 | CQ72: =ROUND((ROUND((AC72*AW72*1),2)*BC72),2) -> 660.1 | CR72: =(ROUND((ROUND(((ET72)*AV72*1),2)*BB72),2)+ROUND((ROUND(((AE72-(EU72))*AV72*1),2)*BS72),2)) -> 0 | CS72: =(ROUND((ROUND(((EU72)*AV72*1),2)*BS72),2)+ROUND((ROUND(((AE72-(EU72))*AV72*1),2)*BS72),2)) -> 0 | CT72: =ROUND((ROUND((AF72*AV72*1),2)*BA72),2) -> 0 | CU72: =AG72 -> 0 | CV72: =(AH72*AV72) -> 0 | CW72: =AI72 -> 0 | CX72: =AJ72 -> 0 | CY72: =(ROUND((((S72+ROUND((ROUND(((EU72)*AV72*1),2)*BS72),2))*AT72)/100),2)+ROUND(((ROUND((ROUND(((AE72-(EU72))*AV72*1),2)*BS72),2)*AT72)/100),2)) -> 0 | CZ72: =(ROUND((((S72+ROUND((ROUND(((EU72)*AV72*1),2)*BS72),2))*AU72)/100),2)+ROUND(((ROUND((ROUND(((AE72-(EU72))*AV72*1),2)*BS72),2)*AU72)/100),2)) -> 0 | DN72: 0 | DO72: 0 | DP72: 1 | DQ72: 1 | EE72: 85635395 | EF72: 30 | EG72: Строительные работы | EH72: 0 | EJ72: 1 | EK72: 23 | EL72: ТСН-2001.3-18. Отопление - внутренние устройства | EM72: ТСН-2001.3-18-1 | EQ72: 0 | ER72: 0 | ES72: 660.1 | ET72: 0 | EU72: 0 | EV72: 0 | EW72: 0 | EX72: 0 | FQ72: 0 | FR72: 0 | FS72: 0 | FX72: 109 | FY72: 61 | GA72: [7 769 / 1,22 / 9,84] + 2% Заг.скл | GD72: 1 | GF72: 1036536234 | GG72: 2 | GH72: 4 | GI72: -2 | GJ72: 0 | GK72: 0 | GL72: =ROUND(IF(AND(BH72=3,BI72=3,FS72<>0),P72,0),2) -> 0 | GM72: =ROUND(O72+X72+Y72,2)+GX72 -> 1980.3 | GN72: =IF(OR(BI72=0,BI72=1),GM72-GX72,0) -> 1980.3 | GO72: =IF(BI72=2,GM72-GX72,0) -> 0 | GP72: =IF(BI72=4,GM72-GX72,0) -> 0 | GR72: 0 | GS72: 2 | GT72: 0 | GV72: =ROUND((GT72),6) -> 0 | GW72: 1 | GX72: =ROUND(HC72*I72,2) -> 0 | HA72: 0 | HB72: 0 | HC72: =GV72*GW72 -> 0 | HE72: 0 | HF72: 2 | HS72: 0 | IK72: 0
A73: 18 | B73: 1 | C73: 105 | E73: 3,5 | F73: КА. п. 6 | G73: Сmальной nанельный paguamop PRADO Classic, mun 20, Bыcoma Н = 500 мм, PRADO Classic-20-500-900 | I73: =I63*J73 -> 3 | J73: 1.9736842 | K73: 1.973684 | O73: =ROUND(CP73,2) -> 19486.15 | P73: =ROUND((ROUND((AC73*AW73*I73),2)*BC73),2) -> 19486.15 | Q73: =(ROUND((ROUND(((ET73)*AV73*I73),2)*BB73),2)+ROUND((ROUND(((AE73-(EU73))*AV73*I73),2)*BS73),2)) -> 0 | R73: =(ROUND((ROUND(((EU73)*AV73*I73),2)*BS73),2)+ROUND((ROUND(((AE73-(EU73))*AV73*I73),2)*BS73),2)) -> 0 | S73: =ROUND((ROUND((AF73*AV73*I73),2)*BA73),2) -> 0 | T73: =ROUND(CU73*I73,2) -> 0 | U73: =CV73*I73 -> 0 | V73: =CW73*I73 -> 0 | W73: =ROUND(CX73*I73,2) -> 0 | X73: =(ROUND((((S73+ROUND((ROUND(((EU73)*AV73*I73),2)*BS73),2))*AT73)/100),2)+ROUND(((ROUND((ROUND(((AE73-(EU73))*AV73*I73),2)*BS73),2)*AT73)/100),2)) -> 0 | Y73: =(ROUND((((S73+ROUND((ROUND(((EU73)*AV73*I73),2)*BS73),2))*AU73)/100),2)+ROUND(((ROUND((ROUND(((AE73-(EU73))*AV73*I73),2)*BS73),2)*AU73)/100),2)) -> 0 | AA73: 86551703 | AB73: =ROUND((AC73+AD73+AF73),6) -> 660.1 | AC73: =ROUND((ES73),6) -> 660.1 | AD73: =ROUND((((ET73)-(EU73))+AE73),6) -> 0 | AE73: =ROUND((EU73),6) -> 0 | AF73: =ROUND((EV73),6) -> 0 | AG73: =ROUND((AP73),6) -> 0 | AH73: =(EW73) -> 0 | AI73: =(EX73) -> 0 | AJ73: =(AS73) -> 0 | AK73: 660.1 | AL73: 660.1 | AM73: 0 | AN73: 0 | AO73: 0 | AP73: 0 | AQ73: 0 | AR73: 0 | AS73: 0 | AT73: 109 | AU73: 61 | AV73: 1 | AW73: 1 | AZ73: 1 | BA73: 1 | BB73: 1 | BC73: 9.84 | BH73: 3 | BI73: 1 | BM73: 23 | BN73: 0 | BP73: 0 | BQ73: 30 | BR73: 0 | BS73: 1 | BT73: 1 | BU73: 1 | BV73: 1 | BW73: 1 | BX73: 1 | BZ73: 109 | CA73: 61 | CE73: 1566 | CF73: 0 | CG73: 0 | CM73: 0 | CO73: 0 | CP73: =(P73+Q73+S73) -> 19486.15 | CQ73: =ROUND((ROUND((AC73*AW73*1),2)*BC73),2) -> 6495.38 | CR73: =(ROUND((ROUND(((ET73)*AV73*1),2)*BB73),2)+ROUND((ROUND(((AE73-(EU73))*AV73*1),2)*BS73),2)) -> 0 | CS73: =(ROUND((ROUND(((EU73)*AV73*1),2)*BS73),2)+ROUND((ROUND(((AE73-(EU73))*AV73*1),2)*BS73),2)) -> 0 | CT73: =ROUND((ROUND((AF73*AV73*1),2)*BA73),2) -> 0 | CU73: =AG73 -> 0 | CV73: =(AH73*AV73) -> 0 | CW73: =AI73 -> 0 | CX73: =AJ73 -> 0 | CY73: =(ROUND((((S73+ROUND((ROUND(((EU73)*AV73*1),2)*BS73),2))*AT73)/100),2)+ROUND(((ROUND((ROUND(((AE73-(EU73))*AV73*1),2)*BS73),2)*AT73)/100),2)) -> 0 | CZ73: =(ROUND((((S73+ROUND((ROUND(((EU73)*AV73*1),2)*BS73),2))*AU73)/100),2)+ROUND(((ROUND((ROUND(((AE73-(EU73))*AV73*1),2)*BS73),2)*AU73)/100),2)) -> 0 | DN73: 0 | DO73: 0 | DP73: 1 | DQ73: 1 | EE73: 85635395 | EF73: 30 | EG73: Строительные работы | EH73: 0 | EJ73: 1 | EK73: 23 | EL73: ТСН-2001.3-18. Отопление - внутренние устройства | EM73: ТСН-2001.3-18-1 | EQ73: 0 | ER73: 660.1 | ES73: 660.1 | ET73: 0 | EU73: 0 | EV73: 0 | EW73: 0 | EX73: 0 | EZ73: 5 | FC73: 1 | FD73: 18 | FF73: 7769 | FQ73: 0 | FR73: 0 | FS73: 0 | FX73: 109 | FY73: 61 | GA73: [7 769 / 1,22 / 9,84] + 2% Заг.скл | GD73: 1 | GF73: 1036536234 | GG73: 2 | GH73: 3 | GI73: 5 | GJ73: 0 | GK73: 0 | GL73: =ROUND(IF(AND(BH73=3,BI73=3,FS73<>0),P73,0),2) -> 0 | GM73: =ROUND(O73+X73+Y73,2)+GX73 -> 19486.15 | GN73: =IF(OR(BI73=0,BI73=1),GM73-GX73,0) -> 19486.15 | GO73: =IF(BI73=2,GM73-GX73,0) -> 0 | GP73: =IF(BI73=4,GM73-GX73,0) -> 0 | GR73: 1 | GS73: 1 | GT73: 0 | GV73: =ROUND((GT73),6) -> 0 | GW73: 1 | GX73: =ROUND(HC73*I73,2) -> 0 | HA73: 0 | HB73: 0 | HC73: =GV73*GW73 -> 0 | HE73: 0 | HF73: 2 | HS73: 0 | IK73: 0
