Workbook

Sheet 09-01-02
A1: =Source!B1 -> Smeta.RU (495) 974-1589
J2: Форма № 4б
B3: "СОГЛАСОВАНО" | G3: "УТВЕРЖДАЮ"
B6: =CONCATENATE("______________________ ", IF(Source!AL12<>"", Source!AL12, "")) -> ______________________ | G6: =CONCATENATE("______________________ ", IF(Source!AH12<>"", Source!AH12, "")) -> ______________________
B7: "_____"________________ 2025 г. | G7: "_____"________________ 2025 г.
A10: Капитальный ремонт здания Государственного бюджетного общеобразовательного учреждения города Москвы «Школа № 236» по адресу: г. Москва, ул. Клязьминская, д. 7, к. 4. I этап | AP10: Капитальный ремонт здания Государственного бюджетного общеобразовательного учреждения города Москвы «Школа № 236» по адресу: г. Москва, ул. Клязьминская, д. 7, к. 4. I этап. 09-01-02 Перевозка мусора
A11: (наименование стройки и/или объекта)
A13: =CONCATENATE( "ЛОКАЛЬНАЯ СМЕТА № ",IF(Source!F20<>"Новая локальная смета", Source!F20, "")) -> ЛОКАЛЬНАЯ СМЕТА № 09-01-02
A15: =IF(Source!G20<>"Новая локальная смета", Source!G20, "") -> Перевозка мусора
A16: (наименование работ и затрат)
A18: =CONCATENATE( "Основание: чертежи № ", Source!J20) -> Основание: чертежи № 0224-00272-01-0-ООС2
I20: В базисном уровне цен | J20: В текущем уровне цен
E21: Сметная стоимость | I21: =I22+I23+I24+I25 -> 188.2 | J21: =J22+J23+J24+J25 -> 2900.21 | K21: тыс.руб.
E22: Строительные работы | I22: =ROUND((Source!F78)/1000, 2) -> 0 | J22: =ROUND((Source!P78)/1000, 2) -> 0 | K22: тыс.руб.
E23: Работы по монтажу оборудования | I23: =ROUND((Source!F79)/1000, 2) -> 0 | J23: =ROUND((Source!P79)/1000, 2) -> 0 | K23: тыс.руб.
E24: Оборудование | I24: =ROUND((Source!F70)/1000, 2) -> 0 | J24: =ROUND((Source!P70)/1000, 2) -> 0 | K24: тыс.руб.
E25: Прочие работы и затраты | I25: =ROUND((Source!F80+Source!F81)/1000, 2) -> 188.2 | J25: =ROUND((Source!P80+Source!P81)/1000, 2) -> 2900.21 | K25: тыс.руб.
E26: Средства на оплату труда | I26: =(Source!F76+ Source!F75)/1000 -> 0 | J26: =((Source!P76 + Source!P75)/1000) -> 0 | K26: тыс.руб.
E27: Затраты труда | I27: =Source!F83 -> 0 | K27: чел.-ч.
E28: Кроме того:
E29: Возврат материалов | I29: =SUM(Y35:Y50)/1000 -> 0 | J29: =SUM(Z35:Z50)/1000 -> 0 | K29: тыс.руб.
A31: Составлен(а) по ТСН-2001 с учетом Дополнения №: 79
A32: № и период сборника коэффициентов (индексов) пересчета: Коэффициенты к ТСН-2001 МГЭ Дополнение 79, строительство №216/79 III квартал 2025 года и Коэффициенты к ТСН-2001.13-2 Дополнение 45 №62/45 III квартал 2025 года | M32: 3 кв-л сентябрь | AP32: № и период сборника коэффициентов (индексов) пересчета: Коэффициенты к ТСН-2001 МГЭ Дополнение 79, строительство №216/79 III квартал 2025 года и Коэффициенты к ТСН-2001.13-2 Дополнение 45 №62/45 III квартал 2025 года
A33: № п/п | B33: Шифр расценки и коды ресурсов | C33: Наименование работ и затрат | D33: Ед. изм. | E33: Кол-во единиц | F33: Цена на ед. изм., руб. | G33: Попра- вочные коэффи- циенты | H33: Коэффи- циенты зимних удорожа- ний | I33: Всего в ценах на январь 2000 года, руб. | J33: Коэффи- циенты (индек- сы) пере- счета, нормы НР и СП | K33: ВСЕГО затрат в текущем уровне цен, руб.
A34: 1 | B34: 2 | C34: 3 | D34: 4 | E34: 5 | F34: 6 | G34: 7 | H34: 8 | I34: 9 | J34: 10 | K34: 11
A36: =CONCATENATE("Раздел: ",IF(Source!G24<>"Новый раздел", Source!G24, "")) -> Раздел: Перевозка мусора
A37: 1 | B37: =Source!F28 -> 15.2-45-42 | C37: Перевозка строительного мусора на расстояние до 45 км автосамосвалами грузоподъемностью до 10 т | D37: =Source!H28 -> т | E37: =Source!I28 -> 3219.898 | M37: исключить лом металла, у него свой путь | Q37: =Source!X28 -> 0 | R37: =Source!X29 -> 0 | S37: =Source!Y28 -> 0 | T37: =Source!Y29 -> 0 | U37: =ROUND((175/100)*ROUND(Source!R28, 2), 2) -> 0 | V37: =ROUND((0/100)*ROUND(Source!R29, 2), 2) -> 0 | AC37: 0
C38: ЭМ | F38: =Source!AM28 -> 58.45 | G38: =Source!DE28 | H38: =Source!AV29 -> 1 | I38: =Source!Q28 -> 188203.04 | J38: =IF(Source!BB29<> 0, Source!BB29, 1) -> 15.41 | K38: =Source!Q29 -> 2900208.9
C39: ВСЕГО работ по позиции: | H39: =I38+0-0-0 -> 188203.04 | J39: =K38+0-0-0 -> 2900208.9
C40: ВСЕГО оборудование по позиции: | H40: =0+0 -> 0 | J40: =0+0 -> 0
C41: ВСЕГО по позиции: | H41: =I38+0 -> 188203.04 | J41: =K38+0 -> 2900208.9 | O41: =I38+0 -> 188203.04 | P41: =K38+0 -> 2900208.9
A44: =CONCATENATE("Итого по разделу: ",IF(Source!G31<>"Новый раздел", Source!G31, "")) -> Итого по разделу: Перевозка мусора | H44: =SUM(O36:O43) -> 188203.04 | J44: =SUM(P36:P43) -> 2900208.9
A45: Итого по ТСН-2001.16 | I45: =SUM(W36:W44) -> 0 | J45: =SUM(X36:X44) -> 0
A46: Итого возвратных сумм | I46: =SUM(Y36:Y45) -> 0 | J46: =SUM(Z36:Z45) -> 0
A48: =CONCATENATE("Итого по локальной смете: ",IF(Source!G61<>"Новая локальная смета", Source!G61, "")) -> Итого по локальной смете: Перевозка мусора | H48: =SUM(O35:O47) -> 188203.04 | J48: =SUM(P35:P47) -> 2900208.9
A49: Итого по ТСН-2001.16 | I49: =SUM(W35:W48) -> 0 | J49: =SUM(X35:X48) -> 0
A50: Итого возвратных сумм | I50: =SUM(Y35:Y49) -> 0 | J50: =SUM(Z35:Z49) -> 0
A53: Составил | C53: =IF(Source!AC12<>"", Source!AC12," ") | H53: =IF(Source!AB12<>"", Source!AB12," ") -> Лукьянова А.Л.
C54: (должность, подпись, инициалы, фамилия)
A56: Проверил | C56: =IF(Source!AE12<>"", Source!AE12," ") | H56: =IF(Source!AD12<>"", Source!AD12," ")
C57: (должность, подпись, инициалы, фамилия)

Sheet Ведомость объемов работ
A1: =Source!B1 -> Smeta.RU (495) 974-1589
E3: "УТВЕРЖДАЮ"
D5: ___________________________
D7: ___________________________
D9: " ___ " ___________ 20 ___ г.
B12: =CONCATENATE("Ведомость объемов работ ", IF(Source!AN15<>"", Source!AN15," ")) -> Ведомость объемов работ
B13: =CONCATENATE(Source!F12, " ", Source!G12) -> 09-01-02 09-01-02 Перевозка мусора
A16: № п/п | B16: № в ЛСР | C16: Наименование работ и затрат | D16: Единица измерения | E16: Количество | F16: Ссылка на чертежи, спецификации | G16: Формула расчета, расчет объемов работ и расхода материалов | H16: Примечание
A17: 1 | B17: 2 | C17: 3 | D17: 4 | E17: 5 | F17: 6 | G17: 7 | H17: 8
A18: =CONCATENATE("Локальная смета: ", Source!G20) -> Локальная смета: Перевозка мусора
A19: =CONCATENATE("Раздел: ", Source!G24) -> Раздел: Перевозка мусора
A20: 1 | B20: =Source!E28 -> 1 | C20: =Source!G28 -> Перевозка строительного мусора на расстояние до 45 км автосамосвалами грузоподъемностью до 10 т | D20: т | E20: =Source!I28 -> 3219.898 | F20: =Source!U24 | G20: =Source!I28 -> 3219.898
C23: Главный инженер проекта _________________ | D23: =IF(Source!X12<>"", Source!X12," ")
C25: Составил _________________ | D25: =IF(Source!AB12<>"", Source!AB12," ") -> Лукьянова А.Л.

Sheet Source
A1: 0 | B1: Smeta.RU (495) 974-1589 | D1: _PS_ | F1: 0 | G1: 0 | H1: 0 | I1: Smeta.RU | K1: 1 | L1: 74562 | M1: 10 | N1: 11 | O1: 14 | P1: 0 | Q1: 0
A4: 1 | B4: 1 | C4: -1 | G4: Капитальный ремонт здания Государственного бюджетного общеобразовательного учреждения города Москвы «Школа № 236» по адресу: г. Москва, ул. Клязьминская, д. 7, к. 4. I этап | EC4: 0
A12: 1 | B12: 131 | C12: 0 | D12: =ROW(A91) -> 91 | E12: 0 | F12: 09-01-02 | G12: 09-01-02 Перевозка мусора | I12: 0 | J12: 0224-00272-01-0-ООС2 | K12: 0 | L12: 0 | M12: 4098 | O12: 0 | P12: 0 | Q12: 0 | R12: 0 | S12: 0 | T12: 1 | V12: 0 | AB12: Лукьянова А.Л. | BB12: 0 | BH12: Сметные нормы списания | BI12: Коды ОКП для ТСН-2001 МГЭ Дополнение 79 | BJ12: 1 | BK12: 1 | BL12: 0 | BM12: 0 | BN12: 1 | BO12: 0 | BP12: 6 | BQ12: 2 | BR12: 1 | BS12: 1 | BT12: 0 | BU12: 0 | BV12: 0 | BW12: 0 | BX12: 0 | BY12: ТСН-2001 (МГЭ) Доп 79 - Новое строительство | BZ12: Типовой расчет для ТСН-2001 МГЭ, Дополнение 79, строительство | CA12: Территориальные сметные нормативы для Москвы ТСН-2001 (МГЭ), дополнение 79 | CB12: Территориальные сметные нормативы для Москвы ТСН-2001 (МГЭ), дополнение 79 | CC12: Территориальные сметные нормативы для Москвы ТСН-2001 (МГЭ), дополнение 79 | CD12: Территориальные сметные нормативы для Москвы ТСН-2001 (МГЭ), дополнение 79 | CE12: Поправки для ТСН-2001 от 03.10.2025 г. доп.79 | CF12: 0 | CG12: 0 | CH12: 8200 | CK12: 79 | CQ12: Территориальные сметные нормативы для Москвы (ТСН-2001) | CR12: ТЕР | CS12: 41660 | CT12: 1 | CU12: 79 | CY12: 0 | EC12: 0
A15: 15 | B15: 1
A18: 52 | B18: =B91 -> 131 | C18: =C91 -> 1 | D18: =D91 -> 12 | E18: =E91 -> 0 | F18: =F91 -> 09-01-02 | G18: =G91 -> 09-01-02 Перевозка мусора | O18: =O91 -> 188203.04 | P18: =P91 -> 0 | Q18: =Q91 -> 188203.04 | R18: =R91 -> 0 | S18: =S91 -> 0 | T18: =T91 -> 0 | U18: =U91 -> 0 | V18: =V91 -> 0 | ... GX18: =GX91 -> 0
A20: 3 | B20: 1 | D20: =ROW(A61) -> 61 | F20: 09-01-02 | G20: Перевозка мусора | I20: 0 | J20: 0224-00272-01-0-ООС2 | K20: -1 | L20: 09-01-02 | S20: 0 | T20: 0 | V20: 0 | AB20: Лукьянова А.Л. | BX20: 0 | CF20: 0 | CG20: 0
A22: 52 | B22: =B61 -> 1 | C22: =C61 -> 3 | D22: =D61 -> 20 | E22: =E61 -> 0 | F22: =F61 -> 09-01-02 | G22: =G61 -> Перевозка мусора | O22: =O61 -> 188203.04 | P22: =P61 -> 0 | Q22: =Q61 -> 188203.04 | R22: =R61 -> 0 | S22: =S61 -> 0 | T22: =T61 -> 0 | U22: =U61 -> 0 | V22: =V61 -> 0 | ... GX22: =GX61 -> 0
A24: 4 | B24: 1 | D24: =ROW(A31) -> 31 | F24: Новый раздел | G24: Перевозка мусора | I24: 0 | K24: 0 | S24: 0 | T24: 0 | V24: 0 | BX24: 0 | CJ24: 0
A26: 52 | B26: =B31 -> 1 | C26: =C31 -> 4 | D26: =D31 -> 24 | E26: =E31 -> 0 | F26: =F31 -> Новый раздел | G26: =G31 -> Перевозка мусора | O26: =O31 -> 188203.04 | P26: =P31 -> 0 | Q26: =Q31 -> 188203.04 | R26: =R31 -> 0 | S26: =S31 -> 0 | T26: =T31 -> 0 | U26: =U31 -> 0 | V26: =V31 -> 0 | ... GX26: =GX31 -> 0
A28: 17 | B28: 1 | C28: =ROW(SmtRes!A1) -> 1 | D28: =ROW(EtalonRes!A1) -> 1 | E28: 1 | F28: 15.2-45-42 | G28: Перевозка строительного мусора на расстояние до 45 км автосамосвалами грузоподъемностью до 10 т | H28: т | I28: 3219.898 | J28: 0 | K28: 3219.898 | O28: =ROUND(CP28,2) -> 188203.04 | P28: =ROUND((ROUND((AC28*AW28*I28),2)*BC28),2) -> 0 | Q28: =(ROUND((ROUND(((ET28)*AV28*I28),2)*BB28),2)+ROUND((ROUND(((AE28-(EU28))*AV28*I28),2)*BS28),2)) -> 188203.04 | R28: =ROUND((ROUND((AE28*AV28*I28),2)*BS28),2) -> 0 | S28: =ROUND((ROUND((AF28*AV28*I28),2)*BA28),2) -> 0 | T28: =ROUND(CU28*I28,2) -> 0 | U28: =CV28*I28 -> 0 | V28: =CW28*I28 -> 0 | W28: =ROUND(CX28*I28,2) -> 0 | X28: =ROUND(CY28,2) -> 0 | Y28: =ROUND(CZ28,2) -> 0 | AA28: 56526069 | AB28: =ROUND((AC28+AD28+AF28),6) -> 58.45 | AC28: =ROUND((ES28),6) -> 0 | AD28: =ROUND((((ET28)-(EU28))+AE28),6) -> 58.45 | AE28: =ROUND((EU28),6) -> 0 | AF28: =ROUND((EV28),6) -> 0 | AG28: =ROUND((AP28),6) -> 0 | AH28: =(EW28) -> 0 | AI28: =(EX28) -> 0 | AJ28: =(AS28) -> 0 | AK28: 58.45 | AL28: 0 | AM28: 58.45 | AN28: 0 | AO28: 0 | AP28: 0 | AQ28: 0 | AR28: 0 | AS28: 0 | AT28: 94 | AU28: 61 | AV28: 1 | AW28: 1 | AZ28: 1 | BA28: 1 | BB28: 1 | BC28: 1 | BH28: 0 | BI28: 4 | BJ28: ТСН-2001.15 Доп. 79, Сб. 2, т. 45, поз. 42 | BM28: 188 | BN28: 0 | BO28: 15.2-45-42 | BP28: 1 | BQ28: 150 | BR28: 0 | BS28: 1 | BT28: 1 | BU28: 1 | BV28: 1 | BW28: 1 | BX28: 1 | BZ28: 94 | CA28: 61 | CE28: 30 | CF28: 0 | CG28: 0 | CM28: 0 | CO28: 0 | CP28: =(P28+Q28+S28) -> 188203.04 | CQ28: =ROUND((ROUND((AC28*AW28*1),2)*BC28),2) -> 0 | CR28: =(ROUND((ROUND(((ET28)*AV28*1),2)*BB28),2)+ROUND((ROUND(((AE28-(EU28))*AV28*1),2)*BS28),2)) -> 58.45 | CS28: =ROUND((ROUND((AE28*AV28*1),2)*BS28),2) -> 0 | CT28: =ROUND((ROUND((AF28*AV28*1),2)*BA28),2) -> 0 | CU28: =AG28 -> 0 | CV28: =(AH28*AV28) -> 0 | CW28: =AI28 -> 0 | CX28: =AJ28 -> 0 | CY28: =(((S28+R28)*AT28)/100) -> 0 | CZ28: =(((S28+R28)*AU28)/100) -> 0 | DN28: 0 | DO28: 0 | DP28: 1 | DQ28: 1 | DU28: 1009 | DV28: т | DW28: т | DX28: 1000 | EE28: 55586142 | EF28: 150 | EG28: Транспортные затраты | EH28: 0 | EJ28: 4 | EK28: 188 | EL28: ТСН-2001.15. Перевозка строительных грузов автомобильным транспортом | EM28: ТСН-2001.15. | EQ28: 0 | ER28: 58.45 | ES28: 0 | ET28: 58.45 | EU28: 0 | EV28: 0 | EW28: 0 | EX28: 0 | EY28: 0 | FQ28: 0 | FR28: 0 | FS28: 0 | FX28: 94 | FY28: 61 | GD28: 1 | GF28: 767338782 | GG28: 2 | GH28: 1 | GI28: 2 | GJ28: 0 | GK28: 0 | GL28: =ROUND(IF(AND(BH28=3,BI28=3,FS28<>0),P28,0),2) -> 0 | GM28: =ROUND(O28+X28+Y28,2)+GX28 -> 188203.04 | GN28: =IF(OR(BI28=0,BI28=1),GM28-GX28,0) -> 0 | GO28: =IF(BI28=2,GM28-GX28,0) -> 0 | GP28: =IF(BI28=4,GM28-GX28,0) -> 188203.04 | GR28: 0 | GS28: 3 | GT28: 0 | GV28: =ROUND((GT28),6) -> 0 | GW28: 1 | GX28: =ROUND(HC28*I28,2) -> 0 | HA28: 0 | HB28: 0 | HC28: =GV28*GW28 -> 0 | HS28: 0 | IK28: 0
A29: 17 | B29: 1 | C29: =ROW(SmtRes!A2) -> 2 | D29: =ROW(EtalonRes!A2) -> 2 | E29: 1 | F29: 15.2-45-42 | G29: Перевозка строительного мусора на расстояние до 45 км автосамосвалами грузоподъемностью до 10 т | H29: т | I29: 3219.898 | J29: 0 | K29: 3219.898 | O29: =ROUND(CP29,2) -> 2900208.9 | P29: =ROUND((ROUND((AC29*AW29*I29),2)*BC29),2) -> 0 | Q29: =(ROUND((ROUND(((ET29)*AV29*I29),2)*BB29),2)+ROUND((ROUND(((AE29-(EU29))*AV29*I29),2)*BS29),2)) -> 2900208.9 | R29: =ROUND((ROUND((AE29*AV29*I29),2)*BS29),2) -> 0 | S29: =ROUND((ROUND((AF29*AV29*I29),2)*BA29),2) -> 0 | T29: =ROUND(CU29*I29,2) -> 0 | U29: =CV29*I29 -> 0 | V29: =CW29*I29 -> 0 | W29: =ROUND(CX29*I29,2) -> 0 | X29: =ROUND(CY29,2) -> 0 | Y29: =ROUND(CZ29,2) -> 0 | AA29: 56526071 | AB29: =ROUND((AC29+AD29+AF29),6) -> 58.45 | AC29: =ROUND((ES29),6) -> 0 | AD29: =ROUND((((ET29)-(EU29))+AE29),6) -> 58.45 | AE29: =ROUND((EU29),6) -> 0 | AF29: =ROUND((EV29),6) -> 0 | AG29: =ROUND((AP29),6) -> 0 | AH29: =(EW29) -> 0 | AI29: =(EX29) -> 0 | AJ29: =(AS29) -> 0 | AK29: 58.45 | AL29: 0 | AM29: 58.45 | AN29: 0 | AO29: 0 | AP29: 0 | AQ29: 0 | AR29: 0 | AS29: 0 | AT29: 94 | AU29: 61 | AV29: 1 | AW29: 1 | AZ29: 1 | BA29: 1 | BB29: 15.41 | BC29: 1 | BH29: 0 | BI29: 4 | BJ29: ТСН-2001.15 Доп. 79, Сб. 2, т. 45, поз. 42 | BM29: 188 | BN29: 0 | BO29: 15.2-45-42 | BP29: 1 | BQ29: 150 | BR29: 0 | BS29: 1 | BT29: 1 | BU29: 1 | BV29: 1 | BW29: 1 | BX29: 1 | BZ29: 94 | CA29: 61 | CE29: 30 | CF29: 0 | CG29: 0 | CM29: 0 | CO29: 0 | CP29: =(P29+Q29+S29) -> 2900208.9 | CQ29: =ROUND((ROUND((AC29*AW29*1),2)*BC29),2) -> 0 | CR29: =(ROUND((ROUND(((ET29)*AV29*1),2)*BB29),2)+ROUND((ROUND(((AE29-(EU29))*AV29*1),2)*BS29),2)) -> 900.71 | CS29: =ROUND((ROUND((AE29*AV29*1),2)*BS29),2) -> 0 | CT29: =ROUND((ROUND((AF29*AV29*1),2)*BA29),2) -> 0 | CU29: =AG29 -> 0 | CV29: =(AH29*AV29) -> 0 | CW29: =AI29 -> 0 | CX29: =AJ29 -> 0 | CY29: =(((S29+R29)*AT29)/100) -> 0 | CZ29: =(((S29+R29)*AU29)/100) -> 0 | DN29: 0 | DO29: 0 | DP29: 1 | DQ29: 1 | DU29: 1009 | DV29: т | DW29: т | DX29: 1000 | EE29: 55586142 | EF29: 150 | EG29: Транспортные затраты | EH29: 0 | EJ29: 4 | EK29: 188 | EL29: ТСН-2001.15. Перевозка строительных грузов автомобильным транспортом | EM29: ТСН-2001.15. | EQ29: 0 | ER29: 58.45 | ES29: 0 | ET29: 58.45 | EU29: 0 | EV29: 0 | EW29: 0 | EX29: 0 | EY29: 0 | FQ29: 0 | FR29: 0 | FS29: 0 | FX29: 94 | FY29: 61 | GD29: 1 | GF29: 767338782 | GG29: 2 | GH29: 1 | GI29: 2 | GJ29: 0 | GK29: 0 | GL29: =ROUND(IF(AND(BH29=3,BI29=3,FS29<>0),P29,0),2) -> 0 | GM29: =ROUND(O29+X29+Y29,2)+GX29 -> 2900208.9 | GN29: =IF(OR(BI29=0,BI29=1),GM29-GX29,0) -> 0 | GO29: =IF(BI29=2,GM29-GX29,0) -> 0 | GP29: =IF(BI29=4,GM29-GX29,0) -> 2900208.9 | GR29: 0 | GS29: 3 | GT29: 0 | GV29: =ROUND((GT29),6) -> 0 | GW29: 1 | GX29: =ROUND(HC29*I29,2) -> 0 | HA29: 0 | HB29: 0 | HC29: =GV29*GW29 -> 0 | HS29: 0 | IK29: 0
A31: 51 | B31: =B24 -> 1 | C31: =A24 -> 4 | D31: =ROW(A24) -> 24 | F31: =IF(F24<>"",F24,"") -> Новый раздел | G31: =IF(G24<>"",G24,"") -> Перевозка мусора | H31: 0 | O31: =ROUND(AB31,2) -> 188203.04 | P31: =ROUND(AC31,2) -> 0 | Q31: =ROUND(AD31,2) -> 188203.04 | R31: =ROUND(AE31,2) -> 0 | S31: =ROUND(AF31,2) -> 0 | T31: =ROUND(AG31,2) -> 0 | U31: =AH31 -> 0 | V31: =AI31 -> 0 | W31: =ROUND(AJ31,2) -> 0 | X31: =ROUND(AK31,2) -> 0 | Y31: =ROUND(AL31,2) -> 0 | AB31: =ROUND(SUMIF(AA28:AA29,"=56526069",O28:O29),2) -> 188203.04 | AC31: =ROUND(SUMIF(AA28:AA29,"=56526069",P28:P29),2) -> 0 | AD31: =ROUND(SUMIF(AA28:AA29,"=56526069",Q28:Q29),2) -> 188203.04 | AE31: =ROUND(SUMIF(AA28:AA29,"=56526069",R28:R29),2) -> 0 | AF31: =ROUND(SUMIF(AA28:AA29,"=56526069",S28:S29),2) -> 0 | AG31: =ROUND(SUMIF(AA28:AA29,"=56526069",T28:T29),2) -> 0 | AH31: =SUMIF(AA28:AA29,"=56526069",U28:U29) -> 0 | AI31: =SUMIF(AA28:AA29,"=56526069",V28:V29) -> 0 | AJ31: =ROUND(SUMIF(AA28:AA29,"=56526069",W28:W29),2) -> 0 | AK31: =ROUND(SUMIF(AA28:AA29,"=56526069",X28:X29),2) -> 0 | AL31: =ROUND(SUMIF(AA28:AA29,"=56526069",Y28:Y29),2) -> 0 | AO31: =ROUND(BX31,2) -> 0 | AP31: =ROUND(BY31,2) -> 0 | AQ31: =ROUND(BZ31,2) -> 0 | AR31: =ROUND(CA31,2) -> 188203.04 | AS31: =ROUND(CB31,2) -> 0 | AT31: =ROUND(CC31,2) -> 0 | AU31: =ROUND(CD31,2) -> 188203.04 | AV31: =ROUND(CE31,2) -> 0 | ... BD31: =ROUND(CM31,2) -> 0 | BX31: =ROUND(SUMIF(AA28:AA29,"=56526069",FQ28:FQ29),2) -> 0 | BY31: =ROUND(SUMIF(AA28:AA29,"=56526069",FR28:FR29),2) -> 0 | BZ31: =ROUND(SUMIF(AA28:AA29,"=56526069",GL28:GL29),2) -> 0 | CA31: =ROUND(SUMIF(AA28:AA29,"=56526069",GM28:GM29),2) -> 188203.04 | CB31: =ROUND(SUMIF(AA28:AA29,"=56526069",GN28:GN29),2) -> 0 | CC31: =ROUND(SUMIF(AA28:AA29,"=56526069",GO28:GO29),2) -> 0 | CD31: =ROUND(SUMIF(AA28:AA29,"=56526069",GP28:GP29),2) -> 188203.04 | CE31: =AC31-BX31 -> 0 | CF31: =AC31-BY31 -> 0 | CG31: =BX31-BZ31 -> 0 | CH31: =AC31-BX31-BY31+BZ31 -> 0 | CI31: =BY31-BZ31 -> 0 | CJ31: =ROUND(SUMIF(AA28:AA29,"=56526069",GX28:GX29),2) -> 0 | CK31: =ROUND(SUMIF(AA28:AA29,"=56526069",GY28:GY29),2) -> 0 | CL31: =ROUND(SUMIF(AA28:AA29,"=56526069",GZ28:GZ29),2) -> 0 | CM31: =ROUND(SUMIF(AA28:AA29,"=56526069",HD28:HD29),2) -> 0 | DG31: =ROUND(DT31,2) -> 2900208.9 | DH31: =ROUND(DU31,2) -> 0 | DI31: =ROUND(DV31,2) -> 2900208.9 | DJ31: =ROUND(DW31,2) -> 0 | DK31: =ROUND(DX31,2) -> 0 | DL31: =ROUND(DY31,2) -> 0 | DM31: =DZ31 -> 0 | DN31: =EA31 -> 0 | DO31: =ROUND(EB31,2) -> 0 | DP31: =ROUND(EC31,2) -> 0 | DQ31: =ROUND(ED31,2) -> 0 | DT31: =ROUND(SUMIF(AA28:AA29,"=56526071",O28:O29),2) -> 2900208.9 | DU31: =ROUND(SUMIF(AA28:AA29,"=56526071",P28:P29),2) -> 0 | DV31: =ROUND(SUMIF(AA28:AA29,"=56526071",Q28:Q29),2) -> 2900208.9 | DW31: =ROUND(SUMIF(AA28:AA29,"=56526071",R28:R29),2) -> 0 | DX31: =ROUND(SUMIF(AA28:AA29,"=56526071",S28:S29),2) -> 0 | DY31: =ROUND(SUMIF(AA28:AA29,"=56526071",T28:T29),2) -> 0 | DZ31: =SUMIF(AA28:AA29,"=56526071",U28:U29) -> 0 | EA31: =SUMIF(AA28:AA29,"=56526071",V28:V29) -> 0 | EB31: =ROUND(SUMIF(AA28:AA29,"=56526071",W28:W29),2) -> 0 | EC31: =ROUND(SUMIF(AA28:AA29,"=56526071",X28:X29),2) -> 0 | ED31: =ROUND(SUMIF(AA28:AA29,"=56526071",Y28:Y29),2) -> 0 | EG31: =ROUND(FP31,2) -> 0 | EH31: =ROUND(FQ31,2) -> 0 | EI31: =ROUND(FR31,2) -> 0 | EJ31: =ROUND(FS31,2) -> 2900208.9 | EK31: =ROUND(FT31,2) -> 0 | EL31: =ROUND(FU31,2) -> 0 | EM31: =ROUND(FV31,2) -> 2900208.9 | EN31: =ROUND(FW31,2) -> 0 | ... EV31: =ROUND(GE31,2) -> 0 | FP31: =ROUND(SUMIF(AA28:AA29,"=56526071",FQ28:FQ29),2) -> 0 | FQ31: =ROUND(SUMIF(AA28:AA29,"=56526071",FR28:FR29),2) -> 0 | FR31: =ROUND(SUMIF(AA28:AA29,"=56526071",GL28:GL29),2) -> 0 | FS31: =ROUND(SUMIF(AA28:AA29,"=56526071",GM28:GM29),2) -> 2900208.9 | FT31: =ROUND(SUMIF(AA28:AA29,"=56526071",GN28:GN29),2) -> 0 | FU31: =ROUND(SUMIF(AA28:AA29,"=56526071",GO28:GO29),2) -> 0 | FV31: =ROUND(SUMIF(AA28:AA29,"=56526071",GP28:GP29),2) -> 2900208.9 | FW31: =DU31-FP31 -> 0 | FX31: =DU31-FQ31 -> 0 | FY31: =FP31-FR31 -> 0 | FZ31: =DU31-FP31-FQ31+FR31 -> 0 | GA31: =FQ31-FR31 -> 0 | GB31: =ROUND(SUMIF(AA28:AA29,"=56526071",GX28:GX29),2) -> 0 | GC31: =ROUND(SUMIF(AA28:AA29,"=56526071",GY28:GY29),2) -> 0 | GD31: =ROUND(SUMIF(AA28:AA29,"=56526071",GZ28:GZ29),2) -> 0 | GE31: =ROUND(SUMIF(AA28:AA29,"=56526071",HD28:HD29),2) -> 0 | GX31: 0
A33: 50 | B33: 0 | C33: 0 | D33: 1 | E33: 201 | F33: =ROUND(Source!O31,O33) -> 188203.04 | G33: ПЗ | H33: Прямые затраты | K33: 201 | L33: 1 | M33: 3 | O33: 2 | P33: =ROUND(Source!DG31,O33) -> 2900208.9 | W33: 188203.04 | X33: 1 | Y33: 188203.04 | Z33: 2900208.9 | AA33: 1 | AB33: 2900208.9
A34: 50 | B34: 0 | C34: 0 | D34: 1 | E34: 202 | F34: =ROUND(Source!P31,O34) -> 0 | G34: СтМатОб | H34: Стоимость материальных ресурсов (всего) | K34: 202 | L34: 2 | M34: 3 | O34: 2 | P34: =ROUND(Source!DH31,O34) -> 0 | W34: 0 | X34: 1 | Y34: 0 | Z34: 0 | AA34: 1 | AB34: 0
A35: 50 | B35: 0 | C35: 0 | D35: 1 | E35: 222 | F35: =ROUND(Source!AO31,O35) -> 0 | G35: СтМатОбЗак | H35: Стоимость материалов и оборудования заказчика | K35: 222 | L35: 3 | M35: 3 | O35: 2 | P35: =ROUND(Source!EG31,O35) -> 0 | W35: 0 | X35: 1 | Y35: 0 | Z35: 0 | AA35: 1 | AB35: 0
A36: 50 | B36: 0 | C36: 0 | D36: 1 | E36: 225 | F36: =ROUND(Source!AV31,O36) -> 0 | G36: СтМатОбПод | H36: Стоимость материалов и оборудования подрядчика | K36: 225 | L36: 4 | M36: 3 | O36: 2 | P36: =ROUND(Source!EN31,O36) -> 0 | W36: 0 | X36: 1 | Y36: 0 | Z36: 0 | AA36: 1 | AB36: 0
A37: 50 | B37: 0 | C37: 0 | D37: 1 | E37: 226 | F37: =ROUND(Source!AW31,O37) -> 0 | G37: СтМат | H37: Стоимость материалов (всего) | K37: 226 | L37: 5 | M37: 3 | O37: 2 | P37: =ROUND(Source!EO31,O37) -> 0 | W37: 0 | X37: 1 | Y37: 0 | Z37: 0 | AA37: 1 | AB37: 0
A38: 50 | B38: 0 | C38: 0 | D38: 1 | E38: 227 | F38: =ROUND(Source!AX31,O38) -> 0 | G38: СтМатЗак | H38: Стоимость материалов заказчика | K38: 227 | L38: 6 | M38: 3 | O38: 2 | P38: =ROUND(Source!EP31,O38) -> 0 | W38: 0 | X38: 1 | Y38: 0 | Z38: 0 | AA38: 1 | AB38: 0
A39: 50 | B39: 0 | C39: 0 | D39: 1 | E39: 228 | F39: =ROUND(Source!AY31,O39) -> 0 | G39: СтМатПод | H39: Стоимость материалов подрядчика | K39: 228 | L39: 7 | M39: 3 | O39: 2 | P39: =ROUND(Source!EQ31,O39) -> 0 | W39: 0 | X39: 1 | Y39: 0 | Z39: 0 | AA39: 1 | AB39: 0
A40: 50 | B40: 0 | C40: 0 | D40: 1 | E40: 216 | F40: =ROUND(Source!AP31,O40) -> 0 | G40: Оборуд | H40: Стоимость оборудования (всего) | K40: 216 | L40: 8 | M40: 3 | O40: 2 | P40: =ROUND(Source!EH31,O40) -> 0 | W40: 0 | X40: 1 | Y40: 0 | Z40: 0 | AA40: 1 | AB40: 0
A41: 50 | B41: 0 | C41: 0 | D41: 1 | E41: 223 | F41: =ROUND(Source!AQ31,O41) -> 0 | G41: ОборудЗак | H41: Стоимость оборудования заказчика | K41: 223 | L41: 9 | M41: 3 | O41: 2 | P41: =ROUND(Source!EI31,O41) -> 0 | W41: 0 | X41: 1 | Y41: 0 | Z41: 0 | AA41: 1 | AB41: 0
A42: 50 | B42: 0 | C42: 0 | D42: 1 | E42: 229 | F42: =ROUND(Source!AZ31,O42) -> 0 | G42: ОборудПод | H42: Стоимость оборудования подрядчика | K42: 229 | L42: 10 | M42: 3 | O42: 2 | P42: =ROUND(Source!ER31,O42) -> 0 | W42: 0 | X42: 1 | Y42: 0 | Z42: 0 | AA42: 1 | AB42: 0
A43: 50 | B43: 0 | C43: 0 | D43: 1 | E43: 203 | F43: =ROUND(Source!Q31,O43) -> 188203.04 | G43: ЭММ | H43: Эксплуатация машин | K43: 203 | L43: 11 | M43: 3 | O43: 2 | P43: =ROUND(Source!DI31,O43) -> 2900208.9 | W43: 188203.04 | X43: 1 | Y43: 188203.04 | Z43: 2900208.9 | AA43: 1 | AB43: 2900208.9
A44: 50 | B44: 0 | C44: 0 | D44: 1 | E44: 231 | F44: =ROUND(Source!BB31,O44) -> 0 | G44: ЭММсНРиСП | H44: Эксплуатация машин по ТСН-2001.16 | K44: 231 | L44: 12 | M44: 3 | O44: 2 | P44: =ROUND(Source!ET31,O44) -> 0 | W44: 0 | X44: 1 | Y44: 0 | Z44: 0 | AA44: 1 | AB44: 0
A45: 50 | B45: 0 | C45: 0 | D45: 1 | E45: 204 | F45: =ROUND(Source!R31,O45) -> 0 | G45: ЗПМ | H45: ЗП машинистов | K45: 204 | L45: 13 | M45: 3 | O45: 2 | P45: =ROUND(Source!DJ31,O45) -> 0 | W45: 0 | X45: 1 | Y45: 0 | Z45: 0 | AA45: 1 | AB45: 0
A46: 50 | B46: 0 | C46: 0 | D46: 1 | E46: 205 | F46: =ROUND(Source!S31,O46) -> 0 | G46: ОЗП | H46: Основная ЗП рабочих | K46: 205 | L46: 14 | M46: 3 | O46: 2 | P46: =ROUND(Source!DK31,O46) -> 0 | W46: 0 | X46: 1 | Y46: 0 | Z46: 0 | AA46: 1 | AB46: 0
A47: 50 | B47: 0 | C47: 0 | D47: 1 | E47: 232 | F47: =ROUND(Source!BC31,O47) -> 0 | G47: ОЗПсНРиСП | H47: Основная ЗП рабочих по ТСН-2001.16 | K47: 232 | L47: 15 | M47: 3 | O47: 2 | P47: =ROUND(Source!EU31,O47) -> 0 | W47: 0 | X47: 1 | Y47: 0 | Z47: 0 | AA47: 1 | AB47: 0
A48: 50 | B48: 0 | C48: 0 | D48: 1 | E48: 214 | F48: =ROUND(Source!AS31,O48) -> 0 | G48: Строит | H48: Строительные работы с НР и СП | K48: 214 | L48: 16 | M48: 3 | O48: 2 | P48: =ROUND(Source!EK31,O48) -> 0 | W48: 0 | X48: 1 | Y48: 0 | Z48: 0 | AA48: 1 | AB48: 0
A49: 50 | B49: 0 | C49: 0 | D49: 1 | E49: 215 | F49: =ROUND(Source!AT31,O49) -> 0 | G49: Монтаж | H49: Монтажные работы с НР и СП | K49: 215 | L49: 17 | M49: 3 | O49: 2 | P49: =ROUND(Source!EL31,O49) -> 0 | W49: 0 | X49: 1 | Y49: 0 | Z49: 0 | AA49: 1 | AB49: 0
A50: 50 | B50: 0 | C50: 0 | D50: 1 | E50: 217 | F50: =ROUND(Source!AU31,O50) -> 188203.04 | G50: Прочие | H50: Прочие работы с НР и СП | K50: 217 | L50: 18 | M50: 3 | O50: 2 | P50: =ROUND(Source!EM31,O50) -> 2900208.9 | W50: 188203.04 | X50: 1 | Y50: 188203.04 | Z50: 2900208.9 | AA50: 1 | AB50: 2900208.9
A51: 50 | B51: 0 | C51: 0 | D51: 1 | E51: 230 | F51: =ROUND(Source!BA31,O51) -> 0 | G51: ПрочиеЗатр | H51: Прочие затраты по ТСН-2001.16 | K51: 230 | L51: 19 | M51: 3 | O51: 2 | P51: =ROUND(Source!ES31,O51) -> 0 | W51: 0 | X51: 1 | Y51: 0 | Z51: 0 | AA51: 1 | AB51: 0
A52: 50 | B52: 0 | C52: 0 | D52: 1 | E52: 206 | F52: =ROUND(Source!T31,O52) -> 0 | G52: ВозврМат | H52: Возврат материалов | K52: 206 | L52: 20 | M52: 3 | O52: 2 | P52: =ROUND(Source!DL31,O52) -> 0 | W52: 0 | X52: 1 | Y52: 0 | Z52: 0 | AA52: 1 | AB52: 0
A53: 50 | B53: 0 | C53: 0 | D53: 1 | E53: 207 | F53: =Source!U31 -> 0 | G53: ТрудСтр | H53: Трудозатраты строителей | K53: 207 | L53: 21 | M53: 3 | O53: -1 | P53: =Source!DM31 -> 0 | W53: 0 | X53: 1 | Y53: 0 | Z53: 0 | AA53: 1 | AB53: 0
A54: 50 | B54: 0 | C54: 0 | D54: 1 | E54: 208 | F54: =Source!V31 -> 0 | G54: ТрудМаш | H54: Трудозатраты машинистов | K54: 208 | L54: 22 | M54: 3 | O54: -1 | P54: =Source!DN31 -> 0 | W54: 0 | X54: 1 | Y54: 0 | Z54: 0 | AA54: 1 | AB54: 0
A55: 50 | B55: 0 | C55: 0 | D55: 1 | E55: 209 | F55: =ROUND(Source!W31,O55) -> 0 | G55: ТранспМат | H55: Транспорт материалов | K55: 209 | L55: 23 | M55: 3 | O55: 2 | P55: =ROUND(Source!DO31,O55) -> 0 | W55: 0 | X55: 1 | Y55: 0 | Z55: 0 | AA55: 1 | AB55: 0
A56: 50 | B56: 0 | C56: 0 | D56: 1 | E56: 233 | F56: =ROUND(Source!BD31,O56) -> 0 | G56: Перевозка | H56: Перевозка грузов | K56: 233 | L56: 24 | M56: 3 | O56: 2 | P56: =ROUND(Source!EV31,O56) -> 0 | W56: 0 | X56: 1 | Y56: 0 | Z56: 0 | AA56: 1 | AB56: 0
A57: 50 | B57: 0 | C57: 0 | D57: 1 | E57: 210 | F57: =ROUND(Source!X31,O57) -> 0 | G57: НР | H57: Накладные расходы | K57: 210 | L57: 25 | M57: 3 | O57: 2 | P57: =ROUND(Source!DP31,O57) -> 0 | W57: 0 | X57: 1 | Y57: 0 | Z57: 0 | AA57: 1 | AB57: 0
A58: 50 | B58: 0 | C58: 0 | D58: 1 | E58: 211 | F58: =ROUND(Source!Y31,O58) -> 0 | G58: СмПриб | H58: Сметная прибыль | K58: 211 | L58: 26 | M58: 3 | O58: 2 | P58: =ROUND(Source!DQ31,O58) -> 0 | W58: 0 | X58: 1 | Y58: 0 | Z58: 0 | AA58: 1 | AB58: 0
A59: 50 | B59: 0 | C59: 0 | D59: 1 | E59: 224 | F59: =ROUND(Source!AR31,O59) -> 188203.04 | G59: Всего | H59: Всего с НР и СП | K59: 224 | L59: 27 | M59: 3 | O59: 2 | P59: =ROUND(Source!EJ31,O59) -> 2900208.9 | W59: 188203.04 | X59: 1 | Y59: 188203.04 | Z59: 2900208.9 | AA59: 1 | AB59: 2900208.9
A61: 51 | B61: =B20 -> 1 | C61: =A20 -> 3 | D61: =ROW(A20) -> 20 | F61: =IF(F20<>"",F20,"") -> 09-01-02 | G61: =IF(G20<>"",G20,"") -> Перевозка мусора | H61: 0 | O61: =ROUND(O31+AB61,2) -> 188203.04 | P61: =ROUND(P31+AC61,2) -> 0 | Q61: =ROUND(Q31+AD61,2) -> 188203.04 | R61: =ROUND(R31+AE61,2) -> 0 | S61: =ROUND(S31+AF61,2) -> 0 | T61: =ROUND(T31+AG61,2) -> 0 | U61: =U31+AH61 -> 0 | V61: =V31+AI61 -> 0 | W61: =ROUND(W31+AJ61,2) -> 0 | X61: =ROUND(X31+AK61,2) -> 0 | Y61: =ROUND(Y31+AL61,2) -> 0 | AO61: =ROUND(AO31+BX61,2) -> 0 | AP61: =ROUND(AP31+BY61,2) -> 0 | AQ61: =ROUND(AQ31+BZ61,2) -> 0 | AR61: =ROUND(AR31+CA61,2) -> 188203.04 | AS61: =ROUND(AS31+CB61,2) -> 0 | AT61: =ROUND(AT31+CC61,2) -> 0 | AU61: =ROUND(AU31+CD61,2) -> 188203.04 | AV61: =ROUND(AV31+CE61,2) -> 0 | ... BD61: =ROUND(BD31+CM61,2) -> 0 | DG61: =ROUND(DG31+DT61,2) -> 2900208.9 | DH61: =ROUND(DH31+DU61,2) -> 0 | DI61: =ROUND(DI31+DV61,2) -> 2900208.9 | DJ61: =ROUND(DJ31+DW61,2) -> 0 | DK61: =ROUND(DK31+DX61,2) -> 0 | DL61: =ROUND(DL31+DY61,2) -> 0 | DM61: =DM31+DZ61 -> 0 | DN61: =DN31+EA61 -> 0 | DO61: =ROUND(DO31+EB61,2) -> 0 | DP61: =ROUND(DP31+EC61,2) -> 0 | DQ61: =ROUND(DQ31+ED61,2) -> 0 | EG61: =ROUND(EG31+FP61,2) -> 0 | EH61: =ROUND(EH31+FQ61,2) -> 0 | EI61: =ROUND(EI31+FR61,2) -> 0 | EJ61: =ROUND(EJ31+FS61,2) -> 2900208.9 | EK61: =ROUND(EK31+FT61,2) -> 0 | EL61: =ROUND(EL31+FU61,2) -> 0 | EM61: =ROUND(EM31+FV61,2) -> 2900208.9 | EN61: =ROUND(EN31+FW61,2) -> 0 | ... EV61: =ROUND(EV31+GE61,2) -> 0 | GX61: 0
A63: 50 | B63: 0 | C63: 0 | D63: 1 | E63: 201 | F63: =ROUND(Source!O61,O63) -> 188203.04 | G63: ПЗ | H63: Прямые затраты | K63: 201 | L63: 1 | M63: 3 | O63: 2 | P63: =ROUND(Source!DG61,O63) -> 2900208.9 | W63: 188203.04 | X63: 1 | Y63: 188203.04 | Z63: 2900208.9 | AA63: 1 | AB63: 2900208.9
A64: 50 | B64: 0 | C64: 0 | D64: 1 | E64: 202 | F64: =ROUND(Source!P61,O64) -> 0 | G64: СтМатОб | H64: Стоимость материальных ресурсов (всего) | K64: 202 | L64: 2 | M64: 3 | O64: 2 | P64: =ROUND(Source!DH61,O64) -> 0 | W64: 0 | X64: 1 | Y64: 0 | Z64: 0 | AA64: 1 | AB64: 0
A65: 50 | B65: 0 | C65: 0 | D65: 1 | E65: 222 | F65: =ROUND(Source!AO61,O65) -> 0 | G65: СтМатОбЗак | H65: Стоимость материалов и оборудования заказчика | K65: 222 | L65: 3 | M65: 3 | O65: 2 | P65: =ROUND(Source!EG61,O65) -> 0 | W65: 0 | X65: 1 | Y65: 0 | Z65: 0 | AA65: 1 | AB65: 0
A66: 50 | B66: 0 | C66: 0 | D66: 1 | E66: 225 | F66: =ROUND(Source!AV61,O66) -> 0 | G66: СтМатОбПод | H66: Стоимость материалов и оборудования подрядчика | K66: 225 | L66: 4 | M66: 3 | O66: 2 | P66: =ROUND(Source!EN61,O66) -> 0 | W66: 0 | X66: 1 | Y66: 0 | Z66: 0 | AA66: 1 | AB66: 0
A67: 50 | B67: 0 | C67: 0 | D67: 1 | E67: 226 | F67: =ROUND(Source!AW61,O67) -> 0 | G67: СтМат | H67: Стоимость материалов (всего) | K67: 226 | L67: 5 | M67: 3 | O67: 2 | P67: =ROUND(Source!EO61,O67) -> 0 | W67: 0 | X67: 1 | Y67: 0 | Z67: 0 | AA67: 1 | AB67: 0
A68: 50 | B68: 0 | C68: 0 | D68: 1 | E68: 227 | F68: =ROUND(Source!AX61,O68) -> 0 | G68: СтМатЗак | H68: Стоимость материалов заказчика | K68: 227 | L68: 6 | M68: 3 | O68: 2 | P68: =ROUND(Source!EP61,O68) -> 0 | W68: 0 | X68: 1 | Y68: 0 | Z68: 0 | AA68: 1 | AB68: 0
A69: 50 | B69: 0 | C69: 0 | D69: 1 | E69: 228 | F69: =ROUND(Source!AY61,O69) -> 0 | G69: СтМатПод | H69: Стоимость материалов подрядчика | K69: 228 | L69: 7 | M69: 3 | O69: 2 | P69: =ROUND(Source!EQ61,O69) -> 0 | W69: 0 | X69: 1 | Y69: 0 | Z69: 0 | AA69: 1 | AB69: 0
A70: 50 | B70: 0 | C70: 0 | D70: 1 | E70: 216 | F70: =ROUND(Source!AP61,O70) -> 0 | G70: Оборуд | H70: Стоимость оборудования (всего) | K70: 216 | L70: 8 | M70: 3 | O70: 2 | P70: =ROUND(Source!EH61,O70) -> 0 | W70: 0 | X70: 1 | Y70: 0 | Z70: 0 | AA70: 1 | AB70: 0
A71: 50 | B71: 0 | C71: 0 | D71: 1 | E71: 223 | F71: =ROUND(Source!AQ61,O71) -> 0 | G71: ОборудЗак | H71: Стоимость оборудования заказчика | K71: 223 | L71: 9 | M71: 3 | O71: 2 | P71: =ROUND(Source!EI61,O71) -> 0 | W71: 0 | X71: 1 | Y71: 0 | Z71: 0 | AA71: 1 | AB71: 0
A72: 50 | B72: 0 | C72: 0 | D72: 1 | E72: 229 | F72: =ROUND(Source!AZ61,O72) -> 0 | G72: ОборудПод | H72: Стоимость оборудования подрядчика | K72: 229 | L72: 10 | M72: 3 | O72: 2 | P72: =ROUND(Source!ER61,O72) -> 0 | W72: 0 | X72: 1 | Y72: 0 | Z72: 0 | AA72: 1 | AB72: 0
A73: 50 | B73: 0 | C73: 0 | D73: 1 | E73: 203 | F73: =ROUND(Source!Q61,O73) -> 188203.04 | G73: ЭММ | H73: Эксплуатация машин | K73: 203 | L73: 11 | M73: 3 | O73: 2 | P73: =ROUND(Source!DI61,O73) -> 2900208.9 | W73: 188203.04 | X73: 1 | Y73: 188203.04 | Z73: 2900208.9 | AA73: 1 | AB73: 2900208.9
A74: 50 | B74: 0 | C74: 0 | D74: 1 | E74: 231 | F74: =ROUND(Source!BB61,O74) -> 0 | G74: ЭММсНРиСП | H74: Эксплуатация машин по ТСН-2001.16 | K74: 231 | L74: 12 | M74: 3 | O74: 2 | P74: =ROUND(Source!ET61,O74) -> 0 | W74: 0 | X74: 1 | Y74: 0 | Z74: 0 | AA74: 1 | AB74: 0
A75: 50 | B75: 0 | C75: 0 | D75: 1 | E75: 204 | F75: =ROUND(Source!R61,O75) -> 0 | G75: ЗПМ | H75: ЗП машинистов | K75: 204 | L75: 13 | M75: 3 | O75: 2 | P75: =ROUND(Source!DJ61,O75) -> 0 | W75: 0 | X75: 1 | Y75: 0 | Z75: 0 | AA75: 1 | AB75: 0
A76: 50 | B76: 0 | C76: 0 | D76: 1 | E76: 205 | F76: =ROUND(Source!S61,O76) -> 0 | G76: ОЗП | H76: Основная ЗП рабочих | K76: 205 | L76: 14 | M76: 3 | O76: 2 | P76: =ROUND(Source!DK61,O76) -> 0 | W76: 0 | X76: 1 | Y76: 0 | Z76: 0 | AA76: 1 | AB76: 0
A77: 50 | B77: 0 | C77: 0 | D77: 1 | E77: 232 | F77: =ROUND(Source!BC61,O77) -> 0 | G77: ОЗПсНРиСП | H77: Основная ЗП рабочих по ТСН-2001.16 | K77: 232 | L77: 15 | M77: 3 | O77: 2 | P77: =ROUND(Source!EU61,O77) -> 0 | W77: 0 | X77: 1 | Y77: 0 | Z77: 0 | AA77: 1 | AB77: 0
A78: 50 | B78: 0 | C78: 0 | D78: 1 | E78: 214 | F78: =ROUND(Source!AS61,O78) -> 0 | G78: Строит | H78: Строительные работы с НР и СП | K78: 214 | L78: 16 | M78: 3 | O78: 2 | P78: =ROUND(Source!EK61,O78) -> 0 | W78: 0 | X78: 1 | Y78: 0 | Z78: 0 | AA78: 1 | AB78: 0
A79: 50 | B79: 0 | C79: 0 | D79: 1 | E79: 215 | F79: =ROUND(Source!AT61,O79) -> 0 | G79: Монтаж | H79: Монтажные работы с НР и СП | K79: 215 | L79: 17 | M79: 3 | O79: 2 | P79: =ROUND(Source!EL61,O79) -> 0 | W79: 0 | X79: 1 | Y79: 0 | Z79: 0 | AA79: 1 | AB79: 0
A80: 50 | B80: 0 | C80: 0 | D80: 1 | E80: 217 | F80: =ROUND(Source!AU61,O80) -> 188203.04 | G80: Прочие | H80: Прочие работы с НР и СП | K80: 217 | L80: 18 | M80: 3 | O80: 2 | P80: =ROUND(Source!EM61,O80) -> 2900208.9 | W80: 188203.04 | X80: 1 | Y80: 188203.04 | Z80: 2900208.9 | AA80: 1 | AB80: 2900208.9
A81: 50 | B81: 0 | C81: 0 | D81: 1 | E81: 230 | F81: =ROUND(Source!BA61,O81) -> 0 | G81: ПрочиеЗатр | H81: Прочие затраты по ТСН-2001.16 | K81: 230 | L81: 19 | M81: 3 | O81: 2 | P81: =ROUND(Source!ES61,O81) -> 0 | W81: 0 | X81: 1 | Y81: 0 | Z81: 0 | AA81: 1 | AB81: 0
A82: 50 | B82: 0 | C82: 0 | D82: 1 | E82: 206 | F82: =ROUND(Source!T61,O82) -> 0 | G82: ВозврМат | H82: Возврат материалов | K82: 206 | L82: 20 | M82: 3 | O82: 2 | P82: =ROUND(Source!DL61,O82) -> 0 | W82: 0 | X82: 1 | Y82: 0 | Z82: 0 | AA82: 1 | AB82: 0
A83: 50 | B83: 0 | C83: 0 | D83: 1 | E83: 207 | F83: =Source!U61 -> 0 | G83: ТрудСтр | H83: Трудозатраты строителей | K83: 207 | L83: 21 | M83: 3 | O83: -1 | P83: =Source!DM61 -> 0 | W83: 0 | X83: 1 | Y83: 0 | Z83: 0 | AA83: 1 | AB83: 0
A84: 50 | B84: 0 | C84: 0 | D84: 1 | E84: 208 | F84: =Source!V61 -> 0 | G84: ТрудМаш | H84: Трудозатраты машинистов | K84: 208 | L84: 22 | M84: 3 | O84: -1 | P84: =Source!DN61 -> 0 | W84: 0 | X84: 1 | Y84: 0 | Z84: 0 | AA84: 1 | AB84: 0
A85: 50 | B85: 0 | C85: 0 | D85: 1 | E85: 209 | F85: =ROUND(Source!W61,O85) -> 0 | G85: ТранспМат | H85: Транспорт материалов | K85: 209 | L85: 23 | M85: 3 | O85: 2 | P85: =ROUND(Source!DO61,O85) -> 0 | W85: 0 | X85: 1 | Y85: 0 | Z85: 0 | AA85: 1 | AB85: 0
A86: 50 | B86: 0 | C86: 0 | D86: 1 | E86: 233 | F86: =ROUND(Source!BD61,O86) -> 0 | G86: Перевозка | H86: Перевозка грузов | K86: 233 | L86: 24 | M86: 3 | O86: 2 | P86: =ROUND(Source!EV61,O86) -> 0 | W86: 0 | X86: 1 | Y86: 0 | Z86: 0 | AA86: 1 | AB86: 0
A87: 50 | B87: 0 | C87: 0 | D87: 1 | E87: 210 | F87: =ROUND(Source!X61,O87) -> 0 | G87: НР | H87: Накладные расходы | K87: 210 | L87: 25 | M87: 3 | O87: 2 | P87: =ROUND(Source!DP61,O87) -> 0 | W87: 0 | X87: 1 | Y87: 0 | Z87: 0 | AA87: 1 | AB87: 0
A88: 50 | B88: 0 | C88: 0 | D88: 1 | E88: 211 | F88: =ROUND(Source!Y61,O88) -> 0 | G88: СмПриб | H88: Сметная прибыль | K88: 211 | L88: 26 | M88: 3 | O88: 2 | P88: =ROUND(Source!DQ61,O88) -> 0 | W88: 0 | X88: 1 | Y88: 0 | Z88: 0 | AA88: 1 | AB88: 0
A89: 50 | B89: 0 | C89: 0 | D89: 1 | E89: 224 | F89: =ROUND(Source!AR61,O89) -> 188203.04 | G89: Всего | H89: Всего с НР и СП | K89: 224 | L89: 27 | M89: 3 | O89: 2 | P89: =ROUND(Source!EJ61,O89) -> 2900208.9 | W89: 188203.04 | X89: 1 | Y89: 188203.04 | Z89: 2900208.9 | AA89: 1 | AB89: 2900208.9
A91: 51 | B91: =B12 -> 131 | C91: =A12 -> 1 | D91: =ROW(A12) -> 12 | F91: =IF(F12<>"",F12,"") -> 09-01-02 | G91: =IF(G12<>"",G12,"") -> 09-01-02 Перевозка мусора | H91: 0 | O91: =ROUND(O61,2) -> 188203.04 | P91: =ROUND(P61,2) -> 0 | Q91: =ROUND(Q61,2) -> 188203.04 | R91: =ROUND(R61,2) -> 0 | S91: =ROUND(S61,2) -> 0 | T91: =ROUND(T61,2) -> 0 | U91: =U61 -> 0 | V91: =V61 -> 0 | W91: =ROUND(W61,2) -> 0 | X91: =ROUND(X61,2) -> 0 | Y91: =ROUND(Y61,2) -> 0 | AO91: =ROUND(AO61,2) -> 0 | AP91: =ROUND(AP61,2) -> 0 | AQ91: =ROUND(AQ61,2) -> 0 | AR91: =ROUND(AR61,2) -> 188203.04 | AS91: =ROUND(AS61,2) -> 0 | AT91: =ROUND(AT61,2) -> 0 | AU91: =ROUND(AU61,2) -> 188203.04 | AV91: =ROUND(AV61,2) -> 0 | ... BD91: =ROUND(BD61,2) -> 0 | DG91: =ROUND(DG61,2) -> 2900208.9 | DH91: =ROUND(DH61,2) -> 0 | DI91: =ROUND(DI61,2) -> 2900208.9 | DJ91: =ROUND(DJ61,2) -> 0 | DK91: =ROUND(DK61,2) -> 0 | DL91: =ROUND(DL61,2) -> 0 | DM91: =DM61 -> 0 | DN91: =DN61 -> 0 | DO91: =ROUND(DO61,2) -> 0 | DP91: =ROUND(DP61,2) -> 0 | DQ91: =ROUND(DQ61,2) -> 0 | EG91: =ROUND(EG61,2) -> 0 | EH91: =ROUND(EH61,2) -> 0 | EI91: =ROUND(EI61,2) -> 0 | EJ91: =ROUND(EJ61,2) -> 2900208.9 | EK91: =ROUND(EK61,2) -> 0 | EL91: =ROUND(EL61,2) -> 0 | EM91: =ROUND(EM61,2) -> 2900208.9 | EN91: =ROUND(EN61,2) -> 0 | ... EV91: =ROUND(EV61,2) -> 0 | GX91: 0
A93: 50 | B93: 0 | C93: 0 | D93: 1 | E93: 201 | F93: =ROUND(Source!O91,O93) -> 188203.04 | G93: ПЗ | H93: Прямые затраты | K93: 201 | L93: 1 | M93: 3 | O93: 2 | P93: =ROUND(Source!DG91,O93) -> 2900208.9 | W93: 188203.04 | X93: 1 | Y93: 188203.04 | Z93: 2900208.9 | AA93: 1 | AB93: 2900208.9
A94: 50 | B94: 0 | C94: 0 | D94: 1 | E94: 202 | F94: =ROUND(Source!P91,O94) -> 0 | G94: СтМатОб | H94: Стоимость материальных ресурсов (всего) | K94: 202 | L94: 2 | M94: 3 | O94: 2 | P94: =ROUND(Source!DH91,O94) -> 0 | W94: 0 | X94: 1 | Y94: 0 | Z94: 0 | AA94: 1 | AB94: 0
A95: 50 | B95: 0 | C95: 0 | D95: 1 | E95: 222 | F95: =ROUND(Source!AO91,O95) -> 0 | G95: СтМатОбЗак | H95: Стоимость материалов и оборудования заказчика | K95: 222 | L95: 3 | M95: 3 | O95: 2 | P95: =ROUND(Source!EG91,O95) -> 0 | W95: 0 | X95: 1 | Y95: 0 | Z95: 0 | AA95: 1 | AB95: 0
A96: 50 | B96: 0 | C96: 0 | D96: 1 | E96: 225 | F96: =ROUND(Source!AV91,O96) -> 0 | G96: СтМатОбПод | H96: Стоимость материалов и оборудования подрядчика | K96: 225 | L96: 4 | M96: 3 | O96: 2 | P96: =ROUND(Source!EN91,O96) -> 0 | W96: 0 | X96: 1 | Y96: 0 | Z96: 0 | AA96: 1 | AB96: 0
A97: 50 | B97: 0 | C97: 0 | D97: 1 | E97: 226 | F97: =ROUND(Source!AW91,O97) -> 0 | G97: СтМат | H97: Стоимость материалов (всего) | K97: 226 | L97: 5 | M97: 3 | O97: 2 | P97: =ROUND(Source!EO91,O97) -> 0 | W97: 0 | X97: 1 | Y97: 0 | Z97: 0 | AA97: 1 | AB97: 0
A98: 50 | B98: 0 | C98: 0 | D98: 1 | E98: 227 | F98: =ROUND(Source!AX91,O98) -> 0 | G98: СтМатЗак | H98: Стоимость материалов заказчика | K98: 227 | L98: 6 | M98: 3 | O98: 2 | P98: =ROUND(Source!EP91,O98) -> 0 | W98: 0 | X98: 1 | Y98: 0 | Z98: 0 | AA98: 1 | AB98: 0
A99: 50 | B99: 0 | C99: 0 | D99: 1 | E99: 228 | F99: =ROUND(Source!AY91,O99) -> 0 | G99: СтМатПод | H99: Стоимость материалов подрядчика | K99: 228 | L99: 7 | M99: 3 | O99: 2 | P99: =ROUND(Source!EQ91,O99) -> 0 | W99: 0 | X99: 1 | Y99: 0 | Z99: 0 | AA99: 1 | AB99: 0
A100: 50 | B100: 0 | C100: 0 | D100: 1 | E100: 216 | F100: =ROUND(Source!AP91,O100) -> 0 | G100: Оборуд | H100: Стоимость оборудования (всего) | K100: 216 | L100: 8 | M100: 3 | O100: 2 | P100: =ROUND(Source!EH91,O100) -> 0 | W100: 0 | X100: 1 | Y100: 0 | Z100: 0 | AA100: 1 | AB100: 0
A101: 50 | B101: 0 | C101: 0 | D101: 1 | E101: 223 | F101: =ROUND(Source!AQ91,O101) -> 0 | G101: ОборудЗак | H101: Стоимость оборудования заказчика | K101: 223 | L101: 9 | M101: 3 | O101: 2 | P101: =ROUND(Source!EI91,O101) -> 0 | W101: 0 | X101: 1 | Y101: 0 | Z101: 0 | AA101: 1 | AB101: 0
A102: 50 | B102: 0 | C102: 0 | D102: 1 | E102: 229 | F102: =ROUND(Source!AZ91,O102) -> 0 | G102: ОборудПод | H102: Стоимость оборудования подрядчика | K102: 229 | L102: 10 | M102: 3 | O102: 2 | P102: =ROUND(Source!ER91,O102) -> 0 | W102: 0 | X102: 1 | Y102: 0 | Z102: 0 | AA102: 1 | AB102: 0
A103: 50 | B103: 0 | C103: 0 | D103: 1 | E103: 203 | F103: =ROUND(Source!Q91,O103) -> 188203.04 | G103: ЭММ | H103: Эксплуатация машин | K103: 203 | L103: 11 | M103: 3 | O103: 2 | P103: =ROUND(Source!DI91,O103) -> 2900208.9 | W103: 188203.04 | X103: 1 | Y103: 188203.04 | Z103: 2900208.9 | AA103: 1 | AB103: 2900208.9
A104: 50 | B104: 0 | C104: 0 | D104: 1 | E104: 231 | F104: =ROUND(Source!BB91,O104) -> 0 | G104: ЭММсНРиСП | H104: Эксплуатация машин по ТСН-2001.16 | K104: 231 | L104: 12 | M104: 3 | O104: 2 | P104: =ROUND(Source!ET91,O104) -> 0 | W104: 0 | X104: 1 | Y104: 0 | Z104: 0 | AA104: 1 | AB104: 0
A105: 50 | B105: 0 | C105: 0 | D105: 1 | E105: 204 | F105: =ROUND(Source!R91,O105) -> 0 | G105: ЗПМ | H105: ЗП машинистов | K105: 204 | L105: 13 | M105: 3 | O105: 2 | P105: =ROUND(Source!DJ91,O105) -> 0 | W105: 0 | X105: 1 | Y105: 0 | Z105: 0 | AA105: 1 | AB105: 0
A106: 50 | B106: 0 | C106: 0 | D106: 1 | E106: 205 | F106: =ROUND(Source!S91,O106) -> 0 | G106: ОЗП | H106: Основная ЗП рабочих | K106: 205 | L106: 14 | M106: 3 | O106: 2 | P106: =ROUND(Source!DK91,O106) -> 0 | W106: 0 | X106: 1 | Y106: 0 | Z106: 0 | AA106: 1 | AB106: 0
A107: 50 | B107: 0 | C107: 0 | D107: 1 | E107: 232 | F107: =ROUND(Source!BC91,O107) -> 0 | G107: ОЗПсНРиСП | H107: Основная ЗП рабочих по ТСН-2001.16 | K107: 232 | L107: 15 | M107: 3 | O107: 2 | P107: =ROUND(Source!EU91,O107) -> 0 | W107: 0 | X107: 1 | Y107: 0 | Z107: 0 | AA107: 1 | AB107: 0
A108: 50 | B108: 0 | C108: 0 | D108: 1 | E108: 214 | F108: =ROUND(Source!AS91,O108) -> 0 | G108: Строит | H108: Строительные работы с НР и СП | K108: 214 | L108: 16 | M108: 3 | O108: 2 | P108: =ROUND(Source!EK91,O108) -> 0 | W108: 0 | X108: 1 | Y108: 0 | Z108: 0 | AA108: 1 | AB108: 0
A109: 50 | B109: 0 | C109: 0 | D109: 1 | E109: 215 | F109: =ROUND(Source!AT91,O109) -> 0 | G109: Монтаж | H109: Монтажные работы с НР и СП | K109: 215 | L109: 17 | M109: 3 | O109: 2 | P109: =ROUND(Source!EL91,O109) -> 0 | W109: 0 | X109: 1 | Y109: 0 | Z109: 0 | AA109: 1 | AB109: 0
A110: 50 | B110: 0 | C110: 0 | D110: 1 | E110: 217 | F110: =ROUND(Source!AU91,O110) -> 188203.04 | G110: Прочие | H110: Прочие работы с НР и СП | K110: 217 | L110: 18 | M110: 3 | O110: 2 | P110: =ROUND(Source!EM91,O110) -> 2900208.9 | W110: 188203.04 | X110: 1 | Y110: 188203.04 | Z110: 2900208.9 | AA110: 1 | AB110: 2900208.9
A111: 50 | B111: 0 | C111: 0 | D111: 1 | E111: 230 | F111: =ROUND(Source!BA91,O111) -> 0 | G111: ПрочиеЗатр | H111: Прочие затраты по ТСН-2001.16 | K111: 230 | L111: 19 | M111: 3 | O111: 2 | P111: =ROUND(Source!ES91,O111) -> 0 | W111: 0 | X111: 1 | Y111: 0 | Z111: 0 | AA111: 1 | AB111: 0
A112: 50 | B112: 0 | C112: 0 | D112: 1 | E112: 206 | F112: =ROUND(Source!T91,O112) -> 0 | G112: ВозврМат | H112: Возврат материалов | K112: 206 | L112: 20 | M112: 3 | O112: 2 | P112: =ROUND(Source!DL91,O112) -> 0 | W112: 0 | X112: 1 | Y112: 0 | Z112: 0 | AA112: 1 | AB112: 0
A113: 50 | B113: 0 | C113: 0 | D113: 1 | E113: 207 | F113: =Source!U91 -> 0 | G113: ТрудСтр | H113: Трудозатраты строителей | K113: 207 | L113: 21 | M113: 3 | O113: -1 | P113: =Source!DM91 -> 0 | W113: 0 | X113: 1 | Y113: 0 | Z113: 0 | AA113: 1 | AB113: 0
A114: 50 | B114: 0 | C114: 0 | D114: 1 | E114: 208 | F114: =Source!V91 -> 0 | G114: ТрудМаш | H114: Трудозатраты машинистов | K114: 208 | L114: 22 | M114: 3 | O114: -1 | P114: =Source!DN91 -> 0 | W114: 0 | X114: 1 | Y114: 0 | Z114: 0 | AA114: 1 | AB114: 0
A115: 50 | B115: 0 | C115: 0 | D115: 1 | E115: 209 | F115: =ROUND(Source!W91,O115) -> 0 | G115: ТранспМат | H115: Транспорт материалов | K115: 209 | L115: 23 | M115: 3 | O115: 2 | P115: =ROUND(Source!DO91,O115) -> 0 | W115: 0 | X115: 1 | Y115: 0 | Z115: 0 | AA115: 1 | AB115: 0
A116: 50 | B116: 0 | C116: 0 | D116: 1 | E116: 233 | F116: =ROUND(Source!BD91,O116) -> 0 | G116: Перевозка | H116: Перевозка грузов | K116: 233 | L116: 24 | M116: 3 | O116: 2 | P116: =ROUND(Source!EV91,O116) -> 0 | W116: 0 | X116: 1 | Y116: 0 | Z116: 0 | AA116: 1 | AB116: 0
A117: 50 | B117: 0 | C117: 0 | D117: 1 | E117: 210 | F117: =ROUND(Source!X91,O117) -> 0 | G117: НР | H117: Накладные расходы | K117: 210 | L117: 25 | M117: 3 | O117: 2 | P117: =ROUND(Source!DP91,O117) -> 0 | W117: 0 | X117: 1 | Y117: 0 | Z117: 0 | AA117: 1 | AB117: 0
A118: 50 | B118: 0 | C118: 0 | D118: 1 | E118: 211 | F118: =ROUND(Source!Y91,O118) -> 0 | G118: СмПриб | H118: Сметная прибыль | K118: 211 | L118: 26 | M118: 3 | O118: 2 | P118: =ROUND(Source!DQ91,O118) -> 0 | W118: 0 | X118: 1 | Y118: 0 | Z118: 0 | AA118: 1 | AB118: 0
A119: 50 | B119: 0 | C119: 0 | D119: 1 | E119: 224 | F119: =ROUND(Source!AR91,O119) -> 188203.04 | G119: Всего | H119: Всего с НР и СП | K119: 224 | L119: 27 | M119: 3 | O119: 2 | P119: =ROUND(Source!EJ91,O119) -> 2900208.9 | W119: 188203.04 | X119: 1 | Y119: 188203.04 | Z119: 2900208.9 | AA119: 1 | AB119: 2900208.9
A122: 70 | B122: 1 | D122: 1 | E122: ОБ_ПР | F122: Объект производственного назначения | G122: 0 | H122: 0 | J122: 1 | K122: 0 | N122: 0 | O122: 0
A123: 70 | B123: 1 | D123: 2 | E123: ОБ_НПР | F123: Объект непроизводственного назначения | G123: 1 | H123: 0 | J123: 1 | K123: 0 | N123: 0 | O123: 1
A124: 70 | B124: 1 | D124: 3 | E124: 3.27_АВТО | F124: {вкл} - НР и СП по п.18.1 "Автомобильные дороги" {выкл} - НР и СП по п.18.2 "Устройство покрытий дорожек, тротуаров, мостовых и площадок и прочее" 3.27 Табл. 3.27-121, расценки 3.27-26-1...4 | G124: 1 | H124: 0 | J124: 0 | K124: 0 | N124: 0 | O124: 1
A125: 70 | B125: 1 | D125: 4 | E125: 3.29_ЗАКР | F125: {вкл} - Тоннели и метрополитены: закрытый способ работ {выкл} - Тоннели и метрополитены: открытый способ работ 3.29 Отдел 1.5; табл. 3.29-1905...1906 | G125: 1 | H125: 0 | J125: 0 | K125: 0 | N125: 0 | O125: 1
A126: 70 | B126: 1 | D126: 5 | E126: 4.10_МЕЖГ | F126: {вкл} - Прокладка и монтаж междугородных линий связи {выкл} - Прокладка и монтаж сетей связи 4.10 Раздел 1.7.3...1.7.5 | G126: 0 | H126: 0 | J126: 0 | K126: 0 | N126: 0 | O126: 0
...

Sheet SourceObSm
A1: 0 | B1: Smeta.RU (495) 974-1589 | D1: _OBSM_ | F1: 0 | G1: 0 | H1: 0 | I1: Smeta.RU | K1: 1 | L1: 74562 | M1: 10 | N1: 11 | O1: 14 | P1: 0 | Q1: 0
A4: 1 | B4: 1 | C4: -1 | G4: Капитальный ремонт здания Государственного бюджетного общеобразовательного учреждения города Москвы «Школа № 236» по адресу: г. Москва, ул. Клязьминская, д. 7, к. 4. I этап | EC4: 0
A12: 1 | B12: 51 | C12: 0 | E12: 0 | F12: 09-01-02 | G12: 09-01-02 Перевозка мусора | I12: 0 | J12: 0224-00272-01-0-ООС2 | K12: 0 | L12: 0 | M12: 4098 | O12: 0 | P12: 0 | Q12: 0 | R12: 0 | S12: 0 | T12: 1 | V12: 0 | AB12: Лукьянова А.Л. | BB12: 0 | BH12: Сметные нормы списания | BI12: Коды ОКП для ТСН-2001 МГЭ Дополнение 79 | BJ12: 1 | BK12: 1 | BL12: 0 | BM12: 0 | BN12: 1 | BO12: 0 | BP12: 6 | BQ12: 2 | BR12: 1 | BS12: 1 | BT12: 0 | BU12: 0 | BV12: 0 | BW12: 0 | BX12: 0 | BY12: ТСН-2001 (МГЭ) Доп 79 - Новое строительство | BZ12: Типовой расчет для ТСН-2001 МГЭ, Дополнение 79, строительство | CA12: Территориальные сметные нормативы для Москвы ТСН-2001 (МГЭ), дополнение 79 | CB12: Территориальные сметные нормативы для Москвы ТСН-2001 (МГЭ), дополнение 79 | CC12: Территориальные сметные нормативы для Москвы ТСН-2001 (МГЭ), дополнение 79 | CD12: Территориальные сметные нормативы для Москвы ТСН-2001 (МГЭ), дополнение 79 | CE12: Поправки для ТСН-2001 от 03.10.2025 г. доп.79 | CF12: 0 | CG12: 0 | CH12: 8200 | CK12: 79 | CQ12: Территориальные сметные нормативы для Москвы (ТСН-2001) | CR12: ТЕР | CS12: 41660 | CT12: 1 | CU12: 79 | CY12: 0 | EC12: 0
A14: 22 | B14: 1 | C14: 0 | D14: 56526071 | E14: 56526069 | F14: 2 | G14: 1
A16: 3 | B16: 1 | C16: 09-01-02 | D16: Перевозка мусора | E16: =ROUND((Source!P78)/1000,2) -> 0 | F16: =ROUND((Source!P79)/1000,2) -> 0 | G16: =ROUND((Source!P70)/1000,2) -> 0 | H16: =ROUND((Source!P80)/1000+(Source!P81)/1000,2) -> 2900.21 | I16: =E16+F16+G16+H16 -> 2900.21 | J16: =ROUND((Source!P76+Source!P75)/1000,2) -> 0 | K16: 2900.21 | L16: 0 | M16: 0 | N16: =I16+L16+M16 -> 2900.21 | T16: =ROUND((Source!F78)/1000,2) -> 0 | U16: =ROUND((Source!F79)/1000,2) -> 0 | V16: =ROUND((Source!F70)/1000,2) -> 0 | W16: =ROUND((Source!F80)/1000+(Source!F81)/1000,2) -> 188.2 | X16: =T16+U16+V16+W16 -> 188.2 | Y16: =ROUND((Source!F76+Source!F75)/1000,2) -> 0 | Z16: 188.2 | AA16: 0 | AB16: 0 | AC16: =X16+AA16+AB16 -> 188.2 | AI16: 0 | AJ16: -1 | AN16: 0 | AT16: 2900208.9 | AU16: 0 | AV16: 0 | AW16: 0 | AX16: 0 | AY16: 2900208.9 | AZ16: 0 | BA16: 0 | BB16: 0 | BC16: 0 | BD16: 2900208.9 | BE16: 0 | BF16: 0 | BG16: 0 | BH16: 0 | BI16: 0 | BJ16: 0 | BK16: 2900208.9 | BR16: 188203.04 | BS16: 0 | BT16: 0 | BU16: 0 | BV16: 0 | BW16: 188203.04 | BX16: 0 | BY16: 0 | BZ16: 0 | CA16: 0 | CB16: 188203.04 | CC16: 0 | CD16: 0 | CE16: 0 | CF16: 0 | CG16: 0 | CH16: 0 | CI16: 188203.04
A18: 51 | E18: 0 | F18: 0 | G18: 0 | H18: 2900.21 | I18: 2900.21 | J18: 0 | K18: 2900.21 | L18: 0 | M18: 0 | N18: 2900.21 | T18: 0 | U18: 0 | V18: 0 | W18: 188.2 | X18: 188.2 | Y18: 0 | Z18: 188.2 | AA18: 0 | AB18: 0 | AC18: 188.2
A20: 50 | B20: 0 | C20: 0 | D20: 1 | E20: 201 | F20: 2900208.9 | G20: ПЗ | H20: Прямые затраты | K20: 201 | L20: 1 | M20: 3 | O20: 2 | P20: 188203.04
A21: 50 | B21: 0 | C21: 0 | D21: 1 | E21: 202 | F21: 0 | G21: СтМатОб | H21: Стоимость материальных ресурсов (всего) | K21: 202 | L21: 2 | M21: 3 | O21: 2 | P21: 0
A22: 50 | B22: 0 | C22: 0 | D22: 1 | E22: 222 | F22: 0 | G22: СтМатОбЗак | H22: Стоимость материалов и оборудования заказчика | K22: 222 | L22: 3 | M22: 3 | O22: 2 | P22: 0
A23: 50 | B23: 0 | C23: 0 | D23: 1 | E23: 225 | F23: 0 | G23: СтМатОбПод | H23: Стоимость материалов и оборудования подрядчика | K23: 225 | L23: 4 | M23: 3 | O23: 2 | P23: 0
A24: 50 | B24: 0 | C24: 0 | D24: 1 | E24: 226 | F24: 0 | G24: СтМат | H24: Стоимость материалов (всего) | K24: 226 | L24: 5 | M24: 3 | O24: 2 | P24: 0
A25: 50 | B25: 0 | C25: 0 | D25: 1 | E25: 227 | F25: 0 | G25: СтМатЗак | H25: Стоимость материалов заказчика | K25: 227 | L25: 6 | M25: 3 | O25: 2 | P25: 0
A26: 50 | B26: 0 | C26: 0 | D26: 1 | E26: 228 | F26: 0 | G26: СтМатПод | H26: Стоимость материалов подрядчика | K26: 228 | L26: 7 | M26: 3 | O26: 2 | P26: 0
A27: 50 | B27: 0 | C27: 0 | D27: 1 | E27: 216 | F27: 0 | G27: Оборуд | H27: Стоимость оборудования (всего) | K27: 216 | L27: 8 | M27: 3 | O27: 2 | P27: 0
A28: 50 | B28: 0 | C28: 0 | D28: 1 | E28: 223 | F28: 0 | G28: ОборудЗак | H28: Стоимость оборудования заказчика | K28: 223 | L28: 9 | M28: 3 | O28: 2 | P28: 0
A29: 50 | B29: 0 | C29: 0 | D29: 1 | E29: 229 | F29: 0 | G29: ОборудПод | H29: Стоимость оборудования подрядчика | K29: 229 | L29: 10 | M29: 3 | O29: 2 | P29: 0
A30: 50 | B30: 0 | C30: 0 | D30: 1 | E30: 203 | F30: 2900208.9 | G30: ЭММ | H30: Эксплуатация машин | K30: 203 | L30: 11 | M30: 3 | O30: 2 | P30: 188203.04
A31: 50 | B31: 0 | C31: 0 | D31: 1 | E31: 231 | F31: 0 | G31: ЭММсНРиСП | H31: Эксплуатация машин по ТСН-2001.16 | K31: 231 | L31: 12 | M31: 3 | O31: 2 | P31: 0
... A46: 50 | B46: 0 | C46: 0 | D46: 1 | E46: 224 | F46: 2900208.9 | G46: Всего | H46: Всего с НР и СП | K46: 224 | L46: 27 | M46: 3 | O46: 2 | P46: 188203.04
A48: -1
A51: 75 | B51: Текущий уровень цен | C51: 2025 | D51: 0 | E51: 7 | G51: 0 | H51: 1 | I51: 1 | J51: 3 | K51: 0 | L51: 0 | M51: 1 | N51: 56526071 | O51: 1
A52: 1 | B52: Сборник индексов | C52: Коэффициенты к ТСН-2001 МГЭ Дополнение 79, строительство | D52: 2025 | E52: 7 | F52: 1 | G52: 1 | H52: 0 | I52: 2 | J52: 1 | K52: 1 | L52: 1 | M52: 1 | N52: 1 | O52: 1 | P52: 1 | Q52: 1 | AA52: 216/79 | AN52: 56526072
A53: 1 | B53: Сборник индексов | C53: Коэффициенты к ТСН-2001.13-2 Дополнение 45 | D53: 2025 | E53: 7 | F53: 1 | G53: 1 | H53: 0 | I53: 2 | J53: 1 | K53: 1 | L53: 1 | M53: 1 | N53: 1 | O53: 1 | P53: 1 | Q53: 1 | AA53: 62/45 | AN53: 56526073
A54: 75 | B54: Базовый уровень цен | C54: 2000 | D54: 0 | E54: 1 | F54: 0 | G54: 0 | H54: 1 | I54: 1 | J54: 3 | K54: 0 | L54: 0 | M54: 0 | N54: 56526069 | O54: 2
A55: 1 | B55: Сборник индексов | C55: Коэффициенты к ТСН-2001 МГЭ Дополнение 79, строительство | D55: 2000 | E55: 1 | F55: 1 | G55: 1 | H55: 0 | I55: 2 | J55: 1 | K55: 1 | L55: 1 | M55: 1 | N55: 1 | O55: 1 | P55: 1 | Q55: 1 | AN55: 56526070

Sheet SmtRes
A1: =ROW(Source!A28) -> 28 | B1: 56526069 | C1: 56526703 | D1: 54836954 | E1: 1079 | F1: 1 | G1: 1079 | H1: 2 | I1: 9999990007 | K1: Стоимость прочих машин (ЭСН) | L1: 1344 | N1: 1008 | O1: руб. | P1: руб. | Q1: 1 | W1: 0 | X1: -1180195794 | Y1: =AT1 -> 58.45 | AA1: 0 | AB1: 1 | AC1: 0 | AD1: 0 | AE1: 0 | AF1: 1 | AG1: 0 | AH1: 0 | AI1: 1 | AJ1: 1 | AK1: 1 | AL1: 1 | AM1: -2 | AN1: 0 | AO1: 1 | AP1: 1 | AQ1: 0 | AR1: 0 | AT1: 58.45 | AV1: 0 | AW1: 2 | AX1: 56526706 | AY1: 1 | AZ1: 0 | BA1: 1 | BB1: 0 | BC1: 0 | BD1: 0 | BE1: 0 | BF1: 0 | BG1: 0 | BH1: 0 | BI1: 0 | BJ1: 0 | BK1: 0 | BL1: 0 | BM1: 0 | BN1: 0 | BO1: 0 | BP1: 0 | BQ1: 0 | BR1: 0 | BS1: 0 | BT1: 0 | BU1: 0 | BV1: 0 | BW1: 0 | CV1: 0 | CW1: =ROUND(Y1*Source!I28*DO1,9) -> 0 | CX1: =ROUND(Y1*Source!I28,9) -> 188203.04 | CY1: =AB1 -> 1 | CZ1: =AF1 -> 1 | DA1: =AJ1 -> 1 | DB1: =ROUND(ROUND(AT1*CZ1,2),6) -> 58.45 | DC1: =ROUND(ROUND(AT1*AG1,2),6) -> 0 | DF1: =ROUND(ROUND(AE1,2)*CX1,2) -> 0 | DG1: =ROUND(ROUND(AF1,2)*CX1,2) -> 188203.04 | DH1: =ROUND(ROUND(AG1,2)*CX1,2) -> 0 | DI1: =ROUND(ROUND(AH1,2)*CX1,2) -> 0 | DJ1: =DG1 -> 188203.04 | DK1: 0 | DM1: 0 | DO1: 0
A2: =ROW(Source!A29) -> 29 | B2: 56526071 | C2: 56526703 | D2: 54836954 | E2: 1079 | F2: 1 | G2: 1079 | H2: 2 | I2: 9999990007 | K2: Стоимость прочих машин (ЭСН) | L2: 1344 | N2: 1008 | O2: руб. | P2: руб. | Q2: 1 | W2: 0 | X2: -1180195794 | Y2: =AT2 -> 58.45 | AA2: 0 | AB2: 1 | AC2: 0 | AD2: 0 | AE2: 0 | AF2: 1 | AG2: 0 | AH2: 0 | AI2: 1 | AJ2: 1 | AK2: 1 | AL2: 1 | AM2: -2 | AN2: 0 | AO2: 1 | AP2: 1 | AQ2: 0 | AR2: 0 | AT2: 58.45 | AV2: 0 | AW2: 2 | AX2: 56526706 | AY2: 1 | AZ2: 0 | BA2: 2 | BB2: 0 | BC2: 0 | BD2: 0 | BE2: 0 | BF2: 0 | BG2: 0 | BH2: 0 | BI2: 0 | BJ2: 0 | BK2: 0 | BL2: 0 | BM2: 0 | BN2: 0 | BO2: 0 | BP2: 0 | BQ2: 0 | BR2: 0 | BS2: 0 | BT2: 0 | BU2: 0 | BV2: 0 | BW2: 0 | CV2: 0 | CW2: =ROUND(Y2*Source!I29*DO2,9) -> 0 | CX2: =ROUND(Y2*Source!I29,9) -> 188203.04 | CY2: =AB2 -> 1 | CZ2: =AF2 -> 1 | DA2: =AJ2 -> 1 | DB2: =ROUND(ROUND(AT2*CZ2,2),6) -> 58.45 | DC2: =ROUND(ROUND(AT2*AG2,2),6) -> 0 | DF2: =ROUND(ROUND(AE2,2)*CX2,2) -> 0 | DG2: =ROUND(ROUND(AF2,2)*CX2,2) -> 188203.04 | DH2: =ROUND(ROUND(AG2,2)*CX2,2) -> 0 | DI2: =ROUND(ROUND(AH2,2)*CX2,2) -> 0 | DJ2: =DG2 -> 188203.04 | DK2: 0 | DM2: 0 | DO2: 0

Sheet EtalonRes
A1: =ROW(Source!A28) -> 28 | B1: 56526706 | C1: 56526703 | D1: 54836954 | E1: 1079 | F1: 1 | G1: 1079 | H1: 2 | I1: 9999990007 | K1: Стоимость прочих машин (ЭСН) | L1: 1344 | N1: 1008 | O1: руб. | P1: руб. | Q1: 1 | X1: 58.45 | Y1: 0 | Z1: 1 | AA1: 0 | AB1: 0 | AC1: 0 | AD1: 1 | AE1: 0 | AG1: 58.45 | AH1: 2 | AI1: 56526706 | AJ1: 1 | AK1: 0 | AL1: 0 | AM1: 0 | AN1: 0 | AO1: 0 | AP1: 0 | AQ1: 0 | AR1: 0
A2: =ROW(Source!A29) -> 29 | B2: 56526706 | C2: 56526703 | D2: 54836954 | E2: 1079 | F2: 1 | G2: 1079 | H2: 2 | I2: 9999990007 | K2: Стоимость прочих машин (ЭСН) | L2: 1344 | N2: 1008 | O2: руб. | P2: руб. | Q2: 1 | X2: 58.45 | Y2: 0 | Z2: 1 | AA2: 0 | AB2: 0 | AC2: 0 | AD2: 1 | AE2: 0 | AG2: 58.45 | AH2: 2 | AI2: 56526706 | AJ2: 2 | AK2: 0 | AL2: 0 | AM2: 0 | AN2: 0 | AO2: 0 | AP2: 0 | AQ2: 0 | AR2: 0

Sheet SrcPoprs

Sheet SrcKA
A1: 0 | B1: Smeta.RU (495) 974-1589 | D1: _PS_ | F1: 0 | G1: 0 | H1: 0 | I1: Smeta.RU | K1: 1 | L1: 74562 | M1: 10 | N1: 11 | O1: 14 | P1: 0 | Q1: 0
F12: =Source!F12 -> 09-01-02 | G12: =Source!G12 -> 09-01-02 Перевозка мусора | CY12: =Source!CY12 -> 0
