Workbook

Sheet 02-01-02
A1: =Source!B1 -> Smeta.RU (495) 974-1589
J2: Форма № 4б
B3: "СОГЛАСОВАНО" | G3: "УТВЕРЖДАЮ"
B6: =CONCATENATE("______________________ ", IF(Source!AL12<>"", Source!AL12, "")) -> ______________________ | G6: =CONCATENATE("______________________ ", IF(Source!AH12<>"", Source!AH12, "")) -> ______________________
B7: "_____"________________ 2025 г. | G7: "_____"________________ 2025 г.
A10: Капитальный ремонт здания Государственного бюджетного общеобразовательного учреждения города Москвы «Школа № 236» по адресу: г. Москва, ул. Клязьминская, д. 7, к. 4. I этап | AP10: Капитальный ремонт здания Государственного бюджетного общеобразовательного учреждения города Москвы «Школа № 236» по адресу: г. Москва, ул. Клязьминская, д. 7, к. 4. I этап. 02-01-02 Конструктивные решения
A11: (наименование стройки и/или объекта)
A13: ЛОКАЛЬНАЯ СМЕТА № 02-01-02
A15: =IF(Source!G20<>"Новая локальная смета", Source!G20, "") -> Конструктивные решения
A16: (наименование работ и затрат)
A18: =CONCATENATE( "Основание: чертежи № ", Source!J20) -> Основание: чертежи № 2024-00272-01-0-КР.ВОР
I20: В базисном уровне цен | J20: В текущем уровне цен
E21: Сметная стоимость | I21: =I22+I23+I24+I25 -> 4298.49 | J21: =J22+J23+J24+J25 -> 68645.51 | K21: тыс.руб.
E22: Строительные работы | I22: =ROUND((Source!F1544)/1000, 2) -> 4298.49 | J22: =ROUND((Source!P1544)/1000, 2) -> 68645.51 | K22: тыс.руб.
E23: Работы по монтажу оборудования | I23: =ROUND((Source!F1545)/1000, 2) -> 0 | J23: =ROUND((Source!P1545)/1000, 2) -> 0 | K23: тыс.руб.
E24: Оборудование | I24: =ROUND((Source!F1536)/1000, 2) -> 0 | J24: =ROUND((Source!P1536)/1000, 2) -> 0 | K24: тыс.руб.
E25: Прочие работы и затраты | I25: =ROUND((Source!F1546+Source!F1547)/1000, 2) -> 0 | J25: =ROUND((Source!P1546+Source!P1547)/1000, 2) -> 0 | K25: тыс.руб.
E26: Средства на оплату труда | I26: =(Source!F1542+ Source!F1541)/1000 -> 364.80192 | J26: =((Source!P1542 + Source!P1541)/1000) -> 17451.356 | K26: тыс.руб.
E27: Затраты труда | I27: =Source!F1549 -> 27400.046 | K27: чел.-ч.
E28: Кроме того:
E29: Возврат материалов | I29: =SUM(Y35:Y1500)/1000 -> 0 | J29: =SUM(Z35:Z1500)/1000 -> 0 | K29: тыс.руб.
A31: Составлен(а) по ТСН-2001 с учетом Дополнения №: 79
A32: № и период сборника коэффициентов (индексов) пересчета: Коэффициенты к ТСН-2001 МГЭ Дополнение 79, ремонт №216/79 III квартал 2025 года и Коэффициенты к ТСН-2001.13-2 Дополнение 45 №62/45 III квартал 2025 года | M32: Пересчитать в Доп. 79, 3 квартал сентябрь | AP32: № и период сборника коэффициентов (индексов) пересчета: Коэффициенты к ТСН-2001 МГЭ Дополнение 79, ремонт №216/79 III квартал 2025 года и Коэффициенты к ТСН-2001.13-2 Дополнение 45 №62/45 III квартал 2025 года
A33: № п/п | B33: Шифр расценки и коды ресурсов | C33: Наименование работ и затрат | D33: Ед. изм. | E33: Кол-во единиц | F33: Цена на ед. изм., руб. | G33: Попра- вочные коэффи- циенты | H33: Коэффи- циенты зимних удорожа- ний | I33: Всего в ценах на январь 2000 года, руб. | J33: Коэффи- циенты (индек- сы) пере- счета, нормы НР и СП | K33: ВСЕГО затрат в текущем уровне цен, руб.
A34: 1 | B34: 2 | C34: 3 | D34: 4 | E34: 5 | F34: 6 | G34: 7 | H34: 8 | I34: 9 | J34: 10 | K34: 11
A36: =CONCATENATE("Раздел: ",IF(Source!G24<>"Новый раздел", Source!G24, "")) -> Раздел: Усиление внутренних и наружных стен в зоне расширяемых проемов в подвале и в надземной части здания. Рама РС-1, 105 шт. (КР-5,6) | AP36: =CONCATENATE("Раздел: ",IF(Source!G24<>"Новый раздел", Source!G24, "")) -> Раздел: Усиление внутренних и наружных стен в зоне расширяемых проемов в подвале и в надземной части здания. Рама РС-1, 105 шт. (КР-5,6)
A37: 1 | B37: 6.53-25-1 Поправка: Гл.12.Прил.8.п.8. 5_12.00.01.11.003 | C37: Усиление кирпичных стен металлическим каркасом | D37: =Source!H28 -> 1 Т | E37: =Source!I28 -> 25.5045 | M37: откорректировать объемы и виды работ в соответствии с КР.ВОР | Q37: =Source!X28 -> 68224.72 | R37: =Source!X29 -> 3262505.9 | S37: =Source!Y28 -> 38561.8 | T37: =Source!Y29 -> 1844025.1 | U37: =ROUND((175/100)*ROUND(Source!R28, 2), 2) -> 116.69 | V37: =ROUND((0/100)*ROUND(Source!R29, 2), 2) -> 0 | AC37: 0
C38: ="Объем: "&Source!I28&"=(70,9+"&"38,5+"&"109,3+"&"7,4+"&"7,2+"&"2,7+"&"6,9)/"&"1000*"&"105" -> Объем: 25,5045=(70,9+38,5+109,3+7,4+7,2+2,7+6,9)/1000*105
C39: ЗП | F39: =Source!AO28 -> 2522.36 | G39: =Source!DG28 -> *1,1 | H39: =Source!AV29 -> 1.047 | I39: =Source!S28 -> 74090.62 | J39: =IF(Source!BA29<> 0, Source!BA29, 1) -> 47.82 | K39: =Source!S29 -> 3543013.5
C40: ЭМ | F40: =Source!AM28 -> 36.08 | G40: =Source!DE28 -> *1,1 | H40: =Source!AV29 -> 1.047 | I40: =Source!Q28 -> 1059.8 | J40: =IF(Source!BB29<> 0, Source!BB29, 1) -> 13.74 | K40: =Source!Q29 -> 14561.65
C41: в т.ч. ЗПМ | F41: =Source!AN28 -> 2.27 | G41: =Source!DF28 -> *1,1 | H41: =Source!AV29 -> 1.047 | I41: =Source!R28 -> 66.68 | J41: =IF(Source!BS29<> 0, Source!BS29, 1) -> 47.82 | K41: =Source!R29 -> 3188.64
C42: МР | F42: =Source!AL28 -> 28.74 | G42: =Source!DD28 | H42: =Source!AW29 -> 1.002 | I42: =Source!P28 -> 734.47 | J42: =IF(Source!BC29<> 0, Source!BC29, 1) -> 13.02 | K42: =Source!P29 -> 9562.8
A43: 1,1 | B43: =Source!F30 -> 1.1-1-1121 | C43: Уголок равнополочный, для строительных стальных конструкций, ширина полки более 70 мм, сталь С235, С245 | D43: =Source!H30 -> т | E43: =Source!I30 -> 24.465 | F43: =Source!AK30 -> 9844.31 | H43: =Source!AW31 -> 1.002 | I43: =Source!O30 -> 241322.73 | J43: =IF(Source!BC31<> 0, Source!BC31, 1) -> 7.54 | K43: =Source!O31 -> 1819573.4 | Q43: =Source!X30 -> 0 | R43: =Source!X31 -> 0 | S43: =Source!Y30 -> 0 | T43: =Source!Y31 -> 0 | U43: =ROUND((175/100)*ROUND(Source!R30, 2), 2) -> 0 | V43: =ROUND((0/100)*ROUND(Source!R31, 2), 2) -> 0 | AC43: 3
A44: 1,2 | B44: =Source!F32 -> 1.1-1-1105 | C44: Прокат листовой из стали С235, С245 для строительных стальных конструкций, толщина более 3 мм | D44: =Source!H32 -> т | E44: =Source!I32 -> 1.0395 | F44: =Source!AK32 -> 6519.2 | H44: =Source!AW33 -> 1.002 | I44: =Source!O32 -> 6790.26 | J44: =IF(Source!BC33<> 0, Source!BC33, 1) -> 10.12 | K44: =Source!O33 -> 68717.43 | Q44: =Source!X32 -> 0 | R44: =Source!X33 -> 0 | S44: =Source!Y32 -> 0 | T44: =Source!Y33 -> 0 | U44: =ROUND((175/100)*ROUND(Source!R32, 2), 2) -> 0 | V44: =ROUND((0/100)*ROUND(Source!R33, 2), 2) -> 0 | AC44: 3
A45: 1,3 | B45: =Source!F34 -> 1.7-5-220 | C45: Шпилька резьбовая, стальная, оцинкованная, с заостренным концом, в комплекте с шайбой и гайкой, М16x190 мм | D45: =Source!H34 -> шт. | E45: =Source!I34 -> 1470 | F45: =Source!AK34 -> 29.8 | H45: =Source!AW35 -> 1.002 | I45: =Source!O34 -> 43893.61 | J45: =IF(Source!BC35<> 0, Source!BC35, 1) -> 11.97 | K45: =Source!O35 -> 525406.51 | Q45: =Source!X34 -> 0 | R45: =Source!X35 -> 0 | S45: =Source!Y34 -> 0 | T45: =Source!Y35 -> 0 | U45: =ROUND((175/100)*ROUND(Source!R34, 2), 2) -> 0 | V45: =ROUND((0/100)*ROUND(Source!R35, 2), 2) -> 0 | AC45: 3
C46: НР от ЗП | D46: % | E46: =Source!BZ29 -> 92 | I46: =SUM(Q37:Q45) -> 68224.72 | J46: =Source!AT29 -> 92 | K46: =SUM(R37:R45) -> 3262505.9
C47: СП от ЗП | D47: % | E47: =Source!CA29 -> 52 | I47: =SUM(S37:S46) -> 38561.8 | J47: =Source!AU29 -> 52 | K47: =SUM(T37:T46) -> 1844025.1
C48: ЗТР | D48: чел-ч | E48: =Source!AQ28 -> 201.95 | G48: =Source!DI28 -> *1,1 | H48: =Source!AV29 -> 1.047 | I48: =Source!U28 -> 5931.9849
C49: ВСЕГО работ по позиции: | H49: =I39+I40+I42+I46+I47+SUM(I43:I45)-SUMIF(AC43:AC45, 5, I43:I45)-SUMIF(AC43:AC45, 6, I43:I45) -> 474678.01 | J49: =K39+K40+K42+K46+K47+SUM(K43:K45)-SUMIF(AC43:AC45, 5, K43:K45)-SUMIF(AC43:AC45, 6, K43:K45) -> 11087366
C50: ВСЕГО оборудование по позиции: | H50: =SUMIF(AC43:AC45, 5, I43:I45)+SUMIF(AC43:AC45, 6, I43:I45) -> 0 | J50: =SUMIF(AC43:AC45, 5, K43:K45)+SUMIF(AC43:AC45, 6, K43:K45) -> 0
C51: ВСЕГО по позиции: | H51: =I39+I40+I42+I46+I47+SUM(I43:I45) -> 474678.01 | J51: =K39+K40+K42+K46+K47+SUM(K43:K45) -> 11087366 | O51: =I39+I40+I42+I46+I47+SUM(I43:I45) -> 474678.01 | P51: =K39+K40+K42+K46+K47+SUM(K43:K45) -> 11087366
A53: 2 | B53: 3.13-9-2 Поправка: О.П. п.3.4. 6 Поправка: О.П. п.3.4.30.в | C53: Огрунтовка металлических поверхностей грунтовкой ГФ-021 за один раз | D53: =Source!H36 -> 100 м2 | E53: =Source!I36 -> 7.6375005 | Q53: =Source!X36 -> 718.83 | R53: =Source!X37 -> 32030.94 | S53: =Source!Y36 -> 460.05 | T53: =Source!Y37 -> 15835.52 | U53: =ROUND((175/100)*ROUND(Source!R36, 2), 2) -> 4.6 | V53: =ROUND((0/100)*ROUND(Source!R37, 2), 2) -> 0 | AC53: 0
C54: ="Объем: "&Source!I36&"=(70,9*"&"26,3+"&"38,5*"&"26,3+"&"109,3*"&"33+"&"7,4*"&"33+"&"7,2*"&"32,1+"&"2,7*"&"32,1+"&"6,9*"&"33)/"&"1000/"&"100*"&"105" -> Объем: 7,6375005=(70,9*26,3+38,5*26,3+109,3*33+7,4*33+7,2*32,1+2,7*32,1+6,9*33)/1000/100*105
C55: ЗП | F55: =Source!AO36 -> 74.13 | G55: =Source!DG36 -> *1,15)*1,1 | H55: =Source!AV37 -> 1.047 | I55: =Source!S36 -> 716.2 | J55: =IF(Source!BA37<> 0, Source!BA37, 1) -> 47.82 | K55: =Source!S37 -> 35858.31
C56: ЭМ | F56: =Source!AM36 -> 13.64 | G56: =Source!DE36 -> *1,25)*1,1 | H56: =Source!AV37 -> 1.047 | I56: =Source!Q36 -> 143.24 | J56: =IF(Source!BB37<> 0, Source!BB37, 1) -> 10.51 | K56: =Source!Q37 -> 1576.18
C57: в т.ч. ЗПМ | F57: =Source!AN36 -> 0.25 | G57: =Source!DF36 -> *1,25)*1,1 | H57: =Source!AV37 -> 1.047 | I57: =Source!R36 -> 2.63 | J57: =IF(Source!BS37<> 0, Source!BS37, 1) -> 47.82 | K57: =Source!R37 -> 131.51
C58: МР | F58: =Source!AL36 -> 9.46 | G58: =Source!DD36 | H58: =Source!AW37 -> 1 | I58: =Source!P36 -> 72.25 | J58: =IF(Source!BC37<> 0, Source!BC37, 1) -> 32.25 | K58: =Source!P37 -> 2330.06
A59: 2,1 | B59: =Source!F38 -> 1.1-1-165 | C59: Грунтовка глифталевая, типа ГФ-021 | D59: =Source!H38 -> т | E59: =Source!I38 -> 0.068738 | F59: =Source!AK38 -> 18660.61 | H59: =Source!AW39 -> 1 | I59: =Source!O38 -> 1282.69 | J59: =IF(Source!BC39<> 0, Source!BC39, 1) -> 3.58 | K59: =Source!O39 -> 4592.03 | Q59: =Source!X38 -> 0 | R59: =Source!X39 -> 0 | S59: =Source!Y38 -> 0 | T59: =Source!Y39 -> 0 | U59: =ROUND((175/100)*ROUND(Source!R38, 2), 2) -> 0 | V59: =ROUND((0/100)*ROUND(Source!R39, 2), 2) -> 0 | AC59: 3
C60: НР от ЗП | D60: % | E60: =Source!BZ37 -> 89 | I60: =SUM(Q53:Q59) -> 718.83 | J60: =Source!AT37 -> 89 | K60: =SUM(R53:R59) -> 32030.94
C61: СП от ЗП | D61: % | E61: =Source!CA37 -> 44 | I61: =SUM(S53:S60) -> 460.05 | J61: =Source!AU37 -> 44 | K61: =SUM(T53:T60) -> 15835.52
C62: ЗТР | D62: чел-ч | E62: =Source!AQ36 -> 5.31 | G62: =Source!DI36 -> *1,15)*1,1 | H62: =Source!AV37 -> 1.047 | I62: =Source!U36 -> 51.302236
C63: ВСЕГО работ по позиции: | H63: =I55+I56+I58+I60+I61+SUM(I59:I59)-SUMIF(AC59:AC59, 5, I59:I59)-SUMIF(AC59:AC59, 6, I59:I59) -> 3393.26 | J63: =K55+K56+K58+K60+K61+SUM(K59:K59)-SUMIF(AC59:AC59, 5, K59:K59)-SUMIF(AC59:AC59, 6, K59:K59) -> 92223.04
C64: ВСЕГО оборудование по позиции: | H64: =SUMIF(AC59:AC59, 5, I59:I59)+SUMIF(AC59:AC59, 6, I59:I59) -> 0 | J64: =SUMIF(AC59:AC59, 5, K59:K59)+SUMIF(AC59:AC59, 6, K59:K59) -> 0
C65: ВСЕГО по позиции: | H65: =I55+I56+I58+I60+I61+SUM(I59:I59) -> 3393.26 | J65: =K55+K56+K58+K60+K61+SUM(K59:K59) -> 92223.04 | O65: =I55+I56+I58+I60+I61+SUM(I59:I59) -> 3393.26 | P65: =K55+K56+K58+K60+K61+SUM(K59:K59) -> 92223.04
A68: =CONCATENATE("Итого по разделу: ",IF(Source!G41<>"Новый раздел", Source!G41, "")) -> Итого по разделу: Усиление внутренних и наружных стен в зоне расширяемых проемов в подвале и в надземной части здания. Рама РС-1, 105 шт. (КР-5,6) | H68: =SUM(O36:O67) -> 478071.27 | J68: =SUM(P36:P67) -> 11179589 | AQ68: =CONCATENATE("Итого по разделу: ",IF(Source!G41<>"Новый раздел", Source!G41, "")) -> Итого по разделу: Усиление внутренних и наружных стен в зоне расширяемых проемов в подвале и в надземной части здания. Рама РС-1, 105 шт. (КР-5,6)
A69: Итого по ТСН-2001.16 | I69: =SUM(W36:W68) -> 0 | J69: =SUM(X36:X68) -> 0
A70: Итого возвратных сумм | I70: =SUM(Y36:Y69) -> 0 | J70: =SUM(Z36:Z69) -> 0
A72: =CONCATENATE("Раздел: ",IF(Source!G71<>"Новый раздел", Source!G71, "")) -> Раздел: Усиление внутренних и наружных стен в зоне расширяемых проемов в подвале и в надземной части здания. Рама РС-2, 22 шт. (КР-5,6) | AP72: =CONCATENATE("Раздел: ",IF(Source!G71<>"Новый раздел", Source!G71, "")) -> Раздел: Усиление внутренних и наружных стен в зоне расширяемых проемов в подвале и в надземной части здания. Рама РС-2, 22 шт. (КР-5,6)
A73: 3 | B73: 6.53-25-1 Поправка: Гл.12.Прил.8.п.8. 5_12.00.01.11.003 | C73: Усиление кирпичных стен металлическим каркасом | D73: =Source!H75 -> 1 Т | E73: =Source!I75 -> 4.7322 | Q73: =Source!X75 -> 12658.67 | R73: =Source!X76 -> 605337.42 | S73: =Source!Y75 -> 7154.9 | T73: =Source!Y76 -> 342147.24 | U73: =ROUND((175/100)*ROUND(Source!R75, 2), 2) -> 21.65 | V73: =ROUND((0/100)*ROUND(Source!R76, 2), 2) -> 0 | AC73: 0
C74: ="Объем: "&Source!I75&"=(67,6+"&"106,3+"&"4,2+"&"6,9+"&"7,2+"&"11,3+"&"0,9+"&"1,4+"&"9,3)/"&"1000*"&"22" -> Объем: 4,7322=(67,6+106,3+4,2+6,9+7,2+11,3+0,9+1,4+9,3)/1000*22
C75: ЗП | F75: =Source!AO75 -> 2522.36 | G75: =Source!DG75 -> *1,1 | H75: =Source!AV76 -> 1.047 | I75: =Source!S75 -> 13747.05 | J75: =IF(Source!BA76<> 0, Source!BA76, 1) -> 47.82 | K75: =Source!S76 -> 657383.93
C76: ЭМ | F76: =Source!AM75 -> 36.08 | G76: =Source!DE75 -> *1,1 | H76: =Source!AV76 -> 1.047 | I76: =Source!Q75 -> 196.64 | J76: =IF(Source!BB76<> 0, Source!BB76, 1) -> 13.74 | K76: =Source!Q76 -> 2701.83
C77: в т.ч. ЗПМ | F77: =Source!AN75 -> 2.27 | G77: =Source!DF75 -> *1,1 | H77: =Source!AV76 -> 1.047 | I77: =Source!R75 -> 12.37 | J77: =IF(Source!BS76<> 0, Source!BS76, 1) -> 47.82 | K77: =Source!R76 -> 591.53
C78: МР | F78: =Source!AL75 -> 28.74 | G78: =Source!DD75 | H78: =Source!AW76 -> 1.002 | I78: =Source!P75 -> 136.28 | J78: =IF(Source!BC76<> 0, Source!BC76, 1) -> 13.02 | K78: =Source!P76 -> 1774.37
A79: 3,1 | B79: =Source!F77 -> 1.1-1-1145 | C79: Швеллер №№ 12-40, из стали углеродистой обыкновенного качества, спокойной | D79: =Source!H77 -> т | E79: =Source!I77 -> 1.4872 | F79: =Source!AK77 -> 8407.51 | H79: =Source!AW78 -> 1.002 | I79: =Source!O77 -> 12503.65 | J79: =IF(Source!BC78<> 0, Source!BC78, 1) -> 11.21 | K79: =Source!O78 -> 140446.28 | Q79: =Source!X77 -> 0 | R79: =Source!X78 -> 0 | S79: =Source!Y77 -> 0 | T79: =Source!Y78 -> 0 | U79: =ROUND((175/100)*ROUND(Source!R77, 2), 2) -> 0 | V79: =ROUND((0/100)*ROUND(Source!R78, 2), 2) -> 0 | AC79: 3
A80: 3,2 | B80: =Source!F79 -> 1.1-1-1121 | C80: Уголок равнополочный, для строительных стальных конструкций, ширина полки более 70 мм, сталь С235, С245 | D80: =Source!H79 -> т | E80: =Source!I79 -> 2.5828 | F80: =Source!AK79 -> 9844.31 | H80: =Source!AW80 -> 1.002 | I80: =Source!O79 -> 25476.74 | J80: =IF(Source!BC80<> 0, Source!BC80, 1) -> 7.54 | K80: =Source!O80 -> 192094.62 | Q80: =Source!X79 -> 0 | R80: =Source!X80 -> 0 | S80: =Source!Y79 -> 0 | T80: =Source!Y80 -> 0 | U80: =ROUND((175/100)*ROUND(Source!R79, 2), 2) -> 0 | V80: =ROUND((0/100)*ROUND(Source!R80, 2), 2) -> 0 | AC80: 3
A81: 3,3 | B81: =Source!F81 -> 1.1-1-1105 | C81: Прокат листовой из стали С235, С245 для строительных стальных конструкций, толщина более 3 мм | D81: =Source!H81 -> т | E81: =Source!I81 -> 0.6622 | F81: =Source!AK81 -> 6519.2 | H81: =Source!AW82 -> 1.002 | I81: =Source!O81 -> 4325.65 | J81: =IF(Source!BC82<> 0, Source!BC82, 1) -> 10.12 | K81: =Source!O82 -> 43775.58 | Q81: =Source!X81 -> 0 | R81: =Source!X82 -> 0 | S81: =Source!Y81 -> 0 | T81: =Source!Y82 -> 0 | U81: =ROUND((175/100)*ROUND(Source!R81, 2), 2) -> 0 | V81: =ROUND((0/100)*ROUND(Source!R82, 2), 2) -> 0 | AC81: 3
A82: 3,4 | B82: =Source!F83 -> 1.7-5-220 | C82: Шпилька резьбовая, стальная, оцинкованная, с заостренным концом, в комплекте с шайбой и гайкой, М16x190 мм | D82: =Source!H83 -> шт. | E82: =Source!I83 -> 176 | F82: =Source!AK83 -> 29.8 | H82: =Source!AW84 -> 1.002 | I82: =Source!O83 -> 5255.29 | J82: =IF(Source!BC84<> 0, Source!BC84, 1) -> 11.97 | K82: =Source!O84 -> 62905.82 | Q82: =Source!X83 -> 0 | R82: =Source!X84 -> 0 | S82: =Source!Y83 -> 0 | T82: =Source!Y84 -> 0 | U82: =ROUND((175/100)*ROUND(Source!R83, 2), 2) -> 0 | V82: =ROUND((0/100)*ROUND(Source!R84, 2), 2) -> 0 | AC82: 3
A83: 3,5 | B83: =Source!F85 -> 1.7-5-233 | C83: Анкер-болт забивной, распорный, стальной, оцинкованный, с широкой шайбой M12х110 | D83: =Source!H85 -> 100 шт. | E83: =Source!I85 -> 0.88 | F83: =Source!AK85 -> 560.04 | H83: =Source!AW86 -> 1.002 | I83: =Source!O85 -> 493.82 | J83: =IF(Source!BC86<> 0, Source!BC86, 1) -> 19.66 | K83: =Source!O86 -> 9708.5 | Q83: =Source!X85 -> 0 | R83: =Source!X86 -> 0 | S83: =Source!Y85 -> 0 | T83: =Source!Y86 -> 0 | U83: =ROUND((175/100)*ROUND(Source!R85, 2), 2) -> 0 | V83: =ROUND((0/100)*ROUND(Source!R86, 2), 2) -> 0 | AC83: 3
C84: НР от ЗП | D84: % | E84: =Source!BZ76 -> 92 | I84: =SUM(Q73:Q83) -> 12658.67 | J84: =Source!AT76 -> 92 | K84: =SUM(R73:R83) -> 605337.42
C85: СП от ЗП | D85: % | E85: =Source!CA76 -> 52 | I85: =SUM(S73:S84) -> 7154.9 | J85: =Source!AU76 -> 52 | K85: =SUM(T73:T84) -> 342147.24
C86: ЗТР | D86: чел-ч | E86: =Source!AQ75 -> 201.95 | G86: =Source!DI75 -> *1,1 | H86: =Source!AV76 -> 1.047 | I86: =Source!U75 -> 1100.6426
C87: ВСЕГО работ по позиции: | H87: =I75+I76+I78+I84+I85+SUM(I79:I83)-SUMIF(AC79:AC83, 5, I79:I83)-SUMIF(AC79:AC83, 6, I79:I83) -> 81948.69 | J87: =K75+K76+K78+K84+K85+SUM(K79:K83)-SUMIF(AC79:AC83, 5, K79:K83)-SUMIF(AC79:AC83, 6, K79:K83) -> 2058275.6
C88: ВСЕГО оборудование по позиции: | H88: =SUMIF(AC79:AC83, 5, I79:I83)+SUMIF(AC79:AC83, 6, I79:I83) -> 0 | J88: =SUMIF(AC79:AC83, 5, K79:K83)+SUMIF(AC79:AC83, 6, K79:K83) -> 0
C89: ВСЕГО по позиции: | H89: =I75+I76+I78+I84+I85+SUM(I79:I83) -> 81948.69 | J89: =K75+K76+K78+K84+K85+SUM(K79:K83) -> 2058275.6 | O89: =I75+I76+I78+I84+I85+SUM(I79:I83) -> 81948.69 | P89: =K75+K76+K78+K84+K85+SUM(K79:K83) -> 2058275.6
A91: 4 | B91: 3.13-9-2 Поправка: О.П. п.3.4. 6 Поправка: О.П. п.3.4.30.в | C91: Огрунтовка металлических поверхностей грунтовкой ГФ-021 за один раз | D91: =Source!H87 -> 100 м2 | E91: =Source!I87 -> 1.4266978 | Q91: =Source!X87 -> 134.28 | R91: =Source!X88 -> 5983.49 | S91: =Source!Y87 -> 85.94 | T91: =Source!Y88 -> 2958.13 | U91: =ROUND((175/100)*ROUND(Source!R87, 2), 2) -> 0.86 | V91: =ROUND((0/100)*ROUND(Source!R88, 2), 2) -> 0 | AC91: 0
C92: ="Объем: "&Source!I87&"=(67,6*"&"26,1+"&"106,3*"&"33+"&"4,2*"&"33+"&"6,9*"&"33+"&"7,2*"&"32,1+"&"11,3*"&"21,5+"&"0,9*"&"32,1+"&"1,4*"&"32,1+"&"9,3*"&"32,1)/"&"1000/"&"100*"&"22" -> Объем: 1,4266978=(67,6*26,1+106,3*33+4,2*33+6,9*33+7,2*32,1+11,3*21,5+0,9*32,1+1,4*32,1+9,3*32,1)/1000/100*22
C93: ЗП | F93: =Source!AO87 -> 74.13 | G93: =Source!DG87 -> *1,15)*1,1 | H93: =Source!AV88 -> 1.047 | I93: =Source!S87 -> 133.79 | J93: =IF(Source!BA88<> 0, Source!BA88, 1) -> 47.82 | K93: =Source!S88 -> 6698.63
C94: ЭМ | F94: =Source!AM87 -> 13.64 | G94: =Source!DE87 -> *1,25)*1,1 | H94: =Source!AV88 -> 1.047 | I94: =Source!Q87 -> 26.76 | J94: =IF(Source!BB88<> 0, Source!BB88, 1) -> 10.51 | K94: =Source!Q88 -> 294.49
C95: в т.ч. ЗПМ | F95: =Source!AN87 -> 0.25 | G95: =Source!DF87 -> *1,25)*1,1 | H95: =Source!AV88 -> 1.047 | I95: =Source!R87 -> 0.49 | J95: =IF(Source!BS88<> 0, Source!BS88, 1) -> 47.82 | K95: =Source!R88 -> 24.39
C96: МР | F96: =Source!AL87 -> 9.46 | G96: =Source!DD87 | H96: =Source!AW88 -> 1 | I96: =Source!P87 -> 13.5 | J96: =IF(Source!BC88<> 0, Source!BC88, 1) -> 32.25 | K96: =Source!P88 -> 435.38
A97: 4,1 | B97: =Source!F89 -> 1.1-1-165 | C97: Грунтовка глифталевая, типа ГФ-021 | D97: =Source!H89 -> т | E97: =Source!I89 -> 0.01284 | F97: =Source!AK89 -> 18660.61 | H97: =Source!AW90 -> 1 | I97: =Source!O89 -> 239.6 | J97: =IF(Source!BC90<> 0, Source!BC90, 1) -> 3.58 | K97: =Source!O90 -> 857.77 | Q97: =Source!X89 -> 0 | R97: =Source!X90 -> 0 | S97: =Source!Y89 -> 0 | T97: =Source!Y90 -> 0 | U97: =ROUND((175/100)*ROUND(Source!R89, 2), 2) -> 0 | V97: =ROUND((0/100)*ROUND(Source!R90, 2), 2) -> 0 | AC97: 3
C98: НР от ЗП | D98: % | E98: =Source!BZ88 -> 89 | I98: =SUM(Q91:Q97) -> 134.28 | J98: =Source!AT88 -> 89 | K98: =SUM(R91:R97) -> 5983.49
C99: СП от ЗП | D99: % | E99: =Source!CA88 -> 44 | I99: =SUM(S91:S98) -> 85.94 | J99: =Source!AU88 -> 44 | K99: =SUM(T91:T98) -> 2958.13
C100: ЗТР | D100: чел-ч | E100: =Source!AQ87 -> 5.31 | G100: =Source!DI87 -> *1,15)*1,1 | H100: =Source!AV88 -> 1.047 | I100: =Source!U87 -> 9.5833431
C101: ВСЕГО работ по позиции: | H101: =I93+I94+I96+I98+I99+SUM(I97:I97)-SUMIF(AC97:AC97, 5, I97:I97)-SUMIF(AC97:AC97, 6, I97:I97) -> 633.87 | J101: =K93+K94+K96+K98+K99+SUM(K97:K97)-SUMIF(AC97:AC97, 5, K97:K97)-SUMIF(AC97:AC97, 6, K97:K97) -> 17227.89
C102: ВСЕГО оборудование по позиции: | H102: =SUMIF(AC97:AC97, 5, I97:I97)+SUMIF(AC97:AC97, 6, I97:I97) -> 0 | J102: =SUMIF(AC97:AC97, 5, K97:K97)+SUMIF(AC97:AC97, 6, K97:K97) -> 0
C103: ВСЕГО по позиции: | H103: =I93+I94+I96+I98+I99+SUM(I97:I97) -> 633.87 | J103: =K93+K94+K96+K98+K99+SUM(K97:K97) -> 17227.89 | O103: =I93+I94+I96+I98+I99+SUM(I97:I97) -> 633.87 | P103: =K93+K94+K96+K98+K99+SUM(K97:K97) -> 17227.89
A106: =CONCATENATE("Итого по разделу: ",IF(Source!G92<>"Новый раздел", Source!G92, "")) -> Итого по разделу: Усиление внутренних и наружных стен в зоне расширяемых проемов в подвале и в надземной части здания. Рама РС-2, 22 шт. (КР-5,6) | H106: =SUM(O72:O105) -> 82582.56 | J106: =SUM(P72:P105) -> 2075503.5 | AQ106: =CONCATENATE("Итого по разделу: ",IF(Source!G92<>"Новый раздел", Source!G92, "")) -> Итого по разделу: Усиление внутренних и наружных стен в зоне расширяемых проемов в подвале и в надземной части здания. Рама РС-2, 22 шт. (КР-5,6)
A107: Итого по ТСН-2001.16 | I107: =SUM(W72:W106) -> 0 | J107: =SUM(X72:X106) -> 0
A108: Итого возвратных сумм | I108: =SUM(Y72:Y107) -> 0 | J108: =SUM(Z72:Z107) -> 0
A110: =CONCATENATE("Раздел: ",IF(Source!G122<>"Новый раздел", Source!G122, "")) -> Раздел: Усиление внутренних и наружных стен в зоне расширяемых проемов в подвале и в надземной части здания. Рама РС-3, 5 шт. (КР-5,6) | AP110: =CONCATENATE("Раздел: ",IF(Source!G122<>"Новый раздел", Source!G122, "")) -> Раздел: Усиление внутренних и наружных стен в зоне расширяемых проемов в подвале и в надземной части здания. Рама РС-3, 5 шт. (КР-5,6)
A111: 5 | B111: 6.53-25-1 Поправка: Гл.12.Прил.8.п.8. 5_12.00.01.11.003 | C111: Усиление кирпичных стен металлическим каркасом | D111: =Source!H126 -> 1 Т | E111: =Source!I126 -> 1.473 | Q111: =Source!X126 -> 3940.29 | R111: =Source!X127 -> 188424.5 | S111: =Source!Y126 -> 2227.12 | T111: =Source!Y127 -> 106500.8 | U111: =ROUND((175/100)*ROUND(Source!R126, 2), 2) -> 6.74 | V111: =ROUND((0/100)*ROUND(Source!R127, 2), 2) -> 0 | AC111: 0
C112: ="Объем: "&Source!I126&"=(146,3+"&"108,5+"&"15,7+"&"7,2+"&"16,9)/"&"1000*"&"5" -> Объем: 1,473=(146,3+108,5+15,7+7,2+16,9)/1000*5
C113: ЗП | F113: =Source!AO126 -> 2522.36 | G113: =Source!DG126 -> *1,1 | H113: =Source!AV127 -> 1.047 | I113: =Source!S126 -> 4279.07 | J113: =IF(Source!BA127<> 0, Source!BA127, 1) -> 47.82 | K113: =Source!S127 -> 204625.13
C114: ЭМ | F114: =Source!AM126 -> 36.08 | G114: =Source!DE126 -> *1,1 | H114: =Source!AV127 -> 1.047 | I114: =Source!Q126 -> 61.21 | J114: =IF(Source!BB127<> 0, Source!BB127, 1) -> 13.74 | K114: =Source!Q127 -> 841.03
C115: в т.ч. ЗПМ | F115: =Source!AN126 -> 2.27 | G115: =Source!DF126 -> *1,1 | H115: =Source!AV127 -> 1.047 | I115: =Source!R126 -> 3.85 | J115: =IF(Source!BS127<> 0, Source!BS127, 1) -> 47.82 | K115: =Source!R127 -> 184.11
C116: МР | F116: =Source!AL126 -> 28.74 | G116: =Source!DD126 | H116: =Source!AW127 -> 1.002 | I116: =Source!P126 -> 42.42 | J116: =IF(Source!BC127<> 0, Source!BC127, 1) -> 13.02 | K116: =Source!P127 -> 552.31
A117: 5,1 | B117: =Source!F128 -> 1.1-1-1121 | C117: Уголок равнополочный, для строительных стальных конструкций, ширина полки более 70 мм, сталь С235, С245 | D117: =Source!H128 -> т | E117: =Source!I128 -> 1.3525 | F117: =Source!AK128 -> 9844.31 | H117: =Source!AW129 -> 1.002 | I117: =Source!O128 -> 13341.06 | J117: =IF(Source!BC129<> 0, Source!BC129, 1) -> 7.54 | K117: =Source!O129 -> 100591.59 | Q117: =Source!X128 -> 0 | R117: =Source!X129 -> 0 | S117: =Source!Y128 -> 0 | T117: =Source!Y129 -> 0 | U117: =ROUND((175/100)*ROUND(Source!R128, 2), 2) -> 0 | V117: =ROUND((0/100)*ROUND(Source!R129, 2), 2) -> 0 | AC117: 3
A118: 5,2 | B118: =Source!F130 -> 1.1-1-1105 | C118: Прокат листовой из стали С235, С245 для строительных стальных конструкций, толщина более 3 мм | D118: =Source!H130 -> т | E118: =Source!I130 -> 0.1205 | F118: =Source!AK130 -> 6519.2 | H118: =Source!AW131 -> 1.002 | I118: =Source!O130 -> 787.13 | J118: =IF(Source!BC131<> 0, Source!BC131, 1) -> 10.12 | K118: =Source!O131 -> 7965.76 | Q118: =Source!X130 -> 0 | R118: =Source!X131 -> 0 | S118: =Source!Y130 -> 0 | T118: =Source!Y131 -> 0 | U118: =ROUND((175/100)*ROUND(Source!R130, 2), 2) -> 0 | V118: =ROUND((0/100)*ROUND(Source!R131, 2), 2) -> 0 | AC118: 3
...

Sheet Ведомость объемов работ
A1: =Source!B1 -> Smeta.RU (495) 974-1589
E3: "УТВЕРЖДАЮ"
D5: ___________________________
D7: ___________________________
D9: " ___ " ___________ 20 ___ г.
B12: =CONCATENATE("Ведомость объемов работ ", IF(Source!AN15<>"", Source!AN15," ")) -> Ведомость объемов работ
B13: =CONCATENATE(Source!F12, " ", Source!G12) -> 02-01-02 02-01-02 Конструктивные решения
A16: № п/п | B16: № в ЛСР | C16: Наименование работ и затрат | D16: Единица измерения | E16: Количество | F16: Ссылка на чертежи, спецификации | G16: Формула расчета, расчет объемов работ и расхода материалов | H16: Примечание
A17: 1 | B17: 2 | C17: 3 | D17: 4 | E17: 5 | F17: 6 | G17: 7 | H17: 8
A18: =CONCATENATE("Локальная смета: ", Source!G20) -> Локальная смета: Конструктивные решения
A19: =CONCATENATE("Раздел: ", Source!G24) -> Раздел: Усиление внутренних и наружных стен в зоне расширяемых проемов в подвале и в надземной части здания. Рама РС-1, 105 шт. (КР-5,6) | AF19: =CONCATENATE("Раздел: ", Source!G24) -> Раздел: Усиление внутренних и наружных стен в зоне расширяемых проемов в подвале и в надземной части здания. Рама РС-1, 105 шт. (КР-5,6)
A20: 1 | B20: =Source!E28 -> 1 | C20: =Source!G28 -> Усиление кирпичных стен металлическим каркасом | D20: 1 Т | E20: =Source!I28 -> 25.5045 | F20: =Source!U24 | G20: ="=(70,9+"&"38,5+"&"109,3+"&"7,4+"&"7,2+"&"2,7+"&"6,9)/"&"1000*"&"105" -> =(70,9+38,5+109,3+7,4+7,2+2,7+6,9)/1000*105
A21: 1.1 | B21: =Source!E30 -> 1,1 | C21: =Source!G30 -> Уголок равнополочный, для строительных стальных конструкций, ширина полки более 70 мм, сталь С235, С245 | D21: т | E21: =Source!I30 -> 24.465 | F21: =Source!U24
A22: 1.2 | B22: =Source!E32 -> 1,2 | C22: =Source!G32 -> Прокат листовой из стали С235, С245 для строительных стальных конструкций, толщина более 3 мм | D22: т | E22: =Source!I32 -> 1.0395 | F22: =Source!U24
A23: 1.3 | B23: =Source!E34 -> 1,3 | C23: =Source!G34 -> Шпилька резьбовая, стальная, оцинкованная, с заостренным концом, в комплекте с шайбой и гайкой, М16x190 мм | D23: шт. | E23: =Source!I34 -> 1470 | F23: =Source!U24
A24: 2 | B24: =Source!E36 -> 2 | C24: =Source!G36 -> Огрунтовка металлических поверхностей грунтовкой ГФ-021 за один раз | D24: 100 м2 | E24: =Source!I36 -> 7.6375005 | F24: =Source!U24 | G24: ="=(70,9*"&"26,3+"&"38,5*"&"26,3+"&"109,3*"&"33+"&"7,4*"&"33+"&"7,2*"&"32,1+"&"2,7*"&"32,1+"&"6,9*"&"33)/"&"1000/"&"100*"&"105" -> =(70,9*26,3+38,5*26,3+109,3*33+7,4*33+7,2*32,1+2,7*32,1+6,9*33)/1000/100*105
A25: 2.1 | B25: =Source!E38 -> 2,1 | C25: =Source!G38 -> Грунтовка глифталевая, типа ГФ-021 | D25: т | E25: =Source!I38 -> 0.068738 | F25: =Source!U24
A26: =CONCATENATE("Раздел: ", Source!G71) -> Раздел: Усиление внутренних и наружных стен в зоне расширяемых проемов в подвале и в надземной части здания. Рама РС-2, 22 шт. (КР-5,6) | AF26: =CONCATENATE("Раздел: ", Source!G71) -> Раздел: Усиление внутренних и наружных стен в зоне расширяемых проемов в подвале и в надземной части здания. Рама РС-2, 22 шт. (КР-5,6)
A27: 3 | B27: =Source!E75 -> 3 | C27: =Source!G75 -> Усиление кирпичных стен металлическим каркасом | D27: 1 Т | E27: =Source!I75 -> 4.7322 | F27: =Source!U71 | G27: ="=(67,6+"&"106,3+"&"4,2+"&"6,9+"&"7,2+"&"11,3+"&"0,9+"&"1,4+"&"9,3)/"&"1000*"&"22" -> =(67,6+106,3+4,2+6,9+7,2+11,3+0,9+1,4+9,3)/1000*22
A28: 3.1 | B28: =Source!E77 -> 3,1 | C28: =Source!G77 -> Швеллер №№ 12-40, из стали углеродистой обыкновенного качества, спокойной | D28: т | E28: =Source!I77 -> 1.4872 | F28: =Source!U71
A29: 3.2 | B29: =Source!E79 -> 3,2 | C29: =Source!G79 -> Уголок равнополочный, для строительных стальных конструкций, ширина полки более 70 мм, сталь С235, С245 | D29: т | E29: =Source!I79 -> 2.5828 | F29: =Source!U71
A30: 3.3 | B30: =Source!E81 -> 3,3 | C30: =Source!G81 -> Прокат листовой из стали С235, С245 для строительных стальных конструкций, толщина более 3 мм | D30: т | E30: =Source!I81 -> 0.6622 | F30: =Source!U71
A31: 3.4 | B31: =Source!E83 -> 3,4 | C31: =Source!G83 -> Шпилька резьбовая, стальная, оцинкованная, с заостренным концом, в комплекте с шайбой и гайкой, М16x190 мм | D31: шт. | E31: =Source!I83 -> 176 | F31: =Source!U71
A32: 3.5 | B32: =Source!E85 -> 3,5 | C32: =Source!G85 -> Анкер-болт забивной, распорный, стальной, оцинкованный, с широкой шайбой M12х110 | D32: 100 шт. | E32: =Source!I85 -> 0.88 | F32: =Source!U71
A33: 4 | B33: =Source!E87 -> 4 | C33: =Source!G87 -> Огрунтовка металлических поверхностей грунтовкой ГФ-021 за один раз | D33: 100 м2 | E33: =Source!I87 -> 1.4266978 | F33: =Source!U71 | G33: ="=(67,6*"&"26,1+"&"106,3*"&"33+"&"4,2*"&"33+"&"6,9*"&"33+"&"7,2*"&"32,1+"&"11,3*"&"21,5+"&"0,9*"&"32,1+"&"1,4*"&"32,1+"&"9,3*"&"32,1)/"&"1000/"&"100*"&"22" -> =(67,6*26,1+106,3*33+4,2*33+6,9*33+7,2*32,1+11,3*21,5+0,9*32,1+1,4*32,1+9,3*32,1)/1000/100*22
A34: 4.1 | B34: =Source!E89 -> 4,1 | C34: =Source!G89 -> Грунтовка глифталевая, типа ГФ-021 | D34: т | E34: =Source!I89 -> 0.01284 | F34: =Source!U71
A35: =CONCATENATE("Раздел: ", Source!G122) -> Раздел: Усиление внутренних и наружных стен в зоне расширяемых проемов в подвале и в надземной части здания. Рама РС-3, 5 шт. (КР-5,6) | AF35: =CONCATENATE("Раздел: ", Source!G122) -> Раздел: Усиление внутренних и наружных стен в зоне расширяемых проемов в подвале и в надземной части здания. Рама РС-3, 5 шт. (КР-5,6)
A36: 5 | B36: =Source!E126 -> 5 | C36: =Source!G126 -> Усиление кирпичных стен металлическим каркасом | D36: 1 Т | E36: =Source!I126 -> 1.473 | F36: =Source!U122 | G36: ="=(146,3+"&"108,5+"&"15,7+"&"7,2+"&"16,9)/"&"1000*"&"5" -> =(146,3+108,5+15,7+7,2+16,9)/1000*5
A37: 5.1 | B37: =Source!E128 -> 5,1 | C37: =Source!G128 -> Уголок равнополочный, для строительных стальных конструкций, ширина полки более 70 мм, сталь С235, С245 | D37: т | E37: =Source!I128 -> 1.3525 | F37: =Source!U122
A38: 5.2 | B38: =Source!E130 -> 5,2 | C38: =Source!G130 -> Прокат листовой из стали С235, С245 для строительных стальных конструкций, толщина более 3 мм | D38: т | E38: =Source!I130 -> 0.1205 | F38: =Source!U122
A39: 5.3 | B39: =Source!E132 -> 5,3 | C39: =Source!G132 -> Шпилька резьбовая, стальная, оцинкованная, с заостренным концом, в комплекте с шайбой и гайкой, М16x190 мм | D39: шт. | E39: =Source!I132 -> 90 | F39: =Source!U122
A40: 6 | B40: =Source!E134 -> 6 | C40: =Source!G134 -> Огрунтовка металлических поверхностей грунтовкой ГФ-021 за один раз | D40: 100 м2 | E40: =Source!I134 -> 0.435995 | F40: =Source!U122 | G40: ="=(146,3*"&"26,3+"&"108,5*"&"33+"&"15,7*"&"33+"&"7,2*"&"32,1+"&"16,9*"&"32,1)/"&"1000/"&"100*"&"5" -> =(146,3*26,3+108,5*33+15,7*33+7,2*32,1+16,9*32,1)/1000/100*5
A41: 6.1 | B41: =Source!E136 -> 6,1 | C41: =Source!G136 -> Грунтовка глифталевая, типа ГФ-021 | D41: т | E41: =Source!I136 -> 0.003924 | F41: =Source!U122
A42: =CONCATENATE("Раздел: ", Source!G169) -> Раздел: Усиление внутренних и наружных стен в зоне расширяемых проемов в подвале и в надземной части здания. Рама РС-6, 2 шт. (КР-5,6) | AF42: =CONCATENATE("Раздел: ", Source!G169) -> Раздел: Усиление внутренних и наружных стен в зоне расширяемых проемов в подвале и в надземной части здания. Рама РС-6, 2 шт. (КР-5,6)
A43: 7 | B43: =Source!E173 -> 7 | C43: =Source!G173 -> Усиление кирпичных стен металлическим каркасом | D43: 1 Т | E43: =Source!I173 -> 0.676 | F43: =Source!U169 | G43: ="=(182,6+"&"50,5+"&"55,4+"&"31,4+"&"3,6+"&"14,5)/"&"1000*"&"2" -> =(182,6+50,5+55,4+31,4+3,6+14,5)/1000*2
A44: 7.1 | B44: =Source!E175 -> 7,1 | C44: =Source!G175 -> Уголок равнополочный, для строительных стальных конструкций, ширина полки более 70 мм, сталь С235, С245 | D44: т | E44: =Source!I175 -> 0.5388 | F44: =Source!U169
A45: 7.2 | B45: =Source!E177 -> 7,2 | C45: =Source!G177 -> Профили стальные электросварные квадратного сечения трубчатые, размер стороны 100 мм, толщина стенки от 3 до 6 мм | D45: т | E45: =Source!I177 -> 0.101 | F45: =Source!U169
A46: 7.3 | B46: =Source!E179 -> 7,3 | C46: =Source!G179 -> Прокат листовой из стали С235, С245 для строительных стальных конструкций, толщина более 3 мм | D46: т | E46: =Source!I179 -> 0.0362 | F46: =Source!U169
A47: 7.4 | B47: =Source!E181 -> 7,4 | C47: =Source!G181 -> Шпилька резьбовая, стальная, оцинкованная, с заостренным концом, в комплекте с шайбой и гайкой, М16x190 мм | D47: шт. | E47: =Source!I181 -> 36 | F47: =Source!U169
A48: 8 | B48: =Source!E183 -> 8 | C48: =Source!G183 -> Огрунтовка металлических поверхностей грунтовкой ГФ-021 за один раз | D48: 100 м2 | E48: =Source!I183 -> 0.1817218 | F48: =Source!U169 | G48: ="=(182,6*"&"26,3+"&"50,5*"&"16,6+"&"55,4*"&"33+"&"31,4*"&"33+"&"3,6*"&"32,1+"&"14,5*"&"32,1)/"&"1000/"&"100*"&"2" -> =(182,6*26,3+50,5*16,6+55,4*33+31,4*33+3,6*32,1+14,5*32,1)/1000/100*2
A49: 8.1 | B49: =Source!E185 -> 8,1 | C49: =Source!G185 -> Грунтовка глифталевая, типа ГФ-021 | D49: т | E49: =Source!I185 -> 0.001635 | F49: =Source!U169
A50: =CONCATENATE("Раздел: ", Source!G218) -> Раздел: Локальный ремонт межпанельных стыков в наружных и внутренних стенах (КР-22)
A51: 9 | B51: =Source!E222 -> 9 | C51: =Source!G222 -> Заполнение бетоном отдельных мест в перекрытиях | D51: 1 м3 | E51: =Source!I222 -> 7.61 | F51: =Source!U218 | G51: =Source!I222 -> 7.61
A52: 9.1 | B52: =Source!E224 -> 9,1 | C52: =Source!G224 -> Смесь сухая, цементная с заполнителем из пенополистирола и химическими добавками, легкая, паропроницаемая, плотность раствора 300 кг/м3, прочность на сжатие не менее 0,5 МПа, коэффициент теплопроводности 0,07 Вт/м х К, температура эксплуатации от -40 до +60°С, для заполнения межпанельных швов, колодезной кладки и других пустот в основаниях стен, в качестве тепло-звукоизоляции | D52: м3 | E52: =Source!I224 -> 7.7622 | F52: =Source!U218
A53: 10 | B53: =Source!E226 -> 10 | C53: =Source!G226 -> Заполнение вертикальных швов стеновых панелей цементным раствором | D53: 100 м шва | E53: =Source!I226 -> 76.1 | F53: =Source!U218 | G53: ="=7610/"&"100" -> =7610/100
A54: 10.1 | B54: =Source!E228 -> 10,1 | C54: =Source!G228 -> Раствор цементный, марка М200 | D54: м3 | E54: =Source!I228 -> 76.1 | F54: =Source!U218
A55: 11 | B55: =Source!E230 -> 11 | C55: =Source!G230 -> Заполнение вертикальных швов стеновых панелей упругими прокладками | D55: 100 м шва | E55: =Source!I230 -> 76.1 | F55: =Source!U218 | G55: ="=7610/"&"100" -> =7610/100
A56: 11.1 | B56: =Source!E232 -> 11,1 | C56: =Source!G232 -> Прокладки из вспененного полиэтилена уплотнительные и теплоизоляционные сплошного сечения, наружный диаметр от 45 до 55 мм | D56: м | E56: =Source!I232 -> 7990.5 | F56: =Source!U218
A57: =CONCATENATE("Раздел: ", Source!G265) -> Раздел: Установка металлического ограждения по периметру кровли (КР-22,29)
A58: 12 | B58: =Source!E269 -> 12 | C58: =Source!G269 -> Ограждение кровель перилами | D58: 100 м ограждения | E58: =Source!I269 -> 4.07 | F58: =Source!U265 | G58: ="=407/"&"100" -> =407/100
A59: 12.1 | B59: =Source!E271 -> 12,1 | C59: =Source!G271 -> Ограждения из прокатных и гнутых профилей полосовой и круглой стали | D59: т | E59: =Source!I271 -> 8.3516 | F59: =Source!U265
A60: 12.2 | B60: =Source!E273 -> 12,2 | C60: =Source!G273 -> Шпилька резьбовая, стальная, оцинкованная, с заостренным концом, в комплекте с шайбой и гайкой, М8х110 мм | D60: шт. | E60: =Source!I273 -> 1628 | F60: =Source!U265
A61: 12.3 | B61: =Source!E275 -> 12,3 | C61: =Source!G275 -> Состав на основе полиэстеровой смолы для анкеров химических, в картридже инъекционном 410 мл | D61: шт. | E61: =Source!I275 -> 32.56 | F61: =Source!U265
A62: =CONCATENATE("Раздел: ", Source!G308) -> Раздел: Замена плит перекрытий. Устройство монолитных ж/б участков (КР-7...11)
A63: 13 | B63: =Source!E312 -> 13 | C63: =Source!G312 -> Монтаж несъемной опалубки сталебетонных перекрытий из стального профилированного настила при ширине листа 1000 мм | D63: 100 м2 | E63: =Source!I312 -> 9.358 | F63: =Source!U308 | G63: ="=935,8/"&"100" -> =935,8/100
A64: 13.1 | B64: =Source!E314 -> 13,1 | C64: =Source!G314 -> Профили стальные оцинкованные листовые гнутые для сталебетонных перекрытий, типа СКН50Z-600, толщина 0,8 мм | D64: м2 | E64: =Source!I314 -> 935.8 | F64: =Source!U308
A65: 13.2 | B65: =Source!E318 -> 13,3 | C65: =Source!G318 -> Каркасы и сетки арматурные плоские, собранные и сваренные (связанные) в арматурные изделия, класс Вр-1, диаметр 5 мм | D65: т | E65: =Source!I318 -> 2.8823 | F65: =Source!U308
A66: 13.3 | B66: =Source!E320 -> 13,4 | C66: =Source!G320 -> Анкер-шпилька распорный, стандартный, с шестигранной гайкой и шайбой, из горячеоцинкованной стали, для использования в бетоне без трещин, диаметр 16 мм, длина 102 мм, толщина прикрепляемой детали 5 мм | D66: шт. | E66: =Source!I320 -> 628 | F66: =Source!U308
A67: 14 | B67: =Source!E322 -> 14 | C67: =Source!G322 -> Устройство перекрытий по стальным балкам и монолитные участки при сборном железобетонном перекрытии площадью до 5 м2 приведенной толщиной до 100 мм | D67: 100 м3 в деле | E67: =Source!I322 -> 0.3847 | F67: =Source!U308 | G67: ="=38,47/"&"100" -> =38,47/100
A68: 14.1 | B68: =Source!E324 -> 14,1 | C68: =Source!G324 -> Арматурные заготовки (стержни, хомуты и т.п.), не собранные в каркасы или сетки, арматурная сталь периодического профиля, класс А-III, диаметр от 16 до 18 мм | D68: т | E68: =Source!I324 -> 0.9373 | F68: =Source!U308
A69: 14.2 | B69: =Source!E326 -> 14,2 | C69: =Source!G326 -> Арматурные заготовки (стержни, хомуты и т.п.), не собранные в каркасы или сетки, арматурная сталь периодического профиля, класс А-III, диаметр от 12 до 14 мм | D69: т | E69: =Source!I326 -> 3.2673 | F69: =Source!U308
A70: 14.3 | B70: =Source!E328 -> 14,3 | C70: =Source!G328 -> Арматурные заготовки (стержни, хомуты и т.п.), не собранные в каркасы или сетки, углеродистая сталь общего назначения и арматурная сталь гладкая, класс А-I, диаметр от 6 до 7 мм | D70: т | E70: =Source!I328 -> 0.289 | F70: =Source!U308
A71: 14.4 | B71: =Source!E330 -> 14,4 | C71: =Source!G330 -> Смесь бетонная тяжелого бетона БСТ на гранитном щебне, крупность заполнителя от 5 до 20 мм, класс прочности В25 (М350), П3, F150, W6 | D71: м3 | E71: =Source!I330 -> 39.04705 | F71: =Source!U308
A72: 14.5 | B72: =Source!E332 -> 14,5 | C72: =Source!G332 -> Щит деревянный для фундаментов, колонн, балок, перекрытий, стен, перегородок и других конструкций из досок, толщина 25 мм | D72: м2 | E72: =Source!I332 -> -58.78216 | F72: =Source!U308
A73: 15 | B73: =Source!E334 -> 15 | C73: =Source!G334 -> Устройство тепло и звукоизоляции засыпной керамзитовой | D73: 1 м3 изоляции | E73: =Source!I334 -> 42.7 | F73: =Source!U308 | G73: =Source!I334 -> 42.7
A74: =CONCATENATE("Раздел: ", Source!G367) -> Раздел: Замена плит перекрытий. Устройство металлических балок (КР-7...11)
A75: 16 | B75: =Source!E371 -> 16 | C75: =Source!G371 -> Монтаж стальных балок и ригелей перекрытий, покрытий и под установку оборудования в зданиях высотой до 30 м | D75: 1 т конструкций | E75: =Source!I371 -> 58.4933 | F75: =Source!U367 | G75: ="=(8827,7+"&"37310,1+"&"1129,6+"&"3440,6+"&"790,1+"&"6995,2)/"&"1000" -> =(8827,7+37310,1+1129,6+3440,6+790,1+6995,2)/1000
A76: 16.1 | B76: =Source!E373 -> 16,1 | C76: =Source!G373 -> Швеллер №№ 12-40, из стали углеродистой обыкновенного качества, спокойной | D76: т | E76: =Source!I373 -> 50.708 | F76: =Source!U367
A77: 16.2 | B77: =Source!E375 -> 16,2 | C77: =Source!G375 -> Уголок равнополочный, для строительных стальных конструкций, ширина полки более 70 мм, сталь С235, С245 | D77: т | E77: =Source!I375 -> 0.7901 | F77: =Source!U367
A78: 16.3 | B78: =Source!E377 -> 16,3 | C78: =Source!G377 -> Уголок неравнополочный, для строительных стальных конструкций, ширина большей полки более 80 мм, сталь С235, С245 | D78: т | E78: =Source!I377 -> 6.9952 | F78: =Source!U367
A79: 17 | B79: =Source!E379 -> 17 | C79: =Source!G379 -> Установка закладных деталей весом до 4 кг | D79: 1 Т | E79: =Source!I379 -> 1.092 | F79: =Source!U367 | G79: ="=1092/"&"1000" -> =1092/1000
A80: 17.1 | B80: =Source!E381 -> 17,1 | C80: =Source!G381 -> Прокат листовой из стали С235, С245 для строительных стальных конструкций, толщина более 3 мм | D80: т | E80: =Source!I381 -> 1.092 | F80: =Source!U367
A81: 18 | B81: =Source!E383 -> 18 | C81: =Source!G383 -> Огрунтовка металлических поверхностей грунтовкой ГФ-021 за один раз | D81: 100 м2 | E81: =Source!I383 -> 19.362251 | F81: =Source!U367 | G81: ="=(8,8277*"&"36,6+"&"37,3101*"&"33,2+"&"1,1296*"&"35+"&"3,4406*"&"26,1+"&"0,7901*"&"33+"&"6,9952*"&"26,3+"&"1,092*"&"32,1)/"&"100" -> =(8,8277*36,6+37,3101*33,2+1,1296*35+3,4406*26,1+0,7901*33+6,9952*26,3+1,092*32,1)/100
A82: 18.1 | B82: =Source!E385 -> 18,1 | C82: =Source!G385 -> Грунтовка глифталевая, типа ГФ-021 | D82: т | E82: =Source!I385 -> 0.17426 | F82: =Source!U367
A83: 19 | B83: =Source!E387 -> 19 | C83: =Source!G387 -> Окраска огрунтованных металлических поверхностей эмалями ПФ-115 | D83: 100 м2 | E83: =Source!I387 -> 19.362251 | F83: =Source!U367 | G83: ="=(8,8277*"&"36,6+"&"37,3101*"&"33,2+"&"1,1296*"&"35+"&"3,4406*"&"26,1+"&"0,7901*"&"33+"&"6,9952*"&"26,3+"&"1,092*"&"32,1)/"&"100" -> =(8,8277*36,6+37,3101*33,2+1,1296*35+3,4406*26,1+0,7901*33+6,9952*26,3+1,092*32,1)/100
A84: 20 | B84: =Source!E389 -> 20 | C84: =Source!G389 -> Устройство огнезащитного покрытия несущих металлоконструкций покрытий, балок перекрытий и ферм терморасширяющимися красками на органической основе с пределом огнестойкости 0,75 часа | D84: 100 м2 окрашенной поверхности | E84: =Source!I389 -> 19.362251 | F84: =Source!U367 | G84: ="=(8,8277*"&"36,6+"&"37,3101*"&"33,2+"&"1,1296*"&"35+"&"3,4406*"&"26,1+"&"0,7901*"&"33+"&"6,9952*"&"26,3+"&"1,092*"&"32,1)/"&"100" -> =(8,8277*36,6+37,3101*33,2+1,1296*35+3,4406*26,1+0,7901*33+6,9952*26,3+1,092*32,1)/100
A85: 20.1 | B85: =Source!E391 -> 20,1 | C85: =Source!G391 -> Краска огнезащитная терморасширяющаяся на органической основе для защиты несущих металлоконструкций | D85: т | E85: =Source!I391 -> 3.485205 | F85: =Source!U367
A86: =CONCATENATE("Раздел: ", Source!G424) -> Раздел: Замена плит перекрытий. Устройство раскрепления (КР-7...11)
A87: 21 | B87: =Source!E428 -> 21 | C87: =Source!G428 -> Монтаж мелких конструкций из стали различного профиля массой до 20 кг | D87: 1 Т | E87: =Source!I428 -> 2.52055 | F87: =Source!U424 | G87: ="=(631+"&"1363,3+"&"85,25+"&"441)/"&"1000" -> =(631+1363,3+85,25+441)/1000
A88: 21.1 | B88: =Source!E430 -> 21,1 | C88: =Source!G430 -> Прокат листовой из стали С235, С245 для строительных стальных конструкций, толщина более 3 мм | D88: т | E88: =Source!I430 -> 1.9943 | F88: =Source!U424
A89: 21.2 | B89: =Source!E432 -> 21,2 | C89: =Source!G432 -> Арматурные заготовки (стержни, хомуты и т.п.), не собранные в каркасы или сетки, арматурная сталь периодического профиля, класс А-III, диаметр от 12 до 14 мм | D89: т | E89: =Source!I432 -> 0.08525 | F89: =Source!U424
A90: 21.3 | B90: =Source!E434 -> 21,3 | C90: =Source!G434 -> Уголок равнополочный, для строительных стальных конструкций, ширина полки более 70 мм, сталь С235, С245 | D90: т | E90: =Source!I434 -> 0.441 | F90: =Source!U424
A91: 21.4 | B91: =Source!E436 -> 21,4 | C91: =Source!G436 -> Шпилька резьбовая, стальная, оцинкованная, с заостренным концом, в комплекте с шайбой и гайкой, М16x190 мм | D91: шт. | E91: =Source!I436 -> 94 | F91: =Source!U424
A92: =CONCATENATE("Раздел: ", Source!G469) -> Раздел: Замена лестницы спуска в подвал м/о 3-5/Ж-Е (КР-12)
A93: 22 | B93: =Source!E473 -> 22 | C93: =Source!G473 -> Кладка стен внутренних при высоте этажа до 4 м | D93: 1 м3 кладки | E93: =Source!I473 -> 7.9 | F93: =Source!U469 | G93: =Source!I473 -> 7.9
A94: 22.1 | B94: =Source!E475 -> 22,1 | C94: =Source!G475 -> Кирпич керамический рядовой, полнотелый, размер 250х120х65 мм, марка 150 | D94: 1000 шт. | E94: =Source!I475 -> 3.002 | F94: =Source!U469
A95: 22.2 | B95: =Source!E477 -> 22,2 | C95: =Source!G477 -> Раствор цементный, марка М150 | D95: м3 | E95: =Source!I477 -> 1.896 | F95: =Source!U469
A96: 23 | B96: =Source!E479 -> 23 | C96: =Source!G479 -> Устройство перекрытий безбалочных толщиной до 200 мм на высоте от опорной площади до 6 м | D96: 100 м3 в деле | E96: =Source!I479 -> 0.034 | F96: =Source!U469 | G96: ="=3,4/"&"100" -> =3,4/100
A97: 23.1 | B97: =Source!E481 -> 23,1 | C97: =Source!G481 -> Арматурные заготовки (стержни, хомуты и т.п.), не собранные в каркасы или сетки, арматурная сталь периодического профиля, класс А-III, диаметр от 16 до 18 мм | D97: т | E97: =Source!I481 -> 0.0294 | F97: =Source!U469
A98: 23.2 | B98: =Source!E483 -> 23,2 | C98: =Source!G483 -> Арматурные заготовки (стержни, хомуты и т.п.), не собранные в каркасы или сетки, арматурная сталь периодического профиля, класс А-III, диаметр от 12 до 14 мм | D98: т | E98: =Source!I483 -> 0.33576 | F98: =Source!U469
A99: 23.3 | B99: =Source!E485 -> 23,3 | C99: =Source!G485 -> Арматурные заготовки (стержни, хомуты и т.п.), не собранные в каркасы или сетки, арматурная сталь периодического профиля, класс А-III, диаметр 8 мм | D99: т | E99: =Source!I485 -> 0.09071 | F99: =Source!U469
A100: 23.4 | B100: =Source!E487 -> 23,4 | C100: =Source!G487 -> Смесь бетонная тяжелого бетона БСТ на гранитном щебне, крупность заполнителя от 5 до 20 мм, класс прочности В25 (М350), П3, F150, W6 | D100: м3 | E100: =Source!I487 -> 3.451 | F100: =Source!U469
A101: =CONCATENATE("Раздел: ", Source!G520) -> Раздел: Локальный ремонт рустов плит перекрытий (КР-22)
A102: 24 | B102: =Source!E526 -> 24 | C102: =Source!G526 -> Заполнение бетоном отдельных мест в перекрытиях | D102: 1 м3 | E102: =Source!I526 -> 60.88 | F102: =Source!U520 | G102: =Source!I526 -> 60.88
A103: 24.1 | B103: =Source!E528 -> 24,1 | C103: =Source!G528 -> Раствор цементный, марка М200 | D103: м3 | E103: =Source!I528 -> 62.0976 | F103: =Source!U520
A104: 25 | B104: =Source!E530 -> 25 | C104: =Source!G530 -> Конопатка швов плит перекрытий просмоленной паклей с частичной разбивкой швов, заделкой раствором толщиной 20 мм | D104: 100 м | E104: =Source!I530 -> 76.1 | F104: =Source!U520 | G104: ="=7610/"&"100" -> =7610/100
A105: 25.1 | B105: =Source!E532 -> 25,1 | C105: =Source!G532 -> Пакля пропитанная | D105: кг | E105: =Source!I532 -> -1674.2 | F105: =Source!U520
A106: 25.2 | B106: =Source!E534 -> 25,2 | C106: =Source!G534 -> Прокладки из вспененного полиэтилена уплотнительные и теплоизоляционные сплошного сечения, наружный диаметр от 45 до 55 мм | D106: м | E106: =Source!I534 -> 7610 | F106: =Source!U520
A107: 25.3 | B107: =Source!E536 -> 25,3 | C107: =Source!G536 -> Раствор цементный, марка М75 | D107: м3 | E107: =Source!I536 -> -3.044 | F107: =Source!U520
A108: 25.4 | B108: =Source!E538 -> 25,4 | C108: =Source!G538 -> Смесь сухая, цементная с заполнителем из пенополистирола и химическими добавками, легкая, паропроницаемая, плотность раствора 300 кг/м3, прочность на сжатие не менее 0,5 МПа, коэффициент теплопроводности 0,07 Вт/м х К, температура эксплуатации от -40 до +60°С, для заполнения межпанельных швов, колодезной кладки и других пустот в основаниях стен, в качестве тепло-звукоизоляции | D108: м3 | E108: =Source!I538 -> 10.65 | F108: =Source!U520
...

Sheet Source
A1: 0 | B1: Smeta.RU (495) 974-1589 | D1: _PS_ | F1: 0 | G1: 0 | H1: 0 | I1: Smeta.RU | K1: 1 | L1: 74562 | M1: 10 | N1: 11 | O1: 14 | P1: 0 | Q1: 0
A4: 1 | B4: 1 | C4: -1 | G4: Капитальный ремонт здания Государственного бюджетного общеобразовательного учреждения города Москвы «Школа № 236» по адресу: г. Москва, ул. Клязьминская, д. 7, к. 4. I этап | EC4: 0
A12: 1 | B12: 1597 | C12: 0 | D12: =ROW(A1557) -> 1557 | E12: 0 | F12: 02-01-02 | G12: 02-01-02 Конструктивные решения | I12: 0 | J12: 2024-00272-01-0-КР.ВОР | K12: 0 | L12: 0 | M12: 4098 | O12: 0 | P12: 0 | Q12: 0 | R12: 0 | S12: 0 | T12: 1 | V12: 0 | AB12: Лукьянова А.Л. | BB12: 0 | BH12: Сметные нормы списания | BI12: Коды ОКП для ТСН-2001 МГЭ Дополнение 79 | BJ12: 1 | BK12: 1 | BL12: 0 | BM12: 0 | BN12: 1 | BO12: 0 | BP12: 6 | BQ12: 2 | BR12: 1 | BS12: 1 | BT12: 0 | BU12: 0 | BV12: 0 | BW12: 0 | BX12: 0 | BY12: ТСН-2001 (МГЭ) Доп 79 - Ремонт | BZ12: Типовой расчет для ТСН-2001 МГЭ, Дополнение 79, ремонт | CA12: Территориальные сметные нормативы для Москвы ТСН-2001 (МГЭ), дополнение 79 | CB12: Территориальные сметные нормативы для Москвы ТСН-2001 (МГЭ), дополнение 79 | CC12: Территориальные сметные нормативы для Москвы ТСН-2001 (МГЭ), дополнение 79 | CD12: Территориальные сметные нормативы для Москвы ТСН-2001 (МГЭ), дополнение 79 | CE12: Поправки для ТСН-2001 от 03.10.2025 г. доп.79 | CF12: 0 | CG12: 0 | CH12: 8200 | CK12: 79 | CQ12: Территориальные сметные нормативы для Москвы (ТСН-2001) | CR12: ТЕР | CS12: 41660 | CT12: 1 | CU12: 79 | CY12: 0 | EC12: 0
A15: 15 | B15: 1
A18: 52 | B18: =B1557 -> 1597 | C18: =C1557 -> 1 | D18: =D1557 -> 12 | E18: =E1557 -> 0 | F18: =F1557 -> 02-01-02 | G18: =G1557 -> 02-01-02 Конструктивные решения | O18: =O1557 -> 3772771 | P18: =P1557 -> 3378093.4 | Q18: =Q1557 -> 32771.56 | R18: =R1557 -> 2895.88 | S18: =S1557 -> 361906.04 | T18: =T1557 -> 0 | U18: =U1557 -> 27400.046 | V18: =V1557 -> 0 | ... GX18: =GX1557 -> 0
A20: 3 | B20: 1 | D20: =ROW(A1527) -> 1527 | G20: Конструктивные решения | I20: 0 | J20: 2024-00272-01-0-КР.ВОР | K20: -1 | L20: 02-01-02 | S20: 0 | T20: 0 | V20: 0 | AB20: Лукьянова А.Л. | BX20: 0 | CF20: 0 | CG20: 0
A22: 52 | B22: =B1527 -> 1 | C22: =C1527 -> 3 | D22: =D1527 -> 20 | E22: =E1527 -> 0 | F22: =F1527 | G22: =G1527 -> Конструктивные решения | O22: =O1527 -> 3772771 | P22: =P1527 -> 3378093.4 | Q22: =Q1527 -> 32771.56 | R22: =R1527 -> 2895.88 | S22: =S1527 -> 361906.04 | T22: =T1527 -> 0 | U22: =U1527 -> 27400.046 | V22: =V1527 -> 0 | ... GX22: =GX1527 -> 0
A24: 4 | B24: 1 | D24: =ROW(A41) -> 41 | G24: Усиление внутренних и наружных стен в зоне расширяемых проемов в подвале и в надземной части здания. Рама РС-1, 105 шт. (КР-5,6) | I24: 0 | K24: -1 | S24: 0 | T24: 0 | V24: 0 | BX24: 0 | CJ24: 0
A26: 52 | B26: =B41 -> 1 | C26: =C41 -> 4 | D26: =D41 -> 24 | E26: =E41 -> 0 | F26: =F41 | G26: =G41 -> Усиление внутренних и наружных стен в зоне расширяемых проемов в подвале и в надземной части здания. Рама РС-1, 105 шт. (КР-5,6) | O26: =O41 -> 370105.87 | P26: =P41 -> 294096.01 | Q26: =Q41 -> 1203.04 | R26: =R41 -> 69.31 | S26: =S41 -> 74806.82 | T26: =T41 -> 0 | U26: =U41 -> 5983.2872 | V26: =V41 -> 0 | ... GX26: =GX41 -> 0
A28: 17 | B28: 1 | C28: =ROW(SmtRes!A3) -> 3 | D28: =ROW(EtalonRes!A8) -> 8 | E28: 1 | F28: 6.53-25-1 | G28: Усиление кирпичных стен металлическим каркасом | H28: 1 Т | I28: =ROUND((70.9+38.5+109.3+7.4+7.2+2.7+6.9)/1000*105,9) -> 25.5045 | J28: 0 | K28: =ROUND((70.9+38.5+109.3+7.4+7.2+2.7+6.9)/1000*105,9) -> 25.5045 | O28: =ROUND(CP28,2) -> 75884.89 | P28: =ROUND((ROUND((AC28*AW28*I28),2)*BC28),2) -> 734.47 | Q28: =(ROUND((ROUND((((ET28*1.1))*AV28*I28),2)*BB28),2)+ROUND((ROUND(((AE28-((EU28*1.1)))*AV28*I28),2)*BS28),2)) -> 1059.8 | R28: =ROUND((ROUND((AE28*AV28*I28),2)*BS28),2) -> 66.68 | S28: =ROUND((ROUND((AF28*AV28*I28),2)*BA28),2) -> 74090.62 | T28: =ROUND(CU28*I28,2) -> 0 | U28: =CV28*I28 -> 5931.9849 | V28: =CW28*I28 -> 0 | W28: =ROUND(CX28*I28,2) -> 0 | X28: =ROUND(CY28,2) -> 68224.72 | Y28: =ROUND(CZ28,2) -> 38561.8 | AA28: 56481265 | AB28: =ROUND((AC28+AD28+AF28),6) -> 2843.024 | AC28: =ROUND((ES28),6) -> 28.74 | AD28: =ROUND(((((ET28*1.1))-((EU28*1.1)))+AE28),6) -> 39.688 | AE28: =ROUND(((EU28*1.1)),6) -> 2.497 | AF28: =ROUND(((EV28*1.1)),6) -> 2774.596 | AG28: =ROUND((AP28),6) -> 0 | AH28: =((EW28*1.1)) -> 222.145 | AI28: =((EX28*1.1)) -> 0 | AJ28: =(AS28) -> 0 | AK28: 2587.18 | AL28: 28.74 | AM28: 36.08 | AN28: 2.27 | AO28: 2522.36 | AP28: 0 | AQ28: 201.95 | AR28: 0 | AS28: 0 | AT28: 92 | AU28: 52 | AV28: 1.047 | AW28: 1.002 | AZ28: 1 | BA28: 1 | BB28: 1 | BC28: 1 | BH28: 0 | BI28: 1 | BJ28: ТСН-2001.6 Доп. 79, Сб. 53, т. 25, поз. 1 | BM28: 90 | BN28: 0 | BO28: 6.53-25-1 | BP28: 1 | BQ28: 60 | BR28: 0 | BS28: 1 | BT28: 1 | BU28: 1 | BV28: 1 | BW28: 1 | BX28: 1 | BZ28: 92 | CA28: 52 | CE28: 30 | CF28: 0 | CG28: 0 | CM28: 0 | CO28: 0 | CP28: =(P28+Q28+S28) -> 75884.89 | CQ28: =ROUND((ROUND((AC28*AW28*1),2)*BC28),2) -> 28.8 | CR28: =(ROUND((ROUND((((ET28*1.1))*AV28*1),2)*BB28),2)+ROUND((ROUND(((AE28-((EU28*1.1)))*AV28*1),2)*BS28),2)) -> 41.55 | CS28: =ROUND((ROUND((AE28*AV28*1),2)*BS28),2) -> 2.61 | CT28: =ROUND((ROUND((AF28*AV28*1),2)*BA28),2) -> 2905 | CU28: =AG28 -> 0 | CV28: =(AH28*AV28) -> 232.58581 | CW28: =AI28 -> 0 | CX28: =AJ28 -> 0 | CY28: =(((S28+R28)*AT28)/100) -> 68224.716 | CZ28: =(((S28+R28)*AU28)/100) -> 38561.796 | DE28: *1,1 | DF28: *1,1 | DG28: *1,1 | DI28: *1,1 | DJ28: *1,1 | DN28: 0 | DO28: 0 | DP28: 1 | DQ28: 1 | DU28: 1013 | DV28: 1 Т | DW28: 1 Т | DX28: 1 | EE28: 55586525 | EF28: 60 | EG28: Ремонтно-строительные работы | EH28: 0 | EJ28: 1 | EK28: 90 | EL28: ТСН-2001.6-53. Стены | EM28: ТСН-2001.6-53-1 | EO28: Поправка: Гл.12.Прил.8.п.8. 5_12.00.01.11.003 | EQ28: 0 | ER28: 2587.18 | ES28: 28.74 | ET28: 36.08 | EU28: 2.27 | EV28: 2522.36 | EW28: 201.95 | EX28: 0 | EY28: 0 | FQ28: 0 | FR28: 0 | FS28: 0 | FX28: 92 | FY28: 52 | GD28: 1 | GF28: -811884377 | GG28: 2 | GH28: 1 | GI28: 2 | GJ28: 0 | GK28: 0 | GL28: =ROUND(IF(AND(BH28=3,BI28=3,FS28<>0),P28,0),2) -> 0 | GM28: =ROUND(O28+X28+Y28,2)+GX28 -> 182671.41 | GN28: =IF(OR(BI28=0,BI28=1),GM28-GX28,0) -> 182671.41 | GO28: =IF(BI28=2,GM28-GX28,0) -> 0 | GP28: =IF(BI28=4,GM28-GX28,0) -> 0 | GR28: 0 | GS28: 3 | GT28: 0 | GV28: =ROUND((GT28),6) -> 0 | GW28: 1 | GX28: =ROUND(HC28*I28,2) -> 0 | HA28: 0 | HB28: 0 | HC28: =GV28*GW28 -> 0 | HS28: 0 | IK28: 0
A29: 17 | B29: 1 | C29: =ROW(SmtRes!A6) -> 6 | D29: =ROW(EtalonRes!A16) -> 16 | E29: 1 | F29: 6.53-25-1 | G29: Усиление кирпичных стен металлическим каркасом | H29: 1 Т | I29: =ROUND((70.9+38.5+109.3+7.4+7.2+2.7+6.9)/1000*105,9) -> 25.5045 | J29: 0 | K29: =ROUND((70.9+38.5+109.3+7.4+7.2+2.7+6.9)/1000*105,9) -> 25.5045 | O29: =ROUND(CP29,2) -> 3567137.9 | P29: =ROUND((ROUND((AC29*AW29*I29),2)*BC29),2) -> 9562.8 | Q29: =(ROUND((ROUND((((ET29*1.1))*AV29*I29),2)*BB29),2)+ROUND((ROUND(((AE29-((EU29*1.1)))*AV29*I29),2)*BS29),2)) -> 14561.65 | R29: =ROUND((ROUND((AE29*AV29*I29),2)*BS29),2) -> 3188.64 | S29: =ROUND((ROUND((AF29*AV29*I29),2)*BA29),2) -> 3543013.5 | T29: =ROUND(CU29*I29,2) -> 0 | U29: =CV29*I29 -> 5931.9849 | V29: =CW29*I29 -> 0 | W29: =ROUND(CX29*I29,2) -> 0 | X29: =ROUND(CY29,2) -> 3262505.9 | Y29: =ROUND(CZ29,2) -> 1844025.1 | AA29: 56481267 | AB29: =ROUND((AC29+AD29+AF29),6) -> 2843.024 | AC29: =ROUND((ES29),6) -> 28.74 | AD29: =ROUND(((((ET29*1.1))-((EU29*1.1)))+AE29),6) -> 39.688 | AE29: =ROUND(((EU29*1.1)),6) -> 2.497 | AF29: =ROUND(((EV29*1.1)),6) -> 2774.596 | AG29: =ROUND((AP29),6) -> 0 | AH29: =((EW29*1.1)) -> 222.145 | AI29: =((EX29*1.1)) -> 0 | AJ29: =(AS29) -> 0 | AK29: 2587.18 | AL29: 28.74 | AM29: 36.08 | AN29: 2.27 | AO29: 2522.36 | AP29: 0 | AQ29: 201.95 | AR29: 0 | AS29: 0 | AT29: 92 | AU29: 52 | AV29: 1.047 | AW29: 1.002 | AZ29: 1 | BA29: 47.82 | BB29: 13.74 | BC29: 13.02 | BH29: 0 | BI29: 1 | BJ29: ТСН-2001.6 Доп. 79, Сб. 53, т. 25, поз. 1 | BM29: 90 | BN29: 0 | BO29: 6.53-25-1 | BP29: 1 | BQ29: 60 | BR29: 0 | BS29: 47.82 | BT29: 1 | BU29: 1 | BV29: 1 | BW29: 1 | BX29: 1 | BZ29: 92 | CA29: 52 | CE29: 30 | CF29: 0 | CG29: 0 | CM29: 0 | CO29: 0 | CP29: =(P29+Q29+S29) -> 3567137.9 | CQ29: =ROUND((ROUND((AC29*AW29*1),2)*BC29),2) -> 374.98 | CR29: =(ROUND((ROUND((((ET29*1.1))*AV29*1),2)*BB29),2)+ROUND((ROUND(((AE29-((EU29*1.1)))*AV29*1),2)*BS29),2)) -> 570.9 | CS29: =ROUND((ROUND((AE29*AV29*1),2)*BS29),2) -> 124.81 | CT29: =ROUND((ROUND((AF29*AV29*1),2)*BA29),2) -> 138917.1 | CU29: =AG29 -> 0 | CV29: =(AH29*AV29) -> 232.58581 | CW29: =AI29 -> 0 | CX29: =AJ29 -> 0 | CY29: =(((S29+R29)*AT29)/100) -> 3262505.9 | CZ29: =(((S29+R29)*AU29)/100) -> 1844025.1 | DE29: *1,1 | DF29: *1,1 | DG29: *1,1 | DI29: *1,1 | DJ29: *1,1 | DN29: 0 | DO29: 0 | DP29: 1 | DQ29: 1 | DU29: 1013 | DV29: 1 Т | DW29: 1 Т | DX29: 1 | EE29: 55586525 | EF29: 60 | EG29: Ремонтно-строительные работы | EH29: 0 | EJ29: 1 | EK29: 90 | EL29: ТСН-2001.6-53. Стены | EM29: ТСН-2001.6-53-1 | EO29: Поправка: Гл.12.Прил.8.п.8. 5_12.00.01.11.003 | EQ29: 0 | ER29: 2587.18 | ES29: 28.74 | ET29: 36.08 | EU29: 2.27 | EV29: 2522.36 | EW29: 201.95 | EX29: 0 | EY29: 0 | FQ29: 0 | FR29: 0 | FS29: 0 | FX29: 92 | FY29: 52 | GD29: 1 | GF29: -811884377 | GG29: 2 | GH29: 1 | GI29: 2 | GJ29: 0 | GK29: 0 | GL29: =ROUND(IF(AND(BH29=3,BI29=3,FS29<>0),P29,0),2) -> 0 | GM29: =ROUND(O29+X29+Y29,2)+GX29 -> 8673668.9 | GN29: =IF(OR(BI29=0,BI29=1),GM29-GX29,0) -> 8673668.9 | GO29: =IF(BI29=2,GM29-GX29,0) -> 0 | GP29: =IF(BI29=4,GM29-GX29,0) -> 0 | GR29: 0 | GS29: 3 | GT29: 0 | GV29: =ROUND((GT29),6) -> 0 | GW29: 1 | GX29: =ROUND(HC29*I29,2) -> 0 | HA29: 0 | HB29: 0 | HC29: =GV29*GW29 -> 0 | HS29: 0 | IK29: 0
A30: 18 | B30: 1 | C30: 2 | E30: 1,1 | F30: 1.1-1-1121 | G30: Уголок равнополочный, для строительных стальных конструкций, ширина полки более 70 мм, сталь С235, С245 | H30: т | I30: =I28*J30 -> 24.465 | J30: 0.95924249 | K30: 0.9592425 | O30: =ROUND(CP30,2) -> 241322.73 | P30: =ROUND((ROUND((AC30*AW30*I30),2)*BC30),2) -> 241322.73 | Q30: =(ROUND((ROUND(((ET30)*AV30*I30),2)*BB30),2)+ROUND((ROUND(((AE30-(EU30))*AV30*I30),2)*BS30),2)) -> 0 | R30: =ROUND((ROUND((AE30*AV30*I30),2)*BS30),2) -> 0 | S30: =ROUND((ROUND((AF30*AV30*I30),2)*BA30),2) -> 0 | T30: =ROUND(CU30*I30,2) -> 0 | U30: =CV30*I30 -> 0 | V30: =CW30*I30 -> 0 | W30: =ROUND(CX30*I30,2) -> 0 | X30: =ROUND(CY30,2) -> 0 | Y30: =ROUND(CZ30,2) -> 0 | AA30: 56481265 | AB30: =ROUND((AC30+AD30+AF30),6) -> 9844.31 | AC30: =ROUND((ES30),6) -> 9844.31 | AD30: =ROUND((((ET30)-(EU30))+AE30),6) -> 0 | AE30: =ROUND((EU30),6) -> 0 | AF30: =ROUND((EV30),6) -> 0 | AG30: =ROUND((AP30),6) -> 0 | AH30: =(EW30) -> 0 | AI30: =(EX30) -> 0 | AJ30: =(AS30) -> 0 | AK30: 9844.31 | AL30: 9844.31 | AM30: 0 | AN30: 0 | AO30: 0 | AP30: 0 | AQ30: 0 | AR30: 0 | AS30: 0 | AT30: 92 | AU30: 52 | AV30: 1 | AW30: 1.002 | AZ30: 1 | BA30: 1 | BB30: 1 | BC30: 1 | BH30: 3 | BI30: 1 | BJ30: ТСН-2001.1 Доп. 79, Р. 1, о. 1, поз. 1121 | BM30: 90 | BN30: 0 | BP30: 0 | BQ30: 60 | BR30: 0 | BS30: 1 | BT30: 1 | BU30: 1 | BV30: 1 | BW30: 1 | BX30: 1 | BZ30: 92 | CA30: 52 | CE30: 30 | CF30: 0 | CG30: 0 | CM30: 0 | CO30: 0 | CP30: =(P30+Q30+S30) -> 241322.73 | CQ30: =ROUND((ROUND((AC30*AW30*1),2)*BC30),2) -> 9864 | CR30: =(ROUND((ROUND(((ET30)*AV30*1),2)*BB30),2)+ROUND((ROUND(((AE30-(EU30))*AV30*1),2)*BS30),2)) -> 0 | CS30: =ROUND((ROUND((AE30*AV30*1),2)*BS30),2) -> 0 | CT30: =ROUND((ROUND((AF30*AV30*1),2)*BA30),2) -> 0 | CU30: =AG30 -> 0 | CV30: =(AH30*AV30) -> 0 | CW30: =AI30 -> 0 | CX30: =AJ30 -> 0 | CY30: =(((S30+R30)*AT30)/100) -> 0 | CZ30: =(((S30+R30)*AU30)/100) -> 0 | DN30: 0 | DO30: 0 | DP30: 1 | DQ30: 1 | DU30: 1009 | DV30: т | DW30: т | DX30: 1000 | EE30: 55586525 | EF30: 60 | EG30: Ремонтно-строительные работы | EH30: 0 | EJ30: 1 | EK30: 90 | EL30: ТСН-2001.6-53. Стены | EM30: ТСН-2001.6-53-1 | EQ30: 0 | ER30: 9844.31 | ES30: 9844.31 | ET30: 0 | EU30: 0 | EV30: 0 | EW30: 0 | EX30: 0 | FQ30: 0 | FR30: 0 | FS30: 0 | FX30: 92 | FY30: 52 | GD30: 1 | GF30: 981881691 | GG30: 2 | GH30: 1 | GI30: -2 | GJ30: 0 | GK30: 0 | GL30: =ROUND(IF(AND(BH30=3,BI30=3,FS30<>0),P30,0),2) -> 0 | GM30: =ROUND(O30+X30+Y30,2)+GX30 -> 241322.73 | GN30: =IF(OR(BI30=0,BI30=1),GM30-GX30,0) -> 241322.73 | GO30: =IF(BI30=2,GM30-GX30,0) -> 0 | GP30: =IF(BI30=4,GM30-GX30,0) -> 0 | GR30: 0 | GS30: 3 | GT30: 0 | GV30: =ROUND((GT30),6) -> 0 | GW30: 1 | GX30: =ROUND(HC30*I30,2) -> 0 | HA30: 0 | HB30: 0 | HC30: =GV30*GW30 -> 0 | HS30: 0 | IK30: 0
A31: 18 | B31: 1 | C31: 5 | E31: 1,1 | F31: 1.1-1-1121 | G31: Уголок равнополочный, для строительных стальных конструкций, ширина полки более 70 мм, сталь С235, С245 | H31: т | I31: =I29*J31 -> 24.465 | J31: 0.95924249 | K31: 0.9592425 | O31: =ROUND(CP31,2) -> 1819573.4 | P31: =ROUND((ROUND((AC31*AW31*I31),2)*BC31),2) -> 1819573.4 | Q31: =(ROUND((ROUND(((ET31)*AV31*I31),2)*BB31),2)+ROUND((ROUND(((AE31-(EU31))*AV31*I31),2)*BS31),2)) -> 0 | R31: =ROUND((ROUND((AE31*AV31*I31),2)*BS31),2) -> 0 | S31: =ROUND((ROUND((AF31*AV31*I31),2)*BA31),2) -> 0 | T31: =ROUND(CU31*I31,2) -> 0 | U31: =CV31*I31 -> 0 | V31: =CW31*I31 -> 0 | W31: =ROUND(CX31*I31,2) -> 0 | X31: =ROUND(CY31,2) -> 0 | Y31: =ROUND(CZ31,2) -> 0 | AA31: 56481267 | AB31: =ROUND((AC31+AD31+AF31),6) -> 9844.31 | AC31: =ROUND((ES31),6) -> 9844.31 | AD31: =ROUND((((ET31)-(EU31))+AE31),6) -> 0 | AE31: =ROUND((EU31),6) -> 0 | AF31: =ROUND((EV31),6) -> 0 | AG31: =ROUND((AP31),6) -> 0 | AH31: =(EW31) -> 0 | AI31: =(EX31) -> 0 | AJ31: =(AS31) -> 0 | AK31: 9844.31 | AL31: 9844.31 | AM31: 0 | AN31: 0 | AO31: 0 | AP31: 0 | AQ31: 0 | AR31: 0 | AS31: 0 | AT31: 92 | AU31: 52 | AV31: 1 | AW31: 1.002 | AZ31: 1 | BA31: 1 | BB31: 1 | BC31: 7.54 | BH31: 3 | BI31: 1 | BJ31: ТСН-2001.1 Доп. 79, Р. 1, о. 1, поз. 1121 | BM31: 90 | BN31: 0 | BO31: 1.1-1-1121 | BP31: 1 | BQ31: 60 | BR31: 0 | BS31: 1 | BT31: 1 | BU31: 1 | BV31: 1 | BW31: 1 | BX31: 1 | BZ31: 92 | CA31: 52 | CE31: 30 | CF31: 0 | CG31: 0 | CM31: 0 | CO31: 0 | CP31: =(P31+Q31+S31) -> 1819573.4 | CQ31: =ROUND((ROUND((AC31*AW31*1),2)*BC31),2) -> 74374.56 | CR31: =(ROUND((ROUND(((ET31)*AV31*1),2)*BB31),2)+ROUND((ROUND(((AE31-(EU31))*AV31*1),2)*BS31),2)) -> 0 | CS31: =ROUND((ROUND((AE31*AV31*1),2)*BS31),2) -> 0 | CT31: =ROUND((ROUND((AF31*AV31*1),2)*BA31),2) -> 0 | CU31: =AG31 -> 0 | CV31: =(AH31*AV31) -> 0 | CW31: =AI31 -> 0 | CX31: =AJ31 -> 0 | CY31: =(((S31+R31)*AT31)/100) -> 0 | CZ31: =(((S31+R31)*AU31)/100) -> 0 | DN31: 0 | DO31: 0 | DP31: 1 | DQ31: 1 | DU31: 1009 | DV31: т | DW31: т | DX31: 1000 | EE31: 55586525 | EF31: 60 | EG31: Ремонтно-строительные работы | EH31: 0 | EJ31: 1 | EK31: 90 | EL31: ТСН-2001.6-53. Стены | EM31: ТСН-2001.6-53-1 | EQ31: 0 | ER31: 9844.31 | ES31: 9844.31 | ET31: 0 | EU31: 0 | EV31: 0 | EW31: 0 | EX31: 0 | FQ31: 0 | FR31: 0 | FS31: 0 | FX31: 92 | FY31: 52 | GD31: 1 | GF31: 981881691 | GG31: 2 | GH31: 1 | GI31: 2 | GJ31: 0 | GK31: 0 | GL31: =ROUND(IF(AND(BH31=3,BI31=3,FS31<>0),P31,0),2) -> 0 | GM31: =ROUND(O31+X31+Y31,2)+GX31 -> 1819573.4 | GN31: =IF(OR(BI31=0,BI31=1),GM31-GX31,0) -> 1819573.4 | GO31: =IF(BI31=2,GM31-GX31,0) -> 0 | GP31: =IF(BI31=4,GM31-GX31,0) -> 0 | GR31: 0 | GS31: 3 | GT31: 0 | GV31: =ROUND((GT31),6) -> 0 | GW31: 1 | GX31: =ROUND(HC31*I31,2) -> 0 | HA31: 0 | HB31: 0 | HC31: =GV31*GW31 -> 0 | HS31: 0 | IK31: 0
A32: 18 | B32: 1 | C32: 1 | E32: 1,2 | F32: 1.1-1-1105 | G32: Прокат листовой из стали С235, С245 для строительных стальных конструкций, толщина более 3 мм | H32: т | I32: =I28*J32 -> 1.0395 | J32: 0.040757513 | K32: 0.0407575 | O32: =ROUND(CP32,2) -> 6790.26 | P32: =ROUND((ROUND((AC32*AW32*I32),2)*BC32),2) -> 6790.26 | Q32: =(ROUND((ROUND(((ET32)*AV32*I32),2)*BB32),2)+ROUND((ROUND(((AE32-(EU32))*AV32*I32),2)*BS32),2)) -> 0 | R32: =ROUND((ROUND((AE32*AV32*I32),2)*BS32),2) -> 0 | S32: =ROUND((ROUND((AF32*AV32*I32),2)*BA32),2) -> 0 | T32: =ROUND(CU32*I32,2) -> 0 | U32: =CV32*I32 -> 0 | V32: =CW32*I32 -> 0 | W32: =ROUND(CX32*I32,2) -> 0 | X32: =ROUND(CY32,2) -> 0 | Y32: =ROUND(CZ32,2) -> 0 | AA32: 56481265 | AB32: =ROUND((AC32+AD32+AF32),6) -> 6519.2 | AC32: =ROUND((ES32),6) -> 6519.2 | AD32: =ROUND((((ET32)-(EU32))+AE32),6) -> 0 | AE32: =ROUND((EU32),6) -> 0 | AF32: =ROUND((EV32),6) -> 0 | AG32: =ROUND((AP32),6) -> 0 | AH32: =(EW32) -> 0 | AI32: =(EX32) -> 0 | AJ32: =(AS32) -> 0 | AK32: 6519.2 | AL32: 6519.2 | AM32: 0 | AN32: 0 | AO32: 0 | AP32: 0 | AQ32: 0 | AR32: 0 | AS32: 0 | AT32: 92 | AU32: 52 | AV32: 1 | AW32: 1.002 | AZ32: 1 | BA32: 1 | BB32: 1 | BC32: 1 | BH32: 3 | BI32: 1 | BJ32: ТСН-2001.1 Доп. 79, Р. 1, о. 1, поз. 1105 | BM32: 90 | BN32: 0 | BP32: 0 | BQ32: 60 | BR32: 0 | BS32: 1 | BT32: 1 | BU32: 1 | BV32: 1 | BW32: 1 | BX32: 1 | BZ32: 92 | CA32: 52 | CE32: 30 | CF32: 0 | CG32: 0 | CM32: 0 | CO32: 0 | CP32: =(P32+Q32+S32) -> 6790.26 | CQ32: =ROUND((ROUND((AC32*AW32*1),2)*BC32),2) -> 6532.24 | CR32: =(ROUND((ROUND(((ET32)*AV32*1),2)*BB32),2)+ROUND((ROUND(((AE32-(EU32))*AV32*1),2)*BS32),2)) -> 0 | CS32: =ROUND((ROUND((AE32*AV32*1),2)*BS32),2) -> 0 | CT32: =ROUND((ROUND((AF32*AV32*1),2)*BA32),2) -> 0 | CU32: =AG32 -> 0 | CV32: =(AH32*AV32) -> 0 | CW32: =AI32 -> 0 | CX32: =AJ32 -> 0 | CY32: =(((S32+R32)*AT32)/100) -> 0 | CZ32: =(((S32+R32)*AU32)/100) -> 0 | DN32: 0 | DO32: 0 | DP32: 1 | DQ32: 1 | DU32: 1009 | DV32: т | DW32: т | DX32: 1000 | EE32: 55586525 | EF32: 60 | EG32: Ремонтно-строительные работы | EH32: 0 | EJ32: 1 | EK32: 90 | EL32: ТСН-2001.6-53. Стены | EM32: ТСН-2001.6-53-1 | EQ32: 0 | ER32: 6519.2 | ES32: 6519.2 | ET32: 0 | EU32: 0 | EV32: 0 | EW32: 0 | EX32: 0 | FQ32: 0 | FR32: 0 | FS32: 0 | FX32: 92 | FY32: 52 | GD32: 1 | GF32: -1891961884 | GG32: 2 | GH32: 1 | GI32: -2 | GJ32: 0 | GK32: 0 | GL32: =ROUND(IF(AND(BH32=3,BI32=3,FS32<>0),P32,0),2) -> 0 | GM32: =ROUND(O32+X32+Y32,2)+GX32 -> 6790.26 | GN32: =IF(OR(BI32=0,BI32=1),GM32-GX32,0) -> 6790.26 | GO32: =IF(BI32=2,GM32-GX32,0) -> 0 | GP32: =IF(BI32=4,GM32-GX32,0) -> 0 | GR32: 0 | GS32: 3 | GT32: 0 | GV32: =ROUND((GT32),6) -> 0 | GW32: 1 | GX32: =ROUND(HC32*I32,2) -> 0 | HA32: 0 | HB32: 0 | HC32: =GV32*GW32 -> 0 | HS32: 0 | IK32: 0
A33: 18 | B33: 1 | C33: 4 | E33: 1,2 | F33: 1.1-1-1105 | G33: Прокат листовой из стали С235, С245 для строительных стальных конструкций, толщина более 3 мм | H33: т | I33: =I29*J33 -> 1.0395 | J33: 0.040757513 | K33: 0.0407575 | O33: =ROUND(CP33,2) -> 68717.43 | P33: =ROUND((ROUND((AC33*AW33*I33),2)*BC33),2) -> 68717.43 | Q33: =(ROUND((ROUND(((ET33)*AV33*I33),2)*BB33),2)+ROUND((ROUND(((AE33-(EU33))*AV33*I33),2)*BS33),2)) -> 0 | R33: =ROUND((ROUND((AE33*AV33*I33),2)*BS33),2) -> 0 | S33: =ROUND((ROUND((AF33*AV33*I33),2)*BA33),2) -> 0 | T33: =ROUND(CU33*I33,2) -> 0 | U33: =CV33*I33 -> 0 | V33: =CW33*I33 -> 0 | W33: =ROUND(CX33*I33,2) -> 0 | X33: =ROUND(CY33,2) -> 0 | Y33: =ROUND(CZ33,2) -> 0 | AA33: 56481267 | AB33: =ROUND((AC33+AD33+AF33),6) -> 6519.2 | AC33: =ROUND((ES33),6) -> 6519.2 | AD33: =ROUND((((ET33)-(EU33))+AE33),6) -> 0 | AE33: =ROUND((EU33),6) -> 0 | AF33: =ROUND((EV33),6) -> 0 | AG33: =ROUND((AP33),6) -> 0 | AH33: =(EW33) -> 0 | AI33: =(EX33) -> 0 | AJ33: =(AS33) -> 0 | AK33: 6519.2 | AL33: 6519.2 | AM33: 0 | AN33: 0 | AO33: 0 | AP33: 0 | AQ33: 0 | AR33: 0 | AS33: 0 | AT33: 92 | AU33: 52 | AV33: 1 | AW33: 1.002 | AZ33: 1 | BA33: 1 | BB33: 1 | BC33: 10.12 | BH33: 3 | BI33: 1 | BJ33: ТСН-2001.1 Доп. 79, Р. 1, о. 1, поз. 1105 | BM33: 90 | BN33: 0 | BO33: 1.1-1-1105 | BP33: 1 | BQ33: 60 | BR33: 0 | BS33: 1 | BT33: 1 | BU33: 1 | BV33: 1 | BW33: 1 | BX33: 1 | BZ33: 92 | CA33: 52 | CE33: 30 | CF33: 0 | CG33: 0 | CM33: 0 | CO33: 0 | CP33: =(P33+Q33+S33) -> 68717.43 | CQ33: =ROUND((ROUND((AC33*AW33*1),2)*BC33),2) -> 66106.27 | CR33: =(ROUND((ROUND(((ET33)*AV33*1),2)*BB33),2)+ROUND((ROUND(((AE33-(EU33))*AV33*1),2)*BS33),2)) -> 0 | CS33: =ROUND((ROUND((AE33*AV33*1),2)*BS33),2) -> 0 | CT33: =ROUND((ROUND((AF33*AV33*1),2)*BA33),2) -> 0 | CU33: =AG33 -> 0 | CV33: =(AH33*AV33) -> 0 | CW33: =AI33 -> 0 | CX33: =AJ33 -> 0 | CY33: =(((S33+R33)*AT33)/100) -> 0 | CZ33: =(((S33+R33)*AU33)/100) -> 0 | DN33: 0 | DO33: 0 | DP33: 1 | DQ33: 1 | DU33: 1009 | DV33: т | DW33: т | DX33: 1000 | EE33: 55586525 | EF33: 60 | EG33: Ремонтно-строительные работы | EH33: 0 | EJ33: 1 | EK33: 90 | EL33: ТСН-2001.6-53. Стены | EM33: ТСН-2001.6-53-1 | EQ33: 0 | ER33: 6519.2 | ES33: 6519.2 | ET33: 0 | EU33: 0 | EV33: 0 | EW33: 0 | EX33: 0 | FQ33: 0 | FR33: 0 | FS33: 0 | FX33: 92 | FY33: 52 | GD33: 1 | GF33: -1891961884 | GG33: 2 | GH33: 1 | GI33: 2 | GJ33: 0 | GK33: 0 | GL33: =ROUND(IF(AND(BH33=3,BI33=3,FS33<>0),P33,0),2) -> 0 | GM33: =ROUND(O33+X33+Y33,2)+GX33 -> 68717.43 | GN33: =IF(OR(BI33=0,BI33=1),GM33-GX33,0) -> 68717.43 | GO33: =IF(BI33=2,GM33-GX33,0) -> 0 | GP33: =IF(BI33=4,GM33-GX33,0) -> 0 | GR33: 0 | GS33: 3 | GT33: 0 | GV33: =ROUND((GT33),6) -> 0 | GW33: 1 | GX33: =ROUND(HC33*I33,2) -> 0 | HA33: 0 | HB33: 0 | HC33: =GV33*GW33 -> 0 | HS33: 0 | IK33: 0
A34: 18 | B34: 1 | C34: 3 | E34: 1,3 | F34: 1.7-5-220 | G34: Шпилька резьбовая, стальная, оцинкованная, с заостренным концом, в комплекте с шайбой и гайкой, М16x190 мм | H34: шт. | I34: =I28*J34 -> 1470 | J34: 57.636888 | K34: 57.636888 | O34: =ROUND(CP34,2) -> 43893.61 | P34: =ROUND((ROUND((AC34*AW34*I34),2)*BC34),2) -> 43893.61 | Q34: =(ROUND((ROUND(((ET34)*AV34*I34),2)*BB34),2)+ROUND((ROUND(((AE34-(EU34))*AV34*I34),2)*BS34),2)) -> 0 | R34: =ROUND((ROUND((AE34*AV34*I34),2)*BS34),2) -> 0 | S34: =ROUND((ROUND((AF34*AV34*I34),2)*BA34),2) -> 0 | T34: =ROUND(CU34*I34,2) -> 0 | U34: =CV34*I34 -> 0 | V34: =CW34*I34 -> 0 | W34: =ROUND(CX34*I34,2) -> 0 | X34: =ROUND(CY34,2) -> 0 | Y34: =ROUND(CZ34,2) -> 0 | AA34: 56481265 | AB34: =ROUND((AC34+AD34+AF34),6) -> 29.8 | AC34: =ROUND((ES34),6) -> 29.8 | AD34: =ROUND((((ET34)-(EU34))+AE34),6) -> 0 | AE34: =ROUND((EU34),6) -> 0 | AF34: =ROUND((EV34),6) -> 0 | AG34: =ROUND((AP34),6) -> 0 | AH34: =(EW34) -> 0 | AI34: =(EX34) -> 0 | AJ34: =(AS34) -> 0 | AK34: 29.8 | AL34: 29.8 | AM34: 0 | AN34: 0 | AO34: 0 | AP34: 0 | AQ34: 0 | AR34: 0 | AS34: 0 | AT34: 92 | AU34: 52 | AV34: 1 | AW34: 1.002 | AZ34: 1 | BA34: 1 | BB34: 1 | BC34: 1 | BH34: 3 | BI34: 1 | BJ34: ТСН-2001.1 Доп. 53, Р. 7, о. 5, поз. 220 | BM34: 90 | BN34: 0 | BP34: 0 | BQ34: 60 | BR34: 0 | BS34: 1 | BT34: 1 | BU34: 1 | BV34: 1 | BW34: 1 | BX34: 1 | BZ34: 92 | CA34: 52 | CE34: 30 | CF34: 0 | CG34: 0 | CM34: 0 | CO34: 0 | CP34: =(P34+Q34+S34) -> 43893.61 | CQ34: =ROUND((ROUND((AC34*AW34*1),2)*BC34),2) -> 29.86 | CR34: =(ROUND((ROUND(((ET34)*AV34*1),2)*BB34),2)+ROUND((ROUND(((AE34-(EU34))*AV34*1),2)*BS34),2)) -> 0 | CS34: =ROUND((ROUND((AE34*AV34*1),2)*BS34),2) -> 0 | CT34: =ROUND((ROUND((AF34*AV34*1),2)*BA34),2) -> 0 | CU34: =AG34 -> 0 | CV34: =(AH34*AV34) -> 0 | CW34: =AI34 -> 0 | CX34: =AJ34 -> 0 | CY34: =(((S34+R34)*AT34)/100) -> 0 | CZ34: =(((S34+R34)*AU34)/100) -> 0 | DN34: 0 | DO34: 0 | DP34: 1 | DQ34: 1 | DU34: 1010 | DV34: шт. | DW34: шт. | DX34: 1 | EE34: 55586525 | EF34: 60 | EG34: Ремонтно-строительные работы | EH34: 0 | EJ34: 1 | EK34: 90 | EL34: ТСН-2001.6-53. Стены | EM34: ТСН-2001.6-53-1 | EQ34: 0 | ER34: 29.8 | ES34: 29.8 | ET34: 0 | EU34: 0 | EV34: 0 | EW34: 0 | EX34: 0 | FQ34: 0 | FR34: 0 | FS34: 0 | FX34: 92 | FY34: 52 | GD34: 1 | GF34: 2014927073 | GG34: 2 | GH34: 1 | GI34: -2 | GJ34: 0 | GK34: 0 | GL34: =ROUND(IF(AND(BH34=3,BI34=3,FS34<>0),P34,0),2) -> 0 | GM34: =ROUND(O34+X34+Y34,2)+GX34 -> 43893.61 | GN34: =IF(OR(BI34=0,BI34=1),GM34-GX34,0) -> 43893.61 | GO34: =IF(BI34=2,GM34-GX34,0) -> 0 | GP34: =IF(BI34=4,GM34-GX34,0) -> 0 | GR34: 0 | GS34: 3 | GT34: 0 | GV34: =ROUND((GT34),6) -> 0 | GW34: 1 | GX34: =ROUND(HC34*I34,2) -> 0 | HA34: 0 | HB34: 0 | HC34: =GV34*GW34 -> 0 | HS34: 0 | IK34: 0
A35: 18 | B35: 1 | C35: 6 | E35: 1,3 | F35: 1.7-5-220 | G35: Шпилька резьбовая, стальная, оцинкованная, с заостренным концом, в комплекте с шайбой и гайкой, М16x190 мм | H35: шт. | I35: =I29*J35 -> 1470 | J35: 57.636888 | K35: 57.636888 | O35: =ROUND(CP35,2) -> 525406.51 | P35: =ROUND((ROUND((AC35*AW35*I35),2)*BC35),2) -> 525406.51 | Q35: =(ROUND((ROUND(((ET35)*AV35*I35),2)*BB35),2)+ROUND((ROUND(((AE35-(EU35))*AV35*I35),2)*BS35),2)) -> 0 | R35: =ROUND((ROUND((AE35*AV35*I35),2)*BS35),2) -> 0 | S35: =ROUND((ROUND((AF35*AV35*I35),2)*BA35),2) -> 0 | T35: =ROUND(CU35*I35,2) -> 0 | U35: =CV35*I35 -> 0 | V35: =CW35*I35 -> 0 | W35: =ROUND(CX35*I35,2) -> 0 | X35: =ROUND(CY35,2) -> 0 | Y35: =ROUND(CZ35,2) -> 0 | AA35: 56481267 | AB35: =ROUND((AC35+AD35+AF35),6) -> 29.8 | AC35: =ROUND((ES35),6) -> 29.8 | AD35: =ROUND((((ET35)-(EU35))+AE35),6) -> 0 | AE35: =ROUND((EU35),6) -> 0 | AF35: =ROUND((EV35),6) -> 0 | AG35: =ROUND((AP35),6) -> 0 | AH35: =(EW35) -> 0 | AI35: =(EX35) -> 0 | AJ35: =(AS35) -> 0 | AK35: 29.8 | AL35: 29.8 | AM35: 0 | AN35: 0 | AO35: 0 | AP35: 0 | AQ35: 0 | AR35: 0 | AS35: 0 | AT35: 92 | AU35: 52 | AV35: 1 | AW35: 1.002 | AZ35: 1 | BA35: 1 | BB35: 1 | BC35: 11.97 | BH35: 3 | BI35: 1 | BJ35: ТСН-2001.1 Доп. 53, Р. 7, о. 5, поз. 220 | BM35: 90 | BN35: 0 | BO35: 1.7-5-220 | BP35: 1 | BQ35: 60 | BR35: 0 | BS35: 1 | BT35: 1 | BU35: 1 | BV35: 1 | BW35: 1 | BX35: 1 | BZ35: 92 | CA35: 52 | CE35: 30 | CF35: 0 | CG35: 0 | CM35: 0 | CO35: 0 | CP35: =(P35+Q35+S35) -> 525406.51 | CQ35: =ROUND((ROUND((AC35*AW35*1),2)*BC35),2) -> 357.42 | CR35: =(ROUND((ROUND(((ET35)*AV35*1),2)*BB35),2)+ROUND((ROUND(((AE35-(EU35))*AV35*1),2)*BS35),2)) -> 0 | CS35: =ROUND((ROUND((AE35*AV35*1),2)*BS35),2) -> 0 | CT35: =ROUND((ROUND((AF35*AV35*1),2)*BA35),2) -> 0 | CU35: =AG35 -> 0 | CV35: =(AH35*AV35) -> 0 | CW35: =AI35 -> 0 | CX35: =AJ35 -> 0 | CY35: =(((S35+R35)*AT35)/100) -> 0 | CZ35: =(((S35+R35)*AU35)/100) -> 0 | DN35: 0 | DO35: 0 | DP35: 1 | DQ35: 1 | DU35: 1010 | DV35: шт. | DW35: шт. | DX35: 1 | EE35: 55586525 | EF35: 60 | EG35: Ремонтно-строительные работы | EH35: 0 | EJ35: 1 | EK35: 90 | EL35: ТСН-2001.6-53. Стены | EM35: ТСН-2001.6-53-1 | EQ35: 0 | ER35: 29.8 | ES35: 29.8 | ET35: 0 | EU35: 0 | EV35: 0 | EW35: 0 | EX35: 0 | FQ35: 0 | FR35: 0 | FS35: 0 | FX35: 92 | FY35: 52 | GD35: 1 | GF35: 2014927073 | GG35: 2 | GH35: 1 | GI35: 2 | GJ35: 0 | GK35: 0 | GL35: =ROUND(IF(AND(BH35=3,BI35=3,FS35<>0),P35,0),2) -> 0 | GM35: =ROUND(O35+X35+Y35,2)+GX35 -> 525406.51 | GN35: =IF(OR(BI35=0,BI35=1),GM35-GX35,0) -> 525406.51 | GO35: =IF(BI35=2,GM35-GX35,0) -> 0 | GP35: =IF(BI35=4,GM35-GX35,0) -> 0 | GR35: 0 | GS35: 3 | GT35: 0 | GV35: =ROUND((GT35),6) -> 0 | GW35: 1 | GX35: =ROUND(HC35*I35,2) -> 0 | HA35: 0 | HB35: 0 | HC35: =GV35*GW35 -> 0 | HS35: 0 | IK35: 0
A36: 17 | B36: 1 | C36: =ROW(SmtRes!A7) -> 7 | E36: 2 | F36: 3.13-9-2 | G36: Огрунтовка металлических поверхностей грунтовкой ГФ-021 за один раз | H36: 100 м2 | I36: =ROUND((70.9*26.3+38.5*26.3+109.3*33+7.4*33+7.2*32.1+2.7*32.1+6.9*33)/1000/100*105,9) -> 7.6375005 | J36: 0 | K36: =ROUND((70.9*26.3+38.5*26.3+109.3*33+7.4*33+7.2*32.1+2.7*32.1+6.9*33)/1000/100*105,9) -> 7.6375005 | O36: =ROUND(CP36,2) -> 931.69 | P36: =ROUND((ROUND((AC36*AW36*I36),2)*BC36),2) -> 72.25 | Q36: =(ROUND((ROUND(((((ET36*1.25)*1.1))*AV36*I36),2)*BB36),2)+ROUND((ROUND(((AE36-(((EU36*1.25)*1.1)))*AV36*I36),2)*BS36),2)) -> 143.24 | R36: =ROUND((ROUND((AE36*AV36*I36),2)*BS36),2) -> 2.63 | S36: =ROUND((ROUND((AF36*AV36*I36),2)*BA36),2) -> 716.2 | T36: =ROUND(CU36*I36,2) -> 0 | U36: =CV36*I36 -> 51.302236 | V36: =CW36*I36 -> 0 | W36: =ROUND(CX36*I36,2) -> 0 | X36: =ROUND(CY36,2) -> 718.83 | Y36: =ROUND(CZ36,2) -> 460.05 | AA36: 56481265 | AB36: =ROUND((AC36+AD36+AF36),6) -> 121.98945 | AC36: =ROUND((ES36),6) -> 9.46 | AD36: =ROUND((((((ET36*1.25)*1.1))-(((EU36*1.25)*1.1)))+AE36),6) -> 18.755 | AE36: =ROUND((((EU36*1.25)*1.1)),6) -> 0.34375 | AF36: =ROUND((((EV36*1.15)*1.1)),6) -> 93.77445 | AG36: =ROUND((AP36),6) -> 0 | AH36: =(((EW36*1.15)*1.1)) -> 6.71715 | AI36: =(((EX36*1.25)*1.1)) -> 0 | AJ36: =(AS36) -> 0 | AK36: 97.23 | AL36: 9.46 | AM36: 13.64 | AN36: 0.25 | AO36: 74.13 | AP36: 0 | AQ36: 5.31 | AR36: 0 | AS36: 0 | AT36: 100 | AU36: 64 | AV36: 1 | AW36: 1 | AZ36: 1 | BA36: 1 | BB36: 1 | BC36: 1 | BH36: 0 | BI36: 1 | BJ36: ТСН-2001.3 Доп. 71, Сб. 13, т. 9, поз. 2 | BM36: 97 | BN36: 0 | BP36: 0 | BQ36: 60 | BR36: 0 | BS36: 1 | BT36: 1 | BU36: 1 | BV36: 1 | BW36: 1 | BX36: 1 | BZ36: 100 | CA36: 64 | CE36: 30 | CF36: 0 | CG36: 0 | CM36: 0 | CO36: 0 | CP36: =(P36+Q36+S36) -> 931.69 | CQ36: =ROUND((ROUND((AC36*AW36*1),2)*BC36),2) -> 9.46 | CR36: =(ROUND((ROUND(((((ET36*1.25)*1.1))*AV36*1),2)*BB36),2)+ROUND((ROUND(((AE36-(((EU36*1.25)*1.1)))*AV36*1),2)*BS36),2)) -> 18.76 | CS36: =ROUND((ROUND((AE36*AV36*1),2)*BS36),2) -> 0.34 | CT36: =ROUND((ROUND((AF36*AV36*1),2)*BA36),2) -> 93.77 | CU36: =AG36 -> 0 | CV36: =(AH36*AV36) -> 6.71715 | CW36: =AI36 -> 0 | CX36: =AJ36 -> 0 | CY36: =(((S36+R36)*AT36)/100) -> 718.83 | CZ36: =(((S36+R36)*AU36)/100) -> 460.0512 | DE36: *1,25)*1,1 | DF36: *1,25)*1,1 | DG36: *1,15)*1,1 | DI36: *1,15)*1,1 | DJ36: *1,25)*1,1 | DN36: 0 | DO36: 0 | DP36: 1.047 | DQ36: 1 | DU36: 1005 | DV36: 100 м2 | DW36: 100 м2 | DX36: 100 | EE36: 55586532 | EF36: 60 | EG36: Ремонтно-строительные работы | EH36: 0 | EJ36: 1 | EK36: 97 | EL36: ТСН-2001.6-60. Печные работы | EM36: ТСН-2001.6-60-1 | EO36: Поправка: О.П. п.3.4. 6 Поправка: О.П. п.3.4.30.в | EQ36: 0 | ER36: 97.23 | ES36: 9.46 | ET36: 13.64 | EU36: 0.25 | EV36: 74.13 | EW36: 5.31 | EX36: 0 | EY36: 0 | FQ36: 0 | FR36: 0 | FS36: 0 | FX36: 100 | FY36: 64 | GD36: 1 | GF36: -673576059 | GG36: 2 | GH36: 1 | GI36: -2 | GJ36: 0 | GK36: 0 | GL36: =ROUND(IF(AND(BH36=3,BI36=3,FS36<>0),P36,0),2) -> 0 | GM36: =ROUND(O36+X36+Y36,2)+GX36 -> 2110.57 | GN36: =IF(OR(BI36=0,BI36=1),GM36-GX36,0) -> 2110.57 | GO36: =IF(BI36=2,GM36-GX36,0) -> 0 | GP36: =IF(BI36=4,GM36-GX36,0) -> 0 | GR36: 0 | GS36: 3 | GT36: 0 | GV36: =ROUND((GT36),6) -> 0 | GW36: 1 | GX36: =ROUND(HC36*I36,2) -> 0 | HA36: 0 | HB36: 0 | HC36: =GV36*GW36 -> 0 | HS36: 0 | IK36: 0
A37: 17 | B37: 1 | C37: =ROW(SmtRes!A8) -> 8 | E37: 2 | F37: 3.13-9-2 | G37: Огрунтовка металлических поверхностей грунтовкой ГФ-021 за один раз | H37: 100 м2 | I37: =ROUND((70.9*26.3+38.5*26.3+109.3*33+7.4*33+7.2*32.1+2.7*32.1+6.9*33)/1000/100*105,9) -> 7.6375005 | J37: 0 | K37: =ROUND((70.9*26.3+38.5*26.3+109.3*33+7.4*33+7.2*32.1+2.7*32.1+6.9*33)/1000/100*105,9) -> 7.6375005 | O37: =ROUND(CP37,2) -> 39764.55 | P37: =ROUND((ROUND((AC37*AW37*I37),2)*BC37),2) -> 2330.06 | Q37: =(ROUND((ROUND(((((ET37*1.25)*1.1))*AV37*I37),2)*BB37),2)+ROUND((ROUND(((AE37-(((EU37*1.25)*1.1)))*AV37*I37),2)*BS37),2)) -> 1576.18 | R37: =ROUND((ROUND((AE37*AV37*I37),2)*BS37),2) -> 131.51 | S37: =ROUND((ROUND((AF37*AV37*I37),2)*BA37),2) -> 35858.31 | T37: =ROUND(CU37*I37,2) -> 0 | U37: =CV37*I37 -> 53.713442 | V37: =CW37*I37 -> 0 | W37: =ROUND(CX37*I37,2) -> 0 | X37: =ROUND(CY37,2) -> 32030.94 | Y37: =ROUND(CZ37,2) -> 15835.52 | AA37: 56481267 | AB37: =ROUND((AC37+AD37+AF37),6) -> 121.98945 | AC37: =ROUND((ES37),6) -> 9.46 | AD37: =ROUND((((((ET37*1.25)*1.1))-(((EU37*1.25)*1.1)))+AE37),6) -> 18.755 | AE37: =ROUND((((EU37*1.25)*1.1)),6) -> 0.34375 | AF37: =ROUND((((EV37*1.15)*1.1)),6) -> 93.77445 | AG37: =ROUND((AP37),6) -> 0 | AH37: =(((EW37*1.15)*1.1)) -> 6.71715 | AI37: =(((EX37*1.25)*1.1)) -> 0 | AJ37: =(AS37) -> 0 | AK37: 97.23 | AL37: 9.46 | AM37: 13.64 | AN37: 0.25 | AO37: 74.13 | AP37: 0 | AQ37: 5.31 | AR37: 0 | AS37: 0 | AT37: 89 | AU37: 44 | AV37: 1.047 | AW37: 1 | AZ37: 1 | BA37: 47.82 | BB37: 10.51 | BC37: 32.25 | BH37: 0 | BI37: 1 | BJ37: ТСН-2001.3 Доп. 71, Сб. 13, т. 9, поз. 2 | BM37: 97 | BN37: 0 | BO37: 3.13-9-2 | BP37: 1 | BQ37: 60 | BR37: 0 | BS37: 47.82 | BT37: 1 | BU37: 1 | BV37: 1 | BW37: 1 | BX37: 1 | BZ37: 89 | CA37: 44 | CE37: 30 | CF37: 0 | CG37: 0 | CM37: 0 | CO37: 0 | CP37: =(P37+Q37+S37) -> 39764.55 | CQ37: =ROUND((ROUND((AC37*AW37*1),2)*BC37),2) -> 305.09 | CR37: =(ROUND((ROUND(((((ET37*1.25)*1.1))*AV37*1),2)*BB37),2)+ROUND((ROUND(((AE37-(((EU37*1.25)*1.1)))*AV37*1),2)*BS37),2)) -> 206.42 | CS37: =ROUND((ROUND((AE37*AV37*1),2)*BS37),2) -> 17.22 | CT37: =ROUND((ROUND((AF37*AV37*1),2)*BA37),2) -> 4694.97 | CU37: =AG37 -> 0 | CV37: =(AH37*AV37) -> 7.032856 | CW37: =AI37 -> 0 | CX37: =AJ37 -> 0 | CY37: =(((S37+R37)*AT37)/100) -> 32030.94 | CZ37: =(((S37+R37)*AU37)/100) -> 15835.521 | DE37: *1,25)*1,1 | DF37: *1,25)*1,1 | DG37: *1,15)*1,1 | DI37: *1,15)*1,1 | DJ37: *1,25)*1,1 | DN37: 0 | DO37: 0 | DP37: 1 | DQ37: 1 | DU37: 1005 | DV37: 100 м2 | DW37: 100 м2 | DX37: 100 | EE37: 55586532 | EF37: 60 | EG37: Ремонтно-строительные работы | EH37: 0 | EJ37: 1 | EK37: 97 | EL37: ТСН-2001.6-60. Печные работы | EM37: ТСН-2001.6-60-1 | EO37: Поправка: О.П. п.3.4. 6 Поправка: О.П. п.3.4.30.в | EQ37: 0 | ER37: 97.23 | ES37: 9.46 | ET37: 13.64 | EU37: 0.25 | EV37: 74.13 | EW37: 5.31 | EX37: 0 | EY37: 0 | FQ37: 0 | FR37: 0 | FS37: 0 | FX37: 89 | FY37: 44 | GD37: 1 | GF37: -673576059 | GG37: 2 | GH37: 1 | GI37: 2 | GJ37: 0 | GK37: 0 | GL37: =ROUND(IF(AND(BH37=3,BI37=3,FS37<>0),P37,0),2) -> 0 | GM37: =ROUND(O37+X37+Y37,2)+GX37 -> 87631.01 | GN37: =IF(OR(BI37=0,BI37=1),GM37-GX37,0) -> 87631.01 | GO37: =IF(BI37=2,GM37-GX37,0) -> 0 | GP37: =IF(BI37=4,GM37-GX37,0) -> 0 | GR37: 0 | GS37: 0 | GT37: 0 | GV37: =ROUND((GT37),6) -> 0 | GW37: 1 | GX37: =ROUND(HC37*I37,2) -> 0 | HA37: 0 | HB37: 0 | HC37: =GV37*GW37 -> 0 | HS37: 0 | IK37: 0
A38: 18 | B38: 1 | C38: 7 | E38: 2,1 | F38: 1.1-1-165 | G38: Грунтовка глифталевая, типа ГФ-021 | H38: т | I38: =I36*J38 -> 0.068738 | J38: 0.0090000649 | K38: 0.009 | O38: =ROUND(CP38,2) -> 1282.69 | P38: =ROUND((ROUND((AC38*AW38*I38),2)*BC38),2) -> 1282.69 | Q38: =(ROUND((ROUND(((ET38)*AV38*I38),2)*BB38),2)+ROUND((ROUND(((AE38-(EU38))*AV38*I38),2)*BS38),2)) -> 0 | R38: =ROUND((ROUND((AE38*AV38*I38),2)*BS38),2) -> 0 | S38: =ROUND((ROUND((AF38*AV38*I38),2)*BA38),2) -> 0 | T38: =ROUND(CU38*I38,2) -> 0 | U38: =CV38*I38 -> 0 | V38: =CW38*I38 -> 0 | W38: =ROUND(CX38*I38,2) -> 0 | X38: =ROUND(CY38,2) -> 0 | Y38: =ROUND(CZ38,2) -> 0 | AA38: 56481265 | AB38: =ROUND((AC38+AD38+AF38),6) -> 18660.61 | AC38: =ROUND((ES38),6) -> 18660.61 | AD38: =ROUND((((ET38)-(EU38))+AE38),6) -> 0 | AE38: =ROUND((EU38),6) -> 0 | AF38: =ROUND((EV38),6) -> 0 | AG38: =ROUND((AP38),6) -> 0 | AH38: =(EW38) -> 0 | AI38: =(EX38) -> 0 | AJ38: =(AS38) -> 0 | AK38: 18660.61 | AL38: 18660.61 | AM38: 0 | AN38: 0 | AO38: 0 | AP38: 0 | AQ38: 0 | AR38: 0 | AS38: 0 | AT38: 100 | AU38: 64 | AV38: 1 | AW38: 1 | AZ38: 1 | BA38: 1 | BB38: 1 | BC38: 1 | BH38: 3 | BI38: 1 | BJ38: ТСН-2001.1 Доп. 67, Р. 1, о. 1, поз. 165 | BM38: 97 | BN38: 0 | BP38: 0 | BQ38: 60 | BR38: 0 | BS38: 1 | BT38: 1 | BU38: 1 | BV38: 1 | BW38: 1 | BX38: 1 | BZ38: 100 | CA38: 64 | CE38: 30 | CF38: 0 | CG38: 0 | CM38: 0 | CO38: 0 | CP38: =(P38+Q38+S38) -> 1282.69 | CQ38: =ROUND((ROUND((AC38*AW38*1),2)*BC38),2) -> 18660.61 | CR38: =(ROUND((ROUND(((ET38)*AV38*1),2)*BB38),2)+ROUND((ROUND(((AE38-(EU38))*AV38*1),2)*BS38),2)) -> 0 | CS38: =ROUND((ROUND((AE38*AV38*1),2)*BS38),2) -> 0 | CT38: =ROUND((ROUND((AF38*AV38*1),2)*BA38),2) -> 0 | CU38: =AG38 -> 0 | CV38: =(AH38*AV38) -> 0 | CW38: =AI38 -> 0 | CX38: =AJ38 -> 0 | CY38: =(((S38+R38)*AT38)/100) -> 0 | CZ38: =(((S38+R38)*AU38)/100) -> 0 | DN38: 0 | DO38: 0 | DP38: 1.047 | DQ38: 1 | DU38: 1009 | DV38: т | DW38: т | DX38: 1000 | EE38: 55586532 | EF38: 60 | EG38: Ремонтно-строительные работы | EH38: 0 | EJ38: 1 | EK38: 97 | EL38: ТСН-2001.6-60. Печные работы | EM38: ТСН-2001.6-60-1 | EQ38: 0 | ER38: 18660.61 | ES38: 18660.61 | ET38: 0 | EU38: 0 | EV38: 0 | EW38: 0 | EX38: 0 | FQ38: 0 | FR38: 0 | FS38: 0 | FX38: 100 | FY38: 64 | GD38: 1 | GF38: 667244177 | GG38: 2 | GH38: 1 | GI38: -2 | GJ38: 0 | GK38: 0 | GL38: =ROUND(IF(AND(BH38=3,BI38=3,FS38<>0),P38,0),2) -> 0 | GM38: =ROUND(O38+X38+Y38,2)+GX38 -> 1282.69 | GN38: =IF(OR(BI38=0,BI38=1),GM38-GX38,0) -> 1282.69 | GO38: =IF(BI38=2,GM38-GX38,0) -> 0 | GP38: =IF(BI38=4,GM38-GX38,0) -> 0 | GR38: 0 | GS38: 3 | GT38: 0 | GV38: =ROUND((GT38),6) -> 0 | GW38: 1 | GX38: =ROUND(HC38*I38,2) -> 0 | HA38: 0 | HB38: 0 | HC38: =GV38*GW38 -> 0 | HS38: 0 | IK38: 0
A39: 18 | B39: 1 | C39: 8 | E39: 2,1 | F39: 1.1-1-165 | G39: Грунтовка глифталевая, типа ГФ-021 | H39: т | I39: =I37*J39 -> 0.068738 | J39: 0.0090000649 | K39: 0.009 | O39: =ROUND(CP39,2) -> 4592.03 | P39: =ROUND((ROUND((AC39*AW39*I39),2)*BC39),2) -> 4592.03 | Q39: =(ROUND((ROUND(((ET39)*AV39*I39),2)*BB39),2)+ROUND((ROUND(((AE39-(EU39))*AV39*I39),2)*BS39),2)) -> 0 | R39: =ROUND((ROUND((AE39*AV39*I39),2)*BS39),2) -> 0 | S39: =ROUND((ROUND((AF39*AV39*I39),2)*BA39),2) -> 0 | T39: =ROUND(CU39*I39,2) -> 0 | U39: =CV39*I39 -> 0 | V39: =CW39*I39 -> 0 | W39: =ROUND(CX39*I39,2) -> 0 | X39: =ROUND(CY39,2) -> 0 | Y39: =ROUND(CZ39,2) -> 0 | AA39: 56481267 | AB39: =ROUND((AC39+AD39+AF39),6) -> 18660.61 | AC39: =ROUND((ES39),6) -> 18660.61 | AD39: =ROUND((((ET39)-(EU39))+AE39),6) -> 0 | AE39: =ROUND((EU39),6) -> 0 | AF39: =ROUND((EV39),6) -> 0 | AG39: =ROUND((AP39),6) -> 0 | AH39: =(EW39) -> 0 | AI39: =(EX39) -> 0 | AJ39: =(AS39) -> 0 | AK39: 18660.61 | AL39: 18660.61 | AM39: 0 | AN39: 0 | AO39: 0 | AP39: 0 | AQ39: 0 | AR39: 0 | AS39: 0 | AT39: 89 | AU39: 44 | AV39: 1 | AW39: 1 | AZ39: 1 | BA39: 1 | BB39: 1 | BC39: 3.58 | BH39: 3 | BI39: 1 | BJ39: ТСН-2001.1 Доп. 67, Р. 1, о. 1, поз. 165 | BM39: 97 | BN39: 0 | BO39: 1.1-1-165 | BP39: 1 | BQ39: 60 | BR39: 0 | BS39: 1 | BT39: 1 | BU39: 1 | BV39: 1 | BW39: 1 | BX39: 1 | BZ39: 89 | CA39: 44 | CE39: 30 | CF39: 0 | CG39: 0 | CM39: 0 | CO39: 0 | CP39: =(P39+Q39+S39) -> 4592.03 | CQ39: =ROUND((ROUND((AC39*AW39*1),2)*BC39),2) -> 66804.98 | CR39: =(ROUND((ROUND(((ET39)*AV39*1),2)*BB39),2)+ROUND((ROUND(((AE39-(EU39))*AV39*1),2)*BS39),2)) -> 0 | CS39: =ROUND((ROUND((AE39*AV39*1),2)*BS39),2) -> 0 | CT39: =ROUND((ROUND((AF39*AV39*1),2)*BA39),2) -> 0 | CU39: =AG39 -> 0 | CV39: =(AH39*AV39) -> 0 | CW39: =AI39 -> 0 | CX39: =AJ39 -> 0 | CY39: =(((S39+R39)*AT39)/100) -> 0 | CZ39: =(((S39+R39)*AU39)/100) -> 0 | DN39: 0 | DO39: 0 | DP39: 1 | DQ39: 1 | DU39: 1009 | DV39: т | DW39: т | DX39: 1000 | EE39: 55586532 | EF39: 60 | EG39: Ремонтно-строительные работы | EH39: 0 | EJ39: 1 | EK39: 97 | EL39: ТСН-2001.6-60. Печные работы | EM39: ТСН-2001.6-60-1 | EQ39: 0 | ER39: 18660.61 | ES39: 18660.61 | ET39: 0 | EU39: 0 | EV39: 0 | EW39: 0 | EX39: 0 | FQ39: 0 | FR39: 0 | FS39: 0 | FX39: 89 | FY39: 44 | GD39: 1 | GF39: 667244177 | GG39: 2 | GH39: 1 | GI39: 2 | GJ39: 0 | GK39: 0 | GL39: =ROUND(IF(AND(BH39=3,BI39=3,FS39<>0),P39,0),2) -> 0 | GM39: =ROUND(O39+X39+Y39,2)+GX39 -> 4592.03 | GN39: =IF(OR(BI39=0,BI39=1),GM39-GX39,0) -> 4592.03 | GO39: =IF(BI39=2,GM39-GX39,0) -> 0 | GP39: =IF(BI39=4,GM39-GX39,0) -> 0 | GR39: 0 | GS39: 0 | GT39: 0 | GV39: =ROUND((GT39),6) -> 0 | GW39: 1 | GX39: =ROUND(HC39*I39,2) -> 0 | HA39: 0 | HB39: 0 | HC39: =GV39*GW39 -> 0 | HS39: 0 | IK39: 0
A41: 51 | B41: =B24 -> 1 | C41: =A24 -> 4 | D41: =ROW(A24) -> 24 | F41: =IF(F24<>"",F24,"") | G41: =IF(G24<>"",G24,"") -> Усиление внутренних и наружных стен в зоне расширяемых проемов в подвале и в надземной части здания. Рама РС-1, 105 шт. (КР-5,6) | H41: 0 | O41: =ROUND(AB41,2) -> 370105.87 | P41: =ROUND(AC41,2) -> 294096.01 | Q41: =ROUND(AD41,2) -> 1203.04 | R41: =ROUND(AE41,2) -> 69.31 | S41: =ROUND(AF41,2) -> 74806.82 | T41: =ROUND(AG41,2) -> 0 | U41: =AH41 -> 5983.2872 | V41: =AI41 -> 0 | W41: =ROUND(AJ41,2) -> 0 | X41: =ROUND(AK41,2) -> 68943.55 | Y41: =ROUND(AL41,2) -> 39021.85 | AB41: =ROUND(SUMIF(AA28:AA39,"=56481265",O28:O39),2) -> 370105.87 | AC41: =ROUND(SUMIF(AA28:AA39,"=56481265",P28:P39),2) -> 294096.01 | AD41: =ROUND(SUMIF(AA28:AA39,"=56481265",Q28:Q39),2) -> 1203.04 | AE41: =ROUND(SUMIF(AA28:AA39,"=56481265",R28:R39),2) -> 69.31 | AF41: =ROUND(SUMIF(AA28:AA39,"=56481265",S28:S39),2) -> 74806.82 | AG41: =ROUND(SUMIF(AA28:AA39,"=56481265",T28:T39),2) -> 0 | AH41: =SUMIF(AA28:AA39,"=56481265",U28:U39) -> 5983.2872 | AI41: =SUMIF(AA28:AA39,"=56481265",V28:V39) -> 0 | AJ41: =ROUND(SUMIF(AA28:AA39,"=56481265",W28:W39),2) -> 0 | AK41: =ROUND(SUMIF(AA28:AA39,"=56481265",X28:X39),2) -> 68943.55 | AL41: =ROUND(SUMIF(AA28:AA39,"=56481265",Y28:Y39),2) -> 39021.85 | AO41: =ROUND(BX41,2) -> 0 | AP41: =ROUND(BY41,2) -> 0 | AQ41: =ROUND(BZ41,2) -> 0 | AR41: =ROUND(CA41,2) -> 478071.27 | AS41: =ROUND(CB41,2) -> 478071.27 | AT41: =ROUND(CC41,2) -> 0 | AU41: =ROUND(CD41,2) -> 0 | AV41: =ROUND(CE41,2) -> 294096.01 | ... BD41: =ROUND(CM41,2) -> 0 | BX41: =ROUND(SUMIF(AA28:AA39,"=56481265",FQ28:FQ39),2) -> 0 | BY41: =ROUND(SUMIF(AA28:AA39,"=56481265",FR28:FR39),2) -> 0 | BZ41: =ROUND(SUMIF(AA28:AA39,"=56481265",GL28:GL39),2) -> 0 | CA41: =ROUND(SUMIF(AA28:AA39,"=56481265",GM28:GM39),2) -> 478071.27 | CB41: =ROUND(SUMIF(AA28:AA39,"=56481265",GN28:GN39),2) -> 478071.27 | CC41: =ROUND(SUMIF(AA28:AA39,"=56481265",GO28:GO39),2) -> 0 | CD41: =ROUND(SUMIF(AA28:AA39,"=56481265",GP28:GP39),2) -> 0 | CE41: =AC41-BX41 -> 294096.01 | CF41: =AC41-BY41 -> 294096.01 | CG41: =BX41-BZ41 -> 0 | CH41: =AC41-BX41-BY41+BZ41 -> 294096.01 | CI41: =BY41-BZ41 -> 0 | CJ41: =ROUND(SUMIF(AA28:AA39,"=56481265",GX28:GX39),2) -> 0 | CK41: =ROUND(SUMIF(AA28:AA39,"=56481265",GY28:GY39),2) -> 0 | CL41: =ROUND(SUMIF(AA28:AA39,"=56481265",GZ28:GZ39),2) -> 0 | CM41: =ROUND(SUMIF(AA28:AA39,"=56481265",HD28:HD39),2) -> 0 | DG41: =ROUND(DT41,2) -> 6025191.8 | DH41: =ROUND(DU41,2) -> 2430182.2 | DI41: =ROUND(DV41,2) -> 16137.83 | DJ41: =ROUND(DW41,2) -> 3320.15 | DK41: =ROUND(DX41,2) -> 3578871.8 | DL41: =ROUND(DY41,2) -> 0 | DM41: =DZ41 -> 5985.6984 | DN41: =EA41 -> 0 | DO41: =ROUND(EB41,2) -> 0 | DP41: =ROUND(EC41,2) -> 3294536.9 | DQ41: =ROUND(ED41,2) -> 1859860.6 | DT41: =ROUND(SUMIF(AA28:AA39,"=56481267",O28:O39),2) -> 6025191.8 | DU41: =ROUND(SUMIF(AA28:AA39,"=56481267",P28:P39),2) -> 2430182.2 | DV41: =ROUND(SUMIF(AA28:AA39,"=56481267",Q28:Q39),2) -> 16137.83 | DW41: =ROUND(SUMIF(AA28:AA39,"=56481267",R28:R39),2) -> 3320.15 | DX41: =ROUND(SUMIF(AA28:AA39,"=56481267",S28:S39),2) -> 3578871.8 | DY41: =ROUND(SUMIF(AA28:AA39,"=56481267",T28:T39),2) -> 0 | DZ41: =SUMIF(AA28:AA39,"=56481267",U28:U39) -> 5985.6984 | EA41: =SUMIF(AA28:AA39,"=56481267",V28:V39) -> 0 | EB41: =ROUND(SUMIF(AA28:AA39,"=56481267",W28:W39),2) -> 0 | EC41: =ROUND(SUMIF(AA28:AA39,"=56481267",X28:X39),2) -> 3294536.9 | ED41: =ROUND(SUMIF(AA28:AA39,"=56481267",Y28:Y39),2) -> 1859860.6 | EG41: =ROUND(FP41,2) -> 0 | EH41: =ROUND(FQ41,2) -> 0 | EI41: =ROUND(FR41,2) -> 0 | EJ41: =ROUND(FS41,2) -> 11179589 | EK41: =ROUND(FT41,2) -> 11179589 | EL41: =ROUND(FU41,2) -> 0 | EM41: =ROUND(FV41,2) -> 0 | EN41: =ROUND(FW41,2) -> 2430182.2 | ... EV41: =ROUND(GE41,2) -> 0 | FP41: =ROUND(SUMIF(AA28:AA39,"=56481267",FQ28:FQ39),2) -> 0 | FQ41: =ROUND(SUMIF(AA28:AA39,"=56481267",FR28:FR39),2) -> 0 | FR41: =ROUND(SUMIF(AA28:AA39,"=56481267",GL28:GL39),2) -> 0 | FS41: =ROUND(SUMIF(AA28:AA39,"=56481267",GM28:GM39),2) -> 11179589 | FT41: =ROUND(SUMIF(AA28:AA39,"=56481267",GN28:GN39),2) -> 11179589 | FU41: =ROUND(SUMIF(AA28:AA39,"=56481267",GO28:GO39),2) -> 0 | FV41: =ROUND(SUMIF(AA28:AA39,"=56481267",GP28:GP39),2) -> 0 | FW41: =DU41-FP41 -> 2430182.2 | FX41: =DU41-FQ41 -> 2430182.2 | FY41: =FP41-FR41 -> 0 | FZ41: =DU41-FP41-FQ41+FR41 -> 2430182.2 | GA41: =FQ41-FR41 -> 0 | GB41: =ROUND(SUMIF(AA28:AA39,"=56481267",GX28:GX39),2) -> 0 | GC41: =ROUND(SUMIF(AA28:AA39,"=56481267",GY28:GY39),2) -> 0 | GD41: =ROUND(SUMIF(AA28:AA39,"=56481267",GZ28:GZ39),2) -> 0 | GE41: =ROUND(SUMIF(AA28:AA39,"=56481267",HD28:HD39),2) -> 0 | GX41: 0
A43: 50 | B43: 0 | C43: 0 | D43: 1 | E43: 201 | F43: =ROUND(Source!O41,O43) -> 370105.87 | G43: ПЗ | H43: Прямые затраты | K43: 201 | L43: 1 | M43: 3 | O43: 2 | P43: =ROUND(Source!DG41,O43) -> 6025191.8 | W43: 370105.87 | X43: 1 | Y43: 370105.87 | Z43: 6025191.8 | AA43: 1 | AB43: 6025191.8
A44: 50 | B44: 0 | C44: 0 | D44: 1 | E44: 202 | F44: =ROUND(Source!P41,O44) -> 294096.01 | G44: СтМатОб | H44: Стоимость материальных ресурсов (всего) | K44: 202 | L44: 2 | M44: 3 | O44: 2 | P44: =ROUND(Source!DH41,O44) -> 2430182.2 | W44: 294096.01 | X44: 1 | Y44: 294096.01 | Z44: 2430182.2 | AA44: 1 | AB44: 2430182.2
A45: 50 | B45: 0 | C45: 0 | D45: 1 | E45: 222 | F45: =ROUND(Source!AO41,O45) -> 0 | G45: СтМатОбЗак | H45: Стоимость материалов и оборудования заказчика | K45: 222 | L45: 3 | M45: 3 | O45: 2 | P45: =ROUND(Source!EG41,O45) -> 0 | W45: 0 | X45: 1 | Y45: 0 | Z45: 0 | AA45: 1 | AB45: 0
A46: 50 | B46: 0 | C46: 0 | D46: 1 | E46: 225 | F46: =ROUND(Source!AV41,O46) -> 294096.01 | G46: СтМатОбПод | H46: Стоимость материалов и оборудования подрядчика | K46: 225 | L46: 4 | M46: 3 | O46: 2 | P46: =ROUND(Source!EN41,O46) -> 2430182.2 | W46: 294096.01 | X46: 1 | Y46: 294096.01 | Z46: 2430182.2 | AA46: 1 | AB46: 2430182.2
A47: 50 | B47: 0 | C47: 0 | D47: 1 | E47: 226 | F47: =ROUND(Source!AW41,O47) -> 294096.01 | G47: СтМат | H47: Стоимость материалов (всего) | K47: 226 | L47: 5 | M47: 3 | O47: 2 | P47: =ROUND(Source!EO41,O47) -> 2430182.2 | W47: 294096.01 | X47: 1 | Y47: 294096.01 | Z47: 2430182.2 | AA47: 1 | AB47: 2430182.2
A48: 50 | B48: 0 | C48: 0 | D48: 1 | E48: 227 | F48: =ROUND(Source!AX41,O48) -> 0 | G48: СтМатЗак | H48: Стоимость материалов заказчика | K48: 227 | L48: 6 | M48: 3 | O48: 2 | P48: =ROUND(Source!EP41,O48) -> 0 | W48: 0 | X48: 1 | Y48: 0 | Z48: 0 | AA48: 1 | AB48: 0
A49: 50 | B49: 0 | C49: 0 | D49: 1 | E49: 228 | F49: =ROUND(Source!AY41,O49) -> 294096.01 | G49: СтМатПод | H49: Стоимость материалов подрядчика | K49: 228 | L49: 7 | M49: 3 | O49: 2 | P49: =ROUND(Source!EQ41,O49) -> 2430182.2 | W49: 294096.01 | X49: 1 | Y49: 294096.01 | Z49: 2430182.2 | AA49: 1 | AB49: 2430182.2
A50: 50 | B50: 0 | C50: 0 | D50: 1 | E50: 216 | F50: =ROUND(Source!AP41,O50) -> 0 | G50: Оборуд | H50: Стоимость оборудования (всего) | K50: 216 | L50: 8 | M50: 3 | O50: 2 | P50: =ROUND(Source!EH41,O50) -> 0 | W50: 0 | X50: 1 | Y50: 0 | Z50: 0 | AA50: 1 | AB50: 0
A51: 50 | B51: 0 | C51: 0 | D51: 1 | E51: 223 | F51: =ROUND(Source!AQ41,O51) -> 0 | G51: ОборудЗак | H51: Стоимость оборудования заказчика | K51: 223 | L51: 9 | M51: 3 | O51: 2 | P51: =ROUND(Source!EI41,O51) -> 0 | W51: 0 | X51: 1 | Y51: 0 | Z51: 0 | AA51: 1 | AB51: 0
A52: 50 | B52: 0 | C52: 0 | D52: 1 | E52: 229 | F52: =ROUND(Source!AZ41,O52) -> 0 | G52: ОборудПод | H52: Стоимость оборудования подрядчика | K52: 229 | L52: 10 | M52: 3 | O52: 2 | P52: =ROUND(Source!ER41,O52) -> 0 | W52: 0 | X52: 1 | Y52: 0 | Z52: 0 | AA52: 1 | AB52: 0
A53: 50 | B53: 0 | C53: 0 | D53: 1 | E53: 203 | F53: =ROUND(Source!Q41,O53) -> 1203.04 | G53: ЭММ | H53: Эксплуатация машин | K53: 203 | L53: 11 | M53: 3 | O53: 2 | P53: =ROUND(Source!DI41,O53) -> 16137.83 | W53: 1203.04 | X53: 1 | Y53: 1203.04 | Z53: 16137.83 | AA53: 1 | AB53: 16137.83
A54: 50 | B54: 0 | C54: 0 | D54: 1 | E54: 231 | F54: =ROUND(Source!BB41,O54) -> 0 | G54: ЭММсНРиСП | H54: Эксплуатация машин по ТСН-2001.16 | K54: 231 | L54: 12 | M54: 3 | O54: 2 | P54: =ROUND(Source!ET41,O54) -> 0 | W54: 0 | X54: 1 | Y54: 0 | Z54: 0 | AA54: 1 | AB54: 0
A55: 50 | B55: 0 | C55: 0 | D55: 1 | E55: 204 | F55: =ROUND(Source!R41,O55) -> 69.31 | G55: ЗПМ | H55: ЗП машинистов | K55: 204 | L55: 13 | M55: 3 | O55: 2 | P55: =ROUND(Source!DJ41,O55) -> 3320.15 | W55: 69.31 | X55: 1 | Y55: 69.31 | Z55: 3320.15 | AA55: 1 | AB55: 3320.15
A56: 50 | B56: 0 | C56: 0 | D56: 1 | E56: 205 | F56: =ROUND(Source!S41,O56) -> 74806.82 | G56: ОЗП | H56: Основная ЗП рабочих | K56: 205 | L56: 14 | M56: 3 | O56: 2 | P56: =ROUND(Source!DK41,O56) -> 3578871.8 | W56: 74806.82 | X56: 1 | Y56: 74806.82 | Z56: 3578871.8 | AA56: 1 | AB56: 3578871.8
A57: 50 | B57: 0 | C57: 0 | D57: 1 | E57: 232 | F57: =ROUND(Source!BC41,O57) -> 0 | G57: ОЗПсНРиСП | H57: Основная ЗП рабочих по ТСН-2001.16 | K57: 232 | L57: 15 | M57: 3 | O57: 2 | P57: =ROUND(Source!EU41,O57) -> 0 | W57: 0 | X57: 1 | Y57: 0 | Z57: 0 | AA57: 1 | AB57: 0
A58: 50 | B58: 0 | C58: 0 | D58: 1 | E58: 214 | F58: =ROUND(Source!AS41,O58) -> 478071.27 | G58: Строит | H58: Строительные работы с НР и СП | K58: 214 | L58: 16 | M58: 3 | O58: 2 | P58: =ROUND(Source!EK41,O58) -> 11179589 | W58: 478071.27 | X58: 1 | Y58: 478071.27 | Z58: 11179589 | AA58: 1 | AB58: 11179589
A59: 50 | B59: 0 | C59: 0 | D59: 1 | E59: 215 | F59: =ROUND(Source!AT41,O59) -> 0 | G59: Монтаж | H59: Монтажные работы с НР и СП | K59: 215 | L59: 17 | M59: 3 | O59: 2 | P59: =ROUND(Source!EL41,O59) -> 0 | W59: 0 | X59: 1 | Y59: 0 | Z59: 0 | AA59: 1 | AB59: 0
A60: 50 | B60: 0 | C60: 0 | D60: 1 | E60: 217 | F60: =ROUND(Source!AU41,O60) -> 0 | G60: Прочие | H60: Прочие работы с НР и СП | K60: 217 | L60: 18 | M60: 3 | O60: 2 | P60: =ROUND(Source!EM41,O60) -> 0 | W60: 0 | X60: 1 | Y60: 0 | Z60: 0 | AA60: 1 | AB60: 0
A61: 50 | B61: 0 | C61: 0 | D61: 1 | E61: 230 | F61: =ROUND(Source!BA41,O61) -> 0 | G61: ПрочиеЗатр | H61: Прочие затраты по ТСН-2001.16 | K61: 230 | L61: 19 | M61: 3 | O61: 2 | P61: =ROUND(Source!ES41,O61) -> 0 | W61: 0 | X61: 1 | Y61: 0 | Z61: 0 | AA61: 1 | AB61: 0
A62: 50 | B62: 0 | C62: 0 | D62: 1 | E62: 206 | F62: =ROUND(Source!T41,O62) -> 0 | G62: ВозврМат | H62: Возврат материалов | K62: 206 | L62: 20 | M62: 3 | O62: 2 | P62: =ROUND(Source!DL41,O62) -> 0 | W62: 0 | X62: 1 | Y62: 0 | Z62: 0 | AA62: 1 | AB62: 0
A63: 50 | B63: 0 | C63: 0 | D63: 1 | E63: 207 | F63: =Source!U41 -> 5983.2872 | G63: ТрудСтр | H63: Трудозатраты строителей | K63: 207 | L63: 21 | M63: 3 | O63: -1 | P63: =Source!DM41 -> 5985.6984 | W63: 5983.2872 | X63: 1 | Y63: 5983.2872 | Z63: 5985.6984 | AA63: 1 | AB63: 5985.6984
A64: 50 | B64: 0 | C64: 0 | D64: 1 | E64: 208 | F64: =Source!V41 -> 0 | G64: ТрудМаш | H64: Трудозатраты машинистов | K64: 208 | L64: 22 | M64: 3 | O64: -1 | P64: =Source!DN41 -> 0 | W64: 0 | X64: 1 | Y64: 0 | Z64: 0 | AA64: 1 | AB64: 0
A65: 50 | B65: 0 | C65: 0 | D65: 1 | E65: 209 | F65: =ROUND(Source!W41,O65) -> 0 | G65: ТранспМат | H65: Транспорт материалов | K65: 209 | L65: 23 | M65: 3 | O65: 2 | P65: =ROUND(Source!DO41,O65) -> 0 | W65: 0 | X65: 1 | Y65: 0 | Z65: 0 | AA65: 1 | AB65: 0
A66: 50 | B66: 0 | C66: 0 | D66: 1 | E66: 233 | F66: =ROUND(Source!BD41,O66) -> 0 | G66: Перевозка | H66: Перевозка грузов | K66: 233 | L66: 24 | M66: 3 | O66: 2 | P66: =ROUND(Source!EV41,O66) -> 0 | W66: 0 | X66: 1 | Y66: 0 | Z66: 0 | AA66: 1 | AB66: 0
A67: 50 | B67: 0 | C67: 0 | D67: 1 | E67: 210 | F67: =ROUND(Source!X41,O67) -> 68943.55 | G67: НР | H67: Накладные расходы | K67: 210 | L67: 25 | M67: 3 | O67: 2 | P67: =ROUND(Source!DP41,O67) -> 3294536.9 | W67: 68943.55 | X67: 1 | Y67: 68943.55 | Z67: 3294536.9 | AA67: 1 | AB67: 3294536.9
A68: 50 | B68: 0 | C68: 0 | D68: 1 | E68: 211 | F68: =ROUND(Source!Y41,O68) -> 39021.85 | G68: СмПриб | H68: Сметная прибыль | K68: 211 | L68: 26 | M68: 3 | O68: 2 | P68: =ROUND(Source!DQ41,O68) -> 1859860.6 | W68: 39021.85 | X68: 1 | Y68: 39021.85 | Z68: 1859860.6 | AA68: 1 | AB68: 1859860.6
A69: 50 | B69: 0 | C69: 0 | D69: 1 | E69: 224 | F69: =ROUND(Source!AR41,O69) -> 478071.27 | G69: Всего | H69: Всего с НР и СП | K69: 224 | L69: 27 | M69: 3 | O69: 2 | P69: =ROUND(Source!EJ41,O69) -> 11179589 | W69: 478071.27 | X69: 1 | Y69: 478071.27 | Z69: 11179589 | AA69: 1 | AB69: 11179589
A71: 4 | B71: 1 | D71: =ROW(A92) -> 92 | G71: Усиление внутренних и наружных стен в зоне расширяемых проемов в подвале и в надземной части здания. Рама РС-2, 22 шт. (КР-5,6) | I71: 0 | K71: -1 | S71: 0 | T71: 0 | V71: 0 | BX71: 0 | CJ71: 0
A73: 52 | B73: =B92 -> 1 | C73: =C92 -> 4 | D73: =D92 -> 71 | E73: =E92 -> 0 | F73: =F92 | G73: =G92 -> Усиление внутренних и наружных стен в зоне расширяемых проемов в подвале и в надземной части здания. Рама РС-2, 22 шт. (КР-5,6) | O73: =O92 -> 62548.77 | P73: =P92 -> 48444.53 | Q73: =Q92 -> 223.4 | R73: =R92 -> 12.86 | S73: =S92 -> 13880.84 | T73: =T92 -> 0 | U73: =U92 -> 1110.2259 | V73: =V92 -> 0 | ... GX73: =GX92 -> 0
A75: 17 | B75: 1 | C75: =ROW(SmtRes!A13) -> 13 | D75: =ROW(EtalonRes!A24) -> 24 | E75: 3 | F75: 6.53-25-1 | G75: Усиление кирпичных стен металлическим каркасом | H75: 1 Т | I75: =ROUND((67.6+106.3+4.2+6.9+7.2+11.3+0.9+1.4+9.3)/1000*22,9) -> 4.7322 | J75: 0 | K75: =ROUND((67.6+106.3+4.2+6.9+7.2+11.3+0.9+1.4+9.3)/1000*22,9) -> 4.7322 | O75: =ROUND(CP75,2) -> 14079.97 | P75: =ROUND((ROUND((AC75*AW75*I75),2)*BC75),2) -> 136.28 | Q75: =(ROUND((ROUND((((ET75*1.1))*AV75*I75),2)*BB75),2)+ROUND((ROUND(((AE75-((EU75*1.1)))*AV75*I75),2)*BS75),2)) -> 196.64 | R75: =ROUND((ROUND((AE75*AV75*I75),2)*BS75),2) -> 12.37 | S75: =ROUND((ROUND((AF75*AV75*I75),2)*BA75),2) -> 13747.05 | T75: =ROUND(CU75*I75,2) -> 0 | U75: =CV75*I75 -> 1100.6426 | V75: =CW75*I75 -> 0 | W75: =ROUND(CX75*I75,2) -> 0 | X75: =ROUND(CY75,2) -> 12658.67 | Y75: =ROUND(CZ75,2) -> 7154.9 | AA75: 56481265 | AB75: =ROUND((AC75+AD75+AF75),6) -> 2843.024 | AC75: =ROUND((ES75),6) -> 28.74 | AD75: =ROUND(((((ET75*1.1))-((EU75*1.1)))+AE75),6) -> 39.688 | AE75: =ROUND(((EU75*1.1)),6) -> 2.497 | AF75: =ROUND(((EV75*1.1)),6) -> 2774.596 | AG75: =ROUND((AP75),6) -> 0 | AH75: =((EW75*1.1)) -> 222.145 | AI75: =((EX75*1.1)) -> 0 | AJ75: =(AS75) -> 0 | AK75: 2587.18 | AL75: 28.74 | AM75: 36.08 | AN75: 2.27 | AO75: 2522.36 | AP75: 0 | AQ75: 201.95 | AR75: 0 | AS75: 0 | AT75: 92 | AU75: 52 | AV75: 1.047 | AW75: 1.002 | AZ75: 1 | BA75: 1 | BB75: 1 | BC75: 1 | BH75: 0 | BI75: 1 | BJ75: ТСН-2001.6 Доп. 79, Сб. 53, т. 25, поз. 1 | BM75: 90 | BN75: 0 | BO75: 6.53-25-1 | BP75: 1 | BQ75: 60 | BR75: 0 | BS75: 1 | BT75: 1 | BU75: 1 | BV75: 1 | BW75: 1 | BX75: 1 | BZ75: 92 | CA75: 52 | CE75: 30 | CF75: 0 | CG75: 0 | CM75: 0 | CO75: 0 | CP75: =(P75+Q75+S75) -> 14079.97 | CQ75: =ROUND((ROUND((AC75*AW75*1),2)*BC75),2) -> 28.8 | CR75: =(ROUND((ROUND((((ET75*1.1))*AV75*1),2)*BB75),2)+ROUND((ROUND(((AE75-((EU75*1.1)))*AV75*1),2)*BS75),2)) -> 41.55 | CS75: =ROUND((ROUND((AE75*AV75*1),2)*BS75),2) -> 2.61 | CT75: =ROUND((ROUND((AF75*AV75*1),2)*BA75),2) -> 2905 | CU75: =AG75 -> 0 | CV75: =(AH75*AV75) -> 232.58581 | CW75: =AI75 -> 0 | CX75: =AJ75 -> 0 | CY75: =(((S75+R75)*AT75)/100) -> 12658.666 | CZ75: =(((S75+R75)*AU75)/100) -> 7154.8984 | DE75: *1,1 | DF75: *1,1 | DG75: *1,1 | DI75: *1,1 | DJ75: *1,1 | DN75: 0 | DO75: 0 | DP75: 1 | DQ75: 1 | DU75: 1013 | DV75: 1 Т | DW75: 1 Т | DX75: 1 | EE75: 55586525 | EF75: 60 | EG75: Ремонтно-строительные работы | EH75: 0 | EJ75: 1 | EK75: 90 | EL75: ТСН-2001.6-53. Стены | EM75: ТСН-2001.6-53-1 | EO75: Поправка: Гл.12.Прил.8.п.8. 5_12.00.01.11.003 | EQ75: 0 | ER75: 2587.18 | ES75: 28.74 | ET75: 36.08 | EU75: 2.27 | EV75: 2522.36 | EW75: 201.95 | EX75: 0 | EY75: 0 | FQ75: 0 | FR75: 0 | FS75: 0 | FX75: 92 | FY75: 52 | GD75: 1 | GF75: -811884377 | GG75: 2 | GH75: 1 | GI75: 2 | GJ75: 0 | GK75: 0 | GL75: =ROUND(IF(AND(BH75=3,BI75=3,FS75<>0),P75,0),2) -> 0 | GM75: =ROUND(O75+X75+Y75,2)+GX75 -> 33893.54 | GN75: =IF(OR(BI75=0,BI75=1),GM75-GX75,0) -> 33893.54 | GO75: =IF(BI75=2,GM75-GX75,0) -> 0 | GP75: =IF(BI75=4,GM75-GX75,0) -> 0 | GR75: 0 | GS75: 3 | GT75: 0 | GV75: =ROUND((GT75),6) -> 0 | GW75: 1 | GX75: =ROUND(HC75*I75,2) -> 0 | HA75: 0 | HB75: 0 | HC75: =GV75*GW75 -> 0 | HS75: 0 | IK75: 0
A76: 17 | B76: 1 | C76: =ROW(SmtRes!A18) -> 18 | D76: =ROW(EtalonRes!A32) -> 32 | E76: 3 | F76: 6.53-25-1 | G76: Усиление кирпичных стен металлическим каркасом | H76: 1 Т | I76: =ROUND((67.6+106.3+4.2+6.9+7.2+11.3+0.9+1.4+9.3)/1000*22,9) -> 4.7322 | J76: 0 | K76: =ROUND((67.6+106.3+4.2+6.9+7.2+11.3+0.9+1.4+9.3)/1000*22,9) -> 4.7322 | O76: =ROUND(CP76,2) -> 661860.13 | P76: =ROUND((ROUND((AC76*AW76*I76),2)*BC76),2) -> 1774.37 | Q76: =(ROUND((ROUND((((ET76*1.1))*AV76*I76),2)*BB76),2)+ROUND((ROUND(((AE76-((EU76*1.1)))*AV76*I76),2)*BS76),2)) -> 2701.83 | R76: =ROUND((ROUND((AE76*AV76*I76),2)*BS76),2) -> 591.53 | S76: =ROUND((ROUND((AF76*AV76*I76),2)*BA76),2) -> 657383.93 | T76: =ROUND(CU76*I76,2) -> 0 | U76: =CV76*I76 -> 1100.6426 | V76: =CW76*I76 -> 0 | W76: =ROUND(CX76*I76,2) -> 0 | X76: =ROUND(CY76,2) -> 605337.42 | Y76: =ROUND(CZ76,2) -> 342147.24 | AA76: 56481267 | AB76: =ROUND((AC76+AD76+AF76),6) -> 2843.024 | AC76: =ROUND((ES76),6) -> 28.74 | AD76: =ROUND(((((ET76*1.1))-((EU76*1.1)))+AE76),6) -> 39.688 | AE76: =ROUND(((EU76*1.1)),6) -> 2.497 | AF76: =ROUND(((EV76*1.1)),6) -> 2774.596 | AG76: =ROUND((AP76),6) -> 0 | AH76: =((EW76*1.1)) -> 222.145 | AI76: =((EX76*1.1)) -> 0 | AJ76: =(AS76) -> 0 | AK76: 2587.18 | AL76: 28.74 | AM76: 36.08 | AN76: 2.27 | AO76: 2522.36 | AP76: 0 | AQ76: 201.95 | AR76: 0 | AS76: 0 | AT76: 92 | AU76: 52 | AV76: 1.047 | AW76: 1.002 | AZ76: 1 | BA76: 47.82 | BB76: 13.74 | BC76: 13.02 | BH76: 0 | BI76: 1 | BJ76: ТСН-2001.6 Доп. 79, Сб. 53, т. 25, поз. 1 | BM76: 90 | BN76: 0 | BO76: 6.53-25-1 | BP76: 1 | BQ76: 60 | BR76: 0 | BS76: 47.82 | BT76: 1 | BU76: 1 | BV76: 1 | BW76: 1 | BX76: 1 | BZ76: 92 | CA76: 52 | CE76: 30 | CF76: 0 | CG76: 0 | CM76: 0 | CO76: 0 | CP76: =(P76+Q76+S76) -> 661860.13 | CQ76: =ROUND((ROUND((AC76*AW76*1),2)*BC76),2) -> 374.98 | CR76: =(ROUND((ROUND((((ET76*1.1))*AV76*1),2)*BB76),2)+ROUND((ROUND(((AE76-((EU76*1.1)))*AV76*1),2)*BS76),2)) -> 570.9 | CS76: =ROUND((ROUND((AE76*AV76*1),2)*BS76),2) -> 124.81 | CT76: =ROUND((ROUND((AF76*AV76*1),2)*BA76),2) -> 138917.1 | CU76: =AG76 -> 0 | CV76: =(AH76*AV76) -> 232.58581 | CW76: =AI76 -> 0 | CX76: =AJ76 -> 0 | CY76: =(((S76+R76)*AT76)/100) -> 605337.42 | CZ76: =(((S76+R76)*AU76)/100) -> 342147.24 | DE76: *1,1 | DF76: *1,1 | DG76: *1,1 | DI76: *1,1 | DJ76: *1,1 | DN76: 0 | DO76: 0 | DP76: 1 | DQ76: 1 | DU76: 1013 | DV76: 1 Т | DW76: 1 Т | DX76: 1 | EE76: 55586525 | EF76: 60 | EG76: Ремонтно-строительные работы | EH76: 0 | EJ76: 1 | EK76: 90 | EL76: ТСН-2001.6-53. Стены | EM76: ТСН-2001.6-53-1 | EO76: Поправка: Гл.12.Прил.8.п.8. 5_12.00.01.11.003 | EQ76: 0 | ER76: 2587.18 | ES76: 28.74 | ET76: 36.08 | EU76: 2.27 | EV76: 2522.36 | EW76: 201.95 | EX76: 0 | EY76: 0 | FQ76: 0 | FR76: 0 | FS76: 0 | FX76: 92 | FY76: 52 | GD76: 1 | GF76: -811884377 | GG76: 2 | GH76: 1 | GI76: 2 | GJ76: 0 | GK76: 0 | GL76: =ROUND(IF(AND(BH76=3,BI76=3,FS76<>0),P76,0),2) -> 0 | GM76: =ROUND(O76+X76+Y76,2)+GX76 -> 1609344.8 | GN76: =IF(OR(BI76=0,BI76=1),GM76-GX76,0) -> 1609344.8 | GO76: =IF(BI76=2,GM76-GX76,0) -> 0 | GP76: =IF(BI76=4,GM76-GX76,0) -> 0 | GR76: 0 | GS76: 3 | GT76: 0 | GV76: =ROUND((GT76),6) -> 0 | GW76: 1 | GX76: =ROUND(HC76*I76,2) -> 0 | HA76: 0 | HB76: 0 | HC76: =GV76*GW76 -> 0 | HS76: 0 | IK76: 0
A77: 18 | B77: 1 | C77: 11 | E77: 3,1 | F77: 1.1-1-1145 | G77: Швеллер №№ 12-40, из стали углеродистой обыкновенного качества, спокойной | H77: т | I77: =I75*J77 -> 1.4872 | J77: 0.31427243 | K77: 0.3142724 | O77: =ROUND(CP77,2) -> 12503.65 | P77: =ROUND((ROUND((AC77*AW77*I77),2)*BC77),2) -> 12503.65 | Q77: =(ROUND((ROUND(((ET77)*AV77*I77),2)*BB77),2)+ROUND((ROUND(((AE77-(EU77))*AV77*I77),2)*BS77),2)) -> 0 | R77: =ROUND((ROUND((AE77*AV77*I77),2)*BS77),2) -> 0 | S77: =ROUND((ROUND((AF77*AV77*I77),2)*BA77),2) -> 0 | T77: =ROUND(CU77*I77,2) -> 0 | U77: =CV77*I77 -> 0 | V77: =CW77*I77 -> 0 | W77: =ROUND(CX77*I77,2) -> 0 | X77: =ROUND(CY77,2) -> 0 | Y77: =ROUND(CZ77,2) -> 0 | AA77: 56481265 | AB77: =ROUND((AC77+AD77+AF77),6) -> 8407.51 | AC77: =ROUND((ES77),6) -> 8407.51 | AD77: =ROUND((((ET77)-(EU77))+AE77),6) -> 0 | AE77: =ROUND((EU77),6) -> 0 | AF77: =ROUND((EV77),6) -> 0 | AG77: =ROUND((AP77),6) -> 0 | AH77: =(EW77) -> 0 | AI77: =(EX77) -> 0 | AJ77: =(AS77) -> 0 | AK77: 8407.51 | AL77: 8407.51 | AM77: 0 | AN77: 0 | AO77: 0 | AP77: 0 | AQ77: 0 | AR77: 0 | AS77: 0 | AT77: 84 | AU77: 53 | AV77: 1 | AW77: 1 | AZ77: 1 | BA77: 1 | BB77: 1 | BC77: 1 | BH77: 3 | BI77: 1 | BJ77: ТСН-2001.1 Доп. 79, Р. 1, о. 1, поз. 1145 | BM77: 13 | BN77: 0 | BP77: 0 | BQ77: 30 | BR77: 0 | BS77: 1 | BT77: 1 | BU77: 1 | BV77: 1 | BW77: 1 | BX77: 1 | BZ77: 84 | CA77: 53 | CE77: 30 | CF77: 0 | CG77: 0 | CM77: 0 | CO77: 0 | CP77: =(P77+Q77+S77) -> 12503.65 | CQ77: =ROUND((ROUND((AC77*AW77*1),2)*BC77),2) -> 8407.51 | CR77: =(ROUND((ROUND(((ET77)*AV77*1),2)*BB77),2)+ROUND((ROUND(((AE77-(EU77))*AV77*1),2)*BS77),2)) -> 0 | CS77: =ROUND((ROUND((AE77*AV77*1),2)*BS77),2) -> 0 | CT77: =ROUND((ROUND((AF77*AV77*1),2)*BA77),2) -> 0 | CU77: =AG77 -> 0 | CV77: =(AH77*AV77) -> 0 | CW77: =AI77 -> 0 | CX77: =AJ77 -> 0 | CY77: =(((S77+R77)*AT77)/100) -> 0 | CZ77: =(((S77+R77)*AU77)/100) -> 0 | DN77: 0 | DO77: 0 | DP77: 1 | DQ77: 1 | DU77: 1009 | DV77: т | DW77: т | DX77: 1000 | EE77: 55586449 | EF77: 30 | EG77: Строительные работы | EH77: 0 | EJ77: 1 | EK77: 13 | EL77: ТСН-2001.3-9. Металлические конструкции | EM77: ТСН-2001.3-9-1 | EQ77: 0 | ER77: 8407.51 | ES77: 8407.51 | ET77: 0 | EU77: 0 | EV77: 0 | EW77: 0 | EX77: 0 | FQ77: 0 | FR77: 0 | FS77: 0 | FX77: 84 | FY77: 53 | GD77: 1 | GF77: 975818671 | GG77: 2 | GH77: 1 | GI77: -2 | GJ77: 0 | GK77: 0 | GL77: =ROUND(IF(AND(BH77=3,BI77=3,FS77<>0),P77,0),2) -> 0 | GM77: =ROUND(O77+X77+Y77,2)+GX77 -> 12503.65 | GN77: =IF(OR(BI77=0,BI77=1),GM77-GX77,0) -> 12503.65 | GO77: =IF(BI77=2,GM77-GX77,0) -> 0 | GP77: =IF(BI77=4,GM77-GX77,0) -> 0 | GR77: 0 | GS77: 3 | GT77: 0 | GV77: =ROUND((GT77),6) -> 0 | GW77: 1 | GX77: =ROUND(HC77*I77,2) -> 0 | HA77: 0 | HB77: 0 | HC77: =GV77*GW77 -> 0 | HS77: 0 | IK77: 0
A78: 18 | B78: 1 | C78: 16 | E78: 3,1 | F78: 1.1-1-1145 | G78: Швеллер №№ 12-40, из стали углеродистой обыкновенного качества, спокойной | H78: т | I78: =I76*J78 -> 1.4872 | J78: 0.31427243 | K78: 0.3142724 | O78: =ROUND(CP78,2) -> 140446.28 | P78: =ROUND((ROUND((AC78*AW78*I78),2)*BC78),2) -> 140446.28 | Q78: =(ROUND((ROUND(((ET78)*AV78*I78),2)*BB78),2)+ROUND((ROUND(((AE78-(EU78))*AV78*I78),2)*BS78),2)) -> 0 | R78: =ROUND((ROUND((AE78*AV78*I78),2)*BS78),2) -> 0 | S78: =ROUND((ROUND((AF78*AV78*I78),2)*BA78),2) -> 0 | T78: =ROUND(CU78*I78,2) -> 0 | U78: =CV78*I78 -> 0 | V78: =CW78*I78 -> 0 | W78: =ROUND(CX78*I78,2) -> 0 | X78: =ROUND(CY78,2) -> 0 | Y78: =ROUND(CZ78,2) -> 0 | AA78: 56481267 | AB78: =ROUND((AC78+AD78+AF78),6) -> 8407.51 | AC78: =ROUND((ES78),6) -> 8407.51 | AD78: =ROUND((((ET78)-(EU78))+AE78),6) -> 0 | AE78: =ROUND((EU78),6) -> 0 | AF78: =ROUND((EV78),6) -> 0 | AG78: =ROUND((AP78),6) -> 0 | AH78: =(EW78) -> 0 | AI78: =(EX78) -> 0 | AJ78: =(AS78) -> 0 | AK78: 8407.51 | AL78: 8407.51 | AM78: 0 | AN78: 0 | AO78: 0 | AP78: 0 | AQ78: 0 | AR78: 0 | AS78: 0 | AT78: 84 | AU78: 53 | AV78: 1 | AW78: 1.002 | AZ78: 1 | BA78: 1 | BB78: 1 | BC78: 11.21 | BH78: 3 | BI78: 1 | BJ78: ТСН-2001.1 Доп. 79, Р. 1, о. 1, поз. 1145 | BM78: 13 | BN78: 0 | BO78: 1.1-1-1145 | BP78: 1 | BQ78: 30 | BR78: 0 | BS78: 1 | BT78: 1 | BU78: 1 | BV78: 1 | BW78: 1 | BX78: 1 | BZ78: 84 | CA78: 53 | CE78: 30 | CF78: 0 | CG78: 0 | CM78: 0 | CO78: 0 | CP78: =(P78+Q78+S78) -> 140446.28 | CQ78: =ROUND((ROUND((AC78*AW78*1),2)*BC78),2) -> 94436.74 | CR78: =(ROUND((ROUND(((ET78)*AV78*1),2)*BB78),2)+ROUND((ROUND(((AE78-(EU78))*AV78*1),2)*BS78),2)) -> 0 | CS78: =ROUND((ROUND((AE78*AV78*1),2)*BS78),2) -> 0 | CT78: =ROUND((ROUND((AF78*AV78*1),2)*BA78),2) -> 0 | CU78: =AG78 -> 0 | CV78: =(AH78*AV78) -> 0 | CW78: =AI78 -> 0 | CX78: =AJ78 -> 0 | CY78: =(((S78+R78)*AT78)/100) -> 0 | CZ78: =(((S78+R78)*AU78)/100) -> 0 | DN78: 0 | DO78: 0 | DP78: 1 | DQ78: 1 | DU78: 1009 | DV78: т | DW78: т | DX78: 1000 | EE78: 55586449 | EF78: 30 | EG78: Строительные работы | EH78: 0 | EJ78: 1 | EK78: 13 | EL78: ТСН-2001.3-9. Металлические конструкции | EM78: ТСН-2001.3-9-1 | EQ78: 0 | ER78: 8407.51 | ES78: 8407.51 | ET78: 0 | EU78: 0 | EV78: 0 | EW78: 0 | EX78: 0 | FQ78: 0 | FR78: 0 | FS78: 0 | FX78: 84 | FY78: 53 | GD78: 1 | GF78: 975818671 | GG78: 2 | GH78: 1 | GI78: 2 | GJ78: 0 | GK78: 0 | GL78: =ROUND(IF(AND(BH78=3,BI78=3,FS78<>0),P78,0),2) -> 0 | GM78: =ROUND(O78+X78+Y78,2)+GX78 -> 140446.28 | GN78: =IF(OR(BI78=0,BI78=1),GM78-GX78,0) -> 140446.28 | GO78: =IF(BI78=2,GM78-GX78,0) -> 0 | GP78: =IF(BI78=4,GM78-GX78,0) -> 0 | GR78: 0 | GS78: 3 | GT78: 0 | GV78: =ROUND((GT78),6) -> 0 | GW78: 1 | GX78: =ROUND(HC78*I78,2) -> 0 | HA78: 0 | HB78: 0 | HC78: =GV78*GW78 -> 0 | HS78: 0 | IK78: 0
A79: 18 | B79: 1 | C79: 10 | E79: 3,2 | F79: 1.1-1-1121 | G79: Уголок равнополочный, для строительных стальных конструкций, ширина полки более 70 мм, сталь С235, С245 | H79: т | I79: =I75*J79 -> 2.5828 | J79: 0.54579265 | K79: 0.5457927 | O79: =ROUND(CP79,2) -> 25476.74 | P79: =ROUND((ROUND((AC79*AW79*I79),2)*BC79),2) -> 25476.74 | Q79: =(ROUND((ROUND(((ET79)*AV79*I79),2)*BB79),2)+ROUND((ROUND(((AE79-(EU79))*AV79*I79),2)*BS79),2)) -> 0 | R79: =ROUND((ROUND((AE79*AV79*I79),2)*BS79),2) -> 0 | S79: =ROUND((ROUND((AF79*AV79*I79),2)*BA79),2) -> 0 | T79: =ROUND(CU79*I79,2) -> 0 | U79: =CV79*I79 -> 0 | V79: =CW79*I79 -> 0 | W79: =ROUND(CX79*I79,2) -> 0 | X79: =ROUND(CY79,2) -> 0 | Y79: =ROUND(CZ79,2) -> 0 | AA79: 56481265 | AB79: =ROUND((AC79+AD79+AF79),6) -> 9844.31 | AC79: =ROUND((ES79),6) -> 9844.31 | AD79: =ROUND((((ET79)-(EU79))+AE79),6) -> 0 | AE79: =ROUND((EU79),6) -> 0 | AF79: =ROUND((EV79),6) -> 0 | AG79: =ROUND((AP79),6) -> 0 | AH79: =(EW79) -> 0 | AI79: =(EX79) -> 0 | AJ79: =(AS79) -> 0 | AK79: 9844.31 | AL79: 9844.31 | AM79: 0 | AN79: 0 | AO79: 0 | AP79: 0 | AQ79: 0 | AR79: 0 | AS79: 0 | AT79: 92 | AU79: 52 | AV79: 1 | AW79: 1.002 | AZ79: 1 | BA79: 1 | BB79: 1 | BC79: 1 | BH79: 3 | BI79: 1 | BJ79: ТСН-2001.1 Доп. 79, Р. 1, о. 1, поз. 1121 | BM79: 90 | BN79: 0 | BP79: 0 | BQ79: 60 | BR79: 0 | BS79: 1 | BT79: 1 | BU79: 1 | BV79: 1 | BW79: 1 | BX79: 1 | BZ79: 92 | CA79: 52 | CE79: 30 | CF79: 0 | CG79: 0 | CM79: 0 | CO79: 0 | CP79: =(P79+Q79+S79) -> 25476.74 | CQ79: =ROUND((ROUND((AC79*AW79*1),2)*BC79),2) -> 9864 | CR79: =(ROUND((ROUND(((ET79)*AV79*1),2)*BB79),2)+ROUND((ROUND(((AE79-(EU79))*AV79*1),2)*BS79),2)) -> 0 | CS79: =ROUND((ROUND((AE79*AV79*1),2)*BS79),2) -> 0 | CT79: =ROUND((ROUND((AF79*AV79*1),2)*BA79),2) -> 0 | CU79: =AG79 -> 0 | CV79: =(AH79*AV79) -> 0 | CW79: =AI79 -> 0 | CX79: =AJ79 -> 0 | CY79: =(((S79+R79)*AT79)/100) -> 0 | CZ79: =(((S79+R79)*AU79)/100) -> 0 | DN79: 0 | DO79: 0 | DP79: 1 | DQ79: 1 | DU79: 1009 | DV79: т | DW79: т | DX79: 1000 | EE79: 55586525 | EF79: 60 | EG79: Ремонтно-строительные работы | EH79: 0 | EJ79: 1 | EK79: 90 | EL79: ТСН-2001.6-53. Стены | EM79: ТСН-2001.6-53-1 | EQ79: 0 | ER79: 9844.31 | ES79: 9844.31 | ET79: 0 | EU79: 0 | EV79: 0 | EW79: 0 | EX79: 0 | FQ79: 0 | FR79: 0 | FS79: 0 | FX79: 92 | FY79: 52 | GD79: 1 | GF79: 981881691 | GG79: 2 | GH79: 1 | GI79: -2 | GJ79: 0 | GK79: 0 | GL79: =ROUND(IF(AND(BH79=3,BI79=3,FS79<>0),P79,0),2) -> 0 | GM79: =ROUND(O79+X79+Y79,2)+GX79 -> 25476.74 | GN79: =IF(OR(BI79=0,BI79=1),GM79-GX79,0) -> 25476.74 | GO79: =IF(BI79=2,GM79-GX79,0) -> 0 | GP79: =IF(BI79=4,GM79-GX79,0) -> 0 | GR79: 0 | GS79: 3 | GT79: 0 | GV79: =ROUND((GT79),6) -> 0 | GW79: 1 | GX79: =ROUND(HC79*I79,2) -> 0 | HA79: 0 | HB79: 0 | HC79: =GV79*GW79 -> 0 | HS79: 0 | IK79: 0
A80: 18 | B80: 1 | C80: 15 | E80: 3,2 | F80: 1.1-1-1121 | G80: Уголок равнополочный, для строительных стальных конструкций, ширина полки более 70 мм, сталь С235, С245 | H80: т | I80: =I76*J80 -> 2.5828 | J80: 0.54579265 | K80: 0.5457927 | O80: =ROUND(CP80,2) -> 192094.62 | P80: =ROUND((ROUND((AC80*AW80*I80),2)*BC80),2) -> 192094.62 | Q80: =(ROUND((ROUND(((ET80)*AV80*I80),2)*BB80),2)+ROUND((ROUND(((AE80-(EU80))*AV80*I80),2)*BS80),2)) -> 0 | R80: =ROUND((ROUND((AE80*AV80*I80),2)*BS80),2) -> 0 | S80: =ROUND((ROUND((AF80*AV80*I80),2)*BA80),2) -> 0 | T80: =ROUND(CU80*I80,2) -> 0 | U80: =CV80*I80 -> 0 | V80: =CW80*I80 -> 0 | W80: =ROUND(CX80*I80,2) -> 0 | X80: =ROUND(CY80,2) -> 0 | Y80: =ROUND(CZ80,2) -> 0 | AA80: 56481267 | AB80: =ROUND((AC80+AD80+AF80),6) -> 9844.31 | AC80: =ROUND((ES80),6) -> 9844.31 | AD80: =ROUND((((ET80)-(EU80))+AE80),6) -> 0 | AE80: =ROUND((EU80),6) -> 0 | AF80: =ROUND((EV80),6) -> 0 | AG80: =ROUND((AP80),6) -> 0 | AH80: =(EW80) -> 0 | AI80: =(EX80) -> 0 | AJ80: =(AS80) -> 0 | AK80: 9844.31 | AL80: 9844.31 | AM80: 0 | AN80: 0 | AO80: 0 | AP80: 0 | AQ80: 0 | AR80: 0 | AS80: 0 | AT80: 92 | AU80: 52 | AV80: 1 | AW80: 1.002 | AZ80: 1 | BA80: 1 | BB80: 1 | BC80: 7.54 | BH80: 3 | BI80: 1 | BJ80: ТСН-2001.1 Доп. 79, Р. 1, о. 1, поз. 1121 | BM80: 90 | BN80: 0 | BO80: 1.1-1-1121 | BP80: 1 | BQ80: 60 | BR80: 0 | BS80: 1 | BT80: 1 | BU80: 1 | BV80: 1 | BW80: 1 | BX80: 1 | BZ80: 92 | CA80: 52 | CE80: 30 | CF80: 0 | CG80: 0 | CM80: 0 | CO80: 0 | CP80: =(P80+Q80+S80) -> 192094.62 | CQ80: =ROUND((ROUND((AC80*AW80*1),2)*BC80),2) -> 74374.56 | CR80: =(ROUND((ROUND(((ET80)*AV80*1),2)*BB80),2)+ROUND((ROUND(((AE80-(EU80))*AV80*1),2)*BS80),2)) -> 0 | CS80: =ROUND((ROUND((AE80*AV80*1),2)*BS80),2) -> 0 | CT80: =ROUND((ROUND((AF80*AV80*1),2)*BA80),2) -> 0 | CU80: =AG80 -> 0 | CV80: =(AH80*AV80) -> 0 | CW80: =AI80 -> 0 | CX80: =AJ80 -> 0 | CY80: =(((S80+R80)*AT80)/100) -> 0 | CZ80: =(((S80+R80)*AU80)/100) -> 0 | DN80: 0 | DO80: 0 | DP80: 1 | DQ80: 1 | DU80: 1009 | DV80: т | DW80: т | DX80: 1000 | EE80: 55586525 | EF80: 60 | EG80: Ремонтно-строительные работы | EH80: 0 | EJ80: 1 | EK80: 90 | EL80: ТСН-2001.6-53. Стены | EM80: ТСН-2001.6-53-1 | EQ80: 0 | ER80: 9844.31 | ES80: 9844.31 | ET80: 0 | EU80: 0 | EV80: 0 | EW80: 0 | EX80: 0 | FQ80: 0 | FR80: 0 | FS80: 0 | FX80: 92 | FY80: 52 | GD80: 1 | GF80: 981881691 | GG80: 2 | GH80: 1 | GI80: 2 | GJ80: 0 | GK80: 0 | GL80: =ROUND(IF(AND(BH80=3,BI80=3,FS80<>0),P80,0),2) -> 0 | GM80: =ROUND(O80+X80+Y80,2)+GX80 -> 192094.62 | GN80: =IF(OR(BI80=0,BI80=1),GM80-GX80,0) -> 192094.62 | GO80: =IF(BI80=2,GM80-GX80,0) -> 0 | GP80: =IF(BI80=4,GM80-GX80,0) -> 0 | GR80: 0 | GS80: 3 | GT80: 0 | GV80: =ROUND((GT80),6) -> 0 | GW80: 1 | GX80: =ROUND(HC80*I80,2) -> 0 | HA80: 0 | HB80: 0 | HC80: =GV80*GW80 -> 0 | HS80: 0 | IK80: 0
A81: 18 | B81: 1 | C81: 9 | E81: 3,3 | F81: 1.1-1-1105 | G81: Прокат листовой из стали С235, С245 для строительных стальных конструкций, толщина более 3 мм | H81: т | I81: =I75*J81 -> 0.6622 | J81: 0.13993491 | K81: 0.139935 | O81: =ROUND(CP81,2) -> 4325.65 | P81: =ROUND((ROUND((AC81*AW81*I81),2)*BC81),2) -> 4325.65 | Q81: =(ROUND((ROUND(((ET81)*AV81*I81),2)*BB81),2)+ROUND((ROUND(((AE81-(EU81))*AV81*I81),2)*BS81),2)) -> 0 | R81: =ROUND((ROUND((AE81*AV81*I81),2)*BS81),2) -> 0 | S81: =ROUND((ROUND((AF81*AV81*I81),2)*BA81),2) -> 0 | T81: =ROUND(CU81*I81,2) -> 0 | U81: =CV81*I81 -> 0 | V81: =CW81*I81 -> 0 | W81: =ROUND(CX81*I81,2) -> 0 | X81: =ROUND(CY81,2) -> 0 | Y81: =ROUND(CZ81,2) -> 0 | AA81: 56481265 | AB81: =ROUND((AC81+AD81+AF81),6) -> 6519.2 | AC81: =ROUND((ES81),6) -> 6519.2 | AD81: =ROUND((((ET81)-(EU81))+AE81),6) -> 0 | AE81: =ROUND((EU81),6) -> 0 | AF81: =ROUND((EV81),6) -> 0 | AG81: =ROUND((AP81),6) -> 0 | AH81: =(EW81) -> 0 | AI81: =(EX81) -> 0 | AJ81: =(AS81) -> 0 | AK81: 6519.2 | AL81: 6519.2 | AM81: 0 | AN81: 0 | AO81: 0 | AP81: 0 | AQ81: 0 | AR81: 0 | AS81: 0 | AT81: 92 | AU81: 52 | AV81: 1 | AW81: 1.002 | AZ81: 1 | BA81: 1 | BB81: 1 | BC81: 1 | BH81: 3 | BI81: 1 | BJ81: ТСН-2001.1 Доп. 79, Р. 1, о. 1, поз. 1105 | BM81: 90 | BN81: 0 | BP81: 0 | BQ81: 60 | BR81: 0 | BS81: 1 | BT81: 1 | BU81: 1 | BV81: 1 | BW81: 1 | BX81: 1 | BZ81: 92 | CA81: 52 | CE81: 30 | CF81: 0 | CG81: 0 | CM81: 0 | CO81: 0 | CP81: =(P81+Q81+S81) -> 4325.65 | CQ81: =ROUND((ROUND((AC81*AW81*1),2)*BC81),2) -> 6532.24 | CR81: =(ROUND((ROUND(((ET81)*AV81*1),2)*BB81),2)+ROUND((ROUND(((AE81-(EU81))*AV81*1),2)*BS81),2)) -> 0 | CS81: =ROUND((ROUND((AE81*AV81*1),2)*BS81),2) -> 0 | CT81: =ROUND((ROUND((AF81*AV81*1),2)*BA81),2) -> 0 | CU81: =AG81 -> 0 | CV81: =(AH81*AV81) -> 0 | CW81: =AI81 -> 0 | CX81: =AJ81 -> 0 | CY81: =(((S81+R81)*AT81)/100) -> 0 | CZ81: =(((S81+R81)*AU81)/100) -> 0 | DN81: 0 | DO81: 0 | DP81: 1 | DQ81: 1 | DU81: 1009 | DV81: т | DW81: т | DX81: 1000 | EE81: 55586525 | EF81: 60 | EG81: Ремонтно-строительные работы | EH81: 0 | EJ81: 1 | EK81: 90 | EL81: ТСН-2001.6-53. Стены | EM81: ТСН-2001.6-53-1 | EQ81: 0 | ER81: 6519.2 | ES81: 6519.2 | ET81: 0 | EU81: 0 | EV81: 0 | EW81: 0 | EX81: 0 | FQ81: 0 | FR81: 0 | FS81: 0 | FX81: 92 | FY81: 52 | GD81: 1 | GF81: -1891961884 | GG81: 2 | GH81: 1 | GI81: -2 | GJ81: 0 | GK81: 0 | GL81: =ROUND(IF(AND(BH81=3,BI81=3,FS81<>0),P81,0),2) -> 0 | GM81: =ROUND(O81+X81+Y81,2)+GX81 -> 4325.65 | GN81: =IF(OR(BI81=0,BI81=1),GM81-GX81,0) -> 4325.65 | GO81: =IF(BI81=2,GM81-GX81,0) -> 0 | GP81: =IF(BI81=4,GM81-GX81,0) -> 0 | GR81: 0 | GS81: 3 | GT81: 0 | GV81: =ROUND((GT81),6) -> 0 | GW81: 1 | GX81: =ROUND(HC81*I81,2) -> 0 | HA81: 0 | HB81: 0 | HC81: =GV81*GW81 -> 0 | HS81: 0 | IK81: 0
A82: 18 | B82: 1 | C82: 14 | E82: 3,3 | F82: 1.1-1-1105 | G82: Прокат листовой из стали С235, С245 для строительных стальных конструкций, толщина более 3 мм | H82: т | I82: =I76*J82 -> 0.6622 | J82: 0.13993491 | K82: 0.139935 | O82: =ROUND(CP82,2) -> 43775.58 | P82: =ROUND((ROUND((AC82*AW82*I82),2)*BC82),2) -> 43775.58 | Q82: =(ROUND((ROUND(((ET82)*AV82*I82),2)*BB82),2)+ROUND((ROUND(((AE82-(EU82))*AV82*I82),2)*BS82),2)) -> 0 | R82: =ROUND((ROUND((AE82*AV82*I82),2)*BS82),2) -> 0 | S82: =ROUND((ROUND((AF82*AV82*I82),2)*BA82),2) -> 0 | T82: =ROUND(CU82*I82,2) -> 0 | U82: =CV82*I82 -> 0 | V82: =CW82*I82 -> 0 | W82: =ROUND(CX82*I82,2) -> 0 | X82: =ROUND(CY82,2) -> 0 | Y82: =ROUND(CZ82,2) -> 0 | AA82: 56481267 | AB82: =ROUND((AC82+AD82+AF82),6) -> 6519.2 | AC82: =ROUND((ES82),6) -> 6519.2 | AD82: =ROUND((((ET82)-(EU82))+AE82),6) -> 0 | AE82: =ROUND((EU82),6) -> 0 | AF82: =ROUND((EV82),6) -> 0 | AG82: =ROUND((AP82),6) -> 0 | AH82: =(EW82) -> 0 | AI82: =(EX82) -> 0 | AJ82: =(AS82) -> 0 | AK82: 6519.2 | AL82: 6519.2 | AM82: 0 | AN82: 0 | AO82: 0 | AP82: 0 | AQ82: 0 | AR82: 0 | AS82: 0 | AT82: 92 | AU82: 52 | AV82: 1 | AW82: 1.002 | AZ82: 1 | BA82: 1 | BB82: 1 | BC82: 10.12 | BH82: 3 | BI82: 1 | BJ82: ТСН-2001.1 Доп. 79, Р. 1, о. 1, поз. 1105 | BM82: 90 | BN82: 0 | BO82: 1.1-1-1105 | BP82: 1 | BQ82: 60 | BR82: 0 | BS82: 1 | BT82: 1 | BU82: 1 | BV82: 1 | BW82: 1 | BX82: 1 | BZ82: 92 | CA82: 52 | CE82: 30 | CF82: 0 | CG82: 0 | CM82: 0 | CO82: 0 | CP82: =(P82+Q82+S82) -> 43775.58 | CQ82: =ROUND((ROUND((AC82*AW82*1),2)*BC82),2) -> 66106.27 | CR82: =(ROUND((ROUND(((ET82)*AV82*1),2)*BB82),2)+ROUND((ROUND(((AE82-(EU82))*AV82*1),2)*BS82),2)) -> 0 | CS82: =ROUND((ROUND((AE82*AV82*1),2)*BS82),2) -> 0 | CT82: =ROUND((ROUND((AF82*AV82*1),2)*BA82),2) -> 0 | CU82: =AG82 -> 0 | CV82: =(AH82*AV82) -> 0 | CW82: =AI82 -> 0 | CX82: =AJ82 -> 0 | CY82: =(((S82+R82)*AT82)/100) -> 0 | CZ82: =(((S82+R82)*AU82)/100) -> 0 | DN82: 0 | DO82: 0 | DP82: 1 | DQ82: 1 | DU82: 1009 | DV82: т | DW82: т | DX82: 1000 | EE82: 55586525 | EF82: 60 | EG82: Ремонтно-строительные работы | EH82: 0 | EJ82: 1 | EK82: 90 | EL82: ТСН-2001.6-53. Стены | EM82: ТСН-2001.6-53-1 | EQ82: 0 | ER82: 6519.2 | ES82: 6519.2 | ET82: 0 | EU82: 0 | EV82: 0 | EW82: 0 | EX82: 0 | FQ82: 0 | FR82: 0 | FS82: 0 | FX82: 92 | FY82: 52 | GD82: 1 | GF82: -1891961884 | GG82: 2 | GH82: 1 | GI82: 2 | GJ82: 0 | GK82: 0 | GL82: =ROUND(IF(AND(BH82=3,BI82=3,FS82<>0),P82,0),2) -> 0 | GM82: =ROUND(O82+X82+Y82,2)+GX82 -> 43775.58 | GN82: =IF(OR(BI82=0,BI82=1),GM82-GX82,0) -> 43775.58 | GO82: =IF(BI82=2,GM82-GX82,0) -> 0 | GP82: =IF(BI82=4,GM82-GX82,0) -> 0 | GR82: 0 | GS82: 3 | GT82: 0 | GV82: =ROUND((GT82),6) -> 0 | GW82: 1 | GX82: =ROUND(HC82*I82,2) -> 0 | HA82: 0 | HB82: 0 | HC82: =GV82*GW82 -> 0 | HS82: 0 | IK82: 0
A83: 18 | B83: 1 | C83: 12 | E83: 3,4 | F83: 1.7-5-220 | G83: Шпилька резьбовая, стальная, оцинкованная, с заостренным концом, в комплекте с шайбой и гайкой, М16x190 мм | H83: шт. | I83: =I75*J83 -> 176 | J83: 37.192004 | K83: 37.192004 | O83: =ROUND(CP83,2) -> 5255.29 | P83: =ROUND((ROUND((AC83*AW83*I83),2)*BC83),2) -> 5255.29 | Q83: =(ROUND((ROUND(((ET83)*AV83*I83),2)*BB83),2)+ROUND((ROUND(((AE83-(EU83))*AV83*I83),2)*BS83),2)) -> 0 | R83: =ROUND((ROUND((AE83*AV83*I83),2)*BS83),2) -> 0 | S83: =ROUND((ROUND((AF83*AV83*I83),2)*BA83),2) -> 0 | T83: =ROUND(CU83*I83,2) -> 0 | U83: =CV83*I83 -> 0 | V83: =CW83*I83 -> 0 | W83: =ROUND(CX83*I83,2) -> 0 | X83: =ROUND(CY83,2) -> 0 | Y83: =ROUND(CZ83,2) -> 0 | AA83: 56481265 | AB83: =ROUND((AC83+AD83+AF83),6) -> 29.8 | AC83: =ROUND((ES83),6) -> 29.8 | AD83: =ROUND((((ET83)-(EU83))+AE83),6) -> 0 | AE83: =ROUND((EU83),6) -> 0 | AF83: =ROUND((EV83),6) -> 0 | AG83: =ROUND((AP83),6) -> 0 | AH83: =(EW83) -> 0 | AI83: =(EX83) -> 0 | AJ83: =(AS83) -> 0 | AK83: 29.8 | AL83: 29.8 | AM83: 0 | AN83: 0 | AO83: 0 | AP83: 0 | AQ83: 0 | AR83: 0 | AS83: 0 | AT83: 92 | AU83: 52 | AV83: 1 | AW83: 1.002 | AZ83: 1 | BA83: 1 | BB83: 1 | BC83: 1 | BH83: 3 | BI83: 1 | BJ83: ТСН-2001.1 Доп. 53, Р. 7, о. 5, поз. 220 | BM83: 90 | BN83: 0 | BP83: 0 | BQ83: 60 | BR83: 0 | BS83: 1 | BT83: 1 | BU83: 1 | BV83: 1 | BW83: 1 | BX83: 1 | BZ83: 92 | CA83: 52 | CE83: 30 | CF83: 0 | CG83: 0 | CM83: 0 | CO83: 0 | CP83: =(P83+Q83+S83) -> 5255.29 | CQ83: =ROUND((ROUND((AC83*AW83*1),2)*BC83),2) -> 29.86 | CR83: =(ROUND((ROUND(((ET83)*AV83*1),2)*BB83),2)+ROUND((ROUND(((AE83-(EU83))*AV83*1),2)*BS83),2)) -> 0 | CS83: =ROUND((ROUND((AE83*AV83*1),2)*BS83),2) -> 0 | CT83: =ROUND((ROUND((AF83*AV83*1),2)*BA83),2) -> 0 | CU83: =AG83 -> 0 | CV83: =(AH83*AV83) -> 0 | CW83: =AI83 -> 0 | CX83: =AJ83 -> 0 | CY83: =(((S83+R83)*AT83)/100) -> 0 | CZ83: =(((S83+R83)*AU83)/100) -> 0 | DN83: 0 | DO83: 0 | DP83: 1 | DQ83: 1 | DU83: 1010 | DV83: шт. | DW83: шт. | DX83: 1 | EE83: 55586525 | EF83: 60 | EG83: Ремонтно-строительные работы | EH83: 0 | EJ83: 1 | EK83: 90 | EL83: ТСН-2001.6-53. Стены | EM83: ТСН-2001.6-53-1 | EQ83: 0 | ER83: 29.8 | ES83: 29.8 | ET83: 0 | EU83: 0 | EV83: 0 | EW83: 0 | EX83: 0 | FQ83: 0 | FR83: 0 | FS83: 0 | FX83: 92 | FY83: 52 | GD83: 1 | GF83: 2014927073 | GG83: 2 | GH83: 1 | GI83: -2 | GJ83: 0 | GK83: 0 | GL83: =ROUND(IF(AND(BH83=3,BI83=3,FS83<>0),P83,0),2) -> 0 | GM83: =ROUND(O83+X83+Y83,2)+GX83 -> 5255.29 | GN83: =IF(OR(BI83=0,BI83=1),GM83-GX83,0) -> 5255.29 | GO83: =IF(BI83=2,GM83-GX83,0) -> 0 | GP83: =IF(BI83=4,GM83-GX83,0) -> 0 | GR83: 0 | GS83: 3 | GT83: 0 | GV83: =ROUND((GT83),6) -> 0 | GW83: 1 | GX83: =ROUND(HC83*I83,2) -> 0 | HA83: 0 | HB83: 0 | HC83: =GV83*GW83 -> 0 | HS83: 0 | IK83: 0
A84: 18 | B84: 1 | C84: 17 | E84: 3,4 | F84: 1.7-5-220 | G84: Шпилька резьбовая, стальная, оцинкованная, с заостренным концом, в комплекте с шайбой и гайкой, М16x190 мм | H84: шт. | I84: =I76*J84 -> 176 | J84: 37.192004 | K84: 37.192004 | O84: =ROUND(CP84,2) -> 62905.82 | P84: =ROUND((ROUND((AC84*AW84*I84),2)*BC84),2) -> 62905.82 | Q84: =(ROUND((ROUND(((ET84)*AV84*I84),2)*BB84),2)+ROUND((ROUND(((AE84-(EU84))*AV84*I84),2)*BS84),2)) -> 0 | R84: =ROUND((ROUND((AE84*AV84*I84),2)*BS84),2) -> 0 | S84: =ROUND((ROUND((AF84*AV84*I84),2)*BA84),2) -> 0 | T84: =ROUND(CU84*I84,2) -> 0 | U84: =CV84*I84 -> 0 | V84: =CW84*I84 -> 0 | W84: =ROUND(CX84*I84,2) -> 0 | X84: =ROUND(CY84,2) -> 0 | Y84: =ROUND(CZ84,2) -> 0 | AA84: 56481267 | AB84: =ROUND((AC84+AD84+AF84),6) -> 29.8 | AC84: =ROUND((ES84),6) -> 29.8 | AD84: =ROUND((((ET84)-(EU84))+AE84),6) -> 0 | AE84: =ROUND((EU84),6) -> 0 | AF84: =ROUND((EV84),6) -> 0 | AG84: =ROUND((AP84),6) -> 0 | AH84: =(EW84) -> 0 | AI84: =(EX84) -> 0 | AJ84: =(AS84) -> 0 | AK84: 29.8 | AL84: 29.8 | AM84: 0 | AN84: 0 | AO84: 0 | AP84: 0 | AQ84: 0 | AR84: 0 | AS84: 0 | AT84: 92 | AU84: 52 | AV84: 1 | AW84: 1.002 | AZ84: 1 | BA84: 1 | BB84: 1 | BC84: 11.97 | BH84: 3 | BI84: 1 | BJ84: ТСН-2001.1 Доп. 53, Р. 7, о. 5, поз. 220 | BM84: 90 | BN84: 0 | BO84: 1.7-5-220 | BP84: 1 | BQ84: 60 | BR84: 0 | BS84: 1 | BT84: 1 | BU84: 1 | BV84: 1 | BW84: 1 | BX84: 1 | BZ84: 92 | CA84: 52 | CE84: 30 | CF84: 0 | CG84: 0 | CM84: 0 | CO84: 0 | CP84: =(P84+Q84+S84) -> 62905.82 | CQ84: =ROUND((ROUND((AC84*AW84*1),2)*BC84),2) -> 357.42 | CR84: =(ROUND((ROUND(((ET84)*AV84*1),2)*BB84),2)+ROUND((ROUND(((AE84-(EU84))*AV84*1),2)*BS84),2)) -> 0 | CS84: =ROUND((ROUND((AE84*AV84*1),2)*BS84),2) -> 0 | CT84: =ROUND((ROUND((AF84*AV84*1),2)*BA84),2) -> 0 | CU84: =AG84 -> 0 | CV84: =(AH84*AV84) -> 0 | CW84: =AI84 -> 0 | CX84: =AJ84 -> 0 | CY84: =(((S84+R84)*AT84)/100) -> 0 | CZ84: =(((S84+R84)*AU84)/100) -> 0 | DN84: 0 | DO84: 0 | DP84: 1 | DQ84: 1 | DU84: 1010 | DV84: шт. | DW84: шт. | DX84: 1 | EE84: 55586525 | EF84: 60 | EG84: Ремонтно-строительные работы | EH84: 0 | EJ84: 1 | EK84: 90 | EL84: ТСН-2001.6-53. Стены | EM84: ТСН-2001.6-53-1 | EQ84: 0 | ER84: 29.8 | ES84: 29.8 | ET84: 0 | EU84: 0 | EV84: 0 | EW84: 0 | EX84: 0 | FQ84: 0 | FR84: 0 | FS84: 0 | FX84: 92 | FY84: 52 | GD84: 1 | GF84: 2014927073 | GG84: 2 | GH84: 1 | GI84: 2 | GJ84: 0 | GK84: 0 | GL84: =ROUND(IF(AND(BH84=3,BI84=3,FS84<>0),P84,0),2) -> 0 | GM84: =ROUND(O84+X84+Y84,2)+GX84 -> 62905.82 | GN84: =IF(OR(BI84=0,BI84=1),GM84-GX84,0) -> 62905.82 | GO84: =IF(BI84=2,GM84-GX84,0) -> 0 | GP84: =IF(BI84=4,GM84-GX84,0) -> 0 | GR84: 0 | GS84: 3 | GT84: 0 | GV84: =ROUND((GT84),6) -> 0 | GW84: 1 | GX84: =ROUND(HC84*I84,2) -> 0 | HA84: 0 | HB84: 0 | HC84: =GV84*GW84 -> 0 | HS84: 0 | IK84: 0
A85: 18 | B85: 1 | C85: 13 | E85: 3,5 | F85: 1.7-5-233 | G85: Анкер-болт забивной, распорный, стальной, оцинкованный, с широкой шайбой M12х110 | H85: 100 шт. | I85: =I75*J85 -> 0.88 | J85: 0.18596002 | K85: 0.18596 | O85: =ROUND(CP85,2) -> 493.82 | P85: =ROUND((ROUND((AC85*AW85*I85),2)*BC85),2) -> 493.82 | Q85: =(ROUND((ROUND(((ET85)*AV85*I85),2)*BB85),2)+ROUND((ROUND(((AE85-(EU85))*AV85*I85),2)*BS85),2)) -> 0 | R85: =ROUND((ROUND((AE85*AV85*I85),2)*BS85),2) -> 0 | S85: =ROUND((ROUND((AF85*AV85*I85),2)*BA85),2) -> 0 | T85: =ROUND(CU85*I85,2) -> 0 | U85: =CV85*I85 -> 0 | V85: =CW85*I85 -> 0 | W85: =ROUND(CX85*I85,2) -> 0 | X85: =ROUND(CY85,2) -> 0 | Y85: =ROUND(CZ85,2) -> 0 | AA85: 56481265 | AB85: =ROUND((AC85+AD85+AF85),6) -> 560.04 | AC85: =ROUND((ES85),6) -> 560.04 | AD85: =ROUND((((ET85)-(EU85))+AE85),6) -> 0 | AE85: =ROUND((EU85),6) -> 0 | AF85: =ROUND((EV85),6) -> 0 | AG85: =ROUND((AP85),6) -> 0 | AH85: =(EW85) -> 0 | AI85: =(EX85) -> 0 | AJ85: =(AS85) -> 0 | AK85: 560.04 | AL85: 560.04 | AM85: 0 | AN85: 0 | AO85: 0 | AP85: 0 | AQ85: 0 | AR85: 0 | AS85: 0 | AT85: 92 | AU85: 52 | AV85: 1 | AW85: 1.002 | AZ85: 1 | BA85: 1 | BB85: 1 | BC85: 1 | BH85: 3 | BI85: 1 | BJ85: ТСН-2001.1 Доп. 79, Р. 7, о. 5, поз. 233 | BM85: 90 | BN85: 0 | BP85: 0 | BQ85: 60 | BR85: 0 | BS85: 1 | BT85: 1 | BU85: 1 | BV85: 1 | BW85: 1 | BX85: 1 | BZ85: 92 | CA85: 52 | CE85: 30 | CF85: 0 | CG85: 0 | CM85: 0 | CO85: 0 | CP85: =(P85+Q85+S85) -> 493.82 | CQ85: =ROUND((ROUND((AC85*AW85*1),2)*BC85),2) -> 561.16 | CR85: =(ROUND((ROUND(((ET85)*AV85*1),2)*BB85),2)+ROUND((ROUND(((AE85-(EU85))*AV85*1),2)*BS85),2)) -> 0 | CS85: =ROUND((ROUND((AE85*AV85*1),2)*BS85),2) -> 0 | CT85: =ROUND((ROUND((AF85*AV85*1),2)*BA85),2) -> 0 | CU85: =AG85 -> 0 | CV85: =(AH85*AV85) -> 0 | CW85: =AI85 -> 0 | CX85: =AJ85 -> 0 | CY85: =(((S85+R85)*AT85)/100) -> 0 | CZ85: =(((S85+R85)*AU85)/100) -> 0 | DN85: 0 | DO85: 0 | DP85: 1 | DQ85: 1 | DU85: 1010 | DV85: 100 шт. | DW85: 100 шт. | DX85: 100 | EE85: 55586525 | EF85: 60 | EG85: Ремонтно-строительные работы | EH85: 0 | EJ85: 1 | EK85: 90 | EL85: ТСН-2001.6-53. Стены | EM85: ТСН-2001.6-53-1 | EQ85: 0 | ER85: 560.04 | ES85: 560.04 | ET85: 0 | EU85: 0 | EV85: 0 | EW85: 0 | EX85: 0 | FQ85: 0 | FR85: 0 | FS85: 0 | FX85: 92 | FY85: 52 | GD85: 1 | GF85: 856224882 | GG85: 2 | GH85: 1 | GI85: -2 | GJ85: 0 | GK85: 0 | GL85: =ROUND(IF(AND(BH85=3,BI85=3,FS85<>0),P85,0),2) -> 0 | GM85: =ROUND(O85+X85+Y85,2)+GX85 -> 493.82 | GN85: =IF(OR(BI85=0,BI85=1),GM85-GX85,0) -> 493.82 | GO85: =IF(BI85=2,GM85-GX85,0) -> 0 | GP85: =IF(BI85=4,GM85-GX85,0) -> 0 | GR85: 0 | GS85: 3 | GT85: 0 | GV85: =ROUND((GT85),6) -> 0 | GW85: 1 | GX85: =ROUND(HC85*I85,2) -> 0 | HA85: 0 | HB85: 0 | HC85: =GV85*GW85 -> 0 | HS85: 0 | IK85: 0
A86: 18 | B86: 1 | C86: 18 | E86: 3,5 | F86: 1.7-5-233 | G86: Анкер-болт забивной, распорный, стальной, оцинкованный, с широкой шайбой M12х110 | H86: 100 шт. | I86: =I76*J86 -> 0.88 | J86: 0.18596002 | K86: 0.18596 | O86: =ROUND(CP86,2) -> 9708.5 | P86: =ROUND((ROUND((AC86*AW86*I86),2)*BC86),2) -> 9708.5 | Q86: =(ROUND((ROUND(((ET86)*AV86*I86),2)*BB86),2)+ROUND((ROUND(((AE86-(EU86))*AV86*I86),2)*BS86),2)) -> 0 | R86: =ROUND((ROUND((AE86*AV86*I86),2)*BS86),2) -> 0 | S86: =ROUND((ROUND((AF86*AV86*I86),2)*BA86),2) -> 0 | T86: =ROUND(CU86*I86,2) -> 0 | U86: =CV86*I86 -> 0 | V86: =CW86*I86 -> 0 | W86: =ROUND(CX86*I86,2) -> 0 | X86: =ROUND(CY86,2) -> 0 | Y86: =ROUND(CZ86,2) -> 0 | AA86: 56481267 | AB86: =ROUND((AC86+AD86+AF86),6) -> 560.04 | AC86: =ROUND((ES86),6) -> 560.04 | AD86: =ROUND((((ET86)-(EU86))+AE86),6) -> 0 | AE86: =ROUND((EU86),6) -> 0 | AF86: =ROUND((EV86),6) -> 0 | AG86: =ROUND((AP86),6) -> 0 | AH86: =(EW86) -> 0 | AI86: =(EX86) -> 0 | AJ86: =(AS86) -> 0 | AK86: 560.04 | AL86: 560.04 | AM86: 0 | AN86: 0 | AO86: 0 | AP86: 0 | AQ86: 0 | AR86: 0 | AS86: 0 | AT86: 92 | AU86: 52 | AV86: 1 | AW86: 1.002 | AZ86: 1 | BA86: 1 | BB86: 1 | BC86: 19.66 | BH86: 3 | BI86: 1 | BJ86: ТСН-2001.1 Доп. 79, Р. 7, о. 5, поз. 233 | BM86: 90 | BN86: 0 | BO86: 1.7-5-233 | BP86: 1 | BQ86: 60 | BR86: 0 | BS86: 1 | BT86: 1 | BU86: 1 | BV86: 1 | BW86: 1 | BX86: 1 | BZ86: 92 | CA86: 52 | CE86: 30 | CF86: 0 | CG86: 0 | CM86: 0 | CO86: 0 | CP86: =(P86+Q86+S86) -> 9708.5 | CQ86: =ROUND((ROUND((AC86*AW86*1),2)*BC86),2) -> 11032.41 | CR86: =(ROUND((ROUND(((ET86)*AV86*1),2)*BB86),2)+ROUND((ROUND(((AE86-(EU86))*AV86*1),2)*BS86),2)) -> 0 | CS86: =ROUND((ROUND((AE86*AV86*1),2)*BS86),2) -> 0 | CT86: =ROUND((ROUND((AF86*AV86*1),2)*BA86),2) -> 0 | CU86: =AG86 -> 0 | CV86: =(AH86*AV86) -> 0 | CW86: =AI86 -> 0 | CX86: =AJ86 -> 0 | CY86: =(((S86+R86)*AT86)/100) -> 0 | CZ86: =(((S86+R86)*AU86)/100) -> 0 | DN86: 0 | DO86: 0 | DP86: 1 | DQ86: 1 | DU86: 1010 | DV86: 100 шт. | DW86: 100 шт. | DX86: 100 | EE86: 55586525 | EF86: 60 | EG86: Ремонтно-строительные работы | EH86: 0 | EJ86: 1 | EK86: 90 | EL86: ТСН-2001.6-53. Стены | EM86: ТСН-2001.6-53-1 | EQ86: 0 | ER86: 560.04 | ES86: 560.04 | ET86: 0 | EU86: 0 | EV86: 0 | EW86: 0 | EX86: 0 | FQ86: 0 | FR86: 0 | FS86: 0 | FX86: 92 | FY86: 52 | GD86: 1 | GF86: 856224882 | GG86: 2 | GH86: 1 | GI86: 2 | GJ86: 0 | GK86: 0 | GL86: =ROUND(IF(AND(BH86=3,BI86=3,FS86<>0),P86,0),2) -> 0 | GM86: =ROUND(O86+X86+Y86,2)+GX86 -> 9708.5 | GN86: =IF(OR(BI86=0,BI86=1),GM86-GX86,0) -> 9708.5 | GO86: =IF(BI86=2,GM86-GX86,0) -> 0 | GP86: =IF(BI86=4,GM86-GX86,0) -> 0 | GR86: 0 | GS86: 3 | GT86: 0 | GV86: =ROUND((GT86),6) -> 0 | GW86: 1 | GX86: =ROUND(HC86*I86,2) -> 0 | HA86: 0 | HB86: 0 | HC86: =GV86*GW86 -> 0 | HS86: 0 | IK86: 0
A87: 17 | B87: 1 | C87: =ROW(SmtRes!A19) -> 19 | E87: 4 | F87: 3.13-9-2 | G87: Огрунтовка металлических поверхностей грунтовкой ГФ-021 за один раз | H87: 100 м2 | I87: =ROUND((67.6*26.1+106.3*33+4.2*33+6.9*33+7.2*32.1+11.3*21.5+0.9*32.1+1.4*32.1+9.3*32.1)/1000/100*22,9) -> 1.4266978 | J87: 0 | K87: =ROUND((67.6*26.1+106.3*33+4.2*33+6.9*33+7.2*32.1+11.3*21.5+0.9*32.1+1.4*32.1+9.3*32.1)/1000/100*22,9) -> 1.4266978 | O87: =ROUND(CP87,2) -> 174.05 | P87: =ROUND((ROUND((AC87*AW87*I87),2)*BC87),2) -> 13.5 | Q87: =(ROUND((ROUND(((((ET87*1.25)*1.1))*AV87*I87),2)*BB87),2)+ROUND((ROUND(((AE87-(((EU87*1.25)*1.1)))*AV87*I87),2)*BS87),2)) -> 26.76 | R87: =ROUND((ROUND((AE87*AV87*I87),2)*BS87),2) -> 0.49 | S87: =ROUND((ROUND((AF87*AV87*I87),2)*BA87),2) -> 133.79 | T87: =ROUND(CU87*I87,2) -> 0 | U87: =CV87*I87 -> 9.5833431 | V87: =CW87*I87 -> 0 | W87: =ROUND(CX87*I87,2) -> 0 | X87: =ROUND(CY87,2) -> 134.28 | Y87: =ROUND(CZ87,2) -> 85.94 | AA87: 56481265 | AB87: =ROUND((AC87+AD87+AF87),6) -> 121.98945 | AC87: =ROUND((ES87),6) -> 9.46 | AD87: =ROUND((((((ET87*1.25)*1.1))-(((EU87*1.25)*1.1)))+AE87),6) -> 18.755 | AE87: =ROUND((((EU87*1.25)*1.1)),6) -> 0.34375 | AF87: =ROUND((((EV87*1.15)*1.1)),6) -> 93.77445 | AG87: =ROUND((AP87),6) -> 0 | AH87: =(((EW87*1.15)*1.1)) -> 6.71715 | AI87: =(((EX87*1.25)*1.1)) -> 0 | AJ87: =(AS87) -> 0 | AK87: 97.23 | AL87: 9.46 | AM87: 13.64 | AN87: 0.25 | AO87: 74.13 | AP87: 0 | AQ87: 5.31 | AR87: 0 | AS87: 0 | AT87: 100 | AU87: 64 | AV87: 1 | AW87: 1 | AZ87: 1 | BA87: 1 | BB87: 1 | BC87: 1 | BH87: 0 | BI87: 1 | BJ87: ТСН-2001.3 Доп. 71, Сб. 13, т. 9, поз. 2 | BM87: 97 | BN87: 0 | BP87: 0 | BQ87: 60 | BR87: 0 | BS87: 1 | BT87: 1 | BU87: 1 | BV87: 1 | BW87: 1 | BX87: 1 | BZ87: 100 | CA87: 64 | CE87: 30 | CF87: 0 | CG87: 0 | CM87: 0 | CO87: 0 | CP87: =(P87+Q87+S87) -> 174.05 | CQ87: =ROUND((ROUND((AC87*AW87*1),2)*BC87),2) -> 9.46 | CR87: =(ROUND((ROUND(((((ET87*1.25)*1.1))*AV87*1),2)*BB87),2)+ROUND((ROUND(((AE87-(((EU87*1.25)*1.1)))*AV87*1),2)*BS87),2)) -> 18.76 | CS87: =ROUND((ROUND((AE87*AV87*1),2)*BS87),2) -> 0.34 | CT87: =ROUND((ROUND((AF87*AV87*1),2)*BA87),2) -> 93.77 | CU87: =AG87 -> 0 | CV87: =(AH87*AV87) -> 6.71715 | CW87: =AI87 -> 0 | CX87: =AJ87 -> 0 | CY87: =(((S87+R87)*AT87)/100) -> 134.28 | CZ87: =(((S87+R87)*AU87)/100) -> 85.9392 | DE87: *1,25)*1,1 | DF87: *1,25)*1,1 | DG87: *1,15)*1,1 | DI87: *1,15)*1,1 | DJ87: *1,25)*1,1 | DN87: 0 | DO87: 0 | DP87: 1.047 | DQ87: 1 | DU87: 1005 | DV87: 100 м2 | DW87: 100 м2 | DX87: 100 | EE87: 55586532 | EF87: 60 | EG87: Ремонтно-строительные работы | EH87: 0 | EJ87: 1 | EK87: 97 | EL87: ТСН-2001.6-60. Печные работы | EM87: ТСН-2001.6-60-1 | EO87: Поправка: О.П. п.3.4. 6 Поправка: О.П. п.3.4.30.в | EQ87: 0 | ER87: 97.23 | ES87: 9.46 | ET87: 13.64 | EU87: 0.25 | EV87: 74.13 | EW87: 5.31 | EX87: 0 | EY87: 0 | FQ87: 0 | FR87: 0 | FS87: 0 | FX87: 100 | FY87: 64 | GD87: 1 | GF87: -673576059 | GG87: 2 | GH87: 1 | GI87: -2 | GJ87: 0 | GK87: 0 | GL87: =ROUND(IF(AND(BH87=3,BI87=3,FS87<>0),P87,0),2) -> 0 | GM87: =ROUND(O87+X87+Y87,2)+GX87 -> 394.27 | GN87: =IF(OR(BI87=0,BI87=1),GM87-GX87,0) -> 394.27 | GO87: =IF(BI87=2,GM87-GX87,0) -> 0 | GP87: =IF(BI87=4,GM87-GX87,0) -> 0 | GR87: 0 | GS87: 3 | GT87: 0 | GV87: =ROUND((GT87),6) -> 0 | GW87: 1 | GX87: =ROUND(HC87*I87,2) -> 0 | HA87: 0 | HB87: 0 | HC87: =GV87*GW87 -> 0 | HS87: 0 | IK87: 0
A88: 17 | B88: 1 | C88: =ROW(SmtRes!A20) -> 20 | E88: 4 | F88: 3.13-9-2 | G88: Огрунтовка металлических поверхностей грунтовкой ГФ-021 за один раз | H88: 100 м2 | I88: =ROUND((67.6*26.1+106.3*33+4.2*33+6.9*33+7.2*32.1+11.3*21.5+0.9*32.1+1.4*32.1+9.3*32.1)/1000/100*22,9) -> 1.4266978 | J88: 0 | K88: =ROUND((67.6*26.1+106.3*33+4.2*33+6.9*33+7.2*32.1+11.3*21.5+0.9*32.1+1.4*32.1+9.3*32.1)/1000/100*22,9) -> 1.4266978 | O88: =ROUND(CP88,2) -> 7428.5 | P88: =ROUND((ROUND((AC88*AW88*I88),2)*BC88),2) -> 435.38 | Q88: =(ROUND((ROUND(((((ET88*1.25)*1.1))*AV88*I88),2)*BB88),2)+ROUND((ROUND(((AE88-(((EU88*1.25)*1.1)))*AV88*I88),2)*BS88),2)) -> 294.49 | R88: =ROUND((ROUND((AE88*AV88*I88),2)*BS88),2) -> 24.39 | S88: =ROUND((ROUND((AF88*AV88*I88),2)*BA88),2) -> 6698.63 | T88: =ROUND(CU88*I88,2) -> 0 | U88: =CV88*I88 -> 10.03376 | V88: =CW88*I88 -> 0 | W88: =ROUND(CX88*I88,2) -> 0 | X88: =ROUND(CY88,2) -> 5983.49 | Y88: =ROUND(CZ88,2) -> 2958.13 | AA88: 56481267 | AB88: =ROUND((AC88+AD88+AF88),6) -> 121.98945 | AC88: =ROUND((ES88),6) -> 9.46 | AD88: =ROUND((((((ET88*1.25)*1.1))-(((EU88*1.25)*1.1)))+AE88),6) -> 18.755 | AE88: =ROUND((((EU88*1.25)*1.1)),6) -> 0.34375 | AF88: =ROUND((((EV88*1.15)*1.1)),6) -> 93.77445 | AG88: =ROUND((AP88),6) -> 0 | AH88: =(((EW88*1.15)*1.1)) -> 6.71715 | AI88: =(((EX88*1.25)*1.1)) -> 0 | AJ88: =(AS88) -> 0 | AK88: 97.23 | AL88: 9.46 | AM88: 13.64 | AN88: 0.25 | AO88: 74.13 | AP88: 0 | AQ88: 5.31 | AR88: 0 | AS88: 0 | AT88: 89 | AU88: 44 | AV88: 1.047 | AW88: 1 | AZ88: 1 | BA88: 47.82 | BB88: 10.51 | BC88: 32.25 | BH88: 0 | BI88: 1 | BJ88: ТСН-2001.3 Доп. 71, Сб. 13, т. 9, поз. 2 | BM88: 97 | BN88: 0 | BO88: 3.13-9-2 | BP88: 1 | BQ88: 60 | BR88: 0 | BS88: 47.82 | BT88: 1 | BU88: 1 | BV88: 1 | BW88: 1 | BX88: 1 | BZ88: 89 | CA88: 44 | CE88: 30 | CF88: 0 | CG88: 0 | CM88: 0 | CO88: 0 | CP88: =(P88+Q88+S88) -> 7428.5 | CQ88: =ROUND((ROUND((AC88*AW88*1),2)*BC88),2) -> 305.09 | CR88: =(ROUND((ROUND(((((ET88*1.25)*1.1))*AV88*1),2)*BB88),2)+ROUND((ROUND(((AE88-(((EU88*1.25)*1.1)))*AV88*1),2)*BS88),2)) -> 206.42 | CS88: =ROUND((ROUND((AE88*AV88*1),2)*BS88),2) -> 17.22 | CT88: =ROUND((ROUND((AF88*AV88*1),2)*BA88),2) -> 4694.97 | CU88: =AG88 -> 0 | CV88: =(AH88*AV88) -> 7.032856 | CW88: =AI88 -> 0 | CX88: =AJ88 -> 0 | CY88: =(((S88+R88)*AT88)/100) -> 5983.4878 | CZ88: =(((S88+R88)*AU88)/100) -> 2958.1288 | DE88: *1,25)*1,1 | DF88: *1,25)*1,1 | DG88: *1,15)*1,1 | DI88: *1,15)*1,1 | DJ88: *1,25)*1,1 | DN88: 0 | DO88: 0 | DP88: 1 | DQ88: 1 | DU88: 1005 | DV88: 100 м2 | DW88: 100 м2 | DX88: 100 | EE88: 55586532 | EF88: 60 | EG88: Ремонтно-строительные работы | EH88: 0 | EJ88: 1 | EK88: 97 | EL88: ТСН-2001.6-60. Печные работы | EM88: ТСН-2001.6-60-1 | EO88: Поправка: О.П. п.3.4. 6 Поправка: О.П. п.3.4.30.в | EQ88: 0 | ER88: 97.23 | ES88: 9.46 | ET88: 13.64 | EU88: 0.25 | EV88: 74.13 | EW88: 5.31 | EX88: 0 | EY88: 0 | FQ88: 0 | FR88: 0 | FS88: 0 | FX88: 89 | FY88: 44 | GD88: 1 | GF88: -673576059 | GG88: 2 | GH88: 1 | GI88: 2 | GJ88: 0 | GK88: 0 | GL88: =ROUND(IF(AND(BH88=3,BI88=3,FS88<>0),P88,0),2) -> 0 | GM88: =ROUND(O88+X88+Y88,2)+GX88 -> 16370.12 | GN88: =IF(OR(BI88=0,BI88=1),GM88-GX88,0) -> 16370.12 | GO88: =IF(BI88=2,GM88-GX88,0) -> 0 | GP88: =IF(BI88=4,GM88-GX88,0) -> 0 | GR88: 0 | GS88: 0 | GT88: 0 | GV88: =ROUND((GT88),6) -> 0 | GW88: 1 | GX88: =ROUND(HC88*I88,2) -> 0 | HA88: 0 | HB88: 0 | HC88: =GV88*GW88 -> 0 | HS88: 0 | IK88: 0
A89: 18 | B89: 1 | C89: 19 | E89: 4,1 | F89: 1.1-1-165 | G89: Грунтовка глифталевая, типа ГФ-021 | H89: т | I89: =I87*J89 -> 0.01284 | J89: 0.0089998036 | K89: 0.009 | O89: =ROUND(CP89,2) -> 239.6 | P89: =ROUND((ROUND((AC89*AW89*I89),2)*BC89),2) -> 239.6 | Q89: =(ROUND((ROUND(((ET89)*AV89*I89),2)*BB89),2)+ROUND((ROUND(((AE89-(EU89))*AV89*I89),2)*BS89),2)) -> 0 | R89: =ROUND((ROUND((AE89*AV89*I89),2)*BS89),2) -> 0 | S89: =ROUND((ROUND((AF89*AV89*I89),2)*BA89),2) -> 0 | T89: =ROUND(CU89*I89,2) -> 0 | U89: =CV89*I89 -> 0 | V89: =CW89*I89 -> 0 | W89: =ROUND(CX89*I89,2) -> 0 | X89: =ROUND(CY89,2) -> 0 | Y89: =ROUND(CZ89,2) -> 0 | AA89: 56481265 | AB89: =ROUND((AC89+AD89+AF89),6) -> 18660.61 | AC89: =ROUND((ES89),6) -> 18660.61 | AD89: =ROUND((((ET89)-(EU89))+AE89),6) -> 0 | AE89: =ROUND((EU89),6) -> 0 | AF89: =ROUND((EV89),6) -> 0 | AG89: =ROUND((AP89),6) -> 0 | AH89: =(EW89) -> 0 | AI89: =(EX89) -> 0 | AJ89: =(AS89) -> 0 | AK89: 18660.61 | AL89: 18660.61 | AM89: 0 | AN89: 0 | AO89: 0 | AP89: 0 | AQ89: 0 | AR89: 0 | AS89: 0 | AT89: 100 | AU89: 64 | AV89: 1 | AW89: 1 | AZ89: 1 | BA89: 1 | BB89: 1 | BC89: 1 | BH89: 3 | BI89: 1 | BJ89: ТСН-2001.1 Доп. 67, Р. 1, о. 1, поз. 165 | BM89: 97 | BN89: 0 | BP89: 0 | BQ89: 60 | BR89: 0 | BS89: 1 | BT89: 1 | BU89: 1 | BV89: 1 | BW89: 1 | BX89: 1 | BZ89: 100 | CA89: 64 | CE89: 30 | CF89: 0 | CG89: 0 | CM89: 0 | CO89: 0 | CP89: =(P89+Q89+S89) -> 239.6 | CQ89: =ROUND((ROUND((AC89*AW89*1),2)*BC89),2) -> 18660.61 | CR89: =(ROUND((ROUND(((ET89)*AV89*1),2)*BB89),2)+ROUND((ROUND(((AE89-(EU89))*AV89*1),2)*BS89),2)) -> 0 | CS89: =ROUND((ROUND((AE89*AV89*1),2)*BS89),2) -> 0 | CT89: =ROUND((ROUND((AF89*AV89*1),2)*BA89),2) -> 0 | CU89: =AG89 -> 0 | CV89: =(AH89*AV89) -> 0 | CW89: =AI89 -> 0 | CX89: =AJ89 -> 0 | CY89: =(((S89+R89)*AT89)/100) -> 0 | CZ89: =(((S89+R89)*AU89)/100) -> 0 | DN89: 0 | DO89: 0 | DP89: 1.047 | DQ89: 1 | DU89: 1009 | DV89: т | DW89: т | DX89: 1000 | EE89: 55586532 | EF89: 60 | EG89: Ремонтно-строительные работы | EH89: 0 | EJ89: 1 | EK89: 97 | EL89: ТСН-2001.6-60. Печные работы | EM89: ТСН-2001.6-60-1 | EQ89: 0 | ER89: 18660.61 | ES89: 18660.61 | ET89: 0 | EU89: 0 | EV89: 0 | EW89: 0 | EX89: 0 | FQ89: 0 | FR89: 0 | FS89: 0 | FX89: 100 | FY89: 64 | GD89: 1 | GF89: 667244177 | GG89: 2 | GH89: 1 | GI89: -2 | GJ89: 0 | GK89: 0 | GL89: =ROUND(IF(AND(BH89=3,BI89=3,FS89<>0),P89,0),2) -> 0 | GM89: =ROUND(O89+X89+Y89,2)+GX89 -> 239.6 | GN89: =IF(OR(BI89=0,BI89=1),GM89-GX89,0) -> 239.6 | GO89: =IF(BI89=2,GM89-GX89,0) -> 0 | GP89: =IF(BI89=4,GM89-GX89,0) -> 0 | GR89: 0 | GS89: 3 | GT89: 0 | GV89: =ROUND((GT89),6) -> 0 | GW89: 1 | GX89: =ROUND(HC89*I89,2) -> 0 | HA89: 0 | HB89: 0 | HC89: =GV89*GW89 -> 0 | HS89: 0 | IK89: 0
A90: 18 | B90: 1 | C90: 20 | E90: 4,1 | F90: 1.1-1-165 | G90: Грунтовка глифталевая, типа ГФ-021 | H90: т | I90: =I88*J90 -> 0.01284 | J90: 0.0089998036 | K90: 0.009 | O90: =ROUND(CP90,2) -> 857.77 | P90: =ROUND((ROUND((AC90*AW90*I90),2)*BC90),2) -> 857.77 | Q90: =(ROUND((ROUND(((ET90)*AV90*I90),2)*BB90),2)+ROUND((ROUND(((AE90-(EU90))*AV90*I90),2)*BS90),2)) -> 0 | R90: =ROUND((ROUND((AE90*AV90*I90),2)*BS90),2) -> 0 | S90: =ROUND((ROUND((AF90*AV90*I90),2)*BA90),2) -> 0 | T90: =ROUND(CU90*I90,2) -> 0 | U90: =CV90*I90 -> 0 | V90: =CW90*I90 -> 0 | W90: =ROUND(CX90*I90,2) -> 0 | X90: =ROUND(CY90,2) -> 0 | Y90: =ROUND(CZ90,2) -> 0 | AA90: 56481267 | AB90: =ROUND((AC90+AD90+AF90),6) -> 18660.61 | AC90: =ROUND((ES90),6) -> 18660.61 | AD90: =ROUND((((ET90)-(EU90))+AE90),6) -> 0 | AE90: =ROUND((EU90),6) -> 0 | AF90: =ROUND((EV90),6) -> 0 | AG90: =ROUND((AP90),6) -> 0 | AH90: =(EW90) -> 0 | AI90: =(EX90) -> 0 | AJ90: =(AS90) -> 0 | AK90: 18660.61 | AL90: 18660.61 | AM90: 0 | AN90: 0 | AO90: 0 | AP90: 0 | AQ90: 0 | AR90: 0 | AS90: 0 | AT90: 89 | AU90: 44 | AV90: 1 | AW90: 1 | AZ90: 1 | BA90: 1 | BB90: 1 | BC90: 3.58 | BH90: 3 | BI90: 1 | BJ90: ТСН-2001.1 Доп. 67, Р. 1, о. 1, поз. 165 | BM90: 97 | BN90: 0 | BO90: 1.1-1-165 | BP90: 1 | BQ90: 60 | BR90: 0 | BS90: 1 | BT90: 1 | BU90: 1 | BV90: 1 | BW90: 1 | BX90: 1 | BZ90: 89 | CA90: 44 | CE90: 30 | CF90: 0 | CG90: 0 | CM90: 0 | CO90: 0 | CP90: =(P90+Q90+S90) -> 857.77 | CQ90: =ROUND((ROUND((AC90*AW90*1),2)*BC90),2) -> 66804.98 | CR90: =(ROUND((ROUND(((ET90)*AV90*1),2)*BB90),2)+ROUND((ROUND(((AE90-(EU90))*AV90*1),2)*BS90),2)) -> 0 | CS90: =ROUND((ROUND((AE90*AV90*1),2)*BS90),2) -> 0 | CT90: =ROUND((ROUND((AF90*AV90*1),2)*BA90),2) -> 0 | CU90: =AG90 -> 0 | CV90: =(AH90*AV90) -> 0 | CW90: =AI90 -> 0 | CX90: =AJ90 -> 0 | CY90: =(((S90+R90)*AT90)/100) -> 0 | CZ90: =(((S90+R90)*AU90)/100) -> 0 | DN90: 0 | DO90: 0 | DP90: 1 | DQ90: 1 | DU90: 1009 | DV90: т | DW90: т | DX90: 1000 | EE90: 55586532 | EF90: 60 | EG90: Ремонтно-строительные работы | EH90: 0 | EJ90: 1 | EK90: 97 | EL90: ТСН-2001.6-60. Печные работы | EM90: ТСН-2001.6-60-1 | EQ90: 0 | ER90: 18660.61 | ES90: 18660.61 | ET90: 0 | EU90: 0 | EV90: 0 | EW90: 0 | EX90: 0 | FQ90: 0 | FR90: 0 | FS90: 0 | FX90: 89 | FY90: 44 | GD90: 1 | GF90: 667244177 | GG90: 2 | GH90: 1 | GI90: 2 | GJ90: 0 | GK90: 0 | GL90: =ROUND(IF(AND(BH90=3,BI90=3,FS90<>0),P90,0),2) -> 0 | GM90: =ROUND(O90+X90+Y90,2)+GX90 -> 857.77 | GN90: =IF(OR(BI90=0,BI90=1),GM90-GX90,0) -> 857.77 | GO90: =IF(BI90=2,GM90-GX90,0) -> 0 | GP90: =IF(BI90=4,GM90-GX90,0) -> 0 | GR90: 0 | GS90: 0 | GT90: 0 | GV90: =ROUND((GT90),6) -> 0 | GW90: 1 | GX90: =ROUND(HC90*I90,2) -> 0 | HA90: 0 | HB90: 0 | HC90: =GV90*GW90 -> 0 | HS90: 0 | IK90: 0
A92: 51 | B92: =B71 -> 1 | C92: =A71 -> 4 | D92: =ROW(A71) -> 71 | F92: =IF(F71<>"",F71,"") | G92: =IF(G71<>"",G71,"") -> Усиление внутренних и наружных стен в зоне расширяемых проемов в подвале и в надземной части здания. Рама РС-2, 22 шт. (КР-5,6) | H92: 0 | O92: =ROUND(AB92,2) -> 62548.77 | P92: =ROUND(AC92,2) -> 48444.53 | Q92: =ROUND(AD92,2) -> 223.4 | R92: =ROUND(AE92,2) -> 12.86 | S92: =ROUND(AF92,2) -> 13880.84 | T92: =ROUND(AG92,2) -> 0 | U92: =AH92 -> 1110.2259 | V92: =AI92 -> 0 | W92: =ROUND(AJ92,2) -> 0 | X92: =ROUND(AK92,2) -> 12792.95 | Y92: =ROUND(AL92,2) -> 7240.84 | AB92: =ROUND(SUMIF(AA75:AA90,"=56481265",O75:O90),2) -> 62548.77 | AC92: =ROUND(SUMIF(AA75:AA90,"=56481265",P75:P90),2) -> 48444.53 | AD92: =ROUND(SUMIF(AA75:AA90,"=56481265",Q75:Q90),2) -> 223.4 | AE92: =ROUND(SUMIF(AA75:AA90,"=56481265",R75:R90),2) -> 12.86 | AF92: =ROUND(SUMIF(AA75:AA90,"=56481265",S75:S90),2) -> 13880.84 | AG92: =ROUND(SUMIF(AA75:AA90,"=56481265",T75:T90),2) -> 0 | AH92: =SUMIF(AA75:AA90,"=56481265",U75:U90) -> 1110.2259 | AI92: =SUMIF(AA75:AA90,"=56481265",V75:V90) -> 0 | AJ92: =ROUND(SUMIF(AA75:AA90,"=56481265",W75:W90),2) -> 0 | AK92: =ROUND(SUMIF(AA75:AA90,"=56481265",X75:X90),2) -> 12792.95 | AL92: =ROUND(SUMIF(AA75:AA90,"=56481265",Y75:Y90),2) -> 7240.84 | AO92: =ROUND(BX92,2) -> 0 | AP92: =ROUND(BY92,2) -> 0 | AQ92: =ROUND(BZ92,2) -> 0 | AR92: =ROUND(CA92,2) -> 82582.56 | AS92: =ROUND(CB92,2) -> 82582.56 | AT92: =ROUND(CC92,2) -> 0 | AU92: =ROUND(CD92,2) -> 0 | AV92: =ROUND(CE92,2) -> 48444.53 | ... BD92: =ROUND(CM92,2) -> 0 | BX92: =ROUND(SUMIF(AA75:AA90,"=56481265",FQ75:FQ90),2) -> 0 | BY92: =ROUND(SUMIF(AA75:AA90,"=56481265",FR75:FR90),2) -> 0 | BZ92: =ROUND(SUMIF(AA75:AA90,"=56481265",GL75:GL90),2) -> 0 | CA92: =ROUND(SUMIF(AA75:AA90,"=56481265",GM75:GM90),2) -> 82582.56 | CB92: =ROUND(SUMIF(AA75:AA90,"=56481265",GN75:GN90),2) -> 82582.56 | CC92: =ROUND(SUMIF(AA75:AA90,"=56481265",GO75:GO90),2) -> 0 | CD92: =ROUND(SUMIF(AA75:AA90,"=56481265",GP75:GP90),2) -> 0 | CE92: =AC92-BX92 -> 48444.53 | CF92: =AC92-BY92 -> 48444.53 | CG92: =BX92-BZ92 -> 0 | CH92: =AC92-BX92-BY92+BZ92 -> 48444.53 | CI92: =BY92-BZ92 -> 0 | CJ92: =ROUND(SUMIF(AA75:AA90,"=56481265",GX75:GX90),2) -> 0 | CK92: =ROUND(SUMIF(AA75:AA90,"=56481265",GY75:GY90),2) -> 0 | CL92: =ROUND(SUMIF(AA75:AA90,"=56481265",GZ75:GZ90),2) -> 0 | CM92: =ROUND(SUMIF(AA75:AA90,"=56481265",HD75:HD90),2) -> 0 | DG92: =ROUND(DT92,2) -> 1119077.2 | DH92: =ROUND(DU92,2) -> 451998.32 | DI92: =ROUND(DV92,2) -> 2996.32 | DJ92: =ROUND(DW92,2) -> 615.92 | DK92: =ROUND(DX92,2) -> 664082.56 | DL92: =ROUND(DY92,2) -> 0 | DM92: =DZ92 -> 1110.6764 | DN92: =EA92 -> 0 | DO92: =ROUND(EB92,2) -> 0 | DP92: =ROUND(EC92,2) -> 611320.91 | DQ92: =ROUND(ED92,2) -> 345105.37 | DT92: =ROUND(SUMIF(AA75:AA90,"=56481267",O75:O90),2) -> 1119077.2 | DU92: =ROUND(SUMIF(AA75:AA90,"=56481267",P75:P90),2) -> 451998.32 | DV92: =ROUND(SUMIF(AA75:AA90,"=56481267",Q75:Q90),2) -> 2996.32 | DW92: =ROUND(SUMIF(AA75:AA90,"=56481267",R75:R90),2) -> 615.92 | DX92: =ROUND(SUMIF(AA75:AA90,"=56481267",S75:S90),2) -> 664082.56 | DY92: =ROUND(SUMIF(AA75:AA90,"=56481267",T75:T90),2) -> 0 | DZ92: =SUMIF(AA75:AA90,"=56481267",U75:U90) -> 1110.6764 | EA92: =SUMIF(AA75:AA90,"=56481267",V75:V90) -> 0 | EB92: =ROUND(SUMIF(AA75:AA90,"=56481267",W75:W90),2) -> 0 | EC92: =ROUND(SUMIF(AA75:AA90,"=56481267",X75:X90),2) -> 611320.91 | ED92: =ROUND(SUMIF(AA75:AA90,"=56481267",Y75:Y90),2) -> 345105.37 | EG92: =ROUND(FP92,2) -> 0 | EH92: =ROUND(FQ92,2) -> 0 | EI92: =ROUND(FR92,2) -> 0 | EJ92: =ROUND(FS92,2) -> 2075503.5 | EK92: =ROUND(FT92,2) -> 2075503.5 | EL92: =ROUND(FU92,2) -> 0 | EM92: =ROUND(FV92,2) -> 0 | EN92: =ROUND(FW92,2) -> 451998.32 | ... EV92: =ROUND(GE92,2) -> 0 | FP92: =ROUND(SUMIF(AA75:AA90,"=56481267",FQ75:FQ90),2) -> 0 | FQ92: =ROUND(SUMIF(AA75:AA90,"=56481267",FR75:FR90),2) -> 0 | FR92: =ROUND(SUMIF(AA75:AA90,"=56481267",GL75:GL90),2) -> 0 | FS92: =ROUND(SUMIF(AA75:AA90,"=56481267",GM75:GM90),2) -> 2075503.5 | FT92: =ROUND(SUMIF(AA75:AA90,"=56481267",GN75:GN90),2) -> 2075503.5 | FU92: =ROUND(SUMIF(AA75:AA90,"=56481267",GO75:GO90),2) -> 0 | FV92: =ROUND(SUMIF(AA75:AA90,"=56481267",GP75:GP90),2) -> 0 | FW92: =DU92-FP92 -> 451998.32 | FX92: =DU92-FQ92 -> 451998.32 | FY92: =FP92-FR92 -> 0 | FZ92: =DU92-FP92-FQ92+FR92 -> 451998.32 | GA92: =FQ92-FR92 -> 0 | GB92: =ROUND(SUMIF(AA75:AA90,"=56481267",GX75:GX90),2) -> 0 | GC92: =ROUND(SUMIF(AA75:AA90,"=56481267",GY75:GY90),2) -> 0 | GD92: =ROUND(SUMIF(AA75:AA90,"=56481267",GZ75:GZ90),2) -> 0 | GE92: =ROUND(SUMIF(AA75:AA90,"=56481267",HD75:HD90),2) -> 0 | GX92: 0
A94: 50 | B94: 0 | C94: 0 | D94: 1 | E94: 201 | F94: =ROUND(Source!O92,O94) -> 62548.77 | G94: ПЗ | H94: Прямые затраты | K94: 201 | L94: 1 | M94: 3 | O94: 2 | P94: =ROUND(Source!DG92,O94) -> 1119077.2 | W94: 62548.77 | X94: 1 | Y94: 62548.77 | Z94: 1119077.2 | AA94: 1 | AB94: 1119077.2
A95: 50 | B95: 0 | C95: 0 | D95: 1 | E95: 202 | F95: =ROUND(Source!P92,O95) -> 48444.53 | G95: СтМатОб | H95: Стоимость материальных ресурсов (всего) | K95: 202 | L95: 2 | M95: 3 | O95: 2 | P95: =ROUND(Source!DH92,O95) -> 451998.32 | W95: 48444.53 | X95: 1 | Y95: 48444.53 | Z95: 451998.32 | AA95: 1 | AB95: 451998.32
A96: 50 | B96: 0 | C96: 0 | D96: 1 | E96: 222 | F96: =ROUND(Source!AO92,O96) -> 0 | G96: СтМатОбЗак | H96: Стоимость материалов и оборудования заказчика | K96: 222 | L96: 3 | M96: 3 | O96: 2 | P96: =ROUND(Source!EG92,O96) -> 0 | W96: 0 | X96: 1 | Y96: 0 | Z96: 0 | AA96: 1 | AB96: 0
A97: 50 | B97: 0 | C97: 0 | D97: 1 | E97: 225 | F97: =ROUND(Source!AV92,O97) -> 48444.53 | G97: СтМатОбПод | H97: Стоимость материалов и оборудования подрядчика | K97: 225 | L97: 4 | M97: 3 | O97: 2 | P97: =ROUND(Source!EN92,O97) -> 451998.32 | W97: 48444.53 | X97: 1 | Y97: 48444.53 | Z97: 451998.32 | AA97: 1 | AB97: 451998.32
A98: 50 | B98: 0 | C98: 0 | D98: 1 | E98: 226 | F98: =ROUND(Source!AW92,O98) -> 48444.53 | G98: СтМат | H98: Стоимость материалов (всего) | K98: 226 | L98: 5 | M98: 3 | O98: 2 | P98: =ROUND(Source!EO92,O98) -> 451998.32 | W98: 48444.53 | X98: 1 | Y98: 48444.53 | Z98: 451998.32 | AA98: 1 | AB98: 451998.32
A99: 50 | B99: 0 | C99: 0 | D99: 1 | E99: 227 | F99: =ROUND(Source!AX92,O99) -> 0 | G99: СтМатЗак | H99: Стоимость материалов заказчика | K99: 227 | L99: 6 | M99: 3 | O99: 2 | P99: =ROUND(Source!EP92,O99) -> 0 | W99: 0 | X99: 1 | Y99: 0 | Z99: 0 | AA99: 1 | AB99: 0
A100: 50 | B100: 0 | C100: 0 | D100: 1 | E100: 228 | F100: =ROUND(Source!AY92,O100) -> 48444.53 | G100: СтМатПод | H100: Стоимость материалов подрядчика | K100: 228 | L100: 7 | M100: 3 | O100: 2 | P100: =ROUND(Source!EQ92,O100) -> 451998.32 | W100: 48444.53 | X100: 1 | Y100: 48444.53 | Z100: 451998.32 | AA100: 1 | AB100: 451998.32
A101: 50 | B101: 0 | C101: 0 | D101: 1 | E101: 216 | F101: =ROUND(Source!AP92,O101) -> 0 | G101: Оборуд | H101: Стоимость оборудования (всего) | K101: 216 | L101: 8 | M101: 3 | O101: 2 | P101: =ROUND(Source!EH92,O101) -> 0 | W101: 0 | X101: 1 | Y101: 0 | Z101: 0 | AA101: 1 | AB101: 0
A102: 50 | B102: 0 | C102: 0 | D102: 1 | E102: 223 | F102: =ROUND(Source!AQ92,O102) -> 0 | G102: ОборудЗак | H102: Стоимость оборудования заказчика | K102: 223 | L102: 9 | M102: 3 | O102: 2 | P102: =ROUND(Source!EI92,O102) -> 0 | W102: 0 | X102: 1 | Y102: 0 | Z102: 0 | AA102: 1 | AB102: 0
A103: 50 | B103: 0 | C103: 0 | D103: 1 | E103: 229 | F103: =ROUND(Source!AZ92,O103) -> 0 | G103: ОборудПод | H103: Стоимость оборудования подрядчика | K103: 229 | L103: 10 | M103: 3 | O103: 2 | P103: =ROUND(Source!ER92,O103) -> 0 | W103: 0 | X103: 1 | Y103: 0 | Z103: 0 | AA103: 1 | AB103: 0
A104: 50 | B104: 0 | C104: 0 | D104: 1 | E104: 203 | F104: =ROUND(Source!Q92,O104) -> 223.4 | G104: ЭММ | H104: Эксплуатация машин | K104: 203 | L104: 11 | M104: 3 | O104: 2 | P104: =ROUND(Source!DI92,O104) -> 2996.32 | W104: 223.4 | X104: 1 | Y104: 223.4 | Z104: 2996.32 | AA104: 1 | AB104: 2996.32
A105: 50 | B105: 0 | C105: 0 | D105: 1 | E105: 231 | F105: =ROUND(Source!BB92,O105) -> 0 | G105: ЭММсНРиСП | H105: Эксплуатация машин по ТСН-2001.16 | K105: 231 | L105: 12 | M105: 3 | O105: 2 | P105: =ROUND(Source!ET92,O105) -> 0 | W105: 0 | X105: 1 | Y105: 0 | Z105: 0 | AA105: 1 | AB105: 0
A106: 50 | B106: 0 | C106: 0 | D106: 1 | E106: 204 | F106: =ROUND(Source!R92,O106) -> 12.86 | G106: ЗПМ | H106: ЗП машинистов | K106: 204 | L106: 13 | M106: 3 | O106: 2 | P106: =ROUND(Source!DJ92,O106) -> 615.92 | W106: 12.86 | X106: 1 | Y106: 12.86 | Z106: 615.92 | AA106: 1 | AB106: 615.92
A107: 50 | B107: 0 | C107: 0 | D107: 1 | E107: 205 | F107: =ROUND(Source!S92,O107) -> 13880.84 | G107: ОЗП | H107: Основная ЗП рабочих | K107: 205 | L107: 14 | M107: 3 | O107: 2 | P107: =ROUND(Source!DK92,O107) -> 664082.56 | W107: 13880.84 | X107: 1 | Y107: 13880.84 | Z107: 664082.56 | AA107: 1 | AB107: 664082.56
A108: 50 | B108: 0 | C108: 0 | D108: 1 | E108: 232 | F108: =ROUND(Source!BC92,O108) -> 0 | G108: ОЗПсНРиСП | H108: Основная ЗП рабочих по ТСН-2001.16 | K108: 232 | L108: 15 | M108: 3 | O108: 2 | P108: =ROUND(Source!EU92,O108) -> 0 | W108: 0 | X108: 1 | Y108: 0 | Z108: 0 | AA108: 1 | AB108: 0
A109: 50 | B109: 0 | C109: 0 | D109: 1 | E109: 214 | F109: =ROUND(Source!AS92,O109) -> 82582.56 | G109: Строит | H109: Строительные работы с НР и СП | K109: 214 | L109: 16 | M109: 3 | O109: 2 | P109: =ROUND(Source!EK92,O109) -> 2075503.5 | W109: 82582.56 | X109: 1 | Y109: 82582.56 | Z109: 2075503.5 | AA109: 1 | AB109: 2075503.5
A110: 50 | B110: 0 | C110: 0 | D110: 1 | E110: 215 | F110: =ROUND(Source!AT92,O110) -> 0 | G110: Монтаж | H110: Монтажные работы с НР и СП | K110: 215 | L110: 17 | M110: 3 | O110: 2 | P110: =ROUND(Source!EL92,O110) -> 0 | W110: 0 | X110: 1 | Y110: 0 | Z110: 0 | AA110: 1 | AB110: 0
A111: 50 | B111: 0 | C111: 0 | D111: 1 | E111: 217 | F111: =ROUND(Source!AU92,O111) -> 0 | G111: Прочие | H111: Прочие работы с НР и СП | K111: 217 | L111: 18 | M111: 3 | O111: 2 | P111: =ROUND(Source!EM92,O111) -> 0 | W111: 0 | X111: 1 | Y111: 0 | Z111: 0 | AA111: 1 | AB111: 0
A112: 50 | B112: 0 | C112: 0 | D112: 1 | E112: 230 | F112: =ROUND(Source!BA92,O112) -> 0 | G112: ПрочиеЗатр | H112: Прочие затраты по ТСН-2001.16 | K112: 230 | L112: 19 | M112: 3 | O112: 2 | P112: =ROUND(Source!ES92,O112) -> 0 | W112: 0 | X112: 1 | Y112: 0 | Z112: 0 | AA112: 1 | AB112: 0
A113: 50 | B113: 0 | C113: 0 | D113: 1 | E113: 206 | F113: =ROUND(Source!T92,O113) -> 0 | G113: ВозврМат | H113: Возврат материалов | K113: 206 | L113: 20 | M113: 3 | O113: 2 | P113: =ROUND(Source!DL92,O113) -> 0 | W113: 0 | X113: 1 | Y113: 0 | Z113: 0 | AA113: 1 | AB113: 0
A114: 50 | B114: 0 | C114: 0 | D114: 1 | E114: 207 | F114: =Source!U92 -> 1110.2259 | G114: ТрудСтр | H114: Трудозатраты строителей | K114: 207 | L114: 21 | M114: 3 | O114: -1 | P114: =Source!DM92 -> 1110.6764 | W114: 1110.2259 | X114: 1 | Y114: 1110.2259 | Z114: 1110.6764 | AA114: 1 | AB114: 1110.6764
A115: 50 | B115: 0 | C115: 0 | D115: 1 | E115: 208 | F115: =Source!V92 -> 0 | G115: ТрудМаш | H115: Трудозатраты машинистов | K115: 208 | L115: 22 | M115: 3 | O115: -1 | P115: =Source!DN92 -> 0 | W115: 0 | X115: 1 | Y115: 0 | Z115: 0 | AA115: 1 | AB115: 0
A116: 50 | B116: 0 | C116: 0 | D116: 1 | E116: 209 | F116: =ROUND(Source!W92,O116) -> 0 | G116: ТранспМат | H116: Транспорт материалов | K116: 209 | L116: 23 | M116: 3 | O116: 2 | P116: =ROUND(Source!DO92,O116) -> 0 | W116: 0 | X116: 1 | Y116: 0 | Z116: 0 | AA116: 1 | AB116: 0
A117: 50 | B117: 0 | C117: 0 | D117: 1 | E117: 233 | F117: =ROUND(Source!BD92,O117) -> 0 | G117: Перевозка | H117: Перевозка грузов | K117: 233 | L117: 24 | M117: 3 | O117: 2 | P117: =ROUND(Source!EV92,O117) -> 0 | W117: 0 | X117: 1 | Y117: 0 | Z117: 0 | AA117: 1 | AB117: 0
A118: 50 | B118: 0 | C118: 0 | D118: 1 | E118: 210 | F118: =ROUND(Source!X92,O118) -> 12792.95 | G118: НР | H118: Накладные расходы | K118: 210 | L118: 25 | M118: 3 | O118: 2 | P118: =ROUND(Source!DP92,O118) -> 611320.91 | W118: 12792.95 | X118: 1 | Y118: 12792.95 | Z118: 611320.91 | AA118: 1 | AB118: 611320.91
A119: 50 | B119: 0 | C119: 0 | D119: 1 | E119: 211 | F119: =ROUND(Source!Y92,O119) -> 7240.84 | G119: СмПриб | H119: Сметная прибыль | K119: 211 | L119: 26 | M119: 3 | O119: 2 | P119: =ROUND(Source!DQ92,O119) -> 345105.37 | W119: 7240.84 | X119: 1 | Y119: 7240.84 | Z119: 345105.37 | AA119: 1 | AB119: 345105.37
A120: 50 | B120: 0 | C120: 0 | D120: 1 | E120: 224 | F120: =ROUND(Source!AR92,O120) -> 82582.56 | G120: Всего | H120: Всего с НР и СП | K120: 224 | L120: 27 | M120: 3 | O120: 2 | P120: =ROUND(Source!EJ92,O120) -> 2075503.5 | W120: 82582.56 | X120: 1 | Y120: 82582.56 | Z120: 2075503.5 | AA120: 1 | AB120: 2075503.5
A122: 4 | B122: 1 | D122: =ROW(A139) -> 139 | G122: Усиление внутренних и наружных стен в зоне расширяемых проемов в подвале и в надземной части здания. Рама РС-3, 5 шт. (КР-5,6) | I122: 0 | K122: -1 | S122: 0 | T122: 0 | V122: 0 | BX122: 0 | CJ122: 0
A124: 52 | B124: =B139 -> 1 | C124: =C139 -> 4 | D124: =D139 -> 122 | E124: =E139 -> 0 | F124: =F139 | G124: =G139 -> Усиление внутренних и наружных стен в зоне расширяемых проемов в подвале и в надземной части здания. Рама РС-3, 5 шт. (КР-5,6) | O124: =O139 -> 21324.66 | P124: =P139 -> 16935.31 | Q124: =Q139 -> 69.39 | R124: =R139 -> 4 | S124: =S139 -> 4319.96 | T124: =T139 -> 0 | U124: =U139 -> 345.52755 | V124: =V139 -> 0 | ... GX124: =GX139 -> 0
A126: 17 | B126: 1 | C126: =ROW(SmtRes!A23) -> 23 | D126: =ROW(EtalonRes!A40) -> 40 | E126: 5 | F126: 6.53-25-1 | G126: Усиление кирпичных стен металлическим каркасом | H126: 1 Т | I126: =ROUND((146.3+108.5+15.7+7.2+16.9)/1000*5,9) -> 1.473 | J126: 0 | K126: =ROUND((146.3+108.5+15.7+7.2+16.9)/1000*5,9) -> 1.473 | O126: =ROUND(CP126,2) -> 4382.7 | P126: =ROUND((ROUND((AC126*AW126*I126),2)*BC126),2) -> 42.42 | Q126: =(ROUND((ROUND((((ET126*1.1))*AV126*I126),2)*BB126),2)+ROUND((ROUND(((AE126-((EU126*1.1)))*AV126*I126),2)*BS126),2)) -> 61.21 | R126: =ROUND((ROUND((AE126*AV126*I126),2)*BS126),2) -> 3.85 | S126: =ROUND((ROUND((AF126*AV126*I126),2)*BA126),2) -> 4279.07 | T126: =ROUND(CU126*I126,2) -> 0 | U126: =CV126*I126 -> 342.59891 | V126: =CW126*I126 -> 0 | W126: =ROUND(CX126*I126,2) -> 0 | X126: =ROUND(CY126,2) -> 3940.29 | Y126: =ROUND(CZ126,2) -> 2227.12 | AA126: 56481265 | AB126: =ROUND((AC126+AD126+AF126),6) -> 2843.024 | AC126: =ROUND((ES126),6) -> 28.74 | AD126: =ROUND(((((ET126*1.1))-((EU126*1.1)))+AE126),6) -> 39.688 | AE126: =ROUND(((EU126*1.1)),6) -> 2.497 | AF126: =ROUND(((EV126*1.1)),6) -> 2774.596 | AG126: =ROUND((AP126),6) -> 0 | AH126: =((EW126*1.1)) -> 222.145 | AI126: =((EX126*1.1)) -> 0 | AJ126: =(AS126) -> 0 | AK126: 2587.18 | AL126: 28.74 | AM126: 36.08 | AN126: 2.27 | AO126: 2522.36 | AP126: 0 | AQ126: 201.95 | AR126: 0 | AS126: 0 | AT126: 92 | AU126: 52 | AV126: 1.047 | AW126: 1.002 | AZ126: 1 | BA126: 1 | BB126: 1 | BC126: 1 | BH126: 0 | BI126: 1 | BJ126: ТСН-2001.6 Доп. 79, Сб. 53, т. 25, поз. 1 | BM126: 90 | BN126: 0 | BO126: 6.53-25-1 | BP126: 1 | BQ126: 60 | BR126: 0 | BS126: 1 | BT126: 1 | BU126: 1 | BV126: 1 | BW126: 1 | BX126: 1 | BZ126: 92 | CA126: 52 | CE126: 30 | CF126: 0 | CG126: 0 | CM126: 0 | CO126: 0 | CP126: =(P126+Q126+S126) -> 4382.7 | CQ126: =ROUND((ROUND((AC126*AW126*1),2)*BC126),2) -> 28.8 | CR126: =(ROUND((ROUND((((ET126*1.1))*AV126*1),2)*BB126),2)+ROUND((ROUND(((AE126-((EU126*1.1)))*AV126*1),2)*BS126),2)) -> 41.55 | CS126: =ROUND((ROUND((AE126*AV126*1),2)*BS126),2) -> 2.61 | CT126: =ROUND((ROUND((AF126*AV126*1),2)*BA126),2) -> 2905 | CU126: =AG126 -> 0 | CV126: =(AH126*AV126) -> 232.58581 | CW126: =AI126 -> 0 | CX126: =AJ126 -> 0 | CY126: =(((S126+R126)*AT126)/100) -> 3940.2864 | CZ126: =(((S126+R126)*AU126)/100) -> 2227.1184 | DE126: *1,1 | DF126: *1,1 | DG126: *1,1 | DI126: *1,1 | DJ126: *1,1 | DN126: 0 | DO126: 0 | DP126: 1 | DQ126: 1 | DU126: 1013 | DV126: 1 Т | DW126: 1 Т | DX126: 1 | EE126: 55586525 | EF126: 60 | EG126: Ремонтно-строительные работы | EH126: 0 | EJ126: 1 | EK126: 90 | EL126: ТСН-2001.6-53. Стены | EM126: ТСН-2001.6-53-1 | EO126: Поправка: Гл.12.Прил.8.п.8. 5_12.00.01.11.003 | EQ126: 0 | ER126: 2587.18 | ES126: 28.74 | ET126: 36.08 | EU126: 2.27 | EV126: 2522.36 | EW126: 201.95 | EX126: 0 | EY126: 0 | FQ126: 0 | FR126: 0 | FS126: 0 | FX126: 92 | FY126: 52 | GD126: 1 | GF126: -811884377 | GG126: 2 | GH126: 1 | GI126: 2 | GJ126: 0 | GK126: 0 | GL126: =ROUND(IF(AND(BH126=3,BI126=3,FS126<>0),P126,0),2) -> 0 | GM126: =ROUND(O126+X126+Y126,2)+GX126 -> 10550.11 | GN126: =IF(OR(BI126=0,BI126=1),GM126-GX126,0) -> 10550.11 | GO126: =IF(BI126=2,GM126-GX126,0) -> 0 | GP126: =IF(BI126=4,GM126-GX126,0) -> 0 | GR126: 0 | GS126: 3 | GT126: 0 | GV126: =ROUND((GT126),6) -> 0 | GW126: 1 | GX126: =ROUND(HC126*I126,2) -> 0 | HA126: 0 | HB126: 0 | HC126: =GV126*GW126 -> 0 | HS126: 0 | IK126: 0
A127: 17 | B127: 1 | C127: =ROW(SmtRes!A26) -> 26 | D127: =ROW(EtalonRes!A48) -> 48 | E127: 5 | F127: 6.53-25-1 | G127: Усиление кирпичных стен металлическим каркасом | H127: 1 Т | I127: =ROUND((146.3+108.5+15.7+7.2+16.9)/1000*5,9) -> 1.473 | J127: 0 | K127: =ROUND((146.3+108.5+15.7+7.2+16.9)/1000*5,9) -> 1.473 | O127: =ROUND(CP127,2) -> 206018.47 | P127: =ROUND((ROUND((AC127*AW127*I127),2)*BC127),2) -> 552.31 | Q127: =(ROUND((ROUND((((ET127*1.1))*AV127*I127),2)*BB127),2)+ROUND((ROUND(((AE127-((EU127*1.1)))*AV127*I127),2)*BS127),2)) -> 841.03 | R127: =ROUND((ROUND((AE127*AV127*I127),2)*BS127),2) -> 184.11 | S127: =ROUND((ROUND((AF127*AV127*I127),2)*BA127),2) -> 204625.13 | T127: =ROUND(CU127*I127,2) -> 0 | U127: =CV127*I127 -> 342.59891 | V127: =CW127*I127 -> 0 | W127: =ROUND(CX127*I127,2) -> 0 | X127: =ROUND(CY127,2) -> 188424.5 | Y127: =ROUND(CZ127,2) -> 106500.8 | AA127: 56481267 | AB127: =ROUND((AC127+AD127+AF127),6) -> 2843.024 | AC127: =ROUND((ES127),6) -> 28.74 | AD127: =ROUND(((((ET127*1.1))-((EU127*1.1)))+AE127),6) -> 39.688 | AE127: =ROUND(((EU127*1.1)),6) -> 2.497 | AF127: =ROUND(((EV127*1.1)),6) -> 2774.596 | AG127: =ROUND((AP127),6) -> 0 | AH127: =((EW127*1.1)) -> 222.145 | AI127: =((EX127*1.1)) -> 0 | AJ127: =(AS127) -> 0 | AK127: 2587.18 | AL127: 28.74 | AM127: 36.08 | AN127: 2.27 | AO127: 2522.36 | AP127: 0 | AQ127: 201.95 | AR127: 0 | AS127: 0 | AT127: 92 | AU127: 52 | AV127: 1.047 | AW127: 1.002 | AZ127: 1 | BA127: 47.82 | BB127: 13.74 | BC127: 13.02 | BH127: 0 | BI127: 1 | BJ127: ТСН-2001.6 Доп. 79, Сб. 53, т. 25, поз. 1 | BM127: 90 | BN127: 0 | BO127: 6.53-25-1 | BP127: 1 | BQ127: 60 | BR127: 0 | BS127: 47.82 | BT127: 1 | BU127: 1 | BV127: 1 | BW127: 1 | BX127: 1 | BZ127: 92 | CA127: 52 | CE127: 30 | CF127: 0 | CG127: 0 | CM127: 0 | CO127: 0 | CP127: =(P127+Q127+S127) -> 206018.47 | CQ127: =ROUND((ROUND((AC127*AW127*1),2)*BC127),2) -> 374.98 | CR127: =(ROUND((ROUND((((ET127*1.1))*AV127*1),2)*BB127),2)+ROUND((ROUND(((AE127-((EU127*1.1)))*AV127*1),2)*BS127),2)) -> 570.9 | CS127: =ROUND((ROUND((AE127*AV127*1),2)*BS127),2) -> 124.81 | CT127: =ROUND((ROUND((AF127*AV127*1),2)*BA127),2) -> 138917.1 | CU127: =AG127 -> 0 | CV127: =(AH127*AV127) -> 232.58581 | CW127: =AI127 -> 0 | CX127: =AJ127 -> 0 | CY127: =(((S127+R127)*AT127)/100) -> 188424.5 | CZ127: =(((S127+R127)*AU127)/100) -> 106500.8 | DE127: *1,1 | DF127: *1,1 | DG127: *1,1 | DI127: *1,1 | DJ127: *1,1 | DN127: 0 | DO127: 0 | DP127: 1 | DQ127: 1 | DU127: 1013 | DV127: 1 Т | DW127: 1 Т | DX127: 1 | EE127: 55586525 | EF127: 60 | EG127: Ремонтно-строительные работы | EH127: 0 | EJ127: 1 | EK127: 90 | EL127: ТСН-2001.6-53. Стены | EM127: ТСН-2001.6-53-1 | EO127: Поправка: Гл.12.Прил.8.п.8. 5_12.00.01.11.003 | EQ127: 0 | ER127: 2587.18 | ES127: 28.74 | ET127: 36.08 | EU127: 2.27 | EV127: 2522.36 | EW127: 201.95 | EX127: 0 | EY127: 0 | FQ127: 0 | FR127: 0 | FS127: 0 | FX127: 92 | FY127: 52 | GD127: 1 | GF127: -811884377 | GG127: 2 | GH127: 1 | GI127: 2 | GJ127: 0 | GK127: 0 | GL127: =ROUND(IF(AND(BH127=3,BI127=3,FS127<>0),P127,0),2) -> 0 | GM127: =ROUND(O127+X127+Y127,2)+GX127 -> 500943.77 | GN127: =IF(OR(BI127=0,BI127=1),GM127-GX127,0) -> 500943.77 | GO127: =IF(BI127=2,GM127-GX127,0) -> 0 | GP127: =IF(BI127=4,GM127-GX127,0) -> 0 | GR127: 0 | GS127: 3 | GT127: 0 | GV127: =ROUND((GT127),6) -> 0 | GW127: 1 | GX127: =ROUND(HC127*I127,2) -> 0 | HA127: 0 | HB127: 0 | HC127: =GV127*GW127 -> 0 | HS127: 0 | IK127: 0
A128: 18 | B128: 1 | C128: 22 | E128: 5,1 | F128: 1.1-1-1121 | G128: Уголок равнополочный, для строительных стальных конструкций, ширина полки более 70 мм, сталь С235, С245 | H128: т | I128: =I126*J128 -> 1.3525 | J128: 0.91819416 | K128: 0.918194 | O128: =ROUND(CP128,2) -> 13341.06 | P128: =ROUND((ROUND((AC128*AW128*I128),2)*BC128),2) -> 13341.06 | Q128: =(ROUND((ROUND(((ET128)*AV128*I128),2)*BB128),2)+ROUND((ROUND(((AE128-(EU128))*AV128*I128),2)*BS128),2)) -> 0 | R128: =ROUND((ROUND((AE128*AV128*I128),2)*BS128),2) -> 0 | S128: =ROUND((ROUND((AF128*AV128*I128),2)*BA128),2) -> 0 | T128: =ROUND(CU128*I128,2) -> 0 | U128: =CV128*I128 -> 0 | V128: =CW128*I128 -> 0 | W128: =ROUND(CX128*I128,2) -> 0 | X128: =ROUND(CY128,2) -> 0 | Y128: =ROUND(CZ128,2) -> 0 | AA128: 56481265 | AB128: =ROUND((AC128+AD128+AF128),6) -> 9844.31 | AC128: =ROUND((ES128),6) -> 9844.31 | AD128: =ROUND((((ET128)-(EU128))+AE128),6) -> 0 | AE128: =ROUND((EU128),6) -> 0 | AF128: =ROUND((EV128),6) -> 0 | AG128: =ROUND((AP128),6) -> 0 | AH128: =(EW128) -> 0 | AI128: =(EX128) -> 0 | AJ128: =(AS128) -> 0 | AK128: 9844.31 | AL128: 9844.31 | AM128: 0 | AN128: 0 | AO128: 0 | AP128: 0 | AQ128: 0 | AR128: 0 | AS128: 0 | AT128: 92 | AU128: 52 | AV128: 1 | AW128: 1.002 | AZ128: 1 | BA128: 1 | BB128: 1 | BC128: 1 | BH128: 3 | BI128: 1 | BJ128: ТСН-2001.1 Доп. 79, Р. 1, о. 1, поз. 1121 | BM128: 90 | BN128: 0 | BP128: 0 | BQ128: 60 | BR128: 0 | BS128: 1 | BT128: 1 | BU128: 1 | BV128: 1 | BW128: 1 | BX128: 1 | BZ128: 92 | CA128: 52 | CE128: 30 | CF128: 0 | CG128: 0 | CM128: 0 | CO128: 0 | CP128: =(P128+Q128+S128) -> 13341.06 | CQ128: =ROUND((ROUND((AC128*AW128*1),2)*BC128),2) -> 9864 | CR128: =(ROUND((ROUND(((ET128)*AV128*1),2)*BB128),2)+ROUND((ROUND(((AE128-(EU128))*AV128*1),2)*BS128),2)) -> 0 | CS128: =ROUND((ROUND((AE128*AV128*1),2)*BS128),2) -> 0 | CT128: =ROUND((ROUND((AF128*AV128*1),2)*BA128),2) -> 0 | CU128: =AG128 -> 0 | CV128: =(AH128*AV128) -> 0 | CW128: =AI128 -> 0 | CX128: =AJ128 -> 0 | CY128: =(((S128+R128)*AT128)/100) -> 0 | CZ128: =(((S128+R128)*AU128)/100) -> 0 | DN128: 0 | DO128: 0 | DP128: 1 | DQ128: 1 | DU128: 1009 | DV128: т | DW128: т | DX128: 1000 | EE128: 55586525 | EF128: 60 | EG128: Ремонтно-строительные работы | EH128: 0 | EJ128: 1 | EK128: 90 | EL128: ТСН-2001.6-53. Стены | EM128: ТСН-2001.6-53-1 | EQ128: 0 | ER128: 9844.31 | ES128: 9844.31 | ET128: 0 | EU128: 0 | EV128: 0 | EW128: 0 | EX128: 0 | FQ128: 0 | FR128: 0 | FS128: 0 | FX128: 92 | FY128: 52 | GD128: 1 | GF128: 981881691 | GG128: 2 | GH128: 1 | GI128: -2 | GJ128: 0 | GK128: 0 | GL128: =ROUND(IF(AND(BH128=3,BI128=3,FS128<>0),P128,0),2) -> 0 | GM128: =ROUND(O128+X128+Y128,2)+GX128 -> 13341.06 | GN128: =IF(OR(BI128=0,BI128=1),GM128-GX128,0) -> 13341.06 | GO128: =IF(BI128=2,GM128-GX128,0) -> 0 | GP128: =IF(BI128=4,GM128-GX128,0) -> 0 | GR128: 0 | GS128: 3 | GT128: 0 | GV128: =ROUND((GT128),6) -> 0 | GW128: 1 | GX128: =ROUND(HC128*I128,2) -> 0 | HA128: 0 | HB128: 0 | HC128: =GV128*GW128 -> 0 | HS128: 0 | IK128: 0
...

Sheet SourceObSm
A1: 0 | B1: Smeta.RU (495) 974-1589 | D1: _OBSM_ | F1: 0 | G1: 0 | H1: 0 | I1: Smeta.RU | K1: 1 | L1: 74562 | M1: 10 | N1: 11 | O1: 14 | P1: 0 | Q1: 0
A4: 1 | B4: 1 | C4: -1 | G4: Капитальный ремонт здания Государственного бюджетного общеобразовательного учреждения города Москвы «Школа № 236» по адресу: г. Москва, ул. Клязьминская, д. 7, к. 4. I этап | EC4: 0
A12: 1 | B12: 51 | C12: 0 | E12: 0 | F12: 02-01-02 | G12: 02-01-02 Конструктивные решения | I12: 0 | J12: 2024-00272-01-0-КР.ВОР | K12: 0 | L12: 0 | M12: 4098 | O12: 0 | P12: 0 | Q12: 0 | R12: 0 | S12: 0 | T12: 1 | V12: 0 | AB12: Лукьянова А.Л. | BB12: 0 | BH12: Сметные нормы списания | BI12: Коды ОКП для ТСН-2001 МГЭ Дополнение 79 | BJ12: 1 | BK12: 1 | BL12: 0 | BM12: 0 | BN12: 1 | BO12: 0 | BP12: 6 | BQ12: 2 | BR12: 1 | BS12: 1 | BT12: 0 | BU12: 0 | BV12: 0 | BW12: 0 | BX12: 0 | BY12: ТСН-2001 (МГЭ) Доп 79 - Ремонт | BZ12: Типовой расчет для ТСН-2001 МГЭ, Дополнение 79, ремонт | CA12: Территориальные сметные нормативы для Москвы ТСН-2001 (МГЭ), дополнение 79 | CB12: Территориальные сметные нормативы для Москвы ТСН-2001 (МГЭ), дополнение 79 | CC12: Территориальные сметные нормативы для Москвы ТСН-2001 (МГЭ), дополнение 79 | CD12: Территориальные сметные нормативы для Москвы ТСН-2001 (МГЭ), дополнение 79 | CE12: Поправки для ТСН-2001 от 03.10.2025 г. доп.79 | CF12: 0 | CG12: 0 | CH12: 8200 | CK12: 79 | CQ12: Территориальные сметные нормативы для Москвы (ТСН-2001) | CR12: ТЕР | CS12: 41660 | CT12: 1 | CU12: 79 | CY12: 0 | EC12: 0
A14: 22 | B14: 1 | C14: 0 | D14: 56481267 | E14: 56481265 | F14: 2 | G14: 1
A16: 3 | B16: 1 | C16: 02-01-02 | D16: Конструктивные решения | E16: =ROUND((Source!P1544)/1000,2) -> 68645.51 | F16: =ROUND((Source!P1545)/1000,2) -> 0 | G16: =ROUND((Source!P1536)/1000,2) -> 0 | H16: =ROUND((Source!P1546)/1000+(Source!P1547)/1000,2) -> 0 | I16: =E16+F16+G16+H16 -> 68645.51 | J16: =ROUND((Source!P1542+Source!P1541)/1000,2) -> 17451.36 | K16: 69332.01 | L16: 0 | M16: 0 | N16: =I16+L16+M16 -> 68645.51 | T16: =ROUND((Source!F1544)/1000,2) -> 4298.49 | U16: =ROUND((Source!F1545)/1000,2) -> 0 | V16: =ROUND((Source!F1536)/1000,2) -> 0 | W16: =ROUND((Source!F1546)/1000+(Source!F1547)/1000,2) -> 0 | X16: =T16+U16+V16+W16 -> 4298.49 | Y16: =ROUND((Source!F1542+Source!F1541)/1000,2) -> 364.8 | Z16: 7150.86 | AA16: 0 | AB16: 0 | AC16: =X16+AA16+AB16 -> 4298.49 | AI16: 0 | AJ16: -1 | AN16: 0 | AT16: 43540191 | AU16: 25791816 | AV16: 0 | AW16: 0 | AX16: 0 | AY16: 435524.02 | AZ16: 138504.98 | BA16: 17312851 | BB16: 68645507 | BC16: 0 | BD16: 0 | BE16: 0 | BF16: 27409.788 | BG16: 0 | BH16: 0 | BI16: 16004219 | BJ16: 9101096.9 | BK16: 68645507 | BR16: 3772771 | BS16: 3378093.4 | BT16: 0 | BU16: 0 | BV16: 0 | BW16: 32771.56 | BX16: 2895.88 | BY16: 361906.04 | BZ16: 4298486 | CA16: 0 | CB16: 0 | CC16: 0 | CD16: 27400.046 | CE16: 0 | CF16: 0 | CG16: 334874.27 | CH16: 190840.66 | CI16: 4298486
A18: 51 | E18: 68645.51 | F18: 0 | G18: 0 | H18: 0 | I18: 68645.51 | J18: 17451.36 | K18: 69332.01 | L18: 0 | M18: 0 | N18: 68645.51 | T18: 4298.49 | U18: 0 | V18: 0 | W18: 0 | X18: 4298.49 | Y18: 364.8 | Z18: 7150.86 | AA18: 0 | AB18: 0 | AC18: 4298.49
A20: 50 | B20: 0 | C20: 0 | D20: 1 | E20: 201 | F20: 43540191 | G20: ПЗ | H20: Прямые затраты | K20: 201 | L20: 1 | M20: 3 | O20: 2 | P20: 3772771
A21: 50 | B21: 0 | C21: 0 | D21: 1 | E21: 202 | F21: 25791816 | G21: СтМатОб | H21: Стоимость материальных ресурсов (всего) | K21: 202 | L21: 2 | M21: 3 | O21: 2 | P21: 3378093.4
A22: 50 | B22: 0 | C22: 0 | D22: 1 | E22: 222 | F22: 0 | G22: СтМатОбЗак | H22: Стоимость материалов и оборудования заказчика | K22: 222 | L22: 3 | M22: 3 | O22: 2 | P22: 0
A23: 50 | B23: 0 | C23: 0 | D23: 1 | E23: 225 | F23: 25791816 | G23: СтМатОбПод | H23: Стоимость материалов и оборудования подрядчика | K23: 225 | L23: 4 | M23: 3 | O23: 2 | P23: 3378093.4
A24: 50 | B24: 0 | C24: 0 | D24: 1 | E24: 226 | F24: 25791816 | G24: СтМат | H24: Стоимость материалов (всего) | K24: 226 | L24: 5 | M24: 3 | O24: 2 | P24: 3378093.4
A25: 50 | B25: 0 | C25: 0 | D25: 1 | E25: 227 | F25: 0 | G25: СтМатЗак | H25: Стоимость материалов заказчика | K25: 227 | L25: 6 | M25: 3 | O25: 2 | P25: 0
A26: 50 | B26: 0 | C26: 0 | D26: 1 | E26: 228 | F26: 25791816 | G26: СтМатПод | H26: Стоимость материалов подрядчика | K26: 228 | L26: 7 | M26: 3 | O26: 2 | P26: 3378093.4
A27: 50 | B27: 0 | C27: 0 | D27: 1 | E27: 216 | F27: 0 | G27: Оборуд | H27: Стоимость оборудования (всего) | K27: 216 | L27: 8 | M27: 3 | O27: 2 | P27: 0
A28: 50 | B28: 0 | C28: 0 | D28: 1 | E28: 223 | F28: 0 | G28: ОборудЗак | H28: Стоимость оборудования заказчика | K28: 223 | L28: 9 | M28: 3 | O28: 2 | P28: 0
A29: 50 | B29: 0 | C29: 0 | D29: 1 | E29: 229 | F29: 0 | G29: ОборудПод | H29: Стоимость оборудования подрядчика | K29: 229 | L29: 10 | M29: 3 | O29: 2 | P29: 0
A30: 50 | B30: 0 | C30: 0 | D30: 1 | E30: 203 | F30: 435524.02 | G30: ЭММ | H30: Эксплуатация машин | K30: 203 | L30: 11 | M30: 3 | O30: 2 | P30: 32771.56
A31: 50 | B31: 0 | C31: 0 | D31: 1 | E31: 231 | F31: 0 | G31: ЭММсНРиСП | H31: Эксплуатация машин по ТСН-2001.16 | K31: 231 | L31: 12 | M31: 3 | O31: 2 | P31: 0
... A46: 50 | B46: 0 | C46: 0 | D46: 1 | E46: 224 | F46: 68645507 | G46: Всего | H46: Всего с НР и СП | K46: 224 | L46: 27 | M46: 3 | O46: 2 | P46: 4298486
A48: -1
A51: 75 | B51: Текущий уровень цен | C51: 2025 | D51: 0 | E51: 7 | G51: 0 | H51: 1 | I51: 1 | J51: 3 | K51: 0 | L51: 0 | M51: 1 | N51: 56481267 | O51: 1
A52: 1 | B52: Сборник индексов | C52: Коэффициенты к ТСН-2001 МГЭ Дополнение 79, ремонт | D52: 2025 | E52: 7 | F52: 1 | G52: 1 | H52: 0 | I52: 2 | J52: 1 | K52: 1 | L52: 1 | M52: 1 | N52: 1 | O52: 1 | P52: 1 | Q52: 1 | AA52: 216/79 | AN52: 56481268
A53: 1 | B53: Сборник индексов | C53: Коэффициенты к ТСН-2001.13-2 Дополнение 45 | D53: 2025 | E53: 7 | F53: 1 | G53: 1 | H53: 0 | I53: 2 | J53: 1 | K53: 1 | L53: 1 | M53: 1 | N53: 1 | O53: 1 | P53: 1 | Q53: 1 | AA53: 62/45 | AN53: 56481269
A54: 75 | B54: Базовый уровень цен | C54: 2000 | D54: 0 | E54: 1 | F54: 0 | G54: 0 | H54: 1 | I54: 1 | J54: 3 | K54: 0 | L54: 0 | M54: 0 | N54: 56481265 | O54: 2
A55: 1 | B55: Сборник индексов | C55: Коэффициенты к ТСН-2001 МГЭ Дополнение 79, ремонт | D55: 2000 | E55: 1 | F55: 1 | G55: 1 | H55: 0 | I55: 2 | J55: 1 | K55: 1 | L55: 1 | M55: 1 | N55: 1 | O55: 1 | P55: 1 | Q55: 1 | AN55: 56481266

Sheet SmtRes
A1: =ROW(Source!A28) -> 28 | B1: 56481265 | C1: 56481649 | D1: 54902988 | E1: 1 | F1: 1 | G1: 1079 | H1: 3 | I1: 1.1-1-1105 | J1: ТСН-2001.1 Доп. 79, Р. 1, о. 1, поз. 1105 | K1: Прокат листовой из стали С235, С245 для строительных стальных конструкций, толщина более 3 мм | L1: 1348 | N1: 1009 | O1: т | P1: т | Q1: 1000 | W1: 0 | X1: -1891961884 | Y1: =AT1 -> 0.040758 | AA1: 6532.24 | AB1: 0 | AC1: 0 | AD1: 0 | AE1: 6519.2 | AF1: 0 | AG1: 0 | AH1: 0 | AI1: 1 | AJ1: 1 | AK1: 1 | AL1: 1 | AM1: 0 | AN1: 0 | AO1: 0 | AP1: 1 | AQ1: 0 | AR1: 0 | AT1: 0.040758 | AV1: 0 | AW1: 1 | AX1: -1 | AY1: 0 | AZ1: 0 | BB1: 0 | BC1: 0 | BD1: 0 | BE1: 0 | BF1: 0 | BG1: 0 | BH1: 0 | BI1: 0 | BJ1: 0 | BK1: 0 | BL1: 0 | BM1: 0 | BN1: 0 | BO1: 0 | BP1: 0 | BQ1: 0 | BR1: 0 | BS1: 0 | BT1: 0 | BU1: 0 | BV1: 0 | BW1: 0 | CV1: 0 | CW1: 0 | CX1: =ROUND(Y1*Source!I28,9) -> 1.0395124 | CY1: =AA1 -> 6532.24 | CZ1: =AE1 -> 6519.2 | DA1: =AI1 -> 1 | DB1: =ROUND(ROUND(AT1*CZ1,2),6) -> 265.71 | DC1: =ROUND(ROUND(AT1*AG1,2),6) -> 0 | DF1: =ROUND(ROUND(AE1,2)*CX1,2) -> 6776.79 | DG1: =ROUND(ROUND(AF1,2)*CX1,2) -> 0 | DH1: =ROUND(ROUND(AG1,2)*CX1,2) -> 0 | DI1: =ROUND(ROUND(AH1,2)*CX1,2) -> 0 | DJ1: =DF1 -> 6776.79 | DK1: 0 | DM1: 0 | DO1: 0
A2: =ROW(Source!A28) -> 28 | B2: 56481265 | C2: 56481649 | D2: 54902999 | E2: 1 | F2: 1 | G2: 1079 | H2: 3 | I2: 1.1-1-1121 | J2: ТСН-2001.1 Доп. 79, Р. 1, о. 1, поз. 1121 | K2: Уголок равнополочный, для строительных стальных конструкций, ширина полки более 70 мм, сталь С235, С245 | L2: 1348 | N2: 1009 | O2: т | P2: т | Q2: 1000 | W2: 0 | X2: 981881691 | Y2: =AT2 -> 0.9592425 | AA2: 9864 | AB2: 0 | AC2: 0 | AD2: 0 | AE2: 9844.31 | AF2: 0 | AG2: 0 | AH2: 0 | AI2: 1 | AJ2: 1 | AK2: 1 | AL2: 1 | AM2: 0 | AN2: 0 | AO2: 0 | AP2: 0 | AQ2: 0 | AR2: 0 | AT2: 0.9592425 | AV2: 0 | AW2: 1 | AX2: -1 | AY2: 0 | AZ2: 0 | BB2: 0 | BC2: 0 | BD2: 0 | BE2: 0 | BF2: 0 | BG2: 0 | BH2: 0 | BI2: 0 | BJ2: 0 | BK2: 0 | BL2: 0 | BM2: 0 | BN2: 0 | BO2: 0 | BP2: 0 | BQ2: 0 | BR2: 0 | BS2: 0 | BT2: 0 | BU2: 0 | BV2: 0 | BW2: 0 | CV2: 0 | CW2: 0 | CX2: =ROUND(Y2*Source!I28,9) -> 24.465 | CY2: =AA2 -> 9864 | CZ2: =AE2 -> 9844.31 | DA2: =AI2 -> 1 | DB2: =ROUND(ROUND(AT2*CZ2,2),6) -> 9443.08 | DC2: =ROUND(ROUND(AT2*AG2,2),6) -> 0 | DF2: =ROUND(ROUND(AE2,2)*CX2,2) -> 240841.05 | DG2: =ROUND(ROUND(AF2,2)*CX2,2) -> 0 | DH2: =ROUND(ROUND(AG2,2)*CX2,2) -> 0 | DI2: =ROUND(ROUND(AH2,2)*CX2,2) -> 0 | DJ2: =DF2 -> 240841.05 | DK2: 0 | DM2: 0 | DO2: 0
A3: =ROW(Source!A28) -> 28 | B3: 56481265 | C3: 56481649 | D3: 54912920 | E3: 1 | F3: 1 | G3: 1079 | H3: 3 | I3: 1.7-5-220 | J3: ТСН-2001.1 Доп. 53, Р. 7, о. 5, поз. 220 | K3: Шпилька резьбовая, стальная, оцинкованная, с заостренным концом, в комплекте с шайбой и гайкой, М16x190 мм | L3: 1354 | N3: 1010 | O3: шт. | P3: шт. | Q3: 1 | W3: 0 | X3: 2014927073 | Y3: =AT3 -> 57.636888 | AA3: 29.86 | AB3: 0 | AC3: 0 | AD3: 0 | AE3: 29.8 | AF3: 0 | AG3: 0 | AH3: 0 | AI3: 1 | AJ3: 1 | AK3: 1 | AL3: 1 | AM3: 0 | AN3: 0 | AO3: 0 | AP3: 1 | AQ3: 0 | AR3: 0 | AT3: 57.636888 | AV3: 0 | AW3: 1 | AX3: -1 | AY3: 0 | AZ3: 0 | BB3: 0 | BC3: 0 | BD3: 0 | BE3: 0 | BF3: 0 | BG3: 0 | BH3: 0 | BI3: 0 | BJ3: 0 | BK3: 0 | BL3: 0 | BM3: 0 | BN3: 0 | BO3: 0 | BP3: 0 | BQ3: 0 | BR3: 0 | BS3: 0 | BT3: 0 | BU3: 0 | BV3: 0 | BW3: 0 | CV3: 0 | CW3: 0 | CX3: =ROUND(Y3*Source!I28,9) -> 1470 | CY3: =AA3 -> 29.86 | CZ3: =AE3 -> 29.8 | DA3: =AI3 -> 1 | DB3: =ROUND(ROUND(AT3*CZ3,2),6) -> 1717.58 | DC3: =ROUND(ROUND(AT3*AG3,2),6) -> 0 | DF3: =ROUND(ROUND(AE3,2)*CX3,2) -> 43806 | DG3: =ROUND(ROUND(AF3,2)*CX3,2) -> 0 | DH3: =ROUND(ROUND(AG3,2)*CX3,2) -> 0 | DI3: =ROUND(ROUND(AH3,2)*CX3,2) -> 0 | DJ3: =DF3 -> 43806 | DK3: 0 | DM3: 0 | DO3: 0
A4: =ROW(Source!A29) -> 29 | B4: 56481267 | C4: 56481649 | D4: 54902988 | E4: 1 | F4: 1 | G4: 1079 | H4: 3 | I4: 1.1-1-1105 | J4: ТСН-2001.1 Доп. 79, Р. 1, о. 1, поз. 1105 | K4: Прокат листовой из стали С235, С245 для строительных стальных конструкций, толщина более 3 мм | L4: 1348 | N4: 1009 | O4: т | P4: т | Q4: 1000 | W4: 0 | X4: -1891961884 | Y4: =AT4 -> 0.040758 | AA4: 66106.25 | AB4: 0 | AC4: 0 | AD4: 0 | AE4: 6519.2 | AF4: 0 | AG4: 0 | AH4: 0 | AI4: 10.12 | AJ4: 1 | AK4: 1 | AL4: 1 | AM4: 0 | AN4: 0 | AO4: 0 | AP4: 1 | AQ4: 0 | AR4: 0 | AT4: 0.040758 | AV4: 0 | AW4: 1 | AX4: -1 | AY4: 0 | AZ4: 0 | BB4: 0 | BC4: 0 | BD4: 0 | BE4: 0 | BF4: 0 | BG4: 0 | BH4: 0 | BI4: 0 | BJ4: 0 | BK4: 0 | BL4: 0 | BM4: 0 | BN4: 0 | BO4: 0 | BP4: 0 | BQ4: 0 | BR4: 0 | BS4: 0 | BT4: 0 | BU4: 0 | BV4: 0 | BW4: 0 | CV4: 0 | CW4: 0 | CX4: =ROUND(Y4*Source!I29,9) -> 1.0395124 | CY4: =AA4 -> 66106.25 | CZ4: =AE4 -> 6519.2 | DA4: =AI4 -> 10.12 | DB4: =ROUND(ROUND(AT4*CZ4,2),6) -> 265.71 | DC4: =ROUND(ROUND(AT4*AG4,2),6) -> 0 | DF4: =ROUND(ROUND(AE4*AI4,2)*CX4,2) -> 68581.1 | DG4: =ROUND(ROUND(AF4,2)*CX4,2) -> 0 | DH4: =ROUND(ROUND(AG4,2)*CX4,2) -> 0 | DI4: =ROUND(ROUND(AH4,2)*CX4,2) -> 0 | DJ4: =DF4 -> 68581.1 | DK4: 0 | DM4: 0 | DO4: 0
A5: =ROW(Source!A29) -> 29 | B5: 56481267 | C5: 56481649 | D5: 54902999 | E5: 1 | F5: 1 | G5: 1079 | H5: 3 | I5: 1.1-1-1121 | J5: ТСН-2001.1 Доп. 79, Р. 1, о. 1, поз. 1121 | K5: Уголок равнополочный, для строительных стальных конструкций, ширина полки более 70 мм, сталь С235, С245 | L5: 1348 | N5: 1009 | O5: т | P5: т | Q5: 1000 | W5: 0 | X5: 981881691 | Y5: =AT5 -> 0.9592425 | AA5: 74374.55 | AB5: 0 | AC5: 0 | AD5: 0 | AE5: 9844.31 | AF5: 0 | AG5: 0 | AH5: 0 | AI5: 7.54 | AJ5: 1 | AK5: 1 | AL5: 1 | AM5: 2 | AN5: 0 | AO5: 0 | AP5: 0 | AQ5: 0 | AR5: 0 | AT5: 0.9592425 | AV5: 0 | AW5: 1 | AX5: -1 | AY5: 0 | AZ5: 0 | BB5: 0 | BC5: 0 | BD5: 0 | BE5: 0 | BF5: 0 | BG5: 0 | BH5: 0 | BI5: 0 | BJ5: 0 | BK5: 0 | BL5: 0 | BM5: 0 | BN5: 0 | BO5: 0 | BP5: 0 | BQ5: 0 | BR5: 0 | BS5: 0 | BT5: 0 | BU5: 0 | BV5: 0 | BW5: 0 | CV5: 0 | CW5: 0 | CX5: =ROUND(Y5*Source!I29,9) -> 24.465 | CY5: =AA5 -> 74374.55 | CZ5: =AE5 -> 9844.31 | DA5: =AI5 -> 7.54 | DB5: =ROUND(ROUND(AT5*CZ5,2),6) -> 9443.08 | DC5: =ROUND(ROUND(AT5*AG5,2),6) -> 0 | DF5: =ROUND(ROUND(AE5*AI5,2)*CX5,2) -> 1815941.6 | DG5: =ROUND(ROUND(AF5,2)*CX5,2) -> 0 | DH5: =ROUND(ROUND(AG5,2)*CX5,2) -> 0 | DI5: =ROUND(ROUND(AH5,2)*CX5,2) -> 0 | DJ5: =DF5 -> 1815941.6 | DK5: 0 | DM5: 0 | DO5: 0
A6: =ROW(Source!A29) -> 29 | B6: 56481267 | C6: 56481649 | D6: 54912920 | E6: 1 | F6: 1 | G6: 1079 | H6: 3 | I6: 1.7-5-220 | J6: ТСН-2001.1 Доп. 53, Р. 7, о. 5, поз. 220 | K6: Шпилька резьбовая, стальная, оцинкованная, с заостренным концом, в комплекте с шайбой и гайкой, М16x190 мм | L6: 1354 | N6: 1010 | O6: шт. | P6: шт. | Q6: 1 | W6: 0 | X6: 2014927073 | Y6: =AT6 -> 57.636888 | AA6: 357.42 | AB6: 0 | AC6: 0 | AD6: 0 | AE6: 29.8 | AF6: 0 | AG6: 0 | AH6: 0 | AI6: 11.97 | AJ6: 1 | AK6: 1 | AL6: 1 | AM6: 0 | AN6: 0 | AO6: 0 | AP6: 1 | AQ6: 0 | AR6: 0 | AT6: 57.636888 | AV6: 0 | AW6: 1 | AX6: -1 | AY6: 0 | AZ6: 0 | BB6: 0 | BC6: 0 | BD6: 0 | BE6: 0 | BF6: 0 | BG6: 0 | BH6: 0 | BI6: 0 | BJ6: 0 | BK6: 0 | BL6: 0 | BM6: 0 | BN6: 0 | BO6: 0 | BP6: 0 | BQ6: 0 | BR6: 0 | BS6: 0 | BT6: 0 | BU6: 0 | BV6: 0 | BW6: 0 | CV6: 0 | CW6: 0 | CX6: =ROUND(Y6*Source!I29,9) -> 1470 | CY6: =AA6 -> 357.42 | CZ6: =AE6 -> 29.8 | DA6: =AI6 -> 11.97 | DB6: =ROUND(ROUND(AT6*CZ6,2),6) -> 1717.58 | DC6: =ROUND(ROUND(AT6*AG6,2),6) -> 0 | DF6: =ROUND(ROUND(AE6*AI6,2)*CX6,2) -> 524363.7 | DG6: =ROUND(ROUND(AF6,2)*CX6,2) -> 0 | DH6: =ROUND(ROUND(AG6,2)*CX6,2) -> 0 | DI6: =ROUND(ROUND(AH6,2)*CX6,2) -> 0 | DJ6: =DF6 -> 524363.7 | DK6: 0 | DM6: 0 | DO6: 0
A7: =ROW(Source!A36) -> 36 | B7: 56481265 | C7: 56491132 | D7: 48547175 | E7: 1 | F7: 1 | G7: 1079 | H7: 3 | I7: 1.1-1-165 | J7: ТСН-2001.1 Доп. 67, Р. 1, о. 1, поз. 165 | K7: Грунтовка глифталевая, типа ГФ-021 | L7: 1348 | N7: 1009 | O7: т | P7: т | Q7: 1000 | W7: 0 | X7: 667244177 | Y7: =AT7 -> 0.009 | AA7: 18660.61 | AB7: 0 | AC7: 0 | AD7: 0 | AE7: 18660.61 | AF7: 0 | AG7: 0 | AH7: 0 | AI7: 1 | AJ7: 1 | AK7: 1 | AL7: 1 | AM7: 0 | AN7: 0 | AO7: 0 | AP7: 0 | AQ7: 0 | AR7: 0 | AT7: 0.009 | AV7: 0 | AW7: 1 | AX7: -1 | AY7: 0 | AZ7: 0 | BB7: 0 | BC7: 0 | BD7: 0 | BE7: 0 | BF7: 0 | BG7: 0 | BH7: 0 | BI7: 0 | BJ7: 0 | BK7: 0 | BL7: 0 | BM7: 0 | BN7: 0 | BO7: 0 | BP7: 0 | BQ7: 0 | BR7: 0 | BS7: 0 | BT7: 0 | BU7: 0 | BV7: 0 | BW7: 0 | CV7: 0 | CW7: 0 | CX7: =ROUND(Y7*Source!I36,9) -> 0.068737505 | CY7: =AA7 -> 18660.61 | CZ7: =AE7 -> 18660.61 | DA7: =AI7 -> 1 | DB7: =ROUND(ROUND(AT7*CZ7,2),6) -> 167.95 | DC7: =ROUND(ROUND(AT7*AG7,2),6) -> 0 | DF7: =ROUND(ROUND(AE7,2)*CX7,2) -> 1282.68 | DG7: =ROUND(ROUND(AF7,2)*CX7,2) -> 0 | DH7: =ROUND(ROUND(AG7,2)*CX7,2) -> 0 | DI7: =ROUND(ROUND(AH7,2)*CX7,2) -> 0 | DJ7: =DF7 -> 1282.68 | DK7: 0 | DM7: 0 | DO7: 0
A8: =ROW(Source!A37) -> 37 | B8: 56481267 | C8: 56491132 | D8: 48547175 | E8: 1 | F8: 1 | G8: 1079 | H8: 3 | I8: 1.1-1-165 | J8: ТСН-2001.1 Доп. 67, Р. 1, о. 1, поз. 165 | K8: Грунтовка глифталевая, типа ГФ-021 | L8: 1348 | N8: 1009 | O8: т | P8: т | Q8: 1000 | W8: 0 | X8: 667244177 | Y8: =AT8 -> 0.009 | AA8: 66804.98 | AB8: 0 | AC8: 0 | AD8: 0 | AE8: 18660.61 | AF8: 0 | AG8: 0 | AH8: 0 | AI8: 3.58 | AJ8: 1 | AK8: 1 | AL8: 1 | AM8: 2 | AN8: 0 | AO8: 0 | AP8: 0 | AQ8: 0 | AR8: 0 | AT8: 0.009 | AV8: 0 | AW8: 1 | AX8: -1 | AY8: 0 | AZ8: 0 | BB8: 0 | BC8: 0 | BD8: 0 | BE8: 0 | BF8: 0 | BG8: 0 | BH8: 0 | BI8: 0 | BJ8: 0 | BK8: 0 | BL8: 0 | BM8: 0 | BN8: 0 | BO8: 0 | BP8: 0 | BQ8: 0 | BR8: 0 | BS8: 0 | BT8: 0 | BU8: 0 | BV8: 0 | BW8: 0 | CV8: 0 | CW8: 0 | CX8: =ROUND(Y8*Source!I37,9) -> 0.068737505 | CY8: =AA8 -> 66804.98 | CZ8: =AE8 -> 18660.61 | DA8: =AI8 -> 3.58 | DB8: =ROUND(ROUND(AT8*CZ8,2),6) -> 167.95 | DC8: =ROUND(ROUND(AT8*AG8,2),6) -> 0 | DF8: =ROUND(ROUND(AE8*AI8,2)*CX8,2) -> 4592.01 | DG8: =ROUND(ROUND(AF8,2)*CX8,2) -> 0 | DH8: =ROUND(ROUND(AG8,2)*CX8,2) -> 0 | DI8: =ROUND(ROUND(AH8,2)*CX8,2) -> 0 | DJ8: =DF8 -> 4592.01 | DK8: 0 | DM8: 0 | DO8: 0
A9: =ROW(Source!A75) -> 75 | B9: 56481265 | C9: 56481865 | D9: 54902988 | E9: 1 | F9: 1 | G9: 1079 | H9: 3 | I9: 1.1-1-1105 | J9: ТСН-2001.1 Доп. 79, Р. 1, о. 1, поз. 1105 | K9: Прокат листовой из стали С235, С245 для строительных стальных конструкций, толщина более 3 мм | L9: 1348 | N9: 1009 | O9: т | P9: т | Q9: 1000 | W9: 0 | X9: -1891961884 | Y9: =AT9 -> 0.139935 | AA9: 6532.24 | AB9: 0 | AC9: 0 | AD9: 0 | AE9: 6519.2 | AF9: 0 | AG9: 0 | AH9: 0 | AI9: 1 | AJ9: 1 | AK9: 1 | AL9: 1 | AM9: 0 | AN9: 0 | AO9: 0 | AP9: 1 | AQ9: 0 | AR9: 0 | AT9: 0.139935 | AV9: 0 | AW9: 1 | AX9: -1 | AY9: 0 | AZ9: 0 | BB9: 0 | BC9: 0 | BD9: 0 | BE9: 0 | BF9: 0 | BG9: 0 | BH9: 0 | BI9: 0 | BJ9: 0 | BK9: 0 | BL9: 0 | BM9: 0 | BN9: 0 | BO9: 0 | BP9: 0 | BQ9: 0 | BR9: 0 | BS9: 0 | BT9: 0 | BU9: 0 | BV9: 0 | BW9: 0 | CV9: 0 | CW9: 0 | CX9: =ROUND(Y9*Source!I75,9) -> 0.66220041 | CY9: =AA9 -> 6532.24 | CZ9: =AE9 -> 6519.2 | DA9: =AI9 -> 1 | DB9: =ROUND(ROUND(AT9*CZ9,2),6) -> 912.26 | DC9: =ROUND(ROUND(AT9*AG9,2),6) -> 0 | DF9: =ROUND(ROUND(AE9,2)*CX9,2) -> 4317.02 | DG9: =ROUND(ROUND(AF9,2)*CX9,2) -> 0 | DH9: =ROUND(ROUND(AG9,2)*CX9,2) -> 0 | DI9: =ROUND(ROUND(AH9,2)*CX9,2) -> 0 | DJ9: =DF9 -> 4317.02 | DK9: 0 | DM9: 0 | DO9: 0
A10: =ROW(Source!A75) -> 75 | B10: 56481265 | C10: 56481865 | D10: 54902999 | E10: 1 | F10: 1 | G10: 1079 | H10: 3 | I10: 1.1-1-1121 | J10: ТСН-2001.1 Доп. 79, Р. 1, о. 1, поз. 1121 | K10: Уголок равнополочный, для строительных стальных конструкций, ширина полки более 70 мм, сталь С235, С245 | L10: 1348 | N10: 1009 | O10: т | P10: т | Q10: 1000 | W10: 0 | X10: 981881691 | Y10: =AT10 -> 0.545793 | AA10: 9864 | AB10: 0 | AC10: 0 | AD10: 0 | AE10: 9844.31 | AF10: 0 | AG10: 0 | AH10: 0 | AI10: 1 | AJ10: 1 | AK10: 1 | AL10: 1 | AM10: 0 | AN10: 0 | AO10: 0 | AP10: 0 | AQ10: 0 | AR10: 0 | AT10: 0.545793 | AV10: 0 | AW10: 1 | AX10: -1 | AY10: 0 | AZ10: 0 | BB10: 0 | BC10: 0 | BD10: 0 | BE10: 0 | BF10: 0 | BG10: 0 | BH10: 0 | BI10: 0 | BJ10: 0 | BK10: 0 | BL10: 0 | BM10: 0 | BN10: 0 | BO10: 0 | BP10: 0 | BQ10: 0 | BR10: 0 | BS10: 0 | BT10: 0 | BU10: 0 | BV10: 0 | BW10: 0 | CV10: 0 | CW10: 0 | CX10: =ROUND(Y10*Source!I75,9) -> 2.5828016 | CY10: =AA10 -> 9864 | CZ10: =AE10 -> 9844.31 | DA10: =AI10 -> 1 | DB10: =ROUND(ROUND(AT10*CZ10,2),6) -> 5372.96 | DC10: =ROUND(ROUND(AT10*AG10,2),6) -> 0 | DF10: =ROUND(ROUND(AE10,2)*CX10,2) -> 25425.9 | DG10: =ROUND(ROUND(AF10,2)*CX10,2) -> 0 | DH10: =ROUND(ROUND(AG10,2)*CX10,2) -> 0 | DI10: =ROUND(ROUND(AH10,2)*CX10,2) -> 0 | DJ10: =DF10 -> 25425.9 | DK10: 0 | DM10: 0 | DO10: 0
A11: =ROW(Source!A75) -> 75 | B11: 56481265 | C11: 56481865 | D11: 54903015 | E11: 1 | F11: 1 | G11: 1079 | H11: 3 | I11: 1.1-1-1145 | J11: ТСН-2001.1 Доп. 79, Р. 1, о. 1, поз. 1145 | K11: Швеллер №№ 12-40, из стали углеродистой обыкновенного качества, спокойной | L11: 1348 | N11: 1009 | O11: т | P11: т | Q11: 1000 | W11: 0 | X11: 975818671 | Y11: =AT11 -> 0.314272 | AA11: 8407.51 | AB11: 0 | AC11: 0 | AD11: 0 | AE11: 8407.51 | AF11: 0 | AG11: 0 | AH11: 0 | AI11: 1 | AJ11: 1 | AK11: 1 | AL11: 1 | AM11: 0 | AN11: 0 | AO11: 0 | AP11: 1 | AQ11: 0 | AR11: 0 | AT11: 0.314272 | AV11: 0 | AW11: 1 | AX11: -1 | AY11: 0 | AZ11: 0 | BB11: 0 | BC11: 0 | BD11: 0 | BE11: 0 | BF11: 0 | BG11: 0 | BH11: 0 | BI11: 0 | BJ11: 0 | BK11: 0 | BL11: 0 | BM11: 0 | BN11: 0 | BO11: 0 | BP11: 0 | BQ11: 0 | BR11: 0 | BS11: 0 | BT11: 0 | BU11: 0 | BV11: 0 | BW11: 0 | CV11: 0 | CW11: 0 | CX11: =ROUND(Y11*Source!I75,9) -> 1.487198 | CY11: =AA11 -> 8407.51 | CZ11: =AE11 -> 8407.51 | DA11: =AI11 -> 1 | DB11: =ROUND(ROUND(AT11*CZ11,2),6) -> 2642.24 | DC11: =ROUND(ROUND(AT11*AG11,2),6) -> 0 | DF11: =ROUND(ROUND(AE11,2)*CX11,2) -> 12503.63 | DG11: =ROUND(ROUND(AF11,2)*CX11,2) -> 0 | DH11: =ROUND(ROUND(AG11,2)*CX11,2) -> 0 | DI11: =ROUND(ROUND(AH11,2)*CX11,2) -> 0 | DJ11: =DF11 -> 12503.63 | DK11: 0 | DM11: 0 | DO11: 0
A12: =ROW(Source!A75) -> 75 | B12: 56481265 | C12: 56481865 | D12: 54912920 | E12: 1 | F12: 1 | G12: 1079 | H12: 3 | I12: 1.7-5-220 | J12: ТСН-2001.1 Доп. 53, Р. 7, о. 5, поз. 220 | K12: Шпилька резьбовая, стальная, оцинкованная, с заостренным концом, в комплекте с шайбой и гайкой, М16x190 мм | L12: 1354 | N12: 1010 | O12: шт. | P12: шт. | Q12: 1 | W12: 0 | X12: 2014927073 | Y12: =AT12 -> 37.192004 | AA12: 29.86 | AB12: 0 | AC12: 0 | AD12: 0 | AE12: 29.8 | AF12: 0 | AG12: 0 | AH12: 0 | AI12: 1 | AJ12: 1 | AK12: 1 | AL12: 1 | AM12: 0 | AN12: 0 | AO12: 0 | AP12: 1 | AQ12: 0 | AR12: 0 | AT12: 37.192004 | AV12: 0 | AW12: 1 | AX12: -1 | AY12: 0 | AZ12: 0 | BB12: 0 | BC12: 0 | BD12: 0 | BE12: 0 | BF12: 0 | BG12: 0 | BH12: 0 | BI12: 0 | BJ12: 0 | BK12: 0 | BL12: 0 | BM12: 0 | BN12: 0 | BO12: 0 | BP12: 0 | BQ12: 0 | BR12: 0 | BS12: 0 | BT12: 0 | BU12: 0 | BV12: 0 | BW12: 0 | CV12: 0 | CW12: 0 | CX12: =ROUND(Y12*Source!I75,9) -> 176 | CY12: =AA12 -> 29.86 | CZ12: =AE12 -> 29.8 | DA12: =AI12 -> 1 | DB12: =ROUND(ROUND(AT12*CZ12,2),6) -> 1108.32 | DC12: =ROUND(ROUND(AT12*AG12,2),6) -> 0 | DF12: =ROUND(ROUND(AE12,2)*CX12,2) -> 5244.8 | DG12: =ROUND(ROUND(AF12,2)*CX12,2) -> 0 | DH12: =ROUND(ROUND(AG12,2)*CX12,2) -> 0 | DI12: =ROUND(ROUND(AH12,2)*CX12,2) -> 0 | DJ12: =DF12 -> 5244.8 | DK12: 0 | DM12: 0 | DO12: 0
A13: =ROW(Source!A75) -> 75 | B13: 56481265 | C13: 56481865 | D13: 54912933 | E13: 1 | F13: 1 | G13: 1079 | H13: 3 | I13: 1.7-5-233 | J13: ТСН-2001.1 Доп. 79, Р. 7, о. 5, поз. 233 | K13: Анкер-болт забивной, распорный, стальной, оцинкованный, с широкой шайбой M12х110 | L13: 1355 | N13: 1010 | O13: 100 шт. | P13: 100 шт. | Q13: 100 | W13: 0 | X13: 856224882 | Y13: =AT13 -> 0.18596 | AA13: 561.16 | AB13: 0 | AC13: 0 | AD13: 0 | AE13: 560.04 | AF13: 0 | AG13: 0 | AH13: 0 | AI13: 1 | AJ13: 1 | AK13: 1 | AL13: 1 | AM13: 0 | AN13: 0 | AO13: 0 | AP13: 1 | AQ13: 0 | AR13: 0 | AT13: 0.18596 | AV13: 0 | AW13: 1 | AX13: -1 | AY13: 0 | AZ13: 0 | BB13: 0 | BC13: 0 | BD13: 0 | BE13: 0 | BF13: 0 | BG13: 0 | BH13: 0 | BI13: 0 | BJ13: 0 | BK13: 0 | BL13: 0 | BM13: 0 | BN13: 0 | BO13: 0 | BP13: 0 | BQ13: 0 | BR13: 0 | BS13: 0 | BT13: 0 | BU13: 0 | BV13: 0 | BW13: 0 | CV13: 0 | CW13: 0 | CX13: =ROUND(Y13*Source!I75,9) -> 0.87999991 | CY13: =AA13 -> 561.16 | CZ13: =AE13 -> 560.04 | DA13: =AI13 -> 1 | DB13: =ROUND(ROUND(AT13*CZ13,2),6) -> 104.15 | DC13: =ROUND(ROUND(AT13*AG13,2),6) -> 0 | DF13: =ROUND(ROUND(AE13,2)*CX13,2) -> 492.84 | DG13: =ROUND(ROUND(AF13,2)*CX13,2) -> 0 | DH13: =ROUND(ROUND(AG13,2)*CX13,2) -> 0 | DI13: =ROUND(ROUND(AH13,2)*CX13,2) -> 0 | DJ13: =DF13 -> 492.84 | DK13: 0 | DM13: 0 | DO13: 0
A14: =ROW(Source!A76) -> 76 | B14: 56481267 | C14: 56481865 | D14: 54902988 | E14: 1 | F14: 1 | G14: 1079 | H14: 3 | I14: 1.1-1-1105 | J14: ТСН-2001.1 Доп. 79, Р. 1, о. 1, поз. 1105 | K14: Прокат листовой из стали С235, С245 для строительных стальных конструкций, толщина более 3 мм | L14: 1348 | N14: 1009 | O14: т | P14: т | Q14: 1000 | W14: 0 | X14: -1891961884 | Y14: =AT14 -> 0.139935 | AA14: 66106.25 | AB14: 0 | AC14: 0 | AD14: 0 | AE14: 6519.2 | AF14: 0 | AG14: 0 | AH14: 0 | AI14: 10.12 | AJ14: 1 | AK14: 1 | AL14: 1 | AM14: 0 | AN14: 0 | AO14: 0 | AP14: 1 | AQ14: 0 | AR14: 0 | AT14: 0.139935 | AV14: 0 | AW14: 1 | AX14: -1 | AY14: 0 | AZ14: 0 | BB14: 0 | BC14: 0 | BD14: 0 | BE14: 0 | BF14: 0 | BG14: 0 | BH14: 0 | BI14: 0 | BJ14: 0 | BK14: 0 | BL14: 0 | BM14: 0 | BN14: 0 | BO14: 0 | BP14: 0 | BQ14: 0 | BR14: 0 | BS14: 0 | BT14: 0 | BU14: 0 | BV14: 0 | BW14: 0 | CV14: 0 | CW14: 0 | CX14: =ROUND(Y14*Source!I76,9) -> 0.66220041 | CY14: =AA14 -> 66106.25 | CZ14: =AE14 -> 6519.2 | DA14: =AI14 -> 10.12 | DB14: =ROUND(ROUND(AT14*CZ14,2),6) -> 912.26 | DC14: =ROUND(ROUND(AT14*AG14,2),6) -> 0 | DF14: =ROUND(ROUND(AE14*AI14,2)*CX14,2) -> 43688.21 | DG14: =ROUND(ROUND(AF14,2)*CX14,2) -> 0 | DH14: =ROUND(ROUND(AG14,2)*CX14,2) -> 0 | DI14: =ROUND(ROUND(AH14,2)*CX14,2) -> 0 | DJ14: =DF14 -> 43688.21 | DK14: 0 | DM14: 0 | DO14: 0
A15: =ROW(Source!A76) -> 76 | B15: 56481267 | C15: 56481865 | D15: 54902999 | E15: 1 | F15: 1 | G15: 1079 | H15: 3 | I15: 1.1-1-1121 | J15: ТСН-2001.1 Доп. 79, Р. 1, о. 1, поз. 1121 | K15: Уголок равнополочный, для строительных стальных конструкций, ширина полки более 70 мм, сталь С235, С245 | L15: 1348 | N15: 1009 | O15: т | P15: т | Q15: 1000 | W15: 0 | X15: 981881691 | Y15: =AT15 -> 0.545793 | AA15: 74374.55 | AB15: 0 | AC15: 0 | AD15: 0 | AE15: 9844.31 | AF15: 0 | AG15: 0 | AH15: 0 | AI15: 7.54 | AJ15: 1 | AK15: 1 | AL15: 1 | AM15: 2 | AN15: 0 | AO15: 0 | AP15: 0 | AQ15: 0 | AR15: 0 | AT15: 0.545793 | AV15: 0 | AW15: 1 | AX15: -1 | AY15: 0 | AZ15: 0 | BB15: 0 | BC15: 0 | BD15: 0 | BE15: 0 | BF15: 0 | BG15: 0 | BH15: 0 | BI15: 0 | BJ15: 0 | BK15: 0 | BL15: 0 | BM15: 0 | BN15: 0 | BO15: 0 | BP15: 0 | BQ15: 0 | BR15: 0 | BS15: 0 | BT15: 0 | BU15: 0 | BV15: 0 | BW15: 0 | CV15: 0 | CW15: 0 | CX15: =ROUND(Y15*Source!I76,9) -> 2.5828016 | CY15: =AA15 -> 74374.55 | CZ15: =AE15 -> 9844.31 | DA15: =AI15 -> 7.54 | DB15: =ROUND(ROUND(AT15*CZ15,2),6) -> 5372.96 | DC15: =ROUND(ROUND(AT15*AG15,2),6) -> 0 | DF15: =ROUND(ROUND(AE15*AI15,2)*CX15,2) -> 191711.29 | DG15: =ROUND(ROUND(AF15,2)*CX15,2) -> 0 | DH15: =ROUND(ROUND(AG15,2)*CX15,2) -> 0 | DI15: =ROUND(ROUND(AH15,2)*CX15,2) -> 0 | DJ15: =DF15 -> 191711.29 | DK15: 0 | DM15: 0 | DO15: 0
A16: =ROW(Source!A76) -> 76 | B16: 56481267 | C16: 56481865 | D16: 54903015 | E16: 1 | F16: 1 | G16: 1079 | H16: 3 | I16: 1.1-1-1145 | J16: ТСН-2001.1 Доп. 79, Р. 1, о. 1, поз. 1145 | K16: Швеллер №№ 12-40, из стали углеродистой обыкновенного качества, спокойной | L16: 1348 | N16: 1009 | O16: т | P16: т | Q16: 1000 | W16: 0 | X16: 975818671 | Y16: =AT16 -> 0.314272 | AA16: 94436.68 | AB16: 0 | AC16: 0 | AD16: 0 | AE16: 8407.51 | AF16: 0 | AG16: 0 | AH16: 0 | AI16: 11.21 | AJ16: 1 | AK16: 1 | AL16: 1 | AM16: 0 | AN16: 0 | AO16: 0 | AP16: 1 | AQ16: 0 | AR16: 0 | AT16: 0.314272 | AV16: 0 | AW16: 1 | AX16: -1 | AY16: 0 | AZ16: 0 | BB16: 0 | BC16: 0 | BD16: 0 | BE16: 0 | BF16: 0 | BG16: 0 | BH16: 0 | BI16: 0 | BJ16: 0 | BK16: 0 | BL16: 0 | BM16: 0 | BN16: 0 | BO16: 0 | BP16: 0 | BQ16: 0 | BR16: 0 | BS16: 0 | BT16: 0 | BU16: 0 | BV16: 0 | BW16: 0 | CV16: 0 | CW16: 0 | CX16: =ROUND(Y16*Source!I76,9) -> 1.487198 | CY16: =AA16 -> 94436.68 | CZ16: =AE16 -> 8407.51 | DA16: =AI16 -> 11.21 | DB16: =ROUND(ROUND(AT16*CZ16,2),6) -> 2642.24 | DC16: =ROUND(ROUND(AT16*AG16,2),6) -> 0 | DF16: =ROUND(ROUND(AE16*AI16,2)*CX16,2) -> 140165.72 | DG16: =ROUND(ROUND(AF16,2)*CX16,2) -> 0 | DH16: =ROUND(ROUND(AG16,2)*CX16,2) -> 0 | DI16: =ROUND(ROUND(AH16,2)*CX16,2) -> 0 | DJ16: =DF16 -> 140165.72 | DK16: 0 | DM16: 0 | DO16: 0
A17: =ROW(Source!A76) -> 76 | B17: 56481267 | C17: 56481865 | D17: 54912920 | E17: 1 | F17: 1 | G17: 1079 | H17: 3 | I17: 1.7-5-220 | J17: ТСН-2001.1 Доп. 53, Р. 7, о. 5, поз. 220 | K17: Шпилька резьбовая, стальная, оцинкованная, с заостренным концом, в комплекте с шайбой и гайкой, М16x190 мм | L17: 1354 | N17: 1010 | O17: шт. | P17: шт. | Q17: 1 | W17: 0 | X17: 2014927073 | Y17: =AT17 -> 37.192004 | AA17: 357.42 | AB17: 0 | AC17: 0 | AD17: 0 | AE17: 29.8 | AF17: 0 | AG17: 0 | AH17: 0 | AI17: 11.97 | AJ17: 1 | AK17: 1 | AL17: 1 | AM17: 0 | AN17: 0 | AO17: 0 | AP17: 1 | AQ17: 0 | AR17: 0 | AT17: 37.192004 | AV17: 0 | AW17: 1 | AX17: -1 | AY17: 0 | AZ17: 0 | BB17: 0 | BC17: 0 | BD17: 0 | BE17: 0 | BF17: 0 | BG17: 0 | BH17: 0 | BI17: 0 | BJ17: 0 | BK17: 0 | BL17: 0 | BM17: 0 | BN17: 0 | BO17: 0 | BP17: 0 | BQ17: 0 | BR17: 0 | BS17: 0 | BT17: 0 | BU17: 0 | BV17: 0 | BW17: 0 | CV17: 0 | CW17: 0 | CX17: =ROUND(Y17*Source!I76,9) -> 176 | CY17: =AA17 -> 357.42 | CZ17: =AE17 -> 29.8 | DA17: =AI17 -> 11.97 | DB17: =ROUND(ROUND(AT17*CZ17,2),6) -> 1108.32 | DC17: =ROUND(ROUND(AT17*AG17,2),6) -> 0 | DF17: =ROUND(ROUND(AE17*AI17,2)*CX17,2) -> 62780.96 | DG17: =ROUND(ROUND(AF17,2)*CX17,2) -> 0 | DH17: =ROUND(ROUND(AG17,2)*CX17,2) -> 0 | DI17: =ROUND(ROUND(AH17,2)*CX17,2) -> 0 | DJ17: =DF17 -> 62780.96 | DK17: 0 | DM17: 0 | DO17: 0
A18: =ROW(Source!A76) -> 76 | B18: 56481267 | C18: 56481865 | D18: 54912933 | E18: 1 | F18: 1 | G18: 1079 | H18: 3 | I18: 1.7-5-233 | J18: ТСН-2001.1 Доп. 79, Р. 7, о. 5, поз. 233 | K18: Анкер-болт забивной, распорный, стальной, оцинкованный, с широкой шайбой M12х110 | L18: 1355 | N18: 1010 | O18: 100 шт. | P18: 100 шт. | Q18: 100 | W18: 0 | X18: 856224882 | Y18: =AT18 -> 0.18596 | AA18: 11032.41 | AB18: 0 | AC18: 0 | AD18: 0 | AE18: 560.04 | AF18: 0 | AG18: 0 | AH18: 0 | AI18: 19.66 | AJ18: 1 | AK18: 1 | AL18: 1 | AM18: 0 | AN18: 0 | AO18: 0 | AP18: 1 | AQ18: 0 | AR18: 0 | AT18: 0.18596 | AV18: 0 | AW18: 1 | AX18: -1 | AY18: 0 | AZ18: 0 | BB18: 0 | BC18: 0 | BD18: 0 | BE18: 0 | BF18: 0 | BG18: 0 | BH18: 0 | BI18: 0 | BJ18: 0 | BK18: 0 | BL18: 0 | BM18: 0 | BN18: 0 | BO18: 0 | BP18: 0 | BQ18: 0 | BR18: 0 | BS18: 0 | BT18: 0 | BU18: 0 | BV18: 0 | BW18: 0 | CV18: 0 | CW18: 0 | CX18: =ROUND(Y18*Source!I76,9) -> 0.87999991 | CY18: =AA18 -> 11032.41 | CZ18: =AE18 -> 560.04 | DA18: =AI18 -> 19.66 | DB18: =ROUND(ROUND(AT18*CZ18,2),6) -> 104.15 | DC18: =ROUND(ROUND(AT18*AG18,2),6) -> 0 | DF18: =ROUND(ROUND(AE18*AI18,2)*CX18,2) -> 9689.14 | DG18: =ROUND(ROUND(AF18,2)*CX18,2) -> 0 | DH18: =ROUND(ROUND(AG18,2)*CX18,2) -> 0 | DI18: =ROUND(ROUND(AH18,2)*CX18,2) -> 0 | DJ18: =DF18 -> 9689.14 | DK18: 0 | DM18: 0 | DO18: 0
A19: =ROW(Source!A87) -> 87 | B19: 56481265 | C19: 56491135 | D19: 48547175 | E19: 1 | F19: 1 | G19: 1079 | H19: 3 | I19: 1.1-1-165 | J19: ТСН-2001.1 Доп. 67, Р. 1, о. 1, поз. 165 | K19: Грунтовка глифталевая, типа ГФ-021 | L19: 1348 | N19: 1009 | O19: т | P19: т | Q19: 1000 | W19: 0 | X19: 667244177 | Y19: =AT19 -> 0.009 | AA19: 18660.61 | AB19: 0 | AC19: 0 | AD19: 0 | AE19: 18660.61 | AF19: 0 | AG19: 0 | AH19: 0 | AI19: 1 | AJ19: 1 | AK19: 1 | AL19: 1 | AM19: 0 | AN19: 0 | AO19: 0 | AP19: 0 | AQ19: 0 | AR19: 0 | AT19: 0.009 | AV19: 0 | AW19: 1 | AX19: -1 | AY19: 0 | AZ19: 0 | BB19: 0 | BC19: 0 | BD19: 0 | BE19: 0 | BF19: 0 | BG19: 0 | BH19: 0 | BI19: 0 | BJ19: 0 | BK19: 0 | BL19: 0 | BM19: 0 | BN19: 0 | BO19: 0 | BP19: 0 | BQ19: 0 | BR19: 0 | BS19: 0 | BT19: 0 | BU19: 0 | BV19: 0 | BW19: 0 | CV19: 0 | CW19: 0 | CX19: =ROUND(Y19*Source!I87,9) -> 0.01284028 | CY19: =AA19 -> 18660.61 | CZ19: =AE19 -> 18660.61 | DA19: =AI19 -> 1 | DB19: =ROUND(ROUND(AT19*CZ19,2),6) -> 167.95 | DC19: =ROUND(ROUND(AT19*AG19,2),6) -> 0 | DF19: =ROUND(ROUND(AE19,2)*CX19,2) -> 239.61 | DG19: =ROUND(ROUND(AF19,2)*CX19,2) -> 0 | DH19: =ROUND(ROUND(AG19,2)*CX19,2) -> 0 | DI19: =ROUND(ROUND(AH19,2)*CX19,2) -> 0 | DJ19: =DF19 -> 239.61 | DK19: 0 | DM19: 0 | DO19: 0
A20: =ROW(Source!A88) -> 88 | B20: 56481267 | C20: 56491135 | D20: 48547175 | E20: 1 | F20: 1 | G20: 1079 | H20: 3 | I20: 1.1-1-165 | J20: ТСН-2001.1 Доп. 67, Р. 1, о. 1, поз. 165 | K20: Грунтовка глифталевая, типа ГФ-021 | L20: 1348 | N20: 1009 | O20: т | P20: т | Q20: 1000 | W20: 0 | X20: 667244177 | Y20: =AT20 -> 0.009 | AA20: 66804.98 | AB20: 0 | AC20: 0 | AD20: 0 | AE20: 18660.61 | AF20: 0 | AG20: 0 | AH20: 0 | AI20: 3.58 | AJ20: 1 | AK20: 1 | AL20: 1 | AM20: 2 | AN20: 0 | AO20: 0 | AP20: 0 | AQ20: 0 | AR20: 0 | AT20: 0.009 | AV20: 0 | AW20: 1 | AX20: -1 | AY20: 0 | AZ20: 0 | BB20: 0 | BC20: 0 | BD20: 0 | BE20: 0 | BF20: 0 | BG20: 0 | BH20: 0 | BI20: 0 | BJ20: 0 | BK20: 0 | BL20: 0 | BM20: 0 | BN20: 0 | BO20: 0 | BP20: 0 | BQ20: 0 | BR20: 0 | BS20: 0 | BT20: 0 | BU20: 0 | BV20: 0 | BW20: 0 | CV20: 0 | CW20: 0 | CX20: =ROUND(Y20*Source!I88,9) -> 0.01284028 | CY20: =AA20 -> 66804.98 | CZ20: =AE20 -> 18660.61 | DA20: =AI20 -> 3.58 | DB20: =ROUND(ROUND(AT20*CZ20,2),6) -> 167.95 | DC20: =ROUND(ROUND(AT20*AG20,2),6) -> 0 | DF20: =ROUND(ROUND(AE20*AI20,2)*CX20,2) -> 857.79 | DG20: =ROUND(ROUND(AF20,2)*CX20,2) -> 0 | DH20: =ROUND(ROUND(AG20,2)*CX20,2) -> 0 | DI20: =ROUND(ROUND(AH20,2)*CX20,2) -> 0 | DJ20: =DF20 -> 857.79 | DK20: 0 | DM20: 0 | DO20: 0
