Workbook

Sheet б_н
A1: =Source!B1 -> Smeta.RU (495) 974-1589
J2: Форма № 4б
B3: "СОГЛАСОВАНО" | G3: "УТВЕРЖДАЮ"
B6: =CONCATENATE("______________________ ", IF(Source!AL12<>"", Source!AL12, "")) -> ______________________ | G6: =CONCATENATE("______________________ ", IF(Source!AH12<>"", Source!AH12, "")) -> ______________________
B7: "_____"________________ 2025 г. | G7: "_____"________________ 2025 г.
A10: Капитальный ремонт здания Государственного бюджетного общеобразовательного учреждения города Москвы «Школа № 236» по адресу: г. Москва, ул. Клязьминская, д. 7, к. 4. I этап | AP10: Капитальный ремонт здания Государственного бюджетного общеобразовательного учреждения города Москвы «Школа № 236» по адресу: г. Москва, ул. Клязьминская, д. 7, к. 4. I этап. б/н Возвратные средства
A11: (наименование стройки и/или объекта)
A13: =CONCATENATE( "ЛОКАЛЬНАЯ СМЕТА № ",IF(Source!F20<>"Новая локальная смета", Source!F20, "")) -> ЛОКАЛЬНАЯ СМЕТА № б/н
A15: =IF(Source!G20<>"Новая локальная смета", Source!G20, "") -> Возвратные средства
A16: (наименование работ и затрат)
A18: =CONCATENATE( "Основание: чертежи № ", Source!J20) -> Основание: чертежи № 0224-00272-01-0-ООС2
I20: В базисном уровне цен | J20: В текущем уровне цен
E21: Сметная стоимость | I21: =I22+I23+I24+I25 -> 0 | J21: =J22+J23+J24+J25 -> 0 | K21: тыс.руб.
E22: Строительные работы | I22: =ROUND((Source!F84)/1000, 2) -> 0 | J22: =ROUND((Source!P84)/1000, 2) -> 0 | K22: тыс.руб.
E23: Работы по монтажу оборудования | I23: =ROUND((Source!F85)/1000, 2) -> 0 | J23: =ROUND((Source!P85)/1000, 2) -> 0 | K23: тыс.руб.
E24: Оборудование | I24: =ROUND((Source!F76)/1000, 2) -> 0 | J24: =ROUND((Source!P76)/1000, 2) -> 0 | K24: тыс.руб.
E25: Прочие работы и затраты | I25: =ROUND((Source!F86+Source!F87)/1000, 2) -> 0 | J25: =ROUND((Source!P86+Source!P87)/1000, 2) -> 0 | K25: тыс.руб.
E26: Средства на оплату труда | I26: =(Source!F82+ Source!F81)/1000 -> 0 | J26: =((Source!P82 + Source!P81)/1000) -> 0 | K26: тыс.руб.
E27: Затраты труда | I27: =Source!F89 -> 0 | K27: чел.-ч.
E28: Кроме того:
E29: Возврат материалов | I29: =SUM(Y35:Y56)/1000 -> 86.06965 | J29: =SUM(Z35:Z56)/1000 -> 733.43555 | K29: тыс.руб.
A31: Составлен(а) по ТСН-2001 с учетом Дополнения №: 79
A32: № и период сборника коэффициентов (индексов) пересчета: Коэффициенты к ТСН-2001 МГЭ Дополнение 79, ремонт №216/79 III квартал 2025 года и Коэффициенты к ТСН-2001.13-2 Дополнение 45 №62/45 III квартал 2025 года | M32: 3 кв-л сентябрь | AP32: № и период сборника коэффициентов (индексов) пересчета: Коэффициенты к ТСН-2001 МГЭ Дополнение 79, ремонт №216/79 III квартал 2025 года и Коэффициенты к ТСН-2001.13-2 Дополнение 45 №62/45 III квартал 2025 года
A33: № п/п | B33: Шифр расценки и коды ресурсов | C33: Наименование работ и затрат | D33: Ед. изм. | E33: Кол-во единиц | F33: Цена на ед. изм., руб. | G33: Попра- вочные коэффи- циенты | H33: Коэффи- циенты зимних удорожа- ний | I33: Всего в ценах на январь 2000 года, руб. | J33: Коэффи- циенты (индек- сы) пере- счета, нормы НР и СП | K33: ВСЕГО затрат в текущем уровне цен, руб.
A34: 1 | B34: 2 | C34: 3 | D34: 4 | E34: 5 | F34: 6 | G34: 7 | H34: 8 | I34: 9 | J34: 10 | K34: 11
A36: =CONCATENATE("Раздел: ",IF(Source!G24<>"Новый раздел", Source!G24, "")) -> Раздел: Возвратные средства
A37: 1 | B37: =Source!F28 -> 1.7-11-59 | C37: ВОЗВРАТ_x000D_ Лом стальной, вид лома 3А, для расчета возвратных сумм | D37: =Source!H28 -> т | E37: =Source!I28 -> 25.996 | F37: =Source!AL28 -> 2092.2 | G37: =Source!DD28 | H37: =Source!AW29 -> 1 | I37: =Source!T28 -> 54388.83 | J37: =IF(Source!BC29<> 0, Source!BC29, 1) -> 8.6 | K37: =Source!T29 -> 467743.94 | M37: 1.7-11-61 | Q37: =Source!X28 -> 0 | R37: =Source!X29 -> 0 | S37: =Source!Y28 -> 0 | T37: =Source!Y29 -> 0 | U37: =ROUND((175/100)*ROUND(Source!R28, 2), 2) -> 0 | V37: =ROUND((0/100)*ROUND(Source!R29, 2), 2) -> 0 | Y37: =I37 -> 54388.83 | Z37: =K37 -> 467743.94 | AC37: 3
C38: ВСЕГО по позиции: | H38: =I37+0 -> 54388.83 | J38: =K37+0 -> 467743.94
A40: 2 | B40: =Source!F30 -> 1.7-11-60 | C40: ВОЗВРАТ_x000D_ Лом стальной, вид лома 5А, для расчета возвратных сумм | D40: =Source!H30 -> т | E40: =Source!I30 -> 13.742 | F40: =Source!AL30 -> 2156.67 | G40: =Source!DD30 | H40: =Source!AW31 -> 1 | I40: =Source!T30 -> 29636.96 | J40: =IF(Source!BC31<> 0, Source!BC31, 1) -> 8.31 | K40: =Source!T31 -> 246283.14 | M40: 1.17-11-59 кусковой | Q40: =Source!X30 -> 0 | R40: =Source!X31 -> 0 | S40: =Source!Y30 -> 0 | T40: =Source!Y31 -> 0 | U40: =ROUND((175/100)*ROUND(Source!R30, 2), 2) -> 0 | V40: =ROUND((0/100)*ROUND(Source!R31, 2), 2) -> 0 | Y40: =I40 -> 29636.96 | Z40: =K40 -> 246283.14 | AC40: 3
C41: ВСЕГО по позиции: | H41: =I40+0 -> 29636.96 | J41: =K40+0 -> 246283.14
A43: 3 | B43: =Source!F32 -> 1.7-11-61 | C43: ВОЗВРАТ_x000D_ Лом стальной, вид лома 12А, для расчета возвратных сумм (прим. алюминий) | D43: =Source!H32 -> т | E43: =Source!I32 -> 0.854 | F43: =Source!AL32 -> 1853.64 | G43: =Source!DD32 | H43: =Source!AW33 -> 1 | I43: =Source!T32 -> 1583.01 | J43: =IF(Source!BC33<> 0, Source!BC33, 1) -> 9.62 | K43: =Source!T33 -> 15228.56 | Q43: =Source!X32 -> 0 | R43: =Source!X33 -> 0 | S43: =Source!Y32 -> 0 | T43: =Source!Y33 -> 0 | U43: =ROUND((175/100)*ROUND(Source!R32, 2), 2) -> 0 | V43: =ROUND((0/100)*ROUND(Source!R33, 2), 2) -> 0 | Y43: =I43 -> 1583.01 | Z43: =K43 -> 15228.56 | AC43: 3
C44: ВСЕГО по позиции: | H44: =I43+0 -> 1583.01 | J44: =K43+0 -> 15228.56
A46: 4 | B46: =Source!F34 -> 1.7-11-63 | C46: ВОЗВРАТ_x000D_ Лом чугунный, вид лома 22А, для расчета возвратных сумм | D46: =Source!H34 -> т | E46: =Source!I34 -> 0.209 | F46: =Source!AL34 -> 2205.03 | G46: =Source!DD34 | H46: =Source!AW35 -> 1 | I46: =Source!T34 -> 460.85 | J46: =IF(Source!BC35<> 0, Source!BC35, 1) -> 9.07 | K46: =Source!T35 -> 4179.91 | Q46: =Source!X34 -> 0 | R46: =Source!X35 -> 0 | S46: =Source!Y34 -> 0 | T46: =Source!Y35 -> 0 | U46: =ROUND((175/100)*ROUND(Source!R34, 2), 2) -> 0 | V46: =ROUND((0/100)*ROUND(Source!R35, 2), 2) -> 0 | Y46: =I46 -> 460.85 | Z46: =K46 -> 4179.91 | AC46: 3
C47: ВСЕГО по позиции: | H47: =I46+0 -> 460.85 | J47: =K46+0 -> 4179.91
A50: =CONCATENATE("Итого по разделу: ",IF(Source!G37<>"Новый раздел", Source!G37, "")) -> Итого по разделу: Возвратные средства | H50: =SUM(O36:O49) -> 0 | J50: =SUM(P36:P49) -> 0
A51: Итого по ТСН-2001.16 | I51: =SUM(W36:W50) -> 0 | J51: =SUM(X36:X50) -> 0
A52: Итого возвратных сумм | H52: =SUM(Y36:Y51) -> 86069.65 | J52: =SUM(Z36:Z51) -> 733435.55
A54: =CONCATENATE("Итого по локальной смете: ",IF(Source!G67<>"Новая локальная смета", Source!G67, "")) -> Итого по локальной смете: Возвратные средства | H54: =SUM(O35:O53) -> 0 | J54: =SUM(P35:P53) -> 0
A55: Итого по ТСН-2001.16 | I55: =SUM(W35:W54) -> 0 | J55: =SUM(X35:X54) -> 0
A56: Итого возвратных сумм | H56: =SUM(Y35:Y55) -> 86069.65 | J56: =SUM(Z35:Z55) -> 733435.55
A59: Составил | C59: =IF(Source!AC12<>"", Source!AC12," ") | H59: =IF(Source!AB12<>"", Source!AB12," ") -> Лукьянова А.Л.
C60: (должность, подпись, инициалы, фамилия)
A62: Проверил | C62: =IF(Source!AE12<>"", Source!AE12," ") | H62: =IF(Source!AD12<>"", Source!AD12," ")
C63: (должность, подпись, инициалы, фамилия)

Sheet Ведомость объемов работ
A1: =Source!B1 -> Smeta.RU (495) 974-1589
E3: "УТВЕРЖДАЮ"
D5: ___________________________
D7: ___________________________
D9: " ___ " ___________ 20 ___ г.
B12: =CONCATENATE("Ведомость объемов работ ", IF(Source!AN15<>"", Source!AN15," ")) -> Ведомость объемов работ
B13: =CONCATENATE(Source!F12, " ", Source!G12) -> б/н б/н Возвратные средства
A16: № п/п | B16: № в ЛСР | C16: Наименование работ и затрат | D16: Единица измерения | E16: Количество | F16: Ссылка на чертежи, спецификации | G16: Формула расчета, расчет объемов работ и расхода материалов | H16: Примечание
A17: 1 | B17: 2 | C17: 3 | D17: 4 | E17: 5 | F17: 6 | G17: 7 | H17: 8
A18: =CONCATENATE("Локальная смета: ", Source!G20) -> Локальная смета: Возвратные средства
A19: =CONCATENATE("Раздел: ", Source!G24) -> Раздел: Возвратные средства
A20: 1 | B20: =Source!E28 -> 1 | C20: =Source!G28 -> Лом стальной, вид лома 3А, для расчета возвратных сумм | D20: т | E20: =Source!I28 -> 25.996 | F20: =Source!U24 | G20: =Source!I28 -> 25.996
A21: 2 | B21: =Source!E30 -> 2 | C21: =Source!G30 -> Лом стальной, вид лома 5А, для расчета возвратных сумм | D21: т | E21: =Source!I30 -> 13.742 | F21: =Source!U24 | G21: =Source!I30 -> 13.742
A22: 3 | B22: =Source!E32 -> 3 | C22: =Source!G32 -> Лом стальной, вид лома 12А, для расчета возвратных сумм (прим. алюминий) | D22: т | E22: =Source!I32 -> 0.854 | F22: =Source!U24 | G22: =Source!I32 -> 0.854
A23: 4 | B23: =Source!E34 -> 4 | C23: =Source!G34 -> Лом чугунный, вид лома 22А, для расчета возвратных сумм | D23: т | E23: =Source!I34 -> 0.209 | F23: =Source!U24 | G23: =Source!I34 -> 0.209
C26: Главный инженер проекта _________________ | D26: =IF(Source!X12<>"", Source!X12," ")
C28: Составил _________________ | D28: =IF(Source!AB12<>"", Source!AB12," ") -> Лукьянова А.Л.

Sheet Source
A1: 0 | B1: Smeta.RU (495) 974-1589 | D1: _PS_ | F1: 0 | G1: 0 | H1: 0 | I1: Smeta.RU | K1: 1 | L1: 74562 | M1: 10 | N1: 11 | O1: 14 | P1: 0 | Q1: 0
A4: 1 | B4: 1 | C4: -1 | G4: Капитальный ремонт здания Государственного бюджетного общеобразовательного учреждения города Москвы «Школа № 236» по адресу: г. Москва, ул. Клязьминская, д. 7, к. 4. I этап | EC4: 0
A12: 1 | B12: 137 | C12: 0 | D12: =ROW(A97) -> 97 | E12: 0 | F12: б/н | G12: б/н Возвратные средства | I12: 0 | J12: 0224-00272-01-0-ООС2 | K12: 0 | L12: 0 | M12: 4098 | O12: 0 | P12: 0 | Q12: 0 | R12: 0 | S12: 0 | T12: 1 | V12: 0 | AB12: Лукьянова А.Л. | BB12: 0 | BH12: Сметные нормы списания | BI12: Коды ОКП для ТСН-2001 МГЭ Дополнение 79 | BJ12: 1 | BK12: 1 | BL12: 0 | BM12: 0 | BN12: 1 | BO12: 0 | BP12: 6 | BQ12: 2 | BR12: 1 | BS12: 1 | BT12: 0 | BU12: 0 | BV12: 0 | BW12: 0 | BX12: 0 | BY12: ТСН-2001 (МГЭ) Доп 79 - Ремонт | BZ12: Типовой расчет для ТСН-2001 МГЭ, Дополнение 79, ремонт | CA12: Территориальные сметные нормативы для Москвы ТСН-2001 (МГЭ), дополнение 79 | CB12: Территориальные сметные нормативы для Москвы ТСН-2001 (МГЭ), дополнение 79 | CC12: Территориальные сметные нормативы для Москвы ТСН-2001 (МГЭ), дополнение 79 | CD12: Территориальные сметные нормативы для Москвы ТСН-2001 (МГЭ), дополнение 79 | CE12: Поправки для ТСН-2001 от 03.10.2025 г. доп.79 | CF12: 0 | CG12: 0 | CH12: 8200 | CK12: 79 | CQ12: Территориальные сметные нормативы для Москвы (ТСН-2001) | CR12: ТЕР | CS12: 41660 | CT12: 1 | CU12: 79 | CY12: 0 | EC12: 0
A15: 15 | B15: 1
A18: 52 | B18: =B97 -> 137 | C18: =C97 -> 1 | D18: =D97 -> 12 | E18: =E97 -> 0 | F18: =F97 -> б/н | G18: =G97 -> б/н Возвратные средства | O18: =O97 -> 0 | P18: =P97 -> 0 | Q18: =Q97 -> 0 | R18: =R97 -> 0 | S18: =S97 -> 0 | T18: =T97 -> 86069.65 | U18: =U97 -> 0 | V18: =V97 -> 0 | ... GX18: =GX97 -> 0
A20: 3 | B20: 1 | D20: =ROW(A67) -> 67 | F20: б/н | G20: Возвратные средства | I20: 0 | J20: 0224-00272-01-0-ООС2 | K20: -1 | L20: б/н | S20: 0 | T20: 0 | V20: 0 | AB20: Лукьянова А.Л. | BX20: 0 | CF20: 0 | CG20: 0
A22: 52 | B22: =B67 -> 1 | C22: =C67 -> 3 | D22: =D67 -> 20 | E22: =E67 -> 0 | F22: =F67 -> б/н | G22: =G67 -> Возвратные средства | O22: =O67 -> 0 | P22: =P67 -> 0 | Q22: =Q67 -> 0 | R22: =R67 -> 0 | S22: =S67 -> 0 | T22: =T67 -> 86069.65 | U22: =U67 -> 0 | V22: =V67 -> 0 | ... GX22: =GX67 -> 0
A24: 4 | B24: 1 | D24: =ROW(A37) -> 37 | G24: Возвратные средства | I24: 0 | K24: -1 | S24: 0 | T24: 0 | V24: 0 | BX24: 0 | CJ24: 0
A26: 52 | B26: =B37 -> 1 | C26: =C37 -> 4 | D26: =D37 -> 24 | E26: =E37 -> 0 | F26: =F37 | G26: =G37 -> Возвратные средства | O26: =O37 -> 0 | P26: =P37 -> 0 | Q26: =Q37 -> 0 | R26: =R37 -> 0 | S26: =S37 -> 0 | T26: =T37 -> 86069.65 | U26: =U37 -> 0 | V26: =V37 -> 0 | ... GX26: =GX37 -> 0
A28: 17 | B28: 1 | E28: 1 | F28: 1.7-11-59 | G28: Лом стальной, вид лома 3А, для расчета возвратных сумм | H28: т | I28: 25.996 | J28: 0 | K28: 25.996 | O28: =ROUND(CP28*I28,2) -> 0 | P28: =ROUND(CQ28*I28,2) -> 0 | Q28: =ROUND(CR28*I28,2) -> 0 | R28: =ROUND(CS28*I28,2) -> 0 | S28: =ROUND(CT28*I28,2) -> 0 | T28: =ROUND((ROUND((AC28*I28),2)*BC28),2) -> 54388.83 | U28: =CV28*I28 -> 0 | V28: =CW28*I28 -> 0 | W28: =ROUND(CX28*I28,2) -> 0 | X28: =ROUND(CY28,2) -> 0 | Y28: =ROUND(CZ28,2) -> 0 | AA28: 56526432 | AB28: =ROUND(0,6) -> 0 | AC28: =ROUND((ES28),6) -> 2092.2 | AD28: =ROUND(0,6) -> 0 | AE28: =ROUND(0,6) -> 0 | AF28: =ROUND(0,6) -> 0 | AG28: =ROUND((ES28),6) -> 2092.2 | AH28: =0 -> 0 | AI28: =0 -> 0 | AJ28: =0 -> 0 | AK28: 2092.2 | AL28: 2092.2 | AM28: 0 | AN28: 0 | AO28: 0 | AP28: 0 | AQ28: 0 | AR28: 0 | AS28: 0 | AT28: 0 | AU28: 0 | AV28: 1 | AW28: 1 | AZ28: 1 | BA28: 1 | BB28: 1 | BC28: 1 | BH28: 3 | BI28: 1 | BJ28: ТСН-2001.1 Доп. 67, Р. 7, о. 11, поз. 59 | BM28: 700000 | BN28: 0 | BP28: 0 | BQ28: 203 | BR28: 0 | BS28: 1 | BT28: 1 | BU28: 1 | BV28: 1 | BW28: 1 | BX28: 1 | BZ28: 0 | CA28: 0 | CE28: 32 | CF28: 0 | CG28: 0 | CM28: 0 | CO28: 0 | CP28: =0 -> 0 | CQ28: =0 -> 0 | CR28: =0 -> 0 | CS28: =0 -> 0 | CT28: =0 -> 0 | CU28: =ROUND((ROUND((AC28*1),2)*BC28),2) -> 2092.2 | CV28: =0 -> 0 | CW28: =0 -> 0 | CX28: =0 -> 0 | CY28: =0 -> 0 | CZ28: =0 -> 0 | DN28: 0 | DO28: 0 | DP28: 1 | DQ28: 1 | DU28: 1009 | DV28: т | DW28: т | DX28: 1000 | EE28: 55586417 | EF28: 203 | EG28: Возврат | EH28: 0 | EJ28: 1 | EK28: 700000 | EL28: ТСН-2001.1-7. 7-11-59...7-11-63 (Возврат) | EM28: ТСН-2001.1-3 | EQ28: 0 | ER28: 2092.2 | ES28: 2092.2 | ET28: 0 | EU28: 0 | EV28: 0 | EW28: 0 | EX28: 0 | EY28: 0 | FQ28: 0 | FR28: 0 | FS28: 0 | FX28: 0 | FY28: 0 | GD28: 1 | GF28: -1131265837 | GG28: 2 | GH28: 1 | GI28: -2 | GJ28: 0 | GK28: 0 | GL28: =ROUND(IF(AND(BH28=3,BI28=3,FS28<>0),P28,0),2) -> 0 | GM28: =ROUND(O28+X28+Y28,2)+GX28 -> 0 | GN28: =IF(OR(BI28=0,BI28=1),GM28-GX28,0) -> 0 | GO28: =IF(BI28=2,GM28-GX28,0) -> 0 | GP28: =IF(BI28=4,GM28-GX28,0) -> 0 | GR28: 0 | GS28: 3 | GT28: 0 | GV28: =ROUND((GT28),6) -> 0 | GW28: 1 | GX28: =ROUND(HC28*I28,2) -> 0 | HA28: 0 | HB28: 0 | HC28: =GV28*GW28 -> 0 | HS28: 0 | IK28: 0
A29: 17 | B29: 1 | E29: 1 | F29: 1.7-11-59 | G29: Лом стальной, вид лома 3А, для расчета возвратных сумм | H29: т | I29: 25.996 | J29: 0 | K29: 25.996 | O29: =ROUND(CP29*I29,2) -> 0 | P29: =ROUND(CQ29*I29,2) -> 0 | Q29: =ROUND(CR29*I29,2) -> 0 | R29: =ROUND(CS29*I29,2) -> 0 | S29: =ROUND(CT29*I29,2) -> 0 | T29: =ROUND((ROUND((AC29*I29),2)*BC29),2) -> 467743.94 | U29: =CV29*I29 -> 0 | V29: =CW29*I29 -> 0 | W29: =ROUND(CX29*I29,2) -> 0 | X29: =ROUND(CY29,2) -> 0 | Y29: =ROUND(CZ29,2) -> 0 | AA29: 56526434 | AB29: =ROUND(0,6) -> 0 | AC29: =ROUND((ES29),6) -> 2092.2 | AD29: =ROUND(0,6) -> 0 | AE29: =ROUND(0,6) -> 0 | AF29: =ROUND(0,6) -> 0 | AG29: =ROUND((ES29),6) -> 2092.2 | AH29: =0 -> 0 | AI29: =0 -> 0 | AJ29: =0 -> 0 | AK29: 2092.2 | AL29: 2092.2 | AM29: 0 | AN29: 0 | AO29: 0 | AP29: 0 | AQ29: 0 | AR29: 0 | AS29: 0 | AT29: 0 | AU29: 0 | AV29: 1 | AW29: 1 | AZ29: 1 | BA29: 1 | BB29: 1 | BC29: 8.6 | BH29: 3 | BI29: 1 | BJ29: ТСН-2001.1 Доп. 67, Р. 7, о. 11, поз. 59 | BM29: 700000 | BN29: 0 | BO29: 1.7-11-59 | BP29: 1 | BQ29: 203 | BR29: 0 | BS29: 1 | BT29: 1 | BU29: 1 | BV29: 1 | BW29: 1 | BX29: 1 | BZ29: 0 | CA29: 0 | CE29: 32 | CF29: 0 | CG29: 0 | CM29: 0 | CO29: 0 | CP29: =0 -> 0 | CQ29: =0 -> 0 | CR29: =0 -> 0 | CS29: =0 -> 0 | CT29: =0 -> 0 | CU29: =ROUND((ROUND((AC29*1),2)*BC29),2) -> 17992.92 | CV29: =0 -> 0 | CW29: =0 -> 0 | CX29: =0 -> 0 | CY29: =0 -> 0 | CZ29: =0 -> 0 | DN29: 0 | DO29: 0 | DP29: 1 | DQ29: 1 | DU29: 1009 | DV29: т | DW29: т | DX29: 1000 | EE29: 55586417 | EF29: 203 | EG29: Возврат | EH29: 0 | EJ29: 1 | EK29: 700000 | EL29: ТСН-2001.1-7. 7-11-59...7-11-63 (Возврат) | EM29: ТСН-2001.1-3 | EQ29: 0 | ER29: 2092.2 | ES29: 2092.2 | ET29: 0 | EU29: 0 | EV29: 0 | EW29: 0 | EX29: 0 | EY29: 0 | FQ29: 0 | FR29: 0 | FS29: 0 | FX29: 0 | FY29: 0 | GD29: 1 | GF29: -1131265837 | GG29: 2 | GH29: 1 | GI29: 2 | GJ29: 0 | GK29: 0 | GL29: =ROUND(IF(AND(BH29=3,BI29=3,FS29<>0),P29,0),2) -> 0 | GM29: =ROUND(O29+X29+Y29,2)+GX29 -> 0 | GN29: =IF(OR(BI29=0,BI29=1),GM29-GX29,0) -> 0 | GO29: =IF(BI29=2,GM29-GX29,0) -> 0 | GP29: =IF(BI29=4,GM29-GX29,0) -> 0 | GR29: 0 | GS29: 3 | GT29: 0 | GV29: =ROUND((GT29),6) -> 0 | GW29: 1 | GX29: =ROUND(HC29*I29,2) -> 0 | HA29: 0 | HB29: 0 | HC29: =GV29*GW29 -> 0 | HS29: 0 | IK29: 0
A30: 17 | B30: 1 | E30: 2 | F30: 1.7-11-60 | G30: Лом стальной, вид лома 5А, для расчета возвратных сумм | H30: т | I30: 13.742 | J30: 0 | K30: 13.742 | O30: =ROUND(CP30*I30,2) -> 0 | P30: =ROUND(CQ30*I30,2) -> 0 | Q30: =ROUND(CR30*I30,2) -> 0 | R30: =ROUND(CS30*I30,2) -> 0 | S30: =ROUND(CT30*I30,2) -> 0 | T30: =ROUND((ROUND((AC30*I30),2)*BC30),2) -> 29636.96 | U30: =CV30*I30 -> 0 | V30: =CW30*I30 -> 0 | W30: =ROUND(CX30*I30,2) -> 0 | X30: =ROUND(CY30,2) -> 0 | Y30: =ROUND(CZ30,2) -> 0 | AA30: 56526432 | AB30: =ROUND(0,6) -> 0 | AC30: =ROUND((ES30),6) -> 2156.67 | AD30: =ROUND(0,6) -> 0 | AE30: =ROUND(0,6) -> 0 | AF30: =ROUND(0,6) -> 0 | AG30: =ROUND((ES30),6) -> 2156.67 | AH30: =0 -> 0 | AI30: =0 -> 0 | AJ30: =0 -> 0 | AK30: 2156.67 | AL30: 2156.67 | AM30: 0 | AN30: 0 | AO30: 0 | AP30: 0 | AQ30: 0 | AR30: 0 | AS30: 0 | AT30: 0 | AU30: 0 | AV30: 1 | AW30: 1 | AZ30: 1 | BA30: 1 | BB30: 1 | BC30: 1 | BH30: 3 | BI30: 1 | BJ30: ТСН-2001.1 Доп. 67, Р. 7, о. 11, поз. 60 | BM30: 700000 | BN30: 0 | BP30: 0 | BQ30: 203 | BR30: 0 | BS30: 1 | BT30: 1 | BU30: 1 | BV30: 1 | BW30: 1 | BX30: 1 | BZ30: 0 | CA30: 0 | CE30: 32 | CF30: 0 | CG30: 0 | CM30: 0 | CO30: 0 | CP30: =0 -> 0 | CQ30: =0 -> 0 | CR30: =0 -> 0 | CS30: =0 -> 0 | CT30: =0 -> 0 | CU30: =ROUND((ROUND((AC30*1),2)*BC30),2) -> 2156.67 | CV30: =0 -> 0 | CW30: =0 -> 0 | CX30: =0 -> 0 | CY30: =0 -> 0 | CZ30: =0 -> 0 | DN30: 0 | DO30: 0 | DP30: 1 | DQ30: 1 | DU30: 1009 | DV30: т | DW30: т | DX30: 1000 | EE30: 55586417 | EF30: 203 | EG30: Возврат | EH30: 0 | EJ30: 1 | EK30: 700000 | EL30: ТСН-2001.1-7. 7-11-59...7-11-63 (Возврат) | EM30: ТСН-2001.1-3 | EQ30: 0 | ER30: 2156.67 | ES30: 2156.67 | ET30: 0 | EU30: 0 | EV30: 0 | EW30: 0 | EX30: 0 | EY30: 0 | FQ30: 0 | FR30: 0 | FS30: 0 | FX30: 0 | FY30: 0 | GD30: 1 | GF30: 1032763957 | GG30: 2 | GH30: 1 | GI30: -2 | GJ30: 0 | GK30: 0 | GL30: =ROUND(IF(AND(BH30=3,BI30=3,FS30<>0),P30,0),2) -> 0 | GM30: =ROUND(O30+X30+Y30,2)+GX30 -> 0 | GN30: =IF(OR(BI30=0,BI30=1),GM30-GX30,0) -> 0 | GO30: =IF(BI30=2,GM30-GX30,0) -> 0 | GP30: =IF(BI30=4,GM30-GX30,0) -> 0 | GR30: 0 | GS30: 3 | GT30: 0 | GV30: =ROUND((GT30),6) -> 0 | GW30: 1 | GX30: =ROUND(HC30*I30,2) -> 0 | HA30: 0 | HB30: 0 | HC30: =GV30*GW30 -> 0 | HS30: 0 | IK30: 0
A31: 17 | B31: 1 | E31: 2 | F31: 1.7-11-60 | G31: Лом стальной, вид лома 5А, для расчета возвратных сумм | H31: т | I31: 13.742 | J31: 0 | K31: 13.742 | O31: =ROUND(CP31*I31,2) -> 0 | P31: =ROUND(CQ31*I31,2) -> 0 | Q31: =ROUND(CR31*I31,2) -> 0 | R31: =ROUND(CS31*I31,2) -> 0 | S31: =ROUND(CT31*I31,2) -> 0 | T31: =ROUND((ROUND((AC31*I31),2)*BC31),2) -> 246283.14 | U31: =CV31*I31 -> 0 | V31: =CW31*I31 -> 0 | W31: =ROUND(CX31*I31,2) -> 0 | X31: =ROUND(CY31,2) -> 0 | Y31: =ROUND(CZ31,2) -> 0 | AA31: 56526434 | AB31: =ROUND(0,6) -> 0 | AC31: =ROUND((ES31),6) -> 2156.67 | AD31: =ROUND(0,6) -> 0 | AE31: =ROUND(0,6) -> 0 | AF31: =ROUND(0,6) -> 0 | AG31: =ROUND((ES31),6) -> 2156.67 | AH31: =0 -> 0 | AI31: =0 -> 0 | AJ31: =0 -> 0 | AK31: 2156.67 | AL31: 2156.67 | AM31: 0 | AN31: 0 | AO31: 0 | AP31: 0 | AQ31: 0 | AR31: 0 | AS31: 0 | AT31: 0 | AU31: 0 | AV31: 1 | AW31: 1 | AZ31: 1 | BA31: 1 | BB31: 1 | BC31: 8.31 | BH31: 3 | BI31: 1 | BJ31: ТСН-2001.1 Доп. 67, Р. 7, о. 11, поз. 60 | BM31: 700000 | BN31: 0 | BO31: 1.7-11-60 | BP31: 1 | BQ31: 203 | BR31: 0 | BS31: 1 | BT31: 1 | BU31: 1 | BV31: 1 | BW31: 1 | BX31: 1 | BZ31: 0 | CA31: 0 | CE31: 32 | CF31: 0 | CG31: 0 | CM31: 0 | CO31: 0 | CP31: =0 -> 0 | CQ31: =0 -> 0 | CR31: =0 -> 0 | CS31: =0 -> 0 | CT31: =0 -> 0 | CU31: =ROUND((ROUND((AC31*1),2)*BC31),2) -> 17921.93 | CV31: =0 -> 0 | CW31: =0 -> 0 | CX31: =0 -> 0 | CY31: =0 -> 0 | CZ31: =0 -> 0 | DN31: 0 | DO31: 0 | DP31: 1 | DQ31: 1 | DU31: 1009 | DV31: т | DW31: т | DX31: 1000 | EE31: 55586417 | EF31: 203 | EG31: Возврат | EH31: 0 | EJ31: 1 | EK31: 700000 | EL31: ТСН-2001.1-7. 7-11-59...7-11-63 (Возврат) | EM31: ТСН-2001.1-3 | EQ31: 0 | ER31: 2156.67 | ES31: 2156.67 | ET31: 0 | EU31: 0 | EV31: 0 | EW31: 0 | EX31: 0 | EY31: 0 | FQ31: 0 | FR31: 0 | FS31: 0 | FX31: 0 | FY31: 0 | GD31: 1 | GF31: 1032763957 | GG31: 2 | GH31: 1 | GI31: 2 | GJ31: 0 | GK31: 0 | GL31: =ROUND(IF(AND(BH31=3,BI31=3,FS31<>0),P31,0),2) -> 0 | GM31: =ROUND(O31+X31+Y31,2)+GX31 -> 0 | GN31: =IF(OR(BI31=0,BI31=1),GM31-GX31,0) -> 0 | GO31: =IF(BI31=2,GM31-GX31,0) -> 0 | GP31: =IF(BI31=4,GM31-GX31,0) -> 0 | GR31: 0 | GS31: 3 | GT31: 0 | GV31: =ROUND((GT31),6) -> 0 | GW31: 1 | GX31: =ROUND(HC31*I31,2) -> 0 | HA31: 0 | HB31: 0 | HC31: =GV31*GW31 -> 0 | HS31: 0 | IK31: 0
A32: 17 | B32: 1 | E32: 3 | F32: 1.7-11-61 | G32: Лом стальной, вид лома 12А, для расчета возвратных сумм (прим. алюминий) | H32: т | I32: 0.854 | J32: 0 | K32: 0.854 | O32: =ROUND(CP32*I32,2) -> 0 | P32: =ROUND(CQ32*I32,2) -> 0 | Q32: =ROUND(CR32*I32,2) -> 0 | R32: =ROUND(CS32*I32,2) -> 0 | S32: =ROUND(CT32*I32,2) -> 0 | T32: =ROUND((ROUND((AC32*I32),2)*BC32),2) -> 1583.01 | U32: =CV32*I32 -> 0 | V32: =CW32*I32 -> 0 | W32: =ROUND(CX32*I32,2) -> 0 | X32: =ROUND(CY32,2) -> 0 | Y32: =ROUND(CZ32,2) -> 0 | AA32: 56526432 | AB32: =ROUND(0,6) -> 0 | AC32: =ROUND((ES32),6) -> 1853.64 | AD32: =ROUND(0,6) -> 0 | AE32: =ROUND(0,6) -> 0 | AF32: =ROUND(0,6) -> 0 | AG32: =ROUND((ES32),6) -> 1853.64 | AH32: =0 -> 0 | AI32: =0 -> 0 | AJ32: =0 -> 0 | AK32: 1853.64 | AL32: 1853.64 | AM32: 0 | AN32: 0 | AO32: 0 | AP32: 0 | AQ32: 0 | AR32: 0 | AS32: 0 | AT32: 0 | AU32: 0 | AV32: 1 | AW32: 1 | AZ32: 1 | BA32: 1 | BB32: 1 | BC32: 1 | BH32: 3 | BI32: 1 | BJ32: ТСН-2001.1 Доп. 67, Р. 7, о. 11, поз. 61 | BM32: 700000 | BN32: 0 | BP32: 0 | BQ32: 203 | BR32: 0 | BS32: 1 | BT32: 1 | BU32: 1 | BV32: 1 | BW32: 1 | BX32: 1 | BZ32: 0 | CA32: 0 | CE32: 32 | CF32: 0 | CG32: 0 | CM32: 0 | CO32: 0 | CP32: =0 -> 0 | CQ32: =0 -> 0 | CR32: =0 -> 0 | CS32: =0 -> 0 | CT32: =0 -> 0 | CU32: =ROUND((ROUND((AC32*1),2)*BC32),2) -> 1853.64 | CV32: =0 -> 0 | CW32: =0 -> 0 | CX32: =0 -> 0 | CY32: =0 -> 0 | CZ32: =0 -> 0 | DN32: 0 | DO32: 0 | DP32: 1 | DQ32: 1 | DU32: 1009 | DV32: т | DW32: т | DX32: 1000 | EE32: 55586417 | EF32: 203 | EG32: Возврат | EH32: 0 | EJ32: 1 | EK32: 700000 | EL32: ТСН-2001.1-7. 7-11-59...7-11-63 (Возврат) | EM32: ТСН-2001.1-3 | EQ32: 0 | ER32: 1853.64 | ES32: 1853.64 | ET32: 0 | EU32: 0 | EV32: 0 | EW32: 0 | EX32: 0 | EY32: 0 | FQ32: 0 | FR32: 0 | FS32: 0 | FX32: 0 | FY32: 0 | GD32: 1 | GF32: 1961057982 | GG32: 2 | GH32: 1 | GI32: -2 | GJ32: 0 | GK32: 0 | GL32: =ROUND(IF(AND(BH32=3,BI32=3,FS32<>0),P32,0),2) -> 0 | GM32: =ROUND(O32+X32+Y32,2)+GX32 -> 0 | GN32: =IF(OR(BI32=0,BI32=1),GM32-GX32,0) -> 0 | GO32: =IF(BI32=2,GM32-GX32,0) -> 0 | GP32: =IF(BI32=4,GM32-GX32,0) -> 0 | GR32: 0 | GS32: 3 | GT32: 0 | GV32: =ROUND((GT32),6) -> 0 | GW32: 1 | GX32: =ROUND(HC32*I32,2) -> 0 | HA32: 0 | HB32: 0 | HC32: =GV32*GW32 -> 0 | HS32: 0 | IK32: 0
A33: 17 | B33: 1 | E33: 3 | F33: 1.7-11-61 | G33: Лом стальной, вид лома 12А, для расчета возвратных сумм (прим. алюминий) | H33: т | I33: 0.854 | J33: 0 | K33: 0.854 | O33: =ROUND(CP33*I33,2) -> 0 | P33: =ROUND(CQ33*I33,2) -> 0 | Q33: =ROUND(CR33*I33,2) -> 0 | R33: =ROUND(CS33*I33,2) -> 0 | S33: =ROUND(CT33*I33,2) -> 0 | T33: =ROUND((ROUND((AC33*I33),2)*BC33),2) -> 15228.56 | U33: =CV33*I33 -> 0 | V33: =CW33*I33 -> 0 | W33: =ROUND(CX33*I33,2) -> 0 | X33: =ROUND(CY33,2) -> 0 | Y33: =ROUND(CZ33,2) -> 0 | AA33: 56526434 | AB33: =ROUND(0,6) -> 0 | AC33: =ROUND((ES33),6) -> 1853.64 | AD33: =ROUND(0,6) -> 0 | AE33: =ROUND(0,6) -> 0 | AF33: =ROUND(0,6) -> 0 | AG33: =ROUND((ES33),6) -> 1853.64 | AH33: =0 -> 0 | AI33: =0 -> 0 | AJ33: =0 -> 0 | AK33: 1853.64 | AL33: 1853.64 | AM33: 0 | AN33: 0 | AO33: 0 | AP33: 0 | AQ33: 0 | AR33: 0 | AS33: 0 | AT33: 0 | AU33: 0 | AV33: 1 | AW33: 1 | AZ33: 1 | BA33: 1 | BB33: 1 | BC33: 9.62 | BH33: 3 | BI33: 1 | BJ33: ТСН-2001.1 Доп. 67, Р. 7, о. 11, поз. 61 | BM33: 700000 | BN33: 0 | BO33: 1.7-11-61 | BP33: 1 | BQ33: 203 | BR33: 0 | BS33: 1 | BT33: 1 | BU33: 1 | BV33: 1 | BW33: 1 | BX33: 1 | BZ33: 0 | CA33: 0 | CE33: 32 | CF33: 0 | CG33: 0 | CM33: 0 | CO33: 0 | CP33: =0 -> 0 | CQ33: =0 -> 0 | CR33: =0 -> 0 | CS33: =0 -> 0 | CT33: =0 -> 0 | CU33: =ROUND((ROUND((AC33*1),2)*BC33),2) -> 17832.02 | CV33: =0 -> 0 | CW33: =0 -> 0 | CX33: =0 -> 0 | CY33: =0 -> 0 | CZ33: =0 -> 0 | DN33: 0 | DO33: 0 | DP33: 1 | DQ33: 1 | DU33: 1009 | DV33: т | DW33: т | DX33: 1000 | EE33: 55586417 | EF33: 203 | EG33: Возврат | EH33: 0 | EJ33: 1 | EK33: 700000 | EL33: ТСН-2001.1-7. 7-11-59...7-11-63 (Возврат) | EM33: ТСН-2001.1-3 | EQ33: 0 | ER33: 1853.64 | ES33: 1853.64 | ET33: 0 | EU33: 0 | EV33: 0 | EW33: 0 | EX33: 0 | EY33: 0 | FQ33: 0 | FR33: 0 | FS33: 0 | FX33: 0 | FY33: 0 | GD33: 1 | GF33: 1961057982 | GG33: 2 | GH33: 1 | GI33: 2 | GJ33: 0 | GK33: 0 | GL33: =ROUND(IF(AND(BH33=3,BI33=3,FS33<>0),P33,0),2) -> 0 | GM33: =ROUND(O33+X33+Y33,2)+GX33 -> 0 | GN33: =IF(OR(BI33=0,BI33=1),GM33-GX33,0) -> 0 | GO33: =IF(BI33=2,GM33-GX33,0) -> 0 | GP33: =IF(BI33=4,GM33-GX33,0) -> 0 | GR33: 0 | GS33: 3 | GT33: 0 | GV33: =ROUND((GT33),6) -> 0 | GW33: 1 | GX33: =ROUND(HC33*I33,2) -> 0 | HA33: 0 | HB33: 0 | HC33: =GV33*GW33 -> 0 | HS33: 0 | IK33: 0
A34: 17 | B34: 1 | E34: 4 | F34: 1.7-11-63 | G34: Лом чугунный, вид лома 22А, для расчета возвратных сумм | H34: т | I34: 0.209 | J34: 0 | K34: 0.209 | O34: =ROUND(CP34*I34,2) -> 0 | P34: =ROUND(CQ34*I34,2) -> 0 | Q34: =ROUND(CR34*I34,2) -> 0 | R34: =ROUND(CS34*I34,2) -> 0 | S34: =ROUND(CT34*I34,2) -> 0 | T34: =ROUND((ROUND((AC34*I34),2)*BC34),2) -> 460.85 | U34: =CV34*I34 -> 0 | V34: =CW34*I34 -> 0 | W34: =ROUND(CX34*I34,2) -> 0 | X34: =ROUND(CY34,2) -> 0 | Y34: =ROUND(CZ34,2) -> 0 | AA34: 56526432 | AB34: =ROUND(0,6) -> 0 | AC34: =ROUND((ES34),6) -> 2205.03 | AD34: =ROUND(0,6) -> 0 | AE34: =ROUND(0,6) -> 0 | AF34: =ROUND(0,6) -> 0 | AG34: =ROUND((ES34),6) -> 2205.03 | AH34: =0 -> 0 | AI34: =0 -> 0 | AJ34: =0 -> 0 | AK34: 2205.03 | AL34: 2205.03 | AM34: 0 | AN34: 0 | AO34: 0 | AP34: 0 | AQ34: 0 | AR34: 0 | AS34: 0 | AT34: 0 | AU34: 0 | AV34: 1 | AW34: 1 | AZ34: 1 | BA34: 1 | BB34: 1 | BC34: 1 | BH34: 3 | BI34: 1 | BJ34: ТСН-2001.1 Доп. 67, Р. 7, о. 11, поз. 63 | BM34: 700000 | BN34: 0 | BP34: 0 | BQ34: 203 | BR34: 0 | BS34: 1 | BT34: 1 | BU34: 1 | BV34: 1 | BW34: 1 | BX34: 1 | BZ34: 0 | CA34: 0 | CE34: 32 | CF34: 0 | CG34: 0 | CM34: 0 | CO34: 0 | CP34: =0 -> 0 | CQ34: =0 -> 0 | CR34: =0 -> 0 | CS34: =0 -> 0 | CT34: =0 -> 0 | CU34: =ROUND((ROUND((AC34*1),2)*BC34),2) -> 2205.03 | CV34: =0 -> 0 | CW34: =0 -> 0 | CX34: =0 -> 0 | CY34: =0 -> 0 | CZ34: =0 -> 0 | DN34: 0 | DO34: 0 | DP34: 1 | DQ34: 1 | DU34: 1009 | DV34: т | DW34: т | DX34: 1000 | EE34: 55586417 | EF34: 203 | EG34: Возврат | EH34: 0 | EJ34: 1 | EK34: 700000 | EL34: ТСН-2001.1-7. 7-11-59...7-11-63 (Возврат) | EM34: ТСН-2001.1-3 | EQ34: 0 | ER34: 2205.03 | ES34: 2205.03 | ET34: 0 | EU34: 0 | EV34: 0 | EW34: 0 | EX34: 0 | EY34: 0 | FQ34: 0 | FR34: 0 | FS34: 0 | FX34: 0 | FY34: 0 | GD34: 1 | GF34: 487029402 | GG34: 2 | GH34: 1 | GI34: -2 | GJ34: 0 | GK34: 0 | GL34: =ROUND(IF(AND(BH34=3,BI34=3,FS34<>0),P34,0),2) -> 0 | GM34: =ROUND(O34+X34+Y34,2)+GX34 -> 0 | GN34: =IF(OR(BI34=0,BI34=1),GM34-GX34,0) -> 0 | GO34: =IF(BI34=2,GM34-GX34,0) -> 0 | GP34: =IF(BI34=4,GM34-GX34,0) -> 0 | GR34: 0 | GS34: 3 | GT34: 0 | GV34: =ROUND((GT34),6) -> 0 | GW34: 1 | GX34: =ROUND(HC34*I34,2) -> 0 | HA34: 0 | HB34: 0 | HC34: =GV34*GW34 -> 0 | HS34: 0 | IK34: 0
A35: 17 | B35: 1 | E35: 4 | F35: 1.7-11-63 | G35: Лом чугунный, вид лома 22А, для расчета возвратных сумм | H35: т | I35: 0.209 | J35: 0 | K35: 0.209 | O35: =ROUND(CP35*I35,2) -> 0 | P35: =ROUND(CQ35*I35,2) -> 0 | Q35: =ROUND(CR35*I35,2) -> 0 | R35: =ROUND(CS35*I35,2) -> 0 | S35: =ROUND(CT35*I35,2) -> 0 | T35: =ROUND((ROUND((AC35*I35),2)*BC35),2) -> 4179.91 | U35: =CV35*I35 -> 0 | V35: =CW35*I35 -> 0 | W35: =ROUND(CX35*I35,2) -> 0 | X35: =ROUND(CY35,2) -> 0 | Y35: =ROUND(CZ35,2) -> 0 | AA35: 56526434 | AB35: =ROUND(0,6) -> 0 | AC35: =ROUND((ES35),6) -> 2205.03 | AD35: =ROUND(0,6) -> 0 | AE35: =ROUND(0,6) -> 0 | AF35: =ROUND(0,6) -> 0 | AG35: =ROUND((ES35),6) -> 2205.03 | AH35: =0 -> 0 | AI35: =0 -> 0 | AJ35: =0 -> 0 | AK35: 2205.03 | AL35: 2205.03 | AM35: 0 | AN35: 0 | AO35: 0 | AP35: 0 | AQ35: 0 | AR35: 0 | AS35: 0 | AT35: 0 | AU35: 0 | AV35: 1 | AW35: 1 | AZ35: 1 | BA35: 1 | BB35: 1 | BC35: 9.07 | BH35: 3 | BI35: 1 | BJ35: ТСН-2001.1 Доп. 67, Р. 7, о. 11, поз. 63 | BM35: 700000 | BN35: 0 | BO35: 1.7-11-63 | BP35: 1 | BQ35: 203 | BR35: 0 | BS35: 1 | BT35: 1 | BU35: 1 | BV35: 1 | BW35: 1 | BX35: 1 | BZ35: 0 | CA35: 0 | CE35: 32 | CF35: 0 | CG35: 0 | CM35: 0 | CO35: 0 | CP35: =0 -> 0 | CQ35: =0 -> 0 | CR35: =0 -> 0 | CS35: =0 -> 0 | CT35: =0 -> 0 | CU35: =ROUND((ROUND((AC35*1),2)*BC35),2) -> 19999.62 | CV35: =0 -> 0 | CW35: =0 -> 0 | CX35: =0 -> 0 | CY35: =0 -> 0 | CZ35: =0 -> 0 | DN35: 0 | DO35: 0 | DP35: 1 | DQ35: 1 | DU35: 1009 | DV35: т | DW35: т | DX35: 1000 | EE35: 55586417 | EF35: 203 | EG35: Возврат | EH35: 0 | EJ35: 1 | EK35: 700000 | EL35: ТСН-2001.1-7. 7-11-59...7-11-63 (Возврат) | EM35: ТСН-2001.1-3 | EQ35: 0 | ER35: 2205.03 | ES35: 2205.03 | ET35: 0 | EU35: 0 | EV35: 0 | EW35: 0 | EX35: 0 | EY35: 0 | FQ35: 0 | FR35: 0 | FS35: 0 | FX35: 0 | FY35: 0 | GD35: 1 | GF35: 487029402 | GG35: 2 | GH35: 1 | GI35: 2 | GJ35: 0 | GK35: 0 | GL35: =ROUND(IF(AND(BH35=3,BI35=3,FS35<>0),P35,0),2) -> 0 | GM35: =ROUND(O35+X35+Y35,2)+GX35 -> 0 | GN35: =IF(OR(BI35=0,BI35=1),GM35-GX35,0) -> 0 | GO35: =IF(BI35=2,GM35-GX35,0) -> 0 | GP35: =IF(BI35=4,GM35-GX35,0) -> 0 | GR35: 0 | GS35: 3 | GT35: 0 | GV35: =ROUND((GT35),6) -> 0 | GW35: 1 | GX35: =ROUND(HC35*I35,2) -> 0 | HA35: 0 | HB35: 0 | HC35: =GV35*GW35 -> 0 | HS35: 0 | IK35: 0
A37: 51 | B37: =B24 -> 1 | C37: =A24 -> 4 | D37: =ROW(A24) -> 24 | F37: =IF(F24<>"",F24,"") | G37: =IF(G24<>"",G24,"") -> Возвратные средства | H37: 0 | O37: =ROUND(AB37,2) -> 0 | P37: =ROUND(AC37,2) -> 0 | Q37: =ROUND(AD37,2) -> 0 | R37: =ROUND(AE37,2) -> 0 | S37: =ROUND(AF37,2) -> 0 | T37: =ROUND(AG37,2) -> 86069.65 | U37: =AH37 -> 0 | V37: =AI37 -> 0 | W37: =ROUND(AJ37,2) -> 0 | X37: =ROUND(AK37,2) -> 0 | Y37: =ROUND(AL37,2) -> 0 | AB37: =ROUND(SUMIF(AA28:AA35,"=56526432",O28:O35),2) -> 0 | AC37: =ROUND(SUMIF(AA28:AA35,"=56526432",P28:P35),2) -> 0 | AD37: =ROUND(SUMIF(AA28:AA35,"=56526432",Q28:Q35),2) -> 0 | AE37: =ROUND(SUMIF(AA28:AA35,"=56526432",R28:R35),2) -> 0 | AF37: =ROUND(SUMIF(AA28:AA35,"=56526432",S28:S35),2) -> 0 | AG37: =ROUND(SUMIF(AA28:AA35,"=56526432",T28:T35),2) -> 86069.65 | AH37: =SUMIF(AA28:AA35,"=56526432",U28:U35) -> 0 | AI37: =SUMIF(AA28:AA35,"=56526432",V28:V35) -> 0 | AJ37: =ROUND(SUMIF(AA28:AA35,"=56526432",W28:W35),2) -> 0 | AK37: =ROUND(SUMIF(AA28:AA35,"=56526432",X28:X35),2) -> 0 | AL37: =ROUND(SUMIF(AA28:AA35,"=56526432",Y28:Y35),2) -> 0 | AO37: =ROUND(BX37,2) -> 0 | AP37: =ROUND(BY37,2) -> 0 | AQ37: =ROUND(BZ37,2) -> 0 | AR37: =ROUND(CA37,2) -> 0 | AS37: =ROUND(CB37,2) -> 0 | AT37: =ROUND(CC37,2) -> 0 | AU37: =ROUND(CD37,2) -> 0 | AV37: =ROUND(CE37,2) -> 0 | ... BD37: =ROUND(CM37,2) -> 0 | BX37: =ROUND(SUMIF(AA28:AA35,"=56526432",FQ28:FQ35),2) -> 0 | BY37: =ROUND(SUMIF(AA28:AA35,"=56526432",FR28:FR35),2) -> 0 | BZ37: =ROUND(SUMIF(AA28:AA35,"=56526432",GL28:GL35),2) -> 0 | CA37: =ROUND(SUMIF(AA28:AA35,"=56526432",GM28:GM35),2) -> 0 | CB37: =ROUND(SUMIF(AA28:AA35,"=56526432",GN28:GN35),2) -> 0 | CC37: =ROUND(SUMIF(AA28:AA35,"=56526432",GO28:GO35),2) -> 0 | CD37: =ROUND(SUMIF(AA28:AA35,"=56526432",GP28:GP35),2) -> 0 | CE37: =AC37-BX37 -> 0 | CF37: =AC37-BY37 -> 0 | CG37: =BX37-BZ37 -> 0 | CH37: =AC37-BX37-BY37+BZ37 -> 0 | CI37: =BY37-BZ37 -> 0 | CJ37: =ROUND(SUMIF(AA28:AA35,"=56526432",GX28:GX35),2) -> 0 | CK37: =ROUND(SUMIF(AA28:AA35,"=56526432",GY28:GY35),2) -> 0 | CL37: =ROUND(SUMIF(AA28:AA35,"=56526432",GZ28:GZ35),2) -> 0 | CM37: =ROUND(SUMIF(AA28:AA35,"=56526432",HD28:HD35),2) -> 0 | DG37: =ROUND(DT37,2) -> 0 | DH37: =ROUND(DU37,2) -> 0 | DI37: =ROUND(DV37,2) -> 0 | DJ37: =ROUND(DW37,2) -> 0 | DK37: =ROUND(DX37,2) -> 0 | DL37: =ROUND(DY37,2) -> 733435.55 | DM37: =DZ37 -> 0 | DN37: =EA37 -> 0 | DO37: =ROUND(EB37,2) -> 0 | DP37: =ROUND(EC37,2) -> 0 | DQ37: =ROUND(ED37,2) -> 0 | DT37: =ROUND(SUMIF(AA28:AA35,"=56526434",O28:O35),2) -> 0 | DU37: =ROUND(SUMIF(AA28:AA35,"=56526434",P28:P35),2) -> 0 | DV37: =ROUND(SUMIF(AA28:AA35,"=56526434",Q28:Q35),2) -> 0 | DW37: =ROUND(SUMIF(AA28:AA35,"=56526434",R28:R35),2) -> 0 | DX37: =ROUND(SUMIF(AA28:AA35,"=56526434",S28:S35),2) -> 0 | DY37: =ROUND(SUMIF(AA28:AA35,"=56526434",T28:T35),2) -> 733435.55 | DZ37: =SUMIF(AA28:AA35,"=56526434",U28:U35) -> 0 | EA37: =SUMIF(AA28:AA35,"=56526434",V28:V35) -> 0 | EB37: =ROUND(SUMIF(AA28:AA35,"=56526434",W28:W35),2) -> 0 | EC37: =ROUND(SUMIF(AA28:AA35,"=56526434",X28:X35),2) -> 0 | ED37: =ROUND(SUMIF(AA28:AA35,"=56526434",Y28:Y35),2) -> 0 | EG37: =ROUND(FP37,2) -> 0 | EH37: =ROUND(FQ37,2) -> 0 | EI37: =ROUND(FR37,2) -> 0 | EJ37: =ROUND(FS37,2) -> 0 | EK37: =ROUND(FT37,2) -> 0 | EL37: =ROUND(FU37,2) -> 0 | EM37: =ROUND(FV37,2) -> 0 | EN37: =ROUND(FW37,2) -> 0 | ... EV37: =ROUND(GE37,2) -> 0 | FP37: =ROUND(SUMIF(AA28:AA35,"=56526434",FQ28:FQ35),2) -> 0 | FQ37: =ROUND(SUMIF(AA28:AA35,"=56526434",FR28:FR35),2) -> 0 | FR37: =ROUND(SUMIF(AA28:AA35,"=56526434",GL28:GL35),2) -> 0 | FS37: =ROUND(SUMIF(AA28:AA35,"=56526434",GM28:GM35),2) -> 0 | FT37: =ROUND(SUMIF(AA28:AA35,"=56526434",GN28:GN35),2) -> 0 | FU37: =ROUND(SUMIF(AA28:AA35,"=56526434",GO28:GO35),2) -> 0 | FV37: =ROUND(SUMIF(AA28:AA35,"=56526434",GP28:GP35),2) -> 0 | FW37: =DU37-FP37 -> 0 | FX37: =DU37-FQ37 -> 0 | FY37: =FP37-FR37 -> 0 | FZ37: =DU37-FP37-FQ37+FR37 -> 0 | GA37: =FQ37-FR37 -> 0 | GB37: =ROUND(SUMIF(AA28:AA35,"=56526434",GX28:GX35),2) -> 0 | GC37: =ROUND(SUMIF(AA28:AA35,"=56526434",GY28:GY35),2) -> 0 | GD37: =ROUND(SUMIF(AA28:AA35,"=56526434",GZ28:GZ35),2) -> 0 | GE37: =ROUND(SUMIF(AA28:AA35,"=56526434",HD28:HD35),2) -> 0 | GX37: 0
A39: 50 | B39: 0 | C39: 0 | D39: 1 | E39: 201 | F39: =ROUND(Source!O37,O39) -> 0 | G39: ПЗ | H39: Прямые затраты | K39: 201 | L39: 1 | M39: 3 | O39: 2 | P39: =ROUND(Source!DG37,O39) -> 0 | W39: 0 | X39: 1 | Y39: 0 | Z39: 0 | AA39: 1 | AB39: 0
A40: 50 | B40: 0 | C40: 0 | D40: 1 | E40: 202 | F40: =ROUND(Source!P37,O40) -> 0 | G40: СтМатОб | H40: Стоимость материальных ресурсов (всего) | K40: 202 | L40: 2 | M40: 3 | O40: 2 | P40: =ROUND(Source!DH37,O40) -> 0 | W40: 0 | X40: 1 | Y40: 0 | Z40: 0 | AA40: 1 | AB40: 0
A41: 50 | B41: 0 | C41: 0 | D41: 1 | E41: 222 | F41: =ROUND(Source!AO37,O41) -> 0 | G41: СтМатОбЗак | H41: Стоимость материалов и оборудования заказчика | K41: 222 | L41: 3 | M41: 3 | O41: 2 | P41: =ROUND(Source!EG37,O41) -> 0 | W41: 0 | X41: 1 | Y41: 0 | Z41: 0 | AA41: 1 | AB41: 0
A42: 50 | B42: 0 | C42: 0 | D42: 1 | E42: 225 | F42: =ROUND(Source!AV37,O42) -> 0 | G42: СтМатОбПод | H42: Стоимость материалов и оборудования подрядчика | K42: 225 | L42: 4 | M42: 3 | O42: 2 | P42: =ROUND(Source!EN37,O42) -> 0 | W42: 0 | X42: 1 | Y42: 0 | Z42: 0 | AA42: 1 | AB42: 0
A43: 50 | B43: 0 | C43: 0 | D43: 1 | E43: 226 | F43: =ROUND(Source!AW37,O43) -> 0 | G43: СтМат | H43: Стоимость материалов (всего) | K43: 226 | L43: 5 | M43: 3 | O43: 2 | P43: =ROUND(Source!EO37,O43) -> 0 | W43: 0 | X43: 1 | Y43: 0 | Z43: 0 | AA43: 1 | AB43: 0
A44: 50 | B44: 0 | C44: 0 | D44: 1 | E44: 227 | F44: =ROUND(Source!AX37,O44) -> 0 | G44: СтМатЗак | H44: Стоимость материалов заказчика | K44: 227 | L44: 6 | M44: 3 | O44: 2 | P44: =ROUND(Source!EP37,O44) -> 0 | W44: 0 | X44: 1 | Y44: 0 | Z44: 0 | AA44: 1 | AB44: 0
A45: 50 | B45: 0 | C45: 0 | D45: 1 | E45: 228 | F45: =ROUND(Source!AY37,O45) -> 0 | G45: СтМатПод | H45: Стоимость материалов подрядчика | K45: 228 | L45: 7 | M45: 3 | O45: 2 | P45: =ROUND(Source!EQ37,O45) -> 0 | W45: 0 | X45: 1 | Y45: 0 | Z45: 0 | AA45: 1 | AB45: 0
A46: 50 | B46: 0 | C46: 0 | D46: 1 | E46: 216 | F46: =ROUND(Source!AP37,O46) -> 0 | G46: Оборуд | H46: Стоимость оборудования (всего) | K46: 216 | L46: 8 | M46: 3 | O46: 2 | P46: =ROUND(Source!EH37,O46) -> 0 | W46: 0 | X46: 1 | Y46: 0 | Z46: 0 | AA46: 1 | AB46: 0
A47: 50 | B47: 0 | C47: 0 | D47: 1 | E47: 223 | F47: =ROUND(Source!AQ37,O47) -> 0 | G47: ОборудЗак | H47: Стоимость оборудования заказчика | K47: 223 | L47: 9 | M47: 3 | O47: 2 | P47: =ROUND(Source!EI37,O47) -> 0 | W47: 0 | X47: 1 | Y47: 0 | Z47: 0 | AA47: 1 | AB47: 0
A48: 50 | B48: 0 | C48: 0 | D48: 1 | E48: 229 | F48: =ROUND(Source!AZ37,O48) -> 0 | G48: ОборудПод | H48: Стоимость оборудования подрядчика | K48: 229 | L48: 10 | M48: 3 | O48: 2 | P48: =ROUND(Source!ER37,O48) -> 0 | W48: 0 | X48: 1 | Y48: 0 | Z48: 0 | AA48: 1 | AB48: 0
A49: 50 | B49: 0 | C49: 0 | D49: 1 | E49: 203 | F49: =ROUND(Source!Q37,O49) -> 0 | G49: ЭММ | H49: Эксплуатация машин | K49: 203 | L49: 11 | M49: 3 | O49: 2 | P49: =ROUND(Source!DI37,O49) -> 0 | W49: 0 | X49: 1 | Y49: 0 | Z49: 0 | AA49: 1 | AB49: 0
A50: 50 | B50: 0 | C50: 0 | D50: 1 | E50: 231 | F50: =ROUND(Source!BB37,O50) -> 0 | G50: ЭММсНРиСП | H50: Эксплуатация машин по ТСН-2001.16 | K50: 231 | L50: 12 | M50: 3 | O50: 2 | P50: =ROUND(Source!ET37,O50) -> 0 | W50: 0 | X50: 1 | Y50: 0 | Z50: 0 | AA50: 1 | AB50: 0
A51: 50 | B51: 0 | C51: 0 | D51: 1 | E51: 204 | F51: =ROUND(Source!R37,O51) -> 0 | G51: ЗПМ | H51: ЗП машинистов | K51: 204 | L51: 13 | M51: 3 | O51: 2 | P51: =ROUND(Source!DJ37,O51) -> 0 | W51: 0 | X51: 1 | Y51: 0 | Z51: 0 | AA51: 1 | AB51: 0
A52: 50 | B52: 0 | C52: 0 | D52: 1 | E52: 205 | F52: =ROUND(Source!S37,O52) -> 0 | G52: ОЗП | H52: Основная ЗП рабочих | K52: 205 | L52: 14 | M52: 3 | O52: 2 | P52: =ROUND(Source!DK37,O52) -> 0 | W52: 0 | X52: 1 | Y52: 0 | Z52: 0 | AA52: 1 | AB52: 0
A53: 50 | B53: 0 | C53: 0 | D53: 1 | E53: 232 | F53: =ROUND(Source!BC37,O53) -> 0 | G53: ОЗПсНРиСП | H53: Основная ЗП рабочих по ТСН-2001.16 | K53: 232 | L53: 15 | M53: 3 | O53: 2 | P53: =ROUND(Source!EU37,O53) -> 0 | W53: 0 | X53: 1 | Y53: 0 | Z53: 0 | AA53: 1 | AB53: 0
A54: 50 | B54: 0 | C54: 0 | D54: 1 | E54: 214 | F54: =ROUND(Source!AS37,O54) -> 0 | G54: Строит | H54: Строительные работы с НР и СП | K54: 214 | L54: 16 | M54: 3 | O54: 2 | P54: =ROUND(Source!EK37,O54) -> 0 | W54: 0 | X54: 1 | Y54: 0 | Z54: 0 | AA54: 1 | AB54: 0
A55: 50 | B55: 0 | C55: 0 | D55: 1 | E55: 215 | F55: =ROUND(Source!AT37,O55) -> 0 | G55: Монтаж | H55: Монтажные работы с НР и СП | K55: 215 | L55: 17 | M55: 3 | O55: 2 | P55: =ROUND(Source!EL37,O55) -> 0 | W55: 0 | X55: 1 | Y55: 0 | Z55: 0 | AA55: 1 | AB55: 0
A56: 50 | B56: 0 | C56: 0 | D56: 1 | E56: 217 | F56: =ROUND(Source!AU37,O56) -> 0 | G56: Прочие | H56: Прочие работы с НР и СП | K56: 217 | L56: 18 | M56: 3 | O56: 2 | P56: =ROUND(Source!EM37,O56) -> 0 | W56: 0 | X56: 1 | Y56: 0 | Z56: 0 | AA56: 1 | AB56: 0
A57: 50 | B57: 0 | C57: 0 | D57: 1 | E57: 230 | F57: =ROUND(Source!BA37,O57) -> 0 | G57: ПрочиеЗатр | H57: Прочие затраты по ТСН-2001.16 | K57: 230 | L57: 19 | M57: 3 | O57: 2 | P57: =ROUND(Source!ES37,O57) -> 0 | W57: 0 | X57: 1 | Y57: 0 | Z57: 0 | AA57: 1 | AB57: 0
A58: 50 | B58: 0 | C58: 0 | D58: 1 | E58: 206 | F58: =ROUND(Source!T37,O58) -> 86069.65 | G58: ВозврМат | H58: Возврат материалов | K58: 206 | L58: 20 | M58: 3 | O58: 2 | P58: =ROUND(Source!DL37,O58) -> 733435.55 | W58: 86069.65 | X58: 1 | Y58: 86069.65 | Z58: 733435.55 | AA58: 1 | AB58: 733435.55
A59: 50 | B59: 0 | C59: 0 | D59: 1 | E59: 207 | F59: =Source!U37 -> 0 | G59: ТрудСтр | H59: Трудозатраты строителей | K59: 207 | L59: 21 | M59: 3 | O59: -1 | P59: =Source!DM37 -> 0 | W59: 0 | X59: 1 | Y59: 0 | Z59: 0 | AA59: 1 | AB59: 0
A60: 50 | B60: 0 | C60: 0 | D60: 1 | E60: 208 | F60: =Source!V37 -> 0 | G60: ТрудМаш | H60: Трудозатраты машинистов | K60: 208 | L60: 22 | M60: 3 | O60: -1 | P60: =Source!DN37 -> 0 | W60: 0 | X60: 1 | Y60: 0 | Z60: 0 | AA60: 1 | AB60: 0
A61: 50 | B61: 0 | C61: 0 | D61: 1 | E61: 209 | F61: =ROUND(Source!W37,O61) -> 0 | G61: ТранспМат | H61: Транспорт материалов | K61: 209 | L61: 23 | M61: 3 | O61: 2 | P61: =ROUND(Source!DO37,O61) -> 0 | W61: 0 | X61: 1 | Y61: 0 | Z61: 0 | AA61: 1 | AB61: 0
A62: 50 | B62: 0 | C62: 0 | D62: 1 | E62: 233 | F62: =ROUND(Source!BD37,O62) -> 0 | G62: Перевозка | H62: Перевозка грузов | K62: 233 | L62: 24 | M62: 3 | O62: 2 | P62: =ROUND(Source!EV37,O62) -> 0 | W62: 0 | X62: 1 | Y62: 0 | Z62: 0 | AA62: 1 | AB62: 0
A63: 50 | B63: 0 | C63: 0 | D63: 1 | E63: 210 | F63: =ROUND(Source!X37,O63) -> 0 | G63: НР | H63: Накладные расходы | K63: 210 | L63: 25 | M63: 3 | O63: 2 | P63: =ROUND(Source!DP37,O63) -> 0 | W63: 0 | X63: 1 | Y63: 0 | Z63: 0 | AA63: 1 | AB63: 0
A64: 50 | B64: 0 | C64: 0 | D64: 1 | E64: 211 | F64: =ROUND(Source!Y37,O64) -> 0 | G64: СмПриб | H64: Сметная прибыль | K64: 211 | L64: 26 | M64: 3 | O64: 2 | P64: =ROUND(Source!DQ37,O64) -> 0 | W64: 0 | X64: 1 | Y64: 0 | Z64: 0 | AA64: 1 | AB64: 0
A65: 50 | B65: 0 | C65: 0 | D65: 1 | E65: 224 | F65: =ROUND(Source!AR37,O65) -> 0 | G65: Всего | H65: Всего с НР и СП | K65: 224 | L65: 27 | M65: 3 | O65: 2 | P65: =ROUND(Source!EJ37,O65) -> 0 | W65: 0 | X65: 1 | Y65: 0 | Z65: 0 | AA65: 1 | AB65: 0
A67: 51 | B67: =B20 -> 1 | C67: =A20 -> 3 | D67: =ROW(A20) -> 20 | F67: =IF(F20<>"",F20,"") -> б/н | G67: =IF(G20<>"",G20,"") -> Возвратные средства | H67: 0 | O67: =ROUND(O37+AB67,2) -> 0 | P67: =ROUND(P37+AC67,2) -> 0 | Q67: =ROUND(Q37+AD67,2) -> 0 | R67: =ROUND(R37+AE67,2) -> 0 | S67: =ROUND(S37+AF67,2) -> 0 | T67: =ROUND(T37+AG67,2) -> 86069.65 | U67: =U37+AH67 -> 0 | V67: =V37+AI67 -> 0 | W67: =ROUND(W37+AJ67,2) -> 0 | X67: =ROUND(X37+AK67,2) -> 0 | Y67: =ROUND(Y37+AL67,2) -> 0 | AO67: =ROUND(AO37+BX67,2) -> 0 | AP67: =ROUND(AP37+BY67,2) -> 0 | AQ67: =ROUND(AQ37+BZ67,2) -> 0 | AR67: =ROUND(AR37+CA67,2) -> 0 | AS67: =ROUND(AS37+CB67,2) -> 0 | AT67: =ROUND(AT37+CC67,2) -> 0 | AU67: =ROUND(AU37+CD67,2) -> 0 | AV67: =ROUND(AV37+CE67,2) -> 0 | ... BD67: =ROUND(BD37+CM67,2) -> 0 | DG67: =ROUND(DG37+DT67,2) -> 0 | DH67: =ROUND(DH37+DU67,2) -> 0 | DI67: =ROUND(DI37+DV67,2) -> 0 | DJ67: =ROUND(DJ37+DW67,2) -> 0 | DK67: =ROUND(DK37+DX67,2) -> 0 | DL67: =ROUND(DL37+DY67,2) -> 733435.55 | DM67: =DM37+DZ67 -> 0 | DN67: =DN37+EA67 -> 0 | DO67: =ROUND(DO37+EB67,2) -> 0 | DP67: =ROUND(DP37+EC67,2) -> 0 | DQ67: =ROUND(DQ37+ED67,2) -> 0 | EG67: =ROUND(EG37+FP67,2) -> 0 | EH67: =ROUND(EH37+FQ67,2) -> 0 | EI67: =ROUND(EI37+FR67,2) -> 0 | EJ67: =ROUND(EJ37+FS67,2) -> 0 | EK67: =ROUND(EK37+FT67,2) -> 0 | EL67: =ROUND(EL37+FU67,2) -> 0 | EM67: =ROUND(EM37+FV67,2) -> 0 | EN67: =ROUND(EN37+FW67,2) -> 0 | ... EV67: =ROUND(EV37+GE67,2) -> 0 | GX67: 0
A69: 50 | B69: 0 | C69: 0 | D69: 1 | E69: 201 | F69: =ROUND(Source!O67,O69) -> 0 | G69: ПЗ | H69: Прямые затраты | K69: 201 | L69: 1 | M69: 3 | O69: 2 | P69: =ROUND(Source!DG67,O69) -> 0 | W69: 0 | X69: 1 | Y69: 0 | Z69: 0 | AA69: 1 | AB69: 0
A70: 50 | B70: 0 | C70: 0 | D70: 1 | E70: 202 | F70: =ROUND(Source!P67,O70) -> 0 | G70: СтМатОб | H70: Стоимость материальных ресурсов (всего) | K70: 202 | L70: 2 | M70: 3 | O70: 2 | P70: =ROUND(Source!DH67,O70) -> 0 | W70: 0 | X70: 1 | Y70: 0 | Z70: 0 | AA70: 1 | AB70: 0
A71: 50 | B71: 0 | C71: 0 | D71: 1 | E71: 222 | F71: =ROUND(Source!AO67,O71) -> 0 | G71: СтМатОбЗак | H71: Стоимость материалов и оборудования заказчика | K71: 222 | L71: 3 | M71: 3 | O71: 2 | P71: =ROUND(Source!EG67,O71) -> 0 | W71: 0 | X71: 1 | Y71: 0 | Z71: 0 | AA71: 1 | AB71: 0
A72: 50 | B72: 0 | C72: 0 | D72: 1 | E72: 225 | F72: =ROUND(Source!AV67,O72) -> 0 | G72: СтМатОбПод | H72: Стоимость материалов и оборудования подрядчика | K72: 225 | L72: 4 | M72: 3 | O72: 2 | P72: =ROUND(Source!EN67,O72) -> 0 | W72: 0 | X72: 1 | Y72: 0 | Z72: 0 | AA72: 1 | AB72: 0
A73: 50 | B73: 0 | C73: 0 | D73: 1 | E73: 226 | F73: =ROUND(Source!AW67,O73) -> 0 | G73: СтМат | H73: Стоимость материалов (всего) | K73: 226 | L73: 5 | M73: 3 | O73: 2 | P73: =ROUND(Source!EO67,O73) -> 0 | W73: 0 | X73: 1 | Y73: 0 | Z73: 0 | AA73: 1 | AB73: 0
A74: 50 | B74: 0 | C74: 0 | D74: 1 | E74: 227 | F74: =ROUND(Source!AX67,O74) -> 0 | G74: СтМатЗак | H74: Стоимость материалов заказчика | K74: 227 | L74: 6 | M74: 3 | O74: 2 | P74: =ROUND(Source!EP67,O74) -> 0 | W74: 0 | X74: 1 | Y74: 0 | Z74: 0 | AA74: 1 | AB74: 0
A75: 50 | B75: 0 | C75: 0 | D75: 1 | E75: 228 | F75: =ROUND(Source!AY67,O75) -> 0 | G75: СтМатПод | H75: Стоимость материалов подрядчика | K75: 228 | L75: 7 | M75: 3 | O75: 2 | P75: =ROUND(Source!EQ67,O75) -> 0 | W75: 0 | X75: 1 | Y75: 0 | Z75: 0 | AA75: 1 | AB75: 0
A76: 50 | B76: 0 | C76: 0 | D76: 1 | E76: 216 | F76: =ROUND(Source!AP67,O76) -> 0 | G76: Оборуд | H76: Стоимость оборудования (всего) | K76: 216 | L76: 8 | M76: 3 | O76: 2 | P76: =ROUND(Source!EH67,O76) -> 0 | W76: 0 | X76: 1 | Y76: 0 | Z76: 0 | AA76: 1 | AB76: 0
A77: 50 | B77: 0 | C77: 0 | D77: 1 | E77: 223 | F77: =ROUND(Source!AQ67,O77) -> 0 | G77: ОборудЗак | H77: Стоимость оборудования заказчика | K77: 223 | L77: 9 | M77: 3 | O77: 2 | P77: =ROUND(Source!EI67,O77) -> 0 | W77: 0 | X77: 1 | Y77: 0 | Z77: 0 | AA77: 1 | AB77: 0
A78: 50 | B78: 0 | C78: 0 | D78: 1 | E78: 229 | F78: =ROUND(Source!AZ67,O78) -> 0 | G78: ОборудПод | H78: Стоимость оборудования подрядчика | K78: 229 | L78: 10 | M78: 3 | O78: 2 | P78: =ROUND(Source!ER67,O78) -> 0 | W78: 0 | X78: 1 | Y78: 0 | Z78: 0 | AA78: 1 | AB78: 0
A79: 50 | B79: 0 | C79: 0 | D79: 1 | E79: 203 | F79: =ROUND(Source!Q67,O79) -> 0 | G79: ЭММ | H79: Эксплуатация машин | K79: 203 | L79: 11 | M79: 3 | O79: 2 | P79: =ROUND(Source!DI67,O79) -> 0 | W79: 0 | X79: 1 | Y79: 0 | Z79: 0 | AA79: 1 | AB79: 0
A80: 50 | B80: 0 | C80: 0 | D80: 1 | E80: 231 | F80: =ROUND(Source!BB67,O80) -> 0 | G80: ЭММсНРиСП | H80: Эксплуатация машин по ТСН-2001.16 | K80: 231 | L80: 12 | M80: 3 | O80: 2 | P80: =ROUND(Source!ET67,O80) -> 0 | W80: 0 | X80: 1 | Y80: 0 | Z80: 0 | AA80: 1 | AB80: 0
A81: 50 | B81: 0 | C81: 0 | D81: 1 | E81: 204 | F81: =ROUND(Source!R67,O81) -> 0 | G81: ЗПМ | H81: ЗП машинистов | K81: 204 | L81: 13 | M81: 3 | O81: 2 | P81: =ROUND(Source!DJ67,O81) -> 0 | W81: 0 | X81: 1 | Y81: 0 | Z81: 0 | AA81: 1 | AB81: 0
A82: 50 | B82: 0 | C82: 0 | D82: 1 | E82: 205 | F82: =ROUND(Source!S67,O82) -> 0 | G82: ОЗП | H82: Основная ЗП рабочих | K82: 205 | L82: 14 | M82: 3 | O82: 2 | P82: =ROUND(Source!DK67,O82) -> 0 | W82: 0 | X82: 1 | Y82: 0 | Z82: 0 | AA82: 1 | AB82: 0
A83: 50 | B83: 0 | C83: 0 | D83: 1 | E83: 232 | F83: =ROUND(Source!BC67,O83) -> 0 | G83: ОЗПсНРиСП | H83: Основная ЗП рабочих по ТСН-2001.16 | K83: 232 | L83: 15 | M83: 3 | O83: 2 | P83: =ROUND(Source!EU67,O83) -> 0 | W83: 0 | X83: 1 | Y83: 0 | Z83: 0 | AA83: 1 | AB83: 0
A84: 50 | B84: 0 | C84: 0 | D84: 1 | E84: 214 | F84: =ROUND(Source!AS67,O84) -> 0 | G84: Строит | H84: Строительные работы с НР и СП | K84: 214 | L84: 16 | M84: 3 | O84: 2 | P84: =ROUND(Source!EK67,O84) -> 0 | W84: 0 | X84: 1 | Y84: 0 | Z84: 0 | AA84: 1 | AB84: 0
A85: 50 | B85: 0 | C85: 0 | D85: 1 | E85: 215 | F85: =ROUND(Source!AT67,O85) -> 0 | G85: Монтаж | H85: Монтажные работы с НР и СП | K85: 215 | L85: 17 | M85: 3 | O85: 2 | P85: =ROUND(Source!EL67,O85) -> 0 | W85: 0 | X85: 1 | Y85: 0 | Z85: 0 | AA85: 1 | AB85: 0
A86: 50 | B86: 0 | C86: 0 | D86: 1 | E86: 217 | F86: =ROUND(Source!AU67,O86) -> 0 | G86: Прочие | H86: Прочие работы с НР и СП | K86: 217 | L86: 18 | M86: 3 | O86: 2 | P86: =ROUND(Source!EM67,O86) -> 0 | W86: 0 | X86: 1 | Y86: 0 | Z86: 0 | AA86: 1 | AB86: 0
A87: 50 | B87: 0 | C87: 0 | D87: 1 | E87: 230 | F87: =ROUND(Source!BA67,O87) -> 0 | G87: ПрочиеЗатр | H87: Прочие затраты по ТСН-2001.16 | K87: 230 | L87: 19 | M87: 3 | O87: 2 | P87: =ROUND(Source!ES67,O87) -> 0 | W87: 0 | X87: 1 | Y87: 0 | Z87: 0 | AA87: 1 | AB87: 0
A88: 50 | B88: 0 | C88: 0 | D88: 1 | E88: 206 | F88: =ROUND(Source!T67,O88) -> 86069.65 | G88: ВозврМат | H88: Возврат материалов | K88: 206 | L88: 20 | M88: 3 | O88: 2 | P88: =ROUND(Source!DL67,O88) -> 733435.55 | W88: 86069.65 | X88: 1 | Y88: 86069.65 | Z88: 733435.55 | AA88: 1 | AB88: 733435.55
A89: 50 | B89: 0 | C89: 0 | D89: 1 | E89: 207 | F89: =Source!U67 -> 0 | G89: ТрудСтр | H89: Трудозатраты строителей | K89: 207 | L89: 21 | M89: 3 | O89: -1 | P89: =Source!DM67 -> 0 | W89: 0 | X89: 1 | Y89: 0 | Z89: 0 | AA89: 1 | AB89: 0
A90: 50 | B90: 0 | C90: 0 | D90: 1 | E90: 208 | F90: =Source!V67 -> 0 | G90: ТрудМаш | H90: Трудозатраты машинистов | K90: 208 | L90: 22 | M90: 3 | O90: -1 | P90: =Source!DN67 -> 0 | W90: 0 | X90: 1 | Y90: 0 | Z90: 0 | AA90: 1 | AB90: 0
A91: 50 | B91: 0 | C91: 0 | D91: 1 | E91: 209 | F91: =ROUND(Source!W67,O91) -> 0 | G91: ТранспМат | H91: Транспорт материалов | K91: 209 | L91: 23 | M91: 3 | O91: 2 | P91: =ROUND(Source!DO67,O91) -> 0 | W91: 0 | X91: 1 | Y91: 0 | Z91: 0 | AA91: 1 | AB91: 0
A92: 50 | B92: 0 | C92: 0 | D92: 1 | E92: 233 | F92: =ROUND(Source!BD67,O92) -> 0 | G92: Перевозка | H92: Перевозка грузов | K92: 233 | L92: 24 | M92: 3 | O92: 2 | P92: =ROUND(Source!EV67,O92) -> 0 | W92: 0 | X92: 1 | Y92: 0 | Z92: 0 | AA92: 1 | AB92: 0
A93: 50 | B93: 0 | C93: 0 | D93: 1 | E93: 210 | F93: =ROUND(Source!X67,O93) -> 0 | G93: НР | H93: Накладные расходы | K93: 210 | L93: 25 | M93: 3 | O93: 2 | P93: =ROUND(Source!DP67,O93) -> 0 | W93: 0 | X93: 1 | Y93: 0 | Z93: 0 | AA93: 1 | AB93: 0
A94: 50 | B94: 0 | C94: 0 | D94: 1 | E94: 211 | F94: =ROUND(Source!Y67,O94) -> 0 | G94: СмПриб | H94: Сметная прибыль | K94: 211 | L94: 26 | M94: 3 | O94: 2 | P94: =ROUND(Source!DQ67,O94) -> 0 | W94: 0 | X94: 1 | Y94: 0 | Z94: 0 | AA94: 1 | AB94: 0
A95: 50 | B95: 0 | C95: 0 | D95: 1 | E95: 224 | F95: =ROUND(Source!AR67,O95) -> 0 | G95: Всего | H95: Всего с НР и СП | K95: 224 | L95: 27 | M95: 3 | O95: 2 | P95: =ROUND(Source!EJ67,O95) -> 0 | W95: 0 | X95: 1 | Y95: 0 | Z95: 0 | AA95: 1 | AB95: 0
A97: 51 | B97: =B12 -> 137 | C97: =A12 -> 1 | D97: =ROW(A12) -> 12 | F97: =IF(F12<>"",F12,"") -> б/н | G97: =IF(G12<>"",G12,"") -> б/н Возвратные средства | H97: 0 | O97: =ROUND(O67,2) -> 0 | P97: =ROUND(P67,2) -> 0 | Q97: =ROUND(Q67,2) -> 0 | R97: =ROUND(R67,2) -> 0 | S97: =ROUND(S67,2) -> 0 | T97: =ROUND(T67,2) -> 86069.65 | U97: =U67 -> 0 | V97: =V67 -> 0 | W97: =ROUND(W67,2) -> 0 | X97: =ROUND(X67,2) -> 0 | Y97: =ROUND(Y67,2) -> 0 | AO97: =ROUND(AO67,2) -> 0 | AP97: =ROUND(AP67,2) -> 0 | AQ97: =ROUND(AQ67,2) -> 0 | AR97: =ROUND(AR67,2) -> 0 | AS97: =ROUND(AS67,2) -> 0 | AT97: =ROUND(AT67,2) -> 0 | AU97: =ROUND(AU67,2) -> 0 | AV97: =ROUND(AV67,2) -> 0 | ... BD97: =ROUND(BD67,2) -> 0 | DG97: =ROUND(DG67,2) -> 0 | DH97: =ROUND(DH67,2) -> 0 | DI97: =ROUND(DI67,2) -> 0 | DJ97: =ROUND(DJ67,2) -> 0 | DK97: =ROUND(DK67,2) -> 0 | DL97: =ROUND(DL67,2) -> 733435.55 | DM97: =DM67 -> 0 | DN97: =DN67 -> 0 | DO97: =ROUND(DO67,2) -> 0 | DP97: =ROUND(DP67,2) -> 0 | DQ97: =ROUND(DQ67,2) -> 0 | EG97: =ROUND(EG67,2) -> 0 | EH97: =ROUND(EH67,2) -> 0 | EI97: =ROUND(EI67,2) -> 0 | EJ97: =ROUND(EJ67,2) -> 0 | EK97: =ROUND(EK67,2) -> 0 | EL97: =ROUND(EL67,2) -> 0 | EM97: =ROUND(EM67,2) -> 0 | EN97: =ROUND(EN67,2) -> 0 | ... EV97: =ROUND(EV67,2) -> 0 | GX97: 0
A99: 50 | B99: 0 | C99: 0 | D99: 1 | E99: 201 | F99: =ROUND(Source!O97,O99) -> 0 | G99: ПЗ | H99: Прямые затраты | K99: 201 | L99: 1 | M99: 3 | O99: 2 | P99: =ROUND(Source!DG97,O99) -> 0 | W99: 0 | X99: 1 | Y99: 0 | Z99: 0 | AA99: 1 | AB99: 0
A100: 50 | B100: 0 | C100: 0 | D100: 1 | E100: 202 | F100: =ROUND(Source!P97,O100) -> 0 | G100: СтМатОб | H100: Стоимость материальных ресурсов (всего) | K100: 202 | L100: 2 | M100: 3 | O100: 2 | P100: =ROUND(Source!DH97,O100) -> 0 | W100: 0 | X100: 1 | Y100: 0 | Z100: 0 | AA100: 1 | AB100: 0
A101: 50 | B101: 0 | C101: 0 | D101: 1 | E101: 222 | F101: =ROUND(Source!AO97,O101) -> 0 | G101: СтМатОбЗак | H101: Стоимость материалов и оборудования заказчика | K101: 222 | L101: 3 | M101: 3 | O101: 2 | P101: =ROUND(Source!EG97,O101) -> 0 | W101: 0 | X101: 1 | Y101: 0 | Z101: 0 | AA101: 1 | AB101: 0
A102: 50 | B102: 0 | C102: 0 | D102: 1 | E102: 225 | F102: =ROUND(Source!AV97,O102) -> 0 | G102: СтМатОбПод | H102: Стоимость материалов и оборудования подрядчика | K102: 225 | L102: 4 | M102: 3 | O102: 2 | P102: =ROUND(Source!EN97,O102) -> 0 | W102: 0 | X102: 1 | Y102: 0 | Z102: 0 | AA102: 1 | AB102: 0
A103: 50 | B103: 0 | C103: 0 | D103: 1 | E103: 226 | F103: =ROUND(Source!AW97,O103) -> 0 | G103: СтМат | H103: Стоимость материалов (всего) | K103: 226 | L103: 5 | M103: 3 | O103: 2 | P103: =ROUND(Source!EO97,O103) -> 0 | W103: 0 | X103: 1 | Y103: 0 | Z103: 0 | AA103: 1 | AB103: 0
A104: 50 | B104: 0 | C104: 0 | D104: 1 | E104: 227 | F104: =ROUND(Source!AX97,O104) -> 0 | G104: СтМатЗак | H104: Стоимость материалов заказчика | K104: 227 | L104: 6 | M104: 3 | O104: 2 | P104: =ROUND(Source!EP97,O104) -> 0 | W104: 0 | X104: 1 | Y104: 0 | Z104: 0 | AA104: 1 | AB104: 0
A105: 50 | B105: 0 | C105: 0 | D105: 1 | E105: 228 | F105: =ROUND(Source!AY97,O105) -> 0 | G105: СтМатПод | H105: Стоимость материалов подрядчика | K105: 228 | L105: 7 | M105: 3 | O105: 2 | P105: =ROUND(Source!EQ97,O105) -> 0 | W105: 0 | X105: 1 | Y105: 0 | Z105: 0 | AA105: 1 | AB105: 0
A106: 50 | B106: 0 | C106: 0 | D106: 1 | E106: 216 | F106: =ROUND(Source!AP97,O106) -> 0 | G106: Оборуд | H106: Стоимость оборудования (всего) | K106: 216 | L106: 8 | M106: 3 | O106: 2 | P106: =ROUND(Source!EH97,O106) -> 0 | W106: 0 | X106: 1 | Y106: 0 | Z106: 0 | AA106: 1 | AB106: 0
A107: 50 | B107: 0 | C107: 0 | D107: 1 | E107: 223 | F107: =ROUND(Source!AQ97,O107) -> 0 | G107: ОборудЗак | H107: Стоимость оборудования заказчика | K107: 223 | L107: 9 | M107: 3 | O107: 2 | P107: =ROUND(Source!EI97,O107) -> 0 | W107: 0 | X107: 1 | Y107: 0 | Z107: 0 | AA107: 1 | AB107: 0
A108: 50 | B108: 0 | C108: 0 | D108: 1 | E108: 229 | F108: =ROUND(Source!AZ97,O108) -> 0 | G108: ОборудПод | H108: Стоимость оборудования подрядчика | K108: 229 | L108: 10 | M108: 3 | O108: 2 | P108: =ROUND(Source!ER97,O108) -> 0 | W108: 0 | X108: 1 | Y108: 0 | Z108: 0 | AA108: 1 | AB108: 0
A109: 50 | B109: 0 | C109: 0 | D109: 1 | E109: 203 | F109: =ROUND(Source!Q97,O109) -> 0 | G109: ЭММ | H109: Эксплуатация машин | K109: 203 | L109: 11 | M109: 3 | O109: 2 | P109: =ROUND(Source!DI97,O109) -> 0 | W109: 0 | X109: 1 | Y109: 0 | Z109: 0 | AA109: 1 | AB109: 0
A110: 50 | B110: 0 | C110: 0 | D110: 1 | E110: 231 | F110: =ROUND(Source!BB97,O110) -> 0 | G110: ЭММсНРиСП | H110: Эксплуатация машин по ТСН-2001.16 | K110: 231 | L110: 12 | M110: 3 | O110: 2 | P110: =ROUND(Source!ET97,O110) -> 0 | W110: 0 | X110: 1 | Y110: 0 | Z110: 0 | AA110: 1 | AB110: 0
A111: 50 | B111: 0 | C111: 0 | D111: 1 | E111: 204 | F111: =ROUND(Source!R97,O111) -> 0 | G111: ЗПМ | H111: ЗП машинистов | K111: 204 | L111: 13 | M111: 3 | O111: 2 | P111: =ROUND(Source!DJ97,O111) -> 0 | W111: 0 | X111: 1 | Y111: 0 | Z111: 0 | AA111: 1 | AB111: 0
A112: 50 | B112: 0 | C112: 0 | D112: 1 | E112: 205 | F112: =ROUND(Source!S97,O112) -> 0 | G112: ОЗП | H112: Основная ЗП рабочих | K112: 205 | L112: 14 | M112: 3 | O112: 2 | P112: =ROUND(Source!DK97,O112) -> 0 | W112: 0 | X112: 1 | Y112: 0 | Z112: 0 | AA112: 1 | AB112: 0
A113: 50 | B113: 0 | C113: 0 | D113: 1 | E113: 232 | F113: =ROUND(Source!BC97,O113) -> 0 | G113: ОЗПсНРиСП | H113: Основная ЗП рабочих по ТСН-2001.16 | K113: 232 | L113: 15 | M113: 3 | O113: 2 | P113: =ROUND(Source!EU97,O113) -> 0 | W113: 0 | X113: 1 | Y113: 0 | Z113: 0 | AA113: 1 | AB113: 0
A114: 50 | B114: 0 | C114: 0 | D114: 1 | E114: 214 | F114: =ROUND(Source!AS97,O114) -> 0 | G114: Строит | H114: Строительные работы с НР и СП | K114: 214 | L114: 16 | M114: 3 | O114: 2 | P114: =ROUND(Source!EK97,O114) -> 0 | W114: 0 | X114: 1 | Y114: 0 | Z114: 0 | AA114: 1 | AB114: 0
A115: 50 | B115: 0 | C115: 0 | D115: 1 | E115: 215 | F115: =ROUND(Source!AT97,O115) -> 0 | G115: Монтаж | H115: Монтажные работы с НР и СП | K115: 215 | L115: 17 | M115: 3 | O115: 2 | P115: =ROUND(Source!EL97,O115) -> 0 | W115: 0 | X115: 1 | Y115: 0 | Z115: 0 | AA115: 1 | AB115: 0
A116: 50 | B116: 0 | C116: 0 | D116: 1 | E116: 217 | F116: =ROUND(Source!AU97,O116) -> 0 | G116: Прочие | H116: Прочие работы с НР и СП | K116: 217 | L116: 18 | M116: 3 | O116: 2 | P116: =ROUND(Source!EM97,O116) -> 0 | W116: 0 | X116: 1 | Y116: 0 | Z116: 0 | AA116: 1 | AB116: 0
A117: 50 | B117: 0 | C117: 0 | D117: 1 | E117: 230 | F117: =ROUND(Source!BA97,O117) -> 0 | G117: ПрочиеЗатр | H117: Прочие затраты по ТСН-2001.16 | K117: 230 | L117: 19 | M117: 3 | O117: 2 | P117: =ROUND(Source!ES97,O117) -> 0 | W117: 0 | X117: 1 | Y117: 0 | Z117: 0 | AA117: 1 | AB117: 0
A118: 50 | B118: 0 | C118: 0 | D118: 1 | E118: 206 | F118: =ROUND(Source!T97,O118) -> 86069.65 | G118: ВозврМат | H118: Возврат материалов | K118: 206 | L118: 20 | M118: 3 | O118: 2 | P118: =ROUND(Source!DL97,O118) -> 733435.55 | W118: 86069.65 | X118: 1 | Y118: 86069.65 | Z118: 733435.55 | AA118: 1 | AB118: 733435.55
A119: 50 | B119: 0 | C119: 0 | D119: 1 | E119: 207 | F119: =Source!U97 -> 0 | G119: ТрудСтр | H119: Трудозатраты строителей | K119: 207 | L119: 21 | M119: 3 | O119: -1 | P119: =Source!DM97 -> 0 | W119: 0 | X119: 1 | Y119: 0 | Z119: 0 | AA119: 1 | AB119: 0
A120: 50 | B120: 0 | C120: 0 | D120: 1 | E120: 208 | F120: =Source!V97 -> 0 | G120: ТрудМаш | H120: Трудозатраты машинистов | K120: 208 | L120: 22 | M120: 3 | O120: -1 | P120: =Source!DN97 -> 0 | W120: 0 | X120: 1 | Y120: 0 | Z120: 0 | AA120: 1 | AB120: 0
A121: 50 | B121: 0 | C121: 0 | D121: 1 | E121: 209 | F121: =ROUND(Source!W97,O121) -> 0 | G121: ТранспМат | H121: Транспорт материалов | K121: 209 | L121: 23 | M121: 3 | O121: 2 | P121: =ROUND(Source!DO97,O121) -> 0 | W121: 0 | X121: 1 | Y121: 0 | Z121: 0 | AA121: 1 | AB121: 0
A122: 50 | B122: 0 | C122: 0 | D122: 1 | E122: 233 | F122: =ROUND(Source!BD97,O122) -> 0 | G122: Перевозка | H122: Перевозка грузов | K122: 233 | L122: 24 | M122: 3 | O122: 2 | P122: =ROUND(Source!EV97,O122) -> 0 | W122: 0 | X122: 1 | Y122: 0 | Z122: 0 | AA122: 1 | AB122: 0
A123: 50 | B123: 0 | C123: 0 | D123: 1 | E123: 210 | F123: =ROUND(Source!X97,O123) -> 0 | G123: НР | H123: Накладные расходы | K123: 210 | L123: 25 | M123: 3 | O123: 2 | P123: =ROUND(Source!DP97,O123) -> 0 | W123: 0 | X123: 1 | Y123: 0 | Z123: 0 | AA123: 1 | AB123: 0
A124: 50 | B124: 0 | C124: 0 | D124: 1 | E124: 211 | F124: =ROUND(Source!Y97,O124) -> 0 | G124: СмПриб | H124: Сметная прибыль | K124: 211 | L124: 26 | M124: 3 | O124: 2 | P124: =ROUND(Source!DQ97,O124) -> 0 | W124: 0 | X124: 1 | Y124: 0 | Z124: 0 | AA124: 1 | AB124: 0
...

Sheet SourceObSm
A1: 0 | B1: Smeta.RU (495) 974-1589 | D1: _OBSM_ | F1: 0 | G1: 0 | H1: 0 | I1: Smeta.RU | K1: 1 | L1: 74562 | M1: 10 | N1: 11 | O1: 14 | P1: 0 | Q1: 0
A4: 1 | B4: 1 | C4: -1 | G4: Капитальный ремонт здания Государственного бюджетного общеобразовательного учреждения города Москвы «Школа № 236» по адресу: г. Москва, ул. Клязьминская, д. 7, к. 4. I этап | EC4: 0
A12: 1 | B12: 51 | C12: 0 | E12: 0 | F12: б/н | G12: б/н Возвратные средства | I12: 0 | J12: 0224-00272-01-0-ООС2 | K12: 0 | L12: 0 | M12: 4098 | O12: 0 | P12: 0 | Q12: 0 | R12: 0 | S12: 0 | T12: 1 | V12: 0 | AB12: Лукьянова А.Л. | BB12: 0 | BH12: Сметные нормы списания | BI12: Коды ОКП для ТСН-2001 МГЭ Дополнение 79 | BJ12: 1 | BK12: 1 | BL12: 0 | BM12: 0 | BN12: 1 | BO12: 0 | BP12: 6 | BQ12: 2 | BR12: 1 | BS12: 1 | BT12: 0 | BU12: 0 | BV12: 0 | BW12: 0 | BX12: 0 | BY12: ТСН-2001 (МГЭ) Доп 79 - Ремонт | BZ12: Типовой расчет для ТСН-2001 МГЭ, Дополнение 79, ремонт | CA12: Территориальные сметные нормативы для Москвы ТСН-2001 (МГЭ), дополнение 79 | CB12: Территориальные сметные нормативы для Москвы ТСН-2001 (МГЭ), дополнение 79 | CC12: Территориальные сметные нормативы для Москвы ТСН-2001 (МГЭ), дополнение 79 | CD12: Территориальные сметные нормативы для Москвы ТСН-2001 (МГЭ), дополнение 79 | CE12: Поправки для ТСН-2001 от 03.10.2025 г. доп.79 | CF12: 0 | CG12: 0 | CH12: 8200 | CK12: 79 | CQ12: Территориальные сметные нормативы для Москвы (ТСН-2001) | CR12: ТЕР | CS12: 41660 | CT12: 1 | CU12: 79 | CY12: 0 | EC12: 0
A14: 22 | B14: 1 | C14: 0 | D14: 56526434 | E14: 56526432 | F14: 2 | G14: 1
A16: 3 | B16: 1 | C16: б/н | D16: Возвратные средства | E16: =ROUND((Source!P84)/1000,2) -> 0 | F16: =ROUND((Source!P85)/1000,2) -> 0 | G16: =ROUND((Source!P76)/1000,2) -> 0 | H16: =ROUND((Source!P86)/1000+(Source!P87)/1000,2) -> 0 | I16: =E16+F16+G16+H16 -> 0 | J16: =ROUND((Source!P82+Source!P81)/1000,2) -> 0 | K16: 0 | L16: 0 | M16: 0 | N16: =I16+L16+M16 -> 0 | T16: =ROUND((Source!F84)/1000,2) -> 0 | U16: =ROUND((Source!F85)/1000,2) -> 0 | V16: =ROUND((Source!F76)/1000,2) -> 0 | W16: =ROUND((Source!F86)/1000+(Source!F87)/1000,2) -> 0 | X16: =T16+U16+V16+W16 -> 0 | Y16: =ROUND((Source!F82+Source!F81)/1000,2) -> 0 | Z16: 0 | AA16: 0 | AB16: 0 | AC16: =X16+AA16+AB16 -> 0 | AI16: 0 | AJ16: -1 | AN16: 0 | AT16: 0 | AU16: 0 | AV16: 0 | AW16: 0 | AX16: 0 | AY16: 0 | AZ16: 0 | BA16: 0 | BB16: 0 | BC16: 0 | BD16: 0 | BE16: 733435.55 | BF16: 0 | BG16: 0 | BH16: 0 | BI16: 0 | BJ16: 0 | BK16: 0 | BR16: 0 | BS16: 0 | BT16: 0 | BU16: 0 | BV16: 0 | BW16: 0 | BX16: 0 | BY16: 0 | BZ16: 0 | CA16: 0 | CB16: 0 | CC16: 86069.65 | CD16: 0 | CE16: 0 | CF16: 0 | CG16: 0 | CH16: 0 | CI16: 0
A18: 51 | E18: 0 | F18: 0 | G18: 0 | H18: 0 | I18: 0 | J18: 0 | K18: 0 | L18: 0 | M18: 0 | N18: 0 | T18: 0 | U18: 0 | V18: 0 | W18: 0 | X18: 0 | Y18: 0 | Z18: 0 | AA18: 0 | AB18: 0 | AC18: 0
A20: 50 | B20: 0 | C20: 0 | D20: 1 | E20: 201 | F20: 0 | G20: ПЗ | H20: Прямые затраты | K20: 201 | L20: 1 | M20: 3 | O20: 2 | P20: 0
A21: 50 | B21: 0 | C21: 0 | D21: 1 | E21: 202 | F21: 0 | G21: СтМатОб | H21: Стоимость материальных ресурсов (всего) | K21: 202 | L21: 2 | M21: 3 | O21: 2 | P21: 0
A22: 50 | B22: 0 | C22: 0 | D22: 1 | E22: 222 | F22: 0 | G22: СтМатОбЗак | H22: Стоимость материалов и оборудования заказчика | K22: 222 | L22: 3 | M22: 3 | O22: 2 | P22: 0
A23: 50 | B23: 0 | C23: 0 | D23: 1 | E23: 225 | F23: 0 | G23: СтМатОбПод | H23: Стоимость материалов и оборудования подрядчика | K23: 225 | L23: 4 | M23: 3 | O23: 2 | P23: 0
A24: 50 | B24: 0 | C24: 0 | D24: 1 | E24: 226 | F24: 0 | G24: СтМат | H24: Стоимость материалов (всего) | K24: 226 | L24: 5 | M24: 3 | O24: 2 | P24: 0
A25: 50 | B25: 0 | C25: 0 | D25: 1 | E25: 227 | F25: 0 | G25: СтМатЗак | H25: Стоимость материалов заказчика | K25: 227 | L25: 6 | M25: 3 | O25: 2 | P25: 0
A26: 50 | B26: 0 | C26: 0 | D26: 1 | E26: 228 | F26: 0 | G26: СтМатПод | H26: Стоимость материалов подрядчика | K26: 228 | L26: 7 | M26: 3 | O26: 2 | P26: 0
A27: 50 | B27: 0 | C27: 0 | D27: 1 | E27: 216 | F27: 0 | G27: Оборуд | H27: Стоимость оборудования (всего) | K27: 216 | L27: 8 | M27: 3 | O27: 2 | P27: 0
A28: 50 | B28: 0 | C28: 0 | D28: 1 | E28: 223 | F28: 0 | G28: ОборудЗак | H28: Стоимость оборудования заказчика | K28: 223 | L28: 9 | M28: 3 | O28: 2 | P28: 0
A29: 50 | B29: 0 | C29: 0 | D29: 1 | E29: 229 | F29: 0 | G29: ОборудПод | H29: Стоимость оборудования подрядчика | K29: 229 | L29: 10 | M29: 3 | O29: 2 | P29: 0
A30: 50 | B30: 0 | C30: 0 | D30: 1 | E30: 203 | F30: 0 | G30: ЭММ | H30: Эксплуатация машин | K30: 203 | L30: 11 | M30: 3 | O30: 2 | P30: 0
A31: 50 | B31: 0 | C31: 0 | D31: 1 | E31: 231 | F31: 0 | G31: ЭММсНРиСП | H31: Эксплуатация машин по ТСН-2001.16 | K31: 231 | L31: 12 | M31: 3 | O31: 2 | P31: 0
... A46: 50 | B46: 0 | C46: 0 | D46: 1 | E46: 224 | F46: 0 | G46: Всего | H46: Всего с НР и СП | K46: 224 | L46: 27 | M46: 3 | O46: 2 | P46: 0
A48: -1
A51: 75 | B51: Текущий уровень цен | C51: 2025 | D51: 0 | E51: 7 | G51: 0 | H51: 1 | I51: 1 | J51: 3 | K51: 0 | L51: 0 | M51: 1 | N51: 56526434 | O51: 1
A52: 1 | B52: Сборник индексов | C52: Коэффициенты к ТСН-2001 МГЭ Дополнение 79, ремонт | D52: 2025 | E52: 7 | F52: 1 | G52: 1 | H52: 0 | I52: 2 | J52: 1 | K52: 1 | L52: 1 | M52: 1 | N52: 1 | O52: 1 | P52: 1 | Q52: 1 | AA52: 216/79 | AN52: 56526435
A53: 1 | B53: Сборник индексов | C53: Коэффициенты к ТСН-2001.13-2 Дополнение 45 | D53: 2025 | E53: 7 | F53: 1 | G53: 1 | H53: 0 | I53: 2 | J53: 1 | K53: 1 | L53: 1 | M53: 1 | N53: 1 | O53: 1 | P53: 1 | Q53: 1 | AA53: 62/45 | AN53: 56526436
A54: 75 | B54: Базовый уровень цен | C54: 2000 | D54: 0 | E54: 1 | F54: 0 | G54: 0 | H54: 1 | I54: 1 | J54: 3 | K54: 0 | L54: 0 | M54: 0 | N54: 56526432 | O54: 2
A55: 1 | B55: Сборник индексов | C55: Коэффициенты к ТСН-2001 МГЭ Дополнение 79, ремонт | D55: 2000 | E55: 1 | F55: 1 | G55: 1 | H55: 0 | I55: 2 | J55: 1 | K55: 1 | L55: 1 | M55: 1 | N55: 1 | O55: 1 | P55: 1 | Q55: 1 | AN55: 56526433

Sheet SmtRes

Sheet EtalonRes

Sheet SrcPoprs

Sheet SrcKA
A1: 0 | B1: Smeta.RU (495) 974-1589 | D1: _PS_ | F1: 0 | G1: 0 | H1: 0 | I1: Smeta.RU | K1: 1 | L1: 74562 | M1: 10 | N1: 11 | O1: 14 | P1: 0 | Q1: 0
F12: =Source!F12 -> б/н | G12: =Source!G12 -> б/н Возвратные средства | CY12: =Source!CY12 -> 0
