Workbook

Sheet 09-01-03
A1: =Source!B1 -> Smeta.RU (495) 974-1589
J2: Форма № 4б
B3: "СОГЛАСОВАНО" | G3: "УТВЕРЖДАЮ"
B6: =CONCATENATE("______________________ ", IF(Source!AL12<>"", Source!AL12, "")) -> ______________________ | G6: =CONCATENATE("______________________ ", IF(Source!AH12<>"", Source!AH12, "")) -> ______________________
B7: "_____"________________ 2025 г. | G7: "_____"________________ 2025 г.
A10: Капитальный ремонт здания Государственного бюджетного общеобразовательного учреждения города Москвы «Школа № 236» по адресу: г. Москва, ул. Клязьминская, д. 7, к. 4. I этап | AP10: Капитальный ремонт здания Государственного бюджетного общеобразовательного учреждения города Москвы «Школа № 236» по адресу: г. Москва, ул. Клязьминская, д. 7, к. 4. I этап. 09-01-03 Размещение и содержание строительного мусора
A11: (наименование стройки и/или объекта)
A13: ЛОКАЛЬНАЯ СМЕТА № 09-01-03
A15: =IF(Source!G20<>"Новая локальная смета", Source!G20, "") -> Размещение и содержание строительного мусора
A16: (наименование работ и затрат)
A18: =CONCATENATE( "Основание: чертежи № ", Source!J20) -> Основание: чертежи № 0224-00272-01-0-ООС2
I20: В базисном уровне цен | J20: В текущем уровне цен
E21: Сметная стоимость | I21: =I22+I23+I24+I25 -> 96.54 | J21: =J22+J23+J24+J25 -> 961.16 | K21: тыс.руб.
E22: Строительные работы | I22: =ROUND((Source!F112)/1000, 2) -> 0 | J22: =ROUND((Source!P112)/1000, 2) -> 0 | K22: тыс.руб.
E23: Работы по монтажу оборудования | I23: =ROUND((Source!F113)/1000, 2) -> 0 | J23: =ROUND((Source!P113)/1000, 2) -> 0 | K23: тыс.руб.
E24: Оборудование | I24: =ROUND((Source!F104)/1000, 2) -> 0 | J24: =ROUND((Source!P104)/1000, 2) -> 0 | K24: тыс.руб.
E25: Прочие работы и затраты | I25: =ROUND((Source!F114+Source!F115)/1000, 2) -> 96.54 | J25: =ROUND((Source!P114+Source!P115)/1000, 2) -> 961.16 | K25: тыс.руб.
E26: Средства на оплату труда | I26: =(Source!F110+ Source!F109)/1000 -> 0 | J26: =((Source!P110 + Source!P109)/1000) -> 0 | K26: тыс.руб.
E27: Затраты труда | I27: =Source!F117 -> 0 | K27: чел.-ч.
E28: Кроме того:
E29: Возврат материалов | I29: =SUM(Y35:Y152)/1000 -> 0 | J29: =SUM(Z35:Z152)/1000 -> 0 | K29: тыс.руб.
A31: Составлен(а) по ТСН-2001 с учетом Дополнения №: 79
A32: № и период сборника коэффициентов (индексов) пересчета: Коэффициенты к ТСН-2001 МГЭ Дополнение 79, ремонт №216/79 III квартал 2025 года и Коэффициенты к ТСН-2001.13-2 Дополнение 45 №62/45 III квартал 2025 года | M32: 3 кв-л сентябрь | AP32: № и период сборника коэффициентов (индексов) пересчета: Коэффициенты к ТСН-2001 МГЭ Дополнение 79, ремонт №216/79 III квартал 2025 года и Коэффициенты к ТСН-2001.13-2 Дополнение 45 №62/45 III квартал 2025 года
A33: № п/п | B33: Шифр расценки и коды ресурсов | C33: Наименование работ и затрат | D33: Ед. изм. | E33: Кол-во единиц | F33: Цена на ед. изм., руб. | G33: Попра- вочные коэффи- циенты | H33: Коэффи- циенты зимних удорожа- ний | I33: Всего в ценах на январь 2000 года, руб. | J33: Коэффи- циенты (индек- сы) пере- счета, нормы НР и СП | K33: ВСЕГО затрат в текущем уровне цен, руб.
A34: 1 | B34: 2 | C34: 3 | D34: 4 | E34: 5 | F34: 6 | G34: 7 | H34: 8 | I34: 9 | J34: 10 | K34: 11
A36: =CONCATENATE("Раздел: ",IF(Source!G24<>"Новый раздел", Source!G24, "")) -> Раздел: Размещение и содержание строительного мусора
A37: 1 | B37: =Source!F28 -> 15.1-1500-01 | C37: Отходы (мусор) от строительных и ремонтных работ малоопасные | D37: =Source!H28 -> 1 Т | E37: =Source!I28 -> 74.973 | Q37: =Source!X28 -> 0 | R37: =Source!X29 -> 0 | S37: =Source!Y28 -> 0 | T37: =Source!Y29 -> 0 | U37: =ROUND((175/100)*ROUND(Source!R28, 2), 2) -> 0 | V37: =ROUND((0/100)*ROUND(Source!R29, 2), 2) -> 0 | AC37: 0
C38: ЭМ | F38: =Source!AM28 -> 31.67 | G38: =Source!DE28 | H38: =Source!AV29 -> 1 | I38: =Source!Q28 -> 2374.39 | J38: =IF(Source!BB29<> 0, Source!BB29, 1) -> 43.37 | K38: =Source!Q29 -> 102977.29
C39: ВСЕГО работ по позиции: | H39: =I38+0-0-0 -> 2374.39 | J39: =K38+0-0-0 -> 102977.29
C40: ВСЕГО оборудование по позиции: | H40: =0+0 -> 0 | J40: =0+0 -> 0
C41: ВСЕГО по позиции: | H41: =I38+0 -> 2374.39 | J41: =K38+0 -> 102977.29 | O41: =I38+0 -> 2374.39 | P41: =K38+0 -> 102977.29
A43: 2 | B43: =Source!F30 -> 15.1-1201-10 | C43: Отходы затвердевшего строительного раствора в кусковой форме, малоопасные | D43: =Source!H30 -> 1 Т | E43: =Source!I30 -> 1545.61 | Q43: =Source!X30 -> 0 | R43: =Source!X31 -> 0 | S43: =Source!Y30 -> 0 | T43: =Source!Y31 -> 0 | U43: =ROUND((175/100)*ROUND(Source!R30, 2), 2) -> 0 | V43: =ROUND((0/100)*ROUND(Source!R31, 2), 2) -> 0 | AC43: 0
C44: ЭМ | F44: =Source!AM30 -> 31.13 | G44: =Source!DE30 | H44: =Source!AV31 -> 1 | I44: =Source!Q30 -> 48114.84 | J44: =IF(Source!BB31<> 0, Source!BB31, 1) -> 9.33 | K44: =Source!Q31 -> 448911.46
C45: ВСЕГО работ по позиции: | H45: =I44+0-0-0 -> 48114.84 | J45: =K44+0-0-0 -> 448911.46
C46: ВСЕГО оборудование по позиции: | H46: =0+0 -> 0 | J46: =0+0 -> 0
C47: ВСЕГО по позиции: | H47: =I44+0 -> 48114.84 | J47: =K44+0 -> 448911.46 | O47: =I44+0 -> 48114.84 | P47: =K44+0 -> 448911.46
A49: 3 | B49: =Source!F32 -> 15.1-1203-06 | C49: Отходы штукатурки затвердевшей малоопасные | D49: =Source!H32 -> 1 Т | E49: =Source!I32 -> 195.77 | Q49: =Source!X32 -> 0 | R49: =Source!X33 -> 0 | S49: =Source!Y32 -> 0 | T49: =Source!Y33 -> 0 | U49: =ROUND((175/100)*ROUND(Source!R32, 2), 2) -> 0 | V49: =ROUND((0/100)*ROUND(Source!R33, 2), 2) -> 0 | AC49: 0
C50: ЭМ | F50: =Source!AM32 -> 36.59 | G50: =Source!DE32 | H50: =Source!AV33 -> 1 | I50: =Source!Q32 -> 7163.22 | J50: =IF(Source!BB33<> 0, Source!BB33, 1) -> 9.57 | K50: =Source!Q33 -> 68552.02
C51: ВСЕГО работ по позиции: | H51: =I50+0-0-0 -> 7163.22 | J51: =K50+0-0-0 -> 68552.02
C52: ВСЕГО оборудование по позиции: | H52: =0+0 -> 0 | J52: =0+0 -> 0
C53: ВСЕГО по позиции: | H53: =I50+0 -> 7163.22 | J53: =K50+0 -> 68552.02 | O53: =I50+0 -> 7163.22 | P53: =K50+0 -> 68552.02
A55: 4 | B55: =Source!F34 -> 15.1-1505-04 | C55: Отходы прочих теплоизоляционных материалов на основе минерального волокна незагрязненные, практически неопасные | D55: =Source!H34 -> 1 Т | E55: =Source!I34 -> 4.248 | Q55: =Source!X34 -> 0 | R55: =Source!X35 -> 0 | S55: =Source!Y34 -> 0 | T55: =Source!Y35 -> 0 | U55: =ROUND((175/100)*ROUND(Source!R34, 2), 2) -> 0 | V55: =ROUND((0/100)*ROUND(Source!R35, 2), 2) -> 0 | AC55: 0
C56: ЭМ | F56: =Source!AM34 -> 98.3 | G56: =Source!DE34 | H56: =Source!AV35 -> 1 | I56: =Source!Q34 -> 417.58 | J56: =IF(Source!BB35<> 0, Source!BB35, 1) -> 11.02 | K56: =Source!Q35 -> 4601.73
C57: ВСЕГО работ по позиции: | H57: =I56+0-0-0 -> 417.58 | J57: =K56+0-0-0 -> 4601.73
C58: ВСЕГО оборудование по позиции: | H58: =0+0 -> 0 | J58: =0+0 -> 0
C59: ВСЕГО по позиции: | H59: =I56+0 -> 417.58 | J59: =K56+0 -> 4601.73 | O59: =I56+0 -> 417.58 | P59: =K56+0 -> 4601.73
A61: 5 | B61: =Source!F36 -> 15.1-1203-02 | C61: Обрезь и лом гипсокартонных листов малоопасные | D61: =Source!H36 -> 1 Т | E61: =Source!I36 -> 0.035 | Q61: =Source!X36 -> 0 | R61: =Source!X37 -> 0 | S61: =Source!Y36 -> 0 | T61: =Source!Y37 -> 0 | U61: =ROUND((175/100)*ROUND(Source!R36, 2), 2) -> 0 | V61: =ROUND((0/100)*ROUND(Source!R37, 2), 2) -> 0 | AC61: 0
C62: ЭМ | F62: =Source!AM36 -> 38.77 | G62: =Source!DE36 | H62: =Source!AV37 -> 1 | I62: =Source!Q36 -> 1.36 | J62: =IF(Source!BB37<> 0, Source!BB37, 1) -> 10.53 | K62: =Source!Q37 -> 14.32
C63: ВСЕГО работ по позиции: | H63: =I62+0-0-0 -> 1.36 | J63: =K62+0-0-0 -> 14.32
C64: ВСЕГО оборудование по позиции: | H64: =0+0 -> 0 | J64: =0+0 -> 0
C65: ВСЕГО по позиции: | H65: =I62+0 -> 1.36 | J65: =K62+0 -> 14.32 | O65: =I62+0 -> 1.36 | P65: =K62+0 -> 14.32
A67: 6 | B67: =Source!F38 -> 15.1-1207-01 | C67: Отходы линолеума незагрязненные малоопасные | D67: =Source!H38 -> 1 Т | E67: =Source!I38 -> 3.487 | Q67: =Source!X38 -> 0 | R67: =Source!X39 -> 0 | S67: =Source!Y38 -> 0 | T67: =Source!Y39 -> 0 | U67: =ROUND((175/100)*ROUND(Source!R38, 2), 2) -> 0 | V67: =ROUND((0/100)*ROUND(Source!R39, 2), 2) -> 0 | AC67: 0
C68: ЭМ | F68: =Source!AM38 -> 38.77 | G68: =Source!DE38 | H68: =Source!AV39 -> 1 | I68: =Source!Q38 -> 135.19 | J68: =IF(Source!BB39<> 0, Source!BB39, 1) -> 49.45 | K68: =Source!Q39 -> 6685.15
C69: ВСЕГО работ по позиции: | H69: =I68+0-0-0 -> 135.19 | J69: =K68+0-0-0 -> 6685.15
C70: ВСЕГО оборудование по позиции: | H70: =0+0 -> 0 | J70: =0+0 -> 0
C71: ВСЕГО по позиции: | H71: =I68+0 -> 135.19 | J71: =K68+0 -> 6685.15 | O71: =I68+0 -> 135.19 | P71: =K68+0 -> 6685.15
A73: 7 | B73: =Source!F40 -> 15.1-1504-23 | C73: Отходы фанеры и изделий из нее незагрязненные | D73: =Source!H40 -> 1 Т | E73: =Source!I40 -> 0.027 | Q73: =Source!X40 -> 0 | R73: =Source!X41 -> 0 | S73: =Source!Y40 -> 0 | T73: =Source!Y41 -> 0 | U73: =ROUND((175/100)*ROUND(Source!R40, 2), 2) -> 0 | V73: =ROUND((0/100)*ROUND(Source!R41, 2), 2) -> 0 | AC73: 0
C74: ЭМ | F74: =Source!AM40 -> 36.3 | G74: =Source!DE40 | H74: =Source!AV41 -> 1 | I74: =Source!Q40 -> 0.98 | J74: =IF(Source!BB41<> 0, Source!BB41, 1) -> 10.25 | K74: =Source!Q41 -> 10.05
C75: ВСЕГО работ по позиции: | H75: =I74+0-0-0 -> 0.98 | J75: =K74+0-0-0 -> 10.05
C76: ВСЕГО оборудование по позиции: | H76: =0+0 -> 0 | J76: =0+0 -> 0
C77: ВСЕГО по позиции: | H77: =I74+0 -> 0.98 | J77: =K74+0 -> 10.05 | O77: =I74+0 -> 0.98 | P77: =K74+0 -> 10.05
A79: 8 | B79: =Source!F42 -> 15.1-1500-01 | C79: Отходы (мусор) от строительных и ремонтных работ малоопасные / светильники со светодиодными элементами в сборе | D79: =Source!H42 -> 1 Т | E79: =Source!I42 -> 0.653 | Q79: =Source!X42 -> 0 | R79: =Source!X43 -> 0 | S79: =Source!Y42 -> 0 | T79: =Source!Y43 -> 0 | U79: =ROUND((175/100)*ROUND(Source!R42, 2), 2) -> 0 | V79: =ROUND((0/100)*ROUND(Source!R43, 2), 2) -> 0 | AC79: 0
C80: ЭМ | F80: =Source!AM42 -> 31.67 | G80: =Source!DE42 | H80: =Source!AV43 -> 1 | I80: =Source!Q42 -> 20.68 | J80: =IF(Source!BB43<> 0, Source!BB43, 1) -> 43.37 | K80: =Source!Q43 -> 896.89
C81: ВСЕГО работ по позиции: | H81: =I80+0-0-0 -> 20.68 | J81: =K80+0-0-0 -> 896.89
C82: ВСЕГО оборудование по позиции: | H82: =0+0 -> 0 | J82: =0+0 -> 0
C83: ВСЕГО по позиции: | H83: =I80+0 -> 20.68 | J83: =K80+0 -> 896.89 | O83: =I80+0 -> 20.68 | P83: =K80+0 -> 896.89
A85: 9 | B85: =Source!F44 -> 15.1-1207-03 | C85: Смесь незагрязненных строительных материалов на основе полимеров, содержащая поливинилхлорид малоопасная | D85: =Source!H44 -> 1 Т | E85: =Source!I44 -> 3.873 | Q85: =Source!X44 -> 0 | R85: =Source!X45 -> 0 | S85: =Source!Y44 -> 0 | T85: =Source!Y45 -> 0 | U85: =ROUND((175/100)*ROUND(Source!R44, 2), 2) -> 0 | V85: =ROUND((0/100)*ROUND(Source!R45, 2), 2) -> 0 | AC85: 0
C86: ЭМ | F86: =Source!AM44 -> 47.51 | G86: =Source!DE44 | H86: =Source!AV45 -> 1 | I86: =Source!Q44 -> 184.01 | J86: =IF(Source!BB45<> 0, Source!BB45, 1) -> 35.52 | K86: =Source!Q45 -> 6536.04
C87: ВСЕГО работ по позиции: | H87: =I86+0-0-0 -> 184.01 | J87: =K86+0-0-0 -> 6536.04
C88: ВСЕГО оборудование по позиции: | H88: =0+0 -> 0 | J88: =0+0 -> 0
C89: ВСЕГО по позиции: | H89: =I86+0 -> 184.01 | J89: =K86+0 -> 6536.04 | O89: =I86+0 -> 184.01 | P89: =K86+0 -> 6536.04
A91: 10 | B91: =Source!F46 -> 15.1-1201-03 | C91: Лом бетонных изделий, отходы бетона в кусковой форме, практически неопасные | D91: =Source!H46 -> 1 Т | E91: =Source!I46 -> 666.679 | Q91: =Source!X46 -> 0 | R91: =Source!X47 -> 0 | S91: =Source!Y46 -> 0 | T91: =Source!Y47 -> 0 | U91: =ROUND((175/100)*ROUND(Source!R46, 2), 2) -> 0 | V91: =ROUND((0/100)*ROUND(Source!R47, 2), 2) -> 0 | AC91: 0
C92: ЭМ | F92: =Source!AM46 -> 22.57 | G92: =Source!DE46 | H92: =Source!AV47 -> 1 | I92: =Source!Q46 -> 15046.95 | J92: =IF(Source!BB47<> 0, Source!BB47, 1) -> 6.48 | K92: =Source!Q47 -> 97504.24
C93: ВСЕГО работ по позиции: | H93: =I92+0-0-0 -> 15046.95 | J93: =K92+0-0-0 -> 97504.24
C94: ВСЕГО оборудование по позиции: | H94: =0+0 -> 0 | J94: =0+0 -> 0
C95: ВСЕГО по позиции: | H95: =I92+0 -> 15046.95 | J95: =K92+0 -> 97504.24 | O95: =I92+0 -> 15046.95 | P95: =K92+0 -> 97504.24
A97: 11 | B97: =Source!F48 -> 15.1-1202-02 | C97: Лом черепицы, керамики незагрязненный практически неопасный | D97: =Source!H48 -> 1 Т | E97: =Source!I48 -> 146.251 | Q97: =Source!X48 -> 0 | R97: =Source!X49 -> 0 | S97: =Source!Y48 -> 0 | T97: =Source!Y49 -> 0 | U97: =ROUND((175/100)*ROUND(Source!R48, 2), 2) -> 0 | V97: =ROUND((0/100)*ROUND(Source!R49, 2), 2) -> 0 | AC97: 0
C98: ЭМ | F98: =Source!AM48 -> 21.71 | G98: =Source!DE48 | H98: =Source!AV49 -> 1 | I98: =Source!Q48 -> 3175.11 | J98: =IF(Source!BB49<> 0, Source!BB49, 1) -> 14.06 | K98: =Source!Q49 -> 44642.05
C99: ВСЕГО работ по позиции: | H99: =I98+0-0-0 -> 3175.11 | J99: =K98+0-0-0 -> 44642.05
C100: ВСЕГО оборудование по позиции: | H100: =0+0 -> 0 | J100: =0+0 -> 0
C101: ВСЕГО по позиции: | H101: =I98+0 -> 3175.11 | J101: =K98+0 -> 44642.05 | O101: =I98+0 -> 3175.11 | P101: =K98+0 -> 44642.05
A103: 12 | B103: =Source!F50 -> 15.1-1202-01 | C103: Лом строительного кирпича незагрязненный практически неопасный | D103: =Source!H50 -> 1 Т | E103: =Source!I50 -> 0.309 | Q103: =Source!X50 -> 0 | R103: =Source!X51 -> 0 | S103: =Source!Y50 -> 0 | T103: =Source!Y51 -> 0 | U103: =ROUND((175/100)*ROUND(Source!R50, 2), 2) -> 0 | V103: =ROUND((0/100)*ROUND(Source!R51, 2), 2) -> 0 | AC103: 0
C104: ЭМ | F104: =Source!AM50 -> 21.71 | G104: =Source!DE50 | H104: =Source!AV51 -> 1 | I104: =Source!Q50 -> 6.71 | J104: =IF(Source!BB51<> 0, Source!BB51, 1) -> 11.3 | K104: =Source!Q51 -> 75.82
C105: ВСЕГО работ по позиции: | H105: =I104+0-0-0 -> 6.71 | J105: =K104+0-0-0 -> 75.82
C106: ВСЕГО оборудование по позиции: | H106: =0+0 -> 0 | J106: =0+0 -> 0
C107: ВСЕГО по позиции: | H107: =I104+0 -> 6.71 | J107: =K104+0 -> 75.82 | O107: =I104+0 -> 6.71 | P107: =K104+0 -> 75.82
A109: 13 | B109: =Source!F52 -> 15.1-1105-01 | C109: Лом кирпичной кладки от сноса и разборки зданий практически неопасный | D109: =Source!H52 -> 1 Т | E109: =Source!I52 -> 206.091 | Q109: =Source!X52 -> 0 | R109: =Source!X53 -> 0 | S109: =Source!Y52 -> 0 | T109: =Source!Y53 -> 0 | U109: =ROUND((175/100)*ROUND(Source!R52, 2), 2) -> 0 | V109: =ROUND((0/100)*ROUND(Source!R53, 2), 2) -> 0 | AC109: 0
C110: ЭМ | F110: =Source!AM52 -> 21.71 | G110: =Source!DE52 | H110: =Source!AV53 -> 1 | I110: =Source!Q52 -> 4474.24 | J110: =IF(Source!BB53<> 0, Source!BB53, 1) -> 11.84 | K110: =Source!Q53 -> 52975
C111: ВСЕГО работ по позиции: | H111: =I110+0-0-0 -> 4474.24 | J111: =K110+0-0-0 -> 52975
C112: ВСЕГО оборудование по позиции: | H112: =0+0 -> 0 | J112: =0+0 -> 0
C113: ВСЕГО по позиции: | H113: =I110+0 -> 4474.24 | J113: =K110+0 -> 52975 | O113: =I110+0 -> 4474.24 | P113: =K110+0 -> 52975
A115: 14 | B115: =Source!F54 -> 15.1-1200-01 | C115: Лом бортовых камней, брусчатки, булыжных камней и прочие отходы изделий из природного камня, практически неопасный | D115: =Source!H54 -> 1 Т | E115: =Source!I54 -> 4.628 | Q115: =Source!X54 -> 0 | R115: =Source!X55 -> 0 | S115: =Source!Y54 -> 0 | T115: =Source!Y55 -> 0 | U115: =ROUND((175/100)*ROUND(Source!R54, 2), 2) -> 0 | V115: =ROUND((0/100)*ROUND(Source!R55, 2), 2) -> 0 | AC115: 0
C116: ЭМ | F116: =Source!AM54 -> 21.71 | G116: =Source!DE54 | H116: =Source!AV55 -> 1 | I116: =Source!Q54 -> 100.47 | J116: =IF(Source!BB55<> 0, Source!BB55, 1) -> 9 | K116: =Source!Q55 -> 904.23
C117: ВСЕГО работ по позиции: | H117: =I116+0-0-0 -> 100.47 | J117: =K116+0-0-0 -> 904.23
C118: ВСЕГО оборудование по позиции: | H118: =0+0 -> 0 | J118: =0+0 -> 0
C119: ВСЕГО по позиции: | H119: =I116+0 -> 100.47 | J119: =K116+0 -> 904.23 | O119: =I116+0 -> 100.47 | P119: =K116+0 -> 904.23
A121: 15 | B121: =Source!F56 -> 15.1-1509-01 | C121: Отходы изолированных проводов и кабелей | D121: =Source!H56 -> 1 Т | E121: =Source!I56 -> 3.611 | Q121: =Source!X56 -> 0 | R121: =Source!X57 -> 0 | S121: =Source!Y56 -> 0 | T121: =Source!Y57 -> 0 | U121: =ROUND((175/100)*ROUND(Source!R56, 2), 2) -> 0 | V121: =ROUND((0/100)*ROUND(Source!R57, 2), 2) -> 0 | AC121: 0
C122: ЭМ | F122: =Source!AM56 -> 24.39 | G122: =Source!DE56 | H122: =Source!AV57 -> 1 | I122: =Source!Q56 -> 88.07 | J122: =IF(Source!BB57<> 0, Source!BB57, 1) -> 10.25 | K122: =Source!Q57 -> 902.72
C123: ВСЕГО работ по позиции: | H123: =I122+0-0-0 -> 88.07 | J123: =K122+0-0-0 -> 902.72
C124: ВСЕГО оборудование по позиции: | H124: =0+0 -> 0 | J124: =0+0 -> 0
...

Sheet Ведомость объемов работ
A1: =Source!B1 -> Smeta.RU (495) 974-1589
E3: "УТВЕРЖДАЮ"
D5: ___________________________
D7: ___________________________
D9: " ___ " ___________ 20 ___ г.
B12: =CONCATENATE("Ведомость объемов работ ", IF(Source!AN15<>"", Source!AN15," ")) -> Ведомость объемов работ
B13: =CONCATENATE(Source!F12, " ", Source!G12) -> 09-01-03 09-01-03 Размещение и содержание строительного мусора
A16: № п/п | B16: № в ЛСР | C16: Наименование работ и затрат | D16: Единица измерения | E16: Количество | F16: Ссылка на чертежи, спецификации | G16: Формула расчета, расчет объемов работ и расхода материалов | H16: Примечание
A17: 1 | B17: 2 | C17: 3 | D17: 4 | E17: 5 | F17: 6 | G17: 7 | H17: 8
A18: =CONCATENATE("Локальная смета: ", Source!G20) -> Локальная смета: Размещение и содержание строительного мусора
A19: =CONCATENATE("Раздел: ", Source!G24) -> Раздел: Размещение и содержание строительного мусора
A20: 1 | B20: =Source!E28 -> 1 | C20: =Source!G28 -> Отходы (мусор) от строительных и ремонтных работ малоопасные | D20: 1 Т | E20: =Source!I28 -> 74.973 | F20: =Source!U24 | G20: =Source!I28 -> 74.973
A21: 2 | B21: =Source!E30 -> 2 | C21: =Source!G30 -> Отходы затвердевшего строительного раствора в кусковой форме, малоопасные | D21: 1 Т | E21: =Source!I30 -> 1545.61 | F21: =Source!U24 | G21: =Source!I30 -> 1545.61
A22: 3 | B22: =Source!E32 -> 3 | C22: =Source!G32 -> Отходы штукатурки затвердевшей малоопасные | D22: 1 Т | E22: =Source!I32 -> 195.77 | F22: =Source!U24 | G22: =Source!I32 -> 195.77
A23: 4 | B23: =Source!E34 -> 4 | C23: =Source!G34 -> Отходы прочих теплоизоляционных материалов на основе минерального волокна незагрязненные, практически неопасные | D23: 1 Т | E23: =Source!I34 -> 4.248 | F23: =Source!U24 | G23: =Source!I34 -> 4.248
A24: 5 | B24: =Source!E36 -> 5 | C24: =Source!G36 -> Обрезь и лом гипсокартонных листов малоопасные | D24: 1 Т | E24: =Source!I36 -> 0.035 | F24: =Source!U24 | G24: =Source!I36 -> 0.035
A25: 6 | B25: =Source!E38 -> 6 | C25: =Source!G38 -> Отходы линолеума незагрязненные малоопасные | D25: 1 Т | E25: =Source!I38 -> 3.487 | F25: =Source!U24 | G25: =Source!I38 -> 3.487
A26: 7 | B26: =Source!E40 -> 7 | C26: =Source!G40 -> Отходы фанеры и изделий из нее незагрязненные | D26: 1 Т | E26: =Source!I40 -> 0.027 | F26: =Source!U24 | G26: =Source!I40 -> 0.027
A27: 8 | B27: =Source!E42 -> 8 | C27: =Source!G42 -> Отходы (мусор) от строительных и ремонтных работ малоопасные / светильники со светодиодными элементами в сборе | D27: 1 Т | E27: =Source!I42 -> 0.653 | F27: =Source!U24 | G27: =Source!I42 -> 0.653
A28: 9 | B28: =Source!E44 -> 9 | C28: =Source!G44 -> Смесь незагрязненных строительных материалов на основе полимеров, содержащая поливинилхлорид малоопасная | D28: 1 Т | E28: =Source!I44 -> 3.873 | F28: =Source!U24 | G28: =Source!I44 -> 3.873
A29: 10 | B29: =Source!E46 -> 10 | C29: =Source!G46 -> Лом бетонных изделий, отходы бетона в кусковой форме, практически неопасные | D29: 1 Т | E29: =Source!I46 -> 666.679 | F29: =Source!U24 | G29: =Source!I46 -> 666.679
A30: 11 | B30: =Source!E48 -> 11 | C30: =Source!G48 -> Лом черепицы, керамики незагрязненный практически неопасный | D30: 1 Т | E30: =Source!I48 -> 146.251 | F30: =Source!U24 | G30: =Source!I48 -> 146.251
A31: 12 | B31: =Source!E50 -> 12 | C31: =Source!G50 -> Лом строительного кирпича незагрязненный практически неопасный | D31: 1 Т | E31: =Source!I50 -> 0.309 | F31: =Source!U24 | G31: =Source!I50 -> 0.309
A32: 13 | B32: =Source!E52 -> 13 | C32: =Source!G52 -> Лом кирпичной кладки от сноса и разборки зданий практически неопасный | D32: 1 Т | E32: =Source!I52 -> 206.091 | F32: =Source!U24 | G32: =Source!I52 -> 206.091
A33: 14 | B33: =Source!E54 -> 14 | C33: =Source!G54 -> Лом бортовых камней, брусчатки, булыжных камней и прочие отходы изделий из природного камня, практически неопасный | D33: 1 Т | E33: =Source!I54 -> 4.628 | F33: =Source!U24 | G33: =Source!I54 -> 4.628
A34: 15 | B34: =Source!E56 -> 15 | C34: =Source!G56 -> Отходы изолированных проводов и кабелей | D34: 1 Т | E34: =Source!I56 -> 3.611 | F34: =Source!U24 | G34: =Source!I56 -> 3.611
A35: 16 | B35: =Source!E58 -> 16 | C35: =Source!G58 -> Лом и отходы изделий из полипропилена незагрязненные (кроме тары) | D35: 1 Т | E35: =Source!I58 -> 1.685 | F35: =Source!U24 | G35: =Source!I58 -> 1.685
A36: 17 | B36: =Source!E60 -> 17 | C36: =Source!G60 -> Прочая продукция из натуральной древесины, утратившая потребительские свойства, незагрязненная | D36: 1 Т | E36: =Source!I60 -> 2.6 | F36: =Source!U24 | G36: =Source!I60 -> 2.6
A37: 18 | B37: =Source!E62 -> 18 | C37: =Source!G62 -> Керамзит, утративший потребительские свойства, незагрязненный, практически неопасный | D37: 1 Т | E37: =Source!I62 -> 318.564 | F37: =Source!U24 | G37: =Source!I62 -> 318.564
C40: Главный инженер проекта _________________ | D40: =IF(Source!X12<>"", Source!X12," ")
C42: Составил _________________ | D42: =IF(Source!AB12<>"", Source!AB12," ") -> Лукьянова А.Л.

Sheet Source
A1: 0 | B1: Smeta.RU (495) 974-1589 | D1: _PS_ | F1: 0 | G1: 0 | H1: 0 | I1: Smeta.RU | K1: 1 | L1: 74562 | M1: 10 | N1: 11 | O1: 14 | P1: 0 | Q1: 0
A4: 1 | B4: 1 | C4: -1 | G4: Капитальный ремонт здания Государственного бюджетного общеобразовательного учреждения города Москвы «Школа № 236» по адресу: г. Москва, ул. Клязьминская, д. 7, к. 4. I этап | EC4: 0
A12: 1 | B12: 165 | C12: 0 | D12: =ROW(A125) -> 125 | E12: 0 | F12: 09-01-03 | G12: 09-01-03 Размещение и содержание строительного мусора | I12: 0 | J12: 0224-00272-01-0-ООС2 | K12: 0 | L12: 0 | M12: 4098 | O12: 0 | P12: 0 | Q12: 0 | R12: 0 | S12: 0 | T12: 1 | V12: 0 | AB12: Лукьянова А.Л. | BB12: 0 | BH12: Сметные нормы списания | BI12: Коды ОКП для ТСН-2001 МГЭ Дополнение 79 | BJ12: 1 | BK12: 1 | BL12: 0 | BM12: 0 | BN12: 1 | BO12: 0 | BP12: 6 | BQ12: 2 | BR12: 1 | BS12: 1 | BT12: 0 | BU12: 0 | BV12: 0 | BW12: 0 | BX12: 0 | BY12: ТСН-2001 (МГЭ) Доп 79 - Ремонт | BZ12: Типовой расчет для ТСН-2001 МГЭ, Дополнение 79, ремонт | CA12: Территориальные сметные нормативы для Москвы ТСН-2001 (МГЭ), дополнение 79 | CB12: Территориальные сметные нормативы для Москвы ТСН-2001 (МГЭ), дополнение 79 | CC12: Территориальные сметные нормативы для Москвы ТСН-2001 (МГЭ), дополнение 79 | CD12: Территориальные сметные нормативы для Москвы ТСН-2001 (МГЭ), дополнение 79 | CE12: Поправки для ТСН-2001 от 03.10.2025 г. доп.79 | CF12: 0 | CG12: 0 | CH12: 8200 | CK12: 79 | CQ12: Территориальные сметные нормативы для Москвы (ТСН-2001) | CR12: ТЕР | CS12: 41660 | CT12: 1 | CU12: 79 | CY12: 0 | EC12: 0
A15: 15 | B15: 1
A18: 52 | B18: =B125 -> 165 | C18: =C125 -> 1 | D18: =D125 -> 12 | E18: =E125 -> 0 | F18: =F125 -> 09-01-03 | G18: =G125 -> 09-01-03 Размещение и содержание строительного мусора | O18: =O125 -> 96538.04 | P18: =P125 -> 0 | Q18: =Q125 -> 96538.04 | R18: =R125 -> 0 | S18: =S125 -> 0 | T18: =T125 -> 0 | U18: =U125 -> 0 | V18: =V125 -> 0 | ... GX18: =GX125 -> 0
A20: 3 | B20: 1 | D20: =ROW(A95) -> 95 | G20: Размещение и содержание строительного мусора | I20: 0 | J20: 0224-00272-01-0-ООС2 | K20: -1 | L20: 09-01-03 | S20: 0 | T20: 0 | V20: 0 | AB20: Лукьянова А.Л. | BX20: 0 | CF20: 0 | CG20: 0
A22: 52 | B22: =B95 -> 1 | C22: =C95 -> 3 | D22: =D95 -> 20 | E22: =E95 -> 0 | F22: =F95 | G22: =G95 -> Размещение и содержание строительного мусора | O22: =O95 -> 96538.04 | P22: =P95 -> 0 | Q22: =Q95 -> 96538.04 | R22: =R95 -> 0 | S22: =S95 -> 0 | T22: =T95 -> 0 | U22: =U95 -> 0 | V22: =V95 -> 0 | ... GX22: =GX95 -> 0
A24: 4 | B24: 1 | D24: =ROW(A65) -> 65 | G24: Размещение и содержание строительного мусора | I24: 0 | K24: -1 | S24: 0 | T24: 0 | V24: 0 | BX24: 0 | CJ24: 0
A26: 52 | B26: =B65 -> 1 | C26: =C65 -> 4 | D26: =D65 -> 24 | E26: =E65 -> 0 | F26: =F65 | G26: =G65 -> Размещение и содержание строительного мусора | O26: =O65 -> 96538.04 | P26: =P65 -> 0 | Q26: =Q65 -> 96538.04 | R26: =R65 -> 0 | S26: =S65 -> 0 | T26: =T65 -> 0 | U26: =U65 -> 0 | V26: =V65 -> 0 | ... GX26: =GX65 -> 0
A28: 17 | B28: 1 | C28: =ROW(SmtRes!A1) -> 1 | D28: =ROW(EtalonRes!A1) -> 1 | E28: 1 | F28: 15.1-1500-01 | G28: Отходы (мусор) от строительных и ремонтных работ малоопасные | H28: 1 Т | I28: 74.973 | J28: 0 | K28: 74.973 | O28: =ROUND(CP28,2) -> 2374.39 | P28: =ROUND((ROUND((AC28*AW28*I28),2)*BC28),2) -> 0 | Q28: =(ROUND((ROUND(((ET28)*AV28*I28),2)*BB28),2)+ROUND((ROUND(((AE28-(EU28))*AV28*I28),2)*BS28),2)) -> 2374.39 | R28: =ROUND((ROUND((AE28*AV28*I28),2)*BS28),2) -> 0 | S28: =ROUND((ROUND((AF28*AV28*I28),2)*BA28),2) -> 0 | T28: =ROUND(CU28*I28,2) -> 0 | U28: =CV28*I28 -> 0 | V28: =CW28*I28 -> 0 | W28: =ROUND(CX28*I28,2) -> 0 | X28: =ROUND(CY28,2) -> 0 | Y28: =ROUND(CZ28,2) -> 0 | AA28: 56526439 | AB28: =ROUND((AC28+AD28+AF28),6) -> 31.67 | AC28: =ROUND((ES28),6) -> 0 | AD28: =ROUND((((ET28)-(EU28))+AE28),6) -> 31.67 | AE28: =ROUND((EU28),6) -> 0 | AF28: =ROUND((EV28),6) -> 0 | AG28: =ROUND((AP28),6) -> 0 | AH28: =(EW28) -> 0 | AI28: =(EX28) -> 0 | AJ28: =(AS28) -> 0 | AK28: 31.67 | AL28: 0 | AM28: 31.67 | AN28: 0 | AO28: 0 | AP28: 0 | AQ28: 0 | AR28: 0 | AS28: 0 | AT28: 94 | AU28: 61 | AV28: 1 | AW28: 1 | AZ28: 1 | BA28: 1 | BB28: 1 | BC28: 1 | BH28: 0 | BI28: 4 | BJ28: ТСН-2001.15 Доп. 56, Сб. 1, т. 1500, поз. 1 | BM28: 188 | BN28: 0 | BO28: 15.1-1500-01 | BP28: 1 | BQ28: 150 | BR28: 0 | BS28: 1 | BT28: 1 | BU28: 1 | BV28: 1 | BW28: 1 | BX28: 1 | BZ28: 94 | CA28: 61 | CE28: 30 | CF28: 0 | CG28: 0 | CM28: 0 | CO28: 0 | CP28: =(P28+Q28+S28) -> 2374.39 | CQ28: =ROUND((ROUND((AC28*AW28*1),2)*BC28),2) -> 0 | CR28: =(ROUND((ROUND(((ET28)*AV28*1),2)*BB28),2)+ROUND((ROUND(((AE28-(EU28))*AV28*1),2)*BS28),2)) -> 31.67 | CS28: =ROUND((ROUND((AE28*AV28*1),2)*BS28),2) -> 0 | CT28: =ROUND((ROUND((AF28*AV28*1),2)*BA28),2) -> 0 | CU28: =AG28 -> 0 | CV28: =(AH28*AV28) -> 0 | CW28: =AI28 -> 0 | CX28: =AJ28 -> 0 | CY28: =(((S28+R28)*AT28)/100) -> 0 | CZ28: =(((S28+R28)*AU28)/100) -> 0 | DN28: 0 | DO28: 0 | DP28: 1 | DQ28: 1 | DU28: 1013 | DV28: 1 Т | DW28: 1 Т | DX28: 1 | EE28: 55586412 | EF28: 150 | EG28: Транспортные затраты | EH28: 0 | EJ28: 4 | EK28: 188 | EL28: ТСН-2001.15. Перевозка строительных грузов автомобильным транспортом | EM28: ТСН-2001.15. | EQ28: 0 | ER28: 31.67 | ES28: 0 | ET28: 31.67 | EU28: 0 | EV28: 0 | EW28: 0 | EX28: 0 | EY28: 0 | FQ28: 0 | FR28: 0 | FS28: 0 | FX28: 94 | FY28: 61 | GD28: 1 | GF28: 247349083 | GG28: 2 | GH28: 1 | GI28: 2 | GJ28: 0 | GK28: 0 | GL28: =ROUND(IF(AND(BH28=3,BI28=3,FS28<>0),P28,0),2) -> 0 | GM28: =ROUND(O28+X28+Y28,2)+GX28 -> 2374.39 | GN28: =IF(OR(BI28=0,BI28=1),GM28-GX28,0) -> 0 | GO28: =IF(BI28=2,GM28-GX28,0) -> 0 | GP28: =IF(BI28=4,GM28-GX28,0) -> 2374.39 | GR28: 0 | GS28: 3 | GT28: 0 | GV28: =ROUND((GT28),6) -> 0 | GW28: 1 | GX28: =ROUND(HC28*I28,2) -> 0 | HA28: 0 | HB28: 0 | HC28: =GV28*GW28 -> 0 | HS28: 0 | IK28: 0
A29: 17 | B29: 1 | C29: =ROW(SmtRes!A2) -> 2 | D29: =ROW(EtalonRes!A2) -> 2 | E29: 1 | F29: 15.1-1500-01 | G29: Отходы (мусор) от строительных и ремонтных работ малоопасные | H29: 1 Т | I29: 74.973 | J29: 0 | K29: 74.973 | O29: =ROUND(CP29,2) -> 102977.29 | P29: =ROUND((ROUND((AC29*AW29*I29),2)*BC29),2) -> 0 | Q29: =(ROUND((ROUND(((ET29)*AV29*I29),2)*BB29),2)+ROUND((ROUND(((AE29-(EU29))*AV29*I29),2)*BS29),2)) -> 102977.29 | R29: =ROUND((ROUND((AE29*AV29*I29),2)*BS29),2) -> 0 | S29: =ROUND((ROUND((AF29*AV29*I29),2)*BA29),2) -> 0 | T29: =ROUND(CU29*I29,2) -> 0 | U29: =CV29*I29 -> 0 | V29: =CW29*I29 -> 0 | W29: =ROUND(CX29*I29,2) -> 0 | X29: =ROUND(CY29,2) -> 0 | Y29: =ROUND(CZ29,2) -> 0 | AA29: 56526441 | AB29: =ROUND((AC29+AD29+AF29),6) -> 31.67 | AC29: =ROUND((ES29),6) -> 0 | AD29: =ROUND((((ET29)-(EU29))+AE29),6) -> 31.67 | AE29: =ROUND((EU29),6) -> 0 | AF29: =ROUND((EV29),6) -> 0 | AG29: =ROUND((AP29),6) -> 0 | AH29: =(EW29) -> 0 | AI29: =(EX29) -> 0 | AJ29: =(AS29) -> 0 | AK29: 31.67 | AL29: 0 | AM29: 31.67 | AN29: 0 | AO29: 0 | AP29: 0 | AQ29: 0 | AR29: 0 | AS29: 0 | AT29: 94 | AU29: 61 | AV29: 1 | AW29: 1 | AZ29: 1 | BA29: 1 | BB29: 43.37 | BC29: 1 | BH29: 0 | BI29: 4 | BJ29: ТСН-2001.15 Доп. 56, Сб. 1, т. 1500, поз. 1 | BM29: 188 | BN29: 0 | BO29: 15.1-1500-01 | BP29: 1 | BQ29: 150 | BR29: 0 | BS29: 1 | BT29: 1 | BU29: 1 | BV29: 1 | BW29: 1 | BX29: 1 | BZ29: 94 | CA29: 61 | CE29: 30 | CF29: 0 | CG29: 0 | CM29: 0 | CO29: 0 | CP29: =(P29+Q29+S29) -> 102977.29 | CQ29: =ROUND((ROUND((AC29*AW29*1),2)*BC29),2) -> 0 | CR29: =(ROUND((ROUND(((ET29)*AV29*1),2)*BB29),2)+ROUND((ROUND(((AE29-(EU29))*AV29*1),2)*BS29),2)) -> 1373.53 | CS29: =ROUND((ROUND((AE29*AV29*1),2)*BS29),2) -> 0 | CT29: =ROUND((ROUND((AF29*AV29*1),2)*BA29),2) -> 0 | CU29: =AG29 -> 0 | CV29: =(AH29*AV29) -> 0 | CW29: =AI29 -> 0 | CX29: =AJ29 -> 0 | CY29: =(((S29+R29)*AT29)/100) -> 0 | CZ29: =(((S29+R29)*AU29)/100) -> 0 | DN29: 0 | DO29: 0 | DP29: 1 | DQ29: 1 | DU29: 1013 | DV29: 1 Т | DW29: 1 Т | DX29: 1 | EE29: 55586412 | EF29: 150 | EG29: Транспортные затраты | EH29: 0 | EJ29: 4 | EK29: 188 | EL29: ТСН-2001.15. Перевозка строительных грузов автомобильным транспортом | EM29: ТСН-2001.15. | EQ29: 0 | ER29: 31.67 | ES29: 0 | ET29: 31.67 | EU29: 0 | EV29: 0 | EW29: 0 | EX29: 0 | EY29: 0 | FQ29: 0 | FR29: 0 | FS29: 0 | FX29: 94 | FY29: 61 | GD29: 1 | GF29: 247349083 | GG29: 2 | GH29: 1 | GI29: 2 | GJ29: 0 | GK29: 0 | GL29: =ROUND(IF(AND(BH29=3,BI29=3,FS29<>0),P29,0),2) -> 0 | GM29: =ROUND(O29+X29+Y29,2)+GX29 -> 102977.29 | GN29: =IF(OR(BI29=0,BI29=1),GM29-GX29,0) -> 0 | GO29: =IF(BI29=2,GM29-GX29,0) -> 0 | GP29: =IF(BI29=4,GM29-GX29,0) -> 102977.29 | GR29: 0 | GS29: 3 | GT29: 0 | GV29: =ROUND((GT29),6) -> 0 | GW29: 1 | GX29: =ROUND(HC29*I29,2) -> 0 | HA29: 0 | HB29: 0 | HC29: =GV29*GW29 -> 0 | HS29: 0 | IK29: 0
A30: 17 | B30: 1 | C30: =ROW(SmtRes!A3) -> 3 | D30: =ROW(EtalonRes!A3) -> 3 | E30: 2 | F30: 15.1-1201-10 | G30: Отходы затвердевшего строительного раствора в кусковой форме, малоопасные | H30: 1 Т | I30: 1545.61 | J30: 0 | K30: 1545.61 | O30: =ROUND(CP30,2) -> 48114.84 | P30: =ROUND((ROUND((AC30*AW30*I30),2)*BC30),2) -> 0 | Q30: =(ROUND((ROUND(((ET30)*AV30*I30),2)*BB30),2)+ROUND((ROUND(((AE30-(EU30))*AV30*I30),2)*BS30),2)) -> 48114.84 | R30: =ROUND((ROUND((AE30*AV30*I30),2)*BS30),2) -> 0 | S30: =ROUND((ROUND((AF30*AV30*I30),2)*BA30),2) -> 0 | T30: =ROUND(CU30*I30,2) -> 0 | U30: =CV30*I30 -> 0 | V30: =CW30*I30 -> 0 | W30: =ROUND(CX30*I30,2) -> 0 | X30: =ROUND(CY30,2) -> 0 | Y30: =ROUND(CZ30,2) -> 0 | AA30: 56526439 | AB30: =ROUND((AC30+AD30+AF30),6) -> 31.13 | AC30: =ROUND((ES30),6) -> 0 | AD30: =ROUND((((ET30)-(EU30))+AE30),6) -> 31.13 | AE30: =ROUND((EU30),6) -> 0 | AF30: =ROUND((EV30),6) -> 0 | AG30: =ROUND((AP30),6) -> 0 | AH30: =(EW30) -> 0 | AI30: =(EX30) -> 0 | AJ30: =(AS30) -> 0 | AK30: 31.13 | AL30: 0 | AM30: 31.13 | AN30: 0 | AO30: 0 | AP30: 0 | AQ30: 0 | AR30: 0 | AS30: 0 | AT30: 94 | AU30: 61 | AV30: 1 | AW30: 1 | AZ30: 1 | BA30: 1 | BB30: 1 | BC30: 1 | BH30: 0 | BI30: 4 | BJ30: ТСН-2001.15 Доп. 56, Сб. 1, т. 1201, поз. 10 | BM30: 188 | BN30: 0 | BO30: 15.1-1201-10 | BP30: 1 | BQ30: 150 | BR30: 0 | BS30: 1 | BT30: 1 | BU30: 1 | BV30: 1 | BW30: 1 | BX30: 1 | BZ30: 94 | CA30: 61 | CE30: 30 | CF30: 0 | CG30: 0 | CM30: 0 | CO30: 0 | CP30: =(P30+Q30+S30) -> 48114.84 | CQ30: =ROUND((ROUND((AC30*AW30*1),2)*BC30),2) -> 0 | CR30: =(ROUND((ROUND(((ET30)*AV30*1),2)*BB30),2)+ROUND((ROUND(((AE30-(EU30))*AV30*1),2)*BS30),2)) -> 31.13 | CS30: =ROUND((ROUND((AE30*AV30*1),2)*BS30),2) -> 0 | CT30: =ROUND((ROUND((AF30*AV30*1),2)*BA30),2) -> 0 | CU30: =AG30 -> 0 | CV30: =(AH30*AV30) -> 0 | CW30: =AI30 -> 0 | CX30: =AJ30 -> 0 | CY30: =(((S30+R30)*AT30)/100) -> 0 | CZ30: =(((S30+R30)*AU30)/100) -> 0 | DN30: 0 | DO30: 0 | DP30: 1 | DQ30: 1 | DU30: 1013 | DV30: 1 Т | DW30: 1 Т | DX30: 1 | EE30: 55586412 | EF30: 150 | EG30: Транспортные затраты | EH30: 0 | EJ30: 4 | EK30: 188 | EL30: ТСН-2001.15. Перевозка строительных грузов автомобильным транспортом | EM30: ТСН-2001.15. | EQ30: 0 | ER30: 31.13 | ES30: 0 | ET30: 31.13 | EU30: 0 | EV30: 0 | EW30: 0 | EX30: 0 | EY30: 0 | FQ30: 0 | FR30: 0 | FS30: 0 | FX30: 94 | FY30: 61 | GD30: 1 | GF30: 1826450107 | GG30: 2 | GH30: 1 | GI30: 2 | GJ30: 0 | GK30: 0 | GL30: =ROUND(IF(AND(BH30=3,BI30=3,FS30<>0),P30,0),2) -> 0 | GM30: =ROUND(O30+X30+Y30,2)+GX30 -> 48114.84 | GN30: =IF(OR(BI30=0,BI30=1),GM30-GX30,0) -> 0 | GO30: =IF(BI30=2,GM30-GX30,0) -> 0 | GP30: =IF(BI30=4,GM30-GX30,0) -> 48114.84 | GR30: 0 | GS30: 3 | GT30: 0 | GV30: =ROUND((GT30),6) -> 0 | GW30: 1 | GX30: =ROUND(HC30*I30,2) -> 0 | HA30: 0 | HB30: 0 | HC30: =GV30*GW30 -> 0 | HS30: 0 | IK30: 0
A31: 17 | B31: 1 | C31: =ROW(SmtRes!A4) -> 4 | D31: =ROW(EtalonRes!A4) -> 4 | E31: 2 | F31: 15.1-1201-10 | G31: Отходы затвердевшего строительного раствора в кусковой форме, малоопасные | H31: 1 Т | I31: 1545.61 | J31: 0 | K31: 1545.61 | O31: =ROUND(CP31,2) -> 448911.46 | P31: =ROUND((ROUND((AC31*AW31*I31),2)*BC31),2) -> 0 | Q31: =(ROUND((ROUND(((ET31)*AV31*I31),2)*BB31),2)+ROUND((ROUND(((AE31-(EU31))*AV31*I31),2)*BS31),2)) -> 448911.46 | R31: =ROUND((ROUND((AE31*AV31*I31),2)*BS31),2) -> 0 | S31: =ROUND((ROUND((AF31*AV31*I31),2)*BA31),2) -> 0 | T31: =ROUND(CU31*I31,2) -> 0 | U31: =CV31*I31 -> 0 | V31: =CW31*I31 -> 0 | W31: =ROUND(CX31*I31,2) -> 0 | X31: =ROUND(CY31,2) -> 0 | Y31: =ROUND(CZ31,2) -> 0 | AA31: 56526441 | AB31: =ROUND((AC31+AD31+AF31),6) -> 31.13 | AC31: =ROUND((ES31),6) -> 0 | AD31: =ROUND((((ET31)-(EU31))+AE31),6) -> 31.13 | AE31: =ROUND((EU31),6) -> 0 | AF31: =ROUND((EV31),6) -> 0 | AG31: =ROUND((AP31),6) -> 0 | AH31: =(EW31) -> 0 | AI31: =(EX31) -> 0 | AJ31: =(AS31) -> 0 | AK31: 31.13 | AL31: 0 | AM31: 31.13 | AN31: 0 | AO31: 0 | AP31: 0 | AQ31: 0 | AR31: 0 | AS31: 0 | AT31: 94 | AU31: 61 | AV31: 1 | AW31: 1 | AZ31: 1 | BA31: 1 | BB31: 9.33 | BC31: 1 | BH31: 0 | BI31: 4 | BJ31: ТСН-2001.15 Доп. 56, Сб. 1, т. 1201, поз. 10 | BM31: 188 | BN31: 0 | BO31: 15.1-1201-10 | BP31: 1 | BQ31: 150 | BR31: 0 | BS31: 1 | BT31: 1 | BU31: 1 | BV31: 1 | BW31: 1 | BX31: 1 | BZ31: 94 | CA31: 61 | CE31: 30 | CF31: 0 | CG31: 0 | CM31: 0 | CO31: 0 | CP31: =(P31+Q31+S31) -> 448911.46 | CQ31: =ROUND((ROUND((AC31*AW31*1),2)*BC31),2) -> 0 | CR31: =(ROUND((ROUND(((ET31)*AV31*1),2)*BB31),2)+ROUND((ROUND(((AE31-(EU31))*AV31*1),2)*BS31),2)) -> 290.44 | CS31: =ROUND((ROUND((AE31*AV31*1),2)*BS31),2) -> 0 | CT31: =ROUND((ROUND((AF31*AV31*1),2)*BA31),2) -> 0 | CU31: =AG31 -> 0 | CV31: =(AH31*AV31) -> 0 | CW31: =AI31 -> 0 | CX31: =AJ31 -> 0 | CY31: =(((S31+R31)*AT31)/100) -> 0 | CZ31: =(((S31+R31)*AU31)/100) -> 0 | DN31: 0 | DO31: 0 | DP31: 1 | DQ31: 1 | DU31: 1013 | DV31: 1 Т | DW31: 1 Т | DX31: 1 | EE31: 55586412 | EF31: 150 | EG31: Транспортные затраты | EH31: 0 | EJ31: 4 | EK31: 188 | EL31: ТСН-2001.15. Перевозка строительных грузов автомобильным транспортом | EM31: ТСН-2001.15. | EQ31: 0 | ER31: 31.13 | ES31: 0 | ET31: 31.13 | EU31: 0 | EV31: 0 | EW31: 0 | EX31: 0 | EY31: 0 | FQ31: 0 | FR31: 0 | FS31: 0 | FX31: 94 | FY31: 61 | GD31: 1 | GF31: 1826450107 | GG31: 2 | GH31: 1 | GI31: 2 | GJ31: 0 | GK31: 0 | GL31: =ROUND(IF(AND(BH31=3,BI31=3,FS31<>0),P31,0),2) -> 0 | GM31: =ROUND(O31+X31+Y31,2)+GX31 -> 448911.46 | GN31: =IF(OR(BI31=0,BI31=1),GM31-GX31,0) -> 0 | GO31: =IF(BI31=2,GM31-GX31,0) -> 0 | GP31: =IF(BI31=4,GM31-GX31,0) -> 448911.46 | GR31: 0 | GS31: 3 | GT31: 0 | GV31: =ROUND((GT31),6) -> 0 | GW31: 1 | GX31: =ROUND(HC31*I31,2) -> 0 | HA31: 0 | HB31: 0 | HC31: =GV31*GW31 -> 0 | HS31: 0 | IK31: 0
A32: 17 | B32: 1 | C32: =ROW(SmtRes!A5) -> 5 | D32: =ROW(EtalonRes!A5) -> 5 | E32: 3 | F32: 15.1-1203-06 | G32: Отходы штукатурки затвердевшей малоопасные | H32: 1 Т | I32: 195.77 | J32: 0 | K32: 195.77 | O32: =ROUND(CP32,2) -> 7163.22 | P32: =ROUND((ROUND((AC32*AW32*I32),2)*BC32),2) -> 0 | Q32: =(ROUND((ROUND(((ET32)*AV32*I32),2)*BB32),2)+ROUND((ROUND(((AE32-(EU32))*AV32*I32),2)*BS32),2)) -> 7163.22 | R32: =ROUND((ROUND((AE32*AV32*I32),2)*BS32),2) -> 0 | S32: =ROUND((ROUND((AF32*AV32*I32),2)*BA32),2) -> 0 | T32: =ROUND(CU32*I32,2) -> 0 | U32: =CV32*I32 -> 0 | V32: =CW32*I32 -> 0 | W32: =ROUND(CX32*I32,2) -> 0 | X32: =ROUND(CY32,2) -> 0 | Y32: =ROUND(CZ32,2) -> 0 | AA32: 56526439 | AB32: =ROUND((AC32+AD32+AF32),6) -> 36.59 | AC32: =ROUND((ES32),6) -> 0 | AD32: =ROUND((((ET32)-(EU32))+AE32),6) -> 36.59 | AE32: =ROUND((EU32),6) -> 0 | AF32: =ROUND((EV32),6) -> 0 | AG32: =ROUND((AP32),6) -> 0 | AH32: =(EW32) -> 0 | AI32: =(EX32) -> 0 | AJ32: =(AS32) -> 0 | AK32: 36.59 | AL32: 0 | AM32: 36.59 | AN32: 0 | AO32: 0 | AP32: 0 | AQ32: 0 | AR32: 0 | AS32: 0 | AT32: 94 | AU32: 61 | AV32: 1 | AW32: 1 | AZ32: 1 | BA32: 1 | BB32: 1 | BC32: 1 | BH32: 0 | BI32: 4 | BJ32: ТСН-2001.15 Доп. 56, Сб. 1, т. 1203, поз. 6 | BM32: 188 | BN32: 0 | BO32: 15.1-1203-06 | BP32: 1 | BQ32: 150 | BR32: 0 | BS32: 1 | BT32: 1 | BU32: 1 | BV32: 1 | BW32: 1 | BX32: 1 | BZ32: 94 | CA32: 61 | CE32: 30 | CF32: 0 | CG32: 0 | CM32: 0 | CO32: 0 | CP32: =(P32+Q32+S32) -> 7163.22 | CQ32: =ROUND((ROUND((AC32*AW32*1),2)*BC32),2) -> 0 | CR32: =(ROUND((ROUND(((ET32)*AV32*1),2)*BB32),2)+ROUND((ROUND(((AE32-(EU32))*AV32*1),2)*BS32),2)) -> 36.59 | CS32: =ROUND((ROUND((AE32*AV32*1),2)*BS32),2) -> 0 | CT32: =ROUND((ROUND((AF32*AV32*1),2)*BA32),2) -> 0 | CU32: =AG32 -> 0 | CV32: =(AH32*AV32) -> 0 | CW32: =AI32 -> 0 | CX32: =AJ32 -> 0 | CY32: =(((S32+R32)*AT32)/100) -> 0 | CZ32: =(((S32+R32)*AU32)/100) -> 0 | DN32: 0 | DO32: 0 | DP32: 1 | DQ32: 1 | DU32: 1013 | DV32: 1 Т | DW32: 1 Т | DX32: 1 | EE32: 55586412 | EF32: 150 | EG32: Транспортные затраты | EH32: 0 | EJ32: 4 | EK32: 188 | EL32: ТСН-2001.15. Перевозка строительных грузов автомобильным транспортом | EM32: ТСН-2001.15. | EQ32: 0 | ER32: 36.59 | ES32: 0 | ET32: 36.59 | EU32: 0 | EV32: 0 | EW32: 0 | EX32: 0 | EY32: 0 | FQ32: 0 | FR32: 0 | FS32: 0 | FX32: 94 | FY32: 61 | GD32: 1 | GF32: -1232021766 | GG32: 2 | GH32: 1 | GI32: 2 | GJ32: 0 | GK32: 0 | GL32: =ROUND(IF(AND(BH32=3,BI32=3,FS32<>0),P32,0),2) -> 0 | GM32: =ROUND(O32+X32+Y32,2)+GX32 -> 7163.22 | GN32: =IF(OR(BI32=0,BI32=1),GM32-GX32,0) -> 0 | GO32: =IF(BI32=2,GM32-GX32,0) -> 0 | GP32: =IF(BI32=4,GM32-GX32,0) -> 7163.22 | GR32: 0 | GS32: 3 | GT32: 0 | GV32: =ROUND((GT32),6) -> 0 | GW32: 1 | GX32: =ROUND(HC32*I32,2) -> 0 | HA32: 0 | HB32: 0 | HC32: =GV32*GW32 -> 0 | HS32: 0 | IK32: 0
A33: 17 | B33: 1 | C33: =ROW(SmtRes!A6) -> 6 | D33: =ROW(EtalonRes!A6) -> 6 | E33: 3 | F33: 15.1-1203-06 | G33: Отходы штукатурки затвердевшей малоопасные | H33: 1 Т | I33: 195.77 | J33: 0 | K33: 195.77 | O33: =ROUND(CP33,2) -> 68552.02 | P33: =ROUND((ROUND((AC33*AW33*I33),2)*BC33),2) -> 0 | Q33: =(ROUND((ROUND(((ET33)*AV33*I33),2)*BB33),2)+ROUND((ROUND(((AE33-(EU33))*AV33*I33),2)*BS33),2)) -> 68552.02 | R33: =ROUND((ROUND((AE33*AV33*I33),2)*BS33),2) -> 0 | S33: =ROUND((ROUND((AF33*AV33*I33),2)*BA33),2) -> 0 | T33: =ROUND(CU33*I33,2) -> 0 | U33: =CV33*I33 -> 0 | V33: =CW33*I33 -> 0 | W33: =ROUND(CX33*I33,2) -> 0 | X33: =ROUND(CY33,2) -> 0 | Y33: =ROUND(CZ33,2) -> 0 | AA33: 56526441 | AB33: =ROUND((AC33+AD33+AF33),6) -> 36.59 | AC33: =ROUND((ES33),6) -> 0 | AD33: =ROUND((((ET33)-(EU33))+AE33),6) -> 36.59 | AE33: =ROUND((EU33),6) -> 0 | AF33: =ROUND((EV33),6) -> 0 | AG33: =ROUND((AP33),6) -> 0 | AH33: =(EW33) -> 0 | AI33: =(EX33) -> 0 | AJ33: =(AS33) -> 0 | AK33: 36.59 | AL33: 0 | AM33: 36.59 | AN33: 0 | AO33: 0 | AP33: 0 | AQ33: 0 | AR33: 0 | AS33: 0 | AT33: 94 | AU33: 61 | AV33: 1 | AW33: 1 | AZ33: 1 | BA33: 1 | BB33: 9.57 | BC33: 1 | BH33: 0 | BI33: 4 | BJ33: ТСН-2001.15 Доп. 56, Сб. 1, т. 1203, поз. 6 | BM33: 188 | BN33: 0 | BO33: 15.1-1203-06 | BP33: 1 | BQ33: 150 | BR33: 0 | BS33: 1 | BT33: 1 | BU33: 1 | BV33: 1 | BW33: 1 | BX33: 1 | BZ33: 94 | CA33: 61 | CE33: 30 | CF33: 0 | CG33: 0 | CM33: 0 | CO33: 0 | CP33: =(P33+Q33+S33) -> 68552.02 | CQ33: =ROUND((ROUND((AC33*AW33*1),2)*BC33),2) -> 0 | CR33: =(ROUND((ROUND(((ET33)*AV33*1),2)*BB33),2)+ROUND((ROUND(((AE33-(EU33))*AV33*1),2)*BS33),2)) -> 350.17 | CS33: =ROUND((ROUND((AE33*AV33*1),2)*BS33),2) -> 0 | CT33: =ROUND((ROUND((AF33*AV33*1),2)*BA33),2) -> 0 | CU33: =AG33 -> 0 | CV33: =(AH33*AV33) -> 0 | CW33: =AI33 -> 0 | CX33: =AJ33 -> 0 | CY33: =(((S33+R33)*AT33)/100) -> 0 | CZ33: =(((S33+R33)*AU33)/100) -> 0 | DN33: 0 | DO33: 0 | DP33: 1 | DQ33: 1 | DU33: 1013 | DV33: 1 Т | DW33: 1 Т | DX33: 1 | EE33: 55586412 | EF33: 150 | EG33: Транспортные затраты | EH33: 0 | EJ33: 4 | EK33: 188 | EL33: ТСН-2001.15. Перевозка строительных грузов автомобильным транспортом | EM33: ТСН-2001.15. | EQ33: 0 | ER33: 36.59 | ES33: 0 | ET33: 36.59 | EU33: 0 | EV33: 0 | EW33: 0 | EX33: 0 | EY33: 0 | FQ33: 0 | FR33: 0 | FS33: 0 | FX33: 94 | FY33: 61 | GD33: 1 | GF33: -1232021766 | GG33: 2 | GH33: 1 | GI33: 2 | GJ33: 0 | GK33: 0 | GL33: =ROUND(IF(AND(BH33=3,BI33=3,FS33<>0),P33,0),2) -> 0 | GM33: =ROUND(O33+X33+Y33,2)+GX33 -> 68552.02 | GN33: =IF(OR(BI33=0,BI33=1),GM33-GX33,0) -> 0 | GO33: =IF(BI33=2,GM33-GX33,0) -> 0 | GP33: =IF(BI33=4,GM33-GX33,0) -> 68552.02 | GR33: 0 | GS33: 3 | GT33: 0 | GV33: =ROUND((GT33),6) -> 0 | GW33: 1 | GX33: =ROUND(HC33*I33,2) -> 0 | HA33: 0 | HB33: 0 | HC33: =GV33*GW33 -> 0 | HS33: 0 | IK33: 0
A34: 17 | B34: 1 | C34: =ROW(SmtRes!A7) -> 7 | D34: =ROW(EtalonRes!A7) -> 7 | E34: 4 | F34: 15.1-1505-04 | G34: Отходы прочих теплоизоляционных материалов на основе минерального волокна незагрязненные, практически неопасные | H34: 1 Т | I34: 4.248 | J34: 0 | K34: 4.248 | O34: =ROUND(CP34,2) -> 417.58 | P34: =ROUND((ROUND((AC34*AW34*I34),2)*BC34),2) -> 0 | Q34: =(ROUND((ROUND(((ET34)*AV34*I34),2)*BB34),2)+ROUND((ROUND(((AE34-(EU34))*AV34*I34),2)*BS34),2)) -> 417.58 | R34: =ROUND((ROUND((AE34*AV34*I34),2)*BS34),2) -> 0 | S34: =ROUND((ROUND((AF34*AV34*I34),2)*BA34),2) -> 0 | T34: =ROUND(CU34*I34,2) -> 0 | U34: =CV34*I34 -> 0 | V34: =CW34*I34 -> 0 | W34: =ROUND(CX34*I34,2) -> 0 | X34: =ROUND(CY34,2) -> 0 | Y34: =ROUND(CZ34,2) -> 0 | AA34: 56526439 | AB34: =ROUND((AC34+AD34+AF34),6) -> 98.3 | AC34: =ROUND((ES34),6) -> 0 | AD34: =ROUND((((ET34)-(EU34))+AE34),6) -> 98.3 | AE34: =ROUND((EU34),6) -> 0 | AF34: =ROUND((EV34),6) -> 0 | AG34: =ROUND((AP34),6) -> 0 | AH34: =(EW34) -> 0 | AI34: =(EX34) -> 0 | AJ34: =(AS34) -> 0 | AK34: 98.3 | AL34: 0 | AM34: 98.3 | AN34: 0 | AO34: 0 | AP34: 0 | AQ34: 0 | AR34: 0 | AS34: 0 | AT34: 94 | AU34: 61 | AV34: 1 | AW34: 1 | AZ34: 1 | BA34: 1 | BB34: 1 | BC34: 1 | BH34: 0 | BI34: 4 | BJ34: ТСН-2001.15 Доп. 56, Сб. 1, т. 1505, поз. 4 | BM34: 188 | BN34: 0 | BO34: 15.1-1505-04 | BP34: 1 | BQ34: 150 | BR34: 0 | BS34: 1 | BT34: 1 | BU34: 1 | BV34: 1 | BW34: 1 | BX34: 1 | BZ34: 94 | CA34: 61 | CE34: 30 | CF34: 0 | CG34: 0 | CM34: 0 | CO34: 0 | CP34: =(P34+Q34+S34) -> 417.58 | CQ34: =ROUND((ROUND((AC34*AW34*1),2)*BC34),2) -> 0 | CR34: =(ROUND((ROUND(((ET34)*AV34*1),2)*BB34),2)+ROUND((ROUND(((AE34-(EU34))*AV34*1),2)*BS34),2)) -> 98.3 | CS34: =ROUND((ROUND((AE34*AV34*1),2)*BS34),2) -> 0 | CT34: =ROUND((ROUND((AF34*AV34*1),2)*BA34),2) -> 0 | CU34: =AG34 -> 0 | CV34: =(AH34*AV34) -> 0 | CW34: =AI34 -> 0 | CX34: =AJ34 -> 0 | CY34: =(((S34+R34)*AT34)/100) -> 0 | CZ34: =(((S34+R34)*AU34)/100) -> 0 | DN34: 0 | DO34: 0 | DP34: 1 | DQ34: 1 | DU34: 1013 | DV34: 1 Т | DW34: 1 Т | DX34: 1 | EE34: 55586412 | EF34: 150 | EG34: Транспортные затраты | EH34: 0 | EJ34: 4 | EK34: 188 | EL34: ТСН-2001.15. Перевозка строительных грузов автомобильным транспортом | EM34: ТСН-2001.15. | EQ34: 0 | ER34: 98.3 | ES34: 0 | ET34: 98.3 | EU34: 0 | EV34: 0 | EW34: 0 | EX34: 0 | EY34: 0 | FQ34: 0 | FR34: 0 | FS34: 0 | FX34: 94 | FY34: 61 | GD34: 1 | GF34: 151177787 | GG34: 2 | GH34: 1 | GI34: 2 | GJ34: 0 | GK34: 0 | GL34: =ROUND(IF(AND(BH34=3,BI34=3,FS34<>0),P34,0),2) -> 0 | GM34: =ROUND(O34+X34+Y34,2)+GX34 -> 417.58 | GN34: =IF(OR(BI34=0,BI34=1),GM34-GX34,0) -> 0 | GO34: =IF(BI34=2,GM34-GX34,0) -> 0 | GP34: =IF(BI34=4,GM34-GX34,0) -> 417.58 | GR34: 0 | GS34: 3 | GT34: 0 | GV34: =ROUND((GT34),6) -> 0 | GW34: 1 | GX34: =ROUND(HC34*I34,2) -> 0 | HA34: 0 | HB34: 0 | HC34: =GV34*GW34 -> 0 | HS34: 0 | IK34: 0
A35: 17 | B35: 1 | C35: =ROW(SmtRes!A8) -> 8 | D35: =ROW(EtalonRes!A8) -> 8 | E35: 4 | F35: 15.1-1505-04 | G35: Отходы прочих теплоизоляционных материалов на основе минерального волокна незагрязненные, практически неопасные | H35: 1 Т | I35: 4.248 | J35: 0 | K35: 4.248 | O35: =ROUND(CP35,2) -> 4601.73 | P35: =ROUND((ROUND((AC35*AW35*I35),2)*BC35),2) -> 0 | Q35: =(ROUND((ROUND(((ET35)*AV35*I35),2)*BB35),2)+ROUND((ROUND(((AE35-(EU35))*AV35*I35),2)*BS35),2)) -> 4601.73 | R35: =ROUND((ROUND((AE35*AV35*I35),2)*BS35),2) -> 0 | S35: =ROUND((ROUND((AF35*AV35*I35),2)*BA35),2) -> 0 | T35: =ROUND(CU35*I35,2) -> 0 | U35: =CV35*I35 -> 0 | V35: =CW35*I35 -> 0 | W35: =ROUND(CX35*I35,2) -> 0 | X35: =ROUND(CY35,2) -> 0 | Y35: =ROUND(CZ35,2) -> 0 | AA35: 56526441 | AB35: =ROUND((AC35+AD35+AF35),6) -> 98.3 | AC35: =ROUND((ES35),6) -> 0 | AD35: =ROUND((((ET35)-(EU35))+AE35),6) -> 98.3 | AE35: =ROUND((EU35),6) -> 0 | AF35: =ROUND((EV35),6) -> 0 | AG35: =ROUND((AP35),6) -> 0 | AH35: =(EW35) -> 0 | AI35: =(EX35) -> 0 | AJ35: =(AS35) -> 0 | AK35: 98.3 | AL35: 0 | AM35: 98.3 | AN35: 0 | AO35: 0 | AP35: 0 | AQ35: 0 | AR35: 0 | AS35: 0 | AT35: 94 | AU35: 61 | AV35: 1 | AW35: 1 | AZ35: 1 | BA35: 1 | BB35: 11.02 | BC35: 1 | BH35: 0 | BI35: 4 | BJ35: ТСН-2001.15 Доп. 56, Сб. 1, т. 1505, поз. 4 | BM35: 188 | BN35: 0 | BO35: 15.1-1505-04 | BP35: 1 | BQ35: 150 | BR35: 0 | BS35: 1 | BT35: 1 | BU35: 1 | BV35: 1 | BW35: 1 | BX35: 1 | BZ35: 94 | CA35: 61 | CE35: 30 | CF35: 0 | CG35: 0 | CM35: 0 | CO35: 0 | CP35: =(P35+Q35+S35) -> 4601.73 | CQ35: =ROUND((ROUND((AC35*AW35*1),2)*BC35),2) -> 0 | CR35: =(ROUND((ROUND(((ET35)*AV35*1),2)*BB35),2)+ROUND((ROUND(((AE35-(EU35))*AV35*1),2)*BS35),2)) -> 1083.27 | CS35: =ROUND((ROUND((AE35*AV35*1),2)*BS35),2) -> 0 | CT35: =ROUND((ROUND((AF35*AV35*1),2)*BA35),2) -> 0 | CU35: =AG35 -> 0 | CV35: =(AH35*AV35) -> 0 | CW35: =AI35 -> 0 | CX35: =AJ35 -> 0 | CY35: =(((S35+R35)*AT35)/100) -> 0 | CZ35: =(((S35+R35)*AU35)/100) -> 0 | DN35: 0 | DO35: 0 | DP35: 1 | DQ35: 1 | DU35: 1013 | DV35: 1 Т | DW35: 1 Т | DX35: 1 | EE35: 55586412 | EF35: 150 | EG35: Транспортные затраты | EH35: 0 | EJ35: 4 | EK35: 188 | EL35: ТСН-2001.15. Перевозка строительных грузов автомобильным транспортом | EM35: ТСН-2001.15. | EQ35: 0 | ER35: 98.3 | ES35: 0 | ET35: 98.3 | EU35: 0 | EV35: 0 | EW35: 0 | EX35: 0 | EY35: 0 | FQ35: 0 | FR35: 0 | FS35: 0 | FX35: 94 | FY35: 61 | GD35: 1 | GF35: 151177787 | GG35: 2 | GH35: 1 | GI35: 2 | GJ35: 0 | GK35: 0 | GL35: =ROUND(IF(AND(BH35=3,BI35=3,FS35<>0),P35,0),2) -> 0 | GM35: =ROUND(O35+X35+Y35,2)+GX35 -> 4601.73 | GN35: =IF(OR(BI35=0,BI35=1),GM35-GX35,0) -> 0 | GO35: =IF(BI35=2,GM35-GX35,0) -> 0 | GP35: =IF(BI35=4,GM35-GX35,0) -> 4601.73 | GR35: 0 | GS35: 3 | GT35: 0 | GV35: =ROUND((GT35),6) -> 0 | GW35: 1 | GX35: =ROUND(HC35*I35,2) -> 0 | HA35: 0 | HB35: 0 | HC35: =GV35*GW35 -> 0 | HS35: 0 | IK35: 0
A36: 17 | B36: 1 | C36: =ROW(SmtRes!A9) -> 9 | D36: =ROW(EtalonRes!A9) -> 9 | E36: 5 | F36: 15.1-1203-02 | G36: Обрезь и лом гипсокартонных листов малоопасные | H36: 1 Т | I36: 0.035 | J36: 0 | K36: 0.035 | O36: =ROUND(CP36,2) -> 1.36 | P36: =ROUND((ROUND((AC36*AW36*I36),2)*BC36),2) -> 0 | Q36: =(ROUND((ROUND(((ET36)*AV36*I36),2)*BB36),2)+ROUND((ROUND(((AE36-(EU36))*AV36*I36),2)*BS36),2)) -> 1.36 | R36: =ROUND((ROUND((AE36*AV36*I36),2)*BS36),2) -> 0 | S36: =ROUND((ROUND((AF36*AV36*I36),2)*BA36),2) -> 0 | T36: =ROUND(CU36*I36,2) -> 0 | U36: =CV36*I36 -> 0 | V36: =CW36*I36 -> 0 | W36: =ROUND(CX36*I36,2) -> 0 | X36: =ROUND(CY36,2) -> 0 | Y36: =ROUND(CZ36,2) -> 0 | AA36: 56526439 | AB36: =ROUND((AC36+AD36+AF36),6) -> 38.77 | AC36: =ROUND((ES36),6) -> 0 | AD36: =ROUND((((ET36)-(EU36))+AE36),6) -> 38.77 | AE36: =ROUND((EU36),6) -> 0 | AF36: =ROUND((EV36),6) -> 0 | AG36: =ROUND((AP36),6) -> 0 | AH36: =(EW36) -> 0 | AI36: =(EX36) -> 0 | AJ36: =(AS36) -> 0 | AK36: 38.77 | AL36: 0 | AM36: 38.77 | AN36: 0 | AO36: 0 | AP36: 0 | AQ36: 0 | AR36: 0 | AS36: 0 | AT36: 94 | AU36: 61 | AV36: 1 | AW36: 1 | AZ36: 1 | BA36: 1 | BB36: 1 | BC36: 1 | BH36: 0 | BI36: 4 | BJ36: ТСН-2001.15 Доп. 56, Сб. 1, т. 1203, поз. 2 | BM36: 188 | BN36: 0 | BO36: 15.1-1203-02 | BP36: 1 | BQ36: 150 | BR36: 0 | BS36: 1 | BT36: 1 | BU36: 1 | BV36: 1 | BW36: 1 | BX36: 1 | BZ36: 94 | CA36: 61 | CE36: 30 | CF36: 0 | CG36: 0 | CM36: 0 | CO36: 0 | CP36: =(P36+Q36+S36) -> 1.36 | CQ36: =ROUND((ROUND((AC36*AW36*1),2)*BC36),2) -> 0 | CR36: =(ROUND((ROUND(((ET36)*AV36*1),2)*BB36),2)+ROUND((ROUND(((AE36-(EU36))*AV36*1),2)*BS36),2)) -> 38.77 | CS36: =ROUND((ROUND((AE36*AV36*1),2)*BS36),2) -> 0 | CT36: =ROUND((ROUND((AF36*AV36*1),2)*BA36),2) -> 0 | CU36: =AG36 -> 0 | CV36: =(AH36*AV36) -> 0 | CW36: =AI36 -> 0 | CX36: =AJ36 -> 0 | CY36: =(((S36+R36)*AT36)/100) -> 0 | CZ36: =(((S36+R36)*AU36)/100) -> 0 | DN36: 0 | DO36: 0 | DP36: 1 | DQ36: 1 | DU36: 1013 | DV36: 1 Т | DW36: 1 Т | DX36: 1 | EE36: 55586412 | EF36: 150 | EG36: Транспортные затраты | EH36: 0 | EJ36: 4 | EK36: 188 | EL36: ТСН-2001.15. Перевозка строительных грузов автомобильным транспортом | EM36: ТСН-2001.15. | EQ36: 0 | ER36: 38.77 | ES36: 0 | ET36: 38.77 | EU36: 0 | EV36: 0 | EW36: 0 | EX36: 0 | EY36: 0 | FQ36: 0 | FR36: 0 | FS36: 0 | FX36: 94 | FY36: 61 | GD36: 1 | GF36: 725869249 | GG36: 2 | GH36: 1 | GI36: 2 | GJ36: 0 | GK36: 0 | GL36: =ROUND(IF(AND(BH36=3,BI36=3,FS36<>0),P36,0),2) -> 0 | GM36: =ROUND(O36+X36+Y36,2)+GX36 -> 1.36 | GN36: =IF(OR(BI36=0,BI36=1),GM36-GX36,0) -> 0 | GO36: =IF(BI36=2,GM36-GX36,0) -> 0 | GP36: =IF(BI36=4,GM36-GX36,0) -> 1.36 | GR36: 0 | GS36: 3 | GT36: 0 | GV36: =ROUND((GT36),6) -> 0 | GW36: 1 | GX36: =ROUND(HC36*I36,2) -> 0 | HA36: 0 | HB36: 0 | HC36: =GV36*GW36 -> 0 | HS36: 0 | IK36: 0
A37: 17 | B37: 1 | C37: =ROW(SmtRes!A10) -> 10 | D37: =ROW(EtalonRes!A10) -> 10 | E37: 5 | F37: 15.1-1203-02 | G37: Обрезь и лом гипсокартонных листов малоопасные | H37: 1 Т | I37: 0.035 | J37: 0 | K37: 0.035 | O37: =ROUND(CP37,2) -> 14.32 | P37: =ROUND((ROUND((AC37*AW37*I37),2)*BC37),2) -> 0 | Q37: =(ROUND((ROUND(((ET37)*AV37*I37),2)*BB37),2)+ROUND((ROUND(((AE37-(EU37))*AV37*I37),2)*BS37),2)) -> 14.32 | R37: =ROUND((ROUND((AE37*AV37*I37),2)*BS37),2) -> 0 | S37: =ROUND((ROUND((AF37*AV37*I37),2)*BA37),2) -> 0 | T37: =ROUND(CU37*I37,2) -> 0 | U37: =CV37*I37 -> 0 | V37: =CW37*I37 -> 0 | W37: =ROUND(CX37*I37,2) -> 0 | X37: =ROUND(CY37,2) -> 0 | Y37: =ROUND(CZ37,2) -> 0 | AA37: 56526441 | AB37: =ROUND((AC37+AD37+AF37),6) -> 38.77 | AC37: =ROUND((ES37),6) -> 0 | AD37: =ROUND((((ET37)-(EU37))+AE37),6) -> 38.77 | AE37: =ROUND((EU37),6) -> 0 | AF37: =ROUND((EV37),6) -> 0 | AG37: =ROUND((AP37),6) -> 0 | AH37: =(EW37) -> 0 | AI37: =(EX37) -> 0 | AJ37: =(AS37) -> 0 | AK37: 38.77 | AL37: 0 | AM37: 38.77 | AN37: 0 | AO37: 0 | AP37: 0 | AQ37: 0 | AR37: 0 | AS37: 0 | AT37: 94 | AU37: 61 | AV37: 1 | AW37: 1 | AZ37: 1 | BA37: 1 | BB37: 10.53 | BC37: 1 | BH37: 0 | BI37: 4 | BJ37: ТСН-2001.15 Доп. 56, Сб. 1, т. 1203, поз. 2 | BM37: 188 | BN37: 0 | BO37: 15.1-1203-02 | BP37: 1 | BQ37: 150 | BR37: 0 | BS37: 1 | BT37: 1 | BU37: 1 | BV37: 1 | BW37: 1 | BX37: 1 | BZ37: 94 | CA37: 61 | CE37: 30 | CF37: 0 | CG37: 0 | CM37: 0 | CO37: 0 | CP37: =(P37+Q37+S37) -> 14.32 | CQ37: =ROUND((ROUND((AC37*AW37*1),2)*BC37),2) -> 0 | CR37: =(ROUND((ROUND(((ET37)*AV37*1),2)*BB37),2)+ROUND((ROUND(((AE37-(EU37))*AV37*1),2)*BS37),2)) -> 408.25 | CS37: =ROUND((ROUND((AE37*AV37*1),2)*BS37),2) -> 0 | CT37: =ROUND((ROUND((AF37*AV37*1),2)*BA37),2) -> 0 | CU37: =AG37 -> 0 | CV37: =(AH37*AV37) -> 0 | CW37: =AI37 -> 0 | CX37: =AJ37 -> 0 | CY37: =(((S37+R37)*AT37)/100) -> 0 | CZ37: =(((S37+R37)*AU37)/100) -> 0 | DN37: 0 | DO37: 0 | DP37: 1 | DQ37: 1 | DU37: 1013 | DV37: 1 Т | DW37: 1 Т | DX37: 1 | EE37: 55586412 | EF37: 150 | EG37: Транспортные затраты | EH37: 0 | EJ37: 4 | EK37: 188 | EL37: ТСН-2001.15. Перевозка строительных грузов автомобильным транспортом | EM37: ТСН-2001.15. | EQ37: 0 | ER37: 38.77 | ES37: 0 | ET37: 38.77 | EU37: 0 | EV37: 0 | EW37: 0 | EX37: 0 | EY37: 0 | FQ37: 0 | FR37: 0 | FS37: 0 | FX37: 94 | FY37: 61 | GD37: 1 | GF37: 725869249 | GG37: 2 | GH37: 1 | GI37: 2 | GJ37: 0 | GK37: 0 | GL37: =ROUND(IF(AND(BH37=3,BI37=3,FS37<>0),P37,0),2) -> 0 | GM37: =ROUND(O37+X37+Y37,2)+GX37 -> 14.32 | GN37: =IF(OR(BI37=0,BI37=1),GM37-GX37,0) -> 0 | GO37: =IF(BI37=2,GM37-GX37,0) -> 0 | GP37: =IF(BI37=4,GM37-GX37,0) -> 14.32 | GR37: 0 | GS37: 3 | GT37: 0 | GV37: =ROUND((GT37),6) -> 0 | GW37: 1 | GX37: =ROUND(HC37*I37,2) -> 0 | HA37: 0 | HB37: 0 | HC37: =GV37*GW37 -> 0 | HS37: 0 | IK37: 0
A38: 17 | B38: 1 | C38: =ROW(SmtRes!A11) -> 11 | D38: =ROW(EtalonRes!A11) -> 11 | E38: 6 | F38: 15.1-1207-01 | G38: Отходы линолеума незагрязненные малоопасные | H38: 1 Т | I38: 3.487 | J38: 0 | K38: 3.487 | O38: =ROUND(CP38,2) -> 135.19 | P38: =ROUND((ROUND((AC38*AW38*I38),2)*BC38),2) -> 0 | Q38: =(ROUND((ROUND(((ET38)*AV38*I38),2)*BB38),2)+ROUND((ROUND(((AE38-(EU38))*AV38*I38),2)*BS38),2)) -> 135.19 | R38: =ROUND((ROUND((AE38*AV38*I38),2)*BS38),2) -> 0 | S38: =ROUND((ROUND((AF38*AV38*I38),2)*BA38),2) -> 0 | T38: =ROUND(CU38*I38,2) -> 0 | U38: =CV38*I38 -> 0 | V38: =CW38*I38 -> 0 | W38: =ROUND(CX38*I38,2) -> 0 | X38: =ROUND(CY38,2) -> 0 | Y38: =ROUND(CZ38,2) -> 0 | AA38: 56526439 | AB38: =ROUND((AC38+AD38+AF38),6) -> 38.77 | AC38: =ROUND((ES38),6) -> 0 | AD38: =ROUND((((ET38)-(EU38))+AE38),6) -> 38.77 | AE38: =ROUND((EU38),6) -> 0 | AF38: =ROUND((EV38),6) -> 0 | AG38: =ROUND((AP38),6) -> 0 | AH38: =(EW38) -> 0 | AI38: =(EX38) -> 0 | AJ38: =(AS38) -> 0 | AK38: 38.77 | AL38: 0 | AM38: 38.77 | AN38: 0 | AO38: 0 | AP38: 0 | AQ38: 0 | AR38: 0 | AS38: 0 | AT38: 94 | AU38: 61 | AV38: 1 | AW38: 1 | AZ38: 1 | BA38: 1 | BB38: 1 | BC38: 1 | BH38: 0 | BI38: 4 | BJ38: ТСН-2001.15 Доп. 56, Сб. 1, т. 1207, поз. 1 | BM38: 188 | BN38: 0 | BO38: 15.1-1207-01 | BP38: 1 | BQ38: 150 | BR38: 0 | BS38: 1 | BT38: 1 | BU38: 1 | BV38: 1 | BW38: 1 | BX38: 1 | BZ38: 94 | CA38: 61 | CE38: 30 | CF38: 0 | CG38: 0 | CM38: 0 | CO38: 0 | CP38: =(P38+Q38+S38) -> 135.19 | CQ38: =ROUND((ROUND((AC38*AW38*1),2)*BC38),2) -> 0 | CR38: =(ROUND((ROUND(((ET38)*AV38*1),2)*BB38),2)+ROUND((ROUND(((AE38-(EU38))*AV38*1),2)*BS38),2)) -> 38.77 | CS38: =ROUND((ROUND((AE38*AV38*1),2)*BS38),2) -> 0 | CT38: =ROUND((ROUND((AF38*AV38*1),2)*BA38),2) -> 0 | CU38: =AG38 -> 0 | CV38: =(AH38*AV38) -> 0 | CW38: =AI38 -> 0 | CX38: =AJ38 -> 0 | CY38: =(((S38+R38)*AT38)/100) -> 0 | CZ38: =(((S38+R38)*AU38)/100) -> 0 | DN38: 0 | DO38: 0 | DP38: 1 | DQ38: 1 | DU38: 1013 | DV38: 1 Т | DW38: 1 Т | DX38: 1 | EE38: 55586412 | EF38: 150 | EG38: Транспортные затраты | EH38: 0 | EJ38: 4 | EK38: 188 | EL38: ТСН-2001.15. Перевозка строительных грузов автомобильным транспортом | EM38: ТСН-2001.15. | EQ38: 0 | ER38: 38.77 | ES38: 0 | ET38: 38.77 | EU38: 0 | EV38: 0 | EW38: 0 | EX38: 0 | EY38: 0 | FQ38: 0 | FR38: 0 | FS38: 0 | FX38: 94 | FY38: 61 | GD38: 1 | GF38: 345636752 | GG38: 2 | GH38: 1 | GI38: 2 | GJ38: 0 | GK38: 0 | GL38: =ROUND(IF(AND(BH38=3,BI38=3,FS38<>0),P38,0),2) -> 0 | GM38: =ROUND(O38+X38+Y38,2)+GX38 -> 135.19 | GN38: =IF(OR(BI38=0,BI38=1),GM38-GX38,0) -> 0 | GO38: =IF(BI38=2,GM38-GX38,0) -> 0 | GP38: =IF(BI38=4,GM38-GX38,0) -> 135.19 | GR38: 0 | GS38: 3 | GT38: 0 | GV38: =ROUND((GT38),6) -> 0 | GW38: 1 | GX38: =ROUND(HC38*I38,2) -> 0 | HA38: 0 | HB38: 0 | HC38: =GV38*GW38 -> 0 | HS38: 0 | IK38: 0
A39: 17 | B39: 1 | C39: =ROW(SmtRes!A12) -> 12 | D39: =ROW(EtalonRes!A12) -> 12 | E39: 6 | F39: 15.1-1207-01 | G39: Отходы линолеума незагрязненные малоопасные | H39: 1 Т | I39: 3.487 | J39: 0 | K39: 3.487 | O39: =ROUND(CP39,2) -> 6685.15 | P39: =ROUND((ROUND((AC39*AW39*I39),2)*BC39),2) -> 0 | Q39: =(ROUND((ROUND(((ET39)*AV39*I39),2)*BB39),2)+ROUND((ROUND(((AE39-(EU39))*AV39*I39),2)*BS39),2)) -> 6685.15 | R39: =ROUND((ROUND((AE39*AV39*I39),2)*BS39),2) -> 0 | S39: =ROUND((ROUND((AF39*AV39*I39),2)*BA39),2) -> 0 | T39: =ROUND(CU39*I39,2) -> 0 | U39: =CV39*I39 -> 0 | V39: =CW39*I39 -> 0 | W39: =ROUND(CX39*I39,2) -> 0 | X39: =ROUND(CY39,2) -> 0 | Y39: =ROUND(CZ39,2) -> 0 | AA39: 56526441 | AB39: =ROUND((AC39+AD39+AF39),6) -> 38.77 | AC39: =ROUND((ES39),6) -> 0 | AD39: =ROUND((((ET39)-(EU39))+AE39),6) -> 38.77 | AE39: =ROUND((EU39),6) -> 0 | AF39: =ROUND((EV39),6) -> 0 | AG39: =ROUND((AP39),6) -> 0 | AH39: =(EW39) -> 0 | AI39: =(EX39) -> 0 | AJ39: =(AS39) -> 0 | AK39: 38.77 | AL39: 0 | AM39: 38.77 | AN39: 0 | AO39: 0 | AP39: 0 | AQ39: 0 | AR39: 0 | AS39: 0 | AT39: 94 | AU39: 61 | AV39: 1 | AW39: 1 | AZ39: 1 | BA39: 1 | BB39: 49.45 | BC39: 1 | BH39: 0 | BI39: 4 | BJ39: ТСН-2001.15 Доп. 56, Сб. 1, т. 1207, поз. 1 | BM39: 188 | BN39: 0 | BO39: 15.1-1207-01 | BP39: 1 | BQ39: 150 | BR39: 0 | BS39: 1 | BT39: 1 | BU39: 1 | BV39: 1 | BW39: 1 | BX39: 1 | BZ39: 94 | CA39: 61 | CE39: 30 | CF39: 0 | CG39: 0 | CM39: 0 | CO39: 0 | CP39: =(P39+Q39+S39) -> 6685.15 | CQ39: =ROUND((ROUND((AC39*AW39*1),2)*BC39),2) -> 0 | CR39: =(ROUND((ROUND(((ET39)*AV39*1),2)*BB39),2)+ROUND((ROUND(((AE39-(EU39))*AV39*1),2)*BS39),2)) -> 1917.18 | CS39: =ROUND((ROUND((AE39*AV39*1),2)*BS39),2) -> 0 | CT39: =ROUND((ROUND((AF39*AV39*1),2)*BA39),2) -> 0 | CU39: =AG39 -> 0 | CV39: =(AH39*AV39) -> 0 | CW39: =AI39 -> 0 | CX39: =AJ39 -> 0 | CY39: =(((S39+R39)*AT39)/100) -> 0 | CZ39: =(((S39+R39)*AU39)/100) -> 0 | DN39: 0 | DO39: 0 | DP39: 1 | DQ39: 1 | DU39: 1013 | DV39: 1 Т | DW39: 1 Т | DX39: 1 | EE39: 55586412 | EF39: 150 | EG39: Транспортные затраты | EH39: 0 | EJ39: 4 | EK39: 188 | EL39: ТСН-2001.15. Перевозка строительных грузов автомобильным транспортом | EM39: ТСН-2001.15. | EQ39: 0 | ER39: 38.77 | ES39: 0 | ET39: 38.77 | EU39: 0 | EV39: 0 | EW39: 0 | EX39: 0 | EY39: 0 | FQ39: 0 | FR39: 0 | FS39: 0 | FX39: 94 | FY39: 61 | GD39: 1 | GF39: 345636752 | GG39: 2 | GH39: 1 | GI39: 2 | GJ39: 0 | GK39: 0 | GL39: =ROUND(IF(AND(BH39=3,BI39=3,FS39<>0),P39,0),2) -> 0 | GM39: =ROUND(O39+X39+Y39,2)+GX39 -> 6685.15 | GN39: =IF(OR(BI39=0,BI39=1),GM39-GX39,0) -> 0 | GO39: =IF(BI39=2,GM39-GX39,0) -> 0 | GP39: =IF(BI39=4,GM39-GX39,0) -> 6685.15 | GR39: 0 | GS39: 3 | GT39: 0 | GV39: =ROUND((GT39),6) -> 0 | GW39: 1 | GX39: =ROUND(HC39*I39,2) -> 0 | HA39: 0 | HB39: 0 | HC39: =GV39*GW39 -> 0 | HS39: 0 | IK39: 0
... A63: 17 | B63: 1 | C63: =ROW(SmtRes!A36) -> 36 | D63: =ROW(EtalonRes!A36) -> 36 | E63: 18 | F63: 15.1-1505-07 | G63: Керамзит, утративший потребительские свойства, незагрязненный, практически неопасный | H63: 1 Т | I63: 318.564 | J63: 0 | K63: 318.564 | O63: =ROUND(CP63,2) -> 123955.49 | P63: =ROUND((ROUND((AC63*AW63*I63),2)*BC63),2) -> 0 | Q63: =(ROUND((ROUND(((ET63)*AV63*I63),2)*BB63),2)+ROUND((ROUND(((AE63-(EU63))*AV63*I63),2)*BS63),2)) -> 123955.49 | R63: =ROUND((ROUND((AE63*AV63*I63),2)*BS63),2) -> 0 | S63: =ROUND((ROUND((AF63*AV63*I63),2)*BA63),2) -> 0 | T63: =ROUND(CU63*I63,2) -> 0 | U63: =CV63*I63 -> 0 | V63: =CW63*I63 -> 0 | W63: =ROUND(CX63*I63,2) -> 0 | X63: =ROUND(CY63,2) -> 0 | Y63: =ROUND(CZ63,2) -> 0 | AA63: 56526441 | AB63: =ROUND((AC63+AD63+AF63),6) -> 47.51 | AC63: =ROUND((ES63),6) -> 0 | AD63: =ROUND((((ET63)-(EU63))+AE63),6) -> 47.51 | AE63: =ROUND((EU63),6) -> 0 | AF63: =ROUND((EV63),6) -> 0 | AG63: =ROUND((AP63),6) -> 0 | AH63: =(EW63) -> 0 | AI63: =(EX63) -> 0 | AJ63: =(AS63) -> 0 | AK63: 47.51 | AL63: 0 | AM63: 47.51 | AN63: 0 | AO63: 0 | AP63: 0 | AQ63: 0 | AR63: 0 | AS63: 0 | AT63: 94 | AU63: 61 | AV63: 1 | AW63: 1 | AZ63: 1 | BA63: 1 | BB63: 8.19 | BC63: 1 | BH63: 0 | BI63: 4 | BJ63: ТСН-2001.15 Доп. 56, Сб. 1, т. 1505, поз. 7 | BM63: 188 | BN63: 0 | BO63: 15.1-1505-07 | BP63: 1 | BQ63: 150 | BR63: 0 | BS63: 1 | BT63: 1 | BU63: 1 | BV63: 1 | BW63: 1 | BX63: 1 | BZ63: 94 | CA63: 61 | CE63: 30 | CF63: 0 | CG63: 0 | CM63: 0 | CO63: 0 | CP63: =(P63+Q63+S63) -> 123955.49 | CQ63: =ROUND((ROUND((AC63*AW63*1),2)*BC63),2) -> 0 | CR63: =(ROUND((ROUND(((ET63)*AV63*1),2)*BB63),2)+ROUND((ROUND(((AE63-(EU63))*AV63*1),2)*BS63),2)) -> 389.11 | CS63: =ROUND((ROUND((AE63*AV63*1),2)*BS63),2) -> 0 | CT63: =ROUND((ROUND((AF63*AV63*1),2)*BA63),2) -> 0 | CU63: =AG63 -> 0 | CV63: =(AH63*AV63) -> 0 | CW63: =AI63 -> 0 | CX63: =AJ63 -> 0 | CY63: =(((S63+R63)*AT63)/100) -> 0 | CZ63: =(((S63+R63)*AU63)/100) -> 0 | DN63: 0 | DO63: 0 | DP63: 1 | DQ63: 1 | DU63: 1013 | DV63: 1 Т | DW63: 1 Т | DX63: 1 | EE63: 55586412 | EF63: 150 | EG63: Транспортные затраты | EH63: 0 | EJ63: 4 | EK63: 188 | EL63: ТСН-2001.15. Перевозка строительных грузов автомобильным транспортом | EM63: ТСН-2001.15. | EQ63: 0 | ER63: 47.51 | ES63: 0 | ET63: 47.51 | EU63: 0 | EV63: 0 | EW63: 0 | EX63: 0 | EY63: 0 | FQ63: 0 | FR63: 0 | FS63: 0 | FX63: 94 | FY63: 61 | GD63: 1 | GF63: -1557990163 | GG63: 2 | GH63: 1 | GI63: 2 | GJ63: 0 | GK63: 0 | GL63: =ROUND(IF(AND(BH63=3,BI63=3,FS63<>0),P63,0),2) -> 0 | GM63: =ROUND(O63+X63+Y63,2)+GX63 -> 123955.49 | GN63: =IF(OR(BI63=0,BI63=1),GM63-GX63,0) -> 0 | GO63: =IF(BI63=2,GM63-GX63,0) -> 0 | GP63: =IF(BI63=4,GM63-GX63,0) -> 123955.49 | GR63: 0 | GS63: 3 | GT63: 0 | GV63: =ROUND((GT63),6) -> 0 | GW63: 1 | GX63: =ROUND(HC63*I63,2) -> 0 | HA63: 0 | HB63: 0 | HC63: =GV63*GW63 -> 0 | HS63: 0 | IK63: 0
A65: 51 | B65: =B24 -> 1 | C65: =A24 -> 4 | D65: =ROW(A24) -> 24 | F65: =IF(F24<>"",F24,"") | G65: =IF(G24<>"",G24,"") -> Размещение и содержание строительного мусора | H65: 0 | O65: =ROUND(AB65,2) -> 96538.04 | P65: =ROUND(AC65,2) -> 0 | Q65: =ROUND(AD65,2) -> 96538.04 | R65: =ROUND(AE65,2) -> 0 | S65: =ROUND(AF65,2) -> 0 | T65: =ROUND(AG65,2) -> 0 | U65: =AH65 -> 0 | V65: =AI65 -> 0 | W65: =ROUND(AJ65,2) -> 0 | X65: =ROUND(AK65,2) -> 0 | Y65: =ROUND(AL65,2) -> 0 | AB65: =ROUND(SUMIF(AA28:AA63,"=56526439",O28:O63),2) -> 96538.04 | AC65: =ROUND(SUMIF(AA28:AA63,"=56526439",P28:P63),2) -> 0 | AD65: =ROUND(SUMIF(AA28:AA63,"=56526439",Q28:Q63),2) -> 96538.04 | AE65: =ROUND(SUMIF(AA28:AA63,"=56526439",R28:R63),2) -> 0 | AF65: =ROUND(SUMIF(AA28:AA63,"=56526439",S28:S63),2) -> 0 | AG65: =ROUND(SUMIF(AA28:AA63,"=56526439",T28:T63),2) -> 0 | AH65: =SUMIF(AA28:AA63,"=56526439",U28:U63) -> 0 | AI65: =SUMIF(AA28:AA63,"=56526439",V28:V63) -> 0 | AJ65: =ROUND(SUMIF(AA28:AA63,"=56526439",W28:W63),2) -> 0 | AK65: =ROUND(SUMIF(AA28:AA63,"=56526439",X28:X63),2) -> 0 | AL65: =ROUND(SUMIF(AA28:AA63,"=56526439",Y28:Y63),2) -> 0 | AO65: =ROUND(BX65,2) -> 0 | AP65: =ROUND(BY65,2) -> 0 | AQ65: =ROUND(BZ65,2) -> 0 | AR65: =ROUND(CA65,2) -> 96538.04 | AS65: =ROUND(CB65,2) -> 0 | AT65: =ROUND(CC65,2) -> 0 | AU65: =ROUND(CD65,2) -> 96538.04 | AV65: =ROUND(CE65,2) -> 0 | ... BD65: =ROUND(CM65,2) -> 0 | BX65: =ROUND(SUMIF(AA28:AA63,"=56526439",FQ28:FQ63),2) -> 0 | BY65: =ROUND(SUMIF(AA28:AA63,"=56526439",FR28:FR63),2) -> 0 | BZ65: =ROUND(SUMIF(AA28:AA63,"=56526439",GL28:GL63),2) -> 0 | CA65: =ROUND(SUMIF(AA28:AA63,"=56526439",GM28:GM63),2) -> 96538.04 | CB65: =ROUND(SUMIF(AA28:AA63,"=56526439",GN28:GN63),2) -> 0 | CC65: =ROUND(SUMIF(AA28:AA63,"=56526439",GO28:GO63),2) -> 0 | CD65: =ROUND(SUMIF(AA28:AA63,"=56526439",GP28:GP63),2) -> 96538.04 | CE65: =AC65-BX65 -> 0 | CF65: =AC65-BY65 -> 0 | CG65: =BX65-BZ65 -> 0 | CH65: =AC65-BX65-BY65+BZ65 -> 0 | CI65: =BY65-BZ65 -> 0 | CJ65: =ROUND(SUMIF(AA28:AA63,"=56526439",GX28:GX63),2) -> 0 | CK65: =ROUND(SUMIF(AA28:AA63,"=56526439",GY28:GY63),2) -> 0 | CL65: =ROUND(SUMIF(AA28:AA63,"=56526439",GZ28:GZ63),2) -> 0 | CM65: =ROUND(SUMIF(AA28:AA63,"=56526439",HD28:HD63),2) -> 0 | DG65: =ROUND(DT65,2) -> 961161.92 | DH65: =ROUND(DU65,2) -> 0 | DI65: =ROUND(DV65,2) -> 961161.92 | DJ65: =ROUND(DW65,2) -> 0 | DK65: =ROUND(DX65,2) -> 0 | DL65: =ROUND(DY65,2) -> 0 | DM65: =DZ65 -> 0 | DN65: =EA65 -> 0 | DO65: =ROUND(EB65,2) -> 0 | DP65: =ROUND(EC65,2) -> 0 | DQ65: =ROUND(ED65,2) -> 0 | DT65: =ROUND(SUMIF(AA28:AA63,"=56526441",O28:O63),2) -> 961161.92 | DU65: =ROUND(SUMIF(AA28:AA63,"=56526441",P28:P63),2) -> 0 | DV65: =ROUND(SUMIF(AA28:AA63,"=56526441",Q28:Q63),2) -> 961161.92 | DW65: =ROUND(SUMIF(AA28:AA63,"=56526441",R28:R63),2) -> 0 | DX65: =ROUND(SUMIF(AA28:AA63,"=56526441",S28:S63),2) -> 0 | DY65: =ROUND(SUMIF(AA28:AA63,"=56526441",T28:T63),2) -> 0 | DZ65: =SUMIF(AA28:AA63,"=56526441",U28:U63) -> 0 | EA65: =SUMIF(AA28:AA63,"=56526441",V28:V63) -> 0 | EB65: =ROUND(SUMIF(AA28:AA63,"=56526441",W28:W63),2) -> 0 | EC65: =ROUND(SUMIF(AA28:AA63,"=56526441",X28:X63),2) -> 0 | ED65: =ROUND(SUMIF(AA28:AA63,"=56526441",Y28:Y63),2) -> 0 | EG65: =ROUND(FP65,2) -> 0 | EH65: =ROUND(FQ65,2) -> 0 | EI65: =ROUND(FR65,2) -> 0 | EJ65: =ROUND(FS65,2) -> 961161.92 | EK65: =ROUND(FT65,2) -> 0 | EL65: =ROUND(FU65,2) -> 0 | EM65: =ROUND(FV65,2) -> 961161.92 | EN65: =ROUND(FW65,2) -> 0 | ... EV65: =ROUND(GE65,2) -> 0 | FP65: =ROUND(SUMIF(AA28:AA63,"=56526441",FQ28:FQ63),2) -> 0 | FQ65: =ROUND(SUMIF(AA28:AA63,"=56526441",FR28:FR63),2) -> 0 | FR65: =ROUND(SUMIF(AA28:AA63,"=56526441",GL28:GL63),2) -> 0 | FS65: =ROUND(SUMIF(AA28:AA63,"=56526441",GM28:GM63),2) -> 961161.92 | FT65: =ROUND(SUMIF(AA28:AA63,"=56526441",GN28:GN63),2) -> 0 | FU65: =ROUND(SUMIF(AA28:AA63,"=56526441",GO28:GO63),2) -> 0 | FV65: =ROUND(SUMIF(AA28:AA63,"=56526441",GP28:GP63),2) -> 961161.92 | FW65: =DU65-FP65 -> 0 | FX65: =DU65-FQ65 -> 0 | FY65: =FP65-FR65 -> 0 | FZ65: =DU65-FP65-FQ65+FR65 -> 0 | GA65: =FQ65-FR65 -> 0 | GB65: =ROUND(SUMIF(AA28:AA63,"=56526441",GX28:GX63),2) -> 0 | GC65: =ROUND(SUMIF(AA28:AA63,"=56526441",GY28:GY63),2) -> 0 | GD65: =ROUND(SUMIF(AA28:AA63,"=56526441",GZ28:GZ63),2) -> 0 | GE65: =ROUND(SUMIF(AA28:AA63,"=56526441",HD28:HD63),2) -> 0 | GX65: 0
A67: 50 | B67: 0 | C67: 0 | D67: 1 | E67: 201 | F67: =ROUND(Source!O65,O67) -> 96538.04 | G67: ПЗ | H67: Прямые затраты | K67: 201 | L67: 1 | M67: 3 | O67: 2 | P67: =ROUND(Source!DG65,O67) -> 961161.92 | W67: 96538.04 | X67: 1 | Y67: 96538.04 | Z67: 961161.92 | AA67: 1 | AB67: 961161.92
A68: 50 | B68: 0 | C68: 0 | D68: 1 | E68: 202 | F68: =ROUND(Source!P65,O68) -> 0 | G68: СтМатОб | H68: Стоимость материальных ресурсов (всего) | K68: 202 | L68: 2 | M68: 3 | O68: 2 | P68: =ROUND(Source!DH65,O68) -> 0 | W68: 0 | X68: 1 | Y68: 0 | Z68: 0 | AA68: 1 | AB68: 0
A69: 50 | B69: 0 | C69: 0 | D69: 1 | E69: 222 | F69: =ROUND(Source!AO65,O69) -> 0 | G69: СтМатОбЗак | H69: Стоимость материалов и оборудования заказчика | K69: 222 | L69: 3 | M69: 3 | O69: 2 | P69: =ROUND(Source!EG65,O69) -> 0 | W69: 0 | X69: 1 | Y69: 0 | Z69: 0 | AA69: 1 | AB69: 0
A70: 50 | B70: 0 | C70: 0 | D70: 1 | E70: 225 | F70: =ROUND(Source!AV65,O70) -> 0 | G70: СтМатОбПод | H70: Стоимость материалов и оборудования подрядчика | K70: 225 | L70: 4 | M70: 3 | O70: 2 | P70: =ROUND(Source!EN65,O70) -> 0 | W70: 0 | X70: 1 | Y70: 0 | Z70: 0 | AA70: 1 | AB70: 0
A71: 50 | B71: 0 | C71: 0 | D71: 1 | E71: 226 | F71: =ROUND(Source!AW65,O71) -> 0 | G71: СтМат | H71: Стоимость материалов (всего) | K71: 226 | L71: 5 | M71: 3 | O71: 2 | P71: =ROUND(Source!EO65,O71) -> 0 | W71: 0 | X71: 1 | Y71: 0 | Z71: 0 | AA71: 1 | AB71: 0
A72: 50 | B72: 0 | C72: 0 | D72: 1 | E72: 227 | F72: =ROUND(Source!AX65,O72) -> 0 | G72: СтМатЗак | H72: Стоимость материалов заказчика | K72: 227 | L72: 6 | M72: 3 | O72: 2 | P72: =ROUND(Source!EP65,O72) -> 0 | W72: 0 | X72: 1 | Y72: 0 | Z72: 0 | AA72: 1 | AB72: 0
A73: 50 | B73: 0 | C73: 0 | D73: 1 | E73: 228 | F73: =ROUND(Source!AY65,O73) -> 0 | G73: СтМатПод | H73: Стоимость материалов подрядчика | K73: 228 | L73: 7 | M73: 3 | O73: 2 | P73: =ROUND(Source!EQ65,O73) -> 0 | W73: 0 | X73: 1 | Y73: 0 | Z73: 0 | AA73: 1 | AB73: 0
A74: 50 | B74: 0 | C74: 0 | D74: 1 | E74: 216 | F74: =ROUND(Source!AP65,O74) -> 0 | G74: Оборуд | H74: Стоимость оборудования (всего) | K74: 216 | L74: 8 | M74: 3 | O74: 2 | P74: =ROUND(Source!EH65,O74) -> 0 | W74: 0 | X74: 1 | Y74: 0 | Z74: 0 | AA74: 1 | AB74: 0
A75: 50 | B75: 0 | C75: 0 | D75: 1 | E75: 223 | F75: =ROUND(Source!AQ65,O75) -> 0 | G75: ОборудЗак | H75: Стоимость оборудования заказчика | K75: 223 | L75: 9 | M75: 3 | O75: 2 | P75: =ROUND(Source!EI65,O75) -> 0 | W75: 0 | X75: 1 | Y75: 0 | Z75: 0 | AA75: 1 | AB75: 0
A76: 50 | B76: 0 | C76: 0 | D76: 1 | E76: 229 | F76: =ROUND(Source!AZ65,O76) -> 0 | G76: ОборудПод | H76: Стоимость оборудования подрядчика | K76: 229 | L76: 10 | M76: 3 | O76: 2 | P76: =ROUND(Source!ER65,O76) -> 0 | W76: 0 | X76: 1 | Y76: 0 | Z76: 0 | AA76: 1 | AB76: 0
A77: 50 | B77: 0 | C77: 0 | D77: 1 | E77: 203 | F77: =ROUND(Source!Q65,O77) -> 96538.04 | G77: ЭММ | H77: Эксплуатация машин | K77: 203 | L77: 11 | M77: 3 | O77: 2 | P77: =ROUND(Source!DI65,O77) -> 961161.92 | W77: 96538.04 | X77: 1 | Y77: 96538.04 | Z77: 961161.92 | AA77: 1 | AB77: 961161.92
A78: 50 | B78: 0 | C78: 0 | D78: 1 | E78: 231 | F78: =ROUND(Source!BB65,O78) -> 0 | G78: ЭММсНРиСП | H78: Эксплуатация машин по ТСН-2001.16 | K78: 231 | L78: 12 | M78: 3 | O78: 2 | P78: =ROUND(Source!ET65,O78) -> 0 | W78: 0 | X78: 1 | Y78: 0 | Z78: 0 | AA78: 1 | AB78: 0
A79: 50 | B79: 0 | C79: 0 | D79: 1 | E79: 204 | F79: =ROUND(Source!R65,O79) -> 0 | G79: ЗПМ | H79: ЗП машинистов | K79: 204 | L79: 13 | M79: 3 | O79: 2 | P79: =ROUND(Source!DJ65,O79) -> 0 | W79: 0 | X79: 1 | Y79: 0 | Z79: 0 | AA79: 1 | AB79: 0
A80: 50 | B80: 0 | C80: 0 | D80: 1 | E80: 205 | F80: =ROUND(Source!S65,O80) -> 0 | G80: ОЗП | H80: Основная ЗП рабочих | K80: 205 | L80: 14 | M80: 3 | O80: 2 | P80: =ROUND(Source!DK65,O80) -> 0 | W80: 0 | X80: 1 | Y80: 0 | Z80: 0 | AA80: 1 | AB80: 0
A81: 50 | B81: 0 | C81: 0 | D81: 1 | E81: 232 | F81: =ROUND(Source!BC65,O81) -> 0 | G81: ОЗПсНРиСП | H81: Основная ЗП рабочих по ТСН-2001.16 | K81: 232 | L81: 15 | M81: 3 | O81: 2 | P81: =ROUND(Source!EU65,O81) -> 0 | W81: 0 | X81: 1 | Y81: 0 | Z81: 0 | AA81: 1 | AB81: 0
A82: 50 | B82: 0 | C82: 0 | D82: 1 | E82: 214 | F82: =ROUND(Source!AS65,O82) -> 0 | G82: Строит | H82: Строительные работы с НР и СП | K82: 214 | L82: 16 | M82: 3 | O82: 2 | P82: =ROUND(Source!EK65,O82) -> 0 | W82: 0 | X82: 1 | Y82: 0 | Z82: 0 | AA82: 1 | AB82: 0
A83: 50 | B83: 0 | C83: 0 | D83: 1 | E83: 215 | F83: =ROUND(Source!AT65,O83) -> 0 | G83: Монтаж | H83: Монтажные работы с НР и СП | K83: 215 | L83: 17 | M83: 3 | O83: 2 | P83: =ROUND(Source!EL65,O83) -> 0 | W83: 0 | X83: 1 | Y83: 0 | Z83: 0 | AA83: 1 | AB83: 0
A84: 50 | B84: 0 | C84: 0 | D84: 1 | E84: 217 | F84: =ROUND(Source!AU65,O84) -> 96538.04 | G84: Прочие | H84: Прочие работы с НР и СП | K84: 217 | L84: 18 | M84: 3 | O84: 2 | P84: =ROUND(Source!EM65,O84) -> 961161.92 | W84: 96538.04 | X84: 1 | Y84: 96538.04 | Z84: 961161.92 | AA84: 1 | AB84: 961161.92
A85: 50 | B85: 0 | C85: 0 | D85: 1 | E85: 230 | F85: =ROUND(Source!BA65,O85) -> 0 | G85: ПрочиеЗатр | H85: Прочие затраты по ТСН-2001.16 | K85: 230 | L85: 19 | M85: 3 | O85: 2 | P85: =ROUND(Source!ES65,O85) -> 0 | W85: 0 | X85: 1 | Y85: 0 | Z85: 0 | AA85: 1 | AB85: 0
A86: 50 | B86: 0 | C86: 0 | D86: 1 | E86: 206 | F86: =ROUND(Source!T65,O86) -> 0 | G86: ВозврМат | H86: Возврат материалов | K86: 206 | L86: 20 | M86: 3 | O86: 2 | P86: =ROUND(Source!DL65,O86) -> 0 | W86: 0 | X86: 1 | Y86: 0 | Z86: 0 | AA86: 1 | AB86: 0
A87: 50 | B87: 0 | C87: 0 | D87: 1 | E87: 207 | F87: =Source!U65 -> 0 | G87: ТрудСтр | H87: Трудозатраты строителей | K87: 207 | L87: 21 | M87: 3 | O87: -1 | P87: =Source!DM65 -> 0 | W87: 0 | X87: 1 | Y87: 0 | Z87: 0 | AA87: 1 | AB87: 0
A88: 50 | B88: 0 | C88: 0 | D88: 1 | E88: 208 | F88: =Source!V65 -> 0 | G88: ТрудМаш | H88: Трудозатраты машинистов | K88: 208 | L88: 22 | M88: 3 | O88: -1 | P88: =Source!DN65 -> 0 | W88: 0 | X88: 1 | Y88: 0 | Z88: 0 | AA88: 1 | AB88: 0
A89: 50 | B89: 0 | C89: 0 | D89: 1 | E89: 209 | F89: =ROUND(Source!W65,O89) -> 0 | G89: ТранспМат | H89: Транспорт материалов | K89: 209 | L89: 23 | M89: 3 | O89: 2 | P89: =ROUND(Source!DO65,O89) -> 0 | W89: 0 | X89: 1 | Y89: 0 | Z89: 0 | AA89: 1 | AB89: 0
A90: 50 | B90: 0 | C90: 0 | D90: 1 | E90: 233 | F90: =ROUND(Source!BD65,O90) -> 0 | G90: Перевозка | H90: Перевозка грузов | K90: 233 | L90: 24 | M90: 3 | O90: 2 | P90: =ROUND(Source!EV65,O90) -> 0 | W90: 0 | X90: 1 | Y90: 0 | Z90: 0 | AA90: 1 | AB90: 0
A91: 50 | B91: 0 | C91: 0 | D91: 1 | E91: 210 | F91: =ROUND(Source!X65,O91) -> 0 | G91: НР | H91: Накладные расходы | K91: 210 | L91: 25 | M91: 3 | O91: 2 | P91: =ROUND(Source!DP65,O91) -> 0 | W91: 0 | X91: 1 | Y91: 0 | Z91: 0 | AA91: 1 | AB91: 0
A92: 50 | B92: 0 | C92: 0 | D92: 1 | E92: 211 | F92: =ROUND(Source!Y65,O92) -> 0 | G92: СмПриб | H92: Сметная прибыль | K92: 211 | L92: 26 | M92: 3 | O92: 2 | P92: =ROUND(Source!DQ65,O92) -> 0 | W92: 0 | X92: 1 | Y92: 0 | Z92: 0 | AA92: 1 | AB92: 0
A93: 50 | B93: 0 | C93: 0 | D93: 1 | E93: 224 | F93: =ROUND(Source!AR65,O93) -> 96538.04 | G93: Всего | H93: Всего с НР и СП | K93: 224 | L93: 27 | M93: 3 | O93: 2 | P93: =ROUND(Source!EJ65,O93) -> 961161.92 | W93: 96538.04 | X93: 1 | Y93: 96538.04 | Z93: 961161.92 | AA93: 1 | AB93: 961161.92
A95: 51 | B95: =B20 -> 1 | C95: =A20 -> 3 | D95: =ROW(A20) -> 20 | F95: =IF(F20<>"",F20,"") | G95: =IF(G20<>"",G20,"") -> Размещение и содержание строительного мусора | H95: 0 | O95: =ROUND(O65+AB95,2) -> 96538.04 | P95: =ROUND(P65+AC95,2) -> 0 | Q95: =ROUND(Q65+AD95,2) -> 96538.04 | R95: =ROUND(R65+AE95,2) -> 0 | S95: =ROUND(S65+AF95,2) -> 0 | T95: =ROUND(T65+AG95,2) -> 0 | U95: =U65+AH95 -> 0 | V95: =V65+AI95 -> 0 | W95: =ROUND(W65+AJ95,2) -> 0 | X95: =ROUND(X65+AK95,2) -> 0 | Y95: =ROUND(Y65+AL95,2) -> 0 | AO95: =ROUND(AO65+BX95,2) -> 0 | AP95: =ROUND(AP65+BY95,2) -> 0 | AQ95: =ROUND(AQ65+BZ95,2) -> 0 | AR95: =ROUND(AR65+CA95,2) -> 96538.04 | AS95: =ROUND(AS65+CB95,2) -> 0 | AT95: =ROUND(AT65+CC95,2) -> 0 | AU95: =ROUND(AU65+CD95,2) -> 96538.04 | AV95: =ROUND(AV65+CE95,2) -> 0 | ... BD95: =ROUND(BD65+CM95,2) -> 0 | DG95: =ROUND(DG65+DT95,2) -> 961161.92 | DH95: =ROUND(DH65+DU95,2) -> 0 | DI95: =ROUND(DI65+DV95,2) -> 961161.92 | DJ95: =ROUND(DJ65+DW95,2) -> 0 | DK95: =ROUND(DK65+DX95,2) -> 0 | DL95: =ROUND(DL65+DY95,2) -> 0 | DM95: =DM65+DZ95 -> 0 | DN95: =DN65+EA95 -> 0 | DO95: =ROUND(DO65+EB95,2) -> 0 | DP95: =ROUND(DP65+EC95,2) -> 0 | DQ95: =ROUND(DQ65+ED95,2) -> 0 | EG95: =ROUND(EG65+FP95,2) -> 0 | EH95: =ROUND(EH65+FQ95,2) -> 0 | EI95: =ROUND(EI65+FR95,2) -> 0 | EJ95: =ROUND(EJ65+FS95,2) -> 961161.92 | EK95: =ROUND(EK65+FT95,2) -> 0 | EL95: =ROUND(EL65+FU95,2) -> 0 | EM95: =ROUND(EM65+FV95,2) -> 961161.92 | EN95: =ROUND(EN65+FW95,2) -> 0 | ... EV95: =ROUND(EV65+GE95,2) -> 0 | GX95: 0
A97: 50 | B97: 0 | C97: 0 | D97: 1 | E97: 201 | F97: =ROUND(Source!O95,O97) -> 96538.04 | G97: ПЗ | H97: Прямые затраты | K97: 201 | L97: 1 | M97: 3 | O97: 2 | P97: =ROUND(Source!DG95,O97) -> 961161.92 | W97: 96538.04 | X97: 1 | Y97: 96538.04 | Z97: 961161.92 | AA97: 1 | AB97: 961161.92
A98: 50 | B98: 0 | C98: 0 | D98: 1 | E98: 202 | F98: =ROUND(Source!P95,O98) -> 0 | G98: СтМатОб | H98: Стоимость материальных ресурсов (всего) | K98: 202 | L98: 2 | M98: 3 | O98: 2 | P98: =ROUND(Source!DH95,O98) -> 0 | W98: 0 | X98: 1 | Y98: 0 | Z98: 0 | AA98: 1 | AB98: 0
A99: 50 | B99: 0 | C99: 0 | D99: 1 | E99: 222 | F99: =ROUND(Source!AO95,O99) -> 0 | G99: СтМатОбЗак | H99: Стоимость материалов и оборудования заказчика | K99: 222 | L99: 3 | M99: 3 | O99: 2 | P99: =ROUND(Source!EG95,O99) -> 0 | W99: 0 | X99: 1 | Y99: 0 | Z99: 0 | AA99: 1 | AB99: 0
A100: 50 | B100: 0 | C100: 0 | D100: 1 | E100: 225 | F100: =ROUND(Source!AV95,O100) -> 0 | G100: СтМатОбПод | H100: Стоимость материалов и оборудования подрядчика | K100: 225 | L100: 4 | M100: 3 | O100: 2 | P100: =ROUND(Source!EN95,O100) -> 0 | W100: 0 | X100: 1 | Y100: 0 | Z100: 0 | AA100: 1 | AB100: 0
A101: 50 | B101: 0 | C101: 0 | D101: 1 | E101: 226 | F101: =ROUND(Source!AW95,O101) -> 0 | G101: СтМат | H101: Стоимость материалов (всего) | K101: 226 | L101: 5 | M101: 3 | O101: 2 | P101: =ROUND(Source!EO95,O101) -> 0 | W101: 0 | X101: 1 | Y101: 0 | Z101: 0 | AA101: 1 | AB101: 0
A102: 50 | B102: 0 | C102: 0 | D102: 1 | E102: 227 | F102: =ROUND(Source!AX95,O102) -> 0 | G102: СтМатЗак | H102: Стоимость материалов заказчика | K102: 227 | L102: 6 | M102: 3 | O102: 2 | P102: =ROUND(Source!EP95,O102) -> 0 | W102: 0 | X102: 1 | Y102: 0 | Z102: 0 | AA102: 1 | AB102: 0
A103: 50 | B103: 0 | C103: 0 | D103: 1 | E103: 228 | F103: =ROUND(Source!AY95,O103) -> 0 | G103: СтМатПод | H103: Стоимость материалов подрядчика | K103: 228 | L103: 7 | M103: 3 | O103: 2 | P103: =ROUND(Source!EQ95,O103) -> 0 | W103: 0 | X103: 1 | Y103: 0 | Z103: 0 | AA103: 1 | AB103: 0
A104: 50 | B104: 0 | C104: 0 | D104: 1 | E104: 216 | F104: =ROUND(Source!AP95,O104) -> 0 | G104: Оборуд | H104: Стоимость оборудования (всего) | K104: 216 | L104: 8 | M104: 3 | O104: 2 | P104: =ROUND(Source!EH95,O104) -> 0 | W104: 0 | X104: 1 | Y104: 0 | Z104: 0 | AA104: 1 | AB104: 0
A105: 50 | B105: 0 | C105: 0 | D105: 1 | E105: 223 | F105: =ROUND(Source!AQ95,O105) -> 0 | G105: ОборудЗак | H105: Стоимость оборудования заказчика | K105: 223 | L105: 9 | M105: 3 | O105: 2 | P105: =ROUND(Source!EI95,O105) -> 0 | W105: 0 | X105: 1 | Y105: 0 | Z105: 0 | AA105: 1 | AB105: 0
A106: 50 | B106: 0 | C106: 0 | D106: 1 | E106: 229 | F106: =ROUND(Source!AZ95,O106) -> 0 | G106: ОборудПод | H106: Стоимость оборудования подрядчика | K106: 229 | L106: 10 | M106: 3 | O106: 2 | P106: =ROUND(Source!ER95,O106) -> 0 | W106: 0 | X106: 1 | Y106: 0 | Z106: 0 | AA106: 1 | AB106: 0
A107: 50 | B107: 0 | C107: 0 | D107: 1 | E107: 203 | F107: =ROUND(Source!Q95,O107) -> 96538.04 | G107: ЭММ | H107: Эксплуатация машин | K107: 203 | L107: 11 | M107: 3 | O107: 2 | P107: =ROUND(Source!DI95,O107) -> 961161.92 | W107: 96538.04 | X107: 1 | Y107: 96538.04 | Z107: 961161.92 | AA107: 1 | AB107: 961161.92
A108: 50 | B108: 0 | C108: 0 | D108: 1 | E108: 231 | F108: =ROUND(Source!BB95,O108) -> 0 | G108: ЭММсНРиСП | H108: Эксплуатация машин по ТСН-2001.16 | K108: 231 | L108: 12 | M108: 3 | O108: 2 | P108: =ROUND(Source!ET95,O108) -> 0 | W108: 0 | X108: 1 | Y108: 0 | Z108: 0 | AA108: 1 | AB108: 0
A109: 50 | B109: 0 | C109: 0 | D109: 1 | E109: 204 | F109: =ROUND(Source!R95,O109) -> 0 | G109: ЗПМ | H109: ЗП машинистов | K109: 204 | L109: 13 | M109: 3 | O109: 2 | P109: =ROUND(Source!DJ95,O109) -> 0 | W109: 0 | X109: 1 | Y109: 0 | Z109: 0 | AA109: 1 | AB109: 0
A110: 50 | B110: 0 | C110: 0 | D110: 1 | E110: 205 | F110: =ROUND(Source!S95,O110) -> 0 | G110: ОЗП | H110: Основная ЗП рабочих | K110: 205 | L110: 14 | M110: 3 | O110: 2 | P110: =ROUND(Source!DK95,O110) -> 0 | W110: 0 | X110: 1 | Y110: 0 | Z110: 0 | AA110: 1 | AB110: 0
A111: 50 | B111: 0 | C111: 0 | D111: 1 | E111: 232 | F111: =ROUND(Source!BC95,O111) -> 0 | G111: ОЗПсНРиСП | H111: Основная ЗП рабочих по ТСН-2001.16 | K111: 232 | L111: 15 | M111: 3 | O111: 2 | P111: =ROUND(Source!EU95,O111) -> 0 | W111: 0 | X111: 1 | Y111: 0 | Z111: 0 | AA111: 1 | AB111: 0
A112: 50 | B112: 0 | C112: 0 | D112: 1 | E112: 214 | F112: =ROUND(Source!AS95,O112) -> 0 | G112: Строит | H112: Строительные работы с НР и СП | K112: 214 | L112: 16 | M112: 3 | O112: 2 | P112: =ROUND(Source!EK95,O112) -> 0 | W112: 0 | X112: 1 | Y112: 0 | Z112: 0 | AA112: 1 | AB112: 0
A113: 50 | B113: 0 | C113: 0 | D113: 1 | E113: 215 | F113: =ROUND(Source!AT95,O113) -> 0 | G113: Монтаж | H113: Монтажные работы с НР и СП | K113: 215 | L113: 17 | M113: 3 | O113: 2 | P113: =ROUND(Source!EL95,O113) -> 0 | W113: 0 | X113: 1 | Y113: 0 | Z113: 0 | AA113: 1 | AB113: 0
A114: 50 | B114: 0 | C114: 0 | D114: 1 | E114: 217 | F114: =ROUND(Source!AU95,O114) -> 96538.04 | G114: Прочие | H114: Прочие работы с НР и СП | K114: 217 | L114: 18 | M114: 3 | O114: 2 | P114: =ROUND(Source!EM95,O114) -> 961161.92 | W114: 96538.04 | X114: 1 | Y114: 96538.04 | Z114: 961161.92 | AA114: 1 | AB114: 961161.92
A115: 50 | B115: 0 | C115: 0 | D115: 1 | E115: 230 | F115: =ROUND(Source!BA95,O115) -> 0 | G115: ПрочиеЗатр | H115: Прочие затраты по ТСН-2001.16 | K115: 230 | L115: 19 | M115: 3 | O115: 2 | P115: =ROUND(Source!ES95,O115) -> 0 | W115: 0 | X115: 1 | Y115: 0 | Z115: 0 | AA115: 1 | AB115: 0
A116: 50 | B116: 0 | C116: 0 | D116: 1 | E116: 206 | F116: =ROUND(Source!T95,O116) -> 0 | G116: ВозврМат | H116: Возврат материалов | K116: 206 | L116: 20 | M116: 3 | O116: 2 | P116: =ROUND(Source!DL95,O116) -> 0 | W116: 0 | X116: 1 | Y116: 0 | Z116: 0 | AA116: 1 | AB116: 0
A117: 50 | B117: 0 | C117: 0 | D117: 1 | E117: 207 | F117: =Source!U95 -> 0 | G117: ТрудСтр | H117: Трудозатраты строителей | K117: 207 | L117: 21 | M117: 3 | O117: -1 | P117: =Source!DM95 -> 0 | W117: 0 | X117: 1 | Y117: 0 | Z117: 0 | AA117: 1 | AB117: 0
A118: 50 | B118: 0 | C118: 0 | D118: 1 | E118: 208 | F118: =Source!V95 -> 0 | G118: ТрудМаш | H118: Трудозатраты машинистов | K118: 208 | L118: 22 | M118: 3 | O118: -1 | P118: =Source!DN95 -> 0 | W118: 0 | X118: 1 | Y118: 0 | Z118: 0 | AA118: 1 | AB118: 0
A119: 50 | B119: 0 | C119: 0 | D119: 1 | E119: 209 | F119: =ROUND(Source!W95,O119) -> 0 | G119: ТранспМат | H119: Транспорт материалов | K119: 209 | L119: 23 | M119: 3 | O119: 2 | P119: =ROUND(Source!DO95,O119) -> 0 | W119: 0 | X119: 1 | Y119: 0 | Z119: 0 | AA119: 1 | AB119: 0
A120: 50 | B120: 0 | C120: 0 | D120: 1 | E120: 233 | F120: =ROUND(Source!BD95,O120) -> 0 | G120: Перевозка | H120: Перевозка грузов | K120: 233 | L120: 24 | M120: 3 | O120: 2 | P120: =ROUND(Source!EV95,O120) -> 0 | W120: 0 | X120: 1 | Y120: 0 | Z120: 0 | AA120: 1 | AB120: 0
A121: 50 | B121: 0 | C121: 0 | D121: 1 | E121: 210 | F121: =ROUND(Source!X95,O121) -> 0 | G121: НР | H121: Накладные расходы | K121: 210 | L121: 25 | M121: 3 | O121: 2 | P121: =ROUND(Source!DP95,O121) -> 0 | W121: 0 | X121: 1 | Y121: 0 | Z121: 0 | AA121: 1 | AB121: 0
A122: 50 | B122: 0 | C122: 0 | D122: 1 | E122: 211 | F122: =ROUND(Source!Y95,O122) -> 0 | G122: СмПриб | H122: Сметная прибыль | K122: 211 | L122: 26 | M122: 3 | O122: 2 | P122: =ROUND(Source!DQ95,O122) -> 0 | W122: 0 | X122: 1 | Y122: 0 | Z122: 0 | AA122: 1 | AB122: 0
A123: 50 | B123: 0 | C123: 0 | D123: 1 | E123: 224 | F123: =ROUND(Source!AR95,O123) -> 96538.04 | G123: Всего | H123: Всего с НР и СП | K123: 224 | L123: 27 | M123: 3 | O123: 2 | P123: =ROUND(Source!EJ95,O123) -> 961161.92 | W123: 96538.04 | X123: 1 | Y123: 96538.04 | Z123: 961161.92 | AA123: 1 | AB123: 961161.92
A125: 51 | B125: =B12 -> 165 | C125: =A12 -> 1 | D125: =ROW(A12) -> 12 | F125: =IF(F12<>"",F12,"") -> 09-01-03 | G125: =IF(G12<>"",G12,"") -> 09-01-03 Размещение и содержание строительного мусора | H125: 0 | O125: =ROUND(O95,2) -> 96538.04 | P125: =ROUND(P95,2) -> 0 | Q125: =ROUND(Q95,2) -> 96538.04 | R125: =ROUND(R95,2) -> 0 | S125: =ROUND(S95,2) -> 0 | T125: =ROUND(T95,2) -> 0 | U125: =U95 -> 0 | V125: =V95 -> 0 | W125: =ROUND(W95,2) -> 0 | X125: =ROUND(X95,2) -> 0 | Y125: =ROUND(Y95,2) -> 0 | AO125: =ROUND(AO95,2) -> 0 | AP125: =ROUND(AP95,2) -> 0 | AQ125: =ROUND(AQ95,2) -> 0 | AR125: =ROUND(AR95,2) -> 96538.04 | AS125: =ROUND(AS95,2) -> 0 | AT125: =ROUND(AT95,2) -> 0 | AU125: =ROUND(AU95,2) -> 96538.04 | AV125: =ROUND(AV95,2) -> 0 | ... BD125: =ROUND(BD95,2) -> 0 | DG125: =ROUND(DG95,2) -> 961161.92 | DH125: =ROUND(DH95,2) -> 0 | DI125: =ROUND(DI95,2) -> 961161.92 | DJ125: =ROUND(DJ95,2) -> 0 | DK125: =ROUND(DK95,2) -> 0 | DL125: =ROUND(DL95,2) -> 0 | DM125: =DM95 -> 0 | DN125: =DN95 -> 0 | DO125: =ROUND(DO95,2) -> 0 | DP125: =ROUND(DP95,2) -> 0 | DQ125: =ROUND(DQ95,2) -> 0 | EG125: =ROUND(EG95,2) -> 0 | EH125: =ROUND(EH95,2) -> 0 | EI125: =ROUND(EI95,2) -> 0 | EJ125: =ROUND(EJ95,2) -> 961161.92 | EK125: =ROUND(EK95,2) -> 0 | EL125: =ROUND(EL95,2) -> 0 | EM125: =ROUND(EM95,2) -> 961161.92 | EN125: =ROUND(EN95,2) -> 0 | ... EV125: =ROUND(EV95,2) -> 0 | GX125: 0
A127: 50 | B127: 0 | C127: 0 | D127: 1 | E127: 201 | F127: =ROUND(Source!O125,O127) -> 96538.04 | G127: ПЗ | H127: Прямые затраты | K127: 201 | L127: 1 | M127: 3 | O127: 2 | P127: =ROUND(Source!DG125,O127) -> 961161.92 | W127: 96538.04 | X127: 1 | Y127: 96538.04 | Z127: 961161.92 | AA127: 1 | AB127: 961161.92
A128: 50 | B128: 0 | C128: 0 | D128: 1 | E128: 202 | F128: =ROUND(Source!P125,O128) -> 0 | G128: СтМатОб | H128: Стоимость материальных ресурсов (всего) | K128: 202 | L128: 2 | M128: 3 | O128: 2 | P128: =ROUND(Source!DH125,O128) -> 0 | W128: 0 | X128: 1 | Y128: 0 | Z128: 0 | AA128: 1 | AB128: 0
A129: 50 | B129: 0 | C129: 0 | D129: 1 | E129: 222 | F129: =ROUND(Source!AO125,O129) -> 0 | G129: СтМатОбЗак | H129: Стоимость материалов и оборудования заказчика | K129: 222 | L129: 3 | M129: 3 | O129: 2 | P129: =ROUND(Source!EG125,O129) -> 0 | W129: 0 | X129: 1 | Y129: 0 | Z129: 0 | AA129: 1 | AB129: 0
A130: 50 | B130: 0 | C130: 0 | D130: 1 | E130: 225 | F130: =ROUND(Source!AV125,O130) -> 0 | G130: СтМатОбПод | H130: Стоимость материалов и оборудования подрядчика | K130: 225 | L130: 4 | M130: 3 | O130: 2 | P130: =ROUND(Source!EN125,O130) -> 0 | W130: 0 | X130: 1 | Y130: 0 | Z130: 0 | AA130: 1 | AB130: 0
A131: 50 | B131: 0 | C131: 0 | D131: 1 | E131: 226 | F131: =ROUND(Source!AW125,O131) -> 0 | G131: СтМат | H131: Стоимость материалов (всего) | K131: 226 | L131: 5 | M131: 3 | O131: 2 | P131: =ROUND(Source!EO125,O131) -> 0 | W131: 0 | X131: 1 | Y131: 0 | Z131: 0 | AA131: 1 | AB131: 0
A132: 50 | B132: 0 | C132: 0 | D132: 1 | E132: 227 | F132: =ROUND(Source!AX125,O132) -> 0 | G132: СтМатЗак | H132: Стоимость материалов заказчика | K132: 227 | L132: 6 | M132: 3 | O132: 2 | P132: =ROUND(Source!EP125,O132) -> 0 | W132: 0 | X132: 1 | Y132: 0 | Z132: 0 | AA132: 1 | AB132: 0
A133: 50 | B133: 0 | C133: 0 | D133: 1 | E133: 228 | F133: =ROUND(Source!AY125,O133) -> 0 | G133: СтМатПод | H133: Стоимость материалов подрядчика | K133: 228 | L133: 7 | M133: 3 | O133: 2 | P133: =ROUND(Source!EQ125,O133) -> 0 | W133: 0 | X133: 1 | Y133: 0 | Z133: 0 | AA133: 1 | AB133: 0
A134: 50 | B134: 0 | C134: 0 | D134: 1 | E134: 216 | F134: =ROUND(Source!AP125,O134) -> 0 | G134: Оборуд | H134: Стоимость оборудования (всего) | K134: 216 | L134: 8 | M134: 3 | O134: 2 | P134: =ROUND(Source!EH125,O134) -> 0 | W134: 0 | X134: 1 | Y134: 0 | Z134: 0 | AA134: 1 | AB134: 0
A135: 50 | B135: 0 | C135: 0 | D135: 1 | E135: 223 | F135: =ROUND(Source!AQ125,O135) -> 0 | G135: ОборудЗак | H135: Стоимость оборудования заказчика | K135: 223 | L135: 9 | M135: 3 | O135: 2 | P135: =ROUND(Source!EI125,O135) -> 0 | W135: 0 | X135: 1 | Y135: 0 | Z135: 0 | AA135: 1 | AB135: 0
A136: 50 | B136: 0 | C136: 0 | D136: 1 | E136: 229 | F136: =ROUND(Source!AZ125,O136) -> 0 | G136: ОборудПод | H136: Стоимость оборудования подрядчика | K136: 229 | L136: 10 | M136: 3 | O136: 2 | P136: =ROUND(Source!ER125,O136) -> 0 | W136: 0 | X136: 1 | Y136: 0 | Z136: 0 | AA136: 1 | AB136: 0
A137: 50 | B137: 0 | C137: 0 | D137: 1 | E137: 203 | F137: =ROUND(Source!Q125,O137) -> 96538.04 | G137: ЭММ | H137: Эксплуатация машин | K137: 203 | L137: 11 | M137: 3 | O137: 2 | P137: =ROUND(Source!DI125,O137) -> 961161.92 | W137: 96538.04 | X137: 1 | Y137: 96538.04 | Z137: 961161.92 | AA137: 1 | AB137: 961161.92
A138: 50 | B138: 0 | C138: 0 | D138: 1 | E138: 231 | F138: =ROUND(Source!BB125,O138) -> 0 | G138: ЭММсНРиСП | H138: Эксплуатация машин по ТСН-2001.16 | K138: 231 | L138: 12 | M138: 3 | O138: 2 | P138: =ROUND(Source!ET125,O138) -> 0 | W138: 0 | X138: 1 | Y138: 0 | Z138: 0 | AA138: 1 | AB138: 0
A139: 50 | B139: 0 | C139: 0 | D139: 1 | E139: 204 | F139: =ROUND(Source!R125,O139) -> 0 | G139: ЗПМ | H139: ЗП машинистов | K139: 204 | L139: 13 | M139: 3 | O139: 2 | P139: =ROUND(Source!DJ125,O139) -> 0 | W139: 0 | X139: 1 | Y139: 0 | Z139: 0 | AA139: 1 | AB139: 0
A140: 50 | B140: 0 | C140: 0 | D140: 1 | E140: 205 | F140: =ROUND(Source!S125,O140) -> 0 | G140: ОЗП | H140: Основная ЗП рабочих | K140: 205 | L140: 14 | M140: 3 | O140: 2 | P140: =ROUND(Source!DK125,O140) -> 0 | W140: 0 | X140: 1 | Y140: 0 | Z140: 0 | AA140: 1 | AB140: 0
A141: 50 | B141: 0 | C141: 0 | D141: 1 | E141: 232 | F141: =ROUND(Source!BC125,O141) -> 0 | G141: ОЗПсНРиСП | H141: Основная ЗП рабочих по ТСН-2001.16 | K141: 232 | L141: 15 | M141: 3 | O141: 2 | P141: =ROUND(Source!EU125,O141) -> 0 | W141: 0 | X141: 1 | Y141: 0 | Z141: 0 | AA141: 1 | AB141: 0
A142: 50 | B142: 0 | C142: 0 | D142: 1 | E142: 214 | F142: =ROUND(Source!AS125,O142) -> 0 | G142: Строит | H142: Строительные работы с НР и СП | K142: 214 | L142: 16 | M142: 3 | O142: 2 | P142: =ROUND(Source!EK125,O142) -> 0 | W142: 0 | X142: 1 | Y142: 0 | Z142: 0 | AA142: 1 | AB142: 0
A143: 50 | B143: 0 | C143: 0 | D143: 1 | E143: 215 | F143: =ROUND(Source!AT125,O143) -> 0 | G143: Монтаж | H143: Монтажные работы с НР и СП | K143: 215 | L143: 17 | M143: 3 | O143: 2 | P143: =ROUND(Source!EL125,O143) -> 0 | W143: 0 | X143: 1 | Y143: 0 | Z143: 0 | AA143: 1 | AB143: 0
A144: 50 | B144: 0 | C144: 0 | D144: 1 | E144: 217 | F144: =ROUND(Source!AU125,O144) -> 96538.04 | G144: Прочие | H144: Прочие работы с НР и СП | K144: 217 | L144: 18 | M144: 3 | O144: 2 | P144: =ROUND(Source!EM125,O144) -> 961161.92 | W144: 96538.04 | X144: 1 | Y144: 96538.04 | Z144: 961161.92 | AA144: 1 | AB144: 961161.92
A145: 50 | B145: 0 | C145: 0 | D145: 1 | E145: 230 | F145: =ROUND(Source!BA125,O145) -> 0 | G145: ПрочиеЗатр | H145: Прочие затраты по ТСН-2001.16 | K145: 230 | L145: 19 | M145: 3 | O145: 2 | P145: =ROUND(Source!ES125,O145) -> 0 | W145: 0 | X145: 1 | Y145: 0 | Z145: 0 | AA145: 1 | AB145: 0
A146: 50 | B146: 0 | C146: 0 | D146: 1 | E146: 206 | F146: =ROUND(Source!T125,O146) -> 0 | G146: ВозврМат | H146: Возврат материалов | K146: 206 | L146: 20 | M146: 3 | O146: 2 | P146: =ROUND(Source!DL125,O146) -> 0 | W146: 0 | X146: 1 | Y146: 0 | Z146: 0 | AA146: 1 | AB146: 0
A147: 50 | B147: 0 | C147: 0 | D147: 1 | E147: 207 | F147: =Source!U125 -> 0 | G147: ТрудСтр | H147: Трудозатраты строителей | K147: 207 | L147: 21 | M147: 3 | O147: -1 | P147: =Source!DM125 -> 0 | W147: 0 | X147: 1 | Y147: 0 | Z147: 0 | AA147: 1 | AB147: 0
...

Sheet SourceObSm
A1: 0 | B1: Smeta.RU (495) 974-1589 | D1: _OBSM_ | F1: 0 | G1: 0 | H1: 0 | I1: Smeta.RU | K1: 1 | L1: 74562 | M1: 10 | N1: 11 | O1: 14 | P1: 0 | Q1: 0
A4: 1 | B4: 1 | C4: -1 | G4: Капитальный ремонт здания Государственного бюджетного общеобразовательного учреждения города Москвы «Школа № 236» по адресу: г. Москва, ул. Клязьминская, д. 7, к. 4. I этап | EC4: 0
A12: 1 | B12: 51 | C12: 0 | E12: 0 | F12: 09-01-03 | G12: 09-01-03 Размещение и содержание строительного мусора | I12: 0 | J12: 0224-00272-01-0-ООС2 | K12: 0 | L12: 0 | M12: 4098 | O12: 0 | P12: 0 | Q12: 0 | R12: 0 | S12: 0 | T12: 1 | V12: 0 | AB12: Лукьянова А.Л. | BB12: 0 | BH12: Сметные нормы списания | BI12: Коды ОКП для ТСН-2001 МГЭ Дополнение 79 | BJ12: 1 | BK12: 1 | BL12: 0 | BM12: 0 | BN12: 1 | BO12: 0 | BP12: 6 | BQ12: 2 | BR12: 1 | BS12: 1 | BT12: 0 | BU12: 0 | BV12: 0 | BW12: 0 | BX12: 0 | BY12: ТСН-2001 (МГЭ) Доп 79 - Ремонт | BZ12: Типовой расчет для ТСН-2001 МГЭ, Дополнение 79, ремонт | CA12: Территориальные сметные нормативы для Москвы ТСН-2001 (МГЭ), дополнение 79 | CB12: Территориальные сметные нормативы для Москвы ТСН-2001 (МГЭ), дополнение 79 | CC12: Территориальные сметные нормативы для Москвы ТСН-2001 (МГЭ), дополнение 79 | CD12: Территориальные сметные нормативы для Москвы ТСН-2001 (МГЭ), дополнение 79 | CE12: Поправки для ТСН-2001 от 03.10.2025 г. доп.79 | CF12: 0 | CG12: 0 | CH12: 8200 | CK12: 79 | CQ12: Территориальные сметные нормативы для Москвы (ТСН-2001) | CR12: ТЕР | CS12: 41660 | CT12: 1 | CU12: 79 | CY12: 0 | EC12: 0
A14: 22 | B14: 1 | C14: 0 | D14: 56526441 | E14: 56526439 | F14: 2 | G14: 1
A16: 3 | B16: 1 | C16: 09-01-03 | D16: Размещение и содержание строительного мусора | E16: =ROUND((Source!P112)/1000,2) -> 0 | F16: =ROUND((Source!P113)/1000,2) -> 0 | G16: =ROUND((Source!P104)/1000,2) -> 0 | H16: =ROUND((Source!P114)/1000+(Source!P115)/1000,2) -> 961.16 | I16: =E16+F16+G16+H16 -> 961.16 | J16: =ROUND((Source!P110+Source!P109)/1000,2) -> 0 | K16: 961.16 | L16: 0 | M16: 0 | N16: =I16+L16+M16 -> 961.16 | T16: =ROUND((Source!F112)/1000,2) -> 0 | U16: =ROUND((Source!F113)/1000,2) -> 0 | V16: =ROUND((Source!F104)/1000,2) -> 0 | W16: =ROUND((Source!F114)/1000+(Source!F115)/1000,2) -> 96.54 | X16: =T16+U16+V16+W16 -> 96.54 | Y16: =ROUND((Source!F110+Source!F109)/1000,2) -> 0 | Z16: 96.54 | AA16: 0 | AB16: 0 | AC16: =X16+AA16+AB16 -> 96.54 | AI16: 0 | AJ16: -1 | AN16: 0 | AT16: 961161.92 | AU16: 0 | AV16: 0 | AW16: 0 | AX16: 0 | AY16: 961161.92 | AZ16: 0 | BA16: 0 | BB16: 0 | BC16: 0 | BD16: 961161.92 | BE16: 0 | BF16: 0 | BG16: 0 | BH16: 0 | BI16: 0 | BJ16: 0 | BK16: 961161.92 | BR16: 96538.04 | BS16: 0 | BT16: 0 | BU16: 0 | BV16: 0 | BW16: 96538.04 | BX16: 0 | BY16: 0 | BZ16: 0 | CA16: 0 | CB16: 96538.04 | CC16: 0 | CD16: 0 | CE16: 0 | CF16: 0 | CG16: 0 | CH16: 0 | CI16: 96538.04
A18: 51 | E18: 0 | F18: 0 | G18: 0 | H18: 961.16 | I18: 961.16 | J18: 0 | K18: 961.16 | L18: 0 | M18: 0 | N18: 961.16 | T18: 0 | U18: 0 | V18: 0 | W18: 96.54 | X18: 96.54 | Y18: 0 | Z18: 96.54 | AA18: 0 | AB18: 0 | AC18: 96.54
A20: 50 | B20: 0 | C20: 0 | D20: 1 | E20: 201 | F20: 961161.92 | G20: ПЗ | H20: Прямые затраты | K20: 201 | L20: 1 | M20: 3 | O20: 2 | P20: 96538.04
A21: 50 | B21: 0 | C21: 0 | D21: 1 | E21: 202 | F21: 0 | G21: СтМатОб | H21: Стоимость материальных ресурсов (всего) | K21: 202 | L21: 2 | M21: 3 | O21: 2 | P21: 0
A22: 50 | B22: 0 | C22: 0 | D22: 1 | E22: 222 | F22: 0 | G22: СтМатОбЗак | H22: Стоимость материалов и оборудования заказчика | K22: 222 | L22: 3 | M22: 3 | O22: 2 | P22: 0
A23: 50 | B23: 0 | C23: 0 | D23: 1 | E23: 225 | F23: 0 | G23: СтМатОбПод | H23: Стоимость материалов и оборудования подрядчика | K23: 225 | L23: 4 | M23: 3 | O23: 2 | P23: 0
A24: 50 | B24: 0 | C24: 0 | D24: 1 | E24: 226 | F24: 0 | G24: СтМат | H24: Стоимость материалов (всего) | K24: 226 | L24: 5 | M24: 3 | O24: 2 | P24: 0
A25: 50 | B25: 0 | C25: 0 | D25: 1 | E25: 227 | F25: 0 | G25: СтМатЗак | H25: Стоимость материалов заказчика | K25: 227 | L25: 6 | M25: 3 | O25: 2 | P25: 0
A26: 50 | B26: 0 | C26: 0 | D26: 1 | E26: 228 | F26: 0 | G26: СтМатПод | H26: Стоимость материалов подрядчика | K26: 228 | L26: 7 | M26: 3 | O26: 2 | P26: 0
A27: 50 | B27: 0 | C27: 0 | D27: 1 | E27: 216 | F27: 0 | G27: Оборуд | H27: Стоимость оборудования (всего) | K27: 216 | L27: 8 | M27: 3 | O27: 2 | P27: 0
A28: 50 | B28: 0 | C28: 0 | D28: 1 | E28: 223 | F28: 0 | G28: ОборудЗак | H28: Стоимость оборудования заказчика | K28: 223 | L28: 9 | M28: 3 | O28: 2 | P28: 0
A29: 50 | B29: 0 | C29: 0 | D29: 1 | E29: 229 | F29: 0 | G29: ОборудПод | H29: Стоимость оборудования подрядчика | K29: 229 | L29: 10 | M29: 3 | O29: 2 | P29: 0
A30: 50 | B30: 0 | C30: 0 | D30: 1 | E30: 203 | F30: 961161.92 | G30: ЭММ | H30: Эксплуатация машин | K30: 203 | L30: 11 | M30: 3 | O30: 2 | P30: 96538.04
A31: 50 | B31: 0 | C31: 0 | D31: 1 | E31: 231 | F31: 0 | G31: ЭММсНРиСП | H31: Эксплуатация машин по ТСН-2001.16 | K31: 231 | L31: 12 | M31: 3 | O31: 2 | P31: 0
... A46: 50 | B46: 0 | C46: 0 | D46: 1 | E46: 224 | F46: 961161.92 | G46: Всего | H46: Всего с НР и СП | K46: 224 | L46: 27 | M46: 3 | O46: 2 | P46: 96538.04
A48: -1
A51: 75 | B51: Текущий уровень цен | C51: 2025 | D51: 0 | E51: 7 | G51: 0 | H51: 1 | I51: 1 | J51: 3 | K51: 0 | L51: 0 | M51: 1 | N51: 56526441 | O51: 1
A52: 1 | B52: Сборник индексов | C52: Коэффициенты к ТСН-2001 МГЭ Дополнение 79, ремонт | D52: 2025 | E52: 7 | F52: 1 | G52: 1 | H52: 0 | I52: 2 | J52: 1 | K52: 1 | L52: 1 | M52: 1 | N52: 1 | O52: 1 | P52: 1 | Q52: 1 | AA52: 216/79 | AN52: 56526442
A53: 1 | B53: Сборник индексов | C53: Коэффициенты к ТСН-2001.13-2 Дополнение 45 | D53: 2025 | E53: 7 | F53: 1 | G53: 1 | H53: 0 | I53: 2 | J53: 1 | K53: 1 | L53: 1 | M53: 1 | N53: 1 | O53: 1 | P53: 1 | Q53: 1 | AA53: 62/45 | AN53: 56526443
A54: 75 | B54: Базовый уровень цен | C54: 2000 | D54: 0 | E54: 1 | F54: 0 | G54: 0 | H54: 1 | I54: 1 | J54: 3 | K54: 0 | L54: 0 | M54: 0 | N54: 56526439 | O54: 2
A55: 1 | B55: Сборник индексов | C55: Коэффициенты к ТСН-2001 МГЭ Дополнение 79, ремонт | D55: 2000 | E55: 1 | F55: 1 | G55: 1 | H55: 0 | I55: 2 | J55: 1 | K55: 1 | L55: 1 | M55: 1 | N55: 1 | O55: 1 | P55: 1 | Q55: 1 | AN55: 56526440

Sheet SmtRes
A1: =ROW(Source!A28) -> 28 | B1: 56526439 | C1: 56526772 | D1: 54836954 | E1: 1079 | F1: 1 | G1: 1079 | H1: 2 | I1: 9999990007 | K1: Стоимость прочих машин (ЭСН) | L1: 1344 | N1: 1008 | O1: руб. | P1: руб. | Q1: 1 | W1: 0 | X1: -1180195794 | Y1: =AT1 -> 31.67 | AA1: 0 | AB1: 1 | AC1: 0 | AD1: 0 | AE1: 0 | AF1: 1 | AG1: 0 | AH1: 0 | AI1: 1 | AJ1: 1 | AK1: 1 | AL1: 1 | AM1: -2 | AN1: 0 | AO1: 1 | AP1: 1 | AQ1: 0 | AR1: 0 | AT1: 31.67 | AV1: 0 | AW1: 2 | AX1: 56526796 | AY1: 1 | AZ1: 0 | BA1: 1 | BB1: 0 | BC1: 0 | BD1: 0 | BE1: 0 | BF1: 0 | BG1: 0 | BH1: 0 | BI1: 0 | BJ1: 0 | BK1: 0 | BL1: 0 | BM1: 0 | BN1: 0 | BO1: 0 | BP1: 0 | BQ1: 0 | BR1: 0 | BS1: 0 | BT1: 0 | BU1: 0 | BV1: 0 | BW1: 0 | CV1: 0 | CW1: =ROUND(Y1*Source!I28*DO1,9) -> 0 | CX1: =ROUND(Y1*Source!I28,9) -> 2374.3949 | CY1: =AB1 -> 1 | CZ1: =AF1 -> 1 | DA1: =AJ1 -> 1 | DB1: =ROUND(ROUND(AT1*CZ1,2),6) -> 31.67 | DC1: =ROUND(ROUND(AT1*AG1,2),6) -> 0 | DF1: =ROUND(ROUND(AE1,2)*CX1,2) -> 0 | DG1: =ROUND(ROUND(AF1,2)*CX1,2) -> 2374.39 | DH1: =ROUND(ROUND(AG1,2)*CX1,2) -> 0 | DI1: =ROUND(ROUND(AH1,2)*CX1,2) -> 0 | DJ1: =DG1 -> 2374.39 | DK1: 0 | DM1: 0 | DO1: 0
A2: =ROW(Source!A29) -> 29 | B2: 56526441 | C2: 56526772 | D2: 54836954 | E2: 1079 | F2: 1 | G2: 1079 | H2: 2 | I2: 9999990007 | K2: Стоимость прочих машин (ЭСН) | L2: 1344 | N2: 1008 | O2: руб. | P2: руб. | Q2: 1 | W2: 0 | X2: -1180195794 | Y2: =AT2 -> 31.67 | AA2: 0 | AB2: 1 | AC2: 0 | AD2: 0 | AE2: 0 | AF2: 1 | AG2: 0 | AH2: 0 | AI2: 1 | AJ2: 1 | AK2: 1 | AL2: 1 | AM2: -2 | AN2: 0 | AO2: 1 | AP2: 1 | AQ2: 0 | AR2: 0 | AT2: 31.67 | AV2: 0 | AW2: 2 | AX2: 56526796 | AY2: 1 | AZ2: 0 | BA2: 2 | BB2: 0 | BC2: 0 | BD2: 0 | BE2: 0 | BF2: 0 | BG2: 0 | BH2: 0 | BI2: 0 | BJ2: 0 | BK2: 0 | BL2: 0 | BM2: 0 | BN2: 0 | BO2: 0 | BP2: 0 | BQ2: 0 | BR2: 0 | BS2: 0 | BT2: 0 | BU2: 0 | BV2: 0 | BW2: 0 | CV2: 0 | CW2: =ROUND(Y2*Source!I29*DO2,9) -> 0 | CX2: =ROUND(Y2*Source!I29,9) -> 2374.3949 | CY2: =AB2 -> 1 | CZ2: =AF2 -> 1 | DA2: =AJ2 -> 1 | DB2: =ROUND(ROUND(AT2*CZ2,2),6) -> 31.67 | DC2: =ROUND(ROUND(AT2*AG2,2),6) -> 0 | DF2: =ROUND(ROUND(AE2,2)*CX2,2) -> 0 | DG2: =ROUND(ROUND(AF2,2)*CX2,2) -> 2374.39 | DH2: =ROUND(ROUND(AG2,2)*CX2,2) -> 0 | DI2: =ROUND(ROUND(AH2,2)*CX2,2) -> 0 | DJ2: =DG2 -> 2374.39 | DK2: 0 | DM2: 0 | DO2: 0
A3: =ROW(Source!A30) -> 30 | B3: 56526439 | C3: 56526775 | D3: 54836954 | E3: 1079 | F3: 1 | G3: 1079 | H3: 2 | I3: 9999990007 | K3: Стоимость прочих машин (ЭСН) | L3: 1344 | N3: 1008 | O3: руб. | P3: руб. | Q3: 1 | W3: 0 | X3: -1180195794 | Y3: =AT3 -> 31.13 | AA3: 0 | AB3: 1 | AC3: 0 | AD3: 0 | AE3: 0 | AF3: 1 | AG3: 0 | AH3: 0 | AI3: 1 | AJ3: 1 | AK3: 1 | AL3: 1 | AM3: -2 | AN3: 0 | AO3: 1 | AP3: 1 | AQ3: 0 | AR3: 0 | AT3: 31.13 | AV3: 0 | AW3: 2 | AX3: 56526797 | AY3: 1 | AZ3: 0 | BA3: 3 | BB3: 0 | BC3: 0 | BD3: 0 | BE3: 0 | BF3: 0 | BG3: 0 | BH3: 0 | BI3: 0 | BJ3: 0 | BK3: 0 | BL3: 0 | BM3: 0 | BN3: 0 | BO3: 0 | BP3: 0 | BQ3: 0 | BR3: 0 | BS3: 0 | BT3: 0 | BU3: 0 | BV3: 0 | BW3: 0 | CV3: 0 | CW3: =ROUND(Y3*Source!I30*DO3,9) -> 0 | CX3: =ROUND(Y3*Source!I30,9) -> 48114.839 | CY3: =AB3 -> 1 | CZ3: =AF3 -> 1 | DA3: =AJ3 -> 1 | DB3: =ROUND(ROUND(AT3*CZ3,2),6) -> 31.13 | DC3: =ROUND(ROUND(AT3*AG3,2),6) -> 0 | DF3: =ROUND(ROUND(AE3,2)*CX3,2) -> 0 | DG3: =ROUND(ROUND(AF3,2)*CX3,2) -> 48114.84 | DH3: =ROUND(ROUND(AG3,2)*CX3,2) -> 0 | DI3: =ROUND(ROUND(AH3,2)*CX3,2) -> 0 | DJ3: =DG3 -> 48114.84 | DK3: 0 | DM3: 0 | DO3: 0
A4: =ROW(Source!A31) -> 31 | B4: 56526441 | C4: 56526775 | D4: 54836954 | E4: 1079 | F4: 1 | G4: 1079 | H4: 2 | I4: 9999990007 | K4: Стоимость прочих машин (ЭСН) | L4: 1344 | N4: 1008 | O4: руб. | P4: руб. | Q4: 1 | W4: 0 | X4: -1180195794 | Y4: =AT4 -> 31.13 | AA4: 0 | AB4: 1 | AC4: 0 | AD4: 0 | AE4: 0 | AF4: 1 | AG4: 0 | AH4: 0 | AI4: 1 | AJ4: 1 | AK4: 1 | AL4: 1 | AM4: -2 | AN4: 0 | AO4: 1 | AP4: 1 | AQ4: 0 | AR4: 0 | AT4: 31.13 | AV4: 0 | AW4: 2 | AX4: 56526797 | AY4: 1 | AZ4: 0 | BA4: 4 | BB4: 0 | BC4: 0 | BD4: 0 | BE4: 0 | BF4: 0 | BG4: 0 | BH4: 0 | BI4: 0 | BJ4: 0 | BK4: 0 | BL4: 0 | BM4: 0 | BN4: 0 | BO4: 0 | BP4: 0 | BQ4: 0 | BR4: 0 | BS4: 0 | BT4: 0 | BU4: 0 | BV4: 0 | BW4: 0 | CV4: 0 | CW4: =ROUND(Y4*Source!I31*DO4,9) -> 0 | CX4: =ROUND(Y4*Source!I31,9) -> 48114.839 | CY4: =AB4 -> 1 | CZ4: =AF4 -> 1 | DA4: =AJ4 -> 1 | DB4: =ROUND(ROUND(AT4*CZ4,2),6) -> 31.13 | DC4: =ROUND(ROUND(AT4*AG4,2),6) -> 0 | DF4: =ROUND(ROUND(AE4,2)*CX4,2) -> 0 | DG4: =ROUND(ROUND(AF4,2)*CX4,2) -> 48114.84 | DH4: =ROUND(ROUND(AG4,2)*CX4,2) -> 0 | DI4: =ROUND(ROUND(AH4,2)*CX4,2) -> 0 | DJ4: =DG4 -> 48114.84 | DK4: 0 | DM4: 0 | DO4: 0
A5: =ROW(Source!A32) -> 32 | B5: 56526439 | C5: 56526778 | D5: 54836954 | E5: 1079 | F5: 1 | G5: 1079 | H5: 2 | I5: 9999990007 | K5: Стоимость прочих машин (ЭСН) | L5: 1344 | N5: 1008 | O5: руб. | P5: руб. | Q5: 1 | W5: 0 | X5: -1180195794 | Y5: =AT5 -> 36.59 | AA5: 0 | AB5: 1 | AC5: 0 | AD5: 0 | AE5: 0 | AF5: 1 | AG5: 0 | AH5: 0 | AI5: 1 | AJ5: 1 | AK5: 1 | AL5: 1 | AM5: -2 | AN5: 0 | AO5: 1 | AP5: 1 | AQ5: 0 | AR5: 0 | AT5: 36.59 | AV5: 0 | AW5: 2 | AX5: 56526798 | AY5: 1 | AZ5: 0 | BA5: 5 | BB5: 0 | BC5: 0 | BD5: 0 | BE5: 0 | BF5: 0 | BG5: 0 | BH5: 0 | BI5: 0 | BJ5: 0 | BK5: 0 | BL5: 0 | BM5: 0 | BN5: 0 | BO5: 0 | BP5: 0 | BQ5: 0 | BR5: 0 | BS5: 0 | BT5: 0 | BU5: 0 | BV5: 0 | BW5: 0 | CV5: 0 | CW5: =ROUND(Y5*Source!I32*DO5,9) -> 0 | CX5: =ROUND(Y5*Source!I32,9) -> 7163.2243 | CY5: =AB5 -> 1 | CZ5: =AF5 -> 1 | DA5: =AJ5 -> 1 | DB5: =ROUND(ROUND(AT5*CZ5,2),6) -> 36.59 | DC5: =ROUND(ROUND(AT5*AG5,2),6) -> 0 | DF5: =ROUND(ROUND(AE5,2)*CX5,2) -> 0 | DG5: =ROUND(ROUND(AF5,2)*CX5,2) -> 7163.22 | DH5: =ROUND(ROUND(AG5,2)*CX5,2) -> 0 | DI5: =ROUND(ROUND(AH5,2)*CX5,2) -> 0 | DJ5: =DG5 -> 7163.22 | DK5: 0 | DM5: 0 | DO5: 0
A6: =ROW(Source!A33) -> 33 | B6: 56526441 | C6: 56526778 | D6: 54836954 | E6: 1079 | F6: 1 | G6: 1079 | H6: 2 | I6: 9999990007 | K6: Стоимость прочих машин (ЭСН) | L6: 1344 | N6: 1008 | O6: руб. | P6: руб. | Q6: 1 | W6: 0 | X6: -1180195794 | Y6: =AT6 -> 36.59 | AA6: 0 | AB6: 1 | AC6: 0 | AD6: 0 | AE6: 0 | AF6: 1 | AG6: 0 | AH6: 0 | AI6: 1 | AJ6: 1 | AK6: 1 | AL6: 1 | AM6: -2 | AN6: 0 | AO6: 1 | AP6: 1 | AQ6: 0 | AR6: 0 | AT6: 36.59 | AV6: 0 | AW6: 2 | AX6: 56526798 | AY6: 1 | AZ6: 0 | BA6: 6 | BB6: 0 | BC6: 0 | BD6: 0 | BE6: 0 | BF6: 0 | BG6: 0 | BH6: 0 | BI6: 0 | BJ6: 0 | BK6: 0 | BL6: 0 | BM6: 0 | BN6: 0 | BO6: 0 | BP6: 0 | BQ6: 0 | BR6: 0 | BS6: 0 | BT6: 0 | BU6: 0 | BV6: 0 | BW6: 0 | CV6: 0 | CW6: =ROUND(Y6*Source!I33*DO6,9) -> 0 | CX6: =ROUND(Y6*Source!I33,9) -> 7163.2243 | CY6: =AB6 -> 1 | CZ6: =AF6 -> 1 | DA6: =AJ6 -> 1 | DB6: =ROUND(ROUND(AT6*CZ6,2),6) -> 36.59 | DC6: =ROUND(ROUND(AT6*AG6,2),6) -> 0 | DF6: =ROUND(ROUND(AE6,2)*CX6,2) -> 0 | DG6: =ROUND(ROUND(AF6,2)*CX6,2) -> 7163.22 | DH6: =ROUND(ROUND(AG6,2)*CX6,2) -> 0 | DI6: =ROUND(ROUND(AH6,2)*CX6,2) -> 0 | DJ6: =DG6 -> 7163.22 | DK6: 0 | DM6: 0 | DO6: 0
A7: =ROW(Source!A34) -> 34 | B7: 56526439 | C7: 56526781 | D7: 54836954 | E7: 1079 | F7: 1 | G7: 1079 | H7: 2 | I7: 9999990007 | K7: Стоимость прочих машин (ЭСН) | L7: 1344 | N7: 1008 | O7: руб. | P7: руб. | Q7: 1 | W7: 0 | X7: -1180195794 | Y7: =AT7 -> 98.3 | AA7: 0 | AB7: 1 | AC7: 0 | AD7: 0 | AE7: 0 | AF7: 1 | AG7: 0 | AH7: 0 | AI7: 1 | AJ7: 1 | AK7: 1 | AL7: 1 | AM7: -2 | AN7: 0 | AO7: 1 | AP7: 1 | AQ7: 0 | AR7: 0 | AT7: 98.3 | AV7: 0 | AW7: 2 | AX7: 56526799 | AY7: 1 | AZ7: 0 | BA7: 7 | BB7: 0 | BC7: 0 | BD7: 0 | BE7: 0 | BF7: 0 | BG7: 0 | BH7: 0 | BI7: 0 | BJ7: 0 | BK7: 0 | BL7: 0 | BM7: 0 | BN7: 0 | BO7: 0 | BP7: 0 | BQ7: 0 | BR7: 0 | BS7: 0 | BT7: 0 | BU7: 0 | BV7: 0 | BW7: 0 | CV7: 0 | CW7: =ROUND(Y7*Source!I34*DO7,9) -> 0 | CX7: =ROUND(Y7*Source!I34,9) -> 417.5784 | CY7: =AB7 -> 1 | CZ7: =AF7 -> 1 | DA7: =AJ7 -> 1 | DB7: =ROUND(ROUND(AT7*CZ7,2),6) -> 98.3 | DC7: =ROUND(ROUND(AT7*AG7,2),6) -> 0 | DF7: =ROUND(ROUND(AE7,2)*CX7,2) -> 0 | DG7: =ROUND(ROUND(AF7,2)*CX7,2) -> 417.58 | DH7: =ROUND(ROUND(AG7,2)*CX7,2) -> 0 | DI7: =ROUND(ROUND(AH7,2)*CX7,2) -> 0 | DJ7: =DG7 -> 417.58 | DK7: 0 | DM7: 0 | DO7: 0
A8: =ROW(Source!A35) -> 35 | B8: 56526441 | C8: 56526781 | D8: 54836954 | E8: 1079 | F8: 1 | G8: 1079 | H8: 2 | I8: 9999990007 | K8: Стоимость прочих машин (ЭСН) | L8: 1344 | N8: 1008 | O8: руб. | P8: руб. | Q8: 1 | W8: 0 | X8: -1180195794 | Y8: =AT8 -> 98.3 | AA8: 0 | AB8: 1 | AC8: 0 | AD8: 0 | AE8: 0 | AF8: 1 | AG8: 0 | AH8: 0 | AI8: 1 | AJ8: 1 | AK8: 1 | AL8: 1 | AM8: -2 | AN8: 0 | AO8: 1 | AP8: 1 | AQ8: 0 | AR8: 0 | AT8: 98.3 | AV8: 0 | AW8: 2 | AX8: 56526799 | AY8: 1 | AZ8: 0 | BA8: 8 | BB8: 0 | BC8: 0 | BD8: 0 | BE8: 0 | BF8: 0 | BG8: 0 | BH8: 0 | BI8: 0 | BJ8: 0 | BK8: 0 | BL8: 0 | BM8: 0 | BN8: 0 | BO8: 0 | BP8: 0 | BQ8: 0 | BR8: 0 | BS8: 0 | BT8: 0 | BU8: 0 | BV8: 0 | BW8: 0 | CV8: 0 | CW8: =ROUND(Y8*Source!I35*DO8,9) -> 0 | CX8: =ROUND(Y8*Source!I35,9) -> 417.5784 | CY8: =AB8 -> 1 | CZ8: =AF8 -> 1 | DA8: =AJ8 -> 1 | DB8: =ROUND(ROUND(AT8*CZ8,2),6) -> 98.3 | DC8: =ROUND(ROUND(AT8*AG8,2),6) -> 0 | DF8: =ROUND(ROUND(AE8,2)*CX8,2) -> 0 | DG8: =ROUND(ROUND(AF8,2)*CX8,2) -> 417.58 | DH8: =ROUND(ROUND(AG8,2)*CX8,2) -> 0 | DI8: =ROUND(ROUND(AH8,2)*CX8,2) -> 0 | DJ8: =DG8 -> 417.58 | DK8: 0 | DM8: 0 | DO8: 0
A9: =ROW(Source!A36) -> 36 | B9: 56526439 | C9: 56526784 | D9: 54836954 | E9: 1079 | F9: 1 | G9: 1079 | H9: 2 | I9: 9999990007 | K9: Стоимость прочих машин (ЭСН) | L9: 1344 | N9: 1008 | O9: руб. | P9: руб. | Q9: 1 | W9: 0 | X9: -1180195794 | Y9: =AT9 -> 38.77 | AA9: 0 | AB9: 1 | AC9: 0 | AD9: 0 | AE9: 0 | AF9: 1 | AG9: 0 | AH9: 0 | AI9: 1 | AJ9: 1 | AK9: 1 | AL9: 1 | AM9: -2 | AN9: 0 | AO9: 1 | AP9: 1 | AQ9: 0 | AR9: 0 | AT9: 38.77 | AV9: 0 | AW9: 2 | AX9: 56526800 | AY9: 1 | AZ9: 0 | BA9: 9 | BB9: 0 | BC9: 0 | BD9: 0 | BE9: 0 | BF9: 0 | BG9: 0 | BH9: 0 | BI9: 0 | BJ9: 0 | BK9: 0 | BL9: 0 | BM9: 0 | BN9: 0 | BO9: 0 | BP9: 0 | BQ9: 0 | BR9: 0 | BS9: 0 | BT9: 0 | BU9: 0 | BV9: 0 | BW9: 0 | CV9: 0 | CW9: =ROUND(Y9*Source!I36*DO9,9) -> 0 | CX9: =ROUND(Y9*Source!I36,9) -> 1.35695 | CY9: =AB9 -> 1 | CZ9: =AF9 -> 1 | DA9: =AJ9 -> 1 | DB9: =ROUND(ROUND(AT9*CZ9,2),6) -> 38.77 | DC9: =ROUND(ROUND(AT9*AG9,2),6) -> 0 | DF9: =ROUND(ROUND(AE9,2)*CX9,2) -> 0 | DG9: =ROUND(ROUND(AF9,2)*CX9,2) -> 1.36 | DH9: =ROUND(ROUND(AG9,2)*CX9,2) -> 0 | DI9: =ROUND(ROUND(AH9,2)*CX9,2) -> 0 | DJ9: =DG9 -> 1.36 | DK9: 0 | DM9: 0 | DO9: 0
A10: =ROW(Source!A37) -> 37 | B10: 56526441 | C10: 56526784 | D10: 54836954 | E10: 1079 | F10: 1 | G10: 1079 | H10: 2 | I10: 9999990007 | K10: Стоимость прочих машин (ЭСН) | L10: 1344 | N10: 1008 | O10: руб. | P10: руб. | Q10: 1 | W10: 0 | X10: -1180195794 | Y10: =AT10 -> 38.77 | AA10: 0 | AB10: 1 | AC10: 0 | AD10: 0 | AE10: 0 | AF10: 1 | AG10: 0 | AH10: 0 | AI10: 1 | AJ10: 1 | AK10: 1 | AL10: 1 | AM10: -2 | AN10: 0 | AO10: 1 | AP10: 1 | AQ10: 0 | AR10: 0 | AT10: 38.77 | AV10: 0 | AW10: 2 | AX10: 56526800 | AY10: 1 | AZ10: 0 | BA10: 10 | BB10: 0 | BC10: 0 | BD10: 0 | BE10: 0 | BF10: 0 | BG10: 0 | BH10: 0 | BI10: 0 | BJ10: 0 | BK10: 0 | BL10: 0 | BM10: 0 | BN10: 0 | BO10: 0 | BP10: 0 | BQ10: 0 | BR10: 0 | BS10: 0 | BT10: 0 | BU10: 0 | BV10: 0 | BW10: 0 | CV10: 0 | CW10: =ROUND(Y10*Source!I37*DO10,9) -> 0 | CX10: =ROUND(Y10*Source!I37,9) -> 1.35695 | CY10: =AB10 -> 1 | CZ10: =AF10 -> 1 | DA10: =AJ10 -> 1 | DB10: =ROUND(ROUND(AT10*CZ10,2),6) -> 38.77 | DC10: =ROUND(ROUND(AT10*AG10,2),6) -> 0 | DF10: =ROUND(ROUND(AE10,2)*CX10,2) -> 0 | DG10: =ROUND(ROUND(AF10,2)*CX10,2) -> 1.36 | DH10: =ROUND(ROUND(AG10,2)*CX10,2) -> 0 | DI10: =ROUND(ROUND(AH10,2)*CX10,2) -> 0 | DJ10: =DG10 -> 1.36 | DK10: 0 | DM10: 0 | DO10: 0
A11: =ROW(Source!A38) -> 38 | B11: 56526439 | C11: 56526787 | D11: 54836954 | E11: 1079 | F11: 1 | G11: 1079 | H11: 2 | I11: 9999990007 | K11: Стоимость прочих машин (ЭСН) | L11: 1344 | N11: 1008 | O11: руб. | P11: руб. | Q11: 1 | W11: 0 | X11: -1180195794 | Y11: =AT11 -> 38.77 | AA11: 0 | AB11: 1 | AC11: 0 | AD11: 0 | AE11: 0 | AF11: 1 | AG11: 0 | AH11: 0 | AI11: 1 | AJ11: 1 | AK11: 1 | AL11: 1 | AM11: -2 | AN11: 0 | AO11: 1 | AP11: 1 | AQ11: 0 | AR11: 0 | AT11: 38.77 | AV11: 0 | AW11: 2 | AX11: 56526801 | AY11: 1 | AZ11: 0 | BA11: 11 | BB11: 0 | BC11: 0 | BD11: 0 | BE11: 0 | BF11: 0 | BG11: 0 | BH11: 0 | BI11: 0 | BJ11: 0 | BK11: 0 | BL11: 0 | BM11: 0 | BN11: 0 | BO11: 0 | BP11: 0 | BQ11: 0 | BR11: 0 | BS11: 0 | BT11: 0 | BU11: 0 | BV11: 0 | BW11: 0 | CV11: 0 | CW11: =ROUND(Y11*Source!I38*DO11,9) -> 0 | CX11: =ROUND(Y11*Source!I38,9) -> 135.19099 | CY11: =AB11 -> 1 | CZ11: =AF11 -> 1 | DA11: =AJ11 -> 1 | DB11: =ROUND(ROUND(AT11*CZ11,2),6) -> 38.77 | DC11: =ROUND(ROUND(AT11*AG11,2),6) -> 0 | DF11: =ROUND(ROUND(AE11,2)*CX11,2) -> 0 | DG11: =ROUND(ROUND(AF11,2)*CX11,2) -> 135.19 | DH11: =ROUND(ROUND(AG11,2)*CX11,2) -> 0 | DI11: =ROUND(ROUND(AH11,2)*CX11,2) -> 0 | DJ11: =DG11 -> 135.19 | DK11: 0 | DM11: 0 | DO11: 0
A12: =ROW(Source!A39) -> 39 | B12: 56526441 | C12: 56526787 | D12: 54836954 | E12: 1079 | F12: 1 | G12: 1079 | H12: 2 | I12: 9999990007 | K12: Стоимость прочих машин (ЭСН) | L12: 1344 | N12: 1008 | O12: руб. | P12: руб. | Q12: 1 | W12: 0 | X12: -1180195794 | Y12: =AT12 -> 38.77 | AA12: 0 | AB12: 1 | AC12: 0 | AD12: 0 | AE12: 0 | AF12: 1 | AG12: 0 | AH12: 0 | AI12: 1 | AJ12: 1 | AK12: 1 | AL12: 1 | AM12: -2 | AN12: 0 | AO12: 1 | AP12: 1 | AQ12: 0 | AR12: 0 | AT12: 38.77 | AV12: 0 | AW12: 2 | AX12: 56526801 | AY12: 1 | AZ12: 0 | BA12: 12 | BB12: 0 | BC12: 0 | BD12: 0 | BE12: 0 | BF12: 0 | BG12: 0 | BH12: 0 | BI12: 0 | BJ12: 0 | BK12: 0 | BL12: 0 | BM12: 0 | BN12: 0 | BO12: 0 | BP12: 0 | BQ12: 0 | BR12: 0 | BS12: 0 | BT12: 0 | BU12: 0 | BV12: 0 | BW12: 0 | CV12: 0 | CW12: =ROUND(Y12*Source!I39*DO12,9) -> 0 | CX12: =ROUND(Y12*Source!I39,9) -> 135.19099 | CY12: =AB12 -> 1 | CZ12: =AF12 -> 1 | DA12: =AJ12 -> 1 | DB12: =ROUND(ROUND(AT12*CZ12,2),6) -> 38.77 | DC12: =ROUND(ROUND(AT12*AG12,2),6) -> 0 | DF12: =ROUND(ROUND(AE12,2)*CX12,2) -> 0 | DG12: =ROUND(ROUND(AF12,2)*CX12,2) -> 135.19 | DH12: =ROUND(ROUND(AG12,2)*CX12,2) -> 0 | DI12: =ROUND(ROUND(AH12,2)*CX12,2) -> 0 | DJ12: =DG12 -> 135.19 | DK12: 0 | DM12: 0 | DO12: 0
... A36: =ROW(Source!A63) -> 63 | B36: 56526441 | C36: 56526834 | D36: 54836954 | E36: 1079 | F36: 1 | G36: 1079 | H36: 2 | I36: 9999990007 | K36: Стоимость прочих машин (ЭСН) | L36: 1344 | N36: 1008 | O36: руб. | P36: руб. | Q36: 1 | W36: 0 | X36: -1180195794 | Y36: =AT36 -> 47.51 | AA36: 0 | AB36: 1 | AC36: 0 | AD36: 0 | AE36: 0 | AF36: 1 | AG36: 0 | AH36: 0 | AI36: 1 | AJ36: 1 | AK36: 1 | AL36: 1 | AM36: -2 | AN36: 0 | AO36: 1 | AP36: 1 | AQ36: 0 | AR36: 0 | AT36: 47.51 | AV36: 0 | AW36: 2 | AX36: 56526837 | AY36: 1 | AZ36: 0 | BA36: 36 | BB36: 0 | BC36: 0 | BD36: 0 | BE36: 0 | BF36: 0 | BG36: 0 | BH36: 0 | BI36: 0 | BJ36: 0 | BK36: 0 | BL36: 0 | BM36: 0 | BN36: 0 | BO36: 0 | BP36: 0 | BQ36: 0 | BR36: 0 | BS36: 0 | BT36: 0 | BU36: 0 | BV36: 0 | BW36: 0 | CV36: 0 | CW36: =ROUND(Y36*Source!I63*DO36,9) -> 0 | CX36: =ROUND(Y36*Source!I63,9) -> 15134.976 | CY36: =AB36 -> 1 | CZ36: =AF36 -> 1 | DA36: =AJ36 -> 1 | DB36: =ROUND(ROUND(AT36*CZ36,2),6) -> 47.51 | DC36: =ROUND(ROUND(AT36*AG36,2),6) -> 0 | DF36: =ROUND(ROUND(AE36,2)*CX36,2) -> 0 | DG36: =ROUND(ROUND(AF36,2)*CX36,2) -> 15134.98 | DH36: =ROUND(ROUND(AG36,2)*CX36,2) -> 0 | DI36: =ROUND(ROUND(AH36,2)*CX36,2) -> 0 | DJ36: =DG36 -> 15134.98 | DK36: 0 | DM36: 0 | DO36: 0

Sheet EtalonRes
A1: =ROW(Source!A28) -> 28 | B1: 56526796 | C1: 56526772 | D1: 54836954 | E1: 1079 | F1: 1 | G1: 1079 | H1: 2 | I1: 9999990007 | K1: Стоимость прочих машин (ЭСН) | L1: 1344 | N1: 1008 | O1: руб. | P1: руб. | Q1: 1 | X1: 31.67 | Y1: 0 | Z1: 1 | AA1: 0 | AB1: 0 | AC1: 0 | AD1: 1 | AE1: 0 | AG1: 31.67 | AH1: 2 | AI1: 56526796 | AJ1: 1 | AK1: 0 | AL1: 0 | AM1: 0 | AN1: 0 | AO1: 0 | AP1: 0 | AQ1: 0 | AR1: 0
A2: =ROW(Source!A29) -> 29 | B2: 56526796 | C2: 56526772 | D2: 54836954 | E2: 1079 | F2: 1 | G2: 1079 | H2: 2 | I2: 9999990007 | K2: Стоимость прочих машин (ЭСН) | L2: 1344 | N2: 1008 | O2: руб. | P2: руб. | Q2: 1 | X2: 31.67 | Y2: 0 | Z2: 1 | AA2: 0 | AB2: 0 | AC2: 0 | AD2: 1 | AE2: 0 | AG2: 31.67 | AH2: 2 | AI2: 56526796 | AJ2: 2 | AK2: 0 | AL2: 0 | AM2: 0 | AN2: 0 | AO2: 0 | AP2: 0 | AQ2: 0 | AR2: 0
A3: =ROW(Source!A30) -> 30 | B3: 56526797 | C3: 56526775 | D3: 54836954 | E3: 1079 | F3: 1 | G3: 1079 | H3: 2 | I3: 9999990007 | K3: Стоимость прочих машин (ЭСН) | L3: 1344 | N3: 1008 | O3: руб. | P3: руб. | Q3: 1 | X3: 31.13 | Y3: 0 | Z3: 1 | AA3: 0 | AB3: 0 | AC3: 0 | AD3: 1 | AE3: 0 | AG3: 31.13 | AH3: 2 | AI3: 56526797 | AJ3: 3 | AK3: 0 | AL3: 0 | AM3: 0 | AN3: 0 | AO3: 0 | AP3: 0 | AQ3: 0 | AR3: 0
A4: =ROW(Source!A31) -> 31 | B4: 56526797 | C4: 56526775 | D4: 54836954 | E4: 1079 | F4: 1 | G4: 1079 | H4: 2 | I4: 9999990007 | K4: Стоимость прочих машин (ЭСН) | L4: 1344 | N4: 1008 | O4: руб. | P4: руб. | Q4: 1 | X4: 31.13 | Y4: 0 | Z4: 1 | AA4: 0 | AB4: 0 | AC4: 0 | AD4: 1 | AE4: 0 | AG4: 31.13 | AH4: 2 | AI4: 56526797 | AJ4: 4 | AK4: 0 | AL4: 0 | AM4: 0 | AN4: 0 | AO4: 0 | AP4: 0 | AQ4: 0 | AR4: 0
A5: =ROW(Source!A32) -> 32 | B5: 56526798 | C5: 56526778 | D5: 54836954 | E5: 1079 | F5: 1 | G5: 1079 | H5: 2 | I5: 9999990007 | K5: Стоимость прочих машин (ЭСН) | L5: 1344 | N5: 1008 | O5: руб. | P5: руб. | Q5: 1 | X5: 36.59 | Y5: 0 | Z5: 1 | AA5: 0 | AB5: 0 | AC5: 0 | AD5: 1 | AE5: 0 | AG5: 36.59 | AH5: 2 | AI5: 56526798 | AJ5: 5 | AK5: 0 | AL5: 0 | AM5: 0 | AN5: 0 | AO5: 0 | AP5: 0 | AQ5: 0 | AR5: 0
A6: =ROW(Source!A33) -> 33 | B6: 56526798 | C6: 56526778 | D6: 54836954 | E6: 1079 | F6: 1 | G6: 1079 | H6: 2 | I6: 9999990007 | K6: Стоимость прочих машин (ЭСН) | L6: 1344 | N6: 1008 | O6: руб. | P6: руб. | Q6: 1 | X6: 36.59 | Y6: 0 | Z6: 1 | AA6: 0 | AB6: 0 | AC6: 0 | AD6: 1 | AE6: 0 | AG6: 36.59 | AH6: 2 | AI6: 56526798 | AJ6: 6 | AK6: 0 | AL6: 0 | AM6: 0 | AN6: 0 | AO6: 0 | AP6: 0 | AQ6: 0 | AR6: 0
A7: =ROW(Source!A34) -> 34 | B7: 56526799 | C7: 56526781 | D7: 54836954 | E7: 1079 | F7: 1 | G7: 1079 | H7: 2 | I7: 9999990007 | K7: Стоимость прочих машин (ЭСН) | L7: 1344 | N7: 1008 | O7: руб. | P7: руб. | Q7: 1 | X7: 98.3 | Y7: 0 | Z7: 1 | AA7: 0 | AB7: 0 | AC7: 0 | AD7: 1 | AE7: 0 | AG7: 98.3 | AH7: 2 | AI7: 56526799 | AJ7: 7 | AK7: 0 | AL7: 0 | AM7: 0 | AN7: 0 | AO7: 0 | AP7: 0 | AQ7: 0 | AR7: 0
A8: =ROW(Source!A35) -> 35 | B8: 56526799 | C8: 56526781 | D8: 54836954 | E8: 1079 | F8: 1 | G8: 1079 | H8: 2 | I8: 9999990007 | K8: Стоимость прочих машин (ЭСН) | L8: 1344 | N8: 1008 | O8: руб. | P8: руб. | Q8: 1 | X8: 98.3 | Y8: 0 | Z8: 1 | AA8: 0 | AB8: 0 | AC8: 0 | AD8: 1 | AE8: 0 | AG8: 98.3 | AH8: 2 | AI8: 56526799 | AJ8: 8 | AK8: 0 | AL8: 0 | AM8: 0 | AN8: 0 | AO8: 0 | AP8: 0 | AQ8: 0 | AR8: 0
A9: =ROW(Source!A36) -> 36 | B9: 56526800 | C9: 56526784 | D9: 54836954 | E9: 1079 | F9: 1 | G9: 1079 | H9: 2 | I9: 9999990007 | K9: Стоимость прочих машин (ЭСН) | L9: 1344 | N9: 1008 | O9: руб. | P9: руб. | Q9: 1 | X9: 38.77 | Y9: 0 | Z9: 1 | AA9: 0 | AB9: 0 | AC9: 0 | AD9: 1 | AE9: 0 | AG9: 38.77 | AH9: 2 | AI9: 56526800 | AJ9: 9 | AK9: 0 | AL9: 0 | AM9: 0 | AN9: 0 | AO9: 0 | AP9: 0 | AQ9: 0 | AR9: 0
A10: =ROW(Source!A37) -> 37 | B10: 56526800 | C10: 56526784 | D10: 54836954 | E10: 1079 | F10: 1 | G10: 1079 | H10: 2 | I10: 9999990007 | K10: Стоимость прочих машин (ЭСН) | L10: 1344 | N10: 1008 | O10: руб. | P10: руб. | Q10: 1 | X10: 38.77 | Y10: 0 | Z10: 1 | AA10: 0 | AB10: 0 | AC10: 0 | AD10: 1 | AE10: 0 | AG10: 38.77 | AH10: 2 | AI10: 56526800 | AJ10: 10 | AK10: 0 | AL10: 0 | AM10: 0 | AN10: 0 | AO10: 0 | AP10: 0 | AQ10: 0 | AR10: 0
A11: =ROW(Source!A38) -> 38 | B11: 56526801 | C11: 56526787 | D11: 54836954 | E11: 1079 | F11: 1 | G11: 1079 | H11: 2 | I11: 9999990007 | K11: Стоимость прочих машин (ЭСН) | L11: 1344 | N11: 1008 | O11: руб. | P11: руб. | Q11: 1 | X11: 38.77 | Y11: 0 | Z11: 1 | AA11: 0 | AB11: 0 | AC11: 0 | AD11: 1 | AE11: 0 | AG11: 38.77 | AH11: 2 | AI11: 56526801 | AJ11: 11 | AK11: 0 | AL11: 0 | AM11: 0 | AN11: 0 | AO11: 0 | AP11: 0 | AQ11: 0 | AR11: 0
A12: =ROW(Source!A39) -> 39 | B12: 56526801 | C12: 56526787 | D12: 54836954 | E12: 1079 | F12: 1 | G12: 1079 | H12: 2 | I12: 9999990007 | K12: Стоимость прочих машин (ЭСН) | L12: 1344 | N12: 1008 | O12: руб. | P12: руб. | Q12: 1 | X12: 38.77 | Y12: 0 | Z12: 1 | AA12: 0 | AB12: 0 | AC12: 0 | AD12: 1 | AE12: 0 | AG12: 38.77 | AH12: 2 | AI12: 56526801 | AJ12: 12 | AK12: 0 | AL12: 0 | AM12: 0 | AN12: 0 | AO12: 0 | AP12: 0 | AQ12: 0 | AR12: 0
... A36: =ROW(Source!A63) -> 63 | B36: 56526837 | C36: 56526834 | D36: 54836954 | E36: 1079 | F36: 1 | G36: 1079 | H36: 2 | I36: 9999990007 | K36: Стоимость прочих машин (ЭСН) | L36: 1344 | N36: 1008 | O36: руб. | P36: руб. | Q36: 1 | X36: 47.51 | Y36: 0 | Z36: 1 | AA36: 0 | AB36: 0 | AC36: 0 | AD36: 1 | AE36: 0 | AG36: 47.51 | AH36: 2 | AI36: 56526837 | AJ36: 36 | AK36: 0 | AL36: 0 | AM36: 0 | AN36: 0 | AO36: 0 | AP36: 0 | AQ36: 0 | AR36: 0

Sheet SrcPoprs

Sheet SrcKA
A1: 0 | B1: Smeta.RU (495) 974-1589 | D1: _PS_ | F1: 0 | G1: 0 | H1: 0 | I1: Smeta.RU | K1: 1 | L1: 74562 | M1: 10 | N1: 11 | O1: 14 | P1: 0 | Q1: 0
F12: =Source!F12 -> 09-01-03 | G12: =Source!G12 -> 09-01-03 Размещение и содержание строительного мусора | CY12: =Source!CY12 -> 0
