Workbook

Sheet 02-01-04
A1: =Source!B1 -> Smeta.RU (495) 974-1589
J2: Форма № 4б
A3: Капитальный ремонт здания Государственного бюджетного общеобразовательного учреждения города Москвы "Школа № 236" по адресу: г. Москва ул. Клязьминская, д. 7 к. 4. 1 этап. | AP3: Капитальный ремонт здания Государственного бюджетного общеобразовательного учреждения города Москвы "Школа № 236" по адресу: г. Москва ул. Клязьминская, д. 7 к. 4. 1 этап. 02-01-04 Система водоснабжения
A4: (наименование стройки и/или объекта)
A6: =CONCATENATE( "ЛОКАЛЬНАЯ СМЕТА № ",IF(Source!F20<>"Новая локальная смета", Source!F20, "")) -> ЛОКАЛЬНАЯ СМЕТА № 02-01-04
A8: =IF(Source!G20<>"Новая локальная смета", Source!G20, "") -> Система водоснабжения
A9: (наименование работ и затрат)
A11: =CONCATENATE( "Основание: чертежи № ", Source!J20) -> Основание: чертежи № 2024-00272-00-0-ИОС2
I13: В базисном уровне цен | J13: В текущем уровне цен
E14: Сметная стоимость | I14: =I15+I16+I17+I18 -> 587.47 | J14: =J15+J16+J17+J18 -> 7939.14 | K14: тыс.руб.
E15: Строительные работы | I15: =ROUND((Source!F974)/1000, 2) -> 521.12 | J15: =ROUND((Source!P974)/1000, 2) -> 7246.55 | K15: тыс.руб.
E16: Работы по монтажу оборудования | I16: =ROUND((Source!F975)/1000, 2) -> 39.95 | J16: =ROUND((Source!P975)/1000, 2) -> 490.36 | K16: тыс.руб.
E17: Оборудование | I17: =ROUND((Source!F966)/1000, 2) -> 26.4 | J17: =ROUND((Source!P966)/1000, 2) -> 202.23 | K17: тыс.руб.
E18: Прочие работы и затраты | I18: =ROUND((Source!F976+Source!F977)/1000, 2) -> 0 | J18: =ROUND((Source!P976+Source!P977)/1000, 2) -> 0 | K18: тыс.руб.
E19: Средства на оплату труда | I19: =(Source!F972+ Source!F971)/1000 -> 24.65016 | J19: =((Source!P972 + Source!P971)/1000) -> 1355.5124 | K19: тыс.руб.
E20: Затраты труда | I20: =Source!F979 -> 1905.881 | K20: чел.-ч.
E21: Кроме того:
E22: Возврат материалов | I22: =SUM(Y28:Y1213)/1000 -> 0 | J22: =SUM(Z28:Z1213)/1000 -> 0 | K22: тыс.руб.
A24: Составлен(а) по ТСН-2001 с учетом Дополнения №: 80
A25: № и период сборника коэффициентов (индексов) пересчета: Коэффициенты к ТСН-2001 МГЭ Дополнение 80, ремонт №217/80 III квартал 2025 года и Коэффициенты к ТСН-2001.13-2 Дополнение 46 №62/46 III квартал 2025 года | AP25: № и период сборника коэффициентов (индексов) пересчета: Коэффициенты к ТСН-2001 МГЭ Дополнение 80, ремонт №217/80 III квартал 2025 года и Коэффициенты к ТСН-2001.13-2 Дополнение 46 №62/46 III квартал 2025 года
A26: № п/п | B26: Шифр расценки и коды ресурсов | C26: Наименование работ и затрат | D26: Ед. изм. | E26: Кол-во единиц | F26: Цена на ед. изм., руб. | G26: Попра- вочные коэффи- циенты | H26: Коэффи- циенты зимних удорожа- ний | I26: Всего в ценах на январь 2000 года, руб. | J26: Коэффи- циенты (индек- сы) пере- счета, нормы НР и СП | K26: ВСЕГО затрат в текущем уровне цен, руб.
A27: 1 | B27: 2 | C27: 3 | D27: 4 | E27: 5 | F27: 6 | G27: 7 | H27: 8 | I27: 9 | J27: 10 | K27: 11
A29: =CONCATENATE("Раздел: ",IF(Source!G24<>"Новый раздел", Source!G24, "")) -> Раздел: Водопровод хозяйственно-питьевой В1 (Подземная часть)
A30: 1 | B30: 3.16-38-1 Поправка: О.П. п.3.4. 6 Поправка: О.П. п.3.4.30.в | C30: Прокладка трубопроводов из стальных труб на бессварных разъемных муфтовых соединениях диаметром до 25 мм | D30: =Source!H28 -> 100 м | E30: =Source!I28 -> 0.18 | Q30: =Source!X28 -> 62.81 | R30: =Source!X29 -> 3453.69 | S30: =Source!Y28 -> 35.15 | T30: =Source!Y29 -> 1932.8 | U30: =ROUND((175/100)*ROUND(Source!R28, 2), 2) -> 0.14 | V30: =ROUND((0/100)*ROUND(Source!R29, 2), 2) -> 0 | AC30: 0
C31: ="Объем: "&Source!I28&"=18/"&"100" -> Объем: 0,18=18/100
C32: ЗП | F32: =Source!AO28 -> 236.83 | G32: =Source!DG28 -> *1,15)*1,1 | H32: =Source!AV29 -> 1.067 | I32: =Source!S28 -> 57.54 | J32: =IF(Source!BA29<> 0, Source!BA29, 1) -> 54.99 | K32: =Source!S29 -> 3164.12
C33: ЭМ | F33: =Source!AM28 -> 4.07 | G33: =Source!DE28 -> *1,25)*1,1 | H33: =Source!AV29 -> 1.067 | I33: =Source!Q28 -> 1.07 | J33: =IF(Source!BB29<> 0, Source!BB29, 1) -> 12.44 | K33: =Source!Q29 -> 13.31
C34: в т.ч. ЗПМ | F34: =Source!AN28 -> 0.3 | G34: =Source!DF28 -> *1,25)*1,1 | H34: =Source!AV29 -> 1.067 | I34: =Source!R28 -> 0.08 | J34: =IF(Source!BS29<> 0, Source!BS29, 1) -> 54.99 | K34: =Source!R29 -> 4.4
C35: МР | F35: =Source!AL28 -> 30.04 | G35: =Source!DD28 | H35: =Source!AW29 -> 1 | I35: =Source!P28 -> 5.41 | J35: =IF(Source!BC29<> 0, Source!BC29, 1) -> 1.79 | K35: =Source!P29 -> 9.68
A36: 1,1 | B36: =Source!F30 -> 1.12-1-52 | C36: Узел трубопровода из стальных водогазопроводных оцинкованных труб, с гильзами, для водоснабжения, диаметр условного прохода 15 мм | D36: =Source!H30 -> м | E36: =Source!I30 -> 18 | F36: =Source!AK30 -> 28.1 | H36: =Source!AW31 -> 1 | I36: =Source!O30 -> 505.8 | J36: =IF(Source!BC31<> 0, Source!BC31, 1) -> 18.63 | K36: =Source!O31 -> 9423.05 | Q36: =Source!X30 -> 0 | R36: =Source!X31 -> 0 | S36: =Source!Y30 -> 0 | T36: =Source!Y31 -> 0 | U36: =ROUND((175/100)*ROUND(Source!R30, 2), 2) -> 0 | V36: =ROUND((0/100)*ROUND(Source!R31, 2), 2) -> 0 | AC36: 3
A37: 1,2 | B37: =Source!F32 -> 1.13-4-61 | C37: Кран шаровой, латунный, никелированный, полнопроходной, с алюминиевой рукояткой, муфтовый, температура рабочей среды от -15 до +110°С, номинальное давление PN 4,0 МПа, номинальный диаметр DN 15 мм | D37: =Source!H32 -> шт. | E37: =Source!I32 -> 6 | F37: =Source!AK32 -> 34.97 | H37: =Source!AW33 -> 1 | I37: =Source!O32 -> 209.82 | J37: =IF(Source!BC33<> 0, Source!BC33, 1) -> 18.72 | K37: =Source!O33 -> 3927.83 | Q37: =Source!X32 -> 0 | R37: =Source!X33 -> 0 | S37: =Source!Y32 -> 0 | T37: =Source!Y33 -> 0 | U37: =ROUND((175/100)*ROUND(Source!R32, 2), 2) -> 0 | V37: =ROUND((0/100)*ROUND(Source!R33, 2), 2) -> 0 | AC37: 3
A38: 1,3 | B38: =Source!F34 -> 1.13-4-137 | C38: Кран шаровой, латунный, никелированный, спускной, с наружной резьбой, с насадкой для шланга, с алюминиевой рукояткой, температура рабочей среды от -15 до +90°С, пропускная способность 1,9 м3/ч, номинальное давление PN 1,0 МПа, номинальный диаметр DN 15 мм | D38: =Source!H34 -> шт. | E38: =Source!I34 -> 44 | F38: =Source!AK34 -> 24.61 | H38: =Source!AW35 -> 1 | I38: =Source!O34 -> 1082.84 | J38: =IF(Source!BC35<> 0, Source!BC35, 1) -> 35.58 | K38: =Source!O35 -> 38527.45 | Q38: =Source!X34 -> 0 | R38: =Source!X35 -> 0 | S38: =Source!Y34 -> 0 | T38: =Source!Y35 -> 0 | U38: =ROUND((175/100)*ROUND(Source!R34, 2), 2) -> 0 | V38: =ROUND((0/100)*ROUND(Source!R35, 2), 2) -> 0 | AC38: 3
A39: 1,4 | B39: =Source!F36 -> 1.12-10-146 | C39: Хомут стальной, оцинкованный, двухболтовой, с поворотным механизмом, каучуковой прокладкой, для крепления труб диаметром от 16 до 20 мм, резьба М8/М10 | D39: =Source!H36 -> 100 шт. | E39: =Source!I36 -> 0.12 | F39: =Source!AK36 -> 526.22 | H39: =Source!AW37 -> 1 | I39: =Source!O36 -> 63.15 | J39: =IF(Source!BC37<> 0, Source!BC37, 1) -> 2.79 | K39: =Source!O37 -> 176.19 | Q39: =Source!X36 -> 0 | R39: =Source!X37 -> 0 | S39: =Source!Y36 -> 0 | T39: =Source!Y37 -> 0 | U39: =ROUND((175/100)*ROUND(Source!R36, 2), 2) -> 0 | V39: =ROUND((0/100)*ROUND(Source!R37, 2), 2) -> 0 | AC39: 3
C40: НР от ФОТ | D40: % | E40: =Source!BZ29 -> 109 | I40: =SUM(Q30:Q39) -> 62.81 | J40: =Source!AT29 -> 109 | K40: =SUM(R30:R39) -> 3453.69
C41: СП от ФОТ | D41: % | E41: =Source!CA29 -> 61 | I41: =SUM(S30:S40) -> 35.15 | J41: =Source!AU29 -> 61 | K41: =SUM(T30:T40) -> 1932.8
C42: ЗТР | D42: чел-ч | E42: =Source!AQ28 -> 19.12 | G42: =Source!DI28 -> *1,15)*1,1 | H42: =Source!AV29 -> 1.067 | I42: =Source!U28 -> 4.6453168
C43: Всего по позиции: | H43: =I32+I33+I35+I40+I41+SUM(I36:I39) -> 2023.59 | J43: =K32+K33+K35+K40+K41+SUM(K36:K39) -> 60628.12 | O43: =I32+I33+I35+I40+I41+SUM(I36:I39) -> 2023.59 | P43: =K32+K33+K35+K40+K41+SUM(K36:K39) -> 60628.12
A45: 2 | B45: 3.16-38-1 Поправка: О.П. п.3.4. 6 Поправка: О.П. п.3.4.30.в | C45: Прокладка трубопроводов из стальных труб на бессварных разъемных муфтовых соединениях диаметром до 25 мм | D45: =Source!H48 -> 100 м | E45: =Source!I48 -> 1.1 | Q45: =Source!X48 -> 383.8 | R45: =Source!X49 -> 21105.16 | S45: =Source!Y48 -> 214.79 | T45: =Source!Y49 -> 11811.14 | U45: =ROUND((175/100)*ROUND(Source!R48, 2), 2) -> 0.84 | V45: =ROUND((0/100)*ROUND(Source!R49, 2), 2) -> 0 | AC45: 0
C46: ="Объем: "&Source!I48&"=110/"&"100" -> Объем: 1,1=110/100
C47: ЗП | F47: =Source!AO48 -> 236.83 | G47: =Source!DG48 -> *1,15)*1,1 | H47: =Source!AV49 -> 1.067 | I47: =Source!S48 -> 351.63 | J47: =IF(Source!BA49<> 0, Source!BA49, 1) -> 54.99 | K47: =Source!S49 -> 19336.13
C48: ЭМ | F48: =Source!AM48 -> 4.07 | G48: =Source!DE48 -> *1,25)*1,1 | H48: =Source!AV49 -> 1.067 | I48: =Source!Q48 -> 6.57 | J48: =IF(Source!BB49<> 0, Source!BB49, 1) -> 12.44 | K48: =Source!Q49 -> 81.73
C49: в т.ч. ЗПМ | F49: =Source!AN48 -> 0.3 | G49: =Source!DF48 -> *1,25)*1,1 | H49: =Source!AV49 -> 1.067 | I49: =Source!R48 -> 0.48 | J49: =IF(Source!BS49<> 0, Source!BS49, 1) -> 54.99 | K49: =Source!R49 -> 26.4
C50: МР | F50: =Source!AL48 -> 30.04 | G50: =Source!DD48 | H50: =Source!AW49 -> 1 | I50: =Source!P48 -> 33.04 | J50: =IF(Source!BC49<> 0, Source!BC49, 1) -> 1.79 | K50: =Source!P49 -> 59.14
A51: 2,1 | B51: =Source!F50 -> 1.12-1-53 | C51: Узел трубопровода из стальных водогазопроводных оцинкованных труб, с гильзами, для водоснабжения, диаметр условного прохода 20 мм | D51: =Source!H50 -> м | E51: =Source!I50 -> 110 | F51: =Source!AK50 -> 31.41 | H51: =Source!AW51 -> 1 | I51: =Source!O50 -> 3455.1 | J51: =IF(Source!BC51<> 0, Source!BC51, 1) -> 18.51 | K51: =Source!O51 -> 63953.9 | Q51: =Source!X50 -> 0 | R51: =Source!X51 -> 0 | S51: =Source!Y50 -> 0 | T51: =Source!Y51 -> 0 | U51: =ROUND((175/100)*ROUND(Source!R50, 2), 2) -> 0 | V51: =ROUND((0/100)*ROUND(Source!R51, 2), 2) -> 0 | AC51: 3
A52: 2,2 | B52: =Source!F52 -> 1.13-4-62 | C52: Кран шаровой, латунный, никелированный, полнопроходной, с алюминиевой рукояткой, муфтовый, температура рабочей среды от -15 до +110°С, номинальное давление PN 4,0 МПа, номинальный диаметр DN 20 мм | D52: =Source!H52 -> шт. | E52: =Source!I52 -> 24 | F52: =Source!AK52 -> 47.24 | H52: =Source!AW53 -> 1 | I52: =Source!O52 -> 1133.76 | J52: =IF(Source!BC53<> 0, Source!BC53, 1) -> 20.7 | K52: =Source!O53 -> 23468.83 | Q52: =Source!X52 -> 0 | R52: =Source!X53 -> 0 | S52: =Source!Y52 -> 0 | T52: =Source!Y53 -> 0 | U52: =ROUND((175/100)*ROUND(Source!R52, 2), 2) -> 0 | V52: =ROUND((0/100)*ROUND(Source!R53, 2), 2) -> 0 | AC52: 3
A53: 2,3 | B53: =Source!F54 -> 1.12-10-146 | C53: Хомут стальной, оцинкованный, двухболтовой, с поворотным механизмом, каучуковой прокладкой, для крепления труб диаметром от 16 до 20 мм, резьба М8/М10 | D53: =Source!H54 -> 100 шт. | E53: =Source!I54 -> 0.55 | F53: =Source!AK54 -> 526.22 | H53: =Source!AW55 -> 1 | I53: =Source!O54 -> 289.42 | J53: =IF(Source!BC55<> 0, Source!BC55, 1) -> 2.79 | K53: =Source!O55 -> 807.48 | Q53: =Source!X54 -> 0 | R53: =Source!X55 -> 0 | S53: =Source!Y54 -> 0 | T53: =Source!Y55 -> 0 | U53: =ROUND((175/100)*ROUND(Source!R54, 2), 2) -> 0 | V53: =ROUND((0/100)*ROUND(Source!R55, 2), 2) -> 0 | AC53: 3
C54: НР от ФОТ | D54: % | E54: =Source!BZ49 -> 109 | I54: =SUM(Q45:Q53) -> 383.8 | J54: =Source!AT49 -> 109 | K54: =SUM(R45:R53) -> 21105.16
C55: СП от ФОТ | D55: % | E55: =Source!CA49 -> 61 | I55: =SUM(S45:S54) -> 214.79 | J55: =Source!AU49 -> 61 | K55: =SUM(T45:T54) -> 11811.14
C56: ЗТР | D56: чел-ч | E56: =Source!AQ48 -> 19.12 | G56: =Source!DI48 -> *1,15)*1,1 | H56: =Source!AV49 -> 1.067 | I56: =Source!U48 -> 28.388047
C57: Всего по позиции: | H57: =I47+I48+I50+I54+I55+SUM(I51:I53) -> 5868.11 | J57: =K47+K48+K50+K54+K55+SUM(K51:K53) -> 140623.51 | O57: =I47+I48+I50+I54+I55+SUM(I51:I53) -> 5868.11 | P57: =K47+K48+K50+K54+K55+SUM(K51:K53) -> 140623.51
A59: 3 | B59: 3.16-38-1 Поправка: О.П. п.3.4. 6 | C59: Прокладка трубопроводов из стальных труб на бессварных разъемных муфтовых соединениях диаметром до 25 мм | D59: =Source!H64 -> 100 м | E59: =Source!I64 -> 1.75 | Q59: =Source!X64 -> 555.08 | R59: =Source!X65 -> 30523.98 | S59: =Source!Y64 -> 310.64 | T59: =Source!Y65 -> 17082.23 | U59: =ROUND((175/100)*ROUND(Source!R64, 2), 2) -> 1.23 | V59: =ROUND((0/100)*ROUND(Source!R65, 2), 2) -> 0 | AC59: 0
C60: ="Объем: "&Source!I64&"=175/"&"100" -> Объем: 1,75=175/100
C61: ЗП | F61: =Source!AO64 -> 236.83 | G61: =Source!DG64 -> *1,15 | H61: =Source!AV65 -> 1.067 | I61: =Source!S64 -> 508.55 | J61: =IF(Source!BA65<> 0, Source!BA65, 1) -> 54.99 | K61: =Source!S65 -> 27965.16
C62: ЭМ | F62: =Source!AM64 -> 4.07 | G62: =Source!DE64 -> *1,25 | H62: =Source!AV65 -> 1.067 | I62: =Source!Q64 -> 9.5 | J62: =IF(Source!BB65<> 0, Source!BB65, 1) -> 12.44 | K62: =Source!Q65 -> 118.18
C63: в т.ч. ЗПМ | F63: =Source!AN64 -> 0.3 | G63: =Source!DF64 -> *1,25 | H63: =Source!AV65 -> 1.067 | I63: =Source!R64 -> 0.7 | J63: =IF(Source!BS65<> 0, Source!BS65, 1) -> 54.99 | K63: =Source!R65 -> 38.49
C64: МР | F64: =Source!AL64 -> 30.04 | G64: =Source!DD64 | H64: =Source!AW65 -> 1 | I64: =Source!P64 -> 52.57 | J64: =IF(Source!BC65<> 0, Source!BC65, 1) -> 1.79 | K64: =Source!P65 -> 94.1
A65: 3,1 | B65: =Source!F66 -> 1.12-1-54 | C65: Узел трубопровода из стальных водогазопроводных оцинкованных труб, с гильзами, для водоснабжения, диаметр условного прохода 25 мм | D65: =Source!H66 -> м | E65: =Source!I66 -> 175 | F65: =Source!AK66 -> 41.57 | H65: =Source!AW67 -> 1 | I65: =Source!O66 -> 7274.75 | J65: =IF(Source!BC67<> 0, Source!BC67, 1) -> 16.55 | K65: =Source!O67 -> 120397.11 | Q65: =Source!X66 -> 0 | R65: =Source!X67 -> 0 | S65: =Source!Y66 -> 0 | T65: =Source!Y67 -> 0 | U65: =ROUND((175/100)*ROUND(Source!R66, 2), 2) -> 0 | V65: =ROUND((0/100)*ROUND(Source!R67, 2), 2) -> 0 | AC65: 3
A66: 3,2 | B66: =Source!F68 -> 1.12-10-146 | C66: Хомут стальной, оцинкованный, двухболтовой, с поворотным механизмом, каучуковой прокладкой, для крепления труб диаметром от 16 до 20 мм, резьба М8/М10 | D66: =Source!H68 -> 100 шт. | E66: =Source!I68 -> 0.87 | F66: =Source!AK68 -> 526.22 | H66: =Source!AW69 -> 1 | I66: =Source!O68 -> 457.81 | J66: =IF(Source!BC69<> 0, Source!BC69, 1) -> 2.79 | K66: =Source!O69 -> 1277.29 | Q66: =Source!X68 -> 0 | R66: =Source!X69 -> 0 | S66: =Source!Y68 -> 0 | T66: =Source!Y69 -> 0 | U66: =ROUND((175/100)*ROUND(Source!R68, 2), 2) -> 0 | V66: =ROUND((0/100)*ROUND(Source!R69, 2), 2) -> 0 | AC66: 3
A67: 3,3 | B67: =Source!F70 -> 1.13-4-63 | C67: Кран шаровой, латунный, никелированный, полнопроходной, с алюминиевой рукояткой, муфтовый, температура рабочей среды от -15 до +110°С, номинальное давление PN 4,0 МПа, номинальный диаметр DN 25 мм | D67: =Source!H70 -> шт. | E67: =Source!I70 -> 14 | F67: =Source!AK70 -> 74.36 | H67: =Source!AW71 -> 1 | I67: =Source!O70 -> 1041.04 | J67: =IF(Source!BC71<> 0, Source!BC71, 1) -> 18.87 | K67: =Source!O71 -> 19644.42 | Q67: =Source!X70 -> 0 | R67: =Source!X71 -> 0 | S67: =Source!Y70 -> 0 | T67: =Source!Y71 -> 0 | U67: =ROUND((175/100)*ROUND(Source!R70, 2), 2) -> 0 | V67: =ROUND((0/100)*ROUND(Source!R71, 2), 2) -> 0 | AC67: 3
C68: НР от ФОТ | D68: % | E68: =Source!BZ65 -> 109 | I68: =SUM(Q59:Q67) -> 555.08 | J68: =Source!AT65 -> 109 | K68: =SUM(R59:R67) -> 30523.98
C69: СП от ФОТ | D69: % | E69: =Source!CA65 -> 61 | I69: =SUM(S59:S68) -> 310.64 | J69: =Source!AU65 -> 61 | K69: =SUM(T59:T68) -> 17082.23
C70: ЗТР | D70: чел-ч | E70: =Source!AQ64 -> 19.12 | G70: =Source!DI64 -> *1,15 | H70: =Source!AV65 -> 1.067 | I70: =Source!U64 -> 41.057093
C71: Всего по позиции: | H71: =I61+I62+I64+I68+I69+SUM(I65:I67) -> 10209.94 | J71: =K61+K62+K64+K68+K69+SUM(K65:K67) -> 217102.47 | O71: =I61+I62+I64+I68+I69+SUM(I65:I67) -> 10209.94 | P71: =K61+K62+K64+K68+K69+SUM(K65:K67) -> 217102.47
A73: 4 | B73: 3.16-38-2 Поправка: О.П. п.3.4. 6 Поправка: О.П. п.3.4.30.в | C73: Прокладка трубопроводов из стальных труб на бессварных разъемных муфтовых соединениях диаметром 32 мм | D73: =Source!H80 -> 100 м | E73: =Source!I80 -> 0.4 | Q73: =Source!X80 -> 123.45 | R73: =Source!X81 -> 6788.71 | S73: =Source!Y80 -> 69.09 | T73: =Source!Y81 -> 3799.18 | U73: =ROUND((175/100)*ROUND(Source!R80, 2), 2) -> 0.32 | V73: =ROUND((0/100)*ROUND(Source!R81, 2), 2) -> 0 | AC73: 0
C74: ="Объем: "&Source!I80&"=40/"&"100" -> Объем: 0,4=40/100
C75: ЗП | F75: =Source!AO80 -> 209.45 | G75: =Source!DG80 -> *1,15)*1,1 | H75: =Source!AV81 -> 1.067 | I75: =Source!S80 -> 113.08 | J75: =IF(Source!BA81<> 0, Source!BA81, 1) -> 54.99 | K75: =Source!S81 -> 6218.27
C76: ЭМ | F76: =Source!AM80 -> 4.01 | G76: =Source!DE80 -> *1,25)*1,1 | H76: =Source!AV81 -> 1.067 | I76: =Source!Q80 -> 2.35 | J76: =IF(Source!BB81<> 0, Source!BB81, 1) -> 12.5 | K76: =Source!Q81 -> 29.38
C77: в т.ч. ЗПМ | F77: =Source!AN80 -> 0.3 | G77: =Source!DF80 -> *1,25)*1,1 | H77: =Source!AV81 -> 1.067 | I77: =Source!R80 -> 0.18 | J77: =IF(Source!BS81<> 0, Source!BS81, 1) -> 54.99 | K77: =Source!R81 -> 9.9
C78: МР | F78: =Source!AL80 -> 26.88 | G78: =Source!DD80 | H78: =Source!AW81 -> 1 | I78: =Source!P80 -> 10.75 | J78: =IF(Source!BC81<> 0, Source!BC81, 1) -> 1.96 | K78: =Source!P81 -> 21.07
A79: 4,1 | B79: =Source!F82 -> 1.12-1-55 | C79: Узел трубопровода из стальных водогазопроводных оцинкованных труб, с гильзами, для водоснабжения, диаметр условного прохода 32 мм | D79: =Source!H82 -> м | E79: =Source!I82 -> 40 | F79: =Source!AK82 -> 51.28 | H79: =Source!AW83 -> 1 | I79: =Source!O82 -> 2051.2 | J79: =IF(Source!BC83<> 0, Source!BC83, 1) -> 20.71 | K79: =Source!O83 -> 42480.35 | Q79: =Source!X82 -> 0 | R79: =Source!X83 -> 0 | S79: =Source!Y82 -> 0 | T79: =Source!Y83 -> 0 | U79: =ROUND((175/100)*ROUND(Source!R82, 2), 2) -> 0 | V79: =ROUND((0/100)*ROUND(Source!R83, 2), 2) -> 0 | AC79: 3
A80: 4,2 | B80: =Source!F84 -> 1.13-4-64 | C80: Кран шаровой, латунный, никелированный, полнопроходной, с алюминиевой рукояткой, муфтовый, температура рабочей среды от -15 до +110°С, номинальное давление PN 4,0 МПа, номинальный диаметр DN 32 мм | D80: =Source!H84 -> шт. | E80: =Source!I84 -> 2 | F80: =Source!AK84 -> 113.32 | H80: =Source!AW85 -> 1 | I80: =Source!O84 -> 226.64 | J80: =IF(Source!BC85<> 0, Source!BC85, 1) -> 19.96 | K80: =Source!O85 -> 4523.73 | Q80: =Source!X84 -> 0 | R80: =Source!X85 -> 0 | S80: =Source!Y84 -> 0 | T80: =Source!Y85 -> 0 | U80: =ROUND((175/100)*ROUND(Source!R84, 2), 2) -> 0 | V80: =ROUND((0/100)*ROUND(Source!R85, 2), 2) -> 0 | AC80: 3
A81: 4,3 | B81: =Source!F86 -> 1.12-10-146 | C81: Хомут стальной, оцинкованный, двухболтовой, с поворотным механизмом, каучуковой прокладкой, для крепления труб диаметром от 16 до 20 мм, резьба М8/М10 | D81: =Source!H86 -> 100 шт. | E81: =Source!I86 -> 0.16 | F81: =Source!AK86 -> 526.22 | H81: =Source!AW87 -> 1 | I81: =Source!O86 -> 84.2 | J81: =IF(Source!BC87<> 0, Source!BC87, 1) -> 2.79 | K81: =Source!O87 -> 234.92 | Q81: =Source!X86 -> 0 | R81: =Source!X87 -> 0 | S81: =Source!Y86 -> 0 | T81: =Source!Y87 -> 0 | U81: =ROUND((175/100)*ROUND(Source!R86, 2), 2) -> 0 | V81: =ROUND((0/100)*ROUND(Source!R87, 2), 2) -> 0 | AC81: 3
C82: НР от ФОТ | D82: % | E82: =Source!BZ81 -> 109 | I82: =SUM(Q73:Q81) -> 123.45 | J82: =Source!AT81 -> 109 | K82: =SUM(R73:R81) -> 6788.71
C83: СП от ФОТ | D83: % | E83: =Source!CA81 -> 61 | I83: =SUM(S73:S82) -> 69.09 | J83: =Source!AU81 -> 61 | K83: =SUM(T73:T82) -> 3799.18
C84: ЗТР | D84: чел-ч | E84: =Source!AQ80 -> 16.83 | G84: =Source!DI80 -> *1,15)*1,1 | H84: =Source!AV81 -> 1.067 | I84: =Source!U80 -> 9.0865507
C85: Всего по позиции: | H85: =I75+I76+I78+I82+I83+SUM(I79:I81) -> 2680.76 | J85: =K75+K76+K78+K82+K83+SUM(K79:K81) -> 64095.61 | O85: =I75+I76+I78+I82+I83+SUM(I79:I81) -> 2680.76 | P85: =K75+K76+K78+K82+K83+SUM(K79:K81) -> 64095.61
A87: 5 | B87: 3.16-38-3 Поправка: О.П. п.3.4. 6 Поправка: О.П. п.3.4.30.в | C87: Прокладка трубопроводов из стальных труб на бессварных разъемных муфтовых соединениях диаметром 40 мм | D87: =Source!H96 -> 100 м | E87: =Source!I96 -> 0.37 | Q87: =Source!X96 -> 140.85 | R87: =Source!X97 -> 7745.33 | S87: =Source!Y96 -> 78.82 | T87: =Source!Y97 -> 4334.54 | U87: =ROUND((175/100)*ROUND(Source!R96, 2), 2) -> 0.56 | V87: =ROUND((0/100)*ROUND(Source!R97, 2), 2) -> 0 | AC87: 0
C88: ="Объем: "&Source!I96&"=37/"&"100" -> Объем: 0,37=37/100
C89: ЗП | F89: =Source!AO96 -> 258.11 | G89: =Source!DG96 -> *1,15)*1,1 | H89: =Source!AV97 -> 1.067 | I89: =Source!S96 -> 128.9 | J89: =IF(Source!BA97<> 0, Source!BA97, 1) -> 54.99 | K89: =Source!S97 -> 7088.21
C90: ЭМ | F90: =Source!AM96 -> 6.68 | G90: =Source!DE96 -> *1,25)*1,1 | H90: =Source!AV97 -> 1.067 | I90: =Source!Q96 -> 3.63 | J90: =IF(Source!BB97<> 0, Source!BB97, 1) -> 13.28 | K90: =Source!Q97 -> 48.21
C91: в т.ч. ЗПМ | F91: =Source!AN96 -> 0.59 | G91: =Source!DF96 -> *1,25)*1,1 | H91: =Source!AV97 -> 1.067 | I91: =Source!R96 -> 0.32 | J91: =IF(Source!BS97<> 0, Source!BS97, 1) -> 54.99 | K91: =Source!R97 -> 17.6
C92: МР | F92: =Source!AL96 -> 24.95 | G92: =Source!DD96 | H92: =Source!AW97 -> 1 | I92: =Source!P96 -> 9.23 | J92: =IF(Source!BC97<> 0, Source!BC97, 1) -> 2.17 | K92: =Source!P97 -> 20.03
A93: 5,1 | B93: =Source!F98 -> 1.12-1-56 | C93: Узел трубопровода из стальных водогазопроводных оцинкованных труб, с гильзами, для водоснабжения, диаметр условного прохода 40 мм | D93: =Source!H98 -> м | E93: =Source!I98 -> 37 | F93: =Source!AK98 -> 61.58 | H93: =Source!AW99 -> 1 | I93: =Source!O98 -> 2278.46 | J93: =IF(Source!BC99<> 0, Source!BC99, 1) -> 11.88 | K93: =Source!O99 -> 27068.1 | Q93: =Source!X98 -> 0 | R93: =Source!X99 -> 0 | S93: =Source!Y98 -> 0 | T93: =Source!Y99 -> 0 | U93: =ROUND((175/100)*ROUND(Source!R98, 2), 2) -> 0 | V93: =ROUND((0/100)*ROUND(Source!R99, 2), 2) -> 0 | AC93: 3
A94: 5,2 | B94: =Source!F100 -> 1.12-10-146 | C94: Хомут стальной, оцинкованный, двухболтовой, с поворотным механизмом, каучуковой прокладкой, для крепления труб диаметром от 16 до 20 мм, резьба М8/М10 | D94: =Source!H100 -> 100 шт. | E94: =Source!I100 -> 0.12 | F94: =Source!AK100 -> 526.22 | H94: =Source!AW101 -> 1 | I94: =Source!O100 -> 63.15 | J94: =IF(Source!BC101<> 0, Source!BC101, 1) -> 2.79 | K94: =Source!O101 -> 176.19 | Q94: =Source!X100 -> 0 | R94: =Source!X101 -> 0 | S94: =Source!Y100 -> 0 | T94: =Source!Y101 -> 0 | U94: =ROUND((175/100)*ROUND(Source!R100, 2), 2) -> 0 | V94: =ROUND((0/100)*ROUND(Source!R101, 2), 2) -> 0 | AC94: 3
C95: НР от ФОТ | D95: % | E95: =Source!BZ97 -> 109 | I95: =SUM(Q87:Q94) -> 140.85 | J95: =Source!AT97 -> 109 | K95: =SUM(R87:R94) -> 7745.33
C96: СП от ФОТ | D96: % | E96: =Source!CA97 -> 61 | I96: =SUM(S87:S95) -> 78.82 | J96: =Source!AU97 -> 61 | K96: =SUM(T87:T95) -> 4334.54
C97: ЗТР | D97: чел-ч | E97: =Source!AQ96 -> 20.97 | G97: =Source!DI96 -> *1,15)*1,1 | H97: =Source!AV97 -> 1.067 | I97: =Source!U96 -> 10.472614
C98: Всего по позиции: | H98: =I89+I90+I92+I95+I96+SUM(I93:I94) -> 2703.04 | J98: =K89+K90+K92+K95+K96+SUM(K93:K94) -> 46480.61 | O98: =I89+I90+I92+I95+I96+SUM(I93:I94) -> 2703.04 | P98: =K89+K90+K92+K95+K96+SUM(K93:K94) -> 46480.61
A100: 6 | B100: 3.16-38-4 Поправка: О.П. п.3.4. 6 Поправка: О.П. п.3.4.30.в | C100: Прокладка трубопроводов из стальных труб на бессварных разъемных муфтовых соединениях диаметром 50 мм | D100: =Source!H108 -> 100 м | E100: =Source!I108 -> 0.35 | Q100: =Source!X108 -> 146.8 | R100: =Source!X109 -> 8072.61 | S100: =Source!Y108 -> 82.15 | T100: =Source!Y109 -> 4517.7 | U100: =ROUND((175/100)*ROUND(Source!R108, 2), 2) -> 0.81 | V100: =ROUND((0/100)*ROUND(Source!R109, 2), 2) -> 0 | AC100: 0
C101: ="Объем: "&Source!I108&"=35/"&"100" -> Объем: 0,35=35/100
C102: ЗП | F102: =Source!AO108 -> 284.12 | G102: =Source!DG108 -> *1,15)*1,1 | H102: =Source!AV109 -> 1.067 | I102: =Source!S108 -> 134.22 | J102: =IF(Source!BA109<> 0, Source!BA109, 1) -> 54.99 | K102: =Source!S109 -> 7380.76
C103: ЭМ | F103: =Source!AM108 -> 9.45 | G103: =Source!DE108 -> *1,25)*1,1 | H103: =Source!AV109 -> 1.067 | I103: =Source!Q108 -> 4.85 | J103: =IF(Source!BB109<> 0, Source!BB109, 1) -> 13.57 | K103: =Source!Q109 -> 65.81
C104: в т.ч. ЗПМ | F104: =Source!AN108 -> 0.89 | G104: =Source!DF108 -> *1,25)*1,1 | H104: =Source!AV109 -> 1.067 | I104: =Source!R108 -> 0.46 | J104: =IF(Source!BS109<> 0, Source!BS109, 1) -> 54.99 | K104: =Source!R109 -> 25.3
C105: МР | F105: =Source!AL108 -> 24.93 | G105: =Source!DD108 | H105: =Source!AW109 -> 1 | I105: =Source!P108 -> 8.73 | J105: =IF(Source!BC109<> 0, Source!BC109, 1) -> 2.49 | K105: =Source!P109 -> 21.74
A106: 6,1 | B106: =Source!F110 -> 1.12-6-670 | C106: Трубы стальные сварные водогазопроводные, оцинкованные, обыкновенные, ГОСТ 3262-75, диаметр условного прохода 50 мм, толщина стенки 3,5 мм | D106: =Source!H110 -> м | E106: =Source!I110 -> 35 | F106: =Source!AK110 -> 52.61 | H106: =Source!AW111 -> 1 | I106: =Source!O110 -> 1841.35 | J106: =IF(Source!BC111<> 0, Source!BC111, 1) -> 7.64 | K106: =Source!O111 -> 14067.91 | Q106: =Source!X110 -> 0 | R106: =Source!X111 -> 0 | S106: =Source!Y110 -> 0 | T106: =Source!Y111 -> 0 | U106: =ROUND((175/100)*ROUND(Source!R110, 2), 2) -> 0 | V106: =ROUND((0/100)*ROUND(Source!R111, 2), 2) -> 0 | AC106: 3
A107: 6,2 | B107: =Source!F112 -> 1.12-10-146 | C107: Хомут стальной, оцинкованный, двухболтовой, с поворотным механизмом, каучуковой прокладкой, для крепления труб диаметром от 16 до 20 мм, резьба М8/М10 | D107: =Source!H112 -> 100 шт. | E107: =Source!I112 -> 0.11 | F107: =Source!AK112 -> 526.22 | H107: =Source!AW113 -> 1 | I107: =Source!O112 -> 57.88 | J107: =IF(Source!BC113<> 0, Source!BC113, 1) -> 2.79 | K107: =Source!O113 -> 161.49 | Q107: =Source!X112 -> 0 | R107: =Source!X113 -> 0 | S107: =Source!Y112 -> 0 | T107: =Source!Y113 -> 0 | U107: =ROUND((175/100)*ROUND(Source!R112, 2), 2) -> 0 | V107: =ROUND((0/100)*ROUND(Source!R113, 2), 2) -> 0 | AC107: 3
C108: НР от ФОТ | D108: % | E108: =Source!BZ109 -> 109 | I108: =SUM(Q100:Q107) -> 146.8 | J108: =Source!AT109 -> 109 | K108: =SUM(R100:R107) -> 8072.61
C109: СП от ФОТ | D109: % | E109: =Source!CA109 -> 61 | I109: =SUM(S100:S108) -> 82.15 | J109: =Source!AU109 -> 61 | K109: =SUM(T100:T108) -> 4517.7
C110: ЗТР | D110: чел-ч | E110: =Source!AQ108 -> 23.23 | G110: =Source!DI108 -> *1,15)*1,1 | H110: =Source!AV109 -> 1.067 | I110: =Source!U108 -> 10.974183
C111: Всего по позиции: | H111: =I102+I103+I105+I108+I109+SUM(I106:I107) -> 2275.98 | J111: =K102+K103+K105+K108+K109+SUM(K106:K107) -> 34288.02 | O111: =I102+I103+I105+I108+I109+SUM(I106:I107) -> 2275.98 | P111: =K102+K103+K105+K108+K109+SUM(K106:K107) -> 34288.02
...

Sheet Ведомость объемов работ
A1: =Source!B1 -> Smeta.RU (495) 974-1589
E3: "УТВЕРЖДАЮ"
D5: ___________________________
D7: ___________________________
D9: " ___ " ___________ 20 ___ г.
B12: =CONCATENATE("Ведомость объемов работ ", IF(Source!AN15<>"", Source!AN15," ")) -> Ведомость объемов работ
B13: =CONCATENATE(Source!F12, " ", Source!G12) -> Новый объект (ТСН-2001 (Мосгосэкспертиза)) 02-01-04 Система водоснабжения
A16: № п/п | B16: № в ЛСР | C16: Наименование работ и затрат | D16: Единица измерения | E16: Количество | F16: Ссылка на чертежи, спецификации | G16: Формула расчета, расчет объемов работ и расхода материалов | H16: Примечание
A17: 1 | B17: 2 | C17: 3 | D17: 4 | E17: 5 | F17: 6 | G17: 7 | H17: 8
A18: =CONCATENATE("Локальная смета: ", Source!G20) -> Локальная смета: Система водоснабжения
A19: =CONCATENATE("Раздел: ", Source!G24) -> Раздел: Водопровод хозяйственно-питьевой В1 (Подземная часть)
A20: 1 | B20: =Source!E28 -> 1 | C20: =Source!G28 -> Прокладка трубопроводов из стальных труб на бессварных разъемных муфтовых соединениях диаметром до 25 мм | D20: 100 м | E20: =Source!I28 -> 0.18 | F20: =Source!U24 | G20: ="=18/"&"100" -> =18/100
A21: 1.1 | B21: =Source!E30 -> 1,1 | C21: =Source!G30 -> Узел трубопровода из стальных водогазопроводных оцинкованных труб, с гильзами, для водоснабжения, диаметр условного прохода 15 мм | D21: м | E21: =Source!I30 -> 18 | F21: =Source!U24
A22: 1.2 | B22: =Source!E32 -> 1,2 | C22: =Source!G32 -> Кран шаровой, латунный, никелированный, полнопроходной, с алюминиевой рукояткой, муфтовый, температура рабочей среды от -15 до +110°С, номинальное давление PN 4,0 МПа, номинальный диаметр DN 15 мм | D22: шт. | E22: =Source!I32 -> 6 | F22: =Source!U24
A23: 1.3 | B23: =Source!E34 -> 1,3 | C23: =Source!G34 -> Кран шаровой, латунный, никелированный, спускной, с наружной резьбой, с насадкой для шланга, с алюминиевой рукояткой, температура рабочей среды от -15 до +90°С, пропускная способность 1,9 м3/ч, номинальное давление PN 1,0 МПа, номинальный диаметр DN 15 мм | D23: шт. | E23: =Source!I34 -> 44 | F23: =Source!U24
A24: 1.4 | B24: =Source!E36 -> 1,4 | C24: =Source!G36 -> Хомут стальной, оцинкованный, двухболтовой, с поворотным механизмом, каучуковой прокладкой, для крепления труб диаметром от 16 до 20 мм, резьба М8/М10 | D24: 100 шт. | E24: =Source!I36 -> 0.12 | F24: =Source!U24
A25: 2 | B25: =Source!E48 -> 2 | C25: =Source!G48 -> Прокладка трубопроводов из стальных труб на бессварных разъемных муфтовых соединениях диаметром до 25 мм | D25: 100 м | E25: =Source!I48 -> 1.1 | F25: =Source!U24 | G25: ="=110/"&"100" -> =110/100
A26: 2.1 | B26: =Source!E50 -> 2,1 | C26: =Source!G50 -> Узел трубопровода из стальных водогазопроводных оцинкованных труб, с гильзами, для водоснабжения, диаметр условного прохода 20 мм | D26: м | E26: =Source!I50 -> 110 | F26: =Source!U24
A27: 2.2 | B27: =Source!E52 -> 2,2 | C27: =Source!G52 -> Кран шаровой, латунный, никелированный, полнопроходной, с алюминиевой рукояткой, муфтовый, температура рабочей среды от -15 до +110°С, номинальное давление PN 4,0 МПа, номинальный диаметр DN 20 мм | D27: шт. | E27: =Source!I52 -> 24 | F27: =Source!U24
A28: 2.3 | B28: =Source!E54 -> 2,3 | C28: =Source!G54 -> Хомут стальной, оцинкованный, двухболтовой, с поворотным механизмом, каучуковой прокладкой, для крепления труб диаметром от 16 до 20 мм, резьба М8/М10 | D28: 100 шт. | E28: =Source!I54 -> 0.55 | F28: =Source!U24
A29: 3 | B29: =Source!E64 -> 3 | C29: =Source!G64 -> Прокладка трубопроводов из стальных труб на бессварных разъемных муфтовых соединениях диаметром до 25 мм | D29: 100 м | E29: =Source!I64 -> 1.75 | F29: =Source!U24 | G29: ="=175/"&"100" -> =175/100
A30: 3.1 | B30: =Source!E66 -> 3,1 | C30: =Source!G66 -> Узел трубопровода из стальных водогазопроводных оцинкованных труб, с гильзами, для водоснабжения, диаметр условного прохода 25 мм | D30: м | E30: =Source!I66 -> 175 | F30: =Source!U24
A31: 3.2 | B31: =Source!E68 -> 3,2 | C31: =Source!G68 -> Хомут стальной, оцинкованный, двухболтовой, с поворотным механизмом, каучуковой прокладкой, для крепления труб диаметром от 16 до 20 мм, резьба М8/М10 | D31: 100 шт. | E31: =Source!I68 -> 0.87 | F31: =Source!U24
A32: 3.3 | B32: =Source!E70 -> 3,3 | C32: =Source!G70 -> Кран шаровой, латунный, никелированный, полнопроходной, с алюминиевой рукояткой, муфтовый, температура рабочей среды от -15 до +110°С, номинальное давление PN 4,0 МПа, номинальный диаметр DN 25 мм | D32: шт. | E32: =Source!I70 -> 14 | F32: =Source!U24
A33: 4 | B33: =Source!E80 -> 4 | C33: =Source!G80 -> Прокладка трубопроводов из стальных труб на бессварных разъемных муфтовых соединениях диаметром 32 мм | D33: 100 м | E33: =Source!I80 -> 0.4 | F33: =Source!U24 | G33: ="=40/"&"100" -> =40/100
A34: 4.1 | B34: =Source!E82 -> 4,1 | C34: =Source!G82 -> Узел трубопровода из стальных водогазопроводных оцинкованных труб, с гильзами, для водоснабжения, диаметр условного прохода 32 мм | D34: м | E34: =Source!I82 -> 40 | F34: =Source!U24
A35: 4.2 | B35: =Source!E84 -> 4,2 | C35: =Source!G84 -> Кран шаровой, латунный, никелированный, полнопроходной, с алюминиевой рукояткой, муфтовый, температура рабочей среды от -15 до +110°С, номинальное давление PN 4,0 МПа, номинальный диаметр DN 32 мм | D35: шт. | E35: =Source!I84 -> 2 | F35: =Source!U24
A36: 4.3 | B36: =Source!E86 -> 4,3 | C36: =Source!G86 -> Хомут стальной, оцинкованный, двухболтовой, с поворотным механизмом, каучуковой прокладкой, для крепления труб диаметром от 16 до 20 мм, резьба М8/М10 | D36: 100 шт. | E36: =Source!I86 -> 0.16 | F36: =Source!U24
A37: 5 | B37: =Source!E96 -> 5 | C37: =Source!G96 -> Прокладка трубопроводов из стальных труб на бессварных разъемных муфтовых соединениях диаметром 40 мм | D37: 100 м | E37: =Source!I96 -> 0.37 | F37: =Source!U24 | G37: ="=37/"&"100" -> =37/100
A38: 5.1 | B38: =Source!E98 -> 5,1 | C38: =Source!G98 -> Узел трубопровода из стальных водогазопроводных оцинкованных труб, с гильзами, для водоснабжения, диаметр условного прохода 40 мм | D38: м | E38: =Source!I98 -> 37 | F38: =Source!U24
A39: 5.2 | B39: =Source!E100 -> 5,2 | C39: =Source!G100 -> Хомут стальной, оцинкованный, двухболтовой, с поворотным механизмом, каучуковой прокладкой, для крепления труб диаметром от 16 до 20 мм, резьба М8/М10 | D39: 100 шт. | E39: =Source!I100 -> 0.12 | F39: =Source!U24
A40: 6 | B40: =Source!E108 -> 6 | C40: =Source!G108 -> Прокладка трубопроводов из стальных труб на бессварных разъемных муфтовых соединениях диаметром 50 мм | D40: 100 м | E40: =Source!I108 -> 0.35 | F40: =Source!U24 | G40: ="=35/"&"100" -> =35/100
A41: 6.1 | B41: =Source!E110 -> 6,1 | C41: =Source!G110 -> Трубы стальные сварные водогазопроводные, оцинкованные, обыкновенные, ГОСТ 3262-75, диаметр условного прохода 50 мм, толщина стенки 3,5 мм | D41: м | E41: =Source!I110 -> 35 | F41: =Source!U24
A42: 6.2 | B42: =Source!E112 -> 6,2 | C42: =Source!G112 -> Хомут стальной, оцинкованный, двухболтовой, с поворотным механизмом, каучуковой прокладкой, для крепления труб диаметром от 16 до 20 мм, резьба М8/М10 | D42: 100 шт. | E42: =Source!I112 -> 0.11 | F42: =Source!U24
A43: 7 | B43: =Source!E120 -> 7 | C43: =Source!G120 -> Прокладка трубопроводов из стальных труб на бессварных разъемных муфтовых соединениях диаметром 65 мм | D43: 100 м | E43: =Source!I120 -> 0.5 | F43: =Source!U24 | G43: ="=50/"&"100" -> =50/100
A44: 7.1 | B44: =Source!E122 -> 7,1 | C44: =Source!G122 -> Трубы стальные сварные водогазопроводные, оцинкованные, обыкновенные, ГОСТ 3262-75, диаметр условного прохода 65 мм, толщина стенки 4 мм | D44: м | E44: =Source!I122 -> 50 | F44: =Source!U24
A45: 7.2 | B45: =Source!E124 -> 7,2 | C45: =Source!G124 -> Хомут металлический для труб, диаметр от 104 до 112 мм | D45: шт. | E45: =Source!I124 -> 25 | F45: =Source!U24
A46: 8 | B46: =Source!E132 -> 8 | C46: =Source!G132 -> Прокладка трубопроводов из стальных труб на бессварных разъемных муфтовых соединениях диаметром 80 мм | D46: 100 м | E46: =Source!I132 -> 0.4 | F46: =Source!U24 | G46: ="=40/"&"100" -> =40/100
A47: 8.1 | B47: =Source!E134 -> 8,1 | C47: =Source!G134 -> Трубы стальные сварные водогазопроводные, оцинкованные, обыкновенные, ГОСТ 3262-75, диаметр условного прохода 80 мм, толщина стенки 4 мм | D47: м | E47: =Source!I134 -> 40 | F47: =Source!U24
A48: 8.2 | B48: =Source!E136 -> 8,2 | C48: =Source!G136 -> Хомут металлический для труб, диаметр от 104 до 112 мм | D48: шт. | E48: =Source!I136 -> 25 | F48: =Source!U24
A49: 9 | B49: =Source!E144 -> 9 | C49: =Source!G144 -> Прокладка трубопроводов из стальных труб на бессварных разъемных муфтовых соединениях диаметром 100 мм | D49: 100 м | E49: =Source!I144 -> 0.05 | F49: =Source!U24 | G49: ="=5/"&"100" -> =5/100
A50: 9.1 | B50: =Source!E146 -> 9,1 | C50: =Source!G146 -> Трубы стальные сварные водогазопроводные, оцинкованные, обыкновенные, ГОСТ 3262-75, диаметр условного прохода 90 мм, толщина стенки 4 мм | D50: м | E50: =Source!I146 -> 5 | F50: =Source!U24
A51: 9.2 | B51: =Source!E148 -> 9,2 | C51: =Source!G148 -> Хомут металлический для труб, диаметр от 104 до 112 мм | D51: шт. | E51: =Source!I148 -> 2 | F51: =Source!U24
A52: 10 | B52: =Source!E156 -> 10 | C52: =Source!G156 -> Гидравлическое испытание трубопроводов систем отопления, водопровода и горячего водоснабжения диаметром до 50 мм | D52: 100 м трубопровода | E52: =Source!I156 -> 4.15 | F52: =Source!U24 | G52: ="=(18+"&"110+"&"175+"&"40+"&"37+"&"35)/"&"100" -> =(18+110+175+40+37+35)/100
A53: 11 | B53: =Source!E158 -> 11 | C53: =Source!G158 -> Гидравлическое испытание трубопроводов систем отопления, водопровода и горячего водоснабжения диаметром до 100 мм | D53: 100 м трубопровода | E53: =Source!I158 -> 0.95 | F53: =Source!U24 | G53: ="=(50+"&"40+"&"5)/"&"100" -> =(50+40+5)/100
A54: 12 | B54: =Source!E160 -> 12 | C54: =Source!G160 -> Прокладка напорного трубопровода водоснабжения и отопления из многослойного полипропилена, армированного стекловолокном, из заранее собранных узлов, наружный диаметр 20 мм | D54: 100 м | E54: =Source!I160 -> 0.35 | F54: =Source!U24 | G54: ="=35/"&"100" -> =35/100
A55: 12.1 | B55: =Source!E162 -> 12,1 | C55: =Source!G162 -> Хомут стальной, оцинкованный, двухболтовой, с поворотным механизмом, каучуковой прокладкой, для крепления труб диаметром от 16 до 20 мм, резьба М8/М10 | D55: 100 шт. | E55: =Source!I162 -> 0.15 | F55: =Source!U24
A56: 12.2 | B56: =Source!E164 -> 12,2 | C56: =Source!G164 -> Трубы напорные многослойные, армированные стекловолокном из полипропилена PPR100/PPRGF/PPR100, ГОСТ 32415-2013, диаметр 20 мм, толщина стенки 2,8 мм | D56: м | E56: =Source!I164 -> 35.875 | F56: =Source!U24
A57: 12.3 | B57: =Source!E166 -> 12,3 | C57: =Source!G166 -> Муфта из полипропилена PP-R тип 3 (PRC-R), ГОСТ 32415-2013, комбинированная разъемная, наружная резьба, диаметр 20-20 мм/Ду=15мм | D57: шт. | E57: =Source!I166 -> 15 | F57: =Source!U24
A58: 12.4 | B58: =Source!E168 -> 12,4 | C58: =Source!G168 -> Тройник из полипропилена PP-R, ГОСТ 32415-2013, равнопроходной, номинальное давление PN 25, номинальный диаметр DN 20 мм /Ду=15мм | D58: шт. | E58: =Source!I168 -> 12 | F58: =Source!U24
A59: 12.5 | B59: =Source!E170 -> 12,5 | C59: =Source!G170 -> Уголок 90° из полипропилена PP-R тип 3 (PRC-R), ГОСТ 32415-2013, наружный диаметр 16 мм | D59: шт. | E59: =Source!I170 -> 20 | F59: =Source!U24
A60: 12.6 | B60: =Source!E172 -> 12,6 | C60: =Source!G172 -> Сверло победитовое, диаметр 8 мм, длина 80 мм | D60: шт. | E60: =Source!I172 -> 0.3675 | F60: =Source!U24
A61: 13 | B61: =Source!E174 -> 13 | C61: =Source!G174 -> Сборка узла напорного трубопровода водоснабжения и отопления из многослойного полипропилена, армированного стекловолокном, раструбная сварка, наружный диаметр 20 мм | D61: 100 сварных соединений | E61: =Source!I174 -> 1.06 | F61: =Source!U24 | G61: ="=(2*"&"15+"&"3*"&"12+"&"2*"&"20)/"&"100" -> =(2*15+3*12+2*20)/100
A62: 14 | B62: =Source!E177 -> 14 | C62: =Source!G177 -> Установка вентилей, задвижек, затворов, клапанов обратных, кранов проходных на трубопроводах из стальных труб диаметром до 100 мм | D62: 1 ШТ. | E62: =Source!I177 -> 1 | F62: =Source!U24 | G62: =Source!I177 -> 1
A63: 14.1 | B63: =Source!E179 -> 14,1 | C63: =Source!G179 -> Фланец стальной плоский приварной с соединительным выступом, ГОСТ 33259-2015, из стали Ст3сп, номинальное давление PN 1,6 МПа, номинальный диаметр DN 100 мм | D63: шт. | E63: =Source!I179 -> 2 | F63: =Source!U24
A64: 14.2 | B64: =Source!E181 -> 14,2 | C64: =Source!G181 -> Задвижка с обрезиненным клином, чугунная, с невыдвижным шпинделем, фланцевая, с ручным приводом, МЗВ (30ч39р), номинальное давление PN 1,6 МПа, номинальный диаметр DN 100 мм | D64: шт. | E64: =Source!I181 -> 1 | F64: =Source!U24
A65: 15 | B65: =Source!E183 -> 15 | C65: =Source!G183 -> Установка вентилей, задвижек, затворов, клапанов обратных, кранов проходных на трубопроводах из стальных труб диаметром до 100 мм | D65: 1 ШТ. | E65: =Source!I183 -> 1 | F65: =Source!U24 | G65: =Source!I183 -> 1
A66: 15.1 | B66: =Source!E185 -> 15,1 | C66: =Source!G185 -> Фланец стальной плоский приварной с соединительным выступом, ГОСТ 33259-2015, из стали Ст3сп, номинальное давление PN 1,6 МПа, номинальный диаметр DN 100 мм | D66: шт. | E66: =Source!I185 -> 2 | F66: =Source!U24
A67: 15.2 | B67: =Source!E187 -> 15,2 | C67: =Source!G187 -> Клапан обратный, чугунный, фланцевый, температура рабочей среды от -10 до +100°С, условная пропускная способность 396 м3/ч, номинальное давление РN 1,6 МПа, номинальный диаметр DN 100 мм | D67: шт. | E67: =Source!I187 -> 1 | F67: =Source!U24
A68: 16 | B68: =Source!E189 -> 16 | C68: =Source!G189 -> Кран шаровой, латунный, никелированный, полнопроходной, с алюминиевой рукояткой, муфтовый, температура рабочей среды от -15 до +110°С, номинальное давление PN 4,0 МПа, номинальный диаметр DN 15 мм | D68: шт. | E68: =Source!I189 -> 2 | F68: =Source!U24 | G68: =Source!I189 -> 2
A69: 17 | B69: =Source!E195 -> 17 | C69: =Source!G195 -> Установка фильтров диаметром до 25 мм | D69: 1 фильтр | E69: =Source!I195 -> 2 | F69: =Source!U24 | G69: =Source!I195 -> 2
A70: 17.1 | B70: =Source!E197 -> 17,1 | C70: =Source!G197 -> Фильтр сетчатый, латунный, муфтовый, со сливной пробкой, температура рабочей среды до +110°С, номинальное давление PN 1,6 МПа, номинальный диаметр DN 15 мм | D70: шт. | E70: =Source!I197 -> 2 | F70: =Source!U24
A71: 18 | B71: =Source!E199 -> 18 | C71: =Source!G199 -> Установка прибора на резьбовых соединениях | D71: 1 ШТ. | E71: =Source!I199 -> 2 | F71: =Source!U24 | G71: =Source!I199 -> 2
A72: 18.1 | B72: =Source!E201 -> 18,1 | C72: =Source!G201 -> Редуктор давления "после себя" муфтовый ф15 | D72: шт. | E72: =Source!I201 -> 2 | F72: =Source!U24
A73: 19 | B73: =Source!E203 -> 19 | C73: =Source!G203 -> Клапан обратный общего назначения, латунный, с внутренней резьбой, температура до +100°С, номинальное давление PN 1,2 МПа, номинальный диаметр DN 15 мм | D73: шт. | E73: =Source!I203 -> 2 | F73: =Source!U24 | G73: =Source!I203 -> 2
A74: 20 | B74: =Source!E209 -> 20 | C74: =Source!G209 -> Установка кранов поливочных, диаметром 25 мм | D74: 1 кран | E74: =Source!I209 -> 7 | F74: =Source!U24 | G74: ="=1*"&"7" -> =1*7
A75: 20.1 | B75: =Source!E211 -> 20,1 | C75: =Source!G211 -> Кран шаровой, латунный, никелированный, полнопроходной, с алюминиевой рукояткой, муфтовый, температура рабочей среды от -15 до +110°С, номинальное давление PN 4,0 МПа, номинальный диаметр DN 25 мм | D75: шт. | E75: =Source!I211 -> 7 | F75: =Source!U24
A76: 20.2 | B76: =Source!E213 -> 20,2 | C76: =Source!G213 -> Рукав резиновый, напорный, с текстильным каркасом, для воды, рабочее давление 1,0 МПа, внутренний диаметр 25 мм | D76: м | E76: =Source!I213 -> 245 | F76: =Source!U24
A77: 21 | B77: =Source!E215 -> 21 | C77: =Source!G215 -> Клапан обратный общего назначения, латунный, с внутренней резьбой, температура до +100°С, номинальное давление PN 1,2 МПа, номинальный диаметр DN 25 мм | D77: шт. | E77: =Source!I215 -> 7 | F77: =Source!U24 | G77: =Source!I215 -> 7
A78: 22 | B78: =Source!E221 -> 22 | C78: =Source!G221 -> Изоляция трубопроводов изделиями из вспененного каучука, вспененного полиэтилена, трубками | D78: 10 м изоляции | E78: =Source!I221 -> 51 | F78: =Source!U24 | G78: ="=(18+"&"110+"&"175+"&"40+"&"37+"&"35+"&"50+"&"40+"&"5)/"&"10" -> =(18+110+175+40+37+35+50+40+5)/10
A79: 22.1 | B79: =Source!E223 -> 22,1 | C79: =Source!G223 -> Трубка теплоизоляционная из вспененного полиэтилена с закрытой ячеистой структурой, для тепло- и шумоизоляции внутренних инженерных систем, температура применения до +95°C, коэффициент теплопроводности при температуре +10°C не более 0,038 Вт/(м х К), группа горючести Г1, внутренний диаметр 22 мм, толщина 9 мм_ф15мм | D79: м | E79: =Source!I223 -> 18.9 | F79: =Source!U24
A80: 22.2 | B80: =Source!E225 -> 22,2 | C80: =Source!G225 -> Трубка теплоизоляционная из вспененного полиэтилена с закрытой ячеистой структурой, для тепло- и шумоизоляции внутренних инженерных систем, температура применения до +95°C, коэффициент теплопроводности при температуре +10°C не более 0,038 Вт/(м х К), группа горючести Г1, внутренний диаметр 22 мм, толщина 9 мм | D80: м | E80: =Source!I225 -> 115.5 | F80: =Source!U24
A81: 22.3 | B81: =Source!E227 -> 22,3 | C81: =Source!G227 -> Трубка теплоизоляционная из вспененного полиэтилена с закрытой ячеистой структурой, для тепло- и шумоизоляции внутренних инженерных систем, температура применения до +95°C, коэффициент теплопроводности при температуре +10°C не более 0,038 Вт/(м х К), группа горючести Г1, внутренний диаметр 28 мм, толщина 9 мм | D81: м | E81: =Source!I227 -> 183.75 | F81: =Source!U24
A82: 22.4 | B82: =Source!E229 -> 22,4 | C82: =Source!G229 -> Трубка теплоизоляционная из вспененного полиэтилена с закрытой ячеистой структурой, для тепло- и шумоизоляции внутренних инженерных систем, температура применения до +95°C, коэффициент теплопроводности при температуре +10°C не более 0,038 Вт/(м х К), группа горючести Г1, внутренний диаметр 35 мм, толщина 9 мм | D82: м | E82: =Source!I229 -> 42 | F82: =Source!U24
A83: 22.5 | B83: =Source!E231 -> 22,5 | C83: =Source!G231 -> Трубка теплоизоляционная из вспененного полиэтилена с закрытой ячеистой структурой, для тепло- и шумоизоляции внутренних инженерных систем, температура применения до +95°C, коэффициент теплопроводности при температуре +10°C не более 0,038 Вт/(м х К), группа горючести Г1, внутренний диаметр 42 мм, толщина 9 мм | D83: м | E83: =Source!I231 -> 38.85 | F83: =Source!U24
A84: 22.6 | B84: =Source!E233 -> 22,6 | C84: =Source!G233 -> Трубка теплоизоляционная из вспененного полиэтилена с закрытой ячеистой структурой, для тепло- и шумоизоляции внутренних инженерных систем, температура применения до +95°C, коэффициент теплопроводности при температуре +10°C не более 0,038 Вт/(м х К), группа горючести Г1, внутренний диаметр 60 мм, толщина 9 мм | D84: м | E84: =Source!I233 -> 36.75 | F84: =Source!U24
A85: 22.7 | B85: =Source!E235 -> 22,7 | C85: =Source!G235 -> Трубка теплоизоляционная из вспененного полиэтилена с закрытой ячеистой структурой, для тепло- и шумоизоляции внутренних инженерных систем, температура применения до +95°C, коэффициент теплопроводности при температуре +10°C не более 0,038 Вт/(м х К), группа горючести Г1, внутренний диаметр 76 мм, толщина 9 мм | D85: м | E85: =Source!I235 -> 52.5 | F85: =Source!U24
A86: 22.8 | B86: =Source!E237 -> 22,8 | C86: =Source!G237 -> Трубка теплоизоляционная из вспененного полиэтилена с закрытой ячеистой структурой, для тепло- и шумоизоляции внутренних инженерных систем, температура применения до +95°C, коэффициент теплопроводности при температуре +10°C не более 0,038 Вт/(м х К), группа горючести Г1, внутренний диаметр 89 мм, толщина 9 мм | D86: м | E86: =Source!I237 -> 42 | F86: =Source!U24
A87: 22.9 | B87: =Source!E239 -> 22,9 | C87: =Source!G239 -> Трубка теплоизоляционная из вспененного полиэтилена с закрытой ячеистой структурой, для тепло- и шумоизоляции внутренних инженерных систем, температура применения до +95°C, коэффициент теплопроводности при температуре +10°C не более 0,038 Вт/(м х К), группа горючести Г1, внутренний диаметр 114 мм, толщина 9 мм | D87: м | E87: =Source!I239 -> 5.25 | F87: =Source!U24
A88: =CONCATENATE("Раздел: ", Source!G272) -> Раздел: Водопровод хозяйственно-питьевой В1 (Надземная часть)
A89: 23 | B89: =Source!E276 -> 23 | C89: =Source!G276 -> Прокладка трубопроводов из стальных труб на бессварных разъемных муфтовых соединениях диаметром до 25 мм | D89: 100 м | E89: =Source!I276 -> 0.1 | F89: =Source!U272 | G89: ="=10/"&"100" -> =10/100
A90: 23.1 | B90: =Source!E278 -> 23,1 | C90: =Source!G278 -> Узел трубопровода из стальных водогазопроводных оцинкованных труб, с гильзами, для водоснабжения, диаметр условного прохода 15 мм | D90: м | E90: =Source!I278 -> 10 | F90: =Source!U272
A91: 23.2 | B91: =Source!E280 -> 23,2 | C91: =Source!G280 -> Хомут стальной, оцинкованный, двухболтовой, с поворотным механизмом, каучуковой прокладкой, для крепления труб диаметром от 16 до 20 мм, резьба М8/М10 | D91: 100 шт. | E91: =Source!I280 -> 0.07 | F91: =Source!U272
A92: 24 | B92: =Source!E288 -> 24 | C92: =Source!G288 -> Прокладка трубопроводов из стальных труб на бессварных разъемных муфтовых соединениях диаметром до 25 мм | D92: 100 м | E92: =Source!I288 -> 1.6 | F92: =Source!U272 | G92: ="=160/"&"100" -> =160/100
A93: 24.1 | B93: =Source!E290 -> 24,1 | C93: =Source!G290 -> Узел трубопровода из стальных водогазопроводных оцинкованных труб, с гильзами, для водоснабжения, диаметр условного прохода 20 мм | D93: м | E93: =Source!I290 -> 160 | F93: =Source!U272
A94: 24.2 | B94: =Source!E292 -> 24,2 | C94: =Source!G292 -> Хомут стальной, оцинкованный, двухболтовой, с поворотным механизмом, каучуковой прокладкой, для крепления труб диаметром от 16 до 20 мм, резьба М8/М10 | D94: 100 шт. | E94: =Source!I292 -> 0.54 | F94: =Source!U272
A95: 25 | B95: =Source!E294 -> 25 | C95: =Source!G294 -> Прокладка трубопроводов из стальных труб на бессварных разъемных муфтовых соединениях диаметром до 25 мм | D95: 100 м | E95: =Source!I294 -> 0.95 | F95: =Source!U272 | G95: ="=95/"&"100" -> =95/100
A96: 25.1 | B96: =Source!E296 -> 25,1 | C96: =Source!G296 -> Узел трубопровода из стальных водогазопроводных оцинкованных труб, с гильзами, для водоснабжения, диаметр условного прохода 20 мм | D96: м | E96: =Source!I296 -> 95 | F96: =Source!U272
A97: 25.2 | B97: =Source!E298 -> 25,2 | C97: =Source!G298 -> Хомут стальной, оцинкованный, двухболтовой, с поворотным механизмом, каучуковой прокладкой, для крепления труб диаметром от 16 до 20 мм, резьба М8/М10 | D97: 100 шт. | E97: =Source!I298 -> 0.32 | F97: =Source!U272
A98: 26 | B98: =Source!E300 -> 26 | C98: =Source!G300 -> Прокладка трубопроводов из стальных труб на бессварных разъемных муфтовых соединениях диаметром 32 мм | D98: 100 м | E98: =Source!I300 -> 0.55 | F98: =Source!U272 | G98: ="=55/"&"100" -> =55/100
A99: 26.1 | B99: =Source!E302 -> 26,1 | C99: =Source!G302 -> Узел трубопровода из стальных водогазопроводных оцинкованных труб, с гильзами, для водоснабжения, диаметр условного прохода 32 мм | D99: м | E99: =Source!I302 -> 55 | F99: =Source!U272
A100: 26.2 | B100: =Source!E304 -> 26,2 | C100: =Source!G304 -> Хомут стальной, оцинкованный, двухболтовой, с поворотным механизмом, каучуковой прокладкой, для крепления труб диаметром от 16 до 20 мм, резьба М8/М10 | D100: 100 шт. | E100: =Source!I304 -> 0.19 | F100: =Source!U272
A101: 27 | B101: =Source!E306 -> 27 | C101: =Source!G306 -> Гидравлическое испытание трубопроводов систем отопления, водопровода и горячего водоснабжения диаметром до 50 мм | D101: 100 м трубопровода | E101: =Source!I306 -> 3.2 | F101: =Source!U272 | G101: ="=(10+"&"160+"&"95+"&"55)/"&"100" -> =(10+160+95+55)/100
A102: 28 | B102: =Source!E308 -> 28 | C102: =Source!G308 -> Прокладка напорного трубопровода водоснабжения и отопления из многослойного полипропилена, армированного стекловолокном, из заранее собранных узлов, наружный диаметр 20 мм | D102: 100 м | E102: =Source!I308 -> 4.1 | F102: =Source!U272 | G102: ="=410/"&"100" -> =410/100
A103: 28.1 | B103: =Source!E310 -> 28,1 | C103: =Source!G310 -> Хомут стальной, оцинкованный, двухболтовой, с поворотным механизмом, каучуковой прокладкой, для крепления труб диаметром от 16 до 20 мм, резьба М8/М10 | D103: 100 шт. | E103: =Source!I310 -> 3.28 | F103: =Source!U272
A104: 28.2 | B104: =Source!E312 -> 28,2 | C104: =Source!G312 -> Трубы напорные многослойные, армированные стекловолокном из полипропилена PPR100/PPRGF/PPR100, ГОСТ 32415-2013, диаметр 20 мм, толщина стенки 2,8 мм | D104: м | E104: =Source!I312 -> 420.25 | F104: =Source!U272
A105: 28.3 | B105: =Source!E314 -> 28,3 | C105: =Source!G314 -> Муфта из полипропилена PP-R тип 3 (PRC-R), ГОСТ 32415-2013, комбинированная разъемная, наружная резьба, диаметр 20-20 мм/Ду=15мм | D105: шт. | E105: =Source!I314 -> 430 | F105: =Source!U272
A106: 28.4 | B106: =Source!E316 -> 28,4 | C106: =Source!G316 -> Муфта из полипропилена PP-R, ГОСТ 32415-2013, переходная, номинальное давление PN 25, номинальный диаметр DN 25х20 мм /Ду20х15 | D106: шт. | E106: =Source!I316 -> 60 | F106: =Source!U272
A107: 28.5 | B107: =Source!E318 -> 28,5 | C107: =Source!G318 -> Тройник из полипропилена PP-R, ГОСТ 32415-2013, равнопроходной, номинальное давление PN 25, номинальный диаметр DN 20 мм /Ду=15мм | D107: шт. | E107: =Source!I318 -> 70 | F107: =Source!U272
A108: 28.6 | B108: =Source!E320 -> 28,6 | C108: =Source!G320 -> Тройник из полипропилена PP-R тип 3 (PRC-R), ГОСТ 32415-2013, переходной, диаметр 25-20-20 мм /Ду20х25х20 | D108: шт. | E108: =Source!I320 -> 10 | F108: =Source!U272
...

Sheet Source
A1: 0 | B1: Smeta.RU (495) 974-1589 | D1: _PS_ | F1: 0 | G1: 0 | H1: 0 | I1: Smeta.RU | K1: 1 | L1: 74402 | M1: 10 | N1: 12 | O1: 0 | P1: 0 | Q1: 3
A4: 1 | B4: 1 | C4: -1 | G4: Капитальный ремонт здания Государственного бюджетного общеобразовательного учреждения города Москвы "Школа № 236" по адресу: г. Москва ул. Клязьминская, д. 7 к. 4. 1 этап | EC4: 0
A12: 1 | B12: 1028 | C12: 0 | D12: =ROW(A987) -> 987 | E12: 0 | F12: Новый объект (ТСН-2001 (Мосгосэкспертиза)) | G12: 02-01-04 Система водоснабжения | I12: 0 | K12: 0 | L12: 0 | M12: 4098 | O12: 0 | P12: 0 | Q12: 0 | R12: 0 | S12: 0 | T12: 1 | V12: 0 | AB12: Кузнецова Е.А. | BB12: 0 | BH12: Сметные нормы списания | BI12: Коды ОКП для ТСН-2001 МГЭ Дополнение 80 | BJ12: 1 | BK12: 1 | BL12: 0 | BM12: 0 | BN12: 1 | BO12: 0 | BP12: 6 | BQ12: 2 | BR12: 1 | BS12: 1 | BT12: 0 | BU12: 0 | BV12: 1 | BW12: 0 | BX12: 0 | BZ12: Типовой расчет для ТСН-2001 МГЭ, Дополнение 80, ремонт | CA12: Территориальные сметные нормативы для Москвы ТСН-2001 (МГЭ), дополнение 80 | CB12: Территориальные сметные нормативы для Москвы ТСН-2001 (МГЭ), дополнение 80 | CC12: Территориальные сметные нормативы для Москвы ТСН-2001 (МГЭ), дополнение 80 | CD12: Территориальные сметные нормативы для Москвы ТСН-2001 (МГЭ), дополнение 80 | CE12: Поправки для ТСН-2001 от 03.02.2026 г. доп.80 | CF12: 0 | CG12: 0 | CH12: 327688 | CK12: 81 | CQ12: Территориальные сметные нормативы для Москвы (ТСН-2001) | CR12: ТЕР | CS12: 41660 | CT12: 1 | CU12: 80 | CY12: 0 | EC12: 0
A15: 15 | B15: 1
A18: 52 | B18: =B987 -> 1028 | C18: =C987 -> 1 | D18: =D987 -> 12 | E18: =E987 -> 0 | F18: =F987 -> Новый объект (ТСН-2001 (Мосгосэкспертиза)) | G18: =G987 -> 02-01-04 Система водоснабжения | O18: =O987 -> 548525.22 | P18: =P987 -> 522059.51 | Q18: =Q987 -> 1991.9 | R18: =R987 -> 176.35 | S18: =S987 -> 24473.81 | T18: =T987 -> 0 | U18: =U987 -> 1905.881 | V18: =V987 -> 0 | ... GX18: =GX987 -> 0
A20: 3 | B20: 1 | D20: =ROW(A957) -> 957 | F20: 02-01-04 | G20: Система водоснабжения | I20: 0 | J20: 2024-00272-00-0-ИОС2 | K20: -1 | L20: 02-01-04 | S20: 0 | T20: 0 | V20: 0 | BX20: 0 | CF20: 0 | CG20: 0
A22: 52 | B22: =B957 -> 1 | C22: =C957 -> 3 | D22: =D957 -> 20 | E22: =E957 -> 0 | F22: =F957 -> 02-01-04 | G22: =G957 -> Система водоснабжения | O22: =O957 -> 548525.22 | P22: =P957 -> 522059.51 | Q22: =Q957 -> 1991.9 | R22: =R957 -> 176.35 | S22: =S957 -> 24473.81 | T22: =T957 -> 0 | U22: =U957 -> 1905.881 | V22: =V957 -> 0 | ... GX22: =GX957 -> 0
A24: 4 | B24: 1 | D24: =ROW(A242) -> 242 | F24: Новый раздел | G24: Водопровод хозяйственно-питьевой В1 (Подземная часть) | I24: 0 | K24: 0 | S24: 0 | T24: 0 | V24: 0 | BX24: 0 | CJ24: 0
A26: 52 | B26: =B242 -> 1 | C26: =C242 -> 4 | D26: =D242 -> 24 | E26: =E242 -> 0 | F26: =F242 -> Новый раздел | G26: =G242 -> Водопровод хозяйственно-питьевой В1 (Подземная часть) | O26: =O242 -> 59830.96 | P26: =P242 -> 55248.57 | Q26: =Q242 -> 147.9 | R26: =R242 -> 15.15 | S26: =S242 -> 4434.49 | T26: =T242 -> 0 | U26: =U242 -> 343.43591 | V26: =V242 -> 0 | ... GX26: =GX242 -> 0
A28: 17 | B28: 1 | C28: =ROW(SmtRes!A12) -> 12 | D28: =ROW(EtalonRes!A11) -> 11 | E28: 1 | F28: 3.16-38-1 | G28: Прокладка трубопроводов из стальных труб на бессварных разъемных муфтовых соединениях диаметром до 25 мм | H28: 100 м | I28: =ROUND(ROUND(18/100,4),9) -> 0.18 | J28: 0 | K28: =ROUND(ROUND(18/100,4),9) -> 0.18 | O28: =ROUND(CP28,2) -> 64.02 | P28: =ROUND((ROUND((AC28*AW28*I28),2)*BC28),2) -> 5.41 | Q28: =(ROUND((ROUND(((((ET28*1.25)*1.1))*AV28*I28),2)*BB28),2)+ROUND((ROUND(((AE28-(((EU28*1.25)*1.1)))*AV28*I28),2)*BS28),2)) -> 1.07 | R28: =ROUND((ROUND((AE28*AV28*I28),2)*BS28),2) -> 0.08 | S28: =ROUND((ROUND((AF28*AV28*I28),2)*BA28),2) -> 57.54 | T28: =ROUND(CU28*I28,2) -> 0 | U28: =CV28*I28 -> 4.6453168 | V28: =CW28*I28 -> 0 | W28: =ROUND(CX28*I28,2) -> 0 | X28: =ROUND(CY28,2) -> 62.81 | Y28: =ROUND(CZ28,2) -> 35.15 | AA28: 59204062 | AB28: =ROUND((AC28+AD28+AF28),6) -> 335.2262 | AC28: =ROUND((ES28),6) -> 30.04 | AD28: =ROUND((((((ET28*1.25)*1.1))-(((EU28*1.25)*1.1)))+AE28),6) -> 5.59625 | AE28: =ROUND((((EU28*1.25)*1.1)),6) -> 0.4125 | AF28: =ROUND((((EV28*1.15)*1.1)),6) -> 299.58995 | AG28: =ROUND((AP28),6) -> 0 | AH28: =(((EW28*1.15)*1.1)) -> 24.1868 | AI28: =(((EX28*1.25)*1.1)) -> 0 | AJ28: =(AS28) -> 0 | AK28: 270.94 | AL28: 30.04 | AM28: 4.07 | AN28: 0.3 | AO28: 236.83 | AP28: 0 | AQ28: 19.12 | AR28: 0 | AS28: 0 | AT28: 109 | AU28: 61 | AV28: 1.067 | AW28: 1 | AZ28: 1 | BA28: 1 | BB28: 1 | BC28: 1 | BH28: 0 | BI28: 1 | BJ28: ТСН-2001.3 Доп. 80, Сб. 16, т. 38, поз. 1 | BM28: 21 | BN28: 0 | BO28: 3.16-38-1 | BP28: 1 | BQ28: 30 | BR28: 0 | BS28: 1 | BT28: 1 | BU28: 1 | BV28: 1 | BW28: 1 | BX28: 1 | BZ28: 109 | CA28: 61 | CE28: 30 | CF28: 0 | CG28: 0 | CM28: 0 | CN28: Поправка: О.П. п.3.4. 6 Наименование: Выполняемые при ремонте и реконструкции работы аналогичные технологическим процессам, характерным для нового строительства и отсутствующим в сборниках на ремонтно-строительные работы Поправка: О.П. п.3.4.30.в Наименование: При применении территориальных сметных нормативов для города Москвы затраты, учитывающие напряженные и стесненные условия производства работ (стесненность, сложность складирования и транспортной логистики и т.п.), исчисляются с применением коэффициентов к затратам труда и заработной плате рабочих, машинистов, времени эксплуатации машин и механизмов, стоимости эксплуатации машин в размере: для объектов, расположенных за пределами Третьего транспортного кольца города Москвы, но в пределах Московской кольцевой автомобильной дороги | CO28: 0 | CP28: =(P28+Q28+S28) -> 64.02 | CQ28: =ROUND((ROUND((AC28*AW28*1),2)*BC28),2) -> 30.04 | CR28: =(ROUND((ROUND(((((ET28*1.25)*1.1))*AV28*1),2)*BB28),2)+ROUND((ROUND(((AE28-(((EU28*1.25)*1.1)))*AV28*1),2)*BS28),2)) -> 5.97 | CS28: =ROUND((ROUND((AE28*AV28*1),2)*BS28),2) -> 0.44 | CT28: =ROUND((ROUND((AF28*AV28*1),2)*BA28),2) -> 319.66 | CU28: =AG28 -> 0 | CV28: =(AH28*AV28) -> 25.807316 | CW28: =AI28 -> 0 | CX28: =AJ28 -> 0 | CY28: =(((S28+R28)*AT28)/100) -> 62.8058 | CZ28: =(((S28+R28)*AU28)/100) -> 35.1482 | DB28: 1 | DE28: *1,25)*1,1 | DF28: *1,25)*1,1 | DG28: *1,15)*1,1 | DI28: *1,15)*1,1 | DJ28: *1,25)*1,1 | DN28: 0 | DO28: 0 | DP28: 1 | DQ28: 1 | DU28: 1003 | DV28: 100 м | DW28: 100 м | DX28: 100 | EE28: 58807897 | EF28: 30 | EG28: Строительные работы | EH28: 0 | EJ28: 1 | EK28: 21 | EL28: ТСН-2001.3-16. Трубопроводы внутренние | EM28: ТСН-2001.3-16-1 | EO28: Поправка: О.П. п.3.4. 6 Поправка: О.П. п.3.4.30.в | EQ28: 0 | ER28: 270.94 | ES28: 30.04 | ET28: 4.07 | EU28: 0.3 | EV28: 236.83 | EW28: 19.12 | EX28: 0 | EY28: 0 | FQ28: 0 | FR28: 0 | FS28: 0 | FX28: 109 | FY28: 61 | GD28: 1 | GF28: -367569951 | GG28: 2 | GH28: 1 | GI28: 2 | GJ28: 0 | GK28: 0 | GL28: =ROUND(IF(AND(BH28=3,BI28=3,FS28<>0),P28,0),2) -> 0 | GM28: =ROUND(O28+X28+Y28,2)+GX28 -> 161.98 | GN28: =IF(OR(BI28=0,BI28=1),GM28-GX28,0) -> 161.98 | GO28: =IF(BI28=2,GM28-GX28,0) -> 0 | GP28: =IF(BI28=4,GM28-GX28,0) -> 0 | GR28: 0 | GS28: 3 | GT28: 0 | GV28: =ROUND((GT28),6) -> 0 | GW28: 1 | GX28: =ROUND(HC28*I28,2) -> 0 | HA28: 0 | HB28: 0 | HC28: =GV28*GW28 -> 0 | HS28: 0 | IK28: 0
A29: 17 | B29: 1 | C29: =ROW(SmtRes!A24) -> 24 | D29: =ROW(EtalonRes!A22) -> 22 | E29: 1 | F29: 3.16-38-1 | G29: Прокладка трубопроводов из стальных труб на бессварных разъемных муфтовых соединениях диаметром до 25 мм | H29: 100 м | I29: =ROUND(ROUND(18/100,4),9) -> 0.18 | J29: 0 | K29: =ROUND(ROUND(18/100,4),9) -> 0.18 | O29: =ROUND(CP29,2) -> 3187.11 | P29: =ROUND((ROUND((AC29*AW29*I29),2)*BC29),2) -> 9.68 | Q29: =(ROUND((ROUND(((((ET29*1.25)*1.1))*AV29*I29),2)*BB29),2)+ROUND((ROUND(((AE29-(((EU29*1.25)*1.1)))*AV29*I29),2)*BS29),2)) -> 13.31 | R29: =ROUND((ROUND((AE29*AV29*I29),2)*BS29),2) -> 4.4 | S29: =ROUND((ROUND((AF29*AV29*I29),2)*BA29),2) -> 3164.12 | T29: =ROUND(CU29*I29,2) -> 0 | U29: =CV29*I29 -> 4.6453168 | V29: =CW29*I29 -> 0 | W29: =ROUND(CX29*I29,2) -> 0 | X29: =ROUND(CY29,2) -> 3453.69 | Y29: =ROUND(CZ29,2) -> 1932.8 | AA29: 59204059 | AB29: =ROUND((AC29+AD29+AF29),6) -> 335.2262 | AC29: =ROUND((ES29),6) -> 30.04 | AD29: =ROUND((((((ET29*1.25)*1.1))-(((EU29*1.25)*1.1)))+AE29),6) -> 5.59625 | AE29: =ROUND((((EU29*1.25)*1.1)),6) -> 0.4125 | AF29: =ROUND((((EV29*1.15)*1.1)),6) -> 299.58995 | AG29: =ROUND((AP29),6) -> 0 | AH29: =(((EW29*1.15)*1.1)) -> 24.1868 | AI29: =(((EX29*1.25)*1.1)) -> 0 | AJ29: =(AS29) -> 0 | AK29: 270.94 | AL29: 30.04 | AM29: 4.07 | AN29: 0.3 | AO29: 236.83 | AP29: 0 | AQ29: 19.12 | AR29: 0 | AS29: 0 | AT29: 109 | AU29: 61 | AV29: 1.067 | AW29: 1 | AZ29: 1 | BA29: 54.99 | BB29: 12.44 | BC29: 1.79 | BH29: 0 | BI29: 1 | BJ29: ТСН-2001.3 Доп. 80, Сб. 16, т. 38, поз. 1 | BM29: 21 | BN29: 0 | BO29: 3.16-38-1 | BP29: 1 | BQ29: 30 | BR29: 0 | BS29: 54.99 | BT29: 1 | BU29: 1 | BV29: 1 | BW29: 1 | BX29: 1 | BZ29: 109 | CA29: 61 | CE29: 30 | CF29: 0 | CG29: 0 | CM29: 0 | CN29: Поправка: О.П. п.3.4. 6 Наименование: Выполняемые при ремонте и реконструкции работы аналогичные технологическим процессам, характерным для нового строительства и отсутствующим в сборниках на ремонтно-строительные работы Поправка: О.П. п.3.4.30.в Наименование: При применении территориальных сметных нормативов для города Москвы затраты, учитывающие напряженные и стесненные условия производства работ (стесненность, сложность складирования и транспортной логистики и т.п.), исчисляются с применением коэффициентов к затратам труда и заработной плате рабочих, машинистов, времени эксплуатации машин и механизмов, стоимости эксплуатации машин в размере: для объектов, расположенных за пределами Третьего транспортного кольца города Москвы, но в пределах Московской кольцевой автомобильной дороги | CO29: 0 | CP29: =(P29+Q29+S29) -> 3187.11 | CQ29: =ROUND((ROUND((AC29*AW29*1),2)*BC29),2) -> 53.77 | CR29: =(ROUND((ROUND(((((ET29*1.25)*1.1))*AV29*1),2)*BB29),2)+ROUND((ROUND(((AE29-(((EU29*1.25)*1.1)))*AV29*1),2)*BS29),2)) -> 74.27 | CS29: =ROUND((ROUND((AE29*AV29*1),2)*BS29),2) -> 24.2 | CT29: =ROUND((ROUND((AF29*AV29*1),2)*BA29),2) -> 17578.1 | CU29: =AG29 -> 0 | CV29: =(AH29*AV29) -> 25.807316 | CW29: =AI29 -> 0 | CX29: =AJ29 -> 0 | CY29: =(((S29+R29)*AT29)/100) -> 3453.6868 | CZ29: =(((S29+R29)*AU29)/100) -> 1932.7972 | DB29: 3 | DE29: *1,25)*1,1 | DF29: *1,25)*1,1 | DG29: *1,15)*1,1 | DI29: *1,15)*1,1 | DJ29: *1,25)*1,1 | DN29: 0 | DO29: 0 | DP29: 1 | DQ29: 1 | DU29: 1003 | DV29: 100 м | DW29: 100 м | DX29: 100 | EE29: 58807897 | EF29: 30 | EG29: Строительные работы | EH29: 0 | EJ29: 1 | EK29: 21 | EL29: ТСН-2001.3-16. Трубопроводы внутренние | EM29: ТСН-2001.3-16-1 | EO29: Поправка: О.П. п.3.4. 6 Поправка: О.П. п.3.4.30.в | EQ29: 0 | ER29: 270.94 | ES29: 30.04 | ET29: 4.07 | EU29: 0.3 | EV29: 236.83 | EW29: 19.12 | EX29: 0 | EY29: 0 | FQ29: 0 | FR29: 0 | FS29: 0 | FX29: 109 | FY29: 61 | GD29: 1 | GF29: -367569951 | GG29: 2 | GH29: 1 | GI29: 2 | GJ29: 0 | GK29: 0 | GL29: =ROUND(IF(AND(BH29=3,BI29=3,FS29<>0),P29,0),2) -> 0 | GM29: =ROUND(O29+X29+Y29,2)+GX29 -> 8573.6 | GN29: =IF(OR(BI29=0,BI29=1),GM29-GX29,0) -> 8573.6 | GO29: =IF(BI29=2,GM29-GX29,0) -> 0 | GP29: =IF(BI29=4,GM29-GX29,0) -> 0 | GR29: 0 | GS29: 3 | GT29: 0 | GV29: =ROUND((GT29),6) -> 0 | GW29: 1 | GX29: =ROUND(HC29*I29,2) -> 0 | HA29: 0 | HB29: 0 | HC29: =GV29*GW29 -> 0 | HS29: 0 | IK29: 0
A30: 18 | B30: 1 | C30: 10 | E30: 1,1 | F30: 1.12-1-52 | G30: Узел трубопровода из стальных водогазопроводных оцинкованных труб, с гильзами, для водоснабжения, диаметр условного прохода 15 мм | H30: м | I30: =I28*J30 -> 18 | J30: 100 | K30: 100 | O30: =ROUND(CP30,2) -> 505.8 | P30: =ROUND((ROUND((AC30*AW30*I30),2)*BC30),2) -> 505.8 | Q30: =(ROUND((ROUND(((ET30)*AV30*I30),2)*BB30),2)+ROUND((ROUND(((AE30-(EU30))*AV30*I30),2)*BS30),2)) -> 0 | R30: =ROUND((ROUND((AE30*AV30*I30),2)*BS30),2) -> 0 | S30: =ROUND((ROUND((AF30*AV30*I30),2)*BA30),2) -> 0 | T30: =ROUND(CU30*I30,2) -> 0 | U30: =CV30*I30 -> 0 | V30: =CW30*I30 -> 0 | W30: =ROUND(CX30*I30,2) -> 0 | X30: =ROUND(CY30,2) -> 0 | Y30: =ROUND(CZ30,2) -> 0 | AA30: 59204062 | AB30: =ROUND((AC30+AD30+AF30),6) -> 28.1 | AC30: =ROUND((ES30),6) -> 28.1 | AD30: =ROUND((((ET30)-(EU30))+AE30),6) -> 0 | AE30: =ROUND((EU30),6) -> 0 | AF30: =ROUND((EV30),6) -> 0 | AG30: =ROUND((AP30),6) -> 0 | AH30: =(EW30) -> 0 | AI30: =(EX30) -> 0 | AJ30: =(AS30) -> 0 | AK30: 28.1 | AL30: 28.1 | AM30: 0 | AN30: 0 | AO30: 0 | AP30: 0 | AQ30: 0 | AR30: 0 | AS30: 0 | AT30: 109 | AU30: 61 | AV30: 1 | AW30: 1 | AZ30: 1 | BA30: 1 | BB30: 1 | BC30: 1 | BH30: 3 | BI30: 1 | BJ30: ТСН-2001.1 Доп. 79, Р. 12, о. 1, поз. 52 | BM30: 21 | BN30: 0 | BP30: 0 | BQ30: 30 | BR30: 0 | BS30: 1 | BT30: 1 | BU30: 1 | BV30: 1 | BW30: 1 | BX30: 1 | BZ30: 109 | CA30: 61 | CE30: 30 | CF30: 0 | CG30: 0 | CM30: 0 | CO30: 0 | CP30: =(P30+Q30+S30) -> 505.8 | CQ30: =ROUND((ROUND((AC30*AW30*1),2)*BC30),2) -> 28.1 | CR30: =(ROUND((ROUND(((ET30)*AV30*1),2)*BB30),2)+ROUND((ROUND(((AE30-(EU30))*AV30*1),2)*BS30),2)) -> 0 | CS30: =ROUND((ROUND((AE30*AV30*1),2)*BS30),2) -> 0 | CT30: =ROUND((ROUND((AF30*AV30*1),2)*BA30),2) -> 0 | CU30: =AG30 -> 0 | CV30: =(AH30*AV30) -> 0 | CW30: =AI30 -> 0 | CX30: =AJ30 -> 0 | CY30: =(((S30+R30)*AT30)/100) -> 0 | CZ30: =(((S30+R30)*AU30)/100) -> 0 | DN30: 0 | DO30: 0 | DP30: 1 | DQ30: 1 | DU30: 1003 | DV30: м | DW30: м | DX30: 1 | EE30: 58807897 | EF30: 30 | EG30: Строительные работы | EH30: 0 | EJ30: 1 | EK30: 21 | EL30: ТСН-2001.3-16. Трубопроводы внутренние | EM30: ТСН-2001.3-16-1 | EQ30: 0 | ER30: 28.1 | ES30: 28.1 | ET30: 0 | EU30: 0 | EV30: 0 | EW30: 0 | EX30: 0 | FQ30: 0 | FR30: 0 | FS30: 0 | FX30: 109 | FY30: 61 | GD30: 1 | GF30: 949658601 | GG30: 2 | GH30: 1 | GI30: -2 | GJ30: 0 | GK30: 0 | GL30: =ROUND(IF(AND(BH30=3,BI30=3,FS30<>0),P30,0),2) -> 0 | GM30: =ROUND(O30+X30+Y30,2)+GX30 -> 505.8 | GN30: =IF(OR(BI30=0,BI30=1),GM30-GX30,0) -> 505.8 | GO30: =IF(BI30=2,GM30-GX30,0) -> 0 | GP30: =IF(BI30=4,GM30-GX30,0) -> 0 | GR30: 0 | GS30: 3 | GT30: 0 | GV30: =ROUND((GT30),6) -> 0 | GW30: 1 | GX30: =ROUND(HC30*I30,2) -> 0 | HA30: 0 | HB30: 0 | HC30: =GV30*GW30 -> 0 | HS30: 0 | IK30: 0
A31: 18 | B31: 1 | C31: 22 | E31: 1,1 | F31: 1.12-1-52 | G31: Узел трубопровода из стальных водогазопроводных оцинкованных труб, с гильзами, для водоснабжения, диаметр условного прохода 15 мм | H31: м | I31: =I29*J31 -> 18 | J31: 100 | K31: 100 | O31: =ROUND(CP31,2) -> 9423.05 | P31: =ROUND((ROUND((AC31*AW31*I31),2)*BC31),2) -> 9423.05 | Q31: =(ROUND((ROUND(((ET31)*AV31*I31),2)*BB31),2)+ROUND((ROUND(((AE31-(EU31))*AV31*I31),2)*BS31),2)) -> 0 | R31: =ROUND((ROUND((AE31*AV31*I31),2)*BS31),2) -> 0 | S31: =ROUND((ROUND((AF31*AV31*I31),2)*BA31),2) -> 0 | T31: =ROUND(CU31*I31,2) -> 0 | U31: =CV31*I31 -> 0 | V31: =CW31*I31 -> 0 | W31: =ROUND(CX31*I31,2) -> 0 | X31: =ROUND(CY31,2) -> 0 | Y31: =ROUND(CZ31,2) -> 0 | AA31: 59204059 | AB31: =ROUND((AC31+AD31+AF31),6) -> 28.1 | AC31: =ROUND((ES31),6) -> 28.1 | AD31: =ROUND((((ET31)-(EU31))+AE31),6) -> 0 | AE31: =ROUND((EU31),6) -> 0 | AF31: =ROUND((EV31),6) -> 0 | AG31: =ROUND((AP31),6) -> 0 | AH31: =(EW31) -> 0 | AI31: =(EX31) -> 0 | AJ31: =(AS31) -> 0 | AK31: 28.1 | AL31: 28.1 | AM31: 0 | AN31: 0 | AO31: 0 | AP31: 0 | AQ31: 0 | AR31: 0 | AS31: 0 | AT31: 109 | AU31: 61 | AV31: 1 | AW31: 1 | AZ31: 1 | BA31: 1 | BB31: 1 | BC31: 18.63 | BH31: 3 | BI31: 1 | BJ31: ТСН-2001.1 Доп. 79, Р. 12, о. 1, поз. 52 | BM31: 21 | BN31: 0 | BO31: 1.12-1-52 | BP31: 1 | BQ31: 30 | BR31: 0 | BS31: 1 | BT31: 1 | BU31: 1 | BV31: 1 | BW31: 1 | BX31: 1 | BZ31: 109 | CA31: 61 | CE31: 30 | CF31: 0 | CG31: 0 | CM31: 0 | CO31: 0 | CP31: =(P31+Q31+S31) -> 9423.05 | CQ31: =ROUND((ROUND((AC31*AW31*1),2)*BC31),2) -> 523.5 | CR31: =(ROUND((ROUND(((ET31)*AV31*1),2)*BB31),2)+ROUND((ROUND(((AE31-(EU31))*AV31*1),2)*BS31),2)) -> 0 | CS31: =ROUND((ROUND((AE31*AV31*1),2)*BS31),2) -> 0 | CT31: =ROUND((ROUND((AF31*AV31*1),2)*BA31),2) -> 0 | CU31: =AG31 -> 0 | CV31: =(AH31*AV31) -> 0 | CW31: =AI31 -> 0 | CX31: =AJ31 -> 0 | CY31: =(((S31+R31)*AT31)/100) -> 0 | CZ31: =(((S31+R31)*AU31)/100) -> 0 | DN31: 0 | DO31: 0 | DP31: 1 | DQ31: 1 | DU31: 1003 | DV31: м | DW31: м | DX31: 1 | EE31: 58807897 | EF31: 30 | EG31: Строительные работы | EH31: 0 | EJ31: 1 | EK31: 21 | EL31: ТСН-2001.3-16. Трубопроводы внутренние | EM31: ТСН-2001.3-16-1 | EQ31: 0 | ER31: 28.1 | ES31: 28.1 | ET31: 0 | EU31: 0 | EV31: 0 | EW31: 0 | EX31: 0 | FQ31: 0 | FR31: 0 | FS31: 0 | FX31: 109 | FY31: 61 | GD31: 1 | GF31: 949658601 | GG31: 2 | GH31: 1 | GI31: 2 | GJ31: 0 | GK31: 0 | GL31: =ROUND(IF(AND(BH31=3,BI31=3,FS31<>0),P31,0),2) -> 0 | GM31: =ROUND(O31+X31+Y31,2)+GX31 -> 9423.05 | GN31: =IF(OR(BI31=0,BI31=1),GM31-GX31,0) -> 9423.05 | GO31: =IF(BI31=2,GM31-GX31,0) -> 0 | GP31: =IF(BI31=4,GM31-GX31,0) -> 0 | GR31: 0 | GS31: 3 | GT31: 0 | GV31: =ROUND((GT31),6) -> 0 | GW31: 1 | GX31: =ROUND(HC31*I31,2) -> 0 | HA31: 0 | HB31: 0 | HC31: =GV31*GW31 -> 0 | HS31: 0 | IK31: 0
A32: 18 | B32: 1 | C32: 12 | E32: 1,2 | F32: 1.13-4-61 | G32: Кран шаровой, латунный, никелированный, полнопроходной, с алюминиевой рукояткой, муфтовый, температура рабочей среды от -15 до +110°С, номинальное давление PN 4,0 МПа, номинальный диаметр DN 15 мм | H32: шт. | I32: =I28*J32 -> 6 | J32: 33.333333 | K32: 33.333333 | O32: =ROUND(CP32,2) -> 209.82 | P32: =ROUND((ROUND((AC32*AW32*I32),2)*BC32),2) -> 209.82 | Q32: =(ROUND((ROUND(((ET32)*AV32*I32),2)*BB32),2)+ROUND((ROUND(((AE32-(EU32))*AV32*I32),2)*BS32),2)) -> 0 | R32: =ROUND((ROUND((AE32*AV32*I32),2)*BS32),2) -> 0 | S32: =ROUND((ROUND((AF32*AV32*I32),2)*BA32),2) -> 0 | T32: =ROUND(CU32*I32,2) -> 0 | U32: =CV32*I32 -> 0 | V32: =CW32*I32 -> 0 | W32: =ROUND(CX32*I32,2) -> 0 | X32: =ROUND(CY32,2) -> 0 | Y32: =ROUND(CZ32,2) -> 0 | AA32: 59204062 | AB32: =ROUND((AC32+AD32+AF32),6) -> 34.97 | AC32: =ROUND((ES32),6) -> 34.97 | AD32: =ROUND((((ET32)-(EU32))+AE32),6) -> 0 | AE32: =ROUND((EU32),6) -> 0 | AF32: =ROUND((EV32),6) -> 0 | AG32: =ROUND((AP32),6) -> 0 | AH32: =(EW32) -> 0 | AI32: =(EX32) -> 0 | AJ32: =(AS32) -> 0 | AK32: 34.97 | AL32: 34.97 | AM32: 0 | AN32: 0 | AO32: 0 | AP32: 0 | AQ32: 0 | AR32: 0 | AS32: 0 | AT32: 109 | AU32: 61 | AV32: 1 | AW32: 1 | AZ32: 1 | BA32: 1 | BB32: 1 | BC32: 1 | BH32: 3 | BI32: 1 | BJ32: ТСН-2001.1 Доп. 73, Р. 13, о. 4, поз. 61 | BM32: 21 | BN32: 0 | BP32: 0 | BQ32: 30 | BR32: 0 | BS32: 1 | BT32: 1 | BU32: 1 | BV32: 1 | BW32: 1 | BX32: 1 | BZ32: 109 | CA32: 61 | CE32: 30 | CF32: 0 | CG32: 0 | CM32: 0 | CO32: 0 | CP32: =(P32+Q32+S32) -> 209.82 | CQ32: =ROUND((ROUND((AC32*AW32*1),2)*BC32),2) -> 34.97 | CR32: =(ROUND((ROUND(((ET32)*AV32*1),2)*BB32),2)+ROUND((ROUND(((AE32-(EU32))*AV32*1),2)*BS32),2)) -> 0 | CS32: =ROUND((ROUND((AE32*AV32*1),2)*BS32),2) -> 0 | CT32: =ROUND((ROUND((AF32*AV32*1),2)*BA32),2) -> 0 | CU32: =AG32 -> 0 | CV32: =(AH32*AV32) -> 0 | CW32: =AI32 -> 0 | CX32: =AJ32 -> 0 | CY32: =(((S32+R32)*AT32)/100) -> 0 | CZ32: =(((S32+R32)*AU32)/100) -> 0 | DN32: 0 | DO32: 0 | DP32: 1 | DQ32: 1 | DU32: 1010 | DV32: шт. | DW32: шт. | DX32: 1 | EE32: 58807897 | EF32: 30 | EG32: Строительные работы | EH32: 0 | EJ32: 1 | EK32: 21 | EL32: ТСН-2001.3-16. Трубопроводы внутренние | EM32: ТСН-2001.3-16-1 | EQ32: 0 | ER32: 34.97 | ES32: 34.97 | ET32: 0 | EU32: 0 | EV32: 0 | EW32: 0 | EX32: 0 | FQ32: 0 | FR32: 0 | FS32: 0 | FX32: 109 | FY32: 61 | GD32: 1 | GF32: -1914030801 | GG32: 2 | GH32: 1 | GI32: -2 | GJ32: 0 | GK32: 0 | GL32: =ROUND(IF(AND(BH32=3,BI32=3,FS32<>0),P32,0),2) -> 0 | GM32: =ROUND(O32+X32+Y32,2)+GX32 -> 209.82 | GN32: =IF(OR(BI32=0,BI32=1),GM32-GX32,0) -> 209.82 | GO32: =IF(BI32=2,GM32-GX32,0) -> 0 | GP32: =IF(BI32=4,GM32-GX32,0) -> 0 | GR32: 0 | GS32: 3 | GT32: 0 | GV32: =ROUND((GT32),6) -> 0 | GW32: 1 | GX32: =ROUND(HC32*I32,2) -> 0 | HA32: 0 | HB32: 0 | HC32: =GV32*GW32 -> 0 | HS32: 0 | IK32: 0
A33: 18 | B33: 1 | C33: 24 | E33: 1,2 | F33: 1.13-4-61 | G33: Кран шаровой, латунный, никелированный, полнопроходной, с алюминиевой рукояткой, муфтовый, температура рабочей среды от -15 до +110°С, номинальное давление PN 4,0 МПа, номинальный диаметр DN 15 мм | H33: шт. | I33: =I29*J33 -> 6 | J33: 33.333333 | K33: 33.333333 | O33: =ROUND(CP33,2) -> 3927.83 | P33: =ROUND((ROUND((AC33*AW33*I33),2)*BC33),2) -> 3927.83 | Q33: =(ROUND((ROUND(((ET33)*AV33*I33),2)*BB33),2)+ROUND((ROUND(((AE33-(EU33))*AV33*I33),2)*BS33),2)) -> 0 | R33: =ROUND((ROUND((AE33*AV33*I33),2)*BS33),2) -> 0 | S33: =ROUND((ROUND((AF33*AV33*I33),2)*BA33),2) -> 0 | T33: =ROUND(CU33*I33,2) -> 0 | U33: =CV33*I33 -> 0 | V33: =CW33*I33 -> 0 | W33: =ROUND(CX33*I33,2) -> 0 | X33: =ROUND(CY33,2) -> 0 | Y33: =ROUND(CZ33,2) -> 0 | AA33: 59204059 | AB33: =ROUND((AC33+AD33+AF33),6) -> 34.97 | AC33: =ROUND((ES33),6) -> 34.97 | AD33: =ROUND((((ET33)-(EU33))+AE33),6) -> 0 | AE33: =ROUND((EU33),6) -> 0 | AF33: =ROUND((EV33),6) -> 0 | AG33: =ROUND((AP33),6) -> 0 | AH33: =(EW33) -> 0 | AI33: =(EX33) -> 0 | AJ33: =(AS33) -> 0 | AK33: 34.97 | AL33: 34.97 | AM33: 0 | AN33: 0 | AO33: 0 | AP33: 0 | AQ33: 0 | AR33: 0 | AS33: 0 | AT33: 109 | AU33: 61 | AV33: 1 | AW33: 1 | AZ33: 1 | BA33: 1 | BB33: 1 | BC33: 18.72 | BH33: 3 | BI33: 1 | BJ33: ТСН-2001.1 Доп. 73, Р. 13, о. 4, поз. 61 | BM33: 21 | BN33: 0 | BO33: 1.13-4-61 | BP33: 1 | BQ33: 30 | BR33: 0 | BS33: 1 | BT33: 1 | BU33: 1 | BV33: 1 | BW33: 1 | BX33: 1 | BZ33: 109 | CA33: 61 | CE33: 30 | CF33: 0 | CG33: 0 | CM33: 0 | CO33: 0 | CP33: =(P33+Q33+S33) -> 3927.83 | CQ33: =ROUND((ROUND((AC33*AW33*1),2)*BC33),2) -> 654.64 | CR33: =(ROUND((ROUND(((ET33)*AV33*1),2)*BB33),2)+ROUND((ROUND(((AE33-(EU33))*AV33*1),2)*BS33),2)) -> 0 | CS33: =ROUND((ROUND((AE33*AV33*1),2)*BS33),2) -> 0 | CT33: =ROUND((ROUND((AF33*AV33*1),2)*BA33),2) -> 0 | CU33: =AG33 -> 0 | CV33: =(AH33*AV33) -> 0 | CW33: =AI33 -> 0 | CX33: =AJ33 -> 0 | CY33: =(((S33+R33)*AT33)/100) -> 0 | CZ33: =(((S33+R33)*AU33)/100) -> 0 | DN33: 0 | DO33: 0 | DP33: 1 | DQ33: 1 | DU33: 1010 | DV33: шт. | DW33: шт. | DX33: 1 | EE33: 58807897 | EF33: 30 | EG33: Строительные работы | EH33: 0 | EJ33: 1 | EK33: 21 | EL33: ТСН-2001.3-16. Трубопроводы внутренние | EM33: ТСН-2001.3-16-1 | EQ33: 0 | ER33: 34.97 | ES33: 34.97 | ET33: 0 | EU33: 0 | EV33: 0 | EW33: 0 | EX33: 0 | FQ33: 0 | FR33: 0 | FS33: 0 | FX33: 109 | FY33: 61 | GD33: 1 | GF33: -1914030801 | GG33: 2 | GH33: 1 | GI33: 2 | GJ33: 0 | GK33: 0 | GL33: =ROUND(IF(AND(BH33=3,BI33=3,FS33<>0),P33,0),2) -> 0 | GM33: =ROUND(O33+X33+Y33,2)+GX33 -> 3927.83 | GN33: =IF(OR(BI33=0,BI33=1),GM33-GX33,0) -> 3927.83 | GO33: =IF(BI33=2,GM33-GX33,0) -> 0 | GP33: =IF(BI33=4,GM33-GX33,0) -> 0 | GR33: 0 | GS33: 3 | GT33: 0 | GV33: =ROUND((GT33),6) -> 0 | GW33: 1 | GX33: =ROUND(HC33*I33,2) -> 0 | HA33: 0 | HB33: 0 | HC33: =GV33*GW33 -> 0 | HS33: 0 | IK33: 0
A34: 18 | B34: 1 | C34: 11 | E34: 1,3 | F34: 1.13-4-137 | G34: Кран шаровой, латунный, никелированный, спускной, с наружной резьбой, с насадкой для шланга, с алюминиевой рукояткой, температура рабочей среды от -15 до +90°С, пропускная способность 1,9 м3/ч, номинальное давление PN 1,0 МПа, номинальный диаметр DN 15 мм | H34: шт. | I34: =I28*J34 -> 44 | J34: 244.44444 | K34: 244.44444 | O34: =ROUND(CP34,2) -> 1082.84 | P34: =ROUND((ROUND((AC34*AW34*I34),2)*BC34),2) -> 1082.84 | Q34: =(ROUND((ROUND(((ET34)*AV34*I34),2)*BB34),2)+ROUND((ROUND(((AE34-(EU34))*AV34*I34),2)*BS34),2)) -> 0 | R34: =ROUND((ROUND((AE34*AV34*I34),2)*BS34),2) -> 0 | S34: =ROUND((ROUND((AF34*AV34*I34),2)*BA34),2) -> 0 | T34: =ROUND(CU34*I34,2) -> 0 | U34: =CV34*I34 -> 0 | V34: =CW34*I34 -> 0 | W34: =ROUND(CX34*I34,2) -> 0 | X34: =ROUND(CY34,2) -> 0 | Y34: =ROUND(CZ34,2) -> 0 | AA34: 59204062 | AB34: =ROUND((AC34+AD34+AF34),6) -> 24.61 | AC34: =ROUND((ES34),6) -> 24.61 | AD34: =ROUND((((ET34)-(EU34))+AE34),6) -> 0 | AE34: =ROUND((EU34),6) -> 0 | AF34: =ROUND((EV34),6) -> 0 | AG34: =ROUND((AP34),6) -> 0 | AH34: =(EW34) -> 0 | AI34: =(EX34) -> 0 | AJ34: =(AS34) -> 0 | AK34: 24.61 | AL34: 24.61 | AM34: 0 | AN34: 0 | AO34: 0 | AP34: 0 | AQ34: 0 | AR34: 0 | AS34: 0 | AT34: 109 | AU34: 61 | AV34: 1 | AW34: 1 | AZ34: 1 | BA34: 1 | BB34: 1 | BC34: 1 | BH34: 3 | BI34: 1 | BJ34: ТСН-2001.1 Доп. 73, Р. 13, о. 4, поз. 137 | BM34: 21 | BN34: 0 | BP34: 0 | BQ34: 30 | BR34: 0 | BS34: 1 | BT34: 1 | BU34: 1 | BV34: 1 | BW34: 1 | BX34: 1 | BZ34: 109 | CA34: 61 | CE34: 30 | CF34: 0 | CG34: 0 | CM34: 0 | CO34: 0 | CP34: =(P34+Q34+S34) -> 1082.84 | CQ34: =ROUND((ROUND((AC34*AW34*1),2)*BC34),2) -> 24.61 | CR34: =(ROUND((ROUND(((ET34)*AV34*1),2)*BB34),2)+ROUND((ROUND(((AE34-(EU34))*AV34*1),2)*BS34),2)) -> 0 | CS34: =ROUND((ROUND((AE34*AV34*1),2)*BS34),2) -> 0 | CT34: =ROUND((ROUND((AF34*AV34*1),2)*BA34),2) -> 0 | CU34: =AG34 -> 0 | CV34: =(AH34*AV34) -> 0 | CW34: =AI34 -> 0 | CX34: =AJ34 -> 0 | CY34: =(((S34+R34)*AT34)/100) -> 0 | CZ34: =(((S34+R34)*AU34)/100) -> 0 | DN34: 0 | DO34: 0 | DP34: 1 | DQ34: 1 | DU34: 1010 | DV34: шт. | DW34: шт. | DX34: 1 | EE34: 58807897 | EF34: 30 | EG34: Строительные работы | EH34: 0 | EJ34: 1 | EK34: 21 | EL34: ТСН-2001.3-16. Трубопроводы внутренние | EM34: ТСН-2001.3-16-1 | EQ34: 0 | ER34: 24.61 | ES34: 24.61 | ET34: 0 | EU34: 0 | EV34: 0 | EW34: 0 | EX34: 0 | FQ34: 0 | FR34: 0 | FS34: 0 | FX34: 109 | FY34: 61 | GD34: 1 | GF34: -877742701 | GG34: 2 | GH34: 1 | GI34: -2 | GJ34: 0 | GK34: 0 | GL34: =ROUND(IF(AND(BH34=3,BI34=3,FS34<>0),P34,0),2) -> 0 | GM34: =ROUND(O34+X34+Y34,2)+GX34 -> 1082.84 | GN34: =IF(OR(BI34=0,BI34=1),GM34-GX34,0) -> 1082.84 | GO34: =IF(BI34=2,GM34-GX34,0) -> 0 | GP34: =IF(BI34=4,GM34-GX34,0) -> 0 | GR34: 0 | GS34: 3 | GT34: 0 | GV34: =ROUND((GT34),6) -> 0 | GW34: 1 | GX34: =ROUND(HC34*I34,2) -> 0 | HA34: 0 | HB34: 0 | HC34: =GV34*GW34 -> 0 | HS34: 0 | IK34: 0
A35: 18 | B35: 1 | C35: 23 | E35: 1,3 | F35: 1.13-4-137 | G35: Кран шаровой, латунный, никелированный, спускной, с наружной резьбой, с насадкой для шланга, с алюминиевой рукояткой, температура рабочей среды от -15 до +90°С, пропускная способность 1,9 м3/ч, номинальное давление PN 1,0 МПа, номинальный диаметр DN 15 мм | H35: шт. | I35: =I29*J35 -> 44 | J35: 244.44444 | K35: 244.44444 | O35: =ROUND(CP35,2) -> 38527.45 | P35: =ROUND((ROUND((AC35*AW35*I35),2)*BC35),2) -> 38527.45 | Q35: =(ROUND((ROUND(((ET35)*AV35*I35),2)*BB35),2)+ROUND((ROUND(((AE35-(EU35))*AV35*I35),2)*BS35),2)) -> 0 | R35: =ROUND((ROUND((AE35*AV35*I35),2)*BS35),2) -> 0 | S35: =ROUND((ROUND((AF35*AV35*I35),2)*BA35),2) -> 0 | T35: =ROUND(CU35*I35,2) -> 0 | U35: =CV35*I35 -> 0 | V35: =CW35*I35 -> 0 | W35: =ROUND(CX35*I35,2) -> 0 | X35: =ROUND(CY35,2) -> 0 | Y35: =ROUND(CZ35,2) -> 0 | AA35: 59204059 | AB35: =ROUND((AC35+AD35+AF35),6) -> 24.61 | AC35: =ROUND((ES35),6) -> 24.61 | AD35: =ROUND((((ET35)-(EU35))+AE35),6) -> 0 | AE35: =ROUND((EU35),6) -> 0 | AF35: =ROUND((EV35),6) -> 0 | AG35: =ROUND((AP35),6) -> 0 | AH35: =(EW35) -> 0 | AI35: =(EX35) -> 0 | AJ35: =(AS35) -> 0 | AK35: 24.61 | AL35: 24.61 | AM35: 0 | AN35: 0 | AO35: 0 | AP35: 0 | AQ35: 0 | AR35: 0 | AS35: 0 | AT35: 109 | AU35: 61 | AV35: 1 | AW35: 1 | AZ35: 1 | BA35: 1 | BB35: 1 | BC35: 35.58 | BH35: 3 | BI35: 1 | BJ35: ТСН-2001.1 Доп. 73, Р. 13, о. 4, поз. 137 | BM35: 21 | BN35: 0 | BO35: 1.13-4-137 | BP35: 1 | BQ35: 30 | BR35: 0 | BS35: 1 | BT35: 1 | BU35: 1 | BV35: 1 | BW35: 1 | BX35: 1 | BZ35: 109 | CA35: 61 | CE35: 30 | CF35: 0 | CG35: 0 | CM35: 0 | CO35: 0 | CP35: =(P35+Q35+S35) -> 38527.45 | CQ35: =ROUND((ROUND((AC35*AW35*1),2)*BC35),2) -> 875.62 | CR35: =(ROUND((ROUND(((ET35)*AV35*1),2)*BB35),2)+ROUND((ROUND(((AE35-(EU35))*AV35*1),2)*BS35),2)) -> 0 | CS35: =ROUND((ROUND((AE35*AV35*1),2)*BS35),2) -> 0 | CT35: =ROUND((ROUND((AF35*AV35*1),2)*BA35),2) -> 0 | CU35: =AG35 -> 0 | CV35: =(AH35*AV35) -> 0 | CW35: =AI35 -> 0 | CX35: =AJ35 -> 0 | CY35: =(((S35+R35)*AT35)/100) -> 0 | CZ35: =(((S35+R35)*AU35)/100) -> 0 | DN35: 0 | DO35: 0 | DP35: 1 | DQ35: 1 | DU35: 1010 | DV35: шт. | DW35: шт. | DX35: 1 | EE35: 58807897 | EF35: 30 | EG35: Строительные работы | EH35: 0 | EJ35: 1 | EK35: 21 | EL35: ТСН-2001.3-16. Трубопроводы внутренние | EM35: ТСН-2001.3-16-1 | EQ35: 0 | ER35: 24.61 | ES35: 24.61 | ET35: 0 | EU35: 0 | EV35: 0 | EW35: 0 | EX35: 0 | FQ35: 0 | FR35: 0 | FS35: 0 | FX35: 109 | FY35: 61 | GD35: 1 | GF35: -877742701 | GG35: 2 | GH35: 1 | GI35: 2 | GJ35: 0 | GK35: 0 | GL35: =ROUND(IF(AND(BH35=3,BI35=3,FS35<>0),P35,0),2) -> 0 | GM35: =ROUND(O35+X35+Y35,2)+GX35 -> 38527.45 | GN35: =IF(OR(BI35=0,BI35=1),GM35-GX35,0) -> 38527.45 | GO35: =IF(BI35=2,GM35-GX35,0) -> 0 | GP35: =IF(BI35=4,GM35-GX35,0) -> 0 | GR35: 0 | GS35: 3 | GT35: 0 | GV35: =ROUND((GT35),6) -> 0 | GW35: 1 | GX35: =ROUND(HC35*I35,2) -> 0 | HA35: 0 | HB35: 0 | HC35: =GV35*GW35 -> 0 | HS35: 0 | IK35: 0
A36: 18 | B36: 1 | C36: 9 | E36: 1,4 | F36: 1.12-10-146 | G36: Хомут стальной, оцинкованный, двухболтовой, с поворотным механизмом, каучуковой прокладкой, для крепления труб диаметром от 16 до 20 мм, резьба М8/М10 | H36: 100 шт. | I36: =I28*J36 -> 0.12 | J36: 0.66666667 | K36: 0.666667 | O36: =ROUND(CP36,2) -> 63.15 | P36: =ROUND((ROUND((AC36*AW36*I36),2)*BC36),2) -> 63.15 | Q36: =(ROUND((ROUND(((ET36)*AV36*I36),2)*BB36),2)+ROUND((ROUND(((AE36-(EU36))*AV36*I36),2)*BS36),2)) -> 0 | R36: =ROUND((ROUND((AE36*AV36*I36),2)*BS36),2) -> 0 | S36: =ROUND((ROUND((AF36*AV36*I36),2)*BA36),2) -> 0 | T36: =ROUND(CU36*I36,2) -> 0 | U36: =CV36*I36 -> 0 | V36: =CW36*I36 -> 0 | W36: =ROUND(CX36*I36,2) -> 0 | X36: =ROUND(CY36,2) -> 0 | Y36: =ROUND(CZ36,2) -> 0 | AA36: 59204062 | AB36: =ROUND((AC36+AD36+AF36),6) -> 526.22 | AC36: =ROUND((ES36),6) -> 526.22 | AD36: =ROUND((((ET36)-(EU36))+AE36),6) -> 0 | AE36: =ROUND((EU36),6) -> 0 | AF36: =ROUND((EV36),6) -> 0 | AG36: =ROUND((AP36),6) -> 0 | AH36: =(EW36) -> 0 | AI36: =(EX36) -> 0 | AJ36: =(AS36) -> 0 | AK36: 526.22 | AL36: 526.22 | AM36: 0 | AN36: 0 | AO36: 0 | AP36: 0 | AQ36: 0 | AR36: 0 | AS36: 0 | AT36: 109 | AU36: 61 | AV36: 1 | AW36: 1 | AZ36: 1 | BA36: 1 | BB36: 1 | BC36: 1 | BH36: 3 | BI36: 1 | BJ36: ТСН-2001.1 Доп. 79, Р. 12, о. 10, поз. 146 | BM36: 21 | BN36: 0 | BP36: 0 | BQ36: 30 | BR36: 0 | BS36: 1 | BT36: 1 | BU36: 1 | BV36: 1 | BW36: 1 | BX36: 1 | BZ36: 109 | CA36: 61 | CE36: 30 | CF36: 0 | CG36: 0 | CM36: 0 | CO36: 0 | CP36: =(P36+Q36+S36) -> 63.15 | CQ36: =ROUND((ROUND((AC36*AW36*1),2)*BC36),2) -> 526.22 | CR36: =(ROUND((ROUND(((ET36)*AV36*1),2)*BB36),2)+ROUND((ROUND(((AE36-(EU36))*AV36*1),2)*BS36),2)) -> 0 | CS36: =ROUND((ROUND((AE36*AV36*1),2)*BS36),2) -> 0 | CT36: =ROUND((ROUND((AF36*AV36*1),2)*BA36),2) -> 0 | CU36: =AG36 -> 0 | CV36: =(AH36*AV36) -> 0 | CW36: =AI36 -> 0 | CX36: =AJ36 -> 0 | CY36: =(((S36+R36)*AT36)/100) -> 0 | CZ36: =(((S36+R36)*AU36)/100) -> 0 | DN36: 0 | DO36: 0 | DP36: 1 | DQ36: 1 | DU36: 1010 | DV36: 100 шт. | DW36: 100 шт. | DX36: 100 | EE36: 58807897 | EF36: 30 | EG36: Строительные работы | EH36: 0 | EJ36: 1 | EK36: 21 | EL36: ТСН-2001.3-16. Трубопроводы внутренние | EM36: ТСН-2001.3-16-1 | EQ36: 0 | ER36: 526.22 | ES36: 526.22 | ET36: 0 | EU36: 0 | EV36: 0 | EW36: 0 | EX36: 0 | FQ36: 0 | FR36: 0 | FS36: 0 | FX36: 109 | FY36: 61 | GD36: 1 | GF36: 1873919888 | GG36: 2 | GH36: 1 | GI36: -2 | GJ36: 0 | GK36: 0 | GL36: =ROUND(IF(AND(BH36=3,BI36=3,FS36<>0),P36,0),2) -> 0 | GM36: =ROUND(O36+X36+Y36,2)+GX36 -> 63.15 | GN36: =IF(OR(BI36=0,BI36=1),GM36-GX36,0) -> 63.15 | GO36: =IF(BI36=2,GM36-GX36,0) -> 0 | GP36: =IF(BI36=4,GM36-GX36,0) -> 0 | GR36: 0 | GS36: 3 | GT36: 0 | GV36: =ROUND((GT36),6) -> 0 | GW36: 1 | GX36: =ROUND(HC36*I36,2) -> 0 | HA36: 0 | HB36: 0 | HC36: =GV36*GW36 -> 0 | HS36: 0 | IK36: 0
A37: 18 | B37: 1 | C37: 21 | E37: 1,4 | F37: 1.12-10-146 | G37: Хомут стальной, оцинкованный, двухболтовой, с поворотным механизмом, каучуковой прокладкой, для крепления труб диаметром от 16 до 20 мм, резьба М8/М10 | H37: 100 шт. | I37: =I29*J37 -> 0.12 | J37: 0.66666667 | K37: 0.666667 | O37: =ROUND(CP37,2) -> 176.19 | P37: =ROUND((ROUND((AC37*AW37*I37),2)*BC37),2) -> 176.19 | Q37: =(ROUND((ROUND(((ET37)*AV37*I37),2)*BB37),2)+ROUND((ROUND(((AE37-(EU37))*AV37*I37),2)*BS37),2)) -> 0 | R37: =ROUND((ROUND((AE37*AV37*I37),2)*BS37),2) -> 0 | S37: =ROUND((ROUND((AF37*AV37*I37),2)*BA37),2) -> 0 | T37: =ROUND(CU37*I37,2) -> 0 | U37: =CV37*I37 -> 0 | V37: =CW37*I37 -> 0 | W37: =ROUND(CX37*I37,2) -> 0 | X37: =ROUND(CY37,2) -> 0 | Y37: =ROUND(CZ37,2) -> 0 | AA37: 59204059 | AB37: =ROUND((AC37+AD37+AF37),6) -> 526.22 | AC37: =ROUND((ES37),6) -> 526.22 | AD37: =ROUND((((ET37)-(EU37))+AE37),6) -> 0 | AE37: =ROUND((EU37),6) -> 0 | AF37: =ROUND((EV37),6) -> 0 | AG37: =ROUND((AP37),6) -> 0 | AH37: =(EW37) -> 0 | AI37: =(EX37) -> 0 | AJ37: =(AS37) -> 0 | AK37: 526.22 | AL37: 526.22 | AM37: 0 | AN37: 0 | AO37: 0 | AP37: 0 | AQ37: 0 | AR37: 0 | AS37: 0 | AT37: 109 | AU37: 61 | AV37: 1 | AW37: 1 | AZ37: 1 | BA37: 1 | BB37: 1 | BC37: 2.79 | BH37: 3 | BI37: 1 | BJ37: ТСН-2001.1 Доп. 79, Р. 12, о. 10, поз. 146 | BM37: 21 | BN37: 0 | BO37: 1.12-10-146 | BP37: 1 | BQ37: 30 | BR37: 0 | BS37: 1 | BT37: 1 | BU37: 1 | BV37: 1 | BW37: 1 | BX37: 1 | BZ37: 109 | CA37: 61 | CE37: 30 | CF37: 0 | CG37: 0 | CM37: 0 | CO37: 0 | CP37: =(P37+Q37+S37) -> 176.19 | CQ37: =ROUND((ROUND((AC37*AW37*1),2)*BC37),2) -> 1468.15 | CR37: =(ROUND((ROUND(((ET37)*AV37*1),2)*BB37),2)+ROUND((ROUND(((AE37-(EU37))*AV37*1),2)*BS37),2)) -> 0 | CS37: =ROUND((ROUND((AE37*AV37*1),2)*BS37),2) -> 0 | CT37: =ROUND((ROUND((AF37*AV37*1),2)*BA37),2) -> 0 | CU37: =AG37 -> 0 | CV37: =(AH37*AV37) -> 0 | CW37: =AI37 -> 0 | CX37: =AJ37 -> 0 | CY37: =(((S37+R37)*AT37)/100) -> 0 | CZ37: =(((S37+R37)*AU37)/100) -> 0 | DN37: 0 | DO37: 0 | DP37: 1 | DQ37: 1 | DU37: 1010 | DV37: 100 шт. | DW37: 100 шт. | DX37: 100 | EE37: 58807897 | EF37: 30 | EG37: Строительные работы | EH37: 0 | EJ37: 1 | EK37: 21 | EL37: ТСН-2001.3-16. Трубопроводы внутренние | EM37: ТСН-2001.3-16-1 | EQ37: 0 | ER37: 526.22 | ES37: 526.22 | ET37: 0 | EU37: 0 | EV37: 0 | EW37: 0 | EX37: 0 | FQ37: 0 | FR37: 0 | FS37: 0 | FX37: 109 | FY37: 61 | GD37: 1 | GF37: 1873919888 | GG37: 2 | GH37: 1 | GI37: 2 | GJ37: 0 | GK37: 0 | GL37: =ROUND(IF(AND(BH37=3,BI37=3,FS37<>0),P37,0),2) -> 0 | GM37: =ROUND(O37+X37+Y37,2)+GX37 -> 176.19 | GN37: =IF(OR(BI37=0,BI37=1),GM37-GX37,0) -> 176.19 | GO37: =IF(BI37=2,GM37-GX37,0) -> 0 | GP37: =IF(BI37=4,GM37-GX37,0) -> 0 | GR37: 0 | GS37: 3 | GT37: 0 | GV37: =ROUND((GT37),6) -> 0 | GW37: 1 | GX37: =ROUND(HC37*I37,2) -> 0 | HA37: 0 | HB37: 0 | HC37: =GV37*GW37 -> 0 | HS37: 0 | IK37: 0
A38: 17 | B38: 1 | C38: =ROW(SmtRes!A40) -> 40 | D38: =ROW(EtalonRes!A37) -> 37 | F38: 3.16-7-1 | G38: Прокладка трубопроводов водоснабжения из стальных водогазопроводных оцинкованных труб диаметром 15 мм | H38: 100 м трубопровода | I38: =ROUND(ROUND(18/100,4)*0,9) -> 0 | J38: 0 | K38: =ROUND(ROUND(18/100,4)*0,9) -> 0 | O38: =ROUND(CP38,2) -> 0 | P38: =ROUND((ROUND((AC38*AW38*I38),2)*BC38),2) -> 0 | Q38: =(ROUND((ROUND(((((ET38*1.25)*1.1))*AV38*I38),2)*BB38),2)+ROUND((ROUND(((AE38-(((EU38*1.25)*1.1)))*AV38*I38),2)*BS38),2)) -> 0 | R38: =ROUND((ROUND((AE38*AV38*I38),2)*BS38),2) -> 0 | S38: =ROUND((ROUND((AF38*AV38*I38),2)*BA38),2) -> 0 | T38: =ROUND(CU38*I38,2) -> 0 | U38: =CV38*I38 -> 0 | V38: =CW38*I38 -> 0 | W38: =ROUND(CX38*I38,2) -> 0 | X38: =ROUND(CY38,2) -> 0 | Y38: =ROUND(CZ38,2) -> 0 | AA38: -1 | AB38: =ROUND((AC38+AD38+AF38),6) -> 648.2556 | AC38: =ROUND((ES38),6) -> 44.58 | AD38: =ROUND((((((ET38*1.25)*1.1))-(((EU38*1.25)*1.1)))+AE38),6) -> 65.68375 | AE38: =ROUND((((EU38*1.25)*1.1)),6) -> 8.3325 | AF38: =ROUND((((EV38*1.15)*1.1)),6) -> 537.99185 | AG38: =ROUND((AP38),6) -> 0 | AH38: =(((EW38*1.15)*1.1)) -> 42.6305 | AI38: =(((EX38*1.25)*1.1)) -> 0 | AJ38: =(AS38) -> 0 | AK38: 517.64 | AL38: 44.58 | AM38: 47.77 | AN38: 6.06 | AO38: 425.29 | AP38: 0 | AQ38: 33.7 | AR38: 0 | AS38: 0 | AT38: 109 | AU38: 61 | AV38: 1.067 | AW38: 1 | AZ38: 1 | BA38: 1 | BB38: 1 | BC38: 1 | BH38: 0 | BI38: 1 | BJ38: ТСН-2001.3 Доп. 79, Сб. 16, т. 7, поз. 1 | BM38: 21 | BN38: 0 | BO38: 3.16-7-1 | BP38: 1 | BQ38: 30 | BR38: 0 | BS38: 1 | BT38: 1 | BU38: 1 | BV38: 1 | BW38: 1 | BX38: 1 | BZ38: 109 | CA38: 61 | CE38: 30 | CF38: 0 | CG38: 0 | CM38: 0 | CN38: Поправка: О.П. п.3.4. 6 Наименование: Выполняемые при ремонте и реконструкции работы аналогичные технологическим процессам, характерным для нового строительства и отсутствующим в сборниках на ремонтно-строительные работы Поправка: О.П. п.3.4.30.в Наименование: При применении территориальных сметных нормативов для города Москвы затраты, учитывающие напряженные и стесненные условия производства работ (стесненность, сложность складирования и транспортной логистики и т.п.), исчисляются с применением коэффициентов к затратам труда и заработной плате рабочих, машинистов, времени эксплуатации машин и механизмов, стоимости эксплуатации машин в размере: для объектов, расположенных за пределами Третьего транспортного кольца города Москвы, но в пределах Московской кольцевой автомобильной дороги | CO38: 0 | CP38: =(P38+Q38+S38) -> 0 | CQ38: =ROUND((ROUND((AC38*AW38*1),2)*BC38),2) -> 44.58 | CR38: =(ROUND((ROUND(((((ET38*1.25)*1.1))*AV38*1),2)*BB38),2)+ROUND((ROUND(((AE38-(((EU38*1.25)*1.1)))*AV38*1),2)*BS38),2)) -> 70.08 | CS38: =ROUND((ROUND((AE38*AV38*1),2)*BS38),2) -> 8.89 | CT38: =ROUND((ROUND((AF38*AV38*1),2)*BA38),2) -> 574.04 | CU38: =AG38 -> 0 | CV38: =(AH38*AV38) -> 45.486744 | CW38: =AI38 -> 0 | CX38: =AJ38 -> 0 | CY38: =(((S38+R38)*AT38)/100) -> 0 | CZ38: =(((S38+R38)*AU38)/100) -> 0 | DB38: 5 | DE38: *1,25)*1,1 | DF38: *1,25)*1,1 | DG38: *1,15)*1,1 | DI38: *1,15)*1,1 | DJ38: *1,25)*1,1 | DN38: 0 | DO38: 0 | DP38: 1 | DQ38: 1 | DU38: 1013 | DV38: 100 м трубопровода | DW38: 100 м трубопровода | DX38: 1 | EE38: 58807897 | EF38: 30 | EG38: Строительные работы | EH38: 0 | EJ38: 1 | EK38: 21 | EL38: ТСН-2001.3-16. Трубопроводы внутренние | EM38: ТСН-2001.3-16-1 | EO38: Поправка: О.П. п.3.4. 6 Поправка: О.П. п.3.4.30.в | EQ38: 1024 | ER38: 517.64 | ES38: 44.58 | ET38: 47.77 | EU38: 6.06 | EV38: 425.29 | EW38: 33.7 | EX38: 0 | EY38: 0 | FQ38: 0 | FR38: 0 | FS38: 0 | FX38: 109 | FY38: 61 | GD38: 1 | GF38: 568000979 | GG38: 2 | GH38: 1 | GI38: 2 | GJ38: 0 | GK38: 0 | GL38: =ROUND(IF(AND(BH38=3,BI38=3,FS38<>0),P38,0),2) -> 0 | GM38: =ROUND(O38+X38+Y38,2)+GX38 -> 0 | GN38: =IF(OR(BI38=0,BI38=1),GM38-GX38,0) -> 0 | GO38: =IF(BI38=2,GM38-GX38,0) -> 0 | GP38: =IF(BI38=4,GM38-GX38,0) -> 0 | GR38: 0 | GS38: 3 | GT38: 0 | GV38: =ROUND((GT38),6) -> 0 | GW38: 1 | GX38: =ROUND(HC38*I38,2) -> 0 | HA38: 0 | HB38: 0 | HC38: =GV38*GW38 -> 0 | HS38: 0 | IK38: 0
A39: 17 | B39: 1 | C39: =ROW(SmtRes!A56) -> 56 | D39: =ROW(EtalonRes!A52) -> 52 | F39: 3.16-7-1 | G39: Прокладка трубопроводов водоснабжения из стальных водогазопроводных оцинкованных труб диаметром 15 мм | H39: 100 м трубопровода | I39: =ROUND(ROUND(18/100,4)*0,9) -> 0 | J39: 0 | K39: =ROUND(ROUND(18/100,4)*0,9) -> 0 | O39: =ROUND(CP39,2) -> 0 | P39: =ROUND((ROUND((AC39*AW39*I39),2)*BC39),2) -> 0 | Q39: =(ROUND((ROUND(((((ET39*1.25)*1.1))*AV39*I39),2)*BB39),2)+ROUND((ROUND(((AE39-(((EU39*1.25)*1.1)))*AV39*I39),2)*BS39),2)) -> 0 | R39: =ROUND((ROUND((AE39*AV39*I39),2)*BS39),2) -> 0 | S39: =ROUND((ROUND((AF39*AV39*I39),2)*BA39),2) -> 0 | T39: =ROUND(CU39*I39,2) -> 0 | U39: =CV39*I39 -> 0 | V39: =CW39*I39 -> 0 | W39: =ROUND(CX39*I39,2) -> 0 | X39: =ROUND(CY39,2) -> 0 | Y39: =ROUND(CZ39,2) -> 0 | AA39: -1 | AB39: =ROUND((AC39+AD39+AF39),6) -> 648.2556 | AC39: =ROUND((ES39),6) -> 44.58 | AD39: =ROUND((((((ET39*1.25)*1.1))-(((EU39*1.25)*1.1)))+AE39),6) -> 65.68375 | AE39: =ROUND((((EU39*1.25)*1.1)),6) -> 8.3325 | AF39: =ROUND((((EV39*1.15)*1.1)),6) -> 537.99185 | AG39: =ROUND((AP39),6) -> 0 | AH39: =(((EW39*1.15)*1.1)) -> 42.6305 | AI39: =(((EX39*1.25)*1.1)) -> 0 | AJ39: =(AS39) -> 0 | AK39: 517.64 | AL39: 44.58 | AM39: 47.77 | AN39: 6.06 | AO39: 425.29 | AP39: 0 | AQ39: 33.7 | AR39: 0 | AS39: 0 | AT39: 109 | AU39: 61 | AV39: 1.067 | AW39: 1 | AZ39: 1 | BA39: 54.99 | BB39: 15.37 | BC39: 6.15 | BH39: 0 | BI39: 1 | BJ39: ТСН-2001.3 Доп. 79, Сб. 16, т. 7, поз. 1 | BM39: 21 | BN39: 0 | BO39: 3.16-7-1 | BP39: 1 | BQ39: 30 | BR39: 0 | BS39: 54.99 | BT39: 1 | BU39: 1 | BV39: 1 | BW39: 1 | BX39: 1 | BZ39: 109 | CA39: 61 | CE39: 30 | CF39: 0 | CG39: 0 | CM39: 0 | CN39: Поправка: О.П. п.3.4. 6 Наименование: Выполняемые при ремонте и реконструкции работы аналогичные технологическим процессам, характерным для нового строительства и отсутствующим в сборниках на ремонтно-строительные работы Поправка: О.П. п.3.4.30.в Наименование: При применении территориальных сметных нормативов для города Москвы затраты, учитывающие напряженные и стесненные условия производства работ (стесненность, сложность складирования и транспортной логистики и т.п.), исчисляются с применением коэффициентов к затратам труда и заработной плате рабочих, машинистов, времени эксплуатации машин и механизмов, стоимости эксплуатации машин в размере: для объектов, расположенных за пределами Третьего транспортного кольца города Москвы, но в пределах Московской кольцевой автомобильной дороги | CO39: 0 | CP39: =(P39+Q39+S39) -> 0 | CQ39: =ROUND((ROUND((AC39*AW39*1),2)*BC39),2) -> 274.17 | CR39: =(ROUND((ROUND(((((ET39*1.25)*1.1))*AV39*1),2)*BB39),2)+ROUND((ROUND(((AE39-(((EU39*1.25)*1.1)))*AV39*1),2)*BS39),2)) -> 1077.13 | CS39: =ROUND((ROUND((AE39*AV39*1),2)*BS39),2) -> 488.86 | CT39: =ROUND((ROUND((AF39*AV39*1),2)*BA39),2) -> 31566.46 | CU39: =AG39 -> 0 | CV39: =(AH39*AV39) -> 45.486744 | CW39: =AI39 -> 0 | CX39: =AJ39 -> 0 | CY39: =(((S39+R39)*AT39)/100) -> 0 | CZ39: =(((S39+R39)*AU39)/100) -> 0 | DB39: 7 | DE39: *1,25)*1,1 | DF39: *1,25)*1,1 | DG39: *1,15)*1,1 | DI39: *1,15)*1,1 | DJ39: *1,25)*1,1 | DN39: 0 | DO39: 0 | DP39: 1 | DQ39: 1 | DU39: 1013 | DV39: 100 м трубопровода | DW39: 100 м трубопровода | DX39: 1 | EE39: 58807897 | EF39: 30 | EG39: Строительные работы | EH39: 0 | EJ39: 1 | EK39: 21 | EL39: ТСН-2001.3-16. Трубопроводы внутренние | EM39: ТСН-2001.3-16-1 | EO39: Поправка: О.П. п.3.4. 6 Поправка: О.П. п.3.4.30.в | EQ39: 1024 | ER39: 517.64 | ES39: 44.58 | ET39: 47.77 | EU39: 6.06 | EV39: 425.29 | EW39: 33.7 | EX39: 0 | EY39: 0 | FQ39: 0 | FR39: 0 | FS39: 0 | FX39: 109 | FY39: 61 | GD39: 1 | GF39: 568000979 | GG39: 2 | GH39: 1 | GI39: 2 | GJ39: 0 | GK39: 0 | GL39: =ROUND(IF(AND(BH39=3,BI39=3,FS39<>0),P39,0),2) -> 0 | GM39: =ROUND(O39+X39+Y39,2)+GX39 -> 0 | GN39: =IF(OR(BI39=0,BI39=1),GM39-GX39,0) -> 0 | GO39: =IF(BI39=2,GM39-GX39,0) -> 0 | GP39: =IF(BI39=4,GM39-GX39,0) -> 0 | GR39: 0 | GS39: 3 | GT39: 0 | GV39: =ROUND((GT39),6) -> 0 | GW39: 1 | GX39: =ROUND(HC39*I39,2) -> 0 | HA39: 0 | HB39: 0 | HC39: =GV39*GW39 -> 0 | HS39: 0 | IK39: 0
A40: 18 | B40: 1 | C40: 37 | F40: 1.12-10-146 | G40: Хомут стальной, оцинкованный, двухболтовой, с поворотным механизмом, каучуковой прокладкой, для крепления труб диаметром от 16 до 20 мм, резьба М8/М10 | H40: 100 шт. | I40: =I38*J40 -> 0 | J40: 0.666667 | K40: 0.666667 | O40: =ROUND(CP40,2) -> 0 | P40: =ROUND((ROUND((AC40*AW40*I40),2)*BC40),2) -> 0 | Q40: =(ROUND((ROUND(((ET40)*AV40*I40),2)*BB40),2)+ROUND((ROUND(((AE40-(EU40))*AV40*I40),2)*BS40),2)) -> 0 | R40: =ROUND((ROUND((AE40*AV40*I40),2)*BS40),2) -> 0 | S40: =ROUND((ROUND((AF40*AV40*I40),2)*BA40),2) -> 0 | T40: =ROUND(CU40*I40,2) -> 0 | U40: =CV40*I40 -> 0 | V40: =CW40*I40 -> 0 | W40: =ROUND(CX40*I40,2) -> 0 | X40: =ROUND(CY40,2) -> 0 | Y40: =ROUND(CZ40,2) -> 0 | AA40: -1 | AB40: =ROUND((AC40+AD40+AF40),6) -> 526.22 | AC40: =ROUND((ES40),6) -> 526.22 | AD40: =ROUND((((ET40)-(EU40))+AE40),6) -> 0 | AE40: =ROUND((EU40),6) -> 0 | AF40: =ROUND((EV40),6) -> 0 | AG40: =ROUND((AP40),6) -> 0 | AH40: =(EW40) -> 0 | AI40: =(EX40) -> 0 | AJ40: =(AS40) -> 0 | AK40: 526.22 | AL40: 526.22 | AM40: 0 | AN40: 0 | AO40: 0 | AP40: 0 | AQ40: 0 | AR40: 0 | AS40: 0 | AT40: 109 | AU40: 61 | AV40: 1 | AW40: 1 | AZ40: 1 | BA40: 1 | BB40: 1 | BC40: 1 | BH40: 3 | BI40: 1 | BJ40: ТСН-2001.1 Доп. 79, Р. 12, о. 10, поз. 146 | BM40: 21 | BN40: 0 | BP40: 0 | BQ40: 30 | BR40: 0 | BS40: 1 | BT40: 1 | BU40: 1 | BV40: 1 | BW40: 1 | BX40: 1 | BZ40: 109 | CA40: 61 | CE40: 30 | CF40: 0 | CG40: 0 | CM40: 0 | CO40: 0 | CP40: =(P40+Q40+S40) -> 0 | CQ40: =ROUND((ROUND((AC40*AW40*1),2)*BC40),2) -> 526.22 | CR40: =(ROUND((ROUND(((ET40)*AV40*1),2)*BB40),2)+ROUND((ROUND(((AE40-(EU40))*AV40*1),2)*BS40),2)) -> 0 | CS40: =ROUND((ROUND((AE40*AV40*1),2)*BS40),2) -> 0 | CT40: =ROUND((ROUND((AF40*AV40*1),2)*BA40),2) -> 0 | CU40: =AG40 -> 0 | CV40: =(AH40*AV40) -> 0 | CW40: =AI40 -> 0 | CX40: =AJ40 -> 0 | CY40: =(((S40+R40)*AT40)/100) -> 0 | CZ40: =(((S40+R40)*AU40)/100) -> 0 | DN40: 0 | DO40: 0 | DP40: 1 | DQ40: 1 | DU40: 1010 | DV40: 100 шт. | DW40: 100 шт. | DX40: 100 | EE40: 58807897 | EF40: 30 | EG40: Строительные работы | EH40: 0 | EJ40: 1 | EK40: 21 | EL40: ТСН-2001.3-16. Трубопроводы внутренние | EM40: ТСН-2001.3-16-1 | EQ40: 1024 | ER40: 526.22 | ES40: 526.22 | ET40: 0 | EU40: 0 | EV40: 0 | EW40: 0 | EX40: 0 | FQ40: 0 | FR40: 0 | FS40: 0 | FX40: 109 | FY40: 61 | GD40: 1 | GF40: 1873919888 | GG40: 2 | GH40: 1 | GI40: -2 | GJ40: 0 | GK40: 0 | GL40: =ROUND(IF(AND(BH40=3,BI40=3,FS40<>0),P40,0),2) -> 0 | GM40: =ROUND(O40+X40+Y40,2)+GX40 -> 0 | GN40: =IF(OR(BI40=0,BI40=1),GM40-GX40,0) -> 0 | GO40: =IF(BI40=2,GM40-GX40,0) -> 0 | GP40: =IF(BI40=4,GM40-GX40,0) -> 0 | GR40: 0 | GS40: 3 | GT40: 0 | GV40: =ROUND((GT40),6) -> 0 | GW40: 1 | GX40: =ROUND(HC40*I40,2) -> 0 | HA40: 0 | HB40: 0 | HC40: =GV40*GW40 -> 0 | HS40: 0 | IK40: 0
A41: 18 | B41: 1 | C41: 53 | F41: 1.12-10-146 | G41: Хомут стальной, оцинкованный, двухболтовой, с поворотным механизмом, каучуковой прокладкой, для крепления труб диаметром от 16 до 20 мм, резьба М8/М10 | H41: 100 шт. | I41: =I39*J41 -> 0 | J41: 0.666667 | K41: 0.666667 | O41: =ROUND(CP41,2) -> 0 | P41: =ROUND((ROUND((AC41*AW41*I41),2)*BC41),2) -> 0 | Q41: =(ROUND((ROUND(((ET41)*AV41*I41),2)*BB41),2)+ROUND((ROUND(((AE41-(EU41))*AV41*I41),2)*BS41),2)) -> 0 | R41: =ROUND((ROUND((AE41*AV41*I41),2)*BS41),2) -> 0 | S41: =ROUND((ROUND((AF41*AV41*I41),2)*BA41),2) -> 0 | T41: =ROUND(CU41*I41,2) -> 0 | U41: =CV41*I41 -> 0 | V41: =CW41*I41 -> 0 | W41: =ROUND(CX41*I41,2) -> 0 | X41: =ROUND(CY41,2) -> 0 | Y41: =ROUND(CZ41,2) -> 0 | AA41: -1 | AB41: =ROUND((AC41+AD41+AF41),6) -> 526.22 | AC41: =ROUND((ES41),6) -> 526.22 | AD41: =ROUND((((ET41)-(EU41))+AE41),6) -> 0 | AE41: =ROUND((EU41),6) -> 0 | AF41: =ROUND((EV41),6) -> 0 | AG41: =ROUND((AP41),6) -> 0 | AH41: =(EW41) -> 0 | AI41: =(EX41) -> 0 | AJ41: =(AS41) -> 0 | AK41: 526.22 | AL41: 526.22 | AM41: 0 | AN41: 0 | AO41: 0 | AP41: 0 | AQ41: 0 | AR41: 0 | AS41: 0 | AT41: 109 | AU41: 61 | AV41: 1 | AW41: 1 | AZ41: 1 | BA41: 1 | BB41: 1 | BC41: 2.79 | BH41: 3 | BI41: 1 | BJ41: ТСН-2001.1 Доп. 79, Р. 12, о. 10, поз. 146 | BM41: 21 | BN41: 0 | BO41: 1.12-10-146 | BP41: 1 | BQ41: 30 | BR41: 0 | BS41: 1 | BT41: 1 | BU41: 1 | BV41: 1 | BW41: 1 | BX41: 1 | BZ41: 109 | CA41: 61 | CE41: 30 | CF41: 0 | CG41: 0 | CM41: 0 | CO41: 0 | CP41: =(P41+Q41+S41) -> 0 | CQ41: =ROUND((ROUND((AC41*AW41*1),2)*BC41),2) -> 1468.15 | CR41: =(ROUND((ROUND(((ET41)*AV41*1),2)*BB41),2)+ROUND((ROUND(((AE41-(EU41))*AV41*1),2)*BS41),2)) -> 0 | CS41: =ROUND((ROUND((AE41*AV41*1),2)*BS41),2) -> 0 | CT41: =ROUND((ROUND((AF41*AV41*1),2)*BA41),2) -> 0 | CU41: =AG41 -> 0 | CV41: =(AH41*AV41) -> 0 | CW41: =AI41 -> 0 | CX41: =AJ41 -> 0 | CY41: =(((S41+R41)*AT41)/100) -> 0 | CZ41: =(((S41+R41)*AU41)/100) -> 0 | DN41: 0 | DO41: 0 | DP41: 1 | DQ41: 1 | DU41: 1010 | DV41: 100 шт. | DW41: 100 шт. | DX41: 100 | EE41: 58807897 | EF41: 30 | EG41: Строительные работы | EH41: 0 | EJ41: 1 | EK41: 21 | EL41: ТСН-2001.3-16. Трубопроводы внутренние | EM41: ТСН-2001.3-16-1 | EQ41: 1024 | ER41: 526.22 | ES41: 526.22 | ET41: 0 | EU41: 0 | EV41: 0 | EW41: 0 | EX41: 0 | FQ41: 0 | FR41: 0 | FS41: 0 | FX41: 109 | FY41: 61 | GD41: 1 | GF41: 1873919888 | GG41: 2 | GH41: 1 | GI41: 2 | GJ41: 0 | GK41: 0 | GL41: =ROUND(IF(AND(BH41=3,BI41=3,FS41<>0),P41,0),2) -> 0 | GM41: =ROUND(O41+X41+Y41,2)+GX41 -> 0 | GN41: =IF(OR(BI41=0,BI41=1),GM41-GX41,0) -> 0 | GO41: =IF(BI41=2,GM41-GX41,0) -> 0 | GP41: =IF(BI41=4,GM41-GX41,0) -> 0 | GR41: 0 | GS41: 3 | GT41: 0 | GV41: =ROUND((GT41),6) -> 0 | GW41: 1 | GX41: =ROUND(HC41*I41,2) -> 0 | HA41: 0 | HB41: 0 | HC41: =GV41*GW41 -> 0 | HS41: 0 | IK41: 0
A42: 18 | B42: 1 | C42: 40 | F42: 1.13-4-61 | G42: Кран шаровой, латунный, никелированный, полнопроходной, с алюминиевой рукояткой, муфтовый, температура рабочей среды от -15 до +110°С, номинальное давление PN 4,0 МПа, номинальный диаметр DN 15 мм | H42: шт. | I42: =I38*J42 -> 0 | J42: 33.333333 | K42: 33.333333 | O42: =ROUND(CP42,2) -> 0 | P42: =ROUND((ROUND((AC42*AW42*I42),2)*BC42),2) -> 0 | Q42: =(ROUND((ROUND(((ET42)*AV42*I42),2)*BB42),2)+ROUND((ROUND(((AE42-(EU42))*AV42*I42),2)*BS42),2)) -> 0 | R42: =ROUND((ROUND((AE42*AV42*I42),2)*BS42),2) -> 0 | S42: =ROUND((ROUND((AF42*AV42*I42),2)*BA42),2) -> 0 | T42: =ROUND(CU42*I42,2) -> 0 | U42: =CV42*I42 -> 0 | V42: =CW42*I42 -> 0 | W42: =ROUND(CX42*I42,2) -> 0 | X42: =ROUND(CY42,2) -> 0 | Y42: =ROUND(CZ42,2) -> 0 | AA42: -1 | AB42: =ROUND((AC42+AD42+AF42),6) -> 34.97 | AC42: =ROUND((ES42),6) -> 34.97 | AD42: =ROUND((((ET42)-(EU42))+AE42),6) -> 0 | AE42: =ROUND((EU42),6) -> 0 | AF42: =ROUND((EV42),6) -> 0 | AG42: =ROUND((AP42),6) -> 0 | AH42: =(EW42) -> 0 | AI42: =(EX42) -> 0 | AJ42: =(AS42) -> 0 | AK42: 34.97 | AL42: 34.97 | AM42: 0 | AN42: 0 | AO42: 0 | AP42: 0 | AQ42: 0 | AR42: 0 | AS42: 0 | AT42: 109 | AU42: 61 | AV42: 1 | AW42: 1 | AZ42: 1 | BA42: 1 | BB42: 1 | BC42: 1 | BH42: 3 | BI42: 1 | BJ42: ТСН-2001.1 Доп. 73, Р. 13, о. 4, поз. 61 | BM42: 21 | BN42: 0 | BP42: 0 | BQ42: 30 | BR42: 0 | BS42: 1 | BT42: 1 | BU42: 1 | BV42: 1 | BW42: 1 | BX42: 1 | BZ42: 109 | CA42: 61 | CE42: 30 | CF42: 0 | CG42: 0 | CM42: 0 | CO42: 0 | CP42: =(P42+Q42+S42) -> 0 | CQ42: =ROUND((ROUND((AC42*AW42*1),2)*BC42),2) -> 34.97 | CR42: =(ROUND((ROUND(((ET42)*AV42*1),2)*BB42),2)+ROUND((ROUND(((AE42-(EU42))*AV42*1),2)*BS42),2)) -> 0 | CS42: =ROUND((ROUND((AE42*AV42*1),2)*BS42),2) -> 0 | CT42: =ROUND((ROUND((AF42*AV42*1),2)*BA42),2) -> 0 | CU42: =AG42 -> 0 | CV42: =(AH42*AV42) -> 0 | CW42: =AI42 -> 0 | CX42: =AJ42 -> 0 | CY42: =(((S42+R42)*AT42)/100) -> 0 | CZ42: =(((S42+R42)*AU42)/100) -> 0 | DN42: 0 | DO42: 0 | DP42: 1 | DQ42: 1 | DU42: 1010 | DV42: шт. | DW42: шт. | DX42: 1 | EE42: 58807897 | EF42: 30 | EG42: Строительные работы | EH42: 0 | EJ42: 1 | EK42: 21 | EL42: ТСН-2001.3-16. Трубопроводы внутренние | EM42: ТСН-2001.3-16-1 | EQ42: 1024 | ER42: 34.97 | ES42: 34.97 | ET42: 0 | EU42: 0 | EV42: 0 | EW42: 0 | EX42: 0 | FQ42: 0 | FR42: 0 | FS42: 0 | FX42: 109 | FY42: 61 | GD42: 1 | GF42: -1914030801 | GG42: 2 | GH42: 1 | GI42: -2 | GJ42: 0 | GK42: 0 | GL42: =ROUND(IF(AND(BH42=3,BI42=3,FS42<>0),P42,0),2) -> 0 | GM42: =ROUND(O42+X42+Y42,2)+GX42 -> 0 | GN42: =IF(OR(BI42=0,BI42=1),GM42-GX42,0) -> 0 | GO42: =IF(BI42=2,GM42-GX42,0) -> 0 | GP42: =IF(BI42=4,GM42-GX42,0) -> 0 | GR42: 0 | GS42: 3 | GT42: 0 | GV42: =ROUND((GT42),6) -> 0 | GW42: 1 | GX42: =ROUND(HC42*I42,2) -> 0 | HA42: 0 | HB42: 0 | HC42: =GV42*GW42 -> 0 | HS42: 0 | IK42: 0
A43: 18 | B43: 1 | C43: 56 | F43: 1.13-4-61 | G43: Кран шаровой, латунный, никелированный, полнопроходной, с алюминиевой рукояткой, муфтовый, температура рабочей среды от -15 до +110°С, номинальное давление PN 4,0 МПа, номинальный диаметр DN 15 мм | H43: шт. | I43: =I39*J43 -> 0 | J43: 33.333333 | K43: 33.333333 | O43: =ROUND(CP43,2) -> 0 | P43: =ROUND((ROUND((AC43*AW43*I43),2)*BC43),2) -> 0 | Q43: =(ROUND((ROUND(((ET43)*AV43*I43),2)*BB43),2)+ROUND((ROUND(((AE43-(EU43))*AV43*I43),2)*BS43),2)) -> 0 | R43: =ROUND((ROUND((AE43*AV43*I43),2)*BS43),2) -> 0 | S43: =ROUND((ROUND((AF43*AV43*I43),2)*BA43),2) -> 0 | T43: =ROUND(CU43*I43,2) -> 0 | U43: =CV43*I43 -> 0 | V43: =CW43*I43 -> 0 | W43: =ROUND(CX43*I43,2) -> 0 | X43: =ROUND(CY43,2) -> 0 | Y43: =ROUND(CZ43,2) -> 0 | AA43: -1 | AB43: =ROUND((AC43+AD43+AF43),6) -> 34.97 | AC43: =ROUND((ES43),6) -> 34.97 | AD43: =ROUND((((ET43)-(EU43))+AE43),6) -> 0 | AE43: =ROUND((EU43),6) -> 0 | AF43: =ROUND((EV43),6) -> 0 | AG43: =ROUND((AP43),6) -> 0 | AH43: =(EW43) -> 0 | AI43: =(EX43) -> 0 | AJ43: =(AS43) -> 0 | AK43: 34.97 | AL43: 34.97 | AM43: 0 | AN43: 0 | AO43: 0 | AP43: 0 | AQ43: 0 | AR43: 0 | AS43: 0 | AT43: 109 | AU43: 61 | AV43: 1 | AW43: 1 | AZ43: 1 | BA43: 1 | BB43: 1 | BC43: 18.72 | BH43: 3 | BI43: 1 | BJ43: ТСН-2001.1 Доп. 73, Р. 13, о. 4, поз. 61 | BM43: 21 | BN43: 0 | BO43: 1.13-4-61 | BP43: 1 | BQ43: 30 | BR43: 0 | BS43: 1 | BT43: 1 | BU43: 1 | BV43: 1 | BW43: 1 | BX43: 1 | BZ43: 109 | CA43: 61 | CE43: 30 | CF43: 0 | CG43: 0 | CM43: 0 | CO43: 0 | CP43: =(P43+Q43+S43) -> 0 | CQ43: =ROUND((ROUND((AC43*AW43*1),2)*BC43),2) -> 654.64 | CR43: =(ROUND((ROUND(((ET43)*AV43*1),2)*BB43),2)+ROUND((ROUND(((AE43-(EU43))*AV43*1),2)*BS43),2)) -> 0 | CS43: =ROUND((ROUND((AE43*AV43*1),2)*BS43),2) -> 0 | CT43: =ROUND((ROUND((AF43*AV43*1),2)*BA43),2) -> 0 | CU43: =AG43 -> 0 | CV43: =(AH43*AV43) -> 0 | CW43: =AI43 -> 0 | CX43: =AJ43 -> 0 | CY43: =(((S43+R43)*AT43)/100) -> 0 | CZ43: =(((S43+R43)*AU43)/100) -> 0 | DN43: 0 | DO43: 0 | DP43: 1 | DQ43: 1 | DU43: 1010 | DV43: шт. | DW43: шт. | DX43: 1 | EE43: 58807897 | EF43: 30 | EG43: Строительные работы | EH43: 0 | EJ43: 1 | EK43: 21 | EL43: ТСН-2001.3-16. Трубопроводы внутренние | EM43: ТСН-2001.3-16-1 | EQ43: 1024 | ER43: 34.97 | ES43: 34.97 | ET43: 0 | EU43: 0 | EV43: 0 | EW43: 0 | EX43: 0 | FQ43: 0 | FR43: 0 | FS43: 0 | FX43: 109 | FY43: 61 | GD43: 1 | GF43: -1914030801 | GG43: 2 | GH43: 1 | GI43: 2 | GJ43: 0 | GK43: 0 | GL43: =ROUND(IF(AND(BH43=3,BI43=3,FS43<>0),P43,0),2) -> 0 | GM43: =ROUND(O43+X43+Y43,2)+GX43 -> 0 | GN43: =IF(OR(BI43=0,BI43=1),GM43-GX43,0) -> 0 | GO43: =IF(BI43=2,GM43-GX43,0) -> 0 | GP43: =IF(BI43=4,GM43-GX43,0) -> 0 | GR43: 0 | GS43: 3 | GT43: 0 | GV43: =ROUND((GT43),6) -> 0 | GW43: 1 | GX43: =ROUND(HC43*I43,2) -> 0 | HA43: 0 | HB43: 0 | HC43: =GV43*GW43 -> 0 | HS43: 0 | IK43: 0
A44: 18 | B44: 1 | C44: 39 | F44: 1.13-4-137 | G44: Кран шаровой, латунный, никелированный, спускной, с наружной резьбой, с насадкой для шланга, с алюминиевой рукояткой, температура рабочей среды от -15 до +90°С, пропускная способность 1,9 м3/ч, номинальное давление PN 1,0 МПа, номинальный диаметр DN 15 мм | H44: шт. | I44: =I38*J44 -> 0 | J44: 244.44444 | K44: 244.44444 | O44: =ROUND(CP44,2) -> 0 | P44: =ROUND((ROUND((AC44*AW44*I44),2)*BC44),2) -> 0 | Q44: =(ROUND((ROUND(((ET44)*AV44*I44),2)*BB44),2)+ROUND((ROUND(((AE44-(EU44))*AV44*I44),2)*BS44),2)) -> 0 | R44: =ROUND((ROUND((AE44*AV44*I44),2)*BS44),2) -> 0 | S44: =ROUND((ROUND((AF44*AV44*I44),2)*BA44),2) -> 0 | T44: =ROUND(CU44*I44,2) -> 0 | U44: =CV44*I44 -> 0 | V44: =CW44*I44 -> 0 | W44: =ROUND(CX44*I44,2) -> 0 | X44: =ROUND(CY44,2) -> 0 | Y44: =ROUND(CZ44,2) -> 0 | AA44: -1 | AB44: =ROUND((AC44+AD44+AF44),6) -> 24.61 | AC44: =ROUND((ES44),6) -> 24.61 | AD44: =ROUND((((ET44)-(EU44))+AE44),6) -> 0 | AE44: =ROUND((EU44),6) -> 0 | AF44: =ROUND((EV44),6) -> 0 | AG44: =ROUND((AP44),6) -> 0 | AH44: =(EW44) -> 0 | AI44: =(EX44) -> 0 | AJ44: =(AS44) -> 0 | AK44: 24.61 | AL44: 24.61 | AM44: 0 | AN44: 0 | AO44: 0 | AP44: 0 | AQ44: 0 | AR44: 0 | AS44: 0 | AT44: 109 | AU44: 61 | AV44: 1 | AW44: 1 | AZ44: 1 | BA44: 1 | BB44: 1 | BC44: 1 | BH44: 3 | BI44: 1 | BJ44: ТСН-2001.1 Доп. 73, Р. 13, о. 4, поз. 137 | BM44: 21 | BN44: 0 | BP44: 0 | BQ44: 30 | BR44: 0 | BS44: 1 | BT44: 1 | BU44: 1 | BV44: 1 | BW44: 1 | BX44: 1 | BZ44: 109 | CA44: 61 | CE44: 30 | CF44: 0 | CG44: 0 | CM44: 0 | CO44: 0 | CP44: =(P44+Q44+S44) -> 0 | CQ44: =ROUND((ROUND((AC44*AW44*1),2)*BC44),2) -> 24.61 | CR44: =(ROUND((ROUND(((ET44)*AV44*1),2)*BB44),2)+ROUND((ROUND(((AE44-(EU44))*AV44*1),2)*BS44),2)) -> 0 | CS44: =ROUND((ROUND((AE44*AV44*1),2)*BS44),2) -> 0 | CT44: =ROUND((ROUND((AF44*AV44*1),2)*BA44),2) -> 0 | CU44: =AG44 -> 0 | CV44: =(AH44*AV44) -> 0 | CW44: =AI44 -> 0 | CX44: =AJ44 -> 0 | CY44: =(((S44+R44)*AT44)/100) -> 0 | CZ44: =(((S44+R44)*AU44)/100) -> 0 | DN44: 0 | DO44: 0 | DP44: 1 | DQ44: 1 | DU44: 1010 | DV44: шт. | DW44: шт. | DX44: 1 | EE44: 58807897 | EF44: 30 | EG44: Строительные работы | EH44: 0 | EJ44: 1 | EK44: 21 | EL44: ТСН-2001.3-16. Трубопроводы внутренние | EM44: ТСН-2001.3-16-1 | EQ44: 1024 | ER44: 24.61 | ES44: 24.61 | ET44: 0 | EU44: 0 | EV44: 0 | EW44: 0 | EX44: 0 | FQ44: 0 | FR44: 0 | FS44: 0 | FX44: 109 | FY44: 61 | GD44: 1 | GF44: -877742701 | GG44: 2 | GH44: 1 | GI44: -2 | GJ44: 0 | GK44: 0 | GL44: =ROUND(IF(AND(BH44=3,BI44=3,FS44<>0),P44,0),2) -> 0 | GM44: =ROUND(O44+X44+Y44,2)+GX44 -> 0 | GN44: =IF(OR(BI44=0,BI44=1),GM44-GX44,0) -> 0 | GO44: =IF(BI44=2,GM44-GX44,0) -> 0 | GP44: =IF(BI44=4,GM44-GX44,0) -> 0 | GR44: 0 | GS44: 3 | GT44: 0 | GV44: =ROUND((GT44),6) -> 0 | GW44: 1 | GX44: =ROUND(HC44*I44,2) -> 0 | HA44: 0 | HB44: 0 | HC44: =GV44*GW44 -> 0 | HS44: 0 | IK44: 0
A45: 18 | B45: 1 | C45: 55 | F45: 1.13-4-137 | G45: Кран шаровой, латунный, никелированный, спускной, с наружной резьбой, с насадкой для шланга, с алюминиевой рукояткой, температура рабочей среды от -15 до +90°С, пропускная способность 1,9 м3/ч, номинальное давление PN 1,0 МПа, номинальный диаметр DN 15 мм | H45: шт. | I45: =I39*J45 -> 0 | J45: 244.44444 | K45: 244.44444 | O45: =ROUND(CP45,2) -> 0 | P45: =ROUND((ROUND((AC45*AW45*I45),2)*BC45),2) -> 0 | Q45: =(ROUND((ROUND(((ET45)*AV45*I45),2)*BB45),2)+ROUND((ROUND(((AE45-(EU45))*AV45*I45),2)*BS45),2)) -> 0 | R45: =ROUND((ROUND((AE45*AV45*I45),2)*BS45),2) -> 0 | S45: =ROUND((ROUND((AF45*AV45*I45),2)*BA45),2) -> 0 | T45: =ROUND(CU45*I45,2) -> 0 | U45: =CV45*I45 -> 0 | V45: =CW45*I45 -> 0 | W45: =ROUND(CX45*I45,2) -> 0 | X45: =ROUND(CY45,2) -> 0 | Y45: =ROUND(CZ45,2) -> 0 | AA45: -1 | AB45: =ROUND((AC45+AD45+AF45),6) -> 24.61 | AC45: =ROUND((ES45),6) -> 24.61 | AD45: =ROUND((((ET45)-(EU45))+AE45),6) -> 0 | AE45: =ROUND((EU45),6) -> 0 | AF45: =ROUND((EV45),6) -> 0 | AG45: =ROUND((AP45),6) -> 0 | AH45: =(EW45) -> 0 | AI45: =(EX45) -> 0 | AJ45: =(AS45) -> 0 | AK45: 24.61 | AL45: 24.61 | AM45: 0 | AN45: 0 | AO45: 0 | AP45: 0 | AQ45: 0 | AR45: 0 | AS45: 0 | AT45: 109 | AU45: 61 | AV45: 1 | AW45: 1 | AZ45: 1 | BA45: 1 | BB45: 1 | BC45: 35.58 | BH45: 3 | BI45: 1 | BJ45: ТСН-2001.1 Доп. 73, Р. 13, о. 4, поз. 137 | BM45: 21 | BN45: 0 | BO45: 1.13-4-137 | BP45: 1 | BQ45: 30 | BR45: 0 | BS45: 1 | BT45: 1 | BU45: 1 | BV45: 1 | BW45: 1 | BX45: 1 | BZ45: 109 | CA45: 61 | CE45: 30 | CF45: 0 | CG45: 0 | CM45: 0 | CO45: 0 | CP45: =(P45+Q45+S45) -> 0 | CQ45: =ROUND((ROUND((AC45*AW45*1),2)*BC45),2) -> 875.62 | CR45: =(ROUND((ROUND(((ET45)*AV45*1),2)*BB45),2)+ROUND((ROUND(((AE45-(EU45))*AV45*1),2)*BS45),2)) -> 0 | CS45: =ROUND((ROUND((AE45*AV45*1),2)*BS45),2) -> 0 | CT45: =ROUND((ROUND((AF45*AV45*1),2)*BA45),2) -> 0 | CU45: =AG45 -> 0 | CV45: =(AH45*AV45) -> 0 | CW45: =AI45 -> 0 | CX45: =AJ45 -> 0 | CY45: =(((S45+R45)*AT45)/100) -> 0 | CZ45: =(((S45+R45)*AU45)/100) -> 0 | DN45: 0 | DO45: 0 | DP45: 1 | DQ45: 1 | DU45: 1010 | DV45: шт. | DW45: шт. | DX45: 1 | EE45: 58807897 | EF45: 30 | EG45: Строительные работы | EH45: 0 | EJ45: 1 | EK45: 21 | EL45: ТСН-2001.3-16. Трубопроводы внутренние | EM45: ТСН-2001.3-16-1 | EQ45: 1024 | ER45: 24.61 | ES45: 24.61 | ET45: 0 | EU45: 0 | EV45: 0 | EW45: 0 | EX45: 0 | FQ45: 0 | FR45: 0 | FS45: 0 | FX45: 109 | FY45: 61 | GD45: 1 | GF45: -877742701 | GG45: 2 | GH45: 1 | GI45: 2 | GJ45: 0 | GK45: 0 | GL45: =ROUND(IF(AND(BH45=3,BI45=3,FS45<>0),P45,0),2) -> 0 | GM45: =ROUND(O45+X45+Y45,2)+GX45 -> 0 | GN45: =IF(OR(BI45=0,BI45=1),GM45-GX45,0) -> 0 | GO45: =IF(BI45=2,GM45-GX45,0) -> 0 | GP45: =IF(BI45=4,GM45-GX45,0) -> 0 | GR45: 0 | GS45: 3 | GT45: 0 | GV45: =ROUND((GT45),6) -> 0 | GW45: 1 | GX45: =ROUND(HC45*I45,2) -> 0 | HA45: 0 | HB45: 0 | HC45: =GV45*GW45 -> 0 | HS45: 0 | IK45: 0
A46: 18 | B46: 1 | C46: 38 | F46: 1.12-1-52 | G46: Узел трубопровода из стальных водогазопроводных оцинкованных труб, с гильзами, для водоснабжения, диаметр условного прохода 15 мм | H46: м | I46: =I38*J46 -> 0 | J46: 100 | K46: 100 | O46: =ROUND(CP46,2) -> 0 | P46: =ROUND((ROUND((AC46*AW46*I46),2)*BC46),2) -> 0 | Q46: =(ROUND((ROUND(((ET46)*AV46*I46),2)*BB46),2)+ROUND((ROUND(((AE46-(EU46))*AV46*I46),2)*BS46),2)) -> 0 | R46: =ROUND((ROUND((AE46*AV46*I46),2)*BS46),2) -> 0 | S46: =ROUND((ROUND((AF46*AV46*I46),2)*BA46),2) -> 0 | T46: =ROUND(CU46*I46,2) -> 0 | U46: =CV46*I46 -> 0 | V46: =CW46*I46 -> 0 | W46: =ROUND(CX46*I46,2) -> 0 | X46: =ROUND(CY46,2) -> 0 | Y46: =ROUND(CZ46,2) -> 0 | AA46: -1 | AB46: =ROUND((AC46+AD46+AF46),6) -> 28.1 | AC46: =ROUND((ES46),6) -> 28.1 | AD46: =ROUND((((ET46)-(EU46))+AE46),6) -> 0 | AE46: =ROUND((EU46),6) -> 0 | AF46: =ROUND((EV46),6) -> 0 | AG46: =ROUND((AP46),6) -> 0 | AH46: =(EW46) -> 0 | AI46: =(EX46) -> 0 | AJ46: =(AS46) -> 0 | AK46: 28.1 | AL46: 28.1 | AM46: 0 | AN46: 0 | AO46: 0 | AP46: 0 | AQ46: 0 | AR46: 0 | AS46: 0 | AT46: 109 | AU46: 61 | AV46: 1 | AW46: 1 | AZ46: 1 | BA46: 1 | BB46: 1 | BC46: 1 | BH46: 3 | BI46: 1 | BJ46: ТСН-2001.1 Доп. 79, Р. 12, о. 1, поз. 52 | BM46: 21 | BN46: 0 | BP46: 0 | BQ46: 30 | BR46: 0 | BS46: 1 | BT46: 1 | BU46: 1 | BV46: 1 | BW46: 1 | BX46: 1 | BZ46: 109 | CA46: 61 | CE46: 30 | CF46: 0 | CG46: 0 | CM46: 0 | CO46: 0 | CP46: =(P46+Q46+S46) -> 0 | CQ46: =ROUND((ROUND((AC46*AW46*1),2)*BC46),2) -> 28.1 | CR46: =(ROUND((ROUND(((ET46)*AV46*1),2)*BB46),2)+ROUND((ROUND(((AE46-(EU46))*AV46*1),2)*BS46),2)) -> 0 | CS46: =ROUND((ROUND((AE46*AV46*1),2)*BS46),2) -> 0 | CT46: =ROUND((ROUND((AF46*AV46*1),2)*BA46),2) -> 0 | CU46: =AG46 -> 0 | CV46: =(AH46*AV46) -> 0 | CW46: =AI46 -> 0 | CX46: =AJ46 -> 0 | CY46: =(((S46+R46)*AT46)/100) -> 0 | CZ46: =(((S46+R46)*AU46)/100) -> 0 | DN46: 0 | DO46: 0 | DP46: 1 | DQ46: 1 | DU46: 1003 | DV46: м | DW46: м | DX46: 1 | EE46: 58807897 | EF46: 30 | EG46: Строительные работы | EH46: 0 | EJ46: 1 | EK46: 21 | EL46: ТСН-2001.3-16. Трубопроводы внутренние | EM46: ТСН-2001.3-16-1 | EQ46: 1024 | ER46: 28.1 | ES46: 28.1 | ET46: 0 | EU46: 0 | EV46: 0 | EW46: 0 | EX46: 0 | FQ46: 0 | FR46: 0 | FS46: 0 | FX46: 109 | FY46: 61 | GD46: 1 | GF46: 949658601 | GG46: 2 | GH46: 1 | GI46: -2 | GJ46: 0 | GK46: 0 | GL46: =ROUND(IF(AND(BH46=3,BI46=3,FS46<>0),P46,0),2) -> 0 | GM46: =ROUND(O46+X46+Y46,2)+GX46 -> 0 | GN46: =IF(OR(BI46=0,BI46=1),GM46-GX46,0) -> 0 | GO46: =IF(BI46=2,GM46-GX46,0) -> 0 | GP46: =IF(BI46=4,GM46-GX46,0) -> 0 | GR46: 0 | GS46: 3 | GT46: 0 | GV46: =ROUND((GT46),6) -> 0 | GW46: 1 | GX46: =ROUND(HC46*I46,2) -> 0 | HA46: 0 | HB46: 0 | HC46: =GV46*GW46 -> 0 | HS46: 0 | IK46: 0
A47: 18 | B47: 1 | C47: 54 | F47: 1.12-1-52 | G47: Узел трубопровода из стальных водогазопроводных оцинкованных труб, с гильзами, для водоснабжения, диаметр условного прохода 15 мм | H47: м | I47: =I39*J47 -> 0 | J47: 100 | K47: 100 | O47: =ROUND(CP47,2) -> 0 | P47: =ROUND((ROUND((AC47*AW47*I47),2)*BC47),2) -> 0 | Q47: =(ROUND((ROUND(((ET47)*AV47*I47),2)*BB47),2)+ROUND((ROUND(((AE47-(EU47))*AV47*I47),2)*BS47),2)) -> 0 | R47: =ROUND((ROUND((AE47*AV47*I47),2)*BS47),2) -> 0 | S47: =ROUND((ROUND((AF47*AV47*I47),2)*BA47),2) -> 0 | T47: =ROUND(CU47*I47,2) -> 0 | U47: =CV47*I47 -> 0 | V47: =CW47*I47 -> 0 | W47: =ROUND(CX47*I47,2) -> 0 | X47: =ROUND(CY47,2) -> 0 | Y47: =ROUND(CZ47,2) -> 0 | AA47: -1 | AB47: =ROUND((AC47+AD47+AF47),6) -> 28.1 | AC47: =ROUND((ES47),6) -> 28.1 | AD47: =ROUND((((ET47)-(EU47))+AE47),6) -> 0 | AE47: =ROUND((EU47),6) -> 0 | AF47: =ROUND((EV47),6) -> 0 | AG47: =ROUND((AP47),6) -> 0 | AH47: =(EW47) -> 0 | AI47: =(EX47) -> 0 | AJ47: =(AS47) -> 0 | AK47: 28.1 | AL47: 28.1 | AM47: 0 | AN47: 0 | AO47: 0 | AP47: 0 | AQ47: 0 | AR47: 0 | AS47: 0 | AT47: 109 | AU47: 61 | AV47: 1 | AW47: 1 | AZ47: 1 | BA47: 1 | BB47: 1 | BC47: 18.63 | BH47: 3 | BI47: 1 | BJ47: ТСН-2001.1 Доп. 79, Р. 12, о. 1, поз. 52 | BM47: 21 | BN47: 0 | BO47: 1.12-1-52 | BP47: 1 | BQ47: 30 | BR47: 0 | BS47: 1 | BT47: 1 | BU47: 1 | BV47: 1 | BW47: 1 | BX47: 1 | BZ47: 109 | CA47: 61 | CE47: 30 | CF47: 0 | CG47: 0 | CM47: 0 | CO47: 0 | CP47: =(P47+Q47+S47) -> 0 | CQ47: =ROUND((ROUND((AC47*AW47*1),2)*BC47),2) -> 523.5 | CR47: =(ROUND((ROUND(((ET47)*AV47*1),2)*BB47),2)+ROUND((ROUND(((AE47-(EU47))*AV47*1),2)*BS47),2)) -> 0 | CS47: =ROUND((ROUND((AE47*AV47*1),2)*BS47),2) -> 0 | CT47: =ROUND((ROUND((AF47*AV47*1),2)*BA47),2) -> 0 | CU47: =AG47 -> 0 | CV47: =(AH47*AV47) -> 0 | CW47: =AI47 -> 0 | CX47: =AJ47 -> 0 | CY47: =(((S47+R47)*AT47)/100) -> 0 | CZ47: =(((S47+R47)*AU47)/100) -> 0 | DN47: 0 | DO47: 0 | DP47: 1 | DQ47: 1 | DU47: 1003 | DV47: м | DW47: м | DX47: 1 | EE47: 58807897 | EF47: 30 | EG47: Строительные работы | EH47: 0 | EJ47: 1 | EK47: 21 | EL47: ТСН-2001.3-16. Трубопроводы внутренние | EM47: ТСН-2001.3-16-1 | EQ47: 1024 | ER47: 28.1 | ES47: 28.1 | ET47: 0 | EU47: 0 | EV47: 0 | EW47: 0 | EX47: 0 | FQ47: 0 | FR47: 0 | FS47: 0 | FX47: 109 | FY47: 61 | GD47: 1 | GF47: 949658601 | GG47: 2 | GH47: 1 | GI47: 2 | GJ47: 0 | GK47: 0 | GL47: =ROUND(IF(AND(BH47=3,BI47=3,FS47<>0),P47,0),2) -> 0 | GM47: =ROUND(O47+X47+Y47,2)+GX47 -> 0 | GN47: =IF(OR(BI47=0,BI47=1),GM47-GX47,0) -> 0 | GO47: =IF(BI47=2,GM47-GX47,0) -> 0 | GP47: =IF(BI47=4,GM47-GX47,0) -> 0 | GR47: 0 | GS47: 3 | GT47: 0 | GV47: =ROUND((GT47),6) -> 0 | GW47: 1 | GX47: =ROUND(HC47*I47,2) -> 0 | HA47: 0 | HB47: 0 | HC47: =GV47*GW47 -> 0 | HS47: 0 | IK47: 0
A48: 17 | B48: 1 | C48: =ROW(SmtRes!A67) -> 67 | D48: =ROW(EtalonRes!A63) -> 63 | E48: 2 | F48: 3.16-38-1 | G48: Прокладка трубопроводов из стальных труб на бессварных разъемных муфтовых соединениях диаметром до 25 мм | H48: 100 м | I48: =ROUND(ROUND(110/100,4),9) -> 1.1 | J48: 0 | K48: =ROUND(ROUND(110/100,4),9) -> 1.1 | O48: =ROUND(CP48,2) -> 391.24 | P48: =ROUND((ROUND((AC48*AW48*I48),2)*BC48),2) -> 33.04 | Q48: =(ROUND((ROUND(((((ET48*1.25)*1.1))*AV48*I48),2)*BB48),2)+ROUND((ROUND(((AE48-(((EU48*1.25)*1.1)))*AV48*I48),2)*BS48),2)) -> 6.57 | R48: =ROUND((ROUND((AE48*AV48*I48),2)*BS48),2) -> 0.48 | S48: =ROUND((ROUND((AF48*AV48*I48),2)*BA48),2) -> 351.63 | T48: =ROUND(CU48*I48,2) -> 0 | U48: =CV48*I48 -> 28.388047 | V48: =CW48*I48 -> 0 | W48: =ROUND(CX48*I48,2) -> 0 | X48: =ROUND(CY48,2) -> 383.8 | Y48: =ROUND(CZ48,2) -> 214.79 | AA48: 59204062 | AB48: =ROUND((AC48+AD48+AF48),6) -> 335.2262 | AC48: =ROUND((ES48),6) -> 30.04 | AD48: =ROUND((((((ET48*1.25)*1.1))-(((EU48*1.25)*1.1)))+AE48),6) -> 5.59625 | AE48: =ROUND((((EU48*1.25)*1.1)),6) -> 0.4125 | AF48: =ROUND((((EV48*1.15)*1.1)),6) -> 299.58995 | AG48: =ROUND((AP48),6) -> 0 | AH48: =(((EW48*1.15)*1.1)) -> 24.1868 | AI48: =(((EX48*1.25)*1.1)) -> 0 | AJ48: =(AS48) -> 0 | AK48: 270.94 | AL48: 30.04 | AM48: 4.07 | AN48: 0.3 | AO48: 236.83 | AP48: 0 | AQ48: 19.12 | AR48: 0 | AS48: 0 | AT48: 109 | AU48: 61 | AV48: 1.067 | AW48: 1 | AZ48: 1 | BA48: 1 | BB48: 1 | BC48: 1 | BH48: 0 | BI48: 1 | BJ48: ТСН-2001.3 Доп. 80, Сб. 16, т. 38, поз. 1 | BM48: 21 | BN48: 0 | BO48: 3.16-38-1 | BP48: 1 | BQ48: 30 | BR48: 0 | BS48: 1 | BT48: 1 | BU48: 1 | BV48: 1 | BW48: 1 | BX48: 1 | BZ48: 109 | CA48: 61 | CE48: 30 | CF48: 0 | CG48: 0 | CM48: 0 | CN48: Поправка: О.П. п.3.4. 6 Наименование: Выполняемые при ремонте и реконструкции работы аналогичные технологическим процессам, характерным для нового строительства и отсутствующим в сборниках на ремонтно-строительные работы Поправка: О.П. п.3.4.30.в Наименование: При применении территориальных сметных нормативов для города Москвы затраты, учитывающие напряженные и стесненные условия производства работ (стесненность, сложность складирования и транспортной логистики и т.п.), исчисляются с применением коэффициентов к затратам труда и заработной плате рабочих, машинистов, времени эксплуатации машин и механизмов, стоимости эксплуатации машин в размере: для объектов, расположенных за пределами Третьего транспортного кольца города Москвы, но в пределах Московской кольцевой автомобильной дороги | CO48: 0 | CP48: =(P48+Q48+S48) -> 391.24 | CQ48: =ROUND((ROUND((AC48*AW48*1),2)*BC48),2) -> 30.04 | CR48: =(ROUND((ROUND(((((ET48*1.25)*1.1))*AV48*1),2)*BB48),2)+ROUND((ROUND(((AE48-(((EU48*1.25)*1.1)))*AV48*1),2)*BS48),2)) -> 5.97 | CS48: =ROUND((ROUND((AE48*AV48*1),2)*BS48),2) -> 0.44 | CT48: =ROUND((ROUND((AF48*AV48*1),2)*BA48),2) -> 319.66 | CU48: =AG48 -> 0 | CV48: =(AH48*AV48) -> 25.807316 | CW48: =AI48 -> 0 | CX48: =AJ48 -> 0 | CY48: =(((S48+R48)*AT48)/100) -> 383.7999 | CZ48: =(((S48+R48)*AU48)/100) -> 214.7871 | DB48: 9 | DE48: *1,25)*1,1 | DF48: *1,25)*1,1 | DG48: *1,15)*1,1 | DI48: *1,15)*1,1 | DJ48: *1,25)*1,1 | DN48: 0 | DO48: 0 | DP48: 1 | DQ48: 1 | DU48: 1003 | DV48: 100 м | DW48: 100 м | DX48: 100 | EE48: 58807897 | EF48: 30 | EG48: Строительные работы | EH48: 0 | EJ48: 1 | EK48: 21 | EL48: ТСН-2001.3-16. Трубопроводы внутренние | EM48: ТСН-2001.3-16-1 | EO48: Поправка: О.П. п.3.4. 6 Поправка: О.П. п.3.4.30.в | EQ48: 0 | ER48: 270.94 | ES48: 30.04 | ET48: 4.07 | EU48: 0.3 | EV48: 236.83 | EW48: 19.12 | EX48: 0 | EY48: 0 | FQ48: 0 | FR48: 0 | FS48: 0 | FX48: 109 | FY48: 61 | GD48: 1 | GF48: -367569951 | GG48: 2 | GH48: 1 | GI48: 2 | GJ48: 0 | GK48: 0 | GL48: =ROUND(IF(AND(BH48=3,BI48=3,FS48<>0),P48,0),2) -> 0 | GM48: =ROUND(O48+X48+Y48,2)+GX48 -> 989.83 | GN48: =IF(OR(BI48=0,BI48=1),GM48-GX48,0) -> 989.83 | GO48: =IF(BI48=2,GM48-GX48,0) -> 0 | GP48: =IF(BI48=4,GM48-GX48,0) -> 0 | GR48: 0 | GS48: 3 | GT48: 0 | GV48: =ROUND((GT48),6) -> 0 | GW48: 1 | GX48: =ROUND(HC48*I48,2) -> 0 | HA48: 0 | HB48: 0 | HC48: =GV48*GW48 -> 0 | HS48: 0 | IK48: 0
A49: 17 | B49: 1 | C49: =ROW(SmtRes!A78) -> 78 | D49: =ROW(EtalonRes!A74) -> 74 | E49: 2 | F49: 3.16-38-1 | G49: Прокладка трубопроводов из стальных труб на бессварных разъемных муфтовых соединениях диаметром до 25 мм | H49: 100 м | I49: =ROUND(ROUND(110/100,4),9) -> 1.1 | J49: 0 | K49: =ROUND(ROUND(110/100,4),9) -> 1.1 | O49: =ROUND(CP49,2) -> 19477 | P49: =ROUND((ROUND((AC49*AW49*I49),2)*BC49),2) -> 59.14 | Q49: =(ROUND((ROUND(((((ET49*1.25)*1.1))*AV49*I49),2)*BB49),2)+ROUND((ROUND(((AE49-(((EU49*1.25)*1.1)))*AV49*I49),2)*BS49),2)) -> 81.73 | R49: =ROUND((ROUND((AE49*AV49*I49),2)*BS49),2) -> 26.4 | S49: =ROUND((ROUND((AF49*AV49*I49),2)*BA49),2) -> 19336.13 | T49: =ROUND(CU49*I49,2) -> 0 | U49: =CV49*I49 -> 28.388047 | V49: =CW49*I49 -> 0 | W49: =ROUND(CX49*I49,2) -> 0 | X49: =ROUND(CY49,2) -> 21105.16 | Y49: =ROUND(CZ49,2) -> 11811.14 | AA49: 59204059 | AB49: =ROUND((AC49+AD49+AF49),6) -> 335.2262 | AC49: =ROUND((ES49),6) -> 30.04 | AD49: =ROUND((((((ET49*1.25)*1.1))-(((EU49*1.25)*1.1)))+AE49),6) -> 5.59625 | AE49: =ROUND((((EU49*1.25)*1.1)),6) -> 0.4125 | AF49: =ROUND((((EV49*1.15)*1.1)),6) -> 299.58995 | AG49: =ROUND((AP49),6) -> 0 | AH49: =(((EW49*1.15)*1.1)) -> 24.1868 | AI49: =(((EX49*1.25)*1.1)) -> 0 | AJ49: =(AS49) -> 0 | AK49: 270.94 | AL49: 30.04 | AM49: 4.07 | AN49: 0.3 | AO49: 236.83 | AP49: 0 | AQ49: 19.12 | AR49: 0 | AS49: 0 | AT49: 109 | AU49: 61 | AV49: 1.067 | AW49: 1 | AZ49: 1 | BA49: 54.99 | BB49: 12.44 | BC49: 1.79 | BH49: 0 | BI49: 1 | BJ49: ТСН-2001.3 Доп. 80, Сб. 16, т. 38, поз. 1 | BM49: 21 | BN49: 0 | BO49: 3.16-38-1 | BP49: 1 | BQ49: 30 | BR49: 0 | BS49: 54.99 | BT49: 1 | BU49: 1 | BV49: 1 | BW49: 1 | BX49: 1 | BZ49: 109 | CA49: 61 | CE49: 30 | CF49: 0 | CG49: 0 | CM49: 0 | CN49: Поправка: О.П. п.3.4. 6 Наименование: Выполняемые при ремонте и реконструкции работы аналогичные технологическим процессам, характерным для нового строительства и отсутствующим в сборниках на ремонтно-строительные работы Поправка: О.П. п.3.4.30.в Наименование: При применении территориальных сметных нормативов для города Москвы затраты, учитывающие напряженные и стесненные условия производства работ (стесненность, сложность складирования и транспортной логистики и т.п.), исчисляются с применением коэффициентов к затратам труда и заработной плате рабочих, машинистов, времени эксплуатации машин и механизмов, стоимости эксплуатации машин в размере: для объектов, расположенных за пределами Третьего транспортного кольца города Москвы, но в пределах Московской кольцевой автомобильной дороги | CO49: 0 | CP49: =(P49+Q49+S49) -> 19477 | CQ49: =ROUND((ROUND((AC49*AW49*1),2)*BC49),2) -> 53.77 | CR49: =(ROUND((ROUND(((((ET49*1.25)*1.1))*AV49*1),2)*BB49),2)+ROUND((ROUND(((AE49-(((EU49*1.25)*1.1)))*AV49*1),2)*BS49),2)) -> 74.27 | CS49: =ROUND((ROUND((AE49*AV49*1),2)*BS49),2) -> 24.2 | CT49: =ROUND((ROUND((AF49*AV49*1),2)*BA49),2) -> 17578.1 | CU49: =AG49 -> 0 | CV49: =(AH49*AV49) -> 25.807316 | CW49: =AI49 -> 0 | CX49: =AJ49 -> 0 | CY49: =(((S49+R49)*AT49)/100) -> 21105.158 | CZ49: =(((S49+R49)*AU49)/100) -> 11811.143 | DB49: 11 | DE49: *1,25)*1,1 | DF49: *1,25)*1,1 | DG49: *1,15)*1,1 | DI49: *1,15)*1,1 | DJ49: *1,25)*1,1 | DN49: 0 | DO49: 0 | DP49: 1 | DQ49: 1 | DU49: 1003 | DV49: 100 м | DW49: 100 м | DX49: 100 | EE49: 58807897 | EF49: 30 | EG49: Строительные работы | EH49: 0 | EJ49: 1 | EK49: 21 | EL49: ТСН-2001.3-16. Трубопроводы внутренние | EM49: ТСН-2001.3-16-1 | EO49: Поправка: О.П. п.3.4. 6 Поправка: О.П. п.3.4.30.в | EQ49: 0 | ER49: 270.94 | ES49: 30.04 | ET49: 4.07 | EU49: 0.3 | EV49: 236.83 | EW49: 19.12 | EX49: 0 | EY49: 0 | FQ49: 0 | FR49: 0 | FS49: 0 | FX49: 109 | FY49: 61 | GD49: 1 | GF49: -367569951 | GG49: 2 | GH49: 1 | GI49: 2 | GJ49: 0 | GK49: 0 | GL49: =ROUND(IF(AND(BH49=3,BI49=3,FS49<>0),P49,0),2) -> 0 | GM49: =ROUND(O49+X49+Y49,2)+GX49 -> 52393.3 | GN49: =IF(OR(BI49=0,BI49=1),GM49-GX49,0) -> 52393.3 | GO49: =IF(BI49=2,GM49-GX49,0) -> 0 | GP49: =IF(BI49=4,GM49-GX49,0) -> 0 | GR49: 0 | GS49: 3 | GT49: 0 | GV49: =ROUND((GT49),6) -> 0 | GW49: 1 | GX49: =ROUND(HC49*I49,2) -> 0 | HA49: 0 | HB49: 0 | HC49: =GV49*GW49 -> 0 | HS49: 0 | IK49: 0
A50: 18 | B50: 1 | C50: 66 | E50: 2,1 | F50: 1.12-1-53 | G50: Узел трубопровода из стальных водогазопроводных оцинкованных труб, с гильзами, для водоснабжения, диаметр условного прохода 20 мм | H50: м | I50: =I48*J50 -> 110 | J50: 100 | K50: 100 | O50: =ROUND(CP50,2) -> 3455.1 | P50: =ROUND((ROUND((AC50*AW50*I50),2)*BC50),2) -> 3455.1 | Q50: =(ROUND((ROUND(((ET50)*AV50*I50),2)*BB50),2)+ROUND((ROUND(((AE50-(EU50))*AV50*I50),2)*BS50),2)) -> 0 | R50: =ROUND((ROUND((AE50*AV50*I50),2)*BS50),2) -> 0 | S50: =ROUND((ROUND((AF50*AV50*I50),2)*BA50),2) -> 0 | T50: =ROUND(CU50*I50,2) -> 0 | U50: =CV50*I50 -> 0 | V50: =CW50*I50 -> 0 | W50: =ROUND(CX50*I50,2) -> 0 | X50: =ROUND(CY50,2) -> 0 | Y50: =ROUND(CZ50,2) -> 0 | AA50: 59204062 | AB50: =ROUND((AC50+AD50+AF50),6) -> 31.41 | AC50: =ROUND((ES50),6) -> 31.41 | AD50: =ROUND((((ET50)-(EU50))+AE50),6) -> 0 | AE50: =ROUND((EU50),6) -> 0 | AF50: =ROUND((EV50),6) -> 0 | AG50: =ROUND((AP50),6) -> 0 | AH50: =(EW50) -> 0 | AI50: =(EX50) -> 0 | AJ50: =(AS50) -> 0 | AK50: 31.41 | AL50: 31.41 | AM50: 0 | AN50: 0 | AO50: 0 | AP50: 0 | AQ50: 0 | AR50: 0 | AS50: 0 | AT50: 109 | AU50: 61 | AV50: 1 | AW50: 1 | AZ50: 1 | BA50: 1 | BB50: 1 | BC50: 1 | BH50: 3 | BI50: 1 | BJ50: ТСН-2001.1 Доп. 79, Р. 12, о. 1, поз. 53 | BM50: 21 | BN50: 0 | BP50: 0 | BQ50: 30 | BR50: 0 | BS50: 1 | BT50: 1 | BU50: 1 | BV50: 1 | BW50: 1 | BX50: 1 | BZ50: 109 | CA50: 61 | CE50: 30 | CF50: 0 | CG50: 0 | CM50: 0 | CO50: 0 | CP50: =(P50+Q50+S50) -> 3455.1 | CQ50: =ROUND((ROUND((AC50*AW50*1),2)*BC50),2) -> 31.41 | CR50: =(ROUND((ROUND(((ET50)*AV50*1),2)*BB50),2)+ROUND((ROUND(((AE50-(EU50))*AV50*1),2)*BS50),2)) -> 0 | CS50: =ROUND((ROUND((AE50*AV50*1),2)*BS50),2) -> 0 | CT50: =ROUND((ROUND((AF50*AV50*1),2)*BA50),2) -> 0 | CU50: =AG50 -> 0 | CV50: =(AH50*AV50) -> 0 | CW50: =AI50 -> 0 | CX50: =AJ50 -> 0 | CY50: =(((S50+R50)*AT50)/100) -> 0 | CZ50: =(((S50+R50)*AU50)/100) -> 0 | DN50: 0 | DO50: 0 | DP50: 1 | DQ50: 1 | DU50: 1003 | DV50: м | DW50: м | DX50: 1 | EE50: 58807897 | EF50: 30 | EG50: Строительные работы | EH50: 0 | EJ50: 1 | EK50: 21 | EL50: ТСН-2001.3-16. Трубопроводы внутренние | EM50: ТСН-2001.3-16-1 | EQ50: 0 | ER50: 31.41 | ES50: 31.41 | ET50: 0 | EU50: 0 | EV50: 0 | EW50: 0 | EX50: 0 | FQ50: 0 | FR50: 0 | FS50: 0 | FX50: 109 | FY50: 61 | GD50: 1 | GF50: -1171880344 | GG50: 2 | GH50: 1 | GI50: -2 | GJ50: 0 | GK50: 0 | GL50: =ROUND(IF(AND(BH50=3,BI50=3,FS50<>0),P50,0),2) -> 0 | GM50: =ROUND(O50+X50+Y50,2)+GX50 -> 3455.1 | GN50: =IF(OR(BI50=0,BI50=1),GM50-GX50,0) -> 3455.1 | GO50: =IF(BI50=2,GM50-GX50,0) -> 0 | GP50: =IF(BI50=4,GM50-GX50,0) -> 0 | GR50: 0 | GS50: 3 | GT50: 0 | GV50: =ROUND((GT50),6) -> 0 | GW50: 1 | GX50: =ROUND(HC50*I50,2) -> 0 | HA50: 0 | HB50: 0 | HC50: =GV50*GW50 -> 0 | HS50: 0 | IK50: 0
A51: 18 | B51: 1 | C51: 77 | E51: 2,1 | F51: 1.12-1-53 | G51: Узел трубопровода из стальных водогазопроводных оцинкованных труб, с гильзами, для водоснабжения, диаметр условного прохода 20 мм | H51: м | I51: =I49*J51 -> 110 | J51: 100 | K51: 100 | O51: =ROUND(CP51,2) -> 63953.9 | P51: =ROUND((ROUND((AC51*AW51*I51),2)*BC51),2) -> 63953.9 | Q51: =(ROUND((ROUND(((ET51)*AV51*I51),2)*BB51),2)+ROUND((ROUND(((AE51-(EU51))*AV51*I51),2)*BS51),2)) -> 0 | R51: =ROUND((ROUND((AE51*AV51*I51),2)*BS51),2) -> 0 | S51: =ROUND((ROUND((AF51*AV51*I51),2)*BA51),2) -> 0 | T51: =ROUND(CU51*I51,2) -> 0 | U51: =CV51*I51 -> 0 | V51: =CW51*I51 -> 0 | W51: =ROUND(CX51*I51,2) -> 0 | X51: =ROUND(CY51,2) -> 0 | Y51: =ROUND(CZ51,2) -> 0 | AA51: 59204059 | AB51: =ROUND((AC51+AD51+AF51),6) -> 31.41 | AC51: =ROUND((ES51),6) -> 31.41 | AD51: =ROUND((((ET51)-(EU51))+AE51),6) -> 0 | AE51: =ROUND((EU51),6) -> 0 | AF51: =ROUND((EV51),6) -> 0 | AG51: =ROUND((AP51),6) -> 0 | AH51: =(EW51) -> 0 | AI51: =(EX51) -> 0 | AJ51: =(AS51) -> 0 | AK51: 31.41 | AL51: 31.41 | AM51: 0 | AN51: 0 | AO51: 0 | AP51: 0 | AQ51: 0 | AR51: 0 | AS51: 0 | AT51: 109 | AU51: 61 | AV51: 1 | AW51: 1 | AZ51: 1 | BA51: 1 | BB51: 1 | BC51: 18.51 | BH51: 3 | BI51: 1 | BJ51: ТСН-2001.1 Доп. 79, Р. 12, о. 1, поз. 53 | BM51: 21 | BN51: 0 | BO51: 1.12-1-53 | BP51: 1 | BQ51: 30 | BR51: 0 | BS51: 1 | BT51: 1 | BU51: 1 | BV51: 1 | BW51: 1 | BX51: 1 | BZ51: 109 | CA51: 61 | CE51: 30 | CF51: 0 | CG51: 0 | CM51: 0 | CO51: 0 | CP51: =(P51+Q51+S51) -> 63953.9 | CQ51: =ROUND((ROUND((AC51*AW51*1),2)*BC51),2) -> 581.4 | CR51: =(ROUND((ROUND(((ET51)*AV51*1),2)*BB51),2)+ROUND((ROUND(((AE51-(EU51))*AV51*1),2)*BS51),2)) -> 0 | CS51: =ROUND((ROUND((AE51*AV51*1),2)*BS51),2) -> 0 | CT51: =ROUND((ROUND((AF51*AV51*1),2)*BA51),2) -> 0 | CU51: =AG51 -> 0 | CV51: =(AH51*AV51) -> 0 | CW51: =AI51 -> 0 | CX51: =AJ51 -> 0 | CY51: =(((S51+R51)*AT51)/100) -> 0 | CZ51: =(((S51+R51)*AU51)/100) -> 0 | DN51: 0 | DO51: 0 | DP51: 1 | DQ51: 1 | DU51: 1003 | DV51: м | DW51: м | DX51: 1 | EE51: 58807897 | EF51: 30 | EG51: Строительные работы | EH51: 0 | EJ51: 1 | EK51: 21 | EL51: ТСН-2001.3-16. Трубопроводы внутренние | EM51: ТСН-2001.3-16-1 | EQ51: 0 | ER51: 31.41 | ES51: 31.41 | ET51: 0 | EU51: 0 | EV51: 0 | EW51: 0 | EX51: 0 | FQ51: 0 | FR51: 0 | FS51: 0 | FX51: 109 | FY51: 61 | GD51: 1 | GF51: -1171880344 | GG51: 2 | GH51: 1 | GI51: 2 | GJ51: 0 | GK51: 0 | GL51: =ROUND(IF(AND(BH51=3,BI51=3,FS51<>0),P51,0),2) -> 0 | GM51: =ROUND(O51+X51+Y51,2)+GX51 -> 63953.9 | GN51: =IF(OR(BI51=0,BI51=1),GM51-GX51,0) -> 63953.9 | GO51: =IF(BI51=2,GM51-GX51,0) -> 0 | GP51: =IF(BI51=4,GM51-GX51,0) -> 0 | GR51: 0 | GS51: 3 | GT51: 0 | GV51: =ROUND((GT51),6) -> 0 | GW51: 1 | GX51: =ROUND(HC51*I51,2) -> 0 | HA51: 0 | HB51: 0 | HC51: =GV51*GW51 -> 0 | HS51: 0 | IK51: 0
A52: 18 | B52: 1 | C52: 67 | E52: 2,2 | F52: 1.13-4-62 | G52: Кран шаровой, латунный, никелированный, полнопроходной, с алюминиевой рукояткой, муфтовый, температура рабочей среды от -15 до +110°С, номинальное давление PN 4,0 МПа, номинальный диаметр DN 20 мм | H52: шт. | I52: =I48*J52 -> 24 | J52: 21.818182 | K52: 21.818182 | O52: =ROUND(CP52,2) -> 1133.76 | P52: =ROUND((ROUND((AC52*AW52*I52),2)*BC52),2) -> 1133.76 | Q52: =(ROUND((ROUND(((ET52)*AV52*I52),2)*BB52),2)+ROUND((ROUND(((AE52-(EU52))*AV52*I52),2)*BS52),2)) -> 0 | R52: =ROUND((ROUND((AE52*AV52*I52),2)*BS52),2) -> 0 | S52: =ROUND((ROUND((AF52*AV52*I52),2)*BA52),2) -> 0 | T52: =ROUND(CU52*I52,2) -> 0 | U52: =CV52*I52 -> 0 | V52: =CW52*I52 -> 0 | W52: =ROUND(CX52*I52,2) -> 0 | X52: =ROUND(CY52,2) -> 0 | Y52: =ROUND(CZ52,2) -> 0 | AA52: 59204062 | AB52: =ROUND((AC52+AD52+AF52),6) -> 47.24 | AC52: =ROUND((ES52),6) -> 47.24 | AD52: =ROUND((((ET52)-(EU52))+AE52),6) -> 0 | AE52: =ROUND((EU52),6) -> 0 | AF52: =ROUND((EV52),6) -> 0 | AG52: =ROUND((AP52),6) -> 0 | AH52: =(EW52) -> 0 | AI52: =(EX52) -> 0 | AJ52: =(AS52) -> 0 | AK52: 47.24 | AL52: 47.24 | AM52: 0 | AN52: 0 | AO52: 0 | AP52: 0 | AQ52: 0 | AR52: 0 | AS52: 0 | AT52: 109 | AU52: 61 | AV52: 1 | AW52: 1 | AZ52: 1 | BA52: 1 | BB52: 1 | BC52: 1 | BH52: 3 | BI52: 1 | BJ52: ТСН-2001.1 Доп. 73, Р. 13, о. 4, поз. 62 | BM52: 21 | BN52: 0 | BP52: 0 | BQ52: 30 | BR52: 0 | BS52: 1 | BT52: 1 | BU52: 1 | BV52: 1 | BW52: 1 | BX52: 1 | BZ52: 109 | CA52: 61 | CE52: 30 | CF52: 0 | CG52: 0 | CM52: 0 | CO52: 0 | CP52: =(P52+Q52+S52) -> 1133.76 | CQ52: =ROUND((ROUND((AC52*AW52*1),2)*BC52),2) -> 47.24 | CR52: =(ROUND((ROUND(((ET52)*AV52*1),2)*BB52),2)+ROUND((ROUND(((AE52-(EU52))*AV52*1),2)*BS52),2)) -> 0 | CS52: =ROUND((ROUND((AE52*AV52*1),2)*BS52),2) -> 0 | CT52: =ROUND((ROUND((AF52*AV52*1),2)*BA52),2) -> 0 | CU52: =AG52 -> 0 | CV52: =(AH52*AV52) -> 0 | CW52: =AI52 -> 0 | CX52: =AJ52 -> 0 | CY52: =(((S52+R52)*AT52)/100) -> 0 | CZ52: =(((S52+R52)*AU52)/100) -> 0 | DN52: 0 | DO52: 0 | DP52: 1 | DQ52: 1 | DU52: 1010 | DV52: шт. | DW52: шт. | DX52: 1 | EE52: 58807897 | EF52: 30 | EG52: Строительные работы | EH52: 0 | EJ52: 1 | EK52: 21 | EL52: ТСН-2001.3-16. Трубопроводы внутренние | EM52: ТСН-2001.3-16-1 | EQ52: 0 | ER52: 47.24 | ES52: 47.24 | ET52: 0 | EU52: 0 | EV52: 0 | EW52: 0 | EX52: 0 | FQ52: 0 | FR52: 0 | FS52: 0 | FX52: 109 | FY52: 61 | GD52: 1 | GF52: -146904554 | GG52: 2 | GH52: 1 | GI52: -2 | GJ52: 0 | GK52: 0 | GL52: =ROUND(IF(AND(BH52=3,BI52=3,FS52<>0),P52,0),2) -> 0 | GM52: =ROUND(O52+X52+Y52,2)+GX52 -> 1133.76 | GN52: =IF(OR(BI52=0,BI52=1),GM52-GX52,0) -> 1133.76 | GO52: =IF(BI52=2,GM52-GX52,0) -> 0 | GP52: =IF(BI52=4,GM52-GX52,0) -> 0 | GR52: 0 | GS52: 3 | GT52: 0 | GV52: =ROUND((GT52),6) -> 0 | GW52: 1 | GX52: =ROUND(HC52*I52,2) -> 0 | HA52: 0 | HB52: 0 | HC52: =GV52*GW52 -> 0 | HS52: 0 | IK52: 0
A53: 18 | B53: 1 | C53: 78 | E53: 2,2 | F53: 1.13-4-62 | G53: Кран шаровой, латунный, никелированный, полнопроходной, с алюминиевой рукояткой, муфтовый, температура рабочей среды от -15 до +110°С, номинальное давление PN 4,0 МПа, номинальный диаметр DN 20 мм | H53: шт. | I53: =I49*J53 -> 24 | J53: 21.818182 | K53: 21.818182 | O53: =ROUND(CP53,2) -> 23468.83 | P53: =ROUND((ROUND((AC53*AW53*I53),2)*BC53),2) -> 23468.83 | Q53: =(ROUND((ROUND(((ET53)*AV53*I53),2)*BB53),2)+ROUND((ROUND(((AE53-(EU53))*AV53*I53),2)*BS53),2)) -> 0 | R53: =ROUND((ROUND((AE53*AV53*I53),2)*BS53),2) -> 0 | S53: =ROUND((ROUND((AF53*AV53*I53),2)*BA53),2) -> 0 | T53: =ROUND(CU53*I53,2) -> 0 | U53: =CV53*I53 -> 0 | V53: =CW53*I53 -> 0 | W53: =ROUND(CX53*I53,2) -> 0 | X53: =ROUND(CY53,2) -> 0 | Y53: =ROUND(CZ53,2) -> 0 | AA53: 59204059 | AB53: =ROUND((AC53+AD53+AF53),6) -> 47.24 | AC53: =ROUND((ES53),6) -> 47.24 | AD53: =ROUND((((ET53)-(EU53))+AE53),6) -> 0 | AE53: =ROUND((EU53),6) -> 0 | AF53: =ROUND((EV53),6) -> 0 | AG53: =ROUND((AP53),6) -> 0 | AH53: =(EW53) -> 0 | AI53: =(EX53) -> 0 | AJ53: =(AS53) -> 0 | AK53: 47.24 | AL53: 47.24 | AM53: 0 | AN53: 0 | AO53: 0 | AP53: 0 | AQ53: 0 | AR53: 0 | AS53: 0 | AT53: 109 | AU53: 61 | AV53: 1 | AW53: 1 | AZ53: 1 | BA53: 1 | BB53: 1 | BC53: 20.7 | BH53: 3 | BI53: 1 | BJ53: ТСН-2001.1 Доп. 73, Р. 13, о. 4, поз. 62 | BM53: 21 | BN53: 0 | BO53: 1.13-4-62 | BP53: 1 | BQ53: 30 | BR53: 0 | BS53: 1 | BT53: 1 | BU53: 1 | BV53: 1 | BW53: 1 | BX53: 1 | BZ53: 109 | CA53: 61 | CE53: 30 | CF53: 0 | CG53: 0 | CM53: 0 | CO53: 0 | CP53: =(P53+Q53+S53) -> 23468.83 | CQ53: =ROUND((ROUND((AC53*AW53*1),2)*BC53),2) -> 977.87 | CR53: =(ROUND((ROUND(((ET53)*AV53*1),2)*BB53),2)+ROUND((ROUND(((AE53-(EU53))*AV53*1),2)*BS53),2)) -> 0 | CS53: =ROUND((ROUND((AE53*AV53*1),2)*BS53),2) -> 0 | CT53: =ROUND((ROUND((AF53*AV53*1),2)*BA53),2) -> 0 | CU53: =AG53 -> 0 | CV53: =(AH53*AV53) -> 0 | CW53: =AI53 -> 0 | CX53: =AJ53 -> 0 | CY53: =(((S53+R53)*AT53)/100) -> 0 | CZ53: =(((S53+R53)*AU53)/100) -> 0 | DN53: 0 | DO53: 0 | DP53: 1 | DQ53: 1 | DU53: 1010 | DV53: шт. | DW53: шт. | DX53: 1 | EE53: 58807897 | EF53: 30 | EG53: Строительные работы | EH53: 0 | EJ53: 1 | EK53: 21 | EL53: ТСН-2001.3-16. Трубопроводы внутренние | EM53: ТСН-2001.3-16-1 | EQ53: 0 | ER53: 47.24 | ES53: 47.24 | ET53: 0 | EU53: 0 | EV53: 0 | EW53: 0 | EX53: 0 | FQ53: 0 | FR53: 0 | FS53: 0 | FX53: 109 | FY53: 61 | GD53: 1 | GF53: -146904554 | GG53: 2 | GH53: 1 | GI53: 2 | GJ53: 0 | GK53: 0 | GL53: =ROUND(IF(AND(BH53=3,BI53=3,FS53<>0),P53,0),2) -> 0 | GM53: =ROUND(O53+X53+Y53,2)+GX53 -> 23468.83 | GN53: =IF(OR(BI53=0,BI53=1),GM53-GX53,0) -> 23468.83 | GO53: =IF(BI53=2,GM53-GX53,0) -> 0 | GP53: =IF(BI53=4,GM53-GX53,0) -> 0 | GR53: 0 | GS53: 3 | GT53: 0 | GV53: =ROUND((GT53),6) -> 0 | GW53: 1 | GX53: =ROUND(HC53*I53,2) -> 0 | HA53: 0 | HB53: 0 | HC53: =GV53*GW53 -> 0 | HS53: 0 | IK53: 0
A54: 18 | B54: 1 | C54: 65 | E54: 2,3 | F54: 1.12-10-146 | G54: Хомут стальной, оцинкованный, двухболтовой, с поворотным механизмом, каучуковой прокладкой, для крепления труб диаметром от 16 до 20 мм, резьба М8/М10 | H54: 100 шт. | I54: =I48*J54 -> 0.55 | J54: 0.5 | K54: 0.5 | O54: =ROUND(CP54,2) -> 289.42 | P54: =ROUND((ROUND((AC54*AW54*I54),2)*BC54),2) -> 289.42 | Q54: =(ROUND((ROUND(((ET54)*AV54*I54),2)*BB54),2)+ROUND((ROUND(((AE54-(EU54))*AV54*I54),2)*BS54),2)) -> 0 | R54: =ROUND((ROUND((AE54*AV54*I54),2)*BS54),2) -> 0 | S54: =ROUND((ROUND((AF54*AV54*I54),2)*BA54),2) -> 0 | T54: =ROUND(CU54*I54,2) -> 0 | U54: =CV54*I54 -> 0 | V54: =CW54*I54 -> 0 | W54: =ROUND(CX54*I54,2) -> 0 | X54: =ROUND(CY54,2) -> 0 | Y54: =ROUND(CZ54,2) -> 0 | AA54: 59204062 | AB54: =ROUND((AC54+AD54+AF54),6) -> 526.22 | AC54: =ROUND((ES54),6) -> 526.22 | AD54: =ROUND((((ET54)-(EU54))+AE54),6) -> 0 | AE54: =ROUND((EU54),6) -> 0 | AF54: =ROUND((EV54),6) -> 0 | AG54: =ROUND((AP54),6) -> 0 | AH54: =(EW54) -> 0 | AI54: =(EX54) -> 0 | AJ54: =(AS54) -> 0 | AK54: 526.22 | AL54: 526.22 | AM54: 0 | AN54: 0 | AO54: 0 | AP54: 0 | AQ54: 0 | AR54: 0 | AS54: 0 | AT54: 109 | AU54: 61 | AV54: 1 | AW54: 1 | AZ54: 1 | BA54: 1 | BB54: 1 | BC54: 1 | BH54: 3 | BI54: 1 | BJ54: ТСН-2001.1 Доп. 79, Р. 12, о. 10, поз. 146 | BM54: 21 | BN54: 0 | BP54: 0 | BQ54: 30 | BR54: 0 | BS54: 1 | BT54: 1 | BU54: 1 | BV54: 1 | BW54: 1 | BX54: 1 | BZ54: 109 | CA54: 61 | CE54: 30 | CF54: 0 | CG54: 0 | CM54: 0 | CO54: 0 | CP54: =(P54+Q54+S54) -> 289.42 | CQ54: =ROUND((ROUND((AC54*AW54*1),2)*BC54),2) -> 526.22 | CR54: =(ROUND((ROUND(((ET54)*AV54*1),2)*BB54),2)+ROUND((ROUND(((AE54-(EU54))*AV54*1),2)*BS54),2)) -> 0 | CS54: =ROUND((ROUND((AE54*AV54*1),2)*BS54),2) -> 0 | CT54: =ROUND((ROUND((AF54*AV54*1),2)*BA54),2) -> 0 | CU54: =AG54 -> 0 | CV54: =(AH54*AV54) -> 0 | CW54: =AI54 -> 0 | CX54: =AJ54 -> 0 | CY54: =(((S54+R54)*AT54)/100) -> 0 | CZ54: =(((S54+R54)*AU54)/100) -> 0 | DN54: 0 | DO54: 0 | DP54: 1 | DQ54: 1 | DU54: 1010 | DV54: 100 шт. | DW54: 100 шт. | DX54: 100 | EE54: 58807897 | EF54: 30 | EG54: Строительные работы | EH54: 0 | EJ54: 1 | EK54: 21 | EL54: ТСН-2001.3-16. Трубопроводы внутренние | EM54: ТСН-2001.3-16-1 | EQ54: 0 | ER54: 526.22 | ES54: 526.22 | ET54: 0 | EU54: 0 | EV54: 0 | EW54: 0 | EX54: 0 | FQ54: 0 | FR54: 0 | FS54: 0 | FX54: 109 | FY54: 61 | GD54: 1 | GF54: 1873919888 | GG54: 2 | GH54: 1 | GI54: -2 | GJ54: 0 | GK54: 0 | GL54: =ROUND(IF(AND(BH54=3,BI54=3,FS54<>0),P54,0),2) -> 0 | GM54: =ROUND(O54+X54+Y54,2)+GX54 -> 289.42 | GN54: =IF(OR(BI54=0,BI54=1),GM54-GX54,0) -> 289.42 | GO54: =IF(BI54=2,GM54-GX54,0) -> 0 | GP54: =IF(BI54=4,GM54-GX54,0) -> 0 | GR54: 0 | GS54: 3 | GT54: 0 | GV54: =ROUND((GT54),6) -> 0 | GW54: 1 | GX54: =ROUND(HC54*I54,2) -> 0 | HA54: 0 | HB54: 0 | HC54: =GV54*GW54 -> 0 | HS54: 0 | IK54: 0
A55: 18 | B55: 1 | C55: 76 | E55: 2,3 | F55: 1.12-10-146 | G55: Хомут стальной, оцинкованный, двухболтовой, с поворотным механизмом, каучуковой прокладкой, для крепления труб диаметром от 16 до 20 мм, резьба М8/М10 | H55: 100 шт. | I55: =I49*J55 -> 0.55 | J55: 0.5 | K55: 0.5 | O55: =ROUND(CP55,2) -> 807.48 | P55: =ROUND((ROUND((AC55*AW55*I55),2)*BC55),2) -> 807.48 | Q55: =(ROUND((ROUND(((ET55)*AV55*I55),2)*BB55),2)+ROUND((ROUND(((AE55-(EU55))*AV55*I55),2)*BS55),2)) -> 0 | R55: =ROUND((ROUND((AE55*AV55*I55),2)*BS55),2) -> 0 | S55: =ROUND((ROUND((AF55*AV55*I55),2)*BA55),2) -> 0 | T55: =ROUND(CU55*I55,2) -> 0 | U55: =CV55*I55 -> 0 | V55: =CW55*I55 -> 0 | W55: =ROUND(CX55*I55,2) -> 0 | X55: =ROUND(CY55,2) -> 0 | Y55: =ROUND(CZ55,2) -> 0 | AA55: 59204059 | AB55: =ROUND((AC55+AD55+AF55),6) -> 526.22 | AC55: =ROUND((ES55),6) -> 526.22 | AD55: =ROUND((((ET55)-(EU55))+AE55),6) -> 0 | AE55: =ROUND((EU55),6) -> 0 | AF55: =ROUND((EV55),6) -> 0 | AG55: =ROUND((AP55),6) -> 0 | AH55: =(EW55) -> 0 | AI55: =(EX55) -> 0 | AJ55: =(AS55) -> 0 | AK55: 526.22 | AL55: 526.22 | AM55: 0 | AN55: 0 | AO55: 0 | AP55: 0 | AQ55: 0 | AR55: 0 | AS55: 0 | AT55: 109 | AU55: 61 | AV55: 1 | AW55: 1 | AZ55: 1 | BA55: 1 | BB55: 1 | BC55: 2.79 | BH55: 3 | BI55: 1 | BJ55: ТСН-2001.1 Доп. 79, Р. 12, о. 10, поз. 146 | BM55: 21 | BN55: 0 | BO55: 1.12-10-146 | BP55: 1 | BQ55: 30 | BR55: 0 | BS55: 1 | BT55: 1 | BU55: 1 | BV55: 1 | BW55: 1 | BX55: 1 | BZ55: 109 | CA55: 61 | CE55: 30 | CF55: 0 | CG55: 0 | CM55: 0 | CO55: 0 | CP55: =(P55+Q55+S55) -> 807.48 | CQ55: =ROUND((ROUND((AC55*AW55*1),2)*BC55),2) -> 1468.15 | CR55: =(ROUND((ROUND(((ET55)*AV55*1),2)*BB55),2)+ROUND((ROUND(((AE55-(EU55))*AV55*1),2)*BS55),2)) -> 0 | CS55: =ROUND((ROUND((AE55*AV55*1),2)*BS55),2) -> 0 | CT55: =ROUND((ROUND((AF55*AV55*1),2)*BA55),2) -> 0 | CU55: =AG55 -> 0 | CV55: =(AH55*AV55) -> 0 | CW55: =AI55 -> 0 | CX55: =AJ55 -> 0 | CY55: =(((S55+R55)*AT55)/100) -> 0 | CZ55: =(((S55+R55)*AU55)/100) -> 0 | DN55: 0 | DO55: 0 | DP55: 1 | DQ55: 1 | DU55: 1010 | DV55: 100 шт. | DW55: 100 шт. | DX55: 100 | EE55: 58807897 | EF55: 30 | EG55: Строительные работы | EH55: 0 | EJ55: 1 | EK55: 21 | EL55: ТСН-2001.3-16. Трубопроводы внутренние | EM55: ТСН-2001.3-16-1 | EQ55: 0 | ER55: 526.22 | ES55: 526.22 | ET55: 0 | EU55: 0 | EV55: 0 | EW55: 0 | EX55: 0 | FQ55: 0 | FR55: 0 | FS55: 0 | FX55: 109 | FY55: 61 | GD55: 1 | GF55: 1873919888 | GG55: 2 | GH55: 1 | GI55: 2 | GJ55: 0 | GK55: 0 | GL55: =ROUND(IF(AND(BH55=3,BI55=3,FS55<>0),P55,0),2) -> 0 | GM55: =ROUND(O55+X55+Y55,2)+GX55 -> 807.48 | GN55: =IF(OR(BI55=0,BI55=1),GM55-GX55,0) -> 807.48 | GO55: =IF(BI55=2,GM55-GX55,0) -> 0 | GP55: =IF(BI55=4,GM55-GX55,0) -> 0 | GR55: 0 | GS55: 3 | GT55: 0 | GV55: =ROUND((GT55),6) -> 0 | GW55: 1 | GX55: =ROUND(HC55*I55,2) -> 0 | HA55: 0 | HB55: 0 | HC55: =GV55*GW55 -> 0 | HS55: 0 | IK55: 0
A56: 17 | B56: 1 | C56: =ROW(SmtRes!A93) -> 93 | D56: =ROW(EtalonRes!A89) -> 89 | F56: 3.16-7-2 | G56: Прокладка трубопроводов водоснабжения из стальных водогазопроводных оцинкованных труб диаметром 20 мм | H56: 100 м трубопровода | I56: =ROUND(ROUND(110/100,4)*0,9) -> 0 | J56: 0 | K56: =ROUND(ROUND(110/100,4)*0,9) -> 0 | O56: =ROUND(CP56,2) -> 0 | P56: =ROUND((ROUND((AC56*AW56*I56),2)*BC56),2) -> 0 | Q56: =(ROUND((ROUND(((((ET56*1.25)*1.1))*AV56*I56),2)*BB56),2)+ROUND((ROUND(((AE56-(((EU56*1.25)*1.1)))*AV56*I56),2)*BS56),2)) -> 0 | R56: =ROUND((ROUND((AE56*AV56*I56),2)*BS56),2) -> 0 | S56: =ROUND((ROUND((AF56*AV56*I56),2)*BA56),2) -> 0 | T56: =ROUND(CU56*I56,2) -> 0 | U56: =CV56*I56 -> 0 | V56: =CW56*I56 -> 0 | W56: =ROUND(CX56*I56,2) -> 0 | X56: =ROUND(CY56,2) -> 0 | Y56: =ROUND(CZ56,2) -> 0 | AA56: -1 | AB56: =ROUND((AC56+AD56+AF56),6) -> 648.4356 | AC56: =ROUND((ES56),6) -> 44.76 | AD56: =ROUND((((((ET56*1.25)*1.1))-(((EU56*1.25)*1.1)))+AE56),6) -> 65.68375 | AE56: =ROUND((((EU56*1.25)*1.1)),6) -> 8.3325 | AF56: =ROUND((((EV56*1.15)*1.1)),6) -> 537.99185 | AG56: =ROUND((AP56),6) -> 0 | AH56: =(((EW56*1.15)*1.1)) -> 42.6305 | AI56: =(((EX56*1.25)*1.1)) -> 0 | AJ56: =(AS56) -> 0 | AK56: 517.82 | AL56: 44.76 | AM56: 47.77 | AN56: 6.06 | AO56: 425.29 | AP56: 0 | AQ56: 33.7 | AR56: 0 | AS56: 0 | AT56: 109 | AU56: 61 | AV56: 1.067 | AW56: 1 | AZ56: 1 | BA56: 1 | BB56: 1 | BC56: 1 | BH56: 0 | BI56: 1 | BJ56: ТСН-2001.3 Доп. 79, Сб. 16, т. 7, поз. 2 | BM56: 21 | BN56: 0 | BO56: 3.16-7-2 | BP56: 1 | BQ56: 30 | BR56: 0 | BS56: 1 | BT56: 1 | BU56: 1 | BV56: 1 | BW56: 1 | BX56: 1 | BZ56: 109 | CA56: 61 | CE56: 30 | CF56: 0 | CG56: 0 | CM56: 0 | CN56: Поправка: О.П. п.3.4. 6 Наименование: Выполняемые при ремонте и реконструкции работы аналогичные технологическим процессам, характерным для нового строительства и отсутствующим в сборниках на ремонтно-строительные работы Поправка: О.П. п.3.4.30.в Наименование: При применении территориальных сметных нормативов для города Москвы затраты, учитывающие напряженные и стесненные условия производства работ (стесненность, сложность складирования и транспортной логистики и т.п.), исчисляются с применением коэффициентов к затратам труда и заработной плате рабочих, машинистов, времени эксплуатации машин и механизмов, стоимости эксплуатации машин в размере: для объектов, расположенных за пределами Третьего транспортного кольца города Москвы, но в пределах Московской кольцевой автомобильной дороги | CO56: 0 | CP56: =(P56+Q56+S56) -> 0 | CQ56: =ROUND((ROUND((AC56*AW56*1),2)*BC56),2) -> 44.76 | CR56: =(ROUND((ROUND(((((ET56*1.25)*1.1))*AV56*1),2)*BB56),2)+ROUND((ROUND(((AE56-(((EU56*1.25)*1.1)))*AV56*1),2)*BS56),2)) -> 70.08 | CS56: =ROUND((ROUND((AE56*AV56*1),2)*BS56),2) -> 8.89 | CT56: =ROUND((ROUND((AF56*AV56*1),2)*BA56),2) -> 574.04 | CU56: =AG56 -> 0 | CV56: =(AH56*AV56) -> 45.486744 | CW56: =AI56 -> 0 | CX56: =AJ56 -> 0 | CY56: =(((S56+R56)*AT56)/100) -> 0 | CZ56: =(((S56+R56)*AU56)/100) -> 0 | DB56: 13 | DE56: *1,25)*1,1 | DF56: *1,25)*1,1 | DG56: *1,15)*1,1 | DI56: *1,15)*1,1 | DJ56: *1,25)*1,1 | DN56: 0 | DO56: 0 | DP56: 1 | DQ56: 1 | DU56: 1013 | DV56: 100 м трубопровода | DW56: 100 м трубопровода | DX56: 1 | EE56: 58807897 | EF56: 30 | EG56: Строительные работы | EH56: 0 | EJ56: 1 | EK56: 21 | EL56: ТСН-2001.3-16. Трубопроводы внутренние | EM56: ТСН-2001.3-16-1 | EO56: Поправка: О.П. п.3.4. 6 Поправка: О.П. п.3.4.30.в | EQ56: 1024 | ER56: 517.82 | ES56: 44.76 | ET56: 47.77 | EU56: 6.06 | EV56: 425.29 | EW56: 33.7 | EX56: 0 | EY56: 0 | FQ56: 0 | FR56: 0 | FS56: 0 | FX56: 109 | FY56: 61 | GD56: 1 | GF56: -1092919114 | GG56: 2 | GH56: 1 | GI56: 2 | GJ56: 0 | GK56: 0 | GL56: =ROUND(IF(AND(BH56=3,BI56=3,FS56<>0),P56,0),2) -> 0 | GM56: =ROUND(O56+X56+Y56,2)+GX56 -> 0 | GN56: =IF(OR(BI56=0,BI56=1),GM56-GX56,0) -> 0 | GO56: =IF(BI56=2,GM56-GX56,0) -> 0 | GP56: =IF(BI56=4,GM56-GX56,0) -> 0 | GR56: 0 | GS56: 3 | GT56: 0 | GV56: =ROUND((GT56),6) -> 0 | GW56: 1 | GX56: =ROUND(HC56*I56,2) -> 0 | HA56: 0 | HB56: 0 | HC56: =GV56*GW56 -> 0 | HS56: 0 | IK56: 0
A57: 17 | B57: 1 | C57: =ROW(SmtRes!A108) -> 108 | D57: =ROW(EtalonRes!A104) -> 104 | F57: 3.16-7-2 | G57: Прокладка трубопроводов водоснабжения из стальных водогазопроводных оцинкованных труб диаметром 20 мм | H57: 100 м трубопровода | I57: =ROUND(ROUND(110/100,4)*0,9) -> 0 | J57: 0 | K57: =ROUND(ROUND(110/100,4)*0,9) -> 0 | O57: =ROUND(CP57,2) -> 0 | P57: =ROUND((ROUND((AC57*AW57*I57),2)*BC57),2) -> 0 | Q57: =(ROUND((ROUND(((((ET57*1.25)*1.1))*AV57*I57),2)*BB57),2)+ROUND((ROUND(((AE57-(((EU57*1.25)*1.1)))*AV57*I57),2)*BS57),2)) -> 0 | R57: =ROUND((ROUND((AE57*AV57*I57),2)*BS57),2) -> 0 | S57: =ROUND((ROUND((AF57*AV57*I57),2)*BA57),2) -> 0 | T57: =ROUND(CU57*I57,2) -> 0 | U57: =CV57*I57 -> 0 | V57: =CW57*I57 -> 0 | W57: =ROUND(CX57*I57,2) -> 0 | X57: =ROUND(CY57,2) -> 0 | Y57: =ROUND(CZ57,2) -> 0 | AA57: -1 | AB57: =ROUND((AC57+AD57+AF57),6) -> 648.4356 | AC57: =ROUND((ES57),6) -> 44.76 | AD57: =ROUND((((((ET57*1.25)*1.1))-(((EU57*1.25)*1.1)))+AE57),6) -> 65.68375 | AE57: =ROUND((((EU57*1.25)*1.1)),6) -> 8.3325 | AF57: =ROUND((((EV57*1.15)*1.1)),6) -> 537.99185 | AG57: =ROUND((AP57),6) -> 0 | AH57: =(((EW57*1.15)*1.1)) -> 42.6305 | AI57: =(((EX57*1.25)*1.1)) -> 0 | AJ57: =(AS57) -> 0 | AK57: 517.82 | AL57: 44.76 | AM57: 47.77 | AN57: 6.06 | AO57: 425.29 | AP57: 0 | AQ57: 33.7 | AR57: 0 | AS57: 0 | AT57: 109 | AU57: 61 | AV57: 1.067 | AW57: 1 | AZ57: 1 | BA57: 54.99 | BB57: 15.37 | BC57: 6.16 | BH57: 0 | BI57: 1 | BJ57: ТСН-2001.3 Доп. 79, Сб. 16, т. 7, поз. 2 | BM57: 21 | BN57: 0 | BO57: 3.16-7-2 | BP57: 1 | BQ57: 30 | BR57: 0 | BS57: 54.99 | BT57: 1 | BU57: 1 | BV57: 1 | BW57: 1 | BX57: 1 | BZ57: 109 | CA57: 61 | CE57: 30 | CF57: 0 | CG57: 0 | CM57: 0 | CN57: Поправка: О.П. п.3.4. 6 Наименование: Выполняемые при ремонте и реконструкции работы аналогичные технологическим процессам, характерным для нового строительства и отсутствующим в сборниках на ремонтно-строительные работы Поправка: О.П. п.3.4.30.в Наименование: При применении территориальных сметных нормативов для города Москвы затраты, учитывающие напряженные и стесненные условия производства работ (стесненность, сложность складирования и транспортной логистики и т.п.), исчисляются с применением коэффициентов к затратам труда и заработной плате рабочих, машинистов, времени эксплуатации машин и механизмов, стоимости эксплуатации машин в размере: для объектов, расположенных за пределами Третьего транспортного кольца города Москвы, но в пределах Московской кольцевой автомобильной дороги | CO57: 0 | CP57: =(P57+Q57+S57) -> 0 | CQ57: =ROUND((ROUND((AC57*AW57*1),2)*BC57),2) -> 275.72 | CR57: =(ROUND((ROUND(((((ET57*1.25)*1.1))*AV57*1),2)*BB57),2)+ROUND((ROUND(((AE57-(((EU57*1.25)*1.1)))*AV57*1),2)*BS57),2)) -> 1077.13 | CS57: =ROUND((ROUND((AE57*AV57*1),2)*BS57),2) -> 488.86 | CT57: =ROUND((ROUND((AF57*AV57*1),2)*BA57),2) -> 31566.46 | CU57: =AG57 -> 0 | CV57: =(AH57*AV57) -> 45.486744 | CW57: =AI57 -> 0 | CX57: =AJ57 -> 0 | CY57: =(((S57+R57)*AT57)/100) -> 0 | CZ57: =(((S57+R57)*AU57)/100) -> 0 | DB57: 15 | DE57: *1,25)*1,1 | DF57: *1,25)*1,1 | DG57: *1,15)*1,1 | DI57: *1,15)*1,1 | DJ57: *1,25)*1,1 | DN57: 0 | DO57: 0 | DP57: 1 | DQ57: 1 | DU57: 1013 | DV57: 100 м трубопровода | DW57: 100 м трубопровода | DX57: 1 | EE57: 58807897 | EF57: 30 | EG57: Строительные работы | EH57: 0 | EJ57: 1 | EK57: 21 | EL57: ТСН-2001.3-16. Трубопроводы внутренние | EM57: ТСН-2001.3-16-1 | EO57: Поправка: О.П. п.3.4. 6 Поправка: О.П. п.3.4.30.в | EQ57: 1024 | ER57: 517.82 | ES57: 44.76 | ET57: 47.77 | EU57: 6.06 | EV57: 425.29 | EW57: 33.7 | EX57: 0 | EY57: 0 | FQ57: 0 | FR57: 0 | FS57: 0 | FX57: 109 | FY57: 61 | GD57: 1 | GF57: -1092919114 | GG57: 2 | GH57: 1 | GI57: 2 | GJ57: 0 | GK57: 0 | GL57: =ROUND(IF(AND(BH57=3,BI57=3,FS57<>0),P57,0),2) -> 0 | GM57: =ROUND(O57+X57+Y57,2)+GX57 -> 0 | GN57: =IF(OR(BI57=0,BI57=1),GM57-GX57,0) -> 0 | GO57: =IF(BI57=2,GM57-GX57,0) -> 0 | GP57: =IF(BI57=4,GM57-GX57,0) -> 0 | GR57: 0 | GS57: 3 | GT57: 0 | GV57: =ROUND((GT57),6) -> 0 | GW57: 1 | GX57: =ROUND(HC57*I57,2) -> 0 | HA57: 0 | HB57: 0 | HC57: =GV57*GW57 -> 0 | HS57: 0 | IK57: 0
A58: 18 | B58: 1 | C58: 91 | F58: 1.12-10-146 | G58: Хомут стальной, оцинкованный, двухболтовой, с поворотным механизмом, каучуковой прокладкой, для крепления труб диаметром от 16 до 20 мм, резьба М8/М10 | H58: 100 шт. | I58: =I56*J58 -> 0 | J58: 0.5 | K58: 0.5 | O58: =ROUND(CP58,2) -> 0 | P58: =ROUND((ROUND((AC58*AW58*I58),2)*BC58),2) -> 0 | Q58: =(ROUND((ROUND(((ET58)*AV58*I58),2)*BB58),2)+ROUND((ROUND(((AE58-(EU58))*AV58*I58),2)*BS58),2)) -> 0 | R58: =ROUND((ROUND((AE58*AV58*I58),2)*BS58),2) -> 0 | S58: =ROUND((ROUND((AF58*AV58*I58),2)*BA58),2) -> 0 | T58: =ROUND(CU58*I58,2) -> 0 | U58: =CV58*I58 -> 0 | V58: =CW58*I58 -> 0 | W58: =ROUND(CX58*I58,2) -> 0 | X58: =ROUND(CY58,2) -> 0 | Y58: =ROUND(CZ58,2) -> 0 | AA58: -1 | AB58: =ROUND((AC58+AD58+AF58),6) -> 526.22 | AC58: =ROUND((ES58),6) -> 526.22 | AD58: =ROUND((((ET58)-(EU58))+AE58),6) -> 0 | AE58: =ROUND((EU58),6) -> 0 | AF58: =ROUND((EV58),6) -> 0 | AG58: =ROUND((AP58),6) -> 0 | AH58: =(EW58) -> 0 | AI58: =(EX58) -> 0 | AJ58: =(AS58) -> 0 | AK58: 526.22 | AL58: 526.22 | AM58: 0 | AN58: 0 | AO58: 0 | AP58: 0 | AQ58: 0 | AR58: 0 | AS58: 0 | AT58: 109 | AU58: 61 | AV58: 1 | AW58: 1 | AZ58: 1 | BA58: 1 | BB58: 1 | BC58: 1 | BH58: 3 | BI58: 1 | BJ58: ТСН-2001.1 Доп. 79, Р. 12, о. 10, поз. 146 | BM58: 21 | BN58: 0 | BP58: 0 | BQ58: 30 | BR58: 0 | BS58: 1 | BT58: 1 | BU58: 1 | BV58: 1 | BW58: 1 | BX58: 1 | BZ58: 109 | CA58: 61 | CE58: 30 | CF58: 0 | CG58: 0 | CM58: 0 | CO58: 0 | CP58: =(P58+Q58+S58) -> 0 | CQ58: =ROUND((ROUND((AC58*AW58*1),2)*BC58),2) -> 526.22 | CR58: =(ROUND((ROUND(((ET58)*AV58*1),2)*BB58),2)+ROUND((ROUND(((AE58-(EU58))*AV58*1),2)*BS58),2)) -> 0 | CS58: =ROUND((ROUND((AE58*AV58*1),2)*BS58),2) -> 0 | CT58: =ROUND((ROUND((AF58*AV58*1),2)*BA58),2) -> 0 | CU58: =AG58 -> 0 | CV58: =(AH58*AV58) -> 0 | CW58: =AI58 -> 0 | CX58: =AJ58 -> 0 | CY58: =(((S58+R58)*AT58)/100) -> 0 | CZ58: =(((S58+R58)*AU58)/100) -> 0 | DN58: 0 | DO58: 0 | DP58: 1 | DQ58: 1 | DU58: 1010 | DV58: 100 шт. | DW58: 100 шт. | DX58: 100 | EE58: 58807897 | EF58: 30 | EG58: Строительные работы | EH58: 0 | EJ58: 1 | EK58: 21 | EL58: ТСН-2001.3-16. Трубопроводы внутренние | EM58: ТСН-2001.3-16-1 | EQ58: 1024 | ER58: 526.22 | ES58: 526.22 | ET58: 0 | EU58: 0 | EV58: 0 | EW58: 0 | EX58: 0 | FQ58: 0 | FR58: 0 | FS58: 0 | FX58: 109 | FY58: 61 | GD58: 1 | GF58: 1873919888 | GG58: 2 | GH58: 1 | GI58: -2 | GJ58: 0 | GK58: 0 | GL58: =ROUND(IF(AND(BH58=3,BI58=3,FS58<>0),P58,0),2) -> 0 | GM58: =ROUND(O58+X58+Y58,2)+GX58 -> 0 | GN58: =IF(OR(BI58=0,BI58=1),GM58-GX58,0) -> 0 | GO58: =IF(BI58=2,GM58-GX58,0) -> 0 | GP58: =IF(BI58=4,GM58-GX58,0) -> 0 | GR58: 0 | GS58: 3 | GT58: 0 | GV58: =ROUND((GT58),6) -> 0 | GW58: 1 | GX58: =ROUND(HC58*I58,2) -> 0 | HA58: 0 | HB58: 0 | HC58: =GV58*GW58 -> 0 | HS58: 0 | IK58: 0
A59: 18 | B59: 1 | C59: 106 | F59: 1.12-10-146 | G59: Хомут стальной, оцинкованный, двухболтовой, с поворотным механизмом, каучуковой прокладкой, для крепления труб диаметром от 16 до 20 мм, резьба М8/М10 | H59: 100 шт. | I59: =I57*J59 -> 0 | J59: 0.5 | K59: 0.5 | O59: =ROUND(CP59,2) -> 0 | P59: =ROUND((ROUND((AC59*AW59*I59),2)*BC59),2) -> 0 | Q59: =(ROUND((ROUND(((ET59)*AV59*I59),2)*BB59),2)+ROUND((ROUND(((AE59-(EU59))*AV59*I59),2)*BS59),2)) -> 0 | R59: =ROUND((ROUND((AE59*AV59*I59),2)*BS59),2) -> 0 | S59: =ROUND((ROUND((AF59*AV59*I59),2)*BA59),2) -> 0 | T59: =ROUND(CU59*I59,2) -> 0 | U59: =CV59*I59 -> 0 | V59: =CW59*I59 -> 0 | W59: =ROUND(CX59*I59,2) -> 0 | X59: =ROUND(CY59,2) -> 0 | Y59: =ROUND(CZ59,2) -> 0 | AA59: -1 | AB59: =ROUND((AC59+AD59+AF59),6) -> 526.22 | AC59: =ROUND((ES59),6) -> 526.22 | AD59: =ROUND((((ET59)-(EU59))+AE59),6) -> 0 | AE59: =ROUND((EU59),6) -> 0 | AF59: =ROUND((EV59),6) -> 0 | AG59: =ROUND((AP59),6) -> 0 | AH59: =(EW59) -> 0 | AI59: =(EX59) -> 0 | AJ59: =(AS59) -> 0 | AK59: 526.22 | AL59: 526.22 | AM59: 0 | AN59: 0 | AO59: 0 | AP59: 0 | AQ59: 0 | AR59: 0 | AS59: 0 | AT59: 109 | AU59: 61 | AV59: 1 | AW59: 1 | AZ59: 1 | BA59: 1 | BB59: 1 | BC59: 2.79 | BH59: 3 | BI59: 1 | BJ59: ТСН-2001.1 Доп. 79, Р. 12, о. 10, поз. 146 | BM59: 21 | BN59: 0 | BO59: 1.12-10-146 | BP59: 1 | BQ59: 30 | BR59: 0 | BS59: 1 | BT59: 1 | BU59: 1 | BV59: 1 | BW59: 1 | BX59: 1 | BZ59: 109 | CA59: 61 | CE59: 30 | CF59: 0 | CG59: 0 | CM59: 0 | CO59: 0 | CP59: =(P59+Q59+S59) -> 0 | CQ59: =ROUND((ROUND((AC59*AW59*1),2)*BC59),2) -> 1468.15 | CR59: =(ROUND((ROUND(((ET59)*AV59*1),2)*BB59),2)+ROUND((ROUND(((AE59-(EU59))*AV59*1),2)*BS59),2)) -> 0 | CS59: =ROUND((ROUND((AE59*AV59*1),2)*BS59),2) -> 0 | CT59: =ROUND((ROUND((AF59*AV59*1),2)*BA59),2) -> 0 | CU59: =AG59 -> 0 | CV59: =(AH59*AV59) -> 0 | CW59: =AI59 -> 0 | CX59: =AJ59 -> 0 | CY59: =(((S59+R59)*AT59)/100) -> 0 | CZ59: =(((S59+R59)*AU59)/100) -> 0 | DN59: 0 | DO59: 0 | DP59: 1 | DQ59: 1 | DU59: 1010 | DV59: 100 шт. | DW59: 100 шт. | DX59: 100 | EE59: 58807897 | EF59: 30 | EG59: Строительные работы | EH59: 0 | EJ59: 1 | EK59: 21 | EL59: ТСН-2001.3-16. Трубопроводы внутренние | EM59: ТСН-2001.3-16-1 | EQ59: 1024 | ER59: 526.22 | ES59: 526.22 | ET59: 0 | EU59: 0 | EV59: 0 | EW59: 0 | EX59: 0 | FQ59: 0 | FR59: 0 | FS59: 0 | FX59: 109 | FY59: 61 | GD59: 1 | GF59: 1873919888 | GG59: 2 | GH59: 1 | GI59: 2 | GJ59: 0 | GK59: 0 | GL59: =ROUND(IF(AND(BH59=3,BI59=3,FS59<>0),P59,0),2) -> 0 | GM59: =ROUND(O59+X59+Y59,2)+GX59 -> 0 | GN59: =IF(OR(BI59=0,BI59=1),GM59-GX59,0) -> 0 | GO59: =IF(BI59=2,GM59-GX59,0) -> 0 | GP59: =IF(BI59=4,GM59-GX59,0) -> 0 | GR59: 0 | GS59: 3 | GT59: 0 | GV59: =ROUND((GT59),6) -> 0 | GW59: 1 | GX59: =ROUND(HC59*I59,2) -> 0 | HA59: 0 | HB59: 0 | HC59: =GV59*GW59 -> 0 | HS59: 0 | IK59: 0
A60: 18 | B60: 1 | C60: 93 | F60: 1.13-4-62 | G60: Кран шаровой, латунный, никелированный, полнопроходной, с алюминиевой рукояткой, муфтовый, температура рабочей среды от -15 до +110°С, номинальное давление PN 4,0 МПа, номинальный диаметр DN 20 мм | H60: шт. | I60: =I56*J60 -> 0 | J60: 21.818182 | K60: 21.818182 | O60: =ROUND(CP60,2) -> 0 | P60: =ROUND((ROUND((AC60*AW60*I60),2)*BC60),2) -> 0 | Q60: =(ROUND((ROUND(((ET60)*AV60*I60),2)*BB60),2)+ROUND((ROUND(((AE60-(EU60))*AV60*I60),2)*BS60),2)) -> 0 | R60: =ROUND((ROUND((AE60*AV60*I60),2)*BS60),2) -> 0 | S60: =ROUND((ROUND((AF60*AV60*I60),2)*BA60),2) -> 0 | T60: =ROUND(CU60*I60,2) -> 0 | U60: =CV60*I60 -> 0 | V60: =CW60*I60 -> 0 | W60: =ROUND(CX60*I60,2) -> 0 | X60: =ROUND(CY60,2) -> 0 | Y60: =ROUND(CZ60,2) -> 0 | AA60: -1 | AB60: =ROUND((AC60+AD60+AF60),6) -> 47.24 | AC60: =ROUND((ES60),6) -> 47.24 | AD60: =ROUND((((ET60)-(EU60))+AE60),6) -> 0 | AE60: =ROUND((EU60),6) -> 0 | AF60: =ROUND((EV60),6) -> 0 | AG60: =ROUND((AP60),6) -> 0 | AH60: =(EW60) -> 0 | AI60: =(EX60) -> 0 | AJ60: =(AS60) -> 0 | AK60: 47.24 | AL60: 47.24 | AM60: 0 | AN60: 0 | AO60: 0 | AP60: 0 | AQ60: 0 | AR60: 0 | AS60: 0 | AT60: 109 | AU60: 61 | AV60: 1 | AW60: 1 | AZ60: 1 | BA60: 1 | BB60: 1 | BC60: 1 | BH60: 3 | BI60: 1 | BJ60: ТСН-2001.1 Доп. 73, Р. 13, о. 4, поз. 62 | BM60: 21 | BN60: 0 | BP60: 0 | BQ60: 30 | BR60: 0 | BS60: 1 | BT60: 1 | BU60: 1 | BV60: 1 | BW60: 1 | BX60: 1 | BZ60: 109 | CA60: 61 | CE60: 30 | CF60: 0 | CG60: 0 | CM60: 0 | CO60: 0 | CP60: =(P60+Q60+S60) -> 0 | CQ60: =ROUND((ROUND((AC60*AW60*1),2)*BC60),2) -> 47.24 | CR60: =(ROUND((ROUND(((ET60)*AV60*1),2)*BB60),2)+ROUND((ROUND(((AE60-(EU60))*AV60*1),2)*BS60),2)) -> 0 | CS60: =ROUND((ROUND((AE60*AV60*1),2)*BS60),2) -> 0 | CT60: =ROUND((ROUND((AF60*AV60*1),2)*BA60),2) -> 0 | CU60: =AG60 -> 0 | CV60: =(AH60*AV60) -> 0 | CW60: =AI60 -> 0 | CX60: =AJ60 -> 0 | CY60: =(((S60+R60)*AT60)/100) -> 0 | CZ60: =(((S60+R60)*AU60)/100) -> 0 | DN60: 0 | DO60: 0 | DP60: 1 | DQ60: 1 | DU60: 1010 | DV60: шт. | DW60: шт. | DX60: 1 | EE60: 58807897 | EF60: 30 | EG60: Строительные работы | EH60: 0 | EJ60: 1 | EK60: 21 | EL60: ТСН-2001.3-16. Трубопроводы внутренние | EM60: ТСН-2001.3-16-1 | EQ60: 1024 | ER60: 47.24 | ES60: 47.24 | ET60: 0 | EU60: 0 | EV60: 0 | EW60: 0 | EX60: 0 | FQ60: 0 | FR60: 0 | FS60: 0 | FX60: 109 | FY60: 61 | GD60: 1 | GF60: -146904554 | GG60: 2 | GH60: 1 | GI60: -2 | GJ60: 0 | GK60: 0 | GL60: =ROUND(IF(AND(BH60=3,BI60=3,FS60<>0),P60,0),2) -> 0 | GM60: =ROUND(O60+X60+Y60,2)+GX60 -> 0 | GN60: =IF(OR(BI60=0,BI60=1),GM60-GX60,0) -> 0 | GO60: =IF(BI60=2,GM60-GX60,0) -> 0 | GP60: =IF(BI60=4,GM60-GX60,0) -> 0 | GR60: 0 | GS60: 3 | GT60: 0 | GV60: =ROUND((GT60),6) -> 0 | GW60: 1 | GX60: =ROUND(HC60*I60,2) -> 0 | HA60: 0 | HB60: 0 | HC60: =GV60*GW60 -> 0 | HS60: 0 | IK60: 0
A61: 18 | B61: 1 | C61: 108 | F61: 1.13-4-62 | G61: Кран шаровой, латунный, никелированный, полнопроходной, с алюминиевой рукояткой, муфтовый, температура рабочей среды от -15 до +110°С, номинальное давление PN 4,0 МПа, номинальный диаметр DN 20 мм | H61: шт. | I61: =I57*J61 -> 0 | J61: 21.818182 | K61: 21.818182 | O61: =ROUND(CP61,2) -> 0 | P61: =ROUND((ROUND((AC61*AW61*I61),2)*BC61),2) -> 0 | Q61: =(ROUND((ROUND(((ET61)*AV61*I61),2)*BB61),2)+ROUND((ROUND(((AE61-(EU61))*AV61*I61),2)*BS61),2)) -> 0 | R61: =ROUND((ROUND((AE61*AV61*I61),2)*BS61),2) -> 0 | S61: =ROUND((ROUND((AF61*AV61*I61),2)*BA61),2) -> 0 | T61: =ROUND(CU61*I61,2) -> 0 | U61: =CV61*I61 -> 0 | V61: =CW61*I61 -> 0 | W61: =ROUND(CX61*I61,2) -> 0 | X61: =ROUND(CY61,2) -> 0 | Y61: =ROUND(CZ61,2) -> 0 | AA61: -1 | AB61: =ROUND((AC61+AD61+AF61),6) -> 47.24 | AC61: =ROUND((ES61),6) -> 47.24 | AD61: =ROUND((((ET61)-(EU61))+AE61),6) -> 0 | AE61: =ROUND((EU61),6) -> 0 | AF61: =ROUND((EV61),6) -> 0 | AG61: =ROUND((AP61),6) -> 0 | AH61: =(EW61) -> 0 | AI61: =(EX61) -> 0 | AJ61: =(AS61) -> 0 | AK61: 47.24 | AL61: 47.24 | AM61: 0 | AN61: 0 | AO61: 0 | AP61: 0 | AQ61: 0 | AR61: 0 | AS61: 0 | AT61: 109 | AU61: 61 | AV61: 1 | AW61: 1 | AZ61: 1 | BA61: 1 | BB61: 1 | BC61: 20.7 | BH61: 3 | BI61: 1 | BJ61: ТСН-2001.1 Доп. 73, Р. 13, о. 4, поз. 62 | BM61: 21 | BN61: 0 | BO61: 1.13-4-62 | BP61: 1 | BQ61: 30 | BR61: 0 | BS61: 1 | BT61: 1 | BU61: 1 | BV61: 1 | BW61: 1 | BX61: 1 | BZ61: 109 | CA61: 61 | CE61: 30 | CF61: 0 | CG61: 0 | CM61: 0 | CO61: 0 | CP61: =(P61+Q61+S61) -> 0 | CQ61: =ROUND((ROUND((AC61*AW61*1),2)*BC61),2) -> 977.87 | CR61: =(ROUND((ROUND(((ET61)*AV61*1),2)*BB61),2)+ROUND((ROUND(((AE61-(EU61))*AV61*1),2)*BS61),2)) -> 0 | CS61: =ROUND((ROUND((AE61*AV61*1),2)*BS61),2) -> 0 | CT61: =ROUND((ROUND((AF61*AV61*1),2)*BA61),2) -> 0 | CU61: =AG61 -> 0 | CV61: =(AH61*AV61) -> 0 | CW61: =AI61 -> 0 | CX61: =AJ61 -> 0 | CY61: =(((S61+R61)*AT61)/100) -> 0 | CZ61: =(((S61+R61)*AU61)/100) -> 0 | DN61: 0 | DO61: 0 | DP61: 1 | DQ61: 1 | DU61: 1010 | DV61: шт. | DW61: шт. | DX61: 1 | EE61: 58807897 | EF61: 30 | EG61: Строительные работы | EH61: 0 | EJ61: 1 | EK61: 21 | EL61: ТСН-2001.3-16. Трубопроводы внутренние | EM61: ТСН-2001.3-16-1 | EQ61: 1024 | ER61: 47.24 | ES61: 47.24 | ET61: 0 | EU61: 0 | EV61: 0 | EW61: 0 | EX61: 0 | FQ61: 0 | FR61: 0 | FS61: 0 | FX61: 109 | FY61: 61 | GD61: 1 | GF61: -146904554 | GG61: 2 | GH61: 1 | GI61: 2 | GJ61: 0 | GK61: 0 | GL61: =ROUND(IF(AND(BH61=3,BI61=3,FS61<>0),P61,0),2) -> 0 | GM61: =ROUND(O61+X61+Y61,2)+GX61 -> 0 | GN61: =IF(OR(BI61=0,BI61=1),GM61-GX61,0) -> 0 | GO61: =IF(BI61=2,GM61-GX61,0) -> 0 | GP61: =IF(BI61=4,GM61-GX61,0) -> 0 | GR61: 0 | GS61: 3 | GT61: 0 | GV61: =ROUND((GT61),6) -> 0 | GW61: 1 | GX61: =ROUND(HC61*I61,2) -> 0 | HA61: 0 | HB61: 0 | HC61: =GV61*GW61 -> 0 | HS61: 0 | IK61: 0
A62: 18 | B62: 1 | C62: 92 | F62: 1.12-6-6 | G62: Трубы стальные электросварные прямошовные, ГОСТ 10705-80, ГОСТ 10704-91, наружный диаметр 25 мм, толщина стенки 2 мм | H62: м | I62: =I56*J62 -> 0 | J62: 100 | K62: 100 | O62: =ROUND(CP62,2) -> 0 | P62: =ROUND((ROUND((AC62*AW62*I62),2)*BC62),2) -> 0 | Q62: =(ROUND((ROUND(((ET62)*AV62*I62),2)*BB62),2)+ROUND((ROUND(((AE62-(EU62))*AV62*I62),2)*BS62),2)) -> 0 | R62: =ROUND((ROUND((AE62*AV62*I62),2)*BS62),2) -> 0 | S62: =ROUND((ROUND((AF62*AV62*I62),2)*BA62),2) -> 0 | T62: =ROUND(CU62*I62,2) -> 0 | U62: =CV62*I62 -> 0 | V62: =CW62*I62 -> 0 | W62: =ROUND(CX62*I62,2) -> 0 | X62: =ROUND(CY62,2) -> 0 | Y62: =ROUND(CZ62,2) -> 0 | AA62: -1 | AB62: =ROUND((AC62+AD62+AF62),6) -> 14.97 | AC62: =ROUND((ES62),6) -> 14.97 | AD62: =ROUND((((ET62)-(EU62))+AE62),6) -> 0 | AE62: =ROUND((EU62),6) -> 0 | AF62: =ROUND((EV62),6) -> 0 | AG62: =ROUND((AP62),6) -> 0 | AH62: =(EW62) -> 0 | AI62: =(EX62) -> 0 | AJ62: =(AS62) -> 0 | AK62: 14.97 | AL62: 14.97 | AM62: 0 | AN62: 0 | AO62: 0 | AP62: 0 | AQ62: 0 | AR62: 0 | AS62: 0 | AT62: 109 | AU62: 61 | AV62: 1 | AW62: 1 | AZ62: 1 | BA62: 1 | BB62: 1 | BC62: 1 | BH62: 3 | BI62: 1 | BJ62: ТСН-2001.1 Доп. 79, Р. 12, о. 6, поз. 6 | BM62: 21 | BN62: 0 | BP62: 0 | BQ62: 30 | BR62: 0 | BS62: 1 | BT62: 1 | BU62: 1 | BV62: 1 | BW62: 1 | BX62: 1 | BZ62: 109 | CA62: 61 | CE62: 30 | CF62: 0 | CG62: 0 | CM62: 0 | CO62: 0 | CP62: =(P62+Q62+S62) -> 0 | CQ62: =ROUND((ROUND((AC62*AW62*1),2)*BC62),2) -> 14.97 | CR62: =(ROUND((ROUND(((ET62)*AV62*1),2)*BB62),2)+ROUND((ROUND(((AE62-(EU62))*AV62*1),2)*BS62),2)) -> 0 | CS62: =ROUND((ROUND((AE62*AV62*1),2)*BS62),2) -> 0 | CT62: =ROUND((ROUND((AF62*AV62*1),2)*BA62),2) -> 0 | CU62: =AG62 -> 0 | CV62: =(AH62*AV62) -> 0 | CW62: =AI62 -> 0 | CX62: =AJ62 -> 0 | CY62: =(((S62+R62)*AT62)/100) -> 0 | CZ62: =(((S62+R62)*AU62)/100) -> 0 | DN62: 0 | DO62: 0 | DP62: 1 | DQ62: 1 | DU62: 1003 | DV62: м | DW62: м | DX62: 1 | EE62: 58807897 | EF62: 30 | EG62: Строительные работы | EH62: 0 | EJ62: 1 | EK62: 21 | EL62: ТСН-2001.3-16. Трубопроводы внутренние | EM62: ТСН-2001.3-16-1 | EQ62: 1024 | ER62: 14.97 | ES62: 14.97 | ET62: 0 | EU62: 0 | EV62: 0 | EW62: 0 | EX62: 0 | FQ62: 0 | FR62: 0 | FS62: 0 | FX62: 109 | FY62: 61 | GD62: 1 | GF62: 2049272964 | GG62: 2 | GH62: 1 | GI62: -2 | GJ62: 0 | GK62: 0 | GL62: =ROUND(IF(AND(BH62=3,BI62=3,FS62<>0),P62,0),2) -> 0 | GM62: =ROUND(O62+X62+Y62,2)+GX62 -> 0 | GN62: =IF(OR(BI62=0,BI62=1),GM62-GX62,0) -> 0 | GO62: =IF(BI62=2,GM62-GX62,0) -> 0 | GP62: =IF(BI62=4,GM62-GX62,0) -> 0 | GR62: 0 | GS62: 3 | GT62: 0 | GV62: =ROUND((GT62),6) -> 0 | GW62: 1 | GX62: =ROUND(HC62*I62,2) -> 0 | HA62: 0 | HB62: 0 | HC62: =GV62*GW62 -> 0 | HS62: 0 | IK62: 0
A63: 18 | B63: 1 | C63: 107 | F63: 1.12-6-6 | G63: Трубы стальные электросварные прямошовные, ГОСТ 10705-80, ГОСТ 10704-91, наружный диаметр 25 мм, толщина стенки 2 мм | H63: м | I63: =I57*J63 -> 0 | J63: 100 | K63: 100 | O63: =ROUND(CP63,2) -> 0 | P63: =ROUND((ROUND((AC63*AW63*I63),2)*BC63),2) -> 0 | Q63: =(ROUND((ROUND(((ET63)*AV63*I63),2)*BB63),2)+ROUND((ROUND(((AE63-(EU63))*AV63*I63),2)*BS63),2)) -> 0 | R63: =ROUND((ROUND((AE63*AV63*I63),2)*BS63),2) -> 0 | S63: =ROUND((ROUND((AF63*AV63*I63),2)*BA63),2) -> 0 | T63: =ROUND(CU63*I63,2) -> 0 | U63: =CV63*I63 -> 0 | V63: =CW63*I63 -> 0 | W63: =ROUND(CX63*I63,2) -> 0 | X63: =ROUND(CY63,2) -> 0 | Y63: =ROUND(CZ63,2) -> 0 | AA63: -1 | AB63: =ROUND((AC63+AD63+AF63),6) -> 14.97 | AC63: =ROUND((ES63),6) -> 14.97 | AD63: =ROUND((((ET63)-(EU63))+AE63),6) -> 0 | AE63: =ROUND((EU63),6) -> 0 | AF63: =ROUND((EV63),6) -> 0 | AG63: =ROUND((AP63),6) -> 0 | AH63: =(EW63) -> 0 | AI63: =(EX63) -> 0 | AJ63: =(AS63) -> 0 | AK63: 14.97 | AL63: 14.97 | AM63: 0 | AN63: 0 | AO63: 0 | AP63: 0 | AQ63: 0 | AR63: 0 | AS63: 0 | AT63: 109 | AU63: 61 | AV63: 1 | AW63: 1 | AZ63: 1 | BA63: 1 | BB63: 1 | BC63: 4.17 | BH63: 3 | BI63: 1 | BJ63: ТСН-2001.1 Доп. 79, Р. 12, о. 6, поз. 6 | BM63: 21 | BN63: 0 | BO63: 1.12-6-6 | BP63: 1 | BQ63: 30 | BR63: 0 | BS63: 1 | BT63: 1 | BU63: 1 | BV63: 1 | BW63: 1 | BX63: 1 | BZ63: 109 | CA63: 61 | CE63: 30 | CF63: 0 | CG63: 0 | CM63: 0 | CO63: 0 | CP63: =(P63+Q63+S63) -> 0 | CQ63: =ROUND((ROUND((AC63*AW63*1),2)*BC63),2) -> 62.42 | CR63: =(ROUND((ROUND(((ET63)*AV63*1),2)*BB63),2)+ROUND((ROUND(((AE63-(EU63))*AV63*1),2)*BS63),2)) -> 0 | CS63: =ROUND((ROUND((AE63*AV63*1),2)*BS63),2) -> 0 | CT63: =ROUND((ROUND((AF63*AV63*1),2)*BA63),2) -> 0 | CU63: =AG63 -> 0 | CV63: =(AH63*AV63) -> 0 | CW63: =AI63 -> 0 | CX63: =AJ63 -> 0 | CY63: =(((S63+R63)*AT63)/100) -> 0 | CZ63: =(((S63+R63)*AU63)/100) -> 0 | DN63: 0 | DO63: 0 | DP63: 1 | DQ63: 1 | DU63: 1003 | DV63: м | DW63: м | DX63: 1 | EE63: 58807897 | EF63: 30 | EG63: Строительные работы | EH63: 0 | EJ63: 1 | EK63: 21 | EL63: ТСН-2001.3-16. Трубопроводы внутренние | EM63: ТСН-2001.3-16-1 | EQ63: 1024 | ER63: 14.97 | ES63: 14.97 | ET63: 0 | EU63: 0 | EV63: 0 | EW63: 0 | EX63: 0 | FQ63: 0 | FR63: 0 | FS63: 0 | FX63: 109 | FY63: 61 | GD63: 1 | GF63: 2049272964 | GG63: 2 | GH63: 1 | GI63: 2 | GJ63: 0 | GK63: 0 | GL63: =ROUND(IF(AND(BH63=3,BI63=3,FS63<>0),P63,0),2) -> 0 | GM63: =ROUND(O63+X63+Y63,2)+GX63 -> 0 | GN63: =IF(OR(BI63=0,BI63=1),GM63-GX63,0) -> 0 | GO63: =IF(BI63=2,GM63-GX63,0) -> 0 | GP63: =IF(BI63=4,GM63-GX63,0) -> 0 | GR63: 0 | GS63: 3 | GT63: 0 | GV63: =ROUND((GT63),6) -> 0 | GW63: 1 | GX63: =ROUND(HC63*I63,2) -> 0 | HA63: 0 | HB63: 0 | HC63: =GV63*GW63 -> 0 | HS63: 0 | IK63: 0
A64: 17 | B64: 1 | C64: =ROW(SmtRes!A119) -> 119 | D64: =ROW(EtalonRes!A115) -> 115 | E64: 3 | F64: 3.16-38-1 | G64: Прокладка трубопроводов из стальных труб на бессварных разъемных муфтовых соединениях диаметром до 25 мм | H64: 100 м | I64: =ROUND(ROUND(175/100,4),9) -> 1.75 | J64: 0 | K64: =ROUND(ROUND(175/100,4),9) -> 1.75 | O64: =ROUND(CP64,2) -> 570.62 | P64: =ROUND((ROUND((AC64*AW64*I64),2)*BC64),2) -> 52.57 | Q64: =(ROUND((ROUND((((ET64*1.25))*AV64*I64),2)*BB64),2)+ROUND((ROUND(((AE64-((EU64*1.25)))*AV64*I64),2)*BS64),2)) -> 9.5 | R64: =ROUND((ROUND((AE64*AV64*I64),2)*BS64),2) -> 0.7 | S64: =ROUND((ROUND((AF64*AV64*I64),2)*BA64),2) -> 508.55 | T64: =ROUND(CU64*I64,2) -> 0 | U64: =CV64*I64 -> 41.057093 | V64: =CW64*I64 -> 0 | W64: =ROUND(CX64*I64,2) -> 0 | X64: =ROUND(CY64,2) -> 555.08 | Y64: =ROUND(CZ64,2) -> 310.64 | AA64: 59204062 | AB64: =ROUND((AC64+AD64+AF64),6) -> 307.482 | AC64: =ROUND((ES64),6) -> 30.04 | AD64: =ROUND(((((ET64*1.25))-((EU64*1.25)))+AE64),6) -> 5.0875 | AE64: =ROUND(((EU64*1.25)),6) -> 0.375 | AF64: =ROUND(((EV64*1.15)),6) -> 272.3545 | AG64: =ROUND((AP64),6) -> 0 | AH64: =((EW64*1.15)) -> 21.988 | AI64: =((EX64*1.25)) -> 0 | AJ64: =(AS64) -> 0 | AK64: 270.94 | AL64: 30.04 | AM64: 4.07 | AN64: 0.3 | AO64: 236.83 | AP64: 0 | AQ64: 19.12 | AR64: 0 | AS64: 0 | AT64: 109 | AU64: 61 | AV64: 1.067 | AW64: 1 | AZ64: 1 | BA64: 1 | BB64: 1 | BC64: 1 | BH64: 0 | BI64: 1 | BJ64: ТСН-2001.3 Доп. 80, Сб. 16, т. 38, поз. 1 | BM64: 21 | BN64: 0 | BO64: 3.16-38-1 | BP64: 1 | BQ64: 30 | BR64: 0 | BS64: 1 | BT64: 1 | BU64: 1 | BV64: 1 | BW64: 1 | BX64: 1 | BZ64: 109 | CA64: 61 | CE64: 30 | CF64: 0 | CG64: 0 | CM64: 0 | CN64: Поправка: О.П. п.3.4. 6 Наименование: Выполняемые при ремонте и реконструкции работы аналогичные технологическим процессам, характерным для нового строительства и отсутствующим в сборниках на ремонтно-строительные работы | CO64: 0 | CP64: =(P64+Q64+S64) -> 570.62 | CQ64: =ROUND((ROUND((AC64*AW64*1),2)*BC64),2) -> 30.04 | CR64: =(ROUND((ROUND((((ET64*1.25))*AV64*1),2)*BB64),2)+ROUND((ROUND(((AE64-((EU64*1.25)))*AV64*1),2)*BS64),2)) -> 5.43 | CS64: =ROUND((ROUND((AE64*AV64*1),2)*BS64),2) -> 0.4 | CT64: =ROUND((ROUND((AF64*AV64*1),2)*BA64),2) -> 290.6 | CU64: =AG64 -> 0 | CV64: =(AH64*AV64) -> 23.461196 | CW64: =AI64 -> 0 | CX64: =AJ64 -> 0 | CY64: =(((S64+R64)*AT64)/100) -> 555.0825 | CZ64: =(((S64+R64)*AU64)/100) -> 310.6425 | DB64: 17 | DE64: *1,25 | DF64: *1,25 | DG64: *1,15 | DI64: *1,15 | DJ64: *1,25 | DN64: 0 | DO64: 0 | DP64: 1 | DQ64: 1 | DU64: 1003 | DV64: 100 м | DW64: 100 м | DX64: 100 | EE64: 58807897 | EF64: 30 | EG64: Строительные работы | EH64: 0 | EJ64: 1 | EK64: 21 | EL64: ТСН-2001.3-16. Трубопроводы внутренние | EM64: ТСН-2001.3-16-1 | EO64: Поправка: О.П. п.3.4. 6 | EQ64: 1310720 | ER64: 270.94 | ES64: 30.04 | ET64: 4.07 | EU64: 0.3 | EV64: 236.83 | EW64: 19.12 | EX64: 0 | EY64: 0 | FQ64: 0 | FR64: 0 | FS64: 0 | FX64: 109 | FY64: 61 | GD64: 1 | GF64: -367569951 | GG64: 2 | GH64: 1 | GI64: 2 | GJ64: 0 | GK64: 0 | GL64: =ROUND(IF(AND(BH64=3,BI64=3,FS64<>0),P64,0),2) -> 0 | GM64: =ROUND(O64+X64+Y64,2)+GX64 -> 1436.34 | GN64: =IF(OR(BI64=0,BI64=1),GM64-GX64,0) -> 1436.34 | GO64: =IF(BI64=2,GM64-GX64,0) -> 0 | GP64: =IF(BI64=4,GM64-GX64,0) -> 0 | GR64: 0 | GS64: 3 | GT64: 0 | GV64: =ROUND((GT64),6) -> 0 | GW64: 1 | GX64: =ROUND(HC64*I64,2) -> 0 | HA64: 0 | HB64: 0 | HC64: =GV64*GW64 -> 0 | HS64: 0 | IK64: 0
A65: 17 | B65: 1 | C65: =ROW(SmtRes!A130) -> 130 | D65: =ROW(EtalonRes!A126) -> 126 | E65: 3 | F65: 3.16-38-1 | G65: Прокладка трубопроводов из стальных труб на бессварных разъемных муфтовых соединениях диаметром до 25 мм | H65: 100 м | I65: =ROUND(ROUND(175/100,4),9) -> 1.75 | J65: 0 | K65: =ROUND(ROUND(175/100,4),9) -> 1.75 | O65: =ROUND(CP65,2) -> 28177.44 | P65: =ROUND((ROUND((AC65*AW65*I65),2)*BC65),2) -> 94.1 | Q65: =(ROUND((ROUND((((ET65*1.25))*AV65*I65),2)*BB65),2)+ROUND((ROUND(((AE65-((EU65*1.25)))*AV65*I65),2)*BS65),2)) -> 118.18 | R65: =ROUND((ROUND((AE65*AV65*I65),2)*BS65),2) -> 38.49 | S65: =ROUND((ROUND((AF65*AV65*I65),2)*BA65),2) -> 27965.16 | T65: =ROUND(CU65*I65,2) -> 0 | U65: =CV65*I65 -> 41.057093 | V65: =CW65*I65 -> 0 | W65: =ROUND(CX65*I65,2) -> 0 | X65: =ROUND(CY65,2) -> 30523.98 | Y65: =ROUND(CZ65,2) -> 17082.23 | AA65: 59204059 | AB65: =ROUND((AC65+AD65+AF65),6) -> 307.482 | AC65: =ROUND((ES65),6) -> 30.04 | AD65: =ROUND(((((ET65*1.25))-((EU65*1.25)))+AE65),6) -> 5.0875 | AE65: =ROUND(((EU65*1.25)),6) -> 0.375 | AF65: =ROUND(((EV65*1.15)),6) -> 272.3545 | AG65: =ROUND((AP65),6) -> 0 | AH65: =((EW65*1.15)) -> 21.988 | AI65: =((EX65*1.25)) -> 0 | AJ65: =(AS65) -> 0 | AK65: 270.94 | AL65: 30.04 | AM65: 4.07 | AN65: 0.3 | AO65: 236.83 | AP65: 0 | AQ65: 19.12 | AR65: 0 | AS65: 0 | AT65: 109 | AU65: 61 | AV65: 1.067 | AW65: 1 | AZ65: 1 | BA65: 54.99 | BB65: 12.44 | BC65: 1.79 | BH65: 0 | BI65: 1 | BJ65: ТСН-2001.3 Доп. 80, Сб. 16, т. 38, поз. 1 | BM65: 21 | BN65: 0 | BO65: 3.16-38-1 | BP65: 1 | BQ65: 30 | BR65: 0 | BS65: 54.99 | BT65: 1 | BU65: 1 | BV65: 1 | BW65: 1 | BX65: 1 | BZ65: 109 | CA65: 61 | CE65: 30 | CF65: 0 | CG65: 0 | CM65: 0 | CN65: Поправка: О.П. п.3.4. 6 Наименование: Выполняемые при ремонте и реконструкции работы аналогичные технологическим процессам, характерным для нового строительства и отсутствующим в сборниках на ремонтно-строительные работы | CO65: 0 | CP65: =(P65+Q65+S65) -> 28177.44 | CQ65: =ROUND((ROUND((AC65*AW65*1),2)*BC65),2) -> 53.77 | CR65: =(ROUND((ROUND((((ET65*1.25))*AV65*1),2)*BB65),2)+ROUND((ROUND(((AE65-((EU65*1.25)))*AV65*1),2)*BS65),2)) -> 67.55 | CS65: =ROUND((ROUND((AE65*AV65*1),2)*BS65),2) -> 22 | CT65: =ROUND((ROUND((AF65*AV65*1),2)*BA65),2) -> 15980.09 | CU65: =AG65 -> 0 | CV65: =(AH65*AV65) -> 23.461196 | CW65: =AI65 -> 0 | CX65: =AJ65 -> 0 | CY65: =(((S65+R65)*AT65)/100) -> 30523.979 | CZ65: =(((S65+R65)*AU65)/100) -> 17082.227 | DB65: 18 | DE65: *1,25 | DF65: *1,25 | DG65: *1,15 | DI65: *1,15 | DJ65: *1,25 | DN65: 0 | DO65: 0 | DP65: 1 | DQ65: 1 | DU65: 1003 | DV65: 100 м | DW65: 100 м | DX65: 100 | EE65: 58807897 | EF65: 30 | EG65: Строительные работы | EH65: 0 | EJ65: 1 | EK65: 21 | EL65: ТСН-2001.3-16. Трубопроводы внутренние | EM65: ТСН-2001.3-16-1 | EO65: Поправка: О.П. п.3.4. 6 | EQ65: 1310720 | ER65: 270.94 | ES65: 30.04 | ET65: 4.07 | EU65: 0.3 | EV65: 236.83 | EW65: 19.12 | EX65: 0 | EY65: 0 | FQ65: 0 | FR65: 0 | FS65: 0 | FX65: 109 | FY65: 61 | GD65: 1 | GF65: -367569951 | GG65: 2 | GH65: 1 | GI65: 2 | GJ65: 0 | GK65: 0 | GL65: =ROUND(IF(AND(BH65=3,BI65=3,FS65<>0),P65,0),2) -> 0 | GM65: =ROUND(O65+X65+Y65,2)+GX65 -> 75783.65 | GN65: =IF(OR(BI65=0,BI65=1),GM65-GX65,0) -> 75783.65 | GO65: =IF(BI65=2,GM65-GX65,0) -> 0 | GP65: =IF(BI65=4,GM65-GX65,0) -> 0 | GR65: 0 | GS65: 3 | GT65: 0 | GV65: =ROUND((GT65),6) -> 0 | GW65: 1 | GX65: =ROUND(HC65*I65,2) -> 0 | HA65: 0 | HB65: 0 | HC65: =GV65*GW65 -> 0 | HS65: 0 | IK65: 0
A66: 18 | B66: 1 | C66: 118 | E66: 3,1 | F66: 1.12-1-54 | G66: Узел трубопровода из стальных водогазопроводных оцинкованных труб, с гильзами, для водоснабжения, диаметр условного прохода 25 мм | H66: м | I66: =I64*J66 -> 175 | J66: 100 | K66: 100 | O66: =ROUND(CP66,2) -> 7274.75 | P66: =ROUND((ROUND((AC66*AW66*I66),2)*BC66),2) -> 7274.75 | Q66: =(ROUND((ROUND(((ET66)*AV66*I66),2)*BB66),2)+ROUND((ROUND(((AE66-(EU66))*AV66*I66),2)*BS66),2)) -> 0 | R66: =ROUND((ROUND((AE66*AV66*I66),2)*BS66),2) -> 0 | S66: =ROUND((ROUND((AF66*AV66*I66),2)*BA66),2) -> 0 | T66: =ROUND(CU66*I66,2) -> 0 | U66: =CV66*I66 -> 0 | V66: =CW66*I66 -> 0 | W66: =ROUND(CX66*I66,2) -> 0 | X66: =ROUND(CY66,2) -> 0 | Y66: =ROUND(CZ66,2) -> 0 | AA66: 59204062 | AB66: =ROUND((AC66+AD66+AF66),6) -> 41.57 | AC66: =ROUND((ES66),6) -> 41.57 | AD66: =ROUND((((ET66)-(EU66))+AE66),6) -> 0 | AE66: =ROUND((EU66),6) -> 0 | AF66: =ROUND((EV66),6) -> 0 | AG66: =ROUND((AP66),6) -> 0 | AH66: =(EW66) -> 0 | AI66: =(EX66) -> 0 | AJ66: =(AS66) -> 0 | AK66: 41.57 | AL66: 41.57 | AM66: 0 | AN66: 0 | AO66: 0 | AP66: 0 | AQ66: 0 | AR66: 0 | AS66: 0 | AT66: 109 | AU66: 61 | AV66: 1 | AW66: 1 | AZ66: 1 | BA66: 1 | BB66: 1 | BC66: 1 | BH66: 3 | BI66: 1 | BJ66: ТСН-2001.1 Доп. 79, Р. 12, о. 1, поз. 54 | BM66: 21 | BN66: 0 | BP66: 0 | BQ66: 30 | BR66: 0 | BS66: 1 | BT66: 1 | BU66: 1 | BV66: 1 | BW66: 1 | BX66: 1 | BZ66: 109 | CA66: 61 | CE66: 30 | CF66: 0 | CG66: 0 | CM66: 0 | CO66: 0 | CP66: =(P66+Q66+S66) -> 7274.75 | CQ66: =ROUND((ROUND((AC66*AW66*1),2)*BC66),2) -> 41.57 | CR66: =(ROUND((ROUND(((ET66)*AV66*1),2)*BB66),2)+ROUND((ROUND(((AE66-(EU66))*AV66*1),2)*BS66),2)) -> 0 | CS66: =ROUND((ROUND((AE66*AV66*1),2)*BS66),2) -> 0 | CT66: =ROUND((ROUND((AF66*AV66*1),2)*BA66),2) -> 0 | CU66: =AG66 -> 0 | CV66: =(AH66*AV66) -> 0 | CW66: =AI66 -> 0 | CX66: =AJ66 -> 0 | CY66: =(((S66+R66)*AT66)/100) -> 0 | CZ66: =(((S66+R66)*AU66)/100) -> 0 | DN66: 0 | DO66: 0 | DP66: 1 | DQ66: 1 | DU66: 1003 | DV66: м | DW66: м | DX66: 1 | EE66: 58807897 | EF66: 30 | EG66: Строительные работы | EH66: 0 | EJ66: 1 | EK66: 21 | EL66: ТСН-2001.3-16. Трубопроводы внутренние | EM66: ТСН-2001.3-16-1 | EQ66: 0 | ER66: 41.57 | ES66: 41.57 | ET66: 0 | EU66: 0 | EV66: 0 | EW66: 0 | EX66: 0 | FQ66: 0 | FR66: 0 | FS66: 0 | FX66: 109 | FY66: 61 | GD66: 1 | GF66: 1800542993 | GG66: 2 | GH66: 1 | GI66: -2 | GJ66: 0 | GK66: 0 | GL66: =ROUND(IF(AND(BH66=3,BI66=3,FS66<>0),P66,0),2) -> 0 | GM66: =ROUND(O66+X66+Y66,2)+GX66 -> 7274.75 | GN66: =IF(OR(BI66=0,BI66=1),GM66-GX66,0) -> 7274.75 | GO66: =IF(BI66=2,GM66-GX66,0) -> 0 | GP66: =IF(BI66=4,GM66-GX66,0) -> 0 | GR66: 0 | GS66: 3 | GT66: 0 | GV66: =ROUND((GT66),6) -> 0 | GW66: 1 | GX66: =ROUND(HC66*I66,2) -> 0 | HA66: 0 | HB66: 0 | HC66: =GV66*GW66 -> 0 | HS66: 0 | IK66: 0
A67: 18 | B67: 1 | C67: 129 | E67: 3,1 | F67: 1.12-1-54 | G67: Узел трубопровода из стальных водогазопроводных оцинкованных труб, с гильзами, для водоснабжения, диаметр условного прохода 25 мм | H67: м | I67: =I65*J67 -> 175 | J67: 100 | K67: 100 | O67: =ROUND(CP67,2) -> 120397.11 | P67: =ROUND((ROUND((AC67*AW67*I67),2)*BC67),2) -> 120397.11 | Q67: =(ROUND((ROUND(((ET67)*AV67*I67),2)*BB67),2)+ROUND((ROUND(((AE67-(EU67))*AV67*I67),2)*BS67),2)) -> 0 | R67: =ROUND((ROUND((AE67*AV67*I67),2)*BS67),2) -> 0 | S67: =ROUND((ROUND((AF67*AV67*I67),2)*BA67),2) -> 0 | T67: =ROUND(CU67*I67,2) -> 0 | U67: =CV67*I67 -> 0 | V67: =CW67*I67 -> 0 | W67: =ROUND(CX67*I67,2) -> 0 | X67: =ROUND(CY67,2) -> 0 | Y67: =ROUND(CZ67,2) -> 0 | AA67: 59204059 | AB67: =ROUND((AC67+AD67+AF67),6) -> 41.57 | AC67: =ROUND((ES67),6) -> 41.57 | AD67: =ROUND((((ET67)-(EU67))+AE67),6) -> 0 | AE67: =ROUND((EU67),6) -> 0 | AF67: =ROUND((EV67),6) -> 0 | AG67: =ROUND((AP67),6) -> 0 | AH67: =(EW67) -> 0 | AI67: =(EX67) -> 0 | AJ67: =(AS67) -> 0 | AK67: 41.57 | AL67: 41.57 | AM67: 0 | AN67: 0 | AO67: 0 | AP67: 0 | AQ67: 0 | AR67: 0 | AS67: 0 | AT67: 109 | AU67: 61 | AV67: 1 | AW67: 1 | AZ67: 1 | BA67: 1 | BB67: 1 | BC67: 16.55 | BH67: 3 | BI67: 1 | BJ67: ТСН-2001.1 Доп. 79, Р. 12, о. 1, поз. 54 | BM67: 21 | BN67: 0 | BO67: 1.12-1-54 | BP67: 1 | BQ67: 30 | BR67: 0 | BS67: 1 | BT67: 1 | BU67: 1 | BV67: 1 | BW67: 1 | BX67: 1 | BZ67: 109 | CA67: 61 | CE67: 30 | CF67: 0 | CG67: 0 | CM67: 0 | CO67: 0 | CP67: =(P67+Q67+S67) -> 120397.11 | CQ67: =ROUND((ROUND((AC67*AW67*1),2)*BC67),2) -> 687.98 | CR67: =(ROUND((ROUND(((ET67)*AV67*1),2)*BB67),2)+ROUND((ROUND(((AE67-(EU67))*AV67*1),2)*BS67),2)) -> 0 | CS67: =ROUND((ROUND((AE67*AV67*1),2)*BS67),2) -> 0 | CT67: =ROUND((ROUND((AF67*AV67*1),2)*BA67),2) -> 0 | CU67: =AG67 -> 0 | CV67: =(AH67*AV67) -> 0 | CW67: =AI67 -> 0 | CX67: =AJ67 -> 0 | CY67: =(((S67+R67)*AT67)/100) -> 0 | CZ67: =(((S67+R67)*AU67)/100) -> 0 | DN67: 0 | DO67: 0 | DP67: 1 | DQ67: 1 | DU67: 1003 | DV67: м | DW67: м | DX67: 1 | EE67: 58807897 | EF67: 30 | EG67: Строительные работы | EH67: 0 | EJ67: 1 | EK67: 21 | EL67: ТСН-2001.3-16. Трубопроводы внутренние | EM67: ТСН-2001.3-16-1 | EQ67: 0 | ER67: 41.57 | ES67: 41.57 | ET67: 0 | EU67: 0 | EV67: 0 | EW67: 0 | EX67: 0 | FQ67: 0 | FR67: 0 | FS67: 0 | FX67: 109 | FY67: 61 | GD67: 1 | GF67: 1800542993 | GG67: 2 | GH67: 1 | GI67: 2 | GJ67: 0 | GK67: 0 | GL67: =ROUND(IF(AND(BH67=3,BI67=3,FS67<>0),P67,0),2) -> 0 | GM67: =ROUND(O67+X67+Y67,2)+GX67 -> 120397.11 | GN67: =IF(OR(BI67=0,BI67=1),GM67-GX67,0) -> 120397.11 | GO67: =IF(BI67=2,GM67-GX67,0) -> 0 | GP67: =IF(BI67=4,GM67-GX67,0) -> 0 | GR67: 0 | GS67: 3 | GT67: 0 | GV67: =ROUND((GT67),6) -> 0 | GW67: 1 | GX67: =ROUND(HC67*I67,2) -> 0 | HA67: 0 | HB67: 0 | HC67: =GV67*GW67 -> 0 | HS67: 0 | IK67: 0
A68: 18 | B68: 1 | C68: 117 | E68: 3,2 | F68: 1.12-10-146 | G68: Хомут стальной, оцинкованный, двухболтовой, с поворотным механизмом, каучуковой прокладкой, для крепления труб диаметром от 16 до 20 мм, резьба М8/М10 | H68: 100 шт. | I68: =I64*J68 -> 0.87 | J68: 0.49714286 | K68: 0.497143 | O68: =ROUND(CP68,2) -> 457.81 | P68: =ROUND((ROUND((AC68*AW68*I68),2)*BC68),2) -> 457.81 | Q68: =(ROUND((ROUND(((ET68)*AV68*I68),2)*BB68),2)+ROUND((ROUND(((AE68-(EU68))*AV68*I68),2)*BS68),2)) -> 0 | R68: =ROUND((ROUND((AE68*AV68*I68),2)*BS68),2) -> 0 | S68: =ROUND((ROUND((AF68*AV68*I68),2)*BA68),2) -> 0 | T68: =ROUND(CU68*I68,2) -> 0 | U68: =CV68*I68 -> 0 | V68: =CW68*I68 -> 0 | W68: =ROUND(CX68*I68,2) -> 0 | X68: =ROUND(CY68,2) -> 0 | Y68: =ROUND(CZ68,2) -> 0 | AA68: 59204062 | AB68: =ROUND((AC68+AD68+AF68),6) -> 526.22 | AC68: =ROUND((ES68),6) -> 526.22 | AD68: =ROUND((((ET68)-(EU68))+AE68),6) -> 0 | AE68: =ROUND((EU68),6) -> 0 | AF68: =ROUND((EV68),6) -> 0 | AG68: =ROUND((AP68),6) -> 0 | AH68: =(EW68) -> 0 | AI68: =(EX68) -> 0 | AJ68: =(AS68) -> 0 | AK68: 526.22 | AL68: 526.22 | AM68: 0 | AN68: 0 | AO68: 0 | AP68: 0 | AQ68: 0 | AR68: 0 | AS68: 0 | AT68: 109 | AU68: 61 | AV68: 1 | AW68: 1 | AZ68: 1 | BA68: 1 | BB68: 1 | BC68: 1 | BH68: 3 | BI68: 1 | BJ68: ТСН-2001.1 Доп. 79, Р. 12, о. 10, поз. 146 | BM68: 21 | BN68: 0 | BP68: 0 | BQ68: 30 | BR68: 0 | BS68: 1 | BT68: 1 | BU68: 1 | BV68: 1 | BW68: 1 | BX68: 1 | BZ68: 109 | CA68: 61 | CE68: 30 | CF68: 0 | CG68: 0 | CM68: 0 | CO68: 0 | CP68: =(P68+Q68+S68) -> 457.81 | CQ68: =ROUND((ROUND((AC68*AW68*1),2)*BC68),2) -> 526.22 | CR68: =(ROUND((ROUND(((ET68)*AV68*1),2)*BB68),2)+ROUND((ROUND(((AE68-(EU68))*AV68*1),2)*BS68),2)) -> 0 | CS68: =ROUND((ROUND((AE68*AV68*1),2)*BS68),2) -> 0 | CT68: =ROUND((ROUND((AF68*AV68*1),2)*BA68),2) -> 0 | CU68: =AG68 -> 0 | CV68: =(AH68*AV68) -> 0 | CW68: =AI68 -> 0 | CX68: =AJ68 -> 0 | CY68: =(((S68+R68)*AT68)/100) -> 0 | CZ68: =(((S68+R68)*AU68)/100) -> 0 | DN68: 0 | DO68: 0 | DP68: 1 | DQ68: 1 | DU68: 1010 | DV68: 100 шт. | DW68: 100 шт. | DX68: 100 | EE68: 58807897 | EF68: 30 | EG68: Строительные работы | EH68: 0 | EJ68: 1 | EK68: 21 | EL68: ТСН-2001.3-16. Трубопроводы внутренние | EM68: ТСН-2001.3-16-1 | EQ68: 0 | ER68: 526.22 | ES68: 526.22 | ET68: 0 | EU68: 0 | EV68: 0 | EW68: 0 | EX68: 0 | FQ68: 0 | FR68: 0 | FS68: 0 | FX68: 109 | FY68: 61 | GD68: 1 | GF68: 1873919888 | GG68: 2 | GH68: 1 | GI68: -2 | GJ68: 0 | GK68: 0 | GL68: =ROUND(IF(AND(BH68=3,BI68=3,FS68<>0),P68,0),2) -> 0 | GM68: =ROUND(O68+X68+Y68,2)+GX68 -> 457.81 | GN68: =IF(OR(BI68=0,BI68=1),GM68-GX68,0) -> 457.81 | GO68: =IF(BI68=2,GM68-GX68,0) -> 0 | GP68: =IF(BI68=4,GM68-GX68,0) -> 0 | GR68: 0 | GS68: 3 | GT68: 0 | GV68: =ROUND((GT68),6) -> 0 | GW68: 1 | GX68: =ROUND(HC68*I68,2) -> 0 | HA68: 0 | HB68: 0 | HC68: =GV68*GW68 -> 0 | HS68: 0 | IK68: 0
A69: 18 | B69: 1 | C69: 128 | E69: 3,2 | F69: 1.12-10-146 | G69: Хомут стальной, оцинкованный, двухболтовой, с поворотным механизмом, каучуковой прокладкой, для крепления труб диаметром от 16 до 20 мм, резьба М8/М10 | H69: 100 шт. | I69: =I65*J69 -> 0.87 | J69: 0.49714286 | K69: 0.497143 | O69: =ROUND(CP69,2) -> 1277.29 | P69: =ROUND((ROUND((AC69*AW69*I69),2)*BC69),2) -> 1277.29 | Q69: =(ROUND((ROUND(((ET69)*AV69*I69),2)*BB69),2)+ROUND((ROUND(((AE69-(EU69))*AV69*I69),2)*BS69),2)) -> 0 | R69: =ROUND((ROUND((AE69*AV69*I69),2)*BS69),2) -> 0 | S69: =ROUND((ROUND((AF69*AV69*I69),2)*BA69),2) -> 0 | T69: =ROUND(CU69*I69,2) -> 0 | U69: =CV69*I69 -> 0 | V69: =CW69*I69 -> 0 | W69: =ROUND(CX69*I69,2) -> 0 | X69: =ROUND(CY69,2) -> 0 | Y69: =ROUND(CZ69,2) -> 0 | AA69: 59204059 | AB69: =ROUND((AC69+AD69+AF69),6) -> 526.22 | AC69: =ROUND((ES69),6) -> 526.22 | AD69: =ROUND((((ET69)-(EU69))+AE69),6) -> 0 | AE69: =ROUND((EU69),6) -> 0 | AF69: =ROUND((EV69),6) -> 0 | AG69: =ROUND((AP69),6) -> 0 | AH69: =(EW69) -> 0 | AI69: =(EX69) -> 0 | AJ69: =(AS69) -> 0 | AK69: 526.22 | AL69: 526.22 | AM69: 0 | AN69: 0 | AO69: 0 | AP69: 0 | AQ69: 0 | AR69: 0 | AS69: 0 | AT69: 109 | AU69: 61 | AV69: 1 | AW69: 1 | AZ69: 1 | BA69: 1 | BB69: 1 | BC69: 2.79 | BH69: 3 | BI69: 1 | BJ69: ТСН-2001.1 Доп. 79, Р. 12, о. 10, поз. 146 | BM69: 21 | BN69: 0 | BO69: 1.12-10-146 | BP69: 1 | BQ69: 30 | BR69: 0 | BS69: 1 | BT69: 1 | BU69: 1 | BV69: 1 | BW69: 1 | BX69: 1 | BZ69: 109 | CA69: 61 | CE69: 30 | CF69: 0 | CG69: 0 | CM69: 0 | CO69: 0 | CP69: =(P69+Q69+S69) -> 1277.29 | CQ69: =ROUND((ROUND((AC69*AW69*1),2)*BC69),2) -> 1468.15 | CR69: =(ROUND((ROUND(((ET69)*AV69*1),2)*BB69),2)+ROUND((ROUND(((AE69-(EU69))*AV69*1),2)*BS69),2)) -> 0 | CS69: =ROUND((ROUND((AE69*AV69*1),2)*BS69),2) -> 0 | CT69: =ROUND((ROUND((AF69*AV69*1),2)*BA69),2) -> 0 | CU69: =AG69 -> 0 | CV69: =(AH69*AV69) -> 0 | CW69: =AI69 -> 0 | CX69: =AJ69 -> 0 | CY69: =(((S69+R69)*AT69)/100) -> 0 | CZ69: =(((S69+R69)*AU69)/100) -> 0 | DN69: 0 | DO69: 0 | DP69: 1 | DQ69: 1 | DU69: 1010 | DV69: 100 шт. | DW69: 100 шт. | DX69: 100 | EE69: 58807897 | EF69: 30 | EG69: Строительные работы | EH69: 0 | EJ69: 1 | EK69: 21 | EL69: ТСН-2001.3-16. Трубопроводы внутренние | EM69: ТСН-2001.3-16-1 | EQ69: 0 | ER69: 526.22 | ES69: 526.22 | ET69: 0 | EU69: 0 | EV69: 0 | EW69: 0 | EX69: 0 | FQ69: 0 | FR69: 0 | FS69: 0 | FX69: 109 | FY69: 61 | GD69: 1 | GF69: 1873919888 | GG69: 2 | GH69: 1 | GI69: 2 | GJ69: 0 | GK69: 0 | GL69: =ROUND(IF(AND(BH69=3,BI69=3,FS69<>0),P69,0),2) -> 0 | GM69: =ROUND(O69+X69+Y69,2)+GX69 -> 1277.29 | GN69: =IF(OR(BI69=0,BI69=1),GM69-GX69,0) -> 1277.29 | GO69: =IF(BI69=2,GM69-GX69,0) -> 0 | GP69: =IF(BI69=4,GM69-GX69,0) -> 0 | GR69: 0 | GS69: 3 | GT69: 0 | GV69: =ROUND((GT69),6) -> 0 | GW69: 1 | GX69: =ROUND(HC69*I69,2) -> 0 | HA69: 0 | HB69: 0 | HC69: =GV69*GW69 -> 0 | HS69: 0 | IK69: 0
A70: 18 | B70: 1 | C70: 119 | E70: 3,3 | F70: 1.13-4-63 | G70: Кран шаровой, латунный, никелированный, полнопроходной, с алюминиевой рукояткой, муфтовый, температура рабочей среды от -15 до +110°С, номинальное давление PN 4,0 МПа, номинальный диаметр DN 25 мм | H70: шт. | I70: =I64*J70 -> 14 | J70: 8 | K70: 8 | O70: =ROUND(CP70,2) -> 1041.04 | P70: =ROUND((ROUND((AC70*AW70*I70),2)*BC70),2) -> 1041.04 | Q70: =(ROUND((ROUND(((ET70)*AV70*I70),2)*BB70),2)+ROUND((ROUND(((AE70-(EU70))*AV70*I70),2)*BS70),2)) -> 0 | R70: =ROUND((ROUND((AE70*AV70*I70),2)*BS70),2) -> 0 | S70: =ROUND((ROUND((AF70*AV70*I70),2)*BA70),2) -> 0 | T70: =ROUND(CU70*I70,2) -> 0 | U70: =CV70*I70 -> 0 | V70: =CW70*I70 -> 0 | W70: =ROUND(CX70*I70,2) -> 0 | X70: =ROUND(CY70,2) -> 0 | Y70: =ROUND(CZ70,2) -> 0 | AA70: 59204062 | AB70: =ROUND((AC70+AD70+AF70),6) -> 74.36 | AC70: =ROUND((ES70),6) -> 74.36 | AD70: =ROUND((((ET70)-(EU70))+AE70),6) -> 0 | AE70: =ROUND((EU70),6) -> 0 | AF70: =ROUND((EV70),6) -> 0 | AG70: =ROUND((AP70),6) -> 0 | AH70: =(EW70) -> 0 | AI70: =(EX70) -> 0 | AJ70: =(AS70) -> 0 | AK70: 74.36 | AL70: 74.36 | AM70: 0 | AN70: 0 | AO70: 0 | AP70: 0 | AQ70: 0 | AR70: 0 | AS70: 0 | AT70: 109 | AU70: 61 | AV70: 1 | AW70: 1 | AZ70: 1 | BA70: 1 | BB70: 1 | BC70: 1 | BH70: 3 | BI70: 1 | BJ70: ТСН-2001.1 Доп. 79, Р. 13, о. 4, поз. 63 | BM70: 21 | BN70: 0 | BP70: 0 | BQ70: 30 | BR70: 0 | BS70: 1 | BT70: 1 | BU70: 1 | BV70: 1 | BW70: 1 | BX70: 1 | BZ70: 109 | CA70: 61 | CE70: 30 | CF70: 0 | CG70: 0 | CM70: 0 | CO70: 0 | CP70: =(P70+Q70+S70) -> 1041.04 | CQ70: =ROUND((ROUND((AC70*AW70*1),2)*BC70),2) -> 74.36 | CR70: =(ROUND((ROUND(((ET70)*AV70*1),2)*BB70),2)+ROUND((ROUND(((AE70-(EU70))*AV70*1),2)*BS70),2)) -> 0 | CS70: =ROUND((ROUND((AE70*AV70*1),2)*BS70),2) -> 0 | CT70: =ROUND((ROUND((AF70*AV70*1),2)*BA70),2) -> 0 | CU70: =AG70 -> 0 | CV70: =(AH70*AV70) -> 0 | CW70: =AI70 -> 0 | CX70: =AJ70 -> 0 | CY70: =(((S70+R70)*AT70)/100) -> 0 | CZ70: =(((S70+R70)*AU70)/100) -> 0 | DN70: 0 | DO70: 0 | DP70: 1 | DQ70: 1 | DU70: 1010 | DV70: шт. | DW70: шт. | DX70: 1 | EE70: 58807897 | EF70: 30 | EG70: Строительные работы | EH70: 0 | EJ70: 1 | EK70: 21 | EL70: ТСН-2001.3-16. Трубопроводы внутренние | EM70: ТСН-2001.3-16-1 | EQ70: 0 | ER70: 74.36 | ES70: 74.36 | ET70: 0 | EU70: 0 | EV70: 0 | EW70: 0 | EX70: 0 | FQ70: 0 | FR70: 0 | FS70: 0 | FX70: 109 | FY70: 61 | GD70: 1 | GF70: -754980731 | GG70: 2 | GH70: 1 | GI70: -2 | GJ70: 0 | GK70: 0 | GL70: =ROUND(IF(AND(BH70=3,BI70=3,FS70<>0),P70,0),2) -> 0 | GM70: =ROUND(O70+X70+Y70,2)+GX70 -> 1041.04 | GN70: =IF(OR(BI70=0,BI70=1),GM70-GX70,0) -> 1041.04 | GO70: =IF(BI70=2,GM70-GX70,0) -> 0 | GP70: =IF(BI70=4,GM70-GX70,0) -> 0 | GR70: 0 | GS70: 3 | GT70: 0 | GV70: =ROUND((GT70),6) -> 0 | GW70: 1 | GX70: =ROUND(HC70*I70,2) -> 0 | HA70: 0 | HB70: 0 | HC70: =GV70*GW70 -> 0 | HS70: 0 | IK70: 0
A71: 18 | B71: 1 | C71: 130 | E71: 3,3 | F71: 1.13-4-63 | G71: Кран шаровой, латунный, никелированный, полнопроходной, с алюминиевой рукояткой, муфтовый, температура рабочей среды от -15 до +110°С, номинальное давление PN 4,0 МПа, номинальный диаметр DN 25 мм | H71: шт. | I71: =I65*J71 -> 14 | J71: 8 | K71: 8 | O71: =ROUND(CP71,2) -> 19644.42 | P71: =ROUND((ROUND((AC71*AW71*I71),2)*BC71),2) -> 19644.42 | Q71: =(ROUND((ROUND(((ET71)*AV71*I71),2)*BB71),2)+ROUND((ROUND(((AE71-(EU71))*AV71*I71),2)*BS71),2)) -> 0 | R71: =ROUND((ROUND((AE71*AV71*I71),2)*BS71),2) -> 0 | S71: =ROUND((ROUND((AF71*AV71*I71),2)*BA71),2) -> 0 | T71: =ROUND(CU71*I71,2) -> 0 | U71: =CV71*I71 -> 0 | V71: =CW71*I71 -> 0 | W71: =ROUND(CX71*I71,2) -> 0 | X71: =ROUND(CY71,2) -> 0 | Y71: =ROUND(CZ71,2) -> 0 | AA71: 59204059 | AB71: =ROUND((AC71+AD71+AF71),6) -> 74.36 | AC71: =ROUND((ES71),6) -> 74.36 | AD71: =ROUND((((ET71)-(EU71))+AE71),6) -> 0 | AE71: =ROUND((EU71),6) -> 0 | AF71: =ROUND((EV71),6) -> 0 | AG71: =ROUND((AP71),6) -> 0 | AH71: =(EW71) -> 0 | AI71: =(EX71) -> 0 | AJ71: =(AS71) -> 0 | AK71: 74.36 | AL71: 74.36 | AM71: 0 | AN71: 0 | AO71: 0 | AP71: 0 | AQ71: 0 | AR71: 0 | AS71: 0 | AT71: 109 | AU71: 61 | AV71: 1 | AW71: 1 | AZ71: 1 | BA71: 1 | BB71: 1 | BC71: 18.87 | BH71: 3 | BI71: 1 | BJ71: ТСН-2001.1 Доп. 79, Р. 13, о. 4, поз. 63 | BM71: 21 | BN71: 0 | BO71: 1.13-4-63 | BP71: 1 | BQ71: 30 | BR71: 0 | BS71: 1 | BT71: 1 | BU71: 1 | BV71: 1 | BW71: 1 | BX71: 1 | BZ71: 109 | CA71: 61 | CE71: 30 | CF71: 0 | CG71: 0 | CM71: 0 | CO71: 0 | CP71: =(P71+Q71+S71) -> 19644.42 | CQ71: =ROUND((ROUND((AC71*AW71*1),2)*BC71),2) -> 1403.17 | CR71: =(ROUND((ROUND(((ET71)*AV71*1),2)*BB71),2)+ROUND((ROUND(((AE71-(EU71))*AV71*1),2)*BS71),2)) -> 0 | CS71: =ROUND((ROUND((AE71*AV71*1),2)*BS71),2) -> 0 | CT71: =ROUND((ROUND((AF71*AV71*1),2)*BA71),2) -> 0 | CU71: =AG71 -> 0 | CV71: =(AH71*AV71) -> 0 | CW71: =AI71 -> 0 | CX71: =AJ71 -> 0 | CY71: =(((S71+R71)*AT71)/100) -> 0 | CZ71: =(((S71+R71)*AU71)/100) -> 0 | DN71: 0 | DO71: 0 | DP71: 1 | DQ71: 1 | DU71: 1010 | DV71: шт. | DW71: шт. | DX71: 1 | EE71: 58807897 | EF71: 30 | EG71: Строительные работы | EH71: 0 | EJ71: 1 | EK71: 21 | EL71: ТСН-2001.3-16. Трубопроводы внутренние | EM71: ТСН-2001.3-16-1 | EQ71: 0 | ER71: 74.36 | ES71: 74.36 | ET71: 0 | EU71: 0 | EV71: 0 | EW71: 0 | EX71: 0 | FQ71: 0 | FR71: 0 | FS71: 0 | FX71: 109 | FY71: 61 | GD71: 1 | GF71: -754980731 | GG71: 2 | GH71: 1 | GI71: 2 | GJ71: 0 | GK71: 0 | GL71: =ROUND(IF(AND(BH71=3,BI71=3,FS71<>0),P71,0),2) -> 0 | GM71: =ROUND(O71+X71+Y71,2)+GX71 -> 19644.42 | GN71: =IF(OR(BI71=0,BI71=1),GM71-GX71,0) -> 19644.42 | GO71: =IF(BI71=2,GM71-GX71,0) -> 0 | GP71: =IF(BI71=4,GM71-GX71,0) -> 0 | GR71: 0 | GS71: 3 | GT71: 0 | GV71: =ROUND((GT71),6) -> 0 | GW71: 1 | GX71: =ROUND(HC71*I71,2) -> 0 | HA71: 0 | HB71: 0 | HC71: =GV71*GW71 -> 0 | HS71: 0 | IK71: 0
A72: 17 | B72: 1 | C72: =ROW(SmtRes!A145) -> 145 | D72: =ROW(EtalonRes!A141) -> 141 | F72: 3.16-7-3 | G72: Прокладка трубопроводов водоснабжения из стальных водогазопроводных оцинкованных труб диаметром 25 мм | H72: 100 м трубопровода | I72: =ROUND(ROUND(175/100,4)*0,9) -> 0 | J72: 0 | K72: =ROUND(ROUND(175/100,4)*0,9) -> 0 | O72: =ROUND(CP72,2) -> 0 | P72: =ROUND((ROUND((AC72*AW72*I72),2)*BC72),2) -> 0 | Q72: =(ROUND((ROUND(((((ET72*1.25)*1.1))*AV72*I72),2)*BB72),2)+ROUND((ROUND(((AE72-(((EU72*1.25)*1.1)))*AV72*I72),2)*BS72),2)) -> 0 | R72: =ROUND((ROUND((AE72*AV72*I72),2)*BS72),2) -> 0 | S72: =ROUND((ROUND((AF72*AV72*I72),2)*BA72),2) -> 0 | T72: =ROUND(CU72*I72,2) -> 0 | U72: =CV72*I72 -> 0 | V72: =CW72*I72 -> 0 | W72: =ROUND(CX72*I72,2) -> 0 | X72: =ROUND(CY72,2) -> 0 | Y72: =ROUND(CZ72,2) -> 0 | AA72: -1 | AB72: =ROUND((AC72+AD72+AF72),6) -> 648.6756 | AC72: =ROUND((ES72),6) -> 45 | AD72: =ROUND((((((ET72*1.25)*1.1))-(((EU72*1.25)*1.1)))+AE72),6) -> 65.68375 | AE72: =ROUND((((EU72*1.25)*1.1)),6) -> 8.3325 | AF72: =ROUND((((EV72*1.15)*1.1)),6) -> 537.99185 | AG72: =ROUND((AP72),6) -> 0 | AH72: =(((EW72*1.15)*1.1)) -> 42.6305 | AI72: =(((EX72*1.25)*1.1)) -> 0 | AJ72: =(AS72) -> 0 | AK72: 518.06 | AL72: 45 | AM72: 47.77 | AN72: 6.06 | AO72: 425.29 | AP72: 0 | AQ72: 33.7 | AR72: 0 | AS72: 0 | AT72: 109 | AU72: 61 | AV72: 1.067 | AW72: 1 | AZ72: 1 | BA72: 1 | BB72: 1 | BC72: 1 | BH72: 0 | BI72: 1 | BJ72: ТСН-2001.3 Доп. 79, Сб. 16, т. 7, поз. 3 | BM72: 21 | BN72: 0 | BO72: 3.16-7-3 | BP72: 1 | BQ72: 30 | BR72: 0 | BS72: 1 | BT72: 1 | BU72: 1 | BV72: 1 | BW72: 1 | BX72: 1 | BZ72: 109 | CA72: 61 | CE72: 30 | CF72: 0 | CG72: 0 | CM72: 0 | CN72: Поправка: О.П. п.3.4. 6 Наименование: Выполняемые при ремонте и реконструкции работы аналогичные технологическим процессам, характерным для нового строительства и отсутствующим в сборниках на ремонтно-строительные работы Поправка: О.П. п.3.4.30.в Наименование: При применении территориальных сметных нормативов для города Москвы затраты, учитывающие напряженные и стесненные условия производства работ (стесненность, сложность складирования и транспортной логистики и т.п.), исчисляются с применением коэффициентов к затратам труда и заработной плате рабочих, машинистов, времени эксплуатации машин и механизмов, стоимости эксплуатации машин в размере: для объектов, расположенных за пределами Третьего транспортного кольца города Москвы, но в пределах Московской кольцевой автомобильной дороги | CO72: 0 | CP72: =(P72+Q72+S72) -> 0 | CQ72: =ROUND((ROUND((AC72*AW72*1),2)*BC72),2) -> 45 | CR72: =(ROUND((ROUND(((((ET72*1.25)*1.1))*AV72*1),2)*BB72),2)+ROUND((ROUND(((AE72-(((EU72*1.25)*1.1)))*AV72*1),2)*BS72),2)) -> 70.08 | CS72: =ROUND((ROUND((AE72*AV72*1),2)*BS72),2) -> 8.89 | CT72: =ROUND((ROUND((AF72*AV72*1),2)*BA72),2) -> 574.04 | CU72: =AG72 -> 0 | CV72: =(AH72*AV72) -> 45.486744 | CW72: =AI72 -> 0 | CX72: =AJ72 -> 0 | CY72: =(((S72+R72)*AT72)/100) -> 0 | CZ72: =(((S72+R72)*AU72)/100) -> 0 | DB72: 19 | DE72: *1,25)*1,1 | DF72: *1,25)*1,1 | DG72: *1,15)*1,1 | DI72: *1,15)*1,1 | DJ72: *1,25)*1,1 | DN72: 0 | DO72: 0 | DP72: 1 | DQ72: 1 | DU72: 1013 | DV72: 100 м трубопровода | DW72: 100 м трубопровода | DX72: 1 | EE72: 58807897 | EF72: 30 | EG72: Строительные работы | EH72: 0 | EJ72: 1 | EK72: 21 | EL72: ТСН-2001.3-16. Трубопроводы внутренние | EM72: ТСН-2001.3-16-1 | EO72: Поправка: О.П. п.3.4. 6 Поправка: О.П. п.3.4.30.в | EQ72: 1024 | ER72: 518.06 | ES72: 45 | ET72: 47.77 | EU72: 6.06 | EV72: 425.29 | EW72: 33.7 | EX72: 0 | EY72: 0 | FQ72: 0 | FR72: 0 | FS72: 0 | FX72: 109 | FY72: 61 | GD72: 1 | GF72: 323771770 | GG72: 2 | GH72: 1 | GI72: 2 | GJ72: 0 | GK72: 0 | GL72: =ROUND(IF(AND(BH72=3,BI72=3,FS72<>0),P72,0),2) -> 0 | GM72: =ROUND(O72+X72+Y72,2)+GX72 -> 0 | GN72: =IF(OR(BI72=0,BI72=1),GM72-GX72,0) -> 0 | GO72: =IF(BI72=2,GM72-GX72,0) -> 0 | GP72: =IF(BI72=4,GM72-GX72,0) -> 0 | GR72: 0 | GS72: 3 | GT72: 0 | GV72: =ROUND((GT72),6) -> 0 | GW72: 1 | GX72: =ROUND(HC72*I72,2) -> 0 | HA72: 0 | HB72: 0 | HC72: =GV72*GW72 -> 0 | HS72: 0 | IK72: 0
A73: 17 | B73: 1 | C73: =ROW(SmtRes!A160) -> 160 | D73: =ROW(EtalonRes!A156) -> 156 | F73: 3.16-7-3 | G73: Прокладка трубопроводов водоснабжения из стальных водогазопроводных оцинкованных труб диаметром 25 мм | H73: 100 м трубопровода | I73: =ROUND(ROUND(175/100,4)*0,9) -> 0 | J73: 0 | K73: =ROUND(ROUND(175/100,4)*0,9) -> 0 | O73: =ROUND(CP73,2) -> 0 | P73: =ROUND((ROUND((AC73*AW73*I73),2)*BC73),2) -> 0 | Q73: =(ROUND((ROUND(((((ET73*1.25)*1.1))*AV73*I73),2)*BB73),2)+ROUND((ROUND(((AE73-(((EU73*1.25)*1.1)))*AV73*I73),2)*BS73),2)) -> 0 | R73: =ROUND((ROUND((AE73*AV73*I73),2)*BS73),2) -> 0 | S73: =ROUND((ROUND((AF73*AV73*I73),2)*BA73),2) -> 0 | T73: =ROUND(CU73*I73,2) -> 0 | U73: =CV73*I73 -> 0 | V73: =CW73*I73 -> 0 | W73: =ROUND(CX73*I73,2) -> 0 | X73: =ROUND(CY73,2) -> 0 | Y73: =ROUND(CZ73,2) -> 0 | AA73: -1 | AB73: =ROUND((AC73+AD73+AF73),6) -> 648.6756 | AC73: =ROUND((ES73),6) -> 45 | AD73: =ROUND((((((ET73*1.25)*1.1))-(((EU73*1.25)*1.1)))+AE73),6) -> 65.68375 | AE73: =ROUND((((EU73*1.25)*1.1)),6) -> 8.3325 | AF73: =ROUND((((EV73*1.15)*1.1)),6) -> 537.99185 | AG73: =ROUND((AP73),6) -> 0 | AH73: =(((EW73*1.15)*1.1)) -> 42.6305 | AI73: =(((EX73*1.25)*1.1)) -> 0 | AJ73: =(AS73) -> 0 | AK73: 518.06 | AL73: 45 | AM73: 47.77 | AN73: 6.06 | AO73: 425.29 | AP73: 0 | AQ73: 33.7 | AR73: 0 | AS73: 0 | AT73: 109 | AU73: 61 | AV73: 1.067 | AW73: 1 | AZ73: 1 | BA73: 54.99 | BB73: 15.37 | BC73: 6.17 | BH73: 0 | BI73: 1 | BJ73: ТСН-2001.3 Доп. 79, Сб. 16, т. 7, поз. 3 | BM73: 21 | BN73: 0 | BO73: 3.16-7-3 | BP73: 1 | BQ73: 30 | BR73: 0 | BS73: 54.99 | BT73: 1 | BU73: 1 | BV73: 1 | BW73: 1 | BX73: 1 | BZ73: 109 | CA73: 61 | CE73: 30 | CF73: 0 | CG73: 0 | CM73: 0 | CN73: Поправка: О.П. п.3.4. 6 Наименование: Выполняемые при ремонте и реконструкции работы аналогичные технологическим процессам, характерным для нового строительства и отсутствующим в сборниках на ремонтно-строительные работы Поправка: О.П. п.3.4.30.в Наименование: При применении территориальных сметных нормативов для города Москвы затраты, учитывающие напряженные и стесненные условия производства работ (стесненность, сложность складирования и транспортной логистики и т.п.), исчисляются с применением коэффициентов к затратам труда и заработной плате рабочих, машинистов, времени эксплуатации машин и механизмов, стоимости эксплуатации машин в размере: для объектов, расположенных за пределами Третьего транспортного кольца города Москвы, но в пределах Московской кольцевой автомобильной дороги | CO73: 0 | CP73: =(P73+Q73+S73) -> 0 | CQ73: =ROUND((ROUND((AC73*AW73*1),2)*BC73),2) -> 277.65 | CR73: =(ROUND((ROUND(((((ET73*1.25)*1.1))*AV73*1),2)*BB73),2)+ROUND((ROUND(((AE73-(((EU73*1.25)*1.1)))*AV73*1),2)*BS73),2)) -> 1077.13 | CS73: =ROUND((ROUND((AE73*AV73*1),2)*BS73),2) -> 488.86 | CT73: =ROUND((ROUND((AF73*AV73*1),2)*BA73),2) -> 31566.46 | CU73: =AG73 -> 0 | CV73: =(AH73*AV73) -> 45.486744 | CW73: =AI73 -> 0 | CX73: =AJ73 -> 0 | CY73: =(((S73+R73)*AT73)/100) -> 0 | CZ73: =(((S73+R73)*AU73)/100) -> 0 | DB73: 21 | DE73: *1,25)*1,1 | DF73: *1,25)*1,1 | DG73: *1,15)*1,1 | DI73: *1,15)*1,1 | DJ73: *1,25)*1,1 | DN73: 0 | DO73: 0 | DP73: 1 | DQ73: 1 | DU73: 1013 | DV73: 100 м трубопровода | DW73: 100 м трубопровода | DX73: 1 | EE73: 58807897 | EF73: 30 | EG73: Строительные работы | EH73: 0 | EJ73: 1 | EK73: 21 | EL73: ТСН-2001.3-16. Трубопроводы внутренние | EM73: ТСН-2001.3-16-1 | EO73: Поправка: О.П. п.3.4. 6 Поправка: О.П. п.3.4.30.в | EQ73: 1024 | ER73: 518.06 | ES73: 45 | ET73: 47.77 | EU73: 6.06 | EV73: 425.29 | EW73: 33.7 | EX73: 0 | EY73: 0 | FQ73: 0 | FR73: 0 | FS73: 0 | FX73: 109 | FY73: 61 | GD73: 1 | GF73: 323771770 | GG73: 2 | GH73: 1 | GI73: 2 | GJ73: 0 | GK73: 0 | GL73: =ROUND(IF(AND(BH73=3,BI73=3,FS73<>0),P73,0),2) -> 0 | GM73: =ROUND(O73+X73+Y73,2)+GX73 -> 0 | GN73: =IF(OR(BI73=0,BI73=1),GM73-GX73,0) -> 0 | GO73: =IF(BI73=2,GM73-GX73,0) -> 0 | GP73: =IF(BI73=4,GM73-GX73,0) -> 0 | GR73: 0 | GS73: 3 | GT73: 0 | GV73: =ROUND((GT73),6) -> 0 | GW73: 1 | GX73: =ROUND(HC73*I73,2) -> 0 | HA73: 0 | HB73: 0 | HC73: =GV73*GW73 -> 0 | HS73: 0 | IK73: 0
