Workbook

Sheet 02-01-18
A1: =Source!B1 -> Smeta.RU (495) 974-1589
J2: Форма № 4б
B3: "СОГЛАСОВАНО" | G3: "УТВЕРЖДАЮ"
B6: =CONCATENATE("______________________ ", IF(Source!AL12<>"", Source!AL12, "")) -> ______________________ | G6: =CONCATENATE("______________________ ", IF(Source!AH12<>"", Source!AH12, "")) -> ______________________
B7: "_____"________________ 2026 г. | G7: "_____"________________ 2026 г.
A10: Капитальный ремонт здания ГБОУ города Москвы «Школа №236» по адресу: город Москва, улица Клязьминская, дом 7, корп. 4 1этап | AP10: Капитальный ремонт здания ГБОУ города Москвы «Школа №236» по адресу: город Москва, улица Клязьминская, дом 7, корп. 4 (ТСН-2001 (Мосгосэкспертиза))
A11: (наименование стройки и/или объекта)
A13: =CONCATENATE( "ЛОКАЛЬНАЯ СМЕТА № ",IF(Source!F20<>"Новая локальная смета", Source!F20, "")) -> ЛОКАЛЬНАЯ СМЕТА № 02-01-18
A15: =IF(Source!G20<>"Новая локальная смета", Source!G20, "") -> Автоматизация и диспетчеризация инженерных систем.
A16: (наименование работ и затрат)
A18: =CONCATENATE( "Основание: чертежи № ", Source!J20) -> Основание: чертежи № 2024-00272-01-0-ИОС5.11
I20: В базисном уровне цен | J20: В текущем уровне цен
E21: Сметная стоимость | I21: =I22+I23+I24+I25 -> 1958.58 | J21: =J22+J23+J24+J25 -> 19507.41 | K21: тыс.руб.
E22: Строительные работы | I22: =ROUND((Source!F612)/1000, 2) -> 0 | J22: =ROUND((Source!P612)/1000, 2) -> 0 | K22: тыс.руб.
E23: Работы по монтажу оборудования | I23: =ROUND((Source!F613)/1000, 2) -> 298.81 | J23: =ROUND((Source!P613)/1000, 2) -> 6896.99 | K23: тыс.руб.
E24: Оборудование | I24: =ROUND((Source!F604)/1000, 2) -> 1659.77 | J24: =ROUND((Source!P604)/1000, 2) -> 12610.42 | K24: тыс.руб.
E25: Прочие работы и затраты | I25: =ROUND((Source!F614+Source!F615)/1000, 2) -> 0 | J25: =ROUND((Source!P614+Source!P615)/1000, 2) -> 0 | K25: тыс.руб.
E26: Средства на оплату труда | I26: =(Source!F610+ Source!F609)/1000 -> 41.81744 | J26: =((Source!P610 + Source!P609)/1000) -> 2299.541 | K26: тыс.руб.
E27: Затраты труда | I27: =Source!F617 -> 3300.0132 | K27: чел.-ч.
E28: Кроме того:
E29: Возврат материалов | I29: =SUM(Y35:Y814)/1000 -> 0 | J29: =SUM(Z35:Z814)/1000 -> 0 | K29: тыс.руб.
A31: Составлен(а) по ТСН-2001 с учетом Дополнения №: 80
A32: № и период сборника коэффициентов (индексов) пересчета: Коэффициенты к ТСН-2001 МГЭ Дополнение 80, строительство №217/80 III квартал 2025 года и Коэффициенты к ТСН-2001.13-2 Дополнение 46 №62/46 III квартал 2025 года | AP32: № и период сборника коэффициентов (индексов) пересчета: Коэффициенты к ТСН-2001 МГЭ Дополнение 80, строительство №217/80 III квартал 2025 года и Коэффициенты к ТСН-2001.13-2 Дополнение 46 №62/46 III квартал 2025 года
A33: № п/п | B33: Шифр расценки и коды ресурсов | C33: Наименование работ и затрат | D33: Ед. изм. | E33: Кол-во единиц | F33: Цена на ед. изм., руб. | G33: Попра- вочные коэффи- циенты | H33: Коэффи- циенты зимних удорожа- ний | I33: Всего в ценах на январь 2000 года, руб. | J33: Коэффи- циенты (индек- сы) пере- счета, нормы НР и СП | K33: ВСЕГО затрат в текущем уровне цен, руб.
A34: 1 | B34: 2 | C34: 3 | D34: 4 | E34: 5 | F34: 6 | G34: 7 | H34: 8 | I34: 9 | J34: 10 | K34: 11
A36: =CONCATENATE("Раздел: ",IF(Source!G24<>"Новый раздел", Source!G24, "")) -> Раздел: Система управления и диспетчерского контроля инженерного
A37: 1 | B37: 4.11-7-2 Поправка: Гл.12.Прил.8.п.8. 5_12.00.01.11.003 | C37: Установка аппарата настольного массой до 0,03 т | D37: =Source!H28 -> 1 ШТ. | E37: =Source!I28 -> 1 | Q37: =Source!X28 -> 40 | R37: =Source!X29 -> 2199.38 | S37: =Source!Y28 -> 20.44 | T37: =Source!Y29 -> 1124.13 | U37: =ROUND((175/100)*ROUND(Source!R28, 2), 2) -> 8.14 | V37: =ROUND((0/100)*ROUND(Source!R29, 2), 2) -> 0 | AC37: 0
C38: ЗП | F38: =Source!AO28 -> 34.55 | G38: =Source!DG28 -> *1,1 | H38: =Source!AV29 -> 1.047 | I38: =Source!S28 -> 39.79 | J38: =IF(Source!BA29<> 0, Source!BA29, 1) -> 54.99 | K38: =Source!S29 -> 2188.05
C39: ЭМ | F39: =Source!AM28 -> 26.59 | G39: =Source!DE28 -> *1,1 | H39: =Source!AV29 -> 1.047 | I39: =Source!Q28 -> 30.62 | J39: =IF(Source!BB29<> 0, Source!BB29, 1) -> 16.3 | K39: =Source!Q29 -> 499.11
C40: в т.ч. ЗПМ | F40: =Source!AN28 -> 4.04 | G40: =Source!DF28 -> *1,1 | H40: =Source!AV29 -> 1.047 | I40: =Source!R28 -> 4.65 | J40: =IF(Source!BS29<> 0, Source!BS29, 1) -> 54.99 | K40: =Source!R29 -> 255.7
C41: НР от ФОТ | D41: % | E41: =Source!BZ29 -> 90 | I41: =SUM(Q37:Q40) -> 40 | J41: =Source!AT29 -> 90 | K41: =SUM(R37:R40) -> 2199.38
C42: СП от ФОТ | D42: % | E42: =Source!CA29 -> 46 | I42: =SUM(S37:S41) -> 20.44 | J42: =Source!AU29 -> 46 | K42: =SUM(T37:T41) -> 1124.13
C43: ЗТР | D43: чел-ч | E43: =Source!AQ28 -> 3.09 | G43: =Source!DI28 -> *1,1 | H43: =Source!AV29 -> 1.047 | I43: =Source!U28 -> 3.558753
C44: ВСЕГО работ по позиции: | H44: =I38+I39+I41+I42+0-0-0 -> 130.85 | J44: =K38+K39+K41+K42+0-0-0 -> 6010.67
C45: ВСЕГО оборудование по позиции: | H45: =0+0 -> 0 | J45: =0+0 -> 0
C46: ВСЕГО по позиции: | H46: =I38+I39+I41+I42+0 -> 130.85 | J46: =K38+K39+K41+K42+0 -> 6010.67 | O46: =I38+I39+I41+I42+0 -> 130.85 | P46: =K38+K39+K41+K42+0 -> 6010.67
A48: 2 | B48: =Source!F30 -> КА №1 | C48: ОБОРУДОВАНИЕ:_x000D_ Моноблок Lenovo V50a-24IMB 8 548,55 = [75 385 / 1,2 / 7,66] + 3% Трансп + 1,2% Заг.скл | D48: =Source!H30 -> шт. | E48: =Source!I30 -> 1 | F48: =Source!AL30 -> 8548.55 | G48: =Source!DD30 | H48: =Source!AW31 -> 1 | I48: =Source!P30 -> 8548.55 | J48: =IF(Source!BC31<> 0, Source!BC31, 1) -> 7.66 | K48: =Source!P31 -> 65481.89 | Q48: =Source!X30 -> 0 | R48: =Source!X31 -> 0 | S48: =Source!Y30 -> 0 | T48: =Source!Y31 -> 0 | U48: =ROUND((175/100)*ROUND(Source!R30, 2), 2) -> 0 | V48: =ROUND((0/100)*ROUND(Source!R31, 2), 2) -> 0 | AC48: 5
C49: ВСЕГО по позиции: | H49: =I48+0 -> 8548.55 | J49: =K48+0 -> 65481.89 | O49: =I48+0 -> 8548.55 | P49: =K48+0 -> 65481.89
A51: 3 | B51: 4.10-118-5 Поправка: Гл.12.Прил.8.п.8. 5_12.00.01.11.003 | C51: Установка для трубных проводок шкафа настенного размерами до 640х840 мм | D51: =Source!H32 -> 1 ШТ. | E51: =Source!I32 -> 1 | Q51: =Source!X32 -> 24.91 | R51: =Source!X33 -> 1369.92 | S51: =Source!Y32 -> 12.73 | T51: =Source!Y33 -> 700.18 | U51: =ROUND((175/100)*ROUND(Source!R32, 2), 2) -> 0.51 | V51: =ROUND((0/100)*ROUND(Source!R33, 2), 2) -> 0 | AC51: 0
C52: ЗП | F52: =Source!AO32 -> 23.78 | G52: =Source!DG32 -> *1,1 | H52: =Source!AV33 -> 1.047 | I52: =Source!S32 -> 27.39 | J52: =IF(Source!BA33<> 0, Source!BA33, 1) -> 54.99 | K52: =Source!S33 -> 1506.18
C53: ЭМ | F53: =Source!AM32 -> 2.38 | G53: =Source!DE32 -> *1,1 | H53: =Source!AV33 -> 1.047 | I53: =Source!Q32 -> 2.74 | J53: =IF(Source!BB33<> 0, Source!BB33, 1) -> 13.99 | K53: =Source!Q33 -> 38.33
C54: в т.ч. ЗПМ | F54: =Source!AN32 -> 0.25 | G54: =Source!DF32 -> *1,1 | H54: =Source!AV33 -> 1.047 | I54: =Source!R32 -> 0.29 | J54: =IF(Source!BS33<> 0, Source!BS33, 1) -> 54.99 | K54: =Source!R33 -> 15.95
C55: МР | F55: =Source!AL32 -> 109.01 | G55: =Source!DD32 | H55: =Source!AW33 -> 1 | I55: =Source!P32 -> 109.01 | J55: =IF(Source!BC33<> 0, Source!BC33, 1) -> 3.26 | K55: =Source!P33 -> 355.37
A56: 3,1 | B56: =Source!F34 -> 1.21-1-63 | C56: Щит навесной, с дверцей и замком, степень защиты IР55, размер 600х600х250 мм, металлоконструкция без аппаратов | D56: =Source!H34 -> шт. | E56: =Source!I34 -> 1 | F56: =Source!AK34 -> 1975.19 | H56: =Source!AW35 -> 1 | I56: =Source!O34 -> 1975.19 | J56: =IF(Source!BC35<> 0, Source!BC35, 1) -> 6.86 | K56: =Source!O35 -> 13549.8 | Q56: =Source!X34 -> 0 | R56: =Source!X35 -> 0 | S56: =Source!Y34 -> 0 | T56: =Source!Y35 -> 0 | U56: =ROUND((175/100)*ROUND(Source!R34, 2), 2) -> 0 | V56: =ROUND((0/100)*ROUND(Source!R35, 2), 2) -> 0 | AC56: 3
C57: НР от ФОТ | D57: % | E57: =Source!BZ33 -> 90 | I57: =SUM(Q51:Q56) -> 24.91 | J57: =Source!AT33 -> 90 | K57: =SUM(R51:R56) -> 1369.92
C58: СП от ФОТ | D58: % | E58: =Source!CA33 -> 46 | I58: =SUM(S51:S57) -> 12.73 | J58: =Source!AU33 -> 46 | K58: =SUM(T51:T57) -> 700.18
C59: ЗТР | D59: чел-ч | E59: =Source!AQ32 -> 2 | G59: =Source!DI32 -> *1,1 | H59: =Source!AV33 -> 1.047 | I59: =Source!U32 -> 2.3034
C60: ВСЕГО работ по позиции: | H60: =I52+I53+I55+I57+I58+SUM(I56:I56)-SUMIF(AC56:AC56, 5, I56:I56)-SUMIF(AC56:AC56, 6, I56:I56) -> 2151.97 | J60: =K52+K53+K55+K57+K58+SUM(K56:K56)-SUMIF(AC56:AC56, 5, K56:K56)-SUMIF(AC56:AC56, 6, K56:K56) -> 17519.78
C61: ВСЕГО оборудование по позиции: | H61: =SUMIF(AC56:AC56, 5, I56:I56)+SUMIF(AC56:AC56, 6, I56:I56) -> 0 | J61: =SUMIF(AC56:AC56, 5, K56:K56)+SUMIF(AC56:AC56, 6, K56:K56) -> 0
C62: ВСЕГО по позиции: | H62: =I52+I53+I55+I57+I58+SUM(I56:I56) -> 2151.97 | J62: =K52+K53+K55+K57+K58+SUM(K56:K56) -> 17519.78 | O62: =I52+I53+I55+I57+I58+SUM(I56:I56) -> 2151.97 | P62: =K52+K53+K55+K57+K58+SUM(K56:K56) -> 17519.78
A64: 4 | B64: 4.11-12-1 Поправка: Гл.12.Прил.8.п.8. 5_12.00.01.11.003 | C64: Установка съемных и выдвижных блоков (модулей, ячеек, ТЭЗ) массой до 5 кг | D64: =Source!H36 -> 1 ШТ. | E64: =Source!I36 -> 1 | Q64: =Source!X36 -> 12.16 | R64: =Source!X37 -> 668.63 | S64: =Source!Y36 -> 6.21 | T64: =Source!Y37 -> 341.74 | U64: =ROUND((175/100)*ROUND(Source!R36, 2), 2) -> 0.16 | V64: =ROUND((0/100)*ROUND(Source!R37, 2), 2) -> 0 | AC64: 0
C65: ЗП | F65: =Source!AO36 -> 11.65 | G65: =Source!DG36 -> *1,1 | H65: =Source!AV37 -> 1.047 | I65: =Source!S36 -> 13.42 | J65: =IF(Source!BA37<> 0, Source!BA37, 1) -> 54.99 | K65: =Source!S37 -> 737.97
C66: ЭМ | F66: =Source!AM36 -> 0.5 | G66: =Source!DE36 -> *1,1 | H66: =Source!AV37 -> 1.047 | I66: =Source!Q36 -> 0.58 | J66: =IF(Source!BB37<> 0, Source!BB37, 1) -> 16.26 | K66: =Source!Q37 -> 9.43
C67: в т.ч. ЗПМ | F67: =Source!AN36 -> 0.08 | G67: =Source!DF36 -> *1,1 | H67: =Source!AV37 -> 1.047 | I67: =Source!R36 -> 0.09 | J67: =IF(Source!BS37<> 0, Source!BS37, 1) -> 54.99 | K67: =Source!R37 -> 4.95
C68: НР от ФОТ | D68: % | E68: =Source!BZ37 -> 90 | I68: =SUM(Q64:Q67) -> 12.16 | J68: =Source!AT37 -> 90 | K68: =SUM(R64:R67) -> 668.63
C69: СП от ФОТ | D69: % | E69: =Source!CA37 -> 46 | I69: =SUM(S64:S68) -> 6.21 | J69: =Source!AU37 -> 46 | K69: =SUM(T64:T68) -> 341.74
C70: ЗТР | D70: чел-ч | E70: =Source!AQ36 -> 1.03 | G70: =Source!DI36 -> *1,1 | H70: =Source!AV37 -> 1.047 | I70: =Source!U36 -> 1.186251
C71: ВСЕГО работ по позиции: | H71: =I65+I66+I68+I69+0-0-0 -> 32.37 | J71: =K65+K66+K68+K69+0-0-0 -> 1757.77
C72: ВСЕГО оборудование по позиции: | H72: =0+0 -> 0 | J72: =0+0 -> 0
C73: ВСЕГО по позиции: | H73: =I65+I66+I68+I69+0 -> 32.37 | J73: =K65+K66+K68+K69+0 -> 1757.77 | O73: =I65+I66+I68+I69+0 -> 32.37 | P73: =K65+K66+K68+K69+0 -> 1757.77
A75: 5 | B75: =Source!F38 -> КА №2 | C75: ОБОРУДОВАНИЕ:_x000D_ Шлюз tGW-715i Segnetics 1 618,36 = [14 271,44 / 1,2 / 7,66] + 3% Трансп + 1,2% Заг.скл | D75: =Source!H38 -> шт. | E75: =Source!I38 -> 1 | F75: =Source!AL38 -> 1618.36 | G75: =Source!DD38 | H75: =Source!AW39 -> 1 | I75: =Source!P38 -> 1618.36 | J75: =IF(Source!BC39<> 0, Source!BC39, 1) -> 7.66 | K75: =Source!P39 -> 12396.64 | Q75: =Source!X38 -> 0 | R75: =Source!X39 -> 0 | S75: =Source!Y38 -> 0 | T75: =Source!Y39 -> 0 | U75: =ROUND((175/100)*ROUND(Source!R38, 2), 2) -> 0 | V75: =ROUND((0/100)*ROUND(Source!R39, 2), 2) -> 0 | AC75: 5
C76: ВСЕГО по позиции: | H76: =I75+0 -> 1618.36 | J76: =K75+0 -> 12396.64 | O76: =I75+0 -> 1618.36 | P76: =K75+0 -> 12396.64
A78: 6 | B78: 4.10-176-1 Поправка: Гл.12.Прил.8.п.8. 5_12.00.01.11.003 | C78: Монтаж блока контроля датчиков (контроллер) | D78: =Source!H40 -> 10 шт. | E78: =Source!I40 -> 0.1 | Q78: =Source!X40 -> 48.83 | R78: =Source!X41 -> 2684.89 | S78: =Source!Y40 -> 24.96 | T78: =Source!Y41 -> 1372.28 | U78: =ROUND((175/100)*ROUND(Source!R40, 2), 2) -> 0.02 | V78: =ROUND((0/100)*ROUND(Source!R41, 2), 2) -> 0 | AC78: 0
C79: ="Объем: "&Source!I40&"=1/"&"10" -> Объем: 0,1=1/10
C80: ЗП | F80: =Source!AO40 -> 470.94 | G80: =Source!DG40 -> *1,1 | H80: =Source!AV41 -> 1.047 | I80: =Source!S40 -> 54.24 | J80: =IF(Source!BA41<> 0, Source!BA41, 1) -> 54.99 | K80: =Source!S41 -> 2982.66
C81: ЭМ | F81: =Source!AM40 -> 1.1 | G81: =Source!DE40 -> *1,1 | H81: =Source!AV41 -> 1.047 | I81: =Source!Q40 -> 0.13 | J81: =IF(Source!BB41<> 0, Source!BB41, 1) -> 14.48 | K81: =Source!Q41 -> 1.88
C82: в т.ч. ЗПМ | F82: =Source!AN40 -> 0.13 | G82: =Source!DF40 -> *1,1 | H82: =Source!AV41 -> 1.047 | I82: =Source!R40 -> 0.01 | J82: =IF(Source!BS41<> 0, Source!BS41, 1) -> 54.99 | K82: =Source!R41 -> 0.55
C83: МР | F83: =Source!AL40 -> 1.29 | G83: =Source!DD40 | H83: =Source!AW41 -> 1 | I83: =Source!P40 -> 0.13 | J83: =IF(Source!BC41<> 0, Source!BC41, 1) -> 7.25 | K83: =Source!P41 -> 0.94
C84: НР от ФОТ | D84: % | E84: =Source!BZ41 -> 90 | I84: =SUM(Q78:Q83) -> 48.83 | J84: =Source!AT41 -> 90 | K84: =SUM(R78:R83) -> 2684.89
C85: СП от ФОТ | D85: % | E85: =Source!CA41 -> 46 | I85: =SUM(S78:S84) -> 24.96 | J85: =Source!AU41 -> 46 | K85: =SUM(T78:T84) -> 1372.28
C86: ЗТР | D86: чел-ч | E86: =Source!AQ40 -> 29.96 | G86: =Source!DI40 -> *1,1 | H86: =Source!AV41 -> 1.047 | I86: =Source!U40 -> 3.4504932
C87: ВСЕГО работ по позиции: | H87: =I80+I81+I83+I84+I85+0-0-0 -> 128.29 | J87: =K80+K81+K83+K84+K85+0-0-0 -> 7042.65
C88: ВСЕГО оборудование по позиции: | H88: =0+0 -> 0 | J88: =0+0 -> 0
C89: ВСЕГО по позиции: | H89: =I80+I81+I83+I84+I85+0 -> 128.29 | J89: =K80+K81+K83+K84+K85+0 -> 7042.65 | O89: =I80+I81+I83+I84+I85+0 -> 128.29 | P89: =K80+K81+K83+K84+K85+0 -> 7042.65
A91: 7 | B91: =Source!F42 -> КА №3 | C91: ОБОРУДОВАНИЕ:_x000D_ Контроллер Matrix-2230-70-0 Segnetics 3 784,21 = [33 370,9 / 1,2 / 7,66] + 3% Трансп + 1,2% Заг.скл | D91: =Source!H42 -> шт. | E91: =Source!I42 -> 1 | F91: =Source!AL42 -> 3784.21 | G91: =Source!DD42 | H91: =Source!AW43 -> 1 | I91: =Source!P42 -> 3784.21 | J91: =IF(Source!BC43<> 0, Source!BC43, 1) -> 7.66 | K91: =Source!P43 -> 28987.05 | Q91: =Source!X42 -> 0 | R91: =Source!X43 -> 0 | S91: =Source!Y42 -> 0 | T91: =Source!Y43 -> 0 | U91: =ROUND((175/100)*ROUND(Source!R42, 2), 2) -> 0 | V91: =ROUND((0/100)*ROUND(Source!R43, 2), 2) -> 0 | AC91: 5
C92: ВСЕГО по позиции: | H92: =I91+0 -> 3784.21 | J92: =K91+0 -> 28987.05 | O92: =I91+0 -> 3784.21 | P92: =K91+0 -> 28987.05
A94: 8 | B94: 4.11-12-1 Поправка: Гл.12.Прил.8.п.8. 5_12.00.01.11.003 | C94: Установка съемных и выдвижных блоков (модулей, ячеек, ТЭЗ) массой до 5 кг | D94: =Source!H44 -> 1 ШТ. | E94: =Source!I44 -> 2 | Q94: =Source!X44 -> 24.31 | R94: =Source!X45 -> 1336.75 | S94: =Source!Y44 -> 12.42 | T94: =Source!Y45 -> 683.23 | U94: =ROUND((175/100)*ROUND(Source!R44, 2), 2) -> 0.32 | V94: =ROUND((0/100)*ROUND(Source!R45, 2), 2) -> 0 | AC94: 0
C95: ЗП | F95: =Source!AO44 -> 11.65 | G95: =Source!DG44 -> *1,1 | H95: =Source!AV45 -> 1.047 | I95: =Source!S44 -> 26.83 | J95: =IF(Source!BA45<> 0, Source!BA45, 1) -> 54.99 | K95: =Source!S45 -> 1475.38
C96: ЭМ | F96: =Source!AM44 -> 0.5 | G96: =Source!DE44 -> *1,1 | H96: =Source!AV45 -> 1.047 | I96: =Source!Q44 -> 1.15 | J96: =IF(Source!BB45<> 0, Source!BB45, 1) -> 16.26 | K96: =Source!Q45 -> 18.7
C97: в т.ч. ЗПМ | F97: =Source!AN44 -> 0.08 | G97: =Source!DF44 -> *1,1 | H97: =Source!AV45 -> 1.047 | I97: =Source!R44 -> 0.18 | J97: =IF(Source!BS45<> 0, Source!BS45, 1) -> 54.99 | K97: =Source!R45 -> 9.9
C98: НР от ФОТ | D98: % | E98: =Source!BZ45 -> 90 | I98: =SUM(Q94:Q97) -> 24.31 | J98: =Source!AT45 -> 90 | K98: =SUM(R94:R97) -> 1336.75
C99: СП от ФОТ | D99: % | E99: =Source!CA45 -> 46 | I99: =SUM(S94:S98) -> 12.42 | J99: =Source!AU45 -> 46 | K99: =SUM(T94:T98) -> 683.23
C100: ЗТР | D100: чел-ч | E100: =Source!AQ44 -> 1.03 | G100: =Source!DI44 -> *1,1 | H100: =Source!AV45 -> 1.047 | I100: =Source!U44 -> 2.372502
C101: ВСЕГО работ по позиции: | H101: =I95+I96+I98+I99+0-0-0 -> 64.71 | J101: =K95+K96+K98+K99+0-0-0 -> 3514.06
C102: ВСЕГО оборудование по позиции: | H102: =0+0 -> 0 | J102: =0+0 -> 0
C103: ВСЕГО по позиции: | H103: =I95+I96+I98+I99+0 -> 64.71 | J103: =K95+K96+K98+K99+0 -> 3514.06 | O103: =I95+I96+I98+I99+0 -> 64.71 | P103: =K95+K96+K98+K99+0 -> 3514.06
A105: 9 | B105: =Source!F46 -> КА №4 | C105: ОБОРУДОВАНИЕ:_x000D_ модуль сбора сигналов FMR-2222-10-0 Segnetics 1 475,55 = [13 012 / 1,2 / 7,66] + 3% Трансп + 1,2% Заг.скл | D105: =Source!H46 -> шт. | E105: =Source!I46 -> 2 | F105: =Source!AL46 -> 1475.55 | G105: =Source!DD46 | H105: =Source!AW47 -> 1 | I105: =Source!P46 -> 2951.1 | J105: =IF(Source!BC47<> 0, Source!BC47, 1) -> 7.66 | K105: =Source!P47 -> 22605.43 | Q105: =Source!X46 -> 0 | R105: =Source!X47 -> 0 | S105: =Source!Y46 -> 0 | T105: =Source!Y47 -> 0 | U105: =ROUND((175/100)*ROUND(Source!R46, 2), 2) -> 0 | V105: =ROUND((0/100)*ROUND(Source!R47, 2), 2) -> 0 | AC105: 5
C106: ВСЕГО по позиции: | H106: =I105+0 -> 2951.1 | J106: =K105+0 -> 22605.43 | O106: =I105+0 -> 2951.1 | P106: =K105+0 -> 22605.43
A108: 10 | B108: 4.11-12-1 Поправка: Гл.12.Прил.8.п.8. 5_12.00.01.11.003 | C108: Установка съемных и выдвижных блоков (модулей, ячеек, ТЭЗ) массой до 5 кг | D108: =Source!H48 -> 1 ШТ. | E108: =Source!I48 -> 1 | Q108: =Source!X48 -> 12.16 | R108: =Source!X49 -> 668.63 | S108: =Source!Y48 -> 6.21 | T108: =Source!Y49 -> 341.74 | U108: =ROUND((175/100)*ROUND(Source!R48, 2), 2) -> 0.16 | V108: =ROUND((0/100)*ROUND(Source!R49, 2), 2) -> 0 | AC108: 0
C109: ЗП | F109: =Source!AO48 -> 11.65 | G109: =Source!DG48 -> *1,1 | H109: =Source!AV49 -> 1.047 | I109: =Source!S48 -> 13.42 | J109: =IF(Source!BA49<> 0, Source!BA49, 1) -> 54.99 | K109: =Source!S49 -> 737.97
C110: ЭМ | F110: =Source!AM48 -> 0.5 | G110: =Source!DE48 -> *1,1 | H110: =Source!AV49 -> 1.047 | I110: =Source!Q48 -> 0.58 | J110: =IF(Source!BB49<> 0, Source!BB49, 1) -> 16.26 | K110: =Source!Q49 -> 9.43
C111: в т.ч. ЗПМ | F111: =Source!AN48 -> 0.08 | G111: =Source!DF48 -> *1,1 | H111: =Source!AV49 -> 1.047 | I111: =Source!R48 -> 0.09 | J111: =IF(Source!BS49<> 0, Source!BS49, 1) -> 54.99 | K111: =Source!R49 -> 4.95
C112: НР от ФОТ | D112: % | E112: =Source!BZ49 -> 90 | I112: =SUM(Q108:Q111) -> 12.16 | J112: =Source!AT49 -> 90 | K112: =SUM(R108:R111) -> 668.63
C113: СП от ФОТ | D113: % | E113: =Source!CA49 -> 46 | I113: =SUM(S108:S112) -> 6.21 | J113: =Source!AU49 -> 46 | K113: =SUM(T108:T112) -> 341.74
C114: ЗТР | D114: чел-ч | E114: =Source!AQ48 -> 1.03 | G114: =Source!DI48 -> *1,1 | H114: =Source!AV49 -> 1.047 | I114: =Source!U48 -> 1.186251
C115: ВСЕГО работ по позиции: | H115: =I109+I110+I112+I113+0-0-0 -> 32.37 | J115: =K109+K110+K112+K113+0-0-0 -> 1757.77
C116: ВСЕГО оборудование по позиции: | H116: =0+0 -> 0 | J116: =0+0 -> 0
C117: ВСЕГО по позиции: | H117: =I109+I110+I112+I113+0 -> 32.37 | J117: =K109+K110+K112+K113+0 -> 1757.77 | O117: =I109+I110+I112+I113+0 -> 32.37 | P117: =K109+K110+K112+K113+0 -> 1757.77
A119: 11 | B119: =Source!F50 -> КА №5 | C119: ОБОРУДОВАНИЕ:_x000D_ ИБП SKAT-UPS 1000 Segnetics 8 137,48 = [71 760 / 1,2 / 7,66] + 3% Трансп + 1,2% Заг.скл | D119: =Source!H50 -> шт. | E119: =Source!I50 -> 1 | F119: =Source!AL50 -> 8137.48 | G119: =Source!DD50 | H119: =Source!AW51 -> 1 | I119: =Source!P50 -> 8137.48 | J119: =IF(Source!BC51<> 0, Source!BC51, 1) -> 7.66 | K119: =Source!P51 -> 62333.1 | Q119: =Source!X50 -> 0 | R119: =Source!X51 -> 0 | S119: =Source!Y50 -> 0 | T119: =Source!Y51 -> 0 | U119: =ROUND((175/100)*ROUND(Source!R50, 2), 2) -> 0 | V119: =ROUND((0/100)*ROUND(Source!R51, 2), 2) -> 0 | AC119: 5
C120: ВСЕГО по позиции: | H120: =I119+0 -> 8137.48 | J120: =K119+0 -> 62333.1 | O120: =I119+0 -> 8137.48 | P120: =K119+0 -> 62333.1
...

Sheet Ведомость объемов работ
A1: =Source!B1 -> Smeta.RU (495) 974-1589
E3: "УТВЕРЖДАЮ"
D5: ___________________________
D7: ___________________________
D9: " ___ " ___________ 20 ___ г.
B12: =CONCATENATE("Ведомость объемов работ ", IF(Source!AN15<>"", Source!AN15," ")) -> Ведомость объемов работ
B13: =CONCATENATE("",Source!G12) -> Капитальный ремонт здания ГБОУ города Москвы «Школа №236» по адресу: город Москва, улица Клязьминская, дом 7, корп. 4 | AE13: =CONCATENATE(Source!F12, " ", Source!G12) -> Новый объект (ТСН-2001 (Мосгосэкспертиза)) Капитальный ремонт здания ГБОУ города Москвы «Школа №236» по адресу: город Москва, улица Клязьминская, дом 7, корп. 4
A16: № п/п | B16: № в ЛСР | C16: Наименование работ и затрат | D16: Единица измерения | E16: Количество | F16: Ссылка на чертежи, спецификации | G16: Формула расчета, расчет объемов работ и расхода материалов | H16: Примечание
A17: 1 | B17: 2 | C17: 3 | D17: 4 | E17: 5 | F17: 6 | G17: 7 | H17: 8
A18: =CONCATENATE("Локальная смета: ", Source!G20) -> Локальная смета: Автоматизация и диспетчеризация инженерных систем.
A19: =CONCATENATE("Раздел: ", Source!G24) -> Раздел: Система управления и диспетчерского контроля инженерного
A20: 1 | B20: =Source!E28 -> 1 | C20: =Source!G28 -> Установка аппарата настольного массой до 0,03 т | D20: 1 ШТ. | E20: =Source!I28 -> 1 | F20: =Source!U24 | G20: =Source!I28 -> 1
A21: 2 | B21: =Source!E30 -> 2 | C21: =Source!G30 -> Моноблок Lenovo V50a-24IMB | D21: шт. | E21: =Source!I30 -> 1 | F21: =Source!U24 | G21: =Source!I30 -> 1
A22: 3 | B22: =Source!E32 -> 3 | C22: =Source!G32 -> Установка для трубных проводок шкафа настенного размерами до 640х840 мм | D22: 1 ШТ. | E22: =Source!I32 -> 1 | F22: =Source!U24 | G22: =Source!I32 -> 1
A23: 3.1 | B23: =Source!E34 -> 3,1 | C23: =Source!G34 -> Щит навесной, с дверцей и замком, степень защиты IР55, размер 600х600х250 мм, металлоконструкция без аппаратов | D23: шт. | E23: =Source!I34 -> 1 | F23: =Source!U24
A24: 4 | B24: =Source!E36 -> 4 | C24: =Source!G36 -> Установка съемных и выдвижных блоков (модулей, ячеек, ТЭЗ) массой до 5 кг | D24: 1 ШТ. | E24: =Source!I36 -> 1 | F24: =Source!U24 | G24: =Source!I36 -> 1
A25: 5 | B25: =Source!E38 -> 5 | C25: =Source!G38 -> Шлюз tGW-715i Segnetics | D25: шт. | E25: =Source!I38 -> 1 | F25: =Source!U24 | G25: =Source!I38 -> 1
A26: 6 | B26: =Source!E40 -> 6 | C26: =Source!G40 -> Монтаж блока контроля датчиков (контроллер) | D26: 10 шт. | E26: =Source!I40 -> 0.1 | F26: =Source!U24 | G26: ="=1/"&"10" -> =1/10
A27: 7 | B27: =Source!E42 -> 7 | C27: =Source!G42 -> Контроллер Matrix-2230-70-0 Segnetics | D27: шт. | E27: =Source!I42 -> 1 | F27: =Source!U24 | G27: =Source!I42 -> 1
A28: 8 | B28: =Source!E44 -> 8 | C28: =Source!G44 -> Установка съемных и выдвижных блоков (модулей, ячеек, ТЭЗ) массой до 5 кг | D28: 1 ШТ. | E28: =Source!I44 -> 2 | F28: =Source!U24 | G28: =Source!I44 -> 2
A29: 9 | B29: =Source!E46 -> 9 | C29: =Source!G46 -> модуль сбора сигналов FMR-2222-10-0 Segnetics | D29: шт. | E29: =Source!I46 -> 2 | F29: =Source!U24 | G29: =Source!I46 -> 2
A30: 10 | B30: =Source!E48 -> 10 | C30: =Source!G48 -> Установка съемных и выдвижных блоков (модулей, ячеек, ТЭЗ) массой до 5 кг | D30: 1 ШТ. | E30: =Source!I48 -> 1 | F30: =Source!U24 | G30: =Source!I48 -> 1
A31: 11 | B31: =Source!E50 -> 11 | C31: =Source!G50 -> ИБП SKAT-UPS 1000 Segnetics | D31: шт. | E31: =Source!I50 -> 1 | F31: =Source!U24 | G31: =Source!I50 -> 1
A32: 12 | B32: =Source!E52 -> 12 | C32: =Source!G52 -> Трубы гофрированные поливинилхлоридные наружным диаметром 20 мм открыто по стенам и потолкам с установкой соединительных коробок | D32: 100 м | E32: =Source!I52 -> 23 | F32: =Source!U24 | G32: ="=2300/"&"100" -> =2300/100
A33: 12.1 | B33: =Source!E54 -> 12,1 | C33: =Source!G54 -> Трубы электротехнические, гофрированные, из ПВХ, негорючие, с зондом, наружный диаметр 20 мм | D33: м | E33: =Source!I54 -> 2346 | F33: =Source!U24
A34: 13 | B34: =Source!E56 -> 13 | C34: =Source!G56 -> Прокладка пластикового кабель-канала по кирпичному основанию | D34: 100 м | E34: =Source!I56 -> 2 | F34: =Source!U24 | G34: ="=200/"&"100" -> =200/100
A35: 13.1 | B35: =Source!E58 -> 13,1 | C35: =Source!G58 -> Кабель-канал, размер 10х15 мм | D35: м | E35: =Source!I58 -> 200 | F35: =Source!U24
A36: 14 | B36: =Source!E60 -> 14 | C36: =Source!G60 -> Затягивание провода в проложенные трубы и металлические рукава, первого одножильного или многожильного в общей оплетке, суммарное сечение до 2,5 мм2 | D36: 100 м | E36: =Source!I60 -> 10 | F36: =Source!U24 | G36: ="=1000/"&"100" -> =1000/100
A37: 14.1 | B37: =Source!E62 -> 14,1 | C37: =Source!G62 -> Кабель КПСЭнг(A)-LSLTx 1х2х0,75 | D37: м.п. | E37: =Source!I62 -> 1020 | F37: =Source!U24
A38: 15 | B38: =Source!E64 -> 15 | C38: =Source!G64 -> Затягивание провода в проложенные трубы и металлические рукава, первого одножильного или многожильного в общей оплетке, суммарное сечение до 2,5 мм2 | D38: 100 м | E38: =Source!I64 -> 13 | F38: =Source!U24 | G38: ="=1300/"&"100" -> =1300/100
A39: 15.1 | B39: =Source!E66 -> 15,1 | C39: =Source!G66 -> Кабель симметричный, парной скрутки, с изоляцией из сплошного полиэтилена, с общим экраном, в оболочке из ПВХ пластиката пониженной пожароопасности, с низким дымо- и газовыделением, марка КИПЭВнг(А)-LS, число пар и сечение жилы 2х2х0,6 мм2 | D39: км | E39: =Source!I66 -> 1.326 | F39: =Source!U24
A40: 16 | B40: =Source!E70 -> 16 | C40: =Source!G70 -> Прокладка в коробах провода сечением до 6 мм2 | D40: 100 м | E40: =Source!I70 -> 2 | F40: =Source!U24 | G40: ="=200/"&"100" -> =200/100
A41: 16.1 | B41: =Source!E72 -> 16,1 | C41: =Source!G72 -> Кабель симметричный, парной скрутки, с изоляцией из сплошного полиэтилена, с общим экраном, в оболочке из ПВХ пластиката пониженной пожароопасности, с низким дымо- и газовыделением, марка КИПЭВнг(А)-LS, число пар и сечение жилы 2х2х0,6 мм2 | D41: км | E41: =Source!I72 -> 0.204 | F41: =Source!U24
A42: =CONCATENATE("Раздел: ", Source!G105) -> Раздел: Программное обеспечение
A43: 17 | B43: =Source!E109 -> 17 | C43: =Source!G109 -> Исполнительная SCADA-система на 1000 внешних точек ввода-вывода MPS-MSRT4D-1K-S | D43: шт. | E43: =Source!I109 -> 1 | F43: =Source!U105 | G43: =Source!I109 -> 1
A44: 18 | B44: =Source!E111 -> 18 | C44: =Source!G111 -> OPC-сервер на одно рабочее место на 2500 точек. Universal Master OPC Server | D44: шт. | E44: =Source!I111 -> 1 | F44: =Source!U105 | G44: =Source!I111 -> 1
A45: =CONCATENATE("Раздел: ", Source!G144) -> Раздел: Диспетчеризация систем водоснабжения и канализации
A46: 19 | B46: =Source!E148 -> 19 | C46: =Source!G148 -> Монтаж детали на пультах и панелях - реле | D46: 1 ШТ. | E46: =Source!I148 -> 2 | F46: =Source!U144 | G46: =Source!I148 -> 2
A47: 20 | B47: =Source!E150 -> 20 | C47: =Source!G150 -> Датчик-реле уровня РОС301 | D47: шт. | E47: =Source!I150 -> 2 | F47: =Source!U144 | G47: =Source!I150 -> 2
A48: 21 | B48: =Source!E152 -> 21 | C48: =Source!G152 -> Трубы гофрированные поливинилхлоридные наружным диаметром 20 мм открыто по стенам и потолкам с установкой соединительных коробок | D48: 100 м | E48: =Source!I152 -> 1 | F48: =Source!U144 | G48: ="=100/"&"100" -> =100/100
A49: 21.1 | B49: =Source!E154 -> 21,1 | C49: =Source!G154 -> Трубы электротехнические, гофрированные, из ПВХ, негорючие, с зондом, наружный диаметр 20 мм | D49: м | E49: =Source!I154 -> 102 | F49: =Source!U144
A50: 22 | B50: =Source!E156 -> 22 | C50: =Source!G156 -> Затягивание провода в проложенные трубы и металлические рукава, первого одножильного или многожильного в общей оплетке, суммарное сечение до 2,5 мм2 | D50: 100 м | E50: =Source!I156 -> 1 | F50: =Source!U144 | G50: ="=100/"&"100" -> =100/100
A51: 22.1 | B51: =Source!E160 -> 22,2 | C51: =Source!G160 -> Кабель КПСнг(A)-LSLTx 1х2х0,75 | D51: м.п. | E51: =Source!I160 -> 102 | F51: =Source!U144
A52: =CONCATENATE("Раздел: ", Source!G193) -> Раздел: Автоматизация противопожарных мероприятий
A53: 23 | B53: =Source!E197 -> 23 | C53: =Source!G197 -> Аппараты приемные, приборы приемно-контрольные объектовые на 2 луча | D53: 1 ШТ. | E53: =Source!I197 -> 1 | F53: =Source!U193 | G53: =Source!I197 -> 1
A54: 24 | B54: =Source!E199 -> 24 | C54: =Source!G199 -> Прибор приемно-контрольный и управления охранно-пожарный R3-Рубеж-2ОП | D54: шт. | E54: =Source!I199 -> 1 | F54: =Source!U193 | G54: =Source!I199 -> 1
A55: 25 | B55: =Source!E201 -> 25 | C55: =Source!G201 -> Установка съемных и выдвижных блоков (модулей, ячеек, ТЭЗ) массой до 5 кг | D55: 1 ШТ. | E55: =Source!I201 -> 186 | F55: =Source!U193 | G55: =Source!I201 -> 186
A56: 26 | B56: =Source!E203 -> 26 | C56: =Source!G203 -> Модуль управления клапаном МДУ-1С прот.R3 МДУ-1С-R3 | D56: шт. | E56: =Source!I203 -> 186 | F56: =Source!U193 | G56: =Source!I203 -> 186
A57: 27 | B57: =Source!E205 -> 27 | C57: =Source!G205 -> Аппараты приемные, устройства промежуточные на 1 луч | D57: 1 ШТ. | E57: =Source!I205 -> 17 | F57: =Source!U193 | G57: =Source!I205 -> 17
A58: 28 | B58: =Source!E207 -> 28 | C58: =Source!G207 -> Модуль релейный РМ-1К прот.R3 РМ-1К-R3 | D58: шт. | E58: =Source!I207 -> 13 | F58: =Source!U193 | G58: =Source!I207 -> 13
A59: 29 | B59: =Source!E209 -> 29 | C59: =Source!G209 -> Модуль релейный РМ-4 прот.R3 РМ-4-R3 | D59: шт. | E59: =Source!I209 -> 4 | F59: =Source!U193 | G59: =Source!I209 -> 4
A60: 30 | B60: =Source!E211 -> 30 | C60: =Source!G211 -> Монтаж детали на пультах и панелях - кнопка | D60: 1 ШТ. | E60: =Source!I211 -> 186 | F60: =Source!U193 | G60: =Source!I211 -> 186
A61: 31 | B61: =Source!E213 -> 31 | C61: =Source!G213 -> Пост управления кнопочный, типа ПКЕ-212-1У3. Номинальное напряжение переменного тока частотой 50 Гц - 660 В, постоянного тока 440 В, номинальный ток 10 А, форма толкателя цилиндрическая, степень защиты IP40 | D61: шт. | E61: =Source!I213 -> 186 | F61: =Source!U193 | G61: =Source!I213 -> 186
A62: 32 | B62: =Source!E215 -> 32 | C62: =Source!G215 -> Монтаж блока бесперебойного питания (ББП) в диспетчерской | D62: 1 ШТ. | E62: =Source!I215 -> 3 | F62: =Source!U193 | G62: =Source!I215 -> 3
A63: 33 | B63: =Source!E217 -> 33 | C63: =Source!G217 -> Источник вторичного электропитания резервирован-ный ИВЭПР 24/2,5 RS-R3 | D63: шт. | E63: =Source!I217 -> 3 | F63: =Source!U193 | G63: =Source!I217 -> 3
A64: 34 | B64: =Source!E221 -> 34 | C64: =Source!G221 -> Монтаж пультов и шкафов управления, шкафа (пульта) управления навесного, высотой, шириной, глубиной до 600х600х350 мм | D64: 1 ШТ. | E64: =Source!I221 -> 18 | F64: =Source!U193 | G64: ="=7+"&"5+"&"1+"&"4+"&"1" -> =7+5+1+4+1
A65: 34.1 | B65: =Source!E223 -> 34,1 | C65: =Source!G223 -> Болты стальные оцинкованные с шестигранной головкой, с полной резьбой, с гайкой оцинкованной, М6, длина от 12 до 60 мм | D65: кг | E65: =Source!I223 -> 1.8 | F65: =Source!U193
A66: 35 | B66: =Source!E225 -> 35 | C66: =Source!G225 -> Шкаф управления вентилятором ШУВ-3-00-R3 | D66: шт. | E66: =Source!I225 -> 7 | F66: =Source!U193 | G66: =Source!I225 -> 7
A67: 36 | B67: =Source!E227 -> 36 | C67: =Source!G227 -> Шкаф управления вентилятором ШУВ-5.5-00-R3 | D67: шт. | E67: =Source!I227 -> 5 | F67: =Source!U193 | G67: =Source!I227 -> 5
A68: 37 | B68: =Source!E229 -> 37 | C68: =Source!G229 -> Шкаф управления вентилятором ШУВ-22-00-R3 | D68: шт. | E68: =Source!I229 -> 1 | F68: =Source!U193 | G68: =Source!I229 -> 1
A69: 38 | B69: =Source!E231 -> 38 | C69: =Source!G231 -> Шкаф управления вентилятором ШУВ-11-00-R3 | D69: шт. | E69: =Source!I231 -> 4 | F69: =Source!U193 | G69: =Source!I231 -> 4
A70: 39 | B70: =Source!E233 -> 39 | C70: =Source!G233 -> Шкаф управления вентилятором ШУВ-15-00-R3 | D70: шт. | E70: =Source!I233 -> 1 | F70: =Source!U193 | G70: =Source!I233 -> 1
A71: 40 | B71: =Source!E235 -> 40 | C71: =Source!G235 -> Трубы гофрированные поливинилхлоридные наружным диаметром 20 мм открыто по стенам и потолкам с установкой соединительных коробок | D71: 100 м | E71: =Source!I235 -> 24.4 | F71: =Source!U193 | G71: ="=2440/"&"100" -> =2440/100
A72: 40.1 | B72: =Source!E237 -> 40,1 | C72: =Source!G237 -> Трубы электротехнические, гофрированные, из ПВХ, негорючие, с зондом, наружный диаметр 20 мм | D72: м | E72: =Source!I237 -> 2488.8 | F72: =Source!U193
A73: 41 | B73: =Source!E239 -> 41 | C73: =Source!G239 -> Затягивание провода в проложенные трубы и металлические рукава, первого одножильного или многожильного в общей оплетке, суммарное сечение до 2,5 мм2 | D73: 100 м | E73: =Source!I239 -> 15 | F73: =Source!U193 | G73: ="=1500/"&"100" -> =1500/100
A74: 41.1 | B74: =Source!E241 -> 41,1 | C74: =Source!G241 -> Кабель симметричный для систем охраны и противопожарной защиты огнестойкий, групповой прокладки, с пониженным дымо- и газовыделением, марка КПСнг(А)-FRLS, напряжение 300 В, число пар и сечение жил 1х2х0,75 мм2 | D74: км | E74: =Source!I241 -> 1.545 | F74: =Source!U193
A75: 42 | B75: =Source!E243 -> 42 | C75: =Source!G243 -> Затягивание провода в проложенные трубы и металлические рукава, первого одножильного или многожильного в общей оплетке, суммарное сечение до 6 мм2 | D75: 100 м | E75: =Source!I243 -> 9.4 | F75: =Source!U193 | G75: ="=940/"&"100" -> =940/100
A76: 42.1 | B76: =Source!E245 -> 42,1 | C76: =Source!G245 -> Кабель КПСнг(А)-FRLSLTx 2х2x0.75 | D76: м.п. | E76: =Source!I245 -> 958.8 | F76: =Source!U193
A77: =CONCATENATE("Раздел: ", Source!G278) -> Раздел: Автоматизация систем общеобменной вентиляции
A78: 43 | B78: =Source!E282 -> 43 | C78: =Source!G282 -> Установка прибора массой до 5 кг на металлоконструкциях или щитах/термостат | D78: 1 ШТ. | E78: =Source!I282 -> 13 | F78: =Source!U278 | G78: ="=2+"&"6+"&"5" -> =2+6+5
A79: 43.1 | B79: =Source!E284 -> 43,1 | C79: =Source!G284 -> Болты строительные с гайками, оцинкованные, М10х100 мм | D79: т | E79: =Source!I284 -> 0.000455 | F79: =Source!U278
A80: 44 | B80: =Source!E286 -> 44 | C80: =Source!G286 -> Термостат 1м КР61 | D80: шт. | E80: =Source!I286 -> 2 | F80: =Source!U278 | G80: =Source!I286 -> 2
A81: 45 | B81: =Source!E288 -> 45 | C81: =Source!G288 -> Термостат 3м КР61 | D81: шт. | E81: =Source!I288 -> 6 | F81: =Source!U278 | G81: =Source!I288 -> 6
A82: 46 | B82: =Source!E290 -> 46 | C82: =Source!G290 -> Термостат 6м КР61 | D82: шт. | E82: =Source!I290 -> 5 | F82: =Source!U278 | G82: =Source!I290 -> 5
A83: 47 | B83: =Source!E292 -> 47 | C83: =Source!G292 -> Установка прибора на резьбовых соединениях/Датчик температуры канальный, Датчик температуры воды погружной, Датчик перепада давления 500 Pa, Датчик температуры | D83: 1 ШТ. | E83: =Source!I292 -> 122 | F83: =Source!U278 | G83: ="=11+"&"4+"&"13+"&"11+"&"2+"&"33+"&"48" -> =11+4+13+11+2+33+48
A84: 48 | B84: =Source!E294 -> 48 | C84: =Source!G294 -> Датчик температуры канальный ARK-3 | D84: шт. | E84: =Source!I294 -> 11 | F84: =Source!U278 | G84: =Source!I294 -> 11
A85: 49 | B85: =Source!E296 -> 49 | C85: =Source!G296 -> Датчик температуры канальный ARK-3S | D85: шт. | E85: =Source!I296 -> 4 | F85: =Source!U278 | G85: =Source!I296 -> 4
A86: 50 | B86: =Source!E298 -> 50 | C86: =Source!G298 -> Датчик температуры наружного воздуха ARN-3 | D86: шт. | E86: =Source!I298 -> 13 | F86: =Source!U278 | G86: =Source!I298 -> 13
A87: 51 | B87: =Source!E300 -> 51 | C87: =Source!G300 -> Датчик температуры воды погружной WTP-3 | D87: шт. | E87: =Source!I300 -> 11 | F87: =Source!U278 | G87: =Source!I300 -> 11
A88: 52 | B88: =Source!E302 -> 52 | C88: =Source!G302 -> Датчик температуры воды накладной WTN-3 | D88: шт. | E88: =Source!I302 -> 2 | F88: =Source!U278 | G88: =Source!I302 -> 2
A89: 53 | B89: =Source!E304 -> 53 | C89: =Source!G304 -> Датчик перепада давления 500 Pa DVL-500 | D89: шт. | E89: =Source!I304 -> 33 | F89: =Source!U278 | G89: =Source!I304 -> 33
A90: 54 | B90: =Source!E306 -> 54 | C90: =Source!G306 -> Датчик перепада давления 200 Pa DVL-200 | D90: шт. | E90: =Source!I306 -> 48 | F90: =Source!U278 | G90: =Source!I306 -> 48
A91: 55 | B91: =Source!E308 -> 55 | C91: =Source!G308 -> Монтаж механизма исполнительного массой до 20 кг/привод | D91: 1 ШТ. | E91: =Source!I308 -> 69 | F91: =Source!U278 | G91: ="=9+"&"43+"&"9+"&"2+"&"6" -> =9+43+9+2+6
A92: 55.1 | B92: =Source!E310 -> 55,1 | C92: =Source!G310 -> Болты стальные оцинкованные с шестигранной головкой, с полной резьбой, с гайкой оцинкованной, М6, длина от 12 до 60 мм | D92: кг | E92: =Source!I310 -> 0.02208 | F92: =Source!U278
A93: 56 | B93: =Source!E312 -> 56 | C93: =Source!G312 -> Привод PDF 05/230.D | D93: шт. | E93: =Source!I312 -> 9 | F93: =Source!U278 | G93: =Source!I312 -> 9
A94: 57 | B94: =Source!E314 -> 57 | C94: =Source!G314 -> Привод PFF 03/230.D | D94: шт. | E94: =Source!I314 -> 43 | F94: =Source!U278 | G94: =Source!I314 -> 43
A95: 58 | B95: =Source!E316 -> 58 | C95: =Source!G316 -> Привод ELVA 05/24.M | D95: шт. | E95: =Source!I316 -> 9 | F95: =Source!U278 | G95: =Source!I316 -> 9
A96: 59 | B96: =Source!E318 -> 59 | C96: =Source!G318 -> Привод PFF 10/230.D | D96: шт. | E96: =Source!I318 -> 2 | F96: =Source!U278 | G96: =Source!I318 -> 2
A97: 60 | B97: =Source!E320 -> 60 | C97: =Source!G320 -> Привод PFS 05/230.DT | D97: шт. | E97: =Source!I320 -> 6 | F97: =Source!U278 | G97: =Source!I320 -> 6
A98: =CONCATENATE("Раздел: ", Source!G353) -> Раздел: Аппаратура в щитах автоматизации
A99: 61 | B99: =Source!E357 -> 61 | C99: =Source!G357 -> Монтаж щитов и пультов массой до 50кг | D99: 1 ШТ. | E99: =Source!I357 -> 63 | F99: =Source!U353 | G99: ="=3+"&"12+"&"35+"&"1+"&"2+"&"2+"&"8" -> =3+12+35+1+2+2+8
A100: 62 | B100: =Source!E361 -> 62 | C100: =Source!G361 -> Блок управления ACW ZE-3R0 | D100: шт. | E100: =Source!I361 -> 3 | F100: =Source!U353 | G100: =Source!I361 -> 3
A101: 63 | B101: =Source!E363 -> 63 | C101: =Source!G363 -> Блок управления ACW ZE-1R0 | D101: шт. | E101: =Source!I363 -> 12 | F101: =Source!U353 | G101: =Source!I363 -> 12
A102: 64 | B102: =Source!E365 -> 64 | C102: =Source!G365 -> Блок управления ACW ZE-10 | D102: шт. | E102: =Source!I365 -> 35 | F102: =Source!U353 | G102: =Source!I365 -> 35
A103: 65 | B103: =Source!E367 -> 65 | C103: =Source!G367 -> Блок управления ACW ZE-3R0 1H25 | D103: шт. | E103: =Source!I367 -> 1 | F103: =Source!U353 | G103: =Source!I367 -> 1
A104: 66 | B104: =Source!E369 -> 66 | C104: =Source!G369 -> Блок управления ACW ZE-1R0 ED | D104: шт. | E104: =Source!I369 -> 2 | F104: =Source!U353 | G104: =Source!I369 -> 2
A105: 67 | B105: =Source!E371 -> 67 | C105: =Source!G371 -> Блок управления ACE ZE-E3 | D105: шт. | E105: =Source!I371 -> 2 | F105: =Source!U353 | G105: =Source!I371 -> 2
A106: 68 | B106: =Source!E373 -> 68 | C106: =Source!G373 -> Блок управления ACW ZE-11 | D106: шт. | E106: =Source!I373 -> 8 | F106: =Source!U353 | G106: =Source!I373 -> 8
A107: 69 | B107: =Source!E375 -> 69 | C107: =Source!G375 -> Установка прибора массой до 5 кг на металлоконструкциях или щитах | D107: 1 ШТ. | E107: =Source!I375 -> 18 | F107: =Source!U353 | G107: ="=2+"&"8+"&"1+"&"2+"&"5" -> =2+8+1+2+5
A108: 69.1 | B108: =Source!E377 -> 69,1 | C108: =Source!G377 -> Болты стальные оцинкованные с шестигранной головкой, с полной резьбой, с гайкой оцинкованной, М6, длина от 12 до 60 мм | D108: кг | E108: =Source!I377 -> 0.63 | F108: =Source!U353
...

Sheet Source
A1: 0 | B1: Smeta.RU (495) 974-1589 | D1: _PS_ | F1: 0 | G1: 0 | H1: 0 | I1: Smeta.RU | K1: 1 | L1: 74570 | M1: 10 | N1: 11 | O1: 15 | P1: 0 | Q1: 2
A12: 1 | B12: 664 | C12: 0 | D12: =ROW(A625) -> 625 | E12: 0 | F12: Новый объект (ТСН-2001 (Мосгосэкспертиза)) | G12: Капитальный ремонт здания ГБОУ города Москвы «Школа №236» по адресу: город Москва, улица Клязьминская, дом 7, корп. 4 | I12: 0 | K12: 0 | L12: 0 | M12: 4098 | O12: 0 | P12: 0 | Q12: 0 | R12: 0 | S12: 0 | T12: 1 | V12: 0 | BB12: 0 | BH12: Сметные нормы списания | BI12: Коды ОКП для ТСН-2001 МГЭ Дополнение 80 | BJ12: 1 | BK12: 1 | BL12: 0 | BM12: 0 | BN12: 1 | BO12: 0 | BP12: 6 | BQ12: 2 | BR12: 1 | BS12: 1 | BT12: 0 | BU12: 0 | BV12: 0 | BW12: 0 | BX12: 0 | BZ12: Типовой расчет для ТСН-2001 МГЭ, Дополнение 80, строительство | CA12: Территориальные сметные нормативы для Москвы ТСН-2001 (МГЭ), дополнение 80 | CB12: Территориальные сметные нормативы для Москвы ТСН-2001 (МГЭ), дополнение 80 | CC12: Территориальные сметные нормативы для Москвы ТСН-2001 (МГЭ), дополнение 80 | CD12: Территориальные сметные нормативы для Москвы ТСН-2001 (МГЭ), дополнение 80 | CE12: Поправки для ТСН-2001 от 30.12.2025 г. доп.80 | CF12: 0 | CG12: 0 | CH12: 8200 | CK12: 80 | CQ12: Территориальные сметные нормативы для Москвы (ТСН-2001) | CR12: ТЕР | CS12: 41660 | CT12: 1 | CU12: 80 | CY12: 0 | EC12: 0
A15: 15 | B15: 1
A18: 52 | B18: =B625 -> 664 | C18: =C625 -> 1 | D18: =D625 -> 12 | E18: =E625 -> 0 | F18: =F625 -> Новый объект (ТСН-2001 (Мосгосэкспертиза)) | G18: =G625 -> Капитальный ремонт здания ГБОУ города Москвы «Школа №236» по адресу: город Москва, улица Клязьминская, дом 7, корп. 4 | O18: =O625 -> 1897925.6 | P18: =P625 -> 1849266.9 | Q18: =Q625 -> 7979.47 | R18: =R625 -> 1138.16 | S18: =S625 -> 40679.28 | T18: =T625 -> 0 | U18: =U625 -> 3300.0132 | V18: =V625 -> 0 | ... GX18: =GX625 -> 0
A20: 3 | B20: 1 | D20: =ROW(A595) -> 595 | F20: 02-01-18 | G20: Автоматизация и диспетчеризация инженерных систем. | I20: 0 | J20: 2024-00272-01-0-ИОС5.11 | K20: -1 | L20: 02-01-18 | S20: 0 | T20: 0 | V20: 2 | BX20: 0 | CF20: 0 | CG20: 0
A22: 52 | B22: =B595 -> 1 | C22: =C595 -> 3 | D22: =D595 -> 20 | E22: =E595 -> 0 | F22: =F595 -> 02-01-18 | G22: =G595 -> Автоматизация и диспетчеризация инженерных систем. | O22: =O595 -> 1897925.6 | P22: =P595 -> 1849266.9 | Q22: =Q595 -> 7979.47 | R22: =R595 -> 1138.16 | S22: =S595 -> 40679.28 | T22: =T595 -> 0 | U22: =U595 -> 3300.0132 | V22: =V595 -> 0 | ... GX22: =GX595 -> 0
A24: 4 | B24: 1 | D24: =ROW(A75) -> 75 | F24: Новый раздел | G24: Система управления и диспетчерского контроля инженерного | I24: 0 | K24: 0 | S24: 0 | T24: 0 | V24: 2 | BX24: 0 | CJ24: 0
A26: 52 | B26: =B75 -> 1 | C26: =C75 -> 4 | D26: =D75 -> 24 | E26: =E75 -> 0 | F26: =F75 -> Новый раздел | G26: =G75 -> Система управления и диспетчерского контроля инженерного | O26: =O75 -> 116438.62 | P26: =P75 -> 107651.76 | Q26: =Q75 -> 1034.27 | R26: =R75 -> 173.24 | S26: =S75 -> 7752.59 | T26: =T75 -> 0 | U26: =U75 -> 615.2796 | V26: =V75 -> 0 | ... GX26: =GX75 -> 0
A28: 17 | B28: 1 | C28: =ROW(SmtRes!A2) -> 2 | D28: =ROW(EtalonRes!A3) -> 3 | E28: 1 | F28: 4.11-7-2 | G28: Установка аппарата настольного массой до 0,03 т | H28: 1 ШТ. | I28: 1 | J28: 0 | K28: 1 | O28: =ROUND(CP28,2) -> 70.41 | P28: =ROUND((ROUND((AC28*AW28*I28),2)*BC28),2) -> 0 | Q28: =(ROUND((ROUND((((ET28*1.1))*AV28*I28),2)*BB28),2)+ROUND((ROUND(((AE28-((EU28*1.1)))*AV28*I28),2)*BS28),2)) -> 30.62 | R28: =ROUND((ROUND((AE28*AV28*I28),2)*BS28),2) -> 4.65 | S28: =ROUND((ROUND((AF28*AV28*I28),2)*BA28),2) -> 39.79 | T28: =ROUND(CU28*I28,2) -> 0 | U28: =CV28*I28 -> 3.558753 | V28: =CW28*I28 -> 0 | W28: =ROUND(CX28*I28,2) -> 0 | X28: =ROUND(CY28,2) -> 40 | Y28: =ROUND(CZ28,2) -> 20.44 | AA28: 56959434 | AB28: =ROUND((AC28+AD28+AF28),6) -> 67.254 | AC28: =ROUND((ES28),6) -> 0 | AD28: =ROUND(((((ET28*1.1))-((EU28*1.1)))+AE28),6) -> 29.249 | AE28: =ROUND(((EU28*1.1)),6) -> 4.444 | AF28: =ROUND(((EV28*1.1)),6) -> 38.005 | AG28: =ROUND((AP28),6) -> 0 | AH28: =((EW28*1.1)) -> 3.399 | AI28: =((EX28*1.1)) -> 0 | AJ28: =(AS28) -> 0 | AK28: 61.14 | AL28: 0 | AM28: 26.59 | AN28: 4.04 | AO28: 34.55 | AP28: 0 | AQ28: 3.09 | AR28: 0 | AS28: 0 | AT28: 90 | AU28: 46 | AV28: 1.047 | AW28: 1 | AZ28: 1 | BA28: 1 | BB28: 1 | BC28: 1 | BH28: 0 | BI28: 2 | BJ28: ТСН-2001.4 Доп. 68, Сб. 11, т. 7, поз. 2 | BM28: 72 | BN28: 55992028 | BO28: 4.11-7-2 | BP28: 1 | BQ28: 40 | BR28: 0 | BS28: 1 | BT28: 1 | BU28: 1 | BV28: 1 | BW28: 1 | BX28: 1 | BZ28: 90 | CA28: 46 | CE28: 30 | CF28: 0 | CG28: 0 | CM28: 0 | CN28: Поправка: Гл.12.Прил.8.п.8. 5_12.00.01.11.003 Наименование: При наличии усложненных условий производства работ (стесненность, сложность складирования и транспортной логистики, наличие в зоне производства работ действующего технологического оборудования или движения технологического транспорта и т.п.) для объектов, расположенных за пределами территории круговой магистральной системы улиц "Садовое кольцо" и за пределами Третьего транспортного кольца города Москвы пунктов "а" и "б", но в пределах Московской кольцевой автомобильной дороги | CO28: 0 | CP28: =(P28+Q28+S28) -> 70.41 | CQ28: =ROUND((ROUND((AC28*AW28*1),2)*BC28),2) -> 0 | CR28: =(ROUND((ROUND((((ET28*1.1))*AV28*1),2)*BB28),2)+ROUND((ROUND(((AE28-((EU28*1.1)))*AV28*1),2)*BS28),2)) -> 30.62 | CS28: =ROUND((ROUND((AE28*AV28*1),2)*BS28),2) -> 4.65 | CT28: =ROUND((ROUND((AF28*AV28*1),2)*BA28),2) -> 39.79 | CU28: =AG28 -> 0 | CV28: =(AH28*AV28) -> 3.558753 | CW28: =AI28 -> 0 | CX28: =AJ28 -> 0 | CY28: =(((S28+R28)*AT28)/100) -> 39.996 | CZ28: =(((S28+R28)*AU28)/100) -> 20.4424 | DE28: *1,1 | DF28: *1,1 | DG28: *1,1 | DI28: *1,1 | DJ28: *1,1 | DN28: 0 | DO28: 0 | DP28: 1 | DQ28: 1 | DU28: 1013 | DV28: 1 ШТ. | DW28: 1 ШТ. | DX28: 1 | EE28: 55992157 | EF28: 40 | EG28: Монтаж оборудования | EH28: 0 | EJ28: 2 | EK28: 72 | EL28: ТСН-2001.4-11. Приборы и средства автоматизации и вычислительной техники | EM28: ТСН-2001.4-11-1 | EO28: Поправка: Гл.12.Прил.8.п.8. 5_12.00.01.11.003 | EQ28: 0 | ER28: 61.14 | ES28: 0 | ET28: 26.59 | EU28: 4.04 | EV28: 34.55 | EW28: 3.09 | EX28: 0 | EY28: 0 | FQ28: 0 | FR28: 0 | FS28: 0 | FX28: 90 | FY28: 46 | GD28: 1 | GF28: -1491520468 | GG28: 2 | GH28: 1 | GI28: 2 | GJ28: 0 | GK28: 0 | GL28: =ROUND(IF(AND(BH28=3,BI28=3,FS28<>0),P28,0),2) -> 0 | GM28: =ROUND(O28+X28+Y28,2)+GX28 -> 130.85 | GN28: =IF(OR(BI28=0,BI28=1),GM28-GX28,0) -> 0 | GO28: =IF(BI28=2,GM28-GX28,0) -> 130.85 | GP28: =IF(BI28=4,GM28-GX28,0) -> 0 | GR28: 0 | GS28: 3 | GT28: 0 | GV28: =ROUND((GT28),6) -> 0 | GW28: 1 | GX28: =ROUND(HC28*I28,2) -> 0 | HA28: 0 | HB28: 0 | HC28: =GV28*GW28 -> 0 | HS28: 0 | IK28: 0
A29: 17 | B29: 1 | C29: =ROW(SmtRes!A4) -> 4 | D29: =ROW(EtalonRes!A6) -> 6 | E29: 1 | F29: 4.11-7-2 | G29: Установка аппарата настольного массой до 0,03 т | H29: 1 ШТ. | I29: 1 | J29: 0 | K29: 1 | O29: =ROUND(CP29,2) -> 2687.16 | P29: =ROUND((ROUND((AC29*AW29*I29),2)*BC29),2) -> 0 | Q29: =(ROUND((ROUND((((ET29*1.1))*AV29*I29),2)*BB29),2)+ROUND((ROUND(((AE29-((EU29*1.1)))*AV29*I29),2)*BS29),2)) -> 499.11 | R29: =ROUND((ROUND((AE29*AV29*I29),2)*BS29),2) -> 255.7 | S29: =ROUND((ROUND((AF29*AV29*I29),2)*BA29),2) -> 2188.05 | T29: =ROUND(CU29*I29,2) -> 0 | U29: =CV29*I29 -> 3.558753 | V29: =CW29*I29 -> 0 | W29: =ROUND(CX29*I29,2) -> 0 | X29: =ROUND(CY29,2) -> 2199.38 | Y29: =ROUND(CZ29,2) -> 1124.13 | AA29: 56959431 | AB29: =ROUND((AC29+AD29+AF29),6) -> 67.254 | AC29: =ROUND((ES29),6) -> 0 | AD29: =ROUND(((((ET29*1.1))-((EU29*1.1)))+AE29),6) -> 29.249 | AE29: =ROUND(((EU29*1.1)),6) -> 4.444 | AF29: =ROUND(((EV29*1.1)),6) -> 38.005 | AG29: =ROUND((AP29),6) -> 0 | AH29: =((EW29*1.1)) -> 3.399 | AI29: =((EX29*1.1)) -> 0 | AJ29: =(AS29) -> 0 | AK29: 61.14 | AL29: 0 | AM29: 26.59 | AN29: 4.04 | AO29: 34.55 | AP29: 0 | AQ29: 3.09 | AR29: 0 | AS29: 0 | AT29: 90 | AU29: 46 | AV29: 1.047 | AW29: 1 | AZ29: 1 | BA29: 54.99 | BB29: 16.3 | BC29: 1 | BH29: 0 | BI29: 2 | BJ29: ТСН-2001.4 Доп. 68, Сб. 11, т. 7, поз. 2 | BM29: 72 | BN29: 55992028 | BO29: 4.11-7-2 | BP29: 1 | BQ29: 40 | BR29: 0 | BS29: 54.99 | BT29: 1 | BU29: 1 | BV29: 1 | BW29: 1 | BX29: 1 | BZ29: 90 | CA29: 46 | CE29: 30 | CF29: 0 | CG29: 0 | CM29: 0 | CN29: Поправка: Гл.12.Прил.8.п.8. 5_12.00.01.11.003 Наименование: При наличии усложненных условий производства работ (стесненность, сложность складирования и транспортной логистики, наличие в зоне производства работ действующего технологического оборудования или движения технологического транспорта и т.п.) для объектов, расположенных за пределами территории круговой магистральной системы улиц "Садовое кольцо" и за пределами Третьего транспортного кольца города Москвы пунктов "а" и "б", но в пределах Московской кольцевой автомобильной дороги | CO29: 0 | CP29: =(P29+Q29+S29) -> 2687.16 | CQ29: =ROUND((ROUND((AC29*AW29*1),2)*BC29),2) -> 0 | CR29: =(ROUND((ROUND((((ET29*1.1))*AV29*1),2)*BB29),2)+ROUND((ROUND(((AE29-((EU29*1.1)))*AV29*1),2)*BS29),2)) -> 499.11 | CS29: =ROUND((ROUND((AE29*AV29*1),2)*BS29),2) -> 255.7 | CT29: =ROUND((ROUND((AF29*AV29*1),2)*BA29),2) -> 2188.05 | CU29: =AG29 -> 0 | CV29: =(AH29*AV29) -> 3.558753 | CW29: =AI29 -> 0 | CX29: =AJ29 -> 0 | CY29: =(((S29+R29)*AT29)/100) -> 2199.375 | CZ29: =(((S29+R29)*AU29)/100) -> 1124.125 | DE29: *1,1 | DF29: *1,1 | DG29: *1,1 | DI29: *1,1 | DJ29: *1,1 | DN29: 0 | DO29: 0 | DP29: 1 | DQ29: 1 | DU29: 1013 | DV29: 1 ШТ. | DW29: 1 ШТ. | DX29: 1 | EE29: 55992157 | EF29: 40 | EG29: Монтаж оборудования | EH29: 0 | EJ29: 2 | EK29: 72 | EL29: ТСН-2001.4-11. Приборы и средства автоматизации и вычислительной техники | EM29: ТСН-2001.4-11-1 | EO29: Поправка: Гл.12.Прил.8.п.8. 5_12.00.01.11.003 | EQ29: 0 | ER29: 61.14 | ES29: 0 | ET29: 26.59 | EU29: 4.04 | EV29: 34.55 | EW29: 3.09 | EX29: 0 | EY29: 0 | FQ29: 0 | FR29: 0 | FS29: 0 | FX29: 90 | FY29: 46 | GD29: 1 | GF29: -1491520468 | GG29: 2 | GH29: 1 | GI29: 2 | GJ29: 0 | GK29: 0 | GL29: =ROUND(IF(AND(BH29=3,BI29=3,FS29<>0),P29,0),2) -> 0 | GM29: =ROUND(O29+X29+Y29,2)+GX29 -> 6010.67 | GN29: =IF(OR(BI29=0,BI29=1),GM29-GX29,0) -> 0 | GO29: =IF(BI29=2,GM29-GX29,0) -> 6010.67 | GP29: =IF(BI29=4,GM29-GX29,0) -> 0 | GR29: 0 | GS29: 3 | GT29: 0 | GV29: =ROUND((GT29),6) -> 0 | GW29: 1 | GX29: =ROUND(HC29*I29,2) -> 0 | HA29: 0 | HB29: 0 | HC29: =GV29*GW29 -> 0 | HS29: 0 | IK29: 0
A30: 17 | B30: 1 | E30: 2 | F30: КА №1 | G30: Моноблок Lenovo V50a-24IMB | H30: шт. | I30: 1 | J30: 0 | K30: 1 | O30: =ROUND(CP30,2) -> 8548.55 | P30: =ROUND((ROUND((AC30*I30),2)*BC30),2) -> 8548.55 | Q30: =(ROUND((ROUND(((ET30)*AV30*I30),2)*BB30),2)+ROUND((ROUND(((AE30-(EU30))*AV30*I30),2)*BS30),2)) -> 0 | R30: =ROUND((ROUND((AE30*AV30*I30),2)*BS30),2) -> 0 | S30: =ROUND((ROUND((AF30*AV30*I30),2)*BA30),2) -> 0 | T30: =ROUND(CU30*I30,2) -> 0 | U30: =CV30*I30 -> 0 | V30: =CW30*I30 -> 0 | W30: =ROUND(CX30*I30,2) -> 0 | X30: =ROUND(CY30,2) -> 0 | Y30: =ROUND(CZ30,2) -> 0 | AA30: 56959434 | AB30: =ROUND((AC30+AD30+AF30),6) -> 8548.55 | AC30: =ROUND((ES30),6) -> 8548.55 | AD30: =ROUND((((ET30)-(EU30))+AE30),6) -> 0 | AE30: =ROUND((EU30),6) -> 0 | AF30: =ROUND((EV30),6) -> 0 | AG30: =ROUND((AP30),6) -> 0 | AH30: =(EW30) -> 0 | AI30: =(EX30) -> 0 | AJ30: =(AS30) -> 0 | AK30: 8548.55 | AL30: 8548.55 | AM30: 0 | AN30: 0 | AO30: 0 | AP30: 0 | AQ30: 0 | AR30: 0 | AS30: 0 | AT30: 0 | AU30: 0 | AV30: 1 | AW30: 1 | AZ30: 1 | BA30: 1 | BB30: 1 | BC30: 1 | BH30: 3 | BI30: 3 | BM30: 746 | BN30: 0 | BP30: 0 | BQ30: 130 | BR30: 0 | BS30: 1 | BT30: 1 | BU30: 1 | BV30: 1 | BW30: 1 | BX30: 1 | BZ30: 0 | CA30: 0 | CE30: 30 | CF30: 0 | CG30: 0 | CM30: 0 | CO30: 0 | CP30: =(P30+Q30+S30) -> 8548.55 | CQ30: =ROUND((ROUND((AC30*1),2)*BC30),2) -> 8548.55 | CR30: =(ROUND((ROUND(((ET30)*AV30*1),2)*BB30),2)+ROUND((ROUND(((AE30-(EU30))*AV30*1),2)*BS30),2)) -> 0 | CS30: =ROUND((ROUND((AE30*AV30*1),2)*BS30),2) -> 0 | CT30: =ROUND((ROUND((AF30*AV30*1),2)*BA30),2) -> 0 | CU30: =AG30 -> 0 | CV30: =(AH30*AV30) -> 0 | CW30: =AI30 -> 0 | CX30: =AJ30 -> 0 | CY30: =(((S30+R30)*AT30)/100) -> 0 | CZ30: =(((S30+R30)*AU30)/100) -> 0 | DN30: 0 | DO30: 0 | DP30: 1 | DQ30: 1 | DU30: 1010 | DV30: шт. | DW30: шт. | DX30: 1 | EE30: 55992259 | EF30: 130 | EG30: Сметная стоимость оборудования | EH30: 0 | EJ30: 3 | EK30: 746 | EL30: ТСН-2001.13. Сметная стоимость оборудования | EM30: ТСН-2001.13 | EQ30: 0 | ER30: 0 | ES30: 8548.55 | ET30: 0 | EU30: 0 | EV30: 0 | EW30: 0 | EX30: 0 | EY30: 0 | FQ30: 0 | FR30: =P30 -> 8548.55 | FS30: 0 | FX30: 0 | FY30: 0 | GA30: [75 385 / 1,2 / 7,66] + 3% Трансп + 1,2% Заг.скл | GD30: 1 | GF30: 540965289 | GG30: 2 | GH30: 4 | GI30: -2 | GJ30: 0 | GK30: 0 | GL30: =ROUND(IF(AND(BH30=3,BI30=3,FS30<>0),P30,0),2) -> 0 | GM30: =ROUND(O30+X30+Y30,2)+GX30 -> 8548.55 | GN30: =IF(OR(BI30=0,BI30=1),GM30-GX30,0) -> 0 | GO30: =IF(BI30=2,GM30-GX30,0) -> 0 | GP30: =IF(BI30=4,GM30-GX30,0) -> 0 | GR30: 0 | GS30: 2 | GT30: 0 | GV30: =ROUND((GT30),6) -> 0 | GW30: 1 | GX30: =ROUND(HC30*I30,2) -> 0 | HA30: 0 | HB30: 0 | HC30: =GV30*GW30 -> 0 | HE30: 3 | HF30: 1,2 | HS30: 0 | IK30: 0
A31: 17 | B31: 1 | E31: 2 | F31: КА №1 | G31: Моноблок Lenovo V50a-24IMB | H31: шт. | I31: 1 | J31: 0 | K31: 1 | O31: =ROUND(CP31,2) -> 65481.89 | P31: =ROUND((ROUND((AC31*I31),2)*BC31),2) -> 65481.89 | Q31: =(ROUND((ROUND(((ET31)*AV31*I31),2)*BB31),2)+ROUND((ROUND(((AE31-(EU31))*AV31*I31),2)*BS31),2)) -> 0 | R31: =ROUND((ROUND((AE31*AV31*I31),2)*BS31),2) -> 0 | S31: =ROUND((ROUND((AF31*AV31*I31),2)*BA31),2) -> 0 | T31: =ROUND(CU31*I31,2) -> 0 | U31: =CV31*I31 -> 0 | V31: =CW31*I31 -> 0 | W31: =ROUND(CX31*I31,2) -> 0 | X31: =ROUND(CY31,2) -> 0 | Y31: =ROUND(CZ31,2) -> 0 | AA31: 56959431 | AB31: =ROUND((AC31+AD31+AF31),6) -> 8548.55 | AC31: =ROUND((ES31),6) -> 8548.55 | AD31: =ROUND((((ET31)-(EU31))+AE31),6) -> 0 | AE31: =ROUND((EU31),6) -> 0 | AF31: =ROUND((EV31),6) -> 0 | AG31: =ROUND((AP31),6) -> 0 | AH31: =(EW31) -> 0 | AI31: =(EX31) -> 0 | AJ31: =(AS31) -> 0 | AK31: 8548.55 | AL31: 8548.55 | AM31: 0 | AN31: 0 | AO31: 0 | AP31: 0 | AQ31: 0 | AR31: 0 | AS31: 0 | AT31: 0 | AU31: 0 | AV31: 1 | AW31: 1 | AZ31: 1 | BA31: 1 | BB31: 1 | BC31: 7.66 | BH31: 3 | BI31: 3 | BM31: 746 | BN31: 0 | BP31: 0 | BQ31: 130 | BR31: 0 | BS31: 1 | BT31: 1 | BU31: 1 | BV31: 1 | BW31: 1 | BX31: 1 | BZ31: 0 | CA31: 0 | CE31: 30 | CF31: 0 | CG31: 0 | CM31: 0 | CO31: 0 | CP31: =(P31+Q31+S31) -> 65481.89 | CQ31: =ROUND((ROUND((AC31*1),2)*BC31),2) -> 65481.89 | CR31: =(ROUND((ROUND(((ET31)*AV31*1),2)*BB31),2)+ROUND((ROUND(((AE31-(EU31))*AV31*1),2)*BS31),2)) -> 0 | CS31: =ROUND((ROUND((AE31*AV31*1),2)*BS31),2) -> 0 | CT31: =ROUND((ROUND((AF31*AV31*1),2)*BA31),2) -> 0 | CU31: =AG31 -> 0 | CV31: =(AH31*AV31) -> 0 | CW31: =AI31 -> 0 | CX31: =AJ31 -> 0 | CY31: =(((S31+R31)*AT31)/100) -> 0 | CZ31: =(((S31+R31)*AU31)/100) -> 0 | DN31: 0 | DO31: 0 | DP31: 1 | DQ31: 1 | DU31: 1010 | DV31: шт. | DW31: шт. | DX31: 1 | EE31: 55992259 | EF31: 130 | EG31: Сметная стоимость оборудования | EH31: 0 | EJ31: 3 | EK31: 746 | EL31: ТСН-2001.13. Сметная стоимость оборудования | EM31: ТСН-2001.13 | EQ31: 0 | ER31: 8548.55 | ES31: 8548.55 | ET31: 0 | EU31: 0 | EV31: 0 | EW31: 0 | EX31: 0 | EY31: 0 | EZ31: 5 | FC31: 1 | FD31: 18 | FF31: 75385 | FQ31: 0 | FR31: =P31 -> 65481.89 | FS31: 0 | FX31: 0 | FY31: 0 | GA31: [75 385 / 1,2 / 7,66] + 3% Трансп + 1,2% Заг.скл | GD31: 1 | GF31: 540965289 | GG31: 2 | GH31: 3 | GI31: 5 | GJ31: 0 | GK31: 0 | GL31: =ROUND(IF(AND(BH31=3,BI31=3,FS31<>0),P31,0),2) -> 0 | GM31: =ROUND(O31+X31+Y31,2)+GX31 -> 65481.89 | GN31: =IF(OR(BI31=0,BI31=1),GM31-GX31,0) -> 0 | GO31: =IF(BI31=2,GM31-GX31,0) -> 0 | GP31: =IF(BI31=4,GM31-GX31,0) -> 0 | GR31: 1 | GS31: 1 | GT31: 0 | GV31: =ROUND((GT31),6) -> 0 | GW31: 1 | GX31: =ROUND(HC31*I31,2) -> 0 | HA31: 0 | HB31: 0 | HC31: =GV31*GW31 -> 0 | HE31: 3 | HF31: 1,2 | HS31: 0 | IK31: 0
A32: 17 | B32: 1 | C32: =ROW(SmtRes!A11) -> 11 | D32: =ROW(EtalonRes!A13) -> 13 | E32: 3 | F32: 4.10-118-5 | G32: Установка для трубных проводок шкафа настенного размерами до 640х840 мм | H32: 1 ШТ. | I32: 1 | J32: 0 | K32: 1 | O32: =ROUND(CP32,2) -> 139.14 | P32: =ROUND((ROUND((AC32*AW32*I32),2)*BC32),2) -> 109.01 | Q32: =(ROUND((ROUND((((ET32*1.1))*AV32*I32),2)*BB32),2)+ROUND((ROUND(((AE32-((EU32*1.1)))*AV32*I32),2)*BS32),2)) -> 2.74 | R32: =ROUND((ROUND((AE32*AV32*I32),2)*BS32),2) -> 0.29 | S32: =ROUND((ROUND((AF32*AV32*I32),2)*BA32),2) -> 27.39 | T32: =ROUND(CU32*I32,2) -> 0 | U32: =CV32*I32 -> 2.3034 | V32: =CW32*I32 -> 0 | W32: =ROUND(CX32*I32,2) -> 0 | X32: =ROUND(CY32,2) -> 24.91 | Y32: =ROUND(CZ32,2) -> 12.73 | AA32: 56959434 | AB32: =ROUND((AC32+AD32+AF32),6) -> 137.786 | AC32: =ROUND((ES32),6) -> 109.01 | AD32: =ROUND(((((ET32*1.1))-((EU32*1.1)))+AE32),6) -> 2.618 | AE32: =ROUND(((EU32*1.1)),6) -> 0.275 | AF32: =ROUND(((EV32*1.1)),6) -> 26.158 | AG32: =ROUND((AP32),6) -> 0 | AH32: =((EW32*1.1)) -> 2.2 | AI32: =((EX32*1.1)) -> 0 | AJ32: =(AS32) -> 0 | AK32: 135.17 | AL32: 109.01 | AM32: 2.38 | AN32: 0.25 | AO32: 23.78 | AP32: 0 | AQ32: 2 | AR32: 0 | AS32: 0 | AT32: 90 | AU32: 46 | AV32: 1.047 | AW32: 1 | AZ32: 1 | BA32: 1 | BB32: 1 | BC32: 1 | BH32: 0 | BI32: 2 | BJ32: ТСН-2001.4 Доп. 79, Сб. 10, т. 118, поз. 5 | BM32: 68 | BN32: 55992028 | BO32: 4.10-118-5 | BP32: 1 | BQ32: 40 | BR32: 0 | BS32: 1 | BT32: 1 | BU32: 1 | BV32: 1 | BW32: 1 | BX32: 1 | BZ32: 90 | CA32: 46 | CE32: 30 | CF32: 0 | CG32: 0 | CM32: 0 | CN32: Поправка: Гл.12.Прил.8.п.8. 5_12.00.01.11.003 Наименование: При наличии усложненных условий производства работ (стесненность, сложность складирования и транспортной логистики, наличие в зоне производства работ действующего технологического оборудования или движения технологического транспорта и т.п.) для объектов, расположенных за пределами территории круговой магистральной системы улиц "Садовое кольцо" и за пределами Третьего транспортного кольца города Москвы пунктов "а" и "б", но в пределах Московской кольцевой автомобильной дороги | CO32: 0 | CP32: =(P32+Q32+S32) -> 139.14 | CQ32: =ROUND((ROUND((AC32*AW32*1),2)*BC32),2) -> 109.01 | CR32: =(ROUND((ROUND((((ET32*1.1))*AV32*1),2)*BB32),2)+ROUND((ROUND(((AE32-((EU32*1.1)))*AV32*1),2)*BS32),2)) -> 2.74 | CS32: =ROUND((ROUND((AE32*AV32*1),2)*BS32),2) -> 0.29 | CT32: =ROUND((ROUND((AF32*AV32*1),2)*BA32),2) -> 27.39 | CU32: =AG32 -> 0 | CV32: =(AH32*AV32) -> 2.3034 | CW32: =AI32 -> 0 | CX32: =AJ32 -> 0 | CY32: =(((S32+R32)*AT32)/100) -> 24.912 | CZ32: =(((S32+R32)*AU32)/100) -> 12.7328 | DE32: *1,1 | DF32: *1,1 | DG32: *1,1 | DI32: *1,1 | DJ32: *1,1 | DN32: 0 | DO32: 0 | DP32: 1 | DQ32: 1 | DU32: 1013 | DV32: 1 ШТ. | DW32: 1 ШТ. | DX32: 1 | EE32: 55992152 | EF32: 40 | EG32: Монтаж оборудования | EH32: 0 | EJ32: 2 | EK32: 68 | EL32: ТСН-2001.4-10. Прокладка и монтаж сетей связи | EM32: ТСН-2001.4-10-1 | EO32: Поправка: Гл.12.Прил.8.п.8. 5_12.00.01.11.003 | EQ32: 0 | ER32: 135.17 | ES32: 109.01 | ET32: 2.38 | EU32: 0.25 | EV32: 23.78 | EW32: 2 | EX32: 0 | EY32: 0 | FQ32: 0 | FR32: 0 | FS32: 0 | FX32: 90 | FY32: 46 | GD32: 1 | GF32: 438712902 | GG32: 2 | GH32: 1 | GI32: 2 | GJ32: 0 | GK32: 0 | GL32: =ROUND(IF(AND(BH32=3,BI32=3,FS32<>0),P32,0),2) -> 0 | GM32: =ROUND(O32+X32+Y32,2)+GX32 -> 176.78 | GN32: =IF(OR(BI32=0,BI32=1),GM32-GX32,0) -> 0 | GO32: =IF(BI32=2,GM32-GX32,0) -> 176.78 | GP32: =IF(BI32=4,GM32-GX32,0) -> 0 | GR32: 0 | GS32: 3 | GT32: 0 | GV32: =ROUND((GT32),6) -> 0 | GW32: 1 | GX32: =ROUND(HC32*I32,2) -> 0 | HA32: 0 | HB32: 0 | HC32: =GV32*GW32 -> 0 | HS32: 0 | IK32: 0
A33: 17 | B33: 1 | C33: =ROW(SmtRes!A18) -> 18 | D33: =ROW(EtalonRes!A20) -> 20 | E33: 3 | F33: 4.10-118-5 | G33: Установка для трубных проводок шкафа настенного размерами до 640х840 мм | H33: 1 ШТ. | I33: 1 | J33: 0 | K33: 1 | O33: =ROUND(CP33,2) -> 1899.88 | P33: =ROUND((ROUND((AC33*AW33*I33),2)*BC33),2) -> 355.37 | Q33: =(ROUND((ROUND((((ET33*1.1))*AV33*I33),2)*BB33),2)+ROUND((ROUND(((AE33-((EU33*1.1)))*AV33*I33),2)*BS33),2)) -> 38.33 | R33: =ROUND((ROUND((AE33*AV33*I33),2)*BS33),2) -> 15.95 | S33: =ROUND((ROUND((AF33*AV33*I33),2)*BA33),2) -> 1506.18 | T33: =ROUND(CU33*I33,2) -> 0 | U33: =CV33*I33 -> 2.3034 | V33: =CW33*I33 -> 0 | W33: =ROUND(CX33*I33,2) -> 0 | X33: =ROUND(CY33,2) -> 1369.92 | Y33: =ROUND(CZ33,2) -> 700.18 | AA33: 56959431 | AB33: =ROUND((AC33+AD33+AF33),6) -> 137.786 | AC33: =ROUND((ES33),6) -> 109.01 | AD33: =ROUND(((((ET33*1.1))-((EU33*1.1)))+AE33),6) -> 2.618 | AE33: =ROUND(((EU33*1.1)),6) -> 0.275 | AF33: =ROUND(((EV33*1.1)),6) -> 26.158 | AG33: =ROUND((AP33),6) -> 0 | AH33: =((EW33*1.1)) -> 2.2 | AI33: =((EX33*1.1)) -> 0 | AJ33: =(AS33) -> 0 | AK33: 135.17 | AL33: 109.01 | AM33: 2.38 | AN33: 0.25 | AO33: 23.78 | AP33: 0 | AQ33: 2 | AR33: 0 | AS33: 0 | AT33: 90 | AU33: 46 | AV33: 1.047 | AW33: 1 | AZ33: 1 | BA33: 54.99 | BB33: 13.99 | BC33: 3.26 | BH33: 0 | BI33: 2 | BJ33: ТСН-2001.4 Доп. 79, Сб. 10, т. 118, поз. 5 | BM33: 68 | BN33: 55992028 | BO33: 4.10-118-5 | BP33: 1 | BQ33: 40 | BR33: 0 | BS33: 54.99 | BT33: 1 | BU33: 1 | BV33: 1 | BW33: 1 | BX33: 1 | BZ33: 90 | CA33: 46 | CE33: 30 | CF33: 0 | CG33: 0 | CM33: 0 | CN33: Поправка: Гл.12.Прил.8.п.8. 5_12.00.01.11.003 Наименование: При наличии усложненных условий производства работ (стесненность, сложность складирования и транспортной логистики, наличие в зоне производства работ действующего технологического оборудования или движения технологического транспорта и т.п.) для объектов, расположенных за пределами территории круговой магистральной системы улиц "Садовое кольцо" и за пределами Третьего транспортного кольца города Москвы пунктов "а" и "б", но в пределах Московской кольцевой автомобильной дороги | CO33: 0 | CP33: =(P33+Q33+S33) -> 1899.88 | CQ33: =ROUND((ROUND((AC33*AW33*1),2)*BC33),2) -> 355.37 | CR33: =(ROUND((ROUND((((ET33*1.1))*AV33*1),2)*BB33),2)+ROUND((ROUND(((AE33-((EU33*1.1)))*AV33*1),2)*BS33),2)) -> 38.33 | CS33: =ROUND((ROUND((AE33*AV33*1),2)*BS33),2) -> 15.95 | CT33: =ROUND((ROUND((AF33*AV33*1),2)*BA33),2) -> 1506.18 | CU33: =AG33 -> 0 | CV33: =(AH33*AV33) -> 2.3034 | CW33: =AI33 -> 0 | CX33: =AJ33 -> 0 | CY33: =(((S33+R33)*AT33)/100) -> 1369.917 | CZ33: =(((S33+R33)*AU33)/100) -> 700.1798 | DE33: *1,1 | DF33: *1,1 | DG33: *1,1 | DI33: *1,1 | DJ33: *1,1 | DN33: 0 | DO33: 0 | DP33: 1 | DQ33: 1 | DU33: 1013 | DV33: 1 ШТ. | DW33: 1 ШТ. | DX33: 1 | EE33: 55992152 | EF33: 40 | EG33: Монтаж оборудования | EH33: 0 | EJ33: 2 | EK33: 68 | EL33: ТСН-2001.4-10. Прокладка и монтаж сетей связи | EM33: ТСН-2001.4-10-1 | EO33: Поправка: Гл.12.Прил.8.п.8. 5_12.00.01.11.003 | EQ33: 0 | ER33: 135.17 | ES33: 109.01 | ET33: 2.38 | EU33: 0.25 | EV33: 23.78 | EW33: 2 | EX33: 0 | EY33: 0 | FQ33: 0 | FR33: 0 | FS33: 0 | FX33: 90 | FY33: 46 | GD33: 1 | GF33: 438712902 | GG33: 2 | GH33: 1 | GI33: 2 | GJ33: 0 | GK33: 0 | GL33: =ROUND(IF(AND(BH33=3,BI33=3,FS33<>0),P33,0),2) -> 0 | GM33: =ROUND(O33+X33+Y33,2)+GX33 -> 3969.98 | GN33: =IF(OR(BI33=0,BI33=1),GM33-GX33,0) -> 0 | GO33: =IF(BI33=2,GM33-GX33,0) -> 3969.98 | GP33: =IF(BI33=4,GM33-GX33,0) -> 0 | GR33: 0 | GS33: 3 | GT33: 0 | GV33: =ROUND((GT33),6) -> 0 | GW33: 1 | GX33: =ROUND(HC33*I33,2) -> 0 | HA33: 0 | HB33: 0 | HC33: =GV33*GW33 -> 0 | HS33: 0 | IK33: 0
A34: 18 | B34: 1 | C34: 10 | E34: 3,1 | F34: 1.21-1-63 | G34: Щит навесной, с дверцей и замком, степень защиты IР55, размер 600х600х250 мм, металлоконструкция без аппаратов | H34: шт. | I34: =I32*J34 -> 1 | J34: 1 | K34: 1 | O34: =ROUND(CP34,2) -> 1975.19 | P34: =ROUND((ROUND((AC34*AW34*I34),2)*BC34),2) -> 1975.19 | Q34: =(ROUND((ROUND(((ET34)*AV34*I34),2)*BB34),2)+ROUND((ROUND(((AE34-(EU34))*AV34*I34),2)*BS34),2)) -> 0 | R34: =ROUND((ROUND((AE34*AV34*I34),2)*BS34),2) -> 0 | S34: =ROUND((ROUND((AF34*AV34*I34),2)*BA34),2) -> 0 | T34: =ROUND(CU34*I34,2) -> 0 | U34: =CV34*I34 -> 0 | V34: =CW34*I34 -> 0 | W34: =ROUND(CX34*I34,2) -> 0 | X34: =ROUND(CY34,2) -> 0 | Y34: =ROUND(CZ34,2) -> 0 | AA34: 56959434 | AB34: =ROUND((AC34+AD34+AF34),6) -> 1975.19 | AC34: =ROUND((ES34),6) -> 1975.19 | AD34: =ROUND((((ET34)-(EU34))+AE34),6) -> 0 | AE34: =ROUND((EU34),6) -> 0 | AF34: =ROUND((EV34),6) -> 0 | AG34: =ROUND((AP34),6) -> 0 | AH34: =(EW34) -> 0 | AI34: =(EX34) -> 0 | AJ34: =(AS34) -> 0 | AK34: 1975.19 | AL34: 1975.19 | AM34: 0 | AN34: 0 | AO34: 0 | AP34: 0 | AQ34: 0 | AR34: 0 | AS34: 0 | AT34: 90 | AU34: 46 | AV34: 1 | AW34: 1 | AZ34: 1 | BA34: 1 | BB34: 1 | BC34: 1 | BH34: 3 | BI34: 2 | BJ34: ТСН-2001.1 Доп. 79, Р. 21, о. 1, поз. 63 | BM34: 68 | BN34: 55992028 | BP34: 0 | BQ34: 40 | BR34: 0 | BS34: 1 | BT34: 1 | BU34: 1 | BV34: 1 | BW34: 1 | BX34: 1 | BZ34: 90 | CA34: 46 | CE34: 30 | CF34: 0 | CG34: 0 | CM34: 0 | CO34: 0 | CP34: =(P34+Q34+S34) -> 1975.19 | CQ34: =ROUND((ROUND((AC34*AW34*1),2)*BC34),2) -> 1975.19 | CR34: =(ROUND((ROUND(((ET34)*AV34*1),2)*BB34),2)+ROUND((ROUND(((AE34-(EU34))*AV34*1),2)*BS34),2)) -> 0 | CS34: =ROUND((ROUND((AE34*AV34*1),2)*BS34),2) -> 0 | CT34: =ROUND((ROUND((AF34*AV34*1),2)*BA34),2) -> 0 | CU34: =AG34 -> 0 | CV34: =(AH34*AV34) -> 0 | CW34: =AI34 -> 0 | CX34: =AJ34 -> 0 | CY34: =(((S34+R34)*AT34)/100) -> 0 | CZ34: =(((S34+R34)*AU34)/100) -> 0 | DN34: 0 | DO34: 0 | DP34: 1 | DQ34: 1 | DU34: 1010 | DV34: шт. | DW34: шт. | DX34: 1 | EE34: 55992152 | EF34: 40 | EG34: Монтаж оборудования | EH34: 0 | EJ34: 2 | EK34: 68 | EL34: ТСН-2001.4-10. Прокладка и монтаж сетей связи | EM34: ТСН-2001.4-10-1 | EQ34: 0 | ER34: 1975.19 | ES34: 1975.19 | ET34: 0 | EU34: 0 | EV34: 0 | EW34: 0 | EX34: 0 | FQ34: 0 | FR34: 0 | FS34: 0 | FX34: 90 | FY34: 46 | GD34: 1 | GF34: 672353504 | GG34: 2 | GH34: 1 | GI34: -2 | GJ34: 0 | GK34: 0 | GL34: =ROUND(IF(AND(BH34=3,BI34=3,FS34<>0),P34,0),2) -> 0 | GM34: =ROUND(O34+X34+Y34,2)+GX34 -> 1975.19 | GN34: =IF(OR(BI34=0,BI34=1),GM34-GX34,0) -> 0 | GO34: =IF(BI34=2,GM34-GX34,0) -> 1975.19 | GP34: =IF(BI34=4,GM34-GX34,0) -> 0 | GR34: 0 | GS34: 3 | GT34: 0 | GV34: =ROUND((GT34),6) -> 0 | GW34: 1 | GX34: =ROUND(HC34*I34,2) -> 0 | HA34: 0 | HB34: 0 | HC34: =GV34*GW34 -> 0 | HS34: 0 | IK34: 0
A35: 18 | B35: 1 | C35: 17 | E35: 3,1 | F35: 1.21-1-63 | G35: Щит навесной, с дверцей и замком, степень защиты IР55, размер 600х600х250 мм, металлоконструкция без аппаратов | H35: шт. | I35: =I33*J35 -> 1 | J35: 1 | K35: 1 | O35: =ROUND(CP35,2) -> 13549.8 | P35: =ROUND((ROUND((AC35*AW35*I35),2)*BC35),2) -> 13549.8 | Q35: =(ROUND((ROUND(((ET35)*AV35*I35),2)*BB35),2)+ROUND((ROUND(((AE35-(EU35))*AV35*I35),2)*BS35),2)) -> 0 | R35: =ROUND((ROUND((AE35*AV35*I35),2)*BS35),2) -> 0 | S35: =ROUND((ROUND((AF35*AV35*I35),2)*BA35),2) -> 0 | T35: =ROUND(CU35*I35,2) -> 0 | U35: =CV35*I35 -> 0 | V35: =CW35*I35 -> 0 | W35: =ROUND(CX35*I35,2) -> 0 | X35: =ROUND(CY35,2) -> 0 | Y35: =ROUND(CZ35,2) -> 0 | AA35: 56959431 | AB35: =ROUND((AC35+AD35+AF35),6) -> 1975.19 | AC35: =ROUND((ES35),6) -> 1975.19 | AD35: =ROUND((((ET35)-(EU35))+AE35),6) -> 0 | AE35: =ROUND((EU35),6) -> 0 | AF35: =ROUND((EV35),6) -> 0 | AG35: =ROUND((AP35),6) -> 0 | AH35: =(EW35) -> 0 | AI35: =(EX35) -> 0 | AJ35: =(AS35) -> 0 | AK35: 1975.19 | AL35: 1975.19 | AM35: 0 | AN35: 0 | AO35: 0 | AP35: 0 | AQ35: 0 | AR35: 0 | AS35: 0 | AT35: 90 | AU35: 46 | AV35: 1 | AW35: 1 | AZ35: 1 | BA35: 1 | BB35: 1 | BC35: 6.86 | BH35: 3 | BI35: 2 | BJ35: ТСН-2001.1 Доп. 79, Р. 21, о. 1, поз. 63 | BM35: 68 | BN35: 55992028 | BO35: 1.21-1-63 | BP35: 1 | BQ35: 40 | BR35: 0 | BS35: 1 | BT35: 1 | BU35: 1 | BV35: 1 | BW35: 1 | BX35: 1 | BZ35: 90 | CA35: 46 | CE35: 30 | CF35: 0 | CG35: 0 | CM35: 0 | CO35: 0 | CP35: =(P35+Q35+S35) -> 13549.8 | CQ35: =ROUND((ROUND((AC35*AW35*1),2)*BC35),2) -> 13549.8 | CR35: =(ROUND((ROUND(((ET35)*AV35*1),2)*BB35),2)+ROUND((ROUND(((AE35-(EU35))*AV35*1),2)*BS35),2)) -> 0 | CS35: =ROUND((ROUND((AE35*AV35*1),2)*BS35),2) -> 0 | CT35: =ROUND((ROUND((AF35*AV35*1),2)*BA35),2) -> 0 | CU35: =AG35 -> 0 | CV35: =(AH35*AV35) -> 0 | CW35: =AI35 -> 0 | CX35: =AJ35 -> 0 | CY35: =(((S35+R35)*AT35)/100) -> 0 | CZ35: =(((S35+R35)*AU35)/100) -> 0 | DN35: 0 | DO35: 0 | DP35: 1 | DQ35: 1 | DU35: 1010 | DV35: шт. | DW35: шт. | DX35: 1 | EE35: 55992152 | EF35: 40 | EG35: Монтаж оборудования | EH35: 0 | EJ35: 2 | EK35: 68 | EL35: ТСН-2001.4-10. Прокладка и монтаж сетей связи | EM35: ТСН-2001.4-10-1 | EQ35: 0 | ER35: 1975.19 | ES35: 1975.19 | ET35: 0 | EU35: 0 | EV35: 0 | EW35: 0 | EX35: 0 | FQ35: 0 | FR35: 0 | FS35: 0 | FX35: 90 | FY35: 46 | GD35: 1 | GF35: 672353504 | GG35: 2 | GH35: 1 | GI35: 2 | GJ35: 0 | GK35: 0 | GL35: =ROUND(IF(AND(BH35=3,BI35=3,FS35<>0),P35,0),2) -> 0 | GM35: =ROUND(O35+X35+Y35,2)+GX35 -> 13549.8 | GN35: =IF(OR(BI35=0,BI35=1),GM35-GX35,0) -> 0 | GO35: =IF(BI35=2,GM35-GX35,0) -> 13549.8 | GP35: =IF(BI35=4,GM35-GX35,0) -> 0 | GR35: 0 | GS35: 3 | GT35: 0 | GV35: =ROUND((GT35),6) -> 0 | GW35: 1 | GX35: =ROUND(HC35*I35,2) -> 0 | HA35: 0 | HB35: 0 | HC35: =GV35*GW35 -> 0 | HS35: 0 | IK35: 0
A36: 17 | B36: 1 | C36: =ROW(SmtRes!A20) -> 20 | D36: =ROW(EtalonRes!A23) -> 23 | E36: 4 | F36: 4.11-12-1 | G36: Установка съемных и выдвижных блоков (модулей, ячеек, ТЭЗ) массой до 5 кг | H36: 1 ШТ. | I36: 1 | J36: 0 | K36: 1 | O36: =ROUND(CP36,2) -> 14 | P36: =ROUND((ROUND((AC36*AW36*I36),2)*BC36),2) -> 0 | Q36: =(ROUND((ROUND((((ET36*1.1))*AV36*I36),2)*BB36),2)+ROUND((ROUND(((AE36-((EU36*1.1)))*AV36*I36),2)*BS36),2)) -> 0.58 | R36: =ROUND((ROUND((AE36*AV36*I36),2)*BS36),2) -> 0.09 | S36: =ROUND((ROUND((AF36*AV36*I36),2)*BA36),2) -> 13.42 | T36: =ROUND(CU36*I36,2) -> 0 | U36: =CV36*I36 -> 1.186251 | V36: =CW36*I36 -> 0 | W36: =ROUND(CX36*I36,2) -> 0 | X36: =ROUND(CY36,2) -> 12.16 | Y36: =ROUND(CZ36,2) -> 6.21 | AA36: 56959434 | AB36: =ROUND((AC36+AD36+AF36),6) -> 13.365 | AC36: =ROUND((ES36),6) -> 0 | AD36: =ROUND(((((ET36*1.1))-((EU36*1.1)))+AE36),6) -> 0.55 | AE36: =ROUND(((EU36*1.1)),6) -> 0.088 | AF36: =ROUND(((EV36*1.1)),6) -> 12.815 | AG36: =ROUND((AP36),6) -> 0 | AH36: =((EW36*1.1)) -> 1.133 | AI36: =((EX36*1.1)) -> 0 | AJ36: =(AS36) -> 0 | AK36: 12.15 | AL36: 0 | AM36: 0.5 | AN36: 0.08 | AO36: 11.65 | AP36: 0 | AQ36: 1.03 | AR36: 0 | AS36: 0 | AT36: 90 | AU36: 46 | AV36: 1.047 | AW36: 1 | AZ36: 1 | BA36: 1 | BB36: 1 | BC36: 1 | BH36: 0 | BI36: 2 | BJ36: ТСН-2001.4 Доп. 68, Сб. 11, т. 12, поз. 1 | BM36: 72 | BN36: 55992028 | BO36: 4.11-12-1 | BP36: 1 | BQ36: 40 | BR36: 0 | BS36: 1 | BT36: 1 | BU36: 1 | BV36: 1 | BW36: 1 | BX36: 1 | BZ36: 90 | CA36: 46 | CE36: 30 | CF36: 0 | CG36: 0 | CM36: 0 | CN36: Поправка: Гл.12.Прил.8.п.8. 5_12.00.01.11.003 Наименование: При наличии усложненных условий производства работ (стесненность, сложность складирования и транспортной логистики, наличие в зоне производства работ действующего технологического оборудования или движения технологического транспорта и т.п.) для объектов, расположенных за пределами территории круговой магистральной системы улиц "Садовое кольцо" и за пределами Третьего транспортного кольца города Москвы пунктов "а" и "б", но в пределах Московской кольцевой автомобильной дороги | CO36: 0 | CP36: =(P36+Q36+S36) -> 14 | CQ36: =ROUND((ROUND((AC36*AW36*1),2)*BC36),2) -> 0 | CR36: =(ROUND((ROUND((((ET36*1.1))*AV36*1),2)*BB36),2)+ROUND((ROUND(((AE36-((EU36*1.1)))*AV36*1),2)*BS36),2)) -> 0.58 | CS36: =ROUND((ROUND((AE36*AV36*1),2)*BS36),2) -> 0.09 | CT36: =ROUND((ROUND((AF36*AV36*1),2)*BA36),2) -> 13.42 | CU36: =AG36 -> 0 | CV36: =(AH36*AV36) -> 1.186251 | CW36: =AI36 -> 0 | CX36: =AJ36 -> 0 | CY36: =(((S36+R36)*AT36)/100) -> 12.159 | CZ36: =(((S36+R36)*AU36)/100) -> 6.2146 | DE36: *1,1 | DF36: *1,1 | DG36: *1,1 | DI36: *1,1 | DJ36: *1,1 | DN36: 0 | DO36: 0 | DP36: 1 | DQ36: 1 | DU36: 1013 | DV36: 1 ШТ. | DW36: 1 ШТ. | DX36: 1 | EE36: 55992157 | EF36: 40 | EG36: Монтаж оборудования | EH36: 0 | EJ36: 2 | EK36: 72 | EL36: ТСН-2001.4-11. Приборы и средства автоматизации и вычислительной техники | EM36: ТСН-2001.4-11-1 | EO36: Поправка: Гл.12.Прил.8.п.8. 5_12.00.01.11.003 | EQ36: 0 | ER36: 12.15 | ES36: 0 | ET36: 0.5 | EU36: 0.08 | EV36: 11.65 | EW36: 1.03 | EX36: 0 | EY36: 0 | FQ36: 0 | FR36: 0 | FS36: 0 | FX36: 90 | FY36: 46 | GD36: 1 | GF36: 1708693888 | GG36: 2 | GH36: 1 | GI36: 2 | GJ36: 0 | GK36: 0 | GL36: =ROUND(IF(AND(BH36=3,BI36=3,FS36<>0),P36,0),2) -> 0 | GM36: =ROUND(O36+X36+Y36,2)+GX36 -> 32.37 | GN36: =IF(OR(BI36=0,BI36=1),GM36-GX36,0) -> 0 | GO36: =IF(BI36=2,GM36-GX36,0) -> 32.37 | GP36: =IF(BI36=4,GM36-GX36,0) -> 0 | GR36: 0 | GS36: 3 | GT36: 0 | GV36: =ROUND((GT36),6) -> 0 | GW36: 1 | GX36: =ROUND(HC36*I36,2) -> 0 | HA36: 0 | HB36: 0 | HC36: =GV36*GW36 -> 0 | HS36: 0 | IK36: 0
A37: 17 | B37: 1 | C37: =ROW(SmtRes!A22) -> 22 | D37: =ROW(EtalonRes!A26) -> 26 | E37: 4 | F37: 4.11-12-1 | G37: Установка съемных и выдвижных блоков (модулей, ячеек, ТЭЗ) массой до 5 кг | H37: 1 ШТ. | I37: 1 | J37: 0 | K37: 1 | O37: =ROUND(CP37,2) -> 747.4 | P37: =ROUND((ROUND((AC37*AW37*I37),2)*BC37),2) -> 0 | Q37: =(ROUND((ROUND((((ET37*1.1))*AV37*I37),2)*BB37),2)+ROUND((ROUND(((AE37-((EU37*1.1)))*AV37*I37),2)*BS37),2)) -> 9.43 | R37: =ROUND((ROUND((AE37*AV37*I37),2)*BS37),2) -> 4.95 | S37: =ROUND((ROUND((AF37*AV37*I37),2)*BA37),2) -> 737.97 | T37: =ROUND(CU37*I37,2) -> 0 | U37: =CV37*I37 -> 1.186251 | V37: =CW37*I37 -> 0 | W37: =ROUND(CX37*I37,2) -> 0 | X37: =ROUND(CY37,2) -> 668.63 | Y37: =ROUND(CZ37,2) -> 341.74 | AA37: 56959431 | AB37: =ROUND((AC37+AD37+AF37),6) -> 13.365 | AC37: =ROUND((ES37),6) -> 0 | AD37: =ROUND(((((ET37*1.1))-((EU37*1.1)))+AE37),6) -> 0.55 | AE37: =ROUND(((EU37*1.1)),6) -> 0.088 | AF37: =ROUND(((EV37*1.1)),6) -> 12.815 | AG37: =ROUND((AP37),6) -> 0 | AH37: =((EW37*1.1)) -> 1.133 | AI37: =((EX37*1.1)) -> 0 | AJ37: =(AS37) -> 0 | AK37: 12.15 | AL37: 0 | AM37: 0.5 | AN37: 0.08 | AO37: 11.65 | AP37: 0 | AQ37: 1.03 | AR37: 0 | AS37: 0 | AT37: 90 | AU37: 46 | AV37: 1.047 | AW37: 1 | AZ37: 1 | BA37: 54.99 | BB37: 16.26 | BC37: 1 | BH37: 0 | BI37: 2 | BJ37: ТСН-2001.4 Доп. 68, Сб. 11, т. 12, поз. 1 | BM37: 72 | BN37: 55992028 | BO37: 4.11-12-1 | BP37: 1 | BQ37: 40 | BR37: 0 | BS37: 54.99 | BT37: 1 | BU37: 1 | BV37: 1 | BW37: 1 | BX37: 1 | BZ37: 90 | CA37: 46 | CE37: 30 | CF37: 0 | CG37: 0 | CM37: 0 | CN37: Поправка: Гл.12.Прил.8.п.8. 5_12.00.01.11.003 Наименование: При наличии усложненных условий производства работ (стесненность, сложность складирования и транспортной логистики, наличие в зоне производства работ действующего технологического оборудования или движения технологического транспорта и т.п.) для объектов, расположенных за пределами территории круговой магистральной системы улиц "Садовое кольцо" и за пределами Третьего транспортного кольца города Москвы пунктов "а" и "б", но в пределах Московской кольцевой автомобильной дороги | CO37: 0 | CP37: =(P37+Q37+S37) -> 747.4 | CQ37: =ROUND((ROUND((AC37*AW37*1),2)*BC37),2) -> 0 | CR37: =(ROUND((ROUND((((ET37*1.1))*AV37*1),2)*BB37),2)+ROUND((ROUND(((AE37-((EU37*1.1)))*AV37*1),2)*BS37),2)) -> 9.43 | CS37: =ROUND((ROUND((AE37*AV37*1),2)*BS37),2) -> 4.95 | CT37: =ROUND((ROUND((AF37*AV37*1),2)*BA37),2) -> 737.97 | CU37: =AG37 -> 0 | CV37: =(AH37*AV37) -> 1.186251 | CW37: =AI37 -> 0 | CX37: =AJ37 -> 0 | CY37: =(((S37+R37)*AT37)/100) -> 668.628 | CZ37: =(((S37+R37)*AU37)/100) -> 341.7432 | DE37: *1,1 | DF37: *1,1 | DG37: *1,1 | DI37: *1,1 | DJ37: *1,1 | DN37: 0 | DO37: 0 | DP37: 1 | DQ37: 1 | DU37: 1013 | DV37: 1 ШТ. | DW37: 1 ШТ. | DX37: 1 | EE37: 55992157 | EF37: 40 | EG37: Монтаж оборудования | EH37: 0 | EJ37: 2 | EK37: 72 | EL37: ТСН-2001.4-11. Приборы и средства автоматизации и вычислительной техники | EM37: ТСН-2001.4-11-1 | EO37: Поправка: Гл.12.Прил.8.п.8. 5_12.00.01.11.003 | EQ37: 0 | ER37: 12.15 | ES37: 0 | ET37: 0.5 | EU37: 0.08 | EV37: 11.65 | EW37: 1.03 | EX37: 0 | EY37: 0 | FQ37: 0 | FR37: 0 | FS37: 0 | FX37: 90 | FY37: 46 | GD37: 1 | GF37: 1708693888 | GG37: 2 | GH37: 1 | GI37: 2 | GJ37: 0 | GK37: 0 | GL37: =ROUND(IF(AND(BH37=3,BI37=3,FS37<>0),P37,0),2) -> 0 | GM37: =ROUND(O37+X37+Y37,2)+GX37 -> 1757.77 | GN37: =IF(OR(BI37=0,BI37=1),GM37-GX37,0) -> 0 | GO37: =IF(BI37=2,GM37-GX37,0) -> 1757.77 | GP37: =IF(BI37=4,GM37-GX37,0) -> 0 | GR37: 0 | GS37: 3 | GT37: 0 | GV37: =ROUND((GT37),6) -> 0 | GW37: 1 | GX37: =ROUND(HC37*I37,2) -> 0 | HA37: 0 | HB37: 0 | HC37: =GV37*GW37 -> 0 | HS37: 0 | IK37: 0
A38: 17 | B38: 1 | E38: 5 | F38: КА №2 | G38: Шлюз tGW-715i Segnetics | H38: шт. | I38: 1 | J38: 0 | K38: 1 | O38: =ROUND(CP38,2) -> 1618.36 | P38: =ROUND((ROUND((AC38*I38),2)*BC38),2) -> 1618.36 | Q38: =(ROUND((ROUND(((ET38)*AV38*I38),2)*BB38),2)+ROUND((ROUND(((AE38-(EU38))*AV38*I38),2)*BS38),2)) -> 0 | R38: =ROUND((ROUND((AE38*AV38*I38),2)*BS38),2) -> 0 | S38: =ROUND((ROUND((AF38*AV38*I38),2)*BA38),2) -> 0 | T38: =ROUND(CU38*I38,2) -> 0 | U38: =CV38*I38 -> 0 | V38: =CW38*I38 -> 0 | W38: =ROUND(CX38*I38,2) -> 0 | X38: =ROUND(CY38,2) -> 0 | Y38: =ROUND(CZ38,2) -> 0 | AA38: 56959434 | AB38: =ROUND((AC38+AD38+AF38),6) -> 1618.36 | AC38: =ROUND((ES38),6) -> 1618.36 | AD38: =ROUND((((ET38)-(EU38))+AE38),6) -> 0 | AE38: =ROUND((EU38),6) -> 0 | AF38: =ROUND((EV38),6) -> 0 | AG38: =ROUND((AP38),6) -> 0 | AH38: =(EW38) -> 0 | AI38: =(EX38) -> 0 | AJ38: =(AS38) -> 0 | AK38: 1618.36 | AL38: 1618.36 | AM38: 0 | AN38: 0 | AO38: 0 | AP38: 0 | AQ38: 0 | AR38: 0 | AS38: 0 | AT38: 0 | AU38: 0 | AV38: 1 | AW38: 1 | AZ38: 1 | BA38: 1 | BB38: 1 | BC38: 1 | BH38: 3 | BI38: 3 | BM38: 746 | BN38: 0 | BP38: 0 | BQ38: 130 | BR38: 0 | BS38: 1 | BT38: 1 | BU38: 1 | BV38: 1 | BW38: 1 | BX38: 1 | BZ38: 0 | CA38: 0 | CE38: 30 | CF38: 0 | CG38: 0 | CM38: 0 | CO38: 0 | CP38: =(P38+Q38+S38) -> 1618.36 | CQ38: =ROUND((ROUND((AC38*1),2)*BC38),2) -> 1618.36 | CR38: =(ROUND((ROUND(((ET38)*AV38*1),2)*BB38),2)+ROUND((ROUND(((AE38-(EU38))*AV38*1),2)*BS38),2)) -> 0 | CS38: =ROUND((ROUND((AE38*AV38*1),2)*BS38),2) -> 0 | CT38: =ROUND((ROUND((AF38*AV38*1),2)*BA38),2) -> 0 | CU38: =AG38 -> 0 | CV38: =(AH38*AV38) -> 0 | CW38: =AI38 -> 0 | CX38: =AJ38 -> 0 | CY38: =(((S38+R38)*AT38)/100) -> 0 | CZ38: =(((S38+R38)*AU38)/100) -> 0 | DN38: 0 | DO38: 0 | DP38: 1 | DQ38: 1 | DU38: 1010 | DV38: шт. | DW38: шт. | DX38: 1 | EE38: 55992259 | EF38: 130 | EG38: Сметная стоимость оборудования | EH38: 0 | EJ38: 3 | EK38: 746 | EL38: ТСН-2001.13. Сметная стоимость оборудования | EM38: ТСН-2001.13 | EQ38: 0 | ER38: 0 | ES38: 1618.36 | ET38: 0 | EU38: 0 | EV38: 0 | EW38: 0 | EX38: 0 | EY38: 0 | FQ38: 0 | FR38: =P38 -> 1618.36 | FS38: 0 | FX38: 0 | FY38: 0 | GA38: [14 271,44 / 1,2 / 7,66] + 3% Трансп + 1,2% Заг.скл | GD38: 1 | GF38: 493595391 | GG38: 2 | GH38: 4 | GI38: -2 | GJ38: 0 | GK38: 0 | GL38: =ROUND(IF(AND(BH38=3,BI38=3,FS38<>0),P38,0),2) -> 0 | GM38: =ROUND(O38+X38+Y38,2)+GX38 -> 1618.36 | GN38: =IF(OR(BI38=0,BI38=1),GM38-GX38,0) -> 0 | GO38: =IF(BI38=2,GM38-GX38,0) -> 0 | GP38: =IF(BI38=4,GM38-GX38,0) -> 0 | GR38: 0 | GS38: 2 | GT38: 0 | GV38: =ROUND((GT38),6) -> 0 | GW38: 1 | GX38: =ROUND(HC38*I38,2) -> 0 | HA38: 0 | HB38: 0 | HC38: =GV38*GW38 -> 0 | HE38: 3 | HF38: 1,2 | HS38: 0 | IK38: 0
A39: 17 | B39: 1 | E39: 5 | F39: КА №2 | G39: Шлюз tGW-715i Segnetics | H39: шт. | I39: 1 | J39: 0 | K39: 1 | O39: =ROUND(CP39,2) -> 12396.64 | P39: =ROUND((ROUND((AC39*I39),2)*BC39),2) -> 12396.64 | Q39: =(ROUND((ROUND(((ET39)*AV39*I39),2)*BB39),2)+ROUND((ROUND(((AE39-(EU39))*AV39*I39),2)*BS39),2)) -> 0 | R39: =ROUND((ROUND((AE39*AV39*I39),2)*BS39),2) -> 0 | S39: =ROUND((ROUND((AF39*AV39*I39),2)*BA39),2) -> 0 | T39: =ROUND(CU39*I39,2) -> 0 | U39: =CV39*I39 -> 0 | V39: =CW39*I39 -> 0 | W39: =ROUND(CX39*I39,2) -> 0 | X39: =ROUND(CY39,2) -> 0 | Y39: =ROUND(CZ39,2) -> 0 | AA39: 56959431 | AB39: =ROUND((AC39+AD39+AF39),6) -> 1618.36 | AC39: =ROUND((ES39),6) -> 1618.36 | AD39: =ROUND((((ET39)-(EU39))+AE39),6) -> 0 | AE39: =ROUND((EU39),6) -> 0 | AF39: =ROUND((EV39),6) -> 0 | AG39: =ROUND((AP39),6) -> 0 | AH39: =(EW39) -> 0 | AI39: =(EX39) -> 0 | AJ39: =(AS39) -> 0 | AK39: 1618.36 | AL39: 1618.36 | AM39: 0 | AN39: 0 | AO39: 0 | AP39: 0 | AQ39: 0 | AR39: 0 | AS39: 0 | AT39: 0 | AU39: 0 | AV39: 1 | AW39: 1 | AZ39: 1 | BA39: 1 | BB39: 1 | BC39: 7.66 | BH39: 3 | BI39: 3 | BM39: 746 | BN39: 0 | BP39: 0 | BQ39: 130 | BR39: 0 | BS39: 1 | BT39: 1 | BU39: 1 | BV39: 1 | BW39: 1 | BX39: 1 | BZ39: 0 | CA39: 0 | CE39: 30 | CF39: 0 | CG39: 0 | CM39: 0 | CO39: 0 | CP39: =(P39+Q39+S39) -> 12396.64 | CQ39: =ROUND((ROUND((AC39*1),2)*BC39),2) -> 12396.64 | CR39: =(ROUND((ROUND(((ET39)*AV39*1),2)*BB39),2)+ROUND((ROUND(((AE39-(EU39))*AV39*1),2)*BS39),2)) -> 0 | CS39: =ROUND((ROUND((AE39*AV39*1),2)*BS39),2) -> 0 | CT39: =ROUND((ROUND((AF39*AV39*1),2)*BA39),2) -> 0 | CU39: =AG39 -> 0 | CV39: =(AH39*AV39) -> 0 | CW39: =AI39 -> 0 | CX39: =AJ39 -> 0 | CY39: =(((S39+R39)*AT39)/100) -> 0 | CZ39: =(((S39+R39)*AU39)/100) -> 0 | DN39: 0 | DO39: 0 | DP39: 1 | DQ39: 1 | DU39: 1010 | DV39: шт. | DW39: шт. | DX39: 1 | EE39: 55992259 | EF39: 130 | EG39: Сметная стоимость оборудования | EH39: 0 | EJ39: 3 | EK39: 746 | EL39: ТСН-2001.13. Сметная стоимость оборудования | EM39: ТСН-2001.13 | EQ39: 0 | ER39: 1618.36 | ES39: 1618.36 | ET39: 0 | EU39: 0 | EV39: 0 | EW39: 0 | EX39: 0 | EY39: 0 | EZ39: 5 | FC39: 1 | FD39: 18 | FF39: 14271.44 | FQ39: 0 | FR39: =P39 -> 12396.64 | FS39: 0 | FX39: 0 | FY39: 0 | GA39: [14 271,44 / 1,2 / 7,66] + 3% Трансп + 1,2% Заг.скл | GD39: 1 | GF39: 493595391 | GG39: 2 | GH39: 3 | GI39: 5 | GJ39: 0 | GK39: 0 | GL39: =ROUND(IF(AND(BH39=3,BI39=3,FS39<>0),P39,0),2) -> 0 | GM39: =ROUND(O39+X39+Y39,2)+GX39 -> 12396.64 | GN39: =IF(OR(BI39=0,BI39=1),GM39-GX39,0) -> 0 | GO39: =IF(BI39=2,GM39-GX39,0) -> 0 | GP39: =IF(BI39=4,GM39-GX39,0) -> 0 | GR39: 1 | GS39: 1 | GT39: 0 | GV39: =ROUND((GT39),6) -> 0 | GW39: 1 | GX39: =ROUND(HC39*I39,2) -> 0 | HA39: 0 | HB39: 0 | HC39: =GV39*GW39 -> 0 | HE39: 3 | HF39: 1,2 | HS39: 0 | IK39: 0
A40: 17 | B40: 1 | C40: =ROW(SmtRes!A26) -> 26 | D40: =ROW(EtalonRes!A31) -> 31 | E40: 6 | F40: 4.10-176-1 | G40: Монтаж блока контроля датчиков (контроллер) | H40: 10 шт. | I40: =ROUND(1/10,9) -> 0.1 | J40: 0 | K40: =ROUND(1/10,9) -> 0.1 | O40: =ROUND(CP40,2) -> 54.5 | P40: =ROUND((ROUND((AC40*AW40*I40),2)*BC40),2) -> 0.13 | Q40: =(ROUND((ROUND((((ET40*1.1))*AV40*I40),2)*BB40),2)+ROUND((ROUND(((AE40-((EU40*1.1)))*AV40*I40),2)*BS40),2)) -> 0.13 | R40: =ROUND((ROUND((AE40*AV40*I40),2)*BS40),2) -> 0.01 | S40: =ROUND((ROUND((AF40*AV40*I40),2)*BA40),2) -> 54.24 | T40: =ROUND(CU40*I40,2) -> 0 | U40: =CV40*I40 -> 3.4504932 | V40: =CW40*I40 -> 0 | W40: =ROUND(CX40*I40,2) -> 0 | X40: =ROUND(CY40,2) -> 48.83 | Y40: =ROUND(CZ40,2) -> 24.96 | AA40: 56959434 | AB40: =ROUND((AC40+AD40+AF40),6) -> 520.534 | AC40: =ROUND((ES40),6) -> 1.29 | AD40: =ROUND(((((ET40*1.1))-((EU40*1.1)))+AE40),6) -> 1.21 | AE40: =ROUND(((EU40*1.1)),6) -> 0.143 | AF40: =ROUND(((EV40*1.1)),6) -> 518.034 | AG40: =ROUND((AP40),6) -> 0 | AH40: =((EW40*1.1)) -> 32.956 | AI40: =((EX40*1.1)) -> 0 | AJ40: =(AS40) -> 0 | AK40: 473.33 | AL40: 1.29 | AM40: 1.1 | AN40: 0.13 | AO40: 470.94 | AP40: 0 | AQ40: 29.96 | AR40: 0 | AS40: 0 | AT40: 90 | AU40: 46 | AV40: 1.047 | AW40: 1 | AZ40: 1 | BA40: 1 | BB40: 1 | BC40: 1 | BH40: 0 | BI40: 2 | BJ40: ТСН-2001.4 Доп. 80, Сб. 10, т. 176, поз. 1 | BM40: 68 | BN40: 55992028 | BO40: 4.10-176-1 | BP40: 1 | BQ40: 40 | BR40: 0 | BS40: 1 | BT40: 1 | BU40: 1 | BV40: 1 | BW40: 1 | BX40: 1 | BZ40: 90 | CA40: 46 | CE40: 30 | CF40: 0 | CG40: 0 | CM40: 0 | CN40: Поправка: Гл.12.Прил.8.п.8. 5_12.00.01.11.003 Наименование: При наличии усложненных условий производства работ (стесненность, сложность складирования и транспортной логистики, наличие в зоне производства работ действующего технологического оборудования или движения технологического транспорта и т.п.) для объектов, расположенных за пределами территории круговой магистральной системы улиц "Садовое кольцо" и за пределами Третьего транспортного кольца города Москвы пунктов "а" и "б", но в пределах Московской кольцевой автомобильной дороги | CO40: 0 | CP40: =(P40+Q40+S40) -> 54.5 | CQ40: =ROUND((ROUND((AC40*AW40*1),2)*BC40),2) -> 1.29 | CR40: =(ROUND((ROUND((((ET40*1.1))*AV40*1),2)*BB40),2)+ROUND((ROUND(((AE40-((EU40*1.1)))*AV40*1),2)*BS40),2)) -> 1.27 | CS40: =ROUND((ROUND((AE40*AV40*1),2)*BS40),2) -> 0.15 | CT40: =ROUND((ROUND((AF40*AV40*1),2)*BA40),2) -> 542.38 | CU40: =AG40 -> 0 | CV40: =(AH40*AV40) -> 34.504932 | CW40: =AI40 -> 0 | CX40: =AJ40 -> 0 | CY40: =(((S40+R40)*AT40)/100) -> 48.825 | CZ40: =(((S40+R40)*AU40)/100) -> 24.955 | DE40: *1,1 | DF40: *1,1 | DG40: *1,1 | DI40: *1,1 | DJ40: *1,1 | DN40: 0 | DO40: 0 | DP40: 1 | DQ40: 1 | DU40: 1010 | DV40: 10 шт. | DW40: 10 шт. | DX40: 10 | EE40: 55992152 | EF40: 40 | EG40: Монтаж оборудования | EH40: 0 | EJ40: 2 | EK40: 68 | EL40: ТСН-2001.4-10. Прокладка и монтаж сетей связи | EM40: ТСН-2001.4-10-1 | EO40: Поправка: Гл.12.Прил.8.п.8. 5_12.00.01.11.003 | EQ40: 0 | ER40: 473.33 | ES40: 1.29 | ET40: 1.1 | EU40: 0.13 | EV40: 470.94 | EW40: 29.96 | EX40: 0 | EY40: 0 | FQ40: 0 | FR40: 0 | FS40: 0 | FX40: 90 | FY40: 46 | GD40: 1 | GF40: -733186695 | GG40: 2 | GH40: 1 | GI40: 2 | GJ40: 0 | GK40: 0 | GL40: =ROUND(IF(AND(BH40=3,BI40=3,FS40<>0),P40,0),2) -> 0 | GM40: =ROUND(O40+X40+Y40,2)+GX40 -> 128.29 | GN40: =IF(OR(BI40=0,BI40=1),GM40-GX40,0) -> 0 | GO40: =IF(BI40=2,GM40-GX40,0) -> 128.29 | GP40: =IF(BI40=4,GM40-GX40,0) -> 0 | GR40: 0 | GS40: 3 | GT40: 0 | GV40: =ROUND((GT40),6) -> 0 | GW40: 1 | GX40: =ROUND(HC40*I40,2) -> 0 | HA40: 0 | HB40: 0 | HC40: =GV40*GW40 -> 0 | HS40: 0 | IK40: 0
A41: 17 | B41: 1 | C41: =ROW(SmtRes!A30) -> 30 | D41: =ROW(EtalonRes!A36) -> 36 | E41: 6 | F41: 4.10-176-1 | G41: Монтаж блока контроля датчиков (контроллер) | H41: 10 шт. | I41: =ROUND(1/10,9) -> 0.1 | J41: 0 | K41: =ROUND(1/10,9) -> 0.1 | O41: =ROUND(CP41,2) -> 2985.48 | P41: =ROUND((ROUND((AC41*AW41*I41),2)*BC41),2) -> 0.94 | Q41: =(ROUND((ROUND((((ET41*1.1))*AV41*I41),2)*BB41),2)+ROUND((ROUND(((AE41-((EU41*1.1)))*AV41*I41),2)*BS41),2)) -> 1.88 | R41: =ROUND((ROUND((AE41*AV41*I41),2)*BS41),2) -> 0.55 | S41: =ROUND((ROUND((AF41*AV41*I41),2)*BA41),2) -> 2982.66 | T41: =ROUND(CU41*I41,2) -> 0 | U41: =CV41*I41 -> 3.4504932 | V41: =CW41*I41 -> 0 | W41: =ROUND(CX41*I41,2) -> 0 | X41: =ROUND(CY41,2) -> 2684.89 | Y41: =ROUND(CZ41,2) -> 1372.28 | AA41: 56959431 | AB41: =ROUND((AC41+AD41+AF41),6) -> 520.534 | AC41: =ROUND((ES41),6) -> 1.29 | AD41: =ROUND(((((ET41*1.1))-((EU41*1.1)))+AE41),6) -> 1.21 | AE41: =ROUND(((EU41*1.1)),6) -> 0.143 | AF41: =ROUND(((EV41*1.1)),6) -> 518.034 | AG41: =ROUND((AP41),6) -> 0 | AH41: =((EW41*1.1)) -> 32.956 | AI41: =((EX41*1.1)) -> 0 | AJ41: =(AS41) -> 0 | AK41: 473.33 | AL41: 1.29 | AM41: 1.1 | AN41: 0.13 | AO41: 470.94 | AP41: 0 | AQ41: 29.96 | AR41: 0 | AS41: 0 | AT41: 90 | AU41: 46 | AV41: 1.047 | AW41: 1 | AZ41: 1 | BA41: 54.99 | BB41: 14.48 | BC41: 7.25 | BH41: 0 | BI41: 2 | BJ41: ТСН-2001.4 Доп. 80, Сб. 10, т. 176, поз. 1 | BM41: 68 | BN41: 55992028 | BO41: 4.10-176-1 | BP41: 1 | BQ41: 40 | BR41: 0 | BS41: 54.99 | BT41: 1 | BU41: 1 | BV41: 1 | BW41: 1 | BX41: 1 | BZ41: 90 | CA41: 46 | CE41: 30 | CF41: 0 | CG41: 0 | CM41: 0 | CN41: Поправка: Гл.12.Прил.8.п.8. 5_12.00.01.11.003 Наименование: При наличии усложненных условий производства работ (стесненность, сложность складирования и транспортной логистики, наличие в зоне производства работ действующего технологического оборудования или движения технологического транспорта и т.п.) для объектов, расположенных за пределами территории круговой магистральной системы улиц "Садовое кольцо" и за пределами Третьего транспортного кольца города Москвы пунктов "а" и "б", но в пределах Московской кольцевой автомобильной дороги | CO41: 0 | CP41: =(P41+Q41+S41) -> 2985.48 | CQ41: =ROUND((ROUND((AC41*AW41*1),2)*BC41),2) -> 9.35 | CR41: =(ROUND((ROUND((((ET41*1.1))*AV41*1),2)*BB41),2)+ROUND((ROUND(((AE41-((EU41*1.1)))*AV41*1),2)*BS41),2)) -> 18.39 | CS41: =ROUND((ROUND((AE41*AV41*1),2)*BS41),2) -> 8.25 | CT41: =ROUND((ROUND((AF41*AV41*1),2)*BA41),2) -> 29825.48 | CU41: =AG41 -> 0 | CV41: =(AH41*AV41) -> 34.504932 | CW41: =AI41 -> 0 | CX41: =AJ41 -> 0 | CY41: =(((S41+R41)*AT41)/100) -> 2684.889 | CZ41: =(((S41+R41)*AU41)/100) -> 1372.2766 | DE41: *1,1 | DF41: *1,1 | DG41: *1,1 | DI41: *1,1 | DJ41: *1,1 | DN41: 0 | DO41: 0 | DP41: 1 | DQ41: 1 | DU41: 1010 | DV41: 10 шт. | DW41: 10 шт. | DX41: 10 | EE41: 55992152 | EF41: 40 | EG41: Монтаж оборудования | EH41: 0 | EJ41: 2 | EK41: 68 | EL41: ТСН-2001.4-10. Прокладка и монтаж сетей связи | EM41: ТСН-2001.4-10-1 | EO41: Поправка: Гл.12.Прил.8.п.8. 5_12.00.01.11.003 | EQ41: 0 | ER41: 473.33 | ES41: 1.29 | ET41: 1.1 | EU41: 0.13 | EV41: 470.94 | EW41: 29.96 | EX41: 0 | EY41: 0 | FQ41: 0 | FR41: 0 | FS41: 0 | FX41: 90 | FY41: 46 | GD41: 1 | GF41: -733186695 | GG41: 2 | GH41: 1 | GI41: 2 | GJ41: 0 | GK41: 0 | GL41: =ROUND(IF(AND(BH41=3,BI41=3,FS41<>0),P41,0),2) -> 0 | GM41: =ROUND(O41+X41+Y41,2)+GX41 -> 7042.65 | GN41: =IF(OR(BI41=0,BI41=1),GM41-GX41,0) -> 0 | GO41: =IF(BI41=2,GM41-GX41,0) -> 7042.65 | GP41: =IF(BI41=4,GM41-GX41,0) -> 0 | GR41: 0 | GS41: 3 | GT41: 0 | GV41: =ROUND((GT41),6) -> 0 | GW41: 1 | GX41: =ROUND(HC41*I41,2) -> 0 | HA41: 0 | HB41: 0 | HC41: =GV41*GW41 -> 0 | HS41: 0 | IK41: 0
A42: 17 | B42: 1 | E42: 7 | F42: КА №3 | G42: Контроллер Matrix-2230-70-0 Segnetics | H42: шт. | I42: 1 | J42: 0 | K42: 1 | O42: =ROUND(CP42,2) -> 3784.21 | P42: =ROUND((ROUND((AC42*I42),2)*BC42),2) -> 3784.21 | Q42: =(ROUND((ROUND(((ET42)*AV42*I42),2)*BB42),2)+ROUND((ROUND(((AE42-(EU42))*AV42*I42),2)*BS42),2)) -> 0 | R42: =ROUND((ROUND((AE42*AV42*I42),2)*BS42),2) -> 0 | S42: =ROUND((ROUND((AF42*AV42*I42),2)*BA42),2) -> 0 | T42: =ROUND(CU42*I42,2) -> 0 | U42: =CV42*I42 -> 0 | V42: =CW42*I42 -> 0 | W42: =ROUND(CX42*I42,2) -> 0 | X42: =ROUND(CY42,2) -> 0 | Y42: =ROUND(CZ42,2) -> 0 | AA42: 56959434 | AB42: =ROUND((AC42+AD42+AF42),6) -> 3784.21 | AC42: =ROUND((ES42),6) -> 3784.21 | AD42: =ROUND((((ET42)-(EU42))+AE42),6) -> 0 | AE42: =ROUND((EU42),6) -> 0 | AF42: =ROUND((EV42),6) -> 0 | AG42: =ROUND((AP42),6) -> 0 | AH42: =(EW42) -> 0 | AI42: =(EX42) -> 0 | AJ42: =(AS42) -> 0 | AK42: 3784.21 | AL42: 3784.21 | AM42: 0 | AN42: 0 | AO42: 0 | AP42: 0 | AQ42: 0 | AR42: 0 | AS42: 0 | AT42: 0 | AU42: 0 | AV42: 1 | AW42: 1 | AZ42: 1 | BA42: 1 | BB42: 1 | BC42: 1 | BH42: 3 | BI42: 3 | BM42: 746 | BN42: 0 | BP42: 0 | BQ42: 130 | BR42: 0 | BS42: 1 | BT42: 1 | BU42: 1 | BV42: 1 | BW42: 1 | BX42: 1 | BZ42: 0 | CA42: 0 | CE42: 30 | CF42: 0 | CG42: 0 | CM42: 0 | CO42: 0 | CP42: =(P42+Q42+S42) -> 3784.21 | CQ42: =ROUND((ROUND((AC42*1),2)*BC42),2) -> 3784.21 | CR42: =(ROUND((ROUND(((ET42)*AV42*1),2)*BB42),2)+ROUND((ROUND(((AE42-(EU42))*AV42*1),2)*BS42),2)) -> 0 | CS42: =ROUND((ROUND((AE42*AV42*1),2)*BS42),2) -> 0 | CT42: =ROUND((ROUND((AF42*AV42*1),2)*BA42),2) -> 0 | CU42: =AG42 -> 0 | CV42: =(AH42*AV42) -> 0 | CW42: =AI42 -> 0 | CX42: =AJ42 -> 0 | CY42: =(((S42+R42)*AT42)/100) -> 0 | CZ42: =(((S42+R42)*AU42)/100) -> 0 | DN42: 0 | DO42: 0 | DP42: 1 | DQ42: 1 | DU42: 1010 | DV42: шт. | DW42: шт. | DX42: 1 | EE42: 55992259 | EF42: 130 | EG42: Сметная стоимость оборудования | EH42: 0 | EJ42: 3 | EK42: 746 | EL42: ТСН-2001.13. Сметная стоимость оборудования | EM42: ТСН-2001.13 | EQ42: 0 | ER42: 0 | ES42: 3784.21 | ET42: 0 | EU42: 0 | EV42: 0 | EW42: 0 | EX42: 0 | EY42: 0 | FQ42: 0 | FR42: =P42 -> 3784.21 | FS42: 0 | FX42: 0 | FY42: 0 | GA42: [33 370,9 / 1,2 / 7,66] + 3% Трансп + 1,2% Заг.скл | GD42: 1 | GF42: 782956652 | GG42: 2 | GH42: 4 | GI42: -2 | GJ42: 0 | GK42: 0 | GL42: =ROUND(IF(AND(BH42=3,BI42=3,FS42<>0),P42,0),2) -> 0 | GM42: =ROUND(O42+X42+Y42,2)+GX42 -> 3784.21 | GN42: =IF(OR(BI42=0,BI42=1),GM42-GX42,0) -> 0 | GO42: =IF(BI42=2,GM42-GX42,0) -> 0 | GP42: =IF(BI42=4,GM42-GX42,0) -> 0 | GR42: 0 | GS42: 2 | GT42: 0 | GV42: =ROUND((GT42),6) -> 0 | GW42: 1 | GX42: =ROUND(HC42*I42,2) -> 0 | HA42: 0 | HB42: 0 | HC42: =GV42*GW42 -> 0 | HE42: 3 | HF42: 1,2 | HS42: 0 | IK42: 0
A43: 17 | B43: 1 | E43: 7 | F43: КА №3 | G43: Контроллер Matrix-2230-70-0 Segnetics | H43: шт. | I43: 1 | J43: 0 | K43: 1 | O43: =ROUND(CP43,2) -> 28987.05 | P43: =ROUND((ROUND((AC43*I43),2)*BC43),2) -> 28987.05 | Q43: =(ROUND((ROUND(((ET43)*AV43*I43),2)*BB43),2)+ROUND((ROUND(((AE43-(EU43))*AV43*I43),2)*BS43),2)) -> 0 | R43: =ROUND((ROUND((AE43*AV43*I43),2)*BS43),2) -> 0 | S43: =ROUND((ROUND((AF43*AV43*I43),2)*BA43),2) -> 0 | T43: =ROUND(CU43*I43,2) -> 0 | U43: =CV43*I43 -> 0 | V43: =CW43*I43 -> 0 | W43: =ROUND(CX43*I43,2) -> 0 | X43: =ROUND(CY43,2) -> 0 | Y43: =ROUND(CZ43,2) -> 0 | AA43: 56959431 | AB43: =ROUND((AC43+AD43+AF43),6) -> 3784.21 | AC43: =ROUND((ES43),6) -> 3784.21 | AD43: =ROUND((((ET43)-(EU43))+AE43),6) -> 0 | AE43: =ROUND((EU43),6) -> 0 | AF43: =ROUND((EV43),6) -> 0 | AG43: =ROUND((AP43),6) -> 0 | AH43: =(EW43) -> 0 | AI43: =(EX43) -> 0 | AJ43: =(AS43) -> 0 | AK43: 3784.21 | AL43: 3784.21 | AM43: 0 | AN43: 0 | AO43: 0 | AP43: 0 | AQ43: 0 | AR43: 0 | AS43: 0 | AT43: 0 | AU43: 0 | AV43: 1 | AW43: 1 | AZ43: 1 | BA43: 1 | BB43: 1 | BC43: 7.66 | BH43: 3 | BI43: 3 | BM43: 746 | BN43: 0 | BP43: 0 | BQ43: 130 | BR43: 0 | BS43: 1 | BT43: 1 | BU43: 1 | BV43: 1 | BW43: 1 | BX43: 1 | BZ43: 0 | CA43: 0 | CE43: 30 | CF43: 0 | CG43: 0 | CM43: 0 | CO43: 0 | CP43: =(P43+Q43+S43) -> 28987.05 | CQ43: =ROUND((ROUND((AC43*1),2)*BC43),2) -> 28987.05 | CR43: =(ROUND((ROUND(((ET43)*AV43*1),2)*BB43),2)+ROUND((ROUND(((AE43-(EU43))*AV43*1),2)*BS43),2)) -> 0 | CS43: =ROUND((ROUND((AE43*AV43*1),2)*BS43),2) -> 0 | CT43: =ROUND((ROUND((AF43*AV43*1),2)*BA43),2) -> 0 | CU43: =AG43 -> 0 | CV43: =(AH43*AV43) -> 0 | CW43: =AI43 -> 0 | CX43: =AJ43 -> 0 | CY43: =(((S43+R43)*AT43)/100) -> 0 | CZ43: =(((S43+R43)*AU43)/100) -> 0 | DN43: 0 | DO43: 0 | DP43: 1 | DQ43: 1 | DU43: 1010 | DV43: шт. | DW43: шт. | DX43: 1 | EE43: 55992259 | EF43: 130 | EG43: Сметная стоимость оборудования | EH43: 0 | EJ43: 3 | EK43: 746 | EL43: ТСН-2001.13. Сметная стоимость оборудования | EM43: ТСН-2001.13 | EQ43: 0 | ER43: 3784.21 | ES43: 3784.21 | ET43: 0 | EU43: 0 | EV43: 0 | EW43: 0 | EX43: 0 | EY43: 0 | EZ43: 5 | FC43: 1 | FD43: 18 | FF43: 33370.9 | FQ43: 0 | FR43: =P43 -> 28987.05 | FS43: 0 | FX43: 0 | FY43: 0 | GA43: [33 370,9 / 1,2 / 7,66] + 3% Трансп + 1,2% Заг.скл | GD43: 1 | GF43: 782956652 | GG43: 2 | GH43: 3 | GI43: 5 | GJ43: 0 | GK43: 0 | GL43: =ROUND(IF(AND(BH43=3,BI43=3,FS43<>0),P43,0),2) -> 0 | GM43: =ROUND(O43+X43+Y43,2)+GX43 -> 28987.05 | GN43: =IF(OR(BI43=0,BI43=1),GM43-GX43,0) -> 0 | GO43: =IF(BI43=2,GM43-GX43,0) -> 0 | GP43: =IF(BI43=4,GM43-GX43,0) -> 0 | GR43: 1 | GS43: 1 | GT43: 0 | GV43: =ROUND((GT43),6) -> 0 | GW43: 1 | GX43: =ROUND(HC43*I43,2) -> 0 | HA43: 0 | HB43: 0 | HC43: =GV43*GW43 -> 0 | HE43: 3 | HF43: 1,2 | HS43: 0 | IK43: 0
A44: 17 | B44: 1 | C44: =ROW(SmtRes!A32) -> 32 | D44: =ROW(EtalonRes!A39) -> 39 | E44: 8 | F44: 4.11-12-1 | G44: Установка съемных и выдвижных блоков (модулей, ячеек, ТЭЗ) массой до 5 кг | H44: 1 ШТ. | I44: 2 | J44: 0 | K44: 2 | O44: =ROUND(CP44,2) -> 27.98 | P44: =ROUND((ROUND((AC44*AW44*I44),2)*BC44),2) -> 0 | Q44: =(ROUND((ROUND((((ET44*1.1))*AV44*I44),2)*BB44),2)+ROUND((ROUND(((AE44-((EU44*1.1)))*AV44*I44),2)*BS44),2)) -> 1.15 | R44: =ROUND((ROUND((AE44*AV44*I44),2)*BS44),2) -> 0.18 | S44: =ROUND((ROUND((AF44*AV44*I44),2)*BA44),2) -> 26.83 | T44: =ROUND(CU44*I44,2) -> 0 | U44: =CV44*I44 -> 2.372502 | V44: =CW44*I44 -> 0 | W44: =ROUND(CX44*I44,2) -> 0 | X44: =ROUND(CY44,2) -> 24.31 | Y44: =ROUND(CZ44,2) -> 12.42 | AA44: 56959434 | AB44: =ROUND((AC44+AD44+AF44),6) -> 13.365 | AC44: =ROUND((ES44),6) -> 0 | AD44: =ROUND(((((ET44*1.1))-((EU44*1.1)))+AE44),6) -> 0.55 | AE44: =ROUND(((EU44*1.1)),6) -> 0.088 | AF44: =ROUND(((EV44*1.1)),6) -> 12.815 | AG44: =ROUND((AP44),6) -> 0 | AH44: =((EW44*1.1)) -> 1.133 | AI44: =((EX44*1.1)) -> 0 | AJ44: =(AS44) -> 0 | AK44: 12.15 | AL44: 0 | AM44: 0.5 | AN44: 0.08 | AO44: 11.65 | AP44: 0 | AQ44: 1.03 | AR44: 0 | AS44: 0 | AT44: 90 | AU44: 46 | AV44: 1.047 | AW44: 1 | AZ44: 1 | BA44: 1 | BB44: 1 | BC44: 1 | BH44: 0 | BI44: 2 | BJ44: ТСН-2001.4 Доп. 68, Сб. 11, т. 12, поз. 1 | BM44: 72 | BN44: 55992028 | BO44: 4.11-12-1 | BP44: 1 | BQ44: 40 | BR44: 0 | BS44: 1 | BT44: 1 | BU44: 1 | BV44: 1 | BW44: 1 | BX44: 1 | BZ44: 90 | CA44: 46 | CE44: 30 | CF44: 0 | CG44: 0 | CM44: 0 | CN44: Поправка: Гл.12.Прил.8.п.8. 5_12.00.01.11.003 Наименование: При наличии усложненных условий производства работ (стесненность, сложность складирования и транспортной логистики, наличие в зоне производства работ действующего технологического оборудования или движения технологического транспорта и т.п.) для объектов, расположенных за пределами территории круговой магистральной системы улиц "Садовое кольцо" и за пределами Третьего транспортного кольца города Москвы пунктов "а" и "б", но в пределах Московской кольцевой автомобильной дороги | CO44: 0 | CP44: =(P44+Q44+S44) -> 27.98 | CQ44: =ROUND((ROUND((AC44*AW44*1),2)*BC44),2) -> 0 | CR44: =(ROUND((ROUND((((ET44*1.1))*AV44*1),2)*BB44),2)+ROUND((ROUND(((AE44-((EU44*1.1)))*AV44*1),2)*BS44),2)) -> 0.58 | CS44: =ROUND((ROUND((AE44*AV44*1),2)*BS44),2) -> 0.09 | CT44: =ROUND((ROUND((AF44*AV44*1),2)*BA44),2) -> 13.42 | CU44: =AG44 -> 0 | CV44: =(AH44*AV44) -> 1.186251 | CW44: =AI44 -> 0 | CX44: =AJ44 -> 0 | CY44: =(((S44+R44)*AT44)/100) -> 24.309 | CZ44: =(((S44+R44)*AU44)/100) -> 12.4246 | DE44: *1,1 | DF44: *1,1 | DG44: *1,1 | DI44: *1,1 | DJ44: *1,1 | DN44: 0 | DO44: 0 | DP44: 1 | DQ44: 1 | DU44: 1013 | DV44: 1 ШТ. | DW44: 1 ШТ. | DX44: 1 | EE44: 55992157 | EF44: 40 | EG44: Монтаж оборудования | EH44: 0 | EJ44: 2 | EK44: 72 | EL44: ТСН-2001.4-11. Приборы и средства автоматизации и вычислительной техники | EM44: ТСН-2001.4-11-1 | EO44: Поправка: Гл.12.Прил.8.п.8. 5_12.00.01.11.003 | EQ44: 0 | ER44: 12.15 | ES44: 0 | ET44: 0.5 | EU44: 0.08 | EV44: 11.65 | EW44: 1.03 | EX44: 0 | EY44: 0 | FQ44: 0 | FR44: 0 | FS44: 0 | FX44: 90 | FY44: 46 | GD44: 1 | GF44: 1708693888 | GG44: 2 | GH44: 1 | GI44: 2 | GJ44: 0 | GK44: 0 | GL44: =ROUND(IF(AND(BH44=3,BI44=3,FS44<>0),P44,0),2) -> 0 | GM44: =ROUND(O44+X44+Y44,2)+GX44 -> 64.71 | GN44: =IF(OR(BI44=0,BI44=1),GM44-GX44,0) -> 0 | GO44: =IF(BI44=2,GM44-GX44,0) -> 64.71 | GP44: =IF(BI44=4,GM44-GX44,0) -> 0 | GR44: 0 | GS44: 3 | GT44: 0 | GV44: =ROUND((GT44),6) -> 0 | GW44: 1 | GX44: =ROUND(HC44*I44,2) -> 0 | HA44: 0 | HB44: 0 | HC44: =GV44*GW44 -> 0 | HS44: 0 | IK44: 0
A45: 17 | B45: 1 | C45: =ROW(SmtRes!A34) -> 34 | D45: =ROW(EtalonRes!A42) -> 42 | E45: 8 | F45: 4.11-12-1 | G45: Установка съемных и выдвижных блоков (модулей, ячеек, ТЭЗ) массой до 5 кг | H45: 1 ШТ. | I45: 2 | J45: 0 | K45: 2 | O45: =ROUND(CP45,2) -> 1494.08 | P45: =ROUND((ROUND((AC45*AW45*I45),2)*BC45),2) -> 0 | Q45: =(ROUND((ROUND((((ET45*1.1))*AV45*I45),2)*BB45),2)+ROUND((ROUND(((AE45-((EU45*1.1)))*AV45*I45),2)*BS45),2)) -> 18.7 | R45: =ROUND((ROUND((AE45*AV45*I45),2)*BS45),2) -> 9.9 | S45: =ROUND((ROUND((AF45*AV45*I45),2)*BA45),2) -> 1475.38 | T45: =ROUND(CU45*I45,2) -> 0 | U45: =CV45*I45 -> 2.372502 | V45: =CW45*I45 -> 0 | W45: =ROUND(CX45*I45,2) -> 0 | X45: =ROUND(CY45,2) -> 1336.75 | Y45: =ROUND(CZ45,2) -> 683.23 | AA45: 56959431 | AB45: =ROUND((AC45+AD45+AF45),6) -> 13.365 | AC45: =ROUND((ES45),6) -> 0 | AD45: =ROUND(((((ET45*1.1))-((EU45*1.1)))+AE45),6) -> 0.55 | AE45: =ROUND(((EU45*1.1)),6) -> 0.088 | AF45: =ROUND(((EV45*1.1)),6) -> 12.815 | AG45: =ROUND((AP45),6) -> 0 | AH45: =((EW45*1.1)) -> 1.133 | AI45: =((EX45*1.1)) -> 0 | AJ45: =(AS45) -> 0 | AK45: 12.15 | AL45: 0 | AM45: 0.5 | AN45: 0.08 | AO45: 11.65 | AP45: 0 | AQ45: 1.03 | AR45: 0 | AS45: 0 | AT45: 90 | AU45: 46 | AV45: 1.047 | AW45: 1 | AZ45: 1 | BA45: 54.99 | BB45: 16.26 | BC45: 1 | BH45: 0 | BI45: 2 | BJ45: ТСН-2001.4 Доп. 68, Сб. 11, т. 12, поз. 1 | BM45: 72 | BN45: 55992028 | BO45: 4.11-12-1 | BP45: 1 | BQ45: 40 | BR45: 0 | BS45: 54.99 | BT45: 1 | BU45: 1 | BV45: 1 | BW45: 1 | BX45: 1 | BZ45: 90 | CA45: 46 | CE45: 30 | CF45: 0 | CG45: 0 | CM45: 0 | CN45: Поправка: Гл.12.Прил.8.п.8. 5_12.00.01.11.003 Наименование: При наличии усложненных условий производства работ (стесненность, сложность складирования и транспортной логистики, наличие в зоне производства работ действующего технологического оборудования или движения технологического транспорта и т.п.) для объектов, расположенных за пределами территории круговой магистральной системы улиц "Садовое кольцо" и за пределами Третьего транспортного кольца города Москвы пунктов "а" и "б", но в пределах Московской кольцевой автомобильной дороги | CO45: 0 | CP45: =(P45+Q45+S45) -> 1494.08 | CQ45: =ROUND((ROUND((AC45*AW45*1),2)*BC45),2) -> 0 | CR45: =(ROUND((ROUND((((ET45*1.1))*AV45*1),2)*BB45),2)+ROUND((ROUND(((AE45-((EU45*1.1)))*AV45*1),2)*BS45),2)) -> 9.43 | CS45: =ROUND((ROUND((AE45*AV45*1),2)*BS45),2) -> 4.95 | CT45: =ROUND((ROUND((AF45*AV45*1),2)*BA45),2) -> 737.97 | CU45: =AG45 -> 0 | CV45: =(AH45*AV45) -> 1.186251 | CW45: =AI45 -> 0 | CX45: =AJ45 -> 0 | CY45: =(((S45+R45)*AT45)/100) -> 1336.752 | CZ45: =(((S45+R45)*AU45)/100) -> 683.2288 | DE45: *1,1 | DF45: *1,1 | DG45: *1,1 | DI45: *1,1 | DJ45: *1,1 | DN45: 0 | DO45: 0 | DP45: 1 | DQ45: 1 | DU45: 1013 | DV45: 1 ШТ. | DW45: 1 ШТ. | DX45: 1 | EE45: 55992157 | EF45: 40 | EG45: Монтаж оборудования | EH45: 0 | EJ45: 2 | EK45: 72 | EL45: ТСН-2001.4-11. Приборы и средства автоматизации и вычислительной техники | EM45: ТСН-2001.4-11-1 | EO45: Поправка: Гл.12.Прил.8.п.8. 5_12.00.01.11.003 | EQ45: 0 | ER45: 12.15 | ES45: 0 | ET45: 0.5 | EU45: 0.08 | EV45: 11.65 | EW45: 1.03 | EX45: 0 | EY45: 0 | FQ45: 0 | FR45: 0 | FS45: 0 | FX45: 90 | FY45: 46 | GD45: 1 | GF45: 1708693888 | GG45: 2 | GH45: 1 | GI45: 2 | GJ45: 0 | GK45: 0 | GL45: =ROUND(IF(AND(BH45=3,BI45=3,FS45<>0),P45,0),2) -> 0 | GM45: =ROUND(O45+X45+Y45,2)+GX45 -> 3514.06 | GN45: =IF(OR(BI45=0,BI45=1),GM45-GX45,0) -> 0 | GO45: =IF(BI45=2,GM45-GX45,0) -> 3514.06 | GP45: =IF(BI45=4,GM45-GX45,0) -> 0 | GR45: 0 | GS45: 3 | GT45: 0 | GV45: =ROUND((GT45),6) -> 0 | GW45: 1 | GX45: =ROUND(HC45*I45,2) -> 0 | HA45: 0 | HB45: 0 | HC45: =GV45*GW45 -> 0 | HS45: 0 | IK45: 0
A46: 17 | B46: 1 | E46: 9 | F46: КА №4 | G46: модуль сбора сигналов FMR-2222-10-0 Segnetics | H46: шт. | I46: 2 | J46: 0 | K46: 2 | O46: =ROUND(CP46,2) -> 2951.1 | P46: =ROUND((ROUND((AC46*I46),2)*BC46),2) -> 2951.1 | Q46: =(ROUND((ROUND(((ET46)*AV46*I46),2)*BB46),2)+ROUND((ROUND(((AE46-(EU46))*AV46*I46),2)*BS46),2)) -> 0 | R46: =ROUND((ROUND((AE46*AV46*I46),2)*BS46),2) -> 0 | S46: =ROUND((ROUND((AF46*AV46*I46),2)*BA46),2) -> 0 | T46: =ROUND(CU46*I46,2) -> 0 | U46: =CV46*I46 -> 0 | V46: =CW46*I46 -> 0 | W46: =ROUND(CX46*I46,2) -> 0 | X46: =ROUND(CY46,2) -> 0 | Y46: =ROUND(CZ46,2) -> 0 | AA46: 56959434 | AB46: =ROUND((AC46+AD46+AF46),6) -> 1475.55 | AC46: =ROUND((ES46),6) -> 1475.55 | AD46: =ROUND((((ET46)-(EU46))+AE46),6) -> 0 | AE46: =ROUND((EU46),6) -> 0 | AF46: =ROUND((EV46),6) -> 0 | AG46: =ROUND((AP46),6) -> 0 | AH46: =(EW46) -> 0 | AI46: =(EX46) -> 0 | AJ46: =(AS46) -> 0 | AK46: 1475.55 | AL46: 1475.55 | AM46: 0 | AN46: 0 | AO46: 0 | AP46: 0 | AQ46: 0 | AR46: 0 | AS46: 0 | AT46: 0 | AU46: 0 | AV46: 1 | AW46: 1 | AZ46: 1 | BA46: 1 | BB46: 1 | BC46: 1 | BH46: 3 | BI46: 3 | BM46: 746 | BN46: 0 | BP46: 0 | BQ46: 130 | BR46: 0 | BS46: 1 | BT46: 1 | BU46: 1 | BV46: 1 | BW46: 1 | BX46: 1 | BZ46: 0 | CA46: 0 | CE46: 30 | CF46: 0 | CG46: 0 | CM46: 0 | CO46: 0 | CP46: =(P46+Q46+S46) -> 2951.1 | CQ46: =ROUND((ROUND((AC46*1),2)*BC46),2) -> 1475.55 | CR46: =(ROUND((ROUND(((ET46)*AV46*1),2)*BB46),2)+ROUND((ROUND(((AE46-(EU46))*AV46*1),2)*BS46),2)) -> 0 | CS46: =ROUND((ROUND((AE46*AV46*1),2)*BS46),2) -> 0 | CT46: =ROUND((ROUND((AF46*AV46*1),2)*BA46),2) -> 0 | CU46: =AG46 -> 0 | CV46: =(AH46*AV46) -> 0 | CW46: =AI46 -> 0 | CX46: =AJ46 -> 0 | CY46: =(((S46+R46)*AT46)/100) -> 0 | CZ46: =(((S46+R46)*AU46)/100) -> 0 | DN46: 0 | DO46: 0 | DP46: 1 | DQ46: 1 | DU46: 1010 | DV46: шт. | DW46: шт. | DX46: 1 | EE46: 55992259 | EF46: 130 | EG46: Сметная стоимость оборудования | EH46: 0 | EJ46: 3 | EK46: 746 | EL46: ТСН-2001.13. Сметная стоимость оборудования | EM46: ТСН-2001.13 | EQ46: 0 | ER46: 0 | ES46: 1475.55 | ET46: 0 | EU46: 0 | EV46: 0 | EW46: 0 | EX46: 0 | EY46: 0 | FQ46: 0 | FR46: =P46 -> 2951.1 | FS46: 0 | FX46: 0 | FY46: 0 | GA46: [13 012 / 1,2 / 7,66] + 3% Трансп + 1,2% Заг.скл | GD46: 1 | GF46: 1155956824 | GG46: 2 | GH46: 4 | GI46: -2 | GJ46: 0 | GK46: 0 | GL46: =ROUND(IF(AND(BH46=3,BI46=3,FS46<>0),P46,0),2) -> 0 | GM46: =ROUND(O46+X46+Y46,2)+GX46 -> 2951.1 | GN46: =IF(OR(BI46=0,BI46=1),GM46-GX46,0) -> 0 | GO46: =IF(BI46=2,GM46-GX46,0) -> 0 | GP46: =IF(BI46=4,GM46-GX46,0) -> 0 | GR46: 0 | GS46: 2 | GT46: 0 | GV46: =ROUND((GT46),6) -> 0 | GW46: 1 | GX46: =ROUND(HC46*I46,2) -> 0 | HA46: 0 | HB46: 0 | HC46: =GV46*GW46 -> 0 | HE46: 3 | HF46: 1,2 | HS46: 0 | IK46: 0
A47: 17 | B47: 1 | E47: 9 | F47: КА №4 | G47: модуль сбора сигналов FMR-2222-10-0 Segnetics | H47: шт. | I47: 2 | J47: 0 | K47: 2 | O47: =ROUND(CP47,2) -> 22605.43 | P47: =ROUND((ROUND((AC47*I47),2)*BC47),2) -> 22605.43 | Q47: =(ROUND((ROUND(((ET47)*AV47*I47),2)*BB47),2)+ROUND((ROUND(((AE47-(EU47))*AV47*I47),2)*BS47),2)) -> 0 | R47: =ROUND((ROUND((AE47*AV47*I47),2)*BS47),2) -> 0 | S47: =ROUND((ROUND((AF47*AV47*I47),2)*BA47),2) -> 0 | T47: =ROUND(CU47*I47,2) -> 0 | U47: =CV47*I47 -> 0 | V47: =CW47*I47 -> 0 | W47: =ROUND(CX47*I47,2) -> 0 | X47: =ROUND(CY47,2) -> 0 | Y47: =ROUND(CZ47,2) -> 0 | AA47: 56959431 | AB47: =ROUND((AC47+AD47+AF47),6) -> 1475.55 | AC47: =ROUND((ES47),6) -> 1475.55 | AD47: =ROUND((((ET47)-(EU47))+AE47),6) -> 0 | AE47: =ROUND((EU47),6) -> 0 | AF47: =ROUND((EV47),6) -> 0 | AG47: =ROUND((AP47),6) -> 0 | AH47: =(EW47) -> 0 | AI47: =(EX47) -> 0 | AJ47: =(AS47) -> 0 | AK47: 1475.55 | AL47: 1475.55 | AM47: 0 | AN47: 0 | AO47: 0 | AP47: 0 | AQ47: 0 | AR47: 0 | AS47: 0 | AT47: 0 | AU47: 0 | AV47: 1 | AW47: 1 | AZ47: 1 | BA47: 1 | BB47: 1 | BC47: 7.66 | BH47: 3 | BI47: 3 | BM47: 746 | BN47: 0 | BP47: 0 | BQ47: 130 | BR47: 0 | BS47: 1 | BT47: 1 | BU47: 1 | BV47: 1 | BW47: 1 | BX47: 1 | BZ47: 0 | CA47: 0 | CE47: 30 | CF47: 0 | CG47: 0 | CM47: 0 | CO47: 0 | CP47: =(P47+Q47+S47) -> 22605.43 | CQ47: =ROUND((ROUND((AC47*1),2)*BC47),2) -> 11302.71 | CR47: =(ROUND((ROUND(((ET47)*AV47*1),2)*BB47),2)+ROUND((ROUND(((AE47-(EU47))*AV47*1),2)*BS47),2)) -> 0 | CS47: =ROUND((ROUND((AE47*AV47*1),2)*BS47),2) -> 0 | CT47: =ROUND((ROUND((AF47*AV47*1),2)*BA47),2) -> 0 | CU47: =AG47 -> 0 | CV47: =(AH47*AV47) -> 0 | CW47: =AI47 -> 0 | CX47: =AJ47 -> 0 | CY47: =(((S47+R47)*AT47)/100) -> 0 | CZ47: =(((S47+R47)*AU47)/100) -> 0 | DN47: 0 | DO47: 0 | DP47: 1 | DQ47: 1 | DU47: 1010 | DV47: шт. | DW47: шт. | DX47: 1 | EE47: 55992259 | EF47: 130 | EG47: Сметная стоимость оборудования | EH47: 0 | EJ47: 3 | EK47: 746 | EL47: ТСН-2001.13. Сметная стоимость оборудования | EM47: ТСН-2001.13 | EQ47: 0 | ER47: 1475.55 | ES47: 1475.55 | ET47: 0 | EU47: 0 | EV47: 0 | EW47: 0 | EX47: 0 | EY47: 0 | EZ47: 5 | FC47: 1 | FD47: 18 | FF47: 13012 | FQ47: 0 | FR47: =P47 -> 22605.43 | FS47: 0 | FX47: 0 | FY47: 0 | GA47: [13 012 / 1,2 / 7,66] + 3% Трансп + 1,2% Заг.скл | GD47: 1 | GF47: 1155956824 | GG47: 2 | GH47: 3 | GI47: 5 | GJ47: 0 | GK47: 0 | GL47: =ROUND(IF(AND(BH47=3,BI47=3,FS47<>0),P47,0),2) -> 0 | GM47: =ROUND(O47+X47+Y47,2)+GX47 -> 22605.43 | GN47: =IF(OR(BI47=0,BI47=1),GM47-GX47,0) -> 0 | GO47: =IF(BI47=2,GM47-GX47,0) -> 0 | GP47: =IF(BI47=4,GM47-GX47,0) -> 0 | GR47: 1 | GS47: 1 | GT47: 0 | GV47: =ROUND((GT47),6) -> 0 | GW47: 1 | GX47: =ROUND(HC47*I47,2) -> 0 | HA47: 0 | HB47: 0 | HC47: =GV47*GW47 -> 0 | HE47: 3 | HF47: 1,2 | HS47: 0 | IK47: 0
A48: 17 | B48: 1 | C48: =ROW(SmtRes!A36) -> 36 | D48: =ROW(EtalonRes!A45) -> 45 | E48: 10 | F48: 4.11-12-1 | G48: Установка съемных и выдвижных блоков (модулей, ячеек, ТЭЗ) массой до 5 кг | H48: 1 ШТ. | I48: 1 | J48: 0 | K48: 1 | O48: =ROUND(CP48,2) -> 14 | P48: =ROUND((ROUND((AC48*AW48*I48),2)*BC48),2) -> 0 | Q48: =(ROUND((ROUND((((ET48*1.1))*AV48*I48),2)*BB48),2)+ROUND((ROUND(((AE48-((EU48*1.1)))*AV48*I48),2)*BS48),2)) -> 0.58 | R48: =ROUND((ROUND((AE48*AV48*I48),2)*BS48),2) -> 0.09 | S48: =ROUND((ROUND((AF48*AV48*I48),2)*BA48),2) -> 13.42 | T48: =ROUND(CU48*I48,2) -> 0 | U48: =CV48*I48 -> 1.186251 | V48: =CW48*I48 -> 0 | W48: =ROUND(CX48*I48,2) -> 0 | X48: =ROUND(CY48,2) -> 12.16 | Y48: =ROUND(CZ48,2) -> 6.21 | AA48: 56959434 | AB48: =ROUND((AC48+AD48+AF48),6) -> 13.365 | AC48: =ROUND((ES48),6) -> 0 | AD48: =ROUND(((((ET48*1.1))-((EU48*1.1)))+AE48),6) -> 0.55 | AE48: =ROUND(((EU48*1.1)),6) -> 0.088 | AF48: =ROUND(((EV48*1.1)),6) -> 12.815 | AG48: =ROUND((AP48),6) -> 0 | AH48: =((EW48*1.1)) -> 1.133 | AI48: =((EX48*1.1)) -> 0 | AJ48: =(AS48) -> 0 | AK48: 12.15 | AL48: 0 | AM48: 0.5 | AN48: 0.08 | AO48: 11.65 | AP48: 0 | AQ48: 1.03 | AR48: 0 | AS48: 0 | AT48: 90 | AU48: 46 | AV48: 1.047 | AW48: 1 | AZ48: 1 | BA48: 1 | BB48: 1 | BC48: 1 | BH48: 0 | BI48: 2 | BJ48: ТСН-2001.4 Доп. 68, Сб. 11, т. 12, поз. 1 | BM48: 72 | BN48: 55992028 | BO48: 4.11-12-1 | BP48: 1 | BQ48: 40 | BR48: 0 | BS48: 1 | BT48: 1 | BU48: 1 | BV48: 1 | BW48: 1 | BX48: 1 | BZ48: 90 | CA48: 46 | CE48: 30 | CF48: 0 | CG48: 0 | CM48: 0 | CN48: Поправка: Гл.12.Прил.8.п.8. 5_12.00.01.11.003 Наименование: При наличии усложненных условий производства работ (стесненность, сложность складирования и транспортной логистики, наличие в зоне производства работ действующего технологического оборудования или движения технологического транспорта и т.п.) для объектов, расположенных за пределами территории круговой магистральной системы улиц "Садовое кольцо" и за пределами Третьего транспортного кольца города Москвы пунктов "а" и "б", но в пределах Московской кольцевой автомобильной дороги | CO48: 0 | CP48: =(P48+Q48+S48) -> 14 | CQ48: =ROUND((ROUND((AC48*AW48*1),2)*BC48),2) -> 0 | CR48: =(ROUND((ROUND((((ET48*1.1))*AV48*1),2)*BB48),2)+ROUND((ROUND(((AE48-((EU48*1.1)))*AV48*1),2)*BS48),2)) -> 0.58 | CS48: =ROUND((ROUND((AE48*AV48*1),2)*BS48),2) -> 0.09 | CT48: =ROUND((ROUND((AF48*AV48*1),2)*BA48),2) -> 13.42 | CU48: =AG48 -> 0 | CV48: =(AH48*AV48) -> 1.186251 | CW48: =AI48 -> 0 | CX48: =AJ48 -> 0 | CY48: =(((S48+R48)*AT48)/100) -> 12.159 | CZ48: =(((S48+R48)*AU48)/100) -> 6.2146 | DE48: *1,1 | DF48: *1,1 | DG48: *1,1 | DI48: *1,1 | DJ48: *1,1 | DN48: 0 | DO48: 0 | DP48: 1 | DQ48: 1 | DU48: 1013 | DV48: 1 ШТ. | DW48: 1 ШТ. | DX48: 1 | EE48: 55992157 | EF48: 40 | EG48: Монтаж оборудования | EH48: 0 | EJ48: 2 | EK48: 72 | EL48: ТСН-2001.4-11. Приборы и средства автоматизации и вычислительной техники | EM48: ТСН-2001.4-11-1 | EO48: Поправка: Гл.12.Прил.8.п.8. 5_12.00.01.11.003 | EQ48: 0 | ER48: 12.15 | ES48: 0 | ET48: 0.5 | EU48: 0.08 | EV48: 11.65 | EW48: 1.03 | EX48: 0 | EY48: 0 | FQ48: 0 | FR48: 0 | FS48: 0 | FX48: 90 | FY48: 46 | GD48: 1 | GF48: 1708693888 | GG48: 2 | GH48: 1 | GI48: 2 | GJ48: 0 | GK48: 0 | GL48: =ROUND(IF(AND(BH48=3,BI48=3,FS48<>0),P48,0),2) -> 0 | GM48: =ROUND(O48+X48+Y48,2)+GX48 -> 32.37 | GN48: =IF(OR(BI48=0,BI48=1),GM48-GX48,0) -> 0 | GO48: =IF(BI48=2,GM48-GX48,0) -> 32.37 | GP48: =IF(BI48=4,GM48-GX48,0) -> 0 | GR48: 0 | GS48: 3 | GT48: 0 | GV48: =ROUND((GT48),6) -> 0 | GW48: 1 | GX48: =ROUND(HC48*I48,2) -> 0 | HA48: 0 | HB48: 0 | HC48: =GV48*GW48 -> 0 | HS48: 0 | IK48: 0
A49: 17 | B49: 1 | C49: =ROW(SmtRes!A38) -> 38 | D49: =ROW(EtalonRes!A48) -> 48 | E49: 10 | F49: 4.11-12-1 | G49: Установка съемных и выдвижных блоков (модулей, ячеек, ТЭЗ) массой до 5 кг | H49: 1 ШТ. | I49: 1 | J49: 0 | K49: 1 | O49: =ROUND(CP49,2) -> 747.4 | P49: =ROUND((ROUND((AC49*AW49*I49),2)*BC49),2) -> 0 | Q49: =(ROUND((ROUND((((ET49*1.1))*AV49*I49),2)*BB49),2)+ROUND((ROUND(((AE49-((EU49*1.1)))*AV49*I49),2)*BS49),2)) -> 9.43 | R49: =ROUND((ROUND((AE49*AV49*I49),2)*BS49),2) -> 4.95 | S49: =ROUND((ROUND((AF49*AV49*I49),2)*BA49),2) -> 737.97 | T49: =ROUND(CU49*I49,2) -> 0 | U49: =CV49*I49 -> 1.186251 | V49: =CW49*I49 -> 0 | W49: =ROUND(CX49*I49,2) -> 0 | X49: =ROUND(CY49,2) -> 668.63 | Y49: =ROUND(CZ49,2) -> 341.74 | AA49: 56959431 | AB49: =ROUND((AC49+AD49+AF49),6) -> 13.365 | AC49: =ROUND((ES49),6) -> 0 | AD49: =ROUND(((((ET49*1.1))-((EU49*1.1)))+AE49),6) -> 0.55 | AE49: =ROUND(((EU49*1.1)),6) -> 0.088 | AF49: =ROUND(((EV49*1.1)),6) -> 12.815 | AG49: =ROUND((AP49),6) -> 0 | AH49: =((EW49*1.1)) -> 1.133 | AI49: =((EX49*1.1)) -> 0 | AJ49: =(AS49) -> 0 | AK49: 12.15 | AL49: 0 | AM49: 0.5 | AN49: 0.08 | AO49: 11.65 | AP49: 0 | AQ49: 1.03 | AR49: 0 | AS49: 0 | AT49: 90 | AU49: 46 | AV49: 1.047 | AW49: 1 | AZ49: 1 | BA49: 54.99 | BB49: 16.26 | BC49: 1 | BH49: 0 | BI49: 2 | BJ49: ТСН-2001.4 Доп. 68, Сб. 11, т. 12, поз. 1 | BM49: 72 | BN49: 55992028 | BO49: 4.11-12-1 | BP49: 1 | BQ49: 40 | BR49: 0 | BS49: 54.99 | BT49: 1 | BU49: 1 | BV49: 1 | BW49: 1 | BX49: 1 | BZ49: 90 | CA49: 46 | CE49: 30 | CF49: 0 | CG49: 0 | CM49: 0 | CN49: Поправка: Гл.12.Прил.8.п.8. 5_12.00.01.11.003 Наименование: При наличии усложненных условий производства работ (стесненность, сложность складирования и транспортной логистики, наличие в зоне производства работ действующего технологического оборудования или движения технологического транспорта и т.п.) для объектов, расположенных за пределами территории круговой магистральной системы улиц "Садовое кольцо" и за пределами Третьего транспортного кольца города Москвы пунктов "а" и "б", но в пределах Московской кольцевой автомобильной дороги | CO49: 0 | CP49: =(P49+Q49+S49) -> 747.4 | CQ49: =ROUND((ROUND((AC49*AW49*1),2)*BC49),2) -> 0 | CR49: =(ROUND((ROUND((((ET49*1.1))*AV49*1),2)*BB49),2)+ROUND((ROUND(((AE49-((EU49*1.1)))*AV49*1),2)*BS49),2)) -> 9.43 | CS49: =ROUND((ROUND((AE49*AV49*1),2)*BS49),2) -> 4.95 | CT49: =ROUND((ROUND((AF49*AV49*1),2)*BA49),2) -> 737.97 | CU49: =AG49 -> 0 | CV49: =(AH49*AV49) -> 1.186251 | CW49: =AI49 -> 0 | CX49: =AJ49 -> 0 | CY49: =(((S49+R49)*AT49)/100) -> 668.628 | CZ49: =(((S49+R49)*AU49)/100) -> 341.7432 | DE49: *1,1 | DF49: *1,1 | DG49: *1,1 | DI49: *1,1 | DJ49: *1,1 | DN49: 0 | DO49: 0 | DP49: 1 | DQ49: 1 | DU49: 1013 | DV49: 1 ШТ. | DW49: 1 ШТ. | DX49: 1 | EE49: 55992157 | EF49: 40 | EG49: Монтаж оборудования | EH49: 0 | EJ49: 2 | EK49: 72 | EL49: ТСН-2001.4-11. Приборы и средства автоматизации и вычислительной техники | EM49: ТСН-2001.4-11-1 | EO49: Поправка: Гл.12.Прил.8.п.8. 5_12.00.01.11.003 | EQ49: 0 | ER49: 12.15 | ES49: 0 | ET49: 0.5 | EU49: 0.08 | EV49: 11.65 | EW49: 1.03 | EX49: 0 | EY49: 0 | FQ49: 0 | FR49: 0 | FS49: 0 | FX49: 90 | FY49: 46 | GD49: 1 | GF49: 1708693888 | GG49: 2 | GH49: 1 | GI49: 2 | GJ49: 0 | GK49: 0 | GL49: =ROUND(IF(AND(BH49=3,BI49=3,FS49<>0),P49,0),2) -> 0 | GM49: =ROUND(O49+X49+Y49,2)+GX49 -> 1757.77 | GN49: =IF(OR(BI49=0,BI49=1),GM49-GX49,0) -> 0 | GO49: =IF(BI49=2,GM49-GX49,0) -> 1757.77 | GP49: =IF(BI49=4,GM49-GX49,0) -> 0 | GR49: 0 | GS49: 3 | GT49: 0 | GV49: =ROUND((GT49),6) -> 0 | GW49: 1 | GX49: =ROUND(HC49*I49,2) -> 0 | HA49: 0 | HB49: 0 | HC49: =GV49*GW49 -> 0 | HS49: 0 | IK49: 0
A50: 17 | B50: 1 | E50: 11 | F50: КА №5 | G50: ИБП SKAT-UPS 1000 Segnetics | H50: шт. | I50: 1 | J50: 0 | K50: 1 | O50: =ROUND(CP50,2) -> 8137.48 | P50: =ROUND((ROUND((AC50*I50),2)*BC50),2) -> 8137.48 | Q50: =(ROUND((ROUND(((ET50)*AV50*I50),2)*BB50),2)+ROUND((ROUND(((AE50-(EU50))*AV50*I50),2)*BS50),2)) -> 0 | R50: =ROUND((ROUND((AE50*AV50*I50),2)*BS50),2) -> 0 | S50: =ROUND((ROUND((AF50*AV50*I50),2)*BA50),2) -> 0 | T50: =ROUND(CU50*I50,2) -> 0 | U50: =CV50*I50 -> 0 | V50: =CW50*I50 -> 0 | W50: =ROUND(CX50*I50,2) -> 0 | X50: =ROUND(CY50,2) -> 0 | Y50: =ROUND(CZ50,2) -> 0 | AA50: 56959434 | AB50: =ROUND((AC50+AD50+AF50),6) -> 8137.48 | AC50: =ROUND((ES50),6) -> 8137.48 | AD50: =ROUND((((ET50)-(EU50))+AE50),6) -> 0 | AE50: =ROUND((EU50),6) -> 0 | AF50: =ROUND((EV50),6) -> 0 | AG50: =ROUND((AP50),6) -> 0 | AH50: =(EW50) -> 0 | AI50: =(EX50) -> 0 | AJ50: =(AS50) -> 0 | AK50: 8137.48 | AL50: 8137.48 | AM50: 0 | AN50: 0 | AO50: 0 | AP50: 0 | AQ50: 0 | AR50: 0 | AS50: 0 | AT50: 0 | AU50: 0 | AV50: 1 | AW50: 1 | AZ50: 1 | BA50: 1 | BB50: 1 | BC50: 1 | BH50: 3 | BI50: 3 | BM50: 746 | BN50: 0 | BP50: 0 | BQ50: 130 | BR50: 0 | BS50: 1 | BT50: 1 | BU50: 1 | BV50: 1 | BW50: 1 | BX50: 1 | BZ50: 0 | CA50: 0 | CE50: 30 | CF50: 0 | CG50: 0 | CM50: 0 | CO50: 0 | CP50: =(P50+Q50+S50) -> 8137.48 | CQ50: =ROUND((ROUND((AC50*1),2)*BC50),2) -> 8137.48 | CR50: =(ROUND((ROUND(((ET50)*AV50*1),2)*BB50),2)+ROUND((ROUND(((AE50-(EU50))*AV50*1),2)*BS50),2)) -> 0 | CS50: =ROUND((ROUND((AE50*AV50*1),2)*BS50),2) -> 0 | CT50: =ROUND((ROUND((AF50*AV50*1),2)*BA50),2) -> 0 | CU50: =AG50 -> 0 | CV50: =(AH50*AV50) -> 0 | CW50: =AI50 -> 0 | CX50: =AJ50 -> 0 | CY50: =(((S50+R50)*AT50)/100) -> 0 | CZ50: =(((S50+R50)*AU50)/100) -> 0 | DN50: 0 | DO50: 0 | DP50: 1 | DQ50: 1 | DU50: 1010 | DV50: шт. | DW50: шт. | DX50: 1 | EE50: 55992259 | EF50: 130 | EG50: Сметная стоимость оборудования | EH50: 0 | EJ50: 3 | EK50: 746 | EL50: ТСН-2001.13. Сметная стоимость оборудования | EM50: ТСН-2001.13 | EQ50: 0 | ER50: 0 | ES50: 8137.48 | ET50: 0 | EU50: 0 | EV50: 0 | EW50: 0 | EX50: 0 | EY50: 0 | FQ50: 0 | FR50: =P50 -> 8137.48 | FS50: 0 | FX50: 0 | FY50: 0 | GA50: [71 760 / 1,2 / 7,66] + 3% Трансп + 1,2% Заг.скл | GD50: 1 | GF50: 1362054495 | GG50: 2 | GH50: 4 | GI50: -2 | GJ50: 0 | GK50: 0 | GL50: =ROUND(IF(AND(BH50=3,BI50=3,FS50<>0),P50,0),2) -> 0 | GM50: =ROUND(O50+X50+Y50,2)+GX50 -> 8137.48 | GN50: =IF(OR(BI50=0,BI50=1),GM50-GX50,0) -> 0 | GO50: =IF(BI50=2,GM50-GX50,0) -> 0 | GP50: =IF(BI50=4,GM50-GX50,0) -> 0 | GR50: 0 | GS50: 2 | GT50: 0 | GV50: =ROUND((GT50),6) -> 0 | GW50: 1 | GX50: =ROUND(HC50*I50,2) -> 0 | HA50: 0 | HB50: 0 | HC50: =GV50*GW50 -> 0 | HE50: 3 | HF50: 1,2 | HS50: 0 | IK50: 0
A51: 17 | B51: 1 | E51: 11 | F51: КА №5 | G51: ИБП SKAT-UPS 1000 Segnetics | H51: шт. | I51: 1 | J51: 0 | K51: 1 | O51: =ROUND(CP51,2) -> 62333.1 | P51: =ROUND((ROUND((AC51*I51),2)*BC51),2) -> 62333.1 | Q51: =(ROUND((ROUND(((ET51)*AV51*I51),2)*BB51),2)+ROUND((ROUND(((AE51-(EU51))*AV51*I51),2)*BS51),2)) -> 0 | R51: =ROUND((ROUND((AE51*AV51*I51),2)*BS51),2) -> 0 | S51: =ROUND((ROUND((AF51*AV51*I51),2)*BA51),2) -> 0 | T51: =ROUND(CU51*I51,2) -> 0 | U51: =CV51*I51 -> 0 | V51: =CW51*I51 -> 0 | W51: =ROUND(CX51*I51,2) -> 0 | X51: =ROUND(CY51,2) -> 0 | Y51: =ROUND(CZ51,2) -> 0 | AA51: 56959431 | AB51: =ROUND((AC51+AD51+AF51),6) -> 8137.48 | AC51: =ROUND((ES51),6) -> 8137.48 | AD51: =ROUND((((ET51)-(EU51))+AE51),6) -> 0 | AE51: =ROUND((EU51),6) -> 0 | AF51: =ROUND((EV51),6) -> 0 | AG51: =ROUND((AP51),6) -> 0 | AH51: =(EW51) -> 0 | AI51: =(EX51) -> 0 | AJ51: =(AS51) -> 0 | AK51: 8137.48 | AL51: 8137.48 | AM51: 0 | AN51: 0 | AO51: 0 | AP51: 0 | AQ51: 0 | AR51: 0 | AS51: 0 | AT51: 0 | AU51: 0 | AV51: 1 | AW51: 1 | AZ51: 1 | BA51: 1 | BB51: 1 | BC51: 7.66 | BH51: 3 | BI51: 3 | BM51: 746 | BN51: 0 | BP51: 0 | BQ51: 130 | BR51: 0 | BS51: 1 | BT51: 1 | BU51: 1 | BV51: 1 | BW51: 1 | BX51: 1 | BZ51: 0 | CA51: 0 | CE51: 30 | CF51: 0 | CG51: 0 | CM51: 0 | CO51: 0 | CP51: =(P51+Q51+S51) -> 62333.1 | CQ51: =ROUND((ROUND((AC51*1),2)*BC51),2) -> 62333.1 | CR51: =(ROUND((ROUND(((ET51)*AV51*1),2)*BB51),2)+ROUND((ROUND(((AE51-(EU51))*AV51*1),2)*BS51),2)) -> 0 | CS51: =ROUND((ROUND((AE51*AV51*1),2)*BS51),2) -> 0 | CT51: =ROUND((ROUND((AF51*AV51*1),2)*BA51),2) -> 0 | CU51: =AG51 -> 0 | CV51: =(AH51*AV51) -> 0 | CW51: =AI51 -> 0 | CX51: =AJ51 -> 0 | CY51: =(((S51+R51)*AT51)/100) -> 0 | CZ51: =(((S51+R51)*AU51)/100) -> 0 | DN51: 0 | DO51: 0 | DP51: 1 | DQ51: 1 | DU51: 1010 | DV51: шт. | DW51: шт. | DX51: 1 | EE51: 55992259 | EF51: 130 | EG51: Сметная стоимость оборудования | EH51: 0 | EJ51: 3 | EK51: 746 | EL51: ТСН-2001.13. Сметная стоимость оборудования | EM51: ТСН-2001.13 | EQ51: 0 | ER51: 8137.48 | ES51: 8137.48 | ET51: 0 | EU51: 0 | EV51: 0 | EW51: 0 | EX51: 0 | EY51: 0 | EZ51: 5 | FC51: 1 | FD51: 18 | FF51: 71760 | FQ51: 0 | FR51: =P51 -> 62333.1 | FS51: 0 | FX51: 0 | FY51: 0 | GA51: [71 760 / 1,2 / 7,66] + 3% Трансп + 1,2% Заг.скл | GD51: 1 | GF51: 1362054495 | GG51: 2 | GH51: 3 | GI51: 5 | GJ51: 0 | GK51: 0 | GL51: =ROUND(IF(AND(BH51=3,BI51=3,FS51<>0),P51,0),2) -> 0 | GM51: =ROUND(O51+X51+Y51,2)+GX51 -> 62333.1 | GN51: =IF(OR(BI51=0,BI51=1),GM51-GX51,0) -> 0 | GO51: =IF(BI51=2,GM51-GX51,0) -> 0 | GP51: =IF(BI51=4,GM51-GX51,0) -> 0 | GR51: 1 | GS51: 1 | GT51: 0 | GV51: =ROUND((GT51),6) -> 0 | GW51: 1 | GX51: =ROUND(HC51*I51,2) -> 0 | HA51: 0 | HB51: 0 | HC51: =GV51*GW51 -> 0 | HE51: 3 | HF51: 1,2 | HS51: 0 | IK51: 0
A52: 17 | B52: 1 | C52: =ROW(SmtRes!A40) -> 40 | D52: =ROW(EtalonRes!A52) -> 52 | E52: 12 | F52: 4.8-288-2 | G52: Трубы гофрированные поливинилхлоридные наружным диаметром 20 мм открыто по стенам и потолкам с установкой соединительных коробок | H52: 100 м | I52: =ROUND(2300/100,9) -> 23 | J52: 0 | K52: =ROUND(2300/100,9) -> 23 | O52: =ROUND(CP52,2) -> 13192.16 | P52: =ROUND((ROUND((AC52*AW52*I52),2)*BC52),2) -> 7228.67 | Q52: =(ROUND((ROUND((((ET52*1.1))*AV52*I52),2)*BB52),2)+ROUND((ROUND(((AE52-((EU52*1.1)))*AV52*I52),2)*BS52),2)) -> 870.7 | R52: =ROUND((ROUND((AE52*AV52*I52),2)*BS52),2) -> 151.25 | S52: =ROUND((ROUND((AF52*AV52*I52),2)*BA52),2) -> 5092.79 | T52: =ROUND(CU52*I52,2) -> 0 | U52: =CV52*I52 -> 397.3365 | V52: =CW52*I52 -> 0 | W52: =ROUND(CX52*I52,2) -> 0 | X52: =ROUND(CY52,2) -> 5086.72 | Y52: =ROUND(CZ52,2) -> 2674.46 | AA52: 56959434 | AB52: =ROUND((AC52+AD52+AF52),6) -> 561.933 | AC52: =ROUND((ES52),6) -> 314.29 | AD52: =ROUND(((((ET52*1.1))-((EU52*1.1)))+AE52),6) -> 36.157 | AE52: =ROUND(((EU52*1.1)),6) -> 6.281 | AF52: =ROUND(((EV52*1.1)),6) -> 211.486 | AG52: =ROUND((AP52),6) -> 0 | AH52: =((EW52*1.1)) -> 16.5 | AI52: =((EX52*1.1)) -> 0 | AJ52: =(AS52) -> 0 | AK52: 539.42 | AL52: 314.29 | AM52: 32.87 | AN52: 5.71 | AO52: 192.26 | AP52: 0 | AQ52: 15 | AR52: 0 | AS52: 0 | AT52: 97 | AU52: 51 | AV52: 1.047 | AW52: 1 | AZ52: 1 | BA52: 1 | BB52: 1 | BC52: 1 | BH52: 0 | BI52: 2 | BJ52: ТСН-2001.4 Доп. 54, Сб. 8, т. 288, поз. 2 | BM52: 67 | BN52: 55992028 | BO52: 4.8-288-2 | BP52: 1 | BQ52: 40 | BR52: 0 | BS52: 1 | BT52: 1 | BU52: 1 | BV52: 1 | BW52: 1 | BX52: 1 | BZ52: 97 | CA52: 51 | CE52: 30 | CF52: 0 | CG52: 0 | CM52: 0 | CN52: Поправка: Гл.12.Прил.8.п.8. 5_12.00.01.11.003 Наименование: При наличии усложненных условий производства работ (стесненность, сложность складирования и транспортной логистики, наличие в зоне производства работ действующего технологического оборудования или движения технологического транспорта и т.п.) для объектов, расположенных за пределами территории круговой магистральной системы улиц "Садовое кольцо" и за пределами Третьего транспортного кольца города Москвы пунктов "а" и "б", но в пределах Московской кольцевой автомобильной дороги | CO52: 0 | CP52: =(P52+Q52+S52) -> 13192.16 | CQ52: =ROUND((ROUND((AC52*AW52*1),2)*BC52),2) -> 314.29 | CR52: =(ROUND((ROUND((((ET52*1.1))*AV52*1),2)*BB52),2)+ROUND((ROUND(((AE52-((EU52*1.1)))*AV52*1),2)*BS52),2)) -> 37.86 | CS52: =ROUND((ROUND((AE52*AV52*1),2)*BS52),2) -> 6.58 | CT52: =ROUND((ROUND((AF52*AV52*1),2)*BA52),2) -> 221.43 | CU52: =AG52 -> 0 | CV52: =(AH52*AV52) -> 17.2755 | CW52: =AI52 -> 0 | CX52: =AJ52 -> 0 | CY52: =(((S52+R52)*AT52)/100) -> 5086.7188 | CZ52: =(((S52+R52)*AU52)/100) -> 2674.4604 | DE52: *1,1 | DF52: *1,1 | DG52: *1,1 | DI52: *1,1 | DJ52: *1,1 | DN52: 0 | DO52: 0 | DP52: 1 | DQ52: 1 | DU52: 1003 | DV52: 100 м | DW52: 100 м | DX52: 100 | EE52: 55992151 | EF52: 40 | EG52: Монтаж оборудования | EH52: 0 | EJ52: 2 | EK52: 67 | EL52: ТСН-2001.4-8. Электротехнические установки | EM52: ТСН-2001.4-8-1 | EO52: Поправка: Гл.12.Прил.8.п.8. 5_12.00.01.11.003 | EQ52: 0 | ER52: 539.42 | ES52: 314.29 | ET52: 32.87 | EU52: 5.71 | EV52: 192.26 | EW52: 15 | EX52: 0 | EY52: 0 | FQ52: 0 | FR52: 0 | FS52: 0 | FX52: 97 | FY52: 51 | GD52: 1 | GF52: 1705749599 | GG52: 2 | GH52: 1 | GI52: 2 | GJ52: 0 | GK52: 0 | GL52: =ROUND(IF(AND(BH52=3,BI52=3,FS52<>0),P52,0),2) -> 0 | GM52: =ROUND(O52+X52+Y52,2)+GX52 -> 20953.34 | GN52: =IF(OR(BI52=0,BI52=1),GM52-GX52,0) -> 0 | GO52: =IF(BI52=2,GM52-GX52,0) -> 20953.34 | GP52: =IF(BI52=4,GM52-GX52,0) -> 0 | GR52: 0 | GS52: 3 | GT52: 0 | GV52: =ROUND((GT52),6) -> 0 | GW52: 1 | GX52: =ROUND(HC52*I52,2) -> 0 | HA52: 0 | HB52: 0 | HC52: =GV52*GW52 -> 0 | HS52: 0 | IK52: 0
A53: 17 | B53: 1 | C53: =ROW(SmtRes!A42) -> 42 | D53: =ROW(EtalonRes!A56) -> 56 | E53: 12 | F53: 4.8-288-2 | G53: Трубы гофрированные поливинилхлоридные наружным диаметром 20 мм открыто по стенам и потолкам с установкой соединительных коробок | H53: 100 м | I53: =ROUND(2300/100,9) -> 23 | J53: 0 | K53: =ROUND(2300/100,9) -> 23 | O53: =ROUND(CP53,2) -> 367086.07 | P53: =ROUND((ROUND((AC53*AW53*I53),2)*BC53),2) -> 71491.55 | Q53: =(ROUND((ROUND((((ET53*1.1))*AV53*I53),2)*BB53),2)+ROUND((ROUND(((AE53-((EU53*1.1)))*AV53*I53),2)*BS53),2)) -> 15542 | R53: =ROUND((ROUND((AE53*AV53*I53),2)*BS53),2) -> 8317.24 | S53: =ROUND((ROUND((AF53*AV53*I53),2)*BA53),2) -> 280052.52 | T53: =ROUND(CU53*I53,2) -> 0 | U53: =CV53*I53 -> 397.3365 | V53: =CW53*I53 -> 0 | W53: =ROUND(CX53*I53,2) -> 0 | X53: =ROUND(CY53,2) -> 279718.67 | Y53: =ROUND(CZ53,2) -> 147068.58 | AA53: 56959431 | AB53: =ROUND((AC53+AD53+AF53),6) -> 561.933 | AC53: =ROUND((ES53),6) -> 314.29 | AD53: =ROUND(((((ET53*1.1))-((EU53*1.1)))+AE53),6) -> 36.157 | AE53: =ROUND(((EU53*1.1)),6) -> 6.281 | AF53: =ROUND(((EV53*1.1)),6) -> 211.486 | AG53: =ROUND((AP53),6) -> 0 | AH53: =((EW53*1.1)) -> 16.5 | AI53: =((EX53*1.1)) -> 0 | AJ53: =(AS53) -> 0 | AK53: 539.42 | AL53: 314.29 | AM53: 32.87 | AN53: 5.71 | AO53: 192.26 | AP53: 0 | AQ53: 15 | AR53: 0 | AS53: 0 | AT53: 97 | AU53: 51 | AV53: 1.047 | AW53: 1 | AZ53: 1 | BA53: 54.99 | BB53: 17.85 | BC53: 9.89 | BH53: 0 | BI53: 2 | BJ53: ТСН-2001.4 Доп. 54, Сб. 8, т. 288, поз. 2 | BM53: 67 | BN53: 55992028 | BO53: 4.8-288-2 | BP53: 1 | BQ53: 40 | BR53: 0 | BS53: 54.99 | BT53: 1 | BU53: 1 | BV53: 1 | BW53: 1 | BX53: 1 | BZ53: 97 | CA53: 51 | CE53: 30 | CF53: 0 | CG53: 0 | CM53: 0 | CN53: Поправка: Гл.12.Прил.8.п.8. 5_12.00.01.11.003 Наименование: При наличии усложненных условий производства работ (стесненность, сложность складирования и транспортной логистики, наличие в зоне производства работ действующего технологического оборудования или движения технологического транспорта и т.п.) для объектов, расположенных за пределами территории круговой магистральной системы улиц "Садовое кольцо" и за пределами Третьего транспортного кольца города Москвы пунктов "а" и "б", но в пределах Московской кольцевой автомобильной дороги | CO53: 0 | CP53: =(P53+Q53+S53) -> 367086.07 | CQ53: =ROUND((ROUND((AC53*AW53*1),2)*BC53),2) -> 3108.33 | CR53: =(ROUND((ROUND((((ET53*1.1))*AV53*1),2)*BB53),2)+ROUND((ROUND(((AE53-((EU53*1.1)))*AV53*1),2)*BS53),2)) -> 675.8 | CS53: =ROUND((ROUND((AE53*AV53*1),2)*BS53),2) -> 361.83 | CT53: =ROUND((ROUND((AF53*AV53*1),2)*BA53),2) -> 12176.44 | CU53: =AG53 -> 0 | CV53: =(AH53*AV53) -> 17.2755 | CW53: =AI53 -> 0 | CX53: =AJ53 -> 0 | CY53: =(((S53+R53)*AT53)/100) -> 279718.67 | CZ53: =(((S53+R53)*AU53)/100) -> 147068.58 | DE53: *1,1 | DF53: *1,1 | DG53: *1,1 | DI53: *1,1 | DJ53: *1,1 | DN53: 0 | DO53: 0 | DP53: 1 | DQ53: 1 | DU53: 1003 | DV53: 100 м | DW53: 100 м | DX53: 100 | EE53: 55992151 | EF53: 40 | EG53: Монтаж оборудования | EH53: 0 | EJ53: 2 | EK53: 67 | EL53: ТСН-2001.4-8. Электротехнические установки | EM53: ТСН-2001.4-8-1 | EO53: Поправка: Гл.12.Прил.8.п.8. 5_12.00.01.11.003 | EQ53: 0 | ER53: 539.42 | ES53: 314.29 | ET53: 32.87 | EU53: 5.71 | EV53: 192.26 | EW53: 15 | EX53: 0 | EY53: 0 | FQ53: 0 | FR53: 0 | FS53: 0 | FX53: 97 | FY53: 51 | GD53: 1 | GF53: 1705749599 | GG53: 2 | GH53: 1 | GI53: 2 | GJ53: 0 | GK53: 0 | GL53: =ROUND(IF(AND(BH53=3,BI53=3,FS53<>0),P53,0),2) -> 0 | GM53: =ROUND(O53+X53+Y53,2)+GX53 -> 793873.32 | GN53: =IF(OR(BI53=0,BI53=1),GM53-GX53,0) -> 0 | GO53: =IF(BI53=2,GM53-GX53,0) -> 793873.32 | GP53: =IF(BI53=4,GM53-GX53,0) -> 0 | GR53: 0 | GS53: 3 | GT53: 0 | GV53: =ROUND((GT53),6) -> 0 | GW53: 1 | GX53: =ROUND(HC53*I53,2) -> 0 | HA53: 0 | HB53: 0 | HC53: =GV53*GW53 -> 0 | HS53: 0 | IK53: 0
A54: 18 | B54: 1 | C54: 40 | E54: 12,1 | F54: 1.12-5-372 | G54: Трубы электротехнические, гофрированные, из ПВХ, негорючие, с зондом, наружный диаметр 20 мм | H54: м | I54: =I52*J54 -> 2346 | J54: 102 | K54: 102 | O54: =ROUND(CP54,2) -> 8093.7 | P54: =ROUND((ROUND((AC54*AW54*I54),2)*BC54),2) -> 8093.7 | Q54: =(ROUND((ROUND(((ET54)*AV54*I54),2)*BB54),2)+ROUND((ROUND(((AE54-(EU54))*AV54*I54),2)*BS54),2)) -> 0 | R54: =ROUND((ROUND((AE54*AV54*I54),2)*BS54),2) -> 0 | S54: =ROUND((ROUND((AF54*AV54*I54),2)*BA54),2) -> 0 | T54: =ROUND(CU54*I54,2) -> 0 | U54: =CV54*I54 -> 0 | V54: =CW54*I54 -> 0 | W54: =ROUND(CX54*I54,2) -> 0 | X54: =ROUND(CY54,2) -> 0 | Y54: =ROUND(CZ54,2) -> 0 | AA54: 56959434 | AB54: =ROUND((AC54+AD54+AF54),6) -> 3.45 | AC54: =ROUND((ES54),6) -> 3.45 | AD54: =ROUND((((ET54)-(EU54))+AE54),6) -> 0 | AE54: =ROUND((EU54),6) -> 0 | AF54: =ROUND((EV54),6) -> 0 | AG54: =ROUND((AP54),6) -> 0 | AH54: =(EW54) -> 0 | AI54: =(EX54) -> 0 | AJ54: =(AS54) -> 0 | AK54: 3.45 | AL54: 3.45 | AM54: 0 | AN54: 0 | AO54: 0 | AP54: 0 | AQ54: 0 | AR54: 0 | AS54: 0 | AT54: 97 | AU54: 51 | AV54: 1 | AW54: 1 | AZ54: 1 | BA54: 1 | BB54: 1 | BC54: 1 | BH54: 3 | BI54: 2 | BJ54: ТСН-2001.1 Доп. 67, Р. 12, о. 5, поз. 372 | BM54: 67 | BN54: 55992028 | BP54: 0 | BQ54: 40 | BR54: 0 | BS54: 1 | BT54: 1 | BU54: 1 | BV54: 1 | BW54: 1 | BX54: 1 | BZ54: 97 | CA54: 51 | CE54: 30 | CF54: 0 | CG54: 0 | CM54: 0 | CO54: 0 | CP54: =(P54+Q54+S54) -> 8093.7 | CQ54: =ROUND((ROUND((AC54*AW54*1),2)*BC54),2) -> 3.45 | CR54: =(ROUND((ROUND(((ET54)*AV54*1),2)*BB54),2)+ROUND((ROUND(((AE54-(EU54))*AV54*1),2)*BS54),2)) -> 0 | CS54: =ROUND((ROUND((AE54*AV54*1),2)*BS54),2) -> 0 | CT54: =ROUND((ROUND((AF54*AV54*1),2)*BA54),2) -> 0 | CU54: =AG54 -> 0 | CV54: =(AH54*AV54) -> 0 | CW54: =AI54 -> 0 | CX54: =AJ54 -> 0 | CY54: =(((S54+R54)*AT54)/100) -> 0 | CZ54: =(((S54+R54)*AU54)/100) -> 0 | DN54: 0 | DO54: 0 | DP54: 1 | DQ54: 1 | DU54: 1003 | DV54: м | DW54: м | DX54: 1 | EE54: 55992151 | EF54: 40 | EG54: Монтаж оборудования | EH54: 0 | EJ54: 2 | EK54: 67 | EL54: ТСН-2001.4-8. Электротехнические установки | EM54: ТСН-2001.4-8-1 | EQ54: 0 | ER54: 3.45 | ES54: 3.45 | ET54: 0 | EU54: 0 | EV54: 0 | EW54: 0 | EX54: 0 | FQ54: 0 | FR54: 0 | FS54: 0 | FX54: 97 | FY54: 51 | GD54: 1 | GF54: -1305428159 | GG54: 2 | GH54: 1 | GI54: -2 | GJ54: 0 | GK54: 0 | GL54: =ROUND(IF(AND(BH54=3,BI54=3,FS54<>0),P54,0),2) -> 0 | GM54: =ROUND(O54+X54+Y54,2)+GX54 -> 8093.7 | GN54: =IF(OR(BI54=0,BI54=1),GM54-GX54,0) -> 0 | GO54: =IF(BI54=2,GM54-GX54,0) -> 8093.7 | GP54: =IF(BI54=4,GM54-GX54,0) -> 0 | GR54: 0 | GS54: 3 | GT54: 0 | GV54: =ROUND((GT54),6) -> 0 | GW54: 1 | GX54: =ROUND(HC54*I54,2) -> 0 | HA54: 0 | HB54: 0 | HC54: =GV54*GW54 -> 0 | HS54: 0 | IK54: 0
A55: 18 | B55: 1 | C55: 42 | E55: 12,1 | F55: 1.12-5-372 | G55: Трубы электротехнические, гофрированные, из ПВХ, негорючие, с зондом, наружный диаметр 20 мм | H55: м | I55: =I53*J55 -> 2346 | J55: 102 | K55: 102 | O55: =ROUND(CP55,2) -> 31808.24 | P55: =ROUND((ROUND((AC55*AW55*I55),2)*BC55),2) -> 31808.24 | Q55: =(ROUND((ROUND(((ET55)*AV55*I55),2)*BB55),2)+ROUND((ROUND(((AE55-(EU55))*AV55*I55),2)*BS55),2)) -> 0 | R55: =ROUND((ROUND((AE55*AV55*I55),2)*BS55),2) -> 0 | S55: =ROUND((ROUND((AF55*AV55*I55),2)*BA55),2) -> 0 | T55: =ROUND(CU55*I55,2) -> 0 | U55: =CV55*I55 -> 0 | V55: =CW55*I55 -> 0 | W55: =ROUND(CX55*I55,2) -> 0 | X55: =ROUND(CY55,2) -> 0 | Y55: =ROUND(CZ55,2) -> 0 | AA55: 56959431 | AB55: =ROUND((AC55+AD55+AF55),6) -> 3.45 | AC55: =ROUND((ES55),6) -> 3.45 | AD55: =ROUND((((ET55)-(EU55))+AE55),6) -> 0 | AE55: =ROUND((EU55),6) -> 0 | AF55: =ROUND((EV55),6) -> 0 | AG55: =ROUND((AP55),6) -> 0 | AH55: =(EW55) -> 0 | AI55: =(EX55) -> 0 | AJ55: =(AS55) -> 0 | AK55: 3.45 | AL55: 3.45 | AM55: 0 | AN55: 0 | AO55: 0 | AP55: 0 | AQ55: 0 | AR55: 0 | AS55: 0 | AT55: 97 | AU55: 51 | AV55: 1 | AW55: 1 | AZ55: 1 | BA55: 1 | BB55: 1 | BC55: 3.93 | BH55: 3 | BI55: 2 | BJ55: ТСН-2001.1 Доп. 67, Р. 12, о. 5, поз. 372 | BM55: 67 | BN55: 55992028 | BO55: 1.12-5-372 | BP55: 1 | BQ55: 40 | BR55: 0 | BS55: 1 | BT55: 1 | BU55: 1 | BV55: 1 | BW55: 1 | BX55: 1 | BZ55: 97 | CA55: 51 | CE55: 30 | CF55: 0 | CG55: 0 | CM55: 0 | CO55: 0 | CP55: =(P55+Q55+S55) -> 31808.24 | CQ55: =ROUND((ROUND((AC55*AW55*1),2)*BC55),2) -> 13.56 | CR55: =(ROUND((ROUND(((ET55)*AV55*1),2)*BB55),2)+ROUND((ROUND(((AE55-(EU55))*AV55*1),2)*BS55),2)) -> 0 | CS55: =ROUND((ROUND((AE55*AV55*1),2)*BS55),2) -> 0 | CT55: =ROUND((ROUND((AF55*AV55*1),2)*BA55),2) -> 0 | CU55: =AG55 -> 0 | CV55: =(AH55*AV55) -> 0 | CW55: =AI55 -> 0 | CX55: =AJ55 -> 0 | CY55: =(((S55+R55)*AT55)/100) -> 0 | CZ55: =(((S55+R55)*AU55)/100) -> 0 | DN55: 0 | DO55: 0 | DP55: 1 | DQ55: 1 | DU55: 1003 | DV55: м | DW55: м | DX55: 1 | EE55: 55992151 | EF55: 40 | EG55: Монтаж оборудования | EH55: 0 | EJ55: 2 | EK55: 67 | EL55: ТСН-2001.4-8. Электротехнические установки | EM55: ТСН-2001.4-8-1 | EQ55: 0 | ER55: 3.45 | ES55: 3.45 | ET55: 0 | EU55: 0 | EV55: 0 | EW55: 0 | EX55: 0 | FQ55: 0 | FR55: 0 | FS55: 0 | FX55: 97 | FY55: 51 | GD55: 1 | GF55: -1305428159 | GG55: 2 | GH55: 1 | GI55: 2 | GJ55: 0 | GK55: 0 | GL55: =ROUND(IF(AND(BH55=3,BI55=3,FS55<>0),P55,0),2) -> 0 | GM55: =ROUND(O55+X55+Y55,2)+GX55 -> 31808.24 | GN55: =IF(OR(BI55=0,BI55=1),GM55-GX55,0) -> 0 | GO55: =IF(BI55=2,GM55-GX55,0) -> 31808.24 | GP55: =IF(BI55=4,GM55-GX55,0) -> 0 | GR55: 0 | GS55: 3 | GT55: 0 | GV55: =ROUND((GT55),6) -> 0 | GW55: 1 | GX55: =ROUND(HC55*I55,2) -> 0 | HA55: 0 | HB55: 0 | HC55: =GV55*GW55 -> 0 | HS55: 0 | IK55: 0
A56: 17 | B56: 1 | C56: =ROW(SmtRes!A44) -> 44 | D56: =ROW(EtalonRes!A64) -> 64 | E56: 13 | F56: 4.8-280-1 | G56: Прокладка пластикового кабель-канала по кирпичному основанию | H56: 100 м | I56: =ROUND(200/100,9) -> 2 | J56: 0 | K56: =ROUND(200/100,9) -> 2 | O56: =ROUND(CP56,2) -> 3027.03 | P56: =ROUND((ROUND((AC56*AW56*I56),2)*BC56),2) -> 2036.54 | Q56: =(ROUND((ROUND((((ET56*1.1))*AV56*I56),2)*BB56),2)+ROUND((ROUND(((AE56-((EU56*1.1)))*AV56*I56),2)*BS56),2)) -> 56.46 | R56: =ROUND((ROUND((AE56*AV56*I56),2)*BS56),2) -> 8.43 | S56: =ROUND((ROUND((AF56*AV56*I56),2)*BA56),2) -> 934.03 | T56: =ROUND(CU56*I56,2) -> 0 | U56: =CV56*I56 -> 77.831886 | V56: =CW56*I56 -> 0 | W56: =ROUND(CX56*I56,2) -> 0 | X56: =ROUND(CY56,2) -> 914.19 | Y56: =ROUND(CZ56,2) -> 480.65 | AA56: 56959434 | AB56: =ROUND((AC56+AD56+AF56),6) -> 1491.281 | AC56: =ROUND((ES56),6) -> 1018.27 | AD56: =ROUND(((((ET56*1.1))-((EU56*1.1)))+AE56),6) -> 26.961 | AE56: =ROUND(((EU56*1.1)),6) -> 4.026 | AF56: =ROUND(((EV56*1.1)),6) -> 446.05 | AG56: =ROUND((AP56),6) -> 0 | AH56: =((EW56*1.1)) -> 37.169 | AI56: =((EX56*1.1)) -> 0 | AJ56: =(AS56) -> 0 | AK56: 1448.28 | AL56: 1018.27 | AM56: 24.51 | AN56: 3.66 | AO56: 405.5 | AP56: 0 | AQ56: 33.79 | AR56: 0 | AS56: 0 | AT56: 97 | AU56: 51 | AV56: 1.047 | AW56: 1 | AZ56: 1 | BA56: 1 | BB56: 1 | BC56: 1 | BH56: 0 | BI56: 2 | BJ56: ТСН-2001.4. Доп. 1-42. Сб. 8, т. 280, поз. 1 | BM56: 67 | BN56: 55992028 | BO56: 4.8-280-1 | BP56: 1 | BQ56: 40 | BR56: 0 | BS56: 1 | BT56: 1 | BU56: 1 | BV56: 1 | BW56: 1 | BX56: 1 | BZ56: 97 | CA56: 51 | CE56: 30 | CF56: 0 | CG56: 0 | CM56: 0 | CN56: Поправка: Гл.12.Прил.8.п.8. 5_12.00.01.11.003 Наименование: При наличии усложненных условий производства работ (стесненность, сложность складирования и транспортной логистики, наличие в зоне производства работ действующего технологического оборудования или движения технологического транспорта и т.п.) для объектов, расположенных за пределами территории круговой магистральной системы улиц "Садовое кольцо" и за пределами Третьего транспортного кольца города Москвы пунктов "а" и "б", но в пределах Московской кольцевой автомобильной дороги | CO56: 0 | CP56: =(P56+Q56+S56) -> 3027.03 | CQ56: =ROUND((ROUND((AC56*AW56*1),2)*BC56),2) -> 1018.27 | CR56: =(ROUND((ROUND((((ET56*1.1))*AV56*1),2)*BB56),2)+ROUND((ROUND(((AE56-((EU56*1.1)))*AV56*1),2)*BS56),2)) -> 28.23 | CS56: =ROUND((ROUND((AE56*AV56*1),2)*BS56),2) -> 4.22 | CT56: =ROUND((ROUND((AF56*AV56*1),2)*BA56),2) -> 467.01 | CU56: =AG56 -> 0 | CV56: =(AH56*AV56) -> 38.915943 | CW56: =AI56 -> 0 | CX56: =AJ56 -> 0 | CY56: =(((S56+R56)*AT56)/100) -> 914.1862 | CZ56: =(((S56+R56)*AU56)/100) -> 480.6546 | DE56: *1,1 | DF56: *1,1 | DG56: *1,1 | DI56: *1,1 | DJ56: *1,1 | DN56: 0 | DO56: 0 | DP56: 1 | DQ56: 1 | DU56: 1003 | DV56: 100 м | DW56: 100 м | DX56: 100 | EE56: 55992151 | EF56: 40 | EG56: Монтаж оборудования | EH56: 0 | EJ56: 2 | EK56: 67 | EL56: ТСН-2001.4-8. Электротехнические установки | EM56: ТСН-2001.4-8-1 | EO56: Поправка: Гл.12.Прил.8.п.8. 5_12.00.01.11.003 | EQ56: 0 | ER56: 1448.28 | ES56: 1018.27 | ET56: 24.51 | EU56: 3.66 | EV56: 405.5 | EW56: 33.79 | EX56: 0 | EY56: 0 | FQ56: 0 | FR56: 0 | FS56: 0 | FX56: 97 | FY56: 51 | GD56: 1 | GF56: -283934161 | GG56: 2 | GH56: 1 | GI56: 2 | GJ56: 0 | GK56: 0 | GL56: =ROUND(IF(AND(BH56=3,BI56=3,FS56<>0),P56,0),2) -> 0 | GM56: =ROUND(O56+X56+Y56,2)+GX56 -> 4421.87 | GN56: =IF(OR(BI56=0,BI56=1),GM56-GX56,0) -> 0 | GO56: =IF(BI56=2,GM56-GX56,0) -> 4421.87 | GP56: =IF(BI56=4,GM56-GX56,0) -> 0 | GR56: 0 | GS56: 3 | GT56: 0 | GV56: =ROUND((GT56),6) -> 0 | GW56: 1 | GX56: =ROUND(HC56*I56,2) -> 0 | HA56: 0 | HB56: 0 | HC56: =GV56*GW56 -> 0 | HS56: 0 | IK56: 0
A57: 17 | B57: 1 | C57: =ROW(SmtRes!A46) -> 46 | D57: =ROW(EtalonRes!A72) -> 72 | E57: 13 | F57: 4.8-280-1 | G57: Прокладка пластикового кабель-канала по кирпичному основанию | H57: 100 м | I57: =ROUND(200/100,9) -> 2 | J57: 0 | K57: =ROUND(200/100,9) -> 2 | O57: =ROUND(CP57,2) -> 72449.4 | P57: =ROUND((ROUND((AC57*AW57*I57),2)*BC57),2) -> 20141.38 | Q57: =(ROUND((ROUND((((ET57*1.1))*AV57*I57),2)*BB57),2)+ROUND((ROUND(((AE57-((EU57*1.1)))*AV57*I57),2)*BS57),2)) -> 945.71 | R57: =ROUND((ROUND((AE57*AV57*I57),2)*BS57),2) -> 463.57 | S57: =ROUND((ROUND((AF57*AV57*I57),2)*BA57),2) -> 51362.31 | T57: =ROUND(CU57*I57,2) -> 0 | U57: =CV57*I57 -> 77.831886 | V57: =CW57*I57 -> 0 | W57: =ROUND(CX57*I57,2) -> 0 | X57: =ROUND(CY57,2) -> 50271.1 | Y57: =ROUND(CZ57,2) -> 26431.2 | AA57: 56959431 | AB57: =ROUND((AC57+AD57+AF57),6) -> 1491.281 | AC57: =ROUND((ES57),6) -> 1018.27 | AD57: =ROUND(((((ET57*1.1))-((EU57*1.1)))+AE57),6) -> 26.961 | AE57: =ROUND(((EU57*1.1)),6) -> 4.026 | AF57: =ROUND(((EV57*1.1)),6) -> 446.05 | AG57: =ROUND((AP57),6) -> 0 | AH57: =((EW57*1.1)) -> 37.169 | AI57: =((EX57*1.1)) -> 0 | AJ57: =(AS57) -> 0 | AK57: 1448.28 | AL57: 1018.27 | AM57: 24.51 | AN57: 3.66 | AO57: 405.5 | AP57: 0 | AQ57: 33.79 | AR57: 0 | AS57: 0 | AT57: 97 | AU57: 51 | AV57: 1.047 | AW57: 1 | AZ57: 1 | BA57: 54.99 | BB57: 16.75 | BC57: 9.89 | BH57: 0 | BI57: 2 | BJ57: ТСН-2001.4. Доп. 1-42. Сб. 8, т. 280, поз. 1 | BM57: 67 | BN57: 55992028 | BO57: 4.8-280-1 | BP57: 1 | BQ57: 40 | BR57: 0 | BS57: 54.99 | BT57: 1 | BU57: 1 | BV57: 1 | BW57: 1 | BX57: 1 | BZ57: 97 | CA57: 51 | CE57: 30 | CF57: 0 | CG57: 0 | CM57: 0 | CN57: Поправка: Гл.12.Прил.8.п.8. 5_12.00.01.11.003 Наименование: При наличии усложненных условий производства работ (стесненность, сложность складирования и транспортной логистики, наличие в зоне производства работ действующего технологического оборудования или движения технологического транспорта и т.п.) для объектов, расположенных за пределами территории круговой магистральной системы улиц "Садовое кольцо" и за пределами Третьего транспортного кольца города Москвы пунктов "а" и "б", но в пределах Московской кольцевой автомобильной дороги | CO57: 0 | CP57: =(P57+Q57+S57) -> 72449.4 | CQ57: =ROUND((ROUND((AC57*AW57*1),2)*BC57),2) -> 10070.69 | CR57: =(ROUND((ROUND((((ET57*1.1))*AV57*1),2)*BB57),2)+ROUND((ROUND(((AE57-((EU57*1.1)))*AV57*1),2)*BS57),2)) -> 472.85 | CS57: =ROUND((ROUND((AE57*AV57*1),2)*BS57),2) -> 232.06 | CT57: =ROUND((ROUND((AF57*AV57*1),2)*BA57),2) -> 25680.88 | CU57: =AG57 -> 0 | CV57: =(AH57*AV57) -> 38.915943 | CW57: =AI57 -> 0 | CX57: =AJ57 -> 0 | CY57: =(((S57+R57)*AT57)/100) -> 50271.104 | CZ57: =(((S57+R57)*AU57)/100) -> 26431.199 | DE57: *1,1 | DF57: *1,1 | DG57: *1,1 | DI57: *1,1 | DJ57: *1,1 | DN57: 0 | DO57: 0 | DP57: 1 | DQ57: 1 | DU57: 1003 | DV57: 100 м | DW57: 100 м | DX57: 100 | EE57: 55992151 | EF57: 40 | EG57: Монтаж оборудования | EH57: 0 | EJ57: 2 | EK57: 67 | EL57: ТСН-2001.4-8. Электротехнические установки | EM57: ТСН-2001.4-8-1 | EO57: Поправка: Гл.12.Прил.8.п.8. 5_12.00.01.11.003 | EQ57: 0 | ER57: 1448.28 | ES57: 1018.27 | ET57: 24.51 | EU57: 3.66 | EV57: 405.5 | EW57: 33.79 | EX57: 0 | EY57: 0 | FQ57: 0 | FR57: 0 | FS57: 0 | FX57: 97 | FY57: 51 | GD57: 1 | GF57: -283934161 | GG57: 2 | GH57: 1 | GI57: 2 | GJ57: 0 | GK57: 0 | GL57: =ROUND(IF(AND(BH57=3,BI57=3,FS57<>0),P57,0),2) -> 0 | GM57: =ROUND(O57+X57+Y57,2)+GX57 -> 149151.7 | GN57: =IF(OR(BI57=0,BI57=1),GM57-GX57,0) -> 0 | GO57: =IF(BI57=2,GM57-GX57,0) -> 149151.7 | GP57: =IF(BI57=4,GM57-GX57,0) -> 0 | GR57: 0 | GS57: 3 | GT57: 0 | GV57: =ROUND((GT57),6) -> 0 | GW57: 1 | GX57: =ROUND(HC57*I57,2) -> 0 | HA57: 0 | HB57: 0 | HC57: =GV57*GW57 -> 0 | HS57: 0 | IK57: 0
A58: 18 | B58: 1 | C58: 44 | E58: 13,1 | F58: 1.1-1-1962 | G58: Кабель-канал, размер 10х15 мм | H58: м | I58: =I56*J58 -> 200 | J58: 100 | K58: 100 | O58: =ROUND(CP58,2) -> 760 | P58: =ROUND((ROUND((AC58*AW58*I58),2)*BC58),2) -> 760 | Q58: =(ROUND((ROUND(((ET58)*AV58*I58),2)*BB58),2)+ROUND((ROUND(((AE58-(EU58))*AV58*I58),2)*BS58),2)) -> 0 | R58: =ROUND((ROUND((AE58*AV58*I58),2)*BS58),2) -> 0 | S58: =ROUND((ROUND((AF58*AV58*I58),2)*BA58),2) -> 0 | T58: =ROUND(CU58*I58,2) -> 0 | U58: =CV58*I58 -> 0 | V58: =CW58*I58 -> 0 | W58: =ROUND(CX58*I58,2) -> 0 | X58: =ROUND(CY58,2) -> 0 | Y58: =ROUND(CZ58,2) -> 0 | AA58: 56959434 | AB58: =ROUND((AC58+AD58+AF58),6) -> 3.8 | AC58: =ROUND((ES58),6) -> 3.8 | AD58: =ROUND((((ET58)-(EU58))+AE58),6) -> 0 | AE58: =ROUND((EU58),6) -> 0 | AF58: =ROUND((EV58),6) -> 0 | AG58: =ROUND((AP58),6) -> 0 | AH58: =(EW58) -> 0 | AI58: =(EX58) -> 0 | AJ58: =(AS58) -> 0 | AK58: 3.8 | AL58: 3.8 | AM58: 0 | AN58: 0 | AO58: 0 | AP58: 0 | AQ58: 0 | AR58: 0 | AS58: 0 | AT58: 97 | AU58: 51 | AV58: 1 | AW58: 1 | AZ58: 1 | BA58: 1 | BB58: 1 | BC58: 1 | BH58: 3 | BI58: 2 | BJ58: ТСН-2001.1 Доп. 67, Р. 1, о. 1, поз. 1962 | BM58: 67 | BN58: 55992028 | BP58: 0 | BQ58: 40 | BR58: 0 | BS58: 1 | BT58: 1 | BU58: 1 | BV58: 1 | BW58: 1 | BX58: 1 | BZ58: 97 | CA58: 51 | CE58: 30 | CF58: 0 | CG58: 0 | CM58: 0 | CO58: 0 | CP58: =(P58+Q58+S58) -> 760 | CQ58: =ROUND((ROUND((AC58*AW58*1),2)*BC58),2) -> 3.8 | CR58: =(ROUND((ROUND(((ET58)*AV58*1),2)*BB58),2)+ROUND((ROUND(((AE58-(EU58))*AV58*1),2)*BS58),2)) -> 0 | CS58: =ROUND((ROUND((AE58*AV58*1),2)*BS58),2) -> 0 | CT58: =ROUND((ROUND((AF58*AV58*1),2)*BA58),2) -> 0 | CU58: =AG58 -> 0 | CV58: =(AH58*AV58) -> 0 | CW58: =AI58 -> 0 | CX58: =AJ58 -> 0 | CY58: =(((S58+R58)*AT58)/100) -> 0 | CZ58: =(((S58+R58)*AU58)/100) -> 0 | DN58: 0 | DO58: 0 | DP58: 1 | DQ58: 1 | DU58: 1003 | DV58: м | DW58: м | DX58: 1 | EE58: 55992151 | EF58: 40 | EG58: Монтаж оборудования | EH58: 0 | EJ58: 2 | EK58: 67 | EL58: ТСН-2001.4-8. Электротехнические установки | EM58: ТСН-2001.4-8-1 | EQ58: 0 | ER58: 3.8 | ES58: 3.8 | ET58: 0 | EU58: 0 | EV58: 0 | EW58: 0 | EX58: 0 | FQ58: 0 | FR58: 0 | FS58: 0 | FX58: 97 | FY58: 51 | GD58: 1 | GF58: 1290991592 | GG58: 2 | GH58: 1 | GI58: -2 | GJ58: 0 | GK58: 0 | GL58: =ROUND(IF(AND(BH58=3,BI58=3,FS58<>0),P58,0),2) -> 0 | GM58: =ROUND(O58+X58+Y58,2)+GX58 -> 760 | GN58: =IF(OR(BI58=0,BI58=1),GM58-GX58,0) -> 0 | GO58: =IF(BI58=2,GM58-GX58,0) -> 760 | GP58: =IF(BI58=4,GM58-GX58,0) -> 0 | GR58: 0 | GS58: 3 | GT58: 0 | GV58: =ROUND((GT58),6) -> 0 | GW58: 1 | GX58: =ROUND(HC58*I58,2) -> 0 | HA58: 0 | HB58: 0 | HC58: =GV58*GW58 -> 0 | HS58: 0 | IK58: 0
A59: 18 | B59: 1 | C59: 46 | E59: 13,1 | F59: 1.1-1-1962 | G59: Кабель-канал, размер 10х15 мм | H59: м | I59: =I57*J59 -> 200 | J59: 100 | K59: 100 | O59: =ROUND(CP59,2) -> 5228.8 | P59: =ROUND((ROUND((AC59*AW59*I59),2)*BC59),2) -> 5228.8 | Q59: =(ROUND((ROUND(((ET59)*AV59*I59),2)*BB59),2)+ROUND((ROUND(((AE59-(EU59))*AV59*I59),2)*BS59),2)) -> 0 | R59: =ROUND((ROUND((AE59*AV59*I59),2)*BS59),2) -> 0 | S59: =ROUND((ROUND((AF59*AV59*I59),2)*BA59),2) -> 0 | T59: =ROUND(CU59*I59,2) -> 0 | U59: =CV59*I59 -> 0 | V59: =CW59*I59 -> 0 | W59: =ROUND(CX59*I59,2) -> 0 | X59: =ROUND(CY59,2) -> 0 | Y59: =ROUND(CZ59,2) -> 0 | AA59: 56959431 | AB59: =ROUND((AC59+AD59+AF59),6) -> 3.8 | AC59: =ROUND((ES59),6) -> 3.8 | AD59: =ROUND((((ET59)-(EU59))+AE59),6) -> 0 | AE59: =ROUND((EU59),6) -> 0 | AF59: =ROUND((EV59),6) -> 0 | AG59: =ROUND((AP59),6) -> 0 | AH59: =(EW59) -> 0 | AI59: =(EX59) -> 0 | AJ59: =(AS59) -> 0 | AK59: 3.8 | AL59: 3.8 | AM59: 0 | AN59: 0 | AO59: 0 | AP59: 0 | AQ59: 0 | AR59: 0 | AS59: 0 | AT59: 97 | AU59: 51 | AV59: 1 | AW59: 1 | AZ59: 1 | BA59: 1 | BB59: 1 | BC59: 6.88 | BH59: 3 | BI59: 2 | BJ59: ТСН-2001.1 Доп. 67, Р. 1, о. 1, поз. 1962 | BM59: 67 | BN59: 55992028 | BO59: 1.1-1-1962 | BP59: 1 | BQ59: 40 | BR59: 0 | BS59: 1 | BT59: 1 | BU59: 1 | BV59: 1 | BW59: 1 | BX59: 1 | BZ59: 97 | CA59: 51 | CE59: 30 | CF59: 0 | CG59: 0 | CM59: 0 | CO59: 0 | CP59: =(P59+Q59+S59) -> 5228.8 | CQ59: =ROUND((ROUND((AC59*AW59*1),2)*BC59),2) -> 26.14 | CR59: =(ROUND((ROUND(((ET59)*AV59*1),2)*BB59),2)+ROUND((ROUND(((AE59-(EU59))*AV59*1),2)*BS59),2)) -> 0 | CS59: =ROUND((ROUND((AE59*AV59*1),2)*BS59),2) -> 0 | CT59: =ROUND((ROUND((AF59*AV59*1),2)*BA59),2) -> 0 | CU59: =AG59 -> 0 | CV59: =(AH59*AV59) -> 0 | CW59: =AI59 -> 0 | CX59: =AJ59 -> 0 | CY59: =(((S59+R59)*AT59)/100) -> 0 | CZ59: =(((S59+R59)*AU59)/100) -> 0 | DN59: 0 | DO59: 0 | DP59: 1 | DQ59: 1 | DU59: 1003 | DV59: м | DW59: м | DX59: 1 | EE59: 55992151 | EF59: 40 | EG59: Монтаж оборудования | EH59: 0 | EJ59: 2 | EK59: 67 | EL59: ТСН-2001.4-8. Электротехнические установки | EM59: ТСН-2001.4-8-1 | EQ59: 0 | ER59: 3.8 | ES59: 3.8 | ET59: 0 | EU59: 0 | EV59: 0 | EW59: 0 | EX59: 0 | FQ59: 0 | FR59: 0 | FS59: 0 | FX59: 97 | FY59: 51 | GD59: 1 | GF59: 1290991592 | GG59: 2 | GH59: 1 | GI59: 2 | GJ59: 0 | GK59: 0 | GL59: =ROUND(IF(AND(BH59=3,BI59=3,FS59<>0),P59,0),2) -> 0 | GM59: =ROUND(O59+X59+Y59,2)+GX59 -> 5228.8 | GN59: =IF(OR(BI59=0,BI59=1),GM59-GX59,0) -> 0 | GO59: =IF(BI59=2,GM59-GX59,0) -> 5228.8 | GP59: =IF(BI59=4,GM59-GX59,0) -> 0 | GR59: 0 | GS59: 3 | GT59: 0 | GV59: =ROUND((GT59),6) -> 0 | GW59: 1 | GX59: =ROUND(HC59*I59,2) -> 0 | HA59: 0 | HB59: 0 | HC59: =GV59*GW59 -> 0 | HS59: 0 | IK59: 0
A60: 17 | B60: 1 | C60: =ROW(SmtRes!A56) -> 56 | D60: =ROW(EtalonRes!A82) -> 82 | E60: 14 | F60: 4.8-175-1 | G60: Затягивание провода в проложенные трубы и металлические рукава, первого одножильного или многожильного в общей оплетке, суммарное сечение до 2,5 мм2 | H60: 100 м | I60: =ROUND(1000/100,9) -> 10 | J60: 0 | K60: =ROUND(1000/100,9) -> 10 | O60: =ROUND(CP60,2) -> 1247.75 | P60: =ROUND((ROUND((AC60*AW60*I60),2)*BC60),2) -> 581.5 | Q60: =(ROUND((ROUND((((ET60*1.1))*AV60*I60),2)*BB60),2)+ROUND((ROUND(((AE60-((EU60*1.1)))*AV60*I60),2)*BS60),2)) -> 30.17 | R60: =ROUND((ROUND((AE60*AV60*I60),2)*BS60),2) -> 3.46 | S60: =ROUND((ROUND((AF60*AV60*I60),2)*BA60),2) -> 636.08 | T60: =ROUND(CU60*I60,2) -> 0 | U60: =CV60*I60 -> 51.71133 | V60: =CW60*I60 -> 0 | W60: =ROUND(CX60*I60,2) -> 0 | X60: =ROUND(CY60,2) -> 620.35 | Y60: =ROUND(CZ60,2) -> 326.17 | AA60: 56959434 | AB60: =ROUND((AC60+AD60+AF60),6) -> 121.785 | AC60: =ROUND((ES60),6) -> 58.15 | AD60: =ROUND(((((ET60*1.1))-((EU60*1.1)))+AE60),6) -> 2.882 | AE60: =ROUND(((EU60*1.1)),6) -> 0.33 | AF60: =ROUND(((EV60*1.1)),6) -> 60.753 | AG60: =ROUND((AP60),6) -> 0 | AH60: =((EW60*1.1)) -> 4.939 | AI60: =((EX60*1.1)) -> 0 | AJ60: =(AS60) -> 0 | AK60: 116 | AL60: 58.15 | AM60: 2.62 | AN60: 0.3 | AO60: 55.23 | AP60: 0 | AQ60: 4.49 | AR60: 0 | AS60: 0 | AT60: 97 | AU60: 51 | AV60: 1.047 | AW60: 1 | AZ60: 1 | BA60: 1 | BB60: 1 | BC60: 1 | BH60: 0 | BI60: 2 | BJ60: ТСН-2001.4 Доп. 71, Сб. 8, т. 175, поз. 1 | BM60: 67 | BN60: 55992028 | BO60: 4.8-175-1 | BP60: 1 | BQ60: 40 | BR60: 0 | BS60: 1 | BT60: 1 | BU60: 1 | BV60: 1 | BW60: 1 | BX60: 1 | BZ60: 97 | CA60: 51 | CE60: 30 | CF60: 0 | CG60: 0 | CM60: 0 | CN60: Поправка: Гл.12.Прил.8.п.8. 5_12.00.01.11.003 Наименование: При наличии усложненных условий производства работ (стесненность, сложность складирования и транспортной логистики, наличие в зоне производства работ действующего технологического оборудования или движения технологического транспорта и т.п.) для объектов, расположенных за пределами территории круговой магистральной системы улиц "Садовое кольцо" и за пределами Третьего транспортного кольца города Москвы пунктов "а" и "б", но в пределах Московской кольцевой автомобильной дороги | CO60: 0 | CP60: =(P60+Q60+S60) -> 1247.75 | CQ60: =ROUND((ROUND((AC60*AW60*1),2)*BC60),2) -> 58.15 | CR60: =(ROUND((ROUND((((ET60*1.1))*AV60*1),2)*BB60),2)+ROUND((ROUND(((AE60-((EU60*1.1)))*AV60*1),2)*BS60),2)) -> 3.02 | CS60: =ROUND((ROUND((AE60*AV60*1),2)*BS60),2) -> 0.35 | CT60: =ROUND((ROUND((AF60*AV60*1),2)*BA60),2) -> 63.61 | CU60: =AG60 -> 0 | CV60: =(AH60*AV60) -> 5.171133 | CW60: =AI60 -> 0 | CX60: =AJ60 -> 0 | CY60: =(((S60+R60)*AT60)/100) -> 620.3538 | CZ60: =(((S60+R60)*AU60)/100) -> 326.1654 | DE60: *1,1 | DF60: *1,1 | DG60: *1,1 | DI60: *1,1 | DJ60: *1,1 | DN60: 0 | DO60: 0 | DP60: 1 | DQ60: 1 | DU60: 1003 | DV60: 100 м | DW60: 100 м | DX60: 100 | EE60: 55992151 | EF60: 40 | EG60: Монтаж оборудования | EH60: 0 | EJ60: 2 | EK60: 67 | EL60: ТСН-2001.4-8. Электротехнические установки | EM60: ТСН-2001.4-8-1 | EO60: Поправка: Гл.12.Прил.8.п.8. 5_12.00.01.11.003 | EQ60: 0 | ER60: 116 | ES60: 58.15 | ET60: 2.62 | EU60: 0.3 | EV60: 55.23 | EW60: 4.49 | EX60: 0 | EY60: 0 | FQ60: 0 | FR60: 0 | FS60: 0 | FX60: 97 | FY60: 51 | GD60: 1 | GF60: 770559996 | GG60: 2 | GH60: 1 | GI60: 2 | GJ60: 0 | GK60: 0 | GL60: =ROUND(IF(AND(BH60=3,BI60=3,FS60<>0),P60,0),2) -> 0 | GM60: =ROUND(O60+X60+Y60,2)+GX60 -> 2194.27 | GN60: =IF(OR(BI60=0,BI60=1),GM60-GX60,0) -> 0 | GO60: =IF(BI60=2,GM60-GX60,0) -> 2194.27 | GP60: =IF(BI60=4,GM60-GX60,0) -> 0 | GR60: 0 | GS60: 3 | GT60: 0 | GV60: =ROUND((GT60),6) -> 0 | GW60: 1 | GX60: =ROUND(HC60*I60,2) -> 0 | HA60: 0 | HB60: 0 | HC60: =GV60*GW60 -> 0 | HS60: 0 | IK60: 0
A61: 17 | B61: 1 | C61: =ROW(SmtRes!A66) -> 66 | D61: =ROW(EtalonRes!A92) -> 92 | E61: 14 | F61: 4.8-175-1 | G61: Затягивание провода в проложенные трубы и металлические рукава, первого одножильного или многожильного в общей оплетке, суммарное сечение до 2,5 мм2 | H61: 100 м | I61: =ROUND(1000/100,9) -> 10 | J61: 0 | K61: =ROUND(1000/100,9) -> 10 | O61: =ROUND(CP61,2) -> 37569.17 | P61: =ROUND((ROUND((AC61*AW61*I61),2)*BC61),2) -> 2151.55 | Q61: =(ROUND((ROUND((((ET61*1.1))*AV61*I61),2)*BB61),2)+ROUND((ROUND(((AE61-((EU61*1.1)))*AV61*I61),2)*BS61),2)) -> 439.58 | R61: =ROUND((ROUND((AE61*AV61*I61),2)*BS61),2) -> 190.27 | S61: =ROUND((ROUND((AF61*AV61*I61),2)*BA61),2) -> 34978.04 | T61: =ROUND(CU61*I61,2) -> 0 | U61: =CV61*I61 -> 51.71133 | V61: =CW61*I61 -> 0 | W61: =ROUND(CX61*I61,2) -> 0 | X61: =ROUND(CY61,2) -> 34113.26 | Y61: =ROUND(CZ61,2) -> 17935.84 | AA61: 56959431 | AB61: =ROUND((AC61+AD61+AF61),6) -> 121.785 | AC61: =ROUND((ES61),6) -> 58.15 | AD61: =ROUND(((((ET61*1.1))-((EU61*1.1)))+AE61),6) -> 2.882 | AE61: =ROUND(((EU61*1.1)),6) -> 0.33 | AF61: =ROUND(((EV61*1.1)),6) -> 60.753 | AG61: =ROUND((AP61),6) -> 0 | AH61: =((EW61*1.1)) -> 4.939 | AI61: =((EX61*1.1)) -> 0 | AJ61: =(AS61) -> 0 | AK61: 116 | AL61: 58.15 | AM61: 2.62 | AN61: 0.3 | AO61: 55.23 | AP61: 0 | AQ61: 4.49 | AR61: 0 | AS61: 0 | AT61: 97 | AU61: 51 | AV61: 1.047 | AW61: 1 | AZ61: 1 | BA61: 54.99 | BB61: 14.57 | BC61: 3.7 | BH61: 0 | BI61: 2 | BJ61: ТСН-2001.4 Доп. 71, Сб. 8, т. 175, поз. 1 | BM61: 67 | BN61: 55992028 | BO61: 4.8-175-1 | BP61: 1 | BQ61: 40 | BR61: 0 | BS61: 54.99 | BT61: 1 | BU61: 1 | BV61: 1 | BW61: 1 | BX61: 1 | BZ61: 97 | CA61: 51 | CE61: 30 | CF61: 0 | CG61: 0 | CM61: 0 | CN61: Поправка: Гл.12.Прил.8.п.8. 5_12.00.01.11.003 Наименование: При наличии усложненных условий производства работ (стесненность, сложность складирования и транспортной логистики, наличие в зоне производства работ действующего технологического оборудования или движения технологического транспорта и т.п.) для объектов, расположенных за пределами территории круговой магистральной системы улиц "Садовое кольцо" и за пределами Третьего транспортного кольца города Москвы пунктов "а" и "б", но в пределах Московской кольцевой автомобильной дороги | CO61: 0 | CP61: =(P61+Q61+S61) -> 37569.17 | CQ61: =ROUND((ROUND((AC61*AW61*1),2)*BC61),2) -> 215.16 | CR61: =(ROUND((ROUND((((ET61*1.1))*AV61*1),2)*BB61),2)+ROUND((ROUND(((AE61-((EU61*1.1)))*AV61*1),2)*BS61),2)) -> 44 | CS61: =ROUND((ROUND((AE61*AV61*1),2)*BS61),2) -> 19.25 | CT61: =ROUND((ROUND((AF61*AV61*1),2)*BA61),2) -> 3497.91 | CU61: =AG61 -> 0 | CV61: =(AH61*AV61) -> 5.171133 | CW61: =AI61 -> 0 | CX61: =AJ61 -> 0 | CY61: =(((S61+R61)*AT61)/100) -> 34113.261 | CZ61: =(((S61+R61)*AU61)/100) -> 17935.838 | DE61: *1,1 | DF61: *1,1 | DG61: *1,1 | DI61: *1,1 | DJ61: *1,1 | DN61: 0 | DO61: 0 | DP61: 1 | DQ61: 1 | DU61: 1003 | DV61: 100 м | DW61: 100 м | DX61: 100 | EE61: 55992151 | EF61: 40 | EG61: Монтаж оборудования | EH61: 0 | EJ61: 2 | EK61: 67 | EL61: ТСН-2001.4-8. Электротехнические установки | EM61: ТСН-2001.4-8-1 | EO61: Поправка: Гл.12.Прил.8.п.8. 5_12.00.01.11.003 | EQ61: 0 | ER61: 116 | ES61: 58.15 | ET61: 2.62 | EU61: 0.3 | EV61: 55.23 | EW61: 4.49 | EX61: 0 | EY61: 0 | FQ61: 0 | FR61: 0 | FS61: 0 | FX61: 97 | FY61: 51 | GD61: 1 | GF61: 770559996 | GG61: 2 | GH61: 1 | GI61: 2 | GJ61: 0 | GK61: 0 | GL61: =ROUND(IF(AND(BH61=3,BI61=3,FS61<>0),P61,0),2) -> 0 | GM61: =ROUND(O61+X61+Y61,2)+GX61 -> 89618.27 | GN61: =IF(OR(BI61=0,BI61=1),GM61-GX61,0) -> 0 | GO61: =IF(BI61=2,GM61-GX61,0) -> 89618.27 | GP61: =IF(BI61=4,GM61-GX61,0) -> 0 | GR61: 0 | GS61: 3 | GT61: 0 | GV61: =ROUND((GT61),6) -> 0 | GW61: 1 | GX61: =ROUND(HC61*I61,2) -> 0 | HA61: 0 | HB61: 0 | HC61: =GV61*GW61 -> 0 | HS61: 0 | IK61: 0
A62: 18 | B62: 1 | C62: 56 | E62: 14,1 | F62: КА №8 | G62: Кабель КПСЭнг(A)-LSLTx 1х2х0,75 | H62: м.п. | I62: =I60*J62 -> 1020 | J62: 102 | K62: 102 | O62: =ROUND(CP62,2) -> 5181.6 | P62: =ROUND((ROUND((AC62*AW62*I62),2)*BC62),2) -> 5181.6 | Q62: =(ROUND((ROUND(((ET62)*AV62*I62),2)*BB62),2)+ROUND((ROUND(((AE62-(EU62))*AV62*I62),2)*BS62),2)) -> 0 | R62: =ROUND((ROUND((AE62*AV62*I62),2)*BS62),2) -> 0 | S62: =ROUND((ROUND((AF62*AV62*I62),2)*BA62),2) -> 0 | T62: =ROUND(CU62*I62,2) -> 0 | U62: =CV62*I62 -> 0 | V62: =CW62*I62 -> 0 | W62: =ROUND(CX62*I62,2) -> 0 | X62: =ROUND(CY62,2) -> 0 | Y62: =ROUND(CZ62,2) -> 0 | AA62: 56959434 | AB62: =ROUND((AC62+AD62+AF62),6) -> 5.08 | AC62: =ROUND((ES62),6) -> 5.08 | AD62: =ROUND((((ET62)-(EU62))+AE62),6) -> 0 | AE62: =ROUND((EU62),6) -> 0 | AF62: =ROUND((EV62),6) -> 0 | AG62: =ROUND((AP62),6) -> 0 | AH62: =(EW62) -> 0 | AI62: =(EX62) -> 0 | AJ62: =(AS62) -> 0 | AK62: 5.08 | AL62: 5.08 | AM62: 0 | AN62: 0 | AO62: 0 | AP62: 0 | AQ62: 0 | AR62: 0 | AS62: 0 | AT62: 97 | AU62: 51 | AV62: 1 | AW62: 1 | AZ62: 1 | BA62: 1 | BB62: 1 | BC62: 1 | BH62: 3 | BI62: 2 | BM62: 67 | BN62: 0 | BP62: 0 | BQ62: 40 | BR62: 0 | BS62: 1 | BT62: 1 | BU62: 1 | BV62: 1 | BW62: 1 | BX62: 1 | BZ62: 97 | CA62: 51 | CE62: 30 | CF62: 0 | CG62: 0 | CM62: 0 | CO62: 0 | CP62: =(P62+Q62+S62) -> 5181.6 | CQ62: =ROUND((ROUND((AC62*AW62*1),2)*BC62),2) -> 5.08 | CR62: =(ROUND((ROUND(((ET62)*AV62*1),2)*BB62),2)+ROUND((ROUND(((AE62-(EU62))*AV62*1),2)*BS62),2)) -> 0 | CS62: =ROUND((ROUND((AE62*AV62*1),2)*BS62),2) -> 0 | CT62: =ROUND((ROUND((AF62*AV62*1),2)*BA62),2) -> 0 | CU62: =AG62 -> 0 | CV62: =(AH62*AV62) -> 0 | CW62: =AI62 -> 0 | CX62: =AJ62 -> 0 | CY62: =(((S62+R62)*AT62)/100) -> 0 | CZ62: =(((S62+R62)*AU62)/100) -> 0 | DN62: 0 | DO62: 0 | DP62: 1 | DQ62: 1 | DU62: 1013 | DV62: м.п. | DW62: м.п. | DX62: 1 | EE62: 55992151 | EF62: 40 | EG62: Монтаж оборудования | EH62: 0 | EJ62: 2 | EK62: 67 | EL62: ТСН-2001.4-8. Электротехнические установки | EM62: ТСН-2001.4-8-1 | EQ62: 0 | ER62: 0 | ES62: 5.08 | ET62: 0 | EU62: 0 | EV62: 0 | EW62: 0 | EX62: 0 | FQ62: 0 | FR62: 0 | FS62: 0 | FX62: 97 | FY62: 51 | GA62: [59 / 1,2 / 9,88] + 2% Заг.скл | GD62: 1 | GF62: 1285757954 | GG62: 2 | GH62: 4 | GI62: -2 | GJ62: 0 | GK62: 0 | GL62: =ROUND(IF(AND(BH62=3,BI62=3,FS62<>0),P62,0),2) -> 0 | GM62: =ROUND(O62+X62+Y62,2)+GX62 -> 5181.6 | GN62: =IF(OR(BI62=0,BI62=1),GM62-GX62,0) -> 0 | GO62: =IF(BI62=2,GM62-GX62,0) -> 5181.6 | GP62: =IF(BI62=4,GM62-GX62,0) -> 0 | GR62: 0 | GS62: 2 | GT62: 0 | GV62: =ROUND((GT62),6) -> 0 | GW62: 1 | GX62: =ROUND(HC62*I62,2) -> 0 | HA62: 0 | HB62: 0 | HC62: =GV62*GW62 -> 0 | HE62: 0 | HF62: 2 | HS62: 0 | IK62: 0
A63: 18 | B63: 1 | C63: 66 | E63: 14,1 | F63: КА №8 | G63: Кабель КПСЭнг(A)-LSLTx 1х2х0,75 | H63: м.п. | I63: =I61*J63 -> 1020 | J63: 102 | K63: 102 | O63: =ROUND(CP63,2) -> 51194.21 | P63: =ROUND((ROUND((AC63*AW63*I63),2)*BC63),2) -> 51194.21 | Q63: =(ROUND((ROUND(((ET63)*AV63*I63),2)*BB63),2)+ROUND((ROUND(((AE63-(EU63))*AV63*I63),2)*BS63),2)) -> 0 | R63: =ROUND((ROUND((AE63*AV63*I63),2)*BS63),2) -> 0 | S63: =ROUND((ROUND((AF63*AV63*I63),2)*BA63),2) -> 0 | T63: =ROUND(CU63*I63,2) -> 0 | U63: =CV63*I63 -> 0 | V63: =CW63*I63 -> 0 | W63: =ROUND(CX63*I63,2) -> 0 | X63: =ROUND(CY63,2) -> 0 | Y63: =ROUND(CZ63,2) -> 0 | AA63: 56959431 | AB63: =ROUND((AC63+AD63+AF63),6) -> 5.08 | AC63: =ROUND((ES63),6) -> 5.08 | AD63: =ROUND((((ET63)-(EU63))+AE63),6) -> 0 | AE63: =ROUND((EU63),6) -> 0 | AF63: =ROUND((EV63),6) -> 0 | AG63: =ROUND((AP63),6) -> 0 | AH63: =(EW63) -> 0 | AI63: =(EX63) -> 0 | AJ63: =(AS63) -> 0 | AK63: 5.08 | AL63: 5.08 | AM63: 0 | AN63: 0 | AO63: 0 | AP63: 0 | AQ63: 0 | AR63: 0 | AS63: 0 | AT63: 97 | AU63: 51 | AV63: 1 | AW63: 1 | AZ63: 1 | BA63: 1 | BB63: 1 | BC63: 9.88 | BH63: 3 | BI63: 2 | BM63: 67 | BN63: 0 | BP63: 0 | BQ63: 40 | BR63: 0 | BS63: 1 | BT63: 1 | BU63: 1 | BV63: 1 | BW63: 1 | BX63: 1 | BZ63: 97 | CA63: 51 | CE63: 30 | CF63: 0 | CG63: 0 | CM63: 0 | CO63: 0 | CP63: =(P63+Q63+S63) -> 51194.21 | CQ63: =ROUND((ROUND((AC63*AW63*1),2)*BC63),2) -> 50.19 | CR63: =(ROUND((ROUND(((ET63)*AV63*1),2)*BB63),2)+ROUND((ROUND(((AE63-(EU63))*AV63*1),2)*BS63),2)) -> 0 | CS63: =ROUND((ROUND((AE63*AV63*1),2)*BS63),2) -> 0 | CT63: =ROUND((ROUND((AF63*AV63*1),2)*BA63),2) -> 0 | CU63: =AG63 -> 0 | CV63: =(AH63*AV63) -> 0 | CW63: =AI63 -> 0 | CX63: =AJ63 -> 0 | CY63: =(((S63+R63)*AT63)/100) -> 0 | CZ63: =(((S63+R63)*AU63)/100) -> 0 | DN63: 0 | DO63: 0 | DP63: 1 | DQ63: 1 | DU63: 1013 | DV63: м.п. | DW63: м.п. | DX63: 1 | EE63: 55992151 | EF63: 40 | EG63: Монтаж оборудования | EH63: 0 | EJ63: 2 | EK63: 67 | EL63: ТСН-2001.4-8. Электротехнические установки | EM63: ТСН-2001.4-8-1 | EQ63: 0 | ER63: 5.08 | ES63: 5.08 | ET63: 0 | EU63: 0 | EV63: 0 | EW63: 0 | EX63: 0 | EZ63: 5 | FC63: 1 | FD63: 18 | FF63: 59 | FQ63: 0 | FR63: 0 | FS63: 0 | FX63: 97 | FY63: 51 | GA63: [59 / 1,2 / 9,88] + 2% Заг.скл | GD63: 1 | GF63: 1285757954 | GG63: 2 | GH63: 3 | GI63: 5 | GJ63: 0 | GK63: 0 | GL63: =ROUND(IF(AND(BH63=3,BI63=3,FS63<>0),P63,0),2) -> 0 | GM63: =ROUND(O63+X63+Y63,2)+GX63 -> 51194.21 | GN63: =IF(OR(BI63=0,BI63=1),GM63-GX63,0) -> 0 | GO63: =IF(BI63=2,GM63-GX63,0) -> 51194.21 | GP63: =IF(BI63=4,GM63-GX63,0) -> 0 | GR63: 1 | GS63: 1 | GT63: 0 | GV63: =ROUND((GT63),6) -> 0 | GW63: 1 | GX63: =ROUND(HC63*I63,2) -> 0 | HA63: 0 | HB63: 0 | HC63: =GV63*GW63 -> 0 | HE63: 0 | HF63: 2 | HS63: 0 | IK63: 0
A64: 17 | B64: 1 | C64: =ROW(SmtRes!A77) -> 77 | D64: =ROW(EtalonRes!A102) -> 102 | E64: 15 | F64: 4.8-175-1 | G64: Затягивание провода в проложенные трубы и металлические рукава, первого одножильного или многожильного в общей оплетке, суммарное сечение до 2,5 мм2 | H64: 100 м | I64: =ROUND(1300/100,9) -> 13 | J64: 0 | K64: =ROUND(1300/100,9) -> 13 | O64: =ROUND(CP64,2) -> 1622.09 | P64: =ROUND((ROUND((AC64*AW64*I64),2)*BC64),2) -> 755.95 | Q64: =(ROUND((ROUND((((ET64*1.1))*AV64*I64),2)*BB64),2)+ROUND((ROUND(((AE64-((EU64*1.1)))*AV64*I64),2)*BS64),2)) -> 39.23 | R64: =ROUND((ROUND((AE64*AV64*I64),2)*BS64),2) -> 4.49 | S64: =ROUND((ROUND((AF64*AV64*I64),2)*BA64),2) -> 826.91 | T64: =ROUND(CU64*I64,2) -> 0 | U64: =CV64*I64 -> 67.224729 | V64: =CW64*I64 -> 0 | W64: =ROUND(CX64*I64,2) -> 0 | X64: =ROUND(CY64,2) -> 806.46 | Y64: =ROUND(CZ64,2) -> 424.01 | AA64: 56959434 | AB64: =ROUND((AC64+AD64+AF64),6) -> 121.785 | AC64: =ROUND((ES64),6) -> 58.15 | AD64: =ROUND(((((ET64*1.1))-((EU64*1.1)))+AE64),6) -> 2.882 | AE64: =ROUND(((EU64*1.1)),6) -> 0.33 | AF64: =ROUND(((EV64*1.1)),6) -> 60.753 | AG64: =ROUND((AP64),6) -> 0 | AH64: =((EW64*1.1)) -> 4.939 | AI64: =((EX64*1.1)) -> 0 | AJ64: =(AS64) -> 0 | AK64: 116 | AL64: 58.15 | AM64: 2.62 | AN64: 0.3 | AO64: 55.23 | AP64: 0 | AQ64: 4.49 | AR64: 0 | AS64: 0 | AT64: 97 | AU64: 51 | AV64: 1.047 | AW64: 1 | AZ64: 1 | BA64: 1 | BB64: 1 | BC64: 1 | BH64: 0 | BI64: 2 | BJ64: ТСН-2001.4 Доп. 71, Сб. 8, т. 175, поз. 1 | BM64: 67 | BN64: 55992028 | BO64: 4.8-175-1 | BP64: 1 | BQ64: 40 | BR64: 0 | BS64: 1 | BT64: 1 | BU64: 1 | BV64: 1 | BW64: 1 | BX64: 1 | BZ64: 97 | CA64: 51 | CE64: 30 | CF64: 0 | CG64: 0 | CM64: 0 | CN64: Поправка: Гл.12.Прил.8.п.8. 5_12.00.01.11.003 Наименование: При наличии усложненных условий производства работ (стесненность, сложность складирования и транспортной логистики, наличие в зоне производства работ действующего технологического оборудования или движения технологического транспорта и т.п.) для объектов, расположенных за пределами территории круговой магистральной системы улиц "Садовое кольцо" и за пределами Третьего транспортного кольца города Москвы пунктов "а" и "б", но в пределах Московской кольцевой автомобильной дороги | CO64: 0 | CP64: =(P64+Q64+S64) -> 1622.09 | CQ64: =ROUND((ROUND((AC64*AW64*1),2)*BC64),2) -> 58.15 | CR64: =(ROUND((ROUND((((ET64*1.1))*AV64*1),2)*BB64),2)+ROUND((ROUND(((AE64-((EU64*1.1)))*AV64*1),2)*BS64),2)) -> 3.02 | CS64: =ROUND((ROUND((AE64*AV64*1),2)*BS64),2) -> 0.35 | CT64: =ROUND((ROUND((AF64*AV64*1),2)*BA64),2) -> 63.61 | CU64: =AG64 -> 0 | CV64: =(AH64*AV64) -> 5.171133 | CW64: =AI64 -> 0 | CX64: =AJ64 -> 0 | CY64: =(((S64+R64)*AT64)/100) -> 806.458 | CZ64: =(((S64+R64)*AU64)/100) -> 424.014 | DE64: *1,1 | DF64: *1,1 | DG64: *1,1 | DI64: *1,1 | DJ64: *1,1 | DN64: 0 | DO64: 0 | DP64: 1 | DQ64: 1 | DU64: 1003 | DV64: 100 м | DW64: 100 м | DX64: 100 | EE64: 55992151 | EF64: 40 | EG64: Монтаж оборудования | EH64: 0 | EJ64: 2 | EK64: 67 | EL64: ТСН-2001.4-8. Электротехнические установки | EM64: ТСН-2001.4-8-1 | EO64: Поправка: Гл.12.Прил.8.п.8. 5_12.00.01.11.003 | EQ64: 0 | ER64: 116 | ES64: 58.15 | ET64: 2.62 | EU64: 0.3 | EV64: 55.23 | EW64: 4.49 | EX64: 0 | EY64: 0 | FQ64: 0 | FR64: 0 | FS64: 0 | FX64: 97 | FY64: 51 | GD64: 1 | GF64: 770559996 | GG64: 2 | GH64: 1 | GI64: 2 | GJ64: 0 | GK64: 0 | GL64: =ROUND(IF(AND(BH64=3,BI64=3,FS64<>0),P64,0),2) -> 0 | GM64: =ROUND(O64+X64+Y64,2)+GX64 -> 2852.56 | GN64: =IF(OR(BI64=0,BI64=1),GM64-GX64,0) -> 0 | GO64: =IF(BI64=2,GM64-GX64,0) -> 2852.56 | GP64: =IF(BI64=4,GM64-GX64,0) -> 0 | GR64: 0 | GS64: 3 | GT64: 0 | GV64: =ROUND((GT64),6) -> 0 | GW64: 1 | GX64: =ROUND(HC64*I64,2) -> 0 | HA64: 0 | HB64: 0 | HC64: =GV64*GW64 -> 0 | HS64: 0 | IK64: 0
A65: 17 | B65: 1 | C65: =ROW(SmtRes!A88) -> 88 | D65: =ROW(EtalonRes!A112) -> 112 | E65: 15 | F65: 4.8-175-1 | G65: Затягивание провода в проложенные трубы и металлические рукава, первого одножильного или многожильного в общей оплетке, суммарное сечение до 2,5 мм2 | H65: 100 м | I65: =ROUND(1300/100,9) -> 13 | J65: 0 | K65: =ROUND(1300/100,9) -> 13 | O65: =ROUND(CP65,2) -> 48840.38 | P65: =ROUND((ROUND((AC65*AW65*I65),2)*BC65),2) -> 2797.02 | Q65: =(ROUND((ROUND((((ET65*1.1))*AV65*I65),2)*BB65),2)+ROUND((ROUND(((AE65-((EU65*1.1)))*AV65*I65),2)*BS65),2)) -> 571.58 | R65: =ROUND((ROUND((AE65*AV65*I65),2)*BS65),2) -> 246.91 | S65: =ROUND((ROUND((AF65*AV65*I65),2)*BA65),2) -> 45471.78 | T65: =ROUND(CU65*I65,2) -> 0 | U65: =CV65*I65 -> 67.224729 | V65: =CW65*I65 -> 0 | W65: =ROUND(CX65*I65,2) -> 0 | X65: =ROUND(CY65,2) -> 44347.13 | Y65: =ROUND(CZ65,2) -> 23316.53 | AA65: 56959431 | AB65: =ROUND((AC65+AD65+AF65),6) -> 121.785 | AC65: =ROUND((ES65),6) -> 58.15 | AD65: =ROUND(((((ET65*1.1))-((EU65*1.1)))+AE65),6) -> 2.882 | AE65: =ROUND(((EU65*1.1)),6) -> 0.33 | AF65: =ROUND(((EV65*1.1)),6) -> 60.753 | AG65: =ROUND((AP65),6) -> 0 | AH65: =((EW65*1.1)) -> 4.939 | AI65: =((EX65*1.1)) -> 0 | AJ65: =(AS65) -> 0 | AK65: 116 | AL65: 58.15 | AM65: 2.62 | AN65: 0.3 | AO65: 55.23 | AP65: 0 | AQ65: 4.49 | AR65: 0 | AS65: 0 | AT65: 97 | AU65: 51 | AV65: 1.047 | AW65: 1 | AZ65: 1 | BA65: 54.99 | BB65: 14.57 | BC65: 3.7 | BH65: 0 | BI65: 2 | BJ65: ТСН-2001.4 Доп. 71, Сб. 8, т. 175, поз. 1 | BM65: 67 | BN65: 55992028 | BO65: 4.8-175-1 | BP65: 1 | BQ65: 40 | BR65: 0 | BS65: 54.99 | BT65: 1 | BU65: 1 | BV65: 1 | BW65: 1 | BX65: 1 | BZ65: 97 | CA65: 51 | CE65: 30 | CF65: 0 | CG65: 0 | CM65: 0 | CN65: Поправка: Гл.12.Прил.8.п.8. 5_12.00.01.11.003 Наименование: При наличии усложненных условий производства работ (стесненность, сложность складирования и транспортной логистики, наличие в зоне производства работ действующего технологического оборудования или движения технологического транспорта и т.п.) для объектов, расположенных за пределами территории круговой магистральной системы улиц "Садовое кольцо" и за пределами Третьего транспортного кольца города Москвы пунктов "а" и "б", но в пределах Московской кольцевой автомобильной дороги | CO65: 0 | CP65: =(P65+Q65+S65) -> 48840.38 | CQ65: =ROUND((ROUND((AC65*AW65*1),2)*BC65),2) -> 215.16 | CR65: =(ROUND((ROUND((((ET65*1.1))*AV65*1),2)*BB65),2)+ROUND((ROUND(((AE65-((EU65*1.1)))*AV65*1),2)*BS65),2)) -> 44 | CS65: =ROUND((ROUND((AE65*AV65*1),2)*BS65),2) -> 19.25 | CT65: =ROUND((ROUND((AF65*AV65*1),2)*BA65),2) -> 3497.91 | CU65: =AG65 -> 0 | CV65: =(AH65*AV65) -> 5.171133 | CW65: =AI65 -> 0 | CX65: =AJ65 -> 0 | CY65: =(((S65+R65)*AT65)/100) -> 44347.129 | CZ65: =(((S65+R65)*AU65)/100) -> 23316.532 | DE65: *1,1 | DF65: *1,1 | DG65: *1,1 | DI65: *1,1 | DJ65: *1,1 | DN65: 0 | DO65: 0 | DP65: 1 | DQ65: 1 | DU65: 1003 | DV65: 100 м | DW65: 100 м | DX65: 100 | EE65: 55992151 | EF65: 40 | EG65: Монтаж оборудования | EH65: 0 | EJ65: 2 | EK65: 67 | EL65: ТСН-2001.4-8. Электротехнические установки | EM65: ТСН-2001.4-8-1 | EO65: Поправка: Гл.12.Прил.8.п.8. 5_12.00.01.11.003 | EQ65: 0 | ER65: 116 | ES65: 58.15 | ET65: 2.62 | EU65: 0.3 | EV65: 55.23 | EW65: 4.49 | EX65: 0 | EY65: 0 | FQ65: 0 | FR65: 0 | FS65: 0 | FX65: 97 | FY65: 51 | GD65: 1 | GF65: 770559996 | GG65: 2 | GH65: 1 | GI65: 2 | GJ65: 0 | GK65: 0 | GL65: =ROUND(IF(AND(BH65=3,BI65=3,FS65<>0),P65,0),2) -> 0 | GM65: =ROUND(O65+X65+Y65,2)+GX65 -> 116504.04 | GN65: =IF(OR(BI65=0,BI65=1),GM65-GX65,0) -> 0 | GO65: =IF(BI65=2,GM65-GX65,0) -> 116504.04 | GP65: =IF(BI65=4,GM65-GX65,0) -> 0 | GR65: 0 | GS65: 3 | GT65: 0 | GV65: =ROUND((GT65),6) -> 0 | GW65: 1 | GX65: =ROUND(HC65*I65,2) -> 0 | HA65: 0 | HB65: 0 | HC65: =GV65*GW65 -> 0 | HS65: 0 | IK65: 0
A66: 18 | B66: 1 | C66: 76 | E66: 15,1 | F66: 1.23-9-92 | G66: Кабель симметричный, парной скрутки, с изоляцией из сплошного полиэтилена, с общим экраном, в оболочке из ПВХ пластиката пониженной пожароопасности, с низким дымо- и газовыделением, марка КИПЭВнг(А)-LS, число пар и сечение жилы 2х2х0,6 мм2 | H66: км | I66: =I64*J66 -> 1.326 | J66: 0.102 | K66: 0.102 | O66: =ROUND(CP66,2) -> 48283.64 | P66: =ROUND((ROUND((AC66*AW66*I66),2)*BC66),2) -> 48283.64 | Q66: =(ROUND((ROUND(((ET66)*AV66*I66),2)*BB66),2)+ROUND((ROUND(((AE66-(EU66))*AV66*I66),2)*BS66),2)) -> 0 | R66: =ROUND((ROUND((AE66*AV66*I66),2)*BS66),2) -> 0 | S66: =ROUND((ROUND((AF66*AV66*I66),2)*BA66),2) -> 0 | T66: =ROUND(CU66*I66,2) -> 0 | U66: =CV66*I66 -> 0 | V66: =CW66*I66 -> 0 | W66: =ROUND(CX66*I66,2) -> 0 | X66: =ROUND(CY66,2) -> 0 | Y66: =ROUND(CZ66,2) -> 0 | AA66: 56959434 | AB66: =ROUND((AC66+AD66+AF66),6) -> 36413 | AC66: =ROUND((ES66),6) -> 36413 | AD66: =ROUND((((ET66)-(EU66))+AE66),6) -> 0 | AE66: =ROUND((EU66),6) -> 0 | AF66: =ROUND((EV66),6) -> 0 | AG66: =ROUND((AP66),6) -> 0 | AH66: =(EW66) -> 0 | AI66: =(EX66) -> 0 | AJ66: =(AS66) -> 0 | AK66: 36413 | AL66: 36413 | AM66: 0 | AN66: 0 | AO66: 0 | AP66: 0 | AQ66: 0 | AR66: 0 | AS66: 0 | AT66: 97 | AU66: 51 | AV66: 1 | AW66: 1 | AZ66: 1 | BA66: 1 | BB66: 1 | BC66: 1 | BH66: 3 | BI66: 2 | BJ66: ТСН-2001.1 Доп. 79, Р. 23, о. 9, поз. 92 | BM66: 67 | BN66: 55992028 | BP66: 0 | BQ66: 40 | BR66: 0 | BS66: 1 | BT66: 1 | BU66: 1 | BV66: 1 | BW66: 1 | BX66: 1 | BZ66: 97 | CA66: 51 | CE66: 30 | CF66: 0 | CG66: 0 | CM66: 0 | CO66: 0 | CP66: =(P66+Q66+S66) -> 48283.64 | CQ66: =ROUND((ROUND((AC66*AW66*1),2)*BC66),2) -> 36413 | CR66: =(ROUND((ROUND(((ET66)*AV66*1),2)*BB66),2)+ROUND((ROUND(((AE66-(EU66))*AV66*1),2)*BS66),2)) -> 0 | CS66: =ROUND((ROUND((AE66*AV66*1),2)*BS66),2) -> 0 | CT66: =ROUND((ROUND((AF66*AV66*1),2)*BA66),2) -> 0 | CU66: =AG66 -> 0 | CV66: =(AH66*AV66) -> 0 | CW66: =AI66 -> 0 | CX66: =AJ66 -> 0 | CY66: =(((S66+R66)*AT66)/100) -> 0 | CZ66: =(((S66+R66)*AU66)/100) -> 0 | DN66: 0 | DO66: 0 | DP66: 1 | DQ66: 1 | DU66: 1003 | DV66: км | DW66: км | DX66: 1000 | EE66: 55992151 | EF66: 40 | EG66: Монтаж оборудования | EH66: 0 | EJ66: 2 | EK66: 67 | EL66: ТСН-2001.4-8. Электротехнические установки | EM66: ТСН-2001.4-8-1 | EQ66: 0 | ER66: 36413 | ES66: 36413 | ET66: 0 | EU66: 0 | EV66: 0 | EW66: 0 | EX66: 0 | FQ66: 0 | FR66: 0 | FS66: 0 | FX66: 97 | FY66: 51 | GD66: 1 | GF66: -205854567 | GG66: 2 | GH66: 1 | GI66: -2 | GJ66: 0 | GK66: 0 | GL66: =ROUND(IF(AND(BH66=3,BI66=3,FS66<>0),P66,0),2) -> 0 | GM66: =ROUND(O66+X66+Y66,2)+GX66 -> 48283.64 | GN66: =IF(OR(BI66=0,BI66=1),GM66-GX66,0) -> 0 | GO66: =IF(BI66=2,GM66-GX66,0) -> 48283.64 | GP66: =IF(BI66=4,GM66-GX66,0) -> 0 | GR66: 0 | GS66: 3 | GT66: 0 | GV66: =ROUND((GT66),6) -> 0 | GW66: 1 | GX66: =ROUND(HC66*I66,2) -> 0 | HA66: 0 | HB66: 0 | HC66: =GV66*GW66 -> 0 | HS66: 0 | IK66: 0
A67: 18 | B67: 1 | C67: 87 | E67: 15,1 | F67: 1.23-9-92 | G67: Кабель симметричный, парной скрутки, с изоляцией из сплошного полиэтилена, с общим экраном, в оболочке из ПВХ пластиката пониженной пожароопасности, с низким дымо- и газовыделением, марка КИПЭВнг(А)-LS, число пар и сечение жилы 2х2х0,6 мм2 | H67: км | I67: =I65*J67 -> 1.326 | J67: 0.102 | K67: 0.102 | O67: =ROUND(CP67,2) -> 224036.09 | P67: =ROUND((ROUND((AC67*AW67*I67),2)*BC67),2) -> 224036.09 | Q67: =(ROUND((ROUND(((ET67)*AV67*I67),2)*BB67),2)+ROUND((ROUND(((AE67-(EU67))*AV67*I67),2)*BS67),2)) -> 0 | R67: =ROUND((ROUND((AE67*AV67*I67),2)*BS67),2) -> 0 | S67: =ROUND((ROUND((AF67*AV67*I67),2)*BA67),2) -> 0 | T67: =ROUND(CU67*I67,2) -> 0 | U67: =CV67*I67 -> 0 | V67: =CW67*I67 -> 0 | W67: =ROUND(CX67*I67,2) -> 0 | X67: =ROUND(CY67,2) -> 0 | Y67: =ROUND(CZ67,2) -> 0 | AA67: 56959431 | AB67: =ROUND((AC67+AD67+AF67),6) -> 36413 | AC67: =ROUND((ES67),6) -> 36413 | AD67: =ROUND((((ET67)-(EU67))+AE67),6) -> 0 | AE67: =ROUND((EU67),6) -> 0 | AF67: =ROUND((EV67),6) -> 0 | AG67: =ROUND((AP67),6) -> 0 | AH67: =(EW67) -> 0 | AI67: =(EX67) -> 0 | AJ67: =(AS67) -> 0 | AK67: 36413 | AL67: 36413 | AM67: 0 | AN67: 0 | AO67: 0 | AP67: 0 | AQ67: 0 | AR67: 0 | AS67: 0 | AT67: 97 | AU67: 51 | AV67: 1 | AW67: 1 | AZ67: 1 | BA67: 1 | BB67: 1 | BC67: 4.64 | BH67: 3 | BI67: 2 | BJ67: ТСН-2001.1 Доп. 79, Р. 23, о. 9, поз. 92 | BM67: 67 | BN67: 55992028 | BO67: 1.23-9-92 | BP67: 1 | BQ67: 40 | BR67: 0 | BS67: 1 | BT67: 1 | BU67: 1 | BV67: 1 | BW67: 1 | BX67: 1 | BZ67: 97 | CA67: 51 | CE67: 30 | CF67: 0 | CG67: 0 | CM67: 0 | CO67: 0 | CP67: =(P67+Q67+S67) -> 224036.09 | CQ67: =ROUND((ROUND((AC67*AW67*1),2)*BC67),2) -> 168956.32 | CR67: =(ROUND((ROUND(((ET67)*AV67*1),2)*BB67),2)+ROUND((ROUND(((AE67-(EU67))*AV67*1),2)*BS67),2)) -> 0 | CS67: =ROUND((ROUND((AE67*AV67*1),2)*BS67),2) -> 0 | CT67: =ROUND((ROUND((AF67*AV67*1),2)*BA67),2) -> 0 | CU67: =AG67 -> 0 | CV67: =(AH67*AV67) -> 0 | CW67: =AI67 -> 0 | CX67: =AJ67 -> 0 | CY67: =(((S67+R67)*AT67)/100) -> 0 | CZ67: =(((S67+R67)*AU67)/100) -> 0 | DN67: 0 | DO67: 0 | DP67: 1 | DQ67: 1 | DU67: 1003 | DV67: км | DW67: км | DX67: 1000 | EE67: 55992151 | EF67: 40 | EG67: Монтаж оборудования | EH67: 0 | EJ67: 2 | EK67: 67 | EL67: ТСН-2001.4-8. Электротехнические установки | EM67: ТСН-2001.4-8-1 | EQ67: 0 | ER67: 36413 | ES67: 36413 | ET67: 0 | EU67: 0 | EV67: 0 | EW67: 0 | EX67: 0 | FQ67: 0 | FR67: 0 | FS67: 0 | FX67: 97 | FY67: 51 | GD67: 1 | GF67: -205854567 | GG67: 2 | GH67: 1 | GI67: 2 | GJ67: 0 | GK67: 0 | GL67: =ROUND(IF(AND(BH67=3,BI67=3,FS67<>0),P67,0),2) -> 0 | GM67: =ROUND(O67+X67+Y67,2)+GX67 -> 224036.09 | GN67: =IF(OR(BI67=0,BI67=1),GM67-GX67,0) -> 0 | GO67: =IF(BI67=2,GM67-GX67,0) -> 224036.09 | GP67: =IF(BI67=4,GM67-GX67,0) -> 0 | GR67: 0 | GS67: 3 | GT67: 0 | GV67: =ROUND((GT67),6) -> 0 | GW67: 1 | GX67: =ROUND(HC67*I67,2) -> 0 | HA67: 0 | HB67: 0 | HC67: =GV67*GW67 -> 0 | HS67: 0 | IK67: 0
A68: 18 | B68: 1 | C68: 77 | E68: 15,2 | F68: КА №9 | G68: Кабель КИПЭнг(А)-LSLTx2х2х0,6 | H68: м.п. | I68: =I64*J68 -> 0 | J68: 0 | K68: 0 | O68: =ROUND(CP68,2) -> 0 | P68: =ROUND((ROUND((AC68*AW68*I68),2)*BC68),2) -> 0 | Q68: =(ROUND((ROUND(((ET68)*AV68*I68),2)*BB68),2)+ROUND((ROUND(((AE68-(EU68))*AV68*I68),2)*BS68),2)) -> 0 | R68: =ROUND((ROUND((AE68*AV68*I68),2)*BS68),2) -> 0 | S68: =ROUND((ROUND((AF68*AV68*I68),2)*BA68),2) -> 0 | T68: =ROUND(CU68*I68,2) -> 0 | U68: =CV68*I68 -> 0 | V68: =CW68*I68 -> 0 | W68: =ROUND(CX68*I68,2) -> 0 | X68: =ROUND(CY68,2) -> 0 | Y68: =ROUND(CZ68,2) -> 0 | AA68: 56959434 | AB68: =ROUND((AC68+AD68+AF68),6) -> 5.08 | AC68: =ROUND((ES68),6) -> 5.08 | AD68: =ROUND((((ET68)-(EU68))+AE68),6) -> 0 | AE68: =ROUND((EU68),6) -> 0 | AF68: =ROUND((EV68),6) -> 0 | AG68: =ROUND((AP68),6) -> 0 | AH68: =(EW68) -> 0 | AI68: =(EX68) -> 0 | AJ68: =(AS68) -> 0 | AK68: 5.08 | AL68: 5.08 | AM68: 0 | AN68: 0 | AO68: 0 | AP68: 0 | AQ68: 0 | AR68: 0 | AS68: 0 | AT68: 97 | AU68: 51 | AV68: 1 | AW68: 1 | AZ68: 1 | BA68: 1 | BB68: 1 | BC68: 1 | BH68: 3 | BI68: 2 | BM68: 67 | BN68: 0 | BP68: 0 | BQ68: 40 | BR68: 0 | BS68: 1 | BT68: 1 | BU68: 1 | BV68: 1 | BW68: 1 | BX68: 1 | BZ68: 97 | CA68: 51 | CE68: 30 | CF68: 0 | CG68: 0 | CM68: 0 | CO68: 0 | CP68: =(P68+Q68+S68) -> 0 | CQ68: =ROUND((ROUND((AC68*AW68*1),2)*BC68),2) -> 5.08 | CR68: =(ROUND((ROUND(((ET68)*AV68*1),2)*BB68),2)+ROUND((ROUND(((AE68-(EU68))*AV68*1),2)*BS68),2)) -> 0 | CS68: =ROUND((ROUND((AE68*AV68*1),2)*BS68),2) -> 0 | CT68: =ROUND((ROUND((AF68*AV68*1),2)*BA68),2) -> 0 | CU68: =AG68 -> 0 | CV68: =(AH68*AV68) -> 0 | CW68: =AI68 -> 0 | CX68: =AJ68 -> 0 | CY68: =(((S68+R68)*AT68)/100) -> 0 | CZ68: =(((S68+R68)*AU68)/100) -> 0 | DN68: 0 | DO68: 0 | DP68: 1 | DQ68: 1 | DU68: 1013 | DV68: м.п. | DW68: м.п. | DX68: 1 | EE68: 55992151 | EF68: 40 | EG68: Монтаж оборудования | EH68: 0 | EJ68: 2 | EK68: 67 | EL68: ТСН-2001.4-8. Электротехнические установки | EM68: ТСН-2001.4-8-1 | EQ68: 0 | ER68: 0 | ES68: 5.08 | ET68: 0 | EU68: 0 | EV68: 0 | EW68: 0 | EX68: 0 | FQ68: 0 | FR68: 0 | FS68: 0 | FX68: 97 | FY68: 51 | GA68: [59 / 1,2 / 9,88] + 2% Заг.скл | GD68: 1 | GF68: 2097214465 | GG68: 2 | GH68: 4 | GI68: -2 | GJ68: 0 | GK68: 0 | GL68: =ROUND(IF(AND(BH68=3,BI68=3,FS68<>0),P68,0),2) -> 0 | GM68: =ROUND(O68+X68+Y68,2)+GX68 -> 0 | GN68: =IF(OR(BI68=0,BI68=1),GM68-GX68,0) -> 0 | GO68: =IF(BI68=2,GM68-GX68,0) -> 0 | GP68: =IF(BI68=4,GM68-GX68,0) -> 0 | GR68: 0 | GS68: 2 | GT68: 0 | GV68: =ROUND((GT68),6) -> 0 | GW68: 1 | GX68: =ROUND(HC68*I68,2) -> 0 | HA68: 0 | HB68: 0 | HC68: =GV68*GW68 -> 0 | HE68: 0 | HF68: 2 | HS68: 0 | IK68: 0
A69: 18 | B69: 1 | C69: 88 | E69: 15,2 | F69: КА №9 | G69: Кабель КИПЭнг(А)-LSLTx2х2х0,6 | H69: м.п. | I69: =I65*J69 -> 0 | J69: 0 | K69: 0 | O69: =ROUND(CP69,2) -> 0 | P69: =ROUND((ROUND((AC69*AW69*I69),2)*BC69),2) -> 0 | Q69: =(ROUND((ROUND(((ET69)*AV69*I69),2)*BB69),2)+ROUND((ROUND(((AE69-(EU69))*AV69*I69),2)*BS69),2)) -> 0 | R69: =ROUND((ROUND((AE69*AV69*I69),2)*BS69),2) -> 0 | S69: =ROUND((ROUND((AF69*AV69*I69),2)*BA69),2) -> 0 | T69: =ROUND(CU69*I69,2) -> 0 | U69: =CV69*I69 -> 0 | V69: =CW69*I69 -> 0 | W69: =ROUND(CX69*I69,2) -> 0 | X69: =ROUND(CY69,2) -> 0 | Y69: =ROUND(CZ69,2) -> 0 | AA69: 56959431 | AB69: =ROUND((AC69+AD69+AF69),6) -> 5.08 | AC69: =ROUND((ES69),6) -> 5.08 | AD69: =ROUND((((ET69)-(EU69))+AE69),6) -> 0 | AE69: =ROUND((EU69),6) -> 0 | AF69: =ROUND((EV69),6) -> 0 | AG69: =ROUND((AP69),6) -> 0 | AH69: =(EW69) -> 0 | AI69: =(EX69) -> 0 | AJ69: =(AS69) -> 0 | AK69: 5.08 | AL69: 5.08 | AM69: 0 | AN69: 0 | AO69: 0 | AP69: 0 | AQ69: 0 | AR69: 0 | AS69: 0 | AT69: 97 | AU69: 51 | AV69: 1 | AW69: 1 | AZ69: 1 | BA69: 1 | BB69: 1 | BC69: 9.88 | BH69: 3 | BI69: 2 | BM69: 67 | BN69: 0 | BP69: 0 | BQ69: 40 | BR69: 0 | BS69: 1 | BT69: 1 | BU69: 1 | BV69: 1 | BW69: 1 | BX69: 1 | BZ69: 97 | CA69: 51 | CE69: 30 | CF69: 0 | CG69: 0 | CM69: 0 | CO69: 0 | CP69: =(P69+Q69+S69) -> 0 | CQ69: =ROUND((ROUND((AC69*AW69*1),2)*BC69),2) -> 50.19 | CR69: =(ROUND((ROUND(((ET69)*AV69*1),2)*BB69),2)+ROUND((ROUND(((AE69-(EU69))*AV69*1),2)*BS69),2)) -> 0 | CS69: =ROUND((ROUND((AE69*AV69*1),2)*BS69),2) -> 0 | CT69: =ROUND((ROUND((AF69*AV69*1),2)*BA69),2) -> 0 | CU69: =AG69 -> 0 | CV69: =(AH69*AV69) -> 0 | CW69: =AI69 -> 0 | CX69: =AJ69 -> 0 | CY69: =(((S69+R69)*AT69)/100) -> 0 | CZ69: =(((S69+R69)*AU69)/100) -> 0 | DN69: 0 | DO69: 0 | DP69: 1 | DQ69: 1 | DU69: 1013 | DV69: м.п. | DW69: м.п. | DX69: 1 | EE69: 55992151 | EF69: 40 | EG69: Монтаж оборудования | EH69: 0 | EJ69: 2 | EK69: 67 | EL69: ТСН-2001.4-8. Электротехнические установки | EM69: ТСН-2001.4-8-1 | EQ69: 0 | ER69: 5.08 | ES69: 5.08 | ET69: 0 | EU69: 0 | EV69: 0 | EW69: 0 | EX69: 0 | EZ69: 5 | FC69: 1 | FD69: 18 | FF69: 59 | FQ69: 0 | FR69: 0 | FS69: 0 | FX69: 97 | FY69: 51 | GA69: [59 / 1,2 / 9,88] + 2% Заг.скл | GD69: 1 | GF69: 2097214465 | GG69: 2 | GH69: 3 | GI69: 5 | GJ69: 0 | GK69: 0 | GL69: =ROUND(IF(AND(BH69=3,BI69=3,FS69<>0),P69,0),2) -> 0 | GM69: =ROUND(O69+X69+Y69,2)+GX69 -> 0 | GN69: =IF(OR(BI69=0,BI69=1),GM69-GX69,0) -> 0 | GO69: =IF(BI69=2,GM69-GX69,0) -> 0 | GP69: =IF(BI69=4,GM69-GX69,0) -> 0 | GR69: 1 | GS69: 1 | GT69: 0 | GV69: =ROUND((GT69),6) -> 0 | GW69: 1 | GX69: =ROUND(HC69*I69,2) -> 0 | HA69: 0 | HB69: 0 | HC69: =GV69*GW69 -> 0 | HE69: 0 | HF69: 2 | HS69: 0 | IK69: 0
A70: 17 | B70: 1 | C70: =ROW(SmtRes!A95) -> 95 | D70: =ROW(EtalonRes!A119) -> 119 | E70: 16 | F70: 4.8-162-1 | G70: Прокладка в коробах провода сечением до 6 мм2 | H70: 100 м | I70: =ROUND(200/100,9) -> 2 | J70: 0 | K70: =ROUND(200/100,9) -> 2 | O70: =ROUND(CP70,2) -> 267.48 | P70: =ROUND((ROUND((AC70*AW70*I70),2)*BC70),2) -> 177.88 | Q70: =(ROUND((ROUND((((ET70*1.1))*AV70*I70),2)*BB70),2)+ROUND((ROUND(((AE70-((EU70*1.1)))*AV70*I70),2)*BS70),2)) -> 1.91 | R70: =ROUND((ROUND((AE70*AV70*I70),2)*BS70),2) -> 0.3 | S70: =ROUND((ROUND((AF70*AV70*I70),2)*BA70),2) -> 87.69 | T70: =ROUND(CU70*I70,2) -> 0 | U70: =CV70*I70 -> 7.117506 | V70: =CW70*I70 -> 0 | W70: =ROUND(CX70*I70,2) -> 0 | X70: =ROUND(CY70,2) -> 85.35 | Y70: =ROUND(CZ70,2) -> 44.87 | AA70: 56959434 | AB70: =ROUND((AC70+AD70+AF70),6) -> 131.73 | AC70: =ROUND((ES70),6) -> 88.94 | AD70: =ROUND(((((ET70*1.1))-((EU70*1.1)))+AE70),6) -> 0.913 | AE70: =ROUND(((EU70*1.1)),6) -> 0.143 | AF70: =ROUND(((EV70*1.1)),6) -> 41.877 | AG70: =ROUND((AP70),6) -> 0 | AH70: =((EW70*1.1)) -> 3.399 | AI70: =((EX70*1.1)) -> 0 | AJ70: =(AS70) -> 0 | AK70: 127.84 | AL70: 88.94 | AM70: 0.83 | AN70: 0.13 | AO70: 38.07 | AP70: 0 | AQ70: 3.09 | AR70: 0 | AS70: 0 | AT70: 97 | AU70: 51 | AV70: 1.047 | AW70: 1 | AZ70: 1 | BA70: 1 | BB70: 1 | BC70: 1 | BH70: 0 | BI70: 2 | BJ70: ТСН-2001.4 Доп. 68, Сб. 8, т. 162, поз. 1 | BM70: 67 | BN70: 55992028 | BO70: 4.8-162-1 | BP70: 1 | BQ70: 40 | BR70: 0 | BS70: 1 | BT70: 1 | BU70: 1 | BV70: 1 | BW70: 1 | BX70: 1 | BZ70: 97 | CA70: 51 | CE70: 30 | CF70: 0 | CG70: 0 | CM70: 0 | CN70: Поправка: Гл.12.Прил.8.п.8. 5_12.00.01.11.003 Наименование: При наличии усложненных условий производства работ (стесненность, сложность складирования и транспортной логистики, наличие в зоне производства работ действующего технологического оборудования или движения технологического транспорта и т.п.) для объектов, расположенных за пределами территории круговой магистральной системы улиц "Садовое кольцо" и за пределами Третьего транспортного кольца города Москвы пунктов "а" и "б", но в пределах Московской кольцевой автомобильной дороги | CO70: 0 | CP70: =(P70+Q70+S70) -> 267.48 | CQ70: =ROUND((ROUND((AC70*AW70*1),2)*BC70),2) -> 88.94 | CR70: =(ROUND((ROUND((((ET70*1.1))*AV70*1),2)*BB70),2)+ROUND((ROUND(((AE70-((EU70*1.1)))*AV70*1),2)*BS70),2)) -> 0.96 | CS70: =ROUND((ROUND((AE70*AV70*1),2)*BS70),2) -> 0.15 | CT70: =ROUND((ROUND((AF70*AV70*1),2)*BA70),2) -> 43.85 | CU70: =AG70 -> 0 | CV70: =(AH70*AV70) -> 3.558753 | CW70: =AI70 -> 0 | CX70: =AJ70 -> 0 | CY70: =(((S70+R70)*AT70)/100) -> 85.3503 | CZ70: =(((S70+R70)*AU70)/100) -> 44.8749 | DE70: *1,1 | DF70: *1,1 | DG70: *1,1 | DI70: *1,1 | DJ70: *1,1 | DN70: 0 | DO70: 0 | DP70: 1 | DQ70: 1 | DU70: 1003 | DV70: 100 м | DW70: 100 м | DX70: 100 | EE70: 55992151 | EF70: 40 | EG70: Монтаж оборудования | EH70: 0 | EJ70: 2 | EK70: 67 | EL70: ТСН-2001.4-8. Электротехнические установки | EM70: ТСН-2001.4-8-1 | EO70: Поправка: Гл.12.Прил.8.п.8. 5_12.00.01.11.003 | EQ70: 0 | ER70: 127.84 | ES70: 88.94 | ET70: 0.83 | EU70: 0.13 | EV70: 38.07 | EW70: 3.09 | EX70: 0 | EY70: 0 | FQ70: 0 | FR70: 0 | FS70: 0 | FX70: 97 | FY70: 51 | GD70: 1 | GF70: -1750277137 | GG70: 2 | GH70: 1 | GI70: 2 | GJ70: 0 | GK70: 0 | GL70: =ROUND(IF(AND(BH70=3,BI70=3,FS70<>0),P70,0),2) -> 0 | GM70: =ROUND(O70+X70+Y70,2)+GX70 -> 397.7 | GN70: =IF(OR(BI70=0,BI70=1),GM70-GX70,0) -> 0 | GO70: =IF(BI70=2,GM70-GX70,0) -> 397.7 | GP70: =IF(BI70=4,GM70-GX70,0) -> 0 | GR70: 0 | GS70: 3 | GT70: 0 | GV70: =ROUND((GT70),6) -> 0 | GW70: 1 | GX70: =ROUND(HC70*I70,2) -> 0 | HA70: 0 | HB70: 0 | HC70: =GV70*GW70 -> 0 | HS70: 0 | IK70: 0
A71: 17 | B71: 1 | C71: =ROW(SmtRes!A102) -> 102 | D71: =ROW(EtalonRes!A126) -> 126 | E71: 16 | F71: 4.8-162-1 | G71: Прокладка в коробах провода сечением до 6 мм2 | H71: 100 м | I71: =ROUND(200/100,9) -> 2 | J71: 0 | K71: =ROUND(200/100,9) -> 2 | O71: =ROUND(CP71,2) -> 6142.89 | P71: =ROUND((ROUND((AC71*AW71*I71),2)*BC71),2) -> 1289.63 | Q71: =(ROUND((ROUND((((ET71*1.1))*AV71*I71),2)*BB71),2)+ROUND((ROUND(((AE71-((EU71*1.1)))*AV71*I71),2)*BS71),2)) -> 31.19 | R71: =ROUND((ROUND((AE71*AV71*I71),2)*BS71),2) -> 16.5 | S71: =ROUND((ROUND((AF71*AV71*I71),2)*BA71),2) -> 4822.07 | T71: =ROUND(CU71*I71,2) -> 0 | U71: =CV71*I71 -> 7.117506 | V71: =CW71*I71 -> 0 | W71: =ROUND(CX71*I71,2) -> 0 | X71: =ROUND(CY71,2) -> 4693.41 | Y71: =ROUND(CZ71,2) -> 2467.67 | AA71: 56959431 | AB71: =ROUND((AC71+AD71+AF71),6) -> 131.73 | AC71: =ROUND((ES71),6) -> 88.94 | AD71: =ROUND(((((ET71*1.1))-((EU71*1.1)))+AE71),6) -> 0.913 | AE71: =ROUND(((EU71*1.1)),6) -> 0.143 | AF71: =ROUND(((EV71*1.1)),6) -> 41.877 | AG71: =ROUND((AP71),6) -> 0 | AH71: =((EW71*1.1)) -> 3.399 | AI71: =((EX71*1.1)) -> 0 | AJ71: =(AS71) -> 0 | AK71: 127.84 | AL71: 88.94 | AM71: 0.83 | AN71: 0.13 | AO71: 38.07 | AP71: 0 | AQ71: 3.09 | AR71: 0 | AS71: 0 | AT71: 97 | AU71: 51 | AV71: 1.047 | AW71: 1 | AZ71: 1 | BA71: 54.99 | BB71: 16.33 | BC71: 7.25 | BH71: 0 | BI71: 2 | BJ71: ТСН-2001.4 Доп. 68, Сб. 8, т. 162, поз. 1 | BM71: 67 | BN71: 55992028 | BO71: 4.8-162-1 | BP71: 1 | BQ71: 40 | BR71: 0 | BS71: 54.99 | BT71: 1 | BU71: 1 | BV71: 1 | BW71: 1 | BX71: 1 | BZ71: 97 | CA71: 51 | CE71: 30 | CF71: 0 | CG71: 0 | CM71: 0 | CN71: Поправка: Гл.12.Прил.8.п.8. 5_12.00.01.11.003 Наименование: При наличии усложненных условий производства работ (стесненность, сложность складирования и транспортной логистики, наличие в зоне производства работ действующего технологического оборудования или движения технологического транспорта и т.п.) для объектов, расположенных за пределами территории круговой магистральной системы улиц "Садовое кольцо" и за пределами Третьего транспортного кольца города Москвы пунктов "а" и "б", но в пределах Московской кольцевой автомобильной дороги | CO71: 0 | CP71: =(P71+Q71+S71) -> 6142.89 | CQ71: =ROUND((ROUND((AC71*AW71*1),2)*BC71),2) -> 644.82 | CR71: =(ROUND((ROUND((((ET71*1.1))*AV71*1),2)*BB71),2)+ROUND((ROUND(((AE71-((EU71*1.1)))*AV71*1),2)*BS71),2)) -> 15.68 | CS71: =ROUND((ROUND((AE71*AV71*1),2)*BS71),2) -> 8.25 | CT71: =ROUND((ROUND((AF71*AV71*1),2)*BA71),2) -> 2411.31 | CU71: =AG71 -> 0 | CV71: =(AH71*AV71) -> 3.558753 | CW71: =AI71 -> 0 | CX71: =AJ71 -> 0 | CY71: =(((S71+R71)*AT71)/100) -> 4693.4129 | CZ71: =(((S71+R71)*AU71)/100) -> 2467.6707 | DE71: *1,1 | DF71: *1,1 | DG71: *1,1 | DI71: *1,1 | DJ71: *1,1 | DN71: 0 | DO71: 0 | DP71: 1 | DQ71: 1 | DU71: 1003 | DV71: 100 м | DW71: 100 м | DX71: 100 | EE71: 55992151 | EF71: 40 | EG71: Монтаж оборудования | EH71: 0 | EJ71: 2 | EK71: 67 | EL71: ТСН-2001.4-8. Электротехнические установки | EM71: ТСН-2001.4-8-1 | EO71: Поправка: Гл.12.Прил.8.п.8. 5_12.00.01.11.003 | EQ71: 0 | ER71: 127.84 | ES71: 88.94 | ET71: 0.83 | EU71: 0.13 | EV71: 38.07 | EW71: 3.09 | EX71: 0 | EY71: 0 | FQ71: 0 | FR71: 0 | FS71: 0 | FX71: 97 | FY71: 51 | GD71: 1 | GF71: -1750277137 | GG71: 2 | GH71: 1 | GI71: 2 | GJ71: 0 | GK71: 0 | GL71: =ROUND(IF(AND(BH71=3,BI71=3,FS71<>0),P71,0),2) -> 0 | GM71: =ROUND(O71+X71+Y71,2)+GX71 -> 13303.97 | GN71: =IF(OR(BI71=0,BI71=1),GM71-GX71,0) -> 0 | GO71: =IF(BI71=2,GM71-GX71,0) -> 13303.97 | GP71: =IF(BI71=4,GM71-GX71,0) -> 0 | GR71: 0 | GS71: 3 | GT71: 0 | GV71: =ROUND((GT71),6) -> 0 | GW71: 1 | GX71: =ROUND(HC71*I71,2) -> 0 | HA71: 0 | HB71: 0 | HC71: =GV71*GW71 -> 0 | HS71: 0 | IK71: 0
A72: 18 | B72: 1 | C72: 95 | E72: 16,1 | F72: 1.23-9-92 | G72: Кабель симметричный, парной скрутки, с изоляцией из сплошного полиэтилена, с общим экраном, в оболочке из ПВХ пластиката пониженной пожароопасности, с низким дымо- и газовыделением, марка КИПЭВнг(А)-LS, число пар и сечение жилы 2х2х0,6 мм2 | H72: км | I72: =I70*J72 -> 0.204 | J72: 0.102 | K72: 0.102 | O72: =ROUND(CP72,2) -> 7428.25 | P72: =ROUND((ROUND((AC72*AW72*I72),2)*BC72),2) -> 7428.25 | Q72: =(ROUND((ROUND(((ET72)*AV72*I72),2)*BB72),2)+ROUND((ROUND(((AE72-(EU72))*AV72*I72),2)*BS72),2)) -> 0 | R72: =ROUND((ROUND((AE72*AV72*I72),2)*BS72),2) -> 0 | S72: =ROUND((ROUND((AF72*AV72*I72),2)*BA72),2) -> 0 | T72: =ROUND(CU72*I72,2) -> 0 | U72: =CV72*I72 -> 0 | V72: =CW72*I72 -> 0 | W72: =ROUND(CX72*I72,2) -> 0 | X72: =ROUND(CY72,2) -> 0 | Y72: =ROUND(CZ72,2) -> 0 | AA72: 56959434 | AB72: =ROUND((AC72+AD72+AF72),6) -> 36413 | AC72: =ROUND((ES72),6) -> 36413 | AD72: =ROUND((((ET72)-(EU72))+AE72),6) -> 0 | AE72: =ROUND((EU72),6) -> 0 | AF72: =ROUND((EV72),6) -> 0 | AG72: =ROUND((AP72),6) -> 0 | AH72: =(EW72) -> 0 | AI72: =(EX72) -> 0 | AJ72: =(AS72) -> 0 | AK72: 36413 | AL72: 36413 | AM72: 0 | AN72: 0 | AO72: 0 | AP72: 0 | AQ72: 0 | AR72: 0 | AS72: 0 | AT72: 97 | AU72: 51 | AV72: 1 | AW72: 1 | AZ72: 1 | BA72: 1 | BB72: 1 | BC72: 1 | BH72: 3 | BI72: 2 | BJ72: ТСН-2001.1 Доп. 79, Р. 23, о. 9, поз. 92 | BM72: 67 | BN72: 55992028 | BP72: 0 | BQ72: 40 | BR72: 0 | BS72: 1 | BT72: 1 | BU72: 1 | BV72: 1 | BW72: 1 | BX72: 1 | BZ72: 97 | CA72: 51 | CE72: 30 | CF72: 0 | CG72: 0 | CM72: 0 | CO72: 0 | CP72: =(P72+Q72+S72) -> 7428.25 | CQ72: =ROUND((ROUND((AC72*AW72*1),2)*BC72),2) -> 36413 | CR72: =(ROUND((ROUND(((ET72)*AV72*1),2)*BB72),2)+ROUND((ROUND(((AE72-(EU72))*AV72*1),2)*BS72),2)) -> 0 | CS72: =ROUND((ROUND((AE72*AV72*1),2)*BS72),2) -> 0 | CT72: =ROUND((ROUND((AF72*AV72*1),2)*BA72),2) -> 0 | CU72: =AG72 -> 0 | CV72: =(AH72*AV72) -> 0 | CW72: =AI72 -> 0 | CX72: =AJ72 -> 0 | CY72: =(((S72+R72)*AT72)/100) -> 0 | CZ72: =(((S72+R72)*AU72)/100) -> 0 | DN72: 0 | DO72: 0 | DP72: 1 | DQ72: 1 | DU72: 1003 | DV72: км | DW72: км | DX72: 1000 | EE72: 55992151 | EF72: 40 | EG72: Монтаж оборудования | EH72: 0 | EJ72: 2 | EK72: 67 | EL72: ТСН-2001.4-8. Электротехнические установки | EM72: ТСН-2001.4-8-1 | EQ72: 0 | ER72: 36413 | ES72: 36413 | ET72: 0 | EU72: 0 | EV72: 0 | EW72: 0 | EX72: 0 | FQ72: 0 | FR72: 0 | FS72: 0 | FX72: 97 | FY72: 51 | GD72: 1 | GF72: -205854567 | GG72: 2 | GH72: 1 | GI72: -2 | GJ72: 0 | GK72: 0 | GL72: =ROUND(IF(AND(BH72=3,BI72=3,FS72<>0),P72,0),2) -> 0 | GM72: =ROUND(O72+X72+Y72,2)+GX72 -> 7428.25 | GN72: =IF(OR(BI72=0,BI72=1),GM72-GX72,0) -> 0 | GO72: =IF(BI72=2,GM72-GX72,0) -> 7428.25 | GP72: =IF(BI72=4,GM72-GX72,0) -> 0 | GR72: 0 | GS72: 3 | GT72: 0 | GV72: =ROUND((GT72),6) -> 0 | GW72: 1 | GX72: =ROUND(HC72*I72,2) -> 0 | HA72: 0 | HB72: 0 | HC72: =GV72*GW72 -> 0 | HS72: 0 | IK72: 0
A73: 18 | B73: 1 | C73: 102 | E73: 16,1 | F73: 1.23-9-92 | G73: Кабель симметричный, парной скрутки, с изоляцией из сплошного полиэтилена, с общим экраном, в оболочке из ПВХ пластиката пониженной пожароопасности, с низким дымо- и газовыделением, марка КИПЭВнг(А)-LS, число пар и сечение жилы 2х2х0,6 мм2 | H73: км | I73: =I71*J73 -> 0.204 | J73: 0.102 | K73: 0.102 | O73: =ROUND(CP73,2) -> 34467.08 | P73: =ROUND((ROUND((AC73*AW73*I73),2)*BC73),2) -> 34467.08 | Q73: =(ROUND((ROUND(((ET73)*AV73*I73),2)*BB73),2)+ROUND((ROUND(((AE73-(EU73))*AV73*I73),2)*BS73),2)) -> 0 | R73: =ROUND((ROUND((AE73*AV73*I73),2)*BS73),2) -> 0 | S73: =ROUND((ROUND((AF73*AV73*I73),2)*BA73),2) -> 0 | T73: =ROUND(CU73*I73,2) -> 0 | U73: =CV73*I73 -> 0 | V73: =CW73*I73 -> 0 | W73: =ROUND(CX73*I73,2) -> 0 | X73: =ROUND(CY73,2) -> 0 | Y73: =ROUND(CZ73,2) -> 0 | AA73: 56959431 | AB73: =ROUND((AC73+AD73+AF73),6) -> 36413 | AC73: =ROUND((ES73),6) -> 36413 | AD73: =ROUND((((ET73)-(EU73))+AE73),6) -> 0 | AE73: =ROUND((EU73),6) -> 0 | AF73: =ROUND((EV73),6) -> 0 | AG73: =ROUND((AP73),6) -> 0 | AH73: =(EW73) -> 0 | AI73: =(EX73) -> 0 | AJ73: =(AS73) -> 0 | AK73: 36413 | AL73: 36413 | AM73: 0 | AN73: 0 | AO73: 0 | AP73: 0 | AQ73: 0 | AR73: 0 | AS73: 0 | AT73: 97 | AU73: 51 | AV73: 1 | AW73: 1 | AZ73: 1 | BA73: 1 | BB73: 1 | BC73: 4.64 | BH73: 3 | BI73: 2 | BJ73: ТСН-2001.1 Доп. 79, Р. 23, о. 9, поз. 92 | BM73: 67 | BN73: 55992028 | BO73: 1.23-9-92 | BP73: 1 | BQ73: 40 | BR73: 0 | BS73: 1 | BT73: 1 | BU73: 1 | BV73: 1 | BW73: 1 | BX73: 1 | BZ73: 97 | CA73: 51 | CE73: 30 | CF73: 0 | CG73: 0 | CM73: 0 | CO73: 0 | CP73: =(P73+Q73+S73) -> 34467.08 | CQ73: =ROUND((ROUND((AC73*AW73*1),2)*BC73),2) -> 168956.32 | CR73: =(ROUND((ROUND(((ET73)*AV73*1),2)*BB73),2)+ROUND((ROUND(((AE73-(EU73))*AV73*1),2)*BS73),2)) -> 0 | CS73: =ROUND((ROUND((AE73*AV73*1),2)*BS73),2) -> 0 | CT73: =ROUND((ROUND((AF73*AV73*1),2)*BA73),2) -> 0 | CU73: =AG73 -> 0 | CV73: =(AH73*AV73) -> 0 | CW73: =AI73 -> 0 | CX73: =AJ73 -> 0 | CY73: =(((S73+R73)*AT73)/100) -> 0 | CZ73: =(((S73+R73)*AU73)/100) -> 0 | DN73: 0 | DO73: 0 | DP73: 1 | DQ73: 1 | DU73: 1003 | DV73: км | DW73: км | DX73: 1000 | EE73: 55992151 | EF73: 40 | EG73: Монтаж оборудования | EH73: 0 | EJ73: 2 | EK73: 67 | EL73: ТСН-2001.4-8. Электротехнические установки | EM73: ТСН-2001.4-8-1 | EQ73: 0 | ER73: 36413 | ES73: 36413 | ET73: 0 | EU73: 0 | EV73: 0 | EW73: 0 | EX73: 0 | FQ73: 0 | FR73: 0 | FS73: 0 | FX73: 97 | FY73: 51 | GD73: 1 | GF73: -205854567 | GG73: 2 | GH73: 1 | GI73: 2 | GJ73: 0 | GK73: 0 | GL73: =ROUND(IF(AND(BH73=3,BI73=3,FS73<>0),P73,0),2) -> 0 | GM73: =ROUND(O73+X73+Y73,2)+GX73 -> 34467.08 | GN73: =IF(OR(BI73=0,BI73=1),GM73-GX73,0) -> 0 | GO73: =IF(BI73=2,GM73-GX73,0) -> 34467.08 | GP73: =IF(BI73=4,GM73-GX73,0) -> 0 | GR73: 0 | GS73: 3 | GT73: 0 | GV73: =ROUND((GT73),6) -> 0 | GW73: 1 | GX73: =ROUND(HC73*I73,2) -> 0 | HA73: 0 | HB73: 0 | HC73: =GV73*GW73 -> 0 | HS73: 0 | IK73: 0
A75: 51 | B75: =B24 -> 1 | C75: =A24 -> 4 | D75: =ROW(A24) -> 24 | F75: =IF(F24<>"",F24,"") -> Новый раздел | G75: =IF(G24<>"",G24,"") -> Система управления и диспетчерского контроля инженерного | H75: 0 | O75: =ROUND(AB75,2) -> 116438.62 | P75: =ROUND(AC75,2) -> 107651.76 | Q75: =ROUND(AD75,2) -> 1034.27 | R75: =ROUND(AE75,2) -> 173.24 | S75: =ROUND(AF75,2) -> 7752.59 | T75: =ROUND(AG75,2) -> 0 | U75: =AH75 -> 615.2796 | V75: =AI75 -> 0 | W75: =ROUND(AJ75,2) -> 0 | X75: =ROUND(AK75,2) -> 7675.44 | Y75: =ROUND(AL75,2) -> 4033.13 | AB75: =ROUND(SUMIF(AA28:AA73,"=56959434",O28:O73),2) -> 116438.62 | AC75: =ROUND(SUMIF(AA28:AA73,"=56959434",P28:P73),2) -> 107651.76 | AD75: =ROUND(SUMIF(AA28:AA73,"=56959434",Q28:Q73),2) -> 1034.27 | AE75: =ROUND(SUMIF(AA28:AA73,"=56959434",R28:R73),2) -> 173.24 | AF75: =ROUND(SUMIF(AA28:AA73,"=56959434",S28:S73),2) -> 7752.59 | AG75: =ROUND(SUMIF(AA28:AA73,"=56959434",T28:T73),2) -> 0 | AH75: =SUMIF(AA28:AA73,"=56959434",U28:U73) -> 615.2796 | AI75: =SUMIF(AA28:AA73,"=56959434",V28:V73) -> 0 | AJ75: =ROUND(SUMIF(AA28:AA73,"=56959434",W28:W73),2) -> 0 | AK75: =ROUND(SUMIF(AA28:AA73,"=56959434",X28:X73),2) -> 7675.44 | AL75: =ROUND(SUMIF(AA28:AA73,"=56959434",Y28:Y73),2) -> 4033.13 | AO75: =ROUND(BX75,2) -> 0 | AP75: =ROUND(BY75,2) -> 25039.7 | AQ75: =ROUND(BZ75,2) -> 0 | AR75: =ROUND(CA75,2) -> 128147.19 | AS75: =ROUND(CB75,2) -> 0 | AT75: =ROUND(CC75,2) -> 103107.49 | AU75: =ROUND(CD75,2) -> 0 | AV75: =ROUND(CE75,2) -> 107651.76 | ... BD75: =ROUND(CM75,2) -> 0 | BX75: =ROUND(SUMIF(AA28:AA73,"=56959434",FQ28:FQ73),2) -> 0 | BY75: =ROUND(SUMIF(AA28:AA73,"=56959434",FR28:FR73),2) -> 25039.7 | BZ75: =ROUND(SUMIF(AA28:AA73,"=56959434",GL28:GL73),2) -> 0 | CA75: =ROUND(SUMIF(AA28:AA73,"=56959434",GM28:GM73),2) -> 128147.19 | CB75: =ROUND(SUMIF(AA28:AA73,"=56959434",GN28:GN73),2) -> 0 | CC75: =ROUND(SUMIF(AA28:AA73,"=56959434",GO28:GO73),2) -> 103107.49 | CD75: =ROUND(SUMIF(AA28:AA73,"=56959434",GP28:GP73),2) -> 0 | CE75: =AC75-BX75 -> 107651.76 | CF75: =AC75-BY75 -> 82612.06 | CG75: =BX75-BZ75 -> 0 | CH75: =AC75-BX75-BY75+BZ75 -> 82612.06 | CI75: =BY75-BZ75 -> 25039.7 | CJ75: =ROUND(SUMIF(AA28:AA73,"=56959434",GX28:GX73),2) -> 0 | CK75: =ROUND(SUMIF(AA28:AA73,"=56959434",GY28:GY73),2) -> 0 | CL75: =ROUND(SUMIF(AA28:AA73,"=56959434",GZ28:GZ73),2) -> 0 | CM75: =ROUND(SUMIF(AA28:AA73,"=56959434",HD28:HD73),2) -> 0 | DG75: =ROUND(DT75,2) -> 1094737.6 | DH75: =ROUND(DU75,2) -> 650315.77 | DI75: =ROUND(DV75,2) -> 18106.94 | DJ75: =ROUND(DW75,2) -> 9526.49 | DK75: =ROUND(DX75,2) -> 426314.93 | DL75: =ROUND(DY75,2) -> 0 | DM75: =DZ75 -> 615.2796 | DN75: =EA75 -> 0 | DO75: =ROUND(EB75,2) -> 0 | DP75: =ROUND(EC75,2) -> 422071.77 | DQ75: =ROUND(ED75,2) -> 221783.12 | DT75: =ROUND(SUMIF(AA28:AA73,"=56959431",O28:O73),2) -> 1094737.6 | DU75: =ROUND(SUMIF(AA28:AA73,"=56959431",P28:P73),2) -> 650315.77 | DV75: =ROUND(SUMIF(AA28:AA73,"=56959431",Q28:Q73),2) -> 18106.94 | DW75: =ROUND(SUMIF(AA28:AA73,"=56959431",R28:R73),2) -> 9526.49 | DX75: =ROUND(SUMIF(AA28:AA73,"=56959431",S28:S73),2) -> 426314.93 | DY75: =ROUND(SUMIF(AA28:AA73,"=56959431",T28:T73),2) -> 0 | DZ75: =SUMIF(AA28:AA73,"=56959431",U28:U73) -> 615.2796 | EA75: =SUMIF(AA28:AA73,"=56959431",V28:V73) -> 0 | EB75: =ROUND(SUMIF(AA28:AA73,"=56959431",W28:W73),2) -> 0 | EC75: =ROUND(SUMIF(AA28:AA73,"=56959431",X28:X73),2) -> 422071.77 | ED75: =ROUND(SUMIF(AA28:AA73,"=56959431",Y28:Y73),2) -> 221783.12 | EG75: =ROUND(FP75,2) -> 0 | EH75: =ROUND(FQ75,2) -> 191804.11 | EI75: =ROUND(FR75,2) -> 0 | EJ75: =ROUND(FS75,2) -> 1738592.5 | EK75: =ROUND(FT75,2) -> 0 | EL75: =ROUND(FU75,2) -> 1546788.4 | EM75: =ROUND(FV75,2) -> 0 | EN75: =ROUND(FW75,2) -> 650315.77 | ... EV75: =ROUND(GE75,2) -> 0 | FP75: =ROUND(SUMIF(AA28:AA73,"=56959431",FQ28:FQ73),2) -> 0 | FQ75: =ROUND(SUMIF(AA28:AA73,"=56959431",FR28:FR73),2) -> 191804.11 | FR75: =ROUND(SUMIF(AA28:AA73,"=56959431",GL28:GL73),2) -> 0 | FS75: =ROUND(SUMIF(AA28:AA73,"=56959431",GM28:GM73),2) -> 1738592.5 | FT75: =ROUND(SUMIF(AA28:AA73,"=56959431",GN28:GN73),2) -> 0 | FU75: =ROUND(SUMIF(AA28:AA73,"=56959431",GO28:GO73),2) -> 1546788.4 | FV75: =ROUND(SUMIF(AA28:AA73,"=56959431",GP28:GP73),2) -> 0 | FW75: =DU75-FP75 -> 650315.77 | FX75: =DU75-FQ75 -> 458511.66 | FY75: =FP75-FR75 -> 0 | FZ75: =DU75-FP75-FQ75+FR75 -> 458511.66 | GA75: =FQ75-FR75 -> 191804.11 | GB75: =ROUND(SUMIF(AA28:AA73,"=56959431",GX28:GX73),2) -> 0 | GC75: =ROUND(SUMIF(AA28:AA73,"=56959431",GY28:GY73),2) -> 0 | GD75: =ROUND(SUMIF(AA28:AA73,"=56959431",GZ28:GZ73),2) -> 0 | GE75: =ROUND(SUMIF(AA28:AA73,"=56959431",HD28:HD73),2) -> 0 | GX75: 0
A77: 50 | B77: 0 | C77: 0 | D77: 1 | E77: 201 | F77: =ROUND(Source!O75,O77) -> 116438.62 | G77: ПЗ | H77: Прямые затраты | K77: 201 | L77: 1 | M77: 3 | O77: 2 | P77: =ROUND(Source!DG75,O77) -> 1094737.6 | W77: 116438.62 | X77: 1 | Y77: 116438.62 | Z77: 1094737.6 | AA77: 1 | AB77: 1094737.6
A78: 50 | B78: 0 | C78: 0 | D78: 1 | E78: 202 | F78: =ROUND(Source!P75,O78) -> 107651.76 | G78: СтМатОб | H78: Стоимость материальных ресурсов (всего) | K78: 202 | L78: 2 | M78: 3 | O78: 2 | P78: =ROUND(Source!DH75,O78) -> 650315.77 | W78: 107651.76 | X78: 1 | Y78: 107651.76 | Z78: 650315.77 | AA78: 1 | AB78: 650315.77
A79: 50 | B79: 0 | C79: 0 | D79: 1 | E79: 222 | F79: =ROUND(Source!AO75,O79) -> 0 | G79: СтМатОбЗак | H79: Стоимость материалов и оборудования заказчика | K79: 222 | L79: 3 | M79: 3 | O79: 2 | P79: =ROUND(Source!EG75,O79) -> 0 | W79: 0 | X79: 1 | Y79: 0 | Z79: 0 | AA79: 1 | AB79: 0
A80: 50 | B80: 0 | C80: 0 | D80: 1 | E80: 225 | F80: =ROUND(Source!AV75,O80) -> 107651.76 | G80: СтМатОбПод | H80: Стоимость материалов и оборудования подрядчика | K80: 225 | L80: 4 | M80: 3 | O80: 2 | P80: =ROUND(Source!EN75,O80) -> 650315.77 | W80: 107651.76 | X80: 1 | Y80: 107651.76 | Z80: 650315.77 | AA80: 1 | AB80: 650315.77
A81: 50 | B81: 0 | C81: 0 | D81: 1 | E81: 226 | F81: =ROUND(Source!AW75,O81) -> 82612.06 | G81: СтМат | H81: Стоимость материалов (всего) | K81: 226 | L81: 5 | M81: 3 | O81: 2 | P81: =ROUND(Source!EO75,O81) -> 458511.66 | W81: 82612.06 | X81: 1 | Y81: 82612.06 | Z81: 458511.66 | AA81: 1 | AB81: 458511.66
A82: 50 | B82: 0 | C82: 0 | D82: 1 | E82: 227 | F82: =ROUND(Source!AX75,O82) -> 0 | G82: СтМатЗак | H82: Стоимость материалов заказчика | K82: 227 | L82: 6 | M82: 3 | O82: 2 | P82: =ROUND(Source!EP75,O82) -> 0 | W82: 0 | X82: 1 | Y82: 0 | Z82: 0 | AA82: 1 | AB82: 0
A83: 50 | B83: 0 | C83: 0 | D83: 1 | E83: 228 | F83: =ROUND(Source!AY75,O83) -> 82612.06 | G83: СтМатПод | H83: Стоимость материалов подрядчика | K83: 228 | L83: 7 | M83: 3 | O83: 2 | P83: =ROUND(Source!EQ75,O83) -> 458511.66 | W83: 82612.06 | X83: 1 | Y83: 82612.06 | Z83: 458511.66 | AA83: 1 | AB83: 458511.66
A84: 50 | B84: 0 | C84: 0 | D84: 1 | E84: 216 | F84: =ROUND(Source!AP75,O84) -> 25039.7 | G84: Оборуд | H84: Стоимость оборудования (всего) | K84: 216 | L84: 8 | M84: 3 | O84: 2 | P84: =ROUND(Source!EH75,O84) -> 191804.11 | W84: 25039.7 | X84: 1 | Y84: 25039.7 | Z84: 191804.11 | AA84: 1 | AB84: 191804.11
A85: 50 | B85: 0 | C85: 0 | D85: 1 | E85: 223 | F85: =ROUND(Source!AQ75,O85) -> 0 | G85: ОборудЗак | H85: Стоимость оборудования заказчика | K85: 223 | L85: 9 | M85: 3 | O85: 2 | P85: =ROUND(Source!EI75,O85) -> 0 | W85: 0 | X85: 1 | Y85: 0 | Z85: 0 | AA85: 1 | AB85: 0
A86: 50 | B86: 0 | C86: 0 | D86: 1 | E86: 229 | F86: =ROUND(Source!AZ75,O86) -> 25039.7 | G86: ОборудПод | H86: Стоимость оборудования подрядчика | K86: 229 | L86: 10 | M86: 3 | O86: 2 | P86: =ROUND(Source!ER75,O86) -> 191804.11 | W86: 25039.7 | X86: 1 | Y86: 25039.7 | Z86: 191804.11 | AA86: 1 | AB86: 191804.11
A87: 50 | B87: 0 | C87: 0 | D87: 1 | E87: 203 | F87: =ROUND(Source!Q75,O87) -> 1034.27 | G87: ЭММ | H87: Эксплуатация машин | K87: 203 | L87: 11 | M87: 3 | O87: 2 | P87: =ROUND(Source!DI75,O87) -> 18106.94 | W87: 1034.27 | X87: 1 | Y87: 1034.27 | Z87: 18106.94 | AA87: 1 | AB87: 18106.94
A88: 50 | B88: 0 | C88: 0 | D88: 1 | E88: 231 | F88: =ROUND(Source!BB75,O88) -> 0 | G88: ЭММсНРиСП | H88: Эксплуатация машин по ТСН-2001.16 | K88: 231 | L88: 12 | M88: 3 | O88: 2 | P88: =ROUND(Source!ET75,O88) -> 0 | W88: 0 | X88: 1 | Y88: 0 | Z88: 0 | AA88: 1 | AB88: 0
A89: 50 | B89: 0 | C89: 0 | D89: 1 | E89: 204 | F89: =ROUND(Source!R75,O89) -> 173.24 | G89: ЗПМ | H89: ЗП машинистов | K89: 204 | L89: 13 | M89: 3 | O89: 2 | P89: =ROUND(Source!DJ75,O89) -> 9526.49 | W89: 173.24 | X89: 1 | Y89: 173.24 | Z89: 9526.49 | AA89: 1 | AB89: 9526.49
A90: 50 | B90: 0 | C90: 0 | D90: 1 | E90: 205 | F90: =ROUND(Source!S75,O90) -> 7752.59 | G90: ОЗП | H90: Основная ЗП рабочих | K90: 205 | L90: 14 | M90: 3 | O90: 2 | P90: =ROUND(Source!DK75,O90) -> 426314.93 | W90: 7752.59 | X90: 1 | Y90: 7752.59 | Z90: 426314.93 | AA90: 1 | AB90: 426314.93
A91: 50 | B91: 0 | C91: 0 | D91: 1 | E91: 232 | F91: =ROUND(Source!BC75,O91) -> 0 | G91: ОЗПсНРиСП | H91: Основная ЗП рабочих по ТСН-2001.16 | K91: 232 | L91: 15 | M91: 3 | O91: 2 | P91: =ROUND(Source!EU75,O91) -> 0 | W91: 0 | X91: 1 | Y91: 0 | Z91: 0 | AA91: 1 | AB91: 0
A92: 50 | B92: 0 | C92: 0 | D92: 1 | E92: 214 | F92: =ROUND(Source!AS75,O92) -> 0 | G92: Строит | H92: Строительные работы с НР и СП | K92: 214 | L92: 16 | M92: 3 | O92: 2 | P92: =ROUND(Source!EK75,O92) -> 0 | W92: 0 | X92: 1 | Y92: 0 | Z92: 0 | AA92: 1 | AB92: 0
A93: 50 | B93: 0 | C93: 0 | D93: 1 | E93: 215 | F93: =ROUND(Source!AT75,O93) -> 103107.49 | G93: Монтаж | H93: Монтажные работы с НР и СП | K93: 215 | L93: 17 | M93: 3 | O93: 2 | P93: =ROUND(Source!EL75,O93) -> 1546788.4 | W93: 103107.49 | X93: 1 | Y93: 103107.49 | Z93: 1546788.4 | AA93: 1 | AB93: 1546788.4
A94: 50 | B94: 0 | C94: 0 | D94: 1 | E94: 217 | F94: =ROUND(Source!AU75,O94) -> 0 | G94: Прочие | H94: Прочие работы с НР и СП | K94: 217 | L94: 18 | M94: 3 | O94: 2 | P94: =ROUND(Source!EM75,O94) -> 0 | W94: 0 | X94: 1 | Y94: 0 | Z94: 0 | AA94: 1 | AB94: 0
A95: 50 | B95: 0 | C95: 0 | D95: 1 | E95: 230 | F95: =ROUND(Source!BA75,O95) -> 0 | G95: ПрочиеЗатр | H95: Прочие затраты по ТСН-2001.16 | K95: 230 | L95: 19 | M95: 3 | O95: 2 | P95: =ROUND(Source!ES75,O95) -> 0 | W95: 0 | X95: 1 | Y95: 0 | Z95: 0 | AA95: 1 | AB95: 0
A96: 50 | B96: 0 | C96: 0 | D96: 1 | E96: 206 | F96: =ROUND(Source!T75,O96) -> 0 | G96: ВозврМат | H96: Возврат материалов | K96: 206 | L96: 20 | M96: 3 | O96: 2 | P96: =ROUND(Source!DL75,O96) -> 0 | W96: 0 | X96: 1 | Y96: 0 | Z96: 0 | AA96: 1 | AB96: 0
A97: 50 | B97: 0 | C97: 0 | D97: 1 | E97: 207 | F97: =Source!U75 -> 615.2796 | G97: ТрудСтр | H97: Трудозатраты строителей | K97: 207 | L97: 21 | M97: 3 | O97: -1 | P97: =Source!DM75 -> 615.2796 | W97: 615.2796 | X97: 1 | Y97: 615.2796 | Z97: 615.2796 | AA97: 1 | AB97: 615.2796
A98: 50 | B98: 0 | C98: 0 | D98: 1 | E98: 208 | F98: =Source!V75 -> 0 | G98: ТрудМаш | H98: Трудозатраты машинистов | K98: 208 | L98: 22 | M98: 3 | O98: -1 | P98: =Source!DN75 -> 0 | W98: 0 | X98: 1 | Y98: 0 | Z98: 0 | AA98: 1 | AB98: 0
A99: 50 | B99: 0 | C99: 0 | D99: 1 | E99: 209 | F99: =ROUND(Source!W75,O99) -> 0 | G99: ТранспМат | H99: Транспорт материалов | K99: 209 | L99: 23 | M99: 3 | O99: 2 | P99: =ROUND(Source!DO75,O99) -> 0 | W99: 0 | X99: 1 | Y99: 0 | Z99: 0 | AA99: 1 | AB99: 0
A100: 50 | B100: 0 | C100: 0 | D100: 1 | E100: 233 | F100: =ROUND(Source!BD75,O100) -> 0 | G100: Перевозка | H100: Перевозка грузов | K100: 233 | L100: 24 | M100: 3 | O100: 2 | P100: =ROUND(Source!EV75,O100) -> 0 | W100: 0 | X100: 1 | Y100: 0 | Z100: 0 | AA100: 1 | AB100: 0
A101: 50 | B101: 0 | C101: 0 | D101: 1 | E101: 210 | F101: =ROUND(Source!X75,O101) -> 7675.44 | G101: НР | H101: Накладные расходы | K101: 210 | L101: 25 | M101: 3 | O101: 2 | P101: =ROUND(Source!DP75,O101) -> 422071.77 | W101: 7675.44 | X101: 1 | Y101: 7675.44 | Z101: 422071.77 | AA101: 1 | AB101: 422071.77
