Workbook

Sheet 02-01-22
A1: =Source!B1 -> Smeta.RU (495) 974-1589
J2: Форма № 4б
A3: Капитальный ремонт здания Государственного бюджетного общеобразовательного учреждения города Москвы «Школа № 236» по адресу: г. Москва, ул. Клязьминская, д. 7, к. 4. I этап | AP3: Капитальный ремонт здания Государственного бюджетного общеобразовательного учреждения города Москвы «Школа № 236» по адресу: г. Москва, ул. Клязьминская, д. 7, к. 4. I этап. 02-01-22 Мероприятия по обеспечению доступа инвалидов
A4: (наименование стройки и/или объекта)
A6: =CONCATENATE( "ЛОКАЛЬНАЯ СМЕТА № ",IF(Source!F20<>"Новая локальная смета", Source!F20, "")) -> ЛОКАЛЬНАЯ СМЕТА № 02-01-22
A8: =IF(Source!G20<>"Новая локальная смета", Source!G20, "") -> Мероприятия по обеспечению доступа инвалидов
A9: (наименование работ и затрат)
A11: =CONCATENATE( "Основание: чертежи № ", Source!J20) -> Основание: чертежи № 2024-00272-01-0-ОДИ.ВОР
I13: В базисном уровне цен | J13: В текущем уровне цен
E14: Сметная стоимость | I14: =I15+I16+I17+I19 -> 77.72 | J14: =J15+J16+J17+J19 -> 695.23 | K14: тыс.руб.
E15: Строительные работы | I15: =ROUND((Source!F480)/1000, 2) -> 42.72 | J15: =ROUND((Source!P480)/1000, 2) -> 516.2 | K15: тыс.руб.
E16: Работы по монтажу оборудования | I16: =ROUND((Source!F481)/1000, 2) -> 0 | J16: =ROUND((Source!P481)/1000, 2) -> 0 | K16: тыс.руб.
E17: Оборудование | I17: =ROUND((Source!F472)/1000, 2) -> 35 | J17: =ROUND((Source!P472)/1000, 2) -> 179.03 | K17: тыс.руб.
E18: В т.ч. оборудование не облагаемое НДС | I18: 19.80483 | J18: 62.665 | K18: тыс.руб.
E19: Прочие работы и затраты | I19: =ROUND((Source!F482+Source!F483)/1000, 2) -> 0 | J19: =ROUND((Source!P482+Source!P483)/1000, 2) -> 0 | K19: тыс.руб.
E20: Средства на оплату труда | I20: =(Source!F478+ Source!F477)/1000 -> 1.50994 | J20: =((Source!P478 + Source!P477)/1000) -> 83.03159 | K20: тыс.руб.
E21: Затраты труда | I21: =Source!F485 -> 97.728297 | K21: чел.-ч.
E22: Кроме того:
E23: Возврат материалов | I23: =SUM(Y29:Y450)/1000 -> 0 | J23: =SUM(Z29:Z450)/1000 -> 0 | K23: тыс.руб.
A25: Составлен(а) по ТСН-2001 с учетом Дополнения №: 80
A26: № и период сборника коэффициентов (индексов) пересчета: Коэффициенты к ТСН-2001 МГЭ Дополнение 80, ремонт №217/80 III квартал 2025 года и Коэффициенты к ТСН-2001.13-2 Дополнение 46 №62/46 III квартал 2025 года | AP26: № и период сборника коэффициентов (индексов) пересчета: Коэффициенты к ТСН-2001 МГЭ Дополнение 80, ремонт №217/80 III квартал 2025 года и Коэффициенты к ТСН-2001.13-2 Дополнение 46 №62/46 III квартал 2025 года
A27: № п/п | B27: Шифр расценки и коды ресурсов | C27: Наименование работ и затрат | D27: Ед. изм. | E27: Кол-во единиц | F27: Цена на ед. изм., руб. | G27: Попра- вочные коэффи- циенты | H27: Коэффи- циенты зимних удорожа- ний | I27: Всего в ценах на январь 2000 года, руб. | J27: Коэффи- циенты (индек- сы) пере- счета, нормы НР и СП | K27: ВСЕГО затрат в текущем уровне цен, руб.
A28: 1 | B28: 2 | C28: 3 | D28: 4 | E28: 5 | F28: 6 | G28: 7 | H28: 8 | I28: 9 | J28: 10 | K28: 11
A30: =CONCATENATE("Раздел: ",IF(Source!G24<>"Новый раздел", Source!G24, "")) -> Раздел: Оборудование санузла для МГН
A31: 1 | B31: 3.17-2-14 Поправка: Гл.12.Прил.8.п.8. 5_12.00.01.11.003 Поправка: Гл.6.Прил.2.2.п.2.2.6_06.00.01.07.001 | C31: Установка гарнитуры туалетной: поручней для ванн | D31: =Source!H28 -> 100 шт. | E31: =Source!I28 -> 0.05 | Q31: =Source!X28 -> 13.93 | R31: =Source!X29 -> 766.02 | S31: =Source!Y28 -> 7.8 | T31: =Source!Y29 -> 428.69 | U31: =ROUND((175/100)*ROUND(Source!R28, 2), 2) -> 0.07 | V31: =ROUND((0/100)*ROUND(Source!R29, 2), 2) -> 0 | AC31: 0
C32: ="Объем: "&Source!I28&"=(1+"&"1+"&"1+"&"1+"&"1)/"&"100" -> Объем: 0,05=(1+1+1+1+1)/100
C33: ЗП | F33: =Source!AO28 -> 188.72 | G33: =Source!DG28 -> *1,1)*1,15 | H33: =Source!AV29 -> 1.067 | I33: =Source!S28 -> 12.74 | J33: =IF(Source!BA29<> 0, Source!BA29, 1) -> 54.99 | K33: =Source!S29 -> 700.57
C34: ЭМ | F34: =Source!AM28 -> 7.54 | G34: =Source!DE28 -> *1,1)*1,25 | H34: =Source!AV29 -> 1.067 | I34: =Source!Q28 -> 0.55 | J34: =IF(Source!BB29<> 0, Source!BB29, 1) -> 12.07 | K34: =Source!Q29 -> 6.64
C35: в т.ч. ЗПМ | F35: =Source!AN28 -> 0.5 | G35: =Source!DF28 -> *1,1)*1,25 | H35: =Source!AV29 -> 1.067 | I35: =Source!R28 -> 0.04 | J35: =IF(Source!BS29<> 0, Source!BS29, 1) -> 54.99 | K35: =Source!R29 -> 2.2
C36: МР | F36: =Source!AL28 -> 5229.82 | G36: =Source!DD28 -> *1)*1 | H36: =Source!AW29 -> 1 | I36: =Source!P28 -> 261.49 | J36: =IF(Source!BC29<> 0, Source!BC29, 1) -> 0.75 | K36: =Source!P29 -> 196.12
C37: НР от ФОТ | D37: % | E37: =Source!BZ29 -> 109 | I37: =SUM(Q31:Q36) -> 13.93 | J37: =Source!AT29 -> 109 | K37: =SUM(R31:R36) -> 766.02
C38: СП от ФОТ | D38: % | E38: =Source!CA29 -> 61 | I38: =SUM(S31:S37) -> 7.8 | J38: =Source!AU29 -> 61 | K38: =SUM(T31:T37) -> 428.69
C39: ЗТР | D39: чел-ч | E39: =Source!AQ28 -> 16.89 | G39: =Source!DI28 -> *1,1)*1,15 | H39: =Source!AV29 -> 1.067 | I39: =Source!U28 -> 1.1398681
C40: ВСЕГО работ по позиции: | H40: =I33+I34+I36+I37+I38+0-0-0 -> 296.51 | J40: =K33+K34+K36+K37+K38+0-0-0 -> 2098.04
C41: ВСЕГО оборудование по позиции: | H41: =0+0 -> 0 | J41: =0+0 -> 0
C42: ВСЕГО по позиции: | H42: =I33+I34+I36+I37+I38+0 -> 296.51 | J42: =K33+K34+K36+K37+K38+0 -> 2098.04 | O42: =I33+I34+I36+I37+I38+0 -> 296.51 | P42: =K33+K34+K36+K37+K38+0 -> 2098.04
A44: 2 | B44: 3.17-2-13 Поправка: Гл.12.Прил.8.п.8. 5_12.00.01.11.003 Поправка: Гл.6.Прил.2.2.п.2.2.6_06.00.01.07.001 | C44: Установка гарнитуры туалетной: вешалок, подстаканников, дозаторов настенных и т.п./ крючки | D44: =Source!H30 -> 100 шт. | E44: =Source!I30 -> 0.02 | Q44: =Source!X30 -> 2.84 | R44: =Source!X31 -> 156.44 | S44: =Source!Y30 -> 1.59 | T44: =Source!Y31 -> 87.55 | U44: =ROUND((175/100)*ROUND(Source!R30, 2), 2) -> 0.05 | V44: =ROUND((0/100)*ROUND(Source!R31, 2), 2) -> 0 | AC44: 0
C45: ="Объем: "&Source!I30&"=2/"&"100" -> Объем: 0,02=2/100
C46: ЗП | F46: =Source!AO30 -> 95.59 | G46: =Source!DG30 -> *1,1)*1,15 | H46: =Source!AV31 -> 1.067 | I46: =Source!S30 -> 2.58 | J46: =IF(Source!BA31<> 0, Source!BA31, 1) -> 54.99 | K46: =Source!S31 -> 141.87
C47: ЭМ | F47: =Source!AM30 -> 8.97 | G47: =Source!DE30 -> *1,1)*1,25 | H47: =Source!AV31 -> 1.067 | I47: =Source!Q30 -> 0.26 | J47: =IF(Source!BB31<> 0, Source!BB31, 1) -> 14.34 | K47: =Source!Q31 -> 3.73
C48: в т.ч. ЗПМ | F48: =Source!AN30 -> 1.01 | G48: =Source!DF30 -> *1,1)*1,25 | H48: =Source!AV31 -> 1.067 | I48: =Source!R30 -> 0.03 | J48: =IF(Source!BS31<> 0, Source!BS31, 1) -> 54.99 | K48: =Source!R31 -> 1.65
C49: МР | F49: =Source!AL30 -> 2202.04 | G49: =Source!DD30 -> *1)*1 | H49: =Source!AW31 -> 1 | I49: =Source!P30 -> 44.04 | J49: =IF(Source!BC31<> 0, Source!BC31, 1) -> 0.75 | K49: =Source!P31 -> 33.03
C50: НР от ФОТ | D50: % | E50: =Source!BZ31 -> 109 | I50: =SUM(Q44:Q49) -> 2.84 | J50: =Source!AT31 -> 109 | K50: =SUM(R44:R49) -> 156.44
C51: СП от ФОТ | D51: % | E51: =Source!CA31 -> 61 | I51: =SUM(S44:S50) -> 1.59 | J51: =Source!AU31 -> 61 | K51: =SUM(T44:T50) -> 87.55
C52: ЗТР | D52: чел-ч | E52: =Source!AQ30 -> 8.58 | G52: =Source!DI30 -> *1,1)*1,15 | H52: =Source!AV31 -> 1.067 | I52: =Source!U30 -> 0.23161796
C53: ВСЕГО работ по позиции: | H53: =I46+I47+I49+I50+I51+0-0-0 -> 51.31 | J53: =K46+K47+K49+K50+K51+0-0-0 -> 422.62
C54: ВСЕГО оборудование по позиции: | H54: =0+0 -> 0 | J54: =0+0 -> 0
C55: ВСЕГО по позиции: | H55: =I46+I47+I49+I50+I51+0 -> 51.31 | J55: =K46+K47+K49+K50+K51+0 -> 422.62 | O55: =I46+I47+I49+I50+I51+0 -> 51.31 | P55: =K46+K47+K49+K50+K51+0 -> 422.62
A57: 3 | B57: 3.17-2-5 Поправка: О.П. п.3.4.30.в | C57: Установка гарнитуры туалетной полочек/зеркало | D57: =Source!H32 -> 1 ШТ. | E57: =Source!I32 -> 1 | Q57: =Source!X32 -> 11.7 | R57: =Source!X33 -> 643.14 | S57: =Source!Y32 -> 6.55 | T57: =Source!Y33 -> 359.92 | U57: =ROUND((175/100)*ROUND(Source!R32, 2), 2) -> 0 | V57: =ROUND((0/100)*ROUND(Source!R33, 2), 2) -> 0 | AC57: 0
C58: ЗП | F58: =Source!AO32 -> 7.95 | G58: =Source!DG32 -> *1,15)*1,1 | H58: =Source!AV33 -> 1.067 | I58: =Source!S32 -> 10.73 | J58: =IF(Source!BA33<> 0, Source!BA33, 1) -> 54.99 | K58: =Source!S33 -> 590.04
C59: МР | F59: =Source!AL32 -> 0.32 | G59: =Source!DD32 | H59: =Source!AW33 -> 1 | I59: =Source!P32 -> 0.32 | J59: =IF(Source!BC33<> 0, Source!BC33, 1) -> 5.91 | K59: =Source!P33 -> 1.89
C60: НР от ФОТ | D60: % | E60: =Source!BZ33 -> 109 | I60: =SUM(Q57:Q59) -> 11.7 | J60: =Source!AT33 -> 109 | K60: =SUM(R57:R59) -> 643.14
C61: СП от ФОТ | D61: % | E61: =Source!CA33 -> 61 | I61: =SUM(S57:S60) -> 6.55 | J61: =Source!AU33 -> 61 | K61: =SUM(T57:T60) -> 359.92
C62: ЗТР | D62: чел-ч | E62: =Source!AQ32 -> 0.63 | G62: =Source!DI32 -> *1,15)*1,1 | H62: =Source!AV33 -> 1.067 | I62: =Source!U32 -> 0.85034565
C63: ВСЕГО работ по позиции: | H63: =I58+I59+I60+I61+0-0-0 -> 29.3 | J63: =K58+K59+K60+K61+0-0-0 -> 1594.99
C64: ВСЕГО оборудование по позиции: | H64: =0+0 -> 0 | J64: =0+0 -> 0
C65: ВСЕГО по позиции: | H65: =I58+I59+I60+I61+0 -> 29.3 | J65: =K58+K59+K60+K61+0 -> 1594.99 | O65: =I58+I59+I60+I61+0 -> 29.3 | P65: =K58+K59+K60+K61+0 -> 1594.99
A67: 4 | B67: 3.17-2-13 Поправка: Гл.12.Прил.8.п.8. 5_12.00.01.11.003 Поправка: Гл.6.Прил.2.2.п.2.2.6_06.00.01.07.001 | C67: Установка гарнитуры туалетной: вешалок, подстаканников, дозаторов настенных и т.п./диспенсер | D67: =Source!H34 -> 100 шт. | E67: =Source!I34 -> 0.03 | Q67: =Source!X34 -> 4.26 | R67: =Source!X35 -> 234.36 | S67: =Source!Y34 -> 2.39 | T67: =Source!Y35 -> 131.16 | U67: =ROUND((175/100)*ROUND(Source!R34, 2), 2) -> 0.07 | V67: =ROUND((0/100)*ROUND(Source!R35, 2), 2) -> 0 | AC67: 0
C68: ="Объем: "&Source!I34&"=3/"&"100" -> Объем: 0,03=3/100
C69: ЗП | F69: =Source!AO34 -> 95.59 | G69: =Source!DG34 -> *1,1)*1,15 | H69: =Source!AV35 -> 1.067 | I69: =Source!S34 -> 3.87 | J69: =IF(Source!BA35<> 0, Source!BA35, 1) -> 54.99 | K69: =Source!S35 -> 212.81
C70: ЭМ | F70: =Source!AM34 -> 8.97 | G70: =Source!DE34 -> *1,1)*1,25 | H70: =Source!AV35 -> 1.067 | I70: =Source!Q34 -> 0.39 | J70: =IF(Source!BB35<> 0, Source!BB35, 1) -> 14.34 | K70: =Source!Q35 -> 5.59
C71: в т.ч. ЗПМ | F71: =Source!AN34 -> 1.01 | G71: =Source!DF34 -> *1,1)*1,25 | H71: =Source!AV35 -> 1.067 | I71: =Source!R34 -> 0.04 | J71: =IF(Source!BS35<> 0, Source!BS35, 1) -> 54.99 | K71: =Source!R35 -> 2.2
C72: МР | F72: =Source!AL34 -> 2202.04 | G72: =Source!DD34 -> *1)*1 | H72: =Source!AW35 -> 1 | I72: =Source!P34 -> 66.06 | J72: =IF(Source!BC35<> 0, Source!BC35, 1) -> 0.75 | K72: =Source!P35 -> 49.55
C73: НР от ФОТ | D73: % | E73: =Source!BZ35 -> 109 | I73: =SUM(Q67:Q72) -> 4.26 | J73: =Source!AT35 -> 109 | K73: =SUM(R67:R72) -> 234.36
C74: СП от ФОТ | D74: % | E74: =Source!CA35 -> 61 | I74: =SUM(S67:S73) -> 2.39 | J74: =Source!AU35 -> 61 | K74: =SUM(T67:T73) -> 131.16
C75: ЗТР | D75: чел-ч | E75: =Source!AQ34 -> 8.58 | G75: =Source!DI34 -> *1,1)*1,15 | H75: =Source!AV35 -> 1.067 | I75: =Source!U34 -> 0.34742694
C76: ВСЕГО работ по позиции: | H76: =I69+I70+I72+I73+I74+0-0-0 -> 76.97 | J76: =K69+K70+K72+K73+K74+0-0-0 -> 633.47
C77: ВСЕГО оборудование по позиции: | H77: =0+0 -> 0 | J77: =0+0 -> 0
C78: ВСЕГО по позиции: | H78: =I69+I70+I72+I73+I74+0 -> 76.97 | J78: =K69+K70+K72+K73+K74+0 -> 633.47 | O78: =I69+I70+I72+I73+I74+0 -> 76.97 | P78: =K69+K70+K72+K73+K74+0 -> 633.47
A80: 5 | B80: 3.17-2-13 Поправка: Гл.12.Прил.8.п.8. 5_12.00.01.11.003 Поправка: Гл.6.Прил.2.2.п.2.2.6_06.00.01.07.001 | C80: Установка гарнитуры туалетной: вешалок, подстаканников, дозаторов настенных и т.п./ туалетный ершик с креплением на стену | D80: =Source!H36 -> 100 шт. | E80: =Source!I36 -> 0.01 | Q80: =Source!X36 -> 1.42 | R80: =Source!X37 -> 77.92 | S80: =Source!Y36 -> 0.79 | T80: =Source!Y37 -> 43.61 | U80: =ROUND((175/100)*ROUND(Source!R36, 2), 2) -> 0.02 | V80: =ROUND((0/100)*ROUND(Source!R37, 2), 2) -> 0 | AC80: 0
C81: ="Объем: "&Source!I36&"=1/"&"100" -> Объем: 0,01=1/100
C82: ЗП | F82: =Source!AO36 -> 95.59 | G82: =Source!DG36 -> *1,1)*1,15 | H82: =Source!AV37 -> 1.067 | I82: =Source!S36 -> 1.29 | J82: =IF(Source!BA37<> 0, Source!BA37, 1) -> 54.99 | K82: =Source!S37 -> 70.94
C83: ЭМ | F83: =Source!AM36 -> 8.97 | G83: =Source!DE36 -> *1,1)*1,25 | H83: =Source!AV37 -> 1.067 | I83: =Source!Q36 -> 0.13 | J83: =IF(Source!BB37<> 0, Source!BB37, 1) -> 14.34 | K83: =Source!Q37 -> 1.86
C84: в т.ч. ЗПМ | F84: =Source!AN36 -> 1.01 | G84: =Source!DF36 -> *1,1)*1,25 | H84: =Source!AV37 -> 1.067 | I84: =Source!R36 -> 0.01 | J84: =IF(Source!BS37<> 0, Source!BS37, 1) -> 54.99 | K84: =Source!R37 -> 0.55
C85: МР | F85: =Source!AL36 -> 2202.04 | G85: =Source!DD36 -> *1)*1 | H85: =Source!AW37 -> 1 | I85: =Source!P36 -> 22.02 | J85: =IF(Source!BC37<> 0, Source!BC37, 1) -> 0.75 | K85: =Source!P37 -> 16.52
C86: НР от ФОТ | D86: % | E86: =Source!BZ37 -> 109 | I86: =SUM(Q80:Q85) -> 1.42 | J86: =Source!AT37 -> 109 | K86: =SUM(R80:R85) -> 77.92
C87: СП от ФОТ | D87: % | E87: =Source!CA37 -> 61 | I87: =SUM(S80:S86) -> 0.79 | J87: =Source!AU37 -> 61 | K87: =SUM(T80:T86) -> 43.61
C88: ЗТР | D88: чел-ч | E88: =Source!AQ36 -> 8.58 | G88: =Source!DI36 -> *1,1)*1,15 | H88: =Source!AV37 -> 1.067 | I88: =Source!U36 -> 0.11580898
C89: ВСЕГО работ по позиции: | H89: =I82+I83+I85+I86+I87+0-0-0 -> 25.65 | J89: =K82+K83+K85+K86+K87+0-0-0 -> 210.85
C90: ВСЕГО оборудование по позиции: | H90: =0+0 -> 0 | J90: =0+0 -> 0
C91: ВСЕГО по позиции: | H91: =I82+I83+I85+I86+I87+0 -> 25.65 | J91: =K82+K83+K85+K86+K87+0 -> 210.85 | O91: =I82+I83+I85+I86+I87+0 -> 25.65 | P91: =K82+K83+K85+K86+K87+0 -> 210.85
A94: =CONCATENATE("Итого по разделу: ",IF(Source!G39<>"Новый раздел", Source!G39, "")) -> Итого по разделу: Оборудование санузла для МГН | H94: =SUM(O30:O93) -> 479.74 | J94: =SUM(P30:P93) -> 4959.97
A95: Итого по ТСН-2001.16 | I95: =SUM(W30:W94) -> 0 | J95: =SUM(X30:X94) -> 0
A96: Итого возвратных сумм | I96: =SUM(Y30:Y95) -> 0 | J96: =SUM(Z30:Z95) -> 0
A98: =CONCATENATE("Раздел: ",IF(Source!G69<>"Новый раздел", Source!G69, "")) -> Раздел: Оборудование, не облагаемое НДС
A99: 6 | B99: =Source!F73 -> 13.3-11-72 | C99: ОБОРУДОВАНИЕ:_x000D_ Поручень реабилитационный откидной для установки около унитаза, габаритные размеры 700х700 мм. Материал сталь нержавеющая с полировкой, крепление к стене в трех точках, в комплекте: прокладки-амортизаторы резиновые, крепежные элементы | D99: =Source!H73 -> КОМПЛЕКТ | E99: =Source!I73 -> 1 | F99: =Source!AL73 -> 7974.05 | G99: =Source!DD73 | H99: =Source!AW74 -> 1 | I99: =Source!P73 -> 7974.05 | J99: =IF(Source!BC74<> 0, Source!BC74, 1) -> 2.58 | K99: =Source!P74 -> 20573.05 | Q99: =Source!X73 -> 0 | R99: =Source!X74 -> 0 | S99: =Source!Y73 -> 0 | T99: =Source!Y74 -> 0 | U99: =ROUND((175/100)*ROUND(Source!R73, 2), 2) -> 0 | V99: =ROUND((0/100)*ROUND(Source!R74, 2), 2) -> 0 | AC99: 5
C100: ВСЕГО по позиции: | H100: =I99+0 -> 7974.05 | J100: =K99+0 -> 20573.05 | O100: =I99+0 -> 7974.05 | P100: =K99+0 -> 20573.05
A102: 7 | B102: =Source!F75 -> 13.3-11-78 | C102: ОБОРУДОВАНИЕ:_x000D_ Поручень реабилитационный настенный, угловой, габаритные размеры 700х700 мм/ 600х600 мм | D102: =Source!H75 -> КОМПЛЕКТ | E102: =Source!I75 -> 2 | F102: =Source!AL75 -> 2960.3 | G102: =Source!DD75 | H102: =Source!AW76 -> 1 | I102: =Source!P75 -> 5920.6 | J102: =IF(Source!BC76<> 0, Source!BC76, 1) -> 3.5 | K102: =Source!P76 -> 20722.1 | Q102: =Source!X75 -> 0 | R102: =Source!X76 -> 0 | S102: =Source!Y75 -> 0 | T102: =Source!Y76 -> 0 | U102: =ROUND((175/100)*ROUND(Source!R75, 2), 2) -> 0 | V102: =ROUND((0/100)*ROUND(Source!R76, 2), 2) -> 0 | AC102: 5
C103: ="Объем: "&Source!I75&"=1+"&"1" -> Объем: 2=1+1
C104: ВСЕГО по позиции: | H104: =I102+0 -> 5920.6 | J104: =K102+0 -> 20722.1 | O104: =I102+0 -> 5920.6 | P104: =K102+0 -> 20722.1
A106: 8 | B106: =Source!F77 -> 13.3-11-77 | C106: ОБОРУДОВАНИЕ:_x000D_ Поручень реабилитационный настенный, габаритные размеры 1500х90 мм/ 1200х120 мм | D106: =Source!H77 -> КОМПЛЕКТ | E106: =Source!I77 -> 1 | F106: =Source!AL77 -> 2991.57 | G106: =Source!DD77 | H106: =Source!AW78 -> 1 | I106: =Source!P77 -> 2991.57 | J106: =IF(Source!BC78<> 0, Source!BC78, 1) -> 3.45 | K106: =Source!P78 -> 10320.92 | Q106: =Source!X77 -> 0 | R106: =Source!X78 -> 0 | S106: =Source!Y77 -> 0 | T106: =Source!Y78 -> 0 | U106: =ROUND((175/100)*ROUND(Source!R77, 2), 2) -> 0 | V106: =ROUND((0/100)*ROUND(Source!R78, 2), 2) -> 0 | AC106: 5
C107: ВСЕГО по позиции: | H107: =I106+0 -> 2991.57 | J107: =K106+0 -> 10320.92 | O107: =I106+0 -> 2991.57 | P107: =K106+0 -> 10320.92
A109: 9 | B109: =Source!F79 -> 13.3-11-80 | C109: ОБОРУДОВАНИЕ:_x000D_ Поручень реабилитационный односекционный, для установки около умывальника, габаритные размеры 700х260 мм/ настенно-напольный 850х196х600 мм | D109: =Source!H79 -> КОМПЛЕКТ | E109: =Source!I79 -> 1 | F109: =Source!AL79 -> 2345.31 | G109: =Source!DD79 | H109: =Source!AW80 -> 1 | I109: =Source!P79 -> 2345.31 | J109: =IF(Source!BC80<> 0, Source!BC80, 1) -> 3.89 | K109: =Source!P80 -> 9123.26 | Q109: =Source!X79 -> 0 | R109: =Source!X80 -> 0 | S109: =Source!Y79 -> 0 | T109: =Source!Y80 -> 0 | U109: =ROUND((175/100)*ROUND(Source!R79, 2), 2) -> 0 | V109: =ROUND((0/100)*ROUND(Source!R80, 2), 2) -> 0 | AC109: 5
C110: ВСЕГО по позиции: | H110: =I109+0 -> 2345.31 | J110: =K109+0 -> 9123.26 | O110: =I109+0 -> 2345.31 | P110: =K109+0 -> 9123.26
A112: 10 | B112: =Source!F81 -> 13.3-11-67 | C112: ОБОРУДОВАНИЕ:_x000D_ Крючок для подвески костылей, габаритные размеры 120х32 мм. Материал сталь нержавеющая с полировкой, крепление на стену, в комплекте: прокладки-амортизаторы резиновые, крепежные элементы | D112: =Source!H81 -> КОМПЛЕКТ | E112: =Source!I81 -> 1 | F112: =Source!AL81 -> 573.3 | G112: =Source!DD81 | H112: =Source!AW82 -> 1 | I112: =Source!P81 -> 573.3 | J112: =IF(Source!BC82<> 0, Source!BC82, 1) -> 3.36 | K112: =Source!P82 -> 1926.29 | Q112: =Source!X81 -> 0 | R112: =Source!X82 -> 0 | S112: =Source!Y81 -> 0 | T112: =Source!Y82 -> 0 | U112: =ROUND((175/100)*ROUND(Source!R81, 2), 2) -> 0 | V112: =ROUND((0/100)*ROUND(Source!R82, 2), 2) -> 0 | AC112: 5
C113: ВСЕГО по позиции: | H113: =I112+0 -> 573.3 | J113: =K112+0 -> 1926.29 | O113: =I112+0 -> 573.3 | P113: =K112+0 -> 1926.29
A116: =CONCATENATE("Итого по разделу: ",IF(Source!G84<>"Новый раздел", Source!G84, "")) -> Итого по разделу: Оборудование, не облагаемое НДС | H116: =SUM(O98:O115) -> 19804.83 | J116: =SUM(P98:P115) -> 62665.62
A117: Итого по ТСН-2001.16 | I117: =SUM(W98:W116) -> 0 | J117: =SUM(X98:X116) -> 0
A118: Итого возвратных сумм | I118: =SUM(Y98:Y117) -> 0 | J118: =SUM(Z98:Z117) -> 0
A120: =CONCATENATE("Раздел: ",IF(Source!G114<>"Новый раздел", Source!G114, "")) -> Раздел: Оборудование, облагаемое НДС
...

Sheet 02-01-22_1
A1: =Source!B1 -> Smeta.RU (495) 974-1589
E3: "УТВЕРЖДАЮ"
D5: ___________________________
D7: ___________________________
D9: " ___ " ___________ 20 ___ г.
B12: =CONCATENATE("Ведомость объемов работ ", IF(Source!AN15<>"", Source!AN15," ")) -> Ведомость объемов работ
B13: =CONCATENATE(Source!F12, " ", Source!G12) -> 02-01-22 02-01-22 Мероприятия по обеспечению доступа инвалидов
B14: =CONCATENATE(Source!F20, " ", Source!G20) -> 02-01-22 Мероприятия по обеспечению доступа инвалидов
A16: № п/п | B16: № в ЛСР | C16: Наименование работ и затрат | D16: Единица измерения | E16: Количество | F16: Ссылка на чертежи, спецификации | G16: Формула расчета, расчет объемов работ и расхода материалов | H16: Примечание
A17: 1 | B17: 2 | C17: 3 | D17: 4 | E17: 5 | F17: 6 | G17: 7 | H17: 8
A18: =CONCATENATE("Раздел: ", Source!G24) -> Раздел: Оборудование санузла для МГН
A19: 1 | B19: =Source!E28 -> 1 | C19: =Source!G28 -> Установка гарнитуры туалетной: поручней для ванн | D19: 100 шт. | E19: =Source!I28 -> 0.05 | F19: =Source!U24 | G19: ="=(1+"&"1+"&"1+"&"1+"&"1)/"&"100" -> =(1+1+1+1+1)/100
A20: 2 | B20: =Source!E30 -> 2 | C20: =Source!G30 -> Установка гарнитуры туалетной: вешалок, подстаканников, дозаторов настенных и т.п./ крючки | D20: 100 шт. | E20: =Source!I30 -> 0.02 | F20: =Source!U24 | G20: ="=2/"&"100" -> =2/100
A21: 3 | B21: =Source!E32 -> 3 | C21: =Source!G32 -> Установка гарнитуры туалетной полочек/зеркало | D21: 1 ШТ. | E21: =Source!I32 -> 1 | F21: =Source!U24 | G21: =Source!I32 -> 1
A22: 4 | B22: =Source!E34 -> 4 | C22: =Source!G34 -> Установка гарнитуры туалетной: вешалок, подстаканников, дозаторов настенных и т.п./диспенсер | D22: 100 шт. | E22: =Source!I34 -> 0.03 | F22: =Source!U24 | G22: ="=3/"&"100" -> =3/100
A23: 5 | B23: =Source!E36 -> 5 | C23: =Source!G36 -> Установка гарнитуры туалетной: вешалок, подстаканников, дозаторов настенных и т.п./ туалетный ершик с креплением на стену | D23: 100 шт. | E23: =Source!I36 -> 0.01 | F23: =Source!U24 | G23: ="=1/"&"100" -> =1/100
A24: =CONCATENATE("Раздел: ", Source!G69) -> Раздел: Оборудование, не облагаемое НДС
A25: 6 | B25: =Source!E73 -> 6 | C25: =Source!G73 -> Поручень реабилитационный откидной для установки около унитаза, габаритные размеры 700х700 мм. Материал сталь нержавеющая с полировкой, крепление к стене в трех точках, в комплекте: прокладки-амортизаторы резиновые, крепежные элементы | D25: КОМПЛЕКТ | E25: =Source!I73 -> 1 | F25: =Source!U69 | G25: =Source!I73 -> 1
A26: 7 | B26: =Source!E75 -> 7 | C26: =Source!G75 -> Поручень реабилитационный настенный, угловой, габаритные размеры 700х700 мм/ 600х600 мм | D26: КОМПЛЕКТ | E26: =Source!I75 -> 2 | F26: =Source!U69 | G26: ="=1+"&"1" -> =1+1
A27: 8 | B27: =Source!E77 -> 8 | C27: =Source!G77 -> Поручень реабилитационный настенный, габаритные размеры 1500х90 мм/ 1200х120 мм | D27: КОМПЛЕКТ | E27: =Source!I77 -> 1 | F27: =Source!U69 | G27: =Source!I77 -> 1
A28: 9 | B28: =Source!E79 -> 9 | C28: =Source!G79 -> Поручень реабилитационный односекционный, для установки около умывальника, габаритные размеры 700х260 мм/ настенно-напольный 850х196х600 мм | D28: КОМПЛЕКТ | E28: =Source!I79 -> 1 | F28: =Source!U69 | G28: =Source!I79 -> 1
A29: 10 | B29: =Source!E81 -> 10 | C29: =Source!G81 -> Крючок для подвески костылей, габаритные размеры 120х32 мм. Материал сталь нержавеющая с полировкой, крепление на стену, в комплекте: прокладки-амортизаторы резиновые, крепежные элементы | D29: КОМПЛЕКТ | E29: =Source!I81 -> 1 | F29: =Source!U69 | G29: =Source!I81 -> 1
A30: =CONCATENATE("Раздел: ", Source!G114) -> Раздел: Оборудование, облагаемое НДС
A31: 11 | B31: =Source!E118 -> 11 | C31: =Source!G118 -> Зеркало поворотное с ручкой управления, какркас из нержавеющей стали AISI 304, арт. 80035 | D31: шт. | E31: =Source!I118 -> 1 | F31: =Source!U114 | G31: =Source!I118 -> 1
A32: 12 | B32: =Source!E120 -> 12 | C32: =Source!G120 -> Корзина металлическая для мусора Tork Image Design B1, 50 л, без крышки, стальная, Артикул:460011 | D32: шт. | E32: =Source!I120 -> 1 | F32: =Source!U114 | G32: =Source!I120 -> 1
A33: 13 | B33: =Source!E122 -> 13 | C33: =Source!G122 -> Диспенсер настенный для бумажных полотенец, 325х245х109 мм, цвет: глянцевый хром, корпус из нержавеющей стали AISI 304 толщиной 1,2 мм. Типа 04046.В | D33: шт. | E33: =Source!I122 -> 1 | F33: =Source!U114 | G33: =Source!I122 -> 1
A34: 14 | B34: =Source!E124 -> 14 | C34: =Source!G124 -> Диспенсер для жидкого мыла сенсорный автоматический, 275х105х95 мм, цвет: глянцевый хром, корпус из нержавеющей стали AISI 304 толщиной 1,0 мм. Типа 03039.B | D34: шт. | E34: =Source!I124 -> 1 | F34: =Source!U114 | G34: =Source!I124 -> 1
A35: 15 | B35: =Source!E126 -> 15 | C35: =Source!G126 -> Диспенсер для туалетной бумаги, 260х112х260 мм, цвет: глянцевый хром, корпус изнержавеющей стали AISI 304 толщиной 1,0 мм. Типа 05006.B | D35: шт. | E35: =Source!I126 -> 1 | F35: =Source!U114 | G35: =Source!I126 -> 1
A36: 16 | B36: =Source!E128 -> 16 | C36: =Source!G128 -> Ершик туалетный с креплением на стену NIZA 16857.S | D36: шт. | E36: =Source!I128 -> 1 | F36: =Source!U114 | G36: =Source!I128 -> 1
A37: =CONCATENATE("Раздел: ", Source!G161) -> Раздел: Информационно-тактильные знаки
A38: 17 | B38: =Source!E165 -> 17 | C38: =Source!G165 -> Установка номерных табличек для этажа, подъезда/ Эвакуационный знак E01-01 (левосторонний), Эвакуационный знак E01-02 (правосторонний) | D38: 1 ШТ. | E38: =Source!I165 -> 6 | F38: =Source!U161 | G38: =Source!I165 -> 6
A39: 17.1 | B39: =Source!E167 -> 17,1 | C39: =Source!G167 -> Знак безопасности и эвакуационный указатель, из пластика с фотолюминесцентным покрытием, размер 200х200 мм | D39: шт. | E39: =Source!I167 -> 6 | F39: =Source!U161
A40: 18 | B40: =Source!E169 -> 18 | C40: =Source!G169 -> Установка номерных табличек для этажа, подъезда/Эвакуационный знак E02-01, "Направляющая стрелка" | D40: 1 ШТ. | E40: =Source!I169 -> 6 | F40: =Source!U161 | G40: =Source!I169 -> 6
A41: 18.1 | B41: =Source!E171 -> 18,1 | C41: =Source!G171 -> Знак безопасности и эвакуационный указатель, из пластика с фотолюминесцентным покрытием, размер 200х200 мм | D41: шт. | E41: =Source!I171 -> 6 | F41: =Source!U161
A42: 19 | B42: =Source!E173 -> 19 | C42: =Source!G173 -> Установка номерных табличек для этажа, подъезда/Эвакуационный знак E13 Направление к эвакуационному выходу по лестнице вниз (правосторонний), Е14 Направление к эвакуационному выходу по лестнице вниз (левосторонний) | D42: 1 ШТ. | E42: =Source!I173 -> 4 | F42: =Source!U161 | G42: =Source!I173 -> 4
A43: 19.1 | B43: =Source!E175 -> 19,1 | C43: =Source!G175 -> Знак безопасности и эвакуационный указатель, из пластика с фотолюминесцентным покрытием, размер 200х200 мм | D43: шт. | E43: =Source!I175 -> 4 | F43: =Source!U161
A44: 20 | B44: =Source!E177 -> 20 | C44: =Source!G177 -> Установка номерных табличек для этажа, подъезда/Эвакуационный знак E22,"Указатель выхода" | D44: 1 ШТ. | E44: =Source!I177 -> 21 | F44: =Source!U161 | G44: =Source!I177 -> 21
A45: 20.1 | B45: =Source!E179 -> 20,1 | C45: =Source!G179 -> Знак безопасности и эвакуационный указатель, из пластика с фотолюминесцентным покрытием, размер 200х200 мм | D45: шт. | E45: =Source!I179 -> 21 | F45: =Source!U161
A46: 21 | B46: =Source!E181 -> 21 | C46: =Source!G181 -> Установка номерных табличек для этажа, подъезда | D46: 1 ШТ. | E46: =Source!I181 -> 4 | F46: =Source!U161 | G46: =Source!I181 -> 4
A47: 21.1 | B47: =Source!E183 -> 21,1 | C47: =Source!G183 -> Тактильный знак СП 01, 150х150 мм "Доступность для инвалидов всех категорий" арт. 902-0-SP-18-150 | D47: шт. | E47: =Source!I183 -> 4 | F47: =Source!U161
A48: 22 | B48: =Source!E185 -> 22 | C48: =Source!G185 -> Установка номерных табличек для этажа, подъезда | D48: 1 ШТ. | E48: =Source!I185 -> 4 | F48: =Source!U161 | G48: =Source!I185 -> 4
A49: 22.1 | B49: =Source!E187 -> 22,1 | C49: =Source!G187 -> Тактильный знак СП 02, 150х150 мм "Доступность для инвалидов в креслах-колясках" арт. 902-0-SP-02-150 | D49: шт. | E49: =Source!I187 -> 4 | F49: =Source!U161
A50: 23 | B50: =Source!E189 -> 23 | C50: =Source!G189 -> Установка номерных табличек для этажа, подъезда | D50: 1 ШТ. | E50: =Source!I189 -> 4 | F50: =Source!U161 | G50: =Source!I189 -> 4
A51: 23.1 | B51: =Source!E191 -> 23,1 | C51: =Source!G191 -> Тактильный знак СП 07, 150х150 мм "Лифт для uнвалидов" арт. 902-0-SP-18-150 | D51: шт. | E51: =Source!I191 -> 4 | F51: =Source!U161
A52: 24 | B52: =Source!E193 -> 24 | C52: =Source!G193 -> Установка номерных табличек для этажа, подъезда | D52: 1 ШТ. | E52: =Source!I193 -> 1 | F52: =Source!U161 | G52: =Source!I193 -> 1
A53: 24.1 | B53: =Source!E195 -> 24,1 | C53: =Source!G195 -> Тактильный знак СП 09, 150х150 мм "Вход в помещение" арт. 902-0-SP-09-150 | D53: шт. | E53: =Source!I195 -> 1 | F53: =Source!U161
A54: 25 | B54: =Source!E197 -> 25 | C54: =Source!G197 -> Установка номерных табличек для этажа, подъезда | D54: 1 ШТ. | E54: =Source!I197 -> 3 | F54: =Source!U161 | G54: =Source!I197 -> 3
A55: 25.1 | B55: =Source!E199 -> 25,1 | C55: =Source!G199 -> Тактильный знак СП 10, 150х150 мм "Выход из помещения" арт. 902-0-SP-10-150 | D55: шт. | E55: =Source!I199 -> 3 | F55: =Source!U161
A56: 26 | B56: =Source!E201 -> 26 | C56: =Source!G201 -> Установка номерных табличек для этажа, подъезда | D56: 1 ШТ. | E56: =Source!I201 -> 2 | F56: =Source!U161 | G56: =Source!I201 -> 2
A57: 26.1 | B57: =Source!E203 -> 26,1 | C57: =Source!G203 -> Тактильный знак СП 11, 150х150 мм "Направление движения, поворот", арт. 902-0-SP-11-150 | D57: шт. | E57: =Source!I203 -> 2 | F57: =Source!U161
A58: 27 | B58: =Source!E205 -> 27 | C58: =Source!G205 -> Установка номерных табличек для этажа, подъезда | D58: 1 ШТ. | E58: =Source!I205 -> 1 | F58: =Source!U161 | G58: =Source!I205 -> 1
A59: 27.1 | B59: =Source!E207 -> 27,1 | C59: =Source!G207 -> Тактильный знак СП 12, 150х150 мм "Информация, место расположения мнемосхем" арт. 902-0-SP-12-150 | D59: шт. | E59: =Source!I207 -> 1 | F59: =Source!U161
A60: 28 | B60: =Source!E209 -> 28 | C60: =Source!G209 -> Установка номерных табличек для этажа, подъезда | D60: 1 ШТ. | E60: =Source!I209 -> 3 | F60: =Source!U161 | G60: =Source!I209 -> 3
A61: 28.1 | B61: =Source!E211 -> 28,1 | C61: =Source!G211 -> Тактильный знак СП 18, 150х150 мм "Туалет для инвалидов", арт.902-0-SP-18-150 | D61: шт. | E61: =Source!I211 -> 3 | F61: =Source!U161
A62: 29 | B62: =Source!E213 -> 29 | C62: =Source!G213 -> Установка номерных табличек для этажа, подъезда | D62: 1 ШТ. | E62: =Source!I213 -> 3 | F62: =Source!U161 | G62: =Source!I213 -> 3
A63: 29.1 | B63: =Source!E215 -> 29,1 | C63: =Source!G215 -> Тактильный знак СП 19, 150х150 мм "Туалет", арт.902-0-SP-18-150 | D63: шт. | E63: =Source!I215 -> 3 | F63: =Source!U161
A64: 30 | B64: =Source!E217 -> 30 | C64: =Source!G217 -> Установка номерных табличек для этажа, подъезда | D64: 1 ШТ. | E64: =Source!I217 -> 12 | F64: =Source!U161 | G64: =Source!I217 -> 12
A65: 30.1 | B65: =Source!E219 -> 30,1 | C65: =Source!G219 -> Тактильная табличка со шрифтом Брайля, 150х300мм"Название помещения", арт.903-2-PVC3-150x300 | D65: шт. | E65: =Source!I219 -> 12 | F65: =Source!U161
A66: 31 | B66: =Source!E221 -> 31 | C66: =Source!G221 -> Установка номерных табличек для этажа, подъезда | D66: 1 ШТ. | E66: =Source!I221 -> 1 | F66: =Source!U161 | G66: =Source!I221 -> 1
A67: 31.1 | B67: =Source!E223 -> 31,1 | C67: =Source!G223 -> Тактильный знак, 150х150 мм"Доступность для инвалидов по зрению", арт. 905-0-G-4-150N | D67: шт. | E67: =Source!I223 -> 1 | F67: =Source!U161
A68: 32 | B68: =Source!E225 -> 32 | C68: =Source!G225 -> Установка номерных табличек для этажа, подъезда | D68: 1 ШТ. | E68: =Source!I225 -> 1 | F68: =Source!U161 | G68: =Source!I225 -> 1
A69: 32.1 | B69: =Source!E227 -> 32,1 | C69: =Source!G227 -> Тактильный знак, 150х150 мм "Доступность для инвалидов по слуху" арт.905-0-G-3-150N | D69: шт. | E69: =Source!I227 -> 1 | F69: =Source!U161
A70: 33 | B70: =Source!E229 -> 33 | C70: =Source!G229 -> Установка номерных табличек для этажа, подъезда | D70: 1 ШТ. | E70: =Source!I229 -> 3 | F70: =Source!U161 | G70: =Source!I229 -> 3
A71: 33.1 | B71: =Source!E231 -> 33,1 | C71: =Source!G231 -> Тактильная мнемосхема санузла, полноцветная на стальной основе 321х411х2 мм, арт. 903-3-ST2-321X411 | D71: шт. | E71: =Source!I231 -> 3 | F71: =Source!U161
A72: 34 | B72: =Source!E233 -> 34 | C72: =Source!G233 -> Установка номерных табличек для этажа, подъезда | D72: 1 ШТ. | E72: =Source!I233 -> 1 | F72: =Source!U161 | G72: =Source!I233 -> 1
A73: 34.1 | B73: =Source!E235 -> 34,1 | C73: =Source!G235 -> Тактильная мнемосхема этажа, полноцветная на основе оргстекла, 470x610х8 мм, арт.906-3-ORG8-470x610 | D73: шт. | E73: =Source!I235 -> 1 | F73: =Source!U161
A74: =CONCATENATE("Раздел: ", Source!G268) -> Раздел: Полимерная краска, цвет желтый
A75: 35 | B75: =Source!E272 -> 35 | C75: =Source!G272 -> Защитно-декоративное покрытие бетонных и оштукатуренных внутренних поверхностей составом на основе акриловой и силановой эмульсий, стен | D75: 100 м2 | E75: =Source!I272 -> 0.64 | F75: =Source!U268 | G75: ="=64/"&"100" -> =64/100
A76: 35.1 | B76: =Source!E274 -> 35,1 | C76: =Source!G274 -> Краска дорожная, желтая, типа АК-505 | D76: т | E76: =Source!I274 -> 0.039552 | F76: =Source!U268
A77: =CONCATENATE("Раздел: ", Source!G307) -> Раздел: Наклейка- круг желтый
A78: 36 | B78: =Source!E311 -> 36 | C78: =Source!G311 -> Оклейка стен поливинилхлоридной декоративно-отделочной самоклеющейся пленкой по листовым материалам | D78: 100 м2 оклеиваемой поверхности | E78: =Source!I311 -> 0.1256 | F78: =Source!U307 | G78: ="=(3,14*"&"0,2*"&"0,2*"&"100)/"&"100" -> =(3,14*0,2*0,2*100)/100
A79: 36.1 | B79: =Source!E313 -> 36,1 | C79: =Source!G313 -> Наклейка, цвет жёлтый, ф20 см | D79: шт. | E79: =Source!I313 -> 100 | F79: =Source!U307
A80: =CONCATENATE("Раздел: ", Source!G346) -> Раздел: Тактильные предупреждающие наклейки на поручни
A81: 37 | B81: =Source!E350 -> 37 | C81: =Source!G350 -> Оклейка стен поливинилхлоридной декоративно-отделочной самоклеющейся пленкой по листовым материалам | D81: 100 м2 оклеиваемой поверхности | E81: =Source!I350 -> 0.025875 | F81: =Source!U346 | G81: ="=(0,23*"&"0,075*"&"3*"&"50)/"&"100" -> =(0,23*0,075*3*50)/100
A82: 37.1 | B82: =Source!E352 -> 37,1 | C82: =Source!G352 -> Тактильные предупреждающие наклейки на поручни 75 x 230мм/ (набор из 3х штук) | D82: шт. | E82: =Source!I352 -> 50 | F82: =Source!U346
A83: =CONCATENATE("Раздел: ", Source!G385) -> Раздел: Панно из алюминиевых тактильных индикаторов-конусов
A84: 38 | B84: =Source!E389 -> 38 | C84: =Source!G389 -> Укладка металлической накладной полосы (порожка) | D84: 100 м | E84: =Source!I389 -> 0.53165 | F84: =Source!U385 | G84: ="=(0,035*"&"1519)/"&"100" -> =(0,035*1519)/100
A85: 38.1 | B85: =Source!E391 -> 38,1 | C85: =Source!G391 -> Алюминиевый индикатор-конус Д=35 мм | D85: шт. | E85: =Source!I391 -> 1519 | F85: =Source!U385
A86: =CONCATENATE("Раздел: ", Source!G424) -> Раздел: Алюминиевая тактильная направляющая полоска
A87: 39 | B87: =Source!E428 -> 39 | C87: =Source!G428 -> Укладка металлической накладной полосы (порожка) | D87: 100 м | E87: =Source!I428 -> 0.14 | F87: =Source!U424 | G87: ="=(0,28*"&"50)/"&"100" -> =(0,28*50)/100
A88: 39.1 | B88: =Source!E430 -> 39,1 | C88: =Source!G430 -> Алюминиевая тактильная направляющая полоса 35х280 мм | D88: шт. | E88: =Source!I430 -> 50 | F88: =Source!U424
C91: Главный инженер проекта _________________ | D91: =IF(Source!X12<>"", Source!X12," ")
C93: Составил _________________ | D93: =IF(Source!AB12<>"", Source!AB12," ") -> Борисова Е.С.

Sheet Source
A1: 0 | B1: Smeta.RU (495) 974-1589 | D1: _PS_ | F1: 0 | G1: 0 | H1: 0 | I1: Smeta.RU | K1: 1 | L1: 74561 | M1: 10 | N1: 12 | O1: 0 | P1: 0 | Q1: 3
A4: 1 | B4: 1 | C4: -1 | G4: Капитальный ремонт здания Государственного бюджетного общеобразовательного учреждения города Москвы «Школа № 236» по адресу: г. Москва, ул. Клязьминская, д. 7, к. 4. I этап | EC4: 0
A12: 1 | B12: 534 | C12: 0 | D12: =ROW(A493) -> 493 | E12: 0 | F12: 02-01-22 | G12: 02-01-22 Мероприятия по обеспечению доступа инвалидов | I12: 0 | J12: 2024-00272-01-0-ОДИ.ВОР | K12: 0 | L12: 0 | M12: 4098 | O12: 0 | P12: 0 | Q12: 0 | R12: 0 | S12: 0 | T12: 1 | V12: 0 | AB12: Борисова Е.С. | BB12: 0 | BH12: Сметные нормы списания | BI12: Коды ОКП для ТСН-2001 МГЭ Дополнение 80 | BJ12: 1 | BK12: 1 | BL12: 0 | BM12: 0 | BN12: 1 | BO12: 0 | BP12: 6 | BQ12: 2 | BR12: 1 | BS12: 0 | BT12: 0 | BU12: 0 | BV12: 0 | BW12: 0 | BX12: 0 | BZ12: Типовой расчет для ТСН-2001 МГЭ, Дополнение 80, ремонт | CA12: Территориальные сметные нормативы для Москвы ТСН-2001 (МГЭ), дополнение 80 | CB12: Территориальные сметные нормативы для Москвы ТСН-2001 (МГЭ), дополнение 80 | CC12: Территориальные сметные нормативы для Москвы ТСН-2001 (МГЭ), дополнение 80 | CD12: Территориальные сметные нормативы для Москвы ТСН-2001 (МГЭ), дополнение 80 | CE12: Поправки для ТСН-2001 от 03.02.2026 г. доп.80 | CF12: 0 | CG12: 0 | CH12: 8 | CK12: 80 | CQ12: Территориальные сметные нормативы для Москвы (ТСН-2001) | CR12: ТЕР | CS12: 41660 | CT12: 1 | CU12: 80 | CY12: 0 | EC12: 0
A15: 15 | B15: 1
A18: 52 | B18: =B493 -> 534 | C18: =C493 -> 1 | D18: =D493 -> 12 | E18: =E493 -> 0 | F18: =F493 -> 02-01-22 | G18: =G493 -> 02-01-22 Мероприятия по обеспечению доступа инвалидов | O18: =O493 -> 75620.22 | P18: =P493 -> 74094.28 | Q18: =Q493 -> 17.6 | R18: =R493 -> 1.6 | S18: =S493 -> 1508.34 | T18: =T493 -> 0 | U18: =U493 -> 97.728297 | V18: =V493 -> 0 | ... GX18: =GX493 -> 0
A20: 3 | B20: 1 | D20: =ROW(A463) -> 463 | F20: 02-01-22 | G20: Мероприятия по обеспечению доступа инвалидов | I20: 0 | J20: 2024-00272-01-0-ОДИ.ВОР | K20: -1 | L20: 02-01-22 | S20: 0 | T20: 0 | V20: 2 | BX20: 0 | CF20: 0 | CG20: 0
A22: 52 | B22: =B463 -> 1 | C22: =C463 -> 3 | D22: =D463 -> 20 | E22: =E463 -> 0 | F22: =F463 -> 02-01-22 | G22: =G463 -> Мероприятия по обеспечению доступа инвалидов | O22: =O463 -> 75620.22 | P22: =P463 -> 74094.28 | Q22: =Q463 -> 17.6 | R22: =R463 -> 1.6 | S22: =S463 -> 1508.34 | T22: =T463 -> 0 | U22: =U463 -> 97.728297 | V22: =V463 -> 0 | ... GX22: =GX463 -> 0
A24: 4 | B24: 1 | D24: =ROW(A39) -> 39 | G24: Оборудование санузла для МГН | I24: 0 | K24: -1 | S24: 0 | T24: 0 | V24: 2 | BX24: 0 | CJ24: 0
A26: 52 | B26: =B39 -> 1 | C26: =C39 -> 4 | D26: =D39 -> 24 | E26: =E39 -> 0 | F26: =F39 | G26: =G39 -> Оборудование санузла для МГН | O26: =O39 -> 426.47 | P26: =P39 -> 393.93 | Q26: =Q39 -> 1.33 | R26: =R39 -> 0.12 | S26: =S39 -> 31.21 | T26: =T39 -> 0 | U26: =U39 -> 2.6850676 | V26: =V39 -> 0 | ... GX26: =GX39 -> 0
A28: 17 | B28: 1 | E28: 1 | F28: 3.17-2-14 | G28: Установка гарнитуры туалетной: поручней для ванн | H28: 100 шт. | I28: =ROUND((1+1+1+1+1)/100,9) -> 0.05 | J28: 0 | K28: =ROUND((1+1+1+1+1)/100,9) -> 0.05 | O28: =ROUND(CP28,2) -> 274.78 | P28: =ROUND((ROUND((AC28*AW28*I28),2)*BC28),2) -> 261.49 | Q28: =(ROUND((ROUND(((((ET28*1.1)*1.25))*AV28*I28),2)*BB28),2)+ROUND((ROUND(((AE28-(((EU28*1.1)*1.25)))*AV28*I28),2)*BS28),2)) -> 0.55 | R28: =(ROUND((ROUND(((((EU28*1.1)*1.25))*AV28*I28),2)*BS28),2)+ROUND((ROUND(((AE28-(((EU28*1.1)*1.25)))*AV28*I28),2)*BS28),2)) -> 0.04 | S28: =ROUND((ROUND((AF28*AV28*I28),2)*BA28),2) -> 12.74 | T28: =ROUND(CU28*I28,2) -> 0 | U28: =CV28*I28 -> 1.1398681 | V28: =CW28*I28 -> 0 | W28: =ROUND(CX28*I28,2) -> 0 | X28: =(ROUND((((S28+ROUND((ROUND(((((EU28*1.1)*1.25))*AV28*I28),2)*BS28),2))*AT28)/100),2)+ROUND(((ROUND((ROUND(((AE28-(((EU28*1.1)*1.25)))*AV28*I28),2)*BS28),2)*AT28)/100),2)) -> 13.93 | Y28: =(ROUND((((S28+ROUND((ROUND(((((EU28*1.1)*1.25))*AV28*I28),2)*BS28),2))*AU28)/100),2)+ROUND(((ROUND((ROUND(((AE28-(((EU28*1.1)*1.25)))*AV28*I28),2)*BS28),2)*AU28)/100),2)) -> 7.8 | AA28: 59499218 | AB28: =ROUND((AC28+AD28+AF28),6) -> 5478.9183 | AC28: =ROUND((((ES28*1)*1)),6) -> 5229.82 | AD28: =ROUND((((((ET28*1.1)*1.25))-(((EU28*1.1)*1.25)))+AE28),6) -> 10.3675 | AE28: =ROUND((((EU28*1.1)*1.25)),6) -> 0.6875 | AF28: =ROUND((((EV28*1.1)*1.15)),6) -> 238.7308 | AG28: =ROUND((AP28),6) -> 0 | AH28: =(((EW28*1.1)*1.15)) -> 21.36585 | AI28: =(((EX28*1.1)*1.25)) -> 0 | AJ28: =(AS28) -> 0 | AK28: 5426.08 | AL28: 5229.82 | AM28: 7.54 | AN28: 0.5 | AO28: 188.72 | AP28: 0 | AQ28: 16.89 | AR28: 0 | AS28: 0 | AT28: 109 | AU28: 61 | AV28: 1.067 | AW28: 1 | AZ28: 1 | BA28: 1 | BB28: 1 | BC28: 1 | BH28: 0 | BI28: 1 | BJ28: ТСН-2001.3 Доп. 80, Сб. 17, т. 2, поз. 14 | BM28: 22 | BN28: 0 | BO28: 3.17-2-14 | BP28: 1 | BQ28: 30 | BR28: 0 | BS28: 1 | BT28: 1 | BU28: 1 | BV28: 1 | BW28: 1 | BX28: 1 | BZ28: 109 | CA28: 61 | CE28: 1566 | CF28: 0 | CG28: 0 | CM28: 0 | CN28: Поправка: Гл.12.Прил.8.п.8. 5_12.00.01.11.003 Наименование: При наличии усложненных условий производства работ (стесненность, сложность складирования и транспортной логистики, наличие в зоне производства работ действующего технологического оборудования или движения технологического транспорта и т.п.) для объектов, расположенных за пределами территории круговой магистральной системы улиц "Садовое кольцо" и за пределами Третьего транспортного кольца города Москвы пунктов "а" и "б", но в пределах Московской кольцевой автомобильной дороги Поправка: Гл.6.Прил.2.2.п.2.2.6_06.00.01.07.001 Наименование: При выполнении при капитальном ремонте и реконструкции работ, аналогичных технологическим процессам, характерным для нового строительства, и отсутствующих в сборниках на ремонтно-строительные работы ТСН-2001.6 | CO28: 0 | CP28: =(P28+Q28+S28) -> 274.78 | CQ28: =ROUND((ROUND((AC28*AW28*1),2)*BC28),2) -> 5229.82 | CR28: =(ROUND((ROUND(((((ET28*1.1)*1.25))*AV28*1),2)*BB28),2)+ROUND((ROUND(((AE28-(((EU28*1.1)*1.25)))*AV28*1),2)*BS28),2)) -> 11.06 | CS28: =(ROUND((ROUND(((((EU28*1.1)*1.25))*AV28*1),2)*BS28),2)+ROUND((ROUND(((AE28-(((EU28*1.1)*1.25)))*AV28*1),2)*BS28),2)) -> 0.73 | CT28: =ROUND((ROUND((AF28*AV28*1),2)*BA28),2) -> 254.73 | CU28: =AG28 -> 0 | CV28: =(AH28*AV28) -> 22.797362 | CW28: =AI28 -> 0 | CX28: =AJ28 -> 0 | CY28: =(ROUND((((S28+ROUND((ROUND(((((EU28*1.1)*1.25))*AV28*1),2)*BS28),2))*AT28)/100),2)+ROUND(((ROUND((ROUND(((AE28-(((EU28*1.1)*1.25)))*AV28*1),2)*BS28),2)*AT28)/100),2)) -> 14.68 | CZ28: =(ROUND((((S28+ROUND((ROUND(((((EU28*1.1)*1.25))*AV28*1),2)*BS28),2))*AU28)/100),2)+ROUND(((ROUND((ROUND(((AE28-(((EU28*1.1)*1.25)))*AV28*1),2)*BS28),2)*AU28)/100),2)) -> 8.22 | DB28: 1 | DD28: *1)*1 | DE28: *1,1)*1,25 | DF28: *1,1)*1,25 | DG28: *1,1)*1,15 | DI28: *1,1)*1,15 | DJ28: *1,1)*1,25 | DN28: 0 | DO28: 0 | DP28: 1 | DQ28: 1 | DU28: 1010 | DV28: 100 шт. | DW28: 100 шт. | DX28: 100 | EE28: 59298928 | EF28: 30 | EG28: Строительные работы | EH28: 0 | EJ28: 1 | EK28: 22 | EL28: ТСН-2001.3-17. Водопровод и канализация - внутренние устройства | EM28: ТСН-2001.3-17-1 | EO28: Поправка: Гл.12.Прил.8.п.8. 5_12.00.01.11.003 Поправка: Гл.6.Прил.2.2.п.2.2.6_06.00.01.07.001 | EQ28: 0 | ER28: 5426.08 | ES28: 5229.82 | ET28: 7.54 | EU28: 0.5 | EV28: 188.72 | EW28: 16.89 | EX28: 0 | EY28: 0 | FQ28: 0 | FR28: 0 | FS28: 0 | FX28: 109 | FY28: 61 | GD28: 1 | GF28: -73133009 | GG28: 2 | GH28: 1 | GI28: 2 | GJ28: 0 | GK28: 0 | GL28: =ROUND(IF(AND(BH28=3,BI28=3,FS28<>0),P28,0),2) -> 0 | GM28: =ROUND(O28+X28+Y28,2)+GX28 -> 296.51 | GN28: =IF(OR(BI28=0,BI28=1),GM28-GX28,0) -> 296.51 | GO28: =IF(BI28=2,GM28-GX28,0) -> 0 | GP28: =IF(BI28=4,GM28-GX28,0) -> 0 | GR28: 0 | GS28: 3 | GT28: 0 | GV28: =ROUND((GT28),6) -> 0 | GW28: 1 | GX28: =ROUND(HC28*I28,2) -> 0 | HA28: 0 | HB28: 0 | HC28: =GV28*GW28 -> 0 | HS28: 0 | IK28: 0
A29: 17 | B29: 1 | E29: 1 | F29: 3.17-2-14 | G29: Установка гарнитуры туалетной: поручней для ванн | H29: 100 шт. | I29: =ROUND((1+1+1+1+1)/100,9) -> 0.05 | J29: 0 | K29: =ROUND((1+1+1+1+1)/100,9) -> 0.05 | O29: =ROUND(CP29,2) -> 903.33 | P29: =ROUND((ROUND((AC29*AW29*I29),2)*BC29),2) -> 196.12 | Q29: =(ROUND((ROUND(((((ET29*1.1)*1.25))*AV29*I29),2)*BB29),2)+ROUND((ROUND(((AE29-(((EU29*1.1)*1.25)))*AV29*I29),2)*BS29),2)) -> 6.64 | R29: =(ROUND((ROUND(((((EU29*1.1)*1.25))*AV29*I29),2)*BS29),2)+ROUND((ROUND(((AE29-(((EU29*1.1)*1.25)))*AV29*I29),2)*BS29),2)) -> 2.2 | S29: =ROUND((ROUND((AF29*AV29*I29),2)*BA29),2) -> 700.57 | T29: =ROUND(CU29*I29,2) -> 0 | U29: =CV29*I29 -> 1.1398681 | V29: =CW29*I29 -> 0 | W29: =ROUND(CX29*I29,2) -> 0 | X29: =(ROUND((((S29+ROUND((ROUND(((((EU29*1.1)*1.25))*AV29*I29),2)*BS29),2))*AT29)/100),2)+ROUND(((ROUND((ROUND(((AE29-(((EU29*1.1)*1.25)))*AV29*I29),2)*BS29),2)*AT29)/100),2)) -> 766.02 | Y29: =(ROUND((((S29+ROUND((ROUND(((((EU29*1.1)*1.25))*AV29*I29),2)*BS29),2))*AU29)/100),2)+ROUND(((ROUND((ROUND(((AE29-(((EU29*1.1)*1.25)))*AV29*I29),2)*BS29),2)*AU29)/100),2)) -> 428.69 | AA29: 59499215 | AB29: =ROUND((AC29+AD29+AF29),6) -> 5478.9183 | AC29: =ROUND((((ES29*1)*1)),6) -> 5229.82 | AD29: =ROUND((((((ET29*1.1)*1.25))-(((EU29*1.1)*1.25)))+AE29),6) -> 10.3675 | AE29: =ROUND((((EU29*1.1)*1.25)),6) -> 0.6875 | AF29: =ROUND((((EV29*1.1)*1.15)),6) -> 238.7308 | AG29: =ROUND((AP29),6) -> 0 | AH29: =(((EW29*1.1)*1.15)) -> 21.36585 | AI29: =(((EX29*1.1)*1.25)) -> 0 | AJ29: =(AS29) -> 0 | AK29: 5426.08 | AL29: 5229.82 | AM29: 7.54 | AN29: 0.5 | AO29: 188.72 | AP29: 0 | AQ29: 16.89 | AR29: 0 | AS29: 0 | AT29: 109 | AU29: 61 | AV29: 1.067 | AW29: 1 | AZ29: 1 | BA29: 54.99 | BB29: 12.07 | BC29: 0.75 | BH29: 0 | BI29: 1 | BJ29: ТСН-2001.3 Доп. 80, Сб. 17, т. 2, поз. 14 | BM29: 22 | BN29: 0 | BO29: 3.17-2-14 | BP29: 1 | BQ29: 30 | BR29: 0 | BS29: 54.99 | BT29: 1 | BU29: 1 | BV29: 1 | BW29: 1 | BX29: 1 | BZ29: 109 | CA29: 61 | CE29: 1566 | CF29: 0 | CG29: 0 | CM29: 0 | CN29: Поправка: Гл.12.Прил.8.п.8. 5_12.00.01.11.003 Наименование: При наличии усложненных условий производства работ (стесненность, сложность складирования и транспортной логистики, наличие в зоне производства работ действующего технологического оборудования или движения технологического транспорта и т.п.) для объектов, расположенных за пределами территории круговой магистральной системы улиц "Садовое кольцо" и за пределами Третьего транспортного кольца города Москвы пунктов "а" и "б", но в пределах Московской кольцевой автомобильной дороги Поправка: Гл.6.Прил.2.2.п.2.2.6_06.00.01.07.001 Наименование: При выполнении при капитальном ремонте и реконструкции работ, аналогичных технологическим процессам, характерным для нового строительства, и отсутствующих в сборниках на ремонтно-строительные работы ТСН-2001.6 | CO29: 0 | CP29: =(P29+Q29+S29) -> 903.33 | CQ29: =ROUND((ROUND((AC29*AW29*1),2)*BC29),2) -> 3922.37 | CR29: =(ROUND((ROUND(((((ET29*1.1)*1.25))*AV29*1),2)*BB29),2)+ROUND((ROUND(((AE29-(((EU29*1.1)*1.25)))*AV29*1),2)*BS29),2)) -> 133.49 | CS29: =(ROUND((ROUND(((((EU29*1.1)*1.25))*AV29*1),2)*BS29),2)+ROUND((ROUND(((AE29-(((EU29*1.1)*1.25)))*AV29*1),2)*BS29),2)) -> 40.14 | CT29: =ROUND((ROUND((AF29*AV29*1),2)*BA29),2) -> 14007.6 | CU29: =AG29 -> 0 | CV29: =(AH29*AV29) -> 22.797362 | CW29: =AI29 -> 0 | CX29: =AJ29 -> 0 | CY29: =(ROUND((((S29+ROUND((ROUND(((((EU29*1.1)*1.25))*AV29*1),2)*BS29),2))*AT29)/100),2)+ROUND(((ROUND((ROUND(((AE29-(((EU29*1.1)*1.25)))*AV29*1),2)*BS29),2)*AT29)/100),2)) -> 807.37 | CZ29: =(ROUND((((S29+ROUND((ROUND(((((EU29*1.1)*1.25))*AV29*1),2)*BS29),2))*AU29)/100),2)+ROUND(((ROUND((ROUND(((AE29-(((EU29*1.1)*1.25)))*AV29*1),2)*BS29),2)*AU29)/100),2)) -> 451.83 | DB29: 3 | DD29: *1)*1 | DE29: *1,1)*1,25 | DF29: *1,1)*1,25 | DG29: *1,1)*1,15 | DI29: *1,1)*1,15 | DJ29: *1,1)*1,25 | DN29: 0 | DO29: 0 | DP29: 1 | DQ29: 1 | DU29: 1010 | DV29: 100 шт. | DW29: 100 шт. | DX29: 100 | EE29: 59298928 | EF29: 30 | EG29: Строительные работы | EH29: 0 | EJ29: 1 | EK29: 22 | EL29: ТСН-2001.3-17. Водопровод и канализация - внутренние устройства | EM29: ТСН-2001.3-17-1 | EO29: Поправка: Гл.12.Прил.8.п.8. 5_12.00.01.11.003 Поправка: Гл.6.Прил.2.2.п.2.2.6_06.00.01.07.001 | EQ29: 0 | ER29: 5426.08 | ES29: 5229.82 | ET29: 7.54 | EU29: 0.5 | EV29: 188.72 | EW29: 16.89 | EX29: 0 | EY29: 0 | FQ29: 0 | FR29: 0 | FS29: 0 | FX29: 109 | FY29: 61 | GD29: 1 | GF29: -73133009 | GG29: 2 | GH29: 1 | GI29: 2 | GJ29: 0 | GK29: 0 | GL29: =ROUND(IF(AND(BH29=3,BI29=3,FS29<>0),P29,0),2) -> 0 | GM29: =ROUND(O29+X29+Y29,2)+GX29 -> 2098.04 | GN29: =IF(OR(BI29=0,BI29=1),GM29-GX29,0) -> 2098.04 | GO29: =IF(BI29=2,GM29-GX29,0) -> 0 | GP29: =IF(BI29=4,GM29-GX29,0) -> 0 | GR29: 0 | GS29: 3 | GT29: 0 | GV29: =ROUND((GT29),6) -> 0 | GW29: 1 | GX29: =ROUND(HC29*I29,2) -> 0 | HA29: 0 | HB29: 0 | HC29: =GV29*GW29 -> 0 | HS29: 0 | IK29: 0
A30: 17 | B30: 1 | E30: 2 | F30: 3.17-2-13 | G30: Установка гарнитуры туалетной: вешалок, подстаканников, дозаторов настенных и т.п./ крючки | H30: 100 шт. | I30: =ROUND(2/100,9) -> 0.02 | J30: 0 | K30: =ROUND(2/100,9) -> 0.02 | O30: =ROUND(CP30,2) -> 46.88 | P30: =ROUND((ROUND((AC30*AW30*I30),2)*BC30),2) -> 44.04 | Q30: =(ROUND((ROUND(((((ET30*1.1)*1.25))*AV30*I30),2)*BB30),2)+ROUND((ROUND(((AE30-(((EU30*1.1)*1.25)))*AV30*I30),2)*BS30),2)) -> 0.26 | R30: =(ROUND((ROUND(((((EU30*1.1)*1.25))*AV30*I30),2)*BS30),2)+ROUND((ROUND(((AE30-(((EU30*1.1)*1.25)))*AV30*I30),2)*BS30),2)) -> 0.03 | S30: =ROUND((ROUND((AF30*AV30*I30),2)*BA30),2) -> 2.58 | T30: =ROUND(CU30*I30,2) -> 0 | U30: =CV30*I30 -> 0.23161796 | V30: =CW30*I30 -> 0 | W30: =ROUND(CX30*I30,2) -> 0 | X30: =(ROUND((((S30+ROUND((ROUND(((((EU30*1.1)*1.25))*AV30*I30),2)*BS30),2))*AT30)/100),2)+ROUND(((ROUND((ROUND(((AE30-(((EU30*1.1)*1.25)))*AV30*I30),2)*BS30),2)*AT30)/100),2)) -> 2.84 | Y30: =(ROUND((((S30+ROUND((ROUND(((((EU30*1.1)*1.25))*AV30*I30),2)*BS30),2))*AU30)/100),2)+ROUND(((ROUND((ROUND(((AE30-(((EU30*1.1)*1.25)))*AV30*I30),2)*BS30),2)*AU30)/100),2)) -> 1.59 | AA30: 59499218 | AB30: =ROUND((AC30+AD30+AF30),6) -> 2335.2951 | AC30: =ROUND((((ES30*1)*1)),6) -> 2202.04 | AD30: =ROUND((((((ET30*1.1)*1.25))-(((EU30*1.1)*1.25)))+AE30),6) -> 12.33375 | AE30: =ROUND((((EU30*1.1)*1.25)),6) -> 1.38875 | AF30: =ROUND((((EV30*1.1)*1.15)),6) -> 120.92135 | AG30: =ROUND((AP30),6) -> 0 | AH30: =(((EW30*1.1)*1.15)) -> 10.8537 | AI30: =(((EX30*1.1)*1.25)) -> 0 | AJ30: =(AS30) -> 0 | AK30: 2306.6 | AL30: 2202.04 | AM30: 8.97 | AN30: 1.01 | AO30: 95.59 | AP30: 0 | AQ30: 8.58 | AR30: 0 | AS30: 0 | AT30: 109 | AU30: 61 | AV30: 1.067 | AW30: 1 | AZ30: 1 | BA30: 1 | BB30: 1 | BC30: 1 | BH30: 0 | BI30: 1 | BJ30: ТСН-2001.3 Доп. 80, Сб. 17, т. 2, поз. 13 | BM30: 22 | BN30: 0 | BO30: 3.17-2-13 | BP30: 1 | BQ30: 30 | BR30: 0 | BS30: 1 | BT30: 1 | BU30: 1 | BV30: 1 | BW30: 1 | BX30: 1 | BZ30: 109 | CA30: 61 | CE30: 1566 | CF30: 0 | CG30: 0 | CM30: 0 | CN30: Поправка: Гл.12.Прил.8.п.8. 5_12.00.01.11.003 Наименование: При наличии усложненных условий производства работ (стесненность, сложность складирования и транспортной логистики, наличие в зоне производства работ действующего технологического оборудования или движения технологического транспорта и т.п.) для объектов, расположенных за пределами территории круговой магистральной системы улиц "Садовое кольцо" и за пределами Третьего транспортного кольца города Москвы пунктов "а" и "б", но в пределах Московской кольцевой автомобильной дороги Поправка: Гл.6.Прил.2.2.п.2.2.6_06.00.01.07.001 Наименование: При выполнении при капитальном ремонте и реконструкции работ, аналогичных технологическим процессам, характерным для нового строительства, и отсутствующих в сборниках на ремонтно-строительные работы ТСН-2001.6 | CO30: 0 | CP30: =(P30+Q30+S30) -> 46.88 | CQ30: =ROUND((ROUND((AC30*AW30*1),2)*BC30),2) -> 2202.04 | CR30: =(ROUND((ROUND(((((ET30*1.1)*1.25))*AV30*1),2)*BB30),2)+ROUND((ROUND(((AE30-(((EU30*1.1)*1.25)))*AV30*1),2)*BS30),2)) -> 13.16 | CS30: =(ROUND((ROUND(((((EU30*1.1)*1.25))*AV30*1),2)*BS30),2)+ROUND((ROUND(((AE30-(((EU30*1.1)*1.25)))*AV30*1),2)*BS30),2)) -> 1.48 | CT30: =ROUND((ROUND((AF30*AV30*1),2)*BA30),2) -> 129.02 | CU30: =AG30 -> 0 | CV30: =(AH30*AV30) -> 11.580898 | CW30: =AI30 -> 0 | CX30: =AJ30 -> 0 | CY30: =(ROUND((((S30+ROUND((ROUND(((((EU30*1.1)*1.25))*AV30*1),2)*BS30),2))*AT30)/100),2)+ROUND(((ROUND((ROUND(((AE30-(((EU30*1.1)*1.25)))*AV30*1),2)*BS30),2)*AT30)/100),2)) -> 4.43 | CZ30: =(ROUND((((S30+ROUND((ROUND(((((EU30*1.1)*1.25))*AV30*1),2)*BS30),2))*AU30)/100),2)+ROUND(((ROUND((ROUND(((AE30-(((EU30*1.1)*1.25)))*AV30*1),2)*BS30),2)*AU30)/100),2)) -> 2.48 | DB30: 5 | DD30: *1)*1 | DE30: *1,1)*1,25 | DF30: *1,1)*1,25 | DG30: *1,1)*1,15 | DI30: *1,1)*1,15 | DJ30: *1,1)*1,25 | DN30: 0 | DO30: 0 | DP30: 1 | DQ30: 1 | DU30: 1010 | DV30: 100 шт. | DW30: 100 шт. | DX30: 100 | EE30: 59298928 | EF30: 30 | EG30: Строительные работы | EH30: 0 | EJ30: 1 | EK30: 22 | EL30: ТСН-2001.3-17. Водопровод и канализация - внутренние устройства | EM30: ТСН-2001.3-17-1 | EO30: Поправка: Гл.12.Прил.8.п.8. 5_12.00.01.11.003 Поправка: Гл.6.Прил.2.2.п.2.2.6_06.00.01.07.001 | EQ30: 0 | ER30: 2306.6 | ES30: 2202.04 | ET30: 8.97 | EU30: 1.01 | EV30: 95.59 | EW30: 8.58 | EX30: 0 | EY30: 0 | FQ30: 0 | FR30: 0 | FS30: 0 | FX30: 109 | FY30: 61 | GD30: 1 | GF30: -488901103 | GG30: 2 | GH30: 1 | GI30: 2 | GJ30: 0 | GK30: 0 | GL30: =ROUND(IF(AND(BH30=3,BI30=3,FS30<>0),P30,0),2) -> 0 | GM30: =ROUND(O30+X30+Y30,2)+GX30 -> 51.31 | GN30: =IF(OR(BI30=0,BI30=1),GM30-GX30,0) -> 51.31 | GO30: =IF(BI30=2,GM30-GX30,0) -> 0 | GP30: =IF(BI30=4,GM30-GX30,0) -> 0 | GR30: 0 | GS30: 3 | GT30: 0 | GV30: =ROUND((GT30),6) -> 0 | GW30: 1 | GX30: =ROUND(HC30*I30,2) -> 0 | HA30: 0 | HB30: 0 | HC30: =GV30*GW30 -> 0 | HS30: 0 | IK30: 0
A31: 17 | B31: 1 | E31: 2 | F31: 3.17-2-13 | G31: Установка гарнитуры туалетной: вешалок, подстаканников, дозаторов настенных и т.п./ крючки | H31: 100 шт. | I31: =ROUND(2/100,9) -> 0.02 | J31: 0 | K31: =ROUND(2/100,9) -> 0.02 | O31: =ROUND(CP31,2) -> 178.63 | P31: =ROUND((ROUND((AC31*AW31*I31),2)*BC31),2) -> 33.03 | Q31: =(ROUND((ROUND(((((ET31*1.1)*1.25))*AV31*I31),2)*BB31),2)+ROUND((ROUND(((AE31-(((EU31*1.1)*1.25)))*AV31*I31),2)*BS31),2)) -> 3.73 | R31: =(ROUND((ROUND(((((EU31*1.1)*1.25))*AV31*I31),2)*BS31),2)+ROUND((ROUND(((AE31-(((EU31*1.1)*1.25)))*AV31*I31),2)*BS31),2)) -> 1.65 | S31: =ROUND((ROUND((AF31*AV31*I31),2)*BA31),2) -> 141.87 | T31: =ROUND(CU31*I31,2) -> 0 | U31: =CV31*I31 -> 0.23161796 | V31: =CW31*I31 -> 0 | W31: =ROUND(CX31*I31,2) -> 0 | X31: =(ROUND((((S31+ROUND((ROUND(((((EU31*1.1)*1.25))*AV31*I31),2)*BS31),2))*AT31)/100),2)+ROUND(((ROUND((ROUND(((AE31-(((EU31*1.1)*1.25)))*AV31*I31),2)*BS31),2)*AT31)/100),2)) -> 156.44 | Y31: =(ROUND((((S31+ROUND((ROUND(((((EU31*1.1)*1.25))*AV31*I31),2)*BS31),2))*AU31)/100),2)+ROUND(((ROUND((ROUND(((AE31-(((EU31*1.1)*1.25)))*AV31*I31),2)*BS31),2)*AU31)/100),2)) -> 87.55 | AA31: 59499215 | AB31: =ROUND((AC31+AD31+AF31),6) -> 2335.2951 | AC31: =ROUND((((ES31*1)*1)),6) -> 2202.04 | AD31: =ROUND((((((ET31*1.1)*1.25))-(((EU31*1.1)*1.25)))+AE31),6) -> 12.33375 | AE31: =ROUND((((EU31*1.1)*1.25)),6) -> 1.38875 | AF31: =ROUND((((EV31*1.1)*1.15)),6) -> 120.92135 | AG31: =ROUND((AP31),6) -> 0 | AH31: =(((EW31*1.1)*1.15)) -> 10.8537 | AI31: =(((EX31*1.1)*1.25)) -> 0 | AJ31: =(AS31) -> 0 | AK31: 2306.6 | AL31: 2202.04 | AM31: 8.97 | AN31: 1.01 | AO31: 95.59 | AP31: 0 | AQ31: 8.58 | AR31: 0 | AS31: 0 | AT31: 109 | AU31: 61 | AV31: 1.067 | AW31: 1 | AZ31: 1 | BA31: 54.99 | BB31: 14.34 | BC31: 0.75 | BH31: 0 | BI31: 1 | BJ31: ТСН-2001.3 Доп. 80, Сб. 17, т. 2, поз. 13 | BM31: 22 | BN31: 0 | BO31: 3.17-2-13 | BP31: 1 | BQ31: 30 | BR31: 0 | BS31: 54.99 | BT31: 1 | BU31: 1 | BV31: 1 | BW31: 1 | BX31: 1 | BZ31: 109 | CA31: 61 | CE31: 1566 | CF31: 0 | CG31: 0 | CM31: 0 | CN31: Поправка: Гл.12.Прил.8.п.8. 5_12.00.01.11.003 Наименование: При наличии усложненных условий производства работ (стесненность, сложность складирования и транспортной логистики, наличие в зоне производства работ действующего технологического оборудования или движения технологического транспорта и т.п.) для объектов, расположенных за пределами территории круговой магистральной системы улиц "Садовое кольцо" и за пределами Третьего транспортного кольца города Москвы пунктов "а" и "б", но в пределах Московской кольцевой автомобильной дороги Поправка: Гл.6.Прил.2.2.п.2.2.6_06.00.01.07.001 Наименование: При выполнении при капитальном ремонте и реконструкции работ, аналогичных технологическим процессам, характерным для нового строительства, и отсутствующих в сборниках на ремонтно-строительные работы ТСН-2001.6 | CO31: 0 | CP31: =(P31+Q31+S31) -> 178.63 | CQ31: =ROUND((ROUND((AC31*AW31*1),2)*BC31),2) -> 1651.53 | CR31: =(ROUND((ROUND(((((ET31*1.1)*1.25))*AV31*1),2)*BB31),2)+ROUND((ROUND(((AE31-(((EU31*1.1)*1.25)))*AV31*1),2)*BS31),2)) -> 188.71 | CS31: =(ROUND((ROUND(((((EU31*1.1)*1.25))*AV31*1),2)*BS31),2)+ROUND((ROUND(((AE31-(((EU31*1.1)*1.25)))*AV31*1),2)*BS31),2)) -> 81.39 | CT31: =ROUND((ROUND((AF31*AV31*1),2)*BA31),2) -> 7094.81 | CU31: =AG31 -> 0 | CV31: =(AH31*AV31) -> 11.580898 | CW31: =AI31 -> 0 | CX31: =AJ31 -> 0 | CY31: =(ROUND((((S31+ROUND((ROUND(((((EU31*1.1)*1.25))*AV31*1),2)*BS31),2))*AT31)/100),2)+ROUND(((ROUND((ROUND(((AE31-(((EU31*1.1)*1.25)))*AV31*1),2)*BS31),2)*AT31)/100),2)) -> 243.35 | CZ31: =(ROUND((((S31+ROUND((ROUND(((((EU31*1.1)*1.25))*AV31*1),2)*BS31),2))*AU31)/100),2)+ROUND(((ROUND((ROUND(((AE31-(((EU31*1.1)*1.25)))*AV31*1),2)*BS31),2)*AU31)/100),2)) -> 136.19 | DB31: 7 | DD31: *1)*1 | DE31: *1,1)*1,25 | DF31: *1,1)*1,25 | DG31: *1,1)*1,15 | DI31: *1,1)*1,15 | DJ31: *1,1)*1,25 | DN31: 0 | DO31: 0 | DP31: 1 | DQ31: 1 | DU31: 1010 | DV31: 100 шт. | DW31: 100 шт. | DX31: 100 | EE31: 59298928 | EF31: 30 | EG31: Строительные работы | EH31: 0 | EJ31: 1 | EK31: 22 | EL31: ТСН-2001.3-17. Водопровод и канализация - внутренние устройства | EM31: ТСН-2001.3-17-1 | EO31: Поправка: Гл.12.Прил.8.п.8. 5_12.00.01.11.003 Поправка: Гл.6.Прил.2.2.п.2.2.6_06.00.01.07.001 | EQ31: 0 | ER31: 2306.6 | ES31: 2202.04 | ET31: 8.97 | EU31: 1.01 | EV31: 95.59 | EW31: 8.58 | EX31: 0 | EY31: 0 | FQ31: 0 | FR31: 0 | FS31: 0 | FX31: 109 | FY31: 61 | GD31: 1 | GF31: -488901103 | GG31: 2 | GH31: 1 | GI31: 2 | GJ31: 0 | GK31: 0 | GL31: =ROUND(IF(AND(BH31=3,BI31=3,FS31<>0),P31,0),2) -> 0 | GM31: =ROUND(O31+X31+Y31,2)+GX31 -> 422.62 | GN31: =IF(OR(BI31=0,BI31=1),GM31-GX31,0) -> 422.62 | GO31: =IF(BI31=2,GM31-GX31,0) -> 0 | GP31: =IF(BI31=4,GM31-GX31,0) -> 0 | GR31: 0 | GS31: 3 | GT31: 0 | GV31: =ROUND((GT31),6) -> 0 | GW31: 1 | GX31: =ROUND(HC31*I31,2) -> 0 | HA31: 0 | HB31: 0 | HC31: =GV31*GW31 -> 0 | HS31: 0 | IK31: 0
A32: 17 | B32: 1 | D32: =ROW(EtalonRes!A4) -> 4 | E32: 3 | F32: 3.17-2-5 | G32: Установка гарнитуры туалетной полочек/зеркало | H32: 1 ШТ. | I32: 1 | J32: 0 | K32: 1 | O32: =ROUND(CP32,2) -> 11.05 | P32: =ROUND((ROUND((AC32*AW32*I32),2)*BC32),2) -> 0.32 | Q32: =(ROUND((ROUND(((((ET32*1.25)*1.1))*AV32*I32),2)*BB32),2)+ROUND((ROUND(((AE32-(((EU32*1.25)*1.1)))*AV32*I32),2)*BS32),2)) -> 0 | R32: =(ROUND((ROUND(((((EU32*1.25)*1.1))*AV32*I32),2)*BS32),2)+ROUND((ROUND(((AE32-(((EU32*1.25)*1.1)))*AV32*I32),2)*BS32),2)) -> 0 | S32: =ROUND((ROUND((AF32*AV32*I32),2)*BA32),2) -> 10.73 | T32: =ROUND(CU32*I32,2) -> 0 | U32: =CV32*I32 -> 0.85034565 | V32: =CW32*I32 -> 0 | W32: =ROUND(CX32*I32,2) -> 0 | X32: =(ROUND((((S32+ROUND((ROUND(((((EU32*1.25)*1.1))*AV32*I32),2)*BS32),2))*AT32)/100),2)+ROUND(((ROUND((ROUND(((AE32-(((EU32*1.25)*1.1)))*AV32*I32),2)*BS32),2)*AT32)/100),2)) -> 11.7 | Y32: =(ROUND((((S32+ROUND((ROUND(((((EU32*1.25)*1.1))*AV32*I32),2)*BS32),2))*AU32)/100),2)+ROUND(((ROUND((ROUND(((AE32-(((EU32*1.25)*1.1)))*AV32*I32),2)*BS32),2)*AU32)/100),2)) -> 6.55 | AA32: 59499218 | AB32: =ROUND((AC32+AD32+AF32),6) -> 10.37675 | AC32: =ROUND((ES32),6) -> 0.32 | AD32: =ROUND((((((ET32*1.25)*1.1))-(((EU32*1.25)*1.1)))+AE32),6) -> 0 | AE32: =ROUND((((EU32*1.25)*1.1)),6) -> 0 | AF32: =ROUND((((EV32*1.15)*1.1)),6) -> 10.05675 | AG32: =ROUND((AP32),6) -> 0 | AH32: =(((EW32*1.15)*1.1)) -> 0.79695 | AI32: =(((EX32*1.25)*1.1)) -> 0 | AJ32: =(AS32) -> 0 | AK32: 8.27 | AL32: 0.32 | AM32: 0 | AN32: 0 | AO32: 7.95 | AP32: 0 | AQ32: 0.63 | AR32: 0 | AS32: 0 | AT32: 109 | AU32: 61 | AV32: 1.067 | AW32: 1 | AZ32: 1 | BA32: 1 | BB32: 1 | BC32: 1 | BH32: 0 | BI32: 1 | BJ32: ТСН-2001.3 Доп. 72, Сб. 17, т. 2, поз. 5 | BM32: 22 | BN32: 59298886 | BO32: 3.17-2-5 | BP32: 1 | BQ32: 30 | BR32: 0 | BS32: 1 | BT32: 1 | BU32: 1 | BV32: 1 | BW32: 1 | BX32: 1 | BZ32: 109 | CA32: 61 | CE32: 1566 | CF32: 0 | CG32: 0 | CM32: 0 | CN32: Поправка: О.П. п.3.4.30.в Наименование: При применении территориальных сметных нормативов для города Москвы затраты, учитывающие напряженные и стесненные условия производства работ (стесненность, сложность складирования и транспортной логистики и т.п.), исчисляются с применением коэффициентов к затратам труда и заработной плате рабочих, машинистов, времени эксплуатации машин и механизмов, стоимости эксплуатации машин в размере: для объектов, расположенных за пределами Третьего транспортного кольца города Москвы, но в пределах Московской кольцевой автомобильной дороги | CO32: 0 | CP32: =(P32+Q32+S32) -> 11.05 | CQ32: =ROUND((ROUND((AC32*AW32*1),2)*BC32),2) -> 0.32 | CR32: =(ROUND((ROUND(((((ET32*1.25)*1.1))*AV32*1),2)*BB32),2)+ROUND((ROUND(((AE32-(((EU32*1.25)*1.1)))*AV32*1),2)*BS32),2)) -> 0 | CS32: =(ROUND((ROUND(((((EU32*1.25)*1.1))*AV32*1),2)*BS32),2)+ROUND((ROUND(((AE32-(((EU32*1.25)*1.1)))*AV32*1),2)*BS32),2)) -> 0 | CT32: =ROUND((ROUND((AF32*AV32*1),2)*BA32),2) -> 10.73 | CU32: =AG32 -> 0 | CV32: =(AH32*AV32) -> 0.85034565 | CW32: =AI32 -> 0 | CX32: =AJ32 -> 0 | CY32: =(ROUND((((S32+ROUND((ROUND(((((EU32*1.25)*1.1))*AV32*1),2)*BS32),2))*AT32)/100),2)+ROUND(((ROUND((ROUND(((AE32-(((EU32*1.25)*1.1)))*AV32*1),2)*BS32),2)*AT32)/100),2)) -> 11.7 | CZ32: =(ROUND((((S32+ROUND((ROUND(((((EU32*1.25)*1.1))*AV32*1),2)*BS32),2))*AU32)/100),2)+ROUND(((ROUND((ROUND(((AE32-(((EU32*1.25)*1.1)))*AV32*1),2)*BS32),2)*AU32)/100),2)) -> 6.55 | DB32: 9 | DE32: *1,25)*1,1 | DF32: *1,25)*1,1 | DG32: *1,15)*1,1 | DI32: *1,15)*1,1 | DJ32: *1,25)*1,1 | DN32: 0 | DO32: 0 | DP32: 1 | DQ32: 1 | DU32: 1013 | DV32: 1 ШТ. | DW32: 1 ШТ. | DX32: 1 | EE32: 59298928 | EF32: 30 | EG32: Строительные работы | EH32: 0 | EJ32: 1 | EK32: 22 | EL32: ТСН-2001.3-17. Водопровод и канализация - внутренние устройства | EM32: ТСН-2001.3-17-1 | EO32: Поправка: О.П. п.3.4.30.в | EQ32: 0 | ER32: 8.27 | ES32: 0.32 | ET32: 0 | EU32: 0 | EV32: 7.95 | EW32: 0.63 | EX32: 0 | EY32: 0 | FQ32: 0 | FR32: 0 | FS32: 0 | FX32: 109 | FY32: 61 | GD32: 1 | GF32: -1951833034 | GG32: 2 | GH32: 1 | GI32: 2 | GJ32: 0 | GK32: 0 | GL32: =ROUND(IF(AND(BH32=3,BI32=3,FS32<>0),P32,0),2) -> 0 | GM32: =ROUND(O32+X32+Y32,2)+GX32 -> 29.3 | GN32: =IF(OR(BI32=0,BI32=1),GM32-GX32,0) -> 29.3 | GO32: =IF(BI32=2,GM32-GX32,0) -> 0 | GP32: =IF(BI32=4,GM32-GX32,0) -> 0 | GR32: 0 | GS32: 3 | GT32: 0 | GV32: =ROUND((GT32),6) -> 0 | GW32: 1 | GX32: =ROUND(HC32*I32,2) -> 0 | HA32: 0 | HB32: 0 | HC32: =GV32*GW32 -> 0 | HS32: 0 | IK32: 0
A33: 17 | B33: 1 | D33: =ROW(EtalonRes!A8) -> 8 | E33: 3 | F33: 3.17-2-5 | G33: Установка гарнитуры туалетной полочек/зеркало | H33: 1 ШТ. | I33: 1 | J33: 0 | K33: 1 | O33: =ROUND(CP33,2) -> 591.93 | P33: =ROUND((ROUND((AC33*AW33*I33),2)*BC33),2) -> 1.89 | Q33: =(ROUND((ROUND(((((ET33*1.25)*1.1))*AV33*I33),2)*BB33),2)+ROUND((ROUND(((AE33-(((EU33*1.25)*1.1)))*AV33*I33),2)*BS33),2)) -> 0 | R33: =(ROUND((ROUND(((((EU33*1.25)*1.1))*AV33*I33),2)*BS33),2)+ROUND((ROUND(((AE33-(((EU33*1.25)*1.1)))*AV33*I33),2)*BS33),2)) -> 0 | S33: =ROUND((ROUND((AF33*AV33*I33),2)*BA33),2) -> 590.04 | T33: =ROUND(CU33*I33,2) -> 0 | U33: =CV33*I33 -> 0.85034565 | V33: =CW33*I33 -> 0 | W33: =ROUND(CX33*I33,2) -> 0 | X33: =(ROUND((((S33+ROUND((ROUND(((((EU33*1.25)*1.1))*AV33*I33),2)*BS33),2))*AT33)/100),2)+ROUND(((ROUND((ROUND(((AE33-(((EU33*1.25)*1.1)))*AV33*I33),2)*BS33),2)*AT33)/100),2)) -> 643.14 | Y33: =(ROUND((((S33+ROUND((ROUND(((((EU33*1.25)*1.1))*AV33*I33),2)*BS33),2))*AU33)/100),2)+ROUND(((ROUND((ROUND(((AE33-(((EU33*1.25)*1.1)))*AV33*I33),2)*BS33),2)*AU33)/100),2)) -> 359.92 | AA33: 59499215 | AB33: =ROUND((AC33+AD33+AF33),6) -> 10.37675 | AC33: =ROUND((ES33),6) -> 0.32 | AD33: =ROUND((((((ET33*1.25)*1.1))-(((EU33*1.25)*1.1)))+AE33),6) -> 0 | AE33: =ROUND((((EU33*1.25)*1.1)),6) -> 0 | AF33: =ROUND((((EV33*1.15)*1.1)),6) -> 10.05675 | AG33: =ROUND((AP33),6) -> 0 | AH33: =(((EW33*1.15)*1.1)) -> 0.79695 | AI33: =(((EX33*1.25)*1.1)) -> 0 | AJ33: =(AS33) -> 0 | AK33: 8.27 | AL33: 0.32 | AM33: 0 | AN33: 0 | AO33: 7.95 | AP33: 0 | AQ33: 0.63 | AR33: 0 | AS33: 0 | AT33: 109 | AU33: 61 | AV33: 1.067 | AW33: 1 | AZ33: 1 | BA33: 54.99 | BB33: 1 | BC33: 5.91 | BH33: 0 | BI33: 1 | BJ33: ТСН-2001.3 Доп. 72, Сб. 17, т. 2, поз. 5 | BM33: 22 | BN33: 59298886 | BO33: 3.17-2-5 | BP33: 1 | BQ33: 30 | BR33: 0 | BS33: 54.99 | BT33: 1 | BU33: 1 | BV33: 1 | BW33: 1 | BX33: 1 | BZ33: 109 | CA33: 61 | CE33: 1566 | CF33: 0 | CG33: 0 | CM33: 0 | CN33: Поправка: О.П. п.3.4.30.в Наименование: При применении территориальных сметных нормативов для города Москвы затраты, учитывающие напряженные и стесненные условия производства работ (стесненность, сложность складирования и транспортной логистики и т.п.), исчисляются с применением коэффициентов к затратам труда и заработной плате рабочих, машинистов, времени эксплуатации машин и механизмов, стоимости эксплуатации машин в размере: для объектов, расположенных за пределами Третьего транспортного кольца города Москвы, но в пределах Московской кольцевой автомобильной дороги | CO33: 0 | CP33: =(P33+Q33+S33) -> 591.93 | CQ33: =ROUND((ROUND((AC33*AW33*1),2)*BC33),2) -> 1.89 | CR33: =(ROUND((ROUND(((((ET33*1.25)*1.1))*AV33*1),2)*BB33),2)+ROUND((ROUND(((AE33-(((EU33*1.25)*1.1)))*AV33*1),2)*BS33),2)) -> 0 | CS33: =(ROUND((ROUND(((((EU33*1.25)*1.1))*AV33*1),2)*BS33),2)+ROUND((ROUND(((AE33-(((EU33*1.25)*1.1)))*AV33*1),2)*BS33),2)) -> 0 | CT33: =ROUND((ROUND((AF33*AV33*1),2)*BA33),2) -> 590.04 | CU33: =AG33 -> 0 | CV33: =(AH33*AV33) -> 0.85034565 | CW33: =AI33 -> 0 | CX33: =AJ33 -> 0 | CY33: =(ROUND((((S33+ROUND((ROUND(((((EU33*1.25)*1.1))*AV33*1),2)*BS33),2))*AT33)/100),2)+ROUND(((ROUND((ROUND(((AE33-(((EU33*1.25)*1.1)))*AV33*1),2)*BS33),2)*AT33)/100),2)) -> 643.14 | CZ33: =(ROUND((((S33+ROUND((ROUND(((((EU33*1.25)*1.1))*AV33*1),2)*BS33),2))*AU33)/100),2)+ROUND(((ROUND((ROUND(((AE33-(((EU33*1.25)*1.1)))*AV33*1),2)*BS33),2)*AU33)/100),2)) -> 359.92 | DB33: 11 | DE33: *1,25)*1,1 | DF33: *1,25)*1,1 | DG33: *1,15)*1,1 | DI33: *1,15)*1,1 | DJ33: *1,25)*1,1 | DN33: 0 | DO33: 0 | DP33: 1 | DQ33: 1 | DU33: 1013 | DV33: 1 ШТ. | DW33: 1 ШТ. | DX33: 1 | EE33: 59298928 | EF33: 30 | EG33: Строительные работы | EH33: 0 | EJ33: 1 | EK33: 22 | EL33: ТСН-2001.3-17. Водопровод и канализация - внутренние устройства | EM33: ТСН-2001.3-17-1 | EO33: Поправка: О.П. п.3.4.30.в | EQ33: 0 | ER33: 8.27 | ES33: 0.32 | ET33: 0 | EU33: 0 | EV33: 7.95 | EW33: 0.63 | EX33: 0 | EY33: 0 | FQ33: 0 | FR33: 0 | FS33: 0 | FX33: 109 | FY33: 61 | GD33: 1 | GF33: -1951833034 | GG33: 2 | GH33: 1 | GI33: 2 | GJ33: 0 | GK33: 0 | GL33: =ROUND(IF(AND(BH33=3,BI33=3,FS33<>0),P33,0),2) -> 0 | GM33: =ROUND(O33+X33+Y33,2)+GX33 -> 1594.99 | GN33: =IF(OR(BI33=0,BI33=1),GM33-GX33,0) -> 1594.99 | GO33: =IF(BI33=2,GM33-GX33,0) -> 0 | GP33: =IF(BI33=4,GM33-GX33,0) -> 0 | GR33: 0 | GS33: 3 | GT33: 0 | GV33: =ROUND((GT33),6) -> 0 | GW33: 1 | GX33: =ROUND(HC33*I33,2) -> 0 | HA33: 0 | HB33: 0 | HC33: =GV33*GW33 -> 0 | HS33: 0 | IK33: 0
A34: 17 | B34: 1 | E34: 4 | F34: 3.17-2-13 | G34: Установка гарнитуры туалетной: вешалок, подстаканников, дозаторов настенных и т.п./диспенсер | H34: 100 шт. | I34: =ROUND(3/100,9) -> 0.03 | J34: 0 | K34: =ROUND(3/100,9) -> 0.03 | O34: =ROUND(CP34,2) -> 70.32 | P34: =ROUND((ROUND((AC34*AW34*I34),2)*BC34),2) -> 66.06 | Q34: =(ROUND((ROUND(((((ET34*1.1)*1.25))*AV34*I34),2)*BB34),2)+ROUND((ROUND(((AE34-(((EU34*1.1)*1.25)))*AV34*I34),2)*BS34),2)) -> 0.39 | R34: =(ROUND((ROUND(((((EU34*1.1)*1.25))*AV34*I34),2)*BS34),2)+ROUND((ROUND(((AE34-(((EU34*1.1)*1.25)))*AV34*I34),2)*BS34),2)) -> 0.04 | S34: =ROUND((ROUND((AF34*AV34*I34),2)*BA34),2) -> 3.87 | T34: =ROUND(CU34*I34,2) -> 0 | U34: =CV34*I34 -> 0.34742694 | V34: =CW34*I34 -> 0 | W34: =ROUND(CX34*I34,2) -> 0 | X34: =(ROUND((((S34+ROUND((ROUND(((((EU34*1.1)*1.25))*AV34*I34),2)*BS34),2))*AT34)/100),2)+ROUND(((ROUND((ROUND(((AE34-(((EU34*1.1)*1.25)))*AV34*I34),2)*BS34),2)*AT34)/100),2)) -> 4.26 | Y34: =(ROUND((((S34+ROUND((ROUND(((((EU34*1.1)*1.25))*AV34*I34),2)*BS34),2))*AU34)/100),2)+ROUND(((ROUND((ROUND(((AE34-(((EU34*1.1)*1.25)))*AV34*I34),2)*BS34),2)*AU34)/100),2)) -> 2.39 | AA34: 59499218 | AB34: =ROUND((AC34+AD34+AF34),6) -> 2335.2951 | AC34: =ROUND((((ES34*1)*1)),6) -> 2202.04 | AD34: =ROUND((((((ET34*1.1)*1.25))-(((EU34*1.1)*1.25)))+AE34),6) -> 12.33375 | AE34: =ROUND((((EU34*1.1)*1.25)),6) -> 1.38875 | AF34: =ROUND((((EV34*1.1)*1.15)),6) -> 120.92135 | AG34: =ROUND((AP34),6) -> 0 | AH34: =(((EW34*1.1)*1.15)) -> 10.8537 | AI34: =(((EX34*1.1)*1.25)) -> 0 | AJ34: =(AS34) -> 0 | AK34: 2306.6 | AL34: 2202.04 | AM34: 8.97 | AN34: 1.01 | AO34: 95.59 | AP34: 0 | AQ34: 8.58 | AR34: 0 | AS34: 0 | AT34: 109 | AU34: 61 | AV34: 1.067 | AW34: 1 | AZ34: 1 | BA34: 1 | BB34: 1 | BC34: 1 | BH34: 0 | BI34: 1 | BJ34: ТСН-2001.3 Доп. 80, Сб. 17, т. 2, поз. 13 | BM34: 22 | BN34: 0 | BO34: 3.17-2-13 | BP34: 1 | BQ34: 30 | BR34: 0 | BS34: 1 | BT34: 1 | BU34: 1 | BV34: 1 | BW34: 1 | BX34: 1 | BZ34: 109 | CA34: 61 | CE34: 1566 | CF34: 0 | CG34: 0 | CM34: 0 | CN34: Поправка: Гл.12.Прил.8.п.8. 5_12.00.01.11.003 Наименование: При наличии усложненных условий производства работ (стесненность, сложность складирования и транспортной логистики, наличие в зоне производства работ действующего технологического оборудования или движения технологического транспорта и т.п.) для объектов, расположенных за пределами территории круговой магистральной системы улиц "Садовое кольцо" и за пределами Третьего транспортного кольца города Москвы пунктов "а" и "б", но в пределах Московской кольцевой автомобильной дороги Поправка: Гл.6.Прил.2.2.п.2.2.6_06.00.01.07.001 Наименование: При выполнении при капитальном ремонте и реконструкции работ, аналогичных технологическим процессам, характерным для нового строительства, и отсутствующих в сборниках на ремонтно-строительные работы ТСН-2001.6 | CO34: 0 | CP34: =(P34+Q34+S34) -> 70.32 | CQ34: =ROUND((ROUND((AC34*AW34*1),2)*BC34),2) -> 2202.04 | CR34: =(ROUND((ROUND(((((ET34*1.1)*1.25))*AV34*1),2)*BB34),2)+ROUND((ROUND(((AE34-(((EU34*1.1)*1.25)))*AV34*1),2)*BS34),2)) -> 13.16 | CS34: =(ROUND((ROUND(((((EU34*1.1)*1.25))*AV34*1),2)*BS34),2)+ROUND((ROUND(((AE34-(((EU34*1.1)*1.25)))*AV34*1),2)*BS34),2)) -> 1.48 | CT34: =ROUND((ROUND((AF34*AV34*1),2)*BA34),2) -> 129.02 | CU34: =AG34 -> 0 | CV34: =(AH34*AV34) -> 11.580898 | CW34: =AI34 -> 0 | CX34: =AJ34 -> 0 | CY34: =(ROUND((((S34+ROUND((ROUND(((((EU34*1.1)*1.25))*AV34*1),2)*BS34),2))*AT34)/100),2)+ROUND(((ROUND((ROUND(((AE34-(((EU34*1.1)*1.25)))*AV34*1),2)*BS34),2)*AT34)/100),2)) -> 5.83 | CZ34: =(ROUND((((S34+ROUND((ROUND(((((EU34*1.1)*1.25))*AV34*1),2)*BS34),2))*AU34)/100),2)+ROUND(((ROUND((ROUND(((AE34-(((EU34*1.1)*1.25)))*AV34*1),2)*BS34),2)*AU34)/100),2)) -> 3.26 | DB34: 13 | DD34: *1)*1 | DE34: *1,1)*1,25 | DF34: *1,1)*1,25 | DG34: *1,1)*1,15 | DI34: *1,1)*1,15 | DJ34: *1,1)*1,25 | DN34: 0 | DO34: 0 | DP34: 1 | DQ34: 1 | DU34: 1010 | DV34: 100 шт. | DW34: 100 шт. | DX34: 100 | EE34: 59298928 | EF34: 30 | EG34: Строительные работы | EH34: 0 | EJ34: 1 | EK34: 22 | EL34: ТСН-2001.3-17. Водопровод и канализация - внутренние устройства | EM34: ТСН-2001.3-17-1 | EO34: Поправка: Гл.12.Прил.8.п.8. 5_12.00.01.11.003 Поправка: Гл.6.Прил.2.2.п.2.2.6_06.00.01.07.001 | EQ34: 0 | ER34: 2306.6 | ES34: 2202.04 | ET34: 8.97 | EU34: 1.01 | EV34: 95.59 | EW34: 8.58 | EX34: 0 | EY34: 0 | FQ34: 0 | FR34: 0 | FS34: 0 | FX34: 109 | FY34: 61 | GD34: 1 | GF34: 486003536 | GG34: 2 | GH34: 1 | GI34: 2 | GJ34: 0 | GK34: 0 | GL34: =ROUND(IF(AND(BH34=3,BI34=3,FS34<>0),P34,0),2) -> 0 | GM34: =ROUND(O34+X34+Y34,2)+GX34 -> 76.97 | GN34: =IF(OR(BI34=0,BI34=1),GM34-GX34,0) -> 76.97 | GO34: =IF(BI34=2,GM34-GX34,0) -> 0 | GP34: =IF(BI34=4,GM34-GX34,0) -> 0 | GR34: 0 | GS34: 3 | GT34: 0 | GV34: =ROUND((GT34),6) -> 0 | GW34: 1 | GX34: =ROUND(HC34*I34,2) -> 0 | HA34: 0 | HB34: 0 | HC34: =GV34*GW34 -> 0 | HS34: 0 | IK34: 0
A35: 17 | B35: 1 | E35: 4 | F35: 3.17-2-13 | G35: Установка гарнитуры туалетной: вешалок, подстаканников, дозаторов настенных и т.п./диспенсер | H35: 100 шт. | I35: =ROUND(3/100,9) -> 0.03 | J35: 0 | K35: =ROUND(3/100,9) -> 0.03 | O35: =ROUND(CP35,2) -> 267.95 | P35: =ROUND((ROUND((AC35*AW35*I35),2)*BC35),2) -> 49.55 | Q35: =(ROUND((ROUND(((((ET35*1.1)*1.25))*AV35*I35),2)*BB35),2)+ROUND((ROUND(((AE35-(((EU35*1.1)*1.25)))*AV35*I35),2)*BS35),2)) -> 5.59 | R35: =(ROUND((ROUND(((((EU35*1.1)*1.25))*AV35*I35),2)*BS35),2)+ROUND((ROUND(((AE35-(((EU35*1.1)*1.25)))*AV35*I35),2)*BS35),2)) -> 2.2 | S35: =ROUND((ROUND((AF35*AV35*I35),2)*BA35),2) -> 212.81 | T35: =ROUND(CU35*I35,2) -> 0 | U35: =CV35*I35 -> 0.34742694 | V35: =CW35*I35 -> 0 | W35: =ROUND(CX35*I35,2) -> 0 | X35: =(ROUND((((S35+ROUND((ROUND(((((EU35*1.1)*1.25))*AV35*I35),2)*BS35),2))*AT35)/100),2)+ROUND(((ROUND((ROUND(((AE35-(((EU35*1.1)*1.25)))*AV35*I35),2)*BS35),2)*AT35)/100),2)) -> 234.36 | Y35: =(ROUND((((S35+ROUND((ROUND(((((EU35*1.1)*1.25))*AV35*I35),2)*BS35),2))*AU35)/100),2)+ROUND(((ROUND((ROUND(((AE35-(((EU35*1.1)*1.25)))*AV35*I35),2)*BS35),2)*AU35)/100),2)) -> 131.16 | AA35: 59499215 | AB35: =ROUND((AC35+AD35+AF35),6) -> 2335.2951 | AC35: =ROUND((((ES35*1)*1)),6) -> 2202.04 | AD35: =ROUND((((((ET35*1.1)*1.25))-(((EU35*1.1)*1.25)))+AE35),6) -> 12.33375 | AE35: =ROUND((((EU35*1.1)*1.25)),6) -> 1.38875 | AF35: =ROUND((((EV35*1.1)*1.15)),6) -> 120.92135 | AG35: =ROUND((AP35),6) -> 0 | AH35: =(((EW35*1.1)*1.15)) -> 10.8537 | AI35: =(((EX35*1.1)*1.25)) -> 0 | AJ35: =(AS35) -> 0 | AK35: 2306.6 | AL35: 2202.04 | AM35: 8.97 | AN35: 1.01 | AO35: 95.59 | AP35: 0 | AQ35: 8.58 | AR35: 0 | AS35: 0 | AT35: 109 | AU35: 61 | AV35: 1.067 | AW35: 1 | AZ35: 1 | BA35: 54.99 | BB35: 14.34 | BC35: 0.75 | BH35: 0 | BI35: 1 | BJ35: ТСН-2001.3 Доп. 80, Сб. 17, т. 2, поз. 13 | BM35: 22 | BN35: 0 | BO35: 3.17-2-13 | BP35: 1 | BQ35: 30 | BR35: 0 | BS35: 54.99 | BT35: 1 | BU35: 1 | BV35: 1 | BW35: 1 | BX35: 1 | BZ35: 109 | CA35: 61 | CE35: 1566 | CF35: 0 | CG35: 0 | CM35: 0 | CN35: Поправка: Гл.12.Прил.8.п.8. 5_12.00.01.11.003 Наименование: При наличии усложненных условий производства работ (стесненность, сложность складирования и транспортной логистики, наличие в зоне производства работ действующего технологического оборудования или движения технологического транспорта и т.п.) для объектов, расположенных за пределами территории круговой магистральной системы улиц "Садовое кольцо" и за пределами Третьего транспортного кольца города Москвы пунктов "а" и "б", но в пределах Московской кольцевой автомобильной дороги Поправка: Гл.6.Прил.2.2.п.2.2.6_06.00.01.07.001 Наименование: При выполнении при капитальном ремонте и реконструкции работ, аналогичных технологическим процессам, характерным для нового строительства, и отсутствующих в сборниках на ремонтно-строительные работы ТСН-2001.6 | CO35: 0 | CP35: =(P35+Q35+S35) -> 267.95 | CQ35: =ROUND((ROUND((AC35*AW35*1),2)*BC35),2) -> 1651.53 | CR35: =(ROUND((ROUND(((((ET35*1.1)*1.25))*AV35*1),2)*BB35),2)+ROUND((ROUND(((AE35-(((EU35*1.1)*1.25)))*AV35*1),2)*BS35),2)) -> 188.71 | CS35: =(ROUND((ROUND(((((EU35*1.1)*1.25))*AV35*1),2)*BS35),2)+ROUND((ROUND(((AE35-(((EU35*1.1)*1.25)))*AV35*1),2)*BS35),2)) -> 81.39 | CT35: =ROUND((ROUND((AF35*AV35*1),2)*BA35),2) -> 7094.81 | CU35: =AG35 -> 0 | CV35: =(AH35*AV35) -> 11.580898 | CW35: =AI35 -> 0 | CX35: =AJ35 -> 0 | CY35: =(ROUND((((S35+ROUND((ROUND(((((EU35*1.1)*1.25))*AV35*1),2)*BS35),2))*AT35)/100),2)+ROUND(((ROUND((ROUND(((AE35-(((EU35*1.1)*1.25)))*AV35*1),2)*BS35),2)*AT35)/100),2)) -> 320.68 | CZ35: =(ROUND((((S35+ROUND((ROUND(((((EU35*1.1)*1.25))*AV35*1),2)*BS35),2))*AU35)/100),2)+ROUND(((ROUND((ROUND(((AE35-(((EU35*1.1)*1.25)))*AV35*1),2)*BS35),2)*AU35)/100),2)) -> 179.46 | DB35: 15 | DD35: *1)*1 | DE35: *1,1)*1,25 | DF35: *1,1)*1,25 | DG35: *1,1)*1,15 | DI35: *1,1)*1,15 | DJ35: *1,1)*1,25 | DN35: 0 | DO35: 0 | DP35: 1 | DQ35: 1 | DU35: 1010 | DV35: 100 шт. | DW35: 100 шт. | DX35: 100 | EE35: 59298928 | EF35: 30 | EG35: Строительные работы | EH35: 0 | EJ35: 1 | EK35: 22 | EL35: ТСН-2001.3-17. Водопровод и канализация - внутренние устройства | EM35: ТСН-2001.3-17-1 | EO35: Поправка: Гл.12.Прил.8.п.8. 5_12.00.01.11.003 Поправка: Гл.6.Прил.2.2.п.2.2.6_06.00.01.07.001 | EQ35: 0 | ER35: 2306.6 | ES35: 2202.04 | ET35: 8.97 | EU35: 1.01 | EV35: 95.59 | EW35: 8.58 | EX35: 0 | EY35: 0 | FQ35: 0 | FR35: 0 | FS35: 0 | FX35: 109 | FY35: 61 | GD35: 1 | GF35: 486003536 | GG35: 2 | GH35: 1 | GI35: 2 | GJ35: 0 | GK35: 0 | GL35: =ROUND(IF(AND(BH35=3,BI35=3,FS35<>0),P35,0),2) -> 0 | GM35: =ROUND(O35+X35+Y35,2)+GX35 -> 633.47 | GN35: =IF(OR(BI35=0,BI35=1),GM35-GX35,0) -> 633.47 | GO35: =IF(BI35=2,GM35-GX35,0) -> 0 | GP35: =IF(BI35=4,GM35-GX35,0) -> 0 | GR35: 0 | GS35: 3 | GT35: 0 | GV35: =ROUND((GT35),6) -> 0 | GW35: 1 | GX35: =ROUND(HC35*I35,2) -> 0 | HA35: 0 | HB35: 0 | HC35: =GV35*GW35 -> 0 | HS35: 0 | IK35: 0
A36: 17 | B36: 1 | E36: 5 | F36: 3.17-2-13 | G36: Установка гарнитуры туалетной: вешалок, подстаканников, дозаторов настенных и т.п./ туалетный ершик с креплением на стену | H36: 100 шт. | I36: =ROUND(1/100,9) -> 0.01 | J36: 0 | K36: =ROUND(1/100,9) -> 0.01 | O36: =ROUND(CP36,2) -> 23.44 | P36: =ROUND((ROUND((AC36*AW36*I36),2)*BC36),2) -> 22.02 | Q36: =(ROUND((ROUND(((((ET36*1.1)*1.25))*AV36*I36),2)*BB36),2)+ROUND((ROUND(((AE36-(((EU36*1.1)*1.25)))*AV36*I36),2)*BS36),2)) -> 0.13 | R36: =(ROUND((ROUND(((((EU36*1.1)*1.25))*AV36*I36),2)*BS36),2)+ROUND((ROUND(((AE36-(((EU36*1.1)*1.25)))*AV36*I36),2)*BS36),2)) -> 0.01 | S36: =ROUND((ROUND((AF36*AV36*I36),2)*BA36),2) -> 1.29 | T36: =ROUND(CU36*I36,2) -> 0 | U36: =CV36*I36 -> 0.11580898 | V36: =CW36*I36 -> 0 | W36: =ROUND(CX36*I36,2) -> 0 | X36: =(ROUND((((S36+ROUND((ROUND(((((EU36*1.1)*1.25))*AV36*I36),2)*BS36),2))*AT36)/100),2)+ROUND(((ROUND((ROUND(((AE36-(((EU36*1.1)*1.25)))*AV36*I36),2)*BS36),2)*AT36)/100),2)) -> 1.42 | Y36: =(ROUND((((S36+ROUND((ROUND(((((EU36*1.1)*1.25))*AV36*I36),2)*BS36),2))*AU36)/100),2)+ROUND(((ROUND((ROUND(((AE36-(((EU36*1.1)*1.25)))*AV36*I36),2)*BS36),2)*AU36)/100),2)) -> 0.79 | AA36: 59499218 | AB36: =ROUND((AC36+AD36+AF36),6) -> 2335.2951 | AC36: =ROUND((((ES36*1)*1)),6) -> 2202.04 | AD36: =ROUND((((((ET36*1.1)*1.25))-(((EU36*1.1)*1.25)))+AE36),6) -> 12.33375 | AE36: =ROUND((((EU36*1.1)*1.25)),6) -> 1.38875 | AF36: =ROUND((((EV36*1.1)*1.15)),6) -> 120.92135 | AG36: =ROUND((AP36),6) -> 0 | AH36: =(((EW36*1.1)*1.15)) -> 10.8537 | AI36: =(((EX36*1.1)*1.25)) -> 0 | AJ36: =(AS36) -> 0 | AK36: 2306.6 | AL36: 2202.04 | AM36: 8.97 | AN36: 1.01 | AO36: 95.59 | AP36: 0 | AQ36: 8.58 | AR36: 0 | AS36: 0 | AT36: 109 | AU36: 61 | AV36: 1.067 | AW36: 1 | AZ36: 1 | BA36: 1 | BB36: 1 | BC36: 1 | BH36: 0 | BI36: 1 | BJ36: ТСН-2001.3 Доп. 80, Сб. 17, т. 2, поз. 13 | BM36: 22 | BN36: 0 | BO36: 3.17-2-13 | BP36: 1 | BQ36: 30 | BR36: 0 | BS36: 1 | BT36: 1 | BU36: 1 | BV36: 1 | BW36: 1 | BX36: 1 | BZ36: 109 | CA36: 61 | CE36: 1566 | CF36: 0 | CG36: 0 | CM36: 0 | CN36: Поправка: Гл.12.Прил.8.п.8. 5_12.00.01.11.003 Наименование: При наличии усложненных условий производства работ (стесненность, сложность складирования и транспортной логистики, наличие в зоне производства работ действующего технологического оборудования или движения технологического транспорта и т.п.) для объектов, расположенных за пределами территории круговой магистральной системы улиц "Садовое кольцо" и за пределами Третьего транспортного кольца города Москвы пунктов "а" и "б", но в пределах Московской кольцевой автомобильной дороги Поправка: Гл.6.Прил.2.2.п.2.2.6_06.00.01.07.001 Наименование: При выполнении при капитальном ремонте и реконструкции работ, аналогичных технологическим процессам, характерным для нового строительства, и отсутствующих в сборниках на ремонтно-строительные работы ТСН-2001.6 | CO36: 0 | CP36: =(P36+Q36+S36) -> 23.44 | CQ36: =ROUND((ROUND((AC36*AW36*1),2)*BC36),2) -> 2202.04 | CR36: =(ROUND((ROUND(((((ET36*1.1)*1.25))*AV36*1),2)*BB36),2)+ROUND((ROUND(((AE36-(((EU36*1.1)*1.25)))*AV36*1),2)*BS36),2)) -> 13.16 | CS36: =(ROUND((ROUND(((((EU36*1.1)*1.25))*AV36*1),2)*BS36),2)+ROUND((ROUND(((AE36-(((EU36*1.1)*1.25)))*AV36*1),2)*BS36),2)) -> 1.48 | CT36: =ROUND((ROUND((AF36*AV36*1),2)*BA36),2) -> 129.02 | CU36: =AG36 -> 0 | CV36: =(AH36*AV36) -> 11.580898 | CW36: =AI36 -> 0 | CX36: =AJ36 -> 0 | CY36: =(ROUND((((S36+ROUND((ROUND(((((EU36*1.1)*1.25))*AV36*1),2)*BS36),2))*AT36)/100),2)+ROUND(((ROUND((ROUND(((AE36-(((EU36*1.1)*1.25)))*AV36*1),2)*BS36),2)*AT36)/100),2)) -> 3.02 | CZ36: =(ROUND((((S36+ROUND((ROUND(((((EU36*1.1)*1.25))*AV36*1),2)*BS36),2))*AU36)/100),2)+ROUND(((ROUND((ROUND(((AE36-(((EU36*1.1)*1.25)))*AV36*1),2)*BS36),2)*AU36)/100),2)) -> 1.69 | DB36: 17 | DD36: *1)*1 | DE36: *1,1)*1,25 | DF36: *1,1)*1,25 | DG36: *1,1)*1,15 | DI36: *1,1)*1,15 | DJ36: *1,1)*1,25 | DN36: 0 | DO36: 0 | DP36: 1 | DQ36: 1 | DU36: 1010 | DV36: 100 шт. | DW36: 100 шт. | DX36: 100 | EE36: 59298928 | EF36: 30 | EG36: Строительные работы | EH36: 0 | EJ36: 1 | EK36: 22 | EL36: ТСН-2001.3-17. Водопровод и канализация - внутренние устройства | EM36: ТСН-2001.3-17-1 | EO36: Поправка: Гл.12.Прил.8.п.8. 5_12.00.01.11.003 Поправка: Гл.6.Прил.2.2.п.2.2.6_06.00.01.07.001 | EQ36: 0 | ER36: 2306.6 | ES36: 2202.04 | ET36: 8.97 | EU36: 1.01 | EV36: 95.59 | EW36: 8.58 | EX36: 0 | EY36: 0 | FQ36: 0 | FR36: 0 | FS36: 0 | FX36: 109 | FY36: 61 | GD36: 1 | GF36: -907614113 | GG36: 2 | GH36: 1 | GI36: 2 | GJ36: 0 | GK36: 0 | GL36: =ROUND(IF(AND(BH36=3,BI36=3,FS36<>0),P36,0),2) -> 0 | GM36: =ROUND(O36+X36+Y36,2)+GX36 -> 25.65 | GN36: =IF(OR(BI36=0,BI36=1),GM36-GX36,0) -> 25.65 | GO36: =IF(BI36=2,GM36-GX36,0) -> 0 | GP36: =IF(BI36=4,GM36-GX36,0) -> 0 | GR36: 0 | GS36: 3 | GT36: 0 | GV36: =ROUND((GT36),6) -> 0 | GW36: 1 | GX36: =ROUND(HC36*I36,2) -> 0 | HA36: 0 | HB36: 0 | HC36: =GV36*GW36 -> 0 | HS36: 0 | IK36: 0
A37: 17 | B37: 1 | E37: 5 | F37: 3.17-2-13 | G37: Установка гарнитуры туалетной: вешалок, подстаканников, дозаторов настенных и т.п./ туалетный ершик с креплением на стену | H37: 100 шт. | I37: =ROUND(1/100,9) -> 0.01 | J37: 0 | K37: =ROUND(1/100,9) -> 0.01 | O37: =ROUND(CP37,2) -> 89.32 | P37: =ROUND((ROUND((AC37*AW37*I37),2)*BC37),2) -> 16.52 | Q37: =(ROUND((ROUND(((((ET37*1.1)*1.25))*AV37*I37),2)*BB37),2)+ROUND((ROUND(((AE37-(((EU37*1.1)*1.25)))*AV37*I37),2)*BS37),2)) -> 1.86 | R37: =(ROUND((ROUND(((((EU37*1.1)*1.25))*AV37*I37),2)*BS37),2)+ROUND((ROUND(((AE37-(((EU37*1.1)*1.25)))*AV37*I37),2)*BS37),2)) -> 0.55 | S37: =ROUND((ROUND((AF37*AV37*I37),2)*BA37),2) -> 70.94 | T37: =ROUND(CU37*I37,2) -> 0 | U37: =CV37*I37 -> 0.11580898 | V37: =CW37*I37 -> 0 | W37: =ROUND(CX37*I37,2) -> 0 | X37: =(ROUND((((S37+ROUND((ROUND(((((EU37*1.1)*1.25))*AV37*I37),2)*BS37),2))*AT37)/100),2)+ROUND(((ROUND((ROUND(((AE37-(((EU37*1.1)*1.25)))*AV37*I37),2)*BS37),2)*AT37)/100),2)) -> 77.92 | Y37: =(ROUND((((S37+ROUND((ROUND(((((EU37*1.1)*1.25))*AV37*I37),2)*BS37),2))*AU37)/100),2)+ROUND(((ROUND((ROUND(((AE37-(((EU37*1.1)*1.25)))*AV37*I37),2)*BS37),2)*AU37)/100),2)) -> 43.61 | AA37: 59499215 | AB37: =ROUND((AC37+AD37+AF37),6) -> 2335.2951 | AC37: =ROUND((((ES37*1)*1)),6) -> 2202.04 | AD37: =ROUND((((((ET37*1.1)*1.25))-(((EU37*1.1)*1.25)))+AE37),6) -> 12.33375 | AE37: =ROUND((((EU37*1.1)*1.25)),6) -> 1.38875 | AF37: =ROUND((((EV37*1.1)*1.15)),6) -> 120.92135 | AG37: =ROUND((AP37),6) -> 0 | AH37: =(((EW37*1.1)*1.15)) -> 10.8537 | AI37: =(((EX37*1.1)*1.25)) -> 0 | AJ37: =(AS37) -> 0 | AK37: 2306.6 | AL37: 2202.04 | AM37: 8.97 | AN37: 1.01 | AO37: 95.59 | AP37: 0 | AQ37: 8.58 | AR37: 0 | AS37: 0 | AT37: 109 | AU37: 61 | AV37: 1.067 | AW37: 1 | AZ37: 1 | BA37: 54.99 | BB37: 14.34 | BC37: 0.75 | BH37: 0 | BI37: 1 | BJ37: ТСН-2001.3 Доп. 80, Сб. 17, т. 2, поз. 13 | BM37: 22 | BN37: 0 | BO37: 3.17-2-13 | BP37: 1 | BQ37: 30 | BR37: 0 | BS37: 54.99 | BT37: 1 | BU37: 1 | BV37: 1 | BW37: 1 | BX37: 1 | BZ37: 109 | CA37: 61 | CE37: 1566 | CF37: 0 | CG37: 0 | CM37: 0 | CN37: Поправка: Гл.12.Прил.8.п.8. 5_12.00.01.11.003 Наименование: При наличии усложненных условий производства работ (стесненность, сложность складирования и транспортной логистики, наличие в зоне производства работ действующего технологического оборудования или движения технологического транспорта и т.п.) для объектов, расположенных за пределами территории круговой магистральной системы улиц "Садовое кольцо" и за пределами Третьего транспортного кольца города Москвы пунктов "а" и "б", но в пределах Московской кольцевой автомобильной дороги Поправка: Гл.6.Прил.2.2.п.2.2.6_06.00.01.07.001 Наименование: При выполнении при капитальном ремонте и реконструкции работ, аналогичных технологическим процессам, характерным для нового строительства, и отсутствующих в сборниках на ремонтно-строительные работы ТСН-2001.6 | CO37: 0 | CP37: =(P37+Q37+S37) -> 89.32 | CQ37: =ROUND((ROUND((AC37*AW37*1),2)*BC37),2) -> 1651.53 | CR37: =(ROUND((ROUND(((((ET37*1.1)*1.25))*AV37*1),2)*BB37),2)+ROUND((ROUND(((AE37-(((EU37*1.1)*1.25)))*AV37*1),2)*BS37),2)) -> 188.71 | CS37: =(ROUND((ROUND(((((EU37*1.1)*1.25))*AV37*1),2)*BS37),2)+ROUND((ROUND(((AE37-(((EU37*1.1)*1.25)))*AV37*1),2)*BS37),2)) -> 81.39 | CT37: =ROUND((ROUND((AF37*AV37*1),2)*BA37),2) -> 7094.81 | CU37: =AG37 -> 0 | CV37: =(AH37*AV37) -> 11.580898 | CW37: =AI37 -> 0 | CX37: =AJ37 -> 0 | CY37: =(ROUND((((S37+ROUND((ROUND(((((EU37*1.1)*1.25))*AV37*1),2)*BS37),2))*AT37)/100),2)+ROUND(((ROUND((ROUND(((AE37-(((EU37*1.1)*1.25)))*AV37*1),2)*BS37),2)*AT37)/100),2)) -> 166.04 | CZ37: =(ROUND((((S37+ROUND((ROUND(((((EU37*1.1)*1.25))*AV37*1),2)*BS37),2))*AU37)/100),2)+ROUND(((ROUND((ROUND(((AE37-(((EU37*1.1)*1.25)))*AV37*1),2)*BS37),2)*AU37)/100),2)) -> 92.92 | DB37: 19 | DD37: *1)*1 | DE37: *1,1)*1,25 | DF37: *1,1)*1,25 | DG37: *1,1)*1,15 | DI37: *1,1)*1,15 | DJ37: *1,1)*1,25 | DN37: 0 | DO37: 0 | DP37: 1 | DQ37: 1 | DU37: 1010 | DV37: 100 шт. | DW37: 100 шт. | DX37: 100 | EE37: 59298928 | EF37: 30 | EG37: Строительные работы | EH37: 0 | EJ37: 1 | EK37: 22 | EL37: ТСН-2001.3-17. Водопровод и канализация - внутренние устройства | EM37: ТСН-2001.3-17-1 | EO37: Поправка: Гл.12.Прил.8.п.8. 5_12.00.01.11.003 Поправка: Гл.6.Прил.2.2.п.2.2.6_06.00.01.07.001 | EQ37: 0 | ER37: 2306.6 | ES37: 2202.04 | ET37: 8.97 | EU37: 1.01 | EV37: 95.59 | EW37: 8.58 | EX37: 0 | EY37: 0 | FQ37: 0 | FR37: 0 | FS37: 0 | FX37: 109 | FY37: 61 | GD37: 1 | GF37: -907614113 | GG37: 2 | GH37: 1 | GI37: 2 | GJ37: 0 | GK37: 0 | GL37: =ROUND(IF(AND(BH37=3,BI37=3,FS37<>0),P37,0),2) -> 0 | GM37: =ROUND(O37+X37+Y37,2)+GX37 -> 210.85 | GN37: =IF(OR(BI37=0,BI37=1),GM37-GX37,0) -> 210.85 | GO37: =IF(BI37=2,GM37-GX37,0) -> 0 | GP37: =IF(BI37=4,GM37-GX37,0) -> 0 | GR37: 0 | GS37: 3 | GT37: 0 | GV37: =ROUND((GT37),6) -> 0 | GW37: 1 | GX37: =ROUND(HC37*I37,2) -> 0 | HA37: 0 | HB37: 0 | HC37: =GV37*GW37 -> 0 | HS37: 0 | IK37: 0
A39: 51 | B39: =B24 -> 1 | C39: =A24 -> 4 | D39: =ROW(A24) -> 24 | F39: =IF(F24<>"",F24,"") | G39: =IF(G24<>"",G24,"") -> Оборудование санузла для МГН | H39: 0 | O39: =ROUND(AB39,2) -> 426.47 | P39: =ROUND(AC39,2) -> 393.93 | Q39: =ROUND(AD39,2) -> 1.33 | R39: =ROUND(AE39,2) -> 0.12 | S39: =ROUND(AF39,2) -> 31.21 | T39: =ROUND(AG39,2) -> 0 | U39: =AH39 -> 2.6850676 | V39: =AI39 -> 0 | W39: =ROUND(AJ39,2) -> 0 | X39: =ROUND(AK39,2) -> 34.15 | Y39: =ROUND(AL39,2) -> 19.12 | AB39: =ROUND(SUMIF(AA28:AA37,"=59499218",O28:O37),2) -> 426.47 | AC39: =ROUND(SUMIF(AA28:AA37,"=59499218",P28:P37),2) -> 393.93 | AD39: =ROUND(SUMIF(AA28:AA37,"=59499218",Q28:Q37),2) -> 1.33 | AE39: =ROUND(SUMIF(AA28:AA37,"=59499218",R28:R37),2) -> 0.12 | AF39: =ROUND(SUMIF(AA28:AA37,"=59499218",S28:S37),2) -> 31.21 | AG39: =ROUND(SUMIF(AA28:AA37,"=59499218",T28:T37),2) -> 0 | AH39: =SUMIF(AA28:AA37,"=59499218",U28:U37) -> 2.6850676 | AI39: =SUMIF(AA28:AA37,"=59499218",V28:V37) -> 0 | AJ39: =ROUND(SUMIF(AA28:AA37,"=59499218",W28:W37),2) -> 0 | AK39: =ROUND(SUMIF(AA28:AA37,"=59499218",X28:X37),2) -> 34.15 | AL39: =ROUND(SUMIF(AA28:AA37,"=59499218",Y28:Y37),2) -> 19.12 | AO39: =ROUND(BX39,2) -> 0 | AP39: =ROUND(BY39,2) -> 0 | AQ39: =ROUND(BZ39,2) -> 0 | AR39: =ROUND(CA39,2) -> 479.74 | AS39: =ROUND(CB39,2) -> 479.74 | AT39: =ROUND(CC39,2) -> 0 | AU39: =ROUND(CD39,2) -> 0 | AV39: =ROUND(CE39,2) -> 393.93 | ... BD39: =ROUND(CM39,2) -> 0 | BX39: =ROUND(SUMIF(AA28:AA37,"=59499218",FQ28:FQ37),2) -> 0 | BY39: =ROUND(SUMIF(AA28:AA37,"=59499218",FR28:FR37),2) -> 0 | BZ39: =ROUND(SUMIF(AA28:AA37,"=59499218",GL28:GL37),2) -> 0 | CA39: =ROUND(SUMIF(AA28:AA37,"=59499218",GM28:GM37),2) -> 479.74 | CB39: =ROUND(SUMIF(AA28:AA37,"=59499218",GN28:GN37),2) -> 479.74 | CC39: =ROUND(SUMIF(AA28:AA37,"=59499218",GO28:GO37),2) -> 0 | CD39: =ROUND(SUMIF(AA28:AA37,"=59499218",GP28:GP37),2) -> 0 | CE39: =AC39-BX39 -> 393.93 | CF39: =AC39-BY39 -> 393.93 | CG39: =BX39-BZ39 -> 0 | CH39: =AC39-BX39-BY39+BZ39 -> 393.93 | CI39: =BY39-BZ39 -> 0 | CJ39: =ROUND(SUMIF(AA28:AA37,"=59499218",GX28:GX37),2) -> 0 | CK39: =ROUND(SUMIF(AA28:AA37,"=59499218",GY28:GY37),2) -> 0 | CL39: =ROUND(SUMIF(AA28:AA37,"=59499218",GZ28:GZ37),2) -> 0 | CM39: =ROUND(SUMIF(AA28:AA37,"=59499218",HD28:HD37),2) -> 0 | DG39: =ROUND(DT39,2) -> 2031.16 | DH39: =ROUND(DU39,2) -> 297.11 | DI39: =ROUND(DV39,2) -> 17.82 | DJ39: =ROUND(DW39,2) -> 6.6 | DK39: =ROUND(DX39,2) -> 1716.23 | DL39: =ROUND(DY39,2) -> 0 | DM39: =DZ39 -> 2.6850676 | DN39: =EA39 -> 0 | DO39: =ROUND(EB39,2) -> 0 | DP39: =ROUND(EC39,2) -> 1877.88 | DQ39: =ROUND(ED39,2) -> 1050.93 | DT39: =ROUND(SUMIF(AA28:AA37,"=59499215",O28:O37),2) -> 2031.16 | DU39: =ROUND(SUMIF(AA28:AA37,"=59499215",P28:P37),2) -> 297.11 | DV39: =ROUND(SUMIF(AA28:AA37,"=59499215",Q28:Q37),2) -> 17.82 | DW39: =ROUND(SUMIF(AA28:AA37,"=59499215",R28:R37),2) -> 6.6 | DX39: =ROUND(SUMIF(AA28:AA37,"=59499215",S28:S37),2) -> 1716.23 | DY39: =ROUND(SUMIF(AA28:AA37,"=59499215",T28:T37),2) -> 0 | DZ39: =SUMIF(AA28:AA37,"=59499215",U28:U37) -> 2.6850676 | EA39: =SUMIF(AA28:AA37,"=59499215",V28:V37) -> 0 | EB39: =ROUND(SUMIF(AA28:AA37,"=59499215",W28:W37),2) -> 0 | EC39: =ROUND(SUMIF(AA28:AA37,"=59499215",X28:X37),2) -> 1877.88 | ED39: =ROUND(SUMIF(AA28:AA37,"=59499215",Y28:Y37),2) -> 1050.93 | EG39: =ROUND(FP39,2) -> 0 | EH39: =ROUND(FQ39,2) -> 0 | EI39: =ROUND(FR39,2) -> 0 | EJ39: =ROUND(FS39,2) -> 4959.97 | EK39: =ROUND(FT39,2) -> 4959.97 | EL39: =ROUND(FU39,2) -> 0 | EM39: =ROUND(FV39,2) -> 0 | EN39: =ROUND(FW39,2) -> 297.11 | ... EV39: =ROUND(GE39,2) -> 0 | FP39: =ROUND(SUMIF(AA28:AA37,"=59499215",FQ28:FQ37),2) -> 0 | FQ39: =ROUND(SUMIF(AA28:AA37,"=59499215",FR28:FR37),2) -> 0 | FR39: =ROUND(SUMIF(AA28:AA37,"=59499215",GL28:GL37),2) -> 0 | FS39: =ROUND(SUMIF(AA28:AA37,"=59499215",GM28:GM37),2) -> 4959.97 | FT39: =ROUND(SUMIF(AA28:AA37,"=59499215",GN28:GN37),2) -> 4959.97 | FU39: =ROUND(SUMIF(AA28:AA37,"=59499215",GO28:GO37),2) -> 0 | FV39: =ROUND(SUMIF(AA28:AA37,"=59499215",GP28:GP37),2) -> 0 | FW39: =DU39-FP39 -> 297.11 | FX39: =DU39-FQ39 -> 297.11 | FY39: =FP39-FR39 -> 0 | FZ39: =DU39-FP39-FQ39+FR39 -> 297.11 | GA39: =FQ39-FR39 -> 0 | GB39: =ROUND(SUMIF(AA28:AA37,"=59499215",GX28:GX37),2) -> 0 | GC39: =ROUND(SUMIF(AA28:AA37,"=59499215",GY28:GY37),2) -> 0 | GD39: =ROUND(SUMIF(AA28:AA37,"=59499215",GZ28:GZ37),2) -> 0 | GE39: =ROUND(SUMIF(AA28:AA37,"=59499215",HD28:HD37),2) -> 0 | GX39: 0
A41: 50 | B41: 0 | C41: 0 | D41: 1 | E41: 201 | F41: =ROUND(Source!O39,O41) -> 426.47 | G41: ПЗ | H41: Прямые затраты | K41: 201 | L41: 1 | M41: 3 | O41: 2 | P41: =ROUND(Source!DG39,O41) -> 2031.16 | W41: 426.47 | X41: 1 | Y41: 426.47 | Z41: 2031.16 | AA41: 1 | AB41: 2031.16
A42: 50 | B42: 0 | C42: 0 | D42: 1 | E42: 202 | F42: =ROUND(Source!P39,O42) -> 393.93 | G42: СтМатОб | H42: Стоимость материальных ресурсов (всего) | K42: 202 | L42: 2 | M42: 3 | O42: 2 | P42: =ROUND(Source!DH39,O42) -> 297.11 | W42: 393.93 | X42: 1 | Y42: 393.93 | Z42: 297.11 | AA42: 1 | AB42: 297.11
A43: 50 | B43: 0 | C43: 0 | D43: 1 | E43: 222 | F43: =ROUND(Source!AO39,O43) -> 0 | G43: СтМатОбЗак | H43: Стоимость материалов и оборудования заказчика | K43: 222 | L43: 3 | M43: 3 | O43: 2 | P43: =ROUND(Source!EG39,O43) -> 0 | W43: 0 | X43: 1 | Y43: 0 | Z43: 0 | AA43: 1 | AB43: 0
A44: 50 | B44: 0 | C44: 0 | D44: 1 | E44: 225 | F44: =ROUND(Source!AV39,O44) -> 393.93 | G44: СтМатОбПод | H44: Стоимость материалов и оборудования подрядчика | K44: 225 | L44: 4 | M44: 3 | O44: 2 | P44: =ROUND(Source!EN39,O44) -> 297.11 | W44: 393.93 | X44: 1 | Y44: 393.93 | Z44: 297.11 | AA44: 1 | AB44: 297.11
A45: 50 | B45: 0 | C45: 0 | D45: 1 | E45: 226 | F45: =ROUND(Source!AW39,O45) -> 393.93 | G45: СтМат | H45: Стоимость материалов (всего) | K45: 226 | L45: 5 | M45: 3 | O45: 2 | P45: =ROUND(Source!EO39,O45) -> 297.11 | W45: 393.93 | X45: 1 | Y45: 393.93 | Z45: 297.11 | AA45: 1 | AB45: 297.11
A46: 50 | B46: 0 | C46: 0 | D46: 1 | E46: 227 | F46: =ROUND(Source!AX39,O46) -> 0 | G46: СтМатЗак | H46: Стоимость материалов заказчика | K46: 227 | L46: 6 | M46: 3 | O46: 2 | P46: =ROUND(Source!EP39,O46) -> 0 | W46: 0 | X46: 1 | Y46: 0 | Z46: 0 | AA46: 1 | AB46: 0
A47: 50 | B47: 0 | C47: 0 | D47: 1 | E47: 228 | F47: =ROUND(Source!AY39,O47) -> 393.93 | G47: СтМатПод | H47: Стоимость материалов подрядчика | K47: 228 | L47: 7 | M47: 3 | O47: 2 | P47: =ROUND(Source!EQ39,O47) -> 297.11 | W47: 393.93 | X47: 1 | Y47: 393.93 | Z47: 297.11 | AA47: 1 | AB47: 297.11
A48: 50 | B48: 0 | C48: 0 | D48: 1 | E48: 216 | F48: =ROUND(Source!AP39,O48) -> 0 | G48: Оборуд | H48: Стоимость оборудования (всего) | K48: 216 | L48: 8 | M48: 3 | O48: 2 | P48: =ROUND(Source!EH39,O48) -> 0 | W48: 0 | X48: 1 | Y48: 0 | Z48: 0 | AA48: 1 | AB48: 0
A49: 50 | B49: 0 | C49: 0 | D49: 1 | E49: 223 | F49: =ROUND(Source!AQ39,O49) -> 0 | G49: ОборудЗак | H49: Стоимость оборудования заказчика | K49: 223 | L49: 9 | M49: 3 | O49: 2 | P49: =ROUND(Source!EI39,O49) -> 0 | W49: 0 | X49: 1 | Y49: 0 | Z49: 0 | AA49: 1 | AB49: 0
A50: 50 | B50: 0 | C50: 0 | D50: 1 | E50: 229 | F50: =ROUND(Source!AZ39,O50) -> 0 | G50: ОборудПод | H50: Стоимость оборудования подрядчика | K50: 229 | L50: 10 | M50: 3 | O50: 2 | P50: =ROUND(Source!ER39,O50) -> 0 | W50: 0 | X50: 1 | Y50: 0 | Z50: 0 | AA50: 1 | AB50: 0
A51: 50 | B51: 0 | C51: 0 | D51: 1 | E51: 203 | F51: =ROUND(Source!Q39,O51) -> 1.33 | G51: ЭММ | H51: Эксплуатация машин | K51: 203 | L51: 11 | M51: 3 | O51: 2 | P51: =ROUND(Source!DI39,O51) -> 17.82 | W51: 1.33 | X51: 1 | Y51: 1.33 | Z51: 17.82 | AA51: 1 | AB51: 17.82
A52: 50 | B52: 0 | C52: 0 | D52: 1 | E52: 231 | F52: =ROUND(Source!BB39,O52) -> 0 | G52: ЭММсНРиСП | H52: Эксплуатация машин по ТСН-2001.16 | K52: 231 | L52: 12 | M52: 3 | O52: 2 | P52: =ROUND(Source!ET39,O52) -> 0 | W52: 0 | X52: 1 | Y52: 0 | Z52: 0 | AA52: 1 | AB52: 0
A53: 50 | B53: 0 | C53: 0 | D53: 1 | E53: 204 | F53: =ROUND(Source!R39,O53) -> 0.12 | G53: ЗПМ | H53: ЗП машинистов | K53: 204 | L53: 13 | M53: 3 | O53: 2 | P53: =ROUND(Source!DJ39,O53) -> 6.6 | W53: 0.12 | X53: 1 | Y53: 0.12 | Z53: 6.6 | AA53: 1 | AB53: 6.6
A54: 50 | B54: 0 | C54: 0 | D54: 1 | E54: 205 | F54: =ROUND(Source!S39,O54) -> 31.21 | G54: ОЗП | H54: Основная ЗП рабочих | K54: 205 | L54: 14 | M54: 3 | O54: 2 | P54: =ROUND(Source!DK39,O54) -> 1716.23 | W54: 31.21 | X54: 1 | Y54: 31.21 | Z54: 1716.23 | AA54: 1 | AB54: 1716.23
A55: 50 | B55: 0 | C55: 0 | D55: 1 | E55: 232 | F55: =ROUND(Source!BC39,O55) -> 0 | G55: ОЗПсНРиСП | H55: Основная ЗП рабочих по ТСН-2001.16 | K55: 232 | L55: 15 | M55: 3 | O55: 2 | P55: =ROUND(Source!EU39,O55) -> 0 | W55: 0 | X55: 1 | Y55: 0 | Z55: 0 | AA55: 1 | AB55: 0
A56: 50 | B56: 0 | C56: 0 | D56: 1 | E56: 214 | F56: =ROUND(Source!AS39,O56) -> 479.74 | G56: Строит | H56: Строительные работы с НР и СП | K56: 214 | L56: 16 | M56: 3 | O56: 2 | P56: =ROUND(Source!EK39,O56) -> 4959.97 | W56: 479.74 | X56: 1 | Y56: 479.74 | Z56: 4959.97 | AA56: 1 | AB56: 4959.97
A57: 50 | B57: 0 | C57: 0 | D57: 1 | E57: 215 | F57: =ROUND(Source!AT39,O57) -> 0 | G57: Монтаж | H57: Монтажные работы с НР и СП | K57: 215 | L57: 17 | M57: 3 | O57: 2 | P57: =ROUND(Source!EL39,O57) -> 0 | W57: 0 | X57: 1 | Y57: 0 | Z57: 0 | AA57: 1 | AB57: 0
A58: 50 | B58: 0 | C58: 0 | D58: 1 | E58: 217 | F58: =ROUND(Source!AU39,O58) -> 0 | G58: Прочие | H58: Прочие работы с НР и СП | K58: 217 | L58: 18 | M58: 3 | O58: 2 | P58: =ROUND(Source!EM39,O58) -> 0 | W58: 0 | X58: 1 | Y58: 0 | Z58: 0 | AA58: 1 | AB58: 0
A59: 50 | B59: 0 | C59: 0 | D59: 1 | E59: 230 | F59: =ROUND(Source!BA39,O59) -> 0 | G59: ПрочиеЗатр | H59: Прочие затраты по ТСН-2001.16 | K59: 230 | L59: 19 | M59: 3 | O59: 2 | P59: =ROUND(Source!ES39,O59) -> 0 | W59: 0 | X59: 1 | Y59: 0 | Z59: 0 | AA59: 1 | AB59: 0
A60: 50 | B60: 0 | C60: 0 | D60: 1 | E60: 206 | F60: =ROUND(Source!T39,O60) -> 0 | G60: ВозврМат | H60: Возврат материалов | K60: 206 | L60: 20 | M60: 3 | O60: 2 | P60: =ROUND(Source!DL39,O60) -> 0 | W60: 0 | X60: 1 | Y60: 0 | Z60: 0 | AA60: 1 | AB60: 0
A61: 50 | B61: 0 | C61: 0 | D61: 1 | E61: 207 | F61: =Source!U39 -> 2.6850676 | G61: ТрудСтр | H61: Трудозатраты строителей | K61: 207 | L61: 21 | M61: 3 | O61: -1 | P61: =Source!DM39 -> 2.6850676 | W61: 2.6850676 | X61: 1 | Y61: 2.6850676 | Z61: 2.6850676 | AA61: 1 | AB61: 2.6850676
A62: 50 | B62: 0 | C62: 0 | D62: 1 | E62: 208 | F62: =Source!V39 -> 0 | G62: ТрудМаш | H62: Трудозатраты машинистов | K62: 208 | L62: 22 | M62: 3 | O62: -1 | P62: =Source!DN39 -> 0 | W62: 0 | X62: 1 | Y62: 0 | Z62: 0 | AA62: 1 | AB62: 0
A63: 50 | B63: 0 | C63: 0 | D63: 1 | E63: 209 | F63: =ROUND(Source!W39,O63) -> 0 | G63: ТранспМат | H63: Транспорт материалов | K63: 209 | L63: 23 | M63: 3 | O63: 2 | P63: =ROUND(Source!DO39,O63) -> 0 | W63: 0 | X63: 1 | Y63: 0 | Z63: 0 | AA63: 1 | AB63: 0
A64: 50 | B64: 0 | C64: 0 | D64: 1 | E64: 233 | F64: =ROUND(Source!BD39,O64) -> 0 | G64: Перевозка | H64: Перевозка грузов | K64: 233 | L64: 24 | M64: 3 | O64: 2 | P64: =ROUND(Source!EV39,O64) -> 0 | W64: 0 | X64: 1 | Y64: 0 | Z64: 0 | AA64: 1 | AB64: 0
A65: 50 | B65: 0 | C65: 0 | D65: 1 | E65: 210 | F65: =ROUND(Source!X39,O65) -> 34.15 | G65: НР | H65: Накладные расходы | K65: 210 | L65: 25 | M65: 3 | O65: 2 | P65: =ROUND(Source!DP39,O65) -> 1877.88 | W65: 34.15 | X65: 1 | Y65: 34.15 | Z65: 1877.88 | AA65: 1 | AB65: 1877.88
A66: 50 | B66: 0 | C66: 0 | D66: 1 | E66: 211 | F66: =ROUND(Source!Y39,O66) -> 19.12 | G66: СмПриб | H66: Сметная прибыль | K66: 211 | L66: 26 | M66: 3 | O66: 2 | P66: =ROUND(Source!DQ39,O66) -> 1050.93 | W66: 19.12 | X66: 1 | Y66: 19.12 | Z66: 1050.93 | AA66: 1 | AB66: 1050.93
A67: 50 | B67: 0 | C67: 0 | D67: 1 | E67: 224 | F67: =ROUND(Source!AR39,O67) -> 479.74 | G67: Всего | H67: Всего с НР и СП | K67: 224 | L67: 27 | M67: 3 | O67: 2 | P67: =ROUND(Source!EJ39,O67) -> 4959.97 | W67: 479.74 | X67: 1 | Y67: 479.74 | Z67: 4959.97 | AA67: 1 | AB67: 4959.97
A69: 4 | B69: 1 | D69: =ROW(A84) -> 84 | G69: Оборудование, не облагаемое НДС | I69: 0 | K69: -1 | S69: 0 | T69: 0 | V69: 2 | BX69: 0 | CJ69: 0
A71: 52 | B71: =B84 -> 1 | C71: =C84 -> 4 | D71: =D84 -> 69 | E71: =E84 -> 0 | F71: =F84 | G71: =G84 -> Оборудование, не облагаемое НДС | O71: =O84 -> 19804.83 | P71: =P84 -> 19804.83 | Q71: =Q84 -> 0 | R71: =R84 -> 0 | S71: =S84 -> 0 | T71: =T84 -> 0 | U71: =U84 -> 0 | V71: =V84 -> 0 | ... GX71: =GX84 -> 0
A73: 17 | B73: 1 | E73: 6 | F73: 13.3-11-72 | G73: Поручень реабилитационный откидной для установки около унитаза, габаритные размеры 700х700 мм. Материал сталь нержавеющая с полировкой, крепление к стене в трех точках, в комплекте: прокладки-амортизаторы резиновые, крепежные элементы | H73: КОМПЛЕКТ | I73: 1 | J73: 0 | K73: 1 | O73: =ROUND(CP73,2) -> 7974.05 | P73: =ROUND((ROUND((AC73*I73),2)*BC73),2) -> 7974.05 | Q73: =(ROUND((ROUND(((ET73)*AV73*I73),2)*BB73),2)+ROUND((ROUND(((AE73-(EU73))*AV73*I73),2)*BS73),2)) -> 0 | R73: =(ROUND((ROUND(((EU73)*AV73*I73),2)*BS73),2)+ROUND((ROUND(((AE73-(EU73))*AV73*I73),2)*BS73),2)) -> 0 | S73: =ROUND((ROUND((AF73*AV73*I73),2)*BA73),2) -> 0 | T73: =ROUND(CU73*I73,2) -> 0 | U73: =CV73*I73 -> 0 | V73: =CW73*I73 -> 0 | W73: =ROUND(CX73*I73,2) -> 0 | X73: =(ROUND((((S73+ROUND((ROUND(((EU73)*AV73*I73),2)*BS73),2))*AT73)/100),2)+ROUND(((ROUND((ROUND(((AE73-(EU73))*AV73*I73),2)*BS73),2)*AT73)/100),2)) -> 0 | Y73: =(ROUND((((S73+ROUND((ROUND(((EU73)*AV73*I73),2)*BS73),2))*AU73)/100),2)+ROUND(((ROUND((ROUND(((AE73-(EU73))*AV73*I73),2)*BS73),2)*AU73)/100),2)) -> 0 | AA73: 59499218 | AB73: =ROUND((AC73+AD73+AF73),6) -> 7974.05 | AC73: =ROUND((ES73),6) -> 7974.05 | AD73: =ROUND((((ET73)-(EU73))+AE73),6) -> 0 | AE73: =ROUND((EU73),6) -> 0 | AF73: =ROUND((EV73),6) -> 0 | AG73: =ROUND((AP73),6) -> 0 | AH73: =(EW73) -> 0 | AI73: =(EX73) -> 0 | AJ73: =(AS73) -> 0 | AK73: 7974.05 | AL73: 7974.05 | AM73: 0 | AN73: 0 | AO73: 0 | AP73: 0 | AQ73: 0 | AR73: 0 | AS73: 0 | AT73: 0 | AU73: 0 | AV73: 1 | AW73: 1 | AZ73: 1 | BA73: 1 | BB73: 1 | BC73: 1 | BH73: 3 | BI73: 3 | BM73: 746 | BN73: 59298886 | BP73: 0 | BQ73: 130 | BR73: 0 | BS73: 1 | BT73: 1 | BU73: 1 | BV73: 1 | BW73: 1 | BX73: 1 | BZ73: 0 | CA73: 0 | CE73: 1566 | CF73: 0 | CG73: 0 | CM73: 0 | CO73: 0 | CP73: =(P73+Q73+S73) -> 7974.05 | CQ73: =ROUND((ROUND((AC73*1),2)*BC73),2) -> 7974.05 | CR73: =(ROUND((ROUND(((ET73)*AV73*1),2)*BB73),2)+ROUND((ROUND(((AE73-(EU73))*AV73*1),2)*BS73),2)) -> 0 | CS73: =(ROUND((ROUND(((EU73)*AV73*1),2)*BS73),2)+ROUND((ROUND(((AE73-(EU73))*AV73*1),2)*BS73),2)) -> 0 | CT73: =ROUND((ROUND((AF73*AV73*1),2)*BA73),2) -> 0 | CU73: =AG73 -> 0 | CV73: =(AH73*AV73) -> 0 | CW73: =AI73 -> 0 | CX73: =AJ73 -> 0 | CY73: =(ROUND((((S73+ROUND((ROUND(((EU73)*AV73*1),2)*BS73),2))*AT73)/100),2)+ROUND(((ROUND((ROUND(((AE73-(EU73))*AV73*1),2)*BS73),2)*AT73)/100),2)) -> 0 | CZ73: =(ROUND((((S73+ROUND((ROUND(((EU73)*AV73*1),2)*BS73),2))*AU73)/100),2)+ROUND(((ROUND((ROUND(((AE73-(EU73))*AV73*1),2)*BS73),2)*AU73)/100),2)) -> 0 | DN73: 0 | DO73: 0 | DP73: 1 | DQ73: 1 | DU73: 1013 | DV73: КОМПЛЕКТ | DW73: КОМПЛЕКТ | DX73: 1 | EE73: 59299131 | EF73: 130 | EG73: Сметная стоимость оборудования | EH73: 0 | EJ73: 3 | EK73: 746 | EL73: ТСН-2001.13. Сметная стоимость оборудования | EM73: ТСН-2001.13 | EQ73: 0 | ER73: 7974.05 | ES73: 7974.05 | ET73: 0 | EU73: 0 | EV73: 0 | EW73: 0 | EX73: 0 | EY73: 0 | FQ73: 0 | FR73: =P73 -> 7974.05 | FS73: 0 | FX73: 0 | FY73: 0 | GD73: 1 | GF73: 929854053 | GG73: 2 | GH73: 1 | GI73: -2 | GJ73: 0 | GK73: 0 | GL73: =ROUND(IF(AND(BH73=3,BI73=3,FS73<>0),P73,0),2) -> 0 | GM73: =ROUND(O73+X73+Y73,2)+GX73 -> 7974.05 | GN73: =IF(OR(BI73=0,BI73=1),GM73-GX73,0) -> 0 | GO73: =IF(BI73=2,GM73-GX73,0) -> 0 | GP73: =IF(BI73=4,GM73-GX73,0) -> 0 | GR73: 0 | GS73: 3 | GT73: 0 | GV73: =ROUND((GT73),6) -> 0 | GW73: 1 | GX73: =ROUND(HC73*I73,2) -> 0 | HA73: 0 | HB73: 0 | HC73: =GV73*GW73 -> 0 | HS73: 0 | IK73: 0
A74: 17 | B74: 1 | E74: 6 | F74: 13.3-11-72 | G74: Поручень реабилитационный откидной для установки около унитаза, габаритные размеры 700х700 мм. Материал сталь нержавеющая с полировкой, крепление к стене в трех точках, в комплекте: прокладки-амортизаторы резиновые, крепежные элементы | H74: КОМПЛЕКТ | I74: 1 | J74: 0 | K74: 1 | O74: =ROUND(CP74,2) -> 20573.05 | P74: =ROUND((ROUND((AC74*I74),2)*BC74),2) -> 20573.05 | Q74: =(ROUND((ROUND(((ET74)*AV74*I74),2)*BB74),2)+ROUND((ROUND(((AE74-(EU74))*AV74*I74),2)*BS74),2)) -> 0 | R74: =(ROUND((ROUND(((EU74)*AV74*I74),2)*BS74),2)+ROUND((ROUND(((AE74-(EU74))*AV74*I74),2)*BS74),2)) -> 0 | S74: =ROUND((ROUND((AF74*AV74*I74),2)*BA74),2) -> 0 | T74: =ROUND(CU74*I74,2) -> 0 | U74: =CV74*I74 -> 0 | V74: =CW74*I74 -> 0 | W74: =ROUND(CX74*I74,2) -> 0 | X74: =(ROUND((((S74+ROUND((ROUND(((EU74)*AV74*I74),2)*BS74),2))*AT74)/100),2)+ROUND(((ROUND((ROUND(((AE74-(EU74))*AV74*I74),2)*BS74),2)*AT74)/100),2)) -> 0 | Y74: =(ROUND((((S74+ROUND((ROUND(((EU74)*AV74*I74),2)*BS74),2))*AU74)/100),2)+ROUND(((ROUND((ROUND(((AE74-(EU74))*AV74*I74),2)*BS74),2)*AU74)/100),2)) -> 0 | AA74: 59499215 | AB74: =ROUND((AC74+AD74+AF74),6) -> 7974.05 | AC74: =ROUND((ES74),6) -> 7974.05 | AD74: =ROUND((((ET74)-(EU74))+AE74),6) -> 0 | AE74: =ROUND((EU74),6) -> 0 | AF74: =ROUND((EV74),6) -> 0 | AG74: =ROUND((AP74),6) -> 0 | AH74: =(EW74) -> 0 | AI74: =(EX74) -> 0 | AJ74: =(AS74) -> 0 | AK74: 7974.05 | AL74: 7974.05 | AM74: 0 | AN74: 0 | AO74: 0 | AP74: 0 | AQ74: 0 | AR74: 0 | AS74: 0 | AT74: 0 | AU74: 0 | AV74: 1 | AW74: 1 | AZ74: 1 | BA74: 1 | BB74: 1 | BC74: 2.58 | BH74: 3 | BI74: 3 | BM74: 746 | BN74: 59298886 | BP74: 0 | BQ74: 130 | BR74: 0 | BS74: 1 | BT74: 1 | BU74: 1 | BV74: 1 | BW74: 1 | BX74: 1 | BZ74: 0 | CA74: 0 | CE74: 1566 | CF74: 0 | CG74: 0 | CM74: 0 | CO74: 0 | CP74: =(P74+Q74+S74) -> 20573.05 | CQ74: =ROUND((ROUND((AC74*1),2)*BC74),2) -> 20573.05 | CR74: =(ROUND((ROUND(((ET74)*AV74*1),2)*BB74),2)+ROUND((ROUND(((AE74-(EU74))*AV74*1),2)*BS74),2)) -> 0 | CS74: =(ROUND((ROUND(((EU74)*AV74*1),2)*BS74),2)+ROUND((ROUND(((AE74-(EU74))*AV74*1),2)*BS74),2)) -> 0 | CT74: =ROUND((ROUND((AF74*AV74*1),2)*BA74),2) -> 0 | CU74: =AG74 -> 0 | CV74: =(AH74*AV74) -> 0 | CW74: =AI74 -> 0 | CX74: =AJ74 -> 0 | CY74: =(ROUND((((S74+ROUND((ROUND(((EU74)*AV74*1),2)*BS74),2))*AT74)/100),2)+ROUND(((ROUND((ROUND(((AE74-(EU74))*AV74*1),2)*BS74),2)*AT74)/100),2)) -> 0 | CZ74: =(ROUND((((S74+ROUND((ROUND(((EU74)*AV74*1),2)*BS74),2))*AU74)/100),2)+ROUND(((ROUND((ROUND(((AE74-(EU74))*AV74*1),2)*BS74),2)*AU74)/100),2)) -> 0 | DN74: 0 | DO74: 0 | DP74: 1 | DQ74: 1 | DU74: 1013 | DV74: КОМПЛЕКТ | DW74: КОМПЛЕКТ | DX74: 1 | EE74: 59299131 | EF74: 130 | EG74: Сметная стоимость оборудования | EH74: 0 | EJ74: 3 | EK74: 746 | EL74: ТСН-2001.13. Сметная стоимость оборудования | EM74: ТСН-2001.13 | EQ74: 0 | ER74: 7974.05 | ES74: 7974.05 | ET74: 0 | EU74: 0 | EV74: 0 | EW74: 0 | EX74: 0 | EY74: 0 | FQ74: 0 | FR74: =P74 -> 20573.05 | FS74: 0 | FX74: 0 | FY74: 0 | GD74: 1 | GF74: 929854053 | GG74: 2 | GH74: 1 | GI74: 2 | GJ74: 0 | GK74: 0 | GL74: =ROUND(IF(AND(BH74=3,BI74=3,FS74<>0),P74,0),2) -> 0 | GM74: =ROUND(O74+X74+Y74,2)+GX74 -> 20573.05 | GN74: =IF(OR(BI74=0,BI74=1),GM74-GX74,0) -> 0 | GO74: =IF(BI74=2,GM74-GX74,0) -> 0 | GP74: =IF(BI74=4,GM74-GX74,0) -> 0 | GR74: 0 | GS74: 3 | GT74: 0 | GV74: =ROUND((GT74),6) -> 0 | GW74: 1 | GX74: =ROUND(HC74*I74,2) -> 0 | HA74: 0 | HB74: 0 | HC74: =GV74*GW74 -> 0 | HS74: 0 | IK74: 0
A75: 17 | B75: 1 | E75: 7 | F75: 13.3-11-78 | G75: Поручень реабилитационный настенный, угловой, габаритные размеры 700х700 мм/ 600х600 мм | H75: КОМПЛЕКТ | I75: =ROUND(1+1,9) -> 2 | J75: 0 | K75: =ROUND(1+1,9) -> 2 | O75: =ROUND(CP75,2) -> 5920.6 | P75: =ROUND((ROUND((AC75*I75),2)*BC75),2) -> 5920.6 | Q75: =(ROUND((ROUND(((ET75)*AV75*I75),2)*BB75),2)+ROUND((ROUND(((AE75-(EU75))*AV75*I75),2)*BS75),2)) -> 0 | R75: =(ROUND((ROUND(((EU75)*AV75*I75),2)*BS75),2)+ROUND((ROUND(((AE75-(EU75))*AV75*I75),2)*BS75),2)) -> 0 | S75: =ROUND((ROUND((AF75*AV75*I75),2)*BA75),2) -> 0 | T75: =ROUND(CU75*I75,2) -> 0 | U75: =CV75*I75 -> 0 | V75: =CW75*I75 -> 0 | W75: =ROUND(CX75*I75,2) -> 0 | X75: =(ROUND((((S75+ROUND((ROUND(((EU75)*AV75*I75),2)*BS75),2))*AT75)/100),2)+ROUND(((ROUND((ROUND(((AE75-(EU75))*AV75*I75),2)*BS75),2)*AT75)/100),2)) -> 0 | Y75: =(ROUND((((S75+ROUND((ROUND(((EU75)*AV75*I75),2)*BS75),2))*AU75)/100),2)+ROUND(((ROUND((ROUND(((AE75-(EU75))*AV75*I75),2)*BS75),2)*AU75)/100),2)) -> 0 | AA75: 59499218 | AB75: =ROUND((AC75+AD75+AF75),6) -> 2960.3 | AC75: =ROUND((ES75),6) -> 2960.3 | AD75: =ROUND((((ET75)-(EU75))+AE75),6) -> 0 | AE75: =ROUND((EU75),6) -> 0 | AF75: =ROUND((EV75),6) -> 0 | AG75: =ROUND((AP75),6) -> 0 | AH75: =(EW75) -> 0 | AI75: =(EX75) -> 0 | AJ75: =(AS75) -> 0 | AK75: 2960.3 | AL75: 2960.3 | AM75: 0 | AN75: 0 | AO75: 0 | AP75: 0 | AQ75: 0 | AR75: 0 | AS75: 0 | AT75: 0 | AU75: 0 | AV75: 1 | AW75: 1 | AZ75: 1 | BA75: 1 | BB75: 1 | BC75: 1 | BH75: 3 | BI75: 3 | BM75: 746 | BN75: 59298886 | BP75: 0 | BQ75: 130 | BR75: 0 | BS75: 1 | BT75: 1 | BU75: 1 | BV75: 1 | BW75: 1 | BX75: 1 | BZ75: 0 | CA75: 0 | CE75: 1566 | CF75: 0 | CG75: 0 | CM75: 0 | CO75: 0 | CP75: =(P75+Q75+S75) -> 5920.6 | CQ75: =ROUND((ROUND((AC75*1),2)*BC75),2) -> 2960.3 | CR75: =(ROUND((ROUND(((ET75)*AV75*1),2)*BB75),2)+ROUND((ROUND(((AE75-(EU75))*AV75*1),2)*BS75),2)) -> 0 | CS75: =(ROUND((ROUND(((EU75)*AV75*1),2)*BS75),2)+ROUND((ROUND(((AE75-(EU75))*AV75*1),2)*BS75),2)) -> 0 | CT75: =ROUND((ROUND((AF75*AV75*1),2)*BA75),2) -> 0 | CU75: =AG75 -> 0 | CV75: =(AH75*AV75) -> 0 | CW75: =AI75 -> 0 | CX75: =AJ75 -> 0 | CY75: =(ROUND((((S75+ROUND((ROUND(((EU75)*AV75*1),2)*BS75),2))*AT75)/100),2)+ROUND(((ROUND((ROUND(((AE75-(EU75))*AV75*1),2)*BS75),2)*AT75)/100),2)) -> 0 | CZ75: =(ROUND((((S75+ROUND((ROUND(((EU75)*AV75*1),2)*BS75),2))*AU75)/100),2)+ROUND(((ROUND((ROUND(((AE75-(EU75))*AV75*1),2)*BS75),2)*AU75)/100),2)) -> 0 | DN75: 0 | DO75: 0 | DP75: 1 | DQ75: 1 | DU75: 1013 | DV75: КОМПЛЕКТ | DW75: КОМПЛЕКТ | DX75: 1 | EE75: 59299131 | EF75: 130 | EG75: Сметная стоимость оборудования | EH75: 0 | EJ75: 3 | EK75: 746 | EL75: ТСН-2001.13. Сметная стоимость оборудования | EM75: ТСН-2001.13 | EQ75: 0 | ER75: 2960.3 | ES75: 2960.3 | ET75: 0 | EU75: 0 | EV75: 0 | EW75: 0 | EX75: 0 | EY75: 0 | FQ75: 0 | FR75: =P75 -> 5920.6 | FS75: 0 | FX75: 0 | FY75: 0 | GD75: 1 | GF75: 334117407 | GG75: 2 | GH75: 1 | GI75: -2 | GJ75: 0 | GK75: 0 | GL75: =ROUND(IF(AND(BH75=3,BI75=3,FS75<>0),P75,0),2) -> 0 | GM75: =ROUND(O75+X75+Y75,2)+GX75 -> 5920.6 | GN75: =IF(OR(BI75=0,BI75=1),GM75-GX75,0) -> 0 | GO75: =IF(BI75=2,GM75-GX75,0) -> 0 | GP75: =IF(BI75=4,GM75-GX75,0) -> 0 | GR75: 0 | GS75: 3 | GT75: 0 | GV75: =ROUND((GT75),6) -> 0 | GW75: 1 | GX75: =ROUND(HC75*I75,2) -> 0 | HA75: 0 | HB75: 0 | HC75: =GV75*GW75 -> 0 | HS75: 0 | IK75: 0
A76: 17 | B76: 1 | E76: 7 | F76: 13.3-11-78 | G76: Поручень реабилитационный настенный, угловой, габаритные размеры 700х700 мм/ 600х600 мм | H76: КОМПЛЕКТ | I76: =ROUND(1+1,9) -> 2 | J76: 0 | K76: =ROUND(1+1,9) -> 2 | O76: =ROUND(CP76,2) -> 20722.1 | P76: =ROUND((ROUND((AC76*I76),2)*BC76),2) -> 20722.1 | Q76: =(ROUND((ROUND(((ET76)*AV76*I76),2)*BB76),2)+ROUND((ROUND(((AE76-(EU76))*AV76*I76),2)*BS76),2)) -> 0 | R76: =(ROUND((ROUND(((EU76)*AV76*I76),2)*BS76),2)+ROUND((ROUND(((AE76-(EU76))*AV76*I76),2)*BS76),2)) -> 0 | S76: =ROUND((ROUND((AF76*AV76*I76),2)*BA76),2) -> 0 | T76: =ROUND(CU76*I76,2) -> 0 | U76: =CV76*I76 -> 0 | V76: =CW76*I76 -> 0 | W76: =ROUND(CX76*I76,2) -> 0 | X76: =(ROUND((((S76+ROUND((ROUND(((EU76)*AV76*I76),2)*BS76),2))*AT76)/100),2)+ROUND(((ROUND((ROUND(((AE76-(EU76))*AV76*I76),2)*BS76),2)*AT76)/100),2)) -> 0 | Y76: =(ROUND((((S76+ROUND((ROUND(((EU76)*AV76*I76),2)*BS76),2))*AU76)/100),2)+ROUND(((ROUND((ROUND(((AE76-(EU76))*AV76*I76),2)*BS76),2)*AU76)/100),2)) -> 0 | AA76: 59499215 | AB76: =ROUND((AC76+AD76+AF76),6) -> 2960.3 | AC76: =ROUND((ES76),6) -> 2960.3 | AD76: =ROUND((((ET76)-(EU76))+AE76),6) -> 0 | AE76: =ROUND((EU76),6) -> 0 | AF76: =ROUND((EV76),6) -> 0 | AG76: =ROUND((AP76),6) -> 0 | AH76: =(EW76) -> 0 | AI76: =(EX76) -> 0 | AJ76: =(AS76) -> 0 | AK76: 2960.3 | AL76: 2960.3 | AM76: 0 | AN76: 0 | AO76: 0 | AP76: 0 | AQ76: 0 | AR76: 0 | AS76: 0 | AT76: 0 | AU76: 0 | AV76: 1 | AW76: 1 | AZ76: 1 | BA76: 1 | BB76: 1 | BC76: 3.5 | BH76: 3 | BI76: 3 | BM76: 746 | BN76: 59298886 | BP76: 0 | BQ76: 130 | BR76: 0 | BS76: 1 | BT76: 1 | BU76: 1 | BV76: 1 | BW76: 1 | BX76: 1 | BZ76: 0 | CA76: 0 | CE76: 1566 | CF76: 0 | CG76: 0 | CM76: 0 | CO76: 0 | CP76: =(P76+Q76+S76) -> 20722.1 | CQ76: =ROUND((ROUND((AC76*1),2)*BC76),2) -> 10361.05 | CR76: =(ROUND((ROUND(((ET76)*AV76*1),2)*BB76),2)+ROUND((ROUND(((AE76-(EU76))*AV76*1),2)*BS76),2)) -> 0 | CS76: =(ROUND((ROUND(((EU76)*AV76*1),2)*BS76),2)+ROUND((ROUND(((AE76-(EU76))*AV76*1),2)*BS76),2)) -> 0 | CT76: =ROUND((ROUND((AF76*AV76*1),2)*BA76),2) -> 0 | CU76: =AG76 -> 0 | CV76: =(AH76*AV76) -> 0 | CW76: =AI76 -> 0 | CX76: =AJ76 -> 0 | CY76: =(ROUND((((S76+ROUND((ROUND(((EU76)*AV76*1),2)*BS76),2))*AT76)/100),2)+ROUND(((ROUND((ROUND(((AE76-(EU76))*AV76*1),2)*BS76),2)*AT76)/100),2)) -> 0 | CZ76: =(ROUND((((S76+ROUND((ROUND(((EU76)*AV76*1),2)*BS76),2))*AU76)/100),2)+ROUND(((ROUND((ROUND(((AE76-(EU76))*AV76*1),2)*BS76),2)*AU76)/100),2)) -> 0 | DN76: 0 | DO76: 0 | DP76: 1 | DQ76: 1 | DU76: 1013 | DV76: КОМПЛЕКТ | DW76: КОМПЛЕКТ | DX76: 1 | EE76: 59299131 | EF76: 130 | EG76: Сметная стоимость оборудования | EH76: 0 | EJ76: 3 | EK76: 746 | EL76: ТСН-2001.13. Сметная стоимость оборудования | EM76: ТСН-2001.13 | EQ76: 0 | ER76: 2960.3 | ES76: 2960.3 | ET76: 0 | EU76: 0 | EV76: 0 | EW76: 0 | EX76: 0 | EY76: 0 | FQ76: 0 | FR76: =P76 -> 20722.1 | FS76: 0 | FX76: 0 | FY76: 0 | GD76: 1 | GF76: 334117407 | GG76: 2 | GH76: 1 | GI76: 2 | GJ76: 0 | GK76: 0 | GL76: =ROUND(IF(AND(BH76=3,BI76=3,FS76<>0),P76,0),2) -> 0 | GM76: =ROUND(O76+X76+Y76,2)+GX76 -> 20722.1 | GN76: =IF(OR(BI76=0,BI76=1),GM76-GX76,0) -> 0 | GO76: =IF(BI76=2,GM76-GX76,0) -> 0 | GP76: =IF(BI76=4,GM76-GX76,0) -> 0 | GR76: 0 | GS76: 3 | GT76: 0 | GV76: =ROUND((GT76),6) -> 0 | GW76: 1 | GX76: =ROUND(HC76*I76,2) -> 0 | HA76: 0 | HB76: 0 | HC76: =GV76*GW76 -> 0 | HS76: 0 | IK76: 0
A77: 17 | B77: 1 | E77: 8 | F77: 13.3-11-77 | G77: Поручень реабилитационный настенный, габаритные размеры 1500х90 мм/ 1200х120 мм | H77: КОМПЛЕКТ | I77: 1 | J77: 0 | K77: 1 | O77: =ROUND(CP77,2) -> 2991.57 | P77: =ROUND((ROUND((AC77*I77),2)*BC77),2) -> 2991.57 | Q77: =(ROUND((ROUND(((ET77)*AV77*I77),2)*BB77),2)+ROUND((ROUND(((AE77-(EU77))*AV77*I77),2)*BS77),2)) -> 0 | R77: =(ROUND((ROUND(((EU77)*AV77*I77),2)*BS77),2)+ROUND((ROUND(((AE77-(EU77))*AV77*I77),2)*BS77),2)) -> 0 | S77: =ROUND((ROUND((AF77*AV77*I77),2)*BA77),2) -> 0 | T77: =ROUND(CU77*I77,2) -> 0 | U77: =CV77*I77 -> 0 | V77: =CW77*I77 -> 0 | W77: =ROUND(CX77*I77,2) -> 0 | X77: =(ROUND((((S77+ROUND((ROUND(((EU77)*AV77*I77),2)*BS77),2))*AT77)/100),2)+ROUND(((ROUND((ROUND(((AE77-(EU77))*AV77*I77),2)*BS77),2)*AT77)/100),2)) -> 0 | Y77: =(ROUND((((S77+ROUND((ROUND(((EU77)*AV77*I77),2)*BS77),2))*AU77)/100),2)+ROUND(((ROUND((ROUND(((AE77-(EU77))*AV77*I77),2)*BS77),2)*AU77)/100),2)) -> 0 | AA77: 59499218 | AB77: =ROUND((AC77+AD77+AF77),6) -> 2991.57 | AC77: =ROUND((ES77),6) -> 2991.57 | AD77: =ROUND((((ET77)-(EU77))+AE77),6) -> 0 | AE77: =ROUND((EU77),6) -> 0 | AF77: =ROUND((EV77),6) -> 0 | AG77: =ROUND((AP77),6) -> 0 | AH77: =(EW77) -> 0 | AI77: =(EX77) -> 0 | AJ77: =(AS77) -> 0 | AK77: 2991.57 | AL77: 2991.57 | AM77: 0 | AN77: 0 | AO77: 0 | AP77: 0 | AQ77: 0 | AR77: 0 | AS77: 0 | AT77: 0 | AU77: 0 | AV77: 1 | AW77: 1 | AZ77: 1 | BA77: 1 | BB77: 1 | BC77: 1 | BH77: 3 | BI77: 3 | BM77: 746 | BN77: 59298886 | BP77: 0 | BQ77: 130 | BR77: 0 | BS77: 1 | BT77: 1 | BU77: 1 | BV77: 1 | BW77: 1 | BX77: 1 | BZ77: 0 | CA77: 0 | CE77: 1566 | CF77: 0 | CG77: 0 | CM77: 0 | CO77: 0 | CP77: =(P77+Q77+S77) -> 2991.57 | CQ77: =ROUND((ROUND((AC77*1),2)*BC77),2) -> 2991.57 | CR77: =(ROUND((ROUND(((ET77)*AV77*1),2)*BB77),2)+ROUND((ROUND(((AE77-(EU77))*AV77*1),2)*BS77),2)) -> 0 | CS77: =(ROUND((ROUND(((EU77)*AV77*1),2)*BS77),2)+ROUND((ROUND(((AE77-(EU77))*AV77*1),2)*BS77),2)) -> 0 | CT77: =ROUND((ROUND((AF77*AV77*1),2)*BA77),2) -> 0 | CU77: =AG77 -> 0 | CV77: =(AH77*AV77) -> 0 | CW77: =AI77 -> 0 | CX77: =AJ77 -> 0 | CY77: =(ROUND((((S77+ROUND((ROUND(((EU77)*AV77*1),2)*BS77),2))*AT77)/100),2)+ROUND(((ROUND((ROUND(((AE77-(EU77))*AV77*1),2)*BS77),2)*AT77)/100),2)) -> 0 | CZ77: =(ROUND((((S77+ROUND((ROUND(((EU77)*AV77*1),2)*BS77),2))*AU77)/100),2)+ROUND(((ROUND((ROUND(((AE77-(EU77))*AV77*1),2)*BS77),2)*AU77)/100),2)) -> 0 | DN77: 0 | DO77: 0 | DP77: 1 | DQ77: 1 | DU77: 1013 | DV77: КОМПЛЕКТ | DW77: КОМПЛЕКТ | DX77: 1 | EE77: 59299131 | EF77: 130 | EG77: Сметная стоимость оборудования | EH77: 0 | EJ77: 3 | EK77: 746 | EL77: ТСН-2001.13. Сметная стоимость оборудования | EM77: ТСН-2001.13 | EQ77: 0 | ER77: 2991.57 | ES77: 2991.57 | ET77: 0 | EU77: 0 | EV77: 0 | EW77: 0 | EX77: 0 | EY77: 0 | FQ77: 0 | FR77: =P77 -> 2991.57 | FS77: 0 | FX77: 0 | FY77: 0 | GD77: 1 | GF77: 576583559 | GG77: 2 | GH77: 1 | GI77: -2 | GJ77: 0 | GK77: 0 | GL77: =ROUND(IF(AND(BH77=3,BI77=3,FS77<>0),P77,0),2) -> 0 | GM77: =ROUND(O77+X77+Y77,2)+GX77 -> 2991.57 | GN77: =IF(OR(BI77=0,BI77=1),GM77-GX77,0) -> 0 | GO77: =IF(BI77=2,GM77-GX77,0) -> 0 | GP77: =IF(BI77=4,GM77-GX77,0) -> 0 | GR77: 0 | GS77: 3 | GT77: 0 | GV77: =ROUND((GT77),6) -> 0 | GW77: 1 | GX77: =ROUND(HC77*I77,2) -> 0 | HA77: 0 | HB77: 0 | HC77: =GV77*GW77 -> 0 | HS77: 0 | IK77: 0
A78: 17 | B78: 1 | E78: 8 | F78: 13.3-11-77 | G78: Поручень реабилитационный настенный, габаритные размеры 1500х90 мм/ 1200х120 мм | H78: КОМПЛЕКТ | I78: 1 | J78: 0 | K78: 1 | O78: =ROUND(CP78,2) -> 10320.92 | P78: =ROUND((ROUND((AC78*I78),2)*BC78),2) -> 10320.92 | Q78: =(ROUND((ROUND(((ET78)*AV78*I78),2)*BB78),2)+ROUND((ROUND(((AE78-(EU78))*AV78*I78),2)*BS78),2)) -> 0 | R78: =(ROUND((ROUND(((EU78)*AV78*I78),2)*BS78),2)+ROUND((ROUND(((AE78-(EU78))*AV78*I78),2)*BS78),2)) -> 0 | S78: =ROUND((ROUND((AF78*AV78*I78),2)*BA78),2) -> 0 | T78: =ROUND(CU78*I78,2) -> 0 | U78: =CV78*I78 -> 0 | V78: =CW78*I78 -> 0 | W78: =ROUND(CX78*I78,2) -> 0 | X78: =(ROUND((((S78+ROUND((ROUND(((EU78)*AV78*I78),2)*BS78),2))*AT78)/100),2)+ROUND(((ROUND((ROUND(((AE78-(EU78))*AV78*I78),2)*BS78),2)*AT78)/100),2)) -> 0 | Y78: =(ROUND((((S78+ROUND((ROUND(((EU78)*AV78*I78),2)*BS78),2))*AU78)/100),2)+ROUND(((ROUND((ROUND(((AE78-(EU78))*AV78*I78),2)*BS78),2)*AU78)/100),2)) -> 0 | AA78: 59499215 | AB78: =ROUND((AC78+AD78+AF78),6) -> 2991.57 | AC78: =ROUND((ES78),6) -> 2991.57 | AD78: =ROUND((((ET78)-(EU78))+AE78),6) -> 0 | AE78: =ROUND((EU78),6) -> 0 | AF78: =ROUND((EV78),6) -> 0 | AG78: =ROUND((AP78),6) -> 0 | AH78: =(EW78) -> 0 | AI78: =(EX78) -> 0 | AJ78: =(AS78) -> 0 | AK78: 2991.57 | AL78: 2991.57 | AM78: 0 | AN78: 0 | AO78: 0 | AP78: 0 | AQ78: 0 | AR78: 0 | AS78: 0 | AT78: 0 | AU78: 0 | AV78: 1 | AW78: 1 | AZ78: 1 | BA78: 1 | BB78: 1 | BC78: 3.45 | BH78: 3 | BI78: 3 | BM78: 746 | BN78: 59298886 | BP78: 0 | BQ78: 130 | BR78: 0 | BS78: 1 | BT78: 1 | BU78: 1 | BV78: 1 | BW78: 1 | BX78: 1 | BZ78: 0 | CA78: 0 | CE78: 1566 | CF78: 0 | CG78: 0 | CM78: 0 | CO78: 0 | CP78: =(P78+Q78+S78) -> 10320.92 | CQ78: =ROUND((ROUND((AC78*1),2)*BC78),2) -> 10320.92 | CR78: =(ROUND((ROUND(((ET78)*AV78*1),2)*BB78),2)+ROUND((ROUND(((AE78-(EU78))*AV78*1),2)*BS78),2)) -> 0 | CS78: =(ROUND((ROUND(((EU78)*AV78*1),2)*BS78),2)+ROUND((ROUND(((AE78-(EU78))*AV78*1),2)*BS78),2)) -> 0 | CT78: =ROUND((ROUND((AF78*AV78*1),2)*BA78),2) -> 0 | CU78: =AG78 -> 0 | CV78: =(AH78*AV78) -> 0 | CW78: =AI78 -> 0 | CX78: =AJ78 -> 0 | CY78: =(ROUND((((S78+ROUND((ROUND(((EU78)*AV78*1),2)*BS78),2))*AT78)/100),2)+ROUND(((ROUND((ROUND(((AE78-(EU78))*AV78*1),2)*BS78),2)*AT78)/100),2)) -> 0 | CZ78: =(ROUND((((S78+ROUND((ROUND(((EU78)*AV78*1),2)*BS78),2))*AU78)/100),2)+ROUND(((ROUND((ROUND(((AE78-(EU78))*AV78*1),2)*BS78),2)*AU78)/100),2)) -> 0 | DN78: 0 | DO78: 0 | DP78: 1 | DQ78: 1 | DU78: 1013 | DV78: КОМПЛЕКТ | DW78: КОМПЛЕКТ | DX78: 1 | EE78: 59299131 | EF78: 130 | EG78: Сметная стоимость оборудования | EH78: 0 | EJ78: 3 | EK78: 746 | EL78: ТСН-2001.13. Сметная стоимость оборудования | EM78: ТСН-2001.13 | EQ78: 0 | ER78: 2991.57 | ES78: 2991.57 | ET78: 0 | EU78: 0 | EV78: 0 | EW78: 0 | EX78: 0 | EY78: 0 | FQ78: 0 | FR78: =P78 -> 10320.92 | FS78: 0 | FX78: 0 | FY78: 0 | GD78: 1 | GF78: 576583559 | GG78: 2 | GH78: 1 | GI78: 2 | GJ78: 0 | GK78: 0 | GL78: =ROUND(IF(AND(BH78=3,BI78=3,FS78<>0),P78,0),2) -> 0 | GM78: =ROUND(O78+X78+Y78,2)+GX78 -> 10320.92 | GN78: =IF(OR(BI78=0,BI78=1),GM78-GX78,0) -> 0 | GO78: =IF(BI78=2,GM78-GX78,0) -> 0 | GP78: =IF(BI78=4,GM78-GX78,0) -> 0 | GR78: 0 | GS78: 3 | GT78: 0 | GV78: =ROUND((GT78),6) -> 0 | GW78: 1 | GX78: =ROUND(HC78*I78,2) -> 0 | HA78: 0 | HB78: 0 | HC78: =GV78*GW78 -> 0 | HS78: 0 | IK78: 0
A79: 17 | B79: 1 | E79: 9 | F79: 13.3-11-80 | G79: Поручень реабилитационный односекционный, для установки около умывальника, габаритные размеры 700х260 мм/ настенно-напольный 850х196х600 мм | H79: КОМПЛЕКТ | I79: 1 | J79: 0 | K79: 1 | O79: =ROUND(CP79,2) -> 2345.31 | P79: =ROUND((ROUND((AC79*I79),2)*BC79),2) -> 2345.31 | Q79: =(ROUND((ROUND(((ET79)*AV79*I79),2)*BB79),2)+ROUND((ROUND(((AE79-(EU79))*AV79*I79),2)*BS79),2)) -> 0 | R79: =(ROUND((ROUND(((EU79)*AV79*I79),2)*BS79),2)+ROUND((ROUND(((AE79-(EU79))*AV79*I79),2)*BS79),2)) -> 0 | S79: =ROUND((ROUND((AF79*AV79*I79),2)*BA79),2) -> 0 | T79: =ROUND(CU79*I79,2) -> 0 | U79: =CV79*I79 -> 0 | V79: =CW79*I79 -> 0 | W79: =ROUND(CX79*I79,2) -> 0 | X79: =(ROUND((((S79+ROUND((ROUND(((EU79)*AV79*I79),2)*BS79),2))*AT79)/100),2)+ROUND(((ROUND((ROUND(((AE79-(EU79))*AV79*I79),2)*BS79),2)*AT79)/100),2)) -> 0 | Y79: =(ROUND((((S79+ROUND((ROUND(((EU79)*AV79*I79),2)*BS79),2))*AU79)/100),2)+ROUND(((ROUND((ROUND(((AE79-(EU79))*AV79*I79),2)*BS79),2)*AU79)/100),2)) -> 0 | AA79: 59499218 | AB79: =ROUND((AC79+AD79+AF79),6) -> 2345.31 | AC79: =ROUND((ES79),6) -> 2345.31 | AD79: =ROUND((((ET79)-(EU79))+AE79),6) -> 0 | AE79: =ROUND((EU79),6) -> 0 | AF79: =ROUND((EV79),6) -> 0 | AG79: =ROUND((AP79),6) -> 0 | AH79: =(EW79) -> 0 | AI79: =(EX79) -> 0 | AJ79: =(AS79) -> 0 | AK79: 2345.31 | AL79: 2345.31 | AM79: 0 | AN79: 0 | AO79: 0 | AP79: 0 | AQ79: 0 | AR79: 0 | AS79: 0 | AT79: 0 | AU79: 0 | AV79: 1 | AW79: 1 | AZ79: 1 | BA79: 1 | BB79: 1 | BC79: 1 | BH79: 3 | BI79: 3 | BM79: 746 | BN79: 59298886 | BP79: 0 | BQ79: 130 | BR79: 0 | BS79: 1 | BT79: 1 | BU79: 1 | BV79: 1 | BW79: 1 | BX79: 1 | BZ79: 0 | CA79: 0 | CE79: 1566 | CF79: 0 | CG79: 0 | CM79: 0 | CO79: 0 | CP79: =(P79+Q79+S79) -> 2345.31 | CQ79: =ROUND((ROUND((AC79*1),2)*BC79),2) -> 2345.31 | CR79: =(ROUND((ROUND(((ET79)*AV79*1),2)*BB79),2)+ROUND((ROUND(((AE79-(EU79))*AV79*1),2)*BS79),2)) -> 0 | CS79: =(ROUND((ROUND(((EU79)*AV79*1),2)*BS79),2)+ROUND((ROUND(((AE79-(EU79))*AV79*1),2)*BS79),2)) -> 0 | CT79: =ROUND((ROUND((AF79*AV79*1),2)*BA79),2) -> 0 | CU79: =AG79 -> 0 | CV79: =(AH79*AV79) -> 0 | CW79: =AI79 -> 0 | CX79: =AJ79 -> 0 | CY79: =(ROUND((((S79+ROUND((ROUND(((EU79)*AV79*1),2)*BS79),2))*AT79)/100),2)+ROUND(((ROUND((ROUND(((AE79-(EU79))*AV79*1),2)*BS79),2)*AT79)/100),2)) -> 0 | CZ79: =(ROUND((((S79+ROUND((ROUND(((EU79)*AV79*1),2)*BS79),2))*AU79)/100),2)+ROUND(((ROUND((ROUND(((AE79-(EU79))*AV79*1),2)*BS79),2)*AU79)/100),2)) -> 0 | DN79: 0 | DO79: 0 | DP79: 1 | DQ79: 1 | DU79: 1013 | DV79: КОМПЛЕКТ | DW79: КОМПЛЕКТ | DX79: 1 | EE79: 59299131 | EF79: 130 | EG79: Сметная стоимость оборудования | EH79: 0 | EJ79: 3 | EK79: 746 | EL79: ТСН-2001.13. Сметная стоимость оборудования | EM79: ТСН-2001.13 | EQ79: 0 | ER79: 2345.31 | ES79: 2345.31 | ET79: 0 | EU79: 0 | EV79: 0 | EW79: 0 | EX79: 0 | EY79: 0 | FQ79: 0 | FR79: =P79 -> 2345.31 | FS79: 0 | FX79: 0 | FY79: 0 | GD79: 1 | GF79: -293542637 | GG79: 2 | GH79: 1 | GI79: -2 | GJ79: 0 | GK79: 0 | GL79: =ROUND(IF(AND(BH79=3,BI79=3,FS79<>0),P79,0),2) -> 0 | GM79: =ROUND(O79+X79+Y79,2)+GX79 -> 2345.31 | GN79: =IF(OR(BI79=0,BI79=1),GM79-GX79,0) -> 0 | GO79: =IF(BI79=2,GM79-GX79,0) -> 0 | GP79: =IF(BI79=4,GM79-GX79,0) -> 0 | GR79: 0 | GS79: 3 | GT79: 0 | GV79: =ROUND((GT79),6) -> 0 | GW79: 1 | GX79: =ROUND(HC79*I79,2) -> 0 | HA79: 0 | HB79: 0 | HC79: =GV79*GW79 -> 0 | HS79: 0 | IK79: 0
A80: 17 | B80: 1 | E80: 9 | F80: 13.3-11-80 | G80: Поручень реабилитационный односекционный, для установки около умывальника, габаритные размеры 700х260 мм/ настенно-напольный 850х196х600 мм | H80: КОМПЛЕКТ | I80: 1 | J80: 0 | K80: 1 | O80: =ROUND(CP80,2) -> 9123.26 | P80: =ROUND((ROUND((AC80*I80),2)*BC80),2) -> 9123.26 | Q80: =(ROUND((ROUND(((ET80)*AV80*I80),2)*BB80),2)+ROUND((ROUND(((AE80-(EU80))*AV80*I80),2)*BS80),2)) -> 0 | R80: =(ROUND((ROUND(((EU80)*AV80*I80),2)*BS80),2)+ROUND((ROUND(((AE80-(EU80))*AV80*I80),2)*BS80),2)) -> 0 | S80: =ROUND((ROUND((AF80*AV80*I80),2)*BA80),2) -> 0 | T80: =ROUND(CU80*I80,2) -> 0 | U80: =CV80*I80 -> 0 | V80: =CW80*I80 -> 0 | W80: =ROUND(CX80*I80,2) -> 0 | X80: =(ROUND((((S80+ROUND((ROUND(((EU80)*AV80*I80),2)*BS80),2))*AT80)/100),2)+ROUND(((ROUND((ROUND(((AE80-(EU80))*AV80*I80),2)*BS80),2)*AT80)/100),2)) -> 0 | Y80: =(ROUND((((S80+ROUND((ROUND(((EU80)*AV80*I80),2)*BS80),2))*AU80)/100),2)+ROUND(((ROUND((ROUND(((AE80-(EU80))*AV80*I80),2)*BS80),2)*AU80)/100),2)) -> 0 | AA80: 59499215 | AB80: =ROUND((AC80+AD80+AF80),6) -> 2345.31 | AC80: =ROUND((ES80),6) -> 2345.31 | AD80: =ROUND((((ET80)-(EU80))+AE80),6) -> 0 | AE80: =ROUND((EU80),6) -> 0 | AF80: =ROUND((EV80),6) -> 0 | AG80: =ROUND((AP80),6) -> 0 | AH80: =(EW80) -> 0 | AI80: =(EX80) -> 0 | AJ80: =(AS80) -> 0 | AK80: 2345.31 | AL80: 2345.31 | AM80: 0 | AN80: 0 | AO80: 0 | AP80: 0 | AQ80: 0 | AR80: 0 | AS80: 0 | AT80: 0 | AU80: 0 | AV80: 1 | AW80: 1 | AZ80: 1 | BA80: 1 | BB80: 1 | BC80: 3.89 | BH80: 3 | BI80: 3 | BM80: 746 | BN80: 59298886 | BP80: 0 | BQ80: 130 | BR80: 0 | BS80: 1 | BT80: 1 | BU80: 1 | BV80: 1 | BW80: 1 | BX80: 1 | BZ80: 0 | CA80: 0 | CE80: 1566 | CF80: 0 | CG80: 0 | CM80: 0 | CO80: 0 | CP80: =(P80+Q80+S80) -> 9123.26 | CQ80: =ROUND((ROUND((AC80*1),2)*BC80),2) -> 9123.26 | CR80: =(ROUND((ROUND(((ET80)*AV80*1),2)*BB80),2)+ROUND((ROUND(((AE80-(EU80))*AV80*1),2)*BS80),2)) -> 0 | CS80: =(ROUND((ROUND(((EU80)*AV80*1),2)*BS80),2)+ROUND((ROUND(((AE80-(EU80))*AV80*1),2)*BS80),2)) -> 0 | CT80: =ROUND((ROUND((AF80*AV80*1),2)*BA80),2) -> 0 | CU80: =AG80 -> 0 | CV80: =(AH80*AV80) -> 0 | CW80: =AI80 -> 0 | CX80: =AJ80 -> 0 | CY80: =(ROUND((((S80+ROUND((ROUND(((EU80)*AV80*1),2)*BS80),2))*AT80)/100),2)+ROUND(((ROUND((ROUND(((AE80-(EU80))*AV80*1),2)*BS80),2)*AT80)/100),2)) -> 0 | CZ80: =(ROUND((((S80+ROUND((ROUND(((EU80)*AV80*1),2)*BS80),2))*AU80)/100),2)+ROUND(((ROUND((ROUND(((AE80-(EU80))*AV80*1),2)*BS80),2)*AU80)/100),2)) -> 0 | DN80: 0 | DO80: 0 | DP80: 1 | DQ80: 1 | DU80: 1013 | DV80: КОМПЛЕКТ | DW80: КОМПЛЕКТ | DX80: 1 | EE80: 59299131 | EF80: 130 | EG80: Сметная стоимость оборудования | EH80: 0 | EJ80: 3 | EK80: 746 | EL80: ТСН-2001.13. Сметная стоимость оборудования | EM80: ТСН-2001.13 | EQ80: 0 | ER80: 2345.31 | ES80: 2345.31 | ET80: 0 | EU80: 0 | EV80: 0 | EW80: 0 | EX80: 0 | EY80: 0 | FQ80: 0 | FR80: =P80 -> 9123.26 | FS80: 0 | FX80: 0 | FY80: 0 | GD80: 1 | GF80: -293542637 | GG80: 2 | GH80: 1 | GI80: 2 | GJ80: 0 | GK80: 0 | GL80: =ROUND(IF(AND(BH80=3,BI80=3,FS80<>0),P80,0),2) -> 0 | GM80: =ROUND(O80+X80+Y80,2)+GX80 -> 9123.26 | GN80: =IF(OR(BI80=0,BI80=1),GM80-GX80,0) -> 0 | GO80: =IF(BI80=2,GM80-GX80,0) -> 0 | GP80: =IF(BI80=4,GM80-GX80,0) -> 0 | GR80: 0 | GS80: 3 | GT80: 0 | GV80: =ROUND((GT80),6) -> 0 | GW80: 1 | GX80: =ROUND(HC80*I80,2) -> 0 | HA80: 0 | HB80: 0 | HC80: =GV80*GW80 -> 0 | HS80: 0 | IK80: 0
A81: 17 | B81: 1 | E81: 10 | F81: 13.3-11-67 | G81: Крючок для подвески костылей, габаритные размеры 120х32 мм. Материал сталь нержавеющая с полировкой, крепление на стену, в комплекте: прокладки-амортизаторы резиновые, крепежные элементы | H81: КОМПЛЕКТ | I81: 1 | J81: 0 | K81: 1 | O81: =ROUND(CP81,2) -> 573.3 | P81: =ROUND((ROUND((AC81*I81),2)*BC81),2) -> 573.3 | Q81: =(ROUND((ROUND(((ET81)*AV81*I81),2)*BB81),2)+ROUND((ROUND(((AE81-(EU81))*AV81*I81),2)*BS81),2)) -> 0 | R81: =(ROUND((ROUND(((EU81)*AV81*I81),2)*BS81),2)+ROUND((ROUND(((AE81-(EU81))*AV81*I81),2)*BS81),2)) -> 0 | S81: =ROUND((ROUND((AF81*AV81*I81),2)*BA81),2) -> 0 | T81: =ROUND(CU81*I81,2) -> 0 | U81: =CV81*I81 -> 0 | V81: =CW81*I81 -> 0 | W81: =ROUND(CX81*I81,2) -> 0 | X81: =(ROUND((((S81+ROUND((ROUND(((EU81)*AV81*I81),2)*BS81),2))*AT81)/100),2)+ROUND(((ROUND((ROUND(((AE81-(EU81))*AV81*I81),2)*BS81),2)*AT81)/100),2)) -> 0 | Y81: =(ROUND((((S81+ROUND((ROUND(((EU81)*AV81*I81),2)*BS81),2))*AU81)/100),2)+ROUND(((ROUND((ROUND(((AE81-(EU81))*AV81*I81),2)*BS81),2)*AU81)/100),2)) -> 0 | AA81: 59499218 | AB81: =ROUND((AC81+AD81+AF81),6) -> 573.3 | AC81: =ROUND((ES81),6) -> 573.3 | AD81: =ROUND((((ET81)-(EU81))+AE81),6) -> 0 | AE81: =ROUND((EU81),6) -> 0 | AF81: =ROUND((EV81),6) -> 0 | AG81: =ROUND((AP81),6) -> 0 | AH81: =(EW81) -> 0 | AI81: =(EX81) -> 0 | AJ81: =(AS81) -> 0 | AK81: 573.3 | AL81: 573.3 | AM81: 0 | AN81: 0 | AO81: 0 | AP81: 0 | AQ81: 0 | AR81: 0 | AS81: 0 | AT81: 0 | AU81: 0 | AV81: 1 | AW81: 1 | AZ81: 1 | BA81: 1 | BB81: 1 | BC81: 1 | BH81: 3 | BI81: 3 | BM81: 746 | BN81: 59298886 | BP81: 0 | BQ81: 130 | BR81: 0 | BS81: 1 | BT81: 1 | BU81: 1 | BV81: 1 | BW81: 1 | BX81: 1 | BZ81: 0 | CA81: 0 | CE81: 1566 | CF81: 0 | CG81: 0 | CM81: 0 | CO81: 0 | CP81: =(P81+Q81+S81) -> 573.3 | CQ81: =ROUND((ROUND((AC81*1),2)*BC81),2) -> 573.3 | CR81: =(ROUND((ROUND(((ET81)*AV81*1),2)*BB81),2)+ROUND((ROUND(((AE81-(EU81))*AV81*1),2)*BS81),2)) -> 0 | CS81: =(ROUND((ROUND(((EU81)*AV81*1),2)*BS81),2)+ROUND((ROUND(((AE81-(EU81))*AV81*1),2)*BS81),2)) -> 0 | CT81: =ROUND((ROUND((AF81*AV81*1),2)*BA81),2) -> 0 | CU81: =AG81 -> 0 | CV81: =(AH81*AV81) -> 0 | CW81: =AI81 -> 0 | CX81: =AJ81 -> 0 | CY81: =(ROUND((((S81+ROUND((ROUND(((EU81)*AV81*1),2)*BS81),2))*AT81)/100),2)+ROUND(((ROUND((ROUND(((AE81-(EU81))*AV81*1),2)*BS81),2)*AT81)/100),2)) -> 0 | CZ81: =(ROUND((((S81+ROUND((ROUND(((EU81)*AV81*1),2)*BS81),2))*AU81)/100),2)+ROUND(((ROUND((ROUND(((AE81-(EU81))*AV81*1),2)*BS81),2)*AU81)/100),2)) -> 0 | DN81: 0 | DO81: 0 | DP81: 1 | DQ81: 1 | DU81: 1013 | DV81: КОМПЛЕКТ | DW81: КОМПЛЕКТ | DX81: 1 | EE81: 59299131 | EF81: 130 | EG81: Сметная стоимость оборудования | EH81: 0 | EJ81: 3 | EK81: 746 | EL81: ТСН-2001.13. Сметная стоимость оборудования | EM81: ТСН-2001.13 | EQ81: 0 | ER81: 573.3 | ES81: 573.3 | ET81: 0 | EU81: 0 | EV81: 0 | EW81: 0 | EX81: 0 | EY81: 0 | FQ81: 0 | FR81: =P81 -> 573.3 | FS81: 0 | FX81: 0 | FY81: 0 | GD81: 1 | GF81: -628451411 | GG81: 2 | GH81: 1 | GI81: -2 | GJ81: 0 | GK81: 0 | GL81: =ROUND(IF(AND(BH81=3,BI81=3,FS81<>0),P81,0),2) -> 0 | GM81: =ROUND(O81+X81+Y81,2)+GX81 -> 573.3 | GN81: =IF(OR(BI81=0,BI81=1),GM81-GX81,0) -> 0 | GO81: =IF(BI81=2,GM81-GX81,0) -> 0 | GP81: =IF(BI81=4,GM81-GX81,0) -> 0 | GR81: 0 | GS81: 3 | GT81: 0 | GV81: =ROUND((GT81),6) -> 0 | GW81: 1 | GX81: =ROUND(HC81*I81,2) -> 0 | HA81: 0 | HB81: 0 | HC81: =GV81*GW81 -> 0 | HS81: 0 | IK81: 0
A82: 17 | B82: 1 | E82: 10 | F82: 13.3-11-67 | G82: Крючок для подвески костылей, габаритные размеры 120х32 мм. Материал сталь нержавеющая с полировкой, крепление на стену, в комплекте: прокладки-амортизаторы резиновые, крепежные элементы | H82: КОМПЛЕКТ | I82: 1 | J82: 0 | K82: 1 | O82: =ROUND(CP82,2) -> 1926.29 | P82: =ROUND((ROUND((AC82*I82),2)*BC82),2) -> 1926.29 | Q82: =(ROUND((ROUND(((ET82)*AV82*I82),2)*BB82),2)+ROUND((ROUND(((AE82-(EU82))*AV82*I82),2)*BS82),2)) -> 0 | R82: =(ROUND((ROUND(((EU82)*AV82*I82),2)*BS82),2)+ROUND((ROUND(((AE82-(EU82))*AV82*I82),2)*BS82),2)) -> 0 | S82: =ROUND((ROUND((AF82*AV82*I82),2)*BA82),2) -> 0 | T82: =ROUND(CU82*I82,2) -> 0 | U82: =CV82*I82 -> 0 | V82: =CW82*I82 -> 0 | W82: =ROUND(CX82*I82,2) -> 0 | X82: =(ROUND((((S82+ROUND((ROUND(((EU82)*AV82*I82),2)*BS82),2))*AT82)/100),2)+ROUND(((ROUND((ROUND(((AE82-(EU82))*AV82*I82),2)*BS82),2)*AT82)/100),2)) -> 0 | Y82: =(ROUND((((S82+ROUND((ROUND(((EU82)*AV82*I82),2)*BS82),2))*AU82)/100),2)+ROUND(((ROUND((ROUND(((AE82-(EU82))*AV82*I82),2)*BS82),2)*AU82)/100),2)) -> 0 | AA82: 59499215 | AB82: =ROUND((AC82+AD82+AF82),6) -> 573.3 | AC82: =ROUND((ES82),6) -> 573.3 | AD82: =ROUND((((ET82)-(EU82))+AE82),6) -> 0 | AE82: =ROUND((EU82),6) -> 0 | AF82: =ROUND((EV82),6) -> 0 | AG82: =ROUND((AP82),6) -> 0 | AH82: =(EW82) -> 0 | AI82: =(EX82) -> 0 | AJ82: =(AS82) -> 0 | AK82: 573.3 | AL82: 573.3 | AM82: 0 | AN82: 0 | AO82: 0 | AP82: 0 | AQ82: 0 | AR82: 0 | AS82: 0 | AT82: 0 | AU82: 0 | AV82: 1 | AW82: 1 | AZ82: 1 | BA82: 1 | BB82: 1 | BC82: 3.36 | BH82: 3 | BI82: 3 | BM82: 746 | BN82: 59298886 | BP82: 0 | BQ82: 130 | BR82: 0 | BS82: 1 | BT82: 1 | BU82: 1 | BV82: 1 | BW82: 1 | BX82: 1 | BZ82: 0 | CA82: 0 | CE82: 1566 | CF82: 0 | CG82: 0 | CM82: 0 | CO82: 0 | CP82: =(P82+Q82+S82) -> 1926.29 | CQ82: =ROUND((ROUND((AC82*1),2)*BC82),2) -> 1926.29 | CR82: =(ROUND((ROUND(((ET82)*AV82*1),2)*BB82),2)+ROUND((ROUND(((AE82-(EU82))*AV82*1),2)*BS82),2)) -> 0 | CS82: =(ROUND((ROUND(((EU82)*AV82*1),2)*BS82),2)+ROUND((ROUND(((AE82-(EU82))*AV82*1),2)*BS82),2)) -> 0 | CT82: =ROUND((ROUND((AF82*AV82*1),2)*BA82),2) -> 0 | CU82: =AG82 -> 0 | CV82: =(AH82*AV82) -> 0 | CW82: =AI82 -> 0 | CX82: =AJ82 -> 0 | CY82: =(ROUND((((S82+ROUND((ROUND(((EU82)*AV82*1),2)*BS82),2))*AT82)/100),2)+ROUND(((ROUND((ROUND(((AE82-(EU82))*AV82*1),2)*BS82),2)*AT82)/100),2)) -> 0 | CZ82: =(ROUND((((S82+ROUND((ROUND(((EU82)*AV82*1),2)*BS82),2))*AU82)/100),2)+ROUND(((ROUND((ROUND(((AE82-(EU82))*AV82*1),2)*BS82),2)*AU82)/100),2)) -> 0 | DN82: 0 | DO82: 0 | DP82: 1 | DQ82: 1 | DU82: 1013 | DV82: КОМПЛЕКТ | DW82: КОМПЛЕКТ | DX82: 1 | EE82: 59299131 | EF82: 130 | EG82: Сметная стоимость оборудования | EH82: 0 | EJ82: 3 | EK82: 746 | EL82: ТСН-2001.13. Сметная стоимость оборудования | EM82: ТСН-2001.13 | EQ82: 0 | ER82: 573.3 | ES82: 573.3 | ET82: 0 | EU82: 0 | EV82: 0 | EW82: 0 | EX82: 0 | EY82: 0 | FQ82: 0 | FR82: =P82 -> 1926.29 | FS82: 0 | FX82: 0 | FY82: 0 | GD82: 1 | GF82: -628451411 | GG82: 2 | GH82: 1 | GI82: 2 | GJ82: 0 | GK82: 0 | GL82: =ROUND(IF(AND(BH82=3,BI82=3,FS82<>0),P82,0),2) -> 0 | GM82: =ROUND(O82+X82+Y82,2)+GX82 -> 1926.29 | GN82: =IF(OR(BI82=0,BI82=1),GM82-GX82,0) -> 0 | GO82: =IF(BI82=2,GM82-GX82,0) -> 0 | GP82: =IF(BI82=4,GM82-GX82,0) -> 0 | GR82: 0 | GS82: 3 | GT82: 0 | GV82: =ROUND((GT82),6) -> 0 | GW82: 1 | GX82: =ROUND(HC82*I82,2) -> 0 | HA82: 0 | HB82: 0 | HC82: =GV82*GW82 -> 0 | HS82: 0 | IK82: 0
A84: 51 | B84: =B69 -> 1 | C84: =A69 -> 4 | D84: =ROW(A69) -> 69 | F84: =IF(F69<>"",F69,"") | G84: =IF(G69<>"",G69,"") -> Оборудование, не облагаемое НДС | H84: 0 | O84: =ROUND(AB84,2) -> 19804.83 | P84: =ROUND(AC84,2) -> 19804.83 | Q84: =ROUND(AD84,2) -> 0 | R84: =ROUND(AE84,2) -> 0 | S84: =ROUND(AF84,2) -> 0 | T84: =ROUND(AG84,2) -> 0 | U84: =AH84 -> 0 | V84: =AI84 -> 0 | W84: =ROUND(AJ84,2) -> 0 | X84: =ROUND(AK84,2) -> 0 | Y84: =ROUND(AL84,2) -> 0 | AB84: =ROUND(SUMIF(AA73:AA82,"=59499218",O73:O82),2) -> 19804.83 | AC84: =ROUND(SUMIF(AA73:AA82,"=59499218",P73:P82),2) -> 19804.83 | AD84: =ROUND(SUMIF(AA73:AA82,"=59499218",Q73:Q82),2) -> 0 | AE84: =ROUND(SUMIF(AA73:AA82,"=59499218",R73:R82),2) -> 0 | AF84: =ROUND(SUMIF(AA73:AA82,"=59499218",S73:S82),2) -> 0 | AG84: =ROUND(SUMIF(AA73:AA82,"=59499218",T73:T82),2) -> 0 | AH84: =SUMIF(AA73:AA82,"=59499218",U73:U82) -> 0 | AI84: =SUMIF(AA73:AA82,"=59499218",V73:V82) -> 0 | AJ84: =ROUND(SUMIF(AA73:AA82,"=59499218",W73:W82),2) -> 0 | AK84: =ROUND(SUMIF(AA73:AA82,"=59499218",X73:X82),2) -> 0 | AL84: =ROUND(SUMIF(AA73:AA82,"=59499218",Y73:Y82),2) -> 0 | AO84: =ROUND(BX84,2) -> 0 | AP84: =ROUND(BY84,2) -> 19804.83 | AQ84: =ROUND(BZ84,2) -> 0 | AR84: =ROUND(CA84,2) -> 19804.83 | AS84: =ROUND(CB84,2) -> 0 | AT84: =ROUND(CC84,2) -> 0 | AU84: =ROUND(CD84,2) -> 0 | AV84: =ROUND(CE84,2) -> 19804.83 | ... BD84: =ROUND(CM84,2) -> 0 | BX84: =ROUND(SUMIF(AA73:AA82,"=59499218",FQ73:FQ82),2) -> 0 | BY84: =ROUND(SUMIF(AA73:AA82,"=59499218",FR73:FR82),2) -> 19804.83 | BZ84: =ROUND(SUMIF(AA73:AA82,"=59499218",GL73:GL82),2) -> 0 | CA84: =ROUND(SUMIF(AA73:AA82,"=59499218",GM73:GM82),2) -> 19804.83 | CB84: =ROUND(SUMIF(AA73:AA82,"=59499218",GN73:GN82),2) -> 0 | CC84: =ROUND(SUMIF(AA73:AA82,"=59499218",GO73:GO82),2) -> 0 | CD84: =ROUND(SUMIF(AA73:AA82,"=59499218",GP73:GP82),2) -> 0 | CE84: =AC84-BX84 -> 19804.83 | CF84: =AC84-BY84 -> 0 | CG84: =BX84-BZ84 -> 0 | CH84: =AC84-BX84-BY84+BZ84 -> 0 | CI84: =BY84-BZ84 -> 19804.83 | CJ84: =ROUND(SUMIF(AA73:AA82,"=59499218",GX73:GX82),2) -> 0 | CK84: =ROUND(SUMIF(AA73:AA82,"=59499218",GY73:GY82),2) -> 0 | CL84: =ROUND(SUMIF(AA73:AA82,"=59499218",GZ73:GZ82),2) -> 0 | CM84: =ROUND(SUMIF(AA73:AA82,"=59499218",HD73:HD82),2) -> 0 | DG84: =ROUND(DT84,2) -> 62665.62 | DH84: =ROUND(DU84,2) -> 62665.62 | DI84: =ROUND(DV84,2) -> 0 | DJ84: =ROUND(DW84,2) -> 0 | DK84: =ROUND(DX84,2) -> 0 | DL84: =ROUND(DY84,2) -> 0 | DM84: =DZ84 -> 0 | DN84: =EA84 -> 0 | DO84: =ROUND(EB84,2) -> 0 | DP84: =ROUND(EC84,2) -> 0 | DQ84: =ROUND(ED84,2) -> 0 | DT84: =ROUND(SUMIF(AA73:AA82,"=59499215",O73:O82),2) -> 62665.62 | DU84: =ROUND(SUMIF(AA73:AA82,"=59499215",P73:P82),2) -> 62665.62 | DV84: =ROUND(SUMIF(AA73:AA82,"=59499215",Q73:Q82),2) -> 0 | DW84: =ROUND(SUMIF(AA73:AA82,"=59499215",R73:R82),2) -> 0 | DX84: =ROUND(SUMIF(AA73:AA82,"=59499215",S73:S82),2) -> 0 | DY84: =ROUND(SUMIF(AA73:AA82,"=59499215",T73:T82),2) -> 0 | DZ84: =SUMIF(AA73:AA82,"=59499215",U73:U82) -> 0 | EA84: =SUMIF(AA73:AA82,"=59499215",V73:V82) -> 0 | EB84: =ROUND(SUMIF(AA73:AA82,"=59499215",W73:W82),2) -> 0 | EC84: =ROUND(SUMIF(AA73:AA82,"=59499215",X73:X82),2) -> 0 | ED84: =ROUND(SUMIF(AA73:AA82,"=59499215",Y73:Y82),2) -> 0 | EG84: =ROUND(FP84,2) -> 0 | EH84: =ROUND(FQ84,2) -> 62665.62 | EI84: =ROUND(FR84,2) -> 0 | EJ84: =ROUND(FS84,2) -> 62665.62 | EK84: =ROUND(FT84,2) -> 0 | EL84: =ROUND(FU84,2) -> 0 | EM84: =ROUND(FV84,2) -> 0 | EN84: =ROUND(FW84,2) -> 62665.62 | ... EV84: =ROUND(GE84,2) -> 0 | FP84: =ROUND(SUMIF(AA73:AA82,"=59499215",FQ73:FQ82),2) -> 0 | FQ84: =ROUND(SUMIF(AA73:AA82,"=59499215",FR73:FR82),2) -> 62665.62 | FR84: =ROUND(SUMIF(AA73:AA82,"=59499215",GL73:GL82),2) -> 0 | FS84: =ROUND(SUMIF(AA73:AA82,"=59499215",GM73:GM82),2) -> 62665.62 | FT84: =ROUND(SUMIF(AA73:AA82,"=59499215",GN73:GN82),2) -> 0 | FU84: =ROUND(SUMIF(AA73:AA82,"=59499215",GO73:GO82),2) -> 0 | FV84: =ROUND(SUMIF(AA73:AA82,"=59499215",GP73:GP82),2) -> 0 | FW84: =DU84-FP84 -> 62665.62 | FX84: =DU84-FQ84 -> 0 | FY84: =FP84-FR84 -> 0 | FZ84: =DU84-FP84-FQ84+FR84 -> 0 | GA84: =FQ84-FR84 -> 62665.62 | GB84: =ROUND(SUMIF(AA73:AA82,"=59499215",GX73:GX82),2) -> 0 | GC84: =ROUND(SUMIF(AA73:AA82,"=59499215",GY73:GY82),2) -> 0 | GD84: =ROUND(SUMIF(AA73:AA82,"=59499215",GZ73:GZ82),2) -> 0 | GE84: =ROUND(SUMIF(AA73:AA82,"=59499215",HD73:HD82),2) -> 0 | GX84: 0
A86: 50 | B86: 0 | C86: 0 | D86: 1 | E86: 201 | F86: =ROUND(Source!O84,O86) -> 19804.83 | G86: ПЗ | H86: Прямые затраты | K86: 201 | L86: 1 | M86: 3 | O86: 2 | P86: =ROUND(Source!DG84,O86) -> 62665.62 | W86: 19804.83 | X86: 1 | Y86: 19804.83 | Z86: 62665.62 | AA86: 1 | AB86: 62665.62
A87: 50 | B87: 0 | C87: 0 | D87: 1 | E87: 202 | F87: =ROUND(Source!P84,O87) -> 19804.83 | G87: СтМатОб | H87: Стоимость материальных ресурсов (всего) | K87: 202 | L87: 2 | M87: 3 | O87: 2 | P87: =ROUND(Source!DH84,O87) -> 62665.62 | W87: 19804.83 | X87: 1 | Y87: 19804.83 | Z87: 62665.62 | AA87: 1 | AB87: 62665.62
A88: 50 | B88: 0 | C88: 0 | D88: 1 | E88: 222 | F88: =ROUND(Source!AO84,O88) -> 0 | G88: СтМатОбЗак | H88: Стоимость материалов и оборудования заказчика | K88: 222 | L88: 3 | M88: 3 | O88: 2 | P88: =ROUND(Source!EG84,O88) -> 0 | W88: 0 | X88: 1 | Y88: 0 | Z88: 0 | AA88: 1 | AB88: 0
A89: 50 | B89: 0 | C89: 0 | D89: 1 | E89: 225 | F89: =ROUND(Source!AV84,O89) -> 19804.83 | G89: СтМатОбПод | H89: Стоимость материалов и оборудования подрядчика | K89: 225 | L89: 4 | M89: 3 | O89: 2 | P89: =ROUND(Source!EN84,O89) -> 62665.62 | W89: 19804.83 | X89: 1 | Y89: 19804.83 | Z89: 62665.62 | AA89: 1 | AB89: 62665.62
A90: 50 | B90: 0 | C90: 0 | D90: 1 | E90: 226 | F90: =ROUND(Source!AW84,O90) -> 0 | G90: СтМат | H90: Стоимость материалов (всего) | K90: 226 | L90: 5 | M90: 3 | O90: 2 | P90: =ROUND(Source!EO84,O90) -> 0 | W90: 0 | X90: 1 | Y90: 0 | Z90: 0 | AA90: 1 | AB90: 0
A91: 50 | B91: 0 | C91: 0 | D91: 1 | E91: 227 | F91: =ROUND(Source!AX84,O91) -> 0 | G91: СтМатЗак | H91: Стоимость материалов заказчика | K91: 227 | L91: 6 | M91: 3 | O91: 2 | P91: =ROUND(Source!EP84,O91) -> 0 | W91: 0 | X91: 1 | Y91: 0 | Z91: 0 | AA91: 1 | AB91: 0
A92: 50 | B92: 0 | C92: 0 | D92: 1 | E92: 228 | F92: =ROUND(Source!AY84,O92) -> 0 | G92: СтМатПод | H92: Стоимость материалов подрядчика | K92: 228 | L92: 7 | M92: 3 | O92: 2 | P92: =ROUND(Source!EQ84,O92) -> 0 | W92: 0 | X92: 1 | Y92: 0 | Z92: 0 | AA92: 1 | AB92: 0
A93: 50 | B93: 0 | C93: 0 | D93: 1 | E93: 216 | F93: =ROUND(Source!AP84,O93) -> 19804.83 | G93: Оборуд | H93: Стоимость оборудования (всего) | K93: 216 | L93: 8 | M93: 3 | O93: 2 | P93: =ROUND(Source!EH84,O93) -> 62665.62 | W93: 19804.83 | X93: 1 | Y93: 19804.83 | Z93: 62665.62 | AA93: 1 | AB93: 62665.62
A94: 50 | B94: 0 | C94: 0 | D94: 1 | E94: 223 | F94: =ROUND(Source!AQ84,O94) -> 0 | G94: ОборудЗак | H94: Стоимость оборудования заказчика | K94: 223 | L94: 9 | M94: 3 | O94: 2 | P94: =ROUND(Source!EI84,O94) -> 0 | W94: 0 | X94: 1 | Y94: 0 | Z94: 0 | AA94: 1 | AB94: 0
A95: 50 | B95: 0 | C95: 0 | D95: 1 | E95: 229 | F95: =ROUND(Source!AZ84,O95) -> 19804.83 | G95: ОборудПод | H95: Стоимость оборудования подрядчика | K95: 229 | L95: 10 | M95: 3 | O95: 2 | P95: =ROUND(Source!ER84,O95) -> 62665.62 | W95: 19804.83 | X95: 1 | Y95: 19804.83 | Z95: 62665.62 | AA95: 1 | AB95: 62665.62
A96: 50 | B96: 0 | C96: 0 | D96: 1 | E96: 203 | F96: =ROUND(Source!Q84,O96) -> 0 | G96: ЭММ | H96: Эксплуатация машин | K96: 203 | L96: 11 | M96: 3 | O96: 2 | P96: =ROUND(Source!DI84,O96) -> 0 | W96: 0 | X96: 1 | Y96: 0 | Z96: 0 | AA96: 1 | AB96: 0
A97: 50 | B97: 0 | C97: 0 | D97: 1 | E97: 231 | F97: =ROUND(Source!BB84,O97) -> 0 | G97: ЭММсНРиСП | H97: Эксплуатация машин по ТСН-2001.16 | K97: 231 | L97: 12 | M97: 3 | O97: 2 | P97: =ROUND(Source!ET84,O97) -> 0 | W97: 0 | X97: 1 | Y97: 0 | Z97: 0 | AA97: 1 | AB97: 0
A98: 50 | B98: 0 | C98: 0 | D98: 1 | E98: 204 | F98: =ROUND(Source!R84,O98) -> 0 | G98: ЗПМ | H98: ЗП машинистов | K98: 204 | L98: 13 | M98: 3 | O98: 2 | P98: =ROUND(Source!DJ84,O98) -> 0 | W98: 0 | X98: 1 | Y98: 0 | Z98: 0 | AA98: 1 | AB98: 0
A99: 50 | B99: 0 | C99: 0 | D99: 1 | E99: 205 | F99: =ROUND(Source!S84,O99) -> 0 | G99: ОЗП | H99: Основная ЗП рабочих | K99: 205 | L99: 14 | M99: 3 | O99: 2 | P99: =ROUND(Source!DK84,O99) -> 0 | W99: 0 | X99: 1 | Y99: 0 | Z99: 0 | AA99: 1 | AB99: 0
A100: 50 | B100: 0 | C100: 0 | D100: 1 | E100: 232 | F100: =ROUND(Source!BC84,O100) -> 0 | G100: ОЗПсНРиСП | H100: Основная ЗП рабочих по ТСН-2001.16 | K100: 232 | L100: 15 | M100: 3 | O100: 2 | P100: =ROUND(Source!EU84,O100) -> 0 | W100: 0 | X100: 1 | Y100: 0 | Z100: 0 | AA100: 1 | AB100: 0
A101: 50 | B101: 0 | C101: 0 | D101: 1 | E101: 214 | F101: =ROUND(Source!AS84,O101) -> 0 | G101: Строит | H101: Строительные работы с НР и СП | K101: 214 | L101: 16 | M101: 3 | O101: 2 | P101: =ROUND(Source!EK84,O101) -> 0 | W101: 0 | X101: 1 | Y101: 0 | Z101: 0 | AA101: 1 | AB101: 0
A102: 50 | B102: 0 | C102: 0 | D102: 1 | E102: 215 | F102: =ROUND(Source!AT84,O102) -> 0 | G102: Монтаж | H102: Монтажные работы с НР и СП | K102: 215 | L102: 17 | M102: 3 | O102: 2 | P102: =ROUND(Source!EL84,O102) -> 0 | W102: 0 | X102: 1 | Y102: 0 | Z102: 0 | AA102: 1 | AB102: 0
A103: 50 | B103: 0 | C103: 0 | D103: 1 | E103: 217 | F103: =ROUND(Source!AU84,O103) -> 0 | G103: Прочие | H103: Прочие работы с НР и СП | K103: 217 | L103: 18 | M103: 3 | O103: 2 | P103: =ROUND(Source!EM84,O103) -> 0 | W103: 0 | X103: 1 | Y103: 0 | Z103: 0 | AA103: 1 | AB103: 0
A104: 50 | B104: 0 | C104: 0 | D104: 1 | E104: 230 | F104: =ROUND(Source!BA84,O104) -> 0 | G104: ПрочиеЗатр | H104: Прочие затраты по ТСН-2001.16 | K104: 230 | L104: 19 | M104: 3 | O104: 2 | P104: =ROUND(Source!ES84,O104) -> 0 | W104: 0 | X104: 1 | Y104: 0 | Z104: 0 | AA104: 1 | AB104: 0
A105: 50 | B105: 0 | C105: 0 | D105: 1 | E105: 206 | F105: =ROUND(Source!T84,O105) -> 0 | G105: ВозврМат | H105: Возврат материалов | K105: 206 | L105: 20 | M105: 3 | O105: 2 | P105: =ROUND(Source!DL84,O105) -> 0 | W105: 0 | X105: 1 | Y105: 0 | Z105: 0 | AA105: 1 | AB105: 0
A106: 50 | B106: 0 | C106: 0 | D106: 1 | E106: 207 | F106: =Source!U84 -> 0 | G106: ТрудСтр | H106: Трудозатраты строителей | K106: 207 | L106: 21 | M106: 3 | O106: -1 | P106: =Source!DM84 -> 0 | W106: 0 | X106: 1 | Y106: 0 | Z106: 0 | AA106: 1 | AB106: 0
A107: 50 | B107: 0 | C107: 0 | D107: 1 | E107: 208 | F107: =Source!V84 -> 0 | G107: ТрудМаш | H107: Трудозатраты машинистов | K107: 208 | L107: 22 | M107: 3 | O107: -1 | P107: =Source!DN84 -> 0 | W107: 0 | X107: 1 | Y107: 0 | Z107: 0 | AA107: 1 | AB107: 0
A108: 50 | B108: 0 | C108: 0 | D108: 1 | E108: 209 | F108: =ROUND(Source!W84,O108) -> 0 | G108: ТранспМат | H108: Транспорт материалов | K108: 209 | L108: 23 | M108: 3 | O108: 2 | P108: =ROUND(Source!DO84,O108) -> 0 | W108: 0 | X108: 1 | Y108: 0 | Z108: 0 | AA108: 1 | AB108: 0
A109: 50 | B109: 0 | C109: 0 | D109: 1 | E109: 233 | F109: =ROUND(Source!BD84,O109) -> 0 | G109: Перевозка | H109: Перевозка грузов | K109: 233 | L109: 24 | M109: 3 | O109: 2 | P109: =ROUND(Source!EV84,O109) -> 0 | W109: 0 | X109: 1 | Y109: 0 | Z109: 0 | AA109: 1 | AB109: 0
A110: 50 | B110: 0 | C110: 0 | D110: 1 | E110: 210 | F110: =ROUND(Source!X84,O110) -> 0 | G110: НР | H110: Накладные расходы | K110: 210 | L110: 25 | M110: 3 | O110: 2 | P110: =ROUND(Source!DP84,O110) -> 0 | W110: 0 | X110: 1 | Y110: 0 | Z110: 0 | AA110: 1 | AB110: 0
A111: 50 | B111: 0 | C111: 0 | D111: 1 | E111: 211 | F111: =ROUND(Source!Y84,O111) -> 0 | G111: СмПриб | H111: Сметная прибыль | K111: 211 | L111: 26 | M111: 3 | O111: 2 | P111: =ROUND(Source!DQ84,O111) -> 0 | W111: 0 | X111: 1 | Y111: 0 | Z111: 0 | AA111: 1 | AB111: 0
A112: 50 | B112: 0 | C112: 0 | D112: 1 | E112: 224 | F112: =ROUND(Source!AR84,O112) -> 19804.83 | G112: Всего | H112: Всего с НР и СП | K112: 224 | L112: 27 | M112: 3 | O112: 2 | P112: =ROUND(Source!EJ84,O112) -> 62665.62 | W112: 19804.83 | X112: 1 | Y112: 19804.83 | Z112: 62665.62 | AA112: 1 | AB112: 62665.62
A114: 4 | B114: 1 | D114: =ROW(A131) -> 131 | G114: Оборудование, облагаемое НДС | I114: 0 | K114: -1 | S114: 0 | T114: 0 | V114: 2 | BX114: 0 | CJ114: 0
A116: 52 | B116: =B131 -> 1 | C116: =C131 -> 4 | D116: =D131 -> 114 | E116: =E131 -> 0 | F116: =F131 | G116: =G131 -> Оборудование, облагаемое НДС | O116: =O131 -> 15190.53 | P116: =P131 -> 15190.53 | Q116: =Q131 -> 0 | R116: =R131 -> 0 | S116: =S131 -> 0 | T116: =T131 -> 0 | U116: =U131 -> 0 | V116: =V131 -> 0 | ... GX116: =GX131 -> 0
A118: 17 | B118: 1 | E118: 11 | F118: КА №1 | G118: Зеркало поворотное с ручкой управления, какркас из нержавеющей стали AISI 304, арт. 80035 | H118: шт. | I118: 1 | J118: 0 | K118: 1 | O118: =ROUND(CP118,2) -> 1879.24 | P118: =ROUND((ROUND((AC118*I118),2)*BC118),2) -> 1879.24 | Q118: =(ROUND((ROUND(((ET118)*AV118*I118),2)*BB118),2)+ROUND((ROUND(((AE118-(EU118))*AV118*I118),2)*BS118),2)) -> 0 | R118: =(ROUND((ROUND(((EU118)*AV118*I118),2)*BS118),2)+ROUND((ROUND(((AE118-(EU118))*AV118*I118),2)*BS118),2)) -> 0 | S118: =ROUND((ROUND((AF118*AV118*I118),2)*BA118),2) -> 0 | T118: =ROUND(CU118*I118,2) -> 0 | U118: =CV118*I118 -> 0 | V118: =CW118*I118 -> 0 | W118: =ROUND(CX118*I118,2) -> 0 | X118: =(ROUND((((S118+ROUND((ROUND(((EU118)*AV118*I118),2)*BS118),2))*AT118)/100),2)+ROUND(((ROUND((ROUND(((AE118-(EU118))*AV118*I118),2)*BS118),2)*AT118)/100),2)) -> 0 | Y118: =(ROUND((((S118+ROUND((ROUND(((EU118)*AV118*I118),2)*BS118),2))*AU118)/100),2)+ROUND(((ROUND((ROUND(((AE118-(EU118))*AV118*I118),2)*BS118),2)*AU118)/100),2)) -> 0 | AA118: 59499218 | AB118: =ROUND((AC118+AD118+AF118),6) -> 1879.24 | AC118: =ROUND((ES118),6) -> 1879.24 | AD118: =ROUND((((ET118)-(EU118))+AE118),6) -> 0 | AE118: =ROUND((EU118),6) -> 0 | AF118: =ROUND((EV118),6) -> 0 | AG118: =ROUND((AP118),6) -> 0 | AH118: =(EW118) -> 0 | AI118: =(EX118) -> 0 | AJ118: =(AS118) -> 0 | AK118: 1879.24 | AL118: 1879.24 | AM118: 0 | AN118: 0 | AO118: 0 | AP118: 0 | AQ118: 0 | AR118: 0 | AS118: 0 | AT118: 0 | AU118: 0 | AV118: 1 | AW118: 1 | AZ118: 1 | BA118: 1 | BB118: 1 | BC118: 1 | BH118: 3 | BI118: 3 | BM118: 746 | BN118: 0 | BP118: 0 | BQ118: 130 | BR118: 0 | BS118: 1 | BT118: 1 | BU118: 1 | BV118: 1 | BW118: 1 | BX118: 1 | BZ118: 0 | CA118: 0 | CE118: 1566 | CF118: 0 | CG118: 0 | CM118: 0 | CO118: 0 | CP118: =(P118+Q118+S118) -> 1879.24 | CQ118: =ROUND((ROUND((AC118*1),2)*BC118),2) -> 1879.24 | CR118: =(ROUND((ROUND(((ET118)*AV118*1),2)*BB118),2)+ROUND((ROUND(((AE118-(EU118))*AV118*1),2)*BS118),2)) -> 0 | CS118: =(ROUND((ROUND(((EU118)*AV118*1),2)*BS118),2)+ROUND((ROUND(((AE118-(EU118))*AV118*1),2)*BS118),2)) -> 0 | CT118: =ROUND((ROUND((AF118*AV118*1),2)*BA118),2) -> 0 | CU118: =AG118 -> 0 | CV118: =(AH118*AV118) -> 0 | CW118: =AI118 -> 0 | CX118: =AJ118 -> 0 | CY118: =(ROUND((((S118+ROUND((ROUND(((EU118)*AV118*1),2)*BS118),2))*AT118)/100),2)+ROUND(((ROUND((ROUND(((AE118-(EU118))*AV118*1),2)*BS118),2)*AT118)/100),2)) -> 0 | CZ118: =(ROUND((((S118+ROUND((ROUND(((EU118)*AV118*1),2)*BS118),2))*AU118)/100),2)+ROUND(((ROUND((ROUND(((AE118-(EU118))*AV118*1),2)*BS118),2)*AU118)/100),2)) -> 0 | DN118: 0 | DO118: 0 | DP118: 1 | DQ118: 1 | DU118: 1010 | DV118: шт. | DW118: шт. | DX118: 1 | EE118: 59299131 | EF118: 130 | EG118: Сметная стоимость оборудования | EH118: 0 | EJ118: 3 | EK118: 746 | EL118: ТСН-2001.13. Сметная стоимость оборудования | EM118: ТСН-2001.13 | EQ118: 0 | ER118: 0 | ES118: 1879.24 | ET118: 0 | EU118: 0 | EV118: 0 | EW118: 0 | EX118: 0 | EY118: 0 | FQ118: 0 | FR118: =P118 -> 1879.24 | FS118: 0 | FX118: 0 | FY118: 0 | GA118: [16 572 / 1,2 / 7,66] + 3% Трансп + 1,2% Заг.скл | GD118: 1 | GF118: -1505903575 | GG118: 2 | GH118: 4 | GI118: -2 | GJ118: 0 | GK118: 0 | GL118: =ROUND(IF(AND(BH118=3,BI118=3,FS118<>0),P118,0),2) -> 0 | GM118: =ROUND(O118+X118+Y118,2)+GX118 -> 1879.24 | GN118: =IF(OR(BI118=0,BI118=1),GM118-GX118,0) -> 0 | GO118: =IF(BI118=2,GM118-GX118,0) -> 0 | GP118: =IF(BI118=4,GM118-GX118,0) -> 0 | GR118: 0 | GS118: 2 | GT118: 0 | GV118: =ROUND((GT118),6) -> 0 | GW118: 1 | GX118: =ROUND(HC118*I118,2) -> 0 | HA118: 0 | HB118: 0 | HC118: =GV118*GW118 -> 0 | HE118: 3 | HF118: 1,2 | HS118: 0 | IK118: 0
A119: 17 | B119: 1 | E119: 11 | F119: КА №1 | G119: Зеркало поворотное с ручкой управления, какркас из нержавеющей стали AISI 304, арт. 80035 | H119: шт. | I119: 1 | J119: 0 | K119: 1 | O119: =ROUND(CP119,2) -> 14394.98 | P119: =ROUND((ROUND((AC119*I119),2)*BC119),2) -> 14394.98 | Q119: =(ROUND((ROUND(((ET119)*AV119*I119),2)*BB119),2)+ROUND((ROUND(((AE119-(EU119))*AV119*I119),2)*BS119),2)) -> 0 | R119: =(ROUND((ROUND(((EU119)*AV119*I119),2)*BS119),2)+ROUND((ROUND(((AE119-(EU119))*AV119*I119),2)*BS119),2)) -> 0 | S119: =ROUND((ROUND((AF119*AV119*I119),2)*BA119),2) -> 0 | T119: =ROUND(CU119*I119,2) -> 0 | U119: =CV119*I119 -> 0 | V119: =CW119*I119 -> 0 | W119: =ROUND(CX119*I119,2) -> 0 | X119: =(ROUND((((S119+ROUND((ROUND(((EU119)*AV119*I119),2)*BS119),2))*AT119)/100),2)+ROUND(((ROUND((ROUND(((AE119-(EU119))*AV119*I119),2)*BS119),2)*AT119)/100),2)) -> 0 | Y119: =(ROUND((((S119+ROUND((ROUND(((EU119)*AV119*I119),2)*BS119),2))*AU119)/100),2)+ROUND(((ROUND((ROUND(((AE119-(EU119))*AV119*I119),2)*BS119),2)*AU119)/100),2)) -> 0 | AA119: 59499215 | AB119: =ROUND((AC119+AD119+AF119),6) -> 1879.24 | AC119: =ROUND((ES119),6) -> 1879.24 | AD119: =ROUND((((ET119)-(EU119))+AE119),6) -> 0 | AE119: =ROUND((EU119),6) -> 0 | AF119: =ROUND((EV119),6) -> 0 | AG119: =ROUND((AP119),6) -> 0 | AH119: =(EW119) -> 0 | AI119: =(EX119) -> 0 | AJ119: =(AS119) -> 0 | AK119: 1879.24 | AL119: 1879.24 | AM119: 0 | AN119: 0 | AO119: 0 | AP119: 0 | AQ119: 0 | AR119: 0 | AS119: 0 | AT119: 0 | AU119: 0 | AV119: 1 | AW119: 1 | AZ119: 1 | BA119: 1 | BB119: 1 | BC119: 7.66 | BH119: 3 | BI119: 3 | BM119: 746 | BN119: 0 | BP119: 0 | BQ119: 130 | BR119: 0 | BS119: 1 | BT119: 1 | BU119: 1 | BV119: 1 | BW119: 1 | BX119: 1 | BZ119: 0 | CA119: 0 | CE119: 1566 | CF119: 0 | CG119: 0 | CM119: 0 | CO119: 0 | CP119: =(P119+Q119+S119) -> 14394.98 | CQ119: =ROUND((ROUND((AC119*1),2)*BC119),2) -> 14394.98 | CR119: =(ROUND((ROUND(((ET119)*AV119*1),2)*BB119),2)+ROUND((ROUND(((AE119-(EU119))*AV119*1),2)*BS119),2)) -> 0 | CS119: =(ROUND((ROUND(((EU119)*AV119*1),2)*BS119),2)+ROUND((ROUND(((AE119-(EU119))*AV119*1),2)*BS119),2)) -> 0 | CT119: =ROUND((ROUND((AF119*AV119*1),2)*BA119),2) -> 0 | CU119: =AG119 -> 0 | CV119: =(AH119*AV119) -> 0 | CW119: =AI119 -> 0 | CX119: =AJ119 -> 0 | CY119: =(ROUND((((S119+ROUND((ROUND(((EU119)*AV119*1),2)*BS119),2))*AT119)/100),2)+ROUND(((ROUND((ROUND(((AE119-(EU119))*AV119*1),2)*BS119),2)*AT119)/100),2)) -> 0 | CZ119: =(ROUND((((S119+ROUND((ROUND(((EU119)*AV119*1),2)*BS119),2))*AU119)/100),2)+ROUND(((ROUND((ROUND(((AE119-(EU119))*AV119*1),2)*BS119),2)*AU119)/100),2)) -> 0 | DN119: 0 | DO119: 0 | DP119: 1 | DQ119: 1 | DU119: 1010 | DV119: шт. | DW119: шт. | DX119: 1 | EE119: 59299131 | EF119: 130 | EG119: Сметная стоимость оборудования | EH119: 0 | EJ119: 3 | EK119: 746 | EL119: ТСН-2001.13. Сметная стоимость оборудования | EM119: ТСН-2001.13 | EQ119: 0 | ER119: 1879.24 | ES119: 1879.24 | ET119: 0 | EU119: 0 | EV119: 0 | EW119: 0 | EX119: 0 | EY119: 0 | EZ119: 5 | FC119: 1 | FD119: 18 | FF119: 16572 | FQ119: 0 | FR119: =P119 -> 14394.98 | FS119: 0 | FX119: 0 | FY119: 0 | GA119: [16 572 / 1,2 / 7,66] + 3% Трансп + 1,2% Заг.скл | GD119: 1 | GF119: -1505903575 | GG119: 2 | GH119: 3 | GI119: 3 | GJ119: 0 | GK119: 0 | GL119: =ROUND(IF(AND(BH119=3,BI119=3,FS119<>0),P119,0),2) -> 0 | GM119: =ROUND(O119+X119+Y119,2)+GX119 -> 14394.98 | GN119: =IF(OR(BI119=0,BI119=1),GM119-GX119,0) -> 0 | GO119: =IF(BI119=2,GM119-GX119,0) -> 0 | GP119: =IF(BI119=4,GM119-GX119,0) -> 0 | GR119: 1 | GS119: 1 | GT119: 0 | GV119: =ROUND((GT119),6) -> 0 | GW119: 1 | GX119: =ROUND(HC119*I119,2) -> 0 | HA119: 0 | HB119: 0 | HC119: =GV119*GW119 -> 0 | HE119: 3 | HF119: 1,2 | HS119: 0 | IK119: 0
A120: 17 | B120: 1 | E120: 12 | F120: КА №2 | G120: Корзина металлическая для мусора Tork Image Design B1, 50 л, без крышки, стальная, Артикул:460011 | H120: шт. | I120: 1 | J120: 0 | K120: 1 | O120: =ROUND(CP120,2) -> 9068.49 | P120: =ROUND((ROUND((AC120*I120),2)*BC120),2) -> 9068.49 | Q120: =(ROUND((ROUND(((ET120)*AV120*I120),2)*BB120),2)+ROUND((ROUND(((AE120-(EU120))*AV120*I120),2)*BS120),2)) -> 0 | R120: =(ROUND((ROUND(((EU120)*AV120*I120),2)*BS120),2)+ROUND((ROUND(((AE120-(EU120))*AV120*I120),2)*BS120),2)) -> 0 | S120: =ROUND((ROUND((AF120*AV120*I120),2)*BA120),2) -> 0 | T120: =ROUND(CU120*I120,2) -> 0 | U120: =CV120*I120 -> 0 | V120: =CW120*I120 -> 0 | W120: =ROUND(CX120*I120,2) -> 0 | X120: =(ROUND((((S120+ROUND((ROUND(((EU120)*AV120*I120),2)*BS120),2))*AT120)/100),2)+ROUND(((ROUND((ROUND(((AE120-(EU120))*AV120*I120),2)*BS120),2)*AT120)/100),2)) -> 0 | Y120: =(ROUND((((S120+ROUND((ROUND(((EU120)*AV120*I120),2)*BS120),2))*AU120)/100),2)+ROUND(((ROUND((ROUND(((AE120-(EU120))*AV120*I120),2)*BS120),2)*AU120)/100),2)) -> 0 | AA120: 59499218 | AB120: =ROUND((AC120+AD120+AF120),6) -> 9068.49 | AC120: =ROUND((ES120),6) -> 9068.49 | AD120: =ROUND((((ET120)-(EU120))+AE120),6) -> 0 | AE120: =ROUND((EU120),6) -> 0 | AF120: =ROUND((EV120),6) -> 0 | AG120: =ROUND((AP120),6) -> 0 | AH120: =(EW120) -> 0 | AI120: =(EX120) -> 0 | AJ120: =(AS120) -> 0 | AK120: 9068.49 | AL120: 9068.49 | AM120: 0 | AN120: 0 | AO120: 0 | AP120: 0 | AQ120: 0 | AR120: 0 | AS120: 0 | AT120: 0 | AU120: 0 | AV120: 1 | AW120: 1 | AZ120: 1 | BA120: 1 | BB120: 1 | BC120: 1 | BH120: 3 | BI120: 3 | BM120: 746 | BN120: 0 | BP120: 0 | BQ120: 130 | BR120: 0 | BS120: 1 | BT120: 1 | BU120: 1 | BV120: 1 | BW120: 1 | BX120: 1 | BZ120: 0 | CA120: 0 | CE120: 1566 | CF120: 0 | CG120: 0 | CM120: 0 | CO120: 0 | CP120: =(P120+Q120+S120) -> 9068.49 | CQ120: =ROUND((ROUND((AC120*1),2)*BC120),2) -> 9068.49 | CR120: =(ROUND((ROUND(((ET120)*AV120*1),2)*BB120),2)+ROUND((ROUND(((AE120-(EU120))*AV120*1),2)*BS120),2)) -> 0 | CS120: =(ROUND((ROUND(((EU120)*AV120*1),2)*BS120),2)+ROUND((ROUND(((AE120-(EU120))*AV120*1),2)*BS120),2)) -> 0 | CT120: =ROUND((ROUND((AF120*AV120*1),2)*BA120),2) -> 0 | CU120: =AG120 -> 0 | CV120: =(AH120*AV120) -> 0 | CW120: =AI120 -> 0 | CX120: =AJ120 -> 0 | CY120: =(ROUND((((S120+ROUND((ROUND(((EU120)*AV120*1),2)*BS120),2))*AT120)/100),2)+ROUND(((ROUND((ROUND(((AE120-(EU120))*AV120*1),2)*BS120),2)*AT120)/100),2)) -> 0 | CZ120: =(ROUND((((S120+ROUND((ROUND(((EU120)*AV120*1),2)*BS120),2))*AU120)/100),2)+ROUND(((ROUND((ROUND(((AE120-(EU120))*AV120*1),2)*BS120),2)*AU120)/100),2)) -> 0 | DN120: 0 | DO120: 0 | DP120: 1 | DQ120: 1 | DU120: 1010 | DV120: шт. | DW120: шт. | DX120: 1 | EE120: 59299131 | EF120: 130 | EG120: Сметная стоимость оборудования | EH120: 0 | EJ120: 3 | EK120: 746 | EL120: ТСН-2001.13. Сметная стоимость оборудования | EM120: ТСН-2001.13 | EQ120: 0 | ER120: 0 | ES120: 9068.49 | ET120: 0 | EU120: 0 | EV120: 0 | EW120: 0 | EX120: 0 | EY120: 0 | FQ120: 0 | FR120: =P120 -> 9068.49 | FS120: 0 | FX120: 0 | FY120: 0 | GA120: [79 970 / 1,2 / 7,66] + 3% Трансп + 1,2% Заг.скл | GD120: 1 | GF120: -58094079 | GG120: 2 | GH120: 4 | GI120: -2 | GJ120: 0 | GK120: 0 | GL120: =ROUND(IF(AND(BH120=3,BI120=3,FS120<>0),P120,0),2) -> 0 | GM120: =ROUND(O120+X120+Y120,2)+GX120 -> 9068.49 | GN120: =IF(OR(BI120=0,BI120=1),GM120-GX120,0) -> 0 | GO120: =IF(BI120=2,GM120-GX120,0) -> 0 | GP120: =IF(BI120=4,GM120-GX120,0) -> 0 | GR120: 0 | GS120: 2 | GT120: 0 | GV120: =ROUND((GT120),6) -> 0 | GW120: 1 | GX120: =ROUND(HC120*I120,2) -> 0 | HA120: 0 | HB120: 0 | HC120: =GV120*GW120 -> 0 | HE120: 3 | HF120: 1,2 | HS120: 0 | IK120: 0
A121: 17 | B121: 1 | E121: 12 | F121: КА №2 | G121: Корзина металлическая для мусора Tork Image Design B1, 50 л, без крышки, стальная, Артикул:460011 | H121: шт. | I121: 1 | J121: 0 | K121: 1 | O121: =ROUND(CP121,2) -> 69464.63 | P121: =ROUND((ROUND((AC121*I121),2)*BC121),2) -> 69464.63 | Q121: =(ROUND((ROUND(((ET121)*AV121*I121),2)*BB121),2)+ROUND((ROUND(((AE121-(EU121))*AV121*I121),2)*BS121),2)) -> 0 | R121: =(ROUND((ROUND(((EU121)*AV121*I121),2)*BS121),2)+ROUND((ROUND(((AE121-(EU121))*AV121*I121),2)*BS121),2)) -> 0 | S121: =ROUND((ROUND((AF121*AV121*I121),2)*BA121),2) -> 0 | T121: =ROUND(CU121*I121,2) -> 0 | U121: =CV121*I121 -> 0 | V121: =CW121*I121 -> 0 | W121: =ROUND(CX121*I121,2) -> 0 | X121: =(ROUND((((S121+ROUND((ROUND(((EU121)*AV121*I121),2)*BS121),2))*AT121)/100),2)+ROUND(((ROUND((ROUND(((AE121-(EU121))*AV121*I121),2)*BS121),2)*AT121)/100),2)) -> 0 | Y121: =(ROUND((((S121+ROUND((ROUND(((EU121)*AV121*I121),2)*BS121),2))*AU121)/100),2)+ROUND(((ROUND((ROUND(((AE121-(EU121))*AV121*I121),2)*BS121),2)*AU121)/100),2)) -> 0 | AA121: 59499215 | AB121: =ROUND((AC121+AD121+AF121),6) -> 9068.49 | AC121: =ROUND((ES121),6) -> 9068.49 | AD121: =ROUND((((ET121)-(EU121))+AE121),6) -> 0 | AE121: =ROUND((EU121),6) -> 0 | AF121: =ROUND((EV121),6) -> 0 | AG121: =ROUND((AP121),6) -> 0 | AH121: =(EW121) -> 0 | AI121: =(EX121) -> 0 | AJ121: =(AS121) -> 0 | AK121: 9068.49 | AL121: 9068.49 | AM121: 0 | AN121: 0 | AO121: 0 | AP121: 0 | AQ121: 0 | AR121: 0 | AS121: 0 | AT121: 0 | AU121: 0 | AV121: 1 | AW121: 1 | AZ121: 1 | BA121: 1 | BB121: 1 | BC121: 7.66 | BH121: 3 | BI121: 3 | BM121: 746 | BN121: 0 | BP121: 0 | BQ121: 130 | BR121: 0 | BS121: 1 | BT121: 1 | BU121: 1 | BV121: 1 | BW121: 1 | BX121: 1 | BZ121: 0 | CA121: 0 | CE121: 1566 | CF121: 0 | CG121: 0 | CM121: 0 | CO121: 0 | CP121: =(P121+Q121+S121) -> 69464.63 | CQ121: =ROUND((ROUND((AC121*1),2)*BC121),2) -> 69464.63 | CR121: =(ROUND((ROUND(((ET121)*AV121*1),2)*BB121),2)+ROUND((ROUND(((AE121-(EU121))*AV121*1),2)*BS121),2)) -> 0 | CS121: =(ROUND((ROUND(((EU121)*AV121*1),2)*BS121),2)+ROUND((ROUND(((AE121-(EU121))*AV121*1),2)*BS121),2)) -> 0 | CT121: =ROUND((ROUND((AF121*AV121*1),2)*BA121),2) -> 0 | CU121: =AG121 -> 0 | CV121: =(AH121*AV121) -> 0 | CW121: =AI121 -> 0 | CX121: =AJ121 -> 0 | CY121: =(ROUND((((S121+ROUND((ROUND(((EU121)*AV121*1),2)*BS121),2))*AT121)/100),2)+ROUND(((ROUND((ROUND(((AE121-(EU121))*AV121*1),2)*BS121),2)*AT121)/100),2)) -> 0 | CZ121: =(ROUND((((S121+ROUND((ROUND(((EU121)*AV121*1),2)*BS121),2))*AU121)/100),2)+ROUND(((ROUND((ROUND(((AE121-(EU121))*AV121*1),2)*BS121),2)*AU121)/100),2)) -> 0 | DN121: 0 | DO121: 0 | DP121: 1 | DQ121: 1 | DU121: 1010 | DV121: шт. | DW121: шт. | DX121: 1 | EE121: 59299131 | EF121: 130 | EG121: Сметная стоимость оборудования | EH121: 0 | EJ121: 3 | EK121: 746 | EL121: ТСН-2001.13. Сметная стоимость оборудования | EM121: ТСН-2001.13 | EQ121: 0 | ER121: 9068.49 | ES121: 9068.49 | ET121: 0 | EU121: 0 | EV121: 0 | EW121: 0 | EX121: 0 | EY121: 0 | EZ121: 5 | FC121: 1 | FD121: 18 | FF121: 79970 | FQ121: 0 | FR121: =P121 -> 69464.63 | FS121: 0 | FX121: 0 | FY121: 0 | GA121: [79 970 / 1,2 / 7,66] + 3% Трансп + 1,2% Заг.скл | GD121: 1 | GF121: -58094079 | GG121: 2 | GH121: 3 | GI121: 3 | GJ121: 0 | GK121: 0 | GL121: =ROUND(IF(AND(BH121=3,BI121=3,FS121<>0),P121,0),2) -> 0 | GM121: =ROUND(O121+X121+Y121,2)+GX121 -> 69464.63 | GN121: =IF(OR(BI121=0,BI121=1),GM121-GX121,0) -> 0 | GO121: =IF(BI121=2,GM121-GX121,0) -> 0 | GP121: =IF(BI121=4,GM121-GX121,0) -> 0 | GR121: 1 | GS121: 1 | GT121: 0 | GV121: =ROUND((GT121),6) -> 0 | GW121: 1 | GX121: =ROUND(HC121*I121,2) -> 0 | HA121: 0 | HB121: 0 | HC121: =GV121*GW121 -> 0 | HE121: 3 | HF121: 1,2 | HS121: 0 | IK121: 0
A122: 17 | B122: 1 | E122: 13 | F122: КА №3 | G122: Диспенсер настенный для бумажных полотенец, 325х245х109 мм, цвет: глянцевый хром, корпус из нержавеющей стали AISI 304 толщиной 1,2 мм. Типа 04046.В | H122: шт. | I122: 1 | J122: 0 | K122: 1 | O122: =ROUND(CP122,2) -> 1253.05 | P122: =ROUND((ROUND((AC122*I122),2)*BC122),2) -> 1253.05 | Q122: =(ROUND((ROUND(((ET122)*AV122*I122),2)*BB122),2)+ROUND((ROUND(((AE122-(EU122))*AV122*I122),2)*BS122),2)) -> 0 | R122: =(ROUND((ROUND(((EU122)*AV122*I122),2)*BS122),2)+ROUND((ROUND(((AE122-(EU122))*AV122*I122),2)*BS122),2)) -> 0 | S122: =ROUND((ROUND((AF122*AV122*I122),2)*BA122),2) -> 0 | T122: =ROUND(CU122*I122,2) -> 0 | U122: =CV122*I122 -> 0 | V122: =CW122*I122 -> 0 | W122: =ROUND(CX122*I122,2) -> 0 | X122: =(ROUND((((S122+ROUND((ROUND(((EU122)*AV122*I122),2)*BS122),2))*AT122)/100),2)+ROUND(((ROUND((ROUND(((AE122-(EU122))*AV122*I122),2)*BS122),2)*AT122)/100),2)) -> 0 | Y122: =(ROUND((((S122+ROUND((ROUND(((EU122)*AV122*I122),2)*BS122),2))*AU122)/100),2)+ROUND(((ROUND((ROUND(((AE122-(EU122))*AV122*I122),2)*BS122),2)*AU122)/100),2)) -> 0 | AA122: 59499218 | AB122: =ROUND((AC122+AD122+AF122),6) -> 1253.05 | AC122: =ROUND((ES122),6) -> 1253.05 | AD122: =ROUND((((ET122)-(EU122))+AE122),6) -> 0 | AE122: =ROUND((EU122),6) -> 0 | AF122: =ROUND((EV122),6) -> 0 | AG122: =ROUND((AP122),6) -> 0 | AH122: =(EW122) -> 0 | AI122: =(EX122) -> 0 | AJ122: =(AS122) -> 0 | AK122: 1253.05 | AL122: 1253.05 | AM122: 0 | AN122: 0 | AO122: 0 | AP122: 0 | AQ122: 0 | AR122: 0 | AS122: 0 | AT122: 0 | AU122: 0 | AV122: 1 | AW122: 1 | AZ122: 1 | BA122: 1 | BB122: 1 | BC122: 1 | BH122: 3 | BI122: 3 | BM122: 746 | BN122: 0 | BP122: 0 | BQ122: 130 | BR122: 0 | BS122: 1 | BT122: 1 | BU122: 1 | BV122: 1 | BW122: 1 | BX122: 1 | BZ122: 0 | CA122: 0 | CE122: 1566 | CF122: 0 | CG122: 0 | CM122: 0 | CO122: 0 | CP122: =(P122+Q122+S122) -> 1253.05 | CQ122: =ROUND((ROUND((AC122*1),2)*BC122),2) -> 1253.05 | CR122: =(ROUND((ROUND(((ET122)*AV122*1),2)*BB122),2)+ROUND((ROUND(((AE122-(EU122))*AV122*1),2)*BS122),2)) -> 0 | CS122: =(ROUND((ROUND(((EU122)*AV122*1),2)*BS122),2)+ROUND((ROUND(((AE122-(EU122))*AV122*1),2)*BS122),2)) -> 0 | CT122: =ROUND((ROUND((AF122*AV122*1),2)*BA122),2) -> 0 | CU122: =AG122 -> 0 | CV122: =(AH122*AV122) -> 0 | CW122: =AI122 -> 0 | CX122: =AJ122 -> 0 | CY122: =(ROUND((((S122+ROUND((ROUND(((EU122)*AV122*1),2)*BS122),2))*AT122)/100),2)+ROUND(((ROUND((ROUND(((AE122-(EU122))*AV122*1),2)*BS122),2)*AT122)/100),2)) -> 0 | CZ122: =(ROUND((((S122+ROUND((ROUND(((EU122)*AV122*1),2)*BS122),2))*AU122)/100),2)+ROUND(((ROUND((ROUND(((AE122-(EU122))*AV122*1),2)*BS122),2)*AU122)/100),2)) -> 0 | DN122: 0 | DO122: 0 | DP122: 1 | DQ122: 1 | DU122: 1010 | DV122: шт. | DW122: шт. | DX122: 1 | EE122: 59299131 | EF122: 130 | EG122: Сметная стоимость оборудования | EH122: 0 | EJ122: 3 | EK122: 746 | EL122: ТСН-2001.13. Сметная стоимость оборудования | EM122: ТСН-2001.13 | EQ122: 0 | ER122: 0 | ES122: 1253.05 | ET122: 0 | EU122: 0 | EV122: 0 | EW122: 0 | EX122: 0 | EY122: 0 | FQ122: 0 | FR122: =P122 -> 1253.05 | FS122: 0 | FX122: 0 | FY122: 0 | GA122: [11 050 / 1,2 / 7,66] + 3% Трансп + 1,2% Заг.скл | GD122: 1 | GF122: 320934078 | GG122: 2 | GH122: 4 | GI122: -2 | GJ122: 0 | GK122: 0 | GL122: =ROUND(IF(AND(BH122=3,BI122=3,FS122<>0),P122,0),2) -> 0 | GM122: =ROUND(O122+X122+Y122,2)+GX122 -> 1253.05 | GN122: =IF(OR(BI122=0,BI122=1),GM122-GX122,0) -> 0 | GO122: =IF(BI122=2,GM122-GX122,0) -> 0 | GP122: =IF(BI122=4,GM122-GX122,0) -> 0 | GR122: 0 | GS122: 2 | GT122: 0 | GV122: =ROUND((GT122),6) -> 0 | GW122: 1 | GX122: =ROUND(HC122*I122,2) -> 0 | HA122: 0 | HB122: 0 | HC122: =GV122*GW122 -> 0 | HE122: 3 | HF122: 1,2 | HS122: 0 | IK122: 0
A123: 17 | B123: 1 | E123: 13 | F123: КА №3 | G123: Диспенсер настенный для бумажных полотенец, 325х245х109 мм, цвет: глянцевый хром, корпус из нержавеющей стали AISI 304 толщиной 1,2 мм. Типа 04046.В | H123: шт. | I123: 1 | J123: 0 | K123: 1 | O123: =ROUND(CP123,2) -> 9598.36 | P123: =ROUND((ROUND((AC123*I123),2)*BC123),2) -> 9598.36 | Q123: =(ROUND((ROUND(((ET123)*AV123*I123),2)*BB123),2)+ROUND((ROUND(((AE123-(EU123))*AV123*I123),2)*BS123),2)) -> 0 | R123: =(ROUND((ROUND(((EU123)*AV123*I123),2)*BS123),2)+ROUND((ROUND(((AE123-(EU123))*AV123*I123),2)*BS123),2)) -> 0 | S123: =ROUND((ROUND((AF123*AV123*I123),2)*BA123),2) -> 0 | T123: =ROUND(CU123*I123,2) -> 0 | U123: =CV123*I123 -> 0 | V123: =CW123*I123 -> 0 | W123: =ROUND(CX123*I123,2) -> 0 | X123: =(ROUND((((S123+ROUND((ROUND(((EU123)*AV123*I123),2)*BS123),2))*AT123)/100),2)+ROUND(((ROUND((ROUND(((AE123-(EU123))*AV123*I123),2)*BS123),2)*AT123)/100),2)) -> 0 | Y123: =(ROUND((((S123+ROUND((ROUND(((EU123)*AV123*I123),2)*BS123),2))*AU123)/100),2)+ROUND(((ROUND((ROUND(((AE123-(EU123))*AV123*I123),2)*BS123),2)*AU123)/100),2)) -> 0 | AA123: 59499215 | AB123: =ROUND((AC123+AD123+AF123),6) -> 1253.05 | AC123: =ROUND((ES123),6) -> 1253.05 | AD123: =ROUND((((ET123)-(EU123))+AE123),6) -> 0 | AE123: =ROUND((EU123),6) -> 0 | AF123: =ROUND((EV123),6) -> 0 | AG123: =ROUND((AP123),6) -> 0 | AH123: =(EW123) -> 0 | AI123: =(EX123) -> 0 | AJ123: =(AS123) -> 0 | AK123: 1253.05 | AL123: 1253.05 | AM123: 0 | AN123: 0 | AO123: 0 | AP123: 0 | AQ123: 0 | AR123: 0 | AS123: 0 | AT123: 0 | AU123: 0 | AV123: 1 | AW123: 1 | AZ123: 1 | BA123: 1 | BB123: 1 | BC123: 7.66 | BH123: 3 | BI123: 3 | BM123: 746 | BN123: 0 | BP123: 0 | BQ123: 130 | BR123: 0 | BS123: 1 | BT123: 1 | BU123: 1 | BV123: 1 | BW123: 1 | BX123: 1 | BZ123: 0 | CA123: 0 | CE123: 1566 | CF123: 0 | CG123: 0 | CM123: 0 | CO123: 0 | CP123: =(P123+Q123+S123) -> 9598.36 | CQ123: =ROUND((ROUND((AC123*1),2)*BC123),2) -> 9598.36 | CR123: =(ROUND((ROUND(((ET123)*AV123*1),2)*BB123),2)+ROUND((ROUND(((AE123-(EU123))*AV123*1),2)*BS123),2)) -> 0 | CS123: =(ROUND((ROUND(((EU123)*AV123*1),2)*BS123),2)+ROUND((ROUND(((AE123-(EU123))*AV123*1),2)*BS123),2)) -> 0 | CT123: =ROUND((ROUND((AF123*AV123*1),2)*BA123),2) -> 0 | CU123: =AG123 -> 0 | CV123: =(AH123*AV123) -> 0 | CW123: =AI123 -> 0 | CX123: =AJ123 -> 0 | CY123: =(ROUND((((S123+ROUND((ROUND(((EU123)*AV123*1),2)*BS123),2))*AT123)/100),2)+ROUND(((ROUND((ROUND(((AE123-(EU123))*AV123*1),2)*BS123),2)*AT123)/100),2)) -> 0 | CZ123: =(ROUND((((S123+ROUND((ROUND(((EU123)*AV123*1),2)*BS123),2))*AU123)/100),2)+ROUND(((ROUND((ROUND(((AE123-(EU123))*AV123*1),2)*BS123),2)*AU123)/100),2)) -> 0 | DN123: 0 | DO123: 0 | DP123: 1 | DQ123: 1 | DU123: 1010 | DV123: шт. | DW123: шт. | DX123: 1 | EE123: 59299131 | EF123: 130 | EG123: Сметная стоимость оборудования | EH123: 0 | EJ123: 3 | EK123: 746 | EL123: ТСН-2001.13. Сметная стоимость оборудования | EM123: ТСН-2001.13 | EQ123: 0 | ER123: 1253.05 | ES123: 1253.05 | ET123: 0 | EU123: 0 | EV123: 0 | EW123: 0 | EX123: 0 | EY123: 0 | EZ123: 5 | FC123: 1 | FD123: 18 | FF123: 11050 | FQ123: 0 | FR123: =P123 -> 9598.36 | FS123: 0 | FX123: 0 | FY123: 0 | GA123: [11 050 / 1,2 / 7,66] + 3% Трансп + 1,2% Заг.скл | GD123: 1 | GF123: 320934078 | GG123: 2 | GH123: 3 | GI123: 3 | GJ123: 0 | GK123: 0 | GL123: =ROUND(IF(AND(BH123=3,BI123=3,FS123<>0),P123,0),2) -> 0 | GM123: =ROUND(O123+X123+Y123,2)+GX123 -> 9598.36 | GN123: =IF(OR(BI123=0,BI123=1),GM123-GX123,0) -> 0 | GO123: =IF(BI123=2,GM123-GX123,0) -> 0 | GP123: =IF(BI123=4,GM123-GX123,0) -> 0 | GR123: 1 | GS123: 1 | GT123: 0 | GV123: =ROUND((GT123),6) -> 0 | GW123: 1 | GX123: =ROUND(HC123*I123,2) -> 0 | HA123: 0 | HB123: 0 | HC123: =GV123*GW123 -> 0 | HE123: 3 | HF123: 1,2 | HS123: 0 | IK123: 0
A124: 17 | B124: 1 | E124: 14 | F124: КА №4 | G124: Диспенсер для жидкого мыла сенсорный автоматический, 275х105х95 мм, цвет: глянцевый хром, корпус из нержавеющей стали AISI 304 толщиной 1,0 мм. Типа 03039.B | H124: шт. | I124: 1 | J124: 0 | K124: 1 | O124: =ROUND(CP124,2) -> 1869.94 | P124: =ROUND((ROUND((AC124*I124),2)*BC124),2) -> 1869.94 | Q124: =(ROUND((ROUND(((ET124)*AV124*I124),2)*BB124),2)+ROUND((ROUND(((AE124-(EU124))*AV124*I124),2)*BS124),2)) -> 0 | R124: =(ROUND((ROUND(((EU124)*AV124*I124),2)*BS124),2)+ROUND((ROUND(((AE124-(EU124))*AV124*I124),2)*BS124),2)) -> 0 | S124: =ROUND((ROUND((AF124*AV124*I124),2)*BA124),2) -> 0 | T124: =ROUND(CU124*I124,2) -> 0 | U124: =CV124*I124 -> 0 | V124: =CW124*I124 -> 0 | W124: =ROUND(CX124*I124,2) -> 0 | X124: =(ROUND((((S124+ROUND((ROUND(((EU124)*AV124*I124),2)*BS124),2))*AT124)/100),2)+ROUND(((ROUND((ROUND(((AE124-(EU124))*AV124*I124),2)*BS124),2)*AT124)/100),2)) -> 0 | Y124: =(ROUND((((S124+ROUND((ROUND(((EU124)*AV124*I124),2)*BS124),2))*AU124)/100),2)+ROUND(((ROUND((ROUND(((AE124-(EU124))*AV124*I124),2)*BS124),2)*AU124)/100),2)) -> 0 | AA124: 59499218 | AB124: =ROUND((AC124+AD124+AF124),6) -> 1869.94 | AC124: =ROUND((ES124),6) -> 1869.94 | AD124: =ROUND((((ET124)-(EU124))+AE124),6) -> 0 | AE124: =ROUND((EU124),6) -> 0 | AF124: =ROUND((EV124),6) -> 0 | AG124: =ROUND((AP124),6) -> 0 | AH124: =(EW124) -> 0 | AI124: =(EX124) -> 0 | AJ124: =(AS124) -> 0 | AK124: 1869.94 | AL124: 1869.94 | AM124: 0 | AN124: 0 | AO124: 0 | AP124: 0 | AQ124: 0 | AR124: 0 | AS124: 0 | AT124: 0 | AU124: 0 | AV124: 1 | AW124: 1 | AZ124: 1 | BA124: 1 | BB124: 1 | BC124: 1 | BH124: 3 | BI124: 3 | BM124: 746 | BN124: 0 | BP124: 0 | BQ124: 130 | BR124: 0 | BS124: 1 | BT124: 1 | BU124: 1 | BV124: 1 | BW124: 1 | BX124: 1 | BZ124: 0 | CA124: 0 | CE124: 1566 | CF124: 0 | CG124: 0 | CM124: 0 | CO124: 0 | CP124: =(P124+Q124+S124) -> 1869.94 | CQ124: =ROUND((ROUND((AC124*1),2)*BC124),2) -> 1869.94 | CR124: =(ROUND((ROUND(((ET124)*AV124*1),2)*BB124),2)+ROUND((ROUND(((AE124-(EU124))*AV124*1),2)*BS124),2)) -> 0 | CS124: =(ROUND((ROUND(((EU124)*AV124*1),2)*BS124),2)+ROUND((ROUND(((AE124-(EU124))*AV124*1),2)*BS124),2)) -> 0 | CT124: =ROUND((ROUND((AF124*AV124*1),2)*BA124),2) -> 0 | CU124: =AG124 -> 0 | CV124: =(AH124*AV124) -> 0 | CW124: =AI124 -> 0 | CX124: =AJ124 -> 0 | CY124: =(ROUND((((S124+ROUND((ROUND(((EU124)*AV124*1),2)*BS124),2))*AT124)/100),2)+ROUND(((ROUND((ROUND(((AE124-(EU124))*AV124*1),2)*BS124),2)*AT124)/100),2)) -> 0 | CZ124: =(ROUND((((S124+ROUND((ROUND(((EU124)*AV124*1),2)*BS124),2))*AU124)/100),2)+ROUND(((ROUND((ROUND(((AE124-(EU124))*AV124*1),2)*BS124),2)*AU124)/100),2)) -> 0 | DN124: 0 | DO124: 0 | DP124: 1 | DQ124: 1 | DU124: 1010 | DV124: шт. | DW124: шт. | DX124: 1 | EE124: 59299131 | EF124: 130 | EG124: Сметная стоимость оборудования | EH124: 0 | EJ124: 3 | EK124: 746 | EL124: ТСН-2001.13. Сметная стоимость оборудования | EM124: ТСН-2001.13 | EQ124: 0 | ER124: 0 | ES124: 1869.94 | ET124: 0 | EU124: 0 | EV124: 0 | EW124: 0 | EX124: 0 | EY124: 0 | FQ124: 0 | FR124: =P124 -> 1869.94 | FS124: 0 | FX124: 0 | FY124: 0 | GA124: [16 490 / 1,2 / 7,66] + 3% Трансп + 1,2% Заг.скл | GD124: 1 | GF124: 703989269 | GG124: 2 | GH124: 4 | GI124: -2 | GJ124: 0 | GK124: 0 | GL124: =ROUND(IF(AND(BH124=3,BI124=3,FS124<>0),P124,0),2) -> 0 | GM124: =ROUND(O124+X124+Y124,2)+GX124 -> 1869.94 | GN124: =IF(OR(BI124=0,BI124=1),GM124-GX124,0) -> 0 | GO124: =IF(BI124=2,GM124-GX124,0) -> 0 | GP124: =IF(BI124=4,GM124-GX124,0) -> 0 | GR124: 0 | GS124: 2 | GT124: 0 | GV124: =ROUND((GT124),6) -> 0 | GW124: 1 | GX124: =ROUND(HC124*I124,2) -> 0 | HA124: 0 | HB124: 0 | HC124: =GV124*GW124 -> 0 | HE124: 3 | HF124: 1,2 | HS124: 0 | IK124: 0
A125: 17 | B125: 1 | E125: 14 | F125: КА №4 | G125: Диспенсер для жидкого мыла сенсорный автоматический, 275х105х95 мм, цвет: глянцевый хром, корпус из нержавеющей стали AISI 304 толщиной 1,0 мм. Типа 03039.B | H125: шт. | I125: 1 | J125: 0 | K125: 1 | O125: =ROUND(CP125,2) -> 14323.74 | P125: =ROUND((ROUND((AC125*I125),2)*BC125),2) -> 14323.74 | Q125: =(ROUND((ROUND(((ET125)*AV125*I125),2)*BB125),2)+ROUND((ROUND(((AE125-(EU125))*AV125*I125),2)*BS125),2)) -> 0 | R125: =(ROUND((ROUND(((EU125)*AV125*I125),2)*BS125),2)+ROUND((ROUND(((AE125-(EU125))*AV125*I125),2)*BS125),2)) -> 0 | S125: =ROUND((ROUND((AF125*AV125*I125),2)*BA125),2) -> 0 | T125: =ROUND(CU125*I125,2) -> 0 | U125: =CV125*I125 -> 0 | V125: =CW125*I125 -> 0 | W125: =ROUND(CX125*I125,2) -> 0 | X125: =(ROUND((((S125+ROUND((ROUND(((EU125)*AV125*I125),2)*BS125),2))*AT125)/100),2)+ROUND(((ROUND((ROUND(((AE125-(EU125))*AV125*I125),2)*BS125),2)*AT125)/100),2)) -> 0 | Y125: =(ROUND((((S125+ROUND((ROUND(((EU125)*AV125*I125),2)*BS125),2))*AU125)/100),2)+ROUND(((ROUND((ROUND(((AE125-(EU125))*AV125*I125),2)*BS125),2)*AU125)/100),2)) -> 0 | AA125: 59499215 | AB125: =ROUND((AC125+AD125+AF125),6) -> 1869.94 | AC125: =ROUND((ES125),6) -> 1869.94 | AD125: =ROUND((((ET125)-(EU125))+AE125),6) -> 0 | AE125: =ROUND((EU125),6) -> 0 | AF125: =ROUND((EV125),6) -> 0 | AG125: =ROUND((AP125),6) -> 0 | AH125: =(EW125) -> 0 | AI125: =(EX125) -> 0 | AJ125: =(AS125) -> 0 | AK125: 1869.94 | AL125: 1869.94 | AM125: 0 | AN125: 0 | AO125: 0 | AP125: 0 | AQ125: 0 | AR125: 0 | AS125: 0 | AT125: 0 | AU125: 0 | AV125: 1 | AW125: 1 | AZ125: 1 | BA125: 1 | BB125: 1 | BC125: 7.66 | BH125: 3 | BI125: 3 | BM125: 746 | BN125: 0 | BP125: 0 | BQ125: 130 | BR125: 0 | BS125: 1 | BT125: 1 | BU125: 1 | BV125: 1 | BW125: 1 | BX125: 1 | BZ125: 0 | CA125: 0 | CE125: 1566 | CF125: 0 | CG125: 0 | CM125: 0 | CO125: 0 | CP125: =(P125+Q125+S125) -> 14323.74 | CQ125: =ROUND((ROUND((AC125*1),2)*BC125),2) -> 14323.74 | CR125: =(ROUND((ROUND(((ET125)*AV125*1),2)*BB125),2)+ROUND((ROUND(((AE125-(EU125))*AV125*1),2)*BS125),2)) -> 0 | CS125: =(ROUND((ROUND(((EU125)*AV125*1),2)*BS125),2)+ROUND((ROUND(((AE125-(EU125))*AV125*1),2)*BS125),2)) -> 0 | CT125: =ROUND((ROUND((AF125*AV125*1),2)*BA125),2) -> 0 | CU125: =AG125 -> 0 | CV125: =(AH125*AV125) -> 0 | CW125: =AI125 -> 0 | CX125: =AJ125 -> 0 | CY125: =(ROUND((((S125+ROUND((ROUND(((EU125)*AV125*1),2)*BS125),2))*AT125)/100),2)+ROUND(((ROUND((ROUND(((AE125-(EU125))*AV125*1),2)*BS125),2)*AT125)/100),2)) -> 0 | CZ125: =(ROUND((((S125+ROUND((ROUND(((EU125)*AV125*1),2)*BS125),2))*AU125)/100),2)+ROUND(((ROUND((ROUND(((AE125-(EU125))*AV125*1),2)*BS125),2)*AU125)/100),2)) -> 0 | DN125: 0 | DO125: 0 | DP125: 1 | DQ125: 1 | DU125: 1010 | DV125: шт. | DW125: шт. | DX125: 1 | EE125: 59299131 | EF125: 130 | EG125: Сметная стоимость оборудования | EH125: 0 | EJ125: 3 | EK125: 746 | EL125: ТСН-2001.13. Сметная стоимость оборудования | EM125: ТСН-2001.13 | EQ125: 0 | ER125: 1869.94 | ES125: 1869.94 | ET125: 0 | EU125: 0 | EV125: 0 | EW125: 0 | EX125: 0 | EY125: 0 | EZ125: 5 | FC125: 1 | FD125: 18 | FF125: 16490 | FQ125: 0 | FR125: =P125 -> 14323.74 | FS125: 0 | FX125: 0 | FY125: 0 | GA125: [16 490 / 1,2 / 7,66] + 3% Трансп + 1,2% Заг.скл | GD125: 1 | GF125: 703989269 | GG125: 2 | GH125: 3 | GI125: 3 | GJ125: 0 | GK125: 0 | GL125: =ROUND(IF(AND(BH125=3,BI125=3,FS125<>0),P125,0),2) -> 0 | GM125: =ROUND(O125+X125+Y125,2)+GX125 -> 14323.74 | GN125: =IF(OR(BI125=0,BI125=1),GM125-GX125,0) -> 0 | GO125: =IF(BI125=2,GM125-GX125,0) -> 0 | GP125: =IF(BI125=4,GM125-GX125,0) -> 0 | GR125: 1 | GS125: 1 | GT125: 0 | GV125: =ROUND((GT125),6) -> 0 | GW125: 1 | GX125: =ROUND(HC125*I125,2) -> 0 | HA125: 0 | HB125: 0 | HC125: =GV125*GW125 -> 0 | HE125: 3 | HF125: 1,2 | HS125: 0 | IK125: 0
A126: 17 | B126: 1 | E126: 15 | F126: КА №5 | G126: Диспенсер для туалетной бумаги, 260х112х260 мм, цвет: глянцевый хром, корпус изнержавеющей стали AISI 304 толщиной 1,0 мм. Типа 05006.B | H126: шт. | I126: 1 | J126: 0 | K126: 1 | O126: =ROUND(CP126,2) -> 605.55 | P126: =ROUND((ROUND((AC126*I126),2)*BC126),2) -> 605.55 | Q126: =(ROUND((ROUND(((ET126)*AV126*I126),2)*BB126),2)+ROUND((ROUND(((AE126-(EU126))*AV126*I126),2)*BS126),2)) -> 0 | R126: =(ROUND((ROUND(((EU126)*AV126*I126),2)*BS126),2)+ROUND((ROUND(((AE126-(EU126))*AV126*I126),2)*BS126),2)) -> 0 | S126: =ROUND((ROUND((AF126*AV126*I126),2)*BA126),2) -> 0 | T126: =ROUND(CU126*I126,2) -> 0 | U126: =CV126*I126 -> 0 | V126: =CW126*I126 -> 0 | W126: =ROUND(CX126*I126,2) -> 0 | X126: =(ROUND((((S126+ROUND((ROUND(((EU126)*AV126*I126),2)*BS126),2))*AT126)/100),2)+ROUND(((ROUND((ROUND(((AE126-(EU126))*AV126*I126),2)*BS126),2)*AT126)/100),2)) -> 0 | Y126: =(ROUND((((S126+ROUND((ROUND(((EU126)*AV126*I126),2)*BS126),2))*AU126)/100),2)+ROUND(((ROUND((ROUND(((AE126-(EU126))*AV126*I126),2)*BS126),2)*AU126)/100),2)) -> 0 | AA126: 59499218 | AB126: =ROUND((AC126+AD126+AF126),6) -> 605.55 | AC126: =ROUND((ES126),6) -> 605.55 | AD126: =ROUND((((ET126)-(EU126))+AE126),6) -> 0 | AE126: =ROUND((EU126),6) -> 0 | AF126: =ROUND((EV126),6) -> 0 | AG126: =ROUND((AP126),6) -> 0 | AH126: =(EW126) -> 0 | AI126: =(EX126) -> 0 | AJ126: =(AS126) -> 0 | AK126: 605.55 | AL126: 605.55 | AM126: 0 | AN126: 0 | AO126: 0 | AP126: 0 | AQ126: 0 | AR126: 0 | AS126: 0 | AT126: 0 | AU126: 0 | AV126: 1 | AW126: 1 | AZ126: 1 | BA126: 1 | BB126: 1 | BC126: 1 | BH126: 3 | BI126: 3 | BM126: 746 | BN126: 0 | BP126: 0 | BQ126: 130 | BR126: 0 | BS126: 1 | BT126: 1 | BU126: 1 | BV126: 1 | BW126: 1 | BX126: 1 | BZ126: 0 | CA126: 0 | CE126: 1566 | CF126: 0 | CG126: 0 | CM126: 0 | CO126: 0 | CP126: =(P126+Q126+S126) -> 605.55 | CQ126: =ROUND((ROUND((AC126*1),2)*BC126),2) -> 605.55 | CR126: =(ROUND((ROUND(((ET126)*AV126*1),2)*BB126),2)+ROUND((ROUND(((AE126-(EU126))*AV126*1),2)*BS126),2)) -> 0 | CS126: =(ROUND((ROUND(((EU126)*AV126*1),2)*BS126),2)+ROUND((ROUND(((AE126-(EU126))*AV126*1),2)*BS126),2)) -> 0 | CT126: =ROUND((ROUND((AF126*AV126*1),2)*BA126),2) -> 0 | CU126: =AG126 -> 0 | CV126: =(AH126*AV126) -> 0 | CW126: =AI126 -> 0 | CX126: =AJ126 -> 0 | CY126: =(ROUND((((S126+ROUND((ROUND(((EU126)*AV126*1),2)*BS126),2))*AT126)/100),2)+ROUND(((ROUND((ROUND(((AE126-(EU126))*AV126*1),2)*BS126),2)*AT126)/100),2)) -> 0 | CZ126: =(ROUND((((S126+ROUND((ROUND(((EU126)*AV126*1),2)*BS126),2))*AU126)/100),2)+ROUND(((ROUND((ROUND(((AE126-(EU126))*AV126*1),2)*BS126),2)*AU126)/100),2)) -> 0 | DN126: 0 | DO126: 0 | DP126: 1 | DQ126: 1 | DU126: 1010 | DV126: шт. | DW126: шт. | DX126: 1 | EE126: 59299131 | EF126: 130 | EG126: Сметная стоимость оборудования | EH126: 0 | EJ126: 3 | EK126: 746 | EL126: ТСН-2001.13. Сметная стоимость оборудования | EM126: ТСН-2001.13 | EQ126: 0 | ER126: 0 | ES126: 605.55 | ET126: 0 | EU126: 0 | EV126: 0 | EW126: 0 | EX126: 0 | EY126: 0 | FQ126: 0 | FR126: =P126 -> 605.55 | FS126: 0 | FX126: 0 | FY126: 0 | GA126: [5 340 / 1,2 / 7,66] + 3% Трансп + 1,2% Заг.скл | GD126: 1 | GF126: 1544061745 | GG126: 2 | GH126: 4 | GI126: -2 | GJ126: 0 | GK126: 0 | GL126: =ROUND(IF(AND(BH126=3,BI126=3,FS126<>0),P126,0),2) -> 0 | GM126: =ROUND(O126+X126+Y126,2)+GX126 -> 605.55 | GN126: =IF(OR(BI126=0,BI126=1),GM126-GX126,0) -> 0 | GO126: =IF(BI126=2,GM126-GX126,0) -> 0 | GP126: =IF(BI126=4,GM126-GX126,0) -> 0 | GR126: 0 | GS126: 2 | GT126: 0 | GV126: =ROUND((GT126),6) -> 0 | GW126: 1 | GX126: =ROUND(HC126*I126,2) -> 0 | HA126: 0 | HB126: 0 | HC126: =GV126*GW126 -> 0 | HE126: 3 | HF126: 1,2 | HS126: 0 | IK126: 0
A127: 17 | B127: 1 | E127: 15 | F127: КА №5 | G127: Диспенсер для туалетной бумаги, 260х112х260 мм, цвет: глянцевый хром, корпус изнержавеющей стали AISI 304 толщиной 1,0 мм. Типа 05006.B | H127: шт. | I127: 1 | J127: 0 | K127: 1 | O127: =ROUND(CP127,2) -> 4638.51 | P127: =ROUND((ROUND((AC127*I127),2)*BC127),2) -> 4638.51 | Q127: =(ROUND((ROUND(((ET127)*AV127*I127),2)*BB127),2)+ROUND((ROUND(((AE127-(EU127))*AV127*I127),2)*BS127),2)) -> 0 | R127: =(ROUND((ROUND(((EU127)*AV127*I127),2)*BS127),2)+ROUND((ROUND(((AE127-(EU127))*AV127*I127),2)*BS127),2)) -> 0 | S127: =ROUND((ROUND((AF127*AV127*I127),2)*BA127),2) -> 0 | T127: =ROUND(CU127*I127,2) -> 0 | U127: =CV127*I127 -> 0 | V127: =CW127*I127 -> 0 | W127: =ROUND(CX127*I127,2) -> 0 | X127: =(ROUND((((S127+ROUND((ROUND(((EU127)*AV127*I127),2)*BS127),2))*AT127)/100),2)+ROUND(((ROUND((ROUND(((AE127-(EU127))*AV127*I127),2)*BS127),2)*AT127)/100),2)) -> 0 | Y127: =(ROUND((((S127+ROUND((ROUND(((EU127)*AV127*I127),2)*BS127),2))*AU127)/100),2)+ROUND(((ROUND((ROUND(((AE127-(EU127))*AV127*I127),2)*BS127),2)*AU127)/100),2)) -> 0 | AA127: 59499215 | AB127: =ROUND((AC127+AD127+AF127),6) -> 605.55 | AC127: =ROUND((ES127),6) -> 605.55 | AD127: =ROUND((((ET127)-(EU127))+AE127),6) -> 0 | AE127: =ROUND((EU127),6) -> 0 | AF127: =ROUND((EV127),6) -> 0 | AG127: =ROUND((AP127),6) -> 0 | AH127: =(EW127) -> 0 | AI127: =(EX127) -> 0 | AJ127: =(AS127) -> 0 | AK127: 605.55 | AL127: 605.55 | AM127: 0 | AN127: 0 | AO127: 0 | AP127: 0 | AQ127: 0 | AR127: 0 | AS127: 0 | AT127: 0 | AU127: 0 | AV127: 1 | AW127: 1 | AZ127: 1 | BA127: 1 | BB127: 1 | BC127: 7.66 | BH127: 3 | BI127: 3 | BM127: 746 | BN127: 0 | BP127: 0 | BQ127: 130 | BR127: 0 | BS127: 1 | BT127: 1 | BU127: 1 | BV127: 1 | BW127: 1 | BX127: 1 | BZ127: 0 | CA127: 0 | CE127: 1566 | CF127: 0 | CG127: 0 | CM127: 0 | CO127: 0 | CP127: =(P127+Q127+S127) -> 4638.51 | CQ127: =ROUND((ROUND((AC127*1),2)*BC127),2) -> 4638.51 | CR127: =(ROUND((ROUND(((ET127)*AV127*1),2)*BB127),2)+ROUND((ROUND(((AE127-(EU127))*AV127*1),2)*BS127),2)) -> 0 | CS127: =(ROUND((ROUND(((EU127)*AV127*1),2)*BS127),2)+ROUND((ROUND(((AE127-(EU127))*AV127*1),2)*BS127),2)) -> 0 | CT127: =ROUND((ROUND((AF127*AV127*1),2)*BA127),2) -> 0 | CU127: =AG127 -> 0 | CV127: =(AH127*AV127) -> 0 | CW127: =AI127 -> 0 | CX127: =AJ127 -> 0 | CY127: =(ROUND((((S127+ROUND((ROUND(((EU127)*AV127*1),2)*BS127),2))*AT127)/100),2)+ROUND(((ROUND((ROUND(((AE127-(EU127))*AV127*1),2)*BS127),2)*AT127)/100),2)) -> 0 | CZ127: =(ROUND((((S127+ROUND((ROUND(((EU127)*AV127*1),2)*BS127),2))*AU127)/100),2)+ROUND(((ROUND((ROUND(((AE127-(EU127))*AV127*1),2)*BS127),2)*AU127)/100),2)) -> 0 | DN127: 0 | DO127: 0 | DP127: 1 | DQ127: 1 | DU127: 1010 | DV127: шт. | DW127: шт. | DX127: 1 | EE127: 59299131 | EF127: 130 | EG127: Сметная стоимость оборудования | EH127: 0 | EJ127: 3 | EK127: 746 | EL127: ТСН-2001.13. Сметная стоимость оборудования | EM127: ТСН-2001.13 | EQ127: 0 | ER127: 605.55 | ES127: 605.55 | ET127: 0 | EU127: 0 | EV127: 0 | EW127: 0 | EX127: 0 | EY127: 0 | EZ127: 5 | FC127: 1 | FD127: 18 | FF127: 5340 | FQ127: 0 | FR127: =P127 -> 4638.51 | FS127: 0 | FX127: 0 | FY127: 0 | GA127: [5 340 / 1,2 / 7,66] + 3% Трансп + 1,2% Заг.скл | GD127: 1 | GF127: 1544061745 | GG127: 2 | GH127: 3 | GI127: 3 | GJ127: 0 | GK127: 0 | GL127: =ROUND(IF(AND(BH127=3,BI127=3,FS127<>0),P127,0),2) -> 0 | GM127: =ROUND(O127+X127+Y127,2)+GX127 -> 4638.51 | GN127: =IF(OR(BI127=0,BI127=1),GM127-GX127,0) -> 0 | GO127: =IF(BI127=2,GM127-GX127,0) -> 0 | GP127: =IF(BI127=4,GM127-GX127,0) -> 0 | GR127: 1 | GS127: 1 | GT127: 0 | GV127: =ROUND((GT127),6) -> 0 | GW127: 1 | GX127: =ROUND(HC127*I127,2) -> 0 | HA127: 0 | HB127: 0 | HC127: =GV127*GW127 -> 0 | HE127: 3 | HF127: 1,2 | HS127: 0 | IK127: 0
A128: 17 | B128: 1 | E128: 16 | F128: КА №6 | G128: Ершик туалетный с креплением на стену NIZA 16857.S | H128: шт. | I128: 1 | J128: 0 | K128: 1 | O128: =ROUND(CP128,2) -> 514.26 | P128: =ROUND((ROUND((AC128*I128),2)*BC128),2) -> 514.26 | Q128: =(ROUND((ROUND(((ET128)*AV128*I128),2)*BB128),2)+ROUND((ROUND(((AE128-(EU128))*AV128*I128),2)*BS128),2)) -> 0 | R128: =(ROUND((ROUND(((EU128)*AV128*I128),2)*BS128),2)+ROUND((ROUND(((AE128-(EU128))*AV128*I128),2)*BS128),2)) -> 0 | S128: =ROUND((ROUND((AF128*AV128*I128),2)*BA128),2) -> 0 | T128: =ROUND(CU128*I128,2) -> 0 | U128: =CV128*I128 -> 0 | V128: =CW128*I128 -> 0 | W128: =ROUND(CX128*I128,2) -> 0 | X128: =(ROUND((((S128+ROUND((ROUND(((EU128)*AV128*I128),2)*BS128),2))*AT128)/100),2)+ROUND(((ROUND((ROUND(((AE128-(EU128))*AV128*I128),2)*BS128),2)*AT128)/100),2)) -> 0 | Y128: =(ROUND((((S128+ROUND((ROUND(((EU128)*AV128*I128),2)*BS128),2))*AU128)/100),2)+ROUND(((ROUND((ROUND(((AE128-(EU128))*AV128*I128),2)*BS128),2)*AU128)/100),2)) -> 0 | AA128: 59499218 | AB128: =ROUND((AC128+AD128+AF128),6) -> 514.26 | AC128: =ROUND((ES128),6) -> 514.26 | AD128: =ROUND((((ET128)-(EU128))+AE128),6) -> 0 | AE128: =ROUND((EU128),6) -> 0 | AF128: =ROUND((EV128),6) -> 0 | AG128: =ROUND((AP128),6) -> 0 | AH128: =(EW128) -> 0 | AI128: =(EX128) -> 0 | AJ128: =(AS128) -> 0 | AK128: 514.26 | AL128: 514.26 | AM128: 0 | AN128: 0 | AO128: 0 | AP128: 0 | AQ128: 0 | AR128: 0 | AS128: 0 | AT128: 0 | AU128: 0 | AV128: 1 | AW128: 1 | AZ128: 1 | BA128: 1 | BB128: 1 | BC128: 1 | BH128: 3 | BI128: 3 | BM128: 746 | BN128: 0 | BP128: 0 | BQ128: 130 | BR128: 0 | BS128: 1 | BT128: 1 | BU128: 1 | BV128: 1 | BW128: 1 | BX128: 1 | BZ128: 0 | CA128: 0 | CE128: 1566 | CF128: 0 | CG128: 0 | CM128: 0 | CO128: 0 | CP128: =(P128+Q128+S128) -> 514.26 | CQ128: =ROUND((ROUND((AC128*1),2)*BC128),2) -> 514.26 | CR128: =(ROUND((ROUND(((ET128)*AV128*1),2)*BB128),2)+ROUND((ROUND(((AE128-(EU128))*AV128*1),2)*BS128),2)) -> 0 | CS128: =(ROUND((ROUND(((EU128)*AV128*1),2)*BS128),2)+ROUND((ROUND(((AE128-(EU128))*AV128*1),2)*BS128),2)) -> 0 | CT128: =ROUND((ROUND((AF128*AV128*1),2)*BA128),2) -> 0 | CU128: =AG128 -> 0 | CV128: =(AH128*AV128) -> 0 | CW128: =AI128 -> 0 | CX128: =AJ128 -> 0 | CY128: =(ROUND((((S128+ROUND((ROUND(((EU128)*AV128*1),2)*BS128),2))*AT128)/100),2)+ROUND(((ROUND((ROUND(((AE128-(EU128))*AV128*1),2)*BS128),2)*AT128)/100),2)) -> 0 | CZ128: =(ROUND((((S128+ROUND((ROUND(((EU128)*AV128*1),2)*BS128),2))*AU128)/100),2)+ROUND(((ROUND((ROUND(((AE128-(EU128))*AV128*1),2)*BS128),2)*AU128)/100),2)) -> 0 | DN128: 0 | DO128: 0 | DP128: 1 | DQ128: 1 | DU128: 1010 | DV128: шт. | DW128: шт. | DX128: 1 | EE128: 59299131 | EF128: 130 | EG128: Сметная стоимость оборудования | EH128: 0 | EJ128: 3 | EK128: 746 | EL128: ТСН-2001.13. Сметная стоимость оборудования | EM128: ТСН-2001.13 | EQ128: 0 | ER128: 0 | ES128: 514.26 | ET128: 0 | EU128: 0 | EV128: 0 | EW128: 0 | EX128: 0 | EY128: 0 | FQ128: 0 | FR128: =P128 -> 514.26 | FS128: 0 | FX128: 0 | FY128: 0 | GA128: [4 535 / 1,2 / 7,66] + 3% Трансп + 1,2% Заг.скл | GD128: 1 | GF128: 1595785961 | GG128: 2 | GH128: 4 | GI128: -2 | GJ128: 0 | GK128: 0 | GL128: =ROUND(IF(AND(BH128=3,BI128=3,FS128<>0),P128,0),2) -> 0 | GM128: =ROUND(O128+X128+Y128,2)+GX128 -> 514.26 | GN128: =IF(OR(BI128=0,BI128=1),GM128-GX128,0) -> 0 | GO128: =IF(BI128=2,GM128-GX128,0) -> 0 | GP128: =IF(BI128=4,GM128-GX128,0) -> 0 | GR128: 0 | GS128: 2 | GT128: 0 | GV128: =ROUND((GT128),6) -> 0 | GW128: 1 | GX128: =ROUND(HC128*I128,2) -> 0 | HA128: 0 | HB128: 0 | HC128: =GV128*GW128 -> 0 | HE128: 3 | HF128: 1,2 | HS128: 0 | IK128: 0
...

Sheet SourceObSm
A1: 0 | B1: Smeta.RU (495) 974-1589 | D1: _OBSM_ | F1: 0 | G1: 0 | H1: 0 | I1: Smeta.RU | K1: 1 | L1: 74561 | M1: 10 | N1: 12 | O1: 0 | P1: 0 | Q1: 3
A4: 1 | B4: 1 | C4: -1 | G4: Капитальный ремонт здания Государственного бюджетного общеобразовательного учреждения города Москвы «Школа № 236» по адресу: г. Москва, ул. Клязьминская, д. 7, к. 4. I этап | EC4: 0
A12: 1 | B12: 51 | C12: 0 | E12: 0 | F12: 02-01-22 | G12: 02-01-22 Мероприятия по обеспечению доступа инвалидов | I12: 0 | J12: 2024-00272-01-0-ОДИ.ВОР | K12: 0 | L12: 0 | M12: 4098 | O12: 0 | P12: 0 | Q12: 0 | R12: 0 | S12: 0 | T12: 1 | V12: 0 | AB12: Борисова Е.С. | BB12: 0 | BH12: Сметные нормы списания | BI12: Коды ОКП для ТСН-2001 МГЭ Дополнение 80 | BJ12: 1 | BK12: 1 | BL12: 0 | BM12: 0 | BN12: 1 | BO12: 0 | BP12: 6 | BQ12: 2 | BR12: 1 | BS12: 0 | BT12: 0 | BU12: 0 | BV12: 0 | BW12: 0 | BX12: 0 | BZ12: Типовой расчет для ТСН-2001 МГЭ, Дополнение 80, ремонт | CA12: Территориальные сметные нормативы для Москвы ТСН-2001 (МГЭ), дополнение 80 | CB12: Территориальные сметные нормативы для Москвы ТСН-2001 (МГЭ), дополнение 80 | CC12: Территориальные сметные нормативы для Москвы ТСН-2001 (МГЭ), дополнение 80 | CD12: Территориальные сметные нормативы для Москвы ТСН-2001 (МГЭ), дополнение 80 | CE12: Поправки для ТСН-2001 от 03.02.2026 г. доп.80 | CF12: 0 | CG12: 0 | CH12: 8 | CK12: 80 | CQ12: Территориальные сметные нормативы для Москвы (ТСН-2001) | CR12: ТЕР | CS12: 41660 | CT12: 1 | CU12: 80 | CY12: 0 | EC12: 0
A14: 22 | B14: 1 | C14: 0 | D14: 59499215 | E14: 59499218 | F14: 2 | G14: 1
A16: 3 | B16: 1 | C16: 02-01-22 | D16: Мероприятия по обеспечению доступа инвалидов | E16: =ROUND((Source!P480)/1000,2) -> 516.2 | F16: =ROUND((Source!P481)/1000,2) -> 0 | G16: =ROUND((Source!P472)/1000,2) -> 179.03 | H16: =ROUND((Source!P482)/1000+(Source!P483)/1000,2) -> 0 | I16: =E16+F16+G16+H16 -> 695.23 | J16: =ROUND((Source!P478+Source!P477)/1000,2) -> 83.03 | K16: 1076.84 | L16: 0 | M16: 0 | N16: =I16+L16+M16 -> 695.23 | T16: =ROUND((Source!F480)/1000,2) -> 42.72 | U16: =ROUND((Source!F481)/1000,2) -> 0 | V16: =ROUND((Source!F472)/1000,2) -> 35 | W16: =ROUND((Source!F482)/1000+(Source!F483)/1000,2) -> 0 | X16: =T16+U16+V16+W16 -> 77.72 | Y16: =ROUND((Source!F478+Source!F477)/1000,2) -> 1.51 | Z16: 149.71 | AA16: 0 | AB16: 0 | AC16: =X16+AA16+AB16 -> 77.72 | AI16: 2 | AJ16: -1 | AN16: 0 | AT16: 580010.74 | AU16: 496833.91 | AV16: 0 | AW16: 179025.07 | AX16: 0 | AY16: 233.23 | AZ16: 87.99 | BA16: 82943.6 | BB16: 516199.83 | BC16: 0 | BD16: 0 | BE16: 0 | BF16: 97.728297 | BG16: 0 | BH16: 0 | BI16: 73119.2 | BJ16: 42094.96 | BK16: 695224.9 | BR16: 75620.22 | BS16: 74094.28 | BT16: 0 | BU16: 34995.36 | BV16: 0 | BW16: 17.6 | BX16: 1.6 | BY16: 1508.34 | BZ16: 42720.06 | CA16: 0 | CB16: 0 | CC16: 0 | CD16: 97.728297 | CE16: 0 | CF16: 0 | CG16: 1329.7 | CH16: 765.5 | CI16: 77715.42
A18: 51 | E18: 516.2 | F18: 0 | G18: 179.03 | H18: 0 | I18: 695.23 | J18: 83.03 | K18: 1076.84 | L18: 0 | M18: 0 | N18: 695.23 | T18: 42.72 | U18: 0 | V18: 35 | W18: 0 | X18: 77.72 | Y18: 1.51 | Z18: 149.71 | AA18: 0 | AB18: 0 | AC18: 77.72
A20: 50 | B20: 0 | C20: 0 | D20: 1 | E20: 201 | F20: 580010.74 | G20: ПЗ | H20: Прямые затраты | K20: 201 | L20: 1 | M20: 3 | O20: 2 | P20: 75620.22
A21: 50 | B21: 0 | C21: 0 | D21: 1 | E21: 202 | F21: 496833.91 | G21: СтМатОб | H21: Стоимость материальных ресурсов (всего) | K21: 202 | L21: 2 | M21: 3 | O21: 2 | P21: 74094.28
A22: 50 | B22: 0 | C22: 0 | D22: 1 | E22: 222 | F22: 0 | G22: СтМатОбЗак | H22: Стоимость материалов и оборудования заказчика | K22: 222 | L22: 3 | M22: 3 | O22: 2 | P22: 0
A23: 50 | B23: 0 | C23: 0 | D23: 1 | E23: 225 | F23: 496833.91 | G23: СтМатОбПод | H23: Стоимость материалов и оборудования подрядчика | K23: 225 | L23: 4 | M23: 3 | O23: 2 | P23: 74094.28
A24: 50 | B24: 0 | C24: 0 | D24: 1 | E24: 226 | F24: 317808.84 | G24: СтМат | H24: Стоимость материалов (всего) | K24: 226 | L24: 5 | M24: 3 | O24: 2 | P24: 39098.92
A25: 50 | B25: 0 | C25: 0 | D25: 1 | E25: 227 | F25: 0 | G25: СтМатЗак | H25: Стоимость материалов заказчика | K25: 227 | L25: 6 | M25: 3 | O25: 2 | P25: 0
A26: 50 | B26: 0 | C26: 0 | D26: 1 | E26: 228 | F26: 317808.84 | G26: СтМатПод | H26: Стоимость материалов подрядчика | K26: 228 | L26: 7 | M26: 3 | O26: 2 | P26: 39098.92
A27: 50 | B27: 0 | C27: 0 | D27: 1 | E27: 216 | F27: 179025.07 | G27: Оборуд | H27: Стоимость оборудования (всего) | K27: 216 | L27: 8 | M27: 3 | O27: 2 | P27: 34995.36
A28: 50 | B28: 0 | C28: 0 | D28: 1 | E28: 223 | F28: 0 | G28: ОборудЗак | H28: Стоимость оборудования заказчика | K28: 223 | L28: 9 | M28: 3 | O28: 2 | P28: 0
A29: 50 | B29: 0 | C29: 0 | D29: 1 | E29: 229 | F29: 179025.07 | G29: ОборудПод | H29: Стоимость оборудования подрядчика | K29: 229 | L29: 10 | M29: 3 | O29: 2 | P29: 34995.36
A30: 50 | B30: 0 | C30: 0 | D30: 1 | E30: 203 | F30: 233.23 | G30: ЭММ | H30: Эксплуатация машин | K30: 203 | L30: 11 | M30: 3 | O30: 2 | P30: 17.6
A31: 50 | B31: 0 | C31: 0 | D31: 1 | E31: 231 | F31: 0 | G31: ЭММсНРиСП | H31: Эксплуатация машин по ТСН-2001.16 | K31: 231 | L31: 12 | M31: 3 | O31: 2 | P31: 0
... A46: 50 | B46: 0 | C46: 0 | D46: 1 | E46: 224 | F46: 695224.9 | G46: Всего | H46: Всего с НР и СП | K46: 224 | L46: 27 | M46: 3 | O46: 2 | P46: 77715.42
A48: -1
A51: 75 | B51: Текущий уровень цен | C51: 2025 | D51: 3 | E51: 0 | G51: 0 | H51: 1 | I51: 1 | J51: 3 | K51: 0 | L51: 0 | M51: 1 | N51: 59499215 | O51: 1
A52: 1 | B52: Сборник индексов | C52: Коэффициенты к ТСН-2001 МГЭ Дополнение 80, ремонт | D52: 2025 | E52: 9 | F52: 1 | G52: 1 | H52: 0 | I52: 2 | J52: 1 | K52: 9.88 | L52: 7.66 | M52: 1 | N52: 1 | O52: 9.88 | P52: 7.66 | Q52: 1 | AA52: 217/80 | AN52: 59499216
A53: 1 | B53: Сборник индексов | C53: Коэффициенты к ТСН-2001.13-2 Дополнение 46 | D53: 2025 | E53: 7 | F53: 1 | G53: 1 | H53: 0 | I53: 2 | J53: 1 | K53: 1 | L53: 1 | M53: 1 | N53: 1 | O53: 1 | P53: 1 | Q53: 1 | AA53: 62/46 | AN53: 59499217
A54: 75 | B54: Базовый уровень цен | C54: 2000 | D54: 0 | E54: 1 | G54: 0 | H54: 1 | I54: 1 | J54: 3 | K54: 0 | L54: 0 | M54: 0 | N54: 59499218 | O54: 2
A55: 1 | B55: Сборник индексов | C55: Коэффициенты к ТСН-2001 МГЭ Дополнение 80, ремонт | D55: 2000 | E55: 1 | F55: 1 | G55: 1 | H55: 0 | I55: 2 | J55: 1 | K55: 1 | L55: 1 | M55: 1 | N55: 1 | O55: 1 | P55: 1 | Q55: 1 | AA55: 0 | AN55: 59499219

Sheet SmtRes
A1: =ROW(Source!A165) -> 165 | B1: 59499218 | C1: 59499536 | D1: 58532980 | E1: 1080 | F1: 1 | G1: 1080 | H1: 1 | I1: 9999990008 | K1: Трудозатраты рабочих | L1: 1191 | N1: 1013 | O1: чел.-ч. | P1: чел.-ч. | Q1: 1 | W1: 0 | X1: 476480486 | Y1: =((AT1*1.15)*1.1) -> 0.6578 | AA1: 0 | AB1: 0 | AC1: 0 | AD1: 0 | AE1: 0 | AF1: 0 | AG1: 0 | AH1: 0 | AI1: 1 | AJ1: 1 | AK1: 1 | AL1: 1 | AM1: -2 | AN1: 0 | AO1: 1 | AP1: 1 | AQ1: 0 | AR1: 0 | AT1: 0.52 | AU1: *1,15)*1,1 | AV1: 1 | AW1: 2 | AX1: 59500043 | AY1: 1 | AZ1: 0 | BA1: 9 | BB1: 0 | BC1: 0 | BD1: 0 | BE1: 0 | BF1: 0 | BG1: 0 | BH1: 0 | BI1: 0 | BJ1: 0 | BK1: 0 | BL1: 0 | BM1: 0 | BN1: 0 | BO1: 0 | BP1: 0 | BQ1: 0 | BR1: 0 | BS1: 0 | BT1: 0 | BU1: 0 | BV1: 0 | BW1: 0 | CU1: =ROUND(AT1*Source!I165*AH1*AL1,2) -> 0 | CV1: =ROUND(Y1*Source!I165,9) -> 3.9468 | CW1: 0 | CX1: =ROUND(Y1*Source!I165,9) -> 3.9468 | CY1: =AD1 -> 0 | CZ1: =AH1 -> 0 | DA1: =AL1 -> 1 | DB1: =ROUND(((ROUND(AT1*CZ1,2)*1.15)*1.1),6) -> 0 | DC1: =ROUND(((ROUND(AT1*AG1,2)*1.15)*1.1),6) -> 0 | DF1: =ROUND(ROUND(AE1,2)*CX1,2) -> 0 | DG1: =ROUND(ROUND(AF1,2)*CX1,2) -> 0 | DH1: =ROUND(ROUND(AG1,2)*CX1,2) -> 0 | DI1: =ROUND(ROUND(AH1,2)*CX1,2) -> 0 | DJ1: =DI1 -> 0 | DK1: 0 | DM1: 0 | DO1: 0
A2: =ROW(Source!A165) -> 165 | B2: 59499218 | C2: 59499536 | D2: 58576492 | E2: 1 | F2: 1 | G2: 1080 | H2: 3 | I2: 1.1-1-1615 | J2: ТСН-2001.1 Доп. 79, Р. 1, о. 1, поз. 1615 | K2: Шурупы с потайной головкой, оцинкованные, длина от 13 до 20 мм | L2: 1348 | N2: 1009 | O2: т | P2: т | Q2: 1000 | W2: 0 | X2: 1986080645 | Y2: =AT2 -> 3e-05 | AA2: 16735.69 | AB2: 0 | AC2: 0 | AD2: 0 | AE2: 16735.69 | AF2: 0 | AG2: 0 | AH2: 0 | AI2: 1 | AJ2: 1 | AK2: 1 | AL2: 1 | AM2: -2 | AN2: 0 | AO2: 1 | AP2: 1 | AQ2: 0 | AR2: 0 | AT2: 3e-05 | AV2: 0 | AW2: 2 | AX2: 59500044 | AY2: 1 | AZ2: 0 | BA2: 10 | BB2: 0 | BC2: 0 | BD2: 0 | BE2: 0 | BF2: 0 | BG2: 0 | BH2: 0 | BI2: 0 | BJ2: 0 | BK2: 0 | BL2: 0 | BM2: 0 | BN2: 0 | BO2: 0 | BP2: 0 | BQ2: 0 | BR2: 0 | BS2: 0 | BT2: 0 | BU2: 0 | BV2: 0 | BW2: 0 | CV2: 0 | CW2: 0 | CX2: =ROUND(Y2*Source!I165,9) -> 0.00018 | CY2: =AA2 -> 16735.69 | CZ2: =AE2 -> 16735.69 | DA2: =AI2 -> 1 | DB2: =ROUND(ROUND(AT2*CZ2,2),6) -> 0.5 | DC2: =ROUND(ROUND(AT2*AG2,2),6) -> 0 | DF2: =ROUND(ROUND(AE2,2)*CX2,2) -> 3.01 | DG2: =ROUND(ROUND(AF2,2)*CX2,2) -> 0 | DH2: =ROUND(ROUND(AG2,2)*CX2,2) -> 0 | DI2: =ROUND(ROUND(AH2,2)*CX2,2) -> 0 | DJ2: =DF2 -> 3.01 | DK2: 0 | DM2: 0 | DO2: 0
A3: =ROW(Source!A165) -> 165 | B3: 59499218 | C3: 59499536 | D3: 58577238 | E3: 1 | F3: 1 | G3: 1080 | H3: 3 | I3: 1.1-1-2638 | J3: ТСН-2001.1 Доп. 67, Р. 1, о. 1, поз. 2638 | K3: Знак безопасности и эвакуационный указатель, из пластика с фотолюминесцентным покрытием, размер 200х200 мм | L3: 1354 | N3: 1010 | O3: шт. | P3: шт. | Q3: 1 | W3: 0 | X3: 1303734261 | Y3: =AT3 -> 1 | AA3: 156.96 | AB3: 0 | AC3: 0 | AD3: 0 | AE3: 156.96 | AF3: 0 | AG3: 0 | AH3: 0 | AI3: 1 | AJ3: 1 | AK3: 1 | AL3: 1 | AM3: 0 | AN3: 0 | AO3: 0 | AP3: 1 | AQ3: 0 | AR3: 0 | AT3: 1 | AV3: 0 | AW3: 1 | AX3: -1 | AY3: 0 | AZ3: 0 | BB3: 0 | BC3: 0 | BD3: 0 | BE3: 0 | BF3: 0 | BG3: 0 | BH3: 0 | BI3: 0 | BJ3: 0 | BK3: 0 | BL3: 0 | BM3: 0 | BN3: 0 | BO3: 0 | BP3: 0 | BQ3: 0 | BR3: 0 | BS3: 0 | BT3: 0 | BU3: 0 | BV3: 0 | BW3: 0 | CV3: 0 | CW3: 0 | CX3: =ROUND(Y3*Source!I165,9) -> 6 | CY3: =AA3 -> 156.96 | CZ3: =AE3 -> 156.96 | DA3: =AI3 -> 1 | DB3: =ROUND(ROUND(AT3*CZ3,2),6) -> 156.96 | DC3: =ROUND(ROUND(AT3*AG3,2),6) -> 0 | DF3: =ROUND(ROUND(AE3,2)*CX3,2) -> 941.76 | DG3: =ROUND(ROUND(AF3,2)*CX3,2) -> 0 | DH3: =ROUND(ROUND(AG3,2)*CX3,2) -> 0 | DI3: =ROUND(ROUND(AH3,2)*CX3,2) -> 0 | DJ3: =DF3 -> 941.76 | DK3: 0 | DM3: 0 | DO3: 0
A4: =ROW(Source!A166) -> 166 | B4: 59499215 | C4: 59499536 | D4: 58532980 | E4: 1080 | F4: 1 | G4: 1080 | H4: 1 | I4: 9999990008 | K4: Трудозатраты рабочих | L4: 1191 | N4: 1013 | O4: чел.-ч. | P4: чел.-ч. | Q4: 1 | W4: 0 | X4: 476480486 | Y4: =((AT4*1.15)*1.1) -> 0.6578 | AA4: 0 | AB4: 0 | AC4: 0 | AD4: 0 | AE4: 0 | AF4: 0 | AG4: 0 | AH4: 0 | AI4: 1 | AJ4: 1 | AK4: 1 | AL4: 1 | AM4: 5 | AN4: 0 | AO4: 1 | AP4: 1 | AQ4: 0 | AR4: 0 | AT4: 0.52 | AU4: *1,15)*1,1 | AV4: 1 | AW4: 2 | AX4: 59500043 | AY4: 1 | AZ4: 0 | BA4: 12 | BB4: 0 | BC4: 0 | BD4: 0 | BE4: 0 | BF4: 0 | BG4: 0 | BH4: 0 | BI4: 0 | BJ4: 0 | BK4: 0 | BL4: 0 | BM4: 0 | BN4: 0 | BO4: 0 | BP4: 0 | BQ4: 0 | BR4: 0 | BS4: 0 | BT4: 0 | BU4: 0 | BV4: 0 | BW4: 0 | CU4: =ROUND(AT4*Source!I166*AH4*AL4,2) -> 0 | CV4: =ROUND(Y4*Source!I166,9) -> 3.9468 | CW4: 0 | CX4: =ROUND(Y4*Source!I166,9) -> 3.9468 | CY4: =AD4 -> 0 | CZ4: =AH4 -> 0 | DA4: =AL4 -> 1 | DB4: =ROUND(((ROUND(AT4*CZ4,2)*1.15)*1.1),6) -> 0 | DC4: =ROUND(((ROUND(AT4*AG4,2)*1.15)*1.1),6) -> 0 | DF4: =ROUND(ROUND(AE4,2)*CX4,2) -> 0 | DG4: =ROUND(ROUND(AF4,2)*CX4,2) -> 0 | DH4: =ROUND(ROUND(AG4,2)*CX4,2) -> 0 | DI4: =ROUND(ROUND(AH4,2)*CX4,2) -> 0 | DJ4: =DI4 -> 0 | DK4: 0 | DM4: 0 | DO4: 0
A5: =ROW(Source!A166) -> 166 | B5: 59499215 | C5: 59499536 | D5: 58576492 | E5: 1 | F5: 1 | G5: 1080 | H5: 3 | I5: 1.1-1-1615 | J5: ТСН-2001.1 Доп. 79, Р. 1, о. 1, поз. 1615 | K5: Шурупы с потайной головкой, оцинкованные, длина от 13 до 20 мм | L5: 1348 | N5: 1009 | O5: т | P5: т | Q5: 1000 | W5: 0 | X5: 1986080645 | Y5: =AT5 -> 3e-05 | AA5: 265093.33 | AB5: 0 | AC5: 0 | AD5: 0 | AE5: 16735.69 | AF5: 0 | AG5: 0 | AH5: 0 | AI5: 15.84 | AJ5: 1 | AK5: 1 | AL5: 1 | AM5: 2 | AN5: 0 | AO5: 1 | AP5: 1 | AQ5: 0 | AR5: 0 | AT5: 3e-05 | AV5: 0 | AW5: 2 | AX5: 59500044 | AY5: 1 | AZ5: 0 | BA5: 13 | BB5: 0 | BC5: 0 | BD5: 0 | BE5: 0 | BF5: 0 | BG5: 0 | BH5: 0 | BI5: 0 | BJ5: 0 | BK5: 0 | BL5: 0 | BM5: 0 | BN5: 0 | BO5: 0 | BP5: 0 | BQ5: 0 | BR5: 0 | BS5: 0 | BT5: 0 | BU5: 0 | BV5: 0 | BW5: 0 | CV5: 0 | CW5: 0 | CX5: =ROUND(Y5*Source!I166,9) -> 0.00018 | CY5: =AA5 -> 265093.33 | CZ5: =AE5 -> 16735.69 | DA5: =AI5 -> 15.84 | DB5: =ROUND(ROUND(AT5*CZ5,2),6) -> 0.5 | DC5: =ROUND(ROUND(AT5*AG5,2),6) -> 0 | DF5: =ROUND(ROUND(AE5*AI5,2)*CX5,2) -> 47.72 | DG5: =ROUND(ROUND(AF5,2)*CX5,2) -> 0 | DH5: =ROUND(ROUND(AG5,2)*CX5,2) -> 0 | DI5: =ROUND(ROUND(AH5,2)*CX5,2) -> 0 | DJ5: =DF5 -> 47.72 | DK5: 0 | DM5: 0 | DO5: 0
A6: =ROW(Source!A166) -> 166 | B6: 59499215 | C6: 59499536 | D6: 58577238 | E6: 1 | F6: 1 | G6: 1080 | H6: 3 | I6: 1.1-1-2638 | J6: ТСН-2001.1 Доп. 67, Р. 1, о. 1, поз. 2638 | K6: Знак безопасности и эвакуационный указатель, из пластика с фотолюминесцентным покрытием, размер 200х200 мм | L6: 1354 | N6: 1010 | O6: шт. | P6: шт. | Q6: 1 | W6: 0 | X6: 1303734261 | Y6: =AT6 -> 1 | AA6: 141.26 | AB6: 0 | AC6: 0 | AD6: 0 | AE6: 156.96 | AF6: 0 | AG6: 0 | AH6: 0 | AI6: 0.9 | AJ6: 1 | AK6: 1 | AL6: 1 | AM6: 0 | AN6: 0 | AO6: 0 | AP6: 1 | AQ6: 0 | AR6: 0 | AT6: 1 | AV6: 0 | AW6: 1 | AX6: -1 | AY6: 0 | AZ6: 0 | BB6: 0 | BC6: 0 | BD6: 0 | BE6: 0 | BF6: 0 | BG6: 0 | BH6: 0 | BI6: 0 | BJ6: 0 | BK6: 0 | BL6: 0 | BM6: 0 | BN6: 0 | BO6: 0 | BP6: 0 | BQ6: 0 | BR6: 0 | BS6: 0 | BT6: 0 | BU6: 0 | BV6: 0 | BW6: 0 | CV6: 0 | CW6: 0 | CX6: =ROUND(Y6*Source!I166,9) -> 6 | CY6: =AA6 -> 141.26 | CZ6: =AE6 -> 156.96 | DA6: =AI6 -> 0.9 | DB6: =ROUND(ROUND(AT6*CZ6,2),6) -> 156.96 | DC6: =ROUND(ROUND(AT6*AG6,2),6) -> 0 | DF6: =ROUND(ROUND(AE6*AI6,2)*CX6,2) -> 847.56 | DG6: =ROUND(ROUND(AF6,2)*CX6,2) -> 0 | DH6: =ROUND(ROUND(AG6,2)*CX6,2) -> 0 | DI6: =ROUND(ROUND(AH6,2)*CX6,2) -> 0 | DJ6: =DF6 -> 847.56 | DK6: 0 | DM6: 0 | DO6: 0
A7: =ROW(Source!A169) -> 169 | B7: 59499218 | C7: 59499544 | D7: 58532980 | E7: 1080 | F7: 1 | G7: 1080 | H7: 1 | I7: 9999990008 | K7: Трудозатраты рабочих | L7: 1191 | N7: 1013 | O7: чел.-ч. | P7: чел.-ч. | Q7: 1 | W7: 0 | X7: 476480486 | Y7: =((AT7*1.15)*1.1) -> 0.6578 | AA7: 0 | AB7: 0 | AC7: 0 | AD7: 0 | AE7: 0 | AF7: 0 | AG7: 0 | AH7: 0 | AI7: 1 | AJ7: 1 | AK7: 1 | AL7: 1 | AM7: -2 | AN7: 0 | AO7: 1 | AP7: 1 | AQ7: 0 | AR7: 0 | AT7: 0.52 | AU7: *1,15)*1,1 | AV7: 1 | AW7: 2 | AX7: 59500046 | AY7: 1 | AZ7: 0 | BA7: 15 | BB7: 0 | BC7: 0 | BD7: 0 | BE7: 0 | BF7: 0 | BG7: 0 | BH7: 0 | BI7: 0 | BJ7: 0 | BK7: 0 | BL7: 0 | BM7: 0 | BN7: 0 | BO7: 0 | BP7: 0 | BQ7: 0 | BR7: 0 | BS7: 0 | BT7: 0 | BU7: 0 | BV7: 0 | BW7: 0 | CU7: =ROUND(AT7*Source!I169*AH7*AL7,2) -> 0 | CV7: =ROUND(Y7*Source!I169,9) -> 3.9468 | CW7: 0 | CX7: =ROUND(Y7*Source!I169,9) -> 3.9468 | CY7: =AD7 -> 0 | CZ7: =AH7 -> 0 | DA7: =AL7 -> 1 | DB7: =ROUND(((ROUND(AT7*CZ7,2)*1.15)*1.1),6) -> 0 | DC7: =ROUND(((ROUND(AT7*AG7,2)*1.15)*1.1),6) -> 0 | DF7: =ROUND(ROUND(AE7,2)*CX7,2) -> 0 | DG7: =ROUND(ROUND(AF7,2)*CX7,2) -> 0 | DH7: =ROUND(ROUND(AG7,2)*CX7,2) -> 0 | DI7: =ROUND(ROUND(AH7,2)*CX7,2) -> 0 | DJ7: =DI7 -> 0 | DK7: 0 | DM7: 0 | DO7: 0
A8: =ROW(Source!A169) -> 169 | B8: 59499218 | C8: 59499544 | D8: 58576492 | E8: 1 | F8: 1 | G8: 1080 | H8: 3 | I8: 1.1-1-1615 | J8: ТСН-2001.1 Доп. 79, Р. 1, о. 1, поз. 1615 | K8: Шурупы с потайной головкой, оцинкованные, длина от 13 до 20 мм | L8: 1348 | N8: 1009 | O8: т | P8: т | Q8: 1000 | W8: 0 | X8: 1986080645 | Y8: =AT8 -> 3e-05 | AA8: 16735.69 | AB8: 0 | AC8: 0 | AD8: 0 | AE8: 16735.69 | AF8: 0 | AG8: 0 | AH8: 0 | AI8: 1 | AJ8: 1 | AK8: 1 | AL8: 1 | AM8: -2 | AN8: 0 | AO8: 1 | AP8: 1 | AQ8: 0 | AR8: 0 | AT8: 3e-05 | AV8: 0 | AW8: 2 | AX8: 59500047 | AY8: 1 | AZ8: 0 | BA8: 16 | BB8: 0 | BC8: 0 | BD8: 0 | BE8: 0 | BF8: 0 | BG8: 0 | BH8: 0 | BI8: 0 | BJ8: 0 | BK8: 0 | BL8: 0 | BM8: 0 | BN8: 0 | BO8: 0 | BP8: 0 | BQ8: 0 | BR8: 0 | BS8: 0 | BT8: 0 | BU8: 0 | BV8: 0 | BW8: 0 | CV8: 0 | CW8: 0 | CX8: =ROUND(Y8*Source!I169,9) -> 0.00018 | CY8: =AA8 -> 16735.69 | CZ8: =AE8 -> 16735.69 | DA8: =AI8 -> 1 | DB8: =ROUND(ROUND(AT8*CZ8,2),6) -> 0.5 | DC8: =ROUND(ROUND(AT8*AG8,2),6) -> 0 | DF8: =ROUND(ROUND(AE8,2)*CX8,2) -> 3.01 | DG8: =ROUND(ROUND(AF8,2)*CX8,2) -> 0 | DH8: =ROUND(ROUND(AG8,2)*CX8,2) -> 0 | DI8: =ROUND(ROUND(AH8,2)*CX8,2) -> 0 | DJ8: =DF8 -> 3.01 | DK8: 0 | DM8: 0 | DO8: 0
