Workbook

Sheet 02-01-09
A1: =Source!B1 -> Smeta.RU (495) 974-1589
J2: Форма № 4б
A3: Капитальный ремонт здания Государственного бюджетного общеобразовательного учреждения города Москвы "Школа №236" по адресу: г. Москва, улица Клязьминская, дом 7, корпус 4. | AP3: Капитальный ремонт здания Государственного бюджетного общеобразовательного учреждения города Москвы "Школа №236" по адресу: г. Москва, улица Клязьминская, дом 7, корпус 4. 02-01-09 СОУЭ
A4: (наименование стройки и/или объекта)
A6: =CONCATENATE( "ЛОКАЛЬНАЯ СМЕТА № ",IF(Source!F20<>"Новая локальная смета", Source!F20, "")) -> ЛОКАЛЬНАЯ СМЕТА № 02-01-09
A8: =IF(Source!G20<>"Новая локальная смета", Source!G20, "") -> Система оповещения управления эвакуацией
A9: (наименование работ и затрат)
A11: =CONCATENATE( "Основание: чертежи № ", Source!J20) -> Основание: чертежи № 2024-00272-01-0-ИОС5.2
I13: В базисном уровне цен | J13: В текущем уровне цен
E14: Сметная стоимость | I14: =I15+I16+I17+I18 -> 213.64 | J14: =J15+J16+J17+J18 -> 3017.09 | K14: тыс.руб.
E15: Строительные работы | I15: =ROUND((Source!F240)/1000, 2) -> 0 | J15: =ROUND((Source!P240)/1000, 2) -> 0 | K15: тыс.руб.
E16: Работы по монтажу оборудования | I16: =ROUND((Source!F241)/1000, 2) -> 65.58 | J16: =ROUND((Source!P241)/1000, 2) -> 1882.99 | K16: тыс.руб.
E17: Оборудование | I17: =ROUND((Source!F232)/1000, 2) -> 148.06 | J17: =ROUND((Source!P232)/1000, 2) -> 1134.1 | K17: тыс.руб.
E18: Прочие работы и затраты | I18: =ROUND((Source!F242+Source!F243)/1000, 2) -> 0 | J18: =ROUND((Source!P242+Source!P243)/1000, 2) -> 0 | K18: тыс.руб.
E19: Средства на оплату труда | I19: =(Source!F238+ Source!F237)/1000 -> 11.66748 | J19: =((Source!P238 + Source!P237)/1000) -> 641.59471 | K19: тыс.руб.
E20: Затраты труда | I20: =Source!F245 -> 980.90519 | K20: чел.-ч.
E21: Кроме того:
E22: Возврат материалов | I22: =SUM(Y28:Y295)/1000 -> 0 | J22: =SUM(Z28:Z295)/1000 -> 0 | K22: тыс.руб.
A24: Составлен(а) по ТСН-2001 с учетом Дополнения №: 80
A25: № и период сборника коэффициентов (индексов) пересчета: Коэффициенты к ТСН-2001 МГЭ Дополнение 80, строительство №217/80 III квартал 2025 года и Коэффициенты к ТСН-2001.13-2 Дополнение 46 №62/46 III квартал 2025 года | AP25: № и период сборника коэффициентов (индексов) пересчета: Коэффициенты к ТСН-2001 МГЭ Дополнение 80, строительство №217/80 III квартал 2025 года и Коэффициенты к ТСН-2001.13-2 Дополнение 46 №62/46 III квартал 2025 года
A26: № п/п | B26: Шифр расценки и коды ресурсов | C26: Наименование работ и затрат | D26: Ед. изм. | E26: Кол-во единиц | F26: Цена на ед. изм., руб. | G26: Попра- вочные коэффи- циенты | H26: Коэффи- циенты зимних удорожа- ний | I26: Всего в ценах на январь 2000 года, руб. | J26: Коэффи- циенты (индек- сы) пере- счета, нормы НР и СП | K26: ВСЕГО затрат в текущем уровне цен, руб.
A27: 1 | B27: 2 | C27: 3 | D27: 4 | E27: 5 | F27: 6 | G27: 7 | H27: 8 | I27: 9 | J27: 10 | K27: 11
A29: =CONCATENATE("Раздел: ",IF(Source!G24<>"Новый раздел", Source!G24, "")) -> Раздел: Оборудование
A30: 1 | B30: =Source!F28 -> 4.10-118-1 | C30: Установка для трубных проводок шкафа напольного размерами до 600х600 мм | D30: =Source!H28 -> 1 ШТ. | E30: =Source!I28 -> 1 | Q30: =Source!X28 -> 22.45 | R30: =Source!X29 -> 1234.31 | S30: =Source!Y28 -> 11.47 | T30: =Source!Y29 -> 630.87 | U30: =ROUND((175/100)*ROUND(Source!R28, 2), 2) -> 0.51 | V30: =ROUND((0/100)*ROUND(Source!R29, 2), 2) -> 0 | AC30: 0
C31: ЗП | F31: =Source!AO28 -> 21.4 | G31: 1,1 | H31: =Source!AV29 -> 1.047 | I31: =Source!S28 -> 24.65 | J31: =IF(Source!BA29<> 0, Source!BA29, 1) -> 54.99 | K31: =Source!S29 -> 1355.5
C32: ЭМ | F32: =Source!AM28 -> 2.38 | G32: 1,1 | H32: =Source!AV29 -> 1.047 | I32: =Source!Q28 -> 2.74 | J32: =IF(Source!BB29<> 0, Source!BB29, 1) -> 13.99 | K32: =Source!Q29 -> 38.33
C33: в т.ч. ЗПМ | F33: =Source!AN28 -> 0.25 | G33: 1,1 | H33: =Source!AV29 -> 1.047 | I33: =Source!R28 -> 0.29 | J33: =IF(Source!BS29<> 0, Source!BS29, 1) -> 54.99 | K33: =Source!R29 -> 15.95
C34: МР | F34: =Source!AL28 -> 70.17 | H34: =Source!AW29 -> 1 | I34: =Source!P28 -> 70.17 | J34: =IF(Source!BC29<> 0, Source!BC29, 1) -> 1.86 | K34: =Source!P29 -> 130.52
C35: НР от ФОТ | D35: % | E35: =Source!BZ29 -> 90 | I35: =SUM(Q30:Q34) -> 22.45 | J35: =Source!AT29 -> 90 | K35: =SUM(R30:R34) -> 1234.31
C36: СП от ФОТ | D36: % | E36: =Source!CA29 -> 46 | I36: =SUM(S30:S35) -> 11.47 | J36: =Source!AU29 -> 46 | K36: =SUM(T30:T35) -> 630.87
C37: ЗТР | D37: чел-ч | E37: =Source!AQ28 -> 2 | G37: 1,1 | H37: =Source!AV29 -> 1.047 | I37: =Source!U28 -> 2.3034
C38: ВСЕГО работ по позиции: | H38: =I31+I32+I34+I35+I36+0-0-0 -> 131.48 | J38: =K31+K32+K34+K35+K36+0-0-0 -> 3389.53
C39: ВСЕГО оборудование по позиции: | H39: =0+0 -> 0 | J39: =0+0 -> 0
C40: ВСЕГО по позиции: | H40: =I31+I32+I34+I35+I36+0 -> 131.48 | J40: =K31+K32+K34+K35+K36+0 -> 3389.53 | O40: =I31+I32+I34+I35+I36+0 -> 131.48 | P40: =K31+K32+K34+K35+K36+0 -> 3389.53
A42: 2 | B42: =Source!F30 -> КА-1 | C42: Шкаф настенный LINEA W 18U 600x600 мм дверь стекло RAL9005 LWR5-18U66-GF 1 952,77 = [22 698,04 / 1,2 / 9,88] + 2% Заг.скл | D42: =Source!H30 -> шт. | E42: =Source!I30 -> 1 | F42: =Source!AL30 -> 1952.77 | H42: =Source!AW31 -> 1 | I42: =Source!P30 -> 1952.77 | J42: =IF(Source!BC31<> 0, Source!BC31, 1) -> 9.88 | K42: =Source!P31 -> 19293.37 | Q42: =Source!X30 -> 0 | R42: =Source!X31 -> 0 | S42: =Source!Y30 -> 0 | T42: =Source!Y31 -> 0 | U42: =ROUND((175/100)*ROUND(Source!R30, 2), 2) -> 0 | V42: =ROUND((0/100)*ROUND(Source!R31, 2), 2) -> 0 | AC42: 3
C43: ВСЕГО по позиции: | H43: =I42+0 -> 1952.77 | J43: =K42+0 -> 19293.37 | O43: =I42+0 -> 1952.77 | P43: =K42+0 -> 19293.37
A45: 3 | B45: =Source!F32 -> 4.10-170-2 | C45: Монтаж блока информационно-управляющего (БИУ) в диспетчерской | D45: =Source!H32 -> 1 ШТ. | E45: =Source!I32 -> 1 | Q45: =Source!X32 -> 34.7 | R45: =Source!X33 -> 1907.87 | S45: =Source!Y32 -> 17.73 | T45: =Source!Y33 -> 975.14 | U45: =ROUND((175/100)*ROUND(Source!R32, 2), 2) -> 0 | V45: =ROUND((0/100)*ROUND(Source!R33, 2), 2) -> 0 | AC45: 0
C46: ЗП | F46: =Source!AO32 -> 33.47 | G46: 1,1 | H46: =Source!AV33 -> 1.047 | I46: =Source!S32 -> 38.55 | J46: =IF(Source!BA33<> 0, Source!BA33, 1) -> 54.99 | K46: =Source!S33 -> 2119.86
C47: МР | F47: =Source!AL32 -> 2.34 | H47: =Source!AW33 -> 1 | I47: =Source!P32 -> 2.34 | J47: =IF(Source!BC33<> 0, Source!BC33, 1) -> 10.26 | K47: =Source!P33 -> 24.01
C48: НР от ФОТ | D48: % | E48: =Source!BZ33 -> 90 | I48: =SUM(Q45:Q47) -> 34.7 | J48: =Source!AT33 -> 90 | K48: =SUM(R45:R47) -> 1907.87
C49: СП от ФОТ | D49: % | E49: =Source!CA33 -> 46 | I49: =SUM(S45:S48) -> 17.73 | J49: =Source!AU33 -> 46 | K49: =SUM(T45:T48) -> 975.14
C50: ЗТР | D50: чел-ч | E50: =Source!AQ32 -> 2.65 | G50: 1,1 | H50: =Source!AV33 -> 1.047 | I50: =Source!U32 -> 3.052005
C51: ВСЕГО работ по позиции: | H51: =I46+I47+I48+I49+0-0-0 -> 93.32 | J51: =K46+K47+K48+K49+0-0-0 -> 5026.88
C52: ВСЕГО оборудование по позиции: | H52: =0+0 -> 0 | J52: =0+0 -> 0
C53: ВСЕГО по позиции: | H53: =I46+I47+I48+I49+0 -> 93.32 | J53: =K46+K47+K48+K49+0 -> 5026.88 | O53: =I46+I47+I48+I49+0 -> 93.32 | P53: =K46+K47+K48+K49+0 -> 5026.88
A55: 4 | B55: =Source!F34 -> КА-2 | C55: ОБОРУДОВАНИЕ:_x000D_ Прибор управления оповещением пожарной Sonar SPM, мощность850 Вт, 20 зон/20 линий оповещения, прием сигнала от ОПС по АЛС, установка в стойку Sonar SPM-C20085-AR 32 107,68 = [283 140 / 1,2 / 7,66] + 3% Трансп + 1,2% Заг.скл | D55: =Source!H34 -> шт. | E55: =Source!I34 -> 1 | F55: =Source!AL34 -> 32107.68 | H55: =Source!AW35 -> 1 | I55: =Source!P34 -> 32107.68 | J55: =IF(Source!BC35<> 0, Source!BC35, 1) -> 7.66 | K55: =Source!P35 -> 245944.83 | Q55: =Source!X34 -> 0 | R55: =Source!X35 -> 0 | S55: =Source!Y34 -> 0 | T55: =Source!Y35 -> 0 | U55: =ROUND((175/100)*ROUND(Source!R34, 2), 2) -> 0 | V55: =ROUND((0/100)*ROUND(Source!R35, 2), 2) -> 0 | AC55: 5
C56: ВСЕГО по позиции: | H56: =I55+0 -> 32107.68 | J56: =K55+0 -> 245944.83 | O56: =I55+0 -> 32107.68 | P56: =K55+0 -> 245944.83
A58: 5 | B58: =Source!F36 -> 4.11-12-1 | C58: Установка съемных и выдвижных блоков (модулей, ячеек, ТЭЗ) массой до 5 кг | D58: =Source!H36 -> 1 ШТ. | E58: =Source!I36 -> 1 | Q58: =Source!X36 -> 12.16 | R58: =Source!X37 -> 668.63 | S58: =Source!Y36 -> 6.21 | T58: =Source!Y37 -> 341.74 | U58: =ROUND((175/100)*ROUND(Source!R36, 2), 2) -> 0.16 | V58: =ROUND((0/100)*ROUND(Source!R37, 2), 2) -> 0 | AC58: 0
C59: ЗП | F59: =Source!AO36 -> 11.65 | G59: 1,1 | H59: =Source!AV37 -> 1.047 | I59: =Source!S36 -> 13.42 | J59: =IF(Source!BA37<> 0, Source!BA37, 1) -> 54.99 | K59: =Source!S37 -> 737.97
C60: ЭМ | F60: =Source!AM36 -> 0.5 | G60: 1,1 | H60: =Source!AV37 -> 1.047 | I60: =Source!Q36 -> 0.58 | J60: =IF(Source!BB37<> 0, Source!BB37, 1) -> 16.26 | K60: =Source!Q37 -> 9.43
C61: в т.ч. ЗПМ | F61: =Source!AN36 -> 0.08 | G61: 1,1 | H61: =Source!AV37 -> 1.047 | I61: =Source!R36 -> 0.09 | J61: =IF(Source!BS37<> 0, Source!BS37, 1) -> 54.99 | K61: =Source!R37 -> 4.95
C62: НР от ФОТ | D62: % | E62: =Source!BZ37 -> 90 | I62: =SUM(Q58:Q61) -> 12.16 | J62: =Source!AT37 -> 90 | K62: =SUM(R58:R61) -> 668.63
C63: СП от ФОТ | D63: % | E63: =Source!CA37 -> 46 | I63: =SUM(S58:S62) -> 6.21 | J63: =Source!AU37 -> 46 | K63: =SUM(T58:T62) -> 341.74
C64: ЗТР | D64: чел-ч | E64: =Source!AQ36 -> 1.03 | G64: 1,1 | H64: =Source!AV37 -> 1.047 | I64: =Source!U36 -> 1.186251
C65: ВСЕГО работ по позиции: | H65: =I59+I60+I62+I63+0-0-0 -> 32.37 | J65: =K59+K60+K62+K63+0-0-0 -> 1757.77
C66: ВСЕГО оборудование по позиции: | H66: =0+0 -> 0 | J66: =0+0 -> 0
C67: ВСЕГО по позиции: | H67: =I59+I60+I62+I63+0 -> 32.37 | J67: =K59+K60+K62+K63+0 -> 1757.77 | O67: =I59+I60+I62+I63+0 -> 32.37 | P67: =K59+K60+K62+K63+0 -> 1757.77
A69: 6 | B69: =Source!F38 -> КА-3 | C69: ОБОРУДОВАНИЕ:_x000D_ Конвертер DAP-IP для объединения приборов Sonar SPM в сеть Ethernet Sonar SNCA-8002 6 860,61 = [60 500 / 1,2 / 7,66] + 3% Трансп + 1,2% Заг.скл | D69: =Source!H38 -> шт. | E69: =Source!I38 -> 1 | F69: =Source!AL38 -> 6860.61 | H69: =Source!AW39 -> 1 | I69: =Source!P38 -> 6860.61 | J69: =IF(Source!BC39<> 0, Source!BC39, 1) -> 7.66 | K69: =Source!P39 -> 52552.27 | Q69: =Source!X38 -> 0 | R69: =Source!X39 -> 0 | S69: =Source!Y38 -> 0 | T69: =Source!Y39 -> 0 | U69: =ROUND((175/100)*ROUND(Source!R38, 2), 2) -> 0 | V69: =ROUND((0/100)*ROUND(Source!R39, 2), 2) -> 0 | AC69: 5
C70: ВСЕГО по позиции: | H70: =I69+0 -> 6860.61 | J70: =K69+0 -> 52552.27 | O70: =I69+0 -> 6860.61 | P70: =K69+0 -> 52552.27
A72: 7 | B72: =Source!F40 -> 4.11-12-1 | C72: Установка съемных и выдвижных блоков (модулей, ячеек, ТЭЗ) массой до 5 кг | D72: =Source!H40 -> 1 ШТ. | E72: =Source!I40 -> 1 | Q72: =Source!X40 -> 12.16 | R72: =Source!X41 -> 668.63 | S72: =Source!Y40 -> 6.21 | T72: =Source!Y41 -> 341.74 | U72: =ROUND((175/100)*ROUND(Source!R40, 2), 2) -> 0.16 | V72: =ROUND((0/100)*ROUND(Source!R41, 2), 2) -> 0 | AC72: 0
C73: ЗП | F73: =Source!AO40 -> 11.65 | G73: 1,1 | H73: =Source!AV41 -> 1.047 | I73: =Source!S40 -> 13.42 | J73: =IF(Source!BA41<> 0, Source!BA41, 1) -> 54.99 | K73: =Source!S41 -> 737.97
C74: ЭМ | F74: =Source!AM40 -> 0.5 | G74: 1,1 | H74: =Source!AV41 -> 1.047 | I74: =Source!Q40 -> 0.58 | J74: =IF(Source!BB41<> 0, Source!BB41, 1) -> 16.26 | K74: =Source!Q41 -> 9.43
C75: в т.ч. ЗПМ | F75: =Source!AN40 -> 0.08 | G75: 1,1 | H75: =Source!AV41 -> 1.047 | I75: =Source!R40 -> 0.09 | J75: =IF(Source!BS41<> 0, Source!BS41, 1) -> 54.99 | K75: =Source!R41 -> 4.95
C76: НР от ФОТ | D76: % | E76: =Source!BZ41 -> 90 | I76: =SUM(Q72:Q75) -> 12.16 | J76: =Source!AT41 -> 90 | K76: =SUM(R72:R75) -> 668.63
C77: СП от ФОТ | D77: % | E77: =Source!CA41 -> 46 | I77: =SUM(S72:S76) -> 6.21 | J77: =Source!AU41 -> 46 | K77: =SUM(T72:T76) -> 341.74
C78: ЗТР | D78: чел-ч | E78: =Source!AQ40 -> 1.03 | G78: 1,1 | H78: =Source!AV41 -> 1.047 | I78: =Source!U40 -> 1.186251
C79: ВСЕГО работ по позиции: | H79: =I73+I74+I76+I77+0-0-0 -> 32.37 | J79: =K73+K74+K76+K77+0-0-0 -> 1757.77
C80: ВСЕГО оборудование по позиции: | H80: =0+0 -> 0 | J80: =0+0 -> 0
C81: ВСЕГО по позиции: | H81: =I73+I74+I76+I77+0 -> 32.37 | J81: =K73+K74+K76+K77+0 -> 1757.77 | O81: =I73+I74+I76+I77+0 -> 32.37 | P81: =K73+K74+K76+K77+0 -> 1757.77
A83: 8 | B83: =Source!F42 -> КА-4 | C83: ОБОРУДОВАНИЕ:_x000D_ Комплект программируемого таймера Sonar STM-1004+GPS-2500 комплект 8 001,86 = [70 564 / 1,2 / 7,66] + 3% Трансп + 1,2% Заг.скл | D83: =Source!H42 -> шт. | E83: =Source!I42 -> 1 | F83: =Source!AL42 -> 8001.86 | H83: =Source!AW43 -> 1 | I83: =Source!P42 -> 8001.86 | J83: =IF(Source!BC43<> 0, Source!BC43, 1) -> 7.66 | K83: =Source!P43 -> 61294.25 | Q83: =Source!X42 -> 0 | R83: =Source!X43 -> 0 | S83: =Source!Y42 -> 0 | T83: =Source!Y43 -> 0 | U83: =ROUND((175/100)*ROUND(Source!R42, 2), 2) -> 0 | V83: =ROUND((0/100)*ROUND(Source!R43, 2), 2) -> 0 | AC83: 5
C84: ВСЕГО по позиции: | H84: =I83+0 -> 8001.86 | J84: =K83+0 -> 61294.25 | O84: =I83+0 -> 8001.86 | P84: =K83+0 -> 61294.25
A86: 9 | B86: =Source!F44 -> 4.11-3-1 | C86: Установка прибора массой до 5 кг на металлоконструкциях или щитах | D86: =Source!H44 -> 1 ШТ. | E86: =Source!I44 -> 1 | Q86: =Source!X44 -> 6.99 | R86: =Source!X45 -> 384.54 | S86: =Source!Y44 -> 3.57 | T86: =Source!Y45 -> 196.54 | U86: =ROUND((175/100)*ROUND(Source!R44, 2), 2) -> 0 | V86: =ROUND((0/100)*ROUND(Source!R45, 2), 2) -> 0 | AC86: 0
C87: ЗП | F87: =Source!AO44 -> 6.75 | G87: 1,1 | H87: =Source!AV45 -> 1.047 | I87: =Source!S44 -> 7.77 | J87: =IF(Source!BA45<> 0, Source!BA45, 1) -> 54.99 | K87: =Source!S45 -> 427.27
A88: 9,1 | B88: =Source!F46 -> 1.1-1-8146 | C88: Болты стальные оцинкованные с шестигранной головкой, с полной резьбой, с гайкой оцинкованной, М6, длина от 12 до 60 мм | D88: =Source!H46 -> кг | E88: =Source!I46 -> 0.035 | F88: =Source!AK46 -> 31.08 | H88: =Source!AW47 -> 1 | I88: =Source!O46 -> 1.09 | J88: =IF(Source!BC47<> 0, Source!BC47, 1) -> 5.12 | K88: =Source!O47 -> 5.58 | Q88: =Source!X46 -> 0 | R88: =Source!X47 -> 0 | S88: =Source!Y46 -> 0 | T88: =Source!Y47 -> 0 | U88: =ROUND((175/100)*ROUND(Source!R46, 2), 2) -> 0 | V88: =ROUND((0/100)*ROUND(Source!R47, 2), 2) -> 0 | AC88: 3
C89: НР от ФОТ | D89: % | E89: =Source!BZ45 -> 90 | I89: =SUM(Q86:Q88) -> 6.99 | J89: =Source!AT45 -> 90 | K89: =SUM(R86:R88) -> 384.54
C90: СП от ФОТ | D90: % | E90: =Source!CA45 -> 46 | I90: =SUM(S86:S89) -> 3.57 | J90: =Source!AU45 -> 46 | K90: =SUM(T86:T89) -> 196.54
C91: ЗТР | D91: чел-ч | E91: =Source!AQ44 -> 0.52 | G91: 1,1 | H91: =Source!AV45 -> 1.047 | I91: =Source!U44 -> 0.598884
C92: ВСЕГО работ по позиции: | H92: =I87+I89+I90+SUM(I88:I88)-SUMIF(AC88:AC88, 5, I88:I88)-SUMIF(AC88:AC88, 6, I88:I88) -> 19.42 | J92: =K87+K89+K90+SUM(K88:K88)-SUMIF(AC88:AC88, 5, K88:K88)-SUMIF(AC88:AC88, 6, K88:K88) -> 1013.93
C93: ВСЕГО оборудование по позиции: | H93: =SUMIF(AC88:AC88, 5, I88:I88)+SUMIF(AC88:AC88, 6, I88:I88) -> 0 | J93: =SUMIF(AC88:AC88, 5, K88:K88)+SUMIF(AC88:AC88, 6, K88:K88) -> 0
C94: ВСЕГО по позиции: | H94: =I87+I89+I90+SUM(I88:I88) -> 19.42 | J94: =K87+K89+K90+SUM(K88:K88) -> 1013.93 | O94: =I87+I89+I90+SUM(I88:I88) -> 19.42 | P94: =K87+K89+K90+SUM(K88:K88) -> 1013.93
A96: 10 | B96: =Source!F48 -> КА-5 | C96: ОБОРУДОВАНИЕ:_x000D_ Силовой блок рапределения питания по стойке оповещения, максимальный ток 50А Sonar RDIP-50A 3 010,39 = [26 547 / 1,2 / 7,66] + 3% Трансп + 1,2% Заг.скл | D96: =Source!H48 -> шт. | E96: =Source!I48 -> 1 | F96: =Source!AL48 -> 3010.39 | H96: =Source!AW49 -> 1 | I96: =Source!P48 -> 3010.39 | J96: =IF(Source!BC49<> 0, Source!BC49, 1) -> 7.66 | K96: =Source!P49 -> 23059.59 | Q96: =Source!X48 -> 0 | R96: =Source!X49 -> 0 | S96: =Source!Y48 -> 0 | T96: =Source!Y49 -> 0 | U96: =ROUND((175/100)*ROUND(Source!R48, 2), 2) -> 0 | V96: =ROUND((0/100)*ROUND(Source!R49, 2), 2) -> 0 | AC96: 5
C97: ВСЕГО по позиции: | H97: =I96+0 -> 3010.39 | J97: =K96+0 -> 23059.59 | O97: =I96+0 -> 3010.39 | P97: =K96+0 -> 23059.59
A99: 11 | B99: =Source!F50 -> 4.10-167-1 | C99: Монтаж блока питания сети (БПС) в диспетчерской | D99: =Source!H50 -> 1 ШТ. | E99: =Source!I50 -> 1 | Q99: =Source!X50 -> 19.63 | R99: =Source!X51 -> 1079.4 | S99: =Source!Y50 -> 10.03 | T99: =Source!Y51 -> 551.69 | U99: =ROUND((175/100)*ROUND(Source!R50, 2), 2) -> 0 | V99: =ROUND((0/100)*ROUND(Source!R51, 2), 2) -> 0 | AC99: 0
C100: ЗП | F100: =Source!AO50 -> 18.94 | G100: 1,1 | H100: =Source!AV51 -> 1.047 | I100: =Source!S50 -> 21.81 | J100: =IF(Source!BA51<> 0, Source!BA51, 1) -> 54.99 | K100: =Source!S51 -> 1199.33
C101: ЭМ | F101: =Source!AM50 -> 0.02 | G101: 1,1 | H101: =Source!AV51 -> 1.047 | I101: =Source!Q50 -> 0.02 | J101: =IF(Source!BB51<> 0, Source!BB51, 1) -> 10 | K101: =Source!Q51 -> 0.2
C102: МР | F102: =Source!AL50 -> 2.34 | H102: =Source!AW51 -> 1 | I102: =Source!P50 -> 2.34 | J102: =IF(Source!BC51<> 0, Source!BC51, 1) -> 10.26 | K102: =Source!P51 -> 24.01
C103: НР от ФОТ | D103: % | E103: =Source!BZ51 -> 90 | I103: =SUM(Q99:Q102) -> 19.63 | J103: =Source!AT51 -> 90 | K103: =SUM(R99:R102) -> 1079.4
C104: СП от ФОТ | D104: % | E104: =Source!CA51 -> 46 | I104: =SUM(S99:S103) -> 10.03 | J104: =Source!AU51 -> 46 | K104: =SUM(T99:T103) -> 551.69
C105: ЗТР | D105: чел-ч | E105: =Source!AQ50 -> 1.36 | G105: 1,1 | H105: =Source!AV51 -> 1.047 | I105: =Source!U50 -> 1.566312
C106: ВСЕГО работ по позиции: | H106: =I100+I101+I102+I103+I104+0-0-0 -> 53.83 | J106: =K100+K101+K102+K103+K104+0-0-0 -> 2854.63
C107: ВСЕГО оборудование по позиции: | H107: =0+0 -> 0 | J107: =0+0 -> 0
C108: ВСЕГО по позиции: | H108: =I100+I101+I102+I103+I104+0 -> 53.83 | J108: =K100+K101+K102+K103+K104+0 -> 2854.63 | O108: =I100+I101+I102+I103+I104+0 -> 53.83 | P108: =K100+K101+K102+K103+K104+0 -> 2854.63
A110: 12 | B110: =Source!F52 -> КА-6 | C110: ОБОРУДОВАНИЕ:_x000D_ Зарядное устройство Sonar SBC-3250 5 636,02 = [49 701 / 1,2 / 7,66] + 3% Трансп + 1,2% Заг.скл | D110: =Source!H52 -> шт. | E110: =Source!I52 -> 1 | F110: =Source!AL52 -> 5636.02 | H110: =Source!AW53 -> 1 | I110: =Source!P52 -> 5636.02 | J110: =IF(Source!BC53<> 0, Source!BC53, 1) -> 7.66 | K110: =Source!P53 -> 43171.91 | Q110: =Source!X52 -> 0 | R110: =Source!X53 -> 0 | S110: =Source!Y52 -> 0 | T110: =Source!Y53 -> 0 | U110: =ROUND((175/100)*ROUND(Source!R52, 2), 2) -> 0 | V110: =ROUND((0/100)*ROUND(Source!R53, 2), 2) -> 0 | AC110: 5
C111: ВСЕГО по позиции: | H111: =I110+0 -> 5636.02 | J111: =K110+0 -> 43171.91 | O111: =I110+0 -> 5636.02 | P111: =K110+0 -> 43171.91
A113: 13 | B113: =Source!F54 -> 4.11-3-1 | C113: Установка прибора массой до 5 кг на металлоконструкциях или щитах | D113: =Source!H54 -> 1 ШТ. | E113: =Source!I54 -> 1 | Q113: =Source!X54 -> 6.99 | R113: =Source!X55 -> 384.54 | S113: =Source!Y54 -> 3.57 | T113: =Source!Y55 -> 196.54 | U113: =ROUND((175/100)*ROUND(Source!R54, 2), 2) -> 0 | V113: =ROUND((0/100)*ROUND(Source!R55, 2), 2) -> 0 | AC113: 0
C114: ЗП | F114: =Source!AO54 -> 6.75 | G114: 1,1 | H114: =Source!AV55 -> 1.047 | I114: =Source!S54 -> 7.77 | J114: =IF(Source!BA55<> 0, Source!BA55, 1) -> 54.99 | K114: =Source!S55 -> 427.27
A115: 13,1 | B115: =Source!F56 -> 1.1-1-8146 | C115: Болты стальные оцинкованные с шестигранной головкой, с полной резьбой, с гайкой оцинкованной, М6, длина от 12 до 60 мм | D115: =Source!H56 -> кг | E115: =Source!I56 -> 0.035 | F115: =Source!AK56 -> 31.08 | H115: =Source!AW57 -> 1 | I115: =Source!O56 -> 1.09 | J115: =IF(Source!BC57<> 0, Source!BC57, 1) -> 5.12 | K115: =Source!O57 -> 5.58 | Q115: =Source!X56 -> 0 | R115: =Source!X57 -> 0 | S115: =Source!Y56 -> 0 | T115: =Source!Y57 -> 0 | U115: =ROUND((175/100)*ROUND(Source!R56, 2), 2) -> 0 | V115: =ROUND((0/100)*ROUND(Source!R57, 2), 2) -> 0 | AC115: 3
C116: НР от ФОТ | D116: % | E116: =Source!BZ55 -> 90 | I116: =SUM(Q113:Q115) -> 6.99 | J116: =Source!AT55 -> 90 | K116: =SUM(R113:R115) -> 384.54
C117: СП от ФОТ | D117: % | E117: =Source!CA55 -> 46 | I117: =SUM(S113:S116) -> 3.57 | J117: =Source!AU55 -> 46 | K117: =SUM(T113:T116) -> 196.54
C118: ЗТР | D118: чел-ч | E118: =Source!AQ54 -> 0.52 | G118: 1,1 | H118: =Source!AV55 -> 1.047 | I118: =Source!U54 -> 0.598884
...

Sheet Ведомость объемов работ
A1: =Source!B1 -> Smeta.RU (495) 974-1589
B4: =CONCATENATE("Ведомость объемов работ ", IF(Source!AN15<>"", Source!AN15," ")) -> Ведомость объемов работ
B5: =CONCATENATE(Source!F12, " ", Source!G12) -> 02-01-09 СОУЭ
A8: № п/п | B8: № в ЛСР | C8: Наименование работ и затрат | D8: Единица измерения | E8: Количество | F8: Ссылка на чертежи, спецификации | G8: Формула расчета, расчет объемов работ и расхода материалов | H8: Примечание
A9: 1 | B9: 2 | C9: 3 | D9: 4 | E9: 5 | F9: 6 | G9: 7 | H9: 8
A10: =CONCATENATE("Локальная смета: ", Source!G20) -> Локальная смета: Система оповещения управления эвакуацией
A11: =CONCATENATE("Раздел: ", Source!G24) -> Раздел: Оборудование
A12: 1 | B12: =Source!E28 -> 1 | C12: =Source!G28 -> Установка для трубных проводок шкафа напольного размерами до 600х600 мм | D12: 1 ШТ. | E12: =Source!I28 -> 1 | F12: =Source!U24 | G12: =Source!I28 -> 1
A13: 2 | B13: =Source!E30 -> 2 | C13: =Source!G30 -> Шкаф настенный LINEA W 18U 600x600 мм дверь стекло RAL9005 LWR5-18U66-GF | D13: шт. | E13: =Source!I30 -> 1 | F13: =Source!U24 | G13: =Source!I30 -> 1
A14: 3 | B14: =Source!E32 -> 3 | C14: =Source!G32 -> Монтаж блока информационно-управляющего (БИУ) в диспетчерской | D14: 1 ШТ. | E14: =Source!I32 -> 1 | F14: =Source!U24 | G14: =Source!I32 -> 1
A15: 4 | B15: =Source!E34 -> 4 | C15: =Source!G34 -> Прибор управления оповещением пожарной Sonar SPM, мощность850 Вт, 20 зон/20 линий оповещения, прием сигнала от ОПС по АЛС, установка в стойку Sonar SPM-C20085-AR | D15: шт. | E15: =Source!I34 -> 1 | F15: =Source!U24 | G15: =Source!I34 -> 1
A16: 5 | B16: =Source!E36 -> 5 | C16: =Source!G36 -> Установка съемных и выдвижных блоков (модулей, ячеек, ТЭЗ) массой до 5 кг | D16: 1 ШТ. | E16: =Source!I36 -> 1 | F16: =Source!U24 | G16: =Source!I36 -> 1
A17: 6 | B17: =Source!E38 -> 6 | C17: =Source!G38 -> Конвертер DAP-IP для объединения приборов Sonar SPM в сеть Ethernet Sonar SNCA-8002 | D17: шт. | E17: =Source!I38 -> 1 | F17: =Source!U24 | G17: =Source!I38 -> 1
A18: 7 | B18: =Source!E40 -> 7 | C18: =Source!G40 -> Установка съемных и выдвижных блоков (модулей, ячеек, ТЭЗ) массой до 5 кг | D18: 1 ШТ. | E18: =Source!I40 -> 1 | F18: =Source!U24 | G18: =Source!I40 -> 1
A19: 8 | B19: =Source!E42 -> 8 | C19: =Source!G42 -> Комплект программируемого таймера Sonar STM-1004+GPS-2500 комплект | D19: шт. | E19: =Source!I42 -> 1 | F19: =Source!U24 | G19: =Source!I42 -> 1
A20: 9 | B20: =Source!E44 -> 9 | C20: =Source!G44 -> Установка прибора массой до 5 кг на металлоконструкциях или щитах | D20: 1 ШТ. | E20: =Source!I44 -> 1 | F20: =Source!U24 | G20: =Source!I44 -> 1
A21: 10 | B21: =Source!E48 -> 10 | C21: =Source!G48 -> Силовой блок рапределения питания по стойке оповещения, максимальный ток 50А Sonar RDIP-50A | D21: шт. | E21: =Source!I48 -> 1 | F21: =Source!U24 | G21: =Source!I48 -> 1
A22: 11 | B22: =Source!E50 -> 11 | C22: =Source!G50 -> Монтаж блока питания сети (БПС) в диспетчерской | D22: 1 ШТ. | E22: =Source!I50 -> 1 | F22: =Source!U24 | G22: =Source!I50 -> 1
A23: 12 | B23: =Source!E52 -> 12 | C23: =Source!G52 -> Зарядное устройство Sonar SBC-3250 | D23: шт. | E23: =Source!I52 -> 1 | F23: =Source!U24 | G23: =Source!I52 -> 1
A24: 13 | B24: =Source!E54 -> 13 | C24: =Source!G54 -> Установка прибора массой до 5 кг на металлоконструкциях или щитах | D24: 1 ШТ. | E24: =Source!I54 -> 1 | F24: =Source!U24 | G24: =Source!I54 -> 1
A25: 14 | B25: =Source!E58 -> 14 | C25: =Source!G58 -> Блок АКБ 24В. Заменяемые АКБ 12В, 5Ач, количество элементов в корпусе - 10 шт. Sonar SBB-2425 | D25: шт. | E25: =Source!I58 -> 1 | F25: =Source!U24 | G25: =Source!I58 -> 1
A26: 15 | B26: =Source!E60 -> 15 | C26: =Source!G60 -> Установка прибора массой до 5 кг на металлоконструкциях или щитах | D26: 1 ШТ. | E26: =Source!I60 -> 1 | F26: =Source!U24 | G26: =Source!I60 -> 1
A27: 16 | B27: =Source!E64 -> 16 | C27: =Source!G64 -> Блок АКБ 24В. Заменяемые АКБ 12В, 5Ач, количество элементов в корпусе - 18 шт. Sonar SBB-2450 | D27: шт. | E27: =Source!I64 -> 1 | F27: =Source!U24 | G27: =Source!I64 -> 1
A28: 17 | B28: =Source!E66 -> 17 | C28: =Source!G66 -> Аппараты приемные, устройства промежуточные на 1 луч | D28: 1 ШТ. | E28: =Source!I66 -> 2 | F28: =Source!U24 | G28: =Source!I66 -> 2
A29: 18 | B29: =Source!E68 -> 18 | C29: =Source!G68 -> Изолятор шлейфа ИЗ-1-R3 | D29: шт. | E29: =Source!I68 -> 2 | F29: =Source!U24 | G29: =Source!I68 -> 2
A30: 19 | B30: =Source!E70 -> 19 | C30: =Source!G70 -> Установка прибора массой до 5 кг на металлоконструкциях или щитах | D30: 1 ШТ. | E30: =Source!I70 -> 2 | F30: =Source!U24 | G30: =Source!I70 -> 2
A31: 20 | B31: =Source!E74 -> 20 | C31: =Source!G74 -> Кабельный органайзер 10" 1U 4 кольца для шкафа 10" серии LINEA WS черный CO05-1M4R-LWS | D31: шт. | E31: =Source!I74 -> 2 | F31: =Source!U24 | G31: =Source!I74 -> 2
A32: 21 | B32: =Source!E76 -> 21 | C32: =Source!G76 -> Установка прибора массой до 5 кг на металлоконструкциях или щитах | D32: 1 ШТ. | E32: =Source!I76 -> 1 | F32: =Source!U24 | G32: =Source!I76 -> 1
A33: 22 | B33: =Source!E80 -> 22 | C33: =Source!G80 -> Панель 19" с DIN-рейкой регулируемая по глубине STK-RACKMNT-704KA | D33: шт. | E33: =Source!I80 -> 1 | F33: =Source!U24 | G33: =Source!I80 -> 1
A34: 23 | B34: =Source!E82 -> 23 | C34: =Source!G82 -> Установка прибора массой до 5 кг на металлоконструкциях или щитах | D34: 1 ШТ. | E34: =Source!I82 -> 2 | F34: =Source!U24 | G34: =Source!I82 -> 2
A35: 24 | B35: =Source!E86 -> 24 | C35: =Source!G86 -> Шина заземления 483х25х3 мм медь ШМТ М1 12 точек подключения М6 ER-12-325-M1 | D35: шт. | E35: =Source!I86 -> 2 | F35: =Source!U24 | G35: =Source!I86 -> 2
A36: 25 | B36: =Source!E88 -> 25 | C36: =Source!G88 -> Коннектор powerCON (in) Sonar SPC-20B | D36: шт. | E36: =Source!I88 -> 3 | F36: =Source!U24 | G36: =Source!I88 -> 3
A37: 26 | B37: =Source!E90 -> 26 | C37: =Source!G90 -> Аккумулятор 12В, 5А*ч Delta | D37: шт. | E37: =Source!I90 -> 28 | F37: =Source!U24 | G37: =Source!I90 -> 28
A38: =CONCATENATE("Раздел: ", Source!G123) -> Раздел: Оборудование оповещения
A39: 27 | B39: =Source!E127 -> 27 | C39: =Source!G127 -> Монтаж громкоговорителя или звуковой колонки в помещении | D39: 1 ШТ. | E39: =Source!I127 -> 213 | F39: =Source!U123 | G39: =Source!I127 -> 213
A40: 28 | B40: =Source!E129 -> 28 | C40: =Source!G129 -> Громкоговоритель трансляционный настенный, 100В, мощность 6/3/1,5Вт Sonar SWS-106-103 | D40: шт. | E40: =Source!I129 -> 213 | F40: =Source!U123 | G40: =Source!I129 -> 213
A41: 29 | B41: =Source!E131 -> 29 | C41: =Source!G131 -> Установка для трубных проводок коробки оконечной | D41: 100 шт. | E41: =Source!I131 -> 0.04 | F41: =Source!U123 | G41: ="=4/"&"100" -> =4/100
A42: 30 | B42: =Source!E133 -> 30 | C42: =Source!G133 -> Фильтр оконечный для трансляционной линии при контроле линии переменным током Sonar SFT-2300-M | D42: шт. | E42: =Source!I133 -> 4 | F42: =Source!U123 | G42: =Source!I133 -> 4
A43: 31 | B43: =Source!E135 -> 31 | C43: =Source!G135 -> Установка пульта или табло вызывной сигнализации с количеством сигналов до 20 | D43: 1 ШТ. | E43: =Source!I135 -> 1 | F43: =Source!U123 | G43: =Source!I135 -> 1
A44: 32 | B44: =Source!E137 -> 32 | C44: =Source!G137 -> Пульт микрофонный Sonar SRM-7020C | D44: шт. | E44: =Source!I137 -> 1 | F44: =Source!U123 | G44: =Source!I137 -> 1
A45: =CONCATENATE("Раздел: ", Source!G170) -> Раздел: Кабельные изделия
A46: 33 | B46: =Source!E174 -> 33 | C46: =Source!G174 -> Прокладка кабеля связи огнестойкого в трубах гофрированных с использованием скобы СМО: по бетонным поверхностям | D46: 100 м | E46: =Source!I174 -> 16 | F46: =Source!U170 | G46: ="=1600/"&"100" -> =1600/100
A47: 34 | B47: =Source!E182 -> 34 | C47: =Source!G182 -> Прокладка кабеля связи огнестойкого в трубах гофрированных с использованием скобы СМО: по бетонным поверхностям | D47: 100 м | E47: =Source!I182 -> 0.2 | F47: =Source!U170 | G47: ="=20/"&"100" -> =20/100
A48: 35 | B48: =Source!E188 -> 35 | C48: =Source!G188 -> Кабель ParLan U/UTP Cat5e PVCLSнг(А)-FRLSLTx 4x2x0,52 | D48: км | E48: =Source!I188 -> 0.0204 | F48: =Source!U170 | G48: ="=(20*"&"1,02)/"&"1000" -> =(20*1,02)/1000
A49: 36 | B49: =Source!E190 -> 36 | C49: =Source!G190 -> Мастика огнезащитная, однокомпонентная, терморасширяющаяся, на основе водных дисперсий акрилатов и наполнителей, для механизированного и ручного нанесения, плотность от 1150 до 1350 кг/м3, расход 1,1 кг/м2, массовая доля нелетучих веществ 65%, для защиты от распространения горения по кабельным линиям | D49: кг | E49: =Source!I190 -> 5 | F49: =Source!U170 | G49: =Source!I190 -> 5
C52: Главный инженер проекта _________________ | D52: =IF(Source!X12<>"", Source!X12," ")
C54: Составил _________________ | D54: =IF(Source!AB12<>"", Source!AB12," ") -> Соколова И.Н.

Sheet Source
A1: 0 | B1: Smeta.RU (495) 974-1589 | D1: _PS_ | F1: 0 | G1: 0 | H1: 0 | I1: Smeta.RU | K1: 1 | L1: 74563 | M1: 10 | N1: 12 | O1: 1 | P1: 0 | Q1: 0
A4: 1 | B4: 1 | C4: -1 | G4: Капитальный ремонт здания Государственного бюджетного общеобразовательного учреждения города Москвы "Школа №236" по адресу: г. Москва, улица Клязьминская, дом 7, корпус 4 | EC4: 0
A12: 1 | B12: 292 | C12: 0 | D12: =ROW(A253) -> 253 | E12: 0 | G12: 02-01-09 СОУЭ | I12: 0 | J12: 2024-00272-010-ИОС5.2 | K12: 0 | L12: 0 | M12: 4098 | O12: 0 | P12: 0 | Q12: 0 | R12: 0 | S12: 0 | T12: 1 | V12: 0 | AB12: Соколова И.Н. | BB12: 0 | BH12: Сметные нормы списания | BI12: Коды ОКП для ТСН-2001 МГЭ Дополнение 80 | BJ12: 1 | BK12: 1 | BL12: 0 | BM12: 0 | BN12: 1 | BO12: 0 | BP12: 6 | BQ12: 2 | BR12: 1 | BS12: 1 | BT12: 0 | BU12: 0 | BV12: 0 | BW12: 0 | BX12: 0 | BZ12: Типовой расчет для ТСН-2001 МГЭ, Дополнение 80, строительство (1) | CA12: Территориальные сметные нормативы для Москвы ТСН-2001 (МГЭ), дополнение 80 | CB12: Территориальные сметные нормативы для Москвы ТСН-2001 (МГЭ), дополнение 80 | CC12: Территориальные сметные нормативы для Москвы ТСН-2001 (МГЭ), дополнение 80 | CD12: Территориальные сметные нормативы для Москвы ТСН-2001 (МГЭ), дополнение 80 | CE12: Поправки для ТСН-2001 от 28.11.2025 г. доп.79 | CF12: 0 | CG12: 0 | CH12: 8200 | CK12: 81 | CQ12: Территориальные сметные нормативы для Москвы (ТСН-2001) | CR12: ТЕР | CS12: 41660 | CT12: 1 | CU12: 80 | CY12: 0 | EC12: 0
A15: 15 | B15: 1
A18: 52 | B18: =B253 -> 292 | C18: =C253 -> 1 | D18: =D253 -> 12 | E18: =E253 -> 0 | F18: =F253 | G18: =G253 -> 02-01-09 СОУЭ | O18: =O253 -> 197064.51 | P18: =P253 -> 185317.71 | Q18: =Q253 -> 79.81 | R18: =R253 -> 0.49 | S18: =S253 -> 11666.99 | T18: =T253 -> 0 | U18: =U253 -> 980.90519 | V18: =V253 -> 0 | ... GX18: =GX253 -> 0
A20: 3 | B20: 1 | D20: =ROW(A223) -> 223 | F20: 02-01-09 | G20: Система оповещения управления эвакуацией | I20: 0 | J20: 2024-00272-01-0-ИОС5.2 | K20: -1 | L20: 02-01-09 | S20: 0 | T20: 0 | V20: 2 | BX20: 0 | CF20: 0 | CG20: 0
A22: 52 | B22: =B223 -> 1 | C22: =C223 -> 3 | D22: =D223 -> 20 | E22: =E223 -> 0 | F22: =F223 -> 02-01-09 | G22: =G223 -> Система оповещения управления эвакуацией | O22: =O223 -> 197064.51 | P22: =P223 -> 185317.71 | Q22: =Q223 -> 79.81 | R22: =R223 -> 0.49 | S22: =S223 -> 11666.99 | T22: =T223 -> 0 | U22: =U223 -> 980.90519 | V22: =V223 -> 0 | ... GX22: =GX223 -> 0
A24: 4 | B24: 1 | D24: =ROW(A93) -> 93 | G24: Оборудование | I24: 0 | K24: -1 | S24: 0 | T24: 0 | V24: 2 | BX24: 0 | CJ24: 0
A26: 52 | B26: =B93 -> 1 | C26: =C93 -> 4 | D26: =D93 -> 24 | E26: =E93 -> 0 | F26: =F93 | G26: =G93 -> Оборудование | O26: =O93 -> 80435.66 | P26: =P93 -> 80220.57 | Q26: =Q93 -> 4.04 | R26: =R93 -> 0.49 | S26: =S93 -> 211.05 | T26: =T93 -> 0 | U26: =U93 -> 16.849371 | V26: =V93 -> 0 | ... GX26: =GX93 -> 0
A28: 17 | B28: 1 | C28: =ROW(SmtRes!A7) -> 7 | D28: =ROW(EtalonRes!A8) -> 8 | E28: 1 | F28: 4.10-118-1 | G28: Установка для трубных проводок шкафа напольного размерами до 600х600 мм | H28: 1 ШТ. | I28: 1 | J28: 0 | K28: 1 | O28: =ROUND(CP28,2) -> 97.56 | P28: =ROUND((ROUND((AC28*AW28*I28),2)*BC28),2) -> 70.17 | Q28: =(ROUND((ROUND((((ET28*1.1))*AV28*I28),2)*BB28),2)+ROUND((ROUND(((AE28-((EU28*1.1)))*AV28*I28),2)*BS28),2)) -> 2.74 | R28: =(ROUND((ROUND((((EU28*1.1))*AV28*I28),2)*BS28),2)+ROUND((ROUND(((AE28-((EU28*1.1)))*AV28*I28),2)*BS28),2)) -> 0.29 | S28: =ROUND((ROUND((AF28*AV28*I28),2)*BA28),2) -> 24.65 | T28: =ROUND(CU28*I28,2) -> 0 | U28: =CV28*I28 -> 2.3034 | V28: =CW28*I28 -> 0 | W28: =ROUND(CX28*I28,2) -> 0 | X28: =(ROUND((((S28+ROUND((ROUND((((EU28*1.1))*AV28*I28),2)*BS28),2))*AT28)/100),2)+ROUND(((ROUND((ROUND(((AE28-((EU28*1.1)))*AV28*I28),2)*BS28),2)*AT28)/100),2)) -> 22.45 | Y28: =(ROUND((((S28+ROUND((ROUND((((EU28*1.1))*AV28*I28),2)*BS28),2))*AU28)/100),2)+ROUND(((ROUND((ROUND(((AE28-((EU28*1.1)))*AV28*I28),2)*BS28),2)*AU28)/100),2)) -> 11.47 | AA28: 60256405 | AB28: =ROUND((AC28+AD28+AF28),6) -> 96.328 | AC28: =ROUND(((ES28*1)),6) -> 70.17 | AD28: =ROUND(((((ET28*1.1))-((EU28*1.1)))+AE28),6) -> 2.618 | AE28: =ROUND(((EU28*1.1)),6) -> 0.275 | AF28: =ROUND(((EV28*1.1)),6) -> 23.54 | AG28: =ROUND((AP28),6) -> 0 | AH28: =((EW28*1.1)) -> 2.2 | AI28: =((EX28*1.1)) -> 0 | AJ28: =(AS28) -> 0 | AK28: 93.95 | AL28: 70.17 | AM28: 2.38 | AN28: 0.25 | AO28: 21.4 | AP28: 0 | AQ28: 2 | AR28: 0 | AS28: 0 | AT28: 90 | AU28: 46 | AV28: 1.047 | AW28: 1 | AZ28: 1 | BA28: 1 | BB28: 1 | BC28: 1 | BH28: 0 | BI28: 2 | BJ28: ТСН-2001.4 Доп. 79, Сб. 10, т. 118, поз. 1 | BM28: 68 | BN28: 58973116 | BO28: 4.10-118-1 | BP28: 1 | BQ28: 40 | BR28: 0 | BS28: 1 | BT28: 1 | BU28: 1 | BV28: 1 | BW28: 1 | BX28: 1 | BZ28: 90 | CA28: 46 | CE28: 1566 | CF28: 0 | CG28: 0 | CM28: 0 | CN28: Поправка: Гл.12.Прил.8.п.8. 5_12.00.01.11.003 Наименование: При наличии усложненных условий производства работ (стесненность, сложность складирования и транспортной логистики, наличие в зоне производства работ действующего технологического оборудования или движения технологического транспорта и т.п.) для объектов, расположенных за пределами территории круговой магистральной системы улиц "Садовое кольцо" и за пределами Третьего транспортного кольца города Москвы пунктов "а" и "б", но в пределах Московской кольцевой автомобильной дороги | CO28: 0 | CP28: =(P28+Q28+S28) -> 97.56 | CQ28: =ROUND((ROUND((AC28*AW28*1),2)*BC28),2) -> 70.17 | CR28: =(ROUND((ROUND((((ET28*1.1))*AV28*1),2)*BB28),2)+ROUND((ROUND(((AE28-((EU28*1.1)))*AV28*1),2)*BS28),2)) -> 2.74 | CS28: =(ROUND((ROUND((((EU28*1.1))*AV28*1),2)*BS28),2)+ROUND((ROUND(((AE28-((EU28*1.1)))*AV28*1),2)*BS28),2)) -> 0.29 | CT28: =ROUND((ROUND((AF28*AV28*1),2)*BA28),2) -> 24.65 | CU28: =AG28 -> 0 | CV28: =(AH28*AV28) -> 2.3034 | CW28: =AI28 -> 0 | CX28: =AJ28 -> 0 | CY28: =(ROUND((((S28+ROUND((ROUND((((EU28*1.1))*AV28*1),2)*BS28),2))*AT28)/100),2)+ROUND(((ROUND((ROUND(((AE28-((EU28*1.1)))*AV28*1),2)*BS28),2)*AT28)/100),2)) -> 22.45 | CZ28: =(ROUND((((S28+ROUND((ROUND((((EU28*1.1))*AV28*1),2)*BS28),2))*AU28)/100),2)+ROUND(((ROUND((ROUND(((AE28-((EU28*1.1)))*AV28*1),2)*BS28),2)*AU28)/100),2)) -> 11.47 | DB28: 1 | DD28: *1 | DE28: *1,1 | DF28: *1,1 | DG28: *1,1 | DI28: *1,1 | DJ28: *1,1 | DN28: 0 | DO28: 0 | DP28: 1 | DQ28: 1 | DU28: 1013 | DV28: 1 ШТ. | DW28: 1 ШТ. | DX28: 1 | EE28: 60088532 | EF28: 40 | EG28: Монтаж оборудования | EH28: 0 | EJ28: 2 | EK28: 68 | EL28: ТСН-2001.4-10. Прокладка и монтаж сетей связи | EM28: ТСН-2001.4-10-1 | EO28: Поправка: Гл.12.Прил.8.п.8. 5_12.00.01.11.003 | EQ28: 0 | ER28: 93.95 | ES28: 70.17 | ET28: 2.38 | EU28: 0.25 | EV28: 21.4 | EW28: 2 | EX28: 0 | EY28: 0 | FQ28: 0 | FR28: 0 | FS28: 0 | FX28: 90 | FY28: 46 | GD28: 1 | GF28: -1502969864 | GG28: 2 | GH28: 1 | GI28: 2 | GJ28: 0 | GK28: 0 | GL28: =ROUND(IF(AND(BH28=3,BI28=3,FS28<>0),P28,0),2) -> 0 | GM28: =ROUND(O28+X28+Y28,2)+GX28 -> 131.48 | GN28: =IF(OR(BI28=0,BI28=1),GM28-GX28,0) -> 0 | GO28: =IF(BI28=2,GM28-GX28,0) -> 131.48 | GP28: =IF(BI28=4,GM28-GX28,0) -> 0 | GR28: 0 | GS28: 3 | GT28: 0 | GV28: =ROUND((GT28),6) -> 0 | GW28: 1 | GX28: =ROUND(HC28*I28,2) -> 0 | HA28: 0 | HB28: 0 | HC28: =GV28*GW28 -> 0 | HS28: 0 | IK28: 0
A29: 17 | B29: 1 | C29: =ROW(SmtRes!A14) -> 14 | D29: =ROW(EtalonRes!A16) -> 16 | E29: 1 | F29: 4.10-118-1 | G29: Установка для трубных проводок шкафа напольного размерами до 600х600 мм | H29: 1 ШТ. | I29: 1 | J29: 0 | K29: 1 | O29: =ROUND(CP29,2) -> 1524.35 | P29: =ROUND((ROUND((AC29*AW29*I29),2)*BC29),2) -> 130.52 | Q29: =(ROUND((ROUND((((ET29*1.1))*AV29*I29),2)*BB29),2)+ROUND((ROUND(((AE29-((EU29*1.1)))*AV29*I29),2)*BS29),2)) -> 38.33 | R29: =(ROUND((ROUND((((EU29*1.1))*AV29*I29),2)*BS29),2)+ROUND((ROUND(((AE29-((EU29*1.1)))*AV29*I29),2)*BS29),2)) -> 15.95 | S29: =ROUND((ROUND((AF29*AV29*I29),2)*BA29),2) -> 1355.5 | T29: =ROUND(CU29*I29,2) -> 0 | U29: =CV29*I29 -> 2.3034 | V29: =CW29*I29 -> 0 | W29: =ROUND(CX29*I29,2) -> 0 | X29: =(ROUND((((S29+ROUND((ROUND((((EU29*1.1))*AV29*I29),2)*BS29),2))*AT29)/100),2)+ROUND(((ROUND((ROUND(((AE29-((EU29*1.1)))*AV29*I29),2)*BS29),2)*AT29)/100),2)) -> 1234.31 | Y29: =(ROUND((((S29+ROUND((ROUND((((EU29*1.1))*AV29*I29),2)*BS29),2))*AU29)/100),2)+ROUND(((ROUND((ROUND(((AE29-((EU29*1.1)))*AV29*I29),2)*BS29),2)*AU29)/100),2)) -> 630.87 | AA29: 60256402 | AB29: =ROUND((AC29+AD29+AF29),6) -> 96.328 | AC29: =ROUND(((ES29*1)),6) -> 70.17 | AD29: =ROUND(((((ET29*1.1))-((EU29*1.1)))+AE29),6) -> 2.618 | AE29: =ROUND(((EU29*1.1)),6) -> 0.275 | AF29: =ROUND(((EV29*1.1)),6) -> 23.54 | AG29: =ROUND((AP29),6) -> 0 | AH29: =((EW29*1.1)) -> 2.2 | AI29: =((EX29*1.1)) -> 0 | AJ29: =(AS29) -> 0 | AK29: 93.95 | AL29: 70.17 | AM29: 2.38 | AN29: 0.25 | AO29: 21.4 | AP29: 0 | AQ29: 2 | AR29: 0 | AS29: 0 | AT29: 90 | AU29: 46 | AV29: 1.047 | AW29: 1 | AZ29: 1 | BA29: 54.99 | BB29: 13.99 | BC29: 1.86 | BH29: 0 | BI29: 2 | BJ29: ТСН-2001.4 Доп. 79, Сб. 10, т. 118, поз. 1 | BM29: 68 | BN29: 58973116 | BO29: 4.10-118-1 | BP29: 1 | BQ29: 40 | BR29: 0 | BS29: 54.99 | BT29: 1 | BU29: 1 | BV29: 1 | BW29: 1 | BX29: 1 | BZ29: 90 | CA29: 46 | CE29: 1566 | CF29: 0 | CG29: 0 | CM29: 0 | CN29: Поправка: Гл.12.Прил.8.п.8. 5_12.00.01.11.003 Наименование: При наличии усложненных условий производства работ (стесненность, сложность складирования и транспортной логистики, наличие в зоне производства работ действующего технологического оборудования или движения технологического транспорта и т.п.) для объектов, расположенных за пределами территории круговой магистральной системы улиц "Садовое кольцо" и за пределами Третьего транспортного кольца города Москвы пунктов "а" и "б", но в пределах Московской кольцевой автомобильной дороги | CO29: 0 | CP29: =(P29+Q29+S29) -> 1524.35 | CQ29: =ROUND((ROUND((AC29*AW29*1),2)*BC29),2) -> 130.52 | CR29: =(ROUND((ROUND((((ET29*1.1))*AV29*1),2)*BB29),2)+ROUND((ROUND(((AE29-((EU29*1.1)))*AV29*1),2)*BS29),2)) -> 38.33 | CS29: =(ROUND((ROUND((((EU29*1.1))*AV29*1),2)*BS29),2)+ROUND((ROUND(((AE29-((EU29*1.1)))*AV29*1),2)*BS29),2)) -> 15.95 | CT29: =ROUND((ROUND((AF29*AV29*1),2)*BA29),2) -> 1355.5 | CU29: =AG29 -> 0 | CV29: =(AH29*AV29) -> 2.3034 | CW29: =AI29 -> 0 | CX29: =AJ29 -> 0 | CY29: =(ROUND((((S29+ROUND((ROUND((((EU29*1.1))*AV29*1),2)*BS29),2))*AT29)/100),2)+ROUND(((ROUND((ROUND(((AE29-((EU29*1.1)))*AV29*1),2)*BS29),2)*AT29)/100),2)) -> 1234.31 | CZ29: =(ROUND((((S29+ROUND((ROUND((((EU29*1.1))*AV29*1),2)*BS29),2))*AU29)/100),2)+ROUND(((ROUND((ROUND(((AE29-((EU29*1.1)))*AV29*1),2)*BS29),2)*AU29)/100),2)) -> 630.87 | DB29: 2 | DD29: *1 | DE29: *1,1 | DF29: *1,1 | DG29: *1,1 | DI29: *1,1 | DJ29: *1,1 | DN29: 0 | DO29: 0 | DP29: 1 | DQ29: 1 | DU29: 1013 | DV29: 1 ШТ. | DW29: 1 ШТ. | DX29: 1 | EE29: 60088532 | EF29: 40 | EG29: Монтаж оборудования | EH29: 0 | EJ29: 2 | EK29: 68 | EL29: ТСН-2001.4-10. Прокладка и монтаж сетей связи | EM29: ТСН-2001.4-10-1 | EO29: Поправка: Гл.12.Прил.8.п.8. 5_12.00.01.11.003 | EQ29: 0 | ER29: 93.95 | ES29: 70.17 | ET29: 2.38 | EU29: 0.25 | EV29: 21.4 | EW29: 2 | EX29: 0 | EY29: 0 | FQ29: 0 | FR29: 0 | FS29: 0 | FX29: 90 | FY29: 46 | GD29: 1 | GF29: -1502969864 | GG29: 2 | GH29: 1 | GI29: 2 | GJ29: 0 | GK29: 0 | GL29: =ROUND(IF(AND(BH29=3,BI29=3,FS29<>0),P29,0),2) -> 0 | GM29: =ROUND(O29+X29+Y29,2)+GX29 -> 3389.53 | GN29: =IF(OR(BI29=0,BI29=1),GM29-GX29,0) -> 0 | GO29: =IF(BI29=2,GM29-GX29,0) -> 3389.53 | GP29: =IF(BI29=4,GM29-GX29,0) -> 0 | GR29: 0 | GS29: 3 | GT29: 0 | GV29: =ROUND((GT29),6) -> 0 | GW29: 1 | GX29: =ROUND(HC29*I29,2) -> 0 | HA29: 0 | HB29: 0 | HC29: =GV29*GW29 -> 0 | HS29: 0 | IK29: 0
A30: 17 | B30: 1 | E30: 2 | F30: КА-1 | G30: Шкаф настенный LINEA W 18U 600x600 мм дверь стекло RAL9005 LWR5-18U66-GF | H30: шт. | I30: 1 | J30: 0 | K30: 1 | O30: =ROUND(CP30,2) -> 1952.77 | P30: =ROUND((ROUND((AC30*AW30*I30),2)*BC30),2) -> 1952.77 | Q30: =(ROUND((ROUND(((ET30)*AV30*I30),2)*BB30),2)+ROUND((ROUND(((AE30-(EU30))*AV30*I30),2)*BS30),2)) -> 0 | R30: =(ROUND((ROUND(((EU30)*AV30*I30),2)*BS30),2)+ROUND((ROUND(((AE30-(EU30))*AV30*I30),2)*BS30),2)) -> 0 | S30: =ROUND((ROUND((AF30*AV30*I30),2)*BA30),2) -> 0 | T30: =ROUND(CU30*I30,2) -> 0 | U30: =CV30*I30 -> 0 | V30: =CW30*I30 -> 0 | W30: =ROUND(CX30*I30,2) -> 0 | X30: =(ROUND((((S30+ROUND((ROUND(((EU30)*AV30*I30),2)*BS30),2))*AT30)/100),2)+ROUND(((ROUND((ROUND(((AE30-(EU30))*AV30*I30),2)*BS30),2)*AT30)/100),2)) -> 0 | Y30: =(ROUND((((S30+ROUND((ROUND(((EU30)*AV30*I30),2)*BS30),2))*AU30)/100),2)+ROUND(((ROUND((ROUND(((AE30-(EU30))*AV30*I30),2)*BS30),2)*AU30)/100),2)) -> 0 | AA30: 60256405 | AB30: =ROUND((AC30+AD30+AF30),6) -> 1952.77 | AC30: =ROUND((ES30),6) -> 1952.77 | AD30: =ROUND((((ET30)-(EU30))+AE30),6) -> 0 | AE30: =ROUND((EU30),6) -> 0 | AF30: =ROUND((EV30),6) -> 0 | AG30: =ROUND((AP30),6) -> 0 | AH30: =(EW30) -> 0 | AI30: =(EX30) -> 0 | AJ30: =(AS30) -> 0 | AK30: 1952.77 | AL30: 1952.77 | AM30: 0 | AN30: 0 | AO30: 0 | AP30: 0 | AQ30: 0 | AR30: 0 | AS30: 0 | AT30: 90 | AU30: 46 | AV30: 1 | AW30: 1 | AZ30: 1 | BA30: 1 | BB30: 1 | BC30: 1 | BH30: 3 | BI30: 2 | BM30: 68 | BN30: 0 | BP30: 0 | BQ30: 40 | BR30: 0 | BS30: 1 | BT30: 1 | BU30: 1 | BV30: 1 | BW30: 1 | BX30: 1 | BZ30: 90 | CA30: 46 | CE30: 1566 | CF30: 0 | CG30: 0 | CM30: 0 | CO30: 0 | CP30: =(P30+Q30+S30) -> 1952.77 | CQ30: =ROUND((ROUND((AC30*AW30*1),2)*BC30),2) -> 1952.77 | CR30: =(ROUND((ROUND(((ET30)*AV30*1),2)*BB30),2)+ROUND((ROUND(((AE30-(EU30))*AV30*1),2)*BS30),2)) -> 0 | CS30: =(ROUND((ROUND(((EU30)*AV30*1),2)*BS30),2)+ROUND((ROUND(((AE30-(EU30))*AV30*1),2)*BS30),2)) -> 0 | CT30: =ROUND((ROUND((AF30*AV30*1),2)*BA30),2) -> 0 | CU30: =AG30 -> 0 | CV30: =(AH30*AV30) -> 0 | CW30: =AI30 -> 0 | CX30: =AJ30 -> 0 | CY30: =(ROUND((((S30+ROUND((ROUND(((EU30)*AV30*1),2)*BS30),2))*AT30)/100),2)+ROUND(((ROUND((ROUND(((AE30-(EU30))*AV30*1),2)*BS30),2)*AT30)/100),2)) -> 0 | CZ30: =(ROUND((((S30+ROUND((ROUND(((EU30)*AV30*1),2)*BS30),2))*AU30)/100),2)+ROUND(((ROUND((ROUND(((AE30-(EU30))*AV30*1),2)*BS30),2)*AU30)/100),2)) -> 0 | DN30: 0 | DO30: 0 | DP30: 1 | DQ30: 1 | DU30: 1010 | DV30: шт. | DW30: шт. | DX30: 1 | EE30: 60088532 | EF30: 40 | EG30: Монтаж оборудования | EH30: 0 | EJ30: 2 | EK30: 68 | EL30: ТСН-2001.4-10. Прокладка и монтаж сетей связи | EM30: ТСН-2001.4-10-1 | EQ30: 0 | ER30: 0 | ES30: 1952.77 | ET30: 0 | EU30: 0 | EV30: 0 | EW30: 0 | EX30: 0 | EY30: 0 | FQ30: 0 | FR30: 0 | FS30: 0 | FX30: 90 | FY30: 46 | GA30: [22 698,04 / 1,2 / 9,88] + 2% Заг.скл | GD30: 1 | GF30: 461997237 | GG30: 2 | GH30: 4 | GI30: -2 | GJ30: 0 | GK30: 0 | GL30: =ROUND(IF(AND(BH30=3,BI30=3,FS30<>0),P30,0),2) -> 0 | GM30: =ROUND(O30+X30+Y30,2)+GX30 -> 1952.77 | GN30: =IF(OR(BI30=0,BI30=1),GM30-GX30,0) -> 0 | GO30: =IF(BI30=2,GM30-GX30,0) -> 1952.77 | GP30: =IF(BI30=4,GM30-GX30,0) -> 0 | GR30: 0 | GS30: 2 | GT30: 0 | GV30: =ROUND((GT30),6) -> 0 | GW30: 1 | GX30: =ROUND(HC30*I30,2) -> 0 | HA30: 0 | HB30: 0 | HC30: =GV30*GW30 -> 0 | HE30: 0 | HF30: 2 | HS30: 0 | IK30: 0
A31: 17 | B31: 1 | E31: 2 | F31: КА-1 | G31: Шкаф настенный LINEA W 18U 600x600 мм дверь стекло RAL9005 LWR5-18U66-GF | H31: шт. | I31: 1 | J31: 0 | K31: 1 | O31: =ROUND(CP31,2) -> 19293.37 | P31: =ROUND((ROUND((AC31*AW31*I31),2)*BC31),2) -> 19293.37 | Q31: =(ROUND((ROUND(((ET31)*AV31*I31),2)*BB31),2)+ROUND((ROUND(((AE31-(EU31))*AV31*I31),2)*BS31),2)) -> 0 | R31: =(ROUND((ROUND(((EU31)*AV31*I31),2)*BS31),2)+ROUND((ROUND(((AE31-(EU31))*AV31*I31),2)*BS31),2)) -> 0 | S31: =ROUND((ROUND((AF31*AV31*I31),2)*BA31),2) -> 0 | T31: =ROUND(CU31*I31,2) -> 0 | U31: =CV31*I31 -> 0 | V31: =CW31*I31 -> 0 | W31: =ROUND(CX31*I31,2) -> 0 | X31: =(ROUND((((S31+ROUND((ROUND(((EU31)*AV31*I31),2)*BS31),2))*AT31)/100),2)+ROUND(((ROUND((ROUND(((AE31-(EU31))*AV31*I31),2)*BS31),2)*AT31)/100),2)) -> 0 | Y31: =(ROUND((((S31+ROUND((ROUND(((EU31)*AV31*I31),2)*BS31),2))*AU31)/100),2)+ROUND(((ROUND((ROUND(((AE31-(EU31))*AV31*I31),2)*BS31),2)*AU31)/100),2)) -> 0 | AA31: 60256402 | AB31: =ROUND((AC31+AD31+AF31),6) -> 1952.77 | AC31: =ROUND((ES31),6) -> 1952.77 | AD31: =ROUND((((ET31)-(EU31))+AE31),6) -> 0 | AE31: =ROUND((EU31),6) -> 0 | AF31: =ROUND((EV31),6) -> 0 | AG31: =ROUND((AP31),6) -> 0 | AH31: =(EW31) -> 0 | AI31: =(EX31) -> 0 | AJ31: =(AS31) -> 0 | AK31: 1952.77 | AL31: 1952.77 | AM31: 0 | AN31: 0 | AO31: 0 | AP31: 0 | AQ31: 0 | AR31: 0 | AS31: 0 | AT31: 90 | AU31: 46 | AV31: 1 | AW31: 1 | AZ31: 1 | BA31: 1 | BB31: 1 | BC31: 9.88 | BH31: 3 | BI31: 2 | BM31: 68 | BN31: 0 | BP31: 0 | BQ31: 40 | BR31: 0 | BS31: 1 | BT31: 1 | BU31: 1 | BV31: 1 | BW31: 1 | BX31: 1 | BZ31: 90 | CA31: 46 | CE31: 1566 | CF31: 0 | CG31: 0 | CM31: 0 | CO31: 0 | CP31: =(P31+Q31+S31) -> 19293.37 | CQ31: =ROUND((ROUND((AC31*AW31*1),2)*BC31),2) -> 19293.37 | CR31: =(ROUND((ROUND(((ET31)*AV31*1),2)*BB31),2)+ROUND((ROUND(((AE31-(EU31))*AV31*1),2)*BS31),2)) -> 0 | CS31: =(ROUND((ROUND(((EU31)*AV31*1),2)*BS31),2)+ROUND((ROUND(((AE31-(EU31))*AV31*1),2)*BS31),2)) -> 0 | CT31: =ROUND((ROUND((AF31*AV31*1),2)*BA31),2) -> 0 | CU31: =AG31 -> 0 | CV31: =(AH31*AV31) -> 0 | CW31: =AI31 -> 0 | CX31: =AJ31 -> 0 | CY31: =(ROUND((((S31+ROUND((ROUND(((EU31)*AV31*1),2)*BS31),2))*AT31)/100),2)+ROUND(((ROUND((ROUND(((AE31-(EU31))*AV31*1),2)*BS31),2)*AT31)/100),2)) -> 0 | CZ31: =(ROUND((((S31+ROUND((ROUND(((EU31)*AV31*1),2)*BS31),2))*AU31)/100),2)+ROUND(((ROUND((ROUND(((AE31-(EU31))*AV31*1),2)*BS31),2)*AU31)/100),2)) -> 0 | DN31: 0 | DO31: 0 | DP31: 1 | DQ31: 1 | DU31: 1010 | DV31: шт. | DW31: шт. | DX31: 1 | EE31: 60088532 | EF31: 40 | EG31: Монтаж оборудования | EH31: 0 | EJ31: 2 | EK31: 68 | EL31: ТСН-2001.4-10. Прокладка и монтаж сетей связи | EM31: ТСН-2001.4-10-1 | EQ31: 0 | ER31: 1952.77 | ES31: 1952.77 | ET31: 0 | EU31: 0 | EV31: 0 | EW31: 0 | EX31: 0 | EY31: 0 | EZ31: 5 | FC31: 1 | FD31: 18 | FF31: 22698.04 | FQ31: 0 | FR31: 0 | FS31: 0 | FX31: 90 | FY31: 46 | GA31: [22 698,04 / 1,2 / 9,88] + 2% Заг.скл | GD31: 1 | GF31: 461997237 | GG31: 2 | GH31: 3 | GI31: 5 | GJ31: 0 | GK31: 0 | GL31: =ROUND(IF(AND(BH31=3,BI31=3,FS31<>0),P31,0),2) -> 0 | GM31: =ROUND(O31+X31+Y31,2)+GX31 -> 19293.37 | GN31: =IF(OR(BI31=0,BI31=1),GM31-GX31,0) -> 0 | GO31: =IF(BI31=2,GM31-GX31,0) -> 19293.37 | GP31: =IF(BI31=4,GM31-GX31,0) -> 0 | GR31: 1 | GS31: 1 | GT31: 0 | GV31: =ROUND((GT31),6) -> 0 | GW31: 1 | GX31: =ROUND(HC31*I31,2) -> 0 | HA31: 0 | HB31: 0 | HC31: =GV31*GW31 -> 0 | HE31: 0 | HF31: 2 | HS31: 0 | IK31: 0
A32: 17 | B32: 1 | C32: =ROW(SmtRes!A18) -> 18 | D32: =ROW(EtalonRes!A21) -> 21 | E32: 3 | F32: 4.10-170-2 | G32: Монтаж блока информационно-управляющего (БИУ) в диспетчерской | H32: 1 ШТ. | I32: 1 | J32: 0 | K32: 1 | O32: =ROUND(CP32,2) -> 40.89 | P32: =ROUND((ROUND((AC32*AW32*I32),2)*BC32),2) -> 2.34 | Q32: =(ROUND((ROUND((((ET32*1.1))*AV32*I32),2)*BB32),2)+ROUND((ROUND(((AE32-((EU32*1.1)))*AV32*I32),2)*BS32),2)) -> 0 | R32: =(ROUND((ROUND((((EU32*1.1))*AV32*I32),2)*BS32),2)+ROUND((ROUND(((AE32-((EU32*1.1)))*AV32*I32),2)*BS32),2)) -> 0 | S32: =ROUND((ROUND((AF32*AV32*I32),2)*BA32),2) -> 38.55 | T32: =ROUND(CU32*I32,2) -> 0 | U32: =CV32*I32 -> 3.052005 | V32: =CW32*I32 -> 0 | W32: =ROUND(CX32*I32,2) -> 0 | X32: =(ROUND((((S32+ROUND((ROUND((((EU32*1.1))*AV32*I32),2)*BS32),2))*AT32)/100),2)+ROUND(((ROUND((ROUND(((AE32-((EU32*1.1)))*AV32*I32),2)*BS32),2)*AT32)/100),2)) -> 34.7 | Y32: =(ROUND((((S32+ROUND((ROUND((((EU32*1.1))*AV32*I32),2)*BS32),2))*AU32)/100),2)+ROUND(((ROUND((ROUND(((AE32-((EU32*1.1)))*AV32*I32),2)*BS32),2)*AU32)/100),2)) -> 17.73 | AA32: 60256405 | AB32: =ROUND((AC32+AD32+AF32),6) -> 39.157 | AC32: =ROUND(((ES32*1)),6) -> 2.34 | AD32: =ROUND(((((ET32*1.1))-((EU32*1.1)))+AE32),6) -> 0 | AE32: =ROUND(((EU32*1.1)),6) -> 0 | AF32: =ROUND(((EV32*1.1)),6) -> 36.817 | AG32: =ROUND((AP32),6) -> 0 | AH32: =((EW32*1.1)) -> 2.915 | AI32: =((EX32*1.1)) -> 0 | AJ32: =(AS32) -> 0 | AK32: 35.81 | AL32: 2.34 | AM32: 0 | AN32: 0 | AO32: 33.47 | AP32: 0 | AQ32: 2.65 | AR32: 0 | AS32: 0 | AT32: 90 | AU32: 46 | AV32: 1.047 | AW32: 1 | AZ32: 1 | BA32: 1 | BB32: 1 | BC32: 1 | BH32: 0 | BI32: 2 | BJ32: ТСН-2001.4 Доп. 67, Сб. 10, т. 170, поз. 2 | BM32: 68 | BN32: 58973116 | BO32: 4.10-170-2 | BP32: 1 | BQ32: 40 | BR32: 0 | BS32: 1 | BT32: 1 | BU32: 1 | BV32: 1 | BW32: 1 | BX32: 1 | BZ32: 90 | CA32: 46 | CE32: 1566 | CF32: 0 | CG32: 0 | CM32: 0 | CN32: Поправка: Гл.12.Прил.8.п.8. 5_12.00.01.11.003 Наименование: При наличии усложненных условий производства работ (стесненность, сложность складирования и транспортной логистики, наличие в зоне производства работ действующего технологического оборудования или движения технологического транспорта и т.п.) для объектов, расположенных за пределами территории круговой магистральной системы улиц "Садовое кольцо" и за пределами Третьего транспортного кольца города Москвы пунктов "а" и "б", но в пределах Московской кольцевой автомобильной дороги | CO32: 0 | CP32: =(P32+Q32+S32) -> 40.89 | CQ32: =ROUND((ROUND((AC32*AW32*1),2)*BC32),2) -> 2.34 | CR32: =(ROUND((ROUND((((ET32*1.1))*AV32*1),2)*BB32),2)+ROUND((ROUND(((AE32-((EU32*1.1)))*AV32*1),2)*BS32),2)) -> 0 | CS32: =(ROUND((ROUND((((EU32*1.1))*AV32*1),2)*BS32),2)+ROUND((ROUND(((AE32-((EU32*1.1)))*AV32*1),2)*BS32),2)) -> 0 | CT32: =ROUND((ROUND((AF32*AV32*1),2)*BA32),2) -> 38.55 | CU32: =AG32 -> 0 | CV32: =(AH32*AV32) -> 3.052005 | CW32: =AI32 -> 0 | CX32: =AJ32 -> 0 | CY32: =(ROUND((((S32+ROUND((ROUND((((EU32*1.1))*AV32*1),2)*BS32),2))*AT32)/100),2)+ROUND(((ROUND((ROUND(((AE32-((EU32*1.1)))*AV32*1),2)*BS32),2)*AT32)/100),2)) -> 34.7 | CZ32: =(ROUND((((S32+ROUND((ROUND((((EU32*1.1))*AV32*1),2)*BS32),2))*AU32)/100),2)+ROUND(((ROUND((ROUND(((AE32-((EU32*1.1)))*AV32*1),2)*BS32),2)*AU32)/100),2)) -> 17.73 | DB32: 3 | DD32: *1 | DE32: *1,1 | DF32: *1,1 | DG32: *1,1 | DI32: *1,1 | DJ32: *1,1 | DN32: 0 | DO32: 0 | DP32: 1 | DQ32: 1 | DU32: 1013 | DV32: 1 ШТ. | DW32: 1 ШТ. | DX32: 1 | EE32: 60088532 | EF32: 40 | EG32: Монтаж оборудования | EH32: 0 | EJ32: 2 | EK32: 68 | EL32: ТСН-2001.4-10. Прокладка и монтаж сетей связи | EM32: ТСН-2001.4-10-1 | EO32: Поправка: Гл.12.Прил.8.п.8. 5_12.00.01.11.003 | EQ32: 0 | ER32: 35.81 | ES32: 2.34 | ET32: 0 | EU32: 0 | EV32: 33.47 | EW32: 2.65 | EX32: 0 | EY32: 0 | FQ32: 0 | FR32: 0 | FS32: 0 | FX32: 90 | FY32: 46 | GD32: 1 | GF32: -1323780471 | GG32: 2 | GH32: 1 | GI32: 2 | GJ32: 0 | GK32: 0 | GL32: =ROUND(IF(AND(BH32=3,BI32=3,FS32<>0),P32,0),2) -> 0 | GM32: =ROUND(O32+X32+Y32,2)+GX32 -> 93.32 | GN32: =IF(OR(BI32=0,BI32=1),GM32-GX32,0) -> 0 | GO32: =IF(BI32=2,GM32-GX32,0) -> 93.32 | GP32: =IF(BI32=4,GM32-GX32,0) -> 0 | GR32: 0 | GS32: 3 | GT32: 0 | GV32: =ROUND((GT32),6) -> 0 | GW32: 1 | GX32: =ROUND(HC32*I32,2) -> 0 | HA32: 0 | HB32: 0 | HC32: =GV32*GW32 -> 0 | HS32: 0 | IK32: 0
A33: 17 | B33: 1 | C33: =ROW(SmtRes!A22) -> 22 | D33: =ROW(EtalonRes!A26) -> 26 | E33: 3 | F33: 4.10-170-2 | G33: Монтаж блока информационно-управляющего (БИУ) в диспетчерской | H33: 1 ШТ. | I33: 1 | J33: 0 | K33: 1 | O33: =ROUND(CP33,2) -> 2143.87 | P33: =ROUND((ROUND((AC33*AW33*I33),2)*BC33),2) -> 24.01 | Q33: =(ROUND((ROUND((((ET33*1.1))*AV33*I33),2)*BB33),2)+ROUND((ROUND(((AE33-((EU33*1.1)))*AV33*I33),2)*BS33),2)) -> 0 | R33: =(ROUND((ROUND((((EU33*1.1))*AV33*I33),2)*BS33),2)+ROUND((ROUND(((AE33-((EU33*1.1)))*AV33*I33),2)*BS33),2)) -> 0 | S33: =ROUND((ROUND((AF33*AV33*I33),2)*BA33),2) -> 2119.86 | T33: =ROUND(CU33*I33,2) -> 0 | U33: =CV33*I33 -> 3.052005 | V33: =CW33*I33 -> 0 | W33: =ROUND(CX33*I33,2) -> 0 | X33: =(ROUND((((S33+ROUND((ROUND((((EU33*1.1))*AV33*I33),2)*BS33),2))*AT33)/100),2)+ROUND(((ROUND((ROUND(((AE33-((EU33*1.1)))*AV33*I33),2)*BS33),2)*AT33)/100),2)) -> 1907.87 | Y33: =(ROUND((((S33+ROUND((ROUND((((EU33*1.1))*AV33*I33),2)*BS33),2))*AU33)/100),2)+ROUND(((ROUND((ROUND(((AE33-((EU33*1.1)))*AV33*I33),2)*BS33),2)*AU33)/100),2)) -> 975.14 | AA33: 60256402 | AB33: =ROUND((AC33+AD33+AF33),6) -> 39.157 | AC33: =ROUND(((ES33*1)),6) -> 2.34 | AD33: =ROUND(((((ET33*1.1))-((EU33*1.1)))+AE33),6) -> 0 | AE33: =ROUND(((EU33*1.1)),6) -> 0 | AF33: =ROUND(((EV33*1.1)),6) -> 36.817 | AG33: =ROUND((AP33),6) -> 0 | AH33: =((EW33*1.1)) -> 2.915 | AI33: =((EX33*1.1)) -> 0 | AJ33: =(AS33) -> 0 | AK33: 35.81 | AL33: 2.34 | AM33: 0 | AN33: 0 | AO33: 33.47 | AP33: 0 | AQ33: 2.65 | AR33: 0 | AS33: 0 | AT33: 90 | AU33: 46 | AV33: 1.047 | AW33: 1 | AZ33: 1 | BA33: 54.99 | BB33: 1 | BC33: 10.26 | BH33: 0 | BI33: 2 | BJ33: ТСН-2001.4 Доп. 67, Сб. 10, т. 170, поз. 2 | BM33: 68 | BN33: 58973116 | BO33: 4.10-170-2 | BP33: 1 | BQ33: 40 | BR33: 0 | BS33: 54.99 | BT33: 1 | BU33: 1 | BV33: 1 | BW33: 1 | BX33: 1 | BZ33: 90 | CA33: 46 | CE33: 1566 | CF33: 0 | CG33: 0 | CM33: 0 | CN33: Поправка: Гл.12.Прил.8.п.8. 5_12.00.01.11.003 Наименование: При наличии усложненных условий производства работ (стесненность, сложность складирования и транспортной логистики, наличие в зоне производства работ действующего технологического оборудования или движения технологического транспорта и т.п.) для объектов, расположенных за пределами территории круговой магистральной системы улиц "Садовое кольцо" и за пределами Третьего транспортного кольца города Москвы пунктов "а" и "б", но в пределах Московской кольцевой автомобильной дороги | CO33: 0 | CP33: =(P33+Q33+S33) -> 2143.87 | CQ33: =ROUND((ROUND((AC33*AW33*1),2)*BC33),2) -> 24.01 | CR33: =(ROUND((ROUND((((ET33*1.1))*AV33*1),2)*BB33),2)+ROUND((ROUND(((AE33-((EU33*1.1)))*AV33*1),2)*BS33),2)) -> 0 | CS33: =(ROUND((ROUND((((EU33*1.1))*AV33*1),2)*BS33),2)+ROUND((ROUND(((AE33-((EU33*1.1)))*AV33*1),2)*BS33),2)) -> 0 | CT33: =ROUND((ROUND((AF33*AV33*1),2)*BA33),2) -> 2119.86 | CU33: =AG33 -> 0 | CV33: =(AH33*AV33) -> 3.052005 | CW33: =AI33 -> 0 | CX33: =AJ33 -> 0 | CY33: =(ROUND((((S33+ROUND((ROUND((((EU33*1.1))*AV33*1),2)*BS33),2))*AT33)/100),2)+ROUND(((ROUND((ROUND(((AE33-((EU33*1.1)))*AV33*1),2)*BS33),2)*AT33)/100),2)) -> 1907.87 | CZ33: =(ROUND((((S33+ROUND((ROUND((((EU33*1.1))*AV33*1),2)*BS33),2))*AU33)/100),2)+ROUND(((ROUND((ROUND(((AE33-((EU33*1.1)))*AV33*1),2)*BS33),2)*AU33)/100),2)) -> 975.14 | DB33: 4 | DD33: *1 | DE33: *1,1 | DF33: *1,1 | DG33: *1,1 | DI33: *1,1 | DJ33: *1,1 | DN33: 0 | DO33: 0 | DP33: 1 | DQ33: 1 | DU33: 1013 | DV33: 1 ШТ. | DW33: 1 ШТ. | DX33: 1 | EE33: 60088532 | EF33: 40 | EG33: Монтаж оборудования | EH33: 0 | EJ33: 2 | EK33: 68 | EL33: ТСН-2001.4-10. Прокладка и монтаж сетей связи | EM33: ТСН-2001.4-10-1 | EO33: Поправка: Гл.12.Прил.8.п.8. 5_12.00.01.11.003 | EQ33: 0 | ER33: 35.81 | ES33: 2.34 | ET33: 0 | EU33: 0 | EV33: 33.47 | EW33: 2.65 | EX33: 0 | EY33: 0 | FQ33: 0 | FR33: 0 | FS33: 0 | FX33: 90 | FY33: 46 | GD33: 1 | GF33: -1323780471 | GG33: 2 | GH33: 1 | GI33: 2 | GJ33: 0 | GK33: 0 | GL33: =ROUND(IF(AND(BH33=3,BI33=3,FS33<>0),P33,0),2) -> 0 | GM33: =ROUND(O33+X33+Y33,2)+GX33 -> 5026.88 | GN33: =IF(OR(BI33=0,BI33=1),GM33-GX33,0) -> 0 | GO33: =IF(BI33=2,GM33-GX33,0) -> 5026.88 | GP33: =IF(BI33=4,GM33-GX33,0) -> 0 | GR33: 0 | GS33: 3 | GT33: 0 | GV33: =ROUND((GT33),6) -> 0 | GW33: 1 | GX33: =ROUND(HC33*I33,2) -> 0 | HA33: 0 | HB33: 0 | HC33: =GV33*GW33 -> 0 | HS33: 0 | IK33: 0
A34: 17 | B34: 1 | E34: 4 | F34: КА-2 | G34: Прибор управления оповещением пожарной Sonar SPM, мощность850 Вт, 20 зон/20 линий оповещения, прием сигнала от ОПС по АЛС, установка в стойку Sonar SPM-C20085-AR | H34: шт. | I34: 1 | J34: 0 | K34: 1 | O34: =ROUND(CP34,2) -> 32107.68 | P34: =ROUND((ROUND((AC34*I34),2)*BC34),2) -> 32107.68 | Q34: =(ROUND((ROUND(((ET34)*AV34*I34),2)*BB34),2)+ROUND((ROUND(((AE34-(EU34))*AV34*I34),2)*BS34),2)) -> 0 | R34: =(ROUND((ROUND(((EU34)*AV34*I34),2)*BS34),2)+ROUND((ROUND(((AE34-(EU34))*AV34*I34),2)*BS34),2)) -> 0 | S34: =ROUND((ROUND((AF34*AV34*I34),2)*BA34),2) -> 0 | T34: =ROUND(CU34*I34,2) -> 0 | U34: =CV34*I34 -> 0 | V34: =CW34*I34 -> 0 | W34: =ROUND(CX34*I34,2) -> 0 | X34: =(ROUND((((S34+ROUND((ROUND(((EU34)*AV34*I34),2)*BS34),2))*AT34)/100),2)+ROUND(((ROUND((ROUND(((AE34-(EU34))*AV34*I34),2)*BS34),2)*AT34)/100),2)) -> 0 | Y34: =(ROUND((((S34+ROUND((ROUND(((EU34)*AV34*I34),2)*BS34),2))*AU34)/100),2)+ROUND(((ROUND((ROUND(((AE34-(EU34))*AV34*I34),2)*BS34),2)*AU34)/100),2)) -> 0 | AA34: 60256405 | AB34: =ROUND((AC34+AD34+AF34),6) -> 32107.68 | AC34: =ROUND((ES34),6) -> 32107.68 | AD34: =ROUND((((ET34)-(EU34))+AE34),6) -> 0 | AE34: =ROUND((EU34),6) -> 0 | AF34: =ROUND((EV34),6) -> 0 | AG34: =ROUND((AP34),6) -> 0 | AH34: =(EW34) -> 0 | AI34: =(EX34) -> 0 | AJ34: =(AS34) -> 0 | AK34: 32107.68 | AL34: 32107.68 | AM34: 0 | AN34: 0 | AO34: 0 | AP34: 0 | AQ34: 0 | AR34: 0 | AS34: 0 | AT34: 0 | AU34: 0 | AV34: 1 | AW34: 1 | AZ34: 1 | BA34: 1 | BB34: 1 | BC34: 1 | BH34: 3 | BI34: 3 | BM34: 746 | BN34: 0 | BP34: 0 | BQ34: 130 | BR34: 0 | BS34: 1 | BT34: 1 | BU34: 1 | BV34: 1 | BW34: 1 | BX34: 1 | BZ34: 0 | CA34: 0 | CE34: 1566 | CF34: 0 | CG34: 0 | CM34: 0 | CO34: 0 | CP34: =(P34+Q34+S34) -> 32107.68 | CQ34: =ROUND((ROUND((AC34*1),2)*BC34),2) -> 32107.68 | CR34: =(ROUND((ROUND(((ET34)*AV34*1),2)*BB34),2)+ROUND((ROUND(((AE34-(EU34))*AV34*1),2)*BS34),2)) -> 0 | CS34: =(ROUND((ROUND(((EU34)*AV34*1),2)*BS34),2)+ROUND((ROUND(((AE34-(EU34))*AV34*1),2)*BS34),2)) -> 0 | CT34: =ROUND((ROUND((AF34*AV34*1),2)*BA34),2) -> 0 | CU34: =AG34 -> 0 | CV34: =(AH34*AV34) -> 0 | CW34: =AI34 -> 0 | CX34: =AJ34 -> 0 | CY34: =(ROUND((((S34+ROUND((ROUND(((EU34)*AV34*1),2)*BS34),2))*AT34)/100),2)+ROUND(((ROUND((ROUND(((AE34-(EU34))*AV34*1),2)*BS34),2)*AT34)/100),2)) -> 0 | CZ34: =(ROUND((((S34+ROUND((ROUND(((EU34)*AV34*1),2)*BS34),2))*AU34)/100),2)+ROUND(((ROUND((ROUND(((AE34-(EU34))*AV34*1),2)*BS34),2)*AU34)/100),2)) -> 0 | DN34: 0 | DO34: 0 | DP34: 1 | DQ34: 1 | DU34: 1010 | DV34: шт. | DW34: шт. | DX34: 1 | EE34: 60088638 | EF34: 130 | EG34: Сметная стоимость оборудования | EH34: 0 | EJ34: 3 | EK34: 746 | EL34: ТСН-2001.13. Сметная стоимость оборудования | EM34: ТСН-2001.13 | EQ34: 0 | ER34: 0 | ES34: 32107.68 | ET34: 0 | EU34: 0 | EV34: 0 | EW34: 0 | EX34: 0 | EY34: 0 | FQ34: 0 | FR34: =P34 -> 32107.68 | FS34: 0 | FX34: 0 | FY34: 0 | GA34: [283 140 / 1,2 / 7,66] + 3% Трансп + 1,2% Заг.скл | GD34: 1 | GF34: -1433651412 | GG34: 2 | GH34: 4 | GI34: -2 | GJ34: 0 | GK34: 0 | GL34: =ROUND(IF(AND(BH34=3,BI34=3,FS34<>0),P34,0),2) -> 0 | GM34: =ROUND(O34+X34+Y34,2)+GX34 -> 32107.68 | GN34: =IF(OR(BI34=0,BI34=1),GM34-GX34,0) -> 0 | GO34: =IF(BI34=2,GM34-GX34,0) -> 0 | GP34: =IF(BI34=4,GM34-GX34,0) -> 0 | GR34: 0 | GS34: 2 | GT34: 0 | GV34: =ROUND((GT34),6) -> 0 | GW34: 1 | GX34: =ROUND(HC34*I34,2) -> 0 | HA34: 0 | HB34: 0 | HC34: =GV34*GW34 -> 0 | HE34: 3 | HF34: 1,2 | HS34: 0 | IK34: 0
A35: 17 | B35: 1 | E35: 4 | F35: КА-2 | G35: Прибор управления оповещением пожарной Sonar SPM, мощность850 Вт, 20 зон/20 линий оповещения, прием сигнала от ОПС по АЛС, установка в стойку Sonar SPM-C20085-AR | H35: шт. | I35: 1 | J35: 0 | K35: 1 | O35: =ROUND(CP35,2) -> 245944.83 | P35: =ROUND((ROUND((AC35*I35),2)*BC35),2) -> 245944.83 | Q35: =(ROUND((ROUND(((ET35)*AV35*I35),2)*BB35),2)+ROUND((ROUND(((AE35-(EU35))*AV35*I35),2)*BS35),2)) -> 0 | R35: =(ROUND((ROUND(((EU35)*AV35*I35),2)*BS35),2)+ROUND((ROUND(((AE35-(EU35))*AV35*I35),2)*BS35),2)) -> 0 | S35: =ROUND((ROUND((AF35*AV35*I35),2)*BA35),2) -> 0 | T35: =ROUND(CU35*I35,2) -> 0 | U35: =CV35*I35 -> 0 | V35: =CW35*I35 -> 0 | W35: =ROUND(CX35*I35,2) -> 0 | X35: =(ROUND((((S35+ROUND((ROUND(((EU35)*AV35*I35),2)*BS35),2))*AT35)/100),2)+ROUND(((ROUND((ROUND(((AE35-(EU35))*AV35*I35),2)*BS35),2)*AT35)/100),2)) -> 0 | Y35: =(ROUND((((S35+ROUND((ROUND(((EU35)*AV35*I35),2)*BS35),2))*AU35)/100),2)+ROUND(((ROUND((ROUND(((AE35-(EU35))*AV35*I35),2)*BS35),2)*AU35)/100),2)) -> 0 | AA35: 60256402 | AB35: =ROUND((AC35+AD35+AF35),6) -> 32107.68 | AC35: =ROUND((ES35),6) -> 32107.68 | AD35: =ROUND((((ET35)-(EU35))+AE35),6) -> 0 | AE35: =ROUND((EU35),6) -> 0 | AF35: =ROUND((EV35),6) -> 0 | AG35: =ROUND((AP35),6) -> 0 | AH35: =(EW35) -> 0 | AI35: =(EX35) -> 0 | AJ35: =(AS35) -> 0 | AK35: 32107.68 | AL35: 32107.68 | AM35: 0 | AN35: 0 | AO35: 0 | AP35: 0 | AQ35: 0 | AR35: 0 | AS35: 0 | AT35: 0 | AU35: 0 | AV35: 1 | AW35: 1 | AZ35: 1 | BA35: 1 | BB35: 1 | BC35: 7.66 | BH35: 3 | BI35: 3 | BM35: 746 | BN35: 0 | BP35: 0 | BQ35: 130 | BR35: 0 | BS35: 1 | BT35: 1 | BU35: 1 | BV35: 1 | BW35: 1 | BX35: 1 | BZ35: 0 | CA35: 0 | CE35: 1566 | CF35: 0 | CG35: 0 | CM35: 0 | CO35: 0 | CP35: =(P35+Q35+S35) -> 245944.83 | CQ35: =ROUND((ROUND((AC35*1),2)*BC35),2) -> 245944.83 | CR35: =(ROUND((ROUND(((ET35)*AV35*1),2)*BB35),2)+ROUND((ROUND(((AE35-(EU35))*AV35*1),2)*BS35),2)) -> 0 | CS35: =(ROUND((ROUND(((EU35)*AV35*1),2)*BS35),2)+ROUND((ROUND(((AE35-(EU35))*AV35*1),2)*BS35),2)) -> 0 | CT35: =ROUND((ROUND((AF35*AV35*1),2)*BA35),2) -> 0 | CU35: =AG35 -> 0 | CV35: =(AH35*AV35) -> 0 | CW35: =AI35 -> 0 | CX35: =AJ35 -> 0 | CY35: =(ROUND((((S35+ROUND((ROUND(((EU35)*AV35*1),2)*BS35),2))*AT35)/100),2)+ROUND(((ROUND((ROUND(((AE35-(EU35))*AV35*1),2)*BS35),2)*AT35)/100),2)) -> 0 | CZ35: =(ROUND((((S35+ROUND((ROUND(((EU35)*AV35*1),2)*BS35),2))*AU35)/100),2)+ROUND(((ROUND((ROUND(((AE35-(EU35))*AV35*1),2)*BS35),2)*AU35)/100),2)) -> 0 | DN35: 0 | DO35: 0 | DP35: 1 | DQ35: 1 | DU35: 1010 | DV35: шт. | DW35: шт. | DX35: 1 | EE35: 60088638 | EF35: 130 | EG35: Сметная стоимость оборудования | EH35: 0 | EJ35: 3 | EK35: 746 | EL35: ТСН-2001.13. Сметная стоимость оборудования | EM35: ТСН-2001.13 | EQ35: 0 | ER35: 24359.21 | ES35: 32107.68 | ET35: 0 | EU35: 0 | EV35: 0 | EW35: 0 | EX35: 0 | EY35: 0 | EZ35: 5 | FC35: 1 | FD35: 18 | FF35: 283140 | FQ35: 0 | FR35: =P35 -> 245944.83 | FS35: 0 | FX35: 0 | FY35: 0 | GA35: [283 140 / 1,2 / 7,66] + 3% Трансп + 1,2% Заг.скл | GD35: 1 | GF35: -1433651412 | GG35: 2 | GH35: 3 | GI35: 5 | GJ35: 0 | GK35: 0 | GL35: =ROUND(IF(AND(BH35=3,BI35=3,FS35<>0),P35,0),2) -> 0 | GM35: =ROUND(O35+X35+Y35,2)+GX35 -> 245944.83 | GN35: =IF(OR(BI35=0,BI35=1),GM35-GX35,0) -> 0 | GO35: =IF(BI35=2,GM35-GX35,0) -> 0 | GP35: =IF(BI35=4,GM35-GX35,0) -> 0 | GR35: 1 | GS35: 1 | GT35: 0 | GV35: =ROUND((GT35),6) -> 0 | GW35: 1 | GX35: =ROUND(HC35*I35,2) -> 0 | HA35: 0 | HB35: 0 | HC35: =GV35*GW35 -> 0 | HE35: 3 | HF35: 1,2 | HS35: 0 | IK35: 0
A36: 17 | B36: 1 | C36: =ROW(SmtRes!A24) -> 24 | D36: =ROW(EtalonRes!A29) -> 29 | E36: 5 | F36: 4.11-12-1 | G36: Установка съемных и выдвижных блоков (модулей, ячеек, ТЭЗ) массой до 5 кг | H36: 1 ШТ. | I36: 1 | J36: 0 | K36: 1 | O36: =ROUND(CP36,2) -> 14 | P36: =ROUND((ROUND((AC36*AW36*I36),2)*BC36),2) -> 0 | Q36: =(ROUND((ROUND((((ET36*1.1))*AV36*I36),2)*BB36),2)+ROUND((ROUND(((AE36-((EU36*1.1)))*AV36*I36),2)*BS36),2)) -> 0.58 | R36: =(ROUND((ROUND((((EU36*1.1))*AV36*I36),2)*BS36),2)+ROUND((ROUND(((AE36-((EU36*1.1)))*AV36*I36),2)*BS36),2)) -> 0.09 | S36: =ROUND((ROUND((AF36*AV36*I36),2)*BA36),2) -> 13.42 | T36: =ROUND(CU36*I36,2) -> 0 | U36: =CV36*I36 -> 1.186251 | V36: =CW36*I36 -> 0 | W36: =ROUND(CX36*I36,2) -> 0 | X36: =(ROUND((((S36+ROUND((ROUND((((EU36*1.1))*AV36*I36),2)*BS36),2))*AT36)/100),2)+ROUND(((ROUND((ROUND(((AE36-((EU36*1.1)))*AV36*I36),2)*BS36),2)*AT36)/100),2)) -> 12.16 | Y36: =(ROUND((((S36+ROUND((ROUND((((EU36*1.1))*AV36*I36),2)*BS36),2))*AU36)/100),2)+ROUND(((ROUND((ROUND(((AE36-((EU36*1.1)))*AV36*I36),2)*BS36),2)*AU36)/100),2)) -> 6.21 | AA36: 60256405 | AB36: =ROUND((AC36+AD36+AF36),6) -> 13.365 | AC36: =ROUND(((ES36*1)),6) -> 0 | AD36: =ROUND(((((ET36*1.1))-((EU36*1.1)))+AE36),6) -> 0.55 | AE36: =ROUND(((EU36*1.1)),6) -> 0.088 | AF36: =ROUND(((EV36*1.1)),6) -> 12.815 | AG36: =ROUND((AP36),6) -> 0 | AH36: =((EW36*1.1)) -> 1.133 | AI36: =((EX36*1.1)) -> 0 | AJ36: =(AS36) -> 0 | AK36: 12.15 | AL36: 0 | AM36: 0.5 | AN36: 0.08 | AO36: 11.65 | AP36: 0 | AQ36: 1.03 | AR36: 0 | AS36: 0 | AT36: 90 | AU36: 46 | AV36: 1.047 | AW36: 1 | AZ36: 1 | BA36: 1 | BB36: 1 | BC36: 1 | BH36: 0 | BI36: 2 | BJ36: ТСН-2001.4 Доп. 68, Сб. 11, т. 12, поз. 1 | BM36: 72 | BN36: 58973116 | BO36: 4.11-12-1 | BP36: 1 | BQ36: 40 | BR36: 0 | BS36: 1 | BT36: 1 | BU36: 1 | BV36: 1 | BW36: 1 | BX36: 1 | BZ36: 90 | CA36: 46 | CE36: 1566 | CF36: 0 | CG36: 0 | CM36: 0 | CN36: Поправка: Гл.12.Прил.8.п.8. 5_12.00.01.11.003 Наименование: При наличии усложненных условий производства работ (стесненность, сложность складирования и транспортной логистики, наличие в зоне производства работ действующего технологического оборудования или движения технологического транспорта и т.п.) для объектов, расположенных за пределами территории круговой магистральной системы улиц "Садовое кольцо" и за пределами Третьего транспортного кольца города Москвы пунктов "а" и "б", но в пределах Московской кольцевой автомобильной дороги | CO36: 0 | CP36: =(P36+Q36+S36) -> 14 | CQ36: =ROUND((ROUND((AC36*AW36*1),2)*BC36),2) -> 0 | CR36: =(ROUND((ROUND((((ET36*1.1))*AV36*1),2)*BB36),2)+ROUND((ROUND(((AE36-((EU36*1.1)))*AV36*1),2)*BS36),2)) -> 0.58 | CS36: =(ROUND((ROUND((((EU36*1.1))*AV36*1),2)*BS36),2)+ROUND((ROUND(((AE36-((EU36*1.1)))*AV36*1),2)*BS36),2)) -> 0.09 | CT36: =ROUND((ROUND((AF36*AV36*1),2)*BA36),2) -> 13.42 | CU36: =AG36 -> 0 | CV36: =(AH36*AV36) -> 1.186251 | CW36: =AI36 -> 0 | CX36: =AJ36 -> 0 | CY36: =(ROUND((((S36+ROUND((ROUND((((EU36*1.1))*AV36*1),2)*BS36),2))*AT36)/100),2)+ROUND(((ROUND((ROUND(((AE36-((EU36*1.1)))*AV36*1),2)*BS36),2)*AT36)/100),2)) -> 12.16 | CZ36: =(ROUND((((S36+ROUND((ROUND((((EU36*1.1))*AV36*1),2)*BS36),2))*AU36)/100),2)+ROUND(((ROUND((ROUND(((AE36-((EU36*1.1)))*AV36*1),2)*BS36),2)*AU36)/100),2)) -> 6.21 | DB36: 5 | DD36: *1 | DE36: *1,1 | DF36: *1,1 | DG36: *1,1 | DI36: *1,1 | DJ36: *1,1 | DN36: 0 | DO36: 0 | DP36: 1 | DQ36: 1 | DU36: 1013 | DV36: 1 ШТ. | DW36: 1 ШТ. | DX36: 1 | EE36: 60088536 | EF36: 40 | EG36: Монтаж оборудования | EH36: 0 | EJ36: 2 | EK36: 72 | EL36: ТСН-2001.4-11. Приборы и средства автоматизации и вычислительной техники | EM36: ТСН-2001.4-11-1 | EO36: Поправка: Гл.12.Прил.8.п.8. 5_12.00.01.11.003 | EQ36: 0 | ER36: 12.15 | ES36: 0 | ET36: 0.5 | EU36: 0.08 | EV36: 11.65 | EW36: 1.03 | EX36: 0 | EY36: 0 | FQ36: 0 | FR36: 0 | FS36: 0 | FX36: 90 | FY36: 46 | GD36: 1 | GF36: 1708693888 | GG36: 2 | GH36: 1 | GI36: 2 | GJ36: 0 | GK36: 0 | GL36: =ROUND(IF(AND(BH36=3,BI36=3,FS36<>0),P36,0),2) -> 0 | GM36: =ROUND(O36+X36+Y36,2)+GX36 -> 32.37 | GN36: =IF(OR(BI36=0,BI36=1),GM36-GX36,0) -> 0 | GO36: =IF(BI36=2,GM36-GX36,0) -> 32.37 | GP36: =IF(BI36=4,GM36-GX36,0) -> 0 | GR36: 0 | GS36: 3 | GT36: 0 | GV36: =ROUND((GT36),6) -> 0 | GW36: 1 | GX36: =ROUND(HC36*I36,2) -> 0 | HA36: 0 | HB36: 0 | HC36: =GV36*GW36 -> 0 | HS36: 0 | IK36: 0
A37: 17 | B37: 1 | C37: =ROW(SmtRes!A26) -> 26 | D37: =ROW(EtalonRes!A32) -> 32 | E37: 5 | F37: 4.11-12-1 | G37: Установка съемных и выдвижных блоков (модулей, ячеек, ТЭЗ) массой до 5 кг | H37: 1 ШТ. | I37: 1 | J37: 0 | K37: 1 | O37: =ROUND(CP37,2) -> 747.4 | P37: =ROUND((ROUND((AC37*AW37*I37),2)*BC37),2) -> 0 | Q37: =(ROUND((ROUND((((ET37*1.1))*AV37*I37),2)*BB37),2)+ROUND((ROUND(((AE37-((EU37*1.1)))*AV37*I37),2)*BS37),2)) -> 9.43 | R37: =(ROUND((ROUND((((EU37*1.1))*AV37*I37),2)*BS37),2)+ROUND((ROUND(((AE37-((EU37*1.1)))*AV37*I37),2)*BS37),2)) -> 4.95 | S37: =ROUND((ROUND((AF37*AV37*I37),2)*BA37),2) -> 737.97 | T37: =ROUND(CU37*I37,2) -> 0 | U37: =CV37*I37 -> 1.186251 | V37: =CW37*I37 -> 0 | W37: =ROUND(CX37*I37,2) -> 0 | X37: =(ROUND((((S37+ROUND((ROUND((((EU37*1.1))*AV37*I37),2)*BS37),2))*AT37)/100),2)+ROUND(((ROUND((ROUND(((AE37-((EU37*1.1)))*AV37*I37),2)*BS37),2)*AT37)/100),2)) -> 668.63 | Y37: =(ROUND((((S37+ROUND((ROUND((((EU37*1.1))*AV37*I37),2)*BS37),2))*AU37)/100),2)+ROUND(((ROUND((ROUND(((AE37-((EU37*1.1)))*AV37*I37),2)*BS37),2)*AU37)/100),2)) -> 341.74 | AA37: 60256402 | AB37: =ROUND((AC37+AD37+AF37),6) -> 13.365 | AC37: =ROUND(((ES37*1)),6) -> 0 | AD37: =ROUND(((((ET37*1.1))-((EU37*1.1)))+AE37),6) -> 0.55 | AE37: =ROUND(((EU37*1.1)),6) -> 0.088 | AF37: =ROUND(((EV37*1.1)),6) -> 12.815 | AG37: =ROUND((AP37),6) -> 0 | AH37: =((EW37*1.1)) -> 1.133 | AI37: =((EX37*1.1)) -> 0 | AJ37: =(AS37) -> 0 | AK37: 12.15 | AL37: 0 | AM37: 0.5 | AN37: 0.08 | AO37: 11.65 | AP37: 0 | AQ37: 1.03 | AR37: 0 | AS37: 0 | AT37: 90 | AU37: 46 | AV37: 1.047 | AW37: 1 | AZ37: 1 | BA37: 54.99 | BB37: 16.26 | BC37: 1 | BH37: 0 | BI37: 2 | BJ37: ТСН-2001.4 Доп. 68, Сб. 11, т. 12, поз. 1 | BM37: 72 | BN37: 58973116 | BO37: 4.11-12-1 | BP37: 1 | BQ37: 40 | BR37: 0 | BS37: 54.99 | BT37: 1 | BU37: 1 | BV37: 1 | BW37: 1 | BX37: 1 | BZ37: 90 | CA37: 46 | CE37: 1566 | CF37: 0 | CG37: 0 | CM37: 0 | CN37: Поправка: Гл.12.Прил.8.п.8. 5_12.00.01.11.003 Наименование: При наличии усложненных условий производства работ (стесненность, сложность складирования и транспортной логистики, наличие в зоне производства работ действующего технологического оборудования или движения технологического транспорта и т.п.) для объектов, расположенных за пределами территории круговой магистральной системы улиц "Садовое кольцо" и за пределами Третьего транспортного кольца города Москвы пунктов "а" и "б", но в пределах Московской кольцевой автомобильной дороги | CO37: 0 | CP37: =(P37+Q37+S37) -> 747.4 | CQ37: =ROUND((ROUND((AC37*AW37*1),2)*BC37),2) -> 0 | CR37: =(ROUND((ROUND((((ET37*1.1))*AV37*1),2)*BB37),2)+ROUND((ROUND(((AE37-((EU37*1.1)))*AV37*1),2)*BS37),2)) -> 9.43 | CS37: =(ROUND((ROUND((((EU37*1.1))*AV37*1),2)*BS37),2)+ROUND((ROUND(((AE37-((EU37*1.1)))*AV37*1),2)*BS37),2)) -> 4.95 | CT37: =ROUND((ROUND((AF37*AV37*1),2)*BA37),2) -> 737.97 | CU37: =AG37 -> 0 | CV37: =(AH37*AV37) -> 1.186251 | CW37: =AI37 -> 0 | CX37: =AJ37 -> 0 | CY37: =(ROUND((((S37+ROUND((ROUND((((EU37*1.1))*AV37*1),2)*BS37),2))*AT37)/100),2)+ROUND(((ROUND((ROUND(((AE37-((EU37*1.1)))*AV37*1),2)*BS37),2)*AT37)/100),2)) -> 668.63 | CZ37: =(ROUND((((S37+ROUND((ROUND((((EU37*1.1))*AV37*1),2)*BS37),2))*AU37)/100),2)+ROUND(((ROUND((ROUND(((AE37-((EU37*1.1)))*AV37*1),2)*BS37),2)*AU37)/100),2)) -> 341.74 | DB37: 6 | DD37: *1 | DE37: *1,1 | DF37: *1,1 | DG37: *1,1 | DI37: *1,1 | DJ37: *1,1 | DN37: 0 | DO37: 0 | DP37: 1 | DQ37: 1 | DU37: 1013 | DV37: 1 ШТ. | DW37: 1 ШТ. | DX37: 1 | EE37: 60088536 | EF37: 40 | EG37: Монтаж оборудования | EH37: 0 | EJ37: 2 | EK37: 72 | EL37: ТСН-2001.4-11. Приборы и средства автоматизации и вычислительной техники | EM37: ТСН-2001.4-11-1 | EO37: Поправка: Гл.12.Прил.8.п.8. 5_12.00.01.11.003 | EQ37: 0 | ER37: 12.15 | ES37: 0 | ET37: 0.5 | EU37: 0.08 | EV37: 11.65 | EW37: 1.03 | EX37: 0 | EY37: 0 | FQ37: 0 | FR37: 0 | FS37: 0 | FX37: 90 | FY37: 46 | GD37: 1 | GF37: 1708693888 | GG37: 2 | GH37: 1 | GI37: 2 | GJ37: 0 | GK37: 0 | GL37: =ROUND(IF(AND(BH37=3,BI37=3,FS37<>0),P37,0),2) -> 0 | GM37: =ROUND(O37+X37+Y37,2)+GX37 -> 1757.77 | GN37: =IF(OR(BI37=0,BI37=1),GM37-GX37,0) -> 0 | GO37: =IF(BI37=2,GM37-GX37,0) -> 1757.77 | GP37: =IF(BI37=4,GM37-GX37,0) -> 0 | GR37: 0 | GS37: 3 | GT37: 0 | GV37: =ROUND((GT37),6) -> 0 | GW37: 1 | GX37: =ROUND(HC37*I37,2) -> 0 | HA37: 0 | HB37: 0 | HC37: =GV37*GW37 -> 0 | HS37: 0 | IK37: 0
A38: 17 | B38: 1 | E38: 6 | F38: КА-3 | G38: Конвертер DAP-IP для объединения приборов Sonar SPM в сеть Ethernet Sonar SNCA-8002 | H38: шт. | I38: 1 | J38: 0 | K38: 1 | O38: =ROUND(CP38,2) -> 6860.61 | P38: =ROUND((ROUND((AC38*I38),2)*BC38),2) -> 6860.61 | Q38: =(ROUND((ROUND(((ET38)*AV38*I38),2)*BB38),2)+ROUND((ROUND(((AE38-(EU38))*AV38*I38),2)*BS38),2)) -> 0 | R38: =(ROUND((ROUND(((EU38)*AV38*I38),2)*BS38),2)+ROUND((ROUND(((AE38-(EU38))*AV38*I38),2)*BS38),2)) -> 0 | S38: =ROUND((ROUND((AF38*AV38*I38),2)*BA38),2) -> 0 | T38: =ROUND(CU38*I38,2) -> 0 | U38: =CV38*I38 -> 0 | V38: =CW38*I38 -> 0 | W38: =ROUND(CX38*I38,2) -> 0 | X38: =(ROUND((((S38+ROUND((ROUND(((EU38)*AV38*I38),2)*BS38),2))*AT38)/100),2)+ROUND(((ROUND((ROUND(((AE38-(EU38))*AV38*I38),2)*BS38),2)*AT38)/100),2)) -> 0 | Y38: =(ROUND((((S38+ROUND((ROUND(((EU38)*AV38*I38),2)*BS38),2))*AU38)/100),2)+ROUND(((ROUND((ROUND(((AE38-(EU38))*AV38*I38),2)*BS38),2)*AU38)/100),2)) -> 0 | AA38: 60256405 | AB38: =ROUND((AC38+AD38+AF38),6) -> 6860.61 | AC38: =ROUND((ES38),6) -> 6860.61 | AD38: =ROUND((((ET38)-(EU38))+AE38),6) -> 0 | AE38: =ROUND((EU38),6) -> 0 | AF38: =ROUND((EV38),6) -> 0 | AG38: =ROUND((AP38),6) -> 0 | AH38: =(EW38) -> 0 | AI38: =(EX38) -> 0 | AJ38: =(AS38) -> 0 | AK38: 6860.61 | AL38: 6860.61 | AM38: 0 | AN38: 0 | AO38: 0 | AP38: 0 | AQ38: 0 | AR38: 0 | AS38: 0 | AT38: 0 | AU38: 0 | AV38: 1 | AW38: 1 | AZ38: 1 | BA38: 1 | BB38: 1 | BC38: 1 | BH38: 3 | BI38: 3 | BM38: 746 | BN38: 0 | BP38: 0 | BQ38: 130 | BR38: 0 | BS38: 1 | BT38: 1 | BU38: 1 | BV38: 1 | BW38: 1 | BX38: 1 | BZ38: 0 | CA38: 0 | CE38: 1566 | CF38: 0 | CG38: 0 | CM38: 0 | CO38: 0 | CP38: =(P38+Q38+S38) -> 6860.61 | CQ38: =ROUND((ROUND((AC38*1),2)*BC38),2) -> 6860.61 | CR38: =(ROUND((ROUND(((ET38)*AV38*1),2)*BB38),2)+ROUND((ROUND(((AE38-(EU38))*AV38*1),2)*BS38),2)) -> 0 | CS38: =(ROUND((ROUND(((EU38)*AV38*1),2)*BS38),2)+ROUND((ROUND(((AE38-(EU38))*AV38*1),2)*BS38),2)) -> 0 | CT38: =ROUND((ROUND((AF38*AV38*1),2)*BA38),2) -> 0 | CU38: =AG38 -> 0 | CV38: =(AH38*AV38) -> 0 | CW38: =AI38 -> 0 | CX38: =AJ38 -> 0 | CY38: =(ROUND((((S38+ROUND((ROUND(((EU38)*AV38*1),2)*BS38),2))*AT38)/100),2)+ROUND(((ROUND((ROUND(((AE38-(EU38))*AV38*1),2)*BS38),2)*AT38)/100),2)) -> 0 | CZ38: =(ROUND((((S38+ROUND((ROUND(((EU38)*AV38*1),2)*BS38),2))*AU38)/100),2)+ROUND(((ROUND((ROUND(((AE38-(EU38))*AV38*1),2)*BS38),2)*AU38)/100),2)) -> 0 | DN38: 0 | DO38: 0 | DP38: 1 | DQ38: 1 | DU38: 1010 | DV38: шт. | DW38: шт. | DX38: 1 | EE38: 60088638 | EF38: 130 | EG38: Сметная стоимость оборудования | EH38: 0 | EJ38: 3 | EK38: 746 | EL38: ТСН-2001.13. Сметная стоимость оборудования | EM38: ТСН-2001.13 | EQ38: 0 | ER38: 0 | ES38: 6860.61 | ET38: 0 | EU38: 0 | EV38: 0 | EW38: 0 | EX38: 0 | EY38: 0 | FQ38: 0 | FR38: =P38 -> 6860.61 | FS38: 0 | FX38: 0 | FY38: 0 | GA38: [60 500 / 1,2 / 7,66] + 3% Трансп + 1,2% Заг.скл | GD38: 1 | GF38: 831235936 | GG38: 2 | GH38: 4 | GI38: -2 | GJ38: 0 | GK38: 0 | GL38: =ROUND(IF(AND(BH38=3,BI38=3,FS38<>0),P38,0),2) -> 0 | GM38: =ROUND(O38+X38+Y38,2)+GX38 -> 6860.61 | GN38: =IF(OR(BI38=0,BI38=1),GM38-GX38,0) -> 0 | GO38: =IF(BI38=2,GM38-GX38,0) -> 0 | GP38: =IF(BI38=4,GM38-GX38,0) -> 0 | GR38: 0 | GS38: 2 | GT38: 0 | GV38: =ROUND((GT38),6) -> 0 | GW38: 1 | GX38: =ROUND(HC38*I38,2) -> 0 | HA38: 0 | HB38: 0 | HC38: =GV38*GW38 -> 0 | HE38: 3 | HF38: 1,2 | HS38: 0 | IK38: 0
A39: 17 | B39: 1 | E39: 6 | F39: КА-3 | G39: Конвертер DAP-IP для объединения приборов Sonar SPM в сеть Ethernet Sonar SNCA-8002 | H39: шт. | I39: 1 | J39: 0 | K39: 1 | O39: =ROUND(CP39,2) -> 52552.27 | P39: =ROUND((ROUND((AC39*I39),2)*BC39),2) -> 52552.27 | Q39: =(ROUND((ROUND(((ET39)*AV39*I39),2)*BB39),2)+ROUND((ROUND(((AE39-(EU39))*AV39*I39),2)*BS39),2)) -> 0 | R39: =(ROUND((ROUND(((EU39)*AV39*I39),2)*BS39),2)+ROUND((ROUND(((AE39-(EU39))*AV39*I39),2)*BS39),2)) -> 0 | S39: =ROUND((ROUND((AF39*AV39*I39),2)*BA39),2) -> 0 | T39: =ROUND(CU39*I39,2) -> 0 | U39: =CV39*I39 -> 0 | V39: =CW39*I39 -> 0 | W39: =ROUND(CX39*I39,2) -> 0 | X39: =(ROUND((((S39+ROUND((ROUND(((EU39)*AV39*I39),2)*BS39),2))*AT39)/100),2)+ROUND(((ROUND((ROUND(((AE39-(EU39))*AV39*I39),2)*BS39),2)*AT39)/100),2)) -> 0 | Y39: =(ROUND((((S39+ROUND((ROUND(((EU39)*AV39*I39),2)*BS39),2))*AU39)/100),2)+ROUND(((ROUND((ROUND(((AE39-(EU39))*AV39*I39),2)*BS39),2)*AU39)/100),2)) -> 0 | AA39: 60256402 | AB39: =ROUND((AC39+AD39+AF39),6) -> 6860.61 | AC39: =ROUND((ES39),6) -> 6860.61 | AD39: =ROUND((((ET39)-(EU39))+AE39),6) -> 0 | AE39: =ROUND((EU39),6) -> 0 | AF39: =ROUND((EV39),6) -> 0 | AG39: =ROUND((AP39),6) -> 0 | AH39: =(EW39) -> 0 | AI39: =(EX39) -> 0 | AJ39: =(AS39) -> 0 | AK39: 6860.61 | AL39: 6860.61 | AM39: 0 | AN39: 0 | AO39: 0 | AP39: 0 | AQ39: 0 | AR39: 0 | AS39: 0 | AT39: 0 | AU39: 0 | AV39: 1 | AW39: 1 | AZ39: 1 | BA39: 1 | BB39: 1 | BC39: 7.66 | BH39: 3 | BI39: 3 | BM39: 746 | BN39: 0 | BP39: 0 | BQ39: 130 | BR39: 0 | BS39: 1 | BT39: 1 | BU39: 1 | BV39: 1 | BW39: 1 | BX39: 1 | BZ39: 0 | CA39: 0 | CE39: 1566 | CF39: 0 | CG39: 0 | CM39: 0 | CO39: 0 | CP39: =(P39+Q39+S39) -> 52552.27 | CQ39: =ROUND((ROUND((AC39*1),2)*BC39),2) -> 52552.27 | CR39: =(ROUND((ROUND(((ET39)*AV39*1),2)*BB39),2)+ROUND((ROUND(((AE39-(EU39))*AV39*1),2)*BS39),2)) -> 0 | CS39: =(ROUND((ROUND(((EU39)*AV39*1),2)*BS39),2)+ROUND((ROUND(((AE39-(EU39))*AV39*1),2)*BS39),2)) -> 0 | CT39: =ROUND((ROUND((AF39*AV39*1),2)*BA39),2) -> 0 | CU39: =AG39 -> 0 | CV39: =(AH39*AV39) -> 0 | CW39: =AI39 -> 0 | CX39: =AJ39 -> 0 | CY39: =(ROUND((((S39+ROUND((ROUND(((EU39)*AV39*1),2)*BS39),2))*AT39)/100),2)+ROUND(((ROUND((ROUND(((AE39-(EU39))*AV39*1),2)*BS39),2)*AT39)/100),2)) -> 0 | CZ39: =(ROUND((((S39+ROUND((ROUND(((EU39)*AV39*1),2)*BS39),2))*AU39)/100),2)+ROUND(((ROUND((ROUND(((AE39-(EU39))*AV39*1),2)*BS39),2)*AU39)/100),2)) -> 0 | DN39: 0 | DO39: 0 | DP39: 1 | DQ39: 1 | DU39: 1010 | DV39: шт. | DW39: шт. | DX39: 1 | EE39: 60088638 | EF39: 130 | EG39: Сметная стоимость оборудования | EH39: 0 | EJ39: 3 | EK39: 746 | EL39: ТСН-2001.13. Сметная стоимость оборудования | EM39: ТСН-2001.13 | EQ39: 0 | ER39: 6860.61 | ES39: 6860.61 | ET39: 0 | EU39: 0 | EV39: 0 | EW39: 0 | EX39: 0 | EY39: 0 | EZ39: 5 | FC39: 1 | FD39: 18 | FF39: 60500 | FQ39: 0 | FR39: =P39 -> 52552.27 | FS39: 0 | FX39: 0 | FY39: 0 | GA39: [60 500 / 1,2 / 7,66] + 3% Трансп + 1,2% Заг.скл | GD39: 1 | GF39: 831235936 | GG39: 2 | GH39: 3 | GI39: 5 | GJ39: 0 | GK39: 0 | GL39: =ROUND(IF(AND(BH39=3,BI39=3,FS39<>0),P39,0),2) -> 0 | GM39: =ROUND(O39+X39+Y39,2)+GX39 -> 52552.27 | GN39: =IF(OR(BI39=0,BI39=1),GM39-GX39,0) -> 0 | GO39: =IF(BI39=2,GM39-GX39,0) -> 0 | GP39: =IF(BI39=4,GM39-GX39,0) -> 0 | GR39: 1 | GS39: 1 | GT39: 0 | GV39: =ROUND((GT39),6) -> 0 | GW39: 1 | GX39: =ROUND(HC39*I39,2) -> 0 | HA39: 0 | HB39: 0 | HC39: =GV39*GW39 -> 0 | HE39: 3 | HF39: 1,2 | HS39: 0 | IK39: 0
A40: 17 | B40: 1 | C40: =ROW(SmtRes!A28) -> 28 | D40: =ROW(EtalonRes!A35) -> 35 | E40: 7 | F40: 4.11-12-1 | G40: Установка съемных и выдвижных блоков (модулей, ячеек, ТЭЗ) массой до 5 кг | H40: 1 ШТ. | I40: 1 | J40: 0 | K40: 1 | O40: =ROUND(CP40,2) -> 14 | P40: =ROUND((ROUND((AC40*AW40*I40),2)*BC40),2) -> 0 | Q40: =(ROUND((ROUND((((ET40*1.1))*AV40*I40),2)*BB40),2)+ROUND((ROUND(((AE40-((EU40*1.1)))*AV40*I40),2)*BS40),2)) -> 0.58 | R40: =(ROUND((ROUND((((EU40*1.1))*AV40*I40),2)*BS40),2)+ROUND((ROUND(((AE40-((EU40*1.1)))*AV40*I40),2)*BS40),2)) -> 0.09 | S40: =ROUND((ROUND((AF40*AV40*I40),2)*BA40),2) -> 13.42 | T40: =ROUND(CU40*I40,2) -> 0 | U40: =CV40*I40 -> 1.186251 | V40: =CW40*I40 -> 0 | W40: =ROUND(CX40*I40,2) -> 0 | X40: =(ROUND((((S40+ROUND((ROUND((((EU40*1.1))*AV40*I40),2)*BS40),2))*AT40)/100),2)+ROUND(((ROUND((ROUND(((AE40-((EU40*1.1)))*AV40*I40),2)*BS40),2)*AT40)/100),2)) -> 12.16 | Y40: =(ROUND((((S40+ROUND((ROUND((((EU40*1.1))*AV40*I40),2)*BS40),2))*AU40)/100),2)+ROUND(((ROUND((ROUND(((AE40-((EU40*1.1)))*AV40*I40),2)*BS40),2)*AU40)/100),2)) -> 6.21 | AA40: 60256405 | AB40: =ROUND((AC40+AD40+AF40),6) -> 13.365 | AC40: =ROUND(((ES40*1)),6) -> 0 | AD40: =ROUND(((((ET40*1.1))-((EU40*1.1)))+AE40),6) -> 0.55 | AE40: =ROUND(((EU40*1.1)),6) -> 0.088 | AF40: =ROUND(((EV40*1.1)),6) -> 12.815 | AG40: =ROUND((AP40),6) -> 0 | AH40: =((EW40*1.1)) -> 1.133 | AI40: =((EX40*1.1)) -> 0 | AJ40: =(AS40) -> 0 | AK40: 12.15 | AL40: 0 | AM40: 0.5 | AN40: 0.08 | AO40: 11.65 | AP40: 0 | AQ40: 1.03 | AR40: 0 | AS40: 0 | AT40: 90 | AU40: 46 | AV40: 1.047 | AW40: 1 | AZ40: 1 | BA40: 1 | BB40: 1 | BC40: 1 | BH40: 0 | BI40: 2 | BJ40: ТСН-2001.4 Доп. 68, Сб. 11, т. 12, поз. 1 | BM40: 72 | BN40: 58973116 | BO40: 4.11-12-1 | BP40: 1 | BQ40: 40 | BR40: 0 | BS40: 1 | BT40: 1 | BU40: 1 | BV40: 1 | BW40: 1 | BX40: 1 | BZ40: 90 | CA40: 46 | CE40: 1566 | CF40: 0 | CG40: 0 | CM40: 0 | CN40: Поправка: Гл.12.Прил.8.п.8. 5_12.00.01.11.003 Наименование: При наличии усложненных условий производства работ (стесненность, сложность складирования и транспортной логистики, наличие в зоне производства работ действующего технологического оборудования или движения технологического транспорта и т.п.) для объектов, расположенных за пределами территории круговой магистральной системы улиц "Садовое кольцо" и за пределами Третьего транспортного кольца города Москвы пунктов "а" и "б", но в пределах Московской кольцевой автомобильной дороги | CO40: 0 | CP40: =(P40+Q40+S40) -> 14 | CQ40: =ROUND((ROUND((AC40*AW40*1),2)*BC40),2) -> 0 | CR40: =(ROUND((ROUND((((ET40*1.1))*AV40*1),2)*BB40),2)+ROUND((ROUND(((AE40-((EU40*1.1)))*AV40*1),2)*BS40),2)) -> 0.58 | CS40: =(ROUND((ROUND((((EU40*1.1))*AV40*1),2)*BS40),2)+ROUND((ROUND(((AE40-((EU40*1.1)))*AV40*1),2)*BS40),2)) -> 0.09 | CT40: =ROUND((ROUND((AF40*AV40*1),2)*BA40),2) -> 13.42 | CU40: =AG40 -> 0 | CV40: =(AH40*AV40) -> 1.186251 | CW40: =AI40 -> 0 | CX40: =AJ40 -> 0 | CY40: =(ROUND((((S40+ROUND((ROUND((((EU40*1.1))*AV40*1),2)*BS40),2))*AT40)/100),2)+ROUND(((ROUND((ROUND(((AE40-((EU40*1.1)))*AV40*1),2)*BS40),2)*AT40)/100),2)) -> 12.16 | CZ40: =(ROUND((((S40+ROUND((ROUND((((EU40*1.1))*AV40*1),2)*BS40),2))*AU40)/100),2)+ROUND(((ROUND((ROUND(((AE40-((EU40*1.1)))*AV40*1),2)*BS40),2)*AU40)/100),2)) -> 6.21 | DB40: 7 | DD40: *1 | DE40: *1,1 | DF40: *1,1 | DG40: *1,1 | DI40: *1,1 | DJ40: *1,1 | DN40: 0 | DO40: 0 | DP40: 1 | DQ40: 1 | DU40: 1013 | DV40: 1 ШТ. | DW40: 1 ШТ. | DX40: 1 | EE40: 60088536 | EF40: 40 | EG40: Монтаж оборудования | EH40: 0 | EJ40: 2 | EK40: 72 | EL40: ТСН-2001.4-11. Приборы и средства автоматизации и вычислительной техники | EM40: ТСН-2001.4-11-1 | EO40: Поправка: Гл.12.Прил.8.п.8. 5_12.00.01.11.003 | EQ40: 0 | ER40: 12.15 | ES40: 0 | ET40: 0.5 | EU40: 0.08 | EV40: 11.65 | EW40: 1.03 | EX40: 0 | EY40: 0 | FQ40: 0 | FR40: 0 | FS40: 0 | FX40: 90 | FY40: 46 | GD40: 1 | GF40: 1708693888 | GG40: 2 | GH40: 1 | GI40: 2 | GJ40: 0 | GK40: 0 | GL40: =ROUND(IF(AND(BH40=3,BI40=3,FS40<>0),P40,0),2) -> 0 | GM40: =ROUND(O40+X40+Y40,2)+GX40 -> 32.37 | GN40: =IF(OR(BI40=0,BI40=1),GM40-GX40,0) -> 0 | GO40: =IF(BI40=2,GM40-GX40,0) -> 32.37 | GP40: =IF(BI40=4,GM40-GX40,0) -> 0 | GR40: 0 | GS40: 3 | GT40: 0 | GV40: =ROUND((GT40),6) -> 0 | GW40: 1 | GX40: =ROUND(HC40*I40,2) -> 0 | HA40: 0 | HB40: 0 | HC40: =GV40*GW40 -> 0 | HS40: 0 | IK40: 0
A41: 17 | B41: 1 | C41: =ROW(SmtRes!A30) -> 30 | D41: =ROW(EtalonRes!A38) -> 38 | E41: 7 | F41: 4.11-12-1 | G41: Установка съемных и выдвижных блоков (модулей, ячеек, ТЭЗ) массой до 5 кг | H41: 1 ШТ. | I41: 1 | J41: 0 | K41: 1 | O41: =ROUND(CP41,2) -> 747.4 | P41: =ROUND((ROUND((AC41*AW41*I41),2)*BC41),2) -> 0 | Q41: =(ROUND((ROUND((((ET41*1.1))*AV41*I41),2)*BB41),2)+ROUND((ROUND(((AE41-((EU41*1.1)))*AV41*I41),2)*BS41),2)) -> 9.43 | R41: =(ROUND((ROUND((((EU41*1.1))*AV41*I41),2)*BS41),2)+ROUND((ROUND(((AE41-((EU41*1.1)))*AV41*I41),2)*BS41),2)) -> 4.95 | S41: =ROUND((ROUND((AF41*AV41*I41),2)*BA41),2) -> 737.97 | T41: =ROUND(CU41*I41,2) -> 0 | U41: =CV41*I41 -> 1.186251 | V41: =CW41*I41 -> 0 | W41: =ROUND(CX41*I41,2) -> 0 | X41: =(ROUND((((S41+ROUND((ROUND((((EU41*1.1))*AV41*I41),2)*BS41),2))*AT41)/100),2)+ROUND(((ROUND((ROUND(((AE41-((EU41*1.1)))*AV41*I41),2)*BS41),2)*AT41)/100),2)) -> 668.63 | Y41: =(ROUND((((S41+ROUND((ROUND((((EU41*1.1))*AV41*I41),2)*BS41),2))*AU41)/100),2)+ROUND(((ROUND((ROUND(((AE41-((EU41*1.1)))*AV41*I41),2)*BS41),2)*AU41)/100),2)) -> 341.74 | AA41: 60256402 | AB41: =ROUND((AC41+AD41+AF41),6) -> 13.365 | AC41: =ROUND(((ES41*1)),6) -> 0 | AD41: =ROUND(((((ET41*1.1))-((EU41*1.1)))+AE41),6) -> 0.55 | AE41: =ROUND(((EU41*1.1)),6) -> 0.088 | AF41: =ROUND(((EV41*1.1)),6) -> 12.815 | AG41: =ROUND((AP41),6) -> 0 | AH41: =((EW41*1.1)) -> 1.133 | AI41: =((EX41*1.1)) -> 0 | AJ41: =(AS41) -> 0 | AK41: 12.15 | AL41: 0 | AM41: 0.5 | AN41: 0.08 | AO41: 11.65 | AP41: 0 | AQ41: 1.03 | AR41: 0 | AS41: 0 | AT41: 90 | AU41: 46 | AV41: 1.047 | AW41: 1 | AZ41: 1 | BA41: 54.99 | BB41: 16.26 | BC41: 1 | BH41: 0 | BI41: 2 | BJ41: ТСН-2001.4 Доп. 68, Сб. 11, т. 12, поз. 1 | BM41: 72 | BN41: 58973116 | BO41: 4.11-12-1 | BP41: 1 | BQ41: 40 | BR41: 0 | BS41: 54.99 | BT41: 1 | BU41: 1 | BV41: 1 | BW41: 1 | BX41: 1 | BZ41: 90 | CA41: 46 | CE41: 1566 | CF41: 0 | CG41: 0 | CM41: 0 | CN41: Поправка: Гл.12.Прил.8.п.8. 5_12.00.01.11.003 Наименование: При наличии усложненных условий производства работ (стесненность, сложность складирования и транспортной логистики, наличие в зоне производства работ действующего технологического оборудования или движения технологического транспорта и т.п.) для объектов, расположенных за пределами территории круговой магистральной системы улиц "Садовое кольцо" и за пределами Третьего транспортного кольца города Москвы пунктов "а" и "б", но в пределах Московской кольцевой автомобильной дороги | CO41: 0 | CP41: =(P41+Q41+S41) -> 747.4 | CQ41: =ROUND((ROUND((AC41*AW41*1),2)*BC41),2) -> 0 | CR41: =(ROUND((ROUND((((ET41*1.1))*AV41*1),2)*BB41),2)+ROUND((ROUND(((AE41-((EU41*1.1)))*AV41*1),2)*BS41),2)) -> 9.43 | CS41: =(ROUND((ROUND((((EU41*1.1))*AV41*1),2)*BS41),2)+ROUND((ROUND(((AE41-((EU41*1.1)))*AV41*1),2)*BS41),2)) -> 4.95 | CT41: =ROUND((ROUND((AF41*AV41*1),2)*BA41),2) -> 737.97 | CU41: =AG41 -> 0 | CV41: =(AH41*AV41) -> 1.186251 | CW41: =AI41 -> 0 | CX41: =AJ41 -> 0 | CY41: =(ROUND((((S41+ROUND((ROUND((((EU41*1.1))*AV41*1),2)*BS41),2))*AT41)/100),2)+ROUND(((ROUND((ROUND(((AE41-((EU41*1.1)))*AV41*1),2)*BS41),2)*AT41)/100),2)) -> 668.63 | CZ41: =(ROUND((((S41+ROUND((ROUND((((EU41*1.1))*AV41*1),2)*BS41),2))*AU41)/100),2)+ROUND(((ROUND((ROUND(((AE41-((EU41*1.1)))*AV41*1),2)*BS41),2)*AU41)/100),2)) -> 341.74 | DB41: 8 | DD41: *1 | DE41: *1,1 | DF41: *1,1 | DG41: *1,1 | DI41: *1,1 | DJ41: *1,1 | DN41: 0 | DO41: 0 | DP41: 1 | DQ41: 1 | DU41: 1013 | DV41: 1 ШТ. | DW41: 1 ШТ. | DX41: 1 | EE41: 60088536 | EF41: 40 | EG41: Монтаж оборудования | EH41: 0 | EJ41: 2 | EK41: 72 | EL41: ТСН-2001.4-11. Приборы и средства автоматизации и вычислительной техники | EM41: ТСН-2001.4-11-1 | EO41: Поправка: Гл.12.Прил.8.п.8. 5_12.00.01.11.003 | EQ41: 0 | ER41: 12.15 | ES41: 0 | ET41: 0.5 | EU41: 0.08 | EV41: 11.65 | EW41: 1.03 | EX41: 0 | EY41: 0 | FQ41: 0 | FR41: 0 | FS41: 0 | FX41: 90 | FY41: 46 | GD41: 1 | GF41: 1708693888 | GG41: 2 | GH41: 1 | GI41: 2 | GJ41: 0 | GK41: 0 | GL41: =ROUND(IF(AND(BH41=3,BI41=3,FS41<>0),P41,0),2) -> 0 | GM41: =ROUND(O41+X41+Y41,2)+GX41 -> 1757.77 | GN41: =IF(OR(BI41=0,BI41=1),GM41-GX41,0) -> 0 | GO41: =IF(BI41=2,GM41-GX41,0) -> 1757.77 | GP41: =IF(BI41=4,GM41-GX41,0) -> 0 | GR41: 0 | GS41: 3 | GT41: 0 | GV41: =ROUND((GT41),6) -> 0 | GW41: 1 | GX41: =ROUND(HC41*I41,2) -> 0 | HA41: 0 | HB41: 0 | HC41: =GV41*GW41 -> 0 | HS41: 0 | IK41: 0
A42: 17 | B42: 1 | E42: 8 | F42: КА-4 | G42: Комплект программируемого таймера Sonar STM-1004+GPS-2500 комплект | H42: шт. | I42: 1 | J42: 0 | K42: 1 | O42: =ROUND(CP42,2) -> 8001.86 | P42: =ROUND((ROUND((AC42*I42),2)*BC42),2) -> 8001.86 | Q42: =(ROUND((ROUND(((ET42)*AV42*I42),2)*BB42),2)+ROUND((ROUND(((AE42-(EU42))*AV42*I42),2)*BS42),2)) -> 0 | R42: =(ROUND((ROUND(((EU42)*AV42*I42),2)*BS42),2)+ROUND((ROUND(((AE42-(EU42))*AV42*I42),2)*BS42),2)) -> 0 | S42: =ROUND((ROUND((AF42*AV42*I42),2)*BA42),2) -> 0 | T42: =ROUND(CU42*I42,2) -> 0 | U42: =CV42*I42 -> 0 | V42: =CW42*I42 -> 0 | W42: =ROUND(CX42*I42,2) -> 0 | X42: =(ROUND((((S42+ROUND((ROUND(((EU42)*AV42*I42),2)*BS42),2))*AT42)/100),2)+ROUND(((ROUND((ROUND(((AE42-(EU42))*AV42*I42),2)*BS42),2)*AT42)/100),2)) -> 0 | Y42: =(ROUND((((S42+ROUND((ROUND(((EU42)*AV42*I42),2)*BS42),2))*AU42)/100),2)+ROUND(((ROUND((ROUND(((AE42-(EU42))*AV42*I42),2)*BS42),2)*AU42)/100),2)) -> 0 | AA42: 60256405 | AB42: =ROUND((AC42+AD42+AF42),6) -> 8001.86 | AC42: =ROUND((ES42),6) -> 8001.86 | AD42: =ROUND((((ET42)-(EU42))+AE42),6) -> 0 | AE42: =ROUND((EU42),6) -> 0 | AF42: =ROUND((EV42),6) -> 0 | AG42: =ROUND((AP42),6) -> 0 | AH42: =(EW42) -> 0 | AI42: =(EX42) -> 0 | AJ42: =(AS42) -> 0 | AK42: 8001.86 | AL42: 8001.86 | AM42: 0 | AN42: 0 | AO42: 0 | AP42: 0 | AQ42: 0 | AR42: 0 | AS42: 0 | AT42: 0 | AU42: 0 | AV42: 1 | AW42: 1 | AZ42: 1 | BA42: 1 | BB42: 1 | BC42: 1 | BH42: 3 | BI42: 3 | BM42: 746 | BN42: 0 | BP42: 0 | BQ42: 130 | BR42: 0 | BS42: 1 | BT42: 1 | BU42: 1 | BV42: 1 | BW42: 1 | BX42: 1 | BZ42: 0 | CA42: 0 | CE42: 1566 | CF42: 0 | CG42: 0 | CM42: 0 | CO42: 0 | CP42: =(P42+Q42+S42) -> 8001.86 | CQ42: =ROUND((ROUND((AC42*1),2)*BC42),2) -> 8001.86 | CR42: =(ROUND((ROUND(((ET42)*AV42*1),2)*BB42),2)+ROUND((ROUND(((AE42-(EU42))*AV42*1),2)*BS42),2)) -> 0 | CS42: =(ROUND((ROUND(((EU42)*AV42*1),2)*BS42),2)+ROUND((ROUND(((AE42-(EU42))*AV42*1),2)*BS42),2)) -> 0 | CT42: =ROUND((ROUND((AF42*AV42*1),2)*BA42),2) -> 0 | CU42: =AG42 -> 0 | CV42: =(AH42*AV42) -> 0 | CW42: =AI42 -> 0 | CX42: =AJ42 -> 0 | CY42: =(ROUND((((S42+ROUND((ROUND(((EU42)*AV42*1),2)*BS42),2))*AT42)/100),2)+ROUND(((ROUND((ROUND(((AE42-(EU42))*AV42*1),2)*BS42),2)*AT42)/100),2)) -> 0 | CZ42: =(ROUND((((S42+ROUND((ROUND(((EU42)*AV42*1),2)*BS42),2))*AU42)/100),2)+ROUND(((ROUND((ROUND(((AE42-(EU42))*AV42*1),2)*BS42),2)*AU42)/100),2)) -> 0 | DN42: 0 | DO42: 0 | DP42: 1 | DQ42: 1 | DU42: 1010 | DV42: шт. | DW42: шт. | DX42: 1 | EE42: 60088638 | EF42: 130 | EG42: Сметная стоимость оборудования | EH42: 0 | EJ42: 3 | EK42: 746 | EL42: ТСН-2001.13. Сметная стоимость оборудования | EM42: ТСН-2001.13 | EQ42: 0 | ER42: 0 | ES42: 8001.86 | ET42: 0 | EU42: 0 | EV42: 0 | EW42: 0 | EX42: 0 | EY42: 0 | FQ42: 0 | FR42: =P42 -> 8001.86 | FS42: 0 | FX42: 0 | FY42: 0 | GA42: [70 564 / 1,2 / 7,66] + 3% Трансп + 1,2% Заг.скл | GD42: 1 | GF42: -909535778 | GG42: 2 | GH42: 4 | GI42: -2 | GJ42: 0 | GK42: 0 | GL42: =ROUND(IF(AND(BH42=3,BI42=3,FS42<>0),P42,0),2) -> 0 | GM42: =ROUND(O42+X42+Y42,2)+GX42 -> 8001.86 | GN42: =IF(OR(BI42=0,BI42=1),GM42-GX42,0) -> 0 | GO42: =IF(BI42=2,GM42-GX42,0) -> 0 | GP42: =IF(BI42=4,GM42-GX42,0) -> 0 | GR42: 0 | GS42: 2 | GT42: 0 | GV42: =ROUND((GT42),6) -> 0 | GW42: 1 | GX42: =ROUND(HC42*I42,2) -> 0 | HA42: 0 | HB42: 0 | HC42: =GV42*GW42 -> 0 | HE42: 3 | HF42: 1,2 | HS42: 0 | IK42: 0
A43: 17 | B43: 1 | E43: 8 | F43: КА-4 | G43: Комплект программируемого таймера Sonar STM-1004+GPS-2500 комплект | H43: шт. | I43: 1 | J43: 0 | K43: 1 | O43: =ROUND(CP43,2) -> 61294.25 | P43: =ROUND((ROUND((AC43*I43),2)*BC43),2) -> 61294.25 | Q43: =(ROUND((ROUND(((ET43)*AV43*I43),2)*BB43),2)+ROUND((ROUND(((AE43-(EU43))*AV43*I43),2)*BS43),2)) -> 0 | R43: =(ROUND((ROUND(((EU43)*AV43*I43),2)*BS43),2)+ROUND((ROUND(((AE43-(EU43))*AV43*I43),2)*BS43),2)) -> 0 | S43: =ROUND((ROUND((AF43*AV43*I43),2)*BA43),2) -> 0 | T43: =ROUND(CU43*I43,2) -> 0 | U43: =CV43*I43 -> 0 | V43: =CW43*I43 -> 0 | W43: =ROUND(CX43*I43,2) -> 0 | X43: =(ROUND((((S43+ROUND((ROUND(((EU43)*AV43*I43),2)*BS43),2))*AT43)/100),2)+ROUND(((ROUND((ROUND(((AE43-(EU43))*AV43*I43),2)*BS43),2)*AT43)/100),2)) -> 0 | Y43: =(ROUND((((S43+ROUND((ROUND(((EU43)*AV43*I43),2)*BS43),2))*AU43)/100),2)+ROUND(((ROUND((ROUND(((AE43-(EU43))*AV43*I43),2)*BS43),2)*AU43)/100),2)) -> 0 | AA43: 60256402 | AB43: =ROUND((AC43+AD43+AF43),6) -> 8001.86 | AC43: =ROUND((ES43),6) -> 8001.86 | AD43: =ROUND((((ET43)-(EU43))+AE43),6) -> 0 | AE43: =ROUND((EU43),6) -> 0 | AF43: =ROUND((EV43),6) -> 0 | AG43: =ROUND((AP43),6) -> 0 | AH43: =(EW43) -> 0 | AI43: =(EX43) -> 0 | AJ43: =(AS43) -> 0 | AK43: 8001.86 | AL43: 8001.86 | AM43: 0 | AN43: 0 | AO43: 0 | AP43: 0 | AQ43: 0 | AR43: 0 | AS43: 0 | AT43: 0 | AU43: 0 | AV43: 1 | AW43: 1 | AZ43: 1 | BA43: 1 | BB43: 1 | BC43: 7.66 | BH43: 3 | BI43: 3 | BM43: 746 | BN43: 0 | BP43: 0 | BQ43: 130 | BR43: 0 | BS43: 1 | BT43: 1 | BU43: 1 | BV43: 1 | BW43: 1 | BX43: 1 | BZ43: 0 | CA43: 0 | CE43: 1566 | CF43: 0 | CG43: 0 | CM43: 0 | CO43: 0 | CP43: =(P43+Q43+S43) -> 61294.25 | CQ43: =ROUND((ROUND((AC43*1),2)*BC43),2) -> 61294.25 | CR43: =(ROUND((ROUND(((ET43)*AV43*1),2)*BB43),2)+ROUND((ROUND(((AE43-(EU43))*AV43*1),2)*BS43),2)) -> 0 | CS43: =(ROUND((ROUND(((EU43)*AV43*1),2)*BS43),2)+ROUND((ROUND(((AE43-(EU43))*AV43*1),2)*BS43),2)) -> 0 | CT43: =ROUND((ROUND((AF43*AV43*1),2)*BA43),2) -> 0 | CU43: =AG43 -> 0 | CV43: =(AH43*AV43) -> 0 | CW43: =AI43 -> 0 | CX43: =AJ43 -> 0 | CY43: =(ROUND((((S43+ROUND((ROUND(((EU43)*AV43*1),2)*BS43),2))*AT43)/100),2)+ROUND(((ROUND((ROUND(((AE43-(EU43))*AV43*1),2)*BS43),2)*AT43)/100),2)) -> 0 | CZ43: =(ROUND((((S43+ROUND((ROUND(((EU43)*AV43*1),2)*BS43),2))*AU43)/100),2)+ROUND(((ROUND((ROUND(((AE43-(EU43))*AV43*1),2)*BS43),2)*AU43)/100),2)) -> 0 | DN43: 0 | DO43: 0 | DP43: 1 | DQ43: 1 | DU43: 1010 | DV43: шт. | DW43: шт. | DX43: 1 | EE43: 60088638 | EF43: 130 | EG43: Сметная стоимость оборудования | EH43: 0 | EJ43: 3 | EK43: 746 | EL43: ТСН-2001.13. Сметная стоимость оборудования | EM43: ТСН-2001.13 | EQ43: 0 | ER43: 8001.86 | ES43: 8001.86 | ET43: 0 | EU43: 0 | EV43: 0 | EW43: 0 | EX43: 0 | EY43: 0 | EZ43: 5 | FC43: 1 | FD43: 18 | FF43: 70564 | FQ43: 0 | FR43: =P43 -> 61294.25 | FS43: 0 | FX43: 0 | FY43: 0 | GA43: [70 564 / 1,2 / 7,66] + 3% Трансп + 1,2% Заг.скл | GD43: 1 | GF43: -909535778 | GG43: 2 | GH43: 3 | GI43: 5 | GJ43: 0 | GK43: 0 | GL43: =ROUND(IF(AND(BH43=3,BI43=3,FS43<>0),P43,0),2) -> 0 | GM43: =ROUND(O43+X43+Y43,2)+GX43 -> 61294.25 | GN43: =IF(OR(BI43=0,BI43=1),GM43-GX43,0) -> 0 | GO43: =IF(BI43=2,GM43-GX43,0) -> 0 | GP43: =IF(BI43=4,GM43-GX43,0) -> 0 | GR43: 1 | GS43: 1 | GT43: 0 | GV43: =ROUND((GT43),6) -> 0 | GW43: 1 | GX43: =ROUND(HC43*I43,2) -> 0 | HA43: 0 | HB43: 0 | HC43: =GV43*GW43 -> 0 | HE43: 3 | HF43: 1,2 | HS43: 0 | IK43: 0
A44: 17 | B44: 1 | C44: =ROW(SmtRes!A32) -> 32 | D44: =ROW(EtalonRes!A41) -> 41 | E44: 9 | F44: 4.11-3-1 | G44: Установка прибора массой до 5 кг на металлоконструкциях или щитах | H44: 1 ШТ. | I44: 1 | J44: 0 | K44: 1 | O44: =ROUND(CP44,2) -> 7.77 | P44: =ROUND((ROUND((AC44*AW44*I44),2)*BC44),2) -> 0 | Q44: =(ROUND((ROUND((((ET44*1.1))*AV44*I44),2)*BB44),2)+ROUND((ROUND(((AE44-((EU44*1.1)))*AV44*I44),2)*BS44),2)) -> 0 | R44: =(ROUND((ROUND((((EU44*1.1))*AV44*I44),2)*BS44),2)+ROUND((ROUND(((AE44-((EU44*1.1)))*AV44*I44),2)*BS44),2)) -> 0 | S44: =ROUND((ROUND((AF44*AV44*I44),2)*BA44),2) -> 7.77 | T44: =ROUND(CU44*I44,2) -> 0 | U44: =CV44*I44 -> 0.598884 | V44: =CW44*I44 -> 0 | W44: =ROUND(CX44*I44,2) -> 0 | X44: =(ROUND((((S44+ROUND((ROUND((((EU44*1.1))*AV44*I44),2)*BS44),2))*AT44)/100),2)+ROUND(((ROUND((ROUND(((AE44-((EU44*1.1)))*AV44*I44),2)*BS44),2)*AT44)/100),2)) -> 6.99 | Y44: =(ROUND((((S44+ROUND((ROUND((((EU44*1.1))*AV44*I44),2)*BS44),2))*AU44)/100),2)+ROUND(((ROUND((ROUND(((AE44-((EU44*1.1)))*AV44*I44),2)*BS44),2)*AU44)/100),2)) -> 3.57 | AA44: 60256405 | AB44: =ROUND((AC44+AD44+AF44),6) -> 7.425 | AC44: =ROUND(((ES44*1)),6) -> 0 | AD44: =ROUND(((((ET44*1.1))-((EU44*1.1)))+AE44),6) -> 0 | AE44: =ROUND(((EU44*1.1)),6) -> 0 | AF44: =ROUND(((EV44*1.1)),6) -> 7.425 | AG44: =ROUND((AP44),6) -> 0 | AH44: =((EW44*1.1)) -> 0.572 | AI44: =((EX44*1.1)) -> 0 | AJ44: =(AS44) -> 0 | AK44: 6.75 | AL44: 0 | AM44: 0 | AN44: 0 | AO44: 6.75 | AP44: 0 | AQ44: 0.52 | AR44: 0 | AS44: 0 | AT44: 90 | AU44: 46 | AV44: 1.047 | AW44: 1 | AZ44: 1 | BA44: 1 | BB44: 1 | BC44: 1 | BH44: 0 | BI44: 2 | BJ44: ТСН-2001.4 Доп. 67, Сб. 11, т. 3, поз. 1 | BM44: 72 | BN44: 58973116 | BO44: 4.11-3-1 | BP44: 1 | BQ44: 40 | BR44: 0 | BS44: 1 | BT44: 1 | BU44: 1 | BV44: 1 | BW44: 1 | BX44: 1 | BZ44: 90 | CA44: 46 | CE44: 1566 | CF44: 0 | CG44: 0 | CM44: 0 | CN44: Поправка: Гл.12.Прил.8.п.8. 5_12.00.01.11.003 Наименование: При наличии усложненных условий производства работ (стесненность, сложность складирования и транспортной логистики, наличие в зоне производства работ действующего технологического оборудования или движения технологического транспорта и т.п.) для объектов, расположенных за пределами территории круговой магистральной системы улиц "Садовое кольцо" и за пределами Третьего транспортного кольца города Москвы пунктов "а" и "б", но в пределах Московской кольцевой автомобильной дороги | CO44: 0 | CP44: =(P44+Q44+S44) -> 7.77 | CQ44: =ROUND((ROUND((AC44*AW44*1),2)*BC44),2) -> 0 | CR44: =(ROUND((ROUND((((ET44*1.1))*AV44*1),2)*BB44),2)+ROUND((ROUND(((AE44-((EU44*1.1)))*AV44*1),2)*BS44),2)) -> 0 | CS44: =(ROUND((ROUND((((EU44*1.1))*AV44*1),2)*BS44),2)+ROUND((ROUND(((AE44-((EU44*1.1)))*AV44*1),2)*BS44),2)) -> 0 | CT44: =ROUND((ROUND((AF44*AV44*1),2)*BA44),2) -> 7.77 | CU44: =AG44 -> 0 | CV44: =(AH44*AV44) -> 0.598884 | CW44: =AI44 -> 0 | CX44: =AJ44 -> 0 | CY44: =(ROUND((((S44+ROUND((ROUND((((EU44*1.1))*AV44*1),2)*BS44),2))*AT44)/100),2)+ROUND(((ROUND((ROUND(((AE44-((EU44*1.1)))*AV44*1),2)*BS44),2)*AT44)/100),2)) -> 6.99 | CZ44: =(ROUND((((S44+ROUND((ROUND((((EU44*1.1))*AV44*1),2)*BS44),2))*AU44)/100),2)+ROUND(((ROUND((ROUND(((AE44-((EU44*1.1)))*AV44*1),2)*BS44),2)*AU44)/100),2)) -> 3.57 | DB44: 9 | DD44: *1 | DE44: *1,1 | DF44: *1,1 | DG44: *1,1 | DI44: *1,1 | DJ44: *1,1 | DN44: 0 | DO44: 0 | DP44: 1 | DQ44: 1 | DU44: 1013 | DV44: 1 ШТ. | DW44: 1 ШТ. | DX44: 1 | EE44: 60088536 | EF44: 40 | EG44: Монтаж оборудования | EH44: 0 | EJ44: 2 | EK44: 72 | EL44: ТСН-2001.4-11. Приборы и средства автоматизации и вычислительной техники | EM44: ТСН-2001.4-11-1 | EO44: Поправка: Гл.12.Прил.8.п.8. 5_12.00.01.11.003 | EQ44: 0 | ER44: 6.75 | ES44: 0 | ET44: 0 | EU44: 0 | EV44: 6.75 | EW44: 0.52 | EX44: 0 | EY44: 0 | FQ44: 0 | FR44: 0 | FS44: 0 | FX44: 90 | FY44: 46 | GD44: 1 | GF44: 338415528 | GG44: 2 | GH44: 1 | GI44: 2 | GJ44: 0 | GK44: 0 | GL44: =ROUND(IF(AND(BH44=3,BI44=3,FS44<>0),P44,0),2) -> 0 | GM44: =ROUND(O44+X44+Y44,2)+GX44 -> 18.33 | GN44: =IF(OR(BI44=0,BI44=1),GM44-GX44,0) -> 0 | GO44: =IF(BI44=2,GM44-GX44,0) -> 18.33 | GP44: =IF(BI44=4,GM44-GX44,0) -> 0 | GR44: 0 | GS44: 3 | GT44: 0 | GV44: =ROUND((GT44),6) -> 0 | GW44: 1 | GX44: =ROUND(HC44*I44,2) -> 0 | HA44: 0 | HB44: 0 | HC44: =GV44*GW44 -> 0 | HS44: 0 | IK44: 0
A45: 17 | B45: 1 | C45: =ROW(SmtRes!A34) -> 34 | D45: =ROW(EtalonRes!A44) -> 44 | E45: 9 | F45: 4.11-3-1 | G45: Установка прибора массой до 5 кг на металлоконструкциях или щитах | H45: 1 ШТ. | I45: 1 | J45: 0 | K45: 1 | O45: =ROUND(CP45,2) -> 427.27 | P45: =ROUND((ROUND((AC45*AW45*I45),2)*BC45),2) -> 0 | Q45: =(ROUND((ROUND((((ET45*1.1))*AV45*I45),2)*BB45),2)+ROUND((ROUND(((AE45-((EU45*1.1)))*AV45*I45),2)*BS45),2)) -> 0 | R45: =(ROUND((ROUND((((EU45*1.1))*AV45*I45),2)*BS45),2)+ROUND((ROUND(((AE45-((EU45*1.1)))*AV45*I45),2)*BS45),2)) -> 0 | S45: =ROUND((ROUND((AF45*AV45*I45),2)*BA45),2) -> 427.27 | T45: =ROUND(CU45*I45,2) -> 0 | U45: =CV45*I45 -> 0.598884 | V45: =CW45*I45 -> 0 | W45: =ROUND(CX45*I45,2) -> 0 | X45: =(ROUND((((S45+ROUND((ROUND((((EU45*1.1))*AV45*I45),2)*BS45),2))*AT45)/100),2)+ROUND(((ROUND((ROUND(((AE45-((EU45*1.1)))*AV45*I45),2)*BS45),2)*AT45)/100),2)) -> 384.54 | Y45: =(ROUND((((S45+ROUND((ROUND((((EU45*1.1))*AV45*I45),2)*BS45),2))*AU45)/100),2)+ROUND(((ROUND((ROUND(((AE45-((EU45*1.1)))*AV45*I45),2)*BS45),2)*AU45)/100),2)) -> 196.54 | AA45: 60256402 | AB45: =ROUND((AC45+AD45+AF45),6) -> 7.425 | AC45: =ROUND(((ES45*1)),6) -> 0 | AD45: =ROUND(((((ET45*1.1))-((EU45*1.1)))+AE45),6) -> 0 | AE45: =ROUND(((EU45*1.1)),6) -> 0 | AF45: =ROUND(((EV45*1.1)),6) -> 7.425 | AG45: =ROUND((AP45),6) -> 0 | AH45: =((EW45*1.1)) -> 0.572 | AI45: =((EX45*1.1)) -> 0 | AJ45: =(AS45) -> 0 | AK45: 6.75 | AL45: 0 | AM45: 0 | AN45: 0 | AO45: 6.75 | AP45: 0 | AQ45: 0.52 | AR45: 0 | AS45: 0 | AT45: 90 | AU45: 46 | AV45: 1.047 | AW45: 1 | AZ45: 1 | BA45: 54.99 | BB45: 1 | BC45: 1 | BH45: 0 | BI45: 2 | BJ45: ТСН-2001.4 Доп. 67, Сб. 11, т. 3, поз. 1 | BM45: 72 | BN45: 58973116 | BO45: 4.11-3-1 | BP45: 1 | BQ45: 40 | BR45: 0 | BS45: 54.99 | BT45: 1 | BU45: 1 | BV45: 1 | BW45: 1 | BX45: 1 | BZ45: 90 | CA45: 46 | CE45: 1566 | CF45: 0 | CG45: 0 | CM45: 0 | CN45: Поправка: Гл.12.Прил.8.п.8. 5_12.00.01.11.003 Наименование: При наличии усложненных условий производства работ (стесненность, сложность складирования и транспортной логистики, наличие в зоне производства работ действующего технологического оборудования или движения технологического транспорта и т.п.) для объектов, расположенных за пределами территории круговой магистральной системы улиц "Садовое кольцо" и за пределами Третьего транспортного кольца города Москвы пунктов "а" и "б", но в пределах Московской кольцевой автомобильной дороги | CO45: 0 | CP45: =(P45+Q45+S45) -> 427.27 | CQ45: =ROUND((ROUND((AC45*AW45*1),2)*BC45),2) -> 0 | CR45: =(ROUND((ROUND((((ET45*1.1))*AV45*1),2)*BB45),2)+ROUND((ROUND(((AE45-((EU45*1.1)))*AV45*1),2)*BS45),2)) -> 0 | CS45: =(ROUND((ROUND((((EU45*1.1))*AV45*1),2)*BS45),2)+ROUND((ROUND(((AE45-((EU45*1.1)))*AV45*1),2)*BS45),2)) -> 0 | CT45: =ROUND((ROUND((AF45*AV45*1),2)*BA45),2) -> 427.27 | CU45: =AG45 -> 0 | CV45: =(AH45*AV45) -> 0.598884 | CW45: =AI45 -> 0 | CX45: =AJ45 -> 0 | CY45: =(ROUND((((S45+ROUND((ROUND((((EU45*1.1))*AV45*1),2)*BS45),2))*AT45)/100),2)+ROUND(((ROUND((ROUND(((AE45-((EU45*1.1)))*AV45*1),2)*BS45),2)*AT45)/100),2)) -> 384.54 | CZ45: =(ROUND((((S45+ROUND((ROUND((((EU45*1.1))*AV45*1),2)*BS45),2))*AU45)/100),2)+ROUND(((ROUND((ROUND(((AE45-((EU45*1.1)))*AV45*1),2)*BS45),2)*AU45)/100),2)) -> 196.54 | DB45: 10 | DD45: *1 | DE45: *1,1 | DF45: *1,1 | DG45: *1,1 | DI45: *1,1 | DJ45: *1,1 | DN45: 0 | DO45: 0 | DP45: 1 | DQ45: 1 | DU45: 1013 | DV45: 1 ШТ. | DW45: 1 ШТ. | DX45: 1 | EE45: 60088536 | EF45: 40 | EG45: Монтаж оборудования | EH45: 0 | EJ45: 2 | EK45: 72 | EL45: ТСН-2001.4-11. Приборы и средства автоматизации и вычислительной техники | EM45: ТСН-2001.4-11-1 | EO45: Поправка: Гл.12.Прил.8.п.8. 5_12.00.01.11.003 | EQ45: 0 | ER45: 6.75 | ES45: 0 | ET45: 0 | EU45: 0 | EV45: 6.75 | EW45: 0.52 | EX45: 0 | EY45: 0 | FQ45: 0 | FR45: 0 | FS45: 0 | FX45: 90 | FY45: 46 | GD45: 1 | GF45: 338415528 | GG45: 2 | GH45: 1 | GI45: 2 | GJ45: 0 | GK45: 0 | GL45: =ROUND(IF(AND(BH45=3,BI45=3,FS45<>0),P45,0),2) -> 0 | GM45: =ROUND(O45+X45+Y45,2)+GX45 -> 1008.35 | GN45: =IF(OR(BI45=0,BI45=1),GM45-GX45,0) -> 0 | GO45: =IF(BI45=2,GM45-GX45,0) -> 1008.35 | GP45: =IF(BI45=4,GM45-GX45,0) -> 0 | GR45: 0 | GS45: 3 | GT45: 0 | GV45: =ROUND((GT45),6) -> 0 | GW45: 1 | GX45: =ROUND(HC45*I45,2) -> 0 | HA45: 0 | HB45: 0 | HC45: =GV45*GW45 -> 0 | HS45: 0 | IK45: 0
A46: 18 | B46: 1 | C46: 32 | E46: 9,1 | F46: 1.1-1-8146 | G46: Болты стальные оцинкованные с шестигранной головкой, с полной резьбой, с гайкой оцинкованной, М6, длина от 12 до 60 мм | H46: кг | I46: =I44*J46 -> 0.035 | J46: 0.035 | K46: 0.035 | O46: =ROUND(CP46,2) -> 1.09 | P46: =ROUND((ROUND((AC46*AW46*I46),2)*BC46),2) -> 1.09 | Q46: =(ROUND((ROUND(((ET46)*AV46*I46),2)*BB46),2)+ROUND((ROUND(((AE46-(EU46))*AV46*I46),2)*BS46),2)) -> 0 | R46: =(ROUND((ROUND(((EU46)*AV46*I46),2)*BS46),2)+ROUND((ROUND(((AE46-(EU46))*AV46*I46),2)*BS46),2)) -> 0 | S46: =ROUND((ROUND((AF46*AV46*I46),2)*BA46),2) -> 0 | T46: =ROUND(CU46*I46,2) -> 0 | U46: =CV46*I46 -> 0 | V46: =CW46*I46 -> 0 | W46: =ROUND(CX46*I46,2) -> 0 | X46: =(ROUND((((S46+ROUND((ROUND(((EU46)*AV46*I46),2)*BS46),2))*AT46)/100),2)+ROUND(((ROUND((ROUND(((AE46-(EU46))*AV46*I46),2)*BS46),2)*AT46)/100),2)) -> 0 | Y46: =(ROUND((((S46+ROUND((ROUND(((EU46)*AV46*I46),2)*BS46),2))*AU46)/100),2)+ROUND(((ROUND((ROUND(((AE46-(EU46))*AV46*I46),2)*BS46),2)*AU46)/100),2)) -> 0 | AA46: 60256405 | AB46: =ROUND((AC46+AD46+AF46),6) -> 31.08 | AC46: =ROUND((ES46),6) -> 31.08 | AD46: =ROUND((((ET46)-(EU46))+AE46),6) -> 0 | AE46: =ROUND((EU46),6) -> 0 | AF46: =ROUND((EV46),6) -> 0 | AG46: =ROUND((AP46),6) -> 0 | AH46: =(EW46) -> 0 | AI46: =(EX46) -> 0 | AJ46: =(AS46) -> 0 | AK46: 31.08 | AL46: 31.08 | AM46: 0 | AN46: 0 | AO46: 0 | AP46: 0 | AQ46: 0 | AR46: 0 | AS46: 0 | AT46: 90 | AU46: 46 | AV46: 1 | AW46: 1 | AZ46: 1 | BA46: 1 | BB46: 1 | BC46: 1 | BH46: 3 | BI46: 2 | BJ46: ТСН-2001.1 Доп. 79, Р. 1, о. 1, поз. 8146 | BM46: 72 | BN46: 58973116 | BP46: 0 | BQ46: 40 | BR46: 0 | BS46: 1 | BT46: 1 | BU46: 1 | BV46: 1 | BW46: 1 | BX46: 1 | BZ46: 90 | CA46: 46 | CE46: 1566 | CF46: 0 | CG46: 0 | CM46: 0 | CN46: Поправка: Гл.12.Прил.8.п.8. 5_12.00.01.11.003 Наименование: При наличии усложненных условий производства работ (стесненность, сложность складирования и транспортной логистики, наличие в зоне производства работ действующего технологического оборудования или движения технологического транспорта и т.п.) для объектов, расположенных за пределами территории круговой магистральной системы улиц "Садовое кольцо" и за пределами Третьего транспортного кольца города Москвы пунктов "а" и "б", но в пределах Московской кольцевой автомобильной дороги | CO46: 0 | CP46: =(P46+Q46+S46) -> 1.09 | CQ46: =ROUND((ROUND((AC46*AW46*1),2)*BC46),2) -> 31.08 | CR46: =(ROUND((ROUND(((ET46)*AV46*1),2)*BB46),2)+ROUND((ROUND(((AE46-(EU46))*AV46*1),2)*BS46),2)) -> 0 | CS46: =(ROUND((ROUND(((EU46)*AV46*1),2)*BS46),2)+ROUND((ROUND(((AE46-(EU46))*AV46*1),2)*BS46),2)) -> 0 | CT46: =ROUND((ROUND((AF46*AV46*1),2)*BA46),2) -> 0 | CU46: =AG46 -> 0 | CV46: =(AH46*AV46) -> 0 | CW46: =AI46 -> 0 | CX46: =AJ46 -> 0 | CY46: =(ROUND((((S46+ROUND((ROUND(((EU46)*AV46*1),2)*BS46),2))*AT46)/100),2)+ROUND(((ROUND((ROUND(((AE46-(EU46))*AV46*1),2)*BS46),2)*AT46)/100),2)) -> 0 | CZ46: =(ROUND((((S46+ROUND((ROUND(((EU46)*AV46*1),2)*BS46),2))*AU46)/100),2)+ROUND(((ROUND((ROUND(((AE46-(EU46))*AV46*1),2)*BS46),2)*AU46)/100),2)) -> 0 | DN46: 0 | DO46: 0 | DP46: 1 | DQ46: 1 | DU46: 1009 | DV46: кг | DW46: кг | DX46: 1 | EE46: 60088536 | EF46: 40 | EG46: Монтаж оборудования | EH46: 0 | EJ46: 2 | EK46: 72 | EL46: ТСН-2001.4-11. Приборы и средства автоматизации и вычислительной техники | EM46: ТСН-2001.4-11-1 | EO46: Поправка: Гл.12.Прил.8.п.8. 5_12.00.01.11.003 | EQ46: 0 | ER46: 31.08 | ES46: 31.08 | ET46: 0 | EU46: 0 | EV46: 0 | EW46: 0 | EX46: 0 | FQ46: 0 | FR46: 0 | FS46: 0 | FX46: 90 | FY46: 46 | GD46: 1 | GF46: 1143487818 | GG46: 2 | GH46: 1 | GI46: -2 | GJ46: 0 | GK46: 0 | GL46: =ROUND(IF(AND(BH46=3,BI46=3,FS46<>0),P46,0),2) -> 0 | GM46: =ROUND(O46+X46+Y46,2)+GX46 -> 1.09 | GN46: =IF(OR(BI46=0,BI46=1),GM46-GX46,0) -> 0 | GO46: =IF(BI46=2,GM46-GX46,0) -> 1.09 | GP46: =IF(BI46=4,GM46-GX46,0) -> 0 | GR46: 0 | GS46: 3 | GT46: 0 | GV46: =ROUND((GT46),6) -> 0 | GW46: 1 | GX46: =ROUND(HC46*I46,2) -> 0 | HA46: 0 | HB46: 0 | HC46: =GV46*GW46 -> 0 | HM46: *1 | HS46: 0 | IK46: 0
A47: 18 | B47: 1 | C47: 34 | E47: 9,1 | F47: 1.1-1-8146 | G47: Болты стальные оцинкованные с шестигранной головкой, с полной резьбой, с гайкой оцинкованной, М6, длина от 12 до 60 мм | H47: кг | I47: =I45*J47 -> 0.035 | J47: 0.035 | K47: 0.035 | O47: =ROUND(CP47,2) -> 5.58 | P47: =ROUND((ROUND((AC47*AW47*I47),2)*BC47),2) -> 5.58 | Q47: =(ROUND((ROUND(((ET47)*AV47*I47),2)*BB47),2)+ROUND((ROUND(((AE47-(EU47))*AV47*I47),2)*BS47),2)) -> 0 | R47: =(ROUND((ROUND(((EU47)*AV47*I47),2)*BS47),2)+ROUND((ROUND(((AE47-(EU47))*AV47*I47),2)*BS47),2)) -> 0 | S47: =ROUND((ROUND((AF47*AV47*I47),2)*BA47),2) -> 0 | T47: =ROUND(CU47*I47,2) -> 0 | U47: =CV47*I47 -> 0 | V47: =CW47*I47 -> 0 | W47: =ROUND(CX47*I47,2) -> 0 | X47: =(ROUND((((S47+ROUND((ROUND(((EU47)*AV47*I47),2)*BS47),2))*AT47)/100),2)+ROUND(((ROUND((ROUND(((AE47-(EU47))*AV47*I47),2)*BS47),2)*AT47)/100),2)) -> 0 | Y47: =(ROUND((((S47+ROUND((ROUND(((EU47)*AV47*I47),2)*BS47),2))*AU47)/100),2)+ROUND(((ROUND((ROUND(((AE47-(EU47))*AV47*I47),2)*BS47),2)*AU47)/100),2)) -> 0 | AA47: 60256402 | AB47: =ROUND((AC47+AD47+AF47),6) -> 31.08 | AC47: =ROUND((ES47),6) -> 31.08 | AD47: =ROUND((((ET47)-(EU47))+AE47),6) -> 0 | AE47: =ROUND((EU47),6) -> 0 | AF47: =ROUND((EV47),6) -> 0 | AG47: =ROUND((AP47),6) -> 0 | AH47: =(EW47) -> 0 | AI47: =(EX47) -> 0 | AJ47: =(AS47) -> 0 | AK47: 31.08 | AL47: 31.08 | AM47: 0 | AN47: 0 | AO47: 0 | AP47: 0 | AQ47: 0 | AR47: 0 | AS47: 0 | AT47: 90 | AU47: 46 | AV47: 1 | AW47: 1 | AZ47: 1 | BA47: 1 | BB47: 1 | BC47: 5.12 | BH47: 3 | BI47: 2 | BJ47: ТСН-2001.1 Доп. 79, Р. 1, о. 1, поз. 8146 | BM47: 72 | BN47: 58973116 | BO47: 1.1-1-8146 | BP47: 1 | BQ47: 40 | BR47: 0 | BS47: 1 | BT47: 1 | BU47: 1 | BV47: 1 | BW47: 1 | BX47: 1 | BZ47: 90 | CA47: 46 | CE47: 1566 | CF47: 0 | CG47: 0 | CM47: 0 | CN47: Поправка: Гл.12.Прил.8.п.8. 5_12.00.01.11.003 Наименование: При наличии усложненных условий производства работ (стесненность, сложность складирования и транспортной логистики, наличие в зоне производства работ действующего технологического оборудования или движения технологического транспорта и т.п.) для объектов, расположенных за пределами территории круговой магистральной системы улиц "Садовое кольцо" и за пределами Третьего транспортного кольца города Москвы пунктов "а" и "б", но в пределах Московской кольцевой автомобильной дороги | CO47: 0 | CP47: =(P47+Q47+S47) -> 5.58 | CQ47: =ROUND((ROUND((AC47*AW47*1),2)*BC47),2) -> 159.13 | CR47: =(ROUND((ROUND(((ET47)*AV47*1),2)*BB47),2)+ROUND((ROUND(((AE47-(EU47))*AV47*1),2)*BS47),2)) -> 0 | CS47: =(ROUND((ROUND(((EU47)*AV47*1),2)*BS47),2)+ROUND((ROUND(((AE47-(EU47))*AV47*1),2)*BS47),2)) -> 0 | CT47: =ROUND((ROUND((AF47*AV47*1),2)*BA47),2) -> 0 | CU47: =AG47 -> 0 | CV47: =(AH47*AV47) -> 0 | CW47: =AI47 -> 0 | CX47: =AJ47 -> 0 | CY47: =(ROUND((((S47+ROUND((ROUND(((EU47)*AV47*1),2)*BS47),2))*AT47)/100),2)+ROUND(((ROUND((ROUND(((AE47-(EU47))*AV47*1),2)*BS47),2)*AT47)/100),2)) -> 0 | CZ47: =(ROUND((((S47+ROUND((ROUND(((EU47)*AV47*1),2)*BS47),2))*AU47)/100),2)+ROUND(((ROUND((ROUND(((AE47-(EU47))*AV47*1),2)*BS47),2)*AU47)/100),2)) -> 0 | DN47: 0 | DO47: 0 | DP47: 1 | DQ47: 1 | DU47: 1009 | DV47: кг | DW47: кг | DX47: 1 | EE47: 60088536 | EF47: 40 | EG47: Монтаж оборудования | EH47: 0 | EJ47: 2 | EK47: 72 | EL47: ТСН-2001.4-11. Приборы и средства автоматизации и вычислительной техники | EM47: ТСН-2001.4-11-1 | EO47: Поправка: Гл.12.Прил.8.п.8. 5_12.00.01.11.003 | EQ47: 0 | ER47: 31.08 | ES47: 31.08 | ET47: 0 | EU47: 0 | EV47: 0 | EW47: 0 | EX47: 0 | FQ47: 0 | FR47: 0 | FS47: 0 | FX47: 90 | FY47: 46 | GD47: 1 | GF47: 1143487818 | GG47: 2 | GH47: 1 | GI47: 2 | GJ47: 0 | GK47: 0 | GL47: =ROUND(IF(AND(BH47=3,BI47=3,FS47<>0),P47,0),2) -> 0 | GM47: =ROUND(O47+X47+Y47,2)+GX47 -> 5.58 | GN47: =IF(OR(BI47=0,BI47=1),GM47-GX47,0) -> 0 | GO47: =IF(BI47=2,GM47-GX47,0) -> 5.58 | GP47: =IF(BI47=4,GM47-GX47,0) -> 0 | GR47: 0 | GS47: 3 | GT47: 0 | GV47: =ROUND((GT47),6) -> 0 | GW47: 1 | GX47: =ROUND(HC47*I47,2) -> 0 | HA47: 0 | HB47: 0 | HC47: =GV47*GW47 -> 0 | HM47: *1 | HS47: 0 | IK47: 0
A48: 17 | B48: 1 | E48: 10 | F48: КА-5 | G48: Силовой блок рапределения питания по стойке оповещения, максимальный ток 50А Sonar RDIP-50A | H48: шт. | I48: 1 | J48: 0 | K48: 1 | O48: =ROUND(CP48,2) -> 3010.39 | P48: =ROUND((ROUND((AC48*I48),2)*BC48),2) -> 3010.39 | Q48: =(ROUND((ROUND(((ET48)*AV48*I48),2)*BB48),2)+ROUND((ROUND(((AE48-(EU48))*AV48*I48),2)*BS48),2)) -> 0 | R48: =(ROUND((ROUND(((EU48)*AV48*I48),2)*BS48),2)+ROUND((ROUND(((AE48-(EU48))*AV48*I48),2)*BS48),2)) -> 0 | S48: =ROUND((ROUND((AF48*AV48*I48),2)*BA48),2) -> 0 | T48: =ROUND(CU48*I48,2) -> 0 | U48: =CV48*I48 -> 0 | V48: =CW48*I48 -> 0 | W48: =ROUND(CX48*I48,2) -> 0 | X48: =(ROUND((((S48+ROUND((ROUND(((EU48)*AV48*I48),2)*BS48),2))*AT48)/100),2)+ROUND(((ROUND((ROUND(((AE48-(EU48))*AV48*I48),2)*BS48),2)*AT48)/100),2)) -> 0 | Y48: =(ROUND((((S48+ROUND((ROUND(((EU48)*AV48*I48),2)*BS48),2))*AU48)/100),2)+ROUND(((ROUND((ROUND(((AE48-(EU48))*AV48*I48),2)*BS48),2)*AU48)/100),2)) -> 0 | AA48: 60256405 | AB48: =ROUND((AC48+AD48+AF48),6) -> 3010.39 | AC48: =ROUND((ES48),6) -> 3010.39 | AD48: =ROUND((((ET48)-(EU48))+AE48),6) -> 0 | AE48: =ROUND((EU48),6) -> 0 | AF48: =ROUND((EV48),6) -> 0 | AG48: =ROUND((AP48),6) -> 0 | AH48: =(EW48) -> 0 | AI48: =(EX48) -> 0 | AJ48: =(AS48) -> 0 | AK48: 3010.39 | AL48: 3010.39 | AM48: 0 | AN48: 0 | AO48: 0 | AP48: 0 | AQ48: 0 | AR48: 0 | AS48: 0 | AT48: 0 | AU48: 0 | AV48: 1 | AW48: 1 | AZ48: 1 | BA48: 1 | BB48: 1 | BC48: 1 | BH48: 3 | BI48: 3 | BM48: 746 | BN48: 0 | BP48: 0 | BQ48: 130 | BR48: 0 | BS48: 1 | BT48: 1 | BU48: 1 | BV48: 1 | BW48: 1 | BX48: 1 | BZ48: 0 | CA48: 0 | CE48: 1566 | CF48: 0 | CG48: 0 | CM48: 0 | CO48: 0 | CP48: =(P48+Q48+S48) -> 3010.39 | CQ48: =ROUND((ROUND((AC48*1),2)*BC48),2) -> 3010.39 | CR48: =(ROUND((ROUND(((ET48)*AV48*1),2)*BB48),2)+ROUND((ROUND(((AE48-(EU48))*AV48*1),2)*BS48),2)) -> 0 | CS48: =(ROUND((ROUND(((EU48)*AV48*1),2)*BS48),2)+ROUND((ROUND(((AE48-(EU48))*AV48*1),2)*BS48),2)) -> 0 | CT48: =ROUND((ROUND((AF48*AV48*1),2)*BA48),2) -> 0 | CU48: =AG48 -> 0 | CV48: =(AH48*AV48) -> 0 | CW48: =AI48 -> 0 | CX48: =AJ48 -> 0 | CY48: =(ROUND((((S48+ROUND((ROUND(((EU48)*AV48*1),2)*BS48),2))*AT48)/100),2)+ROUND(((ROUND((ROUND(((AE48-(EU48))*AV48*1),2)*BS48),2)*AT48)/100),2)) -> 0 | CZ48: =(ROUND((((S48+ROUND((ROUND(((EU48)*AV48*1),2)*BS48),2))*AU48)/100),2)+ROUND(((ROUND((ROUND(((AE48-(EU48))*AV48*1),2)*BS48),2)*AU48)/100),2)) -> 0 | DN48: 0 | DO48: 0 | DP48: 1 | DQ48: 1 | DU48: 1010 | DV48: шт. | DW48: шт. | DX48: 1 | EE48: 60088638 | EF48: 130 | EG48: Сметная стоимость оборудования | EH48: 0 | EJ48: 3 | EK48: 746 | EL48: ТСН-2001.13. Сметная стоимость оборудования | EM48: ТСН-2001.13 | EQ48: 0 | ER48: 0 | ES48: 3010.39 | ET48: 0 | EU48: 0 | EV48: 0 | EW48: 0 | EX48: 0 | EY48: 0 | FQ48: 0 | FR48: =P48 -> 3010.39 | FS48: 0 | FX48: 0 | FY48: 0 | GA48: [26 547 / 1,2 / 7,66] + 3% Трансп + 1,2% Заг.скл | GD48: 1 | GF48: -1990037497 | GG48: 2 | GH48: 4 | GI48: -2 | GJ48: 0 | GK48: 0 | GL48: =ROUND(IF(AND(BH48=3,BI48=3,FS48<>0),P48,0),2) -> 0 | GM48: =ROUND(O48+X48+Y48,2)+GX48 -> 3010.39 | GN48: =IF(OR(BI48=0,BI48=1),GM48-GX48,0) -> 0 | GO48: =IF(BI48=2,GM48-GX48,0) -> 0 | GP48: =IF(BI48=4,GM48-GX48,0) -> 0 | GR48: 0 | GS48: 2 | GT48: 0 | GV48: =ROUND((GT48),6) -> 0 | GW48: 1 | GX48: =ROUND(HC48*I48,2) -> 0 | HA48: 0 | HB48: 0 | HC48: =GV48*GW48 -> 0 | HE48: 3 | HF48: 1,2 | HS48: 0 | IK48: 0
A49: 17 | B49: 1 | E49: 10 | F49: КА-5 | G49: Силовой блок рапределения питания по стойке оповещения, максимальный ток 50А Sonar RDIP-50A | H49: шт. | I49: 1 | J49: 0 | K49: 1 | O49: =ROUND(CP49,2) -> 23059.59 | P49: =ROUND((ROUND((AC49*I49),2)*BC49),2) -> 23059.59 | Q49: =(ROUND((ROUND(((ET49)*AV49*I49),2)*BB49),2)+ROUND((ROUND(((AE49-(EU49))*AV49*I49),2)*BS49),2)) -> 0 | R49: =(ROUND((ROUND(((EU49)*AV49*I49),2)*BS49),2)+ROUND((ROUND(((AE49-(EU49))*AV49*I49),2)*BS49),2)) -> 0 | S49: =ROUND((ROUND((AF49*AV49*I49),2)*BA49),2) -> 0 | T49: =ROUND(CU49*I49,2) -> 0 | U49: =CV49*I49 -> 0 | V49: =CW49*I49 -> 0 | W49: =ROUND(CX49*I49,2) -> 0 | X49: =(ROUND((((S49+ROUND((ROUND(((EU49)*AV49*I49),2)*BS49),2))*AT49)/100),2)+ROUND(((ROUND((ROUND(((AE49-(EU49))*AV49*I49),2)*BS49),2)*AT49)/100),2)) -> 0 | Y49: =(ROUND((((S49+ROUND((ROUND(((EU49)*AV49*I49),2)*BS49),2))*AU49)/100),2)+ROUND(((ROUND((ROUND(((AE49-(EU49))*AV49*I49),2)*BS49),2)*AU49)/100),2)) -> 0 | AA49: 60256402 | AB49: =ROUND((AC49+AD49+AF49),6) -> 3010.39 | AC49: =ROUND((ES49),6) -> 3010.39 | AD49: =ROUND((((ET49)-(EU49))+AE49),6) -> 0 | AE49: =ROUND((EU49),6) -> 0 | AF49: =ROUND((EV49),6) -> 0 | AG49: =ROUND((AP49),6) -> 0 | AH49: =(EW49) -> 0 | AI49: =(EX49) -> 0 | AJ49: =(AS49) -> 0 | AK49: 3010.39 | AL49: 3010.39 | AM49: 0 | AN49: 0 | AO49: 0 | AP49: 0 | AQ49: 0 | AR49: 0 | AS49: 0 | AT49: 0 | AU49: 0 | AV49: 1 | AW49: 1 | AZ49: 1 | BA49: 1 | BB49: 1 | BC49: 7.66 | BH49: 3 | BI49: 3 | BM49: 746 | BN49: 0 | BP49: 0 | BQ49: 130 | BR49: 0 | BS49: 1 | BT49: 1 | BU49: 1 | BV49: 1 | BW49: 1 | BX49: 1 | BZ49: 0 | CA49: 0 | CE49: 1566 | CF49: 0 | CG49: 0 | CM49: 0 | CO49: 0 | CP49: =(P49+Q49+S49) -> 23059.59 | CQ49: =ROUND((ROUND((AC49*1),2)*BC49),2) -> 23059.59 | CR49: =(ROUND((ROUND(((ET49)*AV49*1),2)*BB49),2)+ROUND((ROUND(((AE49-(EU49))*AV49*1),2)*BS49),2)) -> 0 | CS49: =(ROUND((ROUND(((EU49)*AV49*1),2)*BS49),2)+ROUND((ROUND(((AE49-(EU49))*AV49*1),2)*BS49),2)) -> 0 | CT49: =ROUND((ROUND((AF49*AV49*1),2)*BA49),2) -> 0 | CU49: =AG49 -> 0 | CV49: =(AH49*AV49) -> 0 | CW49: =AI49 -> 0 | CX49: =AJ49 -> 0 | CY49: =(ROUND((((S49+ROUND((ROUND(((EU49)*AV49*1),2)*BS49),2))*AT49)/100),2)+ROUND(((ROUND((ROUND(((AE49-(EU49))*AV49*1),2)*BS49),2)*AT49)/100),2)) -> 0 | CZ49: =(ROUND((((S49+ROUND((ROUND(((EU49)*AV49*1),2)*BS49),2))*AU49)/100),2)+ROUND(((ROUND((ROUND(((AE49-(EU49))*AV49*1),2)*BS49),2)*AU49)/100),2)) -> 0 | DN49: 0 | DO49: 0 | DP49: 1 | DQ49: 1 | DU49: 1010 | DV49: шт. | DW49: шт. | DX49: 1 | EE49: 60088638 | EF49: 130 | EG49: Сметная стоимость оборудования | EH49: 0 | EJ49: 3 | EK49: 746 | EL49: ТСН-2001.13. Сметная стоимость оборудования | EM49: ТСН-2001.13 | EQ49: 0 | ER49: 3010.39 | ES49: 3010.39 | ET49: 0 | EU49: 0 | EV49: 0 | EW49: 0 | EX49: 0 | EY49: 0 | EZ49: 5 | FC49: 1 | FD49: 18 | FF49: 26547 | FQ49: 0 | FR49: =P49 -> 23059.59 | FS49: 0 | FX49: 0 | FY49: 0 | GA49: [26 547 / 1,2 / 7,66] + 3% Трансп + 1,2% Заг.скл | GD49: 1 | GF49: -1990037497 | GG49: 2 | GH49: 3 | GI49: 5 | GJ49: 0 | GK49: 0 | GL49: =ROUND(IF(AND(BH49=3,BI49=3,FS49<>0),P49,0),2) -> 0 | GM49: =ROUND(O49+X49+Y49,2)+GX49 -> 23059.59 | GN49: =IF(OR(BI49=0,BI49=1),GM49-GX49,0) -> 0 | GO49: =IF(BI49=2,GM49-GX49,0) -> 0 | GP49: =IF(BI49=4,GM49-GX49,0) -> 0 | GR49: 1 | GS49: 1 | GT49: 0 | GV49: =ROUND((GT49),6) -> 0 | GW49: 1 | GX49: =ROUND(HC49*I49,2) -> 0 | HA49: 0 | HB49: 0 | HC49: =GV49*GW49 -> 0 | HE49: 3 | HF49: 1,2 | HS49: 0 | IK49: 0
A50: 17 | B50: 1 | C50: =ROW(SmtRes!A40) -> 40 | D50: =ROW(EtalonRes!A51) -> 51 | E50: 11 | F50: 4.10-167-1 | G50: Монтаж блока питания сети (БПС) в диспетчерской | H50: 1 ШТ. | I50: 1 | J50: 0 | K50: 1 | O50: =ROUND(CP50,2) -> 24.17 | P50: =ROUND((ROUND((AC50*AW50*I50),2)*BC50),2) -> 2.34 | Q50: =(ROUND((ROUND((((ET50*1.1))*AV50*I50),2)*BB50),2)+ROUND((ROUND(((AE50-((EU50*1.1)))*AV50*I50),2)*BS50),2)) -> 0.02 | R50: =(ROUND((ROUND((((EU50*1.1))*AV50*I50),2)*BS50),2)+ROUND((ROUND(((AE50-((EU50*1.1)))*AV50*I50),2)*BS50),2)) -> 0 | S50: =ROUND((ROUND((AF50*AV50*I50),2)*BA50),2) -> 21.81 | T50: =ROUND(CU50*I50,2) -> 0 | U50: =CV50*I50 -> 1.566312 | V50: =CW50*I50 -> 0 | W50: =ROUND(CX50*I50,2) -> 0 | X50: =(ROUND((((S50+ROUND((ROUND((((EU50*1.1))*AV50*I50),2)*BS50),2))*AT50)/100),2)+ROUND(((ROUND((ROUND(((AE50-((EU50*1.1)))*AV50*I50),2)*BS50),2)*AT50)/100),2)) -> 19.63 | Y50: =(ROUND((((S50+ROUND((ROUND((((EU50*1.1))*AV50*I50),2)*BS50),2))*AU50)/100),2)+ROUND(((ROUND((ROUND(((AE50-((EU50*1.1)))*AV50*I50),2)*BS50),2)*AU50)/100),2)) -> 10.03 | AA50: 60256405 | AB50: =ROUND((AC50+AD50+AF50),6) -> 23.196 | AC50: =ROUND(((ES50*1)),6) -> 2.34 | AD50: =ROUND(((((ET50*1.1))-((EU50*1.1)))+AE50),6) -> 0.022 | AE50: =ROUND(((EU50*1.1)),6) -> 0 | AF50: =ROUND(((EV50*1.1)),6) -> 20.834 | AG50: =ROUND((AP50),6) -> 0 | AH50: =((EW50*1.1)) -> 1.496 | AI50: =((EX50*1.1)) -> 0 | AJ50: =(AS50) -> 0 | AK50: 21.3 | AL50: 2.34 | AM50: 0.02 | AN50: 0 | AO50: 18.94 | AP50: 0 | AQ50: 1.36 | AR50: 0 | AS50: 0 | AT50: 90 | AU50: 46 | AV50: 1.047 | AW50: 1 | AZ50: 1 | BA50: 1 | BB50: 1 | BC50: 1 | BH50: 0 | BI50: 2 | BJ50: ТСН-2001.4 Доп. 69, Сб. 10, т. 167, поз. 1 | BM50: 68 | BN50: 58973116 | BO50: 4.10-167-1 | BP50: 1 | BQ50: 40 | BR50: 0 | BS50: 1 | BT50: 1 | BU50: 1 | BV50: 1 | BW50: 1 | BX50: 1 | BZ50: 90 | CA50: 46 | CE50: 1566 | CF50: 0 | CG50: 0 | CM50: 0 | CN50: Поправка: Гл.12.Прил.8.п.8. 5_12.00.01.11.003 Наименование: При наличии усложненных условий производства работ (стесненность, сложность складирования и транспортной логистики, наличие в зоне производства работ действующего технологического оборудования или движения технологического транспорта и т.п.) для объектов, расположенных за пределами территории круговой магистральной системы улиц "Садовое кольцо" и за пределами Третьего транспортного кольца города Москвы пунктов "а" и "б", но в пределах Московской кольцевой автомобильной дороги | CO50: 0 | CP50: =(P50+Q50+S50) -> 24.17 | CQ50: =ROUND((ROUND((AC50*AW50*1),2)*BC50),2) -> 2.34 | CR50: =(ROUND((ROUND((((ET50*1.1))*AV50*1),2)*BB50),2)+ROUND((ROUND(((AE50-((EU50*1.1)))*AV50*1),2)*BS50),2)) -> 0.02 | CS50: =(ROUND((ROUND((((EU50*1.1))*AV50*1),2)*BS50),2)+ROUND((ROUND(((AE50-((EU50*1.1)))*AV50*1),2)*BS50),2)) -> 0 | CT50: =ROUND((ROUND((AF50*AV50*1),2)*BA50),2) -> 21.81 | CU50: =AG50 -> 0 | CV50: =(AH50*AV50) -> 1.566312 | CW50: =AI50 -> 0 | CX50: =AJ50 -> 0 | CY50: =(ROUND((((S50+ROUND((ROUND((((EU50*1.1))*AV50*1),2)*BS50),2))*AT50)/100),2)+ROUND(((ROUND((ROUND(((AE50-((EU50*1.1)))*AV50*1),2)*BS50),2)*AT50)/100),2)) -> 19.63 | CZ50: =(ROUND((((S50+ROUND((ROUND((((EU50*1.1))*AV50*1),2)*BS50),2))*AU50)/100),2)+ROUND(((ROUND((ROUND(((AE50-((EU50*1.1)))*AV50*1),2)*BS50),2)*AU50)/100),2)) -> 10.03 | DB50: 11 | DD50: *1 | DE50: *1,1 | DF50: *1,1 | DG50: *1,1 | DI50: *1,1 | DJ50: *1,1 | DN50: 0 | DO50: 0 | DP50: 1 | DQ50: 1 | DU50: 1013 | DV50: 1 ШТ. | DW50: 1 ШТ. | DX50: 1 | EE50: 60088532 | EF50: 40 | EG50: Монтаж оборудования | EH50: 0 | EJ50: 2 | EK50: 68 | EL50: ТСН-2001.4-10. Прокладка и монтаж сетей связи | EM50: ТСН-2001.4-10-1 | EO50: Поправка: Гл.12.Прил.8.п.8. 5_12.00.01.11.003 | EQ50: 0 | ER50: 21.3 | ES50: 2.34 | ET50: 0.02 | EU50: 0 | EV50: 18.94 | EW50: 1.36 | EX50: 0 | EY50: 0 | FQ50: 0 | FR50: 0 | FS50: 0 | FX50: 90 | FY50: 46 | GD50: 1 | GF50: 938017806 | GG50: 2 | GH50: 1 | GI50: 2 | GJ50: 0 | GK50: 0 | GL50: =ROUND(IF(AND(BH50=3,BI50=3,FS50<>0),P50,0),2) -> 0 | GM50: =ROUND(O50+X50+Y50,2)+GX50 -> 53.83 | GN50: =IF(OR(BI50=0,BI50=1),GM50-GX50,0) -> 0 | GO50: =IF(BI50=2,GM50-GX50,0) -> 53.83 | GP50: =IF(BI50=4,GM50-GX50,0) -> 0 | GR50: 0 | GS50: 3 | GT50: 0 | GV50: =ROUND((GT50),6) -> 0 | GW50: 1 | GX50: =ROUND(HC50*I50,2) -> 0 | HA50: 0 | HB50: 0 | HC50: =GV50*GW50 -> 0 | HS50: 0 | IK50: 0
A51: 17 | B51: 1 | C51: =ROW(SmtRes!A46) -> 46 | D51: =ROW(EtalonRes!A58) -> 58 | E51: 11 | F51: 4.10-167-1 | G51: Монтаж блока питания сети (БПС) в диспетчерской | H51: 1 ШТ. | I51: 1 | J51: 0 | K51: 1 | O51: =ROUND(CP51,2) -> 1223.54 | P51: =ROUND((ROUND((AC51*AW51*I51),2)*BC51),2) -> 24.01 | Q51: =(ROUND((ROUND((((ET51*1.1))*AV51*I51),2)*BB51),2)+ROUND((ROUND(((AE51-((EU51*1.1)))*AV51*I51),2)*BS51),2)) -> 0.2 | R51: =(ROUND((ROUND((((EU51*1.1))*AV51*I51),2)*BS51),2)+ROUND((ROUND(((AE51-((EU51*1.1)))*AV51*I51),2)*BS51),2)) -> 0 | S51: =ROUND((ROUND((AF51*AV51*I51),2)*BA51),2) -> 1199.33 | T51: =ROUND(CU51*I51,2) -> 0 | U51: =CV51*I51 -> 1.566312 | V51: =CW51*I51 -> 0 | W51: =ROUND(CX51*I51,2) -> 0 | X51: =(ROUND((((S51+ROUND((ROUND((((EU51*1.1))*AV51*I51),2)*BS51),2))*AT51)/100),2)+ROUND(((ROUND((ROUND(((AE51-((EU51*1.1)))*AV51*I51),2)*BS51),2)*AT51)/100),2)) -> 1079.4 | Y51: =(ROUND((((S51+ROUND((ROUND((((EU51*1.1))*AV51*I51),2)*BS51),2))*AU51)/100),2)+ROUND(((ROUND((ROUND(((AE51-((EU51*1.1)))*AV51*I51),2)*BS51),2)*AU51)/100),2)) -> 551.69 | AA51: 60256402 | AB51: =ROUND((AC51+AD51+AF51),6) -> 23.196 | AC51: =ROUND(((ES51*1)),6) -> 2.34 | AD51: =ROUND(((((ET51*1.1))-((EU51*1.1)))+AE51),6) -> 0.022 | AE51: =ROUND(((EU51*1.1)),6) -> 0 | AF51: =ROUND(((EV51*1.1)),6) -> 20.834 | AG51: =ROUND((AP51),6) -> 0 | AH51: =((EW51*1.1)) -> 1.496 | AI51: =((EX51*1.1)) -> 0 | AJ51: =(AS51) -> 0 | AK51: 21.3 | AL51: 2.34 | AM51: 0.02 | AN51: 0 | AO51: 18.94 | AP51: 0 | AQ51: 1.36 | AR51: 0 | AS51: 0 | AT51: 90 | AU51: 46 | AV51: 1.047 | AW51: 1 | AZ51: 1 | BA51: 54.99 | BB51: 10 | BC51: 10.26 | BH51: 0 | BI51: 2 | BJ51: ТСН-2001.4 Доп. 69, Сб. 10, т. 167, поз. 1 | BM51: 68 | BN51: 58973116 | BO51: 4.10-167-1 | BP51: 1 | BQ51: 40 | BR51: 0 | BS51: 54.99 | BT51: 1 | BU51: 1 | BV51: 1 | BW51: 1 | BX51: 1 | BZ51: 90 | CA51: 46 | CE51: 1566 | CF51: 0 | CG51: 0 | CM51: 0 | CN51: Поправка: Гл.12.Прил.8.п.8. 5_12.00.01.11.003 Наименование: При наличии усложненных условий производства работ (стесненность, сложность складирования и транспортной логистики, наличие в зоне производства работ действующего технологического оборудования или движения технологического транспорта и т.п.) для объектов, расположенных за пределами территории круговой магистральной системы улиц "Садовое кольцо" и за пределами Третьего транспортного кольца города Москвы пунктов "а" и "б", но в пределах Московской кольцевой автомобильной дороги | CO51: 0 | CP51: =(P51+Q51+S51) -> 1223.54 | CQ51: =ROUND((ROUND((AC51*AW51*1),2)*BC51),2) -> 24.01 | CR51: =(ROUND((ROUND((((ET51*1.1))*AV51*1),2)*BB51),2)+ROUND((ROUND(((AE51-((EU51*1.1)))*AV51*1),2)*BS51),2)) -> 0.2 | CS51: =(ROUND((ROUND((((EU51*1.1))*AV51*1),2)*BS51),2)+ROUND((ROUND(((AE51-((EU51*1.1)))*AV51*1),2)*BS51),2)) -> 0 | CT51: =ROUND((ROUND((AF51*AV51*1),2)*BA51),2) -> 1199.33 | CU51: =AG51 -> 0 | CV51: =(AH51*AV51) -> 1.566312 | CW51: =AI51 -> 0 | CX51: =AJ51 -> 0 | CY51: =(ROUND((((S51+ROUND((ROUND((((EU51*1.1))*AV51*1),2)*BS51),2))*AT51)/100),2)+ROUND(((ROUND((ROUND(((AE51-((EU51*1.1)))*AV51*1),2)*BS51),2)*AT51)/100),2)) -> 1079.4 | CZ51: =(ROUND((((S51+ROUND((ROUND((((EU51*1.1))*AV51*1),2)*BS51),2))*AU51)/100),2)+ROUND(((ROUND((ROUND(((AE51-((EU51*1.1)))*AV51*1),2)*BS51),2)*AU51)/100),2)) -> 551.69 | DB51: 12 | DD51: *1 | DE51: *1,1 | DF51: *1,1 | DG51: *1,1 | DI51: *1,1 | DJ51: *1,1 | DN51: 0 | DO51: 0 | DP51: 1 | DQ51: 1 | DU51: 1013 | DV51: 1 ШТ. | DW51: 1 ШТ. | DX51: 1 | EE51: 60088532 | EF51: 40 | EG51: Монтаж оборудования | EH51: 0 | EJ51: 2 | EK51: 68 | EL51: ТСН-2001.4-10. Прокладка и монтаж сетей связи | EM51: ТСН-2001.4-10-1 | EO51: Поправка: Гл.12.Прил.8.п.8. 5_12.00.01.11.003 | EQ51: 0 | ER51: 21.3 | ES51: 2.34 | ET51: 0.02 | EU51: 0 | EV51: 18.94 | EW51: 1.36 | EX51: 0 | EY51: 0 | FQ51: 0 | FR51: 0 | FS51: 0 | FX51: 90 | FY51: 46 | GD51: 1 | GF51: 938017806 | GG51: 2 | GH51: 1 | GI51: 2 | GJ51: 0 | GK51: 0 | GL51: =ROUND(IF(AND(BH51=3,BI51=3,FS51<>0),P51,0),2) -> 0 | GM51: =ROUND(O51+X51+Y51,2)+GX51 -> 2854.63 | GN51: =IF(OR(BI51=0,BI51=1),GM51-GX51,0) -> 0 | GO51: =IF(BI51=2,GM51-GX51,0) -> 2854.63 | GP51: =IF(BI51=4,GM51-GX51,0) -> 0 | GR51: 0 | GS51: 3 | GT51: 0 | GV51: =ROUND((GT51),6) -> 0 | GW51: 1 | GX51: =ROUND(HC51*I51,2) -> 0 | HA51: 0 | HB51: 0 | HC51: =GV51*GW51 -> 0 | HS51: 0 | IK51: 0
A52: 17 | B52: 1 | E52: 12 | F52: КА-6 | G52: Зарядное устройство Sonar SBC-3250 | H52: шт. | I52: 1 | J52: 0 | K52: 1 | O52: =ROUND(CP52,2) -> 5636.02 | P52: =ROUND((ROUND((AC52*I52),2)*BC52),2) -> 5636.02 | Q52: =(ROUND((ROUND(((ET52)*AV52*I52),2)*BB52),2)+ROUND((ROUND(((AE52-(EU52))*AV52*I52),2)*BS52),2)) -> 0 | R52: =(ROUND((ROUND(((EU52)*AV52*I52),2)*BS52),2)+ROUND((ROUND(((AE52-(EU52))*AV52*I52),2)*BS52),2)) -> 0 | S52: =ROUND((ROUND((AF52*AV52*I52),2)*BA52),2) -> 0 | T52: =ROUND(CU52*I52,2) -> 0 | U52: =CV52*I52 -> 0 | V52: =CW52*I52 -> 0 | W52: =ROUND(CX52*I52,2) -> 0 | X52: =(ROUND((((S52+ROUND((ROUND(((EU52)*AV52*I52),2)*BS52),2))*AT52)/100),2)+ROUND(((ROUND((ROUND(((AE52-(EU52))*AV52*I52),2)*BS52),2)*AT52)/100),2)) -> 0 | Y52: =(ROUND((((S52+ROUND((ROUND(((EU52)*AV52*I52),2)*BS52),2))*AU52)/100),2)+ROUND(((ROUND((ROUND(((AE52-(EU52))*AV52*I52),2)*BS52),2)*AU52)/100),2)) -> 0 | AA52: 60256405 | AB52: =ROUND((AC52+AD52+AF52),6) -> 5636.02 | AC52: =ROUND((ES52),6) -> 5636.02 | AD52: =ROUND((((ET52)-(EU52))+AE52),6) -> 0 | AE52: =ROUND((EU52),6) -> 0 | AF52: =ROUND((EV52),6) -> 0 | AG52: =ROUND((AP52),6) -> 0 | AH52: =(EW52) -> 0 | AI52: =(EX52) -> 0 | AJ52: =(AS52) -> 0 | AK52: 5636.02 | AL52: 5636.02 | AM52: 0 | AN52: 0 | AO52: 0 | AP52: 0 | AQ52: 0 | AR52: 0 | AS52: 0 | AT52: 0 | AU52: 0 | AV52: 1 | AW52: 1 | AZ52: 1 | BA52: 1 | BB52: 1 | BC52: 1 | BH52: 3 | BI52: 3 | BM52: 746 | BN52: 0 | BP52: 0 | BQ52: 130 | BR52: 0 | BS52: 1 | BT52: 1 | BU52: 1 | BV52: 1 | BW52: 1 | BX52: 1 | BZ52: 0 | CA52: 0 | CE52: 1566 | CF52: 0 | CG52: 0 | CM52: 0 | CO52: 0 | CP52: =(P52+Q52+S52) -> 5636.02 | CQ52: =ROUND((ROUND((AC52*1),2)*BC52),2) -> 5636.02 | CR52: =(ROUND((ROUND(((ET52)*AV52*1),2)*BB52),2)+ROUND((ROUND(((AE52-(EU52))*AV52*1),2)*BS52),2)) -> 0 | CS52: =(ROUND((ROUND(((EU52)*AV52*1),2)*BS52),2)+ROUND((ROUND(((AE52-(EU52))*AV52*1),2)*BS52),2)) -> 0 | CT52: =ROUND((ROUND((AF52*AV52*1),2)*BA52),2) -> 0 | CU52: =AG52 -> 0 | CV52: =(AH52*AV52) -> 0 | CW52: =AI52 -> 0 | CX52: =AJ52 -> 0 | CY52: =(ROUND((((S52+ROUND((ROUND(((EU52)*AV52*1),2)*BS52),2))*AT52)/100),2)+ROUND(((ROUND((ROUND(((AE52-(EU52))*AV52*1),2)*BS52),2)*AT52)/100),2)) -> 0 | CZ52: =(ROUND((((S52+ROUND((ROUND(((EU52)*AV52*1),2)*BS52),2))*AU52)/100),2)+ROUND(((ROUND((ROUND(((AE52-(EU52))*AV52*1),2)*BS52),2)*AU52)/100),2)) -> 0 | DN52: 0 | DO52: 0 | DP52: 1 | DQ52: 1 | DU52: 1010 | DV52: шт. | DW52: шт. | DX52: 1 | EE52: 60088638 | EF52: 130 | EG52: Сметная стоимость оборудования | EH52: 0 | EJ52: 3 | EK52: 746 | EL52: ТСН-2001.13. Сметная стоимость оборудования | EM52: ТСН-2001.13 | EQ52: 0 | ER52: 0 | ES52: 5636.02 | ET52: 0 | EU52: 0 | EV52: 0 | EW52: 0 | EX52: 0 | EY52: 0 | FQ52: 0 | FR52: =P52 -> 5636.02 | FS52: 0 | FX52: 0 | FY52: 0 | GA52: [49 701 / 1,2 / 7,66] + 3% Трансп + 1,2% Заг.скл | GD52: 1 | GF52: -33836111 | GG52: 2 | GH52: 4 | GI52: -2 | GJ52: 0 | GK52: 0 | GL52: =ROUND(IF(AND(BH52=3,BI52=3,FS52<>0),P52,0),2) -> 0 | GM52: =ROUND(O52+X52+Y52,2)+GX52 -> 5636.02 | GN52: =IF(OR(BI52=0,BI52=1),GM52-GX52,0) -> 0 | GO52: =IF(BI52=2,GM52-GX52,0) -> 0 | GP52: =IF(BI52=4,GM52-GX52,0) -> 0 | GR52: 0 | GS52: 2 | GT52: 0 | GV52: =ROUND((GT52),6) -> 0 | GW52: 1 | GX52: =ROUND(HC52*I52,2) -> 0 | HA52: 0 | HB52: 0 | HC52: =GV52*GW52 -> 0 | HE52: 3 | HF52: 1,2 | HS52: 0 | IK52: 0
A53: 17 | B53: 1 | E53: 12 | F53: КА-6 | G53: Зарядное устройство Sonar SBC-3250 | H53: шт. | I53: 1 | J53: 0 | K53: 1 | O53: =ROUND(CP53,2) -> 43171.91 | P53: =ROUND((ROUND((AC53*I53),2)*BC53),2) -> 43171.91 | Q53: =(ROUND((ROUND(((ET53)*AV53*I53),2)*BB53),2)+ROUND((ROUND(((AE53-(EU53))*AV53*I53),2)*BS53),2)) -> 0 | R53: =(ROUND((ROUND(((EU53)*AV53*I53),2)*BS53),2)+ROUND((ROUND(((AE53-(EU53))*AV53*I53),2)*BS53),2)) -> 0 | S53: =ROUND((ROUND((AF53*AV53*I53),2)*BA53),2) -> 0 | T53: =ROUND(CU53*I53,2) -> 0 | U53: =CV53*I53 -> 0 | V53: =CW53*I53 -> 0 | W53: =ROUND(CX53*I53,2) -> 0 | X53: =(ROUND((((S53+ROUND((ROUND(((EU53)*AV53*I53),2)*BS53),2))*AT53)/100),2)+ROUND(((ROUND((ROUND(((AE53-(EU53))*AV53*I53),2)*BS53),2)*AT53)/100),2)) -> 0 | Y53: =(ROUND((((S53+ROUND((ROUND(((EU53)*AV53*I53),2)*BS53),2))*AU53)/100),2)+ROUND(((ROUND((ROUND(((AE53-(EU53))*AV53*I53),2)*BS53),2)*AU53)/100),2)) -> 0 | AA53: 60256402 | AB53: =ROUND((AC53+AD53+AF53),6) -> 5636.02 | AC53: =ROUND((ES53),6) -> 5636.02 | AD53: =ROUND((((ET53)-(EU53))+AE53),6) -> 0 | AE53: =ROUND((EU53),6) -> 0 | AF53: =ROUND((EV53),6) -> 0 | AG53: =ROUND((AP53),6) -> 0 | AH53: =(EW53) -> 0 | AI53: =(EX53) -> 0 | AJ53: =(AS53) -> 0 | AK53: 5636.02 | AL53: 5636.02 | AM53: 0 | AN53: 0 | AO53: 0 | AP53: 0 | AQ53: 0 | AR53: 0 | AS53: 0 | AT53: 0 | AU53: 0 | AV53: 1 | AW53: 1 | AZ53: 1 | BA53: 1 | BB53: 1 | BC53: 7.66 | BH53: 3 | BI53: 3 | BM53: 746 | BN53: 0 | BP53: 0 | BQ53: 130 | BR53: 0 | BS53: 1 | BT53: 1 | BU53: 1 | BV53: 1 | BW53: 1 | BX53: 1 | BZ53: 0 | CA53: 0 | CE53: 1566 | CF53: 0 | CG53: 0 | CM53: 0 | CO53: 0 | CP53: =(P53+Q53+S53) -> 43171.91 | CQ53: =ROUND((ROUND((AC53*1),2)*BC53),2) -> 43171.91 | CR53: =(ROUND((ROUND(((ET53)*AV53*1),2)*BB53),2)+ROUND((ROUND(((AE53-(EU53))*AV53*1),2)*BS53),2)) -> 0 | CS53: =(ROUND((ROUND(((EU53)*AV53*1),2)*BS53),2)+ROUND((ROUND(((AE53-(EU53))*AV53*1),2)*BS53),2)) -> 0 | CT53: =ROUND((ROUND((AF53*AV53*1),2)*BA53),2) -> 0 | CU53: =AG53 -> 0 | CV53: =(AH53*AV53) -> 0 | CW53: =AI53 -> 0 | CX53: =AJ53 -> 0 | CY53: =(ROUND((((S53+ROUND((ROUND(((EU53)*AV53*1),2)*BS53),2))*AT53)/100),2)+ROUND(((ROUND((ROUND(((AE53-(EU53))*AV53*1),2)*BS53),2)*AT53)/100),2)) -> 0 | CZ53: =(ROUND((((S53+ROUND((ROUND(((EU53)*AV53*1),2)*BS53),2))*AU53)/100),2)+ROUND(((ROUND((ROUND(((AE53-(EU53))*AV53*1),2)*BS53),2)*AU53)/100),2)) -> 0 | DN53: 0 | DO53: 0 | DP53: 1 | DQ53: 1 | DU53: 1010 | DV53: шт. | DW53: шт. | DX53: 1 | EE53: 60088638 | EF53: 130 | EG53: Сметная стоимость оборудования | EH53: 0 | EJ53: 3 | EK53: 746 | EL53: ТСН-2001.13. Сметная стоимость оборудования | EM53: ТСН-2001.13 | EQ53: 0 | ER53: 5636.02 | ES53: 5636.02 | ET53: 0 | EU53: 0 | EV53: 0 | EW53: 0 | EX53: 0 | EY53: 0 | EZ53: 5 | FC53: 1 | FD53: 18 | FF53: 49701 | FQ53: 0 | FR53: =P53 -> 43171.91 | FS53: 0 | FX53: 0 | FY53: 0 | GA53: [49 701 / 1,2 / 7,66] + 3% Трансп + 1,2% Заг.скл | GD53: 1 | GF53: -33836111 | GG53: 2 | GH53: 3 | GI53: 5 | GJ53: 0 | GK53: 0 | GL53: =ROUND(IF(AND(BH53=3,BI53=3,FS53<>0),P53,0),2) -> 0 | GM53: =ROUND(O53+X53+Y53,2)+GX53 -> 43171.91 | GN53: =IF(OR(BI53=0,BI53=1),GM53-GX53,0) -> 0 | GO53: =IF(BI53=2,GM53-GX53,0) -> 0 | GP53: =IF(BI53=4,GM53-GX53,0) -> 0 | GR53: 1 | GS53: 1 | GT53: 0 | GV53: =ROUND((GT53),6) -> 0 | GW53: 1 | GX53: =ROUND(HC53*I53,2) -> 0 | HA53: 0 | HB53: 0 | HC53: =GV53*GW53 -> 0 | HE53: 3 | HF53: 1,2 | HS53: 0 | IK53: 0
A54: 17 | B54: 1 | C54: =ROW(SmtRes!A48) -> 48 | D54: =ROW(EtalonRes!A61) -> 61 | E54: 13 | F54: 4.11-3-1 | G54: Установка прибора массой до 5 кг на металлоконструкциях или щитах | H54: 1 ШТ. | I54: 1 | J54: 0 | K54: 1 | O54: =ROUND(CP54,2) -> 7.77 | P54: =ROUND((ROUND((AC54*AW54*I54),2)*BC54),2) -> 0 | Q54: =(ROUND((ROUND((((ET54*1.1))*AV54*I54),2)*BB54),2)+ROUND((ROUND(((AE54-((EU54*1.1)))*AV54*I54),2)*BS54),2)) -> 0 | R54: =(ROUND((ROUND((((EU54*1.1))*AV54*I54),2)*BS54),2)+ROUND((ROUND(((AE54-((EU54*1.1)))*AV54*I54),2)*BS54),2)) -> 0 | S54: =ROUND((ROUND((AF54*AV54*I54),2)*BA54),2) -> 7.77 | T54: =ROUND(CU54*I54,2) -> 0 | U54: =CV54*I54 -> 0.598884 | V54: =CW54*I54 -> 0 | W54: =ROUND(CX54*I54,2) -> 0 | X54: =(ROUND((((S54+ROUND((ROUND((((EU54*1.1))*AV54*I54),2)*BS54),2))*AT54)/100),2)+ROUND(((ROUND((ROUND(((AE54-((EU54*1.1)))*AV54*I54),2)*BS54),2)*AT54)/100),2)) -> 6.99 | Y54: =(ROUND((((S54+ROUND((ROUND((((EU54*1.1))*AV54*I54),2)*BS54),2))*AU54)/100),2)+ROUND(((ROUND((ROUND(((AE54-((EU54*1.1)))*AV54*I54),2)*BS54),2)*AU54)/100),2)) -> 3.57 | AA54: 60256405 | AB54: =ROUND((AC54+AD54+AF54),6) -> 7.425 | AC54: =ROUND(((ES54*1)),6) -> 0 | AD54: =ROUND(((((ET54*1.1))-((EU54*1.1)))+AE54),6) -> 0 | AE54: =ROUND(((EU54*1.1)),6) -> 0 | AF54: =ROUND(((EV54*1.1)),6) -> 7.425 | AG54: =ROUND((AP54),6) -> 0 | AH54: =((EW54*1.1)) -> 0.572 | AI54: =((EX54*1.1)) -> 0 | AJ54: =(AS54) -> 0 | AK54: 6.75 | AL54: 0 | AM54: 0 | AN54: 0 | AO54: 6.75 | AP54: 0 | AQ54: 0.52 | AR54: 0 | AS54: 0 | AT54: 90 | AU54: 46 | AV54: 1.047 | AW54: 1 | AZ54: 1 | BA54: 1 | BB54: 1 | BC54: 1 | BH54: 0 | BI54: 2 | BJ54: ТСН-2001.4 Доп. 67, Сб. 11, т. 3, поз. 1 | BM54: 72 | BN54: 58973116 | BO54: 4.11-3-1 | BP54: 1 | BQ54: 40 | BR54: 0 | BS54: 1 | BT54: 1 | BU54: 1 | BV54: 1 | BW54: 1 | BX54: 1 | BZ54: 90 | CA54: 46 | CE54: 1566 | CF54: 0 | CG54: 0 | CM54: 0 | CN54: Поправка: Гл.12.Прил.8.п.8. 5_12.00.01.11.003 Наименование: При наличии усложненных условий производства работ (стесненность, сложность складирования и транспортной логистики, наличие в зоне производства работ действующего технологического оборудования или движения технологического транспорта и т.п.) для объектов, расположенных за пределами территории круговой магистральной системы улиц "Садовое кольцо" и за пределами Третьего транспортного кольца города Москвы пунктов "а" и "б", но в пределах Московской кольцевой автомобильной дороги | CO54: 0 | CP54: =(P54+Q54+S54) -> 7.77 | CQ54: =ROUND((ROUND((AC54*AW54*1),2)*BC54),2) -> 0 | CR54: =(ROUND((ROUND((((ET54*1.1))*AV54*1),2)*BB54),2)+ROUND((ROUND(((AE54-((EU54*1.1)))*AV54*1),2)*BS54),2)) -> 0 | CS54: =(ROUND((ROUND((((EU54*1.1))*AV54*1),2)*BS54),2)+ROUND((ROUND(((AE54-((EU54*1.1)))*AV54*1),2)*BS54),2)) -> 0 | CT54: =ROUND((ROUND((AF54*AV54*1),2)*BA54),2) -> 7.77 | CU54: =AG54 -> 0 | CV54: =(AH54*AV54) -> 0.598884 | CW54: =AI54 -> 0 | CX54: =AJ54 -> 0 | CY54: =(ROUND((((S54+ROUND((ROUND((((EU54*1.1))*AV54*1),2)*BS54),2))*AT54)/100),2)+ROUND(((ROUND((ROUND(((AE54-((EU54*1.1)))*AV54*1),2)*BS54),2)*AT54)/100),2)) -> 6.99 | CZ54: =(ROUND((((S54+ROUND((ROUND((((EU54*1.1))*AV54*1),2)*BS54),2))*AU54)/100),2)+ROUND(((ROUND((ROUND(((AE54-((EU54*1.1)))*AV54*1),2)*BS54),2)*AU54)/100),2)) -> 3.57 | DB54: 13 | DD54: *1 | DE54: *1,1 | DF54: *1,1 | DG54: *1,1 | DI54: *1,1 | DJ54: *1,1 | DN54: 0 | DO54: 0 | DP54: 1 | DQ54: 1 | DU54: 1013 | DV54: 1 ШТ. | DW54: 1 ШТ. | DX54: 1 | EE54: 60088536 | EF54: 40 | EG54: Монтаж оборудования | EH54: 0 | EJ54: 2 | EK54: 72 | EL54: ТСН-2001.4-11. Приборы и средства автоматизации и вычислительной техники | EM54: ТСН-2001.4-11-1 | EO54: Поправка: Гл.12.Прил.8.п.8. 5_12.00.01.11.003 | EQ54: 0 | ER54: 6.75 | ES54: 0 | ET54: 0 | EU54: 0 | EV54: 6.75 | EW54: 0.52 | EX54: 0 | EY54: 0 | FQ54: 0 | FR54: 0 | FS54: 0 | FX54: 90 | FY54: 46 | GD54: 1 | GF54: 338415528 | GG54: 2 | GH54: 1 | GI54: 2 | GJ54: 0 | GK54: 0 | GL54: =ROUND(IF(AND(BH54=3,BI54=3,FS54<>0),P54,0),2) -> 0 | GM54: =ROUND(O54+X54+Y54,2)+GX54 -> 18.33 | GN54: =IF(OR(BI54=0,BI54=1),GM54-GX54,0) -> 0 | GO54: =IF(BI54=2,GM54-GX54,0) -> 18.33 | GP54: =IF(BI54=4,GM54-GX54,0) -> 0 | GR54: 0 | GS54: 3 | GT54: 0 | GV54: =ROUND((GT54),6) -> 0 | GW54: 1 | GX54: =ROUND(HC54*I54,2) -> 0 | HA54: 0 | HB54: 0 | HC54: =GV54*GW54 -> 0 | HS54: 0 | IK54: 0
A55: 17 | B55: 1 | C55: =ROW(SmtRes!A50) -> 50 | D55: =ROW(EtalonRes!A64) -> 64 | E55: 13 | F55: 4.11-3-1 | G55: Установка прибора массой до 5 кг на металлоконструкциях или щитах | H55: 1 ШТ. | I55: 1 | J55: 0 | K55: 1 | O55: =ROUND(CP55,2) -> 427.27 | P55: =ROUND((ROUND((AC55*AW55*I55),2)*BC55),2) -> 0 | Q55: =(ROUND((ROUND((((ET55*1.1))*AV55*I55),2)*BB55),2)+ROUND((ROUND(((AE55-((EU55*1.1)))*AV55*I55),2)*BS55),2)) -> 0 | R55: =(ROUND((ROUND((((EU55*1.1))*AV55*I55),2)*BS55),2)+ROUND((ROUND(((AE55-((EU55*1.1)))*AV55*I55),2)*BS55),2)) -> 0 | S55: =ROUND((ROUND((AF55*AV55*I55),2)*BA55),2) -> 427.27 | T55: =ROUND(CU55*I55,2) -> 0 | U55: =CV55*I55 -> 0.598884 | V55: =CW55*I55 -> 0 | W55: =ROUND(CX55*I55,2) -> 0 | X55: =(ROUND((((S55+ROUND((ROUND((((EU55*1.1))*AV55*I55),2)*BS55),2))*AT55)/100),2)+ROUND(((ROUND((ROUND(((AE55-((EU55*1.1)))*AV55*I55),2)*BS55),2)*AT55)/100),2)) -> 384.54 | Y55: =(ROUND((((S55+ROUND((ROUND((((EU55*1.1))*AV55*I55),2)*BS55),2))*AU55)/100),2)+ROUND(((ROUND((ROUND(((AE55-((EU55*1.1)))*AV55*I55),2)*BS55),2)*AU55)/100),2)) -> 196.54 | AA55: 60256402 | AB55: =ROUND((AC55+AD55+AF55),6) -> 7.425 | AC55: =ROUND(((ES55*1)),6) -> 0 | AD55: =ROUND(((((ET55*1.1))-((EU55*1.1)))+AE55),6) -> 0 | AE55: =ROUND(((EU55*1.1)),6) -> 0 | AF55: =ROUND(((EV55*1.1)),6) -> 7.425 | AG55: =ROUND((AP55),6) -> 0 | AH55: =((EW55*1.1)) -> 0.572 | AI55: =((EX55*1.1)) -> 0 | AJ55: =(AS55) -> 0 | AK55: 6.75 | AL55: 0 | AM55: 0 | AN55: 0 | AO55: 6.75 | AP55: 0 | AQ55: 0.52 | AR55: 0 | AS55: 0 | AT55: 90 | AU55: 46 | AV55: 1.047 | AW55: 1 | AZ55: 1 | BA55: 54.99 | BB55: 1 | BC55: 1 | BH55: 0 | BI55: 2 | BJ55: ТСН-2001.4 Доп. 67, Сб. 11, т. 3, поз. 1 | BM55: 72 | BN55: 58973116 | BO55: 4.11-3-1 | BP55: 1 | BQ55: 40 | BR55: 0 | BS55: 54.99 | BT55: 1 | BU55: 1 | BV55: 1 | BW55: 1 | BX55: 1 | BZ55: 90 | CA55: 46 | CE55: 1566 | CF55: 0 | CG55: 0 | CM55: 0 | CN55: Поправка: Гл.12.Прил.8.п.8. 5_12.00.01.11.003 Наименование: При наличии усложненных условий производства работ (стесненность, сложность складирования и транспортной логистики, наличие в зоне производства работ действующего технологического оборудования или движения технологического транспорта и т.п.) для объектов, расположенных за пределами территории круговой магистральной системы улиц "Садовое кольцо" и за пределами Третьего транспортного кольца города Москвы пунктов "а" и "б", но в пределах Московской кольцевой автомобильной дороги | CO55: 0 | CP55: =(P55+Q55+S55) -> 427.27 | CQ55: =ROUND((ROUND((AC55*AW55*1),2)*BC55),2) -> 0 | CR55: =(ROUND((ROUND((((ET55*1.1))*AV55*1),2)*BB55),2)+ROUND((ROUND(((AE55-((EU55*1.1)))*AV55*1),2)*BS55),2)) -> 0 | CS55: =(ROUND((ROUND((((EU55*1.1))*AV55*1),2)*BS55),2)+ROUND((ROUND(((AE55-((EU55*1.1)))*AV55*1),2)*BS55),2)) -> 0 | CT55: =ROUND((ROUND((AF55*AV55*1),2)*BA55),2) -> 427.27 | CU55: =AG55 -> 0 | CV55: =(AH55*AV55) -> 0.598884 | CW55: =AI55 -> 0 | CX55: =AJ55 -> 0 | CY55: =(ROUND((((S55+ROUND((ROUND((((EU55*1.1))*AV55*1),2)*BS55),2))*AT55)/100),2)+ROUND(((ROUND((ROUND(((AE55-((EU55*1.1)))*AV55*1),2)*BS55),2)*AT55)/100),2)) -> 384.54 | CZ55: =(ROUND((((S55+ROUND((ROUND((((EU55*1.1))*AV55*1),2)*BS55),2))*AU55)/100),2)+ROUND(((ROUND((ROUND(((AE55-((EU55*1.1)))*AV55*1),2)*BS55),2)*AU55)/100),2)) -> 196.54 | DB55: 14 | DD55: *1 | DE55: *1,1 | DF55: *1,1 | DG55: *1,1 | DI55: *1,1 | DJ55: *1,1 | DN55: 0 | DO55: 0 | DP55: 1 | DQ55: 1 | DU55: 1013 | DV55: 1 ШТ. | DW55: 1 ШТ. | DX55: 1 | EE55: 60088536 | EF55: 40 | EG55: Монтаж оборудования | EH55: 0 | EJ55: 2 | EK55: 72 | EL55: ТСН-2001.4-11. Приборы и средства автоматизации и вычислительной техники | EM55: ТСН-2001.4-11-1 | EO55: Поправка: Гл.12.Прил.8.п.8. 5_12.00.01.11.003 | EQ55: 0 | ER55: 6.75 | ES55: 0 | ET55: 0 | EU55: 0 | EV55: 6.75 | EW55: 0.52 | EX55: 0 | EY55: 0 | FQ55: 0 | FR55: 0 | FS55: 0 | FX55: 90 | FY55: 46 | GD55: 1 | GF55: 338415528 | GG55: 2 | GH55: 1 | GI55: 2 | GJ55: 0 | GK55: 0 | GL55: =ROUND(IF(AND(BH55=3,BI55=3,FS55<>0),P55,0),2) -> 0 | GM55: =ROUND(O55+X55+Y55,2)+GX55 -> 1008.35 | GN55: =IF(OR(BI55=0,BI55=1),GM55-GX55,0) -> 0 | GO55: =IF(BI55=2,GM55-GX55,0) -> 1008.35 | GP55: =IF(BI55=4,GM55-GX55,0) -> 0 | GR55: 0 | GS55: 3 | GT55: 0 | GV55: =ROUND((GT55),6) -> 0 | GW55: 1 | GX55: =ROUND(HC55*I55,2) -> 0 | HA55: 0 | HB55: 0 | HC55: =GV55*GW55 -> 0 | HS55: 0 | IK55: 0
A56: 18 | B56: 1 | C56: 48 | E56: 13,1 | F56: 1.1-1-8146 | G56: Болты стальные оцинкованные с шестигранной головкой, с полной резьбой, с гайкой оцинкованной, М6, длина от 12 до 60 мм | H56: кг | I56: =I54*J56 -> 0.035 | J56: 0.035 | K56: 0.035 | O56: =ROUND(CP56,2) -> 1.09 | P56: =ROUND((ROUND((AC56*AW56*I56),2)*BC56),2) -> 1.09 | Q56: =(ROUND((ROUND(((ET56)*AV56*I56),2)*BB56),2)+ROUND((ROUND(((AE56-(EU56))*AV56*I56),2)*BS56),2)) -> 0 | R56: =(ROUND((ROUND(((EU56)*AV56*I56),2)*BS56),2)+ROUND((ROUND(((AE56-(EU56))*AV56*I56),2)*BS56),2)) -> 0 | S56: =ROUND((ROUND((AF56*AV56*I56),2)*BA56),2) -> 0 | T56: =ROUND(CU56*I56,2) -> 0 | U56: =CV56*I56 -> 0 | V56: =CW56*I56 -> 0 | W56: =ROUND(CX56*I56,2) -> 0 | X56: =(ROUND((((S56+ROUND((ROUND(((EU56)*AV56*I56),2)*BS56),2))*AT56)/100),2)+ROUND(((ROUND((ROUND(((AE56-(EU56))*AV56*I56),2)*BS56),2)*AT56)/100),2)) -> 0 | Y56: =(ROUND((((S56+ROUND((ROUND(((EU56)*AV56*I56),2)*BS56),2))*AU56)/100),2)+ROUND(((ROUND((ROUND(((AE56-(EU56))*AV56*I56),2)*BS56),2)*AU56)/100),2)) -> 0 | AA56: 60256405 | AB56: =ROUND((AC56+AD56+AF56),6) -> 31.08 | AC56: =ROUND((ES56),6) -> 31.08 | AD56: =ROUND((((ET56)-(EU56))+AE56),6) -> 0 | AE56: =ROUND((EU56),6) -> 0 | AF56: =ROUND((EV56),6) -> 0 | AG56: =ROUND((AP56),6) -> 0 | AH56: =(EW56) -> 0 | AI56: =(EX56) -> 0 | AJ56: =(AS56) -> 0 | AK56: 31.08 | AL56: 31.08 | AM56: 0 | AN56: 0 | AO56: 0 | AP56: 0 | AQ56: 0 | AR56: 0 | AS56: 0 | AT56: 90 | AU56: 46 | AV56: 1 | AW56: 1 | AZ56: 1 | BA56: 1 | BB56: 1 | BC56: 1 | BH56: 3 | BI56: 2 | BJ56: ТСН-2001.1 Доп. 79, Р. 1, о. 1, поз. 8146 | BM56: 72 | BN56: 58973116 | BP56: 0 | BQ56: 40 | BR56: 0 | BS56: 1 | BT56: 1 | BU56: 1 | BV56: 1 | BW56: 1 | BX56: 1 | BZ56: 90 | CA56: 46 | CE56: 1566 | CF56: 0 | CG56: 0 | CM56: 0 | CN56: Поправка: Гл.12.Прил.8.п.8. 5_12.00.01.11.003 Наименование: При наличии усложненных условий производства работ (стесненность, сложность складирования и транспортной логистики, наличие в зоне производства работ действующего технологического оборудования или движения технологического транспорта и т.п.) для объектов, расположенных за пределами территории круговой магистральной системы улиц "Садовое кольцо" и за пределами Третьего транспортного кольца города Москвы пунктов "а" и "б", но в пределах Московской кольцевой автомобильной дороги | CO56: 0 | CP56: =(P56+Q56+S56) -> 1.09 | CQ56: =ROUND((ROUND((AC56*AW56*1),2)*BC56),2) -> 31.08 | CR56: =(ROUND((ROUND(((ET56)*AV56*1),2)*BB56),2)+ROUND((ROUND(((AE56-(EU56))*AV56*1),2)*BS56),2)) -> 0 | CS56: =(ROUND((ROUND(((EU56)*AV56*1),2)*BS56),2)+ROUND((ROUND(((AE56-(EU56))*AV56*1),2)*BS56),2)) -> 0 | CT56: =ROUND((ROUND((AF56*AV56*1),2)*BA56),2) -> 0 | CU56: =AG56 -> 0 | CV56: =(AH56*AV56) -> 0 | CW56: =AI56 -> 0 | CX56: =AJ56 -> 0 | CY56: =(ROUND((((S56+ROUND((ROUND(((EU56)*AV56*1),2)*BS56),2))*AT56)/100),2)+ROUND(((ROUND((ROUND(((AE56-(EU56))*AV56*1),2)*BS56),2)*AT56)/100),2)) -> 0 | CZ56: =(ROUND((((S56+ROUND((ROUND(((EU56)*AV56*1),2)*BS56),2))*AU56)/100),2)+ROUND(((ROUND((ROUND(((AE56-(EU56))*AV56*1),2)*BS56),2)*AU56)/100),2)) -> 0 | DN56: 0 | DO56: 0 | DP56: 1 | DQ56: 1 | DU56: 1009 | DV56: кг | DW56: кг | DX56: 1 | EE56: 60088536 | EF56: 40 | EG56: Монтаж оборудования | EH56: 0 | EJ56: 2 | EK56: 72 | EL56: ТСН-2001.4-11. Приборы и средства автоматизации и вычислительной техники | EM56: ТСН-2001.4-11-1 | EO56: Поправка: Гл.12.Прил.8.п.8. 5_12.00.01.11.003 | EQ56: 0 | ER56: 31.08 | ES56: 31.08 | ET56: 0 | EU56: 0 | EV56: 0 | EW56: 0 | EX56: 0 | FQ56: 0 | FR56: 0 | FS56: 0 | FX56: 90 | FY56: 46 | GD56: 1 | GF56: 1143487818 | GG56: 2 | GH56: 1 | GI56: -2 | GJ56: 0 | GK56: 0 | GL56: =ROUND(IF(AND(BH56=3,BI56=3,FS56<>0),P56,0),2) -> 0 | GM56: =ROUND(O56+X56+Y56,2)+GX56 -> 1.09 | GN56: =IF(OR(BI56=0,BI56=1),GM56-GX56,0) -> 0 | GO56: =IF(BI56=2,GM56-GX56,0) -> 1.09 | GP56: =IF(BI56=4,GM56-GX56,0) -> 0 | GR56: 0 | GS56: 3 | GT56: 0 | GV56: =ROUND((GT56),6) -> 0 | GW56: 1 | GX56: =ROUND(HC56*I56,2) -> 0 | HA56: 0 | HB56: 0 | HC56: =GV56*GW56 -> 0 | HM56: *1 | HS56: 0 | IK56: 0
A57: 18 | B57: 1 | C57: 50 | E57: 13,1 | F57: 1.1-1-8146 | G57: Болты стальные оцинкованные с шестигранной головкой, с полной резьбой, с гайкой оцинкованной, М6, длина от 12 до 60 мм | H57: кг | I57: =I55*J57 -> 0.035 | J57: 0.035 | K57: 0.035 | O57: =ROUND(CP57,2) -> 5.58 | P57: =ROUND((ROUND((AC57*AW57*I57),2)*BC57),2) -> 5.58 | Q57: =(ROUND((ROUND(((ET57)*AV57*I57),2)*BB57),2)+ROUND((ROUND(((AE57-(EU57))*AV57*I57),2)*BS57),2)) -> 0 | R57: =(ROUND((ROUND(((EU57)*AV57*I57),2)*BS57),2)+ROUND((ROUND(((AE57-(EU57))*AV57*I57),2)*BS57),2)) -> 0 | S57: =ROUND((ROUND((AF57*AV57*I57),2)*BA57),2) -> 0 | T57: =ROUND(CU57*I57,2) -> 0 | U57: =CV57*I57 -> 0 | V57: =CW57*I57 -> 0 | W57: =ROUND(CX57*I57,2) -> 0 | X57: =(ROUND((((S57+ROUND((ROUND(((EU57)*AV57*I57),2)*BS57),2))*AT57)/100),2)+ROUND(((ROUND((ROUND(((AE57-(EU57))*AV57*I57),2)*BS57),2)*AT57)/100),2)) -> 0 | Y57: =(ROUND((((S57+ROUND((ROUND(((EU57)*AV57*I57),2)*BS57),2))*AU57)/100),2)+ROUND(((ROUND((ROUND(((AE57-(EU57))*AV57*I57),2)*BS57),2)*AU57)/100),2)) -> 0 | AA57: 60256402 | AB57: =ROUND((AC57+AD57+AF57),6) -> 31.08 | AC57: =ROUND((ES57),6) -> 31.08 | AD57: =ROUND((((ET57)-(EU57))+AE57),6) -> 0 | AE57: =ROUND((EU57),6) -> 0 | AF57: =ROUND((EV57),6) -> 0 | AG57: =ROUND((AP57),6) -> 0 | AH57: =(EW57) -> 0 | AI57: =(EX57) -> 0 | AJ57: =(AS57) -> 0 | AK57: 31.08 | AL57: 31.08 | AM57: 0 | AN57: 0 | AO57: 0 | AP57: 0 | AQ57: 0 | AR57: 0 | AS57: 0 | AT57: 90 | AU57: 46 | AV57: 1 | AW57: 1 | AZ57: 1 | BA57: 1 | BB57: 1 | BC57: 5.12 | BH57: 3 | BI57: 2 | BJ57: ТСН-2001.1 Доп. 79, Р. 1, о. 1, поз. 8146 | BM57: 72 | BN57: 58973116 | BO57: 1.1-1-8146 | BP57: 1 | BQ57: 40 | BR57: 0 | BS57: 1 | BT57: 1 | BU57: 1 | BV57: 1 | BW57: 1 | BX57: 1 | BZ57: 90 | CA57: 46 | CE57: 1566 | CF57: 0 | CG57: 0 | CM57: 0 | CN57: Поправка: Гл.12.Прил.8.п.8. 5_12.00.01.11.003 Наименование: При наличии усложненных условий производства работ (стесненность, сложность складирования и транспортной логистики, наличие в зоне производства работ действующего технологического оборудования или движения технологического транспорта и т.п.) для объектов, расположенных за пределами территории круговой магистральной системы улиц "Садовое кольцо" и за пределами Третьего транспортного кольца города Москвы пунктов "а" и "б", но в пределах Московской кольцевой автомобильной дороги | CO57: 0 | CP57: =(P57+Q57+S57) -> 5.58 | CQ57: =ROUND((ROUND((AC57*AW57*1),2)*BC57),2) -> 159.13 | CR57: =(ROUND((ROUND(((ET57)*AV57*1),2)*BB57),2)+ROUND((ROUND(((AE57-(EU57))*AV57*1),2)*BS57),2)) -> 0 | CS57: =(ROUND((ROUND(((EU57)*AV57*1),2)*BS57),2)+ROUND((ROUND(((AE57-(EU57))*AV57*1),2)*BS57),2)) -> 0 | CT57: =ROUND((ROUND((AF57*AV57*1),2)*BA57),2) -> 0 | CU57: =AG57 -> 0 | CV57: =(AH57*AV57) -> 0 | CW57: =AI57 -> 0 | CX57: =AJ57 -> 0 | CY57: =(ROUND((((S57+ROUND((ROUND(((EU57)*AV57*1),2)*BS57),2))*AT57)/100),2)+ROUND(((ROUND((ROUND(((AE57-(EU57))*AV57*1),2)*BS57),2)*AT57)/100),2)) -> 0 | CZ57: =(ROUND((((S57+ROUND((ROUND(((EU57)*AV57*1),2)*BS57),2))*AU57)/100),2)+ROUND(((ROUND((ROUND(((AE57-(EU57))*AV57*1),2)*BS57),2)*AU57)/100),2)) -> 0 | DN57: 0 | DO57: 0 | DP57: 1 | DQ57: 1 | DU57: 1009 | DV57: кг | DW57: кг | DX57: 1 | EE57: 60088536 | EF57: 40 | EG57: Монтаж оборудования | EH57: 0 | EJ57: 2 | EK57: 72 | EL57: ТСН-2001.4-11. Приборы и средства автоматизации и вычислительной техники | EM57: ТСН-2001.4-11-1 | EO57: Поправка: Гл.12.Прил.8.п.8. 5_12.00.01.11.003 | EQ57: 0 | ER57: 31.08 | ES57: 31.08 | ET57: 0 | EU57: 0 | EV57: 0 | EW57: 0 | EX57: 0 | FQ57: 0 | FR57: 0 | FS57: 0 | FX57: 90 | FY57: 46 | GD57: 1 | GF57: 1143487818 | GG57: 2 | GH57: 1 | GI57: 2 | GJ57: 0 | GK57: 0 | GL57: =ROUND(IF(AND(BH57=3,BI57=3,FS57<>0),P57,0),2) -> 0 | GM57: =ROUND(O57+X57+Y57,2)+GX57 -> 5.58 | GN57: =IF(OR(BI57=0,BI57=1),GM57-GX57,0) -> 0 | GO57: =IF(BI57=2,GM57-GX57,0) -> 5.58 | GP57: =IF(BI57=4,GM57-GX57,0) -> 0 | GR57: 0 | GS57: 3 | GT57: 0 | GV57: =ROUND((GT57),6) -> 0 | GW57: 1 | GX57: =ROUND(HC57*I57,2) -> 0 | HA57: 0 | HB57: 0 | HC57: =GV57*GW57 -> 0 | HM57: *1 | HS57: 0 | IK57: 0
A58: 17 | B58: 1 | E58: 14 | F58: КА-7 | G58: Блок АКБ 24В. Заменяемые АКБ 12В, 5Ач, количество элементов в корпусе - 10 шт. Sonar SBB-2425 | H58: шт. | I58: 1 | J58: 0 | K58: 1 | O58: =ROUND(CP58,2) -> 5613.23 | P58: =ROUND((ROUND((AC58*I58),2)*BC58),2) -> 5613.23 | Q58: =(ROUND((ROUND(((ET58)*AV58*I58),2)*BB58),2)+ROUND((ROUND(((AE58-(EU58))*AV58*I58),2)*BS58),2)) -> 0 | R58: =(ROUND((ROUND(((EU58)*AV58*I58),2)*BS58),2)+ROUND((ROUND(((AE58-(EU58))*AV58*I58),2)*BS58),2)) -> 0 | S58: =ROUND((ROUND((AF58*AV58*I58),2)*BA58),2) -> 0 | T58: =ROUND(CU58*I58,2) -> 0 | U58: =CV58*I58 -> 0 | V58: =CW58*I58 -> 0 | W58: =ROUND(CX58*I58,2) -> 0 | X58: =(ROUND((((S58+ROUND((ROUND(((EU58)*AV58*I58),2)*BS58),2))*AT58)/100),2)+ROUND(((ROUND((ROUND(((AE58-(EU58))*AV58*I58),2)*BS58),2)*AT58)/100),2)) -> 0 | Y58: =(ROUND((((S58+ROUND((ROUND(((EU58)*AV58*I58),2)*BS58),2))*AU58)/100),2)+ROUND(((ROUND((ROUND(((AE58-(EU58))*AV58*I58),2)*BS58),2)*AU58)/100),2)) -> 0 | AA58: 60256405 | AB58: =ROUND((AC58+AD58+AF58),6) -> 5613.23 | AC58: =ROUND((ES58),6) -> 5613.23 | AD58: =ROUND((((ET58)-(EU58))+AE58),6) -> 0 | AE58: =ROUND((EU58),6) -> 0 | AF58: =ROUND((EV58),6) -> 0 | AG58: =ROUND((AP58),6) -> 0 | AH58: =(EW58) -> 0 | AI58: =(EX58) -> 0 | AJ58: =(AS58) -> 0 | AK58: 5613.23 | AL58: 5613.23 | AM58: 0 | AN58: 0 | AO58: 0 | AP58: 0 | AQ58: 0 | AR58: 0 | AS58: 0 | AT58: 0 | AU58: 0 | AV58: 1 | AW58: 1 | AZ58: 1 | BA58: 1 | BB58: 1 | BC58: 1 | BH58: 3 | BI58: 3 | BM58: 746 | BN58: 0 | BP58: 0 | BQ58: 130 | BR58: 0 | BS58: 1 | BT58: 1 | BU58: 1 | BV58: 1 | BW58: 1 | BX58: 1 | BZ58: 0 | CA58: 0 | CE58: 1566 | CF58: 0 | CG58: 0 | CM58: 0 | CO58: 0 | CP58: =(P58+Q58+S58) -> 5613.23 | CQ58: =ROUND((ROUND((AC58*1),2)*BC58),2) -> 5613.23 | CR58: =(ROUND((ROUND(((ET58)*AV58*1),2)*BB58),2)+ROUND((ROUND(((AE58-(EU58))*AV58*1),2)*BS58),2)) -> 0 | CS58: =(ROUND((ROUND(((EU58)*AV58*1),2)*BS58),2)+ROUND((ROUND(((AE58-(EU58))*AV58*1),2)*BS58),2)) -> 0 | CT58: =ROUND((ROUND((AF58*AV58*1),2)*BA58),2) -> 0 | CU58: =AG58 -> 0 | CV58: =(AH58*AV58) -> 0 | CW58: =AI58 -> 0 | CX58: =AJ58 -> 0 | CY58: =(ROUND((((S58+ROUND((ROUND(((EU58)*AV58*1),2)*BS58),2))*AT58)/100),2)+ROUND(((ROUND((ROUND(((AE58-(EU58))*AV58*1),2)*BS58),2)*AT58)/100),2)) -> 0 | CZ58: =(ROUND((((S58+ROUND((ROUND(((EU58)*AV58*1),2)*BS58),2))*AU58)/100),2)+ROUND(((ROUND((ROUND(((AE58-(EU58))*AV58*1),2)*BS58),2)*AU58)/100),2)) -> 0 | DN58: 0 | DO58: 0 | DP58: 1 | DQ58: 1 | DU58: 1010 | DV58: шт. | DW58: шт. | DX58: 1 | EE58: 60088638 | EF58: 130 | EG58: Сметная стоимость оборудования | EH58: 0 | EJ58: 3 | EK58: 746 | EL58: ТСН-2001.13. Сметная стоимость оборудования | EM58: ТСН-2001.13 | EQ58: 0 | ER58: 0 | ES58: 5613.23 | ET58: 0 | EU58: 0 | EV58: 0 | EW58: 0 | EX58: 0 | EY58: 0 | FQ58: 0 | FR58: =P58 -> 5613.23 | FS58: 0 | FX58: 0 | FY58: 0 | GA58: [49 500 / 1,2 / 7,66] + 3% Трансп + 1,2% Заг.скл | GD58: 1 | GF58: 827169523 | GG58: 2 | GH58: 4 | GI58: -2 | GJ58: 0 | GK58: 0 | GL58: =ROUND(IF(AND(BH58=3,BI58=3,FS58<>0),P58,0),2) -> 0 | GM58: =ROUND(O58+X58+Y58,2)+GX58 -> 5613.23 | GN58: =IF(OR(BI58=0,BI58=1),GM58-GX58,0) -> 0 | GO58: =IF(BI58=2,GM58-GX58,0) -> 0 | GP58: =IF(BI58=4,GM58-GX58,0) -> 0 | GR58: 0 | GS58: 2 | GT58: 0 | GV58: =ROUND((GT58),6) -> 0 | GW58: 1 | GX58: =ROUND(HC58*I58,2) -> 0 | HA58: 0 | HB58: 0 | HC58: =GV58*GW58 -> 0 | HE58: 3 | HF58: 1,2 | HS58: 0 | IK58: 0
A59: 17 | B59: 1 | E59: 14 | F59: КА-7 | G59: Блок АКБ 24В. Заменяемые АКБ 12В, 5Ач, количество элементов в корпусе - 10 шт. Sonar SBB-2425 | H59: шт. | I59: 1 | J59: 0 | K59: 1 | O59: =ROUND(CP59,2) -> 42997.34 | P59: =ROUND((ROUND((AC59*I59),2)*BC59),2) -> 42997.34 | Q59: =(ROUND((ROUND(((ET59)*AV59*I59),2)*BB59),2)+ROUND((ROUND(((AE59-(EU59))*AV59*I59),2)*BS59),2)) -> 0 | R59: =(ROUND((ROUND(((EU59)*AV59*I59),2)*BS59),2)+ROUND((ROUND(((AE59-(EU59))*AV59*I59),2)*BS59),2)) -> 0 | S59: =ROUND((ROUND((AF59*AV59*I59),2)*BA59),2) -> 0 | T59: =ROUND(CU59*I59,2) -> 0 | U59: =CV59*I59 -> 0 | V59: =CW59*I59 -> 0 | W59: =ROUND(CX59*I59,2) -> 0 | X59: =(ROUND((((S59+ROUND((ROUND(((EU59)*AV59*I59),2)*BS59),2))*AT59)/100),2)+ROUND(((ROUND((ROUND(((AE59-(EU59))*AV59*I59),2)*BS59),2)*AT59)/100),2)) -> 0 | Y59: =(ROUND((((S59+ROUND((ROUND(((EU59)*AV59*I59),2)*BS59),2))*AU59)/100),2)+ROUND(((ROUND((ROUND(((AE59-(EU59))*AV59*I59),2)*BS59),2)*AU59)/100),2)) -> 0 | AA59: 60256402 | AB59: =ROUND((AC59+AD59+AF59),6) -> 5613.23 | AC59: =ROUND((ES59),6) -> 5613.23 | AD59: =ROUND((((ET59)-(EU59))+AE59),6) -> 0 | AE59: =ROUND((EU59),6) -> 0 | AF59: =ROUND((EV59),6) -> 0 | AG59: =ROUND((AP59),6) -> 0 | AH59: =(EW59) -> 0 | AI59: =(EX59) -> 0 | AJ59: =(AS59) -> 0 | AK59: 5613.23 | AL59: 5613.23 | AM59: 0 | AN59: 0 | AO59: 0 | AP59: 0 | AQ59: 0 | AR59: 0 | AS59: 0 | AT59: 0 | AU59: 0 | AV59: 1 | AW59: 1 | AZ59: 1 | BA59: 1 | BB59: 1 | BC59: 7.66 | BH59: 3 | BI59: 3 | BM59: 746 | BN59: 0 | BP59: 0 | BQ59: 130 | BR59: 0 | BS59: 1 | BT59: 1 | BU59: 1 | BV59: 1 | BW59: 1 | BX59: 1 | BZ59: 0 | CA59: 0 | CE59: 1566 | CF59: 0 | CG59: 0 | CM59: 0 | CO59: 0 | CP59: =(P59+Q59+S59) -> 42997.34 | CQ59: =ROUND((ROUND((AC59*1),2)*BC59),2) -> 42997.34 | CR59: =(ROUND((ROUND(((ET59)*AV59*1),2)*BB59),2)+ROUND((ROUND(((AE59-(EU59))*AV59*1),2)*BS59),2)) -> 0 | CS59: =(ROUND((ROUND(((EU59)*AV59*1),2)*BS59),2)+ROUND((ROUND(((AE59-(EU59))*AV59*1),2)*BS59),2)) -> 0 | CT59: =ROUND((ROUND((AF59*AV59*1),2)*BA59),2) -> 0 | CU59: =AG59 -> 0 | CV59: =(AH59*AV59) -> 0 | CW59: =AI59 -> 0 | CX59: =AJ59 -> 0 | CY59: =(ROUND((((S59+ROUND((ROUND(((EU59)*AV59*1),2)*BS59),2))*AT59)/100),2)+ROUND(((ROUND((ROUND(((AE59-(EU59))*AV59*1),2)*BS59),2)*AT59)/100),2)) -> 0 | CZ59: =(ROUND((((S59+ROUND((ROUND(((EU59)*AV59*1),2)*BS59),2))*AU59)/100),2)+ROUND(((ROUND((ROUND(((AE59-(EU59))*AV59*1),2)*BS59),2)*AU59)/100),2)) -> 0 | DN59: 0 | DO59: 0 | DP59: 1 | DQ59: 1 | DU59: 1010 | DV59: шт. | DW59: шт. | DX59: 1 | EE59: 60088638 | EF59: 130 | EG59: Сметная стоимость оборудования | EH59: 0 | EJ59: 3 | EK59: 746 | EL59: ТСН-2001.13. Сметная стоимость оборудования | EM59: ТСН-2001.13 | EQ59: 0 | ER59: 5613.23 | ES59: 5613.23 | ET59: 0 | EU59: 0 | EV59: 0 | EW59: 0 | EX59: 0 | EY59: 0 | EZ59: 5 | FC59: 1 | FD59: 18 | FF59: 49500 | FQ59: 0 | FR59: =P59 -> 42997.34 | FS59: 0 | FX59: 0 | FY59: 0 | GA59: [49 500 / 1,2 / 7,66] + 3% Трансп + 1,2% Заг.скл | GD59: 1 | GF59: 827169523 | GG59: 2 | GH59: 3 | GI59: 5 | GJ59: 0 | GK59: 0 | GL59: =ROUND(IF(AND(BH59=3,BI59=3,FS59<>0),P59,0),2) -> 0 | GM59: =ROUND(O59+X59+Y59,2)+GX59 -> 42997.34 | GN59: =IF(OR(BI59=0,BI59=1),GM59-GX59,0) -> 0 | GO59: =IF(BI59=2,GM59-GX59,0) -> 0 | GP59: =IF(BI59=4,GM59-GX59,0) -> 0 | GR59: 1 | GS59: 1 | GT59: 0 | GV59: =ROUND((GT59),6) -> 0 | GW59: 1 | GX59: =ROUND(HC59*I59,2) -> 0 | HA59: 0 | HB59: 0 | HC59: =GV59*GW59 -> 0 | HE59: 3 | HF59: 1,2 | HS59: 0 | IK59: 0
A60: 17 | B60: 1 | C60: =ROW(SmtRes!A52) -> 52 | D60: =ROW(EtalonRes!A67) -> 67 | E60: 15 | F60: 4.11-3-1 | G60: Установка прибора массой до 5 кг на металлоконструкциях или щитах | H60: 1 ШТ. | I60: 1 | J60: 0 | K60: 1 | O60: =ROUND(CP60,2) -> 7.77 | P60: =ROUND((ROUND((AC60*AW60*I60),2)*BC60),2) -> 0 | Q60: =(ROUND((ROUND((((ET60*1.1))*AV60*I60),2)*BB60),2)+ROUND((ROUND(((AE60-((EU60*1.1)))*AV60*I60),2)*BS60),2)) -> 0 | R60: =(ROUND((ROUND((((EU60*1.1))*AV60*I60),2)*BS60),2)+ROUND((ROUND(((AE60-((EU60*1.1)))*AV60*I60),2)*BS60),2)) -> 0 | S60: =ROUND((ROUND((AF60*AV60*I60),2)*BA60),2) -> 7.77 | T60: =ROUND(CU60*I60,2) -> 0 | U60: =CV60*I60 -> 0.598884 | V60: =CW60*I60 -> 0 | W60: =ROUND(CX60*I60,2) -> 0 | X60: =(ROUND((((S60+ROUND((ROUND((((EU60*1.1))*AV60*I60),2)*BS60),2))*AT60)/100),2)+ROUND(((ROUND((ROUND(((AE60-((EU60*1.1)))*AV60*I60),2)*BS60),2)*AT60)/100),2)) -> 6.99 | Y60: =(ROUND((((S60+ROUND((ROUND((((EU60*1.1))*AV60*I60),2)*BS60),2))*AU60)/100),2)+ROUND(((ROUND((ROUND(((AE60-((EU60*1.1)))*AV60*I60),2)*BS60),2)*AU60)/100),2)) -> 3.57 | AA60: 60256405 | AB60: =ROUND((AC60+AD60+AF60),6) -> 7.425 | AC60: =ROUND(((ES60*1)),6) -> 0 | AD60: =ROUND(((((ET60*1.1))-((EU60*1.1)))+AE60),6) -> 0 | AE60: =ROUND(((EU60*1.1)),6) -> 0 | AF60: =ROUND(((EV60*1.1)),6) -> 7.425 | AG60: =ROUND((AP60),6) -> 0 | AH60: =((EW60*1.1)) -> 0.572 | AI60: =((EX60*1.1)) -> 0 | AJ60: =(AS60) -> 0 | AK60: 6.75 | AL60: 0 | AM60: 0 | AN60: 0 | AO60: 6.75 | AP60: 0 | AQ60: 0.52 | AR60: 0 | AS60: 0 | AT60: 90 | AU60: 46 | AV60: 1.047 | AW60: 1 | AZ60: 1 | BA60: 1 | BB60: 1 | BC60: 1 | BH60: 0 | BI60: 2 | BJ60: ТСН-2001.4 Доп. 67, Сб. 11, т. 3, поз. 1 | BM60: 72 | BN60: 58973116 | BO60: 4.11-3-1 | BP60: 1 | BQ60: 40 | BR60: 0 | BS60: 1 | BT60: 1 | BU60: 1 | BV60: 1 | BW60: 1 | BX60: 1 | BZ60: 90 | CA60: 46 | CE60: 1566 | CF60: 0 | CG60: 0 | CM60: 0 | CN60: Поправка: Гл.12.Прил.8.п.8. 5_12.00.01.11.003 Наименование: При наличии усложненных условий производства работ (стесненность, сложность складирования и транспортной логистики, наличие в зоне производства работ действующего технологического оборудования или движения технологического транспорта и т.п.) для объектов, расположенных за пределами территории круговой магистральной системы улиц "Садовое кольцо" и за пределами Третьего транспортного кольца города Москвы пунктов "а" и "б", но в пределах Московской кольцевой автомобильной дороги | CO60: 0 | CP60: =(P60+Q60+S60) -> 7.77 | CQ60: =ROUND((ROUND((AC60*AW60*1),2)*BC60),2) -> 0 | CR60: =(ROUND((ROUND((((ET60*1.1))*AV60*1),2)*BB60),2)+ROUND((ROUND(((AE60-((EU60*1.1)))*AV60*1),2)*BS60),2)) -> 0 | CS60: =(ROUND((ROUND((((EU60*1.1))*AV60*1),2)*BS60),2)+ROUND((ROUND(((AE60-((EU60*1.1)))*AV60*1),2)*BS60),2)) -> 0 | CT60: =ROUND((ROUND((AF60*AV60*1),2)*BA60),2) -> 7.77 | CU60: =AG60 -> 0 | CV60: =(AH60*AV60) -> 0.598884 | CW60: =AI60 -> 0 | CX60: =AJ60 -> 0 | CY60: =(ROUND((((S60+ROUND((ROUND((((EU60*1.1))*AV60*1),2)*BS60),2))*AT60)/100),2)+ROUND(((ROUND((ROUND(((AE60-((EU60*1.1)))*AV60*1),2)*BS60),2)*AT60)/100),2)) -> 6.99 | CZ60: =(ROUND((((S60+ROUND((ROUND((((EU60*1.1))*AV60*1),2)*BS60),2))*AU60)/100),2)+ROUND(((ROUND((ROUND(((AE60-((EU60*1.1)))*AV60*1),2)*BS60),2)*AU60)/100),2)) -> 3.57 | DB60: 15 | DD60: *1 | DE60: *1,1 | DF60: *1,1 | DG60: *1,1 | DI60: *1,1 | DJ60: *1,1 | DN60: 0 | DO60: 0 | DP60: 1 | DQ60: 1 | DU60: 1013 | DV60: 1 ШТ. | DW60: 1 ШТ. | DX60: 1 | EE60: 60088536 | EF60: 40 | EG60: Монтаж оборудования | EH60: 0 | EJ60: 2 | EK60: 72 | EL60: ТСН-2001.4-11. Приборы и средства автоматизации и вычислительной техники | EM60: ТСН-2001.4-11-1 | EO60: Поправка: Гл.12.Прил.8.п.8. 5_12.00.01.11.003 | EQ60: 0 | ER60: 6.75 | ES60: 0 | ET60: 0 | EU60: 0 | EV60: 6.75 | EW60: 0.52 | EX60: 0 | EY60: 0 | FQ60: 0 | FR60: 0 | FS60: 0 | FX60: 90 | FY60: 46 | GD60: 1 | GF60: 338415528 | GG60: 2 | GH60: 1 | GI60: 2 | GJ60: 0 | GK60: 0 | GL60: =ROUND(IF(AND(BH60=3,BI60=3,FS60<>0),P60,0),2) -> 0 | GM60: =ROUND(O60+X60+Y60,2)+GX60 -> 18.33 | GN60: =IF(OR(BI60=0,BI60=1),GM60-GX60,0) -> 0 | GO60: =IF(BI60=2,GM60-GX60,0) -> 18.33 | GP60: =IF(BI60=4,GM60-GX60,0) -> 0 | GR60: 0 | GS60: 3 | GT60: 0 | GV60: =ROUND((GT60),6) -> 0 | GW60: 1 | GX60: =ROUND(HC60*I60,2) -> 0 | HA60: 0 | HB60: 0 | HC60: =GV60*GW60 -> 0 | HS60: 0 | IK60: 0
A61: 17 | B61: 1 | C61: =ROW(SmtRes!A54) -> 54 | D61: =ROW(EtalonRes!A70) -> 70 | E61: 15 | F61: 4.11-3-1 | G61: Установка прибора массой до 5 кг на металлоконструкциях или щитах | H61: 1 ШТ. | I61: 1 | J61: 0 | K61: 1 | O61: =ROUND(CP61,2) -> 427.27 | P61: =ROUND((ROUND((AC61*AW61*I61),2)*BC61),2) -> 0 | Q61: =(ROUND((ROUND((((ET61*1.1))*AV61*I61),2)*BB61),2)+ROUND((ROUND(((AE61-((EU61*1.1)))*AV61*I61),2)*BS61),2)) -> 0 | R61: =(ROUND((ROUND((((EU61*1.1))*AV61*I61),2)*BS61),2)+ROUND((ROUND(((AE61-((EU61*1.1)))*AV61*I61),2)*BS61),2)) -> 0 | S61: =ROUND((ROUND((AF61*AV61*I61),2)*BA61),2) -> 427.27 | T61: =ROUND(CU61*I61,2) -> 0 | U61: =CV61*I61 -> 0.598884 | V61: =CW61*I61 -> 0 | W61: =ROUND(CX61*I61,2) -> 0 | X61: =(ROUND((((S61+ROUND((ROUND((((EU61*1.1))*AV61*I61),2)*BS61),2))*AT61)/100),2)+ROUND(((ROUND((ROUND(((AE61-((EU61*1.1)))*AV61*I61),2)*BS61),2)*AT61)/100),2)) -> 384.54 | Y61: =(ROUND((((S61+ROUND((ROUND((((EU61*1.1))*AV61*I61),2)*BS61),2))*AU61)/100),2)+ROUND(((ROUND((ROUND(((AE61-((EU61*1.1)))*AV61*I61),2)*BS61),2)*AU61)/100),2)) -> 196.54 | AA61: 60256402 | AB61: =ROUND((AC61+AD61+AF61),6) -> 7.425 | AC61: =ROUND(((ES61*1)),6) -> 0 | AD61: =ROUND(((((ET61*1.1))-((EU61*1.1)))+AE61),6) -> 0 | AE61: =ROUND(((EU61*1.1)),6) -> 0 | AF61: =ROUND(((EV61*1.1)),6) -> 7.425 | AG61: =ROUND((AP61),6) -> 0 | AH61: =((EW61*1.1)) -> 0.572 | AI61: =((EX61*1.1)) -> 0 | AJ61: =(AS61) -> 0 | AK61: 6.75 | AL61: 0 | AM61: 0 | AN61: 0 | AO61: 6.75 | AP61: 0 | AQ61: 0.52 | AR61: 0 | AS61: 0 | AT61: 90 | AU61: 46 | AV61: 1.047 | AW61: 1 | AZ61: 1 | BA61: 54.99 | BB61: 1 | BC61: 1 | BH61: 0 | BI61: 2 | BJ61: ТСН-2001.4 Доп. 67, Сб. 11, т. 3, поз. 1 | BM61: 72 | BN61: 58973116 | BO61: 4.11-3-1 | BP61: 1 | BQ61: 40 | BR61: 0 | BS61: 54.99 | BT61: 1 | BU61: 1 | BV61: 1 | BW61: 1 | BX61: 1 | BZ61: 90 | CA61: 46 | CE61: 1566 | CF61: 0 | CG61: 0 | CM61: 0 | CN61: Поправка: Гл.12.Прил.8.п.8. 5_12.00.01.11.003 Наименование: При наличии усложненных условий производства работ (стесненность, сложность складирования и транспортной логистики, наличие в зоне производства работ действующего технологического оборудования или движения технологического транспорта и т.п.) для объектов, расположенных за пределами территории круговой магистральной системы улиц "Садовое кольцо" и за пределами Третьего транспортного кольца города Москвы пунктов "а" и "б", но в пределах Московской кольцевой автомобильной дороги | CO61: 0 | CP61: =(P61+Q61+S61) -> 427.27 | CQ61: =ROUND((ROUND((AC61*AW61*1),2)*BC61),2) -> 0 | CR61: =(ROUND((ROUND((((ET61*1.1))*AV61*1),2)*BB61),2)+ROUND((ROUND(((AE61-((EU61*1.1)))*AV61*1),2)*BS61),2)) -> 0 | CS61: =(ROUND((ROUND((((EU61*1.1))*AV61*1),2)*BS61),2)+ROUND((ROUND(((AE61-((EU61*1.1)))*AV61*1),2)*BS61),2)) -> 0 | CT61: =ROUND((ROUND((AF61*AV61*1),2)*BA61),2) -> 427.27 | CU61: =AG61 -> 0 | CV61: =(AH61*AV61) -> 0.598884 | CW61: =AI61 -> 0 | CX61: =AJ61 -> 0 | CY61: =(ROUND((((S61+ROUND((ROUND((((EU61*1.1))*AV61*1),2)*BS61),2))*AT61)/100),2)+ROUND(((ROUND((ROUND(((AE61-((EU61*1.1)))*AV61*1),2)*BS61),2)*AT61)/100),2)) -> 384.54 | CZ61: =(ROUND((((S61+ROUND((ROUND((((EU61*1.1))*AV61*1),2)*BS61),2))*AU61)/100),2)+ROUND(((ROUND((ROUND(((AE61-((EU61*1.1)))*AV61*1),2)*BS61),2)*AU61)/100),2)) -> 196.54 | DB61: 16 | DD61: *1 | DE61: *1,1 | DF61: *1,1 | DG61: *1,1 | DI61: *1,1 | DJ61: *1,1 | DN61: 0 | DO61: 0 | DP61: 1 | DQ61: 1 | DU61: 1013 | DV61: 1 ШТ. | DW61: 1 ШТ. | DX61: 1 | EE61: 60088536 | EF61: 40 | EG61: Монтаж оборудования | EH61: 0 | EJ61: 2 | EK61: 72 | EL61: ТСН-2001.4-11. Приборы и средства автоматизации и вычислительной техники | EM61: ТСН-2001.4-11-1 | EO61: Поправка: Гл.12.Прил.8.п.8. 5_12.00.01.11.003 | EQ61: 0 | ER61: 6.75 | ES61: 0 | ET61: 0 | EU61: 0 | EV61: 6.75 | EW61: 0.52 | EX61: 0 | EY61: 0 | FQ61: 0 | FR61: 0 | FS61: 0 | FX61: 90 | FY61: 46 | GD61: 1 | GF61: 338415528 | GG61: 2 | GH61: 1 | GI61: 2 | GJ61: 0 | GK61: 0 | GL61: =ROUND(IF(AND(BH61=3,BI61=3,FS61<>0),P61,0),2) -> 0 | GM61: =ROUND(O61+X61+Y61,2)+GX61 -> 1008.35 | GN61: =IF(OR(BI61=0,BI61=1),GM61-GX61,0) -> 0 | GO61: =IF(BI61=2,GM61-GX61,0) -> 1008.35 | GP61: =IF(BI61=4,GM61-GX61,0) -> 0 | GR61: 0 | GS61: 3 | GT61: 0 | GV61: =ROUND((GT61),6) -> 0 | GW61: 1 | GX61: =ROUND(HC61*I61,2) -> 0 | HA61: 0 | HB61: 0 | HC61: =GV61*GW61 -> 0 | HS61: 0 | IK61: 0
A62: 18 | B62: 1 | C62: 52 | E62: 15,1 | F62: 1.1-1-8146 | G62: Болты стальные оцинкованные с шестигранной головкой, с полной резьбой, с гайкой оцинкованной, М6, длина от 12 до 60 мм | H62: кг | I62: =I60*J62 -> 0.035 | J62: 0.035 | K62: 0.035 | O62: =ROUND(CP62,2) -> 1.09 | P62: =ROUND((ROUND((AC62*AW62*I62),2)*BC62),2) -> 1.09 | Q62: =(ROUND((ROUND(((ET62)*AV62*I62),2)*BB62),2)+ROUND((ROUND(((AE62-(EU62))*AV62*I62),2)*BS62),2)) -> 0 | R62: =(ROUND((ROUND(((EU62)*AV62*I62),2)*BS62),2)+ROUND((ROUND(((AE62-(EU62))*AV62*I62),2)*BS62),2)) -> 0 | S62: =ROUND((ROUND((AF62*AV62*I62),2)*BA62),2) -> 0 | T62: =ROUND(CU62*I62,2) -> 0 | U62: =CV62*I62 -> 0 | V62: =CW62*I62 -> 0 | W62: =ROUND(CX62*I62,2) -> 0 | X62: =(ROUND((((S62+ROUND((ROUND(((EU62)*AV62*I62),2)*BS62),2))*AT62)/100),2)+ROUND(((ROUND((ROUND(((AE62-(EU62))*AV62*I62),2)*BS62),2)*AT62)/100),2)) -> 0 | Y62: =(ROUND((((S62+ROUND((ROUND(((EU62)*AV62*I62),2)*BS62),2))*AU62)/100),2)+ROUND(((ROUND((ROUND(((AE62-(EU62))*AV62*I62),2)*BS62),2)*AU62)/100),2)) -> 0 | AA62: 60256405 | AB62: =ROUND((AC62+AD62+AF62),6) -> 31.08 | AC62: =ROUND((ES62),6) -> 31.08 | AD62: =ROUND((((ET62)-(EU62))+AE62),6) -> 0 | AE62: =ROUND((EU62),6) -> 0 | AF62: =ROUND((EV62),6) -> 0 | AG62: =ROUND((AP62),6) -> 0 | AH62: =(EW62) -> 0 | AI62: =(EX62) -> 0 | AJ62: =(AS62) -> 0 | AK62: 31.08 | AL62: 31.08 | AM62: 0 | AN62: 0 | AO62: 0 | AP62: 0 | AQ62: 0 | AR62: 0 | AS62: 0 | AT62: 90 | AU62: 46 | AV62: 1 | AW62: 1 | AZ62: 1 | BA62: 1 | BB62: 1 | BC62: 1 | BH62: 3 | BI62: 2 | BJ62: ТСН-2001.1 Доп. 79, Р. 1, о. 1, поз. 8146 | BM62: 72 | BN62: 58973116 | BP62: 0 | BQ62: 40 | BR62: 0 | BS62: 1 | BT62: 1 | BU62: 1 | BV62: 1 | BW62: 1 | BX62: 1 | BZ62: 90 | CA62: 46 | CE62: 1566 | CF62: 0 | CG62: 0 | CM62: 0 | CN62: Поправка: Гл.12.Прил.8.п.8. 5_12.00.01.11.003 Наименование: При наличии усложненных условий производства работ (стесненность, сложность складирования и транспортной логистики, наличие в зоне производства работ действующего технологического оборудования или движения технологического транспорта и т.п.) для объектов, расположенных за пределами территории круговой магистральной системы улиц "Садовое кольцо" и за пределами Третьего транспортного кольца города Москвы пунктов "а" и "б", но в пределах Московской кольцевой автомобильной дороги | CO62: 0 | CP62: =(P62+Q62+S62) -> 1.09 | CQ62: =ROUND((ROUND((AC62*AW62*1),2)*BC62),2) -> 31.08 | CR62: =(ROUND((ROUND(((ET62)*AV62*1),2)*BB62),2)+ROUND((ROUND(((AE62-(EU62))*AV62*1),2)*BS62),2)) -> 0 | CS62: =(ROUND((ROUND(((EU62)*AV62*1),2)*BS62),2)+ROUND((ROUND(((AE62-(EU62))*AV62*1),2)*BS62),2)) -> 0 | CT62: =ROUND((ROUND((AF62*AV62*1),2)*BA62),2) -> 0 | CU62: =AG62 -> 0 | CV62: =(AH62*AV62) -> 0 | CW62: =AI62 -> 0 | CX62: =AJ62 -> 0 | CY62: =(ROUND((((S62+ROUND((ROUND(((EU62)*AV62*1),2)*BS62),2))*AT62)/100),2)+ROUND(((ROUND((ROUND(((AE62-(EU62))*AV62*1),2)*BS62),2)*AT62)/100),2)) -> 0 | CZ62: =(ROUND((((S62+ROUND((ROUND(((EU62)*AV62*1),2)*BS62),2))*AU62)/100),2)+ROUND(((ROUND((ROUND(((AE62-(EU62))*AV62*1),2)*BS62),2)*AU62)/100),2)) -> 0 | DN62: 0 | DO62: 0 | DP62: 1 | DQ62: 1 | DU62: 1009 | DV62: кг | DW62: кг | DX62: 1 | EE62: 60088536 | EF62: 40 | EG62: Монтаж оборудования | EH62: 0 | EJ62: 2 | EK62: 72 | EL62: ТСН-2001.4-11. Приборы и средства автоматизации и вычислительной техники | EM62: ТСН-2001.4-11-1 | EO62: Поправка: Гл.12.Прил.8.п.8. 5_12.00.01.11.003 | EQ62: 0 | ER62: 31.08 | ES62: 31.08 | ET62: 0 | EU62: 0 | EV62: 0 | EW62: 0 | EX62: 0 | FQ62: 0 | FR62: 0 | FS62: 0 | FX62: 90 | FY62: 46 | GD62: 1 | GF62: 1143487818 | GG62: 2 | GH62: 1 | GI62: -2 | GJ62: 0 | GK62: 0 | GL62: =ROUND(IF(AND(BH62=3,BI62=3,FS62<>0),P62,0),2) -> 0 | GM62: =ROUND(O62+X62+Y62,2)+GX62 -> 1.09 | GN62: =IF(OR(BI62=0,BI62=1),GM62-GX62,0) -> 0 | GO62: =IF(BI62=2,GM62-GX62,0) -> 1.09 | GP62: =IF(BI62=4,GM62-GX62,0) -> 0 | GR62: 0 | GS62: 3 | GT62: 0 | GV62: =ROUND((GT62),6) -> 0 | GW62: 1 | GX62: =ROUND(HC62*I62,2) -> 0 | HA62: 0 | HB62: 0 | HC62: =GV62*GW62 -> 0 | HM62: *1 | HS62: 0 | IK62: 0
A63: 18 | B63: 1 | C63: 54 | E63: 15,1 | F63: 1.1-1-8146 | G63: Болты стальные оцинкованные с шестигранной головкой, с полной резьбой, с гайкой оцинкованной, М6, длина от 12 до 60 мм | H63: кг | I63: =I61*J63 -> 0.035 | J63: 0.035 | K63: 0.035 | O63: =ROUND(CP63,2) -> 5.58 | P63: =ROUND((ROUND((AC63*AW63*I63),2)*BC63),2) -> 5.58 | Q63: =(ROUND((ROUND(((ET63)*AV63*I63),2)*BB63),2)+ROUND((ROUND(((AE63-(EU63))*AV63*I63),2)*BS63),2)) -> 0 | R63: =(ROUND((ROUND(((EU63)*AV63*I63),2)*BS63),2)+ROUND((ROUND(((AE63-(EU63))*AV63*I63),2)*BS63),2)) -> 0 | S63: =ROUND((ROUND((AF63*AV63*I63),2)*BA63),2) -> 0 | T63: =ROUND(CU63*I63,2) -> 0 | U63: =CV63*I63 -> 0 | V63: =CW63*I63 -> 0 | W63: =ROUND(CX63*I63,2) -> 0 | X63: =(ROUND((((S63+ROUND((ROUND(((EU63)*AV63*I63),2)*BS63),2))*AT63)/100),2)+ROUND(((ROUND((ROUND(((AE63-(EU63))*AV63*I63),2)*BS63),2)*AT63)/100),2)) -> 0 | Y63: =(ROUND((((S63+ROUND((ROUND(((EU63)*AV63*I63),2)*BS63),2))*AU63)/100),2)+ROUND(((ROUND((ROUND(((AE63-(EU63))*AV63*I63),2)*BS63),2)*AU63)/100),2)) -> 0 | AA63: 60256402 | AB63: =ROUND((AC63+AD63+AF63),6) -> 31.08 | AC63: =ROUND((ES63),6) -> 31.08 | AD63: =ROUND((((ET63)-(EU63))+AE63),6) -> 0 | AE63: =ROUND((EU63),6) -> 0 | AF63: =ROUND((EV63),6) -> 0 | AG63: =ROUND((AP63),6) -> 0 | AH63: =(EW63) -> 0 | AI63: =(EX63) -> 0 | AJ63: =(AS63) -> 0 | AK63: 31.08 | AL63: 31.08 | AM63: 0 | AN63: 0 | AO63: 0 | AP63: 0 | AQ63: 0 | AR63: 0 | AS63: 0 | AT63: 90 | AU63: 46 | AV63: 1 | AW63: 1 | AZ63: 1 | BA63: 1 | BB63: 1 | BC63: 5.12 | BH63: 3 | BI63: 2 | BJ63: ТСН-2001.1 Доп. 79, Р. 1, о. 1, поз. 8146 | BM63: 72 | BN63: 58973116 | BO63: 1.1-1-8146 | BP63: 1 | BQ63: 40 | BR63: 0 | BS63: 1 | BT63: 1 | BU63: 1 | BV63: 1 | BW63: 1 | BX63: 1 | BZ63: 90 | CA63: 46 | CE63: 1566 | CF63: 0 | CG63: 0 | CM63: 0 | CN63: Поправка: Гл.12.Прил.8.п.8. 5_12.00.01.11.003 Наименование: При наличии усложненных условий производства работ (стесненность, сложность складирования и транспортной логистики, наличие в зоне производства работ действующего технологического оборудования или движения технологического транспорта и т.п.) для объектов, расположенных за пределами территории круговой магистральной системы улиц "Садовое кольцо" и за пределами Третьего транспортного кольца города Москвы пунктов "а" и "б", но в пределах Московской кольцевой автомобильной дороги | CO63: 0 | CP63: =(P63+Q63+S63) -> 5.58 | CQ63: =ROUND((ROUND((AC63*AW63*1),2)*BC63),2) -> 159.13 | CR63: =(ROUND((ROUND(((ET63)*AV63*1),2)*BB63),2)+ROUND((ROUND(((AE63-(EU63))*AV63*1),2)*BS63),2)) -> 0 | CS63: =(ROUND((ROUND(((EU63)*AV63*1),2)*BS63),2)+ROUND((ROUND(((AE63-(EU63))*AV63*1),2)*BS63),2)) -> 0 | CT63: =ROUND((ROUND((AF63*AV63*1),2)*BA63),2) -> 0 | CU63: =AG63 -> 0 | CV63: =(AH63*AV63) -> 0 | CW63: =AI63 -> 0 | CX63: =AJ63 -> 0 | CY63: =(ROUND((((S63+ROUND((ROUND(((EU63)*AV63*1),2)*BS63),2))*AT63)/100),2)+ROUND(((ROUND((ROUND(((AE63-(EU63))*AV63*1),2)*BS63),2)*AT63)/100),2)) -> 0 | CZ63: =(ROUND((((S63+ROUND((ROUND(((EU63)*AV63*1),2)*BS63),2))*AU63)/100),2)+ROUND(((ROUND((ROUND(((AE63-(EU63))*AV63*1),2)*BS63),2)*AU63)/100),2)) -> 0 | DN63: 0 | DO63: 0 | DP63: 1 | DQ63: 1 | DU63: 1009 | DV63: кг | DW63: кг | DX63: 1 | EE63: 60088536 | EF63: 40 | EG63: Монтаж оборудования | EH63: 0 | EJ63: 2 | EK63: 72 | EL63: ТСН-2001.4-11. Приборы и средства автоматизации и вычислительной техники | EM63: ТСН-2001.4-11-1 | EO63: Поправка: Гл.12.Прил.8.п.8. 5_12.00.01.11.003 | EQ63: 0 | ER63: 31.08 | ES63: 31.08 | ET63: 0 | EU63: 0 | EV63: 0 | EW63: 0 | EX63: 0 | FQ63: 0 | FR63: 0 | FS63: 0 | FX63: 90 | FY63: 46 | GD63: 1 | GF63: 1143487818 | GG63: 2 | GH63: 1 | GI63: 2 | GJ63: 0 | GK63: 0 | GL63: =ROUND(IF(AND(BH63=3,BI63=3,FS63<>0),P63,0),2) -> 0 | GM63: =ROUND(O63+X63+Y63,2)+GX63 -> 5.58 | GN63: =IF(OR(BI63=0,BI63=1),GM63-GX63,0) -> 0 | GO63: =IF(BI63=2,GM63-GX63,0) -> 5.58 | GP63: =IF(BI63=4,GM63-GX63,0) -> 0 | GR63: 0 | GS63: 3 | GT63: 0 | GV63: =ROUND((GT63),6) -> 0 | GW63: 1 | GX63: =ROUND(HC63*I63,2) -> 0 | HA63: 0 | HB63: 0 | HC63: =GV63*GW63 -> 0 | HM63: *1 | HS63: 0 | IK63: 0
A64: 17 | B64: 1 | E64: 16 | F64: КА-8 | G64: Блок АКБ 24В. Заменяемые АКБ 12В, 5Ач, количество элементов в корпусе - 18 шт. Sonar SBB-2450 | H64: шт. | I64: 1 | J64: 0 | K64: 1 | O64: =ROUND(CP64,2) -> 8731.7 | P64: =ROUND((ROUND((AC64*I64),2)*BC64),2) -> 8731.7 | Q64: =(ROUND((ROUND(((ET64)*AV64*I64),2)*BB64),2)+ROUND((ROUND(((AE64-(EU64))*AV64*I64),2)*BS64),2)) -> 0 | R64: =(ROUND((ROUND(((EU64)*AV64*I64),2)*BS64),2)+ROUND((ROUND(((AE64-(EU64))*AV64*I64),2)*BS64),2)) -> 0 | S64: =ROUND((ROUND((AF64*AV64*I64),2)*BA64),2) -> 0 | T64: =ROUND(CU64*I64,2) -> 0 | U64: =CV64*I64 -> 0 | V64: =CW64*I64 -> 0 | W64: =ROUND(CX64*I64,2) -> 0 | X64: =(ROUND((((S64+ROUND((ROUND(((EU64)*AV64*I64),2)*BS64),2))*AT64)/100),2)+ROUND(((ROUND((ROUND(((AE64-(EU64))*AV64*I64),2)*BS64),2)*AT64)/100),2)) -> 0 | Y64: =(ROUND((((S64+ROUND((ROUND(((EU64)*AV64*I64),2)*BS64),2))*AU64)/100),2)+ROUND(((ROUND((ROUND(((AE64-(EU64))*AV64*I64),2)*BS64),2)*AU64)/100),2)) -> 0 | AA64: 60256405 | AB64: =ROUND((AC64+AD64+AF64),6) -> 8731.7 | AC64: =ROUND((ES64),6) -> 8731.7 | AD64: =ROUND((((ET64)-(EU64))+AE64),6) -> 0 | AE64: =ROUND((EU64),6) -> 0 | AF64: =ROUND((EV64),6) -> 0 | AG64: =ROUND((AP64),6) -> 0 | AH64: =(EW64) -> 0 | AI64: =(EX64) -> 0 | AJ64: =(AS64) -> 0 | AK64: 8731.7 | AL64: 8731.7 | AM64: 0 | AN64: 0 | AO64: 0 | AP64: 0 | AQ64: 0 | AR64: 0 | AS64: 0 | AT64: 0 | AU64: 0 | AV64: 1 | AW64: 1 | AZ64: 1 | BA64: 1 | BB64: 1 | BC64: 1 | BH64: 3 | BI64: 3 | BM64: 746 | BN64: 0 | BP64: 0 | BQ64: 130 | BR64: 0 | BS64: 1 | BT64: 1 | BU64: 1 | BV64: 1 | BW64: 1 | BX64: 1 | BZ64: 0 | CA64: 0 | CE64: 1566 | CF64: 0 | CG64: 0 | CM64: 0 | CO64: 0 | CP64: =(P64+Q64+S64) -> 8731.7 | CQ64: =ROUND((ROUND((AC64*1),2)*BC64),2) -> 8731.7 | CR64: =(ROUND((ROUND(((ET64)*AV64*1),2)*BB64),2)+ROUND((ROUND(((AE64-(EU64))*AV64*1),2)*BS64),2)) -> 0 | CS64: =(ROUND((ROUND(((EU64)*AV64*1),2)*BS64),2)+ROUND((ROUND(((AE64-(EU64))*AV64*1),2)*BS64),2)) -> 0 | CT64: =ROUND((ROUND((AF64*AV64*1),2)*BA64),2) -> 0 | CU64: =AG64 -> 0 | CV64: =(AH64*AV64) -> 0 | CW64: =AI64 -> 0 | CX64: =AJ64 -> 0 | CY64: =(ROUND((((S64+ROUND((ROUND(((EU64)*AV64*1),2)*BS64),2))*AT64)/100),2)+ROUND(((ROUND((ROUND(((AE64-(EU64))*AV64*1),2)*BS64),2)*AT64)/100),2)) -> 0 | CZ64: =(ROUND((((S64+ROUND((ROUND(((EU64)*AV64*1),2)*BS64),2))*AU64)/100),2)+ROUND(((ROUND((ROUND(((AE64-(EU64))*AV64*1),2)*BS64),2)*AU64)/100),2)) -> 0 | DN64: 0 | DO64: 0 | DP64: 1 | DQ64: 1 | DU64: 1010 | DV64: шт. | DW64: шт. | DX64: 1 | EE64: 60088638 | EF64: 130 | EG64: Сметная стоимость оборудования | EH64: 0 | EJ64: 3 | EK64: 746 | EL64: ТСН-2001.13. Сметная стоимость оборудования | EM64: ТСН-2001.13 | EQ64: 0 | ER64: 0 | ES64: 8731.7 | ET64: 0 | EU64: 0 | EV64: 0 | EW64: 0 | EX64: 0 | EY64: 0 | FQ64: 0 | FR64: =P64 -> 8731.7 | FS64: 0 | FX64: 0 | FY64: 0 | GA64: [77 000 / 1,2 / 7,66] + 3% Трансп + 1,2% Заг.скл | GD64: 1 | GF64: -1212810449 | GG64: 2 | GH64: 4 | GI64: -2 | GJ64: 0 | GK64: 0 | GL64: =ROUND(IF(AND(BH64=3,BI64=3,FS64<>0),P64,0),2) -> 0 | GM64: =ROUND(O64+X64+Y64,2)+GX64 -> 8731.7 | GN64: =IF(OR(BI64=0,BI64=1),GM64-GX64,0) -> 0 | GO64: =IF(BI64=2,GM64-GX64,0) -> 0 | GP64: =IF(BI64=4,GM64-GX64,0) -> 0 | GR64: 0 | GS64: 2 | GT64: 0 | GV64: =ROUND((GT64),6) -> 0 | GW64: 1 | GX64: =ROUND(HC64*I64,2) -> 0 | HA64: 0 | HB64: 0 | HC64: =GV64*GW64 -> 0 | HE64: 3 | HF64: 1,2 | HS64: 0 | IK64: 0
A65: 17 | B65: 1 | E65: 16 | F65: КА-8 | G65: Блок АКБ 24В. Заменяемые АКБ 12В, 5Ач, количество элементов в корпусе - 18 шт. Sonar SBB-2450 | H65: шт. | I65: 1 | J65: 0 | K65: 1 | O65: =ROUND(CP65,2) -> 66884.82 | P65: =ROUND((ROUND((AC65*I65),2)*BC65),2) -> 66884.82 | Q65: =(ROUND((ROUND(((ET65)*AV65*I65),2)*BB65),2)+ROUND((ROUND(((AE65-(EU65))*AV65*I65),2)*BS65),2)) -> 0 | R65: =(ROUND((ROUND(((EU65)*AV65*I65),2)*BS65),2)+ROUND((ROUND(((AE65-(EU65))*AV65*I65),2)*BS65),2)) -> 0 | S65: =ROUND((ROUND((AF65*AV65*I65),2)*BA65),2) -> 0 | T65: =ROUND(CU65*I65,2) -> 0 | U65: =CV65*I65 -> 0 | V65: =CW65*I65 -> 0 | W65: =ROUND(CX65*I65,2) -> 0 | X65: =(ROUND((((S65+ROUND((ROUND(((EU65)*AV65*I65),2)*BS65),2))*AT65)/100),2)+ROUND(((ROUND((ROUND(((AE65-(EU65))*AV65*I65),2)*BS65),2)*AT65)/100),2)) -> 0 | Y65: =(ROUND((((S65+ROUND((ROUND(((EU65)*AV65*I65),2)*BS65),2))*AU65)/100),2)+ROUND(((ROUND((ROUND(((AE65-(EU65))*AV65*I65),2)*BS65),2)*AU65)/100),2)) -> 0 | AA65: 60256402 | AB65: =ROUND((AC65+AD65+AF65),6) -> 8731.7 | AC65: =ROUND((ES65),6) -> 8731.7 | AD65: =ROUND((((ET65)-(EU65))+AE65),6) -> 0 | AE65: =ROUND((EU65),6) -> 0 | AF65: =ROUND((EV65),6) -> 0 | AG65: =ROUND((AP65),6) -> 0 | AH65: =(EW65) -> 0 | AI65: =(EX65) -> 0 | AJ65: =(AS65) -> 0 | AK65: 8731.7 | AL65: 8731.7 | AM65: 0 | AN65: 0 | AO65: 0 | AP65: 0 | AQ65: 0 | AR65: 0 | AS65: 0 | AT65: 0 | AU65: 0 | AV65: 1 | AW65: 1 | AZ65: 1 | BA65: 1 | BB65: 1 | BC65: 7.66 | BH65: 3 | BI65: 3 | BM65: 746 | BN65: 0 | BP65: 0 | BQ65: 130 | BR65: 0 | BS65: 1 | BT65: 1 | BU65: 1 | BV65: 1 | BW65: 1 | BX65: 1 | BZ65: 0 | CA65: 0 | CE65: 1566 | CF65: 0 | CG65: 0 | CM65: 0 | CO65: 0 | CP65: =(P65+Q65+S65) -> 66884.82 | CQ65: =ROUND((ROUND((AC65*1),2)*BC65),2) -> 66884.82 | CR65: =(ROUND((ROUND(((ET65)*AV65*1),2)*BB65),2)+ROUND((ROUND(((AE65-(EU65))*AV65*1),2)*BS65),2)) -> 0 | CS65: =(ROUND((ROUND(((EU65)*AV65*1),2)*BS65),2)+ROUND((ROUND(((AE65-(EU65))*AV65*1),2)*BS65),2)) -> 0 | CT65: =ROUND((ROUND((AF65*AV65*1),2)*BA65),2) -> 0 | CU65: =AG65 -> 0 | CV65: =(AH65*AV65) -> 0 | CW65: =AI65 -> 0 | CX65: =AJ65 -> 0 | CY65: =(ROUND((((S65+ROUND((ROUND(((EU65)*AV65*1),2)*BS65),2))*AT65)/100),2)+ROUND(((ROUND((ROUND(((AE65-(EU65))*AV65*1),2)*BS65),2)*AT65)/100),2)) -> 0 | CZ65: =(ROUND((((S65+ROUND((ROUND(((EU65)*AV65*1),2)*BS65),2))*AU65)/100),2)+ROUND(((ROUND((ROUND(((AE65-(EU65))*AV65*1),2)*BS65),2)*AU65)/100),2)) -> 0 | DN65: 0 | DO65: 0 | DP65: 1 | DQ65: 1 | DU65: 1010 | DV65: шт. | DW65: шт. | DX65: 1 | EE65: 60088638 | EF65: 130 | EG65: Сметная стоимость оборудования | EH65: 0 | EJ65: 3 | EK65: 746 | EL65: ТСН-2001.13. Сметная стоимость оборудования | EM65: ТСН-2001.13 | EQ65: 0 | ER65: 8731.7 | ES65: 8731.7 | ET65: 0 | EU65: 0 | EV65: 0 | EW65: 0 | EX65: 0 | EY65: 0 | EZ65: 5 | FC65: 1 | FD65: 18 | FF65: 77000 | FQ65: 0 | FR65: =P65 -> 66884.82 | FS65: 0 | FX65: 0 | FY65: 0 | GA65: [77 000 / 1,2 / 7,66] + 3% Трансп + 1,2% Заг.скл | GD65: 1 | GF65: -1212810449 | GG65: 2 | GH65: 3 | GI65: 5 | GJ65: 0 | GK65: 0 | GL65: =ROUND(IF(AND(BH65=3,BI65=3,FS65<>0),P65,0),2) -> 0 | GM65: =ROUND(O65+X65+Y65,2)+GX65 -> 66884.82 | GN65: =IF(OR(BI65=0,BI65=1),GM65-GX65,0) -> 0 | GO65: =IF(BI65=2,GM65-GX65,0) -> 0 | GP65: =IF(BI65=4,GM65-GX65,0) -> 0 | GR65: 1 | GS65: 1 | GT65: 0 | GV65: =ROUND((GT65),6) -> 0 | GW65: 1 | GX65: =ROUND(HC65*I65,2) -> 0 | HA65: 0 | HB65: 0 | HC65: =GV65*GW65 -> 0 | HE65: 3 | HF65: 1,2 | HS65: 0 | IK65: 0
A66: 17 | B66: 1 | C66: =ROW(SmtRes!A55) -> 55 | D66: =ROW(EtalonRes!A71) -> 71 | E66: 17 | F66: 4.10-80-13 | G66: Аппараты приемные, устройства промежуточные на 1 луч | H66: 1 ШТ. | I66: 2 | J66: 0 | K66: 2 | O66: =ROUND(CP66,2) -> 41.06 | P66: =ROUND((ROUND((AC66*AW66*I66),2)*BC66),2) -> 3.92 | Q66: =(ROUND((ROUND((((ET66*1.1))*AV66*I66),2)*BB66),2)+ROUND((ROUND(((AE66-((EU66*1.1)))*AV66*I66),2)*BS66),2)) -> 0.12 | R66: =(ROUND((ROUND((((EU66*1.1))*AV66*I66),2)*BS66),2)+ROUND((ROUND(((AE66-((EU66*1.1)))*AV66*I66),2)*BS66),2)) -> 0.02 | S66: =ROUND((ROUND((AF66*AV66*I66),2)*BA66),2) -> 37.02 | T66: =ROUND(CU66*I66,2) -> 0 | U66: =CV66*I66 -> 2.76408 | V66: =CW66*I66 -> 0 | W66: =ROUND(CX66*I66,2) -> 0 | X66: =(ROUND((((S66+ROUND((ROUND((((EU66*1.1))*AV66*I66),2)*BS66),2))*AT66)/100),2)+ROUND(((ROUND((ROUND(((AE66-((EU66*1.1)))*AV66*I66),2)*BS66),2)*AT66)/100),2)) -> 33.34 | Y66: =(ROUND((((S66+ROUND((ROUND((((EU66*1.1))*AV66*I66),2)*BS66),2))*AU66)/100),2)+ROUND(((ROUND((ROUND(((AE66-((EU66*1.1)))*AV66*I66),2)*BS66),2)*AU66)/100),2)) -> 17.04 | AA66: 60256405 | AB66: =ROUND((AC66+AD66+AF66),6) -> 19.692 | AC66: =ROUND(((ES66*1)),6) -> 1.96 | AD66: =ROUND(((((ET66*1.1))-((EU66*1.1)))+AE66),6) -> 0.055 | AE66: =ROUND(((EU66*1.1)),6) -> 0.011 | AF66: =ROUND(((EV66*1.1)),6) -> 17.677 | AG66: =ROUND((AP66),6) -> 0 | AH66: =((EW66*1.1)) -> 1.32 | AI66: =((EX66*1.1)) -> 0 | AJ66: =(AS66) -> 0 | AK66: 18.08 | AL66: 1.96 | AM66: 0.05 | AN66: 0.01 | AO66: 16.07 | AP66: 0 | AQ66: 1.2 | AR66: 0 | AS66: 0 | AT66: 90 | AU66: 46 | AV66: 1.047 | AW66: 1 | AZ66: 1 | BA66: 1 | BB66: 1 | BC66: 1 | BH66: 0 | BI66: 2 | BJ66: ТСН-2001.4. Доп. 1-42. Сб. 10, т. 80, поз. 13 | BM66: 68 | BN66: 58973116 | BO66: 4.10-80-13 | BP66: 1 | BQ66: 40 | BR66: 0 | BS66: 1 | BT66: 1 | BU66: 1 | BV66: 1 | BW66: 1 | BX66: 1 | BZ66: 90 | CA66: 46 | CE66: 1566 | CF66: 0 | CG66: 0 | CM66: 0 | CN66: Поправка: Гл.12.Прил.8.п.8. 5_12.00.01.11.003 Наименование: При наличии усложненных условий производства работ (стесненность, сложность складирования и транспортной логистики, наличие в зоне производства работ действующего технологического оборудования или движения технологического транспорта и т.п.) для объектов, расположенных за пределами территории круговой магистральной системы улиц "Садовое кольцо" и за пределами Третьего транспортного кольца города Москвы пунктов "а" и "б", но в пределах Московской кольцевой автомобильной дороги | CO66: 0 | CP66: =(P66+Q66+S66) -> 41.06 | CQ66: =ROUND((ROUND((AC66*AW66*1),2)*BC66),2) -> 1.96 | CR66: =(ROUND((ROUND((((ET66*1.1))*AV66*1),2)*BB66),2)+ROUND((ROUND(((AE66-((EU66*1.1)))*AV66*1),2)*BS66),2)) -> 0.06 | CS66: =(ROUND((ROUND((((EU66*1.1))*AV66*1),2)*BS66),2)+ROUND((ROUND(((AE66-((EU66*1.1)))*AV66*1),2)*BS66),2)) -> 0.01 | CT66: =ROUND((ROUND((AF66*AV66*1),2)*BA66),2) -> 18.51 | CU66: =AG66 -> 0 | CV66: =(AH66*AV66) -> 1.38204 | CW66: =AI66 -> 0 | CX66: =AJ66 -> 0 | CY66: =(ROUND((((S66+ROUND((ROUND((((EU66*1.1))*AV66*1),2)*BS66),2))*AT66)/100),2)+ROUND(((ROUND((ROUND(((AE66-((EU66*1.1)))*AV66*1),2)*BS66),2)*AT66)/100),2)) -> 33.33 | CZ66: =(ROUND((((S66+ROUND((ROUND((((EU66*1.1))*AV66*1),2)*BS66),2))*AU66)/100),2)+ROUND(((ROUND((ROUND(((AE66-((EU66*1.1)))*AV66*1),2)*BS66),2)*AU66)/100),2)) -> 17.03 | DB66: 17 | DD66: *1 | DE66: *1,1 | DF66: *1,1 | DG66: *1,1 | DI66: *1,1 | DJ66: *1,1 | DN66: 0 | DO66: 0 | DP66: 1 | DQ66: 1 | DU66: 1013 | DV66: 1 ШТ. | DW66: 1 ШТ. | DX66: 1 | EE66: 60088532 | EF66: 40 | EG66: Монтаж оборудования | EH66: 0 | EJ66: 2 | EK66: 68 | EL66: ТСН-2001.4-10. Прокладка и монтаж сетей связи | EM66: ТСН-2001.4-10-1 | EO66: Поправка: Гл.12.Прил.8.п.8. 5_12.00.01.11.003 | EQ66: 0 | ER66: 18.08 | ES66: 1.96 | ET66: 0.05 | EU66: 0.01 | EV66: 16.07 | EW66: 1.2 | EX66: 0 | EY66: 0 | FQ66: 0 | FR66: 0 | FS66: 0 | FX66: 90 | FY66: 46 | GD66: 1 | GF66: 1665592289 | GG66: 2 | GH66: 1 | GI66: 2 | GJ66: 0 | GK66: 0 | GL66: =ROUND(IF(AND(BH66=3,BI66=3,FS66<>0),P66,0),2) -> 0 | GM66: =ROUND(O66+X66+Y66,2)+GX66 -> 91.44 | GN66: =IF(OR(BI66=0,BI66=1),GM66-GX66,0) -> 0 | GO66: =IF(BI66=2,GM66-GX66,0) -> 91.44 | GP66: =IF(BI66=4,GM66-GX66,0) -> 0 | GR66: 0 | GS66: 3 | GT66: 0 | GV66: =ROUND((GT66),6) -> 0 | GW66: 1 | GX66: =ROUND(HC66*I66,2) -> 0 | HA66: 0 | HB66: 0 | HC66: =GV66*GW66 -> 0 | HS66: 0 | IK66: 0
A67: 17 | B67: 1 | C67: =ROW(SmtRes!A56) -> 56 | D67: =ROW(EtalonRes!A72) -> 72 | E67: 17 | F67: 4.10-80-13 | G67: Аппараты приемные, устройства промежуточные на 1 луч | H67: 1 ШТ. | I67: 2 | J67: 0 | K67: 2 | O67: =ROUND(CP67,2) -> 2076.78 | P67: =ROUND((ROUND((AC67*AW67*I67),2)*BC67),2) -> 38.77 | Q67: =(ROUND((ROUND((((ET67*1.1))*AV67*I67),2)*BB67),2)+ROUND((ROUND(((AE67-((EU67*1.1)))*AV67*I67),2)*BS67),2)) -> 2.28 | R67: =(ROUND((ROUND((((EU67*1.1))*AV67*I67),2)*BS67),2)+ROUND((ROUND(((AE67-((EU67*1.1)))*AV67*I67),2)*BS67),2)) -> 1.1 | S67: =ROUND((ROUND((AF67*AV67*I67),2)*BA67),2) -> 2035.73 | T67: =ROUND(CU67*I67,2) -> 0 | U67: =CV67*I67 -> 2.76408 | V67: =CW67*I67 -> 0 | W67: =ROUND(CX67*I67,2) -> 0 | X67: =(ROUND((((S67+ROUND((ROUND((((EU67*1.1))*AV67*I67),2)*BS67),2))*AT67)/100),2)+ROUND(((ROUND((ROUND(((AE67-((EU67*1.1)))*AV67*I67),2)*BS67),2)*AT67)/100),2)) -> 1833.15 | Y67: =(ROUND((((S67+ROUND((ROUND((((EU67*1.1))*AV67*I67),2)*BS67),2))*AU67)/100),2)+ROUND(((ROUND((ROUND(((AE67-((EU67*1.1)))*AV67*I67),2)*BS67),2)*AU67)/100),2)) -> 936.94 | AA67: 60256402 | AB67: =ROUND((AC67+AD67+AF67),6) -> 19.692 | AC67: =ROUND(((ES67*1)),6) -> 1.96 | AD67: =ROUND(((((ET67*1.1))-((EU67*1.1)))+AE67),6) -> 0.055 | AE67: =ROUND(((EU67*1.1)),6) -> 0.011 | AF67: =ROUND(((EV67*1.1)),6) -> 17.677 | AG67: =ROUND((AP67),6) -> 0 | AH67: =((EW67*1.1)) -> 1.32 | AI67: =((EX67*1.1)) -> 0 | AJ67: =(AS67) -> 0 | AK67: 18.08 | AL67: 1.96 | AM67: 0.05 | AN67: 0.01 | AO67: 16.07 | AP67: 0 | AQ67: 1.2 | AR67: 0 | AS67: 0 | AT67: 90 | AU67: 46 | AV67: 1.047 | AW67: 1 | AZ67: 1 | BA67: 54.99 | BB67: 19 | BC67: 9.89 | BH67: 0 | BI67: 2 | BJ67: ТСН-2001.4. Доп. 1-42. Сб. 10, т. 80, поз. 13 | BM67: 68 | BN67: 58973116 | BO67: 4.10-80-13 | BP67: 1 | BQ67: 40 | BR67: 0 | BS67: 54.99 | BT67: 1 | BU67: 1 | BV67: 1 | BW67: 1 | BX67: 1 | BZ67: 90 | CA67: 46 | CE67: 1566 | CF67: 0 | CG67: 0 | CM67: 0 | CN67: Поправка: Гл.12.Прил.8.п.8. 5_12.00.01.11.003 Наименование: При наличии усложненных условий производства работ (стесненность, сложность складирования и транспортной логистики, наличие в зоне производства работ действующего технологического оборудования или движения технологического транспорта и т.п.) для объектов, расположенных за пределами территории круговой магистральной системы улиц "Садовое кольцо" и за пределами Третьего транспортного кольца города Москвы пунктов "а" и "б", но в пределах Московской кольцевой автомобильной дороги | CO67: 0 | CP67: =(P67+Q67+S67) -> 2076.78 | CQ67: =ROUND((ROUND((AC67*AW67*1),2)*BC67),2) -> 19.38 | CR67: =(ROUND((ROUND((((ET67*1.1))*AV67*1),2)*BB67),2)+ROUND((ROUND(((AE67-((EU67*1.1)))*AV67*1),2)*BS67),2)) -> 1.14 | CS67: =(ROUND((ROUND((((EU67*1.1))*AV67*1),2)*BS67),2)+ROUND((ROUND(((AE67-((EU67*1.1)))*AV67*1),2)*BS67),2)) -> 0.55 | CT67: =ROUND((ROUND((AF67*AV67*1),2)*BA67),2) -> 1017.86 | CU67: =AG67 -> 0 | CV67: =(AH67*AV67) -> 1.38204 | CW67: =AI67 -> 0 | CX67: =AJ67 -> 0 | CY67: =(ROUND((((S67+ROUND((ROUND((((EU67*1.1))*AV67*1),2)*BS67),2))*AT67)/100),2)+ROUND(((ROUND((ROUND(((AE67-((EU67*1.1)))*AV67*1),2)*BS67),2)*AT67)/100),2)) -> 1832.65 | CZ67: =(ROUND((((S67+ROUND((ROUND((((EU67*1.1))*AV67*1),2)*BS67),2))*AU67)/100),2)+ROUND(((ROUND((ROUND(((AE67-((EU67*1.1)))*AV67*1),2)*BS67),2)*AU67)/100),2)) -> 936.69 | DB67: 18 | DD67: *1 | DE67: *1,1 | DF67: *1,1 | DG67: *1,1 | DI67: *1,1 | DJ67: *1,1 | DN67: 0 | DO67: 0 | DP67: 1 | DQ67: 1 | DU67: 1013 | DV67: 1 ШТ. | DW67: 1 ШТ. | DX67: 1 | EE67: 60088532 | EF67: 40 | EG67: Монтаж оборудования | EH67: 0 | EJ67: 2 | EK67: 68 | EL67: ТСН-2001.4-10. Прокладка и монтаж сетей связи | EM67: ТСН-2001.4-10-1 | EO67: Поправка: Гл.12.Прил.8.п.8. 5_12.00.01.11.003 | EQ67: 0 | ER67: 18.08 | ES67: 1.96 | ET67: 0.05 | EU67: 0.01 | EV67: 16.07 | EW67: 1.2 | EX67: 0 | EY67: 0 | FQ67: 0 | FR67: 0 | FS67: 0 | FX67: 90 | FY67: 46 | GD67: 1 | GF67: 1665592289 | GG67: 2 | GH67: 1 | GI67: 2 | GJ67: 0 | GK67: 0 | GL67: =ROUND(IF(AND(BH67=3,BI67=3,FS67<>0),P67,0),2) -> 0 | GM67: =ROUND(O67+X67+Y67,2)+GX67 -> 4846.87 | GN67: =IF(OR(BI67=0,BI67=1),GM67-GX67,0) -> 0 | GO67: =IF(BI67=2,GM67-GX67,0) -> 4846.87 | GP67: =IF(BI67=4,GM67-GX67,0) -> 0 | GR67: 0 | GS67: 3 | GT67: 0 | GV67: =ROUND((GT67),6) -> 0 | GW67: 1 | GX67: =ROUND(HC67*I67,2) -> 0 | HA67: 0 | HB67: 0 | HC67: =GV67*GW67 -> 0 | HS67: 0 | IK67: 0
A68: 17 | B68: 1 | E68: 18 | F68: КА-9 | G68: Изолятор шлейфа ИЗ-1-R3 | H68: шт. | I68: 2 | J68: 0 | K68: 2 | O68: =ROUND(CP68,2) -> 154.46 | P68: =ROUND((ROUND((AC68*I68),2)*BC68),2) -> 154.46 | Q68: =(ROUND((ROUND(((ET68)*AV68*I68),2)*BB68),2)+ROUND((ROUND(((AE68-(EU68))*AV68*I68),2)*BS68),2)) -> 0 | R68: =(ROUND((ROUND(((EU68)*AV68*I68),2)*BS68),2)+ROUND((ROUND(((AE68-(EU68))*AV68*I68),2)*BS68),2)) -> 0 | S68: =ROUND((ROUND((AF68*AV68*I68),2)*BA68),2) -> 0 | T68: =ROUND(CU68*I68,2) -> 0 | U68: =CV68*I68 -> 0 | V68: =CW68*I68 -> 0 | W68: =ROUND(CX68*I68,2) -> 0 | X68: =(ROUND((((S68+ROUND((ROUND(((EU68)*AV68*I68),2)*BS68),2))*AT68)/100),2)+ROUND(((ROUND((ROUND(((AE68-(EU68))*AV68*I68),2)*BS68),2)*AT68)/100),2)) -> 0 | Y68: =(ROUND((((S68+ROUND((ROUND(((EU68)*AV68*I68),2)*BS68),2))*AU68)/100),2)+ROUND(((ROUND((ROUND(((AE68-(EU68))*AV68*I68),2)*BS68),2)*AU68)/100),2)) -> 0 | AA68: 60256405 | AB68: =ROUND((AC68+AD68+AF68),6) -> 77.23 | AC68: =ROUND((ES68),6) -> 77.23 | AD68: =ROUND((((ET68)-(EU68))+AE68),6) -> 0 | AE68: =ROUND((EU68),6) -> 0 | AF68: =ROUND((EV68),6) -> 0 | AG68: =ROUND((AP68),6) -> 0 | AH68: =(EW68) -> 0 | AI68: =(EX68) -> 0 | AJ68: =(AS68) -> 0 | AK68: 77.23 | AL68: 77.23 | AM68: 0 | AN68: 0 | AO68: 0 | AP68: 0 | AQ68: 0 | AR68: 0 | AS68: 0 | AT68: 0 | AU68: 0 | AV68: 1 | AW68: 1 | AZ68: 1 | BA68: 1 | BB68: 1 | BC68: 1 | BH68: 3 | BI68: 3 | BM68: 746 | BN68: 0 | BP68: 0 | BQ68: 130 | BR68: 0 | BS68: 1 | BT68: 1 | BU68: 1 | BV68: 1 | BW68: 1 | BX68: 1 | BZ68: 0 | CA68: 0 | CE68: 1566 | CF68: 0 | CG68: 0 | CM68: 0 | CO68: 0 | CP68: =(P68+Q68+S68) -> 154.46 | CQ68: =ROUND((ROUND((AC68*1),2)*BC68),2) -> 77.23 | CR68: =(ROUND((ROUND(((ET68)*AV68*1),2)*BB68),2)+ROUND((ROUND(((AE68-(EU68))*AV68*1),2)*BS68),2)) -> 0 | CS68: =(ROUND((ROUND(((EU68)*AV68*1),2)*BS68),2)+ROUND((ROUND(((AE68-(EU68))*AV68*1),2)*BS68),2)) -> 0 | CT68: =ROUND((ROUND((AF68*AV68*1),2)*BA68),2) -> 0 | CU68: =AG68 -> 0 | CV68: =(AH68*AV68) -> 0 | CW68: =AI68 -> 0 | CX68: =AJ68 -> 0 | CY68: =(ROUND((((S68+ROUND((ROUND(((EU68)*AV68*1),2)*BS68),2))*AT68)/100),2)+ROUND(((ROUND((ROUND(((AE68-(EU68))*AV68*1),2)*BS68),2)*AT68)/100),2)) -> 0 | CZ68: =(ROUND((((S68+ROUND((ROUND(((EU68)*AV68*1),2)*BS68),2))*AU68)/100),2)+ROUND(((ROUND((ROUND(((AE68-(EU68))*AV68*1),2)*BS68),2)*AU68)/100),2)) -> 0 | DN68: 0 | DO68: 0 | DP68: 1 | DQ68: 1 | DU68: 1010 | DV68: шт. | DW68: шт. | DX68: 1 | EE68: 60088638 | EF68: 130 | EG68: Сметная стоимость оборудования | EH68: 0 | EJ68: 3 | EK68: 746 | EL68: ТСН-2001.13. Сметная стоимость оборудования | EM68: ТСН-2001.13 | EQ68: 0 | ER68: 0 | ES68: 77.23 | ET68: 0 | EU68: 0 | EV68: 0 | EW68: 0 | EX68: 0 | EY68: 0 | FQ68: 0 | FR68: =P68 -> 154.46 | FS68: 0 | FX68: 0 | FY68: 0 | GA68: [681 / 1,2 / 7,66] + 3% Трансп + 1,2% Заг.скл | GD68: 1 | GF68: -826287204 | GG68: 2 | GH68: 4 | GI68: -2 | GJ68: 0 | GK68: 0 | GL68: =ROUND(IF(AND(BH68=3,BI68=3,FS68<>0),P68,0),2) -> 0 | GM68: =ROUND(O68+X68+Y68,2)+GX68 -> 154.46 | GN68: =IF(OR(BI68=0,BI68=1),GM68-GX68,0) -> 0 | GO68: =IF(BI68=2,GM68-GX68,0) -> 0 | GP68: =IF(BI68=4,GM68-GX68,0) -> 0 | GR68: 0 | GS68: 2 | GT68: 0 | GV68: =ROUND((GT68),6) -> 0 | GW68: 1 | GX68: =ROUND(HC68*I68,2) -> 0 | HA68: 0 | HB68: 0 | HC68: =GV68*GW68 -> 0 | HE68: 3 | HF68: 1,2 | HS68: 0 | IK68: 0
A69: 17 | B69: 1 | E69: 18 | F69: КА-9 | G69: Изолятор шлейфа ИЗ-1-R3 | H69: шт. | I69: 2 | J69: 0 | K69: 2 | O69: =ROUND(CP69,2) -> 1183.16 | P69: =ROUND((ROUND((AC69*I69),2)*BC69),2) -> 1183.16 | Q69: =(ROUND((ROUND(((ET69)*AV69*I69),2)*BB69),2)+ROUND((ROUND(((AE69-(EU69))*AV69*I69),2)*BS69),2)) -> 0 | R69: =(ROUND((ROUND(((EU69)*AV69*I69),2)*BS69),2)+ROUND((ROUND(((AE69-(EU69))*AV69*I69),2)*BS69),2)) -> 0 | S69: =ROUND((ROUND((AF69*AV69*I69),2)*BA69),2) -> 0 | T69: =ROUND(CU69*I69,2) -> 0 | U69: =CV69*I69 -> 0 | V69: =CW69*I69 -> 0 | W69: =ROUND(CX69*I69,2) -> 0 | X69: =(ROUND((((S69+ROUND((ROUND(((EU69)*AV69*I69),2)*BS69),2))*AT69)/100),2)+ROUND(((ROUND((ROUND(((AE69-(EU69))*AV69*I69),2)*BS69),2)*AT69)/100),2)) -> 0 | Y69: =(ROUND((((S69+ROUND((ROUND(((EU69)*AV69*I69),2)*BS69),2))*AU69)/100),2)+ROUND(((ROUND((ROUND(((AE69-(EU69))*AV69*I69),2)*BS69),2)*AU69)/100),2)) -> 0 | AA69: 60256402 | AB69: =ROUND((AC69+AD69+AF69),6) -> 77.23 | AC69: =ROUND((ES69),6) -> 77.23 | AD69: =ROUND((((ET69)-(EU69))+AE69),6) -> 0 | AE69: =ROUND((EU69),6) -> 0 | AF69: =ROUND((EV69),6) -> 0 | AG69: =ROUND((AP69),6) -> 0 | AH69: =(EW69) -> 0 | AI69: =(EX69) -> 0 | AJ69: =(AS69) -> 0 | AK69: 77.23 | AL69: 77.23 | AM69: 0 | AN69: 0 | AO69: 0 | AP69: 0 | AQ69: 0 | AR69: 0 | AS69: 0 | AT69: 0 | AU69: 0 | AV69: 1 | AW69: 1 | AZ69: 1 | BA69: 1 | BB69: 1 | BC69: 7.66 | BH69: 3 | BI69: 3 | BM69: 746 | BN69: 0 | BP69: 0 | BQ69: 130 | BR69: 0 | BS69: 1 | BT69: 1 | BU69: 1 | BV69: 1 | BW69: 1 | BX69: 1 | BZ69: 0 | CA69: 0 | CE69: 1566 | CF69: 0 | CG69: 0 | CM69: 0 | CO69: 0 | CP69: =(P69+Q69+S69) -> 1183.16 | CQ69: =ROUND((ROUND((AC69*1),2)*BC69),2) -> 591.58 | CR69: =(ROUND((ROUND(((ET69)*AV69*1),2)*BB69),2)+ROUND((ROUND(((AE69-(EU69))*AV69*1),2)*BS69),2)) -> 0 | CS69: =(ROUND((ROUND(((EU69)*AV69*1),2)*BS69),2)+ROUND((ROUND(((AE69-(EU69))*AV69*1),2)*BS69),2)) -> 0 | CT69: =ROUND((ROUND((AF69*AV69*1),2)*BA69),2) -> 0 | CU69: =AG69 -> 0 | CV69: =(AH69*AV69) -> 0 | CW69: =AI69 -> 0 | CX69: =AJ69 -> 0 | CY69: =(ROUND((((S69+ROUND((ROUND(((EU69)*AV69*1),2)*BS69),2))*AT69)/100),2)+ROUND(((ROUND((ROUND(((AE69-(EU69))*AV69*1),2)*BS69),2)*AT69)/100),2)) -> 0 | CZ69: =(ROUND((((S69+ROUND((ROUND(((EU69)*AV69*1),2)*BS69),2))*AU69)/100),2)+ROUND(((ROUND((ROUND(((AE69-(EU69))*AV69*1),2)*BS69),2)*AU69)/100),2)) -> 0 | DN69: 0 | DO69: 0 | DP69: 1 | DQ69: 1 | DU69: 1010 | DV69: шт. | DW69: шт. | DX69: 1 | EE69: 60088638 | EF69: 130 | EG69: Сметная стоимость оборудования | EH69: 0 | EJ69: 3 | EK69: 746 | EL69: ТСН-2001.13. Сметная стоимость оборудования | EM69: ТСН-2001.13 | EQ69: 0 | ER69: 77.23 | ES69: 77.23 | ET69: 0 | EU69: 0 | EV69: 0 | EW69: 0 | EX69: 0 | EY69: 0 | EZ69: 5 | FC69: 1 | FD69: 18 | FF69: 681 | FQ69: 0 | FR69: =P69 -> 1183.16 | FS69: 0 | FX69: 0 | FY69: 0 | GA69: [681 / 1,2 / 7,66] + 3% Трансп + 1,2% Заг.скл | GD69: 1 | GF69: -826287204 | GG69: 2 | GH69: 3 | GI69: 5 | GJ69: 0 | GK69: 0 | GL69: =ROUND(IF(AND(BH69=3,BI69=3,FS69<>0),P69,0),2) -> 0 | GM69: =ROUND(O69+X69+Y69,2)+GX69 -> 1183.16 | GN69: =IF(OR(BI69=0,BI69=1),GM69-GX69,0) -> 0 | GO69: =IF(BI69=2,GM69-GX69,0) -> 0 | GP69: =IF(BI69=4,GM69-GX69,0) -> 0 | GR69: 1 | GS69: 1 | GT69: 0 | GV69: =ROUND((GT69),6) -> 0 | GW69: 1 | GX69: =ROUND(HC69*I69,2) -> 0 | HA69: 0 | HB69: 0 | HC69: =GV69*GW69 -> 0 | HE69: 3 | HF69: 1,2 | HS69: 0 | IK69: 0
A70: 17 | B70: 1 | C70: =ROW(SmtRes!A58) -> 58 | D70: =ROW(EtalonRes!A75) -> 75 | E70: 19 | F70: 4.11-3-1 | G70: Установка прибора массой до 5 кг на металлоконструкциях или щитах | H70: 1 ШТ. | I70: 2 | J70: 0 | K70: 2 | O70: =ROUND(CP70,2) -> 15.55 | P70: =ROUND((ROUND((AC70*AW70*I70),2)*BC70),2) -> 0 | Q70: =(ROUND((ROUND((((ET70*1.1))*AV70*I70),2)*BB70),2)+ROUND((ROUND(((AE70-((EU70*1.1)))*AV70*I70),2)*BS70),2)) -> 0 | R70: =(ROUND((ROUND((((EU70*1.1))*AV70*I70),2)*BS70),2)+ROUND((ROUND(((AE70-((EU70*1.1)))*AV70*I70),2)*BS70),2)) -> 0 | S70: =ROUND((ROUND((AF70*AV70*I70),2)*BA70),2) -> 15.55 | T70: =ROUND(CU70*I70,2) -> 0 | U70: =CV70*I70 -> 1.197768 | V70: =CW70*I70 -> 0 | W70: =ROUND(CX70*I70,2) -> 0 | X70: =(ROUND((((S70+ROUND((ROUND((((EU70*1.1))*AV70*I70),2)*BS70),2))*AT70)/100),2)+ROUND(((ROUND((ROUND(((AE70-((EU70*1.1)))*AV70*I70),2)*BS70),2)*AT70)/100),2)) -> 14 | Y70: =(ROUND((((S70+ROUND((ROUND((((EU70*1.1))*AV70*I70),2)*BS70),2))*AU70)/100),2)+ROUND(((ROUND((ROUND(((AE70-((EU70*1.1)))*AV70*I70),2)*BS70),2)*AU70)/100),2)) -> 7.15 | AA70: 60256405 | AB70: =ROUND((AC70+AD70+AF70),6) -> 7.425 | AC70: =ROUND(((ES70*1)),6) -> 0 | AD70: =ROUND(((((ET70*1.1))-((EU70*1.1)))+AE70),6) -> 0 | AE70: =ROUND(((EU70*1.1)),6) -> 0 | AF70: =ROUND(((EV70*1.1)),6) -> 7.425 | AG70: =ROUND((AP70),6) -> 0 | AH70: =((EW70*1.1)) -> 0.572 | AI70: =((EX70*1.1)) -> 0 | AJ70: =(AS70) -> 0 | AK70: 6.75 | AL70: 0 | AM70: 0 | AN70: 0 | AO70: 6.75 | AP70: 0 | AQ70: 0.52 | AR70: 0 | AS70: 0 | AT70: 90 | AU70: 46 | AV70: 1.047 | AW70: 1 | AZ70: 1 | BA70: 1 | BB70: 1 | BC70: 1 | BH70: 0 | BI70: 2 | BJ70: ТСН-2001.4 Доп. 67, Сб. 11, т. 3, поз. 1 | BM70: 72 | BN70: 58973116 | BO70: 4.11-3-1 | BP70: 1 | BQ70: 40 | BR70: 0 | BS70: 1 | BT70: 1 | BU70: 1 | BV70: 1 | BW70: 1 | BX70: 1 | BZ70: 90 | CA70: 46 | CE70: 1566 | CF70: 0 | CG70: 0 | CM70: 0 | CN70: Поправка: Гл.12.Прил.8.п.8. 5_12.00.01.11.003 Наименование: При наличии усложненных условий производства работ (стесненность, сложность складирования и транспортной логистики, наличие в зоне производства работ действующего технологического оборудования или движения технологического транспорта и т.п.) для объектов, расположенных за пределами территории круговой магистральной системы улиц "Садовое кольцо" и за пределами Третьего транспортного кольца города Москвы пунктов "а" и "б", но в пределах Московской кольцевой автомобильной дороги | CO70: 0 | CP70: =(P70+Q70+S70) -> 15.55 | CQ70: =ROUND((ROUND((AC70*AW70*1),2)*BC70),2) -> 0 | CR70: =(ROUND((ROUND((((ET70*1.1))*AV70*1),2)*BB70),2)+ROUND((ROUND(((AE70-((EU70*1.1)))*AV70*1),2)*BS70),2)) -> 0 | CS70: =(ROUND((ROUND((((EU70*1.1))*AV70*1),2)*BS70),2)+ROUND((ROUND(((AE70-((EU70*1.1)))*AV70*1),2)*BS70),2)) -> 0 | CT70: =ROUND((ROUND((AF70*AV70*1),2)*BA70),2) -> 7.77 | CU70: =AG70 -> 0 | CV70: =(AH70*AV70) -> 0.598884 | CW70: =AI70 -> 0 | CX70: =AJ70 -> 0 | CY70: =(ROUND((((S70+ROUND((ROUND((((EU70*1.1))*AV70*1),2)*BS70),2))*AT70)/100),2)+ROUND(((ROUND((ROUND(((AE70-((EU70*1.1)))*AV70*1),2)*BS70),2)*AT70)/100),2)) -> 14 | CZ70: =(ROUND((((S70+ROUND((ROUND((((EU70*1.1))*AV70*1),2)*BS70),2))*AU70)/100),2)+ROUND(((ROUND((ROUND(((AE70-((EU70*1.1)))*AV70*1),2)*BS70),2)*AU70)/100),2)) -> 7.15 | DB70: 19 | DD70: *1 | DE70: *1,1 | DF70: *1,1 | DG70: *1,1 | DI70: *1,1 | DJ70: *1,1 | DN70: 0 | DO70: 0 | DP70: 1 | DQ70: 1 | DU70: 1013 | DV70: 1 ШТ. | DW70: 1 ШТ. | DX70: 1 | EE70: 60088536 | EF70: 40 | EG70: Монтаж оборудования | EH70: 0 | EJ70: 2 | EK70: 72 | EL70: ТСН-2001.4-11. Приборы и средства автоматизации и вычислительной техники | EM70: ТСН-2001.4-11-1 | EO70: Поправка: Гл.12.Прил.8.п.8. 5_12.00.01.11.003 | EQ70: 0 | ER70: 6.75 | ES70: 0 | ET70: 0 | EU70: 0 | EV70: 6.75 | EW70: 0.52 | EX70: 0 | EY70: 0 | FQ70: 0 | FR70: 0 | FS70: 0 | FX70: 90 | FY70: 46 | GD70: 1 | GF70: 338415528 | GG70: 2 | GH70: 1 | GI70: 2 | GJ70: 0 | GK70: 0 | GL70: =ROUND(IF(AND(BH70=3,BI70=3,FS70<>0),P70,0),2) -> 0 | GM70: =ROUND(O70+X70+Y70,2)+GX70 -> 36.7 | GN70: =IF(OR(BI70=0,BI70=1),GM70-GX70,0) -> 0 | GO70: =IF(BI70=2,GM70-GX70,0) -> 36.7 | GP70: =IF(BI70=4,GM70-GX70,0) -> 0 | GR70: 0 | GS70: 3 | GT70: 0 | GV70: =ROUND((GT70),6) -> 0 | GW70: 1 | GX70: =ROUND(HC70*I70,2) -> 0 | HA70: 0 | HB70: 0 | HC70: =GV70*GW70 -> 0 | HS70: 0 | IK70: 0
