Workbook

Sheet 02-01-13
A1: =Source!B1 -> Smeta.RU (495) 974-1589
J2: Форма № 4б
A3: Капитальный ремонт здания Государственного бюджетного общеобразовательного учреждения города Москвы "Школа №236" по адресу: г. Москва, улица Клязьминская, дом 7, корпус 4. 02-01-13 Электрочасофикация | AP3: Капитальный ремонт здания Государственного бюджетного общеобразовательного учреждения города Москвы "Школа №236" по адресу: г. Москва, улица Клязьминская, дом 7, корпус 4. 02-01-13 Электрочасофикация
A4: (наименование стройки и/или объекта)
A6: =CONCATENATE( "ЛОКАЛЬНАЯ СМЕТА № ",IF(Source!F20<>"Новая локальная смета", Source!F20, "")) -> ЛОКАЛЬНАЯ СМЕТА № 02-01-13
A8: =IF(Source!G20<>"Новая локальная смета", Source!G20, "") -> Электрочасофикация
A9: (наименование работ и затрат)
A11: =CONCATENATE( "Основание: чертежи № ", Source!J20) -> Основание: чертежи № 2024-00272-01-0-ИОС5.6
I13: В базисном уровне цен | J13: В текущем уровне цен
E14: Сметная стоимость | I14: =I15+I16+I17+I18 -> 13.31 | J14: =J15+J16+J17+J18 -> 128.31 | K14: тыс.руб.
E15: Строительные работы | I15: =ROUND((Source!F131)/1000, 2) -> 0 | J15: =ROUND((Source!P131)/1000, 2) -> 0 | K15: тыс.руб.
E16: Работы по монтажу оборудования | I16: =ROUND((Source!F132)/1000, 2) -> 1.33 | J16: =ROUND((Source!P132)/1000, 2) -> 40.14 | K16: тыс.руб.
E17: Оборудование | I17: =ROUND((Source!F123)/1000, 2) -> 11.98 | J17: =ROUND((Source!P123)/1000, 2) -> 88.17 | K17: тыс.руб.
E18: Прочие работы и затраты | I18: =ROUND((Source!F133+Source!F134)/1000, 2) -> 0 | J18: =ROUND((Source!P133+Source!P134)/1000, 2) -> 0 | K18: тыс.руб.
E19: Средства на оплату труда | I19: =(Source!F129+ Source!F128)/1000 -> 0.25722 | J19: =((Source!P129 + Source!P128)/1000) -> 14.14452 | K19: тыс.руб.
E20: Затраты труда | I20: =Source!F136 -> 19.976236 | K20: чел.-ч.
E21: Кроме того:
E22: Возврат материалов | I22: =SUM(Y28:Y113)/1000 -> 0 | J22: =SUM(Z28:Z113)/1000 -> 0 | K22: тыс.руб.
A24: Составлен(а) по ТСН-2001 с учетом Дополнения №: 80
A25: № и период сборника коэффициентов (индексов) пересчета: Коэффициенты к ТСН-2001 МГЭ Дополнение 80, строительство №217/80 III квартал 2025 года и Коэффициенты к ТСН-2001.13-2 Дополнение 46 №62/46 III квартал 2025 года | AP25: № и период сборника коэффициентов (индексов) пересчета: Коэффициенты к ТСН-2001 МГЭ Дополнение 80, строительство №217/80 III квартал 2025 года и Коэффициенты к ТСН-2001.13-2 Дополнение 46 №62/46 III квартал 2025 года
A26: № п/п | B26: Шифр расценки и коды ресурсов | C26: Наименование работ и затрат | D26: Ед. изм. | E26: Кол-во единиц | F26: Цена на ед. изм., руб. | G26: Попра- вочные коэффи- циенты | H26: Коэффи- циенты зимних удорожа- ний | I26: Всего в ценах на январь 2000 года, руб. | J26: Коэффи- циенты (индек- сы) пере- счета, нормы НР и СП | K26: ВСЕГО затрат в текущем уровне цен, руб.
A27: 1 | B27: 2 | C27: 3 | D27: 4 | E27: 5 | F27: 6 | G27: 7 | H27: 8 | I27: 9 | J27: 10 | K27: 11
A29: =CONCATENATE("Раздел: ",IF(Source!G24<>"Новый раздел", Source!G24, "")) -> Раздел: Оборудование
A30: 1 | B30: =Source!F28 -> 4.10-85-1 | C30: Электрочасы первичные, часы первичные электрические показывающие кварцевые типа ПКЧЗ-2-РИ-Р24-Р6-1 | D30: =Source!H28 -> 1 ШТ. | E30: =Source!I28 -> 1 | Q30: =Source!X28 -> 42.82 | R30: =Source!X29 -> 2354.78 | S30: =Source!Y28 -> 21.89 | T30: =Source!Y29 -> 1203.55 | U30: =ROUND((175/100)*ROUND(Source!R28, 2), 2) -> 0 | V30: =ROUND((0/100)*ROUND(Source!R29, 2), 2) -> 0 | AC30: 0
C31: ЗП | F31: =Source!AO28 -> 41.31 | G31: =Source!DG28 -> *1,1 | H31: =Source!AV29 -> 1.047 | I31: =Source!S28 -> 47.58 | J31: =IF(Source!BA29<> 0, Source!BA29, 1) -> 54.99 | K31: =Source!S29 -> 2616.42
C32: МР | F32: =Source!AL28 -> 0.49 | G32: =Source!DD28 -> *1 | H32: =Source!AW29 -> 1 | I32: =Source!P28 -> 0.49 | J32: =IF(Source!BC29<> 0, Source!BC29, 1) -> 9.9 | K32: =Source!P29 -> 4.85
C33: НР от ФОТ | D33: % | E33: =Source!BZ29 -> 90 | I33: =SUM(Q30:Q32) -> 42.82 | J33: =Source!AT29 -> 90 | K33: =SUM(R30:R32) -> 2354.78
C34: СП от ФОТ | D34: % | E34: =Source!CA29 -> 46 | I34: =SUM(S30:S33) -> 21.89 | J34: =Source!AU29 -> 46 | K34: =SUM(T30:T33) -> 1203.55
C35: ЗТР | D35: чел-ч | E35: =Source!AQ28 -> 3 | G35: =Source!DI28 -> *1,1 | H35: =Source!AV29 -> 1.047 | I35: =Source!U28 -> 3.4551
C36: ВСЕГО работ по позиции: | H36: =I31+I32+I33+I34+0-0-0 -> 112.78 | J36: =K31+K32+K33+K34+0-0-0 -> 6179.6
C37: ВСЕГО оборудование по позиции: | H37: =0+0 -> 0 | J37: =0+0 -> 0
C38: ВСЕГО по позиции: | H38: =I31+I32+I33+I34+0 -> 112.78 | J38: =K31+K32+K33+K34+0 -> 6179.6 | O38: =I31+I32+I33+I34+0 -> 112.78 | P38: =K31+K32+K33+K34+0 -> 6179.6
A40: 2 | B40: =Source!F30 -> КА-1 | C40: ОБОРУДОВАНИЕ:_x000D_ Часовая станция "Первичные часы" ПИК-2М-4002 10 518,85 = [92 760 / 1,2 / 7,66] + 3% Трансп + 1,2% Заг.скл | D40: =Source!H30 -> ШТ | E40: =Source!I30 -> 1 | F40: =Source!AL30 -> 10518.85 | G40: =Source!DD30 | H40: =Source!AW31 -> 1 | I40: =Source!P30 -> 10518.85 | J40: =IF(Source!BC31<> 0, Source!BC31, 1) -> 7.66 | K40: =Source!P31 -> 80574.39 | Q40: =Source!X30 -> 0 | R40: =Source!X31 -> 0 | S40: =Source!Y30 -> 0 | T40: =Source!Y31 -> 0 | U40: =ROUND((175/100)*ROUND(Source!R30, 2), 2) -> 0 | V40: =ROUND((0/100)*ROUND(Source!R31, 2), 2) -> 0 | AC40: 5
C41: ВСЕГО по позиции: | H41: =I40+0 -> 10518.85 | J41: =K40+0 -> 80574.39 | O41: =I40+0 -> 10518.85 | P41: =K40+0 -> 80574.39
A43: 3 | B43: =Source!F32 -> 4.10-86-1 | C43: Электрочасы вторичные для помещений, электрочасы односторонние на стене | D43: =Source!H32 -> 1 ШТ. | E43: =Source!I32 -> 2 | Q43: =Source!X32 -> 49.34 | R43: =Source!X33 -> 2713.1 | S43: =Source!Y32 -> 25.22 | T43: =Source!Y33 -> 1386.69 | U43: =ROUND((175/100)*ROUND(Source!R32, 2), 2) -> 0 | V43: =ROUND((0/100)*ROUND(Source!R33, 2), 2) -> 0 | AC43: 0
C44: ЗП | F44: =Source!AO32 -> 23.8 | G44: =Source!DG32 -> *1,1 | H44: =Source!AV33 -> 1.047 | I44: =Source!S32 -> 54.82 | J44: =IF(Source!BA33<> 0, Source!BA33, 1) -> 54.99 | K44: =Source!S33 -> 3014.55
C45: МР | F45: =Source!AL32 -> 0.28 | G45: =Source!DD32 -> *1 | H45: =Source!AW33 -> 1 | I45: =Source!P32 -> 0.56 | J45: =IF(Source!BC33<> 0, Source!BC33, 1) -> 9.89 | K45: =Source!P33 -> 5.54
C46: НР от ФОТ | D46: % | E46: =Source!BZ33 -> 90 | I46: =SUM(Q43:Q45) -> 49.34 | J46: =Source!AT33 -> 90 | K46: =SUM(R43:R45) -> 2713.1
C47: СП от ФОТ | D47: % | E47: =Source!CA33 -> 46 | I47: =SUM(S43:S46) -> 25.22 | J47: =Source!AU33 -> 46 | K47: =SUM(T43:T46) -> 1386.69
C48: ЗТР | D48: чел-ч | E48: =Source!AQ32 -> 2 | G48: =Source!DI32 -> *1,1 | H48: =Source!AV33 -> 1.047 | I48: =Source!U32 -> 4.6068
C49: ВСЕГО работ по позиции: | H49: =I44+I45+I46+I47+0-0-0 -> 129.94 | J49: =K44+K45+K46+K47+0-0-0 -> 7119.88
C50: ВСЕГО оборудование по позиции: | H50: =0+0 -> 0 | J50: =0+0 -> 0
C51: ВСЕГО по позиции: | H51: =I44+I45+I46+I47+0 -> 129.94 | J51: =K44+K45+K46+K47+0 -> 7119.88 | O51: =I44+I45+I46+I47+0 -> 129.94 | P51: =K44+K45+K46+K47+0 -> 7119.88
A53: 4 | B53: =Source!F34 -> 13.1-2-211 | C53: ОБОРУДОВАНИЕ:_x000D_ Часы электрические вторичные стрелочные, типа ВЧ03/03 | D53: =Source!H34 -> шт. | E53: =Source!I34 -> 2 | F53: =Source!AL34 -> 730.63 | G53: =Source!DD34 | H53: =Source!AW35 -> 1 | I53: =Source!P34 -> 1461.26 | J53: =IF(Source!BC35<> 0, Source!BC35, 1) -> 5.2 | K53: =Source!P35 -> 7598.55 | Q53: =Source!X34 -> 0 | R53: =Source!X35 -> 0 | S53: =Source!Y34 -> 0 | T53: =Source!Y35 -> 0 | U53: =ROUND((175/100)*ROUND(Source!R34, 2), 2) -> 0 | V53: =ROUND((0/100)*ROUND(Source!R35, 2), 2) -> 0 | AC53: 5
C54: ВСЕГО по позиции: | H54: =I53+0 -> 1461.26 | J54: =K53+0 -> 7598.55 | O54: =I53+0 -> 1461.26 | P54: =K53+0 -> 7598.55
A57: =CONCATENATE("Итого по разделу: ",IF(Source!G37<>"Новый раздел", Source!G37, "")) -> Итого по разделу: Оборудование | H57: =SUM(O29:O56) -> 12222.83 | J57: =SUM(P29:P56) -> 101472.42
A58: Итого по ТСН-2001.16 | I58: =SUM(W29:W57) -> 0 | J58: =SUM(X29:X57) -> 0
A59: Итого возвратных сумм | I59: =SUM(Y29:Y58) -> 0 | J59: =SUM(Z29:Z58) -> 0
A61: =CONCATENATE("Раздел: ",IF(Source!G67<>"Новый раздел", Source!G67, "")) -> Раздел: Кабельные изделия
A62: 5 | B62: =Source!F71 -> 4.8-288-1 | C62: Трубы гофрированные поливинилхлоридные наружным диаметром 16 мм открыто по стенам и потолкам с установкой соединительных коробок | D62: =Source!H71 -> 100 м | E62: =Source!I71 -> 0.5 | Q62: =Source!X71 -> 106.43 | R62: =Source!X72 -> 5852.5 | S62: =Source!Y71 -> 55.96 | T62: =Source!Y72 -> 3077.09 | U62: =ROUND((175/100)*ROUND(Source!R71, 2), 2) -> 5.5 | V62: =ROUND((0/100)*ROUND(Source!R72, 2), 2) -> 0 | AC62: 0
C63: ="Объем: "&Source!I71&"=50/"&"100" -> Объем: 0,5=50/100
C64: ЗП | F64: =Source!AO71 -> 185.09 | G64: =Source!DG71 -> *1,1 | H64: =Source!AV72 -> 1.047 | I64: =Source!S71 -> 106.58 | J64: =IF(Source!BA72<> 0, Source!BA72, 1) -> 54.99 | K64: =Source!S72 -> 5860.83
C65: ЭМ | F65: =Source!AM71 -> 32.74 | G65: =Source!DE71 -> *1,1 | H65: =Source!AV72 -> 1.047 | I65: =Source!Q71 -> 18.85 | J65: =IF(Source!BB72<> 0, Source!BB72, 1) -> 17.54 | K65: =Source!Q72 -> 330.63
C66: в т.ч. ЗПМ | F66: =Source!AN71 -> 5.46 | G66: =Source!DF71 -> *1,1 | H66: =Source!AV72 -> 1.047 | I66: =Source!R71 -> 3.14 | J66: =IF(Source!BS72<> 0, Source!BS72, 1) -> 54.99 | K66: =Source!R72 -> 172.67
C67: МР | F67: =Source!AL71 -> 343.03 | G67: =Source!DD71 -> *1 | H67: =Source!AW72 -> 1 | I67: =Source!P71 -> 171.52 | J67: =IF(Source!BC72<> 0, Source!BC72, 1) -> 9.89 | K67: =Source!P72 -> 1696.33
A68: 5,1 | B68: =Source!F73 -> 1.12-5-371 | C68: Трубы электротехнические, гофрированные, из ПВХ, негорючие, с зондом, наружный диаметр 16 мм | D68: =Source!H73 -> м | E68: =Source!I73 -> 51 | F68: =Source!AK73 -> 2.67 | G68: к нр *1 | H68: =Source!AW74 -> 1 | I68: =Source!O73 -> 136.17 | J68: =IF(Source!BC74<> 0, Source!BC74, 1) -> 3.83 | K68: =Source!O74 -> 521.53 | Q68: =Source!X73 -> 0 | R68: =Source!X74 -> 0 | S68: =Source!Y73 -> 0 | T68: =Source!Y74 -> 0 | U68: =ROUND((175/100)*ROUND(Source!R73, 2), 2) -> 0 | V68: =ROUND((0/100)*ROUND(Source!R74, 2), 2) -> 0 | AC68: 3
C69: НР от ФОТ | D69: % | E69: =Source!BZ72 -> 97 | I69: =SUM(Q62:Q68) -> 106.43 | J69: =Source!AT72 -> 97 | K69: =SUM(R62:R68) -> 5852.5
C70: СП от ФОТ | D70: % | E70: =Source!CA72 -> 51 | I70: =SUM(S62:S69) -> 55.96 | J70: =Source!AU72 -> 51 | K70: =SUM(T62:T69) -> 3077.09
C71: ЗТР | D71: чел-ч | E71: =Source!AQ71 -> 14.37 | G71: =Source!DI71 -> *1,1 | H71: =Source!AV72 -> 1.047 | I71: =Source!U71 -> 8.2749645
C72: ВСЕГО работ по позиции: | H72: =I64+I65+I67+I69+I70+SUM(I68:I68)-SUMIF(AC68:AC68, 5, I68:I68)-SUMIF(AC68:AC68, 6, I68:I68) -> 595.51 | J72: =K64+K65+K67+K69+K70+SUM(K68:K68)-SUMIF(AC68:AC68, 5, K68:K68)-SUMIF(AC68:AC68, 6, K68:K68) -> 17338.91
C73: ВСЕГО оборудование по позиции: | H73: =SUMIF(AC68:AC68, 5, I68:I68)+SUMIF(AC68:AC68, 6, I68:I68) -> 0 | J73: =SUMIF(AC68:AC68, 5, K68:K68)+SUMIF(AC68:AC68, 6, K68:K68) -> 0
C74: ВСЕГО по позиции: | H74: =I64+I65+I67+I69+I70+SUM(I68:I68) -> 595.51 | J74: =K64+K65+K67+K69+K70+SUM(K68:K68) -> 17338.91 | O74: =I64+I65+I67+I69+I70+SUM(I68:I68) -> 595.51 | P74: =K64+K65+K67+K69+K70+SUM(K68:K68) -> 17338.91
A76: 6 | B76: =Source!F77 -> 4.8-175-1 | C76: Затягивание провода в проложенные трубы и металлические рукава, первого одножильного или многожильного в общей оплетке, суммарное сечение до 2,5 мм2 | D76: =Source!H77 -> 100 м | E76: =Source!I77 -> 0.5 | Q76: =Source!X77 -> 31.01 | R76: =Source!X78 -> 1705.29 | S76: =Source!Y77 -> 16.3 | T76: =Source!Y78 -> 896.6 | U76: =ROUND((175/100)*ROUND(Source!R77, 2), 2) -> 0.3 | V76: =ROUND((0/100)*ROUND(Source!R78, 2), 2) -> 0 | AC76: 0
C77: ="Объем: "&Source!I77&"=50/"&"100" -> Объем: 0,5=50/100
C78: ЗП | F78: =Source!AO77 -> 55.23 | G78: =Source!DG77 -> *1,1 | H78: =Source!AV78 -> 1.047 | I78: =Source!S77 -> 31.8 | J78: =IF(Source!BA78<> 0, Source!BA78, 1) -> 54.99 | K78: =Source!S78 -> 1748.68
C79: ЭМ | F79: =Source!AM77 -> 2.62 | G79: =Source!DE77 -> *1,1 | H79: =Source!AV78 -> 1.047 | I79: =Source!Q77 -> 1.51 | J79: =IF(Source!BB78<> 0, Source!BB78, 1) -> 14.57 | K79: =Source!Q78 -> 22
C80: в т.ч. ЗПМ | F80: =Source!AN77 -> 0.3 | G80: =Source!DF77 -> *1,1 | H80: =Source!AV78 -> 1.047 | I80: =Source!R77 -> 0.17 | J80: =IF(Source!BS78<> 0, Source!BS78, 1) -> 54.99 | K80: =Source!R78 -> 9.35
C81: МР | F81: =Source!AL77 -> 58.15 | G81: =Source!DD77 -> *1 | H81: =Source!AW78 -> 1 | I81: =Source!P77 -> 29.08 | J81: =IF(Source!BC78<> 0, Source!BC78, 1) -> 3.7 | K81: =Source!P78 -> 107.6
C82: НР от ФОТ | D82: % | E82: =Source!BZ78 -> 97 | I82: =SUM(Q76:Q81) -> 31.01 | J82: =Source!AT78 -> 97 | K82: =SUM(R76:R81) -> 1705.29
C83: СП от ФОТ | D83: % | E83: =Source!CA78 -> 51 | I83: =SUM(S76:S82) -> 16.3 | J83: =Source!AU78 -> 51 | K83: =SUM(T76:T82) -> 896.6
C84: ЗТР | D84: чел-ч | E84: =Source!AQ77 -> 4.49 | G84: =Source!DI77 -> *1,1 | H84: =Source!AV78 -> 1.047 | I84: =Source!U77 -> 2.5855665
C85: ВСЕГО работ по позиции: | H85: =I78+I79+I81+I82+I83+0-0-0 -> 109.7 | J85: =K78+K79+K81+K82+K83+0-0-0 -> 4480.17
C86: ВСЕГО оборудование по позиции: | H86: =0+0 -> 0 | J86: =0+0 -> 0
C87: ВСЕГО по позиции: | H87: =I78+I79+I81+I82+I83+0 -> 109.7 | J87: =K78+K79+K81+K82+K83+0 -> 4480.17 | O87: =I78+I79+I81+I82+I83+0 -> 109.7 | P87: =K78+K79+K81+K82+K83+0 -> 4480.17
A89: 7 | B89: =Source!F79 -> 4.8-175-9 | C89: Добавлять на затягивание провода в проложенные трубы и металлические рукава каждого последующего одножильного или многожильного в общей оплетке, суммарное сечение до 6 мм2 (к нормам и расценкам 4.8-175-1 и 4.8-175-2) | D89: =Source!H79 -> 100 м | E89: =Source!I79 -> 0.5 | Q89: =Source!X79 -> 12.74 | R89: =Source!X80 -> 700.36 | S89: =Source!Y79 -> 6.7 | T89: =Source!Y80 -> 368.23 | U89: =ROUND((175/100)*ROUND(Source!R79, 2), 2) -> 0.3 | V89: =ROUND((0/100)*ROUND(Source!R80, 2), 2) -> 0 | AC89: 0
C90: ="Объем: "&Source!I79&"=50/"&"100" -> Объем: 0,5=50/100
C91: ЗП | F91: =Source!AO79 -> 22.51 | G91: =Source!DG79 -> *1,1 | H91: =Source!AV80 -> 1.047 | I91: =Source!S79 -> 12.96 | J91: =IF(Source!BA80<> 0, Source!BA80, 1) -> 54.99 | K91: =Source!S80 -> 712.67
C92: ЭМ | F92: =Source!AM79 -> 2.62 | G92: =Source!DE79 -> *1,1 | H92: =Source!AV80 -> 1.047 | I92: =Source!Q79 -> 1.51 | J92: =IF(Source!BB80<> 0, Source!BB80, 1) -> 14.57 | K92: =Source!Q80 -> 22
C93: в т.ч. ЗПМ | F93: =Source!AN79 -> 0.3 | G93: =Source!DF79 -> *1,1 | H93: =Source!AV80 -> 1.047 | I93: =Source!R79 -> 0.17 | J93: =IF(Source!BS80<> 0, Source!BS80, 1) -> 54.99 | K93: =Source!R80 -> 9.35
C94: МР | F94: =Source!AL79 -> 55.47 | G94: =Source!DD79 -> *1 | H94: =Source!AW80 -> 1 | I94: =Source!P79 -> 27.74 | J94: =IF(Source!BC80<> 0, Source!BC80, 1) -> 3.09 | K94: =Source!P80 -> 85.72
C95: НР от ФОТ | D95: % | E95: =Source!BZ80 -> 97 | I95: =SUM(Q89:Q94) -> 12.74 | J95: =Source!AT80 -> 97 | K95: =SUM(R89:R94) -> 700.36
C96: СП от ФОТ | D96: % | E96: =Source!CA80 -> 51 | I96: =SUM(S89:S95) -> 6.7 | J96: =Source!AU80 -> 51 | K96: =SUM(T89:T95) -> 368.23
C97: ЗТР | D97: чел-ч | E97: =Source!AQ79 -> 1.83 | G97: =Source!DI79 -> *1,1 | H97: =Source!AV80 -> 1.047 | I97: =Source!U79 -> 1.0538055
C98: ВСЕГО работ по позиции: | H98: =I91+I92+I94+I95+I96+0-0-0 -> 61.65 | J98: =K91+K92+K94+K95+K96+0-0-0 -> 1888.98
C99: ВСЕГО оборудование по позиции: | H99: =0+0 -> 0 | J99: =0+0 -> 0
C100: ВСЕГО по позиции: | H100: =I91+I92+I94+I95+I96+0 -> 61.65 | J100: =K91+K92+K94+K95+K96+0 -> 1888.98 | O100: =I91+I92+I94+I95+I96+0 -> 61.65 | P100: =K91+K92+K94+K95+K96+0 -> 1888.98
A102: 8 | B102: =Source!F81 -> КА-2 | C102: Кабель КПСВВнг(А)-LSLTx 1x2x1,0 3 104,91 = [36 090 / 1,2 / 9,88] + 2% Заг.скл | D102: =Source!H81 -> км | E102: =Source!I81 -> 0.102 | F102: =Source!AL81 -> 3104.91 | G102: =Source!DD81 | H102: =Source!AW82 -> 1 | I102: =Source!P81 -> 316.7 | J102: =IF(Source!BC82<> 0, Source!BC82, 1) -> 9.88 | K102: =Source!P82 -> 3129 | Q102: =Source!X81 -> 0 | R102: =Source!X82 -> 0 | S102: =Source!Y81 -> 0 | T102: =Source!Y82 -> 0 | U102: =ROUND((175/100)*ROUND(Source!R81, 2), 2) -> 0 | V102: =ROUND((0/100)*ROUND(Source!R82, 2), 2) -> 0 | AC102: 3
C103: ="Объем: "&Source!I81&"=0,1*"&"1,02" -> Объем: 0,102=0,1*1,02
C104: ВСЕГО по позиции: | H104: =I102+0 -> 316.7 | J104: =K102+0 -> 3129 | O104: =I102+0 -> 316.7 | P104: =K102+0 -> 3129
A107: =CONCATENATE("Итого по разделу: ",IF(Source!G84<>"Новый раздел", Source!G84, "")) -> Итого по разделу: Кабельные изделия | H107: =SUM(O61:O106) -> 1083.56 | J107: =SUM(P61:P106) -> 26837.06
A108: Итого по ТСН-2001.16 | I108: =SUM(W61:W107) -> 0 | J108: =SUM(X61:X107) -> 0
A109: Итого возвратных сумм | I109: =SUM(Y61:Y108) -> 0 | J109: =SUM(Z61:Z108) -> 0
A111: =CONCATENATE("Итого по локальной смете: ",IF(Source!G114<>"Новая локальная смета", Source!G114, "")) -> Итого по локальной смете: Электрочасофикация | H111: =SUM(O28:O110) -> 13306.39 | J111: =SUM(P28:P110) -> 128309.48
A112: Итого по ТСН-2001.16 | I112: =SUM(W28:W111) -> 0 | J112: =SUM(X28:X111) -> 0
A113: Итого возвратных сумм | I113: =SUM(Y28:Y112) -> 0 | J113: =SUM(Z28:Z112) -> 0
A115: =CONCATENATE("Итого по смете: ",IF(Source!G144<>"Новый объект", Source!G144, "")) -> Итого по смете: 02-01-13 Электрочасофикация | H115: =SUM(O1:O114) -> 13306.39 | J115: =SUM(P1:P114) -> 128309.48
A116: Итого по ТСН-2001.16 | I116: =SUM(W1:W115) -> 0 | J116: =SUM(X1:X115) -> 0
A117: Итого возвратных сумм | I117: =SUM(Y1:Y116) -> 0 | J117: =SUM(Z1:Z116) -> 0
A120: Составил | C120: =IF(Source!AC12<>"", Source!AC12," ") | H120: =IF(Source!AB12<>"", Source!AB12," ") -> Соколова И.Н.
C121: (должность, подпись, инициалы, фамилия)
...

Sheet Ведомость объемов работ
A1: =Source!B1 -> Smeta.RU (495) 974-1589
B4: =CONCATENATE("Ведомость объемов работ ", IF(Source!AN15<>"", Source!AN15," ")) -> Ведомость объемов работ
B5: =CONCATENATE(Source!F12, " ", Source!G12) -> 02-01-13 Электрочасофикация
A8: № п/п | B8: № в ЛСР | C8: Наименование работ и затрат | D8: Единица измерения | E8: Количество | F8: Ссылка на чертежи, спецификации | G8: Формула расчета, расчет объемов работ и расхода материалов | H8: Примечание
A9: 1 | B9: 2 | C9: 3 | D9: 4 | E9: 5 | F9: 6 | G9: 7 | H9: 8
A10: =CONCATENATE("Локальная смета: ", Source!G20) -> Локальная смета: Электрочасофикация
A11: =CONCATENATE("Раздел: ", Source!G24) -> Раздел: Оборудование
A12: 1 | B12: =Source!E28 -> 1 | C12: =Source!G28 -> Электрочасы первичные, часы первичные электрические показывающие кварцевые типа ПКЧЗ-2-РИ-Р24-Р6-1 | D12: 1 ШТ. | E12: =Source!I28 -> 1 | F12: =Source!U24 | G12: =Source!I28 -> 1
A13: 2 | B13: =Source!E30 -> 2 | C13: =Source!G30 -> Часовая станция "Первичные часы" ПИК-2М-4002 | D13: ШТ | E13: =Source!I30 -> 1 | F13: =Source!U24 | G13: =Source!I30 -> 1
A14: 3 | B14: =Source!E32 -> 3 | C14: =Source!G32 -> Электрочасы вторичные для помещений, электрочасы односторонние на стене | D14: 1 ШТ. | E14: =Source!I32 -> 2 | F14: =Source!U24 | G14: =Source!I32 -> 2
A15: 4 | B15: =Source!E34 -> 4 | C15: =Source!G34 -> Часы электрические вторичные стрелочные, типа ВЧ03/03 | D15: шт. | E15: =Source!I34 -> 2 | F15: =Source!U24 | G15: =Source!I34 -> 2
A16: =CONCATENATE("Раздел: ", Source!G67) -> Раздел: Кабельные изделия
A17: 5 | B17: =Source!E71 -> 5 | C17: =Source!G71 -> Трубы гофрированные поливинилхлоридные наружным диаметром 16 мм открыто по стенам и потолкам с установкой соединительных коробок | D17: 100 м | E17: =Source!I71 -> 0.5 | F17: =Source!U67 | G17: ="=50/"&"100" -> =50/100
A18: 6 | B18: =Source!E77 -> 6 | C18: =Source!G77 -> Затягивание провода в проложенные трубы и металлические рукава, первого одножильного или многожильного в общей оплетке, суммарное сечение до 2,5 мм2 | D18: 100 м | E18: =Source!I77 -> 0.5 | F18: =Source!U67 | G18: ="=50/"&"100" -> =50/100
A19: 7 | B19: =Source!E79 -> 7 | C19: =Source!G79 -> Добавлять на затягивание провода в проложенные трубы и металлические рукава каждого последующего одножильного или многожильного в общей оплетке, суммарное сечение до 6 мм2 (к нормам и расценкам 4.8-175-1 и 4.8-175-2) | D19: 100 м | E19: =Source!I79 -> 0.5 | F19: =Source!U67 | G19: ="=50/"&"100" -> =50/100
A20: 8 | B20: =Source!E81 -> 8 | C20: =Source!G81 -> Кабель КПСВВнг(А)-LSLTx 1x2x1,0 | D20: км | E20: =Source!I81 -> 0.102 | F20: =Source!U67 | G20: ="=0,1*"&"1,02" -> =0,1*1,02
C23: Главный инженер проекта _________________ | D23: =IF(Source!X12<>"", Source!X12," ")
C25: Составил _________________ | D25: =IF(Source!AB12<>"", Source!AB12," ") -> Соколова И.Н.

Sheet Source
A1: 0 | B1: Smeta.RU (495) 974-1589 | D1: _PS_ | F1: 0 | G1: 0 | H1: 0 | I1: Smeta.RU | K1: 1 | L1: 74563 | M1: 10 | N1: 12 | O1: 0 | P1: 0 | Q1: 3
A4: 1 | B4: 1 | C4: -1 | G4: Капитальный ремонт здания Государственного бюджетного общеобразовательного учреждения города Москвы "Школа №236" по адресу: г. Москва, улица Клязьминская, дом 7, корпус 4 | EC4: 0
A12: 1 | B12: 183 | C12: 0 | D12: =ROW(A144) -> 144 | E12: 0 | G12: 02-01-13 Электрочасофикация | I12: 0 | J12: 2024-00272-01-0-ИОС5.6 | K12: 0 | L12: 0 | M12: 4098 | O12: 0 | P12: 0 | Q12: 0 | R12: 0 | S12: 0 | T12: 1 | V12: 0 | AB12: Соколова И.Н. | BB12: 0 | BH12: Сметные нормы списания | BI12: Коды ОКП для ТСН-2001 МГЭ Дополнение 80 | BJ12: 1 | BK12: 1 | BL12: 0 | BM12: 0 | BN12: 1 | BO12: 0 | BP12: 6 | BQ12: 2 | BR12: 1 | BS12: 1 | BT12: 0 | BU12: 0 | BV12: 0 | BW12: 0 | BX12: 0 | BZ12: Типовой расчет для ТСН-2001 МГЭ, Дополнение 80, строительство (1) | CA12: Территориальные сметные нормативы для Москвы ТСН-2001 (МГЭ), дополнение 80 | CB12: Территориальные сметные нормативы для Москвы ТСН-2001 (МГЭ), дополнение 80 | CC12: Территориальные сметные нормативы для Москвы ТСН-2001 (МГЭ), дополнение 80 | CD12: Территориальные сметные нормативы для Москвы ТСН-2001 (МГЭ), дополнение 80 | CE12: Поправки для ТСН-2001 от 28.11.2025 г. доп.79 | CF12: 0 | CG12: 0 | CH12: 8200 | CK12: 80 | CQ12: Территориальные сметные нормативы для Москвы (ТСН-2001) | CR12: ТЕР | CS12: 41660 | CT12: 1 | CU12: 80 | CY12: 0 | EC12: 0
A15: 15 | B15: 1
A18: 52 | B18: =B144 -> 183 | C18: =C144 -> 1 | D18: =D144 -> 12 | E18: =E144 -> 0 | F18: =F144 | G18: =G144 -> 02-01-13 Электрочасофикация | O18: =O144 -> 12937.98 | P18: =P144 -> 12662.37 | Q18: =Q144 -> 21.87 | R18: =R144 -> 3.48 | S18: =S144 -> 253.74 | T18: =T144 -> 0 | U18: =U144 -> 19.976236 | V18: =V144 -> 0 | ... GX18: =GX144 -> 0
A20: 3 | B20: 1 | D20: =ROW(A114) -> 114 | F20: 02-01-13 | G20: Электрочасофикация | I20: 0 | J20: 2024-00272-01-0-ИОС5.6 | K20: -1 | L20: 02-01-13 | S20: 0 | T20: 0 | V20: 2 | BX20: 0 | CF20: 0 | CG20: 0
A22: 52 | B22: =B114 -> 1 | C22: =C114 -> 3 | D22: =D114 -> 20 | E22: =E114 -> 0 | F22: =F114 -> 02-01-13 | G22: =G114 -> Электрочасофикация | O22: =O114 -> 12937.98 | P22: =P114 -> 12662.37 | Q22: =Q114 -> 21.87 | R22: =R114 -> 3.48 | S22: =S114 -> 253.74 | T22: =T114 -> 0 | U22: =U114 -> 19.976236 | V22: =V114 -> 0 | ... GX22: =GX114 -> 0
A24: 4 | B24: 1 | D24: =ROW(A37) -> 37 | G24: Оборудование | I24: 0 | K24: -1 | S24: 0 | T24: 0 | V24: 2 | BX24: 0 | CJ24: 0
A26: 52 | B26: =B37 -> 1 | C26: =C37 -> 4 | D26: =D37 -> 24 | E26: =E37 -> 0 | F26: =F37 | G26: =G37 -> Оборудование | O26: =O37 -> 12083.56 | P26: =P37 -> 11981.16 | Q26: =Q37 -> 0 | R26: =R37 -> 0 | S26: =S37 -> 102.4 | T26: =T37 -> 0 | U26: =U37 -> 8.0619 | V26: =V37 -> 0 | ... GX26: =GX37 -> 0
A28: 17 | B28: 1 | C28: =ROW(SmtRes!A1) -> 1 | D28: =ROW(EtalonRes!A1) -> 1 | E28: 1 | F28: 4.10-85-1 | G28: Электрочасы первичные, часы первичные электрические показывающие кварцевые типа ПКЧЗ-2-РИ-Р24-Р6-1 | H28: 1 ШТ. | I28: 1 | J28: 0 | K28: 1 | O28: =ROUND(CP28,2) -> 48.07 | P28: =ROUND((ROUND((AC28*AW28*I28),2)*BC28),2) -> 0.49 | Q28: =(ROUND((ROUND((((ET28*1.1))*AV28*I28),2)*BB28),2)+ROUND((ROUND(((AE28-((EU28*1.1)))*AV28*I28),2)*BS28),2)) -> 0 | R28: =(ROUND((ROUND((((EU28*1.1))*AV28*I28),2)*BS28),2)+ROUND((ROUND(((AE28-((EU28*1.1)))*AV28*I28),2)*BS28),2)) -> 0 | S28: =ROUND((ROUND((AF28*AV28*I28),2)*BA28),2) -> 47.58 | T28: =ROUND(CU28*I28,2) -> 0 | U28: =CV28*I28 -> 3.4551 | V28: =CW28*I28 -> 0 | W28: =ROUND(CX28*I28,2) -> 0 | X28: =(ROUND((((S28+ROUND((ROUND((((EU28*1.1))*AV28*I28),2)*BS28),2))*AT28)/100),2)+ROUND(((ROUND((ROUND(((AE28-((EU28*1.1)))*AV28*I28),2)*BS28),2)*AT28)/100),2)) -> 42.82 | Y28: =(ROUND((((S28+ROUND((ROUND((((EU28*1.1))*AV28*I28),2)*BS28),2))*AU28)/100),2)+ROUND(((ROUND((ROUND(((AE28-((EU28*1.1)))*AV28*I28),2)*BS28),2)*AU28)/100),2)) -> 21.89 | AA28: 60257736 | AB28: =ROUND((AC28+AD28+AF28),6) -> 45.931 | AC28: =ROUND(((ES28*1)),6) -> 0.49 | AD28: =ROUND(((((ET28*1.1))-((EU28*1.1)))+AE28),6) -> 0 | AE28: =ROUND(((EU28*1.1)),6) -> 0 | AF28: =ROUND(((EV28*1.1)),6) -> 45.441 | AG28: =ROUND((AP28),6) -> 0 | AH28: =((EW28*1.1)) -> 3.3 | AI28: =((EX28*1.1)) -> 0 | AJ28: =(AS28) -> 0 | AK28: 41.8 | AL28: 0.49 | AM28: 0 | AN28: 0 | AO28: 41.31 | AP28: 0 | AQ28: 3 | AR28: 0 | AS28: 0 | AT28: 90 | AU28: 46 | AV28: 1.047 | AW28: 1 | AZ28: 1 | BA28: 1 | BB28: 1 | BC28: 1 | BH28: 0 | BI28: 2 | BJ28: ТСН-2001.4 Доп. 80, Сб. 10, т. 85, поз. 1 | BM28: 68 | BN28: 58973116 | BO28: 4.10-85-1 | BP28: 1 | BQ28: 40 | BR28: 0 | BS28: 1 | BT28: 1 | BU28: 1 | BV28: 1 | BW28: 1 | BX28: 1 | BZ28: 90 | CA28: 46 | CE28: 1566 | CF28: 0 | CG28: 0 | CM28: 0 | CN28: Поправка: Гл.12.Прил.8.п.8. 5_12.00.01.11.003 Наименование: При наличии усложненных условий производства работ (стесненность, сложность складирования и транспортной логистики, наличие в зоне производства работ действующего технологического оборудования или движения технологического транспорта и т.п.) для объектов, расположенных за пределами территории круговой магистральной системы улиц "Садовое кольцо" и за пределами Третьего транспортного кольца города Москвы пунктов "а" и "б", но в пределах Московской кольцевой автомобильной дороги | CO28: 0 | CP28: =(P28+Q28+S28) -> 48.07 | CQ28: =ROUND((ROUND((AC28*AW28*1),2)*BC28),2) -> 0.49 | CR28: =(ROUND((ROUND((((ET28*1.1))*AV28*1),2)*BB28),2)+ROUND((ROUND(((AE28-((EU28*1.1)))*AV28*1),2)*BS28),2)) -> 0 | CS28: =(ROUND((ROUND((((EU28*1.1))*AV28*1),2)*BS28),2)+ROUND((ROUND(((AE28-((EU28*1.1)))*AV28*1),2)*BS28),2)) -> 0 | CT28: =ROUND((ROUND((AF28*AV28*1),2)*BA28),2) -> 47.58 | CU28: =AG28 -> 0 | CV28: =(AH28*AV28) -> 3.4551 | CW28: =AI28 -> 0 | CX28: =AJ28 -> 0 | CY28: =(ROUND((((S28+ROUND((ROUND((((EU28*1.1))*AV28*1),2)*BS28),2))*AT28)/100),2)+ROUND(((ROUND((ROUND(((AE28-((EU28*1.1)))*AV28*1),2)*BS28),2)*AT28)/100),2)) -> 42.82 | CZ28: =(ROUND((((S28+ROUND((ROUND((((EU28*1.1))*AV28*1),2)*BS28),2))*AU28)/100),2)+ROUND(((ROUND((ROUND(((AE28-((EU28*1.1)))*AV28*1),2)*BS28),2)*AU28)/100),2)) -> 21.89 | DB28: 1 | DD28: *1 | DE28: *1,1 | DF28: *1,1 | DG28: *1,1 | DI28: *1,1 | DJ28: *1,1 | DN28: 0 | DO28: 0 | DP28: 1 | DQ28: 1 | DU28: 1013 | DV28: 1 ШТ. | DW28: 1 ШТ. | DX28: 1 | EE28: 60088532 | EF28: 40 | EG28: Монтаж оборудования | EH28: 0 | EJ28: 2 | EK28: 68 | EL28: ТСН-2001.4-10. Прокладка и монтаж сетей связи | EM28: ТСН-2001.4-10-1 | EO28: Поправка: Гл.12.Прил.8.п.8. 5_12.00.01.11.003 | EQ28: 0 | ER28: 41.8 | ES28: 0.49 | ET28: 0 | EU28: 0 | EV28: 41.31 | EW28: 3 | EX28: 0 | EY28: 0 | FQ28: 0 | FR28: 0 | FS28: 0 | FX28: 90 | FY28: 46 | GD28: 1 | GF28: -1862400035 | GG28: 2 | GH28: 1 | GI28: 2 | GJ28: 0 | GK28: 0 | GL28: =ROUND(IF(AND(BH28=3,BI28=3,FS28<>0),P28,0),2) -> 0 | GM28: =ROUND(O28+X28+Y28,2)+GX28 -> 112.78 | GN28: =IF(OR(BI28=0,BI28=1),GM28-GX28,0) -> 0 | GO28: =IF(BI28=2,GM28-GX28,0) -> 112.78 | GP28: =IF(BI28=4,GM28-GX28,0) -> 0 | GR28: 0 | GS28: 3 | GT28: 0 | GV28: =ROUND((GT28),6) -> 0 | GW28: 1 | GX28: =ROUND(HC28*I28,2) -> 0 | HA28: 0 | HB28: 0 | HC28: =GV28*GW28 -> 0 | HS28: 0 | IK28: 0
A29: 17 | B29: 1 | C29: =ROW(SmtRes!A2) -> 2 | D29: =ROW(EtalonRes!A2) -> 2 | E29: 1 | F29: 4.10-85-1 | G29: Электрочасы первичные, часы первичные электрические показывающие кварцевые типа ПКЧЗ-2-РИ-Р24-Р6-1 | H29: 1 ШТ. | I29: 1 | J29: 0 | K29: 1 | O29: =ROUND(CP29,2) -> 2621.27 | P29: =ROUND((ROUND((AC29*AW29*I29),2)*BC29),2) -> 4.85 | Q29: =(ROUND((ROUND((((ET29*1.1))*AV29*I29),2)*BB29),2)+ROUND((ROUND(((AE29-((EU29*1.1)))*AV29*I29),2)*BS29),2)) -> 0 | R29: =(ROUND((ROUND((((EU29*1.1))*AV29*I29),2)*BS29),2)+ROUND((ROUND(((AE29-((EU29*1.1)))*AV29*I29),2)*BS29),2)) -> 0 | S29: =ROUND((ROUND((AF29*AV29*I29),2)*BA29),2) -> 2616.42 | T29: =ROUND(CU29*I29,2) -> 0 | U29: =CV29*I29 -> 3.4551 | V29: =CW29*I29 -> 0 | W29: =ROUND(CX29*I29,2) -> 0 | X29: =(ROUND((((S29+ROUND((ROUND((((EU29*1.1))*AV29*I29),2)*BS29),2))*AT29)/100),2)+ROUND(((ROUND((ROUND(((AE29-((EU29*1.1)))*AV29*I29),2)*BS29),2)*AT29)/100),2)) -> 2354.78 | Y29: =(ROUND((((S29+ROUND((ROUND((((EU29*1.1))*AV29*I29),2)*BS29),2))*AU29)/100),2)+ROUND(((ROUND((ROUND(((AE29-((EU29*1.1)))*AV29*I29),2)*BS29),2)*AU29)/100),2)) -> 1203.55 | AA29: 60257733 | AB29: =ROUND((AC29+AD29+AF29),6) -> 45.931 | AC29: =ROUND(((ES29*1)),6) -> 0.49 | AD29: =ROUND(((((ET29*1.1))-((EU29*1.1)))+AE29),6) -> 0 | AE29: =ROUND(((EU29*1.1)),6) -> 0 | AF29: =ROUND(((EV29*1.1)),6) -> 45.441 | AG29: =ROUND((AP29),6) -> 0 | AH29: =((EW29*1.1)) -> 3.3 | AI29: =((EX29*1.1)) -> 0 | AJ29: =(AS29) -> 0 | AK29: 41.8 | AL29: 0.49 | AM29: 0 | AN29: 0 | AO29: 41.31 | AP29: 0 | AQ29: 3 | AR29: 0 | AS29: 0 | AT29: 90 | AU29: 46 | AV29: 1.047 | AW29: 1 | AZ29: 1 | BA29: 54.99 | BB29: 1 | BC29: 9.9 | BH29: 0 | BI29: 2 | BJ29: ТСН-2001.4 Доп. 80, Сб. 10, т. 85, поз. 1 | BM29: 68 | BN29: 58973116 | BO29: 4.10-85-1 | BP29: 1 | BQ29: 40 | BR29: 0 | BS29: 54.99 | BT29: 1 | BU29: 1 | BV29: 1 | BW29: 1 | BX29: 1 | BZ29: 90 | CA29: 46 | CE29: 1566 | CF29: 0 | CG29: 0 | CM29: 0 | CN29: Поправка: Гл.12.Прил.8.п.8. 5_12.00.01.11.003 Наименование: При наличии усложненных условий производства работ (стесненность, сложность складирования и транспортной логистики, наличие в зоне производства работ действующего технологического оборудования или движения технологического транспорта и т.п.) для объектов, расположенных за пределами территории круговой магистральной системы улиц "Садовое кольцо" и за пределами Третьего транспортного кольца города Москвы пунктов "а" и "б", но в пределах Московской кольцевой автомобильной дороги | CO29: 0 | CP29: =(P29+Q29+S29) -> 2621.27 | CQ29: =ROUND((ROUND((AC29*AW29*1),2)*BC29),2) -> 4.85 | CR29: =(ROUND((ROUND((((ET29*1.1))*AV29*1),2)*BB29),2)+ROUND((ROUND(((AE29-((EU29*1.1)))*AV29*1),2)*BS29),2)) -> 0 | CS29: =(ROUND((ROUND((((EU29*1.1))*AV29*1),2)*BS29),2)+ROUND((ROUND(((AE29-((EU29*1.1)))*AV29*1),2)*BS29),2)) -> 0 | CT29: =ROUND((ROUND((AF29*AV29*1),2)*BA29),2) -> 2616.42 | CU29: =AG29 -> 0 | CV29: =(AH29*AV29) -> 3.4551 | CW29: =AI29 -> 0 | CX29: =AJ29 -> 0 | CY29: =(ROUND((((S29+ROUND((ROUND((((EU29*1.1))*AV29*1),2)*BS29),2))*AT29)/100),2)+ROUND(((ROUND((ROUND(((AE29-((EU29*1.1)))*AV29*1),2)*BS29),2)*AT29)/100),2)) -> 2354.78 | CZ29: =(ROUND((((S29+ROUND((ROUND((((EU29*1.1))*AV29*1),2)*BS29),2))*AU29)/100),2)+ROUND(((ROUND((ROUND(((AE29-((EU29*1.1)))*AV29*1),2)*BS29),2)*AU29)/100),2)) -> 1203.55 | DB29: 2 | DD29: *1 | DE29: *1,1 | DF29: *1,1 | DG29: *1,1 | DI29: *1,1 | DJ29: *1,1 | DN29: 0 | DO29: 0 | DP29: 1 | DQ29: 1 | DU29: 1013 | DV29: 1 ШТ. | DW29: 1 ШТ. | DX29: 1 | EE29: 60088532 | EF29: 40 | EG29: Монтаж оборудования | EH29: 0 | EJ29: 2 | EK29: 68 | EL29: ТСН-2001.4-10. Прокладка и монтаж сетей связи | EM29: ТСН-2001.4-10-1 | EO29: Поправка: Гл.12.Прил.8.п.8. 5_12.00.01.11.003 | EQ29: 0 | ER29: 41.8 | ES29: 0.49 | ET29: 0 | EU29: 0 | EV29: 41.31 | EW29: 3 | EX29: 0 | EY29: 0 | FQ29: 0 | FR29: 0 | FS29: 0 | FX29: 90 | FY29: 46 | GD29: 1 | GF29: -1862400035 | GG29: 2 | GH29: 1 | GI29: 2 | GJ29: 0 | GK29: 0 | GL29: =ROUND(IF(AND(BH29=3,BI29=3,FS29<>0),P29,0),2) -> 0 | GM29: =ROUND(O29+X29+Y29,2)+GX29 -> 6179.6 | GN29: =IF(OR(BI29=0,BI29=1),GM29-GX29,0) -> 0 | GO29: =IF(BI29=2,GM29-GX29,0) -> 6179.6 | GP29: =IF(BI29=4,GM29-GX29,0) -> 0 | GR29: 0 | GS29: 3 | GT29: 0 | GV29: =ROUND((GT29),6) -> 0 | GW29: 1 | GX29: =ROUND(HC29*I29,2) -> 0 | HA29: 0 | HB29: 0 | HC29: =GV29*GW29 -> 0 | HS29: 0 | IK29: 0
A30: 17 | B30: 1 | E30: 2 | F30: КА-1 | G30: Часовая станция "Первичные часы" ПИК-2М-4002 | H30: ШТ | I30: 1 | J30: 0 | K30: 1 | O30: =ROUND(CP30,2) -> 10518.85 | P30: =ROUND((ROUND((AC30*I30),2)*BC30),2) -> 10518.85 | Q30: =(ROUND((ROUND(((ET30)*AV30*I30),2)*BB30),2)+ROUND((ROUND(((AE30-(EU30))*AV30*I30),2)*BS30),2)) -> 0 | R30: =(ROUND((ROUND(((EU30)*AV30*I30),2)*BS30),2)+ROUND((ROUND(((AE30-(EU30))*AV30*I30),2)*BS30),2)) -> 0 | S30: =ROUND((ROUND((AF30*AV30*I30),2)*BA30),2) -> 0 | T30: =ROUND(CU30*I30,2) -> 0 | U30: =CV30*I30 -> 0 | V30: =CW30*I30 -> 0 | W30: =ROUND(CX30*I30,2) -> 0 | X30: =(ROUND((((S30+ROUND((ROUND(((EU30)*AV30*I30),2)*BS30),2))*AT30)/100),2)+ROUND(((ROUND((ROUND(((AE30-(EU30))*AV30*I30),2)*BS30),2)*AT30)/100),2)) -> 0 | Y30: =(ROUND((((S30+ROUND((ROUND(((EU30)*AV30*I30),2)*BS30),2))*AU30)/100),2)+ROUND(((ROUND((ROUND(((AE30-(EU30))*AV30*I30),2)*BS30),2)*AU30)/100),2)) -> 0 | AA30: 60257736 | AB30: =ROUND((AC30+AD30+AF30),6) -> 10518.85 | AC30: =ROUND((ES30),6) -> 10518.85 | AD30: =ROUND((((ET30)-(EU30))+AE30),6) -> 0 | AE30: =ROUND((EU30),6) -> 0 | AF30: =ROUND((EV30),6) -> 0 | AG30: =ROUND((AP30),6) -> 0 | AH30: =(EW30) -> 0 | AI30: =(EX30) -> 0 | AJ30: =(AS30) -> 0 | AK30: 10518.85 | AL30: 10518.85 | AM30: 0 | AN30: 0 | AO30: 0 | AP30: 0 | AQ30: 0 | AR30: 0 | AS30: 0 | AT30: 0 | AU30: 0 | AV30: 1 | AW30: 1 | AZ30: 1 | BA30: 1 | BB30: 1 | BC30: 1 | BH30: 3 | BI30: 3 | BM30: 746 | BN30: 0 | BP30: 0 | BQ30: 130 | BR30: 0 | BS30: 1 | BT30: 1 | BU30: 1 | BV30: 1 | BW30: 1 | BX30: 1 | BZ30: 0 | CA30: 0 | CE30: 1566 | CF30: 0 | CG30: 0 | CM30: 0 | CO30: 0 | CP30: =(P30+Q30+S30) -> 10518.85 | CQ30: =ROUND((ROUND((AC30*1),2)*BC30),2) -> 10518.85 | CR30: =(ROUND((ROUND(((ET30)*AV30*1),2)*BB30),2)+ROUND((ROUND(((AE30-(EU30))*AV30*1),2)*BS30),2)) -> 0 | CS30: =(ROUND((ROUND(((EU30)*AV30*1),2)*BS30),2)+ROUND((ROUND(((AE30-(EU30))*AV30*1),2)*BS30),2)) -> 0 | CT30: =ROUND((ROUND((AF30*AV30*1),2)*BA30),2) -> 0 | CU30: =AG30 -> 0 | CV30: =(AH30*AV30) -> 0 | CW30: =AI30 -> 0 | CX30: =AJ30 -> 0 | CY30: =(ROUND((((S30+ROUND((ROUND(((EU30)*AV30*1),2)*BS30),2))*AT30)/100),2)+ROUND(((ROUND((ROUND(((AE30-(EU30))*AV30*1),2)*BS30),2)*AT30)/100),2)) -> 0 | CZ30: =(ROUND((((S30+ROUND((ROUND(((EU30)*AV30*1),2)*BS30),2))*AU30)/100),2)+ROUND(((ROUND((ROUND(((AE30-(EU30))*AV30*1),2)*BS30),2)*AU30)/100),2)) -> 0 | DN30: 0 | DO30: 0 | DP30: 1 | DQ30: 1 | DU30: 1013 | DV30: ШТ | DW30: ШТ | DX30: 1 | EE30: 60088638 | EF30: 130 | EG30: Сметная стоимость оборудования | EH30: 0 | EJ30: 3 | EK30: 746 | EL30: ТСН-2001.13. Сметная стоимость оборудования | EM30: ТСН-2001.13 | EQ30: 0 | ER30: 0 | ES30: 10518.85 | ET30: 0 | EU30: 0 | EV30: 0 | EW30: 0 | EX30: 0 | EY30: 0 | FQ30: 0 | FR30: =P30 -> 10518.85 | FS30: 0 | FX30: 0 | FY30: 0 | GA30: [92 760 / 1,2 / 7,66] + 3% Трансп + 1,2% Заг.скл | GD30: 1 | GF30: -2034863319 | GG30: 2 | GH30: 4 | GI30: -2 | GJ30: 0 | GK30: 0 | GL30: =ROUND(IF(AND(BH30=3,BI30=3,FS30<>0),P30,0),2) -> 0 | GM30: =ROUND(O30+X30+Y30,2)+GX30 -> 10518.85 | GN30: =IF(OR(BI30=0,BI30=1),GM30-GX30,0) -> 0 | GO30: =IF(BI30=2,GM30-GX30,0) -> 0 | GP30: =IF(BI30=4,GM30-GX30,0) -> 0 | GR30: 0 | GS30: 2 | GT30: 0 | GV30: =ROUND((GT30),6) -> 0 | GW30: 1 | GX30: =ROUND(HC30*I30,2) -> 0 | HA30: 0 | HB30: 0 | HC30: =GV30*GW30 -> 0 | HE30: 3 | HF30: 1,2 | HS30: 0 | IK30: 0
A31: 17 | B31: 1 | E31: 2 | F31: КА-1 | G31: Часовая станция "Первичные часы" ПИК-2М-4002 | H31: ШТ | I31: 1 | J31: 0 | K31: 1 | O31: =ROUND(CP31,2) -> 80574.39 | P31: =ROUND((ROUND((AC31*I31),2)*BC31),2) -> 80574.39 | Q31: =(ROUND((ROUND(((ET31)*AV31*I31),2)*BB31),2)+ROUND((ROUND(((AE31-(EU31))*AV31*I31),2)*BS31),2)) -> 0 | R31: =(ROUND((ROUND(((EU31)*AV31*I31),2)*BS31),2)+ROUND((ROUND(((AE31-(EU31))*AV31*I31),2)*BS31),2)) -> 0 | S31: =ROUND((ROUND((AF31*AV31*I31),2)*BA31),2) -> 0 | T31: =ROUND(CU31*I31,2) -> 0 | U31: =CV31*I31 -> 0 | V31: =CW31*I31 -> 0 | W31: =ROUND(CX31*I31,2) -> 0 | X31: =(ROUND((((S31+ROUND((ROUND(((EU31)*AV31*I31),2)*BS31),2))*AT31)/100),2)+ROUND(((ROUND((ROUND(((AE31-(EU31))*AV31*I31),2)*BS31),2)*AT31)/100),2)) -> 0 | Y31: =(ROUND((((S31+ROUND((ROUND(((EU31)*AV31*I31),2)*BS31),2))*AU31)/100),2)+ROUND(((ROUND((ROUND(((AE31-(EU31))*AV31*I31),2)*BS31),2)*AU31)/100),2)) -> 0 | AA31: 60257733 | AB31: =ROUND((AC31+AD31+AF31),6) -> 10518.85 | AC31: =ROUND((ES31),6) -> 10518.85 | AD31: =ROUND((((ET31)-(EU31))+AE31),6) -> 0 | AE31: =ROUND((EU31),6) -> 0 | AF31: =ROUND((EV31),6) -> 0 | AG31: =ROUND((AP31),6) -> 0 | AH31: =(EW31) -> 0 | AI31: =(EX31) -> 0 | AJ31: =(AS31) -> 0 | AK31: 10518.85 | AL31: 10518.85 | AM31: 0 | AN31: 0 | AO31: 0 | AP31: 0 | AQ31: 0 | AR31: 0 | AS31: 0 | AT31: 0 | AU31: 0 | AV31: 1 | AW31: 1 | AZ31: 1 | BA31: 1 | BB31: 1 | BC31: 7.66 | BH31: 3 | BI31: 3 | BM31: 746 | BN31: 0 | BP31: 0 | BQ31: 130 | BR31: 0 | BS31: 1 | BT31: 1 | BU31: 1 | BV31: 1 | BW31: 1 | BX31: 1 | BZ31: 0 | CA31: 0 | CE31: 1566 | CF31: 0 | CG31: 0 | CM31: 0 | CO31: 0 | CP31: =(P31+Q31+S31) -> 80574.39 | CQ31: =ROUND((ROUND((AC31*1),2)*BC31),2) -> 80574.39 | CR31: =(ROUND((ROUND(((ET31)*AV31*1),2)*BB31),2)+ROUND((ROUND(((AE31-(EU31))*AV31*1),2)*BS31),2)) -> 0 | CS31: =(ROUND((ROUND(((EU31)*AV31*1),2)*BS31),2)+ROUND((ROUND(((AE31-(EU31))*AV31*1),2)*BS31),2)) -> 0 | CT31: =ROUND((ROUND((AF31*AV31*1),2)*BA31),2) -> 0 | CU31: =AG31 -> 0 | CV31: =(AH31*AV31) -> 0 | CW31: =AI31 -> 0 | CX31: =AJ31 -> 0 | CY31: =(ROUND((((S31+ROUND((ROUND(((EU31)*AV31*1),2)*BS31),2))*AT31)/100),2)+ROUND(((ROUND((ROUND(((AE31-(EU31))*AV31*1),2)*BS31),2)*AT31)/100),2)) -> 0 | CZ31: =(ROUND((((S31+ROUND((ROUND(((EU31)*AV31*1),2)*BS31),2))*AU31)/100),2)+ROUND(((ROUND((ROUND(((AE31-(EU31))*AV31*1),2)*BS31),2)*AU31)/100),2)) -> 0 | DN31: 0 | DO31: 0 | DP31: 1 | DQ31: 1 | DU31: 1013 | DV31: ШТ | DW31: ШТ | DX31: 1 | EE31: 60088638 | EF31: 130 | EG31: Сметная стоимость оборудования | EH31: 0 | EJ31: 3 | EK31: 746 | EL31: ТСН-2001.13. Сметная стоимость оборудования | EM31: ТСН-2001.13 | EQ31: 0 | ER31: 0 | ES31: 10518.85 | ET31: 0 | EU31: 0 | EV31: 0 | EW31: 0 | EX31: 0 | EY31: 0 | EZ31: 5 | FC31: 1 | FD31: 18 | FF31: 92760 | FQ31: 0 | FR31: =P31 -> 80574.39 | FS31: 0 | FX31: 0 | FY31: 0 | GA31: [92 760 / 1,2 / 7,66] + 3% Трансп + 1,2% Заг.скл | GD31: 1 | GF31: -2034863319 | GG31: 2 | GH31: 3 | GI31: 5 | GJ31: 0 | GK31: 0 | GL31: =ROUND(IF(AND(BH31=3,BI31=3,FS31<>0),P31,0),2) -> 0 | GM31: =ROUND(O31+X31+Y31,2)+GX31 -> 80574.39 | GN31: =IF(OR(BI31=0,BI31=1),GM31-GX31,0) -> 0 | GO31: =IF(BI31=2,GM31-GX31,0) -> 0 | GP31: =IF(BI31=4,GM31-GX31,0) -> 0 | GR31: 1 | GS31: 1 | GT31: 0 | GV31: =ROUND((GT31),6) -> 0 | GW31: 1 | GX31: =ROUND(HC31*I31,2) -> 0 | HA31: 0 | HB31: 0 | HC31: =GV31*GW31 -> 0 | HE31: 3 | HF31: 1,2 | HS31: 0 | IK31: 0
A32: 17 | B32: 1 | C32: =ROW(SmtRes!A3) -> 3 | D32: =ROW(EtalonRes!A3) -> 3 | E32: 3 | F32: 4.10-86-1 | G32: Электрочасы вторичные для помещений, электрочасы односторонние на стене | H32: 1 ШТ. | I32: 2 | J32: 0 | K32: 2 | O32: =ROUND(CP32,2) -> 55.38 | P32: =ROUND((ROUND((AC32*AW32*I32),2)*BC32),2) -> 0.56 | Q32: =(ROUND((ROUND((((ET32*1.1))*AV32*I32),2)*BB32),2)+ROUND((ROUND(((AE32-((EU32*1.1)))*AV32*I32),2)*BS32),2)) -> 0 | R32: =(ROUND((ROUND((((EU32*1.1))*AV32*I32),2)*BS32),2)+ROUND((ROUND(((AE32-((EU32*1.1)))*AV32*I32),2)*BS32),2)) -> 0 | S32: =ROUND((ROUND((AF32*AV32*I32),2)*BA32),2) -> 54.82 | T32: =ROUND(CU32*I32,2) -> 0 | U32: =CV32*I32 -> 4.6068 | V32: =CW32*I32 -> 0 | W32: =ROUND(CX32*I32,2) -> 0 | X32: =(ROUND((((S32+ROUND((ROUND((((EU32*1.1))*AV32*I32),2)*BS32),2))*AT32)/100),2)+ROUND(((ROUND((ROUND(((AE32-((EU32*1.1)))*AV32*I32),2)*BS32),2)*AT32)/100),2)) -> 49.34 | Y32: =(ROUND((((S32+ROUND((ROUND((((EU32*1.1))*AV32*I32),2)*BS32),2))*AU32)/100),2)+ROUND(((ROUND((ROUND(((AE32-((EU32*1.1)))*AV32*I32),2)*BS32),2)*AU32)/100),2)) -> 25.22 | AA32: 60257736 | AB32: =ROUND((AC32+AD32+AF32),6) -> 26.46 | AC32: =ROUND(((ES32*1)),6) -> 0.28 | AD32: =ROUND(((((ET32*1.1))-((EU32*1.1)))+AE32),6) -> 0 | AE32: =ROUND(((EU32*1.1)),6) -> 0 | AF32: =ROUND(((EV32*1.1)),6) -> 26.18 | AG32: =ROUND((AP32),6) -> 0 | AH32: =((EW32*1.1)) -> 2.2 | AI32: =((EX32*1.1)) -> 0 | AJ32: =(AS32) -> 0 | AK32: 24.08 | AL32: 0.28 | AM32: 0 | AN32: 0 | AO32: 23.8 | AP32: 0 | AQ32: 2 | AR32: 0 | AS32: 0 | AT32: 90 | AU32: 46 | AV32: 1.047 | AW32: 1 | AZ32: 1 | BA32: 1 | BB32: 1 | BC32: 1 | BH32: 0 | BI32: 2 | BJ32: ТСН-2001.4. Доп. 1-42. Сб. 10, т. 86, поз. 1 | BM32: 68 | BN32: 58973116 | BO32: 4.10-86-1 | BP32: 1 | BQ32: 40 | BR32: 0 | BS32: 1 | BT32: 1 | BU32: 1 | BV32: 1 | BW32: 1 | BX32: 1 | BZ32: 90 | CA32: 46 | CE32: 1566 | CF32: 0 | CG32: 0 | CM32: 0 | CN32: Поправка: Гл.12.Прил.8.п.8. 5_12.00.01.11.003 Наименование: При наличии усложненных условий производства работ (стесненность, сложность складирования и транспортной логистики, наличие в зоне производства работ действующего технологического оборудования или движения технологического транспорта и т.п.) для объектов, расположенных за пределами территории круговой магистральной системы улиц "Садовое кольцо" и за пределами Третьего транспортного кольца города Москвы пунктов "а" и "б", но в пределах Московской кольцевой автомобильной дороги | CO32: 0 | CP32: =(P32+Q32+S32) -> 55.38 | CQ32: =ROUND((ROUND((AC32*AW32*1),2)*BC32),2) -> 0.28 | CR32: =(ROUND((ROUND((((ET32*1.1))*AV32*1),2)*BB32),2)+ROUND((ROUND(((AE32-((EU32*1.1)))*AV32*1),2)*BS32),2)) -> 0 | CS32: =(ROUND((ROUND((((EU32*1.1))*AV32*1),2)*BS32),2)+ROUND((ROUND(((AE32-((EU32*1.1)))*AV32*1),2)*BS32),2)) -> 0 | CT32: =ROUND((ROUND((AF32*AV32*1),2)*BA32),2) -> 27.41 | CU32: =AG32 -> 0 | CV32: =(AH32*AV32) -> 2.3034 | CW32: =AI32 -> 0 | CX32: =AJ32 -> 0 | CY32: =(ROUND((((S32+ROUND((ROUND((((EU32*1.1))*AV32*1),2)*BS32),2))*AT32)/100),2)+ROUND(((ROUND((ROUND(((AE32-((EU32*1.1)))*AV32*1),2)*BS32),2)*AT32)/100),2)) -> 49.34 | CZ32: =(ROUND((((S32+ROUND((ROUND((((EU32*1.1))*AV32*1),2)*BS32),2))*AU32)/100),2)+ROUND(((ROUND((ROUND(((AE32-((EU32*1.1)))*AV32*1),2)*BS32),2)*AU32)/100),2)) -> 25.22 | DB32: 3 | DD32: *1 | DE32: *1,1 | DF32: *1,1 | DG32: *1,1 | DI32: *1,1 | DJ32: *1,1 | DN32: 0 | DO32: 0 | DP32: 1 | DQ32: 1 | DU32: 1013 | DV32: 1 ШТ. | DW32: 1 ШТ. | DX32: 1 | EE32: 60088532 | EF32: 40 | EG32: Монтаж оборудования | EH32: 0 | EJ32: 2 | EK32: 68 | EL32: ТСН-2001.4-10. Прокладка и монтаж сетей связи | EM32: ТСН-2001.4-10-1 | EO32: Поправка: Гл.12.Прил.8.п.8. 5_12.00.01.11.003 | EQ32: 0 | ER32: 24.08 | ES32: 0.28 | ET32: 0 | EU32: 0 | EV32: 23.8 | EW32: 2 | EX32: 0 | EY32: 0 | FQ32: 0 | FR32: 0 | FS32: 0 | FX32: 90 | FY32: 46 | GD32: 1 | GF32: 1897857927 | GG32: 2 | GH32: 1 | GI32: 2 | GJ32: 0 | GK32: 0 | GL32: =ROUND(IF(AND(BH32=3,BI32=3,FS32<>0),P32,0),2) -> 0 | GM32: =ROUND(O32+X32+Y32,2)+GX32 -> 129.94 | GN32: =IF(OR(BI32=0,BI32=1),GM32-GX32,0) -> 0 | GO32: =IF(BI32=2,GM32-GX32,0) -> 129.94 | GP32: =IF(BI32=4,GM32-GX32,0) -> 0 | GR32: 0 | GS32: 3 | GT32: 0 | GV32: =ROUND((GT32),6) -> 0 | GW32: 1 | GX32: =ROUND(HC32*I32,2) -> 0 | HA32: 0 | HB32: 0 | HC32: =GV32*GW32 -> 0 | HS32: 0 | IK32: 0
A33: 17 | B33: 1 | C33: =ROW(SmtRes!A4) -> 4 | D33: =ROW(EtalonRes!A4) -> 4 | E33: 3 | F33: 4.10-86-1 | G33: Электрочасы вторичные для помещений, электрочасы односторонние на стене | H33: 1 ШТ. | I33: 2 | J33: 0 | K33: 2 | O33: =ROUND(CP33,2) -> 3020.09 | P33: =ROUND((ROUND((AC33*AW33*I33),2)*BC33),2) -> 5.54 | Q33: =(ROUND((ROUND((((ET33*1.1))*AV33*I33),2)*BB33),2)+ROUND((ROUND(((AE33-((EU33*1.1)))*AV33*I33),2)*BS33),2)) -> 0 | R33: =(ROUND((ROUND((((EU33*1.1))*AV33*I33),2)*BS33),2)+ROUND((ROUND(((AE33-((EU33*1.1)))*AV33*I33),2)*BS33),2)) -> 0 | S33: =ROUND((ROUND((AF33*AV33*I33),2)*BA33),2) -> 3014.55 | T33: =ROUND(CU33*I33,2) -> 0 | U33: =CV33*I33 -> 4.6068 | V33: =CW33*I33 -> 0 | W33: =ROUND(CX33*I33,2) -> 0 | X33: =(ROUND((((S33+ROUND((ROUND((((EU33*1.1))*AV33*I33),2)*BS33),2))*AT33)/100),2)+ROUND(((ROUND((ROUND(((AE33-((EU33*1.1)))*AV33*I33),2)*BS33),2)*AT33)/100),2)) -> 2713.1 | Y33: =(ROUND((((S33+ROUND((ROUND((((EU33*1.1))*AV33*I33),2)*BS33),2))*AU33)/100),2)+ROUND(((ROUND((ROUND(((AE33-((EU33*1.1)))*AV33*I33),2)*BS33),2)*AU33)/100),2)) -> 1386.69 | AA33: 60257733 | AB33: =ROUND((AC33+AD33+AF33),6) -> 26.46 | AC33: =ROUND(((ES33*1)),6) -> 0.28 | AD33: =ROUND(((((ET33*1.1))-((EU33*1.1)))+AE33),6) -> 0 | AE33: =ROUND(((EU33*1.1)),6) -> 0 | AF33: =ROUND(((EV33*1.1)),6) -> 26.18 | AG33: =ROUND((AP33),6) -> 0 | AH33: =((EW33*1.1)) -> 2.2 | AI33: =((EX33*1.1)) -> 0 | AJ33: =(AS33) -> 0 | AK33: 24.08 | AL33: 0.28 | AM33: 0 | AN33: 0 | AO33: 23.8 | AP33: 0 | AQ33: 2 | AR33: 0 | AS33: 0 | AT33: 90 | AU33: 46 | AV33: 1.047 | AW33: 1 | AZ33: 1 | BA33: 54.99 | BB33: 1 | BC33: 9.89 | BH33: 0 | BI33: 2 | BJ33: ТСН-2001.4. Доп. 1-42. Сб. 10, т. 86, поз. 1 | BM33: 68 | BN33: 58973116 | BO33: 4.10-86-1 | BP33: 1 | BQ33: 40 | BR33: 0 | BS33: 54.99 | BT33: 1 | BU33: 1 | BV33: 1 | BW33: 1 | BX33: 1 | BZ33: 90 | CA33: 46 | CE33: 1566 | CF33: 0 | CG33: 0 | CM33: 0 | CN33: Поправка: Гл.12.Прил.8.п.8. 5_12.00.01.11.003 Наименование: При наличии усложненных условий производства работ (стесненность, сложность складирования и транспортной логистики, наличие в зоне производства работ действующего технологического оборудования или движения технологического транспорта и т.п.) для объектов, расположенных за пределами территории круговой магистральной системы улиц "Садовое кольцо" и за пределами Третьего транспортного кольца города Москвы пунктов "а" и "б", но в пределах Московской кольцевой автомобильной дороги | CO33: 0 | CP33: =(P33+Q33+S33) -> 3020.09 | CQ33: =ROUND((ROUND((AC33*AW33*1),2)*BC33),2) -> 2.77 | CR33: =(ROUND((ROUND((((ET33*1.1))*AV33*1),2)*BB33),2)+ROUND((ROUND(((AE33-((EU33*1.1)))*AV33*1),2)*BS33),2)) -> 0 | CS33: =(ROUND((ROUND((((EU33*1.1))*AV33*1),2)*BS33),2)+ROUND((ROUND(((AE33-((EU33*1.1)))*AV33*1),2)*BS33),2)) -> 0 | CT33: =ROUND((ROUND((AF33*AV33*1),2)*BA33),2) -> 1507.28 | CU33: =AG33 -> 0 | CV33: =(AH33*AV33) -> 2.3034 | CW33: =AI33 -> 0 | CX33: =AJ33 -> 0 | CY33: =(ROUND((((S33+ROUND((ROUND((((EU33*1.1))*AV33*1),2)*BS33),2))*AT33)/100),2)+ROUND(((ROUND((ROUND(((AE33-((EU33*1.1)))*AV33*1),2)*BS33),2)*AT33)/100),2)) -> 2713.1 | CZ33: =(ROUND((((S33+ROUND((ROUND((((EU33*1.1))*AV33*1),2)*BS33),2))*AU33)/100),2)+ROUND(((ROUND((ROUND(((AE33-((EU33*1.1)))*AV33*1),2)*BS33),2)*AU33)/100),2)) -> 1386.69 | DB33: 4 | DD33: *1 | DE33: *1,1 | DF33: *1,1 | DG33: *1,1 | DI33: *1,1 | DJ33: *1,1 | DN33: 0 | DO33: 0 | DP33: 1 | DQ33: 1 | DU33: 1013 | DV33: 1 ШТ. | DW33: 1 ШТ. | DX33: 1 | EE33: 60088532 | EF33: 40 | EG33: Монтаж оборудования | EH33: 0 | EJ33: 2 | EK33: 68 | EL33: ТСН-2001.4-10. Прокладка и монтаж сетей связи | EM33: ТСН-2001.4-10-1 | EO33: Поправка: Гл.12.Прил.8.п.8. 5_12.00.01.11.003 | EQ33: 0 | ER33: 24.08 | ES33: 0.28 | ET33: 0 | EU33: 0 | EV33: 23.8 | EW33: 2 | EX33: 0 | EY33: 0 | FQ33: 0 | FR33: 0 | FS33: 0 | FX33: 90 | FY33: 46 | GD33: 1 | GF33: 1897857927 | GG33: 2 | GH33: 1 | GI33: 2 | GJ33: 0 | GK33: 0 | GL33: =ROUND(IF(AND(BH33=3,BI33=3,FS33<>0),P33,0),2) -> 0 | GM33: =ROUND(O33+X33+Y33,2)+GX33 -> 7119.88 | GN33: =IF(OR(BI33=0,BI33=1),GM33-GX33,0) -> 0 | GO33: =IF(BI33=2,GM33-GX33,0) -> 7119.88 | GP33: =IF(BI33=4,GM33-GX33,0) -> 0 | GR33: 0 | GS33: 3 | GT33: 0 | GV33: =ROUND((GT33),6) -> 0 | GW33: 1 | GX33: =ROUND(HC33*I33,2) -> 0 | HA33: 0 | HB33: 0 | HC33: =GV33*GW33 -> 0 | HS33: 0 | IK33: 0
A34: 17 | B34: 1 | E34: 4 | F34: 13.1-2-211 | G34: Часы электрические вторичные стрелочные, типа ВЧ03/03 | H34: шт. | I34: 2 | J34: 0 | K34: 2 | O34: =ROUND(CP34,2) -> 1461.26 | P34: =ROUND((ROUND((AC34*I34),2)*BC34),2) -> 1461.26 | Q34: =(ROUND((ROUND(((ET34)*AV34*I34),2)*BB34),2)+ROUND((ROUND(((AE34-(EU34))*AV34*I34),2)*BS34),2)) -> 0 | R34: =(ROUND((ROUND(((EU34)*AV34*I34),2)*BS34),2)+ROUND((ROUND(((AE34-(EU34))*AV34*I34),2)*BS34),2)) -> 0 | S34: =ROUND((ROUND((AF34*AV34*I34),2)*BA34),2) -> 0 | T34: =ROUND(CU34*I34,2) -> 0 | U34: =CV34*I34 -> 0 | V34: =CW34*I34 -> 0 | W34: =ROUND(CX34*I34,2) -> 0 | X34: =(ROUND((((S34+ROUND((ROUND(((EU34)*AV34*I34),2)*BS34),2))*AT34)/100),2)+ROUND(((ROUND((ROUND(((AE34-(EU34))*AV34*I34),2)*BS34),2)*AT34)/100),2)) -> 0 | Y34: =(ROUND((((S34+ROUND((ROUND(((EU34)*AV34*I34),2)*BS34),2))*AU34)/100),2)+ROUND(((ROUND((ROUND(((AE34-(EU34))*AV34*I34),2)*BS34),2)*AU34)/100),2)) -> 0 | AA34: 60257736 | AB34: =ROUND((AC34+AD34+AF34),6) -> 730.63 | AC34: =ROUND((ES34),6) -> 730.63 | AD34: =ROUND((((ET34)-(EU34))+AE34),6) -> 0 | AE34: =ROUND((EU34),6) -> 0 | AF34: =ROUND((EV34),6) -> 0 | AG34: =ROUND((AP34),6) -> 0 | AH34: =(EW34) -> 0 | AI34: =(EX34) -> 0 | AJ34: =(AS34) -> 0 | AK34: 730.63 | AL34: 730.63 | AM34: 0 | AN34: 0 | AO34: 0 | AP34: 0 | AQ34: 0 | AR34: 0 | AS34: 0 | AT34: 0 | AU34: 0 | AV34: 1 | AW34: 1 | AZ34: 1 | BA34: 1 | BB34: 1 | BC34: 1 | BH34: 3 | BI34: 3 | BM34: 746 | BN34: 58973116 | BP34: 0 | BQ34: 130 | BR34: 0 | BS34: 1 | BT34: 1 | BU34: 1 | BV34: 1 | BW34: 1 | BX34: 1 | BZ34: 0 | CA34: 0 | CE34: 1566 | CF34: 0 | CG34: 0 | CM34: 0 | CO34: 0 | CP34: =(P34+Q34+S34) -> 1461.26 | CQ34: =ROUND((ROUND((AC34*1),2)*BC34),2) -> 730.63 | CR34: =(ROUND((ROUND(((ET34)*AV34*1),2)*BB34),2)+ROUND((ROUND(((AE34-(EU34))*AV34*1),2)*BS34),2)) -> 0 | CS34: =(ROUND((ROUND(((EU34)*AV34*1),2)*BS34),2)+ROUND((ROUND(((AE34-(EU34))*AV34*1),2)*BS34),2)) -> 0 | CT34: =ROUND((ROUND((AF34*AV34*1),2)*BA34),2) -> 0 | CU34: =AG34 -> 0 | CV34: =(AH34*AV34) -> 0 | CW34: =AI34 -> 0 | CX34: =AJ34 -> 0 | CY34: =(ROUND((((S34+ROUND((ROUND(((EU34)*AV34*1),2)*BS34),2))*AT34)/100),2)+ROUND(((ROUND((ROUND(((AE34-(EU34))*AV34*1),2)*BS34),2)*AT34)/100),2)) -> 0 | CZ34: =(ROUND((((S34+ROUND((ROUND(((EU34)*AV34*1),2)*BS34),2))*AU34)/100),2)+ROUND(((ROUND((ROUND(((AE34-(EU34))*AV34*1),2)*BS34),2)*AU34)/100),2)) -> 0 | DN34: 0 | DO34: 0 | DP34: 1 | DQ34: 1 | DU34: 1010 | DV34: шт. | DW34: шт. | DX34: 1 | EE34: 60088638 | EF34: 130 | EG34: Сметная стоимость оборудования | EH34: 0 | EJ34: 3 | EK34: 746 | EL34: ТСН-2001.13. Сметная стоимость оборудования | EM34: ТСН-2001.13 | EQ34: 0 | ER34: 730.63 | ES34: 730.63 | ET34: 0 | EU34: 0 | EV34: 0 | EW34: 0 | EX34: 0 | EY34: 0 | FQ34: 0 | FR34: =P34 -> 1461.26 | FS34: 0 | FX34: 0 | FY34: 0 | GD34: 1 | GF34: -1868144852 | GG34: 2 | GH34: 1 | GI34: -2 | GJ34: 0 | GK34: 0 | GL34: =ROUND(IF(AND(BH34=3,BI34=3,FS34<>0),P34,0),2) -> 0 | GM34: =ROUND(O34+X34+Y34,2)+GX34 -> 1461.26 | GN34: =IF(OR(BI34=0,BI34=1),GM34-GX34,0) -> 0 | GO34: =IF(BI34=2,GM34-GX34,0) -> 0 | GP34: =IF(BI34=4,GM34-GX34,0) -> 0 | GR34: 0 | GS34: 3 | GT34: 0 | GV34: =ROUND((GT34),6) -> 0 | GW34: 1 | GX34: =ROUND(HC34*I34,2) -> 0 | HA34: 0 | HB34: 0 | HC34: =GV34*GW34 -> 0 | HS34: 0 | IK34: 0
A35: 17 | B35: 1 | E35: 4 | F35: 13.1-2-211 | G35: Часы электрические вторичные стрелочные, типа ВЧ03/03 | H35: шт. | I35: 2 | J35: 0 | K35: 2 | O35: =ROUND(CP35,2) -> 7598.55 | P35: =ROUND((ROUND((AC35*I35),2)*BC35),2) -> 7598.55 | Q35: =(ROUND((ROUND(((ET35)*AV35*I35),2)*BB35),2)+ROUND((ROUND(((AE35-(EU35))*AV35*I35),2)*BS35),2)) -> 0 | R35: =(ROUND((ROUND(((EU35)*AV35*I35),2)*BS35),2)+ROUND((ROUND(((AE35-(EU35))*AV35*I35),2)*BS35),2)) -> 0 | S35: =ROUND((ROUND((AF35*AV35*I35),2)*BA35),2) -> 0 | T35: =ROUND(CU35*I35,2) -> 0 | U35: =CV35*I35 -> 0 | V35: =CW35*I35 -> 0 | W35: =ROUND(CX35*I35,2) -> 0 | X35: =(ROUND((((S35+ROUND((ROUND(((EU35)*AV35*I35),2)*BS35),2))*AT35)/100),2)+ROUND(((ROUND((ROUND(((AE35-(EU35))*AV35*I35),2)*BS35),2)*AT35)/100),2)) -> 0 | Y35: =(ROUND((((S35+ROUND((ROUND(((EU35)*AV35*I35),2)*BS35),2))*AU35)/100),2)+ROUND(((ROUND((ROUND(((AE35-(EU35))*AV35*I35),2)*BS35),2)*AU35)/100),2)) -> 0 | AA35: 60257733 | AB35: =ROUND((AC35+AD35+AF35),6) -> 730.63 | AC35: =ROUND((ES35),6) -> 730.63 | AD35: =ROUND((((ET35)-(EU35))+AE35),6) -> 0 | AE35: =ROUND((EU35),6) -> 0 | AF35: =ROUND((EV35),6) -> 0 | AG35: =ROUND((AP35),6) -> 0 | AH35: =(EW35) -> 0 | AI35: =(EX35) -> 0 | AJ35: =(AS35) -> 0 | AK35: 730.63 | AL35: 730.63 | AM35: 0 | AN35: 0 | AO35: 0 | AP35: 0 | AQ35: 0 | AR35: 0 | AS35: 0 | AT35: 0 | AU35: 0 | AV35: 1 | AW35: 1 | AZ35: 1 | BA35: 1 | BB35: 1 | BC35: 5.2 | BH35: 3 | BI35: 3 | BM35: 746 | BN35: 58973116 | BP35: 0 | BQ35: 130 | BR35: 0 | BS35: 1 | BT35: 1 | BU35: 1 | BV35: 1 | BW35: 1 | BX35: 1 | BZ35: 0 | CA35: 0 | CE35: 1566 | CF35: 0 | CG35: 0 | CM35: 0 | CO35: 0 | CP35: =(P35+Q35+S35) -> 7598.55 | CQ35: =ROUND((ROUND((AC35*1),2)*BC35),2) -> 3799.28 | CR35: =(ROUND((ROUND(((ET35)*AV35*1),2)*BB35),2)+ROUND((ROUND(((AE35-(EU35))*AV35*1),2)*BS35),2)) -> 0 | CS35: =(ROUND((ROUND(((EU35)*AV35*1),2)*BS35),2)+ROUND((ROUND(((AE35-(EU35))*AV35*1),2)*BS35),2)) -> 0 | CT35: =ROUND((ROUND((AF35*AV35*1),2)*BA35),2) -> 0 | CU35: =AG35 -> 0 | CV35: =(AH35*AV35) -> 0 | CW35: =AI35 -> 0 | CX35: =AJ35 -> 0 | CY35: =(ROUND((((S35+ROUND((ROUND(((EU35)*AV35*1),2)*BS35),2))*AT35)/100),2)+ROUND(((ROUND((ROUND(((AE35-(EU35))*AV35*1),2)*BS35),2)*AT35)/100),2)) -> 0 | CZ35: =(ROUND((((S35+ROUND((ROUND(((EU35)*AV35*1),2)*BS35),2))*AU35)/100),2)+ROUND(((ROUND((ROUND(((AE35-(EU35))*AV35*1),2)*BS35),2)*AU35)/100),2)) -> 0 | DN35: 0 | DO35: 0 | DP35: 1 | DQ35: 1 | DU35: 1010 | DV35: шт. | DW35: шт. | DX35: 1 | EE35: 60088638 | EF35: 130 | EG35: Сметная стоимость оборудования | EH35: 0 | EJ35: 3 | EK35: 746 | EL35: ТСН-2001.13. Сметная стоимость оборудования | EM35: ТСН-2001.13 | EQ35: 0 | ER35: 730.63 | ES35: 730.63 | ET35: 0 | EU35: 0 | EV35: 0 | EW35: 0 | EX35: 0 | EY35: 0 | FQ35: 0 | FR35: =P35 -> 7598.55 | FS35: 0 | FX35: 0 | FY35: 0 | GD35: 1 | GF35: -1868144852 | GG35: 2 | GH35: 1 | GI35: 2 | GJ35: 0 | GK35: 0 | GL35: =ROUND(IF(AND(BH35=3,BI35=3,FS35<>0),P35,0),2) -> 0 | GM35: =ROUND(O35+X35+Y35,2)+GX35 -> 7598.55 | GN35: =IF(OR(BI35=0,BI35=1),GM35-GX35,0) -> 0 | GO35: =IF(BI35=2,GM35-GX35,0) -> 0 | GP35: =IF(BI35=4,GM35-GX35,0) -> 0 | GR35: 0 | GS35: 3 | GT35: 0 | GV35: =ROUND((GT35),6) -> 0 | GW35: 1 | GX35: =ROUND(HC35*I35,2) -> 0 | HA35: 0 | HB35: 0 | HC35: =GV35*GW35 -> 0 | HS35: 0 | IK35: 0
A37: 51 | B37: =B24 -> 1 | C37: =A24 -> 4 | D37: =ROW(A24) -> 24 | F37: =IF(F24<>"",F24,"") | G37: =IF(G24<>"",G24,"") -> Оборудование | H37: 0 | O37: =ROUND(AB37,2) -> 12083.56 | P37: =ROUND(AC37,2) -> 11981.16 | Q37: =ROUND(AD37,2) -> 0 | R37: =ROUND(AE37,2) -> 0 | S37: =ROUND(AF37,2) -> 102.4 | T37: =ROUND(AG37,2) -> 0 | U37: =AH37 -> 8.0619 | V37: =AI37 -> 0 | W37: =ROUND(AJ37,2) -> 0 | X37: =ROUND(AK37,2) -> 92.16 | Y37: =ROUND(AL37,2) -> 47.11 | AB37: =ROUND(SUMIF(AA28:AA35,"=60257736",O28:O35),2) -> 12083.56 | AC37: =ROUND(SUMIF(AA28:AA35,"=60257736",P28:P35),2) -> 11981.16 | AD37: =ROUND(SUMIF(AA28:AA35,"=60257736",Q28:Q35),2) -> 0 | AE37: =ROUND(SUMIF(AA28:AA35,"=60257736",R28:R35),2) -> 0 | AF37: =ROUND(SUMIF(AA28:AA35,"=60257736",S28:S35),2) -> 102.4 | AG37: =ROUND(SUMIF(AA28:AA35,"=60257736",T28:T35),2) -> 0 | AH37: =SUMIF(AA28:AA35,"=60257736",U28:U35) -> 8.0619 | AI37: =SUMIF(AA28:AA35,"=60257736",V28:V35) -> 0 | AJ37: =ROUND(SUMIF(AA28:AA35,"=60257736",W28:W35),2) -> 0 | AK37: =ROUND(SUMIF(AA28:AA35,"=60257736",X28:X35),2) -> 92.16 | AL37: =ROUND(SUMIF(AA28:AA35,"=60257736",Y28:Y35),2) -> 47.11 | AO37: =ROUND(BX37,2) -> 0 | AP37: =ROUND(BY37,2) -> 11980.11 | AQ37: =ROUND(BZ37,2) -> 0 | AR37: =ROUND(CA37,2) -> 12222.83 | AS37: =ROUND(CB37,2) -> 0 | AT37: =ROUND(CC37,2) -> 242.72 | AU37: =ROUND(CD37,2) -> 0 | AV37: =ROUND(CE37,2) -> 11981.16 | ... BD37: =ROUND(CM37,2) -> 0 | BX37: =ROUND(SUMIF(AA28:AA35,"=60257736",FQ28:FQ35),2) -> 0 | BY37: =ROUND(SUMIF(AA28:AA35,"=60257736",FR28:FR35),2) -> 11980.11 | BZ37: =ROUND(SUMIF(AA28:AA35,"=60257736",GL28:GL35),2) -> 0 | CA37: =ROUND(SUMIF(AA28:AA35,"=60257736",GM28:GM35),2) -> 12222.83 | CB37: =ROUND(SUMIF(AA28:AA35,"=60257736",GN28:GN35),2) -> 0 | CC37: =ROUND(SUMIF(AA28:AA35,"=60257736",GO28:GO35),2) -> 242.72 | CD37: =ROUND(SUMIF(AA28:AA35,"=60257736",GP28:GP35),2) -> 0 | CE37: =AC37-BX37 -> 11981.16 | CF37: =AC37-BY37 -> 1.05 | CG37: =BX37-BZ37 -> 0 | CH37: =AC37-BX37-BY37+BZ37 -> 1.05 | CI37: =BY37-BZ37 -> 11980.11 | CJ37: =ROUND(SUMIF(AA28:AA35,"=60257736",GX28:GX35),2) -> 0 | CK37: =ROUND(SUMIF(AA28:AA35,"=60257736",GY28:GY35),2) -> 0 | CL37: =ROUND(SUMIF(AA28:AA35,"=60257736",GZ28:GZ35),2) -> 0 | CM37: =ROUND(SUMIF(AA28:AA35,"=60257736",HD28:HD35),2) -> 0 | DG37: =ROUND(DT37,2) -> 93814.3 | DH37: =ROUND(DU37,2) -> 88183.33 | DI37: =ROUND(DV37,2) -> 0 | DJ37: =ROUND(DW37,2) -> 0 | DK37: =ROUND(DX37,2) -> 5630.97 | DL37: =ROUND(DY37,2) -> 0 | DM37: =DZ37 -> 8.0619 | DN37: =EA37 -> 0 | DO37: =ROUND(EB37,2) -> 0 | DP37: =ROUND(EC37,2) -> 5067.88 | DQ37: =ROUND(ED37,2) -> 2590.24 | DT37: =ROUND(SUMIF(AA28:AA35,"=60257733",O28:O35),2) -> 93814.3 | DU37: =ROUND(SUMIF(AA28:AA35,"=60257733",P28:P35),2) -> 88183.33 | DV37: =ROUND(SUMIF(AA28:AA35,"=60257733",Q28:Q35),2) -> 0 | DW37: =ROUND(SUMIF(AA28:AA35,"=60257733",R28:R35),2) -> 0 | DX37: =ROUND(SUMIF(AA28:AA35,"=60257733",S28:S35),2) -> 5630.97 | DY37: =ROUND(SUMIF(AA28:AA35,"=60257733",T28:T35),2) -> 0 | DZ37: =SUMIF(AA28:AA35,"=60257733",U28:U35) -> 8.0619 | EA37: =SUMIF(AA28:AA35,"=60257733",V28:V35) -> 0 | EB37: =ROUND(SUMIF(AA28:AA35,"=60257733",W28:W35),2) -> 0 | EC37: =ROUND(SUMIF(AA28:AA35,"=60257733",X28:X35),2) -> 5067.88 | ED37: =ROUND(SUMIF(AA28:AA35,"=60257733",Y28:Y35),2) -> 2590.24 | EG37: =ROUND(FP37,2) -> 0 | EH37: =ROUND(FQ37,2) -> 88172.94 | EI37: =ROUND(FR37,2) -> 0 | EJ37: =ROUND(FS37,2) -> 101472.42 | EK37: =ROUND(FT37,2) -> 0 | EL37: =ROUND(FU37,2) -> 13299.48 | EM37: =ROUND(FV37,2) -> 0 | EN37: =ROUND(FW37,2) -> 88183.33 | ... EV37: =ROUND(GE37,2) -> 0 | FP37: =ROUND(SUMIF(AA28:AA35,"=60257733",FQ28:FQ35),2) -> 0 | FQ37: =ROUND(SUMIF(AA28:AA35,"=60257733",FR28:FR35),2) -> 88172.94 | FR37: =ROUND(SUMIF(AA28:AA35,"=60257733",GL28:GL35),2) -> 0 | FS37: =ROUND(SUMIF(AA28:AA35,"=60257733",GM28:GM35),2) -> 101472.42 | FT37: =ROUND(SUMIF(AA28:AA35,"=60257733",GN28:GN35),2) -> 0 | FU37: =ROUND(SUMIF(AA28:AA35,"=60257733",GO28:GO35),2) -> 13299.48 | FV37: =ROUND(SUMIF(AA28:AA35,"=60257733",GP28:GP35),2) -> 0 | FW37: =DU37-FP37 -> 88183.33 | FX37: =DU37-FQ37 -> 10.39 | FY37: =FP37-FR37 -> 0 | FZ37: =DU37-FP37-FQ37+FR37 -> 10.39 | GA37: =FQ37-FR37 -> 88172.94 | GB37: =ROUND(SUMIF(AA28:AA35,"=60257733",GX28:GX35),2) -> 0 | GC37: =ROUND(SUMIF(AA28:AA35,"=60257733",GY28:GY35),2) -> 0 | GD37: =ROUND(SUMIF(AA28:AA35,"=60257733",GZ28:GZ35),2) -> 0 | GE37: =ROUND(SUMIF(AA28:AA35,"=60257733",HD28:HD35),2) -> 0 | GX37: 0
A39: 50 | B39: 0 | C39: 0 | D39: 1 | E39: 201 | F39: =ROUND(Source!O37,O39) -> 12083.56 | G39: ПЗ | H39: Прямые затраты | K39: 201 | L39: 1 | M39: 3 | O39: 2 | P39: =ROUND(Source!DG37,O39) -> 93814.3 | W39: 12083.56 | X39: 1 | Y39: 12083.56 | Z39: 93814.3 | AA39: 1 | AB39: 93814.3
A40: 50 | B40: 0 | C40: 0 | D40: 1 | E40: 202 | F40: =ROUND(Source!P37,O40) -> 11981.16 | G40: СтМатОб | H40: Стоимость материальных ресурсов (всего) | K40: 202 | L40: 2 | M40: 3 | O40: 2 | P40: =ROUND(Source!DH37,O40) -> 88183.33 | W40: 11981.16 | X40: 1 | Y40: 11981.16 | Z40: 88183.33 | AA40: 1 | AB40: 88183.33
A41: 50 | B41: 0 | C41: 0 | D41: 1 | E41: 222 | F41: =ROUND(Source!AO37,O41) -> 0 | G41: СтМатОбЗак | H41: Стоимость материалов и оборудования заказчика | K41: 222 | L41: 3 | M41: 3 | O41: 2 | P41: =ROUND(Source!EG37,O41) -> 0 | W41: 0 | X41: 1 | Y41: 0 | Z41: 0 | AA41: 1 | AB41: 0
A42: 50 | B42: 0 | C42: 0 | D42: 1 | E42: 225 | F42: =ROUND(Source!AV37,O42) -> 11981.16 | G42: СтМатОбПод | H42: Стоимость материалов и оборудования подрядчика | K42: 225 | L42: 4 | M42: 3 | O42: 2 | P42: =ROUND(Source!EN37,O42) -> 88183.33 | W42: 11981.16 | X42: 1 | Y42: 11981.16 | Z42: 88183.33 | AA42: 1 | AB42: 88183.33
A43: 50 | B43: 0 | C43: 0 | D43: 1 | E43: 226 | F43: =ROUND(Source!AW37,O43) -> 1.05 | G43: СтМат | H43: Стоимость материалов (всего) | K43: 226 | L43: 5 | M43: 3 | O43: 2 | P43: =ROUND(Source!EO37,O43) -> 10.39 | W43: 1.05 | X43: 1 | Y43: 1.05 | Z43: 10.39 | AA43: 1 | AB43: 10.39
A44: 50 | B44: 0 | C44: 0 | D44: 1 | E44: 227 | F44: =ROUND(Source!AX37,O44) -> 0 | G44: СтМатЗак | H44: Стоимость материалов заказчика | K44: 227 | L44: 6 | M44: 3 | O44: 2 | P44: =ROUND(Source!EP37,O44) -> 0 | W44: 0 | X44: 1 | Y44: 0 | Z44: 0 | AA44: 1 | AB44: 0
A45: 50 | B45: 0 | C45: 0 | D45: 1 | E45: 228 | F45: =ROUND(Source!AY37,O45) -> 1.05 | G45: СтМатПод | H45: Стоимость материалов подрядчика | K45: 228 | L45: 7 | M45: 3 | O45: 2 | P45: =ROUND(Source!EQ37,O45) -> 10.39 | W45: 1.05 | X45: 1 | Y45: 1.05 | Z45: 10.39 | AA45: 1 | AB45: 10.39
A46: 50 | B46: 0 | C46: 0 | D46: 1 | E46: 216 | F46: =ROUND(Source!AP37,O46) -> 11980.11 | G46: Оборуд | H46: Стоимость оборудования (всего) | K46: 216 | L46: 8 | M46: 3 | O46: 2 | P46: =ROUND(Source!EH37,O46) -> 88172.94 | W46: 11980.11 | X46: 1 | Y46: 11980.11 | Z46: 88172.94 | AA46: 1 | AB46: 88172.94
A47: 50 | B47: 0 | C47: 0 | D47: 1 | E47: 223 | F47: =ROUND(Source!AQ37,O47) -> 0 | G47: ОборудЗак | H47: Стоимость оборудования заказчика | K47: 223 | L47: 9 | M47: 3 | O47: 2 | P47: =ROUND(Source!EI37,O47) -> 0 | W47: 0 | X47: 1 | Y47: 0 | Z47: 0 | AA47: 1 | AB47: 0
A48: 50 | B48: 0 | C48: 0 | D48: 1 | E48: 229 | F48: =ROUND(Source!AZ37,O48) -> 11980.11 | G48: ОборудПод | H48: Стоимость оборудования подрядчика | K48: 229 | L48: 10 | M48: 3 | O48: 2 | P48: =ROUND(Source!ER37,O48) -> 88172.94 | W48: 11980.11 | X48: 1 | Y48: 11980.11 | Z48: 88172.94 | AA48: 1 | AB48: 88172.94
A49: 50 | B49: 0 | C49: 0 | D49: 1 | E49: 203 | F49: =ROUND(Source!Q37,O49) -> 0 | G49: ЭММ | H49: Эксплуатация машин | K49: 203 | L49: 11 | M49: 3 | O49: 2 | P49: =ROUND(Source!DI37,O49) -> 0 | W49: 0 | X49: 1 | Y49: 0 | Z49: 0 | AA49: 1 | AB49: 0
A50: 50 | B50: 0 | C50: 0 | D50: 1 | E50: 231 | F50: =ROUND(Source!BB37,O50) -> 0 | G50: ЭММсНРиСП | H50: Эксплуатация машин по ТСН-2001.16 | K50: 231 | L50: 12 | M50: 3 | O50: 2 | P50: =ROUND(Source!ET37,O50) -> 0 | W50: 0 | X50: 1 | Y50: 0 | Z50: 0 | AA50: 1 | AB50: 0
A51: 50 | B51: 0 | C51: 0 | D51: 1 | E51: 204 | F51: =ROUND(Source!R37,O51) -> 0 | G51: ЗПМ | H51: ЗП машинистов | K51: 204 | L51: 13 | M51: 3 | O51: 2 | P51: =ROUND(Source!DJ37,O51) -> 0 | W51: 0 | X51: 1 | Y51: 0 | Z51: 0 | AA51: 1 | AB51: 0
A52: 50 | B52: 0 | C52: 0 | D52: 1 | E52: 205 | F52: =ROUND(Source!S37,O52) -> 102.4 | G52: ОЗП | H52: Основная ЗП рабочих | K52: 205 | L52: 14 | M52: 3 | O52: 2 | P52: =ROUND(Source!DK37,O52) -> 5630.97 | W52: 102.4 | X52: 1 | Y52: 102.4 | Z52: 5630.97 | AA52: 1 | AB52: 5630.97
A53: 50 | B53: 0 | C53: 0 | D53: 1 | E53: 232 | F53: =ROUND(Source!BC37,O53) -> 0 | G53: ОЗПсНРиСП | H53: Основная ЗП рабочих по ТСН-2001.16 | K53: 232 | L53: 15 | M53: 3 | O53: 2 | P53: =ROUND(Source!EU37,O53) -> 0 | W53: 0 | X53: 1 | Y53: 0 | Z53: 0 | AA53: 1 | AB53: 0
A54: 50 | B54: 0 | C54: 0 | D54: 1 | E54: 214 | F54: =ROUND(Source!AS37,O54) -> 0 | G54: Строит | H54: Строительные работы с НР и СП | K54: 214 | L54: 16 | M54: 3 | O54: 2 | P54: =ROUND(Source!EK37,O54) -> 0 | W54: 0 | X54: 1 | Y54: 0 | Z54: 0 | AA54: 1 | AB54: 0
A55: 50 | B55: 0 | C55: 0 | D55: 1 | E55: 215 | F55: =ROUND(Source!AT37,O55) -> 242.72 | G55: Монтаж | H55: Монтажные работы с НР и СП | K55: 215 | L55: 17 | M55: 3 | O55: 2 | P55: =ROUND(Source!EL37,O55) -> 13299.48 | W55: 242.72 | X55: 1 | Y55: 242.72 | Z55: 13299.48 | AA55: 1 | AB55: 13299.48
A56: 50 | B56: 0 | C56: 0 | D56: 1 | E56: 217 | F56: =ROUND(Source!AU37,O56) -> 0 | G56: Прочие | H56: Прочие работы с НР и СП | K56: 217 | L56: 18 | M56: 3 | O56: 2 | P56: =ROUND(Source!EM37,O56) -> 0 | W56: 0 | X56: 1 | Y56: 0 | Z56: 0 | AA56: 1 | AB56: 0
A57: 50 | B57: 0 | C57: 0 | D57: 1 | E57: 230 | F57: =ROUND(Source!BA37,O57) -> 0 | G57: ПрочиеЗатр | H57: Прочие затраты по ТСН-2001.16 | K57: 230 | L57: 19 | M57: 3 | O57: 2 | P57: =ROUND(Source!ES37,O57) -> 0 | W57: 0 | X57: 1 | Y57: 0 | Z57: 0 | AA57: 1 | AB57: 0
A58: 50 | B58: 0 | C58: 0 | D58: 1 | E58: 206 | F58: =ROUND(Source!T37,O58) -> 0 | G58: ВозврМат | H58: Возврат материалов | K58: 206 | L58: 20 | M58: 3 | O58: 2 | P58: =ROUND(Source!DL37,O58) -> 0 | W58: 0 | X58: 1 | Y58: 0 | Z58: 0 | AA58: 1 | AB58: 0
A59: 50 | B59: 0 | C59: 0 | D59: 1 | E59: 207 | F59: =Source!U37 -> 8.0619 | G59: ТрудСтр | H59: Трудозатраты строителей | K59: 207 | L59: 21 | M59: 3 | O59: -1 | P59: =Source!DM37 -> 8.0619 | W59: 8.0619 | X59: 1 | Y59: 8.0619 | Z59: 8.0619 | AA59: 1 | AB59: 8.0619
A60: 50 | B60: 0 | C60: 0 | D60: 1 | E60: 208 | F60: =Source!V37 -> 0 | G60: ТрудМаш | H60: Трудозатраты машинистов | K60: 208 | L60: 22 | M60: 3 | O60: -1 | P60: =Source!DN37 -> 0 | W60: 0 | X60: 1 | Y60: 0 | Z60: 0 | AA60: 1 | AB60: 0
A61: 50 | B61: 0 | C61: 0 | D61: 1 | E61: 209 | F61: =ROUND(Source!W37,O61) -> 0 | G61: ТранспМат | H61: Транспорт материалов | K61: 209 | L61: 23 | M61: 3 | O61: 2 | P61: =ROUND(Source!DO37,O61) -> 0 | W61: 0 | X61: 1 | Y61: 0 | Z61: 0 | AA61: 1 | AB61: 0
A62: 50 | B62: 0 | C62: 0 | D62: 1 | E62: 233 | F62: =ROUND(Source!BD37,O62) -> 0 | G62: Перевозка | H62: Перевозка грузов | K62: 233 | L62: 24 | M62: 3 | O62: 2 | P62: =ROUND(Source!EV37,O62) -> 0 | W62: 0 | X62: 1 | Y62: 0 | Z62: 0 | AA62: 1 | AB62: 0
A63: 50 | B63: 0 | C63: 0 | D63: 1 | E63: 210 | F63: =ROUND(Source!X37,O63) -> 92.16 | G63: НР | H63: Накладные расходы | K63: 210 | L63: 25 | M63: 3 | O63: 2 | P63: =ROUND(Source!DP37,O63) -> 5067.88 | W63: 92.16 | X63: 1 | Y63: 92.16 | Z63: 5067.88 | AA63: 1 | AB63: 5067.88
A64: 50 | B64: 0 | C64: 0 | D64: 1 | E64: 211 | F64: =ROUND(Source!Y37,O64) -> 47.11 | G64: СмПриб | H64: Сметная прибыль | K64: 211 | L64: 26 | M64: 3 | O64: 2 | P64: =ROUND(Source!DQ37,O64) -> 2590.24 | W64: 47.11 | X64: 1 | Y64: 47.11 | Z64: 2590.24 | AA64: 1 | AB64: 2590.24
A65: 50 | B65: 0 | C65: 0 | D65: 1 | E65: 224 | F65: =ROUND(Source!AR37,O65) -> 12222.83 | G65: Всего | H65: Всего с НР и СП | K65: 224 | L65: 27 | M65: 3 | O65: 2 | P65: =ROUND(Source!EJ37,O65) -> 101472.42 | W65: 12222.83 | X65: 1 | Y65: 12222.83 | Z65: 101472.42 | AA65: 1 | AB65: 101472.42
A67: 4 | B67: 1 | D67: =ROW(A84) -> 84 | G67: Кабельные изделия | I67: 0 | K67: -1 | S67: 0 | T67: 0 | V67: 2 | BX67: 0 | CJ67: 0
A69: 52 | B69: =B84 -> 1 | C69: =C84 -> 4 | D69: =D84 -> 67 | E69: =E84 -> 0 | F69: =F84 | G69: =G84 -> Кабельные изделия | O69: =O84 -> 854.42 | P69: =P84 -> 681.21 | Q69: =Q84 -> 21.87 | R69: =R84 -> 3.48 | S69: =S84 -> 151.34 | T69: =T84 -> 0 | U69: =U84 -> 11.914337 | V69: =V84 -> 0 | ... GX69: =GX84 -> 0
A71: 17 | B71: 1 | C71: =ROW(SmtRes!A7) -> 7 | D71: =ROW(EtalonRes!A8) -> 8 | E71: 5 | F71: 4.8-288-1 | G71: Трубы гофрированные поливинилхлоридные наружным диаметром 16 мм открыто по стенам и потолкам с установкой соединительных коробок | H71: 100 м | I71: =ROUND(50/100,9) -> 0.5 | J71: 0 | K71: =ROUND(50/100,9) -> 0.5 | O71: =ROUND(CP71,2) -> 296.95 | P71: =ROUND((ROUND((AC71*AW71*I71),2)*BC71),2) -> 171.52 | Q71: =(ROUND((ROUND((((ET71*1.1))*AV71*I71),2)*BB71),2)+ROUND((ROUND(((AE71-((EU71*1.1)))*AV71*I71),2)*BS71),2)) -> 18.85 | R71: =(ROUND((ROUND((((EU71*1.1))*AV71*I71),2)*BS71),2)+ROUND((ROUND(((AE71-((EU71*1.1)))*AV71*I71),2)*BS71),2)) -> 3.14 | S71: =ROUND((ROUND((AF71*AV71*I71),2)*BA71),2) -> 106.58 | T71: =ROUND(CU71*I71,2) -> 0 | U71: =CV71*I71 -> 8.2749645 | V71: =CW71*I71 -> 0 | W71: =ROUND(CX71*I71,2) -> 0 | X71: =(ROUND((((S71+ROUND((ROUND((((EU71*1.1))*AV71*I71),2)*BS71),2))*AT71)/100),2)+ROUND(((ROUND((ROUND(((AE71-((EU71*1.1)))*AV71*I71),2)*BS71),2)*AT71)/100),2)) -> 106.43 | Y71: =(ROUND((((S71+ROUND((ROUND((((EU71*1.1))*AV71*I71),2)*BS71),2))*AU71)/100),2)+ROUND(((ROUND((ROUND(((AE71-((EU71*1.1)))*AV71*I71),2)*BS71),2)*AU71)/100),2)) -> 55.96 | AA71: 60257736 | AB71: =ROUND((AC71+AD71+AF71),6) -> 582.643 | AC71: =ROUND(((ES71*1)),6) -> 343.03 | AD71: =ROUND(((((ET71*1.1))-((EU71*1.1)))+AE71),6) -> 36.014 | AE71: =ROUND(((EU71*1.1)),6) -> 6.006 | AF71: =ROUND(((EV71*1.1)),6) -> 203.599 | AG71: =ROUND((AP71),6) -> 0 | AH71: =((EW71*1.1)) -> 15.807 | AI71: =((EX71*1.1)) -> 0 | AJ71: =(AS71) -> 0 | AK71: 560.86 | AL71: 343.03 | AM71: 32.74 | AN71: 5.46 | AO71: 185.09 | AP71: 0 | AQ71: 14.37 | AR71: 0 | AS71: 0 | AT71: 97 | AU71: 51 | AV71: 1.047 | AW71: 1 | AZ71: 1 | BA71: 1 | BB71: 1 | BC71: 1 | BH71: 0 | BI71: 2 | BJ71: ТСН-2001.4 Доп. 54, Сб. 8, т. 288, поз. 1 | BM71: 67 | BN71: 58973116 | BO71: 4.8-288-1 | BP71: 1 | BQ71: 40 | BR71: 0 | BS71: 1 | BT71: 1 | BU71: 1 | BV71: 1 | BW71: 1 | BX71: 1 | BZ71: 97 | CA71: 51 | CE71: 1566 | CF71: 0 | CG71: 0 | CM71: 0 | CN71: Поправка: Гл.12.Прил.8.п.8. 5_12.00.01.11.003 Наименование: При наличии усложненных условий производства работ (стесненность, сложность складирования и транспортной логистики, наличие в зоне производства работ действующего технологического оборудования или движения технологического транспорта и т.п.) для объектов, расположенных за пределами территории круговой магистральной системы улиц "Садовое кольцо" и за пределами Третьего транспортного кольца города Москвы пунктов "а" и "б", но в пределах Московской кольцевой автомобильной дороги | CO71: 0 | CP71: =(P71+Q71+S71) -> 296.95 | CQ71: =ROUND((ROUND((AC71*AW71*1),2)*BC71),2) -> 343.03 | CR71: =(ROUND((ROUND((((ET71*1.1))*AV71*1),2)*BB71),2)+ROUND((ROUND(((AE71-((EU71*1.1)))*AV71*1),2)*BS71),2)) -> 37.71 | CS71: =(ROUND((ROUND((((EU71*1.1))*AV71*1),2)*BS71),2)+ROUND((ROUND(((AE71-((EU71*1.1)))*AV71*1),2)*BS71),2)) -> 6.29 | CT71: =ROUND((ROUND((AF71*AV71*1),2)*BA71),2) -> 213.17 | CU71: =AG71 -> 0 | CV71: =(AH71*AV71) -> 16.549929 | CW71: =AI71 -> 0 | CX71: =AJ71 -> 0 | CY71: =(ROUND((((S71+ROUND((ROUND((((EU71*1.1))*AV71*1),2)*BS71),2))*AT71)/100),2)+ROUND(((ROUND((ROUND(((AE71-((EU71*1.1)))*AV71*1),2)*BS71),2)*AT71)/100),2)) -> 109.48 | CZ71: =(ROUND((((S71+ROUND((ROUND((((EU71*1.1))*AV71*1),2)*BS71),2))*AU71)/100),2)+ROUND(((ROUND((ROUND(((AE71-((EU71*1.1)))*AV71*1),2)*BS71),2)*AU71)/100),2)) -> 57.56 | DB71: 5 | DD71: *1 | DE71: *1,1 | DF71: *1,1 | DG71: *1,1 | DI71: *1,1 | DJ71: *1,1 | DN71: 0 | DO71: 0 | DP71: 1 | DQ71: 1 | DU71: 1003 | DV71: 100 м | DW71: 100 м | DX71: 100 | EE71: 60088531 | EF71: 40 | EG71: Монтаж оборудования | EH71: 0 | EJ71: 2 | EK71: 67 | EL71: ТСН-2001.4-8. Электротехнические установки | EM71: ТСН-2001.4-8-1 | EO71: Поправка: Гл.12.Прил.8.п.8. 5_12.00.01.11.003 | EQ71: 0 | ER71: 560.86 | ES71: 343.03 | ET71: 32.74 | EU71: 5.46 | EV71: 185.09 | EW71: 14.37 | EX71: 0 | EY71: 0 | FQ71: 0 | FR71: 0 | FS71: 0 | FX71: 97 | FY71: 51 | GD71: 1 | GF71: 1777434348 | GG71: 2 | GH71: 1 | GI71: 2 | GJ71: 0 | GK71: 0 | GL71: =ROUND(IF(AND(BH71=3,BI71=3,FS71<>0),P71,0),2) -> 0 | GM71: =ROUND(O71+X71+Y71,2)+GX71 -> 459.34 | GN71: =IF(OR(BI71=0,BI71=1),GM71-GX71,0) -> 0 | GO71: =IF(BI71=2,GM71-GX71,0) -> 459.34 | GP71: =IF(BI71=4,GM71-GX71,0) -> 0 | GR71: 0 | GS71: 3 | GT71: 0 | GV71: =ROUND((GT71),6) -> 0 | GW71: 1 | GX71: =ROUND(HC71*I71,2) -> 0 | HA71: 0 | HB71: 0 | HC71: =GV71*GW71 -> 0 | HS71: 0 | IK71: 0
A72: 17 | B72: 1 | C72: =ROW(SmtRes!A10) -> 10 | D72: =ROW(EtalonRes!A12) -> 12 | E72: 5 | F72: 4.8-288-1 | G72: Трубы гофрированные поливинилхлоридные наружным диаметром 16 мм открыто по стенам и потолкам с установкой соединительных коробок | H72: 100 м | I72: =ROUND(50/100,9) -> 0.5 | J72: 0 | K72: =ROUND(50/100,9) -> 0.5 | O72: =ROUND(CP72,2) -> 7887.79 | P72: =ROUND((ROUND((AC72*AW72*I72),2)*BC72),2) -> 1696.33 | Q72: =(ROUND((ROUND((((ET72*1.1))*AV72*I72),2)*BB72),2)+ROUND((ROUND(((AE72-((EU72*1.1)))*AV72*I72),2)*BS72),2)) -> 330.63 | R72: =(ROUND((ROUND((((EU72*1.1))*AV72*I72),2)*BS72),2)+ROUND((ROUND(((AE72-((EU72*1.1)))*AV72*I72),2)*BS72),2)) -> 172.67 | S72: =ROUND((ROUND((AF72*AV72*I72),2)*BA72),2) -> 5860.83 | T72: =ROUND(CU72*I72,2) -> 0 | U72: =CV72*I72 -> 8.2749645 | V72: =CW72*I72 -> 0 | W72: =ROUND(CX72*I72,2) -> 0 | X72: =(ROUND((((S72+ROUND((ROUND((((EU72*1.1))*AV72*I72),2)*BS72),2))*AT72)/100),2)+ROUND(((ROUND((ROUND(((AE72-((EU72*1.1)))*AV72*I72),2)*BS72),2)*AT72)/100),2)) -> 5852.5 | Y72: =(ROUND((((S72+ROUND((ROUND((((EU72*1.1))*AV72*I72),2)*BS72),2))*AU72)/100),2)+ROUND(((ROUND((ROUND(((AE72-((EU72*1.1)))*AV72*I72),2)*BS72),2)*AU72)/100),2)) -> 3077.09 | AA72: 60257733 | AB72: =ROUND((AC72+AD72+AF72),6) -> 582.643 | AC72: =ROUND(((ES72*1)),6) -> 343.03 | AD72: =ROUND(((((ET72*1.1))-((EU72*1.1)))+AE72),6) -> 36.014 | AE72: =ROUND(((EU72*1.1)),6) -> 6.006 | AF72: =ROUND(((EV72*1.1)),6) -> 203.599 | AG72: =ROUND((AP72),6) -> 0 | AH72: =((EW72*1.1)) -> 15.807 | AI72: =((EX72*1.1)) -> 0 | AJ72: =(AS72) -> 0 | AK72: 560.86 | AL72: 343.03 | AM72: 32.74 | AN72: 5.46 | AO72: 185.09 | AP72: 0 | AQ72: 14.37 | AR72: 0 | AS72: 0 | AT72: 97 | AU72: 51 | AV72: 1.047 | AW72: 1 | AZ72: 1 | BA72: 54.99 | BB72: 17.54 | BC72: 9.89 | BH72: 0 | BI72: 2 | BJ72: ТСН-2001.4 Доп. 54, Сб. 8, т. 288, поз. 1 | BM72: 67 | BN72: 58973116 | BO72: 4.8-288-1 | BP72: 1 | BQ72: 40 | BR72: 0 | BS72: 54.99 | BT72: 1 | BU72: 1 | BV72: 1 | BW72: 1 | BX72: 1 | BZ72: 97 | CA72: 51 | CE72: 1566 | CF72: 0 | CG72: 0 | CM72: 0 | CN72: Поправка: Гл.12.Прил.8.п.8. 5_12.00.01.11.003 Наименование: При наличии усложненных условий производства работ (стесненность, сложность складирования и транспортной логистики, наличие в зоне производства работ действующего технологического оборудования или движения технологического транспорта и т.п.) для объектов, расположенных за пределами территории круговой магистральной системы улиц "Садовое кольцо" и за пределами Третьего транспортного кольца города Москвы пунктов "а" и "б", но в пределах Московской кольцевой автомобильной дороги | CO72: 0 | CP72: =(P72+Q72+S72) -> 7887.79 | CQ72: =ROUND((ROUND((AC72*AW72*1),2)*BC72),2) -> 3392.57 | CR72: =(ROUND((ROUND((((ET72*1.1))*AV72*1),2)*BB72),2)+ROUND((ROUND(((AE72-((EU72*1.1)))*AV72*1),2)*BS72),2)) -> 661.43 | CS72: =(ROUND((ROUND((((EU72*1.1))*AV72*1),2)*BS72),2)+ROUND((ROUND(((AE72-((EU72*1.1)))*AV72*1),2)*BS72),2)) -> 345.89 | CT72: =ROUND((ROUND((AF72*AV72*1),2)*BA72),2) -> 11722.22 | CU72: =AG72 -> 0 | CV72: =(AH72*AV72) -> 16.549929 | CW72: =AI72 -> 0 | CX72: =AJ72 -> 0 | CY72: =(ROUND((((S72+ROUND((ROUND((((EU72*1.1))*AV72*1),2)*BS72),2))*AT72)/100),2)+ROUND(((ROUND((ROUND(((AE72-((EU72*1.1)))*AV72*1),2)*BS72),2)*AT72)/100),2)) -> 6020.52 | CZ72: =(ROUND((((S72+ROUND((ROUND((((EU72*1.1))*AV72*1),2)*BS72),2))*AU72)/100),2)+ROUND(((ROUND((ROUND(((AE72-((EU72*1.1)))*AV72*1),2)*BS72),2)*AU72)/100),2)) -> 3165.43 | DB72: 6 | DD72: *1 | DE72: *1,1 | DF72: *1,1 | DG72: *1,1 | DI72: *1,1 | DJ72: *1,1 | DN72: 0 | DO72: 0 | DP72: 1 | DQ72: 1 | DU72: 1003 | DV72: 100 м | DW72: 100 м | DX72: 100 | EE72: 60088531 | EF72: 40 | EG72: Монтаж оборудования | EH72: 0 | EJ72: 2 | EK72: 67 | EL72: ТСН-2001.4-8. Электротехнические установки | EM72: ТСН-2001.4-8-1 | EO72: Поправка: Гл.12.Прил.8.п.8. 5_12.00.01.11.003 | EQ72: 0 | ER72: 560.86 | ES72: 343.03 | ET72: 32.74 | EU72: 5.46 | EV72: 185.09 | EW72: 14.37 | EX72: 0 | EY72: 0 | FQ72: 0 | FR72: 0 | FS72: 0 | FX72: 97 | FY72: 51 | GD72: 1 | GF72: 1777434348 | GG72: 2 | GH72: 1 | GI72: 2 | GJ72: 0 | GK72: 0 | GL72: =ROUND(IF(AND(BH72=3,BI72=3,FS72<>0),P72,0),2) -> 0 | GM72: =ROUND(O72+X72+Y72,2)+GX72 -> 16817.38 | GN72: =IF(OR(BI72=0,BI72=1),GM72-GX72,0) -> 0 | GO72: =IF(BI72=2,GM72-GX72,0) -> 16817.38 | GP72: =IF(BI72=4,GM72-GX72,0) -> 0 | GR72: 0 | GS72: 3 | GT72: 0 | GV72: =ROUND((GT72),6) -> 0 | GW72: 1 | GX72: =ROUND(HC72*I72,2) -> 0 | HA72: 0 | HB72: 0 | HC72: =GV72*GW72 -> 0 | HS72: 0 | IK72: 0
A73: 18 | B73: 1 | C73: 7 | E73: 5,1 | F73: 1.12-5-371 | G73: Трубы электротехнические, гофрированные, из ПВХ, негорючие, с зондом, наружный диаметр 16 мм | H73: м | I73: =I71*J73 -> 51 | J73: 102 | K73: 102 | O73: =ROUND(CP73,2) -> 136.17 | P73: =ROUND((ROUND((AC73*AW73*I73),2)*BC73),2) -> 136.17 | Q73: =(ROUND((ROUND(((ET73)*AV73*I73),2)*BB73),2)+ROUND((ROUND(((AE73-(EU73))*AV73*I73),2)*BS73),2)) -> 0 | R73: =(ROUND((ROUND(((EU73)*AV73*I73),2)*BS73),2)+ROUND((ROUND(((AE73-(EU73))*AV73*I73),2)*BS73),2)) -> 0 | S73: =ROUND((ROUND((AF73*AV73*I73),2)*BA73),2) -> 0 | T73: =ROUND(CU73*I73,2) -> 0 | U73: =CV73*I73 -> 0 | V73: =CW73*I73 -> 0 | W73: =ROUND(CX73*I73,2) -> 0 | X73: =(ROUND((((S73+ROUND((ROUND(((EU73)*AV73*I73),2)*BS73),2))*AT73)/100),2)+ROUND(((ROUND((ROUND(((AE73-(EU73))*AV73*I73),2)*BS73),2)*AT73)/100),2)) -> 0 | Y73: =(ROUND((((S73+ROUND((ROUND(((EU73)*AV73*I73),2)*BS73),2))*AU73)/100),2)+ROUND(((ROUND((ROUND(((AE73-(EU73))*AV73*I73),2)*BS73),2)*AU73)/100),2)) -> 0 | AA73: 60257736 | AB73: =ROUND((AC73+AD73+AF73),6) -> 2.67 | AC73: =ROUND((ES73),6) -> 2.67 | AD73: =ROUND((((ET73)-(EU73))+AE73),6) -> 0 | AE73: =ROUND((EU73),6) -> 0 | AF73: =ROUND((EV73),6) -> 0 | AG73: =ROUND((AP73),6) -> 0 | AH73: =(EW73) -> 0 | AI73: =(EX73) -> 0 | AJ73: =(AS73) -> 0 | AK73: 2.67 | AL73: 2.67 | AM73: 0 | AN73: 0 | AO73: 0 | AP73: 0 | AQ73: 0 | AR73: 0 | AS73: 0 | AT73: 97 | AU73: 51 | AV73: 1 | AW73: 1 | AZ73: 1 | BA73: 1 | BB73: 1 | BC73: 1 | BH73: 3 | BI73: 2 | BJ73: ТСН-2001.1 Доп. 67, Р. 12, о. 5, поз. 371 | BM73: 67 | BN73: 58973116 | BP73: 0 | BQ73: 40 | BR73: 0 | BS73: 1 | BT73: 1 | BU73: 1 | BV73: 1 | BW73: 1 | BX73: 1 | BZ73: 97 | CA73: 51 | CE73: 1566 | CF73: 0 | CG73: 0 | CM73: 0 | CN73: Поправка: Гл.12.Прил.8.п.8. 5_12.00.01.11.003 Наименование: При наличии усложненных условий производства работ (стесненность, сложность складирования и транспортной логистики, наличие в зоне производства работ действующего технологического оборудования или движения технологического транспорта и т.п.) для объектов, расположенных за пределами территории круговой магистральной системы улиц "Садовое кольцо" и за пределами Третьего транспортного кольца города Москвы пунктов "а" и "б", но в пределах Московской кольцевой автомобильной дороги | CO73: 0 | CP73: =(P73+Q73+S73) -> 136.17 | CQ73: =ROUND((ROUND((AC73*AW73*1),2)*BC73),2) -> 2.67 | CR73: =(ROUND((ROUND(((ET73)*AV73*1),2)*BB73),2)+ROUND((ROUND(((AE73-(EU73))*AV73*1),2)*BS73),2)) -> 0 | CS73: =(ROUND((ROUND(((EU73)*AV73*1),2)*BS73),2)+ROUND((ROUND(((AE73-(EU73))*AV73*1),2)*BS73),2)) -> 0 | CT73: =ROUND((ROUND((AF73*AV73*1),2)*BA73),2) -> 0 | CU73: =AG73 -> 0 | CV73: =(AH73*AV73) -> 0 | CW73: =AI73 -> 0 | CX73: =AJ73 -> 0 | CY73: =(ROUND((((S73+ROUND((ROUND(((EU73)*AV73*1),2)*BS73),2))*AT73)/100),2)+ROUND(((ROUND((ROUND(((AE73-(EU73))*AV73*1),2)*BS73),2)*AT73)/100),2)) -> 0 | CZ73: =(ROUND((((S73+ROUND((ROUND(((EU73)*AV73*1),2)*BS73),2))*AU73)/100),2)+ROUND(((ROUND((ROUND(((AE73-(EU73))*AV73*1),2)*BS73),2)*AU73)/100),2)) -> 0 | DN73: 0 | DO73: 0 | DP73: 1 | DQ73: 1 | DU73: 1003 | DV73: м | DW73: м | DX73: 1 | EE73: 60088531 | EF73: 40 | EG73: Монтаж оборудования | EH73: 0 | EJ73: 2 | EK73: 67 | EL73: ТСН-2001.4-8. Электротехнические установки | EM73: ТСН-2001.4-8-1 | EO73: Поправка: Гл.12.Прил.8.п.8. 5_12.00.01.11.003 | EQ73: 0 | ER73: 2.67 | ES73: 2.67 | ET73: 0 | EU73: 0 | EV73: 0 | EW73: 0 | EX73: 0 | FQ73: 0 | FR73: 0 | FS73: 0 | FX73: 97 | FY73: 51 | GD73: 1 | GF73: 1184991115 | GG73: 2 | GH73: 1 | GI73: -2 | GJ73: 0 | GK73: 0 | GL73: =ROUND(IF(AND(BH73=3,BI73=3,FS73<>0),P73,0),2) -> 0 | GM73: =ROUND(O73+X73+Y73,2)+GX73 -> 136.17 | GN73: =IF(OR(BI73=0,BI73=1),GM73-GX73,0) -> 0 | GO73: =IF(BI73=2,GM73-GX73,0) -> 136.17 | GP73: =IF(BI73=4,GM73-GX73,0) -> 0 | GR73: 0 | GS73: 3 | GT73: 0 | GV73: =ROUND((GT73),6) -> 0 | GW73: 1 | GX73: =ROUND(HC73*I73,2) -> 0 | HA73: 0 | HB73: 0 | HC73: =GV73*GW73 -> 0 | HM73: *1 | HS73: 0 | IK73: 0
A74: 18 | B74: 1 | C74: 10 | E74: 5,1 | F74: 1.12-5-371 | G74: Трубы электротехнические, гофрированные, из ПВХ, негорючие, с зондом, наружный диаметр 16 мм | H74: м | I74: =I72*J74 -> 51 | J74: 102 | K74: 102 | O74: =ROUND(CP74,2) -> 521.53 | P74: =ROUND((ROUND((AC74*AW74*I74),2)*BC74),2) -> 521.53 | Q74: =(ROUND((ROUND(((ET74)*AV74*I74),2)*BB74),2)+ROUND((ROUND(((AE74-(EU74))*AV74*I74),2)*BS74),2)) -> 0 | R74: =(ROUND((ROUND(((EU74)*AV74*I74),2)*BS74),2)+ROUND((ROUND(((AE74-(EU74))*AV74*I74),2)*BS74),2)) -> 0 | S74: =ROUND((ROUND((AF74*AV74*I74),2)*BA74),2) -> 0 | T74: =ROUND(CU74*I74,2) -> 0 | U74: =CV74*I74 -> 0 | V74: =CW74*I74 -> 0 | W74: =ROUND(CX74*I74,2) -> 0 | X74: =(ROUND((((S74+ROUND((ROUND(((EU74)*AV74*I74),2)*BS74),2))*AT74)/100),2)+ROUND(((ROUND((ROUND(((AE74-(EU74))*AV74*I74),2)*BS74),2)*AT74)/100),2)) -> 0 | Y74: =(ROUND((((S74+ROUND((ROUND(((EU74)*AV74*I74),2)*BS74),2))*AU74)/100),2)+ROUND(((ROUND((ROUND(((AE74-(EU74))*AV74*I74),2)*BS74),2)*AU74)/100),2)) -> 0 | AA74: 60257733 | AB74: =ROUND((AC74+AD74+AF74),6) -> 2.67 | AC74: =ROUND((ES74),6) -> 2.67 | AD74: =ROUND((((ET74)-(EU74))+AE74),6) -> 0 | AE74: =ROUND((EU74),6) -> 0 | AF74: =ROUND((EV74),6) -> 0 | AG74: =ROUND((AP74),6) -> 0 | AH74: =(EW74) -> 0 | AI74: =(EX74) -> 0 | AJ74: =(AS74) -> 0 | AK74: 2.67 | AL74: 2.67 | AM74: 0 | AN74: 0 | AO74: 0 | AP74: 0 | AQ74: 0 | AR74: 0 | AS74: 0 | AT74: 97 | AU74: 51 | AV74: 1 | AW74: 1 | AZ74: 1 | BA74: 1 | BB74: 1 | BC74: 3.83 | BH74: 3 | BI74: 2 | BJ74: ТСН-2001.1 Доп. 67, Р. 12, о. 5, поз. 371 | BM74: 67 | BN74: 58973116 | BO74: 1.12-5-371 | BP74: 1 | BQ74: 40 | BR74: 0 | BS74: 1 | BT74: 1 | BU74: 1 | BV74: 1 | BW74: 1 | BX74: 1 | BZ74: 97 | CA74: 51 | CE74: 1566 | CF74: 0 | CG74: 0 | CM74: 0 | CN74: Поправка: Гл.12.Прил.8.п.8. 5_12.00.01.11.003 Наименование: При наличии усложненных условий производства работ (стесненность, сложность складирования и транспортной логистики, наличие в зоне производства работ действующего технологического оборудования или движения технологического транспорта и т.п.) для объектов, расположенных за пределами территории круговой магистральной системы улиц "Садовое кольцо" и за пределами Третьего транспортного кольца города Москвы пунктов "а" и "б", но в пределах Московской кольцевой автомобильной дороги | CO74: 0 | CP74: =(P74+Q74+S74) -> 521.53 | CQ74: =ROUND((ROUND((AC74*AW74*1),2)*BC74),2) -> 10.23 | CR74: =(ROUND((ROUND(((ET74)*AV74*1),2)*BB74),2)+ROUND((ROUND(((AE74-(EU74))*AV74*1),2)*BS74),2)) -> 0 | CS74: =(ROUND((ROUND(((EU74)*AV74*1),2)*BS74),2)+ROUND((ROUND(((AE74-(EU74))*AV74*1),2)*BS74),2)) -> 0 | CT74: =ROUND((ROUND((AF74*AV74*1),2)*BA74),2) -> 0 | CU74: =AG74 -> 0 | CV74: =(AH74*AV74) -> 0 | CW74: =AI74 -> 0 | CX74: =AJ74 -> 0 | CY74: =(ROUND((((S74+ROUND((ROUND(((EU74)*AV74*1),2)*BS74),2))*AT74)/100),2)+ROUND(((ROUND((ROUND(((AE74-(EU74))*AV74*1),2)*BS74),2)*AT74)/100),2)) -> 0 | CZ74: =(ROUND((((S74+ROUND((ROUND(((EU74)*AV74*1),2)*BS74),2))*AU74)/100),2)+ROUND(((ROUND((ROUND(((AE74-(EU74))*AV74*1),2)*BS74),2)*AU74)/100),2)) -> 0 | DN74: 0 | DO74: 0 | DP74: 1 | DQ74: 1 | DU74: 1003 | DV74: м | DW74: м | DX74: 1 | EE74: 60088531 | EF74: 40 | EG74: Монтаж оборудования | EH74: 0 | EJ74: 2 | EK74: 67 | EL74: ТСН-2001.4-8. Электротехнические установки | EM74: ТСН-2001.4-8-1 | EO74: Поправка: Гл.12.Прил.8.п.8. 5_12.00.01.11.003 | EQ74: 0 | ER74: 2.67 | ES74: 2.67 | ET74: 0 | EU74: 0 | EV74: 0 | EW74: 0 | EX74: 0 | FQ74: 0 | FR74: 0 | FS74: 0 | FX74: 97 | FY74: 51 | GD74: 1 | GF74: 1184991115 | GG74: 2 | GH74: 1 | GI74: 2 | GJ74: 0 | GK74: 0 | GL74: =ROUND(IF(AND(BH74=3,BI74=3,FS74<>0),P74,0),2) -> 0 | GM74: =ROUND(O74+X74+Y74,2)+GX74 -> 521.53 | GN74: =IF(OR(BI74=0,BI74=1),GM74-GX74,0) -> 0 | GO74: =IF(BI74=2,GM74-GX74,0) -> 521.53 | GP74: =IF(BI74=4,GM74-GX74,0) -> 0 | GR74: 0 | GS74: 3 | GT74: 0 | GV74: =ROUND((GT74),6) -> 0 | GW74: 1 | GX74: =ROUND(HC74*I74,2) -> 0 | HA74: 0 | HB74: 0 | HC74: =GV74*GW74 -> 0 | HM74: *1 | HS74: 0 | IK74: 0
A75: 18 | B75: 1 | C75: 6 | E75: 5,2 | F75: 1.1-1-16 | G75: Антипирен из нефелина | H75: т | I75: =I71*J75 -> 0 | J75: 0 | K75: 0 | O75: =ROUND(CP75,2) -> 0 | P75: =ROUND((ROUND((AC75*AW75*I75),2)*BC75),2) -> 0 | Q75: =(ROUND((ROUND(((ET75)*AV75*I75),2)*BB75),2)+ROUND((ROUND(((AE75-(EU75))*AV75*I75),2)*BS75),2)) -> 0 | R75: =(ROUND((ROUND(((EU75)*AV75*I75),2)*BS75),2)+ROUND((ROUND(((AE75-(EU75))*AV75*I75),2)*BS75),2)) -> 0 | S75: =ROUND((ROUND((AF75*AV75*I75),2)*BA75),2) -> 0 | T75: =ROUND(CU75*I75,2) -> 0 | U75: =CV75*I75 -> 0 | V75: =CW75*I75 -> 0 | W75: =ROUND(CX75*I75,2) -> 0 | X75: =(ROUND((((S75+ROUND((ROUND(((EU75)*AV75*I75),2)*BS75),2))*AT75)/100),2)+ROUND(((ROUND((ROUND(((AE75-(EU75))*AV75*I75),2)*BS75),2)*AT75)/100),2)) -> 0 | Y75: =(ROUND((((S75+ROUND((ROUND(((EU75)*AV75*I75),2)*BS75),2))*AU75)/100),2)+ROUND(((ROUND((ROUND(((AE75-(EU75))*AV75*I75),2)*BS75),2)*AU75)/100),2)) -> 0 | AA75: 60257736 | AB75: =ROUND((AC75+AD75+AF75),6) -> 10315.31 | AC75: =ROUND((ES75),6) -> 10315.31 | AD75: =ROUND((((ET75)-(EU75))+AE75),6) -> 0 | AE75: =ROUND((EU75),6) -> 0 | AF75: =ROUND((EV75),6) -> 0 | AG75: =ROUND((AP75),6) -> 0 | AH75: =(EW75) -> 0 | AI75: =(EX75) -> 0 | AJ75: =(AS75) -> 0 | AK75: 10315.31 | AL75: 10315.31 | AM75: 0 | AN75: 0 | AO75: 0 | AP75: 0 | AQ75: 0 | AR75: 0 | AS75: 0 | AT75: 97 | AU75: 51 | AV75: 1 | AW75: 1 | AZ75: 1 | BA75: 1 | BB75: 1 | BC75: 1 | BH75: 3 | BI75: 2 | BJ75: ТСН-2001.1 Доп. 79, Р. 1, о. 1, поз. 16 | BM75: 67 | BN75: 58973116 | BP75: 0 | BQ75: 40 | BR75: 0 | BS75: 1 | BT75: 1 | BU75: 1 | BV75: 1 | BW75: 1 | BX75: 1 | BZ75: 97 | CA75: 51 | CE75: 1566 | CF75: 0 | CG75: 0 | CM75: 0 | CN75: Поправка: Гл.12.Прил.8.п.8. 5_12.00.01.11.003 Наименование: При наличии усложненных условий производства работ (стесненность, сложность складирования и транспортной логистики, наличие в зоне производства работ действующего технологического оборудования или движения технологического транспорта и т.п.) для объектов, расположенных за пределами территории круговой магистральной системы улиц "Садовое кольцо" и за пределами Третьего транспортного кольца города Москвы пунктов "а" и "б", но в пределах Московской кольцевой автомобильной дороги | CO75: 0 | CP75: =(P75+Q75+S75) -> 0 | CQ75: =ROUND((ROUND((AC75*AW75*1),2)*BC75),2) -> 10315.31 | CR75: =(ROUND((ROUND(((ET75)*AV75*1),2)*BB75),2)+ROUND((ROUND(((AE75-(EU75))*AV75*1),2)*BS75),2)) -> 0 | CS75: =(ROUND((ROUND(((EU75)*AV75*1),2)*BS75),2)+ROUND((ROUND(((AE75-(EU75))*AV75*1),2)*BS75),2)) -> 0 | CT75: =ROUND((ROUND((AF75*AV75*1),2)*BA75),2) -> 0 | CU75: =AG75 -> 0 | CV75: =(AH75*AV75) -> 0 | CW75: =AI75 -> 0 | CX75: =AJ75 -> 0 | CY75: =(ROUND((((S75+ROUND((ROUND(((EU75)*AV75*1),2)*BS75),2))*AT75)/100),2)+ROUND(((ROUND((ROUND(((AE75-(EU75))*AV75*1),2)*BS75),2)*AT75)/100),2)) -> 0 | CZ75: =(ROUND((((S75+ROUND((ROUND(((EU75)*AV75*1),2)*BS75),2))*AU75)/100),2)+ROUND(((ROUND((ROUND(((AE75-(EU75))*AV75*1),2)*BS75),2)*AU75)/100),2)) -> 0 | DN75: 0 | DO75: 0 | DP75: 1 | DQ75: 1 | DU75: 1009 | DV75: т | DW75: т | DX75: 1000 | EE75: 60088531 | EF75: 40 | EG75: Монтаж оборудования | EH75: 0 | EJ75: 2 | EK75: 67 | EL75: ТСН-2001.4-8. Электротехнические установки | EM75: ТСН-2001.4-8-1 | EO75: Поправка: Гл.12.Прил.8.п.8. 5_12.00.01.11.003 | EQ75: 0 | ER75: 10315.31 | ES75: 10315.31 | ET75: 0 | EU75: 0 | EV75: 0 | EW75: 0 | EX75: 0 | FQ75: 0 | FR75: 0 | FS75: 0 | FX75: 97 | FY75: 51 | GD75: 1 | GF75: -152177588 | GG75: 2 | GH75: 1 | GI75: -2 | GJ75: 0 | GK75: 0 | GL75: =ROUND(IF(AND(BH75=3,BI75=3,FS75<>0),P75,0),2) -> 0 | GM75: =ROUND(O75+X75+Y75,2)+GX75 -> 0 | GN75: =IF(OR(BI75=0,BI75=1),GM75-GX75,0) -> 0 | GO75: =IF(BI75=2,GM75-GX75,0) -> 0 | GP75: =IF(BI75=4,GM75-GX75,0) -> 0 | GR75: 0 | GS75: 3 | GT75: 0 | GV75: =ROUND((GT75),6) -> 0 | GW75: 1 | GX75: =ROUND(HC75*I75,2) -> 0 | HA75: 0 | HB75: 0 | HC75: =GV75*GW75 -> 0 | HM75: *1 | HS75: 0 | IK75: 0
A76: 18 | B76: 1 | C76: 9 | E76: 5,2 | F76: 1.1-1-16 | G76: Антипирен из нефелина | H76: т | I76: =I72*J76 -> 0 | J76: 0 | K76: 0 | O76: =ROUND(CP76,2) -> 0 | P76: =ROUND((ROUND((AC76*AW76*I76),2)*BC76),2) -> 0 | Q76: =(ROUND((ROUND(((ET76)*AV76*I76),2)*BB76),2)+ROUND((ROUND(((AE76-(EU76))*AV76*I76),2)*BS76),2)) -> 0 | R76: =(ROUND((ROUND(((EU76)*AV76*I76),2)*BS76),2)+ROUND((ROUND(((AE76-(EU76))*AV76*I76),2)*BS76),2)) -> 0 | S76: =ROUND((ROUND((AF76*AV76*I76),2)*BA76),2) -> 0 | T76: =ROUND(CU76*I76,2) -> 0 | U76: =CV76*I76 -> 0 | V76: =CW76*I76 -> 0 | W76: =ROUND(CX76*I76,2) -> 0 | X76: =(ROUND((((S76+ROUND((ROUND(((EU76)*AV76*I76),2)*BS76),2))*AT76)/100),2)+ROUND(((ROUND((ROUND(((AE76-(EU76))*AV76*I76),2)*BS76),2)*AT76)/100),2)) -> 0 | Y76: =(ROUND((((S76+ROUND((ROUND(((EU76)*AV76*I76),2)*BS76),2))*AU76)/100),2)+ROUND(((ROUND((ROUND(((AE76-(EU76))*AV76*I76),2)*BS76),2)*AU76)/100),2)) -> 0 | AA76: 60257733 | AB76: =ROUND((AC76+AD76+AF76),6) -> 10315.31 | AC76: =ROUND((ES76),6) -> 10315.31 | AD76: =ROUND((((ET76)-(EU76))+AE76),6) -> 0 | AE76: =ROUND((EU76),6) -> 0 | AF76: =ROUND((EV76),6) -> 0 | AG76: =ROUND((AP76),6) -> 0 | AH76: =(EW76) -> 0 | AI76: =(EX76) -> 0 | AJ76: =(AS76) -> 0 | AK76: 10315.31 | AL76: 10315.31 | AM76: 0 | AN76: 0 | AO76: 0 | AP76: 0 | AQ76: 0 | AR76: 0 | AS76: 0 | AT76: 97 | AU76: 51 | AV76: 1 | AW76: 1 | AZ76: 1 | BA76: 1 | BB76: 1 | BC76: 4.68 | BH76: 3 | BI76: 2 | BJ76: ТСН-2001.1 Доп. 79, Р. 1, о. 1, поз. 16 | BM76: 67 | BN76: 58973116 | BO76: 1.1-1-16 | BP76: 1 | BQ76: 40 | BR76: 0 | BS76: 1 | BT76: 1 | BU76: 1 | BV76: 1 | BW76: 1 | BX76: 1 | BZ76: 97 | CA76: 51 | CE76: 1566 | CF76: 0 | CG76: 0 | CM76: 0 | CN76: Поправка: Гл.12.Прил.8.п.8. 5_12.00.01.11.003 Наименование: При наличии усложненных условий производства работ (стесненность, сложность складирования и транспортной логистики, наличие в зоне производства работ действующего технологического оборудования или движения технологического транспорта и т.п.) для объектов, расположенных за пределами территории круговой магистральной системы улиц "Садовое кольцо" и за пределами Третьего транспортного кольца города Москвы пунктов "а" и "б", но в пределах Московской кольцевой автомобильной дороги | CO76: 0 | CP76: =(P76+Q76+S76) -> 0 | CQ76: =ROUND((ROUND((AC76*AW76*1),2)*BC76),2) -> 48275.65 | CR76: =(ROUND((ROUND(((ET76)*AV76*1),2)*BB76),2)+ROUND((ROUND(((AE76-(EU76))*AV76*1),2)*BS76),2)) -> 0 | CS76: =(ROUND((ROUND(((EU76)*AV76*1),2)*BS76),2)+ROUND((ROUND(((AE76-(EU76))*AV76*1),2)*BS76),2)) -> 0 | CT76: =ROUND((ROUND((AF76*AV76*1),2)*BA76),2) -> 0 | CU76: =AG76 -> 0 | CV76: =(AH76*AV76) -> 0 | CW76: =AI76 -> 0 | CX76: =AJ76 -> 0 | CY76: =(ROUND((((S76+ROUND((ROUND(((EU76)*AV76*1),2)*BS76),2))*AT76)/100),2)+ROUND(((ROUND((ROUND(((AE76-(EU76))*AV76*1),2)*BS76),2)*AT76)/100),2)) -> 0 | CZ76: =(ROUND((((S76+ROUND((ROUND(((EU76)*AV76*1),2)*BS76),2))*AU76)/100),2)+ROUND(((ROUND((ROUND(((AE76-(EU76))*AV76*1),2)*BS76),2)*AU76)/100),2)) -> 0 | DN76: 0 | DO76: 0 | DP76: 1 | DQ76: 1 | DU76: 1009 | DV76: т | DW76: т | DX76: 1000 | EE76: 60088531 | EF76: 40 | EG76: Монтаж оборудования | EH76: 0 | EJ76: 2 | EK76: 67 | EL76: ТСН-2001.4-8. Электротехнические установки | EM76: ТСН-2001.4-8-1 | EO76: Поправка: Гл.12.Прил.8.п.8. 5_12.00.01.11.003 | EQ76: 0 | ER76: 10315.31 | ES76: 10315.31 | ET76: 0 | EU76: 0 | EV76: 0 | EW76: 0 | EX76: 0 | FQ76: 0 | FR76: 0 | FS76: 0 | FX76: 97 | FY76: 51 | GD76: 1 | GF76: -152177588 | GG76: 2 | GH76: 1 | GI76: 2 | GJ76: 0 | GK76: 0 | GL76: =ROUND(IF(AND(BH76=3,BI76=3,FS76<>0),P76,0),2) -> 0 | GM76: =ROUND(O76+X76+Y76,2)+GX76 -> 0 | GN76: =IF(OR(BI76=0,BI76=1),GM76-GX76,0) -> 0 | GO76: =IF(BI76=2,GM76-GX76,0) -> 0 | GP76: =IF(BI76=4,GM76-GX76,0) -> 0 | GR76: 0 | GS76: 3 | GT76: 0 | GV76: =ROUND((GT76),6) -> 0 | GW76: 1 | GX76: =ROUND(HC76*I76,2) -> 0 | HA76: 0 | HB76: 0 | HC76: =GV76*GW76 -> 0 | HM76: *1 | HS76: 0 | IK76: 0
A77: 17 | B77: 1 | C77: =ROW(SmtRes!A19) -> 19 | D77: =ROW(EtalonRes!A22) -> 22 | E77: 6 | F77: 4.8-175-1 | G77: Затягивание провода в проложенные трубы и металлические рукава, первого одножильного или многожильного в общей оплетке, суммарное сечение до 2,5 мм2 | H77: 100 м | I77: =ROUND(50/100,9) -> 0.5 | J77: 0 | K77: =ROUND(50/100,9) -> 0.5 | O77: =ROUND(CP77,2) -> 62.39 | P77: =ROUND((ROUND((AC77*AW77*I77),2)*BC77),2) -> 29.08 | Q77: =(ROUND((ROUND((((ET77*1.1))*AV77*I77),2)*BB77),2)+ROUND((ROUND(((AE77-((EU77*1.1)))*AV77*I77),2)*BS77),2)) -> 1.51 | R77: =(ROUND((ROUND((((EU77*1.1))*AV77*I77),2)*BS77),2)+ROUND((ROUND(((AE77-((EU77*1.1)))*AV77*I77),2)*BS77),2)) -> 0.17 | S77: =ROUND((ROUND((AF77*AV77*I77),2)*BA77),2) -> 31.8 | T77: =ROUND(CU77*I77,2) -> 0 | U77: =CV77*I77 -> 2.5855665 | V77: =CW77*I77 -> 0 | W77: =ROUND(CX77*I77,2) -> 0 | X77: =(ROUND((((S77+ROUND((ROUND((((EU77*1.1))*AV77*I77),2)*BS77),2))*AT77)/100),2)+ROUND(((ROUND((ROUND(((AE77-((EU77*1.1)))*AV77*I77),2)*BS77),2)*AT77)/100),2)) -> 31.01 | Y77: =(ROUND((((S77+ROUND((ROUND((((EU77*1.1))*AV77*I77),2)*BS77),2))*AU77)/100),2)+ROUND(((ROUND((ROUND(((AE77-((EU77*1.1)))*AV77*I77),2)*BS77),2)*AU77)/100),2)) -> 16.3 | AA77: 60257736 | AB77: =ROUND((AC77+AD77+AF77),6) -> 121.785 | AC77: =ROUND(((ES77*1)),6) -> 58.15 | AD77: =ROUND(((((ET77*1.1))-((EU77*1.1)))+AE77),6) -> 2.882 | AE77: =ROUND(((EU77*1.1)),6) -> 0.33 | AF77: =ROUND(((EV77*1.1)),6) -> 60.753 | AG77: =ROUND((AP77),6) -> 0 | AH77: =((EW77*1.1)) -> 4.939 | AI77: =((EX77*1.1)) -> 0 | AJ77: =(AS77) -> 0 | AK77: 116 | AL77: 58.15 | AM77: 2.62 | AN77: 0.3 | AO77: 55.23 | AP77: 0 | AQ77: 4.49 | AR77: 0 | AS77: 0 | AT77: 97 | AU77: 51 | AV77: 1.047 | AW77: 1 | AZ77: 1 | BA77: 1 | BB77: 1 | BC77: 1 | BH77: 0 | BI77: 2 | BJ77: ТСН-2001.4 Доп. 71, Сб. 8, т. 175, поз. 1 | BM77: 67 | BN77: 58973116 | BO77: 4.8-175-1 | BP77: 1 | BQ77: 40 | BR77: 0 | BS77: 1 | BT77: 1 | BU77: 1 | BV77: 1 | BW77: 1 | BX77: 1 | BZ77: 97 | CA77: 51 | CE77: 1566 | CF77: 0 | CG77: 0 | CM77: 0 | CN77: Поправка: Гл.12.Прил.8.п.8. 5_12.00.01.11.003 Наименование: При наличии усложненных условий производства работ (стесненность, сложность складирования и транспортной логистики, наличие в зоне производства работ действующего технологического оборудования или движения технологического транспорта и т.п.) для объектов, расположенных за пределами территории круговой магистральной системы улиц "Садовое кольцо" и за пределами Третьего транспортного кольца города Москвы пунктов "а" и "б", но в пределах Московской кольцевой автомобильной дороги | CO77: 0 | CP77: =(P77+Q77+S77) -> 62.39 | CQ77: =ROUND((ROUND((AC77*AW77*1),2)*BC77),2) -> 58.15 | CR77: =(ROUND((ROUND((((ET77*1.1))*AV77*1),2)*BB77),2)+ROUND((ROUND(((AE77-((EU77*1.1)))*AV77*1),2)*BS77),2)) -> 3.02 | CS77: =(ROUND((ROUND((((EU77*1.1))*AV77*1),2)*BS77),2)+ROUND((ROUND(((AE77-((EU77*1.1)))*AV77*1),2)*BS77),2)) -> 0.35 | CT77: =ROUND((ROUND((AF77*AV77*1),2)*BA77),2) -> 63.61 | CU77: =AG77 -> 0 | CV77: =(AH77*AV77) -> 5.171133 | CW77: =AI77 -> 0 | CX77: =AJ77 -> 0 | CY77: =(ROUND((((S77+ROUND((ROUND((((EU77*1.1))*AV77*1),2)*BS77),2))*AT77)/100),2)+ROUND(((ROUND((ROUND(((AE77-((EU77*1.1)))*AV77*1),2)*BS77),2)*AT77)/100),2)) -> 31.19 | CZ77: =(ROUND((((S77+ROUND((ROUND((((EU77*1.1))*AV77*1),2)*BS77),2))*AU77)/100),2)+ROUND(((ROUND((ROUND(((AE77-((EU77*1.1)))*AV77*1),2)*BS77),2)*AU77)/100),2)) -> 16.4 | DB77: 7 | DD77: *1 | DE77: *1,1 | DF77: *1,1 | DG77: *1,1 | DI77: *1,1 | DJ77: *1,1 | DN77: 0 | DO77: 0 | DP77: 1 | DQ77: 1 | DU77: 1003 | DV77: 100 м | DW77: 100 м | DX77: 100 | EE77: 60088531 | EF77: 40 | EG77: Монтаж оборудования | EH77: 0 | EJ77: 2 | EK77: 67 | EL77: ТСН-2001.4-8. Электротехнические установки | EM77: ТСН-2001.4-8-1 | EO77: Поправка: Гл.12.Прил.8.п.8. 5_12.00.01.11.003 | EQ77: 0 | ER77: 116 | ES77: 58.15 | ET77: 2.62 | EU77: 0.3 | EV77: 55.23 | EW77: 4.49 | EX77: 0 | EY77: 0 | FQ77: 0 | FR77: 0 | FS77: 0 | FX77: 97 | FY77: 51 | GD77: 1 | GF77: 770559996 | GG77: 2 | GH77: 1 | GI77: 2 | GJ77: 0 | GK77: 0 | GL77: =ROUND(IF(AND(BH77=3,BI77=3,FS77<>0),P77,0),2) -> 0 | GM77: =ROUND(O77+X77+Y77,2)+GX77 -> 109.7 | GN77: =IF(OR(BI77=0,BI77=1),GM77-GX77,0) -> 0 | GO77: =IF(BI77=2,GM77-GX77,0) -> 109.7 | GP77: =IF(BI77=4,GM77-GX77,0) -> 0 | GR77: 0 | GS77: 3 | GT77: 0 | GV77: =ROUND((GT77),6) -> 0 | GW77: 1 | GX77: =ROUND(HC77*I77,2) -> 0 | HA77: 0 | HB77: 0 | HC77: =GV77*GW77 -> 0 | HS77: 0 | IK77: 0
A78: 17 | B78: 1 | C78: =ROW(SmtRes!A28) -> 28 | D78: =ROW(EtalonRes!A32) -> 32 | E78: 6 | F78: 4.8-175-1 | G78: Затягивание провода в проложенные трубы и металлические рукава, первого одножильного или многожильного в общей оплетке, суммарное сечение до 2,5 мм2 | H78: 100 м | I78: =ROUND(50/100,9) -> 0.5 | J78: 0 | K78: =ROUND(50/100,9) -> 0.5 | O78: =ROUND(CP78,2) -> 1878.28 | P78: =ROUND((ROUND((AC78*AW78*I78),2)*BC78),2) -> 107.6 | Q78: =(ROUND((ROUND((((ET78*1.1))*AV78*I78),2)*BB78),2)+ROUND((ROUND(((AE78-((EU78*1.1)))*AV78*I78),2)*BS78),2)) -> 22 | R78: =(ROUND((ROUND((((EU78*1.1))*AV78*I78),2)*BS78),2)+ROUND((ROUND(((AE78-((EU78*1.1)))*AV78*I78),2)*BS78),2)) -> 9.35 | S78: =ROUND((ROUND((AF78*AV78*I78),2)*BA78),2) -> 1748.68 | T78: =ROUND(CU78*I78,2) -> 0 | U78: =CV78*I78 -> 2.5855665 | V78: =CW78*I78 -> 0 | W78: =ROUND(CX78*I78,2) -> 0 | X78: =(ROUND((((S78+ROUND((ROUND((((EU78*1.1))*AV78*I78),2)*BS78),2))*AT78)/100),2)+ROUND(((ROUND((ROUND(((AE78-((EU78*1.1)))*AV78*I78),2)*BS78),2)*AT78)/100),2)) -> 1705.29 | Y78: =(ROUND((((S78+ROUND((ROUND((((EU78*1.1))*AV78*I78),2)*BS78),2))*AU78)/100),2)+ROUND(((ROUND((ROUND(((AE78-((EU78*1.1)))*AV78*I78),2)*BS78),2)*AU78)/100),2)) -> 896.6 | AA78: 60257733 | AB78: =ROUND((AC78+AD78+AF78),6) -> 121.785 | AC78: =ROUND(((ES78*1)),6) -> 58.15 | AD78: =ROUND(((((ET78*1.1))-((EU78*1.1)))+AE78),6) -> 2.882 | AE78: =ROUND(((EU78*1.1)),6) -> 0.33 | AF78: =ROUND(((EV78*1.1)),6) -> 60.753 | AG78: =ROUND((AP78),6) -> 0 | AH78: =((EW78*1.1)) -> 4.939 | AI78: =((EX78*1.1)) -> 0 | AJ78: =(AS78) -> 0 | AK78: 116 | AL78: 58.15 | AM78: 2.62 | AN78: 0.3 | AO78: 55.23 | AP78: 0 | AQ78: 4.49 | AR78: 0 | AS78: 0 | AT78: 97 | AU78: 51 | AV78: 1.047 | AW78: 1 | AZ78: 1 | BA78: 54.99 | BB78: 14.57 | BC78: 3.7 | BH78: 0 | BI78: 2 | BJ78: ТСН-2001.4 Доп. 71, Сб. 8, т. 175, поз. 1 | BM78: 67 | BN78: 58973116 | BO78: 4.8-175-1 | BP78: 1 | BQ78: 40 | BR78: 0 | BS78: 54.99 | BT78: 1 | BU78: 1 | BV78: 1 | BW78: 1 | BX78: 1 | BZ78: 97 | CA78: 51 | CE78: 1566 | CF78: 0 | CG78: 0 | CM78: 0 | CN78: Поправка: Гл.12.Прил.8.п.8. 5_12.00.01.11.003 Наименование: При наличии усложненных условий производства работ (стесненность, сложность складирования и транспортной логистики, наличие в зоне производства работ действующего технологического оборудования или движения технологического транспорта и т.п.) для объектов, расположенных за пределами территории круговой магистральной системы улиц "Садовое кольцо" и за пределами Третьего транспортного кольца города Москвы пунктов "а" и "б", но в пределах Московской кольцевой автомобильной дороги | CO78: 0 | CP78: =(P78+Q78+S78) -> 1878.28 | CQ78: =ROUND((ROUND((AC78*AW78*1),2)*BC78),2) -> 215.16 | CR78: =(ROUND((ROUND((((ET78*1.1))*AV78*1),2)*BB78),2)+ROUND((ROUND(((AE78-((EU78*1.1)))*AV78*1),2)*BS78),2)) -> 44 | CS78: =(ROUND((ROUND((((EU78*1.1))*AV78*1),2)*BS78),2)+ROUND((ROUND(((AE78-((EU78*1.1)))*AV78*1),2)*BS78),2)) -> 19.25 | CT78: =ROUND((ROUND((AF78*AV78*1),2)*BA78),2) -> 3497.91 | CU78: =AG78 -> 0 | CV78: =(AH78*AV78) -> 5.171133 | CW78: =AI78 -> 0 | CX78: =AJ78 -> 0 | CY78: =(ROUND((((S78+ROUND((ROUND((((EU78*1.1))*AV78*1),2)*BS78),2))*AT78)/100),2)+ROUND(((ROUND((ROUND(((AE78-((EU78*1.1)))*AV78*1),2)*BS78),2)*AT78)/100),2)) -> 1714.89 | CZ78: =(ROUND((((S78+ROUND((ROUND((((EU78*1.1))*AV78*1),2)*BS78),2))*AU78)/100),2)+ROUND(((ROUND((ROUND(((AE78-((EU78*1.1)))*AV78*1),2)*BS78),2)*AU78)/100),2)) -> 901.64 | DB78: 8 | DD78: *1 | DE78: *1,1 | DF78: *1,1 | DG78: *1,1 | DI78: *1,1 | DJ78: *1,1 | DN78: 0 | DO78: 0 | DP78: 1 | DQ78: 1 | DU78: 1003 | DV78: 100 м | DW78: 100 м | DX78: 100 | EE78: 60088531 | EF78: 40 | EG78: Монтаж оборудования | EH78: 0 | EJ78: 2 | EK78: 67 | EL78: ТСН-2001.4-8. Электротехнические установки | EM78: ТСН-2001.4-8-1 | EO78: Поправка: Гл.12.Прил.8.п.8. 5_12.00.01.11.003 | EQ78: 0 | ER78: 116 | ES78: 58.15 | ET78: 2.62 | EU78: 0.3 | EV78: 55.23 | EW78: 4.49 | EX78: 0 | EY78: 0 | FQ78: 0 | FR78: 0 | FS78: 0 | FX78: 97 | FY78: 51 | GD78: 1 | GF78: 770559996 | GG78: 2 | GH78: 1 | GI78: 2 | GJ78: 0 | GK78: 0 | GL78: =ROUND(IF(AND(BH78=3,BI78=3,FS78<>0),P78,0),2) -> 0 | GM78: =ROUND(O78+X78+Y78,2)+GX78 -> 4480.17 | GN78: =IF(OR(BI78=0,BI78=1),GM78-GX78,0) -> 0 | GO78: =IF(BI78=2,GM78-GX78,0) -> 4480.17 | GP78: =IF(BI78=4,GM78-GX78,0) -> 0 | GR78: 0 | GS78: 3 | GT78: 0 | GV78: =ROUND((GT78),6) -> 0 | GW78: 1 | GX78: =ROUND(HC78*I78,2) -> 0 | HA78: 0 | HB78: 0 | HC78: =GV78*GW78 -> 0 | HS78: 0 | IK78: 0
A79: 17 | B79: 1 | C79: =ROW(SmtRes!A36) -> 36 | D79: =ROW(EtalonRes!A41) -> 41 | E79: 7 | F79: 4.8-175-9 | G79: Добавлять на затягивание провода в проложенные трубы и металлические рукава каждого последующего одножильного или многожильного в общей оплетке, суммарное сечение до 6 мм2 (к нормам и расценкам 4.8-175-1 и 4.8-175-2) | H79: 100 м | I79: =ROUND(50/100,9) -> 0.5 | J79: 0 | K79: =ROUND(50/100,9) -> 0.5 | O79: =ROUND(CP79,2) -> 42.21 | P79: =ROUND((ROUND((AC79*AW79*I79),2)*BC79),2) -> 27.74 | Q79: =(ROUND((ROUND((((ET79*1.1))*AV79*I79),2)*BB79),2)+ROUND((ROUND(((AE79-((EU79*1.1)))*AV79*I79),2)*BS79),2)) -> 1.51 | R79: =(ROUND((ROUND((((EU79*1.1))*AV79*I79),2)*BS79),2)+ROUND((ROUND(((AE79-((EU79*1.1)))*AV79*I79),2)*BS79),2)) -> 0.17 | S79: =ROUND((ROUND((AF79*AV79*I79),2)*BA79),2) -> 12.96 | T79: =ROUND(CU79*I79,2) -> 0 | U79: =CV79*I79 -> 1.0538055 | V79: =CW79*I79 -> 0 | W79: =ROUND(CX79*I79,2) -> 0 | X79: =(ROUND((((S79+ROUND((ROUND((((EU79*1.1))*AV79*I79),2)*BS79),2))*AT79)/100),2)+ROUND(((ROUND((ROUND(((AE79-((EU79*1.1)))*AV79*I79),2)*BS79),2)*AT79)/100),2)) -> 12.74 | Y79: =(ROUND((((S79+ROUND((ROUND((((EU79*1.1))*AV79*I79),2)*BS79),2))*AU79)/100),2)+ROUND(((ROUND((ROUND(((AE79-((EU79*1.1)))*AV79*I79),2)*BS79),2)*AU79)/100),2)) -> 6.7 | AA79: 60257736 | AB79: =ROUND((AC79+AD79+AF79),6) -> 83.113 | AC79: =ROUND(((ES79*1)),6) -> 55.47 | AD79: =ROUND(((((ET79*1.1))-((EU79*1.1)))+AE79),6) -> 2.882 | AE79: =ROUND(((EU79*1.1)),6) -> 0.33 | AF79: =ROUND(((EV79*1.1)),6) -> 24.761 | AG79: =ROUND((AP79),6) -> 0 | AH79: =((EW79*1.1)) -> 2.013 | AI79: =((EX79*1.1)) -> 0 | AJ79: =(AS79) -> 0 | AK79: 80.6 | AL79: 55.47 | AM79: 2.62 | AN79: 0.3 | AO79: 22.51 | AP79: 0 | AQ79: 1.83 | AR79: 0 | AS79: 0 | AT79: 97 | AU79: 51 | AV79: 1.047 | AW79: 1 | AZ79: 1 | BA79: 1 | BB79: 1 | BC79: 1 | BH79: 0 | BI79: 2 | BJ79: ТСН-2001.4 Доп. 80, Сб. 8, т. 175, поз. 9 | BM79: 67 | BN79: 58973116 | BO79: 4.8-175-9 | BP79: 1 | BQ79: 40 | BR79: 0 | BS79: 1 | BT79: 1 | BU79: 1 | BV79: 1 | BW79: 1 | BX79: 1 | BZ79: 97 | CA79: 51 | CE79: 1566 | CF79: 0 | CG79: 0 | CM79: 0 | CN79: Поправка: Гл.12.Прил.8.п.8. 5_12.00.01.11.003 Наименование: При наличии усложненных условий производства работ (стесненность, сложность складирования и транспортной логистики, наличие в зоне производства работ действующего технологического оборудования или движения технологического транспорта и т.п.) для объектов, расположенных за пределами территории круговой магистральной системы улиц "Садовое кольцо" и за пределами Третьего транспортного кольца города Москвы пунктов "а" и "б", но в пределах Московской кольцевой автомобильной дороги | CO79: 0 | CP79: =(P79+Q79+S79) -> 42.21 | CQ79: =ROUND((ROUND((AC79*AW79*1),2)*BC79),2) -> 55.47 | CR79: =(ROUND((ROUND((((ET79*1.1))*AV79*1),2)*BB79),2)+ROUND((ROUND(((AE79-((EU79*1.1)))*AV79*1),2)*BS79),2)) -> 3.02 | CS79: =(ROUND((ROUND((((EU79*1.1))*AV79*1),2)*BS79),2)+ROUND((ROUND(((AE79-((EU79*1.1)))*AV79*1),2)*BS79),2)) -> 0.35 | CT79: =ROUND((ROUND((AF79*AV79*1),2)*BA79),2) -> 25.92 | CU79: =AG79 -> 0 | CV79: =(AH79*AV79) -> 2.107611 | CW79: =AI79 -> 0 | CX79: =AJ79 -> 0 | CY79: =(ROUND((((S79+ROUND((ROUND((((EU79*1.1))*AV79*1),2)*BS79),2))*AT79)/100),2)+ROUND(((ROUND((ROUND(((AE79-((EU79*1.1)))*AV79*1),2)*BS79),2)*AT79)/100),2)) -> 12.91 | CZ79: =(ROUND((((S79+ROUND((ROUND((((EU79*1.1))*AV79*1),2)*BS79),2))*AU79)/100),2)+ROUND(((ROUND((ROUND(((AE79-((EU79*1.1)))*AV79*1),2)*BS79),2)*AU79)/100),2)) -> 6.79 | DB79: 9 | DD79: *1 | DE79: *1,1 | DF79: *1,1 | DG79: *1,1 | DI79: *1,1 | DJ79: *1,1 | DN79: 0 | DO79: 0 | DP79: 1 | DQ79: 1 | DU79: 1003 | DV79: 100 м | DW79: 100 м | DX79: 100 | EE79: 60088531 | EF79: 40 | EG79: Монтаж оборудования | EH79: 0 | EJ79: 2 | EK79: 67 | EL79: ТСН-2001.4-8. Электротехнические установки | EM79: ТСН-2001.4-8-1 | EO79: Поправка: Гл.12.Прил.8.п.8. 5_12.00.01.11.003 | EQ79: 0 | ER79: 80.6 | ES79: 55.47 | ET79: 2.62 | EU79: 0.3 | EV79: 22.51 | EW79: 1.83 | EX79: 0 | EY79: 0 | FQ79: 0 | FR79: 0 | FS79: 0 | FX79: 97 | FY79: 51 | GD79: 1 | GF79: 1118340632 | GG79: 2 | GH79: 1 | GI79: 2 | GJ79: 0 | GK79: 0 | GL79: =ROUND(IF(AND(BH79=3,BI79=3,FS79<>0),P79,0),2) -> 0 | GM79: =ROUND(O79+X79+Y79,2)+GX79 -> 61.65 | GN79: =IF(OR(BI79=0,BI79=1),GM79-GX79,0) -> 0 | GO79: =IF(BI79=2,GM79-GX79,0) -> 61.65 | GP79: =IF(BI79=4,GM79-GX79,0) -> 0 | GR79: 0 | GS79: 3 | GT79: 0 | GV79: =ROUND((GT79),6) -> 0 | GW79: 1 | GX79: =ROUND(HC79*I79,2) -> 0 | HA79: 0 | HB79: 0 | HC79: =GV79*GW79 -> 0 | HS79: 0 | IK79: 0
A80: 17 | B80: 1 | C80: =ROW(SmtRes!A44) -> 44 | D80: =ROW(EtalonRes!A50) -> 50 | E80: 7 | F80: 4.8-175-9 | G80: Добавлять на затягивание провода в проложенные трубы и металлические рукава каждого последующего одножильного или многожильного в общей оплетке, суммарное сечение до 6 мм2 (к нормам и расценкам 4.8-175-1 и 4.8-175-2) | H80: 100 м | I80: =ROUND(50/100,9) -> 0.5 | J80: 0 | K80: =ROUND(50/100,9) -> 0.5 | O80: =ROUND(CP80,2) -> 820.39 | P80: =ROUND((ROUND((AC80*AW80*I80),2)*BC80),2) -> 85.72 | Q80: =(ROUND((ROUND((((ET80*1.1))*AV80*I80),2)*BB80),2)+ROUND((ROUND(((AE80-((EU80*1.1)))*AV80*I80),2)*BS80),2)) -> 22 | R80: =(ROUND((ROUND((((EU80*1.1))*AV80*I80),2)*BS80),2)+ROUND((ROUND(((AE80-((EU80*1.1)))*AV80*I80),2)*BS80),2)) -> 9.35 | S80: =ROUND((ROUND((AF80*AV80*I80),2)*BA80),2) -> 712.67 | T80: =ROUND(CU80*I80,2) -> 0 | U80: =CV80*I80 -> 1.0538055 | V80: =CW80*I80 -> 0 | W80: =ROUND(CX80*I80,2) -> 0 | X80: =(ROUND((((S80+ROUND((ROUND((((EU80*1.1))*AV80*I80),2)*BS80),2))*AT80)/100),2)+ROUND(((ROUND((ROUND(((AE80-((EU80*1.1)))*AV80*I80),2)*BS80),2)*AT80)/100),2)) -> 700.36 | Y80: =(ROUND((((S80+ROUND((ROUND((((EU80*1.1))*AV80*I80),2)*BS80),2))*AU80)/100),2)+ROUND(((ROUND((ROUND(((AE80-((EU80*1.1)))*AV80*I80),2)*BS80),2)*AU80)/100),2)) -> 368.23 | AA80: 60257733 | AB80: =ROUND((AC80+AD80+AF80),6) -> 83.113 | AC80: =ROUND(((ES80*1)),6) -> 55.47 | AD80: =ROUND(((((ET80*1.1))-((EU80*1.1)))+AE80),6) -> 2.882 | AE80: =ROUND(((EU80*1.1)),6) -> 0.33 | AF80: =ROUND(((EV80*1.1)),6) -> 24.761 | AG80: =ROUND((AP80),6) -> 0 | AH80: =((EW80*1.1)) -> 2.013 | AI80: =((EX80*1.1)) -> 0 | AJ80: =(AS80) -> 0 | AK80: 80.6 | AL80: 55.47 | AM80: 2.62 | AN80: 0.3 | AO80: 22.51 | AP80: 0 | AQ80: 1.83 | AR80: 0 | AS80: 0 | AT80: 97 | AU80: 51 | AV80: 1.047 | AW80: 1 | AZ80: 1 | BA80: 54.99 | BB80: 14.57 | BC80: 3.09 | BH80: 0 | BI80: 2 | BJ80: ТСН-2001.4 Доп. 80, Сб. 8, т. 175, поз. 9 | BM80: 67 | BN80: 58973116 | BO80: 4.8-175-9 | BP80: 1 | BQ80: 40 | BR80: 0 | BS80: 54.99 | BT80: 1 | BU80: 1 | BV80: 1 | BW80: 1 | BX80: 1 | BZ80: 97 | CA80: 51 | CE80: 1566 | CF80: 0 | CG80: 0 | CM80: 0 | CN80: Поправка: Гл.12.Прил.8.п.8. 5_12.00.01.11.003 Наименование: При наличии усложненных условий производства работ (стесненность, сложность складирования и транспортной логистики, наличие в зоне производства работ действующего технологического оборудования или движения технологического транспорта и т.п.) для объектов, расположенных за пределами территории круговой магистральной системы улиц "Садовое кольцо" и за пределами Третьего транспортного кольца города Москвы пунктов "а" и "б", но в пределах Московской кольцевой автомобильной дороги | CO80: 0 | CP80: =(P80+Q80+S80) -> 820.39 | CQ80: =ROUND((ROUND((AC80*AW80*1),2)*BC80),2) -> 171.4 | CR80: =(ROUND((ROUND((((ET80*1.1))*AV80*1),2)*BB80),2)+ROUND((ROUND(((AE80-((EU80*1.1)))*AV80*1),2)*BS80),2)) -> 44 | CS80: =(ROUND((ROUND((((EU80*1.1))*AV80*1),2)*BS80),2)+ROUND((ROUND(((AE80-((EU80*1.1)))*AV80*1),2)*BS80),2)) -> 19.25 | CT80: =ROUND((ROUND((AF80*AV80*1),2)*BA80),2) -> 1425.34 | CU80: =AG80 -> 0 | CV80: =(AH80*AV80) -> 2.107611 | CW80: =AI80 -> 0 | CX80: =AJ80 -> 0 | CY80: =(ROUND((((S80+ROUND((ROUND((((EU80*1.1))*AV80*1),2)*BS80),2))*AT80)/100),2)+ROUND(((ROUND((ROUND(((AE80-((EU80*1.1)))*AV80*1),2)*BS80),2)*AT80)/100),2)) -> 709.96 | CZ80: =(ROUND((((S80+ROUND((ROUND((((EU80*1.1))*AV80*1),2)*BS80),2))*AU80)/100),2)+ROUND(((ROUND((ROUND(((AE80-((EU80*1.1)))*AV80*1),2)*BS80),2)*AU80)/100),2)) -> 373.28 | DB80: 10 | DD80: *1 | DE80: *1,1 | DF80: *1,1 | DG80: *1,1 | DI80: *1,1 | DJ80: *1,1 | DN80: 0 | DO80: 0 | DP80: 1 | DQ80: 1 | DU80: 1003 | DV80: 100 м | DW80: 100 м | DX80: 100 | EE80: 60088531 | EF80: 40 | EG80: Монтаж оборудования | EH80: 0 | EJ80: 2 | EK80: 67 | EL80: ТСН-2001.4-8. Электротехнические установки | EM80: ТСН-2001.4-8-1 | EO80: Поправка: Гл.12.Прил.8.п.8. 5_12.00.01.11.003 | EQ80: 0 | ER80: 80.6 | ES80: 55.47 | ET80: 2.62 | EU80: 0.3 | EV80: 22.51 | EW80: 1.83 | EX80: 0 | EY80: 0 | FQ80: 0 | FR80: 0 | FS80: 0 | FX80: 97 | FY80: 51 | GD80: 1 | GF80: 1118340632 | GG80: 2 | GH80: 1 | GI80: 2 | GJ80: 0 | GK80: 0 | GL80: =ROUND(IF(AND(BH80=3,BI80=3,FS80<>0),P80,0),2) -> 0 | GM80: =ROUND(O80+X80+Y80,2)+GX80 -> 1888.98 | GN80: =IF(OR(BI80=0,BI80=1),GM80-GX80,0) -> 0 | GO80: =IF(BI80=2,GM80-GX80,0) -> 1888.98 | GP80: =IF(BI80=4,GM80-GX80,0) -> 0 | GR80: 0 | GS80: 3 | GT80: 0 | GV80: =ROUND((GT80),6) -> 0 | GW80: 1 | GX80: =ROUND(HC80*I80,2) -> 0 | HA80: 0 | HB80: 0 | HC80: =GV80*GW80 -> 0 | HS80: 0 | IK80: 0
A81: 17 | B81: 1 | E81: 8 | F81: КА-2 | G81: Кабель КПСВВнг(А)-LSLTx 1x2x1,0 | H81: км | I81: =ROUND(0.1*1.02,9) -> 0.102 | J81: 0 | K81: =ROUND(0.1*1.02,9) -> 0.102 | O81: =ROUND(CP81,2) -> 316.7 | P81: =ROUND((ROUND((AC81*AW81*I81),2)*BC81),2) -> 316.7 | Q81: =(ROUND((ROUND(((ET81)*AV81*I81),2)*BB81),2)+ROUND((ROUND(((AE81-(EU81))*AV81*I81),2)*BS81),2)) -> 0 | R81: =(ROUND((ROUND(((EU81)*AV81*I81),2)*BS81),2)+ROUND((ROUND(((AE81-(EU81))*AV81*I81),2)*BS81),2)) -> 0 | S81: =ROUND((ROUND((AF81*AV81*I81),2)*BA81),2) -> 0 | T81: =ROUND(CU81*I81,2) -> 0 | U81: =CV81*I81 -> 0 | V81: =CW81*I81 -> 0 | W81: =ROUND(CX81*I81,2) -> 0 | X81: =(ROUND((((S81+ROUND((ROUND(((EU81)*AV81*I81),2)*BS81),2))*AT81)/100),2)+ROUND(((ROUND((ROUND(((AE81-(EU81))*AV81*I81),2)*BS81),2)*AT81)/100),2)) -> 0 | Y81: =(ROUND((((S81+ROUND((ROUND(((EU81)*AV81*I81),2)*BS81),2))*AU81)/100),2)+ROUND(((ROUND((ROUND(((AE81-(EU81))*AV81*I81),2)*BS81),2)*AU81)/100),2)) -> 0 | AA81: 60257736 | AB81: =ROUND((AC81+AD81+AF81),6) -> 3104.91 | AC81: =ROUND((ES81),6) -> 3104.91 | AD81: =ROUND((((ET81)-(EU81))+AE81),6) -> 0 | AE81: =ROUND((EU81),6) -> 0 | AF81: =ROUND((EV81),6) -> 0 | AG81: =ROUND((AP81),6) -> 0 | AH81: =(EW81) -> 0 | AI81: =(EX81) -> 0 | AJ81: =(AS81) -> 0 | AK81: 3104.91 | AL81: 3104.91 | AM81: 0 | AN81: 0 | AO81: 0 | AP81: 0 | AQ81: 0 | AR81: 0 | AS81: 0 | AT81: 0 | AU81: 0 | AV81: 1 | AW81: 1 | AZ81: 1 | BA81: 1 | BB81: 1 | BC81: 1 | BH81: 3 | BI81: 2 | BM81: 400002 | BN81: 0 | BP81: 0 | BQ81: 202 | BR81: 0 | BS81: 1 | BT81: 1 | BU81: 1 | BV81: 1 | BW81: 1 | BX81: 1 | BZ81: 0 | CA81: 0 | CE81: 1566 | CF81: 0 | CG81: 0 | CM81: 0 | CO81: 0 | CP81: =(P81+Q81+S81) -> 316.7 | CQ81: =ROUND((ROUND((AC81*AW81*1),2)*BC81),2) -> 3104.91 | CR81: =(ROUND((ROUND(((ET81)*AV81*1),2)*BB81),2)+ROUND((ROUND(((AE81-(EU81))*AV81*1),2)*BS81),2)) -> 0 | CS81: =(ROUND((ROUND(((EU81)*AV81*1),2)*BS81),2)+ROUND((ROUND(((AE81-(EU81))*AV81*1),2)*BS81),2)) -> 0 | CT81: =ROUND((ROUND((AF81*AV81*1),2)*BA81),2) -> 0 | CU81: =AG81 -> 0 | CV81: =(AH81*AV81) -> 0 | CW81: =AI81 -> 0 | CX81: =AJ81 -> 0 | CY81: =(ROUND((((S81+ROUND((ROUND(((EU81)*AV81*1),2)*BS81),2))*AT81)/100),2)+ROUND(((ROUND((ROUND(((AE81-(EU81))*AV81*1),2)*BS81),2)*AT81)/100),2)) -> 0 | CZ81: =(ROUND((((S81+ROUND((ROUND(((EU81)*AV81*1),2)*BS81),2))*AU81)/100),2)+ROUND(((ROUND((ROUND(((AE81-(EU81))*AV81*1),2)*BS81),2)*AU81)/100),2)) -> 0 | DN81: 0 | DO81: 0 | DP81: 1 | DQ81: 1 | DU81: 1003 | DV81: км | DW81: км | DX81: 1000 | EE81: 60088644 | EF81: 202 | EG81: Материалы | EH81: 0 | EJ81: 1 | EK81: 400002 | EL81: Материалы, изделия и конструкции | EM81: Материалы | EQ81: 0 | ER81: 0 | ES81: 3104.91 | ET81: 0 | EU81: 0 | EV81: 0 | EW81: 0 | EX81: 0 | EY81: 0 | FQ81: 0 | FR81: 0 | FS81: 0 | FX81: 0 | FY81: 0 | GA81: [36 090 / 1,2 / 9,88] + 2% Заг.скл | GD81: 1 | GF81: 411873728 | GG81: 2 | GH81: 4 | GI81: -2 | GJ81: 0 | GK81: 0 | GL81: =ROUND(IF(AND(BH81=3,BI81=3,FS81<>0),P81,0),2) -> 0 | GM81: =ROUND(O81+X81+Y81,2)+GX81 -> 316.7 | GN81: =IF(OR(BI81=0,BI81=1),GM81-GX81,0) -> 0 | GO81: =IF(BI81=2,GM81-GX81,0) -> 316.7 | GP81: =IF(BI81=4,GM81-GX81,0) -> 0 | GR81: 0 | GS81: 2 | GT81: 0 | GV81: =ROUND((GT81),6) -> 0 | GW81: 1 | GX81: =ROUND(HC81*I81,2) -> 0 | HA81: 0 | HB81: 0 | HC81: =GV81*GW81 -> 0 | HE81: 0 | HF81: 2 | HS81: 0 | IK81: 0
A82: 17 | B82: 1 | E82: 8 | F82: КА-2 | G82: Кабель КПСВВнг(А)-LSLTx 1x2x1,0 | H82: км | I82: =ROUND(0.1*1.02,9) -> 0.102 | J82: 0 | K82: =ROUND(0.1*1.02,9) -> 0.102 | O82: =ROUND(CP82,2) -> 3129 | P82: =ROUND((ROUND((AC82*AW82*I82),2)*BC82),2) -> 3129 | Q82: =(ROUND((ROUND(((ET82)*AV82*I82),2)*BB82),2)+ROUND((ROUND(((AE82-(EU82))*AV82*I82),2)*BS82),2)) -> 0 | R82: =(ROUND((ROUND(((EU82)*AV82*I82),2)*BS82),2)+ROUND((ROUND(((AE82-(EU82))*AV82*I82),2)*BS82),2)) -> 0 | S82: =ROUND((ROUND((AF82*AV82*I82),2)*BA82),2) -> 0 | T82: =ROUND(CU82*I82,2) -> 0 | U82: =CV82*I82 -> 0 | V82: =CW82*I82 -> 0 | W82: =ROUND(CX82*I82,2) -> 0 | X82: =(ROUND((((S82+ROUND((ROUND(((EU82)*AV82*I82),2)*BS82),2))*AT82)/100),2)+ROUND(((ROUND((ROUND(((AE82-(EU82))*AV82*I82),2)*BS82),2)*AT82)/100),2)) -> 0 | Y82: =(ROUND((((S82+ROUND((ROUND(((EU82)*AV82*I82),2)*BS82),2))*AU82)/100),2)+ROUND(((ROUND((ROUND(((AE82-(EU82))*AV82*I82),2)*BS82),2)*AU82)/100),2)) -> 0 | AA82: 60257733 | AB82: =ROUND((AC82+AD82+AF82),6) -> 3104.91 | AC82: =ROUND((ES82),6) -> 3104.91 | AD82: =ROUND((((ET82)-(EU82))+AE82),6) -> 0 | AE82: =ROUND((EU82),6) -> 0 | AF82: =ROUND((EV82),6) -> 0 | AG82: =ROUND((AP82),6) -> 0 | AH82: =(EW82) -> 0 | AI82: =(EX82) -> 0 | AJ82: =(AS82) -> 0 | AK82: 3104.91 | AL82: 3104.91 | AM82: 0 | AN82: 0 | AO82: 0 | AP82: 0 | AQ82: 0 | AR82: 0 | AS82: 0 | AT82: 0 | AU82: 0 | AV82: 1 | AW82: 1 | AZ82: 1 | BA82: 1 | BB82: 1 | BC82: 9.88 | BH82: 3 | BI82: 2 | BM82: 400002 | BN82: 0 | BP82: 0 | BQ82: 202 | BR82: 0 | BS82: 1 | BT82: 1 | BU82: 1 | BV82: 1 | BW82: 1 | BX82: 1 | BZ82: 0 | CA82: 0 | CE82: 1566 | CF82: 0 | CG82: 0 | CM82: 0 | CO82: 0 | CP82: =(P82+Q82+S82) -> 3129 | CQ82: =ROUND((ROUND((AC82*AW82*1),2)*BC82),2) -> 30676.51 | CR82: =(ROUND((ROUND(((ET82)*AV82*1),2)*BB82),2)+ROUND((ROUND(((AE82-(EU82))*AV82*1),2)*BS82),2)) -> 0 | CS82: =(ROUND((ROUND(((EU82)*AV82*1),2)*BS82),2)+ROUND((ROUND(((AE82-(EU82))*AV82*1),2)*BS82),2)) -> 0 | CT82: =ROUND((ROUND((AF82*AV82*1),2)*BA82),2) -> 0 | CU82: =AG82 -> 0 | CV82: =(AH82*AV82) -> 0 | CW82: =AI82 -> 0 | CX82: =AJ82 -> 0 | CY82: =(ROUND((((S82+ROUND((ROUND(((EU82)*AV82*1),2)*BS82),2))*AT82)/100),2)+ROUND(((ROUND((ROUND(((AE82-(EU82))*AV82*1),2)*BS82),2)*AT82)/100),2)) -> 0 | CZ82: =(ROUND((((S82+ROUND((ROUND(((EU82)*AV82*1),2)*BS82),2))*AU82)/100),2)+ROUND(((ROUND((ROUND(((AE82-(EU82))*AV82*1),2)*BS82),2)*AU82)/100),2)) -> 0 | DN82: 0 | DO82: 0 | DP82: 1 | DQ82: 1 | DU82: 1003 | DV82: км | DW82: км | DX82: 1000 | EE82: 60088644 | EF82: 202 | EG82: Материалы | EH82: 0 | EJ82: 1 | EK82: 400002 | EL82: Материалы, изделия и конструкции | EM82: Материалы | EQ82: 0 | ER82: 0 | ES82: 3104.91 | ET82: 0 | EU82: 0 | EV82: 0 | EW82: 0 | EX82: 0 | EY82: 0 | EZ82: 5 | FC82: 1 | FD82: 18 | FF82: 36090 | FQ82: 0 | FR82: 0 | FS82: 0 | FX82: 0 | FY82: 0 | GA82: [36 090 / 1,2 / 9,88] + 2% Заг.скл | GD82: 1 | GF82: 411873728 | GG82: 2 | GH82: 3 | GI82: 5 | GJ82: 0 | GK82: 0 | GL82: =ROUND(IF(AND(BH82=3,BI82=3,FS82<>0),P82,0),2) -> 0 | GM82: =ROUND(O82+X82+Y82,2)+GX82 -> 3129 | GN82: =IF(OR(BI82=0,BI82=1),GM82-GX82,0) -> 0 | GO82: =IF(BI82=2,GM82-GX82,0) -> 3129 | GP82: =IF(BI82=4,GM82-GX82,0) -> 0 | GR82: 1 | GS82: 1 | GT82: 0 | GV82: =ROUND((GT82),6) -> 0 | GW82: 1 | GX82: =ROUND(HC82*I82,2) -> 0 | HA82: 0 | HB82: 0 | HC82: =GV82*GW82 -> 0 | HE82: 0 | HF82: 2 | HS82: 0 | IK82: 0
A84: 51 | B84: =B67 -> 1 | C84: =A67 -> 4 | D84: =ROW(A67) -> 67 | F84: =IF(F67<>"",F67,"") | G84: =IF(G67<>"",G67,"") -> Кабельные изделия | H84: 0 | O84: =ROUND(AB84,2) -> 854.42 | P84: =ROUND(AC84,2) -> 681.21 | Q84: =ROUND(AD84,2) -> 21.87 | R84: =ROUND(AE84,2) -> 3.48 | S84: =ROUND(AF84,2) -> 151.34 | T84: =ROUND(AG84,2) -> 0 | U84: =AH84 -> 11.914337 | V84: =AI84 -> 0 | W84: =ROUND(AJ84,2) -> 0 | X84: =ROUND(AK84,2) -> 150.18 | Y84: =ROUND(AL84,2) -> 78.96 | AB84: =ROUND(SUMIF(AA71:AA82,"=60257736",O71:O82),2) -> 854.42 | AC84: =ROUND(SUMIF(AA71:AA82,"=60257736",P71:P82),2) -> 681.21 | AD84: =ROUND(SUMIF(AA71:AA82,"=60257736",Q71:Q82),2) -> 21.87 | AE84: =ROUND(SUMIF(AA71:AA82,"=60257736",R71:R82),2) -> 3.48 | AF84: =ROUND(SUMIF(AA71:AA82,"=60257736",S71:S82),2) -> 151.34 | AG84: =ROUND(SUMIF(AA71:AA82,"=60257736",T71:T82),2) -> 0 | AH84: =SUMIF(AA71:AA82,"=60257736",U71:U82) -> 11.914337 | AI84: =SUMIF(AA71:AA82,"=60257736",V71:V82) -> 0 | AJ84: =ROUND(SUMIF(AA71:AA82,"=60257736",W71:W82),2) -> 0 | AK84: =ROUND(SUMIF(AA71:AA82,"=60257736",X71:X82),2) -> 150.18 | AL84: =ROUND(SUMIF(AA71:AA82,"=60257736",Y71:Y82),2) -> 78.96 | AO84: =ROUND(BX84,2) -> 0 | AP84: =ROUND(BY84,2) -> 0 | AQ84: =ROUND(BZ84,2) -> 0 | AR84: =ROUND(CA84,2) -> 1083.56 | AS84: =ROUND(CB84,2) -> 0 | AT84: =ROUND(CC84,2) -> 1083.56 | AU84: =ROUND(CD84,2) -> 0 | AV84: =ROUND(CE84,2) -> 681.21 | ... BD84: =ROUND(CM84,2) -> 0 | BX84: =ROUND(SUMIF(AA71:AA82,"=60257736",FQ71:FQ82),2) -> 0 | BY84: =ROUND(SUMIF(AA71:AA82,"=60257736",FR71:FR82),2) -> 0 | BZ84: =ROUND(SUMIF(AA71:AA82,"=60257736",GL71:GL82),2) -> 0 | CA84: =ROUND(SUMIF(AA71:AA82,"=60257736",GM71:GM82),2) -> 1083.56 | CB84: =ROUND(SUMIF(AA71:AA82,"=60257736",GN71:GN82),2) -> 0 | CC84: =ROUND(SUMIF(AA71:AA82,"=60257736",GO71:GO82),2) -> 1083.56 | CD84: =ROUND(SUMIF(AA71:AA82,"=60257736",GP71:GP82),2) -> 0 | CE84: =AC84-BX84 -> 681.21 | CF84: =AC84-BY84 -> 681.21 | CG84: =BX84-BZ84 -> 0 | CH84: =AC84-BX84-BY84+BZ84 -> 681.21 | CI84: =BY84-BZ84 -> 0 | CJ84: =ROUND(SUMIF(AA71:AA82,"=60257736",GX71:GX82),2) -> 0 | CK84: =ROUND(SUMIF(AA71:AA82,"=60257736",GY71:GY82),2) -> 0 | CL84: =ROUND(SUMIF(AA71:AA82,"=60257736",GZ71:GZ82),2) -> 0 | CM84: =ROUND(SUMIF(AA71:AA82,"=60257736",HD71:HD82),2) -> 0 | DG84: =ROUND(DT84,2) -> 14236.99 | DH84: =ROUND(DU84,2) -> 5540.18 | DI84: =ROUND(DV84,2) -> 374.63 | DJ84: =ROUND(DW84,2) -> 191.37 | DK84: =ROUND(DX84,2) -> 8322.18 | DL84: =ROUND(DY84,2) -> 0 | DM84: =DZ84 -> 11.914337 | DN84: =EA84 -> 0 | DO84: =ROUND(EB84,2) -> 0 | DP84: =ROUND(EC84,2) -> 8258.15 | DQ84: =ROUND(ED84,2) -> 4341.92 | DT84: =ROUND(SUMIF(AA71:AA82,"=60257733",O71:O82),2) -> 14236.99 | DU84: =ROUND(SUMIF(AA71:AA82,"=60257733",P71:P82),2) -> 5540.18 | DV84: =ROUND(SUMIF(AA71:AA82,"=60257733",Q71:Q82),2) -> 374.63 | DW84: =ROUND(SUMIF(AA71:AA82,"=60257733",R71:R82),2) -> 191.37 | DX84: =ROUND(SUMIF(AA71:AA82,"=60257733",S71:S82),2) -> 8322.18 | DY84: =ROUND(SUMIF(AA71:AA82,"=60257733",T71:T82),2) -> 0 | DZ84: =SUMIF(AA71:AA82,"=60257733",U71:U82) -> 11.914337 | EA84: =SUMIF(AA71:AA82,"=60257733",V71:V82) -> 0 | EB84: =ROUND(SUMIF(AA71:AA82,"=60257733",W71:W82),2) -> 0 | EC84: =ROUND(SUMIF(AA71:AA82,"=60257733",X71:X82),2) -> 8258.15 | ED84: =ROUND(SUMIF(AA71:AA82,"=60257733",Y71:Y82),2) -> 4341.92 | EG84: =ROUND(FP84,2) -> 0 | EH84: =ROUND(FQ84,2) -> 0 | EI84: =ROUND(FR84,2) -> 0 | EJ84: =ROUND(FS84,2) -> 26837.06 | EK84: =ROUND(FT84,2) -> 0 | EL84: =ROUND(FU84,2) -> 26837.06 | EM84: =ROUND(FV84,2) -> 0 | EN84: =ROUND(FW84,2) -> 5540.18 | ... EV84: =ROUND(GE84,2) -> 0 | FP84: =ROUND(SUMIF(AA71:AA82,"=60257733",FQ71:FQ82),2) -> 0 | FQ84: =ROUND(SUMIF(AA71:AA82,"=60257733",FR71:FR82),2) -> 0 | FR84: =ROUND(SUMIF(AA71:AA82,"=60257733",GL71:GL82),2) -> 0 | FS84: =ROUND(SUMIF(AA71:AA82,"=60257733",GM71:GM82),2) -> 26837.06 | FT84: =ROUND(SUMIF(AA71:AA82,"=60257733",GN71:GN82),2) -> 0 | FU84: =ROUND(SUMIF(AA71:AA82,"=60257733",GO71:GO82),2) -> 26837.06 | FV84: =ROUND(SUMIF(AA71:AA82,"=60257733",GP71:GP82),2) -> 0 | FW84: =DU84-FP84 -> 5540.18 | FX84: =DU84-FQ84 -> 5540.18 | FY84: =FP84-FR84 -> 0 | FZ84: =DU84-FP84-FQ84+FR84 -> 5540.18 | GA84: =FQ84-FR84 -> 0 | GB84: =ROUND(SUMIF(AA71:AA82,"=60257733",GX71:GX82),2) -> 0 | GC84: =ROUND(SUMIF(AA71:AA82,"=60257733",GY71:GY82),2) -> 0 | GD84: =ROUND(SUMIF(AA71:AA82,"=60257733",GZ71:GZ82),2) -> 0 | GE84: =ROUND(SUMIF(AA71:AA82,"=60257733",HD71:HD82),2) -> 0 | GX84: 0
A86: 50 | B86: 0 | C86: 0 | D86: 1 | E86: 201 | F86: =ROUND(Source!O84,O86) -> 854.42 | G86: ПЗ | H86: Прямые затраты | K86: 201 | L86: 1 | M86: 3 | O86: 2 | P86: =ROUND(Source!DG84,O86) -> 14236.99 | W86: 854.42 | X86: 1 | Y86: 854.42 | Z86: 14236.99 | AA86: 1 | AB86: 14236.99
A87: 50 | B87: 0 | C87: 0 | D87: 1 | E87: 202 | F87: =ROUND(Source!P84,O87) -> 681.21 | G87: СтМатОб | H87: Стоимость материальных ресурсов (всего) | K87: 202 | L87: 2 | M87: 3 | O87: 2 | P87: =ROUND(Source!DH84,O87) -> 5540.18 | W87: 681.21 | X87: 1 | Y87: 681.21 | Z87: 5540.18 | AA87: 1 | AB87: 5540.18
A88: 50 | B88: 0 | C88: 0 | D88: 1 | E88: 222 | F88: =ROUND(Source!AO84,O88) -> 0 | G88: СтМатОбЗак | H88: Стоимость материалов и оборудования заказчика | K88: 222 | L88: 3 | M88: 3 | O88: 2 | P88: =ROUND(Source!EG84,O88) -> 0 | W88: 0 | X88: 1 | Y88: 0 | Z88: 0 | AA88: 1 | AB88: 0
A89: 50 | B89: 0 | C89: 0 | D89: 1 | E89: 225 | F89: =ROUND(Source!AV84,O89) -> 681.21 | G89: СтМатОбПод | H89: Стоимость материалов и оборудования подрядчика | K89: 225 | L89: 4 | M89: 3 | O89: 2 | P89: =ROUND(Source!EN84,O89) -> 5540.18 | W89: 681.21 | X89: 1 | Y89: 681.21 | Z89: 5540.18 | AA89: 1 | AB89: 5540.18
A90: 50 | B90: 0 | C90: 0 | D90: 1 | E90: 226 | F90: =ROUND(Source!AW84,O90) -> 681.21 | G90: СтМат | H90: Стоимость материалов (всего) | K90: 226 | L90: 5 | M90: 3 | O90: 2 | P90: =ROUND(Source!EO84,O90) -> 5540.18 | W90: 681.21 | X90: 1 | Y90: 681.21 | Z90: 5540.18 | AA90: 1 | AB90: 5540.18
A91: 50 | B91: 0 | C91: 0 | D91: 1 | E91: 227 | F91: =ROUND(Source!AX84,O91) -> 0 | G91: СтМатЗак | H91: Стоимость материалов заказчика | K91: 227 | L91: 6 | M91: 3 | O91: 2 | P91: =ROUND(Source!EP84,O91) -> 0 | W91: 0 | X91: 1 | Y91: 0 | Z91: 0 | AA91: 1 | AB91: 0
A92: 50 | B92: 0 | C92: 0 | D92: 1 | E92: 228 | F92: =ROUND(Source!AY84,O92) -> 681.21 | G92: СтМатПод | H92: Стоимость материалов подрядчика | K92: 228 | L92: 7 | M92: 3 | O92: 2 | P92: =ROUND(Source!EQ84,O92) -> 5540.18 | W92: 681.21 | X92: 1 | Y92: 681.21 | Z92: 5540.18 | AA92: 1 | AB92: 5540.18
A93: 50 | B93: 0 | C93: 0 | D93: 1 | E93: 216 | F93: =ROUND(Source!AP84,O93) -> 0 | G93: Оборуд | H93: Стоимость оборудования (всего) | K93: 216 | L93: 8 | M93: 3 | O93: 2 | P93: =ROUND(Source!EH84,O93) -> 0 | W93: 0 | X93: 1 | Y93: 0 | Z93: 0 | AA93: 1 | AB93: 0
A94: 50 | B94: 0 | C94: 0 | D94: 1 | E94: 223 | F94: =ROUND(Source!AQ84,O94) -> 0 | G94: ОборудЗак | H94: Стоимость оборудования заказчика | K94: 223 | L94: 9 | M94: 3 | O94: 2 | P94: =ROUND(Source!EI84,O94) -> 0 | W94: 0 | X94: 1 | Y94: 0 | Z94: 0 | AA94: 1 | AB94: 0
A95: 50 | B95: 0 | C95: 0 | D95: 1 | E95: 229 | F95: =ROUND(Source!AZ84,O95) -> 0 | G95: ОборудПод | H95: Стоимость оборудования подрядчика | K95: 229 | L95: 10 | M95: 3 | O95: 2 | P95: =ROUND(Source!ER84,O95) -> 0 | W95: 0 | X95: 1 | Y95: 0 | Z95: 0 | AA95: 1 | AB95: 0
A96: 50 | B96: 0 | C96: 0 | D96: 1 | E96: 203 | F96: =ROUND(Source!Q84,O96) -> 21.87 | G96: ЭММ | H96: Эксплуатация машин | K96: 203 | L96: 11 | M96: 3 | O96: 2 | P96: =ROUND(Source!DI84,O96) -> 374.63 | W96: 21.87 | X96: 1 | Y96: 21.87 | Z96: 374.63 | AA96: 1 | AB96: 374.63
A97: 50 | B97: 0 | C97: 0 | D97: 1 | E97: 231 | F97: =ROUND(Source!BB84,O97) -> 0 | G97: ЭММсНРиСП | H97: Эксплуатация машин по ТСН-2001.16 | K97: 231 | L97: 12 | M97: 3 | O97: 2 | P97: =ROUND(Source!ET84,O97) -> 0 | W97: 0 | X97: 1 | Y97: 0 | Z97: 0 | AA97: 1 | AB97: 0
A98: 50 | B98: 0 | C98: 0 | D98: 1 | E98: 204 | F98: =ROUND(Source!R84,O98) -> 3.48 | G98: ЗПМ | H98: ЗП машинистов | K98: 204 | L98: 13 | M98: 3 | O98: 2 | P98: =ROUND(Source!DJ84,O98) -> 191.37 | W98: 3.48 | X98: 1 | Y98: 3.48 | Z98: 191.37 | AA98: 1 | AB98: 191.37
A99: 50 | B99: 0 | C99: 0 | D99: 1 | E99: 205 | F99: =ROUND(Source!S84,O99) -> 151.34 | G99: ОЗП | H99: Основная ЗП рабочих | K99: 205 | L99: 14 | M99: 3 | O99: 2 | P99: =ROUND(Source!DK84,O99) -> 8322.18 | W99: 151.34 | X99: 1 | Y99: 151.34 | Z99: 8322.18 | AA99: 1 | AB99: 8322.18
A100: 50 | B100: 0 | C100: 0 | D100: 1 | E100: 232 | F100: =ROUND(Source!BC84,O100) -> 0 | G100: ОЗПсНРиСП | H100: Основная ЗП рабочих по ТСН-2001.16 | K100: 232 | L100: 15 | M100: 3 | O100: 2 | P100: =ROUND(Source!EU84,O100) -> 0 | W100: 0 | X100: 1 | Y100: 0 | Z100: 0 | AA100: 1 | AB100: 0
A101: 50 | B101: 0 | C101: 0 | D101: 1 | E101: 214 | F101: =ROUND(Source!AS84,O101) -> 0 | G101: Строит | H101: Строительные работы с НР и СП | K101: 214 | L101: 16 | M101: 3 | O101: 2 | P101: =ROUND(Source!EK84,O101) -> 0 | W101: 0 | X101: 1 | Y101: 0 | Z101: 0 | AA101: 1 | AB101: 0
A102: 50 | B102: 0 | C102: 0 | D102: 1 | E102: 215 | F102: =ROUND(Source!AT84,O102) -> 1083.56 | G102: Монтаж | H102: Монтажные работы с НР и СП | K102: 215 | L102: 17 | M102: 3 | O102: 2 | P102: =ROUND(Source!EL84,O102) -> 26837.06 | W102: 1083.56 | X102: 1 | Y102: 1083.56 | Z102: 26837.06 | AA102: 1 | AB102: 26837.06
A103: 50 | B103: 0 | C103: 0 | D103: 1 | E103: 217 | F103: =ROUND(Source!AU84,O103) -> 0 | G103: Прочие | H103: Прочие работы с НР и СП | K103: 217 | L103: 18 | M103: 3 | O103: 2 | P103: =ROUND(Source!EM84,O103) -> 0 | W103: 0 | X103: 1 | Y103: 0 | Z103: 0 | AA103: 1 | AB103: 0
A104: 50 | B104: 0 | C104: 0 | D104: 1 | E104: 230 | F104: =ROUND(Source!BA84,O104) -> 0 | G104: ПрочиеЗатр | H104: Прочие затраты по ТСН-2001.16 | K104: 230 | L104: 19 | M104: 3 | O104: 2 | P104: =ROUND(Source!ES84,O104) -> 0 | W104: 0 | X104: 1 | Y104: 0 | Z104: 0 | AA104: 1 | AB104: 0
A105: 50 | B105: 0 | C105: 0 | D105: 1 | E105: 206 | F105: =ROUND(Source!T84,O105) -> 0 | G105: ВозврМат | H105: Возврат материалов | K105: 206 | L105: 20 | M105: 3 | O105: 2 | P105: =ROUND(Source!DL84,O105) -> 0 | W105: 0 | X105: 1 | Y105: 0 | Z105: 0 | AA105: 1 | AB105: 0
A106: 50 | B106: 0 | C106: 0 | D106: 1 | E106: 207 | F106: =Source!U84 -> 11.914337 | G106: ТрудСтр | H106: Трудозатраты строителей | K106: 207 | L106: 21 | M106: 3 | O106: -1 | P106: =Source!DM84 -> 11.914337 | W106: 11.914336 | X106: 1 | Y106: 11.914336 | Z106: 11.914336 | AA106: 1 | AB106: 11.914336
A107: 50 | B107: 0 | C107: 0 | D107: 1 | E107: 208 | F107: =Source!V84 -> 0 | G107: ТрудМаш | H107: Трудозатраты машинистов | K107: 208 | L107: 22 | M107: 3 | O107: -1 | P107: =Source!DN84 -> 0 | W107: 0 | X107: 1 | Y107: 0 | Z107: 0 | AA107: 1 | AB107: 0
A108: 50 | B108: 0 | C108: 0 | D108: 1 | E108: 209 | F108: =ROUND(Source!W84,O108) -> 0 | G108: ТранспМат | H108: Транспорт материалов | K108: 209 | L108: 23 | M108: 3 | O108: 2 | P108: =ROUND(Source!DO84,O108) -> 0 | W108: 0 | X108: 1 | Y108: 0 | Z108: 0 | AA108: 1 | AB108: 0
A109: 50 | B109: 0 | C109: 0 | D109: 1 | E109: 233 | F109: =ROUND(Source!BD84,O109) -> 0 | G109: Перевозка | H109: Перевозка грузов | K109: 233 | L109: 24 | M109: 3 | O109: 2 | P109: =ROUND(Source!EV84,O109) -> 0 | W109: 0 | X109: 1 | Y109: 0 | Z109: 0 | AA109: 1 | AB109: 0
A110: 50 | B110: 0 | C110: 0 | D110: 1 | E110: 210 | F110: =ROUND(Source!X84,O110) -> 150.18 | G110: НР | H110: Накладные расходы | K110: 210 | L110: 25 | M110: 3 | O110: 2 | P110: =ROUND(Source!DP84,O110) -> 8258.15 | W110: 150.18 | X110: 1 | Y110: 150.18 | Z110: 8258.15 | AA110: 1 | AB110: 8258.15
A111: 50 | B111: 0 | C111: 0 | D111: 1 | E111: 211 | F111: =ROUND(Source!Y84,O111) -> 78.96 | G111: СмПриб | H111: Сметная прибыль | K111: 211 | L111: 26 | M111: 3 | O111: 2 | P111: =ROUND(Source!DQ84,O111) -> 4341.92 | W111: 78.96 | X111: 1 | Y111: 78.96 | Z111: 4341.92 | AA111: 1 | AB111: 4341.92
A112: 50 | B112: 0 | C112: 0 | D112: 1 | E112: 224 | F112: =ROUND(Source!AR84,O112) -> 1083.56 | G112: Всего | H112: Всего с НР и СП | K112: 224 | L112: 27 | M112: 3 | O112: 2 | P112: =ROUND(Source!EJ84,O112) -> 26837.06 | W112: 1083.56 | X112: 1 | Y112: 1083.56 | Z112: 26837.06 | AA112: 1 | AB112: 26837.06
A114: 51 | B114: =B20 -> 1 | C114: =A20 -> 3 | D114: =ROW(A20) -> 20 | F114: =IF(F20<>"",F20,"") -> 02-01-13 | G114: =IF(G20<>"",G20,"") -> Электрочасофикация | H114: 0 | O114: =ROUND(O37+O84+AB114,2) -> 12937.98 | P114: =ROUND(P37+P84+AC114,2) -> 12662.37 | Q114: =ROUND(Q37+Q84+AD114,2) -> 21.87 | R114: =ROUND(R37+R84+AE114,2) -> 3.48 | S114: =ROUND(S37+S84+AF114,2) -> 253.74 | T114: =ROUND(T37+T84+AG114,2) -> 0 | U114: =U37+U84+AH114 -> 19.976236 | V114: =V37+V84+AI114 -> 0 | W114: =ROUND(W37+W84+AJ114,2) -> 0 | X114: =ROUND(X37+X84+AK114,2) -> 242.34 | Y114: =ROUND(Y37+Y84+AL114,2) -> 126.07 | AO114: =ROUND(AO37+AO84+BX114,2) -> 0 | AP114: =ROUND(AP37+AP84+BY114,2) -> 11980.11 | AQ114: =ROUND(AQ37+AQ84+BZ114,2) -> 0 | AR114: =ROUND(AR37+AR84+CA114,2) -> 13306.39 | AS114: =ROUND(AS37+AS84+CB114,2) -> 0 | AT114: =ROUND(AT37+AT84+CC114,2) -> 1326.28 | AU114: =ROUND(AU37+AU84+CD114,2) -> 0 | AV114: =ROUND(AV37+AV84+CE114,2) -> 12662.37 | ... BD114: =ROUND(BD37+BD84+CM114,2) -> 0 | DG114: =ROUND(DG37+DG84+DT114,2) -> 108051.29 | DH114: =ROUND(DH37+DH84+DU114,2) -> 93723.51 | DI114: =ROUND(DI37+DI84+DV114,2) -> 374.63 | DJ114: =ROUND(DJ37+DJ84+DW114,2) -> 191.37 | DK114: =ROUND(DK37+DK84+DX114,2) -> 13953.15 | DL114: =ROUND(DL37+DL84+DY114,2) -> 0 | DM114: =DM37+DM84+DZ114 -> 19.976236 | DN114: =DN37+DN84+EA114 -> 0 | DO114: =ROUND(DO37+DO84+EB114,2) -> 0 | DP114: =ROUND(DP37+DP84+EC114,2) -> 13326.03 | DQ114: =ROUND(DQ37+DQ84+ED114,2) -> 6932.16 | EG114: =ROUND(EG37+EG84+FP114,2) -> 0 | EH114: =ROUND(EH37+EH84+FQ114,2) -> 88172.94 | EI114: =ROUND(EI37+EI84+FR114,2) -> 0 | EJ114: =ROUND(EJ37+EJ84+FS114,2) -> 128309.48 | EK114: =ROUND(EK37+EK84+FT114,2) -> 0 | EL114: =ROUND(EL37+EL84+FU114,2) -> 40136.54 | EM114: =ROUND(EM37+EM84+FV114,2) -> 0 | EN114: =ROUND(EN37+EN84+FW114,2) -> 93723.51 | ... EV114: =ROUND(EV37+EV84+GE114,2) -> 0 | GX114: 0
A116: 50 | B116: 0 | C116: 0 | D116: 1 | E116: 201 | F116: =ROUND(Source!O114,O116) -> 12937.98 | G116: ПЗ | H116: Прямые затраты | K116: 201 | L116: 1 | M116: 3 | O116: 2 | P116: =ROUND(Source!DG114,O116) -> 108051.29 | W116: 12937.98 | X116: 1 | Y116: 12937.98 | Z116: 108051.29 | AA116: 1 | AB116: 108051.29
A117: 50 | B117: 0 | C117: 0 | D117: 1 | E117: 202 | F117: =ROUND(Source!P114,O117) -> 12662.37 | G117: СтМатОб | H117: Стоимость материальных ресурсов (всего) | K117: 202 | L117: 2 | M117: 3 | O117: 2 | P117: =ROUND(Source!DH114,O117) -> 93723.51 | W117: 12662.37 | X117: 1 | Y117: 12662.37 | Z117: 93723.51 | AA117: 1 | AB117: 93723.51
A118: 50 | B118: 0 | C118: 0 | D118: 1 | E118: 222 | F118: =ROUND(Source!AO114,O118) -> 0 | G118: СтМатОбЗак | H118: Стоимость материалов и оборудования заказчика | K118: 222 | L118: 3 | M118: 3 | O118: 2 | P118: =ROUND(Source!EG114,O118) -> 0 | W118: 0 | X118: 1 | Y118: 0 | Z118: 0 | AA118: 1 | AB118: 0
A119: 50 | B119: 0 | C119: 0 | D119: 1 | E119: 225 | F119: =ROUND(Source!AV114,O119) -> 12662.37 | G119: СтМатОбПод | H119: Стоимость материалов и оборудования подрядчика | K119: 225 | L119: 4 | M119: 3 | O119: 2 | P119: =ROUND(Source!EN114,O119) -> 93723.51 | W119: 12662.37 | X119: 1 | Y119: 12662.37 | Z119: 93723.51 | AA119: 1 | AB119: 93723.51
A120: 50 | B120: 0 | C120: 0 | D120: 1 | E120: 226 | F120: =ROUND(Source!AW114,O120) -> 682.26 | G120: СтМат | H120: Стоимость материалов (всего) | K120: 226 | L120: 5 | M120: 3 | O120: 2 | P120: =ROUND(Source!EO114,O120) -> 5550.57 | W120: 682.26 | X120: 1 | Y120: 682.26 | Z120: 5550.57 | AA120: 1 | AB120: 5550.57
A121: 50 | B121: 0 | C121: 0 | D121: 1 | E121: 227 | F121: =ROUND(Source!AX114,O121) -> 0 | G121: СтМатЗак | H121: Стоимость материалов заказчика | K121: 227 | L121: 6 | M121: 3 | O121: 2 | P121: =ROUND(Source!EP114,O121) -> 0 | W121: 0 | X121: 1 | Y121: 0 | Z121: 0 | AA121: 1 | AB121: 0
A122: 50 | B122: 0 | C122: 0 | D122: 1 | E122: 228 | F122: =ROUND(Source!AY114,O122) -> 682.26 | G122: СтМатПод | H122: Стоимость материалов подрядчика | K122: 228 | L122: 7 | M122: 3 | O122: 2 | P122: =ROUND(Source!EQ114,O122) -> 5550.57 | W122: 682.26 | X122: 1 | Y122: 682.26 | Z122: 5550.57 | AA122: 1 | AB122: 5550.57
A123: 50 | B123: 0 | C123: 0 | D123: 1 | E123: 216 | F123: =ROUND(Source!AP114,O123) -> 11980.11 | G123: Оборуд | H123: Стоимость оборудования (всего) | K123: 216 | L123: 8 | M123: 3 | O123: 2 | P123: =ROUND(Source!EH114,O123) -> 88172.94 | W123: 11980.11 | X123: 1 | Y123: 11980.11 | Z123: 88172.94 | AA123: 1 | AB123: 88172.94
A124: 50 | B124: 0 | C124: 0 | D124: 1 | E124: 223 | F124: =ROUND(Source!AQ114,O124) -> 0 | G124: ОборудЗак | H124: Стоимость оборудования заказчика | K124: 223 | L124: 9 | M124: 3 | O124: 2 | P124: =ROUND(Source!EI114,O124) -> 0 | W124: 0 | X124: 1 | Y124: 0 | Z124: 0 | AA124: 1 | AB124: 0
A125: 50 | B125: 0 | C125: 0 | D125: 1 | E125: 229 | F125: =ROUND(Source!AZ114,O125) -> 11980.11 | G125: ОборудПод | H125: Стоимость оборудования подрядчика | K125: 229 | L125: 10 | M125: 3 | O125: 2 | P125: =ROUND(Source!ER114,O125) -> 88172.94 | W125: 11980.11 | X125: 1 | Y125: 11980.11 | Z125: 88172.94 | AA125: 1 | AB125: 88172.94
A126: 50 | B126: 0 | C126: 0 | D126: 1 | E126: 203 | F126: =ROUND(Source!Q114,O126) -> 21.87 | G126: ЭММ | H126: Эксплуатация машин | K126: 203 | L126: 11 | M126: 3 | O126: 2 | P126: =ROUND(Source!DI114,O126) -> 374.63 | W126: 21.87 | X126: 1 | Y126: 21.87 | Z126: 374.63 | AA126: 1 | AB126: 374.63
A127: 50 | B127: 0 | C127: 0 | D127: 1 | E127: 231 | F127: =ROUND(Source!BB114,O127) -> 0 | G127: ЭММсНРиСП | H127: Эксплуатация машин по ТСН-2001.16 | K127: 231 | L127: 12 | M127: 3 | O127: 2 | P127: =ROUND(Source!ET114,O127) -> 0 | W127: 0 | X127: 1 | Y127: 0 | Z127: 0 | AA127: 1 | AB127: 0
...

Sheet SourceObSm
A1: 0 | B1: Smeta.RU (495) 974-1589 | D1: _OBSM_ | F1: 0 | G1: 0 | H1: 0 | I1: Smeta.RU | K1: 1 | L1: 74563 | M1: 10 | N1: 12 | O1: 0 | P1: 0 | Q1: 3
A4: 1 | B4: 1 | C4: -1 | G4: Капитальный ремонт здания Государственного бюджетного общеобразовательного учреждения города Москвы "Школа №236" по адресу: г. Москва, улица Клязьминская, дом 7, корпус 4 | EC4: 0
A12: 1 | B12: 51 | C12: 0 | E12: 0 | G12: 02-01-13 Электрочасофикация | I12: 0 | J12: 2024-00272-01-0-ИОС5.6 | K12: 0 | L12: 0 | M12: 4098 | O12: 0 | P12: 0 | Q12: 0 | R12: 0 | S12: 0 | T12: 1 | V12: 0 | AB12: Соколова И.Н. | BB12: 0 | BH12: Сметные нормы списания | BI12: Коды ОКП для ТСН-2001 МГЭ Дополнение 80 | BJ12: 1 | BK12: 1 | BL12: 0 | BM12: 0 | BN12: 1 | BO12: 0 | BP12: 6 | BQ12: 2 | BR12: 1 | BS12: 1 | BT12: 0 | BU12: 0 | BV12: 0 | BW12: 0 | BX12: 0 | BZ12: Типовой расчет для ТСН-2001 МГЭ, Дополнение 80, строительство (1) | CA12: Территориальные сметные нормативы для Москвы ТСН-2001 (МГЭ), дополнение 80 | CB12: Территориальные сметные нормативы для Москвы ТСН-2001 (МГЭ), дополнение 80 | CC12: Территориальные сметные нормативы для Москвы ТСН-2001 (МГЭ), дополнение 80 | CD12: Территориальные сметные нормативы для Москвы ТСН-2001 (МГЭ), дополнение 80 | CE12: Поправки для ТСН-2001 от 28.11.2025 г. доп.79 | CF12: 0 | CG12: 0 | CH12: 8200 | CK12: 80 | CQ12: Территориальные сметные нормативы для Москвы (ТСН-2001) | CR12: ТЕР | CS12: 41660 | CT12: 1 | CU12: 80 | CY12: 0 | EC12: 0
A14: 22 | B14: 1 | C14: 0 | D14: 60257733 | E14: 60257736 | F14: 2 | G14: 1
A16: 3 | B16: 1 | C16: 02-01-13 | D16: Электрочасофикация | E16: =ROUND((Source!P131)/1000,2) -> 0 | F16: =ROUND((Source!P132)/1000,2) -> 40.14 | G16: =ROUND((Source!P123)/1000,2) -> 88.17 | H16: =ROUND((Source!P133)/1000+(Source!P134)/1000,2) -> 0 | I16: =E16+F16+G16+H16 -> 128.31 | J16: =ROUND((Source!P129+Source!P128)/1000,2) -> 14.14 | K16: 201.77 | L16: 0 | M16: 0 | N16: =I16+L16+M16 -> 128.31 | T16: =ROUND((Source!F131)/1000,2) -> 0 | U16: =ROUND((Source!F132)/1000,2) -> 1.33 | V16: =ROUND((Source!F123)/1000,2) -> 11.98 | W16: =ROUND((Source!F133)/1000+(Source!F134)/1000,2) -> 0 | X16: =T16+U16+V16+W16 -> 13.31 | Y16: =ROUND((Source!F129+Source!F128)/1000,2) -> 0.26 | Z16: 25.6 | AA16: 0 | AB16: 0 | AC16: =X16+AA16+AB16 -> 13.31 | AI16: 2 | AJ16: -1 | AN16: 0 | AT16: 108051.29 | AU16: 93723.51 | AV16: 0 | AW16: 88172.94 | AX16: 0 | AY16: 374.63 | AZ16: 191.37 | BA16: 13953.15 | BB16: 0 | BC16: 40136.54 | BD16: 0 | BE16: 0 | BF16: 19.976236 | BG16: 0 | BH16: 0 | BI16: 13326.03 | BJ16: 6932.16 | BK16: 128309.48 | BR16: 12937.98 | BS16: 12662.37 | BT16: 0 | BU16: 11980.11 | BV16: 0 | BW16: 21.87 | BX16: 3.48 | BY16: 253.74 | BZ16: 0 | CA16: 1326.28 | CB16: 0 | CC16: 0 | CD16: 19.976236 | CE16: 0 | CF16: 0 | CG16: 242.34 | CH16: 126.07 | CI16: 13306.39
A18: 51 | E18: 0 | F18: 40.14 | G18: 88.17 | H18: 0 | I18: 128.31 | J18: 14.14 | K18: 201.77 | L18: 0 | M18: 0 | N18: 128.31 | T18: 0 | U18: 1.33 | V18: 11.98 | W18: 0 | X18: 13.31 | Y18: 0.26 | Z18: 25.6 | AA18: 0 | AB18: 0 | AC18: 13.31
A20: 50 | B20: 0 | C20: 0 | D20: 1 | E20: 201 | F20: 108051.29 | G20: ПЗ | H20: Прямые затраты | K20: 201 | L20: 1 | M20: 3 | O20: 2 | P20: 12937.98
A21: 50 | B21: 0 | C21: 0 | D21: 1 | E21: 202 | F21: 93723.51 | G21: СтМатОб | H21: Стоимость материальных ресурсов (всего) | K21: 202 | L21: 2 | M21: 3 | O21: 2 | P21: 12662.37
A22: 50 | B22: 0 | C22: 0 | D22: 1 | E22: 222 | F22: 0 | G22: СтМатОбЗак | H22: Стоимость материалов и оборудования заказчика | K22: 222 | L22: 3 | M22: 3 | O22: 2 | P22: 0
A23: 50 | B23: 0 | C23: 0 | D23: 1 | E23: 225 | F23: 93723.51 | G23: СтМатОбПод | H23: Стоимость материалов и оборудования подрядчика | K23: 225 | L23: 4 | M23: 3 | O23: 2 | P23: 12662.37
A24: 50 | B24: 0 | C24: 0 | D24: 1 | E24: 226 | F24: 5550.57 | G24: СтМат | H24: Стоимость материалов (всего) | K24: 226 | L24: 5 | M24: 3 | O24: 2 | P24: 682.26
A25: 50 | B25: 0 | C25: 0 | D25: 1 | E25: 227 | F25: 0 | G25: СтМатЗак | H25: Стоимость материалов заказчика | K25: 227 | L25: 6 | M25: 3 | O25: 2 | P25: 0
A26: 50 | B26: 0 | C26: 0 | D26: 1 | E26: 228 | F26: 5550.57 | G26: СтМатПод | H26: Стоимость материалов подрядчика | K26: 228 | L26: 7 | M26: 3 | O26: 2 | P26: 682.26
A27: 50 | B27: 0 | C27: 0 | D27: 1 | E27: 216 | F27: 88172.94 | G27: Оборуд | H27: Стоимость оборудования (всего) | K27: 216 | L27: 8 | M27: 3 | O27: 2 | P27: 11980.11
A28: 50 | B28: 0 | C28: 0 | D28: 1 | E28: 223 | F28: 0 | G28: ОборудЗак | H28: Стоимость оборудования заказчика | K28: 223 | L28: 9 | M28: 3 | O28: 2 | P28: 0
A29: 50 | B29: 0 | C29: 0 | D29: 1 | E29: 229 | F29: 88172.94 | G29: ОборудПод | H29: Стоимость оборудования подрядчика | K29: 229 | L29: 10 | M29: 3 | O29: 2 | P29: 11980.11
A30: 50 | B30: 0 | C30: 0 | D30: 1 | E30: 203 | F30: 374.63 | G30: ЭММ | H30: Эксплуатация машин | K30: 203 | L30: 11 | M30: 3 | O30: 2 | P30: 21.87
A31: 50 | B31: 0 | C31: 0 | D31: 1 | E31: 231 | F31: 0 | G31: ЭММсНРиСП | H31: Эксплуатация машин по ТСН-2001.16 | K31: 231 | L31: 12 | M31: 3 | O31: 2 | P31: 0
... A46: 50 | B46: 0 | C46: 0 | D46: 1 | E46: 224 | F46: 128309.48 | G46: Всего | H46: Всего с НР и СП | K46: 224 | L46: 27 | M46: 3 | O46: 2 | P46: 13306.39
A48: -1
A51: 75 | B51: Текущий уровень цен | C51: 2025 | D51: 3 | E51: 0 | G51: 0 | H51: 1 | I51: 1 | J51: 3 | K51: 0 | L51: 0 | M51: 1 | N51: 60257733 | O51: 1
A52: 1 | B52: Сборник индексов | C52: Коэффициенты к ТСН-2001 МГЭ Дополнение 80, строительство | D52: 2025 | E52: 9 | F52: 1 | G52: 1 | H52: 0 | I52: 2 | J52: 1 | K52: 9.88 | L52: 7.66 | M52: 1 | N52: 1 | O52: 9.88 | P52: 7.66 | Q52: 1 | AA52: 217/80 | AN52: 60257734
A53: 1 | B53: Сборник индексов | C53: Коэффициенты к ТСН-2001.13-2 Дополнение 46 | D53: 2025 | E53: 7 | F53: 1 | G53: 1 | H53: 0 | I53: 2 | J53: 1 | K53: 1 | L53: 1 | M53: 1 | N53: 1 | O53: 1 | P53: 1 | Q53: 1 | AA53: 62/46 | AN53: 60257735
A54: 75 | B54: Базовый уровень цен | C54: 2000 | D54: 0 | E54: 1 | F54: 0 | G54: 0 | H54: 1 | I54: 1 | J54: 3 | K54: 0 | L54: 0 | M54: 0 | N54: 60257736 | O54: 2
A55: 1 | B55: Сборник индексов | C55: Коэффициенты к ТСН-2001 МГЭ Дополнение 80, строительство | D55: 2000 | E55: 1 | F55: 1 | G55: 1 | H55: 0 | I55: 2 | J55: 1 | K55: 1 | L55: 1 | M55: 1 | N55: 1 | O55: 1 | P55: 1 | Q55: 1 | AA55: 0 | AN55: 60257737

Sheet SmtRes
A1: =ROW(Source!A28) -> 28 | B1: 60257736 | C1: 60257850 | D1: 58999254 | E1: 1080 | F1: 1 | G1: 1080 | H1: 1 | I1: 9999990008 | K1: Трудозатраты рабочих | L1: 1191 | N1: 1013 | O1: чел.-ч. | P1: чел.-ч. | Q1: 1 | W1: 0 | X1: 476480486 | Y1: =(AT1*1.1) -> 3.3 | AA1: 0 | AB1: 0 | AC1: 0 | AD1: 0 | AE1: 0 | AF1: 0 | AG1: 0 | AH1: 0 | AI1: 1 | AJ1: 1 | AK1: 1 | AL1: 1 | AM1: -2 | AN1: 0 | AO1: 1 | AP1: 1 | AQ1: 0 | AR1: 0 | AT1: 3 | AU1: *1,1 | AV1: 1 | AW1: 2 | AX1: 60257963 | AY1: 1 | AZ1: 0 | BA1: 1 | BB1: 0 | BC1: 0 | BD1: 0 | BE1: 0 | BF1: 0 | BG1: 0 | BH1: 0 | BI1: 0 | BJ1: 0 | BK1: 0 | BL1: 0 | BM1: 0 | BN1: 0 | BO1: 0 | BP1: 0 | BQ1: 0 | BR1: 0 | BS1: 0 | BT1: 0 | BU1: 0 | BV1: 0 | BW1: 0 | CU1: =ROUND(AT1*Source!I28*AH1*AL1,2) -> 0 | CV1: =ROUND(Y1*Source!I28,9) -> 3.3 | CW1: 0 | CX1: =ROUND(Y1*Source!I28,9) -> 3.3 | CY1: =AD1 -> 0 | CZ1: =AH1 -> 0 | DA1: =AL1 -> 1 | DB1: =ROUND((ROUND(AT1*CZ1,2)*1.1),6) -> 0 | DC1: =ROUND((ROUND(AT1*AG1,2)*1.1),6) -> 0 | DF1: =ROUND(ROUND(AE1,2)*CX1,2) -> 0 | DG1: =ROUND(ROUND(AF1,2)*CX1,2) -> 0 | DH1: =ROUND(ROUND(AG1,2)*CX1,2) -> 0 | DI1: =ROUND(ROUND(AH1,2)*CX1,2) -> 0 | DJ1: =DI1 -> 0 | DK1: 0 | DM1: 0 | DO1: 0
A2: =ROW(Source!A29) -> 29 | B2: 60257733 | C2: 60257850 | D2: 58999254 | E2: 1080 | F2: 1 | G2: 1080 | H2: 1 | I2: 9999990008 | K2: Трудозатраты рабочих | L2: 1191 | N2: 1013 | O2: чел.-ч. | P2: чел.-ч. | Q2: 1 | W2: 0 | X2: 476480486 | Y2: =(AT2*1.1) -> 3.3 | AA2: 0 | AB2: 0 | AC2: 0 | AD2: 0 | AE2: 0 | AF2: 0 | AG2: 0 | AH2: 0 | AI2: 1 | AJ2: 1 | AK2: 1 | AL2: 1 | AM2: 5 | AN2: 0 | AO2: 1 | AP2: 1 | AQ2: 0 | AR2: 0 | AT2: 3 | AU2: *1,1 | AV2: 1 | AW2: 2 | AX2: 60257963 | AY2: 1 | AZ2: 0 | BA2: 2 | BB2: 0 | BC2: 0 | BD2: 0 | BE2: 0 | BF2: 0 | BG2: 0 | BH2: 0 | BI2: 0 | BJ2: 0 | BK2: 0 | BL2: 0 | BM2: 0 | BN2: 0 | BO2: 0 | BP2: 0 | BQ2: 0 | BR2: 0 | BS2: 0 | BT2: 0 | BU2: 0 | BV2: 0 | BW2: 0 | CU2: =ROUND(AT2*Source!I29*AH2*AL2,2) -> 0 | CV2: =ROUND(Y2*Source!I29,9) -> 3.3 | CW2: 0 | CX2: =ROUND(Y2*Source!I29,9) -> 3.3 | CY2: =AD2 -> 0 | CZ2: =AH2 -> 0 | DA2: =AL2 -> 1 | DB2: =ROUND((ROUND(AT2*CZ2,2)*1.1),6) -> 0 | DC2: =ROUND((ROUND(AT2*AG2,2)*1.1),6) -> 0 | DF2: =ROUND(ROUND(AE2,2)*CX2,2) -> 0 | DG2: =ROUND(ROUND(AF2,2)*CX2,2) -> 0 | DH2: =ROUND(ROUND(AG2,2)*CX2,2) -> 0 | DI2: =ROUND(ROUND(AH2,2)*CX2,2) -> 0 | DJ2: =DI2 -> 0 | DK2: 0 | DM2: 0 | DO2: 0
A3: =ROW(Source!A32) -> 32 | B3: 60257736 | C3: 60257854 | D3: 58999254 | E3: 1080 | F3: 1 | G3: 1080 | H3: 1 | I3: 9999990008 | K3: Трудозатраты рабочих | L3: 1191 | N3: 1013 | O3: чел.-ч. | P3: чел.-ч. | Q3: 1 | W3: 0 | X3: 476480486 | Y3: =(AT3*1.1) -> 2.2 | AA3: 0 | AB3: 0 | AC3: 0 | AD3: 0 | AE3: 0 | AF3: 0 | AG3: 0 | AH3: 0 | AI3: 1 | AJ3: 1 | AK3: 1 | AL3: 1 | AM3: -2 | AN3: 0 | AO3: 1 | AP3: 1 | AQ3: 0 | AR3: 0 | AT3: 2 | AU3: *1,1 | AV3: 1 | AW3: 2 | AX3: 60257964 | AY3: 1 | AZ3: 0 | BA3: 3 | BB3: 0 | BC3: 0 | BD3: 0 | BE3: 0 | BF3: 0 | BG3: 0 | BH3: 0 | BI3: 0 | BJ3: 0 | BK3: 0 | BL3: 0 | BM3: 0 | BN3: 0 | BO3: 0 | BP3: 0 | BQ3: 0 | BR3: 0 | BS3: 0 | BT3: 0 | BU3: 0 | BV3: 0 | BW3: 0 | CU3: =ROUND(AT3*Source!I32*AH3*AL3,2) -> 0 | CV3: =ROUND(Y3*Source!I32,9) -> 4.4 | CW3: 0 | CX3: =ROUND(Y3*Source!I32,9) -> 4.4 | CY3: =AD3 -> 0 | CZ3: =AH3 -> 0 | DA3: =AL3 -> 1 | DB3: =ROUND((ROUND(AT3*CZ3,2)*1.1),6) -> 0 | DC3: =ROUND((ROUND(AT3*AG3,2)*1.1),6) -> 0 | DF3: =ROUND(ROUND(AE3,2)*CX3,2) -> 0 | DG3: =ROUND(ROUND(AF3,2)*CX3,2) -> 0 | DH3: =ROUND(ROUND(AG3,2)*CX3,2) -> 0 | DI3: =ROUND(ROUND(AH3,2)*CX3,2) -> 0 | DJ3: =DI3 -> 0 | DK3: 0 | DM3: 0 | DO3: 0
A4: =ROW(Source!A33) -> 33 | B4: 60257733 | C4: 60257854 | D4: 58999254 | E4: 1080 | F4: 1 | G4: 1080 | H4: 1 | I4: 9999990008 | K4: Трудозатраты рабочих | L4: 1191 | N4: 1013 | O4: чел.-ч. | P4: чел.-ч. | Q4: 1 | W4: 0 | X4: 476480486 | Y4: =(AT4*1.1) -> 2.2 | AA4: 0 | AB4: 0 | AC4: 0 | AD4: 0 | AE4: 0 | AF4: 0 | AG4: 0 | AH4: 0 | AI4: 1 | AJ4: 1 | AK4: 1 | AL4: 1 | AM4: 5 | AN4: 0 | AO4: 1 | AP4: 1 | AQ4: 0 | AR4: 0 | AT4: 2 | AU4: *1,1 | AV4: 1 | AW4: 2 | AX4: 60257964 | AY4: 1 | AZ4: 0 | BA4: 4 | BB4: 0 | BC4: 0 | BD4: 0 | BE4: 0 | BF4: 0 | BG4: 0 | BH4: 0 | BI4: 0 | BJ4: 0 | BK4: 0 | BL4: 0 | BM4: 0 | BN4: 0 | BO4: 0 | BP4: 0 | BQ4: 0 | BR4: 0 | BS4: 0 | BT4: 0 | BU4: 0 | BV4: 0 | BW4: 0 | CU4: =ROUND(AT4*Source!I33*AH4*AL4,2) -> 0 | CV4: =ROUND(Y4*Source!I33,9) -> 4.4 | CW4: 0 | CX4: =ROUND(Y4*Source!I33,9) -> 4.4 | CY4: =AD4 -> 0 | CZ4: =AH4 -> 0 | DA4: =AL4 -> 1 | DB4: =ROUND((ROUND(AT4*CZ4,2)*1.1),6) -> 0 | DC4: =ROUND((ROUND(AT4*AG4,2)*1.1),6) -> 0 | DF4: =ROUND(ROUND(AE4,2)*CX4,2) -> 0 | DG4: =ROUND(ROUND(AF4,2)*CX4,2) -> 0 | DH4: =ROUND(ROUND(AG4,2)*CX4,2) -> 0 | DI4: =ROUND(ROUND(AH4,2)*CX4,2) -> 0 | DJ4: =DI4 -> 0 | DK4: 0 | DM4: 0 | DO4: 0
A5: =ROW(Source!A71) -> 71 | B5: 60257736 | C5: 60257914 | D5: 58999254 | E5: 1080 | F5: 1 | G5: 1080 | H5: 1 | I5: 9999990008 | K5: Трудозатраты рабочих | L5: 1191 | N5: 1013 | O5: чел.-ч. | P5: чел.-ч. | Q5: 1 | W5: 0 | X5: 476480486 | Y5: =(AT5*1.1) -> 15.807 | AA5: 0 | AB5: 0 | AC5: 0 | AD5: 0 | AE5: 0 | AF5: 0 | AG5: 0 | AH5: 0 | AI5: 1 | AJ5: 1 | AK5: 1 | AL5: 1 | AM5: -2 | AN5: 0 | AO5: 1 | AP5: 1 | AQ5: 0 | AR5: 0 | AT5: 14.37 | AU5: *1,1 | AV5: 1 | AW5: 2 | AX5: 60257965 | AY5: 1 | AZ5: 0 | BA5: 5 | BB5: 0 | BC5: 0 | BD5: 0 | BE5: 0 | BF5: 0 | BG5: 0 | BH5: 0 | BI5: 0 | BJ5: 0 | BK5: 0 | BL5: 0 | BM5: 0 | BN5: 0 | BO5: 0 | BP5: 0 | BQ5: 0 | BR5: 0 | BS5: 0 | BT5: 0 | BU5: 0 | BV5: 0 | BW5: 0 | CU5: =ROUND(AT5*Source!I71*AH5*AL5,2) -> 0 | CV5: =ROUND(Y5*Source!I71,9) -> 7.9035 | CW5: 0 | CX5: =ROUND(Y5*Source!I71,9) -> 7.9035 | CY5: =AD5 -> 0 | CZ5: =AH5 -> 0 | DA5: =AL5 -> 1 | DB5: =ROUND((ROUND(AT5*CZ5,2)*1.1),6) -> 0 | DC5: =ROUND((ROUND(AT5*AG5,2)*1.1),6) -> 0 | DF5: =ROUND(ROUND(AE5,2)*CX5,2) -> 0 | DG5: =ROUND(ROUND(AF5,2)*CX5,2) -> 0 | DH5: =ROUND(ROUND(AG5,2)*CX5,2) -> 0 | DI5: =ROUND(ROUND(AH5,2)*CX5,2) -> 0 | DJ5: =DI5 -> 0 | DK5: 0 | DM5: 0 | DO5: 0
A6: =ROW(Source!A71) -> 71 | B6: 60257736 | C6: 60257914 | D6: 59038829 | E6: 1 | F6: 1 | G6: 1080 | H6: 3 | I6: 1.1-1-16 | J6: ТСН-2001.1 Доп. 79, Р. 1, о. 1, поз. 16 | K6: Антипирен из нефелина | L6: 1348 | N6: 1009 | O6: т | P6: т | Q6: 1000 | W6: 0 | X6: -152177588 | Y6: =(AT6*1) -> 0 | AA6: 10315.31 | AB6: 0 | AC6: 0 | AD6: 0 | AE6: 10315.31 | AF6: 0 | AG6: 0 | AH6: 0 | AI6: 1 | AJ6: 1 | AK6: 1 | AL6: 1 | AM6: 0 | AN6: 0 | AO6: 0 | AP6: 1 | AQ6: 0 | AR6: 0 | AT6: 0 | AU6: *1 | AV6: 0 | AW6: 1 | AX6: -1 | AY6: 0 | AZ6: 0 | BB6: 0 | BC6: 0 | BD6: 0 | BE6: 0 | BF6: 0 | BG6: 0 | BH6: 0 | BI6: 0 | BJ6: 0 | BK6: 0 | BL6: 0 | BM6: 0 | BN6: 0 | BO6: 0 | BP6: 0 | BQ6: 0 | BR6: 0 | BS6: 0 | BT6: 0 | BU6: 0 | BV6: 0 | BW6: 0 | CV6: 0 | CW6: 0 | CX6: =ROUND(Y6*Source!I71,9) -> 0 | CY6: =AA6 -> 10315.31 | CZ6: =AE6 -> 10315.31 | DA6: =AI6 -> 1 | DB6: =ROUND((ROUND(AT6*CZ6,2)*1),6) -> 0 | DC6: =ROUND((ROUND(AT6*AG6,2)*1),6) -> 0 | DF6: =ROUND(ROUND(AE6,2)*CX6,2) -> 0 | DG6: =ROUND(ROUND(AF6,2)*CX6,2) -> 0 | DH6: =ROUND(ROUND(AG6,2)*CX6,2) -> 0 | DI6: =ROUND(ROUND(AH6,2)*CX6,2) -> 0 | DJ6: =DF6 -> 0 | DK6: 0 | DM6: 0 | DO6: 0
A7: =ROW(Source!A71) -> 71 | B7: 60257736 | C7: 60257914 | D7: 59052975 | E7: 1 | F7: 1 | G7: 1080 | H7: 3 | I7: 1.12-5-371 | J7: ТСН-2001.1 Доп. 67, Р. 12, о. 5, поз. 371 | K7: Трубы электротехнические, гофрированные, из ПВХ, негорючие, с зондом, наружный диаметр 16 мм | L7: 1301 | N7: 1003 | O7: м | P7: м | Q7: 1 | W7: 0 | X7: 1184991115 | Y7: =(AT7*1) -> 102 | AA7: 2.67 | AB7: 0 | AC7: 0 | AD7: 0 | AE7: 2.67 | AF7: 0 | AG7: 0 | AH7: 0 | AI7: 1 | AJ7: 1 | AK7: 1 | AL7: 1 | AM7: 0 | AN7: 0 | AO7: 0 | AP7: 1 | AQ7: 0 | AR7: 0 | AT7: 102 | AU7: *1 | AV7: 0 | AW7: 1 | AX7: -1 | AY7: 0 | AZ7: 0 | BB7: 0 | BC7: 0 | BD7: 0 | BE7: 0 | BF7: 0 | BG7: 0 | BH7: 0 | BI7: 0 | BJ7: 0 | BK7: 0 | BL7: 0 | BM7: 0 | BN7: 0 | BO7: 0 | BP7: 0 | BQ7: 0 | BR7: 0 | BS7: 0 | BT7: 0 | BU7: 0 | BV7: 0 | BW7: 0 | CV7: 0 | CW7: 0 | CX7: =ROUND(Y7*Source!I71,9) -> 51 | CY7: =AA7 -> 2.67 | CZ7: =AE7 -> 2.67 | DA7: =AI7 -> 1 | DB7: =ROUND((ROUND(AT7*CZ7,2)*1),6) -> 272.34 | DC7: =ROUND((ROUND(AT7*AG7,2)*1),6) -> 0 | DF7: =ROUND(ROUND(AE7,2)*CX7,2) -> 136.17 | DG7: =ROUND(ROUND(AF7,2)*CX7,2) -> 0 | DH7: =ROUND(ROUND(AG7,2)*CX7,2) -> 0 | DI7: =ROUND(ROUND(AH7,2)*CX7,2) -> 0 | DJ7: =DF7 -> 136.17 | DK7: 0 | DM7: 0 | DO7: 0
A8: =ROW(Source!A72) -> 72 | B8: 60257733 | C8: 60257914 | D8: 58999254 | E8: 1080 | F8: 1 | G8: 1080 | H8: 1 | I8: 9999990008 | K8: Трудозатраты рабочих | L8: 1191 | N8: 1013 | O8: чел.-ч. | P8: чел.-ч. | Q8: 1 | W8: 0 | X8: 476480486 | Y8: =(AT8*1.1) -> 15.807 | AA8: 0 | AB8: 0 | AC8: 0 | AD8: 0 | AE8: 0 | AF8: 0 | AG8: 0 | AH8: 0 | AI8: 1 | AJ8: 1 | AK8: 1 | AL8: 1 | AM8: 5 | AN8: 0 | AO8: 1 | AP8: 1 | AQ8: 0 | AR8: 0 | AT8: 14.37 | AU8: *1,1 | AV8: 1 | AW8: 2 | AX8: 60257965 | AY8: 1 | AZ8: 0 | BA8: 9 | BB8: 0 | BC8: 0 | BD8: 0 | BE8: 0 | BF8: 0 | BG8: 0 | BH8: 0 | BI8: 0 | BJ8: 0 | BK8: 0 | BL8: 0 | BM8: 0 | BN8: 0 | BO8: 0 | BP8: 0 | BQ8: 0 | BR8: 0 | BS8: 0 | BT8: 0 | BU8: 0 | BV8: 0 | BW8: 0 | CU8: =ROUND(AT8*Source!I72*AH8*AL8,2) -> 0 | CV8: =ROUND(Y8*Source!I72,9) -> 7.9035 | CW8: 0 | CX8: =ROUND(Y8*Source!I72,9) -> 7.9035 | CY8: =AD8 -> 0 | CZ8: =AH8 -> 0 | DA8: =AL8 -> 1 | DB8: =ROUND((ROUND(AT8*CZ8,2)*1.1),6) -> 0 | DC8: =ROUND((ROUND(AT8*AG8,2)*1.1),6) -> 0 | DF8: =ROUND(ROUND(AE8,2)*CX8,2) -> 0 | DG8: =ROUND(ROUND(AF8,2)*CX8,2) -> 0 | DH8: =ROUND(ROUND(AG8,2)*CX8,2) -> 0 | DI8: =ROUND(ROUND(AH8,2)*CX8,2) -> 0 | DJ8: =DI8 -> 0 | DK8: 0 | DM8: 0 | DO8: 0
A9: =ROW(Source!A72) -> 72 | B9: 60257733 | C9: 60257914 | D9: 59038829 | E9: 1 | F9: 1 | G9: 1080 | H9: 3 | I9: 1.1-1-16 | J9: ТСН-2001.1 Доп. 79, Р. 1, о. 1, поз. 16 | K9: Антипирен из нефелина | L9: 1348 | N9: 1009 | O9: т | P9: т | Q9: 1000 | W9: 0 | X9: -152177588 | Y9: =(AT9*1) -> 0 | AA9: 48275.65 | AB9: 0 | AC9: 0 | AD9: 0 | AE9: 10315.31 | AF9: 0 | AG9: 0 | AH9: 0 | AI9: 4.68 | AJ9: 1 | AK9: 1 | AL9: 1 | AM9: 0 | AN9: 0 | AO9: 0 | AP9: 1 | AQ9: 0 | AR9: 0 | AT9: 0 | AU9: *1 | AV9: 0 | AW9: 1 | AX9: -1 | AY9: 0 | AZ9: 0 | BB9: 0 | BC9: 0 | BD9: 0 | BE9: 0 | BF9: 0 | BG9: 0 | BH9: 0 | BI9: 0 | BJ9: 0 | BK9: 0 | BL9: 0 | BM9: 0 | BN9: 0 | BO9: 0 | BP9: 0 | BQ9: 0 | BR9: 0 | BS9: 0 | BT9: 0 | BU9: 0 | BV9: 0 | BW9: 0 | CV9: 0 | CW9: 0 | CX9: =ROUND(Y9*Source!I72,9) -> 0 | CY9: =AA9 -> 48275.65 | CZ9: =AE9 -> 10315.31 | DA9: =AI9 -> 4.68 | DB9: =ROUND((ROUND(AT9*CZ9,2)*1),6) -> 0 | DC9: =ROUND((ROUND(AT9*AG9,2)*1),6) -> 0 | DF9: =ROUND(ROUND(AE9*AI9,2)*CX9,2) -> 0 | DG9: =ROUND(ROUND(AF9,2)*CX9,2) -> 0 | DH9: =ROUND(ROUND(AG9,2)*CX9,2) -> 0 | DI9: =ROUND(ROUND(AH9,2)*CX9,2) -> 0 | DJ9: =DF9 -> 0 | DK9: 0 | DM9: 0 | DO9: 0
A10: =ROW(Source!A72) -> 72 | B10: 60257733 | C10: 60257914 | D10: 59052975 | E10: 1 | F10: 1 | G10: 1080 | H10: 3 | I10: 1.12-5-371 | J10: ТСН-2001.1 Доп. 67, Р. 12, о. 5, поз. 371 | K10: Трубы электротехнические, гофрированные, из ПВХ, негорючие, с зондом, наружный диаметр 16 мм | L10: 1301 | N10: 1003 | O10: м | P10: м | Q10: 1 | W10: 0 | X10: 1184991115 | Y10: =(AT10*1) -> 102 | AA10: 10.23 | AB10: 0 | AC10: 0 | AD10: 0 | AE10: 2.67 | AF10: 0 | AG10: 0 | AH10: 0 | AI10: 3.83 | AJ10: 1 | AK10: 1 | AL10: 1 | AM10: 0 | AN10: 0 | AO10: 0 | AP10: 1 | AQ10: 0 | AR10: 0 | AT10: 102 | AU10: *1 | AV10: 0 | AW10: 1 | AX10: -1 | AY10: 0 | AZ10: 0 | BB10: 0 | BC10: 0 | BD10: 0 | BE10: 0 | BF10: 0 | BG10: 0 | BH10: 0 | BI10: 0 | BJ10: 0 | BK10: 0 | BL10: 0 | BM10: 0 | BN10: 0 | BO10: 0 | BP10: 0 | BQ10: 0 | BR10: 0 | BS10: 0 | BT10: 0 | BU10: 0 | BV10: 0 | BW10: 0 | CV10: 0 | CW10: 0 | CX10: =ROUND(Y10*Source!I72,9) -> 51 | CY10: =AA10 -> 10.23 | CZ10: =AE10 -> 2.67 | DA10: =AI10 -> 3.83 | DB10: =ROUND((ROUND(AT10*CZ10,2)*1),6) -> 272.34 | DC10: =ROUND((ROUND(AT10*AG10,2)*1),6) -> 0 | DF10: =ROUND(ROUND(AE10*AI10,2)*CX10,2) -> 521.73 | DG10: =ROUND(ROUND(AF10,2)*CX10,2) -> 0 | DH10: =ROUND(ROUND(AG10,2)*CX10,2) -> 0 | DI10: =ROUND(ROUND(AH10,2)*CX10,2) -> 0 | DJ10: =DF10 -> 521.73 | DK10: 0 | DM10: 0 | DO10: 0
A11: =ROW(Source!A77) -> 77 | B11: 60257736 | C11: 60257924 | D11: 58999254 | E11: 1080 | F11: 1 | G11: 1080 | H11: 1 | I11: 9999990008 | K11: Трудозатраты рабочих | L11: 1191 | N11: 1013 | O11: чел.-ч. | P11: чел.-ч. | Q11: 1 | W11: 0 | X11: 476480486 | Y11: =(AT11*1.1) -> 4.939 | AA11: 0 | AB11: 0 | AC11: 0 | AD11: 0 | AE11: 0 | AF11: 0 | AG11: 0 | AH11: 0 | AI11: 1 | AJ11: 1 | AK11: 1 | AL11: 1 | AM11: -2 | AN11: 0 | AO11: 1 | AP11: 1 | AQ11: 0 | AR11: 0 | AT11: 4.49 | AU11: *1,1 | AV11: 1 | AW11: 2 | AX11: 60257969 | AY11: 1 | AZ11: 0 | BA11: 13 | BB11: 0 | BC11: 0 | BD11: 0 | BE11: 0 | BF11: 0 | BG11: 0 | BH11: 0 | BI11: 0 | BJ11: 0 | BK11: 0 | BL11: 0 | BM11: 0 | BN11: 0 | BO11: 0 | BP11: 0 | BQ11: 0 | BR11: 0 | BS11: 0 | BT11: 0 | BU11: 0 | BV11: 0 | BW11: 0 | CU11: =ROUND(AT11*Source!I77*AH11*AL11,2) -> 0 | CV11: =ROUND(Y11*Source!I77,9) -> 2.4695 | CW11: 0 | CX11: =ROUND(Y11*Source!I77,9) -> 2.4695 | CY11: =AD11 -> 0 | CZ11: =AH11 -> 0 | DA11: =AL11 -> 1 | DB11: =ROUND((ROUND(AT11*CZ11,2)*1.1),6) -> 0 | DC11: =ROUND((ROUND(AT11*AG11,2)*1.1),6) -> 0 | DF11: =ROUND(ROUND(AE11,2)*CX11,2) -> 0 | DG11: =ROUND(ROUND(AF11,2)*CX11,2) -> 0 | DH11: =ROUND(ROUND(AG11,2)*CX11,2) -> 0 | DI11: =ROUND(ROUND(AH11,2)*CX11,2) -> 0 | DJ11: =DI11 -> 0 | DK11: 0 | DM11: 0 | DO11: 0
A12: =ROW(Source!A77) -> 77 | B12: 60257736 | C12: 60257924 | D12: 59070669 | E12: 1 | F12: 1 | G12: 1080 | H12: 2 | I12: 2.1-18-7 | J12: ТСН-2001.2. Доп. 68. п.1-18-7 (183001) | K12: Автомобили грузовые бортовые, грузоподъемность до 5 т | L12: 1368 | N12: 1011 | O12: маш.-ч | P12: маш.-ч | Q12: 1 | W12: 0 | X12: -1985943078 | Y12: =(AT12*1.1) -> 0.011 | AA12: 0 | AB12: 87.01 | AC12: 13.21 | AD12: 0 | AE12: 0 | AF12: 83.1 | AG12: 12.62 | AH12: 0 | AI12: 1 | AJ12: 1 | AK12: 1 | AL12: 1 | AM12: -2 | AN12: 0 | AO12: 1 | AP12: 1 | AQ12: 0 | AR12: 0 | AT12: 0.01 | AU12: *1,1 | AV12: 0 | AW12: 2 | AX12: 60257970 | AY12: 1 | AZ12: 0 | BA12: 14 | BB12: 0 | BC12: 0 | BD12: 0 | BE12: 0 | BF12: 0 | BG12: 0 | BH12: 0 | BI12: 0 | BJ12: 0 | BK12: 0 | BL12: 0 | BM12: 0 | BN12: 0 | BO12: 0 | BP12: 0 | BQ12: 0 | BR12: 0 | BS12: 0 | BT12: 0 | BU12: 0 | BV12: 0 | BW12: 0 | CV12: 0 | CW12: =ROUND(Y12*Source!I77*DO12,9) -> 0.06941 | CX12: =ROUND(Y12*Source!I77,9) -> 0.0055 | CY12: =AB12 -> 87.01 | CZ12: =AF12 -> 83.1 | DA12: =AJ12 -> 1 | DB12: =ROUND((ROUND(AT12*CZ12,2)*1.1),6) -> 0.913 | DC12: =ROUND((ROUND(AT12*AG12,2)*1.1),6) -> 0.143 | DF12: =ROUND(ROUND(AE12,2)*CX12,2) -> 0 | DG12: =ROUND(ROUND(AF12,2)*CX12,2) -> 0.46 | DH12: =ROUND(ROUND(AG12,2)*CX12,2) -> 0.07 | DI12: =ROUND(ROUND(AH12,2)*CX12,2) -> 0 | DJ12: =DG12 -> 0.46 | DK12: 0 | DL12: 9999990009 | DM12: 0 | DN12: чел.-ч. | DO12: 12.62
A13: =ROW(Source!A77) -> 77 | B13: 60257736 | C13: 60257924 | D13: 59069905 | E13: 1 | F13: 1 | G13: 1080 | H13: 2 | I13: 2.1-3-38 | J13: ТСН-2001.2. Доп. 68. п.1-3-38 (032009) | K13: Краны на автомобильном ходу, грузоподъемность до 16 т | L13: 1368 | N13: 1011 | O13: маш.-ч | P13: маш.-ч | Q13: 1 | W13: 0 | X13: 1087580389 | Y13: =(AT13*1.1) -> 0.011 | AA13: 0 | AB13: 187.59 | AC13: 17.73 | AD13: 0 | AE13: 0 | AF13: 179.17 | AG13: 16.93 | AH13: 0 | AI13: 1 | AJ13: 1 | AK13: 1 | AL13: 1 | AM13: -2 | AN13: 0 | AO13: 1 | AP13: 1 | AQ13: 0 | AR13: 0 | AT13: 0.01 | AU13: *1,1 | AV13: 0 | AW13: 2 | AX13: 60257971 | AY13: 1 | AZ13: 0 | BA13: 15 | BB13: 0 | BC13: 0 | BD13: 0 | BE13: 0 | BF13: 0 | BG13: 0 | BH13: 0 | BI13: 0 | BJ13: 0 | BK13: 0 | BL13: 0 | BM13: 0 | BN13: 0 | BO13: 0 | BP13: 0 | BQ13: 0 | BR13: 0 | BS13: 0 | BT13: 0 | BU13: 0 | BV13: 0 | BW13: 0 | CV13: 0 | CW13: =ROUND(Y13*Source!I77*DO13,9) -> 0.093115 | CX13: =ROUND(Y13*Source!I77,9) -> 0.0055 | CY13: =AB13 -> 187.59 | CZ13: =AF13 -> 179.17 | DA13: =AJ13 -> 1 | DB13: =ROUND((ROUND(AT13*CZ13,2)*1.1),6) -> 1.969 | DC13: =ROUND((ROUND(AT13*AG13,2)*1.1),6) -> 0.187 | DF13: =ROUND(ROUND(AE13,2)*CX13,2) -> 0 | DG13: =ROUND(ROUND(AF13,2)*CX13,2) -> 0.99 | DH13: =ROUND(ROUND(AG13,2)*CX13,2) -> 0.09 | DI13: =ROUND(ROUND(AH13,2)*CX13,2) -> 0 | DJ13: =DG13 -> 0.99 | DK13: 0 | DL13: 9999990009 | DM13: 0 | DN13: чел.-ч. | DO13: 16.93
A14: =ROW(Source!A77) -> 77 | B14: 60257736 | C14: 60257924 | D14: 59039702 | E14: 1 | F14: 1 | G14: 1080 | H14: 3 | I14: 1.1-1-1257 | J14: ТСН-2001.1 Доп. 79, Р. 1, о. 1, поз. 1257 | K14: Тальк молотый | L14: 1346 | N14: 1009 | O14: кг | P14: кг | Q14: 1 | W14: 0 | X14: 1770006655 | Y14: =(AT14*1) -> 0.43 | AA14: 1.38 | AB14: 0 | AC14: 0 | AD14: 0 | AE14: 1.38 | AF14: 0 | AG14: 0 | AH14: 0 | AI14: 1 | AJ14: 1 | AK14: 1 | AL14: 1 | AM14: -2 | AN14: 0 | AO14: 1 | AP14: 1 | AQ14: 0 | AR14: 0 | AT14: 0.43 | AU14: *1 | AV14: 0 | AW14: 2 | AX14: 60257972 | AY14: 1 | AZ14: 0 | BA14: 16 | BB14: 0 | BC14: 0 | BD14: 0 | BE14: 0 | BF14: 0 | BG14: 0 | BH14: 0 | BI14: 0 | BJ14: 0 | BK14: 0 | BL14: 0 | BM14: 0 | BN14: 0 | BO14: 0 | BP14: 0 | BQ14: 0 | BR14: 0 | BS14: 0 | BT14: 0 | BU14: 0 | BV14: 0 | BW14: 0 | CV14: 0 | CW14: 0 | CX14: =ROUND(Y14*Source!I77,9) -> 0.215 | CY14: =AA14 -> 1.38 | CZ14: =AE14 -> 1.38 | DA14: =AI14 -> 1 | DB14: =ROUND((ROUND(AT14*CZ14,2)*1),6) -> 0.59 | DC14: =ROUND((ROUND(AT14*AG14,2)*1),6) -> 0 | DF14: =ROUND(ROUND(AE14,2)*CX14,2) -> 0.3 | DG14: =ROUND(ROUND(AF14,2)*CX14,2) -> 0 | DH14: =ROUND(ROUND(AG14,2)*CX14,2) -> 0 | DI14: =ROUND(ROUND(AH14,2)*CX14,2) -> 0 | DJ14: =DF14 -> 0.3 | DK14: 0 | DM14: 0 | DO14: 0
A15: =ROW(Source!A77) -> 77 | B15: 60257736 | C15: 60257924 | D15: 59040093 | E15: 1 | F15: 1 | G15: 1080 | H15: 3 | I15: 1.1-1-1723 | J15: ТСН-2001.1 Доп. 79, Р. 1, о. 1, поз. 1723 | K15: Лента изоляционная, прорезиненная, односторонняя | L15: 1346 | N15: 1009 | O15: кг | P15: кг | Q15: 1 | W15: 0 | X15: -878159893 | Y15: =(AT15*1) -> 0.16 | AA15: 159.06 | AB15: 0 | AC15: 0 | AD15: 0 | AE15: 159.06 | AF15: 0 | AG15: 0 | AH15: 0 | AI15: 1 | AJ15: 1 | AK15: 1 | AL15: 1 | AM15: -2 | AN15: 0 | AO15: 1 | AP15: 1 | AQ15: 0 | AR15: 0 | AT15: 0.16 | AU15: *1 | AV15: 0 | AW15: 2 | AX15: 60257973 | AY15: 1 | AZ15: 0 | BA15: 17 | BB15: 0 | BC15: 0 | BD15: 0 | BE15: 0 | BF15: 0 | BG15: 0 | BH15: 0 | BI15: 0 | BJ15: 0 | BK15: 0 | BL15: 0 | BM15: 0 | BN15: 0 | BO15: 0 | BP15: 0 | BQ15: 0 | BR15: 0 | BS15: 0 | BT15: 0 | BU15: 0 | BV15: 0 | BW15: 0 | CV15: 0 | CW15: 0 | CX15: =ROUND(Y15*Source!I77,9) -> 0.08 | CY15: =AA15 -> 159.06 | CZ15: =AE15 -> 159.06 | DA15: =AI15 -> 1 | DB15: =ROUND((ROUND(AT15*CZ15,2)*1),6) -> 25.45 | DC15: =ROUND((ROUND(AT15*AG15,2)*1),6) -> 0 | DF15: =ROUND(ROUND(AE15,2)*CX15,2) -> 12.72 | DG15: =ROUND(ROUND(AF15,2)*CX15,2) -> 0 | DH15: =ROUND(ROUND(AG15,2)*CX15,2) -> 0 | DI15: =ROUND(ROUND(AH15,2)*CX15,2) -> 0 | DJ15: =DF15 -> 12.72 | DK15: 0 | DM15: 0 | DO15: 0
A16: =ROW(Source!A77) -> 77 | B16: 60257736 | C16: 60257924 | D16: 59063036 | E16: 1 | F16: 1 | G16: 1080 | H16: 3 | I16: 1.21-5-1543 | J16: ТСН-2001.1 Доп. 65, Р. 21, о. 5, поз. 1543 | K16: Гильзы кабельные медные типа ГМ 2,5 | L16: 1355 | N16: 1010 | O16: 100 шт. | P16: 100 шт. | Q16: 100 | W16: 0 | X16: -456781043 | Y16: =(AT16*1) -> 0.05 | AA16: 68.82 | AB16: 0 | AC16: 0 | AD16: 0 | AE16: 68.82 | AF16: 0 | AG16: 0 | AH16: 0 | AI16: 1 | AJ16: 1 | AK16: 1 | AL16: 1 | AM16: -2 | AN16: 0 | AO16: 1 | AP16: 1 | AQ16: 0 | AR16: 0 | AT16: 0.05 | AU16: *1 | AV16: 0 | AW16: 2 | AX16: 60257974 | AY16: 1 | AZ16: 0 | BA16: 18 | BB16: 0 | BC16: 0 | BD16: 0 | BE16: 0 | BF16: 0 | BG16: 0 | BH16: 0 | BI16: 0 | BJ16: 0 | BK16: 0 | BL16: 0 | BM16: 0 | BN16: 0 | BO16: 0 | BP16: 0 | BQ16: 0 | BR16: 0 | BS16: 0 | BT16: 0 | BU16: 0 | BV16: 0 | BW16: 0 | CV16: 0 | CW16: 0 | CX16: =ROUND(Y16*Source!I77,9) -> 0.025 | CY16: =AA16 -> 68.82 | CZ16: =AE16 -> 68.82 | DA16: =AI16 -> 1 | DB16: =ROUND((ROUND(AT16*CZ16,2)*1),6) -> 3.44 | DC16: =ROUND((ROUND(AT16*AG16,2)*1),6) -> 0 | DF16: =ROUND(ROUND(AE16,2)*CX16,2) -> 1.72 | DG16: =ROUND(ROUND(AF16,2)*CX16,2) -> 0 | DH16: =ROUND(ROUND(AG16,2)*CX16,2) -> 0 | DI16: =ROUND(ROUND(AH16,2)*CX16,2) -> 0 | DJ16: =DF16 -> 1.72 | DK16: 0 | DM16: 0 | DO16: 0
A17: =ROW(Source!A77) -> 77 | B17: 60257736 | C17: 60257924 | D17: 59063047 | E17: 1 | F17: 1 | G17: 1080 | H17: 3 | I17: 1.21-5-1554 | J17: ТСН-2001.1 Доп. 65, Р. 21, о. 5, поз. 1554 | K17: Втулка трубная, полипропиленовая, диаметр 17 мм | L17: 1356 | N17: 1010 | O17: 1000 шт. | P17: 1000 шт. | Q17: 1000 | W17: 0 | X17: 1726193810 | Y17: =(AT17*1) -> 0.0122 | AA17: 183.4 | AB17: 0 | AC17: 0 | AD17: 0 | AE17: 183.4 | AF17: 0 | AG17: 0 | AH17: 0 | AI17: 1 | AJ17: 1 | AK17: 1 | AL17: 1 | AM17: -2 | AN17: 0 | AO17: 1 | AP17: 1 | AQ17: 0 | AR17: 0 | AT17: 0.0122 | AU17: *1 | AV17: 0 | AW17: 2 | AX17: 60257975 | AY17: 1 | AZ17: 0 | BA17: 19 | BB17: 0 | BC17: 0 | BD17: 0 | BE17: 0 | BF17: 0 | BG17: 0 | BH17: 0 | BI17: 0 | BJ17: 0 | BK17: 0 | BL17: 0 | BM17: 0 | BN17: 0 | BO17: 0 | BP17: 0 | BQ17: 0 | BR17: 0 | BS17: 0 | BT17: 0 | BU17: 0 | BV17: 0 | BW17: 0 | CV17: 0 | CW17: 0 | CX17: =ROUND(Y17*Source!I77,9) -> 0.0061 | CY17: =AA17 -> 183.4 | CZ17: =AE17 -> 183.4 | DA17: =AI17 -> 1 | DB17: =ROUND((ROUND(AT17*CZ17,2)*1),6) -> 2.24 | DC17: =ROUND((ROUND(AT17*AG17,2)*1),6) -> 0 | DF17: =ROUND(ROUND(AE17,2)*CX17,2) -> 1.12 | DG17: =ROUND(ROUND(AF17,2)*CX17,2) -> 0 | DH17: =ROUND(ROUND(AG17,2)*CX17,2) -> 0 | DI17: =ROUND(ROUND(AH17,2)*CX17,2) -> 0 | DJ17: =DF17 -> 1.12 | DK17: 0 | DM17: 0 | DO17: 0
A18: =ROW(Source!A77) -> 77 | B18: 60257736 | C18: 60257924 | D18: 59062373 | E18: 1 | F18: 1 | G18: 1080 | H18: 3 | I18: 1.21-5-750 | J18: ТСН-2001.1 Доп. 73, Р. 21, о. 5, поз. 750 | K18: Сжим, типа У 739М для проводников магистральных сечением от 4 до 10 мм2 и ответвительных сечением от 1,5 до 2,5 мм2 | L18: 1354 | N18: 1010 | O18: шт. | P18: шт. | Q18: 1 | W18: 0 | X18: 145081611 | Y18: =(AT18*1) -> 3.1 | AA18: 6.94 | AB18: 0 | AC18: 0 | AD18: 0 | AE18: 6.94 | AF18: 0 | AG18: 0 | AH18: 0 | AI18: 1 | AJ18: 1 | AK18: 1 | AL18: 1 | AM18: -2 | AN18: 0 | AO18: 1 | AP18: 1 | AQ18: 0 | AR18: 0 | AT18: 3.1 | AU18: *1 | AV18: 0 | AW18: 2 | AX18: 60257976 | AY18: 1 | AZ18: 0 | BA18: 20 | BB18: 0 | BC18: 0 | BD18: 0 | BE18: 0 | BF18: 0 | BG18: 0 | BH18: 0 | BI18: 0 | BJ18: 0 | BK18: 0 | BL18: 0 | BM18: 0 | BN18: 0 | BO18: 0 | BP18: 0 | BQ18: 0 | BR18: 0 | BS18: 0 | BT18: 0 | BU18: 0 | BV18: 0 | BW18: 0 | CV18: 0 | CW18: 0 | CX18: =ROUND(Y18*Source!I77,9) -> 1.55 | CY18: =AA18 -> 6.94 | CZ18: =AE18 -> 6.94 | DA18: =AI18 -> 1 | DB18: =ROUND((ROUND(AT18*CZ18,2)*1),6) -> 21.51 | DC18: =ROUND((ROUND(AT18*AG18,2)*1),6) -> 0 | DF18: =ROUND(ROUND(AE18,2)*CX18,2) -> 10.76 | DG18: =ROUND(ROUND(AF18,2)*CX18,2) -> 0 | DH18: =ROUND(ROUND(AG18,2)*CX18,2) -> 0 | DI18: =ROUND(ROUND(AH18,2)*CX18,2) -> 0 | DJ18: =DF18 -> 10.76 | DK18: 0 | DM18: 0 | DO18: 0
A19: =ROW(Source!A77) -> 77 | B19: 60257736 | C19: 60257924 | D19: 59062380 | E19: 1 | F19: 1 | G19: 1080 | H19: 3 | I19: 1.21-5-757 | J19: ТСН-2001.1 Доп. 73, Р. 21, о. 5, поз. 757 | K19: Зажим соединительно-изолирующий, типа СИЗ-2 | L19: 1356 | N19: 1010 | O19: 1000 шт. | P19: 1000 шт. | Q19: 1000 | W19: 0 | X19: -1715273674 | Y19: =(AT19*1) -> 0.008 | AA19: 614.09 | AB19: 0 | AC19: 0 | AD19: 0 | AE19: 614.09 | AF19: 0 | AG19: 0 | AH19: 0 | AI19: 1 | AJ19: 1 | AK19: 1 | AL19: 1 | AM19: -2 | AN19: 0 | AO19: 1 | AP19: 1 | AQ19: 0 | AR19: 0 | AT19: 0.008 | AU19: *1 | AV19: 0 | AW19: 2 | AX19: 60257977 | AY19: 1 | AZ19: 0 | BA19: 21 | BB19: 0 | BC19: 0 | BD19: 0 | BE19: 0 | BF19: 0 | BG19: 0 | BH19: 0 | BI19: 0 | BJ19: 0 | BK19: 0 | BL19: 0 | BM19: 0 | BN19: 0 | BO19: 0 | BP19: 0 | BQ19: 0 | BR19: 0 | BS19: 0 | BT19: 0 | BU19: 0 | BV19: 0 | BW19: 0 | CV19: 0 | CW19: 0 | CX19: =ROUND(Y19*Source!I77,9) -> 0.004 | CY19: =AA19 -> 614.09 | CZ19: =AE19 -> 614.09 | DA19: =AI19 -> 1 | DB19: =ROUND((ROUND(AT19*CZ19,2)*1),6) -> 4.91 | DC19: =ROUND((ROUND(AT19*AG19,2)*1),6) -> 0 | DF19: =ROUND(ROUND(AE19,2)*CX19,2) -> 2.46 | DG19: =ROUND(ROUND(AF19,2)*CX19,2) -> 0 | DH19: =ROUND(ROUND(AG19,2)*CX19,2) -> 0 | DI19: =ROUND(ROUND(AH19,2)*CX19,2) -> 0 | DJ19: =DF19 -> 2.46 | DK19: 0 | DM19: 0 | DO19: 0
A20: =ROW(Source!A78) -> 78 | B20: 60257733 | C20: 60257924 | D20: 58999254 | E20: 1080 | F20: 1 | G20: 1080 | H20: 1 | I20: 9999990008 | K20: Трудозатраты рабочих | L20: 1191 | N20: 1013 | O20: чел.-ч. | P20: чел.-ч. | Q20: 1 | W20: 0 | X20: 476480486 | Y20: =(AT20*1.1) -> 4.939 | AA20: 0 | AB20: 0 | AC20: 0 | AD20: 0 | AE20: 0 | AF20: 0 | AG20: 0 | AH20: 0 | AI20: 1 | AJ20: 1 | AK20: 1 | AL20: 1 | AM20: 5 | AN20: 0 | AO20: 1 | AP20: 1 | AQ20: 0 | AR20: 0 | AT20: 4.49 | AU20: *1,1 | AV20: 1 | AW20: 2 | AX20: 60257969 | AY20: 1 | AZ20: 0 | BA20: 23 | BB20: 0 | BC20: 0 | BD20: 0 | BE20: 0 | BF20: 0 | BG20: 0 | BH20: 0 | BI20: 0 | BJ20: 0 | BK20: 0 | BL20: 0 | BM20: 0 | BN20: 0 | BO20: 0 | BP20: 0 | BQ20: 0 | BR20: 0 | BS20: 0 | BT20: 0 | BU20: 0 | BV20: 0 | BW20: 0 | CU20: =ROUND(AT20*Source!I78*AH20*AL20,2) -> 0 | CV20: =ROUND(Y20*Source!I78,9) -> 2.4695 | CW20: 0 | CX20: =ROUND(Y20*Source!I78,9) -> 2.4695 | CY20: =AD20 -> 0 | CZ20: =AH20 -> 0 | DA20: =AL20 -> 1 | DB20: =ROUND((ROUND(AT20*CZ20,2)*1.1),6) -> 0 | DC20: =ROUND((ROUND(AT20*AG20,2)*1.1),6) -> 0 | DF20: =ROUND(ROUND(AE20,2)*CX20,2) -> 0 | DG20: =ROUND(ROUND(AF20,2)*CX20,2) -> 0 | DH20: =ROUND(ROUND(AG20,2)*CX20,2) -> 0 | DI20: =ROUND(ROUND(AH20,2)*CX20,2) -> 0 | DJ20: =DI20 -> 0 | DK20: 0 | DM20: 0 | DO20: 0
A21: =ROW(Source!A78) -> 78 | B21: 60257733 | C21: 60257924 | D21: 59070669 | E21: 1 | F21: 1 | G21: 1080 | H21: 2 | I21: 2.1-18-7 | J21: ТСН-2001.2. Доп. 68. п.1-18-7 (183001) | K21: Автомобили грузовые бортовые, грузоподъемность до 5 т | L21: 1368 | N21: 1011 | O21: маш.-ч | P21: маш.-ч | Q21: 1 | W21: 0 | X21: -1985943078 | Y21: =(AT21*1.1) -> 0.011 | AA21: 0 | AB21: 1418.19 | AC21: 726.59 | AD21: 0 | AE21: 0 | AF21: 83.1 | AG21: 12.62 | AH21: 0 | AI21: 1 | AJ21: 16.3 | AK21: 54.99 | AL21: 1 | AM21: 2 | AN21: 0 | AO21: 1 | AP21: 1 | AQ21: 0 | AR21: 0 | AT21: 0.01 | AU21: *1,1 | AV21: 0 | AW21: 2 | AX21: 60257970 | AY21: 1 | AZ21: 0 | BA21: 24 | BB21: 0 | BC21: 0 | BD21: 0 | BE21: 0 | BF21: 0 | BG21: 0 | BH21: 0 | BI21: 0 | BJ21: 0 | BK21: 0 | BL21: 0 | BM21: 0 | BN21: 0 | BO21: 0 | BP21: 0 | BQ21: 0 | BR21: 0 | BS21: 0 | BT21: 0 | BU21: 0 | BV21: 0 | BW21: 0 | CV21: 0 | CW21: =ROUND(Y21*Source!I78*DO21,9) -> 0.06941 | CX21: =ROUND(Y21*Source!I78,9) -> 0.0055 | CY21: =AB21 -> 1418.19 | CZ21: =AF21 -> 83.1 | DA21: =AJ21 -> 16.3 | DB21: =ROUND((ROUND(AT21*CZ21,2)*1.1),6) -> 0.913 | DC21: =ROUND((ROUND(AT21*AG21,2)*1.1),6) -> 0.143 | DF21: =ROUND(ROUND(AE21,2)*CX21,2) -> 0 | DG21: =ROUND(ROUND(AF21*AJ21,2)*CX21,2) -> 7.45 | DH21: =ROUND(ROUND(AG21*AK21,2)*CX21,2) -> 3.82 | DI21: =ROUND(ROUND(AH21,2)*CX21,2) -> 0 | DJ21: =DG21 -> 7.45 | DK21: 0 | DL21: 9999990009 | DM21: 0 | DN21: чел.-ч. | DO21: 12.62
A22: =ROW(Source!A78) -> 78 | B22: 60257733 | C22: 60257924 | D22: 59069905 | E22: 1 | F22: 1 | G22: 1080 | H22: 2 | I22: 2.1-3-38 | J22: ТСН-2001.2. Доп. 68. п.1-3-38 (032009) | K22: Краны на автомобильном ходу, грузоподъемность до 16 т | L22: 1368 | N22: 1011 | O22: маш.-ч | P22: маш.-ч | Q22: 1 | W22: 0 | X22: 1087580389 | Y22: =(AT22*1.1) -> 0.011 | AA22: 0 | AB22: 2579.38 | AC22: 974.74 | AD22: 0 | AE22: 0 | AF22: 179.17 | AG22: 16.93 | AH22: 0 | AI22: 1 | AJ22: 13.75 | AK22: 54.99 | AL22: 1 | AM22: 2 | AN22: 0 | AO22: 1 | AP22: 1 | AQ22: 0 | AR22: 0 | AT22: 0.01 | AU22: *1,1 | AV22: 0 | AW22: 2 | AX22: 60257971 | AY22: 1 | AZ22: 0 | BA22: 25 | BB22: 0 | BC22: 0 | BD22: 0 | BE22: 0 | BF22: 0 | BG22: 0 | BH22: 0 | BI22: 0 | BJ22: 0 | BK22: 0 | BL22: 0 | BM22: 0 | BN22: 0 | BO22: 0 | BP22: 0 | BQ22: 0 | BR22: 0 | BS22: 0 | BT22: 0 | BU22: 0 | BV22: 0 | BW22: 0 | CV22: 0 | CW22: =ROUND(Y22*Source!I78*DO22,9) -> 0.093115 | CX22: =ROUND(Y22*Source!I78,9) -> 0.0055 | CY22: =AB22 -> 2579.38 | CZ22: =AF22 -> 179.17 | DA22: =AJ22 -> 13.75 | DB22: =ROUND((ROUND(AT22*CZ22,2)*1.1),6) -> 1.969 | DC22: =ROUND((ROUND(AT22*AG22,2)*1.1),6) -> 0.187 | DF22: =ROUND(ROUND(AE22,2)*CX22,2) -> 0 | DG22: =ROUND(ROUND(AF22*AJ22,2)*CX22,2) -> 13.55 | DH22: =ROUND(ROUND(AG22*AK22,2)*CX22,2) -> 5.12 | DI22: =ROUND(ROUND(AH22,2)*CX22,2) -> 0 | DJ22: =DG22 -> 13.55 | DK22: 0 | DL22: 9999990009 | DM22: 0 | DN22: чел.-ч. | DO22: 16.93
A23: =ROW(Source!A78) -> 78 | B23: 60257733 | C23: 60257924 | D23: 59039702 | E23: 1 | F23: 1 | G23: 1080 | H23: 3 | I23: 1.1-1-1257 | J23: ТСН-2001.1 Доп. 79, Р. 1, о. 1, поз. 1257 | K23: Тальк молотый | L23: 1346 | N23: 1009 | O23: кг | P23: кг | Q23: 1 | W23: 0 | X23: 1770006655 | Y23: =(AT23*1) -> 0.43 | AA23: 29.73 | AB23: 0 | AC23: 0 | AD23: 0 | AE23: 1.38 | AF23: 0 | AG23: 0 | AH23: 0 | AI23: 21.54 | AJ23: 1 | AK23: 1 | AL23: 1 | AM23: 2 | AN23: 0 | AO23: 1 | AP23: 1 | AQ23: 0 | AR23: 0 | AT23: 0.43 | AU23: *1 | AV23: 0 | AW23: 2 | AX23: 60257972 | AY23: 1 | AZ23: 0 | BA23: 26 | BB23: 0 | BC23: 0 | BD23: 0 | BE23: 0 | BF23: 0 | BG23: 0 | BH23: 0 | BI23: 0 | BJ23: 0 | BK23: 0 | BL23: 0 | BM23: 0 | BN23: 0 | BO23: 0 | BP23: 0 | BQ23: 0 | BR23: 0 | BS23: 0 | BT23: 0 | BU23: 0 | BV23: 0 | BW23: 0 | CV23: 0 | CW23: 0 | CX23: =ROUND(Y23*Source!I78,9) -> 0.215 | CY23: =AA23 -> 29.73 | CZ23: =AE23 -> 1.38 | DA23: =AI23 -> 21.54 | DB23: =ROUND((ROUND(AT23*CZ23,2)*1),6) -> 0.59 | DC23: =ROUND((ROUND(AT23*AG23,2)*1),6) -> 0 | DF23: =ROUND(ROUND(AE23*AI23,2)*CX23,2) -> 6.39 | DG23: =ROUND(ROUND(AF23,2)*CX23,2) -> 0 | DH23: =ROUND(ROUND(AG23,2)*CX23,2) -> 0 | DI23: =ROUND(ROUND(AH23,2)*CX23,2) -> 0 | DJ23: =DF23 -> 6.39 | DK23: 0 | DM23: 0 | DO23: 0
A24: =ROW(Source!A78) -> 78 | B24: 60257733 | C24: 60257924 | D24: 59040093 | E24: 1 | F24: 1 | G24: 1080 | H24: 3 | I24: 1.1-1-1723 | J24: ТСН-2001.1 Доп. 79, Р. 1, о. 1, поз. 1723 | K24: Лента изоляционная, прорезиненная, односторонняя | L24: 1346 | N24: 1009 | O24: кг | P24: кг | Q24: 1 | W24: 0 | X24: -878159893 | Y24: =(AT24*1) -> 0.16 | AA24: 286.31 | AB24: 0 | AC24: 0 | AD24: 0 | AE24: 159.06 | AF24: 0 | AG24: 0 | AH24: 0 | AI24: 1.8 | AJ24: 1 | AK24: 1 | AL24: 1 | AM24: 2 | AN24: 0 | AO24: 1 | AP24: 1 | AQ24: 0 | AR24: 0 | AT24: 0.16 | AU24: *1 | AV24: 0 | AW24: 2 | AX24: 60257973 | AY24: 1 | AZ24: 0 | BA24: 27 | BB24: 0 | BC24: 0 | BD24: 0 | BE24: 0 | BF24: 0 | BG24: 0 | BH24: 0 | BI24: 0 | BJ24: 0 | BK24: 0 | BL24: 0 | BM24: 0 | BN24: 0 | BO24: 0 | BP24: 0 | BQ24: 0 | BR24: 0 | BS24: 0 | BT24: 0 | BU24: 0 | BV24: 0 | BW24: 0 | CV24: 0 | CW24: 0 | CX24: =ROUND(Y24*Source!I78,9) -> 0.08 | CY24: =AA24 -> 286.31 | CZ24: =AE24 -> 159.06 | DA24: =AI24 -> 1.8 | DB24: =ROUND((ROUND(AT24*CZ24,2)*1),6) -> 25.45 | DC24: =ROUND((ROUND(AT24*AG24,2)*1),6) -> 0 | DF24: =ROUND(ROUND(AE24*AI24,2)*CX24,2) -> 22.9 | DG24: =ROUND(ROUND(AF24,2)*CX24,2) -> 0 | DH24: =ROUND(ROUND(AG24,2)*CX24,2) -> 0 | DI24: =ROUND(ROUND(AH24,2)*CX24,2) -> 0 | DJ24: =DF24 -> 22.9 | DK24: 0 | DM24: 0 | DO24: 0
A25: =ROW(Source!A78) -> 78 | B25: 60257733 | C25: 60257924 | D25: 59063036 | E25: 1 | F25: 1 | G25: 1080 | H25: 3 | I25: 1.21-5-1543 | J25: ТСН-2001.1 Доп. 65, Р. 21, о. 5, поз. 1543 | K25: Гильзы кабельные медные типа ГМ 2,5 | L25: 1355 | N25: 1010 | O25: 100 шт. | P25: 100 шт. | Q25: 100 | W25: 0 | X25: -456781043 | Y25: =(AT25*1) -> 0.05 | AA25: 1102.5 | AB25: 0 | AC25: 0 | AD25: 0 | AE25: 68.82 | AF25: 0 | AG25: 0 | AH25: 0 | AI25: 16.02 | AJ25: 1 | AK25: 1 | AL25: 1 | AM25: 2 | AN25: 0 | AO25: 1 | AP25: 1 | AQ25: 0 | AR25: 0 | AT25: 0.05 | AU25: *1 | AV25: 0 | AW25: 2 | AX25: 60257974 | AY25: 1 | AZ25: 0 | BA25: 28 | BB25: 0 | BC25: 0 | BD25: 0 | BE25: 0 | BF25: 0 | BG25: 0 | BH25: 0 | BI25: 0 | BJ25: 0 | BK25: 0 | BL25: 0 | BM25: 0 | BN25: 0 | BO25: 0 | BP25: 0 | BQ25: 0 | BR25: 0 | BS25: 0 | BT25: 0 | BU25: 0 | BV25: 0 | BW25: 0 | CV25: 0 | CW25: 0 | CX25: =ROUND(Y25*Source!I78,9) -> 0.025 | CY25: =AA25 -> 1102.5 | CZ25: =AE25 -> 68.82 | DA25: =AI25 -> 16.02 | DB25: =ROUND((ROUND(AT25*CZ25,2)*1),6) -> 3.44 | DC25: =ROUND((ROUND(AT25*AG25,2)*1),6) -> 0 | DF25: =ROUND(ROUND(AE25*AI25,2)*CX25,2) -> 27.56 | DG25: =ROUND(ROUND(AF25,2)*CX25,2) -> 0 | DH25: =ROUND(ROUND(AG25,2)*CX25,2) -> 0 | DI25: =ROUND(ROUND(AH25,2)*CX25,2) -> 0 | DJ25: =DF25 -> 27.56 | DK25: 0 | DM25: 0 | DO25: 0
A26: =ROW(Source!A78) -> 78 | B26: 60257733 | C26: 60257924 | D26: 59063047 | E26: 1 | F26: 1 | G26: 1080 | H26: 3 | I26: 1.21-5-1554 | J26: ТСН-2001.1 Доп. 65, Р. 21, о. 5, поз. 1554 | K26: Втулка трубная, полипропиленовая, диаметр 17 мм | L26: 1356 | N26: 1010 | O26: 1000 шт. | P26: 1000 шт. | Q26: 1000 | W26: 0 | X26: 1726193810 | Y26: =(AT26*1) -> 0.0122 | AA26: 1318.65 | AB26: 0 | AC26: 0 | AD26: 0 | AE26: 183.4 | AF26: 0 | AG26: 0 | AH26: 0 | AI26: 7.19 | AJ26: 1 | AK26: 1 | AL26: 1 | AM26: 2 | AN26: 0 | AO26: 1 | AP26: 1 | AQ26: 0 | AR26: 0 | AT26: 0.0122 | AU26: *1 | AV26: 0 | AW26: 2 | AX26: 60257975 | AY26: 1 | AZ26: 0 | BA26: 29 | BB26: 0 | BC26: 0 | BD26: 0 | BE26: 0 | BF26: 0 | BG26: 0 | BH26: 0 | BI26: 0 | BJ26: 0 | BK26: 0 | BL26: 0 | BM26: 0 | BN26: 0 | BO26: 0 | BP26: 0 | BQ26: 0 | BR26: 0 | BS26: 0 | BT26: 0 | BU26: 0 | BV26: 0 | BW26: 0 | CV26: 0 | CW26: 0 | CX26: =ROUND(Y26*Source!I78,9) -> 0.0061 | CY26: =AA26 -> 1318.65 | CZ26: =AE26 -> 183.4 | DA26: =AI26 -> 7.19 | DB26: =ROUND((ROUND(AT26*CZ26,2)*1),6) -> 2.24 | DC26: =ROUND((ROUND(AT26*AG26,2)*1),6) -> 0 | DF26: =ROUND(ROUND(AE26*AI26,2)*CX26,2) -> 8.04 | DG26: =ROUND(ROUND(AF26,2)*CX26,2) -> 0 | DH26: =ROUND(ROUND(AG26,2)*CX26,2) -> 0 | DI26: =ROUND(ROUND(AH26,2)*CX26,2) -> 0 | DJ26: =DF26 -> 8.04 | DK26: 0 | DM26: 0 | DO26: 0
A27: =ROW(Source!A78) -> 78 | B27: 60257733 | C27: 60257924 | D27: 59062373 | E27: 1 | F27: 1 | G27: 1080 | H27: 3 | I27: 1.21-5-750 | J27: ТСН-2001.1 Доп. 73, Р. 21, о. 5, поз. 750 | K27: Сжим, типа У 739М для проводников магистральных сечением от 4 до 10 мм2 и ответвительных сечением от 1,5 до 2,5 мм2 | L27: 1354 | N27: 1010 | O27: шт. | P27: шт. | Q27: 1 | W27: 0 | X27: 145081611 | Y27: =(AT27*1) -> 3.1 | AA27: 25.47 | AB27: 0 | AC27: 0 | AD27: 0 | AE27: 6.94 | AF27: 0 | AG27: 0 | AH27: 0 | AI27: 3.67 | AJ27: 1 | AK27: 1 | AL27: 1 | AM27: 2 | AN27: 0 | AO27: 1 | AP27: 1 | AQ27: 0 | AR27: 0 | AT27: 3.1 | AU27: *1 | AV27: 0 | AW27: 2 | AX27: 60257976 | AY27: 1 | AZ27: 0 | BA27: 30 | BB27: 0 | BC27: 0 | BD27: 0 | BE27: 0 | BF27: 0 | BG27: 0 | BH27: 0 | BI27: 0 | BJ27: 0 | BK27: 0 | BL27: 0 | BM27: 0 | BN27: 0 | BO27: 0 | BP27: 0 | BQ27: 0 | BR27: 0 | BS27: 0 | BT27: 0 | BU27: 0 | BV27: 0 | BW27: 0 | CV27: 0 | CW27: 0 | CX27: =ROUND(Y27*Source!I78,9) -> 1.55 | CY27: =AA27 -> 25.47 | CZ27: =AE27 -> 6.94 | DA27: =AI27 -> 3.67 | DB27: =ROUND((ROUND(AT27*CZ27,2)*1),6) -> 21.51 | DC27: =ROUND((ROUND(AT27*AG27,2)*1),6) -> 0 | DF27: =ROUND(ROUND(AE27*AI27,2)*CX27,2) -> 39.48 | DG27: =ROUND(ROUND(AF27,2)*CX27,2) -> 0 | DH27: =ROUND(ROUND(AG27,2)*CX27,2) -> 0 | DI27: =ROUND(ROUND(AH27,2)*CX27,2) -> 0 | DJ27: =DF27 -> 39.48 | DK27: 0 | DM27: 0 | DO27: 0
A28: =ROW(Source!A78) -> 78 | B28: 60257733 | C28: 60257924 | D28: 59062380 | E28: 1 | F28: 1 | G28: 1080 | H28: 3 | I28: 1.21-5-757 | J28: ТСН-2001.1 Доп. 73, Р. 21, о. 5, поз. 757 | K28: Зажим соединительно-изолирующий, типа СИЗ-2 | L28: 1356 | N28: 1010 | O28: 1000 шт. | P28: 1000 шт. | Q28: 1000 | W28: 0 | X28: -1715273674 | Y28: =(AT28*1) -> 0.008 | AA28: 786.04 | AB28: 0 | AC28: 0 | AD28: 0 | AE28: 614.09 | AF28: 0 | AG28: 0 | AH28: 0 | AI28: 1.28 | AJ28: 1 | AK28: 1 | AL28: 1 | AM28: 2 | AN28: 0 | AO28: 1 | AP28: 1 | AQ28: 0 | AR28: 0 | AT28: 0.008 | AU28: *1 | AV28: 0 | AW28: 2 | AX28: 60257977 | AY28: 1 | AZ28: 0 | BA28: 31 | BB28: 0 | BC28: 0 | BD28: 0 | BE28: 0 | BF28: 0 | BG28: 0 | BH28: 0 | BI28: 0 | BJ28: 0 | BK28: 0 | BL28: 0 | BM28: 0 | BN28: 0 | BO28: 0 | BP28: 0 | BQ28: 0 | BR28: 0 | BS28: 0 | BT28: 0 | BU28: 0 | BV28: 0 | BW28: 0 | CV28: 0 | CW28: 0 | CX28: =ROUND(Y28*Source!I78,9) -> 0.004 | CY28: =AA28 -> 786.04 | CZ28: =AE28 -> 614.09 | DA28: =AI28 -> 1.28 | DB28: =ROUND((ROUND(AT28*CZ28,2)*1),6) -> 4.91 | DC28: =ROUND((ROUND(AT28*AG28,2)*1),6) -> 0 | DF28: =ROUND(ROUND(AE28*AI28,2)*CX28,2) -> 3.14 | DG28: =ROUND(ROUND(AF28,2)*CX28,2) -> 0 | DH28: =ROUND(ROUND(AG28,2)*CX28,2) -> 0 | DI28: =ROUND(ROUND(AH28,2)*CX28,2) -> 0 | DJ28: =DF28 -> 3.14 | DK28: 0 | DM28: 0 | DO28: 0
A29: =ROW(Source!A79) -> 79 | B29: 60257736 | C29: 60257944 | D29: 58999254 | E29: 1080 | F29: 1 | G29: 1080 | H29: 1 | I29: 9999990008 | K29: Трудозатраты рабочих | L29: 1191 | N29: 1013 | O29: чел.-ч. | P29: чел.-ч. | Q29: 1 | W29: 0 | X29: 476480486 | Y29: =(AT29*1.1) -> 2.013 | AA29: 0 | AB29: 0 | AC29: 0 | AD29: 0 | AE29: 0 | AF29: 0 | AG29: 0 | AH29: 0 | AI29: 1 | AJ29: 1 | AK29: 1 | AL29: 1 | AM29: -2 | AN29: 0 | AO29: 1 | AP29: 1 | AQ29: 0 | AR29: 0 | AT29: 1.83 | AU29: *1,1 | AV29: 1 | AW29: 2 | AX29: 60257979 | AY29: 1 | AZ29: 0 | BA29: 33 | BB29: 0 | BC29: 0 | BD29: 0 | BE29: 0 | BF29: 0 | BG29: 0 | BH29: 0 | BI29: 0 | BJ29: 0 | BK29: 0 | BL29: 0 | BM29: 0 | BN29: 0 | BO29: 0 | BP29: 0 | BQ29: 0 | BR29: 0 | BS29: 0 | BT29: 0 | BU29: 0 | BV29: 0 | BW29: 0 | CU29: =ROUND(AT29*Source!I79*AH29*AL29,2) -> 0 | CV29: =ROUND(Y29*Source!I79,9) -> 1.0065 | CW29: 0 | CX29: =ROUND(Y29*Source!I79,9) -> 1.0065 | CY29: =AD29 -> 0 | CZ29: =AH29 -> 0 | DA29: =AL29 -> 1 | DB29: =ROUND((ROUND(AT29*CZ29,2)*1.1),6) -> 0 | DC29: =ROUND((ROUND(AT29*AG29,2)*1.1),6) -> 0 | DF29: =ROUND(ROUND(AE29,2)*CX29,2) -> 0 | DG29: =ROUND(ROUND(AF29,2)*CX29,2) -> 0 | DH29: =ROUND(ROUND(AG29,2)*CX29,2) -> 0 | DI29: =ROUND(ROUND(AH29,2)*CX29,2) -> 0 | DJ29: =DI29 -> 0 | DK29: 0 | DM29: 0 | DO29: 0
A30: =ROW(Source!A79) -> 79 | B30: 60257736 | C30: 60257944 | D30: 59070669 | E30: 1 | F30: 1 | G30: 1080 | H30: 2 | I30: 2.1-18-7 | J30: ТСН-2001.2. Доп. 68. п.1-18-7 (183001) | K30: Автомобили грузовые бортовые, грузоподъемность до 5 т | L30: 1368 | N30: 1011 | O30: маш.-ч | P30: маш.-ч | Q30: 1 | W30: 0 | X30: -1985943078 | Y30: =(AT30*1.1) -> 0.011 | AA30: 0 | AB30: 87.01 | AC30: 13.21 | AD30: 0 | AE30: 0 | AF30: 83.1 | AG30: 12.62 | AH30: 0 | AI30: 1 | AJ30: 1 | AK30: 1 | AL30: 1 | AM30: -2 | AN30: 0 | AO30: 1 | AP30: 1 | AQ30: 0 | AR30: 0 | AT30: 0.01 | AU30: *1,1 | AV30: 0 | AW30: 2 | AX30: 60257980 | AY30: 1 | AZ30: 0 | BA30: 34 | BB30: 0 | BC30: 0 | BD30: 0 | BE30: 0 | BF30: 0 | BG30: 0 | BH30: 0 | BI30: 0 | BJ30: 0 | BK30: 0 | BL30: 0 | BM30: 0 | BN30: 0 | BO30: 0 | BP30: 0 | BQ30: 0 | BR30: 0 | BS30: 0 | BT30: 0 | BU30: 0 | BV30: 0 | BW30: 0 | CV30: 0 | CW30: =ROUND(Y30*Source!I79*DO30,9) -> 0.06941 | CX30: =ROUND(Y30*Source!I79,9) -> 0.0055 | CY30: =AB30 -> 87.01 | CZ30: =AF30 -> 83.1 | DA30: =AJ30 -> 1 | DB30: =ROUND((ROUND(AT30*CZ30,2)*1.1),6) -> 0.913 | DC30: =ROUND((ROUND(AT30*AG30,2)*1.1),6) -> 0.143 | DF30: =ROUND(ROUND(AE30,2)*CX30,2) -> 0 | DG30: =ROUND(ROUND(AF30,2)*CX30,2) -> 0.46 | DH30: =ROUND(ROUND(AG30,2)*CX30,2) -> 0.07 | DI30: =ROUND(ROUND(AH30,2)*CX30,2) -> 0 | DJ30: =DG30 -> 0.46 | DK30: 0 | DL30: 9999990009 | DM30: 0 | DN30: чел.-ч. | DO30: 12.62
A31: =ROW(Source!A79) -> 79 | B31: 60257736 | C31: 60257944 | D31: 59069905 | E31: 1 | F31: 1 | G31: 1080 | H31: 2 | I31: 2.1-3-38 | J31: ТСН-2001.2. Доп. 68. п.1-3-38 (032009) | K31: Краны на автомобильном ходу, грузоподъемность до 16 т | L31: 1368 | N31: 1011 | O31: маш.-ч | P31: маш.-ч | Q31: 1 | W31: 0 | X31: 1087580389 | Y31: =(AT31*1.1) -> 0.011 | AA31: 0 | AB31: 187.59 | AC31: 17.73 | AD31: 0 | AE31: 0 | AF31: 179.17 | AG31: 16.93 | AH31: 0 | AI31: 1 | AJ31: 1 | AK31: 1 | AL31: 1 | AM31: -2 | AN31: 0 | AO31: 1 | AP31: 1 | AQ31: 0 | AR31: 0 | AT31: 0.01 | AU31: *1,1 | AV31: 0 | AW31: 2 | AX31: 60257981 | AY31: 1 | AZ31: 0 | BA31: 35 | BB31: 0 | BC31: 0 | BD31: 0 | BE31: 0 | BF31: 0 | BG31: 0 | BH31: 0 | BI31: 0 | BJ31: 0 | BK31: 0 | BL31: 0 | BM31: 0 | BN31: 0 | BO31: 0 | BP31: 0 | BQ31: 0 | BR31: 0 | BS31: 0 | BT31: 0 | BU31: 0 | BV31: 0 | BW31: 0 | CV31: 0 | CW31: =ROUND(Y31*Source!I79*DO31,9) -> 0.093115 | CX31: =ROUND(Y31*Source!I79,9) -> 0.0055 | CY31: =AB31 -> 187.59 | CZ31: =AF31 -> 179.17 | DA31: =AJ31 -> 1 | DB31: =ROUND((ROUND(AT31*CZ31,2)*1.1),6) -> 1.969 | DC31: =ROUND((ROUND(AT31*AG31,2)*1.1),6) -> 0.187 | DF31: =ROUND(ROUND(AE31,2)*CX31,2) -> 0 | DG31: =ROUND(ROUND(AF31,2)*CX31,2) -> 0.99 | DH31: =ROUND(ROUND(AG31,2)*CX31,2) -> 0.09 | DI31: =ROUND(ROUND(AH31,2)*CX31,2) -> 0 | DJ31: =DG31 -> 0.99 | DK31: 0 | DL31: 9999990009 | DM31: 0 | DN31: чел.-ч. | DO31: 16.93
A32: =ROW(Source!A79) -> 79 | B32: 60257736 | C32: 60257944 | D32: 59039702 | E32: 1 | F32: 1 | G32: 1080 | H32: 3 | I32: 1.1-1-1257 | J32: ТСН-2001.1 Доп. 79, Р. 1, о. 1, поз. 1257 | K32: Тальк молотый | L32: 1346 | N32: 1009 | O32: кг | P32: кг | Q32: 1 | W32: 0 | X32: 1770006655 | Y32: =(AT32*1) -> 0.6 | AA32: 1.38 | AB32: 0 | AC32: 0 | AD32: 0 | AE32: 1.38 | AF32: 0 | AG32: 0 | AH32: 0 | AI32: 1 | AJ32: 1 | AK32: 1 | AL32: 1 | AM32: -2 | AN32: 0 | AO32: 1 | AP32: 1 | AQ32: 0 | AR32: 0 | AT32: 0.6 | AU32: *1 | AV32: 0 | AW32: 2 | AX32: 60257982 | AY32: 1 | AZ32: 0 | BA32: 36 | BB32: 0 | BC32: 0 | BD32: 0 | BE32: 0 | BF32: 0 | BG32: 0 | BH32: 0 | BI32: 0 | BJ32: 0 | BK32: 0 | BL32: 0 | BM32: 0 | BN32: 0 | BO32: 0 | BP32: 0 | BQ32: 0 | BR32: 0 | BS32: 0 | BT32: 0 | BU32: 0 | BV32: 0 | BW32: 0 | CV32: 0 | CW32: 0 | CX32: =ROUND(Y32*Source!I79,9) -> 0.3 | CY32: =AA32 -> 1.38 | CZ32: =AE32 -> 1.38 | DA32: =AI32 -> 1 | DB32: =ROUND((ROUND(AT32*CZ32,2)*1),6) -> 0.83 | DC32: =ROUND((ROUND(AT32*AG32,2)*1),6) -> 0 | DF32: =ROUND(ROUND(AE32,2)*CX32,2) -> 0.41 | DG32: =ROUND(ROUND(AF32,2)*CX32,2) -> 0 | DH32: =ROUND(ROUND(AG32,2)*CX32,2) -> 0 | DI32: =ROUND(ROUND(AH32,2)*CX32,2) -> 0 | DJ32: =DF32 -> 0.41 | DK32: 0 | DM32: 0 | DO32: 0
A33: =ROW(Source!A79) -> 79 | B33: 60257736 | C33: 60257944 | D33: 59040093 | E33: 1 | F33: 1 | G33: 1080 | H33: 3 | I33: 1.1-1-1723 | J33: ТСН-2001.1 Доп. 79, Р. 1, о. 1, поз. 1723 | K33: Лента изоляционная, прорезиненная, односторонняя | L33: 1346 | N33: 1009 | O33: кг | P33: кг | Q33: 1 | W33: 0 | X33: -878159893 | Y33: =(AT33*1) -> 0.16 | AA33: 159.06 | AB33: 0 | AC33: 0 | AD33: 0 | AE33: 159.06 | AF33: 0 | AG33: 0 | AH33: 0 | AI33: 1 | AJ33: 1 | AK33: 1 | AL33: 1 | AM33: -2 | AN33: 0 | AO33: 1 | AP33: 1 | AQ33: 0 | AR33: 0 | AT33: 0.16 | AU33: *1 | AV33: 0 | AW33: 2 | AX33: 60257983 | AY33: 1 | AZ33: 0 | BA33: 37 | BB33: 0 | BC33: 0 | BD33: 0 | BE33: 0 | BF33: 0 | BG33: 0 | BH33: 0 | BI33: 0 | BJ33: 0 | BK33: 0 | BL33: 0 | BM33: 0 | BN33: 0 | BO33: 0 | BP33: 0 | BQ33: 0 | BR33: 0 | BS33: 0 | BT33: 0 | BU33: 0 | BV33: 0 | BW33: 0 | CV33: 0 | CW33: 0 | CX33: =ROUND(Y33*Source!I79,9) -> 0.08 | CY33: =AA33 -> 159.06 | CZ33: =AE33 -> 159.06 | DA33: =AI33 -> 1 | DB33: =ROUND((ROUND(AT33*CZ33,2)*1),6) -> 25.45 | DC33: =ROUND((ROUND(AT33*AG33,2)*1),6) -> 0 | DF33: =ROUND(ROUND(AE33,2)*CX33,2) -> 12.72 | DG33: =ROUND(ROUND(AF33,2)*CX33,2) -> 0 | DH33: =ROUND(ROUND(AG33,2)*CX33,2) -> 0 | DI33: =ROUND(ROUND(AH33,2)*CX33,2) -> 0 | DJ33: =DF33 -> 12.72 | DK33: 0 | DM33: 0 | DO33: 0
A34: =ROW(Source!A79) -> 79 | B34: 60257736 | C34: 60257944 | D34: 59063048 | E34: 1 | F34: 1 | G34: 1080 | H34: 3 | I34: 1.21-5-1555 | J34: ТСН-2001.1 Доп. 79, Р. 21, о. 5, поз. 1555 | K34: Втулка трубная, полипропиленовая, диаметр 22 мм | L34: 1356 | N34: 1010 | O34: 1000 шт. | P34: 1000 шт. | Q34: 1000 | W34: 0 | X34: -422648154 | Y34: =(AT34*1) -> 0.0122 | AA34: 226.86 | AB34: 0 | AC34: 0 | AD34: 0 | AE34: 226.86 | AF34: 0 | AG34: 0 | AH34: 0 | AI34: 1 | AJ34: 1 | AK34: 1 | AL34: 1 | AM34: -2 | AN34: 0 | AO34: 1 | AP34: 1 | AQ34: 0 | AR34: 0 | AT34: 0.0122 | AU34: *1 | AV34: 0 | AW34: 2 | AX34: 60257984 | AY34: 1 | AZ34: 0 | BA34: 38 | BB34: 0 | BC34: 0 | BD34: 0 | BE34: 0 | BF34: 0 | BG34: 0 | BH34: 0 | BI34: 0 | BJ34: 0 | BK34: 0 | BL34: 0 | BM34: 0 | BN34: 0 | BO34: 0 | BP34: 0 | BQ34: 0 | BR34: 0 | BS34: 0 | BT34: 0 | BU34: 0 | BV34: 0 | BW34: 0 | CV34: 0 | CW34: 0 | CX34: =ROUND(Y34*Source!I79,9) -> 0.0061 | CY34: =AA34 -> 226.86 | CZ34: =AE34 -> 226.86 | DA34: =AI34 -> 1 | DB34: =ROUND((ROUND(AT34*CZ34,2)*1),6) -> 2.77 | DC34: =ROUND((ROUND(AT34*AG34,2)*1),6) -> 0 | DF34: =ROUND(ROUND(AE34,2)*CX34,2) -> 1.38 | DG34: =ROUND(ROUND(AF34,2)*CX34,2) -> 0 | DH34: =ROUND(ROUND(AG34,2)*CX34,2) -> 0 | DI34: =ROUND(ROUND(AH34,2)*CX34,2) -> 0 | DJ34: =DF34 -> 1.38 | DK34: 0 | DM34: 0 | DO34: 0
A35: =ROW(Source!A79) -> 79 | B35: 60257736 | C35: 60257944 | D35: 59062373 | E35: 1 | F35: 1 | G35: 1080 | H35: 3 | I35: 1.21-5-750 | J35: ТСН-2001.1 Доп. 73, Р. 21, о. 5, поз. 750 | K35: Сжим, типа У 739М для проводников магистральных сечением от 4 до 10 мм2 и ответвительных сечением от 1,5 до 2,5 мм2 | L35: 1354 | N35: 1010 | O35: шт. | P35: шт. | Q35: 1 | W35: 0 | X35: 145081611 | Y35: =(AT35*1) -> 3.1 | AA35: 6.94 | AB35: 0 | AC35: 0 | AD35: 0 | AE35: 6.94 | AF35: 0 | AG35: 0 | AH35: 0 | AI35: 1 | AJ35: 1 | AK35: 1 | AL35: 1 | AM35: -2 | AN35: 0 | AO35: 1 | AP35: 1 | AQ35: 0 | AR35: 0 | AT35: 3.1 | AU35: *1 | AV35: 0 | AW35: 2 | AX35: 60257985 | AY35: 1 | AZ35: 0 | BA35: 39 | BB35: 0 | BC35: 0 | BD35: 0 | BE35: 0 | BF35: 0 | BG35: 0 | BH35: 0 | BI35: 0 | BJ35: 0 | BK35: 0 | BL35: 0 | BM35: 0 | BN35: 0 | BO35: 0 | BP35: 0 | BQ35: 0 | BR35: 0 | BS35: 0 | BT35: 0 | BU35: 0 | BV35: 0 | BW35: 0 | CV35: 0 | CW35: 0 | CX35: =ROUND(Y35*Source!I79,9) -> 1.55 | CY35: =AA35 -> 6.94 | CZ35: =AE35 -> 6.94 | DA35: =AI35 -> 1 | DB35: =ROUND((ROUND(AT35*CZ35,2)*1),6) -> 21.51 | DC35: =ROUND((ROUND(AT35*AG35,2)*1),6) -> 0 | DF35: =ROUND(ROUND(AE35,2)*CX35,2) -> 10.76 | DG35: =ROUND(ROUND(AF35,2)*CX35,2) -> 0 | DH35: =ROUND(ROUND(AG35,2)*CX35,2) -> 0 | DI35: =ROUND(ROUND(AH35,2)*CX35,2) -> 0 | DJ35: =DF35 -> 10.76 | DK35: 0 | DM35: 0 | DO35: 0
A36: =ROW(Source!A79) -> 79 | B36: 60257736 | C36: 60257944 | D36: 59062381 | E36: 1 | F36: 1 | G36: 1080 | H36: 3 | I36: 1.21-5-758 | J36: ТСН-2001.1 Доп. 79, Р. 21, о. 5, поз. 758 | K36: Зажим соединительно-изолирующий, типа СИЗ-3 | L36: 1356 | N36: 1010 | O36: 1000 шт. | P36: 1000 шт. | Q36: 1000 | W36: 0 | X36: 807379832 | Y36: =(AT36*1) -> 0.008 | AA36: 614.09 | AB36: 0 | AC36: 0 | AD36: 0 | AE36: 614.09 | AF36: 0 | AG36: 0 | AH36: 0 | AI36: 1 | AJ36: 1 | AK36: 1 | AL36: 1 | AM36: -2 | AN36: 0 | AO36: 1 | AP36: 1 | AQ36: 0 | AR36: 0 | AT36: 0.008 | AU36: *1 | AV36: 0 | AW36: 2 | AX36: 60257986 | AY36: 1 | AZ36: 0 | BA36: 40 | BB36: 0 | BC36: 0 | BD36: 0 | BE36: 0 | BF36: 0 | BG36: 0 | BH36: 0 | BI36: 0 | BJ36: 0 | BK36: 0 | BL36: 0 | BM36: 0 | BN36: 0 | BO36: 0 | BP36: 0 | BQ36: 0 | BR36: 0 | BS36: 0 | BT36: 0 | BU36: 0 | BV36: 0 | BW36: 0 | CV36: 0 | CW36: 0 | CX36: =ROUND(Y36*Source!I79,9) -> 0.004 | CY36: =AA36 -> 614.09 | CZ36: =AE36 -> 614.09 | DA36: =AI36 -> 1 | DB36: =ROUND((ROUND(AT36*CZ36,2)*1),6) -> 4.91 | DC36: =ROUND((ROUND(AT36*AG36,2)*1),6) -> 0 | DF36: =ROUND(ROUND(AE36,2)*CX36,2) -> 2.46 | DG36: =ROUND(ROUND(AF36,2)*CX36,2) -> 0 | DH36: =ROUND(ROUND(AG36,2)*CX36,2) -> 0 | DI36: =ROUND(ROUND(AH36,2)*CX36,2) -> 0 | DJ36: =DF36 -> 2.46 | DK36: 0 | DM36: 0 | DO36: 0
A37: =ROW(Source!A80) -> 80 | B37: 60257733 | C37: 60257944 | D37: 58999254 | E37: 1080 | F37: 1 | G37: 1080 | H37: 1 | I37: 9999990008 | K37: Трудозатраты рабочих | L37: 1191 | N37: 1013 | O37: чел.-ч. | P37: чел.-ч. | Q37: 1 | W37: 0 | X37: 476480486 | Y37: =(AT37*1.1) -> 2.013 | AA37: 0 | AB37: 0 | AC37: 0 | AD37: 0 | AE37: 0 | AF37: 0 | AG37: 0 | AH37: 0 | AI37: 1 | AJ37: 1 | AK37: 1 | AL37: 1 | AM37: 5 | AN37: 0 | AO37: 1 | AP37: 1 | AQ37: 0 | AR37: 0 | AT37: 1.83 | AU37: *1,1 | AV37: 1 | AW37: 2 | AX37: 60257979 | AY37: 1 | AZ37: 0 | BA37: 42 | BB37: 0 | BC37: 0 | BD37: 0 | BE37: 0 | BF37: 0 | BG37: 0 | BH37: 0 | BI37: 0 | BJ37: 0 | BK37: 0 | BL37: 0 | BM37: 0 | BN37: 0 | BO37: 0 | BP37: 0 | BQ37: 0 | BR37: 0 | BS37: 0 | BT37: 0 | BU37: 0 | BV37: 0 | BW37: 0 | CU37: =ROUND(AT37*Source!I80*AH37*AL37,2) -> 0 | CV37: =ROUND(Y37*Source!I80,9) -> 1.0065 | CW37: 0 | CX37: =ROUND(Y37*Source!I80,9) -> 1.0065 | CY37: =AD37 -> 0 | CZ37: =AH37 -> 0 | DA37: =AL37 -> 1 | DB37: =ROUND((ROUND(AT37*CZ37,2)*1.1),6) -> 0 | DC37: =ROUND((ROUND(AT37*AG37,2)*1.1),6) -> 0 | DF37: =ROUND(ROUND(AE37,2)*CX37,2) -> 0 | DG37: =ROUND(ROUND(AF37,2)*CX37,2) -> 0 | DH37: =ROUND(ROUND(AG37,2)*CX37,2) -> 0 | DI37: =ROUND(ROUND(AH37,2)*CX37,2) -> 0 | DJ37: =DI37 -> 0 | DK37: 0 | DM37: 0 | DO37: 0
A38: =ROW(Source!A80) -> 80 | B38: 60257733 | C38: 60257944 | D38: 59070669 | E38: 1 | F38: 1 | G38: 1080 | H38: 2 | I38: 2.1-18-7 | J38: ТСН-2001.2. Доп. 68. п.1-18-7 (183001) | K38: Автомобили грузовые бортовые, грузоподъемность до 5 т | L38: 1368 | N38: 1011 | O38: маш.-ч | P38: маш.-ч | Q38: 1 | W38: 0 | X38: -1985943078 | Y38: =(AT38*1.1) -> 0.011 | AA38: 0 | AB38: 1418.19 | AC38: 726.59 | AD38: 0 | AE38: 0 | AF38: 83.1 | AG38: 12.62 | AH38: 0 | AI38: 1 | AJ38: 16.3 | AK38: 54.99 | AL38: 1 | AM38: 2 | AN38: 0 | AO38: 1 | AP38: 1 | AQ38: 0 | AR38: 0 | AT38: 0.01 | AU38: *1,1 | AV38: 0 | AW38: 2 | AX38: 60257980 | AY38: 1 | AZ38: 0 | BA38: 43 | BB38: 0 | BC38: 0 | BD38: 0 | BE38: 0 | BF38: 0 | BG38: 0 | BH38: 0 | BI38: 0 | BJ38: 0 | BK38: 0 | BL38: 0 | BM38: 0 | BN38: 0 | BO38: 0 | BP38: 0 | BQ38: 0 | BR38: 0 | BS38: 0 | BT38: 0 | BU38: 0 | BV38: 0 | BW38: 0 | CV38: 0 | CW38: =ROUND(Y38*Source!I80*DO38,9) -> 0.06941 | CX38: =ROUND(Y38*Source!I80,9) -> 0.0055 | CY38: =AB38 -> 1418.19 | CZ38: =AF38 -> 83.1 | DA38: =AJ38 -> 16.3 | DB38: =ROUND((ROUND(AT38*CZ38,2)*1.1),6) -> 0.913 | DC38: =ROUND((ROUND(AT38*AG38,2)*1.1),6) -> 0.143 | DF38: =ROUND(ROUND(AE38,2)*CX38,2) -> 0 | DG38: =ROUND(ROUND(AF38*AJ38,2)*CX38,2) -> 7.45 | DH38: =ROUND(ROUND(AG38*AK38,2)*CX38,2) -> 3.82 | DI38: =ROUND(ROUND(AH38,2)*CX38,2) -> 0 | DJ38: =DG38 -> 7.45 | DK38: 0 | DL38: 9999990009 | DM38: 0 | DN38: чел.-ч. | DO38: 12.62
A39: =ROW(Source!A80) -> 80 | B39: 60257733 | C39: 60257944 | D39: 59069905 | E39: 1 | F39: 1 | G39: 1080 | H39: 2 | I39: 2.1-3-38 | J39: ТСН-2001.2. Доп. 68. п.1-3-38 (032009) | K39: Краны на автомобильном ходу, грузоподъемность до 16 т | L39: 1368 | N39: 1011 | O39: маш.-ч | P39: маш.-ч | Q39: 1 | W39: 0 | X39: 1087580389 | Y39: =(AT39*1.1) -> 0.011 | AA39: 0 | AB39: 2579.38 | AC39: 974.74 | AD39: 0 | AE39: 0 | AF39: 179.17 | AG39: 16.93 | AH39: 0 | AI39: 1 | AJ39: 13.75 | AK39: 54.99 | AL39: 1 | AM39: 2 | AN39: 0 | AO39: 1 | AP39: 1 | AQ39: 0 | AR39: 0 | AT39: 0.01 | AU39: *1,1 | AV39: 0 | AW39: 2 | AX39: 60257981 | AY39: 1 | AZ39: 0 | BA39: 44 | BB39: 0 | BC39: 0 | BD39: 0 | BE39: 0 | BF39: 0 | BG39: 0 | BH39: 0 | BI39: 0 | BJ39: 0 | BK39: 0 | BL39: 0 | BM39: 0 | BN39: 0 | BO39: 0 | BP39: 0 | BQ39: 0 | BR39: 0 | BS39: 0 | BT39: 0 | BU39: 0 | BV39: 0 | BW39: 0 | CV39: 0 | CW39: =ROUND(Y39*Source!I80*DO39,9) -> 0.093115 | CX39: =ROUND(Y39*Source!I80,9) -> 0.0055 | CY39: =AB39 -> 2579.38 | CZ39: =AF39 -> 179.17 | DA39: =AJ39 -> 13.75 | DB39: =ROUND((ROUND(AT39*CZ39,2)*1.1),6) -> 1.969 | DC39: =ROUND((ROUND(AT39*AG39,2)*1.1),6) -> 0.187 | DF39: =ROUND(ROUND(AE39,2)*CX39,2) -> 0 | DG39: =ROUND(ROUND(AF39*AJ39,2)*CX39,2) -> 13.55 | DH39: =ROUND(ROUND(AG39*AK39,2)*CX39,2) -> 5.12 | DI39: =ROUND(ROUND(AH39,2)*CX39,2) -> 0 | DJ39: =DG39 -> 13.55 | DK39: 0 | DL39: 9999990009 | DM39: 0 | DN39: чел.-ч. | DO39: 16.93
A40: =ROW(Source!A80) -> 80 | B40: 60257733 | C40: 60257944 | D40: 59039702 | E40: 1 | F40: 1 | G40: 1080 | H40: 3 | I40: 1.1-1-1257 | J40: ТСН-2001.1 Доп. 79, Р. 1, о. 1, поз. 1257 | K40: Тальк молотый | L40: 1346 | N40: 1009 | O40: кг | P40: кг | Q40: 1 | W40: 0 | X40: 1770006655 | Y40: =(AT40*1) -> 0.6 | AA40: 29.73 | AB40: 0 | AC40: 0 | AD40: 0 | AE40: 1.38 | AF40: 0 | AG40: 0 | AH40: 0 | AI40: 21.54 | AJ40: 1 | AK40: 1 | AL40: 1 | AM40: 2 | AN40: 0 | AO40: 1 | AP40: 1 | AQ40: 0 | AR40: 0 | AT40: 0.6 | AU40: *1 | AV40: 0 | AW40: 2 | AX40: 60257982 | AY40: 1 | AZ40: 0 | BA40: 45 | BB40: 0 | BC40: 0 | BD40: 0 | BE40: 0 | BF40: 0 | BG40: 0 | BH40: 0 | BI40: 0 | BJ40: 0 | BK40: 0 | BL40: 0 | BM40: 0 | BN40: 0 | BO40: 0 | BP40: 0 | BQ40: 0 | BR40: 0 | BS40: 0 | BT40: 0 | BU40: 0 | BV40: 0 | BW40: 0 | CV40: 0 | CW40: 0 | CX40: =ROUND(Y40*Source!I80,9) -> 0.3 | CY40: =AA40 -> 29.73 | CZ40: =AE40 -> 1.38 | DA40: =AI40 -> 21.54 | DB40: =ROUND((ROUND(AT40*CZ40,2)*1),6) -> 0.83 | DC40: =ROUND((ROUND(AT40*AG40,2)*1),6) -> 0 | DF40: =ROUND(ROUND(AE40*AI40,2)*CX40,2) -> 8.92 | DG40: =ROUND(ROUND(AF40,2)*CX40,2) -> 0 | DH40: =ROUND(ROUND(AG40,2)*CX40,2) -> 0 | DI40: =ROUND(ROUND(AH40,2)*CX40,2) -> 0 | DJ40: =DF40 -> 8.92 | DK40: 0 | DM40: 0 | DO40: 0
A41: =ROW(Source!A80) -> 80 | B41: 60257733 | C41: 60257944 | D41: 59040093 | E41: 1 | F41: 1 | G41: 1080 | H41: 3 | I41: 1.1-1-1723 | J41: ТСН-2001.1 Доп. 79, Р. 1, о. 1, поз. 1723 | K41: Лента изоляционная, прорезиненная, односторонняя | L41: 1346 | N41: 1009 | O41: кг | P41: кг | Q41: 1 | W41: 0 | X41: -878159893 | Y41: =(AT41*1) -> 0.16 | AA41: 286.31 | AB41: 0 | AC41: 0 | AD41: 0 | AE41: 159.06 | AF41: 0 | AG41: 0 | AH41: 0 | AI41: 1.8 | AJ41: 1 | AK41: 1 | AL41: 1 | AM41: 2 | AN41: 0 | AO41: 1 | AP41: 1 | AQ41: 0 | AR41: 0 | AT41: 0.16 | AU41: *1 | AV41: 0 | AW41: 2 | AX41: 60257983 | AY41: 1 | AZ41: 0 | BA41: 46 | BB41: 0 | BC41: 0 | BD41: 0 | BE41: 0 | BF41: 0 | BG41: 0 | BH41: 0 | BI41: 0 | BJ41: 0 | BK41: 0 | BL41: 0 | BM41: 0 | BN41: 0 | BO41: 0 | BP41: 0 | BQ41: 0 | BR41: 0 | BS41: 0 | BT41: 0 | BU41: 0 | BV41: 0 | BW41: 0 | CV41: 0 | CW41: 0 | CX41: =ROUND(Y41*Source!I80,9) -> 0.08 | CY41: =AA41 -> 286.31 | CZ41: =AE41 -> 159.06 | DA41: =AI41 -> 1.8 | DB41: =ROUND((ROUND(AT41*CZ41,2)*1),6) -> 25.45 | DC41: =ROUND((ROUND(AT41*AG41,2)*1),6) -> 0 | DF41: =ROUND(ROUND(AE41*AI41,2)*CX41,2) -> 22.9 | DG41: =ROUND(ROUND(AF41,2)*CX41,2) -> 0 | DH41: =ROUND(ROUND(AG41,2)*CX41,2) -> 0 | DI41: =ROUND(ROUND(AH41,2)*CX41,2) -> 0 | DJ41: =DF41 -> 22.9 | DK41: 0 | DM41: 0 | DO41: 0
A42: =ROW(Source!A80) -> 80 | B42: 60257733 | C42: 60257944 | D42: 59063048 | E42: 1 | F42: 1 | G42: 1080 | H42: 3 | I42: 1.21-5-1555 | J42: ТСН-2001.1 Доп. 79, Р. 21, о. 5, поз. 1555 | K42: Втулка трубная, полипропиленовая, диаметр 22 мм | L42: 1356 | N42: 1010 | O42: 1000 шт. | P42: 1000 шт. | Q42: 1000 | W42: 0 | X42: -422648154 | Y42: =(AT42*1) -> 0.0122 | AA42: 1599.36 | AB42: 0 | AC42: 0 | AD42: 0 | AE42: 226.86 | AF42: 0 | AG42: 0 | AH42: 0 | AI42: 7.05 | AJ42: 1 | AK42: 1 | AL42: 1 | AM42: 2 | AN42: 0 | AO42: 1 | AP42: 1 | AQ42: 0 | AR42: 0 | AT42: 0.0122 | AU42: *1 | AV42: 0 | AW42: 2 | AX42: 60257984 | AY42: 1 | AZ42: 0 | BA42: 47 | BB42: 0 | BC42: 0 | BD42: 0 | BE42: 0 | BF42: 0 | BG42: 0 | BH42: 0 | BI42: 0 | BJ42: 0 | BK42: 0 | BL42: 0 | BM42: 0 | BN42: 0 | BO42: 0 | BP42: 0 | BQ42: 0 | BR42: 0 | BS42: 0 | BT42: 0 | BU42: 0 | BV42: 0 | BW42: 0 | CV42: 0 | CW42: 0 | CX42: =ROUND(Y42*Source!I80,9) -> 0.0061 | CY42: =AA42 -> 1599.36 | CZ42: =AE42 -> 226.86 | DA42: =AI42 -> 7.05 | DB42: =ROUND((ROUND(AT42*CZ42,2)*1),6) -> 2.77 | DC42: =ROUND((ROUND(AT42*AG42,2)*1),6) -> 0 | DF42: =ROUND(ROUND(AE42*AI42,2)*CX42,2) -> 9.76 | DG42: =ROUND(ROUND(AF42,2)*CX42,2) -> 0 | DH42: =ROUND(ROUND(AG42,2)*CX42,2) -> 0 | DI42: =ROUND(ROUND(AH42,2)*CX42,2) -> 0 | DJ42: =DF42 -> 9.76 | DK42: 0 | DM42: 0 | DO42: 0
A43: =ROW(Source!A80) -> 80 | B43: 60257733 | C43: 60257944 | D43: 59062373 | E43: 1 | F43: 1 | G43: 1080 | H43: 3 | I43: 1.21-5-750 | J43: ТСН-2001.1 Доп. 73, Р. 21, о. 5, поз. 750 | K43: Сжим, типа У 739М для проводников магистральных сечением от 4 до 10 мм2 и ответвительных сечением от 1,5 до 2,5 мм2 | L43: 1354 | N43: 1010 | O43: шт. | P43: шт. | Q43: 1 | W43: 0 | X43: 145081611 | Y43: =(AT43*1) -> 3.1 | AA43: 25.47 | AB43: 0 | AC43: 0 | AD43: 0 | AE43: 6.94 | AF43: 0 | AG43: 0 | AH43: 0 | AI43: 3.67 | AJ43: 1 | AK43: 1 | AL43: 1 | AM43: 2 | AN43: 0 | AO43: 1 | AP43: 1 | AQ43: 0 | AR43: 0 | AT43: 3.1 | AU43: *1 | AV43: 0 | AW43: 2 | AX43: 60257985 | AY43: 1 | AZ43: 0 | BA43: 48 | BB43: 0 | BC43: 0 | BD43: 0 | BE43: 0 | BF43: 0 | BG43: 0 | BH43: 0 | BI43: 0 | BJ43: 0 | BK43: 0 | BL43: 0 | BM43: 0 | BN43: 0 | BO43: 0 | BP43: 0 | BQ43: 0 | BR43: 0 | BS43: 0 | BT43: 0 | BU43: 0 | BV43: 0 | BW43: 0 | CV43: 0 | CW43: 0 | CX43: =ROUND(Y43*Source!I80,9) -> 1.55 | CY43: =AA43 -> 25.47 | CZ43: =AE43 -> 6.94 | DA43: =AI43 -> 3.67 | DB43: =ROUND((ROUND(AT43*CZ43,2)*1),6) -> 21.51 | DC43: =ROUND((ROUND(AT43*AG43,2)*1),6) -> 0 | DF43: =ROUND(ROUND(AE43*AI43,2)*CX43,2) -> 39.48 | DG43: =ROUND(ROUND(AF43,2)*CX43,2) -> 0 | DH43: =ROUND(ROUND(AG43,2)*CX43,2) -> 0 | DI43: =ROUND(ROUND(AH43,2)*CX43,2) -> 0 | DJ43: =DF43 -> 39.48 | DK43: 0 | DM43: 0 | DO43: 0
A44: =ROW(Source!A80) -> 80 | B44: 60257733 | C44: 60257944 | D44: 59062381 | E44: 1 | F44: 1 | G44: 1080 | H44: 3 | I44: 1.21-5-758 | J44: ТСН-2001.1 Доп. 79, Р. 21, о. 5, поз. 758 | K44: Зажим соединительно-изолирующий, типа СИЗ-3 | L44: 1356 | N44: 1010 | O44: 1000 шт. | P44: 1000 шт. | Q44: 1000 | W44: 0 | X44: 807379832 | Y44: =(AT44*1) -> 0.008 | AA44: 1197.48 | AB44: 0 | AC44: 0 | AD44: 0 | AE44: 614.09 | AF44: 0 | AG44: 0 | AH44: 0 | AI44: 1.95 | AJ44: 1 | AK44: 1 | AL44: 1 | AM44: 2 | AN44: 0 | AO44: 1 | AP44: 1 | AQ44: 0 | AR44: 0 | AT44: 0.008 | AU44: *1 | AV44: 0 | AW44: 2 | AX44: 60257986 | AY44: 1 | AZ44: 0 | BA44: 49 | BB44: 0 | BC44: 0 | BD44: 0 | BE44: 0 | BF44: 0 | BG44: 0 | BH44: 0 | BI44: 0 | BJ44: 0 | BK44: 0 | BL44: 0 | BM44: 0 | BN44: 0 | BO44: 0 | BP44: 0 | BQ44: 0 | BR44: 0 | BS44: 0 | BT44: 0 | BU44: 0 | BV44: 0 | BW44: 0 | CV44: 0 | CW44: 0 | CX44: =ROUND(Y44*Source!I80,9) -> 0.004 | CY44: =AA44 -> 1197.48 | CZ44: =AE44 -> 614.09 | DA44: =AI44 -> 1.95 | DB44: =ROUND((ROUND(AT44*CZ44,2)*1),6) -> 4.91 | DC44: =ROUND((ROUND(AT44*AG44,2)*1),6) -> 0 | DF44: =ROUND(ROUND(AE44*AI44,2)*CX44,2) -> 4.79 | DG44: =ROUND(ROUND(AF44,2)*CX44,2) -> 0 | DH44: =ROUND(ROUND(AG44,2)*CX44,2) -> 0 | DI44: =ROUND(ROUND(AH44,2)*CX44,2) -> 0 | DJ44: =DF44 -> 4.79 | DK44: 0 | DM44: 0 | DO44: 0

Sheet EtalonRes
A1: =ROW(Source!A28) -> 28 | B1: 60257963 | C1: 60257850 | D1: 58999254 | E1: 1080 | F1: 1 | G1: 1080 | H1: 1 | I1: 9999990008 | K1: Трудозатраты рабочих | L1: 1191 | N1: 1013 | O1: чел.-ч. | P1: чел.-ч. | Q1: 1 | X1: 3 | Y1: 0 | Z1: 0 | AA1: 0 | AB1: 0 | AC1: 0 | AD1: 1 | AE1: 1 | AF1: *1,1 | AG1: 3.3 | AH1: 2 | AI1: 60257851 | AJ1: 1 | AK1: 0 | AL1: 0 | AM1: 0 | AN1: 0 | AO1: 0 | AP1: 0 | AQ1: 0 | AR1: 0
A2: =ROW(Source!A29) -> 29 | B2: 60257963 | C2: 60257850 | D2: 58999254 | E2: 1080 | F2: 1 | G2: 1080 | H2: 1 | I2: 9999990008 | K2: Трудозатраты рабочих | L2: 1191 | N2: 1013 | O2: чел.-ч. | P2: чел.-ч. | Q2: 1 | X2: 3 | Y2: 0 | Z2: 0 | AA2: 0 | AB2: 0 | AC2: 0 | AD2: 1 | AE2: 1 | AF2: *1,1 | AG2: 3.3 | AH2: 2 | AI2: 60257851 | AJ2: 2 | AK2: 0 | AL2: 0 | AM2: 0 | AN2: 0 | AO2: 0 | AP2: 0 | AQ2: 0 | AR2: 0
A3: =ROW(Source!A32) -> 32 | B3: 60257964 | C3: 60257854 | D3: 58999254 | E3: 1080 | F3: 1 | G3: 1080 | H3: 1 | I3: 9999990008 | K3: Трудозатраты рабочих | L3: 1191 | N3: 1013 | O3: чел.-ч. | P3: чел.-ч. | Q3: 1 | X3: 2 | Y3: 0 | Z3: 0 | AA3: 0 | AB3: 0 | AC3: 0 | AD3: 1 | AE3: 1 | AF3: *1,1 | AG3: 2.2 | AH3: 2 | AI3: 60257855 | AJ3: 3 | AK3: 0 | AL3: 0 | AM3: 0 | AN3: 0 | AO3: 0 | AP3: 0 | AQ3: 0 | AR3: 0
A4: =ROW(Source!A33) -> 33 | B4: 60257964 | C4: 60257854 | D4: 58999254 | E4: 1080 | F4: 1 | G4: 1080 | H4: 1 | I4: 9999990008 | K4: Трудозатраты рабочих | L4: 1191 | N4: 1013 | O4: чел.-ч. | P4: чел.-ч. | Q4: 1 | X4: 2 | Y4: 0 | Z4: 0 | AA4: 0 | AB4: 0 | AC4: 0 | AD4: 1 | AE4: 1 | AF4: *1,1 | AG4: 2.2 | AH4: 2 | AI4: 60257855 | AJ4: 4 | AK4: 0 | AL4: 0 | AM4: 0 | AN4: 0 | AO4: 0 | AP4: 0 | AQ4: 0 | AR4: 0
A5: =ROW(Source!A71) -> 71 | B5: 60257965 | C5: 60257914 | D5: 58999254 | E5: 1080 | F5: 1 | G5: 1080 | H5: 1 | I5: 9999990008 | K5: Трудозатраты рабочих | L5: 1191 | N5: 1013 | O5: чел.-ч. | P5: чел.-ч. | Q5: 1 | X5: 14.37 | Y5: 0 | Z5: 0 | AA5: 0 | AB5: 0 | AC5: 0 | AD5: 1 | AE5: 1 | AF5: *1,1 | AG5: 15.807 | AH5: 2 | AI5: 60257915 | AJ5: 5 | AK5: 0 | AL5: 0 | AM5: 0 | AN5: 0 | AO5: 0 | AP5: 0 | AQ5: 0 | AR5: 0
A6: =ROW(Source!A71) -> 71 | B6: 60257966 | C6: 60257914 | D6: 59008656 | E6: 1080 | F6: 1 | G6: 1080 | H6: 3 | I6: 2248200000 | K6: Трубы поливинилхлоридные гофрированные | L6: 1301 | N6: 1003 | O6: м | P6: м | Q6: 1 | X6: 102 | Y6: 0 | Z6: 0 | AA6: 0 | AB6: 0 | AC6: 0 | AD6: 0 | AE6: 0 | AF6: *1 | AG6: 102 | AH6: 3 | AI6: -1 | AK6: 0 | AL6: 0 | AM6: 0 | AN6: 0 | AO6: 0 | AP6: 0 | AQ6: 0 | AR6: 0
A7: =ROW(Source!A71) -> 71 | B7: 60257967 | C7: 60257914 | D7: 59011823 | E7: 1080 | F7: 1 | G7: 1080 | H7: 3 | I7: 3434200000 | K7: Коробки соединительные | L7: 1354 | N7: 1010 | O7: шт. | P7: шт. | Q7: 1 | X7: 0 | Y7: 0 | Z7: 0 | AA7: 0 | AB7: 0 | AC7: 0 | AD7: 0 | AE7: 0 | AF7: *1 | AG7: 0 | AH7: 3 | AI7: -1 | AK7: 0 | AL7: 0 | AM7: 0 | AN7: 0 | AO7: 0 | AP7: 0 | AQ7: 0 | AR7: 0
A8: =ROW(Source!A71) -> 71 | B8: 60257968 | C8: 60257914 | D8: 59012395 | E8: 1080 | F8: 1 | G8: 1080 | H8: 3 | I8: 3449651000 | K8: Держатели пластиковые для труб | L8: 1354 | N8: 1010 | O8: шт. | P8: шт. | Q8: 1 | X8: 0 | Y8: 0 | Z8: 0 | AA8: 0 | AB8: 0 | AC8: 0 | AD8: 0 | AE8: 0 | AF8: *1 | AG8: 0 | AH8: 3 | AI8: -1 | AK8: 0 | AL8: 0 | AM8: 0 | AN8: 0 | AO8: 0 | AP8: 0 | AQ8: 0 | AR8: 0
A9: =ROW(Source!A72) -> 72 | B9: 60257965 | C9: 60257914 | D9: 58999254 | E9: 1080 | F9: 1 | G9: 1080 | H9: 1 | I9: 9999990008 | K9: Трудозатраты рабочих | L9: 1191 | N9: 1013 | O9: чел.-ч. | P9: чел.-ч. | Q9: 1 | X9: 14.37 | Y9: 0 | Z9: 0 | AA9: 0 | AB9: 0 | AC9: 0 | AD9: 1 | AE9: 1 | AF9: *1,1 | AG9: 15.807 | AH9: 2 | AI9: 60257915 | AJ9: 8 | AK9: 0 | AL9: 0 | AM9: 0 | AN9: 0 | AO9: 0 | AP9: 0 | AQ9: 0 | AR9: 0
