Workbook

Sheet 02-01-05
A1: =Source!B1 -> Smeta.RU (495) 974-1589
J2: Форма № 4б
A3: Капитальный ремонт здания Государственного бюджетного общеобразовательного учреждения города Москвы «Школа № 236». 1 этап. Клязьминская улица, д. 7, к. 4, Дмитровский район Северного административного округа города Москвы | AP3: Капитальный ремонт здания Государственного бюджетного общеобразовательного учреждения города Москвы "Школа № 236" по адресу: г. Москва ул. Клязьминская, д. 7 к. 4. 1 этап. 02-01-05 Система водоотведения
A4: (наименование стройки и/или объекта)
A6: =CONCATENATE( "ЛОКАЛЬНАЯ СМЕТА № ",IF(Source!F20<>"Новая локальная смета", Source!F20, "")) -> ЛОКАЛЬНАЯ СМЕТА № 02-01-05
A8: =IF(Source!G20<>"Новая локальная смета", Source!G20, "") -> Система водоотведения
A9: (наименование работ и затрат)
A11: =CONCATENATE( "Основание: чертежи № ", Source!J20) -> Основание: чертежи № 2024-00272-00-0-ИОС3
I13: В базисном уровне цен | J13: В текущем уровне цен
E14: Сметная стоимость | I14: =I15+I16+I17+I18 -> 872.29 | J14: =J15+J16+J17+J18 -> 9144.62 | K14: тыс.руб.
E15: Строительные работы | I15: =ROUND((Source!F1033)/1000, 2) -> 796.87 | J15: =ROUND((Source!P1033)/1000, 2) -> 8552.93 | K15: тыс.руб.
E16: Работы по монтажу оборудования | I16: =ROUND((Source!F1034)/1000, 2) -> 0.5 | J16: =ROUND((Source!P1034)/1000, 2) -> 17.83 | K16: тыс.руб.
E17: Оборудование | I17: =ROUND((Source!F1025)/1000, 2) -> 74.92 | J17: =ROUND((Source!P1025)/1000, 2) -> 573.86 | K17: тыс.руб.
E18: Прочие работы и затраты | I18: =ROUND((Source!F1035+Source!F1036)/1000, 2) -> 0 | J18: =ROUND((Source!P1035+Source!P1036)/1000, 2) -> 0 | K18: тыс.руб.
E19: Средства на оплату труда | I19: =(Source!F1031+ Source!F1030)/1000 -> 22.53262 | J19: =((Source!P1031 + Source!P1030)/1000) -> 1239.0688 | K19: тыс.руб.
E20: Затраты труда | I20: =Source!F1038 -> 1761.7362 | K20: чел.-ч.
E21: Кроме того:
E22: Возврат материалов | I22: =SUM(Y28:Y849)/1000 -> 0 | J22: =SUM(Z28:Z849)/1000 -> 0 | K22: тыс.руб.
A24: Составлен(а) по ТСН-2001 с учетом Дополнения №: 80
A25: № и период сборника коэффициентов (индексов) пересчета: Коэффициенты к ТСН-2001 МГЭ Дополнение 80, ремонт №217/80 III квартал 2025 года и Коэффициенты к ТСН-2001.13-2 Дополнение 46 №62/46 III квартал 2025 года | AP25: № и период сборника коэффициентов (индексов) пересчета: Коэффициенты к ТСН-2001 МГЭ Дополнение 80, ремонт №217/80 III квартал 2025 года и Коэффициенты к ТСН-2001.13-2 Дополнение 46 №62/46 III квартал 2025 года
A26: № п/п | B26: Шифр расценки и коды ресурсов | C26: Наименование работ и затрат | D26: Ед. изм. | E26: Кол-во единиц | F26: Цена на ед. изм., руб. | G26: Попра- вочные коэффи- циенты | H26: Коэффи- циенты зимних удорожа- ний | I26: Всего в ценах на январь 2000 года, руб. | J26: Коэффи- циенты (индек- сы) пере- счета, нормы НР и СП | K26: ВСЕГО затрат в текущем уровне цен, руб.
A27: 1 | B27: 2 | C27: 3 | D27: 4 | E27: 5 | F27: 6 | G27: 7 | H27: 8 | I27: 9 | J27: 10 | K27: 11
A29: =CONCATENATE("Раздел: ",IF(Source!G24<>"Новый раздел", Source!G24, "")) -> Раздел: Канализация хозяйственно-бытовая (К1) (подвал)
A31: =CONCATENATE("Подраздел: ",IF(Source!G28<>"Новый подраздел", Source!G28, "")) -> Подраздел: Монтажные работы
A32: 1 | B32: 3.16-36-1 Поправка: О.П. п.3.4. 6 Поправка: О.П. п.3.4.30.в | C32: Прокладка трубопроводов канализации из чугунных безраструбных труб, диаметр 50 мм | D32: =Source!H32 -> 100 м | E32: =Source!I32 -> 0.16 | Q32: =Source!X32 -> 433.5 | R32: =Source!X33 -> 23838.39 | S32: =Source!Y32 -> 242.6 | T32: =Source!Y33 -> 13340.75 | U32: =ROUND((175/100)*ROUND(Source!R32, 2), 2) -> 0.74 | V32: =ROUND((0/100)*ROUND(Source!R33, 2), 2) -> 0 | AC32: 0
C33: ="Объем: "&Source!I32&"=16/"&"100" -> Объем: 0,16=16/100
C34: ЗП | F34: =Source!AO32 -> 1839.65 | G34: 1,15*1,1 | H34: =Source!AV33 -> 1.067 | I34: =Source!S32 -> 397.29 | J34: =IF(Source!BA33<> 0, Source!BA33, 1) -> 54.99 | K34: =Source!S33 -> 21846.98
C35: ЭМ | F35: =Source!AM32 -> 21.59 | G35: 1,25*1,1 | H35: =Source!AV33 -> 1.067 | I35: =Source!Q32 -> 5.07 | J35: =IF(Source!BB33<> 0, Source!BB33, 1) -> 12.96 | K35: =Source!Q33 -> 65.71
C36: в т.ч. ЗПМ | F36: =Source!AN32 -> 1.77 | G36: 1,25*1,1 | H36: =Source!AV33 -> 1.067 | I36: =Source!R32 -> 0.42 | J36: =IF(Source!BS33<> 0, Source!BS33, 1) -> 54.99 | K36: =Source!R33 -> 23.1
C37: МР | F37: =Source!AL32 -> 3.3 | H37: =Source!AW33 -> 1 | I37: =Source!P32 -> 0.53 | J37: =IF(Source!BC33<> 0, Source!BC33, 1) -> 8.95 | K37: =Source!P33 -> 4.74
A38: 1,1 | B38: =Source!F34 -> 1.12-8-74 | C38: Комплект деталей трубопроводов из чугуна с мелкодисперсным графитом с внутренним эпоксидным покрытием, наружным слоем краснокоричневой грунтовки (безраструбные трубы, фасонные части, крепеж), диаметр условного прохода 50 мм | D38: =Source!H34 -> м | E38: =Source!I34 -> 16 | F38: =Source!AK34 -> 1328.86 | H38: =Source!AW35 -> 1 | I38: =Source!O34 -> 21261.76 | J38: =IF(Source!BC35<> 0, Source!BC35, 1) -> 0.95 | K38: =Source!O35 -> 20198.67 | Q38: =Source!X34 -> 0 | R38: =Source!X35 -> 0 | S38: =Source!Y34 -> 0 | T38: =Source!Y35 -> 0 | U38: =ROUND((175/100)*ROUND(Source!R34, 2), 2) -> 0 | V38: =ROUND((0/100)*ROUND(Source!R35, 2), 2) -> 0 | AC38: 3
C39: НР от ФОТ | D39: % | E39: =Source!BZ33 -> 109 | I39: =SUM(Q32:Q38) -> 433.5 | J39: =Source!AT33 -> 109 | K39: =SUM(R32:R38) -> 23838.39
C40: СП от ФОТ | D40: % | E40: =Source!CA33 -> 61 | I40: =SUM(S32:S39) -> 242.6 | J40: =Source!AU33 -> 61 | K40: =SUM(T32:T39) -> 13340.75
C41: ЗТР | D41: чел-ч | E41: =Source!AQ32 -> 142.31 | G41: 1,15*1,1 | H41: =Source!AV33 -> 1.067 | I41: =Source!U32 -> 30.733381
C42: Всего по позиции: | H42: =I34+I35+I37+I39+I40+SUM(I38:I38) -> 22340.75 | J42: =K34+K35+K37+K39+K40+SUM(K38:K38) -> 79295.24 | O42: =I34+I35+I37+I39+I40+SUM(I38:I38) -> 22340.75 | P42: =K34+K35+K37+K39+K40+SUM(K38:K38) -> 79295.24
A44: 2 | B44: 3.16-13-2 Поправка: О.П. п.3.4. 6 Поправка: О.П. п.3.4.30.в | C44: Прокладка трубопроводов канализации из ПВХ труб диаметром 100 мм - 150 мм | D44: =Source!H36 -> 100 м | E44: =Source!I36 -> 2.14 | Q44: =Source!X36 -> 2266.59 | R44: =Source!X37 -> 124639.77 | S44: =Source!Y36 -> 1268.46 | T44: =Source!Y37 -> 69752.53 | U44: =ROUND((175/100)*ROUND(Source!R36, 2), 2) -> 15.72 | V44: =ROUND((0/100)*ROUND(Source!R37, 2), 2) -> 0 | AC44: 0
C45: ="Объем: "&Source!I36&"=214/"&"100" -> Объем: 2,14=214/100
C46: ЗП | F46: =Source!AO36 -> 716.8 | G46: 1,15*1,1 | H46: =Source!AV37 -> 1.067 | I46: =Source!S36 -> 2070.46 | J46: =IF(Source!BA37<> 0, Source!BA37, 1) -> 54.99 | K46: =Source!S37 -> 113854.6
C47: ЭМ | F47: =Source!AM36 -> 20.2 | G47: 1,25*1,1 | H47: =Source!AV37 -> 1.067 | I47: =Source!Q36 -> 63.42 | J47: =IF(Source!BB37<> 0, Source!BB37, 1) -> 15.85 | K47: =Source!Q37 -> 1005.21
C48: в т.ч. ЗПМ | F48: =Source!AN36 -> 2.86 | G48: 1,25*1,1 | H48: =Source!AV37 -> 1.067 | I48: =Source!R36 -> 8.98 | J48: =IF(Source!BS37<> 0, Source!BS37, 1) -> 54.99 | K48: =Source!R37 -> 493.81
C49: МР | F49: =Source!AL36 -> 231.71 | H49: =Source!AW37 -> 1 | I49: =Source!P36 -> 495.86 | J49: =IF(Source!BC37<> 0, Source!BC37, 1) -> 16.19 | K49: =Source!P37 -> 8027.97
A50: 2,1 | B50: =Source!F38 -> КА 24 | C50: Трубы канализационные раструбные марки ПП, ГОСТ 32412-213, Д=110 25,81 = [300 / 1,2 / 9,88] + 2% Заг.скл | D50: =Source!H38 -> м | E50: =Source!I38 -> 214 | F50: =Source!AK38 -> 25.81 | H50: =Source!AW39 -> 1 | I50: =Source!O38 -> 5523.34 | J50: =IF(Source!BC39<> 0, Source!BC39, 1) -> 9.88 | K50: =Source!O39 -> 54570.6 | Q50: =Source!X38 -> 0 | R50: =Source!X39 -> 0 | S50: =Source!Y38 -> 0 | T50: =Source!Y39 -> 0 | U50: =ROUND((175/100)*ROUND(Source!R38, 2), 2) -> 0 | V50: =ROUND((0/100)*ROUND(Source!R39, 2), 2) -> 0 | AC50: 3
A51: 2,2 | B51: =Source!F40 -> 1.12-5-133 | C51: Ревизия из полиэтилена, диаметр 110 мм | D51: =Source!H40 -> шт. | E51: =Source!I40 -> 3 | F51: =Source!AK40 -> 53.05 | H51: =Source!AW41 -> 1 | I51: =Source!O40 -> 159.15 | J51: =IF(Source!BC41<> 0, Source!BC41, 1) -> 3.92 | K51: =Source!O41 -> 623.87 | Q51: =Source!X40 -> 0 | R51: =Source!X41 -> 0 | S51: =Source!Y40 -> 0 | T51: =Source!Y41 -> 0 | U51: =ROUND((175/100)*ROUND(Source!R40, 2), 2) -> 0 | V51: =ROUND((0/100)*ROUND(Source!R41, 2), 2) -> 0 | AC51: 3
A52: 2,3 | B52: =Source!F42 -> 1.12-5-133 | C52: Ревизия из полиэтилена, диаметр 110 мм /прочистки | D52: =Source!H42 -> шт. | E52: =Source!I42 -> 18 | F52: =Source!AK42 -> 53.05 | H52: =Source!AW43 -> 1 | I52: =Source!O42 -> 954.9 | J52: =IF(Source!BC43<> 0, Source!BC43, 1) -> 3.92 | K52: =Source!O43 -> 3743.21 | Q52: =Source!X42 -> 0 | R52: =Source!X43 -> 0 | S52: =Source!Y42 -> 0 | T52: =Source!Y43 -> 0 | U52: =ROUND((175/100)*ROUND(Source!R42, 2), 2) -> 0 | V52: =ROUND((0/100)*ROUND(Source!R43, 2), 2) -> 0 | AC52: 3
A53: 2,4 | B53: =Source!F44 -> 1.12-2-1167 | C53: Хомуты из оцинкованной стали с резиновыми прокладками для жесткого и скользящего крепления полипропиленовых труб, наружный диаметр 110 мм | D53: =Source!H44 -> шт. | E53: =Source!I44 -> 71 | F53: =Source!AK44 -> 54.28 | H53: =Source!AW45 -> 1 | I53: =Source!O44 -> 3853.88 | J53: =IF(Source!BC45<> 0, Source!BC45, 1) -> 0.93 | K53: =Source!O45 -> 3584.11 | Q53: =Source!X44 -> 0 | R53: =Source!X45 -> 0 | S53: =Source!Y44 -> 0 | T53: =Source!Y45 -> 0 | U53: =ROUND((175/100)*ROUND(Source!R44, 2), 2) -> 0 | V53: =ROUND((0/100)*ROUND(Source!R45, 2), 2) -> 0 | AC53: 3
C54: НР от ФОТ | D54: % | E54: =Source!BZ37 -> 109 | I54: =SUM(Q44:Q53) -> 2266.59 | J54: =Source!AT37 -> 109 | K54: =SUM(R44:R53) -> 124639.77
C55: СП от ФОТ | D55: % | E55: =Source!CA37 -> 61 | I55: =SUM(S44:S54) -> 1268.46 | J55: =Source!AU37 -> 61 | K55: =SUM(T44:T54) -> 69752.53
C56: ЗТР | D56: чел-ч | E56: =Source!AQ36 -> 56 | G56: 1,15*1,1 | H56: =Source!AV37 -> 1.067 | I56: =Source!U36 -> 161.75464
C57: Всего по позиции: | H57: =I46+I47+I49+I54+I55+SUM(I50:I53) -> 16656.06 | J57: =K46+K47+K49+K54+K55+SUM(K50:K53) -> 379801.87 | O57: =I46+I47+I49+I54+I55+SUM(I50:I53) -> 16656.06 | P57: =K46+K47+K49+K54+K55+SUM(K50:K53) -> 379801.87
A59: 3 | B59: 3.16-13-1 Поправка: О.П. п.3.4. 6 Поправка: О.П. п.3.4.30.в | C59: Прокладка трубопроводов канализации из ПВХ труб диаметром до 50 мм | D59: =Source!H46 -> 100 м | E59: =Source!I46 -> 0.72 | Q59: =Source!X46 -> 793.49 | R59: =Source!X47 -> 43633.87 | S59: =Source!Y46 -> 444.06 | T59: =Source!Y47 -> 24418.95 | U59: =ROUND((175/100)*ROUND(Source!R46, 2), 2) -> 2.64 | V59: =ROUND((0/100)*ROUND(Source!R47, 2), 2) -> 0 | AC59: 0
C60: ="Объем: "&Source!I46&"=72/"&"100" -> Объем: 0,72=72/100
C61: ЗП | F61: =Source!AO46 -> 747.52 | G61: 1,15*1,1 | H61: =Source!AV47 -> 1.067 | I61: =Source!S46 -> 726.46 | J61: =IF(Source!BA47<> 0, Source!BA47, 1) -> 54.99 | K61: =Source!S47 -> 39948.04
C62: ЭМ | F62: =Source!AM46 -> 10.1 | G62: 1,25*1,1 | H62: =Source!AV47 -> 1.067 | I62: =Source!Q46 -> 10.67 | J62: =IF(Source!BB47<> 0, Source!BB47, 1) -> 15.85 | K62: =Source!Q47 -> 169.12
C63: в т.ч. ЗПМ | F63: =Source!AN46 -> 1.43 | G63: 1,25*1,1 | H63: =Source!AV47 -> 1.067 | I63: =Source!R46 -> 1.51 | J63: =IF(Source!BS47<> 0, Source!BS47, 1) -> 54.99 | K63: =Source!R47 -> 83.03
C64: МР | F64: =Source!AL46 -> 85.16 | H64: =Source!AW47 -> 1 | I64: =Source!P46 -> 61.32 | J64: =IF(Source!BC47<> 0, Source!BC47, 1) -> 16.3 | K64: =Source!P47 -> 999.52
A65: 3,1 | B65: =Source!F48 -> КА 25 | C65: Трубы канализационные раструбные марки ПП, ГОСТ 32412-213, Д=50 9,04 = [105 / 1,2 / 9,88] + 2% Заг.скл | D65: =Source!H48 -> м | E65: =Source!I48 -> 72 | F65: =Source!AK48 -> 9.04 | H65: =Source!AW49 -> 1 | I65: =Source!O48 -> 650.88 | J65: =IF(Source!BC49<> 0, Source!BC49, 1) -> 9.88 | K65: =Source!O49 -> 6430.69 | Q65: =Source!X48 -> 0 | R65: =Source!X49 -> 0 | S65: =Source!Y48 -> 0 | T65: =Source!Y49 -> 0 | U65: =ROUND((175/100)*ROUND(Source!R48, 2), 2) -> 0 | V65: =ROUND((0/100)*ROUND(Source!R49, 2), 2) -> 0 | AC65: 3
A66: 3,2 | B66: =Source!F50 -> 1.12-5-97 | C66: Ревизия из полиэтилена низкого давления, с крышкой, для канализации, диаметр 50 мм | D66: =Source!H50 -> шт. | E66: =Source!I50 -> 2 | F66: =Source!AK50 -> 16.74 | H66: =Source!AW51 -> 1 | I66: =Source!O50 -> 33.48 | J66: =IF(Source!BC51<> 0, Source!BC51, 1) -> 3.51 | K66: =Source!O51 -> 117.51 | Q66: =Source!X50 -> 0 | R66: =Source!X51 -> 0 | S66: =Source!Y50 -> 0 | T66: =Source!Y51 -> 0 | U66: =ROUND((175/100)*ROUND(Source!R50, 2), 2) -> 0 | V66: =ROUND((0/100)*ROUND(Source!R51, 2), 2) -> 0 | AC66: 3
A67: 3,3 | B67: =Source!F52 -> 1.12-5-97 | C67: Ревизия из полиэтилена низкого давления, с крышкой, для канализации, диаметр 50 мм /прочистка | D67: =Source!H52 -> шт. | E67: =Source!I52 -> 2 | F67: =Source!AK52 -> 16.74 | H67: =Source!AW53 -> 1 | I67: =Source!O52 -> 33.48 | J67: =IF(Source!BC53<> 0, Source!BC53, 1) -> 3.51 | K67: =Source!O53 -> 117.51 | Q67: =Source!X52 -> 0 | R67: =Source!X53 -> 0 | S67: =Source!Y52 -> 0 | T67: =Source!Y53 -> 0 | U67: =ROUND((175/100)*ROUND(Source!R52, 2), 2) -> 0 | V67: =ROUND((0/100)*ROUND(Source!R53, 2), 2) -> 0 | AC67: 3
A68: 3,4 | B68: =Source!F54 -> 1.12-2-1165 | C68: Хомуты из оцинкованной стали с резиновыми прокладками для жесткого и скользящего крепления полипропиленовых труб, наружный диаметр 50 мм | D68: =Source!H54 -> шт. | E68: =Source!I54 -> 24 | F68: =Source!AK54 -> 21.9 | H68: =Source!AW55 -> 1 | I68: =Source!O54 -> 525.6 | J68: =IF(Source!BC55<> 0, Source!BC55, 1) -> 0.97 | K68: =Source!O55 -> 509.83 | Q68: =Source!X54 -> 0 | R68: =Source!X55 -> 0 | S68: =Source!Y54 -> 0 | T68: =Source!Y55 -> 0 | U68: =ROUND((175/100)*ROUND(Source!R54, 2), 2) -> 0 | V68: =ROUND((0/100)*ROUND(Source!R55, 2), 2) -> 0 | AC68: 3
C69: НР от ФОТ | D69: % | E69: =Source!BZ47 -> 109 | I69: =SUM(Q59:Q68) -> 793.49 | J69: =Source!AT47 -> 109 | K69: =SUM(R59:R68) -> 43633.87
C70: СП от ФОТ | D70: % | E70: =Source!CA47 -> 61 | I70: =SUM(S59:S69) -> 444.06 | J70: =Source!AU47 -> 61 | K70: =SUM(T59:T69) -> 24418.95
C71: ЗТР | D71: чел-ч | E71: =Source!AQ46 -> 58.4 | G71: 1,15*1,1 | H71: =Source!AV47 -> 1.067 | I71: =Source!U46 -> 56.754498
C72: Всего по позиции: | H72: =I61+I62+I64+I69+I70+SUM(I65:I68) -> 3279.44 | J72: =K61+K62+K64+K69+K70+SUM(K65:K68) -> 116345.04 | O72: =I61+I62+I64+I69+I70+SUM(I65:I68) -> 3279.44 | P72: =K61+K62+K64+K69+K70+SUM(K65:K68) -> 116345.04
A74: 4 | B74: 3.16-28-2 Поправка: О.П. п.3.4. 6 Поправка: О.П. п.3.4.30.в | C74: Врезки в действующие внутренние сети трубопроводов канализации диаметром 100 мм | D74: =Source!H56 -> 1 врезка | E74: =Source!I56 -> 3 | Q74: =Source!X56 -> 441.77 | R74: =Source!X57 -> 24292.71 | S74: =Source!Y56 -> 247.23 | T74: =Source!Y57 -> 13595 | U74: =ROUND((175/100)*ROUND(Source!R56, 2), 2) -> 1 | V74: =ROUND((0/100)*ROUND(Source!R57, 2), 2) -> 0 | AC74: 0
C75: ЗП | F75: =Source!AO56 -> 99.95 | G75: 1,15*1,1 | H75: =Source!AV57 -> 1.067 | I75: =Source!S56 -> 404.72 | J75: =IF(Source!BA57<> 0, Source!BA57, 1) -> 54.99 | K75: =Source!S57 -> 22255.55
C76: ЭМ | F76: =Source!AM56 -> 0.83 | G76: 1,25*1,1 | H76: =Source!AV57 -> 1.067 | I76: =Source!Q56 -> 3.65 | J76: =IF(Source!BB57<> 0, Source!BB57, 1) -> 16.33 | K76: =Source!Q57 -> 59.6
C77: в т.ч. ЗПМ | F77: =Source!AN56 -> 0.13 | G77: 1,25*1,1 | H77: =Source!AV57 -> 1.067 | I77: =Source!R56 -> 0.57 | J77: =IF(Source!BS57<> 0, Source!BS57, 1) -> 54.99 | K77: =Source!R57 -> 31.34
C78: МР | F78: =Source!AL56 -> 8.01 | H78: =Source!AW57 -> 1 | I78: =Source!P56 -> 24.03 | J78: =IF(Source!BC57<> 0, Source!BC57, 1) -> 21.31 | K78: =Source!P57 -> 512.08
C79: НР от ФОТ | D79: % | E79: =Source!BZ57 -> 109 | I79: =SUM(Q74:Q78) -> 441.77 | J79: =Source!AT57 -> 109 | K79: =SUM(R74:R78) -> 24292.71
C80: СП от ФОТ | D80: % | E80: =Source!CA57 -> 61 | I80: =SUM(S74:S79) -> 247.23 | J80: =Source!AU57 -> 61 | K80: =SUM(T74:T79) -> 13595
C81: ЗТР | D81: чел-ч | E81: =Source!AQ56 -> 8.94 | G81: 1,15*1,1 | H81: =Source!AV57 -> 1.067 | I81: =Source!U56 -> 36.200429
C82: Всего по позиции: | H82: =I75+I76+I78+I79+I80+0 -> 1121.4 | J82: =K75+K76+K78+K79+K80+0 -> 60714.94 | O82: =I75+I76+I78+I79+I80+0 -> 1121.4 | P82: =K75+K76+K78+K79+K80+0 -> 60714.94
A84: 5 | B84: 3.16-33-1 Поправка: О.П. п.3.4. 6 Поправка: О.П. п.3.4.30.в | C84: Установка противопожарных муфт на канализационных стояках из полипропиленовых труб в междуэтажных перекрытиях, муфт обжимных | D84: =Source!H58 -> 100 шт. | E84: =Source!I58 -> 0.35 | Q84: =Source!X58 -> 94.82 | R84: =Source!X59 -> 5214.1 | S84: =Source!Y58 -> 53.06 | T84: =Source!Y59 -> 2917.98 | U84: =ROUND((175/100)*ROUND(Source!R58, 2), 2) -> 0 | V84: =ROUND((0/100)*ROUND(Source!R59, 2), 2) -> 0 | AC84: 0
C85: ="Объем: "&Source!I58&"=(19+"&"16)/"&"100" -> Объем: 0,35=(19+16)/100
C86: ЗП | F86: =Source!AO58 -> 184.13 | G86: 1,15*1,1 | H86: =Source!AV59 -> 1.067 | I86: =Source!S58 -> 86.99 | J86: =IF(Source!BA59<> 0, Source!BA59, 1) -> 54.99 | K86: =Source!S59 -> 4783.58
A87: 5,1 | B87: =Source!F60 -> 1.12-5-456 | C87: Муфта противопожарная из нержавеющей стали, с вкладышем из терморасширяющейся резины, для трубы диаметром 110 мм | D87: =Source!H60 -> шт. | E87: =Source!I60 -> 19 | F87: =Source!AK60 -> 265.24 | H87: =Source!AW61 -> 1 | I87: =Source!O60 -> 5039.56 | J87: =IF(Source!BC61<> 0, Source!BC61, 1) -> 0.83 | K87: =Source!O61 -> 4182.83 | Q87: =Source!X60 -> 0 | R87: =Source!X61 -> 0 | S87: =Source!Y60 -> 0 | T87: =Source!Y61 -> 0 | U87: =ROUND((175/100)*ROUND(Source!R60, 2), 2) -> 0 | V87: =ROUND((0/100)*ROUND(Source!R61, 2), 2) -> 0 | AC87: 3
A88: 5,2 | B88: =Source!F62 -> 1.12-5-542 | C88: Муфта противопожарная из нержавеющей стали, с вкладышем из терморасширяющейся резины, для трубы диаметром 50 мм | D88: =Source!H62 -> шт. | E88: =Source!I62 -> 16 | F88: =Source!AK62 -> 181.59 | H88: =Source!AW63 -> 1 | I88: =Source!O62 -> 2905.44 | J88: =IF(Source!BC63<> 0, Source!BC63, 1) -> 0.76 | K88: =Source!O63 -> 2208.13 | Q88: =Source!X62 -> 0 | R88: =Source!X63 -> 0 | S88: =Source!Y62 -> 0 | T88: =Source!Y63 -> 0 | U88: =ROUND((175/100)*ROUND(Source!R62, 2), 2) -> 0 | V88: =ROUND((0/100)*ROUND(Source!R63, 2), 2) -> 0 | AC88: 3
C89: НР от ФОТ | D89: % | E89: =Source!BZ59 -> 109 | I89: =SUM(Q84:Q88) -> 94.82 | J89: =Source!AT59 -> 109 | K89: =SUM(R84:R88) -> 5214.1
C90: СП от ФОТ | D90: % | E90: =Source!CA59 -> 61 | I90: =SUM(S84:S89) -> 53.06 | J90: =Source!AU59 -> 61 | K90: =SUM(T84:T89) -> 2917.98
C91: ЗТР | D91: чел-ч | E91: =Source!AQ58 -> 14.63 | G91: 1,15*1,1 | H91: =Source!AV59 -> 1.067 | I91: =Source!U58 -> 6.9114205
C92: Всего по позиции: | H92: =I86+I89+I90+SUM(I87:I88) -> 8179.87 | J92: =K86+K89+K90+SUM(K87:K88) -> 19306.62 | O92: =I86+I89+I90+SUM(I87:I88) -> 8179.87 | P92: =K86+K89+K90+SUM(K87:K88) -> 19306.62
A95: =CONCATENATE("Итого по подразделу: ",IF(Source!G65<>"Новый подраздел", Source!G65, "")) -> Итого по подразделу: Монтажные работы | H95: =SUM(O31:O94) -> 51577.52 | J95: =SUM(P31:P94) -> 655463.71
A96: Итого по ТСН-2001.16 | I96: =SUM(W31:W95) -> 0 | J96: =SUM(X31:X95) -> 0
A97: Итого возвратных сумм | I97: =SUM(Y31:Y96) -> 0 | J97: =SUM(Z31:Z96) -> 0
A99: =CONCATENATE("Итого по разделу: ",IF(Source!G95<>"Новый раздел", Source!G95, "")) -> Итого по разделу: Канализация хозяйственно-бытовая (К1) (подвал) | H99: =SUM(O29:O98) -> 51577.52 | J99: =SUM(P29:P98) -> 655463.71 | AQ99: =CONCATENATE("Итого по разделу: ",IF(Source!G95<>"Новый раздел", Source!G95, "")) -> Итого по разделу: Канализация хозяйственно-бытовая (К1) (подвал)
A100: Итого по ТСН-2001.16 | I100: =SUM(W29:W99) -> 0 | J100: =SUM(X29:X99) -> 0
A101: Итого возвратных сумм | I101: =SUM(Y29:Y100) -> 0 | J101: =SUM(Z29:Z100) -> 0
A103: =CONCATENATE("Раздел: ",IF(Source!G125<>"Новый раздел", Source!G125, "")) -> Раздел: Канализация хозяйственно-бытовая напорная (К1н) (подвал)
A105: =CONCATENATE("Подраздел: ",IF(Source!G129<>"Новый подраздел", Source!G129, "")) -> Подраздел: Монтажные работы
A106: 6 | B106: 3.16-7-5 Поправка: О.П. п.3.4. 6 Поправка: О.П. п.3.4.30.в | C106: Прокладка трубопроводов водоснабжения из стальных водогазопроводных оцинкованных труб диаметром 40 мм | D106: =Source!H133 -> 100 м трубопровода | E106: =Source!I133 -> 0.1 | Q106: =Source!X133 -> 63.54 | R106: =Source!X134 -> 3493.85 | S106: =Source!Y133 -> 35.56 | T106: =Source!Y134 -> 1955.28 | U106: =ROUND((175/100)*ROUND(Source!R133, 2), 2) -> 1.56 | V106: =ROUND((0/100)*ROUND(Source!R134, 2), 2) -> 0 | AC106: 0
C107: ="Объем: "&Source!I133&"=10/"&"100" -> Объем: 0,1=10/100
C108: ЗП | F108: =Source!AO133 -> 425.29 | G108: 1,15*1,1 | H108: =Source!AV134 -> 1.067 | I108: =Source!S133 -> 57.4 | J108: =IF(Source!BA134<> 0, Source!BA134, 1) -> 54.99 | K108: =Source!S134 -> 3156.43
C109: ЭМ | F109: =Source!AM133 -> 47.77 | G109: 1,25*1,1 | H109: =Source!AV134 -> 1.067 | I109: =Source!Q133 -> 7.01 | J109: =IF(Source!BB134<> 0, Source!BB134, 1) -> 15.37 | K109: =Source!Q134 -> 107.74
C110: в т.ч. ЗПМ | F110: =Source!AN133 -> 6.06 | G110: 1,25*1,1 | H110: =Source!AV134 -> 1.067 | I110: =Source!R133 -> 0.89 | J110: =IF(Source!BS134<> 0, Source!BS134, 1) -> 54.99 | K110: =Source!R134 -> 48.94
C111: МР | F111: =Source!AL133 -> 46.02 | H111: =Source!AW134 -> 1 | I111: =Source!P133 -> 4.6 | J111: =IF(Source!BC134<> 0, Source!BC134, 1) -> 6.21 | K111: =Source!P134 -> 28.57
A112: 6,1 | B112: =Source!F135 -> 1.12-2-1164 | C112: Хомуты из оцинкованной стали с резиновыми прокладками для жесткого и скользящего крепления полипропиленовых труб, наружный диаметр 32 мм /ф40мм | D112: =Source!H135 -> шт. | E112: =Source!I135 -> 4 | F112: =Source!AK135 -> 19.61 | H112: =Source!AW136 -> 1 | I112: =Source!O135 -> 78.44 | J112: =IF(Source!BC136<> 0, Source!BC136, 1) -> 1 | K112: =Source!O136 -> 78.44 | Q112: =Source!X135 -> 0 | R112: =Source!X136 -> 0 | S112: =Source!Y135 -> 0 | T112: =Source!Y136 -> 0 | U112: =ROUND((175/100)*ROUND(Source!R135, 2), 2) -> 0 | V112: =ROUND((0/100)*ROUND(Source!R136, 2), 2) -> 0 | AC112: 3
A113: 6,2 | B113: =Source!F137 -> 1.13-4-129 | C113: Кран шаровой, латунный, полнопроходной, муфтовый, 11б27п1, номинальное давление PN 1,6 МПа, номинальный диаметр DN 40 мм | D113: =Source!H137 -> шт. | E113: =Source!I137 -> 1 | F113: =Source!AK137 -> 210.17 | H113: =Source!AW138 -> 1 | I113: =Source!O137 -> 210.17 | J113: =IF(Source!BC138<> 0, Source!BC138, 1) -> 3.3 | K113: =Source!O138 -> 693.56 | Q113: =Source!X137 -> 0 | R113: =Source!X138 -> 0 | S113: =Source!Y137 -> 0 | T113: =Source!Y138 -> 0 | U113: =ROUND((175/100)*ROUND(Source!R137, 2), 2) -> 0 | V113: =ROUND((0/100)*ROUND(Source!R138, 2), 2) -> 0 | AC113: 3
A114: 6,3 | B114: =Source!F139 -> 1.12-1-56 | C114: Узел трубопровода из стальных водогазопроводных оцинкованных труб, с гильзами, для водоснабжения, диаметр условного прохода 40 мм | D114: =Source!H139 -> м | E114: =Source!I139 -> 10 | F114: =Source!AK139 -> 61.58 | H114: =Source!AW140 -> 1 | I114: =Source!O139 -> 615.8 | J114: =IF(Source!BC140<> 0, Source!BC140, 1) -> 11.88 | K114: =Source!O140 -> 7315.7 | Q114: =Source!X139 -> 0 | R114: =Source!X140 -> 0 | S114: =Source!Y139 -> 0 | T114: =Source!Y140 -> 0 | U114: =ROUND((175/100)*ROUND(Source!R139, 2), 2) -> 0 | V114: =ROUND((0/100)*ROUND(Source!R140, 2), 2) -> 0 | AC114: 3
C115: НР от ФОТ | D115: % | E115: =Source!BZ134 -> 109 | I115: =SUM(Q106:Q114) -> 63.54 | J115: =Source!AT134 -> 109 | K115: =SUM(R106:R114) -> 3493.85
C116: СП от ФОТ | D116: % | E116: =Source!CA134 -> 61 | I116: =SUM(S106:S115) -> 35.56 | J116: =Source!AU134 -> 61 | K116: =SUM(T106:T115) -> 1955.28
...

Sheet Ведомость объемов работ
A1: =Source!B1 -> Smeta.RU (495) 974-1589
E3: "УТВЕРЖДАЮ"
D5: ___________________________
D7: ___________________________
D9: " ___ " ___________ 20 ___ г.
B12: =CONCATENATE("Ведомость объемов работ ", IF(Source!AN15<>"", Source!AN15," ")) -> Ведомость объемов работ
B13: =CONCATENATE(Source!F12, " ", Source!G12) -> Новый объект (ТСН-2001 (Мосгосэкспертиза)) 02-01-05 Система водоотведения
A16: № п/п | B16: № в ЛСР | C16: Наименование работ и затрат | D16: Единица измерения | E16: Количество | F16: Ссылка на чертежи, спецификации | G16: Формула расчета, расчет объемов работ и расхода материалов | H16: Примечание
A17: 1 | B17: 2 | C17: 3 | D17: 4 | E17: 5 | F17: 6 | G17: 7 | H17: 8
A18: =CONCATENATE("Локальная смета: ", Source!G20) -> Локальная смета: Система водоотведения
A19: =CONCATENATE("Раздел: ", Source!G24) -> Раздел: Канализация хозяйственно-бытовая (К1) (подвал)
A20: =CONCATENATE("Подраздел: ", Source!G28) -> Подраздел: Монтажные работы
A21: 1 | B21: =Source!E32 -> 1 | C21: =Source!G32 -> Прокладка трубопроводов канализации из чугунных безраструбных труб, диаметр 50 мм | D21: 100 м | E21: =Source!I32 -> 0.16 | F21: =Source!U28 | G21: ="=16/"&"100" -> =16/100
A22: 1.1 | B22: =Source!E34 -> 1,1 | C22: =Source!G34 -> Комплект деталей трубопроводов из чугуна с мелкодисперсным графитом с внутренним эпоксидным покрытием, наружным слоем краснокоричневой грунтовки (безраструбные трубы, фасонные части, крепеж), диаметр условного прохода 50 мм | D22: м | E22: =Source!I34 -> 16 | F22: =Source!U28
A23: 2 | B23: =Source!E36 -> 2 | C23: =Source!G36 -> Прокладка трубопроводов канализации из ПВХ труб диаметром 100 мм - 150 мм | D23: 100 м | E23: =Source!I36 -> 2.14 | F23: =Source!U28 | G23: ="=214/"&"100" -> =214/100
A24: 2.1 | B24: =Source!E38 -> 2,1 | C24: =Source!G38 -> Трубы канализационные раструбные марки ПП, ГОСТ 32412-213, Д=110 | D24: м | E24: =Source!I38 -> 214 | F24: =Source!U28
A25: 2.2 | B25: =Source!E40 -> 2,2 | C25: =Source!G40 -> Ревизия из полиэтилена, диаметр 110 мм | D25: шт. | E25: =Source!I40 -> 3 | F25: =Source!U28
A26: 2.3 | B26: =Source!E42 -> 2,3 | C26: =Source!G42 -> Ревизия из полиэтилена, диаметр 110 мм /прочистки | D26: шт. | E26: =Source!I42 -> 18 | F26: =Source!U28
A27: 2.4 | B27: =Source!E44 -> 2,4 | C27: =Source!G44 -> Хомуты из оцинкованной стали с резиновыми прокладками для жесткого и скользящего крепления полипропиленовых труб, наружный диаметр 110 мм | D27: шт. | E27: =Source!I44 -> 71 | F27: =Source!U28
A28: 3 | B28: =Source!E46 -> 3 | C28: =Source!G46 -> Прокладка трубопроводов канализации из ПВХ труб диаметром до 50 мм | D28: 100 м | E28: =Source!I46 -> 0.72 | F28: =Source!U28 | G28: ="=72/"&"100" -> =72/100
A29: 3.1 | B29: =Source!E48 -> 3,1 | C29: =Source!G48 -> Трубы канализационные раструбные марки ПП, ГОСТ 32412-213, Д=50 | D29: м | E29: =Source!I48 -> 72 | F29: =Source!U28
A30: 3.2 | B30: =Source!E50 -> 3,2 | C30: =Source!G50 -> Ревизия из полиэтилена низкого давления, с крышкой, для канализации, диаметр 50 мм | D30: шт. | E30: =Source!I50 -> 2 | F30: =Source!U28
A31: 3.3 | B31: =Source!E52 -> 3,3 | C31: =Source!G52 -> Ревизия из полиэтилена низкого давления, с крышкой, для канализации, диаметр 50 мм /прочистка | D31: шт. | E31: =Source!I52 -> 2 | F31: =Source!U28
A32: 3.4 | B32: =Source!E54 -> 3,4 | C32: =Source!G54 -> Хомуты из оцинкованной стали с резиновыми прокладками для жесткого и скользящего крепления полипропиленовых труб, наружный диаметр 50 мм | D32: шт. | E32: =Source!I54 -> 24 | F32: =Source!U28
A33: 4 | B33: =Source!E56 -> 4 | C33: =Source!G56 -> Врезки в действующие внутренние сети трубопроводов канализации диаметром 100 мм | D33: 1 врезка | E33: =Source!I56 -> 3 | F33: =Source!U28 | G33: =Source!I56 -> 3
A34: 5 | B34: =Source!E58 -> 5 | C34: =Source!G58 -> Установка противопожарных муфт на канализационных стояках из полипропиленовых труб в междуэтажных перекрытиях, муфт обжимных | D34: 100 шт. | E34: =Source!I58 -> 0.35 | F34: =Source!U28 | G34: ="=(19+"&"16)/"&"100" -> =(19+16)/100
A35: 5.1 | B35: =Source!E60 -> 5,1 | C35: =Source!G60 -> Муфта противопожарная из нержавеющей стали, с вкладышем из терморасширяющейся резины, для трубы диаметром 110 мм | D35: шт. | E35: =Source!I60 -> 19 | F35: =Source!U28
A36: 5.2 | B36: =Source!E62 -> 5,2 | C36: =Source!G62 -> Муфта противопожарная из нержавеющей стали, с вкладышем из терморасширяющейся резины, для трубы диаметром 50 мм | D36: шт. | E36: =Source!I62 -> 16 | F36: =Source!U28
A37: =CONCATENATE("Раздел: ", Source!G125) -> Раздел: Канализация хозяйственно-бытовая напорная (К1н) (подвал)
A38: =CONCATENATE("Подраздел: ", Source!G129) -> Подраздел: Монтажные работы
A39: 6 | B39: =Source!E133 -> 6 | C39: =Source!G133 -> Прокладка трубопроводов водоснабжения из стальных водогазопроводных оцинкованных труб диаметром 40 мм | D39: 100 м трубопровода | E39: =Source!I133 -> 0.1 | F39: =Source!U129 | G39: ="=10/"&"100" -> =10/100
A40: 6.1 | B40: =Source!E135 -> 6,1 | C40: =Source!G135 -> Хомуты из оцинкованной стали с резиновыми прокладками для жесткого и скользящего крепления полипропиленовых труб, наружный диаметр 32 мм /ф40мм | D40: шт. | E40: =Source!I135 -> 4 | F40: =Source!U129
A41: 6.2 | B41: =Source!E137 -> 6,2 | C41: =Source!G137 -> Кран шаровой, латунный, полнопроходной, муфтовый, 11б27п1, номинальное давление PN 1,6 МПа, номинальный диаметр DN 40 мм | D41: шт. | E41: =Source!I137 -> 1 | F41: =Source!U129
A42: 6.3 | B42: =Source!E139 -> 6,3 | C42: =Source!G139 -> Узел трубопровода из стальных водогазопроводных оцинкованных труб, с гильзами, для водоснабжения, диаметр условного прохода 40 мм | D42: м | E42: =Source!I139 -> 10 | F42: =Source!U129
A43: 7 | B43: =Source!E141 -> 7 | C43: =Source!G141 -> Клапан обратный общего назначения, латунный, с внутренней резьбой, температура до +100°С, номинальное давление PN 1,0 МПа, номинальный диаметр DN 40 мм | D43: шт. | E43: =Source!I141 -> 1 | F43: =Source!U129 | G43: =Source!I141 -> 1
A44: 8 | B44: =Source!E147 -> 8 | C44: =Source!G147 -> Монтаж механизма исполнительного массой до 20 кг | D44: 1 ШТ. | E44: =Source!I147 -> 1 | F44: =Source!U129 | G44: =Source!I147 -> 1
A45: 8.1 | B45: =Source!E149 -> 8,1 | C45: =Source!G149 -> Насосная установка Q=3,75м^3/ч; Н=8,8м; U=1х220В; N=0,6кВт CITILIFT TRIO | D45: шт. | E45: =Source!I149 -> 1 | F45: =Source!U129
A46: 9 | B46: =Source!E155 -> 9 | C46: =Source!G155 -> Прокладка трубопроводов водоснабжения из стальных водогазопроводных оцинкованных труб диаметром 32 мм | D46: 100 м трубопровода | E46: =Source!I155 -> 0.1 | F46: =Source!U129 | G46: ="=10/"&"100" -> =10/100
A47: 9.1 | B47: =Source!E157 -> 9,1 | C47: =Source!G157 -> Хомуты из оцинкованной стали с резиновыми прокладками для жесткого и скользящего крепления полипропиленовых труб, наружный диаметр 32 мм | D47: шт. | E47: =Source!I157 -> 5 | F47: =Source!U129
A48: 9.2 | B48: =Source!E159 -> 9,2 | C48: =Source!G159 -> Кран шаровой, латунный, полнопроходной, муфтовый, 11б27п1, номинальное давление PN 1,6 МПа, номинальный диаметр DN 32 мм | D48: шт. | E48: =Source!I159 -> 1 | F48: =Source!U129
A49: 9.3 | B49: =Source!E161 -> 9,3 | C49: =Source!G161 -> Муфта из полипропилена PP-R, ГОСТ 32415-2013, комбинированная с металлом, под ключ, номинальное давление PN 25, номинальный диаметр DN 32 мм, наружная резьба 1'' | D49: шт. | E49: =Source!I161 -> 2 | F49: =Source!U129
A50: 9.4 | B50: =Source!E163 -> 9,4 | C50: =Source!G163 -> Узел трубопровода из стальных водогазопроводных оцинкованных труб, с гильзами, для водоснабжения, диаметр условного прохода 32 мм | D50: м | E50: =Source!I163 -> 10 | F50: =Source!U129
A51: 10 | B51: =Source!E165 -> 10 | C51: =Source!G165 -> Клапан обратный общего назначения, латунный, с внутренней резьбой, температура до +100°С, номинальное давление PN 1,0 МПа, номинальный диаметр DN 32 мм | D51: шт. | E51: =Source!I165 -> 1 | F51: =Source!U129 | G51: =Source!I165 -> 1
A52: 11 | B52: =Source!E171 -> 11 | C52: =Source!G171 -> Гидравлическое испытание трубопроводов систем отопления, водопровода и горячего водоснабжения диаметром до 50 мм | D52: 100 м трубопровода | E52: =Source!I171 -> 0.2 | F52: =Source!U129 | G52: ="=(10+"&"10)/"&"100" -> =(10+10)/100
A53: 12 | B53: =Source!E173 -> 12 | C53: =Source!G173 -> Монтаж механизма исполнительного массой до 20 кг | D53: 1 ШТ. | E53: =Source!I173 -> 1 | F53: =Source!U129 | G53: =Source!I173 -> 1
A54: 12.1 | B54: =Source!E175 -> 12,1 | C54: =Source!G175 -> Канализационная установка Q=1,67л//с; Н=6м; U=1х220В; N=0,3кВт САН-300 Профи | D54: шт. | E54: =Source!I175 -> 1 | F54: =Source!U129
A55: =CONCATENATE("Раздел: ", Source!G238) -> Раздел: Канализация хозяйственно-бытовая (К1) (Надземная часть. Стояки и отводы)
A56: =CONCATENATE("Подраздел: ", Source!G242) -> Подраздел: Монтажные работы
A57: 13 | B57: =Source!E246 -> 13 | C57: =Source!G246 -> Прокладка трубопроводов канализации из ПВХ труб диаметром 100 мм - 150 мм | D57: 100 м | E57: =Source!I246 -> 2.13 | F57: =Source!U242 | G57: ="=213/"&"100" -> =213/100
A58: 13.1 | B58: =Source!E248 -> 13,1 | C58: =Source!G248 -> Трубы канализационные раструбные марки ПП, ГОСТ 32412-213, Д=110 | D58: м | E58: =Source!I248 -> 213 | F58: =Source!U242
A59: 13.2 | B59: =Source!E250 -> 13,2 | C59: =Source!G250 -> Ревизия из полиэтилена, диаметр 110 мм | D59: шт. | E59: =Source!I250 -> 19 | F59: =Source!U242
A60: 13.3 | B60: =Source!E252 -> 13,3 | C60: =Source!G252 -> Ревизия из полиэтилена, диаметр 110 мм /прочистки | D60: шт. | E60: =Source!I252 -> 30 | F60: =Source!U242
A61: 13.4 | B61: =Source!E254 -> 13,4 | C61: =Source!G254 -> Хомуты из оцинкованной стали с резиновыми прокладками для жесткого и скользящего крепления полипропиленовых труб, наружный диаметр 110 мм | D61: шт. | E61: =Source!I254 -> 88 | F61: =Source!U242
A62: 14 | B62: =Source!E256 -> 14 | C62: =Source!G256 -> Прокладка трубопроводов канализации из ПВХ труб диаметром до 50 мм | D62: 100 м | E62: =Source!I256 -> 2.64 | F62: =Source!U242 | G62: ="=264/"&"100" -> =264/100
A63: 14.1 | B63: =Source!E258 -> 14,1 | C63: =Source!G258 -> Трубы канализационные раструбные марки ПП, ГОСТ 32412-213, Д=50 | D63: м | E63: =Source!I258 -> 264 | F63: =Source!U242
A64: 14.2 | B64: =Source!E260 -> 14,2 | C64: =Source!G260 -> Ревизия из полиэтилена низкого давления, с крышкой, для канализации, диаметр 50 мм | D64: шт. | E64: =Source!I260 -> 35 | F64: =Source!U242
A65: 14.3 | B65: =Source!E262 -> 14,3 | C65: =Source!G262 -> Ревизия из полиэтилена низкого давления, с крышкой, для канализации, диаметр 50 мм /прочистка | D65: шт. | E65: =Source!I262 -> 13 | F65: =Source!U242
A66: 14.4 | B66: =Source!E264 -> 14,4 | C66: =Source!G264 -> Хомуты из оцинкованной стали с резиновыми прокладками для жесткого и скользящего крепления полипропиленовых труб, наружный диаметр 50 мм | D66: шт. | E66: =Source!I264 -> 71 | F66: =Source!U242
A67: 15 | B67: =Source!E266 -> 15 | C67: =Source!G266 -> Установка противопожарных муфт на канализационных стояках из полипропиленовых труб в междуэтажных перекрытиях, муфт обжимных | D67: 100 шт. | E67: =Source!I266 -> 0.97 | F67: =Source!U242 | G67: ="=(43+"&"54)/"&"100" -> =(43+54)/100
A68: 15.1 | B68: =Source!E268 -> 15,1 | C68: =Source!G268 -> Муфта противопожарная из нержавеющей стали, с вкладышем из терморасширяющейся резины, для трубы диаметром 110 мм | D68: шт. | E68: =Source!I268 -> 43 | F68: =Source!U242
A69: 15.2 | B69: =Source!E270 -> 15,2 | C69: =Source!G270 -> Муфта противопожарная из нержавеющей стали, с вкладышем из терморасширяющейся резины, для трубы диаметром 50 мм | D69: шт. | E69: =Source!I270 -> 54 | F69: =Source!U242
A70: 16 | B70: =Source!E272 -> 16 | C70: =Source!G272 -> Установка прибора на резьбовых соединениях | D70: 1 ШТ. | E70: =Source!I272 -> 11 | F70: =Source!U242 | G70: =Source!I272 -> 11
A71: 16.1 | B71: =Source!E274 -> 16,1 | C71: =Source!G274 -> Клапаны воздушные полипропиленовые для невентилируемых канализационных стояков c резиновой мембраной, двойной изолированной стенкой, уменьшителем, защитной сеткой, диаметры 50, 75, 110 мм | D71: шт. | E71: =Source!I274 -> 11 | F71: =Source!U242
A72: =CONCATENATE("Раздел: ", Source!G341) -> Раздел: Канализация производственная (К3) (подвал)
A73: =CONCATENATE("Подраздел: ", Source!G345) -> Подраздел: Монтажные работы
A74: 17 | B74: =Source!E349 -> 17 | C74: =Source!G349 -> Прокладка трубопроводов канализации из чугунных безраструбных труб, диаметр 50 мм | D74: 100 м | E74: =Source!I349 -> 0.21 | F74: =Source!U345 | G74: ="=21/"&"100" -> =21/100
A75: 17.1 | B75: =Source!E351 -> 17,1 | C75: =Source!G351 -> Комплект деталей трубопроводов из чугуна с мелкодисперсным графитом с внутренним эпоксидным покрытием, наружным слоем краснокоричневой грунтовки (безраструбные трубы, фасонные части, крепеж), диаметр условного прохода 50 мм | D75: м | E75: =Source!I351 -> 21 | F75: =Source!U345
A76: 17.2 | B76: =Source!E353 -> 17,2 | C76: =Source!G353 -> Переходник с ПВХ/ПП на чугун 50/50 | D76: шт. | E76: =Source!I353 -> 18 | F76: =Source!U345
A77: 18 | B77: =Source!E355 -> 18 | C77: =Source!G355 -> Прокладка трубопроводов канализации из чугунных безраструбных труб, диаметр 100 мм | D77: 100 м | E77: =Source!I355 -> 0.78 | F77: =Source!U345 | G77: ="=78/"&"100" -> =78/100
A78: 18.1 | B78: =Source!E357 -> 18,1 | C78: =Source!G357 -> Комплект деталей трубопроводов из чугуна с мелкодисперсным графитом с внутренним эпоксидным покрытием, наружным слоем краснокоричневой грунтовки (безраструбные трубы, фасонные части, крепеж), диаметр условного прохода 100 мм | D78: м | E78: =Source!I357 -> 78 | F78: =Source!U345
A79: 18.2 | B79: =Source!E359 -> 18,2 | C79: =Source!G359 -> Ревизия чугунная, диаметр условного прохода 100 мм | D79: шт. | E79: =Source!I359 -> 1 | F79: =Source!U345
A80: 18.3 | B80: =Source!E361 -> 18,3 | C80: =Source!G361 -> Ревизия чугунная, диаметр условного прохода 100 мм /прочистки | D80: шт. | E80: =Source!I361 -> 4 | F80: =Source!U345
A81: 18.4 | B81: =Source!E363 -> 18,4 | C81: =Source!G363 -> Переходник с ПВХ/ПП на чугун 100/110 | D81: шт. | E81: =Source!I363 -> 11 | F81: =Source!U345
A82: 19 | B82: =Source!E365 -> 19 | C82: =Source!G365 -> Врезки в действующие внутренние сети трубопроводов канализации диаметром 100 мм | D82: 1 врезка | E82: =Source!I365 -> 1 | F82: =Source!U345 | G82: =Source!I365 -> 1
A83: 20 | B83: =Source!E367 -> 20 | C83: =Source!G367 -> Установка противопожарных муфт на канализационных стояках из полипропиленовых труб в междуэтажных перекрытиях, муфт обжимных | D83: 100 шт. | E83: =Source!I367 -> 0.29 | F83: =Source!U345 | G83: ="=(18+"&"11)/"&"100" -> =(18+11)/100
A84: 20.1 | B84: =Source!E369 -> 20,1 | C84: =Source!G369 -> Муфта противопожарная из нержавеющей стали, с вкладышем из терморасширяющейся резины, для трубы диаметром 110 мм | D84: шт. | E84: =Source!I369 -> 18 | F84: =Source!U345
A85: 20.2 | B85: =Source!E371 -> 20,2 | C85: =Source!G371 -> Муфта противопожарная из нержавеющей стали, с вкладышем из терморасширяющейся резины, для трубы диаметром 50 мм | D85: шт. | E85: =Source!I371 -> 11 | F85: =Source!U345
A86: =CONCATENATE("Раздел: ", Source!G434) -> Раздел: Канализация производственная напорная (К3н) (подвал)
A87: =CONCATENATE("Подраздел: ", Source!G438) -> Подраздел: Монтажные работы
A88: 21 | B88: =Source!E442 -> 21 | C88: =Source!G442 -> Прокладка трубопроводов водоснабжения из стальных водогазопроводных оцинкованных труб диаметром 40 мм | D88: 100 м трубопровода | E88: =Source!I442 -> 0.1 | F88: =Source!U438 | G88: ="=10/"&"100" -> =10/100
A89: 21.1 | B89: =Source!E444 -> 21,1 | C89: =Source!G444 -> Хомуты из оцинкованной стали с резиновыми прокладками для жесткого и скользящего крепления полипропиленовых труб, наружный диаметр 32 мм /ф40мм | D89: шт. | E89: =Source!I444 -> 4 | F89: =Source!U438
A90: 21.2 | B90: =Source!E446 -> 21,2 | C90: =Source!G446 -> Кран шаровой, латунный, полнопроходной, муфтовый, 11б27п1, номинальное давление PN 1,6 МПа, номинальный диаметр DN 32 мм | D90: шт. | E90: =Source!I446 -> 1 | F90: =Source!U438
A91: 21.3 | B91: =Source!E448 -> 21,3 | C91: =Source!G448 -> Узел трубопровода из стальных водогазопроводных оцинкованных труб, с гильзами, для водоснабжения, диаметр условного прохода 40 мм | D91: м | E91: =Source!I448 -> 10 | F91: =Source!U438
A92: 22 | B92: =Source!E450 -> 22 | C92: =Source!G450 -> Клапан обратный общего назначения, латунный, с внутренней резьбой, температура до +100°С, номинальное давление PN 1,0 МПа, номинальный диаметр DN 32 мм | D92: шт. | E92: =Source!I450 -> 1 | F92: =Source!U438 | G92: =Source!I450 -> 1
A93: 23 | B93: =Source!E456 -> 23 | C93: =Source!G456 -> Гидравлическое испытание трубопроводов систем отопления, водопровода и горячего водоснабжения диаметром до 50 мм | D93: 100 м трубопровода | E93: =Source!I456 -> 0.1 | F93: =Source!U438 | G93: ="=10/"&"100" -> =10/100
A94: 24 | B94: =Source!E458 -> 24 | C94: =Source!G458 -> Монтаж механизма исполнительного массой до 20 кг | D94: 1 ШТ. | E94: =Source!I458 -> 1 | F94: =Source!U438 | G94: =Source!I458 -> 1
A95: 24.1 | B95: =Source!E460 -> 24,1 | C95: =Source!G460 -> Канализационная установка Q=1,67л//с; Н=6м; U=1х220В; N=0,3кВт САН-300 Профи | D95: шт. | E95: =Source!I460 -> 1 | F95: =Source!U438
A96: =CONCATENATE("Раздел: ", Source!G523) -> Раздел: Канализация производственная (К3) (Надземная часть. Стояки и отводы)
A97: =CONCATENATE("Подраздел: ", Source!G527) -> Подраздел: Монтажные работы
A98: 25 | B98: =Source!E531 -> 25 | C98: =Source!G531 -> Прокладка трубопроводов канализации из ПВХ труб диаметром до 50 мм | D98: 100 м | E98: =Source!I531 -> 0.53 | F98: =Source!U527 | G98: ="=53/"&"100" -> =53/100
A99: 25.1 | B99: =Source!E533 -> 25,1 | C99: =Source!G533 -> Трубы канализационные раструбные марки ПП, ГОСТ 32412-213, Д=50 | D99: м | E99: =Source!I533 -> 53 | F99: =Source!U527
A100: 25.2 | B100: =Source!E535 -> 25,2 | C100: =Source!G535 -> Ревизия из полиэтилена низкого давления, с крышкой, для канализации, диаметр 50 мм /прочистка | D100: шт. | E100: =Source!I535 -> 11 | F100: =Source!U527
A101: 25.3 | B101: =Source!E537 -> 25,3 | C101: =Source!G537 -> Хомуты из оцинкованной стали с резиновыми прокладками для жесткого и скользящего крепления полипропиленовых труб, наружный диаметр 50 мм | D101: шт. | E101: =Source!I537 -> 17 | F101: =Source!U527
A102: 26 | B102: =Source!E539 -> 26 | C102: =Source!G539 -> Прокладка трубопроводов канализации из ПВХ труб диаметром 100 мм - 150 мм | D102: 100 м | E102: =Source!I539 -> 0.38 | F102: =Source!U527 | G102: ="=38/"&"100" -> =38/100
A103: 26.1 | B103: =Source!E541 -> 26,1 | C103: =Source!G541 -> Трубы канализационные раструбные марки ПП, ГОСТ 32412-213, Д=110 | D103: м | E103: =Source!I541 -> 38 | F103: =Source!U527
A104: 26.2 | B104: =Source!E543 -> 26,2 | C104: =Source!G543 -> Ревизия из полиэтилена, диаметр 110 мм | D104: шт. | E104: =Source!I543 -> 2 | F104: =Source!U527
A105: 26.3 | B105: =Source!E545 -> 26,3 | C105: =Source!G545 -> Ревизия из полиэтилена, диаметр 110 мм /прочистки | D105: шт. | E105: =Source!I545 -> 10 | F105: =Source!U527
A106: 26.4 | B106: =Source!E547 -> 26,4 | C106: =Source!G547 -> Хомуты из оцинкованной стали с резиновыми прокладками для жесткого и скользящего крепления полипропиленовых труб, наружный диаметр 110 мм | D106: шт. | E106: =Source!I547 -> 12 | F106: =Source!U527
A107: 27 | B107: =Source!E549 -> 27 | C107: =Source!G549 -> Установка противопожарных муфт на канализационных стояках из полипропиленовых труб в междуэтажных перекрытиях, муфт обжимных | D107: 100 шт. | E107: =Source!I549 -> 0.03 | F107: =Source!U527 | G107: ="=3/"&"100" -> =3/100
A108: 27.1 | B108: =Source!E551 -> 27,1 | C108: =Source!G551 -> Муфта противопожарная из нержавеющей стали, с вкладышем из терморасширяющейся резины, для трубы диаметром 110 мм | D108: шт. | E108: =Source!I551 -> 3 | F108: =Source!U527
...

Sheet Source
A1: 0 | B1: Smeta.RU (495) 974-1589 | D1: _PS_ | F1: 0 | G1: 0 | H1: 0 | I1: Smeta.RU | K1: 1 | L1: 74402 | M1: 10 | N1: 12 | O1: 1 | P1: 0 | Q1: 0
A4: 1 | B4: 1 | C4: -1 | G4: Капитальный ремонт здания Государственного бюджетного общеобразовательного учреждения города Москвы "Школа № 236" по адресу: г. Москва ул. Клязьминская, д. 7 к. 4. 1 этап | EC4: 0
A12: 1 | B12: 1087 | C12: 0 | D12: =ROW(A1046) -> 1046 | E12: 0 | F12: Новый объект (ТСН-2001 (Мосгосэкспертиза)) | G12: 02-01-05 Система водоотведения | I12: 0 | K12: 0 | L12: 0 | M12: 4098 | O12: 0 | P12: 0 | Q12: 0 | R12: 0 | S12: 0 | T12: 1 | V12: 0 | AB12: Кузнецова Е.А. | BB12: 0 | BH12: Сметные нормы списания | BI12: Коды ОКП для ТСН-2001 МГЭ Дополнение 80 | BJ12: 1 | BK12: 1 | BL12: 0 | BM12: 0 | BN12: 1 | BO12: 0 | BP12: 6 | BQ12: 2 | BR12: 1 | BS12: 1 | BT12: 0 | BU12: 0 | BV12: 1 | BW12: 0 | BX12: 0 | BZ12: Типовой расчет для ТСН-2001 МГЭ, Дополнение 80, ремонт | CA12: Территориальные сметные нормативы для Москвы ТСН-2001 (МГЭ), дополнение 80 | CB12: Территориальные сметные нормативы для Москвы ТСН-2001 (МГЭ), дополнение 80 | CC12: Территориальные сметные нормативы для Москвы ТСН-2001 (МГЭ), дополнение 80 | CD12: Территориальные сметные нормативы для Москвы ТСН-2001 (МГЭ), дополнение 80 | CE12: Поправки для ТСН-2001 от 03.02.2026 г. доп.80 | CF12: 0 | CG12: 0 | CH12: 327688 | CK12: 81 | CQ12: Территориальные сметные нормативы для Москвы (ТСН-2001) | CR12: ТЕР | CS12: 41660 | CT12: 1 | CU12: 80 | CY12: 0 | EC12: 0
A15: 15 | B15: 1
A18: 52 | B18: =B1046 -> 1087 | C18: =C1046 -> 1 | D18: =D1046 -> 12 | E18: =E1046 -> 0 | F18: =F1046 -> Новый объект (ТСН-2001 (Мосгосэкспертиза)) | G18: =G1046 -> 02-01-05 Система водоотведения | O18: =O1046 -> 834463.88 | P18: =P1046 -> 810536.74 | Q18: =Q1046 -> 1595.67 | R18: =R1046 -> 201.15 | S18: =S1046 -> 22331.47 | T18: =T1046 -> 0 | U18: =U1046 -> 1761.7362 | V18: =V1046 -> 0 | ... GX18: =GX1046 -> 0
A20: 3 | B20: 1 | D20: =ROW(A1016) -> 1016 | F20: 02-01-05 | G20: Система водоотведения | I20: 0 | J20: 2024-00272-00-0-ИОС3 | K20: -1 | L20: 02-01-05 | S20: 0 | T20: 0 | V20: 0 | BX20: 0 | CF20: 0 | CG20: 0
A22: 52 | B22: =B1016 -> 1 | C22: =C1016 -> 3 | D22: =D1016 -> 20 | E22: =E1016 -> 0 | F22: =F1016 -> 02-01-05 | G22: =G1016 -> Система водоотведения | O22: =O1016 -> 834463.88 | P22: =P1016 -> 810536.74 | Q22: =Q1016 -> 1595.67 | R22: =R1016 -> 201.15 | S22: =S1016 -> 22331.47 | T22: =T1016 -> 0 | U22: =U1016 -> 1761.7362 | V22: =V1016 -> 0 | ... GX22: =GX1016 -> 0
A24: 4 | B24: 1 | D24: =ROW(A95) -> 95 | F24: Новый раздел | G24: Канализация хозяйственно-бытовая (К1) (подвал) | I24: 0 | K24: 0 | S24: 0 | T24: 0 | V24: 0 | BX24: 0 | CJ24: 0
A26: 52 | B26: =B95 -> 1 | C26: =C95 -> 4 | D26: =D95 -> 24 | E26: =E95 -> 0 | F26: =F95 -> Новый раздел | G26: =G95 -> Канализация хозяйственно-бытовая (К1) (подвал) | O26: =O95 -> 45291.94 | P26: =P95 -> 41523.21 | Q26: =Q95 -> 82.81 | R26: =R95 -> 11.48 | S26: =S95 -> 3685.92 | T26: =T95 -> 0 | U26: =U95 -> 292.35437 | V26: =V95 -> 0 | ... GX26: =GX95 -> 0
A28: 5 | B28: 1 | D28: =ROW(A65) -> 65 | F28: Новый подраздел | G28: Монтажные работы | I28: 0 | K28: 0 | S28: 0 | T28: 0 | V28: 0 | BX28: 0 | CJ28: 0
A30: 52 | B30: =B65 -> 1 | C30: =C65 -> 5 | D30: =D65 -> 28 | E30: =E65 -> 0 | F30: =F65 -> Новый подраздел | G30: =G65 -> Монтажные работы | O30: =O65 -> 45291.94 | P30: =P65 -> 41523.21 | Q30: =Q65 -> 82.81 | R30: =R65 -> 11.48 | S30: =S65 -> 3685.92 | T30: =T65 -> 0 | U30: =U65 -> 292.35437 | V30: =V65 -> 0 | ... GX30: =GX65 -> 0
A32: 17 | B32: 1 | C32: =ROW(SmtRes!A8) -> 8 | D32: =ROW(EtalonRes!A8) -> 8 | E32: 1 | F32: 3.16-36-1 | G32: Прокладка трубопроводов канализации из чугунных безраструбных труб, диаметр 50 мм | H32: 100 м | I32: =ROUND(ROUND(16/100,4),9) -> 0.16 | J32: 0 | K32: =ROUND(ROUND(16/100,4),9) -> 0.16 | O32: =ROUND(CP32,2) -> 402.89 | P32: =ROUND((ROUND((AC32*AW32*I32),2)*BC32),2) -> 0.53 | Q32: =(ROUND((ROUND(((((ET32*1.25)*1.1))*AV32*I32),2)*BB32),2)+ROUND((ROUND(((AE32-(((EU32*1.25)*1.1)))*AV32*I32),2)*BS32),2)) -> 5.07 | R32: =ROUND((ROUND((AE32*AV32*I32),2)*BS32),2) -> 0.42 | S32: =ROUND((ROUND((AF32*AV32*I32),2)*BA32),2) -> 397.29 | T32: =ROUND(CU32*I32,2) -> 0 | U32: =CV32*I32 -> 30.733381 | V32: =CW32*I32 -> 0 | W32: =ROUND(CX32*I32,2) -> 0 | X32: =ROUND(CY32,2) -> 433.5 | Y32: =ROUND(CZ32,2) -> 242.6 | AA32: 59209203 | AB32: =ROUND((AC32+AD32+AF32),6) -> 2360.1435 | AC32: =ROUND((ES32),6) -> 3.3 | AD32: =ROUND((((((ET32*1.25)*1.1))-(((EU32*1.25)*1.1)))+AE32),6) -> 29.68625 | AE32: =ROUND((((EU32*1.25)*1.1)),6) -> 2.43375 | AF32: =ROUND((((EV32*1.15)*1.1)),6) -> 2327.1573 | AG32: =ROUND((AP32),6) -> 0 | AH32: =(((EW32*1.15)*1.1)) -> 180.02215 | AI32: =(((EX32*1.25)*1.1)) -> 0 | AJ32: =(AS32) -> 0 | AK32: 1864.54 | AL32: 3.3 | AM32: 21.59 | AN32: 1.77 | AO32: 1839.65 | AP32: 0 | AQ32: 142.31 | AR32: 0 | AS32: 0 | AT32: 109 | AU32: 61 | AV32: 1.067 | AW32: 1 | AZ32: 1 | BA32: 1 | BB32: 1 | BC32: 1 | BH32: 0 | BI32: 1 | BJ32: ТСН-2001.3 Доп. 72, Сб. 16, т. 36, поз. 1 | BM32: 21 | BN32: 58807811 | BO32: 3.16-36-1 | BP32: 1 | BQ32: 30 | BR32: 0 | BS32: 1 | BT32: 1 | BU32: 1 | BV32: 1 | BW32: 1 | BX32: 1 | BZ32: 109 | CA32: 61 | CE32: 30 | CF32: 0 | CG32: 0 | CM32: 0 | CN32: Поправка: О.П. п.3.4. 6 Наименование: Выполняемые при ремонте и реконструкции работы аналогичные технологическим процессам, характерным для нового строительства и отсутствующим в сборниках на ремонтно-строительные работы Поправка: О.П. п.3.4.30.в Наименование: При применении территориальных сметных нормативов для города Москвы затраты, учитывающие напряженные и стесненные условия производства работ (стесненность, сложность складирования и транспортной логистики и т.п.), исчисляются с применением коэффициентов к затратам труда и заработной плате рабочих, машинистов, времени эксплуатации машин и механизмов, стоимости эксплуатации машин в размере: для объектов, расположенных за пределами Третьего транспортного кольца города Москвы, но в пределах Московской кольцевой автомобильной дороги | CO32: 0 | CP32: =(P32+Q32+S32) -> 402.89 | CQ32: =ROUND((ROUND((AC32*AW32*1),2)*BC32),2) -> 3.3 | CR32: =(ROUND((ROUND(((((ET32*1.25)*1.1))*AV32*1),2)*BB32),2)+ROUND((ROUND(((AE32-(((EU32*1.25)*1.1)))*AV32*1),2)*BS32),2)) -> 31.68 | CS32: =ROUND((ROUND((AE32*AV32*1),2)*BS32),2) -> 2.6 | CT32: =ROUND((ROUND((AF32*AV32*1),2)*BA32),2) -> 2483.08 | CU32: =AG32 -> 0 | CV32: =(AH32*AV32) -> 192.08363 | CW32: =AI32 -> 0 | CX32: =AJ32 -> 0 | CY32: =(((S32+R32)*AT32)/100) -> 433.5039 | CZ32: =(((S32+R32)*AU32)/100) -> 242.6031 | DB32: 1 | DE32: *1,25)*1,1 | DF32: *1,25)*1,1 | DG32: *1,15)*1,1 | DI32: *1,15)*1,1 | DJ32: *1,25)*1,1 | DN32: 0 | DO32: 0 | DP32: 1 | DQ32: 1 | DU32: 1003 | DV32: 100 м | DW32: 100 м | DX32: 100 | EE32: 58807897 | EF32: 30 | EG32: Строительные работы | EH32: 0 | EJ32: 1 | EK32: 21 | EL32: ТСН-2001.3-16. Трубопроводы внутренние | EM32: ТСН-2001.3-16-1 | EO32: Поправка: О.П. п.3.4. 6 Поправка: О.П. п.3.4.30.в | EQ32: 0 | ER32: 1864.54 | ES32: 3.3 | ET32: 21.59 | EU32: 1.77 | EV32: 1839.65 | EW32: 142.31 | EX32: 0 | EY32: 0 | FQ32: 0 | FR32: 0 | FS32: 0 | FX32: 109 | FY32: 61 | GD32: 1 | GF32: -907190157 | GG32: 2 | GH32: 1 | GI32: 2 | GJ32: 0 | GK32: 0 | GL32: =ROUND(IF(AND(BH32=3,BI32=3,FS32<>0),P32,0),2) -> 0 | GM32: =ROUND(O32+X32+Y32,2)+GX32 -> 1078.99 | GN32: =IF(OR(BI32=0,BI32=1),GM32-GX32,0) -> 1078.99 | GO32: =IF(BI32=2,GM32-GX32,0) -> 0 | GP32: =IF(BI32=4,GM32-GX32,0) -> 0 | GR32: 0 | GS32: 3 | GT32: 0 | GV32: =ROUND((GT32),6) -> 0 | GW32: 1 | GX32: =ROUND(HC32*I32,2) -> 0 | HA32: 0 | HB32: 0 | HC32: =GV32*GW32 -> 0 | HS32: 0 | IK32: 0
A33: 17 | B33: 1 | C33: =ROW(SmtRes!A16) -> 16 | D33: =ROW(EtalonRes!A16) -> 16 | E33: 1 | F33: 3.16-36-1 | G33: Прокладка трубопроводов канализации из чугунных безраструбных труб, диаметр 50 мм | H33: 100 м | I33: =ROUND(ROUND(16/100,4),9) -> 0.16 | J33: 0 | K33: =ROUND(ROUND(16/100,4),9) -> 0.16 | O33: =ROUND(CP33,2) -> 21917.43 | P33: =ROUND((ROUND((AC33*AW33*I33),2)*BC33),2) -> 4.74 | Q33: =(ROUND((ROUND(((((ET33*1.25)*1.1))*AV33*I33),2)*BB33),2)+ROUND((ROUND(((AE33-(((EU33*1.25)*1.1)))*AV33*I33),2)*BS33),2)) -> 65.71 | R33: =ROUND((ROUND((AE33*AV33*I33),2)*BS33),2) -> 23.1 | S33: =ROUND((ROUND((AF33*AV33*I33),2)*BA33),2) -> 21846.98 | T33: =ROUND(CU33*I33,2) -> 0 | U33: =CV33*I33 -> 30.733381 | V33: =CW33*I33 -> 0 | W33: =ROUND(CX33*I33,2) -> 0 | X33: =ROUND(CY33,2) -> 23838.39 | Y33: =ROUND(CZ33,2) -> 13340.75 | AA33: 59209200 | AB33: =ROUND((AC33+AD33+AF33),6) -> 2360.1435 | AC33: =ROUND((ES33),6) -> 3.3 | AD33: =ROUND((((((ET33*1.25)*1.1))-(((EU33*1.25)*1.1)))+AE33),6) -> 29.68625 | AE33: =ROUND((((EU33*1.25)*1.1)),6) -> 2.43375 | AF33: =ROUND((((EV33*1.15)*1.1)),6) -> 2327.1573 | AG33: =ROUND((AP33),6) -> 0 | AH33: =(((EW33*1.15)*1.1)) -> 180.02215 | AI33: =(((EX33*1.25)*1.1)) -> 0 | AJ33: =(AS33) -> 0 | AK33: 1864.54 | AL33: 3.3 | AM33: 21.59 | AN33: 1.77 | AO33: 1839.65 | AP33: 0 | AQ33: 142.31 | AR33: 0 | AS33: 0 | AT33: 109 | AU33: 61 | AV33: 1.067 | AW33: 1 | AZ33: 1 | BA33: 54.99 | BB33: 12.96 | BC33: 8.95 | BH33: 0 | BI33: 1 | BJ33: ТСН-2001.3 Доп. 72, Сб. 16, т. 36, поз. 1 | BM33: 21 | BN33: 58807811 | BO33: 3.16-36-1 | BP33: 1 | BQ33: 30 | BR33: 0 | BS33: 54.99 | BT33: 1 | BU33: 1 | BV33: 1 | BW33: 1 | BX33: 1 | BZ33: 109 | CA33: 61 | CE33: 30 | CF33: 0 | CG33: 0 | CM33: 0 | CN33: Поправка: О.П. п.3.4. 6 Наименование: Выполняемые при ремонте и реконструкции работы аналогичные технологическим процессам, характерным для нового строительства и отсутствующим в сборниках на ремонтно-строительные работы Поправка: О.П. п.3.4.30.в Наименование: При применении территориальных сметных нормативов для города Москвы затраты, учитывающие напряженные и стесненные условия производства работ (стесненность, сложность складирования и транспортной логистики и т.п.), исчисляются с применением коэффициентов к затратам труда и заработной плате рабочих, машинистов, времени эксплуатации машин и механизмов, стоимости эксплуатации машин в размере: для объектов, расположенных за пределами Третьего транспортного кольца города Москвы, но в пределах Московской кольцевой автомобильной дороги | CO33: 0 | CP33: =(P33+Q33+S33) -> 21917.43 | CQ33: =ROUND((ROUND((AC33*AW33*1),2)*BC33),2) -> 29.54 | CR33: =(ROUND((ROUND(((((ET33*1.25)*1.1))*AV33*1),2)*BB33),2)+ROUND((ROUND(((AE33-(((EU33*1.25)*1.1)))*AV33*1),2)*BS33),2)) -> 410.57 | CS33: =ROUND((ROUND((AE33*AV33*1),2)*BS33),2) -> 142.97 | CT33: =ROUND((ROUND((AF33*AV33*1),2)*BA33),2) -> 136544.57 | CU33: =AG33 -> 0 | CV33: =(AH33*AV33) -> 192.08363 | CW33: =AI33 -> 0 | CX33: =AJ33 -> 0 | CY33: =(((S33+R33)*AT33)/100) -> 23838.387 | CZ33: =(((S33+R33)*AU33)/100) -> 13340.749 | DB33: 3 | DE33: *1,25)*1,1 | DF33: *1,25)*1,1 | DG33: *1,15)*1,1 | DI33: *1,15)*1,1 | DJ33: *1,25)*1,1 | DN33: 0 | DO33: 0 | DP33: 1 | DQ33: 1 | DU33: 1003 | DV33: 100 м | DW33: 100 м | DX33: 100 | EE33: 58807897 | EF33: 30 | EG33: Строительные работы | EH33: 0 | EJ33: 1 | EK33: 21 | EL33: ТСН-2001.3-16. Трубопроводы внутренние | EM33: ТСН-2001.3-16-1 | EO33: Поправка: О.П. п.3.4. 6 Поправка: О.П. п.3.4.30.в | EQ33: 0 | ER33: 1864.54 | ES33: 3.3 | ET33: 21.59 | EU33: 1.77 | EV33: 1839.65 | EW33: 142.31 | EX33: 0 | EY33: 0 | FQ33: 0 | FR33: 0 | FS33: 0 | FX33: 109 | FY33: 61 | GD33: 1 | GF33: -907190157 | GG33: 2 | GH33: 1 | GI33: 2 | GJ33: 0 | GK33: 0 | GL33: =ROUND(IF(AND(BH33=3,BI33=3,FS33<>0),P33,0),2) -> 0 | GM33: =ROUND(O33+X33+Y33,2)+GX33 -> 59096.57 | GN33: =IF(OR(BI33=0,BI33=1),GM33-GX33,0) -> 59096.57 | GO33: =IF(BI33=2,GM33-GX33,0) -> 0 | GP33: =IF(BI33=4,GM33-GX33,0) -> 0 | GR33: 0 | GS33: 3 | GT33: 0 | GV33: =ROUND((GT33),6) -> 0 | GW33: 1 | GX33: =ROUND(HC33*I33,2) -> 0 | HA33: 0 | HB33: 0 | HC33: =GV33*GW33 -> 0 | HS33: 0 | IK33: 0
A34: 18 | B34: 1 | C34: 8 | E34: 1,1 | F34: 1.12-8-74 | G34: Комплект деталей трубопроводов из чугуна с мелкодисперсным графитом с внутренним эпоксидным покрытием, наружным слоем краснокоричневой грунтовки (безраструбные трубы, фасонные части, крепеж), диаметр условного прохода 50 мм | H34: м | I34: =I32*J34 -> 16 | J34: 100 | K34: 100 | O34: =ROUND(CP34,2) -> 21261.76 | P34: =ROUND((ROUND((AC34*AW34*I34),2)*BC34),2) -> 21261.76 | Q34: =(ROUND((ROUND(((ET34)*AV34*I34),2)*BB34),2)+ROUND((ROUND(((AE34-(EU34))*AV34*I34),2)*BS34),2)) -> 0 | R34: =ROUND((ROUND((AE34*AV34*I34),2)*BS34),2) -> 0 | S34: =ROUND((ROUND((AF34*AV34*I34),2)*BA34),2) -> 0 | T34: =ROUND(CU34*I34,2) -> 0 | U34: =CV34*I34 -> 0 | V34: =CW34*I34 -> 0 | W34: =ROUND(CX34*I34,2) -> 0 | X34: =ROUND(CY34,2) -> 0 | Y34: =ROUND(CZ34,2) -> 0 | AA34: 59209203 | AB34: =ROUND((AC34+AD34+AF34),6) -> 1328.86 | AC34: =ROUND((ES34),6) -> 1328.86 | AD34: =ROUND((((ET34)-(EU34))+AE34),6) -> 0 | AE34: =ROUND((EU34),6) -> 0 | AF34: =ROUND((EV34),6) -> 0 | AG34: =ROUND((AP34),6) -> 0 | AH34: =(EW34) -> 0 | AI34: =(EX34) -> 0 | AJ34: =(AS34) -> 0 | AK34: 1328.86 | AL34: 1328.86 | AM34: 0 | AN34: 0 | AO34: 0 | AP34: 0 | AQ34: 0 | AR34: 0 | AS34: 0 | AT34: 109 | AU34: 61 | AV34: 1 | AW34: 1 | AZ34: 1 | BA34: 1 | BB34: 1 | BC34: 1 | BH34: 3 | BI34: 1 | BJ34: ТСН-2001.1 Доп. 79, Р. 12, о. 8, поз. 74 | BM34: 21 | BN34: 58807811 | BP34: 0 | BQ34: 30 | BR34: 0 | BS34: 1 | BT34: 1 | BU34: 1 | BV34: 1 | BW34: 1 | BX34: 1 | BZ34: 109 | CA34: 61 | CE34: 30 | CF34: 0 | CG34: 0 | CM34: 0 | CO34: 0 | CP34: =(P34+Q34+S34) -> 21261.76 | CQ34: =ROUND((ROUND((AC34*AW34*1),2)*BC34),2) -> 1328.86 | CR34: =(ROUND((ROUND(((ET34)*AV34*1),2)*BB34),2)+ROUND((ROUND(((AE34-(EU34))*AV34*1),2)*BS34),2)) -> 0 | CS34: =ROUND((ROUND((AE34*AV34*1),2)*BS34),2) -> 0 | CT34: =ROUND((ROUND((AF34*AV34*1),2)*BA34),2) -> 0 | CU34: =AG34 -> 0 | CV34: =(AH34*AV34) -> 0 | CW34: =AI34 -> 0 | CX34: =AJ34 -> 0 | CY34: =(((S34+R34)*AT34)/100) -> 0 | CZ34: =(((S34+R34)*AU34)/100) -> 0 | DN34: 0 | DO34: 0 | DP34: 1 | DQ34: 1 | DU34: 1003 | DV34: м | DW34: м | DX34: 1 | EE34: 58807897 | EF34: 30 | EG34: Строительные работы | EH34: 0 | EJ34: 1 | EK34: 21 | EL34: ТСН-2001.3-16. Трубопроводы внутренние | EM34: ТСН-2001.3-16-1 | EQ34: 0 | ER34: 1328.86 | ES34: 1328.86 | ET34: 0 | EU34: 0 | EV34: 0 | EW34: 0 | EX34: 0 | FQ34: 0 | FR34: 0 | FS34: 0 | FX34: 109 | FY34: 61 | GD34: 1 | GF34: 925110201 | GG34: 2 | GH34: 1 | GI34: -2 | GJ34: 0 | GK34: 0 | GL34: =ROUND(IF(AND(BH34=3,BI34=3,FS34<>0),P34,0),2) -> 0 | GM34: =ROUND(O34+X34+Y34,2)+GX34 -> 21261.76 | GN34: =IF(OR(BI34=0,BI34=1),GM34-GX34,0) -> 21261.76 | GO34: =IF(BI34=2,GM34-GX34,0) -> 0 | GP34: =IF(BI34=4,GM34-GX34,0) -> 0 | GR34: 0 | GS34: 3 | GT34: 0 | GV34: =ROUND((GT34),6) -> 0 | GW34: 1 | GX34: =ROUND(HC34*I34,2) -> 0 | HA34: 0 | HB34: 0 | HC34: =GV34*GW34 -> 0 | HS34: 0 | IK34: 0
A35: 18 | B35: 1 | C35: 16 | E35: 1,1 | F35: 1.12-8-74 | G35: Комплект деталей трубопроводов из чугуна с мелкодисперсным графитом с внутренним эпоксидным покрытием, наружным слоем краснокоричневой грунтовки (безраструбные трубы, фасонные части, крепеж), диаметр условного прохода 50 мм | H35: м | I35: =I33*J35 -> 16 | J35: 100 | K35: 100 | O35: =ROUND(CP35,2) -> 20198.67 | P35: =ROUND((ROUND((AC35*AW35*I35),2)*BC35),2) -> 20198.67 | Q35: =(ROUND((ROUND(((ET35)*AV35*I35),2)*BB35),2)+ROUND((ROUND(((AE35-(EU35))*AV35*I35),2)*BS35),2)) -> 0 | R35: =ROUND((ROUND((AE35*AV35*I35),2)*BS35),2) -> 0 | S35: =ROUND((ROUND((AF35*AV35*I35),2)*BA35),2) -> 0 | T35: =ROUND(CU35*I35,2) -> 0 | U35: =CV35*I35 -> 0 | V35: =CW35*I35 -> 0 | W35: =ROUND(CX35*I35,2) -> 0 | X35: =ROUND(CY35,2) -> 0 | Y35: =ROUND(CZ35,2) -> 0 | AA35: 59209200 | AB35: =ROUND((AC35+AD35+AF35),6) -> 1328.86 | AC35: =ROUND((ES35),6) -> 1328.86 | AD35: =ROUND((((ET35)-(EU35))+AE35),6) -> 0 | AE35: =ROUND((EU35),6) -> 0 | AF35: =ROUND((EV35),6) -> 0 | AG35: =ROUND((AP35),6) -> 0 | AH35: =(EW35) -> 0 | AI35: =(EX35) -> 0 | AJ35: =(AS35) -> 0 | AK35: 1328.86 | AL35: 1328.86 | AM35: 0 | AN35: 0 | AO35: 0 | AP35: 0 | AQ35: 0 | AR35: 0 | AS35: 0 | AT35: 109 | AU35: 61 | AV35: 1 | AW35: 1 | AZ35: 1 | BA35: 1 | BB35: 1 | BC35: 0.95 | BH35: 3 | BI35: 1 | BJ35: ТСН-2001.1 Доп. 79, Р. 12, о. 8, поз. 74 | BM35: 21 | BN35: 58807811 | BO35: 1.12-8-74 | BP35: 1 | BQ35: 30 | BR35: 0 | BS35: 1 | BT35: 1 | BU35: 1 | BV35: 1 | BW35: 1 | BX35: 1 | BZ35: 109 | CA35: 61 | CE35: 30 | CF35: 0 | CG35: 0 | CM35: 0 | CO35: 0 | CP35: =(P35+Q35+S35) -> 20198.67 | CQ35: =ROUND((ROUND((AC35*AW35*1),2)*BC35),2) -> 1262.42 | CR35: =(ROUND((ROUND(((ET35)*AV35*1),2)*BB35),2)+ROUND((ROUND(((AE35-(EU35))*AV35*1),2)*BS35),2)) -> 0 | CS35: =ROUND((ROUND((AE35*AV35*1),2)*BS35),2) -> 0 | CT35: =ROUND((ROUND((AF35*AV35*1),2)*BA35),2) -> 0 | CU35: =AG35 -> 0 | CV35: =(AH35*AV35) -> 0 | CW35: =AI35 -> 0 | CX35: =AJ35 -> 0 | CY35: =(((S35+R35)*AT35)/100) -> 0 | CZ35: =(((S35+R35)*AU35)/100) -> 0 | DN35: 0 | DO35: 0 | DP35: 1 | DQ35: 1 | DU35: 1003 | DV35: м | DW35: м | DX35: 1 | EE35: 58807897 | EF35: 30 | EG35: Строительные работы | EH35: 0 | EJ35: 1 | EK35: 21 | EL35: ТСН-2001.3-16. Трубопроводы внутренние | EM35: ТСН-2001.3-16-1 | EQ35: 0 | ER35: 1328.86 | ES35: 1328.86 | ET35: 0 | EU35: 0 | EV35: 0 | EW35: 0 | EX35: 0 | FQ35: 0 | FR35: 0 | FS35: 0 | FX35: 109 | FY35: 61 | GD35: 1 | GF35: 925110201 | GG35: 2 | GH35: 1 | GI35: 2 | GJ35: 0 | GK35: 0 | GL35: =ROUND(IF(AND(BH35=3,BI35=3,FS35<>0),P35,0),2) -> 0 | GM35: =ROUND(O35+X35+Y35,2)+GX35 -> 20198.67 | GN35: =IF(OR(BI35=0,BI35=1),GM35-GX35,0) -> 20198.67 | GO35: =IF(BI35=2,GM35-GX35,0) -> 0 | GP35: =IF(BI35=4,GM35-GX35,0) -> 0 | GR35: 0 | GS35: 3 | GT35: 0 | GV35: =ROUND((GT35),6) -> 0 | GW35: 1 | GX35: =ROUND(HC35*I35,2) -> 0 | HA35: 0 | HB35: 0 | HC35: =GV35*GW35 -> 0 | HS35: 0 | IK35: 0
A36: 17 | B36: 1 | C36: =ROW(SmtRes!A26) -> 26 | D36: =ROW(EtalonRes!A25) -> 25 | E36: 2 | F36: 3.16-13-2 | G36: Прокладка трубопроводов канализации из ПВХ труб диаметром 100 мм - 150 мм | H36: 100 м | I36: =ROUND(ROUND(214/100,4),9) -> 2.14 | J36: 0 | K36: =ROUND(ROUND(214/100,4),9) -> 2.14 | O36: =ROUND(CP36,2) -> 2629.74 | P36: =ROUND((ROUND((AC36*AW36*I36),2)*BC36),2) -> 495.86 | Q36: =(ROUND((ROUND(((((ET36*1.25)*1.1))*AV36*I36),2)*BB36),2)+ROUND((ROUND(((AE36-(((EU36*1.25)*1.1)))*AV36*I36),2)*BS36),2)) -> 63.42 | R36: =ROUND((ROUND((AE36*AV36*I36),2)*BS36),2) -> 8.98 | S36: =ROUND((ROUND((AF36*AV36*I36),2)*BA36),2) -> 2070.46 | T36: =ROUND(CU36*I36,2) -> 0 | U36: =CV36*I36 -> 161.75464 | V36: =CW36*I36 -> 0 | W36: =ROUND(CX36*I36,2) -> 0 | X36: =ROUND(CY36,2) -> 2266.59 | Y36: =ROUND(CZ36,2) -> 1268.46 | AA36: 59209203 | AB36: =ROUND((AC36+AD36+AF36),6) -> 1166.237 | AC36: =ROUND((ES36),6) -> 231.71 | AD36: =ROUND((((((ET36*1.25)*1.1))-(((EU36*1.25)*1.1)))+AE36),6) -> 27.775 | AE36: =ROUND((((EU36*1.25)*1.1)),6) -> 3.9325 | AF36: =ROUND((((EV36*1.15)*1.1)),6) -> 906.752 | AG36: =ROUND((AP36),6) -> 0 | AH36: =(((EW36*1.15)*1.1)) -> 70.84 | AI36: =(((EX36*1.25)*1.1)) -> 0 | AJ36: =(AS36) -> 0 | AK36: 968.71 | AL36: 231.71 | AM36: 20.2 | AN36: 2.86 | AO36: 716.8 | AP36: 0 | AQ36: 56 | AR36: 0 | AS36: 0 | AT36: 109 | AU36: 61 | AV36: 1.067 | AW36: 1 | AZ36: 1 | BA36: 1 | BB36: 1 | BC36: 1 | BH36: 0 | BI36: 1 | BJ36: ТСН-2001.3 Доп. 79, Сб. 16, т. 13, поз. 2 | BM36: 21 | BN36: 58807811 | BO36: 3.16-13-2 | BP36: 1 | BQ36: 30 | BR36: 0 | BS36: 1 | BT36: 1 | BU36: 1 | BV36: 1 | BW36: 1 | BX36: 1 | BZ36: 109 | CA36: 61 | CE36: 30 | CF36: 0 | CG36: 0 | CM36: 0 | CN36: Поправка: О.П. п.3.4. 6 Наименование: Выполняемые при ремонте и реконструкции работы аналогичные технологическим процессам, характерным для нового строительства и отсутствующим в сборниках на ремонтно-строительные работы Поправка: О.П. п.3.4.30.в Наименование: При применении территориальных сметных нормативов для города Москвы затраты, учитывающие напряженные и стесненные условия производства работ (стесненность, сложность складирования и транспортной логистики и т.п.), исчисляются с применением коэффициентов к затратам труда и заработной плате рабочих, машинистов, времени эксплуатации машин и механизмов, стоимости эксплуатации машин в размере: для объектов, расположенных за пределами Третьего транспортного кольца города Москвы, но в пределах Московской кольцевой автомобильной дороги | CO36: 0 | CP36: =(P36+Q36+S36) -> 2629.74 | CQ36: =ROUND((ROUND((AC36*AW36*1),2)*BC36),2) -> 231.71 | CR36: =(ROUND((ROUND(((((ET36*1.25)*1.1))*AV36*1),2)*BB36),2)+ROUND((ROUND(((AE36-(((EU36*1.25)*1.1)))*AV36*1),2)*BS36),2)) -> 29.64 | CS36: =ROUND((ROUND((AE36*AV36*1),2)*BS36),2) -> 4.2 | CT36: =ROUND((ROUND((AF36*AV36*1),2)*BA36),2) -> 967.5 | CU36: =AG36 -> 0 | CV36: =(AH36*AV36) -> 75.58628 | CW36: =AI36 -> 0 | CX36: =AJ36 -> 0 | CY36: =(((S36+R36)*AT36)/100) -> 2266.5896 | CZ36: =(((S36+R36)*AU36)/100) -> 1268.4584 | DB36: 5 | DE36: *1,25)*1,1 | DF36: *1,25)*1,1 | DG36: *1,15)*1,1 | DI36: *1,15)*1,1 | DJ36: *1,25)*1,1 | DN36: 0 | DO36: 0 | DP36: 1 | DQ36: 1 | DU36: 1003 | DV36: 100 м | DW36: 100 м | DX36: 100 | EE36: 58807897 | EF36: 30 | EG36: Строительные работы | EH36: 0 | EJ36: 1 | EK36: 21 | EL36: ТСН-2001.3-16. Трубопроводы внутренние | EM36: ТСН-2001.3-16-1 | EO36: Поправка: О.П. п.3.4. 6 Поправка: О.П. п.3.4.30.в | EQ36: 0 | ER36: 968.71 | ES36: 231.71 | ET36: 20.2 | EU36: 2.86 | EV36: 716.8 | EW36: 56 | EX36: 0 | EY36: 0 | FQ36: 0 | FR36: 0 | FS36: 0 | FX36: 109 | FY36: 61 | GD36: 1 | GF36: 974562283 | GG36: 2 | GH36: 1 | GI36: 2 | GJ36: 0 | GK36: 0 | GL36: =ROUND(IF(AND(BH36=3,BI36=3,FS36<>0),P36,0),2) -> 0 | GM36: =ROUND(O36+X36+Y36,2)+GX36 -> 6164.79 | GN36: =IF(OR(BI36=0,BI36=1),GM36-GX36,0) -> 6164.79 | GO36: =IF(BI36=2,GM36-GX36,0) -> 0 | GP36: =IF(BI36=4,GM36-GX36,0) -> 0 | GR36: 0 | GS36: 3 | GT36: 0 | GV36: =ROUND((GT36),6) -> 0 | GW36: 1 | GX36: =ROUND(HC36*I36,2) -> 0 | HA36: 0 | HB36: 0 | HC36: =GV36*GW36 -> 0 | HS36: 0 | IK36: 0
A37: 17 | B37: 1 | C37: =ROW(SmtRes!A36) -> 36 | D37: =ROW(EtalonRes!A34) -> 34 | E37: 2 | F37: 3.16-13-2 | G37: Прокладка трубопроводов канализации из ПВХ труб диаметром 100 мм - 150 мм | H37: 100 м | I37: =ROUND(ROUND(214/100,4),9) -> 2.14 | J37: 0 | K37: =ROUND(ROUND(214/100,4),9) -> 2.14 | O37: =ROUND(CP37,2) -> 122887.78 | P37: =ROUND((ROUND((AC37*AW37*I37),2)*BC37),2) -> 8027.97 | Q37: =(ROUND((ROUND(((((ET37*1.25)*1.1))*AV37*I37),2)*BB37),2)+ROUND((ROUND(((AE37-(((EU37*1.25)*1.1)))*AV37*I37),2)*BS37),2)) -> 1005.21 | R37: =ROUND((ROUND((AE37*AV37*I37),2)*BS37),2) -> 493.81 | S37: =ROUND((ROUND((AF37*AV37*I37),2)*BA37),2) -> 113854.6 | T37: =ROUND(CU37*I37,2) -> 0 | U37: =CV37*I37 -> 161.75464 | V37: =CW37*I37 -> 0 | W37: =ROUND(CX37*I37,2) -> 0 | X37: =ROUND(CY37,2) -> 124639.77 | Y37: =ROUND(CZ37,2) -> 69752.53 | AA37: 59209200 | AB37: =ROUND((AC37+AD37+AF37),6) -> 1166.237 | AC37: =ROUND((ES37),6) -> 231.71 | AD37: =ROUND((((((ET37*1.25)*1.1))-(((EU37*1.25)*1.1)))+AE37),6) -> 27.775 | AE37: =ROUND((((EU37*1.25)*1.1)),6) -> 3.9325 | AF37: =ROUND((((EV37*1.15)*1.1)),6) -> 906.752 | AG37: =ROUND((AP37),6) -> 0 | AH37: =(((EW37*1.15)*1.1)) -> 70.84 | AI37: =(((EX37*1.25)*1.1)) -> 0 | AJ37: =(AS37) -> 0 | AK37: 968.71 | AL37: 231.71 | AM37: 20.2 | AN37: 2.86 | AO37: 716.8 | AP37: 0 | AQ37: 56 | AR37: 0 | AS37: 0 | AT37: 109 | AU37: 61 | AV37: 1.067 | AW37: 1 | AZ37: 1 | BA37: 54.99 | BB37: 15.85 | BC37: 16.19 | BH37: 0 | BI37: 1 | BJ37: ТСН-2001.3 Доп. 79, Сб. 16, т. 13, поз. 2 | BM37: 21 | BN37: 58807811 | BO37: 3.16-13-2 | BP37: 1 | BQ37: 30 | BR37: 0 | BS37: 54.99 | BT37: 1 | BU37: 1 | BV37: 1 | BW37: 1 | BX37: 1 | BZ37: 109 | CA37: 61 | CE37: 30 | CF37: 0 | CG37: 0 | CM37: 0 | CN37: Поправка: О.П. п.3.4. 6 Наименование: Выполняемые при ремонте и реконструкции работы аналогичные технологическим процессам, характерным для нового строительства и отсутствующим в сборниках на ремонтно-строительные работы Поправка: О.П. п.3.4.30.в Наименование: При применении территориальных сметных нормативов для города Москвы затраты, учитывающие напряженные и стесненные условия производства работ (стесненность, сложность складирования и транспортной логистики и т.п.), исчисляются с применением коэффициентов к затратам труда и заработной плате рабочих, машинистов, времени эксплуатации машин и механизмов, стоимости эксплуатации машин в размере: для объектов, расположенных за пределами Третьего транспортного кольца города Москвы, но в пределах Московской кольцевой автомобильной дороги | CO37: 0 | CP37: =(P37+Q37+S37) -> 122887.78 | CQ37: =ROUND((ROUND((AC37*AW37*1),2)*BC37),2) -> 3751.38 | CR37: =(ROUND((ROUND(((((ET37*1.25)*1.1))*AV37*1),2)*BB37),2)+ROUND((ROUND(((AE37-(((EU37*1.25)*1.1)))*AV37*1),2)*BS37),2)) -> 469.79 | CS37: =ROUND((ROUND((AE37*AV37*1),2)*BS37),2) -> 230.96 | CT37: =ROUND((ROUND((AF37*AV37*1),2)*BA37),2) -> 53202.83 | CU37: =AG37 -> 0 | CV37: =(AH37*AV37) -> 75.58628 | CW37: =AI37 -> 0 | CX37: =AJ37 -> 0 | CY37: =(((S37+R37)*AT37)/100) -> 124639.77 | CZ37: =(((S37+R37)*AU37)/100) -> 69752.53 | DB37: 7 | DE37: *1,25)*1,1 | DF37: *1,25)*1,1 | DG37: *1,15)*1,1 | DI37: *1,15)*1,1 | DJ37: *1,25)*1,1 | DN37: 0 | DO37: 0 | DP37: 1 | DQ37: 1 | DU37: 1003 | DV37: 100 м | DW37: 100 м | DX37: 100 | EE37: 58807897 | EF37: 30 | EG37: Строительные работы | EH37: 0 | EJ37: 1 | EK37: 21 | EL37: ТСН-2001.3-16. Трубопроводы внутренние | EM37: ТСН-2001.3-16-1 | EO37: Поправка: О.П. п.3.4. 6 Поправка: О.П. п.3.4.30.в | EQ37: 0 | ER37: 968.71 | ES37: 231.71 | ET37: 20.2 | EU37: 2.86 | EV37: 716.8 | EW37: 56 | EX37: 0 | EY37: 0 | FQ37: 0 | FR37: 0 | FS37: 0 | FX37: 109 | FY37: 61 | GD37: 1 | GF37: 974562283 | GG37: 2 | GH37: 1 | GI37: 2 | GJ37: 0 | GK37: 0 | GL37: =ROUND(IF(AND(BH37=3,BI37=3,FS37<>0),P37,0),2) -> 0 | GM37: =ROUND(O37+X37+Y37,2)+GX37 -> 317280.08 | GN37: =IF(OR(BI37=0,BI37=1),GM37-GX37,0) -> 317280.08 | GO37: =IF(BI37=2,GM37-GX37,0) -> 0 | GP37: =IF(BI37=4,GM37-GX37,0) -> 0 | GR37: 0 | GS37: 3 | GT37: 0 | GV37: =ROUND((GT37),6) -> 0 | GW37: 1 | GX37: =ROUND(HC37*I37,2) -> 0 | HA37: 0 | HB37: 0 | HC37: =GV37*GW37 -> 0 | HS37: 0 | IK37: 0
A38: 18 | B38: 1 | C38: 26 | E38: 2,1 | F38: КА 24 | G38: Трубы канализационные раструбные марки ПП, ГОСТ 32412-213, Д=110 | H38: м | I38: =I36*J38 -> 214 | J38: 100 | K38: 100 | O38: =ROUND(CP38,2) -> 5523.34 | P38: =ROUND((ROUND((AC38*AW38*I38),2)*BC38),2) -> 5523.34 | Q38: =(ROUND((ROUND(((ET38)*AV38*I38),2)*BB38),2)+ROUND((ROUND(((AE38-(EU38))*AV38*I38),2)*BS38),2)) -> 0 | R38: =ROUND((ROUND((AE38*AV38*I38),2)*BS38),2) -> 0 | S38: =ROUND((ROUND((AF38*AV38*I38),2)*BA38),2) -> 0 | T38: =ROUND(CU38*I38,2) -> 0 | U38: =CV38*I38 -> 0 | V38: =CW38*I38 -> 0 | W38: =ROUND(CX38*I38,2) -> 0 | X38: =ROUND(CY38,2) -> 0 | Y38: =ROUND(CZ38,2) -> 0 | AA38: 59209203 | AB38: =ROUND((AC38+AD38+AF38),6) -> 25.81 | AC38: =ROUND((ES38),6) -> 25.81 | AD38: =ROUND((((ET38)-(EU38))+AE38),6) -> 0 | AE38: =ROUND((EU38),6) -> 0 | AF38: =ROUND((EV38),6) -> 0 | AG38: =ROUND((AP38),6) -> 0 | AH38: =(EW38) -> 0 | AI38: =(EX38) -> 0 | AJ38: =(AS38) -> 0 | AK38: 25.81 | AL38: 25.81 | AM38: 0 | AN38: 0 | AO38: 0 | AP38: 0 | AQ38: 0 | AR38: 0 | AS38: 0 | AT38: 109 | AU38: 61 | AV38: 1 | AW38: 1 | AZ38: 1 | BA38: 1 | BB38: 1 | BC38: 1 | BH38: 3 | BI38: 1 | BM38: 21 | BN38: 0 | BP38: 0 | BQ38: 30 | BR38: 0 | BS38: 1 | BT38: 1 | BU38: 1 | BV38: 1 | BW38: 1 | BX38: 1 | BZ38: 109 | CA38: 61 | CE38: 30 | CF38: 0 | CG38: 0 | CM38: 0 | CO38: 0 | CP38: =(P38+Q38+S38) -> 5523.34 | CQ38: =ROUND((ROUND((AC38*AW38*1),2)*BC38),2) -> 25.81 | CR38: =(ROUND((ROUND(((ET38)*AV38*1),2)*BB38),2)+ROUND((ROUND(((AE38-(EU38))*AV38*1),2)*BS38),2)) -> 0 | CS38: =ROUND((ROUND((AE38*AV38*1),2)*BS38),2) -> 0 | CT38: =ROUND((ROUND((AF38*AV38*1),2)*BA38),2) -> 0 | CU38: =AG38 -> 0 | CV38: =(AH38*AV38) -> 0 | CW38: =AI38 -> 0 | CX38: =AJ38 -> 0 | CY38: =(((S38+R38)*AT38)/100) -> 0 | CZ38: =(((S38+R38)*AU38)/100) -> 0 | DN38: 0 | DO38: 0 | DP38: 1 | DQ38: 1 | DU38: 1003 | DV38: м | DW38: м | DX38: 1 | EE38: 58807897 | EF38: 30 | EG38: Строительные работы | EH38: 0 | EJ38: 1 | EK38: 21 | EL38: ТСН-2001.3-16. Трубопроводы внутренние | EM38: ТСН-2001.3-16-1 | EQ38: 0 | ER38: 0 | ES38: 25.81 | ET38: 0 | EU38: 0 | EV38: 0 | EW38: 0 | EX38: 0 | FQ38: 0 | FR38: 0 | FS38: 0 | FX38: 109 | FY38: 61 | GA38: [300 / 1,2 / 9,88] + 2% Заг.скл | GD38: 1 | GF38: -1486247260 | GG38: 2 | GH38: 4 | GI38: -2 | GJ38: 0 | GK38: 0 | GL38: =ROUND(IF(AND(BH38=3,BI38=3,FS38<>0),P38,0),2) -> 0 | GM38: =ROUND(O38+X38+Y38,2)+GX38 -> 5523.34 | GN38: =IF(OR(BI38=0,BI38=1),GM38-GX38,0) -> 5523.34 | GO38: =IF(BI38=2,GM38-GX38,0) -> 0 | GP38: =IF(BI38=4,GM38-GX38,0) -> 0 | GR38: 0 | GS38: 2 | GT38: 0 | GV38: =ROUND((GT38),6) -> 0 | GW38: 1 | GX38: =ROUND(HC38*I38,2) -> 0 | HA38: 0 | HB38: 0 | HC38: =GV38*GW38 -> 0 | HE38: 0 | HF38: 2 | HS38: 0 | IK38: 0
A39: 18 | B39: 1 | C39: 36 | E39: 2,1 | F39: КА 24 | G39: Трубы канализационные раструбные марки ПП, ГОСТ 32412-213, Д=110 | H39: м | I39: =I37*J39 -> 214 | J39: 100 | K39: 100 | O39: =ROUND(CP39,2) -> 54570.6 | P39: =ROUND((ROUND((AC39*AW39*I39),2)*BC39),2) -> 54570.6 | Q39: =(ROUND((ROUND(((ET39)*AV39*I39),2)*BB39),2)+ROUND((ROUND(((AE39-(EU39))*AV39*I39),2)*BS39),2)) -> 0 | R39: =ROUND((ROUND((AE39*AV39*I39),2)*BS39),2) -> 0 | S39: =ROUND((ROUND((AF39*AV39*I39),2)*BA39),2) -> 0 | T39: =ROUND(CU39*I39,2) -> 0 | U39: =CV39*I39 -> 0 | V39: =CW39*I39 -> 0 | W39: =ROUND(CX39*I39,2) -> 0 | X39: =ROUND(CY39,2) -> 0 | Y39: =ROUND(CZ39,2) -> 0 | AA39: 59209200 | AB39: =ROUND((AC39+AD39+AF39),6) -> 25.81 | AC39: =ROUND((ES39),6) -> 25.81 | AD39: =ROUND((((ET39)-(EU39))+AE39),6) -> 0 | AE39: =ROUND((EU39),6) -> 0 | AF39: =ROUND((EV39),6) -> 0 | AG39: =ROUND((AP39),6) -> 0 | AH39: =(EW39) -> 0 | AI39: =(EX39) -> 0 | AJ39: =(AS39) -> 0 | AK39: 25.81 | AL39: 25.81 | AM39: 0 | AN39: 0 | AO39: 0 | AP39: 0 | AQ39: 0 | AR39: 0 | AS39: 0 | AT39: 109 | AU39: 61 | AV39: 1 | AW39: 1 | AZ39: 1 | BA39: 1 | BB39: 1 | BC39: 9.88 | BH39: 3 | BI39: 1 | BM39: 21 | BN39: 0 | BP39: 0 | BQ39: 30 | BR39: 0 | BS39: 1 | BT39: 1 | BU39: 1 | BV39: 1 | BW39: 1 | BX39: 1 | BZ39: 109 | CA39: 61 | CE39: 30 | CF39: 0 | CG39: 0 | CM39: 0 | CO39: 0 | CP39: =(P39+Q39+S39) -> 54570.6 | CQ39: =ROUND((ROUND((AC39*AW39*1),2)*BC39),2) -> 255 | CR39: =(ROUND((ROUND(((ET39)*AV39*1),2)*BB39),2)+ROUND((ROUND(((AE39-(EU39))*AV39*1),2)*BS39),2)) -> 0 | CS39: =ROUND((ROUND((AE39*AV39*1),2)*BS39),2) -> 0 | CT39: =ROUND((ROUND((AF39*AV39*1),2)*BA39),2) -> 0 | CU39: =AG39 -> 0 | CV39: =(AH39*AV39) -> 0 | CW39: =AI39 -> 0 | CX39: =AJ39 -> 0 | CY39: =(((S39+R39)*AT39)/100) -> 0 | CZ39: =(((S39+R39)*AU39)/100) -> 0 | DN39: 0 | DO39: 0 | DP39: 1 | DQ39: 1 | DU39: 1003 | DV39: м | DW39: м | DX39: 1 | EE39: 58807897 | EF39: 30 | EG39: Строительные работы | EH39: 0 | EJ39: 1 | EK39: 21 | EL39: ТСН-2001.3-16. Трубопроводы внутренние | EM39: ТСН-2001.3-16-1 | EQ39: 0 | ER39: 25.81 | ES39: 25.81 | ET39: 0 | EU39: 0 | EV39: 0 | EW39: 0 | EX39: 0 | EZ39: 5 | FC39: 1 | FD39: 18 | FF39: 300 | FQ39: 0 | FR39: 0 | FS39: 0 | FX39: 109 | FY39: 61 | GA39: [300 / 1,2 / 9,88] + 2% Заг.скл | GD39: 1 | GF39: -1486247260 | GG39: 2 | GH39: 3 | GI39: 5 | GJ39: 0 | GK39: 0 | GL39: =ROUND(IF(AND(BH39=3,BI39=3,FS39<>0),P39,0),2) -> 0 | GM39: =ROUND(O39+X39+Y39,2)+GX39 -> 54570.6 | GN39: =IF(OR(BI39=0,BI39=1),GM39-GX39,0) -> 54570.6 | GO39: =IF(BI39=2,GM39-GX39,0) -> 0 | GP39: =IF(BI39=4,GM39-GX39,0) -> 0 | GR39: 1 | GS39: 1 | GT39: 0 | GV39: =ROUND((GT39),6) -> 0 | GW39: 1 | GX39: =ROUND(HC39*I39,2) -> 0 | HA39: 0 | HB39: 0 | HC39: =GV39*GW39 -> 0 | HE39: 0 | HF39: 2 | HS39: 0 | IK39: 0
A40: 18 | B40: 1 | C40: 23 | E40: 2,2 | F40: 1.12-5-133 | G40: Ревизия из полиэтилена, диаметр 110 мм | H40: шт. | I40: =I36*J40 -> 3 | J40: 1.4018692 | K40: 1.401869 | O40: =ROUND(CP40,2) -> 159.15 | P40: =ROUND((ROUND((AC40*AW40*I40),2)*BC40),2) -> 159.15 | Q40: =(ROUND((ROUND(((ET40)*AV40*I40),2)*BB40),2)+ROUND((ROUND(((AE40-(EU40))*AV40*I40),2)*BS40),2)) -> 0 | R40: =ROUND((ROUND((AE40*AV40*I40),2)*BS40),2) -> 0 | S40: =ROUND((ROUND((AF40*AV40*I40),2)*BA40),2) -> 0 | T40: =ROUND(CU40*I40,2) -> 0 | U40: =CV40*I40 -> 0 | V40: =CW40*I40 -> 0 | W40: =ROUND(CX40*I40,2) -> 0 | X40: =ROUND(CY40,2) -> 0 | Y40: =ROUND(CZ40,2) -> 0 | AA40: 59209203 | AB40: =ROUND((AC40+AD40+AF40),6) -> 53.05 | AC40: =ROUND((ES40),6) -> 53.05 | AD40: =ROUND((((ET40)-(EU40))+AE40),6) -> 0 | AE40: =ROUND((EU40),6) -> 0 | AF40: =ROUND((EV40),6) -> 0 | AG40: =ROUND((AP40),6) -> 0 | AH40: =(EW40) -> 0 | AI40: =(EX40) -> 0 | AJ40: =(AS40) -> 0 | AK40: 53.05 | AL40: 53.05 | AM40: 0 | AN40: 0 | AO40: 0 | AP40: 0 | AQ40: 0 | AR40: 0 | AS40: 0 | AT40: 109 | AU40: 61 | AV40: 1 | AW40: 1 | AZ40: 1 | BA40: 1 | BB40: 1 | BC40: 1 | BH40: 3 | BI40: 1 | BJ40: ТСН-2001.1 Доп. 67, Р. 12, о. 5, поз. 133 | BM40: 21 | BN40: 58807811 | BP40: 0 | BQ40: 30 | BR40: 0 | BS40: 1 | BT40: 1 | BU40: 1 | BV40: 1 | BW40: 1 | BX40: 1 | BZ40: 109 | CA40: 61 | CE40: 30 | CF40: 0 | CG40: 0 | CM40: 0 | CO40: 0 | CP40: =(P40+Q40+S40) -> 159.15 | CQ40: =ROUND((ROUND((AC40*AW40*1),2)*BC40),2) -> 53.05 | CR40: =(ROUND((ROUND(((ET40)*AV40*1),2)*BB40),2)+ROUND((ROUND(((AE40-(EU40))*AV40*1),2)*BS40),2)) -> 0 | CS40: =ROUND((ROUND((AE40*AV40*1),2)*BS40),2) -> 0 | CT40: =ROUND((ROUND((AF40*AV40*1),2)*BA40),2) -> 0 | CU40: =AG40 -> 0 | CV40: =(AH40*AV40) -> 0 | CW40: =AI40 -> 0 | CX40: =AJ40 -> 0 | CY40: =(((S40+R40)*AT40)/100) -> 0 | CZ40: =(((S40+R40)*AU40)/100) -> 0 | DN40: 0 | DO40: 0 | DP40: 1 | DQ40: 1 | DU40: 1010 | DV40: шт. | DW40: шт. | DX40: 1 | EE40: 58807897 | EF40: 30 | EG40: Строительные работы | EH40: 0 | EJ40: 1 | EK40: 21 | EL40: ТСН-2001.3-16. Трубопроводы внутренние | EM40: ТСН-2001.3-16-1 | EQ40: 0 | ER40: 53.05 | ES40: 53.05 | ET40: 0 | EU40: 0 | EV40: 0 | EW40: 0 | EX40: 0 | FQ40: 0 | FR40: 0 | FS40: 0 | FX40: 109 | FY40: 61 | GD40: 1 | GF40: -367918804 | GG40: 2 | GH40: 1 | GI40: -2 | GJ40: 0 | GK40: 0 | GL40: =ROUND(IF(AND(BH40=3,BI40=3,FS40<>0),P40,0),2) -> 0 | GM40: =ROUND(O40+X40+Y40,2)+GX40 -> 159.15 | GN40: =IF(OR(BI40=0,BI40=1),GM40-GX40,0) -> 159.15 | GO40: =IF(BI40=2,GM40-GX40,0) -> 0 | GP40: =IF(BI40=4,GM40-GX40,0) -> 0 | GR40: 0 | GS40: 3 | GT40: 0 | GV40: =ROUND((GT40),6) -> 0 | GW40: 1 | GX40: =ROUND(HC40*I40,2) -> 0 | HA40: 0 | HB40: 0 | HC40: =GV40*GW40 -> 0 | HS40: 0 | IK40: 0
A41: 18 | B41: 1 | C41: 33 | E41: 2,2 | F41: 1.12-5-133 | G41: Ревизия из полиэтилена, диаметр 110 мм | H41: шт. | I41: =I37*J41 -> 3 | J41: 1.4018692 | K41: 1.401869 | O41: =ROUND(CP41,2) -> 623.87 | P41: =ROUND((ROUND((AC41*AW41*I41),2)*BC41),2) -> 623.87 | Q41: =(ROUND((ROUND(((ET41)*AV41*I41),2)*BB41),2)+ROUND((ROUND(((AE41-(EU41))*AV41*I41),2)*BS41),2)) -> 0 | R41: =ROUND((ROUND((AE41*AV41*I41),2)*BS41),2) -> 0 | S41: =ROUND((ROUND((AF41*AV41*I41),2)*BA41),2) -> 0 | T41: =ROUND(CU41*I41,2) -> 0 | U41: =CV41*I41 -> 0 | V41: =CW41*I41 -> 0 | W41: =ROUND(CX41*I41,2) -> 0 | X41: =ROUND(CY41,2) -> 0 | Y41: =ROUND(CZ41,2) -> 0 | AA41: 59209200 | AB41: =ROUND((AC41+AD41+AF41),6) -> 53.05 | AC41: =ROUND((ES41),6) -> 53.05 | AD41: =ROUND((((ET41)-(EU41))+AE41),6) -> 0 | AE41: =ROUND((EU41),6) -> 0 | AF41: =ROUND((EV41),6) -> 0 | AG41: =ROUND((AP41),6) -> 0 | AH41: =(EW41) -> 0 | AI41: =(EX41) -> 0 | AJ41: =(AS41) -> 0 | AK41: 53.05 | AL41: 53.05 | AM41: 0 | AN41: 0 | AO41: 0 | AP41: 0 | AQ41: 0 | AR41: 0 | AS41: 0 | AT41: 109 | AU41: 61 | AV41: 1 | AW41: 1 | AZ41: 1 | BA41: 1 | BB41: 1 | BC41: 3.92 | BH41: 3 | BI41: 1 | BJ41: ТСН-2001.1 Доп. 67, Р. 12, о. 5, поз. 133 | BM41: 21 | BN41: 58807811 | BO41: 1.12-5-133 | BP41: 1 | BQ41: 30 | BR41: 0 | BS41: 1 | BT41: 1 | BU41: 1 | BV41: 1 | BW41: 1 | BX41: 1 | BZ41: 109 | CA41: 61 | CE41: 30 | CF41: 0 | CG41: 0 | CM41: 0 | CO41: 0 | CP41: =(P41+Q41+S41) -> 623.87 | CQ41: =ROUND((ROUND((AC41*AW41*1),2)*BC41),2) -> 207.96 | CR41: =(ROUND((ROUND(((ET41)*AV41*1),2)*BB41),2)+ROUND((ROUND(((AE41-(EU41))*AV41*1),2)*BS41),2)) -> 0 | CS41: =ROUND((ROUND((AE41*AV41*1),2)*BS41),2) -> 0 | CT41: =ROUND((ROUND((AF41*AV41*1),2)*BA41),2) -> 0 | CU41: =AG41 -> 0 | CV41: =(AH41*AV41) -> 0 | CW41: =AI41 -> 0 | CX41: =AJ41 -> 0 | CY41: =(((S41+R41)*AT41)/100) -> 0 | CZ41: =(((S41+R41)*AU41)/100) -> 0 | DN41: 0 | DO41: 0 | DP41: 1 | DQ41: 1 | DU41: 1010 | DV41: шт. | DW41: шт. | DX41: 1 | EE41: 58807897 | EF41: 30 | EG41: Строительные работы | EH41: 0 | EJ41: 1 | EK41: 21 | EL41: ТСН-2001.3-16. Трубопроводы внутренние | EM41: ТСН-2001.3-16-1 | EQ41: 0 | ER41: 53.05 | ES41: 53.05 | ET41: 0 | EU41: 0 | EV41: 0 | EW41: 0 | EX41: 0 | FQ41: 0 | FR41: 0 | FS41: 0 | FX41: 109 | FY41: 61 | GD41: 1 | GF41: -367918804 | GG41: 2 | GH41: 1 | GI41: 2 | GJ41: 0 | GK41: 0 | GL41: =ROUND(IF(AND(BH41=3,BI41=3,FS41<>0),P41,0),2) -> 0 | GM41: =ROUND(O41+X41+Y41,2)+GX41 -> 623.87 | GN41: =IF(OR(BI41=0,BI41=1),GM41-GX41,0) -> 623.87 | GO41: =IF(BI41=2,GM41-GX41,0) -> 0 | GP41: =IF(BI41=4,GM41-GX41,0) -> 0 | GR41: 0 | GS41: 3 | GT41: 0 | GV41: =ROUND((GT41),6) -> 0 | GW41: 1 | GX41: =ROUND(HC41*I41,2) -> 0 | HA41: 0 | HB41: 0 | HC41: =GV41*GW41 -> 0 | HS41: 0 | IK41: 0
A42: 18 | B42: 1 | C42: 24 | E42: 2,3 | F42: 1.12-5-133 | G42: Ревизия из полиэтилена, диаметр 110 мм /прочистки | H42: шт. | I42: =I36*J42 -> 18 | J42: 8.411215 | K42: 8.411215 | O42: =ROUND(CP42,2) -> 954.9 | P42: =ROUND((ROUND((AC42*AW42*I42),2)*BC42),2) -> 954.9 | Q42: =(ROUND((ROUND(((ET42)*AV42*I42),2)*BB42),2)+ROUND((ROUND(((AE42-(EU42))*AV42*I42),2)*BS42),2)) -> 0 | R42: =ROUND((ROUND((AE42*AV42*I42),2)*BS42),2) -> 0 | S42: =ROUND((ROUND((AF42*AV42*I42),2)*BA42),2) -> 0 | T42: =ROUND(CU42*I42,2) -> 0 | U42: =CV42*I42 -> 0 | V42: =CW42*I42 -> 0 | W42: =ROUND(CX42*I42,2) -> 0 | X42: =ROUND(CY42,2) -> 0 | Y42: =ROUND(CZ42,2) -> 0 | AA42: 59209203 | AB42: =ROUND((AC42+AD42+AF42),6) -> 53.05 | AC42: =ROUND((ES42),6) -> 53.05 | AD42: =ROUND((((ET42)-(EU42))+AE42),6) -> 0 | AE42: =ROUND((EU42),6) -> 0 | AF42: =ROUND((EV42),6) -> 0 | AG42: =ROUND((AP42),6) -> 0 | AH42: =(EW42) -> 0 | AI42: =(EX42) -> 0 | AJ42: =(AS42) -> 0 | AK42: 53.05 | AL42: 53.05 | AM42: 0 | AN42: 0 | AO42: 0 | AP42: 0 | AQ42: 0 | AR42: 0 | AS42: 0 | AT42: 109 | AU42: 61 | AV42: 1 | AW42: 1 | AZ42: 1 | BA42: 1 | BB42: 1 | BC42: 1 | BH42: 3 | BI42: 1 | BJ42: ТСН-2001.1 Доп. 67, Р. 12, о. 5, поз. 133 | BM42: 21 | BN42: 58807811 | BP42: 0 | BQ42: 30 | BR42: 0 | BS42: 1 | BT42: 1 | BU42: 1 | BV42: 1 | BW42: 1 | BX42: 1 | BZ42: 109 | CA42: 61 | CE42: 30 | CF42: 0 | CG42: 0 | CM42: 0 | CO42: 0 | CP42: =(P42+Q42+S42) -> 954.9 | CQ42: =ROUND((ROUND((AC42*AW42*1),2)*BC42),2) -> 53.05 | CR42: =(ROUND((ROUND(((ET42)*AV42*1),2)*BB42),2)+ROUND((ROUND(((AE42-(EU42))*AV42*1),2)*BS42),2)) -> 0 | CS42: =ROUND((ROUND((AE42*AV42*1),2)*BS42),2) -> 0 | CT42: =ROUND((ROUND((AF42*AV42*1),2)*BA42),2) -> 0 | CU42: =AG42 -> 0 | CV42: =(AH42*AV42) -> 0 | CW42: =AI42 -> 0 | CX42: =AJ42 -> 0 | CY42: =(((S42+R42)*AT42)/100) -> 0 | CZ42: =(((S42+R42)*AU42)/100) -> 0 | DN42: 0 | DO42: 0 | DP42: 1 | DQ42: 1 | DU42: 1010 | DV42: шт. | DW42: шт. | DX42: 1 | EE42: 58807897 | EF42: 30 | EG42: Строительные работы | EH42: 0 | EJ42: 1 | EK42: 21 | EL42: ТСН-2001.3-16. Трубопроводы внутренние | EM42: ТСН-2001.3-16-1 | EQ42: 0 | ER42: 53.05 | ES42: 53.05 | ET42: 0 | EU42: 0 | EV42: 0 | EW42: 0 | EX42: 0 | FQ42: 0 | FR42: 0 | FS42: 0 | FX42: 109 | FY42: 61 | GD42: 1 | GF42: -1159203431 | GG42: 2 | GH42: 1 | GI42: -2 | GJ42: 0 | GK42: 0 | GL42: =ROUND(IF(AND(BH42=3,BI42=3,FS42<>0),P42,0),2) -> 0 | GM42: =ROUND(O42+X42+Y42,2)+GX42 -> 954.9 | GN42: =IF(OR(BI42=0,BI42=1),GM42-GX42,0) -> 954.9 | GO42: =IF(BI42=2,GM42-GX42,0) -> 0 | GP42: =IF(BI42=4,GM42-GX42,0) -> 0 | GR42: 0 | GS42: 3 | GT42: 0 | GV42: =ROUND((GT42),6) -> 0 | GW42: 1 | GX42: =ROUND(HC42*I42,2) -> 0 | HA42: 0 | HB42: 0 | HC42: =GV42*GW42 -> 0 | HS42: 0 | IK42: 0
A43: 18 | B43: 1 | C43: 34 | E43: 2,3 | F43: 1.12-5-133 | G43: Ревизия из полиэтилена, диаметр 110 мм /прочистки | H43: шт. | I43: =I37*J43 -> 18 | J43: 8.411215 | K43: 8.411215 | O43: =ROUND(CP43,2) -> 3743.21 | P43: =ROUND((ROUND((AC43*AW43*I43),2)*BC43),2) -> 3743.21 | Q43: =(ROUND((ROUND(((ET43)*AV43*I43),2)*BB43),2)+ROUND((ROUND(((AE43-(EU43))*AV43*I43),2)*BS43),2)) -> 0 | R43: =ROUND((ROUND((AE43*AV43*I43),2)*BS43),2) -> 0 | S43: =ROUND((ROUND((AF43*AV43*I43),2)*BA43),2) -> 0 | T43: =ROUND(CU43*I43,2) -> 0 | U43: =CV43*I43 -> 0 | V43: =CW43*I43 -> 0 | W43: =ROUND(CX43*I43,2) -> 0 | X43: =ROUND(CY43,2) -> 0 | Y43: =ROUND(CZ43,2) -> 0 | AA43: 59209200 | AB43: =ROUND((AC43+AD43+AF43),6) -> 53.05 | AC43: =ROUND((ES43),6) -> 53.05 | AD43: =ROUND((((ET43)-(EU43))+AE43),6) -> 0 | AE43: =ROUND((EU43),6) -> 0 | AF43: =ROUND((EV43),6) -> 0 | AG43: =ROUND((AP43),6) -> 0 | AH43: =(EW43) -> 0 | AI43: =(EX43) -> 0 | AJ43: =(AS43) -> 0 | AK43: 53.05 | AL43: 53.05 | AM43: 0 | AN43: 0 | AO43: 0 | AP43: 0 | AQ43: 0 | AR43: 0 | AS43: 0 | AT43: 109 | AU43: 61 | AV43: 1 | AW43: 1 | AZ43: 1 | BA43: 1 | BB43: 1 | BC43: 3.92 | BH43: 3 | BI43: 1 | BJ43: ТСН-2001.1 Доп. 67, Р. 12, о. 5, поз. 133 | BM43: 21 | BN43: 58807811 | BO43: 1.12-5-133 | BP43: 1 | BQ43: 30 | BR43: 0 | BS43: 1 | BT43: 1 | BU43: 1 | BV43: 1 | BW43: 1 | BX43: 1 | BZ43: 109 | CA43: 61 | CE43: 30 | CF43: 0 | CG43: 0 | CM43: 0 | CO43: 0 | CP43: =(P43+Q43+S43) -> 3743.21 | CQ43: =ROUND((ROUND((AC43*AW43*1),2)*BC43),2) -> 207.96 | CR43: =(ROUND((ROUND(((ET43)*AV43*1),2)*BB43),2)+ROUND((ROUND(((AE43-(EU43))*AV43*1),2)*BS43),2)) -> 0 | CS43: =ROUND((ROUND((AE43*AV43*1),2)*BS43),2) -> 0 | CT43: =ROUND((ROUND((AF43*AV43*1),2)*BA43),2) -> 0 | CU43: =AG43 -> 0 | CV43: =(AH43*AV43) -> 0 | CW43: =AI43 -> 0 | CX43: =AJ43 -> 0 | CY43: =(((S43+R43)*AT43)/100) -> 0 | CZ43: =(((S43+R43)*AU43)/100) -> 0 | DN43: 0 | DO43: 0 | DP43: 1 | DQ43: 1 | DU43: 1010 | DV43: шт. | DW43: шт. | DX43: 1 | EE43: 58807897 | EF43: 30 | EG43: Строительные работы | EH43: 0 | EJ43: 1 | EK43: 21 | EL43: ТСН-2001.3-16. Трубопроводы внутренние | EM43: ТСН-2001.3-16-1 | EQ43: 0 | ER43: 53.05 | ES43: 53.05 | ET43: 0 | EU43: 0 | EV43: 0 | EW43: 0 | EX43: 0 | FQ43: 0 | FR43: 0 | FS43: 0 | FX43: 109 | FY43: 61 | GD43: 1 | GF43: -1159203431 | GG43: 2 | GH43: 1 | GI43: 2 | GJ43: 0 | GK43: 0 | GL43: =ROUND(IF(AND(BH43=3,BI43=3,FS43<>0),P43,0),2) -> 0 | GM43: =ROUND(O43+X43+Y43,2)+GX43 -> 3743.21 | GN43: =IF(OR(BI43=0,BI43=1),GM43-GX43,0) -> 3743.21 | GO43: =IF(BI43=2,GM43-GX43,0) -> 0 | GP43: =IF(BI43=4,GM43-GX43,0) -> 0 | GR43: 0 | GS43: 3 | GT43: 0 | GV43: =ROUND((GT43),6) -> 0 | GW43: 1 | GX43: =ROUND(HC43*I43,2) -> 0 | HA43: 0 | HB43: 0 | HC43: =GV43*GW43 -> 0 | HS43: 0 | IK43: 0
A44: 18 | B44: 1 | C44: 22 | E44: 2,4 | F44: 1.12-2-1167 | G44: Хомуты из оцинкованной стали с резиновыми прокладками для жесткого и скользящего крепления полипропиленовых труб, наружный диаметр 110 мм | H44: шт. | I44: =I36*J44 -> 71 | J44: 33.17757 | K44: 33.17757 | O44: =ROUND(CP44,2) -> 3853.88 | P44: =ROUND((ROUND((AC44*AW44*I44),2)*BC44),2) -> 3853.88 | Q44: =(ROUND((ROUND(((ET44)*AV44*I44),2)*BB44),2)+ROUND((ROUND(((AE44-(EU44))*AV44*I44),2)*BS44),2)) -> 0 | R44: =ROUND((ROUND((AE44*AV44*I44),2)*BS44),2) -> 0 | S44: =ROUND((ROUND((AF44*AV44*I44),2)*BA44),2) -> 0 | T44: =ROUND(CU44*I44,2) -> 0 | U44: =CV44*I44 -> 0 | V44: =CW44*I44 -> 0 | W44: =ROUND(CX44*I44,2) -> 0 | X44: =ROUND(CY44,2) -> 0 | Y44: =ROUND(CZ44,2) -> 0 | AA44: 59209203 | AB44: =ROUND((AC44+AD44+AF44),6) -> 54.28 | AC44: =ROUND((ES44),6) -> 54.28 | AD44: =ROUND((((ET44)-(EU44))+AE44),6) -> 0 | AE44: =ROUND((EU44),6) -> 0 | AF44: =ROUND((EV44),6) -> 0 | AG44: =ROUND((AP44),6) -> 0 | AH44: =(EW44) -> 0 | AI44: =(EX44) -> 0 | AJ44: =(AS44) -> 0 | AK44: 54.28 | AL44: 54.28 | AM44: 0 | AN44: 0 | AO44: 0 | AP44: 0 | AQ44: 0 | AR44: 0 | AS44: 0 | AT44: 109 | AU44: 61 | AV44: 1 | AW44: 1 | AZ44: 1 | BA44: 1 | BB44: 1 | BC44: 1 | BH44: 3 | BI44: 1 | BJ44: ТСН-2001.1 Доп. 46, Р. 12, о. 2, поз. 1167 | BM44: 21 | BN44: 0 | BP44: 0 | BQ44: 30 | BR44: 0 | BS44: 1 | BT44: 1 | BU44: 1 | BV44: 1 | BW44: 1 | BX44: 1 | BZ44: 109 | CA44: 61 | CE44: 30 | CF44: 0 | CG44: 0 | CM44: 0 | CO44: 0 | CP44: =(P44+Q44+S44) -> 3853.88 | CQ44: =ROUND((ROUND((AC44*AW44*1),2)*BC44),2) -> 54.28 | CR44: =(ROUND((ROUND(((ET44)*AV44*1),2)*BB44),2)+ROUND((ROUND(((AE44-(EU44))*AV44*1),2)*BS44),2)) -> 0 | CS44: =ROUND((ROUND((AE44*AV44*1),2)*BS44),2) -> 0 | CT44: =ROUND((ROUND((AF44*AV44*1),2)*BA44),2) -> 0 | CU44: =AG44 -> 0 | CV44: =(AH44*AV44) -> 0 | CW44: =AI44 -> 0 | CX44: =AJ44 -> 0 | CY44: =(((S44+R44)*AT44)/100) -> 0 | CZ44: =(((S44+R44)*AU44)/100) -> 0 | DN44: 0 | DO44: 0 | DP44: 1 | DQ44: 1 | DU44: 1010 | DV44: шт. | DW44: шт. | DX44: 1 | EE44: 58807897 | EF44: 30 | EG44: Строительные работы | EH44: 0 | EJ44: 1 | EK44: 21 | EL44: ТСН-2001.3-16. Трубопроводы внутренние | EM44: ТСН-2001.3-16-1 | EQ44: 0 | ER44: 54.28 | ES44: 54.28 | ET44: 0 | EU44: 0 | EV44: 0 | EW44: 0 | EX44: 0 | FQ44: 0 | FR44: 0 | FS44: 0 | FX44: 109 | FY44: 61 | GD44: 1 | GF44: 1014037414 | GG44: 2 | GH44: 1 | GI44: -2 | GJ44: 0 | GK44: 0 | GL44: =ROUND(IF(AND(BH44=3,BI44=3,FS44<>0),P44,0),2) -> 0 | GM44: =ROUND(O44+X44+Y44,2)+GX44 -> 3853.88 | GN44: =IF(OR(BI44=0,BI44=1),GM44-GX44,0) -> 3853.88 | GO44: =IF(BI44=2,GM44-GX44,0) -> 0 | GP44: =IF(BI44=4,GM44-GX44,0) -> 0 | GR44: 0 | GS44: 3 | GT44: 0 | GV44: =ROUND((GT44),6) -> 0 | GW44: 1 | GX44: =ROUND(HC44*I44,2) -> 0 | HA44: 0 | HB44: 0 | HC44: =GV44*GW44 -> 0 | HS44: 0 | IK44: 0
A45: 18 | B45: 1 | C45: 32 | E45: 2,4 | F45: 1.12-2-1167 | G45: Хомуты из оцинкованной стали с резиновыми прокладками для жесткого и скользящего крепления полипропиленовых труб, наружный диаметр 110 мм | H45: шт. | I45: =I37*J45 -> 71 | J45: 33.17757 | K45: 33.17757 | O45: =ROUND(CP45,2) -> 3584.11 | P45: =ROUND((ROUND((AC45*AW45*I45),2)*BC45),2) -> 3584.11 | Q45: =(ROUND((ROUND(((ET45)*AV45*I45),2)*BB45),2)+ROUND((ROUND(((AE45-(EU45))*AV45*I45),2)*BS45),2)) -> 0 | R45: =ROUND((ROUND((AE45*AV45*I45),2)*BS45),2) -> 0 | S45: =ROUND((ROUND((AF45*AV45*I45),2)*BA45),2) -> 0 | T45: =ROUND(CU45*I45,2) -> 0 | U45: =CV45*I45 -> 0 | V45: =CW45*I45 -> 0 | W45: =ROUND(CX45*I45,2) -> 0 | X45: =ROUND(CY45,2) -> 0 | Y45: =ROUND(CZ45,2) -> 0 | AA45: 59209200 | AB45: =ROUND((AC45+AD45+AF45),6) -> 54.28 | AC45: =ROUND((ES45),6) -> 54.28 | AD45: =ROUND((((ET45)-(EU45))+AE45),6) -> 0 | AE45: =ROUND((EU45),6) -> 0 | AF45: =ROUND((EV45),6) -> 0 | AG45: =ROUND((AP45),6) -> 0 | AH45: =(EW45) -> 0 | AI45: =(EX45) -> 0 | AJ45: =(AS45) -> 0 | AK45: 54.28 | AL45: 54.28 | AM45: 0 | AN45: 0 | AO45: 0 | AP45: 0 | AQ45: 0 | AR45: 0 | AS45: 0 | AT45: 109 | AU45: 61 | AV45: 1 | AW45: 1 | AZ45: 1 | BA45: 1 | BB45: 1 | BC45: 0.93 | BH45: 3 | BI45: 1 | BJ45: ТСН-2001.1 Доп. 46, Р. 12, о. 2, поз. 1167 | BM45: 21 | BN45: 0 | BO45: 1.12-2-1167 | BP45: 1 | BQ45: 30 | BR45: 0 | BS45: 1 | BT45: 1 | BU45: 1 | BV45: 1 | BW45: 1 | BX45: 1 | BZ45: 109 | CA45: 61 | CE45: 30 | CF45: 0 | CG45: 0 | CM45: 0 | CO45: 0 | CP45: =(P45+Q45+S45) -> 3584.11 | CQ45: =ROUND((ROUND((AC45*AW45*1),2)*BC45),2) -> 50.48 | CR45: =(ROUND((ROUND(((ET45)*AV45*1),2)*BB45),2)+ROUND((ROUND(((AE45-(EU45))*AV45*1),2)*BS45),2)) -> 0 | CS45: =ROUND((ROUND((AE45*AV45*1),2)*BS45),2) -> 0 | CT45: =ROUND((ROUND((AF45*AV45*1),2)*BA45),2) -> 0 | CU45: =AG45 -> 0 | CV45: =(AH45*AV45) -> 0 | CW45: =AI45 -> 0 | CX45: =AJ45 -> 0 | CY45: =(((S45+R45)*AT45)/100) -> 0 | CZ45: =(((S45+R45)*AU45)/100) -> 0 | DN45: 0 | DO45: 0 | DP45: 1 | DQ45: 1 | DU45: 1010 | DV45: шт. | DW45: шт. | DX45: 1 | EE45: 58807897 | EF45: 30 | EG45: Строительные работы | EH45: 0 | EJ45: 1 | EK45: 21 | EL45: ТСН-2001.3-16. Трубопроводы внутренние | EM45: ТСН-2001.3-16-1 | EQ45: 0 | ER45: 54.28 | ES45: 54.28 | ET45: 0 | EU45: 0 | EV45: 0 | EW45: 0 | EX45: 0 | FQ45: 0 | FR45: 0 | FS45: 0 | FX45: 109 | FY45: 61 | GD45: 1 | GF45: 1014037414 | GG45: 2 | GH45: 1 | GI45: 2 | GJ45: 0 | GK45: 0 | GL45: =ROUND(IF(AND(BH45=3,BI45=3,FS45<>0),P45,0),2) -> 0 | GM45: =ROUND(O45+X45+Y45,2)+GX45 -> 3584.11 | GN45: =IF(OR(BI45=0,BI45=1),GM45-GX45,0) -> 3584.11 | GO45: =IF(BI45=2,GM45-GX45,0) -> 0 | GP45: =IF(BI45=4,GM45-GX45,0) -> 0 | GR45: 0 | GS45: 3 | GT45: 0 | GV45: =ROUND((GT45),6) -> 0 | GW45: 1 | GX45: =ROUND(HC45*I45,2) -> 0 | HA45: 0 | HB45: 0 | HC45: =GV45*GW45 -> 0 | HS45: 0 | IK45: 0
A46: 17 | B46: 1 | C46: =ROW(SmtRes!A46) -> 46 | D46: =ROW(EtalonRes!A43) -> 43 | E46: 3 | F46: 3.16-13-1 | G46: Прокладка трубопроводов канализации из ПВХ труб диаметром до 50 мм | H46: 100 м | I46: =ROUND(ROUND(72/100,4),9) -> 0.72 | J46: 0 | K46: =ROUND(ROUND(72/100,4),9) -> 0.72 | O46: =ROUND(CP46,2) -> 798.45 | P46: =ROUND((ROUND((AC46*AW46*I46),2)*BC46),2) -> 61.32 | Q46: =(ROUND((ROUND(((((ET46*1.25)*1.1))*AV46*I46),2)*BB46),2)+ROUND((ROUND(((AE46-(((EU46*1.25)*1.1)))*AV46*I46),2)*BS46),2)) -> 10.67 | R46: =ROUND((ROUND((AE46*AV46*I46),2)*BS46),2) -> 1.51 | S46: =ROUND((ROUND((AF46*AV46*I46),2)*BA46),2) -> 726.46 | T46: =ROUND(CU46*I46,2) -> 0 | U46: =CV46*I46 -> 56.754498 | V46: =CW46*I46 -> 0 | W46: =ROUND(CX46*I46,2) -> 0 | X46: =ROUND(CY46,2) -> 793.49 | Y46: =ROUND(CZ46,2) -> 444.06 | AA46: 59209203 | AB46: =ROUND((AC46+AD46+AF46),6) -> 1044.6603 | AC46: =ROUND((ES46),6) -> 85.16 | AD46: =ROUND((((((ET46*1.25)*1.1))-(((EU46*1.25)*1.1)))+AE46),6) -> 13.8875 | AE46: =ROUND((((EU46*1.25)*1.1)),6) -> 1.96625 | AF46: =ROUND((((EV46*1.15)*1.1)),6) -> 945.6128 | AG46: =ROUND((AP46),6) -> 0 | AH46: =(((EW46*1.15)*1.1)) -> 73.876 | AI46: =(((EX46*1.25)*1.1)) -> 0 | AJ46: =(AS46) -> 0 | AK46: 842.78 | AL46: 85.16 | AM46: 10.1 | AN46: 1.43 | AO46: 747.52 | AP46: 0 | AQ46: 58.4 | AR46: 0 | AS46: 0 | AT46: 109 | AU46: 61 | AV46: 1.067 | AW46: 1 | AZ46: 1 | BA46: 1 | BB46: 1 | BC46: 1 | BH46: 0 | BI46: 1 | BJ46: ТСН-2001.3 Доп. 79, Сб. 16, т. 13, поз. 1 | BM46: 21 | BN46: 58807811 | BO46: 3.16-13-1 | BP46: 1 | BQ46: 30 | BR46: 0 | BS46: 1 | BT46: 1 | BU46: 1 | BV46: 1 | BW46: 1 | BX46: 1 | BZ46: 109 | CA46: 61 | CE46: 30 | CF46: 0 | CG46: 0 | CM46: 0 | CN46: Поправка: О.П. п.3.4. 6 Наименование: Выполняемые при ремонте и реконструкции работы аналогичные технологическим процессам, характерным для нового строительства и отсутствующим в сборниках на ремонтно-строительные работы Поправка: О.П. п.3.4.30.в Наименование: При применении территориальных сметных нормативов для города Москвы затраты, учитывающие напряженные и стесненные условия производства работ (стесненность, сложность складирования и транспортной логистики и т.п.), исчисляются с применением коэффициентов к затратам труда и заработной плате рабочих, машинистов, времени эксплуатации машин и механизмов, стоимости эксплуатации машин в размере: для объектов, расположенных за пределами Третьего транспортного кольца города Москвы, но в пределах Московской кольцевой автомобильной дороги | CO46: 0 | CP46: =(P46+Q46+S46) -> 798.45 | CQ46: =ROUND((ROUND((AC46*AW46*1),2)*BC46),2) -> 85.16 | CR46: =(ROUND((ROUND(((((ET46*1.25)*1.1))*AV46*1),2)*BB46),2)+ROUND((ROUND(((AE46-(((EU46*1.25)*1.1)))*AV46*1),2)*BS46),2)) -> 14.82 | CS46: =ROUND((ROUND((AE46*AV46*1),2)*BS46),2) -> 2.1 | CT46: =ROUND((ROUND((AF46*AV46*1),2)*BA46),2) -> 1008.97 | CU46: =AG46 -> 0 | CV46: =(AH46*AV46) -> 78.825692 | CW46: =AI46 -> 0 | CX46: =AJ46 -> 0 | CY46: =(((S46+R46)*AT46)/100) -> 793.4873 | CZ46: =(((S46+R46)*AU46)/100) -> 444.0617 | DB46: 9 | DE46: *1,25)*1,1 | DF46: *1,25)*1,1 | DG46: *1,15)*1,1 | DI46: *1,15)*1,1 | DJ46: *1,25)*1,1 | DN46: 0 | DO46: 0 | DP46: 1 | DQ46: 1 | DU46: 1003 | DV46: 100 м | DW46: 100 м | DX46: 100 | EE46: 58807897 | EF46: 30 | EG46: Строительные работы | EH46: 0 | EJ46: 1 | EK46: 21 | EL46: ТСН-2001.3-16. Трубопроводы внутренние | EM46: ТСН-2001.3-16-1 | EO46: Поправка: О.П. п.3.4. 6 Поправка: О.П. п.3.4.30.в | EQ46: 0 | ER46: 842.78 | ES46: 85.16 | ET46: 10.1 | EU46: 1.43 | EV46: 747.52 | EW46: 58.4 | EX46: 0 | EY46: 0 | FQ46: 0 | FR46: 0 | FS46: 0 | FX46: 109 | FY46: 61 | GD46: 1 | GF46: 428623321 | GG46: 2 | GH46: 1 | GI46: 2 | GJ46: 0 | GK46: 0 | GL46: =ROUND(IF(AND(BH46=3,BI46=3,FS46<>0),P46,0),2) -> 0 | GM46: =ROUND(O46+X46+Y46,2)+GX46 -> 2036 | GN46: =IF(OR(BI46=0,BI46=1),GM46-GX46,0) -> 2036 | GO46: =IF(BI46=2,GM46-GX46,0) -> 0 | GP46: =IF(BI46=4,GM46-GX46,0) -> 0 | GR46: 0 | GS46: 3 | GT46: 0 | GV46: =ROUND((GT46),6) -> 0 | GW46: 1 | GX46: =ROUND(HC46*I46,2) -> 0 | HA46: 0 | HB46: 0 | HC46: =GV46*GW46 -> 0 | HS46: 0 | IK46: 0
A47: 17 | B47: 1 | C47: =ROW(SmtRes!A56) -> 56 | D47: =ROW(EtalonRes!A52) -> 52 | E47: 3 | F47: 3.16-13-1 | G47: Прокладка трубопроводов канализации из ПВХ труб диаметром до 50 мм | H47: 100 м | I47: =ROUND(ROUND(72/100,4),9) -> 0.72 | J47: 0 | K47: =ROUND(ROUND(72/100,4),9) -> 0.72 | O47: =ROUND(CP47,2) -> 41116.68 | P47: =ROUND((ROUND((AC47*AW47*I47),2)*BC47),2) -> 999.52 | Q47: =(ROUND((ROUND(((((ET47*1.25)*1.1))*AV47*I47),2)*BB47),2)+ROUND((ROUND(((AE47-(((EU47*1.25)*1.1)))*AV47*I47),2)*BS47),2)) -> 169.12 | R47: =ROUND((ROUND((AE47*AV47*I47),2)*BS47),2) -> 83.03 | S47: =ROUND((ROUND((AF47*AV47*I47),2)*BA47),2) -> 39948.04 | T47: =ROUND(CU47*I47,2) -> 0 | U47: =CV47*I47 -> 56.754498 | V47: =CW47*I47 -> 0 | W47: =ROUND(CX47*I47,2) -> 0 | X47: =ROUND(CY47,2) -> 43633.87 | Y47: =ROUND(CZ47,2) -> 24418.95 | AA47: 59209200 | AB47: =ROUND((AC47+AD47+AF47),6) -> 1044.6603 | AC47: =ROUND((ES47),6) -> 85.16 | AD47: =ROUND((((((ET47*1.25)*1.1))-(((EU47*1.25)*1.1)))+AE47),6) -> 13.8875 | AE47: =ROUND((((EU47*1.25)*1.1)),6) -> 1.96625 | AF47: =ROUND((((EV47*1.15)*1.1)),6) -> 945.6128 | AG47: =ROUND((AP47),6) -> 0 | AH47: =(((EW47*1.15)*1.1)) -> 73.876 | AI47: =(((EX47*1.25)*1.1)) -> 0 | AJ47: =(AS47) -> 0 | AK47: 842.78 | AL47: 85.16 | AM47: 10.1 | AN47: 1.43 | AO47: 747.52 | AP47: 0 | AQ47: 58.4 | AR47: 0 | AS47: 0 | AT47: 109 | AU47: 61 | AV47: 1.067 | AW47: 1 | AZ47: 1 | BA47: 54.99 | BB47: 15.85 | BC47: 16.3 | BH47: 0 | BI47: 1 | BJ47: ТСН-2001.3 Доп. 79, Сб. 16, т. 13, поз. 1 | BM47: 21 | BN47: 58807811 | BO47: 3.16-13-1 | BP47: 1 | BQ47: 30 | BR47: 0 | BS47: 54.99 | BT47: 1 | BU47: 1 | BV47: 1 | BW47: 1 | BX47: 1 | BZ47: 109 | CA47: 61 | CE47: 30 | CF47: 0 | CG47: 0 | CM47: 0 | CN47: Поправка: О.П. п.3.4. 6 Наименование: Выполняемые при ремонте и реконструкции работы аналогичные технологическим процессам, характерным для нового строительства и отсутствующим в сборниках на ремонтно-строительные работы Поправка: О.П. п.3.4.30.в Наименование: При применении территориальных сметных нормативов для города Москвы затраты, учитывающие напряженные и стесненные условия производства работ (стесненность, сложность складирования и транспортной логистики и т.п.), исчисляются с применением коэффициентов к затратам труда и заработной плате рабочих, машинистов, времени эксплуатации машин и механизмов, стоимости эксплуатации машин в размере: для объектов, расположенных за пределами Третьего транспортного кольца города Москвы, но в пределах Московской кольцевой автомобильной дороги | CO47: 0 | CP47: =(P47+Q47+S47) -> 41116.68 | CQ47: =ROUND((ROUND((AC47*AW47*1),2)*BC47),2) -> 1388.11 | CR47: =(ROUND((ROUND(((((ET47*1.25)*1.1))*AV47*1),2)*BB47),2)+ROUND((ROUND(((AE47-(((EU47*1.25)*1.1)))*AV47*1),2)*BS47),2)) -> 234.9 | CS47: =ROUND((ROUND((AE47*AV47*1),2)*BS47),2) -> 115.48 | CT47: =ROUND((ROUND((AF47*AV47*1),2)*BA47),2) -> 55483.26 | CU47: =AG47 -> 0 | CV47: =(AH47*AV47) -> 78.825692 | CW47: =AI47 -> 0 | CX47: =AJ47 -> 0 | CY47: =(((S47+R47)*AT47)/100) -> 43633.866 | CZ47: =(((S47+R47)*AU47)/100) -> 24418.953 | DB47: 11 | DE47: *1,25)*1,1 | DF47: *1,25)*1,1 | DG47: *1,15)*1,1 | DI47: *1,15)*1,1 | DJ47: *1,25)*1,1 | DN47: 0 | DO47: 0 | DP47: 1 | DQ47: 1 | DU47: 1003 | DV47: 100 м | DW47: 100 м | DX47: 100 | EE47: 58807897 | EF47: 30 | EG47: Строительные работы | EH47: 0 | EJ47: 1 | EK47: 21 | EL47: ТСН-2001.3-16. Трубопроводы внутренние | EM47: ТСН-2001.3-16-1 | EO47: Поправка: О.П. п.3.4. 6 Поправка: О.П. п.3.4.30.в | EQ47: 0 | ER47: 842.78 | ES47: 85.16 | ET47: 10.1 | EU47: 1.43 | EV47: 747.52 | EW47: 58.4 | EX47: 0 | EY47: 0 | FQ47: 0 | FR47: 0 | FS47: 0 | FX47: 109 | FY47: 61 | GD47: 1 | GF47: 428623321 | GG47: 2 | GH47: 1 | GI47: 2 | GJ47: 0 | GK47: 0 | GL47: =ROUND(IF(AND(BH47=3,BI47=3,FS47<>0),P47,0),2) -> 0 | GM47: =ROUND(O47+X47+Y47,2)+GX47 -> 109169.5 | GN47: =IF(OR(BI47=0,BI47=1),GM47-GX47,0) -> 109169.5 | GO47: =IF(BI47=2,GM47-GX47,0) -> 0 | GP47: =IF(BI47=4,GM47-GX47,0) -> 0 | GR47: 0 | GS47: 3 | GT47: 0 | GV47: =ROUND((GT47),6) -> 0 | GW47: 1 | GX47: =ROUND(HC47*I47,2) -> 0 | HA47: 0 | HB47: 0 | HC47: =GV47*GW47 -> 0 | HS47: 0 | IK47: 0
A48: 18 | B48: 1 | C48: 46 | E48: 3,1 | F48: КА 25 | G48: Трубы канализационные раструбные марки ПП, ГОСТ 32412-213, Д=50 | H48: м | I48: =I46*J48 -> 72 | J48: 100 | K48: 100 | O48: =ROUND(CP48,2) -> 650.88 | P48: =ROUND((ROUND((AC48*AW48*I48),2)*BC48),2) -> 650.88 | Q48: =(ROUND((ROUND(((ET48)*AV48*I48),2)*BB48),2)+ROUND((ROUND(((AE48-(EU48))*AV48*I48),2)*BS48),2)) -> 0 | R48: =ROUND((ROUND((AE48*AV48*I48),2)*BS48),2) -> 0 | S48: =ROUND((ROUND((AF48*AV48*I48),2)*BA48),2) -> 0 | T48: =ROUND(CU48*I48,2) -> 0 | U48: =CV48*I48 -> 0 | V48: =CW48*I48 -> 0 | W48: =ROUND(CX48*I48,2) -> 0 | X48: =ROUND(CY48,2) -> 0 | Y48: =ROUND(CZ48,2) -> 0 | AA48: 59209203 | AB48: =ROUND((AC48+AD48+AF48),6) -> 9.04 | AC48: =ROUND((ES48),6) -> 9.04 | AD48: =ROUND((((ET48)-(EU48))+AE48),6) -> 0 | AE48: =ROUND((EU48),6) -> 0 | AF48: =ROUND((EV48),6) -> 0 | AG48: =ROUND((AP48),6) -> 0 | AH48: =(EW48) -> 0 | AI48: =(EX48) -> 0 | AJ48: =(AS48) -> 0 | AK48: 9.04 | AL48: 9.04 | AM48: 0 | AN48: 0 | AO48: 0 | AP48: 0 | AQ48: 0 | AR48: 0 | AS48: 0 | AT48: 109 | AU48: 61 | AV48: 1 | AW48: 1 | AZ48: 1 | BA48: 1 | BB48: 1 | BC48: 1 | BH48: 3 | BI48: 1 | BM48: 21 | BN48: 0 | BP48: 0 | BQ48: 30 | BR48: 0 | BS48: 1 | BT48: 1 | BU48: 1 | BV48: 1 | BW48: 1 | BX48: 1 | BZ48: 109 | CA48: 61 | CE48: 30 | CF48: 0 | CG48: 0 | CM48: 0 | CO48: 0 | CP48: =(P48+Q48+S48) -> 650.88 | CQ48: =ROUND((ROUND((AC48*AW48*1),2)*BC48),2) -> 9.04 | CR48: =(ROUND((ROUND(((ET48)*AV48*1),2)*BB48),2)+ROUND((ROUND(((AE48-(EU48))*AV48*1),2)*BS48),2)) -> 0 | CS48: =ROUND((ROUND((AE48*AV48*1),2)*BS48),2) -> 0 | CT48: =ROUND((ROUND((AF48*AV48*1),2)*BA48),2) -> 0 | CU48: =AG48 -> 0 | CV48: =(AH48*AV48) -> 0 | CW48: =AI48 -> 0 | CX48: =AJ48 -> 0 | CY48: =(((S48+R48)*AT48)/100) -> 0 | CZ48: =(((S48+R48)*AU48)/100) -> 0 | DN48: 0 | DO48: 0 | DP48: 1 | DQ48: 1 | DU48: 1003 | DV48: м | DW48: м | DX48: 1 | EE48: 58807897 | EF48: 30 | EG48: Строительные работы | EH48: 0 | EJ48: 1 | EK48: 21 | EL48: ТСН-2001.3-16. Трубопроводы внутренние | EM48: ТСН-2001.3-16-1 | EQ48: 0 | ER48: 0 | ES48: 9.04 | ET48: 0 | EU48: 0 | EV48: 0 | EW48: 0 | EX48: 0 | FQ48: 0 | FR48: 0 | FS48: 0 | FX48: 109 | FY48: 61 | GA48: [105 / 1,2 / 9,88] + 2% Заг.скл | GD48: 1 | GF48: 1334550293 | GG48: 2 | GH48: 4 | GI48: -2 | GJ48: 0 | GK48: 0 | GL48: =ROUND(IF(AND(BH48=3,BI48=3,FS48<>0),P48,0),2) -> 0 | GM48: =ROUND(O48+X48+Y48,2)+GX48 -> 650.88 | GN48: =IF(OR(BI48=0,BI48=1),GM48-GX48,0) -> 650.88 | GO48: =IF(BI48=2,GM48-GX48,0) -> 0 | GP48: =IF(BI48=4,GM48-GX48,0) -> 0 | GR48: 0 | GS48: 2 | GT48: 0 | GV48: =ROUND((GT48),6) -> 0 | GW48: 1 | GX48: =ROUND(HC48*I48,2) -> 0 | HA48: 0 | HB48: 0 | HC48: =GV48*GW48 -> 0 | HE48: 0 | HF48: 2 | HS48: 0 | IK48: 0
A49: 18 | B49: 1 | C49: 56 | E49: 3,1 | F49: КА 25 | G49: Трубы канализационные раструбные марки ПП, ГОСТ 32412-213, Д=50 | H49: м | I49: =I47*J49 -> 72 | J49: 100 | K49: 100 | O49: =ROUND(CP49,2) -> 6430.69 | P49: =ROUND((ROUND((AC49*AW49*I49),2)*BC49),2) -> 6430.69 | Q49: =(ROUND((ROUND(((ET49)*AV49*I49),2)*BB49),2)+ROUND((ROUND(((AE49-(EU49))*AV49*I49),2)*BS49),2)) -> 0 | R49: =ROUND((ROUND((AE49*AV49*I49),2)*BS49),2) -> 0 | S49: =ROUND((ROUND((AF49*AV49*I49),2)*BA49),2) -> 0 | T49: =ROUND(CU49*I49,2) -> 0 | U49: =CV49*I49 -> 0 | V49: =CW49*I49 -> 0 | W49: =ROUND(CX49*I49,2) -> 0 | X49: =ROUND(CY49,2) -> 0 | Y49: =ROUND(CZ49,2) -> 0 | AA49: 59209200 | AB49: =ROUND((AC49+AD49+AF49),6) -> 9.04 | AC49: =ROUND((ES49),6) -> 9.04 | AD49: =ROUND((((ET49)-(EU49))+AE49),6) -> 0 | AE49: =ROUND((EU49),6) -> 0 | AF49: =ROUND((EV49),6) -> 0 | AG49: =ROUND((AP49),6) -> 0 | AH49: =(EW49) -> 0 | AI49: =(EX49) -> 0 | AJ49: =(AS49) -> 0 | AK49: 9.04 | AL49: 9.04 | AM49: 0 | AN49: 0 | AO49: 0 | AP49: 0 | AQ49: 0 | AR49: 0 | AS49: 0 | AT49: 109 | AU49: 61 | AV49: 1 | AW49: 1 | AZ49: 1 | BA49: 1 | BB49: 1 | BC49: 9.88 | BH49: 3 | BI49: 1 | BM49: 21 | BN49: 0 | BP49: 0 | BQ49: 30 | BR49: 0 | BS49: 1 | BT49: 1 | BU49: 1 | BV49: 1 | BW49: 1 | BX49: 1 | BZ49: 109 | CA49: 61 | CE49: 30 | CF49: 0 | CG49: 0 | CM49: 0 | CO49: 0 | CP49: =(P49+Q49+S49) -> 6430.69 | CQ49: =ROUND((ROUND((AC49*AW49*1),2)*BC49),2) -> 89.32 | CR49: =(ROUND((ROUND(((ET49)*AV49*1),2)*BB49),2)+ROUND((ROUND(((AE49-(EU49))*AV49*1),2)*BS49),2)) -> 0 | CS49: =ROUND((ROUND((AE49*AV49*1),2)*BS49),2) -> 0 | CT49: =ROUND((ROUND((AF49*AV49*1),2)*BA49),2) -> 0 | CU49: =AG49 -> 0 | CV49: =(AH49*AV49) -> 0 | CW49: =AI49 -> 0 | CX49: =AJ49 -> 0 | CY49: =(((S49+R49)*AT49)/100) -> 0 | CZ49: =(((S49+R49)*AU49)/100) -> 0 | DN49: 0 | DO49: 0 | DP49: 1 | DQ49: 1 | DU49: 1003 | DV49: м | DW49: м | DX49: 1 | EE49: 58807897 | EF49: 30 | EG49: Строительные работы | EH49: 0 | EJ49: 1 | EK49: 21 | EL49: ТСН-2001.3-16. Трубопроводы внутренние | EM49: ТСН-2001.3-16-1 | EQ49: 0 | ER49: 9.04 | ES49: 9.04 | ET49: 0 | EU49: 0 | EV49: 0 | EW49: 0 | EX49: 0 | EZ49: 5 | FC49: 1 | FD49: 18 | FF49: 105 | FQ49: 0 | FR49: 0 | FS49: 0 | FX49: 109 | FY49: 61 | GA49: [105 / 1,2 / 9,88] + 2% Заг.скл | GD49: 1 | GF49: 1334550293 | GG49: 2 | GH49: 3 | GI49: 5 | GJ49: 0 | GK49: 0 | GL49: =ROUND(IF(AND(BH49=3,BI49=3,FS49<>0),P49,0),2) -> 0 | GM49: =ROUND(O49+X49+Y49,2)+GX49 -> 6430.69 | GN49: =IF(OR(BI49=0,BI49=1),GM49-GX49,0) -> 6430.69 | GO49: =IF(BI49=2,GM49-GX49,0) -> 0 | GP49: =IF(BI49=4,GM49-GX49,0) -> 0 | GR49: 1 | GS49: 1 | GT49: 0 | GV49: =ROUND((GT49),6) -> 0 | GW49: 1 | GX49: =ROUND(HC49*I49,2) -> 0 | HA49: 0 | HB49: 0 | HC49: =GV49*GW49 -> 0 | HE49: 0 | HF49: 2 | HS49: 0 | IK49: 0
A50: 18 | B50: 1 | C50: 44 | E50: 3,2 | F50: 1.12-5-97 | G50: Ревизия из полиэтилена низкого давления, с крышкой, для канализации, диаметр 50 мм | H50: шт. | I50: =I46*J50 -> 2 | J50: 2.7777778 | K50: 2.777778 | O50: =ROUND(CP50,2) -> 33.48 | P50: =ROUND((ROUND((AC50*AW50*I50),2)*BC50),2) -> 33.48 | Q50: =(ROUND((ROUND(((ET50)*AV50*I50),2)*BB50),2)+ROUND((ROUND(((AE50-(EU50))*AV50*I50),2)*BS50),2)) -> 0 | R50: =ROUND((ROUND((AE50*AV50*I50),2)*BS50),2) -> 0 | S50: =ROUND((ROUND((AF50*AV50*I50),2)*BA50),2) -> 0 | T50: =ROUND(CU50*I50,2) -> 0 | U50: =CV50*I50 -> 0 | V50: =CW50*I50 -> 0 | W50: =ROUND(CX50*I50,2) -> 0 | X50: =ROUND(CY50,2) -> 0 | Y50: =ROUND(CZ50,2) -> 0 | AA50: 59209203 | AB50: =ROUND((AC50+AD50+AF50),6) -> 16.74 | AC50: =ROUND((ES50),6) -> 16.74 | AD50: =ROUND((((ET50)-(EU50))+AE50),6) -> 0 | AE50: =ROUND((EU50),6) -> 0 | AF50: =ROUND((EV50),6) -> 0 | AG50: =ROUND((AP50),6) -> 0 | AH50: =(EW50) -> 0 | AI50: =(EX50) -> 0 | AJ50: =(AS50) -> 0 | AK50: 16.74 | AL50: 16.74 | AM50: 0 | AN50: 0 | AO50: 0 | AP50: 0 | AQ50: 0 | AR50: 0 | AS50: 0 | AT50: 109 | AU50: 61 | AV50: 1 | AW50: 1 | AZ50: 1 | BA50: 1 | BB50: 1 | BC50: 1 | BH50: 3 | BI50: 1 | BJ50: ТСН-2001.1 Доп. 67, Р. 12, о. 5, поз. 97 | BM50: 21 | BN50: 58807811 | BP50: 0 | BQ50: 30 | BR50: 0 | BS50: 1 | BT50: 1 | BU50: 1 | BV50: 1 | BW50: 1 | BX50: 1 | BZ50: 109 | CA50: 61 | CE50: 30 | CF50: 0 | CG50: 0 | CM50: 0 | CO50: 0 | CP50: =(P50+Q50+S50) -> 33.48 | CQ50: =ROUND((ROUND((AC50*AW50*1),2)*BC50),2) -> 16.74 | CR50: =(ROUND((ROUND(((ET50)*AV50*1),2)*BB50),2)+ROUND((ROUND(((AE50-(EU50))*AV50*1),2)*BS50),2)) -> 0 | CS50: =ROUND((ROUND((AE50*AV50*1),2)*BS50),2) -> 0 | CT50: =ROUND((ROUND((AF50*AV50*1),2)*BA50),2) -> 0 | CU50: =AG50 -> 0 | CV50: =(AH50*AV50) -> 0 | CW50: =AI50 -> 0 | CX50: =AJ50 -> 0 | CY50: =(((S50+R50)*AT50)/100) -> 0 | CZ50: =(((S50+R50)*AU50)/100) -> 0 | DN50: 0 | DO50: 0 | DP50: 1 | DQ50: 1 | DU50: 1010 | DV50: шт. | DW50: шт. | DX50: 1 | EE50: 58807897 | EF50: 30 | EG50: Строительные работы | EH50: 0 | EJ50: 1 | EK50: 21 | EL50: ТСН-2001.3-16. Трубопроводы внутренние | EM50: ТСН-2001.3-16-1 | EQ50: 0 | ER50: 16.74 | ES50: 16.74 | ET50: 0 | EU50: 0 | EV50: 0 | EW50: 0 | EX50: 0 | FQ50: 0 | FR50: 0 | FS50: 0 | FX50: 109 | FY50: 61 | GD50: 1 | GF50: 1223095212 | GG50: 2 | GH50: 1 | GI50: -2 | GJ50: 0 | GK50: 0 | GL50: =ROUND(IF(AND(BH50=3,BI50=3,FS50<>0),P50,0),2) -> 0 | GM50: =ROUND(O50+X50+Y50,2)+GX50 -> 33.48 | GN50: =IF(OR(BI50=0,BI50=1),GM50-GX50,0) -> 33.48 | GO50: =IF(BI50=2,GM50-GX50,0) -> 0 | GP50: =IF(BI50=4,GM50-GX50,0) -> 0 | GR50: 0 | GS50: 3 | GT50: 0 | GV50: =ROUND((GT50),6) -> 0 | GW50: 1 | GX50: =ROUND(HC50*I50,2) -> 0 | HA50: 0 | HB50: 0 | HC50: =GV50*GW50 -> 0 | HS50: 0 | IK50: 0
A51: 18 | B51: 1 | C51: 54 | E51: 3,2 | F51: 1.12-5-97 | G51: Ревизия из полиэтилена низкого давления, с крышкой, для канализации, диаметр 50 мм | H51: шт. | I51: =I47*J51 -> 2 | J51: 2.7777778 | K51: 2.777778 | O51: =ROUND(CP51,2) -> 117.51 | P51: =ROUND((ROUND((AC51*AW51*I51),2)*BC51),2) -> 117.51 | Q51: =(ROUND((ROUND(((ET51)*AV51*I51),2)*BB51),2)+ROUND((ROUND(((AE51-(EU51))*AV51*I51),2)*BS51),2)) -> 0 | R51: =ROUND((ROUND((AE51*AV51*I51),2)*BS51),2) -> 0 | S51: =ROUND((ROUND((AF51*AV51*I51),2)*BA51),2) -> 0 | T51: =ROUND(CU51*I51,2) -> 0 | U51: =CV51*I51 -> 0 | V51: =CW51*I51 -> 0 | W51: =ROUND(CX51*I51,2) -> 0 | X51: =ROUND(CY51,2) -> 0 | Y51: =ROUND(CZ51,2) -> 0 | AA51: 59209200 | AB51: =ROUND((AC51+AD51+AF51),6) -> 16.74 | AC51: =ROUND((ES51),6) -> 16.74 | AD51: =ROUND((((ET51)-(EU51))+AE51),6) -> 0 | AE51: =ROUND((EU51),6) -> 0 | AF51: =ROUND((EV51),6) -> 0 | AG51: =ROUND((AP51),6) -> 0 | AH51: =(EW51) -> 0 | AI51: =(EX51) -> 0 | AJ51: =(AS51) -> 0 | AK51: 16.74 | AL51: 16.74 | AM51: 0 | AN51: 0 | AO51: 0 | AP51: 0 | AQ51: 0 | AR51: 0 | AS51: 0 | AT51: 109 | AU51: 61 | AV51: 1 | AW51: 1 | AZ51: 1 | BA51: 1 | BB51: 1 | BC51: 3.51 | BH51: 3 | BI51: 1 | BJ51: ТСН-2001.1 Доп. 67, Р. 12, о. 5, поз. 97 | BM51: 21 | BN51: 58807811 | BO51: 1.12-5-97 | BP51: 1 | BQ51: 30 | BR51: 0 | BS51: 1 | BT51: 1 | BU51: 1 | BV51: 1 | BW51: 1 | BX51: 1 | BZ51: 109 | CA51: 61 | CE51: 30 | CF51: 0 | CG51: 0 | CM51: 0 | CO51: 0 | CP51: =(P51+Q51+S51) -> 117.51 | CQ51: =ROUND((ROUND((AC51*AW51*1),2)*BC51),2) -> 58.76 | CR51: =(ROUND((ROUND(((ET51)*AV51*1),2)*BB51),2)+ROUND((ROUND(((AE51-(EU51))*AV51*1),2)*BS51),2)) -> 0 | CS51: =ROUND((ROUND((AE51*AV51*1),2)*BS51),2) -> 0 | CT51: =ROUND((ROUND((AF51*AV51*1),2)*BA51),2) -> 0 | CU51: =AG51 -> 0 | CV51: =(AH51*AV51) -> 0 | CW51: =AI51 -> 0 | CX51: =AJ51 -> 0 | CY51: =(((S51+R51)*AT51)/100) -> 0 | CZ51: =(((S51+R51)*AU51)/100) -> 0 | DN51: 0 | DO51: 0 | DP51: 1 | DQ51: 1 | DU51: 1010 | DV51: шт. | DW51: шт. | DX51: 1 | EE51: 58807897 | EF51: 30 | EG51: Строительные работы | EH51: 0 | EJ51: 1 | EK51: 21 | EL51: ТСН-2001.3-16. Трубопроводы внутренние | EM51: ТСН-2001.3-16-1 | EQ51: 0 | ER51: 16.74 | ES51: 16.74 | ET51: 0 | EU51: 0 | EV51: 0 | EW51: 0 | EX51: 0 | FQ51: 0 | FR51: 0 | FS51: 0 | FX51: 109 | FY51: 61 | GD51: 1 | GF51: 1223095212 | GG51: 2 | GH51: 1 | GI51: 2 | GJ51: 0 | GK51: 0 | GL51: =ROUND(IF(AND(BH51=3,BI51=3,FS51<>0),P51,0),2) -> 0 | GM51: =ROUND(O51+X51+Y51,2)+GX51 -> 117.51 | GN51: =IF(OR(BI51=0,BI51=1),GM51-GX51,0) -> 117.51 | GO51: =IF(BI51=2,GM51-GX51,0) -> 0 | GP51: =IF(BI51=4,GM51-GX51,0) -> 0 | GR51: 0 | GS51: 3 | GT51: 0 | GV51: =ROUND((GT51),6) -> 0 | GW51: 1 | GX51: =ROUND(HC51*I51,2) -> 0 | HA51: 0 | HB51: 0 | HC51: =GV51*GW51 -> 0 | HS51: 0 | IK51: 0
A52: 18 | B52: 1 | C52: 45 | E52: 3,3 | F52: 1.12-5-97 | G52: Ревизия из полиэтилена низкого давления, с крышкой, для канализации, диаметр 50 мм /прочистка | H52: шт. | I52: =I46*J52 -> 2 | J52: 2.7777778 | K52: 2.777778 | O52: =ROUND(CP52,2) -> 33.48 | P52: =ROUND((ROUND((AC52*AW52*I52),2)*BC52),2) -> 33.48 | Q52: =(ROUND((ROUND(((ET52)*AV52*I52),2)*BB52),2)+ROUND((ROUND(((AE52-(EU52))*AV52*I52),2)*BS52),2)) -> 0 | R52: =ROUND((ROUND((AE52*AV52*I52),2)*BS52),2) -> 0 | S52: =ROUND((ROUND((AF52*AV52*I52),2)*BA52),2) -> 0 | T52: =ROUND(CU52*I52,2) -> 0 | U52: =CV52*I52 -> 0 | V52: =CW52*I52 -> 0 | W52: =ROUND(CX52*I52,2) -> 0 | X52: =ROUND(CY52,2) -> 0 | Y52: =ROUND(CZ52,2) -> 0 | AA52: 59209203 | AB52: =ROUND((AC52+AD52+AF52),6) -> 16.74 | AC52: =ROUND((ES52),6) -> 16.74 | AD52: =ROUND((((ET52)-(EU52))+AE52),6) -> 0 | AE52: =ROUND((EU52),6) -> 0 | AF52: =ROUND((EV52),6) -> 0 | AG52: =ROUND((AP52),6) -> 0 | AH52: =(EW52) -> 0 | AI52: =(EX52) -> 0 | AJ52: =(AS52) -> 0 | AK52: 16.74 | AL52: 16.74 | AM52: 0 | AN52: 0 | AO52: 0 | AP52: 0 | AQ52: 0 | AR52: 0 | AS52: 0 | AT52: 109 | AU52: 61 | AV52: 1 | AW52: 1 | AZ52: 1 | BA52: 1 | BB52: 1 | BC52: 1 | BH52: 3 | BI52: 1 | BJ52: ТСН-2001.1 Доп. 67, Р. 12, о. 5, поз. 97 | BM52: 21 | BN52: 58807811 | BP52: 0 | BQ52: 30 | BR52: 0 | BS52: 1 | BT52: 1 | BU52: 1 | BV52: 1 | BW52: 1 | BX52: 1 | BZ52: 109 | CA52: 61 | CE52: 30 | CF52: 0 | CG52: 0 | CM52: 0 | CO52: 0 | CP52: =(P52+Q52+S52) -> 33.48 | CQ52: =ROUND((ROUND((AC52*AW52*1),2)*BC52),2) -> 16.74 | CR52: =(ROUND((ROUND(((ET52)*AV52*1),2)*BB52),2)+ROUND((ROUND(((AE52-(EU52))*AV52*1),2)*BS52),2)) -> 0 | CS52: =ROUND((ROUND((AE52*AV52*1),2)*BS52),2) -> 0 | CT52: =ROUND((ROUND((AF52*AV52*1),2)*BA52),2) -> 0 | CU52: =AG52 -> 0 | CV52: =(AH52*AV52) -> 0 | CW52: =AI52 -> 0 | CX52: =AJ52 -> 0 | CY52: =(((S52+R52)*AT52)/100) -> 0 | CZ52: =(((S52+R52)*AU52)/100) -> 0 | DN52: 0 | DO52: 0 | DP52: 1 | DQ52: 1 | DU52: 1010 | DV52: шт. | DW52: шт. | DX52: 1 | EE52: 58807897 | EF52: 30 | EG52: Строительные работы | EH52: 0 | EJ52: 1 | EK52: 21 | EL52: ТСН-2001.3-16. Трубопроводы внутренние | EM52: ТСН-2001.3-16-1 | EQ52: 0 | ER52: 16.74 | ES52: 16.74 | ET52: 0 | EU52: 0 | EV52: 0 | EW52: 0 | EX52: 0 | FQ52: 0 | FR52: 0 | FS52: 0 | FX52: 109 | FY52: 61 | GD52: 1 | GF52: 491549712 | GG52: 2 | GH52: 1 | GI52: -2 | GJ52: 0 | GK52: 0 | GL52: =ROUND(IF(AND(BH52=3,BI52=3,FS52<>0),P52,0),2) -> 0 | GM52: =ROUND(O52+X52+Y52,2)+GX52 -> 33.48 | GN52: =IF(OR(BI52=0,BI52=1),GM52-GX52,0) -> 33.48 | GO52: =IF(BI52=2,GM52-GX52,0) -> 0 | GP52: =IF(BI52=4,GM52-GX52,0) -> 0 | GR52: 0 | GS52: 3 | GT52: 0 | GV52: =ROUND((GT52),6) -> 0 | GW52: 1 | GX52: =ROUND(HC52*I52,2) -> 0 | HA52: 0 | HB52: 0 | HC52: =GV52*GW52 -> 0 | HS52: 0 | IK52: 0
A53: 18 | B53: 1 | C53: 55 | E53: 3,3 | F53: 1.12-5-97 | G53: Ревизия из полиэтилена низкого давления, с крышкой, для канализации, диаметр 50 мм /прочистка | H53: шт. | I53: =I47*J53 -> 2 | J53: 2.7777778 | K53: 2.777778 | O53: =ROUND(CP53,2) -> 117.51 | P53: =ROUND((ROUND((AC53*AW53*I53),2)*BC53),2) -> 117.51 | Q53: =(ROUND((ROUND(((ET53)*AV53*I53),2)*BB53),2)+ROUND((ROUND(((AE53-(EU53))*AV53*I53),2)*BS53),2)) -> 0 | R53: =ROUND((ROUND((AE53*AV53*I53),2)*BS53),2) -> 0 | S53: =ROUND((ROUND((AF53*AV53*I53),2)*BA53),2) -> 0 | T53: =ROUND(CU53*I53,2) -> 0 | U53: =CV53*I53 -> 0 | V53: =CW53*I53 -> 0 | W53: =ROUND(CX53*I53,2) -> 0 | X53: =ROUND(CY53,2) -> 0 | Y53: =ROUND(CZ53,2) -> 0 | AA53: 59209200 | AB53: =ROUND((AC53+AD53+AF53),6) -> 16.74 | AC53: =ROUND((ES53),6) -> 16.74 | AD53: =ROUND((((ET53)-(EU53))+AE53),6) -> 0 | AE53: =ROUND((EU53),6) -> 0 | AF53: =ROUND((EV53),6) -> 0 | AG53: =ROUND((AP53),6) -> 0 | AH53: =(EW53) -> 0 | AI53: =(EX53) -> 0 | AJ53: =(AS53) -> 0 | AK53: 16.74 | AL53: 16.74 | AM53: 0 | AN53: 0 | AO53: 0 | AP53: 0 | AQ53: 0 | AR53: 0 | AS53: 0 | AT53: 109 | AU53: 61 | AV53: 1 | AW53: 1 | AZ53: 1 | BA53: 1 | BB53: 1 | BC53: 3.51 | BH53: 3 | BI53: 1 | BJ53: ТСН-2001.1 Доп. 67, Р. 12, о. 5, поз. 97 | BM53: 21 | BN53: 58807811 | BO53: 1.12-5-97 | BP53: 1 | BQ53: 30 | BR53: 0 | BS53: 1 | BT53: 1 | BU53: 1 | BV53: 1 | BW53: 1 | BX53: 1 | BZ53: 109 | CA53: 61 | CE53: 30 | CF53: 0 | CG53: 0 | CM53: 0 | CO53: 0 | CP53: =(P53+Q53+S53) -> 117.51 | CQ53: =ROUND((ROUND((AC53*AW53*1),2)*BC53),2) -> 58.76 | CR53: =(ROUND((ROUND(((ET53)*AV53*1),2)*BB53),2)+ROUND((ROUND(((AE53-(EU53))*AV53*1),2)*BS53),2)) -> 0 | CS53: =ROUND((ROUND((AE53*AV53*1),2)*BS53),2) -> 0 | CT53: =ROUND((ROUND((AF53*AV53*1),2)*BA53),2) -> 0 | CU53: =AG53 -> 0 | CV53: =(AH53*AV53) -> 0 | CW53: =AI53 -> 0 | CX53: =AJ53 -> 0 | CY53: =(((S53+R53)*AT53)/100) -> 0 | CZ53: =(((S53+R53)*AU53)/100) -> 0 | DN53: 0 | DO53: 0 | DP53: 1 | DQ53: 1 | DU53: 1010 | DV53: шт. | DW53: шт. | DX53: 1 | EE53: 58807897 | EF53: 30 | EG53: Строительные работы | EH53: 0 | EJ53: 1 | EK53: 21 | EL53: ТСН-2001.3-16. Трубопроводы внутренние | EM53: ТСН-2001.3-16-1 | EQ53: 0 | ER53: 16.74 | ES53: 16.74 | ET53: 0 | EU53: 0 | EV53: 0 | EW53: 0 | EX53: 0 | FQ53: 0 | FR53: 0 | FS53: 0 | FX53: 109 | FY53: 61 | GD53: 1 | GF53: 491549712 | GG53: 2 | GH53: 1 | GI53: 2 | GJ53: 0 | GK53: 0 | GL53: =ROUND(IF(AND(BH53=3,BI53=3,FS53<>0),P53,0),2) -> 0 | GM53: =ROUND(O53+X53+Y53,2)+GX53 -> 117.51 | GN53: =IF(OR(BI53=0,BI53=1),GM53-GX53,0) -> 117.51 | GO53: =IF(BI53=2,GM53-GX53,0) -> 0 | GP53: =IF(BI53=4,GM53-GX53,0) -> 0 | GR53: 0 | GS53: 3 | GT53: 0 | GV53: =ROUND((GT53),6) -> 0 | GW53: 1 | GX53: =ROUND(HC53*I53,2) -> 0 | HA53: 0 | HB53: 0 | HC53: =GV53*GW53 -> 0 | HS53: 0 | IK53: 0
A54: 18 | B54: 1 | C54: 42 | E54: 3,4 | F54: 1.12-2-1165 | G54: Хомуты из оцинкованной стали с резиновыми прокладками для жесткого и скользящего крепления полипропиленовых труб, наружный диаметр 50 мм | H54: шт. | I54: =I46*J54 -> 24 | J54: 33.333333 | K54: 33.333333 | O54: =ROUND(CP54,2) -> 525.6 | P54: =ROUND((ROUND((AC54*AW54*I54),2)*BC54),2) -> 525.6 | Q54: =(ROUND((ROUND(((ET54)*AV54*I54),2)*BB54),2)+ROUND((ROUND(((AE54-(EU54))*AV54*I54),2)*BS54),2)) -> 0 | R54: =ROUND((ROUND((AE54*AV54*I54),2)*BS54),2) -> 0 | S54: =ROUND((ROUND((AF54*AV54*I54),2)*BA54),2) -> 0 | T54: =ROUND(CU54*I54,2) -> 0 | U54: =CV54*I54 -> 0 | V54: =CW54*I54 -> 0 | W54: =ROUND(CX54*I54,2) -> 0 | X54: =ROUND(CY54,2) -> 0 | Y54: =ROUND(CZ54,2) -> 0 | AA54: 59209203 | AB54: =ROUND((AC54+AD54+AF54),6) -> 21.9 | AC54: =ROUND((ES54),6) -> 21.9 | AD54: =ROUND((((ET54)-(EU54))+AE54),6) -> 0 | AE54: =ROUND((EU54),6) -> 0 | AF54: =ROUND((EV54),6) -> 0 | AG54: =ROUND((AP54),6) -> 0 | AH54: =(EW54) -> 0 | AI54: =(EX54) -> 0 | AJ54: =(AS54) -> 0 | AK54: 21.9 | AL54: 21.9 | AM54: 0 | AN54: 0 | AO54: 0 | AP54: 0 | AQ54: 0 | AR54: 0 | AS54: 0 | AT54: 109 | AU54: 61 | AV54: 1 | AW54: 1 | AZ54: 1 | BA54: 1 | BB54: 1 | BC54: 1 | BH54: 3 | BI54: 1 | BJ54: ТСН-2001.1 Доп. 46, Р. 12, о. 2, поз. 1165 | BM54: 21 | BN54: 0 | BP54: 0 | BQ54: 30 | BR54: 0 | BS54: 1 | BT54: 1 | BU54: 1 | BV54: 1 | BW54: 1 | BX54: 1 | BZ54: 109 | CA54: 61 | CE54: 30 | CF54: 0 | CG54: 0 | CM54: 0 | CO54: 0 | CP54: =(P54+Q54+S54) -> 525.6 | CQ54: =ROUND((ROUND((AC54*AW54*1),2)*BC54),2) -> 21.9 | CR54: =(ROUND((ROUND(((ET54)*AV54*1),2)*BB54),2)+ROUND((ROUND(((AE54-(EU54))*AV54*1),2)*BS54),2)) -> 0 | CS54: =ROUND((ROUND((AE54*AV54*1),2)*BS54),2) -> 0 | CT54: =ROUND((ROUND((AF54*AV54*1),2)*BA54),2) -> 0 | CU54: =AG54 -> 0 | CV54: =(AH54*AV54) -> 0 | CW54: =AI54 -> 0 | CX54: =AJ54 -> 0 | CY54: =(((S54+R54)*AT54)/100) -> 0 | CZ54: =(((S54+R54)*AU54)/100) -> 0 | DN54: 0 | DO54: 0 | DP54: 1 | DQ54: 1 | DU54: 1010 | DV54: шт. | DW54: шт. | DX54: 1 | EE54: 58807897 | EF54: 30 | EG54: Строительные работы | EH54: 0 | EJ54: 1 | EK54: 21 | EL54: ТСН-2001.3-16. Трубопроводы внутренние | EM54: ТСН-2001.3-16-1 | EQ54: 0 | ER54: 21.9 | ES54: 21.9 | ET54: 0 | EU54: 0 | EV54: 0 | EW54: 0 | EX54: 0 | FQ54: 0 | FR54: 0 | FS54: 0 | FX54: 109 | FY54: 61 | GD54: 1 | GF54: -1455693793 | GG54: 2 | GH54: 1 | GI54: -2 | GJ54: 0 | GK54: 0 | GL54: =ROUND(IF(AND(BH54=3,BI54=3,FS54<>0),P54,0),2) -> 0 | GM54: =ROUND(O54+X54+Y54,2)+GX54 -> 525.6 | GN54: =IF(OR(BI54=0,BI54=1),GM54-GX54,0) -> 525.6 | GO54: =IF(BI54=2,GM54-GX54,0) -> 0 | GP54: =IF(BI54=4,GM54-GX54,0) -> 0 | GR54: 0 | GS54: 3 | GT54: 0 | GV54: =ROUND((GT54),6) -> 0 | GW54: 1 | GX54: =ROUND(HC54*I54,2) -> 0 | HA54: 0 | HB54: 0 | HC54: =GV54*GW54 -> 0 | HS54: 0 | IK54: 0
A55: 18 | B55: 1 | C55: 52 | E55: 3,4 | F55: 1.12-2-1165 | G55: Хомуты из оцинкованной стали с резиновыми прокладками для жесткого и скользящего крепления полипропиленовых труб, наружный диаметр 50 мм | H55: шт. | I55: =I47*J55 -> 24 | J55: 33.333333 | K55: 33.333333 | O55: =ROUND(CP55,2) -> 509.83 | P55: =ROUND((ROUND((AC55*AW55*I55),2)*BC55),2) -> 509.83 | Q55: =(ROUND((ROUND(((ET55)*AV55*I55),2)*BB55),2)+ROUND((ROUND(((AE55-(EU55))*AV55*I55),2)*BS55),2)) -> 0 | R55: =ROUND((ROUND((AE55*AV55*I55),2)*BS55),2) -> 0 | S55: =ROUND((ROUND((AF55*AV55*I55),2)*BA55),2) -> 0 | T55: =ROUND(CU55*I55,2) -> 0 | U55: =CV55*I55 -> 0 | V55: =CW55*I55 -> 0 | W55: =ROUND(CX55*I55,2) -> 0 | X55: =ROUND(CY55,2) -> 0 | Y55: =ROUND(CZ55,2) -> 0 | AA55: 59209200 | AB55: =ROUND((AC55+AD55+AF55),6) -> 21.9 | AC55: =ROUND((ES55),6) -> 21.9 | AD55: =ROUND((((ET55)-(EU55))+AE55),6) -> 0 | AE55: =ROUND((EU55),6) -> 0 | AF55: =ROUND((EV55),6) -> 0 | AG55: =ROUND((AP55),6) -> 0 | AH55: =(EW55) -> 0 | AI55: =(EX55) -> 0 | AJ55: =(AS55) -> 0 | AK55: 21.9 | AL55: 21.9 | AM55: 0 | AN55: 0 | AO55: 0 | AP55: 0 | AQ55: 0 | AR55: 0 | AS55: 0 | AT55: 109 | AU55: 61 | AV55: 1 | AW55: 1 | AZ55: 1 | BA55: 1 | BB55: 1 | BC55: 0.97 | BH55: 3 | BI55: 1 | BJ55: ТСН-2001.1 Доп. 46, Р. 12, о. 2, поз. 1165 | BM55: 21 | BN55: 0 | BO55: 1.12-2-1165 | BP55: 1 | BQ55: 30 | BR55: 0 | BS55: 1 | BT55: 1 | BU55: 1 | BV55: 1 | BW55: 1 | BX55: 1 | BZ55: 109 | CA55: 61 | CE55: 30 | CF55: 0 | CG55: 0 | CM55: 0 | CO55: 0 | CP55: =(P55+Q55+S55) -> 509.83 | CQ55: =ROUND((ROUND((AC55*AW55*1),2)*BC55),2) -> 21.24 | CR55: =(ROUND((ROUND(((ET55)*AV55*1),2)*BB55),2)+ROUND((ROUND(((AE55-(EU55))*AV55*1),2)*BS55),2)) -> 0 | CS55: =ROUND((ROUND((AE55*AV55*1),2)*BS55),2) -> 0 | CT55: =ROUND((ROUND((AF55*AV55*1),2)*BA55),2) -> 0 | CU55: =AG55 -> 0 | CV55: =(AH55*AV55) -> 0 | CW55: =AI55 -> 0 | CX55: =AJ55 -> 0 | CY55: =(((S55+R55)*AT55)/100) -> 0 | CZ55: =(((S55+R55)*AU55)/100) -> 0 | DN55: 0 | DO55: 0 | DP55: 1 | DQ55: 1 | DU55: 1010 | DV55: шт. | DW55: шт. | DX55: 1 | EE55: 58807897 | EF55: 30 | EG55: Строительные работы | EH55: 0 | EJ55: 1 | EK55: 21 | EL55: ТСН-2001.3-16. Трубопроводы внутренние | EM55: ТСН-2001.3-16-1 | EQ55: 0 | ER55: 21.9 | ES55: 21.9 | ET55: 0 | EU55: 0 | EV55: 0 | EW55: 0 | EX55: 0 | FQ55: 0 | FR55: 0 | FS55: 0 | FX55: 109 | FY55: 61 | GD55: 1 | GF55: -1455693793 | GG55: 2 | GH55: 1 | GI55: 2 | GJ55: 0 | GK55: 0 | GL55: =ROUND(IF(AND(BH55=3,BI55=3,FS55<>0),P55,0),2) -> 0 | GM55: =ROUND(O55+X55+Y55,2)+GX55 -> 509.83 | GN55: =IF(OR(BI55=0,BI55=1),GM55-GX55,0) -> 509.83 | GO55: =IF(BI55=2,GM55-GX55,0) -> 0 | GP55: =IF(BI55=4,GM55-GX55,0) -> 0 | GR55: 0 | GS55: 3 | GT55: 0 | GV55: =ROUND((GT55),6) -> 0 | GW55: 1 | GX55: =ROUND(HC55*I55,2) -> 0 | HA55: 0 | HB55: 0 | HC55: =GV55*GW55 -> 0 | HS55: 0 | IK55: 0
A56: 17 | B56: 1 | C56: =ROW(SmtRes!A60) -> 60 | D56: =ROW(EtalonRes!A59) -> 59 | E56: 4 | F56: 3.16-28-2 | G56: Врезки в действующие внутренние сети трубопроводов канализации диаметром 100 мм | H56: 1 врезка | I56: =ROUND(ROUND(3,4),9) -> 3 | J56: 0 | K56: =ROUND(ROUND(3,4),9) -> 3 | O56: =ROUND(CP56,2) -> 432.4 | P56: =ROUND((ROUND((AC56*AW56*I56),2)*BC56),2) -> 24.03 | Q56: =(ROUND((ROUND(((((ET56*1.25)*1.1))*AV56*I56),2)*BB56),2)+ROUND((ROUND(((AE56-(((EU56*1.25)*1.1)))*AV56*I56),2)*BS56),2)) -> 3.65 | R56: =ROUND((ROUND((AE56*AV56*I56),2)*BS56),2) -> 0.57 | S56: =ROUND((ROUND((AF56*AV56*I56),2)*BA56),2) -> 404.72 | T56: =ROUND(CU56*I56,2) -> 0 | U56: =CV56*I56 -> 36.200429 | V56: =CW56*I56 -> 0 | W56: =ROUND(CX56*I56,2) -> 0 | X56: =ROUND(CY56,2) -> 441.77 | Y56: =ROUND(CZ56,2) -> 247.23 | AA56: 59209203 | AB56: =ROUND((AC56+AD56+AF56),6) -> 135.588 | AC56: =ROUND((ES56),6) -> 8.01 | AD56: =ROUND((((((ET56*1.25)*1.1))-(((EU56*1.25)*1.1)))+AE56),6) -> 1.14125 | AE56: =ROUND((((EU56*1.25)*1.1)),6) -> 0.17875 | AF56: =ROUND((((EV56*1.15)*1.1)),6) -> 126.43675 | AG56: =ROUND((AP56),6) -> 0 | AH56: =(((EW56*1.15)*1.1)) -> 11.3091 | AI56: =(((EX56*1.25)*1.1)) -> 0 | AJ56: =(AS56) -> 0 | AK56: 108.79 | AL56: 8.01 | AM56: 0.83 | AN56: 0.13 | AO56: 99.95 | AP56: 0 | AQ56: 8.94 | AR56: 0 | AS56: 0 | AT56: 109 | AU56: 61 | AV56: 1.067 | AW56: 1 | AZ56: 1 | BA56: 1 | BB56: 1 | BC56: 1 | BH56: 0 | BI56: 1 | BJ56: ТСН-2001.3 Доп. 79, Сб. 16, т. 28, поз. 2 | BM56: 21 | BN56: 58807811 | BO56: 3.16-28-2 | BP56: 1 | BQ56: 30 | BR56: 0 | BS56: 1 | BT56: 1 | BU56: 1 | BV56: 1 | BW56: 1 | BX56: 1 | BZ56: 109 | CA56: 61 | CE56: 30 | CF56: 0 | CG56: 0 | CM56: 0 | CN56: Поправка: О.П. п.3.4. 6 Наименование: Выполняемые при ремонте и реконструкции работы аналогичные технологическим процессам, характерным для нового строительства и отсутствующим в сборниках на ремонтно-строительные работы Поправка: О.П. п.3.4.30.в Наименование: При применении территориальных сметных нормативов для города Москвы затраты, учитывающие напряженные и стесненные условия производства работ (стесненность, сложность складирования и транспортной логистики и т.п.), исчисляются с применением коэффициентов к затратам труда и заработной плате рабочих, машинистов, времени эксплуатации машин и механизмов, стоимости эксплуатации машин в размере: для объектов, расположенных за пределами Третьего транспортного кольца города Москвы, но в пределах Московской кольцевой автомобильной дороги | CO56: 0 | CP56: =(P56+Q56+S56) -> 432.4 | CQ56: =ROUND((ROUND((AC56*AW56*1),2)*BC56),2) -> 8.01 | CR56: =(ROUND((ROUND(((((ET56*1.25)*1.1))*AV56*1),2)*BB56),2)+ROUND((ROUND(((AE56-(((EU56*1.25)*1.1)))*AV56*1),2)*BS56),2)) -> 1.22 | CS56: =ROUND((ROUND((AE56*AV56*1),2)*BS56),2) -> 0.19 | CT56: =ROUND((ROUND((AF56*AV56*1),2)*BA56),2) -> 134.91 | CU56: =AG56 -> 0 | CV56: =(AH56*AV56) -> 12.06681 | CW56: =AI56 -> 0 | CX56: =AJ56 -> 0 | CY56: =(((S56+R56)*AT56)/100) -> 441.7661 | CZ56: =(((S56+R56)*AU56)/100) -> 247.2269 | DB56: 13 | DE56: *1,25)*1,1 | DF56: *1,25)*1,1 | DG56: *1,15)*1,1 | DI56: *1,15)*1,1 | DJ56: *1,25)*1,1 | DN56: 0 | DO56: 0 | DP56: 1 | DQ56: 1 | DU56: 1013 | DV56: 1 врезка | DW56: 1 врезка | DX56: 1 | EE56: 58807897 | EF56: 30 | EG56: Строительные работы | EH56: 0 | EJ56: 1 | EK56: 21 | EL56: ТСН-2001.3-16. Трубопроводы внутренние | EM56: ТСН-2001.3-16-1 | EO56: Поправка: О.П. п.3.4. 6 Поправка: О.П. п.3.4.30.в | EQ56: 0 | ER56: 108.79 | ES56: 8.01 | ET56: 0.83 | EU56: 0.13 | EV56: 99.95 | EW56: 8.94 | EX56: 0 | EY56: 0 | FQ56: 0 | FR56: 0 | FS56: 0 | FX56: 109 | FY56: 61 | GD56: 1 | GF56: -2118052753 | GG56: 2 | GH56: 1 | GI56: 2 | GJ56: 0 | GK56: 0 | GL56: =ROUND(IF(AND(BH56=3,BI56=3,FS56<>0),P56,0),2) -> 0 | GM56: =ROUND(O56+X56+Y56,2)+GX56 -> 1121.4 | GN56: =IF(OR(BI56=0,BI56=1),GM56-GX56,0) -> 1121.4 | GO56: =IF(BI56=2,GM56-GX56,0) -> 0 | GP56: =IF(BI56=4,GM56-GX56,0) -> 0 | GR56: 0 | GS56: 3 | GT56: 0 | GV56: =ROUND((GT56),6) -> 0 | GW56: 1 | GX56: =ROUND(HC56*I56,2) -> 0 | HA56: 0 | HB56: 0 | HC56: =GV56*GW56 -> 0 | HS56: 0 | IK56: 0
A57: 17 | B57: 1 | C57: =ROW(SmtRes!A64) -> 64 | D57: =ROW(EtalonRes!A66) -> 66 | E57: 4 | F57: 3.16-28-2 | G57: Врезки в действующие внутренние сети трубопроводов канализации диаметром 100 мм | H57: 1 врезка | I57: =ROUND(ROUND(3,4),9) -> 3 | J57: 0 | K57: =ROUND(ROUND(3,4),9) -> 3 | O57: =ROUND(CP57,2) -> 22827.23 | P57: =ROUND((ROUND((AC57*AW57*I57),2)*BC57),2) -> 512.08 | Q57: =(ROUND((ROUND(((((ET57*1.25)*1.1))*AV57*I57),2)*BB57),2)+ROUND((ROUND(((AE57-(((EU57*1.25)*1.1)))*AV57*I57),2)*BS57),2)) -> 59.6 | R57: =ROUND((ROUND((AE57*AV57*I57),2)*BS57),2) -> 31.34 | S57: =ROUND((ROUND((AF57*AV57*I57),2)*BA57),2) -> 22255.55 | T57: =ROUND(CU57*I57,2) -> 0 | U57: =CV57*I57 -> 36.200429 | V57: =CW57*I57 -> 0 | W57: =ROUND(CX57*I57,2) -> 0 | X57: =ROUND(CY57,2) -> 24292.71 | Y57: =ROUND(CZ57,2) -> 13595 | AA57: 59209200 | AB57: =ROUND((AC57+AD57+AF57),6) -> 135.588 | AC57: =ROUND((ES57),6) -> 8.01 | AD57: =ROUND((((((ET57*1.25)*1.1))-(((EU57*1.25)*1.1)))+AE57),6) -> 1.14125 | AE57: =ROUND((((EU57*1.25)*1.1)),6) -> 0.17875 | AF57: =ROUND((((EV57*1.15)*1.1)),6) -> 126.43675 | AG57: =ROUND((AP57),6) -> 0 | AH57: =(((EW57*1.15)*1.1)) -> 11.3091 | AI57: =(((EX57*1.25)*1.1)) -> 0 | AJ57: =(AS57) -> 0 | AK57: 108.79 | AL57: 8.01 | AM57: 0.83 | AN57: 0.13 | AO57: 99.95 | AP57: 0 | AQ57: 8.94 | AR57: 0 | AS57: 0 | AT57: 109 | AU57: 61 | AV57: 1.067 | AW57: 1 | AZ57: 1 | BA57: 54.99 | BB57: 16.33 | BC57: 21.31 | BH57: 0 | BI57: 1 | BJ57: ТСН-2001.3 Доп. 79, Сб. 16, т. 28, поз. 2 | BM57: 21 | BN57: 58807811 | BO57: 3.16-28-2 | BP57: 1 | BQ57: 30 | BR57: 0 | BS57: 54.99 | BT57: 1 | BU57: 1 | BV57: 1 | BW57: 1 | BX57: 1 | BZ57: 109 | CA57: 61 | CE57: 30 | CF57: 0 | CG57: 0 | CM57: 0 | CN57: Поправка: О.П. п.3.4. 6 Наименование: Выполняемые при ремонте и реконструкции работы аналогичные технологическим процессам, характерным для нового строительства и отсутствующим в сборниках на ремонтно-строительные работы Поправка: О.П. п.3.4.30.в Наименование: При применении территориальных сметных нормативов для города Москвы затраты, учитывающие напряженные и стесненные условия производства работ (стесненность, сложность складирования и транспортной логистики и т.п.), исчисляются с применением коэффициентов к затратам труда и заработной плате рабочих, машинистов, времени эксплуатации машин и механизмов, стоимости эксплуатации машин в размере: для объектов, расположенных за пределами Третьего транспортного кольца города Москвы, но в пределах Московской кольцевой автомобильной дороги | CO57: 0 | CP57: =(P57+Q57+S57) -> 22827.23 | CQ57: =ROUND((ROUND((AC57*AW57*1),2)*BC57),2) -> 170.69 | CR57: =(ROUND((ROUND(((((ET57*1.25)*1.1))*AV57*1),2)*BB57),2)+ROUND((ROUND(((AE57-(((EU57*1.25)*1.1)))*AV57*1),2)*BS57),2)) -> 19.92 | CS57: =ROUND((ROUND((AE57*AV57*1),2)*BS57),2) -> 10.45 | CT57: =ROUND((ROUND((AF57*AV57*1),2)*BA57),2) -> 7418.7 | CU57: =AG57 -> 0 | CV57: =(AH57*AV57) -> 12.06681 | CW57: =AI57 -> 0 | CX57: =AJ57 -> 0 | CY57: =(((S57+R57)*AT57)/100) -> 24292.71 | CZ57: =(((S57+R57)*AU57)/100) -> 13595.003 | DB57: 15 | DE57: *1,25)*1,1 | DF57: *1,25)*1,1 | DG57: *1,15)*1,1 | DI57: *1,15)*1,1 | DJ57: *1,25)*1,1 | DN57: 0 | DO57: 0 | DP57: 1 | DQ57: 1 | DU57: 1013 | DV57: 1 врезка | DW57: 1 врезка | DX57: 1 | EE57: 58807897 | EF57: 30 | EG57: Строительные работы | EH57: 0 | EJ57: 1 | EK57: 21 | EL57: ТСН-2001.3-16. Трубопроводы внутренние | EM57: ТСН-2001.3-16-1 | EO57: Поправка: О.П. п.3.4. 6 Поправка: О.П. п.3.4.30.в | EQ57: 0 | ER57: 108.79 | ES57: 8.01 | ET57: 0.83 | EU57: 0.13 | EV57: 99.95 | EW57: 8.94 | EX57: 0 | EY57: 0 | FQ57: 0 | FR57: 0 | FS57: 0 | FX57: 109 | FY57: 61 | GD57: 1 | GF57: -2118052753 | GG57: 2 | GH57: 1 | GI57: 2 | GJ57: 0 | GK57: 0 | GL57: =ROUND(IF(AND(BH57=3,BI57=3,FS57<>0),P57,0),2) -> 0 | GM57: =ROUND(O57+X57+Y57,2)+GX57 -> 60714.94 | GN57: =IF(OR(BI57=0,BI57=1),GM57-GX57,0) -> 60714.94 | GO57: =IF(BI57=2,GM57-GX57,0) -> 0 | GP57: =IF(BI57=4,GM57-GX57,0) -> 0 | GR57: 0 | GS57: 3 | GT57: 0 | GV57: =ROUND((GT57),6) -> 0 | GW57: 1 | GX57: =ROUND(HC57*I57,2) -> 0 | HA57: 0 | HB57: 0 | HC57: =GV57*GW57 -> 0 | HS57: 0 | IK57: 0
A58: 17 | B58: 1 | C58: =ROW(SmtRes!A67) -> 67 | D58: =ROW(EtalonRes!A68) -> 68 | E58: 5 | F58: 3.16-33-1 | G58: Установка противопожарных муфт на канализационных стояках из полипропиленовых труб в междуэтажных перекрытиях, муфт обжимных | H58: 100 шт. | I58: =ROUND(ROUND((19+16)/100,4),9) -> 0.35 | J58: 0 | K58: =ROUND(ROUND((19+16)/100,4),9) -> 0.35 | O58: =ROUND(CP58,2) -> 86.99 | P58: =ROUND((ROUND((AC58*AW58*I58),2)*BC58),2) -> 0 | Q58: =(ROUND((ROUND(((((ET58*1.25)*1.1))*AV58*I58),2)*BB58),2)+ROUND((ROUND(((AE58-(((EU58*1.25)*1.1)))*AV58*I58),2)*BS58),2)) -> 0 | R58: =ROUND((ROUND((AE58*AV58*I58),2)*BS58),2) -> 0 | S58: =ROUND((ROUND((AF58*AV58*I58),2)*BA58),2) -> 86.99 | T58: =ROUND(CU58*I58,2) -> 0 | U58: =CV58*I58 -> 6.9114205 | V58: =CW58*I58 -> 0 | W58: =ROUND(CX58*I58,2) -> 0 | X58: =ROUND(CY58,2) -> 94.82 | Y58: =ROUND(CZ58,2) -> 53.06 | AA58: 59209203 | AB58: =ROUND((AC58+AD58+AF58),6) -> 232.92445 | AC58: =ROUND((ES58),6) -> 0 | AD58: =ROUND((((((ET58*1.25)*1.1))-(((EU58*1.25)*1.1)))+AE58),6) -> 0 | AE58: =ROUND((((EU58*1.25)*1.1)),6) -> 0 | AF58: =ROUND((((EV58*1.15)*1.1)),6) -> 232.92445 | AG58: =ROUND((AP58),6) -> 0 | AH58: =(((EW58*1.15)*1.1)) -> 18.50695 | AI58: =(((EX58*1.25)*1.1)) -> 0 | AJ58: =(AS58) -> 0 | AK58: 184.13 | AL58: 0 | AM58: 0 | AN58: 0 | AO58: 184.13 | AP58: 0 | AQ58: 14.63 | AR58: 0 | AS58: 0 | AT58: 109 | AU58: 61 | AV58: 1.067 | AW58: 1 | AZ58: 1 | BA58: 1 | BB58: 1 | BC58: 1 | BH58: 0 | BI58: 1 | BJ58: ТСН-2001.3. Доп. 1-42. Сб. 16, т. 33, поз. 1 | BM58: 21 | BN58: 58807811 | BO58: 3.16-33-1 | BP58: 1 | BQ58: 30 | BR58: 0 | BS58: 1 | BT58: 1 | BU58: 1 | BV58: 1 | BW58: 1 | BX58: 1 | BZ58: 109 | CA58: 61 | CE58: 30 | CF58: 0 | CG58: 0 | CM58: 0 | CN58: Поправка: О.П. п.3.4. 6 Наименование: Выполняемые при ремонте и реконструкции работы аналогичные технологическим процессам, характерным для нового строительства и отсутствующим в сборниках на ремонтно-строительные работы Поправка: О.П. п.3.4.30.в Наименование: При применении территориальных сметных нормативов для города Москвы затраты, учитывающие напряженные и стесненные условия производства работ (стесненность, сложность складирования и транспортной логистики и т.п.), исчисляются с применением коэффициентов к затратам труда и заработной плате рабочих, машинистов, времени эксплуатации машин и механизмов, стоимости эксплуатации машин в размере: для объектов, расположенных за пределами Третьего транспортного кольца города Москвы, но в пределах Московской кольцевой автомобильной дороги | CO58: 0 | CP58: =(P58+Q58+S58) -> 86.99 | CQ58: =ROUND((ROUND((AC58*AW58*1),2)*BC58),2) -> 0 | CR58: =(ROUND((ROUND(((((ET58*1.25)*1.1))*AV58*1),2)*BB58),2)+ROUND((ROUND(((AE58-(((EU58*1.25)*1.1)))*AV58*1),2)*BS58),2)) -> 0 | CS58: =ROUND((ROUND((AE58*AV58*1),2)*BS58),2) -> 0 | CT58: =ROUND((ROUND((AF58*AV58*1),2)*BA58),2) -> 248.53 | CU58: =AG58 -> 0 | CV58: =(AH58*AV58) -> 19.746916 | CW58: =AI58 -> 0 | CX58: =AJ58 -> 0 | CY58: =(((S58+R58)*AT58)/100) -> 94.8191 | CZ58: =(((S58+R58)*AU58)/100) -> 53.0639 | DB58: 17 | DE58: *1,25)*1,1 | DF58: *1,25)*1,1 | DG58: *1,15)*1,1 | DI58: *1,15)*1,1 | DJ58: *1,25)*1,1 | DN58: 0 | DO58: 0 | DP58: 1 | DQ58: 1 | DU58: 1010 | DV58: 100 шт. | DW58: 100 шт. | DX58: 100 | EE58: 58807897 | EF58: 30 | EG58: Строительные работы | EH58: 0 | EJ58: 1 | EK58: 21 | EL58: ТСН-2001.3-16. Трубопроводы внутренние | EM58: ТСН-2001.3-16-1 | EO58: Поправка: О.П. п.3.4. 6 Поправка: О.П. п.3.4.30.в | EQ58: 0 | ER58: 184.13 | ES58: 0 | ET58: 0 | EU58: 0 | EV58: 184.13 | EW58: 14.63 | EX58: 0 | EY58: 0 | FQ58: 0 | FR58: 0 | FS58: 0 | FX58: 109 | FY58: 61 | GD58: 1 | GF58: 974445208 | GG58: 2 | GH58: 1 | GI58: 2 | GJ58: 0 | GK58: 0 | GL58: =ROUND(IF(AND(BH58=3,BI58=3,FS58<>0),P58,0),2) -> 0 | GM58: =ROUND(O58+X58+Y58,2)+GX58 -> 234.87 | GN58: =IF(OR(BI58=0,BI58=1),GM58-GX58,0) -> 234.87 | GO58: =IF(BI58=2,GM58-GX58,0) -> 0 | GP58: =IF(BI58=4,GM58-GX58,0) -> 0 | GR58: 0 | GS58: 3 | GT58: 0 | GV58: =ROUND((GT58),6) -> 0 | GW58: 1 | GX58: =ROUND(HC58*I58,2) -> 0 | HA58: 0 | HB58: 0 | HC58: =GV58*GW58 -> 0 | HS58: 0 | IK58: 0
A59: 17 | B59: 1 | C59: =ROW(SmtRes!A70) -> 70 | D59: =ROW(EtalonRes!A70) -> 70 | E59: 5 | F59: 3.16-33-1 | G59: Установка противопожарных муфт на канализационных стояках из полипропиленовых труб в междуэтажных перекрытиях, муфт обжимных | H59: 100 шт. | I59: =ROUND(ROUND((19+16)/100,4),9) -> 0.35 | J59: 0 | K59: =ROUND(ROUND((19+16)/100,4),9) -> 0.35 | O59: =ROUND(CP59,2) -> 4783.58 | P59: =ROUND((ROUND((AC59*AW59*I59),2)*BC59),2) -> 0 | Q59: =(ROUND((ROUND(((((ET59*1.25)*1.1))*AV59*I59),2)*BB59),2)+ROUND((ROUND(((AE59-(((EU59*1.25)*1.1)))*AV59*I59),2)*BS59),2)) -> 0 | R59: =ROUND((ROUND((AE59*AV59*I59),2)*BS59),2) -> 0 | S59: =ROUND((ROUND((AF59*AV59*I59),2)*BA59),2) -> 4783.58 | T59: =ROUND(CU59*I59,2) -> 0 | U59: =CV59*I59 -> 6.9114205 | V59: =CW59*I59 -> 0 | W59: =ROUND(CX59*I59,2) -> 0 | X59: =ROUND(CY59,2) -> 5214.1 | Y59: =ROUND(CZ59,2) -> 2917.98 | AA59: 59209200 | AB59: =ROUND((AC59+AD59+AF59),6) -> 232.92445 | AC59: =ROUND((ES59),6) -> 0 | AD59: =ROUND((((((ET59*1.25)*1.1))-(((EU59*1.25)*1.1)))+AE59),6) -> 0 | AE59: =ROUND((((EU59*1.25)*1.1)),6) -> 0 | AF59: =ROUND((((EV59*1.15)*1.1)),6) -> 232.92445 | AG59: =ROUND((AP59),6) -> 0 | AH59: =(((EW59*1.15)*1.1)) -> 18.50695 | AI59: =(((EX59*1.25)*1.1)) -> 0 | AJ59: =(AS59) -> 0 | AK59: 184.13 | AL59: 0 | AM59: 0 | AN59: 0 | AO59: 184.13 | AP59: 0 | AQ59: 14.63 | AR59: 0 | AS59: 0 | AT59: 109 | AU59: 61 | AV59: 1.067 | AW59: 1 | AZ59: 1 | BA59: 54.99 | BB59: 1 | BC59: 1 | BH59: 0 | BI59: 1 | BJ59: ТСН-2001.3. Доп. 1-42. Сб. 16, т. 33, поз. 1 | BM59: 21 | BN59: 58807811 | BO59: 3.16-33-1 | BP59: 1 | BQ59: 30 | BR59: 0 | BS59: 54.99 | BT59: 1 | BU59: 1 | BV59: 1 | BW59: 1 | BX59: 1 | BZ59: 109 | CA59: 61 | CE59: 30 | CF59: 0 | CG59: 0 | CM59: 0 | CN59: Поправка: О.П. п.3.4. 6 Наименование: Выполняемые при ремонте и реконструкции работы аналогичные технологическим процессам, характерным для нового строительства и отсутствующим в сборниках на ремонтно-строительные работы Поправка: О.П. п.3.4.30.в Наименование: При применении территориальных сметных нормативов для города Москвы затраты, учитывающие напряженные и стесненные условия производства работ (стесненность, сложность складирования и транспортной логистики и т.п.), исчисляются с применением коэффициентов к затратам труда и заработной плате рабочих, машинистов, времени эксплуатации машин и механизмов, стоимости эксплуатации машин в размере: для объектов, расположенных за пределами Третьего транспортного кольца города Москвы, но в пределах Московской кольцевой автомобильной дороги | CO59: 0 | CP59: =(P59+Q59+S59) -> 4783.58 | CQ59: =ROUND((ROUND((AC59*AW59*1),2)*BC59),2) -> 0 | CR59: =(ROUND((ROUND(((((ET59*1.25)*1.1))*AV59*1),2)*BB59),2)+ROUND((ROUND(((AE59-(((EU59*1.25)*1.1)))*AV59*1),2)*BS59),2)) -> 0 | CS59: =ROUND((ROUND((AE59*AV59*1),2)*BS59),2) -> 0 | CT59: =ROUND((ROUND((AF59*AV59*1),2)*BA59),2) -> 13666.66 | CU59: =AG59 -> 0 | CV59: =(AH59*AV59) -> 19.746916 | CW59: =AI59 -> 0 | CX59: =AJ59 -> 0 | CY59: =(((S59+R59)*AT59)/100) -> 5214.1022 | CZ59: =(((S59+R59)*AU59)/100) -> 2917.9838 | DB59: 19 | DE59: *1,25)*1,1 | DF59: *1,25)*1,1 | DG59: *1,15)*1,1 | DI59: *1,15)*1,1 | DJ59: *1,25)*1,1 | DN59: 0 | DO59: 0 | DP59: 1 | DQ59: 1 | DU59: 1010 | DV59: 100 шт. | DW59: 100 шт. | DX59: 100 | EE59: 58807897 | EF59: 30 | EG59: Строительные работы | EH59: 0 | EJ59: 1 | EK59: 21 | EL59: ТСН-2001.3-16. Трубопроводы внутренние | EM59: ТСН-2001.3-16-1 | EO59: Поправка: О.П. п.3.4. 6 Поправка: О.П. п.3.4.30.в | EQ59: 0 | ER59: 184.13 | ES59: 0 | ET59: 0 | EU59: 0 | EV59: 184.13 | EW59: 14.63 | EX59: 0 | EY59: 0 | FQ59: 0 | FR59: 0 | FS59: 0 | FX59: 109 | FY59: 61 | GD59: 1 | GF59: 974445208 | GG59: 2 | GH59: 1 | GI59: 2 | GJ59: 0 | GK59: 0 | GL59: =ROUND(IF(AND(BH59=3,BI59=3,FS59<>0),P59,0),2) -> 0 | GM59: =ROUND(O59+X59+Y59,2)+GX59 -> 12915.66 | GN59: =IF(OR(BI59=0,BI59=1),GM59-GX59,0) -> 12915.66 | GO59: =IF(BI59=2,GM59-GX59,0) -> 0 | GP59: =IF(BI59=4,GM59-GX59,0) -> 0 | GR59: 0 | GS59: 3 | GT59: 0 | GV59: =ROUND((GT59),6) -> 0 | GW59: 1 | GX59: =ROUND(HC59*I59,2) -> 0 | HA59: 0 | HB59: 0 | HC59: =GV59*GW59 -> 0 | HS59: 0 | IK59: 0
A60: 18 | B60: 1 | C60: 66 | E60: 5,1 | F60: 1.12-5-456 | G60: Муфта противопожарная из нержавеющей стали, с вкладышем из терморасширяющейся резины, для трубы диаметром 110 мм | H60: шт. | I60: =I58*J60 -> 19 | J60: 54.285714 | K60: 54.285714 | O60: =ROUND(CP60,2) -> 5039.56 | P60: =ROUND((ROUND((AC60*AW60*I60),2)*BC60),2) -> 5039.56 | Q60: =(ROUND((ROUND(((ET60)*AV60*I60),2)*BB60),2)+ROUND((ROUND(((AE60-(EU60))*AV60*I60),2)*BS60),2)) -> 0 | R60: =ROUND((ROUND((AE60*AV60*I60),2)*BS60),2) -> 0 | S60: =ROUND((ROUND((AF60*AV60*I60),2)*BA60),2) -> 0 | T60: =ROUND(CU60*I60,2) -> 0 | U60: =CV60*I60 -> 0 | V60: =CW60*I60 -> 0 | W60: =ROUND(CX60*I60,2) -> 0 | X60: =ROUND(CY60,2) -> 0 | Y60: =ROUND(CZ60,2) -> 0 | AA60: 59209203 | AB60: =ROUND((AC60+AD60+AF60),6) -> 265.24 | AC60: =ROUND((ES60),6) -> 265.24 | AD60: =ROUND((((ET60)-(EU60))+AE60),6) -> 0 | AE60: =ROUND((EU60),6) -> 0 | AF60: =ROUND((EV60),6) -> 0 | AG60: =ROUND((AP60),6) -> 0 | AH60: =(EW60) -> 0 | AI60: =(EX60) -> 0 | AJ60: =(AS60) -> 0 | AK60: 265.24 | AL60: 265.24 | AM60: 0 | AN60: 0 | AO60: 0 | AP60: 0 | AQ60: 0 | AR60: 0 | AS60: 0 | AT60: 109 | AU60: 61 | AV60: 1 | AW60: 1 | AZ60: 1 | BA60: 1 | BB60: 1 | BC60: 1 | BH60: 3 | BI60: 1 | BJ60: ТСН-2001.1 Доп. 73, Р. 12, о. 5, поз. 456 | BM60: 21 | BN60: 58807811 | BP60: 0 | BQ60: 30 | BR60: 0 | BS60: 1 | BT60: 1 | BU60: 1 | BV60: 1 | BW60: 1 | BX60: 1 | BZ60: 109 | CA60: 61 | CE60: 30 | CF60: 0 | CG60: 0 | CM60: 0 | CO60: 0 | CP60: =(P60+Q60+S60) -> 5039.56 | CQ60: =ROUND((ROUND((AC60*AW60*1),2)*BC60),2) -> 265.24 | CR60: =(ROUND((ROUND(((ET60)*AV60*1),2)*BB60),2)+ROUND((ROUND(((AE60-(EU60))*AV60*1),2)*BS60),2)) -> 0 | CS60: =ROUND((ROUND((AE60*AV60*1),2)*BS60),2) -> 0 | CT60: =ROUND((ROUND((AF60*AV60*1),2)*BA60),2) -> 0 | CU60: =AG60 -> 0 | CV60: =(AH60*AV60) -> 0 | CW60: =AI60 -> 0 | CX60: =AJ60 -> 0 | CY60: =(((S60+R60)*AT60)/100) -> 0 | CZ60: =(((S60+R60)*AU60)/100) -> 0 | DN60: 0 | DO60: 0 | DP60: 1 | DQ60: 1 | DU60: 1010 | DV60: шт. | DW60: шт. | DX60: 1 | EE60: 58807897 | EF60: 30 | EG60: Строительные работы | EH60: 0 | EJ60: 1 | EK60: 21 | EL60: ТСН-2001.3-16. Трубопроводы внутренние | EM60: ТСН-2001.3-16-1 | EQ60: 0 | ER60: 265.24 | ES60: 265.24 | ET60: 0 | EU60: 0 | EV60: 0 | EW60: 0 | EX60: 0 | FQ60: 0 | FR60: 0 | FS60: 0 | FX60: 109 | FY60: 61 | GD60: 1 | GF60: -462889033 | GG60: 2 | GH60: 1 | GI60: -2 | GJ60: 0 | GK60: 0 | GL60: =ROUND(IF(AND(BH60=3,BI60=3,FS60<>0),P60,0),2) -> 0 | GM60: =ROUND(O60+X60+Y60,2)+GX60 -> 5039.56 | GN60: =IF(OR(BI60=0,BI60=1),GM60-GX60,0) -> 5039.56 | GO60: =IF(BI60=2,GM60-GX60,0) -> 0 | GP60: =IF(BI60=4,GM60-GX60,0) -> 0 | GR60: 0 | GS60: 3 | GT60: 0 | GV60: =ROUND((GT60),6) -> 0 | GW60: 1 | GX60: =ROUND(HC60*I60,2) -> 0 | HA60: 0 | HB60: 0 | HC60: =GV60*GW60 -> 0 | HS60: 0 | IK60: 0
A61: 18 | B61: 1 | C61: 69 | E61: 5,1 | F61: 1.12-5-456 | G61: Муфта противопожарная из нержавеющей стали, с вкладышем из терморасширяющейся резины, для трубы диаметром 110 мм | H61: шт. | I61: =I59*J61 -> 19 | J61: 54.285714 | K61: 54.285714 | O61: =ROUND(CP61,2) -> 4182.83 | P61: =ROUND((ROUND((AC61*AW61*I61),2)*BC61),2) -> 4182.83 | Q61: =(ROUND((ROUND(((ET61)*AV61*I61),2)*BB61),2)+ROUND((ROUND(((AE61-(EU61))*AV61*I61),2)*BS61),2)) -> 0 | R61: =ROUND((ROUND((AE61*AV61*I61),2)*BS61),2) -> 0 | S61: =ROUND((ROUND((AF61*AV61*I61),2)*BA61),2) -> 0 | T61: =ROUND(CU61*I61,2) -> 0 | U61: =CV61*I61 -> 0 | V61: =CW61*I61 -> 0 | W61: =ROUND(CX61*I61,2) -> 0 | X61: =ROUND(CY61,2) -> 0 | Y61: =ROUND(CZ61,2) -> 0 | AA61: 59209200 | AB61: =ROUND((AC61+AD61+AF61),6) -> 265.24 | AC61: =ROUND((ES61),6) -> 265.24 | AD61: =ROUND((((ET61)-(EU61))+AE61),6) -> 0 | AE61: =ROUND((EU61),6) -> 0 | AF61: =ROUND((EV61),6) -> 0 | AG61: =ROUND((AP61),6) -> 0 | AH61: =(EW61) -> 0 | AI61: =(EX61) -> 0 | AJ61: =(AS61) -> 0 | AK61: 265.24 | AL61: 265.24 | AM61: 0 | AN61: 0 | AO61: 0 | AP61: 0 | AQ61: 0 | AR61: 0 | AS61: 0 | AT61: 109 | AU61: 61 | AV61: 1 | AW61: 1 | AZ61: 1 | BA61: 1 | BB61: 1 | BC61: 0.83 | BH61: 3 | BI61: 1 | BJ61: ТСН-2001.1 Доп. 73, Р. 12, о. 5, поз. 456 | BM61: 21 | BN61: 58807811 | BO61: 1.12-5-456 | BP61: 1 | BQ61: 30 | BR61: 0 | BS61: 1 | BT61: 1 | BU61: 1 | BV61: 1 | BW61: 1 | BX61: 1 | BZ61: 109 | CA61: 61 | CE61: 30 | CF61: 0 | CG61: 0 | CM61: 0 | CO61: 0 | CP61: =(P61+Q61+S61) -> 4182.83 | CQ61: =ROUND((ROUND((AC61*AW61*1),2)*BC61),2) -> 220.15 | CR61: =(ROUND((ROUND(((ET61)*AV61*1),2)*BB61),2)+ROUND((ROUND(((AE61-(EU61))*AV61*1),2)*BS61),2)) -> 0 | CS61: =ROUND((ROUND((AE61*AV61*1),2)*BS61),2) -> 0 | CT61: =ROUND((ROUND((AF61*AV61*1),2)*BA61),2) -> 0 | CU61: =AG61 -> 0 | CV61: =(AH61*AV61) -> 0 | CW61: =AI61 -> 0 | CX61: =AJ61 -> 0 | CY61: =(((S61+R61)*AT61)/100) -> 0 | CZ61: =(((S61+R61)*AU61)/100) -> 0 | DN61: 0 | DO61: 0 | DP61: 1 | DQ61: 1 | DU61: 1010 | DV61: шт. | DW61: шт. | DX61: 1 | EE61: 58807897 | EF61: 30 | EG61: Строительные работы | EH61: 0 | EJ61: 1 | EK61: 21 | EL61: ТСН-2001.3-16. Трубопроводы внутренние | EM61: ТСН-2001.3-16-1 | EQ61: 0 | ER61: 265.24 | ES61: 265.24 | ET61: 0 | EU61: 0 | EV61: 0 | EW61: 0 | EX61: 0 | FQ61: 0 | FR61: 0 | FS61: 0 | FX61: 109 | FY61: 61 | GD61: 1 | GF61: -462889033 | GG61: 2 | GH61: 1 | GI61: 2 | GJ61: 0 | GK61: 0 | GL61: =ROUND(IF(AND(BH61=3,BI61=3,FS61<>0),P61,0),2) -> 0 | GM61: =ROUND(O61+X61+Y61,2)+GX61 -> 4182.83 | GN61: =IF(OR(BI61=0,BI61=1),GM61-GX61,0) -> 4182.83 | GO61: =IF(BI61=2,GM61-GX61,0) -> 0 | GP61: =IF(BI61=4,GM61-GX61,0) -> 0 | GR61: 0 | GS61: 3 | GT61: 0 | GV61: =ROUND((GT61),6) -> 0 | GW61: 1 | GX61: =ROUND(HC61*I61,2) -> 0 | HA61: 0 | HB61: 0 | HC61: =GV61*GW61 -> 0 | HS61: 0 | IK61: 0
A62: 18 | B62: 1 | C62: 67 | E62: 5,2 | F62: 1.12-5-542 | G62: Муфта противопожарная из нержавеющей стали, с вкладышем из терморасширяющейся резины, для трубы диаметром 50 мм | H62: шт. | I62: =I58*J62 -> 16 | J62: 45.714286 | K62: 45.714286 | O62: =ROUND(CP62,2) -> 2905.44 | P62: =ROUND((ROUND((AC62*AW62*I62),2)*BC62),2) -> 2905.44 | Q62: =(ROUND((ROUND(((ET62)*AV62*I62),2)*BB62),2)+ROUND((ROUND(((AE62-(EU62))*AV62*I62),2)*BS62),2)) -> 0 | R62: =ROUND((ROUND((AE62*AV62*I62),2)*BS62),2) -> 0 | S62: =ROUND((ROUND((AF62*AV62*I62),2)*BA62),2) -> 0 | T62: =ROUND(CU62*I62,2) -> 0 | U62: =CV62*I62 -> 0 | V62: =CW62*I62 -> 0 | W62: =ROUND(CX62*I62,2) -> 0 | X62: =ROUND(CY62,2) -> 0 | Y62: =ROUND(CZ62,2) -> 0 | AA62: 59209203 | AB62: =ROUND((AC62+AD62+AF62),6) -> 181.59 | AC62: =ROUND((ES62),6) -> 181.59 | AD62: =ROUND((((ET62)-(EU62))+AE62),6) -> 0 | AE62: =ROUND((EU62),6) -> 0 | AF62: =ROUND((EV62),6) -> 0 | AG62: =ROUND((AP62),6) -> 0 | AH62: =(EW62) -> 0 | AI62: =(EX62) -> 0 | AJ62: =(AS62) -> 0 | AK62: 181.59 | AL62: 181.59 | AM62: 0 | AN62: 0 | AO62: 0 | AP62: 0 | AQ62: 0 | AR62: 0 | AS62: 0 | AT62: 109 | AU62: 61 | AV62: 1 | AW62: 1 | AZ62: 1 | BA62: 1 | BB62: 1 | BC62: 1 | BH62: 3 | BI62: 1 | BJ62: ТСН-2001.1 Доп. 67, Р. 12, о. 5, поз. 542 | BM62: 21 | BN62: 58807811 | BP62: 0 | BQ62: 30 | BR62: 0 | BS62: 1 | BT62: 1 | BU62: 1 | BV62: 1 | BW62: 1 | BX62: 1 | BZ62: 109 | CA62: 61 | CE62: 30 | CF62: 0 | CG62: 0 | CM62: 0 | CO62: 0 | CP62: =(P62+Q62+S62) -> 2905.44 | CQ62: =ROUND((ROUND((AC62*AW62*1),2)*BC62),2) -> 181.59 | CR62: =(ROUND((ROUND(((ET62)*AV62*1),2)*BB62),2)+ROUND((ROUND(((AE62-(EU62))*AV62*1),2)*BS62),2)) -> 0 | CS62: =ROUND((ROUND((AE62*AV62*1),2)*BS62),2) -> 0 | CT62: =ROUND((ROUND((AF62*AV62*1),2)*BA62),2) -> 0 | CU62: =AG62 -> 0 | CV62: =(AH62*AV62) -> 0 | CW62: =AI62 -> 0 | CX62: =AJ62 -> 0 | CY62: =(((S62+R62)*AT62)/100) -> 0 | CZ62: =(((S62+R62)*AU62)/100) -> 0 | DN62: 0 | DO62: 0 | DP62: 1 | DQ62: 1 | DU62: 1010 | DV62: шт. | DW62: шт. | DX62: 1 | EE62: 58807897 | EF62: 30 | EG62: Строительные работы | EH62: 0 | EJ62: 1 | EK62: 21 | EL62: ТСН-2001.3-16. Трубопроводы внутренние | EM62: ТСН-2001.3-16-1 | EQ62: 0 | ER62: 181.59 | ES62: 181.59 | ET62: 0 | EU62: 0 | EV62: 0 | EW62: 0 | EX62: 0 | FQ62: 0 | FR62: 0 | FS62: 0 | FX62: 109 | FY62: 61 | GD62: 1 | GF62: -1001613449 | GG62: 2 | GH62: 1 | GI62: -2 | GJ62: 0 | GK62: 0 | GL62: =ROUND(IF(AND(BH62=3,BI62=3,FS62<>0),P62,0),2) -> 0 | GM62: =ROUND(O62+X62+Y62,2)+GX62 -> 2905.44 | GN62: =IF(OR(BI62=0,BI62=1),GM62-GX62,0) -> 2905.44 | GO62: =IF(BI62=2,GM62-GX62,0) -> 0 | GP62: =IF(BI62=4,GM62-GX62,0) -> 0 | GR62: 0 | GS62: 3 | GT62: 0 | GV62: =ROUND((GT62),6) -> 0 | GW62: 1 | GX62: =ROUND(HC62*I62,2) -> 0 | HA62: 0 | HB62: 0 | HC62: =GV62*GW62 -> 0 | HS62: 0 | IK62: 0
A63: 18 | B63: 1 | C63: 70 | E63: 5,2 | F63: 1.12-5-542 | G63: Муфта противопожарная из нержавеющей стали, с вкладышем из терморасширяющейся резины, для трубы диаметром 50 мм | H63: шт. | I63: =I59*J63 -> 16 | J63: 45.714286 | K63: 45.714286 | O63: =ROUND(CP63,2) -> 2208.13 | P63: =ROUND((ROUND((AC63*AW63*I63),2)*BC63),2) -> 2208.13 | Q63: =(ROUND((ROUND(((ET63)*AV63*I63),2)*BB63),2)+ROUND((ROUND(((AE63-(EU63))*AV63*I63),2)*BS63),2)) -> 0 | R63: =ROUND((ROUND((AE63*AV63*I63),2)*BS63),2) -> 0 | S63: =ROUND((ROUND((AF63*AV63*I63),2)*BA63),2) -> 0 | T63: =ROUND(CU63*I63,2) -> 0 | U63: =CV63*I63 -> 0 | V63: =CW63*I63 -> 0 | W63: =ROUND(CX63*I63,2) -> 0 | X63: =ROUND(CY63,2) -> 0 | Y63: =ROUND(CZ63,2) -> 0 | AA63: 59209200 | AB63: =ROUND((AC63+AD63+AF63),6) -> 181.59 | AC63: =ROUND((ES63),6) -> 181.59 | AD63: =ROUND((((ET63)-(EU63))+AE63),6) -> 0 | AE63: =ROUND((EU63),6) -> 0 | AF63: =ROUND((EV63),6) -> 0 | AG63: =ROUND((AP63),6) -> 0 | AH63: =(EW63) -> 0 | AI63: =(EX63) -> 0 | AJ63: =(AS63) -> 0 | AK63: 181.59 | AL63: 181.59 | AM63: 0 | AN63: 0 | AO63: 0 | AP63: 0 | AQ63: 0 | AR63: 0 | AS63: 0 | AT63: 109 | AU63: 61 | AV63: 1 | AW63: 1 | AZ63: 1 | BA63: 1 | BB63: 1 | BC63: 0.76 | BH63: 3 | BI63: 1 | BJ63: ТСН-2001.1 Доп. 67, Р. 12, о. 5, поз. 542 | BM63: 21 | BN63: 58807811 | BO63: 1.12-5-542 | BP63: 1 | BQ63: 30 | BR63: 0 | BS63: 1 | BT63: 1 | BU63: 1 | BV63: 1 | BW63: 1 | BX63: 1 | BZ63: 109 | CA63: 61 | CE63: 30 | CF63: 0 | CG63: 0 | CM63: 0 | CO63: 0 | CP63: =(P63+Q63+S63) -> 2208.13 | CQ63: =ROUND((ROUND((AC63*AW63*1),2)*BC63),2) -> 138.01 | CR63: =(ROUND((ROUND(((ET63)*AV63*1),2)*BB63),2)+ROUND((ROUND(((AE63-(EU63))*AV63*1),2)*BS63),2)) -> 0 | CS63: =ROUND((ROUND((AE63*AV63*1),2)*BS63),2) -> 0 | CT63: =ROUND((ROUND((AF63*AV63*1),2)*BA63),2) -> 0 | CU63: =AG63 -> 0 | CV63: =(AH63*AV63) -> 0 | CW63: =AI63 -> 0 | CX63: =AJ63 -> 0 | CY63: =(((S63+R63)*AT63)/100) -> 0 | CZ63: =(((S63+R63)*AU63)/100) -> 0 | DN63: 0 | DO63: 0 | DP63: 1 | DQ63: 1 | DU63: 1010 | DV63: шт. | DW63: шт. | DX63: 1 | EE63: 58807897 | EF63: 30 | EG63: Строительные работы | EH63: 0 | EJ63: 1 | EK63: 21 | EL63: ТСН-2001.3-16. Трубопроводы внутренние | EM63: ТСН-2001.3-16-1 | EQ63: 0 | ER63: 181.59 | ES63: 181.59 | ET63: 0 | EU63: 0 | EV63: 0 | EW63: 0 | EX63: 0 | FQ63: 0 | FR63: 0 | FS63: 0 | FX63: 109 | FY63: 61 | GD63: 1 | GF63: -1001613449 | GG63: 2 | GH63: 1 | GI63: 2 | GJ63: 0 | GK63: 0 | GL63: =ROUND(IF(AND(BH63=3,BI63=3,FS63<>0),P63,0),2) -> 0 | GM63: =ROUND(O63+X63+Y63,2)+GX63 -> 2208.13 | GN63: =IF(OR(BI63=0,BI63=1),GM63-GX63,0) -> 2208.13 | GO63: =IF(BI63=2,GM63-GX63,0) -> 0 | GP63: =IF(BI63=4,GM63-GX63,0) -> 0 | GR63: 0 | GS63: 3 | GT63: 0 | GV63: =ROUND((GT63),6) -> 0 | GW63: 1 | GX63: =ROUND(HC63*I63,2) -> 0 | HA63: 0 | HB63: 0 | HC63: =GV63*GW63 -> 0 | HS63: 0 | IK63: 0
A65: 51 | B65: =B28 -> 1 | C65: =A28 -> 5 | D65: =ROW(A28) -> 28 | F65: =IF(F28<>"",F28,"") -> Новый подраздел | G65: =IF(G28<>"",G28,"") -> Монтажные работы | H65: 0 | O65: =ROUND(AB65,2) -> 45291.94 | P65: =ROUND(AC65,2) -> 41523.21 | Q65: =ROUND(AD65,2) -> 82.81 | R65: =ROUND(AE65,2) -> 11.48 | S65: =ROUND(AF65,2) -> 3685.92 | T65: =ROUND(AG65,2) -> 0 | U65: =AH65 -> 292.35437 | V65: =AI65 -> 0 | W65: =ROUND(AJ65,2) -> 0 | X65: =ROUND(AK65,2) -> 4030.17 | Y65: =ROUND(AL65,2) -> 2255.41 | AB65: =ROUND(SUMIF(AA32:AA63,"=59209203",O32:O63),2) -> 45291.94 | AC65: =ROUND(SUMIF(AA32:AA63,"=59209203",P32:P63),2) -> 41523.21 | AD65: =ROUND(SUMIF(AA32:AA63,"=59209203",Q32:Q63),2) -> 82.81 | AE65: =ROUND(SUMIF(AA32:AA63,"=59209203",R32:R63),2) -> 11.48 | AF65: =ROUND(SUMIF(AA32:AA63,"=59209203",S32:S63),2) -> 3685.92 | AG65: =ROUND(SUMIF(AA32:AA63,"=59209203",T32:T63),2) -> 0 | AH65: =SUMIF(AA32:AA63,"=59209203",U32:U63) -> 292.35437 | AI65: =SUMIF(AA32:AA63,"=59209203",V32:V63) -> 0 | AJ65: =ROUND(SUMIF(AA32:AA63,"=59209203",W32:W63),2) -> 0 | AK65: =ROUND(SUMIF(AA32:AA63,"=59209203",X32:X63),2) -> 4030.17 | AL65: =ROUND(SUMIF(AA32:AA63,"=59209203",Y32:Y63),2) -> 2255.41 | AO65: =ROUND(BX65,2) -> 0 | AP65: =ROUND(BY65,2) -> 0 | AQ65: =ROUND(BZ65,2) -> 0 | AR65: =ROUND(CA65,2) -> 51577.52 | AS65: =ROUND(CB65,2) -> 51577.52 | AT65: =ROUND(CC65,2) -> 0 | AU65: =ROUND(CD65,2) -> 0 | AV65: =ROUND(CE65,2) -> 41523.21 | ... BD65: =ROUND(CM65,2) -> 0 | BX65: =ROUND(SUMIF(AA32:AA63,"=59209203",FQ32:FQ63),2) -> 0 | BY65: =ROUND(SUMIF(AA32:AA63,"=59209203",FR32:FR63),2) -> 0 | BZ65: =ROUND(SUMIF(AA32:AA63,"=59209203",GL32:GL63),2) -> 0 | CA65: =ROUND(SUMIF(AA32:AA63,"=59209203",GM32:GM63),2) -> 51577.52 | CB65: =ROUND(SUMIF(AA32:AA63,"=59209203",GN32:GN63),2) -> 51577.52 | CC65: =ROUND(SUMIF(AA32:AA63,"=59209203",GO32:GO63),2) -> 0 | CD65: =ROUND(SUMIF(AA32:AA63,"=59209203",GP32:GP63),2) -> 0 | CE65: =AC65-BX65 -> 41523.21 | CF65: =AC65-BY65 -> 41523.21 | CG65: =BX65-BZ65 -> 0 | CH65: =AC65-BX65-BY65+BZ65 -> 41523.21 | CI65: =BY65-BZ65 -> 0 | CJ65: =ROUND(SUMIF(AA32:AA63,"=59209203",GX32:GX63),2) -> 0 | CK65: =ROUND(SUMIF(AA32:AA63,"=59209203",GY32:GY63),2) -> 0 | CL65: =ROUND(SUMIF(AA32:AA63,"=59209203",GZ32:GZ63),2) -> 0 | CM65: =ROUND(SUMIF(AA32:AA63,"=59209203",HD32:HD63),2) -> 0 | DG65: =ROUND(DT65,2) -> 309819.66 | DH65: =ROUND(DU65,2) -> 105831.27 | DI65: =ROUND(DV65,2) -> 1299.64 | DJ65: =ROUND(DW65,2) -> 631.28 | DK65: =ROUND(DX65,2) -> 202688.75 | DL65: =ROUND(DY65,2) -> 0 | DM65: =DZ65 -> 292.35437 | DN65: =EA65 -> 0 | DO65: =ROUND(EB65,2) -> 0 | DP65: =ROUND(EC65,2) -> 221618.84 | DQ65: =ROUND(ED65,2) -> 124025.21 | DT65: =ROUND(SUMIF(AA32:AA63,"=59209200",O32:O63),2) -> 309819.66 | DU65: =ROUND(SUMIF(AA32:AA63,"=59209200",P32:P63),2) -> 105831.27 | DV65: =ROUND(SUMIF(AA32:AA63,"=59209200",Q32:Q63),2) -> 1299.64 | DW65: =ROUND(SUMIF(AA32:AA63,"=59209200",R32:R63),2) -> 631.28 | DX65: =ROUND(SUMIF(AA32:AA63,"=59209200",S32:S63),2) -> 202688.75 | DY65: =ROUND(SUMIF(AA32:AA63,"=59209200",T32:T63),2) -> 0 | DZ65: =SUMIF(AA32:AA63,"=59209200",U32:U63) -> 292.35437 | EA65: =SUMIF(AA32:AA63,"=59209200",V32:V63) -> 0 | EB65: =ROUND(SUMIF(AA32:AA63,"=59209200",W32:W63),2) -> 0 | EC65: =ROUND(SUMIF(AA32:AA63,"=59209200",X32:X63),2) -> 221618.84 | ED65: =ROUND(SUMIF(AA32:AA63,"=59209200",Y32:Y63),2) -> 124025.21 | EG65: =ROUND(FP65,2) -> 0 | EH65: =ROUND(FQ65,2) -> 0 | EI65: =ROUND(FR65,2) -> 0 | EJ65: =ROUND(FS65,2) -> 655463.71 | EK65: =ROUND(FT65,2) -> 655463.71 | EL65: =ROUND(FU65,2) -> 0 | EM65: =ROUND(FV65,2) -> 0 | EN65: =ROUND(FW65,2) -> 105831.27 | ... EV65: =ROUND(GE65,2) -> 0 | FP65: =ROUND(SUMIF(AA32:AA63,"=59209200",FQ32:FQ63),2) -> 0 | FQ65: =ROUND(SUMIF(AA32:AA63,"=59209200",FR32:FR63),2) -> 0 | FR65: =ROUND(SUMIF(AA32:AA63,"=59209200",GL32:GL63),2) -> 0 | FS65: =ROUND(SUMIF(AA32:AA63,"=59209200",GM32:GM63),2) -> 655463.71 | FT65: =ROUND(SUMIF(AA32:AA63,"=59209200",GN32:GN63),2) -> 655463.71 | FU65: =ROUND(SUMIF(AA32:AA63,"=59209200",GO32:GO63),2) -> 0 | FV65: =ROUND(SUMIF(AA32:AA63,"=59209200",GP32:GP63),2) -> 0 | FW65: =DU65-FP65 -> 105831.27 | FX65: =DU65-FQ65 -> 105831.27 | FY65: =FP65-FR65 -> 0 | FZ65: =DU65-FP65-FQ65+FR65 -> 105831.27 | GA65: =FQ65-FR65 -> 0 | GB65: =ROUND(SUMIF(AA32:AA63,"=59209200",GX32:GX63),2) -> 0 | GC65: =ROUND(SUMIF(AA32:AA63,"=59209200",GY32:GY63),2) -> 0 | GD65: =ROUND(SUMIF(AA32:AA63,"=59209200",GZ32:GZ63),2) -> 0 | GE65: =ROUND(SUMIF(AA32:AA63,"=59209200",HD32:HD63),2) -> 0 | GX65: 0
A67: 50 | B67: 0 | C67: 0 | D67: 1 | E67: 201 | F67: =ROUND(Source!O65,O67) -> 45291.94 | G67: ПЗ | H67: Прямые затраты | K67: 201 | L67: 1 | M67: 3 | O67: 2 | P67: =ROUND(Source!DG65,O67) -> 309819.66 | W67: 45291.94 | X67: 1 | Y67: 45291.94 | Z67: 309819.66 | AA67: 1 | AB67: 309819.66
A68: 50 | B68: 0 | C68: 0 | D68: 1 | E68: 202 | F68: =ROUND(Source!P65,O68) -> 41523.21 | G68: СтМатОб | H68: Стоимость материальных ресурсов (всего) | K68: 202 | L68: 2 | M68: 3 | O68: 2 | P68: =ROUND(Source!DH65,O68) -> 105831.27 | W68: 41523.21 | X68: 1 | Y68: 41523.21 | Z68: 105831.27 | AA68: 1 | AB68: 105831.27
A69: 50 | B69: 0 | C69: 0 | D69: 1 | E69: 222 | F69: =ROUND(Source!AO65,O69) -> 0 | G69: СтМатОбЗак | H69: Стоимость материалов и оборудования заказчика | K69: 222 | L69: 3 | M69: 3 | O69: 2 | P69: =ROUND(Source!EG65,O69) -> 0 | W69: 0 | X69: 1 | Y69: 0 | Z69: 0 | AA69: 1 | AB69: 0
A70: 50 | B70: 0 | C70: 0 | D70: 1 | E70: 225 | F70: =ROUND(Source!AV65,O70) -> 41523.21 | G70: СтМатОбПод | H70: Стоимость материалов и оборудования подрядчика | K70: 225 | L70: 4 | M70: 3 | O70: 2 | P70: =ROUND(Source!EN65,O70) -> 105831.27 | W70: 41523.21 | X70: 1 | Y70: 41523.21 | Z70: 105831.27 | AA70: 1 | AB70: 105831.27
A71: 50 | B71: 0 | C71: 0 | D71: 1 | E71: 226 | F71: =ROUND(Source!AW65,O71) -> 41523.21 | G71: СтМат | H71: Стоимость материалов (всего) | K71: 226 | L71: 5 | M71: 3 | O71: 2 | P71: =ROUND(Source!EO65,O71) -> 105831.27 | W71: 41523.21 | X71: 1 | Y71: 41523.21 | Z71: 105831.27 | AA71: 1 | AB71: 105831.27
A72: 50 | B72: 0 | C72: 0 | D72: 1 | E72: 227 | F72: =ROUND(Source!AX65,O72) -> 0 | G72: СтМатЗак | H72: Стоимость материалов заказчика | K72: 227 | L72: 6 | M72: 3 | O72: 2 | P72: =ROUND(Source!EP65,O72) -> 0 | W72: 0 | X72: 1 | Y72: 0 | Z72: 0 | AA72: 1 | AB72: 0
A73: 50 | B73: 0 | C73: 0 | D73: 1 | E73: 228 | F73: =ROUND(Source!AY65,O73) -> 41523.21 | G73: СтМатПод | H73: Стоимость материалов подрядчика | K73: 228 | L73: 7 | M73: 3 | O73: 2 | P73: =ROUND(Source!EQ65,O73) -> 105831.27 | W73: 41523.21 | X73: 1 | Y73: 41523.21 | Z73: 105831.27 | AA73: 1 | AB73: 105831.27
A74: 50 | B74: 0 | C74: 0 | D74: 1 | E74: 216 | F74: =ROUND(Source!AP65,O74) -> 0 | G74: Оборуд | H74: Стоимость оборудования (всего) | K74: 216 | L74: 8 | M74: 3 | O74: 2 | P74: =ROUND(Source!EH65,O74) -> 0 | W74: 0 | X74: 1 | Y74: 0 | Z74: 0 | AA74: 1 | AB74: 0
A75: 50 | B75: 0 | C75: 0 | D75: 1 | E75: 223 | F75: =ROUND(Source!AQ65,O75) -> 0 | G75: ОборудЗак | H75: Стоимость оборудования заказчика | K75: 223 | L75: 9 | M75: 3 | O75: 2 | P75: =ROUND(Source!EI65,O75) -> 0 | W75: 0 | X75: 1 | Y75: 0 | Z75: 0 | AA75: 1 | AB75: 0
A76: 50 | B76: 0 | C76: 0 | D76: 1 | E76: 229 | F76: =ROUND(Source!AZ65,O76) -> 0 | G76: ОборудПод | H76: Стоимость оборудования подрядчика | K76: 229 | L76: 10 | M76: 3 | O76: 2 | P76: =ROUND(Source!ER65,O76) -> 0 | W76: 0 | X76: 1 | Y76: 0 | Z76: 0 | AA76: 1 | AB76: 0
A77: 50 | B77: 0 | C77: 0 | D77: 1 | E77: 203 | F77: =ROUND(Source!Q65,O77) -> 82.81 | G77: ЭММ | H77: Эксплуатация машин | K77: 203 | L77: 11 | M77: 3 | O77: 2 | P77: =ROUND(Source!DI65,O77) -> 1299.64 | W77: 82.81 | X77: 1 | Y77: 82.81 | Z77: 1299.64 | AA77: 1 | AB77: 1299.64
A78: 50 | B78: 0 | C78: 0 | D78: 1 | E78: 231 | F78: =ROUND(Source!BB65,O78) -> 0 | G78: ЭММсНРиСП | H78: Эксплуатация машин по ТСН-2001.16 | K78: 231 | L78: 12 | M78: 3 | O78: 2 | P78: =ROUND(Source!ET65,O78) -> 0 | W78: 0 | X78: 1 | Y78: 0 | Z78: 0 | AA78: 1 | AB78: 0
A79: 50 | B79: 0 | C79: 0 | D79: 1 | E79: 204 | F79: =ROUND(Source!R65,O79) -> 11.48 | G79: ЗПМ | H79: ЗП машинистов | K79: 204 | L79: 13 | M79: 3 | O79: 2 | P79: =ROUND(Source!DJ65,O79) -> 631.28 | W79: 11.48 | X79: 1 | Y79: 11.48 | Z79: 631.28 | AA79: 1 | AB79: 631.28
A80: 50 | B80: 0 | C80: 0 | D80: 1 | E80: 205 | F80: =ROUND(Source!S65,O80) -> 3685.92 | G80: ОЗП | H80: Основная ЗП рабочих | K80: 205 | L80: 14 | M80: 3 | O80: 2 | P80: =ROUND(Source!DK65,O80) -> 202688.75 | W80: 3685.92 | X80: 1 | Y80: 3685.92 | Z80: 202688.75 | AA80: 1 | AB80: 202688.75
A81: 50 | B81: 0 | C81: 0 | D81: 1 | E81: 232 | F81: =ROUND(Source!BC65,O81) -> 0 | G81: ОЗПсНРиСП | H81: Основная ЗП рабочих по ТСН-2001.16 | K81: 232 | L81: 15 | M81: 3 | O81: 2 | P81: =ROUND(Source!EU65,O81) -> 0 | W81: 0 | X81: 1 | Y81: 0 | Z81: 0 | AA81: 1 | AB81: 0
A82: 50 | B82: 0 | C82: 0 | D82: 1 | E82: 214 | F82: =ROUND(Source!AS65,O82) -> 51577.52 | G82: Строит | H82: Строительные работы с НР и СП | K82: 214 | L82: 16 | M82: 3 | O82: 2 | P82: =ROUND(Source!EK65,O82) -> 655463.71 | W82: 51577.52 | X82: 1 | Y82: 51577.52 | Z82: 655463.71 | AA82: 1 | AB82: 655463.71
A83: 50 | B83: 0 | C83: 0 | D83: 1 | E83: 215 | F83: =ROUND(Source!AT65,O83) -> 0 | G83: Монтаж | H83: Монтажные работы с НР и СП | K83: 215 | L83: 17 | M83: 3 | O83: 2 | P83: =ROUND(Source!EL65,O83) -> 0 | W83: 0 | X83: 1 | Y83: 0 | Z83: 0 | AA83: 1 | AB83: 0
A84: 50 | B84: 0 | C84: 0 | D84: 1 | E84: 217 | F84: =ROUND(Source!AU65,O84) -> 0 | G84: Прочие | H84: Прочие работы с НР и СП | K84: 217 | L84: 18 | M84: 3 | O84: 2 | P84: =ROUND(Source!EM65,O84) -> 0 | W84: 0 | X84: 1 | Y84: 0 | Z84: 0 | AA84: 1 | AB84: 0
A85: 50 | B85: 0 | C85: 0 | D85: 1 | E85: 230 | F85: =ROUND(Source!BA65,O85) -> 0 | G85: ПрочиеЗатр | H85: Прочие затраты по ТСН-2001.16 | K85: 230 | L85: 19 | M85: 3 | O85: 2 | P85: =ROUND(Source!ES65,O85) -> 0 | W85: 0 | X85: 1 | Y85: 0 | Z85: 0 | AA85: 1 | AB85: 0
A86: 50 | B86: 0 | C86: 0 | D86: 1 | E86: 206 | F86: =ROUND(Source!T65,O86) -> 0 | G86: ВозврМат | H86: Возврат материалов | K86: 206 | L86: 20 | M86: 3 | O86: 2 | P86: =ROUND(Source!DL65,O86) -> 0 | W86: 0 | X86: 1 | Y86: 0 | Z86: 0 | AA86: 1 | AB86: 0
A87: 50 | B87: 0 | C87: 0 | D87: 1 | E87: 207 | F87: =Source!U65 -> 292.35437 | G87: ТрудСтр | H87: Трудозатраты строителей | K87: 207 | L87: 21 | M87: 3 | O87: -1 | P87: =Source!DM65 -> 292.35437 | W87: 292.35437 | X87: 1 | Y87: 292.35437 | Z87: 292.35437 | AA87: 1 | AB87: 292.35437
A88: 50 | B88: 0 | C88: 0 | D88: 1 | E88: 208 | F88: =Source!V65 -> 0 | G88: ТрудМаш | H88: Трудозатраты машинистов | K88: 208 | L88: 22 | M88: 3 | O88: -1 | P88: =Source!DN65 -> 0 | W88: 0 | X88: 1 | Y88: 0 | Z88: 0 | AA88: 1 | AB88: 0
A89: 50 | B89: 0 | C89: 0 | D89: 1 | E89: 209 | F89: =ROUND(Source!W65,O89) -> 0 | G89: ТранспМат | H89: Транспорт материалов | K89: 209 | L89: 23 | M89: 3 | O89: 2 | P89: =ROUND(Source!DO65,O89) -> 0 | W89: 0 | X89: 1 | Y89: 0 | Z89: 0 | AA89: 1 | AB89: 0
A90: 50 | B90: 0 | C90: 0 | D90: 1 | E90: 233 | F90: =ROUND(Source!BD65,O90) -> 0 | G90: Перевозка | H90: Перевозка грузов | K90: 233 | L90: 24 | M90: 3 | O90: 2 | P90: =ROUND(Source!EV65,O90) -> 0 | W90: 0 | X90: 1 | Y90: 0 | Z90: 0 | AA90: 1 | AB90: 0
A91: 50 | B91: 0 | C91: 0 | D91: 1 | E91: 210 | F91: =ROUND(Source!X65,O91) -> 4030.17 | G91: НР | H91: Накладные расходы | K91: 210 | L91: 25 | M91: 3 | O91: 2 | P91: =ROUND(Source!DP65,O91) -> 221618.84 | W91: 4030.17 | X91: 1 | Y91: 4030.17 | Z91: 221618.84 | AA91: 1 | AB91: 221618.84
A92: 50 | B92: 0 | C92: 0 | D92: 1 | E92: 211 | F92: =ROUND(Source!Y65,O92) -> 2255.41 | G92: СмПриб | H92: Сметная прибыль | K92: 211 | L92: 26 | M92: 3 | O92: 2 | P92: =ROUND(Source!DQ65,O92) -> 124025.21 | W92: 2255.41 | X92: 1 | Y92: 2255.41 | Z92: 124025.21 | AA92: 1 | AB92: 124025.21
A93: 50 | B93: 0 | C93: 0 | D93: 1 | E93: 224 | F93: =ROUND(Source!AR65,O93) -> 51577.52 | G93: Всего | H93: Всего с НР и СП | K93: 224 | L93: 27 | M93: 3 | O93: 2 | P93: =ROUND(Source!EJ65,O93) -> 655463.71 | W93: 51577.52 | X93: 1 | Y93: 51577.52 | Z93: 655463.71 | AA93: 1 | AB93: 655463.71
A95: 51 | B95: =B24 -> 1 | C95: =A24 -> 4 | D95: =ROW(A24) -> 24 | F95: =IF(F24<>"",F24,"") -> Новый раздел | G95: =IF(G24<>"",G24,"") -> Канализация хозяйственно-бытовая (К1) (подвал) | H95: 0 | O95: =ROUND(O65+AB95,2) -> 45291.94 | P95: =ROUND(P65+AC95,2) -> 41523.21 | Q95: =ROUND(Q65+AD95,2) -> 82.81 | R95: =ROUND(R65+AE95,2) -> 11.48 | S95: =ROUND(S65+AF95,2) -> 3685.92 | T95: =ROUND(T65+AG95,2) -> 0 | U95: =U65+AH95 -> 292.35437 | V95: =V65+AI95 -> 0 | W95: =ROUND(W65+AJ95,2) -> 0 | X95: =ROUND(X65+AK95,2) -> 4030.17 | Y95: =ROUND(Y65+AL95,2) -> 2255.41 | AO95: =ROUND(AO65+BX95,2) -> 0 | AP95: =ROUND(AP65+BY95,2) -> 0 | AQ95: =ROUND(AQ65+BZ95,2) -> 0 | AR95: =ROUND(AR65+CA95,2) -> 51577.52 | AS95: =ROUND(AS65+CB95,2) -> 51577.52 | AT95: =ROUND(AT65+CC95,2) -> 0 | AU95: =ROUND(AU65+CD95,2) -> 0 | AV95: =ROUND(AV65+CE95,2) -> 41523.21 | ... BD95: =ROUND(BD65+CM95,2) -> 0 | DG95: =ROUND(DG65+DT95,2) -> 309819.66 | DH95: =ROUND(DH65+DU95,2) -> 105831.27 | DI95: =ROUND(DI65+DV95,2) -> 1299.64 | DJ95: =ROUND(DJ65+DW95,2) -> 631.28 | DK95: =ROUND(DK65+DX95,2) -> 202688.75 | DL95: =ROUND(DL65+DY95,2) -> 0 | DM95: =DM65+DZ95 -> 292.35437 | DN95: =DN65+EA95 -> 0 | DO95: =ROUND(DO65+EB95,2) -> 0 | DP95: =ROUND(DP65+EC95,2) -> 221618.84 | DQ95: =ROUND(DQ65+ED95,2) -> 124025.21 | EG95: =ROUND(EG65+FP95,2) -> 0 | EH95: =ROUND(EH65+FQ95,2) -> 0 | EI95: =ROUND(EI65+FR95,2) -> 0 | EJ95: =ROUND(EJ65+FS95,2) -> 655463.71 | EK95: =ROUND(EK65+FT95,2) -> 655463.71 | EL95: =ROUND(EL65+FU95,2) -> 0 | EM95: =ROUND(EM65+FV95,2) -> 0 | EN95: =ROUND(EN65+FW95,2) -> 105831.27 | ... EV95: =ROUND(EV65+GE95,2) -> 0 | GX95: 0
A97: 50 | B97: 0 | C97: 0 | D97: 1 | E97: 201 | F97: =ROUND(Source!O95,O97) -> 45291.94 | G97: ПЗ | H97: Прямые затраты | K97: 201 | L97: 1 | M97: 3 | O97: 2 | P97: =ROUND(Source!DG95,O97) -> 309819.66 | W97: 45291.94 | X97: 1 | Y97: 45291.94 | Z97: 309819.66 | AA97: 1 | AB97: 309819.66
A98: 50 | B98: 0 | C98: 0 | D98: 1 | E98: 202 | F98: =ROUND(Source!P95,O98) -> 41523.21 | G98: СтМатОб | H98: Стоимость материальных ресурсов (всего) | K98: 202 | L98: 2 | M98: 3 | O98: 2 | P98: =ROUND(Source!DH95,O98) -> 105831.27 | W98: 41523.21 | X98: 1 | Y98: 41523.21 | Z98: 105831.27 | AA98: 1 | AB98: 105831.27
A99: 50 | B99: 0 | C99: 0 | D99: 1 | E99: 222 | F99: =ROUND(Source!AO95,O99) -> 0 | G99: СтМатОбЗак | H99: Стоимость материалов и оборудования заказчика | K99: 222 | L99: 3 | M99: 3 | O99: 2 | P99: =ROUND(Source!EG95,O99) -> 0 | W99: 0 | X99: 1 | Y99: 0 | Z99: 0 | AA99: 1 | AB99: 0
A100: 50 | B100: 0 | C100: 0 | D100: 1 | E100: 225 | F100: =ROUND(Source!AV95,O100) -> 41523.21 | G100: СтМатОбПод | H100: Стоимость материалов и оборудования подрядчика | K100: 225 | L100: 4 | M100: 3 | O100: 2 | P100: =ROUND(Source!EN95,O100) -> 105831.27 | W100: 41523.21 | X100: 1 | Y100: 41523.21 | Z100: 105831.27 | AA100: 1 | AB100: 105831.27
A101: 50 | B101: 0 | C101: 0 | D101: 1 | E101: 226 | F101: =ROUND(Source!AW95,O101) -> 41523.21 | G101: СтМат | H101: Стоимость материалов (всего) | K101: 226 | L101: 5 | M101: 3 | O101: 2 | P101: =ROUND(Source!EO95,O101) -> 105831.27 | W101: 41523.21 | X101: 1 | Y101: 41523.21 | Z101: 105831.27 | AA101: 1 | AB101: 105831.27
A102: 50 | B102: 0 | C102: 0 | D102: 1 | E102: 227 | F102: =ROUND(Source!AX95,O102) -> 0 | G102: СтМатЗак | H102: Стоимость материалов заказчика | K102: 227 | L102: 6 | M102: 3 | O102: 2 | P102: =ROUND(Source!EP95,O102) -> 0 | W102: 0 | X102: 1 | Y102: 0 | Z102: 0 | AA102: 1 | AB102: 0
A103: 50 | B103: 0 | C103: 0 | D103: 1 | E103: 228 | F103: =ROUND(Source!AY95,O103) -> 41523.21 | G103: СтМатПод | H103: Стоимость материалов подрядчика | K103: 228 | L103: 7 | M103: 3 | O103: 2 | P103: =ROUND(Source!EQ95,O103) -> 105831.27 | W103: 41523.21 | X103: 1 | Y103: 41523.21 | Z103: 105831.27 | AA103: 1 | AB103: 105831.27
A104: 50 | B104: 0 | C104: 0 | D104: 1 | E104: 216 | F104: =ROUND(Source!AP95,O104) -> 0 | G104: Оборуд | H104: Стоимость оборудования (всего) | K104: 216 | L104: 8 | M104: 3 | O104: 2 | P104: =ROUND(Source!EH95,O104) -> 0 | W104: 0 | X104: 1 | Y104: 0 | Z104: 0 | AA104: 1 | AB104: 0
A105: 50 | B105: 0 | C105: 0 | D105: 1 | E105: 223 | F105: =ROUND(Source!AQ95,O105) -> 0 | G105: ОборудЗак | H105: Стоимость оборудования заказчика | K105: 223 | L105: 9 | M105: 3 | O105: 2 | P105: =ROUND(Source!EI95,O105) -> 0 | W105: 0 | X105: 1 | Y105: 0 | Z105: 0 | AA105: 1 | AB105: 0
A106: 50 | B106: 0 | C106: 0 | D106: 1 | E106: 229 | F106: =ROUND(Source!AZ95,O106) -> 0 | G106: ОборудПод | H106: Стоимость оборудования подрядчика | K106: 229 | L106: 10 | M106: 3 | O106: 2 | P106: =ROUND(Source!ER95,O106) -> 0 | W106: 0 | X106: 1 | Y106: 0 | Z106: 0 | AA106: 1 | AB106: 0
A107: 50 | B107: 0 | C107: 0 | D107: 1 | E107: 203 | F107: =ROUND(Source!Q95,O107) -> 82.81 | G107: ЭММ | H107: Эксплуатация машин | K107: 203 | L107: 11 | M107: 3 | O107: 2 | P107: =ROUND(Source!DI95,O107) -> 1299.64 | W107: 82.81 | X107: 1 | Y107: 82.81 | Z107: 1299.64 | AA107: 1 | AB107: 1299.64
A108: 50 | B108: 0 | C108: 0 | D108: 1 | E108: 231 | F108: =ROUND(Source!BB95,O108) -> 0 | G108: ЭММсНРиСП | H108: Эксплуатация машин по ТСН-2001.16 | K108: 231 | L108: 12 | M108: 3 | O108: 2 | P108: =ROUND(Source!ET95,O108) -> 0 | W108: 0 | X108: 1 | Y108: 0 | Z108: 0 | AA108: 1 | AB108: 0
A109: 50 | B109: 0 | C109: 0 | D109: 1 | E109: 204 | F109: =ROUND(Source!R95,O109) -> 11.48 | G109: ЗПМ | H109: ЗП машинистов | K109: 204 | L109: 13 | M109: 3 | O109: 2 | P109: =ROUND(Source!DJ95,O109) -> 631.28 | W109: 11.48 | X109: 1 | Y109: 11.48 | Z109: 631.28 | AA109: 1 | AB109: 631.28
A110: 50 | B110: 0 | C110: 0 | D110: 1 | E110: 205 | F110: =ROUND(Source!S95,O110) -> 3685.92 | G110: ОЗП | H110: Основная ЗП рабочих | K110: 205 | L110: 14 | M110: 3 | O110: 2 | P110: =ROUND(Source!DK95,O110) -> 202688.75 | W110: 3685.92 | X110: 1 | Y110: 3685.92 | Z110: 202688.75 | AA110: 1 | AB110: 202688.75
A111: 50 | B111: 0 | C111: 0 | D111: 1 | E111: 232 | F111: =ROUND(Source!BC95,O111) -> 0 | G111: ОЗПсНРиСП | H111: Основная ЗП рабочих по ТСН-2001.16 | K111: 232 | L111: 15 | M111: 3 | O111: 2 | P111: =ROUND(Source!EU95,O111) -> 0 | W111: 0 | X111: 1 | Y111: 0 | Z111: 0 | AA111: 1 | AB111: 0
A112: 50 | B112: 0 | C112: 0 | D112: 1 | E112: 214 | F112: =ROUND(Source!AS95,O112) -> 51577.52 | G112: Строит | H112: Строительные работы с НР и СП | K112: 214 | L112: 16 | M112: 3 | O112: 2 | P112: =ROUND(Source!EK95,O112) -> 655463.71 | W112: 51577.52 | X112: 1 | Y112: 51577.52 | Z112: 655463.71 | AA112: 1 | AB112: 655463.71
A113: 50 | B113: 0 | C113: 0 | D113: 1 | E113: 215 | F113: =ROUND(Source!AT95,O113) -> 0 | G113: Монтаж | H113: Монтажные работы с НР и СП | K113: 215 | L113: 17 | M113: 3 | O113: 2 | P113: =ROUND(Source!EL95,O113) -> 0 | W113: 0 | X113: 1 | Y113: 0 | Z113: 0 | AA113: 1 | AB113: 0
A114: 50 | B114: 0 | C114: 0 | D114: 1 | E114: 217 | F114: =ROUND(Source!AU95,O114) -> 0 | G114: Прочие | H114: Прочие работы с НР и СП | K114: 217 | L114: 18 | M114: 3 | O114: 2 | P114: =ROUND(Source!EM95,O114) -> 0 | W114: 0 | X114: 1 | Y114: 0 | Z114: 0 | AA114: 1 | AB114: 0
A115: 50 | B115: 0 | C115: 0 | D115: 1 | E115: 230 | F115: =ROUND(Source!BA95,O115) -> 0 | G115: ПрочиеЗатр | H115: Прочие затраты по ТСН-2001.16 | K115: 230 | L115: 19 | M115: 3 | O115: 2 | P115: =ROUND(Source!ES95,O115) -> 0 | W115: 0 | X115: 1 | Y115: 0 | Z115: 0 | AA115: 1 | AB115: 0
A116: 50 | B116: 0 | C116: 0 | D116: 1 | E116: 206 | F116: =ROUND(Source!T95,O116) -> 0 | G116: ВозврМат | H116: Возврат материалов | K116: 206 | L116: 20 | M116: 3 | O116: 2 | P116: =ROUND(Source!DL95,O116) -> 0 | W116: 0 | X116: 1 | Y116: 0 | Z116: 0 | AA116: 1 | AB116: 0
A117: 50 | B117: 0 | C117: 0 | D117: 1 | E117: 207 | F117: =Source!U95 -> 292.35437 | G117: ТрудСтр | H117: Трудозатраты строителей | K117: 207 | L117: 21 | M117: 3 | O117: -1 | P117: =Source!DM95 -> 292.35437 | W117: 292.35437 | X117: 1 | Y117: 292.35437 | Z117: 292.35437 | AA117: 1 | AB117: 292.35437
A118: 50 | B118: 0 | C118: 0 | D118: 1 | E118: 208 | F118: =Source!V95 -> 0 | G118: ТрудМаш | H118: Трудозатраты машинистов | K118: 208 | L118: 22 | M118: 3 | O118: -1 | P118: =Source!DN95 -> 0 | W118: 0 | X118: 1 | Y118: 0 | Z118: 0 | AA118: 1 | AB118: 0
A119: 50 | B119: 0 | C119: 0 | D119: 1 | E119: 209 | F119: =ROUND(Source!W95,O119) -> 0 | G119: ТранспМат | H119: Транспорт материалов | K119: 209 | L119: 23 | M119: 3 | O119: 2 | P119: =ROUND(Source!DO95,O119) -> 0 | W119: 0 | X119: 1 | Y119: 0 | Z119: 0 | AA119: 1 | AB119: 0
A120: 50 | B120: 0 | C120: 0 | D120: 1 | E120: 233 | F120: =ROUND(Source!BD95,O120) -> 0 | G120: Перевозка | H120: Перевозка грузов | K120: 233 | L120: 24 | M120: 3 | O120: 2 | P120: =ROUND(Source!EV95,O120) -> 0 | W120: 0 | X120: 1 | Y120: 0 | Z120: 0 | AA120: 1 | AB120: 0
A121: 50 | B121: 0 | C121: 0 | D121: 1 | E121: 210 | F121: =ROUND(Source!X95,O121) -> 4030.17 | G121: НР | H121: Накладные расходы | K121: 210 | L121: 25 | M121: 3 | O121: 2 | P121: =ROUND(Source!DP95,O121) -> 221618.84 | W121: 4030.17 | X121: 1 | Y121: 4030.17 | Z121: 221618.84 | AA121: 1 | AB121: 221618.84
A122: 50 | B122: 0 | C122: 0 | D122: 1 | E122: 211 | F122: =ROUND(Source!Y95,O122) -> 2255.41 | G122: СмПриб | H122: Сметная прибыль | K122: 211 | L122: 26 | M122: 3 | O122: 2 | P122: =ROUND(Source!DQ95,O122) -> 124025.21 | W122: 2255.41 | X122: 1 | Y122: 2255.41 | Z122: 124025.21 | AA122: 1 | AB122: 124025.21
A123: 50 | B123: 0 | C123: 0 | D123: 1 | E123: 224 | F123: =ROUND(Source!AR95,O123) -> 51577.52 | G123: Всего | H123: Всего с НР и СП | K123: 224 | L123: 27 | M123: 3 | O123: 2 | P123: =ROUND(Source!EJ95,O123) -> 655463.71 | W123: 51577.52 | X123: 1 | Y123: 51577.52 | Z123: 655463.71 | AA123: 1 | AB123: 655463.71
A125: 4 | B125: 1 | D125: =ROW(A208) -> 208 | F125: Новый раздел | G125: Канализация хозяйственно-бытовая напорная (К1н) (подвал) | I125: 0 | K125: -1 | S125: 0 | T125: 0 | V125: 0 | BX125: 0 | CJ125: 0
...

Sheet SourceObSm
A1: 0 | B1: Smeta.RU (495) 974-1589 | D1: _OBSM_ | F1: 0 | G1: 0 | H1: 0 | I1: Smeta.RU | K1: 1 | L1: 74402 | M1: 10 | N1: 12 | O1: 1 | P1: 0 | Q1: 0
A4: 1 | B4: 1 | C4: -1 | G4: Капитальный ремонт здания Государственного бюджетного общеобразовательного учреждения города Москвы "Школа № 236" по адресу: г. Москва ул. Клязьминская, д. 7 к. 4. 1 этап | EC4: 0
A12: 1 | B12: 51 | C12: 0 | E12: 0 | F12: Новый объект (ТСН-2001 (Мосгосэкспертиза)) | G12: 02-01-05 Система водоотведения | I12: 0 | K12: 0 | L12: 0 | M12: 4098 | O12: 0 | P12: 0 | Q12: 0 | R12: 0 | S12: 0 | T12: 1 | V12: 0 | AB12: Кузнецова Е.А. | BB12: 0 | BH12: Сметные нормы списания | BI12: Коды ОКП для ТСН-2001 МГЭ Дополнение 80 | BJ12: 1 | BK12: 1 | BL12: 0 | BM12: 0 | BN12: 1 | BO12: 0 | BP12: 6 | BQ12: 2 | BR12: 1 | BS12: 1 | BT12: 0 | BU12: 0 | BV12: 1 | BW12: 0 | BX12: 0 | BZ12: Типовой расчет для ТСН-2001 МГЭ, Дополнение 80, ремонт | CA12: Территориальные сметные нормативы для Москвы ТСН-2001 (МГЭ), дополнение 80 | CB12: Территориальные сметные нормативы для Москвы ТСН-2001 (МГЭ), дополнение 80 | CC12: Территориальные сметные нормативы для Москвы ТСН-2001 (МГЭ), дополнение 80 | CD12: Территориальные сметные нормативы для Москвы ТСН-2001 (МГЭ), дополнение 80 | CE12: Поправки для ТСН-2001 от 03.02.2026 г. доп.80 | CF12: 0 | CG12: 0 | CH12: 327688 | CK12: 81 | CQ12: Территориальные сметные нормативы для Москвы (ТСН-2001) | CR12: ТЕР | CS12: 41660 | CT12: 1 | CU12: 80 | CY12: 0 | EC12: 0
A14: 22 | B14: 1 | C14: 0 | D14: 59209200 | E14: 59209203 | F14: 2 | G14: 1
A16: 3 | B16: 1 | C16: 02-01-05 | D16: Система водоотведения | E16: =ROUND((Source!P1033)/1000,2) -> 8552.93 | F16: =ROUND((Source!P1034)/1000,2) -> 17.83 | G16: =ROUND((Source!P1025)/1000,2) -> 573.86 | H16: =ROUND((Source!P1035)/1000+(Source!P1036)/1000,2) -> 0 | I16: =E16+F16+G16+H16 -> 9144.62 | J16: =ROUND((Source!P1031+Source!P1030)/1000,2) -> 1239.07 | K16: 12877.7 | L16: 0 | M16: 0 | N16: =I16+L16+M16 -> 9144.62 | T16: =ROUND((Source!F1033)/1000,2) -> 796.87 | U16: =ROUND((Source!F1034)/1000,2) -> 0.5 | V16: =ROUND((Source!F1025)/1000,2) -> 74.92 | W16: =ROUND((Source!F1035)/1000+(Source!F1036)/1000,2) -> 0 | X16: =T16+U16+V16+W16 -> 872.29 | Y16: =ROUND((Source!F1031+Source!F1030)/1000,2) -> 22.53 | Z16: 1645 | AA16: 0 | AB16: 0 | AC16: =X16+AA16+AB16 -> 872.29 | AI16: 0 | AJ16: -1 | AN16: 0 | AT16: 7065091 | AU16: 5812607.2 | AV16: 0 | AW16: 573855.26 | AX16: 0 | AY16: 24476.19 | AZ16: 11061.22 | BA16: 1228007.5 | BB16: 8552928 | BC16: 17832.74 | BD16: 0 | BE16: 0 | BF16: 1761.7362 | BG16: 0 | BH16: 0 | BI16: 1334798.3 | BJ16: 744726.73 | BK16: 9144616 | BR16: 834463.88 | BS16: 810536.74 | BT16: 0 | BU16: 74915.83 | BV16: 0 | BW16: 1595.67 | BX16: 201.15 | BY16: 22331.47 | BZ16: 796866.54 | CA16: 497.95 | CB16: 0 | CC16: 0 | CD16: 1761.7362 | CE16: 0 | CF16: 0 | CG16: 24273.49 | CH16: 13542.95 | CI16: 872280.32
A18: 51 | E18: 8552.93 | F18: 17.83 | G18: 573.86 | H18: 0 | I18: 9144.62 | J18: 1239.07 | K18: 12877.7 | L18: 0 | M18: 0 | N18: 9144.62 | T18: 796.87 | U18: 0.5 | V18: 74.92 | W18: 0 | X18: 872.29 | Y18: 22.53 | Z18: 1645 | AA18: 0 | AB18: 0 | AC18: 872.29
A20: 50 | B20: 0 | C20: 0 | D20: 1 | E20: 201 | F20: 7065091 | G20: ПЗ | H20: Прямые затраты | K20: 201 | L20: 1 | M20: 3 | O20: 2 | P20: 834463.88
A21: 50 | B21: 0 | C21: 0 | D21: 1 | E21: 202 | F21: 5812607.2 | G21: СтМатОб | H21: Стоимость материальных ресурсов (всего) | K21: 202 | L21: 2 | M21: 3 | O21: 2 | P21: 810536.74
A22: 50 | B22: 0 | C22: 0 | D22: 1 | E22: 222 | F22: 0 | G22: СтМатОбЗак | H22: Стоимость материалов и оборудования заказчика | K22: 222 | L22: 3 | M22: 3 | O22: 2 | P22: 0
A23: 50 | B23: 0 | C23: 0 | D23: 1 | E23: 225 | F23: 5812607.2 | G23: СтМатОбПод | H23: Стоимость материалов и оборудования подрядчика | K23: 225 | L23: 4 | M23: 3 | O23: 2 | P23: 810536.74
A24: 50 | B24: 0 | C24: 0 | D24: 1 | E24: 226 | F24: 5238752 | G24: СтМат | H24: Стоимость материалов (всего) | K24: 226 | L24: 5 | M24: 3 | O24: 2 | P24: 735620.91
A25: 50 | B25: 0 | C25: 0 | D25: 1 | E25: 227 | F25: 0 | G25: СтМатЗак | H25: Стоимость материалов заказчика | K25: 227 | L25: 6 | M25: 3 | O25: 2 | P25: 0
A26: 50 | B26: 0 | C26: 0 | D26: 1 | E26: 228 | F26: 5238752 | G26: СтМатПод | H26: Стоимость материалов подрядчика | K26: 228 | L26: 7 | M26: 3 | O26: 2 | P26: 735620.91
A27: 50 | B27: 0 | C27: 0 | D27: 1 | E27: 216 | F27: 573855.26 | G27: Оборуд | H27: Стоимость оборудования (всего) | K27: 216 | L27: 8 | M27: 3 | O27: 2 | P27: 74915.83
A28: 50 | B28: 0 | C28: 0 | D28: 1 | E28: 223 | F28: 0 | G28: ОборудЗак | H28: Стоимость оборудования заказчика | K28: 223 | L28: 9 | M28: 3 | O28: 2 | P28: 0
A29: 50 | B29: 0 | C29: 0 | D29: 1 | E29: 229 | F29: 573855.26 | G29: ОборудПод | H29: Стоимость оборудования подрядчика | K29: 229 | L29: 10 | M29: 3 | O29: 2 | P29: 74915.83
A30: 50 | B30: 0 | C30: 0 | D30: 1 | E30: 203 | F30: 24476.19 | G30: ЭММ | H30: Эксплуатация машин | K30: 203 | L30: 11 | M30: 3 | O30: 2 | P30: 1595.67
A31: 50 | B31: 0 | C31: 0 | D31: 1 | E31: 231 | F31: 0 | G31: ЭММсНРиСП | H31: Эксплуатация машин по ТСН-2001.16 | K31: 231 | L31: 12 | M31: 3 | O31: 2 | P31: 0
... A46: 50 | B46: 0 | C46: 0 | D46: 1 | E46: 224 | F46: 9144616 | G46: Всего | H46: Всего с НР и СП | K46: 224 | L46: 27 | M46: 3 | O46: 2 | P46: 872280.32
A48: -1
A51: 75 | B51: Текущий уровень цен | C51: 2025 | D51: 3 | E51: 0 | G51: 0 | H51: 1 | I51: 1 | J51: 1 | K51: 0 | L51: 0 | M51: 1 | N51: 59209200 | O51: 1
A52: 1 | B52: Сборник индексов | C52: Коэффициенты к ТСН-2001 МГЭ Дополнение 80, ремонт | D52: 2025 | E52: 9 | F52: 1 | G52: 1 | H52: 0 | I52: 2 | J52: 1 | K52: 9.88 | L52: 7.66 | M52: 1 | N52: 1 | O52: 9.88 | P52: 7.66 | Q52: 1 | AA52: 217/80 | AN52: 59209201
A53: 1 | B53: Сборник индексов | C53: Коэффициенты к ТСН-2001.13-2 Дополнение 46 | D53: 2025 | E53: 7 | F53: 1 | G53: 1 | H53: 0 | I53: 2 | J53: 1 | K53: 1 | L53: 1 | M53: 1 | N53: 1 | O53: 1 | P53: 1 | Q53: 1 | AA53: 62/46 | AN53: 59209202
A54: 75 | B54: Базовый ровень цен | C54: 2000 | D54: 0 | E54: 1 | F54: 0 | G54: 0 | H54: 1 | I54: 1 | J54: 3 | K54: 0 | L54: 0 | M54: 0 | N54: 59209203 | O54: 2
A55: 1 | B55: Сборник индексов | C55: Коэффициенты к ТСН-2001 МГЭ Дополнение 80, ремонт | D55: 2000 | E55: 1 | F55: 1 | G55: 1 | H55: 0 | I55: 2 | J55: 1 | K55: 1 | L55: 1 | M55: 1 | N55: 1 | O55: 1 | P55: 1 | Q55: 1 | AA55: 0 | AN55: 59209204

Sheet SmtRes
A1: =ROW(Source!A32) -> 32 | B1: 59209203 | C1: 59209356 | D1: 58266404 | E1: 1080 | F1: 1 | G1: 1080 | H1: 1 | I1: 9999990008 | K1: Трудозатраты рабочих | L1: 1191 | N1: 1013 | O1: чел.-ч. | P1: чел.-ч. | Q1: 1 | W1: 0 | X1: 476480486 | Y1: =((AT1*1.15)*1.1) -> 180.02215 | AA1: 0 | AB1: 0 | AC1: 0 | AD1: 0 | AE1: 0 | AF1: 0 | AG1: 0 | AH1: 0 | AI1: 1 | AJ1: 1 | AK1: 1 | AL1: 1 | AM1: -2 | AN1: 0 | AO1: 1 | AP1: 1 | AQ1: 0 | AR1: 0 | AT1: 142.31 | AU1: *1,15)*1,1 | AV1: 1 | AW1: 2 | AX1: 59211297 | AY1: 1 | AZ1: 0 | BA1: 1 | BB1: 0 | BC1: 0 | BD1: 0 | BE1: 0 | BF1: 0 | BG1: 0 | BH1: 0 | BI1: 0 | BJ1: 0 | BK1: 0 | BL1: 0 | BM1: 0 | BN1: 0 | BO1: 0 | BP1: 0 | BQ1: 0 | BR1: 0 | BS1: 0 | BT1: 0 | BU1: 0 | BV1: 0 | BW1: 0 | CU1: =ROUND(AT1*Source!I32*AH1*AL1,2) -> 0 | CV1: =ROUND(Y1*Source!I32,9) -> 28.803544 | CW1: 0 | CX1: =ROUND(Y1*Source!I32,9) -> 28.803544 | CY1: =AD1 -> 0 | CZ1: =AH1 -> 0 | DA1: =AL1 -> 1 | DB1: =ROUND(((ROUND(AT1*CZ1,2)*1.15)*1.1),6) -> 0 | DC1: =ROUND(((ROUND(AT1*AG1,2)*1.15)*1.1),6) -> 0 | DF1: =ROUND(ROUND(AE1,2)*CX1,2) -> 0 | DG1: =ROUND(ROUND(AF1,2)*CX1,2) -> 0 | DH1: =ROUND(ROUND(AG1,2)*CX1,2) -> 0 | DI1: =ROUND(ROUND(AH1,2)*CX1,2) -> 0 | DJ1: =DI1 -> 0 | DK1: 0 | DM1: 0 | DO1: 0
A2: =ROW(Source!A32) -> 32 | B2: 59209203 | C2: 59209356 | D2: 58340581 | E2: 1 | F2: 1 | G2: 1080 | H2: 2 | I2: 2.1-18-10 | J2: ТСН-2001.2. Доп. 68. п.1-18-10 (183004) | K2: Автомобили грузовые бортовые, грузоподъемность до 10 т | L2: 1368 | N2: 1011 | O2: маш.-ч | P2: маш.-ч | Q2: 1 | W2: 0 | X2: 229859724 | Y2: =((AT2*1.25)*1.1) -> 0.0825 | AA2: 0 | AB2: 131.6 | AC2: 13.47 | AD2: 0 | AE2: 0 | AF2: 123.34 | AG2: 12.62 | AH2: 0 | AI2: 1 | AJ2: 1 | AK2: 1 | AL2: 1 | AM2: -2 | AN2: 0 | AO2: 1 | AP2: 1 | AQ2: 0 | AR2: 0 | AT2: 0.06 | AU2: )*1,25)*1,1 | AV2: 0 | AW2: 2 | AX2: 59211298 | AY2: 1 | AZ2: 0 | BA2: 2 | BB2: 0 | BC2: 0 | BD2: 0 | BE2: 0 | BF2: 0 | BG2: 0 | BH2: 0 | BI2: 0 | BJ2: 0 | BK2: 0 | BL2: 0 | BM2: 0 | BN2: 0 | BO2: 0 | BP2: 0 | BQ2: 0 | BR2: 0 | BS2: 0 | BT2: 0 | BU2: 0 | BV2: 0 | BW2: 0 | CV2: 0 | CW2: =ROUND(Y2*Source!I32*DO2,9) -> 0.166584 | CX2: =ROUND(Y2*Source!I32,9) -> 0.0132 | CY2: =AB2 -> 131.6 | CZ2: =AF2 -> 123.34 | DA2: =AJ2 -> 1 | DB2: =ROUND(((ROUND(AT2*CZ2,2)*1.25)*1.1),6) -> 10.175 | DC2: =ROUND(((ROUND(AT2*AG2,2)*1.25)*1.1),6) -> 1.045 | DF2: =ROUND(ROUND(AE2,2)*CX2,2) -> 0 | DG2: =ROUND(ROUND(AF2,2)*CX2,2) -> 1.63 | DH2: =ROUND(ROUND(AG2,2)*CX2,2) -> 0.17 | DI2: =ROUND(ROUND(AH2,2)*CX2,2) -> 0 | DJ2: =DG2 -> 1.63 | DK2: 0 | DL2: 9999990009 | DM2: 0 | DN2: чел.-ч. | DO2: 12.62
A3: =ROW(Source!A32) -> 32 | B3: 59209203 | C3: 59209356 | D3: 58340697 | E3: 1 | F3: 1 | G3: 1080 | H3: 2 | I3: 2.1-30-102 | J3: ТСН-2001.2. Доп. 68. п.1-30-102 (303704) | K3: Дрели, мощность до 800 Вт | L3: 1368 | N3: 1011 | O3: маш.-ч | P3: маш.-ч | Q3: 1 | W3: 0 | X3: 2147454900 | Y3: =((AT3*1.25)*1.1) -> 2.475 | AA3: 0 | AB3: 0.85 | AC3: 0 | AD3: 0 | AE3: 0 | AF3: 0.8 | AG3: 0 | AH3: 0 | AI3: 1 | AJ3: 1 | AK3: 1 | AL3: 1 | AM3: -2 | AN3: 0 | AO3: 1 | AP3: 1 | AQ3: 0 | AR3: 0 | AT3: 1.8 | AU3: )*1,25)*1,1 | AV3: 0 | AW3: 2 | AX3: 59211300 | AY3: 1 | AZ3: 0 | BA3: 3 | BB3: 0 | BC3: 0 | BD3: 0 | BE3: 0 | BF3: 0 | BG3: 0 | BH3: 0 | BI3: 0 | BJ3: 0 | BK3: 0 | BL3: 0 | BM3: 0 | BN3: 0 | BO3: 0 | BP3: 0 | BQ3: 0 | BR3: 0 | BS3: 0 | BT3: 0 | BU3: 0 | BV3: 0 | BW3: 0 | CV3: 0 | CW3: =ROUND(Y3*Source!I32*DO3,9) -> 0 | CX3: =ROUND(Y3*Source!I32,9) -> 0.396 | CY3: =AB3 -> 0.85 | CZ3: =AF3 -> 0.8 | DA3: =AJ3 -> 1 | DB3: =ROUND(((ROUND(AT3*CZ3,2)*1.25)*1.1),6) -> 1.98 | DC3: =ROUND(((ROUND(AT3*AG3,2)*1.25)*1.1),6) -> 0 | DF3: =ROUND(ROUND(AE3,2)*CX3,2) -> 0 | DG3: =ROUND(ROUND(AF3,2)*CX3,2) -> 0.32 | DH3: =ROUND(ROUND(AG3,2)*CX3,2) -> 0 | DI3: =ROUND(ROUND(AH3,2)*CX3,2) -> 0 | DJ3: =DG3 -> 0.32 | DK3: 0 | DM3: 0 | DO3: 0
A4: =ROW(Source!A32) -> 32 | B4: 59209203 | C4: 59209356 | D4: 58340645 | E4: 1 | F4: 1 | G4: 1080 | H4: 2 | I4: 2.1-30-28 | J4: ТСН-2001.2. Доп. 68. п.1-30-28 (306204) | K4: Пилы маятниковые электрические | L4: 1368 | N4: 1011 | O4: маш.-ч | P4: маш.-ч | Q4: 1 | W4: 0 | X4: -118924016 | Y4: =((AT4*1.25)*1.1) -> 2.54375 | AA4: 0 | AB4: 1.15 | AC4: 0 | AD4: 0 | AE4: 0 | AF4: 1.08 | AG4: 0 | AH4: 0 | AI4: 1 | AJ4: 1 | AK4: 1 | AL4: 1 | AM4: -2 | AN4: 0 | AO4: 1 | AP4: 1 | AQ4: 0 | AR4: 0 | AT4: 1.85 | AU4: )*1,25)*1,1 | AV4: 0 | AW4: 2 | AX4: 59211301 | AY4: 1 | AZ4: 0 | BA4: 4 | BB4: 0 | BC4: 0 | BD4: 0 | BE4: 0 | BF4: 0 | BG4: 0 | BH4: 0 | BI4: 0 | BJ4: 0 | BK4: 0 | BL4: 0 | BM4: 0 | BN4: 0 | BO4: 0 | BP4: 0 | BQ4: 0 | BR4: 0 | BS4: 0 | BT4: 0 | BU4: 0 | BV4: 0 | BW4: 0 | CV4: 0 | CW4: =ROUND(Y4*Source!I32*DO4,9) -> 0 | CX4: =ROUND(Y4*Source!I32,9) -> 0.407 | CY4: =AB4 -> 1.15 | CZ4: =AF4 -> 1.08 | DA4: =AJ4 -> 1 | DB4: =ROUND(((ROUND(AT4*CZ4,2)*1.25)*1.1),6) -> 2.75 | DC4: =ROUND(((ROUND(AT4*AG4,2)*1.25)*1.1),6) -> 0 | DF4: =ROUND(ROUND(AE4,2)*CX4,2) -> 0 | DG4: =ROUND(ROUND(AF4,2)*CX4,2) -> 0.44 | DH4: =ROUND(ROUND(AG4,2)*CX4,2) -> 0 | DI4: =ROUND(ROUND(AH4,2)*CX4,2) -> 0 | DJ4: =DG4 -> 0.44 | DK4: 0 | DM4: 0 | DO4: 0
A5: =ROW(Source!A32) -> 32 | B5: 59209203 | C5: 59209356 | D5: 58339814 | E5: 1 | F5: 1 | G5: 1080 | H5: 2 | I5: 2.1-3-38 | J5: ТСН-2001.2. Доп. 68. п.1-3-38 (032009) | K5: Краны на автомобильном ходу, грузоподъемность до 16 т | L5: 1368 | N5: 1011 | O5: маш.-ч | P5: маш.-ч | Q5: 1 | W5: 0 | X5: 1087580389 | Y5: =((AT5*1.25)*1.1) -> 0.0825 | AA5: 0 | AB5: 191.17 | AC5: 18.06 | AD5: 0 | AE5: 0 | AF5: 179.17 | AG5: 16.93 | AH5: 0 | AI5: 1 | AJ5: 1 | AK5: 1 | AL5: 1 | AM5: -2 | AN5: 0 | AO5: 1 | AP5: 1 | AQ5: 0 | AR5: 0 | AT5: 0.06 | AU5: )*1,25)*1,1 | AV5: 0 | AW5: 2 | AX5: 59211299 | AY5: 1 | AZ5: 0 | BA5: 5 | BB5: 0 | BC5: 0 | BD5: 0 | BE5: 0 | BF5: 0 | BG5: 0 | BH5: 0 | BI5: 0 | BJ5: 0 | BK5: 0 | BL5: 0 | BM5: 0 | BN5: 0 | BO5: 0 | BP5: 0 | BQ5: 0 | BR5: 0 | BS5: 0 | BT5: 0 | BU5: 0 | BV5: 0 | BW5: 0 | CV5: 0 | CW5: =ROUND(Y5*Source!I32*DO5,9) -> 0.223476 | CX5: =ROUND(Y5*Source!I32,9) -> 0.0132 | CY5: =AB5 -> 191.17 | CZ5: =AF5 -> 179.17 | DA5: =AJ5 -> 1 | DB5: =ROUND(((ROUND(AT5*CZ5,2)*1.25)*1.1),6) -> 14.78125 | DC5: =ROUND(((ROUND(AT5*AG5,2)*1.25)*1.1),6) -> 1.4025 | DF5: =ROUND(ROUND(AE5,2)*CX5,2) -> 0 | DG5: =ROUND(ROUND(AF5,2)*CX5,2) -> 2.37 | DH5: =ROUND(ROUND(AG5,2)*CX5,2) -> 0.22 | DI5: =ROUND(ROUND(AH5,2)*CX5,2) -> 0 | DJ5: =DG5 -> 2.37 | DK5: 0 | DL5: 9999990009 | DM5: 0 | DN5: чел.-ч. | DO5: 16.93
A6: =ROW(Source!A32) -> 32 | B6: 59209203 | C6: 59209356 | D6: 58308811 | E6: 1 | F6: 1 | G6: 1080 | H6: 3 | I6: 1.1-1-115 | J6: ТСН-2001.1. Доп. 1-42. Р. 1, о. 1, поз. 115 | K6: Ветошь | L6: 1346 | N6: 1009 | O6: кг | P6: кг | Q6: 1 | W6: 0 | X6: -709773495 | Y6: =AT6 -> 0.34 | AA6: 1.61 | AB6: 0 | AC6: 0 | AD6: 0 | AE6: 1.61 | AF6: 0 | AG6: 0 | AH6: 0 | AI6: 1 | AJ6: 1 | AK6: 1 | AL6: 1 | AM6: -2 | AN6: 0 | AO6: 1 | AP6: 1 | AQ6: 0 | AR6: 0 | AT6: 0.34 | AV6: 0 | AW6: 2 | AX6: 59211302 | AY6: 1 | AZ6: 0 | BA6: 6 | BB6: 0 | BC6: 0 | BD6: 0 | BE6: 0 | BF6: 0 | BG6: 0 | BH6: 0 | BI6: 0 | BJ6: 0 | BK6: 0 | BL6: 0 | BM6: 0 | BN6: 0 | BO6: 0 | BP6: 0 | BQ6: 0 | BR6: 0 | BS6: 0 | BT6: 0 | BU6: 0 | BV6: 0 | BW6: 0 | CV6: 0 | CW6: 0 | CX6: =ROUND(Y6*Source!I32,9) -> 0.0544 | CY6: =AA6 -> 1.61 | CZ6: =AE6 -> 1.61 | DA6: =AI6 -> 1 | DB6: =ROUND(ROUND(AT6*CZ6,2),6) -> 0.55 | DC6: =ROUND(ROUND(AT6*AG6,2),6) -> 0 | DF6: =ROUND(ROUND(AE6,2)*CX6,2) -> 0.09 | DG6: =ROUND(ROUND(AF6,2)*CX6,2) -> 0 | DH6: =ROUND(ROUND(AG6,2)*CX6,2) -> 0 | DI6: =ROUND(ROUND(AH6,2)*CX6,2) -> 0 | DJ6: =DF6 -> 0.09 | DK6: 0 | DM6: 0 | DO6: 0
A7: =ROW(Source!A32) -> 32 | B7: 59209203 | C7: 59209356 | D7: 58308814 | E7: 1 | F7: 1 | G7: 1080 | H7: 3 | I7: 1.1-1-118 | J7: ТСН-2001.1. Доп. 1-42. Р. 1, о. 1, поз. 118 | K7: Вода | L7: 1339 | N7: 1007 | O7: м3 | P7: м3 | Q7: 1 | W7: 0 | X7: -744103292 | Y7: =AT7 -> 0.39 | AA7: 7.07 | AB7: 0 | AC7: 0 | AD7: 0 | AE7: 7.07 | AF7: 0 | AG7: 0 | AH7: 0 | AI7: 1 | AJ7: 1 | AK7: 1 | AL7: 1 | AM7: -2 | AN7: 0 | AO7: 1 | AP7: 1 | AQ7: 0 | AR7: 0 | AT7: 0.39 | AV7: 0 | AW7: 2 | AX7: 59211303 | AY7: 1 | AZ7: 0 | BA7: 7 | BB7: 0 | BC7: 0 | BD7: 0 | BE7: 0 | BF7: 0 | BG7: 0 | BH7: 0 | BI7: 0 | BJ7: 0 | BK7: 0 | BL7: 0 | BM7: 0 | BN7: 0 | BO7: 0 | BP7: 0 | BQ7: 0 | BR7: 0 | BS7: 0 | BT7: 0 | BU7: 0 | BV7: 0 | BW7: 0 | CV7: 0 | CW7: 0 | CX7: =ROUND(Y7*Source!I32,9) -> 0.0624 | CY7: =AA7 -> 7.07 | CZ7: =AE7 -> 7.07 | DA7: =AI7 -> 1 | DB7: =ROUND(ROUND(AT7*CZ7,2),6) -> 2.76 | DC7: =ROUND(ROUND(AT7*AG7,2),6) -> 0 | DF7: =ROUND(ROUND(AE7,2)*CX7,2) -> 0.44 | DG7: =ROUND(ROUND(AF7,2)*CX7,2) -> 0 | DH7: =ROUND(ROUND(AG7,2)*CX7,2) -> 0 | DI7: =ROUND(ROUND(AH7,2)*CX7,2) -> 0 | DJ7: =DF7 -> 0.44 | DK7: 0 | DM7: 0 | DO7: 0
A8: =ROW(Source!A32) -> 32 | B8: 59209203 | C8: 59209356 | D8: 58325480 | E8: 1 | F8: 1 | G8: 1080 | H8: 3 | I8: 1.12-8-74 | J8: ТСН-2001.1 Доп. 79, Р. 12, о. 8, поз. 74 | K8: Комплект деталей трубопроводов из чугуна с мелкодисперсным графитом с внутренним эпоксидным покрытием, наружным слоем краснокоричневой грунтовки (безраструбные трубы, фасонные части, крепеж), диаметр условного прохода 50 мм | L8: 1301 | N8: 1003 | O8: м | P8: м | Q8: 1 | W8: 0 | X8: 925110201 | Y8: =AT8 -> 100 | AA8: 1328.86 | AB8: 0 | AC8: 0 | AD8: 0 | AE8: 1328.86 | AF8: 0 | AG8: 0 | AH8: 0 | AI8: 1 | AJ8: 1 | AK8: 1 | AL8: 1 | AM8: 0 | AN8: 0 | AO8: 0 | AP8: 1 | AQ8: 0 | AR8: 0 | AT8: 100 | AV8: 0 | AW8: 1 | AX8: -1 | AY8: 0 | AZ8: 0 | BB8: 0 | BC8: 0 | BD8: 0 | BE8: 0 | BF8: 0 | BG8: 0 | BH8: 0 | BI8: 0 | BJ8: 0 | BK8: 0 | BL8: 0 | BM8: 0 | BN8: 0 | BO8: 0 | BP8: 0 | BQ8: 0 | BR8: 0 | BS8: 0 | BT8: 0 | BU8: 0 | BV8: 0 | BW8: 0 | CV8: 0 | CW8: 0 | CX8: =ROUND(Y8*Source!I32,9) -> 16 | CY8: =AA8 -> 1328.86 | CZ8: =AE8 -> 1328.86 | DA8: =AI8 -> 1 | DB8: =ROUND(ROUND(AT8*CZ8,2),6) -> 132886 | DC8: =ROUND(ROUND(AT8*AG8,2),6) -> 0 | DF8: =ROUND(ROUND(AE8,2)*CX8,2) -> 21261.76 | DG8: =ROUND(ROUND(AF8,2)*CX8,2) -> 0 | DH8: =ROUND(ROUND(AG8,2)*CX8,2) -> 0 | DI8: =ROUND(ROUND(AH8,2)*CX8,2) -> 0 | DJ8: =DF8 -> 21261.76 | DK8: 0 | DM8: 0 | DO8: 0
A9: =ROW(Source!A33) -> 33 | B9: 59209200 | C9: 59209356 | D9: 58266404 | E9: 1080 | F9: 1 | G9: 1080 | H9: 1 | I9: 9999990008 | K9: Трудозатраты рабочих | L9: 1191 | N9: 1013 | O9: чел.-ч. | P9: чел.-ч. | Q9: 1 | W9: 0 | X9: 476480486 | Y9: =((AT9*1.15)*1.1) -> 180.02215 | AA9: 0 | AB9: 0 | AC9: 0 | AD9: 0 | AE9: 0 | AF9: 0 | AG9: 0 | AH9: 0 | AI9: 1 | AJ9: 1 | AK9: 1 | AL9: 1 | AM9: 5 | AN9: 0 | AO9: 1 | AP9: 1 | AQ9: 0 | AR9: 0 | AT9: 142.31 | AU9: *1,15)*1,1 | AV9: 1 | AW9: 2 | AX9: 59211297 | AY9: 1 | AZ9: 0 | BA9: 9 | BB9: 0 | BC9: 0 | BD9: 0 | BE9: 0 | BF9: 0 | BG9: 0 | BH9: 0 | BI9: 0 | BJ9: 0 | BK9: 0 | BL9: 0 | BM9: 0 | BN9: 0 | BO9: 0 | BP9: 0 | BQ9: 0 | BR9: 0 | BS9: 0 | BT9: 0 | BU9: 0 | BV9: 0 | BW9: 0 | CU9: =ROUND(AT9*Source!I33*AH9*AL9,2) -> 0 | CV9: =ROUND(Y9*Source!I33,9) -> 28.803544 | CW9: 0 | CX9: =ROUND(Y9*Source!I33,9) -> 28.803544 | CY9: =AD9 -> 0 | CZ9: =AH9 -> 0 | DA9: =AL9 -> 1 | DB9: =ROUND(((ROUND(AT9*CZ9,2)*1.15)*1.1),6) -> 0 | DC9: =ROUND(((ROUND(AT9*AG9,2)*1.15)*1.1),6) -> 0 | DF9: =ROUND(ROUND(AE9,2)*CX9,2) -> 0 | DG9: =ROUND(ROUND(AF9,2)*CX9,2) -> 0 | DH9: =ROUND(ROUND(AG9,2)*CX9,2) -> 0 | DI9: =ROUND(ROUND(AH9,2)*CX9,2) -> 0 | DJ9: =DI9 -> 0 | DK9: 0 | DM9: 0 | DO9: 0
A10: =ROW(Source!A33) -> 33 | B10: 59209200 | C10: 59209356 | D10: 58340581 | E10: 1 | F10: 1 | G10: 1080 | H10: 2 | I10: 2.1-18-10 | J10: ТСН-2001.2. Доп. 68. п.1-18-10 (183004) | K10: Автомобили грузовые бортовые, грузоподъемность до 10 т | L10: 1368 | N10: 1011 | O10: маш.-ч | P10: маш.-ч | Q10: 1 | W10: 0 | X10: 229859724 | Y10: =((AT10*1.25)*1.1) -> 0.0825 | AA10: 0 | AB10: 1817.45 | AC10: 740.47 | AD10: 0 | AE10: 0 | AF10: 123.34 | AG10: 12.62 | AH10: 0 | AI10: 1 | AJ10: 13.81 | AK10: 54.99 | AL10: 1 | AM10: 2 | AN10: 0 | AO10: 1 | AP10: 1 | AQ10: 0 | AR10: 0 | AT10: 0.06 | AU10: )*1,25)*1,1 | AV10: 0 | AW10: 2 | AX10: 59211298 | AY10: 1 | AZ10: 0 | BA10: 10 | BB10: 0 | BC10: 0 | BD10: 0 | BE10: 0 | BF10: 0 | BG10: 0 | BH10: 0 | BI10: 0 | BJ10: 0 | BK10: 0 | BL10: 0 | BM10: 0 | BN10: 0 | BO10: 0 | BP10: 0 | BQ10: 0 | BR10: 0 | BS10: 0 | BT10: 0 | BU10: 0 | BV10: 0 | BW10: 0 | CV10: 0 | CW10: =ROUND(Y10*Source!I33*DO10,9) -> 0.166584 | CX10: =ROUND(Y10*Source!I33,9) -> 0.0132 | CY10: =AB10 -> 1817.45 | CZ10: =AF10 -> 123.34 | DA10: =AJ10 -> 13.81 | DB10: =ROUND(((ROUND(AT10*CZ10,2)*1.25)*1.1),6) -> 10.175 | DC10: =ROUND(((ROUND(AT10*AG10,2)*1.25)*1.1),6) -> 1.045 | DF10: =ROUND(ROUND(AE10,2)*CX10,2) -> 0 | DG10: =ROUND(ROUND(AF10*AJ10,2)*CX10,2) -> 22.48 | DH10: =ROUND(ROUND(AG10*AK10,2)*CX10,2) -> 9.16 | DI10: =ROUND(ROUND(AH10,2)*CX10,2) -> 0 | DJ10: =DG10 -> 22.48 | DK10: 0 | DL10: 9999990009 | DM10: 0 | DN10: чел.-ч. | DO10: 12.62
A11: =ROW(Source!A33) -> 33 | B11: 59209200 | C11: 59209356 | D11: 58340697 | E11: 1 | F11: 1 | G11: 1080 | H11: 2 | I11: 2.1-30-102 | J11: ТСН-2001.2. Доп. 68. п.1-30-102 (303704) | K11: Дрели, мощность до 800 Вт | L11: 1368 | N11: 1011 | O11: маш.-ч | P11: маш.-ч | Q11: 1 | W11: 0 | X11: 2147454900 | Y11: =((AT11*1.25)*1.1) -> 2.475 | AA11: 0 | AB11: 7.33 | AC11: 0 | AD11: 0 | AE11: 0 | AF11: 0.8 | AG11: 0 | AH11: 0 | AI11: 1 | AJ11: 8.59 | AK11: 54.99 | AL11: 1 | AM11: 2 | AN11: 0 | AO11: 1 | AP11: 1 | AQ11: 0 | AR11: 0 | AT11: 1.8 | AU11: )*1,25)*1,1 | AV11: 0 | AW11: 2 | AX11: 59211300 | AY11: 1 | AZ11: 0 | BA11: 11 | BB11: 0 | BC11: 0 | BD11: 0 | BE11: 0 | BF11: 0 | BG11: 0 | BH11: 0 | BI11: 0 | BJ11: 0 | BK11: 0 | BL11: 0 | BM11: 0 | BN11: 0 | BO11: 0 | BP11: 0 | BQ11: 0 | BR11: 0 | BS11: 0 | BT11: 0 | BU11: 0 | BV11: 0 | BW11: 0 | CV11: 0 | CW11: =ROUND(Y11*Source!I33*DO11,9) -> 0 | CX11: =ROUND(Y11*Source!I33,9) -> 0.396 | CY11: =AB11 -> 7.33 | CZ11: =AF11 -> 0.8 | DA11: =AJ11 -> 8.59 | DB11: =ROUND(((ROUND(AT11*CZ11,2)*1.25)*1.1),6) -> 1.98 | DC11: =ROUND(((ROUND(AT11*AG11,2)*1.25)*1.1),6) -> 0 | DF11: =ROUND(ROUND(AE11,2)*CX11,2) -> 0 | DG11: =ROUND(ROUND(AF11*AJ11,2)*CX11,2) -> 2.72 | DH11: =ROUND(ROUND(AG11*AK11,2)*CX11,2) -> 0 | DI11: =ROUND(ROUND(AH11,2)*CX11,2) -> 0 | DJ11: =DG11 -> 2.72 | DK11: 0 | DM11: 0 | DO11: 0
A12: =ROW(Source!A33) -> 33 | B12: 59209200 | C12: 59209356 | D12: 58340645 | E12: 1 | F12: 1 | G12: 1080 | H12: 2 | I12: 2.1-30-28 | J12: ТСН-2001.2. Доп. 68. п.1-30-28 (306204) | K12: Пилы маятниковые электрические | L12: 1368 | N12: 1011 | O12: маш.-ч | P12: маш.-ч | Q12: 1 | W12: 0 | X12: -118924016 | Y12: =((AT12*1.25)*1.1) -> 2.54375 | AA12: 0 | AB12: 10.08 | AC12: 0 | AD12: 0 | AE12: 0 | AF12: 1.08 | AG12: 0 | AH12: 0 | AI12: 1 | AJ12: 8.75 | AK12: 54.99 | AL12: 1 | AM12: 2 | AN12: 0 | AO12: 1 | AP12: 1 | AQ12: 0 | AR12: 0 | AT12: 1.85 | AU12: )*1,25)*1,1 | AV12: 0 | AW12: 2 | AX12: 59211301 | AY12: 1 | AZ12: 0 | BA12: 12 | BB12: 0 | BC12: 0 | BD12: 0 | BE12: 0 | BF12: 0 | BG12: 0 | BH12: 0 | BI12: 0 | BJ12: 0 | BK12: 0 | BL12: 0 | BM12: 0 | BN12: 0 | BO12: 0 | BP12: 0 | BQ12: 0 | BR12: 0 | BS12: 0 | BT12: 0 | BU12: 0 | BV12: 0 | BW12: 0 | CV12: 0 | CW12: =ROUND(Y12*Source!I33*DO12,9) -> 0 | CX12: =ROUND(Y12*Source!I33,9) -> 0.407 | CY12: =AB12 -> 10.08 | CZ12: =AF12 -> 1.08 | DA12: =AJ12 -> 8.75 | DB12: =ROUND(((ROUND(AT12*CZ12,2)*1.25)*1.1),6) -> 2.75 | DC12: =ROUND(((ROUND(AT12*AG12,2)*1.25)*1.1),6) -> 0 | DF12: =ROUND(ROUND(AE12,2)*CX12,2) -> 0 | DG12: =ROUND(ROUND(AF12*AJ12,2)*CX12,2) -> 3.85 | DH12: =ROUND(ROUND(AG12*AK12,2)*CX12,2) -> 0 | DI12: =ROUND(ROUND(AH12,2)*CX12,2) -> 0 | DJ12: =DG12 -> 3.85 | DK12: 0 | DM12: 0 | DO12: 0
A13: =ROW(Source!A33) -> 33 | B13: 59209200 | C13: 59209356 | D13: 58339814 | E13: 1 | F13: 1 | G13: 1080 | H13: 2 | I13: 2.1-3-38 | J13: ТСН-2001.2. Доп. 68. п.1-3-38 (032009) | K13: Краны на автомобильном ходу, грузоподъемность до 16 т | L13: 1368 | N13: 1011 | O13: маш.-ч | P13: маш.-ч | Q13: 1 | W13: 0 | X13: 1087580389 | Y13: =((AT13*1.25)*1.1) -> 0.0825 | AA13: 0 | AB13: 2628.65 | AC13: 993.36 | AD13: 0 | AE13: 0 | AF13: 179.17 | AG13: 16.93 | AH13: 0 | AI13: 1 | AJ13: 13.75 | AK13: 54.99 | AL13: 1 | AM13: 2 | AN13: 0 | AO13: 1 | AP13: 1 | AQ13: 0 | AR13: 0 | AT13: 0.06 | AU13: )*1,25)*1,1 | AV13: 0 | AW13: 2 | AX13: 59211299 | AY13: 1 | AZ13: 0 | BA13: 13 | BB13: 0 | BC13: 0 | BD13: 0 | BE13: 0 | BF13: 0 | BG13: 0 | BH13: 0 | BI13: 0 | BJ13: 0 | BK13: 0 | BL13: 0 | BM13: 0 | BN13: 0 | BO13: 0 | BP13: 0 | BQ13: 0 | BR13: 0 | BS13: 0 | BT13: 0 | BU13: 0 | BV13: 0 | BW13: 0 | CV13: 0 | CW13: =ROUND(Y13*Source!I33*DO13,9) -> 0.223476 | CX13: =ROUND(Y13*Source!I33,9) -> 0.0132 | CY13: =AB13 -> 2628.65 | CZ13: =AF13 -> 179.17 | DA13: =AJ13 -> 13.75 | DB13: =ROUND(((ROUND(AT13*CZ13,2)*1.25)*1.1),6) -> 14.78125 | DC13: =ROUND(((ROUND(AT13*AG13,2)*1.25)*1.1),6) -> 1.4025 | DF13: =ROUND(ROUND(AE13,2)*CX13,2) -> 0 | DG13: =ROUND(ROUND(AF13*AJ13,2)*CX13,2) -> 32.52 | DH13: =ROUND(ROUND(AG13*AK13,2)*CX13,2) -> 12.29 | DI13: =ROUND(ROUND(AH13,2)*CX13,2) -> 0 | DJ13: =DG13 -> 32.52 | DK13: 0 | DL13: 9999990009 | DM13: 0 | DN13: чел.-ч. | DO13: 16.93
A14: =ROW(Source!A33) -> 33 | B14: 59209200 | C14: 59209356 | D14: 58308811 | E14: 1 | F14: 1 | G14: 1080 | H14: 3 | I14: 1.1-1-115 | J14: ТСН-2001.1. Доп. 1-42. Р. 1, о. 1, поз. 115 | K14: Ветошь | L14: 1346 | N14: 1009 | O14: кг | P14: кг | Q14: 1 | W14: 0 | X14: -709773495 | Y14: =AT14 -> 0.34 | AA14: 23.97 | AB14: 0 | AC14: 0 | AD14: 0 | AE14: 1.61 | AF14: 0 | AG14: 0 | AH14: 0 | AI14: 14.89 | AJ14: 1 | AK14: 1 | AL14: 1 | AM14: 2 | AN14: 0 | AO14: 1 | AP14: 1 | AQ14: 0 | AR14: 0 | AT14: 0.34 | AV14: 0 | AW14: 2 | AX14: 59211302 | AY14: 1 | AZ14: 0 | BA14: 14 | BB14: 0 | BC14: 0 | BD14: 0 | BE14: 0 | BF14: 0 | BG14: 0 | BH14: 0 | BI14: 0 | BJ14: 0 | BK14: 0 | BL14: 0 | BM14: 0 | BN14: 0 | BO14: 0 | BP14: 0 | BQ14: 0 | BR14: 0 | BS14: 0 | BT14: 0 | BU14: 0 | BV14: 0 | BW14: 0 | CV14: 0 | CW14: 0 | CX14: =ROUND(Y14*Source!I33,9) -> 0.0544 | CY14: =AA14 -> 23.97 | CZ14: =AE14 -> 1.61 | DA14: =AI14 -> 14.89 | DB14: =ROUND(ROUND(AT14*CZ14,2),6) -> 0.55 | DC14: =ROUND(ROUND(AT14*AG14,2),6) -> 0 | DF14: =ROUND(ROUND(AE14*AI14,2)*CX14,2) -> 1.3 | DG14: =ROUND(ROUND(AF14,2)*CX14,2) -> 0 | DH14: =ROUND(ROUND(AG14,2)*CX14,2) -> 0 | DI14: =ROUND(ROUND(AH14,2)*CX14,2) -> 0 | DJ14: =DF14 -> 1.3 | DK14: 0 | DM14: 0 | DO14: 0
A15: =ROW(Source!A33) -> 33 | B15: 59209200 | C15: 59209356 | D15: 58308814 | E15: 1 | F15: 1 | G15: 1080 | H15: 3 | I15: 1.1-1-118 | J15: ТСН-2001.1. Доп. 1-42. Р. 1, о. 1, поз. 118 | K15: Вода | L15: 1339 | N15: 1007 | O15: м3 | P15: м3 | Q15: 1 | W15: 0 | X15: -744103292 | Y15: =AT15 -> 0.39 | AA15: 54.79 | AB15: 0 | AC15: 0 | AD15: 0 | AE15: 7.07 | AF15: 0 | AG15: 0 | AH15: 0 | AI15: 7.75 | AJ15: 1 | AK15: 1 | AL15: 1 | AM15: 2 | AN15: 0 | AO15: 1 | AP15: 1 | AQ15: 0 | AR15: 0 | AT15: 0.39 | AV15: 0 | AW15: 2 | AX15: 59211303 | AY15: 1 | AZ15: 0 | BA15: 15 | BB15: 0 | BC15: 0 | BD15: 0 | BE15: 0 | BF15: 0 | BG15: 0 | BH15: 0 | BI15: 0 | BJ15: 0 | BK15: 0 | BL15: 0 | BM15: 0 | BN15: 0 | BO15: 0 | BP15: 0 | BQ15: 0 | BR15: 0 | BS15: 0 | BT15: 0 | BU15: 0 | BV15: 0 | BW15: 0 | CV15: 0 | CW15: 0 | CX15: =ROUND(Y15*Source!I33,9) -> 0.0624 | CY15: =AA15 -> 54.79 | CZ15: =AE15 -> 7.07 | DA15: =AI15 -> 7.75 | DB15: =ROUND(ROUND(AT15*CZ15,2),6) -> 2.76 | DC15: =ROUND(ROUND(AT15*AG15,2),6) -> 0 | DF15: =ROUND(ROUND(AE15*AI15,2)*CX15,2) -> 3.42 | DG15: =ROUND(ROUND(AF15,2)*CX15,2) -> 0 | DH15: =ROUND(ROUND(AG15,2)*CX15,2) -> 0 | DI15: =ROUND(ROUND(AH15,2)*CX15,2) -> 0 | DJ15: =DF15 -> 3.42 | DK15: 0 | DM15: 0 | DO15: 0
A16: =ROW(Source!A33) -> 33 | B16: 59209200 | C16: 59209356 | D16: 58325480 | E16: 1 | F16: 1 | G16: 1080 | H16: 3 | I16: 1.12-8-74 | J16: ТСН-2001.1 Доп. 79, Р. 12, о. 8, поз. 74 | K16: Комплект деталей трубопроводов из чугуна с мелкодисперсным графитом с внутренним эпоксидным покрытием, наружным слоем краснокоричневой грунтовки (безраструбные трубы, фасонные части, крепеж), диаметр условного прохода 50 мм | L16: 1301 | N16: 1003 | O16: м | P16: м | Q16: 1 | W16: 0 | X16: 925110201 | Y16: =AT16 -> 100 | AA16: 1262.42 | AB16: 0 | AC16: 0 | AD16: 0 | AE16: 1328.86 | AF16: 0 | AG16: 0 | AH16: 0 | AI16: 0.95 | AJ16: 1 | AK16: 1 | AL16: 1 | AM16: 0 | AN16: 0 | AO16: 0 | AP16: 1 | AQ16: 0 | AR16: 0 | AT16: 100 | AV16: 0 | AW16: 1 | AX16: -1 | AY16: 0 | AZ16: 0 | BB16: 0 | BC16: 0 | BD16: 0 | BE16: 0 | BF16: 0 | BG16: 0 | BH16: 0 | BI16: 0 | BJ16: 0 | BK16: 0 | BL16: 0 | BM16: 0 | BN16: 0 | BO16: 0 | BP16: 0 | BQ16: 0 | BR16: 0 | BS16: 0 | BT16: 0 | BU16: 0 | BV16: 0 | BW16: 0 | CV16: 0 | CW16: 0 | CX16: =ROUND(Y16*Source!I33,9) -> 16 | CY16: =AA16 -> 1262.42 | CZ16: =AE16 -> 1328.86 | DA16: =AI16 -> 0.95 | DB16: =ROUND(ROUND(AT16*CZ16,2),6) -> 132886 | DC16: =ROUND(ROUND(AT16*AG16,2),6) -> 0 | DF16: =ROUND(ROUND(AE16*AI16,2)*CX16,2) -> 20198.72 | DG16: =ROUND(ROUND(AF16,2)*CX16,2) -> 0 | DH16: =ROUND(ROUND(AG16,2)*CX16,2) -> 0 | DI16: =ROUND(ROUND(AH16,2)*CX16,2) -> 0 | DJ16: =DF16 -> 20198.72 | DK16: 0 | DM16: 0 | DO16: 0
A17: =ROW(Source!A36) -> 36 | B17: 59209203 | C17: 59209374 | D17: 58266404 | E17: 1080 | F17: 1 | G17: 1080 | H17: 1 | I17: 9999990008 | K17: Трудозатраты рабочих | L17: 1191 | N17: 1013 | O17: чел.-ч. | P17: чел.-ч. | Q17: 1 | W17: 0 | X17: 476480486 | Y17: =((AT17*1.15)*1.1) -> 70.84 | AA17: 0 | AB17: 0 | AC17: 0 | AD17: 0 | AE17: 0 | AF17: 0 | AG17: 0 | AH17: 0 | AI17: 1 | AJ17: 1 | AK17: 1 | AL17: 1 | AM17: -2 | AN17: 0 | AO17: 1 | AP17: 1 | AQ17: 0 | AR17: 0 | AT17: 56 | AU17: *1,15)*1,1 | AV17: 1 | AW17: 2 | AX17: 59211305 | AY17: 1 | AZ17: 0 | BA17: 17 | BB17: 0 | BC17: 0 | BD17: 0 | BE17: 0 | BF17: 0 | BG17: 0 | BH17: 0 | BI17: 0 | BJ17: 0 | BK17: 0 | BL17: 0 | BM17: 0 | BN17: 0 | BO17: 0 | BP17: 0 | BQ17: 0 | BR17: 0 | BS17: 0 | BT17: 0 | BU17: 0 | BV17: 0 | BW17: 0 | CU17: =ROUND(AT17*Source!I36*AH17*AL17,2) -> 0 | CV17: =ROUND(Y17*Source!I36,9) -> 151.5976 | CW17: 0 | CX17: =ROUND(Y17*Source!I36,9) -> 151.5976 | CY17: =AD17 -> 0 | CZ17: =AH17 -> 0 | DA17: =AL17 -> 1 | DB17: =ROUND(((ROUND(AT17*CZ17,2)*1.15)*1.1),6) -> 0 | DC17: =ROUND(((ROUND(AT17*AG17,2)*1.15)*1.1),6) -> 0 | DF17: =ROUND(ROUND(AE17,2)*CX17,2) -> 0 | DG17: =ROUND(ROUND(AF17,2)*CX17,2) -> 0 | DH17: =ROUND(ROUND(AG17,2)*CX17,2) -> 0 | DI17: =ROUND(ROUND(AH17,2)*CX17,2) -> 0 | DJ17: =DI17 -> 0 | DK17: 0 | DM17: 0 | DO17: 0
