Workbook

Sheet 02-01-10
A1: =Source!B1 -> Smeta.RU (495) 974-1589
J2: Форма № 4б
A3: Капитальный ремонт здания Государственного бюджетного общеобразовательного учреждения города Москвы "Школа №236" по адресу: г. Москва, улица Клязьминская, дом 7, корпус 4. | AP3: Капитальный ремонт здания Государственного бюджетного общеобразовательного учреждения города Москвы "Школа №236" по адресу: г. Москва, улица Клязьминская, дом 7, корпус 4. 02-01-10 РТС
A4: (наименование стройки и/или объекта)
A6: =CONCATENATE( "ЛОКАЛЬНАЯ СМЕТА № ",IF(Source!F20<>"Новая локальная смета", Source!F20, "")) -> ЛОКАЛЬНАЯ СМЕТА № 02-01-10
A8: =IF(Source!G20<>"Новая локальная смета", Source!G20, "") -> Радиотрансляционная сеть
A9: (наименование работ и затрат)
A11: =CONCATENATE( "Основание: чертежи № ", Source!J20) -> Основание: чертежи № 2024-00272-01-0-ИОС5.3
I13: В базисном уровне цен | J13: В текущем уровне цен
E14: Сметная стоимость | I14: =I15+I16+I17+I18 -> 195.07 | J14: =J15+J16+J17+J18 -> 1717.49 | K14: тыс.руб.
E15: Строительные работы | I15: =ROUND((Source!F238)/1000, 2) -> 0 | J15: =ROUND((Source!P238)/1000, 2) -> 0 | K15: тыс.руб.
E16: Работы по монтажу оборудования | I16: =ROUND((Source!F239)/1000, 2) -> 17.03 | J16: =ROUND((Source!P239)/1000, 2) -> 353.21 | K16: тыс.руб.
E17: Оборудование | I17: =ROUND((Source!F230)/1000, 2) -> 178.04 | J17: =ROUND((Source!P230)/1000, 2) -> 1364.28 | K17: тыс.руб.
E18: Прочие работы и затраты | I18: =ROUND((Source!F240+Source!F241)/1000, 2) -> 0 | J18: =ROUND((Source!P240+Source!P241)/1000, 2) -> 0 | K18: тыс.руб.
E19: Средства на оплату труда | I19: =(Source!F236+ Source!F235)/1000 -> 1.79751 | J19: =((Source!P236 + Source!P235)/1000) -> 98.84508 | K19: тыс.руб.
E20: Затраты труда | I20: =Source!F243 -> 138.52903 | K20: чел.-ч.
E21: Кроме того:
E22: Возврат материалов | I22: =SUM(Y28:Y300)/1000 -> 0 | J22: =SUM(Z28:Z300)/1000 -> 0 | K22: тыс.руб.
A24: Составлен(а) по ТСН-2001 с учетом Дополнения №: 80
A25: № и период сборника коэффициентов (индексов) пересчета: Коэффициенты к ТСН-2001 МГЭ Дополнение 80, строительство №217/80 III квартал 2025 года и Коэффициенты к ТСН-2001.13-2 Дополнение 46 №62/46 III квартал 2025 года | AP25: № и период сборника коэффициентов (индексов) пересчета: Коэффициенты к ТСН-2001 МГЭ Дополнение 80, строительство №217/80 III квартал 2025 года и Коэффициенты к ТСН-2001.13-2 Дополнение 46 №62/46 III квартал 2025 года
A26: № п/п | B26: Шифр расценки и коды ресурсов | C26: Наименование работ и затрат | D26: Ед. изм. | E26: Кол-во единиц | F26: Цена на ед. изм., руб. | G26: Попра- вочные коэффи- циенты | H26: Коэффи- циенты зимних удорожа- ний | I26: Всего в ценах на январь 2000 года, руб. | J26: Коэффи- циенты (индек- сы) пере- счета, нормы НР и СП | K26: ВСЕГО затрат в текущем уровне цен, руб.
A27: 1 | B27: 2 | C27: 3 | D27: 4 | E27: 5 | F27: 6 | G27: 7 | H27: 8 | I27: 9 | J27: 10 | K27: 11
A29: =CONCATENATE("Раздел: ",IF(Source!G24<>"Новый раздел", Source!G24, "")) -> Раздел: Оборудование
A30: 1 | B30: =Source!F28 -> 4.11-17-1 | C30: Монтаж щитов и пультов массой до 50кг | D30: =Source!H28 -> 1 ШТ. | E30: =Source!I28 -> 1 | Q30: =Source!X28 -> 62.37 | R30: =Source!X29 -> 3429.73 | S30: =Source!Y28 -> 31.88 | T30: =Source!Y29 -> 1752.97 | U30: =ROUND((175/100)*ROUND(Source!R28, 2), 2) -> 0.77 | V30: =ROUND((0/100)*ROUND(Source!R29, 2), 2) -> 0 | AC30: 0
C31: ЗП | F31: =Source!AO28 -> 59.79 | G31: =Source!DG28 -> *1,1 | H31: =Source!AV29 -> 1.047 | I31: =Source!S28 -> 68.86 | J31: =IF(Source!BA29<> 0, Source!BA29, 1) -> 54.99 | K31: =Source!S29 -> 3786.61
C32: ЭМ | F32: =Source!AM28 -> 4.27 | G32: =Source!DE28 -> *1,1 | H32: =Source!AV29 -> 1.047 | I32: =Source!Q28 -> 4.92 | J32: =IF(Source!BB29<> 0, Source!BB29, 1) -> 14.09 | K32: =Source!Q29 -> 69.32
C33: в т.ч. ЗПМ | F33: =Source!AN28 -> 0.38 | G33: =Source!DF28 -> *1,1 | H33: =Source!AV29 -> 1.047 | I33: =Source!R28 -> 0.44 | J33: =IF(Source!BS29<> 0, Source!BS29, 1) -> 54.99 | K33: =Source!R29 -> 24.2
C34: МР | F34: =Source!AL28 -> 89.36 | G34: =Source!DD28 | H34: =Source!AW29 -> 1 | I34: =Source!P28 -> 89.36 | J34: =IF(Source!BC29<> 0, Source!BC29, 1) -> 5.08 | K34: =Source!P29 -> 453.95
A35: 1,1 | B35: =Source!F30 -> КА-1 | C35: ОБОРУДОВАНИЕ:_x000D_ Устройство подачи программ вещания УППВ 1918 М1 исп. У (исп. 2022) 45 303,63 = [399 507,72 / 1,2 / 7,66] + 3% Трансп + 1,2% Заг.скл | D35: =Source!H30 -> шт. | E35: =Source!I30 -> 1 | F35: =Source!AK30 -> 45303.63 | H35: =Source!AW31 -> 1 | I35: =Source!O30 -> 45303.63 | J35: =IF(Source!BC31<> 0, Source!BC31, 1) -> 7.66 | K35: =Source!O31 -> 347025.81 | Q35: =Source!X30 -> 0 | R35: =Source!X31 -> 0 | S35: =Source!Y30 -> 0 | T35: =Source!Y31 -> 0 | U35: =ROUND((175/100)*ROUND(Source!R30, 2), 2) -> 0 | V35: =ROUND((0/100)*ROUND(Source!R31, 2), 2) -> 0 | AC35: 5
C36: НР от ФОТ | D36: % | E36: =Source!BZ29 -> 90 | I36: =SUM(Q30:Q35) -> 62.37 | J36: =Source!AT29 -> 90 | K36: =SUM(R30:R35) -> 3429.73
C37: СП от ФОТ | D37: % | E37: =Source!CA29 -> 46 | I37: =SUM(S30:S36) -> 31.88 | J37: =Source!AU29 -> 46 | K37: =SUM(T30:T36) -> 1752.97
C38: ЗТР | D38: чел-ч | E38: =Source!AQ28 -> 5.15 | G38: =Source!DI28 -> *1,1 | H38: =Source!AV29 -> 1.047 | I38: =Source!U28 -> 5.931255
C39: ВСЕГО работ по позиции: | H39: =I31+I32+I34+I36+I37+SUM(I35:I35)-SUMIF(AC35:AC35, 5, I35:I35)-SUMIF(AC35:AC35, 6, I35:I35) -> 257.39 | J39: =K31+K32+K34+K36+K37+SUM(K35:K35)-SUMIF(AC35:AC35, 5, K35:K35)-SUMIF(AC35:AC35, 6, K35:K35) -> 9492.58
C40: ВСЕГО оборудование по позиции: | H40: =SUMIF(AC35:AC35, 5, I35:I35)+SUMIF(AC35:AC35, 6, I35:I35) -> 45303.63 | J40: =SUMIF(AC35:AC35, 5, K35:K35)+SUMIF(AC35:AC35, 6, K35:K35) -> 347025.81
C41: ВСЕГО по позиции: | H41: =I31+I32+I34+I36+I37+SUM(I35:I35) -> 45561.02 | J41: =K31+K32+K34+K36+K37+SUM(K35:K35) -> 356518.39 | O41: =I31+I32+I34+I36+I37+SUM(I35:I35) -> 45561.02 | P41: =K31+K32+K34+K36+K37+SUM(K35:K35) -> 356518.39
A43: 2 | B43: =Source!F32 -> 4.11-12-1 | C43: Установка съемных и выдвижных блоков (модулей, ячеек, ТЭЗ) массой до 5 кг | D43: =Source!H32 -> 1 ШТ. | E43: =Source!I32 -> 1 | Q43: =Source!X32 -> 12.16 | R43: =Source!X33 -> 668.63 | S43: =Source!Y32 -> 6.21 | T43: =Source!Y33 -> 341.74 | U43: =ROUND((175/100)*ROUND(Source!R32, 2), 2) -> 0.16 | V43: =ROUND((0/100)*ROUND(Source!R33, 2), 2) -> 0 | AC43: 0
C44: ЗП | F44: =Source!AO32 -> 11.65 | G44: =Source!DG32 -> *1,1 | H44: =Source!AV33 -> 1.047 | I44: =Source!S32 -> 13.42 | J44: =IF(Source!BA33<> 0, Source!BA33, 1) -> 54.99 | K44: =Source!S33 -> 737.97
C45: ЭМ | F45: =Source!AM32 -> 0.5 | G45: =Source!DE32 -> *1,1 | H45: =Source!AV33 -> 1.047 | I45: =Source!Q32 -> 0.58 | J45: =IF(Source!BB33<> 0, Source!BB33, 1) -> 16.26 | K45: =Source!Q33 -> 9.43
C46: в т.ч. ЗПМ | F46: =Source!AN32 -> 0.08 | G46: =Source!DF32 -> *1,1 | H46: =Source!AV33 -> 1.047 | I46: =Source!R32 -> 0.09 | J46: =IF(Source!BS33<> 0, Source!BS33, 1) -> 54.99 | K46: =Source!R33 -> 4.95
A47: 2,1 | B47: =Source!F34 -> КА-2 | C47: ОБОРУДОВАНИЕ:_x000D_ Модуль для приема интернет вещания радиостанции «Радио Москвы» 3 841,94 = [33 880 / 1,2 / 7,66] + 3% Трансп + 1,2% Заг.скл | D47: =Source!H34 -> шт. | E47: =Source!I34 -> 1 | F47: =Source!AK34 -> 3841.94 | H47: =Source!AW35 -> 1 | I47: =Source!O34 -> 3841.94 | J47: =IF(Source!BC35<> 0, Source!BC35, 1) -> 7.66 | K47: =Source!O35 -> 29429.26 | Q47: =Source!X34 -> 0 | R47: =Source!X35 -> 0 | S47: =Source!Y34 -> 0 | T47: =Source!Y35 -> 0 | U47: =ROUND((175/100)*ROUND(Source!R34, 2), 2) -> 0 | V47: =ROUND((0/100)*ROUND(Source!R35, 2), 2) -> 0 | AC47: 5
C48: НР от ФОТ | D48: % | E48: =Source!BZ33 -> 90 | I48: =SUM(Q43:Q47) -> 12.16 | J48: =Source!AT33 -> 90 | K48: =SUM(R43:R47) -> 668.63
C49: СП от ФОТ | D49: % | E49: =Source!CA33 -> 46 | I49: =SUM(S43:S48) -> 6.21 | J49: =Source!AU33 -> 46 | K49: =SUM(T43:T48) -> 341.74
C50: ЗТР | D50: чел-ч | E50: =Source!AQ32 -> 1.03 | G50: =Source!DI32 -> *1,1 | H50: =Source!AV33 -> 1.047 | I50: =Source!U32 -> 1.186251
C51: ВСЕГО работ по позиции: | H51: =I44+I45+I48+I49+SUM(I47:I47)-SUMIF(AC47:AC47, 5, I47:I47)-SUMIF(AC47:AC47, 6, I47:I47) -> 32.37 | J51: =K44+K45+K48+K49+SUM(K47:K47)-SUMIF(AC47:AC47, 5, K47:K47)-SUMIF(AC47:AC47, 6, K47:K47) -> 1757.77
C52: ВСЕГО оборудование по позиции: | H52: =SUMIF(AC47:AC47, 5, I47:I47)+SUMIF(AC47:AC47, 6, I47:I47) -> 3841.94 | J52: =SUMIF(AC47:AC47, 5, K47:K47)+SUMIF(AC47:AC47, 6, K47:K47) -> 29429.26
C53: ВСЕГО по позиции: | H53: =I44+I45+I48+I49+SUM(I47:I47) -> 3874.31 | J53: =K44+K45+K48+K49+SUM(K47:K47) -> 31187.03 | O53: =I44+I45+I48+I49+SUM(I47:I47) -> 3874.31 | P53: =K44+K45+K48+K49+SUM(K47:K47) -> 31187.03
A55: 3 | B55: =Source!F36 -> 4.11-17-1 | C55: Монтаж щитов и пультов массой до 50кг | D55: =Source!H36 -> 1 ШТ. | E55: =Source!I36 -> 1 | Q55: =Source!X36 -> 62.37 | R55: =Source!X37 -> 3429.73 | S55: =Source!Y36 -> 31.88 | T55: =Source!Y37 -> 1752.97 | U55: =ROUND((175/100)*ROUND(Source!R36, 2), 2) -> 0.77 | V55: =ROUND((0/100)*ROUND(Source!R37, 2), 2) -> 0 | AC55: 0
C56: ЗП | F56: =Source!AO36 -> 59.79 | G56: =Source!DG36 -> *1,1 | H56: =Source!AV37 -> 1.047 | I56: =Source!S36 -> 68.86 | J56: =IF(Source!BA37<> 0, Source!BA37, 1) -> 54.99 | K56: =Source!S37 -> 3786.61
C57: ЭМ | F57: =Source!AM36 -> 4.27 | G57: =Source!DE36 -> *1,1 | H57: =Source!AV37 -> 1.047 | I57: =Source!Q36 -> 4.92 | J57: =IF(Source!BB37<> 0, Source!BB37, 1) -> 14.09 | K57: =Source!Q37 -> 69.32
C58: в т.ч. ЗПМ | F58: =Source!AN36 -> 0.38 | G58: =Source!DF36 -> *1,1 | H58: =Source!AV37 -> 1.047 | I58: =Source!R36 -> 0.44 | J58: =IF(Source!BS37<> 0, Source!BS37, 1) -> 54.99 | K58: =Source!R37 -> 24.2
C59: МР | F59: =Source!AL36 -> 89.36 | G59: =Source!DD36 | H59: =Source!AW37 -> 1 | I59: =Source!P36 -> 89.36 | J59: =IF(Source!BC37<> 0, Source!BC37, 1) -> 5.08 | K59: =Source!P37 -> 453.95
A60: 3,1 | B60: =Source!F38 -> КА-3 | C60: ОБОРУДОВАНИЕ:_x000D_ Устройство сопряжения с РСО г.Москвы УС-1 (БАО-РСПИ+БСМС) 113 908,90 = [1 004 500 / 1,2 / 7,66] + 3% Трансп + 1,2% Заг.скл | D60: =Source!H38 -> шт. | E60: =Source!I38 -> 1 | F60: =Source!AK38 -> 113908.9 | H60: =Source!AW39 -> 1 | I60: =Source!O38 -> 113908.9 | J60: =IF(Source!BC39<> 0, Source!BC39, 1) -> 7.66 | K60: =Source!O39 -> 872542.17 | Q60: =Source!X38 -> 0 | R60: =Source!X39 -> 0 | S60: =Source!Y38 -> 0 | T60: =Source!Y39 -> 0 | U60: =ROUND((175/100)*ROUND(Source!R38, 2), 2) -> 0 | V60: =ROUND((0/100)*ROUND(Source!R39, 2), 2) -> 0 | AC60: 5
C61: НР от ФОТ | D61: % | E61: =Source!BZ37 -> 90 | I61: =SUM(Q55:Q60) -> 62.37 | J61: =Source!AT37 -> 90 | K61: =SUM(R55:R60) -> 3429.73
C62: СП от ФОТ | D62: % | E62: =Source!CA37 -> 46 | I62: =SUM(S55:S61) -> 31.88 | J62: =Source!AU37 -> 46 | K62: =SUM(T55:T61) -> 1752.97
C63: ЗТР | D63: чел-ч | E63: =Source!AQ36 -> 5.15 | G63: =Source!DI36 -> *1,1 | H63: =Source!AV37 -> 1.047 | I63: =Source!U36 -> 5.931255
C64: ВСЕГО работ по позиции: | H64: =I56+I57+I59+I61+I62+SUM(I60:I60)-SUMIF(AC60:AC60, 5, I60:I60)-SUMIF(AC60:AC60, 6, I60:I60) -> 257.39 | J64: =K56+K57+K59+K61+K62+SUM(K60:K60)-SUMIF(AC60:AC60, 5, K60:K60)-SUMIF(AC60:AC60, 6, K60:K60) -> 9492.58
C65: ВСЕГО оборудование по позиции: | H65: =SUMIF(AC60:AC60, 5, I60:I60)+SUMIF(AC60:AC60, 6, I60:I60) -> 113908.9 | J65: =SUMIF(AC60:AC60, 5, K60:K60)+SUMIF(AC60:AC60, 6, K60:K60) -> 872542.17
C66: ВСЕГО по позиции: | H66: =I56+I57+I59+I61+I62+SUM(I60:I60) -> 114166.29 | J66: =K56+K57+K59+K61+K62+SUM(K60:K60) -> 882034.75 | O66: =I56+I57+I59+I61+I62+SUM(I60:I60) -> 114166.29 | P66: =K56+K57+K59+K61+K62+SUM(K60:K60) -> 882034.75
A68: 4 | B68: =Source!F40 -> 4.10-69-3 | C68: Монтаж щита распределительного настенного типа | D68: =Source!H40 -> 1 ШТ. | E68: =Source!I40 -> 1 | Q68: =Source!X40 -> 489.59 | R68: =Source!X41 -> 26922.67 | S68: =Source!Y40 -> 273.14 | T68: =Source!Y41 -> 15020.01 | U68: =ROUND((175/100)*ROUND(Source!R40, 2), 2) -> 0 | V68: =ROUND((0/100)*ROUND(Source!R41, 2), 2) -> 0 | AC68: 0
C69: ЗП | F69: =Source!AO40 -> 447.48 | G69: =Source!DG40 -> *1,1 | H69: =Source!AV41 -> 1.047 | I69: =Source!S40 -> 515.36 | J69: =IF(Source!BA41<> 0, Source!BA41, 1) -> 54.99 | K69: =Source!S41 -> 28339.65
C70: МР | F70: =Source!AL40 -> 76.75 | G70: =Source!DD40 | H70: =Source!AW41 -> 1 | I70: =Source!P40 -> 76.75 | J70: =IF(Source!BC41<> 0, Source!BC41, 1) -> 9.1 | K70: =Source!P41 -> 698.43
A71: 4,1 | B71: =Source!F42 -> КА-4 | C71: ОБОРУДОВАНИЕ:_x000D_ Резервный канал РСПИ ОСПИ-Тандем 11 113,06 = [98 000 / 1,2 / 7,66] + 3% Трансп + 1,2% Заг.скл | D71: =Source!H42 -> шт. | E71: =Source!I42 -> 1 | F71: =Source!AK42 -> 11113.06 | H71: =Source!AW43 -> 1 | I71: =Source!O42 -> 11113.06 | J71: =IF(Source!BC43<> 0, Source!BC43, 1) -> 7.66 | K71: =Source!O43 -> 85126.04 | Q71: =Source!X42 -> 0 | R71: =Source!X43 -> 0 | S71: =Source!Y42 -> 0 | T71: =Source!Y43 -> 0 | U71: =ROUND((175/100)*ROUND(Source!R42, 2), 2) -> 0 | V71: =ROUND((0/100)*ROUND(Source!R43, 2), 2) -> 0 | AC71: 5
C72: НР от ФОТ | D72: % | E72: =Source!BZ41 -> 95 | I72: =SUM(Q68:Q71) -> 489.59 | J72: =Source!AT41 -> 95 | K72: =SUM(R68:R71) -> 26922.67
C73: СП от ФОТ | D73: % | E73: =Source!CA41 -> 53 | I73: =SUM(S68:S72) -> 273.14 | J73: =Source!AU41 -> 53 | K73: =SUM(T68:T72) -> 15020.01
C74: ЗТР | D74: чел-ч | E74: =Source!AQ40 -> 33 | G74: =Source!DI40 -> *1,1 | H74: =Source!AV41 -> 1.047 | I74: =Source!U40 -> 38.0061
C75: ВСЕГО работ по позиции: | H75: =I69+I70+I72+I73+SUM(I71:I71)-SUMIF(AC71:AC71, 5, I71:I71)-SUMIF(AC71:AC71, 6, I71:I71) -> 1354.84 | J75: =K69+K70+K72+K73+SUM(K71:K71)-SUMIF(AC71:AC71, 5, K71:K71)-SUMIF(AC71:AC71, 6, K71:K71) -> 70980.76
C76: ВСЕГО оборудование по позиции: | H76: =SUMIF(AC71:AC71, 5, I71:I71)+SUMIF(AC71:AC71, 6, I71:I71) -> 11113.06 | J76: =SUMIF(AC71:AC71, 5, K71:K71)+SUMIF(AC71:AC71, 6, K71:K71) -> 85126.04
C77: ВСЕГО по позиции: | H77: =I69+I70+I72+I73+SUM(I71:I71) -> 12467.9 | J77: =K69+K70+K72+K73+SUM(K71:K71) -> 156106.8 | O77: =I69+I70+I72+I73+SUM(I71:I71) -> 12467.9 | P77: =K69+K70+K72+K73+SUM(K71:K71) -> 156106.8
A79: 5 | B79: =Source!F44 -> 4.8-333-7 | C79: Монтаж розетки штепсельной скрытого типа | D79: =Source!H44 -> 100 шт. | E79: =Source!I44 -> 0.07 | Q79: =Source!X44 -> 16.48 | R79: =Source!X45 -> 906.25 | S79: =Source!Y44 -> 8.66 | T79: =Source!Y45 -> 476.48 | U79: =ROUND((175/100)*ROUND(Source!R44, 2), 2) -> 0.02 | V79: =ROUND((0/100)*ROUND(Source!R45, 2), 2) -> 0 | AC79: 0
C80: ="Объем: "&Source!I44&"=7/"&"100" -> Объем: 0,07=7/100
C81: ЗП | F81: =Source!AO44 -> 210.57 | G81: =Source!DG44 -> *1,1 | H81: =Source!AV45 -> 1.047 | I81: =Source!S44 -> 16.98 | J81: =IF(Source!BA45<> 0, Source!BA45, 1) -> 54.99 | K81: =Source!S45 -> 933.73
C82: ЭМ | F82: =Source!AM44 -> 0.83 | G82: =Source!DE44 -> *1,1 | H82: =Source!AV45 -> 1.047 | I82: =Source!Q44 -> 0.07 | J82: =IF(Source!BB45<> 0, Source!BB45, 1) -> 16.33 | K82: =Source!Q45 -> 1.14
C83: в т.ч. ЗПМ | F83: =Source!AN44 -> 0.13 | G83: =Source!DF44 -> *1,1 | H83: =Source!AV45 -> 1.047 | I83: =Source!R44 -> 0.01 | J83: =IF(Source!BS45<> 0, Source!BS45, 1) -> 54.99 | K83: =Source!R45 -> 0.55
A84: 5,1 | B84: =Source!F46 -> 1.14-1-23 | C84: Розетка радиотрансляционная, скрытой установки, типа РПВ-2 (прим. АРС-003) | D84: =Source!H46 -> шт. | E84: =Source!I46 -> 7 | F84: =Source!AK46 -> 3.16 | H84: =Source!AW47 -> 1 | I84: =Source!O46 -> 22.12 | J84: =IF(Source!BC47<> 0, Source!BC47, 1) -> 28.28 | K84: =Source!O47 -> 625.55 | Q84: =Source!X46 -> 0 | R84: =Source!X47 -> 0 | S84: =Source!Y46 -> 0 | T84: =Source!Y47 -> 0 | U84: =ROUND((175/100)*ROUND(Source!R46, 2), 2) -> 0 | V84: =ROUND((0/100)*ROUND(Source!R47, 2), 2) -> 0 | AC84: 3
A85: 5,2 | B85: =Source!F48 -> 1.21-5-192 | C85: Коробка, типа КУВ-1М УХЛЗ, для установки выключателей, переключателей и штепсельных розеток при скрытой электропроводке | D85: =Source!H48 -> 1000 шт. | E85: =Source!I48 -> 0.007 | F85: =Source!AK48 -> 3906.65 | H85: =Source!AW49 -> 1 | I85: =Source!O48 -> 27.35 | J85: =IF(Source!BC49<> 0, Source!BC49, 1) -> 13.52 | K85: =Source!O49 -> 369.77 | Q85: =Source!X48 -> 0 | R85: =Source!X49 -> 0 | S85: =Source!Y48 -> 0 | T85: =Source!Y49 -> 0 | U85: =ROUND((175/100)*ROUND(Source!R48, 2), 2) -> 0 | V85: =ROUND((0/100)*ROUND(Source!R49, 2), 2) -> 0 | AC85: 3
C86: НР от ФОТ | D86: % | E86: =Source!BZ45 -> 97 | I86: =SUM(Q79:Q85) -> 16.48 | J86: =Source!AT45 -> 97 | K86: =SUM(R79:R85) -> 906.25
C87: СП от ФОТ | D87: % | E87: =Source!CA45 -> 51 | I87: =SUM(S79:S86) -> 8.66 | J87: =Source!AU45 -> 51 | K87: =SUM(T79:T86) -> 476.48
C88: ЗТР | D88: чел-ч | E88: =Source!AQ44 -> 18.84 | G88: =Source!DI44 -> *1,1 | H88: =Source!AV45 -> 1.047 | I88: =Source!U44 -> 1.518862
C89: ВСЕГО работ по позиции: | H89: =I81+I82+I86+I87+SUM(I84:I85)-SUMIF(AC84:AC85, 5, I84:I85)-SUMIF(AC84:AC85, 6, I84:I85) -> 91.66 | J89: =K81+K82+K86+K87+SUM(K84:K85)-SUMIF(AC84:AC85, 5, K84:K85)-SUMIF(AC84:AC85, 6, K84:K85) -> 3312.92
C90: ВСЕГО оборудование по позиции: | H90: =SUMIF(AC84:AC85, 5, I84:I85)+SUMIF(AC84:AC85, 6, I84:I85) -> 0 | J90: =SUMIF(AC84:AC85, 5, K84:K85)+SUMIF(AC84:AC85, 6, K84:K85) -> 0
C91: ВСЕГО по позиции: | H91: =I81+I82+I86+I87+SUM(I84:I85) -> 91.66 | J91: =K81+K82+K86+K87+SUM(K84:K85) -> 3312.92 | O91: =I81+I82+I86+I87+SUM(I84:I85) -> 91.66 | P91: =K81+K82+K86+K87+SUM(K84:K85) -> 3312.92
A94: =CONCATENATE("Итого по разделу: ",IF(Source!G51<>"Новый раздел", Source!G51, "")) -> Итого по разделу: Оборудование | H94: =SUM(O29:O93) -> 176161.18 | J94: =SUM(P29:P93) -> 1429159.9
A95: Итого по ТСН-2001.16 | I95: =SUM(W29:W94) -> 0 | J95: =SUM(X29:X94) -> 0
A96: Итого возвратных сумм | I96: =SUM(Y29:Y95) -> 0 | J96: =SUM(Z29:Z95) -> 0
A98: =CONCATENATE("Раздел: ",IF(Source!G81<>"Новый раздел", Source!G81, "")) -> Раздел: Кабельные изделия
A99: 6 | B99: =Source!F85 -> 4.8-288-2 | C99: Трубы гофрированные поливинилхлоридные наружным диаметром 20 мм открыто по стенам и потолкам с установкой соединительных коробок | D99: =Source!H85 -> 100 м | E99: =Source!I85 -> 2 | Q99: =Source!X85 -> 442.32 | R99: =Source!X86 -> 24323.18 | S99: =Source!Y85 -> 232.56 | T99: =Source!Y86 -> 12788.47 | U99: =ROUND((175/100)*ROUND(Source!R85, 2), 2) -> 23.01 | V99: =ROUND((0/100)*ROUND(Source!R86, 2), 2) -> 0 | AC99: 0
C100: ="Объем: "&Source!I85&"=200/"&"100" -> Объем: 2=200/100
C101: ЗП | F101: =Source!AO85 -> 192.26 | G101: =Source!DG85 -> *1,1 | H101: =Source!AV86 -> 1.047 | I101: =Source!S85 -> 442.85 | J101: =IF(Source!BA86<> 0, Source!BA86, 1) -> 54.99 | K101: =Source!S86 -> 24352.32
C102: ЭМ | F102: =Source!AM85 -> 32.87 | G102: =Source!DE85 -> *1,1 | H102: =Source!AV86 -> 1.047 | I102: =Source!Q85 -> 75.71 | J102: =IF(Source!BB86<> 0, Source!BB86, 1) -> 17.85 | K102: =Source!Q86 -> 1351.42
C103: в т.ч. ЗПМ | F103: =Source!AN85 -> 5.71 | G103: =Source!DF85 -> *1,1 | H103: =Source!AV86 -> 1.047 | I103: =Source!R85 -> 13.15 | J103: =IF(Source!BS86<> 0, Source!BS86, 1) -> 54.99 | K103: =Source!R86 -> 723.12
C104: МР | F104: =Source!AL85 -> 314.29 | G104: =Source!DD85 | H104: =Source!AW86 -> 1 | I104: =Source!P85 -> 628.58 | J104: =IF(Source!BC86<> 0, Source!BC86, 1) -> 9.89 | K104: =Source!P86 -> 6216.66
A105: 6,1 | B105: =Source!F87 -> 1.12-5-372 | C105: Трубы электротехнические, гофрированные, из ПВХ, негорючие, с зондом, наружный диаметр 20 мм | D105: =Source!H87 -> м | E105: =Source!I87 -> 204 | F105: =Source!AK87 -> 3.45 | H105: =Source!AW88 -> 1 | I105: =Source!O87 -> 703.8 | J105: =IF(Source!BC88<> 0, Source!BC88, 1) -> 3.93 | K105: =Source!O88 -> 2765.93 | Q105: =Source!X87 -> 0 | R105: =Source!X88 -> 0 | S105: =Source!Y87 -> 0 | T105: =Source!Y88 -> 0 | U105: =ROUND((175/100)*ROUND(Source!R87, 2), 2) -> 0 | V105: =ROUND((0/100)*ROUND(Source!R88, 2), 2) -> 0 | AC105: 3
C106: НР от ФОТ | D106: % | E106: =Source!BZ86 -> 97 | I106: =SUM(Q99:Q105) -> 442.32 | J106: =Source!AT86 -> 97 | K106: =SUM(R99:R105) -> 24323.18
C107: СП от ФОТ | D107: % | E107: =Source!CA86 -> 51 | I107: =SUM(S99:S106) -> 232.56 | J107: =Source!AU86 -> 51 | K107: =SUM(T99:T106) -> 12788.47
C108: ЗТР | D108: чел-ч | E108: =Source!AQ85 -> 15 | G108: =Source!DI85 -> *1,1 | H108: =Source!AV86 -> 1.047 | I108: =Source!U85 -> 34.551
C109: ВСЕГО работ по позиции: | H109: =I101+I102+I104+I106+I107+SUM(I105:I105)-SUMIF(AC105:AC105, 5, I105:I105)-SUMIF(AC105:AC105, 6, I105:I105) -> 2525.82 | J109: =K101+K102+K104+K106+K107+SUM(K105:K105)-SUMIF(AC105:AC105, 5, K105:K105)-SUMIF(AC105:AC105, 6, K105:K105) -> 71797.98
C110: ВСЕГО оборудование по позиции: | H110: =SUMIF(AC105:AC105, 5, I105:I105)+SUMIF(AC105:AC105, 6, I105:I105) -> 0 | J110: =SUMIF(AC105:AC105, 5, K105:K105)+SUMIF(AC105:AC105, 6, K105:K105) -> 0
C111: ВСЕГО по позиции: | H111: =I101+I102+I104+I106+I107+SUM(I105:I105) -> 2525.82 | J111: =K101+K102+K104+K106+K107+SUM(K105:K105) -> 71797.98 | O111: =I101+I102+I104+I106+I107+SUM(I105:I105) -> 2525.82 | P111: =K101+K102+K104+K106+K107+SUM(K105:K105) -> 71797.98
A113: 7 | B113: =Source!F91 -> 4.8-174-1 | C113: Прокладка металлического рукава, наружный диаметр до 48 мм | D113: =Source!H91 -> 100 м | E113: =Source!I91 -> 0.3 | Q113: =Source!X91 -> 124.31 | R113: =Source!X92 -> 6835.56 | S113: =Source!Y91 -> 65.36 | T113: =Source!Y92 -> 3593.95 | U113: =ROUND((175/100)*ROUND(Source!R91, 2), 2) -> 1.52 | V113: =ROUND((0/100)*ROUND(Source!R92, 2), 2) -> 0 | AC113: 0
C114: ="Объем: "&Source!I91&"=30/"&"100" -> Объем: 0,3=30/100
...

Sheet Ведомость объемов работ
A1: =Source!B1 -> Smeta.RU (495) 974-1589
B4: =CONCATENATE("Ведомость объемов работ ", IF(Source!AN15<>"", Source!AN15," ")) -> Ведомость объемов работ
B5: =CONCATENATE(Source!F12, " ", Source!G12) -> 02-01-10 РТС
A8: № п/п | B8: № в ЛСР | C8: Наименование работ и затрат | D8: Единица измерения | E8: Количество | F8: Ссылка на чертежи, спецификации | G8: Формула расчета, расчет объемов работ и расхода материалов | H8: Примечание
A9: 1 | B9: 2 | C9: 3 | D9: 4 | E9: 5 | F9: 6 | G9: 7 | H9: 8
A10: =CONCATENATE("Локальная смета: ", Source!G20) -> Локальная смета: Радиотрансляционная сеть
A11: =CONCATENATE("Раздел: ", Source!G24) -> Раздел: Оборудование
A12: 1 | B12: =Source!E28 -> 1 | C12: =Source!G28 -> Монтаж щитов и пультов массой до 50кг | D12: 1 ШТ. | E12: =Source!I28 -> 1 | F12: =Source!U24 | G12: =Source!I28 -> 1
A13: 2 | B13: =Source!E32 -> 2 | C13: =Source!G32 -> Установка съемных и выдвижных блоков (модулей, ячеек, ТЭЗ) массой до 5 кг | D13: 1 ШТ. | E13: =Source!I32 -> 1 | F13: =Source!U24 | G13: =Source!I32 -> 1
A14: 3 | B14: =Source!E36 -> 3 | C14: =Source!G36 -> Монтаж щитов и пультов массой до 50кг | D14: 1 ШТ. | E14: =Source!I36 -> 1 | F14: =Source!U24 | G14: =Source!I36 -> 1
A15: 4 | B15: =Source!E40 -> 4 | C15: =Source!G40 -> Монтаж щита распределительного настенного типа | D15: 1 ШТ. | E15: =Source!I40 -> 1 | F15: =Source!U24 | G15: =Source!I40 -> 1
A16: 5 | B16: =Source!E44 -> 5 | C16: =Source!G44 -> Монтаж розетки штепсельной скрытого типа | D16: 100 шт. | E16: =Source!I44 -> 0.07 | F16: =Source!U24 | G16: ="=7/"&"100" -> =7/100
A17: =CONCATENATE("Раздел: ", Source!G81) -> Раздел: Кабельные изделия
A18: 6 | B18: =Source!E85 -> 6 | C18: =Source!G85 -> Трубы гофрированные поливинилхлоридные наружным диаметром 20 мм открыто по стенам и потолкам с установкой соединительных коробок | D18: 100 м | E18: =Source!I85 -> 2 | F18: =Source!U81 | G18: ="=200/"&"100" -> =200/100
A19: 7 | B19: =Source!E91 -> 7 | C19: =Source!G91 -> Прокладка металлического рукава, наружный диаметр до 48 мм | D19: 100 м | E19: =Source!I91 -> 0.3 | F19: =Source!U81 | G19: ="=30/"&"100" -> =30/100
A20: 8 | B20: =Source!E95 -> 8 | C20: =Source!G95 -> Затягивание провода в проложенные трубы и металлические рукава, первого одножильного или многожильного в общей оплетке, суммарное сечение до 6 мм2 | D20: 100 м | E20: =Source!I95 -> 2.3 | F20: =Source!U81 | G20: ="=(200+"&"30)/"&"100" -> =(200+30)/100
A21: 9 | B21: =Source!E97 -> 9 | C21: =Source!G97 -> Добавлять на затягивание провода в проложенные трубы и металлические рукава каждого последующего одножильного или многожильного в общей оплетке, суммарное сечение до 6 мм2 (к нормам и расценкам 4.8-175-1 и 4.8-175-2) | D21: 100 м | E21: =Source!I97 -> 4.2 | F21: =Source!U81 | G21: ="=(150+"&"350+"&"10+"&"40+"&"20+"&"50+"&"20+"&"10-"&"230)/"&"100" -> =(150+350+10+40+20+50+20+10-230)/100
A22: 10 | B22: =Source!E99 -> 10 | C22: =Source!G99 -> Кабель распределительный КПСВВнг(А)-LSLTx 1x2x1,5 | D22: км | E22: =Source!I99 -> 0.153 | F22: =Source!U81 | G22: ="=(150*"&"1,02)/"&"1000" -> =(150*1,02)/1000
A23: 11 | B23: =Source!E101 -> 11 | C23: =Source!G101 -> Кабель абонентский КПСВВнг(А)-LSLTx 1x2x0,5 | D23: км | E23: =Source!I101 -> 0.357 | F23: =Source!U81 | G23: ="=(350*"&"1,02)/"&"1000" -> =(350*1,02)/1000
A24: 12 | B24: =Source!E103 -> 12 | C24: =Source!G103 -> Кабель витая пара FTP кат. 5е ЛОУТОКС КВПЭфнг(С)-LSLTx-5е 4x2x0,52 | D24: км | E24: =Source!I103 -> 0.0102 | F24: =Source!U81 | G24: ="=(10*"&"1,02)/"&"1000" -> =(10*1,02)/1000
A25: 13 | B25: =Source!E105 -> 13 | C25: =Source!G105 -> Кабель коаксиальный Паракс RG-6 РК 75-4,8-318нг(А)-LSLTx | D25: км | E25: =Source!I105 -> 0.0408 | F25: =Source!U81 | G25: ="=(40*"&"1,02)/"&"1000" -> =(40*1,02)/1000
A26: 14 | B26: =Source!E107 -> 14 | C26: =Source!G107 -> Кабель сопряжения с СОУЭ КПСВэВнг(А)-LSLTx 2x2x0,5 | D26: км | E26: =Source!I107 -> 0.0204 | F26: =Source!U81 | G26: ="=(20*"&"1,02)/"&"1000" -> =(20*1,02)/1000
A27: 15 | B27: =Source!E109 -> 15 | C27: =Source!G109 -> Кабель коаксиальный РК50-7-37нг(А)-HF | D27: км | E27: =Source!I109 -> 0.051 | F27: =Source!U81 | G27: ="=(50*"&"1,02)/"&"1000" -> =(50*1,02)/1000
A28: 16 | B28: =Source!E111 -> 16 | C28: =Source!G111 -> Кабель коммутации передачи сигнала 20нг(А)-FRLSLTx 2x2x0,75 | D28: км | E28: =Source!I111 -> 0.0204 | F28: =Source!U81 | G28: ="=(20*"&"1,02)/"&"1000" -> =(20*1,02)/1000
A29: 17 | B29: =Source!E113 -> 17 | C29: =Source!G113 -> Кабель сопряжения оборудования СОЧС с ОСО КПСВЭВнг(А)-LSLTx 2x2x0,75 | D29: км | E29: =Source!I113 -> 0.102 | F29: =Source!U81 | G29: ="=(100*"&"1,02)/"&"1000" -> =(100*1,02)/1000
A30: =CONCATENATE("Раздел: ", Source!G146) -> Раздел: Материалы
A31: 18 | B31: =Source!E150 -> 18 | C31: =Source!G150 -> Установка для трубных проводок коробки оконечной | D31: 100 шт. | E31: =Source!I150 -> 0.02 | F31: =Source!U146 | G31: ="=2/"&"100" -> =2/100
A32: 19 | B32: =Source!E154 -> 19 | C32: =Source!G154 -> Установка для трубных проводок коробки оконечной | D32: 100 шт. | E32: =Source!I154 -> 0.02 | F32: =Source!U146 | G32: ="=2/"&"100" -> =2/100
A33: 20 | B33: =Source!E158 -> 20 | C33: =Source!G158 -> Антенные устройства, монтаж антенны дополнительной для приема ТВ на ранее установленной опоре, с действующими ТВ антеннами | D33: 1 антенна | E33: =Source!I158 -> 1 | F33: =Source!U146 | G33: =Source!I158 -> 1
A34: 21 | B34: =Source!E162 -> 21 | C34: =Source!G162 -> Антенные устройства, монтаж антенны коллективной для приема ТВ на антенной опоре высотой до 6 м без оттяжек на кровле с ранее оборудованными трубостойками | D34: 1 антенна | E34: =Source!I162 -> 1 | F34: =Source!U146 | G34: =Source!I162 -> 1
A35: 22 | B35: =Source!E166 -> 22 | C35: =Source!G166 -> Антенные устройства, монтаж металлоконструкций для телевизионных антенн (Масса антенны в сборе - 5,1 кг) | D35: 1 Т | E35: =Source!I166 -> 0.0051 | F35: =Source!U146 | G35: ="=5,1/"&"1000" -> =5,1/1000
A36: 23 | B36: =Source!E168 -> 23 | C36: =Source!G168 -> Мачта для телевизионной антенны, высота не более 6 м, без защелок-натяжителей и проволоки для оттяжек | D36: шт. | E36: =Source!I168 -> 1 | F36: =Source!U146 | G36: =Source!I168 -> 1
A37: 24 | B37: =Source!E170 -> 24 | C37: =Source!G170 -> Опора модернизированная с грузом 8х20 кг NPMM-60 | D37: ШТ | E37: =Source!I170 -> 1 | F37: =Source!U146 | G37: =Source!I170 -> 1
A38: 25 | B38: =Source!E172 -> 25 | C38: =Source!G172 -> Комплект заземления мачты (трос стальной 8,3мм-10м; на конечник КВТ35-8-9-1шт.; сжим У859М-1шт.) | D38: ШТ | E38: =Source!I172 -> 1 | F38: =Source!U146 | G38: =Source!I172 -> 1
A39: 26 | B39: =Source!E174 -> 26 | C39: =Source!G174 -> Грозозащита для воздушных абонентских линий | D39: 1 комплект | E39: =Source!I174 -> 1 | F39: =Source!U146 | G39: =Source!I174 -> 1
A40: 27 | B40: =Source!E178 -> 27 | C40: =Source!G178 -> Разъем телевизионный F для коаксиального кабеля стандарта RG6 | D40: шт. | E40: =Source!I178 -> 10 | F40: =Source!U146 | G40: =Source!I178 -> 10
A41: 28 | B41: =Source!E180 -> 28 | C41: =Source!G180 -> Коннектор (вилка) телекоммуникационный 8P8C, RJ45, категория 5E | D41: 100 шт. | E41: =Source!I180 -> 0.04 | F41: =Source!U146 | G41: ="=4/"&"100" -> =4/100
A42: 29 | B42: =Source!E182 -> 29 | C42: =Source!G182 -> Разъем телевизионный "папа", прямой, для коаксиального кабеля стандарта RG6 | D42: шт. | E42: =Source!I182 -> 3 | F42: =Source!U146 | G42: =Source!I182 -> 3
A43: 30 | B43: =Source!E184 -> 30 | C43: =Source!G184 -> Разъем телевизионный F для коаксиального кабеля стандарта RG6 | D43: шт. | E43: =Source!I184 -> 1 | F43: =Source!U146 | G43: =Source!I184 -> 1
A44: 31 | B44: =Source!E186 -> 31 | C44: =Source!G186 -> Грозозащита для воздушных абонентских линий | D44: 1 комплект | E44: =Source!I186 -> 1 | F44: =Source!U146 | G44: =Source!I186 -> 1
C47: Главный инженер проекта _________________ | D47: =IF(Source!X12<>"", Source!X12," ")
C49: Составил _________________ | D49: =IF(Source!AB12<>"", Source!AB12," ") -> Соколова И.Н.

Sheet Source
A1: 0 | B1: Smeta.RU (495) 974-1589 | D1: _PS_ | F1: 0 | G1: 0 | H1: 0 | I1: Smeta.RU | K1: 1 | L1: 74563 | M1: 10 | N1: 12 | O1: 0 | P1: 0 | Q1: 3
A4: 1 | B4: 1 | C4: -1 | G4: Капитальный ремонт здания Государственного бюджетного общеобразовательного учреждения города Москвы "Школа №236" по адресу: г. Москва, улица Клязьминская, дом 7, корпус 4 | EC4: 0
A12: 1 | B12: 290 | C12: 0 | D12: =ROW(A251) -> 251 | E12: 0 | G12: 02-01-10 РТС | I12: 0 | J12: 2024-00272-01-0-ИОС5.3 | K12: 0 | L12: 0 | M12: 4098 | O12: 0 | P12: 0 | Q12: 0 | R12: 0 | S12: 0 | T12: 1 | V12: 0 | AB12: Соколова И.Н. | BB12: 0 | BH12: Сметные нормы списания | BI12: Коды ОКП для ТСН-2001 МГЭ Дополнение 80 | BJ12: 1 | BK12: 1 | BL12: 0 | BM12: 0 | BN12: 1 | BO12: 0 | BP12: 6 | BQ12: 2 | BR12: 1 | BS12: 1 | BT12: 0 | BU12: 0 | BV12: 0 | BW12: 0 | BX12: 0 | BZ12: Типовой расчет для ТСН-2001 МГЭ, Дополнение 80, строительство (1) | CA12: Территориальные сметные нормативы для Москвы ТСН-2001 (МГЭ), дополнение 80 | CB12: Территориальные сметные нормативы для Москвы ТСН-2001 (МГЭ), дополнение 80 | CC12: Территориальные сметные нормативы для Москвы ТСН-2001 (МГЭ), дополнение 80 | CD12: Территориальные сметные нормативы для Москвы ТСН-2001 (МГЭ), дополнение 80 | CE12: Поправки для ТСН-2001 от 28.11.2025 г. доп.79 | CF12: 0 | CG12: 0 | CH12: 8200 | CK12: 80 | CQ12: Территориальные сметные нормативы для Москвы (ТСН-2001) | CR12: ТЕР | CS12: 41660 | CT12: 1 | CU12: 80 | CY12: 0 | EC12: 0
A15: 15 | B15: 1
A18: 52 | B18: =B251 -> 290 | C18: =C251 -> 1 | D18: =D251 -> 12 | E18: =E251 -> 0 | F18: =F251 | G18: =G251 -> 02-01-10 РТС | O18: =O251 -> 192447.83 | P18: =P251 -> 190510.95 | Q18: =Q251 -> 157.38 | R18: =R251 -> 18.01 | S18: =S251 -> 1779.5 | T18: =T251 -> 0 | U18: =U251 -> 138.52903 | V18: =V251 -> 0 | ... GX18: =GX251 -> 0
A20: 3 | B20: 1 | D20: =ROW(A221) -> 221 | F20: 02-01-10 | G20: Радиотрансляционная сеть | I20: 0 | J20: 2024-00272-01-0-ИОС5.3 | K20: -1 | L20: 02-01-10 | S20: 0 | T20: 0 | V20: 2 | BX20: 0 | CF20: 0 | CG20: 0
A22: 52 | B22: =B221 -> 1 | C22: =C221 -> 3 | D22: =D221 -> 20 | E22: =E221 -> 0 | F22: =F221 -> 02-01-10 | G22: =G221 -> Радиотрансляционная сеть | O22: =O221 -> 192447.83 | P22: =P221 -> 190510.95 | Q22: =Q221 -> 157.38 | R22: =R221 -> 18.01 | S22: =S221 -> 1779.5 | T22: =T221 -> 0 | U22: =U221 -> 138.52903 | V22: =V221 -> 0 | ... GX22: =GX221 -> 0
A24: 4 | B24: 1 | D24: =ROW(A51) -> 51 | G24: Оборудование | I24: 0 | K24: -1 | S24: 0 | T24: 0 | V24: 2 | BX24: 0 | CJ24: 0
A26: 52 | B26: =B51 -> 1 | C26: =C51 -> 4 | D26: =D51 -> 24 | E26: =E51 -> 0 | F26: =F51 | G26: =G51 -> Оборудование | O26: =O51 -> 175166.44 | P26: =P51 -> 174472.47 | Q26: =Q51 -> 10.49 | R26: =R51 -> 0.98 | S26: =S51 -> 683.48 | T26: =T51 -> 0 | U26: =U51 -> 52.573723 | V26: =V51 -> 0 | ... GX26: =GX51 -> 0
A28: 17 | B28: 1 | C28: =ROW(SmtRes!A12) -> 12 | D28: =ROW(EtalonRes!A12) -> 12 | E28: 1 | F28: 4.11-17-1 | G28: Монтаж щитов и пультов массой до 50кг | H28: 1 ШТ. | I28: 1 | J28: 0 | K28: 1 | O28: =ROUND(CP28,2) -> 163.14 | P28: =ROUND((ROUND((AC28*AW28*I28),2)*BC28),2) -> 89.36 | Q28: =(ROUND((ROUND((((ET28*1.1))*AV28*I28),2)*BB28),2)+ROUND((ROUND(((AE28-((EU28*1.1)))*AV28*I28),2)*BS28),2)) -> 4.92 | R28: =(ROUND((ROUND((((EU28*1.1))*AV28*I28),2)*BS28),2)+ROUND((ROUND(((AE28-((EU28*1.1)))*AV28*I28),2)*BS28),2)) -> 0.44 | S28: =ROUND((ROUND((AF28*AV28*I28),2)*BA28),2) -> 68.86 | T28: =ROUND(CU28*I28,2) -> 0 | U28: =CV28*I28 -> 5.931255 | V28: =CW28*I28 -> 0 | W28: =ROUND(CX28*I28,2) -> 0 | X28: =(ROUND((((S28+ROUND((ROUND((((EU28*1.1))*AV28*I28),2)*BS28),2))*AT28)/100),2)+ROUND(((ROUND((ROUND(((AE28-((EU28*1.1)))*AV28*I28),2)*BS28),2)*AT28)/100),2)) -> 62.37 | Y28: =(ROUND((((S28+ROUND((ROUND((((EU28*1.1))*AV28*I28),2)*BS28),2))*AU28)/100),2)+ROUND(((ROUND((ROUND(((AE28-((EU28*1.1)))*AV28*I28),2)*BS28),2)*AU28)/100),2)) -> 31.88 | AA28: 60256985 | AB28: =ROUND((AC28+AD28+AF28),6) -> 159.826 | AC28: =ROUND((ES28),6) -> 89.36 | AD28: =ROUND(((((ET28*1.1))-((EU28*1.1)))+AE28),6) -> 4.697 | AE28: =ROUND(((EU28*1.1)),6) -> 0.418 | AF28: =ROUND(((EV28*1.1)),6) -> 65.769 | AG28: =ROUND((AP28),6) -> 0 | AH28: =((EW28*1.1)) -> 5.665 | AI28: =((EX28*1.1)) -> 0 | AJ28: =(AS28) -> 0 | AK28: 153.42 | AL28: 89.36 | AM28: 4.27 | AN28: 0.38 | AO28: 59.79 | AP28: 0 | AQ28: 5.15 | AR28: 0 | AS28: 0 | AT28: 90 | AU28: 46 | AV28: 1.047 | AW28: 1 | AZ28: 1 | BA28: 1 | BB28: 1 | BC28: 1 | BH28: 0 | BI28: 2 | BJ28: ТСН-2001.4 Доп. 80, Сб. 11, т. 17, поз. 1 | BM28: 72 | BN28: 58973116 | BO28: 4.11-17-1 | BP28: 1 | BQ28: 40 | BR28: 0 | BS28: 1 | BT28: 1 | BU28: 1 | BV28: 1 | BW28: 1 | BX28: 1 | BZ28: 90 | CA28: 46 | CE28: 1566 | CF28: 0 | CG28: 0 | CM28: 0 | CN28: Поправка: О.П. п.3.4.30.в Наименование: При применении территориальных сметных нормативов для города Москвы затраты, учитывающие напряженные и стесненные условия производства работ (стесненность, сложность складирования и транспортной логистики и т.п.), исчисляются с применением коэффициентов к затратам труда и заработной плате рабочих, машинистов, времени эксплуатации машин и механизмов, стоимости эксплуатации машин в размере: для объектов, расположенных за пределами Третьего транспортного кольца города Москвы, но в пределах Московской кольцевой автомобильной дороги | CO28: 0 | CP28: =(P28+Q28+S28) -> 163.14 | CQ28: =ROUND((ROUND((AC28*AW28*1),2)*BC28),2) -> 89.36 | CR28: =(ROUND((ROUND((((ET28*1.1))*AV28*1),2)*BB28),2)+ROUND((ROUND(((AE28-((EU28*1.1)))*AV28*1),2)*BS28),2)) -> 4.92 | CS28: =(ROUND((ROUND((((EU28*1.1))*AV28*1),2)*BS28),2)+ROUND((ROUND(((AE28-((EU28*1.1)))*AV28*1),2)*BS28),2)) -> 0.44 | CT28: =ROUND((ROUND((AF28*AV28*1),2)*BA28),2) -> 68.86 | CU28: =AG28 -> 0 | CV28: =(AH28*AV28) -> 5.931255 | CW28: =AI28 -> 0 | CX28: =AJ28 -> 0 | CY28: =(ROUND((((S28+ROUND((ROUND((((EU28*1.1))*AV28*1),2)*BS28),2))*AT28)/100),2)+ROUND(((ROUND((ROUND(((AE28-((EU28*1.1)))*AV28*1),2)*BS28),2)*AT28)/100),2)) -> 62.37 | CZ28: =(ROUND((((S28+ROUND((ROUND((((EU28*1.1))*AV28*1),2)*BS28),2))*AU28)/100),2)+ROUND(((ROUND((ROUND(((AE28-((EU28*1.1)))*AV28*1),2)*BS28),2)*AU28)/100),2)) -> 31.88 | DB28: 1 | DE28: *1,1 | DF28: *1,1 | DG28: *1,1 | DI28: *1,1 | DJ28: *1,1 | DN28: 0 | DO28: 0 | DP28: 1 | DQ28: 1 | DU28: 1013 | DV28: 1 ШТ. | DW28: 1 ШТ. | DX28: 1 | EE28: 60088536 | EF28: 40 | EG28: Монтаж оборудования | EH28: 0 | EJ28: 2 | EK28: 72 | EL28: ТСН-2001.4-11. Приборы и средства автоматизации и вычислительной техники | EM28: ТСН-2001.4-11-1 | EO28: Поправка: О.П. п.3.4.30.в | EQ28: 0 | ER28: 153.42 | ES28: 89.36 | ET28: 4.27 | EU28: 0.38 | EV28: 59.79 | EW28: 5.15 | EX28: 0 | EY28: 0 | FQ28: 0 | FR28: 0 | FS28: 0 | FX28: 90 | FY28: 46 | GD28: 1 | GF28: 1767555919 | GG28: 2 | GH28: 1 | GI28: 2 | GJ28: 0 | GK28: 0 | GL28: =ROUND(IF(AND(BH28=3,BI28=3,FS28<>0),P28,0),2) -> 0 | GM28: =ROUND(O28+X28+Y28,2)+GX28 -> 257.39 | GN28: =IF(OR(BI28=0,BI28=1),GM28-GX28,0) -> 0 | GO28: =IF(BI28=2,GM28-GX28,0) -> 257.39 | GP28: =IF(BI28=4,GM28-GX28,0) -> 0 | GR28: 0 | GS28: 3 | GT28: 0 | GV28: =ROUND((GT28),6) -> 0 | GW28: 1 | GX28: =ROUND(HC28*I28,2) -> 0 | HA28: 0 | HB28: 0 | HC28: =GV28*GW28 -> 0 | HS28: 0 | IK28: 0
A29: 17 | B29: 1 | C29: =ROW(SmtRes!A24) -> 24 | D29: =ROW(EtalonRes!A24) -> 24 | E29: 1 | F29: 4.11-17-1 | G29: Монтаж щитов и пультов массой до 50кг | H29: 1 ШТ. | I29: 1 | J29: 0 | K29: 1 | O29: =ROUND(CP29,2) -> 4309.88 | P29: =ROUND((ROUND((AC29*AW29*I29),2)*BC29),2) -> 453.95 | Q29: =(ROUND((ROUND((((ET29*1.1))*AV29*I29),2)*BB29),2)+ROUND((ROUND(((AE29-((EU29*1.1)))*AV29*I29),2)*BS29),2)) -> 69.32 | R29: =(ROUND((ROUND((((EU29*1.1))*AV29*I29),2)*BS29),2)+ROUND((ROUND(((AE29-((EU29*1.1)))*AV29*I29),2)*BS29),2)) -> 24.2 | S29: =ROUND((ROUND((AF29*AV29*I29),2)*BA29),2) -> 3786.61 | T29: =ROUND(CU29*I29,2) -> 0 | U29: =CV29*I29 -> 5.931255 | V29: =CW29*I29 -> 0 | W29: =ROUND(CX29*I29,2) -> 0 | X29: =(ROUND((((S29+ROUND((ROUND((((EU29*1.1))*AV29*I29),2)*BS29),2))*AT29)/100),2)+ROUND(((ROUND((ROUND(((AE29-((EU29*1.1)))*AV29*I29),2)*BS29),2)*AT29)/100),2)) -> 3429.73 | Y29: =(ROUND((((S29+ROUND((ROUND((((EU29*1.1))*AV29*I29),2)*BS29),2))*AU29)/100),2)+ROUND(((ROUND((ROUND(((AE29-((EU29*1.1)))*AV29*I29),2)*BS29),2)*AU29)/100),2)) -> 1752.97 | AA29: 60256982 | AB29: =ROUND((AC29+AD29+AF29),6) -> 159.826 | AC29: =ROUND((ES29),6) -> 89.36 | AD29: =ROUND(((((ET29*1.1))-((EU29*1.1)))+AE29),6) -> 4.697 | AE29: =ROUND(((EU29*1.1)),6) -> 0.418 | AF29: =ROUND(((EV29*1.1)),6) -> 65.769 | AG29: =ROUND((AP29),6) -> 0 | AH29: =((EW29*1.1)) -> 5.665 | AI29: =((EX29*1.1)) -> 0 | AJ29: =(AS29) -> 0 | AK29: 153.42 | AL29: 89.36 | AM29: 4.27 | AN29: 0.38 | AO29: 59.79 | AP29: 0 | AQ29: 5.15 | AR29: 0 | AS29: 0 | AT29: 90 | AU29: 46 | AV29: 1.047 | AW29: 1 | AZ29: 1 | BA29: 54.99 | BB29: 14.09 | BC29: 5.08 | BH29: 0 | BI29: 2 | BJ29: ТСН-2001.4 Доп. 80, Сб. 11, т. 17, поз. 1 | BM29: 72 | BN29: 58973116 | BO29: 4.11-17-1 | BP29: 1 | BQ29: 40 | BR29: 0 | BS29: 54.99 | BT29: 1 | BU29: 1 | BV29: 1 | BW29: 1 | BX29: 1 | BZ29: 90 | CA29: 46 | CE29: 1566 | CF29: 0 | CG29: 0 | CM29: 0 | CN29: Поправка: О.П. п.3.4.30.в Наименование: При применении территориальных сметных нормативов для города Москвы затраты, учитывающие напряженные и стесненные условия производства работ (стесненность, сложность складирования и транспортной логистики и т.п.), исчисляются с применением коэффициентов к затратам труда и заработной плате рабочих, машинистов, времени эксплуатации машин и механизмов, стоимости эксплуатации машин в размере: для объектов, расположенных за пределами Третьего транспортного кольца города Москвы, но в пределах Московской кольцевой автомобильной дороги | CO29: 0 | CP29: =(P29+Q29+S29) -> 4309.88 | CQ29: =ROUND((ROUND((AC29*AW29*1),2)*BC29),2) -> 453.95 | CR29: =(ROUND((ROUND((((ET29*1.1))*AV29*1),2)*BB29),2)+ROUND((ROUND(((AE29-((EU29*1.1)))*AV29*1),2)*BS29),2)) -> 69.32 | CS29: =(ROUND((ROUND((((EU29*1.1))*AV29*1),2)*BS29),2)+ROUND((ROUND(((AE29-((EU29*1.1)))*AV29*1),2)*BS29),2)) -> 24.2 | CT29: =ROUND((ROUND((AF29*AV29*1),2)*BA29),2) -> 3786.61 | CU29: =AG29 -> 0 | CV29: =(AH29*AV29) -> 5.931255 | CW29: =AI29 -> 0 | CX29: =AJ29 -> 0 | CY29: =(ROUND((((S29+ROUND((ROUND((((EU29*1.1))*AV29*1),2)*BS29),2))*AT29)/100),2)+ROUND(((ROUND((ROUND(((AE29-((EU29*1.1)))*AV29*1),2)*BS29),2)*AT29)/100),2)) -> 3429.73 | CZ29: =(ROUND((((S29+ROUND((ROUND((((EU29*1.1))*AV29*1),2)*BS29),2))*AU29)/100),2)+ROUND(((ROUND((ROUND(((AE29-((EU29*1.1)))*AV29*1),2)*BS29),2)*AU29)/100),2)) -> 1752.97 | DB29: 2 | DE29: *1,1 | DF29: *1,1 | DG29: *1,1 | DI29: *1,1 | DJ29: *1,1 | DN29: 0 | DO29: 0 | DP29: 1 | DQ29: 1 | DU29: 1013 | DV29: 1 ШТ. | DW29: 1 ШТ. | DX29: 1 | EE29: 60088536 | EF29: 40 | EG29: Монтаж оборудования | EH29: 0 | EJ29: 2 | EK29: 72 | EL29: ТСН-2001.4-11. Приборы и средства автоматизации и вычислительной техники | EM29: ТСН-2001.4-11-1 | EO29: Поправка: О.П. п.3.4.30.в | EQ29: 0 | ER29: 153.42 | ES29: 89.36 | ET29: 4.27 | EU29: 0.38 | EV29: 59.79 | EW29: 5.15 | EX29: 0 | EY29: 0 | FQ29: 0 | FR29: 0 | FS29: 0 | FX29: 90 | FY29: 46 | GD29: 1 | GF29: 1767555919 | GG29: 2 | GH29: 1 | GI29: 2 | GJ29: 0 | GK29: 0 | GL29: =ROUND(IF(AND(BH29=3,BI29=3,FS29<>0),P29,0),2) -> 0 | GM29: =ROUND(O29+X29+Y29,2)+GX29 -> 9492.58 | GN29: =IF(OR(BI29=0,BI29=1),GM29-GX29,0) -> 0 | GO29: =IF(BI29=2,GM29-GX29,0) -> 9492.58 | GP29: =IF(BI29=4,GM29-GX29,0) -> 0 | GR29: 0 | GS29: 3 | GT29: 0 | GV29: =ROUND((GT29),6) -> 0 | GW29: 1 | GX29: =ROUND(HC29*I29,2) -> 0 | HA29: 0 | HB29: 0 | HC29: =GV29*GW29 -> 0 | HS29: 0 | IK29: 0
A30: 18 | B30: 1 | C30: 12 | E30: 1,1 | F30: КА-1 | G30: Устройство подачи программ вещания УППВ 1918 М1 исп. У (исп. 2022) | H30: шт. | I30: =I28*J30 -> 1 | J30: 1 | K30: 1 | O30: =ROUND(CP30,2) -> 45303.63 | P30: =ROUND((ROUND((AC30*I30),2)*BC30),2) -> 45303.63 | Q30: =(ROUND((ROUND(((ET30)*AV30*I30),2)*BB30),2)+ROUND((ROUND(((AE30-(EU30))*AV30*I30),2)*BS30),2)) -> 0 | R30: =(ROUND((ROUND(((EU30)*AV30*I30),2)*BS30),2)+ROUND((ROUND(((AE30-(EU30))*AV30*I30),2)*BS30),2)) -> 0 | S30: =ROUND((ROUND((AF30*AV30*I30),2)*BA30),2) -> 0 | T30: =ROUND(CU30*I30,2) -> 0 | U30: =CV30*I30 -> 0 | V30: =CW30*I30 -> 0 | W30: =ROUND(CX30*I30,2) -> 0 | X30: =(ROUND((((S30+ROUND((ROUND(((EU30)*AV30*I30),2)*BS30),2))*AT30)/100),2)+ROUND(((ROUND((ROUND(((AE30-(EU30))*AV30*I30),2)*BS30),2)*AT30)/100),2)) -> 0 | Y30: =(ROUND((((S30+ROUND((ROUND(((EU30)*AV30*I30),2)*BS30),2))*AU30)/100),2)+ROUND(((ROUND((ROUND(((AE30-(EU30))*AV30*I30),2)*BS30),2)*AU30)/100),2)) -> 0 | AA30: 60256985 | AB30: =ROUND((AC30+AD30+AF30),6) -> 45303.63 | AC30: =ROUND((ES30),6) -> 45303.63 | AD30: =ROUND((((ET30)-(EU30))+AE30),6) -> 0 | AE30: =ROUND((EU30),6) -> 0 | AF30: =ROUND((EV30),6) -> 0 | AG30: =ROUND((AP30),6) -> 0 | AH30: =(EW30) -> 0 | AI30: =(EX30) -> 0 | AJ30: =(AS30) -> 0 | AK30: 45303.63 | AL30: 45303.63 | AM30: 0 | AN30: 0 | AO30: 0 | AP30: 0 | AQ30: 0 | AR30: 0 | AS30: 0 | AT30: 0 | AU30: 0 | AV30: 1 | AW30: 1 | AZ30: 1 | BA30: 1 | BB30: 1 | BC30: 1 | BH30: 3 | BI30: 3 | BM30: 746 | BN30: 0 | BP30: 0 | BQ30: 130 | BR30: 0 | BS30: 1 | BT30: 1 | BU30: 1 | BV30: 1 | BW30: 1 | BX30: 1 | BZ30: 90 | CA30: 46 | CE30: 1566 | CF30: 0 | CG30: 0 | CM30: 0 | CO30: 0 | CP30: =(P30+Q30+S30) -> 45303.63 | CQ30: =ROUND((ROUND((AC30*1),2)*BC30),2) -> 45303.63 | CR30: =(ROUND((ROUND(((ET30)*AV30*1),2)*BB30),2)+ROUND((ROUND(((AE30-(EU30))*AV30*1),2)*BS30),2)) -> 0 | CS30: =(ROUND((ROUND(((EU30)*AV30*1),2)*BS30),2)+ROUND((ROUND(((AE30-(EU30))*AV30*1),2)*BS30),2)) -> 0 | CT30: =ROUND((ROUND((AF30*AV30*1),2)*BA30),2) -> 0 | CU30: =AG30 -> 0 | CV30: =(AH30*AV30) -> 0 | CW30: =AI30 -> 0 | CX30: =AJ30 -> 0 | CY30: =(ROUND((((S30+ROUND((ROUND(((EU30)*AV30*1),2)*BS30),2))*AT30)/100),2)+ROUND(((ROUND((ROUND(((AE30-(EU30))*AV30*1),2)*BS30),2)*AT30)/100),2)) -> 0 | CZ30: =(ROUND((((S30+ROUND((ROUND(((EU30)*AV30*1),2)*BS30),2))*AU30)/100),2)+ROUND(((ROUND((ROUND(((AE30-(EU30))*AV30*1),2)*BS30),2)*AU30)/100),2)) -> 0 | DN30: 0 | DO30: 0 | DP30: 1 | DQ30: 1 | DU30: 1010 | DV30: шт. | DW30: шт. | DX30: 1 | EE30: 60088638 | EF30: 130 | EG30: Сметная стоимость оборудования | EH30: 0 | EJ30: 3 | EK30: 746 | EL30: ТСН-2001.13. Сметная стоимость оборудования | EM30: ТСН-2001.13 | EQ30: 0 | ER30: 0 | ES30: 45303.63 | ET30: 0 | EU30: 0 | EV30: 0 | EW30: 0 | EX30: 0 | FQ30: 0 | FR30: =P30 -> 45303.63 | FS30: 0 | FX30: 90 | FY30: 46 | GA30: [399 507,72 / 1,2 / 7,66] + 3% Трансп + 1,2% Заг.скл | GD30: 1 | GF30: -1306002714 | GG30: 2 | GH30: 4 | GI30: -2 | GJ30: 0 | GK30: 0 | GL30: =ROUND(IF(AND(BH30=3,BI30=3,FS30<>0),P30,0),2) -> 0 | GM30: =ROUND(O30+X30+Y30,2)+GX30 -> 45303.63 | GN30: =IF(OR(BI30=0,BI30=1),GM30-GX30,0) -> 0 | GO30: =IF(BI30=2,GM30-GX30,0) -> 0 | GP30: =IF(BI30=4,GM30-GX30,0) -> 0 | GR30: 0 | GS30: 2 | GT30: 0 | GV30: =ROUND((GT30),6) -> 0 | GW30: 1 | GX30: =ROUND(HC30*I30,2) -> 0 | HA30: 0 | HB30: 0 | HC30: =GV30*GW30 -> 0 | HE30: 3 | HF30: 1,2 | HS30: 0 | IK30: 0
A31: 18 | B31: 1 | C31: 24 | E31: 1,1 | F31: КА-1 | G31: Устройство подачи программ вещания УППВ 1918 М1 исп. У (исп. 2022) | H31: шт. | I31: =I29*J31 -> 1 | J31: 1 | K31: 1 | O31: =ROUND(CP31,2) -> 347025.81 | P31: =ROUND((ROUND((AC31*I31),2)*BC31),2) -> 347025.81 | Q31: =(ROUND((ROUND(((ET31)*AV31*I31),2)*BB31),2)+ROUND((ROUND(((AE31-(EU31))*AV31*I31),2)*BS31),2)) -> 0 | R31: =(ROUND((ROUND(((EU31)*AV31*I31),2)*BS31),2)+ROUND((ROUND(((AE31-(EU31))*AV31*I31),2)*BS31),2)) -> 0 | S31: =ROUND((ROUND((AF31*AV31*I31),2)*BA31),2) -> 0 | T31: =ROUND(CU31*I31,2) -> 0 | U31: =CV31*I31 -> 0 | V31: =CW31*I31 -> 0 | W31: =ROUND(CX31*I31,2) -> 0 | X31: =(ROUND((((S31+ROUND((ROUND(((EU31)*AV31*I31),2)*BS31),2))*AT31)/100),2)+ROUND(((ROUND((ROUND(((AE31-(EU31))*AV31*I31),2)*BS31),2)*AT31)/100),2)) -> 0 | Y31: =(ROUND((((S31+ROUND((ROUND(((EU31)*AV31*I31),2)*BS31),2))*AU31)/100),2)+ROUND(((ROUND((ROUND(((AE31-(EU31))*AV31*I31),2)*BS31),2)*AU31)/100),2)) -> 0 | AA31: 60256982 | AB31: =ROUND((AC31+AD31+AF31),6) -> 45303.63 | AC31: =ROUND((ES31),6) -> 45303.63 | AD31: =ROUND((((ET31)-(EU31))+AE31),6) -> 0 | AE31: =ROUND((EU31),6) -> 0 | AF31: =ROUND((EV31),6) -> 0 | AG31: =ROUND((AP31),6) -> 0 | AH31: =(EW31) -> 0 | AI31: =(EX31) -> 0 | AJ31: =(AS31) -> 0 | AK31: 45303.63 | AL31: 45303.63 | AM31: 0 | AN31: 0 | AO31: 0 | AP31: 0 | AQ31: 0 | AR31: 0 | AS31: 0 | AT31: 0 | AU31: 0 | AV31: 1 | AW31: 1 | AZ31: 1 | BA31: 1 | BB31: 1 | BC31: 7.66 | BH31: 3 | BI31: 3 | BM31: 746 | BN31: 0 | BP31: 0 | BQ31: 130 | BR31: 0 | BS31: 1 | BT31: 1 | BU31: 1 | BV31: 1 | BW31: 1 | BX31: 1 | BZ31: 90 | CA31: 46 | CE31: 1566 | CF31: 0 | CG31: 0 | CM31: 0 | CO31: 0 | CP31: =(P31+Q31+S31) -> 347025.81 | CQ31: =ROUND((ROUND((AC31*1),2)*BC31),2) -> 347025.81 | CR31: =(ROUND((ROUND(((ET31)*AV31*1),2)*BB31),2)+ROUND((ROUND(((AE31-(EU31))*AV31*1),2)*BS31),2)) -> 0 | CS31: =(ROUND((ROUND(((EU31)*AV31*1),2)*BS31),2)+ROUND((ROUND(((AE31-(EU31))*AV31*1),2)*BS31),2)) -> 0 | CT31: =ROUND((ROUND((AF31*AV31*1),2)*BA31),2) -> 0 | CU31: =AG31 -> 0 | CV31: =(AH31*AV31) -> 0 | CW31: =AI31 -> 0 | CX31: =AJ31 -> 0 | CY31: =(ROUND((((S31+ROUND((ROUND(((EU31)*AV31*1),2)*BS31),2))*AT31)/100),2)+ROUND(((ROUND((ROUND(((AE31-(EU31))*AV31*1),2)*BS31),2)*AT31)/100),2)) -> 0 | CZ31: =(ROUND((((S31+ROUND((ROUND(((EU31)*AV31*1),2)*BS31),2))*AU31)/100),2)+ROUND(((ROUND((ROUND(((AE31-(EU31))*AV31*1),2)*BS31),2)*AU31)/100),2)) -> 0 | DN31: 0 | DO31: 0 | DP31: 1 | DQ31: 1 | DU31: 1010 | DV31: шт. | DW31: шт. | DX31: 1 | EE31: 60088638 | EF31: 130 | EG31: Сметная стоимость оборудования | EH31: 0 | EJ31: 3 | EK31: 746 | EL31: ТСН-2001.13. Сметная стоимость оборудования | EM31: ТСН-2001.13 | EQ31: 0 | ER31: 0 | ES31: 45303.63 | ET31: 0 | EU31: 0 | EV31: 0 | EW31: 0 | EX31: 0 | EZ31: 5 | FC31: 1 | FD31: 18 | FF31: 399507.72 | FQ31: 0 | FR31: =P31 -> 347025.81 | FS31: 0 | FX31: 90 | FY31: 46 | GA31: [399 507,72 / 1,2 / 7,66] + 3% Трансп + 1,2% Заг.скл | GD31: 1 | GF31: -1306002714 | GG31: 2 | GH31: 3 | GI31: 5 | GJ31: 0 | GK31: 0 | GL31: =ROUND(IF(AND(BH31=3,BI31=3,FS31<>0),P31,0),2) -> 0 | GM31: =ROUND(O31+X31+Y31,2)+GX31 -> 347025.81 | GN31: =IF(OR(BI31=0,BI31=1),GM31-GX31,0) -> 0 | GO31: =IF(BI31=2,GM31-GX31,0) -> 0 | GP31: =IF(BI31=4,GM31-GX31,0) -> 0 | GR31: 1 | GS31: 1 | GT31: 0 | GV31: =ROUND((GT31),6) -> 0 | GW31: 1 | GX31: =ROUND(HC31*I31,2) -> 0 | HA31: 0 | HB31: 0 | HC31: =GV31*GW31 -> 0 | HE31: 3 | HF31: 1,2 | HS31: 0 | IK31: 0
A32: 17 | B32: 1 | C32: =ROW(SmtRes!A27) -> 27 | D32: =ROW(EtalonRes!A27) -> 27 | E32: 2 | F32: 4.11-12-1 | G32: Установка съемных и выдвижных блоков (модулей, ячеек, ТЭЗ) массой до 5 кг | H32: 1 ШТ. | I32: 1 | J32: 0 | K32: 1 | O32: =ROUND(CP32,2) -> 14 | P32: =ROUND((ROUND((AC32*AW32*I32),2)*BC32),2) -> 0 | Q32: =(ROUND((ROUND((((ET32*1.1))*AV32*I32),2)*BB32),2)+ROUND((ROUND(((AE32-((EU32*1.1)))*AV32*I32),2)*BS32),2)) -> 0.58 | R32: =(ROUND((ROUND((((EU32*1.1))*AV32*I32),2)*BS32),2)+ROUND((ROUND(((AE32-((EU32*1.1)))*AV32*I32),2)*BS32),2)) -> 0.09 | S32: =ROUND((ROUND((AF32*AV32*I32),2)*BA32),2) -> 13.42 | T32: =ROUND(CU32*I32,2) -> 0 | U32: =CV32*I32 -> 1.186251 | V32: =CW32*I32 -> 0 | W32: =ROUND(CX32*I32,2) -> 0 | X32: =(ROUND((((S32+ROUND((ROUND((((EU32*1.1))*AV32*I32),2)*BS32),2))*AT32)/100),2)+ROUND(((ROUND((ROUND(((AE32-((EU32*1.1)))*AV32*I32),2)*BS32),2)*AT32)/100),2)) -> 12.16 | Y32: =(ROUND((((S32+ROUND((ROUND((((EU32*1.1))*AV32*I32),2)*BS32),2))*AU32)/100),2)+ROUND(((ROUND((ROUND(((AE32-((EU32*1.1)))*AV32*I32),2)*BS32),2)*AU32)/100),2)) -> 6.21 | AA32: 60256985 | AB32: =ROUND((AC32+AD32+AF32),6) -> 13.365 | AC32: =ROUND((ES32),6) -> 0 | AD32: =ROUND(((((ET32*1.1))-((EU32*1.1)))+AE32),6) -> 0.55 | AE32: =ROUND(((EU32*1.1)),6) -> 0.088 | AF32: =ROUND(((EV32*1.1)),6) -> 12.815 | AG32: =ROUND((AP32),6) -> 0 | AH32: =((EW32*1.1)) -> 1.133 | AI32: =((EX32*1.1)) -> 0 | AJ32: =(AS32) -> 0 | AK32: 12.15 | AL32: 0 | AM32: 0.5 | AN32: 0.08 | AO32: 11.65 | AP32: 0 | AQ32: 1.03 | AR32: 0 | AS32: 0 | AT32: 90 | AU32: 46 | AV32: 1.047 | AW32: 1 | AZ32: 1 | BA32: 1 | BB32: 1 | BC32: 1 | BH32: 0 | BI32: 2 | BJ32: ТСН-2001.4 Доп. 68, Сб. 11, т. 12, поз. 1 | BM32: 72 | BN32: 58973116 | BO32: 4.11-12-1 | BP32: 1 | BQ32: 40 | BR32: 0 | BS32: 1 | BT32: 1 | BU32: 1 | BV32: 1 | BW32: 1 | BX32: 1 | BZ32: 90 | CA32: 46 | CE32: 1566 | CF32: 0 | CG32: 0 | CM32: 0 | CN32: Поправка: О.П. п.3.4.30.в Наименование: При применении территориальных сметных нормативов для города Москвы затраты, учитывающие напряженные и стесненные условия производства работ (стесненность, сложность складирования и транспортной логистики и т.п.), исчисляются с применением коэффициентов к затратам труда и заработной плате рабочих, машинистов, времени эксплуатации машин и механизмов, стоимости эксплуатации машин в размере: для объектов, расположенных за пределами Третьего транспортного кольца города Москвы, но в пределах Московской кольцевой автомобильной дороги | CO32: 0 | CP32: =(P32+Q32+S32) -> 14 | CQ32: =ROUND((ROUND((AC32*AW32*1),2)*BC32),2) -> 0 | CR32: =(ROUND((ROUND((((ET32*1.1))*AV32*1),2)*BB32),2)+ROUND((ROUND(((AE32-((EU32*1.1)))*AV32*1),2)*BS32),2)) -> 0.58 | CS32: =(ROUND((ROUND((((EU32*1.1))*AV32*1),2)*BS32),2)+ROUND((ROUND(((AE32-((EU32*1.1)))*AV32*1),2)*BS32),2)) -> 0.09 | CT32: =ROUND((ROUND((AF32*AV32*1),2)*BA32),2) -> 13.42 | CU32: =AG32 -> 0 | CV32: =(AH32*AV32) -> 1.186251 | CW32: =AI32 -> 0 | CX32: =AJ32 -> 0 | CY32: =(ROUND((((S32+ROUND((ROUND((((EU32*1.1))*AV32*1),2)*BS32),2))*AT32)/100),2)+ROUND(((ROUND((ROUND(((AE32-((EU32*1.1)))*AV32*1),2)*BS32),2)*AT32)/100),2)) -> 12.16 | CZ32: =(ROUND((((S32+ROUND((ROUND((((EU32*1.1))*AV32*1),2)*BS32),2))*AU32)/100),2)+ROUND(((ROUND((ROUND(((AE32-((EU32*1.1)))*AV32*1),2)*BS32),2)*AU32)/100),2)) -> 6.21 | DB32: 3 | DE32: *1,1 | DF32: *1,1 | DG32: *1,1 | DI32: *1,1 | DJ32: *1,1 | DN32: 0 | DO32: 0 | DP32: 1 | DQ32: 1 | DU32: 1013 | DV32: 1 ШТ. | DW32: 1 ШТ. | DX32: 1 | EE32: 60088536 | EF32: 40 | EG32: Монтаж оборудования | EH32: 0 | EJ32: 2 | EK32: 72 | EL32: ТСН-2001.4-11. Приборы и средства автоматизации и вычислительной техники | EM32: ТСН-2001.4-11-1 | EO32: Поправка: О.П. п.3.4.30.в | EQ32: 0 | ER32: 12.15 | ES32: 0 | ET32: 0.5 | EU32: 0.08 | EV32: 11.65 | EW32: 1.03 | EX32: 0 | EY32: 0 | FQ32: 0 | FR32: 0 | FS32: 0 | FX32: 90 | FY32: 46 | GD32: 1 | GF32: 1708693888 | GG32: 2 | GH32: 1 | GI32: 2 | GJ32: 0 | GK32: 0 | GL32: =ROUND(IF(AND(BH32=3,BI32=3,FS32<>0),P32,0),2) -> 0 | GM32: =ROUND(O32+X32+Y32,2)+GX32 -> 32.37 | GN32: =IF(OR(BI32=0,BI32=1),GM32-GX32,0) -> 0 | GO32: =IF(BI32=2,GM32-GX32,0) -> 32.37 | GP32: =IF(BI32=4,GM32-GX32,0) -> 0 | GR32: 0 | GS32: 3 | GT32: 0 | GV32: =ROUND((GT32),6) -> 0 | GW32: 1 | GX32: =ROUND(HC32*I32,2) -> 0 | HA32: 0 | HB32: 0 | HC32: =GV32*GW32 -> 0 | HS32: 0 | IK32: 0
A33: 17 | B33: 1 | C33: =ROW(SmtRes!A30) -> 30 | D33: =ROW(EtalonRes!A30) -> 30 | E33: 2 | F33: 4.11-12-1 | G33: Установка съемных и выдвижных блоков (модулей, ячеек, ТЭЗ) массой до 5 кг | H33: 1 ШТ. | I33: 1 | J33: 0 | K33: 1 | O33: =ROUND(CP33,2) -> 747.4 | P33: =ROUND((ROUND((AC33*AW33*I33),2)*BC33),2) -> 0 | Q33: =(ROUND((ROUND((((ET33*1.1))*AV33*I33),2)*BB33),2)+ROUND((ROUND(((AE33-((EU33*1.1)))*AV33*I33),2)*BS33),2)) -> 9.43 | R33: =(ROUND((ROUND((((EU33*1.1))*AV33*I33),2)*BS33),2)+ROUND((ROUND(((AE33-((EU33*1.1)))*AV33*I33),2)*BS33),2)) -> 4.95 | S33: =ROUND((ROUND((AF33*AV33*I33),2)*BA33),2) -> 737.97 | T33: =ROUND(CU33*I33,2) -> 0 | U33: =CV33*I33 -> 1.186251 | V33: =CW33*I33 -> 0 | W33: =ROUND(CX33*I33,2) -> 0 | X33: =(ROUND((((S33+ROUND((ROUND((((EU33*1.1))*AV33*I33),2)*BS33),2))*AT33)/100),2)+ROUND(((ROUND((ROUND(((AE33-((EU33*1.1)))*AV33*I33),2)*BS33),2)*AT33)/100),2)) -> 668.63 | Y33: =(ROUND((((S33+ROUND((ROUND((((EU33*1.1))*AV33*I33),2)*BS33),2))*AU33)/100),2)+ROUND(((ROUND((ROUND(((AE33-((EU33*1.1)))*AV33*I33),2)*BS33),2)*AU33)/100),2)) -> 341.74 | AA33: 60256982 | AB33: =ROUND((AC33+AD33+AF33),6) -> 13.365 | AC33: =ROUND((ES33),6) -> 0 | AD33: =ROUND(((((ET33*1.1))-((EU33*1.1)))+AE33),6) -> 0.55 | AE33: =ROUND(((EU33*1.1)),6) -> 0.088 | AF33: =ROUND(((EV33*1.1)),6) -> 12.815 | AG33: =ROUND((AP33),6) -> 0 | AH33: =((EW33*1.1)) -> 1.133 | AI33: =((EX33*1.1)) -> 0 | AJ33: =(AS33) -> 0 | AK33: 12.15 | AL33: 0 | AM33: 0.5 | AN33: 0.08 | AO33: 11.65 | AP33: 0 | AQ33: 1.03 | AR33: 0 | AS33: 0 | AT33: 90 | AU33: 46 | AV33: 1.047 | AW33: 1 | AZ33: 1 | BA33: 54.99 | BB33: 16.26 | BC33: 1 | BH33: 0 | BI33: 2 | BJ33: ТСН-2001.4 Доп. 68, Сб. 11, т. 12, поз. 1 | BM33: 72 | BN33: 58973116 | BO33: 4.11-12-1 | BP33: 1 | BQ33: 40 | BR33: 0 | BS33: 54.99 | BT33: 1 | BU33: 1 | BV33: 1 | BW33: 1 | BX33: 1 | BZ33: 90 | CA33: 46 | CE33: 1566 | CF33: 0 | CG33: 0 | CM33: 0 | CN33: Поправка: О.П. п.3.4.30.в Наименование: При применении территориальных сметных нормативов для города Москвы затраты, учитывающие напряженные и стесненные условия производства работ (стесненность, сложность складирования и транспортной логистики и т.п.), исчисляются с применением коэффициентов к затратам труда и заработной плате рабочих, машинистов, времени эксплуатации машин и механизмов, стоимости эксплуатации машин в размере: для объектов, расположенных за пределами Третьего транспортного кольца города Москвы, но в пределах Московской кольцевой автомобильной дороги | CO33: 0 | CP33: =(P33+Q33+S33) -> 747.4 | CQ33: =ROUND((ROUND((AC33*AW33*1),2)*BC33),2) -> 0 | CR33: =(ROUND((ROUND((((ET33*1.1))*AV33*1),2)*BB33),2)+ROUND((ROUND(((AE33-((EU33*1.1)))*AV33*1),2)*BS33),2)) -> 9.43 | CS33: =(ROUND((ROUND((((EU33*1.1))*AV33*1),2)*BS33),2)+ROUND((ROUND(((AE33-((EU33*1.1)))*AV33*1),2)*BS33),2)) -> 4.95 | CT33: =ROUND((ROUND((AF33*AV33*1),2)*BA33),2) -> 737.97 | CU33: =AG33 -> 0 | CV33: =(AH33*AV33) -> 1.186251 | CW33: =AI33 -> 0 | CX33: =AJ33 -> 0 | CY33: =(ROUND((((S33+ROUND((ROUND((((EU33*1.1))*AV33*1),2)*BS33),2))*AT33)/100),2)+ROUND(((ROUND((ROUND(((AE33-((EU33*1.1)))*AV33*1),2)*BS33),2)*AT33)/100),2)) -> 668.63 | CZ33: =(ROUND((((S33+ROUND((ROUND((((EU33*1.1))*AV33*1),2)*BS33),2))*AU33)/100),2)+ROUND(((ROUND((ROUND(((AE33-((EU33*1.1)))*AV33*1),2)*BS33),2)*AU33)/100),2)) -> 341.74 | DB33: 4 | DE33: *1,1 | DF33: *1,1 | DG33: *1,1 | DI33: *1,1 | DJ33: *1,1 | DN33: 0 | DO33: 0 | DP33: 1 | DQ33: 1 | DU33: 1013 | DV33: 1 ШТ. | DW33: 1 ШТ. | DX33: 1 | EE33: 60088536 | EF33: 40 | EG33: Монтаж оборудования | EH33: 0 | EJ33: 2 | EK33: 72 | EL33: ТСН-2001.4-11. Приборы и средства автоматизации и вычислительной техники | EM33: ТСН-2001.4-11-1 | EO33: Поправка: О.П. п.3.4.30.в | EQ33: 0 | ER33: 12.15 | ES33: 0 | ET33: 0.5 | EU33: 0.08 | EV33: 11.65 | EW33: 1.03 | EX33: 0 | EY33: 0 | FQ33: 0 | FR33: 0 | FS33: 0 | FX33: 90 | FY33: 46 | GD33: 1 | GF33: 1708693888 | GG33: 2 | GH33: 1 | GI33: 2 | GJ33: 0 | GK33: 0 | GL33: =ROUND(IF(AND(BH33=3,BI33=3,FS33<>0),P33,0),2) -> 0 | GM33: =ROUND(O33+X33+Y33,2)+GX33 -> 1757.77 | GN33: =IF(OR(BI33=0,BI33=1),GM33-GX33,0) -> 0 | GO33: =IF(BI33=2,GM33-GX33,0) -> 1757.77 | GP33: =IF(BI33=4,GM33-GX33,0) -> 0 | GR33: 0 | GS33: 3 | GT33: 0 | GV33: =ROUND((GT33),6) -> 0 | GW33: 1 | GX33: =ROUND(HC33*I33,2) -> 0 | HA33: 0 | HB33: 0 | HC33: =GV33*GW33 -> 0 | HS33: 0 | IK33: 0
A34: 18 | B34: 1 | C34: 27 | E34: 2,1 | F34: КА-2 | G34: Модуль для приема интернет вещания радиостанции «Радио Москвы» | H34: шт. | I34: =I32*J34 -> 1 | J34: 1 | K34: 1 | O34: =ROUND(CP34,2) -> 3841.94 | P34: =ROUND((ROUND((AC34*I34),2)*BC34),2) -> 3841.94 | Q34: =(ROUND((ROUND(((ET34)*AV34*I34),2)*BB34),2)+ROUND((ROUND(((AE34-(EU34))*AV34*I34),2)*BS34),2)) -> 0 | R34: =(ROUND((ROUND(((EU34)*AV34*I34),2)*BS34),2)+ROUND((ROUND(((AE34-(EU34))*AV34*I34),2)*BS34),2)) -> 0 | S34: =ROUND((ROUND((AF34*AV34*I34),2)*BA34),2) -> 0 | T34: =ROUND(CU34*I34,2) -> 0 | U34: =CV34*I34 -> 0 | V34: =CW34*I34 -> 0 | W34: =ROUND(CX34*I34,2) -> 0 | X34: =(ROUND((((S34+ROUND((ROUND(((EU34)*AV34*I34),2)*BS34),2))*AT34)/100),2)+ROUND(((ROUND((ROUND(((AE34-(EU34))*AV34*I34),2)*BS34),2)*AT34)/100),2)) -> 0 | Y34: =(ROUND((((S34+ROUND((ROUND(((EU34)*AV34*I34),2)*BS34),2))*AU34)/100),2)+ROUND(((ROUND((ROUND(((AE34-(EU34))*AV34*I34),2)*BS34),2)*AU34)/100),2)) -> 0 | AA34: 60256985 | AB34: =ROUND((AC34+AD34+AF34),6) -> 3841.94 | AC34: =ROUND((ES34),6) -> 3841.94 | AD34: =ROUND((((ET34)-(EU34))+AE34),6) -> 0 | AE34: =ROUND((EU34),6) -> 0 | AF34: =ROUND((EV34),6) -> 0 | AG34: =ROUND((AP34),6) -> 0 | AH34: =(EW34) -> 0 | AI34: =(EX34) -> 0 | AJ34: =(AS34) -> 0 | AK34: 3841.94 | AL34: 3841.94 | AM34: 0 | AN34: 0 | AO34: 0 | AP34: 0 | AQ34: 0 | AR34: 0 | AS34: 0 | AT34: 0 | AU34: 0 | AV34: 1 | AW34: 1 | AZ34: 1 | BA34: 1 | BB34: 1 | BC34: 1 | BH34: 3 | BI34: 3 | BM34: 746 | BN34: 0 | BP34: 0 | BQ34: 130 | BR34: 0 | BS34: 1 | BT34: 1 | BU34: 1 | BV34: 1 | BW34: 1 | BX34: 1 | BZ34: 90 | CA34: 46 | CE34: 1566 | CF34: 0 | CG34: 0 | CM34: 0 | CO34: 0 | CP34: =(P34+Q34+S34) -> 3841.94 | CQ34: =ROUND((ROUND((AC34*1),2)*BC34),2) -> 3841.94 | CR34: =(ROUND((ROUND(((ET34)*AV34*1),2)*BB34),2)+ROUND((ROUND(((AE34-(EU34))*AV34*1),2)*BS34),2)) -> 0 | CS34: =(ROUND((ROUND(((EU34)*AV34*1),2)*BS34),2)+ROUND((ROUND(((AE34-(EU34))*AV34*1),2)*BS34),2)) -> 0 | CT34: =ROUND((ROUND((AF34*AV34*1),2)*BA34),2) -> 0 | CU34: =AG34 -> 0 | CV34: =(AH34*AV34) -> 0 | CW34: =AI34 -> 0 | CX34: =AJ34 -> 0 | CY34: =(ROUND((((S34+ROUND((ROUND(((EU34)*AV34*1),2)*BS34),2))*AT34)/100),2)+ROUND(((ROUND((ROUND(((AE34-(EU34))*AV34*1),2)*BS34),2)*AT34)/100),2)) -> 0 | CZ34: =(ROUND((((S34+ROUND((ROUND(((EU34)*AV34*1),2)*BS34),2))*AU34)/100),2)+ROUND(((ROUND((ROUND(((AE34-(EU34))*AV34*1),2)*BS34),2)*AU34)/100),2)) -> 0 | DN34: 0 | DO34: 0 | DP34: 1 | DQ34: 1 | DU34: 1010 | DV34: шт. | DW34: шт. | DX34: 1 | EE34: 60088638 | EF34: 130 | EG34: Сметная стоимость оборудования | EH34: 0 | EJ34: 3 | EK34: 746 | EL34: ТСН-2001.13. Сметная стоимость оборудования | EM34: ТСН-2001.13 | EQ34: 0 | ER34: 0 | ES34: 3841.94 | ET34: 0 | EU34: 0 | EV34: 0 | EW34: 0 | EX34: 0 | FQ34: 0 | FR34: =P34 -> 3841.94 | FS34: 0 | FX34: 90 | FY34: 46 | GA34: [33 880 / 1,2 / 7,66] + 3% Трансп + 1,2% Заг.скл | GD34: 1 | GF34: -1229013042 | GG34: 2 | GH34: 4 | GI34: -2 | GJ34: 0 | GK34: 0 | GL34: =ROUND(IF(AND(BH34=3,BI34=3,FS34<>0),P34,0),2) -> 0 | GM34: =ROUND(O34+X34+Y34,2)+GX34 -> 3841.94 | GN34: =IF(OR(BI34=0,BI34=1),GM34-GX34,0) -> 0 | GO34: =IF(BI34=2,GM34-GX34,0) -> 0 | GP34: =IF(BI34=4,GM34-GX34,0) -> 0 | GR34: 0 | GS34: 2 | GT34: 0 | GV34: =ROUND((GT34),6) -> 0 | GW34: 1 | GX34: =ROUND(HC34*I34,2) -> 0 | HA34: 0 | HB34: 0 | HC34: =GV34*GW34 -> 0 | HE34: 3 | HF34: 1,2 | HS34: 0 | IK34: 0
A35: 18 | B35: 1 | C35: 30 | E35: 2,1 | F35: КА-2 | G35: Модуль для приема интернет вещания радиостанции «Радио Москвы» | H35: шт. | I35: =I33*J35 -> 1 | J35: 1 | K35: 1 | O35: =ROUND(CP35,2) -> 29429.26 | P35: =ROUND((ROUND((AC35*I35),2)*BC35),2) -> 29429.26 | Q35: =(ROUND((ROUND(((ET35)*AV35*I35),2)*BB35),2)+ROUND((ROUND(((AE35-(EU35))*AV35*I35),2)*BS35),2)) -> 0 | R35: =(ROUND((ROUND(((EU35)*AV35*I35),2)*BS35),2)+ROUND((ROUND(((AE35-(EU35))*AV35*I35),2)*BS35),2)) -> 0 | S35: =ROUND((ROUND((AF35*AV35*I35),2)*BA35),2) -> 0 | T35: =ROUND(CU35*I35,2) -> 0 | U35: =CV35*I35 -> 0 | V35: =CW35*I35 -> 0 | W35: =ROUND(CX35*I35,2) -> 0 | X35: =(ROUND((((S35+ROUND((ROUND(((EU35)*AV35*I35),2)*BS35),2))*AT35)/100),2)+ROUND(((ROUND((ROUND(((AE35-(EU35))*AV35*I35),2)*BS35),2)*AT35)/100),2)) -> 0 | Y35: =(ROUND((((S35+ROUND((ROUND(((EU35)*AV35*I35),2)*BS35),2))*AU35)/100),2)+ROUND(((ROUND((ROUND(((AE35-(EU35))*AV35*I35),2)*BS35),2)*AU35)/100),2)) -> 0 | AA35: 60256982 | AB35: =ROUND((AC35+AD35+AF35),6) -> 3841.94 | AC35: =ROUND((ES35),6) -> 3841.94 | AD35: =ROUND((((ET35)-(EU35))+AE35),6) -> 0 | AE35: =ROUND((EU35),6) -> 0 | AF35: =ROUND((EV35),6) -> 0 | AG35: =ROUND((AP35),6) -> 0 | AH35: =(EW35) -> 0 | AI35: =(EX35) -> 0 | AJ35: =(AS35) -> 0 | AK35: 3841.94 | AL35: 3841.94 | AM35: 0 | AN35: 0 | AO35: 0 | AP35: 0 | AQ35: 0 | AR35: 0 | AS35: 0 | AT35: 0 | AU35: 0 | AV35: 1 | AW35: 1 | AZ35: 1 | BA35: 1 | BB35: 1 | BC35: 7.66 | BH35: 3 | BI35: 3 | BM35: 746 | BN35: 0 | BP35: 0 | BQ35: 130 | BR35: 0 | BS35: 1 | BT35: 1 | BU35: 1 | BV35: 1 | BW35: 1 | BX35: 1 | BZ35: 90 | CA35: 46 | CE35: 1566 | CF35: 0 | CG35: 0 | CM35: 0 | CO35: 0 | CP35: =(P35+Q35+S35) -> 29429.26 | CQ35: =ROUND((ROUND((AC35*1),2)*BC35),2) -> 29429.26 | CR35: =(ROUND((ROUND(((ET35)*AV35*1),2)*BB35),2)+ROUND((ROUND(((AE35-(EU35))*AV35*1),2)*BS35),2)) -> 0 | CS35: =(ROUND((ROUND(((EU35)*AV35*1),2)*BS35),2)+ROUND((ROUND(((AE35-(EU35))*AV35*1),2)*BS35),2)) -> 0 | CT35: =ROUND((ROUND((AF35*AV35*1),2)*BA35),2) -> 0 | CU35: =AG35 -> 0 | CV35: =(AH35*AV35) -> 0 | CW35: =AI35 -> 0 | CX35: =AJ35 -> 0 | CY35: =(ROUND((((S35+ROUND((ROUND(((EU35)*AV35*1),2)*BS35),2))*AT35)/100),2)+ROUND(((ROUND((ROUND(((AE35-(EU35))*AV35*1),2)*BS35),2)*AT35)/100),2)) -> 0 | CZ35: =(ROUND((((S35+ROUND((ROUND(((EU35)*AV35*1),2)*BS35),2))*AU35)/100),2)+ROUND(((ROUND((ROUND(((AE35-(EU35))*AV35*1),2)*BS35),2)*AU35)/100),2)) -> 0 | DN35: 0 | DO35: 0 | DP35: 1 | DQ35: 1 | DU35: 1010 | DV35: шт. | DW35: шт. | DX35: 1 | EE35: 60088638 | EF35: 130 | EG35: Сметная стоимость оборудования | EH35: 0 | EJ35: 3 | EK35: 746 | EL35: ТСН-2001.13. Сметная стоимость оборудования | EM35: ТСН-2001.13 | EQ35: 0 | ER35: 0 | ES35: 3841.94 | ET35: 0 | EU35: 0 | EV35: 0 | EW35: 0 | EX35: 0 | EZ35: 5 | FC35: 1 | FD35: 18 | FF35: 33880 | FQ35: 0 | FR35: =P35 -> 29429.26 | FS35: 0 | FX35: 90 | FY35: 46 | GA35: [33 880 / 1,2 / 7,66] + 3% Трансп + 1,2% Заг.скл | GD35: 1 | GF35: -1229013042 | GG35: 2 | GH35: 3 | GI35: 5 | GJ35: 0 | GK35: 0 | GL35: =ROUND(IF(AND(BH35=3,BI35=3,FS35<>0),P35,0),2) -> 0 | GM35: =ROUND(O35+X35+Y35,2)+GX35 -> 29429.26 | GN35: =IF(OR(BI35=0,BI35=1),GM35-GX35,0) -> 0 | GO35: =IF(BI35=2,GM35-GX35,0) -> 0 | GP35: =IF(BI35=4,GM35-GX35,0) -> 0 | GR35: 1 | GS35: 1 | GT35: 0 | GV35: =ROUND((GT35),6) -> 0 | GW35: 1 | GX35: =ROUND(HC35*I35,2) -> 0 | HA35: 0 | HB35: 0 | HC35: =GV35*GW35 -> 0 | HE35: 3 | HF35: 1,2 | HS35: 0 | IK35: 0
A36: 17 | B36: 1 | C36: =ROW(SmtRes!A42) -> 42 | D36: =ROW(EtalonRes!A42) -> 42 | E36: 3 | F36: 4.11-17-1 | G36: Монтаж щитов и пультов массой до 50кг | H36: 1 ШТ. | I36: 1 | J36: 0 | K36: 1 | O36: =ROUND(CP36,2) -> 163.14 | P36: =ROUND((ROUND((AC36*AW36*I36),2)*BC36),2) -> 89.36 | Q36: =(ROUND((ROUND((((ET36*1.1))*AV36*I36),2)*BB36),2)+ROUND((ROUND(((AE36-((EU36*1.1)))*AV36*I36),2)*BS36),2)) -> 4.92 | R36: =(ROUND((ROUND((((EU36*1.1))*AV36*I36),2)*BS36),2)+ROUND((ROUND(((AE36-((EU36*1.1)))*AV36*I36),2)*BS36),2)) -> 0.44 | S36: =ROUND((ROUND((AF36*AV36*I36),2)*BA36),2) -> 68.86 | T36: =ROUND(CU36*I36,2) -> 0 | U36: =CV36*I36 -> 5.931255 | V36: =CW36*I36 -> 0 | W36: =ROUND(CX36*I36,2) -> 0 | X36: =(ROUND((((S36+ROUND((ROUND((((EU36*1.1))*AV36*I36),2)*BS36),2))*AT36)/100),2)+ROUND(((ROUND((ROUND(((AE36-((EU36*1.1)))*AV36*I36),2)*BS36),2)*AT36)/100),2)) -> 62.37 | Y36: =(ROUND((((S36+ROUND((ROUND((((EU36*1.1))*AV36*I36),2)*BS36),2))*AU36)/100),2)+ROUND(((ROUND((ROUND(((AE36-((EU36*1.1)))*AV36*I36),2)*BS36),2)*AU36)/100),2)) -> 31.88 | AA36: 60256985 | AB36: =ROUND((AC36+AD36+AF36),6) -> 159.826 | AC36: =ROUND((ES36),6) -> 89.36 | AD36: =ROUND(((((ET36*1.1))-((EU36*1.1)))+AE36),6) -> 4.697 | AE36: =ROUND(((EU36*1.1)),6) -> 0.418 | AF36: =ROUND(((EV36*1.1)),6) -> 65.769 | AG36: =ROUND((AP36),6) -> 0 | AH36: =((EW36*1.1)) -> 5.665 | AI36: =((EX36*1.1)) -> 0 | AJ36: =(AS36) -> 0 | AK36: 153.42 | AL36: 89.36 | AM36: 4.27 | AN36: 0.38 | AO36: 59.79 | AP36: 0 | AQ36: 5.15 | AR36: 0 | AS36: 0 | AT36: 90 | AU36: 46 | AV36: 1.047 | AW36: 1 | AZ36: 1 | BA36: 1 | BB36: 1 | BC36: 1 | BH36: 0 | BI36: 2 | BJ36: ТСН-2001.4 Доп. 80, Сб. 11, т. 17, поз. 1 | BM36: 72 | BN36: 58973116 | BO36: 4.11-17-1 | BP36: 1 | BQ36: 40 | BR36: 0 | BS36: 1 | BT36: 1 | BU36: 1 | BV36: 1 | BW36: 1 | BX36: 1 | BZ36: 90 | CA36: 46 | CE36: 1566 | CF36: 0 | CG36: 0 | CM36: 0 | CN36: Поправка: О.П. п.3.4.30.в Наименование: При применении территориальных сметных нормативов для города Москвы затраты, учитывающие напряженные и стесненные условия производства работ (стесненность, сложность складирования и транспортной логистики и т.п.), исчисляются с применением коэффициентов к затратам труда и заработной плате рабочих, машинистов, времени эксплуатации машин и механизмов, стоимости эксплуатации машин в размере: для объектов, расположенных за пределами Третьего транспортного кольца города Москвы, но в пределах Московской кольцевой автомобильной дороги | CO36: 0 | CP36: =(P36+Q36+S36) -> 163.14 | CQ36: =ROUND((ROUND((AC36*AW36*1),2)*BC36),2) -> 89.36 | CR36: =(ROUND((ROUND((((ET36*1.1))*AV36*1),2)*BB36),2)+ROUND((ROUND(((AE36-((EU36*1.1)))*AV36*1),2)*BS36),2)) -> 4.92 | CS36: =(ROUND((ROUND((((EU36*1.1))*AV36*1),2)*BS36),2)+ROUND((ROUND(((AE36-((EU36*1.1)))*AV36*1),2)*BS36),2)) -> 0.44 | CT36: =ROUND((ROUND((AF36*AV36*1),2)*BA36),2) -> 68.86 | CU36: =AG36 -> 0 | CV36: =(AH36*AV36) -> 5.931255 | CW36: =AI36 -> 0 | CX36: =AJ36 -> 0 | CY36: =(ROUND((((S36+ROUND((ROUND((((EU36*1.1))*AV36*1),2)*BS36),2))*AT36)/100),2)+ROUND(((ROUND((ROUND(((AE36-((EU36*1.1)))*AV36*1),2)*BS36),2)*AT36)/100),2)) -> 62.37 | CZ36: =(ROUND((((S36+ROUND((ROUND((((EU36*1.1))*AV36*1),2)*BS36),2))*AU36)/100),2)+ROUND(((ROUND((ROUND(((AE36-((EU36*1.1)))*AV36*1),2)*BS36),2)*AU36)/100),2)) -> 31.88 | DB36: 5 | DE36: *1,1 | DF36: *1,1 | DG36: *1,1 | DI36: *1,1 | DJ36: *1,1 | DN36: 0 | DO36: 0 | DP36: 1 | DQ36: 1 | DU36: 1013 | DV36: 1 ШТ. | DW36: 1 ШТ. | DX36: 1 | EE36: 60088536 | EF36: 40 | EG36: Монтаж оборудования | EH36: 0 | EJ36: 2 | EK36: 72 | EL36: ТСН-2001.4-11. Приборы и средства автоматизации и вычислительной техники | EM36: ТСН-2001.4-11-1 | EO36: Поправка: О.П. п.3.4.30.в | EQ36: 0 | ER36: 153.42 | ES36: 89.36 | ET36: 4.27 | EU36: 0.38 | EV36: 59.79 | EW36: 5.15 | EX36: 0 | EY36: 0 | FQ36: 0 | FR36: 0 | FS36: 0 | FX36: 90 | FY36: 46 | GD36: 1 | GF36: 1767555919 | GG36: 2 | GH36: 1 | GI36: 2 | GJ36: 0 | GK36: 0 | GL36: =ROUND(IF(AND(BH36=3,BI36=3,FS36<>0),P36,0),2) -> 0 | GM36: =ROUND(O36+X36+Y36,2)+GX36 -> 257.39 | GN36: =IF(OR(BI36=0,BI36=1),GM36-GX36,0) -> 0 | GO36: =IF(BI36=2,GM36-GX36,0) -> 257.39 | GP36: =IF(BI36=4,GM36-GX36,0) -> 0 | GR36: 0 | GS36: 3 | GT36: 0 | GV36: =ROUND((GT36),6) -> 0 | GW36: 1 | GX36: =ROUND(HC36*I36,2) -> 0 | HA36: 0 | HB36: 0 | HC36: =GV36*GW36 -> 0 | HS36: 0 | IK36: 0
A37: 17 | B37: 1 | C37: =ROW(SmtRes!A54) -> 54 | D37: =ROW(EtalonRes!A54) -> 54 | E37: 3 | F37: 4.11-17-1 | G37: Монтаж щитов и пультов массой до 50кг | H37: 1 ШТ. | I37: 1 | J37: 0 | K37: 1 | O37: =ROUND(CP37,2) -> 4309.88 | P37: =ROUND((ROUND((AC37*AW37*I37),2)*BC37),2) -> 453.95 | Q37: =(ROUND((ROUND((((ET37*1.1))*AV37*I37),2)*BB37),2)+ROUND((ROUND(((AE37-((EU37*1.1)))*AV37*I37),2)*BS37),2)) -> 69.32 | R37: =(ROUND((ROUND((((EU37*1.1))*AV37*I37),2)*BS37),2)+ROUND((ROUND(((AE37-((EU37*1.1)))*AV37*I37),2)*BS37),2)) -> 24.2 | S37: =ROUND((ROUND((AF37*AV37*I37),2)*BA37),2) -> 3786.61 | T37: =ROUND(CU37*I37,2) -> 0 | U37: =CV37*I37 -> 5.931255 | V37: =CW37*I37 -> 0 | W37: =ROUND(CX37*I37,2) -> 0 | X37: =(ROUND((((S37+ROUND((ROUND((((EU37*1.1))*AV37*I37),2)*BS37),2))*AT37)/100),2)+ROUND(((ROUND((ROUND(((AE37-((EU37*1.1)))*AV37*I37),2)*BS37),2)*AT37)/100),2)) -> 3429.73 | Y37: =(ROUND((((S37+ROUND((ROUND((((EU37*1.1))*AV37*I37),2)*BS37),2))*AU37)/100),2)+ROUND(((ROUND((ROUND(((AE37-((EU37*1.1)))*AV37*I37),2)*BS37),2)*AU37)/100),2)) -> 1752.97 | AA37: 60256982 | AB37: =ROUND((AC37+AD37+AF37),6) -> 159.826 | AC37: =ROUND((ES37),6) -> 89.36 | AD37: =ROUND(((((ET37*1.1))-((EU37*1.1)))+AE37),6) -> 4.697 | AE37: =ROUND(((EU37*1.1)),6) -> 0.418 | AF37: =ROUND(((EV37*1.1)),6) -> 65.769 | AG37: =ROUND((AP37),6) -> 0 | AH37: =((EW37*1.1)) -> 5.665 | AI37: =((EX37*1.1)) -> 0 | AJ37: =(AS37) -> 0 | AK37: 153.42 | AL37: 89.36 | AM37: 4.27 | AN37: 0.38 | AO37: 59.79 | AP37: 0 | AQ37: 5.15 | AR37: 0 | AS37: 0 | AT37: 90 | AU37: 46 | AV37: 1.047 | AW37: 1 | AZ37: 1 | BA37: 54.99 | BB37: 14.09 | BC37: 5.08 | BH37: 0 | BI37: 2 | BJ37: ТСН-2001.4 Доп. 80, Сб. 11, т. 17, поз. 1 | BM37: 72 | BN37: 58973116 | BO37: 4.11-17-1 | BP37: 1 | BQ37: 40 | BR37: 0 | BS37: 54.99 | BT37: 1 | BU37: 1 | BV37: 1 | BW37: 1 | BX37: 1 | BZ37: 90 | CA37: 46 | CE37: 1566 | CF37: 0 | CG37: 0 | CM37: 0 | CN37: Поправка: О.П. п.3.4.30.в Наименование: При применении территориальных сметных нормативов для города Москвы затраты, учитывающие напряженные и стесненные условия производства работ (стесненность, сложность складирования и транспортной логистики и т.п.), исчисляются с применением коэффициентов к затратам труда и заработной плате рабочих, машинистов, времени эксплуатации машин и механизмов, стоимости эксплуатации машин в размере: для объектов, расположенных за пределами Третьего транспортного кольца города Москвы, но в пределах Московской кольцевой автомобильной дороги | CO37: 0 | CP37: =(P37+Q37+S37) -> 4309.88 | CQ37: =ROUND((ROUND((AC37*AW37*1),2)*BC37),2) -> 453.95 | CR37: =(ROUND((ROUND((((ET37*1.1))*AV37*1),2)*BB37),2)+ROUND((ROUND(((AE37-((EU37*1.1)))*AV37*1),2)*BS37),2)) -> 69.32 | CS37: =(ROUND((ROUND((((EU37*1.1))*AV37*1),2)*BS37),2)+ROUND((ROUND(((AE37-((EU37*1.1)))*AV37*1),2)*BS37),2)) -> 24.2 | CT37: =ROUND((ROUND((AF37*AV37*1),2)*BA37),2) -> 3786.61 | CU37: =AG37 -> 0 | CV37: =(AH37*AV37) -> 5.931255 | CW37: =AI37 -> 0 | CX37: =AJ37 -> 0 | CY37: =(ROUND((((S37+ROUND((ROUND((((EU37*1.1))*AV37*1),2)*BS37),2))*AT37)/100),2)+ROUND(((ROUND((ROUND(((AE37-((EU37*1.1)))*AV37*1),2)*BS37),2)*AT37)/100),2)) -> 3429.73 | CZ37: =(ROUND((((S37+ROUND((ROUND((((EU37*1.1))*AV37*1),2)*BS37),2))*AU37)/100),2)+ROUND(((ROUND((ROUND(((AE37-((EU37*1.1)))*AV37*1),2)*BS37),2)*AU37)/100),2)) -> 1752.97 | DB37: 6 | DE37: *1,1 | DF37: *1,1 | DG37: *1,1 | DI37: *1,1 | DJ37: *1,1 | DN37: 0 | DO37: 0 | DP37: 1 | DQ37: 1 | DU37: 1013 | DV37: 1 ШТ. | DW37: 1 ШТ. | DX37: 1 | EE37: 60088536 | EF37: 40 | EG37: Монтаж оборудования | EH37: 0 | EJ37: 2 | EK37: 72 | EL37: ТСН-2001.4-11. Приборы и средства автоматизации и вычислительной техники | EM37: ТСН-2001.4-11-1 | EO37: Поправка: О.П. п.3.4.30.в | EQ37: 0 | ER37: 153.42 | ES37: 89.36 | ET37: 4.27 | EU37: 0.38 | EV37: 59.79 | EW37: 5.15 | EX37: 0 | EY37: 0 | FQ37: 0 | FR37: 0 | FS37: 0 | FX37: 90 | FY37: 46 | GD37: 1 | GF37: 1767555919 | GG37: 2 | GH37: 1 | GI37: 2 | GJ37: 0 | GK37: 0 | GL37: =ROUND(IF(AND(BH37=3,BI37=3,FS37<>0),P37,0),2) -> 0 | GM37: =ROUND(O37+X37+Y37,2)+GX37 -> 9492.58 | GN37: =IF(OR(BI37=0,BI37=1),GM37-GX37,0) -> 0 | GO37: =IF(BI37=2,GM37-GX37,0) -> 9492.58 | GP37: =IF(BI37=4,GM37-GX37,0) -> 0 | GR37: 0 | GS37: 3 | GT37: 0 | GV37: =ROUND((GT37),6) -> 0 | GW37: 1 | GX37: =ROUND(HC37*I37,2) -> 0 | HA37: 0 | HB37: 0 | HC37: =GV37*GW37 -> 0 | HS37: 0 | IK37: 0
A38: 18 | B38: 1 | C38: 42 | E38: 3,1 | F38: КА-3 | G38: Устройство сопряжения с РСО г.Москвы УС-1 (БАО-РСПИ+БСМС) | H38: шт. | I38: =I36*J38 -> 1 | J38: 1 | K38: 1 | O38: =ROUND(CP38,2) -> 113908.9 | P38: =ROUND((ROUND((AC38*I38),2)*BC38),2) -> 113908.9 | Q38: =(ROUND((ROUND(((ET38)*AV38*I38),2)*BB38),2)+ROUND((ROUND(((AE38-(EU38))*AV38*I38),2)*BS38),2)) -> 0 | R38: =(ROUND((ROUND(((EU38)*AV38*I38),2)*BS38),2)+ROUND((ROUND(((AE38-(EU38))*AV38*I38),2)*BS38),2)) -> 0 | S38: =ROUND((ROUND((AF38*AV38*I38),2)*BA38),2) -> 0 | T38: =ROUND(CU38*I38,2) -> 0 | U38: =CV38*I38 -> 0 | V38: =CW38*I38 -> 0 | W38: =ROUND(CX38*I38,2) -> 0 | X38: =(ROUND((((S38+ROUND((ROUND(((EU38)*AV38*I38),2)*BS38),2))*AT38)/100),2)+ROUND(((ROUND((ROUND(((AE38-(EU38))*AV38*I38),2)*BS38),2)*AT38)/100),2)) -> 0 | Y38: =(ROUND((((S38+ROUND((ROUND(((EU38)*AV38*I38),2)*BS38),2))*AU38)/100),2)+ROUND(((ROUND((ROUND(((AE38-(EU38))*AV38*I38),2)*BS38),2)*AU38)/100),2)) -> 0 | AA38: 60256985 | AB38: =ROUND((AC38+AD38+AF38),6) -> 113908.9 | AC38: =ROUND((ES38),6) -> 113908.9 | AD38: =ROUND((((ET38)-(EU38))+AE38),6) -> 0 | AE38: =ROUND((EU38),6) -> 0 | AF38: =ROUND((EV38),6) -> 0 | AG38: =ROUND((AP38),6) -> 0 | AH38: =(EW38) -> 0 | AI38: =(EX38) -> 0 | AJ38: =(AS38) -> 0 | AK38: 113908.9 | AL38: 113908.9 | AM38: 0 | AN38: 0 | AO38: 0 | AP38: 0 | AQ38: 0 | AR38: 0 | AS38: 0 | AT38: 0 | AU38: 0 | AV38: 1 | AW38: 1 | AZ38: 1 | BA38: 1 | BB38: 1 | BC38: 1 | BH38: 3 | BI38: 3 | BM38: 746 | BN38: 0 | BP38: 0 | BQ38: 130 | BR38: 0 | BS38: 1 | BT38: 1 | BU38: 1 | BV38: 1 | BW38: 1 | BX38: 1 | BZ38: 90 | CA38: 46 | CE38: 1566 | CF38: 0 | CG38: 0 | CM38: 0 | CO38: 0 | CP38: =(P38+Q38+S38) -> 113908.9 | CQ38: =ROUND((ROUND((AC38*1),2)*BC38),2) -> 113908.9 | CR38: =(ROUND((ROUND(((ET38)*AV38*1),2)*BB38),2)+ROUND((ROUND(((AE38-(EU38))*AV38*1),2)*BS38),2)) -> 0 | CS38: =(ROUND((ROUND(((EU38)*AV38*1),2)*BS38),2)+ROUND((ROUND(((AE38-(EU38))*AV38*1),2)*BS38),2)) -> 0 | CT38: =ROUND((ROUND((AF38*AV38*1),2)*BA38),2) -> 0 | CU38: =AG38 -> 0 | CV38: =(AH38*AV38) -> 0 | CW38: =AI38 -> 0 | CX38: =AJ38 -> 0 | CY38: =(ROUND((((S38+ROUND((ROUND(((EU38)*AV38*1),2)*BS38),2))*AT38)/100),2)+ROUND(((ROUND((ROUND(((AE38-(EU38))*AV38*1),2)*BS38),2)*AT38)/100),2)) -> 0 | CZ38: =(ROUND((((S38+ROUND((ROUND(((EU38)*AV38*1),2)*BS38),2))*AU38)/100),2)+ROUND(((ROUND((ROUND(((AE38-(EU38))*AV38*1),2)*BS38),2)*AU38)/100),2)) -> 0 | DN38: 0 | DO38: 0 | DP38: 1 | DQ38: 1 | DU38: 1010 | DV38: шт. | DW38: шт. | DX38: 1 | EE38: 60088638 | EF38: 130 | EG38: Сметная стоимость оборудования | EH38: 0 | EJ38: 3 | EK38: 746 | EL38: ТСН-2001.13. Сметная стоимость оборудования | EM38: ТСН-2001.13 | EQ38: 0 | ER38: 0 | ES38: 113908.9 | ET38: 0 | EU38: 0 | EV38: 0 | EW38: 0 | EX38: 0 | FQ38: 0 | FR38: =P38 -> 113908.9 | FS38: 0 | FX38: 90 | FY38: 46 | GA38: [1 004 500 / 1,2 / 7,66] + 3% Трансп + 1,2% Заг.скл | GD38: 1 | GF38: -978314307 | GG38: 2 | GH38: 4 | GI38: -2 | GJ38: 0 | GK38: 0 | GL38: =ROUND(IF(AND(BH38=3,BI38=3,FS38<>0),P38,0),2) -> 0 | GM38: =ROUND(O38+X38+Y38,2)+GX38 -> 113908.9 | GN38: =IF(OR(BI38=0,BI38=1),GM38-GX38,0) -> 0 | GO38: =IF(BI38=2,GM38-GX38,0) -> 0 | GP38: =IF(BI38=4,GM38-GX38,0) -> 0 | GR38: 0 | GS38: 2 | GT38: 0 | GV38: =ROUND((GT38),6) -> 0 | GW38: 1 | GX38: =ROUND(HC38*I38,2) -> 0 | HA38: 0 | HB38: 0 | HC38: =GV38*GW38 -> 0 | HE38: 3 | HF38: 1,2 | HS38: 0 | IK38: 0
A39: 18 | B39: 1 | C39: 54 | E39: 3,1 | F39: КА-3 | G39: Устройство сопряжения с РСО г.Москвы УС-1 (БАО-РСПИ+БСМС) | H39: шт. | I39: =I37*J39 -> 1 | J39: 1 | K39: 1 | O39: =ROUND(CP39,2) -> 872542.17 | P39: =ROUND((ROUND((AC39*I39),2)*BC39),2) -> 872542.17 | Q39: =(ROUND((ROUND(((ET39)*AV39*I39),2)*BB39),2)+ROUND((ROUND(((AE39-(EU39))*AV39*I39),2)*BS39),2)) -> 0 | R39: =(ROUND((ROUND(((EU39)*AV39*I39),2)*BS39),2)+ROUND((ROUND(((AE39-(EU39))*AV39*I39),2)*BS39),2)) -> 0 | S39: =ROUND((ROUND((AF39*AV39*I39),2)*BA39),2) -> 0 | T39: =ROUND(CU39*I39,2) -> 0 | U39: =CV39*I39 -> 0 | V39: =CW39*I39 -> 0 | W39: =ROUND(CX39*I39,2) -> 0 | X39: =(ROUND((((S39+ROUND((ROUND(((EU39)*AV39*I39),2)*BS39),2))*AT39)/100),2)+ROUND(((ROUND((ROUND(((AE39-(EU39))*AV39*I39),2)*BS39),2)*AT39)/100),2)) -> 0 | Y39: =(ROUND((((S39+ROUND((ROUND(((EU39)*AV39*I39),2)*BS39),2))*AU39)/100),2)+ROUND(((ROUND((ROUND(((AE39-(EU39))*AV39*I39),2)*BS39),2)*AU39)/100),2)) -> 0 | AA39: 60256982 | AB39: =ROUND((AC39+AD39+AF39),6) -> 113908.9 | AC39: =ROUND((ES39),6) -> 113908.9 | AD39: =ROUND((((ET39)-(EU39))+AE39),6) -> 0 | AE39: =ROUND((EU39),6) -> 0 | AF39: =ROUND((EV39),6) -> 0 | AG39: =ROUND((AP39),6) -> 0 | AH39: =(EW39) -> 0 | AI39: =(EX39) -> 0 | AJ39: =(AS39) -> 0 | AK39: 113908.9 | AL39: 113908.9 | AM39: 0 | AN39: 0 | AO39: 0 | AP39: 0 | AQ39: 0 | AR39: 0 | AS39: 0 | AT39: 0 | AU39: 0 | AV39: 1 | AW39: 1 | AZ39: 1 | BA39: 1 | BB39: 1 | BC39: 7.66 | BH39: 3 | BI39: 3 | BM39: 746 | BN39: 0 | BP39: 0 | BQ39: 130 | BR39: 0 | BS39: 1 | BT39: 1 | BU39: 1 | BV39: 1 | BW39: 1 | BX39: 1 | BZ39: 90 | CA39: 46 | CE39: 1566 | CF39: 0 | CG39: 0 | CM39: 0 | CO39: 0 | CP39: =(P39+Q39+S39) -> 872542.17 | CQ39: =ROUND((ROUND((AC39*1),2)*BC39),2) -> 872542.17 | CR39: =(ROUND((ROUND(((ET39)*AV39*1),2)*BB39),2)+ROUND((ROUND(((AE39-(EU39))*AV39*1),2)*BS39),2)) -> 0 | CS39: =(ROUND((ROUND(((EU39)*AV39*1),2)*BS39),2)+ROUND((ROUND(((AE39-(EU39))*AV39*1),2)*BS39),2)) -> 0 | CT39: =ROUND((ROUND((AF39*AV39*1),2)*BA39),2) -> 0 | CU39: =AG39 -> 0 | CV39: =(AH39*AV39) -> 0 | CW39: =AI39 -> 0 | CX39: =AJ39 -> 0 | CY39: =(ROUND((((S39+ROUND((ROUND(((EU39)*AV39*1),2)*BS39),2))*AT39)/100),2)+ROUND(((ROUND((ROUND(((AE39-(EU39))*AV39*1),2)*BS39),2)*AT39)/100),2)) -> 0 | CZ39: =(ROUND((((S39+ROUND((ROUND(((EU39)*AV39*1),2)*BS39),2))*AU39)/100),2)+ROUND(((ROUND((ROUND(((AE39-(EU39))*AV39*1),2)*BS39),2)*AU39)/100),2)) -> 0 | DN39: 0 | DO39: 0 | DP39: 1 | DQ39: 1 | DU39: 1010 | DV39: шт. | DW39: шт. | DX39: 1 | EE39: 60088638 | EF39: 130 | EG39: Сметная стоимость оборудования | EH39: 0 | EJ39: 3 | EK39: 746 | EL39: ТСН-2001.13. Сметная стоимость оборудования | EM39: ТСН-2001.13 | EQ39: 0 | ER39: 0 | ES39: 113908.9 | ET39: 0 | EU39: 0 | EV39: 0 | EW39: 0 | EX39: 0 | EZ39: 5 | FC39: 1 | FD39: 18 | FF39: 1004500 | FQ39: 0 | FR39: =P39 -> 872542.17 | FS39: 0 | FX39: 90 | FY39: 46 | GA39: [1 004 500 / 1,2 / 7,66] + 3% Трансп + 1,2% Заг.скл | GD39: 1 | GF39: -978314307 | GG39: 2 | GH39: 3 | GI39: 5 | GJ39: 0 | GK39: 0 | GL39: =ROUND(IF(AND(BH39=3,BI39=3,FS39<>0),P39,0),2) -> 0 | GM39: =ROUND(O39+X39+Y39,2)+GX39 -> 872542.17 | GN39: =IF(OR(BI39=0,BI39=1),GM39-GX39,0) -> 0 | GO39: =IF(BI39=2,GM39-GX39,0) -> 0 | GP39: =IF(BI39=4,GM39-GX39,0) -> 0 | GR39: 1 | GS39: 1 | GT39: 0 | GV39: =ROUND((GT39),6) -> 0 | GW39: 1 | GX39: =ROUND(HC39*I39,2) -> 0 | HA39: 0 | HB39: 0 | HC39: =GV39*GW39 -> 0 | HE39: 3 | HF39: 1,2 | HS39: 0 | IK39: 0
A40: 17 | B40: 1 | C40: =ROW(SmtRes!A62) -> 62 | D40: =ROW(EtalonRes!A62) -> 62 | E40: 4 | F40: 4.10-69-3 | G40: Монтаж щита распределительного настенного типа | H40: 1 ШТ. | I40: 1 | J40: 0 | K40: 1 | O40: =ROUND(CP40,2) -> 592.11 | P40: =ROUND((ROUND((AC40*AW40*I40),2)*BC40),2) -> 76.75 | Q40: =(ROUND((ROUND((((ET40*1.1))*AV40*I40),2)*BB40),2)+ROUND((ROUND(((AE40-((EU40*1.1)))*AV40*I40),2)*BS40),2)) -> 0 | R40: =(ROUND((ROUND((((EU40*1.1))*AV40*I40),2)*BS40),2)+ROUND((ROUND(((AE40-((EU40*1.1)))*AV40*I40),2)*BS40),2)) -> 0 | S40: =ROUND((ROUND((AF40*AV40*I40),2)*BA40),2) -> 515.36 | T40: =ROUND(CU40*I40,2) -> 0 | U40: =CV40*I40 -> 38.0061 | V40: =CW40*I40 -> 0 | W40: =ROUND(CX40*I40,2) -> 0 | X40: =(ROUND((((S40+ROUND((ROUND((((EU40*1.1))*AV40*I40),2)*BS40),2))*AT40)/100),2)+ROUND(((ROUND((ROUND(((AE40-((EU40*1.1)))*AV40*I40),2)*BS40),2)*AT40)/100),2)) -> 489.59 | Y40: =(ROUND((((S40+ROUND((ROUND((((EU40*1.1))*AV40*I40),2)*BS40),2))*AU40)/100),2)+ROUND(((ROUND((ROUND(((AE40-((EU40*1.1)))*AV40*I40),2)*BS40),2)*AU40)/100),2)) -> 273.14 | AA40: 60256985 | AB40: =ROUND((AC40+AD40+AF40),6) -> 568.978 | AC40: =ROUND((ES40),6) -> 76.75 | AD40: =ROUND(((((ET40*1.1))-((EU40*1.1)))+AE40),6) -> 0 | AE40: =ROUND(((EU40*1.1)),6) -> 0 | AF40: =ROUND(((EV40*1.1)),6) -> 492.228 | AG40: =ROUND((AP40),6) -> 0 | AH40: =((EW40*1.1)) -> 36.3 | AI40: =((EX40*1.1)) -> 0 | AJ40: =(AS40) -> 0 | AK40: 524.23 | AL40: 76.75 | AM40: 0 | AN40: 0 | AO40: 447.48 | AP40: 0 | AQ40: 33 | AR40: 0 | AS40: 0 | AT40: 95 | AU40: 53 | AV40: 1.047 | AW40: 1 | AZ40: 1 | BA40: 1 | BB40: 1 | BC40: 1 | BH40: 0 | BI40: 2 | BJ40: ТСН-2001.4 Доп. 67, Сб. 10, т. 69, поз. 3 | BM40: 69 | BN40: 58973116 | BO40: 4.10-69-3 | BP40: 1 | BQ40: 40 | BR40: 0 | BS40: 1 | BT40: 1 | BU40: 1 | BV40: 1 | BW40: 1 | BX40: 1 | BZ40: 95 | CA40: 53 | CE40: 1566 | CF40: 0 | CG40: 0 | CM40: 0 | CN40: Поправка: О.П. п.3.4.30.в Наименование: При применении территориальных сметных нормативов для города Москвы затраты, учитывающие напряженные и стесненные условия производства работ (стесненность, сложность складирования и транспортной логистики и т.п.), исчисляются с применением коэффициентов к затратам труда и заработной плате рабочих, машинистов, времени эксплуатации машин и механизмов, стоимости эксплуатации машин в размере: для объектов, расположенных за пределами Третьего транспортного кольца города Москвы, но в пределах Московской кольцевой автомобильной дороги | CO40: 0 | CP40: =(P40+Q40+S40) -> 592.11 | CQ40: =ROUND((ROUND((AC40*AW40*1),2)*BC40),2) -> 76.75 | CR40: =(ROUND((ROUND((((ET40*1.1))*AV40*1),2)*BB40),2)+ROUND((ROUND(((AE40-((EU40*1.1)))*AV40*1),2)*BS40),2)) -> 0 | CS40: =(ROUND((ROUND((((EU40*1.1))*AV40*1),2)*BS40),2)+ROUND((ROUND(((AE40-((EU40*1.1)))*AV40*1),2)*BS40),2)) -> 0 | CT40: =ROUND((ROUND((AF40*AV40*1),2)*BA40),2) -> 515.36 | CU40: =AG40 -> 0 | CV40: =(AH40*AV40) -> 38.0061 | CW40: =AI40 -> 0 | CX40: =AJ40 -> 0 | CY40: =(ROUND((((S40+ROUND((ROUND((((EU40*1.1))*AV40*1),2)*BS40),2))*AT40)/100),2)+ROUND(((ROUND((ROUND(((AE40-((EU40*1.1)))*AV40*1),2)*BS40),2)*AT40)/100),2)) -> 489.59 | CZ40: =(ROUND((((S40+ROUND((ROUND((((EU40*1.1))*AV40*1),2)*BS40),2))*AU40)/100),2)+ROUND(((ROUND((ROUND(((AE40-((EU40*1.1)))*AV40*1),2)*BS40),2)*AU40)/100),2)) -> 273.14 | DB40: 7 | DE40: *1,1 | DF40: *1,1 | DG40: *1,1 | DI40: *1,1 | DJ40: *1,1 | DN40: 0 | DO40: 0 | DP40: 1 | DQ40: 1 | DU40: 1013 | DV40: 1 ШТ. | DW40: 1 ШТ. | DX40: 1 | EE40: 60088533 | EF40: 40 | EG40: Монтаж оборудования | EH40: 0 | EJ40: 2 | EK40: 69 | EL40: ТСН-2001.4-10. Монтаж радиотелевизионного и электронного оборудования | EM40: ТСН-2001.4-10-2 | EO40: Поправка: О.П. п.3.4.30.в | EQ40: 0 | ER40: 524.23 | ES40: 76.75 | ET40: 0 | EU40: 0 | EV40: 447.48 | EW40: 33 | EX40: 0 | EY40: 0 | FQ40: 0 | FR40: 0 | FS40: 0 | FX40: 95 | FY40: 53 | GD40: 1 | GF40: 2038815792 | GG40: 2 | GH40: 1 | GI40: 2 | GJ40: 0 | GK40: 0 | GL40: =ROUND(IF(AND(BH40=3,BI40=3,FS40<>0),P40,0),2) -> 0 | GM40: =ROUND(O40+X40+Y40,2)+GX40 -> 1354.84 | GN40: =IF(OR(BI40=0,BI40=1),GM40-GX40,0) -> 0 | GO40: =IF(BI40=2,GM40-GX40,0) -> 1354.84 | GP40: =IF(BI40=4,GM40-GX40,0) -> 0 | GR40: 0 | GS40: 3 | GT40: 0 | GV40: =ROUND((GT40),6) -> 0 | GW40: 1 | GX40: =ROUND(HC40*I40,2) -> 0 | HA40: 0 | HB40: 0 | HC40: =GV40*GW40 -> 0 | HS40: 0 | IK40: 0
A41: 17 | B41: 1 | C41: =ROW(SmtRes!A70) -> 70 | D41: =ROW(EtalonRes!A70) -> 70 | E41: 4 | F41: 4.10-69-3 | G41: Монтаж щита распределительного настенного типа | H41: 1 ШТ. | I41: 1 | J41: 0 | K41: 1 | O41: =ROUND(CP41,2) -> 29038.08 | P41: =ROUND((ROUND((AC41*AW41*I41),2)*BC41),2) -> 698.43 | Q41: =(ROUND((ROUND((((ET41*1.1))*AV41*I41),2)*BB41),2)+ROUND((ROUND(((AE41-((EU41*1.1)))*AV41*I41),2)*BS41),2)) -> 0 | R41: =(ROUND((ROUND((((EU41*1.1))*AV41*I41),2)*BS41),2)+ROUND((ROUND(((AE41-((EU41*1.1)))*AV41*I41),2)*BS41),2)) -> 0 | S41: =ROUND((ROUND((AF41*AV41*I41),2)*BA41),2) -> 28339.65 | T41: =ROUND(CU41*I41,2) -> 0 | U41: =CV41*I41 -> 38.0061 | V41: =CW41*I41 -> 0 | W41: =ROUND(CX41*I41,2) -> 0 | X41: =(ROUND((((S41+ROUND((ROUND((((EU41*1.1))*AV41*I41),2)*BS41),2))*AT41)/100),2)+ROUND(((ROUND((ROUND(((AE41-((EU41*1.1)))*AV41*I41),2)*BS41),2)*AT41)/100),2)) -> 26922.67 | Y41: =(ROUND((((S41+ROUND((ROUND((((EU41*1.1))*AV41*I41),2)*BS41),2))*AU41)/100),2)+ROUND(((ROUND((ROUND(((AE41-((EU41*1.1)))*AV41*I41),2)*BS41),2)*AU41)/100),2)) -> 15020.01 | AA41: 60256982 | AB41: =ROUND((AC41+AD41+AF41),6) -> 568.978 | AC41: =ROUND((ES41),6) -> 76.75 | AD41: =ROUND(((((ET41*1.1))-((EU41*1.1)))+AE41),6) -> 0 | AE41: =ROUND(((EU41*1.1)),6) -> 0 | AF41: =ROUND(((EV41*1.1)),6) -> 492.228 | AG41: =ROUND((AP41),6) -> 0 | AH41: =((EW41*1.1)) -> 36.3 | AI41: =((EX41*1.1)) -> 0 | AJ41: =(AS41) -> 0 | AK41: 524.23 | AL41: 76.75 | AM41: 0 | AN41: 0 | AO41: 447.48 | AP41: 0 | AQ41: 33 | AR41: 0 | AS41: 0 | AT41: 95 | AU41: 53 | AV41: 1.047 | AW41: 1 | AZ41: 1 | BA41: 54.99 | BB41: 1 | BC41: 9.1 | BH41: 0 | BI41: 2 | BJ41: ТСН-2001.4 Доп. 67, Сб. 10, т. 69, поз. 3 | BM41: 69 | BN41: 58973116 | BO41: 4.10-69-3 | BP41: 1 | BQ41: 40 | BR41: 0 | BS41: 54.99 | BT41: 1 | BU41: 1 | BV41: 1 | BW41: 1 | BX41: 1 | BZ41: 95 | CA41: 53 | CE41: 1566 | CF41: 0 | CG41: 0 | CM41: 0 | CN41: Поправка: О.П. п.3.4.30.в Наименование: При применении территориальных сметных нормативов для города Москвы затраты, учитывающие напряженные и стесненные условия производства работ (стесненность, сложность складирования и транспортной логистики и т.п.), исчисляются с применением коэффициентов к затратам труда и заработной плате рабочих, машинистов, времени эксплуатации машин и механизмов, стоимости эксплуатации машин в размере: для объектов, расположенных за пределами Третьего транспортного кольца города Москвы, но в пределах Московской кольцевой автомобильной дороги | CO41: 0 | CP41: =(P41+Q41+S41) -> 29038.08 | CQ41: =ROUND((ROUND((AC41*AW41*1),2)*BC41),2) -> 698.43 | CR41: =(ROUND((ROUND((((ET41*1.1))*AV41*1),2)*BB41),2)+ROUND((ROUND(((AE41-((EU41*1.1)))*AV41*1),2)*BS41),2)) -> 0 | CS41: =(ROUND((ROUND((((EU41*1.1))*AV41*1),2)*BS41),2)+ROUND((ROUND(((AE41-((EU41*1.1)))*AV41*1),2)*BS41),2)) -> 0 | CT41: =ROUND((ROUND((AF41*AV41*1),2)*BA41),2) -> 28339.65 | CU41: =AG41 -> 0 | CV41: =(AH41*AV41) -> 38.0061 | CW41: =AI41 -> 0 | CX41: =AJ41 -> 0 | CY41: =(ROUND((((S41+ROUND((ROUND((((EU41*1.1))*AV41*1),2)*BS41),2))*AT41)/100),2)+ROUND(((ROUND((ROUND(((AE41-((EU41*1.1)))*AV41*1),2)*BS41),2)*AT41)/100),2)) -> 26922.67 | CZ41: =(ROUND((((S41+ROUND((ROUND((((EU41*1.1))*AV41*1),2)*BS41),2))*AU41)/100),2)+ROUND(((ROUND((ROUND(((AE41-((EU41*1.1)))*AV41*1),2)*BS41),2)*AU41)/100),2)) -> 15020.01 | DB41: 8 | DE41: *1,1 | DF41: *1,1 | DG41: *1,1 | DI41: *1,1 | DJ41: *1,1 | DN41: 0 | DO41: 0 | DP41: 1 | DQ41: 1 | DU41: 1013 | DV41: 1 ШТ. | DW41: 1 ШТ. | DX41: 1 | EE41: 60088533 | EF41: 40 | EG41: Монтаж оборудования | EH41: 0 | EJ41: 2 | EK41: 69 | EL41: ТСН-2001.4-10. Монтаж радиотелевизионного и электронного оборудования | EM41: ТСН-2001.4-10-2 | EO41: Поправка: О.П. п.3.4.30.в | EQ41: 0 | ER41: 524.23 | ES41: 76.75 | ET41: 0 | EU41: 0 | EV41: 447.48 | EW41: 33 | EX41: 0 | EY41: 0 | FQ41: 0 | FR41: 0 | FS41: 0 | FX41: 95 | FY41: 53 | GD41: 1 | GF41: 2038815792 | GG41: 2 | GH41: 1 | GI41: 2 | GJ41: 0 | GK41: 0 | GL41: =ROUND(IF(AND(BH41=3,BI41=3,FS41<>0),P41,0),2) -> 0 | GM41: =ROUND(O41+X41+Y41,2)+GX41 -> 70980.76 | GN41: =IF(OR(BI41=0,BI41=1),GM41-GX41,0) -> 0 | GO41: =IF(BI41=2,GM41-GX41,0) -> 70980.76 | GP41: =IF(BI41=4,GM41-GX41,0) -> 0 | GR41: 0 | GS41: 3 | GT41: 0 | GV41: =ROUND((GT41),6) -> 0 | GW41: 1 | GX41: =ROUND(HC41*I41,2) -> 0 | HA41: 0 | HB41: 0 | HC41: =GV41*GW41 -> 0 | HS41: 0 | IK41: 0
A42: 18 | B42: 1 | C42: 62 | E42: 4,1 | F42: КА-4 | G42: Резервный канал РСПИ ОСПИ-Тандем | H42: шт. | I42: =I40*J42 -> 1 | J42: 1 | K42: 1 | O42: =ROUND(CP42,2) -> 11113.06 | P42: =ROUND((ROUND((AC42*I42),2)*BC42),2) -> 11113.06 | Q42: =(ROUND((ROUND(((ET42)*AV42*I42),2)*BB42),2)+ROUND((ROUND(((AE42-(EU42))*AV42*I42),2)*BS42),2)) -> 0 | R42: =(ROUND((ROUND(((EU42)*AV42*I42),2)*BS42),2)+ROUND((ROUND(((AE42-(EU42))*AV42*I42),2)*BS42),2)) -> 0 | S42: =ROUND((ROUND((AF42*AV42*I42),2)*BA42),2) -> 0 | T42: =ROUND(CU42*I42,2) -> 0 | U42: =CV42*I42 -> 0 | V42: =CW42*I42 -> 0 | W42: =ROUND(CX42*I42,2) -> 0 | X42: =(ROUND((((S42+ROUND((ROUND(((EU42)*AV42*I42),2)*BS42),2))*AT42)/100),2)+ROUND(((ROUND((ROUND(((AE42-(EU42))*AV42*I42),2)*BS42),2)*AT42)/100),2)) -> 0 | Y42: =(ROUND((((S42+ROUND((ROUND(((EU42)*AV42*I42),2)*BS42),2))*AU42)/100),2)+ROUND(((ROUND((ROUND(((AE42-(EU42))*AV42*I42),2)*BS42),2)*AU42)/100),2)) -> 0 | AA42: 60256985 | AB42: =ROUND((AC42+AD42+AF42),6) -> 11113.06 | AC42: =ROUND((ES42),6) -> 11113.06 | AD42: =ROUND((((ET42)-(EU42))+AE42),6) -> 0 | AE42: =ROUND((EU42),6) -> 0 | AF42: =ROUND((EV42),6) -> 0 | AG42: =ROUND((AP42),6) -> 0 | AH42: =(EW42) -> 0 | AI42: =(EX42) -> 0 | AJ42: =(AS42) -> 0 | AK42: 11113.06 | AL42: 11113.06 | AM42: 0 | AN42: 0 | AO42: 0 | AP42: 0 | AQ42: 0 | AR42: 0 | AS42: 0 | AT42: 0 | AU42: 0 | AV42: 1 | AW42: 1 | AZ42: 1 | BA42: 1 | BB42: 1 | BC42: 1 | BH42: 3 | BI42: 3 | BM42: 746 | BN42: 0 | BP42: 0 | BQ42: 130 | BR42: 0 | BS42: 1 | BT42: 1 | BU42: 1 | BV42: 1 | BW42: 1 | BX42: 1 | BZ42: 95 | CA42: 53 | CE42: 1566 | CF42: 0 | CG42: 0 | CM42: 0 | CO42: 0 | CP42: =(P42+Q42+S42) -> 11113.06 | CQ42: =ROUND((ROUND((AC42*1),2)*BC42),2) -> 11113.06 | CR42: =(ROUND((ROUND(((ET42)*AV42*1),2)*BB42),2)+ROUND((ROUND(((AE42-(EU42))*AV42*1),2)*BS42),2)) -> 0 | CS42: =(ROUND((ROUND(((EU42)*AV42*1),2)*BS42),2)+ROUND((ROUND(((AE42-(EU42))*AV42*1),2)*BS42),2)) -> 0 | CT42: =ROUND((ROUND((AF42*AV42*1),2)*BA42),2) -> 0 | CU42: =AG42 -> 0 | CV42: =(AH42*AV42) -> 0 | CW42: =AI42 -> 0 | CX42: =AJ42 -> 0 | CY42: =(ROUND((((S42+ROUND((ROUND(((EU42)*AV42*1),2)*BS42),2))*AT42)/100),2)+ROUND(((ROUND((ROUND(((AE42-(EU42))*AV42*1),2)*BS42),2)*AT42)/100),2)) -> 0 | CZ42: =(ROUND((((S42+ROUND((ROUND(((EU42)*AV42*1),2)*BS42),2))*AU42)/100),2)+ROUND(((ROUND((ROUND(((AE42-(EU42))*AV42*1),2)*BS42),2)*AU42)/100),2)) -> 0 | DN42: 0 | DO42: 0 | DP42: 1 | DQ42: 1 | DU42: 1010 | DV42: шт. | DW42: шт. | DX42: 1 | EE42: 60088638 | EF42: 130 | EG42: Сметная стоимость оборудования | EH42: 0 | EJ42: 3 | EK42: 746 | EL42: ТСН-2001.13. Сметная стоимость оборудования | EM42: ТСН-2001.13 | EQ42: 0 | ER42: 0 | ES42: 11113.06 | ET42: 0 | EU42: 0 | EV42: 0 | EW42: 0 | EX42: 0 | FQ42: 0 | FR42: =P42 -> 11113.06 | FS42: 0 | FX42: 95 | FY42: 53 | GA42: [98 000 / 1,2 / 7,66] + 3% Трансп + 1,2% Заг.скл | GD42: 1 | GF42: -172379434 | GG42: 2 | GH42: 4 | GI42: -2 | GJ42: 0 | GK42: 0 | GL42: =ROUND(IF(AND(BH42=3,BI42=3,FS42<>0),P42,0),2) -> 0 | GM42: =ROUND(O42+X42+Y42,2)+GX42 -> 11113.06 | GN42: =IF(OR(BI42=0,BI42=1),GM42-GX42,0) -> 0 | GO42: =IF(BI42=2,GM42-GX42,0) -> 0 | GP42: =IF(BI42=4,GM42-GX42,0) -> 0 | GR42: 0 | GS42: 2 | GT42: 0 | GV42: =ROUND((GT42),6) -> 0 | GW42: 1 | GX42: =ROUND(HC42*I42,2) -> 0 | HA42: 0 | HB42: 0 | HC42: =GV42*GW42 -> 0 | HE42: 3 | HF42: 1,2 | HS42: 0 | IK42: 0
A43: 18 | B43: 1 | C43: 70 | E43: 4,1 | F43: КА-4 | G43: Резервный канал РСПИ ОСПИ-Тандем | H43: шт. | I43: =I41*J43 -> 1 | J43: 1 | K43: 1 | O43: =ROUND(CP43,2) -> 85126.04 | P43: =ROUND((ROUND((AC43*I43),2)*BC43),2) -> 85126.04 | Q43: =(ROUND((ROUND(((ET43)*AV43*I43),2)*BB43),2)+ROUND((ROUND(((AE43-(EU43))*AV43*I43),2)*BS43),2)) -> 0 | R43: =(ROUND((ROUND(((EU43)*AV43*I43),2)*BS43),2)+ROUND((ROUND(((AE43-(EU43))*AV43*I43),2)*BS43),2)) -> 0 | S43: =ROUND((ROUND((AF43*AV43*I43),2)*BA43),2) -> 0 | T43: =ROUND(CU43*I43,2) -> 0 | U43: =CV43*I43 -> 0 | V43: =CW43*I43 -> 0 | W43: =ROUND(CX43*I43,2) -> 0 | X43: =(ROUND((((S43+ROUND((ROUND(((EU43)*AV43*I43),2)*BS43),2))*AT43)/100),2)+ROUND(((ROUND((ROUND(((AE43-(EU43))*AV43*I43),2)*BS43),2)*AT43)/100),2)) -> 0 | Y43: =(ROUND((((S43+ROUND((ROUND(((EU43)*AV43*I43),2)*BS43),2))*AU43)/100),2)+ROUND(((ROUND((ROUND(((AE43-(EU43))*AV43*I43),2)*BS43),2)*AU43)/100),2)) -> 0 | AA43: 60256982 | AB43: =ROUND((AC43+AD43+AF43),6) -> 11113.06 | AC43: =ROUND((ES43),6) -> 11113.06 | AD43: =ROUND((((ET43)-(EU43))+AE43),6) -> 0 | AE43: =ROUND((EU43),6) -> 0 | AF43: =ROUND((EV43),6) -> 0 | AG43: =ROUND((AP43),6) -> 0 | AH43: =(EW43) -> 0 | AI43: =(EX43) -> 0 | AJ43: =(AS43) -> 0 | AK43: 11113.06 | AL43: 11113.06 | AM43: 0 | AN43: 0 | AO43: 0 | AP43: 0 | AQ43: 0 | AR43: 0 | AS43: 0 | AT43: 0 | AU43: 0 | AV43: 1 | AW43: 1 | AZ43: 1 | BA43: 1 | BB43: 1 | BC43: 7.66 | BH43: 3 | BI43: 3 | BM43: 746 | BN43: 0 | BP43: 0 | BQ43: 130 | BR43: 0 | BS43: 1 | BT43: 1 | BU43: 1 | BV43: 1 | BW43: 1 | BX43: 1 | BZ43: 95 | CA43: 53 | CE43: 1566 | CF43: 0 | CG43: 0 | CM43: 0 | CO43: 0 | CP43: =(P43+Q43+S43) -> 85126.04 | CQ43: =ROUND((ROUND((AC43*1),2)*BC43),2) -> 85126.04 | CR43: =(ROUND((ROUND(((ET43)*AV43*1),2)*BB43),2)+ROUND((ROUND(((AE43-(EU43))*AV43*1),2)*BS43),2)) -> 0 | CS43: =(ROUND((ROUND(((EU43)*AV43*1),2)*BS43),2)+ROUND((ROUND(((AE43-(EU43))*AV43*1),2)*BS43),2)) -> 0 | CT43: =ROUND((ROUND((AF43*AV43*1),2)*BA43),2) -> 0 | CU43: =AG43 -> 0 | CV43: =(AH43*AV43) -> 0 | CW43: =AI43 -> 0 | CX43: =AJ43 -> 0 | CY43: =(ROUND((((S43+ROUND((ROUND(((EU43)*AV43*1),2)*BS43),2))*AT43)/100),2)+ROUND(((ROUND((ROUND(((AE43-(EU43))*AV43*1),2)*BS43),2)*AT43)/100),2)) -> 0 | CZ43: =(ROUND((((S43+ROUND((ROUND(((EU43)*AV43*1),2)*BS43),2))*AU43)/100),2)+ROUND(((ROUND((ROUND(((AE43-(EU43))*AV43*1),2)*BS43),2)*AU43)/100),2)) -> 0 | DN43: 0 | DO43: 0 | DP43: 1 | DQ43: 1 | DU43: 1010 | DV43: шт. | DW43: шт. | DX43: 1 | EE43: 60088638 | EF43: 130 | EG43: Сметная стоимость оборудования | EH43: 0 | EJ43: 3 | EK43: 746 | EL43: ТСН-2001.13. Сметная стоимость оборудования | EM43: ТСН-2001.13 | EQ43: 0 | ER43: 0 | ES43: 11113.06 | ET43: 0 | EU43: 0 | EV43: 0 | EW43: 0 | EX43: 0 | EZ43: 5 | FC43: 1 | FD43: 18 | FF43: 98000 | FQ43: 0 | FR43: =P43 -> 85126.04 | FS43: 0 | FX43: 95 | FY43: 53 | GA43: [98 000 / 1,2 / 7,66] + 3% Трансп + 1,2% Заг.скл | GD43: 1 | GF43: -172379434 | GG43: 2 | GH43: 3 | GI43: 5 | GJ43: 0 | GK43: 0 | GL43: =ROUND(IF(AND(BH43=3,BI43=3,FS43<>0),P43,0),2) -> 0 | GM43: =ROUND(O43+X43+Y43,2)+GX43 -> 85126.04 | GN43: =IF(OR(BI43=0,BI43=1),GM43-GX43,0) -> 0 | GO43: =IF(BI43=2,GM43-GX43,0) -> 0 | GP43: =IF(BI43=4,GM43-GX43,0) -> 0 | GR43: 1 | GS43: 1 | GT43: 0 | GV43: =ROUND((GT43),6) -> 0 | GW43: 1 | GX43: =ROUND(HC43*I43,2) -> 0 | HA43: 0 | HB43: 0 | HC43: =GV43*GW43 -> 0 | HE43: 3 | HF43: 1,2 | HS43: 0 | IK43: 0
A44: 17 | B44: 1 | C44: =ROW(SmtRes!A74) -> 74 | D44: =ROW(EtalonRes!A73) -> 73 | E44: 5 | F44: 4.8-333-7 | G44: Монтаж розетки штепсельной скрытого типа | H44: 100 шт. | I44: =ROUND(7/100,9) -> 0.07 | J44: 0 | K44: =ROUND(7/100,9) -> 0.07 | O44: =ROUND(CP44,2) -> 17.05 | P44: =ROUND((ROUND((AC44*AW44*I44),2)*BC44),2) -> 0 | Q44: =(ROUND((ROUND((((ET44*1.1))*AV44*I44),2)*BB44),2)+ROUND((ROUND(((AE44-((EU44*1.1)))*AV44*I44),2)*BS44),2)) -> 0.07 | R44: =(ROUND((ROUND((((EU44*1.1))*AV44*I44),2)*BS44),2)+ROUND((ROUND(((AE44-((EU44*1.1)))*AV44*I44),2)*BS44),2)) -> 0.01 | S44: =ROUND((ROUND((AF44*AV44*I44),2)*BA44),2) -> 16.98 | T44: =ROUND(CU44*I44,2) -> 0 | U44: =CV44*I44 -> 1.518862 | V44: =CW44*I44 -> 0 | W44: =ROUND(CX44*I44,2) -> 0 | X44: =(ROUND((((S44+ROUND((ROUND((((EU44*1.1))*AV44*I44),2)*BS44),2))*AT44)/100),2)+ROUND(((ROUND((ROUND(((AE44-((EU44*1.1)))*AV44*I44),2)*BS44),2)*AT44)/100),2)) -> 16.48 | Y44: =(ROUND((((S44+ROUND((ROUND((((EU44*1.1))*AV44*I44),2)*BS44),2))*AU44)/100),2)+ROUND(((ROUND((ROUND(((AE44-((EU44*1.1)))*AV44*I44),2)*BS44),2)*AU44)/100),2)) -> 8.66 | AA44: 60256985 | AB44: =ROUND((AC44+AD44+AF44),6) -> 232.54 | AC44: =ROUND((ES44),6) -> 0 | AD44: =ROUND(((((ET44*1.1))-((EU44*1.1)))+AE44),6) -> 0.913 | AE44: =ROUND(((EU44*1.1)),6) -> 0.143 | AF44: =ROUND(((EV44*1.1)),6) -> 231.627 | AG44: =ROUND((AP44),6) -> 0 | AH44: =((EW44*1.1)) -> 20.724 | AI44: =((EX44*1.1)) -> 0 | AJ44: =(AS44) -> 0 | AK44: 211.4 | AL44: 0 | AM44: 0.83 | AN44: 0.13 | AO44: 210.57 | AP44: 0 | AQ44: 18.84 | AR44: 0 | AS44: 0 | AT44: 97 | AU44: 51 | AV44: 1.047 | AW44: 1 | AZ44: 1 | BA44: 1 | BB44: 1 | BC44: 1 | BH44: 0 | BI44: 2 | BJ44: ТСН-2001.4 Доп. 80, Сб. 8, т. 333, поз. 7 | BM44: 67 | BN44: 0 | BO44: 4.8-333-7 | BP44: 1 | BQ44: 40 | BR44: 0 | BS44: 1 | BT44: 1 | BU44: 1 | BV44: 1 | BW44: 1 | BX44: 1 | BZ44: 97 | CA44: 51 | CE44: 1566 | CF44: 0 | CG44: 0 | CM44: 0 | CN44: Поправка: О.П. п.3.4.30.в Наименование: При применении территориальных сметных нормативов для города Москвы затраты, учитывающие напряженные и стесненные условия производства работ (стесненность, сложность складирования и транспортной логистики и т.п.), исчисляются с применением коэффициентов к затратам труда и заработной плате рабочих, машинистов, времени эксплуатации машин и механизмов, стоимости эксплуатации машин в размере: для объектов, расположенных за пределами Третьего транспортного кольца города Москвы, но в пределах Московской кольцевой автомобильной дороги | CO44: 0 | CP44: =(P44+Q44+S44) -> 17.05 | CQ44: =ROUND((ROUND((AC44*AW44*1),2)*BC44),2) -> 0 | CR44: =(ROUND((ROUND((((ET44*1.1))*AV44*1),2)*BB44),2)+ROUND((ROUND(((AE44-((EU44*1.1)))*AV44*1),2)*BS44),2)) -> 0.96 | CS44: =(ROUND((ROUND((((EU44*1.1))*AV44*1),2)*BS44),2)+ROUND((ROUND(((AE44-((EU44*1.1)))*AV44*1),2)*BS44),2)) -> 0.15 | CT44: =ROUND((ROUND((AF44*AV44*1),2)*BA44),2) -> 242.51 | CU44: =AG44 -> 0 | CV44: =(AH44*AV44) -> 21.698028 | CW44: =AI44 -> 0 | CX44: =AJ44 -> 0 | CY44: =(ROUND((((S44+ROUND((ROUND((((EU44*1.1))*AV44*1),2)*BS44),2))*AT44)/100),2)+ROUND(((ROUND((ROUND(((AE44-((EU44*1.1)))*AV44*1),2)*BS44),2)*AT44)/100),2)) -> 16.62 | CZ44: =(ROUND((((S44+ROUND((ROUND((((EU44*1.1))*AV44*1),2)*BS44),2))*AU44)/100),2)+ROUND(((ROUND((ROUND(((AE44-((EU44*1.1)))*AV44*1),2)*BS44),2)*AU44)/100),2)) -> 8.74 | DB44: 9 | DE44: *1,1 | DF44: *1,1 | DG44: *1,1 | DI44: *1,1 | DJ44: *1,1 | DN44: 0 | DO44: 0 | DP44: 1 | DQ44: 1 | DU44: 1010 | DV44: 100 шт. | DW44: 100 шт. | DX44: 100 | EE44: 60088531 | EF44: 40 | EG44: Монтаж оборудования | EH44: 0 | EJ44: 2 | EK44: 67 | EL44: ТСН-2001.4-8. Электротехнические установки | EM44: ТСН-2001.4-8-1 | EO44: Поправка: О.П. п.3.4.30.в | EQ44: 0 | ER44: 211.4 | ES44: 0 | ET44: 0.83 | EU44: 0.13 | EV44: 210.57 | EW44: 18.84 | EX44: 0 | EY44: 0 | FQ44: 0 | FR44: 0 | FS44: 0 | FX44: 97 | FY44: 51 | GD44: 1 | GF44: 728449770 | GG44: 2 | GH44: 1 | GI44: 2 | GJ44: 0 | GK44: 0 | GL44: =ROUND(IF(AND(BH44=3,BI44=3,FS44<>0),P44,0),2) -> 0 | GM44: =ROUND(O44+X44+Y44,2)+GX44 -> 42.19 | GN44: =IF(OR(BI44=0,BI44=1),GM44-GX44,0) -> 0 | GO44: =IF(BI44=2,GM44-GX44,0) -> 42.19 | GP44: =IF(BI44=4,GM44-GX44,0) -> 0 | GR44: 0 | GS44: 3 | GT44: 0 | GV44: =ROUND((GT44),6) -> 0 | GW44: 1 | GX44: =ROUND(HC44*I44,2) -> 0 | HA44: 0 | HB44: 0 | HC44: =GV44*GW44 -> 0 | HS44: 0 | IK44: 0
A45: 17 | B45: 1 | C45: =ROW(SmtRes!A78) -> 78 | D45: =ROW(EtalonRes!A76) -> 76 | E45: 5 | F45: 4.8-333-7 | G45: Монтаж розетки штепсельной скрытого типа | H45: 100 шт. | I45: =ROUND(7/100,9) -> 0.07 | J45: 0 | K45: =ROUND(7/100,9) -> 0.07 | O45: =ROUND(CP45,2) -> 934.87 | P45: =ROUND((ROUND((AC45*AW45*I45),2)*BC45),2) -> 0 | Q45: =(ROUND((ROUND((((ET45*1.1))*AV45*I45),2)*BB45),2)+ROUND((ROUND(((AE45-((EU45*1.1)))*AV45*I45),2)*BS45),2)) -> 1.14 | R45: =(ROUND((ROUND((((EU45*1.1))*AV45*I45),2)*BS45),2)+ROUND((ROUND(((AE45-((EU45*1.1)))*AV45*I45),2)*BS45),2)) -> 0.55 | S45: =ROUND((ROUND((AF45*AV45*I45),2)*BA45),2) -> 933.73 | T45: =ROUND(CU45*I45,2) -> 0 | U45: =CV45*I45 -> 1.518862 | V45: =CW45*I45 -> 0 | W45: =ROUND(CX45*I45,2) -> 0 | X45: =(ROUND((((S45+ROUND((ROUND((((EU45*1.1))*AV45*I45),2)*BS45),2))*AT45)/100),2)+ROUND(((ROUND((ROUND(((AE45-((EU45*1.1)))*AV45*I45),2)*BS45),2)*AT45)/100),2)) -> 906.25 | Y45: =(ROUND((((S45+ROUND((ROUND((((EU45*1.1))*AV45*I45),2)*BS45),2))*AU45)/100),2)+ROUND(((ROUND((ROUND(((AE45-((EU45*1.1)))*AV45*I45),2)*BS45),2)*AU45)/100),2)) -> 476.48 | AA45: 60256982 | AB45: =ROUND((AC45+AD45+AF45),6) -> 232.54 | AC45: =ROUND((ES45),6) -> 0 | AD45: =ROUND(((((ET45*1.1))-((EU45*1.1)))+AE45),6) -> 0.913 | AE45: =ROUND(((EU45*1.1)),6) -> 0.143 | AF45: =ROUND(((EV45*1.1)),6) -> 231.627 | AG45: =ROUND((AP45),6) -> 0 | AH45: =((EW45*1.1)) -> 20.724 | AI45: =((EX45*1.1)) -> 0 | AJ45: =(AS45) -> 0 | AK45: 211.4 | AL45: 0 | AM45: 0.83 | AN45: 0.13 | AO45: 210.57 | AP45: 0 | AQ45: 18.84 | AR45: 0 | AS45: 0 | AT45: 97 | AU45: 51 | AV45: 1.047 | AW45: 1 | AZ45: 1 | BA45: 54.99 | BB45: 16.33 | BC45: 1 | BH45: 0 | BI45: 2 | BJ45: ТСН-2001.4 Доп. 80, Сб. 8, т. 333, поз. 7 | BM45: 67 | BN45: 0 | BO45: 4.8-333-7 | BP45: 1 | BQ45: 40 | BR45: 0 | BS45: 54.99 | BT45: 1 | BU45: 1 | BV45: 1 | BW45: 1 | BX45: 1 | BZ45: 97 | CA45: 51 | CE45: 1566 | CF45: 0 | CG45: 0 | CM45: 0 | CN45: Поправка: О.П. п.3.4.30.в Наименование: При применении территориальных сметных нормативов для города Москвы затраты, учитывающие напряженные и стесненные условия производства работ (стесненность, сложность складирования и транспортной логистики и т.п.), исчисляются с применением коэффициентов к затратам труда и заработной плате рабочих, машинистов, времени эксплуатации машин и механизмов, стоимости эксплуатации машин в размере: для объектов, расположенных за пределами Третьего транспортного кольца города Москвы, но в пределах Московской кольцевой автомобильной дороги | CO45: 0 | CP45: =(P45+Q45+S45) -> 934.87 | CQ45: =ROUND((ROUND((AC45*AW45*1),2)*BC45),2) -> 0 | CR45: =(ROUND((ROUND((((ET45*1.1))*AV45*1),2)*BB45),2)+ROUND((ROUND(((AE45-((EU45*1.1)))*AV45*1),2)*BS45),2)) -> 15.68 | CS45: =(ROUND((ROUND((((EU45*1.1))*AV45*1),2)*BS45),2)+ROUND((ROUND(((AE45-((EU45*1.1)))*AV45*1),2)*BS45),2)) -> 8.25 | CT45: =ROUND((ROUND((AF45*AV45*1),2)*BA45),2) -> 13335.62 | CU45: =AG45 -> 0 | CV45: =(AH45*AV45) -> 21.698028 | CW45: =AI45 -> 0 | CX45: =AJ45 -> 0 | CY45: =(ROUND((((S45+ROUND((ROUND((((EU45*1.1))*AV45*1),2)*BS45),2))*AT45)/100),2)+ROUND(((ROUND((ROUND(((AE45-((EU45*1.1)))*AV45*1),2)*BS45),2)*AT45)/100),2)) -> 913.72 | CZ45: =(ROUND((((S45+ROUND((ROUND((((EU45*1.1))*AV45*1),2)*BS45),2))*AU45)/100),2)+ROUND(((ROUND((ROUND(((AE45-((EU45*1.1)))*AV45*1),2)*BS45),2)*AU45)/100),2)) -> 480.41 | DB45: 10 | DE45: *1,1 | DF45: *1,1 | DG45: *1,1 | DI45: *1,1 | DJ45: *1,1 | DN45: 0 | DO45: 0 | DP45: 1 | DQ45: 1 | DU45: 1010 | DV45: 100 шт. | DW45: 100 шт. | DX45: 100 | EE45: 60088531 | EF45: 40 | EG45: Монтаж оборудования | EH45: 0 | EJ45: 2 | EK45: 67 | EL45: ТСН-2001.4-8. Электротехнические установки | EM45: ТСН-2001.4-8-1 | EO45: Поправка: О.П. п.3.4.30.в | EQ45: 0 | ER45: 211.4 | ES45: 0 | ET45: 0.83 | EU45: 0.13 | EV45: 210.57 | EW45: 18.84 | EX45: 0 | EY45: 0 | FQ45: 0 | FR45: 0 | FS45: 0 | FX45: 97 | FY45: 51 | GD45: 1 | GF45: 728449770 | GG45: 2 | GH45: 1 | GI45: 2 | GJ45: 0 | GK45: 0 | GL45: =ROUND(IF(AND(BH45=3,BI45=3,FS45<>0),P45,0),2) -> 0 | GM45: =ROUND(O45+X45+Y45,2)+GX45 -> 2317.6 | GN45: =IF(OR(BI45=0,BI45=1),GM45-GX45,0) -> 0 | GO45: =IF(BI45=2,GM45-GX45,0) -> 2317.6 | GP45: =IF(BI45=4,GM45-GX45,0) -> 0 | GR45: 0 | GS45: 3 | GT45: 0 | GV45: =ROUND((GT45),6) -> 0 | GW45: 1 | GX45: =ROUND(HC45*I45,2) -> 0 | HA45: 0 | HB45: 0 | HC45: =GV45*GW45 -> 0 | HS45: 0 | IK45: 0
A46: 18 | B46: 1 | C46: 73 | E46: 5,1 | F46: 1.14-1-23 | G46: Розетка радиотрансляционная, скрытой установки, типа РПВ-2 (прим. АРС-003) | H46: шт. | I46: =I44*J46 -> 7 | J46: 100 | K46: 100 | O46: =ROUND(CP46,2) -> 22.12 | P46: =ROUND((ROUND((AC46*AW46*I46),2)*BC46),2) -> 22.12 | Q46: =(ROUND((ROUND(((ET46)*AV46*I46),2)*BB46),2)+ROUND((ROUND(((AE46-(EU46))*AV46*I46),2)*BS46),2)) -> 0 | R46: =(ROUND((ROUND(((EU46)*AV46*I46),2)*BS46),2)+ROUND((ROUND(((AE46-(EU46))*AV46*I46),2)*BS46),2)) -> 0 | S46: =ROUND((ROUND((AF46*AV46*I46),2)*BA46),2) -> 0 | T46: =ROUND(CU46*I46,2) -> 0 | U46: =CV46*I46 -> 0 | V46: =CW46*I46 -> 0 | W46: =ROUND(CX46*I46,2) -> 0 | X46: =(ROUND((((S46+ROUND((ROUND(((EU46)*AV46*I46),2)*BS46),2))*AT46)/100),2)+ROUND(((ROUND((ROUND(((AE46-(EU46))*AV46*I46),2)*BS46),2)*AT46)/100),2)) -> 0 | Y46: =(ROUND((((S46+ROUND((ROUND(((EU46)*AV46*I46),2)*BS46),2))*AU46)/100),2)+ROUND(((ROUND((ROUND(((AE46-(EU46))*AV46*I46),2)*BS46),2)*AU46)/100),2)) -> 0 | AA46: 60256985 | AB46: =ROUND((AC46+AD46+AF46),6) -> 3.16 | AC46: =ROUND((ES46),6) -> 3.16 | AD46: =ROUND((((ET46)-(EU46))+AE46),6) -> 0 | AE46: =ROUND((EU46),6) -> 0 | AF46: =ROUND((EV46),6) -> 0 | AG46: =ROUND((AP46),6) -> 0 | AH46: =(EW46) -> 0 | AI46: =(EX46) -> 0 | AJ46: =(AS46) -> 0 | AK46: 3.16 | AL46: 3.16 | AM46: 0 | AN46: 0 | AO46: 0 | AP46: 0 | AQ46: 0 | AR46: 0 | AS46: 0 | AT46: 97 | AU46: 51 | AV46: 1 | AW46: 1 | AZ46: 1 | BA46: 1 | BB46: 1 | BC46: 1 | BH46: 3 | BI46: 2 | BJ46: ТСН-2001.1 Доп. 79, Р. 14, о. 1, поз. 23 | BM46: 67 | BN46: 0 | BP46: 0 | BQ46: 40 | BR46: 0 | BS46: 1 | BT46: 1 | BU46: 1 | BV46: 1 | BW46: 1 | BX46: 1 | BZ46: 97 | CA46: 51 | CE46: 1566 | CF46: 0 | CG46: 0 | CM46: 0 | CO46: 0 | CP46: =(P46+Q46+S46) -> 22.12 | CQ46: =ROUND((ROUND((AC46*AW46*1),2)*BC46),2) -> 3.16 | CR46: =(ROUND((ROUND(((ET46)*AV46*1),2)*BB46),2)+ROUND((ROUND(((AE46-(EU46))*AV46*1),2)*BS46),2)) -> 0 | CS46: =(ROUND((ROUND(((EU46)*AV46*1),2)*BS46),2)+ROUND((ROUND(((AE46-(EU46))*AV46*1),2)*BS46),2)) -> 0 | CT46: =ROUND((ROUND((AF46*AV46*1),2)*BA46),2) -> 0 | CU46: =AG46 -> 0 | CV46: =(AH46*AV46) -> 0 | CW46: =AI46 -> 0 | CX46: =AJ46 -> 0 | CY46: =(ROUND((((S46+ROUND((ROUND(((EU46)*AV46*1),2)*BS46),2))*AT46)/100),2)+ROUND(((ROUND((ROUND(((AE46-(EU46))*AV46*1),2)*BS46),2)*AT46)/100),2)) -> 0 | CZ46: =(ROUND((((S46+ROUND((ROUND(((EU46)*AV46*1),2)*BS46),2))*AU46)/100),2)+ROUND(((ROUND((ROUND(((AE46-(EU46))*AV46*1),2)*BS46),2)*AU46)/100),2)) -> 0 | DN46: 0 | DO46: 0 | DP46: 1 | DQ46: 1 | DU46: 1010 | DV46: шт. | DW46: шт. | DX46: 1 | EE46: 60088531 | EF46: 40 | EG46: Монтаж оборудования | EH46: 0 | EJ46: 2 | EK46: 67 | EL46: ТСН-2001.4-8. Электротехнические установки | EM46: ТСН-2001.4-8-1 | EQ46: 0 | ER46: 3.16 | ES46: 3.16 | ET46: 0 | EU46: 0 | EV46: 0 | EW46: 0 | EX46: 0 | FQ46: 0 | FR46: 0 | FS46: 0 | FX46: 97 | FY46: 51 | GD46: 1 | GF46: -651334041 | GG46: 2 | GH46: 1 | GI46: -2 | GJ46: 0 | GK46: 0 | GL46: =ROUND(IF(AND(BH46=3,BI46=3,FS46<>0),P46,0),2) -> 0 | GM46: =ROUND(O46+X46+Y46,2)+GX46 -> 22.12 | GN46: =IF(OR(BI46=0,BI46=1),GM46-GX46,0) -> 0 | GO46: =IF(BI46=2,GM46-GX46,0) -> 22.12 | GP46: =IF(BI46=4,GM46-GX46,0) -> 0 | GR46: 0 | GS46: 3 | GT46: 0 | GV46: =ROUND((GT46),6) -> 0 | GW46: 1 | GX46: =ROUND(HC46*I46,2) -> 0 | HA46: 0 | HB46: 0 | HC46: =GV46*GW46 -> 0 | HS46: 0 | IK46: 0
A47: 18 | B47: 1 | C47: 77 | E47: 5,1 | F47: 1.14-1-23 | G47: Розетка радиотрансляционная, скрытой установки, типа РПВ-2 (прим. АРС-003) | H47: шт. | I47: =I45*J47 -> 7 | J47: 100 | K47: 100 | O47: =ROUND(CP47,2) -> 625.55 | P47: =ROUND((ROUND((AC47*AW47*I47),2)*BC47),2) -> 625.55 | Q47: =(ROUND((ROUND(((ET47)*AV47*I47),2)*BB47),2)+ROUND((ROUND(((AE47-(EU47))*AV47*I47),2)*BS47),2)) -> 0 | R47: =(ROUND((ROUND(((EU47)*AV47*I47),2)*BS47),2)+ROUND((ROUND(((AE47-(EU47))*AV47*I47),2)*BS47),2)) -> 0 | S47: =ROUND((ROUND((AF47*AV47*I47),2)*BA47),2) -> 0 | T47: =ROUND(CU47*I47,2) -> 0 | U47: =CV47*I47 -> 0 | V47: =CW47*I47 -> 0 | W47: =ROUND(CX47*I47,2) -> 0 | X47: =(ROUND((((S47+ROUND((ROUND(((EU47)*AV47*I47),2)*BS47),2))*AT47)/100),2)+ROUND(((ROUND((ROUND(((AE47-(EU47))*AV47*I47),2)*BS47),2)*AT47)/100),2)) -> 0 | Y47: =(ROUND((((S47+ROUND((ROUND(((EU47)*AV47*I47),2)*BS47),2))*AU47)/100),2)+ROUND(((ROUND((ROUND(((AE47-(EU47))*AV47*I47),2)*BS47),2)*AU47)/100),2)) -> 0 | AA47: 60256982 | AB47: =ROUND((AC47+AD47+AF47),6) -> 3.16 | AC47: =ROUND((ES47),6) -> 3.16 | AD47: =ROUND((((ET47)-(EU47))+AE47),6) -> 0 | AE47: =ROUND((EU47),6) -> 0 | AF47: =ROUND((EV47),6) -> 0 | AG47: =ROUND((AP47),6) -> 0 | AH47: =(EW47) -> 0 | AI47: =(EX47) -> 0 | AJ47: =(AS47) -> 0 | AK47: 3.16 | AL47: 3.16 | AM47: 0 | AN47: 0 | AO47: 0 | AP47: 0 | AQ47: 0 | AR47: 0 | AS47: 0 | AT47: 97 | AU47: 51 | AV47: 1 | AW47: 1 | AZ47: 1 | BA47: 1 | BB47: 1 | BC47: 28.28 | BH47: 3 | BI47: 2 | BJ47: ТСН-2001.1 Доп. 79, Р. 14, о. 1, поз. 23 | BM47: 67 | BN47: 0 | BO47: 1.14-1-23 | BP47: 1 | BQ47: 40 | BR47: 0 | BS47: 1 | BT47: 1 | BU47: 1 | BV47: 1 | BW47: 1 | BX47: 1 | BZ47: 97 | CA47: 51 | CE47: 1566 | CF47: 0 | CG47: 0 | CM47: 0 | CO47: 0 | CP47: =(P47+Q47+S47) -> 625.55 | CQ47: =ROUND((ROUND((AC47*AW47*1),2)*BC47),2) -> 89.36 | CR47: =(ROUND((ROUND(((ET47)*AV47*1),2)*BB47),2)+ROUND((ROUND(((AE47-(EU47))*AV47*1),2)*BS47),2)) -> 0 | CS47: =(ROUND((ROUND(((EU47)*AV47*1),2)*BS47),2)+ROUND((ROUND(((AE47-(EU47))*AV47*1),2)*BS47),2)) -> 0 | CT47: =ROUND((ROUND((AF47*AV47*1),2)*BA47),2) -> 0 | CU47: =AG47 -> 0 | CV47: =(AH47*AV47) -> 0 | CW47: =AI47 -> 0 | CX47: =AJ47 -> 0 | CY47: =(ROUND((((S47+ROUND((ROUND(((EU47)*AV47*1),2)*BS47),2))*AT47)/100),2)+ROUND(((ROUND((ROUND(((AE47-(EU47))*AV47*1),2)*BS47),2)*AT47)/100),2)) -> 0 | CZ47: =(ROUND((((S47+ROUND((ROUND(((EU47)*AV47*1),2)*BS47),2))*AU47)/100),2)+ROUND(((ROUND((ROUND(((AE47-(EU47))*AV47*1),2)*BS47),2)*AU47)/100),2)) -> 0 | DN47: 0 | DO47: 0 | DP47: 1 | DQ47: 1 | DU47: 1010 | DV47: шт. | DW47: шт. | DX47: 1 | EE47: 60088531 | EF47: 40 | EG47: Монтаж оборудования | EH47: 0 | EJ47: 2 | EK47: 67 | EL47: ТСН-2001.4-8. Электротехнические установки | EM47: ТСН-2001.4-8-1 | EQ47: 0 | ER47: 3.16 | ES47: 3.16 | ET47: 0 | EU47: 0 | EV47: 0 | EW47: 0 | EX47: 0 | FQ47: 0 | FR47: 0 | FS47: 0 | FX47: 97 | FY47: 51 | GD47: 1 | GF47: -651334041 | GG47: 2 | GH47: 1 | GI47: 2 | GJ47: 0 | GK47: 0 | GL47: =ROUND(IF(AND(BH47=3,BI47=3,FS47<>0),P47,0),2) -> 0 | GM47: =ROUND(O47+X47+Y47,2)+GX47 -> 625.55 | GN47: =IF(OR(BI47=0,BI47=1),GM47-GX47,0) -> 0 | GO47: =IF(BI47=2,GM47-GX47,0) -> 625.55 | GP47: =IF(BI47=4,GM47-GX47,0) -> 0 | GR47: 0 | GS47: 3 | GT47: 0 | GV47: =ROUND((GT47),6) -> 0 | GW47: 1 | GX47: =ROUND(HC47*I47,2) -> 0 | HA47: 0 | HB47: 0 | HC47: =GV47*GW47 -> 0 | HS47: 0 | IK47: 0
A48: 18 | B48: 1 | C48: 74 | E48: 5,2 | F48: 1.21-5-192 | G48: Коробка, типа КУВ-1М УХЛЗ, для установки выключателей, переключателей и штепсельных розеток при скрытой электропроводке | H48: 1000 шт. | I48: =I44*J48 -> 0.007 | J48: 0.1 | K48: 0.1 | O48: =ROUND(CP48,2) -> 27.35 | P48: =ROUND((ROUND((AC48*AW48*I48),2)*BC48),2) -> 27.35 | Q48: =(ROUND((ROUND(((ET48)*AV48*I48),2)*BB48),2)+ROUND((ROUND(((AE48-(EU48))*AV48*I48),2)*BS48),2)) -> 0 | R48: =(ROUND((ROUND(((EU48)*AV48*I48),2)*BS48),2)+ROUND((ROUND(((AE48-(EU48))*AV48*I48),2)*BS48),2)) -> 0 | S48: =ROUND((ROUND((AF48*AV48*I48),2)*BA48),2) -> 0 | T48: =ROUND(CU48*I48,2) -> 0 | U48: =CV48*I48 -> 0 | V48: =CW48*I48 -> 0 | W48: =ROUND(CX48*I48,2) -> 0 | X48: =(ROUND((((S48+ROUND((ROUND(((EU48)*AV48*I48),2)*BS48),2))*AT48)/100),2)+ROUND(((ROUND((ROUND(((AE48-(EU48))*AV48*I48),2)*BS48),2)*AT48)/100),2)) -> 0 | Y48: =(ROUND((((S48+ROUND((ROUND(((EU48)*AV48*I48),2)*BS48),2))*AU48)/100),2)+ROUND(((ROUND((ROUND(((AE48-(EU48))*AV48*I48),2)*BS48),2)*AU48)/100),2)) -> 0 | AA48: 60256985 | AB48: =ROUND((AC48+AD48+AF48),6) -> 3906.65 | AC48: =ROUND((ES48),6) -> 3906.65 | AD48: =ROUND((((ET48)-(EU48))+AE48),6) -> 0 | AE48: =ROUND((EU48),6) -> 0 | AF48: =ROUND((EV48),6) -> 0 | AG48: =ROUND((AP48),6) -> 0 | AH48: =(EW48) -> 0 | AI48: =(EX48) -> 0 | AJ48: =(AS48) -> 0 | AK48: 3906.65 | AL48: 3906.65 | AM48: 0 | AN48: 0 | AO48: 0 | AP48: 0 | AQ48: 0 | AR48: 0 | AS48: 0 | AT48: 97 | AU48: 51 | AV48: 1 | AW48: 1 | AZ48: 1 | BA48: 1 | BB48: 1 | BC48: 1 | BH48: 3 | BI48: 2 | BJ48: ТСН-2001.1 Доп. 79, Р. 21, о. 5, поз. 192 | BM48: 67 | BN48: 0 | BP48: 0 | BQ48: 40 | BR48: 0 | BS48: 1 | BT48: 1 | BU48: 1 | BV48: 1 | BW48: 1 | BX48: 1 | BZ48: 97 | CA48: 51 | CE48: 1566 | CF48: 0 | CG48: 0 | CM48: 0 | CO48: 0 | CP48: =(P48+Q48+S48) -> 27.35 | CQ48: =ROUND((ROUND((AC48*AW48*1),2)*BC48),2) -> 3906.65 | CR48: =(ROUND((ROUND(((ET48)*AV48*1),2)*BB48),2)+ROUND((ROUND(((AE48-(EU48))*AV48*1),2)*BS48),2)) -> 0 | CS48: =(ROUND((ROUND(((EU48)*AV48*1),2)*BS48),2)+ROUND((ROUND(((AE48-(EU48))*AV48*1),2)*BS48),2)) -> 0 | CT48: =ROUND((ROUND((AF48*AV48*1),2)*BA48),2) -> 0 | CU48: =AG48 -> 0 | CV48: =(AH48*AV48) -> 0 | CW48: =AI48 -> 0 | CX48: =AJ48 -> 0 | CY48: =(ROUND((((S48+ROUND((ROUND(((EU48)*AV48*1),2)*BS48),2))*AT48)/100),2)+ROUND(((ROUND((ROUND(((AE48-(EU48))*AV48*1),2)*BS48),2)*AT48)/100),2)) -> 0 | CZ48: =(ROUND((((S48+ROUND((ROUND(((EU48)*AV48*1),2)*BS48),2))*AU48)/100),2)+ROUND(((ROUND((ROUND(((AE48-(EU48))*AV48*1),2)*BS48),2)*AU48)/100),2)) -> 0 | DN48: 0 | DO48: 0 | DP48: 1 | DQ48: 1 | DU48: 1010 | DV48: 1000 шт. | DW48: 1000 шт. | DX48: 1000 | EE48: 60088531 | EF48: 40 | EG48: Монтаж оборудования | EH48: 0 | EJ48: 2 | EK48: 67 | EL48: ТСН-2001.4-8. Электротехнические установки | EM48: ТСН-2001.4-8-1 | EQ48: 0 | ER48: 3906.65 | ES48: 3906.65 | ET48: 0 | EU48: 0 | EV48: 0 | EW48: 0 | EX48: 0 | FQ48: 0 | FR48: 0 | FS48: 0 | FX48: 97 | FY48: 51 | GD48: 1 | GF48: -436372382 | GG48: 2 | GH48: 1 | GI48: -2 | GJ48: 0 | GK48: 0 | GL48: =ROUND(IF(AND(BH48=3,BI48=3,FS48<>0),P48,0),2) -> 0 | GM48: =ROUND(O48+X48+Y48,2)+GX48 -> 27.35 | GN48: =IF(OR(BI48=0,BI48=1),GM48-GX48,0) -> 0 | GO48: =IF(BI48=2,GM48-GX48,0) -> 27.35 | GP48: =IF(BI48=4,GM48-GX48,0) -> 0 | GR48: 0 | GS48: 3 | GT48: 0 | GV48: =ROUND((GT48),6) -> 0 | GW48: 1 | GX48: =ROUND(HC48*I48,2) -> 0 | HA48: 0 | HB48: 0 | HC48: =GV48*GW48 -> 0 | HS48: 0 | IK48: 0
A49: 18 | B49: 1 | C49: 78 | E49: 5,2 | F49: 1.21-5-192 | G49: Коробка, типа КУВ-1М УХЛЗ, для установки выключателей, переключателей и штепсельных розеток при скрытой электропроводке | H49: 1000 шт. | I49: =I45*J49 -> 0.007 | J49: 0.1 | K49: 0.1 | O49: =ROUND(CP49,2) -> 369.77 | P49: =ROUND((ROUND((AC49*AW49*I49),2)*BC49),2) -> 369.77 | Q49: =(ROUND((ROUND(((ET49)*AV49*I49),2)*BB49),2)+ROUND((ROUND(((AE49-(EU49))*AV49*I49),2)*BS49),2)) -> 0 | R49: =(ROUND((ROUND(((EU49)*AV49*I49),2)*BS49),2)+ROUND((ROUND(((AE49-(EU49))*AV49*I49),2)*BS49),2)) -> 0 | S49: =ROUND((ROUND((AF49*AV49*I49),2)*BA49),2) -> 0 | T49: =ROUND(CU49*I49,2) -> 0 | U49: =CV49*I49 -> 0 | V49: =CW49*I49 -> 0 | W49: =ROUND(CX49*I49,2) -> 0 | X49: =(ROUND((((S49+ROUND((ROUND(((EU49)*AV49*I49),2)*BS49),2))*AT49)/100),2)+ROUND(((ROUND((ROUND(((AE49-(EU49))*AV49*I49),2)*BS49),2)*AT49)/100),2)) -> 0 | Y49: =(ROUND((((S49+ROUND((ROUND(((EU49)*AV49*I49),2)*BS49),2))*AU49)/100),2)+ROUND(((ROUND((ROUND(((AE49-(EU49))*AV49*I49),2)*BS49),2)*AU49)/100),2)) -> 0 | AA49: 60256982 | AB49: =ROUND((AC49+AD49+AF49),6) -> 3906.65 | AC49: =ROUND((ES49),6) -> 3906.65 | AD49: =ROUND((((ET49)-(EU49))+AE49),6) -> 0 | AE49: =ROUND((EU49),6) -> 0 | AF49: =ROUND((EV49),6) -> 0 | AG49: =ROUND((AP49),6) -> 0 | AH49: =(EW49) -> 0 | AI49: =(EX49) -> 0 | AJ49: =(AS49) -> 0 | AK49: 3906.65 | AL49: 3906.65 | AM49: 0 | AN49: 0 | AO49: 0 | AP49: 0 | AQ49: 0 | AR49: 0 | AS49: 0 | AT49: 97 | AU49: 51 | AV49: 1 | AW49: 1 | AZ49: 1 | BA49: 1 | BB49: 1 | BC49: 13.52 | BH49: 3 | BI49: 2 | BJ49: ТСН-2001.1 Доп. 79, Р. 21, о. 5, поз. 192 | BM49: 67 | BN49: 0 | BO49: 1.21-5-192 | BP49: 1 | BQ49: 40 | BR49: 0 | BS49: 1 | BT49: 1 | BU49: 1 | BV49: 1 | BW49: 1 | BX49: 1 | BZ49: 97 | CA49: 51 | CE49: 1566 | CF49: 0 | CG49: 0 | CM49: 0 | CO49: 0 | CP49: =(P49+Q49+S49) -> 369.77 | CQ49: =ROUND((ROUND((AC49*AW49*1),2)*BC49),2) -> 52817.91 | CR49: =(ROUND((ROUND(((ET49)*AV49*1),2)*BB49),2)+ROUND((ROUND(((AE49-(EU49))*AV49*1),2)*BS49),2)) -> 0 | CS49: =(ROUND((ROUND(((EU49)*AV49*1),2)*BS49),2)+ROUND((ROUND(((AE49-(EU49))*AV49*1),2)*BS49),2)) -> 0 | CT49: =ROUND((ROUND((AF49*AV49*1),2)*BA49),2) -> 0 | CU49: =AG49 -> 0 | CV49: =(AH49*AV49) -> 0 | CW49: =AI49 -> 0 | CX49: =AJ49 -> 0 | CY49: =(ROUND((((S49+ROUND((ROUND(((EU49)*AV49*1),2)*BS49),2))*AT49)/100),2)+ROUND(((ROUND((ROUND(((AE49-(EU49))*AV49*1),2)*BS49),2)*AT49)/100),2)) -> 0 | CZ49: =(ROUND((((S49+ROUND((ROUND(((EU49)*AV49*1),2)*BS49),2))*AU49)/100),2)+ROUND(((ROUND((ROUND(((AE49-(EU49))*AV49*1),2)*BS49),2)*AU49)/100),2)) -> 0 | DN49: 0 | DO49: 0 | DP49: 1 | DQ49: 1 | DU49: 1010 | DV49: 1000 шт. | DW49: 1000 шт. | DX49: 1000 | EE49: 60088531 | EF49: 40 | EG49: Монтаж оборудования | EH49: 0 | EJ49: 2 | EK49: 67 | EL49: ТСН-2001.4-8. Электротехнические установки | EM49: ТСН-2001.4-8-1 | EQ49: 0 | ER49: 3906.65 | ES49: 3906.65 | ET49: 0 | EU49: 0 | EV49: 0 | EW49: 0 | EX49: 0 | FQ49: 0 | FR49: 0 | FS49: 0 | FX49: 97 | FY49: 51 | GD49: 1 | GF49: -436372382 | GG49: 2 | GH49: 1 | GI49: 2 | GJ49: 0 | GK49: 0 | GL49: =ROUND(IF(AND(BH49=3,BI49=3,FS49<>0),P49,0),2) -> 0 | GM49: =ROUND(O49+X49+Y49,2)+GX49 -> 369.77 | GN49: =IF(OR(BI49=0,BI49=1),GM49-GX49,0) -> 0 | GO49: =IF(BI49=2,GM49-GX49,0) -> 369.77 | GP49: =IF(BI49=4,GM49-GX49,0) -> 0 | GR49: 0 | GS49: 3 | GT49: 0 | GV49: =ROUND((GT49),6) -> 0 | GW49: 1 | GX49: =ROUND(HC49*I49,2) -> 0 | HA49: 0 | HB49: 0 | HC49: =GV49*GW49 -> 0 | HS49: 0 | IK49: 0
A51: 51 | B51: =B24 -> 1 | C51: =A24 -> 4 | D51: =ROW(A24) -> 24 | F51: =IF(F24<>"",F24,"") | G51: =IF(G24<>"",G24,"") -> Оборудование | H51: 0 | O51: =ROUND(AB51,2) -> 175166.44 | P51: =ROUND(AC51,2) -> 174472.47 | Q51: =ROUND(AD51,2) -> 10.49 | R51: =ROUND(AE51,2) -> 0.98 | S51: =ROUND(AF51,2) -> 683.48 | T51: =ROUND(AG51,2) -> 0 | U51: =AH51 -> 52.573723 | V51: =AI51 -> 0 | W51: =ROUND(AJ51,2) -> 0 | X51: =ROUND(AK51,2) -> 642.97 | Y51: =ROUND(AL51,2) -> 351.77 | AB51: =ROUND(SUMIF(AA28:AA49,"=60256985",O28:O49),2) -> 175166.44 | AC51: =ROUND(SUMIF(AA28:AA49,"=60256985",P28:P49),2) -> 174472.47 | AD51: =ROUND(SUMIF(AA28:AA49,"=60256985",Q28:Q49),2) -> 10.49 | AE51: =ROUND(SUMIF(AA28:AA49,"=60256985",R28:R49),2) -> 0.98 | AF51: =ROUND(SUMIF(AA28:AA49,"=60256985",S28:S49),2) -> 683.48 | AG51: =ROUND(SUMIF(AA28:AA49,"=60256985",T28:T49),2) -> 0 | AH51: =SUMIF(AA28:AA49,"=60256985",U28:U49) -> 52.573723 | AI51: =SUMIF(AA28:AA49,"=60256985",V28:V49) -> 0 | AJ51: =ROUND(SUMIF(AA28:AA49,"=60256985",W28:W49),2) -> 0 | AK51: =ROUND(SUMIF(AA28:AA49,"=60256985",X28:X49),2) -> 642.97 | AL51: =ROUND(SUMIF(AA28:AA49,"=60256985",Y28:Y49),2) -> 351.77 | AO51: =ROUND(BX51,2) -> 0 | AP51: =ROUND(BY51,2) -> 174167.53 | AQ51: =ROUND(BZ51,2) -> 0 | AR51: =ROUND(CA51,2) -> 176161.18 | AS51: =ROUND(CB51,2) -> 0 | AT51: =ROUND(CC51,2) -> 1993.65 | AU51: =ROUND(CD51,2) -> 0 | AV51: =ROUND(CE51,2) -> 174472.47 | ... BD51: =ROUND(CM51,2) -> 0 | BX51: =ROUND(SUMIF(AA28:AA49,"=60256985",FQ28:FQ49),2) -> 0 | BY51: =ROUND(SUMIF(AA28:AA49,"=60256985",FR28:FR49),2) -> 174167.53 | BZ51: =ROUND(SUMIF(AA28:AA49,"=60256985",GL28:GL49),2) -> 0 | CA51: =ROUND(SUMIF(AA28:AA49,"=60256985",GM28:GM49),2) -> 176161.18 | CB51: =ROUND(SUMIF(AA28:AA49,"=60256985",GN28:GN49),2) -> 0 | CC51: =ROUND(SUMIF(AA28:AA49,"=60256985",GO28:GO49),2) -> 1993.65 | CD51: =ROUND(SUMIF(AA28:AA49,"=60256985",GP28:GP49),2) -> 0 | CE51: =AC51-BX51 -> 174472.47 | CF51: =AC51-BY51 -> 304.94 | CG51: =BX51-BZ51 -> 0 | CH51: =AC51-BX51-BY51+BZ51 -> 304.94 | CI51: =BY51-BZ51 -> 174167.53 | CJ51: =ROUND(SUMIF(AA28:AA49,"=60256985",GX28:GX49),2) -> 0 | CK51: =ROUND(SUMIF(AA28:AA49,"=60256985",GY28:GY49),2) -> 0 | CL51: =ROUND(SUMIF(AA28:AA49,"=60256985",GZ28:GZ49),2) -> 0 | CM51: =ROUND(SUMIF(AA28:AA49,"=60256985",HD28:HD49),2) -> 0 | DG51: =ROUND(DT51,2) -> 1374458.7 | DH51: =ROUND(DU51,2) -> 1336724.9 | DI51: =ROUND(DV51,2) -> 149.21 | DJ51: =ROUND(DW51,2) -> 53.9 | DK51: =ROUND(DX51,2) -> 37584.57 | DL51: =ROUND(DY51,2) -> 0 | DM51: =DZ51 -> 52.573723 | DN51: =EA51 -> 0 | DO51: =ROUND(EB51,2) -> 0 | DP51: =ROUND(EC51,2) -> 35357.01 | DQ51: =ROUND(ED51,2) -> 19344.17 | DT51: =ROUND(SUMIF(AA28:AA49,"=60256982",O28:O49),2) -> 1374458.7 | DU51: =ROUND(SUMIF(AA28:AA49,"=60256982",P28:P49),2) -> 1336724.9 | DV51: =ROUND(SUMIF(AA28:AA49,"=60256982",Q28:Q49),2) -> 149.21 | DW51: =ROUND(SUMIF(AA28:AA49,"=60256982",R28:R49),2) -> 53.9 | DX51: =ROUND(SUMIF(AA28:AA49,"=60256982",S28:S49),2) -> 37584.57 | DY51: =ROUND(SUMIF(AA28:AA49,"=60256982",T28:T49),2) -> 0 | DZ51: =SUMIF(AA28:AA49,"=60256982",U28:U49) -> 52.573723 | EA51: =SUMIF(AA28:AA49,"=60256982",V28:V49) -> 0 | EB51: =ROUND(SUMIF(AA28:AA49,"=60256982",W28:W49),2) -> 0 | EC51: =ROUND(SUMIF(AA28:AA49,"=60256982",X28:X49),2) -> 35357.01 | ED51: =ROUND(SUMIF(AA28:AA49,"=60256982",Y28:Y49),2) -> 19344.17 | EG51: =ROUND(FP51,2) -> 0 | EH51: =ROUND(FQ51,2) -> 1334123.3 | EI51: =ROUND(FR51,2) -> 0 | EJ51: =ROUND(FS51,2) -> 1429159.9 | EK51: =ROUND(FT51,2) -> 0 | EL51: =ROUND(FU51,2) -> 95036.61 | EM51: =ROUND(FV51,2) -> 0 | EN51: =ROUND(FW51,2) -> 1336724.9 | ... EV51: =ROUND(GE51,2) -> 0 | FP51: =ROUND(SUMIF(AA28:AA49,"=60256982",FQ28:FQ49),2) -> 0 | FQ51: =ROUND(SUMIF(AA28:AA49,"=60256982",FR28:FR49),2) -> 1334123.3 | FR51: =ROUND(SUMIF(AA28:AA49,"=60256982",GL28:GL49),2) -> 0 | FS51: =ROUND(SUMIF(AA28:AA49,"=60256982",GM28:GM49),2) -> 1429159.9 | FT51: =ROUND(SUMIF(AA28:AA49,"=60256982",GN28:GN49),2) -> 0 | FU51: =ROUND(SUMIF(AA28:AA49,"=60256982",GO28:GO49),2) -> 95036.61 | FV51: =ROUND(SUMIF(AA28:AA49,"=60256982",GP28:GP49),2) -> 0 | FW51: =DU51-FP51 -> 1336724.9 | FX51: =DU51-FQ51 -> 2601.65 | FY51: =FP51-FR51 -> 0 | FZ51: =DU51-FP51-FQ51+FR51 -> 2601.65 | GA51: =FQ51-FR51 -> 1334123.3 | GB51: =ROUND(SUMIF(AA28:AA49,"=60256982",GX28:GX49),2) -> 0 | GC51: =ROUND(SUMIF(AA28:AA49,"=60256982",GY28:GY49),2) -> 0 | GD51: =ROUND(SUMIF(AA28:AA49,"=60256982",GZ28:GZ49),2) -> 0 | GE51: =ROUND(SUMIF(AA28:AA49,"=60256982",HD28:HD49),2) -> 0 | GX51: 0
A53: 50 | B53: 0 | C53: 0 | D53: 1 | E53: 201 | F53: =ROUND(Source!O51,O53) -> 175166.44 | G53: ПЗ | H53: Прямые затраты | K53: 201 | L53: 1 | M53: 3 | O53: 2 | P53: =ROUND(Source!DG51,O53) -> 1374458.7 | W53: 175166.44 | X53: 1 | Y53: 175166.44 | Z53: 1374458.7 | AA53: 1 | AB53: 1374458.7
A54: 50 | B54: 0 | C54: 0 | D54: 1 | E54: 202 | F54: =ROUND(Source!P51,O54) -> 174472.47 | G54: СтМатОб | H54: Стоимость материальных ресурсов (всего) | K54: 202 | L54: 2 | M54: 3 | O54: 2 | P54: =ROUND(Source!DH51,O54) -> 1336724.9 | W54: 174472.47 | X54: 1 | Y54: 174472.47 | Z54: 1336724.9 | AA54: 1 | AB54: 1336724.9
A55: 50 | B55: 0 | C55: 0 | D55: 1 | E55: 222 | F55: =ROUND(Source!AO51,O55) -> 0 | G55: СтМатОбЗак | H55: Стоимость материалов и оборудования заказчика | K55: 222 | L55: 3 | M55: 3 | O55: 2 | P55: =ROUND(Source!EG51,O55) -> 0 | W55: 0 | X55: 1 | Y55: 0 | Z55: 0 | AA55: 1 | AB55: 0
A56: 50 | B56: 0 | C56: 0 | D56: 1 | E56: 225 | F56: =ROUND(Source!AV51,O56) -> 174472.47 | G56: СтМатОбПод | H56: Стоимость материалов и оборудования подрядчика | K56: 225 | L56: 4 | M56: 3 | O56: 2 | P56: =ROUND(Source!EN51,O56) -> 1336724.9 | W56: 174472.47 | X56: 1 | Y56: 174472.47 | Z56: 1336724.9 | AA56: 1 | AB56: 1336724.9
A57: 50 | B57: 0 | C57: 0 | D57: 1 | E57: 226 | F57: =ROUND(Source!AW51,O57) -> 304.94 | G57: СтМат | H57: Стоимость материалов (всего) | K57: 226 | L57: 5 | M57: 3 | O57: 2 | P57: =ROUND(Source!EO51,O57) -> 2601.65 | W57: 304.94 | X57: 1 | Y57: 304.94 | Z57: 2601.65 | AA57: 1 | AB57: 2601.65
A58: 50 | B58: 0 | C58: 0 | D58: 1 | E58: 227 | F58: =ROUND(Source!AX51,O58) -> 0 | G58: СтМатЗак | H58: Стоимость материалов заказчика | K58: 227 | L58: 6 | M58: 3 | O58: 2 | P58: =ROUND(Source!EP51,O58) -> 0 | W58: 0 | X58: 1 | Y58: 0 | Z58: 0 | AA58: 1 | AB58: 0
A59: 50 | B59: 0 | C59: 0 | D59: 1 | E59: 228 | F59: =ROUND(Source!AY51,O59) -> 304.94 | G59: СтМатПод | H59: Стоимость материалов подрядчика | K59: 228 | L59: 7 | M59: 3 | O59: 2 | P59: =ROUND(Source!EQ51,O59) -> 2601.65 | W59: 304.94 | X59: 1 | Y59: 304.94 | Z59: 2601.65 | AA59: 1 | AB59: 2601.65
A60: 50 | B60: 0 | C60: 0 | D60: 1 | E60: 216 | F60: =ROUND(Source!AP51,O60) -> 174167.53 | G60: Оборуд | H60: Стоимость оборудования (всего) | K60: 216 | L60: 8 | M60: 3 | O60: 2 | P60: =ROUND(Source!EH51,O60) -> 1334123.3 | W60: 174167.53 | X60: 1 | Y60: 174167.53 | Z60: 1334123.3 | AA60: 1 | AB60: 1334123.3
A61: 50 | B61: 0 | C61: 0 | D61: 1 | E61: 223 | F61: =ROUND(Source!AQ51,O61) -> 0 | G61: ОборудЗак | H61: Стоимость оборудования заказчика | K61: 223 | L61: 9 | M61: 3 | O61: 2 | P61: =ROUND(Source!EI51,O61) -> 0 | W61: 0 | X61: 1 | Y61: 0 | Z61: 0 | AA61: 1 | AB61: 0
A62: 50 | B62: 0 | C62: 0 | D62: 1 | E62: 229 | F62: =ROUND(Source!AZ51,O62) -> 174167.53 | G62: ОборудПод | H62: Стоимость оборудования подрядчика | K62: 229 | L62: 10 | M62: 3 | O62: 2 | P62: =ROUND(Source!ER51,O62) -> 1334123.3 | W62: 174167.53 | X62: 1 | Y62: 174167.53 | Z62: 1334123.3 | AA62: 1 | AB62: 1334123.3
A63: 50 | B63: 0 | C63: 0 | D63: 1 | E63: 203 | F63: =ROUND(Source!Q51,O63) -> 10.49 | G63: ЭММ | H63: Эксплуатация машин | K63: 203 | L63: 11 | M63: 3 | O63: 2 | P63: =ROUND(Source!DI51,O63) -> 149.21 | W63: 10.49 | X63: 1 | Y63: 10.49 | Z63: 149.21 | AA63: 1 | AB63: 149.21
A64: 50 | B64: 0 | C64: 0 | D64: 1 | E64: 231 | F64: =ROUND(Source!BB51,O64) -> 0 | G64: ЭММсНРиСП | H64: Эксплуатация машин по ТСН-2001.16 | K64: 231 | L64: 12 | M64: 3 | O64: 2 | P64: =ROUND(Source!ET51,O64) -> 0 | W64: 0 | X64: 1 | Y64: 0 | Z64: 0 | AA64: 1 | AB64: 0
A65: 50 | B65: 0 | C65: 0 | D65: 1 | E65: 204 | F65: =ROUND(Source!R51,O65) -> 0.98 | G65: ЗПМ | H65: ЗП машинистов | K65: 204 | L65: 13 | M65: 3 | O65: 2 | P65: =ROUND(Source!DJ51,O65) -> 53.9 | W65: 0.98 | X65: 1 | Y65: 0.98 | Z65: 53.9 | AA65: 1 | AB65: 53.9
A66: 50 | B66: 0 | C66: 0 | D66: 1 | E66: 205 | F66: =ROUND(Source!S51,O66) -> 683.48 | G66: ОЗП | H66: Основная ЗП рабочих | K66: 205 | L66: 14 | M66: 3 | O66: 2 | P66: =ROUND(Source!DK51,O66) -> 37584.57 | W66: 683.48 | X66: 1 | Y66: 683.48 | Z66: 37584.57 | AA66: 1 | AB66: 37584.57
A67: 50 | B67: 0 | C67: 0 | D67: 1 | E67: 232 | F67: =ROUND(Source!BC51,O67) -> 0 | G67: ОЗПсНРиСП | H67: Основная ЗП рабочих по ТСН-2001.16 | K67: 232 | L67: 15 | M67: 3 | O67: 2 | P67: =ROUND(Source!EU51,O67) -> 0 | W67: 0 | X67: 1 | Y67: 0 | Z67: 0 | AA67: 1 | AB67: 0
A68: 50 | B68: 0 | C68: 0 | D68: 1 | E68: 214 | F68: =ROUND(Source!AS51,O68) -> 0 | G68: Строит | H68: Строительные работы с НР и СП | K68: 214 | L68: 16 | M68: 3 | O68: 2 | P68: =ROUND(Source!EK51,O68) -> 0 | W68: 0 | X68: 1 | Y68: 0 | Z68: 0 | AA68: 1 | AB68: 0
A69: 50 | B69: 0 | C69: 0 | D69: 1 | E69: 215 | F69: =ROUND(Source!AT51,O69) -> 1993.65 | G69: Монтаж | H69: Монтажные работы с НР и СП | K69: 215 | L69: 17 | M69: 3 | O69: 2 | P69: =ROUND(Source!EL51,O69) -> 95036.61 | W69: 1993.65 | X69: 1 | Y69: 1993.65 | Z69: 95036.61 | AA69: 1 | AB69: 95036.61
A70: 50 | B70: 0 | C70: 0 | D70: 1 | E70: 217 | F70: =ROUND(Source!AU51,O70) -> 0 | G70: Прочие | H70: Прочие работы с НР и СП | K70: 217 | L70: 18 | M70: 3 | O70: 2 | P70: =ROUND(Source!EM51,O70) -> 0 | W70: 0 | X70: 1 | Y70: 0 | Z70: 0 | AA70: 1 | AB70: 0
A71: 50 | B71: 0 | C71: 0 | D71: 1 | E71: 230 | F71: =ROUND(Source!BA51,O71) -> 0 | G71: ПрочиеЗатр | H71: Прочие затраты по ТСН-2001.16 | K71: 230 | L71: 19 | M71: 3 | O71: 2 | P71: =ROUND(Source!ES51,O71) -> 0 | W71: 0 | X71: 1 | Y71: 0 | Z71: 0 | AA71: 1 | AB71: 0
A72: 50 | B72: 0 | C72: 0 | D72: 1 | E72: 206 | F72: =ROUND(Source!T51,O72) -> 0 | G72: ВозврМат | H72: Возврат материалов | K72: 206 | L72: 20 | M72: 3 | O72: 2 | P72: =ROUND(Source!DL51,O72) -> 0 | W72: 0 | X72: 1 | Y72: 0 | Z72: 0 | AA72: 1 | AB72: 0
A73: 50 | B73: 0 | C73: 0 | D73: 1 | E73: 207 | F73: =Source!U51 -> 52.573723 | G73: ТрудСтр | H73: Трудозатраты строителей | K73: 207 | L73: 21 | M73: 3 | O73: -1 | P73: =Source!DM51 -> 52.573723 | W73: 52.573723 | X73: 1 | Y73: 52.573723 | Z73: 52.573723 | AA73: 1 | AB73: 52.573723
A74: 50 | B74: 0 | C74: 0 | D74: 1 | E74: 208 | F74: =Source!V51 -> 0 | G74: ТрудМаш | H74: Трудозатраты машинистов | K74: 208 | L74: 22 | M74: 3 | O74: -1 | P74: =Source!DN51 -> 0 | W74: 0 | X74: 1 | Y74: 0 | Z74: 0 | AA74: 1 | AB74: 0
A75: 50 | B75: 0 | C75: 0 | D75: 1 | E75: 209 | F75: =ROUND(Source!W51,O75) -> 0 | G75: ТранспМат | H75: Транспорт материалов | K75: 209 | L75: 23 | M75: 3 | O75: 2 | P75: =ROUND(Source!DO51,O75) -> 0 | W75: 0 | X75: 1 | Y75: 0 | Z75: 0 | AA75: 1 | AB75: 0
A76: 50 | B76: 0 | C76: 0 | D76: 1 | E76: 233 | F76: =ROUND(Source!BD51,O76) -> 0 | G76: Перевозка | H76: Перевозка грузов | K76: 233 | L76: 24 | M76: 3 | O76: 2 | P76: =ROUND(Source!EV51,O76) -> 0 | W76: 0 | X76: 1 | Y76: 0 | Z76: 0 | AA76: 1 | AB76: 0
A77: 50 | B77: 0 | C77: 0 | D77: 1 | E77: 210 | F77: =ROUND(Source!X51,O77) -> 642.97 | G77: НР | H77: Накладные расходы | K77: 210 | L77: 25 | M77: 3 | O77: 2 | P77: =ROUND(Source!DP51,O77) -> 35357.01 | W77: 642.97 | X77: 1 | Y77: 642.97 | Z77: 35357.01 | AA77: 1 | AB77: 35357.01
A78: 50 | B78: 0 | C78: 0 | D78: 1 | E78: 211 | F78: =ROUND(Source!Y51,O78) -> 351.77 | G78: СмПриб | H78: Сметная прибыль | K78: 211 | L78: 26 | M78: 3 | O78: 2 | P78: =ROUND(Source!DQ51,O78) -> 19344.17 | W78: 351.77 | X78: 1 | Y78: 351.77 | Z78: 19344.17 | AA78: 1 | AB78: 19344.17
A79: 50 | B79: 0 | C79: 0 | D79: 1 | E79: 224 | F79: =ROUND(Source!AR51,O79) -> 176161.18 | G79: Всего | H79: Всего с НР и СП | K79: 224 | L79: 27 | M79: 3 | O79: 2 | P79: =ROUND(Source!EJ51,O79) -> 1429159.9 | W79: 176161.18 | X79: 1 | Y79: 176161.18 | Z79: 1429159.9 | AA79: 1 | AB79: 1429159.9
A81: 4 | B81: 1 | D81: =ROW(A116) -> 116 | G81: Кабельные изделия | I81: 0 | K81: -1 | S81: 0 | T81: 0 | V81: 2 | BX81: 0 | CJ81: 0
A83: 52 | B83: =B116 -> 1 | C83: =C116 -> 4 | D83: =D116 -> 81 | E83: =E116 -> 0 | F83: =F116 | G83: =G116 -> Кабельные изделия | O83: =O116 -> 8376.25 | P83: =P116 -> 7374.74 | Q83: =Q116 -> 146.88 | R83: =R116 -> 17.03 | S83: =S116 -> 854.63 | T83: =T116 -> 0 | U83: =U116 -> 68.01134 | V83: =V116 -> 0 | ... GX83: =GX116 -> 0
A85: 17 | B85: 1 | C85: =ROW(SmtRes!A81) -> 81 | D85: =ROW(EtalonRes!A80) -> 80 | E85: 6 | F85: 4.8-288-2 | G85: Трубы гофрированные поливинилхлоридные наружным диаметром 20 мм открыто по стенам и потолкам с установкой соединительных коробок | H85: 100 м | I85: =ROUND(200/100,9) -> 2 | J85: 0 | K85: =ROUND(200/100,9) -> 2 | O85: =ROUND(CP85,2) -> 1147.14 | P85: =ROUND((ROUND((AC85*AW85*I85),2)*BC85),2) -> 628.58 | Q85: =(ROUND((ROUND((((ET85*1.1))*AV85*I85),2)*BB85),2)+ROUND((ROUND(((AE85-((EU85*1.1)))*AV85*I85),2)*BS85),2)) -> 75.71 | R85: =(ROUND((ROUND((((EU85*1.1))*AV85*I85),2)*BS85),2)+ROUND((ROUND(((AE85-((EU85*1.1)))*AV85*I85),2)*BS85),2)) -> 13.15 | S85: =ROUND((ROUND((AF85*AV85*I85),2)*BA85),2) -> 442.85 | T85: =ROUND(CU85*I85,2) -> 0 | U85: =CV85*I85 -> 34.551 | V85: =CW85*I85 -> 0 | W85: =ROUND(CX85*I85,2) -> 0 | X85: =(ROUND((((S85+ROUND((ROUND((((EU85*1.1))*AV85*I85),2)*BS85),2))*AT85)/100),2)+ROUND(((ROUND((ROUND(((AE85-((EU85*1.1)))*AV85*I85),2)*BS85),2)*AT85)/100),2)) -> 442.32 | Y85: =(ROUND((((S85+ROUND((ROUND((((EU85*1.1))*AV85*I85),2)*BS85),2))*AU85)/100),2)+ROUND(((ROUND((ROUND(((AE85-((EU85*1.1)))*AV85*I85),2)*BS85),2)*AU85)/100),2)) -> 232.56 | AA85: 60256985 | AB85: =ROUND((AC85+AD85+AF85),6) -> 561.933 | AC85: =ROUND((ES85),6) -> 314.29 | AD85: =ROUND(((((ET85*1.1))-((EU85*1.1)))+AE85),6) -> 36.157 | AE85: =ROUND(((EU85*1.1)),6) -> 6.281 | AF85: =ROUND(((EV85*1.1)),6) -> 211.486 | AG85: =ROUND((AP85),6) -> 0 | AH85: =((EW85*1.1)) -> 16.5 | AI85: =((EX85*1.1)) -> 0 | AJ85: =(AS85) -> 0 | AK85: 539.42 | AL85: 314.29 | AM85: 32.87 | AN85: 5.71 | AO85: 192.26 | AP85: 0 | AQ85: 15 | AR85: 0 | AS85: 0 | AT85: 97 | AU85: 51 | AV85: 1.047 | AW85: 1 | AZ85: 1 | BA85: 1 | BB85: 1 | BC85: 1 | BH85: 0 | BI85: 2 | BJ85: ТСН-2001.4 Доп. 54, Сб. 8, т. 288, поз. 2 | BM85: 67 | BN85: 58973116 | BO85: 4.8-288-2 | BP85: 1 | BQ85: 40 | BR85: 0 | BS85: 1 | BT85: 1 | BU85: 1 | BV85: 1 | BW85: 1 | BX85: 1 | BZ85: 97 | CA85: 51 | CE85: 1566 | CF85: 0 | CG85: 0 | CM85: 0 | CN85: Поправка: О.П. п.3.4.30.в Наименование: При применении территориальных сметных нормативов для города Москвы затраты, учитывающие напряженные и стесненные условия производства работ (стесненность, сложность складирования и транспортной логистики и т.п.), исчисляются с применением коэффициентов к затратам труда и заработной плате рабочих, машинистов, времени эксплуатации машин и механизмов, стоимости эксплуатации машин в размере: для объектов, расположенных за пределами Третьего транспортного кольца города Москвы, но в пределах Московской кольцевой автомобильной дороги | CO85: 0 | CP85: =(P85+Q85+S85) -> 1147.14 | CQ85: =ROUND((ROUND((AC85*AW85*1),2)*BC85),2) -> 314.29 | CR85: =(ROUND((ROUND((((ET85*1.1))*AV85*1),2)*BB85),2)+ROUND((ROUND(((AE85-((EU85*1.1)))*AV85*1),2)*BS85),2)) -> 37.86 | CS85: =(ROUND((ROUND((((EU85*1.1))*AV85*1),2)*BS85),2)+ROUND((ROUND(((AE85-((EU85*1.1)))*AV85*1),2)*BS85),2)) -> 6.58 | CT85: =ROUND((ROUND((AF85*AV85*1),2)*BA85),2) -> 221.43 | CU85: =AG85 -> 0 | CV85: =(AH85*AV85) -> 17.2755 | CW85: =AI85 -> 0 | CX85: =AJ85 -> 0 | CY85: =(ROUND((((S85+ROUND((ROUND((((EU85*1.1))*AV85*1),2)*BS85),2))*AT85)/100),2)+ROUND(((ROUND((ROUND(((AE85-((EU85*1.1)))*AV85*1),2)*BS85),2)*AT85)/100),2)) -> 435.95 | CZ85: =(ROUND((((S85+ROUND((ROUND((((EU85*1.1))*AV85*1),2)*BS85),2))*AU85)/100),2)+ROUND(((ROUND((ROUND(((AE85-((EU85*1.1)))*AV85*1),2)*BS85),2)*AU85)/100),2)) -> 229.21 | DB85: 11 | DE85: *1,1 | DF85: *1,1 | DG85: *1,1 | DI85: *1,1 | DJ85: *1,1 | DN85: 0 | DO85: 0 | DP85: 1 | DQ85: 1 | DU85: 1003 | DV85: 100 м | DW85: 100 м | DX85: 100 | EE85: 60088531 | EF85: 40 | EG85: Монтаж оборудования | EH85: 0 | EJ85: 2 | EK85: 67 | EL85: ТСН-2001.4-8. Электротехнические установки | EM85: ТСН-2001.4-8-1 | EO85: Поправка: О.П. п.3.4.30.в | EQ85: 0 | ER85: 539.42 | ES85: 314.29 | ET85: 32.87 | EU85: 5.71 | EV85: 192.26 | EW85: 15 | EX85: 0 | EY85: 0 | FQ85: 0 | FR85: 0 | FS85: 0 | FX85: 97 | FY85: 51 | GD85: 1 | GF85: 1705749599 | GG85: 2 | GH85: 1 | GI85: 2 | GJ85: 0 | GK85: 0 | GL85: =ROUND(IF(AND(BH85=3,BI85=3,FS85<>0),P85,0),2) -> 0 | GM85: =ROUND(O85+X85+Y85,2)+GX85 -> 1822.02 | GN85: =IF(OR(BI85=0,BI85=1),GM85-GX85,0) -> 0 | GO85: =IF(BI85=2,GM85-GX85,0) -> 1822.02 | GP85: =IF(BI85=4,GM85-GX85,0) -> 0 | GR85: 0 | GS85: 3 | GT85: 0 | GV85: =ROUND((GT85),6) -> 0 | GW85: 1 | GX85: =ROUND(HC85*I85,2) -> 0 | HA85: 0 | HB85: 0 | HC85: =GV85*GW85 -> 0 | HS85: 0 | IK85: 0
A86: 17 | B86: 1 | C86: =ROW(SmtRes!A84) -> 84 | D86: =ROW(EtalonRes!A84) -> 84 | E86: 6 | F86: 4.8-288-2 | G86: Трубы гофрированные поливинилхлоридные наружным диаметром 20 мм открыто по стенам и потолкам с установкой соединительных коробок | H86: 100 м | I86: =ROUND(200/100,9) -> 2 | J86: 0 | K86: =ROUND(200/100,9) -> 2 | O86: =ROUND(CP86,2) -> 31920.4 | P86: =ROUND((ROUND((AC86*AW86*I86),2)*BC86),2) -> 6216.66 | Q86: =(ROUND((ROUND((((ET86*1.1))*AV86*I86),2)*BB86),2)+ROUND((ROUND(((AE86-((EU86*1.1)))*AV86*I86),2)*BS86),2)) -> 1351.42 | R86: =(ROUND((ROUND((((EU86*1.1))*AV86*I86),2)*BS86),2)+ROUND((ROUND(((AE86-((EU86*1.1)))*AV86*I86),2)*BS86),2)) -> 723.12 | S86: =ROUND((ROUND((AF86*AV86*I86),2)*BA86),2) -> 24352.32 | T86: =ROUND(CU86*I86,2) -> 0 | U86: =CV86*I86 -> 34.551 | V86: =CW86*I86 -> 0 | W86: =ROUND(CX86*I86,2) -> 0 | X86: =(ROUND((((S86+ROUND((ROUND((((EU86*1.1))*AV86*I86),2)*BS86),2))*AT86)/100),2)+ROUND(((ROUND((ROUND(((AE86-((EU86*1.1)))*AV86*I86),2)*BS86),2)*AT86)/100),2)) -> 24323.18 | Y86: =(ROUND((((S86+ROUND((ROUND((((EU86*1.1))*AV86*I86),2)*BS86),2))*AU86)/100),2)+ROUND(((ROUND((ROUND(((AE86-((EU86*1.1)))*AV86*I86),2)*BS86),2)*AU86)/100),2)) -> 12788.47 | AA86: 60256982 | AB86: =ROUND((AC86+AD86+AF86),6) -> 561.933 | AC86: =ROUND((ES86),6) -> 314.29 | AD86: =ROUND(((((ET86*1.1))-((EU86*1.1)))+AE86),6) -> 36.157 | AE86: =ROUND(((EU86*1.1)),6) -> 6.281 | AF86: =ROUND(((EV86*1.1)),6) -> 211.486 | AG86: =ROUND((AP86),6) -> 0 | AH86: =((EW86*1.1)) -> 16.5 | AI86: =((EX86*1.1)) -> 0 | AJ86: =(AS86) -> 0 | AK86: 539.42 | AL86: 314.29 | AM86: 32.87 | AN86: 5.71 | AO86: 192.26 | AP86: 0 | AQ86: 15 | AR86: 0 | AS86: 0 | AT86: 97 | AU86: 51 | AV86: 1.047 | AW86: 1 | AZ86: 1 | BA86: 54.99 | BB86: 17.85 | BC86: 9.89 | BH86: 0 | BI86: 2 | BJ86: ТСН-2001.4 Доп. 54, Сб. 8, т. 288, поз. 2 | BM86: 67 | BN86: 58973116 | BO86: 4.8-288-2 | BP86: 1 | BQ86: 40 | BR86: 0 | BS86: 54.99 | BT86: 1 | BU86: 1 | BV86: 1 | BW86: 1 | BX86: 1 | BZ86: 97 | CA86: 51 | CE86: 1566 | CF86: 0 | CG86: 0 | CM86: 0 | CN86: Поправка: О.П. п.3.4.30.в Наименование: При применении территориальных сметных нормативов для города Москвы затраты, учитывающие напряженные и стесненные условия производства работ (стесненность, сложность складирования и транспортной логистики и т.п.), исчисляются с применением коэффициентов к затратам труда и заработной плате рабочих, машинистов, времени эксплуатации машин и механизмов, стоимости эксплуатации машин в размере: для объектов, расположенных за пределами Третьего транспортного кольца города Москвы, но в пределах Московской кольцевой автомобильной дороги | CO86: 0 | CP86: =(P86+Q86+S86) -> 31920.4 | CQ86: =ROUND((ROUND((AC86*AW86*1),2)*BC86),2) -> 3108.33 | CR86: =(ROUND((ROUND((((ET86*1.1))*AV86*1),2)*BB86),2)+ROUND((ROUND(((AE86-((EU86*1.1)))*AV86*1),2)*BS86),2)) -> 675.8 | CS86: =(ROUND((ROUND((((EU86*1.1))*AV86*1),2)*BS86),2)+ROUND((ROUND(((AE86-((EU86*1.1)))*AV86*1),2)*BS86),2)) -> 361.83 | CT86: =ROUND((ROUND((AF86*AV86*1),2)*BA86),2) -> 12176.44 | CU86: =AG86 -> 0 | CV86: =(AH86*AV86) -> 17.2755 | CW86: =AI86 -> 0 | CX86: =AJ86 -> 0 | CY86: =(ROUND((((S86+ROUND((ROUND((((EU86*1.1))*AV86*1),2)*BS86),2))*AT86)/100),2)+ROUND(((ROUND((ROUND(((AE86-((EU86*1.1)))*AV86*1),2)*BS86),2)*AT86)/100),2)) -> 23972.73 | CZ86: =(ROUND((((S86+ROUND((ROUND((((EU86*1.1))*AV86*1),2)*BS86),2))*AU86)/100),2)+ROUND(((ROUND((ROUND(((AE86-((EU86*1.1)))*AV86*1),2)*BS86),2)*AU86)/100),2)) -> 12604.22 | DB86: 12 | DE86: *1,1 | DF86: *1,1 | DG86: *1,1 | DI86: *1,1 | DJ86: *1,1 | DN86: 0 | DO86: 0 | DP86: 1 | DQ86: 1 | DU86: 1003 | DV86: 100 м | DW86: 100 м | DX86: 100 | EE86: 60088531 | EF86: 40 | EG86: Монтаж оборудования | EH86: 0 | EJ86: 2 | EK86: 67 | EL86: ТСН-2001.4-8. Электротехнические установки | EM86: ТСН-2001.4-8-1 | EO86: Поправка: О.П. п.3.4.30.в | EQ86: 0 | ER86: 539.42 | ES86: 314.29 | ET86: 32.87 | EU86: 5.71 | EV86: 192.26 | EW86: 15 | EX86: 0 | EY86: 0 | FQ86: 0 | FR86: 0 | FS86: 0 | FX86: 97 | FY86: 51 | GD86: 1 | GF86: 1705749599 | GG86: 2 | GH86: 1 | GI86: 2 | GJ86: 0 | GK86: 0 | GL86: =ROUND(IF(AND(BH86=3,BI86=3,FS86<>0),P86,0),2) -> 0 | GM86: =ROUND(O86+X86+Y86,2)+GX86 -> 69032.05 | GN86: =IF(OR(BI86=0,BI86=1),GM86-GX86,0) -> 0 | GO86: =IF(BI86=2,GM86-GX86,0) -> 69032.05 | GP86: =IF(BI86=4,GM86-GX86,0) -> 0 | GR86: 0 | GS86: 3 | GT86: 0 | GV86: =ROUND((GT86),6) -> 0 | GW86: 1 | GX86: =ROUND(HC86*I86,2) -> 0 | HA86: 0 | HB86: 0 | HC86: =GV86*GW86 -> 0 | HS86: 0 | IK86: 0
A87: 18 | B87: 1 | C87: 80 | E87: 6,1 | F87: 1.12-5-372 | G87: Трубы электротехнические, гофрированные, из ПВХ, негорючие, с зондом, наружный диаметр 20 мм | H87: м | I87: =I85*J87 -> 204 | J87: 102 | K87: 102 | O87: =ROUND(CP87,2) -> 703.8 | P87: =ROUND((ROUND((AC87*AW87*I87),2)*BC87),2) -> 703.8 | Q87: =(ROUND((ROUND(((ET87)*AV87*I87),2)*BB87),2)+ROUND((ROUND(((AE87-(EU87))*AV87*I87),2)*BS87),2)) -> 0 | R87: =(ROUND((ROUND(((EU87)*AV87*I87),2)*BS87),2)+ROUND((ROUND(((AE87-(EU87))*AV87*I87),2)*BS87),2)) -> 0 | S87: =ROUND((ROUND((AF87*AV87*I87),2)*BA87),2) -> 0 | T87: =ROUND(CU87*I87,2) -> 0 | U87: =CV87*I87 -> 0 | V87: =CW87*I87 -> 0 | W87: =ROUND(CX87*I87,2) -> 0 | X87: =(ROUND((((S87+ROUND((ROUND(((EU87)*AV87*I87),2)*BS87),2))*AT87)/100),2)+ROUND(((ROUND((ROUND(((AE87-(EU87))*AV87*I87),2)*BS87),2)*AT87)/100),2)) -> 0 | Y87: =(ROUND((((S87+ROUND((ROUND(((EU87)*AV87*I87),2)*BS87),2))*AU87)/100),2)+ROUND(((ROUND((ROUND(((AE87-(EU87))*AV87*I87),2)*BS87),2)*AU87)/100),2)) -> 0 | AA87: 60256985 | AB87: =ROUND((AC87+AD87+AF87),6) -> 3.45 | AC87: =ROUND((ES87),6) -> 3.45 | AD87: =ROUND((((ET87)-(EU87))+AE87),6) -> 0 | AE87: =ROUND((EU87),6) -> 0 | AF87: =ROUND((EV87),6) -> 0 | AG87: =ROUND((AP87),6) -> 0 | AH87: =(EW87) -> 0 | AI87: =(EX87) -> 0 | AJ87: =(AS87) -> 0 | AK87: 3.45 | AL87: 3.45 | AM87: 0 | AN87: 0 | AO87: 0 | AP87: 0 | AQ87: 0 | AR87: 0 | AS87: 0 | AT87: 97 | AU87: 51 | AV87: 1 | AW87: 1 | AZ87: 1 | BA87: 1 | BB87: 1 | BC87: 1 | BH87: 3 | BI87: 2 | BJ87: ТСН-2001.1 Доп. 67, Р. 12, о. 5, поз. 372 | BM87: 67 | BN87: 58973116 | BP87: 0 | BQ87: 40 | BR87: 0 | BS87: 1 | BT87: 1 | BU87: 1 | BV87: 1 | BW87: 1 | BX87: 1 | BZ87: 97 | CA87: 51 | CE87: 1566 | CF87: 0 | CG87: 0 | CM87: 0 | CO87: 0 | CP87: =(P87+Q87+S87) -> 703.8 | CQ87: =ROUND((ROUND((AC87*AW87*1),2)*BC87),2) -> 3.45 | CR87: =(ROUND((ROUND(((ET87)*AV87*1),2)*BB87),2)+ROUND((ROUND(((AE87-(EU87))*AV87*1),2)*BS87),2)) -> 0 | CS87: =(ROUND((ROUND(((EU87)*AV87*1),2)*BS87),2)+ROUND((ROUND(((AE87-(EU87))*AV87*1),2)*BS87),2)) -> 0 | CT87: =ROUND((ROUND((AF87*AV87*1),2)*BA87),2) -> 0 | CU87: =AG87 -> 0 | CV87: =(AH87*AV87) -> 0 | CW87: =AI87 -> 0 | CX87: =AJ87 -> 0 | CY87: =(ROUND((((S87+ROUND((ROUND(((EU87)*AV87*1),2)*BS87),2))*AT87)/100),2)+ROUND(((ROUND((ROUND(((AE87-(EU87))*AV87*1),2)*BS87),2)*AT87)/100),2)) -> 0 | CZ87: =(ROUND((((S87+ROUND((ROUND(((EU87)*AV87*1),2)*BS87),2))*AU87)/100),2)+ROUND(((ROUND((ROUND(((AE87-(EU87))*AV87*1),2)*BS87),2)*AU87)/100),2)) -> 0 | DN87: 0 | DO87: 0 | DP87: 1 | DQ87: 1 | DU87: 1003 | DV87: м | DW87: м | DX87: 1 | EE87: 60088531 | EF87: 40 | EG87: Монтаж оборудования | EH87: 0 | EJ87: 2 | EK87: 67 | EL87: ТСН-2001.4-8. Электротехнические установки | EM87: ТСН-2001.4-8-1 | EQ87: 0 | ER87: 3.45 | ES87: 3.45 | ET87: 0 | EU87: 0 | EV87: 0 | EW87: 0 | EX87: 0 | FQ87: 0 | FR87: 0 | FS87: 0 | FX87: 97 | FY87: 51 | GD87: 1 | GF87: -1305428159 | GG87: 2 | GH87: 1 | GI87: -2 | GJ87: 0 | GK87: 0 | GL87: =ROUND(IF(AND(BH87=3,BI87=3,FS87<>0),P87,0),2) -> 0 | GM87: =ROUND(O87+X87+Y87,2)+GX87 -> 703.8 | GN87: =IF(OR(BI87=0,BI87=1),GM87-GX87,0) -> 0 | GO87: =IF(BI87=2,GM87-GX87,0) -> 703.8 | GP87: =IF(BI87=4,GM87-GX87,0) -> 0 | GR87: 0 | GS87: 3 | GT87: 0 | GV87: =ROUND((GT87),6) -> 0 | GW87: 1 | GX87: =ROUND(HC87*I87,2) -> 0 | HA87: 0 | HB87: 0 | HC87: =GV87*GW87 -> 0 | HS87: 0 | IK87: 0
A88: 18 | B88: 1 | C88: 83 | E88: 6,1 | F88: 1.12-5-372 | G88: Трубы электротехнические, гофрированные, из ПВХ, негорючие, с зондом, наружный диаметр 20 мм | H88: м | I88: =I86*J88 -> 204 | J88: 102 | K88: 102 | O88: =ROUND(CP88,2) -> 2765.93 | P88: =ROUND((ROUND((AC88*AW88*I88),2)*BC88),2) -> 2765.93 | Q88: =(ROUND((ROUND(((ET88)*AV88*I88),2)*BB88),2)+ROUND((ROUND(((AE88-(EU88))*AV88*I88),2)*BS88),2)) -> 0 | R88: =(ROUND((ROUND(((EU88)*AV88*I88),2)*BS88),2)+ROUND((ROUND(((AE88-(EU88))*AV88*I88),2)*BS88),2)) -> 0 | S88: =ROUND((ROUND((AF88*AV88*I88),2)*BA88),2) -> 0 | T88: =ROUND(CU88*I88,2) -> 0 | U88: =CV88*I88 -> 0 | V88: =CW88*I88 -> 0 | W88: =ROUND(CX88*I88,2) -> 0 | X88: =(ROUND((((S88+ROUND((ROUND(((EU88)*AV88*I88),2)*BS88),2))*AT88)/100),2)+ROUND(((ROUND((ROUND(((AE88-(EU88))*AV88*I88),2)*BS88),2)*AT88)/100),2)) -> 0 | Y88: =(ROUND((((S88+ROUND((ROUND(((EU88)*AV88*I88),2)*BS88),2))*AU88)/100),2)+ROUND(((ROUND((ROUND(((AE88-(EU88))*AV88*I88),2)*BS88),2)*AU88)/100),2)) -> 0 | AA88: 60256982 | AB88: =ROUND((AC88+AD88+AF88),6) -> 3.45 | AC88: =ROUND((ES88),6) -> 3.45 | AD88: =ROUND((((ET88)-(EU88))+AE88),6) -> 0 | AE88: =ROUND((EU88),6) -> 0 | AF88: =ROUND((EV88),6) -> 0 | AG88: =ROUND((AP88),6) -> 0 | AH88: =(EW88) -> 0 | AI88: =(EX88) -> 0 | AJ88: =(AS88) -> 0 | AK88: 3.45 | AL88: 3.45 | AM88: 0 | AN88: 0 | AO88: 0 | AP88: 0 | AQ88: 0 | AR88: 0 | AS88: 0 | AT88: 97 | AU88: 51 | AV88: 1 | AW88: 1 | AZ88: 1 | BA88: 1 | BB88: 1 | BC88: 3.93 | BH88: 3 | BI88: 2 | BJ88: ТСН-2001.1 Доп. 67, Р. 12, о. 5, поз. 372 | BM88: 67 | BN88: 58973116 | BO88: 1.12-5-372 | BP88: 1 | BQ88: 40 | BR88: 0 | BS88: 1 | BT88: 1 | BU88: 1 | BV88: 1 | BW88: 1 | BX88: 1 | BZ88: 97 | CA88: 51 | CE88: 1566 | CF88: 0 | CG88: 0 | CM88: 0 | CO88: 0 | CP88: =(P88+Q88+S88) -> 2765.93 | CQ88: =ROUND((ROUND((AC88*AW88*1),2)*BC88),2) -> 13.56 | CR88: =(ROUND((ROUND(((ET88)*AV88*1),2)*BB88),2)+ROUND((ROUND(((AE88-(EU88))*AV88*1),2)*BS88),2)) -> 0 | CS88: =(ROUND((ROUND(((EU88)*AV88*1),2)*BS88),2)+ROUND((ROUND(((AE88-(EU88))*AV88*1),2)*BS88),2)) -> 0 | CT88: =ROUND((ROUND((AF88*AV88*1),2)*BA88),2) -> 0 | CU88: =AG88 -> 0 | CV88: =(AH88*AV88) -> 0 | CW88: =AI88 -> 0 | CX88: =AJ88 -> 0 | CY88: =(ROUND((((S88+ROUND((ROUND(((EU88)*AV88*1),2)*BS88),2))*AT88)/100),2)+ROUND(((ROUND((ROUND(((AE88-(EU88))*AV88*1),2)*BS88),2)*AT88)/100),2)) -> 0 | CZ88: =(ROUND((((S88+ROUND((ROUND(((EU88)*AV88*1),2)*BS88),2))*AU88)/100),2)+ROUND(((ROUND((ROUND(((AE88-(EU88))*AV88*1),2)*BS88),2)*AU88)/100),2)) -> 0 | DN88: 0 | DO88: 0 | DP88: 1 | DQ88: 1 | DU88: 1003 | DV88: м | DW88: м | DX88: 1 | EE88: 60088531 | EF88: 40 | EG88: Монтаж оборудования | EH88: 0 | EJ88: 2 | EK88: 67 | EL88: ТСН-2001.4-8. Электротехнические установки | EM88: ТСН-2001.4-8-1 | EQ88: 0 | ER88: 3.45 | ES88: 3.45 | ET88: 0 | EU88: 0 | EV88: 0 | EW88: 0 | EX88: 0 | FQ88: 0 | FR88: 0 | FS88: 0 | FX88: 97 | FY88: 51 | GD88: 1 | GF88: -1305428159 | GG88: 2 | GH88: 1 | GI88: 2 | GJ88: 0 | GK88: 0 | GL88: =ROUND(IF(AND(BH88=3,BI88=3,FS88<>0),P88,0),2) -> 0 | GM88: =ROUND(O88+X88+Y88,2)+GX88 -> 2765.93 | GN88: =IF(OR(BI88=0,BI88=1),GM88-GX88,0) -> 0 | GO88: =IF(BI88=2,GM88-GX88,0) -> 2765.93 | GP88: =IF(BI88=4,GM88-GX88,0) -> 0 | GR88: 0 | GS88: 3 | GT88: 0 | GV88: =ROUND((GT88),6) -> 0 | GW88: 1 | GX88: =ROUND(HC88*I88,2) -> 0 | HA88: 0 | HB88: 0 | HC88: =GV88*GW88 -> 0 | HS88: 0 | IK88: 0
A89: 18 | B89: 1 | C89: 81 | E89: 6,2 | F89: 1.21-5-1136 | G89: Держатель пластиковый с защелкой для крепления труб, рукавов и гибких вводов диаметром 20 мм | H89: 100 шт. | I89: =I85*J89 -> 0 | J89: 0 | K89: 0 | O89: =ROUND(CP89,2) -> 0 | P89: =ROUND((ROUND((AC89*AW89*I89),2)*BC89),2) -> 0 | Q89: =(ROUND((ROUND(((ET89)*AV89*I89),2)*BB89),2)+ROUND((ROUND(((AE89-(EU89))*AV89*I89),2)*BS89),2)) -> 0 | R89: =(ROUND((ROUND(((EU89)*AV89*I89),2)*BS89),2)+ROUND((ROUND(((AE89-(EU89))*AV89*I89),2)*BS89),2)) -> 0 | S89: =ROUND((ROUND((AF89*AV89*I89),2)*BA89),2) -> 0 | T89: =ROUND(CU89*I89,2) -> 0 | U89: =CV89*I89 -> 0 | V89: =CW89*I89 -> 0 | W89: =ROUND(CX89*I89,2) -> 0 | X89: =(ROUND((((S89+ROUND((ROUND(((EU89)*AV89*I89),2)*BS89),2))*AT89)/100),2)+ROUND(((ROUND((ROUND(((AE89-(EU89))*AV89*I89),2)*BS89),2)*AT89)/100),2)) -> 0 | Y89: =(ROUND((((S89+ROUND((ROUND(((EU89)*AV89*I89),2)*BS89),2))*AU89)/100),2)+ROUND(((ROUND((ROUND(((AE89-(EU89))*AV89*I89),2)*BS89),2)*AU89)/100),2)) -> 0 | AA89: 60256985 | AB89: =ROUND((AC89+AD89+AF89),6) -> 146.89 | AC89: =ROUND((ES89),6) -> 146.89 | AD89: =ROUND((((ET89)-(EU89))+AE89),6) -> 0 | AE89: =ROUND((EU89),6) -> 0 | AF89: =ROUND((EV89),6) -> 0 | AG89: =ROUND((AP89),6) -> 0 | AH89: =(EW89) -> 0 | AI89: =(EX89) -> 0 | AJ89: =(AS89) -> 0 | AK89: 146.89 | AL89: 146.89 | AM89: 0 | AN89: 0 | AO89: 0 | AP89: 0 | AQ89: 0 | AR89: 0 | AS89: 0 | AT89: 97 | AU89: 51 | AV89: 1 | AW89: 1 | AZ89: 1 | BA89: 1 | BB89: 1 | BC89: 1 | BH89: 3 | BI89: 2 | BJ89: ТСН-2001.1 Доп. 73, Р. 21, о. 5, поз. 1136 | BM89: 67 | BN89: 58973116 | BP89: 0 | BQ89: 40 | BR89: 0 | BS89: 1 | BT89: 1 | BU89: 1 | BV89: 1 | BW89: 1 | BX89: 1 | BZ89: 97 | CA89: 51 | CE89: 1566 | CF89: 0 | CG89: 0 | CM89: 0 | CO89: 0 | CP89: =(P89+Q89+S89) -> 0 | CQ89: =ROUND((ROUND((AC89*AW89*1),2)*BC89),2) -> 146.89 | CR89: =(ROUND((ROUND(((ET89)*AV89*1),2)*BB89),2)+ROUND((ROUND(((AE89-(EU89))*AV89*1),2)*BS89),2)) -> 0 | CS89: =(ROUND((ROUND(((EU89)*AV89*1),2)*BS89),2)+ROUND((ROUND(((AE89-(EU89))*AV89*1),2)*BS89),2)) -> 0 | CT89: =ROUND((ROUND((AF89*AV89*1),2)*BA89),2) -> 0 | CU89: =AG89 -> 0 | CV89: =(AH89*AV89) -> 0 | CW89: =AI89 -> 0 | CX89: =AJ89 -> 0 | CY89: =(ROUND((((S89+ROUND((ROUND(((EU89)*AV89*1),2)*BS89),2))*AT89)/100),2)+ROUND(((ROUND((ROUND(((AE89-(EU89))*AV89*1),2)*BS89),2)*AT89)/100),2)) -> 0 | CZ89: =(ROUND((((S89+ROUND((ROUND(((EU89)*AV89*1),2)*BS89),2))*AU89)/100),2)+ROUND(((ROUND((ROUND(((AE89-(EU89))*AV89*1),2)*BS89),2)*AU89)/100),2)) -> 0 | DN89: 0 | DO89: 0 | DP89: 1 | DQ89: 1 | DU89: 1010 | DV89: 100 шт. | DW89: 100 шт. | DX89: 100 | EE89: 60088531 | EF89: 40 | EG89: Монтаж оборудования | EH89: 0 | EJ89: 2 | EK89: 67 | EL89: ТСН-2001.4-8. Электротехнические установки | EM89: ТСН-2001.4-8-1 | EQ89: 0 | ER89: 146.89 | ES89: 146.89 | ET89: 0 | EU89: 0 | EV89: 0 | EW89: 0 | EX89: 0 | FQ89: 0 | FR89: 0 | FS89: 0 | FX89: 97 | FY89: 51 | GD89: 1 | GF89: -1171050213 | GG89: 2 | GH89: 1 | GI89: -2 | GJ89: 0 | GK89: 0 | GL89: =ROUND(IF(AND(BH89=3,BI89=3,FS89<>0),P89,0),2) -> 0 | GM89: =ROUND(O89+X89+Y89,2)+GX89 -> 0 | GN89: =IF(OR(BI89=0,BI89=1),GM89-GX89,0) -> 0 | GO89: =IF(BI89=2,GM89-GX89,0) -> 0 | GP89: =IF(BI89=4,GM89-GX89,0) -> 0 | GR89: 0 | GS89: 3 | GT89: 0 | GV89: =ROUND((GT89),6) -> 0 | GW89: 1 | GX89: =ROUND(HC89*I89,2) -> 0 | HA89: 0 | HB89: 0 | HC89: =GV89*GW89 -> 0 | HS89: 0 | IK89: 0
A90: 18 | B90: 1 | C90: 84 | E90: 6,2 | F90: 1.21-5-1136 | G90: Держатель пластиковый с защелкой для крепления труб, рукавов и гибких вводов диаметром 20 мм | H90: 100 шт. | I90: =I86*J90 -> 0 | J90: 0 | K90: 0 | O90: =ROUND(CP90,2) -> 0 | P90: =ROUND((ROUND((AC90*AW90*I90),2)*BC90),2) -> 0 | Q90: =(ROUND((ROUND(((ET90)*AV90*I90),2)*BB90),2)+ROUND((ROUND(((AE90-(EU90))*AV90*I90),2)*BS90),2)) -> 0 | R90: =(ROUND((ROUND(((EU90)*AV90*I90),2)*BS90),2)+ROUND((ROUND(((AE90-(EU90))*AV90*I90),2)*BS90),2)) -> 0 | S90: =ROUND((ROUND((AF90*AV90*I90),2)*BA90),2) -> 0 | T90: =ROUND(CU90*I90,2) -> 0 | U90: =CV90*I90 -> 0 | V90: =CW90*I90 -> 0 | W90: =ROUND(CX90*I90,2) -> 0 | X90: =(ROUND((((S90+ROUND((ROUND(((EU90)*AV90*I90),2)*BS90),2))*AT90)/100),2)+ROUND(((ROUND((ROUND(((AE90-(EU90))*AV90*I90),2)*BS90),2)*AT90)/100),2)) -> 0 | Y90: =(ROUND((((S90+ROUND((ROUND(((EU90)*AV90*I90),2)*BS90),2))*AU90)/100),2)+ROUND(((ROUND((ROUND(((AE90-(EU90))*AV90*I90),2)*BS90),2)*AU90)/100),2)) -> 0 | AA90: 60256982 | AB90: =ROUND((AC90+AD90+AF90),6) -> 146.89 | AC90: =ROUND((ES90),6) -> 146.89 | AD90: =ROUND((((ET90)-(EU90))+AE90),6) -> 0 | AE90: =ROUND((EU90),6) -> 0 | AF90: =ROUND((EV90),6) -> 0 | AG90: =ROUND((AP90),6) -> 0 | AH90: =(EW90) -> 0 | AI90: =(EX90) -> 0 | AJ90: =(AS90) -> 0 | AK90: 146.89 | AL90: 146.89 | AM90: 0 | AN90: 0 | AO90: 0 | AP90: 0 | AQ90: 0 | AR90: 0 | AS90: 0 | AT90: 97 | AU90: 51 | AV90: 1 | AW90: 1 | AZ90: 1 | BA90: 1 | BB90: 1 | BC90: 2.03 | BH90: 3 | BI90: 2 | BJ90: ТСН-2001.1 Доп. 73, Р. 21, о. 5, поз. 1136 | BM90: 67 | BN90: 58973116 | BO90: 1.21-5-1136 | BP90: 1 | BQ90: 40 | BR90: 0 | BS90: 1 | BT90: 1 | BU90: 1 | BV90: 1 | BW90: 1 | BX90: 1 | BZ90: 97 | CA90: 51 | CE90: 1566 | CF90: 0 | CG90: 0 | CM90: 0 | CO90: 0 | CP90: =(P90+Q90+S90) -> 0 | CQ90: =ROUND((ROUND((AC90*AW90*1),2)*BC90),2) -> 298.19 | CR90: =(ROUND((ROUND(((ET90)*AV90*1),2)*BB90),2)+ROUND((ROUND(((AE90-(EU90))*AV90*1),2)*BS90),2)) -> 0 | CS90: =(ROUND((ROUND(((EU90)*AV90*1),2)*BS90),2)+ROUND((ROUND(((AE90-(EU90))*AV90*1),2)*BS90),2)) -> 0 | CT90: =ROUND((ROUND((AF90*AV90*1),2)*BA90),2) -> 0 | CU90: =AG90 -> 0 | CV90: =(AH90*AV90) -> 0 | CW90: =AI90 -> 0 | CX90: =AJ90 -> 0 | CY90: =(ROUND((((S90+ROUND((ROUND(((EU90)*AV90*1),2)*BS90),2))*AT90)/100),2)+ROUND(((ROUND((ROUND(((AE90-(EU90))*AV90*1),2)*BS90),2)*AT90)/100),2)) -> 0 | CZ90: =(ROUND((((S90+ROUND((ROUND(((EU90)*AV90*1),2)*BS90),2))*AU90)/100),2)+ROUND(((ROUND((ROUND(((AE90-(EU90))*AV90*1),2)*BS90),2)*AU90)/100),2)) -> 0 | DN90: 0 | DO90: 0 | DP90: 1 | DQ90: 1 | DU90: 1010 | DV90: 100 шт. | DW90: 100 шт. | DX90: 100 | EE90: 60088531 | EF90: 40 | EG90: Монтаж оборудования | EH90: 0 | EJ90: 2 | EK90: 67 | EL90: ТСН-2001.4-8. Электротехнические установки | EM90: ТСН-2001.4-8-1 | EQ90: 0 | ER90: 146.89 | ES90: 146.89 | ET90: 0 | EU90: 0 | EV90: 0 | EW90: 0 | EX90: 0 | FQ90: 0 | FR90: 0 | FS90: 0 | FX90: 97 | FY90: 51 | GD90: 1 | GF90: -1171050213 | GG90: 2 | GH90: 1 | GI90: 2 | GJ90: 0 | GK90: 0 | GL90: =ROUND(IF(AND(BH90=3,BI90=3,FS90<>0),P90,0),2) -> 0 | GM90: =ROUND(O90+X90+Y90,2)+GX90 -> 0 | GN90: =IF(OR(BI90=0,BI90=1),GM90-GX90,0) -> 0 | GO90: =IF(BI90=2,GM90-GX90,0) -> 0 | GP90: =IF(BI90=4,GM90-GX90,0) -> 0 | GR90: 0 | GS90: 3 | GT90: 0 | GV90: =ROUND((GT90),6) -> 0 | GW90: 1 | GX90: =ROUND(HC90*I90,2) -> 0 | HA90: 0 | HB90: 0 | HC90: =GV90*GW90 -> 0 | HS90: 0 | IK90: 0
A91: 17 | B91: 1 | C91: =ROW(SmtRes!A96) -> 96 | D91: =ROW(EtalonRes!A100) -> 100 | E91: 7 | F91: 4.8-174-1 | G91: Прокладка металлического рукава, наружный диаметр до 48 мм | H91: 100 м | I91: =ROUND(30/100,9) -> 0.3 | J91: 0 | K91: =ROUND(30/100,9) -> 0.3 | O91: =ROUND(CP91,2) -> 700.99 | P91: =ROUND((ROUND((AC91*AW91*I91),2)*BC91),2) -> 529.12 | Q91: =(ROUND((ROUND((((ET91*1.1))*AV91*I91),2)*BB91),2)+ROUND((ROUND(((AE91-((EU91*1.1)))*AV91*I91),2)*BS91),2)) -> 44.59 | R91: =(ROUND((ROUND((((EU91*1.1))*AV91*I91),2)*BS91),2)+ROUND((ROUND(((AE91-((EU91*1.1)))*AV91*I91),2)*BS91),2)) -> 0.87 | S91: =ROUND((ROUND((AF91*AV91*I91),2)*BA91),2) -> 127.28 | T91: =ROUND(CU91*I91,2) -> 0 | U91: =CV91*I91 -> 10.330749 | V91: =CW91*I91 -> 0 | W91: =ROUND(CX91*I91,2) -> 0 | X91: =(ROUND((((S91+ROUND((ROUND((((EU91*1.1))*AV91*I91),2)*BS91),2))*AT91)/100),2)+ROUND(((ROUND((ROUND(((AE91-((EU91*1.1)))*AV91*I91),2)*BS91),2)*AT91)/100),2)) -> 124.31 | Y91: =(ROUND((((S91+ROUND((ROUND((((EU91*1.1))*AV91*I91),2)*BS91),2))*AU91)/100),2)+ROUND(((ROUND((ROUND(((AE91-((EU91*1.1)))*AV91*I91),2)*BS91),2)*AU91)/100),2)) -> 65.36 | AA91: 60256985 | AB91: =ROUND((AC91+AD91+AF91),6) -> 2310.913 | AC91: =ROUND((ES91),6) -> 1763.74 | AD91: =ROUND(((((ET91*1.1))-((EU91*1.1)))+AE91),6) -> 141.966 | AE91: =ROUND(((EU91*1.1)),6) -> 2.772 | AF91: =ROUND(((EV91*1.1)),6) -> 405.207 | AG91: =ROUND((AP91),6) -> 0 | AH91: =((EW91*1.1)) -> 32.89 | AI91: =((EX91*1.1)) -> 0 | AJ91: =(AS91) -> 0 | AK91: 2261.17 | AL91: 1763.74 | AM91: 129.06 | AN91: 2.52 | AO91: 368.37 | AP91: 0 | AQ91: 29.9 | AR91: 0 | AS91: 0 | AT91: 97 | AU91: 51 | AV91: 1.047 | AW91: 1 | AZ91: 1 | BA91: 1 | BB91: 1 | BC91: 1 | BH91: 0 | BI91: 2 | BJ91: ТСН-2001.4 Доп. 80, Сб. 8, т. 174, поз. 1 | BM91: 67 | BN91: 58973116 | BO91: 4.8-174-1 | BP91: 1 | BQ91: 40 | BR91: 0 | BS91: 1 | BT91: 1 | BU91: 1 | BV91: 1 | BW91: 1 | BX91: 1 | BZ91: 97 | CA91: 51 | CE91: 1566 | CF91: 0 | CG91: 0 | CM91: 0 | CN91: Поправка: О.П. п.3.4.30.в Наименование: При применении территориальных сметных нормативов для города Москвы затраты, учитывающие напряженные и стесненные условия производства работ (стесненность, сложность складирования и транспортной логистики и т.п.), исчисляются с применением коэффициентов к затратам труда и заработной плате рабочих, машинистов, времени эксплуатации машин и механизмов, стоимости эксплуатации машин в размере: для объектов, расположенных за пределами Третьего транспортного кольца города Москвы, но в пределах Московской кольцевой автомобильной дороги | CO91: 0 | CP91: =(P91+Q91+S91) -> 700.99 | CQ91: =ROUND((ROUND((AC91*AW91*1),2)*BC91),2) -> 1763.74 | CR91: =(ROUND((ROUND((((ET91*1.1))*AV91*1),2)*BB91),2)+ROUND((ROUND(((AE91-((EU91*1.1)))*AV91*1),2)*BS91),2)) -> 148.64 | CS91: =(ROUND((ROUND((((EU91*1.1))*AV91*1),2)*BS91),2)+ROUND((ROUND(((AE91-((EU91*1.1)))*AV91*1),2)*BS91),2)) -> 2.9 | CT91: =ROUND((ROUND((AF91*AV91*1),2)*BA91),2) -> 424.25 | CU91: =AG91 -> 0 | CV91: =(AH91*AV91) -> 34.43583 | CW91: =AI91 -> 0 | CX91: =AJ91 -> 0 | CY91: =(ROUND((((S91+ROUND((ROUND((((EU91*1.1))*AV91*1),2)*BS91),2))*AT91)/100),2)+ROUND(((ROUND((ROUND(((AE91-((EU91*1.1)))*AV91*1),2)*BS91),2)*AT91)/100),2)) -> 126.27 | CZ91: =(ROUND((((S91+ROUND((ROUND((((EU91*1.1))*AV91*1),2)*BS91),2))*AU91)/100),2)+ROUND(((ROUND((ROUND(((AE91-((EU91*1.1)))*AV91*1),2)*BS91),2)*AU91)/100),2)) -> 66.39 | DB91: 13 | DE91: *1,1 | DF91: *1,1 | DG91: *1,1 | DI91: *1,1 | DJ91: *1,1 | DN91: 0 | DO91: 0 | DP91: 1 | DQ91: 1 | DU91: 1003 | DV91: 100 м | DW91: 100 м | DX91: 100 | EE91: 60088531 | EF91: 40 | EG91: Монтаж оборудования | EH91: 0 | EJ91: 2 | EK91: 67 | EL91: ТСН-2001.4-8. Электротехнические установки | EM91: ТСН-2001.4-8-1 | EO91: Поправка: О.П. п.3.4.30.в | EQ91: 0 | ER91: 2261.17 | ES91: 1763.74 | ET91: 129.06 | EU91: 2.52 | EV91: 368.37 | EW91: 29.9 | EX91: 0 | EY91: 0 | FQ91: 0 | FR91: 0 | FS91: 0 | FX91: 97 | FY91: 51 | GD91: 1 | GF91: 1516590241 | GG91: 2 | GH91: 1 | GI91: 2 | GJ91: 0 | GK91: 0 | GL91: =ROUND(IF(AND(BH91=3,BI91=3,FS91<>0),P91,0),2) -> 0 | GM91: =ROUND(O91+X91+Y91,2)+GX91 -> 890.66 | GN91: =IF(OR(BI91=0,BI91=1),GM91-GX91,0) -> 0 | GO91: =IF(BI91=2,GM91-GX91,0) -> 890.66 | GP91: =IF(BI91=4,GM91-GX91,0) -> 0 | GR91: 0 | GS91: 3 | GT91: 0 | GV91: =ROUND((GT91),6) -> 0 | GW91: 1 | GX91: =ROUND(HC91*I91,2) -> 0 | HA91: 0 | HB91: 0 | HC91: =GV91*GW91 -> 0 | HS91: 0 | IK91: 0
A92: 17 | B92: 1 | C92: =ROW(SmtRes!A108) -> 108 | D92: =ROW(EtalonRes!A116) -> 116 | E92: 7 | F92: 4.8-174-1 | G92: Прокладка металлического рукава, наружный диаметр до 48 мм | H92: 100 м | I92: =ROUND(30/100,9) -> 0.3 | J92: 0 | K92: =ROUND(30/100,9) -> 0.3 | O92: =ROUND(CP92,2) -> 9966.44 | P92: =ROUND((ROUND((AC92*AW92*I92),2)*BC92),2) -> 2428.66 | Q92: =(ROUND((ROUND((((ET92*1.1))*AV92*I92),2)*BB92),2)+ROUND((ROUND(((AE92-((EU92*1.1)))*AV92*I92),2)*BS92),2)) -> 538.65 | R92: =(ROUND((ROUND((((EU92*1.1))*AV92*I92),2)*BS92),2)+ROUND((ROUND(((AE92-((EU92*1.1)))*AV92*I92),2)*BS92),2)) -> 47.84 | S92: =ROUND((ROUND((AF92*AV92*I92),2)*BA92),2) -> 6999.13 | T92: =ROUND(CU92*I92,2) -> 0 | U92: =CV92*I92 -> 10.330749 | V92: =CW92*I92 -> 0 | W92: =ROUND(CX92*I92,2) -> 0 | X92: =(ROUND((((S92+ROUND((ROUND((((EU92*1.1))*AV92*I92),2)*BS92),2))*AT92)/100),2)+ROUND(((ROUND((ROUND(((AE92-((EU92*1.1)))*AV92*I92),2)*BS92),2)*AT92)/100),2)) -> 6835.56 | Y92: =(ROUND((((S92+ROUND((ROUND((((EU92*1.1))*AV92*I92),2)*BS92),2))*AU92)/100),2)+ROUND(((ROUND((ROUND(((AE92-((EU92*1.1)))*AV92*I92),2)*BS92),2)*AU92)/100),2)) -> 3593.95 | AA92: 60256982 | AB92: =ROUND((AC92+AD92+AF92),6) -> 2310.913 | AC92: =ROUND((ES92),6) -> 1763.74 | AD92: =ROUND(((((ET92*1.1))-((EU92*1.1)))+AE92),6) -> 141.966 | AE92: =ROUND(((EU92*1.1)),6) -> 2.772 | AF92: =ROUND(((EV92*1.1)),6) -> 405.207 | AG92: =ROUND((AP92),6) -> 0 | AH92: =((EW92*1.1)) -> 32.89 | AI92: =((EX92*1.1)) -> 0 | AJ92: =(AS92) -> 0 | AK92: 2261.17 | AL92: 1763.74 | AM92: 129.06 | AN92: 2.52 | AO92: 368.37 | AP92: 0 | AQ92: 29.9 | AR92: 0 | AS92: 0 | AT92: 97 | AU92: 51 | AV92: 1.047 | AW92: 1 | AZ92: 1 | BA92: 54.99 | BB92: 12.08 | BC92: 4.59 | BH92: 0 | BI92: 2 | BJ92: ТСН-2001.4 Доп. 80, Сб. 8, т. 174, поз. 1 | BM92: 67 | BN92: 58973116 | BO92: 4.8-174-1 | BP92: 1 | BQ92: 40 | BR92: 0 | BS92: 54.99 | BT92: 1 | BU92: 1 | BV92: 1 | BW92: 1 | BX92: 1 | BZ92: 97 | CA92: 51 | CE92: 1566 | CF92: 0 | CG92: 0 | CM92: 0 | CN92: Поправка: О.П. п.3.4.30.в Наименование: При применении территориальных сметных нормативов для города Москвы затраты, учитывающие напряженные и стесненные условия производства работ (стесненность, сложность складирования и транспортной логистики и т.п.), исчисляются с применением коэффициентов к затратам труда и заработной плате рабочих, машинистов, времени эксплуатации машин и механизмов, стоимости эксплуатации машин в размере: для объектов, расположенных за пределами Третьего транспортного кольца города Москвы, но в пределах Московской кольцевой автомобильной дороги | CO92: 0 | CP92: =(P92+Q92+S92) -> 9966.44 | CQ92: =ROUND((ROUND((AC92*AW92*1),2)*BC92),2) -> 8095.57 | CR92: =(ROUND((ROUND((((ET92*1.1))*AV92*1),2)*BB92),2)+ROUND((ROUND(((AE92-((EU92*1.1)))*AV92*1),2)*BS92),2)) -> 1795.57 | CS92: =(ROUND((ROUND((((EU92*1.1))*AV92*1),2)*BS92),2)+ROUND((ROUND(((AE92-((EU92*1.1)))*AV92*1),2)*BS92),2)) -> 159.47 | CT92: =ROUND((ROUND((AF92*AV92*1),2)*BA92),2) -> 23329.51 | CU92: =AG92 -> 0 | CV92: =(AH92*AV92) -> 34.43583 | CW92: =AI92 -> 0 | CX92: =AJ92 -> 0 | CY92: =(ROUND((((S92+ROUND((ROUND((((EU92*1.1))*AV92*1),2)*BS92),2))*AT92)/100),2)+ROUND(((ROUND((ROUND(((AE92-((EU92*1.1)))*AV92*1),2)*BS92),2)*AT92)/100),2)) -> 6943.84 | CZ92: =(ROUND((((S92+ROUND((ROUND((((EU92*1.1))*AV92*1),2)*BS92),2))*AU92)/100),2)+ROUND(((ROUND((ROUND(((AE92-((EU92*1.1)))*AV92*1),2)*BS92),2)*AU92)/100),2)) -> 3650.89 | DB92: 14 | DE92: *1,1 | DF92: *1,1 | DG92: *1,1 | DI92: *1,1 | DJ92: *1,1 | DN92: 0 | DO92: 0 | DP92: 1 | DQ92: 1 | DU92: 1003 | DV92: 100 м | DW92: 100 м | DX92: 100 | EE92: 60088531 | EF92: 40 | EG92: Монтаж оборудования | EH92: 0 | EJ92: 2 | EK92: 67 | EL92: ТСН-2001.4-8. Электротехнические установки | EM92: ТСН-2001.4-8-1 | EO92: Поправка: О.П. п.3.4.30.в | EQ92: 0 | ER92: 2261.17 | ES92: 1763.74 | ET92: 129.06 | EU92: 2.52 | EV92: 368.37 | EW92: 29.9 | EX92: 0 | EY92: 0 | FQ92: 0 | FR92: 0 | FS92: 0 | FX92: 97 | FY92: 51 | GD92: 1 | GF92: 1516590241 | GG92: 2 | GH92: 1 | GI92: 2 | GJ92: 0 | GK92: 0 | GL92: =ROUND(IF(AND(BH92=3,BI92=3,FS92<>0),P92,0),2) -> 0 | GM92: =ROUND(O92+X92+Y92,2)+GX92 -> 20395.95 | GN92: =IF(OR(BI92=0,BI92=1),GM92-GX92,0) -> 0 | GO92: =IF(BI92=2,GM92-GX92,0) -> 20395.95 | GP92: =IF(BI92=4,GM92-GX92,0) -> 0 | GR92: 0 | GS92: 3 | GT92: 0 | GV92: =ROUND((GT92),6) -> 0 | GW92: 1 | GX92: =ROUND(HC92*I92,2) -> 0 | HA92: 0 | HB92: 0 | HC92: =GV92*GW92 -> 0 | HS92: 0 | IK92: 0
A93: 18 | B93: 1 | C93: 94 | E93: 7,1 | F93: 1.21-5-1413 | G93: Рукав металлополимерный гибкий герметичный, внутренний слой из оцинкованной стальной ленты, наружный из полимерного материала, категория НГ-LS HF, степень защиты IP 65, диаметр условного прохода 20 мм, для защиты кабеля при прокладке | H93: м | I93: =I91*J93 -> 30.9 | J93: 103 | K93: 103 | O93: =ROUND(CP93,2) -> 998.69 | P93: =ROUND((ROUND((AC93*AW93*I93),2)*BC93),2) -> 998.69 | Q93: =(ROUND((ROUND(((ET93)*AV93*I93),2)*BB93),2)+ROUND((ROUND(((AE93-(EU93))*AV93*I93),2)*BS93),2)) -> 0 | R93: =(ROUND((ROUND(((EU93)*AV93*I93),2)*BS93),2)+ROUND((ROUND(((AE93-(EU93))*AV93*I93),2)*BS93),2)) -> 0 | S93: =ROUND((ROUND((AF93*AV93*I93),2)*BA93),2) -> 0 | T93: =ROUND(CU93*I93,2) -> 0 | U93: =CV93*I93 -> 0 | V93: =CW93*I93 -> 0 | W93: =ROUND(CX93*I93,2) -> 0 | X93: =(ROUND((((S93+ROUND((ROUND(((EU93)*AV93*I93),2)*BS93),2))*AT93)/100),2)+ROUND(((ROUND((ROUND(((AE93-(EU93))*AV93*I93),2)*BS93),2)*AT93)/100),2)) -> 0 | Y93: =(ROUND((((S93+ROUND((ROUND(((EU93)*AV93*I93),2)*BS93),2))*AU93)/100),2)+ROUND(((ROUND((ROUND(((AE93-(EU93))*AV93*I93),2)*BS93),2)*AU93)/100),2)) -> 0 | AA93: 60256985 | AB93: =ROUND((AC93+AD93+AF93),6) -> 32.32 | AC93: =ROUND((ES93),6) -> 32.32 | AD93: =ROUND((((ET93)-(EU93))+AE93),6) -> 0 | AE93: =ROUND((EU93),6) -> 0 | AF93: =ROUND((EV93),6) -> 0 | AG93: =ROUND((AP93),6) -> 0 | AH93: =(EW93) -> 0 | AI93: =(EX93) -> 0 | AJ93: =(AS93) -> 0 | AK93: 32.32 | AL93: 32.32 | AM93: 0 | AN93: 0 | AO93: 0 | AP93: 0 | AQ93: 0 | AR93: 0 | AS93: 0 | AT93: 97 | AU93: 51 | AV93: 1 | AW93: 1 | AZ93: 1 | BA93: 1 | BB93: 1 | BC93: 1 | BH93: 3 | BI93: 2 | BJ93: ТСН-2001.1 Доп. 54, Р. 21, о. 5, поз. 1413 | BM93: 67 | BN93: 58973116 | BP93: 0 | BQ93: 40 | BR93: 0 | BS93: 1 | BT93: 1 | BU93: 1 | BV93: 1 | BW93: 1 | BX93: 1 | BZ93: 97 | CA93: 51 | CE93: 1566 | CF93: 0 | CG93: 0 | CM93: 0 | CO93: 0 | CP93: =(P93+Q93+S93) -> 998.69 | CQ93: =ROUND((ROUND((AC93*AW93*1),2)*BC93),2) -> 32.32 | CR93: =(ROUND((ROUND(((ET93)*AV93*1),2)*BB93),2)+ROUND((ROUND(((AE93-(EU93))*AV93*1),2)*BS93),2)) -> 0 | CS93: =(ROUND((ROUND(((EU93)*AV93*1),2)*BS93),2)+ROUND((ROUND(((AE93-(EU93))*AV93*1),2)*BS93),2)) -> 0 | CT93: =ROUND((ROUND((AF93*AV93*1),2)*BA93),2) -> 0 | CU93: =AG93 -> 0 | CV93: =(AH93*AV93) -> 0 | CW93: =AI93 -> 0 | CX93: =AJ93 -> 0 | CY93: =(ROUND((((S93+ROUND((ROUND(((EU93)*AV93*1),2)*BS93),2))*AT93)/100),2)+ROUND(((ROUND((ROUND(((AE93-(EU93))*AV93*1),2)*BS93),2)*AT93)/100),2)) -> 0 | CZ93: =(ROUND((((S93+ROUND((ROUND(((EU93)*AV93*1),2)*BS93),2))*AU93)/100),2)+ROUND(((ROUND((ROUND(((AE93-(EU93))*AV93*1),2)*BS93),2)*AU93)/100),2)) -> 0 | DN93: 0 | DO93: 0 | DP93: 1 | DQ93: 1 | DU93: 1003 | DV93: м | DW93: м | DX93: 1 | EE93: 60088531 | EF93: 40 | EG93: Монтаж оборудования | EH93: 0 | EJ93: 2 | EK93: 67 | EL93: ТСН-2001.4-8. Электротехнические установки | EM93: ТСН-2001.4-8-1 | EQ93: 0 | ER93: 32.32 | ES93: 32.32 | ET93: 0 | EU93: 0 | EV93: 0 | EW93: 0 | EX93: 0 | FQ93: 0 | FR93: 0 | FS93: 0 | FX93: 97 | FY93: 51 | GD93: 1 | GF93: 550947997 | GG93: 2 | GH93: 1 | GI93: -2 | GJ93: 0 | GK93: 0 | GL93: =ROUND(IF(AND(BH93=3,BI93=3,FS93<>0),P93,0),2) -> 0 | GM93: =ROUND(O93+X93+Y93,2)+GX93 -> 998.69 | GN93: =IF(OR(BI93=0,BI93=1),GM93-GX93,0) -> 0 | GO93: =IF(BI93=2,GM93-GX93,0) -> 998.69 | GP93: =IF(BI93=4,GM93-GX93,0) -> 0 | GR93: 0 | GS93: 3 | GT93: 0 | GV93: =ROUND((GT93),6) -> 0 | GW93: 1 | GX93: =ROUND(HC93*I93,2) -> 0 | HA93: 0 | HB93: 0 | HC93: =GV93*GW93 -> 0 | HS93: 0 | IK93: 0
A94: 18 | B94: 1 | C94: 106 | E94: 7,1 | F94: 1.21-5-1413 | G94: Рукав металлополимерный гибкий герметичный, внутренний слой из оцинкованной стальной ленты, наружный из полимерного материала, категория НГ-LS HF, степень защиты IP 65, диаметр условного прохода 20 мм, для защиты кабеля при прокладке | H94: м | I94: =I92*J94 -> 30.9 | J94: 103 | K94: 103 | O94: =ROUND(CP94,2) -> 6940.9 | P94: =ROUND((ROUND((AC94*AW94*I94),2)*BC94),2) -> 6940.9 | Q94: =(ROUND((ROUND(((ET94)*AV94*I94),2)*BB94),2)+ROUND((ROUND(((AE94-(EU94))*AV94*I94),2)*BS94),2)) -> 0 | R94: =(ROUND((ROUND(((EU94)*AV94*I94),2)*BS94),2)+ROUND((ROUND(((AE94-(EU94))*AV94*I94),2)*BS94),2)) -> 0 | S94: =ROUND((ROUND((AF94*AV94*I94),2)*BA94),2) -> 0 | T94: =ROUND(CU94*I94,2) -> 0 | U94: =CV94*I94 -> 0 | V94: =CW94*I94 -> 0 | W94: =ROUND(CX94*I94,2) -> 0 | X94: =(ROUND((((S94+ROUND((ROUND(((EU94)*AV94*I94),2)*BS94),2))*AT94)/100),2)+ROUND(((ROUND((ROUND(((AE94-(EU94))*AV94*I94),2)*BS94),2)*AT94)/100),2)) -> 0 | Y94: =(ROUND((((S94+ROUND((ROUND(((EU94)*AV94*I94),2)*BS94),2))*AU94)/100),2)+ROUND(((ROUND((ROUND(((AE94-(EU94))*AV94*I94),2)*BS94),2)*AU94)/100),2)) -> 0 | AA94: 60256982 | AB94: =ROUND((AC94+AD94+AF94),6) -> 32.32 | AC94: =ROUND((ES94),6) -> 32.32 | AD94: =ROUND((((ET94)-(EU94))+AE94),6) -> 0 | AE94: =ROUND((EU94),6) -> 0 | AF94: =ROUND((EV94),6) -> 0 | AG94: =ROUND((AP94),6) -> 0 | AH94: =(EW94) -> 0 | AI94: =(EX94) -> 0 | AJ94: =(AS94) -> 0 | AK94: 32.32 | AL94: 32.32 | AM94: 0 | AN94: 0 | AO94: 0 | AP94: 0 | AQ94: 0 | AR94: 0 | AS94: 0 | AT94: 97 | AU94: 51 | AV94: 1 | AW94: 1 | AZ94: 1 | BA94: 1 | BB94: 1 | BC94: 6.95 | BH94: 3 | BI94: 2 | BJ94: ТСН-2001.1 Доп. 54, Р. 21, о. 5, поз. 1413 | BM94: 67 | BN94: 58973116 | BO94: 1.21-5-1413 | BP94: 1 | BQ94: 40 | BR94: 0 | BS94: 1 | BT94: 1 | BU94: 1 | BV94: 1 | BW94: 1 | BX94: 1 | BZ94: 97 | CA94: 51 | CE94: 1566 | CF94: 0 | CG94: 0 | CM94: 0 | CO94: 0 | CP94: =(P94+Q94+S94) -> 6940.9 | CQ94: =ROUND((ROUND((AC94*AW94*1),2)*BC94),2) -> 224.62 | CR94: =(ROUND((ROUND(((ET94)*AV94*1),2)*BB94),2)+ROUND((ROUND(((AE94-(EU94))*AV94*1),2)*BS94),2)) -> 0 | CS94: =(ROUND((ROUND(((EU94)*AV94*1),2)*BS94),2)+ROUND((ROUND(((AE94-(EU94))*AV94*1),2)*BS94),2)) -> 0 | CT94: =ROUND((ROUND((AF94*AV94*1),2)*BA94),2) -> 0 | CU94: =AG94 -> 0 | CV94: =(AH94*AV94) -> 0 | CW94: =AI94 -> 0 | CX94: =AJ94 -> 0 | CY94: =(ROUND((((S94+ROUND((ROUND(((EU94)*AV94*1),2)*BS94),2))*AT94)/100),2)+ROUND(((ROUND((ROUND(((AE94-(EU94))*AV94*1),2)*BS94),2)*AT94)/100),2)) -> 0 | CZ94: =(ROUND((((S94+ROUND((ROUND(((EU94)*AV94*1),2)*BS94),2))*AU94)/100),2)+ROUND(((ROUND((ROUND(((AE94-(EU94))*AV94*1),2)*BS94),2)*AU94)/100),2)) -> 0 | DN94: 0 | DO94: 0 | DP94: 1 | DQ94: 1 | DU94: 1003 | DV94: м | DW94: м | DX94: 1 | EE94: 60088531 | EF94: 40 | EG94: Монтаж оборудования | EH94: 0 | EJ94: 2 | EK94: 67 | EL94: ТСН-2001.4-8. Электротехнические установки | EM94: ТСН-2001.4-8-1 | EQ94: 0 | ER94: 32.32 | ES94: 32.32 | ET94: 0 | EU94: 0 | EV94: 0 | EW94: 0 | EX94: 0 | FQ94: 0 | FR94: 0 | FS94: 0 | FX94: 97 | FY94: 51 | GD94: 1 | GF94: 550947997 | GG94: 2 | GH94: 1 | GI94: 2 | GJ94: 0 | GK94: 0 | GL94: =ROUND(IF(AND(BH94=3,BI94=3,FS94<>0),P94,0),2) -> 0 | GM94: =ROUND(O94+X94+Y94,2)+GX94 -> 6940.9 | GN94: =IF(OR(BI94=0,BI94=1),GM94-GX94,0) -> 0 | GO94: =IF(BI94=2,GM94-GX94,0) -> 6940.9 | GP94: =IF(BI94=4,GM94-GX94,0) -> 0 | GR94: 0 | GS94: 3 | GT94: 0 | GV94: =ROUND((GT94),6) -> 0 | GW94: 1 | GX94: =ROUND(HC94*I94,2) -> 0 | HA94: 0 | HB94: 0 | HC94: =GV94*GW94 -> 0 | HS94: 0 | IK94: 0
A95: 17 | B95: 1 | C95: =ROW(SmtRes!A117) -> 117 | D95: =ROW(EtalonRes!A126) -> 126 | E95: 8 | F95: 4.8-175-2 | G95: Затягивание провода в проложенные трубы и металлические рукава, первого одножильного или многожильного в общей оплетке, суммарное сечение до 6 мм2 | H95: 100 м | I95: =ROUND((200+30)/100,9) -> 2.3 | J95: 0 | K95: =ROUND((200+30)/100,9) -> 2.3 | O95: =ROUND(CP95,2) -> 332.08 | P95: =ROUND((ROUND((AC95*AW95*I95),2)*BC95),2) -> 142.55 | Q95: =(ROUND((ROUND((((ET95*1.1))*AV95*I95),2)*BB95),2)+ROUND((ROUND(((AE95-((EU95*1.1)))*AV95*I95),2)*BS95),2)) -> 13.91 | R95: =(ROUND((ROUND((((EU95*1.1))*AV95*I95),2)*BS95),2)+ROUND((ROUND(((AE95-((EU95*1.1)))*AV95*I95),2)*BS95),2)) -> 1.56 | S95: =ROUND((ROUND((AF95*AV95*I95),2)*BA95),2) -> 175.62 | T95: =ROUND(CU95*I95,2) -> 0 | U95: =CV95*I95 -> 14.277625 | V95: =CW95*I95 -> 0 | W95: =ROUND(CX95*I95,2) -> 0 | X95: =(ROUND((((S95+ROUND((ROUND((((EU95*1.1))*AV95*I95),2)*BS95),2))*AT95)/100),2)+ROUND(((ROUND((ROUND(((AE95-((EU95*1.1)))*AV95*I95),2)*BS95),2)*AT95)/100),2)) -> 171.86 | Y95: =(ROUND((((S95+ROUND((ROUND((((EU95*1.1))*AV95*I95),2)*BS95),2))*AU95)/100),2)+ROUND(((ROUND((ROUND(((AE95-((EU95*1.1)))*AV95*I95),2)*BS95),2)*AU95)/100),2)) -> 90.36 | AA95: 60256985 | AB95: =ROUND((AC95+AD95+AF95),6) -> 140.685 | AC95: =ROUND((ES95),6) -> 61.98 | AD95: =ROUND(((((ET95*1.1))-((EU95*1.1)))+AE95),6) -> 5.775 | AE95: =ROUND(((EU95*1.1)),6) -> 0.649 | AF95: =ROUND(((EV95*1.1)),6) -> 72.93 | AG95: =ROUND((AP95),6) -> 0 | AH95: =((EW95*1.1)) -> 5.929 | AI95: =((EX95*1.1)) -> 0 | AJ95: =(AS95) -> 0 | AK95: 133.53 | AL95: 61.98 | AM95: 5.25 | AN95: 0.59 | AO95: 66.3 | AP95: 0 | AQ95: 5.39 | AR95: 0 | AS95: 0 | AT95: 97 | AU95: 51 | AV95: 1.047 | AW95: 1 | AZ95: 1 | BA95: 1 | BB95: 1 | BC95: 1 | BH95: 0 | BI95: 2 | BJ95: ТСН-2001.4 Доп. 79, Сб. 8, т. 175, поз. 2 | BM95: 67 | BN95: 58973116 | BO95: 4.8-175-2 | BP95: 1 | BQ95: 40 | BR95: 0 | BS95: 1 | BT95: 1 | BU95: 1 | BV95: 1 | BW95: 1 | BX95: 1 | BZ95: 97 | CA95: 51 | CE95: 1566 | CF95: 0 | CG95: 0 | CM95: 0 | CN95: Поправка: О.П. п.3.4.30.в Наименование: При применении территориальных сметных нормативов для города Москвы затраты, учитывающие напряженные и стесненные условия производства работ (стесненность, сложность складирования и транспортной логистики и т.п.), исчисляются с применением коэффициентов к затратам труда и заработной плате рабочих, машинистов, времени эксплуатации машин и механизмов, стоимости эксплуатации машин в размере: для объектов, расположенных за пределами Третьего транспортного кольца города Москвы, но в пределах Московской кольцевой автомобильной дороги | CO95: 0 | CP95: =(P95+Q95+S95) -> 332.08 | CQ95: =ROUND((ROUND((AC95*AW95*1),2)*BC95),2) -> 61.98 | CR95: =(ROUND((ROUND((((ET95*1.1))*AV95*1),2)*BB95),2)+ROUND((ROUND(((AE95-((EU95*1.1)))*AV95*1),2)*BS95),2)) -> 6.05 | CS95: =(ROUND((ROUND((((EU95*1.1))*AV95*1),2)*BS95),2)+ROUND((ROUND(((AE95-((EU95*1.1)))*AV95*1),2)*BS95),2)) -> 0.68 | CT95: =ROUND((ROUND((AF95*AV95*1),2)*BA95),2) -> 76.36 | CU95: =AG95 -> 0 | CV95: =(AH95*AV95) -> 6.207663 | CW95: =AI95 -> 0 | CX95: =AJ95 -> 0 | CY95: =(ROUND((((S95+ROUND((ROUND((((EU95*1.1))*AV95*1),2)*BS95),2))*AT95)/100),2)+ROUND(((ROUND((ROUND(((AE95-((EU95*1.1)))*AV95*1),2)*BS95),2)*AT95)/100),2)) -> 171.01 | CZ95: =(ROUND((((S95+ROUND((ROUND((((EU95*1.1))*AV95*1),2)*BS95),2))*AU95)/100),2)+ROUND(((ROUND((ROUND(((AE95-((EU95*1.1)))*AV95*1),2)*BS95),2)*AU95)/100),2)) -> 89.91 | DB95: 15 | DE95: *1,1 | DF95: *1,1 | DG95: *1,1 | DI95: *1,1 | DJ95: *1,1 | DN95: 0 | DO95: 0 | DP95: 1 | DQ95: 1 | DU95: 1003 | DV95: 100 м | DW95: 100 м | DX95: 100 | EE95: 60088531 | EF95: 40 | EG95: Монтаж оборудования | EH95: 0 | EJ95: 2 | EK95: 67 | EL95: ТСН-2001.4-8. Электротехнические установки | EM95: ТСН-2001.4-8-1 | EO95: Поправка: О.П. п.3.4.30.в | EQ95: 0 | ER95: 133.53 | ES95: 61.98 | ET95: 5.25 | EU95: 0.59 | EV95: 66.3 | EW95: 5.39 | EX95: 0 | EY95: 0 | FQ95: 0 | FR95: 0 | FS95: 0 | FX95: 97 | FY95: 51 | GD95: 1 | GF95: -1822715932 | GG95: 2 | GH95: 1 | GI95: 2 | GJ95: 0 | GK95: 0 | GL95: =ROUND(IF(AND(BH95=3,BI95=3,FS95<>0),P95,0),2) -> 0 | GM95: =ROUND(O95+X95+Y95,2)+GX95 -> 594.3 | GN95: =IF(OR(BI95=0,BI95=1),GM95-GX95,0) -> 0 | GO95: =IF(BI95=2,GM95-GX95,0) -> 594.3 | GP95: =IF(BI95=4,GM95-GX95,0) -> 0 | GR95: 0 | GS95: 3 | GT95: 0 | GV95: =ROUND((GT95),6) -> 0 | GW95: 1 | GX95: =ROUND(HC95*I95,2) -> 0 | HA95: 0 | HB95: 0 | HC95: =GV95*GW95 -> 0 | HS95: 0 | IK95: 0
A96: 17 | B96: 1 | C96: =ROW(SmtRes!A126) -> 126 | D96: =ROW(EtalonRes!A136) -> 136 | E96: 8 | F96: 4.8-175-2 | G96: Затягивание провода в проложенные трубы и металлические рукава, первого одножильного или многожильного в общей оплетке, суммарное сечение до 6 мм2 | H96: 100 м | I96: =ROUND((200+30)/100,9) -> 2.3 | J96: 0 | K96: =ROUND((200+30)/100,9) -> 2.3 | O96: =ROUND(CP96,2) -> 10505.34 | P96: =ROUND((ROUND((AC96*AW96*I96),2)*BC96),2) -> 645.75 | Q96: =(ROUND((ROUND((((ET96*1.1))*AV96*I96),2)*BB96),2)+ROUND((ROUND(((AE96-((EU96*1.1)))*AV96*I96),2)*BS96),2)) -> 202.25 | R96: =(ROUND((ROUND((((EU96*1.1))*AV96*I96),2)*BS96),2)+ROUND((ROUND(((AE96-((EU96*1.1)))*AV96*I96),2)*BS96),2)) -> 85.78 | S96: =ROUND((ROUND((AF96*AV96*I96),2)*BA96),2) -> 9657.34 | T96: =ROUND(CU96*I96,2) -> 0 | U96: =CV96*I96 -> 14.277625 | V96: =CW96*I96 -> 0 | W96: =ROUND(CX96*I96,2) -> 0 | X96: =(ROUND((((S96+ROUND((ROUND((((EU96*1.1))*AV96*I96),2)*BS96),2))*AT96)/100),2)+ROUND(((ROUND((ROUND(((AE96-((EU96*1.1)))*AV96*I96),2)*BS96),2)*AT96)/100),2)) -> 9450.83 | Y96: =(ROUND((((S96+ROUND((ROUND((((EU96*1.1))*AV96*I96),2)*BS96),2))*AU96)/100),2)+ROUND(((ROUND((ROUND(((AE96-((EU96*1.1)))*AV96*I96),2)*BS96),2)*AU96)/100),2)) -> 4968.99 | AA96: 60256982 | AB96: =ROUND((AC96+AD96+AF96),6) -> 140.685 | AC96: =ROUND((ES96),6) -> 61.98 | AD96: =ROUND(((((ET96*1.1))-((EU96*1.1)))+AE96),6) -> 5.775 | AE96: =ROUND(((EU96*1.1)),6) -> 0.649 | AF96: =ROUND(((EV96*1.1)),6) -> 72.93 | AG96: =ROUND((AP96),6) -> 0 | AH96: =((EW96*1.1)) -> 5.929 | AI96: =((EX96*1.1)) -> 0 | AJ96: =(AS96) -> 0 | AK96: 133.53 | AL96: 61.98 | AM96: 5.25 | AN96: 0.59 | AO96: 66.3 | AP96: 0 | AQ96: 5.39 | AR96: 0 | AS96: 0 | AT96: 97 | AU96: 51 | AV96: 1.047 | AW96: 1 | AZ96: 1 | BA96: 54.99 | BB96: 14.54 | BC96: 4.53 | BH96: 0 | BI96: 2 | BJ96: ТСН-2001.4 Доп. 79, Сб. 8, т. 175, поз. 2 | BM96: 67 | BN96: 58973116 | BO96: 4.8-175-2 | BP96: 1 | BQ96: 40 | BR96: 0 | BS96: 54.99 | BT96: 1 | BU96: 1 | BV96: 1 | BW96: 1 | BX96: 1 | BZ96: 97 | CA96: 51 | CE96: 1566 | CF96: 0 | CG96: 0 | CM96: 0 | CN96: Поправка: О.П. п.3.4.30.в Наименование: При применении территориальных сметных нормативов для города Москвы затраты, учитывающие напряженные и стесненные условия производства работ (стесненность, сложность складирования и транспортной логистики и т.п.), исчисляются с применением коэффициентов к затратам труда и заработной плате рабочих, машинистов, времени эксплуатации машин и механизмов, стоимости эксплуатации машин в размере: для объектов, расположенных за пределами Третьего транспортного кольца города Москвы, но в пределах Московской кольцевой автомобильной дороги | CO96: 0 | CP96: =(P96+Q96+S96) -> 10505.34 | CQ96: =ROUND((ROUND((AC96*AW96*1),2)*BC96),2) -> 280.77 | CR96: =(ROUND((ROUND((((ET96*1.1))*AV96*1),2)*BB96),2)+ROUND((ROUND(((AE96-((EU96*1.1)))*AV96*1),2)*BS96),2)) -> 87.97 | CS96: =(ROUND((ROUND((((EU96*1.1))*AV96*1),2)*BS96),2)+ROUND((ROUND(((AE96-((EU96*1.1)))*AV96*1),2)*BS96),2)) -> 37.39 | CT96: =ROUND((ROUND((AF96*AV96*1),2)*BA96),2) -> 4199.04 | CU96: =AG96 -> 0 | CV96: =(AH96*AV96) -> 6.207663 | CW96: =AI96 -> 0 | CX96: =AJ96 -> 0 | CY96: =(ROUND((((S96+ROUND((ROUND((((EU96*1.1))*AV96*1),2)*BS96),2))*AT96)/100),2)+ROUND(((ROUND((ROUND(((AE96-((EU96*1.1)))*AV96*1),2)*BS96),2)*AT96)/100),2)) -> 9403.89 | CZ96: =(ROUND((((S96+ROUND((ROUND((((EU96*1.1))*AV96*1),2)*BS96),2))*AU96)/100),2)+ROUND(((ROUND((ROUND(((AE96-((EU96*1.1)))*AV96*1),2)*BS96),2)*AU96)/100),2)) -> 4944.31 | DB96: 16 | DE96: *1,1 | DF96: *1,1 | DG96: *1,1 | DI96: *1,1 | DJ96: *1,1 | DN96: 0 | DO96: 0 | DP96: 1 | DQ96: 1 | DU96: 1003 | DV96: 100 м | DW96: 100 м | DX96: 100 | EE96: 60088531 | EF96: 40 | EG96: Монтаж оборудования | EH96: 0 | EJ96: 2 | EK96: 67 | EL96: ТСН-2001.4-8. Электротехнические установки | EM96: ТСН-2001.4-8-1 | EO96: Поправка: О.П. п.3.4.30.в | EQ96: 0 | ER96: 133.53 | ES96: 61.98 | ET96: 5.25 | EU96: 0.59 | EV96: 66.3 | EW96: 5.39 | EX96: 0 | EY96: 0 | FQ96: 0 | FR96: 0 | FS96: 0 | FX96: 97 | FY96: 51 | GD96: 1 | GF96: -1822715932 | GG96: 2 | GH96: 1 | GI96: 2 | GJ96: 0 | GK96: 0 | GL96: =ROUND(IF(AND(BH96=3,BI96=3,FS96<>0),P96,0),2) -> 0 | GM96: =ROUND(O96+X96+Y96,2)+GX96 -> 24925.16 | GN96: =IF(OR(BI96=0,BI96=1),GM96-GX96,0) -> 0 | GO96: =IF(BI96=2,GM96-GX96,0) -> 24925.16 | GP96: =IF(BI96=4,GM96-GX96,0) -> 0 | GR96: 0 | GS96: 3 | GT96: 0 | GV96: =ROUND((GT96),6) -> 0 | GW96: 1 | GX96: =ROUND(HC96*I96,2) -> 0 | HA96: 0 | HB96: 0 | HC96: =GV96*GW96 -> 0 | HS96: 0 | IK96: 0
A97: 17 | B97: 1 | C97: =ROW(SmtRes!A134) -> 134 | D97: =ROW(EtalonRes!A145) -> 145 | E97: 9 | F97: 4.8-175-9 | G97: Добавлять на затягивание провода в проложенные трубы и металлические рукава каждого последующего одножильного или многожильного в общей оплетке, суммарное сечение до 6 мм2 (к нормам и расценкам 4.8-175-1 и 4.8-175-2) | H97: 100 м | I97: =ROUND((150+350+10+40+20+50+20+10-230)/100,9) -> 4.2 | J97: 0 | K97: =ROUND((150+350+10+40+20+50+20+10-230)/100,9) -> 4.2 | O97: =ROUND(CP97,2) -> 354.52 | P97: =ROUND((ROUND((AC97*AW97*I97),2)*BC97),2) -> 232.97 | Q97: =(ROUND((ROUND((((ET97*1.1))*AV97*I97),2)*BB97),2)+ROUND((ROUND(((AE97-((EU97*1.1)))*AV97*I97),2)*BS97),2)) -> 12.67 | R97: =(ROUND((ROUND((((EU97*1.1))*AV97*I97),2)*BS97),2)+ROUND((ROUND(((AE97-((EU97*1.1)))*AV97*I97),2)*BS97),2)) -> 1.45 | S97: =ROUND((ROUND((AF97*AV97*I97),2)*BA97),2) -> 108.88 | T97: =ROUND(CU97*I97,2) -> 0 | U97: =CV97*I97 -> 8.8519662 | V97: =CW97*I97 -> 0 | W97: =ROUND(CX97*I97,2) -> 0 | X97: =(ROUND((((S97+ROUND((ROUND((((EU97*1.1))*AV97*I97),2)*BS97),2))*AT97)/100),2)+ROUND(((ROUND((ROUND(((AE97-((EU97*1.1)))*AV97*I97),2)*BS97),2)*AT97)/100),2)) -> 107.02 | Y97: =(ROUND((((S97+ROUND((ROUND((((EU97*1.1))*AV97*I97),2)*BS97),2))*AU97)/100),2)+ROUND(((ROUND((ROUND(((AE97-((EU97*1.1)))*AV97*I97),2)*BS97),2)*AU97)/100),2)) -> 56.27 | AA97: 60256985 | AB97: =ROUND((AC97+AD97+AF97),6) -> 83.113 | AC97: =ROUND((ES97),6) -> 55.47 | AD97: =ROUND(((((ET97*1.1))-((EU97*1.1)))+AE97),6) -> 2.882 | AE97: =ROUND(((EU97*1.1)),6) -> 0.33 | AF97: =ROUND(((EV97*1.1)),6) -> 24.761 | AG97: =ROUND((AP97),6) -> 0 | AH97: =((EW97*1.1)) -> 2.013 | AI97: =((EX97*1.1)) -> 0 | AJ97: =(AS97) -> 0 | AK97: 80.6 | AL97: 55.47 | AM97: 2.62 | AN97: 0.3 | AO97: 22.51 | AP97: 0 | AQ97: 1.83 | AR97: 0 | AS97: 0 | AT97: 97 | AU97: 51 | AV97: 1.047 | AW97: 1 | AZ97: 1 | BA97: 1 | BB97: 1 | BC97: 1 | BH97: 0 | BI97: 2 | BJ97: ТСН-2001.4 Доп. 80, Сб. 8, т. 175, поз. 9 | BM97: 67 | BN97: 58973116 | BO97: 4.8-175-9 | BP97: 1 | BQ97: 40 | BR97: 0 | BS97: 1 | BT97: 1 | BU97: 1 | BV97: 1 | BW97: 1 | BX97: 1 | BZ97: 97 | CA97: 51 | CE97: 1566 | CF97: 0 | CG97: 0 | CM97: 0 | CN97: Поправка: О.П. п.3.4.30.в Наименование: При применении территориальных сметных нормативов для города Москвы затраты, учитывающие напряженные и стесненные условия производства работ (стесненность, сложность складирования и транспортной логистики и т.п.), исчисляются с применением коэффициентов к затратам труда и заработной плате рабочих, машинистов, времени эксплуатации машин и механизмов, стоимости эксплуатации машин в размере: для объектов, расположенных за пределами Третьего транспортного кольца города Москвы, но в пределах Московской кольцевой автомобильной дороги | CO97: 0 | CP97: =(P97+Q97+S97) -> 354.52 | CQ97: =ROUND((ROUND((AC97*AW97*1),2)*BC97),2) -> 55.47 | CR97: =(ROUND((ROUND((((ET97*1.1))*AV97*1),2)*BB97),2)+ROUND((ROUND(((AE97-((EU97*1.1)))*AV97*1),2)*BS97),2)) -> 3.02 | CS97: =(ROUND((ROUND((((EU97*1.1))*AV97*1),2)*BS97),2)+ROUND((ROUND(((AE97-((EU97*1.1)))*AV97*1),2)*BS97),2)) -> 0.35 | CT97: =ROUND((ROUND((AF97*AV97*1),2)*BA97),2) -> 25.92 | CU97: =AG97 -> 0 | CV97: =(AH97*AV97) -> 2.107611 | CW97: =AI97 -> 0 | CX97: =AJ97 -> 0 | CY97: =(ROUND((((S97+ROUND((ROUND((((EU97*1.1))*AV97*1),2)*BS97),2))*AT97)/100),2)+ROUND(((ROUND((ROUND(((AE97-((EU97*1.1)))*AV97*1),2)*BS97),2)*AT97)/100),2)) -> 105.95 | CZ97: =(ROUND((((S97+ROUND((ROUND((((EU97*1.1))*AV97*1),2)*BS97),2))*AU97)/100),2)+ROUND(((ROUND((ROUND(((AE97-((EU97*1.1)))*AV97*1),2)*BS97),2)*AU97)/100),2)) -> 55.71 | DB97: 17 | DE97: *1,1 | DF97: *1,1 | DG97: *1,1 | DI97: *1,1 | DJ97: *1,1 | DN97: 0 | DO97: 0 | DP97: 1 | DQ97: 1 | DU97: 1003 | DV97: 100 м | DW97: 100 м | DX97: 100 | EE97: 60088531 | EF97: 40 | EG97: Монтаж оборудования | EH97: 0 | EJ97: 2 | EK97: 67 | EL97: ТСН-2001.4-8. Электротехнические установки | EM97: ТСН-2001.4-8-1 | EO97: Поправка: О.П. п.3.4.30.в | EQ97: 0 | ER97: 80.6 | ES97: 55.47 | ET97: 2.62 | EU97: 0.3 | EV97: 22.51 | EW97: 1.83 | EX97: 0 | EY97: 0 | FQ97: 0 | FR97: 0 | FS97: 0 | FX97: 97 | FY97: 51 | GD97: 1 | GF97: 1118340632 | GG97: 2 | GH97: 1 | GI97: 2 | GJ97: 0 | GK97: 0 | GL97: =ROUND(IF(AND(BH97=3,BI97=3,FS97<>0),P97,0),2) -> 0 | GM97: =ROUND(O97+X97+Y97,2)+GX97 -> 517.81 | GN97: =IF(OR(BI97=0,BI97=1),GM97-GX97,0) -> 0 | GO97: =IF(BI97=2,GM97-GX97,0) -> 517.81 | GP97: =IF(BI97=4,GM97-GX97,0) -> 0 | GR97: 0 | GS97: 3 | GT97: 0 | GV97: =ROUND((GT97),6) -> 0 | GW97: 1 | GX97: =ROUND(HC97*I97,2) -> 0 | HA97: 0 | HB97: 0 | HC97: =GV97*GW97 -> 0 | HS97: 0 | IK97: 0
A98: 17 | B98: 1 | C98: =ROW(SmtRes!A142) -> 142 | D98: =ROW(EtalonRes!A154) -> 154 | E98: 9 | F98: 4.8-175-9 | G98: Добавлять на затягивание провода в проложенные трубы и металлические рукава каждого последующего одножильного или многожильного в общей оплетке, суммарное сечение до 6 мм2 (к нормам и расценкам 4.8-175-1 и 4.8-175-2) | H98: 100 м | I98: =ROUND((150+350+10+40+20+50+20+10-230)/100,9) -> 4.2 | J98: 0 | K98: =ROUND((150+350+10+40+20+50+20+10-230)/100,9) -> 4.2 | O98: =ROUND(CP98,2) -> 6891.79 | P98: =ROUND((ROUND((AC98*AW98*I98),2)*BC98),2) -> 719.88 | Q98: =(ROUND((ROUND((((ET98*1.1))*AV98*I98),2)*BB98),2)+ROUND((ROUND(((AE98-((EU98*1.1)))*AV98*I98),2)*BS98),2)) -> 184.6 | R98: =(ROUND((ROUND((((EU98*1.1))*AV98*I98),2)*BS98),2)+ROUND((ROUND(((AE98-((EU98*1.1)))*AV98*I98),2)*BS98),2)) -> 79.74 | S98: =ROUND((ROUND((AF98*AV98*I98),2)*BA98),2) -> 5987.31 | T98: =ROUND(CU98*I98,2) -> 0 | U98: =CV98*I98 -> 8.8519662 | V98: =CW98*I98 -> 0 | W98: =ROUND(CX98*I98,2) -> 0 | X98: =(ROUND((((S98+ROUND((ROUND((((EU98*1.1))*AV98*I98),2)*BS98),2))*AT98)/100),2)+ROUND(((ROUND((ROUND(((AE98-((EU98*1.1)))*AV98*I98),2)*BS98),2)*AT98)/100),2)) -> 5885.04 | Y98: =(ROUND((((S98+ROUND((ROUND((((EU98*1.1))*AV98*I98),2)*BS98),2))*AU98)/100),2)+ROUND(((ROUND((ROUND(((AE98-((EU98*1.1)))*AV98*I98),2)*BS98),2)*AU98)/100),2)) -> 3094.2 | AA98: 60256982 | AB98: =ROUND((AC98+AD98+AF98),6) -> 83.113 | AC98: =ROUND((ES98),6) -> 55.47 | AD98: =ROUND(((((ET98*1.1))-((EU98*1.1)))+AE98),6) -> 2.882 | AE98: =ROUND(((EU98*1.1)),6) -> 0.33 | AF98: =ROUND(((EV98*1.1)),6) -> 24.761 | AG98: =ROUND((AP98),6) -> 0 | AH98: =((EW98*1.1)) -> 2.013 | AI98: =((EX98*1.1)) -> 0 | AJ98: =(AS98) -> 0 | AK98: 80.6 | AL98: 55.47 | AM98: 2.62 | AN98: 0.3 | AO98: 22.51 | AP98: 0 | AQ98: 1.83 | AR98: 0 | AS98: 0 | AT98: 97 | AU98: 51 | AV98: 1.047 | AW98: 1 | AZ98: 1 | BA98: 54.99 | BB98: 14.57 | BC98: 3.09 | BH98: 0 | BI98: 2 | BJ98: ТСН-2001.4 Доп. 80, Сб. 8, т. 175, поз. 9 | BM98: 67 | BN98: 58973116 | BO98: 4.8-175-9 | BP98: 1 | BQ98: 40 | BR98: 0 | BS98: 54.99 | BT98: 1 | BU98: 1 | BV98: 1 | BW98: 1 | BX98: 1 | BZ98: 97 | CA98: 51 | CE98: 1566 | CF98: 0 | CG98: 0 | CM98: 0 | CN98: Поправка: О.П. п.3.4.30.в Наименование: При применении территориальных сметных нормативов для города Москвы затраты, учитывающие напряженные и стесненные условия производства работ (стесненность, сложность складирования и транспортной логистики и т.п.), исчисляются с применением коэффициентов к затратам труда и заработной плате рабочих, машинистов, времени эксплуатации машин и механизмов, стоимости эксплуатации машин в размере: для объектов, расположенных за пределами Третьего транспортного кольца города Москвы, но в пределах Московской кольцевой автомобильной дороги | CO98: 0 | CP98: =(P98+Q98+S98) -> 6891.79 | CQ98: =ROUND((ROUND((AC98*AW98*1),2)*BC98),2) -> 171.4 | CR98: =(ROUND((ROUND((((ET98*1.1))*AV98*1),2)*BB98),2)+ROUND((ROUND(((AE98-((EU98*1.1)))*AV98*1),2)*BS98),2)) -> 44 | CS98: =(ROUND((ROUND((((EU98*1.1))*AV98*1),2)*BS98),2)+ROUND((ROUND(((AE98-((EU98*1.1)))*AV98*1),2)*BS98),2)) -> 19.25 | CT98: =ROUND((ROUND((AF98*AV98*1),2)*BA98),2) -> 1425.34 | CU98: =AG98 -> 0 | CV98: =(AH98*AV98) -> 2.107611 | CW98: =AI98 -> 0 | CX98: =AJ98 -> 0 | CY98: =(ROUND((((S98+ROUND((ROUND((((EU98*1.1))*AV98*1),2)*BS98),2))*AT98)/100),2)+ROUND(((ROUND((ROUND(((AE98-((EU98*1.1)))*AV98*1),2)*BS98),2)*AT98)/100),2)) -> 5826.36 | CZ98: =(ROUND((((S98+ROUND((ROUND((((EU98*1.1))*AV98*1),2)*BS98),2))*AU98)/100),2)+ROUND(((ROUND((ROUND(((AE98-((EU98*1.1)))*AV98*1),2)*BS98),2)*AU98)/100),2)) -> 3063.35 | DB98: 18 | DE98: *1,1 | DF98: *1,1 | DG98: *1,1 | DI98: *1,1 | DJ98: *1,1 | DN98: 0 | DO98: 0 | DP98: 1 | DQ98: 1 | DU98: 1003 | DV98: 100 м | DW98: 100 м | DX98: 100 | EE98: 60088531 | EF98: 40 | EG98: Монтаж оборудования | EH98: 0 | EJ98: 2 | EK98: 67 | EL98: ТСН-2001.4-8. Электротехнические установки | EM98: ТСН-2001.4-8-1 | EO98: Поправка: О.П. п.3.4.30.в | EQ98: 0 | ER98: 80.6 | ES98: 55.47 | ET98: 2.62 | EU98: 0.3 | EV98: 22.51 | EW98: 1.83 | EX98: 0 | EY98: 0 | FQ98: 0 | FR98: 0 | FS98: 0 | FX98: 97 | FY98: 51 | GD98: 1 | GF98: 1118340632 | GG98: 2 | GH98: 1 | GI98: 2 | GJ98: 0 | GK98: 0 | GL98: =ROUND(IF(AND(BH98=3,BI98=3,FS98<>0),P98,0),2) -> 0 | GM98: =ROUND(O98+X98+Y98,2)+GX98 -> 15871.03 | GN98: =IF(OR(BI98=0,BI98=1),GM98-GX98,0) -> 0 | GO98: =IF(BI98=2,GM98-GX98,0) -> 15871.03 | GP98: =IF(BI98=4,GM98-GX98,0) -> 0 | GR98: 0 | GS98: 3 | GT98: 0 | GV98: =ROUND((GT98),6) -> 0 | GW98: 1 | GX98: =ROUND(HC98*I98,2) -> 0 | HA98: 0 | HB98: 0 | HC98: =GV98*GW98 -> 0 | HS98: 0 | IK98: 0
A99: 17 | B99: 1 | E99: 10 | F99: КА-5 | G99: Кабель распределительный КПСВВнг(А)-LSLTx 1x2x1,5 | H99: км | I99: =ROUND((150*1.02)/1000,9) -> 0.153 | J99: 0 | K99: =ROUND((150*1.02)/1000,9) -> 0.153 | O99: =ROUND(CP99,2) -> 671.31 | P99: =ROUND((ROUND((AC99*AW99*I99),2)*BC99),2) -> 671.31 | Q99: =(ROUND((ROUND(((ET99)*AV99*I99),2)*BB99),2)+ROUND((ROUND(((AE99-(EU99))*AV99*I99),2)*BS99),2)) -> 0 | R99: =(ROUND((ROUND(((EU99)*AV99*I99),2)*BS99),2)+ROUND((ROUND(((AE99-(EU99))*AV99*I99),2)*BS99),2)) -> 0 | S99: =ROUND((ROUND((AF99*AV99*I99),2)*BA99),2) -> 0 | T99: =ROUND(CU99*I99,2) -> 0 | U99: =CV99*I99 -> 0 | V99: =CW99*I99 -> 0 | W99: =ROUND(CX99*I99,2) -> 0 | X99: =(ROUND((((S99+ROUND((ROUND(((EU99)*AV99*I99),2)*BS99),2))*AT99)/100),2)+ROUND(((ROUND((ROUND(((AE99-(EU99))*AV99*I99),2)*BS99),2)*AT99)/100),2)) -> 0 | Y99: =(ROUND((((S99+ROUND((ROUND(((EU99)*AV99*I99),2)*BS99),2))*AU99)/100),2)+ROUND(((ROUND((ROUND(((AE99-(EU99))*AV99*I99),2)*BS99),2)*AU99)/100),2)) -> 0 | AA99: 60256985 | AB99: =ROUND((AC99+AD99+AF99),6) -> 4387.65 | AC99: =ROUND((ES99),6) -> 4387.65 | AD99: =ROUND((((ET99)-(EU99))+AE99),6) -> 0 | AE99: =ROUND((EU99),6) -> 0 | AF99: =ROUND((EV99),6) -> 0 | AG99: =ROUND((AP99),6) -> 0 | AH99: =(EW99) -> 0 | AI99: =(EX99) -> 0 | AJ99: =(AS99) -> 0 | AK99: 4387.65 | AL99: 4387.65 | AM99: 0 | AN99: 0 | AO99: 0 | AP99: 0 | AQ99: 0 | AR99: 0 | AS99: 0 | AT99: 0 | AU99: 0 | AV99: 1 | AW99: 1 | AZ99: 1 | BA99: 1 | BB99: 1 | BC99: 1 | BH99: 3 | BI99: 2 | BM99: 400002 | BN99: 0 | BP99: 0 | BQ99: 202 | BR99: 0 | BS99: 1 | BT99: 1 | BU99: 1 | BV99: 1 | BW99: 1 | BX99: 1 | BZ99: 0 | CA99: 0 | CE99: 1566 | CF99: 0 | CG99: 0 | CM99: 0 | CO99: 0 | CP99: =(P99+Q99+S99) -> 671.31 | CQ99: =ROUND((ROUND((AC99*AW99*1),2)*BC99),2) -> 4387.65 | CR99: =(ROUND((ROUND(((ET99)*AV99*1),2)*BB99),2)+ROUND((ROUND(((AE99-(EU99))*AV99*1),2)*BS99),2)) -> 0 | CS99: =(ROUND((ROUND(((EU99)*AV99*1),2)*BS99),2)+ROUND((ROUND(((AE99-(EU99))*AV99*1),2)*BS99),2)) -> 0 | CT99: =ROUND((ROUND((AF99*AV99*1),2)*BA99),2) -> 0 | CU99: =AG99 -> 0 | CV99: =(AH99*AV99) -> 0 | CW99: =AI99 -> 0 | CX99: =AJ99 -> 0 | CY99: =(ROUND((((S99+ROUND((ROUND(((EU99)*AV99*1),2)*BS99),2))*AT99)/100),2)+ROUND(((ROUND((ROUND(((AE99-(EU99))*AV99*1),2)*BS99),2)*AT99)/100),2)) -> 0 | CZ99: =(ROUND((((S99+ROUND((ROUND(((EU99)*AV99*1),2)*BS99),2))*AU99)/100),2)+ROUND(((ROUND((ROUND(((AE99-(EU99))*AV99*1),2)*BS99),2)*AU99)/100),2)) -> 0 | DN99: 0 | DO99: 0 | DP99: 1 | DQ99: 1 | DU99: 1003 | DV99: км | DW99: км | DX99: 1000 | EE99: 60088644 | EF99: 202 | EG99: Материалы | EH99: 0 | EJ99: 1 | EK99: 400002 | EL99: Материалы, изделия и конструкции | EM99: Материалы | EQ99: 0 | ER99: 0 | ES99: 4387.65 | ET99: 0 | EU99: 0 | EV99: 0 | EW99: 0 | EX99: 0 | EY99: 0 | FQ99: 0 | FR99: 0 | FS99: 0 | FX99: 0 | FY99: 0 | GA99: [51 000 / 1,2 / 9,88] + 2% Заг.скл | GD99: 1 | GF99: 8023903 | GG99: 2 | GH99: 4 | GI99: -2 | GJ99: 0 | GK99: 0 | GL99: =ROUND(IF(AND(BH99=3,BI99=3,FS99<>0),P99,0),2) -> 0 | GM99: =ROUND(O99+X99+Y99,2)+GX99 -> 671.31 | GN99: =IF(OR(BI99=0,BI99=1),GM99-GX99,0) -> 0 | GO99: =IF(BI99=2,GM99-GX99,0) -> 671.31 | GP99: =IF(BI99=4,GM99-GX99,0) -> 0 | GR99: 0 | GS99: 2 | GT99: 0 | GV99: =ROUND((GT99),6) -> 0 | GW99: 1 | GX99: =ROUND(HC99*I99,2) -> 0 | HA99: 0 | HB99: 0 | HC99: =GV99*GW99 -> 0 | HE99: 0 | HF99: 2 | HS99: 0 | IK99: 0
A100: 17 | B100: 1 | E100: 10 | F100: КА-5 | G100: Кабель распределительный КПСВВнг(А)-LSLTx 1x2x1,5 | H100: км | I100: =ROUND((150*1.02)/1000,9) -> 0.153 | J100: 0 | K100: =ROUND((150*1.02)/1000,9) -> 0.153 | O100: =ROUND(CP100,2) -> 6632.54 | P100: =ROUND((ROUND((AC100*AW100*I100),2)*BC100),2) -> 6632.54 | Q100: =(ROUND((ROUND(((ET100)*AV100*I100),2)*BB100),2)+ROUND((ROUND(((AE100-(EU100))*AV100*I100),2)*BS100),2)) -> 0 | R100: =(ROUND((ROUND(((EU100)*AV100*I100),2)*BS100),2)+ROUND((ROUND(((AE100-(EU100))*AV100*I100),2)*BS100),2)) -> 0 | S100: =ROUND((ROUND((AF100*AV100*I100),2)*BA100),2) -> 0 | T100: =ROUND(CU100*I100,2) -> 0 | U100: =CV100*I100 -> 0 | V100: =CW100*I100 -> 0 | W100: =ROUND(CX100*I100,2) -> 0 | X100: =(ROUND((((S100+ROUND((ROUND(((EU100)*AV100*I100),2)*BS100),2))*AT100)/100),2)+ROUND(((ROUND((ROUND(((AE100-(EU100))*AV100*I100),2)*BS100),2)*AT100)/100),2)) -> 0 | Y100: =(ROUND((((S100+ROUND((ROUND(((EU100)*AV100*I100),2)*BS100),2))*AU100)/100),2)+ROUND(((ROUND((ROUND(((AE100-(EU100))*AV100*I100),2)*BS100),2)*AU100)/100),2)) -> 0 | AA100: 60256982 | AB100: =ROUND((AC100+AD100+AF100),6) -> 4387.65 | AC100: =ROUND((ES100),6) -> 4387.65 | AD100: =ROUND((((ET100)-(EU100))+AE100),6) -> 0 | AE100: =ROUND((EU100),6) -> 0 | AF100: =ROUND((EV100),6) -> 0 | AG100: =ROUND((AP100),6) -> 0 | AH100: =(EW100) -> 0 | AI100: =(EX100) -> 0 | AJ100: =(AS100) -> 0 | AK100: 4387.65 | AL100: 4387.65 | AM100: 0 | AN100: 0 | AO100: 0 | AP100: 0 | AQ100: 0 | AR100: 0 | AS100: 0 | AT100: 0 | AU100: 0 | AV100: 1 | AW100: 1 | AZ100: 1 | BA100: 1 | BB100: 1 | BC100: 9.88 | BH100: 3 | BI100: 2 | BM100: 400002 | BN100: 0 | BP100: 0 | BQ100: 202 | BR100: 0 | BS100: 1 | BT100: 1 | BU100: 1 | BV100: 1 | BW100: 1 | BX100: 1 | BZ100: 0 | CA100: 0 | CE100: 1566 | CF100: 0 | CG100: 0 | CM100: 0 | CO100: 0 | CP100: =(P100+Q100+S100) -> 6632.54 | CQ100: =ROUND((ROUND((AC100*AW100*1),2)*BC100),2) -> 43349.98 | CR100: =(ROUND((ROUND(((ET100)*AV100*1),2)*BB100),2)+ROUND((ROUND(((AE100-(EU100))*AV100*1),2)*BS100),2)) -> 0 | CS100: =(ROUND((ROUND(((EU100)*AV100*1),2)*BS100),2)+ROUND((ROUND(((AE100-(EU100))*AV100*1),2)*BS100),2)) -> 0 | CT100: =ROUND((ROUND((AF100*AV100*1),2)*BA100),2) -> 0 | CU100: =AG100 -> 0 | CV100: =(AH100*AV100) -> 0 | CW100: =AI100 -> 0 | CX100: =AJ100 -> 0 | CY100: =(ROUND((((S100+ROUND((ROUND(((EU100)*AV100*1),2)*BS100),2))*AT100)/100),2)+ROUND(((ROUND((ROUND(((AE100-(EU100))*AV100*1),2)*BS100),2)*AT100)/100),2)) -> 0 | CZ100: =(ROUND((((S100+ROUND((ROUND(((EU100)*AV100*1),2)*BS100),2))*AU100)/100),2)+ROUND(((ROUND((ROUND(((AE100-(EU100))*AV100*1),2)*BS100),2)*AU100)/100),2)) -> 0 | DN100: 0 | DO100: 0 | DP100: 1 | DQ100: 1 | DU100: 1003 | DV100: км | DW100: км | DX100: 1000 | EE100: 60088644 | EF100: 202 | EG100: Материалы | EH100: 0 | EJ100: 1 | EK100: 400002 | EL100: Материалы, изделия и конструкции | EM100: Материалы | EQ100: 0 | ER100: 0 | ES100: 4387.65 | ET100: 0 | EU100: 0 | EV100: 0 | EW100: 0 | EX100: 0 | EY100: 0 | EZ100: 5 | FC100: 1 | FD100: 18 | FF100: 51000 | FQ100: 0 | FR100: 0 | FS100: 0 | FX100: 0 | FY100: 0 | GA100: [51 000 / 1,2 / 9,88] + 2% Заг.скл | GD100: 1 | GF100: 8023903 | GG100: 2 | GH100: 3 | GI100: 5 | GJ100: 0 | GK100: 0 | GL100: =ROUND(IF(AND(BH100=3,BI100=3,FS100<>0),P100,0),2) -> 0 | GM100: =ROUND(O100+X100+Y100,2)+GX100 -> 6632.54 | GN100: =IF(OR(BI100=0,BI100=1),GM100-GX100,0) -> 0 | GO100: =IF(BI100=2,GM100-GX100,0) -> 6632.54 | GP100: =IF(BI100=4,GM100-GX100,0) -> 0 | GR100: 1 | GS100: 1 | GT100: 0 | GV100: =ROUND((GT100),6) -> 0 | GW100: 1 | GX100: =ROUND(HC100*I100,2) -> 0 | HA100: 0 | HB100: 0 | HC100: =GV100*GW100 -> 0 | HE100: 0 | HF100: 2 | HS100: 0 | IK100: 0
A101: 17 | B101: 1 | E101: 11 | F101: КА-6 | G101: Кабель абонентский КПСВВнг(А)-LSLTx 1x2x0,5 | H101: км | I101: =ROUND((350*1.02)/1000,9) -> 0.357 | J101: 0 | K101: =ROUND((350*1.02)/1000,9) -> 0.357 | O101: =ROUND(CP101,2) -> 609.97 | P101: =ROUND((ROUND((AC101*AW101*I101),2)*BC101),2) -> 609.97 | Q101: =(ROUND((ROUND(((ET101)*AV101*I101),2)*BB101),2)+ROUND((ROUND(((AE101-(EU101))*AV101*I101),2)*BS101),2)) -> 0 | R101: =(ROUND((ROUND(((EU101)*AV101*I101),2)*BS101),2)+ROUND((ROUND(((AE101-(EU101))*AV101*I101),2)*BS101),2)) -> 0 | S101: =ROUND((ROUND((AF101*AV101*I101),2)*BA101),2) -> 0 | T101: =ROUND(CU101*I101,2) -> 0 | U101: =CV101*I101 -> 0 | V101: =CW101*I101 -> 0 | W101: =ROUND(CX101*I101,2) -> 0 | X101: =(ROUND((((S101+ROUND((ROUND(((EU101)*AV101*I101),2)*BS101),2))*AT101)/100),2)+ROUND(((ROUND((ROUND(((AE101-(EU101))*AV101*I101),2)*BS101),2)*AT101)/100),2)) -> 0 | Y101: =(ROUND((((S101+ROUND((ROUND(((EU101)*AV101*I101),2)*BS101),2))*AU101)/100),2)+ROUND(((ROUND((ROUND(((AE101-(EU101))*AV101*I101),2)*BS101),2)*AU101)/100),2)) -> 0 | AA101: 60256985 | AB101: =ROUND((AC101+AD101+AF101),6) -> 1708.6 | AC101: =ROUND((ES101),6) -> 1708.6 | AD101: =ROUND((((ET101)-(EU101))+AE101),6) -> 0 | AE101: =ROUND((EU101),6) -> 0 | AF101: =ROUND((EV101),6) -> 0 | AG101: =ROUND((AP101),6) -> 0 | AH101: =(EW101) -> 0 | AI101: =(EX101) -> 0 | AJ101: =(AS101) -> 0 | AK101: 1708.6 | AL101: 1708.6 | AM101: 0 | AN101: 0 | AO101: 0 | AP101: 0 | AQ101: 0 | AR101: 0 | AS101: 0 | AT101: 0 | AU101: 0 | AV101: 1 | AW101: 1 | AZ101: 1 | BA101: 1 | BB101: 1 | BC101: 1 | BH101: 3 | BI101: 2 | BM101: 400002 | BN101: 0 | BP101: 0 | BQ101: 202 | BR101: 0 | BS101: 1 | BT101: 1 | BU101: 1 | BV101: 1 | BW101: 1 | BX101: 1 | BZ101: 0 | CA101: 0 | CE101: 1566 | CF101: 0 | CG101: 0 | CM101: 0 | CO101: 0 | CP101: =(P101+Q101+S101) -> 609.97 | CQ101: =ROUND((ROUND((AC101*AW101*1),2)*BC101),2) -> 1708.6 | CR101: =(ROUND((ROUND(((ET101)*AV101*1),2)*BB101),2)+ROUND((ROUND(((AE101-(EU101))*AV101*1),2)*BS101),2)) -> 0 | CS101: =(ROUND((ROUND(((EU101)*AV101*1),2)*BS101),2)+ROUND((ROUND(((AE101-(EU101))*AV101*1),2)*BS101),2)) -> 0 | CT101: =ROUND((ROUND((AF101*AV101*1),2)*BA101),2) -> 0 | CU101: =AG101 -> 0 | CV101: =(AH101*AV101) -> 0 | CW101: =AI101 -> 0 | CX101: =AJ101 -> 0 | CY101: =(ROUND((((S101+ROUND((ROUND(((EU101)*AV101*1),2)*BS101),2))*AT101)/100),2)+ROUND(((ROUND((ROUND(((AE101-(EU101))*AV101*1),2)*BS101),2)*AT101)/100),2)) -> 0 | CZ101: =(ROUND((((S101+ROUND((ROUND(((EU101)*AV101*1),2)*BS101),2))*AU101)/100),2)+ROUND(((ROUND((ROUND(((AE101-(EU101))*AV101*1),2)*BS101),2)*AU101)/100),2)) -> 0 | DN101: 0 | DO101: 0 | DP101: 1 | DQ101: 1 | DU101: 1003 | DV101: км | DW101: км | DX101: 1000 | EE101: 60088644 | EF101: 202 | EG101: Материалы | EH101: 0 | EJ101: 1 | EK101: 400002 | EL101: Материалы, изделия и конструкции | EM101: Материалы | EQ101: 0 | ER101: 0 | ES101: 1708.6 | ET101: 0 | EU101: 0 | EV101: 0 | EW101: 0 | EX101: 0 | EY101: 0 | FQ101: 0 | FR101: 0 | FS101: 0 | FX101: 0 | FY101: 0 | GA101: [19 860 / 1,2 / 9,88] + 2% Заг.скл | GD101: 1 | GF101: -2083123476 | GG101: 2 | GH101: 4 | GI101: -2 | GJ101: 0 | GK101: 0 | GL101: =ROUND(IF(AND(BH101=3,BI101=3,FS101<>0),P101,0),2) -> 0 | GM101: =ROUND(O101+X101+Y101,2)+GX101 -> 609.97 | GN101: =IF(OR(BI101=0,BI101=1),GM101-GX101,0) -> 0 | GO101: =IF(BI101=2,GM101-GX101,0) -> 609.97 | GP101: =IF(BI101=4,GM101-GX101,0) -> 0 | GR101: 0 | GS101: 2 | GT101: 0 | GV101: =ROUND((GT101),6) -> 0 | GW101: 1 | GX101: =ROUND(HC101*I101,2) -> 0 | HA101: 0 | HB101: 0 | HC101: =GV101*GW101 -> 0 | HE101: 0 | HF101: 2 | HS101: 0 | IK101: 0
A102: 17 | B102: 1 | E102: 11 | F102: КА-6 | G102: Кабель абонентский КПСВВнг(А)-LSLTx 1x2x0,5 | H102: км | I102: =ROUND((350*1.02)/1000,9) -> 0.357 | J102: 0 | K102: =ROUND((350*1.02)/1000,9) -> 0.357 | O102: =ROUND(CP102,2) -> 6026.5 | P102: =ROUND((ROUND((AC102*AW102*I102),2)*BC102),2) -> 6026.5 | Q102: =(ROUND((ROUND(((ET102)*AV102*I102),2)*BB102),2)+ROUND((ROUND(((AE102-(EU102))*AV102*I102),2)*BS102),2)) -> 0 | R102: =(ROUND((ROUND(((EU102)*AV102*I102),2)*BS102),2)+ROUND((ROUND(((AE102-(EU102))*AV102*I102),2)*BS102),2)) -> 0 | S102: =ROUND((ROUND((AF102*AV102*I102),2)*BA102),2) -> 0 | T102: =ROUND(CU102*I102,2) -> 0 | U102: =CV102*I102 -> 0 | V102: =CW102*I102 -> 0 | W102: =ROUND(CX102*I102,2) -> 0 | X102: =(ROUND((((S102+ROUND((ROUND(((EU102)*AV102*I102),2)*BS102),2))*AT102)/100),2)+ROUND(((ROUND((ROUND(((AE102-(EU102))*AV102*I102),2)*BS102),2)*AT102)/100),2)) -> 0 | Y102: =(ROUND((((S102+ROUND((ROUND(((EU102)*AV102*I102),2)*BS102),2))*AU102)/100),2)+ROUND(((ROUND((ROUND(((AE102-(EU102))*AV102*I102),2)*BS102),2)*AU102)/100),2)) -> 0 | AA102: 60256982 | AB102: =ROUND((AC102+AD102+AF102),6) -> 1708.6 | AC102: =ROUND((ES102),6) -> 1708.6 | AD102: =ROUND((((ET102)-(EU102))+AE102),6) -> 0 | AE102: =ROUND((EU102),6) -> 0 | AF102: =ROUND((EV102),6) -> 0 | AG102: =ROUND((AP102),6) -> 0 | AH102: =(EW102) -> 0 | AI102: =(EX102) -> 0 | AJ102: =(AS102) -> 0 | AK102: 1708.6 | AL102: 1708.6 | AM102: 0 | AN102: 0 | AO102: 0 | AP102: 0 | AQ102: 0 | AR102: 0 | AS102: 0 | AT102: 0 | AU102: 0 | AV102: 1 | AW102: 1 | AZ102: 1 | BA102: 1 | BB102: 1 | BC102: 9.88 | BH102: 3 | BI102: 2 | BM102: 400002 | BN102: 0 | BP102: 0 | BQ102: 202 | BR102: 0 | BS102: 1 | BT102: 1 | BU102: 1 | BV102: 1 | BW102: 1 | BX102: 1 | BZ102: 0 | CA102: 0 | CE102: 1566 | CF102: 0 | CG102: 0 | CM102: 0 | CO102: 0 | CP102: =(P102+Q102+S102) -> 6026.5 | CQ102: =ROUND((ROUND((AC102*AW102*1),2)*BC102),2) -> 16880.97 | CR102: =(ROUND((ROUND(((ET102)*AV102*1),2)*BB102),2)+ROUND((ROUND(((AE102-(EU102))*AV102*1),2)*BS102),2)) -> 0 | CS102: =(ROUND((ROUND(((EU102)*AV102*1),2)*BS102),2)+ROUND((ROUND(((AE102-(EU102))*AV102*1),2)*BS102),2)) -> 0 | CT102: =ROUND((ROUND((AF102*AV102*1),2)*BA102),2) -> 0 | CU102: =AG102 -> 0 | CV102: =(AH102*AV102) -> 0 | CW102: =AI102 -> 0 | CX102: =AJ102 -> 0 | CY102: =(ROUND((((S102+ROUND((ROUND(((EU102)*AV102*1),2)*BS102),2))*AT102)/100),2)+ROUND(((ROUND((ROUND(((AE102-(EU102))*AV102*1),2)*BS102),2)*AT102)/100),2)) -> 0 | CZ102: =(ROUND((((S102+ROUND((ROUND(((EU102)*AV102*1),2)*BS102),2))*AU102)/100),2)+ROUND(((ROUND((ROUND(((AE102-(EU102))*AV102*1),2)*BS102),2)*AU102)/100),2)) -> 0 | DN102: 0 | DO102: 0 | DP102: 1 | DQ102: 1 | DU102: 1003 | DV102: км | DW102: км | DX102: 1000 | EE102: 60088644 | EF102: 202 | EG102: Материалы | EH102: 0 | EJ102: 1 | EK102: 400002 | EL102: Материалы, изделия и конструкции | EM102: Материалы | EQ102: 0 | ER102: 0 | ES102: 1708.6 | ET102: 0 | EU102: 0 | EV102: 0 | EW102: 0 | EX102: 0 | EY102: 0 | EZ102: 5 | FC102: 1 | FD102: 18 | FF102: 19860 | FQ102: 0 | FR102: 0 | FS102: 0 | FX102: 0 | FY102: 0 | GA102: [19 860 / 1,2 / 9,88] + 2% Заг.скл | GD102: 1 | GF102: -2083123476 | GG102: 2 | GH102: 3 | GI102: 5 | GJ102: 0 | GK102: 0 | GL102: =ROUND(IF(AND(BH102=3,BI102=3,FS102<>0),P102,0),2) -> 0 | GM102: =ROUND(O102+X102+Y102,2)+GX102 -> 6026.5 | GN102: =IF(OR(BI102=0,BI102=1),GM102-GX102,0) -> 0 | GO102: =IF(BI102=2,GM102-GX102,0) -> 6026.5 | GP102: =IF(BI102=4,GM102-GX102,0) -> 0 | GR102: 1 | GS102: 1 | GT102: 0 | GV102: =ROUND((GT102),6) -> 0 | GW102: 1 | GX102: =ROUND(HC102*I102,2) -> 0 | HA102: 0 | HB102: 0 | HC102: =GV102*GW102 -> 0 | HE102: 0 | HF102: 2 | HS102: 0 | IK102: 0
