Workbook

Sheet 02-01-16
A1: =Source!B1 -> Smeta.RU (495) 974-1589
J2: Форма № 4б
A3: Капитальный ремонт здания Государственного бюджетного общеобразовательного учреждения города Москвы "Школа №236" по адресу: г. Москва, улица Клязьминская, дом 7, корпус 4. | AP3: Капитальный ремонт здания Государственного бюджетного общеобразовательного учреждения города Москвы "Школа №236" по адресу: г. Москва, улица Клязьминская, дом 7, корпус 4. 02-01-16 СОС
A4: (наименование стройки и/или объекта)
A6: =CONCATENATE( "ЛОКАЛЬНАЯ СМЕТА № ",IF(Source!F20<>"Новая локальная смета", Source!F20, "")) -> ЛОКАЛЬНАЯ СМЕТА № 02-01-16
A8: =IF(Source!G20<>"Новая локальная смета", Source!G20, "") -> Система охранно-тревожной сигнализации
A9: (наименование работ и затрат)
A11: =CONCATENATE( "Основание: чертежи № ", Source!J20) -> Основание: чертежи № 2024-00272-00-ИОС5.8
I13: В базисном уровне цен | J13: В текущем уровне цен
E14: Сметная стоимость | I14: =I15+I16+I17+I18 -> 136.25 | J14: =J15+J16+J17+J18 -> 2626.43 | K14: тыс.руб.
E15: Строительные работы | I15: =ROUND((Source!F199)/1000, 2) -> 0 | J15: =ROUND((Source!P199)/1000, 2) -> 0 | K15: тыс.руб.
E16: Работы по монтажу оборудования | I16: =ROUND((Source!F200)/1000, 2) -> 69.47 | J16: =ROUND((Source!P200)/1000, 2) -> 2114.92 | K16: тыс.руб.
E17: Оборудование | I17: =ROUND((Source!F191)/1000, 2) -> 66.78 | J17: =ROUND((Source!P191)/1000, 2) -> 511.51 | K17: тыс.руб.
E18: Прочие работы и затраты | I18: =ROUND((Source!F201+Source!F202)/1000, 2) -> 0 | J18: =ROUND((Source!P201+Source!P202)/1000, 2) -> 0 | K18: тыс.руб.
E19: Средства на оплату труда | I19: =(Source!F197+ Source!F196)/1000 -> 13.60692 | J19: =((Source!P197 + Source!P196)/1000) -> 748.24452 | K19: тыс.руб.
E20: Затраты труда | I20: =Source!F204 -> 1038.104 | K20: чел.-ч.
E21: Кроме того:
E22: Возврат материалов | I22: =SUM(Y28:Y335)/1000 -> 0 | J22: =SUM(Z28:Z335)/1000 -> 0 | K22: тыс.руб.
A24: Составлен(а) по ТСН-2001 с учетом Дополнения №: 80
A25: № и период сборника коэффициентов (индексов) пересчета: Коэффициенты к ТСН-2001 МГЭ Дополнение 80, строительство №217/80 III квартал 2025 года и Коэффициенты к ТСН-2001.13-2 Дополнение 46 №62/46 III квартал 2025 года | AP25: № и период сборника коэффициентов (индексов) пересчета: Коэффициенты к ТСН-2001 МГЭ Дополнение 80, строительство №217/80 III квартал 2025 года и Коэффициенты к ТСН-2001.13-2 Дополнение 46 №62/46 III квартал 2025 года
A26: № п/п | B26: Шифр расценки и коды ресурсов | C26: Наименование работ и затрат | D26: Ед. изм. | E26: Кол-во единиц | F26: Цена на ед. изм., руб. | G26: Попра- вочные коэффи- циенты | H26: Коэффи- циенты зимних удорожа- ний | I26: Всего в ценах на январь 2000 года, руб. | J26: Коэффи- циенты (индек- сы) пере- счета, нормы НР и СП | K26: ВСЕГО затрат в текущем уровне цен, руб.
A27: 1 | B27: 2 | C27: 3 | D27: 4 | E27: 5 | F27: 6 | G27: 7 | H27: 8 | I27: 9 | J27: 10 | K27: 11
A29: =CONCATENATE("Раздел: ",IF(Source!G24<>"Новый раздел", Source!G24, "")) -> Раздел: Оборудование
A30: 1 | B30: =Source!F28 -> 4.10-75-6 | C30: Монтаж аппаратуры настольной массой до 20 кг | D30: =Source!H28 -> 1 ШТ. | E30: =Source!I28 -> 1 | Q30: =Source!X28 -> 96.65 | R30: =Source!X29 -> 5314.95 | S30: =Source!Y28 -> 53.92 | T30: =Source!Y29 -> 2965.18 | U30: =ROUND((175/100)*ROUND(Source!R28, 2), 2) -> 0 | V30: =ROUND((0/100)*ROUND(Source!R29, 2), 2) -> 0 | AC30: 0
C31: ЗП | F31: =Source!AO28 -> 88.34 | G31: =Source!DG28 -> *1,1 | H31: =Source!AV29 -> 1.047 | I31: =Source!S28 -> 101.74 | J31: =IF(Source!BA29<> 0, Source!BA29, 1) -> 54.99 | K31: =Source!S29 -> 5594.68
C32: МР | F32: =Source!AL28 -> 34.87 | G32: =Source!DD28 -> *1 | H32: =Source!AW29 -> 1 | I32: =Source!P28 -> 34.87 | J32: =IF(Source!BC29<> 0, Source!BC29, 1) -> 11.35 | K32: =Source!P29 -> 395.77
C33: НР от ФОТ | D33: % | E33: =Source!BZ29 -> 95 | I33: =SUM(Q30:Q32) -> 96.65 | J33: =Source!AT29 -> 95 | K33: =SUM(R30:R32) -> 5314.95
C34: СП от ФОТ | D34: % | E34: =Source!CA29 -> 53 | I34: =SUM(S30:S33) -> 53.92 | J34: =Source!AU29 -> 53 | K34: =SUM(T30:T33) -> 2965.18
C35: ЗТР | D35: чел-ч | E35: =Source!AQ28 -> 7 | G35: =Source!DI28 -> *1,1 | H35: =Source!AV29 -> 1.047 | I35: =Source!U28 -> 8.0619
C36: ВСЕГО работ по позиции: | H36: =I31+I32+I33+I34+0-0-0 -> 287.18 | J36: =K31+K32+K33+K34+0-0-0 -> 14270.58
C37: ВСЕГО оборудование по позиции: | H37: =0+0 -> 0 | J37: =0+0 -> 0
C38: ВСЕГО по позиции: | H38: =I31+I32+I33+I34+0 -> 287.18 | J38: =K31+K32+K33+K34+0 -> 14270.58 | O38: =I31+I32+I33+I34+0 -> 287.18 | P38: =K31+K32+K33+K34+0 -> 14270.58
A40: 2 | B40: =Source!F30 -> КА-1 | C40: ОБОРУДОВАНИЕ:_x000D_ Компьютер персональный АРМ DEPO ПЕРЕСВЕТ 110D11 (системный блок, монитор 21,5", клавиатура, мышь) 8 561,59 = [75 500 / 1,2 / 7,66] + 3% Трансп + 1,2% Заг.скл | D40: =Source!H30 -> ШТ | E40: =Source!I30 -> 1 | F40: =Source!AL30 -> 8561.59 | G40: =Source!DD30 | H40: =Source!AW31 -> 1 | I40: =Source!P30 -> 8561.59 | J40: =IF(Source!BC31<> 0, Source!BC31, 1) -> 7.66 | K40: =Source!P31 -> 65581.78 | Q40: =Source!X30 -> 0 | R40: =Source!X31 -> 0 | S40: =Source!Y30 -> 0 | T40: =Source!Y31 -> 0 | U40: =ROUND((175/100)*ROUND(Source!R30, 2), 2) -> 0 | V40: =ROUND((0/100)*ROUND(Source!R31, 2), 2) -> 0 | AC40: 5
C41: ВСЕГО по позиции: | H41: =I40+0 -> 8561.59 | J41: =K40+0 -> 65581.78 | O41: =I40+0 -> 8561.59 | P41: =K40+0 -> 65581.78
A43: 3 | B43: =Source!F32 -> КА-2 | C43: ОБОРУДОВАНИЕ:_x000D_ Операционная система REDOS-DSP-STD-BAS-VDI 1 655,62 = [14 600 / 1,2 / 7,66] + 3% Трансп + 1,2% Заг.скл | D43: =Source!H32 -> ШТ | E43: =Source!I32 -> 1 | F43: =Source!AL32 -> 1655.62 | G43: =Source!DD32 | H43: =Source!AW33 -> 1 | I43: =Source!P32 -> 1655.62 | J43: =IF(Source!BC33<> 0, Source!BC33, 1) -> 7.66 | K43: =Source!P33 -> 12682.05 | Q43: =Source!X32 -> 0 | R43: =Source!X33 -> 0 | S43: =Source!Y32 -> 0 | T43: =Source!Y33 -> 0 | U43: =ROUND((175/100)*ROUND(Source!R32, 2), 2) -> 0 | V43: =ROUND((0/100)*ROUND(Source!R33, 2), 2) -> 0 | AC43: 5
C44: ВСЕГО по позиции: | H44: =I43+0 -> 1655.62 | J44: =K43+0 -> 12682.05 | O44: =I43+0 -> 1655.62 | P44: =K43+0 -> 12682.05
A46: 4 | B46: =Source!F34 -> 4.10-173-2 | C46: Монтаж блока бесперебойного питания (ББП) в диспетчерской | D46: =Source!H34 -> 1 ШТ. | E46: =Source!I34 -> 1 | Q46: =Source!X34 -> 41.63 | R46: =Source!X35 -> 2289.46 | S46: =Source!Y34 -> 21.28 | T46: =Source!Y35 -> 1170.17 | U46: =ROUND((175/100)*ROUND(Source!R34, 2), 2) -> 0 | V46: =ROUND((0/100)*ROUND(Source!R35, 2), 2) -> 0 | AC46: 0
C47: ЗП | F47: =Source!AO34 -> 40.17 | G47: =Source!DG34 -> *1,1 | H47: =Source!AV35 -> 1.047 | I47: =Source!S34 -> 46.26 | J47: =IF(Source!BA35<> 0, Source!BA35, 1) -> 54.99 | K47: =Source!S35 -> 2543.84
C48: МР | F48: =Source!AL34 -> 2.34 | G48: =Source!DD34 -> *1 | H48: =Source!AW35 -> 1 | I48: =Source!P34 -> 2.34 | J48: =IF(Source!BC35<> 0, Source!BC35, 1) -> 10.26 | K48: =Source!P35 -> 24.01
C49: НР от ФОТ | D49: % | E49: =Source!BZ35 -> 90 | I49: =SUM(Q46:Q48) -> 41.63 | J49: =Source!AT35 -> 90 | K49: =SUM(R46:R48) -> 2289.46
C50: СП от ФОТ | D50: % | E50: =Source!CA35 -> 46 | I50: =SUM(S46:S49) -> 21.28 | J50: =Source!AU35 -> 46 | K50: =SUM(T46:T49) -> 1170.17
C51: ЗТР | D51: чел-ч | E51: =Source!AQ34 -> 3.18 | G51: =Source!DI34 -> *1,1 | H51: =Source!AV35 -> 1.047 | I51: =Source!U34 -> 3.662406
C52: ВСЕГО работ по позиции: | H52: =I47+I48+I49+I50+0-0-0 -> 111.51 | J52: =K47+K48+K49+K50+0-0-0 -> 6027.48
C53: ВСЕГО оборудование по позиции: | H53: =0+0 -> 0 | J53: =0+0 -> 0
C54: ВСЕГО по позиции: | H54: =I47+I48+I49+I50+0 -> 111.51 | J54: =K47+K48+K49+K50+0 -> 6027.48 | O54: =I47+I48+I49+I50+0 -> 111.51 | P54: =K47+K48+K49+K50+0 -> 6027.48
A56: 5 | B56: =Source!F36 -> КА-3 | C56: ОБОРУДОВАНИЕ:_x000D_ Источник бесперебойного питания, 600Вт Back Basic 1050S Euro 1 280,27 = [11 290 / 1,2 / 7,66] + 3% Трансп + 1,2% Заг.скл | D56: =Source!H36 -> ШТ | E56: =Source!I36 -> 1 | F56: =Source!AL36 -> 1280.27 | G56: =Source!DD36 | H56: =Source!AW37 -> 1 | I56: =Source!P36 -> 1280.27 | J56: =IF(Source!BC37<> 0, Source!BC37, 1) -> 7.66 | K56: =Source!P37 -> 9806.87 | Q56: =Source!X36 -> 0 | R56: =Source!X37 -> 0 | S56: =Source!Y36 -> 0 | T56: =Source!Y37 -> 0 | U56: =ROUND((175/100)*ROUND(Source!R36, 2), 2) -> 0 | V56: =ROUND((0/100)*ROUND(Source!R37, 2), 2) -> 0 | AC56: 5
C57: ВСЕГО по позиции: | H57: =I56+0 -> 1280.27 | J57: =K56+0 -> 9806.87 | O57: =I56+0 -> 1280.27 | P57: =K56+0 -> 9806.87
A59: 6 | B59: =Source!F38 -> 4.10-80-1 | C59: Аппараты приемные, приборы ПС приемно-контрольные, пусковые, концентратор, блок базовый на 10 лучей | D59: =Source!H38 -> 1 ШТ. | E59: =Source!I38 -> 1 | Q59: =Source!X38 -> 98.52 | R59: =Source!X39 -> 5417.78 | S59: =Source!Y38 -> 50.36 | T59: =Source!Y39 -> 2769.09 | U59: =ROUND((175/100)*ROUND(Source!R38, 2), 2) -> 0.02 | V59: =ROUND((0/100)*ROUND(Source!R39, 2), 2) -> 0 | AC59: 0
C60: ЗП | F60: =Source!AO38 -> 95.04 | G60: =Source!DG38 -> *1,1 | H60: =Source!AV39 -> 1.047 | I60: =Source!S38 -> 109.46 | J60: =IF(Source!BA39<> 0, Source!BA39, 1) -> 54.99 | K60: =Source!S39 -> 6019.21
C61: ЭМ | F61: =Source!AM38 -> 0.06 | G61: =Source!DE38 -> *1,1 | H61: =Source!AV39 -> 1.047 | I61: =Source!Q38 -> 0.07 | J61: =IF(Source!BB39<> 0, Source!BB39, 1) -> 17.5 | K61: =Source!Q39 -> 1.23
C62: в т.ч. ЗПМ | F62: =Source!AN38 -> 0.01 | G62: =Source!DF38 -> *1,1 | H62: =Source!AV39 -> 1.047 | I62: =Source!R38 -> 0.01 | J62: =IF(Source!BS39<> 0, Source!BS39, 1) -> 54.99 | K62: =Source!R39 -> 0.55
C63: МР | F63: =Source!AL38 -> 12.53 | G63: =Source!DD38 -> *1 | H63: =Source!AW39 -> 1 | I63: =Source!P38 -> 12.53 | J63: =IF(Source!BC39<> 0, Source!BC39, 1) -> 9.89 | K63: =Source!P39 -> 123.92
C64: НР от ФОТ | D64: % | E64: =Source!BZ39 -> 90 | I64: =SUM(Q59:Q63) -> 98.52 | J64: =Source!AT39 -> 90 | K64: =SUM(R59:R63) -> 5417.78
C65: СП от ФОТ | D65: % | E65: =Source!CA39 -> 46 | I65: =SUM(S59:S64) -> 50.36 | J65: =Source!AU39 -> 46 | K65: =SUM(T59:T64) -> 2769.09
C66: ЗТР | D66: чел-ч | E66: =Source!AQ38 -> 7.2 | G66: =Source!DI38 -> *1,1 | H66: =Source!AV39 -> 1.047 | I66: =Source!U38 -> 8.29224
C67: ВСЕГО работ по позиции: | H67: =I60+I61+I63+I64+I65+0-0-0 -> 270.94 | J67: =K60+K61+K63+K64+K65+0-0-0 -> 14331.23
C68: ВСЕГО оборудование по позиции: | H68: =0+0 -> 0 | J68: =0+0 -> 0
C69: ВСЕГО по позиции: | H69: =I60+I61+I63+I64+I65+0 -> 270.94 | J69: =K60+K61+K63+K64+K65+0 -> 14331.23 | O69: =I60+I61+I63+I64+I65+0 -> 270.94 | P69: =K60+K61+K63+K64+K65+0 -> 14331.23
A71: 7 | B71: =Source!F40 -> КА-4 | C71: ОБОРУДОВАНИЕ:_x000D_ Прибор приемно-контрольный и управленя Рубеж-20П прот. R3 9 985,54 = [88 057 / 1,2 / 7,66] + 3% Трансп + 1,2% Заг.скл | D71: =Source!H40 -> ШТ | E71: =Source!I40 -> 1 | F71: =Source!AL40 -> 9985.54 | G71: =Source!DD40 | H71: =Source!AW41 -> 1 | I71: =Source!P40 -> 9985.54 | J71: =IF(Source!BC41<> 0, Source!BC41, 1) -> 7.66 | K71: =Source!P41 -> 76489.24 | Q71: =Source!X40 -> 0 | R71: =Source!X41 -> 0 | S71: =Source!Y40 -> 0 | T71: =Source!Y41 -> 0 | U71: =ROUND((175/100)*ROUND(Source!R40, 2), 2) -> 0 | V71: =ROUND((0/100)*ROUND(Source!R41, 2), 2) -> 0 | AC71: 5
C72: ВСЕГО по позиции: | H72: =I71+0 -> 9985.54 | J72: =K71+0 -> 76489.24 | O72: =I71+0 -> 9985.54 | P72: =K71+0 -> 76489.24
A74: 8 | B74: =Source!F42 -> 4.10-80-13 | C74: Аппараты приемные, устройства промежуточные на 1 луч | D74: =Source!H42 -> 1 ШТ. | E74: =Source!I42 -> 1 | Q74: =Source!X42 -> 16.67 | R74: =Source!X43 -> 916.57 | S74: =Source!Y42 -> 8.52 | T74: =Source!Y43 -> 468.47 | U74: =ROUND((175/100)*ROUND(Source!R42, 2), 2) -> 0.02 | V74: =ROUND((0/100)*ROUND(Source!R43, 2), 2) -> 0 | AC74: 0
C75: ЗП | F75: =Source!AO42 -> 16.07 | G75: =Source!DG42 -> *1,1 | H75: =Source!AV43 -> 1.047 | I75: =Source!S42 -> 18.51 | J75: =IF(Source!BA43<> 0, Source!BA43, 1) -> 54.99 | K75: =Source!S43 -> 1017.86
C76: ЭМ | F76: =Source!AM42 -> 0.05 | G76: =Source!DE42 -> *1,1 | H76: =Source!AV43 -> 1.047 | I76: =Source!Q42 -> 0.06 | J76: =IF(Source!BB43<> 0, Source!BB43, 1) -> 19 | K76: =Source!Q43 -> 1.14
C77: в т.ч. ЗПМ | F77: =Source!AN42 -> 0.01 | G77: =Source!DF42 -> *1,1 | H77: =Source!AV43 -> 1.047 | I77: =Source!R42 -> 0.01 | J77: =IF(Source!BS43<> 0, Source!BS43, 1) -> 54.99 | K77: =Source!R43 -> 0.55
C78: МР | F78: =Source!AL42 -> 1.96 | G78: =Source!DD42 -> *1 | H78: =Source!AW43 -> 1 | I78: =Source!P42 -> 1.96 | J78: =IF(Source!BC43<> 0, Source!BC43, 1) -> 9.89 | K78: =Source!P43 -> 19.38
C79: НР от ФОТ | D79: % | E79: =Source!BZ43 -> 90 | I79: =SUM(Q74:Q78) -> 16.67 | J79: =Source!AT43 -> 90 | K79: =SUM(R74:R78) -> 916.57
C80: СП от ФОТ | D80: % | E80: =Source!CA43 -> 46 | I80: =SUM(S74:S79) -> 8.52 | J80: =Source!AU43 -> 46 | K80: =SUM(T74:T79) -> 468.47
C81: ЗТР | D81: чел-ч | E81: =Source!AQ42 -> 1.2 | G81: =Source!DI42 -> *1,1 | H81: =Source!AV43 -> 1.047 | I81: =Source!U42 -> 1.38204
C82: ВСЕГО работ по позиции: | H82: =I75+I76+I78+I79+I80+0-0-0 -> 45.72 | J82: =K75+K76+K78+K79+K80+0-0-0 -> 2423.42
C83: ВСЕГО оборудование по позиции: | H83: =0+0 -> 0 | J83: =0+0 -> 0
C84: ВСЕГО по позиции: | H84: =I75+I76+I78+I79+I80+0 -> 45.72 | J84: =K75+K76+K78+K79+K80+0 -> 2423.42 | O84: =I75+I76+I78+I79+I80+0 -> 45.72 | P84: =K75+K76+K78+K79+K80+0 -> 2423.42
A86: 9 | B86: =Source!F44 -> КА-5 | C86: ОБОРУДОВАНИЕ:_x000D_ Модуль сопряжения МС-Е 997,80 = [8 799 / 1,2 / 7,66] + 3% Трансп + 1,2% Заг.скл | D86: =Source!H44 -> ШТ | E86: =Source!I44 -> 1 | F86: =Source!AL44 -> 997.8 | G86: =Source!DD44 | H86: =Source!AW45 -> 1 | I86: =Source!P44 -> 997.8 | J86: =IF(Source!BC45<> 0, Source!BC45, 1) -> 7.66 | K86: =Source!P45 -> 7643.15 | Q86: =Source!X44 -> 0 | R86: =Source!X45 -> 0 | S86: =Source!Y44 -> 0 | T86: =Source!Y45 -> 0 | U86: =ROUND((175/100)*ROUND(Source!R44, 2), 2) -> 0 | V86: =ROUND((0/100)*ROUND(Source!R45, 2), 2) -> 0 | AC86: 5
C87: ВСЕГО по позиции: | H87: =I86+0 -> 997.8 | J87: =K86+0 -> 7643.15 | O87: =I86+0 -> 997.8 | P87: =K86+0 -> 7643.15
A89: 10 | B89: =Source!F46 -> 4.10-80-9 | C89: Аппараты приемные, приборы приемно-контрольные объектовые на 2 луча | D89: =Source!H46 -> 1 ШТ. | E89: =Source!I46 -> 1 | Q89: =Source!X46 -> 80.18 | R89: =Source!X47 -> 4409.15 | S89: =Source!Y46 -> 40.98 | T89: =Source!Y47 -> 2253.57 | U89: =ROUND((175/100)*ROUND(Source!R46, 2), 2) -> 0.02 | V89: =ROUND((0/100)*ROUND(Source!R47, 2), 2) -> 0 | AC89: 0
C90: ЗП | F90: =Source!AO46 -> 77.35 | G90: =Source!DG46 -> *1,1 | H90: =Source!AV47 -> 1.047 | I90: =Source!S46 -> 89.08 | J90: =IF(Source!BA47<> 0, Source!BA47, 1) -> 54.99 | K90: =Source!S47 -> 4898.51
C91: ЭМ | F91: =Source!AM46 -> 0.05 | G91: =Source!DE46 -> *1,1 | H91: =Source!AV47 -> 1.047 | I91: =Source!Q46 -> 0.06 | J91: =IF(Source!BB47<> 0, Source!BB47, 1) -> 19 | K91: =Source!Q47 -> 1.14
C92: в т.ч. ЗПМ | F92: =Source!AN46 -> 0.01 | G92: =Source!DF46 -> *1,1 | H92: =Source!AV47 -> 1.047 | I92: =Source!R46 -> 0.01 | J92: =IF(Source!BS47<> 0, Source!BS47, 1) -> 54.99 | K92: =Source!R47 -> 0.55
C93: МР | F93: =Source!AL46 -> 4.83 | G93: =Source!DD46 -> *1 | H93: =Source!AW47 -> 1 | I93: =Source!P46 -> 4.83 | J93: =IF(Source!BC47<> 0, Source!BC47, 1) -> 9.89 | K93: =Source!P47 -> 47.77
C94: НР от ФОТ | D94: % | E94: =Source!BZ47 -> 90 | I94: =SUM(Q89:Q93) -> 80.18 | J94: =Source!AT47 -> 90 | K94: =SUM(R89:R93) -> 4409.15
C95: СП от ФОТ | D95: % | E95: =Source!CA47 -> 46 | I95: =SUM(S89:S94) -> 40.98 | J95: =Source!AU47 -> 46 | K95: =SUM(T89:T94) -> 2253.57
C96: ЗТР | D96: чел-ч | E96: =Source!AQ46 -> 5.7 | G96: =Source!DI46 -> *1,1 | H96: =Source!AV47 -> 1.047 | I96: =Source!U46 -> 6.56469
C97: ВСЕГО работ по позиции: | H97: =I90+I91+I93+I94+I95+0-0-0 -> 215.13 | J97: =K90+K91+K93+K94+K95+0-0-0 -> 11610.14
C98: ВСЕГО оборудование по позиции: | H98: =0+0 -> 0 | J98: =0+0 -> 0
C99: ВСЕГО по позиции: | H99: =I90+I91+I93+I94+I95+0 -> 215.13 | J99: =K90+K91+K93+K94+K95+0 -> 11610.14 | O99: =I90+I91+I93+I94+I95+0 -> 215.13 | P99: =K90+K91+K93+K94+K95+0 -> 11610.14
A101: 11 | B101: =Source!F48 -> КА-6 | C101: ОБОРУДОВАНИЕ:_x000D_ Блок индикации и управления Рубеж-БИУ 2 396,35 = [21 132 / 1,2 / 7,66] + 3% Трансп + 1,2% Заг.скл | D101: =Source!H48 -> ШТ | E101: =Source!I48 -> 1 | F101: =Source!AL48 -> 2396.35 | G101: =Source!DD48 | H101: =Source!AW49 -> 1 | I101: =Source!P48 -> 2396.35 | J101: =IF(Source!BC49<> 0, Source!BC49, 1) -> 7.66 | K101: =Source!P49 -> 18356.04 | Q101: =Source!X48 -> 0 | R101: =Source!X49 -> 0 | S101: =Source!Y48 -> 0 | T101: =Source!Y49 -> 0 | U101: =ROUND((175/100)*ROUND(Source!R48, 2), 2) -> 0 | V101: =ROUND((0/100)*ROUND(Source!R49, 2), 2) -> 0 | AC101: 5
C102: ВСЕГО по позиции: | H102: =I101+0 -> 2396.35 | J102: =K101+0 -> 18356.04 | O102: =I101+0 -> 2396.35 | P102: =K101+0 -> 18356.04
A104: 12 | B104: =Source!F50 -> 4.10-82-3 | C104: Приборы и устройства сигнализирующие объектовые, устройства ультразвуковые, блок питания и контроля | D104: =Source!H50 -> 1 ШТ. | E104: =Source!I50 -> 1 | Q104: =Source!X50 -> 49.97 | R104: =Source!X51 -> 2747.74 | S104: =Source!Y50 -> 25.54 | T104: =Source!Y51 -> 1404.4 | U104: =ROUND((175/100)*ROUND(Source!R50, 2), 2) -> 0.02 | V104: =ROUND((0/100)*ROUND(Source!R51, 2), 2) -> 0 | AC104: 0
C105: ЗП | F105: =Source!AO50 -> 48.2 | G105: =Source!DG50 -> *1,1 | H105: =Source!AV51 -> 1.047 | I105: =Source!S50 -> 55.51 | J105: =IF(Source!BA51<> 0, Source!BA51, 1) -> 54.99 | K105: =Source!S51 -> 3052.49
C106: ЭМ | F106: =Source!AM50 -> 0.05 | G106: =Source!DE50 -> *1,1 | H106: =Source!AV51 -> 1.047 | I106: =Source!Q50 -> 0.06 | J106: =IF(Source!BB51<> 0, Source!BB51, 1) -> 19 | K106: =Source!Q51 -> 1.14
C107: в т.ч. ЗПМ | F107: =Source!AN50 -> 0.01 | G107: =Source!DF50 -> *1,1 | H107: =Source!AV51 -> 1.047 | I107: =Source!R50 -> 0.01 | J107: =IF(Source!BS51<> 0, Source!BS51, 1) -> 54.99 | K107: =Source!R51 -> 0.55
C108: МР | F108: =Source!AL50 -> 3.36 | G108: =Source!DD50 -> *1 | H108: =Source!AW51 -> 1 | I108: =Source!P50 -> 3.36 | J108: =IF(Source!BC51<> 0, Source!BC51, 1) -> 9.89 | K108: =Source!P51 -> 33.23
C109: НР от ФОТ | D109: % | E109: =Source!BZ51 -> 90 | I109: =SUM(Q104:Q108) -> 49.97 | J109: =Source!AT51 -> 90 | K109: =SUM(R104:R108) -> 2747.74
C110: СП от ФОТ | D110: % | E110: =Source!CA51 -> 46 | I110: =SUM(S104:S109) -> 25.54 | J110: =Source!AU51 -> 46 | K110: =SUM(T104:T109) -> 1404.4
C111: ЗТР | D111: чел-ч | E111: =Source!AQ50 -> 3.6 | G111: =Source!DI50 -> *1,1 | H111: =Source!AV51 -> 1.047 | I111: =Source!U50 -> 4.14612
C112: ВСЕГО работ по позиции: | H112: =I105+I106+I108+I109+I110+0-0-0 -> 134.44 | J112: =K105+K106+K108+K109+K110+0-0-0 -> 7239
C113: ВСЕГО оборудование по позиции: | H113: =0+0 -> 0 | J113: =0+0 -> 0
C114: ВСЕГО по позиции: | H114: =I105+I106+I108+I109+I110+0 -> 134.44 | J114: =K105+K106+K108+K109+K110+0 -> 7239 | O114: =I105+I106+I108+I109+I110+0 -> 134.44 | P114: =K105+K106+K108+K109+K110+0 -> 7239
A116: 13 | B116: =Source!F52 -> КА-7 | C116: ОБОРУДОВАНИЕ:_x000D_ Устройство оконечное объектовое Приток-А КОП-1 исп.1 1 829,80 = [16 136 / 1,2 / 7,66] + 3% Трансп + 1,2% Заг.скл | D116: =Source!H52 -> ШТ | E116: =Source!I52 -> 1 | F116: =Source!AL52 -> 1829.8 | G116: =Source!DD52 | H116: =Source!AW53 -> 1 | I116: =Source!P52 -> 1829.8 | J116: =IF(Source!BC53<> 0, Source!BC53, 1) -> 7.66 | K116: =Source!P53 -> 14016.27 | Q116: =Source!X52 -> 0 | R116: =Source!X53 -> 0 | S116: =Source!Y52 -> 0 | T116: =Source!Y53 -> 0 | U116: =ROUND((175/100)*ROUND(Source!R52, 2), 2) -> 0 | V116: =ROUND((0/100)*ROUND(Source!R53, 2), 2) -> 0 | AC116: 5
C117: ВСЕГО по позиции: | H117: =I116+0 -> 1829.8 | J117: =K116+0 -> 14016.27 | O117: =I116+0 -> 1829.8 | P117: =K116+0 -> 14016.27
A119: 14 | B119: =Source!F54 -> 4.10-173-2 | C119: Монтаж блока бесперебойного питания (ББП) в диспетчерской | D119: =Source!H54 -> 1 ШТ. | E119: =Source!I54 -> 3 | Q119: =Source!X54 -> 124.91 | R119: =Source!X55 -> 6868.85 | S119: =Source!Y54 -> 63.84 | T119: =Source!Y55 -> 3510.75 | U119: =ROUND((175/100)*ROUND(Source!R54, 2), 2) -> 0 | V119: =ROUND((0/100)*ROUND(Source!R55, 2), 2) -> 0 | AC119: 0
...

Sheet Ведомость объемов работ
A1: =Source!B1 -> Smeta.RU (495) 974-1589
B4: =CONCATENATE("Ведомость объемов работ ", IF(Source!AN15<>"", Source!AN15," ")) -> Ведомость объемов работ
B5: =CONCATENATE(Source!F12, " ", Source!G12) -> 02-01-16 СОС
A8: № п/п | B8: № в ЛСР | C8: Наименование работ и затрат | D8: Единица измерения | E8: Количество | F8: Ссылка на чертежи, спецификации | G8: Формула расчета, расчет объемов работ и расхода материалов | H8: Примечание
A9: 1 | B9: 2 | C9: 3 | D9: 4 | E9: 5 | F9: 6 | G9: 7 | H9: 8
A10: =CONCATENATE("Локальная смета: ", Source!G20) -> Локальная смета: Система охранно-тревожной сигнализации
A11: =CONCATENATE("Раздел: ", Source!G24) -> Раздел: Оборудование
A12: 1 | B12: =Source!E28 -> 1 | C12: =Source!G28 -> Монтаж аппаратуры настольной массой до 20 кг | D12: 1 ШТ. | E12: =Source!I28 -> 1 | F12: =Source!U24 | G12: =Source!I28 -> 1
A13: 2 | B13: =Source!E30 -> 2 | C13: =Source!G30 -> Компьютер персональный АРМ DEPO ПЕРЕСВЕТ 110D11 (системный блок, монитор 21,5", клавиатура, мышь) | D13: ШТ | E13: =Source!I30 -> 1 | F13: =Source!U24 | G13: =Source!I30 -> 1
A14: 3 | B14: =Source!E32 -> 3 | C14: =Source!G32 -> Операционная система REDOS-DSP-STD-BAS-VDI | D14: ШТ | E14: =Source!I32 -> 1 | F14: =Source!U24 | G14: =Source!I32 -> 1
A15: 4 | B15: =Source!E34 -> 4 | C15: =Source!G34 -> Монтаж блока бесперебойного питания (ББП) в диспетчерской | D15: 1 ШТ. | E15: =Source!I34 -> 1 | F15: =Source!U24 | G15: =Source!I34 -> 1
A16: 5 | B16: =Source!E36 -> 5 | C16: =Source!G36 -> Источник бесперебойного питания, 600Вт Back Basic 1050S Euro | D16: ШТ | E16: =Source!I36 -> 1 | F16: =Source!U24 | G16: =Source!I36 -> 1
A17: 6 | B17: =Source!E38 -> 6 | C17: =Source!G38 -> Аппараты приемные, приборы ПС приемно-контрольные, пусковые, концентратор, блок базовый на 10 лучей | D17: 1 ШТ. | E17: =Source!I38 -> 1 | F17: =Source!U24 | G17: =Source!I38 -> 1
A18: 7 | B18: =Source!E40 -> 7 | C18: =Source!G40 -> Прибор приемно-контрольный и управленя Рубеж-20П прот. R3 | D18: ШТ | E18: =Source!I40 -> 1 | F18: =Source!U24 | G18: =Source!I40 -> 1
A19: 8 | B19: =Source!E42 -> 8 | C19: =Source!G42 -> Аппараты приемные, устройства промежуточные на 1 луч | D19: 1 ШТ. | E19: =Source!I42 -> 1 | F19: =Source!U24 | G19: =Source!I42 -> 1
A20: 9 | B20: =Source!E44 -> 9 | C20: =Source!G44 -> Модуль сопряжения МС-Е | D20: ШТ | E20: =Source!I44 -> 1 | F20: =Source!U24 | G20: =Source!I44 -> 1
A21: 10 | B21: =Source!E46 -> 10 | C21: =Source!G46 -> Аппараты приемные, приборы приемно-контрольные объектовые на 2 луча | D21: 1 ШТ. | E21: =Source!I46 -> 1 | F21: =Source!U24 | G21: =Source!I46 -> 1
A22: 11 | B22: =Source!E48 -> 11 | C22: =Source!G48 -> Блок индикации и управления Рубеж-БИУ | D22: ШТ | E22: =Source!I48 -> 1 | F22: =Source!U24 | G22: =Source!I48 -> 1
A23: 12 | B23: =Source!E50 -> 12 | C23: =Source!G50 -> Приборы и устройства сигнализирующие объектовые, устройства ультразвуковые, блок питания и контроля | D23: 1 ШТ. | E23: =Source!I50 -> 1 | F23: =Source!U24 | G23: =Source!I50 -> 1
A24: 13 | B24: =Source!E52 -> 13 | C24: =Source!G52 -> Устройство оконечное объектовое Приток-А КОП-1 исп.1 | D24: ШТ | E24: =Source!I52 -> 1 | F24: =Source!U24 | G24: =Source!I52 -> 1
A25: 14 | B25: =Source!E54 -> 14 | C25: =Source!G54 -> Монтаж блока бесперебойного питания (ББП) в диспетчерской | D25: 1 ШТ. | E25: =Source!I54 -> 3 | F25: =Source!U24 | G25: =Source!I54 -> 3
A26: 15 | B26: =Source!E56 -> 15 | C26: =Source!G56 -> Блок питания, 12В, 2А ИВЭПР 12/2 RS-R3 | D26: ШТ | E26: =Source!I56 -> 3 | F26: =Source!U24 | G26: =Source!I56 -> 3
A27: 16 | B27: =Source!E58 -> 16 | C27: =Source!G58 -> Аккумултор 12В 7Ач DTM 1207 | D27: ШТ | E27: =Source!I58 -> 3 | F27: =Source!U24 | G27: =Source!I58 -> 3
A28: 17 | B28: =Source!E60 -> 17 | C28: =Source!G60 -> Аппараты приемные, устройства промежуточные на 1 луч | D28: 1 ШТ. | E28: =Source!I60 -> 1 | F28: =Source!U24 | G28: =Source!I60 -> 1
A29: 18 | B29: =Source!E62 -> 18 | C29: =Source!G62 -> Адресный релейный модуль РМ-1-R3 Рубеж | D29: ШТ | E29: =Source!I62 -> 1 | F29: =Source!U24 | G29: =Source!I62 -> 1
A30: 19 | B30: =Source!E64 -> 19 | C30: =Source!G64 -> Аппараты приемные, устройства промежуточные на 1 луч | D30: 1 ШТ. | E30: =Source!I64 -> 2 | F30: =Source!U24 | G30: =Source!I64 -> 2
A31: 20 | B31: =Source!E66 -> 20 | C31: =Source!G66 -> Изолятор шлейфа ИЗ-1 прот. R3 | D31: ШТ | E31: =Source!I66 -> 2 | F31: =Source!U24 | G31: =Source!I66 -> 2
A32: 21 | B32: =Source!E68 -> 21 | C32: =Source!G68 -> Приборы и устройства сигнализирующие объектовые, устройства ультразвуковые, прибор ультразвуковой в одноблочном исполнении | D32: 1 ШТ. | E32: =Source!I68 -> 30 | F32: =Source!U24 | G32: =Source!I68 -> 30
A33: 22 | B33: =Source!E70 -> 22 | C33: =Source!G70 -> Извещатель охранный объемный оптико-электронный адресный ИО 40920-2 | D33: ШТ | E33: =Source!I70 -> 30 | F33: =Source!U24 | G33: =Source!I70 -> 30
A34: 23 | B34: =Source!E72 -> 23 | C34: =Source!G72 -> Извещатели ОС автоматические, контактный, магнито-контактный на открывание окон, дверей | D34: 1 ШТ. | E34: =Source!I72 -> 86 | F34: =Source!U24 | G34: =Source!I72 -> 86
A35: 24 | B35: =Source!E74 -> 24 | C35: =Source!G74 -> Извещатель охранный поверхностный звуковой адресный ИО 32920-2 | D35: ШТ | E35: =Source!I74 -> 86 | F35: =Source!U24 | G35: =Source!I74 -> 86
A36: 25 | B36: =Source!E76 -> 25 | C36: =Source!G76 -> Извещатели ОС автоматические, контактный, магнито-контактный на открывание окон, дверей | D36: 1 ШТ. | E36: =Source!I76 -> 90 | F36: =Source!U24 | G36: =Source!I76 -> 90
A37: 26 | B37: =Source!E78 -> 26 | C37: =Source!G78 -> Извещатель охранный магнитноуправляемый адресный ИО 10220-2 | D37: ШТ | E37: =Source!I78 -> 90 | F37: =Source!U24 | G37: =Source!I78 -> 90
A38: 27 | B38: =Source!E80 -> 27 | C38: =Source!G80 -> Аппараты приемные, устройства промежуточные на 1 луч | D38: 1 ШТ. | E38: =Source!I80 -> 9 | F38: =Source!U24 | G38: =Source!I80 -> 9
A39: 28 | B39: =Source!E82 -> 28 | C39: =Source!G82 -> Адресная метка, 4 шлейфа АМ-4-R3 | D39: ШТ | E39: =Source!I82 -> 9 | F39: =Source!U24 | G39: =Source!I82 -> 9
A40: 29 | B40: =Source!E84 -> 29 | C40: =Source!G84 -> Монтаж детали на пультах и панелях - кнопка | D40: 1 ШТ. | E40: =Source!I84 -> 10 | F40: =Source!U24 | G40: =Source!I84 -> 10
A41: 30 | B41: =Source!E86 -> 30 | C41: =Source!G86 -> Извещатель охранный ручной точечный электроконтактный Астра-321 (ИО 101-7) | D41: ШТ | E41: =Source!I86 -> 10 | F41: =Source!U24 | G41: =Source!I86 -> 10
A42: 31 | B42: =Source!E88 -> 31 | C42: =Source!G88 -> Монтаж светильников с лампами накаливания, светового настенного указателя | D42: 100 шт. | E42: =Source!I88 -> 0.01 | F42: =Source!U24 | G42: ="=1/"&"100" -> =1/100
A43: 32 | B43: =Source!E90 -> 32 | C43: =Source!G90 -> Световой оповещатель "Маяк-12-С" | D43: ШТ | E43: =Source!I90 -> 1 | F43: =Source!U24 | G43: =Source!I90 -> 1
A44: =CONCATENATE("Раздел: ", Source!G123) -> Раздел: Кабельные изделия СОТС
A45: 33 | B45: =Source!E127 -> 33 | C45: =Source!G127 -> Трубы гофрированные поливинилхлоридные наружным диаметром 16 мм открыто по стенам и потолкам с установкой соединительных коробок | D45: 100 м | E45: =Source!I127 -> 30 | F45: =Source!U123 | G45: ="=3000/"&"100" -> =3000/100
A46: 34 | B46: =Source!E133 -> 34 | C46: =Source!G133 -> Прокладка по установленным конструкциям, по стенам с креплением скобами стальной трубы диаметром до 25 мм | D46: 100 м | E46: =Source!I133 -> 0.5 | F46: =Source!U123 | G46: ="=50/"&"100" -> =50/100
A47: 35 | B47: =Source!E137 -> 35 | C47: =Source!G137 -> Шнур коммутационный (патч-корд) тип разъемов RJ45 - RJ45, категория 5E, оболочка LSZH, длина 1 м, неэкранированный | D47: шт. | E47: =Source!I137 -> 2 | F47: =Source!U123 | G47: =Source!I137 -> 2
A48: 36 | B48: =Source!E139 -> 36 | C48: =Source!G139 -> Затягивание провода в проложенные трубы и металлические рукава, первого одножильного или многожильного в общей оплетке, суммарное сечение до 2,5 мм2 | D48: 100 м | E48: =Source!I139 -> 30 | F48: =Source!U123 | G48: ="=3000/"&"100" -> =3000/100
A49: 37 | B49: =Source!E141 -> 37 | C49: =Source!G141 -> Добавлять на затягивание провода в проложенные трубы и металлические рукава каждого последующего одножильного или многожильного в общей оплетке, суммарное сечение до 6 мм2 (к нормам и расценкам 4.8-175-1 и 4.8-175-2) | D49: 100 м | E49: =Source!I141 -> 2 | F49: =Source!U123 | G49: ="=(100+"&"100+"&"2500+"&"500-"&"3000)/"&"100" -> =(100+100+2500+500-3000)/100
A50: 38 | B50: =Source!E143 -> 38 | C50: =Source!G143 -> Кабель интерфейса RS-485 Лоутокс 20нг(А)-LSLTx 1x2x0,5 | D50: км | E50: =Source!I143 -> 0.102 | F50: =Source!U123 | G50: ="=(100*"&"1,02)/"&"1000" -> =(100*1,02)/1000
A51: 39 | B51: =Source!E145 -> 39 | C51: =Source!G145 -> Кавбель КСВВнг(А)-LSLTx 1x2x0,8 | D51: км | E51: =Source!I145 -> 0.102 | F51: =Source!U123 | G51: ="=(100*"&"1,02)/"&"1000" -> =(100*1,02)/1000
A52: 40 | B52: =Source!E147 -> 40 | C52: =Source!G147 -> Кабель витая пара UTP Cat5e PVCLS 1х2х0,52нг(A)- LSLTx | D52: км | E52: =Source!I147 -> 2.55 | F52: =Source!U123 | G52: ="=(2500*"&"1,02)/"&"1000" -> =(2500*1,02)/1000
A53: 41 | B53: =Source!E149 -> 41 | C53: =Source!G149 -> Кабель витая пара UTP Cat5e PVCLS 4х2х0,52нг(A)- LSLTx | D53: км | E53: =Source!I149 -> 0.51 | F53: =Source!U123 | G53: ="=(500*"&"1,02)/"&"1000" -> =(500*1,02)/1000
C56: Главный инженер проекта _________________ | D56: =IF(Source!X12<>"", Source!X12," ")
C58: Составил _________________ | D58: =IF(Source!AB12<>"", Source!AB12," ") -> Соколова И.Н.

Sheet Source
A1: 0 | B1: Smeta.RU (495) 974-1589 | D1: _PS_ | F1: 0 | G1: 0 | H1: 0 | I1: Smeta.RU | K1: 1 | L1: 74563 | M1: 10 | N1: 12 | O1: 0 | P1: 0 | Q1: 3
A4: 1 | B4: 1 | C4: -1 | G4: Капитальный ремонт здания Государственного бюджетного общеобразовательного учреждения города Москвы "Школа №236" по адресу: г. Москва, улица Клязьминская, дом 7, корпус 4 | EC4: 0
A12: 1 | B12: 251 | C12: 0 | D12: =ROW(A212) -> 212 | E12: 0 | G12: 02-01-16 СОС | I12: 0 | J12: 2024-00272-00-ИОС5.8 | K12: 0 | L12: 0 | M12: 4098 | O12: 0 | P12: 0 | Q12: 0 | R12: 0 | S12: 0 | T12: 1 | V12: 0 | AB12: Соколова И.Н. | BB12: 0 | BH12: Сметные нормы списания | BI12: Коды ОКП для ТСН-2001 МГЭ Дополнение 80 | BJ12: 1 | BK12: 1 | BL12: 0 | BM12: 0 | BN12: 1 | BO12: 0 | BP12: 6 | BQ12: 2 | BR12: 1 | BS12: 1 | BT12: 0 | BU12: 0 | BV12: 0 | BW12: 0 | BX12: 0 | BZ12: Типовой расчет для ТСН-2001 МГЭ, Дополнение 80, строительство (1) | CA12: Территориальные сметные нормативы для Москвы ТСН-2001 (МГЭ), дополнение 80 | CB12: Территориальные сметные нормативы для Москвы ТСН-2001 (МГЭ), дополнение 80 | CC12: Территориальные сметные нормативы для Москвы ТСН-2001 (МГЭ), дополнение 80 | CD12: Территориальные сметные нормативы для Москвы ТСН-2001 (МГЭ), дополнение 80 | CE12: Поправки для ТСН-2001 от 28.11.2025 г. доп.79 | CF12: 0 | CG12: 0 | CH12: 8200 | CK12: 80 | CQ12: Территориальные сметные нормативы для Москвы (ТСН-2001) | CR12: ТЕР | CS12: 41660 | CT12: 1 | CU12: 80 | CY12: 0 | EC12: 0
A15: 15 | B15: 1
A18: 52 | B18: =B212 -> 251 | C18: =C212 -> 1 | D18: =D212 -> 12 | E18: =E212 -> 0 | F18: =F212 | G18: =G212 -> 02-01-16 СОС | O18: =O212 -> 116647.27 | P18: =P212 -> 101836.17 | Q18: =Q212 -> 1534.51 | R18: =R212 -> 330.33 | S18: =S212 -> 13276.59 | T18: =T212 -> 0 | U18: =U212 -> 1038.104 | V18: =V212 -> 0 | ... GX18: =GX212 -> 0
A20: 3 | B20: 1 | D20: =ROW(A182) -> 182 | F20: 02-01-16 | G20: Система охранно-тревожной сигнализации | I20: 0 | J20: 2024-00272-00-ИОС5.8 | K20: -1 | L20: 02-01-16 | S20: 0 | T20: 0 | V20: 2 | BX20: 0 | CF20: 0 | CG20: 0
A22: 52 | B22: =B182 -> 1 | C22: =C182 -> 3 | D22: =D182 -> 20 | E22: =E182 -> 0 | F22: =F182 -> 02-01-16 | G22: =G182 -> Система охранно-тревожной сигнализации | O22: =O182 -> 116647.27 | P22: =P182 -> 101836.17 | Q22: =Q182 -> 1534.51 | R22: =R182 -> 330.33 | S22: =S182 -> 13276.59 | T22: =T182 -> 0 | U22: =U182 -> 1038.104 | V22: =V182 -> 0 | ... GX22: =GX182 -> 0
A24: 4 | B24: 1 | D24: =ROW(A93) -> 93 | G24: Оборудование | I24: 0 | K24: -1 | S24: 0 | T24: 0 | V24: 2 | BX24: 0 | CJ24: 0
A26: 52 | B26: =B93 -> 1 | C26: =C93 -> 4 | D26: =D93 -> 24 | E26: =E93 -> 0 | F26: =F93 | G26: =G93 -> Оборудование | O26: =O93 -> 71809.67 | P26: =P93 -> 67074.95 | Q26: =Q93 -> 3.4 | R26: =R93 -> 0.32 | S26: =S93 -> 4731.32 | T26: =T93 -> 0 | U26: =U93 -> 366.82417 | V26: =V93 -> 0 | ... GX26: =GX93 -> 0
A28: 17 | B28: 1 | C28: =ROW(SmtRes!A5) -> 5 | D28: =ROW(EtalonRes!A7) -> 7 | E28: 1 | F28: 4.10-75-6 | G28: Монтаж аппаратуры настольной массой до 20 кг | H28: 1 ШТ. | I28: 1 | J28: 0 | K28: 1 | O28: =ROUND(CP28,2) -> 136.61 | P28: =ROUND((ROUND((AC28*AW28*I28),2)*BC28),2) -> 34.87 | Q28: =(ROUND((ROUND((((ET28*1.1))*AV28*I28),2)*BB28),2)+ROUND((ROUND(((AE28-((EU28*1.1)))*AV28*I28),2)*BS28),2)) -> 0 | R28: =(ROUND((ROUND((((EU28*1.1))*AV28*I28),2)*BS28),2)+ROUND((ROUND(((AE28-((EU28*1.1)))*AV28*I28),2)*BS28),2)) -> 0 | S28: =ROUND((ROUND((AF28*AV28*I28),2)*BA28),2) -> 101.74 | T28: =ROUND(CU28*I28,2) -> 0 | U28: =CV28*I28 -> 8.0619 | V28: =CW28*I28 -> 0 | W28: =ROUND(CX28*I28,2) -> 0 | X28: =(ROUND((((S28+ROUND((ROUND((((EU28*1.1))*AV28*I28),2)*BS28),2))*AT28)/100),2)+ROUND(((ROUND((ROUND(((AE28-((EU28*1.1)))*AV28*I28),2)*BS28),2)*AT28)/100),2)) -> 96.65 | Y28: =(ROUND((((S28+ROUND((ROUND((((EU28*1.1))*AV28*I28),2)*BS28),2))*AU28)/100),2)+ROUND(((ROUND((ROUND(((AE28-((EU28*1.1)))*AV28*I28),2)*BS28),2)*AU28)/100),2)) -> 53.92 | AA28: 60258621 | AB28: =ROUND((AC28+AD28+AF28),6) -> 132.044 | AC28: =ROUND(((ES28*1)),6) -> 34.87 | AD28: =ROUND(((((ET28*1.1))-((EU28*1.1)))+AE28),6) -> 0 | AE28: =ROUND(((EU28*1.1)),6) -> 0 | AF28: =ROUND(((EV28*1.1)),6) -> 97.174 | AG28: =ROUND((AP28),6) -> 0 | AH28: =((EW28*1.1)) -> 7.7 | AI28: =((EX28*1.1)) -> 0 | AJ28: =(AS28) -> 0 | AK28: 123.21 | AL28: 34.87 | AM28: 0 | AN28: 0 | AO28: 88.34 | AP28: 0 | AQ28: 7 | AR28: 0 | AS28: 0 | AT28: 95 | AU28: 53 | AV28: 1.047 | AW28: 1 | AZ28: 1 | BA28: 1 | BB28: 1 | BC28: 1 | BH28: 0 | BI28: 2 | BJ28: ТСН-2001.4 Доп. 79, Сб. 10, т. 75, поз. 6 | BM28: 69 | BN28: 58973116 | BO28: 4.10-75-6 | BP28: 1 | BQ28: 40 | BR28: 0 | BS28: 1 | BT28: 1 | BU28: 1 | BV28: 1 | BW28: 1 | BX28: 1 | BZ28: 95 | CA28: 53 | CE28: 1566 | CF28: 0 | CG28: 0 | CM28: 0 | CN28: Поправка: Гл.12.Прил.8.п.8. 5_12.00.01.11.003 Наименование: При наличии усложненных условий производства работ (стесненность, сложность складирования и транспортной логистики, наличие в зоне производства работ действующего технологического оборудования или движения технологического транспорта и т.п.) для объектов, расположенных за пределами территории круговой магистральной системы улиц "Садовое кольцо" и за пределами Третьего транспортного кольца города Москвы пунктов "а" и "б", но в пределах Московской кольцевой автомобильной дороги | CO28: 0 | CP28: =(P28+Q28+S28) -> 136.61 | CQ28: =ROUND((ROUND((AC28*AW28*1),2)*BC28),2) -> 34.87 | CR28: =(ROUND((ROUND((((ET28*1.1))*AV28*1),2)*BB28),2)+ROUND((ROUND(((AE28-((EU28*1.1)))*AV28*1),2)*BS28),2)) -> 0 | CS28: =(ROUND((ROUND((((EU28*1.1))*AV28*1),2)*BS28),2)+ROUND((ROUND(((AE28-((EU28*1.1)))*AV28*1),2)*BS28),2)) -> 0 | CT28: =ROUND((ROUND((AF28*AV28*1),2)*BA28),2) -> 101.74 | CU28: =AG28 -> 0 | CV28: =(AH28*AV28) -> 8.0619 | CW28: =AI28 -> 0 | CX28: =AJ28 -> 0 | CY28: =(ROUND((((S28+ROUND((ROUND((((EU28*1.1))*AV28*1),2)*BS28),2))*AT28)/100),2)+ROUND(((ROUND((ROUND(((AE28-((EU28*1.1)))*AV28*1),2)*BS28),2)*AT28)/100),2)) -> 96.65 | CZ28: =(ROUND((((S28+ROUND((ROUND((((EU28*1.1))*AV28*1),2)*BS28),2))*AU28)/100),2)+ROUND(((ROUND((ROUND(((AE28-((EU28*1.1)))*AV28*1),2)*BS28),2)*AU28)/100),2)) -> 53.92 | DB28: 1 | DD28: *1 | DE28: *1,1 | DF28: *1,1 | DG28: *1,1 | DI28: *1,1 | DJ28: *1,1 | DN28: 0 | DO28: 0 | DP28: 1 | DQ28: 1 | DU28: 1013 | DV28: 1 ШТ. | DW28: 1 ШТ. | DX28: 1 | EE28: 60088533 | EF28: 40 | EG28: Монтаж оборудования | EH28: 0 | EJ28: 2 | EK28: 69 | EL28: ТСН-2001.4-10. Монтаж радиотелевизионного и электронного оборудования | EM28: ТСН-2001.4-10-2 | EO28: Поправка: Гл.12.Прил.8.п.8. 5_12.00.01.11.003 | EQ28: 0 | ER28: 123.21 | ES28: 34.87 | ET28: 0 | EU28: 0 | EV28: 88.34 | EW28: 7 | EX28: 0 | EY28: 0 | FQ28: 0 | FR28: 0 | FS28: 0 | FX28: 95 | FY28: 53 | GD28: 1 | GF28: 1652728637 | GG28: 2 | GH28: 1 | GI28: 2 | GJ28: 0 | GK28: 0 | GL28: =ROUND(IF(AND(BH28=3,BI28=3,FS28<>0),P28,0),2) -> 0 | GM28: =ROUND(O28+X28+Y28,2)+GX28 -> 287.18 | GN28: =IF(OR(BI28=0,BI28=1),GM28-GX28,0) -> 0 | GO28: =IF(BI28=2,GM28-GX28,0) -> 287.18 | GP28: =IF(BI28=4,GM28-GX28,0) -> 0 | GR28: 0 | GS28: 3 | GT28: 0 | GV28: =ROUND((GT28),6) -> 0 | GW28: 1 | GX28: =ROUND(HC28*I28,2) -> 0 | HA28: 0 | HB28: 0 | HC28: =GV28*GW28 -> 0 | HS28: 0 | IK28: 0
A29: 17 | B29: 1 | C29: =ROW(SmtRes!A10) -> 10 | D29: =ROW(EtalonRes!A14) -> 14 | E29: 1 | F29: 4.10-75-6 | G29: Монтаж аппаратуры настольной массой до 20 кг | H29: 1 ШТ. | I29: 1 | J29: 0 | K29: 1 | O29: =ROUND(CP29,2) -> 5990.45 | P29: =ROUND((ROUND((AC29*AW29*I29),2)*BC29),2) -> 395.77 | Q29: =(ROUND((ROUND((((ET29*1.1))*AV29*I29),2)*BB29),2)+ROUND((ROUND(((AE29-((EU29*1.1)))*AV29*I29),2)*BS29),2)) -> 0 | R29: =(ROUND((ROUND((((EU29*1.1))*AV29*I29),2)*BS29),2)+ROUND((ROUND(((AE29-((EU29*1.1)))*AV29*I29),2)*BS29),2)) -> 0 | S29: =ROUND((ROUND((AF29*AV29*I29),2)*BA29),2) -> 5594.68 | T29: =ROUND(CU29*I29,2) -> 0 | U29: =CV29*I29 -> 8.0619 | V29: =CW29*I29 -> 0 | W29: =ROUND(CX29*I29,2) -> 0 | X29: =(ROUND((((S29+ROUND((ROUND((((EU29*1.1))*AV29*I29),2)*BS29),2))*AT29)/100),2)+ROUND(((ROUND((ROUND(((AE29-((EU29*1.1)))*AV29*I29),2)*BS29),2)*AT29)/100),2)) -> 5314.95 | Y29: =(ROUND((((S29+ROUND((ROUND((((EU29*1.1))*AV29*I29),2)*BS29),2))*AU29)/100),2)+ROUND(((ROUND((ROUND(((AE29-((EU29*1.1)))*AV29*I29),2)*BS29),2)*AU29)/100),2)) -> 2965.18 | AA29: 60258618 | AB29: =ROUND((AC29+AD29+AF29),6) -> 132.044 | AC29: =ROUND(((ES29*1)),6) -> 34.87 | AD29: =ROUND(((((ET29*1.1))-((EU29*1.1)))+AE29),6) -> 0 | AE29: =ROUND(((EU29*1.1)),6) -> 0 | AF29: =ROUND(((EV29*1.1)),6) -> 97.174 | AG29: =ROUND((AP29),6) -> 0 | AH29: =((EW29*1.1)) -> 7.7 | AI29: =((EX29*1.1)) -> 0 | AJ29: =(AS29) -> 0 | AK29: 123.21 | AL29: 34.87 | AM29: 0 | AN29: 0 | AO29: 88.34 | AP29: 0 | AQ29: 7 | AR29: 0 | AS29: 0 | AT29: 95 | AU29: 53 | AV29: 1.047 | AW29: 1 | AZ29: 1 | BA29: 54.99 | BB29: 1 | BC29: 11.35 | BH29: 0 | BI29: 2 | BJ29: ТСН-2001.4 Доп. 79, Сб. 10, т. 75, поз. 6 | BM29: 69 | BN29: 58973116 | BO29: 4.10-75-6 | BP29: 1 | BQ29: 40 | BR29: 0 | BS29: 54.99 | BT29: 1 | BU29: 1 | BV29: 1 | BW29: 1 | BX29: 1 | BZ29: 95 | CA29: 53 | CE29: 1566 | CF29: 0 | CG29: 0 | CM29: 0 | CN29: Поправка: Гл.12.Прил.8.п.8. 5_12.00.01.11.003 Наименование: При наличии усложненных условий производства работ (стесненность, сложность складирования и транспортной логистики, наличие в зоне производства работ действующего технологического оборудования или движения технологического транспорта и т.п.) для объектов, расположенных за пределами территории круговой магистральной системы улиц "Садовое кольцо" и за пределами Третьего транспортного кольца города Москвы пунктов "а" и "б", но в пределах Московской кольцевой автомобильной дороги | CO29: 0 | CP29: =(P29+Q29+S29) -> 5990.45 | CQ29: =ROUND((ROUND((AC29*AW29*1),2)*BC29),2) -> 395.77 | CR29: =(ROUND((ROUND((((ET29*1.1))*AV29*1),2)*BB29),2)+ROUND((ROUND(((AE29-((EU29*1.1)))*AV29*1),2)*BS29),2)) -> 0 | CS29: =(ROUND((ROUND((((EU29*1.1))*AV29*1),2)*BS29),2)+ROUND((ROUND(((AE29-((EU29*1.1)))*AV29*1),2)*BS29),2)) -> 0 | CT29: =ROUND((ROUND((AF29*AV29*1),2)*BA29),2) -> 5594.68 | CU29: =AG29 -> 0 | CV29: =(AH29*AV29) -> 8.0619 | CW29: =AI29 -> 0 | CX29: =AJ29 -> 0 | CY29: =(ROUND((((S29+ROUND((ROUND((((EU29*1.1))*AV29*1),2)*BS29),2))*AT29)/100),2)+ROUND(((ROUND((ROUND(((AE29-((EU29*1.1)))*AV29*1),2)*BS29),2)*AT29)/100),2)) -> 5314.95 | CZ29: =(ROUND((((S29+ROUND((ROUND((((EU29*1.1))*AV29*1),2)*BS29),2))*AU29)/100),2)+ROUND(((ROUND((ROUND(((AE29-((EU29*1.1)))*AV29*1),2)*BS29),2)*AU29)/100),2)) -> 2965.18 | DB29: 2 | DD29: *1 | DE29: *1,1 | DF29: *1,1 | DG29: *1,1 | DI29: *1,1 | DJ29: *1,1 | DN29: 0 | DO29: 0 | DP29: 1 | DQ29: 1 | DU29: 1013 | DV29: 1 ШТ. | DW29: 1 ШТ. | DX29: 1 | EE29: 60088533 | EF29: 40 | EG29: Монтаж оборудования | EH29: 0 | EJ29: 2 | EK29: 69 | EL29: ТСН-2001.4-10. Монтаж радиотелевизионного и электронного оборудования | EM29: ТСН-2001.4-10-2 | EO29: Поправка: Гл.12.Прил.8.п.8. 5_12.00.01.11.003 | EQ29: 0 | ER29: 123.21 | ES29: 34.87 | ET29: 0 | EU29: 0 | EV29: 88.34 | EW29: 7 | EX29: 0 | EY29: 0 | FQ29: 0 | FR29: 0 | FS29: 0 | FX29: 95 | FY29: 53 | GD29: 1 | GF29: 1652728637 | GG29: 2 | GH29: 1 | GI29: 2 | GJ29: 0 | GK29: 0 | GL29: =ROUND(IF(AND(BH29=3,BI29=3,FS29<>0),P29,0),2) -> 0 | GM29: =ROUND(O29+X29+Y29,2)+GX29 -> 14270.58 | GN29: =IF(OR(BI29=0,BI29=1),GM29-GX29,0) -> 0 | GO29: =IF(BI29=2,GM29-GX29,0) -> 14270.58 | GP29: =IF(BI29=4,GM29-GX29,0) -> 0 | GR29: 0 | GS29: 3 | GT29: 0 | GV29: =ROUND((GT29),6) -> 0 | GW29: 1 | GX29: =ROUND(HC29*I29,2) -> 0 | HA29: 0 | HB29: 0 | HC29: =GV29*GW29 -> 0 | HS29: 0 | IK29: 0
A30: 17 | B30: 1 | E30: 2 | F30: КА-1 | G30: Компьютер персональный АРМ DEPO ПЕРЕСВЕТ 110D11 (системный блок, монитор 21,5", клавиатура, мышь) | H30: ШТ | I30: 1 | J30: 0 | K30: 1 | O30: =ROUND(CP30,2) -> 8561.59 | P30: =ROUND((ROUND((AC30*I30),2)*BC30),2) -> 8561.59 | Q30: =(ROUND((ROUND(((ET30)*AV30*I30),2)*BB30),2)+ROUND((ROUND(((AE30-(EU30))*AV30*I30),2)*BS30),2)) -> 0 | R30: =(ROUND((ROUND(((EU30)*AV30*I30),2)*BS30),2)+ROUND((ROUND(((AE30-(EU30))*AV30*I30),2)*BS30),2)) -> 0 | S30: =ROUND((ROUND((AF30*AV30*I30),2)*BA30),2) -> 0 | T30: =ROUND(CU30*I30,2) -> 0 | U30: =CV30*I30 -> 0 | V30: =CW30*I30 -> 0 | W30: =ROUND(CX30*I30,2) -> 0 | X30: =(ROUND((((S30+ROUND((ROUND(((EU30)*AV30*I30),2)*BS30),2))*AT30)/100),2)+ROUND(((ROUND((ROUND(((AE30-(EU30))*AV30*I30),2)*BS30),2)*AT30)/100),2)) -> 0 | Y30: =(ROUND((((S30+ROUND((ROUND(((EU30)*AV30*I30),2)*BS30),2))*AU30)/100),2)+ROUND(((ROUND((ROUND(((AE30-(EU30))*AV30*I30),2)*BS30),2)*AU30)/100),2)) -> 0 | AA30: 60258621 | AB30: =ROUND((AC30+AD30+AF30),6) -> 8561.59 | AC30: =ROUND((ES30),6) -> 8561.59 | AD30: =ROUND((((ET30)-(EU30))+AE30),6) -> 0 | AE30: =ROUND((EU30),6) -> 0 | AF30: =ROUND((EV30),6) -> 0 | AG30: =ROUND((AP30),6) -> 0 | AH30: =(EW30) -> 0 | AI30: =(EX30) -> 0 | AJ30: =(AS30) -> 0 | AK30: 8561.59 | AL30: 8561.59 | AM30: 0 | AN30: 0 | AO30: 0 | AP30: 0 | AQ30: 0 | AR30: 0 | AS30: 0 | AT30: 0 | AU30: 0 | AV30: 1 | AW30: 1 | AZ30: 1 | BA30: 1 | BB30: 1 | BC30: 1 | BH30: 3 | BI30: 3 | BM30: 746 | BN30: 0 | BP30: 0 | BQ30: 130 | BR30: 0 | BS30: 1 | BT30: 1 | BU30: 1 | BV30: 1 | BW30: 1 | BX30: 1 | BZ30: 0 | CA30: 0 | CE30: 1566 | CF30: 0 | CG30: 0 | CM30: 0 | CO30: 0 | CP30: =(P30+Q30+S30) -> 8561.59 | CQ30: =ROUND((ROUND((AC30*1),2)*BC30),2) -> 8561.59 | CR30: =(ROUND((ROUND(((ET30)*AV30*1),2)*BB30),2)+ROUND((ROUND(((AE30-(EU30))*AV30*1),2)*BS30),2)) -> 0 | CS30: =(ROUND((ROUND(((EU30)*AV30*1),2)*BS30),2)+ROUND((ROUND(((AE30-(EU30))*AV30*1),2)*BS30),2)) -> 0 | CT30: =ROUND((ROUND((AF30*AV30*1),2)*BA30),2) -> 0 | CU30: =AG30 -> 0 | CV30: =(AH30*AV30) -> 0 | CW30: =AI30 -> 0 | CX30: =AJ30 -> 0 | CY30: =(ROUND((((S30+ROUND((ROUND(((EU30)*AV30*1),2)*BS30),2))*AT30)/100),2)+ROUND(((ROUND((ROUND(((AE30-(EU30))*AV30*1),2)*BS30),2)*AT30)/100),2)) -> 0 | CZ30: =(ROUND((((S30+ROUND((ROUND(((EU30)*AV30*1),2)*BS30),2))*AU30)/100),2)+ROUND(((ROUND((ROUND(((AE30-(EU30))*AV30*1),2)*BS30),2)*AU30)/100),2)) -> 0 | DN30: 0 | DO30: 0 | DP30: 1 | DQ30: 1 | DU30: 1013 | DV30: ШТ | DW30: ШТ | DX30: 1 | EE30: 60088638 | EF30: 130 | EG30: Сметная стоимость оборудования | EH30: 0 | EJ30: 3 | EK30: 746 | EL30: ТСН-2001.13. Сметная стоимость оборудования | EM30: ТСН-2001.13 | EQ30: 0 | ER30: 0 | ES30: 8561.59 | ET30: 0 | EU30: 0 | EV30: 0 | EW30: 0 | EX30: 0 | EY30: 0 | FQ30: 0 | FR30: =P30 -> 8561.59 | FS30: 0 | FX30: 0 | FY30: 0 | GA30: [75 500 / 1,2 / 7,66] + 3% Трансп + 1,2% Заг.скл | GD30: 1 | GF30: 521336863 | GG30: 2 | GH30: 4 | GI30: -2 | GJ30: 0 | GK30: 0 | GL30: =ROUND(IF(AND(BH30=3,BI30=3,FS30<>0),P30,0),2) -> 0 | GM30: =ROUND(O30+X30+Y30,2)+GX30 -> 8561.59 | GN30: =IF(OR(BI30=0,BI30=1),GM30-GX30,0) -> 0 | GO30: =IF(BI30=2,GM30-GX30,0) -> 0 | GP30: =IF(BI30=4,GM30-GX30,0) -> 0 | GR30: 0 | GS30: 2 | GT30: 0 | GV30: =ROUND((GT30),6) -> 0 | GW30: 1 | GX30: =ROUND(HC30*I30,2) -> 0 | HA30: 0 | HB30: 0 | HC30: =GV30*GW30 -> 0 | HE30: 3 | HF30: 1,2 | HS30: 0 | IK30: 0
A31: 17 | B31: 1 | E31: 2 | F31: КА-1 | G31: Компьютер персональный АРМ DEPO ПЕРЕСВЕТ 110D11 (системный блок, монитор 21,5", клавиатура, мышь) | H31: ШТ | I31: 1 | J31: 0 | K31: 1 | O31: =ROUND(CP31,2) -> 65581.78 | P31: =ROUND((ROUND((AC31*I31),2)*BC31),2) -> 65581.78 | Q31: =(ROUND((ROUND(((ET31)*AV31*I31),2)*BB31),2)+ROUND((ROUND(((AE31-(EU31))*AV31*I31),2)*BS31),2)) -> 0 | R31: =(ROUND((ROUND(((EU31)*AV31*I31),2)*BS31),2)+ROUND((ROUND(((AE31-(EU31))*AV31*I31),2)*BS31),2)) -> 0 | S31: =ROUND((ROUND((AF31*AV31*I31),2)*BA31),2) -> 0 | T31: =ROUND(CU31*I31,2) -> 0 | U31: =CV31*I31 -> 0 | V31: =CW31*I31 -> 0 | W31: =ROUND(CX31*I31,2) -> 0 | X31: =(ROUND((((S31+ROUND((ROUND(((EU31)*AV31*I31),2)*BS31),2))*AT31)/100),2)+ROUND(((ROUND((ROUND(((AE31-(EU31))*AV31*I31),2)*BS31),2)*AT31)/100),2)) -> 0 | Y31: =(ROUND((((S31+ROUND((ROUND(((EU31)*AV31*I31),2)*BS31),2))*AU31)/100),2)+ROUND(((ROUND((ROUND(((AE31-(EU31))*AV31*I31),2)*BS31),2)*AU31)/100),2)) -> 0 | AA31: 60258618 | AB31: =ROUND((AC31+AD31+AF31),6) -> 8561.59 | AC31: =ROUND((ES31),6) -> 8561.59 | AD31: =ROUND((((ET31)-(EU31))+AE31),6) -> 0 | AE31: =ROUND((EU31),6) -> 0 | AF31: =ROUND((EV31),6) -> 0 | AG31: =ROUND((AP31),6) -> 0 | AH31: =(EW31) -> 0 | AI31: =(EX31) -> 0 | AJ31: =(AS31) -> 0 | AK31: 8561.59 | AL31: 8561.59 | AM31: 0 | AN31: 0 | AO31: 0 | AP31: 0 | AQ31: 0 | AR31: 0 | AS31: 0 | AT31: 0 | AU31: 0 | AV31: 1 | AW31: 1 | AZ31: 1 | BA31: 1 | BB31: 1 | BC31: 7.66 | BH31: 3 | BI31: 3 | BM31: 746 | BN31: 0 | BP31: 0 | BQ31: 130 | BR31: 0 | BS31: 1 | BT31: 1 | BU31: 1 | BV31: 1 | BW31: 1 | BX31: 1 | BZ31: 0 | CA31: 0 | CE31: 1566 | CF31: 0 | CG31: 0 | CM31: 0 | CO31: 0 | CP31: =(P31+Q31+S31) -> 65581.78 | CQ31: =ROUND((ROUND((AC31*1),2)*BC31),2) -> 65581.78 | CR31: =(ROUND((ROUND(((ET31)*AV31*1),2)*BB31),2)+ROUND((ROUND(((AE31-(EU31))*AV31*1),2)*BS31),2)) -> 0 | CS31: =(ROUND((ROUND(((EU31)*AV31*1),2)*BS31),2)+ROUND((ROUND(((AE31-(EU31))*AV31*1),2)*BS31),2)) -> 0 | CT31: =ROUND((ROUND((AF31*AV31*1),2)*BA31),2) -> 0 | CU31: =AG31 -> 0 | CV31: =(AH31*AV31) -> 0 | CW31: =AI31 -> 0 | CX31: =AJ31 -> 0 | CY31: =(ROUND((((S31+ROUND((ROUND(((EU31)*AV31*1),2)*BS31),2))*AT31)/100),2)+ROUND(((ROUND((ROUND(((AE31-(EU31))*AV31*1),2)*BS31),2)*AT31)/100),2)) -> 0 | CZ31: =(ROUND((((S31+ROUND((ROUND(((EU31)*AV31*1),2)*BS31),2))*AU31)/100),2)+ROUND(((ROUND((ROUND(((AE31-(EU31))*AV31*1),2)*BS31),2)*AU31)/100),2)) -> 0 | DN31: 0 | DO31: 0 | DP31: 1 | DQ31: 1 | DU31: 1013 | DV31: ШТ | DW31: ШТ | DX31: 1 | EE31: 60088638 | EF31: 130 | EG31: Сметная стоимость оборудования | EH31: 0 | EJ31: 3 | EK31: 746 | EL31: ТСН-2001.13. Сметная стоимость оборудования | EM31: ТСН-2001.13 | EQ31: 0 | ER31: 0 | ES31: 8561.59 | ET31: 0 | EU31: 0 | EV31: 0 | EW31: 0 | EX31: 0 | EY31: 0 | EZ31: 5 | FC31: 1 | FD31: 18 | FF31: 75500 | FQ31: 0 | FR31: =P31 -> 65581.78 | FS31: 0 | FX31: 0 | FY31: 0 | GA31: [75 500 / 1,2 / 7,66] + 3% Трансп + 1,2% Заг.скл | GD31: 1 | GF31: 521336863 | GG31: 2 | GH31: 3 | GI31: 5 | GJ31: 0 | GK31: 0 | GL31: =ROUND(IF(AND(BH31=3,BI31=3,FS31<>0),P31,0),2) -> 0 | GM31: =ROUND(O31+X31+Y31,2)+GX31 -> 65581.78 | GN31: =IF(OR(BI31=0,BI31=1),GM31-GX31,0) -> 0 | GO31: =IF(BI31=2,GM31-GX31,0) -> 0 | GP31: =IF(BI31=4,GM31-GX31,0) -> 0 | GR31: 1 | GS31: 1 | GT31: 0 | GV31: =ROUND((GT31),6) -> 0 | GW31: 1 | GX31: =ROUND(HC31*I31,2) -> 0 | HA31: 0 | HB31: 0 | HC31: =GV31*GW31 -> 0 | HE31: 3 | HF31: 1,2 | HS31: 0 | IK31: 0
A32: 17 | B32: 1 | E32: 3 | F32: КА-2 | G32: Операционная система REDOS-DSP-STD-BAS-VDI | H32: ШТ | I32: 1 | J32: 0 | K32: 1 | O32: =ROUND(CP32,2) -> 1655.62 | P32: =ROUND((ROUND((AC32*I32),2)*BC32),2) -> 1655.62 | Q32: =(ROUND((ROUND(((ET32)*AV32*I32),2)*BB32),2)+ROUND((ROUND(((AE32-(EU32))*AV32*I32),2)*BS32),2)) -> 0 | R32: =(ROUND((ROUND(((EU32)*AV32*I32),2)*BS32),2)+ROUND((ROUND(((AE32-(EU32))*AV32*I32),2)*BS32),2)) -> 0 | S32: =ROUND((ROUND((AF32*AV32*I32),2)*BA32),2) -> 0 | T32: =ROUND(CU32*I32,2) -> 0 | U32: =CV32*I32 -> 0 | V32: =CW32*I32 -> 0 | W32: =ROUND(CX32*I32,2) -> 0 | X32: =(ROUND((((S32+ROUND((ROUND(((EU32)*AV32*I32),2)*BS32),2))*AT32)/100),2)+ROUND(((ROUND((ROUND(((AE32-(EU32))*AV32*I32),2)*BS32),2)*AT32)/100),2)) -> 0 | Y32: =(ROUND((((S32+ROUND((ROUND(((EU32)*AV32*I32),2)*BS32),2))*AU32)/100),2)+ROUND(((ROUND((ROUND(((AE32-(EU32))*AV32*I32),2)*BS32),2)*AU32)/100),2)) -> 0 | AA32: 60258621 | AB32: =ROUND((AC32+AD32+AF32),6) -> 1655.62 | AC32: =ROUND((ES32),6) -> 1655.62 | AD32: =ROUND((((ET32)-(EU32))+AE32),6) -> 0 | AE32: =ROUND((EU32),6) -> 0 | AF32: =ROUND((EV32),6) -> 0 | AG32: =ROUND((AP32),6) -> 0 | AH32: =(EW32) -> 0 | AI32: =(EX32) -> 0 | AJ32: =(AS32) -> 0 | AK32: 1655.62 | AL32: 1655.62 | AM32: 0 | AN32: 0 | AO32: 0 | AP32: 0 | AQ32: 0 | AR32: 0 | AS32: 0 | AT32: 0 | AU32: 0 | AV32: 1 | AW32: 1 | AZ32: 1 | BA32: 1 | BB32: 1 | BC32: 1 | BH32: 3 | BI32: 3 | BM32: 746 | BN32: 0 | BP32: 0 | BQ32: 130 | BR32: 0 | BS32: 1 | BT32: 1 | BU32: 1 | BV32: 1 | BW32: 1 | BX32: 1 | BZ32: 0 | CA32: 0 | CE32: 1566 | CF32: 0 | CG32: 0 | CM32: 0 | CO32: 0 | CP32: =(P32+Q32+S32) -> 1655.62 | CQ32: =ROUND((ROUND((AC32*1),2)*BC32),2) -> 1655.62 | CR32: =(ROUND((ROUND(((ET32)*AV32*1),2)*BB32),2)+ROUND((ROUND(((AE32-(EU32))*AV32*1),2)*BS32),2)) -> 0 | CS32: =(ROUND((ROUND(((EU32)*AV32*1),2)*BS32),2)+ROUND((ROUND(((AE32-(EU32))*AV32*1),2)*BS32),2)) -> 0 | CT32: =ROUND((ROUND((AF32*AV32*1),2)*BA32),2) -> 0 | CU32: =AG32 -> 0 | CV32: =(AH32*AV32) -> 0 | CW32: =AI32 -> 0 | CX32: =AJ32 -> 0 | CY32: =(ROUND((((S32+ROUND((ROUND(((EU32)*AV32*1),2)*BS32),2))*AT32)/100),2)+ROUND(((ROUND((ROUND(((AE32-(EU32))*AV32*1),2)*BS32),2)*AT32)/100),2)) -> 0 | CZ32: =(ROUND((((S32+ROUND((ROUND(((EU32)*AV32*1),2)*BS32),2))*AU32)/100),2)+ROUND(((ROUND((ROUND(((AE32-(EU32))*AV32*1),2)*BS32),2)*AU32)/100),2)) -> 0 | DN32: 0 | DO32: 0 | DP32: 1 | DQ32: 1 | DU32: 1013 | DV32: ШТ | DW32: ШТ | DX32: 1 | EE32: 60088638 | EF32: 130 | EG32: Сметная стоимость оборудования | EH32: 0 | EJ32: 3 | EK32: 746 | EL32: ТСН-2001.13. Сметная стоимость оборудования | EM32: ТСН-2001.13 | EQ32: 0 | ER32: 0 | ES32: 1655.62 | ET32: 0 | EU32: 0 | EV32: 0 | EW32: 0 | EX32: 0 | EY32: 0 | FQ32: 0 | FR32: =P32 -> 1655.62 | FS32: 0 | FX32: 0 | FY32: 0 | GA32: [14 600 / 1,2 / 7,66] + 3% Трансп + 1,2% Заг.скл | GD32: 1 | GF32: 963458923 | GG32: 2 | GH32: 4 | GI32: -2 | GJ32: 0 | GK32: 0 | GL32: =ROUND(IF(AND(BH32=3,BI32=3,FS32<>0),P32,0),2) -> 0 | GM32: =ROUND(O32+X32+Y32,2)+GX32 -> 1655.62 | GN32: =IF(OR(BI32=0,BI32=1),GM32-GX32,0) -> 0 | GO32: =IF(BI32=2,GM32-GX32,0) -> 0 | GP32: =IF(BI32=4,GM32-GX32,0) -> 0 | GR32: 0 | GS32: 2 | GT32: 0 | GV32: =ROUND((GT32),6) -> 0 | GW32: 1 | GX32: =ROUND(HC32*I32,2) -> 0 | HA32: 0 | HB32: 0 | HC32: =GV32*GW32 -> 0 | HE32: 3 | HF32: 1,2 | HS32: 0 | IK32: 0
A33: 17 | B33: 1 | E33: 3 | F33: КА-2 | G33: Операционная система REDOS-DSP-STD-BAS-VDI | H33: ШТ | I33: 1 | J33: 0 | K33: 1 | O33: =ROUND(CP33,2) -> 12682.05 | P33: =ROUND((ROUND((AC33*I33),2)*BC33),2) -> 12682.05 | Q33: =(ROUND((ROUND(((ET33)*AV33*I33),2)*BB33),2)+ROUND((ROUND(((AE33-(EU33))*AV33*I33),2)*BS33),2)) -> 0 | R33: =(ROUND((ROUND(((EU33)*AV33*I33),2)*BS33),2)+ROUND((ROUND(((AE33-(EU33))*AV33*I33),2)*BS33),2)) -> 0 | S33: =ROUND((ROUND((AF33*AV33*I33),2)*BA33),2) -> 0 | T33: =ROUND(CU33*I33,2) -> 0 | U33: =CV33*I33 -> 0 | V33: =CW33*I33 -> 0 | W33: =ROUND(CX33*I33,2) -> 0 | X33: =(ROUND((((S33+ROUND((ROUND(((EU33)*AV33*I33),2)*BS33),2))*AT33)/100),2)+ROUND(((ROUND((ROUND(((AE33-(EU33))*AV33*I33),2)*BS33),2)*AT33)/100),2)) -> 0 | Y33: =(ROUND((((S33+ROUND((ROUND(((EU33)*AV33*I33),2)*BS33),2))*AU33)/100),2)+ROUND(((ROUND((ROUND(((AE33-(EU33))*AV33*I33),2)*BS33),2)*AU33)/100),2)) -> 0 | AA33: 60258618 | AB33: =ROUND((AC33+AD33+AF33),6) -> 1655.62 | AC33: =ROUND((ES33),6) -> 1655.62 | AD33: =ROUND((((ET33)-(EU33))+AE33),6) -> 0 | AE33: =ROUND((EU33),6) -> 0 | AF33: =ROUND((EV33),6) -> 0 | AG33: =ROUND((AP33),6) -> 0 | AH33: =(EW33) -> 0 | AI33: =(EX33) -> 0 | AJ33: =(AS33) -> 0 | AK33: 1655.62 | AL33: 1655.62 | AM33: 0 | AN33: 0 | AO33: 0 | AP33: 0 | AQ33: 0 | AR33: 0 | AS33: 0 | AT33: 0 | AU33: 0 | AV33: 1 | AW33: 1 | AZ33: 1 | BA33: 1 | BB33: 1 | BC33: 7.66 | BH33: 3 | BI33: 3 | BM33: 746 | BN33: 0 | BP33: 0 | BQ33: 130 | BR33: 0 | BS33: 1 | BT33: 1 | BU33: 1 | BV33: 1 | BW33: 1 | BX33: 1 | BZ33: 0 | CA33: 0 | CE33: 1566 | CF33: 0 | CG33: 0 | CM33: 0 | CO33: 0 | CP33: =(P33+Q33+S33) -> 12682.05 | CQ33: =ROUND((ROUND((AC33*1),2)*BC33),2) -> 12682.05 | CR33: =(ROUND((ROUND(((ET33)*AV33*1),2)*BB33),2)+ROUND((ROUND(((AE33-(EU33))*AV33*1),2)*BS33),2)) -> 0 | CS33: =(ROUND((ROUND(((EU33)*AV33*1),2)*BS33),2)+ROUND((ROUND(((AE33-(EU33))*AV33*1),2)*BS33),2)) -> 0 | CT33: =ROUND((ROUND((AF33*AV33*1),2)*BA33),2) -> 0 | CU33: =AG33 -> 0 | CV33: =(AH33*AV33) -> 0 | CW33: =AI33 -> 0 | CX33: =AJ33 -> 0 | CY33: =(ROUND((((S33+ROUND((ROUND(((EU33)*AV33*1),2)*BS33),2))*AT33)/100),2)+ROUND(((ROUND((ROUND(((AE33-(EU33))*AV33*1),2)*BS33),2)*AT33)/100),2)) -> 0 | CZ33: =(ROUND((((S33+ROUND((ROUND(((EU33)*AV33*1),2)*BS33),2))*AU33)/100),2)+ROUND(((ROUND((ROUND(((AE33-(EU33))*AV33*1),2)*BS33),2)*AU33)/100),2)) -> 0 | DN33: 0 | DO33: 0 | DP33: 1 | DQ33: 1 | DU33: 1013 | DV33: ШТ | DW33: ШТ | DX33: 1 | EE33: 60088638 | EF33: 130 | EG33: Сметная стоимость оборудования | EH33: 0 | EJ33: 3 | EK33: 746 | EL33: ТСН-2001.13. Сметная стоимость оборудования | EM33: ТСН-2001.13 | EQ33: 0 | ER33: 0 | ES33: 1655.62 | ET33: 0 | EU33: 0 | EV33: 0 | EW33: 0 | EX33: 0 | EY33: 0 | EZ33: 5 | FC33: 1 | FD33: 18 | FF33: 14600 | FQ33: 0 | FR33: =P33 -> 12682.05 | FS33: 0 | FX33: 0 | FY33: 0 | GA33: [14 600 / 1,2 / 7,66] + 3% Трансп + 1,2% Заг.скл | GD33: 1 | GF33: 963458923 | GG33: 2 | GH33: 3 | GI33: 5 | GJ33: 0 | GK33: 0 | GL33: =ROUND(IF(AND(BH33=3,BI33=3,FS33<>0),P33,0),2) -> 0 | GM33: =ROUND(O33+X33+Y33,2)+GX33 -> 12682.05 | GN33: =IF(OR(BI33=0,BI33=1),GM33-GX33,0) -> 0 | GO33: =IF(BI33=2,GM33-GX33,0) -> 0 | GP33: =IF(BI33=4,GM33-GX33,0) -> 0 | GR33: 1 | GS33: 1 | GT33: 0 | GV33: =ROUND((GT33),6) -> 0 | GW33: 1 | GX33: =ROUND(HC33*I33,2) -> 0 | HA33: 0 | HB33: 0 | HC33: =GV33*GW33 -> 0 | HE33: 3 | HF33: 1,2 | HS33: 0 | IK33: 0
A34: 17 | B34: 1 | C34: =ROW(SmtRes!A14) -> 14 | D34: =ROW(EtalonRes!A19) -> 19 | E34: 4 | F34: 4.10-173-2 | G34: Монтаж блока бесперебойного питания (ББП) в диспетчерской | H34: 1 ШТ. | I34: 1 | J34: 0 | K34: 1 | O34: =ROUND(CP34,2) -> 48.6 | P34: =ROUND((ROUND((AC34*AW34*I34),2)*BC34),2) -> 2.34 | Q34: =(ROUND((ROUND((((ET34*1.1))*AV34*I34),2)*BB34),2)+ROUND((ROUND(((AE34-((EU34*1.1)))*AV34*I34),2)*BS34),2)) -> 0 | R34: =(ROUND((ROUND((((EU34*1.1))*AV34*I34),2)*BS34),2)+ROUND((ROUND(((AE34-((EU34*1.1)))*AV34*I34),2)*BS34),2)) -> 0 | S34: =ROUND((ROUND((AF34*AV34*I34),2)*BA34),2) -> 46.26 | T34: =ROUND(CU34*I34,2) -> 0 | U34: =CV34*I34 -> 3.662406 | V34: =CW34*I34 -> 0 | W34: =ROUND(CX34*I34,2) -> 0 | X34: =(ROUND((((S34+ROUND((ROUND((((EU34*1.1))*AV34*I34),2)*BS34),2))*AT34)/100),2)+ROUND(((ROUND((ROUND(((AE34-((EU34*1.1)))*AV34*I34),2)*BS34),2)*AT34)/100),2)) -> 41.63 | Y34: =(ROUND((((S34+ROUND((ROUND((((EU34*1.1))*AV34*I34),2)*BS34),2))*AU34)/100),2)+ROUND(((ROUND((ROUND(((AE34-((EU34*1.1)))*AV34*I34),2)*BS34),2)*AU34)/100),2)) -> 21.28 | AA34: 60258621 | AB34: =ROUND((AC34+AD34+AF34),6) -> 46.527 | AC34: =ROUND(((ES34*1)),6) -> 2.34 | AD34: =ROUND(((((ET34*1.1))-((EU34*1.1)))+AE34),6) -> 0 | AE34: =ROUND(((EU34*1.1)),6) -> 0 | AF34: =ROUND(((EV34*1.1)),6) -> 44.187 | AG34: =ROUND((AP34),6) -> 0 | AH34: =((EW34*1.1)) -> 3.498 | AI34: =((EX34*1.1)) -> 0 | AJ34: =(AS34) -> 0 | AK34: 42.51 | AL34: 2.34 | AM34: 0 | AN34: 0 | AO34: 40.17 | AP34: 0 | AQ34: 3.18 | AR34: 0 | AS34: 0 | AT34: 90 | AU34: 46 | AV34: 1.047 | AW34: 1 | AZ34: 1 | BA34: 1 | BB34: 1 | BC34: 1 | BH34: 0 | BI34: 2 | BJ34: ТСН-2001.4 Доп. 67, Сб. 10, т. 173, поз. 2 | BM34: 68 | BN34: 58973116 | BO34: 4.10-173-2 | BP34: 1 | BQ34: 40 | BR34: 0 | BS34: 1 | BT34: 1 | BU34: 1 | BV34: 1 | BW34: 1 | BX34: 1 | BZ34: 90 | CA34: 46 | CE34: 1566 | CF34: 0 | CG34: 0 | CM34: 0 | CN34: Поправка: Гл.12.Прил.8.п.8. 5_12.00.01.11.003 Наименование: При наличии усложненных условий производства работ (стесненность, сложность складирования и транспортной логистики, наличие в зоне производства работ действующего технологического оборудования или движения технологического транспорта и т.п.) для объектов, расположенных за пределами территории круговой магистральной системы улиц "Садовое кольцо" и за пределами Третьего транспортного кольца города Москвы пунктов "а" и "б", но в пределах Московской кольцевой автомобильной дороги | CO34: 0 | CP34: =(P34+Q34+S34) -> 48.6 | CQ34: =ROUND((ROUND((AC34*AW34*1),2)*BC34),2) -> 2.34 | CR34: =(ROUND((ROUND((((ET34*1.1))*AV34*1),2)*BB34),2)+ROUND((ROUND(((AE34-((EU34*1.1)))*AV34*1),2)*BS34),2)) -> 0 | CS34: =(ROUND((ROUND((((EU34*1.1))*AV34*1),2)*BS34),2)+ROUND((ROUND(((AE34-((EU34*1.1)))*AV34*1),2)*BS34),2)) -> 0 | CT34: =ROUND((ROUND((AF34*AV34*1),2)*BA34),2) -> 46.26 | CU34: =AG34 -> 0 | CV34: =(AH34*AV34) -> 3.662406 | CW34: =AI34 -> 0 | CX34: =AJ34 -> 0 | CY34: =(ROUND((((S34+ROUND((ROUND((((EU34*1.1))*AV34*1),2)*BS34),2))*AT34)/100),2)+ROUND(((ROUND((ROUND(((AE34-((EU34*1.1)))*AV34*1),2)*BS34),2)*AT34)/100),2)) -> 41.63 | CZ34: =(ROUND((((S34+ROUND((ROUND((((EU34*1.1))*AV34*1),2)*BS34),2))*AU34)/100),2)+ROUND(((ROUND((ROUND(((AE34-((EU34*1.1)))*AV34*1),2)*BS34),2)*AU34)/100),2)) -> 21.28 | DB34: 3 | DD34: *1 | DE34: *1,1 | DF34: *1,1 | DG34: *1,1 | DI34: *1,1 | DJ34: *1,1 | DN34: 0 | DO34: 0 | DP34: 1 | DQ34: 1 | DU34: 1013 | DV34: 1 ШТ. | DW34: 1 ШТ. | DX34: 1 | EE34: 60088532 | EF34: 40 | EG34: Монтаж оборудования | EH34: 0 | EJ34: 2 | EK34: 68 | EL34: ТСН-2001.4-10. Прокладка и монтаж сетей связи | EM34: ТСН-2001.4-10-1 | EO34: Поправка: Гл.12.Прил.8.п.8. 5_12.00.01.11.003 | EQ34: 0 | ER34: 42.51 | ES34: 2.34 | ET34: 0 | EU34: 0 | EV34: 40.17 | EW34: 3.18 | EX34: 0 | EY34: 0 | FQ34: 0 | FR34: 0 | FS34: 0 | FX34: 90 | FY34: 46 | GD34: 1 | GF34: 1548884140 | GG34: 2 | GH34: 1 | GI34: 2 | GJ34: 0 | GK34: 0 | GL34: =ROUND(IF(AND(BH34=3,BI34=3,FS34<>0),P34,0),2) -> 0 | GM34: =ROUND(O34+X34+Y34,2)+GX34 -> 111.51 | GN34: =IF(OR(BI34=0,BI34=1),GM34-GX34,0) -> 0 | GO34: =IF(BI34=2,GM34-GX34,0) -> 111.51 | GP34: =IF(BI34=4,GM34-GX34,0) -> 0 | GR34: 0 | GS34: 3 | GT34: 0 | GV34: =ROUND((GT34),6) -> 0 | GW34: 1 | GX34: =ROUND(HC34*I34,2) -> 0 | HA34: 0 | HB34: 0 | HC34: =GV34*GW34 -> 0 | HS34: 0 | IK34: 0
A35: 17 | B35: 1 | C35: =ROW(SmtRes!A18) -> 18 | D35: =ROW(EtalonRes!A24) -> 24 | E35: 4 | F35: 4.10-173-2 | G35: Монтаж блока бесперебойного питания (ББП) в диспетчерской | H35: 1 ШТ. | I35: 1 | J35: 0 | K35: 1 | O35: =ROUND(CP35,2) -> 2567.85 | P35: =ROUND((ROUND((AC35*AW35*I35),2)*BC35),2) -> 24.01 | Q35: =(ROUND((ROUND((((ET35*1.1))*AV35*I35),2)*BB35),2)+ROUND((ROUND(((AE35-((EU35*1.1)))*AV35*I35),2)*BS35),2)) -> 0 | R35: =(ROUND((ROUND((((EU35*1.1))*AV35*I35),2)*BS35),2)+ROUND((ROUND(((AE35-((EU35*1.1)))*AV35*I35),2)*BS35),2)) -> 0 | S35: =ROUND((ROUND((AF35*AV35*I35),2)*BA35),2) -> 2543.84 | T35: =ROUND(CU35*I35,2) -> 0 | U35: =CV35*I35 -> 3.662406 | V35: =CW35*I35 -> 0 | W35: =ROUND(CX35*I35,2) -> 0 | X35: =(ROUND((((S35+ROUND((ROUND((((EU35*1.1))*AV35*I35),2)*BS35),2))*AT35)/100),2)+ROUND(((ROUND((ROUND(((AE35-((EU35*1.1)))*AV35*I35),2)*BS35),2)*AT35)/100),2)) -> 2289.46 | Y35: =(ROUND((((S35+ROUND((ROUND((((EU35*1.1))*AV35*I35),2)*BS35),2))*AU35)/100),2)+ROUND(((ROUND((ROUND(((AE35-((EU35*1.1)))*AV35*I35),2)*BS35),2)*AU35)/100),2)) -> 1170.17 | AA35: 60258618 | AB35: =ROUND((AC35+AD35+AF35),6) -> 46.527 | AC35: =ROUND(((ES35*1)),6) -> 2.34 | AD35: =ROUND(((((ET35*1.1))-((EU35*1.1)))+AE35),6) -> 0 | AE35: =ROUND(((EU35*1.1)),6) -> 0 | AF35: =ROUND(((EV35*1.1)),6) -> 44.187 | AG35: =ROUND((AP35),6) -> 0 | AH35: =((EW35*1.1)) -> 3.498 | AI35: =((EX35*1.1)) -> 0 | AJ35: =(AS35) -> 0 | AK35: 42.51 | AL35: 2.34 | AM35: 0 | AN35: 0 | AO35: 40.17 | AP35: 0 | AQ35: 3.18 | AR35: 0 | AS35: 0 | AT35: 90 | AU35: 46 | AV35: 1.047 | AW35: 1 | AZ35: 1 | BA35: 54.99 | BB35: 1 | BC35: 10.26 | BH35: 0 | BI35: 2 | BJ35: ТСН-2001.4 Доп. 67, Сб. 10, т. 173, поз. 2 | BM35: 68 | BN35: 58973116 | BO35: 4.10-173-2 | BP35: 1 | BQ35: 40 | BR35: 0 | BS35: 54.99 | BT35: 1 | BU35: 1 | BV35: 1 | BW35: 1 | BX35: 1 | BZ35: 90 | CA35: 46 | CE35: 1566 | CF35: 0 | CG35: 0 | CM35: 0 | CN35: Поправка: Гл.12.Прил.8.п.8. 5_12.00.01.11.003 Наименование: При наличии усложненных условий производства работ (стесненность, сложность складирования и транспортной логистики, наличие в зоне производства работ действующего технологического оборудования или движения технологического транспорта и т.п.) для объектов, расположенных за пределами территории круговой магистральной системы улиц "Садовое кольцо" и за пределами Третьего транспортного кольца города Москвы пунктов "а" и "б", но в пределах Московской кольцевой автомобильной дороги | CO35: 0 | CP35: =(P35+Q35+S35) -> 2567.85 | CQ35: =ROUND((ROUND((AC35*AW35*1),2)*BC35),2) -> 24.01 | CR35: =(ROUND((ROUND((((ET35*1.1))*AV35*1),2)*BB35),2)+ROUND((ROUND(((AE35-((EU35*1.1)))*AV35*1),2)*BS35),2)) -> 0 | CS35: =(ROUND((ROUND((((EU35*1.1))*AV35*1),2)*BS35),2)+ROUND((ROUND(((AE35-((EU35*1.1)))*AV35*1),2)*BS35),2)) -> 0 | CT35: =ROUND((ROUND((AF35*AV35*1),2)*BA35),2) -> 2543.84 | CU35: =AG35 -> 0 | CV35: =(AH35*AV35) -> 3.662406 | CW35: =AI35 -> 0 | CX35: =AJ35 -> 0 | CY35: =(ROUND((((S35+ROUND((ROUND((((EU35*1.1))*AV35*1),2)*BS35),2))*AT35)/100),2)+ROUND(((ROUND((ROUND(((AE35-((EU35*1.1)))*AV35*1),2)*BS35),2)*AT35)/100),2)) -> 2289.46 | CZ35: =(ROUND((((S35+ROUND((ROUND((((EU35*1.1))*AV35*1),2)*BS35),2))*AU35)/100),2)+ROUND(((ROUND((ROUND(((AE35-((EU35*1.1)))*AV35*1),2)*BS35),2)*AU35)/100),2)) -> 1170.17 | DB35: 4 | DD35: *1 | DE35: *1,1 | DF35: *1,1 | DG35: *1,1 | DI35: *1,1 | DJ35: *1,1 | DN35: 0 | DO35: 0 | DP35: 1 | DQ35: 1 | DU35: 1013 | DV35: 1 ШТ. | DW35: 1 ШТ. | DX35: 1 | EE35: 60088532 | EF35: 40 | EG35: Монтаж оборудования | EH35: 0 | EJ35: 2 | EK35: 68 | EL35: ТСН-2001.4-10. Прокладка и монтаж сетей связи | EM35: ТСН-2001.4-10-1 | EO35: Поправка: Гл.12.Прил.8.п.8. 5_12.00.01.11.003 | EQ35: 0 | ER35: 42.51 | ES35: 2.34 | ET35: 0 | EU35: 0 | EV35: 40.17 | EW35: 3.18 | EX35: 0 | EY35: 0 | FQ35: 0 | FR35: 0 | FS35: 0 | FX35: 90 | FY35: 46 | GD35: 1 | GF35: 1548884140 | GG35: 2 | GH35: 1 | GI35: 2 | GJ35: 0 | GK35: 0 | GL35: =ROUND(IF(AND(BH35=3,BI35=3,FS35<>0),P35,0),2) -> 0 | GM35: =ROUND(O35+X35+Y35,2)+GX35 -> 6027.48 | GN35: =IF(OR(BI35=0,BI35=1),GM35-GX35,0) -> 0 | GO35: =IF(BI35=2,GM35-GX35,0) -> 6027.48 | GP35: =IF(BI35=4,GM35-GX35,0) -> 0 | GR35: 0 | GS35: 3 | GT35: 0 | GV35: =ROUND((GT35),6) -> 0 | GW35: 1 | GX35: =ROUND(HC35*I35,2) -> 0 | HA35: 0 | HB35: 0 | HC35: =GV35*GW35 -> 0 | HS35: 0 | IK35: 0
A36: 17 | B36: 1 | E36: 5 | F36: КА-3 | G36: Источник бесперебойного питания, 600Вт Back Basic 1050S Euro | H36: ШТ | I36: 1 | J36: 0 | K36: 1 | O36: =ROUND(CP36,2) -> 1280.27 | P36: =ROUND((ROUND((AC36*I36),2)*BC36),2) -> 1280.27 | Q36: =(ROUND((ROUND(((ET36)*AV36*I36),2)*BB36),2)+ROUND((ROUND(((AE36-(EU36))*AV36*I36),2)*BS36),2)) -> 0 | R36: =(ROUND((ROUND(((EU36)*AV36*I36),2)*BS36),2)+ROUND((ROUND(((AE36-(EU36))*AV36*I36),2)*BS36),2)) -> 0 | S36: =ROUND((ROUND((AF36*AV36*I36),2)*BA36),2) -> 0 | T36: =ROUND(CU36*I36,2) -> 0 | U36: =CV36*I36 -> 0 | V36: =CW36*I36 -> 0 | W36: =ROUND(CX36*I36,2) -> 0 | X36: =(ROUND((((S36+ROUND((ROUND(((EU36)*AV36*I36),2)*BS36),2))*AT36)/100),2)+ROUND(((ROUND((ROUND(((AE36-(EU36))*AV36*I36),2)*BS36),2)*AT36)/100),2)) -> 0 | Y36: =(ROUND((((S36+ROUND((ROUND(((EU36)*AV36*I36),2)*BS36),2))*AU36)/100),2)+ROUND(((ROUND((ROUND(((AE36-(EU36))*AV36*I36),2)*BS36),2)*AU36)/100),2)) -> 0 | AA36: 60258621 | AB36: =ROUND((AC36+AD36+AF36),6) -> 1280.27 | AC36: =ROUND((ES36),6) -> 1280.27 | AD36: =ROUND((((ET36)-(EU36))+AE36),6) -> 0 | AE36: =ROUND((EU36),6) -> 0 | AF36: =ROUND((EV36),6) -> 0 | AG36: =ROUND((AP36),6) -> 0 | AH36: =(EW36) -> 0 | AI36: =(EX36) -> 0 | AJ36: =(AS36) -> 0 | AK36: 1280.27 | AL36: 1280.27 | AM36: 0 | AN36: 0 | AO36: 0 | AP36: 0 | AQ36: 0 | AR36: 0 | AS36: 0 | AT36: 0 | AU36: 0 | AV36: 1 | AW36: 1 | AZ36: 1 | BA36: 1 | BB36: 1 | BC36: 1 | BH36: 3 | BI36: 3 | BM36: 746 | BN36: 0 | BP36: 0 | BQ36: 130 | BR36: 0 | BS36: 1 | BT36: 1 | BU36: 1 | BV36: 1 | BW36: 1 | BX36: 1 | BZ36: 0 | CA36: 0 | CE36: 1566 | CF36: 0 | CG36: 0 | CM36: 0 | CO36: 0 | CP36: =(P36+Q36+S36) -> 1280.27 | CQ36: =ROUND((ROUND((AC36*1),2)*BC36),2) -> 1280.27 | CR36: =(ROUND((ROUND(((ET36)*AV36*1),2)*BB36),2)+ROUND((ROUND(((AE36-(EU36))*AV36*1),2)*BS36),2)) -> 0 | CS36: =(ROUND((ROUND(((EU36)*AV36*1),2)*BS36),2)+ROUND((ROUND(((AE36-(EU36))*AV36*1),2)*BS36),2)) -> 0 | CT36: =ROUND((ROUND((AF36*AV36*1),2)*BA36),2) -> 0 | CU36: =AG36 -> 0 | CV36: =(AH36*AV36) -> 0 | CW36: =AI36 -> 0 | CX36: =AJ36 -> 0 | CY36: =(ROUND((((S36+ROUND((ROUND(((EU36)*AV36*1),2)*BS36),2))*AT36)/100),2)+ROUND(((ROUND((ROUND(((AE36-(EU36))*AV36*1),2)*BS36),2)*AT36)/100),2)) -> 0 | CZ36: =(ROUND((((S36+ROUND((ROUND(((EU36)*AV36*1),2)*BS36),2))*AU36)/100),2)+ROUND(((ROUND((ROUND(((AE36-(EU36))*AV36*1),2)*BS36),2)*AU36)/100),2)) -> 0 | DN36: 0 | DO36: 0 | DP36: 1 | DQ36: 1 | DU36: 1013 | DV36: ШТ | DW36: ШТ | DX36: 1 | EE36: 60088638 | EF36: 130 | EG36: Сметная стоимость оборудования | EH36: 0 | EJ36: 3 | EK36: 746 | EL36: ТСН-2001.13. Сметная стоимость оборудования | EM36: ТСН-2001.13 | EQ36: 0 | ER36: 0 | ES36: 1280.27 | ET36: 0 | EU36: 0 | EV36: 0 | EW36: 0 | EX36: 0 | EY36: 0 | FQ36: 0 | FR36: =P36 -> 1280.27 | FS36: 0 | FX36: 0 | FY36: 0 | GA36: [11 290 / 1,2 / 7,66] + 3% Трансп + 1,2% Заг.скл | GD36: 1 | GF36: -410713413 | GG36: 2 | GH36: 4 | GI36: -2 | GJ36: 0 | GK36: 0 | GL36: =ROUND(IF(AND(BH36=3,BI36=3,FS36<>0),P36,0),2) -> 0 | GM36: =ROUND(O36+X36+Y36,2)+GX36 -> 1280.27 | GN36: =IF(OR(BI36=0,BI36=1),GM36-GX36,0) -> 0 | GO36: =IF(BI36=2,GM36-GX36,0) -> 0 | GP36: =IF(BI36=4,GM36-GX36,0) -> 0 | GR36: 0 | GS36: 2 | GT36: 0 | GV36: =ROUND((GT36),6) -> 0 | GW36: 1 | GX36: =ROUND(HC36*I36,2) -> 0 | HA36: 0 | HB36: 0 | HC36: =GV36*GW36 -> 0 | HE36: 3 | HF36: 1,2 | HS36: 0 | IK36: 0
A37: 17 | B37: 1 | E37: 5 | F37: КА-3 | G37: Источник бесперебойного питания, 600Вт Back Basic 1050S Euro | H37: ШТ | I37: 1 | J37: 0 | K37: 1 | O37: =ROUND(CP37,2) -> 9806.87 | P37: =ROUND((ROUND((AC37*I37),2)*BC37),2) -> 9806.87 | Q37: =(ROUND((ROUND(((ET37)*AV37*I37),2)*BB37),2)+ROUND((ROUND(((AE37-(EU37))*AV37*I37),2)*BS37),2)) -> 0 | R37: =(ROUND((ROUND(((EU37)*AV37*I37),2)*BS37),2)+ROUND((ROUND(((AE37-(EU37))*AV37*I37),2)*BS37),2)) -> 0 | S37: =ROUND((ROUND((AF37*AV37*I37),2)*BA37),2) -> 0 | T37: =ROUND(CU37*I37,2) -> 0 | U37: =CV37*I37 -> 0 | V37: =CW37*I37 -> 0 | W37: =ROUND(CX37*I37,2) -> 0 | X37: =(ROUND((((S37+ROUND((ROUND(((EU37)*AV37*I37),2)*BS37),2))*AT37)/100),2)+ROUND(((ROUND((ROUND(((AE37-(EU37))*AV37*I37),2)*BS37),2)*AT37)/100),2)) -> 0 | Y37: =(ROUND((((S37+ROUND((ROUND(((EU37)*AV37*I37),2)*BS37),2))*AU37)/100),2)+ROUND(((ROUND((ROUND(((AE37-(EU37))*AV37*I37),2)*BS37),2)*AU37)/100),2)) -> 0 | AA37: 60258618 | AB37: =ROUND((AC37+AD37+AF37),6) -> 1280.27 | AC37: =ROUND((ES37),6) -> 1280.27 | AD37: =ROUND((((ET37)-(EU37))+AE37),6) -> 0 | AE37: =ROUND((EU37),6) -> 0 | AF37: =ROUND((EV37),6) -> 0 | AG37: =ROUND((AP37),6) -> 0 | AH37: =(EW37) -> 0 | AI37: =(EX37) -> 0 | AJ37: =(AS37) -> 0 | AK37: 1280.27 | AL37: 1280.27 | AM37: 0 | AN37: 0 | AO37: 0 | AP37: 0 | AQ37: 0 | AR37: 0 | AS37: 0 | AT37: 0 | AU37: 0 | AV37: 1 | AW37: 1 | AZ37: 1 | BA37: 1 | BB37: 1 | BC37: 7.66 | BH37: 3 | BI37: 3 | BM37: 746 | BN37: 0 | BP37: 0 | BQ37: 130 | BR37: 0 | BS37: 1 | BT37: 1 | BU37: 1 | BV37: 1 | BW37: 1 | BX37: 1 | BZ37: 0 | CA37: 0 | CE37: 1566 | CF37: 0 | CG37: 0 | CM37: 0 | CO37: 0 | CP37: =(P37+Q37+S37) -> 9806.87 | CQ37: =ROUND((ROUND((AC37*1),2)*BC37),2) -> 9806.87 | CR37: =(ROUND((ROUND(((ET37)*AV37*1),2)*BB37),2)+ROUND((ROUND(((AE37-(EU37))*AV37*1),2)*BS37),2)) -> 0 | CS37: =(ROUND((ROUND(((EU37)*AV37*1),2)*BS37),2)+ROUND((ROUND(((AE37-(EU37))*AV37*1),2)*BS37),2)) -> 0 | CT37: =ROUND((ROUND((AF37*AV37*1),2)*BA37),2) -> 0 | CU37: =AG37 -> 0 | CV37: =(AH37*AV37) -> 0 | CW37: =AI37 -> 0 | CX37: =AJ37 -> 0 | CY37: =(ROUND((((S37+ROUND((ROUND(((EU37)*AV37*1),2)*BS37),2))*AT37)/100),2)+ROUND(((ROUND((ROUND(((AE37-(EU37))*AV37*1),2)*BS37),2)*AT37)/100),2)) -> 0 | CZ37: =(ROUND((((S37+ROUND((ROUND(((EU37)*AV37*1),2)*BS37),2))*AU37)/100),2)+ROUND(((ROUND((ROUND(((AE37-(EU37))*AV37*1),2)*BS37),2)*AU37)/100),2)) -> 0 | DN37: 0 | DO37: 0 | DP37: 1 | DQ37: 1 | DU37: 1013 | DV37: ШТ | DW37: ШТ | DX37: 1 | EE37: 60088638 | EF37: 130 | EG37: Сметная стоимость оборудования | EH37: 0 | EJ37: 3 | EK37: 746 | EL37: ТСН-2001.13. Сметная стоимость оборудования | EM37: ТСН-2001.13 | EQ37: 0 | ER37: 0 | ES37: 1280.27 | ET37: 0 | EU37: 0 | EV37: 0 | EW37: 0 | EX37: 0 | EY37: 0 | EZ37: 5 | FC37: 1 | FD37: 18 | FF37: 11290 | FQ37: 0 | FR37: =P37 -> 9806.87 | FS37: 0 | FX37: 0 | FY37: 0 | GA37: [11 290 / 1,2 / 7,66] + 3% Трансп + 1,2% Заг.скл | GD37: 1 | GF37: -410713413 | GG37: 2 | GH37: 3 | GI37: 5 | GJ37: 0 | GK37: 0 | GL37: =ROUND(IF(AND(BH37=3,BI37=3,FS37<>0),P37,0),2) -> 0 | GM37: =ROUND(O37+X37+Y37,2)+GX37 -> 9806.87 | GN37: =IF(OR(BI37=0,BI37=1),GM37-GX37,0) -> 0 | GO37: =IF(BI37=2,GM37-GX37,0) -> 0 | GP37: =IF(BI37=4,GM37-GX37,0) -> 0 | GR37: 1 | GS37: 1 | GT37: 0 | GV37: =ROUND((GT37),6) -> 0 | GW37: 1 | GX37: =ROUND(HC37*I37,2) -> 0 | HA37: 0 | HB37: 0 | HC37: =GV37*GW37 -> 0 | HE37: 3 | HF37: 1,2 | HS37: 0 | IK37: 0
A38: 17 | B38: 1 | C38: =ROW(SmtRes!A19) -> 19 | D38: =ROW(EtalonRes!A25) -> 25 | E38: 6 | F38: 4.10-80-1 | G38: Аппараты приемные, приборы ПС приемно-контрольные, пусковые, концентратор, блок базовый на 10 лучей | H38: 1 ШТ. | I38: 1 | J38: 0 | K38: 1 | O38: =ROUND(CP38,2) -> 122.06 | P38: =ROUND((ROUND((AC38*AW38*I38),2)*BC38),2) -> 12.53 | Q38: =(ROUND((ROUND((((ET38*1.1))*AV38*I38),2)*BB38),2)+ROUND((ROUND(((AE38-((EU38*1.1)))*AV38*I38),2)*BS38),2)) -> 0.07 | R38: =(ROUND((ROUND((((EU38*1.1))*AV38*I38),2)*BS38),2)+ROUND((ROUND(((AE38-((EU38*1.1)))*AV38*I38),2)*BS38),2)) -> 0.01 | S38: =ROUND((ROUND((AF38*AV38*I38),2)*BA38),2) -> 109.46 | T38: =ROUND(CU38*I38,2) -> 0 | U38: =CV38*I38 -> 8.29224 | V38: =CW38*I38 -> 0 | W38: =ROUND(CX38*I38,2) -> 0 | X38: =(ROUND((((S38+ROUND((ROUND((((EU38*1.1))*AV38*I38),2)*BS38),2))*AT38)/100),2)+ROUND(((ROUND((ROUND(((AE38-((EU38*1.1)))*AV38*I38),2)*BS38),2)*AT38)/100),2)) -> 98.52 | Y38: =(ROUND((((S38+ROUND((ROUND((((EU38*1.1))*AV38*I38),2)*BS38),2))*AU38)/100),2)+ROUND(((ROUND((ROUND(((AE38-((EU38*1.1)))*AV38*I38),2)*BS38),2)*AU38)/100),2)) -> 50.36 | AA38: 60258621 | AB38: =ROUND((AC38+AD38+AF38),6) -> 117.14 | AC38: =ROUND(((ES38*1)),6) -> 12.53 | AD38: =ROUND(((((ET38*1.1))-((EU38*1.1)))+AE38),6) -> 0.066 | AE38: =ROUND(((EU38*1.1)),6) -> 0.011 | AF38: =ROUND(((EV38*1.1)),6) -> 104.544 | AG38: =ROUND((AP38),6) -> 0 | AH38: =((EW38*1.1)) -> 7.92 | AI38: =((EX38*1.1)) -> 0 | AJ38: =(AS38) -> 0 | AK38: 107.63 | AL38: 12.53 | AM38: 0.06 | AN38: 0.01 | AO38: 95.04 | AP38: 0 | AQ38: 7.2 | AR38: 0 | AS38: 0 | AT38: 90 | AU38: 46 | AV38: 1.047 | AW38: 1 | AZ38: 1 | BA38: 1 | BB38: 1 | BC38: 1 | BH38: 0 | BI38: 2 | BJ38: ТСН-2001.4 Доп. 68, Сб. 10, т. 80, поз. 1 | BM38: 68 | BN38: 58973116 | BO38: 4.10-80-1 | BP38: 1 | BQ38: 40 | BR38: 0 | BS38: 1 | BT38: 1 | BU38: 1 | BV38: 1 | BW38: 1 | BX38: 1 | BZ38: 90 | CA38: 46 | CE38: 1566 | CF38: 0 | CG38: 0 | CM38: 0 | CN38: Поправка: Гл.12.Прил.8.п.8. 5_12.00.01.11.003 Наименование: При наличии усложненных условий производства работ (стесненность, сложность складирования и транспортной логистики, наличие в зоне производства работ действующего технологического оборудования или движения технологического транспорта и т.п.) для объектов, расположенных за пределами территории круговой магистральной системы улиц "Садовое кольцо" и за пределами Третьего транспортного кольца города Москвы пунктов "а" и "б", но в пределах Московской кольцевой автомобильной дороги | CO38: 0 | CP38: =(P38+Q38+S38) -> 122.06 | CQ38: =ROUND((ROUND((AC38*AW38*1),2)*BC38),2) -> 12.53 | CR38: =(ROUND((ROUND((((ET38*1.1))*AV38*1),2)*BB38),2)+ROUND((ROUND(((AE38-((EU38*1.1)))*AV38*1),2)*BS38),2)) -> 0.07 | CS38: =(ROUND((ROUND((((EU38*1.1))*AV38*1),2)*BS38),2)+ROUND((ROUND(((AE38-((EU38*1.1)))*AV38*1),2)*BS38),2)) -> 0.01 | CT38: =ROUND((ROUND((AF38*AV38*1),2)*BA38),2) -> 109.46 | CU38: =AG38 -> 0 | CV38: =(AH38*AV38) -> 8.29224 | CW38: =AI38 -> 0 | CX38: =AJ38 -> 0 | CY38: =(ROUND((((S38+ROUND((ROUND((((EU38*1.1))*AV38*1),2)*BS38),2))*AT38)/100),2)+ROUND(((ROUND((ROUND(((AE38-((EU38*1.1)))*AV38*1),2)*BS38),2)*AT38)/100),2)) -> 98.52 | CZ38: =(ROUND((((S38+ROUND((ROUND((((EU38*1.1))*AV38*1),2)*BS38),2))*AU38)/100),2)+ROUND(((ROUND((ROUND(((AE38-((EU38*1.1)))*AV38*1),2)*BS38),2)*AU38)/100),2)) -> 50.36 | DB38: 5 | DD38: *1 | DE38: *1,1 | DF38: *1,1 | DG38: *1,1 | DI38: *1,1 | DJ38: *1,1 | DN38: 0 | DO38: 0 | DP38: 1 | DQ38: 1 | DU38: 1013 | DV38: 1 ШТ. | DW38: 1 ШТ. | DX38: 1 | EE38: 60088532 | EF38: 40 | EG38: Монтаж оборудования | EH38: 0 | EJ38: 2 | EK38: 68 | EL38: ТСН-2001.4-10. Прокладка и монтаж сетей связи | EM38: ТСН-2001.4-10-1 | EO38: Поправка: Гл.12.Прил.8.п.8. 5_12.00.01.11.003 | EQ38: 0 | ER38: 107.63 | ES38: 12.53 | ET38: 0.06 | EU38: 0.01 | EV38: 95.04 | EW38: 7.2 | EX38: 0 | EY38: 0 | FQ38: 0 | FR38: 0 | FS38: 0 | FX38: 90 | FY38: 46 | GD38: 1 | GF38: 723018335 | GG38: 2 | GH38: 1 | GI38: 2 | GJ38: 0 | GK38: 0 | GL38: =ROUND(IF(AND(BH38=3,BI38=3,FS38<>0),P38,0),2) -> 0 | GM38: =ROUND(O38+X38+Y38,2)+GX38 -> 270.94 | GN38: =IF(OR(BI38=0,BI38=1),GM38-GX38,0) -> 0 | GO38: =IF(BI38=2,GM38-GX38,0) -> 270.94 | GP38: =IF(BI38=4,GM38-GX38,0) -> 0 | GR38: 0 | GS38: 3 | GT38: 0 | GV38: =ROUND((GT38),6) -> 0 | GW38: 1 | GX38: =ROUND(HC38*I38,2) -> 0 | HA38: 0 | HB38: 0 | HC38: =GV38*GW38 -> 0 | HS38: 0 | IK38: 0
A39: 17 | B39: 1 | C39: =ROW(SmtRes!A20) -> 20 | D39: =ROW(EtalonRes!A26) -> 26 | E39: 6 | F39: 4.10-80-1 | G39: Аппараты приемные, приборы ПС приемно-контрольные, пусковые, концентратор, блок базовый на 10 лучей | H39: 1 ШТ. | I39: 1 | J39: 0 | K39: 1 | O39: =ROUND(CP39,2) -> 6144.36 | P39: =ROUND((ROUND((AC39*AW39*I39),2)*BC39),2) -> 123.92 | Q39: =(ROUND((ROUND((((ET39*1.1))*AV39*I39),2)*BB39),2)+ROUND((ROUND(((AE39-((EU39*1.1)))*AV39*I39),2)*BS39),2)) -> 1.23 | R39: =(ROUND((ROUND((((EU39*1.1))*AV39*I39),2)*BS39),2)+ROUND((ROUND(((AE39-((EU39*1.1)))*AV39*I39),2)*BS39),2)) -> 0.55 | S39: =ROUND((ROUND((AF39*AV39*I39),2)*BA39),2) -> 6019.21 | T39: =ROUND(CU39*I39,2) -> 0 | U39: =CV39*I39 -> 8.29224 | V39: =CW39*I39 -> 0 | W39: =ROUND(CX39*I39,2) -> 0 | X39: =(ROUND((((S39+ROUND((ROUND((((EU39*1.1))*AV39*I39),2)*BS39),2))*AT39)/100),2)+ROUND(((ROUND((ROUND(((AE39-((EU39*1.1)))*AV39*I39),2)*BS39),2)*AT39)/100),2)) -> 5417.78 | Y39: =(ROUND((((S39+ROUND((ROUND((((EU39*1.1))*AV39*I39),2)*BS39),2))*AU39)/100),2)+ROUND(((ROUND((ROUND(((AE39-((EU39*1.1)))*AV39*I39),2)*BS39),2)*AU39)/100),2)) -> 2769.09 | AA39: 60258618 | AB39: =ROUND((AC39+AD39+AF39),6) -> 117.14 | AC39: =ROUND(((ES39*1)),6) -> 12.53 | AD39: =ROUND(((((ET39*1.1))-((EU39*1.1)))+AE39),6) -> 0.066 | AE39: =ROUND(((EU39*1.1)),6) -> 0.011 | AF39: =ROUND(((EV39*1.1)),6) -> 104.544 | AG39: =ROUND((AP39),6) -> 0 | AH39: =((EW39*1.1)) -> 7.92 | AI39: =((EX39*1.1)) -> 0 | AJ39: =(AS39) -> 0 | AK39: 107.63 | AL39: 12.53 | AM39: 0.06 | AN39: 0.01 | AO39: 95.04 | AP39: 0 | AQ39: 7.2 | AR39: 0 | AS39: 0 | AT39: 90 | AU39: 46 | AV39: 1.047 | AW39: 1 | AZ39: 1 | BA39: 54.99 | BB39: 17.5 | BC39: 9.89 | BH39: 0 | BI39: 2 | BJ39: ТСН-2001.4 Доп. 68, Сб. 10, т. 80, поз. 1 | BM39: 68 | BN39: 58973116 | BO39: 4.10-80-1 | BP39: 1 | BQ39: 40 | BR39: 0 | BS39: 54.99 | BT39: 1 | BU39: 1 | BV39: 1 | BW39: 1 | BX39: 1 | BZ39: 90 | CA39: 46 | CE39: 1566 | CF39: 0 | CG39: 0 | CM39: 0 | CN39: Поправка: Гл.12.Прил.8.п.8. 5_12.00.01.11.003 Наименование: При наличии усложненных условий производства работ (стесненность, сложность складирования и транспортной логистики, наличие в зоне производства работ действующего технологического оборудования или движения технологического транспорта и т.п.) для объектов, расположенных за пределами территории круговой магистральной системы улиц "Садовое кольцо" и за пределами Третьего транспортного кольца города Москвы пунктов "а" и "б", но в пределах Московской кольцевой автомобильной дороги | CO39: 0 | CP39: =(P39+Q39+S39) -> 6144.36 | CQ39: =ROUND((ROUND((AC39*AW39*1),2)*BC39),2) -> 123.92 | CR39: =(ROUND((ROUND((((ET39*1.1))*AV39*1),2)*BB39),2)+ROUND((ROUND(((AE39-((EU39*1.1)))*AV39*1),2)*BS39),2)) -> 1.23 | CS39: =(ROUND((ROUND((((EU39*1.1))*AV39*1),2)*BS39),2)+ROUND((ROUND(((AE39-((EU39*1.1)))*AV39*1),2)*BS39),2)) -> 0.55 | CT39: =ROUND((ROUND((AF39*AV39*1),2)*BA39),2) -> 6019.21 | CU39: =AG39 -> 0 | CV39: =(AH39*AV39) -> 8.29224 | CW39: =AI39 -> 0 | CX39: =AJ39 -> 0 | CY39: =(ROUND((((S39+ROUND((ROUND((((EU39*1.1))*AV39*1),2)*BS39),2))*AT39)/100),2)+ROUND(((ROUND((ROUND(((AE39-((EU39*1.1)))*AV39*1),2)*BS39),2)*AT39)/100),2)) -> 5417.78 | CZ39: =(ROUND((((S39+ROUND((ROUND((((EU39*1.1))*AV39*1),2)*BS39),2))*AU39)/100),2)+ROUND(((ROUND((ROUND(((AE39-((EU39*1.1)))*AV39*1),2)*BS39),2)*AU39)/100),2)) -> 2769.09 | DB39: 6 | DD39: *1 | DE39: *1,1 | DF39: *1,1 | DG39: *1,1 | DI39: *1,1 | DJ39: *1,1 | DN39: 0 | DO39: 0 | DP39: 1 | DQ39: 1 | DU39: 1013 | DV39: 1 ШТ. | DW39: 1 ШТ. | DX39: 1 | EE39: 60088532 | EF39: 40 | EG39: Монтаж оборудования | EH39: 0 | EJ39: 2 | EK39: 68 | EL39: ТСН-2001.4-10. Прокладка и монтаж сетей связи | EM39: ТСН-2001.4-10-1 | EO39: Поправка: Гл.12.Прил.8.п.8. 5_12.00.01.11.003 | EQ39: 0 | ER39: 107.63 | ES39: 12.53 | ET39: 0.06 | EU39: 0.01 | EV39: 95.04 | EW39: 7.2 | EX39: 0 | EY39: 0 | FQ39: 0 | FR39: 0 | FS39: 0 | FX39: 90 | FY39: 46 | GD39: 1 | GF39: 723018335 | GG39: 2 | GH39: 1 | GI39: 2 | GJ39: 0 | GK39: 0 | GL39: =ROUND(IF(AND(BH39=3,BI39=3,FS39<>0),P39,0),2) -> 0 | GM39: =ROUND(O39+X39+Y39,2)+GX39 -> 14331.23 | GN39: =IF(OR(BI39=0,BI39=1),GM39-GX39,0) -> 0 | GO39: =IF(BI39=2,GM39-GX39,0) -> 14331.23 | GP39: =IF(BI39=4,GM39-GX39,0) -> 0 | GR39: 0 | GS39: 3 | GT39: 0 | GV39: =ROUND((GT39),6) -> 0 | GW39: 1 | GX39: =ROUND(HC39*I39,2) -> 0 | HA39: 0 | HB39: 0 | HC39: =GV39*GW39 -> 0 | HS39: 0 | IK39: 0
A40: 17 | B40: 1 | E40: 7 | F40: КА-4 | G40: Прибор приемно-контрольный и управленя Рубеж-20П прот. R3 | H40: ШТ | I40: 1 | J40: 0 | K40: 1 | O40: =ROUND(CP40,2) -> 9985.54 | P40: =ROUND((ROUND((AC40*I40),2)*BC40),2) -> 9985.54 | Q40: =(ROUND((ROUND(((ET40)*AV40*I40),2)*BB40),2)+ROUND((ROUND(((AE40-(EU40))*AV40*I40),2)*BS40),2)) -> 0 | R40: =(ROUND((ROUND(((EU40)*AV40*I40),2)*BS40),2)+ROUND((ROUND(((AE40-(EU40))*AV40*I40),2)*BS40),2)) -> 0 | S40: =ROUND((ROUND((AF40*AV40*I40),2)*BA40),2) -> 0 | T40: =ROUND(CU40*I40,2) -> 0 | U40: =CV40*I40 -> 0 | V40: =CW40*I40 -> 0 | W40: =ROUND(CX40*I40,2) -> 0 | X40: =(ROUND((((S40+ROUND((ROUND(((EU40)*AV40*I40),2)*BS40),2))*AT40)/100),2)+ROUND(((ROUND((ROUND(((AE40-(EU40))*AV40*I40),2)*BS40),2)*AT40)/100),2)) -> 0 | Y40: =(ROUND((((S40+ROUND((ROUND(((EU40)*AV40*I40),2)*BS40),2))*AU40)/100),2)+ROUND(((ROUND((ROUND(((AE40-(EU40))*AV40*I40),2)*BS40),2)*AU40)/100),2)) -> 0 | AA40: 60258621 | AB40: =ROUND((AC40+AD40+AF40),6) -> 9985.54 | AC40: =ROUND((ES40),6) -> 9985.54 | AD40: =ROUND((((ET40)-(EU40))+AE40),6) -> 0 | AE40: =ROUND((EU40),6) -> 0 | AF40: =ROUND((EV40),6) -> 0 | AG40: =ROUND((AP40),6) -> 0 | AH40: =(EW40) -> 0 | AI40: =(EX40) -> 0 | AJ40: =(AS40) -> 0 | AK40: 9985.54 | AL40: 9985.54 | AM40: 0 | AN40: 0 | AO40: 0 | AP40: 0 | AQ40: 0 | AR40: 0 | AS40: 0 | AT40: 0 | AU40: 0 | AV40: 1 | AW40: 1 | AZ40: 1 | BA40: 1 | BB40: 1 | BC40: 1 | BH40: 3 | BI40: 3 | BM40: 746 | BN40: 0 | BP40: 0 | BQ40: 130 | BR40: 0 | BS40: 1 | BT40: 1 | BU40: 1 | BV40: 1 | BW40: 1 | BX40: 1 | BZ40: 0 | CA40: 0 | CE40: 1566 | CF40: 0 | CG40: 0 | CM40: 0 | CO40: 0 | CP40: =(P40+Q40+S40) -> 9985.54 | CQ40: =ROUND((ROUND((AC40*1),2)*BC40),2) -> 9985.54 | CR40: =(ROUND((ROUND(((ET40)*AV40*1),2)*BB40),2)+ROUND((ROUND(((AE40-(EU40))*AV40*1),2)*BS40),2)) -> 0 | CS40: =(ROUND((ROUND(((EU40)*AV40*1),2)*BS40),2)+ROUND((ROUND(((AE40-(EU40))*AV40*1),2)*BS40),2)) -> 0 | CT40: =ROUND((ROUND((AF40*AV40*1),2)*BA40),2) -> 0 | CU40: =AG40 -> 0 | CV40: =(AH40*AV40) -> 0 | CW40: =AI40 -> 0 | CX40: =AJ40 -> 0 | CY40: =(ROUND((((S40+ROUND((ROUND(((EU40)*AV40*1),2)*BS40),2))*AT40)/100),2)+ROUND(((ROUND((ROUND(((AE40-(EU40))*AV40*1),2)*BS40),2)*AT40)/100),2)) -> 0 | CZ40: =(ROUND((((S40+ROUND((ROUND(((EU40)*AV40*1),2)*BS40),2))*AU40)/100),2)+ROUND(((ROUND((ROUND(((AE40-(EU40))*AV40*1),2)*BS40),2)*AU40)/100),2)) -> 0 | DN40: 0 | DO40: 0 | DP40: 1 | DQ40: 1 | DU40: 1013 | DV40: ШТ | DW40: ШТ | DX40: 1 | EE40: 60088638 | EF40: 130 | EG40: Сметная стоимость оборудования | EH40: 0 | EJ40: 3 | EK40: 746 | EL40: ТСН-2001.13. Сметная стоимость оборудования | EM40: ТСН-2001.13 | EQ40: 0 | ER40: 0 | ES40: 9985.54 | ET40: 0 | EU40: 0 | EV40: 0 | EW40: 0 | EX40: 0 | EY40: 0 | FQ40: 0 | FR40: =P40 -> 9985.54 | FS40: 0 | FX40: 0 | FY40: 0 | GA40: [88 057 / 1,2 / 7,66] + 3% Трансп + 1,2% Заг.скл | GD40: 1 | GF40: 1190544240 | GG40: 2 | GH40: 4 | GI40: -2 | GJ40: 0 | GK40: 0 | GL40: =ROUND(IF(AND(BH40=3,BI40=3,FS40<>0),P40,0),2) -> 0 | GM40: =ROUND(O40+X40+Y40,2)+GX40 -> 9985.54 | GN40: =IF(OR(BI40=0,BI40=1),GM40-GX40,0) -> 0 | GO40: =IF(BI40=2,GM40-GX40,0) -> 0 | GP40: =IF(BI40=4,GM40-GX40,0) -> 0 | GR40: 0 | GS40: 2 | GT40: 0 | GV40: =ROUND((GT40),6) -> 0 | GW40: 1 | GX40: =ROUND(HC40*I40,2) -> 0 | HA40: 0 | HB40: 0 | HC40: =GV40*GW40 -> 0 | HE40: 3 | HF40: 1,2 | HS40: 0 | IK40: 0
A41: 17 | B41: 1 | E41: 7 | F41: КА-4 | G41: Прибор приемно-контрольный и управленя Рубеж-20П прот. R3 | H41: ШТ | I41: 1 | J41: 0 | K41: 1 | O41: =ROUND(CP41,2) -> 76489.24 | P41: =ROUND((ROUND((AC41*I41),2)*BC41),2) -> 76489.24 | Q41: =(ROUND((ROUND(((ET41)*AV41*I41),2)*BB41),2)+ROUND((ROUND(((AE41-(EU41))*AV41*I41),2)*BS41),2)) -> 0 | R41: =(ROUND((ROUND(((EU41)*AV41*I41),2)*BS41),2)+ROUND((ROUND(((AE41-(EU41))*AV41*I41),2)*BS41),2)) -> 0 | S41: =ROUND((ROUND((AF41*AV41*I41),2)*BA41),2) -> 0 | T41: =ROUND(CU41*I41,2) -> 0 | U41: =CV41*I41 -> 0 | V41: =CW41*I41 -> 0 | W41: =ROUND(CX41*I41,2) -> 0 | X41: =(ROUND((((S41+ROUND((ROUND(((EU41)*AV41*I41),2)*BS41),2))*AT41)/100),2)+ROUND(((ROUND((ROUND(((AE41-(EU41))*AV41*I41),2)*BS41),2)*AT41)/100),2)) -> 0 | Y41: =(ROUND((((S41+ROUND((ROUND(((EU41)*AV41*I41),2)*BS41),2))*AU41)/100),2)+ROUND(((ROUND((ROUND(((AE41-(EU41))*AV41*I41),2)*BS41),2)*AU41)/100),2)) -> 0 | AA41: 60258618 | AB41: =ROUND((AC41+AD41+AF41),6) -> 9985.54 | AC41: =ROUND((ES41),6) -> 9985.54 | AD41: =ROUND((((ET41)-(EU41))+AE41),6) -> 0 | AE41: =ROUND((EU41),6) -> 0 | AF41: =ROUND((EV41),6) -> 0 | AG41: =ROUND((AP41),6) -> 0 | AH41: =(EW41) -> 0 | AI41: =(EX41) -> 0 | AJ41: =(AS41) -> 0 | AK41: 9985.54 | AL41: 9985.54 | AM41: 0 | AN41: 0 | AO41: 0 | AP41: 0 | AQ41: 0 | AR41: 0 | AS41: 0 | AT41: 0 | AU41: 0 | AV41: 1 | AW41: 1 | AZ41: 1 | BA41: 1 | BB41: 1 | BC41: 7.66 | BH41: 3 | BI41: 3 | BM41: 746 | BN41: 0 | BP41: 0 | BQ41: 130 | BR41: 0 | BS41: 1 | BT41: 1 | BU41: 1 | BV41: 1 | BW41: 1 | BX41: 1 | BZ41: 0 | CA41: 0 | CE41: 1566 | CF41: 0 | CG41: 0 | CM41: 0 | CO41: 0 | CP41: =(P41+Q41+S41) -> 76489.24 | CQ41: =ROUND((ROUND((AC41*1),2)*BC41),2) -> 76489.24 | CR41: =(ROUND((ROUND(((ET41)*AV41*1),2)*BB41),2)+ROUND((ROUND(((AE41-(EU41))*AV41*1),2)*BS41),2)) -> 0 | CS41: =(ROUND((ROUND(((EU41)*AV41*1),2)*BS41),2)+ROUND((ROUND(((AE41-(EU41))*AV41*1),2)*BS41),2)) -> 0 | CT41: =ROUND((ROUND((AF41*AV41*1),2)*BA41),2) -> 0 | CU41: =AG41 -> 0 | CV41: =(AH41*AV41) -> 0 | CW41: =AI41 -> 0 | CX41: =AJ41 -> 0 | CY41: =(ROUND((((S41+ROUND((ROUND(((EU41)*AV41*1),2)*BS41),2))*AT41)/100),2)+ROUND(((ROUND((ROUND(((AE41-(EU41))*AV41*1),2)*BS41),2)*AT41)/100),2)) -> 0 | CZ41: =(ROUND((((S41+ROUND((ROUND(((EU41)*AV41*1),2)*BS41),2))*AU41)/100),2)+ROUND(((ROUND((ROUND(((AE41-(EU41))*AV41*1),2)*BS41),2)*AU41)/100),2)) -> 0 | DN41: 0 | DO41: 0 | DP41: 1 | DQ41: 1 | DU41: 1013 | DV41: ШТ | DW41: ШТ | DX41: 1 | EE41: 60088638 | EF41: 130 | EG41: Сметная стоимость оборудования | EH41: 0 | EJ41: 3 | EK41: 746 | EL41: ТСН-2001.13. Сметная стоимость оборудования | EM41: ТСН-2001.13 | EQ41: 0 | ER41: 0 | ES41: 9985.54 | ET41: 0 | EU41: 0 | EV41: 0 | EW41: 0 | EX41: 0 | EY41: 0 | EZ41: 5 | FC41: 1 | FD41: 18 | FF41: 88057 | FQ41: 0 | FR41: =P41 -> 76489.24 | FS41: 0 | FX41: 0 | FY41: 0 | GA41: [88 057 / 1,2 / 7,66] + 3% Трансп + 1,2% Заг.скл | GD41: 1 | GF41: 1190544240 | GG41: 2 | GH41: 3 | GI41: 5 | GJ41: 0 | GK41: 0 | GL41: =ROUND(IF(AND(BH41=3,BI41=3,FS41<>0),P41,0),2) -> 0 | GM41: =ROUND(O41+X41+Y41,2)+GX41 -> 76489.24 | GN41: =IF(OR(BI41=0,BI41=1),GM41-GX41,0) -> 0 | GO41: =IF(BI41=2,GM41-GX41,0) -> 0 | GP41: =IF(BI41=4,GM41-GX41,0) -> 0 | GR41: 1 | GS41: 1 | GT41: 0 | GV41: =ROUND((GT41),6) -> 0 | GW41: 1 | GX41: =ROUND(HC41*I41,2) -> 0 | HA41: 0 | HB41: 0 | HC41: =GV41*GW41 -> 0 | HE41: 3 | HF41: 1,2 | HS41: 0 | IK41: 0
A42: 17 | B42: 1 | C42: =ROW(SmtRes!A21) -> 21 | D42: =ROW(EtalonRes!A27) -> 27 | E42: 8 | F42: 4.10-80-13 | G42: Аппараты приемные, устройства промежуточные на 1 луч | H42: 1 ШТ. | I42: 1 | J42: 0 | K42: 1 | O42: =ROUND(CP42,2) -> 20.53 | P42: =ROUND((ROUND((AC42*AW42*I42),2)*BC42),2) -> 1.96 | Q42: =(ROUND((ROUND((((ET42*1.1))*AV42*I42),2)*BB42),2)+ROUND((ROUND(((AE42-((EU42*1.1)))*AV42*I42),2)*BS42),2)) -> 0.06 | R42: =(ROUND((ROUND((((EU42*1.1))*AV42*I42),2)*BS42),2)+ROUND((ROUND(((AE42-((EU42*1.1)))*AV42*I42),2)*BS42),2)) -> 0.01 | S42: =ROUND((ROUND((AF42*AV42*I42),2)*BA42),2) -> 18.51 | T42: =ROUND(CU42*I42,2) -> 0 | U42: =CV42*I42 -> 1.38204 | V42: =CW42*I42 -> 0 | W42: =ROUND(CX42*I42,2) -> 0 | X42: =(ROUND((((S42+ROUND((ROUND((((EU42*1.1))*AV42*I42),2)*BS42),2))*AT42)/100),2)+ROUND(((ROUND((ROUND(((AE42-((EU42*1.1)))*AV42*I42),2)*BS42),2)*AT42)/100),2)) -> 16.67 | Y42: =(ROUND((((S42+ROUND((ROUND((((EU42*1.1))*AV42*I42),2)*BS42),2))*AU42)/100),2)+ROUND(((ROUND((ROUND(((AE42-((EU42*1.1)))*AV42*I42),2)*BS42),2)*AU42)/100),2)) -> 8.52 | AA42: 60258621 | AB42: =ROUND((AC42+AD42+AF42),6) -> 19.692 | AC42: =ROUND(((ES42*1)),6) -> 1.96 | AD42: =ROUND(((((ET42*1.1))-((EU42*1.1)))+AE42),6) -> 0.055 | AE42: =ROUND(((EU42*1.1)),6) -> 0.011 | AF42: =ROUND(((EV42*1.1)),6) -> 17.677 | AG42: =ROUND((AP42),6) -> 0 | AH42: =((EW42*1.1)) -> 1.32 | AI42: =((EX42*1.1)) -> 0 | AJ42: =(AS42) -> 0 | AK42: 18.08 | AL42: 1.96 | AM42: 0.05 | AN42: 0.01 | AO42: 16.07 | AP42: 0 | AQ42: 1.2 | AR42: 0 | AS42: 0 | AT42: 90 | AU42: 46 | AV42: 1.047 | AW42: 1 | AZ42: 1 | BA42: 1 | BB42: 1 | BC42: 1 | BH42: 0 | BI42: 2 | BJ42: ТСН-2001.4. Доп. 1-42. Сб. 10, т. 80, поз. 13 | BM42: 68 | BN42: 58973116 | BO42: 4.10-80-13 | BP42: 1 | BQ42: 40 | BR42: 0 | BS42: 1 | BT42: 1 | BU42: 1 | BV42: 1 | BW42: 1 | BX42: 1 | BZ42: 90 | CA42: 46 | CE42: 1566 | CF42: 0 | CG42: 0 | CM42: 0 | CN42: Поправка: Гл.12.Прил.8.п.8. 5_12.00.01.11.003 Наименование: При наличии усложненных условий производства работ (стесненность, сложность складирования и транспортной логистики, наличие в зоне производства работ действующего технологического оборудования или движения технологического транспорта и т.п.) для объектов, расположенных за пределами территории круговой магистральной системы улиц "Садовое кольцо" и за пределами Третьего транспортного кольца города Москвы пунктов "а" и "б", но в пределах Московской кольцевой автомобильной дороги | CO42: 0 | CP42: =(P42+Q42+S42) -> 20.53 | CQ42: =ROUND((ROUND((AC42*AW42*1),2)*BC42),2) -> 1.96 | CR42: =(ROUND((ROUND((((ET42*1.1))*AV42*1),2)*BB42),2)+ROUND((ROUND(((AE42-((EU42*1.1)))*AV42*1),2)*BS42),2)) -> 0.06 | CS42: =(ROUND((ROUND((((EU42*1.1))*AV42*1),2)*BS42),2)+ROUND((ROUND(((AE42-((EU42*1.1)))*AV42*1),2)*BS42),2)) -> 0.01 | CT42: =ROUND((ROUND((AF42*AV42*1),2)*BA42),2) -> 18.51 | CU42: =AG42 -> 0 | CV42: =(AH42*AV42) -> 1.38204 | CW42: =AI42 -> 0 | CX42: =AJ42 -> 0 | CY42: =(ROUND((((S42+ROUND((ROUND((((EU42*1.1))*AV42*1),2)*BS42),2))*AT42)/100),2)+ROUND(((ROUND((ROUND(((AE42-((EU42*1.1)))*AV42*1),2)*BS42),2)*AT42)/100),2)) -> 16.67 | CZ42: =(ROUND((((S42+ROUND((ROUND((((EU42*1.1))*AV42*1),2)*BS42),2))*AU42)/100),2)+ROUND(((ROUND((ROUND(((AE42-((EU42*1.1)))*AV42*1),2)*BS42),2)*AU42)/100),2)) -> 8.52 | DB42: 7 | DD42: *1 | DE42: *1,1 | DF42: *1,1 | DG42: *1,1 | DI42: *1,1 | DJ42: *1,1 | DN42: 0 | DO42: 0 | DP42: 1 | DQ42: 1 | DU42: 1013 | DV42: 1 ШТ. | DW42: 1 ШТ. | DX42: 1 | EE42: 60088532 | EF42: 40 | EG42: Монтаж оборудования | EH42: 0 | EJ42: 2 | EK42: 68 | EL42: ТСН-2001.4-10. Прокладка и монтаж сетей связи | EM42: ТСН-2001.4-10-1 | EO42: Поправка: Гл.12.Прил.8.п.8. 5_12.00.01.11.003 | EQ42: 0 | ER42: 18.08 | ES42: 1.96 | ET42: 0.05 | EU42: 0.01 | EV42: 16.07 | EW42: 1.2 | EX42: 0 | EY42: 0 | FQ42: 0 | FR42: 0 | FS42: 0 | FX42: 90 | FY42: 46 | GD42: 1 | GF42: 1665592289 | GG42: 2 | GH42: 1 | GI42: 2 | GJ42: 0 | GK42: 0 | GL42: =ROUND(IF(AND(BH42=3,BI42=3,FS42<>0),P42,0),2) -> 0 | GM42: =ROUND(O42+X42+Y42,2)+GX42 -> 45.72 | GN42: =IF(OR(BI42=0,BI42=1),GM42-GX42,0) -> 0 | GO42: =IF(BI42=2,GM42-GX42,0) -> 45.72 | GP42: =IF(BI42=4,GM42-GX42,0) -> 0 | GR42: 0 | GS42: 3 | GT42: 0 | GV42: =ROUND((GT42),6) -> 0 | GW42: 1 | GX42: =ROUND(HC42*I42,2) -> 0 | HA42: 0 | HB42: 0 | HC42: =GV42*GW42 -> 0 | HS42: 0 | IK42: 0
A43: 17 | B43: 1 | C43: =ROW(SmtRes!A22) -> 22 | D43: =ROW(EtalonRes!A28) -> 28 | E43: 8 | F43: 4.10-80-13 | G43: Аппараты приемные, устройства промежуточные на 1 луч | H43: 1 ШТ. | I43: 1 | J43: 0 | K43: 1 | O43: =ROUND(CP43,2) -> 1038.38 | P43: =ROUND((ROUND((AC43*AW43*I43),2)*BC43),2) -> 19.38 | Q43: =(ROUND((ROUND((((ET43*1.1))*AV43*I43),2)*BB43),2)+ROUND((ROUND(((AE43-((EU43*1.1)))*AV43*I43),2)*BS43),2)) -> 1.14 | R43: =(ROUND((ROUND((((EU43*1.1))*AV43*I43),2)*BS43),2)+ROUND((ROUND(((AE43-((EU43*1.1)))*AV43*I43),2)*BS43),2)) -> 0.55 | S43: =ROUND((ROUND((AF43*AV43*I43),2)*BA43),2) -> 1017.86 | T43: =ROUND(CU43*I43,2) -> 0 | U43: =CV43*I43 -> 1.38204 | V43: =CW43*I43 -> 0 | W43: =ROUND(CX43*I43,2) -> 0 | X43: =(ROUND((((S43+ROUND((ROUND((((EU43*1.1))*AV43*I43),2)*BS43),2))*AT43)/100),2)+ROUND(((ROUND((ROUND(((AE43-((EU43*1.1)))*AV43*I43),2)*BS43),2)*AT43)/100),2)) -> 916.57 | Y43: =(ROUND((((S43+ROUND((ROUND((((EU43*1.1))*AV43*I43),2)*BS43),2))*AU43)/100),2)+ROUND(((ROUND((ROUND(((AE43-((EU43*1.1)))*AV43*I43),2)*BS43),2)*AU43)/100),2)) -> 468.47 | AA43: 60258618 | AB43: =ROUND((AC43+AD43+AF43),6) -> 19.692 | AC43: =ROUND(((ES43*1)),6) -> 1.96 | AD43: =ROUND(((((ET43*1.1))-((EU43*1.1)))+AE43),6) -> 0.055 | AE43: =ROUND(((EU43*1.1)),6) -> 0.011 | AF43: =ROUND(((EV43*1.1)),6) -> 17.677 | AG43: =ROUND((AP43),6) -> 0 | AH43: =((EW43*1.1)) -> 1.32 | AI43: =((EX43*1.1)) -> 0 | AJ43: =(AS43) -> 0 | AK43: 18.08 | AL43: 1.96 | AM43: 0.05 | AN43: 0.01 | AO43: 16.07 | AP43: 0 | AQ43: 1.2 | AR43: 0 | AS43: 0 | AT43: 90 | AU43: 46 | AV43: 1.047 | AW43: 1 | AZ43: 1 | BA43: 54.99 | BB43: 19 | BC43: 9.89 | BH43: 0 | BI43: 2 | BJ43: ТСН-2001.4. Доп. 1-42. Сб. 10, т. 80, поз. 13 | BM43: 68 | BN43: 58973116 | BO43: 4.10-80-13 | BP43: 1 | BQ43: 40 | BR43: 0 | BS43: 54.99 | BT43: 1 | BU43: 1 | BV43: 1 | BW43: 1 | BX43: 1 | BZ43: 90 | CA43: 46 | CE43: 1566 | CF43: 0 | CG43: 0 | CM43: 0 | CN43: Поправка: Гл.12.Прил.8.п.8. 5_12.00.01.11.003 Наименование: При наличии усложненных условий производства работ (стесненность, сложность складирования и транспортной логистики, наличие в зоне производства работ действующего технологического оборудования или движения технологического транспорта и т.п.) для объектов, расположенных за пределами территории круговой магистральной системы улиц "Садовое кольцо" и за пределами Третьего транспортного кольца города Москвы пунктов "а" и "б", но в пределах Московской кольцевой автомобильной дороги | CO43: 0 | CP43: =(P43+Q43+S43) -> 1038.38 | CQ43: =ROUND((ROUND((AC43*AW43*1),2)*BC43),2) -> 19.38 | CR43: =(ROUND((ROUND((((ET43*1.1))*AV43*1),2)*BB43),2)+ROUND((ROUND(((AE43-((EU43*1.1)))*AV43*1),2)*BS43),2)) -> 1.14 | CS43: =(ROUND((ROUND((((EU43*1.1))*AV43*1),2)*BS43),2)+ROUND((ROUND(((AE43-((EU43*1.1)))*AV43*1),2)*BS43),2)) -> 0.55 | CT43: =ROUND((ROUND((AF43*AV43*1),2)*BA43),2) -> 1017.86 | CU43: =AG43 -> 0 | CV43: =(AH43*AV43) -> 1.38204 | CW43: =AI43 -> 0 | CX43: =AJ43 -> 0 | CY43: =(ROUND((((S43+ROUND((ROUND((((EU43*1.1))*AV43*1),2)*BS43),2))*AT43)/100),2)+ROUND(((ROUND((ROUND(((AE43-((EU43*1.1)))*AV43*1),2)*BS43),2)*AT43)/100),2)) -> 916.57 | CZ43: =(ROUND((((S43+ROUND((ROUND((((EU43*1.1))*AV43*1),2)*BS43),2))*AU43)/100),2)+ROUND(((ROUND((ROUND(((AE43-((EU43*1.1)))*AV43*1),2)*BS43),2)*AU43)/100),2)) -> 468.47 | DB43: 8 | DD43: *1 | DE43: *1,1 | DF43: *1,1 | DG43: *1,1 | DI43: *1,1 | DJ43: *1,1 | DN43: 0 | DO43: 0 | DP43: 1 | DQ43: 1 | DU43: 1013 | DV43: 1 ШТ. | DW43: 1 ШТ. | DX43: 1 | EE43: 60088532 | EF43: 40 | EG43: Монтаж оборудования | EH43: 0 | EJ43: 2 | EK43: 68 | EL43: ТСН-2001.4-10. Прокладка и монтаж сетей связи | EM43: ТСН-2001.4-10-1 | EO43: Поправка: Гл.12.Прил.8.п.8. 5_12.00.01.11.003 | EQ43: 0 | ER43: 18.08 | ES43: 1.96 | ET43: 0.05 | EU43: 0.01 | EV43: 16.07 | EW43: 1.2 | EX43: 0 | EY43: 0 | FQ43: 0 | FR43: 0 | FS43: 0 | FX43: 90 | FY43: 46 | GD43: 1 | GF43: 1665592289 | GG43: 2 | GH43: 1 | GI43: 2 | GJ43: 0 | GK43: 0 | GL43: =ROUND(IF(AND(BH43=3,BI43=3,FS43<>0),P43,0),2) -> 0 | GM43: =ROUND(O43+X43+Y43,2)+GX43 -> 2423.42 | GN43: =IF(OR(BI43=0,BI43=1),GM43-GX43,0) -> 0 | GO43: =IF(BI43=2,GM43-GX43,0) -> 2423.42 | GP43: =IF(BI43=4,GM43-GX43,0) -> 0 | GR43: 0 | GS43: 3 | GT43: 0 | GV43: =ROUND((GT43),6) -> 0 | GW43: 1 | GX43: =ROUND(HC43*I43,2) -> 0 | HA43: 0 | HB43: 0 | HC43: =GV43*GW43 -> 0 | HS43: 0 | IK43: 0
A44: 17 | B44: 1 | E44: 9 | F44: КА-5 | G44: Модуль сопряжения МС-Е | H44: ШТ | I44: 1 | J44: 0 | K44: 1 | O44: =ROUND(CP44,2) -> 997.8 | P44: =ROUND((ROUND((AC44*I44),2)*BC44),2) -> 997.8 | Q44: =(ROUND((ROUND(((ET44)*AV44*I44),2)*BB44),2)+ROUND((ROUND(((AE44-(EU44))*AV44*I44),2)*BS44),2)) -> 0 | R44: =(ROUND((ROUND(((EU44)*AV44*I44),2)*BS44),2)+ROUND((ROUND(((AE44-(EU44))*AV44*I44),2)*BS44),2)) -> 0 | S44: =ROUND((ROUND((AF44*AV44*I44),2)*BA44),2) -> 0 | T44: =ROUND(CU44*I44,2) -> 0 | U44: =CV44*I44 -> 0 | V44: =CW44*I44 -> 0 | W44: =ROUND(CX44*I44,2) -> 0 | X44: =(ROUND((((S44+ROUND((ROUND(((EU44)*AV44*I44),2)*BS44),2))*AT44)/100),2)+ROUND(((ROUND((ROUND(((AE44-(EU44))*AV44*I44),2)*BS44),2)*AT44)/100),2)) -> 0 | Y44: =(ROUND((((S44+ROUND((ROUND(((EU44)*AV44*I44),2)*BS44),2))*AU44)/100),2)+ROUND(((ROUND((ROUND(((AE44-(EU44))*AV44*I44),2)*BS44),2)*AU44)/100),2)) -> 0 | AA44: 60258621 | AB44: =ROUND((AC44+AD44+AF44),6) -> 997.8 | AC44: =ROUND((ES44),6) -> 997.8 | AD44: =ROUND((((ET44)-(EU44))+AE44),6) -> 0 | AE44: =ROUND((EU44),6) -> 0 | AF44: =ROUND((EV44),6) -> 0 | AG44: =ROUND((AP44),6) -> 0 | AH44: =(EW44) -> 0 | AI44: =(EX44) -> 0 | AJ44: =(AS44) -> 0 | AK44: 997.8 | AL44: 997.8 | AM44: 0 | AN44: 0 | AO44: 0 | AP44: 0 | AQ44: 0 | AR44: 0 | AS44: 0 | AT44: 0 | AU44: 0 | AV44: 1 | AW44: 1 | AZ44: 1 | BA44: 1 | BB44: 1 | BC44: 1 | BH44: 3 | BI44: 3 | BM44: 746 | BN44: 0 | BP44: 0 | BQ44: 130 | BR44: 0 | BS44: 1 | BT44: 1 | BU44: 1 | BV44: 1 | BW44: 1 | BX44: 1 | BZ44: 0 | CA44: 0 | CE44: 1566 | CF44: 0 | CG44: 0 | CM44: 0 | CO44: 0 | CP44: =(P44+Q44+S44) -> 997.8 | CQ44: =ROUND((ROUND((AC44*1),2)*BC44),2) -> 997.8 | CR44: =(ROUND((ROUND(((ET44)*AV44*1),2)*BB44),2)+ROUND((ROUND(((AE44-(EU44))*AV44*1),2)*BS44),2)) -> 0 | CS44: =(ROUND((ROUND(((EU44)*AV44*1),2)*BS44),2)+ROUND((ROUND(((AE44-(EU44))*AV44*1),2)*BS44),2)) -> 0 | CT44: =ROUND((ROUND((AF44*AV44*1),2)*BA44),2) -> 0 | CU44: =AG44 -> 0 | CV44: =(AH44*AV44) -> 0 | CW44: =AI44 -> 0 | CX44: =AJ44 -> 0 | CY44: =(ROUND((((S44+ROUND((ROUND(((EU44)*AV44*1),2)*BS44),2))*AT44)/100),2)+ROUND(((ROUND((ROUND(((AE44-(EU44))*AV44*1),2)*BS44),2)*AT44)/100),2)) -> 0 | CZ44: =(ROUND((((S44+ROUND((ROUND(((EU44)*AV44*1),2)*BS44),2))*AU44)/100),2)+ROUND(((ROUND((ROUND(((AE44-(EU44))*AV44*1),2)*BS44),2)*AU44)/100),2)) -> 0 | DN44: 0 | DO44: 0 | DP44: 1 | DQ44: 1 | DU44: 1013 | DV44: ШТ | DW44: ШТ | DX44: 1 | EE44: 60088638 | EF44: 130 | EG44: Сметная стоимость оборудования | EH44: 0 | EJ44: 3 | EK44: 746 | EL44: ТСН-2001.13. Сметная стоимость оборудования | EM44: ТСН-2001.13 | EQ44: 0 | ER44: 0 | ES44: 997.8 | ET44: 0 | EU44: 0 | EV44: 0 | EW44: 0 | EX44: 0 | EY44: 0 | FQ44: 0 | FR44: =P44 -> 997.8 | FS44: 0 | FX44: 0 | FY44: 0 | GA44: [8 799 / 1,2 / 7,66] + 3% Трансп + 1,2% Заг.скл | GD44: 1 | GF44: -1747575220 | GG44: 2 | GH44: 4 | GI44: -2 | GJ44: 0 | GK44: 0 | GL44: =ROUND(IF(AND(BH44=3,BI44=3,FS44<>0),P44,0),2) -> 0 | GM44: =ROUND(O44+X44+Y44,2)+GX44 -> 997.8 | GN44: =IF(OR(BI44=0,BI44=1),GM44-GX44,0) -> 0 | GO44: =IF(BI44=2,GM44-GX44,0) -> 0 | GP44: =IF(BI44=4,GM44-GX44,0) -> 0 | GR44: 0 | GS44: 2 | GT44: 0 | GV44: =ROUND((GT44),6) -> 0 | GW44: 1 | GX44: =ROUND(HC44*I44,2) -> 0 | HA44: 0 | HB44: 0 | HC44: =GV44*GW44 -> 0 | HE44: 3 | HF44: 1,2 | HS44: 0 | IK44: 0
A45: 17 | B45: 1 | E45: 9 | F45: КА-5 | G45: Модуль сопряжения МС-Е | H45: ШТ | I45: 1 | J45: 0 | K45: 1 | O45: =ROUND(CP45,2) -> 7643.15 | P45: =ROUND((ROUND((AC45*I45),2)*BC45),2) -> 7643.15 | Q45: =(ROUND((ROUND(((ET45)*AV45*I45),2)*BB45),2)+ROUND((ROUND(((AE45-(EU45))*AV45*I45),2)*BS45),2)) -> 0 | R45: =(ROUND((ROUND(((EU45)*AV45*I45),2)*BS45),2)+ROUND((ROUND(((AE45-(EU45))*AV45*I45),2)*BS45),2)) -> 0 | S45: =ROUND((ROUND((AF45*AV45*I45),2)*BA45),2) -> 0 | T45: =ROUND(CU45*I45,2) -> 0 | U45: =CV45*I45 -> 0 | V45: =CW45*I45 -> 0 | W45: =ROUND(CX45*I45,2) -> 0 | X45: =(ROUND((((S45+ROUND((ROUND(((EU45)*AV45*I45),2)*BS45),2))*AT45)/100),2)+ROUND(((ROUND((ROUND(((AE45-(EU45))*AV45*I45),2)*BS45),2)*AT45)/100),2)) -> 0 | Y45: =(ROUND((((S45+ROUND((ROUND(((EU45)*AV45*I45),2)*BS45),2))*AU45)/100),2)+ROUND(((ROUND((ROUND(((AE45-(EU45))*AV45*I45),2)*BS45),2)*AU45)/100),2)) -> 0 | AA45: 60258618 | AB45: =ROUND((AC45+AD45+AF45),6) -> 997.8 | AC45: =ROUND((ES45),6) -> 997.8 | AD45: =ROUND((((ET45)-(EU45))+AE45),6) -> 0 | AE45: =ROUND((EU45),6) -> 0 | AF45: =ROUND((EV45),6) -> 0 | AG45: =ROUND((AP45),6) -> 0 | AH45: =(EW45) -> 0 | AI45: =(EX45) -> 0 | AJ45: =(AS45) -> 0 | AK45: 997.8 | AL45: 997.8 | AM45: 0 | AN45: 0 | AO45: 0 | AP45: 0 | AQ45: 0 | AR45: 0 | AS45: 0 | AT45: 0 | AU45: 0 | AV45: 1 | AW45: 1 | AZ45: 1 | BA45: 1 | BB45: 1 | BC45: 7.66 | BH45: 3 | BI45: 3 | BM45: 746 | BN45: 0 | BP45: 0 | BQ45: 130 | BR45: 0 | BS45: 1 | BT45: 1 | BU45: 1 | BV45: 1 | BW45: 1 | BX45: 1 | BZ45: 0 | CA45: 0 | CE45: 1566 | CF45: 0 | CG45: 0 | CM45: 0 | CO45: 0 | CP45: =(P45+Q45+S45) -> 7643.15 | CQ45: =ROUND((ROUND((AC45*1),2)*BC45),2) -> 7643.15 | CR45: =(ROUND((ROUND(((ET45)*AV45*1),2)*BB45),2)+ROUND((ROUND(((AE45-(EU45))*AV45*1),2)*BS45),2)) -> 0 | CS45: =(ROUND((ROUND(((EU45)*AV45*1),2)*BS45),2)+ROUND((ROUND(((AE45-(EU45))*AV45*1),2)*BS45),2)) -> 0 | CT45: =ROUND((ROUND((AF45*AV45*1),2)*BA45),2) -> 0 | CU45: =AG45 -> 0 | CV45: =(AH45*AV45) -> 0 | CW45: =AI45 -> 0 | CX45: =AJ45 -> 0 | CY45: =(ROUND((((S45+ROUND((ROUND(((EU45)*AV45*1),2)*BS45),2))*AT45)/100),2)+ROUND(((ROUND((ROUND(((AE45-(EU45))*AV45*1),2)*BS45),2)*AT45)/100),2)) -> 0 | CZ45: =(ROUND((((S45+ROUND((ROUND(((EU45)*AV45*1),2)*BS45),2))*AU45)/100),2)+ROUND(((ROUND((ROUND(((AE45-(EU45))*AV45*1),2)*BS45),2)*AU45)/100),2)) -> 0 | DN45: 0 | DO45: 0 | DP45: 1 | DQ45: 1 | DU45: 1013 | DV45: ШТ | DW45: ШТ | DX45: 1 | EE45: 60088638 | EF45: 130 | EG45: Сметная стоимость оборудования | EH45: 0 | EJ45: 3 | EK45: 746 | EL45: ТСН-2001.13. Сметная стоимость оборудования | EM45: ТСН-2001.13 | EQ45: 0 | ER45: 0 | ES45: 997.8 | ET45: 0 | EU45: 0 | EV45: 0 | EW45: 0 | EX45: 0 | EY45: 0 | EZ45: 5 | FC45: 1 | FD45: 18 | FF45: 8799 | FQ45: 0 | FR45: =P45 -> 7643.15 | FS45: 0 | FX45: 0 | FY45: 0 | GA45: [8 799 / 1,2 / 7,66] + 3% Трансп + 1,2% Заг.скл | GD45: 1 | GF45: -1747575220 | GG45: 2 | GH45: 3 | GI45: 5 | GJ45: 0 | GK45: 0 | GL45: =ROUND(IF(AND(BH45=3,BI45=3,FS45<>0),P45,0),2) -> 0 | GM45: =ROUND(O45+X45+Y45,2)+GX45 -> 7643.15 | GN45: =IF(OR(BI45=0,BI45=1),GM45-GX45,0) -> 0 | GO45: =IF(BI45=2,GM45-GX45,0) -> 0 | GP45: =IF(BI45=4,GM45-GX45,0) -> 0 | GR45: 1 | GS45: 1 | GT45: 0 | GV45: =ROUND((GT45),6) -> 0 | GW45: 1 | GX45: =ROUND(HC45*I45,2) -> 0 | HA45: 0 | HB45: 0 | HC45: =GV45*GW45 -> 0 | HE45: 3 | HF45: 1,2 | HS45: 0 | IK45: 0
A46: 17 | B46: 1 | C46: =ROW(SmtRes!A23) -> 23 | D46: =ROW(EtalonRes!A29) -> 29 | E46: 10 | F46: 4.10-80-9 | G46: Аппараты приемные, приборы приемно-контрольные объектовые на 2 луча | H46: 1 ШТ. | I46: 1 | J46: 0 | K46: 1 | O46: =ROUND(CP46,2) -> 93.97 | P46: =ROUND((ROUND((AC46*AW46*I46),2)*BC46),2) -> 4.83 | Q46: =(ROUND((ROUND((((ET46*1.1))*AV46*I46),2)*BB46),2)+ROUND((ROUND(((AE46-((EU46*1.1)))*AV46*I46),2)*BS46),2)) -> 0.06 | R46: =(ROUND((ROUND((((EU46*1.1))*AV46*I46),2)*BS46),2)+ROUND((ROUND(((AE46-((EU46*1.1)))*AV46*I46),2)*BS46),2)) -> 0.01 | S46: =ROUND((ROUND((AF46*AV46*I46),2)*BA46),2) -> 89.08 | T46: =ROUND(CU46*I46,2) -> 0 | U46: =CV46*I46 -> 6.56469 | V46: =CW46*I46 -> 0 | W46: =ROUND(CX46*I46,2) -> 0 | X46: =(ROUND((((S46+ROUND((ROUND((((EU46*1.1))*AV46*I46),2)*BS46),2))*AT46)/100),2)+ROUND(((ROUND((ROUND(((AE46-((EU46*1.1)))*AV46*I46),2)*BS46),2)*AT46)/100),2)) -> 80.18 | Y46: =(ROUND((((S46+ROUND((ROUND((((EU46*1.1))*AV46*I46),2)*BS46),2))*AU46)/100),2)+ROUND(((ROUND((ROUND(((AE46-((EU46*1.1)))*AV46*I46),2)*BS46),2)*AU46)/100),2)) -> 40.98 | AA46: 60258621 | AB46: =ROUND((AC46+AD46+AF46),6) -> 89.97 | AC46: =ROUND(((ES46*1)),6) -> 4.83 | AD46: =ROUND(((((ET46*1.1))-((EU46*1.1)))+AE46),6) -> 0.055 | AE46: =ROUND(((EU46*1.1)),6) -> 0.011 | AF46: =ROUND(((EV46*1.1)),6) -> 85.085 | AG46: =ROUND((AP46),6) -> 0 | AH46: =((EW46*1.1)) -> 6.27 | AI46: =((EX46*1.1)) -> 0 | AJ46: =(AS46) -> 0 | AK46: 82.23 | AL46: 4.83 | AM46: 0.05 | AN46: 0.01 | AO46: 77.35 | AP46: 0 | AQ46: 5.7 | AR46: 0 | AS46: 0 | AT46: 90 | AU46: 46 | AV46: 1.047 | AW46: 1 | AZ46: 1 | BA46: 1 | BB46: 1 | BC46: 1 | BH46: 0 | BI46: 2 | BJ46: ТСН-2001.4. Доп. 1-42. Сб. 10, т. 80, поз. 9 | BM46: 68 | BN46: 58973116 | BO46: 4.10-80-9 | BP46: 1 | BQ46: 40 | BR46: 0 | BS46: 1 | BT46: 1 | BU46: 1 | BV46: 1 | BW46: 1 | BX46: 1 | BZ46: 90 | CA46: 46 | CE46: 1566 | CF46: 0 | CG46: 0 | CM46: 0 | CN46: Поправка: Гл.12.Прил.8.п.8. 5_12.00.01.11.003 Наименование: При наличии усложненных условий производства работ (стесненность, сложность складирования и транспортной логистики, наличие в зоне производства работ действующего технологического оборудования или движения технологического транспорта и т.п.) для объектов, расположенных за пределами территории круговой магистральной системы улиц "Садовое кольцо" и за пределами Третьего транспортного кольца города Москвы пунктов "а" и "б", но в пределах Московской кольцевой автомобильной дороги | CO46: 0 | CP46: =(P46+Q46+S46) -> 93.97 | CQ46: =ROUND((ROUND((AC46*AW46*1),2)*BC46),2) -> 4.83 | CR46: =(ROUND((ROUND((((ET46*1.1))*AV46*1),2)*BB46),2)+ROUND((ROUND(((AE46-((EU46*1.1)))*AV46*1),2)*BS46),2)) -> 0.06 | CS46: =(ROUND((ROUND((((EU46*1.1))*AV46*1),2)*BS46),2)+ROUND((ROUND(((AE46-((EU46*1.1)))*AV46*1),2)*BS46),2)) -> 0.01 | CT46: =ROUND((ROUND((AF46*AV46*1),2)*BA46),2) -> 89.08 | CU46: =AG46 -> 0 | CV46: =(AH46*AV46) -> 6.56469 | CW46: =AI46 -> 0 | CX46: =AJ46 -> 0 | CY46: =(ROUND((((S46+ROUND((ROUND((((EU46*1.1))*AV46*1),2)*BS46),2))*AT46)/100),2)+ROUND(((ROUND((ROUND(((AE46-((EU46*1.1)))*AV46*1),2)*BS46),2)*AT46)/100),2)) -> 80.18 | CZ46: =(ROUND((((S46+ROUND((ROUND((((EU46*1.1))*AV46*1),2)*BS46),2))*AU46)/100),2)+ROUND(((ROUND((ROUND(((AE46-((EU46*1.1)))*AV46*1),2)*BS46),2)*AU46)/100),2)) -> 40.98 | DB46: 9 | DD46: *1 | DE46: *1,1 | DF46: *1,1 | DG46: *1,1 | DI46: *1,1 | DJ46: *1,1 | DN46: 0 | DO46: 0 | DP46: 1 | DQ46: 1 | DU46: 1013 | DV46: 1 ШТ. | DW46: 1 ШТ. | DX46: 1 | EE46: 60088532 | EF46: 40 | EG46: Монтаж оборудования | EH46: 0 | EJ46: 2 | EK46: 68 | EL46: ТСН-2001.4-10. Прокладка и монтаж сетей связи | EM46: ТСН-2001.4-10-1 | EO46: Поправка: Гл.12.Прил.8.п.8. 5_12.00.01.11.003 | EQ46: 0 | ER46: 82.23 | ES46: 4.83 | ET46: 0.05 | EU46: 0.01 | EV46: 77.35 | EW46: 5.7 | EX46: 0 | EY46: 0 | FQ46: 0 | FR46: 0 | FS46: 0 | FX46: 90 | FY46: 46 | GD46: 1 | GF46: 1762388533 | GG46: 2 | GH46: 1 | GI46: 2 | GJ46: 0 | GK46: 0 | GL46: =ROUND(IF(AND(BH46=3,BI46=3,FS46<>0),P46,0),2) -> 0 | GM46: =ROUND(O46+X46+Y46,2)+GX46 -> 215.13 | GN46: =IF(OR(BI46=0,BI46=1),GM46-GX46,0) -> 0 | GO46: =IF(BI46=2,GM46-GX46,0) -> 215.13 | GP46: =IF(BI46=4,GM46-GX46,0) -> 0 | GR46: 0 | GS46: 3 | GT46: 0 | GV46: =ROUND((GT46),6) -> 0 | GW46: 1 | GX46: =ROUND(HC46*I46,2) -> 0 | HA46: 0 | HB46: 0 | HC46: =GV46*GW46 -> 0 | HS46: 0 | IK46: 0
A47: 17 | B47: 1 | C47: =ROW(SmtRes!A24) -> 24 | D47: =ROW(EtalonRes!A30) -> 30 | E47: 10 | F47: 4.10-80-9 | G47: Аппараты приемные, приборы приемно-контрольные объектовые на 2 луча | H47: 1 ШТ. | I47: 1 | J47: 0 | K47: 1 | O47: =ROUND(CP47,2) -> 4947.42 | P47: =ROUND((ROUND((AC47*AW47*I47),2)*BC47),2) -> 47.77 | Q47: =(ROUND((ROUND((((ET47*1.1))*AV47*I47),2)*BB47),2)+ROUND((ROUND(((AE47-((EU47*1.1)))*AV47*I47),2)*BS47),2)) -> 1.14 | R47: =(ROUND((ROUND((((EU47*1.1))*AV47*I47),2)*BS47),2)+ROUND((ROUND(((AE47-((EU47*1.1)))*AV47*I47),2)*BS47),2)) -> 0.55 | S47: =ROUND((ROUND((AF47*AV47*I47),2)*BA47),2) -> 4898.51 | T47: =ROUND(CU47*I47,2) -> 0 | U47: =CV47*I47 -> 6.56469 | V47: =CW47*I47 -> 0 | W47: =ROUND(CX47*I47,2) -> 0 | X47: =(ROUND((((S47+ROUND((ROUND((((EU47*1.1))*AV47*I47),2)*BS47),2))*AT47)/100),2)+ROUND(((ROUND((ROUND(((AE47-((EU47*1.1)))*AV47*I47),2)*BS47),2)*AT47)/100),2)) -> 4409.15 | Y47: =(ROUND((((S47+ROUND((ROUND((((EU47*1.1))*AV47*I47),2)*BS47),2))*AU47)/100),2)+ROUND(((ROUND((ROUND(((AE47-((EU47*1.1)))*AV47*I47),2)*BS47),2)*AU47)/100),2)) -> 2253.57 | AA47: 60258618 | AB47: =ROUND((AC47+AD47+AF47),6) -> 89.97 | AC47: =ROUND(((ES47*1)),6) -> 4.83 | AD47: =ROUND(((((ET47*1.1))-((EU47*1.1)))+AE47),6) -> 0.055 | AE47: =ROUND(((EU47*1.1)),6) -> 0.011 | AF47: =ROUND(((EV47*1.1)),6) -> 85.085 | AG47: =ROUND((AP47),6) -> 0 | AH47: =((EW47*1.1)) -> 6.27 | AI47: =((EX47*1.1)) -> 0 | AJ47: =(AS47) -> 0 | AK47: 82.23 | AL47: 4.83 | AM47: 0.05 | AN47: 0.01 | AO47: 77.35 | AP47: 0 | AQ47: 5.7 | AR47: 0 | AS47: 0 | AT47: 90 | AU47: 46 | AV47: 1.047 | AW47: 1 | AZ47: 1 | BA47: 54.99 | BB47: 19 | BC47: 9.89 | BH47: 0 | BI47: 2 | BJ47: ТСН-2001.4. Доп. 1-42. Сб. 10, т. 80, поз. 9 | BM47: 68 | BN47: 58973116 | BO47: 4.10-80-9 | BP47: 1 | BQ47: 40 | BR47: 0 | BS47: 54.99 | BT47: 1 | BU47: 1 | BV47: 1 | BW47: 1 | BX47: 1 | BZ47: 90 | CA47: 46 | CE47: 1566 | CF47: 0 | CG47: 0 | CM47: 0 | CN47: Поправка: Гл.12.Прил.8.п.8. 5_12.00.01.11.003 Наименование: При наличии усложненных условий производства работ (стесненность, сложность складирования и транспортной логистики, наличие в зоне производства работ действующего технологического оборудования или движения технологического транспорта и т.п.) для объектов, расположенных за пределами территории круговой магистральной системы улиц "Садовое кольцо" и за пределами Третьего транспортного кольца города Москвы пунктов "а" и "б", но в пределах Московской кольцевой автомобильной дороги | CO47: 0 | CP47: =(P47+Q47+S47) -> 4947.42 | CQ47: =ROUND((ROUND((AC47*AW47*1),2)*BC47),2) -> 47.77 | CR47: =(ROUND((ROUND((((ET47*1.1))*AV47*1),2)*BB47),2)+ROUND((ROUND(((AE47-((EU47*1.1)))*AV47*1),2)*BS47),2)) -> 1.14 | CS47: =(ROUND((ROUND((((EU47*1.1))*AV47*1),2)*BS47),2)+ROUND((ROUND(((AE47-((EU47*1.1)))*AV47*1),2)*BS47),2)) -> 0.55 | CT47: =ROUND((ROUND((AF47*AV47*1),2)*BA47),2) -> 4898.51 | CU47: =AG47 -> 0 | CV47: =(AH47*AV47) -> 6.56469 | CW47: =AI47 -> 0 | CX47: =AJ47 -> 0 | CY47: =(ROUND((((S47+ROUND((ROUND((((EU47*1.1))*AV47*1),2)*BS47),2))*AT47)/100),2)+ROUND(((ROUND((ROUND(((AE47-((EU47*1.1)))*AV47*1),2)*BS47),2)*AT47)/100),2)) -> 4409.15 | CZ47: =(ROUND((((S47+ROUND((ROUND((((EU47*1.1))*AV47*1),2)*BS47),2))*AU47)/100),2)+ROUND(((ROUND((ROUND(((AE47-((EU47*1.1)))*AV47*1),2)*BS47),2)*AU47)/100),2)) -> 2253.57 | DB47: 10 | DD47: *1 | DE47: *1,1 | DF47: *1,1 | DG47: *1,1 | DI47: *1,1 | DJ47: *1,1 | DN47: 0 | DO47: 0 | DP47: 1 | DQ47: 1 | DU47: 1013 | DV47: 1 ШТ. | DW47: 1 ШТ. | DX47: 1 | EE47: 60088532 | EF47: 40 | EG47: Монтаж оборудования | EH47: 0 | EJ47: 2 | EK47: 68 | EL47: ТСН-2001.4-10. Прокладка и монтаж сетей связи | EM47: ТСН-2001.4-10-1 | EO47: Поправка: Гл.12.Прил.8.п.8. 5_12.00.01.11.003 | EQ47: 0 | ER47: 82.23 | ES47: 4.83 | ET47: 0.05 | EU47: 0.01 | EV47: 77.35 | EW47: 5.7 | EX47: 0 | EY47: 0 | FQ47: 0 | FR47: 0 | FS47: 0 | FX47: 90 | FY47: 46 | GD47: 1 | GF47: 1762388533 | GG47: 2 | GH47: 1 | GI47: 2 | GJ47: 0 | GK47: 0 | GL47: =ROUND(IF(AND(BH47=3,BI47=3,FS47<>0),P47,0),2) -> 0 | GM47: =ROUND(O47+X47+Y47,2)+GX47 -> 11610.14 | GN47: =IF(OR(BI47=0,BI47=1),GM47-GX47,0) -> 0 | GO47: =IF(BI47=2,GM47-GX47,0) -> 11610.14 | GP47: =IF(BI47=4,GM47-GX47,0) -> 0 | GR47: 0 | GS47: 3 | GT47: 0 | GV47: =ROUND((GT47),6) -> 0 | GW47: 1 | GX47: =ROUND(HC47*I47,2) -> 0 | HA47: 0 | HB47: 0 | HC47: =GV47*GW47 -> 0 | HS47: 0 | IK47: 0
A48: 17 | B48: 1 | E48: 11 | F48: КА-6 | G48: Блок индикации и управления Рубеж-БИУ | H48: ШТ | I48: 1 | J48: 0 | K48: 1 | O48: =ROUND(CP48,2) -> 2396.35 | P48: =ROUND((ROUND((AC48*I48),2)*BC48),2) -> 2396.35 | Q48: =(ROUND((ROUND(((ET48)*AV48*I48),2)*BB48),2)+ROUND((ROUND(((AE48-(EU48))*AV48*I48),2)*BS48),2)) -> 0 | R48: =(ROUND((ROUND(((EU48)*AV48*I48),2)*BS48),2)+ROUND((ROUND(((AE48-(EU48))*AV48*I48),2)*BS48),2)) -> 0 | S48: =ROUND((ROUND((AF48*AV48*I48),2)*BA48),2) -> 0 | T48: =ROUND(CU48*I48,2) -> 0 | U48: =CV48*I48 -> 0 | V48: =CW48*I48 -> 0 | W48: =ROUND(CX48*I48,2) -> 0 | X48: =(ROUND((((S48+ROUND((ROUND(((EU48)*AV48*I48),2)*BS48),2))*AT48)/100),2)+ROUND(((ROUND((ROUND(((AE48-(EU48))*AV48*I48),2)*BS48),2)*AT48)/100),2)) -> 0 | Y48: =(ROUND((((S48+ROUND((ROUND(((EU48)*AV48*I48),2)*BS48),2))*AU48)/100),2)+ROUND(((ROUND((ROUND(((AE48-(EU48))*AV48*I48),2)*BS48),2)*AU48)/100),2)) -> 0 | AA48: 60258621 | AB48: =ROUND((AC48+AD48+AF48),6) -> 2396.35 | AC48: =ROUND((ES48),6) -> 2396.35 | AD48: =ROUND((((ET48)-(EU48))+AE48),6) -> 0 | AE48: =ROUND((EU48),6) -> 0 | AF48: =ROUND((EV48),6) -> 0 | AG48: =ROUND((AP48),6) -> 0 | AH48: =(EW48) -> 0 | AI48: =(EX48) -> 0 | AJ48: =(AS48) -> 0 | AK48: 2396.35 | AL48: 2396.35 | AM48: 0 | AN48: 0 | AO48: 0 | AP48: 0 | AQ48: 0 | AR48: 0 | AS48: 0 | AT48: 0 | AU48: 0 | AV48: 1 | AW48: 1 | AZ48: 1 | BA48: 1 | BB48: 1 | BC48: 1 | BH48: 3 | BI48: 3 | BM48: 746 | BN48: 0 | BP48: 0 | BQ48: 130 | BR48: 0 | BS48: 1 | BT48: 1 | BU48: 1 | BV48: 1 | BW48: 1 | BX48: 1 | BZ48: 0 | CA48: 0 | CE48: 1566 | CF48: 0 | CG48: 0 | CM48: 0 | CO48: 0 | CP48: =(P48+Q48+S48) -> 2396.35 | CQ48: =ROUND((ROUND((AC48*1),2)*BC48),2) -> 2396.35 | CR48: =(ROUND((ROUND(((ET48)*AV48*1),2)*BB48),2)+ROUND((ROUND(((AE48-(EU48))*AV48*1),2)*BS48),2)) -> 0 | CS48: =(ROUND((ROUND(((EU48)*AV48*1),2)*BS48),2)+ROUND((ROUND(((AE48-(EU48))*AV48*1),2)*BS48),2)) -> 0 | CT48: =ROUND((ROUND((AF48*AV48*1),2)*BA48),2) -> 0 | CU48: =AG48 -> 0 | CV48: =(AH48*AV48) -> 0 | CW48: =AI48 -> 0 | CX48: =AJ48 -> 0 | CY48: =(ROUND((((S48+ROUND((ROUND(((EU48)*AV48*1),2)*BS48),2))*AT48)/100),2)+ROUND(((ROUND((ROUND(((AE48-(EU48))*AV48*1),2)*BS48),2)*AT48)/100),2)) -> 0 | CZ48: =(ROUND((((S48+ROUND((ROUND(((EU48)*AV48*1),2)*BS48),2))*AU48)/100),2)+ROUND(((ROUND((ROUND(((AE48-(EU48))*AV48*1),2)*BS48),2)*AU48)/100),2)) -> 0 | DN48: 0 | DO48: 0 | DP48: 1 | DQ48: 1 | DU48: 1013 | DV48: ШТ | DW48: ШТ | DX48: 1 | EE48: 60088638 | EF48: 130 | EG48: Сметная стоимость оборудования | EH48: 0 | EJ48: 3 | EK48: 746 | EL48: ТСН-2001.13. Сметная стоимость оборудования | EM48: ТСН-2001.13 | EQ48: 0 | ER48: 0 | ES48: 2396.35 | ET48: 0 | EU48: 0 | EV48: 0 | EW48: 0 | EX48: 0 | EY48: 0 | FQ48: 0 | FR48: =P48 -> 2396.35 | FS48: 0 | FX48: 0 | FY48: 0 | GA48: [21 132 / 1,2 / 7,66] + 3% Трансп + 1,2% Заг.скл | GD48: 1 | GF48: -1794690275 | GG48: 2 | GH48: 4 | GI48: -2 | GJ48: 0 | GK48: 0 | GL48: =ROUND(IF(AND(BH48=3,BI48=3,FS48<>0),P48,0),2) -> 0 | GM48: =ROUND(O48+X48+Y48,2)+GX48 -> 2396.35 | GN48: =IF(OR(BI48=0,BI48=1),GM48-GX48,0) -> 0 | GO48: =IF(BI48=2,GM48-GX48,0) -> 0 | GP48: =IF(BI48=4,GM48-GX48,0) -> 0 | GR48: 0 | GS48: 2 | GT48: 0 | GV48: =ROUND((GT48),6) -> 0 | GW48: 1 | GX48: =ROUND(HC48*I48,2) -> 0 | HA48: 0 | HB48: 0 | HC48: =GV48*GW48 -> 0 | HE48: 3 | HF48: 1,2 | HS48: 0 | IK48: 0
A49: 17 | B49: 1 | E49: 11 | F49: КА-6 | G49: Блок индикации и управления Рубеж-БИУ | H49: ШТ | I49: 1 | J49: 0 | K49: 1 | O49: =ROUND(CP49,2) -> 18356.04 | P49: =ROUND((ROUND((AC49*I49),2)*BC49),2) -> 18356.04 | Q49: =(ROUND((ROUND(((ET49)*AV49*I49),2)*BB49),2)+ROUND((ROUND(((AE49-(EU49))*AV49*I49),2)*BS49),2)) -> 0 | R49: =(ROUND((ROUND(((EU49)*AV49*I49),2)*BS49),2)+ROUND((ROUND(((AE49-(EU49))*AV49*I49),2)*BS49),2)) -> 0 | S49: =ROUND((ROUND((AF49*AV49*I49),2)*BA49),2) -> 0 | T49: =ROUND(CU49*I49,2) -> 0 | U49: =CV49*I49 -> 0 | V49: =CW49*I49 -> 0 | W49: =ROUND(CX49*I49,2) -> 0 | X49: =(ROUND((((S49+ROUND((ROUND(((EU49)*AV49*I49),2)*BS49),2))*AT49)/100),2)+ROUND(((ROUND((ROUND(((AE49-(EU49))*AV49*I49),2)*BS49),2)*AT49)/100),2)) -> 0 | Y49: =(ROUND((((S49+ROUND((ROUND(((EU49)*AV49*I49),2)*BS49),2))*AU49)/100),2)+ROUND(((ROUND((ROUND(((AE49-(EU49))*AV49*I49),2)*BS49),2)*AU49)/100),2)) -> 0 | AA49: 60258618 | AB49: =ROUND((AC49+AD49+AF49),6) -> 2396.35 | AC49: =ROUND((ES49),6) -> 2396.35 | AD49: =ROUND((((ET49)-(EU49))+AE49),6) -> 0 | AE49: =ROUND((EU49),6) -> 0 | AF49: =ROUND((EV49),6) -> 0 | AG49: =ROUND((AP49),6) -> 0 | AH49: =(EW49) -> 0 | AI49: =(EX49) -> 0 | AJ49: =(AS49) -> 0 | AK49: 2396.35 | AL49: 2396.35 | AM49: 0 | AN49: 0 | AO49: 0 | AP49: 0 | AQ49: 0 | AR49: 0 | AS49: 0 | AT49: 0 | AU49: 0 | AV49: 1 | AW49: 1 | AZ49: 1 | BA49: 1 | BB49: 1 | BC49: 7.66 | BH49: 3 | BI49: 3 | BM49: 746 | BN49: 0 | BP49: 0 | BQ49: 130 | BR49: 0 | BS49: 1 | BT49: 1 | BU49: 1 | BV49: 1 | BW49: 1 | BX49: 1 | BZ49: 0 | CA49: 0 | CE49: 1566 | CF49: 0 | CG49: 0 | CM49: 0 | CO49: 0 | CP49: =(P49+Q49+S49) -> 18356.04 | CQ49: =ROUND((ROUND((AC49*1),2)*BC49),2) -> 18356.04 | CR49: =(ROUND((ROUND(((ET49)*AV49*1),2)*BB49),2)+ROUND((ROUND(((AE49-(EU49))*AV49*1),2)*BS49),2)) -> 0 | CS49: =(ROUND((ROUND(((EU49)*AV49*1),2)*BS49),2)+ROUND((ROUND(((AE49-(EU49))*AV49*1),2)*BS49),2)) -> 0 | CT49: =ROUND((ROUND((AF49*AV49*1),2)*BA49),2) -> 0 | CU49: =AG49 -> 0 | CV49: =(AH49*AV49) -> 0 | CW49: =AI49 -> 0 | CX49: =AJ49 -> 0 | CY49: =(ROUND((((S49+ROUND((ROUND(((EU49)*AV49*1),2)*BS49),2))*AT49)/100),2)+ROUND(((ROUND((ROUND(((AE49-(EU49))*AV49*1),2)*BS49),2)*AT49)/100),2)) -> 0 | CZ49: =(ROUND((((S49+ROUND((ROUND(((EU49)*AV49*1),2)*BS49),2))*AU49)/100),2)+ROUND(((ROUND((ROUND(((AE49-(EU49))*AV49*1),2)*BS49),2)*AU49)/100),2)) -> 0 | DN49: 0 | DO49: 0 | DP49: 1 | DQ49: 1 | DU49: 1013 | DV49: ШТ | DW49: ШТ | DX49: 1 | EE49: 60088638 | EF49: 130 | EG49: Сметная стоимость оборудования | EH49: 0 | EJ49: 3 | EK49: 746 | EL49: ТСН-2001.13. Сметная стоимость оборудования | EM49: ТСН-2001.13 | EQ49: 0 | ER49: 0 | ES49: 2396.35 | ET49: 0 | EU49: 0 | EV49: 0 | EW49: 0 | EX49: 0 | EY49: 0 | EZ49: 5 | FC49: 1 | FD49: 18 | FF49: 21132 | FQ49: 0 | FR49: =P49 -> 18356.04 | FS49: 0 | FX49: 0 | FY49: 0 | GA49: [21 132 / 1,2 / 7,66] + 3% Трансп + 1,2% Заг.скл | GD49: 1 | GF49: -1794690275 | GG49: 2 | GH49: 3 | GI49: 5 | GJ49: 0 | GK49: 0 | GL49: =ROUND(IF(AND(BH49=3,BI49=3,FS49<>0),P49,0),2) -> 0 | GM49: =ROUND(O49+X49+Y49,2)+GX49 -> 18356.04 | GN49: =IF(OR(BI49=0,BI49=1),GM49-GX49,0) -> 0 | GO49: =IF(BI49=2,GM49-GX49,0) -> 0 | GP49: =IF(BI49=4,GM49-GX49,0) -> 0 | GR49: 1 | GS49: 1 | GT49: 0 | GV49: =ROUND((GT49),6) -> 0 | GW49: 1 | GX49: =ROUND(HC49*I49,2) -> 0 | HA49: 0 | HB49: 0 | HC49: =GV49*GW49 -> 0 | HE49: 3 | HF49: 1,2 | HS49: 0 | IK49: 0
A50: 17 | B50: 1 | C50: =ROW(SmtRes!A25) -> 25 | D50: =ROW(EtalonRes!A31) -> 31 | E50: 12 | F50: 4.10-82-3 | G50: Приборы и устройства сигнализирующие объектовые, устройства ультразвуковые, блок питания и контроля | H50: 1 ШТ. | I50: 1 | J50: 0 | K50: 1 | O50: =ROUND(CP50,2) -> 58.93 | P50: =ROUND((ROUND((AC50*AW50*I50),2)*BC50),2) -> 3.36 | Q50: =(ROUND((ROUND((((ET50*1.1))*AV50*I50),2)*BB50),2)+ROUND((ROUND(((AE50-((EU50*1.1)))*AV50*I50),2)*BS50),2)) -> 0.06 | R50: =(ROUND((ROUND((((EU50*1.1))*AV50*I50),2)*BS50),2)+ROUND((ROUND(((AE50-((EU50*1.1)))*AV50*I50),2)*BS50),2)) -> 0.01 | S50: =ROUND((ROUND((AF50*AV50*I50),2)*BA50),2) -> 55.51 | T50: =ROUND(CU50*I50,2) -> 0 | U50: =CV50*I50 -> 4.14612 | V50: =CW50*I50 -> 0 | W50: =ROUND(CX50*I50,2) -> 0 | X50: =(ROUND((((S50+ROUND((ROUND((((EU50*1.1))*AV50*I50),2)*BS50),2))*AT50)/100),2)+ROUND(((ROUND((ROUND(((AE50-((EU50*1.1)))*AV50*I50),2)*BS50),2)*AT50)/100),2)) -> 49.97 | Y50: =(ROUND((((S50+ROUND((ROUND((((EU50*1.1))*AV50*I50),2)*BS50),2))*AU50)/100),2)+ROUND(((ROUND((ROUND(((AE50-((EU50*1.1)))*AV50*I50),2)*BS50),2)*AU50)/100),2)) -> 25.54 | AA50: 60258621 | AB50: =ROUND((AC50+AD50+AF50),6) -> 56.435 | AC50: =ROUND(((ES50*1)),6) -> 3.36 | AD50: =ROUND(((((ET50*1.1))-((EU50*1.1)))+AE50),6) -> 0.055 | AE50: =ROUND(((EU50*1.1)),6) -> 0.011 | AF50: =ROUND(((EV50*1.1)),6) -> 53.02 | AG50: =ROUND((AP50),6) -> 0 | AH50: =((EW50*1.1)) -> 3.96 | AI50: =((EX50*1.1)) -> 0 | AJ50: =(AS50) -> 0 | AK50: 51.61 | AL50: 3.36 | AM50: 0.05 | AN50: 0.01 | AO50: 48.2 | AP50: 0 | AQ50: 3.6 | AR50: 0 | AS50: 0 | AT50: 90 | AU50: 46 | AV50: 1.047 | AW50: 1 | AZ50: 1 | BA50: 1 | BB50: 1 | BC50: 1 | BH50: 0 | BI50: 2 | BJ50: ТСН-2001.4 Доп. 70, Сб. 10, т. 82, поз. 3 | BM50: 68 | BN50: 58973116 | BO50: 4.10-82-3 | BP50: 1 | BQ50: 40 | BR50: 0 | BS50: 1 | BT50: 1 | BU50: 1 | BV50: 1 | BW50: 1 | BX50: 1 | BZ50: 90 | CA50: 46 | CE50: 1566 | CF50: 0 | CG50: 0 | CM50: 0 | CN50: Поправка: Гл.12.Прил.8.п.8. 5_12.00.01.11.003 Наименование: При наличии усложненных условий производства работ (стесненность, сложность складирования и транспортной логистики, наличие в зоне производства работ действующего технологического оборудования или движения технологического транспорта и т.п.) для объектов, расположенных за пределами территории круговой магистральной системы улиц "Садовое кольцо" и за пределами Третьего транспортного кольца города Москвы пунктов "а" и "б", но в пределах Московской кольцевой автомобильной дороги | CO50: 0 | CP50: =(P50+Q50+S50) -> 58.93 | CQ50: =ROUND((ROUND((AC50*AW50*1),2)*BC50),2) -> 3.36 | CR50: =(ROUND((ROUND((((ET50*1.1))*AV50*1),2)*BB50),2)+ROUND((ROUND(((AE50-((EU50*1.1)))*AV50*1),2)*BS50),2)) -> 0.06 | CS50: =(ROUND((ROUND((((EU50*1.1))*AV50*1),2)*BS50),2)+ROUND((ROUND(((AE50-((EU50*1.1)))*AV50*1),2)*BS50),2)) -> 0.01 | CT50: =ROUND((ROUND((AF50*AV50*1),2)*BA50),2) -> 55.51 | CU50: =AG50 -> 0 | CV50: =(AH50*AV50) -> 4.14612 | CW50: =AI50 -> 0 | CX50: =AJ50 -> 0 | CY50: =(ROUND((((S50+ROUND((ROUND((((EU50*1.1))*AV50*1),2)*BS50),2))*AT50)/100),2)+ROUND(((ROUND((ROUND(((AE50-((EU50*1.1)))*AV50*1),2)*BS50),2)*AT50)/100),2)) -> 49.97 | CZ50: =(ROUND((((S50+ROUND((ROUND((((EU50*1.1))*AV50*1),2)*BS50),2))*AU50)/100),2)+ROUND(((ROUND((ROUND(((AE50-((EU50*1.1)))*AV50*1),2)*BS50),2)*AU50)/100),2)) -> 25.54 | DB50: 11 | DD50: *1 | DE50: *1,1 | DF50: *1,1 | DG50: *1,1 | DI50: *1,1 | DJ50: *1,1 | DN50: 0 | DO50: 0 | DP50: 1 | DQ50: 1 | DU50: 1013 | DV50: 1 ШТ. | DW50: 1 ШТ. | DX50: 1 | EE50: 60088532 | EF50: 40 | EG50: Монтаж оборудования | EH50: 0 | EJ50: 2 | EK50: 68 | EL50: ТСН-2001.4-10. Прокладка и монтаж сетей связи | EM50: ТСН-2001.4-10-1 | EO50: Поправка: Гл.12.Прил.8.п.8. 5_12.00.01.11.003 | EQ50: 0 | ER50: 51.61 | ES50: 3.36 | ET50: 0.05 | EU50: 0.01 | EV50: 48.2 | EW50: 3.6 | EX50: 0 | EY50: 0 | FQ50: 0 | FR50: 0 | FS50: 0 | FX50: 90 | FY50: 46 | GD50: 1 | GF50: 743435106 | GG50: 2 | GH50: 1 | GI50: 2 | GJ50: 0 | GK50: 0 | GL50: =ROUND(IF(AND(BH50=3,BI50=3,FS50<>0),P50,0),2) -> 0 | GM50: =ROUND(O50+X50+Y50,2)+GX50 -> 134.44 | GN50: =IF(OR(BI50=0,BI50=1),GM50-GX50,0) -> 0 | GO50: =IF(BI50=2,GM50-GX50,0) -> 134.44 | GP50: =IF(BI50=4,GM50-GX50,0) -> 0 | GR50: 0 | GS50: 3 | GT50: 0 | GV50: =ROUND((GT50),6) -> 0 | GW50: 1 | GX50: =ROUND(HC50*I50,2) -> 0 | HA50: 0 | HB50: 0 | HC50: =GV50*GW50 -> 0 | HS50: 0 | IK50: 0
A51: 17 | B51: 1 | C51: =ROW(SmtRes!A26) -> 26 | D51: =ROW(EtalonRes!A32) -> 32 | E51: 12 | F51: 4.10-82-3 | G51: Приборы и устройства сигнализирующие объектовые, устройства ультразвуковые, блок питания и контроля | H51: 1 ШТ. | I51: 1 | J51: 0 | K51: 1 | O51: =ROUND(CP51,2) -> 3086.86 | P51: =ROUND((ROUND((AC51*AW51*I51),2)*BC51),2) -> 33.23 | Q51: =(ROUND((ROUND((((ET51*1.1))*AV51*I51),2)*BB51),2)+ROUND((ROUND(((AE51-((EU51*1.1)))*AV51*I51),2)*BS51),2)) -> 1.14 | R51: =(ROUND((ROUND((((EU51*1.1))*AV51*I51),2)*BS51),2)+ROUND((ROUND(((AE51-((EU51*1.1)))*AV51*I51),2)*BS51),2)) -> 0.55 | S51: =ROUND((ROUND((AF51*AV51*I51),2)*BA51),2) -> 3052.49 | T51: =ROUND(CU51*I51,2) -> 0 | U51: =CV51*I51 -> 4.14612 | V51: =CW51*I51 -> 0 | W51: =ROUND(CX51*I51,2) -> 0 | X51: =(ROUND((((S51+ROUND((ROUND((((EU51*1.1))*AV51*I51),2)*BS51),2))*AT51)/100),2)+ROUND(((ROUND((ROUND(((AE51-((EU51*1.1)))*AV51*I51),2)*BS51),2)*AT51)/100),2)) -> 2747.74 | Y51: =(ROUND((((S51+ROUND((ROUND((((EU51*1.1))*AV51*I51),2)*BS51),2))*AU51)/100),2)+ROUND(((ROUND((ROUND(((AE51-((EU51*1.1)))*AV51*I51),2)*BS51),2)*AU51)/100),2)) -> 1404.4 | AA51: 60258618 | AB51: =ROUND((AC51+AD51+AF51),6) -> 56.435 | AC51: =ROUND(((ES51*1)),6) -> 3.36 | AD51: =ROUND(((((ET51*1.1))-((EU51*1.1)))+AE51),6) -> 0.055 | AE51: =ROUND(((EU51*1.1)),6) -> 0.011 | AF51: =ROUND(((EV51*1.1)),6) -> 53.02 | AG51: =ROUND((AP51),6) -> 0 | AH51: =((EW51*1.1)) -> 3.96 | AI51: =((EX51*1.1)) -> 0 | AJ51: =(AS51) -> 0 | AK51: 51.61 | AL51: 3.36 | AM51: 0.05 | AN51: 0.01 | AO51: 48.2 | AP51: 0 | AQ51: 3.6 | AR51: 0 | AS51: 0 | AT51: 90 | AU51: 46 | AV51: 1.047 | AW51: 1 | AZ51: 1 | BA51: 54.99 | BB51: 19 | BC51: 9.89 | BH51: 0 | BI51: 2 | BJ51: ТСН-2001.4 Доп. 70, Сб. 10, т. 82, поз. 3 | BM51: 68 | BN51: 58973116 | BO51: 4.10-82-3 | BP51: 1 | BQ51: 40 | BR51: 0 | BS51: 54.99 | BT51: 1 | BU51: 1 | BV51: 1 | BW51: 1 | BX51: 1 | BZ51: 90 | CA51: 46 | CE51: 1566 | CF51: 0 | CG51: 0 | CM51: 0 | CN51: Поправка: Гл.12.Прил.8.п.8. 5_12.00.01.11.003 Наименование: При наличии усложненных условий производства работ (стесненность, сложность складирования и транспортной логистики, наличие в зоне производства работ действующего технологического оборудования или движения технологического транспорта и т.п.) для объектов, расположенных за пределами территории круговой магистральной системы улиц "Садовое кольцо" и за пределами Третьего транспортного кольца города Москвы пунктов "а" и "б", но в пределах Московской кольцевой автомобильной дороги | CO51: 0 | CP51: =(P51+Q51+S51) -> 3086.86 | CQ51: =ROUND((ROUND((AC51*AW51*1),2)*BC51),2) -> 33.23 | CR51: =(ROUND((ROUND((((ET51*1.1))*AV51*1),2)*BB51),2)+ROUND((ROUND(((AE51-((EU51*1.1)))*AV51*1),2)*BS51),2)) -> 1.14 | CS51: =(ROUND((ROUND((((EU51*1.1))*AV51*1),2)*BS51),2)+ROUND((ROUND(((AE51-((EU51*1.1)))*AV51*1),2)*BS51),2)) -> 0.55 | CT51: =ROUND((ROUND((AF51*AV51*1),2)*BA51),2) -> 3052.49 | CU51: =AG51 -> 0 | CV51: =(AH51*AV51) -> 4.14612 | CW51: =AI51 -> 0 | CX51: =AJ51 -> 0 | CY51: =(ROUND((((S51+ROUND((ROUND((((EU51*1.1))*AV51*1),2)*BS51),2))*AT51)/100),2)+ROUND(((ROUND((ROUND(((AE51-((EU51*1.1)))*AV51*1),2)*BS51),2)*AT51)/100),2)) -> 2747.74 | CZ51: =(ROUND((((S51+ROUND((ROUND((((EU51*1.1))*AV51*1),2)*BS51),2))*AU51)/100),2)+ROUND(((ROUND((ROUND(((AE51-((EU51*1.1)))*AV51*1),2)*BS51),2)*AU51)/100),2)) -> 1404.4 | DB51: 12 | DD51: *1 | DE51: *1,1 | DF51: *1,1 | DG51: *1,1 | DI51: *1,1 | DJ51: *1,1 | DN51: 0 | DO51: 0 | DP51: 1 | DQ51: 1 | DU51: 1013 | DV51: 1 ШТ. | DW51: 1 ШТ. | DX51: 1 | EE51: 60088532 | EF51: 40 | EG51: Монтаж оборудования | EH51: 0 | EJ51: 2 | EK51: 68 | EL51: ТСН-2001.4-10. Прокладка и монтаж сетей связи | EM51: ТСН-2001.4-10-1 | EO51: Поправка: Гл.12.Прил.8.п.8. 5_12.00.01.11.003 | EQ51: 0 | ER51: 51.61 | ES51: 3.36 | ET51: 0.05 | EU51: 0.01 | EV51: 48.2 | EW51: 3.6 | EX51: 0 | EY51: 0 | FQ51: 0 | FR51: 0 | FS51: 0 | FX51: 90 | FY51: 46 | GD51: 1 | GF51: 743435106 | GG51: 2 | GH51: 1 | GI51: 2 | GJ51: 0 | GK51: 0 | GL51: =ROUND(IF(AND(BH51=3,BI51=3,FS51<>0),P51,0),2) -> 0 | GM51: =ROUND(O51+X51+Y51,2)+GX51 -> 7239 | GN51: =IF(OR(BI51=0,BI51=1),GM51-GX51,0) -> 0 | GO51: =IF(BI51=2,GM51-GX51,0) -> 7239 | GP51: =IF(BI51=4,GM51-GX51,0) -> 0 | GR51: 0 | GS51: 3 | GT51: 0 | GV51: =ROUND((GT51),6) -> 0 | GW51: 1 | GX51: =ROUND(HC51*I51,2) -> 0 | HA51: 0 | HB51: 0 | HC51: =GV51*GW51 -> 0 | HS51: 0 | IK51: 0
A52: 17 | B52: 1 | E52: 13 | F52: КА-7 | G52: Устройство оконечное объектовое Приток-А КОП-1 исп.1 | H52: ШТ | I52: 1 | J52: 0 | K52: 1 | O52: =ROUND(CP52,2) -> 1829.8 | P52: =ROUND((ROUND((AC52*I52),2)*BC52),2) -> 1829.8 | Q52: =(ROUND((ROUND(((ET52)*AV52*I52),2)*BB52),2)+ROUND((ROUND(((AE52-(EU52))*AV52*I52),2)*BS52),2)) -> 0 | R52: =(ROUND((ROUND(((EU52)*AV52*I52),2)*BS52),2)+ROUND((ROUND(((AE52-(EU52))*AV52*I52),2)*BS52),2)) -> 0 | S52: =ROUND((ROUND((AF52*AV52*I52),2)*BA52),2) -> 0 | T52: =ROUND(CU52*I52,2) -> 0 | U52: =CV52*I52 -> 0 | V52: =CW52*I52 -> 0 | W52: =ROUND(CX52*I52,2) -> 0 | X52: =(ROUND((((S52+ROUND((ROUND(((EU52)*AV52*I52),2)*BS52),2))*AT52)/100),2)+ROUND(((ROUND((ROUND(((AE52-(EU52))*AV52*I52),2)*BS52),2)*AT52)/100),2)) -> 0 | Y52: =(ROUND((((S52+ROUND((ROUND(((EU52)*AV52*I52),2)*BS52),2))*AU52)/100),2)+ROUND(((ROUND((ROUND(((AE52-(EU52))*AV52*I52),2)*BS52),2)*AU52)/100),2)) -> 0 | AA52: 60258621 | AB52: =ROUND((AC52+AD52+AF52),6) -> 1829.8 | AC52: =ROUND((ES52),6) -> 1829.8 | AD52: =ROUND((((ET52)-(EU52))+AE52),6) -> 0 | AE52: =ROUND((EU52),6) -> 0 | AF52: =ROUND((EV52),6) -> 0 | AG52: =ROUND((AP52),6) -> 0 | AH52: =(EW52) -> 0 | AI52: =(EX52) -> 0 | AJ52: =(AS52) -> 0 | AK52: 1829.8 | AL52: 1829.8 | AM52: 0 | AN52: 0 | AO52: 0 | AP52: 0 | AQ52: 0 | AR52: 0 | AS52: 0 | AT52: 0 | AU52: 0 | AV52: 1 | AW52: 1 | AZ52: 1 | BA52: 1 | BB52: 1 | BC52: 1 | BH52: 3 | BI52: 3 | BM52: 746 | BN52: 0 | BP52: 0 | BQ52: 130 | BR52: 0 | BS52: 1 | BT52: 1 | BU52: 1 | BV52: 1 | BW52: 1 | BX52: 1 | BZ52: 0 | CA52: 0 | CE52: 1566 | CF52: 0 | CG52: 0 | CM52: 0 | CO52: 0 | CP52: =(P52+Q52+S52) -> 1829.8 | CQ52: =ROUND((ROUND((AC52*1),2)*BC52),2) -> 1829.8 | CR52: =(ROUND((ROUND(((ET52)*AV52*1),2)*BB52),2)+ROUND((ROUND(((AE52-(EU52))*AV52*1),2)*BS52),2)) -> 0 | CS52: =(ROUND((ROUND(((EU52)*AV52*1),2)*BS52),2)+ROUND((ROUND(((AE52-(EU52))*AV52*1),2)*BS52),2)) -> 0 | CT52: =ROUND((ROUND((AF52*AV52*1),2)*BA52),2) -> 0 | CU52: =AG52 -> 0 | CV52: =(AH52*AV52) -> 0 | CW52: =AI52 -> 0 | CX52: =AJ52 -> 0 | CY52: =(ROUND((((S52+ROUND((ROUND(((EU52)*AV52*1),2)*BS52),2))*AT52)/100),2)+ROUND(((ROUND((ROUND(((AE52-(EU52))*AV52*1),2)*BS52),2)*AT52)/100),2)) -> 0 | CZ52: =(ROUND((((S52+ROUND((ROUND(((EU52)*AV52*1),2)*BS52),2))*AU52)/100),2)+ROUND(((ROUND((ROUND(((AE52-(EU52))*AV52*1),2)*BS52),2)*AU52)/100),2)) -> 0 | DN52: 0 | DO52: 0 | DP52: 1 | DQ52: 1 | DU52: 1013 | DV52: ШТ | DW52: ШТ | DX52: 1 | EE52: 60088638 | EF52: 130 | EG52: Сметная стоимость оборудования | EH52: 0 | EJ52: 3 | EK52: 746 | EL52: ТСН-2001.13. Сметная стоимость оборудования | EM52: ТСН-2001.13 | EQ52: 0 | ER52: 0 | ES52: 1829.8 | ET52: 0 | EU52: 0 | EV52: 0 | EW52: 0 | EX52: 0 | EY52: 0 | FQ52: 0 | FR52: =P52 -> 1829.8 | FS52: 0 | FX52: 0 | FY52: 0 | GA52: [16 136 / 1,2 / 7,66] + 3% Трансп + 1,2% Заг.скл | GD52: 1 | GF52: 1667450026 | GG52: 2 | GH52: 4 | GI52: -2 | GJ52: 0 | GK52: 0 | GL52: =ROUND(IF(AND(BH52=3,BI52=3,FS52<>0),P52,0),2) -> 0 | GM52: =ROUND(O52+X52+Y52,2)+GX52 -> 1829.8 | GN52: =IF(OR(BI52=0,BI52=1),GM52-GX52,0) -> 0 | GO52: =IF(BI52=2,GM52-GX52,0) -> 0 | GP52: =IF(BI52=4,GM52-GX52,0) -> 0 | GR52: 0 | GS52: 2 | GT52: 0 | GV52: =ROUND((GT52),6) -> 0 | GW52: 1 | GX52: =ROUND(HC52*I52,2) -> 0 | HA52: 0 | HB52: 0 | HC52: =GV52*GW52 -> 0 | HE52: 3 | HF52: 1,2 | HS52: 0 | IK52: 0
A53: 17 | B53: 1 | E53: 13 | F53: КА-7 | G53: Устройство оконечное объектовое Приток-А КОП-1 исп.1 | H53: ШТ | I53: 1 | J53: 0 | K53: 1 | O53: =ROUND(CP53,2) -> 14016.27 | P53: =ROUND((ROUND((AC53*I53),2)*BC53),2) -> 14016.27 | Q53: =(ROUND((ROUND(((ET53)*AV53*I53),2)*BB53),2)+ROUND((ROUND(((AE53-(EU53))*AV53*I53),2)*BS53),2)) -> 0 | R53: =(ROUND((ROUND(((EU53)*AV53*I53),2)*BS53),2)+ROUND((ROUND(((AE53-(EU53))*AV53*I53),2)*BS53),2)) -> 0 | S53: =ROUND((ROUND((AF53*AV53*I53),2)*BA53),2) -> 0 | T53: =ROUND(CU53*I53,2) -> 0 | U53: =CV53*I53 -> 0 | V53: =CW53*I53 -> 0 | W53: =ROUND(CX53*I53,2) -> 0 | X53: =(ROUND((((S53+ROUND((ROUND(((EU53)*AV53*I53),2)*BS53),2))*AT53)/100),2)+ROUND(((ROUND((ROUND(((AE53-(EU53))*AV53*I53),2)*BS53),2)*AT53)/100),2)) -> 0 | Y53: =(ROUND((((S53+ROUND((ROUND(((EU53)*AV53*I53),2)*BS53),2))*AU53)/100),2)+ROUND(((ROUND((ROUND(((AE53-(EU53))*AV53*I53),2)*BS53),2)*AU53)/100),2)) -> 0 | AA53: 60258618 | AB53: =ROUND((AC53+AD53+AF53),6) -> 1829.8 | AC53: =ROUND((ES53),6) -> 1829.8 | AD53: =ROUND((((ET53)-(EU53))+AE53),6) -> 0 | AE53: =ROUND((EU53),6) -> 0 | AF53: =ROUND((EV53),6) -> 0 | AG53: =ROUND((AP53),6) -> 0 | AH53: =(EW53) -> 0 | AI53: =(EX53) -> 0 | AJ53: =(AS53) -> 0 | AK53: 1829.8 | AL53: 1829.8 | AM53: 0 | AN53: 0 | AO53: 0 | AP53: 0 | AQ53: 0 | AR53: 0 | AS53: 0 | AT53: 0 | AU53: 0 | AV53: 1 | AW53: 1 | AZ53: 1 | BA53: 1 | BB53: 1 | BC53: 7.66 | BH53: 3 | BI53: 3 | BM53: 746 | BN53: 0 | BP53: 0 | BQ53: 130 | BR53: 0 | BS53: 1 | BT53: 1 | BU53: 1 | BV53: 1 | BW53: 1 | BX53: 1 | BZ53: 0 | CA53: 0 | CE53: 1566 | CF53: 0 | CG53: 0 | CM53: 0 | CO53: 0 | CP53: =(P53+Q53+S53) -> 14016.27 | CQ53: =ROUND((ROUND((AC53*1),2)*BC53),2) -> 14016.27 | CR53: =(ROUND((ROUND(((ET53)*AV53*1),2)*BB53),2)+ROUND((ROUND(((AE53-(EU53))*AV53*1),2)*BS53),2)) -> 0 | CS53: =(ROUND((ROUND(((EU53)*AV53*1),2)*BS53),2)+ROUND((ROUND(((AE53-(EU53))*AV53*1),2)*BS53),2)) -> 0 | CT53: =ROUND((ROUND((AF53*AV53*1),2)*BA53),2) -> 0 | CU53: =AG53 -> 0 | CV53: =(AH53*AV53) -> 0 | CW53: =AI53 -> 0 | CX53: =AJ53 -> 0 | CY53: =(ROUND((((S53+ROUND((ROUND(((EU53)*AV53*1),2)*BS53),2))*AT53)/100),2)+ROUND(((ROUND((ROUND(((AE53-(EU53))*AV53*1),2)*BS53),2)*AT53)/100),2)) -> 0 | CZ53: =(ROUND((((S53+ROUND((ROUND(((EU53)*AV53*1),2)*BS53),2))*AU53)/100),2)+ROUND(((ROUND((ROUND(((AE53-(EU53))*AV53*1),2)*BS53),2)*AU53)/100),2)) -> 0 | DN53: 0 | DO53: 0 | DP53: 1 | DQ53: 1 | DU53: 1013 | DV53: ШТ | DW53: ШТ | DX53: 1 | EE53: 60088638 | EF53: 130 | EG53: Сметная стоимость оборудования | EH53: 0 | EJ53: 3 | EK53: 746 | EL53: ТСН-2001.13. Сметная стоимость оборудования | EM53: ТСН-2001.13 | EQ53: 0 | ER53: 0 | ES53: 1829.8 | ET53: 0 | EU53: 0 | EV53: 0 | EW53: 0 | EX53: 0 | EY53: 0 | EZ53: 5 | FC53: 1 | FD53: 18 | FF53: 16136 | FQ53: 0 | FR53: =P53 -> 14016.27 | FS53: 0 | FX53: 0 | FY53: 0 | GA53: [16 136 / 1,2 / 7,66] + 3% Трансп + 1,2% Заг.скл | GD53: 1 | GF53: 1667450026 | GG53: 2 | GH53: 3 | GI53: 5 | GJ53: 0 | GK53: 0 | GL53: =ROUND(IF(AND(BH53=3,BI53=3,FS53<>0),P53,0),2) -> 0 | GM53: =ROUND(O53+X53+Y53,2)+GX53 -> 14016.27 | GN53: =IF(OR(BI53=0,BI53=1),GM53-GX53,0) -> 0 | GO53: =IF(BI53=2,GM53-GX53,0) -> 0 | GP53: =IF(BI53=4,GM53-GX53,0) -> 0 | GR53: 1 | GS53: 1 | GT53: 0 | GV53: =ROUND((GT53),6) -> 0 | GW53: 1 | GX53: =ROUND(HC53*I53,2) -> 0 | HA53: 0 | HB53: 0 | HC53: =GV53*GW53 -> 0 | HE53: 3 | HF53: 1,2 | HS53: 0 | IK53: 0
A54: 17 | B54: 1 | C54: =ROW(SmtRes!A30) -> 30 | D54: =ROW(EtalonRes!A37) -> 37 | E54: 14 | F54: 4.10-173-2 | G54: Монтаж блока бесперебойного питания (ББП) в диспетчерской | H54: 1 ШТ. | I54: 3 | J54: 0 | K54: 3 | O54: =ROUND(CP54,2) -> 145.81 | P54: =ROUND((ROUND((AC54*AW54*I54),2)*BC54),2) -> 7.02 | Q54: =(ROUND((ROUND((((ET54*1.1))*AV54*I54),2)*BB54),2)+ROUND((ROUND(((AE54-((EU54*1.1)))*AV54*I54),2)*BS54),2)) -> 0 | R54: =(ROUND((ROUND((((EU54*1.1))*AV54*I54),2)*BS54),2)+ROUND((ROUND(((AE54-((EU54*1.1)))*AV54*I54),2)*BS54),2)) -> 0 | S54: =ROUND((ROUND((AF54*AV54*I54),2)*BA54),2) -> 138.79 | T54: =ROUND(CU54*I54,2) -> 0 | U54: =CV54*I54 -> 10.987218 | V54: =CW54*I54 -> 0 | W54: =ROUND(CX54*I54,2) -> 0 | X54: =(ROUND((((S54+ROUND((ROUND((((EU54*1.1))*AV54*I54),2)*BS54),2))*AT54)/100),2)+ROUND(((ROUND((ROUND(((AE54-((EU54*1.1)))*AV54*I54),2)*BS54),2)*AT54)/100),2)) -> 124.91 | Y54: =(ROUND((((S54+ROUND((ROUND((((EU54*1.1))*AV54*I54),2)*BS54),2))*AU54)/100),2)+ROUND(((ROUND((ROUND(((AE54-((EU54*1.1)))*AV54*I54),2)*BS54),2)*AU54)/100),2)) -> 63.84 | AA54: 60258621 | AB54: =ROUND((AC54+AD54+AF54),6) -> 46.527 | AC54: =ROUND(((ES54*1)),6) -> 2.34 | AD54: =ROUND(((((ET54*1.1))-((EU54*1.1)))+AE54),6) -> 0 | AE54: =ROUND(((EU54*1.1)),6) -> 0 | AF54: =ROUND(((EV54*1.1)),6) -> 44.187 | AG54: =ROUND((AP54),6) -> 0 | AH54: =((EW54*1.1)) -> 3.498 | AI54: =((EX54*1.1)) -> 0 | AJ54: =(AS54) -> 0 | AK54: 42.51 | AL54: 2.34 | AM54: 0 | AN54: 0 | AO54: 40.17 | AP54: 0 | AQ54: 3.18 | AR54: 0 | AS54: 0 | AT54: 90 | AU54: 46 | AV54: 1.047 | AW54: 1 | AZ54: 1 | BA54: 1 | BB54: 1 | BC54: 1 | BH54: 0 | BI54: 2 | BJ54: ТСН-2001.4 Доп. 67, Сб. 10, т. 173, поз. 2 | BM54: 68 | BN54: 58973116 | BO54: 4.10-173-2 | BP54: 1 | BQ54: 40 | BR54: 0 | BS54: 1 | BT54: 1 | BU54: 1 | BV54: 1 | BW54: 1 | BX54: 1 | BZ54: 90 | CA54: 46 | CE54: 1566 | CF54: 0 | CG54: 0 | CM54: 0 | CN54: Поправка: Гл.12.Прил.8.п.8. 5_12.00.01.11.003 Наименование: При наличии усложненных условий производства работ (стесненность, сложность складирования и транспортной логистики, наличие в зоне производства работ действующего технологического оборудования или движения технологического транспорта и т.п.) для объектов, расположенных за пределами территории круговой магистральной системы улиц "Садовое кольцо" и за пределами Третьего транспортного кольца города Москвы пунктов "а" и "б", но в пределах Московской кольцевой автомобильной дороги | CO54: 0 | CP54: =(P54+Q54+S54) -> 145.81 | CQ54: =ROUND((ROUND((AC54*AW54*1),2)*BC54),2) -> 2.34 | CR54: =(ROUND((ROUND((((ET54*1.1))*AV54*1),2)*BB54),2)+ROUND((ROUND(((AE54-((EU54*1.1)))*AV54*1),2)*BS54),2)) -> 0 | CS54: =(ROUND((ROUND((((EU54*1.1))*AV54*1),2)*BS54),2)+ROUND((ROUND(((AE54-((EU54*1.1)))*AV54*1),2)*BS54),2)) -> 0 | CT54: =ROUND((ROUND((AF54*AV54*1),2)*BA54),2) -> 46.26 | CU54: =AG54 -> 0 | CV54: =(AH54*AV54) -> 3.662406 | CW54: =AI54 -> 0 | CX54: =AJ54 -> 0 | CY54: =(ROUND((((S54+ROUND((ROUND((((EU54*1.1))*AV54*1),2)*BS54),2))*AT54)/100),2)+ROUND(((ROUND((ROUND(((AE54-((EU54*1.1)))*AV54*1),2)*BS54),2)*AT54)/100),2)) -> 124.91 | CZ54: =(ROUND((((S54+ROUND((ROUND((((EU54*1.1))*AV54*1),2)*BS54),2))*AU54)/100),2)+ROUND(((ROUND((ROUND(((AE54-((EU54*1.1)))*AV54*1),2)*BS54),2)*AU54)/100),2)) -> 63.84 | DB54: 13 | DD54: *1 | DE54: *1,1 | DF54: *1,1 | DG54: *1,1 | DI54: *1,1 | DJ54: *1,1 | DN54: 0 | DO54: 0 | DP54: 1 | DQ54: 1 | DU54: 1013 | DV54: 1 ШТ. | DW54: 1 ШТ. | DX54: 1 | EE54: 60088532 | EF54: 40 | EG54: Монтаж оборудования | EH54: 0 | EJ54: 2 | EK54: 68 | EL54: ТСН-2001.4-10. Прокладка и монтаж сетей связи | EM54: ТСН-2001.4-10-1 | EO54: Поправка: Гл.12.Прил.8.п.8. 5_12.00.01.11.003 | EQ54: 0 | ER54: 42.51 | ES54: 2.34 | ET54: 0 | EU54: 0 | EV54: 40.17 | EW54: 3.18 | EX54: 0 | EY54: 0 | FQ54: 0 | FR54: 0 | FS54: 0 | FX54: 90 | FY54: 46 | GD54: 1 | GF54: 1548884140 | GG54: 2 | GH54: 1 | GI54: 2 | GJ54: 0 | GK54: 0 | GL54: =ROUND(IF(AND(BH54=3,BI54=3,FS54<>0),P54,0),2) -> 0 | GM54: =ROUND(O54+X54+Y54,2)+GX54 -> 334.56 | GN54: =IF(OR(BI54=0,BI54=1),GM54-GX54,0) -> 0 | GO54: =IF(BI54=2,GM54-GX54,0) -> 334.56 | GP54: =IF(BI54=4,GM54-GX54,0) -> 0 | GR54: 0 | GS54: 3 | GT54: 0 | GV54: =ROUND((GT54),6) -> 0 | GW54: 1 | GX54: =ROUND(HC54*I54,2) -> 0 | HA54: 0 | HB54: 0 | HC54: =GV54*GW54 -> 0 | HS54: 0 | IK54: 0
A55: 17 | B55: 1 | C55: =ROW(SmtRes!A34) -> 34 | D55: =ROW(EtalonRes!A42) -> 42 | E55: 14 | F55: 4.10-173-2 | G55: Монтаж блока бесперебойного питания (ББП) в диспетчерской | H55: 1 ШТ. | I55: 3 | J55: 0 | K55: 3 | O55: =ROUND(CP55,2) -> 7704.09 | P55: =ROUND((ROUND((AC55*AW55*I55),2)*BC55),2) -> 72.03 | Q55: =(ROUND((ROUND((((ET55*1.1))*AV55*I55),2)*BB55),2)+ROUND((ROUND(((AE55-((EU55*1.1)))*AV55*I55),2)*BS55),2)) -> 0 | R55: =(ROUND((ROUND((((EU55*1.1))*AV55*I55),2)*BS55),2)+ROUND((ROUND(((AE55-((EU55*1.1)))*AV55*I55),2)*BS55),2)) -> 0 | S55: =ROUND((ROUND((AF55*AV55*I55),2)*BA55),2) -> 7632.06 | T55: =ROUND(CU55*I55,2) -> 0 | U55: =CV55*I55 -> 10.987218 | V55: =CW55*I55 -> 0 | W55: =ROUND(CX55*I55,2) -> 0 | X55: =(ROUND((((S55+ROUND((ROUND((((EU55*1.1))*AV55*I55),2)*BS55),2))*AT55)/100),2)+ROUND(((ROUND((ROUND(((AE55-((EU55*1.1)))*AV55*I55),2)*BS55),2)*AT55)/100),2)) -> 6868.85 | Y55: =(ROUND((((S55+ROUND((ROUND((((EU55*1.1))*AV55*I55),2)*BS55),2))*AU55)/100),2)+ROUND(((ROUND((ROUND(((AE55-((EU55*1.1)))*AV55*I55),2)*BS55),2)*AU55)/100),2)) -> 3510.75 | AA55: 60258618 | AB55: =ROUND((AC55+AD55+AF55),6) -> 46.527 | AC55: =ROUND(((ES55*1)),6) -> 2.34 | AD55: =ROUND(((((ET55*1.1))-((EU55*1.1)))+AE55),6) -> 0 | AE55: =ROUND(((EU55*1.1)),6) -> 0 | AF55: =ROUND(((EV55*1.1)),6) -> 44.187 | AG55: =ROUND((AP55),6) -> 0 | AH55: =((EW55*1.1)) -> 3.498 | AI55: =((EX55*1.1)) -> 0 | AJ55: =(AS55) -> 0 | AK55: 42.51 | AL55: 2.34 | AM55: 0 | AN55: 0 | AO55: 40.17 | AP55: 0 | AQ55: 3.18 | AR55: 0 | AS55: 0 | AT55: 90 | AU55: 46 | AV55: 1.047 | AW55: 1 | AZ55: 1 | BA55: 54.99 | BB55: 1 | BC55: 10.26 | BH55: 0 | BI55: 2 | BJ55: ТСН-2001.4 Доп. 67, Сб. 10, т. 173, поз. 2 | BM55: 68 | BN55: 58973116 | BO55: 4.10-173-2 | BP55: 1 | BQ55: 40 | BR55: 0 | BS55: 54.99 | BT55: 1 | BU55: 1 | BV55: 1 | BW55: 1 | BX55: 1 | BZ55: 90 | CA55: 46 | CE55: 1566 | CF55: 0 | CG55: 0 | CM55: 0 | CN55: Поправка: Гл.12.Прил.8.п.8. 5_12.00.01.11.003 Наименование: При наличии усложненных условий производства работ (стесненность, сложность складирования и транспортной логистики, наличие в зоне производства работ действующего технологического оборудования или движения технологического транспорта и т.п.) для объектов, расположенных за пределами территории круговой магистральной системы улиц "Садовое кольцо" и за пределами Третьего транспортного кольца города Москвы пунктов "а" и "б", но в пределах Московской кольцевой автомобильной дороги | CO55: 0 | CP55: =(P55+Q55+S55) -> 7704.09 | CQ55: =ROUND((ROUND((AC55*AW55*1),2)*BC55),2) -> 24.01 | CR55: =(ROUND((ROUND((((ET55*1.1))*AV55*1),2)*BB55),2)+ROUND((ROUND(((AE55-((EU55*1.1)))*AV55*1),2)*BS55),2)) -> 0 | CS55: =(ROUND((ROUND((((EU55*1.1))*AV55*1),2)*BS55),2)+ROUND((ROUND(((AE55-((EU55*1.1)))*AV55*1),2)*BS55),2)) -> 0 | CT55: =ROUND((ROUND((AF55*AV55*1),2)*BA55),2) -> 2543.84 | CU55: =AG55 -> 0 | CV55: =(AH55*AV55) -> 3.662406 | CW55: =AI55 -> 0 | CX55: =AJ55 -> 0 | CY55: =(ROUND((((S55+ROUND((ROUND((((EU55*1.1))*AV55*1),2)*BS55),2))*AT55)/100),2)+ROUND(((ROUND((ROUND(((AE55-((EU55*1.1)))*AV55*1),2)*BS55),2)*AT55)/100),2)) -> 6868.85 | CZ55: =(ROUND((((S55+ROUND((ROUND((((EU55*1.1))*AV55*1),2)*BS55),2))*AU55)/100),2)+ROUND(((ROUND((ROUND(((AE55-((EU55*1.1)))*AV55*1),2)*BS55),2)*AU55)/100),2)) -> 3510.75 | DB55: 14 | DD55: *1 | DE55: *1,1 | DF55: *1,1 | DG55: *1,1 | DI55: *1,1 | DJ55: *1,1 | DN55: 0 | DO55: 0 | DP55: 1 | DQ55: 1 | DU55: 1013 | DV55: 1 ШТ. | DW55: 1 ШТ. | DX55: 1 | EE55: 60088532 | EF55: 40 | EG55: Монтаж оборудования | EH55: 0 | EJ55: 2 | EK55: 68 | EL55: ТСН-2001.4-10. Прокладка и монтаж сетей связи | EM55: ТСН-2001.4-10-1 | EO55: Поправка: Гл.12.Прил.8.п.8. 5_12.00.01.11.003 | EQ55: 0 | ER55: 42.51 | ES55: 2.34 | ET55: 0 | EU55: 0 | EV55: 40.17 | EW55: 3.18 | EX55: 0 | EY55: 0 | FQ55: 0 | FR55: 0 | FS55: 0 | FX55: 90 | FY55: 46 | GD55: 1 | GF55: 1548884140 | GG55: 2 | GH55: 1 | GI55: 2 | GJ55: 0 | GK55: 0 | GL55: =ROUND(IF(AND(BH55=3,BI55=3,FS55<>0),P55,0),2) -> 0 | GM55: =ROUND(O55+X55+Y55,2)+GX55 -> 18083.69 | GN55: =IF(OR(BI55=0,BI55=1),GM55-GX55,0) -> 0 | GO55: =IF(BI55=2,GM55-GX55,0) -> 18083.69 | GP55: =IF(BI55=4,GM55-GX55,0) -> 0 | GR55: 0 | GS55: 3 | GT55: 0 | GV55: =ROUND((GT55),6) -> 0 | GW55: 1 | GX55: =ROUND(HC55*I55,2) -> 0 | HA55: 0 | HB55: 0 | HC55: =GV55*GW55 -> 0 | HS55: 0 | IK55: 0
A56: 17 | B56: 1 | E56: 15 | F56: КА-8 | G56: Блок питания, 12В, 2А ИВЭПР 12/2 RS-R3 | H56: ШТ | I56: 3 | J56: 0 | K56: 3 | O56: =ROUND(CP56,2) -> 2523.75 | P56: =ROUND((ROUND((AC56*I56),2)*BC56),2) -> 2523.75 | Q56: =(ROUND((ROUND(((ET56)*AV56*I56),2)*BB56),2)+ROUND((ROUND(((AE56-(EU56))*AV56*I56),2)*BS56),2)) -> 0 | R56: =(ROUND((ROUND(((EU56)*AV56*I56),2)*BS56),2)+ROUND((ROUND(((AE56-(EU56))*AV56*I56),2)*BS56),2)) -> 0 | S56: =ROUND((ROUND((AF56*AV56*I56),2)*BA56),2) -> 0 | T56: =ROUND(CU56*I56,2) -> 0 | U56: =CV56*I56 -> 0 | V56: =CW56*I56 -> 0 | W56: =ROUND(CX56*I56,2) -> 0 | X56: =(ROUND((((S56+ROUND((ROUND(((EU56)*AV56*I56),2)*BS56),2))*AT56)/100),2)+ROUND(((ROUND((ROUND(((AE56-(EU56))*AV56*I56),2)*BS56),2)*AT56)/100),2)) -> 0 | Y56: =(ROUND((((S56+ROUND((ROUND(((EU56)*AV56*I56),2)*BS56),2))*AU56)/100),2)+ROUND(((ROUND((ROUND(((AE56-(EU56))*AV56*I56),2)*BS56),2)*AU56)/100),2)) -> 0 | AA56: 60258621 | AB56: =ROUND((AC56+AD56+AF56),6) -> 841.25 | AC56: =ROUND((ES56),6) -> 841.25 | AD56: =ROUND((((ET56)-(EU56))+AE56),6) -> 0 | AE56: =ROUND((EU56),6) -> 0 | AF56: =ROUND((EV56),6) -> 0 | AG56: =ROUND((AP56),6) -> 0 | AH56: =(EW56) -> 0 | AI56: =(EX56) -> 0 | AJ56: =(AS56) -> 0 | AK56: 841.25 | AL56: 841.25 | AM56: 0 | AN56: 0 | AO56: 0 | AP56: 0 | AQ56: 0 | AR56: 0 | AS56: 0 | AT56: 0 | AU56: 0 | AV56: 1 | AW56: 1 | AZ56: 1 | BA56: 1 | BB56: 1 | BC56: 1 | BH56: 3 | BI56: 3 | BM56: 746 | BN56: 0 | BP56: 0 | BQ56: 130 | BR56: 0 | BS56: 1 | BT56: 1 | BU56: 1 | BV56: 1 | BW56: 1 | BX56: 1 | BZ56: 0 | CA56: 0 | CE56: 1566 | CF56: 0 | CG56: 0 | CM56: 0 | CO56: 0 | CP56: =(P56+Q56+S56) -> 2523.75 | CQ56: =ROUND((ROUND((AC56*1),2)*BC56),2) -> 841.25 | CR56: =(ROUND((ROUND(((ET56)*AV56*1),2)*BB56),2)+ROUND((ROUND(((AE56-(EU56))*AV56*1),2)*BS56),2)) -> 0 | CS56: =(ROUND((ROUND(((EU56)*AV56*1),2)*BS56),2)+ROUND((ROUND(((AE56-(EU56))*AV56*1),2)*BS56),2)) -> 0 | CT56: =ROUND((ROUND((AF56*AV56*1),2)*BA56),2) -> 0 | CU56: =AG56 -> 0 | CV56: =(AH56*AV56) -> 0 | CW56: =AI56 -> 0 | CX56: =AJ56 -> 0 | CY56: =(ROUND((((S56+ROUND((ROUND(((EU56)*AV56*1),2)*BS56),2))*AT56)/100),2)+ROUND(((ROUND((ROUND(((AE56-(EU56))*AV56*1),2)*BS56),2)*AT56)/100),2)) -> 0 | CZ56: =(ROUND((((S56+ROUND((ROUND(((EU56)*AV56*1),2)*BS56),2))*AU56)/100),2)+ROUND(((ROUND((ROUND(((AE56-(EU56))*AV56*1),2)*BS56),2)*AU56)/100),2)) -> 0 | DN56: 0 | DO56: 0 | DP56: 1 | DQ56: 1 | DU56: 1013 | DV56: ШТ | DW56: ШТ | DX56: 1 | EE56: 60088638 | EF56: 130 | EG56: Сметная стоимость оборудования | EH56: 0 | EJ56: 3 | EK56: 746 | EL56: ТСН-2001.13. Сметная стоимость оборудования | EM56: ТСН-2001.13 | EQ56: 0 | ER56: 0 | ES56: 841.25 | ET56: 0 | EU56: 0 | EV56: 0 | EW56: 0 | EX56: 0 | EY56: 0 | FQ56: 0 | FR56: =P56 -> 2523.75 | FS56: 0 | FX56: 0 | FY56: 0 | GA56: [7 418,45 / 1,2 / 7,66] + 3% Трансп + 1,2% Заг.скл | GD56: 1 | GF56: -64086888 | GG56: 2 | GH56: 4 | GI56: -2 | GJ56: 0 | GK56: 0 | GL56: =ROUND(IF(AND(BH56=3,BI56=3,FS56<>0),P56,0),2) -> 0 | GM56: =ROUND(O56+X56+Y56,2)+GX56 -> 2523.75 | GN56: =IF(OR(BI56=0,BI56=1),GM56-GX56,0) -> 0 | GO56: =IF(BI56=2,GM56-GX56,0) -> 0 | GP56: =IF(BI56=4,GM56-GX56,0) -> 0 | GR56: 0 | GS56: 2 | GT56: 0 | GV56: =ROUND((GT56),6) -> 0 | GW56: 1 | GX56: =ROUND(HC56*I56,2) -> 0 | HA56: 0 | HB56: 0 | HC56: =GV56*GW56 -> 0 | HE56: 3 | HF56: 1,2 | HS56: 0 | IK56: 0
A57: 17 | B57: 1 | E57: 15 | F57: КА-8 | G57: Блок питания, 12В, 2А ИВЭПР 12/2 RS-R3 | H57: ШТ | I57: 3 | J57: 0 | K57: 3 | O57: =ROUND(CP57,2) -> 19331.93 | P57: =ROUND((ROUND((AC57*I57),2)*BC57),2) -> 19331.93 | Q57: =(ROUND((ROUND(((ET57)*AV57*I57),2)*BB57),2)+ROUND((ROUND(((AE57-(EU57))*AV57*I57),2)*BS57),2)) -> 0 | R57: =(ROUND((ROUND(((EU57)*AV57*I57),2)*BS57),2)+ROUND((ROUND(((AE57-(EU57))*AV57*I57),2)*BS57),2)) -> 0 | S57: =ROUND((ROUND((AF57*AV57*I57),2)*BA57),2) -> 0 | T57: =ROUND(CU57*I57,2) -> 0 | U57: =CV57*I57 -> 0 | V57: =CW57*I57 -> 0 | W57: =ROUND(CX57*I57,2) -> 0 | X57: =(ROUND((((S57+ROUND((ROUND(((EU57)*AV57*I57),2)*BS57),2))*AT57)/100),2)+ROUND(((ROUND((ROUND(((AE57-(EU57))*AV57*I57),2)*BS57),2)*AT57)/100),2)) -> 0 | Y57: =(ROUND((((S57+ROUND((ROUND(((EU57)*AV57*I57),2)*BS57),2))*AU57)/100),2)+ROUND(((ROUND((ROUND(((AE57-(EU57))*AV57*I57),2)*BS57),2)*AU57)/100),2)) -> 0 | AA57: 60258618 | AB57: =ROUND((AC57+AD57+AF57),6) -> 841.25 | AC57: =ROUND((ES57),6) -> 841.25 | AD57: =ROUND((((ET57)-(EU57))+AE57),6) -> 0 | AE57: =ROUND((EU57),6) -> 0 | AF57: =ROUND((EV57),6) -> 0 | AG57: =ROUND((AP57),6) -> 0 | AH57: =(EW57) -> 0 | AI57: =(EX57) -> 0 | AJ57: =(AS57) -> 0 | AK57: 841.25 | AL57: 841.25 | AM57: 0 | AN57: 0 | AO57: 0 | AP57: 0 | AQ57: 0 | AR57: 0 | AS57: 0 | AT57: 0 | AU57: 0 | AV57: 1 | AW57: 1 | AZ57: 1 | BA57: 1 | BB57: 1 | BC57: 7.66 | BH57: 3 | BI57: 3 | BM57: 746 | BN57: 0 | BP57: 0 | BQ57: 130 | BR57: 0 | BS57: 1 | BT57: 1 | BU57: 1 | BV57: 1 | BW57: 1 | BX57: 1 | BZ57: 0 | CA57: 0 | CE57: 1566 | CF57: 0 | CG57: 0 | CM57: 0 | CO57: 0 | CP57: =(P57+Q57+S57) -> 19331.93 | CQ57: =ROUND((ROUND((AC57*1),2)*BC57),2) -> 6443.98 | CR57: =(ROUND((ROUND(((ET57)*AV57*1),2)*BB57),2)+ROUND((ROUND(((AE57-(EU57))*AV57*1),2)*BS57),2)) -> 0 | CS57: =(ROUND((ROUND(((EU57)*AV57*1),2)*BS57),2)+ROUND((ROUND(((AE57-(EU57))*AV57*1),2)*BS57),2)) -> 0 | CT57: =ROUND((ROUND((AF57*AV57*1),2)*BA57),2) -> 0 | CU57: =AG57 -> 0 | CV57: =(AH57*AV57) -> 0 | CW57: =AI57 -> 0 | CX57: =AJ57 -> 0 | CY57: =(ROUND((((S57+ROUND((ROUND(((EU57)*AV57*1),2)*BS57),2))*AT57)/100),2)+ROUND(((ROUND((ROUND(((AE57-(EU57))*AV57*1),2)*BS57),2)*AT57)/100),2)) -> 0 | CZ57: =(ROUND((((S57+ROUND((ROUND(((EU57)*AV57*1),2)*BS57),2))*AU57)/100),2)+ROUND(((ROUND((ROUND(((AE57-(EU57))*AV57*1),2)*BS57),2)*AU57)/100),2)) -> 0 | DN57: 0 | DO57: 0 | DP57: 1 | DQ57: 1 | DU57: 1013 | DV57: ШТ | DW57: ШТ | DX57: 1 | EE57: 60088638 | EF57: 130 | EG57: Сметная стоимость оборудования | EH57: 0 | EJ57: 3 | EK57: 746 | EL57: ТСН-2001.13. Сметная стоимость оборудования | EM57: ТСН-2001.13 | EQ57: 0 | ER57: 0 | ES57: 841.25 | ET57: 0 | EU57: 0 | EV57: 0 | EW57: 0 | EX57: 0 | EY57: 0 | EZ57: 5 | FC57: 1 | FD57: 18 | FF57: 7418.45 | FQ57: 0 | FR57: =P57 -> 19331.93 | FS57: 0 | FX57: 0 | FY57: 0 | GA57: [7 418,45 / 1,2 / 7,66] + 3% Трансп + 1,2% Заг.скл | GD57: 1 | GF57: -64086888 | GG57: 2 | GH57: 3 | GI57: 5 | GJ57: 0 | GK57: 0 | GL57: =ROUND(IF(AND(BH57=3,BI57=3,FS57<>0),P57,0),2) -> 0 | GM57: =ROUND(O57+X57+Y57,2)+GX57 -> 19331.93 | GN57: =IF(OR(BI57=0,BI57=1),GM57-GX57,0) -> 0 | GO57: =IF(BI57=2,GM57-GX57,0) -> 0 | GP57: =IF(BI57=4,GM57-GX57,0) -> 0 | GR57: 1 | GS57: 1 | GT57: 0 | GV57: =ROUND((GT57),6) -> 0 | GW57: 1 | GX57: =ROUND(HC57*I57,2) -> 0 | HA57: 0 | HB57: 0 | HC57: =GV57*GW57 -> 0 | HE57: 3 | HF57: 1,2 | HS57: 0 | IK57: 0
A58: 17 | B58: 1 | E58: 16 | F58: КА-9 | G58: Аккумултор 12В 7Ач DTM 1207 | H58: ШТ | I58: 3 | J58: 0 | K58: 3 | O58: =ROUND(CP58,2) -> 479.67 | P58: =ROUND((ROUND((AC58*I58),2)*BC58),2) -> 479.67 | Q58: =(ROUND((ROUND(((ET58)*AV58*I58),2)*BB58),2)+ROUND((ROUND(((AE58-(EU58))*AV58*I58),2)*BS58),2)) -> 0 | R58: =(ROUND((ROUND(((EU58)*AV58*I58),2)*BS58),2)+ROUND((ROUND(((AE58-(EU58))*AV58*I58),2)*BS58),2)) -> 0 | S58: =ROUND((ROUND((AF58*AV58*I58),2)*BA58),2) -> 0 | T58: =ROUND(CU58*I58,2) -> 0 | U58: =CV58*I58 -> 0 | V58: =CW58*I58 -> 0 | W58: =ROUND(CX58*I58,2) -> 0 | X58: =(ROUND((((S58+ROUND((ROUND(((EU58)*AV58*I58),2)*BS58),2))*AT58)/100),2)+ROUND(((ROUND((ROUND(((AE58-(EU58))*AV58*I58),2)*BS58),2)*AT58)/100),2)) -> 0 | Y58: =(ROUND((((S58+ROUND((ROUND(((EU58)*AV58*I58),2)*BS58),2))*AU58)/100),2)+ROUND(((ROUND((ROUND(((AE58-(EU58))*AV58*I58),2)*BS58),2)*AU58)/100),2)) -> 0 | AA58: 60258621 | AB58: =ROUND((AC58+AD58+AF58),6) -> 159.89 | AC58: =ROUND((ES58),6) -> 159.89 | AD58: =ROUND((((ET58)-(EU58))+AE58),6) -> 0 | AE58: =ROUND((EU58),6) -> 0 | AF58: =ROUND((EV58),6) -> 0 | AG58: =ROUND((AP58),6) -> 0 | AH58: =(EW58) -> 0 | AI58: =(EX58) -> 0 | AJ58: =(AS58) -> 0 | AK58: 159.89 | AL58: 159.89 | AM58: 0 | AN58: 0 | AO58: 0 | AP58: 0 | AQ58: 0 | AR58: 0 | AS58: 0 | AT58: 0 | AU58: 0 | AV58: 1 | AW58: 1 | AZ58: 1 | BA58: 1 | BB58: 1 | BC58: 1 | BH58: 3 | BI58: 3 | BM58: 746 | BN58: 0 | BP58: 0 | BQ58: 130 | BR58: 0 | BS58: 1 | BT58: 1 | BU58: 1 | BV58: 1 | BW58: 1 | BX58: 1 | BZ58: 0 | CA58: 0 | CE58: 1566 | CF58: 0 | CG58: 0 | CM58: 0 | CO58: 0 | CP58: =(P58+Q58+S58) -> 479.67 | CQ58: =ROUND((ROUND((AC58*1),2)*BC58),2) -> 159.89 | CR58: =(ROUND((ROUND(((ET58)*AV58*1),2)*BB58),2)+ROUND((ROUND(((AE58-(EU58))*AV58*1),2)*BS58),2)) -> 0 | CS58: =(ROUND((ROUND(((EU58)*AV58*1),2)*BS58),2)+ROUND((ROUND(((AE58-(EU58))*AV58*1),2)*BS58),2)) -> 0 | CT58: =ROUND((ROUND((AF58*AV58*1),2)*BA58),2) -> 0 | CU58: =AG58 -> 0 | CV58: =(AH58*AV58) -> 0 | CW58: =AI58 -> 0 | CX58: =AJ58 -> 0 | CY58: =(ROUND((((S58+ROUND((ROUND(((EU58)*AV58*1),2)*BS58),2))*AT58)/100),2)+ROUND(((ROUND((ROUND(((AE58-(EU58))*AV58*1),2)*BS58),2)*AT58)/100),2)) -> 0 | CZ58: =(ROUND((((S58+ROUND((ROUND(((EU58)*AV58*1),2)*BS58),2))*AU58)/100),2)+ROUND(((ROUND((ROUND(((AE58-(EU58))*AV58*1),2)*BS58),2)*AU58)/100),2)) -> 0 | DN58: 0 | DO58: 0 | DP58: 1 | DQ58: 1 | DU58: 1013 | DV58: ШТ | DW58: ШТ | DX58: 1 | EE58: 60088638 | EF58: 130 | EG58: Сметная стоимость оборудования | EH58: 0 | EJ58: 3 | EK58: 746 | EL58: ТСН-2001.13. Сметная стоимость оборудования | EM58: ТСН-2001.13 | EQ58: 0 | ER58: 0 | ES58: 159.89 | ET58: 0 | EU58: 0 | EV58: 0 | EW58: 0 | EX58: 0 | EY58: 0 | FQ58: 0 | FR58: =P58 -> 479.67 | FS58: 0 | FX58: 0 | FY58: 0 | GA58: [1 410 / 1,2 / 7,66] + 3% Трансп + 1,2% Заг.скл | GD58: 1 | GF58: 680371573 | GG58: 2 | GH58: 4 | GI58: -2 | GJ58: 0 | GK58: 0 | GL58: =ROUND(IF(AND(BH58=3,BI58=3,FS58<>0),P58,0),2) -> 0 | GM58: =ROUND(O58+X58+Y58,2)+GX58 -> 479.67 | GN58: =IF(OR(BI58=0,BI58=1),GM58-GX58,0) -> 0 | GO58: =IF(BI58=2,GM58-GX58,0) -> 0 | GP58: =IF(BI58=4,GM58-GX58,0) -> 0 | GR58: 0 | GS58: 2 | GT58: 0 | GV58: =ROUND((GT58),6) -> 0 | GW58: 1 | GX58: =ROUND(HC58*I58,2) -> 0 | HA58: 0 | HB58: 0 | HC58: =GV58*GW58 -> 0 | HE58: 3 | HF58: 1,2 | HS58: 0 | IK58: 0
A59: 17 | B59: 1 | E59: 16 | F59: КА-9 | G59: Аккумултор 12В 7Ач DTM 1207 | H59: ШТ | I59: 3 | J59: 0 | K59: 3 | O59: =ROUND(CP59,2) -> 3674.27 | P59: =ROUND((ROUND((AC59*I59),2)*BC59),2) -> 3674.27 | Q59: =(ROUND((ROUND(((ET59)*AV59*I59),2)*BB59),2)+ROUND((ROUND(((AE59-(EU59))*AV59*I59),2)*BS59),2)) -> 0 | R59: =(ROUND((ROUND(((EU59)*AV59*I59),2)*BS59),2)+ROUND((ROUND(((AE59-(EU59))*AV59*I59),2)*BS59),2)) -> 0 | S59: =ROUND((ROUND((AF59*AV59*I59),2)*BA59),2) -> 0 | T59: =ROUND(CU59*I59,2) -> 0 | U59: =CV59*I59 -> 0 | V59: =CW59*I59 -> 0 | W59: =ROUND(CX59*I59,2) -> 0 | X59: =(ROUND((((S59+ROUND((ROUND(((EU59)*AV59*I59),2)*BS59),2))*AT59)/100),2)+ROUND(((ROUND((ROUND(((AE59-(EU59))*AV59*I59),2)*BS59),2)*AT59)/100),2)) -> 0 | Y59: =(ROUND((((S59+ROUND((ROUND(((EU59)*AV59*I59),2)*BS59),2))*AU59)/100),2)+ROUND(((ROUND((ROUND(((AE59-(EU59))*AV59*I59),2)*BS59),2)*AU59)/100),2)) -> 0 | AA59: 60258618 | AB59: =ROUND((AC59+AD59+AF59),6) -> 159.89 | AC59: =ROUND((ES59),6) -> 159.89 | AD59: =ROUND((((ET59)-(EU59))+AE59),6) -> 0 | AE59: =ROUND((EU59),6) -> 0 | AF59: =ROUND((EV59),6) -> 0 | AG59: =ROUND((AP59),6) -> 0 | AH59: =(EW59) -> 0 | AI59: =(EX59) -> 0 | AJ59: =(AS59) -> 0 | AK59: 159.89 | AL59: 159.89 | AM59: 0 | AN59: 0 | AO59: 0 | AP59: 0 | AQ59: 0 | AR59: 0 | AS59: 0 | AT59: 0 | AU59: 0 | AV59: 1 | AW59: 1 | AZ59: 1 | BA59: 1 | BB59: 1 | BC59: 7.66 | BH59: 3 | BI59: 3 | BM59: 746 | BN59: 0 | BP59: 0 | BQ59: 130 | BR59: 0 | BS59: 1 | BT59: 1 | BU59: 1 | BV59: 1 | BW59: 1 | BX59: 1 | BZ59: 0 | CA59: 0 | CE59: 1566 | CF59: 0 | CG59: 0 | CM59: 0 | CO59: 0 | CP59: =(P59+Q59+S59) -> 3674.27 | CQ59: =ROUND((ROUND((AC59*1),2)*BC59),2) -> 1224.76 | CR59: =(ROUND((ROUND(((ET59)*AV59*1),2)*BB59),2)+ROUND((ROUND(((AE59-(EU59))*AV59*1),2)*BS59),2)) -> 0 | CS59: =(ROUND((ROUND(((EU59)*AV59*1),2)*BS59),2)+ROUND((ROUND(((AE59-(EU59))*AV59*1),2)*BS59),2)) -> 0 | CT59: =ROUND((ROUND((AF59*AV59*1),2)*BA59),2) -> 0 | CU59: =AG59 -> 0 | CV59: =(AH59*AV59) -> 0 | CW59: =AI59 -> 0 | CX59: =AJ59 -> 0 | CY59: =(ROUND((((S59+ROUND((ROUND(((EU59)*AV59*1),2)*BS59),2))*AT59)/100),2)+ROUND(((ROUND((ROUND(((AE59-(EU59))*AV59*1),2)*BS59),2)*AT59)/100),2)) -> 0 | CZ59: =(ROUND((((S59+ROUND((ROUND(((EU59)*AV59*1),2)*BS59),2))*AU59)/100),2)+ROUND(((ROUND((ROUND(((AE59-(EU59))*AV59*1),2)*BS59),2)*AU59)/100),2)) -> 0 | DN59: 0 | DO59: 0 | DP59: 1 | DQ59: 1 | DU59: 1013 | DV59: ШТ | DW59: ШТ | DX59: 1 | EE59: 60088638 | EF59: 130 | EG59: Сметная стоимость оборудования | EH59: 0 | EJ59: 3 | EK59: 746 | EL59: ТСН-2001.13. Сметная стоимость оборудования | EM59: ТСН-2001.13 | EQ59: 0 | ER59: 0 | ES59: 159.89 | ET59: 0 | EU59: 0 | EV59: 0 | EW59: 0 | EX59: 0 | EY59: 0 | EZ59: 5 | FC59: 1 | FD59: 18 | FF59: 1410 | FQ59: 0 | FR59: =P59 -> 3674.27 | FS59: 0 | FX59: 0 | FY59: 0 | GA59: [1 410 / 1,2 / 7,66] + 3% Трансп + 1,2% Заг.скл | GD59: 1 | GF59: 680371573 | GG59: 2 | GH59: 3 | GI59: 5 | GJ59: 0 | GK59: 0 | GL59: =ROUND(IF(AND(BH59=3,BI59=3,FS59<>0),P59,0),2) -> 0 | GM59: =ROUND(O59+X59+Y59,2)+GX59 -> 3674.27 | GN59: =IF(OR(BI59=0,BI59=1),GM59-GX59,0) -> 0 | GO59: =IF(BI59=2,GM59-GX59,0) -> 0 | GP59: =IF(BI59=4,GM59-GX59,0) -> 0 | GR59: 1 | GS59: 1 | GT59: 0 | GV59: =ROUND((GT59),6) -> 0 | GW59: 1 | GX59: =ROUND(HC59*I59,2) -> 0 | HA59: 0 | HB59: 0 | HC59: =GV59*GW59 -> 0 | HE59: 3 | HF59: 1,2 | HS59: 0 | IK59: 0
A60: 17 | B60: 1 | C60: =ROW(SmtRes!A35) -> 35 | D60: =ROW(EtalonRes!A43) -> 43 | E60: 17 | F60: 4.10-80-13 | G60: Аппараты приемные, устройства промежуточные на 1 луч | H60: 1 ШТ. | I60: 1 | J60: 0 | K60: 1 | O60: =ROUND(CP60,2) -> 20.53 | P60: =ROUND((ROUND((AC60*AW60*I60),2)*BC60),2) -> 1.96 | Q60: =(ROUND((ROUND((((ET60*1.1))*AV60*I60),2)*BB60),2)+ROUND((ROUND(((AE60-((EU60*1.1)))*AV60*I60),2)*BS60),2)) -> 0.06 | R60: =(ROUND((ROUND((((EU60*1.1))*AV60*I60),2)*BS60),2)+ROUND((ROUND(((AE60-((EU60*1.1)))*AV60*I60),2)*BS60),2)) -> 0.01 | S60: =ROUND((ROUND((AF60*AV60*I60),2)*BA60),2) -> 18.51 | T60: =ROUND(CU60*I60,2) -> 0 | U60: =CV60*I60 -> 1.38204 | V60: =CW60*I60 -> 0 | W60: =ROUND(CX60*I60,2) -> 0 | X60: =(ROUND((((S60+ROUND((ROUND((((EU60*1.1))*AV60*I60),2)*BS60),2))*AT60)/100),2)+ROUND(((ROUND((ROUND(((AE60-((EU60*1.1)))*AV60*I60),2)*BS60),2)*AT60)/100),2)) -> 16.67 | Y60: =(ROUND((((S60+ROUND((ROUND((((EU60*1.1))*AV60*I60),2)*BS60),2))*AU60)/100),2)+ROUND(((ROUND((ROUND(((AE60-((EU60*1.1)))*AV60*I60),2)*BS60),2)*AU60)/100),2)) -> 8.52 | AA60: 60258621 | AB60: =ROUND((AC60+AD60+AF60),6) -> 19.692 | AC60: =ROUND(((ES60*1)),6) -> 1.96 | AD60: =ROUND(((((ET60*1.1))-((EU60*1.1)))+AE60),6) -> 0.055 | AE60: =ROUND(((EU60*1.1)),6) -> 0.011 | AF60: =ROUND(((EV60*1.1)),6) -> 17.677 | AG60: =ROUND((AP60),6) -> 0 | AH60: =((EW60*1.1)) -> 1.32 | AI60: =((EX60*1.1)) -> 0 | AJ60: =(AS60) -> 0 | AK60: 18.08 | AL60: 1.96 | AM60: 0.05 | AN60: 0.01 | AO60: 16.07 | AP60: 0 | AQ60: 1.2 | AR60: 0 | AS60: 0 | AT60: 90 | AU60: 46 | AV60: 1.047 | AW60: 1 | AZ60: 1 | BA60: 1 | BB60: 1 | BC60: 1 | BH60: 0 | BI60: 2 | BJ60: ТСН-2001.4. Доп. 1-42. Сб. 10, т. 80, поз. 13 | BM60: 68 | BN60: 58973116 | BO60: 4.10-80-13 | BP60: 1 | BQ60: 40 | BR60: 0 | BS60: 1 | BT60: 1 | BU60: 1 | BV60: 1 | BW60: 1 | BX60: 1 | BZ60: 90 | CA60: 46 | CE60: 1566 | CF60: 0 | CG60: 0 | CM60: 0 | CN60: Поправка: Гл.12.Прил.8.п.8. 5_12.00.01.11.003 Наименование: При наличии усложненных условий производства работ (стесненность, сложность складирования и транспортной логистики, наличие в зоне производства работ действующего технологического оборудования или движения технологического транспорта и т.п.) для объектов, расположенных за пределами территории круговой магистральной системы улиц "Садовое кольцо" и за пределами Третьего транспортного кольца города Москвы пунктов "а" и "б", но в пределах Московской кольцевой автомобильной дороги | CO60: 0 | CP60: =(P60+Q60+S60) -> 20.53 | CQ60: =ROUND((ROUND((AC60*AW60*1),2)*BC60),2) -> 1.96 | CR60: =(ROUND((ROUND((((ET60*1.1))*AV60*1),2)*BB60),2)+ROUND((ROUND(((AE60-((EU60*1.1)))*AV60*1),2)*BS60),2)) -> 0.06 | CS60: =(ROUND((ROUND((((EU60*1.1))*AV60*1),2)*BS60),2)+ROUND((ROUND(((AE60-((EU60*1.1)))*AV60*1),2)*BS60),2)) -> 0.01 | CT60: =ROUND((ROUND((AF60*AV60*1),2)*BA60),2) -> 18.51 | CU60: =AG60 -> 0 | CV60: =(AH60*AV60) -> 1.38204 | CW60: =AI60 -> 0 | CX60: =AJ60 -> 0 | CY60: =(ROUND((((S60+ROUND((ROUND((((EU60*1.1))*AV60*1),2)*BS60),2))*AT60)/100),2)+ROUND(((ROUND((ROUND(((AE60-((EU60*1.1)))*AV60*1),2)*BS60),2)*AT60)/100),2)) -> 16.67 | CZ60: =(ROUND((((S60+ROUND((ROUND((((EU60*1.1))*AV60*1),2)*BS60),2))*AU60)/100),2)+ROUND(((ROUND((ROUND(((AE60-((EU60*1.1)))*AV60*1),2)*BS60),2)*AU60)/100),2)) -> 8.52 | DB60: 15 | DD60: *1 | DE60: *1,1 | DF60: *1,1 | DG60: *1,1 | DI60: *1,1 | DJ60: *1,1 | DN60: 0 | DO60: 0 | DP60: 1 | DQ60: 1 | DU60: 1013 | DV60: 1 ШТ. | DW60: 1 ШТ. | DX60: 1 | EE60: 60088532 | EF60: 40 | EG60: Монтаж оборудования | EH60: 0 | EJ60: 2 | EK60: 68 | EL60: ТСН-2001.4-10. Прокладка и монтаж сетей связи | EM60: ТСН-2001.4-10-1 | EO60: Поправка: Гл.12.Прил.8.п.8. 5_12.00.01.11.003 | EQ60: 0 | ER60: 18.08 | ES60: 1.96 | ET60: 0.05 | EU60: 0.01 | EV60: 16.07 | EW60: 1.2 | EX60: 0 | EY60: 0 | FQ60: 0 | FR60: 0 | FS60: 0 | FX60: 90 | FY60: 46 | GD60: 1 | GF60: 1665592289 | GG60: 2 | GH60: 1 | GI60: 2 | GJ60: 0 | GK60: 0 | GL60: =ROUND(IF(AND(BH60=3,BI60=3,FS60<>0),P60,0),2) -> 0 | GM60: =ROUND(O60+X60+Y60,2)+GX60 -> 45.72 | GN60: =IF(OR(BI60=0,BI60=1),GM60-GX60,0) -> 0 | GO60: =IF(BI60=2,GM60-GX60,0) -> 45.72 | GP60: =IF(BI60=4,GM60-GX60,0) -> 0 | GR60: 0 | GS60: 3 | GT60: 0 | GV60: =ROUND((GT60),6) -> 0 | GW60: 1 | GX60: =ROUND(HC60*I60,2) -> 0 | HA60: 0 | HB60: 0 | HC60: =GV60*GW60 -> 0 | HS60: 0 | IK60: 0
A61: 17 | B61: 1 | C61: =ROW(SmtRes!A36) -> 36 | D61: =ROW(EtalonRes!A44) -> 44 | E61: 17 | F61: 4.10-80-13 | G61: Аппараты приемные, устройства промежуточные на 1 луч | H61: 1 ШТ. | I61: 1 | J61: 0 | K61: 1 | O61: =ROUND(CP61,2) -> 1038.38 | P61: =ROUND((ROUND((AC61*AW61*I61),2)*BC61),2) -> 19.38 | Q61: =(ROUND((ROUND((((ET61*1.1))*AV61*I61),2)*BB61),2)+ROUND((ROUND(((AE61-((EU61*1.1)))*AV61*I61),2)*BS61),2)) -> 1.14 | R61: =(ROUND((ROUND((((EU61*1.1))*AV61*I61),2)*BS61),2)+ROUND((ROUND(((AE61-((EU61*1.1)))*AV61*I61),2)*BS61),2)) -> 0.55 | S61: =ROUND((ROUND((AF61*AV61*I61),2)*BA61),2) -> 1017.86 | T61: =ROUND(CU61*I61,2) -> 0 | U61: =CV61*I61 -> 1.38204 | V61: =CW61*I61 -> 0 | W61: =ROUND(CX61*I61,2) -> 0 | X61: =(ROUND((((S61+ROUND((ROUND((((EU61*1.1))*AV61*I61),2)*BS61),2))*AT61)/100),2)+ROUND(((ROUND((ROUND(((AE61-((EU61*1.1)))*AV61*I61),2)*BS61),2)*AT61)/100),2)) -> 916.57 | Y61: =(ROUND((((S61+ROUND((ROUND((((EU61*1.1))*AV61*I61),2)*BS61),2))*AU61)/100),2)+ROUND(((ROUND((ROUND(((AE61-((EU61*1.1)))*AV61*I61),2)*BS61),2)*AU61)/100),2)) -> 468.47 | AA61: 60258618 | AB61: =ROUND((AC61+AD61+AF61),6) -> 19.692 | AC61: =ROUND(((ES61*1)),6) -> 1.96 | AD61: =ROUND(((((ET61*1.1))-((EU61*1.1)))+AE61),6) -> 0.055 | AE61: =ROUND(((EU61*1.1)),6) -> 0.011 | AF61: =ROUND(((EV61*1.1)),6) -> 17.677 | AG61: =ROUND((AP61),6) -> 0 | AH61: =((EW61*1.1)) -> 1.32 | AI61: =((EX61*1.1)) -> 0 | AJ61: =(AS61) -> 0 | AK61: 18.08 | AL61: 1.96 | AM61: 0.05 | AN61: 0.01 | AO61: 16.07 | AP61: 0 | AQ61: 1.2 | AR61: 0 | AS61: 0 | AT61: 90 | AU61: 46 | AV61: 1.047 | AW61: 1 | AZ61: 1 | BA61: 54.99 | BB61: 19 | BC61: 9.89 | BH61: 0 | BI61: 2 | BJ61: ТСН-2001.4. Доп. 1-42. Сб. 10, т. 80, поз. 13 | BM61: 68 | BN61: 58973116 | BO61: 4.10-80-13 | BP61: 1 | BQ61: 40 | BR61: 0 | BS61: 54.99 | BT61: 1 | BU61: 1 | BV61: 1 | BW61: 1 | BX61: 1 | BZ61: 90 | CA61: 46 | CE61: 1566 | CF61: 0 | CG61: 0 | CM61: 0 | CN61: Поправка: Гл.12.Прил.8.п.8. 5_12.00.01.11.003 Наименование: При наличии усложненных условий производства работ (стесненность, сложность складирования и транспортной логистики, наличие в зоне производства работ действующего технологического оборудования или движения технологического транспорта и т.п.) для объектов, расположенных за пределами территории круговой магистральной системы улиц "Садовое кольцо" и за пределами Третьего транспортного кольца города Москвы пунктов "а" и "б", но в пределах Московской кольцевой автомобильной дороги | CO61: 0 | CP61: =(P61+Q61+S61) -> 1038.38 | CQ61: =ROUND((ROUND((AC61*AW61*1),2)*BC61),2) -> 19.38 | CR61: =(ROUND((ROUND((((ET61*1.1))*AV61*1),2)*BB61),2)+ROUND((ROUND(((AE61-((EU61*1.1)))*AV61*1),2)*BS61),2)) -> 1.14 | CS61: =(ROUND((ROUND((((EU61*1.1))*AV61*1),2)*BS61),2)+ROUND((ROUND(((AE61-((EU61*1.1)))*AV61*1),2)*BS61),2)) -> 0.55 | CT61: =ROUND((ROUND((AF61*AV61*1),2)*BA61),2) -> 1017.86 | CU61: =AG61 -> 0 | CV61: =(AH61*AV61) -> 1.38204 | CW61: =AI61 -> 0 | CX61: =AJ61 -> 0 | CY61: =(ROUND((((S61+ROUND((ROUND((((EU61*1.1))*AV61*1),2)*BS61),2))*AT61)/100),2)+ROUND(((ROUND((ROUND(((AE61-((EU61*1.1)))*AV61*1),2)*BS61),2)*AT61)/100),2)) -> 916.57 | CZ61: =(ROUND((((S61+ROUND((ROUND((((EU61*1.1))*AV61*1),2)*BS61),2))*AU61)/100),2)+ROUND(((ROUND((ROUND(((AE61-((EU61*1.1)))*AV61*1),2)*BS61),2)*AU61)/100),2)) -> 468.47 | DB61: 16 | DD61: *1 | DE61: *1,1 | DF61: *1,1 | DG61: *1,1 | DI61: *1,1 | DJ61: *1,1 | DN61: 0 | DO61: 0 | DP61: 1 | DQ61: 1 | DU61: 1013 | DV61: 1 ШТ. | DW61: 1 ШТ. | DX61: 1 | EE61: 60088532 | EF61: 40 | EG61: Монтаж оборудования | EH61: 0 | EJ61: 2 | EK61: 68 | EL61: ТСН-2001.4-10. Прокладка и монтаж сетей связи | EM61: ТСН-2001.4-10-1 | EO61: Поправка: Гл.12.Прил.8.п.8. 5_12.00.01.11.003 | EQ61: 0 | ER61: 18.08 | ES61: 1.96 | ET61: 0.05 | EU61: 0.01 | EV61: 16.07 | EW61: 1.2 | EX61: 0 | EY61: 0 | FQ61: 0 | FR61: 0 | FS61: 0 | FX61: 90 | FY61: 46 | GD61: 1 | GF61: 1665592289 | GG61: 2 | GH61: 1 | GI61: 2 | GJ61: 0 | GK61: 0 | GL61: =ROUND(IF(AND(BH61=3,BI61=3,FS61<>0),P61,0),2) -> 0 | GM61: =ROUND(O61+X61+Y61,2)+GX61 -> 2423.42 | GN61: =IF(OR(BI61=0,BI61=1),GM61-GX61,0) -> 0 | GO61: =IF(BI61=2,GM61-GX61,0) -> 2423.42 | GP61: =IF(BI61=4,GM61-GX61,0) -> 0 | GR61: 0 | GS61: 3 | GT61: 0 | GV61: =ROUND((GT61),6) -> 0 | GW61: 1 | GX61: =ROUND(HC61*I61,2) -> 0 | HA61: 0 | HB61: 0 | HC61: =GV61*GW61 -> 0 | HS61: 0 | IK61: 0
A62: 17 | B62: 1 | E62: 18 | F62: КА-10 | G62: Адресный релейный модуль РМ-1-R3 Рубеж | H62: ШТ | I62: 1 | J62: 0 | K62: 1 | O62: =ROUND(CP62,2) -> 159.15 | P62: =ROUND((ROUND((AC62*I62),2)*BC62),2) -> 159.15 | Q62: =(ROUND((ROUND(((ET62)*AV62*I62),2)*BB62),2)+ROUND((ROUND(((AE62-(EU62))*AV62*I62),2)*BS62),2)) -> 0 | R62: =(ROUND((ROUND(((EU62)*AV62*I62),2)*BS62),2)+ROUND((ROUND(((AE62-(EU62))*AV62*I62),2)*BS62),2)) -> 0 | S62: =ROUND((ROUND((AF62*AV62*I62),2)*BA62),2) -> 0 | T62: =ROUND(CU62*I62,2) -> 0 | U62: =CV62*I62 -> 0 | V62: =CW62*I62 -> 0 | W62: =ROUND(CX62*I62,2) -> 0 | X62: =(ROUND((((S62+ROUND((ROUND(((EU62)*AV62*I62),2)*BS62),2))*AT62)/100),2)+ROUND(((ROUND((ROUND(((AE62-(EU62))*AV62*I62),2)*BS62),2)*AT62)/100),2)) -> 0 | Y62: =(ROUND((((S62+ROUND((ROUND(((EU62)*AV62*I62),2)*BS62),2))*AU62)/100),2)+ROUND(((ROUND((ROUND(((AE62-(EU62))*AV62*I62),2)*BS62),2)*AU62)/100),2)) -> 0 | AA62: 60258621 | AB62: =ROUND((AC62+AD62+AF62),6) -> 159.15 | AC62: =ROUND((ES62),6) -> 159.15 | AD62: =ROUND((((ET62)-(EU62))+AE62),6) -> 0 | AE62: =ROUND((EU62),6) -> 0 | AF62: =ROUND((EV62),6) -> 0 | AG62: =ROUND((AP62),6) -> 0 | AH62: =(EW62) -> 0 | AI62: =(EX62) -> 0 | AJ62: =(AS62) -> 0 | AK62: 159.15 | AL62: 159.15 | AM62: 0 | AN62: 0 | AO62: 0 | AP62: 0 | AQ62: 0 | AR62: 0 | AS62: 0 | AT62: 0 | AU62: 0 | AV62: 1 | AW62: 1 | AZ62: 1 | BA62: 1 | BB62: 1 | BC62: 1 | BH62: 3 | BI62: 3 | BM62: 746 | BN62: 0 | BP62: 0 | BQ62: 130 | BR62: 0 | BS62: 1 | BT62: 1 | BU62: 1 | BV62: 1 | BW62: 1 | BX62: 1 | BZ62: 0 | CA62: 0 | CE62: 1566 | CF62: 0 | CG62: 0 | CM62: 0 | CO62: 0 | CP62: =(P62+Q62+S62) -> 159.15 | CQ62: =ROUND((ROUND((AC62*1),2)*BC62),2) -> 159.15 | CR62: =(ROUND((ROUND(((ET62)*AV62*1),2)*BB62),2)+ROUND((ROUND(((AE62-(EU62))*AV62*1),2)*BS62),2)) -> 0 | CS62: =(ROUND((ROUND(((EU62)*AV62*1),2)*BS62),2)+ROUND((ROUND(((AE62-(EU62))*AV62*1),2)*BS62),2)) -> 0 | CT62: =ROUND((ROUND((AF62*AV62*1),2)*BA62),2) -> 0 | CU62: =AG62 -> 0 | CV62: =(AH62*AV62) -> 0 | CW62: =AI62 -> 0 | CX62: =AJ62 -> 0 | CY62: =(ROUND((((S62+ROUND((ROUND(((EU62)*AV62*1),2)*BS62),2))*AT62)/100),2)+ROUND(((ROUND((ROUND(((AE62-(EU62))*AV62*1),2)*BS62),2)*AT62)/100),2)) -> 0 | CZ62: =(ROUND((((S62+ROUND((ROUND(((EU62)*AV62*1),2)*BS62),2))*AU62)/100),2)+ROUND(((ROUND((ROUND(((AE62-(EU62))*AV62*1),2)*BS62),2)*AU62)/100),2)) -> 0 | DN62: 0 | DO62: 0 | DP62: 1 | DQ62: 1 | DU62: 1013 | DV62: ШТ | DW62: ШТ | DX62: 1 | EE62: 60088638 | EF62: 130 | EG62: Сметная стоимость оборудования | EH62: 0 | EJ62: 3 | EK62: 746 | EL62: ТСН-2001.13. Сметная стоимость оборудования | EM62: ТСН-2001.13 | EQ62: 0 | ER62: 0 | ES62: 159.15 | ET62: 0 | EU62: 0 | EV62: 0 | EW62: 0 | EX62: 0 | EY62: 0 | FQ62: 0 | FR62: =P62 -> 159.15 | FS62: 0 | FX62: 0 | FY62: 0 | GA62: [1 403,46 / 1,2 / 7,66] + 3% Трансп + 1,2% Заг.скл | GD62: 1 | GF62: -568813654 | GG62: 2 | GH62: 4 | GI62: -2 | GJ62: 0 | GK62: 0 | GL62: =ROUND(IF(AND(BH62=3,BI62=3,FS62<>0),P62,0),2) -> 0 | GM62: =ROUND(O62+X62+Y62,2)+GX62 -> 159.15 | GN62: =IF(OR(BI62=0,BI62=1),GM62-GX62,0) -> 0 | GO62: =IF(BI62=2,GM62-GX62,0) -> 0 | GP62: =IF(BI62=4,GM62-GX62,0) -> 0 | GR62: 0 | GS62: 2 | GT62: 0 | GV62: =ROUND((GT62),6) -> 0 | GW62: 1 | GX62: =ROUND(HC62*I62,2) -> 0 | HA62: 0 | HB62: 0 | HC62: =GV62*GW62 -> 0 | HE62: 3 | HF62: 1,2 | HS62: 0 | IK62: 0
A63: 17 | B63: 1 | E63: 18 | F63: КА-10 | G63: Адресный релейный модуль РМ-1-R3 Рубеж | H63: ШТ | I63: 1 | J63: 0 | K63: 1 | O63: =ROUND(CP63,2) -> 1219.09 | P63: =ROUND((ROUND((AC63*I63),2)*BC63),2) -> 1219.09 | Q63: =(ROUND((ROUND(((ET63)*AV63*I63),2)*BB63),2)+ROUND((ROUND(((AE63-(EU63))*AV63*I63),2)*BS63),2)) -> 0 | R63: =(ROUND((ROUND(((EU63)*AV63*I63),2)*BS63),2)+ROUND((ROUND(((AE63-(EU63))*AV63*I63),2)*BS63),2)) -> 0 | S63: =ROUND((ROUND((AF63*AV63*I63),2)*BA63),2) -> 0 | T63: =ROUND(CU63*I63,2) -> 0 | U63: =CV63*I63 -> 0 | V63: =CW63*I63 -> 0 | W63: =ROUND(CX63*I63,2) -> 0 | X63: =(ROUND((((S63+ROUND((ROUND(((EU63)*AV63*I63),2)*BS63),2))*AT63)/100),2)+ROUND(((ROUND((ROUND(((AE63-(EU63))*AV63*I63),2)*BS63),2)*AT63)/100),2)) -> 0 | Y63: =(ROUND((((S63+ROUND((ROUND(((EU63)*AV63*I63),2)*BS63),2))*AU63)/100),2)+ROUND(((ROUND((ROUND(((AE63-(EU63))*AV63*I63),2)*BS63),2)*AU63)/100),2)) -> 0 | AA63: 60258618 | AB63: =ROUND((AC63+AD63+AF63),6) -> 159.15 | AC63: =ROUND((ES63),6) -> 159.15 | AD63: =ROUND((((ET63)-(EU63))+AE63),6) -> 0 | AE63: =ROUND((EU63),6) -> 0 | AF63: =ROUND((EV63),6) -> 0 | AG63: =ROUND((AP63),6) -> 0 | AH63: =(EW63) -> 0 | AI63: =(EX63) -> 0 | AJ63: =(AS63) -> 0 | AK63: 159.15 | AL63: 159.15 | AM63: 0 | AN63: 0 | AO63: 0 | AP63: 0 | AQ63: 0 | AR63: 0 | AS63: 0 | AT63: 0 | AU63: 0 | AV63: 1 | AW63: 1 | AZ63: 1 | BA63: 1 | BB63: 1 | BC63: 7.66 | BH63: 3 | BI63: 3 | BM63: 746 | BN63: 0 | BP63: 0 | BQ63: 130 | BR63: 0 | BS63: 1 | BT63: 1 | BU63: 1 | BV63: 1 | BW63: 1 | BX63: 1 | BZ63: 0 | CA63: 0 | CE63: 1566 | CF63: 0 | CG63: 0 | CM63: 0 | CO63: 0 | CP63: =(P63+Q63+S63) -> 1219.09 | CQ63: =ROUND((ROUND((AC63*1),2)*BC63),2) -> 1219.09 | CR63: =(ROUND((ROUND(((ET63)*AV63*1),2)*BB63),2)+ROUND((ROUND(((AE63-(EU63))*AV63*1),2)*BS63),2)) -> 0 | CS63: =(ROUND((ROUND(((EU63)*AV63*1),2)*BS63),2)+ROUND((ROUND(((AE63-(EU63))*AV63*1),2)*BS63),2)) -> 0 | CT63: =ROUND((ROUND((AF63*AV63*1),2)*BA63),2) -> 0 | CU63: =AG63 -> 0 | CV63: =(AH63*AV63) -> 0 | CW63: =AI63 -> 0 | CX63: =AJ63 -> 0 | CY63: =(ROUND((((S63+ROUND((ROUND(((EU63)*AV63*1),2)*BS63),2))*AT63)/100),2)+ROUND(((ROUND((ROUND(((AE63-(EU63))*AV63*1),2)*BS63),2)*AT63)/100),2)) -> 0 | CZ63: =(ROUND((((S63+ROUND((ROUND(((EU63)*AV63*1),2)*BS63),2))*AU63)/100),2)+ROUND(((ROUND((ROUND(((AE63-(EU63))*AV63*1),2)*BS63),2)*AU63)/100),2)) -> 0 | DN63: 0 | DO63: 0 | DP63: 1 | DQ63: 1 | DU63: 1013 | DV63: ШТ | DW63: ШТ | DX63: 1 | EE63: 60088638 | EF63: 130 | EG63: Сметная стоимость оборудования | EH63: 0 | EJ63: 3 | EK63: 746 | EL63: ТСН-2001.13. Сметная стоимость оборудования | EM63: ТСН-2001.13 | EQ63: 0 | ER63: 0 | ES63: 159.15 | ET63: 0 | EU63: 0 | EV63: 0 | EW63: 0 | EX63: 0 | EY63: 0 | EZ63: 5 | FC63: 1 | FD63: 18 | FF63: 1403.46 | FQ63: 0 | FR63: =P63 -> 1219.09 | FS63: 0 | FX63: 0 | FY63: 0 | GA63: [1 403,46 / 1,2 / 7,66] + 3% Трансп + 1,2% Заг.скл | GD63: 1 | GF63: -568813654 | GG63: 2 | GH63: 3 | GI63: 5 | GJ63: 0 | GK63: 0 | GL63: =ROUND(IF(AND(BH63=3,BI63=3,FS63<>0),P63,0),2) -> 0 | GM63: =ROUND(O63+X63+Y63,2)+GX63 -> 1219.09 | GN63: =IF(OR(BI63=0,BI63=1),GM63-GX63,0) -> 0 | GO63: =IF(BI63=2,GM63-GX63,0) -> 0 | GP63: =IF(BI63=4,GM63-GX63,0) -> 0 | GR63: 1 | GS63: 1 | GT63: 0 | GV63: =ROUND((GT63),6) -> 0 | GW63: 1 | GX63: =ROUND(HC63*I63,2) -> 0 | HA63: 0 | HB63: 0 | HC63: =GV63*GW63 -> 0 | HE63: 3 | HF63: 1,2 | HS63: 0 | IK63: 0
A64: 17 | B64: 1 | C64: =ROW(SmtRes!A37) -> 37 | D64: =ROW(EtalonRes!A45) -> 45 | E64: 19 | F64: 4.10-80-13 | G64: Аппараты приемные, устройства промежуточные на 1 луч | H64: 1 ШТ. | I64: 2 | J64: 0 | K64: 2 | O64: =ROUND(CP64,2) -> 41.06 | P64: =ROUND((ROUND((AC64*AW64*I64),2)*BC64),2) -> 3.92 | Q64: =(ROUND((ROUND((((ET64*1.1))*AV64*I64),2)*BB64),2)+ROUND((ROUND(((AE64-((EU64*1.1)))*AV64*I64),2)*BS64),2)) -> 0.12 | R64: =(ROUND((ROUND((((EU64*1.1))*AV64*I64),2)*BS64),2)+ROUND((ROUND(((AE64-((EU64*1.1)))*AV64*I64),2)*BS64),2)) -> 0.02 | S64: =ROUND((ROUND((AF64*AV64*I64),2)*BA64),2) -> 37.02 | T64: =ROUND(CU64*I64,2) -> 0 | U64: =CV64*I64 -> 2.76408 | V64: =CW64*I64 -> 0 | W64: =ROUND(CX64*I64,2) -> 0 | X64: =(ROUND((((S64+ROUND((ROUND((((EU64*1.1))*AV64*I64),2)*BS64),2))*AT64)/100),2)+ROUND(((ROUND((ROUND(((AE64-((EU64*1.1)))*AV64*I64),2)*BS64),2)*AT64)/100),2)) -> 33.34 | Y64: =(ROUND((((S64+ROUND((ROUND((((EU64*1.1))*AV64*I64),2)*BS64),2))*AU64)/100),2)+ROUND(((ROUND((ROUND(((AE64-((EU64*1.1)))*AV64*I64),2)*BS64),2)*AU64)/100),2)) -> 17.04 | AA64: 60258621 | AB64: =ROUND((AC64+AD64+AF64),6) -> 19.692 | AC64: =ROUND(((ES64*1)),6) -> 1.96 | AD64: =ROUND(((((ET64*1.1))-((EU64*1.1)))+AE64),6) -> 0.055 | AE64: =ROUND(((EU64*1.1)),6) -> 0.011 | AF64: =ROUND(((EV64*1.1)),6) -> 17.677 | AG64: =ROUND((AP64),6) -> 0 | AH64: =((EW64*1.1)) -> 1.32 | AI64: =((EX64*1.1)) -> 0 | AJ64: =(AS64) -> 0 | AK64: 18.08 | AL64: 1.96 | AM64: 0.05 | AN64: 0.01 | AO64: 16.07 | AP64: 0 | AQ64: 1.2 | AR64: 0 | AS64: 0 | AT64: 90 | AU64: 46 | AV64: 1.047 | AW64: 1 | AZ64: 1 | BA64: 1 | BB64: 1 | BC64: 1 | BH64: 0 | BI64: 2 | BJ64: ТСН-2001.4. Доп. 1-42. Сб. 10, т. 80, поз. 13 | BM64: 68 | BN64: 58973116 | BO64: 4.10-80-13 | BP64: 1 | BQ64: 40 | BR64: 0 | BS64: 1 | BT64: 1 | BU64: 1 | BV64: 1 | BW64: 1 | BX64: 1 | BZ64: 90 | CA64: 46 | CE64: 1566 | CF64: 0 | CG64: 0 | CM64: 0 | CN64: Поправка: Гл.12.Прил.8.п.8. 5_12.00.01.11.003 Наименование: При наличии усложненных условий производства работ (стесненность, сложность складирования и транспортной логистики, наличие в зоне производства работ действующего технологического оборудования или движения технологического транспорта и т.п.) для объектов, расположенных за пределами территории круговой магистральной системы улиц "Садовое кольцо" и за пределами Третьего транспортного кольца города Москвы пунктов "а" и "б", но в пределах Московской кольцевой автомобильной дороги | CO64: 0 | CP64: =(P64+Q64+S64) -> 41.06 | CQ64: =ROUND((ROUND((AC64*AW64*1),2)*BC64),2) -> 1.96 | CR64: =(ROUND((ROUND((((ET64*1.1))*AV64*1),2)*BB64),2)+ROUND((ROUND(((AE64-((EU64*1.1)))*AV64*1),2)*BS64),2)) -> 0.06 | CS64: =(ROUND((ROUND((((EU64*1.1))*AV64*1),2)*BS64),2)+ROUND((ROUND(((AE64-((EU64*1.1)))*AV64*1),2)*BS64),2)) -> 0.01 | CT64: =ROUND((ROUND((AF64*AV64*1),2)*BA64),2) -> 18.51 | CU64: =AG64 -> 0 | CV64: =(AH64*AV64) -> 1.38204 | CW64: =AI64 -> 0 | CX64: =AJ64 -> 0 | CY64: =(ROUND((((S64+ROUND((ROUND((((EU64*1.1))*AV64*1),2)*BS64),2))*AT64)/100),2)+ROUND(((ROUND((ROUND(((AE64-((EU64*1.1)))*AV64*1),2)*BS64),2)*AT64)/100),2)) -> 33.33 | CZ64: =(ROUND((((S64+ROUND((ROUND((((EU64*1.1))*AV64*1),2)*BS64),2))*AU64)/100),2)+ROUND(((ROUND((ROUND(((AE64-((EU64*1.1)))*AV64*1),2)*BS64),2)*AU64)/100),2)) -> 17.03 | DB64: 17 | DD64: *1 | DE64: *1,1 | DF64: *1,1 | DG64: *1,1 | DI64: *1,1 | DJ64: *1,1 | DN64: 0 | DO64: 0 | DP64: 1 | DQ64: 1 | DU64: 1013 | DV64: 1 ШТ. | DW64: 1 ШТ. | DX64: 1 | EE64: 60088532 | EF64: 40 | EG64: Монтаж оборудования | EH64: 0 | EJ64: 2 | EK64: 68 | EL64: ТСН-2001.4-10. Прокладка и монтаж сетей связи | EM64: ТСН-2001.4-10-1 | EO64: Поправка: Гл.12.Прил.8.п.8. 5_12.00.01.11.003 | EQ64: 0 | ER64: 18.08 | ES64: 1.96 | ET64: 0.05 | EU64: 0.01 | EV64: 16.07 | EW64: 1.2 | EX64: 0 | EY64: 0 | FQ64: 0 | FR64: 0 | FS64: 0 | FX64: 90 | FY64: 46 | GD64: 1 | GF64: 1665592289 | GG64: 2 | GH64: 1 | GI64: 2 | GJ64: 0 | GK64: 0 | GL64: =ROUND(IF(AND(BH64=3,BI64=3,FS64<>0),P64,0),2) -> 0 | GM64: =ROUND(O64+X64+Y64,2)+GX64 -> 91.44 | GN64: =IF(OR(BI64=0,BI64=1),GM64-GX64,0) -> 0 | GO64: =IF(BI64=2,GM64-GX64,0) -> 91.44 | GP64: =IF(BI64=4,GM64-GX64,0) -> 0 | GR64: 0 | GS64: 3 | GT64: 0 | GV64: =ROUND((GT64),6) -> 0 | GW64: 1 | GX64: =ROUND(HC64*I64,2) -> 0 | HA64: 0 | HB64: 0 | HC64: =GV64*GW64 -> 0 | HS64: 0 | IK64: 0
A65: 17 | B65: 1 | C65: =ROW(SmtRes!A38) -> 38 | D65: =ROW(EtalonRes!A46) -> 46 | E65: 19 | F65: 4.10-80-13 | G65: Аппараты приемные, устройства промежуточные на 1 луч | H65: 1 ШТ. | I65: 2 | J65: 0 | K65: 2 | O65: =ROUND(CP65,2) -> 2076.78 | P65: =ROUND((ROUND((AC65*AW65*I65),2)*BC65),2) -> 38.77 | Q65: =(ROUND((ROUND((((ET65*1.1))*AV65*I65),2)*BB65),2)+ROUND((ROUND(((AE65-((EU65*1.1)))*AV65*I65),2)*BS65),2)) -> 2.28 | R65: =(ROUND((ROUND((((EU65*1.1))*AV65*I65),2)*BS65),2)+ROUND((ROUND(((AE65-((EU65*1.1)))*AV65*I65),2)*BS65),2)) -> 1.1 | S65: =ROUND((ROUND((AF65*AV65*I65),2)*BA65),2) -> 2035.73 | T65: =ROUND(CU65*I65,2) -> 0 | U65: =CV65*I65 -> 2.76408 | V65: =CW65*I65 -> 0 | W65: =ROUND(CX65*I65,2) -> 0 | X65: =(ROUND((((S65+ROUND((ROUND((((EU65*1.1))*AV65*I65),2)*BS65),2))*AT65)/100),2)+ROUND(((ROUND((ROUND(((AE65-((EU65*1.1)))*AV65*I65),2)*BS65),2)*AT65)/100),2)) -> 1833.15 | Y65: =(ROUND((((S65+ROUND((ROUND((((EU65*1.1))*AV65*I65),2)*BS65),2))*AU65)/100),2)+ROUND(((ROUND((ROUND(((AE65-((EU65*1.1)))*AV65*I65),2)*BS65),2)*AU65)/100),2)) -> 936.94 | AA65: 60258618 | AB65: =ROUND((AC65+AD65+AF65),6) -> 19.692 | AC65: =ROUND(((ES65*1)),6) -> 1.96 | AD65: =ROUND(((((ET65*1.1))-((EU65*1.1)))+AE65),6) -> 0.055 | AE65: =ROUND(((EU65*1.1)),6) -> 0.011 | AF65: =ROUND(((EV65*1.1)),6) -> 17.677 | AG65: =ROUND((AP65),6) -> 0 | AH65: =((EW65*1.1)) -> 1.32 | AI65: =((EX65*1.1)) -> 0 | AJ65: =(AS65) -> 0 | AK65: 18.08 | AL65: 1.96 | AM65: 0.05 | AN65: 0.01 | AO65: 16.07 | AP65: 0 | AQ65: 1.2 | AR65: 0 | AS65: 0 | AT65: 90 | AU65: 46 | AV65: 1.047 | AW65: 1 | AZ65: 1 | BA65: 54.99 | BB65: 19 | BC65: 9.89 | BH65: 0 | BI65: 2 | BJ65: ТСН-2001.4. Доп. 1-42. Сб. 10, т. 80, поз. 13 | BM65: 68 | BN65: 58973116 | BO65: 4.10-80-13 | BP65: 1 | BQ65: 40 | BR65: 0 | BS65: 54.99 | BT65: 1 | BU65: 1 | BV65: 1 | BW65: 1 | BX65: 1 | BZ65: 90 | CA65: 46 | CE65: 1566 | CF65: 0 | CG65: 0 | CM65: 0 | CN65: Поправка: Гл.12.Прил.8.п.8. 5_12.00.01.11.003 Наименование: При наличии усложненных условий производства работ (стесненность, сложность складирования и транспортной логистики, наличие в зоне производства работ действующего технологического оборудования или движения технологического транспорта и т.п.) для объектов, расположенных за пределами территории круговой магистральной системы улиц "Садовое кольцо" и за пределами Третьего транспортного кольца города Москвы пунктов "а" и "б", но в пределах Московской кольцевой автомобильной дороги | CO65: 0 | CP65: =(P65+Q65+S65) -> 2076.78 | CQ65: =ROUND((ROUND((AC65*AW65*1),2)*BC65),2) -> 19.38 | CR65: =(ROUND((ROUND((((ET65*1.1))*AV65*1),2)*BB65),2)+ROUND((ROUND(((AE65-((EU65*1.1)))*AV65*1),2)*BS65),2)) -> 1.14 | CS65: =(ROUND((ROUND((((EU65*1.1))*AV65*1),2)*BS65),2)+ROUND((ROUND(((AE65-((EU65*1.1)))*AV65*1),2)*BS65),2)) -> 0.55 | CT65: =ROUND((ROUND((AF65*AV65*1),2)*BA65),2) -> 1017.86 | CU65: =AG65 -> 0 | CV65: =(AH65*AV65) -> 1.38204 | CW65: =AI65 -> 0 | CX65: =AJ65 -> 0 | CY65: =(ROUND((((S65+ROUND((ROUND((((EU65*1.1))*AV65*1),2)*BS65),2))*AT65)/100),2)+ROUND(((ROUND((ROUND(((AE65-((EU65*1.1)))*AV65*1),2)*BS65),2)*AT65)/100),2)) -> 1832.65 | CZ65: =(ROUND((((S65+ROUND((ROUND((((EU65*1.1))*AV65*1),2)*BS65),2))*AU65)/100),2)+ROUND(((ROUND((ROUND(((AE65-((EU65*1.1)))*AV65*1),2)*BS65),2)*AU65)/100),2)) -> 936.69 | DB65: 18 | DD65: *1 | DE65: *1,1 | DF65: *1,1 | DG65: *1,1 | DI65: *1,1 | DJ65: *1,1 | DN65: 0 | DO65: 0 | DP65: 1 | DQ65: 1 | DU65: 1013 | DV65: 1 ШТ. | DW65: 1 ШТ. | DX65: 1 | EE65: 60088532 | EF65: 40 | EG65: Монтаж оборудования | EH65: 0 | EJ65: 2 | EK65: 68 | EL65: ТСН-2001.4-10. Прокладка и монтаж сетей связи | EM65: ТСН-2001.4-10-1 | EO65: Поправка: Гл.12.Прил.8.п.8. 5_12.00.01.11.003 | EQ65: 0 | ER65: 18.08 | ES65: 1.96 | ET65: 0.05 | EU65: 0.01 | EV65: 16.07 | EW65: 1.2 | EX65: 0 | EY65: 0 | FQ65: 0 | FR65: 0 | FS65: 0 | FX65: 90 | FY65: 46 | GD65: 1 | GF65: 1665592289 | GG65: 2 | GH65: 1 | GI65: 2 | GJ65: 0 | GK65: 0 | GL65: =ROUND(IF(AND(BH65=3,BI65=3,FS65<>0),P65,0),2) -> 0 | GM65: =ROUND(O65+X65+Y65,2)+GX65 -> 4846.87 | GN65: =IF(OR(BI65=0,BI65=1),GM65-GX65,0) -> 0 | GO65: =IF(BI65=2,GM65-GX65,0) -> 4846.87 | GP65: =IF(BI65=4,GM65-GX65,0) -> 0 | GR65: 0 | GS65: 3 | GT65: 0 | GV65: =ROUND((GT65),6) -> 0 | GW65: 1 | GX65: =ROUND(HC65*I65,2) -> 0 | HA65: 0 | HB65: 0 | HC65: =GV65*GW65 -> 0 | HS65: 0 | IK65: 0
A66: 17 | B66: 1 | E66: 20 | F66: КА-11 | G66: Изолятор шлейфа ИЗ-1 прот. R3 | H66: ШТ | I66: 2 | J66: 0 | K66: 2 | O66: =ROUND(CP66,2) -> 154.6 | P66: =ROUND((ROUND((AC66*I66),2)*BC66),2) -> 154.6 | Q66: =(ROUND((ROUND(((ET66)*AV66*I66),2)*BB66),2)+ROUND((ROUND(((AE66-(EU66))*AV66*I66),2)*BS66),2)) -> 0 | R66: =(ROUND((ROUND(((EU66)*AV66*I66),2)*BS66),2)+ROUND((ROUND(((AE66-(EU66))*AV66*I66),2)*BS66),2)) -> 0 | S66: =ROUND((ROUND((AF66*AV66*I66),2)*BA66),2) -> 0 | T66: =ROUND(CU66*I66,2) -> 0 | U66: =CV66*I66 -> 0 | V66: =CW66*I66 -> 0 | W66: =ROUND(CX66*I66,2) -> 0 | X66: =(ROUND((((S66+ROUND((ROUND(((EU66)*AV66*I66),2)*BS66),2))*AT66)/100),2)+ROUND(((ROUND((ROUND(((AE66-(EU66))*AV66*I66),2)*BS66),2)*AT66)/100),2)) -> 0 | Y66: =(ROUND((((S66+ROUND((ROUND(((EU66)*AV66*I66),2)*BS66),2))*AU66)/100),2)+ROUND(((ROUND((ROUND(((AE66-(EU66))*AV66*I66),2)*BS66),2)*AU66)/100),2)) -> 0 | AA66: 60258621 | AB66: =ROUND((AC66+AD66+AF66),6) -> 77.3 | AC66: =ROUND((ES66),6) -> 77.3 | AD66: =ROUND((((ET66)-(EU66))+AE66),6) -> 0 | AE66: =ROUND((EU66),6) -> 0 | AF66: =ROUND((EV66),6) -> 0 | AG66: =ROUND((AP66),6) -> 0 | AH66: =(EW66) -> 0 | AI66: =(EX66) -> 0 | AJ66: =(AS66) -> 0 | AK66: 77.3 | AL66: 77.3 | AM66: 0 | AN66: 0 | AO66: 0 | AP66: 0 | AQ66: 0 | AR66: 0 | AS66: 0 | AT66: 0 | AU66: 0 | AV66: 1 | AW66: 1 | AZ66: 1 | BA66: 1 | BB66: 1 | BC66: 1 | BH66: 3 | BI66: 3 | BM66: 746 | BN66: 0 | BP66: 0 | BQ66: 130 | BR66: 0 | BS66: 1 | BT66: 1 | BU66: 1 | BV66: 1 | BW66: 1 | BX66: 1 | BZ66: 0 | CA66: 0 | CE66: 1566 | CF66: 0 | CG66: 0 | CM66: 0 | CO66: 0 | CP66: =(P66+Q66+S66) -> 154.6 | CQ66: =ROUND((ROUND((AC66*1),2)*BC66),2) -> 77.3 | CR66: =(ROUND((ROUND(((ET66)*AV66*1),2)*BB66),2)+ROUND((ROUND(((AE66-(EU66))*AV66*1),2)*BS66),2)) -> 0 | CS66: =(ROUND((ROUND(((EU66)*AV66*1),2)*BS66),2)+ROUND((ROUND(((AE66-(EU66))*AV66*1),2)*BS66),2)) -> 0 | CT66: =ROUND((ROUND((AF66*AV66*1),2)*BA66),2) -> 0 | CU66: =AG66 -> 0 | CV66: =(AH66*AV66) -> 0 | CW66: =AI66 -> 0 | CX66: =AJ66 -> 0 | CY66: =(ROUND((((S66+ROUND((ROUND(((EU66)*AV66*1),2)*BS66),2))*AT66)/100),2)+ROUND(((ROUND((ROUND(((AE66-(EU66))*AV66*1),2)*BS66),2)*AT66)/100),2)) -> 0 | CZ66: =(ROUND((((S66+ROUND((ROUND(((EU66)*AV66*1),2)*BS66),2))*AU66)/100),2)+ROUND(((ROUND((ROUND(((AE66-(EU66))*AV66*1),2)*BS66),2)*AU66)/100),2)) -> 0 | DN66: 0 | DO66: 0 | DP66: 1 | DQ66: 1 | DU66: 1013 | DV66: ШТ | DW66: ШТ | DX66: 1 | EE66: 60088638 | EF66: 130 | EG66: Сметная стоимость оборудования | EH66: 0 | EJ66: 3 | EK66: 746 | EL66: ТСН-2001.13. Сметная стоимость оборудования | EM66: ТСН-2001.13 | EQ66: 0 | ER66: 0 | ES66: 77.3 | ET66: 0 | EU66: 0 | EV66: 0 | EW66: 0 | EX66: 0 | EY66: 0 | FQ66: 0 | FR66: =P66 -> 154.6 | FS66: 0 | FX66: 0 | FY66: 0 | GA66: [681,72 / 1,2 / 7,66] + 3% Трансп + 1,2% Заг.скл | GD66: 1 | GF66: 424247577 | GG66: 2 | GH66: 4 | GI66: -2 | GJ66: 0 | GK66: 0 | GL66: =ROUND(IF(AND(BH66=3,BI66=3,FS66<>0),P66,0),2) -> 0 | GM66: =ROUND(O66+X66+Y66,2)+GX66 -> 154.6 | GN66: =IF(OR(BI66=0,BI66=1),GM66-GX66,0) -> 0 | GO66: =IF(BI66=2,GM66-GX66,0) -> 0 | GP66: =IF(BI66=4,GM66-GX66,0) -> 0 | GR66: 0 | GS66: 2 | GT66: 0 | GV66: =ROUND((GT66),6) -> 0 | GW66: 1 | GX66: =ROUND(HC66*I66,2) -> 0 | HA66: 0 | HB66: 0 | HC66: =GV66*GW66 -> 0 | HE66: 3 | HF66: 1,2 | HS66: 0 | IK66: 0
A67: 17 | B67: 1 | E67: 20 | F67: КА-11 | G67: Изолятор шлейфа ИЗ-1 прот. R3 | H67: ШТ | I67: 2 | J67: 0 | K67: 2 | O67: =ROUND(CP67,2) -> 1184.24 | P67: =ROUND((ROUND((AC67*I67),2)*BC67),2) -> 1184.24 | Q67: =(ROUND((ROUND(((ET67)*AV67*I67),2)*BB67),2)+ROUND((ROUND(((AE67-(EU67))*AV67*I67),2)*BS67),2)) -> 0 | R67: =(ROUND((ROUND(((EU67)*AV67*I67),2)*BS67),2)+ROUND((ROUND(((AE67-(EU67))*AV67*I67),2)*BS67),2)) -> 0 | S67: =ROUND((ROUND((AF67*AV67*I67),2)*BA67),2) -> 0 | T67: =ROUND(CU67*I67,2) -> 0 | U67: =CV67*I67 -> 0 | V67: =CW67*I67 -> 0 | W67: =ROUND(CX67*I67,2) -> 0 | X67: =(ROUND((((S67+ROUND((ROUND(((EU67)*AV67*I67),2)*BS67),2))*AT67)/100),2)+ROUND(((ROUND((ROUND(((AE67-(EU67))*AV67*I67),2)*BS67),2)*AT67)/100),2)) -> 0 | Y67: =(ROUND((((S67+ROUND((ROUND(((EU67)*AV67*I67),2)*BS67),2))*AU67)/100),2)+ROUND(((ROUND((ROUND(((AE67-(EU67))*AV67*I67),2)*BS67),2)*AU67)/100),2)) -> 0 | AA67: 60258618 | AB67: =ROUND((AC67+AD67+AF67),6) -> 77.3 | AC67: =ROUND((ES67),6) -> 77.3 | AD67: =ROUND((((ET67)-(EU67))+AE67),6) -> 0 | AE67: =ROUND((EU67),6) -> 0 | AF67: =ROUND((EV67),6) -> 0 | AG67: =ROUND((AP67),6) -> 0 | AH67: =(EW67) -> 0 | AI67: =(EX67) -> 0 | AJ67: =(AS67) -> 0 | AK67: 77.3 | AL67: 77.3 | AM67: 0 | AN67: 0 | AO67: 0 | AP67: 0 | AQ67: 0 | AR67: 0 | AS67: 0 | AT67: 0 | AU67: 0 | AV67: 1 | AW67: 1 | AZ67: 1 | BA67: 1 | BB67: 1 | BC67: 7.66 | BH67: 3 | BI67: 3 | BM67: 746 | BN67: 0 | BP67: 0 | BQ67: 130 | BR67: 0 | BS67: 1 | BT67: 1 | BU67: 1 | BV67: 1 | BW67: 1 | BX67: 1 | BZ67: 0 | CA67: 0 | CE67: 1566 | CF67: 0 | CG67: 0 | CM67: 0 | CO67: 0 | CP67: =(P67+Q67+S67) -> 1184.24 | CQ67: =ROUND((ROUND((AC67*1),2)*BC67),2) -> 592.12 | CR67: =(ROUND((ROUND(((ET67)*AV67*1),2)*BB67),2)+ROUND((ROUND(((AE67-(EU67))*AV67*1),2)*BS67),2)) -> 0 | CS67: =(ROUND((ROUND(((EU67)*AV67*1),2)*BS67),2)+ROUND((ROUND(((AE67-(EU67))*AV67*1),2)*BS67),2)) -> 0 | CT67: =ROUND((ROUND((AF67*AV67*1),2)*BA67),2) -> 0 | CU67: =AG67 -> 0 | CV67: =(AH67*AV67) -> 0 | CW67: =AI67 -> 0 | CX67: =AJ67 -> 0 | CY67: =(ROUND((((S67+ROUND((ROUND(((EU67)*AV67*1),2)*BS67),2))*AT67)/100),2)+ROUND(((ROUND((ROUND(((AE67-(EU67))*AV67*1),2)*BS67),2)*AT67)/100),2)) -> 0 | CZ67: =(ROUND((((S67+ROUND((ROUND(((EU67)*AV67*1),2)*BS67),2))*AU67)/100),2)+ROUND(((ROUND((ROUND(((AE67-(EU67))*AV67*1),2)*BS67),2)*AU67)/100),2)) -> 0 | DN67: 0 | DO67: 0 | DP67: 1 | DQ67: 1 | DU67: 1013 | DV67: ШТ | DW67: ШТ | DX67: 1 | EE67: 60088638 | EF67: 130 | EG67: Сметная стоимость оборудования | EH67: 0 | EJ67: 3 | EK67: 746 | EL67: ТСН-2001.13. Сметная стоимость оборудования | EM67: ТСН-2001.13 | EQ67: 0 | ER67: 0 | ES67: 77.3 | ET67: 0 | EU67: 0 | EV67: 0 | EW67: 0 | EX67: 0 | EY67: 0 | EZ67: 5 | FC67: 1 | FD67: 18 | FF67: 681.72 | FQ67: 0 | FR67: =P67 -> 1184.24 | FS67: 0 | FX67: 0 | FY67: 0 | GA67: [681,72 / 1,2 / 7,66] + 3% Трансп + 1,2% Заг.скл | GD67: 1 | GF67: 424247577 | GG67: 2 | GH67: 3 | GI67: 5 | GJ67: 0 | GK67: 0 | GL67: =ROUND(IF(AND(BH67=3,BI67=3,FS67<>0),P67,0),2) -> 0 | GM67: =ROUND(O67+X67+Y67,2)+GX67 -> 1184.24 | GN67: =IF(OR(BI67=0,BI67=1),GM67-GX67,0) -> 0 | GO67: =IF(BI67=2,GM67-GX67,0) -> 0 | GP67: =IF(BI67=4,GM67-GX67,0) -> 0 | GR67: 1 | GS67: 1 | GT67: 0 | GV67: =ROUND((GT67),6) -> 0 | GW67: 1 | GX67: =ROUND(HC67*I67,2) -> 0 | HA67: 0 | HB67: 0 | HC67: =GV67*GW67 -> 0 | HE67: 3 | HF67: 1,2 | HS67: 0 | IK67: 0
A68: 17 | B68: 1 | C68: =ROW(SmtRes!A39) -> 39 | D68: =ROW(EtalonRes!A47) -> 47 | E68: 21 | F68: 4.10-82-2 | G68: Приборы и устройства сигнализирующие объектовые, устройства ультразвуковые, прибор ультразвуковой в одноблочном исполнении | H68: 1 ШТ. | I68: 30 | J68: 0 | K68: 30 | O68: =ROUND(CP68,2) -> 1717.14 | P68: =ROUND((ROUND((AC68*AW68*I68),2)*BC68),2) -> 50.4 | Q68: =(ROUND((ROUND((((ET68*1.1))*AV68*I68),2)*BB68),2)+ROUND((ROUND(((AE68-((EU68*1.1)))*AV68*I68),2)*BS68),2)) -> 1.38 | R68: =(ROUND((ROUND((((EU68*1.1))*AV68*I68),2)*BS68),2)+ROUND((ROUND(((AE68-((EU68*1.1)))*AV68*I68),2)*BS68),2)) -> 0 | S68: =ROUND((ROUND((AF68*AV68*I68),2)*BA68),2) -> 1665.36 | T68: =ROUND(CU68*I68,2) -> 0 | U68: =CV68*I68 -> 124.3836 | V68: =CW68*I68 -> 0 | W68: =ROUND(CX68*I68,2) -> 0 | X68: =(ROUND((((S68+ROUND((ROUND((((EU68*1.1))*AV68*I68),2)*BS68),2))*AT68)/100),2)+ROUND(((ROUND((ROUND(((AE68-((EU68*1.1)))*AV68*I68),2)*BS68),2)*AT68)/100),2)) -> 1498.82 | Y68: =(ROUND((((S68+ROUND((ROUND((((EU68*1.1))*AV68*I68),2)*BS68),2))*AU68)/100),2)+ROUND(((ROUND((ROUND(((AE68-((EU68*1.1)))*AV68*I68),2)*BS68),2)*AU68)/100),2)) -> 766.07 | AA68: 60258621 | AB68: =ROUND((AC68+AD68+AF68),6) -> 54.744 | AC68: =ROUND(((ES68*1)),6) -> 1.68 | AD68: =ROUND(((((ET68*1.1))-((EU68*1.1)))+AE68),6) -> 0.044 | AE68: =ROUND(((EU68*1.1)),6) -> 0 | AF68: =ROUND(((EV68*1.1)),6) -> 53.02 | AG68: =ROUND((AP68),6) -> 0 | AH68: =((EW68*1.1)) -> 3.96 | AI68: =((EX68*1.1)) -> 0 | AJ68: =(AS68) -> 0 | AK68: 49.92 | AL68: 1.68 | AM68: 0.04 | AN68: 0 | AO68: 48.2 | AP68: 0 | AQ68: 3.6 | AR68: 0 | AS68: 0 | AT68: 90 | AU68: 46 | AV68: 1.047 | AW68: 1 | AZ68: 1 | BA68: 1 | BB68: 1 | BC68: 1 | BH68: 0 | BI68: 2 | BJ68: ТСН-2001.4 Доп. 70, Сб. 10, т. 82, поз. 2 | BM68: 68 | BN68: 58973116 | BO68: 4.10-82-2 | BP68: 1 | BQ68: 40 | BR68: 0 | BS68: 1 | BT68: 1 | BU68: 1 | BV68: 1 | BW68: 1 | BX68: 1 | BZ68: 90 | CA68: 46 | CE68: 1566 | CF68: 0 | CG68: 0 | CM68: 0 | CN68: Поправка: Гл.12.Прил.8.п.8. 5_12.00.01.11.003 Наименование: При наличии усложненных условий производства работ (стесненность, сложность складирования и транспортной логистики, наличие в зоне производства работ действующего технологического оборудования или движения технологического транспорта и т.п.) для объектов, расположенных за пределами территории круговой магистральной системы улиц "Садовое кольцо" и за пределами Третьего транспортного кольца города Москвы пунктов "а" и "б", но в пределах Московской кольцевой автомобильной дороги | CO68: 0 | CP68: =(P68+Q68+S68) -> 1717.14 | CQ68: =ROUND((ROUND((AC68*AW68*1),2)*BC68),2) -> 1.68 | CR68: =(ROUND((ROUND((((ET68*1.1))*AV68*1),2)*BB68),2)+ROUND((ROUND(((AE68-((EU68*1.1)))*AV68*1),2)*BS68),2)) -> 0.05 | CS68: =(ROUND((ROUND((((EU68*1.1))*AV68*1),2)*BS68),2)+ROUND((ROUND(((AE68-((EU68*1.1)))*AV68*1),2)*BS68),2)) -> 0 | CT68: =ROUND((ROUND((AF68*AV68*1),2)*BA68),2) -> 55.51 | CU68: =AG68 -> 0 | CV68: =(AH68*AV68) -> 4.14612 | CW68: =AI68 -> 0 | CX68: =AJ68 -> 0 | CY68: =(ROUND((((S68+ROUND((ROUND((((EU68*1.1))*AV68*1),2)*BS68),2))*AT68)/100),2)+ROUND(((ROUND((ROUND(((AE68-((EU68*1.1)))*AV68*1),2)*BS68),2)*AT68)/100),2)) -> 1498.82 | CZ68: =(ROUND((((S68+ROUND((ROUND((((EU68*1.1))*AV68*1),2)*BS68),2))*AU68)/100),2)+ROUND(((ROUND((ROUND(((AE68-((EU68*1.1)))*AV68*1),2)*BS68),2)*AU68)/100),2)) -> 766.07 | DB68: 19 | DD68: *1 | DE68: *1,1 | DF68: *1,1 | DG68: *1,1 | DI68: *1,1 | DJ68: *1,1 | DN68: 0 | DO68: 0 | DP68: 1 | DQ68: 1 | DU68: 1013 | DV68: 1 ШТ. | DW68: 1 ШТ. | DX68: 1 | EE68: 60088532 | EF68: 40 | EG68: Монтаж оборудования | EH68: 0 | EJ68: 2 | EK68: 68 | EL68: ТСН-2001.4-10. Прокладка и монтаж сетей связи | EM68: ТСН-2001.4-10-1 | EO68: Поправка: Гл.12.Прил.8.п.8. 5_12.00.01.11.003 | EQ68: 0 | ER68: 49.92 | ES68: 1.68 | ET68: 0.04 | EU68: 0 | EV68: 48.2 | EW68: 3.6 | EX68: 0 | EY68: 0 | FQ68: 0 | FR68: 0 | FS68: 0 | FX68: 90 | FY68: 46 | GD68: 1 | GF68: -1118583181 | GG68: 2 | GH68: 1 | GI68: 2 | GJ68: 0 | GK68: 0 | GL68: =ROUND(IF(AND(BH68=3,BI68=3,FS68<>0),P68,0),2) -> 0 | GM68: =ROUND(O68+X68+Y68,2)+GX68 -> 3982.03 | GN68: =IF(OR(BI68=0,BI68=1),GM68-GX68,0) -> 0 | GO68: =IF(BI68=2,GM68-GX68,0) -> 3982.03 | GP68: =IF(BI68=4,GM68-GX68,0) -> 0 | GR68: 0 | GS68: 3 | GT68: 0 | GV68: =ROUND((GT68),6) -> 0 | GW68: 1 | GX68: =ROUND(HC68*I68,2) -> 0 | HA68: 0 | HB68: 0 | HC68: =GV68*GW68 -> 0 | HS68: 0 | IK68: 0
A69: 17 | B69: 1 | C69: =ROW(SmtRes!A40) -> 40 | D69: =ROW(EtalonRes!A48) -> 48 | E69: 21 | F69: 4.10-82-2 | G69: Приборы и устройства сигнализирующие объектовые, устройства ультразвуковые, прибор ультразвуковой в одноблочном исполнении | H69: 1 ШТ. | I69: 30 | J69: 0 | K69: 30 | O69: =ROUND(CP69,2) -> 92090.41 | P69: =ROUND((ROUND((AC69*AW69*I69),2)*BC69),2) -> 498.46 | Q69: =(ROUND((ROUND((((ET69*1.1))*AV69*I69),2)*BB69),2)+ROUND((ROUND(((AE69-((EU69*1.1)))*AV69*I69),2)*BS69),2)) -> 13.8 | R69: =(ROUND((ROUND((((EU69*1.1))*AV69*I69),2)*BS69),2)+ROUND((ROUND(((AE69-((EU69*1.1)))*AV69*I69),2)*BS69),2)) -> 0 | S69: =ROUND((ROUND((AF69*AV69*I69),2)*BA69),2) -> 91578.15 | T69: =ROUND(CU69*I69,2) -> 0 | U69: =CV69*I69 -> 124.3836 | V69: =CW69*I69 -> 0 | W69: =ROUND(CX69*I69,2) -> 0 | X69: =(ROUND((((S69+ROUND((ROUND((((EU69*1.1))*AV69*I69),2)*BS69),2))*AT69)/100),2)+ROUND(((ROUND((ROUND(((AE69-((EU69*1.1)))*AV69*I69),2)*BS69),2)*AT69)/100),2)) -> 82420.34 | Y69: =(ROUND((((S69+ROUND((ROUND((((EU69*1.1))*AV69*I69),2)*BS69),2))*AU69)/100),2)+ROUND(((ROUND((ROUND(((AE69-((EU69*1.1)))*AV69*I69),2)*BS69),2)*AU69)/100),2)) -> 42125.95 | AA69: 60258618 | AB69: =ROUND((AC69+AD69+AF69),6) -> 54.744 | AC69: =ROUND(((ES69*1)),6) -> 1.68 | AD69: =ROUND(((((ET69*1.1))-((EU69*1.1)))+AE69),6) -> 0.044 | AE69: =ROUND(((EU69*1.1)),6) -> 0 | AF69: =ROUND(((EV69*1.1)),6) -> 53.02 | AG69: =ROUND((AP69),6) -> 0 | AH69: =((EW69*1.1)) -> 3.96 | AI69: =((EX69*1.1)) -> 0 | AJ69: =(AS69) -> 0 | AK69: 49.92 | AL69: 1.68 | AM69: 0.04 | AN69: 0 | AO69: 48.2 | AP69: 0 | AQ69: 3.6 | AR69: 0 | AS69: 0 | AT69: 90 | AU69: 46 | AV69: 1.047 | AW69: 1 | AZ69: 1 | BA69: 54.99 | BB69: 10 | BC69: 9.89 | BH69: 0 | BI69: 2 | BJ69: ТСН-2001.4 Доп. 70, Сб. 10, т. 82, поз. 2 | BM69: 68 | BN69: 58973116 | BO69: 4.10-82-2 | BP69: 1 | BQ69: 40 | BR69: 0 | BS69: 54.99 | BT69: 1 | BU69: 1 | BV69: 1 | BW69: 1 | BX69: 1 | BZ69: 90 | CA69: 46 | CE69: 1566 | CF69: 0 | CG69: 0 | CM69: 0 | CN69: Поправка: Гл.12.Прил.8.п.8. 5_12.00.01.11.003 Наименование: При наличии усложненных условий производства работ (стесненность, сложность складирования и транспортной логистики, наличие в зоне производства работ действующего технологического оборудования или движения технологического транспорта и т.п.) для объектов, расположенных за пределами территории круговой магистральной системы улиц "Садовое кольцо" и за пределами Третьего транспортного кольца города Москвы пунктов "а" и "б", но в пределах Московской кольцевой автомобильной дороги | CO69: 0 | CP69: =(P69+Q69+S69) -> 92090.41 | CQ69: =ROUND((ROUND((AC69*AW69*1),2)*BC69),2) -> 16.62 | CR69: =(ROUND((ROUND((((ET69*1.1))*AV69*1),2)*BB69),2)+ROUND((ROUND(((AE69-((EU69*1.1)))*AV69*1),2)*BS69),2)) -> 0.5 | CS69: =(ROUND((ROUND((((EU69*1.1))*AV69*1),2)*BS69),2)+ROUND((ROUND(((AE69-((EU69*1.1)))*AV69*1),2)*BS69),2)) -> 0 | CT69: =ROUND((ROUND((AF69*AV69*1),2)*BA69),2) -> 3052.49 | CU69: =AG69 -> 0 | CV69: =(AH69*AV69) -> 4.14612 | CW69: =AI69 -> 0 | CX69: =AJ69 -> 0 | CY69: =(ROUND((((S69+ROUND((ROUND((((EU69*1.1))*AV69*1),2)*BS69),2))*AT69)/100),2)+ROUND(((ROUND((ROUND(((AE69-((EU69*1.1)))*AV69*1),2)*BS69),2)*AT69)/100),2)) -> 82420.34 | CZ69: =(ROUND((((S69+ROUND((ROUND((((EU69*1.1))*AV69*1),2)*BS69),2))*AU69)/100),2)+ROUND(((ROUND((ROUND(((AE69-((EU69*1.1)))*AV69*1),2)*BS69),2)*AU69)/100),2)) -> 42125.95 | DB69: 20 | DD69: *1 | DE69: *1,1 | DF69: *1,1 | DG69: *1,1 | DI69: *1,1 | DJ69: *1,1 | DN69: 0 | DO69: 0 | DP69: 1 | DQ69: 1 | DU69: 1013 | DV69: 1 ШТ. | DW69: 1 ШТ. | DX69: 1 | EE69: 60088532 | EF69: 40 | EG69: Монтаж оборудования | EH69: 0 | EJ69: 2 | EK69: 68 | EL69: ТСН-2001.4-10. Прокладка и монтаж сетей связи | EM69: ТСН-2001.4-10-1 | EO69: Поправка: Гл.12.Прил.8.п.8. 5_12.00.01.11.003 | EQ69: 0 | ER69: 49.92 | ES69: 1.68 | ET69: 0.04 | EU69: 0 | EV69: 48.2 | EW69: 3.6 | EX69: 0 | EY69: 0 | FQ69: 0 | FR69: 0 | FS69: 0 | FX69: 90 | FY69: 46 | GD69: 1 | GF69: -1118583181 | GG69: 2 | GH69: 1 | GI69: 2 | GJ69: 0 | GK69: 0 | GL69: =ROUND(IF(AND(BH69=3,BI69=3,FS69<>0),P69,0),2) -> 0 | GM69: =ROUND(O69+X69+Y69,2)+GX69 -> 216636.7 | GN69: =IF(OR(BI69=0,BI69=1),GM69-GX69,0) -> 0 | GO69: =IF(BI69=2,GM69-GX69,0) -> 216636.7 | GP69: =IF(BI69=4,GM69-GX69,0) -> 0 | GR69: 0 | GS69: 3 | GT69: 0 | GV69: =ROUND((GT69),6) -> 0 | GW69: 1 | GX69: =ROUND(HC69*I69,2) -> 0 | HA69: 0 | HB69: 0 | HC69: =GV69*GW69 -> 0 | HS69: 0 | IK69: 0
A70: 17 | B70: 1 | E70: 22 | F70: КА-12 | G70: Извещатель охранный объемный оптико-электронный адресный ИО 40920-2 | H70: ШТ | I70: 30 | J70: 0 | K70: 30 | O70: =ROUND(CP70,2) -> 7202.1 | P70: =ROUND((ROUND((AC70*I70),2)*BC70),2) -> 7202.1 | Q70: =(ROUND((ROUND(((ET70)*AV70*I70),2)*BB70),2)+ROUND((ROUND(((AE70-(EU70))*AV70*I70),2)*BS70),2)) -> 0 | R70: =(ROUND((ROUND(((EU70)*AV70*I70),2)*BS70),2)+ROUND((ROUND(((AE70-(EU70))*AV70*I70),2)*BS70),2)) -> 0 | S70: =ROUND((ROUND((AF70*AV70*I70),2)*BA70),2) -> 0 | T70: =ROUND(CU70*I70,2) -> 0 | U70: =CV70*I70 -> 0 | V70: =CW70*I70 -> 0 | W70: =ROUND(CX70*I70,2) -> 0 | X70: =(ROUND((((S70+ROUND((ROUND(((EU70)*AV70*I70),2)*BS70),2))*AT70)/100),2)+ROUND(((ROUND((ROUND(((AE70-(EU70))*AV70*I70),2)*BS70),2)*AT70)/100),2)) -> 0 | Y70: =(ROUND((((S70+ROUND((ROUND(((EU70)*AV70*I70),2)*BS70),2))*AU70)/100),2)+ROUND(((ROUND((ROUND(((AE70-(EU70))*AV70*I70),2)*BS70),2)*AU70)/100),2)) -> 0 | AA70: 60258621 | AB70: =ROUND((AC70+AD70+AF70),6) -> 240.07 | AC70: =ROUND((ES70),6) -> 240.07 | AD70: =ROUND((((ET70)-(EU70))+AE70),6) -> 0 | AE70: =ROUND((EU70),6) -> 0 | AF70: =ROUND((EV70),6) -> 0 | AG70: =ROUND((AP70),6) -> 0 | AH70: =(EW70) -> 0 | AI70: =(EX70) -> 0 | AJ70: =(AS70) -> 0 | AK70: 240.07 | AL70: 240.07 | AM70: 0 | AN70: 0 | AO70: 0 | AP70: 0 | AQ70: 0 | AR70: 0 | AS70: 0 | AT70: 0 | AU70: 0 | AV70: 1 | AW70: 1 | AZ70: 1 | BA70: 1 | BB70: 1 | BC70: 1 | BH70: 3 | BI70: 3 | BM70: 746 | BN70: 0 | BP70: 0 | BQ70: 130 | BR70: 0 | BS70: 1 | BT70: 1 | BU70: 1 | BV70: 1 | BW70: 1 | BX70: 1 | BZ70: 0 | CA70: 0 | CE70: 1566 | CF70: 0 | CG70: 0 | CM70: 0 | CO70: 0 | CP70: =(P70+Q70+S70) -> 7202.1 | CQ70: =ROUND((ROUND((AC70*1),2)*BC70),2) -> 240.07 | CR70: =(ROUND((ROUND(((ET70)*AV70*1),2)*BB70),2)+ROUND((ROUND(((AE70-(EU70))*AV70*1),2)*BS70),2)) -> 0 | CS70: =(ROUND((ROUND(((EU70)*AV70*1),2)*BS70),2)+ROUND((ROUND(((AE70-(EU70))*AV70*1),2)*BS70),2)) -> 0 | CT70: =ROUND((ROUND((AF70*AV70*1),2)*BA70),2) -> 0 | CU70: =AG70 -> 0 | CV70: =(AH70*AV70) -> 0 | CW70: =AI70 -> 0 | CX70: =AJ70 -> 0 | CY70: =(ROUND((((S70+ROUND((ROUND(((EU70)*AV70*1),2)*BS70),2))*AT70)/100),2)+ROUND(((ROUND((ROUND(((AE70-(EU70))*AV70*1),2)*BS70),2)*AT70)/100),2)) -> 0 | CZ70: =(ROUND((((S70+ROUND((ROUND(((EU70)*AV70*1),2)*BS70),2))*AU70)/100),2)+ROUND(((ROUND((ROUND(((AE70-(EU70))*AV70*1),2)*BS70),2)*AU70)/100),2)) -> 0 | DN70: 0 | DO70: 0 | DP70: 1 | DQ70: 1 | DU70: 1013 | DV70: ШТ | DW70: ШТ | DX70: 1 | EE70: 60088638 | EF70: 130 | EG70: Сметная стоимость оборудования | EH70: 0 | EJ70: 3 | EK70: 746 | EL70: ТСН-2001.13. Сметная стоимость оборудования | EM70: ТСН-2001.13 | EQ70: 0 | ER70: 0 | ES70: 240.07 | ET70: 0 | EU70: 0 | EV70: 0 | EW70: 0 | EX70: 0 | EY70: 0 | FQ70: 0 | FR70: =P70 -> 7202.1 | FS70: 0 | FX70: 0 | FY70: 0 | GA70: [2 117 / 1,2 / 7,66] + 3% Трансп + 1,2% Заг.скл | GD70: 1 | GF70: 1183657808 | GG70: 2 | GH70: 4 | GI70: -2 | GJ70: 0 | GK70: 0 | GL70: =ROUND(IF(AND(BH70=3,BI70=3,FS70<>0),P70,0),2) -> 0 | GM70: =ROUND(O70+X70+Y70,2)+GX70 -> 7202.1 | GN70: =IF(OR(BI70=0,BI70=1),GM70-GX70,0) -> 0 | GO70: =IF(BI70=2,GM70-GX70,0) -> 0 | GP70: =IF(BI70=4,GM70-GX70,0) -> 0 | GR70: 0 | GS70: 2 | GT70: 0 | GV70: =ROUND((GT70),6) -> 0 | GW70: 1 | GX70: =ROUND(HC70*I70,2) -> 0 | HA70: 0 | HB70: 0 | HC70: =GV70*GW70 -> 0 | HE70: 3 | HF70: 1,2 | HS70: 0 | IK70: 0
A71: 17 | B71: 1 | E71: 22 | F71: КА-12 | G71: Извещатель охранный объемный оптико-электронный адресный ИО 40920-2 | H71: ШТ | I71: 30 | J71: 0 | K71: 30 | O71: =ROUND(CP71,2) -> 55168.09 | P71: =ROUND((ROUND((AC71*I71),2)*BC71),2) -> 55168.09 | Q71: =(ROUND((ROUND(((ET71)*AV71*I71),2)*BB71),2)+ROUND((ROUND(((AE71-(EU71))*AV71*I71),2)*BS71),2)) -> 0 | R71: =(ROUND((ROUND(((EU71)*AV71*I71),2)*BS71),2)+ROUND((ROUND(((AE71-(EU71))*AV71*I71),2)*BS71),2)) -> 0 | S71: =ROUND((ROUND((AF71*AV71*I71),2)*BA71),2) -> 0 | T71: =ROUND(CU71*I71,2) -> 0 | U71: =CV71*I71 -> 0 | V71: =CW71*I71 -> 0 | W71: =ROUND(CX71*I71,2) -> 0 | X71: =(ROUND((((S71+ROUND((ROUND(((EU71)*AV71*I71),2)*BS71),2))*AT71)/100),2)+ROUND(((ROUND((ROUND(((AE71-(EU71))*AV71*I71),2)*BS71),2)*AT71)/100),2)) -> 0 | Y71: =(ROUND((((S71+ROUND((ROUND(((EU71)*AV71*I71),2)*BS71),2))*AU71)/100),2)+ROUND(((ROUND((ROUND(((AE71-(EU71))*AV71*I71),2)*BS71),2)*AU71)/100),2)) -> 0 | AA71: 60258618 | AB71: =ROUND((AC71+AD71+AF71),6) -> 240.07 | AC71: =ROUND((ES71),6) -> 240.07 | AD71: =ROUND((((ET71)-(EU71))+AE71),6) -> 0 | AE71: =ROUND((EU71),6) -> 0 | AF71: =ROUND((EV71),6) -> 0 | AG71: =ROUND((AP71),6) -> 0 | AH71: =(EW71) -> 0 | AI71: =(EX71) -> 0 | AJ71: =(AS71) -> 0 | AK71: 240.07 | AL71: 240.07 | AM71: 0 | AN71: 0 | AO71: 0 | AP71: 0 | AQ71: 0 | AR71: 0 | AS71: 0 | AT71: 0 | AU71: 0 | AV71: 1 | AW71: 1 | AZ71: 1 | BA71: 1 | BB71: 1 | BC71: 7.66 | BH71: 3 | BI71: 3 | BM71: 746 | BN71: 0 | BP71: 0 | BQ71: 130 | BR71: 0 | BS71: 1 | BT71: 1 | BU71: 1 | BV71: 1 | BW71: 1 | BX71: 1 | BZ71: 0 | CA71: 0 | CE71: 1566 | CF71: 0 | CG71: 0 | CM71: 0 | CO71: 0 | CP71: =(P71+Q71+S71) -> 55168.09 | CQ71: =ROUND((ROUND((AC71*1),2)*BC71),2) -> 1838.94 | CR71: =(ROUND((ROUND(((ET71)*AV71*1),2)*BB71),2)+ROUND((ROUND(((AE71-(EU71))*AV71*1),2)*BS71),2)) -> 0 | CS71: =(ROUND((ROUND(((EU71)*AV71*1),2)*BS71),2)+ROUND((ROUND(((AE71-(EU71))*AV71*1),2)*BS71),2)) -> 0 | CT71: =ROUND((ROUND((AF71*AV71*1),2)*BA71),2) -> 0 | CU71: =AG71 -> 0 | CV71: =(AH71*AV71) -> 0 | CW71: =AI71 -> 0 | CX71: =AJ71 -> 0 | CY71: =(ROUND((((S71+ROUND((ROUND(((EU71)*AV71*1),2)*BS71),2))*AT71)/100),2)+ROUND(((ROUND((ROUND(((AE71-(EU71))*AV71*1),2)*BS71),2)*AT71)/100),2)) -> 0 | CZ71: =(ROUND((((S71+ROUND((ROUND(((EU71)*AV71*1),2)*BS71),2))*AU71)/100),2)+ROUND(((ROUND((ROUND(((AE71-(EU71))*AV71*1),2)*BS71),2)*AU71)/100),2)) -> 0 | DN71: 0 | DO71: 0 | DP71: 1 | DQ71: 1 | DU71: 1013 | DV71: ШТ | DW71: ШТ | DX71: 1 | EE71: 60088638 | EF71: 130 | EG71: Сметная стоимость оборудования | EH71: 0 | EJ71: 3 | EK71: 746 | EL71: ТСН-2001.13. Сметная стоимость оборудования | EM71: ТСН-2001.13 | EQ71: 0 | ER71: 0 | ES71: 240.07 | ET71: 0 | EU71: 0 | EV71: 0 | EW71: 0 | EX71: 0 | EY71: 0 | EZ71: 5 | FC71: 1 | FD71: 18 | FF71: 2117 | FQ71: 0 | FR71: =P71 -> 55168.09 | FS71: 0 | FX71: 0 | FY71: 0 | GA71: [2 117 / 1,2 / 7,66] + 3% Трансп + 1,2% Заг.скл | GD71: 1 | GF71: 1183657808 | GG71: 2 | GH71: 3 | GI71: 5 | GJ71: 0 | GK71: 0 | GL71: =ROUND(IF(AND(BH71=3,BI71=3,FS71<>0),P71,0),2) -> 0 | GM71: =ROUND(O71+X71+Y71,2)+GX71 -> 55168.09 | GN71: =IF(OR(BI71=0,BI71=1),GM71-GX71,0) -> 0 | GO71: =IF(BI71=2,GM71-GX71,0) -> 0 | GP71: =IF(BI71=4,GM71-GX71,0) -> 0 | GR71: 1 | GS71: 1 | GT71: 0 | GV71: =ROUND((GT71),6) -> 0 | GW71: 1 | GX71: =ROUND(HC71*I71,2) -> 0 | HA71: 0 | HB71: 0 | HC71: =GV71*GW71 -> 0 | HE71: 3 | HF71: 1,2 | HS71: 0 | IK71: 0
