Workbook

Sheet 02-01-20
A1: =Source!B1 -> Smeta.RU (495) 974-1589
J2: Форма № 4б
A3: Капитальный ремонт здания Государственного бюджетного общеобразовательного учреждения города Москвы "Школа № 236" по адресу: г. Москва ул. Клязьминская, д. 7 к. 4. 1 этап. | AP3: Капитальный ремонт здания Государственного бюджетного общеобразовательного учреждения города Москвы "Школа № 236" по адресу: г. Москва ул. Клязьминская, д. 7 к. 4. 1 этап. 02-01-20 ПТА
A4: (наименование стройки и/или объекта)
A6: =CONCATENATE( "ЛОКАЛЬНАЯ СМЕТА № ",IF(Source!F20<>"Новая локальная смета", Source!F20, "")) -> ЛОКАЛЬНАЯ СМЕТА № 02-01-20
A8: =IF(Source!G20<>"Новая локальная смета", Source!G20, "") -> Мероприятия по противодействию террористическим актам
A9: (наименование работ и затрат)
A11: =CONCATENATE( "Основание: чертежи № ", Source!J20) -> Основание: чертежи № 2024-00272-01-0-ПТА
I13: В базисном уровне цен | J13: В текущем уровне цен
E14: Сметная стоимость | I14: =I15+I16+I17+I18 -> 376.17 | J14: =J15+J16+J17+J18 -> 2977.26 | K14: тыс.руб.
E15: Строительные работы | I15: =ROUND((Source!F98)/1000, 2) -> 26.42 | J15: =ROUND((Source!P98)/1000, 2) -> 266.61 | K15: тыс.руб.
E16: Работы по монтажу оборудования | I16: =ROUND((Source!F99)/1000, 2) -> 0.13 | J16: =ROUND((Source!P99)/1000, 2) -> 7.19 | K16: тыс.руб.
E17: Оборудование | I17: =ROUND((Source!F90)/1000, 2) -> 349.62 | J17: =ROUND((Source!P90)/1000, 2) -> 2703.46 | K17: тыс.руб.
E18: Прочие работы и затраты | I18: =ROUND((Source!F100+Source!F101)/1000, 2) -> 0 | J18: =ROUND((Source!P100+Source!P101)/1000, 2) -> 0 | K18: тыс.руб.
E19: Средства на оплату труда | I19: =(Source!F96+ Source!F95)/1000 -> 0.10155 | J19: =((Source!P96 + Source!P95)/1000) -> 5.58424 | K19: тыс.руб.
E20: Затраты труда | I20: =Source!F103 -> 8.0418206 | K20: чел.-ч.
E21: Кроме того:
E22: Возврат материалов | I22: =SUM(Y28:Y86)/1000 -> 0 | J22: =SUM(Z28:Z86)/1000 -> 0 | K22: тыс.руб.
A24: Составлен(а) по ТСН-2001 с учетом Дополнения №: 80
A25: № и период сборника коэффициентов (индексов) пересчета: Коэффициенты к ТСН-2001 МГЭ Дополнение 80, строительство №217/80 III квартал 2025 года и Коэффициенты к ТСН-2001.13-2 Дополнение 46 №62/46 III квартал 2025 года | AP25: № и период сборника коэффициентов (индексов) пересчета: Коэффициенты к ТСН-2001 МГЭ Дополнение 80, строительство №217/80 III квартал 2025 года и Коэффициенты к ТСН-2001.13-2 Дополнение 46 №62/46 III квартал 2025 года
A26: № п/п | B26: Шифр расценки и коды ресурсов | C26: Наименование работ и затрат | D26: Ед. изм. | E26: Кол-во единиц | F26: Цена на ед. изм., руб. | G26: Попра- вочные коэффи- циенты | H26: Коэффи- циенты зимних удорожа- ний | I26: Всего в ценах на январь 2000 года, руб. | J26: Коэффи- циенты (индек- сы) пере- счета, нормы НР и СП | K26: ВСЕГО затрат в текущем уровне цен, руб.
A27: 1 | B27: 2 | C27: 3 | D27: 4 | E27: 5 | F27: 6 | G27: 7 | H27: 8 | I27: 9 | J27: 10 | K27: 11
A29: =CONCATENATE("Раздел: ",IF(Source!G24<>"Новый раздел", Source!G24, "")) -> Раздел: Оборудование
A30: 1 | B30: 4.10-161-1 Поправка: Гл.12.Прил.8.п.8. 5_12.00.01.11.003 | C30: Монтаж стационарного металлодетектора арочного типа | D30: =Source!H28 -> 1 ШТ. | E30: =Source!I28 -> 2 | Q30: =Source!X28 -> 49.82 | R30: =Source!X29 -> 2739.33 | S30: =Source!Y28 -> 25.46 | T30: =Source!Y29 -> 1400.1 | U30: =ROUND((175/100)*ROUND(Source!R28, 2), 2) -> 0 | V30: =ROUND((0/100)*ROUND(Source!R29, 2), 2) -> 0 | AC30: 0
C31: ЗП | F31: =Source!AO28 -> 23.58 | G31: =Source!DG28 -> *1,1 | H31: =Source!AV29 -> 1.067 | I31: =Source!S28 -> 55.35 | J31: =IF(Source!BA29<> 0, Source!BA29, 1) -> 54.99 | K31: =Source!S29 -> 3043.7
C32: ЭМ | F32: =Source!AM28 -> 0.51 | G32: =Source!DE28 -> *1,1 | H32: =Source!AV29 -> 1.067 | I32: =Source!Q28 -> 1.2 | J32: =IF(Source!BB29<> 0, Source!BB29, 1) -> 8.63 | K32: =Source!Q29 -> 10.36
C33: НР от ФОТ | D33: % | E33: =Source!BZ29 -> 90 | I33: =SUM(Q30:Q32) -> 49.82 | J33: =Source!AT29 -> 90 | K33: =SUM(R30:R32) -> 2739.33
C34: СП от ФОТ | D34: % | E34: =Source!CA29 -> 46 | I34: =SUM(S30:S33) -> 25.46 | J34: =Source!AU29 -> 46 | K34: =SUM(T30:T33) -> 1400.1
C35: ЗТР | D35: чел-ч | E35: =Source!AQ28 -> 1.69 | G35: =Source!DI28 -> *1,1 | H35: =Source!AV29 -> 1.067 | I35: =Source!U28 -> 3.967106
C36: Всего по позиции: | H36: =I31+I32+I33+I34+0 -> 131.83 | J36: =K31+K32+K33+K34+0 -> 7193.49 | O36: =I31+I32+I33+I34+0 -> 131.83 | P36: =K31+K32+K33+K34+0 -> 7193.49
A38: 2 | B38: =Source!F30 -> КА 1 | C38: ОБОРУДОВАНИЕ:_x000D_ Металлодетектор арочный Паутина-Н2-1 33 055,69 = [291 500 / 1,2 / 7,66] + 3% Трансп + 1,2% Заг.скл | D38: =Source!H30 -> шт. | E38: =Source!I30 -> 2 | F38: =Source!AL30 -> 33055.69 | G38: =Source!DD30 | H38: =Source!AW31 -> 1 | I38: =Source!P30 -> 66111.38 | J38: =IF(Source!BC31<> 0, Source!BC31, 1) -> 7.66 | K38: =Source!P31 -> 506413.17 | Q38: =Source!X30 -> 0 | R38: =Source!X31 -> 0 | S38: =Source!Y30 -> 0 | T38: =Source!Y31 -> 0 | U38: =ROUND((175/100)*ROUND(Source!R30, 2), 2) -> 0 | V38: =ROUND((0/100)*ROUND(Source!R31, 2), 2) -> 0 | AC38: 5
C39: Всего по позиции: | H39: =I38+0 -> 66111.38 | J39: =K38+0 -> 506413.17 | O39: =I38+0 -> 66111.38 | P39: =K38+0 -> 506413.17
A41: 3 | B41: =Source!F32 -> КА 2 | C41: ОБОРУДОВАНИЕ:_x000D_ Ручной металлодетектор «СФИНКС ВМ-611 РД-2.0» 6 798,25 = [59 950 / 1,2 / 7,66] + 3% Трансп + 1,2% Заг.скл | D41: =Source!H32 -> шт. | E41: =Source!I32 -> 3 | F41: =Source!AL32 -> 6798.25 | G41: =Source!DD32 | H41: =Source!AW33 -> 1 | I41: =Source!P32 -> 20394.75 | J41: =IF(Source!BC33<> 0, Source!BC33, 1) -> 7.66 | K41: =Source!P33 -> 156223.79 | Q41: =Source!X32 -> 0 | R41: =Source!X33 -> 0 | S41: =Source!Y32 -> 0 | T41: =Source!Y33 -> 0 | U41: =ROUND((175/100)*ROUND(Source!R32, 2), 2) -> 0 | V41: =ROUND((0/100)*ROUND(Source!R33, 2), 2) -> 0 | AC41: 5
C42: Всего по позиции: | H42: =I41+0 -> 20394.75 | J42: =K41+0 -> 156223.79 | O42: =I41+0 -> 20394.75 | P42: =K41+0 -> 156223.79
A44: 4 | B44: =Source!F34 -> КА 3 | C44: ОБОРУДОВАНИЕ:_x000D_ Газоанализатор паров взрывчатых веществ «Кербер-Т» 249 476,94 = [2 200 000 / 1,2 / 7,66] + 3% Трансп + 1,2% Заг.скл | D44: =Source!H34 -> шт. | E44: =Source!I34 -> 1 | F44: =Source!AL34 -> 249476.94 | G44: =Source!DD34 | H44: =Source!AW35 -> 1 | I44: =Source!P34 -> 249476.94 | J44: =IF(Source!BC35<> 0, Source!BC35, 1) -> 7.66 | K44: =Source!P35 -> 1910993.4 | Q44: =Source!X34 -> 0 | R44: =Source!X35 -> 0 | S44: =Source!Y34 -> 0 | T44: =Source!Y35 -> 0 | U44: =ROUND((175/100)*ROUND(Source!R34, 2), 2) -> 0 | V44: =ROUND((0/100)*ROUND(Source!R35, 2), 2) -> 0 | AC44: 5
C45: Всего по позиции: | H45: =I44+0 -> 249476.94 | J45: =K44+0 -> 1910993.4 | O45: =I44+0 -> 249476.94 | P45: =K44+0 -> 1910993.4
A47: 5 | B47: =Source!F36 -> 13.3-9-180 | C47: ОБОРУДОВАНИЕ:_x000D_ Устройство для защиты от взрыва типа Фонтан-2 10У. Мобильное устройство для подавления не более 1000 г ТНТ, локализуемый объем до 15 дм3, выполнено в форме купола с двумя ручками, стенки и верх купола наполнены специальным диспенсером, поглощающим тепловую и ударную волну, габаритные размеры 610х610х365 мм | D47: =Source!H36 -> шт. | E47: =Source!I36 -> 1 | F47: =Source!AL36 -> 8188.38 | G47: =Source!DD36 | H47: =Source!AW37 -> 1 | I47: =Source!P36 -> 8188.38 | J47: =IF(Source!BC37<> 0, Source!BC37, 1) -> 10.36 | K47: =Source!P37 -> 84831.62 | Q47: =Source!X36 -> 0 | R47: =Source!X37 -> 0 | S47: =Source!Y36 -> 0 | T47: =Source!Y37 -> 0 | U47: =ROUND((175/100)*ROUND(Source!R36, 2), 2) -> 0 | V47: =ROUND((0/100)*ROUND(Source!R37, 2), 2) -> 0 | AC47: 5
C48: Всего по позиции: | H48: =I47+0 -> 8188.38 | J48: =K47+0 -> 84831.62 | O48: =I47+0 -> 8188.38 | P48: =K47+0 -> 84831.62
A50: 6 | B50: =Source!F38 -> 13.1-2-203 | C50: ОБОРУДОВАНИЕ:_x000D_ Устройство досмотровое (зеркало) для осмотра грузов, транспортных средств, неосвещенных и труднодоступных мест в помещениях. В составе: телескопическая штанга со встроенными светодиодами, с регулировкой длины от 600 до 1850 мм, набор зеркал различного размера и формы - 4 шт. Время непрерывной работы светодиодов не менее 9 часов, диапазон рабочих температур от -20 до +50°С | D50: =Source!H38 -> КОМПЛЕКТ | E50: =Source!I38 -> 1 | F50: =Source!AL38 -> 866.44 | G50: =Source!DD38 | H50: =Source!AW39 -> 1 | I50: =Source!P38 -> 866.44 | J50: =IF(Source!BC39<> 0, Source!BC39, 1) -> 11.43 | K50: =Source!P39 -> 9903.41 | Q50: =Source!X38 -> 0 | R50: =Source!X39 -> 0 | S50: =Source!Y38 -> 0 | T50: =Source!Y39 -> 0 | U50: =ROUND((175/100)*ROUND(Source!R38, 2), 2) -> 0 | V50: =ROUND((0/100)*ROUND(Source!R39, 2), 2) -> 0 | AC50: 5
C51: Всего по позиции: | H51: =I50+0 -> 866.44 | J51: =K50+0 -> 9903.41 | O51: =I50+0 -> 866.44 | P51: =K50+0 -> 9903.41
A53: 7 | B53: 3.10-33-1 Поправка: О.П. п.3.4.30.в | C53: Установка штучных изделий столов, шкафов под мойки, холодильных шкафов и других | D53: =Source!H40 -> 100 изделий | E53: =Source!I40 -> 0.04 | Q53: =Source!X40 -> 36.99 | R53: =Source!X41 -> 2034.08 | S53: =Source!Y40 -> 18.84 | T53: =Source!Y41 -> 1035.88 | U53: =ROUND((175/100)*ROUND(Source!R40, 2), 2) -> 2.52 | V53: =ROUND((0/100)*ROUND(Source!R41, 2), 2) -> 0 | AC53: 0
C54: ="Объем: "&Source!I40&"=4/"&"100" -> Объем: 0,04=4/100
C55: ЗП | F55: =Source!AO40 -> 712.2 | G55: =Source!DG40 -> *1,1 | H55: =Source!AV41 -> 1.047 | I55: =Source!S40 -> 32.81 | J55: =IF(Source!BA41<> 0, Source!BA41, 1) -> 54.99 | K55: =Source!S41 -> 1804.22
C56: ЭМ | F56: =Source!AM40 -> 205.26 | G56: =Source!DE40 -> *1,1 | H56: =Source!AV41 -> 1.047 | I56: =Source!Q40 -> 9.46 | J56: =IF(Source!BB41<> 0, Source!BB41, 1) -> 16.3 | K56: =Source!Q41 -> 154.2
C57: в т.ч. ЗПМ | F57: =Source!AN40 -> 31.17 | G57: =Source!DF40 -> *1,1 | H57: =Source!AV41 -> 1.047 | I57: =Source!R40 -> 1.44 | J57: =IF(Source!BS41<> 0, Source!BS41, 1) -> 54.99 | K57: =Source!R41 -> 79.19
C58: МР | F58: =Source!AL40 -> 318.28 | G58: =Source!DD40 | H58: =Source!AW41 -> 1 | I58: =Source!P40 -> 12.73 | J58: =IF(Source!BC41<> 0, Source!BC41, 1) -> 9.11 | K58: =Source!P41 -> 115.97
C59: НР от ФОТ | D59: % | E59: =Source!BZ41 -> 108 | I59: =SUM(Q53:Q58) -> 36.99 | J59: =Source!AT41 -> 108 | K59: =SUM(R53:R58) -> 2034.08
C60: СП от ФОТ | D60: % | E60: =Source!CA41 -> 55 | I60: =SUM(S53:S59) -> 18.84 | J60: =Source!AU41 -> 55 | K60: =SUM(T53:T59) -> 1035.88
C61: ЗТР | D61: чел-ч | E61: =Source!AQ40 -> 67.7 | G61: =Source!DI40 -> *1,1 | H61: =Source!AV41 -> 1.047 | I61: =Source!U40 -> 3.1188036
C62: Всего по позиции: | H62: =I55+I56+I58+I59+I60+0 -> 110.83 | J62: =K55+K56+K58+K59+K60+0 -> 5144.35 | O62: =I55+I56+I58+I59+I60+0 -> 110.83 | P62: =K55+K56+K58+K59+K60+0 -> 5144.35
A64: 8 | B64: =Source!F42 -> КА 4 | C64: ОБОРУДОВАНИЕ:_x000D_ Стол досмотровый СД-950 (500х400х900) 1 145,32 = [10 100 / 1,2 / 7,66] + 3% Трансп + 1,2% Заг.скл | D64: =Source!H42 -> шт. | E64: =Source!I42 -> 4 | F64: =Source!AL42 -> 1145.32 | G64: =Source!DD42 | H64: =Source!AW43 -> 1 | I64: =Source!P42 -> 4581.28 | J64: =IF(Source!BC43<> 0, Source!BC43, 1) -> 7.66 | K64: =Source!P43 -> 35092.6 | Q64: =Source!X42 -> 0 | R64: =Source!X43 -> 0 | S64: =Source!Y42 -> 0 | T64: =Source!Y43 -> 0 | U64: =ROUND((175/100)*ROUND(Source!R42, 2), 2) -> 0 | V64: =ROUND((0/100)*ROUND(Source!R43, 2), 2) -> 0 | AC64: 5
C65: Всего по позиции: | H65: =I64+0 -> 4581.28 | J65: =K64+0 -> 35092.6 | O65: =I64+0 -> 4581.28 | P65: =K64+0 -> 35092.6
A67: 9 | B67: 3.7-60-4 Поправка: О.П. п.3.4.30.в | C67: Установка металлических ограждений без поручня | D67: =Source!H44 -> 100 м ограждений | E67: =Source!I44 -> 0.02 | Q67: =Source!X44 -> 13.15 | R67: =Source!X45 -> 722.84 | S67: =Source!Y44 -> 8.72 | T67: =Source!Y45 -> 479.7 | U67: =ROUND((175/100)*ROUND(Source!R44, 2), 2) -> 0.28 | V67: =ROUND((0/100)*ROUND(Source!R45, 2), 2) -> 0 | AC67: 0
C68: ="Объем: "&Source!I44&"=2/"&"100" -> Объем: 0,02=2/100
C69: ЗП | F69: =Source!AO44 -> 511.69 | G69: =Source!DG44 -> *1,1 | H69: =Source!AV45 -> 1.047 | I69: =Source!S44 -> 11.79 | J69: =IF(Source!BA45<> 0, Source!BA45, 1) -> 54.99 | K69: =Source!S45 -> 648.33
C70: ЭМ | F70: =Source!AM44 -> 58.27 | G70: =Source!DE44 -> *1,1 | H70: =Source!AV45 -> 1.047 | I70: =Source!Q44 -> 1.34 | J70: =IF(Source!BB45<> 0, Source!BB45, 1) -> 14.73 | K70: =Source!Q45 -> 19.74
C71: в т.ч. ЗПМ | F71: =Source!AN44 -> 6.79 | G71: =Source!DF44 -> *1,1 | H71: =Source!AV45 -> 1.047 | I71: =Source!R44 -> 0.16 | J71: =IF(Source!BS45<> 0, Source!BS45, 1) -> 54.99 | K71: =Source!R45 -> 8.8
A72: 9,1 | B72: =Source!F46 -> КА 5 | C72: Ограждение полуростовое BH02 PERCo 3 178,13 = [36 941 / 1,2 / 9,88] + 2% Заг.скл | D72: =Source!H46 -> м.п. | E72: =Source!I46 -> 2 | F72: =Source!AK46 -> 3178.13 | H72: =Source!AW47 -> 1 | I72: =Source!O46 -> 6356.26 | J72: =IF(Source!BC47<> 0, Source!BC47, 1) -> 9.88 | K72: =Source!O47 -> 62799.85 | Q72: =Source!X46 -> 0 | R72: =Source!X47 -> 0 | S72: =Source!Y46 -> 0 | T72: =Source!Y47 -> 0 | U72: =ROUND((175/100)*ROUND(Source!R46, 2), 2) -> 0 | V72: =ROUND((0/100)*ROUND(Source!R47, 2), 2) -> 0 | AC72: 3
A73: 9,2 | B73: =Source!F48 -> КА 6 | C73: Калитка одностворчатая PERCo 9 959,48 = [115 764,37 / 1,2 / 9,88] + 2% Заг.скл | D73: =Source!H48 -> шт. | E73: =Source!I48 -> 2 | F73: =Source!AK48 -> 9959.48 | H73: =Source!AW49 -> 1 | I73: =Source!O48 -> 19918.96 | J73: =IF(Source!BC49<> 0, Source!BC49, 1) -> 9.88 | K73: =Source!O49 -> 196799.32 | Q73: =Source!X48 -> 0 | R73: =Source!X49 -> 0 | S73: =Source!Y48 -> 0 | T73: =Source!Y49 -> 0 | U73: =ROUND((175/100)*ROUND(Source!R48, 2), 2) -> 0 | V73: =ROUND((0/100)*ROUND(Source!R49, 2), 2) -> 0 | AC73: 3
C74: НР от ФОТ | D74: % | E74: =Source!BZ45 -> 110 | I74: =SUM(Q67:Q73) -> 13.15 | J74: =Source!AT45 -> 110 | K74: =SUM(R67:R73) -> 722.84
C75: СП от ФОТ | D75: % | E75: =Source!CA45 -> 73 | I75: =SUM(S67:S74) -> 8.72 | J75: =Source!AU45 -> 73 | K75: =SUM(T67:T74) -> 479.7
C76: ЗТР | D76: чел-ч | E76: =Source!AQ44 -> 41.5 | G76: =Source!DI44 -> *1,1 | H76: =Source!AV45 -> 1.047 | I76: =Source!U44 -> 0.955911
C77: Всего по позиции: | H77: =I69+I70+I74+I75+SUM(I72:I73) -> 26310.22 | J77: =K69+K70+K74+K75+SUM(K72:K73) -> 261469.78 | O77: =I69+I70+I74+I75+SUM(I72:I73) -> 26310.22 | P77: =K69+K70+K74+K75+SUM(K72:K73) -> 261469.78
A80: =CONCATENATE("Итого по разделу: ",IF(Source!G51<>"Новый раздел", Source!G51, "")) -> Итого по разделу: Оборудование | H80: =SUM(O29:O79) -> 376172.05 | J80: =SUM(P29:P79) -> 2977265.6
A81: Итого по ТСН-2001.16 | I81: =SUM(W29:W80) -> 0 | J81: =SUM(X29:X80) -> 0
A82: Итого возвратных сумм | I82: =SUM(Y29:Y81) -> 0 | J82: =SUM(Z29:Z81) -> 0
A84: =CONCATENATE("Итого по локальной смете: ",IF(Source!G81<>"Новая локальная смета", Source!G81, "")) -> Итого по локальной смете: Мероприятия по противодействию террористическим актам | H84: =SUM(O28:O83) -> 376172.05 | J84: =SUM(P28:P83) -> 2977265.6 | AQ84: =CONCATENATE("Итого по локальной смете: ",IF(Source!G81<>"Новая локальная смета", Source!G81, "")) -> Итого по локальной смете: Мероприятия по противодействию террористическим актам
A85: Итого по ТСН-2001.16 | I85: =SUM(W28:W84) -> 0 | J85: =SUM(X28:X84) -> 0
A86: Итого возвратных сумм | I86: =SUM(Y28:Y85) -> 0 | J86: =SUM(Z28:Z85) -> 0
A89: Составил | C89: =IF(Source!AC12<>"", Source!AC12," ") | H89: =IF(Source!AB12<>"", Source!AB12," ") -> Кузнецова Е.А.
C90: (должность, подпись, инициалы, фамилия)
A92: Проверил | C92: =IF(Source!AE12<>"", Source!AE12," ") | H92: =IF(Source!AD12<>"", Source!AD12," ")
C93: (должность, подпись, инициалы, фамилия)

Sheet Ведомость объемов работ
A1: =Source!B1 -> Smeta.RU (495) 974-1589
E3: "УТВЕРЖДАЮ"
D5: ___________________________
D7: ___________________________
D9: " ___ " ___________ 20 ___ г.
B12: =CONCATENATE("Ведомость объемов работ ", IF(Source!AN15<>"", Source!AN15," ")) -> Ведомость объемов работ
B13: =CONCATENATE(Source!F12, " ", Source!G12) -> Новый объект (ТСН-2001 (Мосгосэкспертиза)) 02-01-20 ПТА
A16: № п/п | B16: № в ЛСР | C16: Наименование работ и затрат | D16: Единица измерения | E16: Количество | F16: Ссылка на чертежи, спецификации | G16: Формула расчета, расчет объемов работ и расхода материалов | H16: Примечание
A17: 1 | B17: 2 | C17: 3 | D17: 4 | E17: 5 | F17: 6 | G17: 7 | H17: 8
A18: =CONCATENATE("Локальная смета: ", Source!G20) -> Локальная смета: Мероприятия по противодействию террористическим актам
A19: =CONCATENATE("Раздел: ", Source!G24) -> Раздел: Оборудование
A20: 1 | B20: =Source!E28 -> 1 | C20: =Source!G28 -> Монтаж стационарного металлодетектора арочного типа | D20: 1 ШТ. | E20: =Source!I28 -> 2 | F20: =Source!U24 | G20: =Source!I28 -> 2
A21: 2 | B21: =Source!E30 -> 2 | C21: =Source!G30 -> Металлодетектор арочный Паутина-Н2-1 | D21: шт. | E21: =Source!I30 -> 2 | F21: =Source!U24 | G21: =Source!I30 -> 2
A22: 3 | B22: =Source!E32 -> 3 | C22: =Source!G32 -> Ручной металлодетектор «СФИНКС ВМ-611 РД-2.0» | D22: шт. | E22: =Source!I32 -> 3 | F22: =Source!U24 | G22: =Source!I32 -> 3
A23: 4 | B23: =Source!E34 -> 4 | C23: =Source!G34 -> Газоанализатор паров взрывчатых веществ «Кербер-Т» | D23: шт. | E23: =Source!I34 -> 1 | F23: =Source!U24 | G23: =Source!I34 -> 1
A24: 5 | B24: =Source!E36 -> 5 | C24: =Source!G36 -> Устройство для защиты от взрыва типа Фонтан-2 10У. Мобильное устройство для подавления не более 1000 г ТНТ, локализуемый объем до 15 дм3, выполнено в форме купола с двумя ручками, стенки и верх купола наполнены специальным диспенсером, поглощающим тепловую и ударную волну, габаритные размеры 610х610х365 мм | D24: шт. | E24: =Source!I36 -> 1 | F24: =Source!U24 | G24: =Source!I36 -> 1
A25: 6 | B25: =Source!E38 -> 6 | C25: =Source!G38 -> Устройство досмотровое (зеркало) для осмотра грузов, транспортных средств, неосвещенных и труднодоступных мест в помещениях. В составе: телескопическая штанга со встроенными светодиодами, с регулировкой длины от 600 до 1850 мм, набор зеркал различного размера и формы - 4 шт. Время непрерывной работы светодиодов не менее 9 часов, диапазон рабочих температур от -20 до +50°С | D25: КОМПЛЕКТ | E25: =Source!I38 -> 1 | F25: =Source!U24 | G25: =Source!I38 -> 1
A26: 7 | B26: =Source!E40 -> 7 | C26: =Source!G40 -> Установка штучных изделий столов, шкафов под мойки, холодильных шкафов и других | D26: 100 изделий | E26: =Source!I40 -> 0.04 | F26: =Source!U24 | G26: ="=4/"&"100" -> =4/100
A27: 8 | B27: =Source!E42 -> 8 | C27: =Source!G42 -> Стол досмотровый СД-950 (500х400х900) | D27: шт. | E27: =Source!I42 -> 4 | F27: =Source!U24 | G27: =Source!I42 -> 4
A28: 9 | B28: =Source!E44 -> 9 | C28: =Source!G44 -> Установка металлических ограждений без поручня | D28: 100 м ограждений | E28: =Source!I44 -> 0.02 | F28: =Source!U24 | G28: ="=2/"&"100" -> =2/100
A29: 9.1 | B29: =Source!E46 -> 9,1 | C29: =Source!G46 -> Ограждение полуростовое BH02 PERCo | D29: м.п. | E29: =Source!I46 -> 2 | F29: =Source!U24
A30: 9.2 | B30: =Source!E48 -> 9,2 | C30: =Source!G48 -> Калитка одностворчатая PERCo | D30: шт. | E30: =Source!I48 -> 2 | F30: =Source!U24
C33: Главный инженер проекта _________________ | D33: =IF(Source!X12<>"", Source!X12," ")
C35: Составил _________________ | D35: =IF(Source!AB12<>"", Source!AB12," ") -> Кузнецова Е.А.

Sheet Source
A1: 0 | B1: Smeta.RU (495) 974-1589 | D1: _PS_ | F1: 0 | G1: 0 | H1: 0 | I1: Smeta.RU | K1: 1 | L1: 74402 | M1: 10 | N1: 12 | O1: 0 | P1: 0 | Q1: 3
A4: 1 | B4: 1 | C4: -1 | G4: Капитальный ремонт здания Государственного бюджетного общеобразовательного учреждения города Москвы "Школа № 236" по адресу: г. Москва ул. Клязьминская, д. 7 к. 4. 1 этап | EC4: 0
A12: 1 | B12: 150 | C12: 0 | D12: =ROW(A111) -> 111 | E12: 0 | F12: Новый объект (ТСН-2001 (Мосгосэкспертиза)) | G12: 02-01-20 ПТА | I12: 0 | K12: 0 | L12: 0 | M12: 4098 | O12: 0 | P12: 0 | Q12: 0 | R12: 0 | S12: 0 | T12: 1 | V12: 0 | AB12: Кузнецова Е.А. | BB12: 0 | BH12: Сметные нормы списания | BI12: Коды ОКП для ТСН-2001 МГЭ Дополнение 80 | BJ12: 1 | BK12: 1 | BL12: 0 | BM12: 0 | BN12: 1 | BO12: 0 | BP12: 6 | BQ12: 2 | BR12: 1 | BS12: 1 | BT12: 0 | BU12: 0 | BV12: 1 | BW12: 0 | BX12: 0 | BZ12: Типовой расчет для ТСН-2001 МГЭ, Дополнение 80, строительство | CA12: Территориальные сметные нормативы для Москвы ТСН-2001 (МГЭ), дополнение 80 | CB12: Территориальные сметные нормативы для Москвы ТСН-2001 (МГЭ), дополнение 80 | CC12: Территориальные сметные нормативы для Москвы ТСН-2001 (МГЭ), дополнение 80 | CD12: Территориальные сметные нормативы для Москвы ТСН-2001 (МГЭ), дополнение 80 | CE12: Поправки для ТСН-2001 от 03.10.2025 г. доп.79 | CF12: 0 | CG12: 0 | CH12: 327688 | CK12: 80 | CQ12: Территориальные сметные нормативы для Москвы (ТСН-2001) | CR12: ТЕР | CS12: 41660 | CT12: 1 | CU12: 80 | CY12: 0 | EC12: 0
A15: 15 | B15: 1
A18: 52 | B18: =B111 -> 150 | C18: =C111 -> 1 | D18: =D111 -> 12 | E18: =E111 -> 0 | F18: =F111 -> Новый объект (ТСН-2001 (Мосгосэкспертиза)) | G18: =G111 -> 02-01-20 ПТА | O18: =O111 -> 376019.07 | P18: =P111 -> 375907.12 | Q18: =Q111 -> 12 | R18: =R111 -> 1.6 | S18: =S111 -> 99.95 | T18: =T111 -> 0 | U18: =U111 -> 8.0418206 | V18: =V111 -> 0 | ... GX18: =GX111 -> 0
A20: 3 | B20: 1 | D20: =ROW(A81) -> 81 | F20: 02-01-20 | G20: Мероприятия по противодействию террористическим актам | I20: 0 | J20: 2024-00272-01-0-ПТА | K20: -1 | L20: 02-01-20 | S20: 0 | T20: 0 | V20: 2 | BX20: 0 | CF20: 0 | CG20: 0
A22: 52 | B22: =B81 -> 1 | C22: =C81 -> 3 | D22: =D81 -> 20 | E22: =E81 -> 0 | F22: =F81 -> 02-01-20 | G22: =G81 -> Мероприятия по противодействию террористическим актам | O22: =O81 -> 376019.07 | P22: =P81 -> 375907.12 | Q22: =Q81 -> 12 | R22: =R81 -> 1.6 | S22: =S81 -> 99.95 | T22: =T81 -> 0 | U22: =U81 -> 8.0418206 | V22: =V81 -> 0 | ... GX22: =GX81 -> 0
A24: 4 | B24: 1 | D24: =ROW(A51) -> 51 | F24: Новый раздел | G24: Оборудование | I24: 0 | K24: 0 | S24: 0 | T24: 0 | V24: 2 | BX24: 0 | CJ24: 0
A26: 52 | B26: =B51 -> 1 | C26: =C51 -> 4 | D26: =D51 -> 24 | E26: =E51 -> 0 | F26: =F51 -> Новый раздел | G26: =G51 -> Оборудование | O26: =O51 -> 376019.07 | P26: =P51 -> 375907.12 | Q26: =Q51 -> 12 | R26: =R51 -> 1.6 | S26: =S51 -> 99.95 | T26: =T51 -> 0 | U26: =U51 -> 8.0418206 | V26: =V51 -> 0 | ... GX26: =GX51 -> 0
A28: 17 | B28: 1 | C28: =ROW(SmtRes!A3) -> 3 | D28: =ROW(EtalonRes!A4) -> 4 | E28: 1 | F28: 4.10-161-1 | G28: Монтаж стационарного металлодетектора арочного типа | H28: 1 ШТ. | I28: =ROUND(ROUND(2,4),9) -> 2 | J28: 0 | K28: =ROUND(ROUND(2,4),9) -> 2 | O28: =ROUND(CP28,2) -> 56.55 | P28: =ROUND((ROUND((AC28*AW28*I28),2)*BC28),2) -> 0 | Q28: =(ROUND((ROUND((((ET28*1.1))*AV28*I28),2)*BB28),2)+ROUND((ROUND(((AE28-((EU28*1.1)))*AV28*I28),2)*BS28),2)) -> 1.2 | R28: =ROUND((ROUND((AE28*AV28*I28),2)*BS28),2) -> 0 | S28: =ROUND((ROUND((AF28*AV28*I28),2)*BA28),2) -> 55.35 | T28: =ROUND(CU28*I28,2) -> 0 | U28: =CV28*I28 -> 3.967106 | V28: =CW28*I28 -> 0 | W28: =ROUND(CX28*I28,2) -> 0 | X28: =ROUND(CY28,2) -> 49.82 | Y28: =ROUND(CZ28,2) -> 25.46 | AA28: 59214062 | AB28: =ROUND((AC28+AD28+AF28),6) -> 26.499 | AC28: =ROUND(((ES28*1)),6) -> 0 | AD28: =ROUND(((((ET28*1.1))-((EU28*1.1)))+AE28),6) -> 0.561 | AE28: =ROUND(((EU28*1.1)),6) -> 0 | AF28: =ROUND(((EV28*1.1)),6) -> 25.938 | AG28: =ROUND((AP28),6) -> 0 | AH28: =((EW28*1.1)) -> 1.859 | AI28: =((EX28*1.1)) -> 0 | AJ28: =(AS28) -> 0 | AK28: 24.09 | AL28: 0 | AM28: 0.51 | AN28: 0 | AO28: 23.58 | AP28: 0 | AQ28: 1.69 | AR28: 0 | AS28: 0 | AT28: 90 | AU28: 46 | AV28: 1.067 | AW28: 1.028 | AZ28: 1 | BA28: 1 | BB28: 1 | BC28: 1 | BH28: 0 | BI28: 2 | BJ28: ТСН-2001.4 Доп. 68, Сб. 10, т. 161, поз. 1 | BM28: 68 | BN28: 58808062 | BO28: 4.10-161-1 | BP28: 1 | BQ28: 40 | BR28: 0 | BS28: 1 | BT28: 1 | BU28: 1 | BV28: 1 | BW28: 1 | BX28: 1 | BZ28: 90 | CA28: 46 | CE28: 30 | CF28: 0 | CG28: 0 | CM28: 0 | CN28: Поправка: Гл.12.Прил.8.п.8. 5_12.00.01.11.003 Наименование: При наличии усложненных условий производства работ (стесненность, сложность складирования и транспортной логистики, наличие в зоне производства работ действующего технологического оборудования или движения технологического транспорта и т.п.) для объектов, расположенных за пределами территории круговой магистральной системы улиц "Садовое кольцо" и за пределами Третьего транспортного кольца города Москвы пунктов "а" и "б", но в пределах Московской кольцевой автомобильной дороги | CO28: 0 | CP28: =(P28+Q28+S28) -> 56.55 | CQ28: =ROUND((ROUND((AC28*AW28*1),2)*BC28),2) -> 0 | CR28: =(ROUND((ROUND((((ET28*1.1))*AV28*1),2)*BB28),2)+ROUND((ROUND(((AE28-((EU28*1.1)))*AV28*1),2)*BS28),2)) -> 0.6 | CS28: =ROUND((ROUND((AE28*AV28*1),2)*BS28),2) -> 0 | CT28: =ROUND((ROUND((AF28*AV28*1),2)*BA28),2) -> 27.68 | CU28: =AG28 -> 0 | CV28: =(AH28*AV28) -> 1.983553 | CW28: =AI28 -> 0 | CX28: =AJ28 -> 0 | CY28: =(((S28+R28)*AT28)/100) -> 49.815 | CZ28: =(((S28+R28)*AU28)/100) -> 25.461 | DB28: 1 | DD28: *1 | DE28: *1,1 | DF28: *1,1 | DG28: *1,1 | DI28: *1,1 | DJ28: *1,1 | DN28: 0 | DO28: 0 | DP28: 1 | DQ28: 1 | DU28: 1013 | DV28: 1 ШТ. | DW28: 1 ШТ. | DX28: 1 | EE28: 58808178 | EF28: 40 | EG28: Монтаж оборудования | EH28: 0 | EJ28: 2 | EK28: 68 | EL28: ТСН-2001.4-10. Прокладка и монтаж сетей связи | EM28: ТСН-2001.4-10-1 | EO28: Поправка: Гл.12.Прил.8.п.8. 5_12.00.01.11.003 | EQ28: 0 | ER28: 24.09 | ES28: 0 | ET28: 0.51 | EU28: 0 | EV28: 23.58 | EW28: 1.69 | EX28: 0 | EY28: 0 | FQ28: 0 | FR28: 0 | FS28: 0 | FX28: 90 | FY28: 46 | GD28: 1 | GF28: 363374648 | GG28: 2 | GH28: 1 | GI28: 2 | GJ28: 0 | GK28: 0 | GL28: =ROUND(IF(AND(BH28=3,BI28=3,FS28<>0),P28,0),2) -> 0 | GM28: =ROUND(O28+X28+Y28,2)+GX28 -> 131.83 | GN28: =IF(OR(BI28=0,BI28=1),GM28-GX28,0) -> 0 | GO28: =IF(BI28=2,GM28-GX28,0) -> 131.83 | GP28: =IF(BI28=4,GM28-GX28,0) -> 0 | GR28: 0 | GS28: 3 | GT28: 0 | GV28: =ROUND((GT28),6) -> 0 | GW28: 1 | GX28: =ROUND(HC28*I28,2) -> 0 | HA28: 0 | HB28: 0 | HC28: =GV28*GW28 -> 0 | HS28: 0 | IK28: 0
A29: 17 | B29: 1 | C29: =ROW(SmtRes!A6) -> 6 | D29: =ROW(EtalonRes!A8) -> 8 | E29: 1 | F29: 4.10-161-1 | G29: Монтаж стационарного металлодетектора арочного типа | H29: 1 ШТ. | I29: =ROUND(ROUND(2,4),9) -> 2 | J29: 0 | K29: =ROUND(ROUND(2,4),9) -> 2 | O29: =ROUND(CP29,2) -> 3054.06 | P29: =ROUND((ROUND((AC29*AW29*I29),2)*BC29),2) -> 0 | Q29: =(ROUND((ROUND((((ET29*1.1))*AV29*I29),2)*BB29),2)+ROUND((ROUND(((AE29-((EU29*1.1)))*AV29*I29),2)*BS29),2)) -> 10.36 | R29: =ROUND((ROUND((AE29*AV29*I29),2)*BS29),2) -> 0 | S29: =ROUND((ROUND((AF29*AV29*I29),2)*BA29),2) -> 3043.7 | T29: =ROUND(CU29*I29,2) -> 0 | U29: =CV29*I29 -> 3.967106 | V29: =CW29*I29 -> 0 | W29: =ROUND(CX29*I29,2) -> 0 | X29: =ROUND(CY29,2) -> 2739.33 | Y29: =ROUND(CZ29,2) -> 1400.1 | AA29: 59214059 | AB29: =ROUND((AC29+AD29+AF29),6) -> 26.499 | AC29: =ROUND(((ES29*1)),6) -> 0 | AD29: =ROUND(((((ET29*1.1))-((EU29*1.1)))+AE29),6) -> 0.561 | AE29: =ROUND(((EU29*1.1)),6) -> 0 | AF29: =ROUND(((EV29*1.1)),6) -> 25.938 | AG29: =ROUND((AP29),6) -> 0 | AH29: =((EW29*1.1)) -> 1.859 | AI29: =((EX29*1.1)) -> 0 | AJ29: =(AS29) -> 0 | AK29: 24.09 | AL29: 0 | AM29: 0.51 | AN29: 0 | AO29: 23.58 | AP29: 0 | AQ29: 1.69 | AR29: 0 | AS29: 0 | AT29: 90 | AU29: 46 | AV29: 1.067 | AW29: 1.028 | AZ29: 1 | BA29: 54.99 | BB29: 8.63 | BC29: 1 | BH29: 0 | BI29: 2 | BJ29: ТСН-2001.4 Доп. 68, Сб. 10, т. 161, поз. 1 | BM29: 68 | BN29: 58808062 | BO29: 4.10-161-1 | BP29: 1 | BQ29: 40 | BR29: 0 | BS29: 54.99 | BT29: 1 | BU29: 1 | BV29: 1 | BW29: 1 | BX29: 1 | BZ29: 90 | CA29: 46 | CE29: 30 | CF29: 0 | CG29: 0 | CM29: 0 | CN29: Поправка: Гл.12.Прил.8.п.8. 5_12.00.01.11.003 Наименование: При наличии усложненных условий производства работ (стесненность, сложность складирования и транспортной логистики, наличие в зоне производства работ действующего технологического оборудования или движения технологического транспорта и т.п.) для объектов, расположенных за пределами территории круговой магистральной системы улиц "Садовое кольцо" и за пределами Третьего транспортного кольца города Москвы пунктов "а" и "б", но в пределах Московской кольцевой автомобильной дороги | CO29: 0 | CP29: =(P29+Q29+S29) -> 3054.06 | CQ29: =ROUND((ROUND((AC29*AW29*1),2)*BC29),2) -> 0 | CR29: =(ROUND((ROUND((((ET29*1.1))*AV29*1),2)*BB29),2)+ROUND((ROUND(((AE29-((EU29*1.1)))*AV29*1),2)*BS29),2)) -> 5.18 | CS29: =ROUND((ROUND((AE29*AV29*1),2)*BS29),2) -> 0 | CT29: =ROUND((ROUND((AF29*AV29*1),2)*BA29),2) -> 1522.12 | CU29: =AG29 -> 0 | CV29: =(AH29*AV29) -> 1.983553 | CW29: =AI29 -> 0 | CX29: =AJ29 -> 0 | CY29: =(((S29+R29)*AT29)/100) -> 2739.33 | CZ29: =(((S29+R29)*AU29)/100) -> 1400.102 | DB29: 2 | DD29: *1 | DE29: *1,1 | DF29: *1,1 | DG29: *1,1 | DI29: *1,1 | DJ29: *1,1 | DN29: 0 | DO29: 0 | DP29: 1 | DQ29: 1 | DU29: 1013 | DV29: 1 ШТ. | DW29: 1 ШТ. | DX29: 1 | EE29: 58808178 | EF29: 40 | EG29: Монтаж оборудования | EH29: 0 | EJ29: 2 | EK29: 68 | EL29: ТСН-2001.4-10. Прокладка и монтаж сетей связи | EM29: ТСН-2001.4-10-1 | EO29: Поправка: Гл.12.Прил.8.п.8. 5_12.00.01.11.003 | EQ29: 0 | ER29: 24.09 | ES29: 0 | ET29: 0.51 | EU29: 0 | EV29: 23.58 | EW29: 1.69 | EX29: 0 | EY29: 0 | FQ29: 0 | FR29: 0 | FS29: 0 | FX29: 90 | FY29: 46 | GD29: 1 | GF29: 363374648 | GG29: 2 | GH29: 1 | GI29: 2 | GJ29: 0 | GK29: 0 | GL29: =ROUND(IF(AND(BH29=3,BI29=3,FS29<>0),P29,0),2) -> 0 | GM29: =ROUND(O29+X29+Y29,2)+GX29 -> 7193.49 | GN29: =IF(OR(BI29=0,BI29=1),GM29-GX29,0) -> 0 | GO29: =IF(BI29=2,GM29-GX29,0) -> 7193.49 | GP29: =IF(BI29=4,GM29-GX29,0) -> 0 | GR29: 0 | GS29: 3 | GT29: 0 | GV29: =ROUND((GT29),6) -> 0 | GW29: 1 | GX29: =ROUND(HC29*I29,2) -> 0 | HA29: 0 | HB29: 0 | HC29: =GV29*GW29 -> 0 | HS29: 0 | IK29: 0
A30: 17 | B30: 1 | E30: 2 | F30: КА 1 | G30: Металлодетектор арочный Паутина-Н2-1 | H30: шт. | I30: =ROUND(ROUND(2,4),9) -> 2 | J30: 0 | K30: =ROUND(ROUND(2,4),9) -> 2 | O30: =ROUND(CP30,2) -> 66111.38 | P30: =ROUND((ROUND((AC30*I30),2)*BC30),2) -> 66111.38 | Q30: =(ROUND((ROUND(((ET30)*AV30*I30),2)*BB30),2)+ROUND((ROUND(((AE30-(EU30))*AV30*I30),2)*BS30),2)) -> 0 | R30: =ROUND((ROUND((AE30*AV30*I30),2)*BS30),2) -> 0 | S30: =ROUND((ROUND((AF30*AV30*I30),2)*BA30),2) -> 0 | T30: =ROUND(CU30*I30,2) -> 0 | U30: =CV30*I30 -> 0 | V30: =CW30*I30 -> 0 | W30: =ROUND(CX30*I30,2) -> 0 | X30: =ROUND(CY30,2) -> 0 | Y30: =ROUND(CZ30,2) -> 0 | AA30: 59214062 | AB30: =ROUND((AC30+AD30+AF30),6) -> 33055.69 | AC30: =ROUND((ES30),6) -> 33055.69 | AD30: =ROUND((((ET30)-(EU30))+AE30),6) -> 0 | AE30: =ROUND((EU30),6) -> 0 | AF30: =ROUND((EV30),6) -> 0 | AG30: =ROUND((AP30),6) -> 0 | AH30: =(EW30) -> 0 | AI30: =(EX30) -> 0 | AJ30: =(AS30) -> 0 | AK30: 33055.69 | AL30: 33055.69 | AM30: 0 | AN30: 0 | AO30: 0 | AP30: 0 | AQ30: 0 | AR30: 0 | AS30: 0 | AT30: 0 | AU30: 0 | AV30: 1 | AW30: 1 | AZ30: 1 | BA30: 1 | BB30: 1 | BC30: 1 | BH30: 3 | BI30: 3 | BM30: 746 | BN30: 0 | BP30: 0 | BQ30: 130 | BR30: 0 | BS30: 1 | BT30: 1 | BU30: 1 | BV30: 1 | BW30: 1 | BX30: 1 | BZ30: 0 | CA30: 0 | CE30: 30 | CF30: 0 | CG30: 0 | CM30: 0 | CO30: 0 | CP30: =(P30+Q30+S30) -> 66111.38 | CQ30: =ROUND((ROUND((AC30*1),2)*BC30),2) -> 33055.69 | CR30: =(ROUND((ROUND(((ET30)*AV30*1),2)*BB30),2)+ROUND((ROUND(((AE30-(EU30))*AV30*1),2)*BS30),2)) -> 0 | CS30: =ROUND((ROUND((AE30*AV30*1),2)*BS30),2) -> 0 | CT30: =ROUND((ROUND((AF30*AV30*1),2)*BA30),2) -> 0 | CU30: =AG30 -> 0 | CV30: =(AH30*AV30) -> 0 | CW30: =AI30 -> 0 | CX30: =AJ30 -> 0 | CY30: =(((S30+R30)*AT30)/100) -> 0 | CZ30: =(((S30+R30)*AU30)/100) -> 0 | DN30: 0 | DO30: 0 | DP30: 1 | DQ30: 1 | DU30: 1010 | DV30: шт. | DW30: шт. | DX30: 1 | EE30: 58808284 | EF30: 130 | EG30: Сметная стоимость оборудования | EH30: 0 | EJ30: 3 | EK30: 746 | EL30: ТСН-2001.13. Сметная стоимость оборудования | EM30: ТСН-2001.13 | EQ30: 0 | ER30: 0 | ES30: 33055.69 | ET30: 0 | EU30: 0 | EV30: 0 | EW30: 0 | EX30: 0 | EY30: 0 | FQ30: 0 | FR30: =P30 -> 66111.38 | FS30: 0 | FX30: 0 | FY30: 0 | GA30: [291 500 / 1,2 / 7,66] + 3% Трансп + 1,2% Заг.скл | GD30: 1 | GF30: -1911462648 | GG30: 2 | GH30: 4 | GI30: 0 | GJ30: 0 | GK30: 0 | GL30: =ROUND(IF(AND(BH30=3,BI30=3,FS30<>0),P30,0),2) -> 0 | GM30: =ROUND(O30+X30+Y30,2)+GX30 -> 66111.38 | GN30: =IF(OR(BI30=0,BI30=1),GM30-GX30,0) -> 0 | GO30: =IF(BI30=2,GM30-GX30,0) -> 0 | GP30: =IF(BI30=4,GM30-GX30,0) -> 0 | GR30: 2 | GS30: 2 | GT30: 0 | GV30: =ROUND((GT30),6) -> 0 | GW30: 1 | GX30: =ROUND(HC30*I30,2) -> 0 | HA30: 0 | HB30: 0 | HC30: =GV30*GW30 -> 0 | HE30: 3 | HF30: 1,2 | HS30: 0 | IK30: 0
A31: 17 | B31: 1 | E31: 2 | F31: КА 1 | G31: Металлодетектор арочный Паутина-Н2-1 | H31: шт. | I31: =ROUND(ROUND(2,4),9) -> 2 | J31: 0 | K31: =ROUND(ROUND(2,4),9) -> 2 | O31: =ROUND(CP31,2) -> 506413.17 | P31: =ROUND((ROUND((AC31*I31),2)*BC31),2) -> 506413.17 | Q31: =(ROUND((ROUND(((ET31)*AV31*I31),2)*BB31),2)+ROUND((ROUND(((AE31-(EU31))*AV31*I31),2)*BS31),2)) -> 0 | R31: =ROUND((ROUND((AE31*AV31*I31),2)*BS31),2) -> 0 | S31: =ROUND((ROUND((AF31*AV31*I31),2)*BA31),2) -> 0 | T31: =ROUND(CU31*I31,2) -> 0 | U31: =CV31*I31 -> 0 | V31: =CW31*I31 -> 0 | W31: =ROUND(CX31*I31,2) -> 0 | X31: =ROUND(CY31,2) -> 0 | Y31: =ROUND(CZ31,2) -> 0 | AA31: 59214059 | AB31: =ROUND((AC31+AD31+AF31),6) -> 33055.69 | AC31: =ROUND((ES31),6) -> 33055.69 | AD31: =ROUND((((ET31)-(EU31))+AE31),6) -> 0 | AE31: =ROUND((EU31),6) -> 0 | AF31: =ROUND((EV31),6) -> 0 | AG31: =ROUND((AP31),6) -> 0 | AH31: =(EW31) -> 0 | AI31: =(EX31) -> 0 | AJ31: =(AS31) -> 0 | AK31: 33055.69 | AL31: 33055.69 | AM31: 0 | AN31: 0 | AO31: 0 | AP31: 0 | AQ31: 0 | AR31: 0 | AS31: 0 | AT31: 0 | AU31: 0 | AV31: 1 | AW31: 1 | AZ31: 1 | BA31: 1 | BB31: 1 | BC31: 7.66 | BH31: 3 | BI31: 3 | BM31: 746 | BN31: 0 | BP31: 0 | BQ31: 130 | BR31: 0 | BS31: 1 | BT31: 1 | BU31: 1 | BV31: 1 | BW31: 1 | BX31: 1 | BZ31: 0 | CA31: 0 | CE31: 30 | CF31: 0 | CG31: 0 | CM31: 0 | CO31: 0 | CP31: =(P31+Q31+S31) -> 506413.17 | CQ31: =ROUND((ROUND((AC31*1),2)*BC31),2) -> 253206.59 | CR31: =(ROUND((ROUND(((ET31)*AV31*1),2)*BB31),2)+ROUND((ROUND(((AE31-(EU31))*AV31*1),2)*BS31),2)) -> 0 | CS31: =ROUND((ROUND((AE31*AV31*1),2)*BS31),2) -> 0 | CT31: =ROUND((ROUND((AF31*AV31*1),2)*BA31),2) -> 0 | CU31: =AG31 -> 0 | CV31: =(AH31*AV31) -> 0 | CW31: =AI31 -> 0 | CX31: =AJ31 -> 0 | CY31: =(((S31+R31)*AT31)/100) -> 0 | CZ31: =(((S31+R31)*AU31)/100) -> 0 | DN31: 0 | DO31: 0 | DP31: 1 | DQ31: 1 | DU31: 1010 | DV31: шт. | DW31: шт. | DX31: 1 | EE31: 58808284 | EF31: 130 | EG31: Сметная стоимость оборудования | EH31: 0 | EJ31: 3 | EK31: 746 | EL31: ТСН-2001.13. Сметная стоимость оборудования | EM31: ТСН-2001.13 | EQ31: 0 | ER31: 0 | ES31: 33055.69 | ET31: 0 | EU31: 0 | EV31: 0 | EW31: 0 | EX31: 0 | EY31: 0 | EZ31: 5 | FC31: 1 | FD31: 18 | FF31: 291500 | FQ31: 0 | FR31: =P31 -> 506413.17 | FS31: 0 | FX31: 0 | FY31: 0 | GA31: [291 500 / 1,2 / 7,66] + 3% Трансп + 1,2% Заг.скл | GD31: 1 | GF31: -1911462648 | GG31: 2 | GH31: 2 | GI31: 5 | GJ31: 0 | GK31: 0 | GL31: =ROUND(IF(AND(BH31=3,BI31=3,FS31<>0),P31,0),2) -> 0 | GM31: =ROUND(O31+X31+Y31,2)+GX31 -> 506413.17 | GN31: =IF(OR(BI31=0,BI31=1),GM31-GX31,0) -> 0 | GO31: =IF(BI31=2,GM31-GX31,0) -> 0 | GP31: =IF(BI31=4,GM31-GX31,0) -> 0 | GR31: 2 | GS31: 1 | GT31: 0 | GV31: =ROUND((GT31),6) -> 0 | GW31: 1 | GX31: =ROUND(HC31*I31,2) -> 0 | HA31: 0 | HB31: 0 | HC31: =GV31*GW31 -> 0 | HE31: 3 | HF31: 1,2 | HS31: 0 | IK31: 0
A32: 17 | B32: 1 | E32: 3 | F32: КА 2 | G32: Ручной металлодетектор «СФИНКС ВМ-611 РД-2.0» | H32: шт. | I32: =ROUND(ROUND(3,4),9) -> 3 | J32: 0 | K32: =ROUND(ROUND(3,4),9) -> 3 | O32: =ROUND(CP32,2) -> 20394.75 | P32: =ROUND((ROUND((AC32*I32),2)*BC32),2) -> 20394.75 | Q32: =(ROUND((ROUND(((ET32)*AV32*I32),2)*BB32),2)+ROUND((ROUND(((AE32-(EU32))*AV32*I32),2)*BS32),2)) -> 0 | R32: =ROUND((ROUND((AE32*AV32*I32),2)*BS32),2) -> 0 | S32: =ROUND((ROUND((AF32*AV32*I32),2)*BA32),2) -> 0 | T32: =ROUND(CU32*I32,2) -> 0 | U32: =CV32*I32 -> 0 | V32: =CW32*I32 -> 0 | W32: =ROUND(CX32*I32,2) -> 0 | X32: =ROUND(CY32,2) -> 0 | Y32: =ROUND(CZ32,2) -> 0 | AA32: 59214062 | AB32: =ROUND((AC32+AD32+AF32),6) -> 6798.25 | AC32: =ROUND((ES32),6) -> 6798.25 | AD32: =ROUND((((ET32)-(EU32))+AE32),6) -> 0 | AE32: =ROUND((EU32),6) -> 0 | AF32: =ROUND((EV32),6) -> 0 | AG32: =ROUND((AP32),6) -> 0 | AH32: =(EW32) -> 0 | AI32: =(EX32) -> 0 | AJ32: =(AS32) -> 0 | AK32: 6798.25 | AL32: 6798.25 | AM32: 0 | AN32: 0 | AO32: 0 | AP32: 0 | AQ32: 0 | AR32: 0 | AS32: 0 | AT32: 0 | AU32: 0 | AV32: 1 | AW32: 1 | AZ32: 1 | BA32: 1 | BB32: 1 | BC32: 1 | BH32: 3 | BI32: 3 | BM32: 746 | BN32: 0 | BP32: 0 | BQ32: 130 | BR32: 0 | BS32: 1 | BT32: 1 | BU32: 1 | BV32: 1 | BW32: 1 | BX32: 1 | BZ32: 0 | CA32: 0 | CE32: 30 | CF32: 0 | CG32: 0 | CM32: 0 | CO32: 0 | CP32: =(P32+Q32+S32) -> 20394.75 | CQ32: =ROUND((ROUND((AC32*1),2)*BC32),2) -> 6798.25 | CR32: =(ROUND((ROUND(((ET32)*AV32*1),2)*BB32),2)+ROUND((ROUND(((AE32-(EU32))*AV32*1),2)*BS32),2)) -> 0 | CS32: =ROUND((ROUND((AE32*AV32*1),2)*BS32),2) -> 0 | CT32: =ROUND((ROUND((AF32*AV32*1),2)*BA32),2) -> 0 | CU32: =AG32 -> 0 | CV32: =(AH32*AV32) -> 0 | CW32: =AI32 -> 0 | CX32: =AJ32 -> 0 | CY32: =(((S32+R32)*AT32)/100) -> 0 | CZ32: =(((S32+R32)*AU32)/100) -> 0 | DN32: 0 | DO32: 0 | DP32: 1 | DQ32: 1 | DU32: 1010 | DV32: шт. | DW32: шт. | DX32: 1 | EE32: 58808284 | EF32: 130 | EG32: Сметная стоимость оборудования | EH32: 0 | EJ32: 3 | EK32: 746 | EL32: ТСН-2001.13. Сметная стоимость оборудования | EM32: ТСН-2001.13 | EQ32: 0 | ER32: 0 | ES32: 6798.25 | ET32: 0 | EU32: 0 | EV32: 0 | EW32: 0 | EX32: 0 | EY32: 0 | FQ32: 0 | FR32: =P32 -> 20394.75 | FS32: 0 | FX32: 0 | FY32: 0 | GA32: [59 950 / 1,2 / 7,66] + 3% Трансп + 1,2% Заг.скл | GD32: 1 | GF32: -338370289 | GG32: 2 | GH32: 4 | GI32: 0 | GJ32: 0 | GK32: 0 | GL32: =ROUND(IF(AND(BH32=3,BI32=3,FS32<>0),P32,0),2) -> 0 | GM32: =ROUND(O32+X32+Y32,2)+GX32 -> 20394.75 | GN32: =IF(OR(BI32=0,BI32=1),GM32-GX32,0) -> 0 | GO32: =IF(BI32=2,GM32-GX32,0) -> 0 | GP32: =IF(BI32=4,GM32-GX32,0) -> 0 | GR32: 2 | GS32: 2 | GT32: 0 | GV32: =ROUND((GT32),6) -> 0 | GW32: 1 | GX32: =ROUND(HC32*I32,2) -> 0 | HA32: 0 | HB32: 0 | HC32: =GV32*GW32 -> 0 | HE32: 3 | HF32: 1,2 | HS32: 0 | IK32: 0
A33: 17 | B33: 1 | E33: 3 | F33: КА 2 | G33: Ручной металлодетектор «СФИНКС ВМ-611 РД-2.0» | H33: шт. | I33: =ROUND(ROUND(3,4),9) -> 3 | J33: 0 | K33: =ROUND(ROUND(3,4),9) -> 3 | O33: =ROUND(CP33,2) -> 156223.79 | P33: =ROUND((ROUND((AC33*I33),2)*BC33),2) -> 156223.79 | Q33: =(ROUND((ROUND(((ET33)*AV33*I33),2)*BB33),2)+ROUND((ROUND(((AE33-(EU33))*AV33*I33),2)*BS33),2)) -> 0 | R33: =ROUND((ROUND((AE33*AV33*I33),2)*BS33),2) -> 0 | S33: =ROUND((ROUND((AF33*AV33*I33),2)*BA33),2) -> 0 | T33: =ROUND(CU33*I33,2) -> 0 | U33: =CV33*I33 -> 0 | V33: =CW33*I33 -> 0 | W33: =ROUND(CX33*I33,2) -> 0 | X33: =ROUND(CY33,2) -> 0 | Y33: =ROUND(CZ33,2) -> 0 | AA33: 59214059 | AB33: =ROUND((AC33+AD33+AF33),6) -> 6798.25 | AC33: =ROUND((ES33),6) -> 6798.25 | AD33: =ROUND((((ET33)-(EU33))+AE33),6) -> 0 | AE33: =ROUND((EU33),6) -> 0 | AF33: =ROUND((EV33),6) -> 0 | AG33: =ROUND((AP33),6) -> 0 | AH33: =(EW33) -> 0 | AI33: =(EX33) -> 0 | AJ33: =(AS33) -> 0 | AK33: 6798.25 | AL33: 6798.25 | AM33: 0 | AN33: 0 | AO33: 0 | AP33: 0 | AQ33: 0 | AR33: 0 | AS33: 0 | AT33: 0 | AU33: 0 | AV33: 1 | AW33: 1 | AZ33: 1 | BA33: 1 | BB33: 1 | BC33: 7.66 | BH33: 3 | BI33: 3 | BM33: 746 | BN33: 0 | BP33: 0 | BQ33: 130 | BR33: 0 | BS33: 1 | BT33: 1 | BU33: 1 | BV33: 1 | BW33: 1 | BX33: 1 | BZ33: 0 | CA33: 0 | CE33: 30 | CF33: 0 | CG33: 0 | CM33: 0 | CO33: 0 | CP33: =(P33+Q33+S33) -> 156223.79 | CQ33: =ROUND((ROUND((AC33*1),2)*BC33),2) -> 52074.6 | CR33: =(ROUND((ROUND(((ET33)*AV33*1),2)*BB33),2)+ROUND((ROUND(((AE33-(EU33))*AV33*1),2)*BS33),2)) -> 0 | CS33: =ROUND((ROUND((AE33*AV33*1),2)*BS33),2) -> 0 | CT33: =ROUND((ROUND((AF33*AV33*1),2)*BA33),2) -> 0 | CU33: =AG33 -> 0 | CV33: =(AH33*AV33) -> 0 | CW33: =AI33 -> 0 | CX33: =AJ33 -> 0 | CY33: =(((S33+R33)*AT33)/100) -> 0 | CZ33: =(((S33+R33)*AU33)/100) -> 0 | DN33: 0 | DO33: 0 | DP33: 1 | DQ33: 1 | DU33: 1010 | DV33: шт. | DW33: шт. | DX33: 1 | EE33: 58808284 | EF33: 130 | EG33: Сметная стоимость оборудования | EH33: 0 | EJ33: 3 | EK33: 746 | EL33: ТСН-2001.13. Сметная стоимость оборудования | EM33: ТСН-2001.13 | EQ33: 0 | ER33: 0 | ES33: 6798.25 | ET33: 0 | EU33: 0 | EV33: 0 | EW33: 0 | EX33: 0 | EY33: 0 | EZ33: 5 | FC33: 1 | FD33: 18 | FF33: 59950 | FQ33: 0 | FR33: =P33 -> 156223.79 | FS33: 0 | FX33: 0 | FY33: 0 | GA33: [59 950 / 1,2 / 7,66] + 3% Трансп + 1,2% Заг.скл | GD33: 1 | GF33: -338370289 | GG33: 2 | GH33: 2 | GI33: 5 | GJ33: 0 | GK33: 0 | GL33: =ROUND(IF(AND(BH33=3,BI33=3,FS33<>0),P33,0),2) -> 0 | GM33: =ROUND(O33+X33+Y33,2)+GX33 -> 156223.79 | GN33: =IF(OR(BI33=0,BI33=1),GM33-GX33,0) -> 0 | GO33: =IF(BI33=2,GM33-GX33,0) -> 0 | GP33: =IF(BI33=4,GM33-GX33,0) -> 0 | GR33: 2 | GS33: 1 | GT33: 0 | GV33: =ROUND((GT33),6) -> 0 | GW33: 1 | GX33: =ROUND(HC33*I33,2) -> 0 | HA33: 0 | HB33: 0 | HC33: =GV33*GW33 -> 0 | HE33: 3 | HF33: 1,2 | HS33: 0 | IK33: 0
A34: 17 | B34: 1 | E34: 4 | F34: КА 3 | G34: Газоанализатор паров взрывчатых веществ «Кербер-Т» | H34: шт. | I34: =ROUND(ROUND(1,4),9) -> 1 | J34: 0 | K34: =ROUND(ROUND(1,4),9) -> 1 | O34: =ROUND(CP34,2) -> 249476.94 | P34: =ROUND((ROUND((AC34*I34),2)*BC34),2) -> 249476.94 | Q34: =(ROUND((ROUND(((ET34)*AV34*I34),2)*BB34),2)+ROUND((ROUND(((AE34-(EU34))*AV34*I34),2)*BS34),2)) -> 0 | R34: =ROUND((ROUND((AE34*AV34*I34),2)*BS34),2) -> 0 | S34: =ROUND((ROUND((AF34*AV34*I34),2)*BA34),2) -> 0 | T34: =ROUND(CU34*I34,2) -> 0 | U34: =CV34*I34 -> 0 | V34: =CW34*I34 -> 0 | W34: =ROUND(CX34*I34,2) -> 0 | X34: =ROUND(CY34,2) -> 0 | Y34: =ROUND(CZ34,2) -> 0 | AA34: 59214062 | AB34: =ROUND((AC34+AD34+AF34),6) -> 249476.94 | AC34: =ROUND((ES34),6) -> 249476.94 | AD34: =ROUND((((ET34)-(EU34))+AE34),6) -> 0 | AE34: =ROUND((EU34),6) -> 0 | AF34: =ROUND((EV34),6) -> 0 | AG34: =ROUND((AP34),6) -> 0 | AH34: =(EW34) -> 0 | AI34: =(EX34) -> 0 | AJ34: =(AS34) -> 0 | AK34: 249476.94 | AL34: 249476.94 | AM34: 0 | AN34: 0 | AO34: 0 | AP34: 0 | AQ34: 0 | AR34: 0 | AS34: 0 | AT34: 0 | AU34: 0 | AV34: 1 | AW34: 1 | AZ34: 1 | BA34: 1 | BB34: 1 | BC34: 1 | BH34: 3 | BI34: 3 | BM34: 746 | BN34: 0 | BP34: 0 | BQ34: 130 | BR34: 0 | BS34: 1 | BT34: 1 | BU34: 1 | BV34: 1 | BW34: 1 | BX34: 1 | BZ34: 0 | CA34: 0 | CE34: 30 | CF34: 0 | CG34: 0 | CM34: 0 | CO34: 0 | CP34: =(P34+Q34+S34) -> 249476.94 | CQ34: =ROUND((ROUND((AC34*1),2)*BC34),2) -> 249476.94 | CR34: =(ROUND((ROUND(((ET34)*AV34*1),2)*BB34),2)+ROUND((ROUND(((AE34-(EU34))*AV34*1),2)*BS34),2)) -> 0 | CS34: =ROUND((ROUND((AE34*AV34*1),2)*BS34),2) -> 0 | CT34: =ROUND((ROUND((AF34*AV34*1),2)*BA34),2) -> 0 | CU34: =AG34 -> 0 | CV34: =(AH34*AV34) -> 0 | CW34: =AI34 -> 0 | CX34: =AJ34 -> 0 | CY34: =(((S34+R34)*AT34)/100) -> 0 | CZ34: =(((S34+R34)*AU34)/100) -> 0 | DN34: 0 | DO34: 0 | DP34: 1 | DQ34: 1 | DU34: 1010 | DV34: шт. | DW34: шт. | DX34: 1 | EE34: 58808284 | EF34: 130 | EG34: Сметная стоимость оборудования | EH34: 0 | EJ34: 3 | EK34: 746 | EL34: ТСН-2001.13. Сметная стоимость оборудования | EM34: ТСН-2001.13 | EQ34: 0 | ER34: 0 | ES34: 249476.94 | ET34: 0 | EU34: 0 | EV34: 0 | EW34: 0 | EX34: 0 | EY34: 0 | FQ34: 0 | FR34: =P34 -> 249476.94 | FS34: 0 | FX34: 0 | FY34: 0 | GA34: [2 200 000 / 1,2 / 7,66] + 3% Трансп + 1,2% Заг.скл | GD34: 1 | GF34: -709671177 | GG34: 2 | GH34: 4 | GI34: 0 | GJ34: 0 | GK34: 0 | GL34: =ROUND(IF(AND(BH34=3,BI34=3,FS34<>0),P34,0),2) -> 0 | GM34: =ROUND(O34+X34+Y34,2)+GX34 -> 249476.94 | GN34: =IF(OR(BI34=0,BI34=1),GM34-GX34,0) -> 0 | GO34: =IF(BI34=2,GM34-GX34,0) -> 0 | GP34: =IF(BI34=4,GM34-GX34,0) -> 0 | GR34: 2 | GS34: 2 | GT34: 0 | GV34: =ROUND((GT34),6) -> 0 | GW34: 1 | GX34: =ROUND(HC34*I34,2) -> 0 | HA34: 0 | HB34: 0 | HC34: =GV34*GW34 -> 0 | HE34: 3 | HF34: 1,2 | HS34: 0 | IK34: 0
A35: 17 | B35: 1 | E35: 4 | F35: КА 3 | G35: Газоанализатор паров взрывчатых веществ «Кербер-Т» | H35: шт. | I35: =ROUND(ROUND(1,4),9) -> 1 | J35: 0 | K35: =ROUND(ROUND(1,4),9) -> 1 | O35: =ROUND(CP35,2) -> 1910993.4 | P35: =ROUND((ROUND((AC35*I35),2)*BC35),2) -> 1910993.4 | Q35: =(ROUND((ROUND(((ET35)*AV35*I35),2)*BB35),2)+ROUND((ROUND(((AE35-(EU35))*AV35*I35),2)*BS35),2)) -> 0 | R35: =ROUND((ROUND((AE35*AV35*I35),2)*BS35),2) -> 0 | S35: =ROUND((ROUND((AF35*AV35*I35),2)*BA35),2) -> 0 | T35: =ROUND(CU35*I35,2) -> 0 | U35: =CV35*I35 -> 0 | V35: =CW35*I35 -> 0 | W35: =ROUND(CX35*I35,2) -> 0 | X35: =ROUND(CY35,2) -> 0 | Y35: =ROUND(CZ35,2) -> 0 | AA35: 59214059 | AB35: =ROUND((AC35+AD35+AF35),6) -> 249476.94 | AC35: =ROUND((ES35),6) -> 249476.94 | AD35: =ROUND((((ET35)-(EU35))+AE35),6) -> 0 | AE35: =ROUND((EU35),6) -> 0 | AF35: =ROUND((EV35),6) -> 0 | AG35: =ROUND((AP35),6) -> 0 | AH35: =(EW35) -> 0 | AI35: =(EX35) -> 0 | AJ35: =(AS35) -> 0 | AK35: 249476.94 | AL35: 249476.94 | AM35: 0 | AN35: 0 | AO35: 0 | AP35: 0 | AQ35: 0 | AR35: 0 | AS35: 0 | AT35: 0 | AU35: 0 | AV35: 1 | AW35: 1 | AZ35: 1 | BA35: 1 | BB35: 1 | BC35: 7.66 | BH35: 3 | BI35: 3 | BM35: 746 | BN35: 0 | BP35: 0 | BQ35: 130 | BR35: 0 | BS35: 1 | BT35: 1 | BU35: 1 | BV35: 1 | BW35: 1 | BX35: 1 | BZ35: 0 | CA35: 0 | CE35: 30 | CF35: 0 | CG35: 0 | CM35: 0 | CO35: 0 | CP35: =(P35+Q35+S35) -> 1910993.4 | CQ35: =ROUND((ROUND((AC35*1),2)*BC35),2) -> 1910993.4 | CR35: =(ROUND((ROUND(((ET35)*AV35*1),2)*BB35),2)+ROUND((ROUND(((AE35-(EU35))*AV35*1),2)*BS35),2)) -> 0 | CS35: =ROUND((ROUND((AE35*AV35*1),2)*BS35),2) -> 0 | CT35: =ROUND((ROUND((AF35*AV35*1),2)*BA35),2) -> 0 | CU35: =AG35 -> 0 | CV35: =(AH35*AV35) -> 0 | CW35: =AI35 -> 0 | CX35: =AJ35 -> 0 | CY35: =(((S35+R35)*AT35)/100) -> 0 | CZ35: =(((S35+R35)*AU35)/100) -> 0 | DN35: 0 | DO35: 0 | DP35: 1 | DQ35: 1 | DU35: 1010 | DV35: шт. | DW35: шт. | DX35: 1 | EE35: 58808284 | EF35: 130 | EG35: Сметная стоимость оборудования | EH35: 0 | EJ35: 3 | EK35: 746 | EL35: ТСН-2001.13. Сметная стоимость оборудования | EM35: ТСН-2001.13 | EQ35: 0 | ER35: 0 | ES35: 249476.94 | ET35: 0 | EU35: 0 | EV35: 0 | EW35: 0 | EX35: 0 | EY35: 0 | EZ35: 5 | FC35: 1 | FD35: 18 | FF35: 2200000 | FQ35: 0 | FR35: =P35 -> 1910993.4 | FS35: 0 | FX35: 0 | FY35: 0 | GA35: [2 200 000 / 1,2 / 7,66] + 3% Трансп + 1,2% Заг.скл | GD35: 1 | GF35: -709671177 | GG35: 2 | GH35: 2 | GI35: 5 | GJ35: 0 | GK35: 0 | GL35: =ROUND(IF(AND(BH35=3,BI35=3,FS35<>0),P35,0),2) -> 0 | GM35: =ROUND(O35+X35+Y35,2)+GX35 -> 1910993.4 | GN35: =IF(OR(BI35=0,BI35=1),GM35-GX35,0) -> 0 | GO35: =IF(BI35=2,GM35-GX35,0) -> 0 | GP35: =IF(BI35=4,GM35-GX35,0) -> 0 | GR35: 2 | GS35: 1 | GT35: 0 | GV35: =ROUND((GT35),6) -> 0 | GW35: 1 | GX35: =ROUND(HC35*I35,2) -> 0 | HA35: 0 | HB35: 0 | HC35: =GV35*GW35 -> 0 | HE35: 3 | HF35: 1,2 | HS35: 0 | IK35: 0
A36: 17 | B36: 1 | E36: 5 | F36: 13.3-9-180 | G36: Устройство для защиты от взрыва типа Фонтан-2 10У. Мобильное устройство для подавления не более 1000 г ТНТ, локализуемый объем до 15 дм3, выполнено в форме купола с двумя ручками, стенки и верх купола наполнены специальным диспенсером, поглощающим тепловую и ударную волну, габаритные размеры 610х610х365 мм | H36: шт. | I36: =ROUND(ROUND(1,4),9) -> 1 | J36: 0 | K36: =ROUND(ROUND(1,4),9) -> 1 | O36: =ROUND(CP36,2) -> 8188.38 | P36: =ROUND((ROUND((AC36*I36),2)*BC36),2) -> 8188.38 | Q36: =(ROUND((ROUND(((ET36)*AV36*I36),2)*BB36),2)+ROUND((ROUND(((AE36-(EU36))*AV36*I36),2)*BS36),2)) -> 0 | R36: =ROUND((ROUND((AE36*AV36*I36),2)*BS36),2) -> 0 | S36: =ROUND((ROUND((AF36*AV36*I36),2)*BA36),2) -> 0 | T36: =ROUND(CU36*I36,2) -> 0 | U36: =CV36*I36 -> 0 | V36: =CW36*I36 -> 0 | W36: =ROUND(CX36*I36,2) -> 0 | X36: =ROUND(CY36,2) -> 0 | Y36: =ROUND(CZ36,2) -> 0 | AA36: 59214062 | AB36: =ROUND((AC36+AD36+AF36),6) -> 8188.38 | AC36: =ROUND((ES36),6) -> 8188.38 | AD36: =ROUND((((ET36)-(EU36))+AE36),6) -> 0 | AE36: =ROUND((EU36),6) -> 0 | AF36: =ROUND((EV36),6) -> 0 | AG36: =ROUND((AP36),6) -> 0 | AH36: =(EW36) -> 0 | AI36: =(EX36) -> 0 | AJ36: =(AS36) -> 0 | AK36: 8188.38 | AL36: 8188.38 | AM36: 0 | AN36: 0 | AO36: 0 | AP36: 0 | AQ36: 0 | AR36: 0 | AS36: 0 | AT36: 0 | AU36: 0 | AV36: 1 | AW36: 1 | AZ36: 1 | BA36: 1 | BB36: 1 | BC36: 1 | BH36: 3 | BI36: 3 | BM36: 746 | BN36: 58808062 | BP36: 0 | BQ36: 130 | BR36: 0 | BS36: 1 | BT36: 1 | BU36: 1 | BV36: 1 | BW36: 1 | BX36: 1 | BZ36: 0 | CA36: 0 | CE36: 30 | CF36: 0 | CG36: 0 | CM36: 0 | CO36: 0 | CP36: =(P36+Q36+S36) -> 8188.38 | CQ36: =ROUND((ROUND((AC36*1),2)*BC36),2) -> 8188.38 | CR36: =(ROUND((ROUND(((ET36)*AV36*1),2)*BB36),2)+ROUND((ROUND(((AE36-(EU36))*AV36*1),2)*BS36),2)) -> 0 | CS36: =ROUND((ROUND((AE36*AV36*1),2)*BS36),2) -> 0 | CT36: =ROUND((ROUND((AF36*AV36*1),2)*BA36),2) -> 0 | CU36: =AG36 -> 0 | CV36: =(AH36*AV36) -> 0 | CW36: =AI36 -> 0 | CX36: =AJ36 -> 0 | CY36: =(((S36+R36)*AT36)/100) -> 0 | CZ36: =(((S36+R36)*AU36)/100) -> 0 | DN36: 0 | DO36: 0 | DP36: 1 | DQ36: 1 | DU36: 1010 | DV36: шт. | DW36: шт. | DX36: 1 | EE36: 58808284 | EF36: 130 | EG36: Сметная стоимость оборудования | EH36: 0 | EJ36: 3 | EK36: 746 | EL36: ТСН-2001.13. Сметная стоимость оборудования | EM36: ТСН-2001.13 | EQ36: 0 | ER36: 8188.38 | ES36: 8188.38 | ET36: 0 | EU36: 0 | EV36: 0 | EW36: 0 | EX36: 0 | EY36: 0 | FQ36: 0 | FR36: =P36 -> 8188.38 | FS36: 0 | FX36: 0 | FY36: 0 | GD36: 1 | GF36: 844771149 | GG36: 2 | GH36: 1 | GI36: -2 | GJ36: 0 | GK36: 0 | GL36: =ROUND(IF(AND(BH36=3,BI36=3,FS36<>0),P36,0),2) -> 0 | GM36: =ROUND(O36+X36+Y36,2)+GX36 -> 8188.38 | GN36: =IF(OR(BI36=0,BI36=1),GM36-GX36,0) -> 0 | GO36: =IF(BI36=2,GM36-GX36,0) -> 0 | GP36: =IF(BI36=4,GM36-GX36,0) -> 0 | GR36: 0 | GS36: 3 | GT36: 0 | GV36: =ROUND((GT36),6) -> 0 | GW36: 1 | GX36: =ROUND(HC36*I36,2) -> 0 | HA36: 0 | HB36: 0 | HC36: =GV36*GW36 -> 0 | HS36: 0 | IK36: 0
A37: 17 | B37: 1 | E37: 5 | F37: 13.3-9-180 | G37: Устройство для защиты от взрыва типа Фонтан-2 10У. Мобильное устройство для подавления не более 1000 г ТНТ, локализуемый объем до 15 дм3, выполнено в форме купола с двумя ручками, стенки и верх купола наполнены специальным диспенсером, поглощающим тепловую и ударную волну, габаритные размеры 610х610х365 мм | H37: шт. | I37: =ROUND(ROUND(1,4),9) -> 1 | J37: 0 | K37: =ROUND(ROUND(1,4),9) -> 1 | O37: =ROUND(CP37,2) -> 84831.62 | P37: =ROUND((ROUND((AC37*I37),2)*BC37),2) -> 84831.62 | Q37: =(ROUND((ROUND(((ET37)*AV37*I37),2)*BB37),2)+ROUND((ROUND(((AE37-(EU37))*AV37*I37),2)*BS37),2)) -> 0 | R37: =ROUND((ROUND((AE37*AV37*I37),2)*BS37),2) -> 0 | S37: =ROUND((ROUND((AF37*AV37*I37),2)*BA37),2) -> 0 | T37: =ROUND(CU37*I37,2) -> 0 | U37: =CV37*I37 -> 0 | V37: =CW37*I37 -> 0 | W37: =ROUND(CX37*I37,2) -> 0 | X37: =ROUND(CY37,2) -> 0 | Y37: =ROUND(CZ37,2) -> 0 | AA37: 59214059 | AB37: =ROUND((AC37+AD37+AF37),6) -> 8188.38 | AC37: =ROUND((ES37),6) -> 8188.38 | AD37: =ROUND((((ET37)-(EU37))+AE37),6) -> 0 | AE37: =ROUND((EU37),6) -> 0 | AF37: =ROUND((EV37),6) -> 0 | AG37: =ROUND((AP37),6) -> 0 | AH37: =(EW37) -> 0 | AI37: =(EX37) -> 0 | AJ37: =(AS37) -> 0 | AK37: 8188.38 | AL37: 8188.38 | AM37: 0 | AN37: 0 | AO37: 0 | AP37: 0 | AQ37: 0 | AR37: 0 | AS37: 0 | AT37: 0 | AU37: 0 | AV37: 1 | AW37: 1 | AZ37: 1 | BA37: 1 | BB37: 1 | BC37: 10.36 | BH37: 3 | BI37: 3 | BM37: 746 | BN37: 58808062 | BP37: 0 | BQ37: 130 | BR37: 0 | BS37: 1 | BT37: 1 | BU37: 1 | BV37: 1 | BW37: 1 | BX37: 1 | BZ37: 0 | CA37: 0 | CE37: 30 | CF37: 0 | CG37: 0 | CM37: 0 | CO37: 0 | CP37: =(P37+Q37+S37) -> 84831.62 | CQ37: =ROUND((ROUND((AC37*1),2)*BC37),2) -> 84831.62 | CR37: =(ROUND((ROUND(((ET37)*AV37*1),2)*BB37),2)+ROUND((ROUND(((AE37-(EU37))*AV37*1),2)*BS37),2)) -> 0 | CS37: =ROUND((ROUND((AE37*AV37*1),2)*BS37),2) -> 0 | CT37: =ROUND((ROUND((AF37*AV37*1),2)*BA37),2) -> 0 | CU37: =AG37 -> 0 | CV37: =(AH37*AV37) -> 0 | CW37: =AI37 -> 0 | CX37: =AJ37 -> 0 | CY37: =(((S37+R37)*AT37)/100) -> 0 | CZ37: =(((S37+R37)*AU37)/100) -> 0 | DN37: 0 | DO37: 0 | DP37: 1 | DQ37: 1 | DU37: 1010 | DV37: шт. | DW37: шт. | DX37: 1 | EE37: 58808284 | EF37: 130 | EG37: Сметная стоимость оборудования | EH37: 0 | EJ37: 3 | EK37: 746 | EL37: ТСН-2001.13. Сметная стоимость оборудования | EM37: ТСН-2001.13 | EQ37: 0 | ER37: 8188.38 | ES37: 8188.38 | ET37: 0 | EU37: 0 | EV37: 0 | EW37: 0 | EX37: 0 | EY37: 0 | FQ37: 0 | FR37: =P37 -> 84831.62 | FS37: 0 | FX37: 0 | FY37: 0 | GD37: 1 | GF37: 844771149 | GG37: 2 | GH37: 1 | GI37: 2 | GJ37: 0 | GK37: 0 | GL37: =ROUND(IF(AND(BH37=3,BI37=3,FS37<>0),P37,0),2) -> 0 | GM37: =ROUND(O37+X37+Y37,2)+GX37 -> 84831.62 | GN37: =IF(OR(BI37=0,BI37=1),GM37-GX37,0) -> 0 | GO37: =IF(BI37=2,GM37-GX37,0) -> 0 | GP37: =IF(BI37=4,GM37-GX37,0) -> 0 | GR37: 0 | GS37: 3 | GT37: 0 | GV37: =ROUND((GT37),6) -> 0 | GW37: 1 | GX37: =ROUND(HC37*I37,2) -> 0 | HA37: 0 | HB37: 0 | HC37: =GV37*GW37 -> 0 | HS37: 0 | IK37: 0
A38: 17 | B38: 1 | E38: 6 | F38: 13.1-2-203 | G38: Устройство досмотровое (зеркало) для осмотра грузов, транспортных средств, неосвещенных и труднодоступных мест в помещениях. В составе: телескопическая штанга со встроенными светодиодами, с регулировкой длины от 600 до 1850 мм, набор зеркал различного размера и формы - 4 шт. Время непрерывной работы светодиодов не менее 9 часов, диапазон рабочих температур от -20 до +50°С | H38: КОМПЛЕКТ | I38: =ROUND(ROUND(1,4),9) -> 1 | J38: 0 | K38: =ROUND(ROUND(1,4),9) -> 1 | O38: =ROUND(CP38,2) -> 866.44 | P38: =ROUND((ROUND((AC38*I38),2)*BC38),2) -> 866.44 | Q38: =(ROUND((ROUND(((ET38)*AV38*I38),2)*BB38),2)+ROUND((ROUND(((AE38-(EU38))*AV38*I38),2)*BS38),2)) -> 0 | R38: =ROUND((ROUND((AE38*AV38*I38),2)*BS38),2) -> 0 | S38: =ROUND((ROUND((AF38*AV38*I38),2)*BA38),2) -> 0 | T38: =ROUND(CU38*I38,2) -> 0 | U38: =CV38*I38 -> 0 | V38: =CW38*I38 -> 0 | W38: =ROUND(CX38*I38,2) -> 0 | X38: =ROUND(CY38,2) -> 0 | Y38: =ROUND(CZ38,2) -> 0 | AA38: 59214062 | AB38: =ROUND((AC38+AD38+AF38),6) -> 866.44 | AC38: =ROUND((ES38),6) -> 866.44 | AD38: =ROUND((((ET38)-(EU38))+AE38),6) -> 0 | AE38: =ROUND((EU38),6) -> 0 | AF38: =ROUND((EV38),6) -> 0 | AG38: =ROUND((AP38),6) -> 0 | AH38: =(EW38) -> 0 | AI38: =(EX38) -> 0 | AJ38: =(AS38) -> 0 | AK38: 866.44 | AL38: 866.44 | AM38: 0 | AN38: 0 | AO38: 0 | AP38: 0 | AQ38: 0 | AR38: 0 | AS38: 0 | AT38: 0 | AU38: 0 | AV38: 1 | AW38: 1 | AZ38: 1 | BA38: 1 | BB38: 1 | BC38: 1 | BH38: 3 | BI38: 3 | BM38: 746 | BN38: 58808062 | BP38: 0 | BQ38: 130 | BR38: 0 | BS38: 1 | BT38: 1 | BU38: 1 | BV38: 1 | BW38: 1 | BX38: 1 | BZ38: 0 | CA38: 0 | CE38: 30 | CF38: 0 | CG38: 0 | CM38: 0 | CO38: 0 | CP38: =(P38+Q38+S38) -> 866.44 | CQ38: =ROUND((ROUND((AC38*1),2)*BC38),2) -> 866.44 | CR38: =(ROUND((ROUND(((ET38)*AV38*1),2)*BB38),2)+ROUND((ROUND(((AE38-(EU38))*AV38*1),2)*BS38),2)) -> 0 | CS38: =ROUND((ROUND((AE38*AV38*1),2)*BS38),2) -> 0 | CT38: =ROUND((ROUND((AF38*AV38*1),2)*BA38),2) -> 0 | CU38: =AG38 -> 0 | CV38: =(AH38*AV38) -> 0 | CW38: =AI38 -> 0 | CX38: =AJ38 -> 0 | CY38: =(((S38+R38)*AT38)/100) -> 0 | CZ38: =(((S38+R38)*AU38)/100) -> 0 | DN38: 0 | DO38: 0 | DP38: 1 | DQ38: 1 | DU38: 1013 | DV38: КОМПЛЕКТ | DW38: КОМПЛЕКТ | DX38: 1 | EE38: 58808284 | EF38: 130 | EG38: Сметная стоимость оборудования | EH38: 0 | EJ38: 3 | EK38: 746 | EL38: ТСН-2001.13. Сметная стоимость оборудования | EM38: ТСН-2001.13 | EQ38: 0 | ER38: 866.44 | ES38: 866.44 | ET38: 0 | EU38: 0 | EV38: 0 | EW38: 0 | EX38: 0 | EY38: 0 | FQ38: 0 | FR38: =P38 -> 866.44 | FS38: 0 | FX38: 0 | FY38: 0 | GD38: 1 | GF38: -1221268236 | GG38: 2 | GH38: 1 | GI38: -2 | GJ38: 0 | GK38: 0 | GL38: =ROUND(IF(AND(BH38=3,BI38=3,FS38<>0),P38,0),2) -> 0 | GM38: =ROUND(O38+X38+Y38,2)+GX38 -> 866.44 | GN38: =IF(OR(BI38=0,BI38=1),GM38-GX38,0) -> 0 | GO38: =IF(BI38=2,GM38-GX38,0) -> 0 | GP38: =IF(BI38=4,GM38-GX38,0) -> 0 | GR38: 0 | GS38: 3 | GT38: 0 | GV38: =ROUND((GT38),6) -> 0 | GW38: 1 | GX38: =ROUND(HC38*I38,2) -> 0 | HA38: 0 | HB38: 0 | HC38: =GV38*GW38 -> 0 | HS38: 0 | IK38: 0
A39: 17 | B39: 1 | E39: 6 | F39: 13.1-2-203 | G39: Устройство досмотровое (зеркало) для осмотра грузов, транспортных средств, неосвещенных и труднодоступных мест в помещениях. В составе: телескопическая штанга со встроенными светодиодами, с регулировкой длины от 600 до 1850 мм, набор зеркал различного размера и формы - 4 шт. Время непрерывной работы светодиодов не менее 9 часов, диапазон рабочих температур от -20 до +50°С | H39: КОМПЛЕКТ | I39: =ROUND(ROUND(1,4),9) -> 1 | J39: 0 | K39: =ROUND(ROUND(1,4),9) -> 1 | O39: =ROUND(CP39,2) -> 9903.41 | P39: =ROUND((ROUND((AC39*I39),2)*BC39),2) -> 9903.41 | Q39: =(ROUND((ROUND(((ET39)*AV39*I39),2)*BB39),2)+ROUND((ROUND(((AE39-(EU39))*AV39*I39),2)*BS39),2)) -> 0 | R39: =ROUND((ROUND((AE39*AV39*I39),2)*BS39),2) -> 0 | S39: =ROUND((ROUND((AF39*AV39*I39),2)*BA39),2) -> 0 | T39: =ROUND(CU39*I39,2) -> 0 | U39: =CV39*I39 -> 0 | V39: =CW39*I39 -> 0 | W39: =ROUND(CX39*I39,2) -> 0 | X39: =ROUND(CY39,2) -> 0 | Y39: =ROUND(CZ39,2) -> 0 | AA39: 59214059 | AB39: =ROUND((AC39+AD39+AF39),6) -> 866.44 | AC39: =ROUND((ES39),6) -> 866.44 | AD39: =ROUND((((ET39)-(EU39))+AE39),6) -> 0 | AE39: =ROUND((EU39),6) -> 0 | AF39: =ROUND((EV39),6) -> 0 | AG39: =ROUND((AP39),6) -> 0 | AH39: =(EW39) -> 0 | AI39: =(EX39) -> 0 | AJ39: =(AS39) -> 0 | AK39: 866.44 | AL39: 866.44 | AM39: 0 | AN39: 0 | AO39: 0 | AP39: 0 | AQ39: 0 | AR39: 0 | AS39: 0 | AT39: 0 | AU39: 0 | AV39: 1 | AW39: 1 | AZ39: 1 | BA39: 1 | BB39: 1 | BC39: 11.43 | BH39: 3 | BI39: 3 | BM39: 746 | BN39: 58808062 | BP39: 0 | BQ39: 130 | BR39: 0 | BS39: 1 | BT39: 1 | BU39: 1 | BV39: 1 | BW39: 1 | BX39: 1 | BZ39: 0 | CA39: 0 | CE39: 30 | CF39: 0 | CG39: 0 | CM39: 0 | CO39: 0 | CP39: =(P39+Q39+S39) -> 9903.41 | CQ39: =ROUND((ROUND((AC39*1),2)*BC39),2) -> 9903.41 | CR39: =(ROUND((ROUND(((ET39)*AV39*1),2)*BB39),2)+ROUND((ROUND(((AE39-(EU39))*AV39*1),2)*BS39),2)) -> 0 | CS39: =ROUND((ROUND((AE39*AV39*1),2)*BS39),2) -> 0 | CT39: =ROUND((ROUND((AF39*AV39*1),2)*BA39),2) -> 0 | CU39: =AG39 -> 0 | CV39: =(AH39*AV39) -> 0 | CW39: =AI39 -> 0 | CX39: =AJ39 -> 0 | CY39: =(((S39+R39)*AT39)/100) -> 0 | CZ39: =(((S39+R39)*AU39)/100) -> 0 | DN39: 0 | DO39: 0 | DP39: 1 | DQ39: 1 | DU39: 1013 | DV39: КОМПЛЕКТ | DW39: КОМПЛЕКТ | DX39: 1 | EE39: 58808284 | EF39: 130 | EG39: Сметная стоимость оборудования | EH39: 0 | EJ39: 3 | EK39: 746 | EL39: ТСН-2001.13. Сметная стоимость оборудования | EM39: ТСН-2001.13 | EQ39: 0 | ER39: 866.44 | ES39: 866.44 | ET39: 0 | EU39: 0 | EV39: 0 | EW39: 0 | EX39: 0 | EY39: 0 | FQ39: 0 | FR39: =P39 -> 9903.41 | FS39: 0 | FX39: 0 | FY39: 0 | GD39: 1 | GF39: -1221268236 | GG39: 2 | GH39: 1 | GI39: 2 | GJ39: 0 | GK39: 0 | GL39: =ROUND(IF(AND(BH39=3,BI39=3,FS39<>0),P39,0),2) -> 0 | GM39: =ROUND(O39+X39+Y39,2)+GX39 -> 9903.41 | GN39: =IF(OR(BI39=0,BI39=1),GM39-GX39,0) -> 0 | GO39: =IF(BI39=2,GM39-GX39,0) -> 0 | GP39: =IF(BI39=4,GM39-GX39,0) -> 0 | GR39: 0 | GS39: 3 | GT39: 0 | GV39: =ROUND((GT39),6) -> 0 | GW39: 1 | GX39: =ROUND(HC39*I39,2) -> 0 | HA39: 0 | HB39: 0 | HC39: =GV39*GW39 -> 0 | HS39: 0 | IK39: 0
A40: 17 | B40: 1 | C40: =ROW(SmtRes!A10) -> 10 | D40: =ROW(EtalonRes!A14) -> 14 | E40: 7 | F40: 3.10-33-1 | G40: Установка штучных изделий столов, шкафов под мойки, холодильных шкафов и других | H40: 100 изделий | I40: =ROUND(ROUND(4/100,4),9) -> 0.04 | J40: 0 | K40: =ROUND(ROUND(4/100,4),9) -> 0.04 | O40: =ROUND(CP40,2) -> 55 | P40: =ROUND((ROUND((AC40*AW40*I40),2)*BC40),2) -> 12.73 | Q40: =(ROUND((ROUND((((ET40*1.1))*AV40*I40),2)*BB40),2)+ROUND((ROUND(((AE40-((EU40*1.1)))*AV40*I40),2)*BS40),2)) -> 9.46 | R40: =ROUND((ROUND((AE40*AV40*I40),2)*BS40),2) -> 1.44 | S40: =ROUND((ROUND((AF40*AV40*I40),2)*BA40),2) -> 32.81 | T40: =ROUND(CU40*I40,2) -> 0 | U40: =CV40*I40 -> 3.1188036 | V40: =CW40*I40 -> 0 | W40: =ROUND(CX40*I40,2) -> 0 | X40: =ROUND(CY40,2) -> 36.99 | Y40: =ROUND(CZ40,2) -> 18.84 | AA40: 59214062 | AB40: =ROUND((AC40+AD40+AF40),6) -> 1327.486 | AC40: =ROUND((ES40),6) -> 318.28 | AD40: =ROUND(((((ET40*1.1))-((EU40*1.1)))+AE40),6) -> 225.786 | AE40: =ROUND(((EU40*1.1)),6) -> 34.287 | AF40: =ROUND(((EV40*1.1)),6) -> 783.42 | AG40: =ROUND((AP40),6) -> 0 | AH40: =((EW40*1.1)) -> 74.47 | AI40: =((EX40*1.1)) -> 0 | AJ40: =(AS40) -> 0 | AK40: 1235.74 | AL40: 318.28 | AM40: 205.26 | AN40: 31.17 | AO40: 712.2 | AP40: 0 | AQ40: 67.7 | AR40: 0 | AS40: 0 | AT40: 108 | AU40: 55 | AV40: 1.047 | AW40: 1 | AZ40: 1 | BA40: 1 | BB40: 1 | BC40: 1 | BH40: 0 | BI40: 1 | BJ40: ТСН-2001.3 Доп. 79, Сб. 10, т. 33, поз. 1 | BM40: 14 | BN40: 58808062 | BO40: 3.10-33-1 | BP40: 1 | BQ40: 30 | BR40: 0 | BS40: 1 | BT40: 1 | BU40: 1 | BV40: 1 | BW40: 1 | BX40: 1 | BZ40: 108 | CA40: 55 | CE40: 30 | CF40: 0 | CG40: 0 | CM40: 0 | CN40: Поправка: О.П. п.3.4.30.в Наименование: При применении территориальных сметных нормативов для города Москвы затраты, учитывающие напряженные и стесненные условия производства работ (стесненность, сложность складирования и транспортной логистики и т.п.), исчисляются с применением коэффициентов к затратам труда и заработной плате рабочих, машинистов, времени эксплуатации машин и механизмов, стоимости эксплуатации машин в размере: для объектов, расположенных за пределами Третьего транспортного кольца города Москвы, но в пределах Московской кольцевой автомобильной дороги | CO40: 0 | CP40: =(P40+Q40+S40) -> 55 | CQ40: =ROUND((ROUND((AC40*AW40*1),2)*BC40),2) -> 318.28 | CR40: =(ROUND((ROUND((((ET40*1.1))*AV40*1),2)*BB40),2)+ROUND((ROUND(((AE40-((EU40*1.1)))*AV40*1),2)*BS40),2)) -> 236.4 | CS40: =ROUND((ROUND((AE40*AV40*1),2)*BS40),2) -> 35.9 | CT40: =ROUND((ROUND((AF40*AV40*1),2)*BA40),2) -> 820.24 | CU40: =AG40 -> 0 | CV40: =(AH40*AV40) -> 77.97009 | CW40: =AI40 -> 0 | CX40: =AJ40 -> 0 | CY40: =(((S40+R40)*AT40)/100) -> 36.99 | CZ40: =(((S40+R40)*AU40)/100) -> 18.8375 | DB40: 3 | DE40: *1,1 | DF40: *1,1 | DG40: *1,1 | DI40: *1,1 | DJ40: *1,1 | DN40: 0 | DO40: 0 | DP40: 1 | DQ40: 1 | DU40: 30517203 | DV40: 100 изделий | DW40: 100 изделий | DX40: 1 | EE40: 58808123 | EF40: 30 | EG40: Строительные работы | EH40: 0 | EJ40: 1 | EK40: 14 | EL40: ТСН-2001.3-10. Элементы и конструкции из дерева и пластмасс | EM40: ТСН-2001.3-10-1 | EO40: Поправка: О.П. п.3.4.30.в | EQ40: 0 | ER40: 1235.74 | ES40: 318.28 | ET40: 205.26 | EU40: 31.17 | EV40: 712.2 | EW40: 67.7 | EX40: 0 | EY40: 0 | FQ40: 0 | FR40: 0 | FS40: 0 | FX40: 108 | FY40: 55 | GD40: 1 | GF40: -1266291315 | GG40: 2 | GH40: 1 | GI40: 2 | GJ40: 0 | GK40: 0 | GL40: =ROUND(IF(AND(BH40=3,BI40=3,FS40<>0),P40,0),2) -> 0 | GM40: =ROUND(O40+X40+Y40,2)+GX40 -> 110.83 | GN40: =IF(OR(BI40=0,BI40=1),GM40-GX40,0) -> 110.83 | GO40: =IF(BI40=2,GM40-GX40,0) -> 0 | GP40: =IF(BI40=4,GM40-GX40,0) -> 0 | GR40: 0 | GS40: 3 | GT40: 0 | GV40: =ROUND((GT40),6) -> 0 | GW40: 1 | GX40: =ROUND(HC40*I40,2) -> 0 | HA40: 0 | HB40: 0 | HC40: =GV40*GW40 -> 0 | HS40: 0 | IK40: 0
A41: 17 | B41: 1 | C41: =ROW(SmtRes!A14) -> 14 | D41: =ROW(EtalonRes!A20) -> 20 | E41: 7 | F41: 3.10-33-1 | G41: Установка штучных изделий столов, шкафов под мойки, холодильных шкафов и других | H41: 100 изделий | I41: =ROUND(ROUND(4/100,4),9) -> 0.04 | J41: 0 | K41: =ROUND(ROUND(4/100,4),9) -> 0.04 | O41: =ROUND(CP41,2) -> 2074.39 | P41: =ROUND((ROUND((AC41*AW41*I41),2)*BC41),2) -> 115.97 | Q41: =(ROUND((ROUND((((ET41*1.1))*AV41*I41),2)*BB41),2)+ROUND((ROUND(((AE41-((EU41*1.1)))*AV41*I41),2)*BS41),2)) -> 154.2 | R41: =ROUND((ROUND((AE41*AV41*I41),2)*BS41),2) -> 79.19 | S41: =ROUND((ROUND((AF41*AV41*I41),2)*BA41),2) -> 1804.22 | T41: =ROUND(CU41*I41,2) -> 0 | U41: =CV41*I41 -> 3.1188036 | V41: =CW41*I41 -> 0 | W41: =ROUND(CX41*I41,2) -> 0 | X41: =ROUND(CY41,2) -> 2034.08 | Y41: =ROUND(CZ41,2) -> 1035.88 | AA41: 59214059 | AB41: =ROUND((AC41+AD41+AF41),6) -> 1327.486 | AC41: =ROUND((ES41),6) -> 318.28 | AD41: =ROUND(((((ET41*1.1))-((EU41*1.1)))+AE41),6) -> 225.786 | AE41: =ROUND(((EU41*1.1)),6) -> 34.287 | AF41: =ROUND(((EV41*1.1)),6) -> 783.42 | AG41: =ROUND((AP41),6) -> 0 | AH41: =((EW41*1.1)) -> 74.47 | AI41: =((EX41*1.1)) -> 0 | AJ41: =(AS41) -> 0 | AK41: 1235.74 | AL41: 318.28 | AM41: 205.26 | AN41: 31.17 | AO41: 712.2 | AP41: 0 | AQ41: 67.7 | AR41: 0 | AS41: 0 | AT41: 108 | AU41: 55 | AV41: 1.047 | AW41: 1 | AZ41: 1 | BA41: 54.99 | BB41: 16.3 | BC41: 9.11 | BH41: 0 | BI41: 1 | BJ41: ТСН-2001.3 Доп. 79, Сб. 10, т. 33, поз. 1 | BM41: 14 | BN41: 58808062 | BO41: 3.10-33-1 | BP41: 1 | BQ41: 30 | BR41: 0 | BS41: 54.99 | BT41: 1 | BU41: 1 | BV41: 1 | BW41: 1 | BX41: 1 | BZ41: 108 | CA41: 55 | CE41: 30 | CF41: 0 | CG41: 0 | CM41: 0 | CN41: Поправка: О.П. п.3.4.30.в Наименование: При применении территориальных сметных нормативов для города Москвы затраты, учитывающие напряженные и стесненные условия производства работ (стесненность, сложность складирования и транспортной логистики и т.п.), исчисляются с применением коэффициентов к затратам труда и заработной плате рабочих, машинистов, времени эксплуатации машин и механизмов, стоимости эксплуатации машин в размере: для объектов, расположенных за пределами Третьего транспортного кольца города Москвы, но в пределах Московской кольцевой автомобильной дороги | CO41: 0 | CP41: =(P41+Q41+S41) -> 2074.39 | CQ41: =ROUND((ROUND((AC41*AW41*1),2)*BC41),2) -> 2899.53 | CR41: =(ROUND((ROUND((((ET41*1.1))*AV41*1),2)*BB41),2)+ROUND((ROUND(((AE41-((EU41*1.1)))*AV41*1),2)*BS41),2)) -> 3853.32 | CS41: =ROUND((ROUND((AE41*AV41*1),2)*BS41),2) -> 1974.14 | CT41: =ROUND((ROUND((AF41*AV41*1),2)*BA41),2) -> 45105 | CU41: =AG41 -> 0 | CV41: =(AH41*AV41) -> 77.97009 | CW41: =AI41 -> 0 | CX41: =AJ41 -> 0 | CY41: =(((S41+R41)*AT41)/100) -> 2034.0828 | CZ41: =(((S41+R41)*AU41)/100) -> 1035.8755 | DB41: 4 | DE41: *1,1 | DF41: *1,1 | DG41: *1,1 | DI41: *1,1 | DJ41: *1,1 | DN41: 0 | DO41: 0 | DP41: 1 | DQ41: 1 | DU41: 30517203 | DV41: 100 изделий | DW41: 100 изделий | DX41: 1 | EE41: 58808123 | EF41: 30 | EG41: Строительные работы | EH41: 0 | EJ41: 1 | EK41: 14 | EL41: ТСН-2001.3-10. Элементы и конструкции из дерева и пластмасс | EM41: ТСН-2001.3-10-1 | EO41: Поправка: О.П. п.3.4.30.в | EQ41: 0 | ER41: 1235.74 | ES41: 318.28 | ET41: 205.26 | EU41: 31.17 | EV41: 712.2 | EW41: 67.7 | EX41: 0 | EY41: 0 | FQ41: 0 | FR41: 0 | FS41: 0 | FX41: 108 | FY41: 55 | GD41: 1 | GF41: -1266291315 | GG41: 2 | GH41: 1 | GI41: 2 | GJ41: 0 | GK41: 0 | GL41: =ROUND(IF(AND(BH41=3,BI41=3,FS41<>0),P41,0),2) -> 0 | GM41: =ROUND(O41+X41+Y41,2)+GX41 -> 5144.35 | GN41: =IF(OR(BI41=0,BI41=1),GM41-GX41,0) -> 5144.35 | GO41: =IF(BI41=2,GM41-GX41,0) -> 0 | GP41: =IF(BI41=4,GM41-GX41,0) -> 0 | GR41: 0 | GS41: 3 | GT41: 0 | GV41: =ROUND((GT41),6) -> 0 | GW41: 1 | GX41: =ROUND(HC41*I41,2) -> 0 | HA41: 0 | HB41: 0 | HC41: =GV41*GW41 -> 0 | HS41: 0 | IK41: 0
A42: 17 | B42: 1 | E42: 8 | F42: КА 4 | G42: Стол досмотровый СД-950 (500х400х900) | H42: шт. | I42: =ROUND(ROUND(4,4),9) -> 4 | J42: 0 | K42: =ROUND(ROUND(4,4),9) -> 4 | O42: =ROUND(CP42,2) -> 4581.28 | P42: =ROUND((ROUND((AC42*I42),2)*BC42),2) -> 4581.28 | Q42: =(ROUND((ROUND(((ET42)*AV42*I42),2)*BB42),2)+ROUND((ROUND(((AE42-(EU42))*AV42*I42),2)*BS42),2)) -> 0 | R42: =ROUND((ROUND((AE42*AV42*I42),2)*BS42),2) -> 0 | S42: =ROUND((ROUND((AF42*AV42*I42),2)*BA42),2) -> 0 | T42: =ROUND(CU42*I42,2) -> 0 | U42: =CV42*I42 -> 0 | V42: =CW42*I42 -> 0 | W42: =ROUND(CX42*I42,2) -> 0 | X42: =ROUND(CY42,2) -> 0 | Y42: =ROUND(CZ42,2) -> 0 | AA42: 59214062 | AB42: =ROUND((AC42+AD42+AF42),6) -> 1145.32 | AC42: =ROUND((ES42),6) -> 1145.32 | AD42: =ROUND((((ET42)-(EU42))+AE42),6) -> 0 | AE42: =ROUND((EU42),6) -> 0 | AF42: =ROUND((EV42),6) -> 0 | AG42: =ROUND((AP42),6) -> 0 | AH42: =(EW42) -> 0 | AI42: =(EX42) -> 0 | AJ42: =(AS42) -> 0 | AK42: 1145.32 | AL42: 1145.32 | AM42: 0 | AN42: 0 | AO42: 0 | AP42: 0 | AQ42: 0 | AR42: 0 | AS42: 0 | AT42: 0 | AU42: 0 | AV42: 1 | AW42: 1 | AZ42: 1 | BA42: 1 | BB42: 1 | BC42: 1 | BH42: 3 | BI42: 3 | BM42: 746 | BN42: 0 | BP42: 0 | BQ42: 130 | BR42: 0 | BS42: 1 | BT42: 1 | BU42: 1 | BV42: 1 | BW42: 1 | BX42: 1 | BZ42: 0 | CA42: 0 | CE42: 30 | CF42: 0 | CG42: 0 | CM42: 0 | CO42: 0 | CP42: =(P42+Q42+S42) -> 4581.28 | CQ42: =ROUND((ROUND((AC42*1),2)*BC42),2) -> 1145.32 | CR42: =(ROUND((ROUND(((ET42)*AV42*1),2)*BB42),2)+ROUND((ROUND(((AE42-(EU42))*AV42*1),2)*BS42),2)) -> 0 | CS42: =ROUND((ROUND((AE42*AV42*1),2)*BS42),2) -> 0 | CT42: =ROUND((ROUND((AF42*AV42*1),2)*BA42),2) -> 0 | CU42: =AG42 -> 0 | CV42: =(AH42*AV42) -> 0 | CW42: =AI42 -> 0 | CX42: =AJ42 -> 0 | CY42: =(((S42+R42)*AT42)/100) -> 0 | CZ42: =(((S42+R42)*AU42)/100) -> 0 | DN42: 0 | DO42: 0 | DP42: 1 | DQ42: 1 | DU42: 1010 | DV42: шт. | DW42: шт. | DX42: 1 | EE42: 58808284 | EF42: 130 | EG42: Сметная стоимость оборудования | EH42: 0 | EJ42: 3 | EK42: 746 | EL42: ТСН-2001.13. Сметная стоимость оборудования | EM42: ТСН-2001.13 | EQ42: 0 | ER42: 0 | ES42: 1145.32 | ET42: 0 | EU42: 0 | EV42: 0 | EW42: 0 | EX42: 0 | EY42: 0 | FQ42: 0 | FR42: =P42 -> 4581.28 | FS42: 0 | FX42: 0 | FY42: 0 | GA42: [10 100 / 1,2 / 7,66] + 3% Трансп + 1,2% Заг.скл | GD42: 1 | GF42: 1665855222 | GG42: 2 | GH42: 4 | GI42: 0 | GJ42: 0 | GK42: 0 | GL42: =ROUND(IF(AND(BH42=3,BI42=3,FS42<>0),P42,0),2) -> 0 | GM42: =ROUND(O42+X42+Y42,2)+GX42 -> 4581.28 | GN42: =IF(OR(BI42=0,BI42=1),GM42-GX42,0) -> 0 | GO42: =IF(BI42=2,GM42-GX42,0) -> 0 | GP42: =IF(BI42=4,GM42-GX42,0) -> 0 | GR42: 2 | GS42: 2 | GT42: 0 | GV42: =ROUND((GT42),6) -> 0 | GW42: 1 | GX42: =ROUND(HC42*I42,2) -> 0 | HA42: 0 | HB42: 0 | HC42: =GV42*GW42 -> 0 | HE42: 3 | HF42: 1,2 | HS42: 0 | IK42: 0
A43: 17 | B43: 1 | E43: 8 | F43: КА 4 | G43: Стол досмотровый СД-950 (500х400х900) | H43: шт. | I43: =ROUND(ROUND(4,4),9) -> 4 | J43: 0 | K43: =ROUND(ROUND(4,4),9) -> 4 | O43: =ROUND(CP43,2) -> 35092.6 | P43: =ROUND((ROUND((AC43*I43),2)*BC43),2) -> 35092.6 | Q43: =(ROUND((ROUND(((ET43)*AV43*I43),2)*BB43),2)+ROUND((ROUND(((AE43-(EU43))*AV43*I43),2)*BS43),2)) -> 0 | R43: =ROUND((ROUND((AE43*AV43*I43),2)*BS43),2) -> 0 | S43: =ROUND((ROUND((AF43*AV43*I43),2)*BA43),2) -> 0 | T43: =ROUND(CU43*I43,2) -> 0 | U43: =CV43*I43 -> 0 | V43: =CW43*I43 -> 0 | W43: =ROUND(CX43*I43,2) -> 0 | X43: =ROUND(CY43,2) -> 0 | Y43: =ROUND(CZ43,2) -> 0 | AA43: 59214059 | AB43: =ROUND((AC43+AD43+AF43),6) -> 1145.32 | AC43: =ROUND((ES43),6) -> 1145.32 | AD43: =ROUND((((ET43)-(EU43))+AE43),6) -> 0 | AE43: =ROUND((EU43),6) -> 0 | AF43: =ROUND((EV43),6) -> 0 | AG43: =ROUND((AP43),6) -> 0 | AH43: =(EW43) -> 0 | AI43: =(EX43) -> 0 | AJ43: =(AS43) -> 0 | AK43: 1145.32 | AL43: 1145.32 | AM43: 0 | AN43: 0 | AO43: 0 | AP43: 0 | AQ43: 0 | AR43: 0 | AS43: 0 | AT43: 0 | AU43: 0 | AV43: 1 | AW43: 1 | AZ43: 1 | BA43: 1 | BB43: 1 | BC43: 7.66 | BH43: 3 | BI43: 3 | BM43: 746 | BN43: 0 | BP43: 0 | BQ43: 130 | BR43: 0 | BS43: 1 | BT43: 1 | BU43: 1 | BV43: 1 | BW43: 1 | BX43: 1 | BZ43: 0 | CA43: 0 | CE43: 30 | CF43: 0 | CG43: 0 | CM43: 0 | CO43: 0 | CP43: =(P43+Q43+S43) -> 35092.6 | CQ43: =ROUND((ROUND((AC43*1),2)*BC43),2) -> 8773.15 | CR43: =(ROUND((ROUND(((ET43)*AV43*1),2)*BB43),2)+ROUND((ROUND(((AE43-(EU43))*AV43*1),2)*BS43),2)) -> 0 | CS43: =ROUND((ROUND((AE43*AV43*1),2)*BS43),2) -> 0 | CT43: =ROUND((ROUND((AF43*AV43*1),2)*BA43),2) -> 0 | CU43: =AG43 -> 0 | CV43: =(AH43*AV43) -> 0 | CW43: =AI43 -> 0 | CX43: =AJ43 -> 0 | CY43: =(((S43+R43)*AT43)/100) -> 0 | CZ43: =(((S43+R43)*AU43)/100) -> 0 | DN43: 0 | DO43: 0 | DP43: 1 | DQ43: 1 | DU43: 1010 | DV43: шт. | DW43: шт. | DX43: 1 | EE43: 58808284 | EF43: 130 | EG43: Сметная стоимость оборудования | EH43: 0 | EJ43: 3 | EK43: 746 | EL43: ТСН-2001.13. Сметная стоимость оборудования | EM43: ТСН-2001.13 | EQ43: 0 | ER43: 0 | ES43: 1145.32 | ET43: 0 | EU43: 0 | EV43: 0 | EW43: 0 | EX43: 0 | EY43: 0 | EZ43: 5 | FC43: 1 | FD43: 18 | FF43: 10100 | FQ43: 0 | FR43: =P43 -> 35092.6 | FS43: 0 | FX43: 0 | FY43: 0 | GA43: [10 100 / 1,2 / 7,66] + 3% Трансп + 1,2% Заг.скл | GD43: 1 | GF43: 1665855222 | GG43: 2 | GH43: 2 | GI43: 5 | GJ43: 0 | GK43: 0 | GL43: =ROUND(IF(AND(BH43=3,BI43=3,FS43<>0),P43,0),2) -> 0 | GM43: =ROUND(O43+X43+Y43,2)+GX43 -> 35092.6 | GN43: =IF(OR(BI43=0,BI43=1),GM43-GX43,0) -> 0 | GO43: =IF(BI43=2,GM43-GX43,0) -> 0 | GP43: =IF(BI43=4,GM43-GX43,0) -> 0 | GR43: 2 | GS43: 1 | GT43: 0 | GV43: =ROUND((GT43),6) -> 0 | GW43: 1 | GX43: =ROUND(HC43*I43,2) -> 0 | HA43: 0 | HB43: 0 | HC43: =GV43*GW43 -> 0 | HE43: 3 | HF43: 1,2 | HS43: 0 | IK43: 0
A44: 17 | B44: 1 | C44: =ROW(SmtRes!A19) -> 19 | D44: =ROW(EtalonRes!A25) -> 25 | E44: 9 | F44: 3.7-60-4 | G44: Установка металлических ограждений без поручня | H44: 100 м ограждений | I44: =ROUND(ROUND(2/100,4),9) -> 0.02 | J44: 0 | K44: =ROUND(ROUND(2/100,4),9) -> 0.02 | O44: =ROUND(CP44,2) -> 13.13 | P44: =ROUND((ROUND((AC44*AW44*I44),2)*BC44),2) -> 0 | Q44: =(ROUND((ROUND((((ET44*1.1))*AV44*I44),2)*BB44),2)+ROUND((ROUND(((AE44-((EU44*1.1)))*AV44*I44),2)*BS44),2)) -> 1.34 | R44: =ROUND((ROUND((AE44*AV44*I44),2)*BS44),2) -> 0.16 | S44: =ROUND((ROUND((AF44*AV44*I44),2)*BA44),2) -> 11.79 | T44: =ROUND(CU44*I44,2) -> 0 | U44: =CV44*I44 -> 0.955911 | V44: =CW44*I44 -> 0 | W44: =ROUND(CX44*I44,2) -> 0 | X44: =ROUND(CY44,2) -> 13.15 | Y44: =ROUND(CZ44,2) -> 8.72 | AA44: 59214062 | AB44: =ROUND((AC44+AD44+AF44),6) -> 626.956 | AC44: =ROUND((ES44),6) -> 0 | AD44: =ROUND(((((ET44*1.1))-((EU44*1.1)))+AE44),6) -> 64.097 | AE44: =ROUND(((EU44*1.1)),6) -> 7.469 | AF44: =ROUND(((EV44*1.1)),6) -> 562.859 | AG44: =ROUND((AP44),6) -> 0 | AH44: =((EW44*1.1)) -> 45.65 | AI44: =((EX44*1.1)) -> 0 | AJ44: =(AS44) -> 0 | AK44: 569.96 | AL44: 0 | AM44: 58.27 | AN44: 6.79 | AO44: 511.69 | AP44: 0 | AQ44: 41.5 | AR44: 0 | AS44: 0 | AT44: 110 | AU44: 73 | AV44: 1.047 | AW44: 1 | AZ44: 1 | BA44: 1 | BB44: 1 | BC44: 1 | BH44: 0 | BI44: 1 | BJ44: ТСН-2001.3 Доп. 70, Сб. 7, т. 60, поз. 4 | BM44: 10 | BN44: 58808062 | BO44: 3.7-60-4 | BP44: 1 | BQ44: 30 | BR44: 0 | BS44: 1 | BT44: 1 | BU44: 1 | BV44: 1 | BW44: 1 | BX44: 1 | BZ44: 110 | CA44: 73 | CE44: 30 | CF44: 0 | CG44: 0 | CM44: 0 | CN44: Поправка: О.П. п.3.4.30.в Наименование: При применении территориальных сметных нормативов для города Москвы затраты, учитывающие напряженные и стесненные условия производства работ (стесненность, сложность складирования и транспортной логистики и т.п.), исчисляются с применением коэффициентов к затратам труда и заработной плате рабочих, машинистов, времени эксплуатации машин и механизмов, стоимости эксплуатации машин в размере: для объектов, расположенных за пределами Третьего транспортного кольца города Москвы, но в пределах Московской кольцевой автомобильной дороги | CO44: 0 | CP44: =(P44+Q44+S44) -> 13.13 | CQ44: =ROUND((ROUND((AC44*AW44*1),2)*BC44),2) -> 0 | CR44: =(ROUND((ROUND((((ET44*1.1))*AV44*1),2)*BB44),2)+ROUND((ROUND(((AE44-((EU44*1.1)))*AV44*1),2)*BS44),2)) -> 67.11 | CS44: =ROUND((ROUND((AE44*AV44*1),2)*BS44),2) -> 7.82 | CT44: =ROUND((ROUND((AF44*AV44*1),2)*BA44),2) -> 589.31 | CU44: =AG44 -> 0 | CV44: =(AH44*AV44) -> 47.79555 | CW44: =AI44 -> 0 | CX44: =AJ44 -> 0 | CY44: =(((S44+R44)*AT44)/100) -> 13.145 | CZ44: =(((S44+R44)*AU44)/100) -> 8.7235 | DB44: 5 | DE44: *1,1 | DF44: *1,1 | DG44: *1,1 | DI44: *1,1 | DJ44: *1,1 | DN44: 0 | DO44: 0 | DP44: 1 | DQ44: 1 | DU44: 1013 | DV44: 100 м ограждений | DW44: 100 м ограждений | DX44: 1 | EE44: 58808119 | EF44: 30 | EG44: Строительные работы | EH44: 0 | EJ44: 1 | EK44: 10 | EL44: ТСН-2001.3-7. Бетонные и железобетонные конструкции сборные | EM44: ТСН-2001.3-7-1 | EO44: Поправка: О.П. п.3.4.30.в | EQ44: 0 | ER44: 569.96 | ES44: 0 | ET44: 58.27 | EU44: 6.79 | EV44: 511.69 | EW44: 41.5 | EX44: 0 | EY44: 0 | FQ44: 0 | FR44: 0 | FS44: 0 | FX44: 110 | FY44: 73 | GD44: 1 | GF44: 100471651 | GG44: 2 | GH44: 1 | GI44: 2 | GJ44: 0 | GK44: 0 | GL44: =ROUND(IF(AND(BH44=3,BI44=3,FS44<>0),P44,0),2) -> 0 | GM44: =ROUND(O44+X44+Y44,2)+GX44 -> 35 | GN44: =IF(OR(BI44=0,BI44=1),GM44-GX44,0) -> 35 | GO44: =IF(BI44=2,GM44-GX44,0) -> 0 | GP44: =IF(BI44=4,GM44-GX44,0) -> 0 | GR44: 0 | GS44: 3 | GT44: 0 | GV44: =ROUND((GT44),6) -> 0 | GW44: 1 | GX44: =ROUND(HC44*I44,2) -> 0 | HA44: 0 | HB44: 0 | HC44: =GV44*GW44 -> 0 | HS44: 0 | IK44: 0
A45: 17 | B45: 1 | C45: =ROW(SmtRes!A24) -> 24 | D45: =ROW(EtalonRes!A30) -> 30 | E45: 9 | F45: 3.7-60-4 | G45: Установка металлических ограждений без поручня | H45: 100 м ограждений | I45: =ROUND(ROUND(2/100,4),9) -> 0.02 | J45: 0 | K45: =ROUND(ROUND(2/100,4),9) -> 0.02 | O45: =ROUND(CP45,2) -> 668.07 | P45: =ROUND((ROUND((AC45*AW45*I45),2)*BC45),2) -> 0 | Q45: =(ROUND((ROUND((((ET45*1.1))*AV45*I45),2)*BB45),2)+ROUND((ROUND(((AE45-((EU45*1.1)))*AV45*I45),2)*BS45),2)) -> 19.74 | R45: =ROUND((ROUND((AE45*AV45*I45),2)*BS45),2) -> 8.8 | S45: =ROUND((ROUND((AF45*AV45*I45),2)*BA45),2) -> 648.33 | T45: =ROUND(CU45*I45,2) -> 0 | U45: =CV45*I45 -> 0.955911 | V45: =CW45*I45 -> 0 | W45: =ROUND(CX45*I45,2) -> 0 | X45: =ROUND(CY45,2) -> 722.84 | Y45: =ROUND(CZ45,2) -> 479.7 | AA45: 59214059 | AB45: =ROUND((AC45+AD45+AF45),6) -> 626.956 | AC45: =ROUND((ES45),6) -> 0 | AD45: =ROUND(((((ET45*1.1))-((EU45*1.1)))+AE45),6) -> 64.097 | AE45: =ROUND(((EU45*1.1)),6) -> 7.469 | AF45: =ROUND(((EV45*1.1)),6) -> 562.859 | AG45: =ROUND((AP45),6) -> 0 | AH45: =((EW45*1.1)) -> 45.65 | AI45: =((EX45*1.1)) -> 0 | AJ45: =(AS45) -> 0 | AK45: 569.96 | AL45: 0 | AM45: 58.27 | AN45: 6.79 | AO45: 511.69 | AP45: 0 | AQ45: 41.5 | AR45: 0 | AS45: 0 | AT45: 110 | AU45: 73 | AV45: 1.047 | AW45: 1 | AZ45: 1 | BA45: 54.99 | BB45: 14.73 | BC45: 1 | BH45: 0 | BI45: 1 | BJ45: ТСН-2001.3 Доп. 70, Сб. 7, т. 60, поз. 4 | BM45: 10 | BN45: 58808062 | BO45: 3.7-60-4 | BP45: 1 | BQ45: 30 | BR45: 0 | BS45: 54.99 | BT45: 1 | BU45: 1 | BV45: 1 | BW45: 1 | BX45: 1 | BZ45: 110 | CA45: 73 | CE45: 30 | CF45: 0 | CG45: 0 | CM45: 0 | CN45: Поправка: О.П. п.3.4.30.в Наименование: При применении территориальных сметных нормативов для города Москвы затраты, учитывающие напряженные и стесненные условия производства работ (стесненность, сложность складирования и транспортной логистики и т.п.), исчисляются с применением коэффициентов к затратам труда и заработной плате рабочих, машинистов, времени эксплуатации машин и механизмов, стоимости эксплуатации машин в размере: для объектов, расположенных за пределами Третьего транспортного кольца города Москвы, но в пределах Московской кольцевой автомобильной дороги | CO45: 0 | CP45: =(P45+Q45+S45) -> 668.07 | CQ45: =ROUND((ROUND((AC45*AW45*1),2)*BC45),2) -> 0 | CR45: =(ROUND((ROUND((((ET45*1.1))*AV45*1),2)*BB45),2)+ROUND((ROUND(((AE45-((EU45*1.1)))*AV45*1),2)*BS45),2)) -> 988.53 | CS45: =ROUND((ROUND((AE45*AV45*1),2)*BS45),2) -> 430.02 | CT45: =ROUND((ROUND((AF45*AV45*1),2)*BA45),2) -> 32406.16 | CU45: =AG45 -> 0 | CV45: =(AH45*AV45) -> 47.79555 | CW45: =AI45 -> 0 | CX45: =AJ45 -> 0 | CY45: =(((S45+R45)*AT45)/100) -> 722.843 | CZ45: =(((S45+R45)*AU45)/100) -> 479.7049 | DB45: 6 | DE45: *1,1 | DF45: *1,1 | DG45: *1,1 | DI45: *1,1 | DJ45: *1,1 | DN45: 0 | DO45: 0 | DP45: 1 | DQ45: 1 | DU45: 1013 | DV45: 100 м ограждений | DW45: 100 м ограждений | DX45: 1 | EE45: 58808119 | EF45: 30 | EG45: Строительные работы | EH45: 0 | EJ45: 1 | EK45: 10 | EL45: ТСН-2001.3-7. Бетонные и железобетонные конструкции сборные | EM45: ТСН-2001.3-7-1 | EO45: Поправка: О.П. п.3.4.30.в | EQ45: 0 | ER45: 569.96 | ES45: 0 | ET45: 58.27 | EU45: 6.79 | EV45: 511.69 | EW45: 41.5 | EX45: 0 | EY45: 0 | FQ45: 0 | FR45: 0 | FS45: 0 | FX45: 110 | FY45: 73 | GD45: 1 | GF45: 100471651 | GG45: 2 | GH45: 1 | GI45: 2 | GJ45: 0 | GK45: 0 | GL45: =ROUND(IF(AND(BH45=3,BI45=3,FS45<>0),P45,0),2) -> 0 | GM45: =ROUND(O45+X45+Y45,2)+GX45 -> 1870.61 | GN45: =IF(OR(BI45=0,BI45=1),GM45-GX45,0) -> 1870.61 | GO45: =IF(BI45=2,GM45-GX45,0) -> 0 | GP45: =IF(BI45=4,GM45-GX45,0) -> 0 | GR45: 0 | GS45: 3 | GT45: 0 | GV45: =ROUND((GT45),6) -> 0 | GW45: 1 | GX45: =ROUND(HC45*I45,2) -> 0 | HA45: 0 | HB45: 0 | HC45: =GV45*GW45 -> 0 | HS45: 0 | IK45: 0
A46: 18 | B46: 1 | C46: 18 | E46: 9,1 | F46: КА 5 | G46: Ограждение полуростовое BH02 PERCo | H46: м.п. | I46: =I44*J46 -> 2 | J46: 100 | K46: 1 | O46: =ROUND(CP46,2) -> 6356.26 | P46: =ROUND((ROUND((AC46*AW46*I46),2)*BC46),2) -> 6356.26 | Q46: =(ROUND((ROUND(((ET46)*AV46*I46),2)*BB46),2)+ROUND((ROUND(((AE46-(EU46))*AV46*I46),2)*BS46),2)) -> 0 | R46: =ROUND((ROUND((AE46*AV46*I46),2)*BS46),2) -> 0 | S46: =ROUND((ROUND((AF46*AV46*I46),2)*BA46),2) -> 0 | T46: =ROUND(CU46*I46,2) -> 0 | U46: =CV46*I46 -> 0 | V46: =CW46*I46 -> 0 | W46: =ROUND(CX46*I46,2) -> 0 | X46: =ROUND(CY46,2) -> 0 | Y46: =ROUND(CZ46,2) -> 0 | AA46: 59214062 | AB46: =ROUND((AC46+AD46+AF46),6) -> 3178.13 | AC46: =ROUND((ES46),6) -> 3178.13 | AD46: =ROUND((((ET46)-(EU46))+AE46),6) -> 0 | AE46: =ROUND((EU46),6) -> 0 | AF46: =ROUND((EV46),6) -> 0 | AG46: =ROUND((AP46),6) -> 0 | AH46: =(EW46) -> 0 | AI46: =(EX46) -> 0 | AJ46: =(AS46) -> 0 | AK46: 3178.13 | AL46: 3178.13 | AM46: 0 | AN46: 0 | AO46: 0 | AP46: 0 | AQ46: 0 | AR46: 0 | AS46: 0 | AT46: 110 | AU46: 73 | AV46: 1 | AW46: 1 | AZ46: 1 | BA46: 1 | BB46: 1 | BC46: 1 | BH46: 3 | BI46: 1 | BM46: 10 | BN46: 0 | BP46: 0 | BQ46: 30 | BR46: 0 | BS46: 1 | BT46: 1 | BU46: 1 | BV46: 1 | BW46: 1 | BX46: 1 | BZ46: 110 | CA46: 73 | CE46: 30 | CF46: 0 | CG46: 0 | CM46: 0 | CO46: 0 | CP46: =(P46+Q46+S46) -> 6356.26 | CQ46: =ROUND((ROUND((AC46*AW46*1),2)*BC46),2) -> 3178.13 | CR46: =(ROUND((ROUND(((ET46)*AV46*1),2)*BB46),2)+ROUND((ROUND(((AE46-(EU46))*AV46*1),2)*BS46),2)) -> 0 | CS46: =ROUND((ROUND((AE46*AV46*1),2)*BS46),2) -> 0 | CT46: =ROUND((ROUND((AF46*AV46*1),2)*BA46),2) -> 0 | CU46: =AG46 -> 0 | CV46: =(AH46*AV46) -> 0 | CW46: =AI46 -> 0 | CX46: =AJ46 -> 0 | CY46: =(((S46+R46)*AT46)/100) -> 0 | CZ46: =(((S46+R46)*AU46)/100) -> 0 | DN46: 0 | DO46: 0 | DP46: 1 | DQ46: 1 | DU46: 1013 | DV46: м.п. | DW46: м.п. | DX46: 1 | EE46: 58808119 | EF46: 30 | EG46: Строительные работы | EH46: 0 | EJ46: 1 | EK46: 10 | EL46: ТСН-2001.3-7. Бетонные и железобетонные конструкции сборные | EM46: ТСН-2001.3-7-1 | EQ46: 0 | ER46: 0 | ES46: 3178.13 | ET46: 0 | EU46: 0 | EV46: 0 | EW46: 0 | EX46: 0 | FQ46: 0 | FR46: 0 | FS46: 0 | FX46: 110 | FY46: 73 | GA46: [36 941 / 1,2 / 9,88] + 2% Заг.скл | GD46: 1 | GF46: 1742101416 | GG46: 2 | GH46: 4 | GI46: -2 | GJ46: 0 | GK46: 0 | GL46: =ROUND(IF(AND(BH46=3,BI46=3,FS46<>0),P46,0),2) -> 0 | GM46: =ROUND(O46+X46+Y46,2)+GX46 -> 6356.26 | GN46: =IF(OR(BI46=0,BI46=1),GM46-GX46,0) -> 6356.26 | GO46: =IF(BI46=2,GM46-GX46,0) -> 0 | GP46: =IF(BI46=4,GM46-GX46,0) -> 0 | GR46: 0 | GS46: 2 | GT46: 0 | GV46: =ROUND((GT46),6) -> 0 | GW46: 1 | GX46: =ROUND(HC46*I46,2) -> 0 | HA46: 0 | HB46: 0 | HC46: =GV46*GW46 -> 0 | HE46: 0 | HF46: 2 | HS46: 0 | IK46: 0
A47: 18 | B47: 1 | C47: 23 | E47: 9,1 | F47: КА 5 | G47: Ограждение полуростовое BH02 PERCo | H47: м.п. | I47: =I45*J47 -> 2 | J47: 100 | K47: 1 | O47: =ROUND(CP47,2) -> 62799.85 | P47: =ROUND((ROUND((AC47*AW47*I47),2)*BC47),2) -> 62799.85 | Q47: =(ROUND((ROUND(((ET47)*AV47*I47),2)*BB47),2)+ROUND((ROUND(((AE47-(EU47))*AV47*I47),2)*BS47),2)) -> 0 | R47: =ROUND((ROUND((AE47*AV47*I47),2)*BS47),2) -> 0 | S47: =ROUND((ROUND((AF47*AV47*I47),2)*BA47),2) -> 0 | T47: =ROUND(CU47*I47,2) -> 0 | U47: =CV47*I47 -> 0 | V47: =CW47*I47 -> 0 | W47: =ROUND(CX47*I47,2) -> 0 | X47: =ROUND(CY47,2) -> 0 | Y47: =ROUND(CZ47,2) -> 0 | AA47: 59214059 | AB47: =ROUND((AC47+AD47+AF47),6) -> 3178.13 | AC47: =ROUND((ES47),6) -> 3178.13 | AD47: =ROUND((((ET47)-(EU47))+AE47),6) -> 0 | AE47: =ROUND((EU47),6) -> 0 | AF47: =ROUND((EV47),6) -> 0 | AG47: =ROUND((AP47),6) -> 0 | AH47: =(EW47) -> 0 | AI47: =(EX47) -> 0 | AJ47: =(AS47) -> 0 | AK47: 3178.13 | AL47: 3178.13 | AM47: 0 | AN47: 0 | AO47: 0 | AP47: 0 | AQ47: 0 | AR47: 0 | AS47: 0 | AT47: 110 | AU47: 73 | AV47: 1 | AW47: 1 | AZ47: 1 | BA47: 1 | BB47: 1 | BC47: 9.88 | BH47: 3 | BI47: 1 | BM47: 10 | BN47: 0 | BP47: 0 | BQ47: 30 | BR47: 0 | BS47: 1 | BT47: 1 | BU47: 1 | BV47: 1 | BW47: 1 | BX47: 1 | BZ47: 110 | CA47: 73 | CE47: 30 | CF47: 0 | CG47: 0 | CM47: 0 | CO47: 0 | CP47: =(P47+Q47+S47) -> 62799.85 | CQ47: =ROUND((ROUND((AC47*AW47*1),2)*BC47),2) -> 31399.92 | CR47: =(ROUND((ROUND(((ET47)*AV47*1),2)*BB47),2)+ROUND((ROUND(((AE47-(EU47))*AV47*1),2)*BS47),2)) -> 0 | CS47: =ROUND((ROUND((AE47*AV47*1),2)*BS47),2) -> 0 | CT47: =ROUND((ROUND((AF47*AV47*1),2)*BA47),2) -> 0 | CU47: =AG47 -> 0 | CV47: =(AH47*AV47) -> 0 | CW47: =AI47 -> 0 | CX47: =AJ47 -> 0 | CY47: =(((S47+R47)*AT47)/100) -> 0 | CZ47: =(((S47+R47)*AU47)/100) -> 0 | DN47: 0 | DO47: 0 | DP47: 1 | DQ47: 1 | DU47: 1013 | DV47: м.п. | DW47: м.п. | DX47: 1 | EE47: 58808119 | EF47: 30 | EG47: Строительные работы | EH47: 0 | EJ47: 1 | EK47: 10 | EL47: ТСН-2001.3-7. Бетонные и железобетонные конструкции сборные | EM47: ТСН-2001.3-7-1 | EQ47: 0 | ER47: 3178.13 | ES47: 3178.13 | ET47: 0 | EU47: 0 | EV47: 0 | EW47: 0 | EX47: 0 | EZ47: 5 | FC47: 1 | FD47: 18 | FF47: 36941 | FQ47: 0 | FR47: 0 | FS47: 0 | FX47: 110 | FY47: 73 | GA47: [36 941 / 1,2 / 9,88] + 2% Заг.скл | GD47: 1 | GF47: 1742101416 | GG47: 2 | GH47: 3 | GI47: 5 | GJ47: 0 | GK47: 0 | GL47: =ROUND(IF(AND(BH47=3,BI47=3,FS47<>0),P47,0),2) -> 0 | GM47: =ROUND(O47+X47+Y47,2)+GX47 -> 62799.85 | GN47: =IF(OR(BI47=0,BI47=1),GM47-GX47,0) -> 62799.85 | GO47: =IF(BI47=2,GM47-GX47,0) -> 0 | GP47: =IF(BI47=4,GM47-GX47,0) -> 0 | GR47: 1 | GS47: 1 | GT47: 0 | GV47: =ROUND((GT47),6) -> 0 | GW47: 1 | GX47: =ROUND(HC47*I47,2) -> 0 | HA47: 0 | HB47: 0 | HC47: =GV47*GW47 -> 0 | HE47: 0 | HF47: 2 | HS47: 0 | IK47: 0
A48: 18 | B48: 1 | C48: 19 | E48: 9,2 | F48: КА 6 | G48: Калитка одностворчатая PERCo | H48: шт. | I48: =I44*J48 -> 2 | J48: 100 | K48: 1 | O48: =ROUND(CP48,2) -> 19918.96 | P48: =ROUND((ROUND((AC48*AW48*I48),2)*BC48),2) -> 19918.96 | Q48: =(ROUND((ROUND(((ET48)*AV48*I48),2)*BB48),2)+ROUND((ROUND(((AE48-(EU48))*AV48*I48),2)*BS48),2)) -> 0 | R48: =ROUND((ROUND((AE48*AV48*I48),2)*BS48),2) -> 0 | S48: =ROUND((ROUND((AF48*AV48*I48),2)*BA48),2) -> 0 | T48: =ROUND(CU48*I48,2) -> 0 | U48: =CV48*I48 -> 0 | V48: =CW48*I48 -> 0 | W48: =ROUND(CX48*I48,2) -> 0 | X48: =ROUND(CY48,2) -> 0 | Y48: =ROUND(CZ48,2) -> 0 | AA48: 59214062 | AB48: =ROUND((AC48+AD48+AF48),6) -> 9959.48 | AC48: =ROUND((ES48),6) -> 9959.48 | AD48: =ROUND((((ET48)-(EU48))+AE48),6) -> 0 | AE48: =ROUND((EU48),6) -> 0 | AF48: =ROUND((EV48),6) -> 0 | AG48: =ROUND((AP48),6) -> 0 | AH48: =(EW48) -> 0 | AI48: =(EX48) -> 0 | AJ48: =(AS48) -> 0 | AK48: 9959.48 | AL48: 9959.48 | AM48: 0 | AN48: 0 | AO48: 0 | AP48: 0 | AQ48: 0 | AR48: 0 | AS48: 0 | AT48: 110 | AU48: 73 | AV48: 1 | AW48: 1 | AZ48: 1 | BA48: 1 | BB48: 1 | BC48: 1 | BH48: 3 | BI48: 1 | BM48: 10 | BN48: 0 | BP48: 0 | BQ48: 30 | BR48: 0 | BS48: 1 | BT48: 1 | BU48: 1 | BV48: 1 | BW48: 1 | BX48: 1 | BZ48: 110 | CA48: 73 | CE48: 30 | CF48: 0 | CG48: 0 | CM48: 0 | CO48: 0 | CP48: =(P48+Q48+S48) -> 19918.96 | CQ48: =ROUND((ROUND((AC48*AW48*1),2)*BC48),2) -> 9959.48 | CR48: =(ROUND((ROUND(((ET48)*AV48*1),2)*BB48),2)+ROUND((ROUND(((AE48-(EU48))*AV48*1),2)*BS48),2)) -> 0 | CS48: =ROUND((ROUND((AE48*AV48*1),2)*BS48),2) -> 0 | CT48: =ROUND((ROUND((AF48*AV48*1),2)*BA48),2) -> 0 | CU48: =AG48 -> 0 | CV48: =(AH48*AV48) -> 0 | CW48: =AI48 -> 0 | CX48: =AJ48 -> 0 | CY48: =(((S48+R48)*AT48)/100) -> 0 | CZ48: =(((S48+R48)*AU48)/100) -> 0 | DN48: 0 | DO48: 0 | DP48: 1 | DQ48: 1 | DU48: 1010 | DV48: шт. | DW48: шт. | DX48: 1 | EE48: 58808119 | EF48: 30 | EG48: Строительные работы | EH48: 0 | EJ48: 1 | EK48: 10 | EL48: ТСН-2001.3-7. Бетонные и железобетонные конструкции сборные | EM48: ТСН-2001.3-7-1 | EQ48: 0 | ER48: 0 | ES48: 9959.48 | ET48: 0 | EU48: 0 | EV48: 0 | EW48: 0 | EX48: 0 | FQ48: 0 | FR48: 0 | FS48: 0 | FX48: 110 | FY48: 73 | GA48: [115 764,37 / 1,2 / 9,88] + 2% Заг.скл | GD48: 1 | GF48: -1584551560 | GG48: 2 | GH48: 4 | GI48: -2 | GJ48: 0 | GK48: 0 | GL48: =ROUND(IF(AND(BH48=3,BI48=3,FS48<>0),P48,0),2) -> 0 | GM48: =ROUND(O48+X48+Y48,2)+GX48 -> 19918.96 | GN48: =IF(OR(BI48=0,BI48=1),GM48-GX48,0) -> 19918.96 | GO48: =IF(BI48=2,GM48-GX48,0) -> 0 | GP48: =IF(BI48=4,GM48-GX48,0) -> 0 | GR48: 0 | GS48: 2 | GT48: 0 | GV48: =ROUND((GT48),6) -> 0 | GW48: 1 | GX48: =ROUND(HC48*I48,2) -> 0 | HA48: 0 | HB48: 0 | HC48: =GV48*GW48 -> 0 | HE48: 0 | HF48: 2 | HS48: 0 | IK48: 0
A49: 18 | B49: 1 | C49: 24 | E49: 9,2 | F49: КА 6 | G49: Калитка одностворчатая PERCo | H49: шт. | I49: =I45*J49 -> 2 | J49: 100 | K49: 1 | O49: =ROUND(CP49,2) -> 196799.32 | P49: =ROUND((ROUND((AC49*AW49*I49),2)*BC49),2) -> 196799.32 | Q49: =(ROUND((ROUND(((ET49)*AV49*I49),2)*BB49),2)+ROUND((ROUND(((AE49-(EU49))*AV49*I49),2)*BS49),2)) -> 0 | R49: =ROUND((ROUND((AE49*AV49*I49),2)*BS49),2) -> 0 | S49: =ROUND((ROUND((AF49*AV49*I49),2)*BA49),2) -> 0 | T49: =ROUND(CU49*I49,2) -> 0 | U49: =CV49*I49 -> 0 | V49: =CW49*I49 -> 0 | W49: =ROUND(CX49*I49,2) -> 0 | X49: =ROUND(CY49,2) -> 0 | Y49: =ROUND(CZ49,2) -> 0 | AA49: 59214059 | AB49: =ROUND((AC49+AD49+AF49),6) -> 9959.48 | AC49: =ROUND((ES49),6) -> 9959.48 | AD49: =ROUND((((ET49)-(EU49))+AE49),6) -> 0 | AE49: =ROUND((EU49),6) -> 0 | AF49: =ROUND((EV49),6) -> 0 | AG49: =ROUND((AP49),6) -> 0 | AH49: =(EW49) -> 0 | AI49: =(EX49) -> 0 | AJ49: =(AS49) -> 0 | AK49: 9959.48 | AL49: 9959.48 | AM49: 0 | AN49: 0 | AO49: 0 | AP49: 0 | AQ49: 0 | AR49: 0 | AS49: 0 | AT49: 110 | AU49: 73 | AV49: 1 | AW49: 1 | AZ49: 1 | BA49: 1 | BB49: 1 | BC49: 9.88 | BH49: 3 | BI49: 1 | BM49: 10 | BN49: 0 | BP49: 0 | BQ49: 30 | BR49: 0 | BS49: 1 | BT49: 1 | BU49: 1 | BV49: 1 | BW49: 1 | BX49: 1 | BZ49: 110 | CA49: 73 | CE49: 30 | CF49: 0 | CG49: 0 | CM49: 0 | CO49: 0 | CP49: =(P49+Q49+S49) -> 196799.32 | CQ49: =ROUND((ROUND((AC49*AW49*1),2)*BC49),2) -> 98399.66 | CR49: =(ROUND((ROUND(((ET49)*AV49*1),2)*BB49),2)+ROUND((ROUND(((AE49-(EU49))*AV49*1),2)*BS49),2)) -> 0 | CS49: =ROUND((ROUND((AE49*AV49*1),2)*BS49),2) -> 0 | CT49: =ROUND((ROUND((AF49*AV49*1),2)*BA49),2) -> 0 | CU49: =AG49 -> 0 | CV49: =(AH49*AV49) -> 0 | CW49: =AI49 -> 0 | CX49: =AJ49 -> 0 | CY49: =(((S49+R49)*AT49)/100) -> 0 | CZ49: =(((S49+R49)*AU49)/100) -> 0 | DN49: 0 | DO49: 0 | DP49: 1 | DQ49: 1 | DU49: 1010 | DV49: шт. | DW49: шт. | DX49: 1 | EE49: 58808119 | EF49: 30 | EG49: Строительные работы | EH49: 0 | EJ49: 1 | EK49: 10 | EL49: ТСН-2001.3-7. Бетонные и железобетонные конструкции сборные | EM49: ТСН-2001.3-7-1 | EQ49: 0 | ER49: 9959.48 | ES49: 9959.48 | ET49: 0 | EU49: 0 | EV49: 0 | EW49: 0 | EX49: 0 | EZ49: 5 | FC49: 1 | FD49: 18 | FF49: 115764.37 | FQ49: 0 | FR49: 0 | FS49: 0 | FX49: 110 | FY49: 73 | GA49: [115 764,37 / 1,2 / 9,88] + 2% Заг.скл | GD49: 1 | GF49: -1584551560 | GG49: 2 | GH49: 3 | GI49: 5 | GJ49: 0 | GK49: 0 | GL49: =ROUND(IF(AND(BH49=3,BI49=3,FS49<>0),P49,0),2) -> 0 | GM49: =ROUND(O49+X49+Y49,2)+GX49 -> 196799.32 | GN49: =IF(OR(BI49=0,BI49=1),GM49-GX49,0) -> 196799.32 | GO49: =IF(BI49=2,GM49-GX49,0) -> 0 | GP49: =IF(BI49=4,GM49-GX49,0) -> 0 | GR49: 1 | GS49: 1 | GT49: 0 | GV49: =ROUND((GT49),6) -> 0 | GW49: 1 | GX49: =ROUND(HC49*I49,2) -> 0 | HA49: 0 | HB49: 0 | HC49: =GV49*GW49 -> 0 | HE49: 0 | HF49: 2 | HS49: 0 | IK49: 0
A51: 51 | B51: =B24 -> 1 | C51: =A24 -> 4 | D51: =ROW(A24) -> 24 | F51: =IF(F24<>"",F24,"") -> Новый раздел | G51: =IF(G24<>"",G24,"") -> Оборудование | H51: 0 | O51: =ROUND(AB51,2) -> 376019.07 | P51: =ROUND(AC51,2) -> 375907.12 | Q51: =ROUND(AD51,2) -> 12 | R51: =ROUND(AE51,2) -> 1.6 | S51: =ROUND(AF51,2) -> 99.95 | T51: =ROUND(AG51,2) -> 0 | U51: =AH51 -> 8.0418206 | V51: =AI51 -> 0 | W51: =ROUND(AJ51,2) -> 0 | X51: =ROUND(AK51,2) -> 99.96 | Y51: =ROUND(AL51,2) -> 53.02 | AB51: =ROUND(SUMIF(AA28:AA49,"=59214062",O28:O49),2) -> 376019.07 | AC51: =ROUND(SUMIF(AA28:AA49,"=59214062",P28:P49),2) -> 375907.12 | AD51: =ROUND(SUMIF(AA28:AA49,"=59214062",Q28:Q49),2) -> 12 | AE51: =ROUND(SUMIF(AA28:AA49,"=59214062",R28:R49),2) -> 1.6 | AF51: =ROUND(SUMIF(AA28:AA49,"=59214062",S28:S49),2) -> 99.95 | AG51: =ROUND(SUMIF(AA28:AA49,"=59214062",T28:T49),2) -> 0 | AH51: =SUMIF(AA28:AA49,"=59214062",U28:U49) -> 8.0418206 | AI51: =SUMIF(AA28:AA49,"=59214062",V28:V49) -> 0 | AJ51: =ROUND(SUMIF(AA28:AA49,"=59214062",W28:W49),2) -> 0 | AK51: =ROUND(SUMIF(AA28:AA49,"=59214062",X28:X49),2) -> 99.96 | AL51: =ROUND(SUMIF(AA28:AA49,"=59214062",Y28:Y49),2) -> 53.02 | AO51: =ROUND(BX51,2) -> 0 | AP51: =ROUND(BY51,2) -> 349619.17 | AQ51: =ROUND(BZ51,2) -> 0 | AR51: =ROUND(CA51,2) -> 376172.05 | AS51: =ROUND(CB51,2) -> 26421.05 | AT51: =ROUND(CC51,2) -> 131.83 | AU51: =ROUND(CD51,2) -> 0 | AV51: =ROUND(CE51,2) -> 375907.12 | ... BD51: =ROUND(CM51,2) -> 0 | BX51: =ROUND(SUMIF(AA28:AA49,"=59214062",FQ28:FQ49),2) -> 0 | BY51: =ROUND(SUMIF(AA28:AA49,"=59214062",FR28:FR49),2) -> 349619.17 | BZ51: =ROUND(SUMIF(AA28:AA49,"=59214062",GL28:GL49),2) -> 0 | CA51: =ROUND(SUMIF(AA28:AA49,"=59214062",GM28:GM49),2) -> 376172.05 | CB51: =ROUND(SUMIF(AA28:AA49,"=59214062",GN28:GN49),2) -> 26421.05 | CC51: =ROUND(SUMIF(AA28:AA49,"=59214062",GO28:GO49),2) -> 131.83 | CD51: =ROUND(SUMIF(AA28:AA49,"=59214062",GP28:GP49),2) -> 0 | CE51: =AC51-BX51 -> 375907.12 | CF51: =AC51-BY51 -> 26287.95 | CG51: =BX51-BZ51 -> 0 | CH51: =AC51-BX51-BY51+BZ51 -> 26287.95 | CI51: =BY51-BZ51 -> 349619.17 | CJ51: =ROUND(SUMIF(AA28:AA49,"=59214062",GX28:GX49),2) -> 0 | CK51: =ROUND(SUMIF(AA28:AA49,"=59214062",GY28:GY49),2) -> 0 | CL51: =ROUND(SUMIF(AA28:AA49,"=59214062",GZ28:GZ49),2) -> 0 | CM51: =ROUND(SUMIF(AA28:AA49,"=59214062",HD28:HD49),2) -> 0 | DG51: =ROUND(DT51,2) -> 2968853.6 | DH51: =ROUND(DU51,2) -> 2963173.1 | DI51: =ROUND(DV51,2) -> 184.3 | DJ51: =ROUND(DW51,2) -> 87.99 | DK51: =ROUND(DX51,2) -> 5496.25 | DL51: =ROUND(DY51,2) -> 0 | DM51: =DZ51 -> 8.0418206 | DN51: =EA51 -> 0 | DO51: =ROUND(EB51,2) -> 0 | DP51: =ROUND(EC51,2) -> 5496.25 | DQ51: =ROUND(ED51,2) -> 2915.68 | DT51: =ROUND(SUMIF(AA28:AA49,"=59214059",O28:O49),2) -> 2968853.6 | DU51: =ROUND(SUMIF(AA28:AA49,"=59214059",P28:P49),2) -> 2963173.1 | DV51: =ROUND(SUMIF(AA28:AA49,"=59214059",Q28:Q49),2) -> 184.3 | DW51: =ROUND(SUMIF(AA28:AA49,"=59214059",R28:R49),2) -> 87.99 | DX51: =ROUND(SUMIF(AA28:AA49,"=59214059",S28:S49),2) -> 5496.25 | DY51: =ROUND(SUMIF(AA28:AA49,"=59214059",T28:T49),2) -> 0 | DZ51: =SUMIF(AA28:AA49,"=59214059",U28:U49) -> 8.0418206 | EA51: =SUMIF(AA28:AA49,"=59214059",V28:V49) -> 0 | EB51: =ROUND(SUMIF(AA28:AA49,"=59214059",W28:W49),2) -> 0 | EC51: =ROUND(SUMIF(AA28:AA49,"=59214059",X28:X49),2) -> 5496.25 | ED51: =ROUND(SUMIF(AA28:AA49,"=59214059",Y28:Y49),2) -> 2915.68 | EG51: =ROUND(FP51,2) -> 0 | EH51: =ROUND(FQ51,2) -> 2703458 | EI51: =ROUND(FR51,2) -> 0 | EJ51: =ROUND(FS51,2) -> 2977265.6 | EK51: =ROUND(FT51,2) -> 266614.13 | EL51: =ROUND(FU51,2) -> 7193.49 | EM51: =ROUND(FV51,2) -> 0 | EN51: =ROUND(FW51,2) -> 2963173.1 | ... EV51: =ROUND(GE51,2) -> 0 | FP51: =ROUND(SUMIF(AA28:AA49,"=59214059",FQ28:FQ49),2) -> 0 | FQ51: =ROUND(SUMIF(AA28:AA49,"=59214059",FR28:FR49),2) -> 2703458 | FR51: =ROUND(SUMIF(AA28:AA49,"=59214059",GL28:GL49),2) -> 0 | FS51: =ROUND(SUMIF(AA28:AA49,"=59214059",GM28:GM49),2) -> 2977265.6 | FT51: =ROUND(SUMIF(AA28:AA49,"=59214059",GN28:GN49),2) -> 266614.13 | FU51: =ROUND(SUMIF(AA28:AA49,"=59214059",GO28:GO49),2) -> 7193.49 | FV51: =ROUND(SUMIF(AA28:AA49,"=59214059",GP28:GP49),2) -> 0 | FW51: =DU51-FP51 -> 2963173.1 | FX51: =DU51-FQ51 -> 259715.14 | FY51: =FP51-FR51 -> 0 | FZ51: =DU51-FP51-FQ51+FR51 -> 259715.14 | GA51: =FQ51-FR51 -> 2703458 | GB51: =ROUND(SUMIF(AA28:AA49,"=59214059",GX28:GX49),2) -> 0 | GC51: =ROUND(SUMIF(AA28:AA49,"=59214059",GY28:GY49),2) -> 0 | GD51: =ROUND(SUMIF(AA28:AA49,"=59214059",GZ28:GZ49),2) -> 0 | GE51: =ROUND(SUMIF(AA28:AA49,"=59214059",HD28:HD49),2) -> 0 | GX51: 0
A53: 50 | B53: 0 | C53: 0 | D53: 1 | E53: 201 | F53: =ROUND(Source!O51,O53) -> 376019.07 | G53: ПЗ | H53: Прямые затраты | K53: 201 | L53: 1 | M53: 3 | O53: 2 | P53: =ROUND(Source!DG51,O53) -> 2968853.6 | W53: 376019.07 | X53: 1 | Y53: 376019.07 | Z53: 2968853.6 | AA53: 1 | AB53: 2968853.6
A54: 50 | B54: 0 | C54: 0 | D54: 1 | E54: 202 | F54: =ROUND(Source!P51,O54) -> 375907.12 | G54: СтМатОб | H54: Стоимость материальных ресурсов (всего) | K54: 202 | L54: 2 | M54: 3 | O54: 2 | P54: =ROUND(Source!DH51,O54) -> 2963173.1 | W54: 375907.12 | X54: 1 | Y54: 375907.12 | Z54: 2963173.1 | AA54: 1 | AB54: 2963173.1
A55: 50 | B55: 0 | C55: 0 | D55: 1 | E55: 222 | F55: =ROUND(Source!AO51,O55) -> 0 | G55: СтМатОбЗак | H55: Стоимость материалов и оборудования заказчика | K55: 222 | L55: 3 | M55: 3 | O55: 2 | P55: =ROUND(Source!EG51,O55) -> 0 | W55: 0 | X55: 1 | Y55: 0 | Z55: 0 | AA55: 1 | AB55: 0
A56: 50 | B56: 0 | C56: 0 | D56: 1 | E56: 225 | F56: =ROUND(Source!AV51,O56) -> 375907.12 | G56: СтМатОбПод | H56: Стоимость материалов и оборудования подрядчика | K56: 225 | L56: 4 | M56: 3 | O56: 2 | P56: =ROUND(Source!EN51,O56) -> 2963173.1 | W56: 375907.12 | X56: 1 | Y56: 375907.12 | Z56: 2963173.1 | AA56: 1 | AB56: 2963173.1
A57: 50 | B57: 0 | C57: 0 | D57: 1 | E57: 226 | F57: =ROUND(Source!AW51,O57) -> 26287.95 | G57: СтМат | H57: Стоимость материалов (всего) | K57: 226 | L57: 5 | M57: 3 | O57: 2 | P57: =ROUND(Source!EO51,O57) -> 259715.14 | W57: 26287.95 | X57: 1 | Y57: 26287.95 | Z57: 259715.14 | AA57: 1 | AB57: 259715.14
A58: 50 | B58: 0 | C58: 0 | D58: 1 | E58: 227 | F58: =ROUND(Source!AX51,O58) -> 0 | G58: СтМатЗак | H58: Стоимость материалов заказчика | K58: 227 | L58: 6 | M58: 3 | O58: 2 | P58: =ROUND(Source!EP51,O58) -> 0 | W58: 0 | X58: 1 | Y58: 0 | Z58: 0 | AA58: 1 | AB58: 0
A59: 50 | B59: 0 | C59: 0 | D59: 1 | E59: 228 | F59: =ROUND(Source!AY51,O59) -> 26287.95 | G59: СтМатПод | H59: Стоимость материалов подрядчика | K59: 228 | L59: 7 | M59: 3 | O59: 2 | P59: =ROUND(Source!EQ51,O59) -> 259715.14 | W59: 26287.95 | X59: 1 | Y59: 26287.95 | Z59: 259715.14 | AA59: 1 | AB59: 259715.14
A60: 50 | B60: 0 | C60: 0 | D60: 1 | E60: 216 | F60: =ROUND(Source!AP51,O60) -> 349619.17 | G60: Оборуд | H60: Стоимость оборудования (всего) | K60: 216 | L60: 8 | M60: 3 | O60: 2 | P60: =ROUND(Source!EH51,O60) -> 2703458 | W60: 349619.17 | X60: 1 | Y60: 349619.17 | Z60: 2703458 | AA60: 1 | AB60: 2703458
A61: 50 | B61: 0 | C61: 0 | D61: 1 | E61: 223 | F61: =ROUND(Source!AQ51,O61) -> 0 | G61: ОборудЗак | H61: Стоимость оборудования заказчика | K61: 223 | L61: 9 | M61: 3 | O61: 2 | P61: =ROUND(Source!EI51,O61) -> 0 | W61: 0 | X61: 1 | Y61: 0 | Z61: 0 | AA61: 1 | AB61: 0
A62: 50 | B62: 0 | C62: 0 | D62: 1 | E62: 229 | F62: =ROUND(Source!AZ51,O62) -> 349619.17 | G62: ОборудПод | H62: Стоимость оборудования подрядчика | K62: 229 | L62: 10 | M62: 3 | O62: 2 | P62: =ROUND(Source!ER51,O62) -> 2703458 | W62: 349619.17 | X62: 1 | Y62: 349619.17 | Z62: 2703458 | AA62: 1 | AB62: 2703458
A63: 50 | B63: 0 | C63: 0 | D63: 1 | E63: 203 | F63: =ROUND(Source!Q51,O63) -> 12 | G63: ЭММ | H63: Эксплуатация машин | K63: 203 | L63: 11 | M63: 3 | O63: 2 | P63: =ROUND(Source!DI51,O63) -> 184.3 | W63: 12 | X63: 1 | Y63: 12 | Z63: 184.3 | AA63: 1 | AB63: 184.3
A64: 50 | B64: 0 | C64: 0 | D64: 1 | E64: 231 | F64: =ROUND(Source!BB51,O64) -> 0 | G64: ЭММсНРиСП | H64: Эксплуатация машин по ТСН-2001.16 | K64: 231 | L64: 12 | M64: 3 | O64: 2 | P64: =ROUND(Source!ET51,O64) -> 0 | W64: 0 | X64: 1 | Y64: 0 | Z64: 0 | AA64: 1 | AB64: 0
A65: 50 | B65: 0 | C65: 0 | D65: 1 | E65: 204 | F65: =ROUND(Source!R51,O65) -> 1.6 | G65: ЗПМ | H65: ЗП машинистов | K65: 204 | L65: 13 | M65: 3 | O65: 2 | P65: =ROUND(Source!DJ51,O65) -> 87.99 | W65: 1.6 | X65: 1 | Y65: 1.6 | Z65: 87.99 | AA65: 1 | AB65: 87.99
A66: 50 | B66: 0 | C66: 0 | D66: 1 | E66: 205 | F66: =ROUND(Source!S51,O66) -> 99.95 | G66: ОЗП | H66: Основная ЗП рабочих | K66: 205 | L66: 14 | M66: 3 | O66: 2 | P66: =ROUND(Source!DK51,O66) -> 5496.25 | W66: 99.95 | X66: 1 | Y66: 99.95 | Z66: 5496.25 | AA66: 1 | AB66: 5496.25
A67: 50 | B67: 0 | C67: 0 | D67: 1 | E67: 232 | F67: =ROUND(Source!BC51,O67) -> 0 | G67: ОЗПсНРиСП | H67: Основная ЗП рабочих по ТСН-2001.16 | K67: 232 | L67: 15 | M67: 3 | O67: 2 | P67: =ROUND(Source!EU51,O67) -> 0 | W67: 0 | X67: 1 | Y67: 0 | Z67: 0 | AA67: 1 | AB67: 0
A68: 50 | B68: 0 | C68: 0 | D68: 1 | E68: 214 | F68: =ROUND(Source!AS51,O68) -> 26421.05 | G68: Строит | H68: Строительные работы с НР и СП | K68: 214 | L68: 16 | M68: 3 | O68: 2 | P68: =ROUND(Source!EK51,O68) -> 266614.13 | W68: 26421.05 | X68: 1 | Y68: 26421.05 | Z68: 266614.13 | AA68: 1 | AB68: 266614.13
A69: 50 | B69: 0 | C69: 0 | D69: 1 | E69: 215 | F69: =ROUND(Source!AT51,O69) -> 131.83 | G69: Монтаж | H69: Монтажные работы с НР и СП | K69: 215 | L69: 17 | M69: 3 | O69: 2 | P69: =ROUND(Source!EL51,O69) -> 7193.49 | W69: 131.83 | X69: 1 | Y69: 131.83 | Z69: 7193.49 | AA69: 1 | AB69: 7193.49
A70: 50 | B70: 0 | C70: 0 | D70: 1 | E70: 217 | F70: =ROUND(Source!AU51,O70) -> 0 | G70: Прочие | H70: Прочие работы с НР и СП | K70: 217 | L70: 18 | M70: 3 | O70: 2 | P70: =ROUND(Source!EM51,O70) -> 0 | W70: 0 | X70: 1 | Y70: 0 | Z70: 0 | AA70: 1 | AB70: 0
A71: 50 | B71: 0 | C71: 0 | D71: 1 | E71: 230 | F71: =ROUND(Source!BA51,O71) -> 0 | G71: ПрочиеЗатр | H71: Прочие затраты по ТСН-2001.16 | K71: 230 | L71: 19 | M71: 3 | O71: 2 | P71: =ROUND(Source!ES51,O71) -> 0 | W71: 0 | X71: 1 | Y71: 0 | Z71: 0 | AA71: 1 | AB71: 0
A72: 50 | B72: 0 | C72: 0 | D72: 1 | E72: 206 | F72: =ROUND(Source!T51,O72) -> 0 | G72: ВозврМат | H72: Возврат материалов | K72: 206 | L72: 20 | M72: 3 | O72: 2 | P72: =ROUND(Source!DL51,O72) -> 0 | W72: 0 | X72: 1 | Y72: 0 | Z72: 0 | AA72: 1 | AB72: 0
A73: 50 | B73: 0 | C73: 0 | D73: 1 | E73: 207 | F73: =Source!U51 -> 8.0418206 | G73: ТрудСтр | H73: Трудозатраты строителей | K73: 207 | L73: 21 | M73: 3 | O73: -1 | P73: =Source!DM51 -> 8.0418206 | W73: 8.0418206 | X73: 1 | Y73: 8.0418206 | Z73: 8.0418206 | AA73: 1 | AB73: 8.0418206
A74: 50 | B74: 0 | C74: 0 | D74: 1 | E74: 208 | F74: =Source!V51 -> 0 | G74: ТрудМаш | H74: Трудозатраты машинистов | K74: 208 | L74: 22 | M74: 3 | O74: -1 | P74: =Source!DN51 -> 0 | W74: 0 | X74: 1 | Y74: 0 | Z74: 0 | AA74: 1 | AB74: 0
A75: 50 | B75: 0 | C75: 0 | D75: 1 | E75: 209 | F75: =ROUND(Source!W51,O75) -> 0 | G75: ТранспМат | H75: Транспорт материалов | K75: 209 | L75: 23 | M75: 3 | O75: 2 | P75: =ROUND(Source!DO51,O75) -> 0 | W75: 0 | X75: 1 | Y75: 0 | Z75: 0 | AA75: 1 | AB75: 0
A76: 50 | B76: 0 | C76: 0 | D76: 1 | E76: 233 | F76: =ROUND(Source!BD51,O76) -> 0 | G76: Перевозка | H76: Перевозка грузов | K76: 233 | L76: 24 | M76: 3 | O76: 2 | P76: =ROUND(Source!EV51,O76) -> 0 | W76: 0 | X76: 1 | Y76: 0 | Z76: 0 | AA76: 1 | AB76: 0
A77: 50 | B77: 0 | C77: 0 | D77: 1 | E77: 210 | F77: =ROUND(Source!X51,O77) -> 99.96 | G77: НР | H77: Накладные расходы | K77: 210 | L77: 25 | M77: 3 | O77: 2 | P77: =ROUND(Source!DP51,O77) -> 5496.25 | W77: 99.96 | X77: 1 | Y77: 99.96 | Z77: 5496.25 | AA77: 1 | AB77: 5496.25
A78: 50 | B78: 0 | C78: 0 | D78: 1 | E78: 211 | F78: =ROUND(Source!Y51,O78) -> 53.02 | G78: СмПриб | H78: Сметная прибыль | K78: 211 | L78: 26 | M78: 3 | O78: 2 | P78: =ROUND(Source!DQ51,O78) -> 2915.68 | W78: 53.02 | X78: 1 | Y78: 53.02 | Z78: 2915.68 | AA78: 1 | AB78: 2915.68
A79: 50 | B79: 0 | C79: 0 | D79: 1 | E79: 224 | F79: =ROUND(Source!AR51,O79) -> 376172.05 | G79: Всего | H79: Всего с НР и СП | K79: 224 | L79: 27 | M79: 3 | O79: 2 | P79: =ROUND(Source!EJ51,O79) -> 2977265.6 | W79: 376172.05 | X79: 1 | Y79: 376172.05 | Z79: 2977265.6 | AA79: 1 | AB79: 2977265.6
A81: 51 | B81: =B20 -> 1 | C81: =A20 -> 3 | D81: =ROW(A20) -> 20 | F81: =IF(F20<>"",F20,"") -> 02-01-20 | G81: =IF(G20<>"",G20,"") -> Мероприятия по противодействию террористическим актам | H81: 0 | O81: =ROUND(O51+AB81,2) -> 376019.07 | P81: =ROUND(P51+AC81,2) -> 375907.12 | Q81: =ROUND(Q51+AD81,2) -> 12 | R81: =ROUND(R51+AE81,2) -> 1.6 | S81: =ROUND(S51+AF81,2) -> 99.95 | T81: =ROUND(T51+AG81,2) -> 0 | U81: =U51+AH81 -> 8.0418206 | V81: =V51+AI81 -> 0 | W81: =ROUND(W51+AJ81,2) -> 0 | X81: =ROUND(X51+AK81,2) -> 99.96 | Y81: =ROUND(Y51+AL81,2) -> 53.02 | AO81: =ROUND(AO51+BX81,2) -> 0 | AP81: =ROUND(AP51+BY81,2) -> 349619.17 | AQ81: =ROUND(AQ51+BZ81,2) -> 0 | AR81: =ROUND(AR51+CA81,2) -> 376172.05 | AS81: =ROUND(AS51+CB81,2) -> 26421.05 | AT81: =ROUND(AT51+CC81,2) -> 131.83 | AU81: =ROUND(AU51+CD81,2) -> 0 | AV81: =ROUND(AV51+CE81,2) -> 375907.12 | ... BD81: =ROUND(BD51+CM81,2) -> 0 | DG81: =ROUND(DG51+DT81,2) -> 2968853.6 | DH81: =ROUND(DH51+DU81,2) -> 2963173.1 | DI81: =ROUND(DI51+DV81,2) -> 184.3 | DJ81: =ROUND(DJ51+DW81,2) -> 87.99 | DK81: =ROUND(DK51+DX81,2) -> 5496.25 | DL81: =ROUND(DL51+DY81,2) -> 0 | DM81: =DM51+DZ81 -> 8.0418206 | DN81: =DN51+EA81 -> 0 | DO81: =ROUND(DO51+EB81,2) -> 0 | DP81: =ROUND(DP51+EC81,2) -> 5496.25 | DQ81: =ROUND(DQ51+ED81,2) -> 2915.68 | EG81: =ROUND(EG51+FP81,2) -> 0 | EH81: =ROUND(EH51+FQ81,2) -> 2703458 | EI81: =ROUND(EI51+FR81,2) -> 0 | EJ81: =ROUND(EJ51+FS81,2) -> 2977265.6 | EK81: =ROUND(EK51+FT81,2) -> 266614.13 | EL81: =ROUND(EL51+FU81,2) -> 7193.49 | EM81: =ROUND(EM51+FV81,2) -> 0 | EN81: =ROUND(EN51+FW81,2) -> 2963173.1 | ... EV81: =ROUND(EV51+GE81,2) -> 0 | GX81: 0
A83: 50 | B83: 0 | C83: 0 | D83: 1 | E83: 201 | F83: =ROUND(Source!O81,O83) -> 376019.07 | G83: ПЗ | H83: Прямые затраты | K83: 201 | L83: 1 | M83: 3 | O83: 2 | P83: =ROUND(Source!DG81,O83) -> 2968853.6 | W83: 376019.07 | X83: 1 | Y83: 376019.07 | Z83: 2968853.6 | AA83: 1 | AB83: 2968853.6
A84: 50 | B84: 0 | C84: 0 | D84: 1 | E84: 202 | F84: =ROUND(Source!P81,O84) -> 375907.12 | G84: СтМатОб | H84: Стоимость материальных ресурсов (всего) | K84: 202 | L84: 2 | M84: 3 | O84: 2 | P84: =ROUND(Source!DH81,O84) -> 2963173.1 | W84: 375907.12 | X84: 1 | Y84: 375907.12 | Z84: 2963173.1 | AA84: 1 | AB84: 2963173.1
A85: 50 | B85: 0 | C85: 0 | D85: 1 | E85: 222 | F85: =ROUND(Source!AO81,O85) -> 0 | G85: СтМатОбЗак | H85: Стоимость материалов и оборудования заказчика | K85: 222 | L85: 3 | M85: 3 | O85: 2 | P85: =ROUND(Source!EG81,O85) -> 0 | W85: 0 | X85: 1 | Y85: 0 | Z85: 0 | AA85: 1 | AB85: 0
A86: 50 | B86: 0 | C86: 0 | D86: 1 | E86: 225 | F86: =ROUND(Source!AV81,O86) -> 375907.12 | G86: СтМатОбПод | H86: Стоимость материалов и оборудования подрядчика | K86: 225 | L86: 4 | M86: 3 | O86: 2 | P86: =ROUND(Source!EN81,O86) -> 2963173.1 | W86: 375907.12 | X86: 1 | Y86: 375907.12 | Z86: 2963173.1 | AA86: 1 | AB86: 2963173.1
A87: 50 | B87: 0 | C87: 0 | D87: 1 | E87: 226 | F87: =ROUND(Source!AW81,O87) -> 26287.95 | G87: СтМат | H87: Стоимость материалов (всего) | K87: 226 | L87: 5 | M87: 3 | O87: 2 | P87: =ROUND(Source!EO81,O87) -> 259715.14 | W87: 26287.95 | X87: 1 | Y87: 26287.95 | Z87: 259715.14 | AA87: 1 | AB87: 259715.14
A88: 50 | B88: 0 | C88: 0 | D88: 1 | E88: 227 | F88: =ROUND(Source!AX81,O88) -> 0 | G88: СтМатЗак | H88: Стоимость материалов заказчика | K88: 227 | L88: 6 | M88: 3 | O88: 2 | P88: =ROUND(Source!EP81,O88) -> 0 | W88: 0 | X88: 1 | Y88: 0 | Z88: 0 | AA88: 1 | AB88: 0
A89: 50 | B89: 0 | C89: 0 | D89: 1 | E89: 228 | F89: =ROUND(Source!AY81,O89) -> 26287.95 | G89: СтМатПод | H89: Стоимость материалов подрядчика | K89: 228 | L89: 7 | M89: 3 | O89: 2 | P89: =ROUND(Source!EQ81,O89) -> 259715.14 | W89: 26287.95 | X89: 1 | Y89: 26287.95 | Z89: 259715.14 | AA89: 1 | AB89: 259715.14
A90: 50 | B90: 0 | C90: 0 | D90: 1 | E90: 216 | F90: =ROUND(Source!AP81,O90) -> 349619.17 | G90: Оборуд | H90: Стоимость оборудования (всего) | K90: 216 | L90: 8 | M90: 3 | O90: 2 | P90: =ROUND(Source!EH81,O90) -> 2703458 | W90: 349619.17 | X90: 1 | Y90: 349619.17 | Z90: 2703458 | AA90: 1 | AB90: 2703458
A91: 50 | B91: 0 | C91: 0 | D91: 1 | E91: 223 | F91: =ROUND(Source!AQ81,O91) -> 0 | G91: ОборудЗак | H91: Стоимость оборудования заказчика | K91: 223 | L91: 9 | M91: 3 | O91: 2 | P91: =ROUND(Source!EI81,O91) -> 0 | W91: 0 | X91: 1 | Y91: 0 | Z91: 0 | AA91: 1 | AB91: 0
A92: 50 | B92: 0 | C92: 0 | D92: 1 | E92: 229 | F92: =ROUND(Source!AZ81,O92) -> 349619.17 | G92: ОборудПод | H92: Стоимость оборудования подрядчика | K92: 229 | L92: 10 | M92: 3 | O92: 2 | P92: =ROUND(Source!ER81,O92) -> 2703458 | W92: 349619.17 | X92: 1 | Y92: 349619.17 | Z92: 2703458 | AA92: 1 | AB92: 2703458
A93: 50 | B93: 0 | C93: 0 | D93: 1 | E93: 203 | F93: =ROUND(Source!Q81,O93) -> 12 | G93: ЭММ | H93: Эксплуатация машин | K93: 203 | L93: 11 | M93: 3 | O93: 2 | P93: =ROUND(Source!DI81,O93) -> 184.3 | W93: 12 | X93: 1 | Y93: 12 | Z93: 184.3 | AA93: 1 | AB93: 184.3
A94: 50 | B94: 0 | C94: 0 | D94: 1 | E94: 231 | F94: =ROUND(Source!BB81,O94) -> 0 | G94: ЭММсНРиСП | H94: Эксплуатация машин по ТСН-2001.16 | K94: 231 | L94: 12 | M94: 3 | O94: 2 | P94: =ROUND(Source!ET81,O94) -> 0 | W94: 0 | X94: 1 | Y94: 0 | Z94: 0 | AA94: 1 | AB94: 0
A95: 50 | B95: 0 | C95: 0 | D95: 1 | E95: 204 | F95: =ROUND(Source!R81,O95) -> 1.6 | G95: ЗПМ | H95: ЗП машинистов | K95: 204 | L95: 13 | M95: 3 | O95: 2 | P95: =ROUND(Source!DJ81,O95) -> 87.99 | W95: 1.6 | X95: 1 | Y95: 1.6 | Z95: 87.99 | AA95: 1 | AB95: 87.99
A96: 50 | B96: 0 | C96: 0 | D96: 1 | E96: 205 | F96: =ROUND(Source!S81,O96) -> 99.95 | G96: ОЗП | H96: Основная ЗП рабочих | K96: 205 | L96: 14 | M96: 3 | O96: 2 | P96: =ROUND(Source!DK81,O96) -> 5496.25 | W96: 99.95 | X96: 1 | Y96: 99.95 | Z96: 5496.25 | AA96: 1 | AB96: 5496.25
A97: 50 | B97: 0 | C97: 0 | D97: 1 | E97: 232 | F97: =ROUND(Source!BC81,O97) -> 0 | G97: ОЗПсНРиСП | H97: Основная ЗП рабочих по ТСН-2001.16 | K97: 232 | L97: 15 | M97: 3 | O97: 2 | P97: =ROUND(Source!EU81,O97) -> 0 | W97: 0 | X97: 1 | Y97: 0 | Z97: 0 | AA97: 1 | AB97: 0
A98: 50 | B98: 0 | C98: 0 | D98: 1 | E98: 214 | F98: =ROUND(Source!AS81,O98) -> 26421.05 | G98: Строит | H98: Строительные работы с НР и СП | K98: 214 | L98: 16 | M98: 3 | O98: 2 | P98: =ROUND(Source!EK81,O98) -> 266614.13 | W98: 26421.05 | X98: 1 | Y98: 26421.05 | Z98: 266614.13 | AA98: 1 | AB98: 266614.13
A99: 50 | B99: 0 | C99: 0 | D99: 1 | E99: 215 | F99: =ROUND(Source!AT81,O99) -> 131.83 | G99: Монтаж | H99: Монтажные работы с НР и СП | K99: 215 | L99: 17 | M99: 3 | O99: 2 | P99: =ROUND(Source!EL81,O99) -> 7193.49 | W99: 131.83 | X99: 1 | Y99: 131.83 | Z99: 7193.49 | AA99: 1 | AB99: 7193.49
A100: 50 | B100: 0 | C100: 0 | D100: 1 | E100: 217 | F100: =ROUND(Source!AU81,O100) -> 0 | G100: Прочие | H100: Прочие работы с НР и СП | K100: 217 | L100: 18 | M100: 3 | O100: 2 | P100: =ROUND(Source!EM81,O100) -> 0 | W100: 0 | X100: 1 | Y100: 0 | Z100: 0 | AA100: 1 | AB100: 0
A101: 50 | B101: 0 | C101: 0 | D101: 1 | E101: 230 | F101: =ROUND(Source!BA81,O101) -> 0 | G101: ПрочиеЗатр | H101: Прочие затраты по ТСН-2001.16 | K101: 230 | L101: 19 | M101: 3 | O101: 2 | P101: =ROUND(Source!ES81,O101) -> 0 | W101: 0 | X101: 1 | Y101: 0 | Z101: 0 | AA101: 1 | AB101: 0
A102: 50 | B102: 0 | C102: 0 | D102: 1 | E102: 206 | F102: =ROUND(Source!T81,O102) -> 0 | G102: ВозврМат | H102: Возврат материалов | K102: 206 | L102: 20 | M102: 3 | O102: 2 | P102: =ROUND(Source!DL81,O102) -> 0 | W102: 0 | X102: 1 | Y102: 0 | Z102: 0 | AA102: 1 | AB102: 0
A103: 50 | B103: 0 | C103: 0 | D103: 1 | E103: 207 | F103: =Source!U81 -> 8.0418206 | G103: ТрудСтр | H103: Трудозатраты строителей | K103: 207 | L103: 21 | M103: 3 | O103: -1 | P103: =Source!DM81 -> 8.0418206 | W103: 8.0418206 | X103: 1 | Y103: 8.0418206 | Z103: 8.0418206 | AA103: 1 | AB103: 8.0418206
A104: 50 | B104: 0 | C104: 0 | D104: 1 | E104: 208 | F104: =Source!V81 -> 0 | G104: ТрудМаш | H104: Трудозатраты машинистов | K104: 208 | L104: 22 | M104: 3 | O104: -1 | P104: =Source!DN81 -> 0 | W104: 0 | X104: 1 | Y104: 0 | Z104: 0 | AA104: 1 | AB104: 0
A105: 50 | B105: 0 | C105: 0 | D105: 1 | E105: 209 | F105: =ROUND(Source!W81,O105) -> 0 | G105: ТранспМат | H105: Транспорт материалов | K105: 209 | L105: 23 | M105: 3 | O105: 2 | P105: =ROUND(Source!DO81,O105) -> 0 | W105: 0 | X105: 1 | Y105: 0 | Z105: 0 | AA105: 1 | AB105: 0
A106: 50 | B106: 0 | C106: 0 | D106: 1 | E106: 233 | F106: =ROUND(Source!BD81,O106) -> 0 | G106: Перевозка | H106: Перевозка грузов | K106: 233 | L106: 24 | M106: 3 | O106: 2 | P106: =ROUND(Source!EV81,O106) -> 0 | W106: 0 | X106: 1 | Y106: 0 | Z106: 0 | AA106: 1 | AB106: 0
A107: 50 | B107: 0 | C107: 0 | D107: 1 | E107: 210 | F107: =ROUND(Source!X81,O107) -> 99.96 | G107: НР | H107: Накладные расходы | K107: 210 | L107: 25 | M107: 3 | O107: 2 | P107: =ROUND(Source!DP81,O107) -> 5496.25 | W107: 99.96 | X107: 1 | Y107: 99.96 | Z107: 5496.25 | AA107: 1 | AB107: 5496.25
A108: 50 | B108: 0 | C108: 0 | D108: 1 | E108: 211 | F108: =ROUND(Source!Y81,O108) -> 53.02 | G108: СмПриб | H108: Сметная прибыль | K108: 211 | L108: 26 | M108: 3 | O108: 2 | P108: =ROUND(Source!DQ81,O108) -> 2915.68 | W108: 53.02 | X108: 1 | Y108: 53.02 | Z108: 2915.68 | AA108: 1 | AB108: 2915.68
A109: 50 | B109: 0 | C109: 0 | D109: 1 | E109: 224 | F109: =ROUND(Source!AR81,O109) -> 376172.05 | G109: Всего | H109: Всего с НР и СП | K109: 224 | L109: 27 | M109: 3 | O109: 2 | P109: =ROUND(Source!EJ81,O109) -> 2977265.6 | W109: 376172.05 | X109: 1 | Y109: 376172.05 | Z109: 2977265.6 | AA109: 1 | AB109: 2977265.6
A111: 51 | B111: =B12 -> 150 | C111: =A12 -> 1 | D111: =ROW(A12) -> 12 | F111: =IF(F12<>"",F12,"") -> Новый объект (ТСН-2001 (Мосгосэкспертиза)) | G111: =IF(G12<>"",G12,"") -> 02-01-20 ПТА | H111: 0 | O111: =ROUND(O81,2) -> 376019.07 | P111: =ROUND(P81,2) -> 375907.12 | Q111: =ROUND(Q81,2) -> 12 | R111: =ROUND(R81,2) -> 1.6 | S111: =ROUND(S81,2) -> 99.95 | T111: =ROUND(T81,2) -> 0 | U111: =U81 -> 8.0418206 | V111: =V81 -> 0 | W111: =ROUND(W81,2) -> 0 | X111: =ROUND(X81,2) -> 99.96 | Y111: =ROUND(Y81,2) -> 53.02 | AO111: =ROUND(AO81,2) -> 0 | AP111: =ROUND(AP81,2) -> 349619.17 | AQ111: =ROUND(AQ81,2) -> 0 | AR111: =ROUND(AR81,2) -> 376172.05 | AS111: =ROUND(AS81,2) -> 26421.05 | AT111: =ROUND(AT81,2) -> 131.83 | AU111: =ROUND(AU81,2) -> 0 | AV111: =ROUND(AV81,2) -> 375907.12 | ... BD111: =ROUND(BD81,2) -> 0 | DG111: =ROUND(DG81,2) -> 2968853.6 | DH111: =ROUND(DH81,2) -> 2963173.1 | DI111: =ROUND(DI81,2) -> 184.3 | DJ111: =ROUND(DJ81,2) -> 87.99 | DK111: =ROUND(DK81,2) -> 5496.25 | DL111: =ROUND(DL81,2) -> 0 | DM111: =DM81 -> 8.0418206 | DN111: =DN81 -> 0 | DO111: =ROUND(DO81,2) -> 0 | DP111: =ROUND(DP81,2) -> 5496.25 | DQ111: =ROUND(DQ81,2) -> 2915.68 | EG111: =ROUND(EG81,2) -> 0 | EH111: =ROUND(EH81,2) -> 2703458 | EI111: =ROUND(EI81,2) -> 0 | EJ111: =ROUND(EJ81,2) -> 2977265.6 | EK111: =ROUND(EK81,2) -> 266614.13 | EL111: =ROUND(EL81,2) -> 7193.49 | EM111: =ROUND(EM81,2) -> 0 | EN111: =ROUND(EN81,2) -> 2963173.1 | ... EV111: =ROUND(EV81,2) -> 0 | GX111: 0
A113: 50 | B113: 0 | C113: 0 | D113: 1 | E113: 201 | F113: =ROUND(Source!O111,O113) -> 376019.07 | G113: ПЗ | H113: Прямые затраты | K113: 201 | L113: 1 | M113: 3 | O113: 2 | P113: =ROUND(Source!DG111,O113) -> 2968853.6 | W113: 376019.07 | X113: 1 | Y113: 376019.07 | Z113: 2968853.6 | AA113: 1 | AB113: 2968853.6
A114: 50 | B114: 0 | C114: 0 | D114: 1 | E114: 202 | F114: =ROUND(Source!P111,O114) -> 375907.12 | G114: СтМатОб | H114: Стоимость материальных ресурсов (всего) | K114: 202 | L114: 2 | M114: 3 | O114: 2 | P114: =ROUND(Source!DH111,O114) -> 2963173.1 | W114: 375907.12 | X114: 1 | Y114: 375907.12 | Z114: 2963173.1 | AA114: 1 | AB114: 2963173.1
A115: 50 | B115: 0 | C115: 0 | D115: 1 | E115: 222 | F115: =ROUND(Source!AO111,O115) -> 0 | G115: СтМатОбЗак | H115: Стоимость материалов и оборудования заказчика | K115: 222 | L115: 3 | M115: 3 | O115: 2 | P115: =ROUND(Source!EG111,O115) -> 0 | W115: 0 | X115: 1 | Y115: 0 | Z115: 0 | AA115: 1 | AB115: 0
A116: 50 | B116: 0 | C116: 0 | D116: 1 | E116: 225 | F116: =ROUND(Source!AV111,O116) -> 375907.12 | G116: СтМатОбПод | H116: Стоимость материалов и оборудования подрядчика | K116: 225 | L116: 4 | M116: 3 | O116: 2 | P116: =ROUND(Source!EN111,O116) -> 2963173.1 | W116: 375907.12 | X116: 1 | Y116: 375907.12 | Z116: 2963173.1 | AA116: 1 | AB116: 2963173.1
A117: 50 | B117: 0 | C117: 0 | D117: 1 | E117: 226 | F117: =ROUND(Source!AW111,O117) -> 26287.95 | G117: СтМат | H117: Стоимость материалов (всего) | K117: 226 | L117: 5 | M117: 3 | O117: 2 | P117: =ROUND(Source!EO111,O117) -> 259715.14 | W117: 26287.95 | X117: 1 | Y117: 26287.95 | Z117: 259715.14 | AA117: 1 | AB117: 259715.14
A118: 50 | B118: 0 | C118: 0 | D118: 1 | E118: 227 | F118: =ROUND(Source!AX111,O118) -> 0 | G118: СтМатЗак | H118: Стоимость материалов заказчика | K118: 227 | L118: 6 | M118: 3 | O118: 2 | P118: =ROUND(Source!EP111,O118) -> 0 | W118: 0 | X118: 1 | Y118: 0 | Z118: 0 | AA118: 1 | AB118: 0
A119: 50 | B119: 0 | C119: 0 | D119: 1 | E119: 228 | F119: =ROUND(Source!AY111,O119) -> 26287.95 | G119: СтМатПод | H119: Стоимость материалов подрядчика | K119: 228 | L119: 7 | M119: 3 | O119: 2 | P119: =ROUND(Source!EQ111,O119) -> 259715.14 | W119: 26287.95 | X119: 1 | Y119: 26287.95 | Z119: 259715.14 | AA119: 1 | AB119: 259715.14
A120: 50 | B120: 0 | C120: 0 | D120: 1 | E120: 216 | F120: =ROUND(Source!AP111,O120) -> 349619.17 | G120: Оборуд | H120: Стоимость оборудования (всего) | K120: 216 | L120: 8 | M120: 3 | O120: 2 | P120: =ROUND(Source!EH111,O120) -> 2703458 | W120: 349619.17 | X120: 1 | Y120: 349619.17 | Z120: 2703458 | AA120: 1 | AB120: 2703458
A121: 50 | B121: 0 | C121: 0 | D121: 1 | E121: 223 | F121: =ROUND(Source!AQ111,O121) -> 0 | G121: ОборудЗак | H121: Стоимость оборудования заказчика | K121: 223 | L121: 9 | M121: 3 | O121: 2 | P121: =ROUND(Source!EI111,O121) -> 0 | W121: 0 | X121: 1 | Y121: 0 | Z121: 0 | AA121: 1 | AB121: 0
A122: 50 | B122: 0 | C122: 0 | D122: 1 | E122: 229 | F122: =ROUND(Source!AZ111,O122) -> 349619.17 | G122: ОборудПод | H122: Стоимость оборудования подрядчика | K122: 229 | L122: 10 | M122: 3 | O122: 2 | P122: =ROUND(Source!ER111,O122) -> 2703458 | W122: 349619.17 | X122: 1 | Y122: 349619.17 | Z122: 2703458 | AA122: 1 | AB122: 2703458
A123: 50 | B123: 0 | C123: 0 | D123: 1 | E123: 203 | F123: =ROUND(Source!Q111,O123) -> 12 | G123: ЭММ | H123: Эксплуатация машин | K123: 203 | L123: 11 | M123: 3 | O123: 2 | P123: =ROUND(Source!DI111,O123) -> 184.3 | W123: 12 | X123: 1 | Y123: 12 | Z123: 184.3 | AA123: 1 | AB123: 184.3
A124: 50 | B124: 0 | C124: 0 | D124: 1 | E124: 231 | F124: =ROUND(Source!BB111,O124) -> 0 | G124: ЭММсНРиСП | H124: Эксплуатация машин по ТСН-2001.16 | K124: 231 | L124: 12 | M124: 3 | O124: 2 | P124: =ROUND(Source!ET111,O124) -> 0 | W124: 0 | X124: 1 | Y124: 0 | Z124: 0 | AA124: 1 | AB124: 0
...

Sheet SourceObSm
A1: 0 | B1: Smeta.RU (495) 974-1589 | D1: _OBSM_ | F1: 0 | G1: 0 | H1: 0 | I1: Smeta.RU | K1: 1 | L1: 74402 | M1: 10 | N1: 12 | O1: 0 | P1: 0 | Q1: 3
A4: 1 | B4: 1 | C4: -1 | G4: Капитальный ремонт здания Государственного бюджетного общеобразовательного учреждения города Москвы "Школа № 236" по адресу: г. Москва ул. Клязьминская, д. 7 к. 4. 1 этап | EC4: 0
A12: 1 | B12: 51 | C12: 0 | E12: 0 | F12: Новый объект (ТСН-2001 (Мосгосэкспертиза)) | G12: 02-01-20 ПТА | I12: 0 | K12: 0 | L12: 0 | M12: 4098 | O12: 0 | P12: 0 | Q12: 0 | R12: 0 | S12: 0 | T12: 1 | V12: 0 | AB12: Кузнецова Е.А. | BB12: 0 | BH12: Сметные нормы списания | BI12: Коды ОКП для ТСН-2001 МГЭ Дополнение 80 | BJ12: 1 | BK12: 1 | BL12: 0 | BM12: 0 | BN12: 1 | BO12: 0 | BP12: 6 | BQ12: 2 | BR12: 1 | BS12: 1 | BT12: 0 | BU12: 0 | BV12: 1 | BW12: 0 | BX12: 0 | BZ12: Типовой расчет для ТСН-2001 МГЭ, Дополнение 80, строительство | CA12: Территориальные сметные нормативы для Москвы ТСН-2001 (МГЭ), дополнение 80 | CB12: Территориальные сметные нормативы для Москвы ТСН-2001 (МГЭ), дополнение 80 | CC12: Территориальные сметные нормативы для Москвы ТСН-2001 (МГЭ), дополнение 80 | CD12: Территориальные сметные нормативы для Москвы ТСН-2001 (МГЭ), дополнение 80 | CE12: Поправки для ТСН-2001 от 03.10.2025 г. доп.79 | CF12: 0 | CG12: 0 | CH12: 327688 | CK12: 80 | CQ12: Территориальные сметные нормативы для Москвы (ТСН-2001) | CR12: ТЕР | CS12: 41660 | CT12: 1 | CU12: 80 | CY12: 0 | EC12: 0
A14: 22 | B14: 1 | C14: 0 | D14: 59214059 | E14: 59214062 | F14: 2 | G14: 1
A16: 3 | B16: 1 | C16: 02-01-20 | D16: Мероприятия по противодействию террористическим актам | E16: =ROUND((Source!P98)/1000,2) -> 266.61 | F16: =ROUND((Source!P99)/1000,2) -> 7.19 | G16: =ROUND((Source!P90)/1000,2) -> 2703.46 | H16: =ROUND((Source!P100)/1000+(Source!P101)/1000,2) -> 0 | I16: =E16+F16+G16+H16 -> 2977.26 | J16: =ROUND((Source!P96+Source!P95)/1000,2) -> 5.58 | K16: 5932.03 | L16: 0 | M16: 0 | N16: =I16+L16+M16 -> 2977.26 | T16: =ROUND((Source!F98)/1000,2) -> 26.42 | U16: =ROUND((Source!F99)/1000,2) -> 0.13 | V16: =ROUND((Source!F90)/1000,2) -> 349.62 | W16: =ROUND((Source!F100)/1000+(Source!F101)/1000,2) -> 0 | X16: =T16+U16+V16+W16 -> 376.17 | Y16: =ROUND((Source!F96+Source!F95)/1000,2) -> 0.1 | Z16: 751.93 | AA16: 0 | AB16: 0 | AC16: =X16+AA16+AB16 -> 376.17 | AI16: 2 | AJ16: -1 | AN16: 0 | AT16: 2968853.6 | AU16: 2963173.1 | AV16: 0 | AW16: 2703458 | AX16: 0 | AY16: 184.3 | AZ16: 87.99 | BA16: 5496.25 | BB16: 266614.13 | BC16: 7193.49 | BD16: 0 | BE16: 0 | BF16: 8.0418206 | BG16: 0 | BH16: 0 | BI16: 5496.25 | BJ16: 2915.68 | BK16: 2977265.6 | BR16: 376019.07 | BS16: 375907.12 | BT16: 0 | BU16: 349619.17 | BV16: 0 | BW16: 12 | BX16: 1.6 | BY16: 99.95 | BZ16: 26421.05 | CA16: 131.83 | CB16: 0 | CC16: 0 | CD16: 8.0418206 | CE16: 0 | CF16: 0 | CG16: 99.96 | CH16: 53.02 | CI16: 376172.05
A18: 51 | E18: 266.61 | F18: 7.19 | G18: 2703.46 | H18: 0 | I18: 2977.26 | J18: 5.58 | K18: 5932.03 | L18: 0 | M18: 0 | N18: 2977.26 | T18: 26.42 | U18: 0.13 | V18: 349.62 | W18: 0 | X18: 376.17 | Y18: 0.1 | Z18: 751.93 | AA18: 0 | AB18: 0 | AC18: 376.17
A20: 50 | B20: 0 | C20: 0 | D20: 1 | E20: 201 | F20: 2968853.6 | G20: ПЗ | H20: Прямые затраты | K20: 201 | L20: 1 | M20: 3 | O20: 2 | P20: 376019.07
A21: 50 | B21: 0 | C21: 0 | D21: 1 | E21: 202 | F21: 2963173.1 | G21: СтМатОб | H21: Стоимость материальных ресурсов (всего) | K21: 202 | L21: 2 | M21: 3 | O21: 2 | P21: 375907.12
A22: 50 | B22: 0 | C22: 0 | D22: 1 | E22: 222 | F22: 0 | G22: СтМатОбЗак | H22: Стоимость материалов и оборудования заказчика | K22: 222 | L22: 3 | M22: 3 | O22: 2 | P22: 0
A23: 50 | B23: 0 | C23: 0 | D23: 1 | E23: 225 | F23: 2963173.1 | G23: СтМатОбПод | H23: Стоимость материалов и оборудования подрядчика | K23: 225 | L23: 4 | M23: 3 | O23: 2 | P23: 375907.12
A24: 50 | B24: 0 | C24: 0 | D24: 1 | E24: 226 | F24: 259715.14 | G24: СтМат | H24: Стоимость материалов (всего) | K24: 226 | L24: 5 | M24: 3 | O24: 2 | P24: 26287.95
A25: 50 | B25: 0 | C25: 0 | D25: 1 | E25: 227 | F25: 0 | G25: СтМатЗак | H25: Стоимость материалов заказчика | K25: 227 | L25: 6 | M25: 3 | O25: 2 | P25: 0
A26: 50 | B26: 0 | C26: 0 | D26: 1 | E26: 228 | F26: 259715.14 | G26: СтМатПод | H26: Стоимость материалов подрядчика | K26: 228 | L26: 7 | M26: 3 | O26: 2 | P26: 26287.95
A27: 50 | B27: 0 | C27: 0 | D27: 1 | E27: 216 | F27: 2703458 | G27: Оборуд | H27: Стоимость оборудования (всего) | K27: 216 | L27: 8 | M27: 3 | O27: 2 | P27: 349619.17
A28: 50 | B28: 0 | C28: 0 | D28: 1 | E28: 223 | F28: 0 | G28: ОборудЗак | H28: Стоимость оборудования заказчика | K28: 223 | L28: 9 | M28: 3 | O28: 2 | P28: 0
A29: 50 | B29: 0 | C29: 0 | D29: 1 | E29: 229 | F29: 2703458 | G29: ОборудПод | H29: Стоимость оборудования подрядчика | K29: 229 | L29: 10 | M29: 3 | O29: 2 | P29: 349619.17
A30: 50 | B30: 0 | C30: 0 | D30: 1 | E30: 203 | F30: 184.3 | G30: ЭММ | H30: Эксплуатация машин | K30: 203 | L30: 11 | M30: 3 | O30: 2 | P30: 12
A31: 50 | B31: 0 | C31: 0 | D31: 1 | E31: 231 | F31: 0 | G31: ЭММсНРиСП | H31: Эксплуатация машин по ТСН-2001.16 | K31: 231 | L31: 12 | M31: 3 | O31: 2 | P31: 0
... A46: 50 | B46: 0 | C46: 0 | D46: 1 | E46: 224 | F46: 2977265.6 | G46: Всего | H46: Всего с НР и СП | K46: 224 | L46: 27 | M46: 3 | O46: 2 | P46: 376172.05
A48: -1
A51: 75 | B51: Текущий уровень цен | C51: 2025 | D51: 3 | E51: 0 | G51: 0 | H51: 1 | I51: 1 | J51: 1 | K51: 0 | L51: 0 | M51: 1 | N51: 59214059 | O51: 1
A52: 1 | B52: Сборник индексов | C52: Коэффициенты к ТСН-2001 МГЭ Дополнение 80, строительство | D52: 2025 | E52: 9 | F52: 1 | G52: 1 | H52: 0 | I52: 2 | J52: 1 | K52: 9.88 | L52: 7.66 | M52: 1 | N52: 1 | O52: 9.88 | P52: 7.66 | Q52: 1 | AA52: 217/80 | AN52: 59214060
A53: 1 | B53: Сборник индексов | C53: Коэффициенты к ТСН-2001.13-2 Дополнение 46 | D53: 2025 | E53: 7 | F53: 1 | G53: 1 | H53: 0 | I53: 2 | J53: 1 | K53: 1 | L53: 1 | M53: 1 | N53: 1 | O53: 1 | P53: 1 | Q53: 1 | AA53: 62/46 | AN53: 59214061
A54: 75 | B54: Базовый уровень цен | C54: 2000 | D54: 0 | E54: 1 | F54: 0 | G54: 0 | H54: 1 | I54: 1 | J54: 3 | K54: 0 | L54: 0 | M54: 0 | N54: 59214062 | O54: 2
A55: 1 | B55: Сборник индексов | C55: Коэффициенты к ТСН-2001 МГЭ Дополнение 80, строительство | D55: 2000 | E55: 1 | F55: 1 | G55: 1 | H55: 0 | I55: 2 | J55: 1 | K55: 1 | L55: 1 | M55: 1 | N55: 1 | O55: 1 | P55: 1 | Q55: 1 | AA55: 0 | AN55: 59214063

Sheet SmtRes
A1: =ROW(Source!A28) -> 28 | B1: 59214062 | C1: 59214176 | D1: 58266404 | E1: 1080 | F1: 1 | G1: 1080 | H1: 1 | I1: 9999990008 | K1: Трудозатраты рабочих | L1: 1191 | N1: 1013 | O1: чел.-ч. | P1: чел.-ч. | Q1: 1 | W1: 0 | X1: 476480486 | Y1: =(AT1*1.1) -> 1.859 | AA1: 0 | AB1: 0 | AC1: 0 | AD1: 0 | AE1: 0 | AF1: 0 | AG1: 0 | AH1: 0 | AI1: 1 | AJ1: 1 | AK1: 1 | AL1: 1 | AM1: -2 | AN1: 0 | AO1: 1 | AP1: 1 | AQ1: 0 | AR1: 0 | AT1: 1.69 | AU1: *1,1 | AV1: 1 | AW1: 2 | AX1: 59214214 | AY1: 1 | AZ1: 0 | BA1: 1 | BB1: 0 | BC1: 0 | BD1: 0 | BE1: 0 | BF1: 0 | BG1: 0 | BH1: 0 | BI1: 0 | BJ1: 0 | BK1: 0 | BL1: 0 | BM1: 0 | BN1: 0 | BO1: 0 | BP1: 0 | BQ1: 0 | BR1: 0 | BS1: 0 | BT1: 0 | BU1: 0 | BV1: 0 | BW1: 0 | CU1: =ROUND(AT1*Source!I28*AH1*AL1,2) -> 0 | CV1: =ROUND(Y1*Source!I28,9) -> 3.718 | CW1: 0 | CX1: =ROUND(Y1*Source!I28,9) -> 3.718 | CY1: =AD1 -> 0 | CZ1: =AH1 -> 0 | DA1: =AL1 -> 1 | DB1: =ROUND((ROUND(AT1*CZ1,2)*1.1),6) -> 0 | DC1: =ROUND((ROUND(AT1*AG1,2)*1.1),6) -> 0 | DF1: =ROUND(ROUND(AE1,2)*CX1,2) -> 0 | DG1: =ROUND(ROUND(AF1,2)*CX1,2) -> 0 | DH1: =ROUND(ROUND(AG1,2)*CX1,2) -> 0 | DI1: =ROUND(ROUND(AH1,2)*CX1,2) -> 0 | DJ1: =DI1 -> 0 | DK1: 0 | DM1: 0 | DO1: 0
A2: =ROW(Source!A28) -> 28 | B2: 59214062 | C2: 59214176 | D2: 58340700 | E2: 1 | F2: 1 | G2: 1080 | H2: 2 | I2: 2.1-30-106 | J2: ТСН-2001.2. Доп. 68. п.1-30-106 (304105) | K2: Перфораторы, мощность до 1,5 кВт | L2: 1368 | N2: 1011 | O2: маш.-ч | P2: маш.-ч | Q2: 1 | W2: 0 | X2: -947993098 | Y2: =(AT2*1.1) -> 0.308 | AA2: 0 | AB2: 1.53 | AC2: 0 | AD2: 0 | AE2: 0 | AF2: 1.43 | AG2: 0 | AH2: 0 | AI2: 1 | AJ2: 1 | AK2: 1 | AL2: 1 | AM2: -2 | AN2: 0 | AO2: 1 | AP2: 1 | AQ2: 0 | AR2: 0 | AT2: 0.28 | AU2: *1,1 | AV2: 0 | AW2: 2 | AX2: 59214215 | AY2: 1 | AZ2: 0 | BA2: 2 | BB2: 0 | BC2: 0 | BD2: 0 | BE2: 0 | BF2: 0 | BG2: 0 | BH2: 0 | BI2: 0 | BJ2: 0 | BK2: 0 | BL2: 0 | BM2: 0 | BN2: 0 | BO2: 0 | BP2: 0 | BQ2: 0 | BR2: 0 | BS2: 0 | BT2: 0 | BU2: 0 | BV2: 0 | BW2: 0 | CV2: 0 | CW2: =ROUND(Y2*Source!I28*DO2,9) -> 0 | CX2: =ROUND(Y2*Source!I28,9) -> 0.616 | CY2: =AB2 -> 1.53 | CZ2: =AF2 -> 1.43 | DA2: =AJ2 -> 1 | DB2: =ROUND((ROUND(AT2*CZ2,2)*1.1),6) -> 0.44 | DC2: =ROUND((ROUND(AT2*AG2,2)*1.1),6) -> 0 | DF2: =ROUND(ROUND(AE2,2)*CX2,2) -> 0 | DG2: =ROUND(ROUND(AF2,2)*CX2,2) -> 0.88 | DH2: =ROUND(ROUND(AG2,2)*CX2,2) -> 0 | DI2: =ROUND(ROUND(AH2,2)*CX2,2) -> 0 | DJ2: =DG2 -> 0.88 | DK2: 0 | DM2: 0 | DO2: 0
A3: =ROW(Source!A28) -> 28 | B3: 59214062 | C3: 59214176 | D3: 58340663 | E3: 1 | F3: 1 | G3: 1080 | H3: 2 | I3: 2.1-30-56 | J3: ТСН-2001.2. Доп. 68. п.1-30-56 (309101) | K3: Шуруповерты | L3: 1368 | N3: 1011 | O3: маш.-ч | P3: маш.-ч | Q3: 1 | W3: 0 | X3: 1645565003 | Y3: =(AT3*1.1) -> 0.253 | AA3: 0 | AB3: 0.5 | AC3: 0 | AD3: 0 | AE3: 0 | AF3: 0.47 | AG3: 0 | AH3: 0 | AI3: 1 | AJ3: 1 | AK3: 1 | AL3: 1 | AM3: -2 | AN3: 0 | AO3: 1 | AP3: 1 | AQ3: 0 | AR3: 0 | AT3: 0.23 | AU3: *1,1 | AV3: 0 | AW3: 2 | AX3: 59214216 | AY3: 1 | AZ3: 0 | BA3: 3 | BB3: 0 | BC3: 0 | BD3: 0 | BE3: 0 | BF3: 0 | BG3: 0 | BH3: 0 | BI3: 0 | BJ3: 0 | BK3: 0 | BL3: 0 | BM3: 0 | BN3: 0 | BO3: 0 | BP3: 0 | BQ3: 0 | BR3: 0 | BS3: 0 | BT3: 0 | BU3: 0 | BV3: 0 | BW3: 0 | CV3: 0 | CW3: =ROUND(Y3*Source!I28*DO3,9) -> 0 | CX3: =ROUND(Y3*Source!I28,9) -> 0.506 | CY3: =AB3 -> 0.5 | CZ3: =AF3 -> 0.47 | DA3: =AJ3 -> 1 | DB3: =ROUND((ROUND(AT3*CZ3,2)*1.1),6) -> 0.121 | DC3: =ROUND((ROUND(AT3*AG3,2)*1.1),6) -> 0 | DF3: =ROUND(ROUND(AE3,2)*CX3,2) -> 0 | DG3: =ROUND(ROUND(AF3,2)*CX3,2) -> 0.24 | DH3: =ROUND(ROUND(AG3,2)*CX3,2) -> 0 | DI3: =ROUND(ROUND(AH3,2)*CX3,2) -> 0 | DJ3: =DG3 -> 0.24 | DK3: 0 | DM3: 0 | DO3: 0
A4: =ROW(Source!A29) -> 29 | B4: 59214059 | C4: 59214176 | D4: 58266404 | E4: 1080 | F4: 1 | G4: 1080 | H4: 1 | I4: 9999990008 | K4: Трудозатраты рабочих | L4: 1191 | N4: 1013 | O4: чел.-ч. | P4: чел.-ч. | Q4: 1 | W4: 0 | X4: 476480486 | Y4: =(AT4*1.1) -> 1.859 | AA4: 0 | AB4: 0 | AC4: 0 | AD4: 0 | AE4: 0 | AF4: 0 | AG4: 0 | AH4: 0 | AI4: 1 | AJ4: 1 | AK4: 1 | AL4: 1 | AM4: 5 | AN4: 0 | AO4: 1 | AP4: 1 | AQ4: 0 | AR4: 0 | AT4: 1.69 | AU4: *1,1 | AV4: 1 | AW4: 2 | AX4: 59214214 | AY4: 1 | AZ4: 0 | BA4: 5 | BB4: 0 | BC4: 0 | BD4: 0 | BE4: 0 | BF4: 0 | BG4: 0 | BH4: 0 | BI4: 0 | BJ4: 0 | BK4: 0 | BL4: 0 | BM4: 0 | BN4: 0 | BO4: 0 | BP4: 0 | BQ4: 0 | BR4: 0 | BS4: 0 | BT4: 0 | BU4: 0 | BV4: 0 | BW4: 0 | CU4: =ROUND(AT4*Source!I29*AH4*AL4,2) -> 0 | CV4: =ROUND(Y4*Source!I29,9) -> 3.718 | CW4: 0 | CX4: =ROUND(Y4*Source!I29,9) -> 3.718 | CY4: =AD4 -> 0 | CZ4: =AH4 -> 0 | DA4: =AL4 -> 1 | DB4: =ROUND((ROUND(AT4*CZ4,2)*1.1),6) -> 0 | DC4: =ROUND((ROUND(AT4*AG4,2)*1.1),6) -> 0 | DF4: =ROUND(ROUND(AE4,2)*CX4,2) -> 0 | DG4: =ROUND(ROUND(AF4,2)*CX4,2) -> 0 | DH4: =ROUND(ROUND(AG4,2)*CX4,2) -> 0 | DI4: =ROUND(ROUND(AH4,2)*CX4,2) -> 0 | DJ4: =DI4 -> 0 | DK4: 0 | DM4: 0 | DO4: 0
A5: =ROW(Source!A29) -> 29 | B5: 59214059 | C5: 59214176 | D5: 58340700 | E5: 1 | F5: 1 | G5: 1080 | H5: 2 | I5: 2.1-30-106 | J5: ТСН-2001.2. Доп. 68. п.1-30-106 (304105) | K5: Перфораторы, мощность до 1,5 кВт | L5: 1368 | N5: 1011 | O5: маш.-ч | P5: маш.-ч | Q5: 1 | W5: 0 | X5: -947993098 | Y5: =(AT5*1.1) -> 0.308 | AA5: 0 | AB5: 13.15 | AC5: 0 | AD5: 0 | AE5: 0 | AF5: 1.43 | AG5: 0 | AH5: 0 | AI5: 1 | AJ5: 8.62 | AK5: 54.99 | AL5: 1 | AM5: 2 | AN5: 0 | AO5: 1 | AP5: 1 | AQ5: 0 | AR5: 0 | AT5: 0.28 | AU5: *1,1 | AV5: 0 | AW5: 2 | AX5: 59214215 | AY5: 1 | AZ5: 0 | BA5: 6 | BB5: 0 | BC5: 0 | BD5: 0 | BE5: 0 | BF5: 0 | BG5: 0 | BH5: 0 | BI5: 0 | BJ5: 0 | BK5: 0 | BL5: 0 | BM5: 0 | BN5: 0 | BO5: 0 | BP5: 0 | BQ5: 0 | BR5: 0 | BS5: 0 | BT5: 0 | BU5: 0 | BV5: 0 | BW5: 0 | CV5: 0 | CW5: =ROUND(Y5*Source!I29*DO5,9) -> 0 | CX5: =ROUND(Y5*Source!I29,9) -> 0.616 | CY5: =AB5 -> 13.15 | CZ5: =AF5 -> 1.43 | DA5: =AJ5 -> 8.62 | DB5: =ROUND((ROUND(AT5*CZ5,2)*1.1),6) -> 0.44 | DC5: =ROUND((ROUND(AT5*AG5,2)*1.1),6) -> 0 | DF5: =ROUND(ROUND(AE5,2)*CX5,2) -> 0 | DG5: =ROUND(ROUND(AF5*AJ5,2)*CX5,2) -> 7.6 | DH5: =ROUND(ROUND(AG5*AK5,2)*CX5,2) -> 0 | DI5: =ROUND(ROUND(AH5,2)*CX5,2) -> 0 | DJ5: =DG5 -> 7.6 | DK5: 0 | DM5: 0 | DO5: 0
A6: =ROW(Source!A29) -> 29 | B6: 59214059 | C6: 59214176 | D6: 58340663 | E6: 1 | F6: 1 | G6: 1080 | H6: 2 | I6: 2.1-30-56 | J6: ТСН-2001.2. Доп. 68. п.1-30-56 (309101) | K6: Шуруповерты | L6: 1368 | N6: 1011 | O6: маш.-ч | P6: маш.-ч | Q6: 1 | W6: 0 | X6: 1645565003 | Y6: =(AT6*1.1) -> 0.253 | AA6: 0 | AB6: 4.38 | AC6: 0 | AD6: 0 | AE6: 0 | AF6: 0.47 | AG6: 0 | AH6: 0 | AI6: 1 | AJ6: 8.74 | AK6: 54.99 | AL6: 1 | AM6: 2 | AN6: 0 | AO6: 1 | AP6: 1 | AQ6: 0 | AR6: 0 | AT6: 0.23 | AU6: *1,1 | AV6: 0 | AW6: 2 | AX6: 59214216 | AY6: 1 | AZ6: 0 | BA6: 7 | BB6: 0 | BC6: 0 | BD6: 0 | BE6: 0 | BF6: 0 | BG6: 0 | BH6: 0 | BI6: 0 | BJ6: 0 | BK6: 0 | BL6: 0 | BM6: 0 | BN6: 0 | BO6: 0 | BP6: 0 | BQ6: 0 | BR6: 0 | BS6: 0 | BT6: 0 | BU6: 0 | BV6: 0 | BW6: 0 | CV6: 0 | CW6: =ROUND(Y6*Source!I29*DO6,9) -> 0 | CX6: =ROUND(Y6*Source!I29,9) -> 0.506 | CY6: =AB6 -> 4.38 | CZ6: =AF6 -> 0.47 | DA6: =AJ6 -> 8.74 | DB6: =ROUND((ROUND(AT6*CZ6,2)*1.1),6) -> 0.121 | DC6: =ROUND((ROUND(AT6*AG6,2)*1.1),6) -> 0 | DF6: =ROUND(ROUND(AE6,2)*CX6,2) -> 0 | DG6: =ROUND(ROUND(AF6*AJ6,2)*CX6,2) -> 2.08 | DH6: =ROUND(ROUND(AG6*AK6,2)*CX6,2) -> 0 | DI6: =ROUND(ROUND(AH6,2)*CX6,2) -> 0 | DJ6: =DG6 -> 2.08 | DK6: 0 | DM6: 0 | DO6: 0
A7: =ROW(Source!A40) -> 40 | B7: 59214062 | C7: 59214189 | D7: 58266404 | E7: 1080 | F7: 1 | G7: 1080 | H7: 1 | I7: 9999990008 | K7: Трудозатраты рабочих | L7: 1191 | N7: 1013 | O7: чел.-ч. | P7: чел.-ч. | Q7: 1 | W7: 0 | X7: 476480486 | Y7: =(AT7*1.1) -> 74.47 | AA7: 0 | AB7: 0 | AC7: 0 | AD7: 0 | AE7: 0 | AF7: 0 | AG7: 0 | AH7: 0 | AI7: 1 | AJ7: 1 | AK7: 1 | AL7: 1 | AM7: -2 | AN7: 0 | AO7: 1 | AP7: 1 | AQ7: 0 | AR7: 0 | AT7: 67.7 | AU7: *1,1 | AV7: 1 | AW7: 2 | AX7: 59214218 | AY7: 1 | AZ7: 0 | BA7: 9 | BB7: 0 | BC7: 0 | BD7: 0 | BE7: 0 | BF7: 0 | BG7: 0 | BH7: 0 | BI7: 0 | BJ7: 0 | BK7: 0 | BL7: 0 | BM7: 0 | BN7: 0 | BO7: 0 | BP7: 0 | BQ7: 0 | BR7: 0 | BS7: 0 | BT7: 0 | BU7: 0 | BV7: 0 | BW7: 0 | CU7: =ROUND(AT7*Source!I40*AH7*AL7,2) -> 0 | CV7: =ROUND(Y7*Source!I40,9) -> 2.9788 | CW7: 0 | CX7: =ROUND(Y7*Source!I40,9) -> 2.9788 | CY7: =AD7 -> 0 | CZ7: =AH7 -> 0 | DA7: =AL7 -> 1 | DB7: =ROUND((ROUND(AT7*CZ7,2)*1.1),6) -> 0 | DC7: =ROUND((ROUND(AT7*AG7,2)*1.1),6) -> 0 | DF7: =ROUND(ROUND(AE7,2)*CX7,2) -> 0 | DG7: =ROUND(ROUND(AF7,2)*CX7,2) -> 0 | DH7: =ROUND(ROUND(AG7,2)*CX7,2) -> 0 | DI7: =ROUND(ROUND(AH7,2)*CX7,2) -> 0 | DJ7: =DI7 -> 0 | DK7: 0 | DM7: 0 | DO7: 0
A8: =ROW(Source!A40) -> 40 | B8: 59214062 | C8: 59214189 | D8: 58340578 | E8: 1 | F8: 1 | G8: 1080 | H8: 2 | I8: 2.1-18-7 | J8: ТСН-2001.2. Доп. 68. п.1-18-7 (183001) | K8: Автомобили грузовые бортовые, грузоподъемность до 5 т | L8: 1368 | N8: 1011 | O8: маш.-ч | P8: маш.-ч | Q8: 1 | W8: 0 | X8: -1985943078 | Y8: =(AT8*1.1) -> 2.717 | AA8: 0 | AB8: 87.01 | AC8: 13.21 | AD8: 0 | AE8: 0 | AF8: 83.1 | AG8: 12.62 | AH8: 0 | AI8: 1 | AJ8: 1 | AK8: 1 | AL8: 1 | AM8: -2 | AN8: 0 | AO8: 1 | AP8: 1 | AQ8: 0 | AR8: 0 | AT8: 2.47 | AU8: *1,1 | AV8: 0 | AW8: 2 | AX8: 59214219 | AY8: 1 | AZ8: 0 | BA8: 10 | BB8: 0 | BC8: 0 | BD8: 0 | BE8: 0 | BF8: 0 | BG8: 0 | BH8: 0 | BI8: 0 | BJ8: 0 | BK8: 0 | BL8: 0 | BM8: 0 | BN8: 0 | BO8: 0 | BP8: 0 | BQ8: 0 | BR8: 0 | BS8: 0 | BT8: 0 | BU8: 0 | BV8: 0 | BW8: 0 | CV8: 0 | CW8: =ROUND(Y8*Source!I40*DO8,9) -> 1.3715416 | CX8: =ROUND(Y8*Source!I40,9) -> 0.10868 | CY8: =AB8 -> 87.01 | CZ8: =AF8 -> 83.1 | DA8: =AJ8 -> 1 | DB8: =ROUND((ROUND(AT8*CZ8,2)*1.1),6) -> 225.786 | DC8: =ROUND((ROUND(AT8*AG8,2)*1.1),6) -> 34.287 | DF8: =ROUND(ROUND(AE8,2)*CX8,2) -> 0 | DG8: =ROUND(ROUND(AF8,2)*CX8,2) -> 9.03 | DH8: =ROUND(ROUND(AG8,2)*CX8,2) -> 1.37 | DI8: =ROUND(ROUND(AH8,2)*CX8,2) -> 0 | DJ8: =DG8 -> 9.03 | DK8: 0 | DL8: 9999990009 | DM8: 0 | DN8: чел.-ч. | DO8: 12.62
A9: =ROW(Source!A40) -> 40 | B9: 59214062 | C9: 59214189 | D9: 58308826 | E9: 1 | F9: 1 | G9: 1080 | H9: 3 | I9: 1.1-1-132 | J9: ТСН-2001.1 Доп. 79, Р. 1, о. 1, поз. 132 | K9: Гвозди строительные | L9: 1348 | N9: 1009 | O9: т | P9: т | Q9: 1000 | W9: 0 | X9: -1489740832 | Y9: =AT9 -> 0.012 | AA9: 6512.79 | AB9: 0 | AC9: 0 | AD9: 0 | AE9: 6512.79 | AF9: 0 | AG9: 0 | AH9: 0 | AI9: 1 | AJ9: 1 | AK9: 1 | AL9: 1 | AM9: -2 | AN9: 0 | AO9: 1 | AP9: 1 | AQ9: 0 | AR9: 0 | AT9: 0.012 | AV9: 0 | AW9: 2 | AX9: 59214220 | AY9: 1 | AZ9: 0 | BA9: 11 | BB9: 0 | BC9: 0 | BD9: 0 | BE9: 0 | BF9: 0 | BG9: 0 | BH9: 0 | BI9: 0 | BJ9: 0 | BK9: 0 | BL9: 0 | BM9: 0 | BN9: 0 | BO9: 0 | BP9: 0 | BQ9: 0 | BR9: 0 | BS9: 0 | BT9: 0 | BU9: 0 | BV9: 0 | BW9: 0 | CV9: 0 | CW9: 0 | CX9: =ROUND(Y9*Source!I40,9) -> 0.00048 | CY9: =AA9 -> 6512.79 | CZ9: =AE9 -> 6512.79 | DA9: =AI9 -> 1 | DB9: =ROUND(ROUND(AT9*CZ9,2),6) -> 78.15 | DC9: =ROUND(ROUND(AT9*AG9,2),6) -> 0 | DF9: =ROUND(ROUND(AE9,2)*CX9,2) -> 3.13 | DG9: =ROUND(ROUND(AF9,2)*CX9,2) -> 0 | DH9: =ROUND(ROUND(AG9,2)*CX9,2) -> 0 | DI9: =ROUND(ROUND(AH9,2)*CX9,2) -> 0 | DJ9: =DF9 -> 3.13 | DK9: 0 | DM9: 0 | DO9: 0
A10: =ROW(Source!A40) -> 40 | B10: 59214062 | C10: 59214189 | D10: 58309357 | E10: 1 | F10: 1 | G10: 1080 | H10: 3 | I10: 1.1-1-924 | J10: ТСН-2001.1 Доп. 79, Р. 1, о. 1, поз. 924 | K10: Поковки строительные (скобы, закрепы, хомуты) простые, масса от 2,5 до 4 кг | L10: 1348 | N10: 1009 | O10: т | P10: т | Q10: 1000 | W10: 0 | X10: -1458073705 | Y10: =AT10 -> 0.035 | AA10: 6860.76 | AB10: 0 | AC10: 0 | AD10: 0 | AE10: 6860.76 | AF10: 0 | AG10: 0 | AH10: 0 | AI10: 1 | AJ10: 1 | AK10: 1 | AL10: 1 | AM10: -2 | AN10: 0 | AO10: 1 | AP10: 1 | AQ10: 0 | AR10: 0 | AT10: 0.035 | AV10: 0 | AW10: 2 | AX10: 59214221 | AY10: 1 | AZ10: 0 | BA10: 12 | BB10: 0 | BC10: 0 | BD10: 0 | BE10: 0 | BF10: 0 | BG10: 0 | BH10: 0 | BI10: 0 | BJ10: 0 | BK10: 0 | BL10: 0 | BM10: 0 | BN10: 0 | BO10: 0 | BP10: 0 | BQ10: 0 | BR10: 0 | BS10: 0 | BT10: 0 | BU10: 0 | BV10: 0 | BW10: 0 | CV10: 0 | CW10: 0 | CX10: =ROUND(Y10*Source!I40,9) -> 0.0014 | CY10: =AA10 -> 6860.76 | CZ10: =AE10 -> 6860.76 | DA10: =AI10 -> 1 | DB10: =ROUND(ROUND(AT10*CZ10,2),6) -> 240.13 | DC10: =ROUND(ROUND(AT10*AG10,2),6) -> 0 | DF10: =ROUND(ROUND(AE10,2)*CX10,2) -> 9.61 | DG10: =ROUND(ROUND(AF10,2)*CX10,2) -> 0 | DH10: =ROUND(ROUND(AG10,2)*CX10,2) -> 0 | DI10: =ROUND(ROUND(AH10,2)*CX10,2) -> 0 | DJ10: =DF10 -> 9.61 | DK10: 0 | DM10: 0 | DO10: 0
A11: =ROW(Source!A41) -> 41 | B11: 59214059 | C11: 59214189 | D11: 58266404 | E11: 1080 | F11: 1 | G11: 1080 | H11: 1 | I11: 9999990008 | K11: Трудозатраты рабочих | L11: 1191 | N11: 1013 | O11: чел.-ч. | P11: чел.-ч. | Q11: 1 | W11: 0 | X11: 476480486 | Y11: =(AT11*1.1) -> 74.47 | AA11: 0 | AB11: 0 | AC11: 0 | AD11: 0 | AE11: 0 | AF11: 0 | AG11: 0 | AH11: 0 | AI11: 1 | AJ11: 1 | AK11: 1 | AL11: 1 | AM11: 5 | AN11: 0 | AO11: 1 | AP11: 1 | AQ11: 0 | AR11: 0 | AT11: 67.7 | AU11: *1,1 | AV11: 1 | AW11: 2 | AX11: 59214218 | AY11: 1 | AZ11: 0 | BA11: 15 | BB11: 0 | BC11: 0 | BD11: 0 | BE11: 0 | BF11: 0 | BG11: 0 | BH11: 0 | BI11: 0 | BJ11: 0 | BK11: 0 | BL11: 0 | BM11: 0 | BN11: 0 | BO11: 0 | BP11: 0 | BQ11: 0 | BR11: 0 | BS11: 0 | BT11: 0 | BU11: 0 | BV11: 0 | BW11: 0 | CU11: =ROUND(AT11*Source!I41*AH11*AL11,2) -> 0 | CV11: =ROUND(Y11*Source!I41,9) -> 2.9788 | CW11: 0 | CX11: =ROUND(Y11*Source!I41,9) -> 2.9788 | CY11: =AD11 -> 0 | CZ11: =AH11 -> 0 | DA11: =AL11 -> 1 | DB11: =ROUND((ROUND(AT11*CZ11,2)*1.1),6) -> 0 | DC11: =ROUND((ROUND(AT11*AG11,2)*1.1),6) -> 0 | DF11: =ROUND(ROUND(AE11,2)*CX11,2) -> 0 | DG11: =ROUND(ROUND(AF11,2)*CX11,2) -> 0 | DH11: =ROUND(ROUND(AG11,2)*CX11,2) -> 0 | DI11: =ROUND(ROUND(AH11,2)*CX11,2) -> 0 | DJ11: =DI11 -> 0 | DK11: 0 | DM11: 0 | DO11: 0
A12: =ROW(Source!A41) -> 41 | B12: 59214059 | C12: 59214189 | D12: 58340578 | E12: 1 | F12: 1 | G12: 1080 | H12: 2 | I12: 2.1-18-7 | J12: ТСН-2001.2. Доп. 68. п.1-18-7 (183001) | K12: Автомобили грузовые бортовые, грузоподъемность до 5 т | L12: 1368 | N12: 1011 | O12: маш.-ч | P12: маш.-ч | Q12: 1 | W12: 0 | X12: -1985943078 | Y12: =(AT12*1.1) -> 2.717 | AA12: 0 | AB12: 1418.19 | AC12: 726.59 | AD12: 0 | AE12: 0 | AF12: 83.1 | AG12: 12.62 | AH12: 0 | AI12: 1 | AJ12: 16.3 | AK12: 54.99 | AL12: 1 | AM12: 2 | AN12: 0 | AO12: 1 | AP12: 1 | AQ12: 0 | AR12: 0 | AT12: 2.47 | AU12: *1,1 | AV12: 0 | AW12: 2 | AX12: 59214219 | AY12: 1 | AZ12: 0 | BA12: 16 | BB12: 0 | BC12: 0 | BD12: 0 | BE12: 0 | BF12: 0 | BG12: 0 | BH12: 0 | BI12: 0 | BJ12: 0 | BK12: 0 | BL12: 0 | BM12: 0 | BN12: 0 | BO12: 0 | BP12: 0 | BQ12: 0 | BR12: 0 | BS12: 0 | BT12: 0 | BU12: 0 | BV12: 0 | BW12: 0 | CV12: 0 | CW12: =ROUND(Y12*Source!I41*DO12,9) -> 1.3715416 | CX12: =ROUND(Y12*Source!I41,9) -> 0.10868 | CY12: =AB12 -> 1418.19 | CZ12: =AF12 -> 83.1 | DA12: =AJ12 -> 16.3 | DB12: =ROUND((ROUND(AT12*CZ12,2)*1.1),6) -> 225.786 | DC12: =ROUND((ROUND(AT12*AG12,2)*1.1),6) -> 34.287 | DF12: =ROUND(ROUND(AE12,2)*CX12,2) -> 0 | DG12: =ROUND(ROUND(AF12*AJ12,2)*CX12,2) -> 147.21 | DH12: =ROUND(ROUND(AG12*AK12,2)*CX12,2) -> 75.42 | DI12: =ROUND(ROUND(AH12,2)*CX12,2) -> 0 | DJ12: =DG12 -> 147.21 | DK12: 0 | DL12: 9999990009 | DM12: 0 | DN12: чел.-ч. | DO12: 12.62
A13: =ROW(Source!A41) -> 41 | B13: 59214059 | C13: 59214189 | D13: 58308826 | E13: 1 | F13: 1 | G13: 1080 | H13: 3 | I13: 1.1-1-132 | J13: ТСН-2001.1 Доп. 79, Р. 1, о. 1, поз. 132 | K13: Гвозди строительные | L13: 1348 | N13: 1009 | O13: т | P13: т | Q13: 1000 | W13: 0 | X13: -1489740832 | Y13: =AT13 -> 0.012 | AA13: 81865.77 | AB13: 0 | AC13: 0 | AD13: 0 | AE13: 6512.79 | AF13: 0 | AG13: 0 | AH13: 0 | AI13: 12.57 | AJ13: 1 | AK13: 1 | AL13: 1 | AM13: 2 | AN13: 0 | AO13: 1 | AP13: 1 | AQ13: 0 | AR13: 0 | AT13: 0.012 | AV13: 0 | AW13: 2 | AX13: 59214220 | AY13: 1 | AZ13: 0 | BA13: 17 | BB13: 0 | BC13: 0 | BD13: 0 | BE13: 0 | BF13: 0 | BG13: 0 | BH13: 0 | BI13: 0 | BJ13: 0 | BK13: 0 | BL13: 0 | BM13: 0 | BN13: 0 | BO13: 0 | BP13: 0 | BQ13: 0 | BR13: 0 | BS13: 0 | BT13: 0 | BU13: 0 | BV13: 0 | BW13: 0 | CV13: 0 | CW13: 0 | CX13: =ROUND(Y13*Source!I41,9) -> 0.00048 | CY13: =AA13 -> 81865.77 | CZ13: =AE13 -> 6512.79 | DA13: =AI13 -> 12.57 | DB13: =ROUND(ROUND(AT13*CZ13,2),6) -> 78.15 | DC13: =ROUND(ROUND(AT13*AG13,2),6) -> 0 | DF13: =ROUND(ROUND(AE13*AI13,2)*CX13,2) -> 39.3 | DG13: =ROUND(ROUND(AF13,2)*CX13,2) -> 0 | DH13: =ROUND(ROUND(AG13,2)*CX13,2) -> 0 | DI13: =ROUND(ROUND(AH13,2)*CX13,2) -> 0 | DJ13: =DF13 -> 39.3 | DK13: 0 | DM13: 0 | DO13: 0
A14: =ROW(Source!A41) -> 41 | B14: 59214059 | C14: 59214189 | D14: 58309357 | E14: 1 | F14: 1 | G14: 1080 | H14: 3 | I14: 1.1-1-924 | J14: ТСН-2001.1 Доп. 79, Р. 1, о. 1, поз. 924 | K14: Поковки строительные (скобы, закрепы, хомуты) простые, масса от 2,5 до 4 кг | L14: 1348 | N14: 1009 | O14: т | P14: т | Q14: 1000 | W14: 0 | X14: -1458073705 | Y14: =AT14 -> 0.035 | AA14: 54748.86 | AB14: 0 | AC14: 0 | AD14: 0 | AE14: 6860.76 | AF14: 0 | AG14: 0 | AH14: 0 | AI14: 7.98 | AJ14: 1 | AK14: 1 | AL14: 1 | AM14: 2 | AN14: 0 | AO14: 1 | AP14: 1 | AQ14: 0 | AR14: 0 | AT14: 0.035 | AV14: 0 | AW14: 2 | AX14: 59214221 | AY14: 1 | AZ14: 0 | BA14: 18 | BB14: 0 | BC14: 0 | BD14: 0 | BE14: 0 | BF14: 0 | BG14: 0 | BH14: 0 | BI14: 0 | BJ14: 0 | BK14: 0 | BL14: 0 | BM14: 0 | BN14: 0 | BO14: 0 | BP14: 0 | BQ14: 0 | BR14: 0 | BS14: 0 | BT14: 0 | BU14: 0 | BV14: 0 | BW14: 0 | CV14: 0 | CW14: 0 | CX14: =ROUND(Y14*Source!I41,9) -> 0.0014 | CY14: =AA14 -> 54748.86 | CZ14: =AE14 -> 6860.76 | DA14: =AI14 -> 7.98 | DB14: =ROUND(ROUND(AT14*CZ14,2),6) -> 240.13 | DC14: =ROUND(ROUND(AT14*AG14,2),6) -> 0 | DF14: =ROUND(ROUND(AE14*AI14,2)*CX14,2) -> 76.65 | DG14: =ROUND(ROUND(AF14,2)*CX14,2) -> 0 | DH14: =ROUND(ROUND(AG14,2)*CX14,2) -> 0 | DI14: =ROUND(ROUND(AH14,2)*CX14,2) -> 0 | DJ14: =DF14 -> 76.65 | DK14: 0 | DM14: 0 | DO14: 0
A15: =ROW(Source!A44) -> 44 | B15: 59214062 | C15: 59214201 | D15: 58266404 | E15: 1080 | F15: 1 | G15: 1080 | H15: 1 | I15: 9999990008 | K15: Трудозатраты рабочих | L15: 1191 | N15: 1013 | O15: чел.-ч. | P15: чел.-ч. | Q15: 1 | W15: 0 | X15: 476480486 | Y15: =(AT15*1.1) -> 45.65 | AA15: 0 | AB15: 0 | AC15: 0 | AD15: 0 | AE15: 0 | AF15: 0 | AG15: 0 | AH15: 0 | AI15: 1 | AJ15: 1 | AK15: 1 | AL15: 1 | AM15: -2 | AN15: 0 | AO15: 1 | AP15: 1 | AQ15: 0 | AR15: 0 | AT15: 41.5 | AU15: *1,1 | AV15: 1 | AW15: 2 | AX15: 59214224 | AY15: 1 | AZ15: 0 | BA15: 21 | BB15: 0 | BC15: 0 | BD15: 0 | BE15: 0 | BF15: 0 | BG15: 0 | BH15: 0 | BI15: 0 | BJ15: 0 | BK15: 0 | BL15: 0 | BM15: 0 | BN15: 0 | BO15: 0 | BP15: 0 | BQ15: 0 | BR15: 0 | BS15: 0 | BT15: 0 | BU15: 0 | BV15: 0 | BW15: 0 | CU15: =ROUND(AT15*Source!I44*AH15*AL15,2) -> 0 | CV15: =ROUND(Y15*Source!I44,9) -> 0.913 | CW15: 0 | CX15: =ROUND(Y15*Source!I44,9) -> 0.913 | CY15: =AD15 -> 0 | CZ15: =AH15 -> 0 | DA15: =AL15 -> 1 | DB15: =ROUND((ROUND(AT15*CZ15,2)*1.1),6) -> 0 | DC15: =ROUND((ROUND(AT15*AG15,2)*1.1),6) -> 0 | DF15: =ROUND(ROUND(AE15,2)*CX15,2) -> 0 | DG15: =ROUND(ROUND(AF15,2)*CX15,2) -> 0 | DH15: =ROUND(ROUND(AG15,2)*CX15,2) -> 0 | DI15: =ROUND(ROUND(AH15,2)*CX15,2) -> 0 | DJ15: =DI15 -> 0 | DK15: 0 | DM15: 0 | DO15: 0
A16: =ROW(Source!A44) -> 44 | B16: 59214062 | C16: 59214201 | D16: 58340578 | E16: 1 | F16: 1 | G16: 1080 | H16: 2 | I16: 2.1-18-7 | J16: ТСН-2001.2. Доп. 68. п.1-18-7 (183001) | K16: Автомобили грузовые бортовые, грузоподъемность до 5 т | L16: 1368 | N16: 1011 | O16: маш.-ч | P16: маш.-ч | Q16: 1 | W16: 0 | X16: -1985943078 | Y16: =(AT16*1.1) -> 0.297 | AA16: 0 | AB16: 87.01 | AC16: 13.21 | AD16: 0 | AE16: 0 | AF16: 83.1 | AG16: 12.62 | AH16: 0 | AI16: 1 | AJ16: 1 | AK16: 1 | AL16: 1 | AM16: -2 | AN16: 0 | AO16: 1 | AP16: 1 | AQ16: 0 | AR16: 0 | AT16: 0.27 | AU16: *1,1 | AV16: 0 | AW16: 2 | AX16: 59214225 | AY16: 1 | AZ16: 0 | BA16: 22 | BB16: 0 | BC16: 0 | BD16: 0 | BE16: 0 | BF16: 0 | BG16: 0 | BH16: 0 | BI16: 0 | BJ16: 0 | BK16: 0 | BL16: 0 | BM16: 0 | BN16: 0 | BO16: 0 | BP16: 0 | BQ16: 0 | BR16: 0 | BS16: 0 | BT16: 0 | BU16: 0 | BV16: 0 | BW16: 0 | CV16: 0 | CW16: =ROUND(Y16*Source!I44*DO16,9) -> 0.0749628 | CX16: =ROUND(Y16*Source!I44,9) -> 0.00594 | CY16: =AB16 -> 87.01 | CZ16: =AF16 -> 83.1 | DA16: =AJ16 -> 1 | DB16: =ROUND((ROUND(AT16*CZ16,2)*1.1),6) -> 24.684 | DC16: =ROUND((ROUND(AT16*AG16,2)*1.1),6) -> 3.751 | DF16: =ROUND(ROUND(AE16,2)*CX16,2) -> 0 | DG16: =ROUND(ROUND(AF16,2)*CX16,2) -> 0.49 | DH16: =ROUND(ROUND(AG16,2)*CX16,2) -> 0.07 | DI16: =ROUND(ROUND(AH16,2)*CX16,2) -> 0 | DJ16: =DG16 -> 0.49 | DK16: 0 | DL16: 9999990009 | DM16: 0 | DN16: чел.-ч. | DO16: 12.62
A17: =ROW(Source!A44) -> 44 | B17: 59214062 | C17: 59214201 | D17: 58339814 | E17: 1 | F17: 1 | G17: 1080 | H17: 2 | I17: 2.1-3-38 | J17: ТСН-2001.2. Доп. 68. п.1-3-38 (032009) | K17: Краны на автомобильном ходу, грузоподъемность до 16 т | L17: 1368 | N17: 1011 | O17: маш.-ч | P17: маш.-ч | Q17: 1 | W17: 0 | X17: 1087580389 | Y17: =(AT17*1.1) -> 0.22 | AA17: 0 | AB17: 187.59 | AC17: 17.73 | AD17: 0 | AE17: 0 | AF17: 179.17 | AG17: 16.93 | AH17: 0 | AI17: 1 | AJ17: 1 | AK17: 1 | AL17: 1 | AM17: -2 | AN17: 0 | AO17: 1 | AP17: 1 | AQ17: 0 | AR17: 0 | AT17: 0.2 | AU17: *1,1 | AV17: 0 | AW17: 2 | AX17: 59214226 | AY17: 1 | AZ17: 0 | BA17: 23 | BB17: 0 | BC17: 0 | BD17: 0 | BE17: 0 | BF17: 0 | BG17: 0 | BH17: 0 | BI17: 0 | BJ17: 0 | BK17: 0 | BL17: 0 | BM17: 0 | BN17: 0 | BO17: 0 | BP17: 0 | BQ17: 0 | BR17: 0 | BS17: 0 | BT17: 0 | BU17: 0 | BV17: 0 | BW17: 0 | CV17: 0 | CW17: =ROUND(Y17*Source!I44*DO17,9) -> 0.074492 | CX17: =ROUND(Y17*Source!I44,9) -> 0.0044 | CY17: =AB17 -> 187.59 | CZ17: =AF17 -> 179.17 | DA17: =AJ17 -> 1 | DB17: =ROUND((ROUND(AT17*CZ17,2)*1.1),6) -> 39.413 | DC17: =ROUND((ROUND(AT17*AG17,2)*1.1),6) -> 3.729 | DF17: =ROUND(ROUND(AE17,2)*CX17,2) -> 0 | DG17: =ROUND(ROUND(AF17,2)*CX17,2) -> 0.79 | DH17: =ROUND(ROUND(AG17,2)*CX17,2) -> 0.07 | DI17: =ROUND(ROUND(AH17,2)*CX17,2) -> 0 | DJ17: =DG17 -> 0.79 | DK17: 0 | DL17: 9999990009 | DM17: 0 | DN17: чел.-ч. | DO17: 16.93
A18: =ROW(Source!A44) -> 44 | B18: 59214062 | C18: 59214201 | D18: 0 | E18: 1080 | F18: 1 | G18: 1080 | H18: 3 | I18: КА 5 | K18: Ограждение полуростовое BH02 PERCo | L18: 2698 | N18: 1013 | O18: м.п. | P18: м.п. | Q18: 1 | W18: 0 | X18: 1742101416 | Y18: =AT18 -> 1 | AA18: 3178.13 | AB18: 0 | AC18: 0 | AD18: 0 | AE18: 3178.13 | AF18: 0 | AG18: 0 | AH18: 0 | AI18: 1 | AJ18: 1 | AK18: 1 | AL18: 1 | AM18: 0 | AN18: 0 | AO18: 0 | AP18: 0 | AQ18: 0 | AR18: 0 | AT18: 1 | AV18: 0 | AW18: 1 | AX18: -1 | AY18: 0 | AZ18: 0 | BB18: 0 | BC18: 0 | BD18: 0 | BE18: 0 | BF18: 0 | BG18: 0 | BH18: 0 | BI18: 0 | BJ18: 0 | BK18: 0 | BL18: 0 | BM18: 0 | BN18: 0 | BO18: 0 | BP18: 0 | BQ18: 0 | BR18: 0 | BS18: 0 | BT18: 0 | BU18: 0 | BV18: 0 | BW18: 0 | CV18: 0 | CW18: 0 | CX18: =ROUND(Y18*Source!I44,9) -> 0.02 | CY18: =AA18 -> 3178.13 | CZ18: =AE18 -> 3178.13 | DA18: =AI18 -> 1 | DB18: =ROUND(ROUND(AT18*CZ18,2),6) -> 3178.13 | DC18: =ROUND(ROUND(AT18*AG18,2),6) -> 0 | DF18: =ROUND(ROUND(AE18,2)*CX18,2) -> 63.56 | DG18: =ROUND(ROUND(AF18,2)*CX18,2) -> 0 | DH18: =ROUND(ROUND(AG18,2)*CX18,2) -> 0 | DI18: =ROUND(ROUND(AH18,2)*CX18,2) -> 0 | DJ18: =DF18 -> 63.56 | DK18: 0 | DM18: 0 | DO18: 0
A19: =ROW(Source!A44) -> 44 | B19: 59214062 | C19: 59214201 | D19: 0 | E19: 1080 | F19: 1 | G19: 1080 | H19: 3 | I19: КА 6 | K19: Калитка одностворчатая PERCo | L19: 1354 | N19: 1010 | O19: шт. | P19: шт. | Q19: 1 | W19: 0 | X19: -1584551560 | Y19: =AT19 -> 1 | AA19: 9959.48 | AB19: 0 | AC19: 0 | AD19: 0 | AE19: 9959.48 | AF19: 0 | AG19: 0 | AH19: 0 | AI19: 1 | AJ19: 1 | AK19: 1 | AL19: 1 | AM19: 0 | AN19: 0 | AO19: 0 | AP19: 0 | AQ19: 0 | AR19: 0 | AT19: 1 | AV19: 0 | AW19: 1 | AX19: -1 | AY19: 0 | AZ19: 0 | BB19: 0 | BC19: 0 | BD19: 0 | BE19: 0 | BF19: 0 | BG19: 0 | BH19: 0 | BI19: 0 | BJ19: 0 | BK19: 0 | BL19: 0 | BM19: 0 | BN19: 0 | BO19: 0 | BP19: 0 | BQ19: 0 | BR19: 0 | BS19: 0 | BT19: 0 | BU19: 0 | BV19: 0 | BW19: 0 | CV19: 0 | CW19: 0 | CX19: =ROUND(Y19*Source!I44,9) -> 0.02 | CY19: =AA19 -> 9959.48 | CZ19: =AE19 -> 9959.48 | DA19: =AI19 -> 1 | DB19: =ROUND(ROUND(AT19*CZ19,2),6) -> 9959.48 | DC19: =ROUND(ROUND(AT19*AG19,2),6) -> 0 | DF19: =ROUND(ROUND(AE19,2)*CX19,2) -> 199.19 | DG19: =ROUND(ROUND(AF19,2)*CX19,2) -> 0 | DH19: =ROUND(ROUND(AG19,2)*CX19,2) -> 0 | DI19: =ROUND(ROUND(AH19,2)*CX19,2) -> 0 | DJ19: =DF19 -> 199.19 | DK19: 0 | DM19: 0 | DO19: 0
A20: =ROW(Source!A45) -> 45 | B20: 59214059 | C20: 59214201 | D20: 58266404 | E20: 1080 | F20: 1 | G20: 1080 | H20: 1 | I20: 9999990008 | K20: Трудозатраты рабочих | L20: 1191 | N20: 1013 | O20: чел.-ч. | P20: чел.-ч. | Q20: 1 | W20: 0 | X20: 476480486 | Y20: =(AT20*1.1) -> 45.65 | AA20: 0 | AB20: 0 | AC20: 0 | AD20: 0 | AE20: 0 | AF20: 0 | AG20: 0 | AH20: 0 | AI20: 1 | AJ20: 1 | AK20: 1 | AL20: 1 | AM20: 5 | AN20: 0 | AO20: 1 | AP20: 1 | AQ20: 0 | AR20: 0 | AT20: 41.5 | AU20: *1,1 | AV20: 1 | AW20: 2 | AX20: 59214224 | AY20: 1 | AZ20: 0 | BA20: 26 | BB20: 0 | BC20: 0 | BD20: 0 | BE20: 0 | BF20: 0 | BG20: 0 | BH20: 0 | BI20: 0 | BJ20: 0 | BK20: 0 | BL20: 0 | BM20: 0 | BN20: 0 | BO20: 0 | BP20: 0 | BQ20: 0 | BR20: 0 | BS20: 0 | BT20: 0 | BU20: 0 | BV20: 0 | BW20: 0 | CU20: =ROUND(AT20*Source!I45*AH20*AL20,2) -> 0 | CV20: =ROUND(Y20*Source!I45,9) -> 0.913 | CW20: 0 | CX20: =ROUND(Y20*Source!I45,9) -> 0.913 | CY20: =AD20 -> 0 | CZ20: =AH20 -> 0 | DA20: =AL20 -> 1 | DB20: =ROUND((ROUND(AT20*CZ20,2)*1.1),6) -> 0 | DC20: =ROUND((ROUND(AT20*AG20,2)*1.1),6) -> 0 | DF20: =ROUND(ROUND(AE20,2)*CX20,2) -> 0 | DG20: =ROUND(ROUND(AF20,2)*CX20,2) -> 0 | DH20: =ROUND(ROUND(AG20,2)*CX20,2) -> 0 | DI20: =ROUND(ROUND(AH20,2)*CX20,2) -> 0 | DJ20: =DI20 -> 0 | DK20: 0 | DM20: 0 | DO20: 0
A21: =ROW(Source!A45) -> 45 | B21: 59214059 | C21: 59214201 | D21: 58340578 | E21: 1 | F21: 1 | G21: 1080 | H21: 2 | I21: 2.1-18-7 | J21: ТСН-2001.2. Доп. 68. п.1-18-7 (183001) | K21: Автомобили грузовые бортовые, грузоподъемность до 5 т | L21: 1368 | N21: 1011 | O21: маш.-ч | P21: маш.-ч | Q21: 1 | W21: 0 | X21: -1985943078 | Y21: =(AT21*1.1) -> 0.297 | AA21: 0 | AB21: 1418.19 | AC21: 726.59 | AD21: 0 | AE21: 0 | AF21: 83.1 | AG21: 12.62 | AH21: 0 | AI21: 1 | AJ21: 16.3 | AK21: 54.99 | AL21: 1 | AM21: 2 | AN21: 0 | AO21: 1 | AP21: 1 | AQ21: 0 | AR21: 0 | AT21: 0.27 | AU21: *1,1 | AV21: 0 | AW21: 2 | AX21: 59214225 | AY21: 1 | AZ21: 0 | BA21: 27 | BB21: 0 | BC21: 0 | BD21: 0 | BE21: 0 | BF21: 0 | BG21: 0 | BH21: 0 | BI21: 0 | BJ21: 0 | BK21: 0 | BL21: 0 | BM21: 0 | BN21: 0 | BO21: 0 | BP21: 0 | BQ21: 0 | BR21: 0 | BS21: 0 | BT21: 0 | BU21: 0 | BV21: 0 | BW21: 0 | CV21: 0 | CW21: =ROUND(Y21*Source!I45*DO21,9) -> 0.0749628 | CX21: =ROUND(Y21*Source!I45,9) -> 0.00594 | CY21: =AB21 -> 1418.19 | CZ21: =AF21 -> 83.1 | DA21: =AJ21 -> 16.3 | DB21: =ROUND((ROUND(AT21*CZ21,2)*1.1),6) -> 24.684 | DC21: =ROUND((ROUND(AT21*AG21,2)*1.1),6) -> 3.751 | DF21: =ROUND(ROUND(AE21,2)*CX21,2) -> 0 | DG21: =ROUND(ROUND(AF21*AJ21,2)*CX21,2) -> 8.05 | DH21: =ROUND(ROUND(AG21*AK21,2)*CX21,2) -> 4.12 | DI21: =ROUND(ROUND(AH21,2)*CX21,2) -> 0 | DJ21: =DG21 -> 8.05 | DK21: 0 | DL21: 9999990009 | DM21: 0 | DN21: чел.-ч. | DO21: 12.62
A22: =ROW(Source!A45) -> 45 | B22: 59214059 | C22: 59214201 | D22: 58339814 | E22: 1 | F22: 1 | G22: 1080 | H22: 2 | I22: 2.1-3-38 | J22: ТСН-2001.2. Доп. 68. п.1-3-38 (032009) | K22: Краны на автомобильном ходу, грузоподъемность до 16 т | L22: 1368 | N22: 1011 | O22: маш.-ч | P22: маш.-ч | Q22: 1 | W22: 0 | X22: 1087580389 | Y22: =(AT22*1.1) -> 0.22 | AA22: 0 | AB22: 2579.38 | AC22: 974.74 | AD22: 0 | AE22: 0 | AF22: 179.17 | AG22: 16.93 | AH22: 0 | AI22: 1 | AJ22: 13.75 | AK22: 54.99 | AL22: 1 | AM22: 2 | AN22: 0 | AO22: 1 | AP22: 1 | AQ22: 0 | AR22: 0 | AT22: 0.2 | AU22: *1,1 | AV22: 0 | AW22: 2 | AX22: 59214226 | AY22: 1 | AZ22: 0 | BA22: 28 | BB22: 0 | BC22: 0 | BD22: 0 | BE22: 0 | BF22: 0 | BG22: 0 | BH22: 0 | BI22: 0 | BJ22: 0 | BK22: 0 | BL22: 0 | BM22: 0 | BN22: 0 | BO22: 0 | BP22: 0 | BQ22: 0 | BR22: 0 | BS22: 0 | BT22: 0 | BU22: 0 | BV22: 0 | BW22: 0 | CV22: 0 | CW22: =ROUND(Y22*Source!I45*DO22,9) -> 0.074492 | CX22: =ROUND(Y22*Source!I45,9) -> 0.0044 | CY22: =AB22 -> 2579.38 | CZ22: =AF22 -> 179.17 | DA22: =AJ22 -> 13.75 | DB22: =ROUND((ROUND(AT22*CZ22,2)*1.1),6) -> 39.413 | DC22: =ROUND((ROUND(AT22*AG22,2)*1.1),6) -> 3.729 | DF22: =ROUND(ROUND(AE22,2)*CX22,2) -> 0 | DG22: =ROUND(ROUND(AF22*AJ22,2)*CX22,2) -> 10.84 | DH22: =ROUND(ROUND(AG22*AK22,2)*CX22,2) -> 4.1 | DI22: =ROUND(ROUND(AH22,2)*CX22,2) -> 0 | DJ22: =DG22 -> 10.84 | DK22: 0 | DL22: 9999990009 | DM22: 0 | DN22: чел.-ч. | DO22: 16.93
A23: =ROW(Source!A45) -> 45 | B23: 59214059 | C23: 59214201 | D23: 0 | E23: 1080 | F23: 1 | G23: 1080 | H23: 3 | I23: КА 5 | K23: Ограждение полуростовое BH02 PERCo | L23: 2698 | N23: 1013 | O23: м.п. | P23: м.п. | Q23: 1 | W23: 0 | X23: 1742101416 | Y23: =AT23 -> 1 | AA23: 31399.92 | AB23: 0 | AC23: 0 | AD23: 0 | AE23: 3178.13 | AF23: 0 | AG23: 0 | AH23: 0 | AI23: 9.88 | AJ23: 1 | AK23: 1 | AL23: 1 | AM23: 0 | AN23: 0 | AO23: 0 | AP23: 0 | AQ23: 0 | AR23: 0 | AT23: 1 | AV23: 0 | AW23: 1 | AX23: -1 | AY23: 0 | AZ23: 0 | BB23: 0 | BC23: 0 | BD23: 0 | BE23: 0 | BF23: 0 | BG23: 0 | BH23: 0 | BI23: 0 | BJ23: 0 | BK23: 0 | BL23: 0 | BM23: 0 | BN23: 0 | BO23: 0 | BP23: 0 | BQ23: 0 | BR23: 0 | BS23: 0 | BT23: 0 | BU23: 0 | BV23: 0 | BW23: 0 | CV23: 0 | CW23: 0 | CX23: =ROUND(Y23*Source!I45,9) -> 0.02 | CY23: =AA23 -> 31399.92 | CZ23: =AE23 -> 3178.13 | DA23: =AI23 -> 9.88 | DB23: =ROUND(ROUND(AT23*CZ23,2),6) -> 3178.13 | DC23: =ROUND(ROUND(AT23*AG23,2),6) -> 0 | DF23: =ROUND(ROUND(AE23*AI23,2)*CX23,2) -> 628 | DG23: =ROUND(ROUND(AF23,2)*CX23,2) -> 0 | DH23: =ROUND(ROUND(AG23,2)*CX23,2) -> 0 | DI23: =ROUND(ROUND(AH23,2)*CX23,2) -> 0 | DJ23: =DF23 -> 628 | DK23: 0 | DM23: 0 | DO23: 0
A24: =ROW(Source!A45) -> 45 | B24: 59214059 | C24: 59214201 | D24: 0 | E24: 1080 | F24: 1 | G24: 1080 | H24: 3 | I24: КА 6 | K24: Калитка одностворчатая PERCo | L24: 1354 | N24: 1010 | O24: шт. | P24: шт. | Q24: 1 | W24: 0 | X24: -1584551560 | Y24: =AT24 -> 1 | AA24: 98399.66 | AB24: 0 | AC24: 0 | AD24: 0 | AE24: 9959.48 | AF24: 0 | AG24: 0 | AH24: 0 | AI24: 9.88 | AJ24: 1 | AK24: 1 | AL24: 1 | AM24: 0 | AN24: 0 | AO24: 0 | AP24: 0 | AQ24: 0 | AR24: 0 | AT24: 1 | AV24: 0 | AW24: 1 | AX24: -1 | AY24: 0 | AZ24: 0 | BB24: 0 | BC24: 0 | BD24: 0 | BE24: 0 | BF24: 0 | BG24: 0 | BH24: 0 | BI24: 0 | BJ24: 0 | BK24: 0 | BL24: 0 | BM24: 0 | BN24: 0 | BO24: 0 | BP24: 0 | BQ24: 0 | BR24: 0 | BS24: 0 | BT24: 0 | BU24: 0 | BV24: 0 | BW24: 0 | CV24: 0 | CW24: 0 | CX24: =ROUND(Y24*Source!I45,9) -> 0.02 | CY24: =AA24 -> 98399.66 | CZ24: =AE24 -> 9959.48 | DA24: =AI24 -> 9.88 | DB24: =ROUND(ROUND(AT24*CZ24,2),6) -> 9959.48 | DC24: =ROUND(ROUND(AT24*AG24,2),6) -> 0 | DF24: =ROUND(ROUND(AE24*AI24,2)*CX24,2) -> 1967.99 | DG24: =ROUND(ROUND(AF24,2)*CX24,2) -> 0 | DH24: =ROUND(ROUND(AG24,2)*CX24,2) -> 0 | DI24: =ROUND(ROUND(AH24,2)*CX24,2) -> 0 | DJ24: =DF24 -> 1967.99 | DK24: 0 | DM24: 0 | DO24: 0

Sheet EtalonRes
A1: =ROW(Source!A28) -> 28 | B1: 59214214 | C1: 59214176 | D1: 58266404 | E1: 1080 | F1: 1 | G1: 1080 | H1: 1 | I1: 9999990008 | K1: Трудозатраты рабочих | L1: 1191 | N1: 1013 | O1: чел.-ч. | P1: чел.-ч. | Q1: 1 | X1: 1.69 | Y1: 0 | Z1: 0 | AA1: 0 | AB1: 0 | AC1: 0 | AD1: 1 | AE1: 1 | AF1: *1,1 | AG1: 1.859 | AH1: 2 | AI1: 59214177 | AJ1: 1 | AK1: 0 | AL1: 0 | AM1: 0 | AN1: 0 | AO1: 0 | AP1: 0 | AQ1: 0 | AR1: 0
A2: =ROW(Source!A28) -> 28 | B2: 59214215 | C2: 59214176 | D2: 58340700 | E2: 1 | F2: 1 | G2: 1080 | H2: 2 | I2: 2.1-30-106 | J2: ТСН-2001.2. Доп. 68. п.1-30-106 (304105) | K2: Перфораторы, мощность до 1,5 кВт | L2: 1368 | N2: 1011 | O2: маш.-ч | P2: маш.-ч | Q2: 1 | X2: 0.28 | Y2: 0 | Z2: 1.43 | AA2: 0 | AB2: 0 | AC2: 0 | AD2: 1 | AE2: 0 | AF2: *1,1 | AG2: 0.308 | AH2: 2 | AI2: 59214178 | AJ2: 2 | AK2: 0 | AL2: 0 | AM2: 0 | AN2: 0 | AO2: 0 | AP2: 0 | AQ2: 0 | AR2: 0
A3: =ROW(Source!A28) -> 28 | B3: 59214216 | C3: 59214176 | D3: 58340663 | E3: 1 | F3: 1 | G3: 1080 | H3: 2 | I3: 2.1-30-56 | J3: ТСН-2001.2. Доп. 68. п.1-30-56 (309101) | K3: Шуруповерты | L3: 1368 | N3: 1011 | O3: маш.-ч | P3: маш.-ч | Q3: 1 | X3: 0.23 | Y3: 0 | Z3: 0.47 | AA3: 0 | AB3: 0 | AC3: 0 | AD3: 1 | AE3: 0 | AF3: *1,1 | AG3: 0.253 | AH3: 2 | AI3: 59214179 | AJ3: 3 | AK3: 0 | AL3: 0 | AM3: 0 | AN3: 0 | AO3: 0 | AP3: 0 | AQ3: 0 | AR3: 0
A4: =ROW(Source!A28) -> 28 | B4: 59214217 | C4: 59214176 | D4: 58288466 | E4: 1080 | F4: 1 | G4: 1080 | H4: 3 | I4: 4372910000 | K4: Стационарные металлодетекторы арочного типа | L4: 1391 | N4: 1013 | O4: КОМПЛЕКТ | P4: КОМПЛЕКТ | Q4: 1 | X4: 1 | Y4: 0 | Z4: 0 | AA4: 0 | AB4: 0 | AC4: 0 | AD4: 0 | AE4: 0 | AF4: *1 | AG4: 1 | AH4: 3 | AI4: -1 | AK4: 0 | AL4: 0 | AM4: 0 | AN4: 0 | AO4: 0 | AP4: 0 | AQ4: 0 | AR4: 0
A5: =ROW(Source!A29) -> 29 | B5: 59214214 | C5: 59214176 | D5: 58266404 | E5: 1080 | F5: 1 | G5: 1080 | H5: 1 | I5: 9999990008 | K5: Трудозатраты рабочих | L5: 1191 | N5: 1013 | O5: чел.-ч. | P5: чел.-ч. | Q5: 1 | X5: 1.69 | Y5: 0 | Z5: 0 | AA5: 0 | AB5: 0 | AC5: 0 | AD5: 1 | AE5: 1 | AF5: *1,1 | AG5: 1.859 | AH5: 2 | AI5: 59214177 | AJ5: 4 | AK5: 0 | AL5: 0 | AM5: 0 | AN5: 0 | AO5: 0 | AP5: 0 | AQ5: 0 | AR5: 0
A6: =ROW(Source!A29) -> 29 | B6: 59214215 | C6: 59214176 | D6: 58340700 | E6: 1 | F6: 1 | G6: 1080 | H6: 2 | I6: 2.1-30-106 | J6: ТСН-2001.2. Доп. 68. п.1-30-106 (304105) | K6: Перфораторы, мощность до 1,5 кВт | L6: 1368 | N6: 1011 | O6: маш.-ч | P6: маш.-ч | Q6: 1 | X6: 0.28 | Y6: 0 | Z6: 1.43 | AA6: 0 | AB6: 0 | AC6: 0 | AD6: 1 | AE6: 0 | AF6: *1,1 | AG6: 0.308 | AH6: 2 | AI6: 59214178 | AJ6: 5 | AK6: 0 | AL6: 0 | AM6: 0 | AN6: 0 | AO6: 0 | AP6: 0 | AQ6: 0 | AR6: 0
A7: =ROW(Source!A29) -> 29 | B7: 59214216 | C7: 59214176 | D7: 58340663 | E7: 1 | F7: 1 | G7: 1080 | H7: 2 | I7: 2.1-30-56 | J7: ТСН-2001.2. Доп. 68. п.1-30-56 (309101) | K7: Шуруповерты | L7: 1368 | N7: 1011 | O7: маш.-ч | P7: маш.-ч | Q7: 1 | X7: 0.23 | Y7: 0 | Z7: 0.47 | AA7: 0 | AB7: 0 | AC7: 0 | AD7: 1 | AE7: 0 | AF7: *1,1 | AG7: 0.253 | AH7: 2 | AI7: 59214179 | AJ7: 6 | AK7: 0 | AL7: 0 | AM7: 0 | AN7: 0 | AO7: 0 | AP7: 0 | AQ7: 0 | AR7: 0
A8: =ROW(Source!A29) -> 29 | B8: 59214217 | C8: 59214176 | D8: 58288466 | E8: 1080 | F8: 1 | G8: 1080 | H8: 3 | I8: 4372910000 | K8: Стационарные металлодетекторы арочного типа | L8: 1391 | N8: 1013 | O8: КОМПЛЕКТ | P8: КОМПЛЕКТ | Q8: 1 | X8: 1 | Y8: 0 | Z8: 0 | AA8: 0 | AB8: 0 | AC8: 0 | AD8: 0 | AE8: 0 | AF8: *1 | AG8: 1 | AH8: 3 | AI8: -1 | AK8: 0 | AL8: 0 | AM8: 0 | AN8: 0 | AO8: 0 | AP8: 0 | AQ8: 0 | AR8: 0
A9: =ROW(Source!A40) -> 40 | B9: 59214218 | C9: 59214189 | D9: 58266404 | E9: 1080 | F9: 1 | G9: 1080 | H9: 1 | I9: 9999990008 | K9: Трудозатраты рабочих | L9: 1191 | N9: 1013 | O9: чел.-ч. | P9: чел.-ч. | Q9: 1 | X9: 67.7 | Y9: 0 | Z9: 0 | AA9: 0 | AB9: 0 | AC9: 0 | AD9: 1 | AE9: 1 | AF9: *1,1 | AG9: 74.47 | AH9: 2 | AI9: 59214190 | AJ9: 7 | AK9: 0 | AL9: 0 | AM9: 0 | AN9: 0 | AO9: 0 | AP9: 0 | AQ9: 0 | AR9: 0
A10: =ROW(Source!A40) -> 40 | B10: 59214219 | C10: 59214189 | D10: 58340578 | E10: 1 | F10: 1 | G10: 1080 | H10: 2 | I10: 2.1-18-7 | J10: ТСН-2001.2. Доп. 68. п.1-18-7 (183001) | K10: Автомобили грузовые бортовые, грузоподъемность до 5 т | L10: 1368 | N10: 1011 | O10: маш.-ч | P10: маш.-ч | Q10: 1 | X10: 2.47 | Y10: 0 | Z10: 83.1 | AA10: 12.62 | AB10: 0 | AC10: 0 | AD10: 1 | AE10: 0 | AF10: *1,1 | AG10: 2.717 | AH10: 2 | AI10: 59214191 | AJ10: 8 | AK10: 0 | AL10: 0 | AM10: 0 | AN10: 0 | AO10: 0 | AP10: 0 | AQ10: 0 | AR10: 0
A11: =ROW(Source!A40) -> 40 | B11: 59214220 | C11: 59214189 | D11: 58308826 | E11: 1 | F11: 1 | G11: 1080 | H11: 3 | I11: 1.1-1-132 | J11: ТСН-2001.1 Доп. 79, Р. 1, о. 1, поз. 132 | K11: Гвозди строительные | L11: 1348 | N11: 1009 | O11: т | P11: т | Q11: 1000 | X11: 0.012 | Y11: 6512.79 | Z11: 0 | AA11: 0 | AB11: 0 | AC11: 0 | AD11: 1 | AE11: 0 | AG11: 0.012 | AH11: 2 | AI11: 59214192 | AJ11: 9 | AK11: 0 | AL11: 0 | AM11: 0 | AN11: 0 | AO11: 0 | AP11: 0 | AQ11: 0 | AR11: 0
A12: =ROW(Source!A40) -> 40 | B12: 59214221 | C12: 59214189 | D12: 58309357 | E12: 1 | F12: 1 | G12: 1080 | H12: 3 | I12: 1.1-1-924 | J12: ТСН-2001.1 Доп. 79, Р. 1, о. 1, поз. 924 | K12: Поковки строительные (скобы, закрепы, хомуты) простые, масса от 2,5 до 4 кг | L12: 1348 | N12: 1009 | O12: т | P12: т | Q12: 1000 | X12: 0.035 | Y12: 6860.76 | Z12: 0 | AA12: 0 | AB12: 0 | AC12: 0 | AD12: 1 | AE12: 0 | AG12: 0.035 | AH12: 2 | AI12: 59214193 | AJ12: 10 | AK12: 0 | AL12: 0 | AM12: 0 | AN12: 0 | AO12: 0 | AP12: 0 | AQ12: 0 | AR12: 0
A13: =ROW(Source!A40) -> 40 | B13: 59214222 | C13: 59214189 | D13: 58297874 | E13: 1080 | F13: 1 | G13: 1080 | H13: 3 | I13: 5361750000 | K13: Раскладка, размером 19х19 мм | L13: 1301 | N13: 1003 | O13: м | P13: м | Q13: 1 | X13: 400 | Y13: 0 | Z13: 0 | AA13: 0 | AB13: 0 | AC13: 0 | AD13: 0 | AE13: 0 | AG13: 400 | AH13: 3 | AI13: -1 | AK13: 0 | AL13: 0 | AM13: 0 | AN13: 0 | AO13: 0 | AP13: 0 | AQ13: 0 | AR13: 0
A14: =ROW(Source!A40) -> 40 | B14: 59214223 | C14: 59214189 | D14: 58297965 | E14: 1080 | F14: 1 | G14: 1080 | H14: 3 | I14: 5369680000 | K14: Кухонные подстолья | L14: 1354 | N14: 1010 | O14: шт. | P14: шт. | Q14: 1 | X14: 100 | Y14: 0 | Z14: 0 | AA14: 0 | AB14: 0 | AC14: 0 | AD14: 0 | AE14: 0 | AG14: 100 | AH14: 3 | AI14: -1 | AK14: 0 | AL14: 0 | AM14: 0 | AN14: 0 | AO14: 0 | AP14: 0 | AQ14: 0 | AR14: 0
A15: =ROW(Source!A41) -> 41 | B15: 59214218 | C15: 59214189 | D15: 58266404 | E15: 1080 | F15: 1 | G15: 1080 | H15: 1 | I15: 9999990008 | K15: Трудозатраты рабочих | L15: 1191 | N15: 1013 | O15: чел.-ч. | P15: чел.-ч. | Q15: 1 | X15: 67.7 | Y15: 0 | Z15: 0 | AA15: 0 | AB15: 0 | AC15: 0 | AD15: 1 | AE15: 1 | AF15: *1,1 | AG15: 74.47 | AH15: 2 | AI15: 59214190 | AJ15: 11 | AK15: 0 | AL15: 0 | AM15: 0 | AN15: 0 | AO15: 0 | AP15: 0 | AQ15: 0 | AR15: 0
A16: =ROW(Source!A41) -> 41 | B16: 59214219 | C16: 59214189 | D16: 58340578 | E16: 1 | F16: 1 | G16: 1080 | H16: 2 | I16: 2.1-18-7 | J16: ТСН-2001.2. Доп. 68. п.1-18-7 (183001) | K16: Автомобили грузовые бортовые, грузоподъемность до 5 т | L16: 1368 | N16: 1011 | O16: маш.-ч | P16: маш.-ч | Q16: 1 | X16: 2.47 | Y16: 0 | Z16: 83.1 | AA16: 12.62 | AB16: 0 | AC16: 0 | AD16: 1 | AE16: 0 | AF16: *1,1 | AG16: 2.717 | AH16: 2 | AI16: 59214191 | AJ16: 12 | AK16: 0 | AL16: 0 | AM16: 0 | AN16: 0 | AO16: 0 | AP16: 0 | AQ16: 0 | AR16: 0
A17: =ROW(Source!A41) -> 41 | B17: 59214220 | C17: 59214189 | D17: 58308826 | E17: 1 | F17: 1 | G17: 1080 | H17: 3 | I17: 1.1-1-132 | J17: ТСН-2001.1 Доп. 79, Р. 1, о. 1, поз. 132 | K17: Гвозди строительные | L17: 1348 | N17: 1009 | O17: т | P17: т | Q17: 1000 | X17: 0.012 | Y17: 6512.79 | Z17: 0 | AA17: 0 | AB17: 0 | AC17: 0 | AD17: 1 | AE17: 0 | AG17: 0.012 | AH17: 2 | AI17: 59214192 | AJ17: 13 | AK17: 0 | AL17: 0 | AM17: 0 | AN17: 0 | AO17: 0 | AP17: 0 | AQ17: 0 | AR17: 0
A18: =ROW(Source!A41) -> 41 | B18: 59214221 | C18: 59214189 | D18: 58309357 | E18: 1 | F18: 1 | G18: 1080 | H18: 3 | I18: 1.1-1-924 | J18: ТСН-2001.1 Доп. 79, Р. 1, о. 1, поз. 924 | K18: Поковки строительные (скобы, закрепы, хомуты) простые, масса от 2,5 до 4 кг | L18: 1348 | N18: 1009 | O18: т | P18: т | Q18: 1000 | X18: 0.035 | Y18: 6860.76 | Z18: 0 | AA18: 0 | AB18: 0 | AC18: 0 | AD18: 1 | AE18: 0 | AG18: 0.035 | AH18: 2 | AI18: 59214193 | AJ18: 14 | AK18: 0 | AL18: 0 | AM18: 0 | AN18: 0 | AO18: 0 | AP18: 0 | AQ18: 0 | AR18: 0
A19: =ROW(Source!A41) -> 41 | B19: 59214222 | C19: 59214189 | D19: 58297874 | E19: 1080 | F19: 1 | G19: 1080 | H19: 3 | I19: 5361750000 | K19: Раскладка, размером 19х19 мм | L19: 1301 | N19: 1003 | O19: м | P19: м | Q19: 1 | X19: 400 | Y19: 0 | Z19: 0 | AA19: 0 | AB19: 0 | AC19: 0 | AD19: 0 | AE19: 0 | AG19: 400 | AH19: 3 | AI19: -1 | AK19: 0 | AL19: 0 | AM19: 0 | AN19: 0 | AO19: 0 | AP19: 0 | AQ19: 0 | AR19: 0
A20: =ROW(Source!A41) -> 41 | B20: 59214223 | C20: 59214189 | D20: 58297965 | E20: 1080 | F20: 1 | G20: 1080 | H20: 3 | I20: 5369680000 | K20: Кухонные подстолья | L20: 1354 | N20: 1010 | O20: шт. | P20: шт. | Q20: 1 | X20: 100 | Y20: 0 | Z20: 0 | AA20: 0 | AB20: 0 | AC20: 0 | AD20: 0 | AE20: 0 | AG20: 100 | AH20: 3 | AI20: -1 | AK20: 0 | AL20: 0 | AM20: 0 | AN20: 0 | AO20: 0 | AP20: 0 | AQ20: 0 | AR20: 0
A21: =ROW(Source!A44) -> 44 | B21: 59214224 | C21: 59214201 | D21: 58266404 | E21: 1080 | F21: 1 | G21: 1080 | H21: 1 | I21: 9999990008 | K21: Трудозатраты рабочих | L21: 1191 | N21: 1013 | O21: чел.-ч. | P21: чел.-ч. | Q21: 1 | X21: 41.5 | Y21: 0 | Z21: 0 | AA21: 0 | AB21: 0 | AC21: 0 | AD21: 1 | AE21: 1 | AF21: *1,1 | AG21: 45.65 | AH21: 2 | AI21: 59214202 | AJ21: 15 | AK21: 0 | AL21: 0 | AM21: 0 | AN21: 0 | AO21: 0 | AP21: 0 | AQ21: 0 | AR21: 0
A22: =ROW(Source!A44) -> 44 | B22: 59214225 | C22: 59214201 | D22: 58340578 | E22: 1 | F22: 1 | G22: 1080 | H22: 2 | I22: 2.1-18-7 | J22: ТСН-2001.2. Доп. 68. п.1-18-7 (183001) | K22: Автомобили грузовые бортовые, грузоподъемность до 5 т | L22: 1368 | N22: 1011 | O22: маш.-ч | P22: маш.-ч | Q22: 1 | X22: 0.27 | Y22: 0 | Z22: 83.1 | AA22: 12.62 | AB22: 0 | AC22: 0 | AD22: 1 | AE22: 0 | AF22: *1,1 | AG22: 0.297 | AH22: 2 | AI22: 59214203 | AJ22: 16 | AK22: 0 | AL22: 0 | AM22: 0 | AN22: 0 | AO22: 0 | AP22: 0 | AQ22: 0 | AR22: 0
A23: =ROW(Source!A44) -> 44 | B23: 59214226 | C23: 59214201 | D23: 58339814 | E23: 1 | F23: 1 | G23: 1080 | H23: 2 | I23: 2.1-3-38 | J23: ТСН-2001.2. Доп. 68. п.1-3-38 (032009) | K23: Краны на автомобильном ходу, грузоподъемность до 16 т | L23: 1368 | N23: 1011 | O23: маш.-ч | P23: маш.-ч | Q23: 1 | X23: 0.2 | Y23: 0 | Z23: 179.17 | AA23: 16.93 | AB23: 0 | AC23: 0 | AD23: 1 | AE23: 0 | AF23: *1,1 | AG23: 0.22 | AH23: 2 | AI23: 59214204 | AJ23: 17 | AK23: 0 | AL23: 0 | AM23: 0 | AN23: 0 | AO23: 0 | AP23: 0 | AQ23: 0 | AR23: 0
A24: =ROW(Source!A44) -> 44 | B24: 59214227 | C24: 59214201 | D24: 58294107 | E24: 1080 | F24: 1 | G24: 1080 | H24: 3 | I24: 5262420000 | K24: Лестницы, косоуры, площадки, ограждения | L24: 1348 | N24: 1009 | O24: т | P24: т | Q24: 1000 | X24: 2.09 | Y24: 0 | Z24: 0 | AA24: 0 | AB24: 0 | AC24: 0 | AD24: 0 | AE24: 0 | AG24: 2.09 | AH24: 3 | AI24: -1 | AK24: 0 | AL24: 0 | AM24: 0 | AN24: 0 | AO24: 0 | AP24: 0 | AQ24: 0 | AR24: 0
A25: =ROW(Source!A44) -> 44 | B25: 59214228 | C25: 59214201 | D25: 58298817 | E25: 1080 | F25: 1 | G25: 1080 | H25: 3 | I25: 5733110000 | K25: Цемент | L25: 1348 | N25: 1009 | O25: т | P25: т | Q25: 1000 | X25: 0.15 | Y25: 0 | Z25: 0 | AA25: 0 | AB25: 0 | AC25: 0 | AD25: 0 | AE25: 0 | AG25: 0.15 | AH25: 3 | AI25: -1 | AK25: 0 | AL25: 0 | AM25: 0 | AN25: 0 | AO25: 0 | AP25: 0 | AQ25: 0 | AR25: 0
A26: =ROW(Source!A45) -> 45 | B26: 59214224 | C26: 59214201 | D26: 58266404 | E26: 1080 | F26: 1 | G26: 1080 | H26: 1 | I26: 9999990008 | K26: Трудозатраты рабочих | L26: 1191 | N26: 1013 | O26: чел.-ч. | P26: чел.-ч. | Q26: 1 | X26: 41.5 | Y26: 0 | Z26: 0 | AA26: 0 | AB26: 0 | AC26: 0 | AD26: 1 | AE26: 1 | AF26: *1,1 | AG26: 45.65 | AH26: 2 | AI26: 59214202 | AJ26: 20 | AK26: 0 | AL26: 0 | AM26: 0 | AN26: 0 | AO26: 0 | AP26: 0 | AQ26: 0 | AR26: 0
A27: =ROW(Source!A45) -> 45 | B27: 59214225 | C27: 59214201 | D27: 58340578 | E27: 1 | F27: 1 | G27: 1080 | H27: 2 | I27: 2.1-18-7 | J27: ТСН-2001.2. Доп. 68. п.1-18-7 (183001) | K27: Автомобили грузовые бортовые, грузоподъемность до 5 т | L27: 1368 | N27: 1011 | O27: маш.-ч | P27: маш.-ч | Q27: 1 | X27: 0.27 | Y27: 0 | Z27: 83.1 | AA27: 12.62 | AB27: 0 | AC27: 0 | AD27: 1 | AE27: 0 | AF27: *1,1 | AG27: 0.297 | AH27: 2 | AI27: 59214203 | AJ27: 21 | AK27: 0 | AL27: 0 | AM27: 0 | AN27: 0 | AO27: 0 | AP27: 0 | AQ27: 0 | AR27: 0
A28: =ROW(Source!A45) -> 45 | B28: 59214226 | C28: 59214201 | D28: 58339814 | E28: 1 | F28: 1 | G28: 1080 | H28: 2 | I28: 2.1-3-38 | J28: ТСН-2001.2. Доп. 68. п.1-3-38 (032009) | K28: Краны на автомобильном ходу, грузоподъемность до 16 т | L28: 1368 | N28: 1011 | O28: маш.-ч | P28: маш.-ч | Q28: 1 | X28: 0.2 | Y28: 0 | Z28: 179.17 | AA28: 16.93 | AB28: 0 | AC28: 0 | AD28: 1 | AE28: 0 | AF28: *1,1 | AG28: 0.22 | AH28: 2 | AI28: 59214204 | AJ28: 22 | AK28: 0 | AL28: 0 | AM28: 0 | AN28: 0 | AO28: 0 | AP28: 0 | AQ28: 0 | AR28: 0
A29: =ROW(Source!A45) -> 45 | B29: 59214227 | C29: 59214201 | D29: 58294107 | E29: 1080 | F29: 1 | G29: 1080 | H29: 3 | I29: 5262420000 | K29: Лестницы, косоуры, площадки, ограждения | L29: 1348 | N29: 1009 | O29: т | P29: т | Q29: 1000 | X29: 2.09 | Y29: 0 | Z29: 0 | AA29: 0 | AB29: 0 | AC29: 0 | AD29: 0 | AE29: 0 | AG29: 2.09 | AH29: 3 | AI29: -1 | AK29: 0 | AL29: 0 | AM29: 0 | AN29: 0 | AO29: 0 | AP29: 0 | AQ29: 0 | AR29: 0
A30: =ROW(Source!A45) -> 45 | B30: 59214228 | C30: 59214201 | D30: 58298817 | E30: 1080 | F30: 1 | G30: 1080 | H30: 3 | I30: 5733110000 | K30: Цемент | L30: 1348 | N30: 1009 | O30: т | P30: т | Q30: 1000 | X30: 0.15 | Y30: 0 | Z30: 0 | AA30: 0 | AB30: 0 | AC30: 0 | AD30: 0 | AE30: 0 | AG30: 0.15 | AH30: 3 | AI30: -1 | AK30: 0 | AL30: 0 | AM30: 0 | AN30: 0 | AO30: 0 | AP30: 0 | AQ30: 0 | AR30: 0

Sheet SrcPoprs
A1: 28 | B1: 1 | D1: *1 | E1: *1,1 | F1: *1,1 | G1: *1,1 | I1: *1,1 | J1: *1,1 | N1: *1 | O1: *1,1 | S1: Гл.12.Прил.8.п.8. 5_12.00.01.11.003 | T1: При наличии усложненных условий производства работ (стесненность, сложность складирования и транспортной логистики, наличие в зоне производства работ действующего технологического оборудования или движения технологического транспорта и т.п.) для объектов, расположенных за пределами территории круговой магистральной системы улиц "Садовое кольцо" и за пределами Третьего транспортного кольца города Москвы пунктов "а" и "б", но в пределах Московской кольцевой автомобильной дороги | U1: Глава 12
A2: 29 | B2: 1 | D2: *1 | E2: *1,1 | F2: *1,1 | G2: *1,1 | I2: *1,1 | J2: *1,1 | N2: *1 | O2: *1,1 | S2: Гл.12.Прил.8.п.8. 5_12.00.01.11.003 | T2: При наличии усложненных условий производства работ (стесненность, сложность складирования и транспортной логистики, наличие в зоне производства работ действующего технологического оборудования или движения технологического транспорта и т.п.) для объектов, расположенных за пределами территории круговой магистральной системы улиц "Садовое кольцо" и за пределами Третьего транспортного кольца города Москвы пунктов "а" и "б", но в пределах Московской кольцевой автомобильной дороги | U2: Глава 12
A3: 40 | B3: 1 | E3: *1,1 | F3: *1,1 | G3: *1,1 | I3: *1,1 | J3: *1,1 | O3: *1,1 | S3: О.П. п.3.4.30.в | T3: При применении территориальных сметных нормативов для города Москвы затраты, учитывающие напряженные и стесненные условия производства работ (стесненность, сложность складирования и транспортной логистики и т.п.), исчисляются с применением коэффициентов к затратам труда и заработной плате рабочих, машинистов, времени эксплуатации машин и механизмов, стоимости эксплуатации машин в размере: для объектов, расположенных за пределами Третьего транспортного кольца города Москвы, но в пределах Московской кольцевой автомобильной дороги | U3: Глава 12
A4: 41 | B4: 1 | E4: *1,1 | F4: *1,1 | G4: *1,1 | I4: *1,1 | J4: *1,1 | O4: *1,1 | S4: О.П. п.3.4.30.в | T4: При применении территориальных сметных нормативов для города Москвы затраты, учитывающие напряженные и стесненные условия производства работ (стесненность, сложность складирования и транспортной логистики и т.п.), исчисляются с применением коэффициентов к затратам труда и заработной плате рабочих, машинистов, времени эксплуатации машин и механизмов, стоимости эксплуатации машин в размере: для объектов, расположенных за пределами Третьего транспортного кольца города Москвы, но в пределах Московской кольцевой автомобильной дороги | U4: Глава 12
A5: 44 | B5: 1 | E5: *1,1 | F5: *1,1 | G5: *1,1 | I5: *1,1 | J5: *1,1 | O5: *1,1 | S5: О.П. п.3.4.30.в | T5: При применении территориальных сметных нормативов для города Москвы затраты, учитывающие напряженные и стесненные условия производства работ (стесненность, сложность складирования и транспортной логистики и т.п.), исчисляются с применением коэффициентов к затратам труда и заработной плате рабочих, машинистов, времени эксплуатации машин и механизмов, стоимости эксплуатации машин в размере: для объектов, расположенных за пределами Третьего транспортного кольца города Москвы, но в пределах Московской кольцевой автомобильной дороги | U5: Глава 12
A6: 45 | B6: 1 | E6: *1,1 | F6: *1,1 | G6: *1,1 | I6: *1,1 | J6: *1,1 | O6: *1,1 | S6: О.П. п.3.4.30.в | T6: При применении территориальных сметных нормативов для города Москвы затраты, учитывающие напряженные и стесненные условия производства работ (стесненность, сложность складирования и транспортной логистики и т.п.), исчисляются с применением коэффициентов к затратам труда и заработной плате рабочих, машинистов, времени эксплуатации машин и механизмов, стоимости эксплуатации машин в размере: для объектов, расположенных за пределами Третьего транспортного кольца города Москвы, но в пределах Московской кольцевой автомобильной дороги | U6: Глава 12

Sheet SrcKA
A1: 0 | B1: Smeta.RU (495) 974-1589 | D1: _PS_ | F1: 0 | G1: 0 | H1: 0 | I1: Smeta.RU | K1: 1 | L1: 74402 | M1: 10 | N1: 12 | O1: 0 | P1: 0 | Q1: 3
F12: =Source!F12 -> Новый объект (ТСН-2001 (Мосгосэкспертиза)) | G12: =Source!G12 -> 02-01-20 ПТА | AJ12: 0 | CY12: 0
