Workbook

Sheet 02-01-11
A1: =Source!B1 -> Smeta.RU (495) 974-1589
J2: Форма № 4б
A3: Капитальный ремонт здания Государственного бюджетного общеобразовательного учреждения города Москвы «Школа № 236» по адресу: г. Москва, ул. Клязьминская, д. 7, к. 4. I этап | AP3: Капитальный ремонт здания Государственного бюджетного общеобразовательного учреждения города Москвы «Школа № 236» по адресу: г. Москва, ул. Клязьминская, д. 7, к. 4. I этап. 02-01-11 СКТ
A4: (наименование стройки и/или объекта)
A6: =CONCATENATE( "ЛОКАЛЬНАЯ СМЕТА № ",IF(Source!F20<>"Новая локальная смета", Source!F20, "")) -> ЛОКАЛЬНАЯ СМЕТА № 02-01-11
A8: =IF(Source!G20<>"Новая локальная смета", Source!G20, "") -> Система кабельного телевидения
A9: (наименование работ и затрат)
A11: =CONCATENATE( "Основание: чертежи № ", Source!J20) -> Основание: чертежи № 2024-00272-01-0-ИОС5.4
I13: В базисном уровне цен | J13: В текущем уровне цен
E14: Сметная стоимость | I14: =I15+I16+I17+I18 -> 22.04 | J14: =J15+J16+J17+J18 -> 267.52 | K14: тыс.руб.
E15: Строительные работы | I15: =ROUND((Source!F177)/1000, 2) -> 0 | J15: =ROUND((Source!P177)/1000, 2) -> 0 | K15: тыс.руб.
E16: Работы по монтажу оборудования | I16: =ROUND((Source!F178)/1000, 2) -> 13.25 | J16: =ROUND((Source!P178)/1000, 2) -> 200.2 | K16: тыс.руб.
E17: Оборудование | I17: =ROUND((Source!F169)/1000, 2) -> 8.79 | J17: =ROUND((Source!P169)/1000, 2) -> 67.32 | K17: тыс.руб.
E18: Прочие работы и затраты | I18: =ROUND((Source!F179+Source!F180)/1000, 2) -> 0 | J18: =ROUND((Source!P179+Source!P180)/1000, 2) -> 0 | K18: тыс.руб.
E19: Средства на оплату труда | I19: =(Source!F175+ Source!F174)/1000 -> 0.79884 | J19: =((Source!P175 + Source!P174)/1000) -> 43.92823 | K19: тыс.руб.
E20: Затраты труда | I20: =Source!F182 -> 63.539123 | K20: чел.-ч.
E21: Кроме того:
E22: Возврат материалов | I22: =SUM(Y28:Y136)/1000 -> 0 | J22: =SUM(Z28:Z136)/1000 -> 0 | K22: тыс.руб.
A24: Составлен(а) по ТСН-2001 с учетом Дополнения №: 80
A25: № и период сборника коэффициентов (индексов) пересчета: Коэффициенты к ТСН-2001 МГЭ Дополнение 80, строительство №217/80 III квартал 2025 года и Коэффициенты к ТСН-2001.13-2 Дополнение 46 №62/46 III квартал 2025 года | AP25: № и период сборника коэффициентов (индексов) пересчета: Коэффициенты к ТСН-2001 МГЭ Дополнение 80, строительство №217/80 III квартал 2025 года и Коэффициенты к ТСН-2001.13-2 Дополнение 46 №62/46 III квартал 2025 года
A26: № п/п | B26: Шифр расценки и коды ресурсов | C26: Наименование работ и затрат | D26: Ед. изм. | E26: Кол-во единиц | F26: Цена на ед. изм., руб. | G26: Попра- вочные коэффи- циенты | H26: Коэффи- циенты зимних удорожа- ний | I26: Всего в ценах на январь 2000 года, руб. | J26: Коэффи- циенты (индек- сы) пере- счета, нормы НР и СП | K26: ВСЕГО затрат в текущем уровне цен, руб.
A27: 1 | B27: 2 | C27: 3 | D27: 4 | E27: 5 | F27: 6 | G27: 7 | H27: 8 | I27: 9 | J27: 10 | K27: 11
A29: =CONCATENATE("Раздел: ",IF(Source!G24<>"Новый раздел", Source!G24, "")) -> Раздел: Оборудование
A30: 1 | B30: 4.10-136-5 Поправка: Гл.12.Прил.8.п.8. 5_12.00.01.11.003 | C30: Разные устройства, монтаж базового блока головной станции настенного типа | D30: =Source!H28 -> 1 ШТ. | E30: =Source!I28 -> 1 | Q30: =Source!X28 -> 126.86 | R30: =Source!X29 -> 6976.19 | S30: =Source!Y28 -> 70.78 | T30: =Source!Y29 -> 3891.98 | U30: =ROUND((175/100)*ROUND(Source!R28, 2), 2) -> 0 | V30: =ROUND((0/100)*ROUND(Source!R29, 2), 2) -> 0 | AC30: 0
C31: ЗП | F31: =Source!AO28 -> 111.68 | G31: =Source!DG28 -> *1,1 | H31: =Source!AV29 -> 1.087 | I31: =Source!S28 -> 133.54 | J31: =IF(Source!BA29<> 0, Source!BA29, 1) -> 54.99 | K31: =Source!S29 -> 7343.36
C32: МР | F32: =Source!AL28 -> 0.29 | G32: =Source!DD28 | H32: =Source!AW29 -> 1 | I32: =Source!P28 -> 0.29 | J32: =IF(Source!BC29<> 0, Source!BC29, 1) -> 9.9 | K32: =Source!P29 -> 2.87
A33: 1,1 | B33: =Source!F30 -> КА 1 | C33: ОБОРУДОВАНИЕ:_x000D_ Головная станция СКТ "Мини-ГС" на базе оборудования VS50 Pro в шкафу с блоком розеток и автоматом 8 788,39 = [77 500 / 1,2 / 7,66] + 3% Трансп + 1,2% Заг.скл | D33: =Source!H30 -> шт. | E33: =Source!I30 -> 1 | F33: =Source!AK30 -> 8788.39 | H33: =Source!AW31 -> 1 | I33: =Source!O30 -> 8788.39 | J33: =IF(Source!BC31<> 0, Source!BC31, 1) -> 7.66 | K33: =Source!O31 -> 67319.07 | Q33: =Source!X30 -> 0 | R33: =Source!X31 -> 0 | S33: =Source!Y30 -> 0 | T33: =Source!Y31 -> 0 | U33: =ROUND((175/100)*ROUND(Source!R30, 2), 2) -> 0 | V33: =ROUND((0/100)*ROUND(Source!R31, 2), 2) -> 0 | AC33: 5
C34: НР от ФОТ | D34: % | E34: =Source!BZ29 -> 95 | I34: =SUM(Q30:Q33) -> 126.86 | J34: =Source!AT29 -> 95 | K34: =SUM(R30:R33) -> 6976.19
C35: СП от ФОТ | D35: % | E35: =Source!CA29 -> 53 | I35: =SUM(S30:S34) -> 70.78 | J35: =Source!AU29 -> 53 | K35: =SUM(T30:T34) -> 3891.98
C36: ЗТР | D36: чел-ч | E36: =Source!AQ28 -> 8 | G36: =Source!DI28 -> *1,1 | H36: =Source!AV29 -> 1.087 | I36: =Source!U28 -> 9.5656
C37: ВСЕГО работ по позиции: | H37: =I31+I32+I34+I35+SUM(I33:I33)-SUMIF(AC33:AC33, 5, I33:I33)-SUMIF(AC33:AC33, 6, I33:I33) -> 331.47 | J37: =K31+K32+K34+K35+SUM(K33:K33)-SUMIF(AC33:AC33, 5, K33:K33)-SUMIF(AC33:AC33, 6, K33:K33) -> 18214.4
C38: ВСЕГО оборудование по позиции: | H38: =SUMIF(AC33:AC33, 5, I33:I33)+SUMIF(AC33:AC33, 6, I33:I33) -> 8788.39 | J38: =SUMIF(AC33:AC33, 5, K33:K33)+SUMIF(AC33:AC33, 6, K33:K33) -> 67319.07
C39: ВСЕГО по позиции: | H39: =I31+I32+I34+I35+SUM(I33:I33) -> 9119.86 | J39: =K31+K32+K34+K35+SUM(K33:K33) -> 85533.47 | O39: =I31+I32+I34+I35+SUM(I33:I33) -> 9119.86 | P39: =K31+K32+K34+K35+SUM(K33:K33) -> 85533.47
A41: 2 | B41: 4.11-2-1 Поправка: Гл.12.Прил.8.п.8. 5_12.00.01.11.003 | C41: Установка прибора на резьбовых соединениях | D41: =Source!H32 -> 1 ШТ. | E41: =Source!I32 -> 3 | Q41: =Source!X32 -> 12.12 | R41: =Source!X33 -> 666.65 | S41: =Source!Y32 -> 6.2 | T41: =Source!Y33 -> 340.73 | U41: =ROUND((175/100)*ROUND(Source!R32, 2), 2) -> 0 | V41: =ROUND((0/100)*ROUND(Source!R33, 2), 2) -> 0 | AC41: 0
C42: ЗП | F42: =Source!AO32 -> 3.9 | G42: =Source!DG32 -> *1,1 | H42: =Source!AV33 -> 1.047 | I42: =Source!S32 -> 13.47 | J42: =IF(Source!BA33<> 0, Source!BA33, 1) -> 54.99 | K42: =Source!S33 -> 740.72
C43: МР | F43: =Source!AL32 -> 0.81 | G43: =Source!DD32 | H43: =Source!AW33 -> 1 | I43: =Source!P32 -> 2.43 | J43: =IF(Source!BC33<> 0, Source!BC33, 1) -> 8.8 | K43: =Source!P33 -> 21.38
A44: 2,1 | B44: =Source!F34 -> 1.14-1-551 | C44: Ответвитель направленный, абонентский, типа ОАТ 410 | D44: =Source!H34 -> шт. | E44: =Source!I34 -> 1 | F44: =Source!AK34 -> 39.87 | H44: =Source!AW35 -> 1 | I44: =Source!O34 -> 39.87 | J44: =IF(Source!BC35<> 0, Source!BC35, 1) -> 2.85 | K44: =Source!O35 -> 113.63 | Q44: =Source!X34 -> 0 | R44: =Source!X35 -> 0 | S44: =Source!Y34 -> 0 | T44: =Source!Y35 -> 0 | U44: =ROUND((175/100)*ROUND(Source!R34, 2), 2) -> 0 | V44: =ROUND((0/100)*ROUND(Source!R35, 2), 2) -> 0 | AC44: 3
A45: 2,2 | B45: =Source!F36 -> 1.14-1-552 | C45: Ответвитель направленный, абонентский, типа ОАТ 412 | D45: =Source!H36 -> шт. | E45: =Source!I36 -> 1 | F45: =Source!AK36 -> 40.05 | H45: =Source!AW37 -> 1 | I45: =Source!O36 -> 40.05 | J45: =IF(Source!BC37<> 0, Source!BC37, 1) -> 2.83 | K45: =Source!O37 -> 113.34 | Q45: =Source!X36 -> 0 | R45: =Source!X37 -> 0 | S45: =Source!Y36 -> 0 | T45: =Source!Y37 -> 0 | U45: =ROUND((175/100)*ROUND(Source!R36, 2), 2) -> 0 | V45: =ROUND((0/100)*ROUND(Source!R37, 2), 2) -> 0 | AC45: 3
A46: 2,3 | B46: =Source!F38 -> 1.14-1-553 | C46: Ответвитель направленный, абонентский, типа ОАТ 416 | D46: =Source!H38 -> шт. | E46: =Source!I38 -> 1 | F46: =Source!AK38 -> 40.17 | H46: =Source!AW39 -> 1 | I46: =Source!O38 -> 40.17 | J46: =IF(Source!BC39<> 0, Source!BC39, 1) -> 2.83 | K46: =Source!O39 -> 113.68 | Q46: =Source!X38 -> 0 | R46: =Source!X39 -> 0 | S46: =Source!Y38 -> 0 | T46: =Source!Y39 -> 0 | U46: =ROUND((175/100)*ROUND(Source!R38, 2), 2) -> 0 | V46: =ROUND((0/100)*ROUND(Source!R39, 2), 2) -> 0 | AC46: 3
C47: НР от ФОТ | D47: % | E47: =Source!BZ33 -> 90 | I47: =SUM(Q41:Q46) -> 12.12 | J47: =Source!AT33 -> 90 | K47: =SUM(R41:R46) -> 666.65
C48: СП от ФОТ | D48: % | E48: =Source!CA33 -> 46 | I48: =SUM(S41:S47) -> 6.2 | J48: =Source!AU33 -> 46 | K48: =SUM(T41:T47) -> 340.73
C49: ЗТР | D49: чел-ч | E49: =Source!AQ32 -> 0.3 | G49: =Source!DI32 -> *1,1 | H49: =Source!AV33 -> 1.047 | I49: =Source!U32 -> 1.03653
C50: ВСЕГО работ по позиции: | H50: =I42+I43+I47+I48+SUM(I44:I46)-SUMIF(AC44:AC46, 5, I44:I46)-SUMIF(AC44:AC46, 6, I44:I46) -> 154.31 | J50: =K42+K43+K47+K48+SUM(K44:K46)-SUMIF(AC44:AC46, 5, K44:K46)-SUMIF(AC44:AC46, 6, K44:K46) -> 2110.13
C51: ВСЕГО оборудование по позиции: | H51: =SUMIF(AC44:AC46, 5, I44:I46)+SUMIF(AC44:AC46, 6, I44:I46) -> 0 | J51: =SUMIF(AC44:AC46, 5, K44:K46)+SUMIF(AC44:AC46, 6, K44:K46) -> 0
C52: ВСЕГО по позиции: | H52: =I42+I43+I47+I48+SUM(I44:I46) -> 154.31 | J52: =K42+K43+K47+K48+SUM(K44:K46) -> 2110.13 | O52: =I42+I43+I47+I48+SUM(I44:I46) -> 154.31 | P52: =K42+K43+K47+K48+SUM(K44:K46) -> 2110.13
A55: =CONCATENATE("Итого по разделу: ",IF(Source!G41<>"Новый раздел", Source!G41, "")) -> Итого по разделу: Оборудование | H55: =SUM(O29:O54) -> 9274.17 | J55: =SUM(P29:P54) -> 87643.6
A56: Итого по ТСН-2001.16 | I56: =SUM(W29:W55) -> 0 | J56: =SUM(X29:X55) -> 0
A57: Итого возвратных сумм | I57: =SUM(Y29:Y56) -> 0 | J57: =SUM(Z29:Z56) -> 0
A59: =CONCATENATE("Раздел: ",IF(Source!G71<>"Новый раздел", Source!G71, "")) -> Раздел: Материалы
A60: 3 | B60: 4.8-243-11 Поправка: Гл.12.Прил.8.п.8. 5_12.00.01.11.003 | C60: Монтаж розетки штепсельной трехполюсной | D60: =Source!H75 -> 100 шт. | E60: =Source!I75 -> 0.05 | Q60: =Source!X75 -> 48.96 | R60: =Source!X76 -> 2692.09 | S60: =Source!Y75 -> 25.74 | T60: =Source!Y76 -> 1415.43 | U60: =ROUND((175/100)*ROUND(Source!R75, 2), 2) -> 0.14 | V60: =ROUND((0/100)*ROUND(Source!R76, 2), 2) -> 0 | AC60: 0
C61: ="Объем: "&Source!I75&"=5/"&"100" -> Объем: 0,05=5/100
C62: ЗП | F62: =Source!AO75 -> 875.14 | G62: =Source!DG75 -> *1,1 | H62: =Source!AV76 -> 1.047 | I62: =Source!S75 -> 50.39 | J62: =IF(Source!BA76<> 0, Source!BA76, 1) -> 54.99 | K62: =Source!S76 -> 2770.95
C63: ЭМ | F63: =Source!AM75 -> 9.14 | G63: =Source!DE75 -> *1,1 | H63: =Source!AV76 -> 1.047 | I63: =Source!Q75 -> 0.53 | J63: =IF(Source!BB76<> 0, Source!BB76, 1) -> 16.3 | K63: =Source!Q76 -> 8.64
C64: в т.ч. ЗПМ | F64: =Source!AN75 -> 1.39 | G64: =Source!DF75 -> *1,1 | H64: =Source!AV76 -> 1.047 | I64: =Source!R75 -> 0.08 | J64: =IF(Source!BS76<> 0, Source!BS76, 1) -> 54.99 | K64: =Source!R76 -> 4.4
C65: МР | F65: =Source!AL75 -> 857 | G65: =Source!DD75 | H65: =Source!AW76 -> 1 | I65: =Source!P75 -> 42.85 | J65: =IF(Source!BC76<> 0, Source!BC76, 1) -> 2.95 | K65: =Source!P76 -> 126.41
A66: 3,1 | B66: =Source!F77 -> 1.14-1-199 | C66: Розетка телевизионная, скрытой установки, раздельная, двухместная, "штырь" и "гнездо", конечная, затухание 4 дБ, возвратные потери от 12 до 18 дБ, диапазон частот от 5 до 2400 МГц, степень защиты IP20, с безвинтовыми зажимами для радиочастотного коаксиального кабеля с диаметром внутреннего проводника от 0,58 до 1,15 мм и диаметром по изоляции от 3,7 до 5,8 мм, механизм с литой цинковой крепежной рамой, без декоративной крышки, размер не более 71х71х22 мм | D66: =Source!H77 -> шт. | E66: =Source!I77 -> 5 | F66: =Source!AK77 -> 133.05 | H66: =Source!AW78 -> 1 | I66: =Source!O77 -> 665.25 | J66: =IF(Source!BC78<> 0, Source!BC78, 1) -> 9.34 | K66: =Source!O78 -> 6213.44 | Q66: =Source!X77 -> 0 | R66: =Source!X78 -> 0 | S66: =Source!Y77 -> 0 | T66: =Source!Y78 -> 0 | U66: =ROUND((175/100)*ROUND(Source!R77, 2), 2) -> 0 | V66: =ROUND((0/100)*ROUND(Source!R78, 2), 2) -> 0 | AC66: 3
C67: НР от ФОТ | D67: % | E67: =Source!BZ76 -> 97 | I67: =SUM(Q60:Q66) -> 48.96 | J67: =Source!AT76 -> 97 | K67: =SUM(R60:R66) -> 2692.09
C68: СП от ФОТ | D68: % | E68: =Source!CA76 -> 51 | I68: =SUM(S60:S67) -> 25.74 | J68: =Source!AU76 -> 51 | K68: =SUM(T60:T67) -> 1415.43
C69: ЗТР | D69: чел-ч | E69: =Source!AQ75 -> 67.37 | G69: =Source!DI75 -> *1,1 | H69: =Source!AV76 -> 1.047 | I69: =Source!U75 -> 3.8795015
C70: ВСЕГО работ по позиции: | H70: =I62+I63+I65+I67+I68+SUM(I66:I66)-SUMIF(AC66:AC66, 5, I66:I66)-SUMIF(AC66:AC66, 6, I66:I66) -> 833.72 | J70: =K62+K63+K65+K67+K68+SUM(K66:K66)-SUMIF(AC66:AC66, 5, K66:K66)-SUMIF(AC66:AC66, 6, K66:K66) -> 13226.96
C71: ВСЕГО оборудование по позиции: | H71: =SUMIF(AC66:AC66, 5, I66:I66)+SUMIF(AC66:AC66, 6, I66:I66) -> 0 | J71: =SUMIF(AC66:AC66, 5, K66:K66)+SUMIF(AC66:AC66, 6, K66:K66) -> 0
C72: ВСЕГО по позиции: | H72: =I62+I63+I65+I67+I68+SUM(I66:I66) -> 833.72 | J72: =K62+K63+K65+K67+K68+SUM(K66:K66) -> 13226.96 | O72: =I62+I63+I65+I67+I68+SUM(I66:I66) -> 833.72 | P72: =K62+K63+K65+K67+K68+SUM(K66:K66) -> 13226.96
A74: 4 | B74: 4.10-186-5 Поправка: Гл.12.Прил.8.п.8. 5_12.00.01.11.003 | C74: Прокладка кабеля связи симметричного для цифровых систем передачи в трубах гофрированных: по бетонным и кирпичным поверхностям стен и потолка | D74: =Source!H79 -> 100 м | E74: =Source!I79 -> 2 | Q74: =Source!X79 -> 408.97 | R74: =Source!X80 -> 22489.21 | S74: =Source!Y79 -> 209.03 | T74: =Source!Y80 -> 11494.48 | U74: =ROUND((175/100)*ROUND(Source!R79, 2), 2) -> 0 | V74: =ROUND((0/100)*ROUND(Source!R80, 2), 2) -> 0 | AC74: 0
C75: ="Объем: "&Source!I79&"=200/"&"100" -> Объем: 2=200/100
C76: ЗП | F76: =Source!AO79 -> 197.28 | G76: =Source!DG79 -> *1,1 | H76: =Source!AV80 -> 1.047 | I76: =Source!S79 -> 454.41 | J76: =IF(Source!BA80<> 0, Source!BA80, 1) -> 54.99 | K76: =Source!S80 -> 24988.01
C77: ЭМ | F77: =Source!AM79 -> 1.73 | G77: =Source!DE79 -> *1,1 | H77: =Source!AV80 -> 1.047 | I77: =Source!Q79 -> 3.98 | J77: =IF(Source!BB80<> 0, Source!BB80, 1) -> 8.71 | K77: =Source!Q80 -> 34.67
C78: МР | F78: =Source!AL79 -> 91.91 | G78: =Source!DD79 | H78: =Source!AW80 -> 1 | I78: =Source!P79 -> 183.82 | J78: =IF(Source!BC80<> 0, Source!BC80, 1) -> 2.76 | K78: =Source!P80 -> 507.34
A79: 4,1 | B79: =Source!F81 -> 1.12-5-372 | C79: Трубы электротехнические, гофрированные, из ПВХ, негорючие, с зондом, наружный диаметр 20 мм | D79: =Source!H81 -> м | E79: =Source!I81 -> 204 | F79: =Source!AK81 -> 3.45 | H79: =Source!AW82 -> 1 | I79: =Source!O81 -> 703.8 | J79: =IF(Source!BC82<> 0, Source!BC82, 1) -> 3.93 | K79: =Source!O82 -> 2765.93 | Q79: =Source!X81 -> 0 | R79: =Source!X82 -> 0 | S79: =Source!Y81 -> 0 | T79: =Source!Y82 -> 0 | U79: =ROUND((175/100)*ROUND(Source!R81, 2), 2) -> 0 | V79: =ROUND((0/100)*ROUND(Source!R82, 2), 2) -> 0 | AC79: 3
A80: 4,2 | B80: =Source!F83 -> 1.21-5-896 | C80: Коробка установочная, для скрытой проводки, из полистирола, диаметр 65 мм, высота 40 мм, без саморезов | D80: =Source!H83 -> шт. | E80: =Source!I83 -> 5 | F80: =Source!AK83 -> 1.06 | H80: =Source!AW84 -> 1 | I80: =Source!O83 -> 5.3 | J80: =IF(Source!BC84<> 0, Source!BC84, 1) -> 5.93 | K80: =Source!O84 -> 31.43 | Q80: =Source!X83 -> 0 | R80: =Source!X84 -> 0 | S80: =Source!Y83 -> 0 | T80: =Source!Y84 -> 0 | U80: =ROUND((175/100)*ROUND(Source!R83, 2), 2) -> 0 | V80: =ROUND((0/100)*ROUND(Source!R84, 2), 2) -> 0 | AC80: 3
A81: 4,3 | B81: =Source!F85 -> 1.21-5-1136 | C81: Держатель пластиковый с защелкой для крепления труб, рукавов и гибких вводов диаметром 20 мм | D81: =Source!H85 -> 100 шт. | E81: =Source!I85 -> 6 | F81: =Source!AK85 -> 146.89 | H81: =Source!AW86 -> 1 | I81: =Source!O85 -> 881.34 | J81: =IF(Source!BC86<> 0, Source!BC86, 1) -> 2.03 | K81: =Source!O86 -> 1789.12 | Q81: =Source!X85 -> 0 | R81: =Source!X86 -> 0 | S81: =Source!Y85 -> 0 | T81: =Source!Y86 -> 0 | U81: =ROUND((175/100)*ROUND(Source!R85, 2), 2) -> 0 | V81: =ROUND((0/100)*ROUND(Source!R86, 2), 2) -> 0 | AC81: 3
A82: 4,4 | B82: =Source!F87 -> КА 2 | C82: Кабель коаксиальный РК 75-4,8-319нг(А)-LSLTx 13 813,36 = [160 560 / 1,2 / 9,88] + 2% Заг.скл | D82: =Source!H87 -> км | E82: =Source!I87 -> 0.255 | F82: =Source!AK87 -> 13813.36 | H82: =Source!AW88 -> 1 | I82: =Source!O87 -> 3522.41 | J82: =IF(Source!BC88<> 0, Source!BC88, 1) -> 9.88 | K82: =Source!O88 -> 34801.41 | Q82: =Source!X87 -> 0 | R82: =Source!X88 -> 0 | S82: =Source!Y87 -> 0 | T82: =Source!Y88 -> 0 | U82: =ROUND((175/100)*ROUND(Source!R87, 2), 2) -> 0 | V82: =ROUND((0/100)*ROUND(Source!R88, 2), 2) -> 0 | AC82: 3
A83: 4,5 | B83: =Source!F89 -> КА 3 | C83: Кабель коаксиальный РК 75-7-327нг(А)-LSLTx 22 280,67 = [258 980 / 1,2 / 9,88] + 2% Заг.скл | D83: =Source!H89 -> км | E83: =Source!I89 -> 0.1377 | F83: =Source!AK89 -> 22280.67 | H83: =Source!AW90 -> 1 | I83: =Source!O89 -> 3068.05 | J83: =IF(Source!BC90<> 0, Source!BC90, 1) -> 9.88 | K83: =Source!O90 -> 30312.33 | Q83: =Source!X89 -> 0 | R83: =Source!X90 -> 0 | S83: =Source!Y89 -> 0 | T83: =Source!Y90 -> 0 | U83: =ROUND((175/100)*ROUND(Source!R89, 2), 2) -> 0 | V83: =ROUND((0/100)*ROUND(Source!R90, 2), 2) -> 0 | AC83: 3
A84: 4,6 | B84: =Source!F91 -> 1.14-1-281 | C84: Разъем телевизионный F для коаксиального кабеля стандарта RG11 | D84: =Source!H91 -> шт. | E84: =Source!I91 -> 20 | F84: =Source!AK91 -> 30.69 | H84: =Source!AW92 -> 1 | I84: =Source!O91 -> 613.8 | J84: =IF(Source!BC92<> 0, Source!BC92, 1) -> 5.76 | K84: =Source!O92 -> 3535.49 | Q84: =Source!X91 -> 0 | R84: =Source!X92 -> 0 | S84: =Source!Y91 -> 0 | T84: =Source!Y92 -> 0 | U84: =ROUND((175/100)*ROUND(Source!R91, 2), 2) -> 0 | V84: =ROUND((0/100)*ROUND(Source!R92, 2), 2) -> 0 | AC84: 3
A85: 4,7 | B85: =Source!F93 -> 1.14-1-280 | C85: Разъем телевизионный F для коаксиального кабеля стандарта RG6 | D85: =Source!H93 -> шт. | E85: =Source!I93 -> 15 | F85: =Source!AK93 -> 9.12 | H85: =Source!AW94 -> 1 | I85: =Source!O93 -> 136.8 | J85: =IF(Source!BC94<> 0, Source!BC94, 1) -> 2.68 | K85: =Source!O94 -> 366.62 | Q85: =Source!X93 -> 0 | R85: =Source!X94 -> 0 | S85: =Source!Y93 -> 0 | T85: =Source!Y94 -> 0 | U85: =ROUND((175/100)*ROUND(Source!R93, 2), 2) -> 0 | V85: =ROUND((0/100)*ROUND(Source!R94, 2), 2) -> 0 | AC85: 3
C86: НР от ФОТ | D86: % | E86: =Source!BZ80 -> 90 | I86: =SUM(Q74:Q85) -> 408.97 | J86: =Source!AT80 -> 90 | K86: =SUM(R74:R85) -> 22489.21
C87: СП от ФОТ | D87: % | E87: =Source!CA80 -> 46 | I87: =SUM(S74:S86) -> 209.03 | J87: =Source!AU80 -> 46 | K87: =SUM(T74:T86) -> 11494.48
C88: ЗТР | D88: чел-ч | E88: =Source!AQ79 -> 16.6 | G88: =Source!DI79 -> *1,1 | H88: =Source!AV80 -> 1.047 | I88: =Source!U79 -> 38.23644
C89: ВСЕГО работ по позиции: | H89: =I76+I77+I78+I86+I87+SUM(I79:I85)-SUMIF(AC79:AC85, 5, I79:I85)-SUMIF(AC79:AC85, 6, I79:I85) -> 10191.71 | J89: =K76+K77+K78+K86+K87+SUM(K79:K85)-SUMIF(AC79:AC85, 5, K79:K85)-SUMIF(AC79:AC85, 6, K79:K85) -> 133116.04
C90: ВСЕГО оборудование по позиции: | H90: =SUMIF(AC79:AC85, 5, I79:I85)+SUMIF(AC79:AC85, 6, I79:I85) -> 0 | J90: =SUMIF(AC79:AC85, 5, K79:K85)+SUMIF(AC79:AC85, 6, K79:K85) -> 0
C91: ВСЕГО по позиции: | H91: =I76+I77+I78+I86+I87+SUM(I79:I85) -> 10191.71 | J91: =K76+K77+K78+K86+K87+SUM(K79:K85) -> 133116.04 | O91: =I76+I77+I78+I86+I87+SUM(I79:I85) -> 10191.71 | P91: =K76+K77+K78+K86+K87+SUM(K79:K85) -> 133116.04
A93: 5 | B93: 4.10-134-4 Поправка: Гл.12.Прил.8.п.8. 5_12.00.01.11.003 | C93: Антенные устройства, монтаж антенны коллективной для приема ТВ на антенной опоре высотой до 6 м без оттяжек на кровле с ранее оборудованными трубостойками | D93: =Source!H109 -> 1 антенна | E93: =Source!I109 -> 1 | Q93: =Source!X109 -> 86.5 | R93: =Source!X110 -> 4756.5 | S93: =Source!Y109 -> 48.26 | T93: =Source!Y110 -> 2653.63 | U93: =ROUND((175/100)*ROUND(Source!R109, 2), 2) -> 0 | V93: =ROUND((0/100)*ROUND(Source!R110, 2), 2) -> 0 | AC93: 0
C94: ЗП | F94: =Source!AO109 -> 76.15 | G94: =Source!DG109 -> *1,1 | H94: =Source!AV110 -> 1.087 | I94: =Source!S109 -> 91.05 | J94: =IF(Source!BA110<> 0, Source!BA110, 1) -> 54.99 | K94: =Source!S110 -> 5006.84
C95: МР | F95: =Source!AL109 -> 0.37 | G95: =Source!DD109 | H95: =Source!AW110 -> 1 | I95: =Source!P109 -> 0.37 | J95: =IF(Source!BC110<> 0, Source!BC110, 1) -> 9.89 | K95: =Source!P110 -> 3.66
A96: 5,1 | B96: =Source!F111 -> КА 4 | C96: Антенна ДМВ диапазона EB45LTE 473,18 = [5 500 / 1,2 / 9,88] + 2% Заг.скл | D96: =Source!H111 -> шт. | E96: =Source!I111 -> 1 | F96: =Source!AK111 -> 473.18 | H96: =Source!AW112 -> 1 | I96: =Source!O111 -> 473.18 | J96: =IF(Source!BC112<> 0, Source!BC112, 1) -> 9.88 | K96: =Source!O112 -> 4675.02 | Q96: =Source!X111 -> 0 | R96: =Source!X112 -> 0 | S96: =Source!Y111 -> 0 | T96: =Source!Y112 -> 0 | U96: =ROUND((175/100)*ROUND(Source!R111, 2), 2) -> 0 | V96: =ROUND((0/100)*ROUND(Source!R112, 2), 2) -> 0 | AC96: 3
C97: НР от ФОТ | D97: % | E97: =Source!BZ110 -> 95 | I97: =SUM(Q93:Q96) -> 86.5 | J97: =Source!AT110 -> 95 | K97: =SUM(R93:R96) -> 4756.5
C98: СП от ФОТ | D98: % | E98: =Source!CA110 -> 53 | I98: =SUM(S93:S97) -> 48.26 | J98: =Source!AU110 -> 53 | K98: =SUM(T93:T97) -> 2653.63
C99: ЗТР | D99: чел-ч | E99: =Source!AQ109 -> 5.37 | G99: =Source!DI109 -> *1,1 | H99: =Source!AV110 -> 1.087 | I99: =Source!U109 -> 6.420909
C100: ВСЕГО работ по позиции: | H100: =I94+I95+I97+I98+SUM(I96:I96)-SUMIF(AC96:AC96, 5, I96:I96)-SUMIF(AC96:AC96, 6, I96:I96) -> 699.36 | J100: =K94+K95+K97+K98+SUM(K96:K96)-SUMIF(AC96:AC96, 5, K96:K96)-SUMIF(AC96:AC96, 6, K96:K96) -> 17095.65
C101: ВСЕГО оборудование по позиции: | H101: =SUMIF(AC96:AC96, 5, I96:I96)+SUMIF(AC96:AC96, 6, I96:I96) -> 0 | J101: =SUMIF(AC96:AC96, 5, K96:K96)+SUMIF(AC96:AC96, 6, K96:K96) -> 0
C102: ВСЕГО по позиции: | H102: =I94+I95+I97+I98+SUM(I96:I96) -> 699.36 | J102: =K94+K95+K97+K98+SUM(K96:K96) -> 17095.65 | O102: =I94+I95+I97+I98+SUM(I96:I96) -> 699.36 | P102: =K94+K95+K97+K98+SUM(K96:K96) -> 17095.65
A104: 6 | B104: 4.10-136-1 Поправка: Гл.12.Прил.8.п.8. 5_12.00.01.11.003 | C104: Разные устройства, монтаж коробки телевизионной (ответвители, разветвители магистральные, домовые, абонентские), УСС, БФТК | D104: =Source!H113 -> 1 ШТ. | E104: =Source!I113 -> 1 | Q104: =Source!X113 -> 12.52 | R104: =Source!X114 -> 688.53 | S104: =Source!Y113 -> 6.99 | T104: =Source!Y114 -> 384.13 | U104: =ROUND((175/100)*ROUND(Source!R113, 2), 2) -> 0 | V104: =ROUND((0/100)*ROUND(Source!R114, 2), 2) -> 0 | AC104: 0
C105: ЗП | F105: =Source!AO113 -> 11.02 | G105: =Source!DG113 -> *1,1 | H105: =Source!AV114 -> 1.087 | I105: =Source!S113 -> 13.18 | J105: =IF(Source!BA114<> 0, Source!BA114, 1) -> 54.99 | K105: =Source!S114 -> 724.77
C106: МР | F106: =Source!AL113 -> 0.29 | G106: =Source!DD113 | H106: =Source!AW114 -> 1 | I106: =Source!P113 -> 0.29 | J106: =IF(Source!BC114<> 0, Source!BC114, 1) -> 9.9 | K106: =Source!P114 -> 2.87
A107: 6,1 | B107: =Source!F115 -> КА 5 | C107: Грозозащита 75 Ом ОВР 523,16 = [6 081 / 1,2 / 9,88] + 2% Заг.скл | D107: =Source!H115 -> шт. | E107: =Source!I115 -> 1 | F107: =Source!AK115 -> 523.16 | H107: =Source!AW116 -> 1 | I107: =Source!O115 -> 523.16 | J107: =IF(Source!BC116<> 0, Source!BC116, 1) -> 9.88 | K107: =Source!O116 -> 5168.82 | Q107: =Source!X115 -> 0 | R107: =Source!X116 -> 0 | S107: =Source!Y115 -> 0 | T107: =Source!Y116 -> 0 | U107: =ROUND((175/100)*ROUND(Source!R115, 2), 2) -> 0 | V107: =ROUND((0/100)*ROUND(Source!R116, 2), 2) -> 0 | AC107: 3
C108: НР от ФОТ | D108: % | E108: =Source!BZ114 -> 95 | I108: =SUM(Q104:Q107) -> 12.52 | J108: =Source!AT114 -> 95 | K108: =SUM(R104:R107) -> 688.53
C109: СП от ФОТ | D109: % | E109: =Source!CA114 -> 53 | I109: =SUM(S104:S108) -> 6.99 | J109: =Source!AU114 -> 53 | K109: =SUM(T104:T108) -> 384.13
C110: ЗТР | D110: чел-ч | E110: =Source!AQ113 -> 0.8 | G110: =Source!DI113 -> *1,1 | H110: =Source!AV114 -> 1.087 | I110: =Source!U113 -> 0.95656
C111: ВСЕГО работ по позиции: | H111: =I105+I106+I108+I109+SUM(I107:I107)-SUMIF(AC107:AC107, 5, I107:I107)-SUMIF(AC107:AC107, 6, I107:I107) -> 556.14 | J111: =K105+K106+K108+K109+SUM(K107:K107)-SUMIF(AC107:AC107, 5, K107:K107)-SUMIF(AC107:AC107, 6, K107:K107) -> 6969.12
C112: ВСЕГО оборудование по позиции: | H112: =SUMIF(AC107:AC107, 5, I107:I107)+SUMIF(AC107:AC107, 6, I107:I107) -> 0 | J112: =SUMIF(AC107:AC107, 5, K107:K107)+SUMIF(AC107:AC107, 6, K107:K107) -> 0
C113: ВСЕГО по позиции: | H113: =I105+I106+I108+I109+SUM(I107:I107) -> 556.14 | J113: =K105+K106+K108+K109+SUM(K107:K107) -> 6969.12 | O113: =I105+I106+I108+I109+SUM(I107:I107) -> 556.14 | P113: =K105+K106+K108+K109+SUM(K107:K107) -> 6969.12
...

Sheet Ведомость объемов работ
A1: =Source!B1 -> Smeta.RU (495) 974-1589
E3: "УТВЕРЖДАЮ"
D5: ___________________________
D7: ___________________________
D9: " ___ " ___________ 20 ___ г.
B12: =CONCATENATE("Ведомость объемов работ ", IF(Source!AN15<>"", Source!AN15," ")) -> Ведомость объемов работ
B13: =CONCATENATE(Source!F12, " ", Source!G12) -> 02-01-11 02-01-11 СКТ
A16: № п/п | B16: № в ЛСР | C16: Наименование работ и затрат | D16: Единица измерения | E16: Количество | F16: Ссылка на чертежи, спецификации | G16: Формула расчета, расчет объемов работ и расхода материалов | H16: Примечание
A17: 1 | B17: 2 | C17: 3 | D17: 4 | E17: 5 | F17: 6 | G17: 7 | H17: 8
A18: =CONCATENATE("Локальная смета: ", Source!G20) -> Локальная смета: Система кабельного телевидения
A19: =CONCATENATE("Раздел: ", Source!G24) -> Раздел: Оборудование
A20: 1 | B20: =Source!E28 -> 1 | C20: =Source!G28 -> Разные устройства, монтаж базового блока головной станции настенного типа | D20: 1 ШТ. | E20: =Source!I28 -> 1 | F20: =Source!U24 | G20: =Source!I28 -> 1
A21: 1.1 | B21: =Source!E30 -> 1,1 | C21: =Source!G30 -> Головная станция СКТ "Мини-ГС" на базе оборудования VS50 Pro в шкафу с блоком розеток и автоматом | D21: шт. | E21: =Source!I30 -> 1 | F21: =Source!U24
A22: 2 | B22: =Source!E32 -> 2 | C22: =Source!G32 -> Установка прибора на резьбовых соединениях | D22: 1 ШТ. | E22: =Source!I32 -> 3 | F22: =Source!U24 | G22: =Source!I32 -> 3
A23: 2.1 | B23: =Source!E34 -> 2,1 | C23: =Source!G34 -> Ответвитель направленный, абонентский, типа ОАТ 410 | D23: шт. | E23: =Source!I34 -> 1 | F23: =Source!U24
A24: 2.2 | B24: =Source!E36 -> 2,2 | C24: =Source!G36 -> Ответвитель направленный, абонентский, типа ОАТ 412 | D24: шт. | E24: =Source!I36 -> 1 | F24: =Source!U24
A25: 2.3 | B25: =Source!E38 -> 2,3 | C25: =Source!G38 -> Ответвитель направленный, абонентский, типа ОАТ 416 | D25: шт. | E25: =Source!I38 -> 1 | F25: =Source!U24
A26: =CONCATENATE("Раздел: ", Source!G71) -> Раздел: Материалы
A27: 3 | B27: =Source!E75 -> 3 | C27: =Source!G75 -> Монтаж розетки штепсельной трехполюсной | D27: 100 шт. | E27: =Source!I75 -> 0.05 | F27: =Source!U71 | G27: ="=5/"&"100" -> =5/100
A28: 3.1 | B28: =Source!E77 -> 3,1 | C28: =Source!G77 -> Розетка телевизионная, скрытой установки, раздельная, двухместная, "штырь" и "гнездо", конечная, затухание 4 дБ, возвратные потери от 12 до 18 дБ, диапазон частот от 5 до 2400 МГц, степень защиты IP20, с безвинтовыми зажимами для радиочастотного коаксиального кабеля с диаметром внутреннего проводника от 0,58 до 1,15 мм и диаметром по изоляции от 3,7 до 5,8 мм, механизм с литой цинковой крепежной рамой, без декоративной крышки, размер не более 71х71х22 мм | D28: шт. | E28: =Source!I77 -> 5 | F28: =Source!U71
A29: 4 | B29: =Source!E79 -> 4 | C29: =Source!G79 -> Прокладка кабеля связи симметричного для цифровых систем передачи в трубах гофрированных: по бетонным и кирпичным поверхностям стен и потолка | D29: 100 м | E29: =Source!I79 -> 2 | F29: =Source!U71 | G29: ="=200/"&"100" -> =200/100
A30: 4.1 | B30: =Source!E81 -> 4,1 | C30: =Source!G81 -> Трубы электротехнические, гофрированные, из ПВХ, негорючие, с зондом, наружный диаметр 20 мм | D30: м | E30: =Source!I81 -> 204 | F30: =Source!U71
A31: 4.2 | B31: =Source!E83 -> 4,2 | C31: =Source!G83 -> Коробка установочная, для скрытой проводки, из полистирола, диаметр 65 мм, высота 40 мм, без саморезов | D31: шт. | E31: =Source!I83 -> 5 | F31: =Source!U71
A32: 4.3 | B32: =Source!E85 -> 4,3 | C32: =Source!G85 -> Держатель пластиковый с защелкой для крепления труб, рукавов и гибких вводов диаметром 20 мм | D32: 100 шт. | E32: =Source!I85 -> 6 | F32: =Source!U71
A33: 4.4 | B33: =Source!E87 -> 4,4 | C33: =Source!G87 -> Кабель коаксиальный РК 75-4,8-319нг(А)-LSLTx | D33: км | E33: =Source!I87 -> 0.255 | F33: =Source!U71
A34: 4.5 | B34: =Source!E89 -> 4,5 | C34: =Source!G89 -> Кабель коаксиальный РК 75-7-327нг(А)-LSLTx | D34: км | E34: =Source!I89 -> 0.1377 | F34: =Source!U71
A35: 4.6 | B35: =Source!E91 -> 4,6 | C35: =Source!G91 -> Разъем телевизионный F для коаксиального кабеля стандарта RG11 | D35: шт. | E35: =Source!I91 -> 20 | F35: =Source!U71
A36: 4.7 | B36: =Source!E93 -> 4,7 | C36: =Source!G93 -> Разъем телевизионный F для коаксиального кабеля стандарта RG6 | D36: шт. | E36: =Source!I93 -> 15 | F36: =Source!U71
A37: 5 | B37: =Source!E109 -> 5 | C37: =Source!G109 -> Антенные устройства, монтаж антенны коллективной для приема ТВ на антенной опоре высотой до 6 м без оттяжек на кровле с ранее оборудованными трубостойками | D37: 1 антенна | E37: =Source!I109 -> 1 | F37: =Source!U71 | G37: =Source!I109 -> 1
A38: 5.1 | B38: =Source!E111 -> 5,1 | C38: =Source!G111 -> Антенна ДМВ диапазона EB45LTE | D38: шт. | E38: =Source!I111 -> 1 | F38: =Source!U71
A39: 6 | B39: =Source!E113 -> 6 | C39: =Source!G113 -> Разные устройства, монтаж коробки телевизионной (ответвители, разветвители магистральные, домовые, абонентские), УСС, БФТК | D39: 1 ШТ. | E39: =Source!I113 -> 1 | F39: =Source!U71 | G39: =Source!I113 -> 1
A40: 6.1 | B40: =Source!E115 -> 6,1 | C40: =Source!G115 -> Грозозащита 75 Ом ОВР | D40: шт. | E40: =Source!I115 -> 1 | F40: =Source!U71
A41: 7 | B41: =Source!E117 -> 7 | C41: =Source!G117 -> Прокладка металлического рукава, наружный диаметр до 48 мм | D41: 100 м | E41: =Source!I117 -> 0.1 | F41: =Source!U71 | G41: ="=10/"&"100" -> =10/100
A42: 7.1 | B42: =Source!E119 -> 7,1 | C42: =Source!G119 -> Рукав металлический из алюминиевой ленты, негерметичный, уплотненный хлопчатобумажной нитью, для защиты кабеля от механических повреждений, номинальный диаметр 22 мм | D42: м | E42: =Source!I119 -> 10.3 | F42: =Source!U71
C45: Главный инженер проекта _________________ | D45: =IF(Source!X12<>"", Source!X12," ")
C47: Составил _________________ | D47: =IF(Source!AB12<>"", Source!AB12," ") -> Лукьянова А.Л.

Sheet Source
A1: 0 | B1: Smeta.RU (495) 974-1589 | D1: _PS_ | F1: 0 | G1: 0 | H1: 0 | I1: Smeta.RU | K1: 1 | L1: 74562 | M1: 10 | N1: 12 | O1: 0 | P1: 0 | Q1: 3
A4: 1 | B4: 1 | C4: -1 | G4: Капитальный ремонт здания Государственного бюджетного общеобразовательного учреждения города Москвы «Школа № 236» по адресу: г. Москва, ул. Клязьминская, д. 7, к. 4. I этап | EC4: 0
A12: 1 | B12: 229 | C12: 0 | D12: =ROW(A190) -> 190 | E12: 0 | F12: 02-01-11 | G12: 02-01-11 СКТ | I12: 0 | J12: 2024-00272-01-0-ИОС5.4 | K12: 0 | L12: 0 | M12: 4098 | O12: 0 | P12: 0 | Q12: 0 | R12: 0 | S12: 0 | T12: 1 | V12: 0 | AB12: Лукьянова А.Л. | BB12: 0 | BH12: Сметные нормы списания | BI12: Коды ОКП для ТСН-2001 МГЭ Дополнение 80 | BJ12: 1 | BK12: 1 | BL12: 0 | BM12: 0 | BN12: 1 | BO12: 0 | BP12: 6 | BQ12: 2 | BR12: 1 | BS12: 1 | BT12: 1 | BU12: 0 | BV12: 1 | BW12: 0 | BX12: 0 | BY12: ТСН-2001 (МГЭ) Доп 80 - Новое строительство | BZ12: Типовой расчет для ТСН-2001 МГЭ, Дополнение 80, строительство | CA12: Территориальные сметные нормативы для Москвы ТСН-2001 (МГЭ), дополнение 80 | CB12: Территориальные сметные нормативы для Москвы ТСН-2001 (МГЭ), дополнение 80 | CC12: Территориальные сметные нормативы для Москвы ТСН-2001 (МГЭ), дополнение 80 | CD12: Территориальные сметные нормативы для Москвы ТСН-2001 (МГЭ), дополнение 80 | CE12: Поправки для ТСН-2001 от 03.02.2026 г. доп.80 | CF12: 0 | CG12: 0 | CH12: 8200 | CK12: 80 | CQ12: Территориальные сметные нормативы для Москвы (ТСН-2001) | CR12: ТЕР | CS12: 41660 | CT12: 1 | CU12: 80 | CY12: 0 | EC12: 0
A15: 15 | B15: 1
A18: 52 | B18: =B190 -> 229 | C18: =C190 -> 1 | D18: =D190 -> 12 | E18: =E190 -> 0 | F18: =F190 -> 02-01-11 | G18: =G190 -> 02-01-11 СКТ | O18: =O190 -> 20912.05 | P18: =P190 -> 20094.21 | Q18: =Q190 -> 19.37 | R18: =R190 -> 0.37 | S18: =S190 -> 798.47 | T18: =T190 -> 0 | U18: =U190 -> 63.539123 | V18: =V190 -> 0 | ... GX18: =GX190 -> 0
A20: 3 | B20: 1 | D20: =ROW(A160) -> 160 | F20: 02-01-11 | G20: Система кабельного телевидения | I20: 0 | J20: 2024-00272-01-0-ИОС5.4 | K20: -1 | L20: 02-01-11 | S20: 0 | T20: 0 | V20: 0 | AB20: Лукьянова А.Л. | BX20: 0 | CF20: 0 | CG20: 0
A22: 52 | B22: =B160 -> 1 | C22: =C160 -> 3 | D22: =D160 -> 20 | E22: =E160 -> 0 | F22: =F160 -> 02-01-11 | G22: =G160 -> Система кабельного телевидения | O22: =O160 -> 20912.05 | P22: =P160 -> 20094.21 | Q22: =Q160 -> 19.37 | R22: =R160 -> 0.37 | S22: =S160 -> 798.47 | T22: =T160 -> 0 | U22: =U160 -> 63.539123 | V22: =V160 -> 0 | ... GX22: =GX160 -> 0
A24: 4 | B24: 1 | D24: =ROW(A41) -> 41 | G24: Оборудование | I24: 0 | K24: -1 | S24: 0 | T24: 0 | V24: 0 | BX24: 0 | CJ24: 0
A26: 52 | B26: =B41 -> 1 | C26: =C41 -> 4 | D26: =D41 -> 24 | E26: =E41 -> 0 | F26: =F41 | G26: =G41 -> Оборудование | O26: =O41 -> 9058.21 | P26: =P41 -> 8911.2 | Q26: =Q41 -> 0 | R26: =R41 -> 0 | S26: =S41 -> 147.01 | T26: =T41 -> 0 | U26: =U41 -> 10.60213 | V26: =V41 -> 0 | ... GX26: =GX41 -> 0
A28: 17 | B28: 1 | D28: =ROW(EtalonRes!A1) -> 1 | E28: 1 | F28: 4.10-136-5 | G28: Разные устройства, монтаж базового блока головной станции настенного типа | H28: 1 ШТ. | I28: 1 | J28: 0 | K28: 1 | O28: =ROUND(CP28,2) -> 133.83 | P28: =ROUND((ROUND((AC28*AW28*I28),2)*BC28),2) -> 0.29 | Q28: =(ROUND((ROUND((((ET28*1.1))*AV28*I28),2)*BB28),2)+ROUND((ROUND(((AE28-((EU28*1.1)))*AV28*I28),2)*BS28),2)) -> 0 | R28: =ROUND((ROUND((AE28*AV28*I28),2)*BS28),2) -> 0 | S28: =ROUND((ROUND((AF28*AV28*I28),2)*BA28),2) -> 133.54 | T28: =ROUND(CU28*I28,2) -> 0 | U28: =CV28*I28 -> 9.5656 | V28: =CW28*I28 -> 0 | W28: =ROUND(CX28*I28,2) -> 0 | X28: =ROUND(CY28,2) -> 126.86 | Y28: =ROUND(CZ28,2) -> 70.78 | AA28: 56503348 | AB28: =ROUND((AC28+AD28+AF28),6) -> 123.138 | AC28: =ROUND((ES28),6) -> 0.29 | AD28: =ROUND(((((ET28*1.1))-((EU28*1.1)))+AE28),6) -> 0 | AE28: =ROUND(((EU28*1.1)),6) -> 0 | AF28: =ROUND(((EV28*1.1)),6) -> 122.848 | AG28: =ROUND((AP28),6) -> 0 | AH28: =((EW28*1.1)) -> 8.8 | AI28: =((EX28*1.1)) -> 0 | AJ28: =(AS28) -> 0 | AK28: 111.97 | AL28: 0.29 | AM28: 0 | AN28: 0 | AO28: 111.68 | AP28: 0 | AQ28: 8 | AR28: 0 | AS28: 0 | AT28: 95 | AU28: 53 | AV28: 1.087 | AW28: 1 | AZ28: 1 | BA28: 1 | BB28: 1 | BC28: 1 | BH28: 0 | BI28: 2 | BJ28: ТСН-2001.4. Доп. 1-42. Сб. 10, т. 136, поз. 5 | BM28: 69 | BN28: 0 | BO28: 4.10-136-5 | BP28: 1 | BQ28: 40 | BR28: 0 | BS28: 1 | BT28: 1 | BU28: 1 | BV28: 1 | BW28: 1 | BX28: 1 | BZ28: 95 | CA28: 53 | CE28: 30 | CF28: 0 | CG28: 0 | CM28: 0 | CO28: 0 | CP28: =(P28+Q28+S28) -> 133.83 | CQ28: =ROUND((ROUND((AC28*AW28*1),2)*BC28),2) -> 0.29 | CR28: =(ROUND((ROUND((((ET28*1.1))*AV28*1),2)*BB28),2)+ROUND((ROUND(((AE28-((EU28*1.1)))*AV28*1),2)*BS28),2)) -> 0 | CS28: =ROUND((ROUND((AE28*AV28*1),2)*BS28),2) -> 0 | CT28: =ROUND((ROUND((AF28*AV28*1),2)*BA28),2) -> 133.54 | CU28: =AG28 -> 0 | CV28: =(AH28*AV28) -> 9.5656 | CW28: =AI28 -> 0 | CX28: =AJ28 -> 0 | CY28: =(((S28+R28)*AT28)/100) -> 126.863 | CZ28: =(((S28+R28)*AU28)/100) -> 70.7762 | DE28: *1,1 | DF28: *1,1 | DG28: *1,1 | DI28: *1,1 | DJ28: *1,1 | DN28: 0 | DO28: 0 | DP28: 1 | DQ28: 1 | DU28: 1013 | DV28: 1 ШТ. | DW28: 1 ШТ. | DX28: 1 | EE28: 58162631 | EF28: 40 | EG28: Монтаж оборудования | EH28: 0 | EJ28: 2 | EK28: 69 | EL28: ТСН-2001.4-10. Монтаж радиотелевизионного и электронного оборудования | EM28: ТСН-2001.4-10-2 | EO28: Поправка: Гл.12.Прил.8.п.8. 5_12.00.01.11.003 | EQ28: 0 | ER28: 111.97 | ES28: 0.29 | ET28: 0 | EU28: 0 | EV28: 111.68 | EW28: 8 | EX28: 0 | EY28: 0 | FQ28: 0 | FR28: 0 | FS28: 0 | FX28: 95 | FY28: 53 | GD28: 1 | GF28: -860106978 | GG28: 2 | GH28: 1 | GI28: 2 | GJ28: 0 | GK28: 0 | GL28: =ROUND(IF(AND(BH28=3,BI28=3,FS28<>0),P28,0),2) -> 0 | GM28: =ROUND(O28+X28+Y28,2)+GX28 -> 331.47 | GN28: =IF(OR(BI28=0,BI28=1),GM28-GX28,0) -> 0 | GO28: =IF(BI28=2,GM28-GX28,0) -> 331.47 | GP28: =IF(BI28=4,GM28-GX28,0) -> 0 | GR28: 0 | GS28: 3 | GT28: 0 | GV28: =ROUND((GT28),6) -> 0 | GW28: 1 | GX28: =ROUND(HC28*I28,2) -> 0 | HA28: 0 | HB28: 0 | HC28: =GV28*GW28 -> 0 | HS28: 0 | IK28: 0
A29: 17 | B29: 1 | D29: =ROW(EtalonRes!A2) -> 2 | E29: 1 | F29: 4.10-136-5 | G29: Разные устройства, монтаж базового блока головной станции настенного типа | H29: 1 ШТ. | I29: 1 | J29: 0 | K29: 1 | O29: =ROUND(CP29,2) -> 7346.23 | P29: =ROUND((ROUND((AC29*AW29*I29),2)*BC29),2) -> 2.87 | Q29: =(ROUND((ROUND((((ET29*1.1))*AV29*I29),2)*BB29),2)+ROUND((ROUND(((AE29-((EU29*1.1)))*AV29*I29),2)*BS29),2)) -> 0 | R29: =ROUND((ROUND((AE29*AV29*I29),2)*BS29),2) -> 0 | S29: =ROUND((ROUND((AF29*AV29*I29),2)*BA29),2) -> 7343.36 | T29: =ROUND(CU29*I29,2) -> 0 | U29: =CV29*I29 -> 9.5656 | V29: =CW29*I29 -> 0 | W29: =ROUND(CX29*I29,2) -> 0 | X29: =ROUND(CY29,2) -> 6976.19 | Y29: =ROUND(CZ29,2) -> 3891.98 | AA29: 56503350 | AB29: =ROUND((AC29+AD29+AF29),6) -> 123.138 | AC29: =ROUND((ES29),6) -> 0.29 | AD29: =ROUND(((((ET29*1.1))-((EU29*1.1)))+AE29),6) -> 0 | AE29: =ROUND(((EU29*1.1)),6) -> 0 | AF29: =ROUND(((EV29*1.1)),6) -> 122.848 | AG29: =ROUND((AP29),6) -> 0 | AH29: =((EW29*1.1)) -> 8.8 | AI29: =((EX29*1.1)) -> 0 | AJ29: =(AS29) -> 0 | AK29: 111.97 | AL29: 0.29 | AM29: 0 | AN29: 0 | AO29: 111.68 | AP29: 0 | AQ29: 8 | AR29: 0 | AS29: 0 | AT29: 95 | AU29: 53 | AV29: 1.087 | AW29: 1 | AZ29: 1 | BA29: 54.99 | BB29: 1 | BC29: 9.9 | BH29: 0 | BI29: 2 | BJ29: ТСН-2001.4. Доп. 1-42. Сб. 10, т. 136, поз. 5 | BM29: 69 | BN29: 0 | BO29: 4.10-136-5 | BP29: 1 | BQ29: 40 | BR29: 0 | BS29: 54.99 | BT29: 1 | BU29: 1 | BV29: 1 | BW29: 1 | BX29: 1 | BZ29: 95 | CA29: 53 | CE29: 30 | CF29: 0 | CG29: 0 | CM29: 0 | CO29: 0 | CP29: =(P29+Q29+S29) -> 7346.23 | CQ29: =ROUND((ROUND((AC29*AW29*1),2)*BC29),2) -> 2.87 | CR29: =(ROUND((ROUND((((ET29*1.1))*AV29*1),2)*BB29),2)+ROUND((ROUND(((AE29-((EU29*1.1)))*AV29*1),2)*BS29),2)) -> 0 | CS29: =ROUND((ROUND((AE29*AV29*1),2)*BS29),2) -> 0 | CT29: =ROUND((ROUND((AF29*AV29*1),2)*BA29),2) -> 7343.36 | CU29: =AG29 -> 0 | CV29: =(AH29*AV29) -> 9.5656 | CW29: =AI29 -> 0 | CX29: =AJ29 -> 0 | CY29: =(((S29+R29)*AT29)/100) -> 6976.192 | CZ29: =(((S29+R29)*AU29)/100) -> 3891.9808 | DE29: *1,1 | DF29: *1,1 | DG29: *1,1 | DI29: *1,1 | DJ29: *1,1 | DN29: 0 | DO29: 0 | DP29: 1 | DQ29: 1 | DU29: 1013 | DV29: 1 ШТ. | DW29: 1 ШТ. | DX29: 1 | EE29: 58162631 | EF29: 40 | EG29: Монтаж оборудования | EH29: 0 | EJ29: 2 | EK29: 69 | EL29: ТСН-2001.4-10. Монтаж радиотелевизионного и электронного оборудования | EM29: ТСН-2001.4-10-2 | EO29: Поправка: Гл.12.Прил.8.п.8. 5_12.00.01.11.003 | EQ29: 0 | ER29: 111.97 | ES29: 0.29 | ET29: 0 | EU29: 0 | EV29: 111.68 | EW29: 8 | EX29: 0 | EY29: 0 | FQ29: 0 | FR29: 0 | FS29: 0 | FX29: 95 | FY29: 53 | GD29: 1 | GF29: -860106978 | GG29: 2 | GH29: 1 | GI29: 2 | GJ29: 0 | GK29: 0 | GL29: =ROUND(IF(AND(BH29=3,BI29=3,FS29<>0),P29,0),2) -> 0 | GM29: =ROUND(O29+X29+Y29,2)+GX29 -> 18214.4 | GN29: =IF(OR(BI29=0,BI29=1),GM29-GX29,0) -> 0 | GO29: =IF(BI29=2,GM29-GX29,0) -> 18214.4 | GP29: =IF(BI29=4,GM29-GX29,0) -> 0 | GR29: 0 | GS29: 3 | GT29: 0 | GV29: =ROUND((GT29),6) -> 0 | GW29: 1 | GX29: =ROUND(HC29*I29,2) -> 0 | HA29: 0 | HB29: 0 | HC29: =GV29*GW29 -> 0 | HS29: 0 | IK29: 0
A30: 18 | B30: 1 | E30: 1,1 | F30: КА 1 | G30: Головная станция СКТ "Мини-ГС" на базе оборудования VS50 Pro в шкафу с блоком розеток и автоматом | H30: шт. | I30: =I28*J30 -> 1 | J30: 1 | K30: 1 | O30: =ROUND(CP30,2) -> 8788.39 | P30: =ROUND((ROUND((AC30*I30),2)*BC30),2) -> 8788.39 | Q30: =(ROUND((ROUND(((ET30)*AV30*I30),2)*BB30),2)+ROUND((ROUND(((AE30-(EU30))*AV30*I30),2)*BS30),2)) -> 0 | R30: =ROUND((ROUND((AE30*AV30*I30),2)*BS30),2) -> 0 | S30: =ROUND((ROUND((AF30*AV30*I30),2)*BA30),2) -> 0 | T30: =ROUND(CU30*I30,2) -> 0 | U30: =CV30*I30 -> 0 | V30: =CW30*I30 -> 0 | W30: =ROUND(CX30*I30,2) -> 0 | X30: =ROUND(CY30,2) -> 0 | Y30: =ROUND(CZ30,2) -> 0 | AA30: 56503348 | AB30: =ROUND((AC30+AD30+AF30),6) -> 8788.39 | AC30: =ROUND((ES30),6) -> 8788.39 | AD30: =ROUND((((ET30)-(EU30))+AE30),6) -> 0 | AE30: =ROUND((EU30),6) -> 0 | AF30: =ROUND((EV30),6) -> 0 | AG30: =ROUND((AP30),6) -> 0 | AH30: =(EW30) -> 0 | AI30: =(EX30) -> 0 | AJ30: =(AS30) -> 0 | AK30: 8788.39 | AL30: 8788.39 | AM30: 0 | AN30: 0 | AO30: 0 | AP30: 0 | AQ30: 0 | AR30: 0 | AS30: 0 | AT30: 0 | AU30: 0 | AV30: 1 | AW30: 1 | AZ30: 1 | BA30: 1 | BB30: 1 | BC30: 1 | BH30: 3 | BI30: 3 | BM30: 746 | BN30: 0 | BP30: 0 | BQ30: 130 | BR30: 0 | BS30: 1 | BT30: 1 | BU30: 1 | BV30: 1 | BW30: 1 | BX30: 1 | BZ30: 95 | CA30: 53 | CE30: 30 | CF30: 0 | CG30: 0 | CM30: 0 | CO30: 0 | CP30: =(P30+Q30+S30) -> 8788.39 | CQ30: =ROUND((ROUND((AC30*1),2)*BC30),2) -> 8788.39 | CR30: =(ROUND((ROUND(((ET30)*AV30*1),2)*BB30),2)+ROUND((ROUND(((AE30-(EU30))*AV30*1),2)*BS30),2)) -> 0 | CS30: =ROUND((ROUND((AE30*AV30*1),2)*BS30),2) -> 0 | CT30: =ROUND((ROUND((AF30*AV30*1),2)*BA30),2) -> 0 | CU30: =AG30 -> 0 | CV30: =(AH30*AV30) -> 0 | CW30: =AI30 -> 0 | CX30: =AJ30 -> 0 | CY30: =(((S30+R30)*AT30)/100) -> 0 | CZ30: =(((S30+R30)*AU30)/100) -> 0 | DN30: 0 | DO30: 0 | DP30: 1 | DQ30: 1 | DU30: 1010 | DV30: шт. | DW30: шт. | DX30: 1 | EE30: 58162750 | EF30: 130 | EG30: Сметная стоимость оборудования | EH30: 0 | EJ30: 3 | EK30: 746 | EL30: ТСН-2001.13. Сметная стоимость оборудования | EM30: ТСН-2001.13 | EQ30: 0 | ER30: 0 | ES30: 8788.39 | ET30: 0 | EU30: 0 | EV30: 0 | EW30: 0 | EX30: 0 | FQ30: 0 | FR30: =P30 -> 8788.39 | FS30: 0 | FX30: 95 | FY30: 53 | GA30: [77 500 / 1,2 / 7,66] + 3% Трансп + 1,2% Заг.скл | GD30: 1 | GF30: 1252201046 | GG30: 2 | GH30: 4 | GI30: -2 | GJ30: 0 | GK30: 0 | GL30: =ROUND(IF(AND(BH30=3,BI30=3,FS30<>0),P30,0),2) -> 0 | GM30: =ROUND(O30+X30+Y30,2)+GX30 -> 8788.39 | GN30: =IF(OR(BI30=0,BI30=1),GM30-GX30,0) -> 0 | GO30: =IF(BI30=2,GM30-GX30,0) -> 0 | GP30: =IF(BI30=4,GM30-GX30,0) -> 0 | GR30: 0 | GS30: 2 | GT30: 0 | GV30: =ROUND((GT30),6) -> 0 | GW30: 1 | GX30: =ROUND(HC30*I30,2) -> 0 | HA30: 0 | HB30: 0 | HC30: =GV30*GW30 -> 0 | HE30: 3 | HF30: 1,2 | HS30: 0 | IK30: 0
A31: 18 | B31: 1 | E31: 1,1 | F31: КА 1 | G31: Головная станция СКТ "Мини-ГС" на базе оборудования VS50 Pro в шкафу с блоком розеток и автоматом | H31: шт. | I31: =I29*J31 -> 1 | J31: 1 | K31: 1 | O31: =ROUND(CP31,2) -> 67319.07 | P31: =ROUND((ROUND((AC31*I31),2)*BC31),2) -> 67319.07 | Q31: =(ROUND((ROUND(((ET31)*AV31*I31),2)*BB31),2)+ROUND((ROUND(((AE31-(EU31))*AV31*I31),2)*BS31),2)) -> 0 | R31: =ROUND((ROUND((AE31*AV31*I31),2)*BS31),2) -> 0 | S31: =ROUND((ROUND((AF31*AV31*I31),2)*BA31),2) -> 0 | T31: =ROUND(CU31*I31,2) -> 0 | U31: =CV31*I31 -> 0 | V31: =CW31*I31 -> 0 | W31: =ROUND(CX31*I31,2) -> 0 | X31: =ROUND(CY31,2) -> 0 | Y31: =ROUND(CZ31,2) -> 0 | AA31: 56503350 | AB31: =ROUND((AC31+AD31+AF31),6) -> 8788.39 | AC31: =ROUND((ES31),6) -> 8788.39 | AD31: =ROUND((((ET31)-(EU31))+AE31),6) -> 0 | AE31: =ROUND((EU31),6) -> 0 | AF31: =ROUND((EV31),6) -> 0 | AG31: =ROUND((AP31),6) -> 0 | AH31: =(EW31) -> 0 | AI31: =(EX31) -> 0 | AJ31: =(AS31) -> 0 | AK31: 8788.39 | AL31: 8788.39 | AM31: 0 | AN31: 0 | AO31: 0 | AP31: 0 | AQ31: 0 | AR31: 0 | AS31: 0 | AT31: 0 | AU31: 0 | AV31: 1 | AW31: 1 | AZ31: 1 | BA31: 1 | BB31: 1 | BC31: 7.66 | BH31: 3 | BI31: 3 | BM31: 746 | BN31: 0 | BP31: 0 | BQ31: 130 | BR31: 0 | BS31: 1 | BT31: 1 | BU31: 1 | BV31: 1 | BW31: 1 | BX31: 1 | BZ31: 95 | CA31: 53 | CE31: 30 | CF31: 0 | CG31: 0 | CM31: 0 | CO31: 0 | CP31: =(P31+Q31+S31) -> 67319.07 | CQ31: =ROUND((ROUND((AC31*1),2)*BC31),2) -> 67319.07 | CR31: =(ROUND((ROUND(((ET31)*AV31*1),2)*BB31),2)+ROUND((ROUND(((AE31-(EU31))*AV31*1),2)*BS31),2)) -> 0 | CS31: =ROUND((ROUND((AE31*AV31*1),2)*BS31),2) -> 0 | CT31: =ROUND((ROUND((AF31*AV31*1),2)*BA31),2) -> 0 | CU31: =AG31 -> 0 | CV31: =(AH31*AV31) -> 0 | CW31: =AI31 -> 0 | CX31: =AJ31 -> 0 | CY31: =(((S31+R31)*AT31)/100) -> 0 | CZ31: =(((S31+R31)*AU31)/100) -> 0 | DN31: 0 | DO31: 0 | DP31: 1 | DQ31: 1 | DU31: 1010 | DV31: шт. | DW31: шт. | DX31: 1 | EE31: 58162750 | EF31: 130 | EG31: Сметная стоимость оборудования | EH31: 0 | EJ31: 3 | EK31: 746 | EL31: ТСН-2001.13. Сметная стоимость оборудования | EM31: ТСН-2001.13 | EQ31: 0 | ER31: 8788.39 | ES31: 8788.39 | ET31: 0 | EU31: 0 | EV31: 0 | EW31: 0 | EX31: 0 | EZ31: 5 | FC31: 1 | FD31: 18 | FF31: 77500 | FQ31: 0 | FR31: =P31 -> 67319.07 | FS31: 0 | FX31: 95 | FY31: 53 | GA31: [77 500 / 1,2 / 7,66] + 3% Трансп + 1,2% Заг.скл | GD31: 1 | GF31: 1252201046 | GG31: 2 | GH31: 3 | GI31: 5 | GJ31: 0 | GK31: 0 | GL31: =ROUND(IF(AND(BH31=3,BI31=3,FS31<>0),P31,0),2) -> 0 | GM31: =ROUND(O31+X31+Y31,2)+GX31 -> 67319.07 | GN31: =IF(OR(BI31=0,BI31=1),GM31-GX31,0) -> 0 | GO31: =IF(BI31=2,GM31-GX31,0) -> 0 | GP31: =IF(BI31=4,GM31-GX31,0) -> 0 | GR31: 1 | GS31: 1 | GT31: 0 | GV31: =ROUND((GT31),6) -> 0 | GW31: 1 | GX31: =ROUND(HC31*I31,2) -> 0 | HA31: 0 | HB31: 0 | HC31: =GV31*GW31 -> 0 | HE31: 3 | HF31: 1,2 | HS31: 0 | IK31: 0
A32: 17 | B32: 1 | D32: =ROW(EtalonRes!A6) -> 6 | E32: 2 | F32: 4.11-2-1 | G32: Установка прибора на резьбовых соединениях | H32: 1 ШТ. | I32: 3 | J32: 0 | K32: 3 | O32: =ROUND(CP32,2) -> 15.9 | P32: =ROUND((ROUND((AC32*AW32*I32),2)*BC32),2) -> 2.43 | Q32: =(ROUND((ROUND((((ET32*1.1))*AV32*I32),2)*BB32),2)+ROUND((ROUND(((AE32-((EU32*1.1)))*AV32*I32),2)*BS32),2)) -> 0 | R32: =ROUND((ROUND((AE32*AV32*I32),2)*BS32),2) -> 0 | S32: =ROUND((ROUND((AF32*AV32*I32),2)*BA32),2) -> 13.47 | T32: =ROUND(CU32*I32,2) -> 0 | U32: =CV32*I32 -> 1.03653 | V32: =CW32*I32 -> 0 | W32: =ROUND(CX32*I32,2) -> 0 | X32: =ROUND(CY32,2) -> 12.12 | Y32: =ROUND(CZ32,2) -> 6.2 | AA32: 56503348 | AB32: =ROUND((AC32+AD32+AF32),6) -> 5.1 | AC32: =ROUND((ES32),6) -> 0.81 | AD32: =ROUND(((((ET32*1.1))-((EU32*1.1)))+AE32),6) -> 0 | AE32: =ROUND(((EU32*1.1)),6) -> 0 | AF32: =ROUND(((EV32*1.1)),6) -> 4.29 | AG32: =ROUND((AP32),6) -> 0 | AH32: =((EW32*1.1)) -> 0.33 | AI32: =((EX32*1.1)) -> 0 | AJ32: =(AS32) -> 0 | AK32: 4.71 | AL32: 0.81 | AM32: 0 | AN32: 0 | AO32: 3.9 | AP32: 0 | AQ32: 0.3 | AR32: 0 | AS32: 0 | AT32: 90 | AU32: 46 | AV32: 1.047 | AW32: 1 | AZ32: 1 | BA32: 1 | BB32: 1 | BC32: 1 | BH32: 0 | BI32: 2 | BJ32: ТСН-2001.4 Доп. 67, Сб. 11, т. 2, поз. 1 | BM32: 72 | BN32: 0 | BO32: 4.11-2-1 | BP32: 1 | BQ32: 40 | BR32: 0 | BS32: 1 | BT32: 1 | BU32: 1 | BV32: 1 | BW32: 1 | BX32: 1 | BZ32: 90 | CA32: 46 | CE32: 30 | CF32: 0 | CG32: 0 | CM32: 0 | CO32: 0 | CP32: =(P32+Q32+S32) -> 15.9 | CQ32: =ROUND((ROUND((AC32*AW32*1),2)*BC32),2) -> 0.81 | CR32: =(ROUND((ROUND((((ET32*1.1))*AV32*1),2)*BB32),2)+ROUND((ROUND(((AE32-((EU32*1.1)))*AV32*1),2)*BS32),2)) -> 0 | CS32: =ROUND((ROUND((AE32*AV32*1),2)*BS32),2) -> 0 | CT32: =ROUND((ROUND((AF32*AV32*1),2)*BA32),2) -> 4.49 | CU32: =AG32 -> 0 | CV32: =(AH32*AV32) -> 0.34551 | CW32: =AI32 -> 0 | CX32: =AJ32 -> 0 | CY32: =(((S32+R32)*AT32)/100) -> 12.123 | CZ32: =(((S32+R32)*AU32)/100) -> 6.1962 | DE32: *1,1 | DF32: *1,1 | DG32: *1,1 | DI32: *1,1 | DJ32: *1,1 | DN32: 0 | DO32: 0 | DP32: 1 | DQ32: 1 | DU32: 1013 | DV32: 1 ШТ. | DW32: 1 ШТ. | DX32: 1 | EE32: 58162634 | EF32: 40 | EG32: Монтаж оборудования | EH32: 0 | EJ32: 2 | EK32: 72 | EL32: ТСН-2001.4-11. Приборы и средства автоматизации и вычислительной техники | EM32: ТСН-2001.4-11-1 | EO32: Поправка: Гл.12.Прил.8.п.8. 5_12.00.01.11.003 | EQ32: 0 | ER32: 4.71 | ES32: 0.81 | ET32: 0 | EU32: 0 | EV32: 3.9 | EW32: 0.3 | EX32: 0 | EY32: 0 | FQ32: 0 | FR32: 0 | FS32: 0 | FX32: 90 | FY32: 46 | GD32: 1 | GF32: -1494899736 | GG32: 2 | GH32: 1 | GI32: 2 | GJ32: 0 | GK32: 0 | GL32: =ROUND(IF(AND(BH32=3,BI32=3,FS32<>0),P32,0),2) -> 0 | GM32: =ROUND(O32+X32+Y32,2)+GX32 -> 34.22 | GN32: =IF(OR(BI32=0,BI32=1),GM32-GX32,0) -> 0 | GO32: =IF(BI32=2,GM32-GX32,0) -> 34.22 | GP32: =IF(BI32=4,GM32-GX32,0) -> 0 | GR32: 0 | GS32: 3 | GT32: 0 | GV32: =ROUND((GT32),6) -> 0 | GW32: 1 | GX32: =ROUND(HC32*I32,2) -> 0 | HA32: 0 | HB32: 0 | HC32: =GV32*GW32 -> 0 | HS32: 0 | IK32: 0
A33: 17 | B33: 1 | D33: =ROW(EtalonRes!A10) -> 10 | E33: 2 | F33: 4.11-2-1 | G33: Установка прибора на резьбовых соединениях | H33: 1 ШТ. | I33: 3 | J33: 0 | K33: 3 | O33: =ROUND(CP33,2) -> 762.1 | P33: =ROUND((ROUND((AC33*AW33*I33),2)*BC33),2) -> 21.38 | Q33: =(ROUND((ROUND((((ET33*1.1))*AV33*I33),2)*BB33),2)+ROUND((ROUND(((AE33-((EU33*1.1)))*AV33*I33),2)*BS33),2)) -> 0 | R33: =ROUND((ROUND((AE33*AV33*I33),2)*BS33),2) -> 0 | S33: =ROUND((ROUND((AF33*AV33*I33),2)*BA33),2) -> 740.72 | T33: =ROUND(CU33*I33,2) -> 0 | U33: =CV33*I33 -> 1.03653 | V33: =CW33*I33 -> 0 | W33: =ROUND(CX33*I33,2) -> 0 | X33: =ROUND(CY33,2) -> 666.65 | Y33: =ROUND(CZ33,2) -> 340.73 | AA33: 56503350 | AB33: =ROUND((AC33+AD33+AF33),6) -> 5.1 | AC33: =ROUND((ES33),6) -> 0.81 | AD33: =ROUND(((((ET33*1.1))-((EU33*1.1)))+AE33),6) -> 0 | AE33: =ROUND(((EU33*1.1)),6) -> 0 | AF33: =ROUND(((EV33*1.1)),6) -> 4.29 | AG33: =ROUND((AP33),6) -> 0 | AH33: =((EW33*1.1)) -> 0.33 | AI33: =((EX33*1.1)) -> 0 | AJ33: =(AS33) -> 0 | AK33: 4.71 | AL33: 0.81 | AM33: 0 | AN33: 0 | AO33: 3.9 | AP33: 0 | AQ33: 0.3 | AR33: 0 | AS33: 0 | AT33: 90 | AU33: 46 | AV33: 1.047 | AW33: 1 | AZ33: 1 | BA33: 54.99 | BB33: 1 | BC33: 8.8 | BH33: 0 | BI33: 2 | BJ33: ТСН-2001.4 Доп. 67, Сб. 11, т. 2, поз. 1 | BM33: 72 | BN33: 0 | BO33: 4.11-2-1 | BP33: 1 | BQ33: 40 | BR33: 0 | BS33: 54.99 | BT33: 1 | BU33: 1 | BV33: 1 | BW33: 1 | BX33: 1 | BZ33: 90 | CA33: 46 | CE33: 30 | CF33: 0 | CG33: 0 | CM33: 0 | CO33: 0 | CP33: =(P33+Q33+S33) -> 762.1 | CQ33: =ROUND((ROUND((AC33*AW33*1),2)*BC33),2) -> 7.13 | CR33: =(ROUND((ROUND((((ET33*1.1))*AV33*1),2)*BB33),2)+ROUND((ROUND(((AE33-((EU33*1.1)))*AV33*1),2)*BS33),2)) -> 0 | CS33: =ROUND((ROUND((AE33*AV33*1),2)*BS33),2) -> 0 | CT33: =ROUND((ROUND((AF33*AV33*1),2)*BA33),2) -> 246.91 | CU33: =AG33 -> 0 | CV33: =(AH33*AV33) -> 0.34551 | CW33: =AI33 -> 0 | CX33: =AJ33 -> 0 | CY33: =(((S33+R33)*AT33)/100) -> 666.648 | CZ33: =(((S33+R33)*AU33)/100) -> 340.7312 | DE33: *1,1 | DF33: *1,1 | DG33: *1,1 | DI33: *1,1 | DJ33: *1,1 | DN33: 0 | DO33: 0 | DP33: 1 | DQ33: 1 | DU33: 1013 | DV33: 1 ШТ. | DW33: 1 ШТ. | DX33: 1 | EE33: 58162634 | EF33: 40 | EG33: Монтаж оборудования | EH33: 0 | EJ33: 2 | EK33: 72 | EL33: ТСН-2001.4-11. Приборы и средства автоматизации и вычислительной техники | EM33: ТСН-2001.4-11-1 | EO33: Поправка: Гл.12.Прил.8.п.8. 5_12.00.01.11.003 | EQ33: 0 | ER33: 4.71 | ES33: 0.81 | ET33: 0 | EU33: 0 | EV33: 3.9 | EW33: 0.3 | EX33: 0 | EY33: 0 | FQ33: 0 | FR33: 0 | FS33: 0 | FX33: 90 | FY33: 46 | GD33: 1 | GF33: -1494899736 | GG33: 2 | GH33: 1 | GI33: 2 | GJ33: 0 | GK33: 0 | GL33: =ROUND(IF(AND(BH33=3,BI33=3,FS33<>0),P33,0),2) -> 0 | GM33: =ROUND(O33+X33+Y33,2)+GX33 -> 1769.48 | GN33: =IF(OR(BI33=0,BI33=1),GM33-GX33,0) -> 0 | GO33: =IF(BI33=2,GM33-GX33,0) -> 1769.48 | GP33: =IF(BI33=4,GM33-GX33,0) -> 0 | GR33: 0 | GS33: 3 | GT33: 0 | GV33: =ROUND((GT33),6) -> 0 | GW33: 1 | GX33: =ROUND(HC33*I33,2) -> 0 | HA33: 0 | HB33: 0 | HC33: =GV33*GW33 -> 0 | HS33: 0 | IK33: 0
A34: 18 | B34: 1 | E34: 2,1 | F34: 1.14-1-551 | G34: Ответвитель направленный, абонентский, типа ОАТ 410 | H34: шт. | I34: =I32*J34 -> 1 | J34: 0.33333333 | K34: 0.3333333 | O34: =ROUND(CP34,2) -> 39.87 | P34: =ROUND((ROUND((AC34*AW34*I34),2)*BC34),2) -> 39.87 | Q34: =(ROUND((ROUND(((ET34)*AV34*I34),2)*BB34),2)+ROUND((ROUND(((AE34-(EU34))*AV34*I34),2)*BS34),2)) -> 0 | R34: =ROUND((ROUND((AE34*AV34*I34),2)*BS34),2) -> 0 | S34: =ROUND((ROUND((AF34*AV34*I34),2)*BA34),2) -> 0 | T34: =ROUND(CU34*I34,2) -> 0 | U34: =CV34*I34 -> 0 | V34: =CW34*I34 -> 0 | W34: =ROUND(CX34*I34,2) -> 0 | X34: =ROUND(CY34,2) -> 0 | Y34: =ROUND(CZ34,2) -> 0 | AA34: 56503348 | AB34: =ROUND((AC34+AD34+AF34),6) -> 39.87 | AC34: =ROUND((ES34),6) -> 39.87 | AD34: =ROUND((((ET34)-(EU34))+AE34),6) -> 0 | AE34: =ROUND((EU34),6) -> 0 | AF34: =ROUND((EV34),6) -> 0 | AG34: =ROUND((AP34),6) -> 0 | AH34: =(EW34) -> 0 | AI34: =(EX34) -> 0 | AJ34: =(AS34) -> 0 | AK34: 39.87 | AL34: 39.87 | AM34: 0 | AN34: 0 | AO34: 0 | AP34: 0 | AQ34: 0 | AR34: 0 | AS34: 0 | AT34: 90 | AU34: 46 | AV34: 1 | AW34: 1 | AZ34: 1 | BA34: 1 | BB34: 1 | BC34: 1 | BH34: 3 | BI34: 2 | BJ34: ТСН-2001.1 Доп. 73, Р. 14, о. 1, поз. 551 | BM34: 72 | BN34: 0 | BP34: 0 | BQ34: 40 | BR34: 0 | BS34: 1 | BT34: 1 | BU34: 1 | BV34: 1 | BW34: 1 | BX34: 1 | BZ34: 90 | CA34: 46 | CE34: 30 | CF34: 0 | CG34: 0 | CM34: 0 | CO34: 0 | CP34: =(P34+Q34+S34) -> 39.87 | CQ34: =ROUND((ROUND((AC34*AW34*1),2)*BC34),2) -> 39.87 | CR34: =(ROUND((ROUND(((ET34)*AV34*1),2)*BB34),2)+ROUND((ROUND(((AE34-(EU34))*AV34*1),2)*BS34),2)) -> 0 | CS34: =ROUND((ROUND((AE34*AV34*1),2)*BS34),2) -> 0 | CT34: =ROUND((ROUND((AF34*AV34*1),2)*BA34),2) -> 0 | CU34: =AG34 -> 0 | CV34: =(AH34*AV34) -> 0 | CW34: =AI34 -> 0 | CX34: =AJ34 -> 0 | CY34: =(((S34+R34)*AT34)/100) -> 0 | CZ34: =(((S34+R34)*AU34)/100) -> 0 | DN34: 0 | DO34: 0 | DP34: 1 | DQ34: 1 | DU34: 1010 | DV34: шт. | DW34: шт. | DX34: 1 | EE34: 58162634 | EF34: 40 | EG34: Монтаж оборудования | EH34: 0 | EJ34: 2 | EK34: 72 | EL34: ТСН-2001.4-11. Приборы и средства автоматизации и вычислительной техники | EM34: ТСН-2001.4-11-1 | EQ34: 0 | ER34: 39.87 | ES34: 39.87 | ET34: 0 | EU34: 0 | EV34: 0 | EW34: 0 | EX34: 0 | FQ34: 0 | FR34: 0 | FS34: 0 | FX34: 90 | FY34: 46 | GD34: 1 | GF34: -1718720141 | GG34: 2 | GH34: 1 | GI34: -2 | GJ34: 0 | GK34: 0 | GL34: =ROUND(IF(AND(BH34=3,BI34=3,FS34<>0),P34,0),2) -> 0 | GM34: =ROUND(O34+X34+Y34,2)+GX34 -> 39.87 | GN34: =IF(OR(BI34=0,BI34=1),GM34-GX34,0) -> 0 | GO34: =IF(BI34=2,GM34-GX34,0) -> 39.87 | GP34: =IF(BI34=4,GM34-GX34,0) -> 0 | GR34: 0 | GS34: 3 | GT34: 0 | GV34: =ROUND((GT34),6) -> 0 | GW34: 1 | GX34: =ROUND(HC34*I34,2) -> 0 | HA34: 0 | HB34: 0 | HC34: =GV34*GW34 -> 0 | HS34: 0 | IK34: 0
A35: 18 | B35: 1 | E35: 2,1 | F35: 1.14-1-551 | G35: Ответвитель направленный, абонентский, типа ОАТ 410 | H35: шт. | I35: =I33*J35 -> 1 | J35: 0.33333333 | K35: 0.3333333 | O35: =ROUND(CP35,2) -> 113.63 | P35: =ROUND((ROUND((AC35*AW35*I35),2)*BC35),2) -> 113.63 | Q35: =(ROUND((ROUND(((ET35)*AV35*I35),2)*BB35),2)+ROUND((ROUND(((AE35-(EU35))*AV35*I35),2)*BS35),2)) -> 0 | R35: =ROUND((ROUND((AE35*AV35*I35),2)*BS35),2) -> 0 | S35: =ROUND((ROUND((AF35*AV35*I35),2)*BA35),2) -> 0 | T35: =ROUND(CU35*I35,2) -> 0 | U35: =CV35*I35 -> 0 | V35: =CW35*I35 -> 0 | W35: =ROUND(CX35*I35,2) -> 0 | X35: =ROUND(CY35,2) -> 0 | Y35: =ROUND(CZ35,2) -> 0 | AA35: 56503350 | AB35: =ROUND((AC35+AD35+AF35),6) -> 39.87 | AC35: =ROUND((ES35),6) -> 39.87 | AD35: =ROUND((((ET35)-(EU35))+AE35),6) -> 0 | AE35: =ROUND((EU35),6) -> 0 | AF35: =ROUND((EV35),6) -> 0 | AG35: =ROUND((AP35),6) -> 0 | AH35: =(EW35) -> 0 | AI35: =(EX35) -> 0 | AJ35: =(AS35) -> 0 | AK35: 39.87 | AL35: 39.87 | AM35: 0 | AN35: 0 | AO35: 0 | AP35: 0 | AQ35: 0 | AR35: 0 | AS35: 0 | AT35: 90 | AU35: 46 | AV35: 1 | AW35: 1 | AZ35: 1 | BA35: 1 | BB35: 1 | BC35: 2.85 | BH35: 3 | BI35: 2 | BJ35: ТСН-2001.1 Доп. 73, Р. 14, о. 1, поз. 551 | BM35: 72 | BN35: 0 | BO35: 1.14-1-551 | BP35: 1 | BQ35: 40 | BR35: 0 | BS35: 1 | BT35: 1 | BU35: 1 | BV35: 1 | BW35: 1 | BX35: 1 | BZ35: 90 | CA35: 46 | CE35: 30 | CF35: 0 | CG35: 0 | CM35: 0 | CO35: 0 | CP35: =(P35+Q35+S35) -> 113.63 | CQ35: =ROUND((ROUND((AC35*AW35*1),2)*BC35),2) -> 113.63 | CR35: =(ROUND((ROUND(((ET35)*AV35*1),2)*BB35),2)+ROUND((ROUND(((AE35-(EU35))*AV35*1),2)*BS35),2)) -> 0 | CS35: =ROUND((ROUND((AE35*AV35*1),2)*BS35),2) -> 0 | CT35: =ROUND((ROUND((AF35*AV35*1),2)*BA35),2) -> 0 | CU35: =AG35 -> 0 | CV35: =(AH35*AV35) -> 0 | CW35: =AI35 -> 0 | CX35: =AJ35 -> 0 | CY35: =(((S35+R35)*AT35)/100) -> 0 | CZ35: =(((S35+R35)*AU35)/100) -> 0 | DN35: 0 | DO35: 0 | DP35: 1 | DQ35: 1 | DU35: 1010 | DV35: шт. | DW35: шт. | DX35: 1 | EE35: 58162634 | EF35: 40 | EG35: Монтаж оборудования | EH35: 0 | EJ35: 2 | EK35: 72 | EL35: ТСН-2001.4-11. Приборы и средства автоматизации и вычислительной техники | EM35: ТСН-2001.4-11-1 | EQ35: 0 | ER35: 39.87 | ES35: 39.87 | ET35: 0 | EU35: 0 | EV35: 0 | EW35: 0 | EX35: 0 | FQ35: 0 | FR35: 0 | FS35: 0 | FX35: 90 | FY35: 46 | GD35: 1 | GF35: -1718720141 | GG35: 2 | GH35: 1 | GI35: 2 | GJ35: 0 | GK35: 0 | GL35: =ROUND(IF(AND(BH35=3,BI35=3,FS35<>0),P35,0),2) -> 0 | GM35: =ROUND(O35+X35+Y35,2)+GX35 -> 113.63 | GN35: =IF(OR(BI35=0,BI35=1),GM35-GX35,0) -> 0 | GO35: =IF(BI35=2,GM35-GX35,0) -> 113.63 | GP35: =IF(BI35=4,GM35-GX35,0) -> 0 | GR35: 0 | GS35: 3 | GT35: 0 | GV35: =ROUND((GT35),6) -> 0 | GW35: 1 | GX35: =ROUND(HC35*I35,2) -> 0 | HA35: 0 | HB35: 0 | HC35: =GV35*GW35 -> 0 | HS35: 0 | IK35: 0
A36: 18 | B36: 1 | E36: 2,2 | F36: 1.14-1-552 | G36: Ответвитель направленный, абонентский, типа ОАТ 412 | H36: шт. | I36: =I32*J36 -> 1 | J36: 0.33333333 | K36: 0.3333333 | O36: =ROUND(CP36,2) -> 40.05 | P36: =ROUND((ROUND((AC36*AW36*I36),2)*BC36),2) -> 40.05 | Q36: =(ROUND((ROUND(((ET36)*AV36*I36),2)*BB36),2)+ROUND((ROUND(((AE36-(EU36))*AV36*I36),2)*BS36),2)) -> 0 | R36: =ROUND((ROUND((AE36*AV36*I36),2)*BS36),2) -> 0 | S36: =ROUND((ROUND((AF36*AV36*I36),2)*BA36),2) -> 0 | T36: =ROUND(CU36*I36,2) -> 0 | U36: =CV36*I36 -> 0 | V36: =CW36*I36 -> 0 | W36: =ROUND(CX36*I36,2) -> 0 | X36: =ROUND(CY36,2) -> 0 | Y36: =ROUND(CZ36,2) -> 0 | AA36: 56503348 | AB36: =ROUND((AC36+AD36+AF36),6) -> 40.05 | AC36: =ROUND((ES36),6) -> 40.05 | AD36: =ROUND((((ET36)-(EU36))+AE36),6) -> 0 | AE36: =ROUND((EU36),6) -> 0 | AF36: =ROUND((EV36),6) -> 0 | AG36: =ROUND((AP36),6) -> 0 | AH36: =(EW36) -> 0 | AI36: =(EX36) -> 0 | AJ36: =(AS36) -> 0 | AK36: 40.05 | AL36: 40.05 | AM36: 0 | AN36: 0 | AO36: 0 | AP36: 0 | AQ36: 0 | AR36: 0 | AS36: 0 | AT36: 90 | AU36: 46 | AV36: 1 | AW36: 1 | AZ36: 1 | BA36: 1 | BB36: 1 | BC36: 1 | BH36: 3 | BI36: 2 | BJ36: ТСН-2001.1 Доп. 73, Р. 14, о. 1, поз. 552 | BM36: 72 | BN36: 0 | BP36: 0 | BQ36: 40 | BR36: 0 | BS36: 1 | BT36: 1 | BU36: 1 | BV36: 1 | BW36: 1 | BX36: 1 | BZ36: 90 | CA36: 46 | CE36: 30 | CF36: 0 | CG36: 0 | CM36: 0 | CO36: 0 | CP36: =(P36+Q36+S36) -> 40.05 | CQ36: =ROUND((ROUND((AC36*AW36*1),2)*BC36),2) -> 40.05 | CR36: =(ROUND((ROUND(((ET36)*AV36*1),2)*BB36),2)+ROUND((ROUND(((AE36-(EU36))*AV36*1),2)*BS36),2)) -> 0 | CS36: =ROUND((ROUND((AE36*AV36*1),2)*BS36),2) -> 0 | CT36: =ROUND((ROUND((AF36*AV36*1),2)*BA36),2) -> 0 | CU36: =AG36 -> 0 | CV36: =(AH36*AV36) -> 0 | CW36: =AI36 -> 0 | CX36: =AJ36 -> 0 | CY36: =(((S36+R36)*AT36)/100) -> 0 | CZ36: =(((S36+R36)*AU36)/100) -> 0 | DN36: 0 | DO36: 0 | DP36: 1 | DQ36: 1 | DU36: 1010 | DV36: шт. | DW36: шт. | DX36: 1 | EE36: 58162634 | EF36: 40 | EG36: Монтаж оборудования | EH36: 0 | EJ36: 2 | EK36: 72 | EL36: ТСН-2001.4-11. Приборы и средства автоматизации и вычислительной техники | EM36: ТСН-2001.4-11-1 | EQ36: 0 | ER36: 40.05 | ES36: 40.05 | ET36: 0 | EU36: 0 | EV36: 0 | EW36: 0 | EX36: 0 | FQ36: 0 | FR36: 0 | FS36: 0 | FX36: 90 | FY36: 46 | GD36: 1 | GF36: -1000652985 | GG36: 2 | GH36: 1 | GI36: -2 | GJ36: 0 | GK36: 0 | GL36: =ROUND(IF(AND(BH36=3,BI36=3,FS36<>0),P36,0),2) -> 0 | GM36: =ROUND(O36+X36+Y36,2)+GX36 -> 40.05 | GN36: =IF(OR(BI36=0,BI36=1),GM36-GX36,0) -> 0 | GO36: =IF(BI36=2,GM36-GX36,0) -> 40.05 | GP36: =IF(BI36=4,GM36-GX36,0) -> 0 | GR36: 0 | GS36: 3 | GT36: 0 | GV36: =ROUND((GT36),6) -> 0 | GW36: 1 | GX36: =ROUND(HC36*I36,2) -> 0 | HA36: 0 | HB36: 0 | HC36: =GV36*GW36 -> 0 | HS36: 0 | IK36: 0
A37: 18 | B37: 1 | E37: 2,2 | F37: 1.14-1-552 | G37: Ответвитель направленный, абонентский, типа ОАТ 412 | H37: шт. | I37: =I33*J37 -> 1 | J37: 0.33333333 | K37: 0.3333333 | O37: =ROUND(CP37,2) -> 113.34 | P37: =ROUND((ROUND((AC37*AW37*I37),2)*BC37),2) -> 113.34 | Q37: =(ROUND((ROUND(((ET37)*AV37*I37),2)*BB37),2)+ROUND((ROUND(((AE37-(EU37))*AV37*I37),2)*BS37),2)) -> 0 | R37: =ROUND((ROUND((AE37*AV37*I37),2)*BS37),2) -> 0 | S37: =ROUND((ROUND((AF37*AV37*I37),2)*BA37),2) -> 0 | T37: =ROUND(CU37*I37,2) -> 0 | U37: =CV37*I37 -> 0 | V37: =CW37*I37 -> 0 | W37: =ROUND(CX37*I37,2) -> 0 | X37: =ROUND(CY37,2) -> 0 | Y37: =ROUND(CZ37,2) -> 0 | AA37: 56503350 | AB37: =ROUND((AC37+AD37+AF37),6) -> 40.05 | AC37: =ROUND((ES37),6) -> 40.05 | AD37: =ROUND((((ET37)-(EU37))+AE37),6) -> 0 | AE37: =ROUND((EU37),6) -> 0 | AF37: =ROUND((EV37),6) -> 0 | AG37: =ROUND((AP37),6) -> 0 | AH37: =(EW37) -> 0 | AI37: =(EX37) -> 0 | AJ37: =(AS37) -> 0 | AK37: 40.05 | AL37: 40.05 | AM37: 0 | AN37: 0 | AO37: 0 | AP37: 0 | AQ37: 0 | AR37: 0 | AS37: 0 | AT37: 90 | AU37: 46 | AV37: 1 | AW37: 1 | AZ37: 1 | BA37: 1 | BB37: 1 | BC37: 2.83 | BH37: 3 | BI37: 2 | BJ37: ТСН-2001.1 Доп. 73, Р. 14, о. 1, поз. 552 | BM37: 72 | BN37: 0 | BO37: 1.14-1-552 | BP37: 1 | BQ37: 40 | BR37: 0 | BS37: 1 | BT37: 1 | BU37: 1 | BV37: 1 | BW37: 1 | BX37: 1 | BZ37: 90 | CA37: 46 | CE37: 30 | CF37: 0 | CG37: 0 | CM37: 0 | CO37: 0 | CP37: =(P37+Q37+S37) -> 113.34 | CQ37: =ROUND((ROUND((AC37*AW37*1),2)*BC37),2) -> 113.34 | CR37: =(ROUND((ROUND(((ET37)*AV37*1),2)*BB37),2)+ROUND((ROUND(((AE37-(EU37))*AV37*1),2)*BS37),2)) -> 0 | CS37: =ROUND((ROUND((AE37*AV37*1),2)*BS37),2) -> 0 | CT37: =ROUND((ROUND((AF37*AV37*1),2)*BA37),2) -> 0 | CU37: =AG37 -> 0 | CV37: =(AH37*AV37) -> 0 | CW37: =AI37 -> 0 | CX37: =AJ37 -> 0 | CY37: =(((S37+R37)*AT37)/100) -> 0 | CZ37: =(((S37+R37)*AU37)/100) -> 0 | DN37: 0 | DO37: 0 | DP37: 1 | DQ37: 1 | DU37: 1010 | DV37: шт. | DW37: шт. | DX37: 1 | EE37: 58162634 | EF37: 40 | EG37: Монтаж оборудования | EH37: 0 | EJ37: 2 | EK37: 72 | EL37: ТСН-2001.4-11. Приборы и средства автоматизации и вычислительной техники | EM37: ТСН-2001.4-11-1 | EQ37: 0 | ER37: 40.05 | ES37: 40.05 | ET37: 0 | EU37: 0 | EV37: 0 | EW37: 0 | EX37: 0 | FQ37: 0 | FR37: 0 | FS37: 0 | FX37: 90 | FY37: 46 | GD37: 1 | GF37: -1000652985 | GG37: 2 | GH37: 1 | GI37: 2 | GJ37: 0 | GK37: 0 | GL37: =ROUND(IF(AND(BH37=3,BI37=3,FS37<>0),P37,0),2) -> 0 | GM37: =ROUND(O37+X37+Y37,2)+GX37 -> 113.34 | GN37: =IF(OR(BI37=0,BI37=1),GM37-GX37,0) -> 0 | GO37: =IF(BI37=2,GM37-GX37,0) -> 113.34 | GP37: =IF(BI37=4,GM37-GX37,0) -> 0 | GR37: 0 | GS37: 3 | GT37: 0 | GV37: =ROUND((GT37),6) -> 0 | GW37: 1 | GX37: =ROUND(HC37*I37,2) -> 0 | HA37: 0 | HB37: 0 | HC37: =GV37*GW37 -> 0 | HS37: 0 | IK37: 0
A38: 18 | B38: 1 | E38: 2,3 | F38: 1.14-1-553 | G38: Ответвитель направленный, абонентский, типа ОАТ 416 | H38: шт. | I38: =I32*J38 -> 1 | J38: 0.33333333 | K38: 0.3333333 | O38: =ROUND(CP38,2) -> 40.17 | P38: =ROUND((ROUND((AC38*AW38*I38),2)*BC38),2) -> 40.17 | Q38: =(ROUND((ROUND(((ET38)*AV38*I38),2)*BB38),2)+ROUND((ROUND(((AE38-(EU38))*AV38*I38),2)*BS38),2)) -> 0 | R38: =ROUND((ROUND((AE38*AV38*I38),2)*BS38),2) -> 0 | S38: =ROUND((ROUND((AF38*AV38*I38),2)*BA38),2) -> 0 | T38: =ROUND(CU38*I38,2) -> 0 | U38: =CV38*I38 -> 0 | V38: =CW38*I38 -> 0 | W38: =ROUND(CX38*I38,2) -> 0 | X38: =ROUND(CY38,2) -> 0 | Y38: =ROUND(CZ38,2) -> 0 | AA38: 56503348 | AB38: =ROUND((AC38+AD38+AF38),6) -> 40.17 | AC38: =ROUND((ES38),6) -> 40.17 | AD38: =ROUND((((ET38)-(EU38))+AE38),6) -> 0 | AE38: =ROUND((EU38),6) -> 0 | AF38: =ROUND((EV38),6) -> 0 | AG38: =ROUND((AP38),6) -> 0 | AH38: =(EW38) -> 0 | AI38: =(EX38) -> 0 | AJ38: =(AS38) -> 0 | AK38: 40.17 | AL38: 40.17 | AM38: 0 | AN38: 0 | AO38: 0 | AP38: 0 | AQ38: 0 | AR38: 0 | AS38: 0 | AT38: 90 | AU38: 46 | AV38: 1 | AW38: 1 | AZ38: 1 | BA38: 1 | BB38: 1 | BC38: 1 | BH38: 3 | BI38: 2 | BJ38: ТСН-2001.1 Доп. 73, Р. 14, о. 1, поз. 553 | BM38: 72 | BN38: 0 | BP38: 0 | BQ38: 40 | BR38: 0 | BS38: 1 | BT38: 1 | BU38: 1 | BV38: 1 | BW38: 1 | BX38: 1 | BZ38: 90 | CA38: 46 | CE38: 30 | CF38: 0 | CG38: 0 | CM38: 0 | CO38: 0 | CP38: =(P38+Q38+S38) -> 40.17 | CQ38: =ROUND((ROUND((AC38*AW38*1),2)*BC38),2) -> 40.17 | CR38: =(ROUND((ROUND(((ET38)*AV38*1),2)*BB38),2)+ROUND((ROUND(((AE38-(EU38))*AV38*1),2)*BS38),2)) -> 0 | CS38: =ROUND((ROUND((AE38*AV38*1),2)*BS38),2) -> 0 | CT38: =ROUND((ROUND((AF38*AV38*1),2)*BA38),2) -> 0 | CU38: =AG38 -> 0 | CV38: =(AH38*AV38) -> 0 | CW38: =AI38 -> 0 | CX38: =AJ38 -> 0 | CY38: =(((S38+R38)*AT38)/100) -> 0 | CZ38: =(((S38+R38)*AU38)/100) -> 0 | DN38: 0 | DO38: 0 | DP38: 1 | DQ38: 1 | DU38: 1010 | DV38: шт. | DW38: шт. | DX38: 1 | EE38: 58162634 | EF38: 40 | EG38: Монтаж оборудования | EH38: 0 | EJ38: 2 | EK38: 72 | EL38: ТСН-2001.4-11. Приборы и средства автоматизации и вычислительной техники | EM38: ТСН-2001.4-11-1 | EQ38: 0 | ER38: 40.17 | ES38: 40.17 | ET38: 0 | EU38: 0 | EV38: 0 | EW38: 0 | EX38: 0 | FQ38: 0 | FR38: 0 | FS38: 0 | FX38: 90 | FY38: 46 | GD38: 1 | GF38: -872873899 | GG38: 2 | GH38: 1 | GI38: -2 | GJ38: 0 | GK38: 0 | GL38: =ROUND(IF(AND(BH38=3,BI38=3,FS38<>0),P38,0),2) -> 0 | GM38: =ROUND(O38+X38+Y38,2)+GX38 -> 40.17 | GN38: =IF(OR(BI38=0,BI38=1),GM38-GX38,0) -> 0 | GO38: =IF(BI38=2,GM38-GX38,0) -> 40.17 | GP38: =IF(BI38=4,GM38-GX38,0) -> 0 | GR38: 0 | GS38: 3 | GT38: 0 | GV38: =ROUND((GT38),6) -> 0 | GW38: 1 | GX38: =ROUND(HC38*I38,2) -> 0 | HA38: 0 | HB38: 0 | HC38: =GV38*GW38 -> 0 | HS38: 0 | IK38: 0
A39: 18 | B39: 1 | E39: 2,3 | F39: 1.14-1-553 | G39: Ответвитель направленный, абонентский, типа ОАТ 416 | H39: шт. | I39: =I33*J39 -> 1 | J39: 0.33333333 | K39: 0.3333333 | O39: =ROUND(CP39,2) -> 113.68 | P39: =ROUND((ROUND((AC39*AW39*I39),2)*BC39),2) -> 113.68 | Q39: =(ROUND((ROUND(((ET39)*AV39*I39),2)*BB39),2)+ROUND((ROUND(((AE39-(EU39))*AV39*I39),2)*BS39),2)) -> 0 | R39: =ROUND((ROUND((AE39*AV39*I39),2)*BS39),2) -> 0 | S39: =ROUND((ROUND((AF39*AV39*I39),2)*BA39),2) -> 0 | T39: =ROUND(CU39*I39,2) -> 0 | U39: =CV39*I39 -> 0 | V39: =CW39*I39 -> 0 | W39: =ROUND(CX39*I39,2) -> 0 | X39: =ROUND(CY39,2) -> 0 | Y39: =ROUND(CZ39,2) -> 0 | AA39: 56503350 | AB39: =ROUND((AC39+AD39+AF39),6) -> 40.17 | AC39: =ROUND((ES39),6) -> 40.17 | AD39: =ROUND((((ET39)-(EU39))+AE39),6) -> 0 | AE39: =ROUND((EU39),6) -> 0 | AF39: =ROUND((EV39),6) -> 0 | AG39: =ROUND((AP39),6) -> 0 | AH39: =(EW39) -> 0 | AI39: =(EX39) -> 0 | AJ39: =(AS39) -> 0 | AK39: 40.17 | AL39: 40.17 | AM39: 0 | AN39: 0 | AO39: 0 | AP39: 0 | AQ39: 0 | AR39: 0 | AS39: 0 | AT39: 90 | AU39: 46 | AV39: 1 | AW39: 1 | AZ39: 1 | BA39: 1 | BB39: 1 | BC39: 2.83 | BH39: 3 | BI39: 2 | BJ39: ТСН-2001.1 Доп. 73, Р. 14, о. 1, поз. 553 | BM39: 72 | BN39: 0 | BO39: 1.14-1-553 | BP39: 1 | BQ39: 40 | BR39: 0 | BS39: 1 | BT39: 1 | BU39: 1 | BV39: 1 | BW39: 1 | BX39: 1 | BZ39: 90 | CA39: 46 | CE39: 30 | CF39: 0 | CG39: 0 | CM39: 0 | CO39: 0 | CP39: =(P39+Q39+S39) -> 113.68 | CQ39: =ROUND((ROUND((AC39*AW39*1),2)*BC39),2) -> 113.68 | CR39: =(ROUND((ROUND(((ET39)*AV39*1),2)*BB39),2)+ROUND((ROUND(((AE39-(EU39))*AV39*1),2)*BS39),2)) -> 0 | CS39: =ROUND((ROUND((AE39*AV39*1),2)*BS39),2) -> 0 | CT39: =ROUND((ROUND((AF39*AV39*1),2)*BA39),2) -> 0 | CU39: =AG39 -> 0 | CV39: =(AH39*AV39) -> 0 | CW39: =AI39 -> 0 | CX39: =AJ39 -> 0 | CY39: =(((S39+R39)*AT39)/100) -> 0 | CZ39: =(((S39+R39)*AU39)/100) -> 0 | DN39: 0 | DO39: 0 | DP39: 1 | DQ39: 1 | DU39: 1010 | DV39: шт. | DW39: шт. | DX39: 1 | EE39: 58162634 | EF39: 40 | EG39: Монтаж оборудования | EH39: 0 | EJ39: 2 | EK39: 72 | EL39: ТСН-2001.4-11. Приборы и средства автоматизации и вычислительной техники | EM39: ТСН-2001.4-11-1 | EQ39: 0 | ER39: 40.17 | ES39: 40.17 | ET39: 0 | EU39: 0 | EV39: 0 | EW39: 0 | EX39: 0 | FQ39: 0 | FR39: 0 | FS39: 0 | FX39: 90 | FY39: 46 | GD39: 1 | GF39: -872873899 | GG39: 2 | GH39: 1 | GI39: 2 | GJ39: 0 | GK39: 0 | GL39: =ROUND(IF(AND(BH39=3,BI39=3,FS39<>0),P39,0),2) -> 0 | GM39: =ROUND(O39+X39+Y39,2)+GX39 -> 113.68 | GN39: =IF(OR(BI39=0,BI39=1),GM39-GX39,0) -> 0 | GO39: =IF(BI39=2,GM39-GX39,0) -> 113.68 | GP39: =IF(BI39=4,GM39-GX39,0) -> 0 | GR39: 0 | GS39: 3 | GT39: 0 | GV39: =ROUND((GT39),6) -> 0 | GW39: 1 | GX39: =ROUND(HC39*I39,2) -> 0 | HA39: 0 | HB39: 0 | HC39: =GV39*GW39 -> 0 | HS39: 0 | IK39: 0
A41: 51 | B41: =B24 -> 1 | C41: =A24 -> 4 | D41: =ROW(A24) -> 24 | F41: =IF(F24<>"",F24,"") | G41: =IF(G24<>"",G24,"") -> Оборудование | H41: 0 | O41: =ROUND(AB41,2) -> 9058.21 | P41: =ROUND(AC41,2) -> 8911.2 | Q41: =ROUND(AD41,2) -> 0 | R41: =ROUND(AE41,2) -> 0 | S41: =ROUND(AF41,2) -> 147.01 | T41: =ROUND(AG41,2) -> 0 | U41: =AH41 -> 10.60213 | V41: =AI41 -> 0 | W41: =ROUND(AJ41,2) -> 0 | X41: =ROUND(AK41,2) -> 138.98 | Y41: =ROUND(AL41,2) -> 76.98 | AB41: =ROUND(SUMIF(AA28:AA39,"=56503348",O28:O39),2) -> 9058.21 | AC41: =ROUND(SUMIF(AA28:AA39,"=56503348",P28:P39),2) -> 8911.2 | AD41: =ROUND(SUMIF(AA28:AA39,"=56503348",Q28:Q39),2) -> 0 | AE41: =ROUND(SUMIF(AA28:AA39,"=56503348",R28:R39),2) -> 0 | AF41: =ROUND(SUMIF(AA28:AA39,"=56503348",S28:S39),2) -> 147.01 | AG41: =ROUND(SUMIF(AA28:AA39,"=56503348",T28:T39),2) -> 0 | AH41: =SUMIF(AA28:AA39,"=56503348",U28:U39) -> 10.60213 | AI41: =SUMIF(AA28:AA39,"=56503348",V28:V39) -> 0 | AJ41: =ROUND(SUMIF(AA28:AA39,"=56503348",W28:W39),2) -> 0 | AK41: =ROUND(SUMIF(AA28:AA39,"=56503348",X28:X39),2) -> 138.98 | AL41: =ROUND(SUMIF(AA28:AA39,"=56503348",Y28:Y39),2) -> 76.98 | AO41: =ROUND(BX41,2) -> 0 | AP41: =ROUND(BY41,2) -> 8788.39 | AQ41: =ROUND(BZ41,2) -> 0 | AR41: =ROUND(CA41,2) -> 9274.17 | AS41: =ROUND(CB41,2) -> 0 | AT41: =ROUND(CC41,2) -> 485.78 | AU41: =ROUND(CD41,2) -> 0 | AV41: =ROUND(CE41,2) -> 8911.2 | ... BD41: =ROUND(CM41,2) -> 0 | BX41: =ROUND(SUMIF(AA28:AA39,"=56503348",FQ28:FQ39),2) -> 0 | BY41: =ROUND(SUMIF(AA28:AA39,"=56503348",FR28:FR39),2) -> 8788.39 | BZ41: =ROUND(SUMIF(AA28:AA39,"=56503348",GL28:GL39),2) -> 0 | CA41: =ROUND(SUMIF(AA28:AA39,"=56503348",GM28:GM39),2) -> 9274.17 | CB41: =ROUND(SUMIF(AA28:AA39,"=56503348",GN28:GN39),2) -> 0 | CC41: =ROUND(SUMIF(AA28:AA39,"=56503348",GO28:GO39),2) -> 485.78 | CD41: =ROUND(SUMIF(AA28:AA39,"=56503348",GP28:GP39),2) -> 0 | CE41: =AC41-BX41 -> 8911.2 | CF41: =AC41-BY41 -> 122.81 | CG41: =BX41-BZ41 -> 0 | CH41: =AC41-BX41-BY41+BZ41 -> 122.81 | CI41: =BY41-BZ41 -> 8788.39 | CJ41: =ROUND(SUMIF(AA28:AA39,"=56503348",GX28:GX39),2) -> 0 | CK41: =ROUND(SUMIF(AA28:AA39,"=56503348",GY28:GY39),2) -> 0 | CL41: =ROUND(SUMIF(AA28:AA39,"=56503348",GZ28:GZ39),2) -> 0 | CM41: =ROUND(SUMIF(AA28:AA39,"=56503348",HD28:HD39),2) -> 0 | DG41: =ROUND(DT41,2) -> 75768.05 | DH41: =ROUND(DU41,2) -> 67683.97 | DI41: =ROUND(DV41,2) -> 0 | DJ41: =ROUND(DW41,2) -> 0 | DK41: =ROUND(DX41,2) -> 8084.08 | DL41: =ROUND(DY41,2) -> 0 | DM41: =DZ41 -> 10.60213 | DN41: =EA41 -> 0 | DO41: =ROUND(EB41,2) -> 0 | DP41: =ROUND(EC41,2) -> 7642.84 | DQ41: =ROUND(ED41,2) -> 4232.71 | DT41: =ROUND(SUMIF(AA28:AA39,"=56503350",O28:O39),2) -> 75768.05 | DU41: =ROUND(SUMIF(AA28:AA39,"=56503350",P28:P39),2) -> 67683.97 | DV41: =ROUND(SUMIF(AA28:AA39,"=56503350",Q28:Q39),2) -> 0 | DW41: =ROUND(SUMIF(AA28:AA39,"=56503350",R28:R39),2) -> 0 | DX41: =ROUND(SUMIF(AA28:AA39,"=56503350",S28:S39),2) -> 8084.08 | DY41: =ROUND(SUMIF(AA28:AA39,"=56503350",T28:T39),2) -> 0 | DZ41: =SUMIF(AA28:AA39,"=56503350",U28:U39) -> 10.60213 | EA41: =SUMIF(AA28:AA39,"=56503350",V28:V39) -> 0 | EB41: =ROUND(SUMIF(AA28:AA39,"=56503350",W28:W39),2) -> 0 | EC41: =ROUND(SUMIF(AA28:AA39,"=56503350",X28:X39),2) -> 7642.84 | ED41: =ROUND(SUMIF(AA28:AA39,"=56503350",Y28:Y39),2) -> 4232.71 | EG41: =ROUND(FP41,2) -> 0 | EH41: =ROUND(FQ41,2) -> 67319.07 | EI41: =ROUND(FR41,2) -> 0 | EJ41: =ROUND(FS41,2) -> 87643.6 | EK41: =ROUND(FT41,2) -> 0 | EL41: =ROUND(FU41,2) -> 20324.53 | EM41: =ROUND(FV41,2) -> 0 | EN41: =ROUND(FW41,2) -> 67683.97 | ... EV41: =ROUND(GE41,2) -> 0 | FP41: =ROUND(SUMIF(AA28:AA39,"=56503350",FQ28:FQ39),2) -> 0 | FQ41: =ROUND(SUMIF(AA28:AA39,"=56503350",FR28:FR39),2) -> 67319.07 | FR41: =ROUND(SUMIF(AA28:AA39,"=56503350",GL28:GL39),2) -> 0 | FS41: =ROUND(SUMIF(AA28:AA39,"=56503350",GM28:GM39),2) -> 87643.6 | FT41: =ROUND(SUMIF(AA28:AA39,"=56503350",GN28:GN39),2) -> 0 | FU41: =ROUND(SUMIF(AA28:AA39,"=56503350",GO28:GO39),2) -> 20324.53 | FV41: =ROUND(SUMIF(AA28:AA39,"=56503350",GP28:GP39),2) -> 0 | FW41: =DU41-FP41 -> 67683.97 | FX41: =DU41-FQ41 -> 364.9 | FY41: =FP41-FR41 -> 0 | FZ41: =DU41-FP41-FQ41+FR41 -> 364.9 | GA41: =FQ41-FR41 -> 67319.07 | GB41: =ROUND(SUMIF(AA28:AA39,"=56503350",GX28:GX39),2) -> 0 | GC41: =ROUND(SUMIF(AA28:AA39,"=56503350",GY28:GY39),2) -> 0 | GD41: =ROUND(SUMIF(AA28:AA39,"=56503350",GZ28:GZ39),2) -> 0 | GE41: =ROUND(SUMIF(AA28:AA39,"=56503350",HD28:HD39),2) -> 0 | GX41: 0
A43: 50 | B43: 0 | C43: 0 | D43: 1 | E43: 201 | F43: =ROUND(Source!O41,O43) -> 9058.21 | G43: ПЗ | H43: Прямые затраты | K43: 201 | L43: 1 | M43: 3 | O43: 2 | P43: =ROUND(Source!DG41,O43) -> 75768.05 | W43: 9058.21 | X43: 1 | Y43: 9058.21 | Z43: 75768.05 | AA43: 1 | AB43: 75768.05
A44: 50 | B44: 0 | C44: 0 | D44: 1 | E44: 202 | F44: =ROUND(Source!P41,O44) -> 8911.2 | G44: СтМатОб | H44: Стоимость материальных ресурсов (всего) | K44: 202 | L44: 2 | M44: 3 | O44: 2 | P44: =ROUND(Source!DH41,O44) -> 67683.97 | W44: 8911.2 | X44: 1 | Y44: 8911.2 | Z44: 67683.97 | AA44: 1 | AB44: 67683.97
A45: 50 | B45: 0 | C45: 0 | D45: 1 | E45: 222 | F45: =ROUND(Source!AO41,O45) -> 0 | G45: СтМатОбЗак | H45: Стоимость материалов и оборудования заказчика | K45: 222 | L45: 3 | M45: 3 | O45: 2 | P45: =ROUND(Source!EG41,O45) -> 0 | W45: 0 | X45: 1 | Y45: 0 | Z45: 0 | AA45: 1 | AB45: 0
A46: 50 | B46: 0 | C46: 0 | D46: 1 | E46: 225 | F46: =ROUND(Source!AV41,O46) -> 8911.2 | G46: СтМатОбПод | H46: Стоимость материалов и оборудования подрядчика | K46: 225 | L46: 4 | M46: 3 | O46: 2 | P46: =ROUND(Source!EN41,O46) -> 67683.97 | W46: 8911.2 | X46: 1 | Y46: 8911.2 | Z46: 67683.97 | AA46: 1 | AB46: 67683.97
A47: 50 | B47: 0 | C47: 0 | D47: 1 | E47: 226 | F47: =ROUND(Source!AW41,O47) -> 122.81 | G47: СтМат | H47: Стоимость материалов (всего) | K47: 226 | L47: 5 | M47: 3 | O47: 2 | P47: =ROUND(Source!EO41,O47) -> 364.9 | W47: 122.81 | X47: 1 | Y47: 122.81 | Z47: 364.9 | AA47: 1 | AB47: 364.9
A48: 50 | B48: 0 | C48: 0 | D48: 1 | E48: 227 | F48: =ROUND(Source!AX41,O48) -> 0 | G48: СтМатЗак | H48: Стоимость материалов заказчика | K48: 227 | L48: 6 | M48: 3 | O48: 2 | P48: =ROUND(Source!EP41,O48) -> 0 | W48: 0 | X48: 1 | Y48: 0 | Z48: 0 | AA48: 1 | AB48: 0
A49: 50 | B49: 0 | C49: 0 | D49: 1 | E49: 228 | F49: =ROUND(Source!AY41,O49) -> 122.81 | G49: СтМатПод | H49: Стоимость материалов подрядчика | K49: 228 | L49: 7 | M49: 3 | O49: 2 | P49: =ROUND(Source!EQ41,O49) -> 364.9 | W49: 122.81 | X49: 1 | Y49: 122.81 | Z49: 364.9 | AA49: 1 | AB49: 364.9
A50: 50 | B50: 0 | C50: 0 | D50: 1 | E50: 216 | F50: =ROUND(Source!AP41,O50) -> 8788.39 | G50: Оборуд | H50: Стоимость оборудования (всего) | K50: 216 | L50: 8 | M50: 3 | O50: 2 | P50: =ROUND(Source!EH41,O50) -> 67319.07 | W50: 8788.39 | X50: 1 | Y50: 8788.39 | Z50: 67319.07 | AA50: 1 | AB50: 67319.07
A51: 50 | B51: 0 | C51: 0 | D51: 1 | E51: 223 | F51: =ROUND(Source!AQ41,O51) -> 0 | G51: ОборудЗак | H51: Стоимость оборудования заказчика | K51: 223 | L51: 9 | M51: 3 | O51: 2 | P51: =ROUND(Source!EI41,O51) -> 0 | W51: 0 | X51: 1 | Y51: 0 | Z51: 0 | AA51: 1 | AB51: 0
A52: 50 | B52: 0 | C52: 0 | D52: 1 | E52: 229 | F52: =ROUND(Source!AZ41,O52) -> 8788.39 | G52: ОборудПод | H52: Стоимость оборудования подрядчика | K52: 229 | L52: 10 | M52: 3 | O52: 2 | P52: =ROUND(Source!ER41,O52) -> 67319.07 | W52: 8788.39 | X52: 1 | Y52: 8788.39 | Z52: 67319.07 | AA52: 1 | AB52: 67319.07
A53: 50 | B53: 0 | C53: 0 | D53: 1 | E53: 203 | F53: =ROUND(Source!Q41,O53) -> 0 | G53: ЭММ | H53: Эксплуатация машин | K53: 203 | L53: 11 | M53: 3 | O53: 2 | P53: =ROUND(Source!DI41,O53) -> 0 | W53: 0 | X53: 1 | Y53: 0 | Z53: 0 | AA53: 1 | AB53: 0
A54: 50 | B54: 0 | C54: 0 | D54: 1 | E54: 231 | F54: =ROUND(Source!BB41,O54) -> 0 | G54: ЭММсНРиСП | H54: Эксплуатация машин по ТСН-2001.16 | K54: 231 | L54: 12 | M54: 3 | O54: 2 | P54: =ROUND(Source!ET41,O54) -> 0 | W54: 0 | X54: 1 | Y54: 0 | Z54: 0 | AA54: 1 | AB54: 0
A55: 50 | B55: 0 | C55: 0 | D55: 1 | E55: 204 | F55: =ROUND(Source!R41,O55) -> 0 | G55: ЗПМ | H55: ЗП машинистов | K55: 204 | L55: 13 | M55: 3 | O55: 2 | P55: =ROUND(Source!DJ41,O55) -> 0 | W55: 0 | X55: 1 | Y55: 0 | Z55: 0 | AA55: 1 | AB55: 0
A56: 50 | B56: 0 | C56: 0 | D56: 1 | E56: 205 | F56: =ROUND(Source!S41,O56) -> 147.01 | G56: ОЗП | H56: Основная ЗП рабочих | K56: 205 | L56: 14 | M56: 3 | O56: 2 | P56: =ROUND(Source!DK41,O56) -> 8084.08 | W56: 147.01 | X56: 1 | Y56: 147.01 | Z56: 8084.08 | AA56: 1 | AB56: 8084.08
A57: 50 | B57: 0 | C57: 0 | D57: 1 | E57: 232 | F57: =ROUND(Source!BC41,O57) -> 0 | G57: ОЗПсНРиСП | H57: Основная ЗП рабочих по ТСН-2001.16 | K57: 232 | L57: 15 | M57: 3 | O57: 2 | P57: =ROUND(Source!EU41,O57) -> 0 | W57: 0 | X57: 1 | Y57: 0 | Z57: 0 | AA57: 1 | AB57: 0
A58: 50 | B58: 0 | C58: 0 | D58: 1 | E58: 214 | F58: =ROUND(Source!AS41,O58) -> 0 | G58: Строит | H58: Строительные работы с НР и СП | K58: 214 | L58: 16 | M58: 3 | O58: 2 | P58: =ROUND(Source!EK41,O58) -> 0 | W58: 0 | X58: 1 | Y58: 0 | Z58: 0 | AA58: 1 | AB58: 0
A59: 50 | B59: 0 | C59: 0 | D59: 1 | E59: 215 | F59: =ROUND(Source!AT41,O59) -> 485.78 | G59: Монтаж | H59: Монтажные работы с НР и СП | K59: 215 | L59: 17 | M59: 3 | O59: 2 | P59: =ROUND(Source!EL41,O59) -> 20324.53 | W59: 485.78 | X59: 1 | Y59: 485.78 | Z59: 20324.53 | AA59: 1 | AB59: 20324.53
A60: 50 | B60: 0 | C60: 0 | D60: 1 | E60: 217 | F60: =ROUND(Source!AU41,O60) -> 0 | G60: Прочие | H60: Прочие работы с НР и СП | K60: 217 | L60: 18 | M60: 3 | O60: 2 | P60: =ROUND(Source!EM41,O60) -> 0 | W60: 0 | X60: 1 | Y60: 0 | Z60: 0 | AA60: 1 | AB60: 0
A61: 50 | B61: 0 | C61: 0 | D61: 1 | E61: 230 | F61: =ROUND(Source!BA41,O61) -> 0 | G61: ПрочиеЗатр | H61: Прочие затраты по ТСН-2001.16 | K61: 230 | L61: 19 | M61: 3 | O61: 2 | P61: =ROUND(Source!ES41,O61) -> 0 | W61: 0 | X61: 1 | Y61: 0 | Z61: 0 | AA61: 1 | AB61: 0
A62: 50 | B62: 0 | C62: 0 | D62: 1 | E62: 206 | F62: =ROUND(Source!T41,O62) -> 0 | G62: ВозврМат | H62: Возврат материалов | K62: 206 | L62: 20 | M62: 3 | O62: 2 | P62: =ROUND(Source!DL41,O62) -> 0 | W62: 0 | X62: 1 | Y62: 0 | Z62: 0 | AA62: 1 | AB62: 0
A63: 50 | B63: 0 | C63: 0 | D63: 1 | E63: 207 | F63: =Source!U41 -> 10.60213 | G63: ТрудСтр | H63: Трудозатраты строителей | K63: 207 | L63: 21 | M63: 3 | O63: -1 | P63: =Source!DM41 -> 10.60213 | W63: 10.60213 | X63: 1 | Y63: 10.60213 | Z63: 10.60213 | AA63: 1 | AB63: 10.60213
A64: 50 | B64: 0 | C64: 0 | D64: 1 | E64: 208 | F64: =Source!V41 -> 0 | G64: ТрудМаш | H64: Трудозатраты машинистов | K64: 208 | L64: 22 | M64: 3 | O64: -1 | P64: =Source!DN41 -> 0 | W64: 0 | X64: 1 | Y64: 0 | Z64: 0 | AA64: 1 | AB64: 0
A65: 50 | B65: 0 | C65: 0 | D65: 1 | E65: 209 | F65: =ROUND(Source!W41,O65) -> 0 | G65: ТранспМат | H65: Транспорт материалов | K65: 209 | L65: 23 | M65: 3 | O65: 2 | P65: =ROUND(Source!DO41,O65) -> 0 | W65: 0 | X65: 1 | Y65: 0 | Z65: 0 | AA65: 1 | AB65: 0
A66: 50 | B66: 0 | C66: 0 | D66: 1 | E66: 233 | F66: =ROUND(Source!BD41,O66) -> 0 | G66: Перевозка | H66: Перевозка грузов | K66: 233 | L66: 24 | M66: 3 | O66: 2 | P66: =ROUND(Source!EV41,O66) -> 0 | W66: 0 | X66: 1 | Y66: 0 | Z66: 0 | AA66: 1 | AB66: 0
A67: 50 | B67: 0 | C67: 0 | D67: 1 | E67: 210 | F67: =ROUND(Source!X41,O67) -> 138.98 | G67: НР | H67: Накладные расходы | K67: 210 | L67: 25 | M67: 3 | O67: 2 | P67: =ROUND(Source!DP41,O67) -> 7642.84 | W67: 138.98 | X67: 1 | Y67: 138.98 | Z67: 7642.84 | AA67: 1 | AB67: 7642.84
A68: 50 | B68: 0 | C68: 0 | D68: 1 | E68: 211 | F68: =ROUND(Source!Y41,O68) -> 76.98 | G68: СмПриб | H68: Сметная прибыль | K68: 211 | L68: 26 | M68: 3 | O68: 2 | P68: =ROUND(Source!DQ41,O68) -> 4232.71 | W68: 76.98 | X68: 1 | Y68: 76.98 | Z68: 4232.71 | AA68: 1 | AB68: 4232.71
A69: 50 | B69: 0 | C69: 0 | D69: 1 | E69: 224 | F69: =ROUND(Source!AR41,O69) -> 9274.17 | G69: Всего | H69: Всего с НР и СП | K69: 224 | L69: 27 | M69: 3 | O69: 2 | P69: =ROUND(Source!EJ41,O69) -> 87643.6 | W69: 9274.17 | X69: 1 | Y69: 9274.17 | Z69: 87643.6 | AA69: 1 | AB69: 87643.6
A71: 4 | B71: 1 | D71: =ROW(A130) -> 130 | G71: Материалы | I71: 0 | K71: -1 | S71: 0 | T71: 0 | V71: 0 | BX71: 0 | CJ71: 0
A73: 52 | B73: =B130 -> 1 | C73: =C130 -> 4 | D73: =D130 -> 71 | E73: =E130 -> 0 | F73: =F130 | G73: =G130 -> Материалы | O73: =O130 -> 11853.84 | P73: =P130 -> 11183.01 | Q73: =Q130 -> 19.37 | R73: =R130 -> 0.37 | S73: =S130 -> 651.46 | T73: =T130 -> 0 | U73: =U130 -> 52.936993 | V73: =V130 -> 0 | ... GX73: =GX130 -> 0
A75: 17 | B75: 1 | C75: =ROW(SmtRes!A5) -> 5 | D75: =ROW(EtalonRes!A15) -> 15 | E75: 3 | F75: 4.8-243-11 | G75: Монтаж розетки штепсельной трехполюсной | H75: 100 шт. | I75: =ROUND(5/100,9) -> 0.05 | J75: 0 | K75: =ROUND(5/100,9) -> 0.05 | O75: =ROUND(CP75,2) -> 93.77 | P75: =ROUND((ROUND((AC75*AW75*I75),2)*BC75),2) -> 42.85 | Q75: =(ROUND((ROUND((((ET75*1.1))*AV75*I75),2)*BB75),2)+ROUND((ROUND(((AE75-((EU75*1.1)))*AV75*I75),2)*BS75),2)) -> 0.53 | R75: =ROUND((ROUND((AE75*AV75*I75),2)*BS75),2) -> 0.08 | S75: =ROUND((ROUND((AF75*AV75*I75),2)*BA75),2) -> 50.39 | T75: =ROUND(CU75*I75,2) -> 0 | U75: =CV75*I75 -> 3.8795015 | V75: =CW75*I75 -> 0 | W75: =ROUND(CX75*I75,2) -> 0 | X75: =ROUND(CY75,2) -> 48.96 | Y75: =ROUND(CZ75,2) -> 25.74 | AA75: 56503348 | AB75: =ROUND((AC75+AD75+AF75),6) -> 1829.708 | AC75: =ROUND((ES75),6) -> 857 | AD75: =ROUND(((((ET75*1.1))-((EU75*1.1)))+AE75),6) -> 10.054 | AE75: =ROUND(((EU75*1.1)),6) -> 1.529 | AF75: =ROUND(((EV75*1.1)),6) -> 962.654 | AG75: =ROUND((AP75),6) -> 0 | AH75: =((EW75*1.1)) -> 74.107 | AI75: =((EX75*1.1)) -> 0 | AJ75: =(AS75) -> 0 | AK75: 1741.28 | AL75: 857 | AM75: 9.14 | AN75: 1.39 | AO75: 875.14 | AP75: 0 | AQ75: 67.37 | AR75: 0 | AS75: 0 | AT75: 97 | AU75: 51 | AV75: 1.047 | AW75: 1 | AZ75: 1 | BA75: 1 | BB75: 1 | BC75: 1 | BH75: 0 | BI75: 2 | BJ75: ТСН-2001.4 Доп. 79, Сб. 8, т. 243, поз. 11 | BM75: 67 | BN75: 0 | BO75: 4.8-243-11 | BP75: 1 | BQ75: 40 | BR75: 0 | BS75: 1 | BT75: 1 | BU75: 1 | BV75: 1 | BW75: 1 | BX75: 1 | BZ75: 97 | CA75: 51 | CE75: 30 | CF75: 0 | CG75: 0 | CM75: 0 | CO75: 0 | CP75: =(P75+Q75+S75) -> 93.77 | CQ75: =ROUND((ROUND((AC75*AW75*1),2)*BC75),2) -> 857 | CR75: =(ROUND((ROUND((((ET75*1.1))*AV75*1),2)*BB75),2)+ROUND((ROUND(((AE75-((EU75*1.1)))*AV75*1),2)*BS75),2)) -> 10.53 | CS75: =ROUND((ROUND((AE75*AV75*1),2)*BS75),2) -> 1.6 | CT75: =ROUND((ROUND((AF75*AV75*1),2)*BA75),2) -> 1007.9 | CU75: =AG75 -> 0 | CV75: =(AH75*AV75) -> 77.590029 | CW75: =AI75 -> 0 | CX75: =AJ75 -> 0 | CY75: =(((S75+R75)*AT75)/100) -> 48.9559 | CZ75: =(((S75+R75)*AU75)/100) -> 25.7397 | DE75: *1,1 | DF75: *1,1 | DG75: *1,1 | DI75: *1,1 | DJ75: *1,1 | DN75: 0 | DO75: 0 | DP75: 1 | DQ75: 1 | DU75: 1010 | DV75: 100 шт. | DW75: 100 шт. | DX75: 100 | EE75: 58162629 | EF75: 40 | EG75: Монтаж оборудования | EH75: 0 | EJ75: 2 | EK75: 67 | EL75: ТСН-2001.4-8. Электротехнические установки | EM75: ТСН-2001.4-8-1 | EO75: Поправка: Гл.12.Прил.8.п.8. 5_12.00.01.11.003 | EQ75: 0 | ER75: 1741.28 | ES75: 857 | ET75: 9.14 | EU75: 1.39 | EV75: 875.14 | EW75: 67.37 | EX75: 0 | EY75: 0 | FQ75: 0 | FR75: 0 | FS75: 0 | FX75: 97 | FY75: 51 | GD75: 1 | GF75: 693897660 | GG75: 2 | GH75: 1 | GI75: 2 | GJ75: 0 | GK75: 0 | GL75: =ROUND(IF(AND(BH75=3,BI75=3,FS75<>0),P75,0),2) -> 0 | GM75: =ROUND(O75+X75+Y75,2)+GX75 -> 168.47 | GN75: =IF(OR(BI75=0,BI75=1),GM75-GX75,0) -> 0 | GO75: =IF(BI75=2,GM75-GX75,0) -> 168.47 | GP75: =IF(BI75=4,GM75-GX75,0) -> 0 | GR75: 0 | GS75: 3 | GT75: 0 | GV75: =ROUND((GT75),6) -> 0 | GW75: 1 | GX75: =ROUND(HC75*I75,2) -> 0 | HA75: 0 | HB75: 0 | HC75: =GV75*GW75 -> 0 | HS75: 0 | IK75: 0
A76: 17 | B76: 1 | C76: =ROW(SmtRes!A10) -> 10 | D76: =ROW(EtalonRes!A20) -> 20 | E76: 3 | F76: 4.8-243-11 | G76: Монтаж розетки штепсельной трехполюсной | H76: 100 шт. | I76: =ROUND(5/100,9) -> 0.05 | J76: 0 | K76: =ROUND(5/100,9) -> 0.05 | O76: =ROUND(CP76,2) -> 2906 | P76: =ROUND((ROUND((AC76*AW76*I76),2)*BC76),2) -> 126.41 | Q76: =(ROUND((ROUND((((ET76*1.1))*AV76*I76),2)*BB76),2)+ROUND((ROUND(((AE76-((EU76*1.1)))*AV76*I76),2)*BS76),2)) -> 8.64 | R76: =ROUND((ROUND((AE76*AV76*I76),2)*BS76),2) -> 4.4 | S76: =ROUND((ROUND((AF76*AV76*I76),2)*BA76),2) -> 2770.95 | T76: =ROUND(CU76*I76,2) -> 0 | U76: =CV76*I76 -> 3.8795015 | V76: =CW76*I76 -> 0 | W76: =ROUND(CX76*I76,2) -> 0 | X76: =ROUND(CY76,2) -> 2692.09 | Y76: =ROUND(CZ76,2) -> 1415.43 | AA76: 56503350 | AB76: =ROUND((AC76+AD76+AF76),6) -> 1829.708 | AC76: =ROUND((ES76),6) -> 857 | AD76: =ROUND(((((ET76*1.1))-((EU76*1.1)))+AE76),6) -> 10.054 | AE76: =ROUND(((EU76*1.1)),6) -> 1.529 | AF76: =ROUND(((EV76*1.1)),6) -> 962.654 | AG76: =ROUND((AP76),6) -> 0 | AH76: =((EW76*1.1)) -> 74.107 | AI76: =((EX76*1.1)) -> 0 | AJ76: =(AS76) -> 0 | AK76: 1741.28 | AL76: 857 | AM76: 9.14 | AN76: 1.39 | AO76: 875.14 | AP76: 0 | AQ76: 67.37 | AR76: 0 | AS76: 0 | AT76: 97 | AU76: 51 | AV76: 1.047 | AW76: 1 | AZ76: 1 | BA76: 54.99 | BB76: 16.3 | BC76: 2.95 | BH76: 0 | BI76: 2 | BJ76: ТСН-2001.4 Доп. 79, Сб. 8, т. 243, поз. 11 | BM76: 67 | BN76: 0 | BO76: 4.8-243-11 | BP76: 1 | BQ76: 40 | BR76: 0 | BS76: 54.99 | BT76: 1 | BU76: 1 | BV76: 1 | BW76: 1 | BX76: 1 | BZ76: 97 | CA76: 51 | CE76: 30 | CF76: 0 | CG76: 0 | CM76: 0 | CO76: 0 | CP76: =(P76+Q76+S76) -> 2906 | CQ76: =ROUND((ROUND((AC76*AW76*1),2)*BC76),2) -> 2528.15 | CR76: =(ROUND((ROUND((((ET76*1.1))*AV76*1),2)*BB76),2)+ROUND((ROUND(((AE76-((EU76*1.1)))*AV76*1),2)*BS76),2)) -> 171.64 | CS76: =ROUND((ROUND((AE76*AV76*1),2)*BS76),2) -> 87.98 | CT76: =ROUND((ROUND((AF76*AV76*1),2)*BA76),2) -> 55424.42 | CU76: =AG76 -> 0 | CV76: =(AH76*AV76) -> 77.590029 | CW76: =AI76 -> 0 | CX76: =AJ76 -> 0 | CY76: =(((S76+R76)*AT76)/100) -> 2692.0895 | CZ76: =(((S76+R76)*AU76)/100) -> 1415.4285 | DE76: *1,1 | DF76: *1,1 | DG76: *1,1 | DI76: *1,1 | DJ76: *1,1 | DN76: 0 | DO76: 0 | DP76: 1 | DQ76: 1 | DU76: 1010 | DV76: 100 шт. | DW76: 100 шт. | DX76: 100 | EE76: 58162629 | EF76: 40 | EG76: Монтаж оборудования | EH76: 0 | EJ76: 2 | EK76: 67 | EL76: ТСН-2001.4-8. Электротехнические установки | EM76: ТСН-2001.4-8-1 | EO76: Поправка: Гл.12.Прил.8.п.8. 5_12.00.01.11.003 | EQ76: 0 | ER76: 1741.28 | ES76: 857 | ET76: 9.14 | EU76: 1.39 | EV76: 875.14 | EW76: 67.37 | EX76: 0 | EY76: 0 | FQ76: 0 | FR76: 0 | FS76: 0 | FX76: 97 | FY76: 51 | GD76: 1 | GF76: 693897660 | GG76: 2 | GH76: 1 | GI76: 2 | GJ76: 0 | GK76: 0 | GL76: =ROUND(IF(AND(BH76=3,BI76=3,FS76<>0),P76,0),2) -> 0 | GM76: =ROUND(O76+X76+Y76,2)+GX76 -> 7013.52 | GN76: =IF(OR(BI76=0,BI76=1),GM76-GX76,0) -> 0 | GO76: =IF(BI76=2,GM76-GX76,0) -> 7013.52 | GP76: =IF(BI76=4,GM76-GX76,0) -> 0 | GR76: 0 | GS76: 3 | GT76: 0 | GV76: =ROUND((GT76),6) -> 0 | GW76: 1 | GX76: =ROUND(HC76*I76,2) -> 0 | HA76: 0 | HB76: 0 | HC76: =GV76*GW76 -> 0 | HS76: 0 | IK76: 0
A77: 18 | B77: 1 | C77: 5 | E77: 3,1 | F77: 1.14-1-199 | G77: Розетка телевизионная, скрытой установки, раздельная, двухместная, "штырь" и "гнездо", конечная, затухание 4 дБ, возвратные потери от 12 до 18 дБ, диапазон частот от 5 до 2400 МГц, степень защиты IP20, с безвинтовыми зажимами для радиочастотного коаксиального кабеля с диаметром внутреннего проводника от 0,58 до 1,15 мм и диаметром по изоляции от 3,7 до 5,8 мм, механизм с литой цинковой крепежной рамой, без декоративной крышки, размер не более 71х71х22 мм | H77: шт. | I77: =I75*J77 -> 5 | J77: 100 | K77: 100 | O77: =ROUND(CP77,2) -> 665.25 | P77: =ROUND((ROUND((AC77*AW77*I77),2)*BC77),2) -> 665.25 | Q77: =(ROUND((ROUND(((ET77)*AV77*I77),2)*BB77),2)+ROUND((ROUND(((AE77-(EU77))*AV77*I77),2)*BS77),2)) -> 0 | R77: =ROUND((ROUND((AE77*AV77*I77),2)*BS77),2) -> 0 | S77: =ROUND((ROUND((AF77*AV77*I77),2)*BA77),2) -> 0 | T77: =ROUND(CU77*I77,2) -> 0 | U77: =CV77*I77 -> 0 | V77: =CW77*I77 -> 0 | W77: =ROUND(CX77*I77,2) -> 0 | X77: =ROUND(CY77,2) -> 0 | Y77: =ROUND(CZ77,2) -> 0 | AA77: 56503348 | AB77: =ROUND((AC77+AD77+AF77),6) -> 133.05 | AC77: =ROUND((ES77),6) -> 133.05 | AD77: =ROUND((((ET77)-(EU77))+AE77),6) -> 0 | AE77: =ROUND((EU77),6) -> 0 | AF77: =ROUND((EV77),6) -> 0 | AG77: =ROUND((AP77),6) -> 0 | AH77: =(EW77) -> 0 | AI77: =(EX77) -> 0 | AJ77: =(AS77) -> 0 | AK77: 133.05 | AL77: 133.05 | AM77: 0 | AN77: 0 | AO77: 0 | AP77: 0 | AQ77: 0 | AR77: 0 | AS77: 0 | AT77: 97 | AU77: 51 | AV77: 1 | AW77: 1 | AZ77: 1 | BA77: 1 | BB77: 1 | BC77: 1 | BH77: 3 | BI77: 2 | BJ77: ТСН-2001.1 Доп. 67, Р. 14, о. 1, поз. 199 | BM77: 67 | BN77: 0 | BP77: 0 | BQ77: 40 | BR77: 0 | BS77: 1 | BT77: 1 | BU77: 1 | BV77: 1 | BW77: 1 | BX77: 1 | BZ77: 97 | CA77: 51 | CE77: 30 | CF77: 0 | CG77: 0 | CM77: 0 | CO77: 0 | CP77: =(P77+Q77+S77) -> 665.25 | CQ77: =ROUND((ROUND((AC77*AW77*1),2)*BC77),2) -> 133.05 | CR77: =(ROUND((ROUND(((ET77)*AV77*1),2)*BB77),2)+ROUND((ROUND(((AE77-(EU77))*AV77*1),2)*BS77),2)) -> 0 | CS77: =ROUND((ROUND((AE77*AV77*1),2)*BS77),2) -> 0 | CT77: =ROUND((ROUND((AF77*AV77*1),2)*BA77),2) -> 0 | CU77: =AG77 -> 0 | CV77: =(AH77*AV77) -> 0 | CW77: =AI77 -> 0 | CX77: =AJ77 -> 0 | CY77: =(((S77+R77)*AT77)/100) -> 0 | CZ77: =(((S77+R77)*AU77)/100) -> 0 | DN77: 0 | DO77: 0 | DP77: 1 | DQ77: 1 | DU77: 1010 | DV77: шт. | DW77: шт. | DX77: 1 | EE77: 58162629 | EF77: 40 | EG77: Монтаж оборудования | EH77: 0 | EJ77: 2 | EK77: 67 | EL77: ТСН-2001.4-8. Электротехнические установки | EM77: ТСН-2001.4-8-1 | EQ77: 0 | ER77: 133.05 | ES77: 133.05 | ET77: 0 | EU77: 0 | EV77: 0 | EW77: 0 | EX77: 0 | FQ77: 0 | FR77: 0 | FS77: 0 | FX77: 97 | FY77: 51 | GD77: 1 | GF77: -971037413 | GG77: 2 | GH77: 1 | GI77: -2 | GJ77: 0 | GK77: 0 | GL77: =ROUND(IF(AND(BH77=3,BI77=3,FS77<>0),P77,0),2) -> 0 | GM77: =ROUND(O77+X77+Y77,2)+GX77 -> 665.25 | GN77: =IF(OR(BI77=0,BI77=1),GM77-GX77,0) -> 0 | GO77: =IF(BI77=2,GM77-GX77,0) -> 665.25 | GP77: =IF(BI77=4,GM77-GX77,0) -> 0 | GR77: 0 | GS77: 3 | GT77: 0 | GV77: =ROUND((GT77),6) -> 0 | GW77: 1 | GX77: =ROUND(HC77*I77,2) -> 0 | HA77: 0 | HB77: 0 | HC77: =GV77*GW77 -> 0 | HS77: 0 | IK77: 0
A78: 18 | B78: 1 | C78: 10 | E78: 3,1 | F78: 1.14-1-199 | G78: Розетка телевизионная, скрытой установки, раздельная, двухместная, "штырь" и "гнездо", конечная, затухание 4 дБ, возвратные потери от 12 до 18 дБ, диапазон частот от 5 до 2400 МГц, степень защиты IP20, с безвинтовыми зажимами для радиочастотного коаксиального кабеля с диаметром внутреннего проводника от 0,58 до 1,15 мм и диаметром по изоляции от 3,7 до 5,8 мм, механизм с литой цинковой крепежной рамой, без декоративной крышки, размер не более 71х71х22 мм | H78: шт. | I78: =I76*J78 -> 5 | J78: 100 | K78: 100 | O78: =ROUND(CP78,2) -> 6213.44 | P78: =ROUND((ROUND((AC78*AW78*I78),2)*BC78),2) -> 6213.44 | Q78: =(ROUND((ROUND(((ET78)*AV78*I78),2)*BB78),2)+ROUND((ROUND(((AE78-(EU78))*AV78*I78),2)*BS78),2)) -> 0 | R78: =ROUND((ROUND((AE78*AV78*I78),2)*BS78),2) -> 0 | S78: =ROUND((ROUND((AF78*AV78*I78),2)*BA78),2) -> 0 | T78: =ROUND(CU78*I78,2) -> 0 | U78: =CV78*I78 -> 0 | V78: =CW78*I78 -> 0 | W78: =ROUND(CX78*I78,2) -> 0 | X78: =ROUND(CY78,2) -> 0 | Y78: =ROUND(CZ78,2) -> 0 | AA78: 56503350 | AB78: =ROUND((AC78+AD78+AF78),6) -> 133.05 | AC78: =ROUND((ES78),6) -> 133.05 | AD78: =ROUND((((ET78)-(EU78))+AE78),6) -> 0 | AE78: =ROUND((EU78),6) -> 0 | AF78: =ROUND((EV78),6) -> 0 | AG78: =ROUND((AP78),6) -> 0 | AH78: =(EW78) -> 0 | AI78: =(EX78) -> 0 | AJ78: =(AS78) -> 0 | AK78: 133.05 | AL78: 133.05 | AM78: 0 | AN78: 0 | AO78: 0 | AP78: 0 | AQ78: 0 | AR78: 0 | AS78: 0 | AT78: 97 | AU78: 51 | AV78: 1 | AW78: 1 | AZ78: 1 | BA78: 1 | BB78: 1 | BC78: 9.34 | BH78: 3 | BI78: 2 | BJ78: ТСН-2001.1 Доп. 67, Р. 14, о. 1, поз. 199 | BM78: 67 | BN78: 0 | BO78: 1.14-1-199 | BP78: 1 | BQ78: 40 | BR78: 0 | BS78: 1 | BT78: 1 | BU78: 1 | BV78: 1 | BW78: 1 | BX78: 1 | BZ78: 97 | CA78: 51 | CE78: 30 | CF78: 0 | CG78: 0 | CM78: 0 | CO78: 0 | CP78: =(P78+Q78+S78) -> 6213.44 | CQ78: =ROUND((ROUND((AC78*AW78*1),2)*BC78),2) -> 1242.69 | CR78: =(ROUND((ROUND(((ET78)*AV78*1),2)*BB78),2)+ROUND((ROUND(((AE78-(EU78))*AV78*1),2)*BS78),2)) -> 0 | CS78: =ROUND((ROUND((AE78*AV78*1),2)*BS78),2) -> 0 | CT78: =ROUND((ROUND((AF78*AV78*1),2)*BA78),2) -> 0 | CU78: =AG78 -> 0 | CV78: =(AH78*AV78) -> 0 | CW78: =AI78 -> 0 | CX78: =AJ78 -> 0 | CY78: =(((S78+R78)*AT78)/100) -> 0 | CZ78: =(((S78+R78)*AU78)/100) -> 0 | DN78: 0 | DO78: 0 | DP78: 1 | DQ78: 1 | DU78: 1010 | DV78: шт. | DW78: шт. | DX78: 1 | EE78: 58162629 | EF78: 40 | EG78: Монтаж оборудования | EH78: 0 | EJ78: 2 | EK78: 67 | EL78: ТСН-2001.4-8. Электротехнические установки | EM78: ТСН-2001.4-8-1 | EQ78: 0 | ER78: 133.05 | ES78: 133.05 | ET78: 0 | EU78: 0 | EV78: 0 | EW78: 0 | EX78: 0 | FQ78: 0 | FR78: 0 | FS78: 0 | FX78: 97 | FY78: 51 | GD78: 1 | GF78: -971037413 | GG78: 2 | GH78: 1 | GI78: 2 | GJ78: 0 | GK78: 0 | GL78: =ROUND(IF(AND(BH78=3,BI78=3,FS78<>0),P78,0),2) -> 0 | GM78: =ROUND(O78+X78+Y78,2)+GX78 -> 6213.44 | GN78: =IF(OR(BI78=0,BI78=1),GM78-GX78,0) -> 0 | GO78: =IF(BI78=2,GM78-GX78,0) -> 6213.44 | GP78: =IF(BI78=4,GM78-GX78,0) -> 0 | GR78: 0 | GS78: 3 | GT78: 0 | GV78: =ROUND((GT78),6) -> 0 | GW78: 1 | GX78: =ROUND(HC78*I78,2) -> 0 | HA78: 0 | HB78: 0 | HC78: =GV78*GW78 -> 0 | HS78: 0 | IK78: 0
A79: 17 | B79: 1 | D79: =ROW(EtalonRes!A31) -> 31 | E79: 4 | F79: 4.10-186-5 | G79: Прокладка кабеля связи симметричного для цифровых систем передачи в трубах гофрированных: по бетонным и кирпичным поверхностям стен и потолка | H79: 100 м | I79: =ROUND(200/100,9) -> 2 | J79: 0 | K79: =ROUND(200/100,9) -> 2 | O79: =ROUND(CP79,2) -> 642.21 | P79: =ROUND((ROUND((AC79*AW79*I79),2)*BC79),2) -> 183.82 | Q79: =(ROUND((ROUND((((ET79*1.1))*AV79*I79),2)*BB79),2)+ROUND((ROUND(((AE79-((EU79*1.1)))*AV79*I79),2)*BS79),2)) -> 3.98 | R79: =ROUND((ROUND((AE79*AV79*I79),2)*BS79),2) -> 0 | S79: =ROUND((ROUND((AF79*AV79*I79),2)*BA79),2) -> 454.41 | T79: =ROUND(CU79*I79,2) -> 0 | U79: =CV79*I79 -> 38.23644 | V79: =CW79*I79 -> 0 | W79: =ROUND(CX79*I79,2) -> 0 | X79: =ROUND(CY79,2) -> 408.97 | Y79: =ROUND(CZ79,2) -> 209.03 | AA79: 56503348 | AB79: =ROUND((AC79+AD79+AF79),6) -> 310.821 | AC79: =ROUND((ES79),6) -> 91.91 | AD79: =ROUND(((((ET79*1.1))-((EU79*1.1)))+AE79),6) -> 1.903 | AE79: =ROUND(((EU79*1.1)),6) -> 0 | AF79: =ROUND(((EV79*1.1)),6) -> 217.008 | AG79: =ROUND((AP79),6) -> 0 | AH79: =((EW79*1.1)) -> 18.26 | AI79: =((EX79*1.1)) -> 0 | AJ79: =(AS79) -> 0 | AK79: 290.92 | AL79: 91.91 | AM79: 1.73 | AN79: 0 | AO79: 197.28 | AP79: 0 | AQ79: 16.6 | AR79: 0 | AS79: 0 | AT79: 90 | AU79: 46 | AV79: 1.047 | AW79: 1 | AZ79: 1 | BA79: 1 | BB79: 1 | BC79: 1 | BH79: 0 | BI79: 2 | BJ79: ТСН-2001.4 Доп. 79, Сб. 10, т. 186, поз. 5 | BM79: 68 | BN79: 0 | BO79: 4.10-186-5 | BP79: 1 | BQ79: 40 | BR79: 0 | BS79: 1 | BT79: 1 | BU79: 1 | BV79: 1 | BW79: 1 | BX79: 1 | BZ79: 90 | CA79: 46 | CE79: 30 | CF79: 0 | CG79: 0 | CM79: 0 | CO79: 0 | CP79: =(P79+Q79+S79) -> 642.21 | CQ79: =ROUND((ROUND((AC79*AW79*1),2)*BC79),2) -> 91.91 | CR79: =(ROUND((ROUND((((ET79*1.1))*AV79*1),2)*BB79),2)+ROUND((ROUND(((AE79-((EU79*1.1)))*AV79*1),2)*BS79),2)) -> 1.99 | CS79: =ROUND((ROUND((AE79*AV79*1),2)*BS79),2) -> 0 | CT79: =ROUND((ROUND((AF79*AV79*1),2)*BA79),2) -> 227.21 | CU79: =AG79 -> 0 | CV79: =(AH79*AV79) -> 19.11822 | CW79: =AI79 -> 0 | CX79: =AJ79 -> 0 | CY79: =(((S79+R79)*AT79)/100) -> 408.969 | CZ79: =(((S79+R79)*AU79)/100) -> 209.0286 | DE79: *1,1 | DF79: *1,1 | DG79: *1,1 | DI79: *1,1 | DJ79: *1,1 | DN79: 0 | DO79: 0 | DP79: 1 | DQ79: 1 | DU79: 1003 | DV79: 100 м | DW79: 100 м | DX79: 100 | EE79: 58162630 | EF79: 40 | EG79: Монтаж оборудования | EH79: 0 | EJ79: 2 | EK79: 68 | EL79: ТСН-2001.4-10. Прокладка и монтаж сетей связи | EM79: ТСН-2001.4-10-1 | EO79: Поправка: Гл.12.Прил.8.п.8. 5_12.00.01.11.003 | EQ79: 0 | ER79: 290.92 | ES79: 91.91 | ET79: 1.73 | EU79: 0 | EV79: 197.28 | EW79: 16.6 | EX79: 0 | EY79: 0 | FQ79: 0 | FR79: 0 | FS79: 0 | FX79: 90 | FY79: 46 | GD79: 1 | GF79: -250176620 | GG79: 2 | GH79: 1 | GI79: 2 | GJ79: 0 | GK79: 0 | GL79: =ROUND(IF(AND(BH79=3,BI79=3,FS79<>0),P79,0),2) -> 0 | GM79: =ROUND(O79+X79+Y79,2)+GX79 -> 1260.21 | GN79: =IF(OR(BI79=0,BI79=1),GM79-GX79,0) -> 0 | GO79: =IF(BI79=2,GM79-GX79,0) -> 1260.21 | GP79: =IF(BI79=4,GM79-GX79,0) -> 0 | GR79: 0 | GS79: 3 | GT79: 0 | GV79: =ROUND((GT79),6) -> 0 | GW79: 1 | GX79: =ROUND(HC79*I79,2) -> 0 | HA79: 0 | HB79: 0 | HC79: =GV79*GW79 -> 0 | HS79: 0 | IK79: 0
A80: 17 | B80: 1 | D80: =ROW(EtalonRes!A42) -> 42 | E80: 4 | F80: 4.10-186-5 | G80: Прокладка кабеля связи симметричного для цифровых систем передачи в трубах гофрированных: по бетонным и кирпичным поверхностям стен и потолка | H80: 100 м | I80: =ROUND(200/100,9) -> 2 | J80: 0 | K80: =ROUND(200/100,9) -> 2 | O80: =ROUND(CP80,2) -> 25530.02 | P80: =ROUND((ROUND((AC80*AW80*I80),2)*BC80),2) -> 507.34 | Q80: =(ROUND((ROUND((((ET80*1.1))*AV80*I80),2)*BB80),2)+ROUND((ROUND(((AE80-((EU80*1.1)))*AV80*I80),2)*BS80),2)) -> 34.67 | R80: =ROUND((ROUND((AE80*AV80*I80),2)*BS80),2) -> 0 | S80: =ROUND((ROUND((AF80*AV80*I80),2)*BA80),2) -> 24988.01 | T80: =ROUND(CU80*I80,2) -> 0 | U80: =CV80*I80 -> 38.23644 | V80: =CW80*I80 -> 0 | W80: =ROUND(CX80*I80,2) -> 0 | X80: =ROUND(CY80,2) -> 22489.21 | Y80: =ROUND(CZ80,2) -> 11494.48 | AA80: 56503350 | AB80: =ROUND((AC80+AD80+AF80),6) -> 310.821 | AC80: =ROUND((ES80),6) -> 91.91 | AD80: =ROUND(((((ET80*1.1))-((EU80*1.1)))+AE80),6) -> 1.903 | AE80: =ROUND(((EU80*1.1)),6) -> 0 | AF80: =ROUND(((EV80*1.1)),6) -> 217.008 | AG80: =ROUND((AP80),6) -> 0 | AH80: =((EW80*1.1)) -> 18.26 | AI80: =((EX80*1.1)) -> 0 | AJ80: =(AS80) -> 0 | AK80: 290.92 | AL80: 91.91 | AM80: 1.73 | AN80: 0 | AO80: 197.28 | AP80: 0 | AQ80: 16.6 | AR80: 0 | AS80: 0 | AT80: 90 | AU80: 46 | AV80: 1.047 | AW80: 1 | AZ80: 1 | BA80: 54.99 | BB80: 8.71 | BC80: 2.76 | BH80: 0 | BI80: 2 | BJ80: ТСН-2001.4 Доп. 79, Сб. 10, т. 186, поз. 5 | BM80: 68 | BN80: 0 | BO80: 4.10-186-5 | BP80: 1 | BQ80: 40 | BR80: 0 | BS80: 54.99 | BT80: 1 | BU80: 1 | BV80: 1 | BW80: 1 | BX80: 1 | BZ80: 90 | CA80: 46 | CE80: 30 | CF80: 0 | CG80: 0 | CM80: 0 | CO80: 0 | CP80: =(P80+Q80+S80) -> 25530.02 | CQ80: =ROUND((ROUND((AC80*AW80*1),2)*BC80),2) -> 253.67 | CR80: =(ROUND((ROUND((((ET80*1.1))*AV80*1),2)*BB80),2)+ROUND((ROUND(((AE80-((EU80*1.1)))*AV80*1),2)*BS80),2)) -> 17.33 | CS80: =ROUND((ROUND((AE80*AV80*1),2)*BS80),2) -> 0 | CT80: =ROUND((ROUND((AF80*AV80*1),2)*BA80),2) -> 12494.28 | CU80: =AG80 -> 0 | CV80: =(AH80*AV80) -> 19.11822 | CW80: =AI80 -> 0 | CX80: =AJ80 -> 0 | CY80: =(((S80+R80)*AT80)/100) -> 22489.209 | CZ80: =(((S80+R80)*AU80)/100) -> 11494.485 | DE80: *1,1 | DF80: *1,1 | DG80: *1,1 | DI80: *1,1 | DJ80: *1,1 | DN80: 0 | DO80: 0 | DP80: 1 | DQ80: 1 | DU80: 1003 | DV80: 100 м | DW80: 100 м | DX80: 100 | EE80: 58162630 | EF80: 40 | EG80: Монтаж оборудования | EH80: 0 | EJ80: 2 | EK80: 68 | EL80: ТСН-2001.4-10. Прокладка и монтаж сетей связи | EM80: ТСН-2001.4-10-1 | EO80: Поправка: Гл.12.Прил.8.п.8. 5_12.00.01.11.003 | EQ80: 0 | ER80: 290.92 | ES80: 91.91 | ET80: 1.73 | EU80: 0 | EV80: 197.28 | EW80: 16.6 | EX80: 0 | EY80: 0 | FQ80: 0 | FR80: 0 | FS80: 0 | FX80: 90 | FY80: 46 | GD80: 1 | GF80: -250176620 | GG80: 2 | GH80: 1 | GI80: 2 | GJ80: 0 | GK80: 0 | GL80: =ROUND(IF(AND(BH80=3,BI80=3,FS80<>0),P80,0),2) -> 0 | GM80: =ROUND(O80+X80+Y80,2)+GX80 -> 59513.71 | GN80: =IF(OR(BI80=0,BI80=1),GM80-GX80,0) -> 0 | GO80: =IF(BI80=2,GM80-GX80,0) -> 59513.71 | GP80: =IF(BI80=4,GM80-GX80,0) -> 0 | GR80: 0 | GS80: 3 | GT80: 0 | GV80: =ROUND((GT80),6) -> 0 | GW80: 1 | GX80: =ROUND(HC80*I80,2) -> 0 | HA80: 0 | HB80: 0 | HC80: =GV80*GW80 -> 0 | HS80: 0 | IK80: 0
A81: 18 | B81: 1 | E81: 4,1 | F81: 1.12-5-372 | G81: Трубы электротехнические, гофрированные, из ПВХ, негорючие, с зондом, наружный диаметр 20 мм | H81: м | I81: =I79*J81 -> 204 | J81: 102 | K81: 102 | O81: =ROUND(CP81,2) -> 703.8 | P81: =ROUND((ROUND((AC81*AW81*I81),2)*BC81),2) -> 703.8 | Q81: =(ROUND((ROUND(((ET81)*AV81*I81),2)*BB81),2)+ROUND((ROUND(((AE81-(EU81))*AV81*I81),2)*BS81),2)) -> 0 | R81: =ROUND((ROUND((AE81*AV81*I81),2)*BS81),2) -> 0 | S81: =ROUND((ROUND((AF81*AV81*I81),2)*BA81),2) -> 0 | T81: =ROUND(CU81*I81,2) -> 0 | U81: =CV81*I81 -> 0 | V81: =CW81*I81 -> 0 | W81: =ROUND(CX81*I81,2) -> 0 | X81: =ROUND(CY81,2) -> 0 | Y81: =ROUND(CZ81,2) -> 0 | AA81: 56503348 | AB81: =ROUND((AC81+AD81+AF81),6) -> 3.45 | AC81: =ROUND((ES81),6) -> 3.45 | AD81: =ROUND((((ET81)-(EU81))+AE81),6) -> 0 | AE81: =ROUND((EU81),6) -> 0 | AF81: =ROUND((EV81),6) -> 0 | AG81: =ROUND((AP81),6) -> 0 | AH81: =(EW81) -> 0 | AI81: =(EX81) -> 0 | AJ81: =(AS81) -> 0 | AK81: 3.45 | AL81: 3.45 | AM81: 0 | AN81: 0 | AO81: 0 | AP81: 0 | AQ81: 0 | AR81: 0 | AS81: 0 | AT81: 90 | AU81: 46 | AV81: 1 | AW81: 1 | AZ81: 1 | BA81: 1 | BB81: 1 | BC81: 1 | BH81: 3 | BI81: 2 | BJ81: ТСН-2001.1 Доп. 67, Р. 12, о. 5, поз. 372 | BM81: 68 | BN81: 0 | BP81: 0 | BQ81: 40 | BR81: 0 | BS81: 1 | BT81: 1 | BU81: 1 | BV81: 1 | BW81: 1 | BX81: 1 | BZ81: 90 | CA81: 46 | CE81: 30 | CF81: 0 | CG81: 0 | CM81: 0 | CO81: 0 | CP81: =(P81+Q81+S81) -> 703.8 | CQ81: =ROUND((ROUND((AC81*AW81*1),2)*BC81),2) -> 3.45 | CR81: =(ROUND((ROUND(((ET81)*AV81*1),2)*BB81),2)+ROUND((ROUND(((AE81-(EU81))*AV81*1),2)*BS81),2)) -> 0 | CS81: =ROUND((ROUND((AE81*AV81*1),2)*BS81),2) -> 0 | CT81: =ROUND((ROUND((AF81*AV81*1),2)*BA81),2) -> 0 | CU81: =AG81 -> 0 | CV81: =(AH81*AV81) -> 0 | CW81: =AI81 -> 0 | CX81: =AJ81 -> 0 | CY81: =(((S81+R81)*AT81)/100) -> 0 | CZ81: =(((S81+R81)*AU81)/100) -> 0 | DN81: 0 | DO81: 0 | DP81: 1 | DQ81: 1 | DU81: 1003 | DV81: м | DW81: м | DX81: 1 | EE81: 58162630 | EF81: 40 | EG81: Монтаж оборудования | EH81: 0 | EJ81: 2 | EK81: 68 | EL81: ТСН-2001.4-10. Прокладка и монтаж сетей связи | EM81: ТСН-2001.4-10-1 | EQ81: 0 | ER81: 3.45 | ES81: 3.45 | ET81: 0 | EU81: 0 | EV81: 0 | EW81: 0 | EX81: 0 | FQ81: 0 | FR81: 0 | FS81: 0 | FX81: 90 | FY81: 46 | GD81: 1 | GF81: -1305428159 | GG81: 2 | GH81: 1 | GI81: -2 | GJ81: 0 | GK81: 0 | GL81: =ROUND(IF(AND(BH81=3,BI81=3,FS81<>0),P81,0),2) -> 0 | GM81: =ROUND(O81+X81+Y81,2)+GX81 -> 703.8 | GN81: =IF(OR(BI81=0,BI81=1),GM81-GX81,0) -> 0 | GO81: =IF(BI81=2,GM81-GX81,0) -> 703.8 | GP81: =IF(BI81=4,GM81-GX81,0) -> 0 | GR81: 0 | GS81: 3 | GT81: 0 | GV81: =ROUND((GT81),6) -> 0 | GW81: 1 | GX81: =ROUND(HC81*I81,2) -> 0 | HA81: 0 | HB81: 0 | HC81: =GV81*GW81 -> 0 | HS81: 0 | IK81: 0
A82: 18 | B82: 1 | E82: 4,1 | F82: 1.12-5-372 | G82: Трубы электротехнические, гофрированные, из ПВХ, негорючие, с зондом, наружный диаметр 20 мм | H82: м | I82: =I80*J82 -> 204 | J82: 102 | K82: 102 | O82: =ROUND(CP82,2) -> 2765.93 | P82: =ROUND((ROUND((AC82*AW82*I82),2)*BC82),2) -> 2765.93 | Q82: =(ROUND((ROUND(((ET82)*AV82*I82),2)*BB82),2)+ROUND((ROUND(((AE82-(EU82))*AV82*I82),2)*BS82),2)) -> 0 | R82: =ROUND((ROUND((AE82*AV82*I82),2)*BS82),2) -> 0 | S82: =ROUND((ROUND((AF82*AV82*I82),2)*BA82),2) -> 0 | T82: =ROUND(CU82*I82,2) -> 0 | U82: =CV82*I82 -> 0 | V82: =CW82*I82 -> 0 | W82: =ROUND(CX82*I82,2) -> 0 | X82: =ROUND(CY82,2) -> 0 | Y82: =ROUND(CZ82,2) -> 0 | AA82: 56503350 | AB82: =ROUND((AC82+AD82+AF82),6) -> 3.45 | AC82: =ROUND((ES82),6) -> 3.45 | AD82: =ROUND((((ET82)-(EU82))+AE82),6) -> 0 | AE82: =ROUND((EU82),6) -> 0 | AF82: =ROUND((EV82),6) -> 0 | AG82: =ROUND((AP82),6) -> 0 | AH82: =(EW82) -> 0 | AI82: =(EX82) -> 0 | AJ82: =(AS82) -> 0 | AK82: 3.45 | AL82: 3.45 | AM82: 0 | AN82: 0 | AO82: 0 | AP82: 0 | AQ82: 0 | AR82: 0 | AS82: 0 | AT82: 90 | AU82: 46 | AV82: 1 | AW82: 1 | AZ82: 1 | BA82: 1 | BB82: 1 | BC82: 3.93 | BH82: 3 | BI82: 2 | BJ82: ТСН-2001.1 Доп. 67, Р. 12, о. 5, поз. 372 | BM82: 68 | BN82: 0 | BO82: 1.12-5-372 | BP82: 1 | BQ82: 40 | BR82: 0 | BS82: 1 | BT82: 1 | BU82: 1 | BV82: 1 | BW82: 1 | BX82: 1 | BZ82: 90 | CA82: 46 | CE82: 30 | CF82: 0 | CG82: 0 | CM82: 0 | CO82: 0 | CP82: =(P82+Q82+S82) -> 2765.93 | CQ82: =ROUND((ROUND((AC82*AW82*1),2)*BC82),2) -> 13.56 | CR82: =(ROUND((ROUND(((ET82)*AV82*1),2)*BB82),2)+ROUND((ROUND(((AE82-(EU82))*AV82*1),2)*BS82),2)) -> 0 | CS82: =ROUND((ROUND((AE82*AV82*1),2)*BS82),2) -> 0 | CT82: =ROUND((ROUND((AF82*AV82*1),2)*BA82),2) -> 0 | CU82: =AG82 -> 0 | CV82: =(AH82*AV82) -> 0 | CW82: =AI82 -> 0 | CX82: =AJ82 -> 0 | CY82: =(((S82+R82)*AT82)/100) -> 0 | CZ82: =(((S82+R82)*AU82)/100) -> 0 | DN82: 0 | DO82: 0 | DP82: 1 | DQ82: 1 | DU82: 1003 | DV82: м | DW82: м | DX82: 1 | EE82: 58162630 | EF82: 40 | EG82: Монтаж оборудования | EH82: 0 | EJ82: 2 | EK82: 68 | EL82: ТСН-2001.4-10. Прокладка и монтаж сетей связи | EM82: ТСН-2001.4-10-1 | EQ82: 0 | ER82: 3.45 | ES82: 3.45 | ET82: 0 | EU82: 0 | EV82: 0 | EW82: 0 | EX82: 0 | FQ82: 0 | FR82: 0 | FS82: 0 | FX82: 90 | FY82: 46 | GD82: 1 | GF82: -1305428159 | GG82: 2 | GH82: 1 | GI82: 2 | GJ82: 0 | GK82: 0 | GL82: =ROUND(IF(AND(BH82=3,BI82=3,FS82<>0),P82,0),2) -> 0 | GM82: =ROUND(O82+X82+Y82,2)+GX82 -> 2765.93 | GN82: =IF(OR(BI82=0,BI82=1),GM82-GX82,0) -> 0 | GO82: =IF(BI82=2,GM82-GX82,0) -> 2765.93 | GP82: =IF(BI82=4,GM82-GX82,0) -> 0 | GR82: 0 | GS82: 3 | GT82: 0 | GV82: =ROUND((GT82),6) -> 0 | GW82: 1 | GX82: =ROUND(HC82*I82,2) -> 0 | HA82: 0 | HB82: 0 | HC82: =GV82*GW82 -> 0 | HS82: 0 | IK82: 0
A83: 18 | B83: 1 | E83: 4,2 | F83: 1.21-5-896 | G83: Коробка установочная, для скрытой проводки, из полистирола, диаметр 65 мм, высота 40 мм, без саморезов | H83: шт. | I83: =I79*J83 -> 5 | J83: 2.5 | K83: 2.5 | O83: =ROUND(CP83,2) -> 5.3 | P83: =ROUND((ROUND((AC83*AW83*I83),2)*BC83),2) -> 5.3 | Q83: =(ROUND((ROUND(((ET83)*AV83*I83),2)*BB83),2)+ROUND((ROUND(((AE83-(EU83))*AV83*I83),2)*BS83),2)) -> 0 | R83: =ROUND((ROUND((AE83*AV83*I83),2)*BS83),2) -> 0 | S83: =ROUND((ROUND((AF83*AV83*I83),2)*BA83),2) -> 0 | T83: =ROUND(CU83*I83,2) -> 0 | U83: =CV83*I83 -> 0 | V83: =CW83*I83 -> 0 | W83: =ROUND(CX83*I83,2) -> 0 | X83: =ROUND(CY83,2) -> 0 | Y83: =ROUND(CZ83,2) -> 0 | AA83: 56503348 | AB83: =ROUND((AC83+AD83+AF83),6) -> 1.06 | AC83: =ROUND((ES83),6) -> 1.06 | AD83: =ROUND((((ET83)-(EU83))+AE83),6) -> 0 | AE83: =ROUND((EU83),6) -> 0 | AF83: =ROUND((EV83),6) -> 0 | AG83: =ROUND((AP83),6) -> 0 | AH83: =(EW83) -> 0 | AI83: =(EX83) -> 0 | AJ83: =(AS83) -> 0 | AK83: 1.06 | AL83: 1.06 | AM83: 0 | AN83: 0 | AO83: 0 | AP83: 0 | AQ83: 0 | AR83: 0 | AS83: 0 | AT83: 90 | AU83: 46 | AV83: 1 | AW83: 1 | AZ83: 1 | BA83: 1 | BB83: 1 | BC83: 1 | BH83: 3 | BI83: 2 | BJ83: ТСН-2001.1 Доп. 73, Р. 21, о. 5, поз. 896 | BM83: 68 | BN83: 0 | BP83: 0 | BQ83: 40 | BR83: 0 | BS83: 1 | BT83: 1 | BU83: 1 | BV83: 1 | BW83: 1 | BX83: 1 | BZ83: 90 | CA83: 46 | CE83: 30 | CF83: 0 | CG83: 0 | CM83: 0 | CO83: 0 | CP83: =(P83+Q83+S83) -> 5.3 | CQ83: =ROUND((ROUND((AC83*AW83*1),2)*BC83),2) -> 1.06 | CR83: =(ROUND((ROUND(((ET83)*AV83*1),2)*BB83),2)+ROUND((ROUND(((AE83-(EU83))*AV83*1),2)*BS83),2)) -> 0 | CS83: =ROUND((ROUND((AE83*AV83*1),2)*BS83),2) -> 0 | CT83: =ROUND((ROUND((AF83*AV83*1),2)*BA83),2) -> 0 | CU83: =AG83 -> 0 | CV83: =(AH83*AV83) -> 0 | CW83: =AI83 -> 0 | CX83: =AJ83 -> 0 | CY83: =(((S83+R83)*AT83)/100) -> 0 | CZ83: =(((S83+R83)*AU83)/100) -> 0 | DN83: 0 | DO83: 0 | DP83: 1 | DQ83: 1 | DU83: 1010 | DV83: шт. | DW83: шт. | DX83: 1 | EE83: 58162630 | EF83: 40 | EG83: Монтаж оборудования | EH83: 0 | EJ83: 2 | EK83: 68 | EL83: ТСН-2001.4-10. Прокладка и монтаж сетей связи | EM83: ТСН-2001.4-10-1 | EQ83: 0 | ER83: 1.06 | ES83: 1.06 | ET83: 0 | EU83: 0 | EV83: 0 | EW83: 0 | EX83: 0 | FQ83: 0 | FR83: 0 | FS83: 0 | FX83: 90 | FY83: 46 | GD83: 1 | GF83: -2026322809 | GG83: 2 | GH83: 1 | GI83: -2 | GJ83: 0 | GK83: 0 | GL83: =ROUND(IF(AND(BH83=3,BI83=3,FS83<>0),P83,0),2) -> 0 | GM83: =ROUND(O83+X83+Y83,2)+GX83 -> 5.3 | GN83: =IF(OR(BI83=0,BI83=1),GM83-GX83,0) -> 0 | GO83: =IF(BI83=2,GM83-GX83,0) -> 5.3 | GP83: =IF(BI83=4,GM83-GX83,0) -> 0 | GR83: 0 | GS83: 3 | GT83: 0 | GV83: =ROUND((GT83),6) -> 0 | GW83: 1 | GX83: =ROUND(HC83*I83,2) -> 0 | HA83: 0 | HB83: 0 | HC83: =GV83*GW83 -> 0 | HS83: 0 | IK83: 0
A84: 18 | B84: 1 | E84: 4,2 | F84: 1.21-5-896 | G84: Коробка установочная, для скрытой проводки, из полистирола, диаметр 65 мм, высота 40 мм, без саморезов | H84: шт. | I84: =I80*J84 -> 5 | J84: 2.5 | K84: 2.5 | O84: =ROUND(CP84,2) -> 31.43 | P84: =ROUND((ROUND((AC84*AW84*I84),2)*BC84),2) -> 31.43 | Q84: =(ROUND((ROUND(((ET84)*AV84*I84),2)*BB84),2)+ROUND((ROUND(((AE84-(EU84))*AV84*I84),2)*BS84),2)) -> 0 | R84: =ROUND((ROUND((AE84*AV84*I84),2)*BS84),2) -> 0 | S84: =ROUND((ROUND((AF84*AV84*I84),2)*BA84),2) -> 0 | T84: =ROUND(CU84*I84,2) -> 0 | U84: =CV84*I84 -> 0 | V84: =CW84*I84 -> 0 | W84: =ROUND(CX84*I84,2) -> 0 | X84: =ROUND(CY84,2) -> 0 | Y84: =ROUND(CZ84,2) -> 0 | AA84: 56503350 | AB84: =ROUND((AC84+AD84+AF84),6) -> 1.06 | AC84: =ROUND((ES84),6) -> 1.06 | AD84: =ROUND((((ET84)-(EU84))+AE84),6) -> 0 | AE84: =ROUND((EU84),6) -> 0 | AF84: =ROUND((EV84),6) -> 0 | AG84: =ROUND((AP84),6) -> 0 | AH84: =(EW84) -> 0 | AI84: =(EX84) -> 0 | AJ84: =(AS84) -> 0 | AK84: 1.06 | AL84: 1.06 | AM84: 0 | AN84: 0 | AO84: 0 | AP84: 0 | AQ84: 0 | AR84: 0 | AS84: 0 | AT84: 90 | AU84: 46 | AV84: 1 | AW84: 1 | AZ84: 1 | BA84: 1 | BB84: 1 | BC84: 5.93 | BH84: 3 | BI84: 2 | BJ84: ТСН-2001.1 Доп. 73, Р. 21, о. 5, поз. 896 | BM84: 68 | BN84: 0 | BO84: 1.21-5-896 | BP84: 1 | BQ84: 40 | BR84: 0 | BS84: 1 | BT84: 1 | BU84: 1 | BV84: 1 | BW84: 1 | BX84: 1 | BZ84: 90 | CA84: 46 | CE84: 30 | CF84: 0 | CG84: 0 | CM84: 0 | CO84: 0 | CP84: =(P84+Q84+S84) -> 31.43 | CQ84: =ROUND((ROUND((AC84*AW84*1),2)*BC84),2) -> 6.29 | CR84: =(ROUND((ROUND(((ET84)*AV84*1),2)*BB84),2)+ROUND((ROUND(((AE84-(EU84))*AV84*1),2)*BS84),2)) -> 0 | CS84: =ROUND((ROUND((AE84*AV84*1),2)*BS84),2) -> 0 | CT84: =ROUND((ROUND((AF84*AV84*1),2)*BA84),2) -> 0 | CU84: =AG84 -> 0 | CV84: =(AH84*AV84) -> 0 | CW84: =AI84 -> 0 | CX84: =AJ84 -> 0 | CY84: =(((S84+R84)*AT84)/100) -> 0 | CZ84: =(((S84+R84)*AU84)/100) -> 0 | DN84: 0 | DO84: 0 | DP84: 1 | DQ84: 1 | DU84: 1010 | DV84: шт. | DW84: шт. | DX84: 1 | EE84: 58162630 | EF84: 40 | EG84: Монтаж оборудования | EH84: 0 | EJ84: 2 | EK84: 68 | EL84: ТСН-2001.4-10. Прокладка и монтаж сетей связи | EM84: ТСН-2001.4-10-1 | EQ84: 0 | ER84: 1.06 | ES84: 1.06 | ET84: 0 | EU84: 0 | EV84: 0 | EW84: 0 | EX84: 0 | FQ84: 0 | FR84: 0 | FS84: 0 | FX84: 90 | FY84: 46 | GD84: 1 | GF84: -2026322809 | GG84: 2 | GH84: 1 | GI84: 2 | GJ84: 0 | GK84: 0 | GL84: =ROUND(IF(AND(BH84=3,BI84=3,FS84<>0),P84,0),2) -> 0 | GM84: =ROUND(O84+X84+Y84,2)+GX84 -> 31.43 | GN84: =IF(OR(BI84=0,BI84=1),GM84-GX84,0) -> 0 | GO84: =IF(BI84=2,GM84-GX84,0) -> 31.43 | GP84: =IF(BI84=4,GM84-GX84,0) -> 0 | GR84: 0 | GS84: 3 | GT84: 0 | GV84: =ROUND((GT84),6) -> 0 | GW84: 1 | GX84: =ROUND(HC84*I84,2) -> 0 | HA84: 0 | HB84: 0 | HC84: =GV84*GW84 -> 0 | HS84: 0 | IK84: 0
A85: 18 | B85: 1 | E85: 4,3 | F85: 1.21-5-1136 | G85: Держатель пластиковый с защелкой для крепления труб, рукавов и гибких вводов диаметром 20 мм | H85: 100 шт. | I85: =I79*J85 -> 6 | J85: 3 | K85: 3 | O85: =ROUND(CP85,2) -> 881.34 | P85: =ROUND((ROUND((AC85*AW85*I85),2)*BC85),2) -> 881.34 | Q85: =(ROUND((ROUND(((ET85)*AV85*I85),2)*BB85),2)+ROUND((ROUND(((AE85-(EU85))*AV85*I85),2)*BS85),2)) -> 0 | R85: =ROUND((ROUND((AE85*AV85*I85),2)*BS85),2) -> 0 | S85: =ROUND((ROUND((AF85*AV85*I85),2)*BA85),2) -> 0 | T85: =ROUND(CU85*I85,2) -> 0 | U85: =CV85*I85 -> 0 | V85: =CW85*I85 -> 0 | W85: =ROUND(CX85*I85,2) -> 0 | X85: =ROUND(CY85,2) -> 0 | Y85: =ROUND(CZ85,2) -> 0 | AA85: 56503348 | AB85: =ROUND((AC85+AD85+AF85),6) -> 146.89 | AC85: =ROUND((ES85),6) -> 146.89 | AD85: =ROUND((((ET85)-(EU85))+AE85),6) -> 0 | AE85: =ROUND((EU85),6) -> 0 | AF85: =ROUND((EV85),6) -> 0 | AG85: =ROUND((AP85),6) -> 0 | AH85: =(EW85) -> 0 | AI85: =(EX85) -> 0 | AJ85: =(AS85) -> 0 | AK85: 146.89 | AL85: 146.89 | AM85: 0 | AN85: 0 | AO85: 0 | AP85: 0 | AQ85: 0 | AR85: 0 | AS85: 0 | AT85: 90 | AU85: 46 | AV85: 1 | AW85: 1 | AZ85: 1 | BA85: 1 | BB85: 1 | BC85: 1 | BH85: 3 | BI85: 2 | BJ85: ТСН-2001.1 Доп. 73, Р. 21, о. 5, поз. 1136 | BM85: 68 | BN85: 0 | BP85: 0 | BQ85: 40 | BR85: 0 | BS85: 1 | BT85: 1 | BU85: 1 | BV85: 1 | BW85: 1 | BX85: 1 | BZ85: 90 | CA85: 46 | CE85: 30 | CF85: 0 | CG85: 0 | CM85: 0 | CO85: 0 | CP85: =(P85+Q85+S85) -> 881.34 | CQ85: =ROUND((ROUND((AC85*AW85*1),2)*BC85),2) -> 146.89 | CR85: =(ROUND((ROUND(((ET85)*AV85*1),2)*BB85),2)+ROUND((ROUND(((AE85-(EU85))*AV85*1),2)*BS85),2)) -> 0 | CS85: =ROUND((ROUND((AE85*AV85*1),2)*BS85),2) -> 0 | CT85: =ROUND((ROUND((AF85*AV85*1),2)*BA85),2) -> 0 | CU85: =AG85 -> 0 | CV85: =(AH85*AV85) -> 0 | CW85: =AI85 -> 0 | CX85: =AJ85 -> 0 | CY85: =(((S85+R85)*AT85)/100) -> 0 | CZ85: =(((S85+R85)*AU85)/100) -> 0 | DN85: 0 | DO85: 0 | DP85: 1 | DQ85: 1 | DU85: 1010 | DV85: 100 шт. | DW85: 100 шт. | DX85: 100 | EE85: 58162630 | EF85: 40 | EG85: Монтаж оборудования | EH85: 0 | EJ85: 2 | EK85: 68 | EL85: ТСН-2001.4-10. Прокладка и монтаж сетей связи | EM85: ТСН-2001.4-10-1 | EQ85: 0 | ER85: 146.89 | ES85: 146.89 | ET85: 0 | EU85: 0 | EV85: 0 | EW85: 0 | EX85: 0 | FQ85: 0 | FR85: 0 | FS85: 0 | FX85: 90 | FY85: 46 | GD85: 1 | GF85: -1171050213 | GG85: 2 | GH85: 1 | GI85: -2 | GJ85: 0 | GK85: 0 | GL85: =ROUND(IF(AND(BH85=3,BI85=3,FS85<>0),P85,0),2) -> 0 | GM85: =ROUND(O85+X85+Y85,2)+GX85 -> 881.34 | GN85: =IF(OR(BI85=0,BI85=1),GM85-GX85,0) -> 0 | GO85: =IF(BI85=2,GM85-GX85,0) -> 881.34 | GP85: =IF(BI85=4,GM85-GX85,0) -> 0 | GR85: 0 | GS85: 3 | GT85: 0 | GV85: =ROUND((GT85),6) -> 0 | GW85: 1 | GX85: =ROUND(HC85*I85,2) -> 0 | HA85: 0 | HB85: 0 | HC85: =GV85*GW85 -> 0 | HS85: 0 | IK85: 0
A86: 18 | B86: 1 | E86: 4,3 | F86: 1.21-5-1136 | G86: Держатель пластиковый с защелкой для крепления труб, рукавов и гибких вводов диаметром 20 мм | H86: 100 шт. | I86: =I80*J86 -> 6 | J86: 3 | K86: 3 | O86: =ROUND(CP86,2) -> 1789.12 | P86: =ROUND((ROUND((AC86*AW86*I86),2)*BC86),2) -> 1789.12 | Q86: =(ROUND((ROUND(((ET86)*AV86*I86),2)*BB86),2)+ROUND((ROUND(((AE86-(EU86))*AV86*I86),2)*BS86),2)) -> 0 | R86: =ROUND((ROUND((AE86*AV86*I86),2)*BS86),2) -> 0 | S86: =ROUND((ROUND((AF86*AV86*I86),2)*BA86),2) -> 0 | T86: =ROUND(CU86*I86,2) -> 0 | U86: =CV86*I86 -> 0 | V86: =CW86*I86 -> 0 | W86: =ROUND(CX86*I86,2) -> 0 | X86: =ROUND(CY86,2) -> 0 | Y86: =ROUND(CZ86,2) -> 0 | AA86: 56503350 | AB86: =ROUND((AC86+AD86+AF86),6) -> 146.89 | AC86: =ROUND((ES86),6) -> 146.89 | AD86: =ROUND((((ET86)-(EU86))+AE86),6) -> 0 | AE86: =ROUND((EU86),6) -> 0 | AF86: =ROUND((EV86),6) -> 0 | AG86: =ROUND((AP86),6) -> 0 | AH86: =(EW86) -> 0 | AI86: =(EX86) -> 0 | AJ86: =(AS86) -> 0 | AK86: 146.89 | AL86: 146.89 | AM86: 0 | AN86: 0 | AO86: 0 | AP86: 0 | AQ86: 0 | AR86: 0 | AS86: 0 | AT86: 90 | AU86: 46 | AV86: 1 | AW86: 1 | AZ86: 1 | BA86: 1 | BB86: 1 | BC86: 2.03 | BH86: 3 | BI86: 2 | BJ86: ТСН-2001.1 Доп. 73, Р. 21, о. 5, поз. 1136 | BM86: 68 | BN86: 0 | BO86: 1.21-5-1136 | BP86: 1 | BQ86: 40 | BR86: 0 | BS86: 1 | BT86: 1 | BU86: 1 | BV86: 1 | BW86: 1 | BX86: 1 | BZ86: 90 | CA86: 46 | CE86: 30 | CF86: 0 | CG86: 0 | CM86: 0 | CO86: 0 | CP86: =(P86+Q86+S86) -> 1789.12 | CQ86: =ROUND((ROUND((AC86*AW86*1),2)*BC86),2) -> 298.19 | CR86: =(ROUND((ROUND(((ET86)*AV86*1),2)*BB86),2)+ROUND((ROUND(((AE86-(EU86))*AV86*1),2)*BS86),2)) -> 0 | CS86: =ROUND((ROUND((AE86*AV86*1),2)*BS86),2) -> 0 | CT86: =ROUND((ROUND((AF86*AV86*1),2)*BA86),2) -> 0 | CU86: =AG86 -> 0 | CV86: =(AH86*AV86) -> 0 | CW86: =AI86 -> 0 | CX86: =AJ86 -> 0 | CY86: =(((S86+R86)*AT86)/100) -> 0 | CZ86: =(((S86+R86)*AU86)/100) -> 0 | DN86: 0 | DO86: 0 | DP86: 1 | DQ86: 1 | DU86: 1010 | DV86: 100 шт. | DW86: 100 шт. | DX86: 100 | EE86: 58162630 | EF86: 40 | EG86: Монтаж оборудования | EH86: 0 | EJ86: 2 | EK86: 68 | EL86: ТСН-2001.4-10. Прокладка и монтаж сетей связи | EM86: ТСН-2001.4-10-1 | EQ86: 0 | ER86: 146.89 | ES86: 146.89 | ET86: 0 | EU86: 0 | EV86: 0 | EW86: 0 | EX86: 0 | FQ86: 0 | FR86: 0 | FS86: 0 | FX86: 90 | FY86: 46 | GD86: 1 | GF86: -1171050213 | GG86: 2 | GH86: 1 | GI86: 2 | GJ86: 0 | GK86: 0 | GL86: =ROUND(IF(AND(BH86=3,BI86=3,FS86<>0),P86,0),2) -> 0 | GM86: =ROUND(O86+X86+Y86,2)+GX86 -> 1789.12 | GN86: =IF(OR(BI86=0,BI86=1),GM86-GX86,0) -> 0 | GO86: =IF(BI86=2,GM86-GX86,0) -> 1789.12 | GP86: =IF(BI86=4,GM86-GX86,0) -> 0 | GR86: 0 | GS86: 3 | GT86: 0 | GV86: =ROUND((GT86),6) -> 0 | GW86: 1 | GX86: =ROUND(HC86*I86,2) -> 0 | HA86: 0 | HB86: 0 | HC86: =GV86*GW86 -> 0 | HS86: 0 | IK86: 0
A87: 18 | B87: 1 | E87: 4,4 | F87: КА 2 | G87: Кабель коаксиальный РК 75-4,8-319нг(А)-LSLTx | H87: км | I87: =I79*J87 -> 0.255 | J87: 0.1275 | K87: 0.1275 | O87: =ROUND(CP87,2) -> 3522.41 | P87: =ROUND((ROUND((AC87*AW87*I87),2)*BC87),2) -> 3522.41 | Q87: =(ROUND((ROUND(((ET87)*AV87*I87),2)*BB87),2)+ROUND((ROUND(((AE87-(EU87))*AV87*I87),2)*BS87),2)) -> 0 | R87: =ROUND((ROUND((AE87*AV87*I87),2)*BS87),2) -> 0 | S87: =ROUND((ROUND((AF87*AV87*I87),2)*BA87),2) -> 0 | T87: =ROUND(CU87*I87,2) -> 0 | U87: =CV87*I87 -> 0 | V87: =CW87*I87 -> 0 | W87: =ROUND(CX87*I87,2) -> 0 | X87: =ROUND(CY87,2) -> 0 | Y87: =ROUND(CZ87,2) -> 0 | AA87: 56503348 | AB87: =ROUND((AC87+AD87+AF87),6) -> 13813.36 | AC87: =ROUND((ES87),6) -> 13813.36 | AD87: =ROUND((((ET87)-(EU87))+AE87),6) -> 0 | AE87: =ROUND((EU87),6) -> 0 | AF87: =ROUND((EV87),6) -> 0 | AG87: =ROUND((AP87),6) -> 0 | AH87: =(EW87) -> 0 | AI87: =(EX87) -> 0 | AJ87: =(AS87) -> 0 | AK87: 13813.36 | AL87: 13813.36 | AM87: 0 | AN87: 0 | AO87: 0 | AP87: 0 | AQ87: 0 | AR87: 0 | AS87: 0 | AT87: 90 | AU87: 46 | AV87: 1 | AW87: 1 | AZ87: 1 | BA87: 1 | BB87: 1 | BC87: 1 | BH87: 3 | BI87: 2 | BM87: 68 | BN87: 0 | BP87: 0 | BQ87: 40 | BR87: 0 | BS87: 1 | BT87: 1 | BU87: 1 | BV87: 1 | BW87: 1 | BX87: 1 | BZ87: 90 | CA87: 46 | CE87: 30 | CF87: 0 | CG87: 0 | CM87: 0 | CO87: 0 | CP87: =(P87+Q87+S87) -> 3522.41 | CQ87: =ROUND((ROUND((AC87*AW87*1),2)*BC87),2) -> 13813.36 | CR87: =(ROUND((ROUND(((ET87)*AV87*1),2)*BB87),2)+ROUND((ROUND(((AE87-(EU87))*AV87*1),2)*BS87),2)) -> 0 | CS87: =ROUND((ROUND((AE87*AV87*1),2)*BS87),2) -> 0 | CT87: =ROUND((ROUND((AF87*AV87*1),2)*BA87),2) -> 0 | CU87: =AG87 -> 0 | CV87: =(AH87*AV87) -> 0 | CW87: =AI87 -> 0 | CX87: =AJ87 -> 0 | CY87: =(((S87+R87)*AT87)/100) -> 0 | CZ87: =(((S87+R87)*AU87)/100) -> 0 | DN87: 0 | DO87: 0 | DP87: 1 | DQ87: 1 | DU87: 1003 | DV87: км | DW87: км | DX87: 1000 | EE87: 58162630 | EF87: 40 | EG87: Монтаж оборудования | EH87: 0 | EJ87: 2 | EK87: 68 | EL87: ТСН-2001.4-10. Прокладка и монтаж сетей связи | EM87: ТСН-2001.4-10-1 | EQ87: 0 | ER87: 0 | ES87: 13813.36 | ET87: 0 | EU87: 0 | EV87: 0 | EW87: 0 | EX87: 0 | FQ87: 0 | FR87: 0 | FS87: 0 | FX87: 90 | FY87: 46 | GA87: [160 560 / 1,2 / 9,88] + 2% Заг.скл | GD87: 1 | GF87: -1070144849 | GG87: 2 | GH87: 4 | GI87: -2 | GJ87: 0 | GK87: 0 | GL87: =ROUND(IF(AND(BH87=3,BI87=3,FS87<>0),P87,0),2) -> 0 | GM87: =ROUND(O87+X87+Y87,2)+GX87 -> 3522.41 | GN87: =IF(OR(BI87=0,BI87=1),GM87-GX87,0) -> 0 | GO87: =IF(BI87=2,GM87-GX87,0) -> 3522.41 | GP87: =IF(BI87=4,GM87-GX87,0) -> 0 | GR87: 0 | GS87: 2 | GT87: 0 | GV87: =ROUND((GT87),6) -> 0 | GW87: 1 | GX87: =ROUND(HC87*I87,2) -> 0 | HA87: 0 | HB87: 0 | HC87: =GV87*GW87 -> 0 | HE87: 0 | HF87: 2 | HS87: 0 | IK87: 0
A88: 18 | B88: 1 | E88: 4,4 | F88: КА 2 | G88: Кабель коаксиальный РК 75-4,8-319нг(А)-LSLTx | H88: км | I88: =I80*J88 -> 0.255 | J88: 0.1275 | K88: 0.1275 | O88: =ROUND(CP88,2) -> 34801.41 | P88: =ROUND((ROUND((AC88*AW88*I88),2)*BC88),2) -> 34801.41 | Q88: =(ROUND((ROUND(((ET88)*AV88*I88),2)*BB88),2)+ROUND((ROUND(((AE88-(EU88))*AV88*I88),2)*BS88),2)) -> 0 | R88: =ROUND((ROUND((AE88*AV88*I88),2)*BS88),2) -> 0 | S88: =ROUND((ROUND((AF88*AV88*I88),2)*BA88),2) -> 0 | T88: =ROUND(CU88*I88,2) -> 0 | U88: =CV88*I88 -> 0 | V88: =CW88*I88 -> 0 | W88: =ROUND(CX88*I88,2) -> 0 | X88: =ROUND(CY88,2) -> 0 | Y88: =ROUND(CZ88,2) -> 0 | AA88: 56503350 | AB88: =ROUND((AC88+AD88+AF88),6) -> 13813.36 | AC88: =ROUND((ES88),6) -> 13813.36 | AD88: =ROUND((((ET88)-(EU88))+AE88),6) -> 0 | AE88: =ROUND((EU88),6) -> 0 | AF88: =ROUND((EV88),6) -> 0 | AG88: =ROUND((AP88),6) -> 0 | AH88: =(EW88) -> 0 | AI88: =(EX88) -> 0 | AJ88: =(AS88) -> 0 | AK88: 13813.36 | AL88: 13813.36 | AM88: 0 | AN88: 0 | AO88: 0 | AP88: 0 | AQ88: 0 | AR88: 0 | AS88: 0 | AT88: 90 | AU88: 46 | AV88: 1 | AW88: 1 | AZ88: 1 | BA88: 1 | BB88: 1 | BC88: 9.88 | BH88: 3 | BI88: 2 | BM88: 68 | BN88: 0 | BP88: 0 | BQ88: 40 | BR88: 0 | BS88: 1 | BT88: 1 | BU88: 1 | BV88: 1 | BW88: 1 | BX88: 1 | BZ88: 90 | CA88: 46 | CE88: 30 | CF88: 0 | CG88: 0 | CM88: 0 | CO88: 0 | CP88: =(P88+Q88+S88) -> 34801.41 | CQ88: =ROUND((ROUND((AC88*AW88*1),2)*BC88),2) -> 136476 | CR88: =(ROUND((ROUND(((ET88)*AV88*1),2)*BB88),2)+ROUND((ROUND(((AE88-(EU88))*AV88*1),2)*BS88),2)) -> 0 | CS88: =ROUND((ROUND((AE88*AV88*1),2)*BS88),2) -> 0 | CT88: =ROUND((ROUND((AF88*AV88*1),2)*BA88),2) -> 0 | CU88: =AG88 -> 0 | CV88: =(AH88*AV88) -> 0 | CW88: =AI88 -> 0 | CX88: =AJ88 -> 0 | CY88: =(((S88+R88)*AT88)/100) -> 0 | CZ88: =(((S88+R88)*AU88)/100) -> 0 | DN88: 0 | DO88: 0 | DP88: 1 | DQ88: 1 | DU88: 1003 | DV88: км | DW88: км | DX88: 1000 | EE88: 58162630 | EF88: 40 | EG88: Монтаж оборудования | EH88: 0 | EJ88: 2 | EK88: 68 | EL88: ТСН-2001.4-10. Прокладка и монтаж сетей связи | EM88: ТСН-2001.4-10-1 | EQ88: 0 | ER88: 13813.36 | ES88: 13813.36 | ET88: 0 | EU88: 0 | EV88: 0 | EW88: 0 | EX88: 0 | EZ88: 5 | FC88: 1 | FD88: 18 | FF88: 160560 | FQ88: 0 | FR88: 0 | FS88: 0 | FX88: 90 | FY88: 46 | GA88: [160 560 / 1,2 / 9,88] + 2% Заг.скл | GD88: 1 | GF88: -1070144849 | GG88: 2 | GH88: 3 | GI88: 5 | GJ88: 0 | GK88: 0 | GL88: =ROUND(IF(AND(BH88=3,BI88=3,FS88<>0),P88,0),2) -> 0 | GM88: =ROUND(O88+X88+Y88,2)+GX88 -> 34801.41 | GN88: =IF(OR(BI88=0,BI88=1),GM88-GX88,0) -> 0 | GO88: =IF(BI88=2,GM88-GX88,0) -> 34801.41 | GP88: =IF(BI88=4,GM88-GX88,0) -> 0 | GR88: 1 | GS88: 1 | GT88: 0 | GV88: =ROUND((GT88),6) -> 0 | GW88: 1 | GX88: =ROUND(HC88*I88,2) -> 0 | HA88: 0 | HB88: 0 | HC88: =GV88*GW88 -> 0 | HE88: 0 | HF88: 2 | HS88: 0 | IK88: 0
A89: 18 | B89: 1 | E89: 4,5 | F89: КА 3 | G89: Кабель коаксиальный РК 75-7-327нг(А)-LSLTx | H89: км | I89: =I79*J89 -> 0.1377 | J89: 0.06885 | K89: 0.06885 | O89: =ROUND(CP89,2) -> 3068.05 | P89: =ROUND((ROUND((AC89*AW89*I89),2)*BC89),2) -> 3068.05 | Q89: =(ROUND((ROUND(((ET89)*AV89*I89),2)*BB89),2)+ROUND((ROUND(((AE89-(EU89))*AV89*I89),2)*BS89),2)) -> 0 | R89: =ROUND((ROUND((AE89*AV89*I89),2)*BS89),2) -> 0 | S89: =ROUND((ROUND((AF89*AV89*I89),2)*BA89),2) -> 0 | T89: =ROUND(CU89*I89,2) -> 0 | U89: =CV89*I89 -> 0 | V89: =CW89*I89 -> 0 | W89: =ROUND(CX89*I89,2) -> 0 | X89: =ROUND(CY89,2) -> 0 | Y89: =ROUND(CZ89,2) -> 0 | AA89: 56503348 | AB89: =ROUND((AC89+AD89+AF89),6) -> 22280.67 | AC89: =ROUND((ES89),6) -> 22280.67 | AD89: =ROUND((((ET89)-(EU89))+AE89),6) -> 0 | AE89: =ROUND((EU89),6) -> 0 | AF89: =ROUND((EV89),6) -> 0 | AG89: =ROUND((AP89),6) -> 0 | AH89: =(EW89) -> 0 | AI89: =(EX89) -> 0 | AJ89: =(AS89) -> 0 | AK89: 22280.67 | AL89: 22280.67 | AM89: 0 | AN89: 0 | AO89: 0 | AP89: 0 | AQ89: 0 | AR89: 0 | AS89: 0 | AT89: 90 | AU89: 46 | AV89: 1 | AW89: 1 | AZ89: 1 | BA89: 1 | BB89: 1 | BC89: 1 | BH89: 3 | BI89: 2 | BM89: 68 | BN89: 0 | BP89: 0 | BQ89: 40 | BR89: 0 | BS89: 1 | BT89: 1 | BU89: 1 | BV89: 1 | BW89: 1 | BX89: 1 | BZ89: 90 | CA89: 46 | CE89: 30 | CF89: 0 | CG89: 0 | CM89: 0 | CO89: 0 | CP89: =(P89+Q89+S89) -> 3068.05 | CQ89: =ROUND((ROUND((AC89*AW89*1),2)*BC89),2) -> 22280.67 | CR89: =(ROUND((ROUND(((ET89)*AV89*1),2)*BB89),2)+ROUND((ROUND(((AE89-(EU89))*AV89*1),2)*BS89),2)) -> 0 | CS89: =ROUND((ROUND((AE89*AV89*1),2)*BS89),2) -> 0 | CT89: =ROUND((ROUND((AF89*AV89*1),2)*BA89),2) -> 0 | CU89: =AG89 -> 0 | CV89: =(AH89*AV89) -> 0 | CW89: =AI89 -> 0 | CX89: =AJ89 -> 0 | CY89: =(((S89+R89)*AT89)/100) -> 0 | CZ89: =(((S89+R89)*AU89)/100) -> 0 | DN89: 0 | DO89: 0 | DP89: 1 | DQ89: 1 | DU89: 1003 | DV89: км | DW89: км | DX89: 1000 | EE89: 58162630 | EF89: 40 | EG89: Монтаж оборудования | EH89: 0 | EJ89: 2 | EK89: 68 | EL89: ТСН-2001.4-10. Прокладка и монтаж сетей связи | EM89: ТСН-2001.4-10-1 | EQ89: 0 | ER89: 0 | ES89: 22280.67 | ET89: 0 | EU89: 0 | EV89: 0 | EW89: 0 | EX89: 0 | FQ89: 0 | FR89: 0 | FS89: 0 | FX89: 90 | FY89: 46 | GA89: [258 980 / 1,2 / 9,88] + 2% Заг.скл | GD89: 1 | GF89: 585815009 | GG89: 2 | GH89: 4 | GI89: -2 | GJ89: 0 | GK89: 0 | GL89: =ROUND(IF(AND(BH89=3,BI89=3,FS89<>0),P89,0),2) -> 0 | GM89: =ROUND(O89+X89+Y89,2)+GX89 -> 3068.05 | GN89: =IF(OR(BI89=0,BI89=1),GM89-GX89,0) -> 0 | GO89: =IF(BI89=2,GM89-GX89,0) -> 3068.05 | GP89: =IF(BI89=4,GM89-GX89,0) -> 0 | GR89: 0 | GS89: 2 | GT89: 0 | GV89: =ROUND((GT89),6) -> 0 | GW89: 1 | GX89: =ROUND(HC89*I89,2) -> 0 | HA89: 0 | HB89: 0 | HC89: =GV89*GW89 -> 0 | HE89: 0 | HF89: 2 | HS89: 0 | IK89: 0
A90: 18 | B90: 1 | E90: 4,5 | F90: КА 3 | G90: Кабель коаксиальный РК 75-7-327нг(А)-LSLTx | H90: км | I90: =I80*J90 -> 0.1377 | J90: 0.06885 | K90: 0.06885 | O90: =ROUND(CP90,2) -> 30312.33 | P90: =ROUND((ROUND((AC90*AW90*I90),2)*BC90),2) -> 30312.33 | Q90: =(ROUND((ROUND(((ET90)*AV90*I90),2)*BB90),2)+ROUND((ROUND(((AE90-(EU90))*AV90*I90),2)*BS90),2)) -> 0 | R90: =ROUND((ROUND((AE90*AV90*I90),2)*BS90),2) -> 0 | S90: =ROUND((ROUND((AF90*AV90*I90),2)*BA90),2) -> 0 | T90: =ROUND(CU90*I90,2) -> 0 | U90: =CV90*I90 -> 0 | V90: =CW90*I90 -> 0 | W90: =ROUND(CX90*I90,2) -> 0 | X90: =ROUND(CY90,2) -> 0 | Y90: =ROUND(CZ90,2) -> 0 | AA90: 56503350 | AB90: =ROUND((AC90+AD90+AF90),6) -> 22280.67 | AC90: =ROUND((ES90),6) -> 22280.67 | AD90: =ROUND((((ET90)-(EU90))+AE90),6) -> 0 | AE90: =ROUND((EU90),6) -> 0 | AF90: =ROUND((EV90),6) -> 0 | AG90: =ROUND((AP90),6) -> 0 | AH90: =(EW90) -> 0 | AI90: =(EX90) -> 0 | AJ90: =(AS90) -> 0 | AK90: 22280.67 | AL90: 22280.67 | AM90: 0 | AN90: 0 | AO90: 0 | AP90: 0 | AQ90: 0 | AR90: 0 | AS90: 0 | AT90: 90 | AU90: 46 | AV90: 1 | AW90: 1 | AZ90: 1 | BA90: 1 | BB90: 1 | BC90: 9.88 | BH90: 3 | BI90: 2 | BM90: 68 | BN90: 0 | BP90: 0 | BQ90: 40 | BR90: 0 | BS90: 1 | BT90: 1 | BU90: 1 | BV90: 1 | BW90: 1 | BX90: 1 | BZ90: 90 | CA90: 46 | CE90: 30 | CF90: 0 | CG90: 0 | CM90: 0 | CO90: 0 | CP90: =(P90+Q90+S90) -> 30312.33 | CQ90: =ROUND((ROUND((AC90*AW90*1),2)*BC90),2) -> 220133.02 | CR90: =(ROUND((ROUND(((ET90)*AV90*1),2)*BB90),2)+ROUND((ROUND(((AE90-(EU90))*AV90*1),2)*BS90),2)) -> 0 | CS90: =ROUND((ROUND((AE90*AV90*1),2)*BS90),2) -> 0 | CT90: =ROUND((ROUND((AF90*AV90*1),2)*BA90),2) -> 0 | CU90: =AG90 -> 0 | CV90: =(AH90*AV90) -> 0 | CW90: =AI90 -> 0 | CX90: =AJ90 -> 0 | CY90: =(((S90+R90)*AT90)/100) -> 0 | CZ90: =(((S90+R90)*AU90)/100) -> 0 | DN90: 0 | DO90: 0 | DP90: 1 | DQ90: 1 | DU90: 1003 | DV90: км | DW90: км | DX90: 1000 | EE90: 58162630 | EF90: 40 | EG90: Монтаж оборудования | EH90: 0 | EJ90: 2 | EK90: 68 | EL90: ТСН-2001.4-10. Прокладка и монтаж сетей связи | EM90: ТСН-2001.4-10-1 | EQ90: 0 | ER90: 22280.67 | ES90: 22280.67 | ET90: 0 | EU90: 0 | EV90: 0 | EW90: 0 | EX90: 0 | EZ90: 5 | FC90: 1 | FD90: 18 | FF90: 258980 | FQ90: 0 | FR90: 0 | FS90: 0 | FX90: 90 | FY90: 46 | GA90: [258 980 / 1,2 / 9,88] + 2% Заг.скл | GD90: 1 | GF90: 585815009 | GG90: 2 | GH90: 3 | GI90: 5 | GJ90: 0 | GK90: 0 | GL90: =ROUND(IF(AND(BH90=3,BI90=3,FS90<>0),P90,0),2) -> 0 | GM90: =ROUND(O90+X90+Y90,2)+GX90 -> 30312.33 | GN90: =IF(OR(BI90=0,BI90=1),GM90-GX90,0) -> 0 | GO90: =IF(BI90=2,GM90-GX90,0) -> 30312.33 | GP90: =IF(BI90=4,GM90-GX90,0) -> 0 | GR90: 1 | GS90: 1 | GT90: 0 | GV90: =ROUND((GT90),6) -> 0 | GW90: 1 | GX90: =ROUND(HC90*I90,2) -> 0 | HA90: 0 | HB90: 0 | HC90: =GV90*GW90 -> 0 | HE90: 0 | HF90: 2 | HS90: 0 | IK90: 0
A91: 18 | B91: 1 | E91: 4,6 | F91: 1.14-1-281 | G91: Разъем телевизионный F для коаксиального кабеля стандарта RG11 | H91: шт. | I91: =I79*J91 -> 20 | J91: 10 | K91: 10 | O91: =ROUND(CP91,2) -> 613.8 | P91: =ROUND((ROUND((AC91*AW91*I91),2)*BC91),2) -> 613.8 | Q91: =(ROUND((ROUND(((ET91)*AV91*I91),2)*BB91),2)+ROUND((ROUND(((AE91-(EU91))*AV91*I91),2)*BS91),2)) -> 0 | R91: =ROUND((ROUND((AE91*AV91*I91),2)*BS91),2) -> 0 | S91: =ROUND((ROUND((AF91*AV91*I91),2)*BA91),2) -> 0 | T91: =ROUND(CU91*I91,2) -> 0 | U91: =CV91*I91 -> 0 | V91: =CW91*I91 -> 0 | W91: =ROUND(CX91*I91,2) -> 0 | X91: =ROUND(CY91,2) -> 0 | Y91: =ROUND(CZ91,2) -> 0 | AA91: 56503348 | AB91: =ROUND((AC91+AD91+AF91),6) -> 30.69 | AC91: =ROUND((ES91),6) -> 30.69 | AD91: =ROUND((((ET91)-(EU91))+AE91),6) -> 0 | AE91: =ROUND((EU91),6) -> 0 | AF91: =ROUND((EV91),6) -> 0 | AG91: =ROUND((AP91),6) -> 0 | AH91: =(EW91) -> 0 | AI91: =(EX91) -> 0 | AJ91: =(AS91) -> 0 | AK91: 30.69 | AL91: 30.69 | AM91: 0 | AN91: 0 | AO91: 0 | AP91: 0 | AQ91: 0 | AR91: 0 | AS91: 0 | AT91: 90 | AU91: 46 | AV91: 1 | AW91: 1 | AZ91: 1 | BA91: 1 | BB91: 1 | BC91: 1 | BH91: 3 | BI91: 2 | BJ91: ТСН-2001.1 Доп. 67, Р. 14, о. 1, поз. 281 | BM91: 68 | BN91: 0 | BP91: 0 | BQ91: 40 | BR91: 0 | BS91: 1 | BT91: 1 | BU91: 1 | BV91: 1 | BW91: 1 | BX91: 1 | BZ91: 90 | CA91: 46 | CE91: 30 | CF91: 0 | CG91: 0 | CM91: 0 | CO91: 0 | CP91: =(P91+Q91+S91) -> 613.8 | CQ91: =ROUND((ROUND((AC91*AW91*1),2)*BC91),2) -> 30.69 | CR91: =(ROUND((ROUND(((ET91)*AV91*1),2)*BB91),2)+ROUND((ROUND(((AE91-(EU91))*AV91*1),2)*BS91),2)) -> 0 | CS91: =ROUND((ROUND((AE91*AV91*1),2)*BS91),2) -> 0 | CT91: =ROUND((ROUND((AF91*AV91*1),2)*BA91),2) -> 0 | CU91: =AG91 -> 0 | CV91: =(AH91*AV91) -> 0 | CW91: =AI91 -> 0 | CX91: =AJ91 -> 0 | CY91: =(((S91+R91)*AT91)/100) -> 0 | CZ91: =(((S91+R91)*AU91)/100) -> 0 | DN91: 0 | DO91: 0 | DP91: 1 | DQ91: 1 | DU91: 1010 | DV91: шт. | DW91: шт. | DX91: 1 | EE91: 58162630 | EF91: 40 | EG91: Монтаж оборудования | EH91: 0 | EJ91: 2 | EK91: 68 | EL91: ТСН-2001.4-10. Прокладка и монтаж сетей связи | EM91: ТСН-2001.4-10-1 | EQ91: 0 | ER91: 30.69 | ES91: 30.69 | ET91: 0 | EU91: 0 | EV91: 0 | EW91: 0 | EX91: 0 | FQ91: 0 | FR91: 0 | FS91: 0 | FX91: 90 | FY91: 46 | GD91: 1 | GF91: -688640225 | GG91: 2 | GH91: 1 | GI91: -2 | GJ91: 0 | GK91: 0 | GL91: =ROUND(IF(AND(BH91=3,BI91=3,FS91<>0),P91,0),2) -> 0 | GM91: =ROUND(O91+X91+Y91,2)+GX91 -> 613.8 | GN91: =IF(OR(BI91=0,BI91=1),GM91-GX91,0) -> 0 | GO91: =IF(BI91=2,GM91-GX91,0) -> 613.8 | GP91: =IF(BI91=4,GM91-GX91,0) -> 0 | GR91: 0 | GS91: 3 | GT91: 0 | GV91: =ROUND((GT91),6) -> 0 | GW91: 1 | GX91: =ROUND(HC91*I91,2) -> 0 | HA91: 0 | HB91: 0 | HC91: =GV91*GW91 -> 0 | HS91: 0 | IK91: 0
A92: 18 | B92: 1 | E92: 4,6 | F92: 1.14-1-281 | G92: Разъем телевизионный F для коаксиального кабеля стандарта RG11 | H92: шт. | I92: =I80*J92 -> 20 | J92: 10 | K92: 10 | O92: =ROUND(CP92,2) -> 3535.49 | P92: =ROUND((ROUND((AC92*AW92*I92),2)*BC92),2) -> 3535.49 | Q92: =(ROUND((ROUND(((ET92)*AV92*I92),2)*BB92),2)+ROUND((ROUND(((AE92-(EU92))*AV92*I92),2)*BS92),2)) -> 0 | R92: =ROUND((ROUND((AE92*AV92*I92),2)*BS92),2) -> 0 | S92: =ROUND((ROUND((AF92*AV92*I92),2)*BA92),2) -> 0 | T92: =ROUND(CU92*I92,2) -> 0 | U92: =CV92*I92 -> 0 | V92: =CW92*I92 -> 0 | W92: =ROUND(CX92*I92,2) -> 0 | X92: =ROUND(CY92,2) -> 0 | Y92: =ROUND(CZ92,2) -> 0 | AA92: 56503350 | AB92: =ROUND((AC92+AD92+AF92),6) -> 30.69 | AC92: =ROUND((ES92),6) -> 30.69 | AD92: =ROUND((((ET92)-(EU92))+AE92),6) -> 0 | AE92: =ROUND((EU92),6) -> 0 | AF92: =ROUND((EV92),6) -> 0 | AG92: =ROUND((AP92),6) -> 0 | AH92: =(EW92) -> 0 | AI92: =(EX92) -> 0 | AJ92: =(AS92) -> 0 | AK92: 30.69 | AL92: 30.69 | AM92: 0 | AN92: 0 | AO92: 0 | AP92: 0 | AQ92: 0 | AR92: 0 | AS92: 0 | AT92: 90 | AU92: 46 | AV92: 1 | AW92: 1 | AZ92: 1 | BA92: 1 | BB92: 1 | BC92: 5.76 | BH92: 3 | BI92: 2 | BJ92: ТСН-2001.1 Доп. 67, Р. 14, о. 1, поз. 281 | BM92: 68 | BN92: 0 | BO92: 1.14-1-281 | BP92: 1 | BQ92: 40 | BR92: 0 | BS92: 1 | BT92: 1 | BU92: 1 | BV92: 1 | BW92: 1 | BX92: 1 | BZ92: 90 | CA92: 46 | CE92: 30 | CF92: 0 | CG92: 0 | CM92: 0 | CO92: 0 | CP92: =(P92+Q92+S92) -> 3535.49 | CQ92: =ROUND((ROUND((AC92*AW92*1),2)*BC92),2) -> 176.77 | CR92: =(ROUND((ROUND(((ET92)*AV92*1),2)*BB92),2)+ROUND((ROUND(((AE92-(EU92))*AV92*1),2)*BS92),2)) -> 0 | CS92: =ROUND((ROUND((AE92*AV92*1),2)*BS92),2) -> 0 | CT92: =ROUND((ROUND((AF92*AV92*1),2)*BA92),2) -> 0 | CU92: =AG92 -> 0 | CV92: =(AH92*AV92) -> 0 | CW92: =AI92 -> 0 | CX92: =AJ92 -> 0 | CY92: =(((S92+R92)*AT92)/100) -> 0 | CZ92: =(((S92+R92)*AU92)/100) -> 0 | DN92: 0 | DO92: 0 | DP92: 1 | DQ92: 1 | DU92: 1010 | DV92: шт. | DW92: шт. | DX92: 1 | EE92: 58162630 | EF92: 40 | EG92: Монтаж оборудования | EH92: 0 | EJ92: 2 | EK92: 68 | EL92: ТСН-2001.4-10. Прокладка и монтаж сетей связи | EM92: ТСН-2001.4-10-1 | EQ92: 0 | ER92: 30.69 | ES92: 30.69 | ET92: 0 | EU92: 0 | EV92: 0 | EW92: 0 | EX92: 0 | FQ92: 0 | FR92: 0 | FS92: 0 | FX92: 90 | FY92: 46 | GD92: 1 | GF92: -688640225 | GG92: 2 | GH92: 1 | GI92: 2 | GJ92: 0 | GK92: 0 | GL92: =ROUND(IF(AND(BH92=3,BI92=3,FS92<>0),P92,0),2) -> 0 | GM92: =ROUND(O92+X92+Y92,2)+GX92 -> 3535.49 | GN92: =IF(OR(BI92=0,BI92=1),GM92-GX92,0) -> 0 | GO92: =IF(BI92=2,GM92-GX92,0) -> 3535.49 | GP92: =IF(BI92=4,GM92-GX92,0) -> 0 | GR92: 0 | GS92: 3 | GT92: 0 | GV92: =ROUND((GT92),6) -> 0 | GW92: 1 | GX92: =ROUND(HC92*I92,2) -> 0 | HA92: 0 | HB92: 0 | HC92: =GV92*GW92 -> 0 | HS92: 0 | IK92: 0
A93: 18 | B93: 1 | E93: 4,7 | F93: 1.14-1-280 | G93: Разъем телевизионный F для коаксиального кабеля стандарта RG6 | H93: шт. | I93: =I79*J93 -> 15 | J93: 7.5 | K93: 7.5 | O93: =ROUND(CP93,2) -> 136.8 | P93: =ROUND((ROUND((AC93*AW93*I93),2)*BC93),2) -> 136.8 | Q93: =(ROUND((ROUND(((ET93)*AV93*I93),2)*BB93),2)+ROUND((ROUND(((AE93-(EU93))*AV93*I93),2)*BS93),2)) -> 0 | R93: =ROUND((ROUND((AE93*AV93*I93),2)*BS93),2) -> 0 | S93: =ROUND((ROUND((AF93*AV93*I93),2)*BA93),2) -> 0 | T93: =ROUND(CU93*I93,2) -> 0 | U93: =CV93*I93 -> 0 | V93: =CW93*I93 -> 0 | W93: =ROUND(CX93*I93,2) -> 0 | X93: =ROUND(CY93,2) -> 0 | Y93: =ROUND(CZ93,2) -> 0 | AA93: 56503348 | AB93: =ROUND((AC93+AD93+AF93),6) -> 9.12 | AC93: =ROUND((ES93),6) -> 9.12 | AD93: =ROUND((((ET93)-(EU93))+AE93),6) -> 0 | AE93: =ROUND((EU93),6) -> 0 | AF93: =ROUND((EV93),6) -> 0 | AG93: =ROUND((AP93),6) -> 0 | AH93: =(EW93) -> 0 | AI93: =(EX93) -> 0 | AJ93: =(AS93) -> 0 | AK93: 9.12 | AL93: 9.12 | AM93: 0 | AN93: 0 | AO93: 0 | AP93: 0 | AQ93: 0 | AR93: 0 | AS93: 0 | AT93: 90 | AU93: 46 | AV93: 1 | AW93: 1 | AZ93: 1 | BA93: 1 | BB93: 1 | BC93: 1 | BH93: 3 | BI93: 2 | BJ93: ТСН-2001.1 Доп. 67, Р. 14, о. 1, поз. 280 | BM93: 68 | BN93: 0 | BP93: 0 | BQ93: 40 | BR93: 0 | BS93: 1 | BT93: 1 | BU93: 1 | BV93: 1 | BW93: 1 | BX93: 1 | BZ93: 90 | CA93: 46 | CE93: 30 | CF93: 0 | CG93: 0 | CM93: 0 | CO93: 0 | CP93: =(P93+Q93+S93) -> 136.8 | CQ93: =ROUND((ROUND((AC93*AW93*1),2)*BC93),2) -> 9.12 | CR93: =(ROUND((ROUND(((ET93)*AV93*1),2)*BB93),2)+ROUND((ROUND(((AE93-(EU93))*AV93*1),2)*BS93),2)) -> 0 | CS93: =ROUND((ROUND((AE93*AV93*1),2)*BS93),2) -> 0 | CT93: =ROUND((ROUND((AF93*AV93*1),2)*BA93),2) -> 0 | CU93: =AG93 -> 0 | CV93: =(AH93*AV93) -> 0 | CW93: =AI93 -> 0 | CX93: =AJ93 -> 0 | CY93: =(((S93+R93)*AT93)/100) -> 0 | CZ93: =(((S93+R93)*AU93)/100) -> 0 | DN93: 0 | DO93: 0 | DP93: 1 | DQ93: 1 | DU93: 1010 | DV93: шт. | DW93: шт. | DX93: 1 | EE93: 58162630 | EF93: 40 | EG93: Монтаж оборудования | EH93: 0 | EJ93: 2 | EK93: 68 | EL93: ТСН-2001.4-10. Прокладка и монтаж сетей связи | EM93: ТСН-2001.4-10-1 | EQ93: 0 | ER93: 9.12 | ES93: 9.12 | ET93: 0 | EU93: 0 | EV93: 0 | EW93: 0 | EX93: 0 | FQ93: 0 | FR93: 0 | FS93: 0 | FX93: 90 | FY93: 46 | GD93: 1 | GF93: -664968350 | GG93: 2 | GH93: 1 | GI93: -2 | GJ93: 0 | GK93: 0 | GL93: =ROUND(IF(AND(BH93=3,BI93=3,FS93<>0),P93,0),2) -> 0 | GM93: =ROUND(O93+X93+Y93,2)+GX93 -> 136.8 | GN93: =IF(OR(BI93=0,BI93=1),GM93-GX93,0) -> 0 | GO93: =IF(BI93=2,GM93-GX93,0) -> 136.8 | GP93: =IF(BI93=4,GM93-GX93,0) -> 0 | GR93: 0 | GS93: 3 | GT93: 0 | GV93: =ROUND((GT93),6) -> 0 | GW93: 1 | GX93: =ROUND(HC93*I93,2) -> 0 | HA93: 0 | HB93: 0 | HC93: =GV93*GW93 -> 0 | HS93: 0 | IK93: 0
A94: 18 | B94: 1 | E94: 4,7 | F94: 1.14-1-280 | G94: Разъем телевизионный F для коаксиального кабеля стандарта RG6 | H94: шт. | I94: =I80*J94 -> 15 | J94: 7.5 | K94: 7.5 | O94: =ROUND(CP94,2) -> 366.62 | P94: =ROUND((ROUND((AC94*AW94*I94),2)*BC94),2) -> 366.62 | Q94: =(ROUND((ROUND(((ET94)*AV94*I94),2)*BB94),2)+ROUND((ROUND(((AE94-(EU94))*AV94*I94),2)*BS94),2)) -> 0 | R94: =ROUND((ROUND((AE94*AV94*I94),2)*BS94),2) -> 0 | S94: =ROUND((ROUND((AF94*AV94*I94),2)*BA94),2) -> 0 | T94: =ROUND(CU94*I94,2) -> 0 | U94: =CV94*I94 -> 0 | V94: =CW94*I94 -> 0 | W94: =ROUND(CX94*I94,2) -> 0 | X94: =ROUND(CY94,2) -> 0 | Y94: =ROUND(CZ94,2) -> 0 | AA94: 56503350 | AB94: =ROUND((AC94+AD94+AF94),6) -> 9.12 | AC94: =ROUND((ES94),6) -> 9.12 | AD94: =ROUND((((ET94)-(EU94))+AE94),6) -> 0 | AE94: =ROUND((EU94),6) -> 0 | AF94: =ROUND((EV94),6) -> 0 | AG94: =ROUND((AP94),6) -> 0 | AH94: =(EW94) -> 0 | AI94: =(EX94) -> 0 | AJ94: =(AS94) -> 0 | AK94: 9.12 | AL94: 9.12 | AM94: 0 | AN94: 0 | AO94: 0 | AP94: 0 | AQ94: 0 | AR94: 0 | AS94: 0 | AT94: 90 | AU94: 46 | AV94: 1 | AW94: 1 | AZ94: 1 | BA94: 1 | BB94: 1 | BC94: 2.68 | BH94: 3 | BI94: 2 | BJ94: ТСН-2001.1 Доп. 67, Р. 14, о. 1, поз. 280 | BM94: 68 | BN94: 0 | BO94: 1.14-1-280 | BP94: 1 | BQ94: 40 | BR94: 0 | BS94: 1 | BT94: 1 | BU94: 1 | BV94: 1 | BW94: 1 | BX94: 1 | BZ94: 90 | CA94: 46 | CE94: 30 | CF94: 0 | CG94: 0 | CM94: 0 | CO94: 0 | CP94: =(P94+Q94+S94) -> 366.62 | CQ94: =ROUND((ROUND((AC94*AW94*1),2)*BC94),2) -> 24.44 | CR94: =(ROUND((ROUND(((ET94)*AV94*1),2)*BB94),2)+ROUND((ROUND(((AE94-(EU94))*AV94*1),2)*BS94),2)) -> 0 | CS94: =ROUND((ROUND((AE94*AV94*1),2)*BS94),2) -> 0 | CT94: =ROUND((ROUND((AF94*AV94*1),2)*BA94),2) -> 0 | CU94: =AG94 -> 0 | CV94: =(AH94*AV94) -> 0 | CW94: =AI94 -> 0 | CX94: =AJ94 -> 0 | CY94: =(((S94+R94)*AT94)/100) -> 0 | CZ94: =(((S94+R94)*AU94)/100) -> 0 | DN94: 0 | DO94: 0 | DP94: 1 | DQ94: 1 | DU94: 1010 | DV94: шт. | DW94: шт. | DX94: 1 | EE94: 58162630 | EF94: 40 | EG94: Монтаж оборудования | EH94: 0 | EJ94: 2 | EK94: 68 | EL94: ТСН-2001.4-10. Прокладка и монтаж сетей связи | EM94: ТСН-2001.4-10-1 | EQ94: 0 | ER94: 9.12 | ES94: 9.12 | ET94: 0 | EU94: 0 | EV94: 0 | EW94: 0 | EX94: 0 | FQ94: 0 | FR94: 0 | FS94: 0 | FX94: 90 | FY94: 46 | GD94: 1 | GF94: -664968350 | GG94: 2 | GH94: 1 | GI94: 2 | GJ94: 0 | GK94: 0 | GL94: =ROUND(IF(AND(BH94=3,BI94=3,FS94<>0),P94,0),2) -> 0 | GM94: =ROUND(O94+X94+Y94,2)+GX94 -> 366.62 | GN94: =IF(OR(BI94=0,BI94=1),GM94-GX94,0) -> 0 | GO94: =IF(BI94=2,GM94-GX94,0) -> 366.62 | GP94: =IF(BI94=4,GM94-GX94,0) -> 0 | GR94: 0 | GS94: 3 | GT94: 0 | GV94: =ROUND((GT94),6) -> 0 | GW94: 1 | GX94: =ROUND(HC94*I94,2) -> 0 | HA94: 0 | HB94: 0 | HC94: =GV94*GW94 -> 0 | HS94: 0 | IK94: 0
A95: 17 | B95: 1 | D95: =ROW(EtalonRes!A52) -> 52 | F95: 4.8-175-2 | G95: Затягивание провода в проложенные трубы и металлические рукава, первого одножильного или многожильного в общей оплетке, суммарное сечение до 6 мм2 | H95: 100 м | I95: =ROUND(200/100,9) -> 2 | J95: 0 | K95: =ROUND(200/100,9) -> 2 | O95: =ROUND(CP95,2) -> 288.77 | P95: =ROUND((ROUND((AC95*AW95*I95),2)*BC95),2) -> 123.96 | Q95: =(ROUND((ROUND((((ET95*1.1))*AV95*I95),2)*BB95),2)+ROUND((ROUND(((AE95-((EU95*1.1)))*AV95*I95),2)*BS95),2)) -> 12.09 | R95: =ROUND((ROUND((AE95*AV95*I95),2)*BS95),2) -> 1.36 | S95: =ROUND((ROUND((AF95*AV95*I95),2)*BA95),2) -> 152.72 | T95: =ROUND(CU95*I95,2) -> 0 | U95: =CV95*I95 -> 12.415326 | V95: =CW95*I95 -> 0 | W95: =ROUND(CX95*I95,2) -> 0 | X95: =ROUND(CY95,2) -> 149.46 | Y95: =ROUND(CZ95,2) -> 78.58 | AA95: -1 | AB95: =ROUND((AC95+AD95+AF95),6) -> 140.685 | AC95: =ROUND((ES95),6) -> 61.98 | AD95: =ROUND(((((ET95*1.1))-((EU95*1.1)))+AE95),6) -> 5.775 | AE95: =ROUND(((EU95*1.1)),6) -> 0.649 | AF95: =ROUND(((EV95*1.1)),6) -> 72.93 | AG95: =ROUND((AP95),6) -> 0 | AH95: =((EW95*1.1)) -> 5.929 | AI95: =((EX95*1.1)) -> 0 | AJ95: =(AS95) -> 0 | AK95: 133.53 | AL95: 61.98 | AM95: 5.25 | AN95: 0.59 | AO95: 66.3 | AP95: 0 | AQ95: 5.39 | AR95: 0 | AS95: 0 | AT95: 97 | AU95: 51 | AV95: 1.047 | AW95: 1 | AZ95: 1 | BA95: 1 | BB95: 1 | BC95: 1 | BH95: 0 | BI95: 2 | BJ95: ТСН-2001.4 Доп. 79, Сб. 8, т. 175, поз. 2 | BM95: 67 | BN95: 0 | BO95: 4.8-175-2 | BP95: 1 | BQ95: 40 | BR95: 0 | BS95: 1 | BT95: 1 | BU95: 1 | BV95: 1 | BW95: 1 | BX95: 1 | BZ95: 97 | CA95: 51 | CE95: 30 | CF95: 0 | CG95: 0 | CM95: 0 | CO95: 0 | CP95: =(P95+Q95+S95) -> 288.77 | CQ95: =ROUND((ROUND((AC95*AW95*1),2)*BC95),2) -> 61.98 | CR95: =(ROUND((ROUND((((ET95*1.1))*AV95*1),2)*BB95),2)+ROUND((ROUND(((AE95-((EU95*1.1)))*AV95*1),2)*BS95),2)) -> 6.05 | CS95: =ROUND((ROUND((AE95*AV95*1),2)*BS95),2) -> 0.68 | CT95: =ROUND((ROUND((AF95*AV95*1),2)*BA95),2) -> 76.36 | CU95: =AG95 -> 0 | CV95: =(AH95*AV95) -> 6.207663 | CW95: =AI95 -> 0 | CX95: =AJ95 -> 0 | CY95: =(((S95+R95)*AT95)/100) -> 149.4576 | CZ95: =(((S95+R95)*AU95)/100) -> 78.5808 | DE95: *1,1 | DF95: *1,1 | DG95: *1,1 | DI95: *1,1 | DJ95: *1,1 | DN95: 0 | DO95: 0 | DP95: 1 | DQ95: 1 | DU95: 1003 | DV95: 100 м | DW95: 100 м | DX95: 100 | EE95: 58162629 | EF95: 40 | EG95: Монтаж оборудования | EH95: 0 | EJ95: 2 | EK95: 67 | EL95: ТСН-2001.4-8. Электротехнические установки | EM95: ТСН-2001.4-8-1 | EO95: Поправка: Гл.12.Прил.8.п.8. 5_12.00.01.11.003 | EQ95: 1024 | ER95: 133.53 | ES95: 61.98 | ET95: 5.25 | EU95: 0.59 | EV95: 66.3 | EW95: 5.39 | EX95: 0 | EY95: 0 | FQ95: 0 | FR95: 0 | FS95: 0 | FX95: 97 | FY95: 51 | GD95: 1 | GF95: -1822715932 | GG95: 2 | GH95: 1 | GI95: 2 | GJ95: 0 | GK95: 0 | GL95: =ROUND(IF(AND(BH95=3,BI95=3,FS95<>0),P95,0),2) -> 0 | GM95: =ROUND(O95+X95+Y95,2)+GX95 -> 516.81 | GN95: =IF(OR(BI95=0,BI95=1),GM95-GX95,0) -> 0 | GO95: =IF(BI95=2,GM95-GX95,0) -> 516.81 | GP95: =IF(BI95=4,GM95-GX95,0) -> 0 | GR95: 0 | GS95: 3 | GT95: 0 | GV95: =ROUND((GT95),6) -> 0 | GW95: 1 | GX95: =ROUND(HC95*I95,2) -> 0 | HA95: 0 | HB95: 0 | HC95: =GV95*GW95 -> 0 | HS95: 0 | IK95: 0
A96: 17 | B96: 1 | D96: =ROW(EtalonRes!A62) -> 62 | F96: 4.8-175-2 | G96: Затягивание провода в проложенные трубы и металлические рукава, первого одножильного или многожильного в общей оплетке, суммарное сечение до 6 мм2 | H96: 100 м | I96: =ROUND(200/100,9) -> 2 | J96: 0 | K96: =ROUND(200/100,9) -> 2 | O96: =ROUND(CP96,2) -> 9135.4 | P96: =ROUND((ROUND((AC96*AW96*I96),2)*BC96),2) -> 561.54 | Q96: =(ROUND((ROUND((((ET96*1.1))*AV96*I96),2)*BB96),2)+ROUND((ROUND(((AE96-((EU96*1.1)))*AV96*I96),2)*BS96),2)) -> 175.79 | R96: =ROUND((ROUND((AE96*AV96*I96),2)*BS96),2) -> 74.79 | S96: =ROUND((ROUND((AF96*AV96*I96),2)*BA96),2) -> 8398.07 | T96: =ROUND(CU96*I96,2) -> 0 | U96: =CV96*I96 -> 12.415326 | V96: =CW96*I96 -> 0 | W96: =ROUND(CX96*I96,2) -> 0 | X96: =ROUND(CY96,2) -> 8218.67 | Y96: =ROUND(CZ96,2) -> 4321.16 | AA96: -1 | AB96: =ROUND((AC96+AD96+AF96),6) -> 140.685 | AC96: =ROUND((ES96),6) -> 61.98 | AD96: =ROUND(((((ET96*1.1))-((EU96*1.1)))+AE96),6) -> 5.775 | AE96: =ROUND(((EU96*1.1)),6) -> 0.649 | AF96: =ROUND(((EV96*1.1)),6) -> 72.93 | AG96: =ROUND((AP96),6) -> 0 | AH96: =((EW96*1.1)) -> 5.929 | AI96: =((EX96*1.1)) -> 0 | AJ96: =(AS96) -> 0 | AK96: 133.53 | AL96: 61.98 | AM96: 5.25 | AN96: 0.59 | AO96: 66.3 | AP96: 0 | AQ96: 5.39 | AR96: 0 | AS96: 0 | AT96: 97 | AU96: 51 | AV96: 1.047 | AW96: 1 | AZ96: 1 | BA96: 54.99 | BB96: 14.54 | BC96: 4.53 | BH96: 0 | BI96: 2 | BJ96: ТСН-2001.4 Доп. 79, Сб. 8, т. 175, поз. 2 | BM96: 67 | BN96: 0 | BO96: 4.8-175-2 | BP96: 1 | BQ96: 40 | BR96: 0 | BS96: 54.99 | BT96: 1 | BU96: 1 | BV96: 1 | BW96: 1 | BX96: 1 | BZ96: 97 | CA96: 51 | CE96: 30 | CF96: 0 | CG96: 0 | CM96: 0 | CO96: 0 | CP96: =(P96+Q96+S96) -> 9135.4 | CQ96: =ROUND((ROUND((AC96*AW96*1),2)*BC96),2) -> 280.77 | CR96: =(ROUND((ROUND((((ET96*1.1))*AV96*1),2)*BB96),2)+ROUND((ROUND(((AE96-((EU96*1.1)))*AV96*1),2)*BS96),2)) -> 87.97 | CS96: =ROUND((ROUND((AE96*AV96*1),2)*BS96),2) -> 37.39 | CT96: =ROUND((ROUND((AF96*AV96*1),2)*BA96),2) -> 4199.04 | CU96: =AG96 -> 0 | CV96: =(AH96*AV96) -> 6.207663 | CW96: =AI96 -> 0 | CX96: =AJ96 -> 0 | CY96: =(((S96+R96)*AT96)/100) -> 8218.6742 | CZ96: =(((S96+R96)*AU96)/100) -> 4321.1586 | DE96: *1,1 | DF96: *1,1 | DG96: *1,1 | DI96: *1,1 | DJ96: *1,1 | DN96: 0 | DO96: 0 | DP96: 1 | DQ96: 1 | DU96: 1003 | DV96: 100 м | DW96: 100 м | DX96: 100 | EE96: 58162629 | EF96: 40 | EG96: Монтаж оборудования | EH96: 0 | EJ96: 2 | EK96: 67 | EL96: ТСН-2001.4-8. Электротехнические установки | EM96: ТСН-2001.4-8-1 | EO96: Поправка: Гл.12.Прил.8.п.8. 5_12.00.01.11.003 | EQ96: 1024 | ER96: 133.53 | ES96: 61.98 | ET96: 5.25 | EU96: 0.59 | EV96: 66.3 | EW96: 5.39 | EX96: 0 | EY96: 0 | FQ96: 0 | FR96: 0 | FS96: 0 | FX96: 97 | FY96: 51 | GD96: 1 | GF96: -1822715932 | GG96: 2 | GH96: 1 | GI96: 2 | GJ96: 0 | GK96: 0 | GL96: =ROUND(IF(AND(BH96=3,BI96=3,FS96<>0),P96,0),2) -> 0 | GM96: =ROUND(O96+X96+Y96,2)+GX96 -> 21675.23 | GN96: =IF(OR(BI96=0,BI96=1),GM96-GX96,0) -> 0 | GO96: =IF(BI96=2,GM96-GX96,0) -> 21675.23 | GP96: =IF(BI96=4,GM96-GX96,0) -> 0 | GR96: 0 | GS96: 3 | GT96: 0 | GV96: =ROUND((GT96),6) -> 0 | GW96: 1 | GX96: =ROUND(HC96*I96,2) -> 0 | HA96: 0 | HB96: 0 | HC96: =GV96*GW96 -> 0 | HS96: 0 | IK96: 0
A97: 18 | B97: 1 | F97: КА 2 | G97: Кабель коаксиальный РК 75-4,8-319нг(А)-LSLTx | H97: км | I97: =I95*J97 -> 0.204 | J97: 0.102 | K97: 0.102 | O97: =ROUND(CP97,2) -> 2817.93 | P97: =ROUND((ROUND((AC97*AW97*I97),2)*BC97),2) -> 2817.93 | Q97: =(ROUND((ROUND(((ET97)*AV97*I97),2)*BB97),2)+ROUND((ROUND(((AE97-(EU97))*AV97*I97),2)*BS97),2)) -> 0 | R97: =ROUND((ROUND((AE97*AV97*I97),2)*BS97),2) -> 0 | S97: =ROUND((ROUND((AF97*AV97*I97),2)*BA97),2) -> 0 | T97: =ROUND(CU97*I97,2) -> 0 | U97: =CV97*I97 -> 0 | V97: =CW97*I97 -> 0 | W97: =ROUND(CX97*I97,2) -> 0 | X97: =ROUND(CY97,2) -> 0 | Y97: =ROUND(CZ97,2) -> 0 | AA97: -1 | AB97: =ROUND((AC97+AD97+AF97),6) -> 13813.36 | AC97: =ROUND((ES97),6) -> 13813.36 | AD97: =ROUND((((ET97)-(EU97))+AE97),6) -> 0 | AE97: =ROUND((EU97),6) -> 0 | AF97: =ROUND((EV97),6) -> 0 | AG97: =ROUND((AP97),6) -> 0 | AH97: =(EW97) -> 0 | AI97: =(EX97) -> 0 | AJ97: =(AS97) -> 0 | AK97: 13813.36 | AL97: 13813.36 | AM97: 0 | AN97: 0 | AO97: 0 | AP97: 0 | AQ97: 0 | AR97: 0 | AS97: 0 | AT97: 97 | AU97: 51 | AV97: 1 | AW97: 1 | AZ97: 1 | BA97: 1 | BB97: 1 | BC97: 1 | BH97: 3 | BI97: 2 | BM97: 67 | BN97: 0 | BP97: 0 | BQ97: 40 | BR97: 0 | BS97: 1 | BT97: 1 | BU97: 1 | BV97: 1 | BW97: 1 | BX97: 1 | BZ97: 97 | CA97: 51 | CE97: 30 | CF97: 0 | CG97: 0 | CM97: 0 | CO97: 0 | CP97: =(P97+Q97+S97) -> 2817.93 | CQ97: =ROUND((ROUND((AC97*AW97*1),2)*BC97),2) -> 13813.36 | CR97: =(ROUND((ROUND(((ET97)*AV97*1),2)*BB97),2)+ROUND((ROUND(((AE97-(EU97))*AV97*1),2)*BS97),2)) -> 0 | CS97: =ROUND((ROUND((AE97*AV97*1),2)*BS97),2) -> 0 | CT97: =ROUND((ROUND((AF97*AV97*1),2)*BA97),2) -> 0 | CU97: =AG97 -> 0 | CV97: =(AH97*AV97) -> 0 | CW97: =AI97 -> 0 | CX97: =AJ97 -> 0 | CY97: =(((S97+R97)*AT97)/100) -> 0 | CZ97: =(((S97+R97)*AU97)/100) -> 0 | DN97: 0 | DO97: 0 | DP97: 1 | DQ97: 1 | DU97: 1003 | DV97: км | DW97: км | DX97: 1000 | EE97: 58162629 | EF97: 40 | EG97: Монтаж оборудования | EH97: 0 | EJ97: 2 | EK97: 67 | EL97: ТСН-2001.4-8. Электротехнические установки | EM97: ТСН-2001.4-8-1 | EQ97: 1024 | ER97: 0 | ES97: 13813.36 | ET97: 0 | EU97: 0 | EV97: 0 | EW97: 0 | EX97: 0 | FQ97: 0 | FR97: 0 | FS97: 0 | FX97: 97 | FY97: 51 | GA97: [160 560 / 1,2 / 9,88] + 2% Заг.скл | GD97: 1 | GF97: -1070144849 | GG97: 2 | GH97: 4 | GI97: -2 | GJ97: 0 | GK97: 0 | GL97: =ROUND(IF(AND(BH97=3,BI97=3,FS97<>0),P97,0),2) -> 0 | GM97: =ROUND(O97+X97+Y97,2)+GX97 -> 2817.93 | GN97: =IF(OR(BI97=0,BI97=1),GM97-GX97,0) -> 0 | GO97: =IF(BI97=2,GM97-GX97,0) -> 2817.93 | GP97: =IF(BI97=4,GM97-GX97,0) -> 0 | GR97: 0 | GS97: 2 | GT97: 0 | GV97: =ROUND((GT97),6) -> 0 | GW97: 1 | GX97: =ROUND(HC97*I97,2) -> 0 | HA97: 0 | HB97: 0 | HC97: =GV97*GW97 -> 0 | HE97: 0 | HF97: 2 | HS97: 0 | IK97: 0
A98: 18 | B98: 1 | F98: КА 2 | G98: Кабель коаксиальный РК 75-4,8-319нг(А)-LSLTx | H98: км | I98: =I96*J98 -> 0.204 | J98: 0.102 | K98: 0.102 | O98: =ROUND(CP98,2) -> 27841.15 | P98: =ROUND((ROUND((AC98*AW98*I98),2)*BC98),2) -> 27841.15 | Q98: =(ROUND((ROUND(((ET98)*AV98*I98),2)*BB98),2)+ROUND((ROUND(((AE98-(EU98))*AV98*I98),2)*BS98),2)) -> 0 | R98: =ROUND((ROUND((AE98*AV98*I98),2)*BS98),2) -> 0 | S98: =ROUND((ROUND((AF98*AV98*I98),2)*BA98),2) -> 0 | T98: =ROUND(CU98*I98,2) -> 0 | U98: =CV98*I98 -> 0 | V98: =CW98*I98 -> 0 | W98: =ROUND(CX98*I98,2) -> 0 | X98: =ROUND(CY98,2) -> 0 | Y98: =ROUND(CZ98,2) -> 0 | AA98: -1 | AB98: =ROUND((AC98+AD98+AF98),6) -> 13813.36 | AC98: =ROUND((ES98),6) -> 13813.36 | AD98: =ROUND((((ET98)-(EU98))+AE98),6) -> 0 | AE98: =ROUND((EU98),6) -> 0 | AF98: =ROUND((EV98),6) -> 0 | AG98: =ROUND((AP98),6) -> 0 | AH98: =(EW98) -> 0 | AI98: =(EX98) -> 0 | AJ98: =(AS98) -> 0 | AK98: 13813.36 | AL98: 13813.36 | AM98: 0 | AN98: 0 | AO98: 0 | AP98: 0 | AQ98: 0 | AR98: 0 | AS98: 0 | AT98: 97 | AU98: 51 | AV98: 1 | AW98: 1 | AZ98: 1 | BA98: 1 | BB98: 1 | BC98: 9.88 | BH98: 3 | BI98: 2 | BM98: 67 | BN98: 0 | BP98: 0 | BQ98: 40 | BR98: 0 | BS98: 1 | BT98: 1 | BU98: 1 | BV98: 1 | BW98: 1 | BX98: 1 | BZ98: 97 | CA98: 51 | CE98: 30 | CF98: 0 | CG98: 0 | CM98: 0 | CO98: 0 | CP98: =(P98+Q98+S98) -> 27841.15 | CQ98: =ROUND((ROUND((AC98*AW98*1),2)*BC98),2) -> 136476 | CR98: =(ROUND((ROUND(((ET98)*AV98*1),2)*BB98),2)+ROUND((ROUND(((AE98-(EU98))*AV98*1),2)*BS98),2)) -> 0 | CS98: =ROUND((ROUND((AE98*AV98*1),2)*BS98),2) -> 0 | CT98: =ROUND((ROUND((AF98*AV98*1),2)*BA98),2) -> 0 | CU98: =AG98 -> 0 | CV98: =(AH98*AV98) -> 0 | CW98: =AI98 -> 0 | CX98: =AJ98 -> 0 | CY98: =(((S98+R98)*AT98)/100) -> 0 | CZ98: =(((S98+R98)*AU98)/100) -> 0 | DN98: 0 | DO98: 0 | DP98: 1 | DQ98: 1 | DU98: 1003 | DV98: км | DW98: км | DX98: 1000 | EE98: 58162629 | EF98: 40 | EG98: Монтаж оборудования | EH98: 0 | EJ98: 2 | EK98: 67 | EL98: ТСН-2001.4-8. Электротехнические установки | EM98: ТСН-2001.4-8-1 | EQ98: 1024 | ER98: 13813.36 | ES98: 13813.36 | ET98: 0 | EU98: 0 | EV98: 0 | EW98: 0 | EX98: 0 | EZ98: 5 | FC98: 1 | FD98: 18 | FF98: 160560 | FQ98: 0 | FR98: 0 | FS98: 0 | FX98: 97 | FY98: 51 | GA98: [160 560 / 1,2 / 9,88] + 2% Заг.скл | GD98: 1 | GF98: -1070144849 | GG98: 2 | GH98: 3 | GI98: 5 | GJ98: 0 | GK98: 0 | GL98: =ROUND(IF(AND(BH98=3,BI98=3,FS98<>0),P98,0),2) -> 0 | GM98: =ROUND(O98+X98+Y98,2)+GX98 -> 27841.15 | GN98: =IF(OR(BI98=0,BI98=1),GM98-GX98,0) -> 0 | GO98: =IF(BI98=2,GM98-GX98,0) -> 27841.15 | GP98: =IF(BI98=4,GM98-GX98,0) -> 0 | GR98: 1 | GS98: 1 | GT98: 0 | GV98: =ROUND((GT98),6) -> 0 | GW98: 1 | GX98: =ROUND(HC98*I98,2) -> 0 | HA98: 0 | HB98: 0 | HC98: =GV98*GW98 -> 0 | HE98: 0 | HF98: 2 | HS98: 0 | IK98: 0
A99: 18 | B99: 1 | F99: 1.14-1-281 | G99: Разъем телевизионный F для коаксиального кабеля стандарта RG11 | H99: шт. | I99: =I95*J99 -> 20 | J99: 10 | K99: 10 | O99: =ROUND(CP99,2) -> 613.8 | P99: =ROUND((ROUND((AC99*AW99*I99),2)*BC99),2) -> 613.8 | Q99: =(ROUND((ROUND(((ET99)*AV99*I99),2)*BB99),2)+ROUND((ROUND(((AE99-(EU99))*AV99*I99),2)*BS99),2)) -> 0 | R99: =ROUND((ROUND((AE99*AV99*I99),2)*BS99),2) -> 0 | S99: =ROUND((ROUND((AF99*AV99*I99),2)*BA99),2) -> 0 | T99: =ROUND(CU99*I99,2) -> 0 | U99: =CV99*I99 -> 0 | V99: =CW99*I99 -> 0 | W99: =ROUND(CX99*I99,2) -> 0 | X99: =ROUND(CY99,2) -> 0 | Y99: =ROUND(CZ99,2) -> 0 | AA99: -1 | AB99: =ROUND((AC99+AD99+AF99),6) -> 30.69 | AC99: =ROUND((ES99),6) -> 30.69 | AD99: =ROUND((((ET99)-(EU99))+AE99),6) -> 0 | AE99: =ROUND((EU99),6) -> 0 | AF99: =ROUND((EV99),6) -> 0 | AG99: =ROUND((AP99),6) -> 0 | AH99: =(EW99) -> 0 | AI99: =(EX99) -> 0 | AJ99: =(AS99) -> 0 | AK99: 30.69 | AL99: 30.69 | AM99: 0 | AN99: 0 | AO99: 0 | AP99: 0 | AQ99: 0 | AR99: 0 | AS99: 0 | AT99: 97 | AU99: 51 | AV99: 1 | AW99: 1 | AZ99: 1 | BA99: 1 | BB99: 1 | BC99: 1 | BH99: 3 | BI99: 2 | BJ99: ТСН-2001.1 Доп. 67, Р. 14, о. 1, поз. 281 | BM99: 67 | BN99: 0 | BP99: 0 | BQ99: 40 | BR99: 0 | BS99: 1 | BT99: 1 | BU99: 1 | BV99: 1 | BW99: 1 | BX99: 1 | BZ99: 97 | CA99: 51 | CE99: 30 | CF99: 0 | CG99: 0 | CM99: 0 | CO99: 0 | CP99: =(P99+Q99+S99) -> 613.8 | CQ99: =ROUND((ROUND((AC99*AW99*1),2)*BC99),2) -> 30.69 | CR99: =(ROUND((ROUND(((ET99)*AV99*1),2)*BB99),2)+ROUND((ROUND(((AE99-(EU99))*AV99*1),2)*BS99),2)) -> 0 | CS99: =ROUND((ROUND((AE99*AV99*1),2)*BS99),2) -> 0 | CT99: =ROUND((ROUND((AF99*AV99*1),2)*BA99),2) -> 0 | CU99: =AG99 -> 0 | CV99: =(AH99*AV99) -> 0 | CW99: =AI99 -> 0 | CX99: =AJ99 -> 0 | CY99: =(((S99+R99)*AT99)/100) -> 0 | CZ99: =(((S99+R99)*AU99)/100) -> 0 | DN99: 0 | DO99: 0 | DP99: 1 | DQ99: 1 | DU99: 1010 | DV99: шт. | DW99: шт. | DX99: 1 | EE99: 58162629 | EF99: 40 | EG99: Монтаж оборудования | EH99: 0 | EJ99: 2 | EK99: 67 | EL99: ТСН-2001.4-8. Электротехнические установки | EM99: ТСН-2001.4-8-1 | EQ99: 1024 | ER99: 30.69 | ES99: 30.69 | ET99: 0 | EU99: 0 | EV99: 0 | EW99: 0 | EX99: 0 | FQ99: 0 | FR99: 0 | FS99: 0 | FX99: 97 | FY99: 51 | GD99: 1 | GF99: -688640225 | GG99: 2 | GH99: 1 | GI99: -2 | GJ99: 0 | GK99: 0 | GL99: =ROUND(IF(AND(BH99=3,BI99=3,FS99<>0),P99,0),2) -> 0 | GM99: =ROUND(O99+X99+Y99,2)+GX99 -> 613.8 | GN99: =IF(OR(BI99=0,BI99=1),GM99-GX99,0) -> 0 | GO99: =IF(BI99=2,GM99-GX99,0) -> 613.8 | GP99: =IF(BI99=4,GM99-GX99,0) -> 0 | GR99: 0 | GS99: 3 | GT99: 0 | GV99: =ROUND((GT99),6) -> 0 | GW99: 1 | GX99: =ROUND(HC99*I99,2) -> 0 | HA99: 0 | HB99: 0 | HC99: =GV99*GW99 -> 0 | HS99: 0 | IK99: 0
A100: 18 | B100: 1 | F100: 1.14-1-281 | G100: Разъем телевизионный F для коаксиального кабеля стандарта RG11 | H100: шт. | I100: =I96*J100 -> 20 | J100: 10 | K100: 10 | O100: =ROUND(CP100,2) -> 3535.49 | P100: =ROUND((ROUND((AC100*AW100*I100),2)*BC100),2) -> 3535.49 | Q100: =(ROUND((ROUND(((ET100)*AV100*I100),2)*BB100),2)+ROUND((ROUND(((AE100-(EU100))*AV100*I100),2)*BS100),2)) -> 0 | R100: =ROUND((ROUND((AE100*AV100*I100),2)*BS100),2) -> 0 | S100: =ROUND((ROUND((AF100*AV100*I100),2)*BA100),2) -> 0 | T100: =ROUND(CU100*I100,2) -> 0 | U100: =CV100*I100 -> 0 | V100: =CW100*I100 -> 0 | W100: =ROUND(CX100*I100,2) -> 0 | X100: =ROUND(CY100,2) -> 0 | Y100: =ROUND(CZ100,2) -> 0 | AA100: -1 | AB100: =ROUND((AC100+AD100+AF100),6) -> 30.69 | AC100: =ROUND((ES100),6) -> 30.69 | AD100: =ROUND((((ET100)-(EU100))+AE100),6) -> 0 | AE100: =ROUND((EU100),6) -> 0 | AF100: =ROUND((EV100),6) -> 0 | AG100: =ROUND((AP100),6) -> 0 | AH100: =(EW100) -> 0 | AI100: =(EX100) -> 0 | AJ100: =(AS100) -> 0 | AK100: 30.69 | AL100: 30.69 | AM100: 0 | AN100: 0 | AO100: 0 | AP100: 0 | AQ100: 0 | AR100: 0 | AS100: 0 | AT100: 97 | AU100: 51 | AV100: 1 | AW100: 1 | AZ100: 1 | BA100: 1 | BB100: 1 | BC100: 5.76 | BH100: 3 | BI100: 2 | BJ100: ТСН-2001.1 Доп. 67, Р. 14, о. 1, поз. 281 | BM100: 67 | BN100: 0 | BO100: 1.14-1-281 | BP100: 1 | BQ100: 40 | BR100: 0 | BS100: 1 | BT100: 1 | BU100: 1 | BV100: 1 | BW100: 1 | BX100: 1 | BZ100: 97 | CA100: 51 | CE100: 30 | CF100: 0 | CG100: 0 | CM100: 0 | CO100: 0 | CP100: =(P100+Q100+S100) -> 3535.49 | CQ100: =ROUND((ROUND((AC100*AW100*1),2)*BC100),2) -> 176.77 | CR100: =(ROUND((ROUND(((ET100)*AV100*1),2)*BB100),2)+ROUND((ROUND(((AE100-(EU100))*AV100*1),2)*BS100),2)) -> 0 | CS100: =ROUND((ROUND((AE100*AV100*1),2)*BS100),2) -> 0 | CT100: =ROUND((ROUND((AF100*AV100*1),2)*BA100),2) -> 0 | CU100: =AG100 -> 0 | CV100: =(AH100*AV100) -> 0 | CW100: =AI100 -> 0 | CX100: =AJ100 -> 0 | CY100: =(((S100+R100)*AT100)/100) -> 0 | CZ100: =(((S100+R100)*AU100)/100) -> 0 | DN100: 0 | DO100: 0 | DP100: 1 | DQ100: 1 | DU100: 1010 | DV100: шт. | DW100: шт. | DX100: 1 | EE100: 58162629 | EF100: 40 | EG100: Монтаж оборудования | EH100: 0 | EJ100: 2 | EK100: 67 | EL100: ТСН-2001.4-8. Электротехнические установки | EM100: ТСН-2001.4-8-1 | EQ100: 1024 | ER100: 30.69 | ES100: 30.69 | ET100: 0 | EU100: 0 | EV100: 0 | EW100: 0 | EX100: 0 | FQ100: 0 | FR100: 0 | FS100: 0 | FX100: 97 | FY100: 51 | GD100: 1 | GF100: -688640225 | GG100: 2 | GH100: 1 | GI100: 2 | GJ100: 0 | GK100: 0 | GL100: =ROUND(IF(AND(BH100=3,BI100=3,FS100<>0),P100,0),2) -> 0 | GM100: =ROUND(O100+X100+Y100,2)+GX100 -> 3535.49 | GN100: =IF(OR(BI100=0,BI100=1),GM100-GX100,0) -> 0 | GO100: =IF(BI100=2,GM100-GX100,0) -> 3535.49 | GP100: =IF(BI100=4,GM100-GX100,0) -> 0 | GR100: 0 | GS100: 3 | GT100: 0 | GV100: =ROUND((GT100),6) -> 0 | GW100: 1 | GX100: =ROUND(HC100*I100,2) -> 0 | HA100: 0 | HB100: 0 | HC100: =GV100*GW100 -> 0 | HS100: 0 | IK100: 0
A101: 18 | B101: 1 | F101: 1.14-1-280 | G101: Разъем телевизионный F для коаксиального кабеля стандарта RG6 | H101: шт. | I101: =I95*J101 -> 15 | J101: 7.5 | K101: 7.5 | O101: =ROUND(CP101,2) -> 136.8 | P101: =ROUND((ROUND((AC101*AW101*I101),2)*BC101),2) -> 136.8 | Q101: =(ROUND((ROUND(((ET101)*AV101*I101),2)*BB101),2)+ROUND((ROUND(((AE101-(EU101))*AV101*I101),2)*BS101),2)) -> 0 | R101: =ROUND((ROUND((AE101*AV101*I101),2)*BS101),2) -> 0 | S101: =ROUND((ROUND((AF101*AV101*I101),2)*BA101),2) -> 0 | T101: =ROUND(CU101*I101,2) -> 0 | U101: =CV101*I101 -> 0 | V101: =CW101*I101 -> 0 | W101: =ROUND(CX101*I101,2) -> 0 | X101: =ROUND(CY101,2) -> 0 | Y101: =ROUND(CZ101,2) -> 0 | AA101: -1 | AB101: =ROUND((AC101+AD101+AF101),6) -> 9.12 | AC101: =ROUND((ES101),6) -> 9.12 | AD101: =ROUND((((ET101)-(EU101))+AE101),6) -> 0 | AE101: =ROUND((EU101),6) -> 0 | AF101: =ROUND((EV101),6) -> 0 | AG101: =ROUND((AP101),6) -> 0 | AH101: =(EW101) -> 0 | AI101: =(EX101) -> 0 | AJ101: =(AS101) -> 0 | AK101: 9.12 | AL101: 9.12 | AM101: 0 | AN101: 0 | AO101: 0 | AP101: 0 | AQ101: 0 | AR101: 0 | AS101: 0 | AT101: 97 | AU101: 51 | AV101: 1 | AW101: 1 | AZ101: 1 | BA101: 1 | BB101: 1 | BC101: 1 | BH101: 3 | BI101: 2 | BJ101: ТСН-2001.1 Доп. 67, Р. 14, о. 1, поз. 280 | BM101: 67 | BN101: 0 | BP101: 0 | BQ101: 40 | BR101: 0 | BS101: 1 | BT101: 1 | BU101: 1 | BV101: 1 | BW101: 1 | BX101: 1 | BZ101: 97 | CA101: 51 | CE101: 30 | CF101: 0 | CG101: 0 | CM101: 0 | CO101: 0 | CP101: =(P101+Q101+S101) -> 136.8 | CQ101: =ROUND((ROUND((AC101*AW101*1),2)*BC101),2) -> 9.12 | CR101: =(ROUND((ROUND(((ET101)*AV101*1),2)*BB101),2)+ROUND((ROUND(((AE101-(EU101))*AV101*1),2)*BS101),2)) -> 0 | CS101: =ROUND((ROUND((AE101*AV101*1),2)*BS101),2) -> 0 | CT101: =ROUND((ROUND((AF101*AV101*1),2)*BA101),2) -> 0 | CU101: =AG101 -> 0 | CV101: =(AH101*AV101) -> 0 | CW101: =AI101 -> 0 | CX101: =AJ101 -> 0 | CY101: =(((S101+R101)*AT101)/100) -> 0 | CZ101: =(((S101+R101)*AU101)/100) -> 0 | DN101: 0 | DO101: 0 | DP101: 1 | DQ101: 1 | DU101: 1010 | DV101: шт. | DW101: шт. | DX101: 1 | EE101: 58162629 | EF101: 40 | EG101: Монтаж оборудования | EH101: 0 | EJ101: 2 | EK101: 67 | EL101: ТСН-2001.4-8. Электротехнические установки | EM101: ТСН-2001.4-8-1 | EQ101: 1024 | ER101: 9.12 | ES101: 9.12 | ET101: 0 | EU101: 0 | EV101: 0 | EW101: 0 | EX101: 0 | FQ101: 0 | FR101: 0 | FS101: 0 | FX101: 97 | FY101: 51 | GD101: 1 | GF101: -664968350 | GG101: 2 | GH101: 1 | GI101: -2 | GJ101: 0 | GK101: 0 | GL101: =ROUND(IF(AND(BH101=3,BI101=3,FS101<>0),P101,0),2) -> 0 | GM101: =ROUND(O101+X101+Y101,2)+GX101 -> 136.8 | GN101: =IF(OR(BI101=0,BI101=1),GM101-GX101,0) -> 0 | GO101: =IF(BI101=2,GM101-GX101,0) -> 136.8 | GP101: =IF(BI101=4,GM101-GX101,0) -> 0 | GR101: 0 | GS101: 3 | GT101: 0 | GV101: =ROUND((GT101),6) -> 0 | GW101: 1 | GX101: =ROUND(HC101*I101,2) -> 0 | HA101: 0 | HB101: 0 | HC101: =GV101*GW101 -> 0 | HS101: 0 | IK101: 0
A102: 18 | B102: 1 | F102: 1.14-1-280 | G102: Разъем телевизионный F для коаксиального кабеля стандарта RG6 | H102: шт. | I102: =I96*J102 -> 15 | J102: 7.5 | K102: 7.5 | O102: =ROUND(CP102,2) -> 366.62 | P102: =ROUND((ROUND((AC102*AW102*I102),2)*BC102),2) -> 366.62 | Q102: =(ROUND((ROUND(((ET102)*AV102*I102),2)*BB102),2)+ROUND((ROUND(((AE102-(EU102))*AV102*I102),2)*BS102),2)) -> 0 | R102: =ROUND((ROUND((AE102*AV102*I102),2)*BS102),2) -> 0 | S102: =ROUND((ROUND((AF102*AV102*I102),2)*BA102),2) -> 0 | T102: =ROUND(CU102*I102,2) -> 0 | U102: =CV102*I102 -> 0 | V102: =CW102*I102 -> 0 | W102: =ROUND(CX102*I102,2) -> 0 | X102: =ROUND(CY102,2) -> 0 | Y102: =ROUND(CZ102,2) -> 0 | AA102: -1 | AB102: =ROUND((AC102+AD102+AF102),6) -> 9.12 | AC102: =ROUND((ES102),6) -> 9.12 | AD102: =ROUND((((ET102)-(EU102))+AE102),6) -> 0 | AE102: =ROUND((EU102),6) -> 0 | AF102: =ROUND((EV102),6) -> 0 | AG102: =ROUND((AP102),6) -> 0 | AH102: =(EW102) -> 0 | AI102: =(EX102) -> 0 | AJ102: =(AS102) -> 0 | AK102: 9.12 | AL102: 9.12 | AM102: 0 | AN102: 0 | AO102: 0 | AP102: 0 | AQ102: 0 | AR102: 0 | AS102: 0 | AT102: 97 | AU102: 51 | AV102: 1 | AW102: 1 | AZ102: 1 | BA102: 1 | BB102: 1 | BC102: 2.68 | BH102: 3 | BI102: 2 | BJ102: ТСН-2001.1 Доп. 67, Р. 14, о. 1, поз. 280 | BM102: 67 | BN102: 0 | BO102: 1.14-1-280 | BP102: 1 | BQ102: 40 | BR102: 0 | BS102: 1 | BT102: 1 | BU102: 1 | BV102: 1 | BW102: 1 | BX102: 1 | BZ102: 97 | CA102: 51 | CE102: 30 | CF102: 0 | CG102: 0 | CM102: 0 | CO102: 0 | CP102: =(P102+Q102+S102) -> 366.62 | CQ102: =ROUND((ROUND((AC102*AW102*1),2)*BC102),2) -> 24.44 | CR102: =(ROUND((ROUND(((ET102)*AV102*1),2)*BB102),2)+ROUND((ROUND(((AE102-(EU102))*AV102*1),2)*BS102),2)) -> 0 | CS102: =ROUND((ROUND((AE102*AV102*1),2)*BS102),2) -> 0 | CT102: =ROUND((ROUND((AF102*AV102*1),2)*BA102),2) -> 0 | CU102: =AG102 -> 0 | CV102: =(AH102*AV102) -> 0 | CW102: =AI102 -> 0 | CX102: =AJ102 -> 0 | CY102: =(((S102+R102)*AT102)/100) -> 0 | CZ102: =(((S102+R102)*AU102)/100) -> 0 | DN102: 0 | DO102: 0 | DP102: 1 | DQ102: 1 | DU102: 1010 | DV102: шт. | DW102: шт. | DX102: 1 | EE102: 58162629 | EF102: 40 | EG102: Монтаж оборудования | EH102: 0 | EJ102: 2 | EK102: 67 | EL102: ТСН-2001.4-8. Электротехнические установки | EM102: ТСН-2001.4-8-1 | EQ102: 1024 | ER102: 9.12 | ES102: 9.12 | ET102: 0 | EU102: 0 | EV102: 0 | EW102: 0 | EX102: 0 | FQ102: 0 | FR102: 0 | FS102: 0 | FX102: 97 | FY102: 51 | GD102: 1 | GF102: -664968350 | GG102: 2 | GH102: 1 | GI102: 2 | GJ102: 0 | GK102: 0 | GL102: =ROUND(IF(AND(BH102=3,BI102=3,FS102<>0),P102,0),2) -> 0 | GM102: =ROUND(O102+X102+Y102,2)+GX102 -> 366.62 | GN102: =IF(OR(BI102=0,BI102=1),GM102-GX102,0) -> 0 | GO102: =IF(BI102=2,GM102-GX102,0) -> 366.62 | GP102: =IF(BI102=4,GM102-GX102,0) -> 0 | GR102: 0 | GS102: 3 | GT102: 0 | GV102: =ROUND((GT102),6) -> 0 | GW102: 1 | GX102: =ROUND(HC102*I102,2) -> 0 | HA102: 0 | HB102: 0 | HC102: =GV102*GW102 -> 0 | HS102: 0 | IK102: 0
A103: 17 | B103: 1 | D103: =ROW(EtalonRes!A71) -> 71 | F103: 4.8-175-9 | G103: Добавлять на затягивание провода в проложенные трубы и металлические рукава каждого последующего одножильного или многожильного в общей оплетке, суммарное сечение до 6 мм2 (к нормам и расценкам 8-175-1 и 8-175-2) | H103: 100 м | I103: =ROUND((135+250-200)/100,9) -> 1.85 | J103: 0 | K103: =ROUND((135+250-200)/100,9) -> 1.85 | O103: =ROUND(CP103,2) -> 156.16 | P103: =ROUND((ROUND((AC103*AW103*I103),2)*BC103),2) -> 102.62 | Q103: =(ROUND((ROUND((((ET103*1.1))*AV103*I103),2)*BB103),2)+ROUND((ROUND(((AE103-((EU103*1.1)))*AV103*I103),2)*BS103),2)) -> 5.58 | R103: =ROUND((ROUND((AE103*AV103*I103),2)*BS103),2) -> 0.64 | S103: =ROUND((ROUND((AF103*AV103*I103),2)*BA103),2) -> 47.96 | T103: =ROUND(CU103*I103,2) -> 0 | U103: =CV103*I103 -> 3.8990804 | V103: =CW103*I103 -> 0 | W103: =ROUND(CX103*I103,2) -> 0 | X103: =ROUND(CY103,2) -> 47.14 | Y103: =ROUND(CZ103,2) -> 24.79 | AA103: -1 | AB103: =ROUND((AC103+AD103+AF103),6) -> 83.113 | AC103: =ROUND((ES103),6) -> 55.47 | AD103: =ROUND(((((ET103*1.1))-((EU103*1.1)))+AE103),6) -> 2.882 | AE103: =ROUND(((EU103*1.1)),6) -> 0.33 | AF103: =ROUND(((EV103*1.1)),6) -> 24.761 | AG103: =ROUND((AP103),6) -> 0 | AH103: =((EW103*1.1)) -> 2.013 | AI103: =((EX103*1.1)) -> 0 | AJ103: =(AS103) -> 0 | AK103: 80.6 | AL103: 55.47 | AM103: 2.62 | AN103: 0.3 | AO103: 22.51 | AP103: 0 | AQ103: 1.83 | AR103: 0 | AS103: 0 | AT103: 97 | AU103: 51 | AV103: 1.047 | AW103: 1 | AZ103: 1 | BA103: 1 | BB103: 1 | BC103: 1 | BH103: 0 | BI103: 2 | BJ103: ТСН-2001.4 Доп. 80, Сб. 8, т. 175, поз. 9 | BM103: 67 | BN103: 0 | BO103: 4.8-175-9 | BP103: 1 | BQ103: 40 | BR103: 0 | BS103: 1 | BT103: 1 | BU103: 1 | BV103: 1 | BW103: 1 | BX103: 1 | BZ103: 97 | CA103: 51 | CE103: 30 | CF103: 0 | CG103: 0 | CM103: 0 | CO103: 0 | CP103: =(P103+Q103+S103) -> 156.16 | CQ103: =ROUND((ROUND((AC103*AW103*1),2)*BC103),2) -> 55.47 | CR103: =(ROUND((ROUND((((ET103*1.1))*AV103*1),2)*BB103),2)+ROUND((ROUND(((AE103-((EU103*1.1)))*AV103*1),2)*BS103),2)) -> 3.02 | CS103: =ROUND((ROUND((AE103*AV103*1),2)*BS103),2) -> 0.35 | CT103: =ROUND((ROUND((AF103*AV103*1),2)*BA103),2) -> 25.92 | CU103: =AG103 -> 0 | CV103: =(AH103*AV103) -> 2.107611 | CW103: =AI103 -> 0 | CX103: =AJ103 -> 0 | CY103: =(((S103+R103)*AT103)/100) -> 47.142 | CZ103: =(((S103+R103)*AU103)/100) -> 24.786 | DE103: *1,1 | DF103: *1,1 | DG103: *1,1 | DI103: *1,1 | DJ103: *1,1 | DN103: 0 | DO103: 0 | DP103: 1 | DQ103: 1 | DU103: 1003 | DV103: 100 м | DW103: 100 м | DX103: 100 | EE103: 58162629 | EF103: 40 | EG103: Монтаж оборудования | EH103: 0 | EJ103: 2 | EK103: 67 | EL103: ТСН-2001.4-8. Электротехнические установки | EM103: ТСН-2001.4-8-1 | EO103: Поправка: Гл.12.Прил.8.п.8. 5_12.00.01.11.003 | EQ103: 1024 | ER103: 80.6 | ES103: 55.47 | ET103: 2.62 | EU103: 0.3 | EV103: 22.51 | EW103: 1.83 | EX103: 0 | EY103: 0 | FQ103: 0 | FR103: 0 | FS103: 0 | FX103: 97 | FY103: 51 | GD103: 1 | GF103: -938160609 | GG103: 2 | GH103: 1 | GI103: 2 | GJ103: 0 | GK103: 0 | GL103: =ROUND(IF(AND(BH103=3,BI103=3,FS103<>0),P103,0),2) -> 0 | GM103: =ROUND(O103+X103+Y103,2)+GX103 -> 228.09 | GN103: =IF(OR(BI103=0,BI103=1),GM103-GX103,0) -> 0 | GO103: =IF(BI103=2,GM103-GX103,0) -> 228.09 | GP103: =IF(BI103=4,GM103-GX103,0) -> 0 | GR103: 0 | GS103: 3 | GT103: 0 | GV103: =ROUND((GT103),6) -> 0 | GW103: 1 | GX103: =ROUND(HC103*I103,2) -> 0 | HA103: 0 | HB103: 0 | HC103: =GV103*GW103 -> 0 | HS103: 0 | IK103: 0
A104: 17 | B104: 1 | D104: =ROW(EtalonRes!A80) -> 80 | F104: 4.8-175-9 | G104: Добавлять на затягивание провода в проложенные трубы и металлические рукава каждого последующего одножильного или многожильного в общей оплетке, суммарное сечение до 6 мм2 (к нормам и расценкам 8-175-1 и 8-175-2) | H104: 100 м | I104: =ROUND((135+250-200)/100,9) -> 1.85 | J104: 0 | K104: =ROUND((135+250-200)/100,9) -> 1.85 | O104: =ROUND(CP104,2) -> 3035.72 | P104: =ROUND((ROUND((AC104*AW104*I104),2)*BC104),2) -> 317.1 | Q104: =(ROUND((ROUND((((ET104*1.1))*AV104*I104),2)*BB104),2)+ROUND((ROUND(((AE104-((EU104*1.1)))*AV104*I104),2)*BS104),2)) -> 81.3 | R104: =ROUND((ROUND((AE104*AV104*I104),2)*BS104),2) -> 35.19 | S104: =ROUND((ROUND((AF104*AV104*I104),2)*BA104),2) -> 2637.32 | T104: =ROUND(CU104*I104,2) -> 0 | U104: =CV104*I104 -> 3.8990804 | V104: =CW104*I104 -> 0 | W104: =ROUND(CX104*I104,2) -> 0 | X104: =ROUND(CY104,2) -> 2592.33 | Y104: =ROUND(CZ104,2) -> 1362.98 | AA104: -1 | AB104: =ROUND((AC104+AD104+AF104),6) -> 83.113 | AC104: =ROUND((ES104),6) -> 55.47 | AD104: =ROUND(((((ET104*1.1))-((EU104*1.1)))+AE104),6) -> 2.882 | AE104: =ROUND(((EU104*1.1)),6) -> 0.33 | AF104: =ROUND(((EV104*1.1)),6) -> 24.761 | AG104: =ROUND((AP104),6) -> 0 | AH104: =((EW104*1.1)) -> 2.013 | AI104: =((EX104*1.1)) -> 0 | AJ104: =(AS104) -> 0 | AK104: 80.6 | AL104: 55.47 | AM104: 2.62 | AN104: 0.3 | AO104: 22.51 | AP104: 0 | AQ104: 1.83 | AR104: 0 | AS104: 0 | AT104: 97 | AU104: 51 | AV104: 1.047 | AW104: 1 | AZ104: 1 | BA104: 54.99 | BB104: 14.57 | BC104: 3.09 | BH104: 0 | BI104: 2 | BJ104: ТСН-2001.4 Доп. 80, Сб. 8, т. 175, поз. 9 | BM104: 67 | BN104: 0 | BO104: 4.8-175-9 | BP104: 1 | BQ104: 40 | BR104: 0 | BS104: 54.99 | BT104: 1 | BU104: 1 | BV104: 1 | BW104: 1 | BX104: 1 | BZ104: 97 | CA104: 51 | CE104: 30 | CF104: 0 | CG104: 0 | CM104: 0 | CO104: 0 | CP104: =(P104+Q104+S104) -> 3035.72 | CQ104: =ROUND((ROUND((AC104*AW104*1),2)*BC104),2) -> 171.4 | CR104: =(ROUND((ROUND((((ET104*1.1))*AV104*1),2)*BB104),2)+ROUND((ROUND(((AE104-((EU104*1.1)))*AV104*1),2)*BS104),2)) -> 44 | CS104: =ROUND((ROUND((AE104*AV104*1),2)*BS104),2) -> 19.25 | CT104: =ROUND((ROUND((AF104*AV104*1),2)*BA104),2) -> 1425.34 | CU104: =AG104 -> 0 | CV104: =(AH104*AV104) -> 2.107611 | CW104: =AI104 -> 0 | CX104: =AJ104 -> 0 | CY104: =(((S104+R104)*AT104)/100) -> 2592.3347 | CZ104: =(((S104+R104)*AU104)/100) -> 1362.9801 | DE104: *1,1 | DF104: *1,1 | DG104: *1,1 | DI104: *1,1 | DJ104: *1,1 | DN104: 0 | DO104: 0 | DP104: 1 | DQ104: 1 | DU104: 1003 | DV104: 100 м | DW104: 100 м | DX104: 100 | EE104: 58162629 | EF104: 40 | EG104: Монтаж оборудования | EH104: 0 | EJ104: 2 | EK104: 67 | EL104: ТСН-2001.4-8. Электротехнические установки | EM104: ТСН-2001.4-8-1 | EO104: Поправка: Гл.12.Прил.8.п.8. 5_12.00.01.11.003 | EQ104: 1024 | ER104: 80.6 | ES104: 55.47 | ET104: 2.62 | EU104: 0.3 | EV104: 22.51 | EW104: 1.83 | EX104: 0 | EY104: 0 | FQ104: 0 | FR104: 0 | FS104: 0 | FX104: 97 | FY104: 51 | GD104: 1 | GF104: -938160609 | GG104: 2 | GH104: 1 | GI104: 2 | GJ104: 0 | GK104: 0 | GL104: =ROUND(IF(AND(BH104=3,BI104=3,FS104<>0),P104,0),2) -> 0 | GM104: =ROUND(O104+X104+Y104,2)+GX104 -> 6991.03 | GN104: =IF(OR(BI104=0,BI104=1),GM104-GX104,0) -> 0 | GO104: =IF(BI104=2,GM104-GX104,0) -> 6991.03 | GP104: =IF(BI104=4,GM104-GX104,0) -> 0 | GR104: 0 | GS104: 3 | GT104: 0 | GV104: =ROUND((GT104),6) -> 0 | GW104: 1 | GX104: =ROUND(HC104*I104,2) -> 0 | HA104: 0 | HB104: 0 | HC104: =GV104*GW104 -> 0 | HS104: 0 | IK104: 0
A105: 18 | B105: 1 | F105: КА 2 | G105: Кабель коаксиальный РК 75-4,8-319нг(А)-LSLTx | H105: км | I105: =I103*J105 -> 0.051 | J105: 0.027567568 | K105: 0.0275676 | O105: =ROUND(CP105,2) -> 704.48 | P105: =ROUND((ROUND((AC105*AW105*I105),2)*BC105),2) -> 704.48 | Q105: =(ROUND((ROUND(((ET105)*AV105*I105),2)*BB105),2)+ROUND((ROUND(((AE105-(EU105))*AV105*I105),2)*BS105),2)) -> 0 | R105: =ROUND((ROUND((AE105*AV105*I105),2)*BS105),2) -> 0 | S105: =ROUND((ROUND((AF105*AV105*I105),2)*BA105),2) -> 0 | T105: =ROUND(CU105*I105,2) -> 0 | U105: =CV105*I105 -> 0 | V105: =CW105*I105 -> 0 | W105: =ROUND(CX105*I105,2) -> 0 | X105: =ROUND(CY105,2) -> 0 | Y105: =ROUND(CZ105,2) -> 0 | AA105: -1 | AB105: =ROUND((AC105+AD105+AF105),6) -> 13813.36 | AC105: =ROUND((ES105),6) -> 13813.36 | AD105: =ROUND((((ET105)-(EU105))+AE105),6) -> 0 | AE105: =ROUND((EU105),6) -> 0 | AF105: =ROUND((EV105),6) -> 0 | AG105: =ROUND((AP105),6) -> 0 | AH105: =(EW105) -> 0 | AI105: =(EX105) -> 0 | AJ105: =(AS105) -> 0 | AK105: 13813.36 | AL105: 13813.36 | AM105: 0 | AN105: 0 | AO105: 0 | AP105: 0 | AQ105: 0 | AR105: 0 | AS105: 0 | AT105: 97 | AU105: 51 | AV105: 1 | AW105: 1 | AZ105: 1 | BA105: 1 | BB105: 1 | BC105: 1 | BH105: 3 | BI105: 2 | BM105: 67 | BN105: 0 | BP105: 0 | BQ105: 40 | BR105: 0 | BS105: 1 | BT105: 1 | BU105: 1 | BV105: 1 | BW105: 1 | BX105: 1 | BZ105: 97 | CA105: 51 | CE105: 30 | CF105: 0 | CG105: 0 | CM105: 0 | CO105: 0 | CP105: =(P105+Q105+S105) -> 704.48 | CQ105: =ROUND((ROUND((AC105*AW105*1),2)*BC105),2) -> 13813.36 | CR105: =(ROUND((ROUND(((ET105)*AV105*1),2)*BB105),2)+ROUND((ROUND(((AE105-(EU105))*AV105*1),2)*BS105),2)) -> 0 | CS105: =ROUND((ROUND((AE105*AV105*1),2)*BS105),2) -> 0 | CT105: =ROUND((ROUND((AF105*AV105*1),2)*BA105),2) -> 0 | CU105: =AG105 -> 0 | CV105: =(AH105*AV105) -> 0 | CW105: =AI105 -> 0 | CX105: =AJ105 -> 0 | CY105: =(((S105+R105)*AT105)/100) -> 0 | CZ105: =(((S105+R105)*AU105)/100) -> 0 | DN105: 0 | DO105: 0 | DP105: 1 | DQ105: 1 | DU105: 1003 | DV105: км | DW105: км | DX105: 1000 | EE105: 58162629 | EF105: 40 | EG105: Монтаж оборудования | EH105: 0 | EJ105: 2 | EK105: 67 | EL105: ТСН-2001.4-8. Электротехнические установки | EM105: ТСН-2001.4-8-1 | EQ105: 1024 | ER105: 0 | ES105: 13813.36 | ET105: 0 | EU105: 0 | EV105: 0 | EW105: 0 | EX105: 0 | FQ105: 0 | FR105: 0 | FS105: 0 | FX105: 97 | FY105: 51 | GA105: [160 560 / 1,2 / 9,88] + 2% Заг.скл | GD105: 1 | GF105: -1070144849 | GG105: 2 | GH105: 4 | GI105: -2 | GJ105: 0 | GK105: 0 | GL105: =ROUND(IF(AND(BH105=3,BI105=3,FS105<>0),P105,0),2) -> 0 | GM105: =ROUND(O105+X105+Y105,2)+GX105 -> 704.48 | GN105: =IF(OR(BI105=0,BI105=1),GM105-GX105,0) -> 0 | GO105: =IF(BI105=2,GM105-GX105,0) -> 704.48 | GP105: =IF(BI105=4,GM105-GX105,0) -> 0 | GR105: 0 | GS105: 2 | GT105: 0 | GV105: =ROUND((GT105),6) -> 0 | GW105: 1 | GX105: =ROUND(HC105*I105,2) -> 0 | HA105: 0 | HB105: 0 | HC105: =GV105*GW105 -> 0 | HE105: 0 | HF105: 2 | HS105: 0 | IK105: 0
A106: 18 | B106: 1 | F106: КА 2 | G106: Кабель коаксиальный РК 75-4,8-319нг(А)-LSLTx | H106: км | I106: =I104*J106 -> 0.051 | J106: 0.027567568 | K106: 0.0275676 | O106: =ROUND(CP106,2) -> 6960.26 | P106: =ROUND((ROUND((AC106*AW106*I106),2)*BC106),2) -> 6960.26 | Q106: =(ROUND((ROUND(((ET106)*AV106*I106),2)*BB106),2)+ROUND((ROUND(((AE106-(EU106))*AV106*I106),2)*BS106),2)) -> 0 | R106: =ROUND((ROUND((AE106*AV106*I106),2)*BS106),2) -> 0 | S106: =ROUND((ROUND((AF106*AV106*I106),2)*BA106),2) -> 0 | T106: =ROUND(CU106*I106,2) -> 0 | U106: =CV106*I106 -> 0 | V106: =CW106*I106 -> 0 | W106: =ROUND(CX106*I106,2) -> 0 | X106: =ROUND(CY106,2) -> 0 | Y106: =ROUND(CZ106,2) -> 0 | AA106: -1 | AB106: =ROUND((AC106+AD106+AF106),6) -> 13813.36 | AC106: =ROUND((ES106),6) -> 13813.36 | AD106: =ROUND((((ET106)-(EU106))+AE106),6) -> 0 | AE106: =ROUND((EU106),6) -> 0 | AF106: =ROUND((EV106),6) -> 0 | AG106: =ROUND((AP106),6) -> 0 | AH106: =(EW106) -> 0 | AI106: =(EX106) -> 0 | AJ106: =(AS106) -> 0 | AK106: 13813.36 | AL106: 13813.36 | AM106: 0 | AN106: 0 | AO106: 0 | AP106: 0 | AQ106: 0 | AR106: 0 | AS106: 0 | AT106: 97 | AU106: 51 | AV106: 1 | AW106: 1 | AZ106: 1 | BA106: 1 | BB106: 1 | BC106: 9.88 | BH106: 3 | BI106: 2 | BM106: 67 | BN106: 0 | BP106: 0 | BQ106: 40 | BR106: 0 | BS106: 1 | BT106: 1 | BU106: 1 | BV106: 1 | BW106: 1 | BX106: 1 | BZ106: 97 | CA106: 51 | CE106: 30 | CF106: 0 | CG106: 0 | CM106: 0 | CO106: 0 | CP106: =(P106+Q106+S106) -> 6960.26 | CQ106: =ROUND((ROUND((AC106*AW106*1),2)*BC106),2) -> 136476 | CR106: =(ROUND((ROUND(((ET106)*AV106*1),2)*BB106),2)+ROUND((ROUND(((AE106-(EU106))*AV106*1),2)*BS106),2)) -> 0 | CS106: =ROUND((ROUND((AE106*AV106*1),2)*BS106),2) -> 0 | CT106: =ROUND((ROUND((AF106*AV106*1),2)*BA106),2) -> 0 | CU106: =AG106 -> 0 | CV106: =(AH106*AV106) -> 0 | CW106: =AI106 -> 0 | CX106: =AJ106 -> 0 | CY106: =(((S106+R106)*AT106)/100) -> 0 | CZ106: =(((S106+R106)*AU106)/100) -> 0 | DN106: 0 | DO106: 0 | DP106: 1 | DQ106: 1 | DU106: 1003 | DV106: км | DW106: км | DX106: 1000 | EE106: 58162629 | EF106: 40 | EG106: Монтаж оборудования | EH106: 0 | EJ106: 2 | EK106: 67 | EL106: ТСН-2001.4-8. Электротехнические установки | EM106: ТСН-2001.4-8-1 | EQ106: 1024 | ER106: 13813.36 | ES106: 13813.36 | ET106: 0 | EU106: 0 | EV106: 0 | EW106: 0 | EX106: 0 | EZ106: 5 | FC106: 1 | FD106: 18 | FF106: 160560 | FQ106: 0 | FR106: 0 | FS106: 0 | FX106: 97 | FY106: 51 | GA106: [160 560 / 1,2 / 9,88] + 2% Заг.скл | GD106: 1 | GF106: -1070144849 | GG106: 2 | GH106: 3 | GI106: 5 | GJ106: 0 | GK106: 0 | GL106: =ROUND(IF(AND(BH106=3,BI106=3,FS106<>0),P106,0),2) -> 0 | GM106: =ROUND(O106+X106+Y106,2)+GX106 -> 6960.26 | GN106: =IF(OR(BI106=0,BI106=1),GM106-GX106,0) -> 0 | GO106: =IF(BI106=2,GM106-GX106,0) -> 6960.26 | GP106: =IF(BI106=4,GM106-GX106,0) -> 0 | GR106: 1 | GS106: 1 | GT106: 0 | GV106: =ROUND((GT106),6) -> 0 | GW106: 1 | GX106: =ROUND(HC106*I106,2) -> 0 | HA106: 0 | HB106: 0 | HC106: =GV106*GW106 -> 0 | HE106: 0 | HF106: 2 | HS106: 0 | IK106: 0
A107: 18 | B107: 1 | F107: КА 3 | G107: Кабель коаксиальный РК 75-7-327нг(А)-LSLTx | H107: км | I107: =I103*J107 -> 0.1377 | J107: 0.074432432 | K107: 0.0744324 | O107: =ROUND(CP107,2) -> 3068.05 | P107: =ROUND((ROUND((AC107*AW107*I107),2)*BC107),2) -> 3068.05 | Q107: =(ROUND((ROUND(((ET107)*AV107*I107),2)*BB107),2)+ROUND((ROUND(((AE107-(EU107))*AV107*I107),2)*BS107),2)) -> 0 | R107: =ROUND((ROUND((AE107*AV107*I107),2)*BS107),2) -> 0 | S107: =ROUND((ROUND((AF107*AV107*I107),2)*BA107),2) -> 0 | T107: =ROUND(CU107*I107,2) -> 0 | U107: =CV107*I107 -> 0 | V107: =CW107*I107 -> 0 | W107: =ROUND(CX107*I107,2) -> 0 | X107: =ROUND(CY107,2) -> 0 | Y107: =ROUND(CZ107,2) -> 0 | AA107: -1 | AB107: =ROUND((AC107+AD107+AF107),6) -> 22280.67 | AC107: =ROUND((ES107),6) -> 22280.67 | AD107: =ROUND((((ET107)-(EU107))+AE107),6) -> 0 | AE107: =ROUND((EU107),6) -> 0 | AF107: =ROUND((EV107),6) -> 0 | AG107: =ROUND((AP107),6) -> 0 | AH107: =(EW107) -> 0 | AI107: =(EX107) -> 0 | AJ107: =(AS107) -> 0 | AK107: 22280.67 | AL107: 22280.67 | AM107: 0 | AN107: 0 | AO107: 0 | AP107: 0 | AQ107: 0 | AR107: 0 | AS107: 0 | AT107: 97 | AU107: 51 | AV107: 1 | AW107: 1 | AZ107: 1 | BA107: 1 | BB107: 1 | BC107: 1 | BH107: 3 | BI107: 2 | BM107: 67 | BN107: 0 | BP107: 0 | BQ107: 40 | BR107: 0 | BS107: 1 | BT107: 1 | BU107: 1 | BV107: 1 | BW107: 1 | BX107: 1 | BZ107: 97 | CA107: 51 | CE107: 30 | CF107: 0 | CG107: 0 | CM107: 0 | CO107: 0 | CP107: =(P107+Q107+S107) -> 3068.05 | CQ107: =ROUND((ROUND((AC107*AW107*1),2)*BC107),2) -> 22280.67 | CR107: =(ROUND((ROUND(((ET107)*AV107*1),2)*BB107),2)+ROUND((ROUND(((AE107-(EU107))*AV107*1),2)*BS107),2)) -> 0 | CS107: =ROUND((ROUND((AE107*AV107*1),2)*BS107),2) -> 0 | CT107: =ROUND((ROUND((AF107*AV107*1),2)*BA107),2) -> 0 | CU107: =AG107 -> 0 | CV107: =(AH107*AV107) -> 0 | CW107: =AI107 -> 0 | CX107: =AJ107 -> 0 | CY107: =(((S107+R107)*AT107)/100) -> 0 | CZ107: =(((S107+R107)*AU107)/100) -> 0 | DN107: 0 | DO107: 0 | DP107: 1 | DQ107: 1 | DU107: 1003 | DV107: км | DW107: км | DX107: 1000 | EE107: 58162629 | EF107: 40 | EG107: Монтаж оборудования | EH107: 0 | EJ107: 2 | EK107: 67 | EL107: ТСН-2001.4-8. Электротехнические установки | EM107: ТСН-2001.4-8-1 | EQ107: 1024 | ER107: 0 | ES107: 22280.67 | ET107: 0 | EU107: 0 | EV107: 0 | EW107: 0 | EX107: 0 | FQ107: 0 | FR107: 0 | FS107: 0 | FX107: 97 | FY107: 51 | GA107: [258 980 / 1,2 / 9,88] + 2% Заг.скл | GD107: 1 | GF107: 585815009 | GG107: 2 | GH107: 4 | GI107: -2 | GJ107: 0 | GK107: 0 | GL107: =ROUND(IF(AND(BH107=3,BI107=3,FS107<>0),P107,0),2) -> 0 | GM107: =ROUND(O107+X107+Y107,2)+GX107 -> 3068.05 | GN107: =IF(OR(BI107=0,BI107=1),GM107-GX107,0) -> 0 | GO107: =IF(BI107=2,GM107-GX107,0) -> 3068.05 | GP107: =IF(BI107=4,GM107-GX107,0) -> 0 | GR107: 0 | GS107: 2 | GT107: 0 | GV107: =ROUND((GT107),6) -> 0 | GW107: 1 | GX107: =ROUND(HC107*I107,2) -> 0 | HA107: 0 | HB107: 0 | HC107: =GV107*GW107 -> 0 | HE107: 0 | HF107: 2 | HS107: 0 | IK107: 0
A108: 18 | B108: 1 | F108: КА 3 | G108: Кабель коаксиальный РК 75-7-327нг(А)-LSLTx | H108: км | I108: =I104*J108 -> 0.1377 | J108: 0.074432432 | K108: 0.0744324 | O108: =ROUND(CP108,2) -> 30312.33 | P108: =ROUND((ROUND((AC108*AW108*I108),2)*BC108),2) -> 30312.33 | Q108: =(ROUND((ROUND(((ET108)*AV108*I108),2)*BB108),2)+ROUND((ROUND(((AE108-(EU108))*AV108*I108),2)*BS108),2)) -> 0 | R108: =ROUND((ROUND((AE108*AV108*I108),2)*BS108),2) -> 0 | S108: =ROUND((ROUND((AF108*AV108*I108),2)*BA108),2) -> 0 | T108: =ROUND(CU108*I108,2) -> 0 | U108: =CV108*I108 -> 0 | V108: =CW108*I108 -> 0 | W108: =ROUND(CX108*I108,2) -> 0 | X108: =ROUND(CY108,2) -> 0 | Y108: =ROUND(CZ108,2) -> 0 | AA108: -1 | AB108: =ROUND((AC108+AD108+AF108),6) -> 22280.67 | AC108: =ROUND((ES108),6) -> 22280.67 | AD108: =ROUND((((ET108)-(EU108))+AE108),6) -> 0 | AE108: =ROUND((EU108),6) -> 0 | AF108: =ROUND((EV108),6) -> 0 | AG108: =ROUND((AP108),6) -> 0 | AH108: =(EW108) -> 0 | AI108: =(EX108) -> 0 | AJ108: =(AS108) -> 0 | AK108: 22280.67 | AL108: 22280.67 | AM108: 0 | AN108: 0 | AO108: 0 | AP108: 0 | AQ108: 0 | AR108: 0 | AS108: 0 | AT108: 97 | AU108: 51 | AV108: 1 | AW108: 1 | AZ108: 1 | BA108: 1 | BB108: 1 | BC108: 9.88 | BH108: 3 | BI108: 2 | BM108: 67 | BN108: 0 | BP108: 0 | BQ108: 40 | BR108: 0 | BS108: 1 | BT108: 1 | BU108: 1 | BV108: 1 | BW108: 1 | BX108: 1 | BZ108: 97 | CA108: 51 | CE108: 30 | CF108: 0 | CG108: 0 | CM108: 0 | CO108: 0 | CP108: =(P108+Q108+S108) -> 30312.33 | CQ108: =ROUND((ROUND((AC108*AW108*1),2)*BC108),2) -> 220133.02 | CR108: =(ROUND((ROUND(((ET108)*AV108*1),2)*BB108),2)+ROUND((ROUND(((AE108-(EU108))*AV108*1),2)*BS108),2)) -> 0 | CS108: =ROUND((ROUND((AE108*AV108*1),2)*BS108),2) -> 0 | CT108: =ROUND((ROUND((AF108*AV108*1),2)*BA108),2) -> 0 | CU108: =AG108 -> 0 | CV108: =(AH108*AV108) -> 0 | CW108: =AI108 -> 0 | CX108: =AJ108 -> 0 | CY108: =(((S108+R108)*AT108)/100) -> 0 | CZ108: =(((S108+R108)*AU108)/100) -> 0 | DN108: 0 | DO108: 0 | DP108: 1 | DQ108: 1 | DU108: 1003 | DV108: км | DW108: км | DX108: 1000 | EE108: 58162629 | EF108: 40 | EG108: Монтаж оборудования | EH108: 0 | EJ108: 2 | EK108: 67 | EL108: ТСН-2001.4-8. Электротехнические установки | EM108: ТСН-2001.4-8-1 | EQ108: 1024 | ER108: 22280.67 | ES108: 22280.67 | ET108: 0 | EU108: 0 | EV108: 0 | EW108: 0 | EX108: 0 | EZ108: 5 | FC108: 1 | FD108: 18 | FF108: 258980 | FQ108: 0 | FR108: 0 | FS108: 0 | FX108: 97 | FY108: 51 | GA108: [258 980 / 1,2 / 9,88] + 2% Заг.скл | GD108: 1 | GF108: 585815009 | GG108: 2 | GH108: 3 | GI108: 5 | GJ108: 0 | GK108: 0 | GL108: =ROUND(IF(AND(BH108=3,BI108=3,FS108<>0),P108,0),2) -> 0 | GM108: =ROUND(O108+X108+Y108,2)+GX108 -> 30312.33 | GN108: =IF(OR(BI108=0,BI108=1),GM108-GX108,0) -> 0 | GO108: =IF(BI108=2,GM108-GX108,0) -> 30312.33 | GP108: =IF(BI108=4,GM108-GX108,0) -> 0 | GR108: 1 | GS108: 1 | GT108: 0 | GV108: =ROUND((GT108),6) -> 0 | GW108: 1 | GX108: =ROUND(HC108*I108,2) -> 0 | HA108: 0 | HB108: 0 | HC108: =GV108*GW108 -> 0 | HE108: 0 | HF108: 2 | HS108: 0 | IK108: 0
A109: 17 | B109: 1 | D109: =ROW(EtalonRes!A81) -> 81 | E109: 5 | F109: 4.10-134-4 | G109: Антенные устройства, монтаж антенны коллективной для приема ТВ на антенной опоре высотой до 6 м без оттяжек на кровле с ранее оборудованными трубостойками | H109: 1 антенна | I109: =ROUND(ROUND(1,4),9) -> 1 | J109: 0 | K109: =ROUND(ROUND(1,4),9) -> 1 | O109: =ROUND(CP109,2) -> 91.42 | P109: =ROUND((ROUND((AC109*AW109*I109),2)*BC109),2) -> 0.37 | Q109: =(ROUND((ROUND((((ET109*1.1))*AV109*I109),2)*BB109),2)+ROUND((ROUND(((AE109-((EU109*1.1)))*AV109*I109),2)*BS109),2)) -> 0 | R109: =ROUND((ROUND((AE109*AV109*I109),2)*BS109),2) -> 0 | S109: =ROUND((ROUND((AF109*AV109*I109),2)*BA109),2) -> 91.05 | T109: =ROUND(CU109*I109,2) -> 0 | U109: =CV109*I109 -> 6.420909 | V109: =CW109*I109 -> 0 | W109: =ROUND(CX109*I109,2) -> 0 | X109: =ROUND(CY109,2) -> 86.5 | Y109: =ROUND(CZ109,2) -> 48.26 | AA109: 56503348 | AB109: =ROUND((AC109+AD109+AF109),6) -> 84.135 | AC109: =ROUND((ES109),6) -> 0.37 | AD109: =ROUND(((((ET109*1.1))-((EU109*1.1)))+AE109),6) -> 0 | AE109: =ROUND(((EU109*1.1)),6) -> 0 | AF109: =ROUND(((EV109*1.1)),6) -> 83.765 | AG109: =ROUND((AP109),6) -> 0 | AH109: =((EW109*1.1)) -> 5.907 | AI109: =((EX109*1.1)) -> 0 | AJ109: =(AS109) -> 0 | AK109: 76.52 | AL109: 0.37 | AM109: 0 | AN109: 0 | AO109: 76.15 | AP109: 0 | AQ109: 5.37 | AR109: 0 | AS109: 0 | AT109: 95 | AU109: 53 | AV109: 1.087 | AW109: 1 | AZ109: 1 | BA109: 1 | BB109: 1 | BC109: 1 | BH109: 0 | BI109: 2 | BJ109: ТСН-2001.4. Доп. 1-42. Сб. 10, т. 134, поз. 4 | BM109: 69 | BN109: 0 | BO109: 4.10-134-4 | BP109: 1 | BQ109: 40 | BR109: 0 | BS109: 1 | BT109: 1 | BU109: 1 | BV109: 1 | BW109: 1 | BX109: 1 | BZ109: 95 | CA109: 53 | CE109: 30 | CF109: 0 | CG109: 0 | CM109: 0 | CO109: 0 | CP109: =(P109+Q109+S109) -> 91.42 | CQ109: =ROUND((ROUND((AC109*AW109*1),2)*BC109),2) -> 0.37 | CR109: =(ROUND((ROUND((((ET109*1.1))*AV109*1),2)*BB109),2)+ROUND((ROUND(((AE109-((EU109*1.1)))*AV109*1),2)*BS109),2)) -> 0 | CS109: =ROUND((ROUND((AE109*AV109*1),2)*BS109),2) -> 0 | CT109: =ROUND((ROUND((AF109*AV109*1),2)*BA109),2) -> 91.05 | CU109: =AG109 -> 0 | CV109: =(AH109*AV109) -> 6.420909 | CW109: =AI109 -> 0 | CX109: =AJ109 -> 0 | CY109: =(((S109+R109)*AT109)/100) -> 86.4975 | CZ109: =(((S109+R109)*AU109)/100) -> 48.2565 | DE109: *1,1 | DF109: *1,1 | DG109: *1,1 | DI109: *1,1 | DJ109: *1,1 | DN109: 0 | DO109: 0 | DP109: 1 | DQ109: 1 | DU109: 1013 | DV109: 1 антенна | DW109: 1 антенна | DX109: 1 | EE109: 58162631 | EF109: 40 | EG109: Монтаж оборудования | EH109: 0 | EJ109: 2 | EK109: 69 | EL109: ТСН-2001.4-10. Монтаж радиотелевизионного и электронного оборудования | EM109: ТСН-2001.4-10-2 | EO109: Поправка: Гл.12.Прил.8.п.8. 5_12.00.01.11.003 | EQ109: 0 | ER109: 76.52 | ES109: 0.37 | ET109: 0 | EU109: 0 | EV109: 76.15 | EW109: 5.37 | EX109: 0 | EY109: 0 | FQ109: 0 | FR109: 0 | FS109: 0 | FX109: 95 | FY109: 53 | GD109: 1 | GF109: 951999700 | GG109: 2 | GH109: 1 | GI109: 2 | GJ109: 0 | GK109: 0 | GL109: =ROUND(IF(AND(BH109=3,BI109=3,FS109<>0),P109,0),2) -> 0 | GM109: =ROUND(O109+X109+Y109,2)+GX109 -> 226.18 | GN109: =IF(OR(BI109=0,BI109=1),GM109-GX109,0) -> 0 | GO109: =IF(BI109=2,GM109-GX109,0) -> 226.18 | GP109: =IF(BI109=4,GM109-GX109,0) -> 0 | GR109: 0 | GS109: 3 | GT109: 0 | GV109: =ROUND((GT109),6) -> 0 | GW109: 1 | GX109: =ROUND(HC109*I109,2) -> 0 | HA109: 0 | HB109: 0 | HC109: =GV109*GW109 -> 0 | HS109: 0 | IK109: 0
A110: 17 | B110: 1 | D110: =ROW(EtalonRes!A82) -> 82 | E110: 5 | F110: 4.10-134-4 | G110: Антенные устройства, монтаж антенны коллективной для приема ТВ на антенной опоре высотой до 6 м без оттяжек на кровле с ранее оборудованными трубостойками | H110: 1 антенна | I110: =ROUND(ROUND(1,4),9) -> 1 | J110: 0 | K110: =ROUND(ROUND(1,4),9) -> 1 | O110: =ROUND(CP110,2) -> 5010.5 | P110: =ROUND((ROUND((AC110*AW110*I110),2)*BC110),2) -> 3.66 | Q110: =(ROUND((ROUND((((ET110*1.1))*AV110*I110),2)*BB110),2)+ROUND((ROUND(((AE110-((EU110*1.1)))*AV110*I110),2)*BS110),2)) -> 0 | R110: =ROUND((ROUND((AE110*AV110*I110),2)*BS110),2) -> 0 | S110: =ROUND((ROUND((AF110*AV110*I110),2)*BA110),2) -> 5006.84 | T110: =ROUND(CU110*I110,2) -> 0 | U110: =CV110*I110 -> 6.420909 | V110: =CW110*I110 -> 0 | W110: =ROUND(CX110*I110,2) -> 0 | X110: =ROUND(CY110,2) -> 4756.5 | Y110: =ROUND(CZ110,2) -> 2653.63 | AA110: 56503350 | AB110: =ROUND((AC110+AD110+AF110),6) -> 84.135 | AC110: =ROUND((ES110),6) -> 0.37 | AD110: =ROUND(((((ET110*1.1))-((EU110*1.1)))+AE110),6) -> 0 | AE110: =ROUND(((EU110*1.1)),6) -> 0 | AF110: =ROUND(((EV110*1.1)),6) -> 83.765 | AG110: =ROUND((AP110),6) -> 0 | AH110: =((EW110*1.1)) -> 5.907 | AI110: =((EX110*1.1)) -> 0 | AJ110: =(AS110) -> 0 | AK110: 76.52 | AL110: 0.37 | AM110: 0 | AN110: 0 | AO110: 76.15 | AP110: 0 | AQ110: 5.37 | AR110: 0 | AS110: 0 | AT110: 95 | AU110: 53 | AV110: 1.087 | AW110: 1 | AZ110: 1 | BA110: 54.99 | BB110: 1 | BC110: 9.89 | BH110: 0 | BI110: 2 | BJ110: ТСН-2001.4. Доп. 1-42. Сб. 10, т. 134, поз. 4 | BM110: 69 | BN110: 0 | BO110: 4.10-134-4 | BP110: 1 | BQ110: 40 | BR110: 0 | BS110: 54.99 | BT110: 1 | BU110: 1 | BV110: 1 | BW110: 1 | BX110: 1 | BZ110: 95 | CA110: 53 | CE110: 30 | CF110: 0 | CG110: 0 | CM110: 0 | CO110: 0 | CP110: =(P110+Q110+S110) -> 5010.5 | CQ110: =ROUND((ROUND((AC110*AW110*1),2)*BC110),2) -> 3.66 | CR110: =(ROUND((ROUND((((ET110*1.1))*AV110*1),2)*BB110),2)+ROUND((ROUND(((AE110-((EU110*1.1)))*AV110*1),2)*BS110),2)) -> 0 | CS110: =ROUND((ROUND((AE110*AV110*1),2)*BS110),2) -> 0 | CT110: =ROUND((ROUND((AF110*AV110*1),2)*BA110),2) -> 5006.84 | CU110: =AG110 -> 0 | CV110: =(AH110*AV110) -> 6.420909 | CW110: =AI110 -> 0 | CX110: =AJ110 -> 0 | CY110: =(((S110+R110)*AT110)/100) -> 4756.498 | CZ110: =(((S110+R110)*AU110)/100) -> 2653.6252 | DE110: *1,1 | DF110: *1,1 | DG110: *1,1 | DI110: *1,1 | DJ110: *1,1 | DN110: 0 | DO110: 0 | DP110: 1 | DQ110: 1 | DU110: 1013 | DV110: 1 антенна | DW110: 1 антенна | DX110: 1 | EE110: 58162631 | EF110: 40 | EG110: Монтаж оборудования | EH110: 0 | EJ110: 2 | EK110: 69 | EL110: ТСН-2001.4-10. Монтаж радиотелевизионного и электронного оборудования | EM110: ТСН-2001.4-10-2 | EO110: Поправка: Гл.12.Прил.8.п.8. 5_12.00.01.11.003 | EQ110: 0 | ER110: 76.52 | ES110: 0.37 | ET110: 0 | EU110: 0 | EV110: 76.15 | EW110: 5.37 | EX110: 0 | EY110: 0 | FQ110: 0 | FR110: 0 | FS110: 0 | FX110: 95 | FY110: 53 | GD110: 1 | GF110: 951999700 | GG110: 2 | GH110: 1 | GI110: 2 | GJ110: 0 | GK110: 0 | GL110: =ROUND(IF(AND(BH110=3,BI110=3,FS110<>0),P110,0),2) -> 0 | GM110: =ROUND(O110+X110+Y110,2)+GX110 -> 12420.63 | GN110: =IF(OR(BI110=0,BI110=1),GM110-GX110,0) -> 0 | GO110: =IF(BI110=2,GM110-GX110,0) -> 12420.63 | GP110: =IF(BI110=4,GM110-GX110,0) -> 0 | GR110: 0 | GS110: 3 | GT110: 0 | GV110: =ROUND((GT110),6) -> 0 | GW110: 1 | GX110: =ROUND(HC110*I110,2) -> 0 | HA110: 0 | HB110: 0 | HC110: =GV110*GW110 -> 0 | HS110: 0 | IK110: 0
A111: 18 | B111: 1 | E111: 5,1 | F111: КА 4 | G111: Антенна ДМВ диапазона EB45LTE | H111: шт. | I111: =I109*J111 -> 1 | J111: 1 | K111: 1 | O111: =ROUND(CP111,2) -> 473.18 | P111: =ROUND((ROUND((AC111*AW111*I111),2)*BC111),2) -> 473.18 | Q111: =(ROUND((ROUND(((ET111)*AV111*I111),2)*BB111),2)+ROUND((ROUND(((AE111-(EU111))*AV111*I111),2)*BS111),2)) -> 0 | R111: =ROUND((ROUND((AE111*AV111*I111),2)*BS111),2) -> 0 | S111: =ROUND((ROUND((AF111*AV111*I111),2)*BA111),2) -> 0 | T111: =ROUND(CU111*I111,2) -> 0 | U111: =CV111*I111 -> 0 | V111: =CW111*I111 -> 0 | W111: =ROUND(CX111*I111,2) -> 0 | X111: =ROUND(CY111,2) -> 0 | Y111: =ROUND(CZ111,2) -> 0 | AA111: 56503348 | AB111: =ROUND((AC111+AD111+AF111),6) -> 473.18 | AC111: =ROUND((ES111),6) -> 473.18 | AD111: =ROUND((((ET111)-(EU111))+AE111),6) -> 0 | AE111: =ROUND((EU111),6) -> 0 | AF111: =ROUND((EV111),6) -> 0 | AG111: =ROUND((AP111),6) -> 0 | AH111: =(EW111) -> 0 | AI111: =(EX111) -> 0 | AJ111: =(AS111) -> 0 | AK111: 473.18 | AL111: 473.18 | AM111: 0 | AN111: 0 | AO111: 0 | AP111: 0 | AQ111: 0 | AR111: 0 | AS111: 0 | AT111: 95 | AU111: 53 | AV111: 1 | AW111: 1 | AZ111: 1 | BA111: 1 | BB111: 1 | BC111: 1 | BH111: 3 | BI111: 2 | BM111: 69 | BN111: 0 | BP111: 0 | BQ111: 40 | BR111: 0 | BS111: 1 | BT111: 1 | BU111: 1 | BV111: 1 | BW111: 1 | BX111: 1 | BZ111: 95 | CA111: 53 | CE111: 30 | CF111: 0 | CG111: 0 | CM111: 0 | CO111: 0 | CP111: =(P111+Q111+S111) -> 473.18 | CQ111: =ROUND((ROUND((AC111*AW111*1),2)*BC111),2) -> 473.18 | CR111: =(ROUND((ROUND(((ET111)*AV111*1),2)*BB111),2)+ROUND((ROUND(((AE111-(EU111))*AV111*1),2)*BS111),2)) -> 0 | CS111: =ROUND((ROUND((AE111*AV111*1),2)*BS111),2) -> 0 | CT111: =ROUND((ROUND((AF111*AV111*1),2)*BA111),2) -> 0 | CU111: =AG111 -> 0 | CV111: =(AH111*AV111) -> 0 | CW111: =AI111 -> 0 | CX111: =AJ111 -> 0 | CY111: =(((S111+R111)*AT111)/100) -> 0 | CZ111: =(((S111+R111)*AU111)/100) -> 0 | DN111: 0 | DO111: 0 | DP111: 1 | DQ111: 1 | DU111: 1010 | DV111: шт. | DW111: шт. | DX111: 1 | EE111: 58162631 | EF111: 40 | EG111: Монтаж оборудования | EH111: 0 | EJ111: 2 | EK111: 69 | EL111: ТСН-2001.4-10. Монтаж радиотелевизионного и электронного оборудования | EM111: ТСН-2001.4-10-2 | EQ111: 0 | ER111: 0 | ES111: 473.18 | ET111: 0 | EU111: 0 | EV111: 0 | EW111: 0 | EX111: 0 | FQ111: 0 | FR111: 0 | FS111: 0 | FX111: 95 | FY111: 53 | GA111: [5 500 / 1,2 / 9,88] + 2% Заг.скл | GD111: 1 | GF111: -900683088 | GG111: 2 | GH111: 4 | GI111: -2 | GJ111: 0 | GK111: 0 | GL111: =ROUND(IF(AND(BH111=3,BI111=3,FS111<>0),P111,0),2) -> 0 | GM111: =ROUND(O111+X111+Y111,2)+GX111 -> 473.18 | GN111: =IF(OR(BI111=0,BI111=1),GM111-GX111,0) -> 0 | GO111: =IF(BI111=2,GM111-GX111,0) -> 473.18 | GP111: =IF(BI111=4,GM111-GX111,0) -> 0 | GR111: 0 | GS111: 2 | GT111: 0 | GV111: =ROUND((GT111),6) -> 0 | GW111: 1 | GX111: =ROUND(HC111*I111,2) -> 0 | HA111: 0 | HB111: 0 | HC111: =GV111*GW111 -> 0 | HE111: 0 | HF111: 2 | HS111: 0 | IK111: 0
A112: 18 | B112: 1 | E112: 5,1 | F112: КА 4 | G112: Антенна ДМВ диапазона EB45LTE | H112: шт. | I112: =I110*J112 -> 1 | J112: 1 | K112: 1 | O112: =ROUND(CP112,2) -> 4675.02 | P112: =ROUND((ROUND((AC112*AW112*I112),2)*BC112),2) -> 4675.02 | Q112: =(ROUND((ROUND(((ET112)*AV112*I112),2)*BB112),2)+ROUND((ROUND(((AE112-(EU112))*AV112*I112),2)*BS112),2)) -> 0 | R112: =ROUND((ROUND((AE112*AV112*I112),2)*BS112),2) -> 0 | S112: =ROUND((ROUND((AF112*AV112*I112),2)*BA112),2) -> 0 | T112: =ROUND(CU112*I112,2) -> 0 | U112: =CV112*I112 -> 0 | V112: =CW112*I112 -> 0 | W112: =ROUND(CX112*I112,2) -> 0 | X112: =ROUND(CY112,2) -> 0 | Y112: =ROUND(CZ112,2) -> 0 | AA112: 56503350 | AB112: =ROUND((AC112+AD112+AF112),6) -> 473.18 | AC112: =ROUND((ES112),6) -> 473.18 | AD112: =ROUND((((ET112)-(EU112))+AE112),6) -> 0 | AE112: =ROUND((EU112),6) -> 0 | AF112: =ROUND((EV112),6) -> 0 | AG112: =ROUND((AP112),6) -> 0 | AH112: =(EW112) -> 0 | AI112: =(EX112) -> 0 | AJ112: =(AS112) -> 0 | AK112: 473.18 | AL112: 473.18 | AM112: 0 | AN112: 0 | AO112: 0 | AP112: 0 | AQ112: 0 | AR112: 0 | AS112: 0 | AT112: 95 | AU112: 53 | AV112: 1 | AW112: 1 | AZ112: 1 | BA112: 1 | BB112: 1 | BC112: 9.88 | BH112: 3 | BI112: 2 | BM112: 69 | BN112: 0 | BP112: 0 | BQ112: 40 | BR112: 0 | BS112: 1 | BT112: 1 | BU112: 1 | BV112: 1 | BW112: 1 | BX112: 1 | BZ112: 95 | CA112: 53 | CE112: 30 | CF112: 0 | CG112: 0 | CM112: 0 | CO112: 0 | CP112: =(P112+Q112+S112) -> 4675.02 | CQ112: =ROUND((ROUND((AC112*AW112*1),2)*BC112),2) -> 4675.02 | CR112: =(ROUND((ROUND(((ET112)*AV112*1),2)*BB112),2)+ROUND((ROUND(((AE112-(EU112))*AV112*1),2)*BS112),2)) -> 0 | CS112: =ROUND((ROUND((AE112*AV112*1),2)*BS112),2) -> 0 | CT112: =ROUND((ROUND((AF112*AV112*1),2)*BA112),2) -> 0 | CU112: =AG112 -> 0 | CV112: =(AH112*AV112) -> 0 | CW112: =AI112 -> 0 | CX112: =AJ112 -> 0 | CY112: =(((S112+R112)*AT112)/100) -> 0 | CZ112: =(((S112+R112)*AU112)/100) -> 0 | DN112: 0 | DO112: 0 | DP112: 1 | DQ112: 1 | DU112: 1010 | DV112: шт. | DW112: шт. | DX112: 1 | EE112: 58162631 | EF112: 40 | EG112: Монтаж оборудования | EH112: 0 | EJ112: 2 | EK112: 69 | EL112: ТСН-2001.4-10. Монтаж радиотелевизионного и электронного оборудования | EM112: ТСН-2001.4-10-2 | EQ112: 0 | ER112: 473.18 | ES112: 473.18 | ET112: 0 | EU112: 0 | EV112: 0 | EW112: 0 | EX112: 0 | EZ112: 5 | FC112: 1 | FD112: 18 | FF112: 5500 | FQ112: 0 | FR112: 0 | FS112: 0 | FX112: 95 | FY112: 53 | GA112: [5 500 / 1,2 / 9,88] + 2% Заг.скл | GD112: 1 | GF112: -900683088 | GG112: 2 | GH112: 3 | GI112: 5 | GJ112: 0 | GK112: 0 | GL112: =ROUND(IF(AND(BH112=3,BI112=3,FS112<>0),P112,0),2) -> 0 | GM112: =ROUND(O112+X112+Y112,2)+GX112 -> 4675.02 | GN112: =IF(OR(BI112=0,BI112=1),GM112-GX112,0) -> 0 | GO112: =IF(BI112=2,GM112-GX112,0) -> 4675.02 | GP112: =IF(BI112=4,GM112-GX112,0) -> 0 | GR112: 1 | GS112: 1 | GT112: 0 | GV112: =ROUND((GT112),6) -> 0 | GW112: 1 | GX112: =ROUND(HC112*I112,2) -> 0 | HA112: 0 | HB112: 0 | HC112: =GV112*GW112 -> 0 | HE112: 0 | HF112: 2 | HS112: 0 | IK112: 0
A113: 17 | B113: 1 | D113: =ROW(EtalonRes!A83) -> 83 | E113: 6 | F113: 4.10-136-1 | G113: Разные устройства, монтаж коробки телевизионной (ответвители, разветвители магистральные, домовые, абонентские), УСС, БФТК | H113: 1 ШТ. | I113: 1 | J113: 0 | K113: 1 | O113: =ROUND(CP113,2) -> 13.47 | P113: =ROUND((ROUND((AC113*AW113*I113),2)*BC113),2) -> 0.29 | Q113: =(ROUND((ROUND((((ET113*1.1))*AV113*I113),2)*BB113),2)+ROUND((ROUND(((AE113-((EU113*1.1)))*AV113*I113),2)*BS113),2)) -> 0 | R113: =ROUND((ROUND((AE113*AV113*I113),2)*BS113),2) -> 0 | S113: =ROUND((ROUND((AF113*AV113*I113),2)*BA113),2) -> 13.18 | T113: =ROUND(CU113*I113,2) -> 0 | U113: =CV113*I113 -> 0.95656 | V113: =CW113*I113 -> 0 | W113: =ROUND(CX113*I113,2) -> 0 | X113: =ROUND(CY113,2) -> 12.52 | Y113: =ROUND(CZ113,2) -> 6.99 | AA113: 56503348 | AB113: =ROUND((AC113+AD113+AF113),6) -> 12.412 | AC113: =ROUND((ES113),6) -> 0.29 | AD113: =ROUND(((((ET113*1.1))-((EU113*1.1)))+AE113),6) -> 0 | AE113: =ROUND(((EU113*1.1)),6) -> 0 | AF113: =ROUND(((EV113*1.1)),6) -> 12.122 | AG113: =ROUND((AP113),6) -> 0 | AH113: =((EW113*1.1)) -> 0.88 | AI113: =((EX113*1.1)) -> 0 | AJ113: =(AS113) -> 0 | AK113: 11.31 | AL113: 0.29 | AM113: 0 | AN113: 0 | AO113: 11.02 | AP113: 0 | AQ113: 0.8 | AR113: 0 | AS113: 0 | AT113: 95 | AU113: 53 | AV113: 1.087 | AW113: 1 | AZ113: 1 | BA113: 1 | BB113: 1 | BC113: 1 | BH113: 0 | BI113: 2 | BJ113: ТСН-2001.4. Доп. 1-42. Сб. 10, т. 136, поз. 1 | BM113: 69 | BN113: 0 | BO113: 4.10-136-1 | BP113: 1 | BQ113: 40 | BR113: 0 | BS113: 1 | BT113: 1 | BU113: 1 | BV113: 1 | BW113: 1 | BX113: 1 | BZ113: 95 | CA113: 53 | CE113: 30 | CF113: 0 | CG113: 0 | CM113: 0 | CO113: 0 | CP113: =(P113+Q113+S113) -> 13.47 | CQ113: =ROUND((ROUND((AC113*AW113*1),2)*BC113),2) -> 0.29 | CR113: =(ROUND((ROUND((((ET113*1.1))*AV113*1),2)*BB113),2)+ROUND((ROUND(((AE113-((EU113*1.1)))*AV113*1),2)*BS113),2)) -> 0 | CS113: =ROUND((ROUND((AE113*AV113*1),2)*BS113),2) -> 0 | CT113: =ROUND((ROUND((AF113*AV113*1),2)*BA113),2) -> 13.18 | CU113: =AG113 -> 0 | CV113: =(AH113*AV113) -> 0.95656 | CW113: =AI113 -> 0 | CX113: =AJ113 -> 0 | CY113: =(((S113+R113)*AT113)/100) -> 12.521 | CZ113: =(((S113+R113)*AU113)/100) -> 6.9854 | DE113: *1,1 | DF113: *1,1 | DG113: *1,1 | DI113: *1,1 | DJ113: *1,1 | DN113: 0 | DO113: 0 | DP113: 1 | DQ113: 1 | DU113: 1013 | DV113: 1 ШТ. | DW113: 1 ШТ. | DX113: 1 | EE113: 58162631 | EF113: 40 | EG113: Монтаж оборудования | EH113: 0 | EJ113: 2 | EK113: 69 | EL113: ТСН-2001.4-10. Монтаж радиотелевизионного и электронного оборудования | EM113: ТСН-2001.4-10-2 | EO113: Поправка: Гл.12.Прил.8.п.8. 5_12.00.01.11.003 | EQ113: 0 | ER113: 11.31 | ES113: 0.29 | ET113: 0 | EU113: 0 | EV113: 11.02 | EW113: 0.8 | EX113: 0 | EY113: 0 | FQ113: 0 | FR113: 0 | FS113: 0 | FX113: 95 | FY113: 53 | GD113: 1 | GF113: 105814318 | GG113: 2 | GH113: 1 | GI113: 2 | GJ113: 0 | GK113: 0 | GL113: =ROUND(IF(AND(BH113=3,BI113=3,FS113<>0),P113,0),2) -> 0 | GM113: =ROUND(O113+X113+Y113,2)+GX113 -> 32.98 | GN113: =IF(OR(BI113=0,BI113=1),GM113-GX113,0) -> 0 | GO113: =IF(BI113=2,GM113-GX113,0) -> 32.98 | GP113: =IF(BI113=4,GM113-GX113,0) -> 0 | GR113: 0 | GS113: 3 | GT113: 0 | GV113: =ROUND((GT113),6) -> 0 | GW113: 1 | GX113: =ROUND(HC113*I113,2) -> 0 | HA113: 0 | HB113: 0 | HC113: =GV113*GW113 -> 0 | HS113: 0 | IK113: 0
A114: 17 | B114: 1 | D114: =ROW(EtalonRes!A84) -> 84 | E114: 6 | F114: 4.10-136-1 | G114: Разные устройства, монтаж коробки телевизионной (ответвители, разветвители магистральные, домовые, абонентские), УСС, БФТК | H114: 1 ШТ. | I114: 1 | J114: 0 | K114: 1 | O114: =ROUND(CP114,2) -> 727.64 | P114: =ROUND((ROUND((AC114*AW114*I114),2)*BC114),2) -> 2.87 | Q114: =(ROUND((ROUND((((ET114*1.1))*AV114*I114),2)*BB114),2)+ROUND((ROUND(((AE114-((EU114*1.1)))*AV114*I114),2)*BS114),2)) -> 0 | R114: =ROUND((ROUND((AE114*AV114*I114),2)*BS114),2) -> 0 | S114: =ROUND((ROUND((AF114*AV114*I114),2)*BA114),2) -> 724.77 | T114: =ROUND(CU114*I114,2) -> 0 | U114: =CV114*I114 -> 0.95656 | V114: =CW114*I114 -> 0 | W114: =ROUND(CX114*I114,2) -> 0 | X114: =ROUND(CY114,2) -> 688.53 | Y114: =ROUND(CZ114,2) -> 384.13 | AA114: 56503350 | AB114: =ROUND((AC114+AD114+AF114),6) -> 12.412 | AC114: =ROUND((ES114),6) -> 0.29 | AD114: =ROUND(((((ET114*1.1))-((EU114*1.1)))+AE114),6) -> 0 | AE114: =ROUND(((EU114*1.1)),6) -> 0 | AF114: =ROUND(((EV114*1.1)),6) -> 12.122 | AG114: =ROUND((AP114),6) -> 0 | AH114: =((EW114*1.1)) -> 0.88 | AI114: =((EX114*1.1)) -> 0 | AJ114: =(AS114) -> 0 | AK114: 11.31 | AL114: 0.29 | AM114: 0 | AN114: 0 | AO114: 11.02 | AP114: 0 | AQ114: 0.8 | AR114: 0 | AS114: 0 | AT114: 95 | AU114: 53 | AV114: 1.087 | AW114: 1 | AZ114: 1 | BA114: 54.99 | BB114: 1 | BC114: 9.9 | BH114: 0 | BI114: 2 | BJ114: ТСН-2001.4. Доп. 1-42. Сб. 10, т. 136, поз. 1 | BM114: 69 | BN114: 0 | BO114: 4.10-136-1 | BP114: 1 | BQ114: 40 | BR114: 0 | BS114: 54.99 | BT114: 1 | BU114: 1 | BV114: 1 | BW114: 1 | BX114: 1 | BZ114: 95 | CA114: 53 | CE114: 30 | CF114: 0 | CG114: 0 | CM114: 0 | CO114: 0 | CP114: =(P114+Q114+S114) -> 727.64 | CQ114: =ROUND((ROUND((AC114*AW114*1),2)*BC114),2) -> 2.87 | CR114: =(ROUND((ROUND((((ET114*1.1))*AV114*1),2)*BB114),2)+ROUND((ROUND(((AE114-((EU114*1.1)))*AV114*1),2)*BS114),2)) -> 0 | CS114: =ROUND((ROUND((AE114*AV114*1),2)*BS114),2) -> 0 | CT114: =ROUND((ROUND((AF114*AV114*1),2)*BA114),2) -> 724.77 | CU114: =AG114 -> 0 | CV114: =(AH114*AV114) -> 0.95656 | CW114: =AI114 -> 0 | CX114: =AJ114 -> 0 | CY114: =(((S114+R114)*AT114)/100) -> 688.5315 | CZ114: =(((S114+R114)*AU114)/100) -> 384.1281 | DE114: *1,1 | DF114: *1,1 | DG114: *1,1 | DI114: *1,1 | DJ114: *1,1 | DN114: 0 | DO114: 0 | DP114: 1 | DQ114: 1 | DU114: 1013 | DV114: 1 ШТ. | DW114: 1 ШТ. | DX114: 1 | EE114: 58162631 | EF114: 40 | EG114: Монтаж оборудования | EH114: 0 | EJ114: 2 | EK114: 69 | EL114: ТСН-2001.4-10. Монтаж радиотелевизионного и электронного оборудования | EM114: ТСН-2001.4-10-2 | EO114: Поправка: Гл.12.Прил.8.п.8. 5_12.00.01.11.003 | EQ114: 0 | ER114: 11.31 | ES114: 0.29 | ET114: 0 | EU114: 0 | EV114: 11.02 | EW114: 0.8 | EX114: 0 | EY114: 0 | FQ114: 0 | FR114: 0 | FS114: 0 | FX114: 95 | FY114: 53 | GD114: 1 | GF114: 105814318 | GG114: 2 | GH114: 1 | GI114: 2 | GJ114: 0 | GK114: 0 | GL114: =ROUND(IF(AND(BH114=3,BI114=3,FS114<>0),P114,0),2) -> 0 | GM114: =ROUND(O114+X114+Y114,2)+GX114 -> 1800.3 | GN114: =IF(OR(BI114=0,BI114=1),GM114-GX114,0) -> 0 | GO114: =IF(BI114=2,GM114-GX114,0) -> 1800.3 | GP114: =IF(BI114=4,GM114-GX114,0) -> 0 | GR114: 0 | GS114: 3 | GT114: 0 | GV114: =ROUND((GT114),6) -> 0 | GW114: 1 | GX114: =ROUND(HC114*I114,2) -> 0 | HA114: 0 | HB114: 0 | HC114: =GV114*GW114 -> 0 | HS114: 0 | IK114: 0
