Workbook

Sheet 02-01-03
A1: =Source!B1 -> Smeta.RU (495) 974-1589
J2: Форма № 4б
A3: Капитальный ремонт здания Государственного бюджетного общеобразовательного учреждения города Москвы "Школа №236" по адресу: г. Москва, улица Клязьминская, дом 7, корпус 4. | AP3: Капитальный ремонт здания Государственного бюджетного общеобразовательного учреждения города Москвы "Школа №236" по адресу: г. Москва, улица Клязьминская, дом 7, корпус 4. 02-01-03 ЭОМ
A4: (наименование стройки и/или объекта)
A6: =CONCATENATE( "ЛОКАЛЬНАЯ СМЕТА № ",IF(Source!F20<>"Новая локальная смета", Source!F20, "")) -> ЛОКАЛЬНАЯ СМЕТА № 02-01-03
A8: =IF(Source!G20<>"Новая локальная смета", Source!G20, "") -> Система электроснабжения
A9: (наименование работ и затрат)
A11: =CONCATENATE( "Основание: чертежи № ", Source!J20) -> Основание: чертежи № 2024-00272-01-0-ИОС1
I13: В базисном уровне цен | J13: В текущем уровне цен
E14: Сметная стоимость | I14: =I15+I16+I17+I18 -> 6460.79 | J14: =J15+J16+J17+J18 -> 59208.78 | K14: тыс.руб.
E15: Строительные работы | I15: =ROUND((Source!F863)/1000, 2) -> 0 | J15: =ROUND((Source!P863)/1000, 2) -> 0 | K15: тыс.руб.
E16: Работы по монтажу оборудования | I16: =ROUND((Source!F864)/1000, 2) -> 5360.51 | J16: =ROUND((Source!P864)/1000, 2) -> 50786.26 | K16: тыс.руб.
E17: Оборудование | I17: =ROUND((Source!F855)/1000, 2) -> 1100.28 | J17: =ROUND((Source!P855)/1000, 2) -> 8422.52 | K17: тыс.руб.
E18: Прочие работы и затраты | I18: =ROUND((Source!F865+Source!F866)/1000, 2) -> 0 | J18: =ROUND((Source!P865+Source!P866)/1000, 2) -> 0 | K18: тыс.руб.
E19: Средства на оплату труда | I19: =(Source!F861+ Source!F860)/1000 -> 74.37731 | J19: =((Source!P861 + Source!P860)/1000) -> 4090.0083 | K19: тыс.руб.
E20: Затраты труда | I20: =Source!F868 -> 5619.3181 | K20: чел.-ч.
E21: Кроме того:
E22: Возврат материалов | I22: =SUM(Y28:Y1292)/1000 -> 0 | J22: =SUM(Z28:Z1292)/1000 -> 0 | K22: тыс.руб.
A24: Составлен(а) по ТСН-2001 с учетом Дополнения №: 80
A25: № и период сборника коэффициентов (индексов) пересчета: Коэффициенты к ТСН-2001 МГЭ Дополнение 80, строительство №217/80 III квартал 2025 года и Коэффициенты к ТСН-2001.13-2 Дополнение 46 №62/46 III квартал 2025 года | AP25: № и период сборника коэффициентов (индексов) пересчета: Коэффициенты к ТСН-2001 МГЭ Дополнение 80, строительство №217/80 III квартал 2025 года и Коэффициенты к ТСН-2001.13-2 Дополнение 46 №62/46 III квартал 2025 года
A26: № п/п | B26: Шифр расценки и коды ресурсов | C26: Наименование работ и затрат | D26: Ед. изм. | E26: Кол-во единиц | F26: Цена на ед. изм., руб. | G26: Попра- вочные коэффи- циенты | H26: Коэффи- циенты зимних удорожа- ний | I26: Всего в ценах на январь 2000 года, руб. | J26: Коэффи- циенты (индек- сы) пере- счета, нормы НР и СП | K26: ВСЕГО затрат в текущем уровне цен, руб.
A27: 1 | B27: 2 | C27: 3 | D27: 4 | E27: 5 | F27: 6 | G27: 7 | H27: 8 | I27: 9 | J27: 10 | K27: 11
A29: =CONCATENATE("Раздел: ",IF(Source!G24<>"Новый раздел", Source!G24, "")) -> Раздел: Щитовое оборудование
B31: =Source!G28 -> Вводная панель
A32: 1 | B32: =Source!F29 -> 4.8-238-3 | C32: Монтаж щитов и стеллажей с блоками резисторов (ящиками сопротивлений) высотой свыше 1700 мм, щита заводского изготовления однорядного или двухрядного открытого исполнения шириной 800 мм | D32: =Source!H29 -> 1 м ширины по фронту | E32: =Source!I29 -> 1.2 | Q32: =Source!X29 -> 116.75 | R32: =Source!X30 -> 6420.04 | S32: =Source!Y29 -> 61.38 | T32: =Source!Y30 -> 3375.49 | U32: =ROUND((175/100)*ROUND(Source!R29, 2), 2) -> 16.47 | V32: =ROUND((0/100)*ROUND(Source!R30, 2), 2) -> 0 | AC32: 0
C33: ="Объем: "&Source!I29&"=0,6+"&"0,6" -> Объем: 1,2=0,6+0,6
C34: ЗП | F34: =Source!AO29 -> 80.28 | G34: =Source!DG29 -> *1,1 | H34: =Source!AV30 -> 1.047 | I34: =Source!S29 -> 110.95 | J34: =IF(Source!BA30<> 0, Source!BA30, 1) -> 54.99 | K34: =Source!S30 -> 6101.14
C35: ЭМ | F35: =Source!AM29 -> 56.75 | G35: =Source!DE29 -> *1,1 | H35: =Source!AV30 -> 1.047 | I35: =Source!Q29 -> 78.43 | J35: =IF(Source!BB30<> 0, Source!BB30, 1) -> 15.3 | K35: =Source!Q30 -> 1199.98
C36: в т.ч. ЗПМ | F36: =Source!AN29 -> 6.81 | G36: =Source!DF29 -> *1,1 | H36: =Source!AV30 -> 1.047 | I36: =Source!R29 -> 9.41 | J36: =IF(Source!BS30<> 0, Source!BS30, 1) -> 54.99 | K36: =Source!R30 -> 517.46
C37: МР | F37: =Source!AL29 -> 23.66 | G37: =Source!DD29 | H37: =Source!AW30 -> 1 | I37: =Source!P29 -> 28.39 | J37: =IF(Source!BC30<> 0, Source!BC30, 1) -> 7.98 | K37: =Source!P30 -> 226.55
A38: 1,1 | B38: =Source!F31 -> 1.1-1-58 | C38: Болты строительные с гайками, оцинкованные, М10х100 мм | D38: =Source!H31 -> т | E38: =Source!I31 -> 0.000612 | F38: =Source!AK31 -> 24609.76 | H38: =Source!AW32 -> 1 | I38: =Source!O31 -> 15.06 | J38: =IF(Source!BC32<> 0, Source!BC32, 1) -> 5.15 | K38: =Source!O32 -> 77.56 | Q38: =Source!X31 -> 0 | R38: =Source!X32 -> 0 | S38: =Source!Y31 -> 0 | T38: =Source!Y32 -> 0 | U38: =ROUND((175/100)*ROUND(Source!R31, 2), 2) -> 0 | V38: =ROUND((0/100)*ROUND(Source!R32, 2), 2) -> 0 | AC38: 3
C39: НР от ФОТ | D39: % | E39: =Source!BZ30 -> 97 | I39: =SUM(Q32:Q38) -> 116.75 | J39: =Source!AT30 -> 97 | K39: =SUM(R32:R38) -> 6420.04
C40: СП от ФОТ | D40: % | E40: =Source!CA30 -> 51 | I40: =SUM(S32:S39) -> 61.38 | J40: =Source!AU30 -> 51 | K40: =SUM(T32:T39) -> 3375.49
C41: ЗТР | D41: чел-ч | E41: =Source!AQ29 -> 6.18 | G41: =Source!DI29 -> *1,1 | H41: =Source!AV30 -> 1.047 | I41: =Source!U29 -> 8.5410072
C42: ВСЕГО работ по позиции: | H42: =I34+I35+I37+I39+I40+SUM(I38:I38)-SUMIF(AC38:AC38, 5, I38:I38)-SUMIF(AC38:AC38, 6, I38:I38) -> 410.96 | J42: =K34+K35+K37+K39+K40+SUM(K38:K38)-SUMIF(AC38:AC38, 5, K38:K38)-SUMIF(AC38:AC38, 6, K38:K38) -> 17400.76
C43: ВСЕГО оборудование по позиции: | H43: =SUMIF(AC38:AC38, 5, I38:I38)+SUMIF(AC38:AC38, 6, I38:I38) -> 0 | J43: =SUMIF(AC38:AC38, 5, K38:K38)+SUMIF(AC38:AC38, 6, K38:K38) -> 0
C44: ВСЕГО по позиции: | H44: =I34+I35+I37+I39+I40+SUM(I38:I38) -> 410.96 | J44: =K34+K35+K37+K39+K40+SUM(K38:K38) -> 17400.76 | O44: =I34+I35+I37+I39+I40+SUM(I38:I38) -> 410.96 | P44: =K34+K35+K37+K39+K40+SUM(K38:K38) -> 17400.76
A46: 2 | B46: =Source!F33 -> КА-1 | C46: ОБОРУДОВАНИЕ:_x000D_ Вводная панель ВП1 60 887,82 = [536 936,24 / 1,2 / 7,66] + 3% Трансп + 1,2% Заг.скл | D46: =Source!H33 -> ШТ | E46: =Source!I33 -> 1 | F46: =Source!AL33 -> 60887.82 | G46: =Source!DD33 | H46: =Source!AW34 -> 1 | I46: =Source!P33 -> 60887.82 | J46: =IF(Source!BC34<> 0, Source!BC34, 1) -> 7.66 | K46: =Source!P34 -> 466400.7 | Q46: =Source!X33 -> 0 | R46: =Source!X34 -> 0 | S46: =Source!Y33 -> 0 | T46: =Source!Y34 -> 0 | U46: =ROUND((175/100)*ROUND(Source!R33, 2), 2) -> 0 | V46: =ROUND((0/100)*ROUND(Source!R34, 2), 2) -> 0 | AC46: 5
C47: ВСЕГО по позиции: | H47: =I46+0 -> 60887.82 | J47: =K46+0 -> 466400.7 | O47: =I46+0 -> 60887.82 | P47: =K46+0 -> 466400.7
A49: 3 | B49: =Source!F35 -> КА-2 | C49: ОБОРУДОВАНИЕ:_x000D_ Вводная панель ВП1 44 301,78 = [390 673,02 / 1,2 / 7,66] + 3% Трансп + 1,2% Заг.скл | D49: =Source!H35 -> ШТ | E49: =Source!I35 -> 1 | F49: =Source!AL35 -> 44301.78 | G49: =Source!DD35 | H49: =Source!AW36 -> 1 | I49: =Source!P35 -> 44301.78 | J49: =IF(Source!BC36<> 0, Source!BC36, 1) -> 7.66 | K49: =Source!P36 -> 339351.63 | Q49: =Source!X35 -> 0 | R49: =Source!X36 -> 0 | S49: =Source!Y35 -> 0 | T49: =Source!Y36 -> 0 | U49: =ROUND((175/100)*ROUND(Source!R35, 2), 2) -> 0 | V49: =ROUND((0/100)*ROUND(Source!R36, 2), 2) -> 0 | AC49: 5
C50: ВСЕГО по позиции: | H50: =I49+0 -> 44301.78 | J50: =K49+0 -> 339351.63 | O50: =I49+0 -> 44301.78 | P50: =K49+0 -> 339351.63
B53: =Source!G37 -> Распределительная панель
A54: 4 | B54: =Source!F38 -> 4.8-238-3 | C54: Монтаж щитов и стеллажей с блоками резисторов (ящиками сопротивлений) высотой свыше 1700 мм, щита заводского изготовления однорядного или двухрядного открытого исполнения шириной 800 мм | D54: =Source!H38 -> 1 м ширины по фронту | E54: =Source!I38 -> 1.2 | Q54: =Source!X38 -> 116.75 | R54: =Source!X39 -> 6420.04 | S54: =Source!Y38 -> 61.38 | T54: =Source!Y39 -> 3375.49 | U54: =ROUND((175/100)*ROUND(Source!R38, 2), 2) -> 16.47 | V54: =ROUND((0/100)*ROUND(Source!R39, 2), 2) -> 0 | AC54: 0
C55: ="Объем: "&Source!I38&"=0,6+"&"0,6" -> Объем: 1,2=0,6+0,6
C56: ЗП | F56: =Source!AO38 -> 80.28 | G56: =Source!DG38 -> *1,1 | H56: =Source!AV39 -> 1.047 | I56: =Source!S38 -> 110.95 | J56: =IF(Source!BA39<> 0, Source!BA39, 1) -> 54.99 | K56: =Source!S39 -> 6101.14
C57: ЭМ | F57: =Source!AM38 -> 56.75 | G57: =Source!DE38 -> *1,1 | H57: =Source!AV39 -> 1.047 | I57: =Source!Q38 -> 78.43 | J57: =IF(Source!BB39<> 0, Source!BB39, 1) -> 15.3 | K57: =Source!Q39 -> 1199.98
C58: в т.ч. ЗПМ | F58: =Source!AN38 -> 6.81 | G58: =Source!DF38 -> *1,1 | H58: =Source!AV39 -> 1.047 | I58: =Source!R38 -> 9.41 | J58: =IF(Source!BS39<> 0, Source!BS39, 1) -> 54.99 | K58: =Source!R39 -> 517.46
C59: МР | F59: =Source!AL38 -> 23.66 | G59: =Source!DD38 | H59: =Source!AW39 -> 1 | I59: =Source!P38 -> 28.39 | J59: =IF(Source!BC39<> 0, Source!BC39, 1) -> 7.98 | K59: =Source!P39 -> 226.55
A60: 4,1 | B60: =Source!F40 -> 1.1-1-58 | C60: Болты строительные с гайками, оцинкованные, М10х100 мм | D60: =Source!H40 -> т | E60: =Source!I40 -> 0.000612 | F60: =Source!AK40 -> 24609.76 | H60: =Source!AW41 -> 1 | I60: =Source!O40 -> 15.06 | J60: =IF(Source!BC41<> 0, Source!BC41, 1) -> 5.15 | K60: =Source!O41 -> 77.56 | Q60: =Source!X40 -> 0 | R60: =Source!X41 -> 0 | S60: =Source!Y40 -> 0 | T60: =Source!Y41 -> 0 | U60: =ROUND((175/100)*ROUND(Source!R40, 2), 2) -> 0 | V60: =ROUND((0/100)*ROUND(Source!R41, 2), 2) -> 0 | AC60: 3
C61: НР от ФОТ | D61: % | E61: =Source!BZ39 -> 97 | I61: =SUM(Q54:Q60) -> 116.75 | J61: =Source!AT39 -> 97 | K61: =SUM(R54:R60) -> 6420.04
C62: СП от ФОТ | D62: % | E62: =Source!CA39 -> 51 | I62: =SUM(S54:S61) -> 61.38 | J62: =Source!AU39 -> 51 | K62: =SUM(T54:T61) -> 3375.49
C63: ЗТР | D63: чел-ч | E63: =Source!AQ38 -> 6.18 | G63: =Source!DI38 -> *1,1 | H63: =Source!AV39 -> 1.047 | I63: =Source!U38 -> 8.5410072
C64: ВСЕГО работ по позиции: | H64: =I56+I57+I59+I61+I62+SUM(I60:I60)-SUMIF(AC60:AC60, 5, I60:I60)-SUMIF(AC60:AC60, 6, I60:I60) -> 410.96 | J64: =K56+K57+K59+K61+K62+SUM(K60:K60)-SUMIF(AC60:AC60, 5, K60:K60)-SUMIF(AC60:AC60, 6, K60:K60) -> 17400.76
C65: ВСЕГО оборудование по позиции: | H65: =SUMIF(AC60:AC60, 5, I60:I60)+SUMIF(AC60:AC60, 6, I60:I60) -> 0 | J65: =SUMIF(AC60:AC60, 5, K60:K60)+SUMIF(AC60:AC60, 6, K60:K60) -> 0
C66: ВСЕГО по позиции: | H66: =I56+I57+I59+I61+I62+SUM(I60:I60) -> 410.96 | J66: =K56+K57+K59+K61+K62+SUM(K60:K60) -> 17400.76 | O66: =I56+I57+I59+I61+I62+SUM(I60:I60) -> 410.96 | P66: =K56+K57+K59+K61+K62+SUM(K60:K60) -> 17400.76
A68: 5 | B68: =Source!F42 -> КА-3 | C68: ОБОРУДОВАНИЕ:_x000D_ Распределительная панель РП-1 38 512,11 = [339 617,08 / 1,2 / 7,66] + 3% Трансп + 1,2% Заг.скл | D68: =Source!H42 -> ШТ | E68: =Source!I42 -> 1 | F68: =Source!AL42 -> 38512.11 | G68: =Source!DD42 | H68: =Source!AW43 -> 1 | I68: =Source!P42 -> 38512.11 | J68: =IF(Source!BC43<> 0, Source!BC43, 1) -> 7.66 | K68: =Source!P43 -> 295002.76 | Q68: =Source!X42 -> 0 | R68: =Source!X43 -> 0 | S68: =Source!Y42 -> 0 | T68: =Source!Y43 -> 0 | U68: =ROUND((175/100)*ROUND(Source!R42, 2), 2) -> 0 | V68: =ROUND((0/100)*ROUND(Source!R43, 2), 2) -> 0 | AC68: 5
C69: ВСЕГО по позиции: | H69: =I68+0 -> 38512.11 | J69: =K68+0 -> 295002.76 | O69: =I68+0 -> 38512.11 | P69: =K68+0 -> 295002.76
A71: 6 | B71: =Source!F44 -> КА-4 | C71: ОБОРУДОВАНИЕ:_x000D_ Распределительная панель РП-2 37 439,23 = [330 156,03 / 1,2 / 7,66] + 3% Трансп + 1,2% Заг.скл | D71: =Source!H44 -> ШТ | E71: =Source!I44 -> 1 | F71: =Source!AL44 -> 37439.23 | G71: =Source!DD44 | H71: =Source!AW45 -> 1 | I71: =Source!P44 -> 37439.23 | J71: =IF(Source!BC45<> 0, Source!BC45, 1) -> 7.66 | K71: =Source!P45 -> 286784.5 | Q71: =Source!X44 -> 0 | R71: =Source!X45 -> 0 | S71: =Source!Y44 -> 0 | T71: =Source!Y45 -> 0 | U71: =ROUND((175/100)*ROUND(Source!R44, 2), 2) -> 0 | V71: =ROUND((0/100)*ROUND(Source!R45, 2), 2) -> 0 | AC71: 5
C72: ВСЕГО по позиции: | H72: =I71+0 -> 37439.23 | J72: =K71+0 -> 286784.5 | O72: =I71+0 -> 37439.23 | P72: =K71+0 -> 286784.5
B75: =Source!G46 -> Панель ЩГП с АВР
A76: 7 | B76: =Source!F47 -> 4.8-238-3 | C76: Монтаж щитов и стеллажей с блоками резисторов (ящиками сопротивлений) высотой свыше 1700 мм, щита заводского изготовления однорядного или двухрядного открытого исполнения шириной 800 мм | D76: =Source!H47 -> 1 м ширины по фронту | E76: =Source!I47 -> 0.6 | Q76: =Source!X47 -> 58.38 | R76: =Source!X48 -> 3210.55 | S76: =Source!Y47 -> 30.7 | T76: =Source!Y48 -> 1688.02 | U76: =ROUND((175/100)*ROUND(Source!R47, 2), 2) -> 8.24 | V76: =ROUND((0/100)*ROUND(Source!R48, 2), 2) -> 0 | AC76: 0
C77: ЗП | F77: =Source!AO47 -> 80.28 | G77: =Source!DG47 -> *1,1 | H77: =Source!AV48 -> 1.047 | I77: =Source!S47 -> 55.48 | J77: =IF(Source!BA48<> 0, Source!BA48, 1) -> 54.99 | K77: =Source!S48 -> 3050.85
C78: ЭМ | F78: =Source!AM47 -> 56.75 | G78: =Source!DE47 -> *1,1 | H78: =Source!AV48 -> 1.047 | I78: =Source!Q47 -> 39.22 | J78: =IF(Source!BB48<> 0, Source!BB48, 1) -> 15.3 | K78: =Source!Q48 -> 600.07
C79: в т.ч. ЗПМ | F79: =Source!AN47 -> 6.81 | G79: =Source!DF47 -> *1,1 | H79: =Source!AV48 -> 1.047 | I79: =Source!R47 -> 4.71 | J79: =IF(Source!BS48<> 0, Source!BS48, 1) -> 54.99 | K79: =Source!R48 -> 259
C80: МР | F80: =Source!AL47 -> 23.66 | G80: =Source!DD47 | H80: =Source!AW48 -> 1 | I80: =Source!P47 -> 14.2 | J80: =IF(Source!BC48<> 0, Source!BC48, 1) -> 7.98 | K80: =Source!P48 -> 113.32
A81: 7,1 | B81: =Source!F49 -> 1.1-1-58 | C81: Болты строительные с гайками, оцинкованные, М10х100 мм | D81: =Source!H49 -> т | E81: =Source!I49 -> 0.000306 | F81: =Source!AK49 -> 24609.76 | H81: =Source!AW50 -> 1 | I81: =Source!O49 -> 7.53 | J81: =IF(Source!BC50<> 0, Source!BC50, 1) -> 5.15 | K81: =Source!O50 -> 38.78 | Q81: =Source!X49 -> 0 | R81: =Source!X50 -> 0 | S81: =Source!Y49 -> 0 | T81: =Source!Y50 -> 0 | U81: =ROUND((175/100)*ROUND(Source!R49, 2), 2) -> 0 | V81: =ROUND((0/100)*ROUND(Source!R50, 2), 2) -> 0 | AC81: 3
C82: НР от ФОТ | D82: % | E82: =Source!BZ48 -> 97 | I82: =SUM(Q76:Q81) -> 58.38 | J82: =Source!AT48 -> 97 | K82: =SUM(R76:R81) -> 3210.55
C83: СП от ФОТ | D83: % | E83: =Source!CA48 -> 51 | I83: =SUM(S76:S82) -> 30.7 | J83: =Source!AU48 -> 51 | K83: =SUM(T76:T82) -> 1688.02
C84: ЗТР | D84: чел-ч | E84: =Source!AQ47 -> 6.18 | G84: =Source!DI47 -> *1,1 | H84: =Source!AV48 -> 1.047 | I84: =Source!U47 -> 4.2705036
C85: ВСЕГО работ по позиции: | H85: =I77+I78+I80+I82+I83+SUM(I81:I81)-SUMIF(AC81:AC81, 5, I81:I81)-SUMIF(AC81:AC81, 6, I81:I81) -> 205.51 | J85: =K77+K78+K80+K82+K83+SUM(K81:K81)-SUMIF(AC81:AC81, 5, K81:K81)-SUMIF(AC81:AC81, 6, K81:K81) -> 8701.59
C86: ВСЕГО оборудование по позиции: | H86: =SUMIF(AC81:AC81, 5, I81:I81)+SUMIF(AC81:AC81, 6, I81:I81) -> 0 | J86: =SUMIF(AC81:AC81, 5, K81:K81)+SUMIF(AC81:AC81, 6, K81:K81) -> 0
C87: ВСЕГО по позиции: | H87: =I77+I78+I80+I82+I83+SUM(I81:I81) -> 205.51 | J87: =K77+K78+K80+K82+K83+SUM(K81:K81) -> 8701.59 | O87: =I77+I78+I80+I82+I83+SUM(I81:I81) -> 205.51 | P87: =K77+K78+K80+K82+K83+SUM(K81:K81) -> 8701.59
A89: 8 | B89: =Source!F51 -> КА-5 | C89: ОБОРУДОВАНИЕ:_x000D_ Панель ЩГП с АВР 29 029,49 = [255 995,17 / 1,2 / 7,66] + 3% Трансп + 1,2% Заг.скл | D89: =Source!H51 -> ШТ | E89: =Source!I51 -> 1 | F89: =Source!AL51 -> 29029.49 | G89: =Source!DD51 | H89: =Source!AW52 -> 1 | I89: =Source!P51 -> 29029.49 | J89: =IF(Source!BC52<> 0, Source!BC52, 1) -> 7.66 | K89: =Source!P52 -> 222365.89 | Q89: =Source!X51 -> 0 | R89: =Source!X52 -> 0 | S89: =Source!Y51 -> 0 | T89: =Source!Y52 -> 0 | U89: =ROUND((175/100)*ROUND(Source!R51, 2), 2) -> 0 | V89: =ROUND((0/100)*ROUND(Source!R52, 2), 2) -> 0 | AC89: 5
C90: ВСЕГО по позиции: | H90: =I89+0 -> 29029.49 | J90: =K89+0 -> 222365.89 | O90: =I89+0 -> 29029.49 | P90: =K89+0 -> 222365.89
B93: =Source!G53 -> Панель ПЭСПЗ с АВР
A94: 9 | B94: =Source!F54 -> 4.8-238-3 | C94: Монтаж щитов и стеллажей с блоками резисторов (ящиками сопротивлений) высотой свыше 1700 мм, щита заводского изготовления однорядного или двухрядного открытого исполнения шириной 800 мм | D94: =Source!H54 -> 1 м ширины по фронту | E94: =Source!I54 -> 0.6 | Q94: =Source!X54 -> 58.38 | R94: =Source!X55 -> 3210.55 | S94: =Source!Y54 -> 30.7 | T94: =Source!Y55 -> 1688.02 | U94: =ROUND((175/100)*ROUND(Source!R54, 2), 2) -> 8.24 | V94: =ROUND((0/100)*ROUND(Source!R55, 2), 2) -> 0 | AC94: 0
C95: ЗП | F95: =Source!AO54 -> 80.28 | G95: =Source!DG54 -> *1,1 | H95: =Source!AV55 -> 1.047 | I95: =Source!S54 -> 55.48 | J95: =IF(Source!BA55<> 0, Source!BA55, 1) -> 54.99 | K95: =Source!S55 -> 3050.85
C96: ЭМ | F96: =Source!AM54 -> 56.75 | G96: =Source!DE54 -> *1,1 | H96: =Source!AV55 -> 1.047 | I96: =Source!Q54 -> 39.22 | J96: =IF(Source!BB55<> 0, Source!BB55, 1) -> 15.3 | K96: =Source!Q55 -> 600.07
C97: в т.ч. ЗПМ | F97: =Source!AN54 -> 6.81 | G97: =Source!DF54 -> *1,1 | H97: =Source!AV55 -> 1.047 | I97: =Source!R54 -> 4.71 | J97: =IF(Source!BS55<> 0, Source!BS55, 1) -> 54.99 | K97: =Source!R55 -> 259
C98: МР | F98: =Source!AL54 -> 23.66 | G98: =Source!DD54 | H98: =Source!AW55 -> 1 | I98: =Source!P54 -> 14.2 | J98: =IF(Source!BC55<> 0, Source!BC55, 1) -> 7.98 | K98: =Source!P55 -> 113.32
A99: 9,1 | B99: =Source!F56 -> 1.1-1-58 | C99: Болты строительные с гайками, оцинкованные, М10х100 мм | D99: =Source!H56 -> т | E99: =Source!I56 -> 0.000306 | F99: =Source!AK56 -> 24609.76 | H99: =Source!AW57 -> 1 | I99: =Source!O56 -> 7.53 | J99: =IF(Source!BC57<> 0, Source!BC57, 1) -> 5.15 | K99: =Source!O57 -> 38.78 | Q99: =Source!X56 -> 0 | R99: =Source!X57 -> 0 | S99: =Source!Y56 -> 0 | T99: =Source!Y57 -> 0 | U99: =ROUND((175/100)*ROUND(Source!R56, 2), 2) -> 0 | V99: =ROUND((0/100)*ROUND(Source!R57, 2), 2) -> 0 | AC99: 3
C100: НР от ФОТ | D100: % | E100: =Source!BZ55 -> 97 | I100: =SUM(Q94:Q99) -> 58.38 | J100: =Source!AT55 -> 97 | K100: =SUM(R94:R99) -> 3210.55
C101: СП от ФОТ | D101: % | E101: =Source!CA55 -> 51 | I101: =SUM(S94:S100) -> 30.7 | J101: =Source!AU55 -> 51 | K101: =SUM(T94:T100) -> 1688.02
C102: ЗТР | D102: чел-ч | E102: =Source!AQ54 -> 6.18 | G102: =Source!DI54 -> *1,1 | H102: =Source!AV55 -> 1.047 | I102: =Source!U54 -> 4.2705036
C103: ВСЕГО работ по позиции: | H103: =I95+I96+I98+I100+I101+SUM(I99:I99)-SUMIF(AC99:AC99, 5, I99:I99)-SUMIF(AC99:AC99, 6, I99:I99) -> 205.51 | J103: =K95+K96+K98+K100+K101+SUM(K99:K99)-SUMIF(AC99:AC99, 5, K99:K99)-SUMIF(AC99:AC99, 6, K99:K99) -> 8701.59
C104: ВСЕГО оборудование по позиции: | H104: =SUMIF(AC99:AC99, 5, I99:I99)+SUMIF(AC99:AC99, 6, I99:I99) -> 0 | J104: =SUMIF(AC99:AC99, 5, K99:K99)+SUMIF(AC99:AC99, 6, K99:K99) -> 0
C105: ВСЕГО по позиции: | H105: =I95+I96+I98+I100+I101+SUM(I99:I99) -> 205.51 | J105: =K95+K96+K98+K100+K101+SUM(K99:K99) -> 8701.59 | O105: =I95+I96+I98+I100+I101+SUM(I99:I99) -> 205.51 | P105: =K95+K96+K98+K100+K101+SUM(K99:K99) -> 8701.59
A107: 10 | B107: =Source!F58 -> КА-6 | C107: ОБОРУДОВАНИЕ:_x000D_ Панель ПЭСПЗ с АВР 34 835,39 = [255 995,17 / 7,66] + 3% Трансп + 1,2% Заг.скл | D107: =Source!H58 -> ШТ | E107: =Source!I58 -> 1 | F107: =Source!AL58 -> 34835.39 | G107: =Source!DD58 | H107: =Source!AW59 -> 1 | I107: =Source!P58 -> 34835.39 | J107: =IF(Source!BC59<> 0, Source!BC59, 1) -> 7.66 | K107: =Source!P59 -> 266839.09 | Q107: =Source!X58 -> 0 | R107: =Source!X59 -> 0 | S107: =Source!Y58 -> 0 | T107: =Source!Y59 -> 0 | U107: =ROUND((175/100)*ROUND(Source!R58, 2), 2) -> 0 | V107: =ROUND((0/100)*ROUND(Source!R59, 2), 2) -> 0 | AC107: 5
C108: ВСЕГО по позиции: | H108: =I107+0 -> 34835.39 | J108: =K107+0 -> 266839.09 | O108: =I107+0 -> 34835.39 | P108: =K107+0 -> 266839.09
B111: =Source!G60 -> УКРМ 50-10
A112: 11 | B112: =Source!F61 -> 4.8-240-2 | C112: Монтаж пультов и шкафов управления, пульта управления напольного, высотой до 1200 мм, глубиной и шириной по фронту до 700х1000 мм | D112: =Source!H61 -> 1 ШТ. | E112: =Source!I61 -> 2 | Q112: =Source!X61 -> 81.51 | R112: =Source!X62 -> 4482.19 | S112: =Source!Y61 -> 42.86 | T112: =Source!Y62 -> 2356.61 | U112: =ROUND((175/100)*ROUND(Source!R61, 2), 2) -> 39.18 | V112: =ROUND((0/100)*ROUND(Source!R62, 2), 2) -> 0 | AC112: 0
C113: ЗП | F113: =Source!AO61 -> 26.76 | G113: =Source!DG61 -> *1,1 | H113: =Source!AV62 -> 1.047 | I113: =Source!S61 -> 61.64 | J113: =IF(Source!BA62<> 0, Source!BA62, 1) -> 54.99 | K113: =Source!S62 -> 3389.58
C114: ЭМ | F114: =Source!AM61 -> 52.68 | G114: =Source!DE61 -> *1,1 | H114: =Source!AV62 -> 1.047 | I114: =Source!Q61 -> 121.34 | J114: =IF(Source!BB62<> 0, Source!BB62, 1) -> 18.57 | K114: =Source!Q62 -> 2253.28
C115: в т.ч. ЗПМ | F115: =Source!AN61 -> 9.72 | G115: =Source!DF61 -> *1,1 | H115: =Source!AV62 -> 1.047 | I115: =Source!R61 -> 22.39 | J115: =IF(Source!BS62<> 0, Source!BS62, 1) -> 54.99 | K115: =Source!R62 -> 1231.23
C116: МР | F116: =Source!AL61 -> 6.11 | G116: =Source!DD61 | H116: =Source!AW62 -> 1 | I116: =Source!P61 -> 12.22 | J116: =IF(Source!BC62<> 0, Source!BC62, 1) -> 10.72 | K116: =Source!P62 -> 131
A117: 11,1 | B117: =Source!F63 -> 1.1-1-58 | C117: Болты строительные с гайками, оцинкованные, М10х100 мм | D117: =Source!H63 -> т | E117: =Source!I63 -> 0.0002 | F117: =Source!AK63 -> 24609.76 | H117: =Source!AW64 -> 1 | I117: =Source!O63 -> 4.92 | J117: =IF(Source!BC64<> 0, Source!BC64, 1) -> 5.15 | K117: =Source!O64 -> 25.34 | Q117: =Source!X63 -> 0 | R117: =Source!X64 -> 0 | S117: =Source!Y63 -> 0 | T117: =Source!Y64 -> 0 | U117: =ROUND((175/100)*ROUND(Source!R63, 2), 2) -> 0 | V117: =ROUND((0/100)*ROUND(Source!R64, 2), 2) -> 0 | AC117: 3
C118: НР от ФОТ | D118: % | E118: =Source!BZ62 -> 97 | I118: =SUM(Q112:Q117) -> 81.51 | J118: =Source!AT62 -> 97 | K118: =SUM(R112:R117) -> 4482.19
C119: СП от ФОТ | D119: % | E119: =Source!CA62 -> 51 | I119: =SUM(S112:S118) -> 42.86 | J119: =Source!AU62 -> 51 | K119: =SUM(T112:T118) -> 2356.61
C120: ЗТР | D120: чел-ч | E120: =Source!AQ61 -> 2.06 | G120: =Source!DI61 -> *1,1 | H120: =Source!AV62 -> 1.047 | I120: =Source!U61 -> 4.745004
C121: ВСЕГО работ по позиции: | H121: =I113+I114+I116+I118+I119+SUM(I117:I117)-SUMIF(AC117:AC117, 5, I117:I117)-SUMIF(AC117:AC117, 6, I117:I117) -> 324.49 | J121: =K113+K114+K116+K118+K119+SUM(K117:K117)-SUMIF(AC117:AC117, 5, K117:K117)-SUMIF(AC117:AC117, 6, K117:K117) -> 12638
...

Sheet Ведомость объемов работ
A1: =Source!B1 -> Smeta.RU (495) 974-1589
B4: =CONCATENATE("Ведомость объемов работ ", IF(Source!AN15<>"", Source!AN15," ")) -> Ведомость объемов работ
B5: =CONCATENATE(Source!F12, " ", Source!G12) -> 02-01-03 ЭОМ
A8: № п/п | B8: № в ЛСР | C8: Наименование работ и затрат | D8: Единица измерения | E8: Количество | F8: Ссылка на чертежи, спецификации | G8: Формула расчета, расчет объемов работ и расхода материалов | H8: Примечание
A9: 1 | B9: 2 | C9: 3 | D9: 4 | E9: 5 | F9: 6 | G9: 7 | H9: 8
A10: =CONCATENATE("Локальная смета: ", Source!G20) -> Локальная смета: Система электроснабжения
A11: =CONCATENATE("Раздел: ", Source!G24) -> Раздел: Щитовое оборудование
A12: 1 | B12: =Source!E29 -> 1 | C12: =Source!G29 -> Монтаж щитов и стеллажей с блоками резисторов (ящиками сопротивлений) высотой свыше 1700 мм, щита заводского изготовления однорядного или двухрядного открытого исполнения шириной 800 мм | D12: 1 м ширины по фронту | E12: =Source!I29 -> 1.2 | F12: =Source!U24 | G12: ="=0,6+"&"0,6" -> =0,6+0,6
A13: 2 | B13: =Source!E33 -> 2 | C13: =Source!G33 -> Вводная панель ВП1 | D13: ШТ | E13: =Source!I33 -> 1 | F13: =Source!U24 | G13: =Source!I33 -> 1
A14: 3 | B14: =Source!E35 -> 3 | C14: =Source!G35 -> Вводная панель ВП1 | D14: ШТ | E14: =Source!I35 -> 1 | F14: =Source!U24 | G14: =Source!I35 -> 1
A15: 4 | B15: =Source!E38 -> 4 | C15: =Source!G38 -> Монтаж щитов и стеллажей с блоками резисторов (ящиками сопротивлений) высотой свыше 1700 мм, щита заводского изготовления однорядного или двухрядного открытого исполнения шириной 800 мм | D15: 1 м ширины по фронту | E15: =Source!I38 -> 1.2 | F15: =Source!U24 | G15: ="=0,6+"&"0,6" -> =0,6+0,6
A16: 5 | B16: =Source!E42 -> 5 | C16: =Source!G42 -> Распределительная панель РП-1 | D16: ШТ | E16: =Source!I42 -> 1 | F16: =Source!U24 | G16: =Source!I42 -> 1
A17: 6 | B17: =Source!E44 -> 6 | C17: =Source!G44 -> Распределительная панель РП-2 | D17: ШТ | E17: =Source!I44 -> 1 | F17: =Source!U24 | G17: =Source!I44 -> 1
A18: 7 | B18: =Source!E47 -> 7 | C18: =Source!G47 -> Монтаж щитов и стеллажей с блоками резисторов (ящиками сопротивлений) высотой свыше 1700 мм, щита заводского изготовления однорядного или двухрядного открытого исполнения шириной 800 мм | D18: 1 м ширины по фронту | E18: =Source!I47 -> 0.6 | F18: =Source!U24 | G18: =Source!I47 -> 0.6
A19: 8 | B19: =Source!E51 -> 8 | C19: =Source!G51 -> Панель ЩГП с АВР | D19: ШТ | E19: =Source!I51 -> 1 | F19: =Source!U24 | G19: =Source!I51 -> 1
A20: 9 | B20: =Source!E54 -> 9 | C20: =Source!G54 -> Монтаж щитов и стеллажей с блоками резисторов (ящиками сопротивлений) высотой свыше 1700 мм, щита заводского изготовления однорядного или двухрядного открытого исполнения шириной 800 мм | D20: 1 м ширины по фронту | E20: =Source!I54 -> 0.6 | F20: =Source!U24 | G20: =Source!I54 -> 0.6
A21: 10 | B21: =Source!E58 -> 10 | C21: =Source!G58 -> Панель ПЭСПЗ с АВР | D21: ШТ | E21: =Source!I58 -> 1 | F21: =Source!U24 | G21: =Source!I58 -> 1
A22: 11 | B22: =Source!E61 -> 11 | C22: =Source!G61 -> Монтаж пультов и шкафов управления, пульта управления напольного, высотой до 1200 мм, глубиной и шириной по фронту до 700х1000 мм | D22: 1 ШТ. | E22: =Source!I61 -> 2 | F22: =Source!U24 | G22: =Source!I61 -> 2
A23: 12 | B23: =Source!E65 -> 12 | C23: =Source!G65 -> УКРМ 50-10 | D23: ШТ | E23: =Source!I65 -> 2 | F23: =Source!U24 | G23: =Source!I65 -> 2
A24: 13 | B24: =Source!E68 -> 13 | C24: =Source!G68 -> Монтаж пультов и шкафов управления, шкафа (пульта) управления навесного, высотой, шириной, глубиной до 600х600х350 мм | D24: 1 ШТ. | E24: =Source!I68 -> 60 | F24: =Source!U24 | G24: =Source!I68 -> 60
A25: 14 | B25: =Source!E72 -> 14 | C25: =Source!G72 -> ЩМТ-1 | D25: ШТ | E25: =Source!I72 -> 1 | F25: =Source!U24 | G25: =Source!I72 -> 1
A26: 15 | B26: =Source!E74 -> 15 | C26: =Source!G74 -> ЩО1.1 | D26: ШТ | E26: =Source!I74 -> 1 | F26: =Source!U24 | G26: =Source!I74 -> 1
A27: 16 | B27: =Source!E76 -> 16 | C27: =Source!G76 -> ЩО1.2 | D27: ШТ | E27: =Source!I76 -> 1 | F27: =Source!U24 | G27: =Source!I76 -> 1
A28: 17 | B28: =Source!E78 -> 17 | C28: =Source!G78 -> ЩО1.3 | D28: ШТ | E28: =Source!I78 -> 1 | F28: =Source!U24 | G28: =Source!I78 -> 1
A29: 18 | B29: =Source!E80 -> 18 | C29: =Source!G80 -> ЩО1.4 | D29: ШТ | E29: =Source!I80 -> 1 | F29: =Source!U24 | G29: =Source!I80 -> 1
A30: 19 | B30: =Source!E82 -> 19 | C30: =Source!G82 -> ЩО2.1 | D30: ШТ | E30: =Source!I82 -> 1 | F30: =Source!U24 | G30: =Source!I82 -> 1
A31: 20 | B31: =Source!E84 -> 20 | C31: =Source!G84 -> ЩО2.2 | D31: ШТ | E31: =Source!I84 -> 1 | F31: =Source!U24 | G31: =Source!I84 -> 1
A32: 21 | B32: =Source!E86 -> 21 | C32: =Source!G86 -> ЩО2.3 | D32: ШТ | E32: =Source!I86 -> 1 | F32: =Source!U24 | G32: =Source!I86 -> 1
A33: 22 | B33: =Source!E88 -> 22 | C33: =Source!G88 -> ЩО2.4 | D33: ШТ | E33: =Source!I88 -> 1 | F33: =Source!U24 | G33: =Source!I88 -> 1
A34: 23 | B34: =Source!E90 -> 23 | C34: =Source!G90 -> ЩО3.1 | D34: ШТ | E34: =Source!I90 -> 1 | F34: =Source!U24 | G34: =Source!I90 -> 1
A35: 24 | B35: =Source!E92 -> 24 | C35: =Source!G92 -> ЩО3.2 | D35: ШТ | E35: =Source!I92 -> 1 | F35: =Source!U24 | G35: =Source!I92 -> 1
A36: 25 | B36: =Source!E94 -> 25 | C36: =Source!G94 -> ЩО3.3 | D36: ШТ | E36: =Source!I94 -> 1 | F36: =Source!U24 | G36: =Source!I94 -> 1
A37: 26 | B37: =Source!E96 -> 26 | C37: =Source!G96 -> ЩО3.4 | D37: ШТ | E37: =Source!I96 -> 1 | F37: =Source!U24 | G37: =Source!I96 -> 1
A38: 27 | B38: =Source!E98 -> 27 | C38: =Source!G98 -> ЩОА1.1 | D38: ШТ | E38: =Source!I98 -> 1 | F38: =Source!U24 | G38: =Source!I98 -> 1
A39: 28 | B39: =Source!E100 -> 28 | C39: =Source!G100 -> ЩОА1.2 | D39: ШТ | E39: =Source!I100 -> 1 | F39: =Source!U24 | G39: =Source!I100 -> 1
A40: 29 | B40: =Source!E102 -> 29 | C40: =Source!G102 -> ЩОА1.3 | D40: ШТ | E40: =Source!I102 -> 1 | F40: =Source!U24 | G40: =Source!I102 -> 1
A41: 30 | B41: =Source!E104 -> 30 | C41: =Source!G104 -> ЩОА1.4 | D41: ШТ | E41: =Source!I104 -> 1 | F41: =Source!U24 | G41: =Source!I104 -> 1
A42: 31 | B42: =Source!E106 -> 31 | C42: =Source!G106 -> ЩОА2.1 | D42: ШТ | E42: =Source!I106 -> 1 | F42: =Source!U24 | G42: =Source!I106 -> 1
A43: 32 | B43: =Source!E108 -> 32 | C43: =Source!G108 -> ЩОА2.2 | D43: ШТ | E43: =Source!I108 -> 1 | F43: =Source!U24 | G43: =Source!I108 -> 1
A44: 33 | B44: =Source!E110 -> 33 | C44: =Source!G110 -> ЩОА2.3 | D44: ШТ | E44: =Source!I110 -> 1 | F44: =Source!U24 | G44: =Source!I110 -> 1
A45: 34 | B45: =Source!E112 -> 34 | C45: =Source!G112 -> ЩОА2.4 | D45: ШТ | E45: =Source!I112 -> 1 | F45: =Source!U24 | G45: =Source!I112 -> 1
A46: 35 | B46: =Source!E114 -> 35 | C46: =Source!G114 -> ЩОА3.1 | D46: ШТ | E46: =Source!I114 -> 1 | F46: =Source!U24 | G46: =Source!I114 -> 1
A47: 36 | B47: =Source!E116 -> 36 | C47: =Source!G116 -> ЩОА3.2 | D47: ШТ | E47: =Source!I116 -> 1 | F47: =Source!U24 | G47: =Source!I116 -> 1
A48: 37 | B48: =Source!E118 -> 37 | C48: =Source!G118 -> ЩОА3.3 | D48: ШТ | E48: =Source!I118 -> 1 | F48: =Source!U24 | G48: =Source!I118 -> 1
A49: 38 | B49: =Source!E120 -> 38 | C49: =Source!G120 -> ЩОА3.4 | D49: ШТ | E49: =Source!I120 -> 1 | F49: =Source!U24 | G49: =Source!I120 -> 1
A50: 39 | B50: =Source!E122 -> 39 | C50: =Source!G122 -> ЩОАП | D50: ШТ | E50: =Source!I122 -> 1 | F50: =Source!U24 | G50: =Source!I122 -> 1
A51: 40 | B51: =Source!E124 -> 40 | C51: =Source!G124 -> ЩОП | D51: ШТ | E51: =Source!I124 -> 1 | F51: =Source!U24 | G51: =Source!I124 -> 1
A52: 41 | B52: =Source!E126 -> 41 | C52: =Source!G126 -> ЩПВ-1 | D52: ШТ | E52: =Source!I126 -> 1 | F52: =Source!U24 | G52: =Source!I126 -> 1
A53: 42 | B53: =Source!E128 -> 42 | C53: =Source!G128 -> ЩПВ-2 | D53: ШТ | E53: =Source!I128 -> 1 | F53: =Source!U24 | G53: =Source!I128 -> 1
A54: 43 | B54: =Source!E130 -> 43 | C54: =Source!G130 -> ЩСП | D54: ШТ | E54: =Source!I130 -> 1 | F54: =Source!U24 | G54: =Source!I130 -> 1
A55: 44 | B55: =Source!E132 -> 44 | C55: =Source!G132 -> ЩА-В1 | D55: ШТ | E55: =Source!I132 -> 1 | F55: =Source!U24 | G55: =Source!I132 -> 1
A56: 45 | B56: =Source!E134 -> 45 | C56: =Source!G134 -> ЩА-В2 | D56: ШТ | E56: =Source!I134 -> 1 | F56: =Source!U24 | G56: =Source!I134 -> 1
A57: 46 | B57: =Source!E136 -> 46 | C57: =Source!G136 -> ЩА-В3 | D57: ШТ | E57: =Source!I136 -> 1 | F57: =Source!U24 | G57: =Source!I136 -> 1
A58: 47 | B58: =Source!E138 -> 47 | C58: =Source!G138 -> ЩА-В4 | D58: ШТ | E58: =Source!I138 -> 1 | F58: =Source!U24 | G58: =Source!I138 -> 1
A59: 48 | B59: =Source!E140 -> 48 | C59: =Source!G140 -> ЩА-В5 | D59: ШТ | E59: =Source!I140 -> 1 | F59: =Source!U24 | G59: =Source!I140 -> 1
A60: 49 | B60: =Source!E142 -> 49 | C60: =Source!G142 -> ЩА-В6 | D60: ШТ | E60: =Source!I142 -> 1 | F60: =Source!U24 | G60: =Source!I142 -> 1
A61: 50 | B61: =Source!E144 -> 50 | C61: =Source!G144 -> ЩА-В7 | D61: ШТ | E61: =Source!I144 -> 1 | F61: =Source!U24 | G61: =Source!I144 -> 1
A62: 51 | B62: =Source!E146 -> 51 | C62: =Source!G146 -> ЩВК1 | D62: ШТ | E62: =Source!I146 -> 1 | F62: =Source!U24 | G62: =Source!I146 -> 1
A63: 52 | B63: =Source!E148 -> 52 | C63: =Source!G148 -> ЩВК2 | D63: ШТ | E63: =Source!I148 -> 1 | F63: =Source!U24 | G63: =Source!I148 -> 1
A64: 53 | B64: =Source!E150 -> 53 | C64: =Source!G150 -> ЩВК3 | D64: ШТ | E64: =Source!I150 -> 1 | F64: =Source!U24 | G64: =Source!I150 -> 1
A65: 54 | B65: =Source!E152 -> 54 | C65: =Source!G152 -> ЩМТ-2 | D65: ШТ | E65: =Source!I152 -> 1 | F65: =Source!U24 | G65: =Source!I152 -> 1
A66: 55 | B66: =Source!E154 -> 55 | C66: =Source!G154 -> ЩМТ-3 | D66: ШТ | E66: =Source!I154 -> 1 | F66: =Source!U24 | G66: =Source!I154 -> 1
A67: 56 | B67: =Source!E156 -> 56 | C67: =Source!G156 -> ЩСК1 | D67: ШТ | E67: =Source!I156 -> 1 | F67: =Source!U24 | G67: =Source!I156 -> 1
A68: 57 | B68: =Source!E158 -> 57 | C68: =Source!G158 -> ЩСК2 | D68: ШТ | E68: =Source!I158 -> 1 | F68: =Source!U24 | G68: =Source!I158 -> 1
A69: 58 | B69: =Source!E160 -> 58 | C69: =Source!G160 -> ЩГЦ | D69: ШТ | E69: =Source!I160 -> 1 | F69: =Source!U24 | G69: =Source!I160 -> 1
A70: 59 | B70: =Source!E162 -> 59 | C70: =Source!G162 -> ЩПБ-1 | D70: ШТ | E70: =Source!I162 -> 1 | F70: =Source!U24 | G70: =Source!I162 -> 1
A71: 60 | B71: =Source!E164 -> 60 | C71: =Source!G164 -> ЩПБ-2 | D71: ШТ | E71: =Source!I164 -> 1 | F71: =Source!U24 | G71: =Source!I164 -> 1
A72: 61 | B72: =Source!E166 -> 61 | C72: =Source!G166 -> ЩС1.1 | D72: ШТ | E72: =Source!I166 -> 1 | F72: =Source!U24 | G72: =Source!I166 -> 1
A73: 62 | B73: =Source!E168 -> 62 | C73: =Source!G168 -> ЩС1.2 | D73: ШТ | E73: =Source!I168 -> 1 | F73: =Source!U24 | G73: =Source!I168 -> 1
A74: 63 | B74: =Source!E170 -> 63 | C74: =Source!G170 -> ЩС1.3 | D74: ШТ | E74: =Source!I170 -> 1 | F74: =Source!U24 | G74: =Source!I170 -> 1
A75: 64 | B75: =Source!E172 -> 64 | C75: =Source!G172 -> ЩС1.4 | D75: ШТ | E75: =Source!I172 -> 1 | F75: =Source!U24 | G75: =Source!I172 -> 1
A76: 65 | B76: =Source!E174 -> 65 | C76: =Source!G174 -> ЩСК2.1 | D76: ШТ | E76: =Source!I174 -> 1 | F76: =Source!U24 | G76: =Source!I174 -> 1
A77: 66 | B77: =Source!E176 -> 66 | C77: =Source!G176 -> ЩСК2.2 | D77: ШТ | E77: =Source!I176 -> 1 | F77: =Source!U24 | G77: =Source!I176 -> 1
A78: 67 | B78: =Source!E178 -> 67 | C78: =Source!G178 -> ЩС2.3 | D78: ШТ | E78: =Source!I178 -> 1 | F78: =Source!U24 | G78: =Source!I178 -> 1
A79: 68 | B79: =Source!E180 -> 68 | C79: =Source!G180 -> ЩС2.4 | D79: ШТ | E79: =Source!I180 -> 1 | F79: =Source!U24 | G79: =Source!I180 -> 1
A80: 69 | B80: =Source!E182 -> 69 | C80: =Source!G182 -> ЩСК3.1 | D80: ШТ | E80: =Source!I182 -> 1 | F80: =Source!U24 | G80: =Source!I182 -> 1
A81: 70 | B81: =Source!E184 -> 70 | C81: =Source!G184 -> ЩС3.3 | D81: ШТ | E81: =Source!I184 -> 1 | F81: =Source!U24 | G81: =Source!I184 -> 1
A82: 71 | B82: =Source!E186 -> 71 | C82: =Source!G186 -> ЩС3.3 | D82: ШТ | E82: =Source!I186 -> 1 | F82: =Source!U24 | G82: =Source!I186 -> 1
A83: 72 | B83: =Source!E188 -> 72 | C83: =Source!G188 -> ЩСК3.4 | D83: ШТ | E83: =Source!I188 -> 1 | F83: =Source!U24 | G83: =Source!I188 -> 1
A84: 73 | B84: =Source!E190 -> 73 | C84: =Source!G190 -> ЩСКС | D84: ШТ | E84: =Source!I190 -> 1 | F84: =Source!U24 | G84: =Source!I190 -> 1
A85: =CONCATENATE("Раздел: ", Source!G223) -> Раздел: Кабельная продукция
A86: 74 | B86: =Source!E227 -> 74 | C86: =Source!G227 -> Прокладка в коробах провода сечением до 6 мм2 | D86: 100 м | E86: =Source!I227 -> 225.5 | F86: =Source!U223 | G86: ="=(10000+"&"11600+"&"950)/"&"100" -> =(10000+11600+950)/100
A87: 75 | B87: =Source!E229 -> 75 | C87: =Source!G229 -> Кабель силовой, с медными жилами, с изоляцией и оболочкой из ПВХ пластиката пониженной пожарной опасности, не распространяющий горение, с пониженным дымо- и газовыделением и с низкой токсичностью продуктов горения, марка ВВГнг(А)-LSLTх, напряжение 1000 В, число жил и сечение 3х1,5 мм2 | D87: км | E87: =Source!I229 -> 10.2 | F87: =Source!U223 | G87: ="=(10000*"&"1,02)/"&"1000" -> =(10000*1,02)/1000
A88: 76 | B88: =Source!E231 -> 76 | C88: =Source!G231 -> Кабель силовой с медными жилами, огнестойкий, с изоляцией и оболочкой из ПВХ пластиката пониженной пожарной опасности, не распространяющий горение, с пониженным дымо- и газовыделением и с низкой токсичностью продуктов горения, марка ВВГнг(А)-FRLSLTх, напряжение 1000 В, число жил и сечение 3х1,5 мм2 | D88: км | E88: =Source!I231 -> 11.832 | F88: =Source!U223 | G88: ="=(11600*"&"1,02)/"&"1000" -> =(11600*1,02)/1000
A89: 77 | B89: =Source!E233 -> 77 | C89: =Source!G233 -> Провод ПуГВнг(A)-LSLTx 1x6 мм2 | D89: км | E89: =Source!I233 -> 0.9785 | F89: =Source!U223 | G89: ="=(950/"&"1000)*"&"1,03" -> =(950/1000)*1,03
A90: 78 | B90: =Source!E235 -> 78 | C90: =Source!G235 -> Прокладка в коробах провода сечением до 35 мм2 | D90: 100 м | E90: =Source!I235 -> 184.7 | F90: =Source!U223 | G90: ="=(2640+"&"2200+"&"11850+"&"1380+"&"400)/"&"100" -> =(2640+2200+11850+1380+400)/100
A91: 79 | B91: =Source!E237 -> 79 | C91: =Source!G237 -> Кабель силовой, с медными жилами, с изоляцией и оболочкой из ПВХ пластиката пониженной пожарной опасности, не распространяющий горение, с пониженным дымо- и газовыделением и с низкой токсичностью продуктов горения, марка ВВГнг(А)-LSLTх, напряжение 1000 В, число жил и сечение 5х4 мм2 | D91: км | E91: =Source!I237 -> 2.6928 | F91: =Source!U223 | G91: ="=(2640*"&"1,02)/"&"1000" -> =(2640*1,02)/1000
A92: 80 | B92: =Source!E239 -> 80 | C92: =Source!G239 -> Кабель силовой, с медными жилами, с изоляцией и оболочкой из ПВХ пластиката пониженной пожарной опасности, не распространяющий горение, с пониженным дымо- и газовыделением и с низкой токсичностью продуктов горения, марка ВВГнг(А)-LSLTх, напряжение 1000 В, число жил и сечение 5х2,5 мм2 | D92: км | E92: =Source!I239 -> 2.244 | F92: =Source!U223 | G92: ="=(2200*"&"1,02)/"&"1000" -> =(2200*1,02)/1000
A93: 81 | B93: =Source!E241 -> 81 | C93: =Source!G241 -> Кабель силовой, с медными жилами, с изоляцией и оболочкой из ПВХ пластиката пониженной пожарной опасности, не распространяющий горение, с пониженным дымо- и газовыделением и с низкой токсичностью продуктов горения, марка ВВГнг(А)-LSLTх, напряжение 1000 В, число жил и сечение 3х2,5 мм2 | D93: км | E93: =Source!I241 -> 12.087 | F93: =Source!U223 | G93: ="=(11850*"&"1,02)/"&"1000" -> =(11850*1,02)/1000
A94: 82 | B94: =Source!E243 -> 82 | C94: =Source!G243 -> Кабель силовой с медными жилами, огнестойкий, с изоляцией и оболочкой из ПВХ пластиката пониженной пожарной опасности, не распространяющий горение, с пониженным дымо- и газовыделением и с низкой токсичностью продуктов горения, марка ВВГнг(А)-FRLSLTх, напряжение 1000 В, число жил и сечение 5х4 мм2 | D94: км | E94: =Source!I243 -> 1.4076 | F94: =Source!U223 | G94: ="=(1380*"&"1,02)/"&"1000" -> =(1380*1,02)/1000
A95: 83 | B95: =Source!E245 -> 83 | C95: =Source!G245 -> Провод ПуГВнг(A)-LSLTx 1x25 мм2 | D95: км | E95: =Source!I245 -> 0.408 | F95: =Source!U223 | G95: ="=(400/"&"1000)*"&"1,02" -> =(400/1000)*1,02
A96: 84 | B96: =Source!E247 -> 84 | C96: =Source!G247 -> Прокладка в коробах провода сечением до 70 мм2 | D96: 100 м | E96: =Source!I247 -> 12 | F96: =Source!U223 | G96: ="=1200/"&"100" -> =1200/100
A97: 85 | B97: =Source!E249 -> 85 | C97: =Source!G249 -> Кабель силовой, с медными жилами, с изоляцией и оболочкой из ПВХ пластиката пониженной пожарной опасности, не распространяющий горение, с пониженным дымо- и газовыделением и с низкой токсичностью продуктов горения, марка ВВГнг(А)-LSLTх, напряжение 1000 В, число жил и сечение 5х10 мм2 | D97: км | E97: =Source!I249 -> 1.224 | F97: =Source!U223 | G97: ="=(1200*"&"1,02)/"&"1000" -> =(1200*1,02)/1000
A98: 86 | B98: =Source!E251 -> 86 | C98: =Source!G251 -> Прокладка в коробах провода сечением до 120 мм2 | D98: 100 м | E98: =Source!I251 -> 9 | F98: =Source!U223 | G98: ="=(650+"&"250)/"&"100" -> =(650+250)/100
A99: 87 | B99: =Source!E253 -> 87 | C99: =Source!G253 -> Кабель силовой, с медными жилами, с изоляцией и оболочкой из ПВХ пластиката пониженной пожарной опасности, не распространяющий горение, с пониженным дымо- и газовыделением и с низкой токсичностью продуктов горения, марка ВВГнг(А)-LSLTх, напряжение 1000 В, число жил и сечение 5х16 мм2 | D99: км | E99: =Source!I253 -> 0.663 | F99: =Source!U223 | G99: ="=(650*"&"1,02)/"&"1000" -> =(650*1,02)/1000
A100: 88 | B100: =Source!E255 -> 88 | C100: =Source!G255 -> Провод ПуГВнг(A)-LSLTx 1x95 мм2 | D100: км | E100: =Source!I255 -> 0.255 | F100: =Source!U223 | G100: ="=(250/"&"1000)*"&"1,02" -> =(250/1000)*1,02
A101: 89 | B101: =Source!E257 -> 89 | C101: =Source!G257 -> Прокладка в коробах провода сечением до 185 мм2 | D101: 100 м | E101: =Source!I257 -> 0.75 | F101: =Source!U223 | G101: ="=75/"&"100" -> =75/100
A102: 90 | B102: =Source!E259 -> 90 | C102: =Source!G259 -> Кабель силовой, с медными жилами, с изоляцией и оболочкой из ПВХ пластиката пониженной пожарной опасности, не распространяющий горение, с пониженным дымо- и газовыделением и с низкой токсичностью продуктов горения, марка ВВГнг(А)-LSLTх, напряжение 1000 В, число жил и сечение 5х25 мм2 | D102: км | E102: =Source!I259 -> 0.0765 | F102: =Source!U223 | G102: ="=(75*"&"1,02)/"&"1000" -> =(75*1,02)/1000
A103: 91 | B103: =Source!E261 -> 91 | C103: =Source!G261 -> Прокладка кабеля напряжением до 35 кВ по установленным конструкциям и лоткам с креплением по всей длине при массе 1 м до 9 кг | D103: 100 М КАБЕЛЯ | E103: =Source!I261 -> 0.7 | F103: =Source!U223 | G103: ="=70/"&"100" -> =70/100
A104: 92 | B104: =Source!E263 -> 92 | C104: =Source!G263 -> Кабель ВВГнг(А)-LSLTx 5x120 мм2 (1000 В) | D104: км | E104: =Source!I263 -> 0.0714 | F104: =Source!U223 | G104: ="=(70/"&"1000)*"&"1,02" -> =(70/1000)*1,02
...

Sheet Source
A1: 0 | B1: Smeta.RU (495) 974-1589 | D1: _PS_ | F1: 0 | G1: 0 | H1: 0 | I1: Smeta.RU | K1: 1 | L1: 74563 | M1: 10 | N1: 12 | O1: 0 | P1: 0 | Q1: 3
A4: 1 | B4: 1 | C4: -1 | G4: Капитальный ремонт здания Государственного бюджетного общеобразовательного учреждения города Москвы "Школа №236" по адресу: г. Москва, улица Клязьминская, дом 7, корпус 4 | EC4: 0
A12: 1 | B12: 915 | C12: 0 | D12: =ROW(A876) -> 876 | E12: 0 | G12: 02-01-03 ЭОМ | I12: 0 | J12: 2024-00272-01-0-ИОС1 | K12: 0 | L12: 0 | M12: 4098 | O12: 0 | P12: 0 | Q12: 0 | R12: 0 | S12: 0 | T12: 1 | V12: 0 | AB12: Соколова И.Н. | BB12: 0 | BH12: Сметные нормы списания | BI12: Коды ОКП для ТСН-2001 МГЭ Дополнение 80 | BJ12: 1 | BK12: 1 | BL12: 0 | BM12: 0 | BN12: 1 | BO12: 0 | BP12: 6 | BQ12: 2 | BR12: 1 | BS12: 1 | BT12: 0 | BU12: 0 | BV12: 0 | BW12: 0 | BX12: 0 | BZ12: Типовой расчет для ТСН-2001 МГЭ, Дополнение 80, строительство | CA12: Территориальные сметные нормативы для Москвы ТСН-2001 (МГЭ), дополнение 80 | CB12: Территориальные сметные нормативы для Москвы ТСН-2001 (МГЭ), дополнение 80 | CC12: Территориальные сметные нормативы для Москвы ТСН-2001 (МГЭ), дополнение 80 | CD12: Территориальные сметные нормативы для Москвы ТСН-2001 (МГЭ), дополнение 80 | CE12: Поправки для ТСН-2001 от 03.02.2026 г. доп.80 | CF12: 0 | CG12: 0 | CH12: 8200 | CK12: 80 | CQ12: Территориальные сметные нормативы для Москвы (ТСН-2001) | CR12: ТЕР | CS12: 41660 | CT12: 1 | CU12: 80 | CY12: 0 | EC12: 0
A15: 15 | B15: 1
A18: 52 | B18: =B876 -> 915 | C18: =C876 -> 1 | D18: =D876 -> 12 | E18: =E876 -> 0 | F18: =F876 | G18: =G876 -> 02-01-03 ЭОМ | O18: =O876 -> 6350730 | P18: =P876 -> 6264077.8 | Q18: =Q876 -> 17638.23 | R18: =R876 -> 5363.32 | S18: =S876 -> 69013.99 | T18: =T876 -> 0 | U18: =U876 -> 5619.3181 | V18: =V876 -> 0 | ... GX18: =GX876 -> 0
A20: 3 | B20: 1 | D20: =ROW(A846) -> 846 | F20: 02-01-03 | G20: Система электроснабжения | I20: 0 | J20: 2024-00272-01-0-ИОС1 | K20: -1 | L20: 02-01-03 | S20: 0 | T20: 0 | V20: 2 | BX20: 0 | CF20: 0 | CG20: 0
A22: 52 | B22: =B846 -> 1 | C22: =C846 -> 3 | D22: =D846 -> 20 | E22: =E846 -> 0 | F22: =F846 -> 02-01-03 | G22: =G846 -> Система электроснабжения | O22: =O846 -> 6350730 | P22: =P846 -> 6264077.8 | Q22: =Q846 -> 17638.23 | R22: =R846 -> 5363.32 | S22: =S846 -> 69013.99 | T22: =T846 -> 0 | U22: =U846 -> 5619.3181 | V22: =V846 -> 0 | ... GX22: =GX846 -> 0
A24: 4 | B24: 1 | D24: =ROW(A193) -> 193 | G24: Щитовое оборудование | I24: 0 | K24: -1 | S24: 0 | T24: 0 | V24: 2 | BX24: 0 | CJ24: 0
A26: 52 | B26: =B193 -> 1 | C26: =C193 -> 4 | D26: =D193 -> 24 | E26: =E193 -> 0 | F26: =F193 | G26: =G193 -> Щитовое оборудование | O26: =O193 -> 1099578 | P26: =P193 -> 1095773.9 | Q26: =Q193 -> 1560.4 | R26: =R193 -> 268.99 | S26: =S193 -> 2243.67 | T26: =T193 -> 0 | U26: =U193 -> 172.71815 | V26: =V193 -> 0 | ... GX26: =GX193 -> 0
A28: 19 | B28: 1 | G28: Вводная панель | AA28: 1 | IK28: 0
A29: 17 | B29: 1 | C29: =ROW(SmtRes!A8) -> 8 | D29: =ROW(EtalonRes!A9) -> 9 | E29: 1 | F29: 4.8-238-3 | G29: Монтаж щитов и стеллажей с блоками резисторов (ящиками сопротивлений) высотой свыше 1700 мм, щита заводского изготовления однорядного или двухрядного открытого исполнения шириной 800 мм | H29: 1 м ширины по фронту | I29: =ROUND(0.6+0.6,9) -> 1.2 | J29: 0 | K29: =ROUND(0.6+0.6,9) -> 1.2 | O29: =ROUND(CP29,2) -> 217.77 | P29: =ROUND((ROUND((AC29*AW29*I29),2)*BC29),2) -> 28.39 | Q29: =(ROUND((ROUND((((ET29*1.1))*AV29*I29),2)*BB29),2)+ROUND((ROUND(((AE29-((EU29*1.1)))*AV29*I29),2)*BS29),2)) -> 78.43 | R29: =ROUND((ROUND((AE29*AV29*I29),2)*BS29),2) -> 9.41 | S29: =ROUND((ROUND((AF29*AV29*I29),2)*BA29),2) -> 110.95 | T29: =ROUND(CU29*I29,2) -> 0 | U29: =CV29*I29 -> 8.5410072 | V29: =CW29*I29 -> 0 | W29: =ROUND(CX29*I29,2) -> 0 | X29: =ROUND(CY29,2) -> 116.75 | Y29: =ROUND(CZ29,2) -> 61.38 | AA29: 60252778 | AB29: =ROUND((AC29+AD29+AF29),6) -> 174.393 | AC29: =ROUND((ES29),6) -> 23.66 | AD29: =ROUND(((((ET29*1.1))-((EU29*1.1)))+AE29),6) -> 62.425 | AE29: =ROUND(((EU29*1.1)),6) -> 7.491 | AF29: =ROUND(((EV29*1.1)),6) -> 88.308 | AG29: =ROUND((AP29),6) -> 0 | AH29: =((EW29*1.1)) -> 6.798 | AI29: =((EX29*1.1)) -> 0 | AJ29: =(AS29) -> 0 | AK29: 160.69 | AL29: 23.66 | AM29: 56.75 | AN29: 6.81 | AO29: 80.28 | AP29: 0 | AQ29: 6.18 | AR29: 0 | AS29: 0 | AT29: 97 | AU29: 51 | AV29: 1.047 | AW29: 1 | AZ29: 1 | BA29: 1 | BB29: 1 | BC29: 1 | BH29: 0 | BI29: 2 | BJ29: ТСН-2001.4 Доп. 79, Сб. 8, т. 238, поз. 3 | BM29: 67 | BN29: 59540665 | BO29: 4.8-238-3 | BP29: 1 | BQ29: 40 | BR29: 0 | BS29: 1 | BT29: 1 | BU29: 1 | BV29: 1 | BW29: 1 | BX29: 1 | BZ29: 97 | CA29: 51 | CE29: 30 | CF29: 0 | CG29: 0 | CM29: 0 | CN29: Поправка: О.П. п.3.4.30.в Наименование: При применении территориальных сметных нормативов для города Москвы затраты, учитывающие напряженные и стесненные условия производства работ (стесненность, сложность складирования и транспортной логистики и т.п.), исчисляются с применением коэффициентов к затратам труда и заработной плате рабочих, машинистов, времени эксплуатации машин и механизмов, стоимости эксплуатации машин в размере: для объектов, расположенных за пределами Третьего транспортного кольца города Москвы, но в пределах Московской кольцевой автомобильной дороги | CO29: 0 | CP29: =(P29+Q29+S29) -> 217.77 | CQ29: =ROUND((ROUND((AC29*AW29*1),2)*BC29),2) -> 23.66 | CR29: =(ROUND((ROUND((((ET29*1.1))*AV29*1),2)*BB29),2)+ROUND((ROUND(((AE29-((EU29*1.1)))*AV29*1),2)*BS29),2)) -> 65.36 | CS29: =ROUND((ROUND((AE29*AV29*1),2)*BS29),2) -> 7.84 | CT29: =ROUND((ROUND((AF29*AV29*1),2)*BA29),2) -> 92.46 | CU29: =AG29 -> 0 | CV29: =(AH29*AV29) -> 7.117506 | CW29: =AI29 -> 0 | CX29: =AJ29 -> 0 | CY29: =(((S29+R29)*AT29)/100) -> 116.7492 | CZ29: =(((S29+R29)*AU29)/100) -> 61.3836 | DB29: 1 | DE29: *1,1 | DF29: *1,1 | DG29: *1,1 | DI29: *1,1 | DJ29: *1,1 | DN29: 0 | DO29: 0 | DP29: 1 | DQ29: 1 | DU29: 1013 | DV29: 1 м ширины по фронту | DW29: 1 м ширины по фронту | DX29: 1 | EE29: 59540733 | EF29: 40 | EG29: Монтаж оборудования | EH29: 0 | EJ29: 2 | EK29: 67 | EL29: ТСН-2001.4-8. Электротехнические установки | EM29: ТСН-2001.4-8-1 | EO29: Поправка: О.П. п.3.4.30.в | EQ29: 0 | ER29: 160.69 | ES29: 23.66 | ET29: 56.75 | EU29: 6.81 | EV29: 80.28 | EW29: 6.18 | EX29: 0 | EY29: 0 | FQ29: 0 | FR29: 0 | FS29: 0 | FX29: 97 | FY29: 51 | GD29: 1 | GF29: 373468362 | GG29: 2 | GH29: 1 | GI29: 2 | GJ29: 0 | GK29: 0 | GL29: =ROUND(IF(AND(BH29=3,BI29=3,FS29<>0),P29,0),2) -> 0 | GM29: =ROUND(O29+X29+Y29,2)+GX29 -> 395.9 | GN29: =IF(OR(BI29=0,BI29=1),GM29-GX29,0) -> 0 | GO29: =IF(BI29=2,GM29-GX29,0) -> 395.9 | GP29: =IF(BI29=4,GM29-GX29,0) -> 0 | GR29: 0 | GS29: 3 | GT29: 0 | GV29: =ROUND((GT29),6) -> 0 | GW29: 1 | GX29: =ROUND(HC29*I29,2) -> 0 | HA29: 0 | HB29: 0 | HC29: =GV29*GW29 -> 0 | HS29: 0 | IK29: 0
A30: 17 | B30: 1 | C30: =ROW(SmtRes!A16) -> 16 | D30: =ROW(EtalonRes!A18) -> 18 | E30: 1 | F30: 4.8-238-3 | G30: Монтаж щитов и стеллажей с блоками резисторов (ящиками сопротивлений) высотой свыше 1700 мм, щита заводского изготовления однорядного или двухрядного открытого исполнения шириной 800 мм | H30: 1 м ширины по фронту | I30: =ROUND(0.6+0.6,9) -> 1.2 | J30: 0 | K30: =ROUND(0.6+0.6,9) -> 1.2 | O30: =ROUND(CP30,2) -> 7527.67 | P30: =ROUND((ROUND((AC30*AW30*I30),2)*BC30),2) -> 226.55 | Q30: =(ROUND((ROUND((((ET30*1.1))*AV30*I30),2)*BB30),2)+ROUND((ROUND(((AE30-((EU30*1.1)))*AV30*I30),2)*BS30),2)) -> 1199.98 | R30: =ROUND((ROUND((AE30*AV30*I30),2)*BS30),2) -> 517.46 | S30: =ROUND((ROUND((AF30*AV30*I30),2)*BA30),2) -> 6101.14 | T30: =ROUND(CU30*I30,2) -> 0 | U30: =CV30*I30 -> 8.5410072 | V30: =CW30*I30 -> 0 | W30: =ROUND(CX30*I30,2) -> 0 | X30: =ROUND(CY30,2) -> 6420.04 | Y30: =ROUND(CZ30,2) -> 3375.49 | AA30: 60252775 | AB30: =ROUND((AC30+AD30+AF30),6) -> 174.393 | AC30: =ROUND((ES30),6) -> 23.66 | AD30: =ROUND(((((ET30*1.1))-((EU30*1.1)))+AE30),6) -> 62.425 | AE30: =ROUND(((EU30*1.1)),6) -> 7.491 | AF30: =ROUND(((EV30*1.1)),6) -> 88.308 | AG30: =ROUND((AP30),6) -> 0 | AH30: =((EW30*1.1)) -> 6.798 | AI30: =((EX30*1.1)) -> 0 | AJ30: =(AS30) -> 0 | AK30: 160.69 | AL30: 23.66 | AM30: 56.75 | AN30: 6.81 | AO30: 80.28 | AP30: 0 | AQ30: 6.18 | AR30: 0 | AS30: 0 | AT30: 97 | AU30: 51 | AV30: 1.047 | AW30: 1 | AZ30: 1 | BA30: 54.99 | BB30: 15.3 | BC30: 7.98 | BH30: 0 | BI30: 2 | BJ30: ТСН-2001.4 Доп. 79, Сб. 8, т. 238, поз. 3 | BM30: 67 | BN30: 59540665 | BO30: 4.8-238-3 | BP30: 1 | BQ30: 40 | BR30: 0 | BS30: 54.99 | BT30: 1 | BU30: 1 | BV30: 1 | BW30: 1 | BX30: 1 | BZ30: 97 | CA30: 51 | CE30: 30 | CF30: 0 | CG30: 0 | CM30: 0 | CN30: Поправка: О.П. п.3.4.30.в Наименование: При применении территориальных сметных нормативов для города Москвы затраты, учитывающие напряженные и стесненные условия производства работ (стесненность, сложность складирования и транспортной логистики и т.п.), исчисляются с применением коэффициентов к затратам труда и заработной плате рабочих, машинистов, времени эксплуатации машин и механизмов, стоимости эксплуатации машин в размере: для объектов, расположенных за пределами Третьего транспортного кольца города Москвы, но в пределах Московской кольцевой автомобильной дороги | CO30: 0 | CP30: =(P30+Q30+S30) -> 7527.67 | CQ30: =ROUND((ROUND((AC30*AW30*1),2)*BC30),2) -> 188.81 | CR30: =(ROUND((ROUND((((ET30*1.1))*AV30*1),2)*BB30),2)+ROUND((ROUND(((AE30-((EU30*1.1)))*AV30*1),2)*BS30),2)) -> 1000.01 | CS30: =ROUND((ROUND((AE30*AV30*1),2)*BS30),2) -> 431.12 | CT30: =ROUND((ROUND((AF30*AV30*1),2)*BA30),2) -> 5084.38 | CU30: =AG30 -> 0 | CV30: =(AH30*AV30) -> 7.117506 | CW30: =AI30 -> 0 | CX30: =AJ30 -> 0 | CY30: =(((S30+R30)*AT30)/100) -> 6420.042 | CZ30: =(((S30+R30)*AU30)/100) -> 3375.486 | DB30: 2 | DE30: *1,1 | DF30: *1,1 | DG30: *1,1 | DI30: *1,1 | DJ30: *1,1 | DN30: 0 | DO30: 0 | DP30: 1 | DQ30: 1 | DU30: 1013 | DV30: 1 м ширины по фронту | DW30: 1 м ширины по фронту | DX30: 1 | EE30: 59540733 | EF30: 40 | EG30: Монтаж оборудования | EH30: 0 | EJ30: 2 | EK30: 67 | EL30: ТСН-2001.4-8. Электротехнические установки | EM30: ТСН-2001.4-8-1 | EO30: Поправка: О.П. п.3.4.30.в | EQ30: 0 | ER30: 160.69 | ES30: 23.66 | ET30: 56.75 | EU30: 6.81 | EV30: 80.28 | EW30: 6.18 | EX30: 0 | EY30: 0 | FQ30: 0 | FR30: 0 | FS30: 0 | FX30: 97 | FY30: 51 | GD30: 1 | GF30: 373468362 | GG30: 2 | GH30: 1 | GI30: 2 | GJ30: 0 | GK30: 0 | GL30: =ROUND(IF(AND(BH30=3,BI30=3,FS30<>0),P30,0),2) -> 0 | GM30: =ROUND(O30+X30+Y30,2)+GX30 -> 17323.2 | GN30: =IF(OR(BI30=0,BI30=1),GM30-GX30,0) -> 0 | GO30: =IF(BI30=2,GM30-GX30,0) -> 17323.2 | GP30: =IF(BI30=4,GM30-GX30,0) -> 0 | GR30: 0 | GS30: 3 | GT30: 0 | GV30: =ROUND((GT30),6) -> 0 | GW30: 1 | GX30: =ROUND(HC30*I30,2) -> 0 | HA30: 0 | HB30: 0 | HC30: =GV30*GW30 -> 0 | HS30: 0 | IK30: 0
A31: 18 | B31: 1 | C31: 7 | E31: 1,1 | F31: 1.1-1-58 | G31: Болты строительные с гайками, оцинкованные, М10х100 мм | H31: т | I31: =I29*J31 -> 0.000612 | J31: 0.00051 | K31: 0.00051 | O31: =ROUND(CP31,2) -> 15.06 | P31: =ROUND((ROUND((AC31*AW31*I31),2)*BC31),2) -> 15.06 | Q31: =(ROUND((ROUND(((ET31)*AV31*I31),2)*BB31),2)+ROUND((ROUND(((AE31-(EU31))*AV31*I31),2)*BS31),2)) -> 0 | R31: =ROUND((ROUND((AE31*AV31*I31),2)*BS31),2) -> 0 | S31: =ROUND((ROUND((AF31*AV31*I31),2)*BA31),2) -> 0 | T31: =ROUND(CU31*I31,2) -> 0 | U31: =CV31*I31 -> 0 | V31: =CW31*I31 -> 0 | W31: =ROUND(CX31*I31,2) -> 0 | X31: =ROUND(CY31,2) -> 0 | Y31: =ROUND(CZ31,2) -> 0 | AA31: 60252778 | AB31: =ROUND((AC31+AD31+AF31),6) -> 24609.76 | AC31: =ROUND((ES31),6) -> 24609.76 | AD31: =ROUND((((ET31)-(EU31))+AE31),6) -> 0 | AE31: =ROUND((EU31),6) -> 0 | AF31: =ROUND((EV31),6) -> 0 | AG31: =ROUND((AP31),6) -> 0 | AH31: =(EW31) -> 0 | AI31: =(EX31) -> 0 | AJ31: =(AS31) -> 0 | AK31: 24609.76 | AL31: 24609.76 | AM31: 0 | AN31: 0 | AO31: 0 | AP31: 0 | AQ31: 0 | AR31: 0 | AS31: 0 | AT31: 97 | AU31: 51 | AV31: 1 | AW31: 1 | AZ31: 1 | BA31: 1 | BB31: 1 | BC31: 1 | BH31: 3 | BI31: 2 | BJ31: ТСН-2001.1 Доп. 79, Р. 1, о. 1, поз. 58 | BM31: 67 | BN31: 59540665 | BP31: 0 | BQ31: 40 | BR31: 0 | BS31: 1 | BT31: 1 | BU31: 1 | BV31: 1 | BW31: 1 | BX31: 1 | BZ31: 97 | CA31: 51 | CE31: 30 | CF31: 0 | CG31: 0 | CM31: 0 | CO31: 0 | CP31: =(P31+Q31+S31) -> 15.06 | CQ31: =ROUND((ROUND((AC31*AW31*1),2)*BC31),2) -> 24609.76 | CR31: =(ROUND((ROUND(((ET31)*AV31*1),2)*BB31),2)+ROUND((ROUND(((AE31-(EU31))*AV31*1),2)*BS31),2)) -> 0 | CS31: =ROUND((ROUND((AE31*AV31*1),2)*BS31),2) -> 0 | CT31: =ROUND((ROUND((AF31*AV31*1),2)*BA31),2) -> 0 | CU31: =AG31 -> 0 | CV31: =(AH31*AV31) -> 0 | CW31: =AI31 -> 0 | CX31: =AJ31 -> 0 | CY31: =(((S31+R31)*AT31)/100) -> 0 | CZ31: =(((S31+R31)*AU31)/100) -> 0 | DN31: 0 | DO31: 0 | DP31: 1 | DQ31: 1 | DU31: 1009 | DV31: т | DW31: т | DX31: 1000 | EE31: 59540733 | EF31: 40 | EG31: Монтаж оборудования | EH31: 0 | EJ31: 2 | EK31: 67 | EL31: ТСН-2001.4-8. Электротехнические установки | EM31: ТСН-2001.4-8-1 | EQ31: 0 | ER31: 24609.76 | ES31: 24609.76 | ET31: 0 | EU31: 0 | EV31: 0 | EW31: 0 | EX31: 0 | FQ31: 0 | FR31: 0 | FS31: 0 | FX31: 97 | FY31: 51 | GD31: 1 | GF31: -566361729 | GG31: 2 | GH31: 1 | GI31: -2 | GJ31: 0 | GK31: 0 | GL31: =ROUND(IF(AND(BH31=3,BI31=3,FS31<>0),P31,0),2) -> 0 | GM31: =ROUND(O31+X31+Y31,2)+GX31 -> 15.06 | GN31: =IF(OR(BI31=0,BI31=1),GM31-GX31,0) -> 0 | GO31: =IF(BI31=2,GM31-GX31,0) -> 15.06 | GP31: =IF(BI31=4,GM31-GX31,0) -> 0 | GR31: 0 | GS31: 3 | GT31: 0 | GV31: =ROUND((GT31),6) -> 0 | GW31: 1 | GX31: =ROUND(HC31*I31,2) -> 0 | HA31: 0 | HB31: 0 | HC31: =GV31*GW31 -> 0 | HS31: 0 | IK31: 0
A32: 18 | B32: 1 | C32: 15 | E32: 1,1 | F32: 1.1-1-58 | G32: Болты строительные с гайками, оцинкованные, М10х100 мм | H32: т | I32: =I30*J32 -> 0.000612 | J32: 0.00051 | K32: 0.00051 | O32: =ROUND(CP32,2) -> 77.56 | P32: =ROUND((ROUND((AC32*AW32*I32),2)*BC32),2) -> 77.56 | Q32: =(ROUND((ROUND(((ET32)*AV32*I32),2)*BB32),2)+ROUND((ROUND(((AE32-(EU32))*AV32*I32),2)*BS32),2)) -> 0 | R32: =ROUND((ROUND((AE32*AV32*I32),2)*BS32),2) -> 0 | S32: =ROUND((ROUND((AF32*AV32*I32),2)*BA32),2) -> 0 | T32: =ROUND(CU32*I32,2) -> 0 | U32: =CV32*I32 -> 0 | V32: =CW32*I32 -> 0 | W32: =ROUND(CX32*I32,2) -> 0 | X32: =ROUND(CY32,2) -> 0 | Y32: =ROUND(CZ32,2) -> 0 | AA32: 60252775 | AB32: =ROUND((AC32+AD32+AF32),6) -> 24609.76 | AC32: =ROUND((ES32),6) -> 24609.76 | AD32: =ROUND((((ET32)-(EU32))+AE32),6) -> 0 | AE32: =ROUND((EU32),6) -> 0 | AF32: =ROUND((EV32),6) -> 0 | AG32: =ROUND((AP32),6) -> 0 | AH32: =(EW32) -> 0 | AI32: =(EX32) -> 0 | AJ32: =(AS32) -> 0 | AK32: 24609.76 | AL32: 24609.76 | AM32: 0 | AN32: 0 | AO32: 0 | AP32: 0 | AQ32: 0 | AR32: 0 | AS32: 0 | AT32: 97 | AU32: 51 | AV32: 1 | AW32: 1 | AZ32: 1 | BA32: 1 | BB32: 1 | BC32: 5.15 | BH32: 3 | BI32: 2 | BJ32: ТСН-2001.1 Доп. 79, Р. 1, о. 1, поз. 58 | BM32: 67 | BN32: 59540665 | BO32: 1.1-1-58 | BP32: 1 | BQ32: 40 | BR32: 0 | BS32: 1 | BT32: 1 | BU32: 1 | BV32: 1 | BW32: 1 | BX32: 1 | BZ32: 97 | CA32: 51 | CE32: 30 | CF32: 0 | CG32: 0 | CM32: 0 | CO32: 0 | CP32: =(P32+Q32+S32) -> 77.56 | CQ32: =ROUND((ROUND((AC32*AW32*1),2)*BC32),2) -> 126740.26 | CR32: =(ROUND((ROUND(((ET32)*AV32*1),2)*BB32),2)+ROUND((ROUND(((AE32-(EU32))*AV32*1),2)*BS32),2)) -> 0 | CS32: =ROUND((ROUND((AE32*AV32*1),2)*BS32),2) -> 0 | CT32: =ROUND((ROUND((AF32*AV32*1),2)*BA32),2) -> 0 | CU32: =AG32 -> 0 | CV32: =(AH32*AV32) -> 0 | CW32: =AI32 -> 0 | CX32: =AJ32 -> 0 | CY32: =(((S32+R32)*AT32)/100) -> 0 | CZ32: =(((S32+R32)*AU32)/100) -> 0 | DN32: 0 | DO32: 0 | DP32: 1 | DQ32: 1 | DU32: 1009 | DV32: т | DW32: т | DX32: 1000 | EE32: 59540733 | EF32: 40 | EG32: Монтаж оборудования | EH32: 0 | EJ32: 2 | EK32: 67 | EL32: ТСН-2001.4-8. Электротехнические установки | EM32: ТСН-2001.4-8-1 | EQ32: 0 | ER32: 24609.76 | ES32: 24609.76 | ET32: 0 | EU32: 0 | EV32: 0 | EW32: 0 | EX32: 0 | FQ32: 0 | FR32: 0 | FS32: 0 | FX32: 97 | FY32: 51 | GD32: 1 | GF32: -566361729 | GG32: 2 | GH32: 1 | GI32: 2 | GJ32: 0 | GK32: 0 | GL32: =ROUND(IF(AND(BH32=3,BI32=3,FS32<>0),P32,0),2) -> 0 | GM32: =ROUND(O32+X32+Y32,2)+GX32 -> 77.56 | GN32: =IF(OR(BI32=0,BI32=1),GM32-GX32,0) -> 0 | GO32: =IF(BI32=2,GM32-GX32,0) -> 77.56 | GP32: =IF(BI32=4,GM32-GX32,0) -> 0 | GR32: 0 | GS32: 3 | GT32: 0 | GV32: =ROUND((GT32),6) -> 0 | GW32: 1 | GX32: =ROUND(HC32*I32,2) -> 0 | HA32: 0 | HB32: 0 | HC32: =GV32*GW32 -> 0 | HS32: 0 | IK32: 0
A33: 17 | B33: 1 | E33: 2 | F33: КА-1 | G33: Вводная панель ВП1 | H33: ШТ | I33: 1 | J33: 0 | K33: 1 | O33: =ROUND(CP33,2) -> 60887.82 | P33: =ROUND((ROUND((AC33*I33),2)*BC33),2) -> 60887.82 | Q33: =(ROUND((ROUND(((ET33)*AV33*I33),2)*BB33),2)+ROUND((ROUND(((AE33-(EU33))*AV33*I33),2)*BS33),2)) -> 0 | R33: =ROUND((ROUND((AE33*AV33*I33),2)*BS33),2) -> 0 | S33: =ROUND((ROUND((AF33*AV33*I33),2)*BA33),2) -> 0 | T33: =ROUND(CU33*I33,2) -> 0 | U33: =CV33*I33 -> 0 | V33: =CW33*I33 -> 0 | W33: =ROUND(CX33*I33,2) -> 0 | X33: =ROUND(CY33,2) -> 0 | Y33: =ROUND(CZ33,2) -> 0 | AA33: 60252778 | AB33: =ROUND((AC33+AD33+AF33),6) -> 60887.82 | AC33: =ROUND((ES33),6) -> 60887.82 | AD33: =ROUND((((ET33)-(EU33))+AE33),6) -> 0 | AE33: =ROUND((EU33),6) -> 0 | AF33: =ROUND((EV33),6) -> 0 | AG33: =ROUND((AP33),6) -> 0 | AH33: =(EW33) -> 0 | AI33: =(EX33) -> 0 | AJ33: =(AS33) -> 0 | AK33: 60887.82 | AL33: 60887.82 | AM33: 0 | AN33: 0 | AO33: 0 | AP33: 0 | AQ33: 0 | AR33: 0 | AS33: 0 | AT33: 0 | AU33: 0 | AV33: 1 | AW33: 1 | AZ33: 1 | BA33: 1 | BB33: 1 | BC33: 1 | BH33: 3 | BI33: 3 | BM33: 746 | BN33: 0 | BP33: 0 | BQ33: 130 | BR33: 0 | BS33: 1 | BT33: 1 | BU33: 1 | BV33: 1 | BW33: 1 | BX33: 1 | BZ33: 0 | CA33: 0 | CE33: 30 | CF33: 0 | CG33: 0 | CM33: 0 | CO33: 0 | CP33: =(P33+Q33+S33) -> 60887.82 | CQ33: =ROUND((ROUND((AC33*1),2)*BC33),2) -> 60887.82 | CR33: =(ROUND((ROUND(((ET33)*AV33*1),2)*BB33),2)+ROUND((ROUND(((AE33-(EU33))*AV33*1),2)*BS33),2)) -> 0 | CS33: =ROUND((ROUND((AE33*AV33*1),2)*BS33),2) -> 0 | CT33: =ROUND((ROUND((AF33*AV33*1),2)*BA33),2) -> 0 | CU33: =AG33 -> 0 | CV33: =(AH33*AV33) -> 0 | CW33: =AI33 -> 0 | CX33: =AJ33 -> 0 | CY33: =(((S33+R33)*AT33)/100) -> 0 | CZ33: =(((S33+R33)*AU33)/100) -> 0 | DN33: 0 | DO33: 0 | DP33: 1 | DQ33: 1 | DU33: 1013 | DV33: ШТ | DW33: ШТ | DX33: 1 | EE33: 59540854 | EF33: 130 | EG33: Сметная стоимость оборудования | EH33: 0 | EJ33: 3 | EK33: 746 | EL33: ТСН-2001.13. Сметная стоимость оборудования | EM33: ТСН-2001.13 | EQ33: 0 | ER33: 0 | ES33: 60887.82 | ET33: 0 | EU33: 0 | EV33: 0 | EW33: 0 | EX33: 0 | EY33: 0 | FQ33: 0 | FR33: =P33 -> 60887.82 | FS33: 0 | FX33: 0 | FY33: 0 | GA33: [536 936,24 / 1,2 / 7,66] + 3% Трансп + 1,2% Заг.скл | GD33: 1 | GF33: 1316245378 | GG33: 2 | GH33: 4 | GI33: -2 | GJ33: 0 | GK33: 0 | GL33: =ROUND(IF(AND(BH33=3,BI33=3,FS33<>0),P33,0),2) -> 0 | GM33: =ROUND(O33+X33+Y33,2)+GX33 -> 60887.82 | GN33: =IF(OR(BI33=0,BI33=1),GM33-GX33,0) -> 0 | GO33: =IF(BI33=2,GM33-GX33,0) -> 0 | GP33: =IF(BI33=4,GM33-GX33,0) -> 0 | GR33: 0 | GS33: 2 | GT33: 0 | GV33: =ROUND((GT33),6) -> 0 | GW33: 1 | GX33: =ROUND(HC33*I33,2) -> 0 | HA33: 0 | HB33: 0 | HC33: =GV33*GW33 -> 0 | HE33: 3 | HF33: 1,2 | HS33: 0 | IK33: 0
A34: 17 | B34: 1 | E34: 2 | F34: КА-1 | G34: Вводная панель ВП1 | H34: ШТ | I34: 1 | J34: 0 | K34: 1 | O34: =ROUND(CP34,2) -> 466400.7 | P34: =ROUND((ROUND((AC34*I34),2)*BC34),2) -> 466400.7 | Q34: =(ROUND((ROUND(((ET34)*AV34*I34),2)*BB34),2)+ROUND((ROUND(((AE34-(EU34))*AV34*I34),2)*BS34),2)) -> 0 | R34: =ROUND((ROUND((AE34*AV34*I34),2)*BS34),2) -> 0 | S34: =ROUND((ROUND((AF34*AV34*I34),2)*BA34),2) -> 0 | T34: =ROUND(CU34*I34,2) -> 0 | U34: =CV34*I34 -> 0 | V34: =CW34*I34 -> 0 | W34: =ROUND(CX34*I34,2) -> 0 | X34: =ROUND(CY34,2) -> 0 | Y34: =ROUND(CZ34,2) -> 0 | AA34: 60252775 | AB34: =ROUND((AC34+AD34+AF34),6) -> 60887.82 | AC34: =ROUND((ES34),6) -> 60887.82 | AD34: =ROUND((((ET34)-(EU34))+AE34),6) -> 0 | AE34: =ROUND((EU34),6) -> 0 | AF34: =ROUND((EV34),6) -> 0 | AG34: =ROUND((AP34),6) -> 0 | AH34: =(EW34) -> 0 | AI34: =(EX34) -> 0 | AJ34: =(AS34) -> 0 | AK34: 60887.82 | AL34: 60887.82 | AM34: 0 | AN34: 0 | AO34: 0 | AP34: 0 | AQ34: 0 | AR34: 0 | AS34: 0 | AT34: 0 | AU34: 0 | AV34: 1 | AW34: 1 | AZ34: 1 | BA34: 1 | BB34: 1 | BC34: 7.66 | BH34: 3 | BI34: 3 | BM34: 746 | BN34: 0 | BP34: 0 | BQ34: 130 | BR34: 0 | BS34: 1 | BT34: 1 | BU34: 1 | BV34: 1 | BW34: 1 | BX34: 1 | BZ34: 0 | CA34: 0 | CE34: 30 | CF34: 0 | CG34: 0 | CM34: 0 | CO34: 0 | CP34: =(P34+Q34+S34) -> 466400.7 | CQ34: =ROUND((ROUND((AC34*1),2)*BC34),2) -> 466400.7 | CR34: =(ROUND((ROUND(((ET34)*AV34*1),2)*BB34),2)+ROUND((ROUND(((AE34-(EU34))*AV34*1),2)*BS34),2)) -> 0 | CS34: =ROUND((ROUND((AE34*AV34*1),2)*BS34),2) -> 0 | CT34: =ROUND((ROUND((AF34*AV34*1),2)*BA34),2) -> 0 | CU34: =AG34 -> 0 | CV34: =(AH34*AV34) -> 0 | CW34: =AI34 -> 0 | CX34: =AJ34 -> 0 | CY34: =(((S34+R34)*AT34)/100) -> 0 | CZ34: =(((S34+R34)*AU34)/100) -> 0 | DN34: 0 | DO34: 0 | DP34: 1 | DQ34: 1 | DU34: 1013 | DV34: ШТ | DW34: ШТ | DX34: 1 | EE34: 59540854 | EF34: 130 | EG34: Сметная стоимость оборудования | EH34: 0 | EJ34: 3 | EK34: 746 | EL34: ТСН-2001.13. Сметная стоимость оборудования | EM34: ТСН-2001.13 | EQ34: 0 | ER34: 60887.82 | ES34: 60887.82 | ET34: 0 | EU34: 0 | EV34: 0 | EW34: 0 | EX34: 0 | EY34: 0 | EZ34: 5 | FC34: 1 | FD34: 18 | FF34: 536936.24 | FQ34: 0 | FR34: =P34 -> 466400.7 | FS34: 0 | FX34: 0 | FY34: 0 | GA34: [536 936,24 / 1,2 / 7,66] + 3% Трансп + 1,2% Заг.скл | GD34: 1 | GF34: 1316245378 | GG34: 2 | GH34: 3 | GI34: 5 | GJ34: 0 | GK34: 0 | GL34: =ROUND(IF(AND(BH34=3,BI34=3,FS34<>0),P34,0),2) -> 0 | GM34: =ROUND(O34+X34+Y34,2)+GX34 -> 466400.7 | GN34: =IF(OR(BI34=0,BI34=1),GM34-GX34,0) -> 0 | GO34: =IF(BI34=2,GM34-GX34,0) -> 0 | GP34: =IF(BI34=4,GM34-GX34,0) -> 0 | GR34: 1 | GS34: 1 | GT34: 0 | GV34: =ROUND((GT34),6) -> 0 | GW34: 1 | GX34: =ROUND(HC34*I34,2) -> 0 | HA34: 0 | HB34: 0 | HC34: =GV34*GW34 -> 0 | HE34: 3 | HF34: 1,2 | HS34: 0 | IK34: 0
A35: 17 | B35: 1 | E35: 3 | F35: КА-2 | G35: Вводная панель ВП1 | H35: ШТ | I35: 1 | J35: 0 | K35: 1 | O35: =ROUND(CP35,2) -> 44301.78 | P35: =ROUND((ROUND((AC35*I35),2)*BC35),2) -> 44301.78 | Q35: =(ROUND((ROUND(((ET35)*AV35*I35),2)*BB35),2)+ROUND((ROUND(((AE35-(EU35))*AV35*I35),2)*BS35),2)) -> 0 | R35: =ROUND((ROUND((AE35*AV35*I35),2)*BS35),2) -> 0 | S35: =ROUND((ROUND((AF35*AV35*I35),2)*BA35),2) -> 0 | T35: =ROUND(CU35*I35,2) -> 0 | U35: =CV35*I35 -> 0 | V35: =CW35*I35 -> 0 | W35: =ROUND(CX35*I35,2) -> 0 | X35: =ROUND(CY35,2) -> 0 | Y35: =ROUND(CZ35,2) -> 0 | AA35: 60252778 | AB35: =ROUND((AC35+AD35+AF35),6) -> 44301.78 | AC35: =ROUND((ES35),6) -> 44301.78 | AD35: =ROUND((((ET35)-(EU35))+AE35),6) -> 0 | AE35: =ROUND((EU35),6) -> 0 | AF35: =ROUND((EV35),6) -> 0 | AG35: =ROUND((AP35),6) -> 0 | AH35: =(EW35) -> 0 | AI35: =(EX35) -> 0 | AJ35: =(AS35) -> 0 | AK35: 44301.78 | AL35: 44301.78 | AM35: 0 | AN35: 0 | AO35: 0 | AP35: 0 | AQ35: 0 | AR35: 0 | AS35: 0 | AT35: 0 | AU35: 0 | AV35: 1 | AW35: 1 | AZ35: 1 | BA35: 1 | BB35: 1 | BC35: 1 | BH35: 3 | BI35: 3 | BM35: 746 | BN35: 0 | BP35: 0 | BQ35: 130 | BR35: 0 | BS35: 1 | BT35: 1 | BU35: 1 | BV35: 1 | BW35: 1 | BX35: 1 | BZ35: 0 | CA35: 0 | CE35: 30 | CF35: 0 | CG35: 0 | CM35: 0 | CO35: 0 | CP35: =(P35+Q35+S35) -> 44301.78 | CQ35: =ROUND((ROUND((AC35*1),2)*BC35),2) -> 44301.78 | CR35: =(ROUND((ROUND(((ET35)*AV35*1),2)*BB35),2)+ROUND((ROUND(((AE35-(EU35))*AV35*1),2)*BS35),2)) -> 0 | CS35: =ROUND((ROUND((AE35*AV35*1),2)*BS35),2) -> 0 | CT35: =ROUND((ROUND((AF35*AV35*1),2)*BA35),2) -> 0 | CU35: =AG35 -> 0 | CV35: =(AH35*AV35) -> 0 | CW35: =AI35 -> 0 | CX35: =AJ35 -> 0 | CY35: =(((S35+R35)*AT35)/100) -> 0 | CZ35: =(((S35+R35)*AU35)/100) -> 0 | DN35: 0 | DO35: 0 | DP35: 1 | DQ35: 1 | DU35: 1013 | DV35: ШТ | DW35: ШТ | DX35: 1 | EE35: 59540854 | EF35: 130 | EG35: Сметная стоимость оборудования | EH35: 0 | EJ35: 3 | EK35: 746 | EL35: ТСН-2001.13. Сметная стоимость оборудования | EM35: ТСН-2001.13 | EQ35: 0 | ER35: 0 | ES35: 44301.78 | ET35: 0 | EU35: 0 | EV35: 0 | EW35: 0 | EX35: 0 | EY35: 0 | FQ35: 0 | FR35: =P35 -> 44301.78 | FS35: 0 | FX35: 0 | FY35: 0 | GA35: [390 673,02 / 1,2 / 7,66] + 3% Трансп + 1,2% Заг.скл | GD35: 1 | GF35: -1527606560 | GG35: 2 | GH35: 4 | GI35: -2 | GJ35: 0 | GK35: 0 | GL35: =ROUND(IF(AND(BH35=3,BI35=3,FS35<>0),P35,0),2) -> 0 | GM35: =ROUND(O35+X35+Y35,2)+GX35 -> 44301.78 | GN35: =IF(OR(BI35=0,BI35=1),GM35-GX35,0) -> 0 | GO35: =IF(BI35=2,GM35-GX35,0) -> 0 | GP35: =IF(BI35=4,GM35-GX35,0) -> 0 | GR35: 0 | GS35: 2 | GT35: 0 | GV35: =ROUND((GT35),6) -> 0 | GW35: 1 | GX35: =ROUND(HC35*I35,2) -> 0 | HA35: 0 | HB35: 0 | HC35: =GV35*GW35 -> 0 | HE35: 3 | HF35: 1,2 | HS35: 0 | IK35: 0
A36: 17 | B36: 1 | E36: 3 | F36: КА-2 | G36: Вводная панель ВП1 | H36: ШТ | I36: 1 | J36: 0 | K36: 1 | O36: =ROUND(CP36,2) -> 339351.63 | P36: =ROUND((ROUND((AC36*I36),2)*BC36),2) -> 339351.63 | Q36: =(ROUND((ROUND(((ET36)*AV36*I36),2)*BB36),2)+ROUND((ROUND(((AE36-(EU36))*AV36*I36),2)*BS36),2)) -> 0 | R36: =ROUND((ROUND((AE36*AV36*I36),2)*BS36),2) -> 0 | S36: =ROUND((ROUND((AF36*AV36*I36),2)*BA36),2) -> 0 | T36: =ROUND(CU36*I36,2) -> 0 | U36: =CV36*I36 -> 0 | V36: =CW36*I36 -> 0 | W36: =ROUND(CX36*I36,2) -> 0 | X36: =ROUND(CY36,2) -> 0 | Y36: =ROUND(CZ36,2) -> 0 | AA36: 60252775 | AB36: =ROUND((AC36+AD36+AF36),6) -> 44301.78 | AC36: =ROUND((ES36),6) -> 44301.78 | AD36: =ROUND((((ET36)-(EU36))+AE36),6) -> 0 | AE36: =ROUND((EU36),6) -> 0 | AF36: =ROUND((EV36),6) -> 0 | AG36: =ROUND((AP36),6) -> 0 | AH36: =(EW36) -> 0 | AI36: =(EX36) -> 0 | AJ36: =(AS36) -> 0 | AK36: 44301.78 | AL36: 44301.78 | AM36: 0 | AN36: 0 | AO36: 0 | AP36: 0 | AQ36: 0 | AR36: 0 | AS36: 0 | AT36: 0 | AU36: 0 | AV36: 1 | AW36: 1 | AZ36: 1 | BA36: 1 | BB36: 1 | BC36: 7.66 | BH36: 3 | BI36: 3 | BM36: 746 | BN36: 0 | BP36: 0 | BQ36: 130 | BR36: 0 | BS36: 1 | BT36: 1 | BU36: 1 | BV36: 1 | BW36: 1 | BX36: 1 | BZ36: 0 | CA36: 0 | CE36: 30 | CF36: 0 | CG36: 0 | CM36: 0 | CO36: 0 | CP36: =(P36+Q36+S36) -> 339351.63 | CQ36: =ROUND((ROUND((AC36*1),2)*BC36),2) -> 339351.63 | CR36: =(ROUND((ROUND(((ET36)*AV36*1),2)*BB36),2)+ROUND((ROUND(((AE36-(EU36))*AV36*1),2)*BS36),2)) -> 0 | CS36: =ROUND((ROUND((AE36*AV36*1),2)*BS36),2) -> 0 | CT36: =ROUND((ROUND((AF36*AV36*1),2)*BA36),2) -> 0 | CU36: =AG36 -> 0 | CV36: =(AH36*AV36) -> 0 | CW36: =AI36 -> 0 | CX36: =AJ36 -> 0 | CY36: =(((S36+R36)*AT36)/100) -> 0 | CZ36: =(((S36+R36)*AU36)/100) -> 0 | DN36: 0 | DO36: 0 | DP36: 1 | DQ36: 1 | DU36: 1013 | DV36: ШТ | DW36: ШТ | DX36: 1 | EE36: 59540854 | EF36: 130 | EG36: Сметная стоимость оборудования | EH36: 0 | EJ36: 3 | EK36: 746 | EL36: ТСН-2001.13. Сметная стоимость оборудования | EM36: ТСН-2001.13 | EQ36: 0 | ER36: 44301.78 | ES36: 44301.78 | ET36: 0 | EU36: 0 | EV36: 0 | EW36: 0 | EX36: 0 | EY36: 0 | EZ36: 5 | FC36: 1 | FD36: 18 | FF36: 390673.02 | FQ36: 0 | FR36: =P36 -> 339351.63 | FS36: 0 | FX36: 0 | FY36: 0 | GA36: [390 673,02 / 1,2 / 7,66] + 3% Трансп + 1,2% Заг.скл | GD36: 1 | GF36: -1527606560 | GG36: 2 | GH36: 3 | GI36: 5 | GJ36: 0 | GK36: 0 | GL36: =ROUND(IF(AND(BH36=3,BI36=3,FS36<>0),P36,0),2) -> 0 | GM36: =ROUND(O36+X36+Y36,2)+GX36 -> 339351.63 | GN36: =IF(OR(BI36=0,BI36=1),GM36-GX36,0) -> 0 | GO36: =IF(BI36=2,GM36-GX36,0) -> 0 | GP36: =IF(BI36=4,GM36-GX36,0) -> 0 | GR36: 1 | GS36: 1 | GT36: 0 | GV36: =ROUND((GT36),6) -> 0 | GW36: 1 | GX36: =ROUND(HC36*I36,2) -> 0 | HA36: 0 | HB36: 0 | HC36: =GV36*GW36 -> 0 | HE36: 3 | HF36: 1,2 | HS36: 0 | IK36: 0
A37: 19 | B37: 1 | G37: Распределительная панель | AA37: 1 | IK37: 0
A38: 17 | B38: 1 | C38: =ROW(SmtRes!A24) -> 24 | D38: =ROW(EtalonRes!A27) -> 27 | E38: 4 | F38: 4.8-238-3 | G38: Монтаж щитов и стеллажей с блоками резисторов (ящиками сопротивлений) высотой свыше 1700 мм, щита заводского изготовления однорядного или двухрядного открытого исполнения шириной 800 мм | H38: 1 м ширины по фронту | I38: =ROUND(0.6+0.6,9) -> 1.2 | J38: 0 | K38: =ROUND(0.6+0.6,9) -> 1.2 | O38: =ROUND(CP38,2) -> 217.77 | P38: =ROUND((ROUND((AC38*AW38*I38),2)*BC38),2) -> 28.39 | Q38: =(ROUND((ROUND((((ET38*1.1))*AV38*I38),2)*BB38),2)+ROUND((ROUND(((AE38-((EU38*1.1)))*AV38*I38),2)*BS38),2)) -> 78.43 | R38: =ROUND((ROUND((AE38*AV38*I38),2)*BS38),2) -> 9.41 | S38: =ROUND((ROUND((AF38*AV38*I38),2)*BA38),2) -> 110.95 | T38: =ROUND(CU38*I38,2) -> 0 | U38: =CV38*I38 -> 8.5410072 | V38: =CW38*I38 -> 0 | W38: =ROUND(CX38*I38,2) -> 0 | X38: =ROUND(CY38,2) -> 116.75 | Y38: =ROUND(CZ38,2) -> 61.38 | AA38: 60252778 | AB38: =ROUND((AC38+AD38+AF38),6) -> 174.393 | AC38: =ROUND((ES38),6) -> 23.66 | AD38: =ROUND(((((ET38*1.1))-((EU38*1.1)))+AE38),6) -> 62.425 | AE38: =ROUND(((EU38*1.1)),6) -> 7.491 | AF38: =ROUND(((EV38*1.1)),6) -> 88.308 | AG38: =ROUND((AP38),6) -> 0 | AH38: =((EW38*1.1)) -> 6.798 | AI38: =((EX38*1.1)) -> 0 | AJ38: =(AS38) -> 0 | AK38: 160.69 | AL38: 23.66 | AM38: 56.75 | AN38: 6.81 | AO38: 80.28 | AP38: 0 | AQ38: 6.18 | AR38: 0 | AS38: 0 | AT38: 97 | AU38: 51 | AV38: 1.047 | AW38: 1 | AZ38: 1 | BA38: 1 | BB38: 1 | BC38: 1 | BH38: 0 | BI38: 2 | BJ38: ТСН-2001.4 Доп. 79, Сб. 8, т. 238, поз. 3 | BM38: 67 | BN38: 59540665 | BO38: 4.8-238-3 | BP38: 1 | BQ38: 40 | BR38: 0 | BS38: 1 | BT38: 1 | BU38: 1 | BV38: 1 | BW38: 1 | BX38: 1 | BZ38: 97 | CA38: 51 | CE38: 30 | CF38: 0 | CG38: 0 | CM38: 0 | CN38: Поправка: О.П. п.3.4.30.в Наименование: При применении территориальных сметных нормативов для города Москвы затраты, учитывающие напряженные и стесненные условия производства работ (стесненность, сложность складирования и транспортной логистики и т.п.), исчисляются с применением коэффициентов к затратам труда и заработной плате рабочих, машинистов, времени эксплуатации машин и механизмов, стоимости эксплуатации машин в размере: для объектов, расположенных за пределами Третьего транспортного кольца города Москвы, но в пределах Московской кольцевой автомобильной дороги | CO38: 0 | CP38: =(P38+Q38+S38) -> 217.77 | CQ38: =ROUND((ROUND((AC38*AW38*1),2)*BC38),2) -> 23.66 | CR38: =(ROUND((ROUND((((ET38*1.1))*AV38*1),2)*BB38),2)+ROUND((ROUND(((AE38-((EU38*1.1)))*AV38*1),2)*BS38),2)) -> 65.36 | CS38: =ROUND((ROUND((AE38*AV38*1),2)*BS38),2) -> 7.84 | CT38: =ROUND((ROUND((AF38*AV38*1),2)*BA38),2) -> 92.46 | CU38: =AG38 -> 0 | CV38: =(AH38*AV38) -> 7.117506 | CW38: =AI38 -> 0 | CX38: =AJ38 -> 0 | CY38: =(((S38+R38)*AT38)/100) -> 116.7492 | CZ38: =(((S38+R38)*AU38)/100) -> 61.3836 | DB38: 3 | DE38: *1,1 | DF38: *1,1 | DG38: *1,1 | DI38: *1,1 | DJ38: *1,1 | DN38: 0 | DO38: 0 | DP38: 1 | DQ38: 1 | DU38: 1013 | DV38: 1 м ширины по фронту | DW38: 1 м ширины по фронту | DX38: 1 | EE38: 59540733 | EF38: 40 | EG38: Монтаж оборудования | EH38: 0 | EJ38: 2 | EK38: 67 | EL38: ТСН-2001.4-8. Электротехнические установки | EM38: ТСН-2001.4-8-1 | EO38: Поправка: О.П. п.3.4.30.в | EQ38: 0 | ER38: 160.69 | ES38: 23.66 | ET38: 56.75 | EU38: 6.81 | EV38: 80.28 | EW38: 6.18 | EX38: 0 | EY38: 0 | FQ38: 0 | FR38: 0 | FS38: 0 | FX38: 97 | FY38: 51 | GD38: 1 | GF38: 373468362 | GG38: 2 | GH38: 1 | GI38: 2 | GJ38: 0 | GK38: 0 | GL38: =ROUND(IF(AND(BH38=3,BI38=3,FS38<>0),P38,0),2) -> 0 | GM38: =ROUND(O38+X38+Y38,2)+GX38 -> 395.9 | GN38: =IF(OR(BI38=0,BI38=1),GM38-GX38,0) -> 0 | GO38: =IF(BI38=2,GM38-GX38,0) -> 395.9 | GP38: =IF(BI38=4,GM38-GX38,0) -> 0 | GR38: 0 | GS38: 3 | GT38: 0 | GV38: =ROUND((GT38),6) -> 0 | GW38: 1 | GX38: =ROUND(HC38*I38,2) -> 0 | HA38: 0 | HB38: 0 | HC38: =GV38*GW38 -> 0 | HS38: 0 | IK38: 0
A39: 17 | B39: 1 | C39: =ROW(SmtRes!A32) -> 32 | D39: =ROW(EtalonRes!A36) -> 36 | E39: 4 | F39: 4.8-238-3 | G39: Монтаж щитов и стеллажей с блоками резисторов (ящиками сопротивлений) высотой свыше 1700 мм, щита заводского изготовления однорядного или двухрядного открытого исполнения шириной 800 мм | H39: 1 м ширины по фронту | I39: =ROUND(0.6+0.6,9) -> 1.2 | J39: 0 | K39: =ROUND(0.6+0.6,9) -> 1.2 | O39: =ROUND(CP39,2) -> 7527.67 | P39: =ROUND((ROUND((AC39*AW39*I39),2)*BC39),2) -> 226.55 | Q39: =(ROUND((ROUND((((ET39*1.1))*AV39*I39),2)*BB39),2)+ROUND((ROUND(((AE39-((EU39*1.1)))*AV39*I39),2)*BS39),2)) -> 1199.98 | R39: =ROUND((ROUND((AE39*AV39*I39),2)*BS39),2) -> 517.46 | S39: =ROUND((ROUND((AF39*AV39*I39),2)*BA39),2) -> 6101.14 | T39: =ROUND(CU39*I39,2) -> 0 | U39: =CV39*I39 -> 8.5410072 | V39: =CW39*I39 -> 0 | W39: =ROUND(CX39*I39,2) -> 0 | X39: =ROUND(CY39,2) -> 6420.04 | Y39: =ROUND(CZ39,2) -> 3375.49 | AA39: 60252775 | AB39: =ROUND((AC39+AD39+AF39),6) -> 174.393 | AC39: =ROUND((ES39),6) -> 23.66 | AD39: =ROUND(((((ET39*1.1))-((EU39*1.1)))+AE39),6) -> 62.425 | AE39: =ROUND(((EU39*1.1)),6) -> 7.491 | AF39: =ROUND(((EV39*1.1)),6) -> 88.308 | AG39: =ROUND((AP39),6) -> 0 | AH39: =((EW39*1.1)) -> 6.798 | AI39: =((EX39*1.1)) -> 0 | AJ39: =(AS39) -> 0 | AK39: 160.69 | AL39: 23.66 | AM39: 56.75 | AN39: 6.81 | AO39: 80.28 | AP39: 0 | AQ39: 6.18 | AR39: 0 | AS39: 0 | AT39: 97 | AU39: 51 | AV39: 1.047 | AW39: 1 | AZ39: 1 | BA39: 54.99 | BB39: 15.3 | BC39: 7.98 | BH39: 0 | BI39: 2 | BJ39: ТСН-2001.4 Доп. 79, Сб. 8, т. 238, поз. 3 | BM39: 67 | BN39: 59540665 | BO39: 4.8-238-3 | BP39: 1 | BQ39: 40 | BR39: 0 | BS39: 54.99 | BT39: 1 | BU39: 1 | BV39: 1 | BW39: 1 | BX39: 1 | BZ39: 97 | CA39: 51 | CE39: 30 | CF39: 0 | CG39: 0 | CM39: 0 | CN39: Поправка: О.П. п.3.4.30.в Наименование: При применении территориальных сметных нормативов для города Москвы затраты, учитывающие напряженные и стесненные условия производства работ (стесненность, сложность складирования и транспортной логистики и т.п.), исчисляются с применением коэффициентов к затратам труда и заработной плате рабочих, машинистов, времени эксплуатации машин и механизмов, стоимости эксплуатации машин в размере: для объектов, расположенных за пределами Третьего транспортного кольца города Москвы, но в пределах Московской кольцевой автомобильной дороги | CO39: 0 | CP39: =(P39+Q39+S39) -> 7527.67 | CQ39: =ROUND((ROUND((AC39*AW39*1),2)*BC39),2) -> 188.81 | CR39: =(ROUND((ROUND((((ET39*1.1))*AV39*1),2)*BB39),2)+ROUND((ROUND(((AE39-((EU39*1.1)))*AV39*1),2)*BS39),2)) -> 1000.01 | CS39: =ROUND((ROUND((AE39*AV39*1),2)*BS39),2) -> 431.12 | CT39: =ROUND((ROUND((AF39*AV39*1),2)*BA39),2) -> 5084.38 | CU39: =AG39 -> 0 | CV39: =(AH39*AV39) -> 7.117506 | CW39: =AI39 -> 0 | CX39: =AJ39 -> 0 | CY39: =(((S39+R39)*AT39)/100) -> 6420.042 | CZ39: =(((S39+R39)*AU39)/100) -> 3375.486 | DB39: 4 | DE39: *1,1 | DF39: *1,1 | DG39: *1,1 | DI39: *1,1 | DJ39: *1,1 | DN39: 0 | DO39: 0 | DP39: 1 | DQ39: 1 | DU39: 1013 | DV39: 1 м ширины по фронту | DW39: 1 м ширины по фронту | DX39: 1 | EE39: 59540733 | EF39: 40 | EG39: Монтаж оборудования | EH39: 0 | EJ39: 2 | EK39: 67 | EL39: ТСН-2001.4-8. Электротехнические установки | EM39: ТСН-2001.4-8-1 | EO39: Поправка: О.П. п.3.4.30.в | EQ39: 0 | ER39: 160.69 | ES39: 23.66 | ET39: 56.75 | EU39: 6.81 | EV39: 80.28 | EW39: 6.18 | EX39: 0 | EY39: 0 | FQ39: 0 | FR39: 0 | FS39: 0 | FX39: 97 | FY39: 51 | GD39: 1 | GF39: 373468362 | GG39: 2 | GH39: 1 | GI39: 2 | GJ39: 0 | GK39: 0 | GL39: =ROUND(IF(AND(BH39=3,BI39=3,FS39<>0),P39,0),2) -> 0 | GM39: =ROUND(O39+X39+Y39,2)+GX39 -> 17323.2 | GN39: =IF(OR(BI39=0,BI39=1),GM39-GX39,0) -> 0 | GO39: =IF(BI39=2,GM39-GX39,0) -> 17323.2 | GP39: =IF(BI39=4,GM39-GX39,0) -> 0 | GR39: 0 | GS39: 3 | GT39: 0 | GV39: =ROUND((GT39),6) -> 0 | GW39: 1 | GX39: =ROUND(HC39*I39,2) -> 0 | HA39: 0 | HB39: 0 | HC39: =GV39*GW39 -> 0 | HS39: 0 | IK39: 0
A40: 18 | B40: 1 | C40: 23 | E40: 4,1 | F40: 1.1-1-58 | G40: Болты строительные с гайками, оцинкованные, М10х100 мм | H40: т | I40: =I38*J40 -> 0.000612 | J40: 0.00051 | K40: 0.00051 | O40: =ROUND(CP40,2) -> 15.06 | P40: =ROUND((ROUND((AC40*AW40*I40),2)*BC40),2) -> 15.06 | Q40: =(ROUND((ROUND(((ET40)*AV40*I40),2)*BB40),2)+ROUND((ROUND(((AE40-(EU40))*AV40*I40),2)*BS40),2)) -> 0 | R40: =ROUND((ROUND((AE40*AV40*I40),2)*BS40),2) -> 0 | S40: =ROUND((ROUND((AF40*AV40*I40),2)*BA40),2) -> 0 | T40: =ROUND(CU40*I40,2) -> 0 | U40: =CV40*I40 -> 0 | V40: =CW40*I40 -> 0 | W40: =ROUND(CX40*I40,2) -> 0 | X40: =ROUND(CY40,2) -> 0 | Y40: =ROUND(CZ40,2) -> 0 | AA40: 60252778 | AB40: =ROUND((AC40+AD40+AF40),6) -> 24609.76 | AC40: =ROUND((ES40),6) -> 24609.76 | AD40: =ROUND((((ET40)-(EU40))+AE40),6) -> 0 | AE40: =ROUND((EU40),6) -> 0 | AF40: =ROUND((EV40),6) -> 0 | AG40: =ROUND((AP40),6) -> 0 | AH40: =(EW40) -> 0 | AI40: =(EX40) -> 0 | AJ40: =(AS40) -> 0 | AK40: 24609.76 | AL40: 24609.76 | AM40: 0 | AN40: 0 | AO40: 0 | AP40: 0 | AQ40: 0 | AR40: 0 | AS40: 0 | AT40: 97 | AU40: 51 | AV40: 1 | AW40: 1 | AZ40: 1 | BA40: 1 | BB40: 1 | BC40: 1 | BH40: 3 | BI40: 2 | BJ40: ТСН-2001.1 Доп. 79, Р. 1, о. 1, поз. 58 | BM40: 67 | BN40: 59540665 | BP40: 0 | BQ40: 40 | BR40: 0 | BS40: 1 | BT40: 1 | BU40: 1 | BV40: 1 | BW40: 1 | BX40: 1 | BZ40: 97 | CA40: 51 | CE40: 30 | CF40: 0 | CG40: 0 | CM40: 0 | CO40: 0 | CP40: =(P40+Q40+S40) -> 15.06 | CQ40: =ROUND((ROUND((AC40*AW40*1),2)*BC40),2) -> 24609.76 | CR40: =(ROUND((ROUND(((ET40)*AV40*1),2)*BB40),2)+ROUND((ROUND(((AE40-(EU40))*AV40*1),2)*BS40),2)) -> 0 | CS40: =ROUND((ROUND((AE40*AV40*1),2)*BS40),2) -> 0 | CT40: =ROUND((ROUND((AF40*AV40*1),2)*BA40),2) -> 0 | CU40: =AG40 -> 0 | CV40: =(AH40*AV40) -> 0 | CW40: =AI40 -> 0 | CX40: =AJ40 -> 0 | CY40: =(((S40+R40)*AT40)/100) -> 0 | CZ40: =(((S40+R40)*AU40)/100) -> 0 | DN40: 0 | DO40: 0 | DP40: 1 | DQ40: 1 | DU40: 1009 | DV40: т | DW40: т | DX40: 1000 | EE40: 59540733 | EF40: 40 | EG40: Монтаж оборудования | EH40: 0 | EJ40: 2 | EK40: 67 | EL40: ТСН-2001.4-8. Электротехнические установки | EM40: ТСН-2001.4-8-1 | EQ40: 0 | ER40: 24609.76 | ES40: 24609.76 | ET40: 0 | EU40: 0 | EV40: 0 | EW40: 0 | EX40: 0 | FQ40: 0 | FR40: 0 | FS40: 0 | FX40: 97 | FY40: 51 | GD40: 1 | GF40: -566361729 | GG40: 2 | GH40: 1 | GI40: -2 | GJ40: 0 | GK40: 0 | GL40: =ROUND(IF(AND(BH40=3,BI40=3,FS40<>0),P40,0),2) -> 0 | GM40: =ROUND(O40+X40+Y40,2)+GX40 -> 15.06 | GN40: =IF(OR(BI40=0,BI40=1),GM40-GX40,0) -> 0 | GO40: =IF(BI40=2,GM40-GX40,0) -> 15.06 | GP40: =IF(BI40=4,GM40-GX40,0) -> 0 | GR40: 0 | GS40: 3 | GT40: 0 | GV40: =ROUND((GT40),6) -> 0 | GW40: 1 | GX40: =ROUND(HC40*I40,2) -> 0 | HA40: 0 | HB40: 0 | HC40: =GV40*GW40 -> 0 | HS40: 0 | IK40: 0
A41: 18 | B41: 1 | C41: 31 | E41: 4,1 | F41: 1.1-1-58 | G41: Болты строительные с гайками, оцинкованные, М10х100 мм | H41: т | I41: =I39*J41 -> 0.000612 | J41: 0.00051 | K41: 0.00051 | O41: =ROUND(CP41,2) -> 77.56 | P41: =ROUND((ROUND((AC41*AW41*I41),2)*BC41),2) -> 77.56 | Q41: =(ROUND((ROUND(((ET41)*AV41*I41),2)*BB41),2)+ROUND((ROUND(((AE41-(EU41))*AV41*I41),2)*BS41),2)) -> 0 | R41: =ROUND((ROUND((AE41*AV41*I41),2)*BS41),2) -> 0 | S41: =ROUND((ROUND((AF41*AV41*I41),2)*BA41),2) -> 0 | T41: =ROUND(CU41*I41,2) -> 0 | U41: =CV41*I41 -> 0 | V41: =CW41*I41 -> 0 | W41: =ROUND(CX41*I41,2) -> 0 | X41: =ROUND(CY41,2) -> 0 | Y41: =ROUND(CZ41,2) -> 0 | AA41: 60252775 | AB41: =ROUND((AC41+AD41+AF41),6) -> 24609.76 | AC41: =ROUND((ES41),6) -> 24609.76 | AD41: =ROUND((((ET41)-(EU41))+AE41),6) -> 0 | AE41: =ROUND((EU41),6) -> 0 | AF41: =ROUND((EV41),6) -> 0 | AG41: =ROUND((AP41),6) -> 0 | AH41: =(EW41) -> 0 | AI41: =(EX41) -> 0 | AJ41: =(AS41) -> 0 | AK41: 24609.76 | AL41: 24609.76 | AM41: 0 | AN41: 0 | AO41: 0 | AP41: 0 | AQ41: 0 | AR41: 0 | AS41: 0 | AT41: 97 | AU41: 51 | AV41: 1 | AW41: 1 | AZ41: 1 | BA41: 1 | BB41: 1 | BC41: 5.15 | BH41: 3 | BI41: 2 | BJ41: ТСН-2001.1 Доп. 79, Р. 1, о. 1, поз. 58 | BM41: 67 | BN41: 59540665 | BO41: 1.1-1-58 | BP41: 1 | BQ41: 40 | BR41: 0 | BS41: 1 | BT41: 1 | BU41: 1 | BV41: 1 | BW41: 1 | BX41: 1 | BZ41: 97 | CA41: 51 | CE41: 30 | CF41: 0 | CG41: 0 | CM41: 0 | CO41: 0 | CP41: =(P41+Q41+S41) -> 77.56 | CQ41: =ROUND((ROUND((AC41*AW41*1),2)*BC41),2) -> 126740.26 | CR41: =(ROUND((ROUND(((ET41)*AV41*1),2)*BB41),2)+ROUND((ROUND(((AE41-(EU41))*AV41*1),2)*BS41),2)) -> 0 | CS41: =ROUND((ROUND((AE41*AV41*1),2)*BS41),2) -> 0 | CT41: =ROUND((ROUND((AF41*AV41*1),2)*BA41),2) -> 0 | CU41: =AG41 -> 0 | CV41: =(AH41*AV41) -> 0 | CW41: =AI41 -> 0 | CX41: =AJ41 -> 0 | CY41: =(((S41+R41)*AT41)/100) -> 0 | CZ41: =(((S41+R41)*AU41)/100) -> 0 | DN41: 0 | DO41: 0 | DP41: 1 | DQ41: 1 | DU41: 1009 | DV41: т | DW41: т | DX41: 1000 | EE41: 59540733 | EF41: 40 | EG41: Монтаж оборудования | EH41: 0 | EJ41: 2 | EK41: 67 | EL41: ТСН-2001.4-8. Электротехнические установки | EM41: ТСН-2001.4-8-1 | EQ41: 0 | ER41: 24609.76 | ES41: 24609.76 | ET41: 0 | EU41: 0 | EV41: 0 | EW41: 0 | EX41: 0 | FQ41: 0 | FR41: 0 | FS41: 0 | FX41: 97 | FY41: 51 | GD41: 1 | GF41: -566361729 | GG41: 2 | GH41: 1 | GI41: 2 | GJ41: 0 | GK41: 0 | GL41: =ROUND(IF(AND(BH41=3,BI41=3,FS41<>0),P41,0),2) -> 0 | GM41: =ROUND(O41+X41+Y41,2)+GX41 -> 77.56 | GN41: =IF(OR(BI41=0,BI41=1),GM41-GX41,0) -> 0 | GO41: =IF(BI41=2,GM41-GX41,0) -> 77.56 | GP41: =IF(BI41=4,GM41-GX41,0) -> 0 | GR41: 0 | GS41: 3 | GT41: 0 | GV41: =ROUND((GT41),6) -> 0 | GW41: 1 | GX41: =ROUND(HC41*I41,2) -> 0 | HA41: 0 | HB41: 0 | HC41: =GV41*GW41 -> 0 | HS41: 0 | IK41: 0
A42: 17 | B42: 1 | E42: 5 | F42: КА-3 | G42: Распределительная панель РП-1 | H42: ШТ | I42: 1 | J42: 0 | K42: 1 | O42: =ROUND(CP42,2) -> 38512.11 | P42: =ROUND((ROUND((AC42*I42),2)*BC42),2) -> 38512.11 | Q42: =(ROUND((ROUND(((ET42)*AV42*I42),2)*BB42),2)+ROUND((ROUND(((AE42-(EU42))*AV42*I42),2)*BS42),2)) -> 0 | R42: =ROUND((ROUND((AE42*AV42*I42),2)*BS42),2) -> 0 | S42: =ROUND((ROUND((AF42*AV42*I42),2)*BA42),2) -> 0 | T42: =ROUND(CU42*I42,2) -> 0 | U42: =CV42*I42 -> 0 | V42: =CW42*I42 -> 0 | W42: =ROUND(CX42*I42,2) -> 0 | X42: =ROUND(CY42,2) -> 0 | Y42: =ROUND(CZ42,2) -> 0 | AA42: 60252778 | AB42: =ROUND((AC42+AD42+AF42),6) -> 38512.11 | AC42: =ROUND((ES42),6) -> 38512.11 | AD42: =ROUND((((ET42)-(EU42))+AE42),6) -> 0 | AE42: =ROUND((EU42),6) -> 0 | AF42: =ROUND((EV42),6) -> 0 | AG42: =ROUND((AP42),6) -> 0 | AH42: =(EW42) -> 0 | AI42: =(EX42) -> 0 | AJ42: =(AS42) -> 0 | AK42: 38512.11 | AL42: 38512.11 | AM42: 0 | AN42: 0 | AO42: 0 | AP42: 0 | AQ42: 0 | AR42: 0 | AS42: 0 | AT42: 0 | AU42: 0 | AV42: 1 | AW42: 1 | AZ42: 1 | BA42: 1 | BB42: 1 | BC42: 1 | BH42: 3 | BI42: 3 | BM42: 746 | BN42: 0 | BP42: 0 | BQ42: 130 | BR42: 0 | BS42: 1 | BT42: 1 | BU42: 1 | BV42: 1 | BW42: 1 | BX42: 1 | BZ42: 0 | CA42: 0 | CE42: 30 | CF42: 0 | CG42: 0 | CM42: 0 | CO42: 0 | CP42: =(P42+Q42+S42) -> 38512.11 | CQ42: =ROUND((ROUND((AC42*1),2)*BC42),2) -> 38512.11 | CR42: =(ROUND((ROUND(((ET42)*AV42*1),2)*BB42),2)+ROUND((ROUND(((AE42-(EU42))*AV42*1),2)*BS42),2)) -> 0 | CS42: =ROUND((ROUND((AE42*AV42*1),2)*BS42),2) -> 0 | CT42: =ROUND((ROUND((AF42*AV42*1),2)*BA42),2) -> 0 | CU42: =AG42 -> 0 | CV42: =(AH42*AV42) -> 0 | CW42: =AI42 -> 0 | CX42: =AJ42 -> 0 | CY42: =(((S42+R42)*AT42)/100) -> 0 | CZ42: =(((S42+R42)*AU42)/100) -> 0 | DN42: 0 | DO42: 0 | DP42: 1 | DQ42: 1 | DU42: 1013 | DV42: ШТ | DW42: ШТ | DX42: 1 | EE42: 59540854 | EF42: 130 | EG42: Сметная стоимость оборудования | EH42: 0 | EJ42: 3 | EK42: 746 | EL42: ТСН-2001.13. Сметная стоимость оборудования | EM42: ТСН-2001.13 | EQ42: 0 | ER42: 0 | ES42: 38512.11 | ET42: 0 | EU42: 0 | EV42: 0 | EW42: 0 | EX42: 0 | EY42: 0 | FQ42: 0 | FR42: =P42 -> 38512.11 | FS42: 0 | FX42: 0 | FY42: 0 | GA42: [339 617,08 / 1,2 / 7,66] + 3% Трансп + 1,2% Заг.скл | GD42: 1 | GF42: -237304851 | GG42: 2 | GH42: 4 | GI42: -2 | GJ42: 0 | GK42: 0 | GL42: =ROUND(IF(AND(BH42=3,BI42=3,FS42<>0),P42,0),2) -> 0 | GM42: =ROUND(O42+X42+Y42,2)+GX42 -> 38512.11 | GN42: =IF(OR(BI42=0,BI42=1),GM42-GX42,0) -> 0 | GO42: =IF(BI42=2,GM42-GX42,0) -> 0 | GP42: =IF(BI42=4,GM42-GX42,0) -> 0 | GR42: 0 | GS42: 2 | GT42: 0 | GV42: =ROUND((GT42),6) -> 0 | GW42: 1 | GX42: =ROUND(HC42*I42,2) -> 0 | HA42: 0 | HB42: 0 | HC42: =GV42*GW42 -> 0 | HE42: 3 | HF42: 1,2 | HS42: 0 | IK42: 0
A43: 17 | B43: 1 | E43: 5 | F43: КА-3 | G43: Распределительная панель РП-1 | H43: ШТ | I43: 1 | J43: 0 | K43: 1 | O43: =ROUND(CP43,2) -> 295002.76 | P43: =ROUND((ROUND((AC43*I43),2)*BC43),2) -> 295002.76 | Q43: =(ROUND((ROUND(((ET43)*AV43*I43),2)*BB43),2)+ROUND((ROUND(((AE43-(EU43))*AV43*I43),2)*BS43),2)) -> 0 | R43: =ROUND((ROUND((AE43*AV43*I43),2)*BS43),2) -> 0 | S43: =ROUND((ROUND((AF43*AV43*I43),2)*BA43),2) -> 0 | T43: =ROUND(CU43*I43,2) -> 0 | U43: =CV43*I43 -> 0 | V43: =CW43*I43 -> 0 | W43: =ROUND(CX43*I43,2) -> 0 | X43: =ROUND(CY43,2) -> 0 | Y43: =ROUND(CZ43,2) -> 0 | AA43: 60252775 | AB43: =ROUND((AC43+AD43+AF43),6) -> 38512.11 | AC43: =ROUND((ES43),6) -> 38512.11 | AD43: =ROUND((((ET43)-(EU43))+AE43),6) -> 0 | AE43: =ROUND((EU43),6) -> 0 | AF43: =ROUND((EV43),6) -> 0 | AG43: =ROUND((AP43),6) -> 0 | AH43: =(EW43) -> 0 | AI43: =(EX43) -> 0 | AJ43: =(AS43) -> 0 | AK43: 38512.11 | AL43: 38512.11 | AM43: 0 | AN43: 0 | AO43: 0 | AP43: 0 | AQ43: 0 | AR43: 0 | AS43: 0 | AT43: 0 | AU43: 0 | AV43: 1 | AW43: 1 | AZ43: 1 | BA43: 1 | BB43: 1 | BC43: 7.66 | BH43: 3 | BI43: 3 | BM43: 746 | BN43: 0 | BP43: 0 | BQ43: 130 | BR43: 0 | BS43: 1 | BT43: 1 | BU43: 1 | BV43: 1 | BW43: 1 | BX43: 1 | BZ43: 0 | CA43: 0 | CE43: 30 | CF43: 0 | CG43: 0 | CM43: 0 | CO43: 0 | CP43: =(P43+Q43+S43) -> 295002.76 | CQ43: =ROUND((ROUND((AC43*1),2)*BC43),2) -> 295002.76 | CR43: =(ROUND((ROUND(((ET43)*AV43*1),2)*BB43),2)+ROUND((ROUND(((AE43-(EU43))*AV43*1),2)*BS43),2)) -> 0 | CS43: =ROUND((ROUND((AE43*AV43*1),2)*BS43),2) -> 0 | CT43: =ROUND((ROUND((AF43*AV43*1),2)*BA43),2) -> 0 | CU43: =AG43 -> 0 | CV43: =(AH43*AV43) -> 0 | CW43: =AI43 -> 0 | CX43: =AJ43 -> 0 | CY43: =(((S43+R43)*AT43)/100) -> 0 | CZ43: =(((S43+R43)*AU43)/100) -> 0 | DN43: 0 | DO43: 0 | DP43: 1 | DQ43: 1 | DU43: 1013 | DV43: ШТ | DW43: ШТ | DX43: 1 | EE43: 59540854 | EF43: 130 | EG43: Сметная стоимость оборудования | EH43: 0 | EJ43: 3 | EK43: 746 | EL43: ТСН-2001.13. Сметная стоимость оборудования | EM43: ТСН-2001.13 | EQ43: 0 | ER43: 38512.11 | ES43: 38512.11 | ET43: 0 | EU43: 0 | EV43: 0 | EW43: 0 | EX43: 0 | EY43: 0 | EZ43: 5 | FC43: 1 | FD43: 18 | FF43: 339617.08 | FQ43: 0 | FR43: =P43 -> 295002.76 | FS43: 0 | FX43: 0 | FY43: 0 | GA43: [339 617,08 / 1,2 / 7,66] + 3% Трансп + 1,2% Заг.скл | GD43: 1 | GF43: -237304851 | GG43: 2 | GH43: 3 | GI43: 5 | GJ43: 0 | GK43: 0 | GL43: =ROUND(IF(AND(BH43=3,BI43=3,FS43<>0),P43,0),2) -> 0 | GM43: =ROUND(O43+X43+Y43,2)+GX43 -> 295002.76 | GN43: =IF(OR(BI43=0,BI43=1),GM43-GX43,0) -> 0 | GO43: =IF(BI43=2,GM43-GX43,0) -> 0 | GP43: =IF(BI43=4,GM43-GX43,0) -> 0 | GR43: 1 | GS43: 1 | GT43: 0 | GV43: =ROUND((GT43),6) -> 0 | GW43: 1 | GX43: =ROUND(HC43*I43,2) -> 0 | HA43: 0 | HB43: 0 | HC43: =GV43*GW43 -> 0 | HE43: 3 | HF43: 1,2 | HS43: 0 | IK43: 0
A44: 17 | B44: 1 | E44: 6 | F44: КА-4 | G44: Распределительная панель РП-2 | H44: ШТ | I44: 1 | J44: 0 | K44: 1 | O44: =ROUND(CP44,2) -> 37439.23 | P44: =ROUND((ROUND((AC44*I44),2)*BC44),2) -> 37439.23 | Q44: =(ROUND((ROUND(((ET44)*AV44*I44),2)*BB44),2)+ROUND((ROUND(((AE44-(EU44))*AV44*I44),2)*BS44),2)) -> 0 | R44: =ROUND((ROUND((AE44*AV44*I44),2)*BS44),2) -> 0 | S44: =ROUND((ROUND((AF44*AV44*I44),2)*BA44),2) -> 0 | T44: =ROUND(CU44*I44,2) -> 0 | U44: =CV44*I44 -> 0 | V44: =CW44*I44 -> 0 | W44: =ROUND(CX44*I44,2) -> 0 | X44: =ROUND(CY44,2) -> 0 | Y44: =ROUND(CZ44,2) -> 0 | AA44: 60252778 | AB44: =ROUND((AC44+AD44+AF44),6) -> 37439.23 | AC44: =ROUND((ES44),6) -> 37439.23 | AD44: =ROUND((((ET44)-(EU44))+AE44),6) -> 0 | AE44: =ROUND((EU44),6) -> 0 | AF44: =ROUND((EV44),6) -> 0 | AG44: =ROUND((AP44),6) -> 0 | AH44: =(EW44) -> 0 | AI44: =(EX44) -> 0 | AJ44: =(AS44) -> 0 | AK44: 37439.23 | AL44: 37439.23 | AM44: 0 | AN44: 0 | AO44: 0 | AP44: 0 | AQ44: 0 | AR44: 0 | AS44: 0 | AT44: 0 | AU44: 0 | AV44: 1 | AW44: 1 | AZ44: 1 | BA44: 1 | BB44: 1 | BC44: 1 | BH44: 3 | BI44: 3 | BM44: 746 | BN44: 0 | BP44: 0 | BQ44: 130 | BR44: 0 | BS44: 1 | BT44: 1 | BU44: 1 | BV44: 1 | BW44: 1 | BX44: 1 | BZ44: 0 | CA44: 0 | CE44: 30 | CF44: 0 | CG44: 0 | CM44: 0 | CO44: 0 | CP44: =(P44+Q44+S44) -> 37439.23 | CQ44: =ROUND((ROUND((AC44*1),2)*BC44),2) -> 37439.23 | CR44: =(ROUND((ROUND(((ET44)*AV44*1),2)*BB44),2)+ROUND((ROUND(((AE44-(EU44))*AV44*1),2)*BS44),2)) -> 0 | CS44: =ROUND((ROUND((AE44*AV44*1),2)*BS44),2) -> 0 | CT44: =ROUND((ROUND((AF44*AV44*1),2)*BA44),2) -> 0 | CU44: =AG44 -> 0 | CV44: =(AH44*AV44) -> 0 | CW44: =AI44 -> 0 | CX44: =AJ44 -> 0 | CY44: =(((S44+R44)*AT44)/100) -> 0 | CZ44: =(((S44+R44)*AU44)/100) -> 0 | DN44: 0 | DO44: 0 | DP44: 1 | DQ44: 1 | DU44: 1013 | DV44: ШТ | DW44: ШТ | DX44: 1 | EE44: 59540854 | EF44: 130 | EG44: Сметная стоимость оборудования | EH44: 0 | EJ44: 3 | EK44: 746 | EL44: ТСН-2001.13. Сметная стоимость оборудования | EM44: ТСН-2001.13 | EQ44: 0 | ER44: 0 | ES44: 37439.23 | ET44: 0 | EU44: 0 | EV44: 0 | EW44: 0 | EX44: 0 | EY44: 0 | FQ44: 0 | FR44: =P44 -> 37439.23 | FS44: 0 | FX44: 0 | FY44: 0 | GA44: [330 156,03 / 1,2 / 7,66] + 3% Трансп + 1,2% Заг.скл | GD44: 1 | GF44: 226487503 | GG44: 2 | GH44: 4 | GI44: -2 | GJ44: 0 | GK44: 0 | GL44: =ROUND(IF(AND(BH44=3,BI44=3,FS44<>0),P44,0),2) -> 0 | GM44: =ROUND(O44+X44+Y44,2)+GX44 -> 37439.23 | GN44: =IF(OR(BI44=0,BI44=1),GM44-GX44,0) -> 0 | GO44: =IF(BI44=2,GM44-GX44,0) -> 0 | GP44: =IF(BI44=4,GM44-GX44,0) -> 0 | GR44: 0 | GS44: 2 | GT44: 0 | GV44: =ROUND((GT44),6) -> 0 | GW44: 1 | GX44: =ROUND(HC44*I44,2) -> 0 | HA44: 0 | HB44: 0 | HC44: =GV44*GW44 -> 0 | HE44: 3 | HF44: 1,2 | HS44: 0 | IK44: 0
A45: 17 | B45: 1 | E45: 6 | F45: КА-4 | G45: Распределительная панель РП-2 | H45: ШТ | I45: 1 | J45: 0 | K45: 1 | O45: =ROUND(CP45,2) -> 286784.5 | P45: =ROUND((ROUND((AC45*I45),2)*BC45),2) -> 286784.5 | Q45: =(ROUND((ROUND(((ET45)*AV45*I45),2)*BB45),2)+ROUND((ROUND(((AE45-(EU45))*AV45*I45),2)*BS45),2)) -> 0 | R45: =ROUND((ROUND((AE45*AV45*I45),2)*BS45),2) -> 0 | S45: =ROUND((ROUND((AF45*AV45*I45),2)*BA45),2) -> 0 | T45: =ROUND(CU45*I45,2) -> 0 | U45: =CV45*I45 -> 0 | V45: =CW45*I45 -> 0 | W45: =ROUND(CX45*I45,2) -> 0 | X45: =ROUND(CY45,2) -> 0 | Y45: =ROUND(CZ45,2) -> 0 | AA45: 60252775 | AB45: =ROUND((AC45+AD45+AF45),6) -> 37439.23 | AC45: =ROUND((ES45),6) -> 37439.23 | AD45: =ROUND((((ET45)-(EU45))+AE45),6) -> 0 | AE45: =ROUND((EU45),6) -> 0 | AF45: =ROUND((EV45),6) -> 0 | AG45: =ROUND((AP45),6) -> 0 | AH45: =(EW45) -> 0 | AI45: =(EX45) -> 0 | AJ45: =(AS45) -> 0 | AK45: 37439.23 | AL45: 37439.23 | AM45: 0 | AN45: 0 | AO45: 0 | AP45: 0 | AQ45: 0 | AR45: 0 | AS45: 0 | AT45: 0 | AU45: 0 | AV45: 1 | AW45: 1 | AZ45: 1 | BA45: 1 | BB45: 1 | BC45: 7.66 | BH45: 3 | BI45: 3 | BM45: 746 | BN45: 0 | BP45: 0 | BQ45: 130 | BR45: 0 | BS45: 1 | BT45: 1 | BU45: 1 | BV45: 1 | BW45: 1 | BX45: 1 | BZ45: 0 | CA45: 0 | CE45: 30 | CF45: 0 | CG45: 0 | CM45: 0 | CO45: 0 | CP45: =(P45+Q45+S45) -> 286784.5 | CQ45: =ROUND((ROUND((AC45*1),2)*BC45),2) -> 286784.5 | CR45: =(ROUND((ROUND(((ET45)*AV45*1),2)*BB45),2)+ROUND((ROUND(((AE45-(EU45))*AV45*1),2)*BS45),2)) -> 0 | CS45: =ROUND((ROUND((AE45*AV45*1),2)*BS45),2) -> 0 | CT45: =ROUND((ROUND((AF45*AV45*1),2)*BA45),2) -> 0 | CU45: =AG45 -> 0 | CV45: =(AH45*AV45) -> 0 | CW45: =AI45 -> 0 | CX45: =AJ45 -> 0 | CY45: =(((S45+R45)*AT45)/100) -> 0 | CZ45: =(((S45+R45)*AU45)/100) -> 0 | DN45: 0 | DO45: 0 | DP45: 1 | DQ45: 1 | DU45: 1013 | DV45: ШТ | DW45: ШТ | DX45: 1 | EE45: 59540854 | EF45: 130 | EG45: Сметная стоимость оборудования | EH45: 0 | EJ45: 3 | EK45: 746 | EL45: ТСН-2001.13. Сметная стоимость оборудования | EM45: ТСН-2001.13 | EQ45: 0 | ER45: 37439.23 | ES45: 37439.23 | ET45: 0 | EU45: 0 | EV45: 0 | EW45: 0 | EX45: 0 | EY45: 0 | EZ45: 5 | FC45: 1 | FD45: 18 | FF45: 330156.03 | FQ45: 0 | FR45: =P45 -> 286784.5 | FS45: 0 | FX45: 0 | FY45: 0 | GA45: [330 156,03 / 1,2 / 7,66] + 3% Трансп + 1,2% Заг.скл | GD45: 1 | GF45: 226487503 | GG45: 2 | GH45: 3 | GI45: 5 | GJ45: 0 | GK45: 0 | GL45: =ROUND(IF(AND(BH45=3,BI45=3,FS45<>0),P45,0),2) -> 0 | GM45: =ROUND(O45+X45+Y45,2)+GX45 -> 286784.5 | GN45: =IF(OR(BI45=0,BI45=1),GM45-GX45,0) -> 0 | GO45: =IF(BI45=2,GM45-GX45,0) -> 0 | GP45: =IF(BI45=4,GM45-GX45,0) -> 0 | GR45: 1 | GS45: 1 | GT45: 0 | GV45: =ROUND((GT45),6) -> 0 | GW45: 1 | GX45: =ROUND(HC45*I45,2) -> 0 | HA45: 0 | HB45: 0 | HC45: =GV45*GW45 -> 0 | HE45: 3 | HF45: 1,2 | HS45: 0 | IK45: 0
A46: 19 | B46: 1 | G46: Панель ЩГП с АВР | AA46: 1 | IK46: 0
A47: 17 | B47: 1 | C47: =ROW(SmtRes!A40) -> 40 | D47: =ROW(EtalonRes!A45) -> 45 | E47: 7 | F47: 4.8-238-3 | G47: Монтаж щитов и стеллажей с блоками резисторов (ящиками сопротивлений) высотой свыше 1700 мм, щита заводского изготовления однорядного или двухрядного открытого исполнения шириной 800 мм | H47: 1 м ширины по фронту | I47: 0.6 | J47: 0 | K47: 0.6 | O47: =ROUND(CP47,2) -> 108.9 | P47: =ROUND((ROUND((AC47*AW47*I47),2)*BC47),2) -> 14.2 | Q47: =(ROUND((ROUND((((ET47*1.1))*AV47*I47),2)*BB47),2)+ROUND((ROUND(((AE47-((EU47*1.1)))*AV47*I47),2)*BS47),2)) -> 39.22 | R47: =ROUND((ROUND((AE47*AV47*I47),2)*BS47),2) -> 4.71 | S47: =ROUND((ROUND((AF47*AV47*I47),2)*BA47),2) -> 55.48 | T47: =ROUND(CU47*I47,2) -> 0 | U47: =CV47*I47 -> 4.2705036 | V47: =CW47*I47 -> 0 | W47: =ROUND(CX47*I47,2) -> 0 | X47: =ROUND(CY47,2) -> 58.38 | Y47: =ROUND(CZ47,2) -> 30.7 | AA47: 60252778 | AB47: =ROUND((AC47+AD47+AF47),6) -> 174.393 | AC47: =ROUND((ES47),6) -> 23.66 | AD47: =ROUND(((((ET47*1.1))-((EU47*1.1)))+AE47),6) -> 62.425 | AE47: =ROUND(((EU47*1.1)),6) -> 7.491 | AF47: =ROUND(((EV47*1.1)),6) -> 88.308 | AG47: =ROUND((AP47),6) -> 0 | AH47: =((EW47*1.1)) -> 6.798 | AI47: =((EX47*1.1)) -> 0 | AJ47: =(AS47) -> 0 | AK47: 160.69 | AL47: 23.66 | AM47: 56.75 | AN47: 6.81 | AO47: 80.28 | AP47: 0 | AQ47: 6.18 | AR47: 0 | AS47: 0 | AT47: 97 | AU47: 51 | AV47: 1.047 | AW47: 1 | AZ47: 1 | BA47: 1 | BB47: 1 | BC47: 1 | BH47: 0 | BI47: 2 | BJ47: ТСН-2001.4 Доп. 79, Сб. 8, т. 238, поз. 3 | BM47: 67 | BN47: 59540665 | BO47: 4.8-238-3 | BP47: 1 | BQ47: 40 | BR47: 0 | BS47: 1 | BT47: 1 | BU47: 1 | BV47: 1 | BW47: 1 | BX47: 1 | BZ47: 97 | CA47: 51 | CE47: 30 | CF47: 0 | CG47: 0 | CM47: 0 | CN47: Поправка: О.П. п.3.4.30.в Наименование: При применении территориальных сметных нормативов для города Москвы затраты, учитывающие напряженные и стесненные условия производства работ (стесненность, сложность складирования и транспортной логистики и т.п.), исчисляются с применением коэффициентов к затратам труда и заработной плате рабочих, машинистов, времени эксплуатации машин и механизмов, стоимости эксплуатации машин в размере: для объектов, расположенных за пределами Третьего транспортного кольца города Москвы, но в пределах Московской кольцевой автомобильной дороги | CO47: 0 | CP47: =(P47+Q47+S47) -> 108.9 | CQ47: =ROUND((ROUND((AC47*AW47*1),2)*BC47),2) -> 23.66 | CR47: =(ROUND((ROUND((((ET47*1.1))*AV47*1),2)*BB47),2)+ROUND((ROUND(((AE47-((EU47*1.1)))*AV47*1),2)*BS47),2)) -> 65.36 | CS47: =ROUND((ROUND((AE47*AV47*1),2)*BS47),2) -> 7.84 | CT47: =ROUND((ROUND((AF47*AV47*1),2)*BA47),2) -> 92.46 | CU47: =AG47 -> 0 | CV47: =(AH47*AV47) -> 7.117506 | CW47: =AI47 -> 0 | CX47: =AJ47 -> 0 | CY47: =(((S47+R47)*AT47)/100) -> 58.3843 | CZ47: =(((S47+R47)*AU47)/100) -> 30.6969 | DB47: 5 | DE47: *1,1 | DF47: *1,1 | DG47: *1,1 | DI47: *1,1 | DJ47: *1,1 | DN47: 0 | DO47: 0 | DP47: 1 | DQ47: 1 | DU47: 1013 | DV47: 1 м ширины по фронту | DW47: 1 м ширины по фронту | DX47: 1 | EE47: 59540733 | EF47: 40 | EG47: Монтаж оборудования | EH47: 0 | EJ47: 2 | EK47: 67 | EL47: ТСН-2001.4-8. Электротехнические установки | EM47: ТСН-2001.4-8-1 | EO47: Поправка: О.П. п.3.4.30.в | EQ47: 0 | ER47: 160.69 | ES47: 23.66 | ET47: 56.75 | EU47: 6.81 | EV47: 80.28 | EW47: 6.18 | EX47: 0 | EY47: 0 | FQ47: 0 | FR47: 0 | FS47: 0 | FX47: 97 | FY47: 51 | GD47: 1 | GF47: 373468362 | GG47: 2 | GH47: 1 | GI47: 2 | GJ47: 0 | GK47: 0 | GL47: =ROUND(IF(AND(BH47=3,BI47=3,FS47<>0),P47,0),2) -> 0 | GM47: =ROUND(O47+X47+Y47,2)+GX47 -> 197.98 | GN47: =IF(OR(BI47=0,BI47=1),GM47-GX47,0) -> 0 | GO47: =IF(BI47=2,GM47-GX47,0) -> 197.98 | GP47: =IF(BI47=4,GM47-GX47,0) -> 0 | GR47: 0 | GS47: 3 | GT47: 0 | GV47: =ROUND((GT47),6) -> 0 | GW47: 1 | GX47: =ROUND(HC47*I47,2) -> 0 | HA47: 0 | HB47: 0 | HC47: =GV47*GW47 -> 0 | HS47: 0 | IK47: 0
A48: 17 | B48: 1 | C48: =ROW(SmtRes!A48) -> 48 | D48: =ROW(EtalonRes!A54) -> 54 | E48: 7 | F48: 4.8-238-3 | G48: Монтаж щитов и стеллажей с блоками резисторов (ящиками сопротивлений) высотой свыше 1700 мм, щита заводского изготовления однорядного или двухрядного открытого исполнения шириной 800 мм | H48: 1 м ширины по фронту | I48: 0.6 | J48: 0 | K48: 0.6 | O48: =ROUND(CP48,2) -> 3764.24 | P48: =ROUND((ROUND((AC48*AW48*I48),2)*BC48),2) -> 113.32 | Q48: =(ROUND((ROUND((((ET48*1.1))*AV48*I48),2)*BB48),2)+ROUND((ROUND(((AE48-((EU48*1.1)))*AV48*I48),2)*BS48),2)) -> 600.07 | R48: =ROUND((ROUND((AE48*AV48*I48),2)*BS48),2) -> 259 | S48: =ROUND((ROUND((AF48*AV48*I48),2)*BA48),2) -> 3050.85 | T48: =ROUND(CU48*I48,2) -> 0 | U48: =CV48*I48 -> 4.2705036 | V48: =CW48*I48 -> 0 | W48: =ROUND(CX48*I48,2) -> 0 | X48: =ROUND(CY48,2) -> 3210.55 | Y48: =ROUND(CZ48,2) -> 1688.02 | AA48: 60252775 | AB48: =ROUND((AC48+AD48+AF48),6) -> 174.393 | AC48: =ROUND((ES48),6) -> 23.66 | AD48: =ROUND(((((ET48*1.1))-((EU48*1.1)))+AE48),6) -> 62.425 | AE48: =ROUND(((EU48*1.1)),6) -> 7.491 | AF48: =ROUND(((EV48*1.1)),6) -> 88.308 | AG48: =ROUND((AP48),6) -> 0 | AH48: =((EW48*1.1)) -> 6.798 | AI48: =((EX48*1.1)) -> 0 | AJ48: =(AS48) -> 0 | AK48: 160.69 | AL48: 23.66 | AM48: 56.75 | AN48: 6.81 | AO48: 80.28 | AP48: 0 | AQ48: 6.18 | AR48: 0 | AS48: 0 | AT48: 97 | AU48: 51 | AV48: 1.047 | AW48: 1 | AZ48: 1 | BA48: 54.99 | BB48: 15.3 | BC48: 7.98 | BH48: 0 | BI48: 2 | BJ48: ТСН-2001.4 Доп. 79, Сб. 8, т. 238, поз. 3 | BM48: 67 | BN48: 59540665 | BO48: 4.8-238-3 | BP48: 1 | BQ48: 40 | BR48: 0 | BS48: 54.99 | BT48: 1 | BU48: 1 | BV48: 1 | BW48: 1 | BX48: 1 | BZ48: 97 | CA48: 51 | CE48: 30 | CF48: 0 | CG48: 0 | CM48: 0 | CN48: Поправка: О.П. п.3.4.30.в Наименование: При применении территориальных сметных нормативов для города Москвы затраты, учитывающие напряженные и стесненные условия производства работ (стесненность, сложность складирования и транспортной логистики и т.п.), исчисляются с применением коэффициентов к затратам труда и заработной плате рабочих, машинистов, времени эксплуатации машин и механизмов, стоимости эксплуатации машин в размере: для объектов, расположенных за пределами Третьего транспортного кольца города Москвы, но в пределах Московской кольцевой автомобильной дороги | CO48: 0 | CP48: =(P48+Q48+S48) -> 3764.24 | CQ48: =ROUND((ROUND((AC48*AW48*1),2)*BC48),2) -> 188.81 | CR48: =(ROUND((ROUND((((ET48*1.1))*AV48*1),2)*BB48),2)+ROUND((ROUND(((AE48-((EU48*1.1)))*AV48*1),2)*BS48),2)) -> 1000.01 | CS48: =ROUND((ROUND((AE48*AV48*1),2)*BS48),2) -> 431.12 | CT48: =ROUND((ROUND((AF48*AV48*1),2)*BA48),2) -> 5084.38 | CU48: =AG48 -> 0 | CV48: =(AH48*AV48) -> 7.117506 | CW48: =AI48 -> 0 | CX48: =AJ48 -> 0 | CY48: =(((S48+R48)*AT48)/100) -> 3210.5545 | CZ48: =(((S48+R48)*AU48)/100) -> 1688.0235 | DB48: 6 | DE48: *1,1 | DF48: *1,1 | DG48: *1,1 | DI48: *1,1 | DJ48: *1,1 | DN48: 0 | DO48: 0 | DP48: 1 | DQ48: 1 | DU48: 1013 | DV48: 1 м ширины по фронту | DW48: 1 м ширины по фронту | DX48: 1 | EE48: 59540733 | EF48: 40 | EG48: Монтаж оборудования | EH48: 0 | EJ48: 2 | EK48: 67 | EL48: ТСН-2001.4-8. Электротехнические установки | EM48: ТСН-2001.4-8-1 | EO48: Поправка: О.П. п.3.4.30.в | EQ48: 0 | ER48: 160.69 | ES48: 23.66 | ET48: 56.75 | EU48: 6.81 | EV48: 80.28 | EW48: 6.18 | EX48: 0 | EY48: 0 | FQ48: 0 | FR48: 0 | FS48: 0 | FX48: 97 | FY48: 51 | GD48: 1 | GF48: 373468362 | GG48: 2 | GH48: 1 | GI48: 2 | GJ48: 0 | GK48: 0 | GL48: =ROUND(IF(AND(BH48=3,BI48=3,FS48<>0),P48,0),2) -> 0 | GM48: =ROUND(O48+X48+Y48,2)+GX48 -> 8662.81 | GN48: =IF(OR(BI48=0,BI48=1),GM48-GX48,0) -> 0 | GO48: =IF(BI48=2,GM48-GX48,0) -> 8662.81 | GP48: =IF(BI48=4,GM48-GX48,0) -> 0 | GR48: 0 | GS48: 3 | GT48: 0 | GV48: =ROUND((GT48),6) -> 0 | GW48: 1 | GX48: =ROUND(HC48*I48,2) -> 0 | HA48: 0 | HB48: 0 | HC48: =GV48*GW48 -> 0 | HS48: 0 | IK48: 0
A49: 18 | B49: 1 | C49: 39 | E49: 7,1 | F49: 1.1-1-58 | G49: Болты строительные с гайками, оцинкованные, М10х100 мм | H49: т | I49: =I47*J49 -> 0.000306 | J49: 0.00051 | K49: 0.00051 | O49: =ROUND(CP49,2) -> 7.53 | P49: =ROUND((ROUND((AC49*AW49*I49),2)*BC49),2) -> 7.53 | Q49: =(ROUND((ROUND(((ET49)*AV49*I49),2)*BB49),2)+ROUND((ROUND(((AE49-(EU49))*AV49*I49),2)*BS49),2)) -> 0 | R49: =ROUND((ROUND((AE49*AV49*I49),2)*BS49),2) -> 0 | S49: =ROUND((ROUND((AF49*AV49*I49),2)*BA49),2) -> 0 | T49: =ROUND(CU49*I49,2) -> 0 | U49: =CV49*I49 -> 0 | V49: =CW49*I49 -> 0 | W49: =ROUND(CX49*I49,2) -> 0 | X49: =ROUND(CY49,2) -> 0 | Y49: =ROUND(CZ49,2) -> 0 | AA49: 60252778 | AB49: =ROUND((AC49+AD49+AF49),6) -> 24609.76 | AC49: =ROUND((ES49),6) -> 24609.76 | AD49: =ROUND((((ET49)-(EU49))+AE49),6) -> 0 | AE49: =ROUND((EU49),6) -> 0 | AF49: =ROUND((EV49),6) -> 0 | AG49: =ROUND((AP49),6) -> 0 | AH49: =(EW49) -> 0 | AI49: =(EX49) -> 0 | AJ49: =(AS49) -> 0 | AK49: 24609.76 | AL49: 24609.76 | AM49: 0 | AN49: 0 | AO49: 0 | AP49: 0 | AQ49: 0 | AR49: 0 | AS49: 0 | AT49: 97 | AU49: 51 | AV49: 1 | AW49: 1 | AZ49: 1 | BA49: 1 | BB49: 1 | BC49: 1 | BH49: 3 | BI49: 2 | BJ49: ТСН-2001.1 Доп. 79, Р. 1, о. 1, поз. 58 | BM49: 67 | BN49: 59540665 | BP49: 0 | BQ49: 40 | BR49: 0 | BS49: 1 | BT49: 1 | BU49: 1 | BV49: 1 | BW49: 1 | BX49: 1 | BZ49: 97 | CA49: 51 | CE49: 30 | CF49: 0 | CG49: 0 | CM49: 0 | CO49: 0 | CP49: =(P49+Q49+S49) -> 7.53 | CQ49: =ROUND((ROUND((AC49*AW49*1),2)*BC49),2) -> 24609.76 | CR49: =(ROUND((ROUND(((ET49)*AV49*1),2)*BB49),2)+ROUND((ROUND(((AE49-(EU49))*AV49*1),2)*BS49),2)) -> 0 | CS49: =ROUND((ROUND((AE49*AV49*1),2)*BS49),2) -> 0 | CT49: =ROUND((ROUND((AF49*AV49*1),2)*BA49),2) -> 0 | CU49: =AG49 -> 0 | CV49: =(AH49*AV49) -> 0 | CW49: =AI49 -> 0 | CX49: =AJ49 -> 0 | CY49: =(((S49+R49)*AT49)/100) -> 0 | CZ49: =(((S49+R49)*AU49)/100) -> 0 | DN49: 0 | DO49: 0 | DP49: 1 | DQ49: 1 | DU49: 1009 | DV49: т | DW49: т | DX49: 1000 | EE49: 59540733 | EF49: 40 | EG49: Монтаж оборудования | EH49: 0 | EJ49: 2 | EK49: 67 | EL49: ТСН-2001.4-8. Электротехнические установки | EM49: ТСН-2001.4-8-1 | EQ49: 0 | ER49: 24609.76 | ES49: 24609.76 | ET49: 0 | EU49: 0 | EV49: 0 | EW49: 0 | EX49: 0 | FQ49: 0 | FR49: 0 | FS49: 0 | FX49: 97 | FY49: 51 | GD49: 1 | GF49: -566361729 | GG49: 2 | GH49: 1 | GI49: -2 | GJ49: 0 | GK49: 0 | GL49: =ROUND(IF(AND(BH49=3,BI49=3,FS49<>0),P49,0),2) -> 0 | GM49: =ROUND(O49+X49+Y49,2)+GX49 -> 7.53 | GN49: =IF(OR(BI49=0,BI49=1),GM49-GX49,0) -> 0 | GO49: =IF(BI49=2,GM49-GX49,0) -> 7.53 | GP49: =IF(BI49=4,GM49-GX49,0) -> 0 | GR49: 0 | GS49: 3 | GT49: 0 | GV49: =ROUND((GT49),6) -> 0 | GW49: 1 | GX49: =ROUND(HC49*I49,2) -> 0 | HA49: 0 | HB49: 0 | HC49: =GV49*GW49 -> 0 | HS49: 0 | IK49: 0
A50: 18 | B50: 1 | C50: 47 | E50: 7,1 | F50: 1.1-1-58 | G50: Болты строительные с гайками, оцинкованные, М10х100 мм | H50: т | I50: =I48*J50 -> 0.000306 | J50: 0.00051 | K50: 0.00051 | O50: =ROUND(CP50,2) -> 38.78 | P50: =ROUND((ROUND((AC50*AW50*I50),2)*BC50),2) -> 38.78 | Q50: =(ROUND((ROUND(((ET50)*AV50*I50),2)*BB50),2)+ROUND((ROUND(((AE50-(EU50))*AV50*I50),2)*BS50),2)) -> 0 | R50: =ROUND((ROUND((AE50*AV50*I50),2)*BS50),2) -> 0 | S50: =ROUND((ROUND((AF50*AV50*I50),2)*BA50),2) -> 0 | T50: =ROUND(CU50*I50,2) -> 0 | U50: =CV50*I50 -> 0 | V50: =CW50*I50 -> 0 | W50: =ROUND(CX50*I50,2) -> 0 | X50: =ROUND(CY50,2) -> 0 | Y50: =ROUND(CZ50,2) -> 0 | AA50: 60252775 | AB50: =ROUND((AC50+AD50+AF50),6) -> 24609.76 | AC50: =ROUND((ES50),6) -> 24609.76 | AD50: =ROUND((((ET50)-(EU50))+AE50),6) -> 0 | AE50: =ROUND((EU50),6) -> 0 | AF50: =ROUND((EV50),6) -> 0 | AG50: =ROUND((AP50),6) -> 0 | AH50: =(EW50) -> 0 | AI50: =(EX50) -> 0 | AJ50: =(AS50) -> 0 | AK50: 24609.76 | AL50: 24609.76 | AM50: 0 | AN50: 0 | AO50: 0 | AP50: 0 | AQ50: 0 | AR50: 0 | AS50: 0 | AT50: 97 | AU50: 51 | AV50: 1 | AW50: 1 | AZ50: 1 | BA50: 1 | BB50: 1 | BC50: 5.15 | BH50: 3 | BI50: 2 | BJ50: ТСН-2001.1 Доп. 79, Р. 1, о. 1, поз. 58 | BM50: 67 | BN50: 59540665 | BO50: 1.1-1-58 | BP50: 1 | BQ50: 40 | BR50: 0 | BS50: 1 | BT50: 1 | BU50: 1 | BV50: 1 | BW50: 1 | BX50: 1 | BZ50: 97 | CA50: 51 | CE50: 30 | CF50: 0 | CG50: 0 | CM50: 0 | CO50: 0 | CP50: =(P50+Q50+S50) -> 38.78 | CQ50: =ROUND((ROUND((AC50*AW50*1),2)*BC50),2) -> 126740.26 | CR50: =(ROUND((ROUND(((ET50)*AV50*1),2)*BB50),2)+ROUND((ROUND(((AE50-(EU50))*AV50*1),2)*BS50),2)) -> 0 | CS50: =ROUND((ROUND((AE50*AV50*1),2)*BS50),2) -> 0 | CT50: =ROUND((ROUND((AF50*AV50*1),2)*BA50),2) -> 0 | CU50: =AG50 -> 0 | CV50: =(AH50*AV50) -> 0 | CW50: =AI50 -> 0 | CX50: =AJ50 -> 0 | CY50: =(((S50+R50)*AT50)/100) -> 0 | CZ50: =(((S50+R50)*AU50)/100) -> 0 | DN50: 0 | DO50: 0 | DP50: 1 | DQ50: 1 | DU50: 1009 | DV50: т | DW50: т | DX50: 1000 | EE50: 59540733 | EF50: 40 | EG50: Монтаж оборудования | EH50: 0 | EJ50: 2 | EK50: 67 | EL50: ТСН-2001.4-8. Электротехнические установки | EM50: ТСН-2001.4-8-1 | EQ50: 0 | ER50: 24609.76 | ES50: 24609.76 | ET50: 0 | EU50: 0 | EV50: 0 | EW50: 0 | EX50: 0 | FQ50: 0 | FR50: 0 | FS50: 0 | FX50: 97 | FY50: 51 | GD50: 1 | GF50: -566361729 | GG50: 2 | GH50: 1 | GI50: 2 | GJ50: 0 | GK50: 0 | GL50: =ROUND(IF(AND(BH50=3,BI50=3,FS50<>0),P50,0),2) -> 0 | GM50: =ROUND(O50+X50+Y50,2)+GX50 -> 38.78 | GN50: =IF(OR(BI50=0,BI50=1),GM50-GX50,0) -> 0 | GO50: =IF(BI50=2,GM50-GX50,0) -> 38.78 | GP50: =IF(BI50=4,GM50-GX50,0) -> 0 | GR50: 0 | GS50: 3 | GT50: 0 | GV50: =ROUND((GT50),6) -> 0 | GW50: 1 | GX50: =ROUND(HC50*I50,2) -> 0 | HA50: 0 | HB50: 0 | HC50: =GV50*GW50 -> 0 | HS50: 0 | IK50: 0
A51: 17 | B51: 1 | E51: 8 | F51: КА-5 | G51: Панель ЩГП с АВР | H51: ШТ | I51: 1 | J51: 0 | K51: 1 | O51: =ROUND(CP51,2) -> 29029.49 | P51: =ROUND((ROUND((AC51*I51),2)*BC51),2) -> 29029.49 | Q51: =(ROUND((ROUND(((ET51)*AV51*I51),2)*BB51),2)+ROUND((ROUND(((AE51-(EU51))*AV51*I51),2)*BS51),2)) -> 0 | R51: =ROUND((ROUND((AE51*AV51*I51),2)*BS51),2) -> 0 | S51: =ROUND((ROUND((AF51*AV51*I51),2)*BA51),2) -> 0 | T51: =ROUND(CU51*I51,2) -> 0 | U51: =CV51*I51 -> 0 | V51: =CW51*I51 -> 0 | W51: =ROUND(CX51*I51,2) -> 0 | X51: =ROUND(CY51,2) -> 0 | Y51: =ROUND(CZ51,2) -> 0 | AA51: 60252778 | AB51: =ROUND((AC51+AD51+AF51),6) -> 29029.49 | AC51: =ROUND((ES51),6) -> 29029.49 | AD51: =ROUND((((ET51)-(EU51))+AE51),6) -> 0 | AE51: =ROUND((EU51),6) -> 0 | AF51: =ROUND((EV51),6) -> 0 | AG51: =ROUND((AP51),6) -> 0 | AH51: =(EW51) -> 0 | AI51: =(EX51) -> 0 | AJ51: =(AS51) -> 0 | AK51: 29029.49 | AL51: 29029.49 | AM51: 0 | AN51: 0 | AO51: 0 | AP51: 0 | AQ51: 0 | AR51: 0 | AS51: 0 | AT51: 0 | AU51: 0 | AV51: 1 | AW51: 1 | AZ51: 1 | BA51: 1 | BB51: 1 | BC51: 1 | BH51: 3 | BI51: 3 | BM51: 746 | BN51: 0 | BP51: 0 | BQ51: 130 | BR51: 0 | BS51: 1 | BT51: 1 | BU51: 1 | BV51: 1 | BW51: 1 | BX51: 1 | BZ51: 0 | CA51: 0 | CE51: 30 | CF51: 0 | CG51: 0 | CM51: 0 | CO51: 0 | CP51: =(P51+Q51+S51) -> 29029.49 | CQ51: =ROUND((ROUND((AC51*1),2)*BC51),2) -> 29029.49 | CR51: =(ROUND((ROUND(((ET51)*AV51*1),2)*BB51),2)+ROUND((ROUND(((AE51-(EU51))*AV51*1),2)*BS51),2)) -> 0 | CS51: =ROUND((ROUND((AE51*AV51*1),2)*BS51),2) -> 0 | CT51: =ROUND((ROUND((AF51*AV51*1),2)*BA51),2) -> 0 | CU51: =AG51 -> 0 | CV51: =(AH51*AV51) -> 0 | CW51: =AI51 -> 0 | CX51: =AJ51 -> 0 | CY51: =(((S51+R51)*AT51)/100) -> 0 | CZ51: =(((S51+R51)*AU51)/100) -> 0 | DN51: 0 | DO51: 0 | DP51: 1 | DQ51: 1 | DU51: 1013 | DV51: ШТ | DW51: ШТ | DX51: 1 | EE51: 59540854 | EF51: 130 | EG51: Сметная стоимость оборудования | EH51: 0 | EJ51: 3 | EK51: 746 | EL51: ТСН-2001.13. Сметная стоимость оборудования | EM51: ТСН-2001.13 | EQ51: 0 | ER51: 0 | ES51: 29029.49 | ET51: 0 | EU51: 0 | EV51: 0 | EW51: 0 | EX51: 0 | EY51: 0 | FQ51: 0 | FR51: =P51 -> 29029.49 | FS51: 0 | FX51: 0 | FY51: 0 | GA51: [255 995,17 / 1,2 / 7,66] + 3% Трансп + 1,2% Заг.скл | GD51: 1 | GF51: -65391095 | GG51: 2 | GH51: 4 | GI51: -2 | GJ51: 0 | GK51: 0 | GL51: =ROUND(IF(AND(BH51=3,BI51=3,FS51<>0),P51,0),2) -> 0 | GM51: =ROUND(O51+X51+Y51,2)+GX51 -> 29029.49 | GN51: =IF(OR(BI51=0,BI51=1),GM51-GX51,0) -> 0 | GO51: =IF(BI51=2,GM51-GX51,0) -> 0 | GP51: =IF(BI51=4,GM51-GX51,0) -> 0 | GR51: 0 | GS51: 2 | GT51: 0 | GV51: =ROUND((GT51),6) -> 0 | GW51: 1 | GX51: =ROUND(HC51*I51,2) -> 0 | HA51: 0 | HB51: 0 | HC51: =GV51*GW51 -> 0 | HE51: 3 | HF51: 1,2 | HS51: 0 | IK51: 0
A52: 17 | B52: 1 | E52: 8 | F52: КА-5 | G52: Панель ЩГП с АВР | H52: ШТ | I52: 1 | J52: 0 | K52: 1 | O52: =ROUND(CP52,2) -> 222365.89 | P52: =ROUND((ROUND((AC52*I52),2)*BC52),2) -> 222365.89 | Q52: =(ROUND((ROUND(((ET52)*AV52*I52),2)*BB52),2)+ROUND((ROUND(((AE52-(EU52))*AV52*I52),2)*BS52),2)) -> 0 | R52: =ROUND((ROUND((AE52*AV52*I52),2)*BS52),2) -> 0 | S52: =ROUND((ROUND((AF52*AV52*I52),2)*BA52),2) -> 0 | T52: =ROUND(CU52*I52,2) -> 0 | U52: =CV52*I52 -> 0 | V52: =CW52*I52 -> 0 | W52: =ROUND(CX52*I52,2) -> 0 | X52: =ROUND(CY52,2) -> 0 | Y52: =ROUND(CZ52,2) -> 0 | AA52: 60252775 | AB52: =ROUND((AC52+AD52+AF52),6) -> 29029.49 | AC52: =ROUND((ES52),6) -> 29029.49 | AD52: =ROUND((((ET52)-(EU52))+AE52),6) -> 0 | AE52: =ROUND((EU52),6) -> 0 | AF52: =ROUND((EV52),6) -> 0 | AG52: =ROUND((AP52),6) -> 0 | AH52: =(EW52) -> 0 | AI52: =(EX52) -> 0 | AJ52: =(AS52) -> 0 | AK52: 29029.49 | AL52: 29029.49 | AM52: 0 | AN52: 0 | AO52: 0 | AP52: 0 | AQ52: 0 | AR52: 0 | AS52: 0 | AT52: 0 | AU52: 0 | AV52: 1 | AW52: 1 | AZ52: 1 | BA52: 1 | BB52: 1 | BC52: 7.66 | BH52: 3 | BI52: 3 | BM52: 746 | BN52: 0 | BP52: 0 | BQ52: 130 | BR52: 0 | BS52: 1 | BT52: 1 | BU52: 1 | BV52: 1 | BW52: 1 | BX52: 1 | BZ52: 0 | CA52: 0 | CE52: 30 | CF52: 0 | CG52: 0 | CM52: 0 | CO52: 0 | CP52: =(P52+Q52+S52) -> 222365.89 | CQ52: =ROUND((ROUND((AC52*1),2)*BC52),2) -> 222365.89 | CR52: =(ROUND((ROUND(((ET52)*AV52*1),2)*BB52),2)+ROUND((ROUND(((AE52-(EU52))*AV52*1),2)*BS52),2)) -> 0 | CS52: =ROUND((ROUND((AE52*AV52*1),2)*BS52),2) -> 0 | CT52: =ROUND((ROUND((AF52*AV52*1),2)*BA52),2) -> 0 | CU52: =AG52 -> 0 | CV52: =(AH52*AV52) -> 0 | CW52: =AI52 -> 0 | CX52: =AJ52 -> 0 | CY52: =(((S52+R52)*AT52)/100) -> 0 | CZ52: =(((S52+R52)*AU52)/100) -> 0 | DN52: 0 | DO52: 0 | DP52: 1 | DQ52: 1 | DU52: 1013 | DV52: ШТ | DW52: ШТ | DX52: 1 | EE52: 59540854 | EF52: 130 | EG52: Сметная стоимость оборудования | EH52: 0 | EJ52: 3 | EK52: 746 | EL52: ТСН-2001.13. Сметная стоимость оборудования | EM52: ТСН-2001.13 | EQ52: 0 | ER52: 29029.49 | ES52: 29029.49 | ET52: 0 | EU52: 0 | EV52: 0 | EW52: 0 | EX52: 0 | EY52: 0 | EZ52: 5 | FC52: 1 | FD52: 18 | FF52: 255995.17 | FQ52: 0 | FR52: =P52 -> 222365.89 | FS52: 0 | FX52: 0 | FY52: 0 | GA52: [255 995,17 / 1,2 / 7,66] + 3% Трансп + 1,2% Заг.скл | GD52: 1 | GF52: -65391095 | GG52: 2 | GH52: 3 | GI52: 5 | GJ52: 0 | GK52: 0 | GL52: =ROUND(IF(AND(BH52=3,BI52=3,FS52<>0),P52,0),2) -> 0 | GM52: =ROUND(O52+X52+Y52,2)+GX52 -> 222365.89 | GN52: =IF(OR(BI52=0,BI52=1),GM52-GX52,0) -> 0 | GO52: =IF(BI52=2,GM52-GX52,0) -> 0 | GP52: =IF(BI52=4,GM52-GX52,0) -> 0 | GR52: 1 | GS52: 1 | GT52: 0 | GV52: =ROUND((GT52),6) -> 0 | GW52: 1 | GX52: =ROUND(HC52*I52,2) -> 0 | HA52: 0 | HB52: 0 | HC52: =GV52*GW52 -> 0 | HE52: 3 | HF52: 1,2 | HS52: 0 | IK52: 0
A53: 19 | B53: 1 | G53: Панель ПЭСПЗ с АВР | AA53: 1 | IK53: 0
A54: 17 | B54: 1 | C54: =ROW(SmtRes!A56) -> 56 | D54: =ROW(EtalonRes!A63) -> 63 | E54: 9 | F54: 4.8-238-3 | G54: Монтаж щитов и стеллажей с блоками резисторов (ящиками сопротивлений) высотой свыше 1700 мм, щита заводского изготовления однорядного или двухрядного открытого исполнения шириной 800 мм | H54: 1 м ширины по фронту | I54: 0.6 | J54: 0 | K54: 0.6 | O54: =ROUND(CP54,2) -> 108.9 | P54: =ROUND((ROUND((AC54*AW54*I54),2)*BC54),2) -> 14.2 | Q54: =(ROUND((ROUND((((ET54*1.1))*AV54*I54),2)*BB54),2)+ROUND((ROUND(((AE54-((EU54*1.1)))*AV54*I54),2)*BS54),2)) -> 39.22 | R54: =ROUND((ROUND((AE54*AV54*I54),2)*BS54),2) -> 4.71 | S54: =ROUND((ROUND((AF54*AV54*I54),2)*BA54),2) -> 55.48 | T54: =ROUND(CU54*I54,2) -> 0 | U54: =CV54*I54 -> 4.2705036 | V54: =CW54*I54 -> 0 | W54: =ROUND(CX54*I54,2) -> 0 | X54: =ROUND(CY54,2) -> 58.38 | Y54: =ROUND(CZ54,2) -> 30.7 | AA54: 60252778 | AB54: =ROUND((AC54+AD54+AF54),6) -> 174.393 | AC54: =ROUND((ES54),6) -> 23.66 | AD54: =ROUND(((((ET54*1.1))-((EU54*1.1)))+AE54),6) -> 62.425 | AE54: =ROUND(((EU54*1.1)),6) -> 7.491 | AF54: =ROUND(((EV54*1.1)),6) -> 88.308 | AG54: =ROUND((AP54),6) -> 0 | AH54: =((EW54*1.1)) -> 6.798 | AI54: =((EX54*1.1)) -> 0 | AJ54: =(AS54) -> 0 | AK54: 160.69 | AL54: 23.66 | AM54: 56.75 | AN54: 6.81 | AO54: 80.28 | AP54: 0 | AQ54: 6.18 | AR54: 0 | AS54: 0 | AT54: 97 | AU54: 51 | AV54: 1.047 | AW54: 1 | AZ54: 1 | BA54: 1 | BB54: 1 | BC54: 1 | BH54: 0 | BI54: 2 | BJ54: ТСН-2001.4 Доп. 79, Сб. 8, т. 238, поз. 3 | BM54: 67 | BN54: 59540665 | BO54: 4.8-238-3 | BP54: 1 | BQ54: 40 | BR54: 0 | BS54: 1 | BT54: 1 | BU54: 1 | BV54: 1 | BW54: 1 | BX54: 1 | BZ54: 97 | CA54: 51 | CE54: 30 | CF54: 0 | CG54: 0 | CM54: 0 | CN54: Поправка: О.П. п.3.4.30.в Наименование: При применении территориальных сметных нормативов для города Москвы затраты, учитывающие напряженные и стесненные условия производства работ (стесненность, сложность складирования и транспортной логистики и т.п.), исчисляются с применением коэффициентов к затратам труда и заработной плате рабочих, машинистов, времени эксплуатации машин и механизмов, стоимости эксплуатации машин в размере: для объектов, расположенных за пределами Третьего транспортного кольца города Москвы, но в пределах Московской кольцевой автомобильной дороги | CO54: 0 | CP54: =(P54+Q54+S54) -> 108.9 | CQ54: =ROUND((ROUND((AC54*AW54*1),2)*BC54),2) -> 23.66 | CR54: =(ROUND((ROUND((((ET54*1.1))*AV54*1),2)*BB54),2)+ROUND((ROUND(((AE54-((EU54*1.1)))*AV54*1),2)*BS54),2)) -> 65.36 | CS54: =ROUND((ROUND((AE54*AV54*1),2)*BS54),2) -> 7.84 | CT54: =ROUND((ROUND((AF54*AV54*1),2)*BA54),2) -> 92.46 | CU54: =AG54 -> 0 | CV54: =(AH54*AV54) -> 7.117506 | CW54: =AI54 -> 0 | CX54: =AJ54 -> 0 | CY54: =(((S54+R54)*AT54)/100) -> 58.3843 | CZ54: =(((S54+R54)*AU54)/100) -> 30.6969 | DB54: 7 | DE54: *1,1 | DF54: *1,1 | DG54: *1,1 | DI54: *1,1 | DJ54: *1,1 | DN54: 0 | DO54: 0 | DP54: 1 | DQ54: 1 | DU54: 1013 | DV54: 1 м ширины по фронту | DW54: 1 м ширины по фронту | DX54: 1 | EE54: 59540733 | EF54: 40 | EG54: Монтаж оборудования | EH54: 0 | EJ54: 2 | EK54: 67 | EL54: ТСН-2001.4-8. Электротехнические установки | EM54: ТСН-2001.4-8-1 | EO54: Поправка: О.П. п.3.4.30.в | EQ54: 0 | ER54: 160.69 | ES54: 23.66 | ET54: 56.75 | EU54: 6.81 | EV54: 80.28 | EW54: 6.18 | EX54: 0 | EY54: 0 | FQ54: 0 | FR54: 0 | FS54: 0 | FX54: 97 | FY54: 51 | GD54: 1 | GF54: 373468362 | GG54: 2 | GH54: 1 | GI54: 2 | GJ54: 0 | GK54: 0 | GL54: =ROUND(IF(AND(BH54=3,BI54=3,FS54<>0),P54,0),2) -> 0 | GM54: =ROUND(O54+X54+Y54,2)+GX54 -> 197.98 | GN54: =IF(OR(BI54=0,BI54=1),GM54-GX54,0) -> 0 | GO54: =IF(BI54=2,GM54-GX54,0) -> 197.98 | GP54: =IF(BI54=4,GM54-GX54,0) -> 0 | GR54: 0 | GS54: 3 | GT54: 0 | GV54: =ROUND((GT54),6) -> 0 | GW54: 1 | GX54: =ROUND(HC54*I54,2) -> 0 | HA54: 0 | HB54: 0 | HC54: =GV54*GW54 -> 0 | HS54: 0 | IK54: 0
A55: 17 | B55: 1 | C55: =ROW(SmtRes!A64) -> 64 | D55: =ROW(EtalonRes!A72) -> 72 | E55: 9 | F55: 4.8-238-3 | G55: Монтаж щитов и стеллажей с блоками резисторов (ящиками сопротивлений) высотой свыше 1700 мм, щита заводского изготовления однорядного или двухрядного открытого исполнения шириной 800 мм | H55: 1 м ширины по фронту | I55: 0.6 | J55: 0 | K55: 0.6 | O55: =ROUND(CP55,2) -> 3764.24 | P55: =ROUND((ROUND((AC55*AW55*I55),2)*BC55),2) -> 113.32 | Q55: =(ROUND((ROUND((((ET55*1.1))*AV55*I55),2)*BB55),2)+ROUND((ROUND(((AE55-((EU55*1.1)))*AV55*I55),2)*BS55),2)) -> 600.07 | R55: =ROUND((ROUND((AE55*AV55*I55),2)*BS55),2) -> 259 | S55: =ROUND((ROUND((AF55*AV55*I55),2)*BA55),2) -> 3050.85 | T55: =ROUND(CU55*I55,2) -> 0 | U55: =CV55*I55 -> 4.2705036 | V55: =CW55*I55 -> 0 | W55: =ROUND(CX55*I55,2) -> 0 | X55: =ROUND(CY55,2) -> 3210.55 | Y55: =ROUND(CZ55,2) -> 1688.02 | AA55: 60252775 | AB55: =ROUND((AC55+AD55+AF55),6) -> 174.393 | AC55: =ROUND((ES55),6) -> 23.66 | AD55: =ROUND(((((ET55*1.1))-((EU55*1.1)))+AE55),6) -> 62.425 | AE55: =ROUND(((EU55*1.1)),6) -> 7.491 | AF55: =ROUND(((EV55*1.1)),6) -> 88.308 | AG55: =ROUND((AP55),6) -> 0 | AH55: =((EW55*1.1)) -> 6.798 | AI55: =((EX55*1.1)) -> 0 | AJ55: =(AS55) -> 0 | AK55: 160.69 | AL55: 23.66 | AM55: 56.75 | AN55: 6.81 | AO55: 80.28 | AP55: 0 | AQ55: 6.18 | AR55: 0 | AS55: 0 | AT55: 97 | AU55: 51 | AV55: 1.047 | AW55: 1 | AZ55: 1 | BA55: 54.99 | BB55: 15.3 | BC55: 7.98 | BH55: 0 | BI55: 2 | BJ55: ТСН-2001.4 Доп. 79, Сб. 8, т. 238, поз. 3 | BM55: 67 | BN55: 59540665 | BO55: 4.8-238-3 | BP55: 1 | BQ55: 40 | BR55: 0 | BS55: 54.99 | BT55: 1 | BU55: 1 | BV55: 1 | BW55: 1 | BX55: 1 | BZ55: 97 | CA55: 51 | CE55: 30 | CF55: 0 | CG55: 0 | CM55: 0 | CN55: Поправка: О.П. п.3.4.30.в Наименование: При применении территориальных сметных нормативов для города Москвы затраты, учитывающие напряженные и стесненные условия производства работ (стесненность, сложность складирования и транспортной логистики и т.п.), исчисляются с применением коэффициентов к затратам труда и заработной плате рабочих, машинистов, времени эксплуатации машин и механизмов, стоимости эксплуатации машин в размере: для объектов, расположенных за пределами Третьего транспортного кольца города Москвы, но в пределах Московской кольцевой автомобильной дороги | CO55: 0 | CP55: =(P55+Q55+S55) -> 3764.24 | CQ55: =ROUND((ROUND((AC55*AW55*1),2)*BC55),2) -> 188.81 | CR55: =(ROUND((ROUND((((ET55*1.1))*AV55*1),2)*BB55),2)+ROUND((ROUND(((AE55-((EU55*1.1)))*AV55*1),2)*BS55),2)) -> 1000.01 | CS55: =ROUND((ROUND((AE55*AV55*1),2)*BS55),2) -> 431.12 | CT55: =ROUND((ROUND((AF55*AV55*1),2)*BA55),2) -> 5084.38 | CU55: =AG55 -> 0 | CV55: =(AH55*AV55) -> 7.117506 | CW55: =AI55 -> 0 | CX55: =AJ55 -> 0 | CY55: =(((S55+R55)*AT55)/100) -> 3210.5545 | CZ55: =(((S55+R55)*AU55)/100) -> 1688.0235 | DB55: 8 | DE55: *1,1 | DF55: *1,1 | DG55: *1,1 | DI55: *1,1 | DJ55: *1,1 | DN55: 0 | DO55: 0 | DP55: 1 | DQ55: 1 | DU55: 1013 | DV55: 1 м ширины по фронту | DW55: 1 м ширины по фронту | DX55: 1 | EE55: 59540733 | EF55: 40 | EG55: Монтаж оборудования | EH55: 0 | EJ55: 2 | EK55: 67 | EL55: ТСН-2001.4-8. Электротехнические установки | EM55: ТСН-2001.4-8-1 | EO55: Поправка: О.П. п.3.4.30.в | EQ55: 0 | ER55: 160.69 | ES55: 23.66 | ET55: 56.75 | EU55: 6.81 | EV55: 80.28 | EW55: 6.18 | EX55: 0 | EY55: 0 | FQ55: 0 | FR55: 0 | FS55: 0 | FX55: 97 | FY55: 51 | GD55: 1 | GF55: 373468362 | GG55: 2 | GH55: 1 | GI55: 2 | GJ55: 0 | GK55: 0 | GL55: =ROUND(IF(AND(BH55=3,BI55=3,FS55<>0),P55,0),2) -> 0 | GM55: =ROUND(O55+X55+Y55,2)+GX55 -> 8662.81 | GN55: =IF(OR(BI55=0,BI55=1),GM55-GX55,0) -> 0 | GO55: =IF(BI55=2,GM55-GX55,0) -> 8662.81 | GP55: =IF(BI55=4,GM55-GX55,0) -> 0 | GR55: 0 | GS55: 3 | GT55: 0 | GV55: =ROUND((GT55),6) -> 0 | GW55: 1 | GX55: =ROUND(HC55*I55,2) -> 0 | HA55: 0 | HB55: 0 | HC55: =GV55*GW55 -> 0 | HS55: 0 | IK55: 0
A56: 18 | B56: 1 | C56: 55 | E56: 9,1 | F56: 1.1-1-58 | G56: Болты строительные с гайками, оцинкованные, М10х100 мм | H56: т | I56: =I54*J56 -> 0.000306 | J56: 0.00051 | K56: 0.00051 | O56: =ROUND(CP56,2) -> 7.53 | P56: =ROUND((ROUND((AC56*AW56*I56),2)*BC56),2) -> 7.53 | Q56: =(ROUND((ROUND(((ET56)*AV56*I56),2)*BB56),2)+ROUND((ROUND(((AE56-(EU56))*AV56*I56),2)*BS56),2)) -> 0 | R56: =ROUND((ROUND((AE56*AV56*I56),2)*BS56),2) -> 0 | S56: =ROUND((ROUND((AF56*AV56*I56),2)*BA56),2) -> 0 | T56: =ROUND(CU56*I56,2) -> 0 | U56: =CV56*I56 -> 0 | V56: =CW56*I56 -> 0 | W56: =ROUND(CX56*I56,2) -> 0 | X56: =ROUND(CY56,2) -> 0 | Y56: =ROUND(CZ56,2) -> 0 | AA56: 60252778 | AB56: =ROUND((AC56+AD56+AF56),6) -> 24609.76 | AC56: =ROUND((ES56),6) -> 24609.76 | AD56: =ROUND((((ET56)-(EU56))+AE56),6) -> 0 | AE56: =ROUND((EU56),6) -> 0 | AF56: =ROUND((EV56),6) -> 0 | AG56: =ROUND((AP56),6) -> 0 | AH56: =(EW56) -> 0 | AI56: =(EX56) -> 0 | AJ56: =(AS56) -> 0 | AK56: 24609.76 | AL56: 24609.76 | AM56: 0 | AN56: 0 | AO56: 0 | AP56: 0 | AQ56: 0 | AR56: 0 | AS56: 0 | AT56: 97 | AU56: 51 | AV56: 1 | AW56: 1 | AZ56: 1 | BA56: 1 | BB56: 1 | BC56: 1 | BH56: 3 | BI56: 2 | BJ56: ТСН-2001.1 Доп. 79, Р. 1, о. 1, поз. 58 | BM56: 67 | BN56: 59540665 | BP56: 0 | BQ56: 40 | BR56: 0 | BS56: 1 | BT56: 1 | BU56: 1 | BV56: 1 | BW56: 1 | BX56: 1 | BZ56: 97 | CA56: 51 | CE56: 30 | CF56: 0 | CG56: 0 | CM56: 0 | CO56: 0 | CP56: =(P56+Q56+S56) -> 7.53 | CQ56: =ROUND((ROUND((AC56*AW56*1),2)*BC56),2) -> 24609.76 | CR56: =(ROUND((ROUND(((ET56)*AV56*1),2)*BB56),2)+ROUND((ROUND(((AE56-(EU56))*AV56*1),2)*BS56),2)) -> 0 | CS56: =ROUND((ROUND((AE56*AV56*1),2)*BS56),2) -> 0 | CT56: =ROUND((ROUND((AF56*AV56*1),2)*BA56),2) -> 0 | CU56: =AG56 -> 0 | CV56: =(AH56*AV56) -> 0 | CW56: =AI56 -> 0 | CX56: =AJ56 -> 0 | CY56: =(((S56+R56)*AT56)/100) -> 0 | CZ56: =(((S56+R56)*AU56)/100) -> 0 | DN56: 0 | DO56: 0 | DP56: 1 | DQ56: 1 | DU56: 1009 | DV56: т | DW56: т | DX56: 1000 | EE56: 59540733 | EF56: 40 | EG56: Монтаж оборудования | EH56: 0 | EJ56: 2 | EK56: 67 | EL56: ТСН-2001.4-8. Электротехнические установки | EM56: ТСН-2001.4-8-1 | EQ56: 0 | ER56: 24609.76 | ES56: 24609.76 | ET56: 0 | EU56: 0 | EV56: 0 | EW56: 0 | EX56: 0 | FQ56: 0 | FR56: 0 | FS56: 0 | FX56: 97 | FY56: 51 | GD56: 1 | GF56: -566361729 | GG56: 2 | GH56: 1 | GI56: -2 | GJ56: 0 | GK56: 0 | GL56: =ROUND(IF(AND(BH56=3,BI56=3,FS56<>0),P56,0),2) -> 0 | GM56: =ROUND(O56+X56+Y56,2)+GX56 -> 7.53 | GN56: =IF(OR(BI56=0,BI56=1),GM56-GX56,0) -> 0 | GO56: =IF(BI56=2,GM56-GX56,0) -> 7.53 | GP56: =IF(BI56=4,GM56-GX56,0) -> 0 | GR56: 0 | GS56: 3 | GT56: 0 | GV56: =ROUND((GT56),6) -> 0 | GW56: 1 | GX56: =ROUND(HC56*I56,2) -> 0 | HA56: 0 | HB56: 0 | HC56: =GV56*GW56 -> 0 | HS56: 0 | IK56: 0
A57: 18 | B57: 1 | C57: 63 | E57: 9,1 | F57: 1.1-1-58 | G57: Болты строительные с гайками, оцинкованные, М10х100 мм | H57: т | I57: =I55*J57 -> 0.000306 | J57: 0.00051 | K57: 0.00051 | O57: =ROUND(CP57,2) -> 38.78 | P57: =ROUND((ROUND((AC57*AW57*I57),2)*BC57),2) -> 38.78 | Q57: =(ROUND((ROUND(((ET57)*AV57*I57),2)*BB57),2)+ROUND((ROUND(((AE57-(EU57))*AV57*I57),2)*BS57),2)) -> 0 | R57: =ROUND((ROUND((AE57*AV57*I57),2)*BS57),2) -> 0 | S57: =ROUND((ROUND((AF57*AV57*I57),2)*BA57),2) -> 0 | T57: =ROUND(CU57*I57,2) -> 0 | U57: =CV57*I57 -> 0 | V57: =CW57*I57 -> 0 | W57: =ROUND(CX57*I57,2) -> 0 | X57: =ROUND(CY57,2) -> 0 | Y57: =ROUND(CZ57,2) -> 0 | AA57: 60252775 | AB57: =ROUND((AC57+AD57+AF57),6) -> 24609.76 | AC57: =ROUND((ES57),6) -> 24609.76 | AD57: =ROUND((((ET57)-(EU57))+AE57),6) -> 0 | AE57: =ROUND((EU57),6) -> 0 | AF57: =ROUND((EV57),6) -> 0 | AG57: =ROUND((AP57),6) -> 0 | AH57: =(EW57) -> 0 | AI57: =(EX57) -> 0 | AJ57: =(AS57) -> 0 | AK57: 24609.76 | AL57: 24609.76 | AM57: 0 | AN57: 0 | AO57: 0 | AP57: 0 | AQ57: 0 | AR57: 0 | AS57: 0 | AT57: 97 | AU57: 51 | AV57: 1 | AW57: 1 | AZ57: 1 | BA57: 1 | BB57: 1 | BC57: 5.15 | BH57: 3 | BI57: 2 | BJ57: ТСН-2001.1 Доп. 79, Р. 1, о. 1, поз. 58 | BM57: 67 | BN57: 59540665 | BO57: 1.1-1-58 | BP57: 1 | BQ57: 40 | BR57: 0 | BS57: 1 | BT57: 1 | BU57: 1 | BV57: 1 | BW57: 1 | BX57: 1 | BZ57: 97 | CA57: 51 | CE57: 30 | CF57: 0 | CG57: 0 | CM57: 0 | CO57: 0 | CP57: =(P57+Q57+S57) -> 38.78 | CQ57: =ROUND((ROUND((AC57*AW57*1),2)*BC57),2) -> 126740.26 | CR57: =(ROUND((ROUND(((ET57)*AV57*1),2)*BB57),2)+ROUND((ROUND(((AE57-(EU57))*AV57*1),2)*BS57),2)) -> 0 | CS57: =ROUND((ROUND((AE57*AV57*1),2)*BS57),2) -> 0 | CT57: =ROUND((ROUND((AF57*AV57*1),2)*BA57),2) -> 0 | CU57: =AG57 -> 0 | CV57: =(AH57*AV57) -> 0 | CW57: =AI57 -> 0 | CX57: =AJ57 -> 0 | CY57: =(((S57+R57)*AT57)/100) -> 0 | CZ57: =(((S57+R57)*AU57)/100) -> 0 | DN57: 0 | DO57: 0 | DP57: 1 | DQ57: 1 | DU57: 1009 | DV57: т | DW57: т | DX57: 1000 | EE57: 59540733 | EF57: 40 | EG57: Монтаж оборудования | EH57: 0 | EJ57: 2 | EK57: 67 | EL57: ТСН-2001.4-8. Электротехнические установки | EM57: ТСН-2001.4-8-1 | EQ57: 0 | ER57: 24609.76 | ES57: 24609.76 | ET57: 0 | EU57: 0 | EV57: 0 | EW57: 0 | EX57: 0 | FQ57: 0 | FR57: 0 | FS57: 0 | FX57: 97 | FY57: 51 | GD57: 1 | GF57: -566361729 | GG57: 2 | GH57: 1 | GI57: 2 | GJ57: 0 | GK57: 0 | GL57: =ROUND(IF(AND(BH57=3,BI57=3,FS57<>0),P57,0),2) -> 0 | GM57: =ROUND(O57+X57+Y57,2)+GX57 -> 38.78 | GN57: =IF(OR(BI57=0,BI57=1),GM57-GX57,0) -> 0 | GO57: =IF(BI57=2,GM57-GX57,0) -> 38.78 | GP57: =IF(BI57=4,GM57-GX57,0) -> 0 | GR57: 0 | GS57: 3 | GT57: 0 | GV57: =ROUND((GT57),6) -> 0 | GW57: 1 | GX57: =ROUND(HC57*I57,2) -> 0 | HA57: 0 | HB57: 0 | HC57: =GV57*GW57 -> 0 | HS57: 0 | IK57: 0
A58: 17 | B58: 1 | E58: 10 | F58: КА-6 | G58: Панель ПЭСПЗ с АВР | H58: ШТ | I58: 1 | J58: 0 | K58: 1 | O58: =ROUND(CP58,2) -> 34835.39 | P58: =ROUND((ROUND((AC58*I58),2)*BC58),2) -> 34835.39 | Q58: =(ROUND((ROUND(((ET58)*AV58*I58),2)*BB58),2)+ROUND((ROUND(((AE58-(EU58))*AV58*I58),2)*BS58),2)) -> 0 | R58: =ROUND((ROUND((AE58*AV58*I58),2)*BS58),2) -> 0 | S58: =ROUND((ROUND((AF58*AV58*I58),2)*BA58),2) -> 0 | T58: =ROUND(CU58*I58,2) -> 0 | U58: =CV58*I58 -> 0 | V58: =CW58*I58 -> 0 | W58: =ROUND(CX58*I58,2) -> 0 | X58: =ROUND(CY58,2) -> 0 | Y58: =ROUND(CZ58,2) -> 0 | AA58: 60252778 | AB58: =ROUND((AC58+AD58+AF58),6) -> 34835.39 | AC58: =ROUND((ES58),6) -> 34835.39 | AD58: =ROUND((((ET58)-(EU58))+AE58),6) -> 0 | AE58: =ROUND((EU58),6) -> 0 | AF58: =ROUND((EV58),6) -> 0 | AG58: =ROUND((AP58),6) -> 0 | AH58: =(EW58) -> 0 | AI58: =(EX58) -> 0 | AJ58: =(AS58) -> 0 | AK58: 34835.39 | AL58: 34835.39 | AM58: 0 | AN58: 0 | AO58: 0 | AP58: 0 | AQ58: 0 | AR58: 0 | AS58: 0 | AT58: 0 | AU58: 0 | AV58: 1 | AW58: 1 | AZ58: 1 | BA58: 1 | BB58: 1 | BC58: 1 | BH58: 3 | BI58: 3 | BM58: 746 | BN58: 0 | BP58: 0 | BQ58: 130 | BR58: 0 | BS58: 1 | BT58: 1 | BU58: 1 | BV58: 1 | BW58: 1 | BX58: 1 | BZ58: 0 | CA58: 0 | CE58: 30 | CF58: 0 | CG58: 0 | CM58: 0 | CO58: 0 | CP58: =(P58+Q58+S58) -> 34835.39 | CQ58: =ROUND((ROUND((AC58*1),2)*BC58),2) -> 34835.39 | CR58: =(ROUND((ROUND(((ET58)*AV58*1),2)*BB58),2)+ROUND((ROUND(((AE58-(EU58))*AV58*1),2)*BS58),2)) -> 0 | CS58: =ROUND((ROUND((AE58*AV58*1),2)*BS58),2) -> 0 | CT58: =ROUND((ROUND((AF58*AV58*1),2)*BA58),2) -> 0 | CU58: =AG58 -> 0 | CV58: =(AH58*AV58) -> 0 | CW58: =AI58 -> 0 | CX58: =AJ58 -> 0 | CY58: =(((S58+R58)*AT58)/100) -> 0 | CZ58: =(((S58+R58)*AU58)/100) -> 0 | DN58: 0 | DO58: 0 | DP58: 1 | DQ58: 1 | DU58: 1013 | DV58: ШТ | DW58: ШТ | DX58: 1 | EE58: 59540854 | EF58: 130 | EG58: Сметная стоимость оборудования | EH58: 0 | EJ58: 3 | EK58: 746 | EL58: ТСН-2001.13. Сметная стоимость оборудования | EM58: ТСН-2001.13 | EQ58: 0 | ER58: 0 | ES58: 34835.39 | ET58: 0 | EU58: 0 | EV58: 0 | EW58: 0 | EX58: 0 | EY58: 0 | FQ58: 0 | FR58: =P58 -> 34835.39 | FS58: 0 | FX58: 0 | FY58: 0 | GA58: [255 995,17 / 7,66] + 3% Трансп + 1,2% Заг.скл | GD58: 1 | GF58: 1893588202 | GG58: 2 | GH58: 4 | GI58: -2 | GJ58: 0 | GK58: 0 | GL58: =ROUND(IF(AND(BH58=3,BI58=3,FS58<>0),P58,0),2) -> 0 | GM58: =ROUND(O58+X58+Y58,2)+GX58 -> 34835.39 | GN58: =IF(OR(BI58=0,BI58=1),GM58-GX58,0) -> 0 | GO58: =IF(BI58=2,GM58-GX58,0) -> 0 | GP58: =IF(BI58=4,GM58-GX58,0) -> 0 | GR58: 0 | GS58: 2 | GT58: 0 | GV58: =ROUND((GT58),6) -> 0 | GW58: 1 | GX58: =ROUND(HC58*I58,2) -> 0 | HA58: 0 | HB58: 0 | HC58: =GV58*GW58 -> 0 | HE58: 3 | HF58: 1,2 | HS58: 0 | IK58: 0
A59: 17 | B59: 1 | E59: 10 | F59: КА-6 | G59: Панель ПЭСПЗ с АВР | H59: ШТ | I59: 1 | J59: 0 | K59: 1 | O59: =ROUND(CP59,2) -> 266839.09 | P59: =ROUND((ROUND((AC59*I59),2)*BC59),2) -> 266839.09 | Q59: =(ROUND((ROUND(((ET59)*AV59*I59),2)*BB59),2)+ROUND((ROUND(((AE59-(EU59))*AV59*I59),2)*BS59),2)) -> 0 | R59: =ROUND((ROUND((AE59*AV59*I59),2)*BS59),2) -> 0 | S59: =ROUND((ROUND((AF59*AV59*I59),2)*BA59),2) -> 0 | T59: =ROUND(CU59*I59,2) -> 0 | U59: =CV59*I59 -> 0 | V59: =CW59*I59 -> 0 | W59: =ROUND(CX59*I59,2) -> 0 | X59: =ROUND(CY59,2) -> 0 | Y59: =ROUND(CZ59,2) -> 0 | AA59: 60252775 | AB59: =ROUND((AC59+AD59+AF59),6) -> 34835.39 | AC59: =ROUND((ES59),6) -> 34835.39 | AD59: =ROUND((((ET59)-(EU59))+AE59),6) -> 0 | AE59: =ROUND((EU59),6) -> 0 | AF59: =ROUND((EV59),6) -> 0 | AG59: =ROUND((AP59),6) -> 0 | AH59: =(EW59) -> 0 | AI59: =(EX59) -> 0 | AJ59: =(AS59) -> 0 | AK59: 34835.39 | AL59: 34835.39 | AM59: 0 | AN59: 0 | AO59: 0 | AP59: 0 | AQ59: 0 | AR59: 0 | AS59: 0 | AT59: 0 | AU59: 0 | AV59: 1 | AW59: 1 | AZ59: 1 | BA59: 1 | BB59: 1 | BC59: 7.66 | BH59: 3 | BI59: 3 | BM59: 746 | BN59: 0 | BP59: 0 | BQ59: 130 | BR59: 0 | BS59: 1 | BT59: 1 | BU59: 1 | BV59: 1 | BW59: 1 | BX59: 1 | BZ59: 0 | CA59: 0 | CE59: 30 | CF59: 0 | CG59: 0 | CM59: 0 | CO59: 0 | CP59: =(P59+Q59+S59) -> 266839.09 | CQ59: =ROUND((ROUND((AC59*1),2)*BC59),2) -> 266839.09 | CR59: =(ROUND((ROUND(((ET59)*AV59*1),2)*BB59),2)+ROUND((ROUND(((AE59-(EU59))*AV59*1),2)*BS59),2)) -> 0 | CS59: =ROUND((ROUND((AE59*AV59*1),2)*BS59),2) -> 0 | CT59: =ROUND((ROUND((AF59*AV59*1),2)*BA59),2) -> 0 | CU59: =AG59 -> 0 | CV59: =(AH59*AV59) -> 0 | CW59: =AI59 -> 0 | CX59: =AJ59 -> 0 | CY59: =(((S59+R59)*AT59)/100) -> 0 | CZ59: =(((S59+R59)*AU59)/100) -> 0 | DN59: 0 | DO59: 0 | DP59: 1 | DQ59: 1 | DU59: 1013 | DV59: ШТ | DW59: ШТ | DX59: 1 | EE59: 59540854 | EF59: 130 | EG59: Сметная стоимость оборудования | EH59: 0 | EJ59: 3 | EK59: 746 | EL59: ТСН-2001.13. Сметная стоимость оборудования | EM59: ТСН-2001.13 | EQ59: 0 | ER59: 34835.39 | ES59: 34835.39 | ET59: 0 | EU59: 0 | EV59: 0 | EW59: 0 | EX59: 0 | EY59: 0 | EZ59: 5 | FC59: 0 | FD59: 18 | FF59: 255995.17 | FQ59: 0 | FR59: =P59 -> 266839.09 | FS59: 0 | FX59: 0 | FY59: 0 | GA59: [255 995,17 / 7,66] + 3% Трансп + 1,2% Заг.скл | GD59: 1 | GF59: 1893588202 | GG59: 2 | GH59: 3 | GI59: 5 | GJ59: 0 | GK59: 0 | GL59: =ROUND(IF(AND(BH59=3,BI59=3,FS59<>0),P59,0),2) -> 0 | GM59: =ROUND(O59+X59+Y59,2)+GX59 -> 266839.09 | GN59: =IF(OR(BI59=0,BI59=1),GM59-GX59,0) -> 0 | GO59: =IF(BI59=2,GM59-GX59,0) -> 0 | GP59: =IF(BI59=4,GM59-GX59,0) -> 0 | GR59: 1 | GS59: 1 | GT59: 0 | GV59: =ROUND((GT59),6) -> 0 | GW59: 1 | GX59: =ROUND(HC59*I59,2) -> 0 | HA59: 0 | HB59: 0 | HC59: =GV59*GW59 -> 0 | HE59: 3 | HF59: 1,2 | HS59: 0 | IK59: 0
A60: 19 | B60: 1 | G60: УКРМ 50-10 | AA60: 1 | IK60: 0
A61: 17 | B61: 1 | C61: =ROW(SmtRes!A73) -> 73 | D61: =ROW(EtalonRes!A82) -> 82 | E61: 11 | F61: 4.8-240-2 | G61: Монтаж пультов и шкафов управления, пульта управления напольного, высотой до 1200 мм, глубиной и шириной по фронту до 700х1000 мм | H61: 1 ШТ. | I61: 2 | J61: 0 | K61: 2 | O61: =ROUND(CP61,2) -> 195.2 | P61: =ROUND((ROUND((AC61*AW61*I61),2)*BC61),2) -> 12.22 | Q61: =(ROUND((ROUND((((ET61*1.1))*AV61*I61),2)*BB61),2)+ROUND((ROUND(((AE61-((EU61*1.1)))*AV61*I61),2)*BS61),2)) -> 121.34 | R61: =ROUND((ROUND((AE61*AV61*I61),2)*BS61),2) -> 22.39 | S61: =ROUND((ROUND((AF61*AV61*I61),2)*BA61),2) -> 61.64 | T61: =ROUND(CU61*I61,2) -> 0 | U61: =CV61*I61 -> 4.745004 | V61: =CW61*I61 -> 0 | W61: =ROUND(CX61*I61,2) -> 0 | X61: =ROUND(CY61,2) -> 81.51 | Y61: =ROUND(CZ61,2) -> 42.86 | AA61: 60252778 | AB61: =ROUND((AC61+AD61+AF61),6) -> 93.494 | AC61: =ROUND((ES61),6) -> 6.11 | AD61: =ROUND(((((ET61*1.1))-((EU61*1.1)))+AE61),6) -> 57.948 | AE61: =ROUND(((EU61*1.1)),6) -> 10.692 | AF61: =ROUND(((EV61*1.1)),6) -> 29.436 | AG61: =ROUND((AP61),6) -> 0 | AH61: =((EW61*1.1)) -> 2.266 | AI61: =((EX61*1.1)) -> 0 | AJ61: =(AS61) -> 0 | AK61: 85.55 | AL61: 6.11 | AM61: 52.68 | AN61: 9.72 | AO61: 26.76 | AP61: 0 | AQ61: 2.06 | AR61: 0 | AS61: 0 | AT61: 97 | AU61: 51 | AV61: 1.047 | AW61: 1 | AZ61: 1 | BA61: 1 | BB61: 1 | BC61: 1 | BH61: 0 | BI61: 2 | BJ61: ТСН-2001.4 Доп. 79, Сб. 8, т. 240, поз. 2 | BM61: 67 | BN61: 59540665 | BO61: 4.8-240-2 | BP61: 1 | BQ61: 40 | BR61: 0 | BS61: 1 | BT61: 1 | BU61: 1 | BV61: 1 | BW61: 1 | BX61: 1 | BZ61: 97 | CA61: 51 | CE61: 30 | CF61: 0 | CG61: 0 | CM61: 0 | CN61: Поправка: Гл.12.Прил.8.п.8. 5_12.00.01.11.003 Наименование: При наличии усложненных условий производства работ (стесненность, сложность складирования и транспортной логистики, наличие в зоне производства работ действующего технологического оборудования или движения технологического транспорта и т.п.) для объектов, расположенных за пределами территории круговой магистральной системы улиц "Садовое кольцо" и за пределами Третьего транспортного кольца города Москвы пунктов "а" и "б", но в пределах Московской кольцевой автомобильной дороги | CO61: 0 | CP61: =(P61+Q61+S61) -> 195.2 | CQ61: =ROUND((ROUND((AC61*AW61*1),2)*BC61),2) -> 6.11 | CR61: =(ROUND((ROUND((((ET61*1.1))*AV61*1),2)*BB61),2)+ROUND((ROUND(((AE61-((EU61*1.1)))*AV61*1),2)*BS61),2)) -> 60.67 | CS61: =ROUND((ROUND((AE61*AV61*1),2)*BS61),2) -> 11.19 | CT61: =ROUND((ROUND((AF61*AV61*1),2)*BA61),2) -> 30.82 | CU61: =AG61 -> 0 | CV61: =(AH61*AV61) -> 2.372502 | CW61: =AI61 -> 0 | CX61: =AJ61 -> 0 | CY61: =(((S61+R61)*AT61)/100) -> 81.5091 | CZ61: =(((S61+R61)*AU61)/100) -> 42.8553 | DE61: *1,1 | DF61: *1,1 | DG61: *1,1 | DI61: *1,1 | DJ61: *1,1 | DN61: 0 | DO61: 0 | DP61: 1 | DQ61: 1 | DU61: 1013 | DV61: 1 ШТ. | DW61: 1 ШТ. | DX61: 1 | EE61: 59540733 | EF61: 40 | EG61: Монтаж оборудования | EH61: 0 | EJ61: 2 | EK61: 67 | EL61: ТСН-2001.4-8. Электротехнические установки | EM61: ТСН-2001.4-8-1 | EO61: Поправка: Гл.12.Прил.8.п.8. 5_12.00.01.11.003 | EQ61: 0 | ER61: 85.55 | ES61: 6.11 | ET61: 52.68 | EU61: 9.72 | EV61: 26.76 | EW61: 2.06 | EX61: 0 | EY61: 0 | FQ61: 0 | FR61: 0 | FS61: 0 | FX61: 97 | FY61: 51 | GD61: 1 | GF61: 2083079522 | GG61: 2 | GH61: 1 | GI61: 2 | GJ61: 0 | GK61: 0 | GL61: =ROUND(IF(AND(BH61=3,BI61=3,FS61<>0),P61,0),2) -> 0 | GM61: =ROUND(O61+X61+Y61,2)+GX61 -> 319.57 | GN61: =IF(OR(BI61=0,BI61=1),GM61-GX61,0) -> 0 | GO61: =IF(BI61=2,GM61-GX61,0) -> 319.57 | GP61: =IF(BI61=4,GM61-GX61,0) -> 0 | GR61: 0 | GS61: 3 | GT61: 0 | GV61: =ROUND((GT61),6) -> 0 | GW61: 1 | GX61: =ROUND(HC61*I61,2) -> 0 | HA61: 0 | HB61: 0 | HC61: =GV61*GW61 -> 0 | HS61: 0 | IK61: 0
A62: 17 | B62: 1 | C62: =ROW(SmtRes!A82) -> 82 | D62: =ROW(EtalonRes!A92) -> 92 | E62: 11 | F62: 4.8-240-2 | G62: Монтаж пультов и шкафов управления, пульта управления напольного, высотой до 1200 мм, глубиной и шириной по фронту до 700х1000 мм | H62: 1 ШТ. | I62: 2 | J62: 0 | K62: 2 | O62: =ROUND(CP62,2) -> 5773.86 | P62: =ROUND((ROUND((AC62*AW62*I62),2)*BC62),2) -> 131 | Q62: =(ROUND((ROUND((((ET62*1.1))*AV62*I62),2)*BB62),2)+ROUND((ROUND(((AE62-((EU62*1.1)))*AV62*I62),2)*BS62),2)) -> 2253.28 | R62: =ROUND((ROUND((AE62*AV62*I62),2)*BS62),2) -> 1231.23 | S62: =ROUND((ROUND((AF62*AV62*I62),2)*BA62),2) -> 3389.58 | T62: =ROUND(CU62*I62,2) -> 0 | U62: =CV62*I62 -> 4.745004 | V62: =CW62*I62 -> 0 | W62: =ROUND(CX62*I62,2) -> 0 | X62: =ROUND(CY62,2) -> 4482.19 | Y62: =ROUND(CZ62,2) -> 2356.61 | AA62: 60252775 | AB62: =ROUND((AC62+AD62+AF62),6) -> 93.494 | AC62: =ROUND((ES62),6) -> 6.11 | AD62: =ROUND(((((ET62*1.1))-((EU62*1.1)))+AE62),6) -> 57.948 | AE62: =ROUND(((EU62*1.1)),6) -> 10.692 | AF62: =ROUND(((EV62*1.1)),6) -> 29.436 | AG62: =ROUND((AP62),6) -> 0 | AH62: =((EW62*1.1)) -> 2.266 | AI62: =((EX62*1.1)) -> 0 | AJ62: =(AS62) -> 0 | AK62: 85.55 | AL62: 6.11 | AM62: 52.68 | AN62: 9.72 | AO62: 26.76 | AP62: 0 | AQ62: 2.06 | AR62: 0 | AS62: 0 | AT62: 97 | AU62: 51 | AV62: 1.047 | AW62: 1 | AZ62: 1 | BA62: 54.99 | BB62: 18.57 | BC62: 10.72 | BH62: 0 | BI62: 2 | BJ62: ТСН-2001.4 Доп. 79, Сб. 8, т. 240, поз. 2 | BM62: 67 | BN62: 59540665 | BO62: 4.8-240-2 | BP62: 1 | BQ62: 40 | BR62: 0 | BS62: 54.99 | BT62: 1 | BU62: 1 | BV62: 1 | BW62: 1 | BX62: 1 | BZ62: 97 | CA62: 51 | CE62: 30 | CF62: 0 | CG62: 0 | CM62: 0 | CN62: Поправка: Гл.12.Прил.8.п.8. 5_12.00.01.11.003 Наименование: При наличии усложненных условий производства работ (стесненность, сложность складирования и транспортной логистики, наличие в зоне производства работ действующего технологического оборудования или движения технологического транспорта и т.п.) для объектов, расположенных за пределами территории круговой магистральной системы улиц "Садовое кольцо" и за пределами Третьего транспортного кольца города Москвы пунктов "а" и "б", но в пределах Московской кольцевой автомобильной дороги | CO62: 0 | CP62: =(P62+Q62+S62) -> 5773.86 | CQ62: =ROUND((ROUND((AC62*AW62*1),2)*BC62),2) -> 65.5 | CR62: =(ROUND((ROUND((((ET62*1.1))*AV62*1),2)*BB62),2)+ROUND((ROUND(((AE62-((EU62*1.1)))*AV62*1),2)*BS62),2)) -> 1126.64 | CS62: =ROUND((ROUND((AE62*AV62*1),2)*BS62),2) -> 615.34 | CT62: =ROUND((ROUND((AF62*AV62*1),2)*BA62),2) -> 1694.79 | CU62: =AG62 -> 0 | CV62: =(AH62*AV62) -> 2.372502 | CW62: =AI62 -> 0 | CX62: =AJ62 -> 0 | CY62: =(((S62+R62)*AT62)/100) -> 4482.1857 | CZ62: =(((S62+R62)*AU62)/100) -> 2356.6131 | DE62: *1,1 | DF62: *1,1 | DG62: *1,1 | DI62: *1,1 | DJ62: *1,1 | DN62: 0 | DO62: 0 | DP62: 1 | DQ62: 1 | DU62: 1013 | DV62: 1 ШТ. | DW62: 1 ШТ. | DX62: 1 | EE62: 59540733 | EF62: 40 | EG62: Монтаж оборудования | EH62: 0 | EJ62: 2 | EK62: 67 | EL62: ТСН-2001.4-8. Электротехнические установки | EM62: ТСН-2001.4-8-1 | EO62: Поправка: Гл.12.Прил.8.п.8. 5_12.00.01.11.003 | EQ62: 0 | ER62: 85.55 | ES62: 6.11 | ET62: 52.68 | EU62: 9.72 | EV62: 26.76 | EW62: 2.06 | EX62: 0 | EY62: 0 | FQ62: 0 | FR62: 0 | FS62: 0 | FX62: 97 | FY62: 51 | GD62: 1 | GF62: 2083079522 | GG62: 2 | GH62: 1 | GI62: 2 | GJ62: 0 | GK62: 0 | GL62: =ROUND(IF(AND(BH62=3,BI62=3,FS62<>0),P62,0),2) -> 0 | GM62: =ROUND(O62+X62+Y62,2)+GX62 -> 12612.66 | GN62: =IF(OR(BI62=0,BI62=1),GM62-GX62,0) -> 0 | GO62: =IF(BI62=2,GM62-GX62,0) -> 12612.66 | GP62: =IF(BI62=4,GM62-GX62,0) -> 0 | GR62: 0 | GS62: 3 | GT62: 0 | GV62: =ROUND((GT62),6) -> 0 | GW62: 1 | GX62: =ROUND(HC62*I62,2) -> 0 | HA62: 0 | HB62: 0 | HC62: =GV62*GW62 -> 0 | HS62: 0 | IK62: 0
A63: 18 | B63: 1 | C63: 73 | E63: 11,1 | F63: 1.1-1-58 | G63: Болты строительные с гайками, оцинкованные, М10х100 мм | H63: т | I63: =I61*J63 -> 0.0002 | J63: 0.0001 | K63: 0.0001 | O63: =ROUND(CP63,2) -> 4.92 | P63: =ROUND((ROUND((AC63*AW63*I63),2)*BC63),2) -> 4.92 | Q63: =(ROUND((ROUND(((ET63)*AV63*I63),2)*BB63),2)+ROUND((ROUND(((AE63-(EU63))*AV63*I63),2)*BS63),2)) -> 0 | R63: =ROUND((ROUND((AE63*AV63*I63),2)*BS63),2) -> 0 | S63: =ROUND((ROUND((AF63*AV63*I63),2)*BA63),2) -> 0 | T63: =ROUND(CU63*I63,2) -> 0 | U63: =CV63*I63 -> 0 | V63: =CW63*I63 -> 0 | W63: =ROUND(CX63*I63,2) -> 0 | X63: =ROUND(CY63,2) -> 0 | Y63: =ROUND(CZ63,2) -> 0 | AA63: 60252778 | AB63: =ROUND((AC63+AD63+AF63),6) -> 24609.76 | AC63: =ROUND((ES63),6) -> 24609.76 | AD63: =ROUND((((ET63)-(EU63))+AE63),6) -> 0 | AE63: =ROUND((EU63),6) -> 0 | AF63: =ROUND((EV63),6) -> 0 | AG63: =ROUND((AP63),6) -> 0 | AH63: =(EW63) -> 0 | AI63: =(EX63) -> 0 | AJ63: =(AS63) -> 0 | AK63: 24609.76 | AL63: 24609.76 | AM63: 0 | AN63: 0 | AO63: 0 | AP63: 0 | AQ63: 0 | AR63: 0 | AS63: 0 | AT63: 97 | AU63: 51 | AV63: 1 | AW63: 1 | AZ63: 1 | BA63: 1 | BB63: 1 | BC63: 1 | BH63: 3 | BI63: 2 | BJ63: ТСН-2001.1 Доп. 79, Р. 1, о. 1, поз. 58 | BM63: 67 | BN63: 59540665 | BP63: 0 | BQ63: 40 | BR63: 0 | BS63: 1 | BT63: 1 | BU63: 1 | BV63: 1 | BW63: 1 | BX63: 1 | BZ63: 97 | CA63: 51 | CE63: 30 | CF63: 0 | CG63: 0 | CM63: 0 | CN63: Поправка: Гл.12.Прил.8.п.8. 5_12.00.01.11.003 Наименование: При наличии усложненных условий производства работ (стесненность, сложность складирования и транспортной логистики, наличие в зоне производства работ действующего технологического оборудования или движения технологического транспорта и т.п.) для объектов, расположенных за пределами территории круговой магистральной системы улиц "Садовое кольцо" и за пределами Третьего транспортного кольца города Москвы пунктов "а" и "б", но в пределах Московской кольцевой автомобильной дороги | CO63: 0 | CP63: =(P63+Q63+S63) -> 4.92 | CQ63: =ROUND((ROUND((AC63*AW63*1),2)*BC63),2) -> 24609.76 | CR63: =(ROUND((ROUND(((ET63)*AV63*1),2)*BB63),2)+ROUND((ROUND(((AE63-(EU63))*AV63*1),2)*BS63),2)) -> 0 | CS63: =ROUND((ROUND((AE63*AV63*1),2)*BS63),2) -> 0 | CT63: =ROUND((ROUND((AF63*AV63*1),2)*BA63),2) -> 0 | CU63: =AG63 -> 0 | CV63: =(AH63*AV63) -> 0 | CW63: =AI63 -> 0 | CX63: =AJ63 -> 0 | CY63: =(((S63+R63)*AT63)/100) -> 0 | CZ63: =(((S63+R63)*AU63)/100) -> 0 | DN63: 0 | DO63: 0 | DP63: 1 | DQ63: 1 | DU63: 1009 | DV63: т | DW63: т | DX63: 1000 | EE63: 59540733 | EF63: 40 | EG63: Монтаж оборудования | EH63: 0 | EJ63: 2 | EK63: 67 | EL63: ТСН-2001.4-8. Электротехнические установки | EM63: ТСН-2001.4-8-1 | EO63: Поправка: Гл.12.Прил.8.п.8. 5_12.00.01.11.003 | EQ63: 0 | ER63: 24609.76 | ES63: 24609.76 | ET63: 0 | EU63: 0 | EV63: 0 | EW63: 0 | EX63: 0 | FQ63: 0 | FR63: 0 | FS63: 0 | FX63: 97 | FY63: 51 | GD63: 1 | GF63: -566361729 | GG63: 2 | GH63: 1 | GI63: -2 | GJ63: 0 | GK63: 0 | GL63: =ROUND(IF(AND(BH63=3,BI63=3,FS63<>0),P63,0),2) -> 0 | GM63: =ROUND(O63+X63+Y63,2)+GX63 -> 4.92 | GN63: =IF(OR(BI63=0,BI63=1),GM63-GX63,0) -> 0 | GO63: =IF(BI63=2,GM63-GX63,0) -> 4.92 | GP63: =IF(BI63=4,GM63-GX63,0) -> 0 | GR63: 0 | GS63: 3 | GT63: 0 | GV63: =ROUND((GT63),6) -> 0 | GW63: 1 | GX63: =ROUND(HC63*I63,2) -> 0 | HA63: 0 | HB63: 0 | HC63: =GV63*GW63 -> 0 | HS63: 0 | IK63: 0
A64: 18 | B64: 1 | C64: 82 | E64: 11,1 | F64: 1.1-1-58 | G64: Болты строительные с гайками, оцинкованные, М10х100 мм | H64: т | I64: =I62*J64 -> 0.0002 | J64: 0.0001 | K64: 0.0001 | O64: =ROUND(CP64,2) -> 25.34 | P64: =ROUND((ROUND((AC64*AW64*I64),2)*BC64),2) -> 25.34 | Q64: =(ROUND((ROUND(((ET64)*AV64*I64),2)*BB64),2)+ROUND((ROUND(((AE64-(EU64))*AV64*I64),2)*BS64),2)) -> 0 | R64: =ROUND((ROUND((AE64*AV64*I64),2)*BS64),2) -> 0 | S64: =ROUND((ROUND((AF64*AV64*I64),2)*BA64),2) -> 0 | T64: =ROUND(CU64*I64,2) -> 0 | U64: =CV64*I64 -> 0 | V64: =CW64*I64 -> 0 | W64: =ROUND(CX64*I64,2) -> 0 | X64: =ROUND(CY64,2) -> 0 | Y64: =ROUND(CZ64,2) -> 0 | AA64: 60252775 | AB64: =ROUND((AC64+AD64+AF64),6) -> 24609.76 | AC64: =ROUND((ES64),6) -> 24609.76 | AD64: =ROUND((((ET64)-(EU64))+AE64),6) -> 0 | AE64: =ROUND((EU64),6) -> 0 | AF64: =ROUND((EV64),6) -> 0 | AG64: =ROUND((AP64),6) -> 0 | AH64: =(EW64) -> 0 | AI64: =(EX64) -> 0 | AJ64: =(AS64) -> 0 | AK64: 24609.76 | AL64: 24609.76 | AM64: 0 | AN64: 0 | AO64: 0 | AP64: 0 | AQ64: 0 | AR64: 0 | AS64: 0 | AT64: 97 | AU64: 51 | AV64: 1 | AW64: 1 | AZ64: 1 | BA64: 1 | BB64: 1 | BC64: 5.15 | BH64: 3 | BI64: 2 | BJ64: ТСН-2001.1 Доп. 79, Р. 1, о. 1, поз. 58 | BM64: 67 | BN64: 59540665 | BO64: 1.1-1-58 | BP64: 1 | BQ64: 40 | BR64: 0 | BS64: 1 | BT64: 1 | BU64: 1 | BV64: 1 | BW64: 1 | BX64: 1 | BZ64: 97 | CA64: 51 | CE64: 30 | CF64: 0 | CG64: 0 | CM64: 0 | CN64: Поправка: Гл.12.Прил.8.п.8. 5_12.00.01.11.003 Наименование: При наличии усложненных условий производства работ (стесненность, сложность складирования и транспортной логистики, наличие в зоне производства работ действующего технологического оборудования или движения технологического транспорта и т.п.) для объектов, расположенных за пределами территории круговой магистральной системы улиц "Садовое кольцо" и за пределами Третьего транспортного кольца города Москвы пунктов "а" и "б", но в пределах Московской кольцевой автомобильной дороги | CO64: 0 | CP64: =(P64+Q64+S64) -> 25.34 | CQ64: =ROUND((ROUND((AC64*AW64*1),2)*BC64),2) -> 126740.26 | CR64: =(ROUND((ROUND(((ET64)*AV64*1),2)*BB64),2)+ROUND((ROUND(((AE64-(EU64))*AV64*1),2)*BS64),2)) -> 0 | CS64: =ROUND((ROUND((AE64*AV64*1),2)*BS64),2) -> 0 | CT64: =ROUND((ROUND((AF64*AV64*1),2)*BA64),2) -> 0 | CU64: =AG64 -> 0 | CV64: =(AH64*AV64) -> 0 | CW64: =AI64 -> 0 | CX64: =AJ64 -> 0 | CY64: =(((S64+R64)*AT64)/100) -> 0 | CZ64: =(((S64+R64)*AU64)/100) -> 0 | DN64: 0 | DO64: 0 | DP64: 1 | DQ64: 1 | DU64: 1009 | DV64: т | DW64: т | DX64: 1000 | EE64: 59540733 | EF64: 40 | EG64: Монтаж оборудования | EH64: 0 | EJ64: 2 | EK64: 67 | EL64: ТСН-2001.4-8. Электротехнические установки | EM64: ТСН-2001.4-8-1 | EO64: Поправка: Гл.12.Прил.8.п.8. 5_12.00.01.11.003 | EQ64: 0 | ER64: 24609.76 | ES64: 24609.76 | ET64: 0 | EU64: 0 | EV64: 0 | EW64: 0 | EX64: 0 | FQ64: 0 | FR64: 0 | FS64: 0 | FX64: 97 | FY64: 51 | GD64: 1 | GF64: -566361729 | GG64: 2 | GH64: 1 | GI64: 2 | GJ64: 0 | GK64: 0 | GL64: =ROUND(IF(AND(BH64=3,BI64=3,FS64<>0),P64,0),2) -> 0 | GM64: =ROUND(O64+X64+Y64,2)+GX64 -> 25.34 | GN64: =IF(OR(BI64=0,BI64=1),GM64-GX64,0) -> 0 | GO64: =IF(BI64=2,GM64-GX64,0) -> 25.34 | GP64: =IF(BI64=4,GM64-GX64,0) -> 0 | GR64: 0 | GS64: 3 | GT64: 0 | GV64: =ROUND((GT64),6) -> 0 | GW64: 1 | GX64: =ROUND(HC64*I64,2) -> 0 | HA64: 0 | HB64: 0 | HC64: =GV64*GW64 -> 0 | HS64: 0 | IK64: 0
A65: 17 | B65: 1 | E65: 12 | F65: КА-7 | G65: УКРМ 50-10 | H65: ШТ | I65: 2 | J65: 0 | K65: 2 | O65: =ROUND(CP65,2) -> 15041.14 | P65: =ROUND((ROUND((AC65*I65),2)*BC65),2) -> 15041.14 | Q65: =(ROUND((ROUND(((ET65)*AV65*I65),2)*BB65),2)+ROUND((ROUND(((AE65-(EU65))*AV65*I65),2)*BS65),2)) -> 0 | R65: =ROUND((ROUND((AE65*AV65*I65),2)*BS65),2) -> 0 | S65: =ROUND((ROUND((AF65*AV65*I65),2)*BA65),2) -> 0 | T65: =ROUND(CU65*I65,2) -> 0 | U65: =CV65*I65 -> 0 | V65: =CW65*I65 -> 0 | W65: =ROUND(CX65*I65,2) -> 0 | X65: =ROUND(CY65,2) -> 0 | Y65: =ROUND(CZ65,2) -> 0 | AA65: 60252778 | AB65: =ROUND((AC65+AD65+AF65),6) -> 7520.57 | AC65: =ROUND((ES65),6) -> 7520.57 | AD65: =ROUND((((ET65)-(EU65))+AE65),6) -> 0 | AE65: =ROUND((EU65),6) -> 0 | AF65: =ROUND((EV65),6) -> 0 | AG65: =ROUND((AP65),6) -> 0 | AH65: =(EW65) -> 0 | AI65: =(EX65) -> 0 | AJ65: =(AS65) -> 0 | AK65: 7520.57 | AL65: 7520.57 | AM65: 0 | AN65: 0 | AO65: 0 | AP65: 0 | AQ65: 0 | AR65: 0 | AS65: 0 | AT65: 0 | AU65: 0 | AV65: 1 | AW65: 1 | AZ65: 1 | BA65: 1 | BB65: 1 | BC65: 1 | BH65: 3 | BI65: 3 | BM65: 746 | BN65: 0 | BP65: 0 | BQ65: 130 | BR65: 0 | BS65: 1 | BT65: 1 | BU65: 1 | BV65: 1 | BW65: 1 | BX65: 1 | BZ65: 0 | CA65: 0 | CE65: 30 | CF65: 0 | CG65: 0 | CM65: 0 | CO65: 0 | CP65: =(P65+Q65+S65) -> 15041.14 | CQ65: =ROUND((ROUND((AC65*1),2)*BC65),2) -> 7520.57 | CR65: =(ROUND((ROUND(((ET65)*AV65*1),2)*BB65),2)+ROUND((ROUND(((AE65-(EU65))*AV65*1),2)*BS65),2)) -> 0 | CS65: =ROUND((ROUND((AE65*AV65*1),2)*BS65),2) -> 0 | CT65: =ROUND((ROUND((AF65*AV65*1),2)*BA65),2) -> 0 | CU65: =AG65 -> 0 | CV65: =(AH65*AV65) -> 0 | CW65: =AI65 -> 0 | CX65: =AJ65 -> 0 | CY65: =(((S65+R65)*AT65)/100) -> 0 | CZ65: =(((S65+R65)*AU65)/100) -> 0 | DN65: 0 | DO65: 0 | DP65: 1 | DQ65: 1 | DU65: 1013 | DV65: ШТ | DW65: ШТ | DX65: 1 | EE65: 59540854 | EF65: 130 | EG65: Сметная стоимость оборудования | EH65: 0 | EJ65: 3 | EK65: 746 | EL65: ТСН-2001.13. Сметная стоимость оборудования | EM65: ТСН-2001.13 | EQ65: 0 | ER65: 0 | ES65: 7520.57 | ET65: 0 | EU65: 0 | EV65: 0 | EW65: 0 | EX65: 0 | EY65: 0 | FQ65: 0 | FR65: =P65 -> 15041.14 | FS65: 0 | FX65: 0 | FY65: 0 | GA65: [66 319,7 / 1,2 / 7,66] + 3% Трансп + 1,2% Заг.скл | GD65: 1 | GF65: 1741110623 | GG65: 2 | GH65: 4 | GI65: -2 | GJ65: 0 | GK65: 0 | GL65: =ROUND(IF(AND(BH65=3,BI65=3,FS65<>0),P65,0),2) -> 0 | GM65: =ROUND(O65+X65+Y65,2)+GX65 -> 15041.14 | GN65: =IF(OR(BI65=0,BI65=1),GM65-GX65,0) -> 0 | GO65: =IF(BI65=2,GM65-GX65,0) -> 0 | GP65: =IF(BI65=4,GM65-GX65,0) -> 0 | GR65: 0 | GS65: 2 | GT65: 0 | GV65: =ROUND((GT65),6) -> 0 | GW65: 1 | GX65: =ROUND(HC65*I65,2) -> 0 | HA65: 0 | HB65: 0 | HC65: =GV65*GW65 -> 0 | HE65: 3 | HF65: 1,2 | HS65: 0 | IK65: 0
A66: 17 | B66: 1 | E66: 12 | F66: КА-7 | G66: УКРМ 50-10 | H66: ШТ | I66: 2 | J66: 0 | K66: 2 | O66: =ROUND(CP66,2) -> 115215.13 | P66: =ROUND((ROUND((AC66*I66),2)*BC66),2) -> 115215.13 | Q66: =(ROUND((ROUND(((ET66)*AV66*I66),2)*BB66),2)+ROUND((ROUND(((AE66-(EU66))*AV66*I66),2)*BS66),2)) -> 0 | R66: =ROUND((ROUND((AE66*AV66*I66),2)*BS66),2) -> 0 | S66: =ROUND((ROUND((AF66*AV66*I66),2)*BA66),2) -> 0 | T66: =ROUND(CU66*I66,2) -> 0 | U66: =CV66*I66 -> 0 | V66: =CW66*I66 -> 0 | W66: =ROUND(CX66*I66,2) -> 0 | X66: =ROUND(CY66,2) -> 0 | Y66: =ROUND(CZ66,2) -> 0 | AA66: 60252775 | AB66: =ROUND((AC66+AD66+AF66),6) -> 7520.57 | AC66: =ROUND((ES66),6) -> 7520.57 | AD66: =ROUND((((ET66)-(EU66))+AE66),6) -> 0 | AE66: =ROUND((EU66),6) -> 0 | AF66: =ROUND((EV66),6) -> 0 | AG66: =ROUND((AP66),6) -> 0 | AH66: =(EW66) -> 0 | AI66: =(EX66) -> 0 | AJ66: =(AS66) -> 0 | AK66: 7520.57 | AL66: 7520.57 | AM66: 0 | AN66: 0 | AO66: 0 | AP66: 0 | AQ66: 0 | AR66: 0 | AS66: 0 | AT66: 0 | AU66: 0 | AV66: 1 | AW66: 1 | AZ66: 1 | BA66: 1 | BB66: 1 | BC66: 7.66 | BH66: 3 | BI66: 3 | BM66: 746 | BN66: 0 | BP66: 0 | BQ66: 130 | BR66: 0 | BS66: 1 | BT66: 1 | BU66: 1 | BV66: 1 | BW66: 1 | BX66: 1 | BZ66: 0 | CA66: 0 | CE66: 30 | CF66: 0 | CG66: 0 | CM66: 0 | CO66: 0 | CP66: =(P66+Q66+S66) -> 115215.13 | CQ66: =ROUND((ROUND((AC66*1),2)*BC66),2) -> 57607.57 | CR66: =(ROUND((ROUND(((ET66)*AV66*1),2)*BB66),2)+ROUND((ROUND(((AE66-(EU66))*AV66*1),2)*BS66),2)) -> 0 | CS66: =ROUND((ROUND((AE66*AV66*1),2)*BS66),2) -> 0 | CT66: =ROUND((ROUND((AF66*AV66*1),2)*BA66),2) -> 0 | CU66: =AG66 -> 0 | CV66: =(AH66*AV66) -> 0 | CW66: =AI66 -> 0 | CX66: =AJ66 -> 0 | CY66: =(((S66+R66)*AT66)/100) -> 0 | CZ66: =(((S66+R66)*AU66)/100) -> 0 | DN66: 0 | DO66: 0 | DP66: 1 | DQ66: 1 | DU66: 1013 | DV66: ШТ | DW66: ШТ | DX66: 1 | EE66: 59540854 | EF66: 130 | EG66: Сметная стоимость оборудования | EH66: 0 | EJ66: 3 | EK66: 746 | EL66: ТСН-2001.13. Сметная стоимость оборудования | EM66: ТСН-2001.13 | EQ66: 0 | ER66: 7520.57 | ES66: 7520.57 | ET66: 0 | EU66: 0 | EV66: 0 | EW66: 0 | EX66: 0 | EY66: 0 | EZ66: 5 | FC66: 1 | FD66: 18 | FF66: 66319.7 | FQ66: 0 | FR66: =P66 -> 115215.13 | FS66: 0 | FX66: 0 | FY66: 0 | GA66: [66 319,7 / 1,2 / 7,66] + 3% Трансп + 1,2% Заг.скл | GD66: 1 | GF66: 1741110623 | GG66: 2 | GH66: 3 | GI66: 5 | GJ66: 0 | GK66: 0 | GL66: =ROUND(IF(AND(BH66=3,BI66=3,FS66<>0),P66,0),2) -> 0 | GM66: =ROUND(O66+X66+Y66,2)+GX66 -> 115215.13 | GN66: =IF(OR(BI66=0,BI66=1),GM66-GX66,0) -> 0 | GO66: =IF(BI66=2,GM66-GX66,0) -> 0 | GP66: =IF(BI66=4,GM66-GX66,0) -> 0 | GR66: 1 | GS66: 1 | GT66: 0 | GV66: =ROUND((GT66),6) -> 0 | GW66: 1 | GX66: =ROUND(HC66*I66,2) -> 0 | HA66: 0 | HB66: 0 | HC66: =GV66*GW66 -> 0 | HE66: 3 | HF66: 1,2 | HS66: 0 | IK66: 0
A67: 19 | B67: 1 | G67: Щиты | AA67: 1 | IK67: 0
A68: 17 | B68: 1 | C68: =ROW(SmtRes!A90) -> 90 | D68: =ROW(EtalonRes!A101) -> 101 | E68: 13 | F68: 4.8-240-4 | G68: Монтаж пультов и шкафов управления, шкафа (пульта) управления навесного, высотой, шириной, глубиной до 600х600х350 мм | H68: 1 ШТ. | I68: 60 | J68: 0 | K68: 60 | O68: =ROUND(CP68,2) -> 3140.53 | P68: =ROUND((ROUND((AC68*AW68*I68),2)*BC68),2) -> 87.6 | Q68: =(ROUND((ROUND((((ET68*1.1))*AV68*I68),2)*BB68),2)+ROUND((ROUND(((AE68-((EU68*1.1)))*AV68*I68),2)*BS68),2)) -> 1203.76 | R68: =ROUND((ROUND((AE68*AV68*I68),2)*BS68),2) -> 218.36 | S68: =ROUND((ROUND((AF68*AV68*I68),2)*BA68),2) -> 1849.17 | T68: =ROUND(CU68*I68,2) -> 0 | U68: =CV68*I68 -> 142.35012 | V68: =CW68*I68 -> 0 | W68: =ROUND(CX68*I68,2) -> 0 | X68: =ROUND(CY68,2) -> 2005.5 | Y68: =ROUND(CZ68,2) -> 1054.44 | AA68: 60252778 | AB68: =ROUND((AC68+AD68+AF68),6) -> 50.058 | AC68: =ROUND((ES68),6) -> 1.46 | AD68: =ROUND(((((ET68*1.1))-((EU68*1.1)))+AE68),6) -> 19.162 | AE68: =ROUND(((EU68*1.1)),6) -> 3.476 | AF68: =ROUND(((EV68*1.1)),6) -> 29.436 | AG68: =ROUND((AP68),6) -> 0 | AH68: =((EW68*1.1)) -> 2.266 | AI68: =((EX68*1.1)) -> 0 | AJ68: =(AS68) -> 0 | AK68: 45.64 | AL68: 1.46 | AM68: 17.42 | AN68: 3.16 | AO68: 26.76 | AP68: 0 | AQ68: 2.06 | AR68: 0 | AS68: 0 | AT68: 97 | AU68: 51 | AV68: 1.047 | AW68: 1 | AZ68: 1 | BA68: 1 | BB68: 1 | BC68: 1 | BH68: 0 | BI68: 2 | BJ68: ТСН-2001.4 Доп. 80, Сб. 8, т. 240, поз. 4 | BM68: 67 | BN68: 59540665 | BO68: 4.8-240-4 | BP68: 1 | BQ68: 40 | BR68: 0 | BS68: 1 | BT68: 1 | BU68: 1 | BV68: 1 | BW68: 1 | BX68: 1 | BZ68: 97 | CA68: 51 | CE68: 30 | CF68: 0 | CG68: 0 | CM68: 0 | CN68: Поправка: О.П. п.3.4.30.в Наименование: При применении территориальных сметных нормативов для города Москвы затраты, учитывающие напряженные и стесненные условия производства работ (стесненность, сложность складирования и транспортной логистики и т.п.), исчисляются с применением коэффициентов к затратам труда и заработной плате рабочих, машинистов, времени эксплуатации машин и механизмов, стоимости эксплуатации машин в размере: для объектов, расположенных за пределами Третьего транспортного кольца города Москвы, но в пределах Московской кольцевой автомобильной дороги | CO68: 0 | CP68: =(P68+Q68+S68) -> 3140.53 | CQ68: =ROUND((ROUND((AC68*AW68*1),2)*BC68),2) -> 1.46 | CR68: =(ROUND((ROUND((((ET68*1.1))*AV68*1),2)*BB68),2)+ROUND((ROUND(((AE68-((EU68*1.1)))*AV68*1),2)*BS68),2)) -> 20.06 | CS68: =ROUND((ROUND((AE68*AV68*1),2)*BS68),2) -> 3.64 | CT68: =ROUND((ROUND((AF68*AV68*1),2)*BA68),2) -> 30.82 | CU68: =AG68 -> 0 | CV68: =(AH68*AV68) -> 2.372502 | CW68: =AI68 -> 0 | CX68: =AJ68 -> 0 | CY68: =(((S68+R68)*AT68)/100) -> 2005.5041 | CZ68: =(((S68+R68)*AU68)/100) -> 1054.4403 | DB68: 9 | DE68: *1,1 | DF68: *1,1 | DG68: *1,1 | DI68: *1,1 | DJ68: *1,1 | DN68: 0 | DO68: 0 | DP68: 1 | DQ68: 1 | DU68: 1013 | DV68: 1 ШТ. | DW68: 1 ШТ. | DX68: 1 | EE68: 59540733 | EF68: 40 | EG68: Монтаж оборудования | EH68: 0 | EJ68: 2 | EK68: 67 | EL68: ТСН-2001.4-8. Электротехнические установки | EM68: ТСН-2001.4-8-1 | EO68: Поправка: О.П. п.3.4.30.в | EQ68: 0 | ER68: 45.64 | ES68: 1.46 | ET68: 17.42 | EU68: 3.16 | EV68: 26.76 | EW68: 2.06 | EX68: 0 | EY68: 0 | FQ68: 0 | FR68: 0 | FS68: 0 | FX68: 97 | FY68: 51 | GD68: 1 | GF68: -208332064 | GG68: 2 | GH68: 1 | GI68: 2 | GJ68: 0 | GK68: 0 | GL68: =ROUND(IF(AND(BH68=3,BI68=3,FS68<>0),P68,0),2) -> 0 | GM68: =ROUND(O68+X68+Y68,2)+GX68 -> 6200.47 | GN68: =IF(OR(BI68=0,BI68=1),GM68-GX68,0) -> 0 | GO68: =IF(BI68=2,GM68-GX68,0) -> 6200.47 | GP68: =IF(BI68=4,GM68-GX68,0) -> 0 | GR68: 0 | GS68: 3 | GT68: 0 | GV68: =ROUND((GT68),6) -> 0 | GW68: 1 | GX68: =ROUND(HC68*I68,2) -> 0 | HA68: 0 | HB68: 0 | HC68: =GV68*GW68 -> 0 | HS68: 0 | IK68: 0
A69: 17 | B69: 1 | C69: =ROW(SmtRes!A98) -> 98 | D69: =ROW(EtalonRes!A110) -> 110 | E69: 13 | F69: 4.8-240-4 | G69: Монтаж пультов и шкафов управления, шкафа (пульта) управления навесного, высотой, шириной, глубиной до 600х600х350 мм | H69: 1 ШТ. | I69: 60 | J69: 0 | K69: 60 | O69: =ROUND(CP69,2) -> 125370.83 | P69: =ROUND((ROUND((AC69*AW69*I69),2)*BC69),2) -> 1078.36 | Q69: =(ROUND((ROUND((((ET69*1.1))*AV69*I69),2)*BB69),2)+ROUND((ROUND(((AE69-((EU69*1.1)))*AV69*I69),2)*BS69),2)) -> 22606.61 | R69: =ROUND((ROUND((AE69*AV69*I69),2)*BS69),2) -> 12007.62 | S69: =ROUND((ROUND((AF69*AV69*I69),2)*BA69),2) -> 101685.86 | T69: =ROUND(CU69*I69,2) -> 0 | U69: =CV69*I69 -> 142.35012 | V69: =CW69*I69 -> 0 | W69: =ROUND(CX69*I69,2) -> 0 | X69: =ROUND(CY69,2) -> 110282.68 | Y69: =ROUND(CZ69,2) -> 57983.67 | AA69: 60252775 | AB69: =ROUND((AC69+AD69+AF69),6) -> 50.058 | AC69: =ROUND((ES69),6) -> 1.46 | AD69: =ROUND(((((ET69*1.1))-((EU69*1.1)))+AE69),6) -> 19.162 | AE69: =ROUND(((EU69*1.1)),6) -> 3.476 | AF69: =ROUND(((EV69*1.1)),6) -> 29.436 | AG69: =ROUND((AP69),6) -> 0 | AH69: =((EW69*1.1)) -> 2.266 | AI69: =((EX69*1.1)) -> 0 | AJ69: =(AS69) -> 0 | AK69: 45.64 | AL69: 1.46 | AM69: 17.42 | AN69: 3.16 | AO69: 26.76 | AP69: 0 | AQ69: 2.06 | AR69: 0 | AS69: 0 | AT69: 97 | AU69: 51 | AV69: 1.047 | AW69: 1 | AZ69: 1 | BA69: 54.99 | BB69: 18.78 | BC69: 12.31 | BH69: 0 | BI69: 2 | BJ69: ТСН-2001.4 Доп. 80, Сб. 8, т. 240, поз. 4 | BM69: 67 | BN69: 59540665 | BO69: 4.8-240-4 | BP69: 1 | BQ69: 40 | BR69: 0 | BS69: 54.99 | BT69: 1 | BU69: 1 | BV69: 1 | BW69: 1 | BX69: 1 | BZ69: 97 | CA69: 51 | CE69: 30 | CF69: 0 | CG69: 0 | CM69: 0 | CN69: Поправка: О.П. п.3.4.30.в Наименование: При применении территориальных сметных нормативов для города Москвы затраты, учитывающие напряженные и стесненные условия производства работ (стесненность, сложность складирования и транспортной логистики и т.п.), исчисляются с применением коэффициентов к затратам труда и заработной плате рабочих, машинистов, времени эксплуатации машин и механизмов, стоимости эксплуатации машин в размере: для объектов, расположенных за пределами Третьего транспортного кольца города Москвы, но в пределах Московской кольцевой автомобильной дороги | CO69: 0 | CP69: =(P69+Q69+S69) -> 125370.83 | CQ69: =ROUND((ROUND((AC69*AW69*1),2)*BC69),2) -> 17.97 | CR69: =(ROUND((ROUND((((ET69*1.1))*AV69*1),2)*BB69),2)+ROUND((ROUND(((AE69-((EU69*1.1)))*AV69*1),2)*BS69),2)) -> 376.73 | CS69: =ROUND((ROUND((AE69*AV69*1),2)*BS69),2) -> 200.16 | CT69: =ROUND((ROUND((AF69*AV69*1),2)*BA69),2) -> 1694.79 | CU69: =AG69 -> 0 | CV69: =(AH69*AV69) -> 2.372502 | CW69: =AI69 -> 0 | CX69: =AJ69 -> 0 | CY69: =(((S69+R69)*AT69)/100) -> 110282.68 | CZ69: =(((S69+R69)*AU69)/100) -> 57983.675 | DB69: 10 | DE69: *1,1 | DF69: *1,1 | DG69: *1,1 | DI69: *1,1 | DJ69: *1,1 | DN69: 0 | DO69: 0 | DP69: 1 | DQ69: 1 | DU69: 1013 | DV69: 1 ШТ. | DW69: 1 ШТ. | DX69: 1 | EE69: 59540733 | EF69: 40 | EG69: Монтаж оборудования | EH69: 0 | EJ69: 2 | EK69: 67 | EL69: ТСН-2001.4-8. Электротехнические установки | EM69: ТСН-2001.4-8-1 | EO69: Поправка: О.П. п.3.4.30.в | EQ69: 0 | ER69: 45.64 | ES69: 1.46 | ET69: 17.42 | EU69: 3.16 | EV69: 26.76 | EW69: 2.06 | EX69: 0 | EY69: 0 | FQ69: 0 | FR69: 0 | FS69: 0 | FX69: 97 | FY69: 51 | GD69: 1 | GF69: -208332064 | GG69: 2 | GH69: 1 | GI69: 2 | GJ69: 0 | GK69: 0 | GL69: =ROUND(IF(AND(BH69=3,BI69=3,FS69<>0),P69,0),2) -> 0 | GM69: =ROUND(O69+X69+Y69,2)+GX69 -> 293637.18 | GN69: =IF(OR(BI69=0,BI69=1),GM69-GX69,0) -> 0 | GO69: =IF(BI69=2,GM69-GX69,0) -> 293637.18 | GP69: =IF(BI69=4,GM69-GX69,0) -> 0 | GR69: 0 | GS69: 3 | GT69: 0 | GV69: =ROUND((GT69),6) -> 0 | GW69: 1 | GX69: =ROUND(HC69*I69,2) -> 0 | HA69: 0 | HB69: 0 | HC69: =GV69*GW69 -> 0 | HS69: 0 | IK69: 0
A70: 18 | B70: 1 | C70: 90 | E70: 13,1 | F70: 1.1-1-58 | G70: Болты строительные с гайками, оцинкованные, М10х100 мм | H70: т | I70: =I68*J70 -> 0.006 | J70: 0.0001 | K70: 0.0001 | O70: =ROUND(CP70,2) -> 147.66 | P70: =ROUND((ROUND((AC70*AW70*I70),2)*BC70),2) -> 147.66 | Q70: =(ROUND((ROUND(((ET70)*AV70*I70),2)*BB70),2)+ROUND((ROUND(((AE70-(EU70))*AV70*I70),2)*BS70),2)) -> 0 | R70: =ROUND((ROUND((AE70*AV70*I70),2)*BS70),2) -> 0 | S70: =ROUND((ROUND((AF70*AV70*I70),2)*BA70),2) -> 0 | T70: =ROUND(CU70*I70,2) -> 0 | U70: =CV70*I70 -> 0 | V70: =CW70*I70 -> 0 | W70: =ROUND(CX70*I70,2) -> 0 | X70: =ROUND(CY70,2) -> 0 | Y70: =ROUND(CZ70,2) -> 0 | AA70: 60252778 | AB70: =ROUND((AC70+AD70+AF70),6) -> 24609.76 | AC70: =ROUND((ES70),6) -> 24609.76 | AD70: =ROUND((((ET70)-(EU70))+AE70),6) -> 0 | AE70: =ROUND((EU70),6) -> 0 | AF70: =ROUND((EV70),6) -> 0 | AG70: =ROUND((AP70),6) -> 0 | AH70: =(EW70) -> 0 | AI70: =(EX70) -> 0 | AJ70: =(AS70) -> 0 | AK70: 24609.76 | AL70: 24609.76 | AM70: 0 | AN70: 0 | AO70: 0 | AP70: 0 | AQ70: 0 | AR70: 0 | AS70: 0 | AT70: 97 | AU70: 51 | AV70: 1 | AW70: 1 | AZ70: 1 | BA70: 1 | BB70: 1 | BC70: 1 | BH70: 3 | BI70: 2 | BJ70: ТСН-2001.1 Доп. 79, Р. 1, о. 1, поз. 58 | BM70: 67 | BN70: 59540665 | BP70: 0 | BQ70: 40 | BR70: 0 | BS70: 1 | BT70: 1 | BU70: 1 | BV70: 1 | BW70: 1 | BX70: 1 | BZ70: 97 | CA70: 51 | CE70: 30 | CF70: 0 | CG70: 0 | CM70: 0 | CO70: 0 | CP70: =(P70+Q70+S70) -> 147.66 | CQ70: =ROUND((ROUND((AC70*AW70*1),2)*BC70),2) -> 24609.76 | CR70: =(ROUND((ROUND(((ET70)*AV70*1),2)*BB70),2)+ROUND((ROUND(((AE70-(EU70))*AV70*1),2)*BS70),2)) -> 0 | CS70: =ROUND((ROUND((AE70*AV70*1),2)*BS70),2) -> 0 | CT70: =ROUND((ROUND((AF70*AV70*1),2)*BA70),2) -> 0 | CU70: =AG70 -> 0 | CV70: =(AH70*AV70) -> 0 | CW70: =AI70 -> 0 | CX70: =AJ70 -> 0 | CY70: =(((S70+R70)*AT70)/100) -> 0 | CZ70: =(((S70+R70)*AU70)/100) -> 0 | DN70: 0 | DO70: 0 | DP70: 1 | DQ70: 1 | DU70: 1009 | DV70: т | DW70: т | DX70: 1000 | EE70: 59540733 | EF70: 40 | EG70: Монтаж оборудования | EH70: 0 | EJ70: 2 | EK70: 67 | EL70: ТСН-2001.4-8. Электротехнические установки | EM70: ТСН-2001.4-8-1 | EQ70: 0 | ER70: 24609.76 | ES70: 24609.76 | ET70: 0 | EU70: 0 | EV70: 0 | EW70: 0 | EX70: 0 | FQ70: 0 | FR70: 0 | FS70: 0 | FX70: 97 | FY70: 51 | GD70: 1 | GF70: -566361729 | GG70: 2 | GH70: 1 | GI70: -2 | GJ70: 0 | GK70: 0 | GL70: =ROUND(IF(AND(BH70=3,BI70=3,FS70<>0),P70,0),2) -> 0 | GM70: =ROUND(O70+X70+Y70,2)+GX70 -> 147.66 | GN70: =IF(OR(BI70=0,BI70=1),GM70-GX70,0) -> 0 | GO70: =IF(BI70=2,GM70-GX70,0) -> 147.66 | GP70: =IF(BI70=4,GM70-GX70,0) -> 0 | GR70: 0 | GS70: 3 | GT70: 0 | GV70: =ROUND((GT70),6) -> 0 | GW70: 1 | GX70: =ROUND(HC70*I70,2) -> 0 | HA70: 0 | HB70: 0 | HC70: =GV70*GW70 -> 0 | HS70: 0 | IK70: 0
A71: 18 | B71: 1 | C71: 98 | E71: 13,1 | F71: 1.1-1-58 | G71: Болты строительные с гайками, оцинкованные, М10х100 мм | H71: т | I71: =I69*J71 -> 0.006 | J71: 0.0001 | K71: 0.0001 | O71: =ROUND(CP71,2) -> 760.45 | P71: =ROUND((ROUND((AC71*AW71*I71),2)*BC71),2) -> 760.45 | Q71: =(ROUND((ROUND(((ET71)*AV71*I71),2)*BB71),2)+ROUND((ROUND(((AE71-(EU71))*AV71*I71),2)*BS71),2)) -> 0 | R71: =ROUND((ROUND((AE71*AV71*I71),2)*BS71),2) -> 0 | S71: =ROUND((ROUND((AF71*AV71*I71),2)*BA71),2) -> 0 | T71: =ROUND(CU71*I71,2) -> 0 | U71: =CV71*I71 -> 0 | V71: =CW71*I71 -> 0 | W71: =ROUND(CX71*I71,2) -> 0 | X71: =ROUND(CY71,2) -> 0 | Y71: =ROUND(CZ71,2) -> 0 | AA71: 60252775 | AB71: =ROUND((AC71+AD71+AF71),6) -> 24609.76 | AC71: =ROUND((ES71),6) -> 24609.76 | AD71: =ROUND((((ET71)-(EU71))+AE71),6) -> 0 | AE71: =ROUND((EU71),6) -> 0 | AF71: =ROUND((EV71),6) -> 0 | AG71: =ROUND((AP71),6) -> 0 | AH71: =(EW71) -> 0 | AI71: =(EX71) -> 0 | AJ71: =(AS71) -> 0 | AK71: 24609.76 | AL71: 24609.76 | AM71: 0 | AN71: 0 | AO71: 0 | AP71: 0 | AQ71: 0 | AR71: 0 | AS71: 0 | AT71: 97 | AU71: 51 | AV71: 1 | AW71: 1 | AZ71: 1 | BA71: 1 | BB71: 1 | BC71: 5.15 | BH71: 3 | BI71: 2 | BJ71: ТСН-2001.1 Доп. 79, Р. 1, о. 1, поз. 58 | BM71: 67 | BN71: 59540665 | BO71: 1.1-1-58 | BP71: 1 | BQ71: 40 | BR71: 0 | BS71: 1 | BT71: 1 | BU71: 1 | BV71: 1 | BW71: 1 | BX71: 1 | BZ71: 97 | CA71: 51 | CE71: 30 | CF71: 0 | CG71: 0 | CM71: 0 | CO71: 0 | CP71: =(P71+Q71+S71) -> 760.45 | CQ71: =ROUND((ROUND((AC71*AW71*1),2)*BC71),2) -> 126740.26 | CR71: =(ROUND((ROUND(((ET71)*AV71*1),2)*BB71),2)+ROUND((ROUND(((AE71-(EU71))*AV71*1),2)*BS71),2)) -> 0 | CS71: =ROUND((ROUND((AE71*AV71*1),2)*BS71),2) -> 0 | CT71: =ROUND((ROUND((AF71*AV71*1),2)*BA71),2) -> 0 | CU71: =AG71 -> 0 | CV71: =(AH71*AV71) -> 0 | CW71: =AI71 -> 0 | CX71: =AJ71 -> 0 | CY71: =(((S71+R71)*AT71)/100) -> 0 | CZ71: =(((S71+R71)*AU71)/100) -> 0 | DN71: 0 | DO71: 0 | DP71: 1 | DQ71: 1 | DU71: 1009 | DV71: т | DW71: т | DX71: 1000 | EE71: 59540733 | EF71: 40 | EG71: Монтаж оборудования | EH71: 0 | EJ71: 2 | EK71: 67 | EL71: ТСН-2001.4-8. Электротехнические установки | EM71: ТСН-2001.4-8-1 | EQ71: 0 | ER71: 24609.76 | ES71: 24609.76 | ET71: 0 | EU71: 0 | EV71: 0 | EW71: 0 | EX71: 0 | FQ71: 0 | FR71: 0 | FS71: 0 | FX71: 97 | FY71: 51 | GD71: 1 | GF71: -566361729 | GG71: 2 | GH71: 1 | GI71: 2 | GJ71: 0 | GK71: 0 | GL71: =ROUND(IF(AND(BH71=3,BI71=3,FS71<>0),P71,0),2) -> 0 | GM71: =ROUND(O71+X71+Y71,2)+GX71 -> 760.45 | GN71: =IF(OR(BI71=0,BI71=1),GM71-GX71,0) -> 0 | GO71: =IF(BI71=2,GM71-GX71,0) -> 760.45 | GP71: =IF(BI71=4,GM71-GX71,0) -> 0 | GR71: 0 | GS71: 3 | GT71: 0 | GV71: =ROUND((GT71),6) -> 0 | GW71: 1 | GX71: =ROUND(HC71*I71,2) -> 0 | HA71: 0 | HB71: 0 | HC71: =GV71*GW71 -> 0 | HS71: 0 | IK71: 0
A72: 17 | B72: 1 | E72: 14 | F72: КА-8 | G72: ЩМТ-1 | H72: ШТ | I72: 1 | J72: 0 | K72: 1 | O72: =ROUND(CP72,2) -> 14728.25 | P72: =ROUND((ROUND((AC72*I72),2)*BC72),2) -> 14728.25 | Q72: =(ROUND((ROUND(((ET72)*AV72*I72),2)*BB72),2)+ROUND((ROUND(((AE72-(EU72))*AV72*I72),2)*BS72),2)) -> 0 | R72: =ROUND((ROUND((AE72*AV72*I72),2)*BS72),2) -> 0 | S72: =ROUND((ROUND((AF72*AV72*I72),2)*BA72),2) -> 0 | T72: =ROUND(CU72*I72,2) -> 0 | U72: =CV72*I72 -> 0 | V72: =CW72*I72 -> 0 | W72: =ROUND(CX72*I72,2) -> 0 | X72: =ROUND(CY72,2) -> 0 | Y72: =ROUND(CZ72,2) -> 0 | AA72: 60252778 | AB72: =ROUND((AC72+AD72+AF72),6) -> 14728.25 | AC72: =ROUND((ES72),6) -> 14728.25 | AD72: =ROUND((((ET72)-(EU72))+AE72),6) -> 0 | AE72: =ROUND((EU72),6) -> 0 | AF72: =ROUND((EV72),6) -> 0 | AG72: =ROUND((AP72),6) -> 0 | AH72: =(EW72) -> 0 | AI72: =(EX72) -> 0 | AJ72: =(AS72) -> 0 | AK72: 14728.25 | AL72: 14728.25 | AM72: 0 | AN72: 0 | AO72: 0 | AP72: 0 | AQ72: 0 | AR72: 0 | AS72: 0 | AT72: 0 | AU72: 0 | AV72: 1 | AW72: 1 | AZ72: 1 | BA72: 1 | BB72: 1 | BC72: 1 | BH72: 3 | BI72: 3 | BM72: 746 | BN72: 0 | BP72: 0 | BQ72: 130 | BR72: 0 | BS72: 1 | BT72: 1 | BU72: 1 | BV72: 1 | BW72: 1 | BX72: 1 | BZ72: 0 | CA72: 0 | CE72: 30 | CF72: 0 | CG72: 0 | CM72: 0 | CO72: 0 | CP72: =(P72+Q72+S72) -> 14728.25 | CQ72: =ROUND((ROUND((AC72*1),2)*BC72),2) -> 14728.25 | CR72: =(ROUND((ROUND(((ET72)*AV72*1),2)*BB72),2)+ROUND((ROUND(((AE72-(EU72))*AV72*1),2)*BS72),2)) -> 0 | CS72: =ROUND((ROUND((AE72*AV72*1),2)*BS72),2) -> 0 | CT72: =ROUND((ROUND((AF72*AV72*1),2)*BA72),2) -> 0 | CU72: =AG72 -> 0 | CV72: =(AH72*AV72) -> 0 | CW72: =AI72 -> 0 | CX72: =AJ72 -> 0 | CY72: =(((S72+R72)*AT72)/100) -> 0 | CZ72: =(((S72+R72)*AU72)/100) -> 0 | DN72: 0 | DO72: 0 | DP72: 1 | DQ72: 1 | DU72: 1013 | DV72: ШТ | DW72: ШТ | DX72: 1 | EE72: 59540854 | EF72: 130 | EG72: Сметная стоимость оборудования | EH72: 0 | EJ72: 3 | EK72: 746 | EL72: ТСН-2001.13. Сметная стоимость оборудования | EM72: ТСН-2001.13 | EQ72: 0 | ER72: 0 | ES72: 14728.25 | ET72: 0 | EU72: 0 | EV72: 0 | EW72: 0 | EX72: 0 | EY72: 0 | FQ72: 0 | FR72: =P72 -> 14728.25 | FS72: 0 | FX72: 0 | FY72: 0 | GA72: [129 880,42 / 1,2 / 7,66] + 3% Трансп + 1,2% Заг.скл | GD72: 1 | GF72: 1681511625 | GG72: 2 | GH72: 4 | GI72: -2 | GJ72: 0 | GK72: 0 | GL72: =ROUND(IF(AND(BH72=3,BI72=3,FS72<>0),P72,0),2) -> 0 | GM72: =ROUND(O72+X72+Y72,2)+GX72 -> 14728.25 | GN72: =IF(OR(BI72=0,BI72=1),GM72-GX72,0) -> 0 | GO72: =IF(BI72=2,GM72-GX72,0) -> 0 | GP72: =IF(BI72=4,GM72-GX72,0) -> 0 | GR72: 0 | GS72: 2 | GT72: 0 | GV72: =ROUND((GT72),6) -> 0 | GW72: 1 | GX72: =ROUND(HC72*I72,2) -> 0 | HA72: 0 | HB72: 0 | HC72: =GV72*GW72 -> 0 | HE72: 3 | HF72: 1,2 | HS72: 0 | IK72: 0
A73: 17 | B73: 1 | E73: 14 | F73: КА-8 | G73: ЩМТ-1 | H73: ШТ | I73: 1 | J73: 0 | K73: 1 | O73: =ROUND(CP73,2) -> 112818.4 | P73: =ROUND((ROUND((AC73*I73),2)*BC73),2) -> 112818.4 | Q73: =(ROUND((ROUND(((ET73)*AV73*I73),2)*BB73),2)+ROUND((ROUND(((AE73-(EU73))*AV73*I73),2)*BS73),2)) -> 0 | R73: =ROUND((ROUND((AE73*AV73*I73),2)*BS73),2) -> 0 | S73: =ROUND((ROUND((AF73*AV73*I73),2)*BA73),2) -> 0 | T73: =ROUND(CU73*I73,2) -> 0 | U73: =CV73*I73 -> 0 | V73: =CW73*I73 -> 0 | W73: =ROUND(CX73*I73,2) -> 0 | X73: =ROUND(CY73,2) -> 0 | Y73: =ROUND(CZ73,2) -> 0 | AA73: 60252775 | AB73: =ROUND((AC73+AD73+AF73),6) -> 14728.25 | AC73: =ROUND((ES73),6) -> 14728.25 | AD73: =ROUND((((ET73)-(EU73))+AE73),6) -> 0 | AE73: =ROUND((EU73),6) -> 0 | AF73: =ROUND((EV73),6) -> 0 | AG73: =ROUND((AP73),6) -> 0 | AH73: =(EW73) -> 0 | AI73: =(EX73) -> 0 | AJ73: =(AS73) -> 0 | AK73: 14728.25 | AL73: 14728.25 | AM73: 0 | AN73: 0 | AO73: 0 | AP73: 0 | AQ73: 0 | AR73: 0 | AS73: 0 | AT73: 0 | AU73: 0 | AV73: 1 | AW73: 1 | AZ73: 1 | BA73: 1 | BB73: 1 | BC73: 7.66 | BH73: 3 | BI73: 3 | BM73: 746 | BN73: 0 | BP73: 0 | BQ73: 130 | BR73: 0 | BS73: 1 | BT73: 1 | BU73: 1 | BV73: 1 | BW73: 1 | BX73: 1 | BZ73: 0 | CA73: 0 | CE73: 30 | CF73: 0 | CG73: 0 | CM73: 0 | CO73: 0 | CP73: =(P73+Q73+S73) -> 112818.4 | CQ73: =ROUND((ROUND((AC73*1),2)*BC73),2) -> 112818.4 | CR73: =(ROUND((ROUND(((ET73)*AV73*1),2)*BB73),2)+ROUND((ROUND(((AE73-(EU73))*AV73*1),2)*BS73),2)) -> 0 | CS73: =ROUND((ROUND((AE73*AV73*1),2)*BS73),2) -> 0 | CT73: =ROUND((ROUND((AF73*AV73*1),2)*BA73),2) -> 0 | CU73: =AG73 -> 0 | CV73: =(AH73*AV73) -> 0 | CW73: =AI73 -> 0 | CX73: =AJ73 -> 0 | CY73: =(((S73+R73)*AT73)/100) -> 0 | CZ73: =(((S73+R73)*AU73)/100) -> 0 | DN73: 0 | DO73: 0 | DP73: 1 | DQ73: 1 | DU73: 1013 | DV73: ШТ | DW73: ШТ | DX73: 1 | EE73: 59540854 | EF73: 130 | EG73: Сметная стоимость оборудования | EH73: 0 | EJ73: 3 | EK73: 746 | EL73: ТСН-2001.13. Сметная стоимость оборудования | EM73: ТСН-2001.13 | EQ73: 0 | ER73: 14728.25 | ES73: 14728.25 | ET73: 0 | EU73: 0 | EV73: 0 | EW73: 0 | EX73: 0 | EY73: 0 | EZ73: 5 | FC73: 1 | FD73: 18 | FF73: 129880.42 | FQ73: 0 | FR73: =P73 -> 112818.4 | FS73: 0 | FX73: 0 | FY73: 0 | GA73: [129 880,42 / 1,2 / 7,66] + 3% Трансп + 1,2% Заг.скл | GD73: 1 | GF73: 1681511625 | GG73: 2 | GH73: 3 | GI73: 5 | GJ73: 0 | GK73: 0 | GL73: =ROUND(IF(AND(BH73=3,BI73=3,FS73<>0),P73,0),2) -> 0 | GM73: =ROUND(O73+X73+Y73,2)+GX73 -> 112818.4 | GN73: =IF(OR(BI73=0,BI73=1),GM73-GX73,0) -> 0 | GO73: =IF(BI73=2,GM73-GX73,0) -> 0 | GP73: =IF(BI73=4,GM73-GX73,0) -> 0 | GR73: 1 | GS73: 1 | GT73: 0 | GV73: =ROUND((GT73),6) -> 0 | GW73: 1 | GX73: =ROUND(HC73*I73,2) -> 0 | HA73: 0 | HB73: 0 | HC73: =GV73*GW73 -> 0 | HE73: 3 | HF73: 1,2 | HS73: 0 | IK73: 0
A74: 17 | B74: 1 | E74: 15 | F74: КА-9 | G74: ЩО1.1 | H74: ШТ | I74: 1 | J74: 0 | K74: 1 | O74: =ROUND(CP74,2) -> 19534.56 | P74: =ROUND((ROUND((AC74*I74),2)*BC74),2) -> 19534.56 | Q74: =(ROUND((ROUND(((ET74)*AV74*I74),2)*BB74),2)+ROUND((ROUND(((AE74-(EU74))*AV74*I74),2)*BS74),2)) -> 0 | R74: =ROUND((ROUND((AE74*AV74*I74),2)*BS74),2) -> 0 | S74: =ROUND((ROUND((AF74*AV74*I74),2)*BA74),2) -> 0 | T74: =ROUND(CU74*I74,2) -> 0 | U74: =CV74*I74 -> 0 | V74: =CW74*I74 -> 0 | W74: =ROUND(CX74*I74,2) -> 0 | X74: =ROUND(CY74,2) -> 0 | Y74: =ROUND(CZ74,2) -> 0 | AA74: 60252778 | AB74: =ROUND((AC74+AD74+AF74),6) -> 19534.56 | AC74: =ROUND((ES74),6) -> 19534.56 | AD74: =ROUND((((ET74)-(EU74))+AE74),6) -> 0 | AE74: =ROUND((EU74),6) -> 0 | AF74: =ROUND((EV74),6) -> 0 | AG74: =ROUND((AP74),6) -> 0 | AH74: =(EW74) -> 0 | AI74: =(EX74) -> 0 | AJ74: =(AS74) -> 0 | AK74: 19534.56 | AL74: 19534.56 | AM74: 0 | AN74: 0 | AO74: 0 | AP74: 0 | AQ74: 0 | AR74: 0 | AS74: 0 | AT74: 0 | AU74: 0 | AV74: 1 | AW74: 1 | AZ74: 1 | BA74: 1 | BB74: 1 | BC74: 1 | BH74: 3 | BI74: 3 | BM74: 746 | BN74: 0 | BP74: 0 | BQ74: 130 | BR74: 0 | BS74: 1 | BT74: 1 | BU74: 1 | BV74: 1 | BW74: 1 | BX74: 1 | BZ74: 0 | CA74: 0 | CE74: 30 | CF74: 0 | CG74: 0 | CM74: 0 | CO74: 0 | CP74: =(P74+Q74+S74) -> 19534.56 | CQ74: =ROUND((ROUND((AC74*1),2)*BC74),2) -> 19534.56 | CR74: =(ROUND((ROUND(((ET74)*AV74*1),2)*BB74),2)+ROUND((ROUND(((AE74-(EU74))*AV74*1),2)*BS74),2)) -> 0 | CS74: =ROUND((ROUND((AE74*AV74*1),2)*BS74),2) -> 0 | CT74: =ROUND((ROUND((AF74*AV74*1),2)*BA74),2) -> 0 | CU74: =AG74 -> 0 | CV74: =(AH74*AV74) -> 0 | CW74: =AI74 -> 0 | CX74: =AJ74 -> 0 | CY74: =(((S74+R74)*AT74)/100) -> 0 | CZ74: =(((S74+R74)*AU74)/100) -> 0 | DN74: 0 | DO74: 0 | DP74: 1 | DQ74: 1 | DU74: 1013 | DV74: ШТ | DW74: ШТ | DX74: 1 | EE74: 59540854 | EF74: 130 | EG74: Сметная стоимость оборудования | EH74: 0 | EJ74: 3 | EK74: 746 | EL74: ТСН-2001.13. Сметная стоимость оборудования | EM74: ТСН-2001.13 | EQ74: 0 | ER74: 0 | ES74: 19534.56 | ET74: 0 | EU74: 0 | EV74: 0 | EW74: 0 | EX74: 0 | EY74: 0 | FQ74: 0 | FR74: =P74 -> 19534.56 | FS74: 0 | FX74: 0 | FY74: 0 | GA74: [172 264,5 / 1,2 / 7,66] + 3% Трансп + 1,2% Заг.скл | GD74: 1 | GF74: 886969074 | GG74: 2 | GH74: 4 | GI74: -2 | GJ74: 0 | GK74: 0 | GL74: =ROUND(IF(AND(BH74=3,BI74=3,FS74<>0),P74,0),2) -> 0 | GM74: =ROUND(O74+X74+Y74,2)+GX74 -> 19534.56 | GN74: =IF(OR(BI74=0,BI74=1),GM74-GX74,0) -> 0 | GO74: =IF(BI74=2,GM74-GX74,0) -> 0 | GP74: =IF(BI74=4,GM74-GX74,0) -> 0 | GR74: 0 | GS74: 2 | GT74: 0 | GV74: =ROUND((GT74),6) -> 0 | GW74: 1 | GX74: =ROUND(HC74*I74,2) -> 0 | HA74: 0 | HB74: 0 | HC74: =GV74*GW74 -> 0 | HE74: 3 | HF74: 1,2 | HS74: 0 | IK74: 0
A75: 17 | B75: 1 | E75: 15 | F75: КА-9 | G75: ЩО1.1 | H75: ШТ | I75: 1 | J75: 0 | K75: 1 | O75: =ROUND(CP75,2) -> 149634.73 | P75: =ROUND((ROUND((AC75*I75),2)*BC75),2) -> 149634.73 | Q75: =(ROUND((ROUND(((ET75)*AV75*I75),2)*BB75),2)+ROUND((ROUND(((AE75-(EU75))*AV75*I75),2)*BS75),2)) -> 0 | R75: =ROUND((ROUND((AE75*AV75*I75),2)*BS75),2) -> 0 | S75: =ROUND((ROUND((AF75*AV75*I75),2)*BA75),2) -> 0 | T75: =ROUND(CU75*I75,2) -> 0 | U75: =CV75*I75 -> 0 | V75: =CW75*I75 -> 0 | W75: =ROUND(CX75*I75,2) -> 0 | X75: =ROUND(CY75,2) -> 0 | Y75: =ROUND(CZ75,2) -> 0 | AA75: 60252775 | AB75: =ROUND((AC75+AD75+AF75),6) -> 19534.56 | AC75: =ROUND((ES75),6) -> 19534.56 | AD75: =ROUND((((ET75)-(EU75))+AE75),6) -> 0 | AE75: =ROUND((EU75),6) -> 0 | AF75: =ROUND((EV75),6) -> 0 | AG75: =ROUND((AP75),6) -> 0 | AH75: =(EW75) -> 0 | AI75: =(EX75) -> 0 | AJ75: =(AS75) -> 0 | AK75: 19534.56 | AL75: 19534.56 | AM75: 0 | AN75: 0 | AO75: 0 | AP75: 0 | AQ75: 0 | AR75: 0 | AS75: 0 | AT75: 0 | AU75: 0 | AV75: 1 | AW75: 1 | AZ75: 1 | BA75: 1 | BB75: 1 | BC75: 7.66 | BH75: 3 | BI75: 3 | BM75: 746 | BN75: 0 | BP75: 0 | BQ75: 130 | BR75: 0 | BS75: 1 | BT75: 1 | BU75: 1 | BV75: 1 | BW75: 1 | BX75: 1 | BZ75: 0 | CA75: 0 | CE75: 30 | CF75: 0 | CG75: 0 | CM75: 0 | CO75: 0 | CP75: =(P75+Q75+S75) -> 149634.73 | CQ75: =ROUND((ROUND((AC75*1),2)*BC75),2) -> 149634.73 | CR75: =(ROUND((ROUND(((ET75)*AV75*1),2)*BB75),2)+ROUND((ROUND(((AE75-(EU75))*AV75*1),2)*BS75),2)) -> 0 | CS75: =ROUND((ROUND((AE75*AV75*1),2)*BS75),2) -> 0 | CT75: =ROUND((ROUND((AF75*AV75*1),2)*BA75),2) -> 0 | CU75: =AG75 -> 0 | CV75: =(AH75*AV75) -> 0 | CW75: =AI75 -> 0 | CX75: =AJ75 -> 0 | CY75: =(((S75+R75)*AT75)/100) -> 0 | CZ75: =(((S75+R75)*AU75)/100) -> 0 | DN75: 0 | DO75: 0 | DP75: 1 | DQ75: 1 | DU75: 1013 | DV75: ШТ | DW75: ШТ | DX75: 1 | EE75: 59540854 | EF75: 130 | EG75: Сметная стоимость оборудования | EH75: 0 | EJ75: 3 | EK75: 746 | EL75: ТСН-2001.13. Сметная стоимость оборудования | EM75: ТСН-2001.13 | EQ75: 0 | ER75: 19534.56 | ES75: 19534.56 | ET75: 0 | EU75: 0 | EV75: 0 | EW75: 0 | EX75: 0 | EY75: 0 | EZ75: 5 | FC75: 1 | FD75: 18 | FF75: 172264.5 | FQ75: 0 | FR75: =P75 -> 149634.73 | FS75: 0 | FX75: 0 | FY75: 0 | GA75: [172 264,5 / 1,2 / 7,66] + 3% Трансп + 1,2% Заг.скл | GD75: 1 | GF75: 886969074 | GG75: 2 | GH75: 3 | GI75: 5 | GJ75: 0 | GK75: 0 | GL75: =ROUND(IF(AND(BH75=3,BI75=3,FS75<>0),P75,0),2) -> 0 | GM75: =ROUND(O75+X75+Y75,2)+GX75 -> 149634.73 | GN75: =IF(OR(BI75=0,BI75=1),GM75-GX75,0) -> 0 | GO75: =IF(BI75=2,GM75-GX75,0) -> 0 | GP75: =IF(BI75=4,GM75-GX75,0) -> 0 | GR75: 1 | GS75: 1 | GT75: 0 | GV75: =ROUND((GT75),6) -> 0 | GW75: 1 | GX75: =ROUND(HC75*I75,2) -> 0 | HA75: 0 | HB75: 0 | HC75: =GV75*GW75 -> 0 | HE75: 3 | HF75: 1,2 | HS75: 0 | IK75: 0
A76: 17 | B76: 1 | E76: 16 | F76: КА-10 | G76: ЩО1.2 | H76: ШТ | I76: 1 | J76: 0 | K76: 1 | O76: =ROUND(CP76,2) -> 22080.87 | P76: =ROUND((ROUND((AC76*I76),2)*BC76),2) -> 22080.87 | Q76: =(ROUND((ROUND(((ET76)*AV76*I76),2)*BB76),2)+ROUND((ROUND(((AE76-(EU76))*AV76*I76),2)*BS76),2)) -> 0 | R76: =ROUND((ROUND((AE76*AV76*I76),2)*BS76),2) -> 0 | S76: =ROUND((ROUND((AF76*AV76*I76),2)*BA76),2) -> 0 | T76: =ROUND(CU76*I76,2) -> 0 | U76: =CV76*I76 -> 0 | V76: =CW76*I76 -> 0 | W76: =ROUND(CX76*I76,2) -> 0 | X76: =ROUND(CY76,2) -> 0 | Y76: =ROUND(CZ76,2) -> 0 | AA76: 60252778 | AB76: =ROUND((AC76+AD76+AF76),6) -> 22080.87 | AC76: =ROUND((ES76),6) -> 22080.87 | AD76: =ROUND((((ET76)-(EU76))+AE76),6) -> 0 | AE76: =ROUND((EU76),6) -> 0 | AF76: =ROUND((EV76),6) -> 0 | AG76: =ROUND((AP76),6) -> 0 | AH76: =(EW76) -> 0 | AI76: =(EX76) -> 0 | AJ76: =(AS76) -> 0 | AK76: 22080.87 | AL76: 22080.87 | AM76: 0 | AN76: 0 | AO76: 0 | AP76: 0 | AQ76: 0 | AR76: 0 | AS76: 0 | AT76: 0 | AU76: 0 | AV76: 1 | AW76: 1 | AZ76: 1 | BA76: 1 | BB76: 1 | BC76: 1 | BH76: 3 | BI76: 3 | BM76: 746 | BN76: 0 | BP76: 0 | BQ76: 130 | BR76: 0 | BS76: 1 | BT76: 1 | BU76: 1 | BV76: 1 | BW76: 1 | BX76: 1 | BZ76: 0 | CA76: 0 | CE76: 30 | CF76: 0 | CG76: 0 | CM76: 0 | CO76: 0 | CP76: =(P76+Q76+S76) -> 22080.87 | CQ76: =ROUND((ROUND((AC76*1),2)*BC76),2) -> 22080.87 | CR76: =(ROUND((ROUND(((ET76)*AV76*1),2)*BB76),2)+ROUND((ROUND(((AE76-(EU76))*AV76*1),2)*BS76),2)) -> 0 | CS76: =ROUND((ROUND((AE76*AV76*1),2)*BS76),2) -> 0 | CT76: =ROUND((ROUND((AF76*AV76*1),2)*BA76),2) -> 0 | CU76: =AG76 -> 0 | CV76: =(AH76*AV76) -> 0 | CW76: =AI76 -> 0 | CX76: =AJ76 -> 0 | CY76: =(((S76+R76)*AT76)/100) -> 0 | CZ76: =(((S76+R76)*AU76)/100) -> 0 | DN76: 0 | DO76: 0 | DP76: 1 | DQ76: 1 | DU76: 1013 | DV76: ШТ | DW76: ШТ | DX76: 1 | EE76: 59540854 | EF76: 130 | EG76: Сметная стоимость оборудования | EH76: 0 | EJ76: 3 | EK76: 746 | EL76: ТСН-2001.13. Сметная стоимость оборудования | EM76: ТСН-2001.13 | EQ76: 0 | ER76: 0 | ES76: 22080.87 | ET76: 0 | EU76: 0 | EV76: 0 | EW76: 0 | EX76: 0 | EY76: 0 | FQ76: 0 | FR76: =P76 -> 22080.87 | FS76: 0 | FX76: 0 | FY76: 0 | GA76: [194 719,03 / 1,2 / 7,66] + 3% Трансп + 1,2% Заг.скл | GD76: 1 | GF76: 884704110 | GG76: 2 | GH76: 4 | GI76: -2 | GJ76: 0 | GK76: 0 | GL76: =ROUND(IF(AND(BH76=3,BI76=3,FS76<>0),P76,0),2) -> 0 | GM76: =ROUND(O76+X76+Y76,2)+GX76 -> 22080.87 | GN76: =IF(OR(BI76=0,BI76=1),GM76-GX76,0) -> 0 | GO76: =IF(BI76=2,GM76-GX76,0) -> 0 | GP76: =IF(BI76=4,GM76-GX76,0) -> 0 | GR76: 0 | GS76: 2 | GT76: 0 | GV76: =ROUND((GT76),6) -> 0 | GW76: 1 | GX76: =ROUND(HC76*I76,2) -> 0 | HA76: 0 | HB76: 0 | HC76: =GV76*GW76 -> 0 | HE76: 3 | HF76: 1,2 | HS76: 0 | IK76: 0
A77: 17 | B77: 1 | E77: 16 | F77: КА-10 | G77: ЩО1.2 | H77: ШТ | I77: 1 | J77: 0 | K77: 1 | O77: =ROUND(CP77,2) -> 169139.46 | P77: =ROUND((ROUND((AC77*I77),2)*BC77),2) -> 169139.46 | Q77: =(ROUND((ROUND(((ET77)*AV77*I77),2)*BB77),2)+ROUND((ROUND(((AE77-(EU77))*AV77*I77),2)*BS77),2)) -> 0 | R77: =ROUND((ROUND((AE77*AV77*I77),2)*BS77),2) -> 0 | S77: =ROUND((ROUND((AF77*AV77*I77),2)*BA77),2) -> 0 | T77: =ROUND(CU77*I77,2) -> 0 | U77: =CV77*I77 -> 0 | V77: =CW77*I77 -> 0 | W77: =ROUND(CX77*I77,2) -> 0 | X77: =ROUND(CY77,2) -> 0 | Y77: =ROUND(CZ77,2) -> 0 | AA77: 60252775 | AB77: =ROUND((AC77+AD77+AF77),6) -> 22080.87 | AC77: =ROUND((ES77),6) -> 22080.87 | AD77: =ROUND((((ET77)-(EU77))+AE77),6) -> 0 | AE77: =ROUND((EU77),6) -> 0 | AF77: =ROUND((EV77),6) -> 0 | AG77: =ROUND((AP77),6) -> 0 | AH77: =(EW77) -> 0 | AI77: =(EX77) -> 0 | AJ77: =(AS77) -> 0 | AK77: 22080.87 | AL77: 22080.87 | AM77: 0 | AN77: 0 | AO77: 0 | AP77: 0 | AQ77: 0 | AR77: 0 | AS77: 0 | AT77: 0 | AU77: 0 | AV77: 1 | AW77: 1 | AZ77: 1 | BA77: 1 | BB77: 1 | BC77: 7.66 | BH77: 3 | BI77: 3 | BM77: 746 | BN77: 0 | BP77: 0 | BQ77: 130 | BR77: 0 | BS77: 1 | BT77: 1 | BU77: 1 | BV77: 1 | BW77: 1 | BX77: 1 | BZ77: 0 | CA77: 0 | CE77: 30 | CF77: 0 | CG77: 0 | CM77: 0 | CO77: 0 | CP77: =(P77+Q77+S77) -> 169139.46 | CQ77: =ROUND((ROUND((AC77*1),2)*BC77),2) -> 169139.46 | CR77: =(ROUND((ROUND(((ET77)*AV77*1),2)*BB77),2)+ROUND((ROUND(((AE77-(EU77))*AV77*1),2)*BS77),2)) -> 0 | CS77: =ROUND((ROUND((AE77*AV77*1),2)*BS77),2) -> 0 | CT77: =ROUND((ROUND((AF77*AV77*1),2)*BA77),2) -> 0 | CU77: =AG77 -> 0 | CV77: =(AH77*AV77) -> 0 | CW77: =AI77 -> 0 | CX77: =AJ77 -> 0 | CY77: =(((S77+R77)*AT77)/100) -> 0 | CZ77: =(((S77+R77)*AU77)/100) -> 0 | DN77: 0 | DO77: 0 | DP77: 1 | DQ77: 1 | DU77: 1013 | DV77: ШТ | DW77: ШТ | DX77: 1 | EE77: 59540854 | EF77: 130 | EG77: Сметная стоимость оборудования | EH77: 0 | EJ77: 3 | EK77: 746 | EL77: ТСН-2001.13. Сметная стоимость оборудования | EM77: ТСН-2001.13 | EQ77: 0 | ER77: 22080.87 | ES77: 22080.87 | ET77: 0 | EU77: 0 | EV77: 0 | EW77: 0 | EX77: 0 | EY77: 0 | EZ77: 5 | FC77: 1 | FD77: 18 | FF77: 194719.03 | FQ77: 0 | FR77: =P77 -> 169139.46 | FS77: 0 | FX77: 0 | FY77: 0 | GA77: [194 719,03 / 1,2 / 7,66] + 3% Трансп + 1,2% Заг.скл | GD77: 1 | GF77: 884704110 | GG77: 2 | GH77: 3 | GI77: 5 | GJ77: 0 | GK77: 0 | GL77: =ROUND(IF(AND(BH77=3,BI77=3,FS77<>0),P77,0),2) -> 0 | GM77: =ROUND(O77+X77+Y77,2)+GX77 -> 169139.46 | GN77: =IF(OR(BI77=0,BI77=1),GM77-GX77,0) -> 0 | GO77: =IF(BI77=2,GM77-GX77,0) -> 0 | GP77: =IF(BI77=4,GM77-GX77,0) -> 0 | GR77: 1 | GS77: 1 | GT77: 0 | GV77: =ROUND((GT77),6) -> 0 | GW77: 1 | GX77: =ROUND(HC77*I77,2) -> 0 | HA77: 0 | HB77: 0 | HC77: =GV77*GW77 -> 0 | HE77: 3 | HF77: 1,2 | HS77: 0 | IK77: 0
A78: 17 | B78: 1 | E78: 17 | F78: КА-11 | G78: ЩО1.3 | H78: ШТ | I78: 1 | J78: 0 | K78: 1 | O78: =ROUND(CP78,2) -> 9836.69 | P78: =ROUND((ROUND((AC78*I78),2)*BC78),2) -> 9836.69 | Q78: =(ROUND((ROUND(((ET78)*AV78*I78),2)*BB78),2)+ROUND((ROUND(((AE78-(EU78))*AV78*I78),2)*BS78),2)) -> 0 | R78: =ROUND((ROUND((AE78*AV78*I78),2)*BS78),2) -> 0 | S78: =ROUND((ROUND((AF78*AV78*I78),2)*BA78),2) -> 0 | T78: =ROUND(CU78*I78,2) -> 0 | U78: =CV78*I78 -> 0 | V78: =CW78*I78 -> 0 | W78: =ROUND(CX78*I78,2) -> 0 | X78: =ROUND(CY78,2) -> 0 | Y78: =ROUND(CZ78,2) -> 0 | AA78: 60252778 | AB78: =ROUND((AC78+AD78+AF78),6) -> 9836.69 | AC78: =ROUND((ES78),6) -> 9836.69 | AD78: =ROUND((((ET78)-(EU78))+AE78),6) -> 0 | AE78: =ROUND((EU78),6) -> 0 | AF78: =ROUND((EV78),6) -> 0 | AG78: =ROUND((AP78),6) -> 0 | AH78: =(EW78) -> 0 | AI78: =(EX78) -> 0 | AJ78: =(AS78) -> 0 | AK78: 9836.69 | AL78: 9836.69 | AM78: 0 | AN78: 0 | AO78: 0 | AP78: 0 | AQ78: 0 | AR78: 0 | AS78: 0 | AT78: 0 | AU78: 0 | AV78: 1 | AW78: 1 | AZ78: 1 | BA78: 1 | BB78: 1 | BC78: 1 | BH78: 3 | BI78: 3 | BM78: 746 | BN78: 0 | BP78: 0 | BQ78: 130 | BR78: 0 | BS78: 1 | BT78: 1 | BU78: 1 | BV78: 1 | BW78: 1 | BX78: 1 | BZ78: 0 | CA78: 0 | CE78: 30 | CF78: 0 | CG78: 0 | CM78: 0 | CO78: 0 | CP78: =(P78+Q78+S78) -> 9836.69 | CQ78: =ROUND((ROUND((AC78*1),2)*BC78),2) -> 9836.69 | CR78: =(ROUND((ROUND(((ET78)*AV78*1),2)*BB78),2)+ROUND((ROUND(((AE78-(EU78))*AV78*1),2)*BS78),2)) -> 0 | CS78: =ROUND((ROUND((AE78*AV78*1),2)*BS78),2) -> 0 | CT78: =ROUND((ROUND((AF78*AV78*1),2)*BA78),2) -> 0 | CU78: =AG78 -> 0 | CV78: =(AH78*AV78) -> 0 | CW78: =AI78 -> 0 | CX78: =AJ78 -> 0 | CY78: =(((S78+R78)*AT78)/100) -> 0 | CZ78: =(((S78+R78)*AU78)/100) -> 0 | DN78: 0 | DO78: 0 | DP78: 1 | DQ78: 1 | DU78: 1013 | DV78: ШТ | DW78: ШТ | DX78: 1 | EE78: 59540854 | EF78: 130 | EG78: Сметная стоимость оборудования | EH78: 0 | EJ78: 3 | EK78: 746 | EL78: ТСН-2001.13. Сметная стоимость оборудования | EM78: ТСН-2001.13 | EQ78: 0 | ER78: 0 | ES78: 9836.69 | ET78: 0 | EU78: 0 | EV78: 0 | EW78: 0 | EX78: 0 | EY78: 0 | FQ78: 0 | FR78: =P78 -> 9836.69 | FS78: 0 | FX78: 0 | FY78: 0 | GA78: [72 286,97 / 7,66] + 3% Трансп + 1,2% Заг.скл | GD78: 1 | GF78: 1721557992 | GG78: 2 | GH78: 4 | GI78: -2 | GJ78: 0 | GK78: 0 | GL78: =ROUND(IF(AND(BH78=3,BI78=3,FS78<>0),P78,0),2) -> 0 | GM78: =ROUND(O78+X78+Y78,2)+GX78 -> 9836.69 | GN78: =IF(OR(BI78=0,BI78=1),GM78-GX78,0) -> 0 | GO78: =IF(BI78=2,GM78-GX78,0) -> 0 | GP78: =IF(BI78=4,GM78-GX78,0) -> 0 | GR78: 0 | GS78: 2 | GT78: 0 | GV78: =ROUND((GT78),6) -> 0 | GW78: 1 | GX78: =ROUND(HC78*I78,2) -> 0 | HA78: 0 | HB78: 0 | HC78: =GV78*GW78 -> 0 | HE78: 3 | HF78: 1,2 | HS78: 0 | IK78: 0
A79: 17 | B79: 1 | E79: 17 | F79: КА-11 | G79: ЩО1.3 | H79: ШТ | I79: 1 | J79: 0 | K79: 1 | O79: =ROUND(CP79,2) -> 75349.05 | P79: =ROUND((ROUND((AC79*I79),2)*BC79),2) -> 75349.05 | Q79: =(ROUND((ROUND(((ET79)*AV79*I79),2)*BB79),2)+ROUND((ROUND(((AE79-(EU79))*AV79*I79),2)*BS79),2)) -> 0 | R79: =ROUND((ROUND((AE79*AV79*I79),2)*BS79),2) -> 0 | S79: =ROUND((ROUND((AF79*AV79*I79),2)*BA79),2) -> 0 | T79: =ROUND(CU79*I79,2) -> 0 | U79: =CV79*I79 -> 0 | V79: =CW79*I79 -> 0 | W79: =ROUND(CX79*I79,2) -> 0 | X79: =ROUND(CY79,2) -> 0 | Y79: =ROUND(CZ79,2) -> 0 | AA79: 60252775 | AB79: =ROUND((AC79+AD79+AF79),6) -> 9836.69 | AC79: =ROUND((ES79),6) -> 9836.69 | AD79: =ROUND((((ET79)-(EU79))+AE79),6) -> 0 | AE79: =ROUND((EU79),6) -> 0 | AF79: =ROUND((EV79),6) -> 0 | AG79: =ROUND((AP79),6) -> 0 | AH79: =(EW79) -> 0 | AI79: =(EX79) -> 0 | AJ79: =(AS79) -> 0 | AK79: 9836.69 | AL79: 9836.69 | AM79: 0 | AN79: 0 | AO79: 0 | AP79: 0 | AQ79: 0 | AR79: 0 | AS79: 0 | AT79: 0 | AU79: 0 | AV79: 1 | AW79: 1 | AZ79: 1 | BA79: 1 | BB79: 1 | BC79: 7.66 | BH79: 3 | BI79: 3 | BM79: 746 | BN79: 0 | BP79: 0 | BQ79: 130 | BR79: 0 | BS79: 1 | BT79: 1 | BU79: 1 | BV79: 1 | BW79: 1 | BX79: 1 | BZ79: 0 | CA79: 0 | CE79: 30 | CF79: 0 | CG79: 0 | CM79: 0 | CO79: 0 | CP79: =(P79+Q79+S79) -> 75349.05 | CQ79: =ROUND((ROUND((AC79*1),2)*BC79),2) -> 75349.05 | CR79: =(ROUND((ROUND(((ET79)*AV79*1),2)*BB79),2)+ROUND((ROUND(((AE79-(EU79))*AV79*1),2)*BS79),2)) -> 0 | CS79: =ROUND((ROUND((AE79*AV79*1),2)*BS79),2) -> 0 | CT79: =ROUND((ROUND((AF79*AV79*1),2)*BA79),2) -> 0 | CU79: =AG79 -> 0 | CV79: =(AH79*AV79) -> 0 | CW79: =AI79 -> 0 | CX79: =AJ79 -> 0 | CY79: =(((S79+R79)*AT79)/100) -> 0 | CZ79: =(((S79+R79)*AU79)/100) -> 0 | DN79: 0 | DO79: 0 | DP79: 1 | DQ79: 1 | DU79: 1013 | DV79: ШТ | DW79: ШТ | DX79: 1 | EE79: 59540854 | EF79: 130 | EG79: Сметная стоимость оборудования | EH79: 0 | EJ79: 3 | EK79: 746 | EL79: ТСН-2001.13. Сметная стоимость оборудования | EM79: ТСН-2001.13 | EQ79: 0 | ER79: 9836.69 | ES79: 9836.69 | ET79: 0 | EU79: 0 | EV79: 0 | EW79: 0 | EX79: 0 | EY79: 0 | EZ79: 5 | FC79: 0 | FD79: 18 | FF79: 72286.97 | FQ79: 0 | FR79: =P79 -> 75349.05 | FS79: 0 | FX79: 0 | FY79: 0 | GA79: [72 286,97 / 7,66] + 3% Трансп + 1,2% Заг.скл | GD79: 1 | GF79: 1721557992 | GG79: 2 | GH79: 3 | GI79: 5 | GJ79: 0 | GK79: 0 | GL79: =ROUND(IF(AND(BH79=3,BI79=3,FS79<>0),P79,0),2) -> 0 | GM79: =ROUND(O79+X79+Y79,2)+GX79 -> 75349.05 | GN79: =IF(OR(BI79=0,BI79=1),GM79-GX79,0) -> 0 | GO79: =IF(BI79=2,GM79-GX79,0) -> 0 | GP79: =IF(BI79=4,GM79-GX79,0) -> 0 | GR79: 1 | GS79: 1 | GT79: 0 | GV79: =ROUND((GT79),6) -> 0 | GW79: 1 | GX79: =ROUND(HC79*I79,2) -> 0 | HA79: 0 | HB79: 0 | HC79: =GV79*GW79 -> 0 | HE79: 3 | HF79: 1,2 | HS79: 0 | IK79: 0
A80: 17 | B80: 1 | E80: 18 | F80: КА-12 | G80: ЩО1.4 | H80: ШТ | I80: 1 | J80: 0 | K80: 1 | O80: =ROUND(CP80,2) -> 19569.45 | P80: =ROUND((ROUND((AC80*I80),2)*BC80),2) -> 19569.45 | Q80: =(ROUND((ROUND(((ET80)*AV80*I80),2)*BB80),2)+ROUND((ROUND(((AE80-(EU80))*AV80*I80),2)*BS80),2)) -> 0 | R80: =ROUND((ROUND((AE80*AV80*I80),2)*BS80),2) -> 0 | S80: =ROUND((ROUND((AF80*AV80*I80),2)*BA80),2) -> 0 | T80: =ROUND(CU80*I80,2) -> 0 | U80: =CV80*I80 -> 0 | V80: =CW80*I80 -> 0 | W80: =ROUND(CX80*I80,2) -> 0 | X80: =ROUND(CY80,2) -> 0 | Y80: =ROUND(CZ80,2) -> 0 | AA80: 60252778 | AB80: =ROUND((AC80+AD80+AF80),6) -> 19569.45 | AC80: =ROUND((ES80),6) -> 19569.45 | AD80: =ROUND((((ET80)-(EU80))+AE80),6) -> 0 | AE80: =ROUND((EU80),6) -> 0 | AF80: =ROUND((EV80),6) -> 0 | AG80: =ROUND((AP80),6) -> 0 | AH80: =(EW80) -> 0 | AI80: =(EX80) -> 0 | AJ80: =(AS80) -> 0 | AK80: 19569.45 | AL80: 19569.45 | AM80: 0 | AN80: 0 | AO80: 0 | AP80: 0 | AQ80: 0 | AR80: 0 | AS80: 0 | AT80: 0 | AU80: 0 | AV80: 1 | AW80: 1 | AZ80: 1 | BA80: 1 | BB80: 1 | BC80: 1 | BH80: 3 | BI80: 3 | BM80: 746 | BN80: 0 | BP80: 0 | BQ80: 130 | BR80: 0 | BS80: 1 | BT80: 1 | BU80: 1 | BV80: 1 | BW80: 1 | BX80: 1 | BZ80: 0 | CA80: 0 | CE80: 30 | CF80: 0 | CG80: 0 | CM80: 0 | CO80: 0 | CP80: =(P80+Q80+S80) -> 19569.45 | CQ80: =ROUND((ROUND((AC80*1),2)*BC80),2) -> 19569.45 | CR80: =(ROUND((ROUND(((ET80)*AV80*1),2)*BB80),2)+ROUND((ROUND(((AE80-(EU80))*AV80*1),2)*BS80),2)) -> 0 | CS80: =ROUND((ROUND((AE80*AV80*1),2)*BS80),2) -> 0 | CT80: =ROUND((ROUND((AF80*AV80*1),2)*BA80),2) -> 0 | CU80: =AG80 -> 0 | CV80: =(AH80*AV80) -> 0 | CW80: =AI80 -> 0 | CX80: =AJ80 -> 0 | CY80: =(((S80+R80)*AT80)/100) -> 0 | CZ80: =(((S80+R80)*AU80)/100) -> 0 | DN80: 0 | DO80: 0 | DP80: 1 | DQ80: 1 | DU80: 1013 | DV80: ШТ | DW80: ШТ | DX80: 1 | EE80: 59540854 | EF80: 130 | EG80: Сметная стоимость оборудования | EH80: 0 | EJ80: 3 | EK80: 746 | EL80: ТСН-2001.13. Сметная стоимость оборудования | EM80: ТСН-2001.13 | EQ80: 0 | ER80: 0 | ES80: 19569.45 | ET80: 0 | EU80: 0 | EV80: 0 | EW80: 0 | EX80: 0 | EY80: 0 | FQ80: 0 | FR80: =P80 -> 19569.45 | FS80: 0 | FX80: 0 | FY80: 0 | GA80: [172 572,16 / 1,2 / 7,66] + 3% Трансп + 1,2% Заг.скл | GD80: 1 | GF80: 694967194 | GG80: 2 | GH80: 4 | GI80: -2 | GJ80: 0 | GK80: 0 | GL80: =ROUND(IF(AND(BH80=3,BI80=3,FS80<>0),P80,0),2) -> 0 | GM80: =ROUND(O80+X80+Y80,2)+GX80 -> 19569.45 | GN80: =IF(OR(BI80=0,BI80=1),GM80-GX80,0) -> 0 | GO80: =IF(BI80=2,GM80-GX80,0) -> 0 | GP80: =IF(BI80=4,GM80-GX80,0) -> 0 | GR80: 0 | GS80: 2 | GT80: 0 | GV80: =ROUND((GT80),6) -> 0 | GW80: 1 | GX80: =ROUND(HC80*I80,2) -> 0 | HA80: 0 | HB80: 0 | HC80: =GV80*GW80 -> 0 | HE80: 3 | HF80: 1,2 | HS80: 0 | IK80: 0
A81: 17 | B81: 1 | E81: 18 | F81: КА-12 | G81: ЩО1.4 | H81: ШТ | I81: 1 | J81: 0 | K81: 1 | O81: =ROUND(CP81,2) -> 149901.99 | P81: =ROUND((ROUND((AC81*I81),2)*BC81),2) -> 149901.99 | Q81: =(ROUND((ROUND(((ET81)*AV81*I81),2)*BB81),2)+ROUND((ROUND(((AE81-(EU81))*AV81*I81),2)*BS81),2)) -> 0 | R81: =ROUND((ROUND((AE81*AV81*I81),2)*BS81),2) -> 0 | S81: =ROUND((ROUND((AF81*AV81*I81),2)*BA81),2) -> 0 | T81: =ROUND(CU81*I81,2) -> 0 | U81: =CV81*I81 -> 0 | V81: =CW81*I81 -> 0 | W81: =ROUND(CX81*I81,2) -> 0 | X81: =ROUND(CY81,2) -> 0 | Y81: =ROUND(CZ81,2) -> 0 | AA81: 60252775 | AB81: =ROUND((AC81+AD81+AF81),6) -> 19569.45 | AC81: =ROUND((ES81),6) -> 19569.45 | AD81: =ROUND((((ET81)-(EU81))+AE81),6) -> 0 | AE81: =ROUND((EU81),6) -> 0 | AF81: =ROUND((EV81),6) -> 0 | AG81: =ROUND((AP81),6) -> 0 | AH81: =(EW81) -> 0 | AI81: =(EX81) -> 0 | AJ81: =(AS81) -> 0 | AK81: 19569.45 | AL81: 19569.45 | AM81: 0 | AN81: 0 | AO81: 0 | AP81: 0 | AQ81: 0 | AR81: 0 | AS81: 0 | AT81: 0 | AU81: 0 | AV81: 1 | AW81: 1 | AZ81: 1 | BA81: 1 | BB81: 1 | BC81: 7.66 | BH81: 3 | BI81: 3 | BM81: 746 | BN81: 0 | BP81: 0 | BQ81: 130 | BR81: 0 | BS81: 1 | BT81: 1 | BU81: 1 | BV81: 1 | BW81: 1 | BX81: 1 | BZ81: 0 | CA81: 0 | CE81: 30 | CF81: 0 | CG81: 0 | CM81: 0 | CO81: 0 | CP81: =(P81+Q81+S81) -> 149901.99 | CQ81: =ROUND((ROUND((AC81*1),2)*BC81),2) -> 149901.99 | CR81: =(ROUND((ROUND(((ET81)*AV81*1),2)*BB81),2)+ROUND((ROUND(((AE81-(EU81))*AV81*1),2)*BS81),2)) -> 0 | CS81: =ROUND((ROUND((AE81*AV81*1),2)*BS81),2) -> 0 | CT81: =ROUND((ROUND((AF81*AV81*1),2)*BA81),2) -> 0 | CU81: =AG81 -> 0 | CV81: =(AH81*AV81) -> 0 | CW81: =AI81 -> 0 | CX81: =AJ81 -> 0 | CY81: =(((S81+R81)*AT81)/100) -> 0 | CZ81: =(((S81+R81)*AU81)/100) -> 0 | DN81: 0 | DO81: 0 | DP81: 1 | DQ81: 1 | DU81: 1013 | DV81: ШТ | DW81: ШТ | DX81: 1 | EE81: 59540854 | EF81: 130 | EG81: Сметная стоимость оборудования | EH81: 0 | EJ81: 3 | EK81: 746 | EL81: ТСН-2001.13. Сметная стоимость оборудования | EM81: ТСН-2001.13 | EQ81: 0 | ER81: 19569.45 | ES81: 19569.45 | ET81: 0 | EU81: 0 | EV81: 0 | EW81: 0 | EX81: 0 | EY81: 0 | EZ81: 5 | FC81: 1 | FD81: 18 | FF81: 172572.16 | FQ81: 0 | FR81: =P81 -> 149901.99 | FS81: 0 | FX81: 0 | FY81: 0 | GA81: [172 572,16 / 1,2 / 7,66] + 3% Трансп + 1,2% Заг.скл | GD81: 1 | GF81: 694967194 | GG81: 2 | GH81: 3 | GI81: 5 | GJ81: 0 | GK81: 0 | GL81: =ROUND(IF(AND(BH81=3,BI81=3,FS81<>0),P81,0),2) -> 0 | GM81: =ROUND(O81+X81+Y81,2)+GX81 -> 149901.99 | GN81: =IF(OR(BI81=0,BI81=1),GM81-GX81,0) -> 0 | GO81: =IF(BI81=2,GM81-GX81,0) -> 0 | GP81: =IF(BI81=4,GM81-GX81,0) -> 0 | GR81: 1 | GS81: 1 | GT81: 0 | GV81: =ROUND((GT81),6) -> 0 | GW81: 1 | GX81: =ROUND(HC81*I81,2) -> 0 | HA81: 0 | HB81: 0 | HC81: =GV81*GW81 -> 0 | HE81: 3 | HF81: 1,2 | HS81: 0 | IK81: 0
A82: 17 | B82: 1 | E82: 19 | F82: КА-13 | G82: ЩО2.1 | H82: ШТ | I82: 1 | J82: 0 | K82: 1 | O82: =ROUND(CP82,2) -> 16210.39 | P82: =ROUND((ROUND((AC82*I82),2)*BC82),2) -> 16210.39 | Q82: =(ROUND((ROUND(((ET82)*AV82*I82),2)*BB82),2)+ROUND((ROUND(((AE82-(EU82))*AV82*I82),2)*BS82),2)) -> 0 | R82: =ROUND((ROUND((AE82*AV82*I82),2)*BS82),2) -> 0 | S82: =ROUND((ROUND((AF82*AV82*I82),2)*BA82),2) -> 0 | T82: =ROUND(CU82*I82,2) -> 0 | U82: =CV82*I82 -> 0 | V82: =CW82*I82 -> 0 | W82: =ROUND(CX82*I82,2) -> 0 | X82: =ROUND(CY82,2) -> 0 | Y82: =ROUND(CZ82,2) -> 0 | AA82: 60252778 | AB82: =ROUND((AC82+AD82+AF82),6) -> 16210.39 | AC82: =ROUND((ES82),6) -> 16210.39 | AD82: =ROUND((((ET82)-(EU82))+AE82),6) -> 0 | AE82: =ROUND((EU82),6) -> 0 | AF82: =ROUND((EV82),6) -> 0 | AG82: =ROUND((AP82),6) -> 0 | AH82: =(EW82) -> 0 | AI82: =(EX82) -> 0 | AJ82: =(AS82) -> 0 | AK82: 16210.39 | AL82: 16210.39 | AM82: 0 | AN82: 0 | AO82: 0 | AP82: 0 | AQ82: 0 | AR82: 0 | AS82: 0 | AT82: 0 | AU82: 0 | AV82: 1 | AW82: 1 | AZ82: 1 | BA82: 1 | BB82: 1 | BC82: 1 | BH82: 3 | BI82: 3 | BM82: 746 | BN82: 0 | BP82: 0 | BQ82: 130 | BR82: 0 | BS82: 1 | BT82: 1 | BU82: 1 | BV82: 1 | BW82: 1 | BX82: 1 | BZ82: 0 | CA82: 0 | CE82: 30 | CF82: 0 | CG82: 0 | CM82: 0 | CO82: 0 | CP82: =(P82+Q82+S82) -> 16210.39 | CQ82: =ROUND((ROUND((AC82*1),2)*BC82),2) -> 16210.39 | CR82: =(ROUND((ROUND(((ET82)*AV82*1),2)*BB82),2)+ROUND((ROUND(((AE82-(EU82))*AV82*1),2)*BS82),2)) -> 0 | CS82: =ROUND((ROUND((AE82*AV82*1),2)*BS82),2) -> 0 | CT82: =ROUND((ROUND((AF82*AV82*1),2)*BA82),2) -> 0 | CU82: =AG82 -> 0 | CV82: =(AH82*AV82) -> 0 | CW82: =AI82 -> 0 | CX82: =AJ82 -> 0 | CY82: =(((S82+R82)*AT82)/100) -> 0 | CZ82: =(((S82+R82)*AU82)/100) -> 0 | DN82: 0 | DO82: 0 | DP82: 1 | DQ82: 1 | DU82: 1013 | DV82: ШТ | DW82: ШТ | DX82: 1 | EE82: 59540854 | EF82: 130 | EG82: Сметная стоимость оборудования | EH82: 0 | EJ82: 3 | EK82: 746 | EL82: ТСН-2001.13. Сметная стоимость оборудования | EM82: ТСН-2001.13 | EQ82: 0 | ER82: 0 | ES82: 16210.39 | ET82: 0 | EU82: 0 | EV82: 0 | EW82: 0 | EX82: 0 | EY82: 0 | FQ82: 0 | FR82: =P82 -> 16210.39 | FS82: 0 | FX82: 0 | FY82: 0 | GA82: [142 950,46 / 1,2 / 7,66] + 3% Трансп + 1,2% Заг.скл | GD82: 1 | GF82: 2118740729 | GG82: 2 | GH82: 4 | GI82: -2 | GJ82: 0 | GK82: 0 | GL82: =ROUND(IF(AND(BH82=3,BI82=3,FS82<>0),P82,0),2) -> 0 | GM82: =ROUND(O82+X82+Y82,2)+GX82 -> 16210.39 | GN82: =IF(OR(BI82=0,BI82=1),GM82-GX82,0) -> 0 | GO82: =IF(BI82=2,GM82-GX82,0) -> 0 | GP82: =IF(BI82=4,GM82-GX82,0) -> 0 | GR82: 0 | GS82: 2 | GT82: 0 | GV82: =ROUND((GT82),6) -> 0 | GW82: 1 | GX82: =ROUND(HC82*I82,2) -> 0 | HA82: 0 | HB82: 0 | HC82: =GV82*GW82 -> 0 | HE82: 3 | HF82: 1,2 | HS82: 0 | IK82: 0
A83: 17 | B83: 1 | E83: 19 | F83: КА-13 | G83: ЩО2.1 | H83: ШТ | I83: 1 | J83: 0 | K83: 1 | O83: =ROUND(CP83,2) -> 124171.59 | P83: =ROUND((ROUND((AC83*I83),2)*BC83),2) -> 124171.59 | Q83: =(ROUND((ROUND(((ET83)*AV83*I83),2)*BB83),2)+ROUND((ROUND(((AE83-(EU83))*AV83*I83),2)*BS83),2)) -> 0 | R83: =ROUND((ROUND((AE83*AV83*I83),2)*BS83),2) -> 0 | S83: =ROUND((ROUND((AF83*AV83*I83),2)*BA83),2) -> 0 | T83: =ROUND(CU83*I83,2) -> 0 | U83: =CV83*I83 -> 0 | V83: =CW83*I83 -> 0 | W83: =ROUND(CX83*I83,2) -> 0 | X83: =ROUND(CY83,2) -> 0 | Y83: =ROUND(CZ83,2) -> 0 | AA83: 60252775 | AB83: =ROUND((AC83+AD83+AF83),6) -> 16210.39 | AC83: =ROUND((ES83),6) -> 16210.39 | AD83: =ROUND((((ET83)-(EU83))+AE83),6) -> 0 | AE83: =ROUND((EU83),6) -> 0 | AF83: =ROUND((EV83),6) -> 0 | AG83: =ROUND((AP83),6) -> 0 | AH83: =(EW83) -> 0 | AI83: =(EX83) -> 0 | AJ83: =(AS83) -> 0 | AK83: 16210.39 | AL83: 16210.39 | AM83: 0 | AN83: 0 | AO83: 0 | AP83: 0 | AQ83: 0 | AR83: 0 | AS83: 0 | AT83: 0 | AU83: 0 | AV83: 1 | AW83: 1 | AZ83: 1 | BA83: 1 | BB83: 1 | BC83: 7.66 | BH83: 3 | BI83: 3 | BM83: 746 | BN83: 0 | BP83: 0 | BQ83: 130 | BR83: 0 | BS83: 1 | BT83: 1 | BU83: 1 | BV83: 1 | BW83: 1 | BX83: 1 | BZ83: 0 | CA83: 0 | CE83: 30 | CF83: 0 | CG83: 0 | CM83: 0 | CO83: 0 | CP83: =(P83+Q83+S83) -> 124171.59 | CQ83: =ROUND((ROUND((AC83*1),2)*BC83),2) -> 124171.59 | CR83: =(ROUND((ROUND(((ET83)*AV83*1),2)*BB83),2)+ROUND((ROUND(((AE83-(EU83))*AV83*1),2)*BS83),2)) -> 0 | CS83: =ROUND((ROUND((AE83*AV83*1),2)*BS83),2) -> 0 | CT83: =ROUND((ROUND((AF83*AV83*1),2)*BA83),2) -> 0 | CU83: =AG83 -> 0 | CV83: =(AH83*AV83) -> 0 | CW83: =AI83 -> 0 | CX83: =AJ83 -> 0 | CY83: =(((S83+R83)*AT83)/100) -> 0 | CZ83: =(((S83+R83)*AU83)/100) -> 0 | DN83: 0 | DO83: 0 | DP83: 1 | DQ83: 1 | DU83: 1013 | DV83: ШТ | DW83: ШТ | DX83: 1 | EE83: 59540854 | EF83: 130 | EG83: Сметная стоимость оборудования | EH83: 0 | EJ83: 3 | EK83: 746 | EL83: ТСН-2001.13. Сметная стоимость оборудования | EM83: ТСН-2001.13 | EQ83: 0 | ER83: 16210.39 | ES83: 16210.39 | ET83: 0 | EU83: 0 | EV83: 0 | EW83: 0 | EX83: 0 | EY83: 0 | EZ83: 5 | FC83: 1 | FD83: 18 | FF83: 142950.46 | FQ83: 0 | FR83: =P83 -> 124171.59 | FS83: 0 | FX83: 0 | FY83: 0 | GA83: [142 950,46 / 1,2 / 7,66] + 3% Трансп + 1,2% Заг.скл | GD83: 1 | GF83: 2118740729 | GG83: 2 | GH83: 3 | GI83: 5 | GJ83: 0 | GK83: 0 | GL83: =ROUND(IF(AND(BH83=3,BI83=3,FS83<>0),P83,0),2) -> 0 | GM83: =ROUND(O83+X83+Y83,2)+GX83 -> 124171.59 | GN83: =IF(OR(BI83=0,BI83=1),GM83-GX83,0) -> 0 | GO83: =IF(BI83=2,GM83-GX83,0) -> 0 | GP83: =IF(BI83=4,GM83-GX83,0) -> 0 | GR83: 1 | GS83: 1 | GT83: 0 | GV83: =ROUND((GT83),6) -> 0 | GW83: 1 | GX83: =ROUND(HC83*I83,2) -> 0 | HA83: 0 | HB83: 0 | HC83: =GV83*GW83 -> 0 | HE83: 3 | HF83: 1,2 | HS83: 0 | IK83: 0
A84: 17 | B84: 1 | E84: 20 | F84: КА-14 | G84: ЩО2.2 | H84: ШТ | I84: 1 | J84: 0 | K84: 1 | O84: =ROUND(CP84,2) -> 11296.34 | P84: =ROUND((ROUND((AC84*I84),2)*BC84),2) -> 11296.34 | Q84: =(ROUND((ROUND(((ET84)*AV84*I84),2)*BB84),2)+ROUND((ROUND(((AE84-(EU84))*AV84*I84),2)*BS84),2)) -> 0 | R84: =ROUND((ROUND((AE84*AV84*I84),2)*BS84),2) -> 0 | S84: =ROUND((ROUND((AF84*AV84*I84),2)*BA84),2) -> 0 | T84: =ROUND(CU84*I84,2) -> 0 | U84: =CV84*I84 -> 0 | V84: =CW84*I84 -> 0 | W84: =ROUND(CX84*I84,2) -> 0 | X84: =ROUND(CY84,2) -> 0 | Y84: =ROUND(CZ84,2) -> 0 | AA84: 60252778 | AB84: =ROUND((AC84+AD84+AF84),6) -> 11296.34 | AC84: =ROUND((ES84),6) -> 11296.34 | AD84: =ROUND((((ET84)-(EU84))+AE84),6) -> 0 | AE84: =ROUND((EU84),6) -> 0 | AF84: =ROUND((EV84),6) -> 0 | AG84: =ROUND((AP84),6) -> 0 | AH84: =(EW84) -> 0 | AI84: =(EX84) -> 0 | AJ84: =(AS84) -> 0 | AK84: 11296.34 | AL84: 11296.34 | AM84: 0 | AN84: 0 | AO84: 0 | AP84: 0 | AQ84: 0 | AR84: 0 | AS84: 0 | AT84: 0 | AU84: 0 | AV84: 1 | AW84: 1 | AZ84: 1 | BA84: 1 | BB84: 1 | BC84: 1 | BH84: 3 | BI84: 3 | BM84: 746 | BN84: 0 | BP84: 0 | BQ84: 130 | BR84: 0 | BS84: 1 | BT84: 1 | BU84: 1 | BV84: 1 | BW84: 1 | BX84: 1 | BZ84: 0 | CA84: 0 | CE84: 30 | CF84: 0 | CG84: 0 | CM84: 0 | CO84: 0 | CP84: =(P84+Q84+S84) -> 11296.34 | CQ84: =ROUND((ROUND((AC84*1),2)*BC84),2) -> 11296.34 | CR84: =(ROUND((ROUND(((ET84)*AV84*1),2)*BB84),2)+ROUND((ROUND(((AE84-(EU84))*AV84*1),2)*BS84),2)) -> 0 | CS84: =ROUND((ROUND((AE84*AV84*1),2)*BS84),2) -> 0 | CT84: =ROUND((ROUND((AF84*AV84*1),2)*BA84),2) -> 0 | CU84: =AG84 -> 0 | CV84: =(AH84*AV84) -> 0 | CW84: =AI84 -> 0 | CX84: =AJ84 -> 0 | CY84: =(((S84+R84)*AT84)/100) -> 0 | CZ84: =(((S84+R84)*AU84)/100) -> 0 | DN84: 0 | DO84: 0 | DP84: 1 | DQ84: 1 | DU84: 1013 | DV84: ШТ | DW84: ШТ | DX84: 1 | EE84: 59540854 | EF84: 130 | EG84: Сметная стоимость оборудования | EH84: 0 | EJ84: 3 | EK84: 746 | EL84: ТСН-2001.13. Сметная стоимость оборудования | EM84: ТСН-2001.13 | EQ84: 0 | ER84: 0 | ES84: 11296.34 | ET84: 0 | EU84: 0 | EV84: 0 | EW84: 0 | EX84: 0 | EY84: 0 | FQ84: 0 | FR84: =P84 -> 11296.34 | FS84: 0 | FX84: 0 | FY84: 0 | GA84: [99 616,2 / 1,2 / 7,66] + 3% Трансп + 1,2% Заг.скл | GD84: 1 | GF84: 418557978 | GG84: 2 | GH84: 4 | GI84: -2 | GJ84: 0 | GK84: 0 | GL84: =ROUND(IF(AND(BH84=3,BI84=3,FS84<>0),P84,0),2) -> 0 | GM84: =ROUND(O84+X84+Y84,2)+GX84 -> 11296.34 | GN84: =IF(OR(BI84=0,BI84=1),GM84-GX84,0) -> 0 | GO84: =IF(BI84=2,GM84-GX84,0) -> 0 | GP84: =IF(BI84=4,GM84-GX84,0) -> 0 | GR84: 0 | GS84: 2 | GT84: 0 | GV84: =ROUND((GT84),6) -> 0 | GW84: 1 | GX84: =ROUND(HC84*I84,2) -> 0 | HA84: 0 | HB84: 0 | HC84: =GV84*GW84 -> 0 | HE84: 3 | HF84: 1,2 | HS84: 0 | IK84: 0
A85: 17 | B85: 1 | E85: 20 | F85: КА-14 | G85: ЩО2.2 | H85: ШТ | I85: 1 | J85: 0 | K85: 1 | O85: =ROUND(CP85,2) -> 86529.96 | P85: =ROUND((ROUND((AC85*I85),2)*BC85),2) -> 86529.96 | Q85: =(ROUND((ROUND(((ET85)*AV85*I85),2)*BB85),2)+ROUND((ROUND(((AE85-(EU85))*AV85*I85),2)*BS85),2)) -> 0 | R85: =ROUND((ROUND((AE85*AV85*I85),2)*BS85),2) -> 0 | S85: =ROUND((ROUND((AF85*AV85*I85),2)*BA85),2) -> 0 | T85: =ROUND(CU85*I85,2) -> 0 | U85: =CV85*I85 -> 0 | V85: =CW85*I85 -> 0 | W85: =ROUND(CX85*I85,2) -> 0 | X85: =ROUND(CY85,2) -> 0 | Y85: =ROUND(CZ85,2) -> 0 | AA85: 60252775 | AB85: =ROUND((AC85+AD85+AF85),6) -> 11296.34 | AC85: =ROUND((ES85),6) -> 11296.34 | AD85: =ROUND((((ET85)-(EU85))+AE85),6) -> 0 | AE85: =ROUND((EU85),6) -> 0 | AF85: =ROUND((EV85),6) -> 0 | AG85: =ROUND((AP85),6) -> 0 | AH85: =(EW85) -> 0 | AI85: =(EX85) -> 0 | AJ85: =(AS85) -> 0 | AK85: 11296.34 | AL85: 11296.34 | AM85: 0 | AN85: 0 | AO85: 0 | AP85: 0 | AQ85: 0 | AR85: 0 | AS85: 0 | AT85: 0 | AU85: 0 | AV85: 1 | AW85: 1 | AZ85: 1 | BA85: 1 | BB85: 1 | BC85: 7.66 | BH85: 3 | BI85: 3 | BM85: 746 | BN85: 0 | BP85: 0 | BQ85: 130 | BR85: 0 | BS85: 1 | BT85: 1 | BU85: 1 | BV85: 1 | BW85: 1 | BX85: 1 | BZ85: 0 | CA85: 0 | CE85: 30 | CF85: 0 | CG85: 0 | CM85: 0 | CO85: 0 | CP85: =(P85+Q85+S85) -> 86529.96 | CQ85: =ROUND((ROUND((AC85*1),2)*BC85),2) -> 86529.96 | CR85: =(ROUND((ROUND(((ET85)*AV85*1),2)*BB85),2)+ROUND((ROUND(((AE85-(EU85))*AV85*1),2)*BS85),2)) -> 0 | CS85: =ROUND((ROUND((AE85*AV85*1),2)*BS85),2) -> 0 | CT85: =ROUND((ROUND((AF85*AV85*1),2)*BA85),2) -> 0 | CU85: =AG85 -> 0 | CV85: =(AH85*AV85) -> 0 | CW85: =AI85 -> 0 | CX85: =AJ85 -> 0 | CY85: =(((S85+R85)*AT85)/100) -> 0 | CZ85: =(((S85+R85)*AU85)/100) -> 0 | DN85: 0 | DO85: 0 | DP85: 1 | DQ85: 1 | DU85: 1013 | DV85: ШТ | DW85: ШТ | DX85: 1 | EE85: 59540854 | EF85: 130 | EG85: Сметная стоимость оборудования | EH85: 0 | EJ85: 3 | EK85: 746 | EL85: ТСН-2001.13. Сметная стоимость оборудования | EM85: ТСН-2001.13 | EQ85: 0 | ER85: 11296.34 | ES85: 11296.34 | ET85: 0 | EU85: 0 | EV85: 0 | EW85: 0 | EX85: 0 | EY85: 0 | EZ85: 5 | FC85: 1 | FD85: 18 | FF85: 99616.2 | FQ85: 0 | FR85: =P85 -> 86529.96 | FS85: 0 | FX85: 0 | FY85: 0 | GA85: [99 616,2 / 1,2 / 7,66] + 3% Трансп + 1,2% Заг.скл | GD85: 1 | GF85: 418557978 | GG85: 2 | GH85: 3 | GI85: 5 | GJ85: 0 | GK85: 0 | GL85: =ROUND(IF(AND(BH85=3,BI85=3,FS85<>0),P85,0),2) -> 0 | GM85: =ROUND(O85+X85+Y85,2)+GX85 -> 86529.96 | GN85: =IF(OR(BI85=0,BI85=1),GM85-GX85,0) -> 0 | GO85: =IF(BI85=2,GM85-GX85,0) -> 0 | GP85: =IF(BI85=4,GM85-GX85,0) -> 0 | GR85: 1 | GS85: 1 | GT85: 0 | GV85: =ROUND((GT85),6) -> 0 | GW85: 1 | GX85: =ROUND(HC85*I85,2) -> 0 | HA85: 0 | HB85: 0 | HC85: =GV85*GW85 -> 0 | HE85: 3 | HF85: 1,2 | HS85: 0 | IK85: 0
