Workbook

Sheet 02-01-06
A1: =Source!B1 -> Smeta.RU (495) 974-1589
J2: Форма № 4б
A3: Капитальный ремонт здания Государственного бюджетного общеобразовательного учреждения города Москвы "Школа №236" по адресу: г. Москва, улица Клязьминская, дом 7, корпус 4. | AP3: Капитальный ремонт здания Государственного бюджетного общеобразовательного учреждения города Москвы "Школа №236" по адресу: г. Москва, улица Клязьминская, дом 7, корпус 4. 02-01-06 Отопление
A4: (наименование стройки и/или объекта)
A6: =CONCATENATE( "ЛОКАЛЬНАЯ СМЕТА № ",IF(Source!F20<>"Новая локальная смета", Source!F20, "")) -> ЛОКАЛЬНАЯ СМЕТА № 02-01-06
A8: =IF(Source!G20<>"Новая локальная смета", Source!G20, "") -> Отопление
A9: (наименование работ и затрат)
A11: =CONCATENATE( "Основание: чертежи № ", Source!J20) -> Основание: чертежи № 2024-00272-00-0-ИОС4.1
I13: В базисном уровне цен | J13: В текущем уровне цен
E14: Сметная стоимость | I14: =I15+I16+I17+I18 -> 1090.71 | J14: =J15+J16+J17+J18 -> 14180.73 | K14: тыс.руб.
E15: Строительные работы | I15: =ROUND((Source!F411)/1000, 2) -> 1065.26 | J15: =ROUND((Source!P411)/1000, 2) -> 13845.9 | K15: тыс.руб.
E16: Работы по монтажу оборудования | I16: =ROUND((Source!F412)/1000, 2) -> 24.13 | J16: =ROUND((Source!P412)/1000, 2) -> 326.58 | K16: тыс.руб.
E17: Оборудование | I17: =ROUND((Source!F403)/1000, 2) -> 1.32 | J17: =ROUND((Source!P403)/1000, 2) -> 8.25 | K17: тыс.руб.
E18: Прочие работы и затраты | I18: =ROUND((Source!F413+Source!F414)/1000, 2) -> 0 | J18: =ROUND((Source!P413+Source!P414)/1000, 2) -> 0 | K18: тыс.руб.
E19: Средства на оплату труда | I19: =(Source!F409+ Source!F408)/1000 -> 41.32684 | J19: =((Source!P409 + Source!P408)/1000) -> 2272.5629 | K19: тыс.руб.
E20: Затраты труда | I20: =Source!F416 -> 3249.222 | K20: чел.-ч.
E21: Кроме того:
E22: Возврат материалов | I22: =SUM(Y28:Y595)/1000 -> 0 | J22: =SUM(Z28:Z595)/1000 -> 0 | K22: тыс.руб.
A24: Составлен(а) по ТСН-2001 с учетом Дополнения №: 80
A25: № и период сборника коэффициентов (индексов) пересчета: Коэффициенты к ТСН-2001 МГЭ Дополнение 80, ремонт №217/80 III квартал 2025 года и Коэффициенты к ТСН-2001.13-2 Дополнение 46 №62/46 III квартал 2025 года | AP25: № и период сборника коэффициентов (индексов) пересчета: Коэффициенты к ТСН-2001 МГЭ Дополнение 80, ремонт №217/80 III квартал 2025 года и Коэффициенты к ТСН-2001.13-2 Дополнение 46 №62/46 III квартал 2025 года
A26: № п/п | B26: Шифр расценки и коды ресурсов | C26: Наименование работ и затрат | D26: Ед. изм. | E26: Кол-во единиц | F26: Цена на ед. изм., руб. | G26: Попра- вочные коэффи- циенты | H26: Коэффи- циенты зимних удорожа- ний | I26: Всего в ценах на январь 2000 года, руб. | J26: Коэффи- циенты (индек- сы) пере- счета, нормы НР и СП | K26: ВСЕГО затрат в текущем уровне цен, руб.
A27: 1 | B27: 2 | C27: 3 | D27: 4 | E27: 5 | F27: 6 | G27: 7 | H27: 8 | I27: 9 | J27: 10 | K27: 11
A29: =CONCATENATE("Раздел: ",IF(Source!G24<>"Новый раздел", Source!G24, "")) -> Раздел: Конвекторы
A30: 1 | B30: =Source!F28 -> 4.8-254-1 | C30: Монтаж приборов нагревательных, электрополотенце/прим. конвектор электрический настенный 1000 Вт | D30: =Source!H28 -> 1 ШТ. | E30: =Source!I28 -> 3 | Q30: =Source!X28 -> 45.28 | R30: =Source!X29 -> 2489.93 | S30: =Source!Y28 -> 23.81 | T30: =Source!Y29 -> 1309.14 | U30: =ROUND((175/100)*ROUND(Source!R28, 2), 2) -> 0.79 | V30: =ROUND((0/100)*ROUND(Source!R29, 2), 2) -> 0 | AC30: 0
C31: ="Объем: "&Source!I28&"=1+"&"2" -> Объем: 3=1+2
C32: ЗП | F32: =Source!AO28 -> 13.38 | G32: =Source!DG28 -> *1,1 | H32: =Source!AV29 -> 1.047 | I32: =Source!S28 -> 46.23 | J32: =IF(Source!BA29<> 0, Source!BA29, 1) -> 54.99 | K32: =Source!S29 -> 2542.19
C33: ЭМ | F33: =Source!AM28 -> 0.91 | G33: =Source!DE28 -> *1,1 | H33: =Source!AV29 -> 1.047 | I33: =Source!Q28 -> 3.14 | J33: =IF(Source!BB29<> 0, Source!BB29, 1) -> 15.59 | K33: =Source!Q29 -> 48.95
C34: в т.ч. ЗПМ | F34: =Source!AN28 -> 0.13 | G34: =Source!DF28 -> *1,1 | H34: =Source!AV29 -> 1.047 | I34: =Source!R28 -> 0.45 | J34: =IF(Source!BS29<> 0, Source!BS29, 1) -> 54.99 | K34: =Source!R29 -> 24.75
C35: МР | F35: =Source!AL28 -> 0.41 | G35: =Source!DD28 | H35: =Source!AW29 -> 1 | I35: =Source!P28 -> 1.23 | J35: =IF(Source!BC29<> 0, Source!BC29, 1) -> 3.95 | K35: =Source!P29 -> 4.86
C36: НР от ФОТ | D36: % | E36: =Source!BZ29 -> 97 | I36: =SUM(Q30:Q35) -> 45.28 | J36: =Source!AT29 -> 97 | K36: =SUM(R30:R35) -> 2489.93
C37: СП от ФОТ | D37: % | E37: =Source!CA29 -> 51 | I37: =SUM(S30:S36) -> 23.81 | J37: =Source!AU29 -> 51 | K37: =SUM(T30:T36) -> 1309.14
C38: ЗТР | D38: чел-ч | E38: =Source!AQ28 -> 1.03 | G38: =Source!DI28 -> *1,1 | H38: =Source!AV29 -> 1.047 | I38: =Source!U28 -> 3.558753
C39: ВСЕГО работ по позиции: | H39: =I32+I33+I35+I36+I37+0-0-0 -> 119.69 | J39: =K32+K33+K35+K36+K37+0-0-0 -> 6395.07
C40: ВСЕГО оборудование по позиции: | H40: =0+0 -> 0 | J40: =0+0 -> 0
C41: ВСЕГО по позиции: | H41: =I32+I33+I35+I36+I37+0 -> 119.69 | J41: =K32+K33+K35+K36+K37+0 -> 6395.07 | O41: =I32+I33+I35+I36+I37+0 -> 119.69 | P41: =K32+K33+K35+K36+K37+0 -> 6395.07
A43: 2 | B43: =Source!F30 -> 13.1-11-142 | C43: ОБОРУДОВАНИЕ:_x000D_ Конвектор электрический, номинальная мощность 0,5 кВт, для отопления жилых и промышленных помещений | D43: =Source!H30 -> шт. | E43: =Source!I30 -> 1 | F43: =Source!AL30 -> 388.69 | G43: =Source!DD30 | H43: =Source!AW31 -> 1 | I43: =Source!P30 -> 388.69 | J43: =IF(Source!BC31<> 0, Source!BC31, 1) -> 6.57 | K43: =Source!P31 -> 2553.69 | Q43: =Source!X30 -> 0 | R43: =Source!X31 -> 0 | S43: =Source!Y30 -> 0 | T43: =Source!Y31 -> 0 | U43: =ROUND((175/100)*ROUND(Source!R30, 2), 2) -> 0 | V43: =ROUND((0/100)*ROUND(Source!R31, 2), 2) -> 0 | AC43: 5
C44: ВСЕГО по позиции: | H44: =I43+0 -> 388.69 | J44: =K43+0 -> 2553.69 | O44: =I43+0 -> 388.69 | P44: =K43+0 -> 2553.69
A46: 3 | B46: =Source!F32 -> 13.1-11-143 | C46: ОБОРУДОВАНИЕ:_x000D_ Конвектор электрический, номинальная мощность 1 кВт, для отопления жилых и промышленных помещений | D46: =Source!H32 -> шт. | E46: =Source!I32 -> 2 | F46: =Source!AL32 -> 464.74 | G46: =Source!DD32 | H46: =Source!AW33 -> 1 | I46: =Source!P32 -> 929.48 | J46: =IF(Source!BC33<> 0, Source!BC33, 1) -> 6.13 | K46: =Source!P33 -> 5697.71 | Q46: =Source!X32 -> 0 | R46: =Source!X33 -> 0 | S46: =Source!Y32 -> 0 | T46: =Source!Y33 -> 0 | U46: =ROUND((175/100)*ROUND(Source!R32, 2), 2) -> 0 | V46: =ROUND((0/100)*ROUND(Source!R33, 2), 2) -> 0 | AC46: 5
C47: ВСЕГО по позиции: | H47: =I46+0 -> 929.48 | J47: =K46+0 -> 5697.71 | O47: =I46+0 -> 929.48 | P47: =K46+0 -> 5697.71
A50: =CONCATENATE("Итого по разделу: ",IF(Source!G35<>"Новый раздел", Source!G35, "")) -> Итого по разделу: Конвекторы | H50: =SUM(O29:O49) -> 1437.86 | J50: =SUM(P29:P49) -> 14646.47
A51: Итого по ТСН-2001.16 | I51: =SUM(W29:W50) -> 0 | J51: =SUM(X29:X50) -> 0
A52: Итого возвратных сумм | I52: =SUM(Y29:Y51) -> 0 | J52: =SUM(Z29:Z51) -> 0
A54: =CONCATENATE("Раздел: ",IF(Source!G65<>"Новый раздел", Source!G65, "")) -> Раздел: Радиаторы отопления
A55: 4 | B55: =Source!F69 -> 3.18-25-1 | C55: Установка радиаторов стальных панельных однорядных с креплением к стене длиной до 1600 мм | D55: =Source!H69 -> 100 шт. | E55: =Source!I69 -> 0.36 | Q55: =Source!X69 -> 491.4 | R55: =Source!X70 -> 27022.35 | S55: =Source!Y69 -> 275.01 | T55: =Source!Y70 -> 15122.6 | U55: =ROUND((175/100)*ROUND(Source!R69, 2), 2) -> 9.52 | V55: =ROUND((0/100)*ROUND(Source!R70, 2), 2) -> 0 | AC55: 0
C56: ="Объем: "&Source!I69&"=(1+"&"3+"&"2+"&"20+"&"1+"&"9)/"&"100" -> Объем: 0,36=(1+3+2+20+1+9)/100
C57: ЗП | F57: =Source!AO69 -> 916.6 | G57: =Source!DG69 -> *1,15)*1,1 | H57: =Source!AV70 -> 1.067 | I57: =Source!S69 -> 445.39 | J57: =IF(Source!BA70<> 0, Source!BA70, 1) -> 54.99 | K57: =Source!S70 -> 24492
C58: ЭМ | F58: =Source!AM69 -> 95.35 | G58: =Source!DE69 -> *1,25)*1,1 | H58: =Source!AV70 -> 1.067 | I58: =Source!Q69 -> 50.36 | J58: =IF(Source!BB70<> 0, Source!BB70, 1) -> 14.33 | K58: =Source!Q70 -> 721.66
C59: в т.ч. ЗПМ | F59: =Source!AN69 -> 10.3 | G59: =Source!DF69 -> *1,25)*1,1 | H59: =Source!AV70 -> 1.067 | I59: =Source!R69 -> 5.44 | J59: =IF(Source!BS70<> 0, Source!BS70, 1) -> 54.99 | K59: =Source!R70 -> 299.15
C60: МР | F60: =Source!AL69 -> 2078.9 | G60: =Source!DD69 | H60: =Source!AW70 -> 1 | I60: =Source!P69 -> 748.4 | J60: =IF(Source!BC70<> 0, Source!BC70, 1) -> 20.59 | K60: =Source!P70 -> 15409.56
C61: НР от ФОТ | D61: % | E61: =Source!BZ70 -> 109 | I61: =SUM(Q55:Q60) -> 491.4 | J61: =Source!AT70 -> 109 | K61: =SUM(R55:R60) -> 27022.35
C62: СП от ФОТ | D62: % | E62: =Source!CA70 -> 61 | I62: =SUM(S55:S61) -> 275.01 | J62: =Source!AU70 -> 61 | K62: =SUM(T55:T61) -> 15122.6
C63: ЗТР | D63: чел-ч | E63: =Source!AQ69 -> 74.7 | G63: =Source!DI69 -> *1,15)*1,1 | H63: =Source!AV70 -> 1.067 | I63: =Source!U69 -> 36.297611
C64: ВСЕГО работ по позиции: | H64: =I57+I58+I60+I61+I62+0-0-0 -> 2010.56 | J64: =K57+K58+K60+K61+K62+0-0-0 -> 82768.17
C65: ВСЕГО оборудование по позиции: | H65: =0+0 -> 0 | J65: =0+0 -> 0
C66: ВСЕГО по позиции: | H66: =I57+I58+I60+I61+I62+0 -> 2010.56 | J66: =K57+K58+K60+K61+K62+0 -> 82768.17 | O66: =I57+I58+I60+I61+I62+0 -> 2010.56 | P66: =K57+K58+K60+K61+K62+0 -> 82768.17
A68: 5 | B68: =Source!F71 -> КА-1 | C68: Радиатор стальной трубчатый GUARDO TORRE 3D, 400 мм (BK-VER-BLACK), черный 3D-400-350 (мощность 0,336 кВт) 988,51 = [11 490 / 1,2 / 9,88] + 2% Заг.скл | D68: =Source!H71 -> ШТ | E68: =Source!I71 -> 1 | F68: =Source!AL71 -> 988.51 | G68: =Source!DD71 | H68: =Source!AW72 -> 1 | I68: =Source!P71 -> 988.51 | J68: =IF(Source!BC72<> 0, Source!BC72, 1) -> 9.88 | K68: =Source!P72 -> 9766.48 | Q68: =Source!X71 -> 0 | R68: =Source!X72 -> 0 | S68: =Source!Y71 -> 0 | T68: =Source!Y72 -> 0 | U68: =ROUND((175/100)*ROUND(Source!R71, 2), 2) -> 0 | V68: =ROUND((0/100)*ROUND(Source!R72, 2), 2) -> 0 | AC68: 3
C69: ВСЕГО по позиции: | H69: =I68+0 -> 988.51 | J69: =K68+0 -> 9766.48 | O69: =I68+0 -> 988.51 | P69: =K68+0 -> 9766.48
A71: 6 | B71: =Source!F73 -> КА-2 | C71: Радиатор стальной трубчатый GUARDO TORRE 3D, 400 мм (BK-VER-BLACK), черный 3D-400-750 (мощность 0,663 кВт) 1 646,66 = [19 140 / 1,2 / 9,88] + 2% Заг.скл | D71: =Source!H73 -> ШТ | E71: =Source!I73 -> 3 | F71: =Source!AL73 -> 1646.66 | G71: =Source!DD73 | H71: =Source!AW74 -> 1 | I71: =Source!P73 -> 4939.98 | J71: =IF(Source!BC74<> 0, Source!BC74, 1) -> 9.88 | K71: =Source!P74 -> 48807 | Q71: =Source!X73 -> 0 | R71: =Source!X74 -> 0 | S71: =Source!Y73 -> 0 | T71: =Source!Y74 -> 0 | U71: =ROUND((175/100)*ROUND(Source!R73, 2), 2) -> 0 | V71: =ROUND((0/100)*ROUND(Source!R74, 2), 2) -> 0 | AC71: 3
C72: ВСЕГО по позиции: | H72: =I71+0 -> 4939.98 | J72: =K71+0 -> 48807 | O72: =I71+0 -> 4939.98 | P72: =K71+0 -> 48807
A74: 7 | B74: =Source!F75 -> КА-3 | C74: Радиатор стальной трубчатый GUARDO TORRE 3D, 400 мм (BK-VER-WHITE), белый 3D-400-1650 (мощность 1,330 кВт) 3 182,34 = [36 990 / 1,2 / 9,88] + 2% Заг.скл | D74: =Source!H75 -> ШТ | E74: =Source!I75 -> 2 | F74: =Source!AL75 -> 3182.34 | G74: =Source!DD75 | H74: =Source!AW76 -> 1 | I74: =Source!P75 -> 6364.68 | J74: =IF(Source!BC76<> 0, Source!BC76, 1) -> 9.88 | K74: =Source!P76 -> 62883.04 | Q74: =Source!X75 -> 0 | R74: =Source!X76 -> 0 | S74: =Source!Y75 -> 0 | T74: =Source!Y76 -> 0 | U74: =ROUND((175/100)*ROUND(Source!R75, 2), 2) -> 0 | V74: =ROUND((0/100)*ROUND(Source!R76, 2), 2) -> 0 | AC74: 3
C75: ВСЕГО по позиции: | H75: =I74+0 -> 6364.68 | J75: =K74+0 -> 62883.04 | O75: =I74+0 -> 6364.68 | P75: =K74+0 -> 62883.04
A77: 8 | B77: =Source!F77 -> КА-4 | C77: Радиатор стальной трубчатый GUARDO TORRE 3D, 400 мм (BK-VER-WHITE), белый 3D-400-1950 (мощность 1,552 кВт) 3 714,01 = [43 170 / 1,2 / 9,88] + 2% Заг.скл | D77: =Source!H77 -> ШТ | E77: =Source!I77 -> 20 | F77: =Source!AL77 -> 3714.01 | G77: =Source!DD77 | H77: =Source!AW78 -> 1 | I77: =Source!P77 -> 74280.2 | J77: =IF(Source!BC78<> 0, Source!BC78, 1) -> 9.88 | K77: =Source!P78 -> 733888.38 | Q77: =Source!X77 -> 0 | R77: =Source!X78 -> 0 | S77: =Source!Y77 -> 0 | T77: =Source!Y78 -> 0 | U77: =ROUND((175/100)*ROUND(Source!R77, 2), 2) -> 0 | V77: =ROUND((0/100)*ROUND(Source!R78, 2), 2) -> 0 | AC77: 3
C78: ВСЕГО по позиции: | H78: =I77+0 -> 74280.2 | J78: =K77+0 -> 733888.38 | O78: =I77+0 -> 74280.2 | P78: =K77+0 -> 733888.38
A80: 9 | B80: =Source!F79 -> КА-5 | C80: Радиатор стальной трубчатый GUARDO TORRE 3D, 400 мм (BK-VER-WHITE), белый 3D-400-350 (мощность 0,336 к Вт) 988,51 = [11 490 / 1,2 / 9,88] + 2% Заг.скл | D80: =Source!H79 -> ШТ | E80: =Source!I79 -> 1 | F80: =Source!AL79 -> 988.51 | G80: =Source!DD79 | H80: =Source!AW80 -> 1 | I80: =Source!P79 -> 988.51 | J80: =IF(Source!BC80<> 0, Source!BC80, 1) -> 9.88 | K80: =Source!P80 -> 9766.48 | Q80: =Source!X79 -> 0 | R80: =Source!X80 -> 0 | S80: =Source!Y79 -> 0 | T80: =Source!Y80 -> 0 | U80: =ROUND((175/100)*ROUND(Source!R79, 2), 2) -> 0 | V80: =ROUND((0/100)*ROUND(Source!R80, 2), 2) -> 0 | AC80: 3
C81: ВСЕГО по позиции: | H81: =I80+0 -> 988.51 | J81: =K80+0 -> 9766.48 | O81: =I80+0 -> 988.51 | P81: =K80+0 -> 9766.48
A83: 10 | B83: =Source!F81 -> КА-6 | C83: Радиатор стальной трубчатый GUARDO TORRE 3D, 400 мм (BK-VER-WHITE), белый 3D-400-750 (мощность 0,663 кВт) 1 646,66 = [19 140 / 1,2 / 9,88] + 2% Заг.скл | D83: =Source!H81 -> ШТ | E83: =Source!I81 -> 9 | F83: =Source!AL81 -> 1646.66 | G83: =Source!DD81 | H83: =Source!AW82 -> 1 | I83: =Source!P81 -> 14819.94 | J83: =IF(Source!BC82<> 0, Source!BC82, 1) -> 9.88 | K83: =Source!P82 -> 146421.01 | Q83: =Source!X81 -> 0 | R83: =Source!X82 -> 0 | S83: =Source!Y81 -> 0 | T83: =Source!Y82 -> 0 | U83: =ROUND((175/100)*ROUND(Source!R81, 2), 2) -> 0 | V83: =ROUND((0/100)*ROUND(Source!R82, 2), 2) -> 0 | AC83: 3
C84: ВСЕГО по позиции: | H84: =I83+0 -> 14819.94 | J84: =K83+0 -> 146421.01 | O84: =I83+0 -> 14819.94 | P84: =K83+0 -> 146421.01
A86: 11 | B86: =Source!F83 -> 3.18-25-1 | C86: Установка радиаторов стальных панельных однорядных с креплением к стене длиной до 1600 мм | D86: =Source!H83 -> 100 шт. | E86: =Source!I83 -> 0.1 | Q86: =Source!X83 -> 136.5 | R86: =Source!X84 -> 7506.17 | S86: =Source!Y83 -> 76.39 | T86: =Source!Y84 -> 4200.7 | U86: =ROUND((175/100)*ROUND(Source!R83, 2), 2) -> 2.64 | V86: =ROUND((0/100)*ROUND(Source!R84, 2), 2) -> 0 | AC86: 0
C87: ="Объем: "&Source!I83&"=(1+"&"2+"&"1+"&"1+"&"3+"&"2)/"&"100" -> Объем: 0,1=(1+2+1+1+3+2)/100
C88: ЗП | F88: =Source!AO83 -> 916.6 | G88: =Source!DG83 -> *1,15)*1,1 | H88: =Source!AV84 -> 1.067 | I88: =Source!S83 -> 123.72 | J88: =IF(Source!BA84<> 0, Source!BA84, 1) -> 54.99 | K88: =Source!S84 -> 6803.36
C89: ЭМ | F89: =Source!AM83 -> 95.35 | G89: =Source!DE83 -> *1,25)*1,1 | H89: =Source!AV84 -> 1.067 | I89: =Source!Q83 -> 13.99 | J89: =IF(Source!BB84<> 0, Source!BB84, 1) -> 14.33 | K89: =Source!Q84 -> 200.48
C90: в т.ч. ЗПМ | F90: =Source!AN83 -> 10.3 | G90: =Source!DF83 -> *1,25)*1,1 | H90: =Source!AV84 -> 1.067 | I90: =Source!R83 -> 1.51 | J90: =IF(Source!BS84<> 0, Source!BS84, 1) -> 54.99 | K90: =Source!R84 -> 83.03
C91: МР | F91: =Source!AL83 -> 2078.9 | G91: =Source!DD83 | H91: =Source!AW84 -> 1 | I91: =Source!P83 -> 207.89 | J91: =IF(Source!BC84<> 0, Source!BC84, 1) -> 20.59 | K91: =Source!P84 -> 4280.46
C92: НР от ФОТ | D92: % | E92: =Source!BZ84 -> 109 | I92: =SUM(Q86:Q91) -> 136.5 | J92: =Source!AT84 -> 109 | K92: =SUM(R86:R91) -> 7506.17
C93: СП от ФОТ | D93: % | E93: =Source!CA84 -> 61 | I93: =SUM(S86:S92) -> 76.39 | J93: =Source!AU84 -> 61 | K93: =SUM(T86:T92) -> 4200.7
C94: ЗТР | D94: чел-ч | E94: =Source!AQ83 -> 74.7 | G94: =Source!DI83 -> *1,15)*1,1 | H94: =Source!AV84 -> 1.067 | I94: =Source!U83 -> 10.08267
C95: ВСЕГО работ по позиции: | H95: =I88+I89+I91+I92+I93+0-0-0 -> 558.49 | J95: =K88+K89+K91+K92+K93+0-0-0 -> 22991.17
C96: ВСЕГО оборудование по позиции: | H96: =0+0 -> 0 | J96: =0+0 -> 0
C97: ВСЕГО по позиции: | H97: =I88+I89+I91+I92+I93+0 -> 558.49 | J97: =K88+K89+K91+K92+K93+0 -> 22991.17 | O97: =I88+I89+I91+I92+I93+0 -> 558.49 | P97: =K88+K89+K91+K92+K93+0 -> 22991.17
A99: 12 | B99: =Source!F85 -> КА-7 | C99: Стальной панельный радиатор, гигиеническое исполнение Royal Thermo H 20-0400-0400 (тепловая мощность 0,488 кВт) 345,85 = [4 020 / 1,2 / 9,88] + 2% Заг.скл | D99: =Source!H85 -> ШТ | E99: =Source!I85 -> 1 | F99: =Source!AL85 -> 345.85 | G99: =Source!DD85 | H99: =Source!AW86 -> 1 | I99: =Source!P85 -> 345.85 | J99: =IF(Source!BC86<> 0, Source!BC86, 1) -> 9.88 | K99: =Source!P86 -> 3417 | Q99: =Source!X85 -> 0 | R99: =Source!X86 -> 0 | S99: =Source!Y85 -> 0 | T99: =Source!Y86 -> 0 | U99: =ROUND((175/100)*ROUND(Source!R85, 2), 2) -> 0 | V99: =ROUND((0/100)*ROUND(Source!R86, 2), 2) -> 0 | AC99: 3
C100: ВСЕГО по позиции: | H100: =I99+0 -> 345.85 | J100: =K99+0 -> 3417 | O100: =I99+0 -> 345.85 | P100: =K99+0 -> 3417
A102: 13 | B102: =Source!F87 -> КА-8 | C102: Стальной панельный радиатор, гигиеническое исполнение Royal Thermо H 20-0400-0600 (тепловая мощность 0,732 кВт) 351,87 = [4 090 / 1,2 / 9,88] + 2% Заг.скл | D102: =Source!H87 -> ШТ | E102: =Source!I87 -> 2 | F102: =Source!AL87 -> 351.87 | G102: =Source!DD87 | H102: =Source!AW88 -> 1 | I102: =Source!P87 -> 703.74 | J102: =IF(Source!BC88<> 0, Source!BC88, 1) -> 9.88 | K102: =Source!P88 -> 6952.95 | Q102: =Source!X87 -> 0 | R102: =Source!X88 -> 0 | S102: =Source!Y87 -> 0 | T102: =Source!Y88 -> 0 | U102: =ROUND((175/100)*ROUND(Source!R87, 2), 2) -> 0 | V102: =ROUND((0/100)*ROUND(Source!R88, 2), 2) -> 0 | AC102: 3
C103: ВСЕГО по позиции: | H103: =I102+0 -> 703.74 | J103: =K102+0 -> 6952.95 | O103: =I102+0 -> 703.74 | P103: =K102+0 -> 6952.95
A105: 14 | B105: =Source!F89 -> КА-9 | C105: Стальной панельный радиатор, гигиеническое исполнение Royal Thermо H 20-0400-0800 (тепловая мощность 0,9759 кВт) 417,26 = [4 850 / 1,2 / 9,88] + 2% Заг.скл | D105: =Source!H89 -> ШТ | E105: =Source!I89 -> 1 | F105: =Source!AL89 -> 417.26 | G105: =Source!DD89 | H105: =Source!AW90 -> 1 | I105: =Source!P89 -> 417.26 | J105: =IF(Source!BC90<> 0, Source!BC90, 1) -> 9.88 | K105: =Source!P90 -> 4122.53 | Q105: =Source!X89 -> 0 | R105: =Source!X90 -> 0 | S105: =Source!Y89 -> 0 | T105: =Source!Y90 -> 0 | U105: =ROUND((175/100)*ROUND(Source!R89, 2), 2) -> 0 | V105: =ROUND((0/100)*ROUND(Source!R90, 2), 2) -> 0 | AC105: 3
C106: ВСЕГО по позиции: | H106: =I105+0 -> 417.26 | J106: =K105+0 -> 4122.53 | O106: =I105+0 -> 417.26 | P106: =K105+0 -> 4122.53
A108: 15 | B108: =Source!F91 -> КА-10 | C108: Стальной панельный радиатор, гигиеническое исполнение Royal Thermо H 20-0400-1000 (тепловая мощность1,2199 кВт) 503,29 = [5 850 / 1,2 / 9,88] + 2% Заг.скл | D108: =Source!H91 -> ШТ | E108: =Source!I91 -> 1 | F108: =Source!AL91 -> 503.29 | G108: =Source!DD91 | H108: =Source!AW92 -> 1 | I108: =Source!P91 -> 503.29 | J108: =IF(Source!BC92<> 0, Source!BC92, 1) -> 9.88 | K108: =Source!P92 -> 4972.51 | Q108: =Source!X91 -> 0 | R108: =Source!X92 -> 0 | S108: =Source!Y91 -> 0 | T108: =Source!Y92 -> 0 | U108: =ROUND((175/100)*ROUND(Source!R91, 2), 2) -> 0 | V108: =ROUND((0/100)*ROUND(Source!R92, 2), 2) -> 0 | AC108: 3
C109: ВСЕГО по позиции: | H109: =I108+0 -> 503.29 | J109: =K108+0 -> 4972.51 | O109: =I108+0 -> 503.29 | P109: =K108+0 -> 4972.51
A111: 16 | B111: =Source!F93 -> КА-11 | C111: Стальной панельный радиатор, гигиеническое исполнение Royal Thermо H 20-0400-1200 (тепловая мощность 1,4639 кВт) 572,12 = [6 650 / 1,2 / 9,88] + 2% Заг.скл | D111: =Source!H93 -> ШТ | E111: =Source!I93 -> 3 | F111: =Source!AL93 -> 572.12 | G111: =Source!DD93 | H111: =Source!AW94 -> 1 | I111: =Source!P93 -> 1716.36 | J111: =IF(Source!BC94<> 0, Source!BC94, 1) -> 9.88 | K111: =Source!P94 -> 16957.64 | Q111: =Source!X93 -> 0 | R111: =Source!X94 -> 0 | S111: =Source!Y93 -> 0 | T111: =Source!Y94 -> 0 | U111: =ROUND((175/100)*ROUND(Source!R93, 2), 2) -> 0 | V111: =ROUND((0/100)*ROUND(Source!R94, 2), 2) -> 0 | AC111: 3
C112: ВСЕГО по позиции: | H112: =I111+0 -> 1716.36 | J112: =K111+0 -> 16957.64 | O112: =I111+0 -> 1716.36 | P112: =K111+0 -> 16957.64
A114: 17 | B114: =Source!F95 -> КА-12 | C114: Стальной панельный радиатор, гигиеническое исполнение Royal Thermо H 20-0400-1400 (тепловая мощность 1,7079 кВт) 644,39 = [7 490 / 1,2 / 9,88] + 2% Заг.скл | D114: =Source!H95 -> ШТ | E114: =Source!I95 -> 2 | F114: =Source!AL95 -> 644.39 | G114: =Source!DD95 | H114: =Source!AW96 -> 1 | I114: =Source!P95 -> 1288.78 | J114: =IF(Source!BC96<> 0, Source!BC96, 1) -> 9.88 | K114: =Source!P96 -> 12733.15 | Q114: =Source!X95 -> 0 | R114: =Source!X96 -> 0 | S114: =Source!Y95 -> 0 | T114: =Source!Y96 -> 0 | U114: =ROUND((175/100)*ROUND(Source!R95, 2), 2) -> 0 | V114: =ROUND((0/100)*ROUND(Source!R96, 2), 2) -> 0 | AC114: 3
C115: ВСЕГО по позиции: | H115: =I114+0 -> 1288.78 | J115: =K114+0 -> 12733.15 | O115: =I114+0 -> 1288.78 | P115: =K114+0 -> 12733.15
A117: 18 | B117: =Source!F97 -> 3.18-25-1 | C117: Установка радиаторов стальных панельных однорядных с креплением к стене длиной до 1600 мм | D117: =Source!H97 -> 100 шт. | E117: =Source!I97 -> 0.16 | Q117: =Source!X97 -> 218.4 | R117: =Source!X98 -> 12010 | S117: =Source!Y97 -> 122.23 | T117: =Source!Y98 -> 6721.19 | U117: =ROUND((175/100)*ROUND(Source!R97, 2), 2) -> 4.24 | V117: =ROUND((0/100)*ROUND(Source!R98, 2), 2) -> 0 | AC117: 0
C118: ="Объем: "&Source!I97&"=(1+"&"5+"&"8+"&"2)/"&"100" -> Объем: 0,16=(1+5+8+2)/100
C119: ЗП | F119: =Source!AO97 -> 916.6 | G119: =Source!DG97 -> *1,15)*1,1 | H119: =Source!AV98 -> 1.067 | I119: =Source!S97 -> 197.95 | J119: =IF(Source!BA98<> 0, Source!BA98, 1) -> 54.99 | K119: =Source!S98 -> 10885.27
C120: ЭМ | F120: =Source!AM97 -> 95.35 | G120: =Source!DE97 -> *1,25)*1,1 | H120: =Source!AV98 -> 1.067 | I120: =Source!Q97 -> 22.38 | J120: =IF(Source!BB98<> 0, Source!BB98, 1) -> 14.33 | K120: =Source!Q98 -> 320.71
C121: в т.ч. ЗПМ | F121: =Source!AN97 -> 10.3 | G121: =Source!DF97 -> *1,25)*1,1 | H121: =Source!AV98 -> 1.067 | I121: =Source!R97 -> 2.42 | J121: =IF(Source!BS98<> 0, Source!BS98, 1) -> 54.99 | K121: =Source!R98 -> 133.08
C122: МР | F122: =Source!AL97 -> 2078.9 | G122: =Source!DD97 | H122: =Source!AW98 -> 1 | I122: =Source!P97 -> 332.62 | J122: =IF(Source!BC98<> 0, Source!BC98, 1) -> 20.59 | K122: =Source!P98 -> 6848.65
C123: НР от ФОТ | D123: % | E123: =Source!BZ98 -> 109 | I123: =SUM(Q117:Q122) -> 218.4 | J123: =Source!AT98 -> 109 | K123: =SUM(R117:R122) -> 12010
C124: СП от ФОТ | D124: % | E124: =Source!CA98 -> 61 | I124: =SUM(S117:S123) -> 122.23 | J124: =Source!AU98 -> 61 | K124: =SUM(T117:T123) -> 6721.19
C125: ЗТР | D125: чел-ч | E125: =Source!AQ97 -> 74.7 | G125: =Source!DI97 -> *1,15)*1,1 | H125: =Source!AV98 -> 1.067 | I125: =Source!U97 -> 16.132272
...

Sheet Ведомость объемов работ
A1: =Source!B1 -> Smeta.RU (495) 974-1589
B4: =CONCATENATE("Ведомость объемов работ ", IF(Source!AN15<>"", Source!AN15," ")) -> Ведомость объемов работ
B5: =CONCATENATE(Source!F12, " ", Source!G12) -> 02-01-06 Отопление
A8: № п/п | B8: № в ЛСР | C8: Наименование работ и затрат | D8: Единица измерения | E8: Количество | F8: Ссылка на чертежи, спецификации | G8: Формула расчета, расчет объемов работ и расхода материалов | H8: Примечание
A9: 1 | B9: 2 | C9: 3 | D9: 4 | E9: 5 | F9: 6 | G9: 7 | H9: 8
A10: =CONCATENATE("Локальная смета: ", Source!G20) -> Локальная смета: Отопление
A11: =CONCATENATE("Раздел: ", Source!G24) -> Раздел: Конвекторы
A12: 1 | B12: =Source!E28 -> 1 | C12: =Source!G28 -> Монтаж приборов нагревательных, электрополотенце/прим. конвектор электрический настенный 1000 Вт | D12: 1 ШТ. | E12: =Source!I28 -> 3 | F12: =Source!U24 | G12: ="=1+"&"2" -> =1+2
A13: 2 | B13: =Source!E30 -> 2 | C13: =Source!G30 -> Конвектор электрический, номинальная мощность 0,5 кВт, для отопления жилых и промышленных помещений | D13: шт. | E13: =Source!I30 -> 1 | F13: =Source!U24 | G13: =Source!I30 -> 1
A14: 3 | B14: =Source!E32 -> 3 | C14: =Source!G32 -> Конвектор электрический, номинальная мощность 1 кВт, для отопления жилых и промышленных помещений | D14: шт. | E14: =Source!I32 -> 2 | F14: =Source!U24 | G14: =Source!I32 -> 2
A15: =CONCATENATE("Раздел: ", Source!G65) -> Раздел: Радиаторы отопления
A16: 4 | B16: =Source!E69 -> 4 | C16: =Source!G69 -> Установка радиаторов стальных панельных однорядных с креплением к стене длиной до 1600 мм | D16: 100 шт. | E16: =Source!I69 -> 0.36 | F16: =Source!U65 | G16: ="=(1+"&"3+"&"2+"&"20+"&"1+"&"9)/"&"100" -> =(1+3+2+20+1+9)/100
A17: 5 | B17: =Source!E71 -> 5 | C17: =Source!G71 -> Радиатор стальной трубчатый GUARDO TORRE 3D, 400 мм (BK-VER-BLACK), черный 3D-400-350 (мощность 0,336 кВт) | D17: ШТ | E17: =Source!I71 -> 1 | F17: =Source!U65 | G17: =Source!I71 -> 1
A18: 6 | B18: =Source!E73 -> 6 | C18: =Source!G73 -> Радиатор стальной трубчатый GUARDO TORRE 3D, 400 мм (BK-VER-BLACK), черный 3D-400-750 (мощность 0,663 кВт) | D18: ШТ | E18: =Source!I73 -> 3 | F18: =Source!U65 | G18: =Source!I73 -> 3
A19: 7 | B19: =Source!E75 -> 7 | C19: =Source!G75 -> Радиатор стальной трубчатый GUARDO TORRE 3D, 400 мм (BK-VER-WHITE), белый 3D-400-1650 (мощность 1,330 кВт) | D19: ШТ | E19: =Source!I75 -> 2 | F19: =Source!U65 | G19: =Source!I75 -> 2
A20: 8 | B20: =Source!E77 -> 8 | C20: =Source!G77 -> Радиатор стальной трубчатый GUARDO TORRE 3D, 400 мм (BK-VER-WHITE), белый 3D-400-1950 (мощность 1,552 кВт) | D20: ШТ | E20: =Source!I77 -> 20 | F20: =Source!U65 | G20: =Source!I77 -> 20
A21: 9 | B21: =Source!E79 -> 9 | C21: =Source!G79 -> Радиатор стальной трубчатый GUARDO TORRE 3D, 400 мм (BK-VER-WHITE), белый 3D-400-350 (мощность 0,336 к Вт) | D21: ШТ | E21: =Source!I79 -> 1 | F21: =Source!U65 | G21: =Source!I79 -> 1
A22: 10 | B22: =Source!E81 -> 10 | C22: =Source!G81 -> Радиатор стальной трубчатый GUARDO TORRE 3D, 400 мм (BK-VER-WHITE), белый 3D-400-750 (мощность 0,663 кВт) | D22: ШТ | E22: =Source!I81 -> 9 | F22: =Source!U65 | G22: =Source!I81 -> 9
A23: 11 | B23: =Source!E83 -> 11 | C23: =Source!G83 -> Установка радиаторов стальных панельных однорядных с креплением к стене длиной до 1600 мм | D23: 100 шт. | E23: =Source!I83 -> 0.1 | F23: =Source!U65 | G23: ="=(1+"&"2+"&"1+"&"1+"&"3+"&"2)/"&"100" -> =(1+2+1+1+3+2)/100
A24: 12 | B24: =Source!E85 -> 12 | C24: =Source!G85 -> Стальной панельный радиатор, гигиеническое исполнение Royal Thermo H 20-0400-0400 (тепловая мощность 0,488 кВт) | D24: ШТ | E24: =Source!I85 -> 1 | F24: =Source!U65 | G24: =Source!I85 -> 1
A25: 13 | B25: =Source!E87 -> 13 | C25: =Source!G87 -> Стальной панельный радиатор, гигиеническое исполнение Royal Thermо H 20-0400-0600 (тепловая мощность 0,732 кВт) | D25: ШТ | E25: =Source!I87 -> 2 | F25: =Source!U65 | G25: =Source!I87 -> 2
A26: 14 | B26: =Source!E89 -> 14 | C26: =Source!G89 -> Стальной панельный радиатор, гигиеническое исполнение Royal Thermо H 20-0400-0800 (тепловая мощность 0,9759 кВт) | D26: ШТ | E26: =Source!I89 -> 1 | F26: =Source!U65 | G26: =Source!I89 -> 1
A27: 15 | B27: =Source!E91 -> 15 | C27: =Source!G91 -> Стальной панельный радиатор, гигиеническое исполнение Royal Thermо H 20-0400-1000 (тепловая мощность1,2199 кВт) | D27: ШТ | E27: =Source!I91 -> 1 | F27: =Source!U65 | G27: =Source!I91 -> 1
A28: 16 | B28: =Source!E93 -> 16 | C28: =Source!G93 -> Стальной панельный радиатор, гигиеническое исполнение Royal Thermо H 20-0400-1200 (тепловая мощность 1,4639 кВт) | D28: ШТ | E28: =Source!I93 -> 3 | F28: =Source!U65 | G28: =Source!I93 -> 3
A29: 17 | B29: =Source!E95 -> 17 | C29: =Source!G95 -> Стальной панельный радиатор, гигиеническое исполнение Royal Thermо H 20-0400-1400 (тепловая мощность 1,7079 кВт) | D29: ШТ | E29: =Source!I95 -> 2 | F29: =Source!U65 | G29: =Source!I95 -> 2
A30: 18 | B30: =Source!E97 -> 18 | C30: =Source!G97 -> Установка радиаторов стальных панельных однорядных с креплением к стене длиной до 1600 мм | D30: 100 шт. | E30: =Source!I97 -> 0.16 | F30: =Source!U65 | G30: ="=(1+"&"5+"&"8+"&"2)/"&"100" -> =(1+5+8+2)/100
A31: 19 | B31: =Source!E99 -> 19 | C31: =Source!G99 -> Стальной панельный радиатор, гигиеническое исполнение Royal Thermо H 10-0400-0600 (тепловая мощность 0,4221 кВт) | D31: ШТ | E31: =Source!I99 -> 1 | F31: =Source!U65 | G31: =Source!I99 -> 1
A32: 20 | B32: =Source!E101 -> 20 | C32: =Source!G101 -> Стальной панельный радиатор, гигиеническое исполнение Royal Thermо H 10-0400-1000 (тепловая мощность 0,7035 кВт) | D32: ШТ | E32: =Source!I101 -> 5 | F32: =Source!U65 | G32: =Source!I101 -> 5
A33: 21 | B33: =Source!E103 -> 21 | C33: =Source!G103 -> Стальной панельный радиатор, гигиеническое исполнение Royal Thermо H 10-0400-1400 (тепловая мощность 0,9849 кВт) | D33: ШТ | E33: =Source!I103 -> 8 | F33: =Source!U65 | G33: =Source!I103 -> 8
A34: 22 | B34: =Source!E105 -> 22 | C34: =Source!G105 -> Стальной панельный радиатор, гигиеническое исполнение Royal Thermо H 10-0400-1600 (тепловая мощность 1,1256 кВт) | D34: ШТ | E34: =Source!I105 -> 2 | F34: =Source!U65 | G34: =Source!I105 -> 2
A35: 23 | B35: =Source!E107 -> 23 | C35: =Source!G107 -> Установка радиаторов стальных панельных однорядных с креплением к стене длиной до 1600 мм | D35: 100 шт. | E35: =Source!I107 -> 0.01 | F35: =Source!U65 | G35: ="=1/"&"100" -> =1/100
A36: 24 | B36: =Source!E109 -> 24 | C36: =Source!G109 -> Стальной панельный радиатор, гигиеническое исполнение Royal Thermо H 30-0400-0600 (тепловая мощность 1,019 кВт) | D36: ШТ | E36: =Source!I109 -> 1 | F36: =Source!U65 | G36: =Source!I109 -> 1
A37: 25 | B37: =Source!E111 -> 25 | C37: =Source!G111 -> Установка радиаторов стальных панельных однорядных с креплением к стене длиной до 1600 мм | D37: 100 шт. | E37: =Source!I111 -> 1.44 | F37: =Source!U65 | G37: ="=(1+"&"43+"&"87+"&"13)/"&"100" -> =(1+43+87+13)/100
A38: 26 | B38: =Source!E113 -> 26 | C38: =Source!G113 -> Стальной панельный радиатор боковое подключение Royal Thermо С 11-0400-1000 (тепловая мощность 0,9956 кВт) | D38: ШТ | E38: =Source!I113 -> 1 | F38: =Source!U65 | G38: =Source!I113 -> 1
A39: 27 | B39: =Source!E115 -> 27 | C39: =Source!G115 -> Стальной панельный радиатор боковое подключение Royal Thermо С 11-0400-1200 (тепловая мощность 1.1948 кВт) | D39: ШТ | E39: =Source!I115 -> 43 | F39: =Source!U65 | G39: =Source!I115 -> 43
A40: 28 | B40: =Source!E117 -> 28 | C40: =Source!G117 -> Стальной панельный радиатор боковое подключение Royal Thermо С 11-0400-1400 (тепловая мощность 1.3939 кВт) | D40: ШТ | E40: =Source!I117 -> 87 | F40: =Source!U65 | G40: =Source!I117 -> 87
A41: 29 | B41: =Source!E119 -> 29 | C41: =Source!G119 -> Стальной панельный радиатор боковое подключение Royal Thermо С 11-0400-1600 (тепловая мощность 1.593 кВт) | D41: ШТ | E41: =Source!I119 -> 13 | F41: =Source!U65 | G41: =Source!I119 -> 13
A42: 30 | B42: =Source!E121 -> 30 | C42: =Source!G121 -> Установка радиаторов стальных панельных однорядных с креплением к стене длиной свыше 1600 до 2000 мм | D42: 100 шт. | E42: =Source!I121 -> 0.7 | F42: =Source!U65 | G42: ="=70/"&"100" -> =70/100
A43: 31 | B43: =Source!E123 -> 31 | C43: =Source!G123 -> Стальной панельный радиатор боковое подключение Royal Thermо С 11-0400-1800 (тепловая мощность 1.7922 кВт) | D43: ШТ | E43: =Source!I123 -> 70 | F43: =Source!U65 | G43: =Source!I123 -> 70
A44: 32 | B44: =Source!E125 -> 32 | C44: =Source!G125 -> Установка радиаторов стальных панельных однорядных с креплением к стене длиной до 1600 мм | D44: 100 шт. | E44: =Source!I125 -> 0.08 | F44: =Source!U65 | G44: ="=(1+"&"1+"&"4+"&"2)/"&"100" -> =(1+1+4+2)/100
A45: 33 | B45: =Source!E127 -> 33 | C45: =Source!G127 -> Радиатор отопительный, стальной, панельный, ГОСТ 31311, с боковым подключением, типа 21 K, высота 400 мм, длина 800 мм, теплоотдача 1291 Вт | D45: шт. | E45: =Source!I127 -> 1 | F45: =Source!U65 | G45: =Source!I127 -> 1
A46: 34 | B46: =Source!E129 -> 34 | C46: =Source!G129 -> Радиатор отопительный, стальной, панельный, ГОСТ 31311, с боковым подключением, типа 21 K, высота 400 мм, длина 1200 мм, теплоотдача 1936 Вт | D46: шт. | E46: =Source!I129 -> 1 | F46: =Source!U65 | G46: =Source!I129 -> 1
A47: 35 | B47: =Source!E131 -> 35 | C47: =Source!G131 -> Радиатор отопительный, стальной, панельный, ГОСТ 31311, с боковым подключением, типа 21 K, высота 400 мм, длина 1400 мм, теплоотдача 2259 Вт | D47: шт. | E47: =Source!I131 -> 4 | F47: =Source!U65 | G47: =Source!I131 -> 4
A48: 36 | B48: =Source!E133 -> 36 | C48: =Source!G133 -> Радиатор отопительный, стальной, панельный, ГОСТ 31311, с боковым подключением, типа 21 K, высота 400 мм, длина 1600 мм, теплоотдача 2582 Вт | D48: шт. | E48: =Source!I133 -> 2 | F48: =Source!U65 | G48: =Source!I133 -> 2
A49: 37 | B49: =Source!E135 -> 37 | C49: =Source!G135 -> Установка радиаторов стальных панельных однорядных с креплением к стене длиной свыше 1600 до 2000 мм | D49: 100 шт. | E49: =Source!I135 -> 0.1 | F49: =Source!U65 | G49: ="=(6+"&"4)/"&"100" -> =(6+4)/100
A50: 38 | B50: =Source!E137 -> 38 | C50: =Source!G137 -> Радиатор отопительный, стальной, панельный, ГОСТ 31311, с боковым подключением, типа 21 K, высота 400 мм, длина 1800 мм, теплоотдача 2905 Вт | D50: шт. | E50: =Source!I137 -> 6 | F50: =Source!U65 | G50: =Source!I137 -> 6
A51: 39 | B51: =Source!E139 -> 39 | C51: =Source!G139 -> Стальной панельный радиатор боковое подключение Royal Thermо С 21-0400-2000 (тепловая мощность 2,8201 кВт) | D51: ШТ | E51: =Source!I139 -> 4 | F51: =Source!U65 | G51: =Source!I139 -> 4
A52: 40 | B52: =Source!E141 -> 40 | C52: =Source!G141 -> Установка радиаторов стальных панельных однорядных с креплением к стене длиной до 1600 мм | D52: 100 шт. | E52: =Source!I141 -> 0.19 | F52: =Source!U65 | G52: ="=(2+"&"17)/"&"100" -> =(2+17)/100
A53: 41 | B53: =Source!E143 -> 41 | C53: =Source!G143 -> Радиатор отопительный, стальной, панельный, ГОСТ 31311, с боковым подключением, типа 22 K, высота 400 мм, длина 800 мм, теплоотдача 1683 Вт | D53: шт. | E53: =Source!I143 -> 2 | F53: =Source!U65 | G53: =Source!I143 -> 2
A54: 42 | B54: =Source!E145 -> 42 | C54: =Source!G145 -> Радиатор отопительный, стальной, панельный, ГОСТ 31311, с боковым подключением, типа 22 K, высота 400 мм, длина 1600 мм, теплоотдача 3366 Вт | D54: шт. | E54: =Source!I145 -> 17 | F54: =Source!U65 | G54: =Source!I145 -> 17
A55: 43 | B55: =Source!E147 -> 43 | C55: =Source!G147 -> Установка радиаторов стальных панельных однорядных с креплением к стене длиной свыше 1600 до 2000 мм | D55: 100 шт. | E55: =Source!I147 -> 0.02 | F55: =Source!U65 | G55: ="=(2)/"&"100" -> =(2)/100
A56: 44 | B56: =Source!E149 -> 44 | C56: =Source!G149 -> Радиатор отопительный, стальной, панельный, ГОСТ 31311, с боковым подключением, типа 22 K, высота 400 мм, длина 1800 мм, теплоотдача 3787 Вт | D56: шт. | E56: =Source!I149 -> 2 | F56: =Source!U65 | G56: =Source!I149 -> 2
A57: 45 | B57: =Source!E151 -> 45 | C57: =Source!G151 -> Установка радиаторов стальных панельных однорядных с креплением к стене длиной до 1600 мм | D57: 100 шт. | E57: =Source!I151 -> 0.31 | F57: =Source!U65 | G57: ="=(1+"&"5+"&"13+"&"12)/"&"100" -> =(1+5+13+12)/100
A58: 46 | B58: =Source!E153 -> 46 | C58: =Source!G153 -> Стальной панельный радиатор боковое подключение Royal Thermо С 33-0400-0400 (тепловая мощность 1,0383 кВт) | D58: ШТ | E58: =Source!I153 -> 1 | F58: =Source!U65 | G58: =Source!I153 -> 1
A59: 47 | B59: =Source!E155 -> 47 | C59: =Source!G155 -> Стальной панельный радиатор боковое подключение Royal Thermо С 33-0400-0600 (тепловая мощность 1,5575 кВт) | D59: ШТ | E59: =Source!I155 -> 5 | F59: =Source!U65 | G59: =Source!I155 -> 5
A60: 48 | B60: =Source!E157 -> 48 | C60: =Source!G157 -> Радиатор отопительный, стальной, панельный, ГОСТ 31311, с боковым подключением, типа 33 K, высота 400 мм, длина 800 мм, теплоотдача 2405 Вт | D60: шт. | E60: =Source!I157 -> 13 | F60: =Source!U65 | G60: =Source!I157 -> 13
A61: 49 | B61: =Source!E159 -> 49 | C61: =Source!G159 -> Радиатор отопительный, стальной, панельный, ГОСТ 31311, с боковым подключением, типа 33 K, высота 400 мм, длина 1000 мм, теплоотдача 3006 Вт | D61: шт. | E61: =Source!I159 -> 12 | F61: =Source!U65 | G61: =Source!I159 -> 12
A62: 50 | B62: =Source!E162 -> 50 | C62: =Source!G162 -> Комплект KIT 1/2" (футорки 1/2" - 4 шт., возд. 1/2", загл. 1/2", ключ для воздух) | D62: ШТ | E62: =Source!I162 -> 347 | F62: =Source!U65 | G62: =Source!I162 -> 347
A63: 51 | B63: =Source!E165 -> 51 | C63: =Source!G165 -> Установка терморегулирующих клапанов на отопительных приборах | D63: 100 шт. | E63: =Source!I165 -> 3.47 | F63: =Source!U65 | G63: ="=347/"&"100" -> =347/100
A64: 52 | B64: =Source!E171 -> 52 | C64: =Source!G171 -> Установка прибора на резьбовых соединениях | D64: 1 ШТ. | E64: =Source!I171 -> 347 | F64: =Source!U65 | G64: =Source!I171 -> 347
A65: =CONCATENATE("Раздел: ", Source!G206) -> Раздел: Арматура трубопроводная
A66: 53 | B66: =Source!E210 -> 53 | C66: =Source!G210 -> Кран шаровой, латунный, никелированный, запорный, полнопроходной, со спускным элементом, с алюминиевой ручкой, муфтовый, температура рабочей среды от -15 до +110°С, пропускная способность 28 м3/ч, номинальное давление PN 4,0 МПа, номинальный диаметр DN 20 мм | D66: шт. | E66: =Source!I210 -> 120 | F66: =Source!U206 | G66: =Source!I210 -> 120
A67: 54 | B67: =Source!E212 -> 54 | C67: =Source!G212 -> Установка кранов воздушных | D67: 1 комплект | E67: =Source!I212 -> 20 | F67: =Source!U206 | G67: =Source!I212 -> 20
A68: 55 | B68: =Source!E218 -> 55 | C68: =Source!G218 -> Кран шаровой, латунный, полнопроходной, муфтовый, 11б27п1, номинальное давление PN 1,6 МПа, номинальный диаметр DN 15 мм | D68: шт. | E68: =Source!I218 -> 86 | F68: =Source!U206 | G68: =Source!I218 -> 86
A69: 56 | B69: =Source!E220 -> 56 | C69: =Source!G220 -> Кран шаровой, латунный, полнопроходной, муфтовый, 11б27п1, номинальное давление PN 1,6 МПа, номинальный диаметр DN 20 мм | D69: шт. | E69: =Source!I220 -> 10 | F69: =Source!U206 | G69: =Source!I220 -> 10
A70: 57 | B70: =Source!E222 -> 57 | C70: =Source!G222 -> Кран шаровой, латунный, полнопроходной, муфтовый, 11б27п1, номинальное давление PN 1,6 МПа, номинальный диаметр DN 25 мм | D70: шт. | E70: =Source!I222 -> 6 | F70: =Source!U206 | G70: =Source!I222 -> 6
A71: 58 | B71: =Source!E224 -> 58 | C71: =Source!G224 -> Установка прибора на резьбовых соединениях | D71: 1 ШТ. | E71: =Source!I224 -> 45 | F71: =Source!U206 | G71: =Source!I224 -> 45
A72: 59 | B72: =Source!E226 -> 59 | C72: =Source!G226 -> Регулятор перепада давления Dy15 APT-R 15 | D72: ШТ | E72: =Source!I226 -> 45 | F72: =Source!U206 | G72: =Source!I226 -> 45
A73: 60 | B73: =Source!E228 -> 60 | C73: =Source!G228 -> Клапан запорно-балансировочный, латунный, муфтовый, ручной, с измерительным ниппелем и дренажным краном, максимальная температура +120°С, пропускная способность 1,6 м3/ч, номинальное давление PN 1,6 МПа, номинальный диаметр DN 15 мм | D73: шт. | E73: =Source!I228 -> 45 | F73: =Source!U206 | G73: =Source!I228 -> 45
A74: 61 | B74: =Source!E230 -> 61 | C74: =Source!G230 -> Установка прибора на резьбовых соединениях | D74: 1 ШТ. | E74: =Source!I230 -> 4 | F74: =Source!U206 | G74: =Source!I230 -> 4
A75: 62 | B75: =Source!E232 -> 62 | C75: =Source!G232 -> Регулятор перепада давления Dy20 APT-R 20 | D75: ШТ | E75: =Source!I232 -> 4 | F75: =Source!U206 | G75: =Source!I232 -> 4
A76: 63 | B76: =Source!E234 -> 63 | C76: =Source!G234 -> Клапан запорно-балансировочный, латунный, муфтовый, ручной, с измерительным ниппелем и дренажным краном, максимальная температура +120°С, пропускная способность 2,5 м3/ч, номинальное давление PN 1,6 МПа, номинальный диаметр DN 20 мм | D76: шт. | E76: =Source!I234 -> 4 | F76: =Source!U206 | G76: =Source!I234 -> 4
A77: 64 | B77: =Source!E236 -> 64 | C77: =Source!G236 -> Установка прибора на резьбовых соединениях | D77: 1 ШТ. | E77: =Source!I236 -> 3 | F77: =Source!U206 | G77: =Source!I236 -> 3
A78: 65 | B78: =Source!E240 -> 65 | C78: =Source!G240 -> Клапан запорно-балансировочный, латунный, муфтовый, ручной, с измерительным ниппелем и дренажным краном, максимальная температура +120°С, пропускная способность 4,0 м3/ч, номинальное давление PN 1,6 МПа, номинальный диаметр DN 25 мм | D78: шт. | E78: =Source!I240 -> 3 | F78: =Source!U206 | G78: =Source!I240 -> 3
A79: 66 | B79: =Source!E243 -> 66 | C79: =Source!G243 -> Установка распределительного коллектора для систем отопления и водоснабжения диаметром до 32 мм до 4-х контуров | D79: 10 шт. | E79: =Source!I243 -> 0.1 | F79: =Source!U206 | G79: ="=1/"&"10" -> =1/10
A80: 67 | B80: =Source!E245 -> 67 | C80: =Source!G245 -> Установка распределительного коллектора для систем отопления и водоснабжения, добавляется к позиции 3.16-39-1 на каждый последующий контур | D80: 10 шт. | E80: =Source!I245 -> 0.01 | F80: =Source!U206 | G80: ="=1/"&"100" -> =1/100
A81: 68 | B81: =Source!E247 -> 68 | C81: =Source!G247 -> Комплект коллекторов РИДАН FHF-5RF set с расходомерами, кронштейнами и воздухоотводчиками, 5 контуров (2024-00272-00-0-ИОС4.1 Лист 5 Схема гребенки отопления) | D81: ШТ | E81: =Source!I247 -> 1 | F81: =Source!U206 | G81: =Source!I247 -> 1
A82: =CONCATENATE("Раздел: ", Source!G280) -> Раздел: Трубы стальные
A83: 69 | B83: =Source!E284 -> 69 | C83: =Source!G284 -> Прокладка трубопроводов отопления из стальных водогазопроводных неоцинкованных труб диаметром 15 мм | D83: 100 м трубопровода | E83: =Source!I284 -> 34 | F83: =Source!U280 | G83: ="=3400/"&"100" -> =3400/100
A84: 70 | B84: =Source!E288 -> 70 | C84: =Source!G288 -> Прокладка трубопроводов отопления из стальных водогазопроводных неоцинкованных труб диаметром 20 мм | D84: 100 м трубопровода | E84: =Source!I288 -> 6 | F84: =Source!U280 | G84: ="=600/"&"100" -> =600/100
A85: 71 | B85: =Source!E292 -> 71 | C85: =Source!G292 -> Прокладка трубопроводов отопления из стальных водогазопроводных неоцинкованных труб диаметром 25 мм | D85: 100 м трубопровода | E85: =Source!I292 -> 1.1 | F85: =Source!U280 | G85: ="=110/"&"100" -> =110/100
A86: 72 | B86: =Source!E296 -> 72 | C86: =Source!G296 -> Прокладка трубопроводов отопления из стальных водогазопроводных неоцинкованных труб диаметром 32 мм | D86: 100 м трубопровода | E86: =Source!I296 -> 2 | F86: =Source!U280 | G86: ="=200/"&"100" -> =200/100
A87: 73 | B87: =Source!E300 -> 73 | C87: =Source!G300 -> Прокладка трубопроводов отопления из стальных водогазопроводных неоцинкованных труб диаметром 40 мм | D87: 100 м трубопровода | E87: =Source!I300 -> 1 | F87: =Source!U280 | G87: ="=100/"&"100" -> =100/100
A88: 74 | B88: =Source!E304 -> 74 | C88: =Source!G304 -> Прокладка трубопроводов отопления и водоснабжения из стальных электросварных труб диаметром 50 мм | D88: 100 м трубопровода | E88: =Source!I304 -> 1.3 | F88: =Source!U280 | G88: ="=130/"&"100" -> =130/100
A89: 75 | B89: =Source!E308 -> 75 | C89: =Source!G308 -> Прокладка трубопроводов отопления и водоснабжения из стальных электросварных труб диаметром 65 мм | D89: 100 м трубопровода | E89: =Source!I308 -> 0.2 | F89: =Source!U280 | G89: ="=20/"&"100" -> =20/100
A90: =CONCATENATE("Раздел: ", Source!G343) -> Раздел: Изоляция трубная
A91: 76 | B91: =Source!E347 -> 76 | C91: =Source!G347 -> Изоляция трубопроводов цилиндрами, полуцилиндрами из минеральной ваты на синтетическом связующем | D91: 1 м3 | E91: =Source!I347 -> 17.18836 | F91: =Source!U343 | G91: ="=(((3,14*"&"(0,021+"&"0,04)*"&"0,04)*"&"800)+"&"((3,14*"&"(0,028+"&"0,04)*"&"0,04)*"&"600)+"&"((3,14*"&"(0,032+"&"0,04)*"&"0,04)*"&"110)+"&"((3,14*"&"(0,038+"&"0,04)*"&"0,04)*"&"200)+"&"((3,14*"&"(0,048+"&"0,04)*"&"0,04)*"&"100)+"&"((3,14*"&"(0,057+"&"0,04)*"&"0,04)*"&"130)+"&"((3,14*"&"(0,076+"&"0,04)*"&"0,04)*"&"20))" -> =(((3,14*(0,021+0,04)*0,04)*800)+((3,14*(0,028+0,04)*0,04)*600)+((3,14*(0,032+0,04)*0,04)*110)+((3,14*(0,038+0,04)*0,04)*200)+((3,14*(0,048+0,04)*0,04)*100)+((3,14*(0,057+0,04)*0,04)*130)+((3,14*(0,076+0,04)*0,04)*20))
A92: 77 | B92: =Source!E349 -> 77 | C92: =Source!G349 -> Цилиндры и полуцилиндры теплоизоляционные минераловатные на синтетическом связующем, простые, диаметр 25 мм, толщина 40 мм | D92: м | E92: =Source!I349 -> 824 | F92: =Source!U343 | G92: ="=800*"&"1,03" -> =800*1,03
A93: 78 | B93: =Source!E351 -> 78 | C93: =Source!G351 -> Цилиндры и полуцилиндры теплоизоляционные минераловатные на синтетическом связующем, простые, диаметр 25 мм, толщина 40 мм (прим. диам.28 мм) | D93: м | E93: =Source!I351 -> 618 | F93: =Source!U343 | G93: =Source!I351 -> 618
A94: 79 | B94: =Source!E353 -> 79 | C94: =Source!G353 -> Цилиндры и полуцилиндры теплоизоляционные минераловатные на синтетическом связующем, простые, диаметр 32 мм, толщина 40 мм | D94: м | E94: =Source!I353 -> 113.63 | F94: =Source!U343 | G94: ="=110*"&"1,033" -> =110*1,033
A95: 80 | B95: =Source!E355 -> 80 | C95: =Source!G355 -> Цилиндры и полуцилиндры теплоизоляционные минераловатные на синтетическом связующем, простые, диаметр 38 мм, толщина 40 мм | D95: м | E95: =Source!I355 -> 206 | F95: =Source!U343 | G95: ="=200*"&"1,03" -> =200*1,03
A96: 81 | B96: =Source!E357 -> 81 | C96: =Source!G357 -> Цилиндры и полуцилиндры теплоизоляционные минераловатные на синтетическом связующем, простые, диаметр 45 мм, толщина 40 мм (прим. диам.48 мм) | D96: м | E96: =Source!I357 -> 103 | F96: =Source!U343 | G96: =Source!I357 -> 103
A97: 82 | B97: =Source!E359 -> 82 | C97: =Source!G359 -> Цилиндры и полуцилиндры теплоизоляционные минераловатные на синтетическом связующем, простые, диаметр 57 мм, толщина 40 мм | D97: м | E97: =Source!I359 -> 133.9 | F97: =Source!U343 | G97: ="=130*"&"1,03" -> =130*1,03
A98: 83 | B98: =Source!E361 -> 83 | C98: =Source!G361 -> Цилиндры и полуцилиндры теплоизоляционные минераловатные на синтетическом связующем, простые, диаметр 76 мм, толщина 40 мм | D98: м | E98: =Source!I361 -> 20.6 | F98: =Source!U343 | G98: ="=20*"&"1,03" -> =20*1,03
C101: Главный инженер проекта _________________ | D101: =IF(Source!X12<>"", Source!X12," ")
C103: Составил _________________ | D103: =IF(Source!AB12<>"", Source!AB12," ") -> Соколова И.Н.

Sheet Source
A1: 0 | B1: Smeta.RU (495) 974-1589 | D1: _PS_ | F1: 0 | G1: 0 | H1: 0 | I1: Smeta.RU | K1: 1 | L1: 74563 | M1: 10 | N1: 12 | O1: 0 | P1: 0 | Q1: 3
A4: 1 | B4: 1 | C4: -1 | G4: Капитальный ремонт здания Государственного бюджетного общеобразовательного учреждения города Москвы "Школа №236" по адресу: г. Москва, улица Клязьминская, дом 7, корпус 4 | EC4: 0
A12: 1 | B12: 465 | C12: 0 | D12: =ROW(A424) -> 424 | E12: 0 | G12: 02-01-06 Отопление | I12: 0 | J12: 2024-00272-00-0-ИОС4.1 | K12: 0 | L12: 0 | M12: 4098 | O12: 0 | P12: 0 | Q12: 0 | R12: 0 | S12: 0 | T12: 1 | V12: 0 | AB12: Соколова И.Н. | BB12: 0 | BH12: Сметные нормы списания | BI12: Коды ОКП для ТСН-2001 МГЭ Дополнение 80 | BJ12: 1 | BK12: 1 | BL12: 0 | BM12: 0 | BN12: 1 | BO12: 0 | BP12: 6 | BQ12: 2 | BR12: 1 | BS12: 1 | BT12: 0 | BU12: 0 | BV12: 0 | BW12: 0 | BX12: 0 | BZ12: Типовой расчет для ТСН-2001 МГЭ, Дополнение 80, ремонт (1) | CA12: Территориальные сметные нормативы для Москвы ТСН-2001 (МГЭ), дополнение 80 | CB12: Территориальные сметные нормативы для Москвы ТСН-2001 (МГЭ), дополнение 80 | CC12: Территориальные сметные нормативы для Москвы ТСН-2001 (МГЭ), дополнение 80 | CD12: Территориальные сметные нормативы для Москвы ТСН-2001 (МГЭ), дополнение 80 | CE12: Поправки для ТСН-2001 от 28.11.2025 г. доп.79 | CF12: 0 | CG12: 0 | CH12: 8200 | CK12: 80 | CQ12: Территориальные сметные нормативы для Москвы (ТСН-2001) | CR12: ТЕР | CS12: 41660 | CT12: 1 | CU12: 80 | CY12: 0 | EC12: 0
A15: 15 | B15: 1
A18: 52 | B18: =B424 -> 465 | C18: =C424 -> 1 | D18: =D424 -> 12 | E18: =E424 -> 0 | F18: =F424 | G18: =G424 -> 02-01-06 Отопление | O18: =O424 -> 1023233.4 | P18: =P424 -> 978175.47 | Q18: =Q424 -> 4626.47 | R18: =R424 -> 895.4 | S18: =S424 -> 40431.44 | T18: =T424 -> 0 | U18: =U424 -> 3249.222 | V18: =V424 -> 0 | ... GX18: =GX424 -> 0
A20: 3 | B20: 1 | D20: =ROW(A394) -> 394 | F20: 02-01-06 | G20: Отопление | I20: 0 | J20: 2024-00272-00-0-ИОС4.1 | K20: -1 | L20: 02-01-06 | S20: 0 | T20: 0 | V20: 0 | BX20: 0 | CF20: 0 | CG20: 0
A22: 52 | B22: =B394 -> 1 | C22: =C394 -> 3 | D22: =D394 -> 20 | E22: =E394 -> 0 | F22: =F394 -> 02-01-06 | G22: =G394 -> Отопление | O22: =O394 -> 1023233.4 | P22: =P394 -> 978175.47 | Q22: =Q394 -> 4626.47 | R22: =R394 -> 895.4 | S22: =S394 -> 40431.44 | T22: =T394 -> 0 | U22: =U394 -> 3249.222 | V22: =V394 -> 0 | ... GX22: =GX394 -> 0
A24: 4 | B24: 1 | D24: =ROW(A35) -> 35 | G24: Конвекторы | I24: 0 | K24: -1 | S24: 0 | T24: 0 | V24: 0 | BX24: 0 | CJ24: 0
A26: 52 | B26: =B35 -> 1 | C26: =C35 -> 4 | D26: =D35 -> 24 | E26: =E35 -> 0 | F26: =F35 | G26: =G35 -> Конвекторы | O26: =O35 -> 1368.77 | P26: =P35 -> 1319.4 | Q26: =Q35 -> 3.14 | R26: =R35 -> 0.45 | S26: =S35 -> 46.23 | T26: =T35 -> 0 | U26: =U35 -> 3.558753 | V26: =V35 -> 0 | ... GX26: =GX35 -> 0
A28: 17 | B28: 1 | C28: =ROW(SmtRes!A4) -> 4 | D28: =ROW(EtalonRes!A5) -> 5 | E28: 1 | F28: 4.8-254-1 | G28: Монтаж приборов нагревательных, электрополотенце/прим. конвектор электрический настенный 1000 Вт | H28: 1 ШТ. | I28: =ROUND(1+2,9) -> 3 | J28: 0 | K28: =ROUND(1+2,9) -> 3 | O28: =ROUND(CP28,2) -> 50.6 | P28: =ROUND((ROUND((AC28*AW28*I28),2)*BC28),2) -> 1.23 | Q28: =(ROUND((ROUND((((ET28*1.1))*AV28*I28),2)*BB28),2)+ROUND((ROUND(((AE28-((EU28*1.1)))*AV28*I28),2)*BS28),2)) -> 3.14 | R28: =(ROUND((ROUND((((EU28*1.1))*AV28*I28),2)*BS28),2)+ROUND((ROUND(((AE28-((EU28*1.1)))*AV28*I28),2)*BS28),2)) -> 0.45 | S28: =ROUND((ROUND((AF28*AV28*I28),2)*BA28),2) -> 46.23 | T28: =ROUND(CU28*I28,2) -> 0 | U28: =CV28*I28 -> 3.558753 | V28: =CW28*I28 -> 0 | W28: =ROUND(CX28*I28,2) -> 0 | X28: =(ROUND((((S28+ROUND((ROUND((((EU28*1.1))*AV28*I28),2)*BS28),2))*AT28)/100),2)+ROUND(((ROUND((ROUND(((AE28-((EU28*1.1)))*AV28*I28),2)*BS28),2)*AT28)/100),2)) -> 45.28 | Y28: =(ROUND((((S28+ROUND((ROUND((((EU28*1.1))*AV28*I28),2)*BS28),2))*AU28)/100),2)+ROUND(((ROUND((ROUND(((AE28-((EU28*1.1)))*AV28*I28),2)*BS28),2)*AU28)/100),2)) -> 23.81 | AA28: 60255014 | AB28: =ROUND((AC28+AD28+AF28),6) -> 16.129 | AC28: =ROUND((ES28),6) -> 0.41 | AD28: =ROUND(((((ET28*1.1))-((EU28*1.1)))+AE28),6) -> 1.001 | AE28: =ROUND(((EU28*1.1)),6) -> 0.143 | AF28: =ROUND(((EV28*1.1)),6) -> 14.718 | AG28: =ROUND((AP28),6) -> 0 | AH28: =((EW28*1.1)) -> 1.133 | AI28: =((EX28*1.1)) -> 0 | AJ28: =(AS28) -> 0 | AK28: 14.7 | AL28: 0.41 | AM28: 0.91 | AN28: 0.13 | AO28: 13.38 | AP28: 0 | AQ28: 1.03 | AR28: 0 | AS28: 0 | AT28: 97 | AU28: 51 | AV28: 1.047 | AW28: 1 | AZ28: 1 | BA28: 1 | BB28: 1 | BC28: 1 | BH28: 0 | BI28: 2 | BJ28: ТСН-2001.4 Доп. 68, Сб. 8, т. 254, поз. 1 | BM28: 67 | BN28: 58973374 | BO28: 4.8-254-1 | BP28: 1 | BQ28: 40 | BR28: 0 | BS28: 1 | BT28: 1 | BU28: 1 | BV28: 1 | BW28: 1 | BX28: 1 | BZ28: 97 | CA28: 51 | CE28: 1566 | CF28: 0 | CG28: 0 | CM28: 0 | CN28: Поправка: Гл.12.Прил.8.п.8. 5_12.00.01.11.003 Наименование: При наличии усложненных условий производства работ (стесненность, сложность складирования и транспортной логистики, наличие в зоне производства работ действующего технологического оборудования или движения технологического транспорта и т.п.) для объектов, расположенных за пределами территории круговой магистральной системы улиц "Садовое кольцо" и за пределами Третьего транспортного кольца города Москвы пунктов "а" и "б", но в пределах Московской кольцевой автомобильной дороги | CO28: 0 | CP28: =(P28+Q28+S28) -> 50.6 | CQ28: =ROUND((ROUND((AC28*AW28*1),2)*BC28),2) -> 0.41 | CR28: =(ROUND((ROUND((((ET28*1.1))*AV28*1),2)*BB28),2)+ROUND((ROUND(((AE28-((EU28*1.1)))*AV28*1),2)*BS28),2)) -> 1.05 | CS28: =(ROUND((ROUND((((EU28*1.1))*AV28*1),2)*BS28),2)+ROUND((ROUND(((AE28-((EU28*1.1)))*AV28*1),2)*BS28),2)) -> 0.15 | CT28: =ROUND((ROUND((AF28*AV28*1),2)*BA28),2) -> 15.41 | CU28: =AG28 -> 0 | CV28: =(AH28*AV28) -> 1.186251 | CW28: =AI28 -> 0 | CX28: =AJ28 -> 0 | CY28: =(ROUND((((S28+ROUND((ROUND((((EU28*1.1))*AV28*1),2)*BS28),2))*AT28)/100),2)+ROUND(((ROUND((ROUND(((AE28-((EU28*1.1)))*AV28*1),2)*BS28),2)*AT28)/100),2)) -> 44.99 | CZ28: =(ROUND((((S28+ROUND((ROUND((((EU28*1.1))*AV28*1),2)*BS28),2))*AU28)/100),2)+ROUND(((ROUND((ROUND(((AE28-((EU28*1.1)))*AV28*1),2)*BS28),2)*AU28)/100),2)) -> 23.65 | DE28: *1,1 | DF28: *1,1 | DG28: *1,1 | DI28: *1,1 | DJ28: *1,1 | DN28: 0 | DO28: 0 | DP28: 1 | DQ28: 1 | DU28: 1013 | DV28: 1 ШТ. | DW28: 1 ШТ. | DX28: 1 | EE28: 60088299 | EF28: 40 | EG28: Монтаж оборудования | EH28: 0 | EJ28: 2 | EK28: 67 | EL28: ТСН-2001.4-8. Электротехнические установки | EM28: ТСН-2001.4-8-1 | EO28: Поправка: Гл.12.Прил.8.п.8. 5_12.00.01.11.003 | EQ28: 0 | ER28: 14.7 | ES28: 0.41 | ET28: 0.91 | EU28: 0.13 | EV28: 13.38 | EW28: 1.03 | EX28: 0 | EY28: 0 | FQ28: 0 | FR28: 0 | FS28: 0 | FX28: 97 | FY28: 51 | GD28: 1 | GF28: -1561628963 | GG28: 2 | GH28: 1 | GI28: 2 | GJ28: 0 | GK28: 0 | GL28: =ROUND(IF(AND(BH28=3,BI28=3,FS28<>0),P28,0),2) -> 0 | GM28: =ROUND(O28+X28+Y28,2)+GX28 -> 119.69 | GN28: =IF(OR(BI28=0,BI28=1),GM28-GX28,0) -> 0 | GO28: =IF(BI28=2,GM28-GX28,0) -> 119.69 | GP28: =IF(BI28=4,GM28-GX28,0) -> 0 | GR28: 0 | GS28: 3 | GT28: 0 | GV28: =ROUND((GT28),6) -> 0 | GW28: 1 | GX28: =ROUND(HC28*I28,2) -> 0 | HA28: 0 | HB28: 0 | HC28: =GV28*GW28 -> 0 | HS28: 0 | IK28: 0
A29: 17 | B29: 1 | C29: =ROW(SmtRes!A8) -> 8 | D29: =ROW(EtalonRes!A10) -> 10 | E29: 1 | F29: 4.8-254-1 | G29: Монтаж приборов нагревательных, электрополотенце/прим. конвектор электрический настенный 1000 Вт | H29: 1 ШТ. | I29: =ROUND(1+2,9) -> 3 | J29: 0 | K29: =ROUND(1+2,9) -> 3 | O29: =ROUND(CP29,2) -> 2596 | P29: =ROUND((ROUND((AC29*AW29*I29),2)*BC29),2) -> 4.86 | Q29: =(ROUND((ROUND((((ET29*1.1))*AV29*I29),2)*BB29),2)+ROUND((ROUND(((AE29-((EU29*1.1)))*AV29*I29),2)*BS29),2)) -> 48.95 | R29: =(ROUND((ROUND((((EU29*1.1))*AV29*I29),2)*BS29),2)+ROUND((ROUND(((AE29-((EU29*1.1)))*AV29*I29),2)*BS29),2)) -> 24.75 | S29: =ROUND((ROUND((AF29*AV29*I29),2)*BA29),2) -> 2542.19 | T29: =ROUND(CU29*I29,2) -> 0 | U29: =CV29*I29 -> 3.558753 | V29: =CW29*I29 -> 0 | W29: =ROUND(CX29*I29,2) -> 0 | X29: =(ROUND((((S29+ROUND((ROUND((((EU29*1.1))*AV29*I29),2)*BS29),2))*AT29)/100),2)+ROUND(((ROUND((ROUND(((AE29-((EU29*1.1)))*AV29*I29),2)*BS29),2)*AT29)/100),2)) -> 2489.93 | Y29: =(ROUND((((S29+ROUND((ROUND((((EU29*1.1))*AV29*I29),2)*BS29),2))*AU29)/100),2)+ROUND(((ROUND((ROUND(((AE29-((EU29*1.1)))*AV29*I29),2)*BS29),2)*AU29)/100),2)) -> 1309.14 | AA29: 60255011 | AB29: =ROUND((AC29+AD29+AF29),6) -> 16.129 | AC29: =ROUND((ES29),6) -> 0.41 | AD29: =ROUND(((((ET29*1.1))-((EU29*1.1)))+AE29),6) -> 1.001 | AE29: =ROUND(((EU29*1.1)),6) -> 0.143 | AF29: =ROUND(((EV29*1.1)),6) -> 14.718 | AG29: =ROUND((AP29),6) -> 0 | AH29: =((EW29*1.1)) -> 1.133 | AI29: =((EX29*1.1)) -> 0 | AJ29: =(AS29) -> 0 | AK29: 14.7 | AL29: 0.41 | AM29: 0.91 | AN29: 0.13 | AO29: 13.38 | AP29: 0 | AQ29: 1.03 | AR29: 0 | AS29: 0 | AT29: 97 | AU29: 51 | AV29: 1.047 | AW29: 1 | AZ29: 1 | BA29: 54.99 | BB29: 15.59 | BC29: 3.95 | BH29: 0 | BI29: 2 | BJ29: ТСН-2001.4 Доп. 68, Сб. 8, т. 254, поз. 1 | BM29: 67 | BN29: 58973374 | BO29: 4.8-254-1 | BP29: 1 | BQ29: 40 | BR29: 0 | BS29: 54.99 | BT29: 1 | BU29: 1 | BV29: 1 | BW29: 1 | BX29: 1 | BZ29: 97 | CA29: 51 | CE29: 1566 | CF29: 0 | CG29: 0 | CM29: 0 | CN29: Поправка: Гл.12.Прил.8.п.8. 5_12.00.01.11.003 Наименование: При наличии усложненных условий производства работ (стесненность, сложность складирования и транспортной логистики, наличие в зоне производства работ действующего технологического оборудования или движения технологического транспорта и т.п.) для объектов, расположенных за пределами территории круговой магистральной системы улиц "Садовое кольцо" и за пределами Третьего транспортного кольца города Москвы пунктов "а" и "б", но в пределах Московской кольцевой автомобильной дороги | CO29: 0 | CP29: =(P29+Q29+S29) -> 2596 | CQ29: =ROUND((ROUND((AC29*AW29*1),2)*BC29),2) -> 1.62 | CR29: =(ROUND((ROUND((((ET29*1.1))*AV29*1),2)*BB29),2)+ROUND((ROUND(((AE29-((EU29*1.1)))*AV29*1),2)*BS29),2)) -> 16.37 | CS29: =(ROUND((ROUND((((EU29*1.1))*AV29*1),2)*BS29),2)+ROUND((ROUND(((AE29-((EU29*1.1)))*AV29*1),2)*BS29),2)) -> 8.25 | CT29: =ROUND((ROUND((AF29*AV29*1),2)*BA29),2) -> 847.4 | CU29: =AG29 -> 0 | CV29: =(AH29*AV29) -> 1.186251 | CW29: =AI29 -> 0 | CX29: =AJ29 -> 0 | CY29: =(ROUND((((S29+ROUND((ROUND((((EU29*1.1))*AV29*1),2)*BS29),2))*AT29)/100),2)+ROUND(((ROUND((ROUND(((AE29-((EU29*1.1)))*AV29*1),2)*BS29),2)*AT29)/100),2)) -> 2473.93 | CZ29: =(ROUND((((S29+ROUND((ROUND((((EU29*1.1))*AV29*1),2)*BS29),2))*AU29)/100),2)+ROUND(((ROUND((ROUND(((AE29-((EU29*1.1)))*AV29*1),2)*BS29),2)*AU29)/100),2)) -> 1300.72 | DE29: *1,1 | DF29: *1,1 | DG29: *1,1 | DI29: *1,1 | DJ29: *1,1 | DN29: 0 | DO29: 0 | DP29: 1 | DQ29: 1 | DU29: 1013 | DV29: 1 ШТ. | DW29: 1 ШТ. | DX29: 1 | EE29: 60088299 | EF29: 40 | EG29: Монтаж оборудования | EH29: 0 | EJ29: 2 | EK29: 67 | EL29: ТСН-2001.4-8. Электротехнические установки | EM29: ТСН-2001.4-8-1 | EO29: Поправка: Гл.12.Прил.8.п.8. 5_12.00.01.11.003 | EQ29: 0 | ER29: 14.7 | ES29: 0.41 | ET29: 0.91 | EU29: 0.13 | EV29: 13.38 | EW29: 1.03 | EX29: 0 | EY29: 0 | FQ29: 0 | FR29: 0 | FS29: 0 | FX29: 97 | FY29: 51 | GD29: 1 | GF29: -1561628963 | GG29: 2 | GH29: 1 | GI29: 2 | GJ29: 0 | GK29: 0 | GL29: =ROUND(IF(AND(BH29=3,BI29=3,FS29<>0),P29,0),2) -> 0 | GM29: =ROUND(O29+X29+Y29,2)+GX29 -> 6395.07 | GN29: =IF(OR(BI29=0,BI29=1),GM29-GX29,0) -> 0 | GO29: =IF(BI29=2,GM29-GX29,0) -> 6395.07 | GP29: =IF(BI29=4,GM29-GX29,0) -> 0 | GR29: 0 | GS29: 3 | GT29: 0 | GV29: =ROUND((GT29),6) -> 0 | GW29: 1 | GX29: =ROUND(HC29*I29,2) -> 0 | HA29: 0 | HB29: 0 | HC29: =GV29*GW29 -> 0 | HS29: 0 | IK29: 0
A30: 17 | B30: 1 | E30: 2 | F30: 13.1-11-142 | G30: Конвектор электрический, номинальная мощность 0,5 кВт, для отопления жилых и промышленных помещений | H30: шт. | I30: 1 | J30: 0 | K30: 1 | O30: =ROUND(CP30,2) -> 388.69 | P30: =ROUND((ROUND((AC30*I30),2)*BC30),2) -> 388.69 | Q30: =(ROUND((ROUND(((ET30)*AV30*I30),2)*BB30),2)+ROUND((ROUND(((AE30-(EU30))*AV30*I30),2)*BS30),2)) -> 0 | R30: =(ROUND((ROUND(((EU30)*AV30*I30),2)*BS30),2)+ROUND((ROUND(((AE30-(EU30))*AV30*I30),2)*BS30),2)) -> 0 | S30: =ROUND((ROUND((AF30*AV30*I30),2)*BA30),2) -> 0 | T30: =ROUND(CU30*I30,2) -> 0 | U30: =CV30*I30 -> 0 | V30: =CW30*I30 -> 0 | W30: =ROUND(CX30*I30,2) -> 0 | X30: =(ROUND((((S30+ROUND((ROUND(((EU30)*AV30*I30),2)*BS30),2))*AT30)/100),2)+ROUND(((ROUND((ROUND(((AE30-(EU30))*AV30*I30),2)*BS30),2)*AT30)/100),2)) -> 0 | Y30: =(ROUND((((S30+ROUND((ROUND(((EU30)*AV30*I30),2)*BS30),2))*AU30)/100),2)+ROUND(((ROUND((ROUND(((AE30-(EU30))*AV30*I30),2)*BS30),2)*AU30)/100),2)) -> 0 | AA30: 60255014 | AB30: =ROUND((AC30+AD30+AF30),6) -> 388.69 | AC30: =ROUND((ES30),6) -> 388.69 | AD30: =ROUND((((ET30)-(EU30))+AE30),6) -> 0 | AE30: =ROUND((EU30),6) -> 0 | AF30: =ROUND((EV30),6) -> 0 | AG30: =ROUND((AP30),6) -> 0 | AH30: =(EW30) -> 0 | AI30: =(EX30) -> 0 | AJ30: =(AS30) -> 0 | AK30: 388.69 | AL30: 388.69 | AM30: 0 | AN30: 0 | AO30: 0 | AP30: 0 | AQ30: 0 | AR30: 0 | AS30: 0 | AT30: 0 | AU30: 0 | AV30: 1 | AW30: 1 | AZ30: 1 | BA30: 1 | BB30: 1 | BC30: 1 | BH30: 3 | BI30: 3 | BM30: 746 | BN30: 58973374 | BP30: 0 | BQ30: 130 | BR30: 0 | BS30: 1 | BT30: 1 | BU30: 1 | BV30: 1 | BW30: 1 | BX30: 1 | BZ30: 0 | CA30: 0 | CE30: 1566 | CF30: 0 | CG30: 0 | CM30: 0 | CO30: 0 | CP30: =(P30+Q30+S30) -> 388.69 | CQ30: =ROUND((ROUND((AC30*1),2)*BC30),2) -> 388.69 | CR30: =(ROUND((ROUND(((ET30)*AV30*1),2)*BB30),2)+ROUND((ROUND(((AE30-(EU30))*AV30*1),2)*BS30),2)) -> 0 | CS30: =(ROUND((ROUND(((EU30)*AV30*1),2)*BS30),2)+ROUND((ROUND(((AE30-(EU30))*AV30*1),2)*BS30),2)) -> 0 | CT30: =ROUND((ROUND((AF30*AV30*1),2)*BA30),2) -> 0 | CU30: =AG30 -> 0 | CV30: =(AH30*AV30) -> 0 | CW30: =AI30 -> 0 | CX30: =AJ30 -> 0 | CY30: =(ROUND((((S30+ROUND((ROUND(((EU30)*AV30*1),2)*BS30),2))*AT30)/100),2)+ROUND(((ROUND((ROUND(((AE30-(EU30))*AV30*1),2)*BS30),2)*AT30)/100),2)) -> 0 | CZ30: =(ROUND((((S30+ROUND((ROUND(((EU30)*AV30*1),2)*BS30),2))*AU30)/100),2)+ROUND(((ROUND((ROUND(((AE30-(EU30))*AV30*1),2)*BS30),2)*AU30)/100),2)) -> 0 | DN30: 0 | DO30: 0 | DP30: 1 | DQ30: 1 | DU30: 1010 | DV30: шт. | DW30: шт. | DX30: 1 | EE30: 60088205 | EF30: 130 | EG30: Сметная стоимость оборудования | EH30: 0 | EJ30: 3 | EK30: 746 | EL30: ТСН-2001.13. Сметная стоимость оборудования | EM30: ТСН-2001.13 | EQ30: 0 | ER30: 388.69 | ES30: 388.69 | ET30: 0 | EU30: 0 | EV30: 0 | EW30: 0 | EX30: 0 | EY30: 0 | FQ30: 0 | FR30: =P30 -> 388.69 | FS30: 0 | FX30: 0 | FY30: 0 | GD30: 1 | GF30: -1177766710 | GG30: 2 | GH30: 1 | GI30: -2 | GJ30: 0 | GK30: 0 | GL30: =ROUND(IF(AND(BH30=3,BI30=3,FS30<>0),P30,0),2) -> 0 | GM30: =ROUND(O30+X30+Y30,2)+GX30 -> 388.69 | GN30: =IF(OR(BI30=0,BI30=1),GM30-GX30,0) -> 0 | GO30: =IF(BI30=2,GM30-GX30,0) -> 0 | GP30: =IF(BI30=4,GM30-GX30,0) -> 0 | GR30: 0 | GS30: 3 | GT30: 0 | GV30: =ROUND((GT30),6) -> 0 | GW30: 1 | GX30: =ROUND(HC30*I30,2) -> 0 | HA30: 0 | HB30: 0 | HC30: =GV30*GW30 -> 0 | HS30: 0 | IK30: 0
A31: 17 | B31: 1 | E31: 2 | F31: 13.1-11-142 | G31: Конвектор электрический, номинальная мощность 0,5 кВт, для отопления жилых и промышленных помещений | H31: шт. | I31: 1 | J31: 0 | K31: 1 | O31: =ROUND(CP31,2) -> 2553.69 | P31: =ROUND((ROUND((AC31*I31),2)*BC31),2) -> 2553.69 | Q31: =(ROUND((ROUND(((ET31)*AV31*I31),2)*BB31),2)+ROUND((ROUND(((AE31-(EU31))*AV31*I31),2)*BS31),2)) -> 0 | R31: =(ROUND((ROUND(((EU31)*AV31*I31),2)*BS31),2)+ROUND((ROUND(((AE31-(EU31))*AV31*I31),2)*BS31),2)) -> 0 | S31: =ROUND((ROUND((AF31*AV31*I31),2)*BA31),2) -> 0 | T31: =ROUND(CU31*I31,2) -> 0 | U31: =CV31*I31 -> 0 | V31: =CW31*I31 -> 0 | W31: =ROUND(CX31*I31,2) -> 0 | X31: =(ROUND((((S31+ROUND((ROUND(((EU31)*AV31*I31),2)*BS31),2))*AT31)/100),2)+ROUND(((ROUND((ROUND(((AE31-(EU31))*AV31*I31),2)*BS31),2)*AT31)/100),2)) -> 0 | Y31: =(ROUND((((S31+ROUND((ROUND(((EU31)*AV31*I31),2)*BS31),2))*AU31)/100),2)+ROUND(((ROUND((ROUND(((AE31-(EU31))*AV31*I31),2)*BS31),2)*AU31)/100),2)) -> 0 | AA31: 60255011 | AB31: =ROUND((AC31+AD31+AF31),6) -> 388.69 | AC31: =ROUND((ES31),6) -> 388.69 | AD31: =ROUND((((ET31)-(EU31))+AE31),6) -> 0 | AE31: =ROUND((EU31),6) -> 0 | AF31: =ROUND((EV31),6) -> 0 | AG31: =ROUND((AP31),6) -> 0 | AH31: =(EW31) -> 0 | AI31: =(EX31) -> 0 | AJ31: =(AS31) -> 0 | AK31: 388.69 | AL31: 388.69 | AM31: 0 | AN31: 0 | AO31: 0 | AP31: 0 | AQ31: 0 | AR31: 0 | AS31: 0 | AT31: 0 | AU31: 0 | AV31: 1 | AW31: 1 | AZ31: 1 | BA31: 1 | BB31: 1 | BC31: 6.57 | BH31: 3 | BI31: 3 | BM31: 746 | BN31: 58973374 | BP31: 0 | BQ31: 130 | BR31: 0 | BS31: 1 | BT31: 1 | BU31: 1 | BV31: 1 | BW31: 1 | BX31: 1 | BZ31: 0 | CA31: 0 | CE31: 1566 | CF31: 0 | CG31: 0 | CM31: 0 | CO31: 0 | CP31: =(P31+Q31+S31) -> 2553.69 | CQ31: =ROUND((ROUND((AC31*1),2)*BC31),2) -> 2553.69 | CR31: =(ROUND((ROUND(((ET31)*AV31*1),2)*BB31),2)+ROUND((ROUND(((AE31-(EU31))*AV31*1),2)*BS31),2)) -> 0 | CS31: =(ROUND((ROUND(((EU31)*AV31*1),2)*BS31),2)+ROUND((ROUND(((AE31-(EU31))*AV31*1),2)*BS31),2)) -> 0 | CT31: =ROUND((ROUND((AF31*AV31*1),2)*BA31),2) -> 0 | CU31: =AG31 -> 0 | CV31: =(AH31*AV31) -> 0 | CW31: =AI31 -> 0 | CX31: =AJ31 -> 0 | CY31: =(ROUND((((S31+ROUND((ROUND(((EU31)*AV31*1),2)*BS31),2))*AT31)/100),2)+ROUND(((ROUND((ROUND(((AE31-(EU31))*AV31*1),2)*BS31),2)*AT31)/100),2)) -> 0 | CZ31: =(ROUND((((S31+ROUND((ROUND(((EU31)*AV31*1),2)*BS31),2))*AU31)/100),2)+ROUND(((ROUND((ROUND(((AE31-(EU31))*AV31*1),2)*BS31),2)*AU31)/100),2)) -> 0 | DN31: 0 | DO31: 0 | DP31: 1 | DQ31: 1 | DU31: 1010 | DV31: шт. | DW31: шт. | DX31: 1 | EE31: 60088205 | EF31: 130 | EG31: Сметная стоимость оборудования | EH31: 0 | EJ31: 3 | EK31: 746 | EL31: ТСН-2001.13. Сметная стоимость оборудования | EM31: ТСН-2001.13 | EQ31: 0 | ER31: 388.69 | ES31: 388.69 | ET31: 0 | EU31: 0 | EV31: 0 | EW31: 0 | EX31: 0 | EY31: 0 | FQ31: 0 | FR31: =P31 -> 2553.69 | FS31: 0 | FX31: 0 | FY31: 0 | GD31: 1 | GF31: -1177766710 | GG31: 2 | GH31: 1 | GI31: 2 | GJ31: 0 | GK31: 0 | GL31: =ROUND(IF(AND(BH31=3,BI31=3,FS31<>0),P31,0),2) -> 0 | GM31: =ROUND(O31+X31+Y31,2)+GX31 -> 2553.69 | GN31: =IF(OR(BI31=0,BI31=1),GM31-GX31,0) -> 0 | GO31: =IF(BI31=2,GM31-GX31,0) -> 0 | GP31: =IF(BI31=4,GM31-GX31,0) -> 0 | GR31: 0 | GS31: 3 | GT31: 0 | GV31: =ROUND((GT31),6) -> 0 | GW31: 1 | GX31: =ROUND(HC31*I31,2) -> 0 | HA31: 0 | HB31: 0 | HC31: =GV31*GW31 -> 0 | HS31: 0 | IK31: 0
A32: 17 | B32: 1 | E32: 3 | F32: 13.1-11-143 | G32: Конвектор электрический, номинальная мощность 1 кВт, для отопления жилых и промышленных помещений | H32: шт. | I32: 2 | J32: 0 | K32: 2 | O32: =ROUND(CP32,2) -> 929.48 | P32: =ROUND((ROUND((AC32*I32),2)*BC32),2) -> 929.48 | Q32: =(ROUND((ROUND(((ET32)*AV32*I32),2)*BB32),2)+ROUND((ROUND(((AE32-(EU32))*AV32*I32),2)*BS32),2)) -> 0 | R32: =(ROUND((ROUND(((EU32)*AV32*I32),2)*BS32),2)+ROUND((ROUND(((AE32-(EU32))*AV32*I32),2)*BS32),2)) -> 0 | S32: =ROUND((ROUND((AF32*AV32*I32),2)*BA32),2) -> 0 | T32: =ROUND(CU32*I32,2) -> 0 | U32: =CV32*I32 -> 0 | V32: =CW32*I32 -> 0 | W32: =ROUND(CX32*I32,2) -> 0 | X32: =(ROUND((((S32+ROUND((ROUND(((EU32)*AV32*I32),2)*BS32),2))*AT32)/100),2)+ROUND(((ROUND((ROUND(((AE32-(EU32))*AV32*I32),2)*BS32),2)*AT32)/100),2)) -> 0 | Y32: =(ROUND((((S32+ROUND((ROUND(((EU32)*AV32*I32),2)*BS32),2))*AU32)/100),2)+ROUND(((ROUND((ROUND(((AE32-(EU32))*AV32*I32),2)*BS32),2)*AU32)/100),2)) -> 0 | AA32: 60255014 | AB32: =ROUND((AC32+AD32+AF32),6) -> 464.74 | AC32: =ROUND((ES32),6) -> 464.74 | AD32: =ROUND((((ET32)-(EU32))+AE32),6) -> 0 | AE32: =ROUND((EU32),6) -> 0 | AF32: =ROUND((EV32),6) -> 0 | AG32: =ROUND((AP32),6) -> 0 | AH32: =(EW32) -> 0 | AI32: =(EX32) -> 0 | AJ32: =(AS32) -> 0 | AK32: 464.74 | AL32: 464.74 | AM32: 0 | AN32: 0 | AO32: 0 | AP32: 0 | AQ32: 0 | AR32: 0 | AS32: 0 | AT32: 0 | AU32: 0 | AV32: 1 | AW32: 1 | AZ32: 1 | BA32: 1 | BB32: 1 | BC32: 1 | BH32: 3 | BI32: 3 | BM32: 746 | BN32: 58973374 | BP32: 0 | BQ32: 130 | BR32: 0 | BS32: 1 | BT32: 1 | BU32: 1 | BV32: 1 | BW32: 1 | BX32: 1 | BZ32: 0 | CA32: 0 | CE32: 1566 | CF32: 0 | CG32: 0 | CM32: 0 | CO32: 0 | CP32: =(P32+Q32+S32) -> 929.48 | CQ32: =ROUND((ROUND((AC32*1),2)*BC32),2) -> 464.74 | CR32: =(ROUND((ROUND(((ET32)*AV32*1),2)*BB32),2)+ROUND((ROUND(((AE32-(EU32))*AV32*1),2)*BS32),2)) -> 0 | CS32: =(ROUND((ROUND(((EU32)*AV32*1),2)*BS32),2)+ROUND((ROUND(((AE32-(EU32))*AV32*1),2)*BS32),2)) -> 0 | CT32: =ROUND((ROUND((AF32*AV32*1),2)*BA32),2) -> 0 | CU32: =AG32 -> 0 | CV32: =(AH32*AV32) -> 0 | CW32: =AI32 -> 0 | CX32: =AJ32 -> 0 | CY32: =(ROUND((((S32+ROUND((ROUND(((EU32)*AV32*1),2)*BS32),2))*AT32)/100),2)+ROUND(((ROUND((ROUND(((AE32-(EU32))*AV32*1),2)*BS32),2)*AT32)/100),2)) -> 0 | CZ32: =(ROUND((((S32+ROUND((ROUND(((EU32)*AV32*1),2)*BS32),2))*AU32)/100),2)+ROUND(((ROUND((ROUND(((AE32-(EU32))*AV32*1),2)*BS32),2)*AU32)/100),2)) -> 0 | DN32: 0 | DO32: 0 | DP32: 1 | DQ32: 1 | DU32: 1010 | DV32: шт. | DW32: шт. | DX32: 1 | EE32: 60088205 | EF32: 130 | EG32: Сметная стоимость оборудования | EH32: 0 | EJ32: 3 | EK32: 746 | EL32: ТСН-2001.13. Сметная стоимость оборудования | EM32: ТСН-2001.13 | EQ32: 0 | ER32: 464.74 | ES32: 464.74 | ET32: 0 | EU32: 0 | EV32: 0 | EW32: 0 | EX32: 0 | EY32: 0 | FQ32: 0 | FR32: =P32 -> 929.48 | FS32: 0 | FX32: 0 | FY32: 0 | GD32: 1 | GF32: 1803617062 | GG32: 2 | GH32: 1 | GI32: -2 | GJ32: 0 | GK32: 0 | GL32: =ROUND(IF(AND(BH32=3,BI32=3,FS32<>0),P32,0),2) -> 0 | GM32: =ROUND(O32+X32+Y32,2)+GX32 -> 929.48 | GN32: =IF(OR(BI32=0,BI32=1),GM32-GX32,0) -> 0 | GO32: =IF(BI32=2,GM32-GX32,0) -> 0 | GP32: =IF(BI32=4,GM32-GX32,0) -> 0 | GR32: 0 | GS32: 3 | GT32: 0 | GV32: =ROUND((GT32),6) -> 0 | GW32: 1 | GX32: =ROUND(HC32*I32,2) -> 0 | HA32: 0 | HB32: 0 | HC32: =GV32*GW32 -> 0 | HS32: 0 | IK32: 0
A33: 17 | B33: 1 | E33: 3 | F33: 13.1-11-143 | G33: Конвектор электрический, номинальная мощность 1 кВт, для отопления жилых и промышленных помещений | H33: шт. | I33: 2 | J33: 0 | K33: 2 | O33: =ROUND(CP33,2) -> 5697.71 | P33: =ROUND((ROUND((AC33*I33),2)*BC33),2) -> 5697.71 | Q33: =(ROUND((ROUND(((ET33)*AV33*I33),2)*BB33),2)+ROUND((ROUND(((AE33-(EU33))*AV33*I33),2)*BS33),2)) -> 0 | R33: =(ROUND((ROUND(((EU33)*AV33*I33),2)*BS33),2)+ROUND((ROUND(((AE33-(EU33))*AV33*I33),2)*BS33),2)) -> 0 | S33: =ROUND((ROUND((AF33*AV33*I33),2)*BA33),2) -> 0 | T33: =ROUND(CU33*I33,2) -> 0 | U33: =CV33*I33 -> 0 | V33: =CW33*I33 -> 0 | W33: =ROUND(CX33*I33,2) -> 0 | X33: =(ROUND((((S33+ROUND((ROUND(((EU33)*AV33*I33),2)*BS33),2))*AT33)/100),2)+ROUND(((ROUND((ROUND(((AE33-(EU33))*AV33*I33),2)*BS33),2)*AT33)/100),2)) -> 0 | Y33: =(ROUND((((S33+ROUND((ROUND(((EU33)*AV33*I33),2)*BS33),2))*AU33)/100),2)+ROUND(((ROUND((ROUND(((AE33-(EU33))*AV33*I33),2)*BS33),2)*AU33)/100),2)) -> 0 | AA33: 60255011 | AB33: =ROUND((AC33+AD33+AF33),6) -> 464.74 | AC33: =ROUND((ES33),6) -> 464.74 | AD33: =ROUND((((ET33)-(EU33))+AE33),6) -> 0 | AE33: =ROUND((EU33),6) -> 0 | AF33: =ROUND((EV33),6) -> 0 | AG33: =ROUND((AP33),6) -> 0 | AH33: =(EW33) -> 0 | AI33: =(EX33) -> 0 | AJ33: =(AS33) -> 0 | AK33: 464.74 | AL33: 464.74 | AM33: 0 | AN33: 0 | AO33: 0 | AP33: 0 | AQ33: 0 | AR33: 0 | AS33: 0 | AT33: 0 | AU33: 0 | AV33: 1 | AW33: 1 | AZ33: 1 | BA33: 1 | BB33: 1 | BC33: 6.13 | BH33: 3 | BI33: 3 | BM33: 746 | BN33: 58973374 | BP33: 0 | BQ33: 130 | BR33: 0 | BS33: 1 | BT33: 1 | BU33: 1 | BV33: 1 | BW33: 1 | BX33: 1 | BZ33: 0 | CA33: 0 | CE33: 1566 | CF33: 0 | CG33: 0 | CM33: 0 | CO33: 0 | CP33: =(P33+Q33+S33) -> 5697.71 | CQ33: =ROUND((ROUND((AC33*1),2)*BC33),2) -> 2848.86 | CR33: =(ROUND((ROUND(((ET33)*AV33*1),2)*BB33),2)+ROUND((ROUND(((AE33-(EU33))*AV33*1),2)*BS33),2)) -> 0 | CS33: =(ROUND((ROUND(((EU33)*AV33*1),2)*BS33),2)+ROUND((ROUND(((AE33-(EU33))*AV33*1),2)*BS33),2)) -> 0 | CT33: =ROUND((ROUND((AF33*AV33*1),2)*BA33),2) -> 0 | CU33: =AG33 -> 0 | CV33: =(AH33*AV33) -> 0 | CW33: =AI33 -> 0 | CX33: =AJ33 -> 0 | CY33: =(ROUND((((S33+ROUND((ROUND(((EU33)*AV33*1),2)*BS33),2))*AT33)/100),2)+ROUND(((ROUND((ROUND(((AE33-(EU33))*AV33*1),2)*BS33),2)*AT33)/100),2)) -> 0 | CZ33: =(ROUND((((S33+ROUND((ROUND(((EU33)*AV33*1),2)*BS33),2))*AU33)/100),2)+ROUND(((ROUND((ROUND(((AE33-(EU33))*AV33*1),2)*BS33),2)*AU33)/100),2)) -> 0 | DN33: 0 | DO33: 0 | DP33: 1 | DQ33: 1 | DU33: 1010 | DV33: шт. | DW33: шт. | DX33: 1 | EE33: 60088205 | EF33: 130 | EG33: Сметная стоимость оборудования | EH33: 0 | EJ33: 3 | EK33: 746 | EL33: ТСН-2001.13. Сметная стоимость оборудования | EM33: ТСН-2001.13 | EQ33: 0 | ER33: 464.74 | ES33: 464.74 | ET33: 0 | EU33: 0 | EV33: 0 | EW33: 0 | EX33: 0 | EY33: 0 | FQ33: 0 | FR33: =P33 -> 5697.71 | FS33: 0 | FX33: 0 | FY33: 0 | GD33: 1 | GF33: 1803617062 | GG33: 2 | GH33: 1 | GI33: 2 | GJ33: 0 | GK33: 0 | GL33: =ROUND(IF(AND(BH33=3,BI33=3,FS33<>0),P33,0),2) -> 0 | GM33: =ROUND(O33+X33+Y33,2)+GX33 -> 5697.71 | GN33: =IF(OR(BI33=0,BI33=1),GM33-GX33,0) -> 0 | GO33: =IF(BI33=2,GM33-GX33,0) -> 0 | GP33: =IF(BI33=4,GM33-GX33,0) -> 0 | GR33: 0 | GS33: 3 | GT33: 0 | GV33: =ROUND((GT33),6) -> 0 | GW33: 1 | GX33: =ROUND(HC33*I33,2) -> 0 | HA33: 0 | HB33: 0 | HC33: =GV33*GW33 -> 0 | HS33: 0 | IK33: 0
A35: 51 | B35: =B24 -> 1 | C35: =A24 -> 4 | D35: =ROW(A24) -> 24 | F35: =IF(F24<>"",F24,"") | G35: =IF(G24<>"",G24,"") -> Конвекторы | H35: 0 | O35: =ROUND(AB35,2) -> 1368.77 | P35: =ROUND(AC35,2) -> 1319.4 | Q35: =ROUND(AD35,2) -> 3.14 | R35: =ROUND(AE35,2) -> 0.45 | S35: =ROUND(AF35,2) -> 46.23 | T35: =ROUND(AG35,2) -> 0 | U35: =AH35 -> 3.558753 | V35: =AI35 -> 0 | W35: =ROUND(AJ35,2) -> 0 | X35: =ROUND(AK35,2) -> 45.28 | Y35: =ROUND(AL35,2) -> 23.81 | AB35: =ROUND(SUMIF(AA28:AA33,"=60255014",O28:O33),2) -> 1368.77 | AC35: =ROUND(SUMIF(AA28:AA33,"=60255014",P28:P33),2) -> 1319.4 | AD35: =ROUND(SUMIF(AA28:AA33,"=60255014",Q28:Q33),2) -> 3.14 | AE35: =ROUND(SUMIF(AA28:AA33,"=60255014",R28:R33),2) -> 0.45 | AF35: =ROUND(SUMIF(AA28:AA33,"=60255014",S28:S33),2) -> 46.23 | AG35: =ROUND(SUMIF(AA28:AA33,"=60255014",T28:T33),2) -> 0 | AH35: =SUMIF(AA28:AA33,"=60255014",U28:U33) -> 3.558753 | AI35: =SUMIF(AA28:AA33,"=60255014",V28:V33) -> 0 | AJ35: =ROUND(SUMIF(AA28:AA33,"=60255014",W28:W33),2) -> 0 | AK35: =ROUND(SUMIF(AA28:AA33,"=60255014",X28:X33),2) -> 45.28 | AL35: =ROUND(SUMIF(AA28:AA33,"=60255014",Y28:Y33),2) -> 23.81 | AO35: =ROUND(BX35,2) -> 0 | AP35: =ROUND(BY35,2) -> 1318.17 | AQ35: =ROUND(BZ35,2) -> 0 | AR35: =ROUND(CA35,2) -> 1437.86 | AS35: =ROUND(CB35,2) -> 0 | AT35: =ROUND(CC35,2) -> 119.69 | AU35: =ROUND(CD35,2) -> 0 | AV35: =ROUND(CE35,2) -> 1319.4 | ... BD35: =ROUND(CM35,2) -> 0 | BX35: =ROUND(SUMIF(AA28:AA33,"=60255014",FQ28:FQ33),2) -> 0 | BY35: =ROUND(SUMIF(AA28:AA33,"=60255014",FR28:FR33),2) -> 1318.17 | BZ35: =ROUND(SUMIF(AA28:AA33,"=60255014",GL28:GL33),2) -> 0 | CA35: =ROUND(SUMIF(AA28:AA33,"=60255014",GM28:GM33),2) -> 1437.86 | CB35: =ROUND(SUMIF(AA28:AA33,"=60255014",GN28:GN33),2) -> 0 | CC35: =ROUND(SUMIF(AA28:AA33,"=60255014",GO28:GO33),2) -> 119.69 | CD35: =ROUND(SUMIF(AA28:AA33,"=60255014",GP28:GP33),2) -> 0 | CE35: =AC35-BX35 -> 1319.4 | CF35: =AC35-BY35 -> 1.23 | CG35: =BX35-BZ35 -> 0 | CH35: =AC35-BX35-BY35+BZ35 -> 1.23 | CI35: =BY35-BZ35 -> 1318.17 | CJ35: =ROUND(SUMIF(AA28:AA33,"=60255014",GX28:GX33),2) -> 0 | CK35: =ROUND(SUMIF(AA28:AA33,"=60255014",GY28:GY33),2) -> 0 | CL35: =ROUND(SUMIF(AA28:AA33,"=60255014",GZ28:GZ33),2) -> 0 | CM35: =ROUND(SUMIF(AA28:AA33,"=60255014",HD28:HD33),2) -> 0 | DG35: =ROUND(DT35,2) -> 10847.4 | DH35: =ROUND(DU35,2) -> 8256.26 | DI35: =ROUND(DV35,2) -> 48.95 | DJ35: =ROUND(DW35,2) -> 24.75 | DK35: =ROUND(DX35,2) -> 2542.19 | DL35: =ROUND(DY35,2) -> 0 | DM35: =DZ35 -> 3.558753 | DN35: =EA35 -> 0 | DO35: =ROUND(EB35,2) -> 0 | DP35: =ROUND(EC35,2) -> 2489.93 | DQ35: =ROUND(ED35,2) -> 1309.14 | DT35: =ROUND(SUMIF(AA28:AA33,"=60255011",O28:O33),2) -> 10847.4 | DU35: =ROUND(SUMIF(AA28:AA33,"=60255011",P28:P33),2) -> 8256.26 | DV35: =ROUND(SUMIF(AA28:AA33,"=60255011",Q28:Q33),2) -> 48.95 | DW35: =ROUND(SUMIF(AA28:AA33,"=60255011",R28:R33),2) -> 24.75 | DX35: =ROUND(SUMIF(AA28:AA33,"=60255011",S28:S33),2) -> 2542.19 | DY35: =ROUND(SUMIF(AA28:AA33,"=60255011",T28:T33),2) -> 0 | DZ35: =SUMIF(AA28:AA33,"=60255011",U28:U33) -> 3.558753 | EA35: =SUMIF(AA28:AA33,"=60255011",V28:V33) -> 0 | EB35: =ROUND(SUMIF(AA28:AA33,"=60255011",W28:W33),2) -> 0 | EC35: =ROUND(SUMIF(AA28:AA33,"=60255011",X28:X33),2) -> 2489.93 | ED35: =ROUND(SUMIF(AA28:AA33,"=60255011",Y28:Y33),2) -> 1309.14 | EG35: =ROUND(FP35,2) -> 0 | EH35: =ROUND(FQ35,2) -> 8251.4 | EI35: =ROUND(FR35,2) -> 0 | EJ35: =ROUND(FS35,2) -> 14646.47 | EK35: =ROUND(FT35,2) -> 0 | EL35: =ROUND(FU35,2) -> 6395.07 | EM35: =ROUND(FV35,2) -> 0 | EN35: =ROUND(FW35,2) -> 8256.26 | ... EV35: =ROUND(GE35,2) -> 0 | FP35: =ROUND(SUMIF(AA28:AA33,"=60255011",FQ28:FQ33),2) -> 0 | FQ35: =ROUND(SUMIF(AA28:AA33,"=60255011",FR28:FR33),2) -> 8251.4 | FR35: =ROUND(SUMIF(AA28:AA33,"=60255011",GL28:GL33),2) -> 0 | FS35: =ROUND(SUMIF(AA28:AA33,"=60255011",GM28:GM33),2) -> 14646.47 | FT35: =ROUND(SUMIF(AA28:AA33,"=60255011",GN28:GN33),2) -> 0 | FU35: =ROUND(SUMIF(AA28:AA33,"=60255011",GO28:GO33),2) -> 6395.07 | FV35: =ROUND(SUMIF(AA28:AA33,"=60255011",GP28:GP33),2) -> 0 | FW35: =DU35-FP35 -> 8256.26 | FX35: =DU35-FQ35 -> 4.86 | FY35: =FP35-FR35 -> 0 | FZ35: =DU35-FP35-FQ35+FR35 -> 4.86 | GA35: =FQ35-FR35 -> 8251.4 | GB35: =ROUND(SUMIF(AA28:AA33,"=60255011",GX28:GX33),2) -> 0 | GC35: =ROUND(SUMIF(AA28:AA33,"=60255011",GY28:GY33),2) -> 0 | GD35: =ROUND(SUMIF(AA28:AA33,"=60255011",GZ28:GZ33),2) -> 0 | GE35: =ROUND(SUMIF(AA28:AA33,"=60255011",HD28:HD33),2) -> 0 | GX35: 0
A37: 50 | B37: 0 | C37: 0 | D37: 1 | E37: 201 | F37: =ROUND(Source!O35,O37) -> 1368.77 | G37: ПЗ | H37: Прямые затраты | K37: 201 | L37: 1 | M37: 3 | O37: 2 | P37: =ROUND(Source!DG35,O37) -> 10847.4 | W37: 1368.77 | X37: 1 | Y37: 1368.77 | Z37: 10847.4 | AA37: 1 | AB37: 10847.4
A38: 50 | B38: 0 | C38: 0 | D38: 1 | E38: 202 | F38: =ROUND(Source!P35,O38) -> 1319.4 | G38: СтМатОб | H38: Стоимость материальных ресурсов (всего) | K38: 202 | L38: 2 | M38: 3 | O38: 2 | P38: =ROUND(Source!DH35,O38) -> 8256.26 | W38: 1319.4 | X38: 1 | Y38: 1319.4 | Z38: 8256.26 | AA38: 1 | AB38: 8256.26
A39: 50 | B39: 0 | C39: 0 | D39: 1 | E39: 222 | F39: =ROUND(Source!AO35,O39) -> 0 | G39: СтМатОбЗак | H39: Стоимость материалов и оборудования заказчика | K39: 222 | L39: 3 | M39: 3 | O39: 2 | P39: =ROUND(Source!EG35,O39) -> 0 | W39: 0 | X39: 1 | Y39: 0 | Z39: 0 | AA39: 1 | AB39: 0
A40: 50 | B40: 0 | C40: 0 | D40: 1 | E40: 225 | F40: =ROUND(Source!AV35,O40) -> 1319.4 | G40: СтМатОбПод | H40: Стоимость материалов и оборудования подрядчика | K40: 225 | L40: 4 | M40: 3 | O40: 2 | P40: =ROUND(Source!EN35,O40) -> 8256.26 | W40: 1319.4 | X40: 1 | Y40: 1319.4 | Z40: 8256.26 | AA40: 1 | AB40: 8256.26
A41: 50 | B41: 0 | C41: 0 | D41: 1 | E41: 226 | F41: =ROUND(Source!AW35,O41) -> 1.23 | G41: СтМат | H41: Стоимость материалов (всего) | K41: 226 | L41: 5 | M41: 3 | O41: 2 | P41: =ROUND(Source!EO35,O41) -> 4.86 | W41: 1.23 | X41: 1 | Y41: 1.23 | Z41: 4.86 | AA41: 1 | AB41: 4.86
A42: 50 | B42: 0 | C42: 0 | D42: 1 | E42: 227 | F42: =ROUND(Source!AX35,O42) -> 0 | G42: СтМатЗак | H42: Стоимость материалов заказчика | K42: 227 | L42: 6 | M42: 3 | O42: 2 | P42: =ROUND(Source!EP35,O42) -> 0 | W42: 0 | X42: 1 | Y42: 0 | Z42: 0 | AA42: 1 | AB42: 0
A43: 50 | B43: 0 | C43: 0 | D43: 1 | E43: 228 | F43: =ROUND(Source!AY35,O43) -> 1.23 | G43: СтМатПод | H43: Стоимость материалов подрядчика | K43: 228 | L43: 7 | M43: 3 | O43: 2 | P43: =ROUND(Source!EQ35,O43) -> 4.86 | W43: 1.23 | X43: 1 | Y43: 1.23 | Z43: 4.86 | AA43: 1 | AB43: 4.86
A44: 50 | B44: 0 | C44: 0 | D44: 1 | E44: 216 | F44: =ROUND(Source!AP35,O44) -> 1318.17 | G44: Оборуд | H44: Стоимость оборудования (всего) | K44: 216 | L44: 8 | M44: 3 | O44: 2 | P44: =ROUND(Source!EH35,O44) -> 8251.4 | W44: 1318.17 | X44: 1 | Y44: 1318.17 | Z44: 8251.4 | AA44: 1 | AB44: 8251.4
A45: 50 | B45: 0 | C45: 0 | D45: 1 | E45: 223 | F45: =ROUND(Source!AQ35,O45) -> 0 | G45: ОборудЗак | H45: Стоимость оборудования заказчика | K45: 223 | L45: 9 | M45: 3 | O45: 2 | P45: =ROUND(Source!EI35,O45) -> 0 | W45: 0 | X45: 1 | Y45: 0 | Z45: 0 | AA45: 1 | AB45: 0
A46: 50 | B46: 0 | C46: 0 | D46: 1 | E46: 229 | F46: =ROUND(Source!AZ35,O46) -> 1318.17 | G46: ОборудПод | H46: Стоимость оборудования подрядчика | K46: 229 | L46: 10 | M46: 3 | O46: 2 | P46: =ROUND(Source!ER35,O46) -> 8251.4 | W46: 1318.17 | X46: 1 | Y46: 1318.17 | Z46: 8251.4 | AA46: 1 | AB46: 8251.4
A47: 50 | B47: 0 | C47: 0 | D47: 1 | E47: 203 | F47: =ROUND(Source!Q35,O47) -> 3.14 | G47: ЭММ | H47: Эксплуатация машин | K47: 203 | L47: 11 | M47: 3 | O47: 2 | P47: =ROUND(Source!DI35,O47) -> 48.95 | W47: 3.14 | X47: 1 | Y47: 3.14 | Z47: 48.95 | AA47: 1 | AB47: 48.95
A48: 50 | B48: 0 | C48: 0 | D48: 1 | E48: 231 | F48: =ROUND(Source!BB35,O48) -> 0 | G48: ЭММсНРиСП | H48: Эксплуатация машин по ТСН-2001.16 | K48: 231 | L48: 12 | M48: 3 | O48: 2 | P48: =ROUND(Source!ET35,O48) -> 0 | W48: 0 | X48: 1 | Y48: 0 | Z48: 0 | AA48: 1 | AB48: 0
A49: 50 | B49: 0 | C49: 0 | D49: 1 | E49: 204 | F49: =ROUND(Source!R35,O49) -> 0.45 | G49: ЗПМ | H49: ЗП машинистов | K49: 204 | L49: 13 | M49: 3 | O49: 2 | P49: =ROUND(Source!DJ35,O49) -> 24.75 | W49: 0.45 | X49: 1 | Y49: 0.45 | Z49: 24.75 | AA49: 1 | AB49: 24.75
A50: 50 | B50: 0 | C50: 0 | D50: 1 | E50: 205 | F50: =ROUND(Source!S35,O50) -> 46.23 | G50: ОЗП | H50: Основная ЗП рабочих | K50: 205 | L50: 14 | M50: 3 | O50: 2 | P50: =ROUND(Source!DK35,O50) -> 2542.19 | W50: 46.23 | X50: 1 | Y50: 46.23 | Z50: 2542.19 | AA50: 1 | AB50: 2542.19
A51: 50 | B51: 0 | C51: 0 | D51: 1 | E51: 232 | F51: =ROUND(Source!BC35,O51) -> 0 | G51: ОЗПсНРиСП | H51: Основная ЗП рабочих по ТСН-2001.16 | K51: 232 | L51: 15 | M51: 3 | O51: 2 | P51: =ROUND(Source!EU35,O51) -> 0 | W51: 0 | X51: 1 | Y51: 0 | Z51: 0 | AA51: 1 | AB51: 0
A52: 50 | B52: 0 | C52: 0 | D52: 1 | E52: 214 | F52: =ROUND(Source!AS35,O52) -> 0 | G52: Строит | H52: Строительные работы с НР и СП | K52: 214 | L52: 16 | M52: 3 | O52: 2 | P52: =ROUND(Source!EK35,O52) -> 0 | W52: 0 | X52: 1 | Y52: 0 | Z52: 0 | AA52: 1 | AB52: 0
A53: 50 | B53: 0 | C53: 0 | D53: 1 | E53: 215 | F53: =ROUND(Source!AT35,O53) -> 119.69 | G53: Монтаж | H53: Монтажные работы с НР и СП | K53: 215 | L53: 17 | M53: 3 | O53: 2 | P53: =ROUND(Source!EL35,O53) -> 6395.07 | W53: 119.69 | X53: 1 | Y53: 119.69 | Z53: 6395.07 | AA53: 1 | AB53: 6395.07
A54: 50 | B54: 0 | C54: 0 | D54: 1 | E54: 217 | F54: =ROUND(Source!AU35,O54) -> 0 | G54: Прочие | H54: Прочие работы с НР и СП | K54: 217 | L54: 18 | M54: 3 | O54: 2 | P54: =ROUND(Source!EM35,O54) -> 0 | W54: 0 | X54: 1 | Y54: 0 | Z54: 0 | AA54: 1 | AB54: 0
A55: 50 | B55: 0 | C55: 0 | D55: 1 | E55: 230 | F55: =ROUND(Source!BA35,O55) -> 0 | G55: ПрочиеЗатр | H55: Прочие затраты по ТСН-2001.16 | K55: 230 | L55: 19 | M55: 3 | O55: 2 | P55: =ROUND(Source!ES35,O55) -> 0 | W55: 0 | X55: 1 | Y55: 0 | Z55: 0 | AA55: 1 | AB55: 0
A56: 50 | B56: 0 | C56: 0 | D56: 1 | E56: 206 | F56: =ROUND(Source!T35,O56) -> 0 | G56: ВозврМат | H56: Возврат материалов | K56: 206 | L56: 20 | M56: 3 | O56: 2 | P56: =ROUND(Source!DL35,O56) -> 0 | W56: 0 | X56: 1 | Y56: 0 | Z56: 0 | AA56: 1 | AB56: 0
A57: 50 | B57: 0 | C57: 0 | D57: 1 | E57: 207 | F57: =Source!U35 -> 3.558753 | G57: ТрудСтр | H57: Трудозатраты строителей | K57: 207 | L57: 21 | M57: 3 | O57: -1 | P57: =Source!DM35 -> 3.558753 | W57: 3.558753 | X57: 1 | Y57: 3.558753 | Z57: 3.558753 | AA57: 1 | AB57: 3.558753
A58: 50 | B58: 0 | C58: 0 | D58: 1 | E58: 208 | F58: =Source!V35 -> 0 | G58: ТрудМаш | H58: Трудозатраты машинистов | K58: 208 | L58: 22 | M58: 3 | O58: -1 | P58: =Source!DN35 -> 0 | W58: 0 | X58: 1 | Y58: 0 | Z58: 0 | AA58: 1 | AB58: 0
A59: 50 | B59: 0 | C59: 0 | D59: 1 | E59: 209 | F59: =ROUND(Source!W35,O59) -> 0 | G59: ТранспМат | H59: Транспорт материалов | K59: 209 | L59: 23 | M59: 3 | O59: 2 | P59: =ROUND(Source!DO35,O59) -> 0 | W59: 0 | X59: 1 | Y59: 0 | Z59: 0 | AA59: 1 | AB59: 0
A60: 50 | B60: 0 | C60: 0 | D60: 1 | E60: 233 | F60: =ROUND(Source!BD35,O60) -> 0 | G60: Перевозка | H60: Перевозка грузов | K60: 233 | L60: 24 | M60: 3 | O60: 2 | P60: =ROUND(Source!EV35,O60) -> 0 | W60: 0 | X60: 1 | Y60: 0 | Z60: 0 | AA60: 1 | AB60: 0
A61: 50 | B61: 0 | C61: 0 | D61: 1 | E61: 210 | F61: =ROUND(Source!X35,O61) -> 45.28 | G61: НР | H61: Накладные расходы | K61: 210 | L61: 25 | M61: 3 | O61: 2 | P61: =ROUND(Source!DP35,O61) -> 2489.93 | W61: 45.28 | X61: 1 | Y61: 45.28 | Z61: 2489.93 | AA61: 1 | AB61: 2489.93
A62: 50 | B62: 0 | C62: 0 | D62: 1 | E62: 211 | F62: =ROUND(Source!Y35,O62) -> 23.81 | G62: СмПриб | H62: Сметная прибыль | K62: 211 | L62: 26 | M62: 3 | O62: 2 | P62: =ROUND(Source!DQ35,O62) -> 1309.14 | W62: 23.81 | X62: 1 | Y62: 23.81 | Z62: 1309.14 | AA62: 1 | AB62: 1309.14
A63: 50 | B63: 0 | C63: 0 | D63: 1 | E63: 224 | F63: =ROUND(Source!AR35,O63) -> 1437.86 | G63: Всего | H63: Всего с НР и СП | K63: 224 | L63: 27 | M63: 3 | O63: 2 | P63: =ROUND(Source!EJ35,O63) -> 14646.47 | W63: 1437.86 | X63: 1 | Y63: 1437.86 | Z63: 14646.47 | AA63: 1 | AB63: 14646.47
A65: 4 | B65: 1 | D65: =ROW(A176) -> 176 | G65: Радиаторы отопления | I65: 0 | K65: -1 | S65: 0 | T65: 0 | V65: 0 | BX65: 0 | CJ65: 0
A67: 52 | B67: =B176 -> 1 | C67: =C176 -> 4 | D67: =D176 -> 65 | E67: =E176 -> 0 | F67: =F176 | G67: =G176 -> Радиаторы отопления | O67: =O176 -> 606112.63 | P67: =P176 -> 594287.54 | Q67: =Q176 -> 607.51 | R67: =R176 -> 63.31 | S67: =S176 -> 11217.58 | T67: =T176 -> 0 | U67: =U176 -> 918.31099 | V67: =V176 -> 0 | ... GX67: =GX176 -> 0
A69: 17 | B69: 1 | C69: =ROW(SmtRes!A18) -> 18 | D69: =ROW(EtalonRes!A21) -> 21 | E69: 4 | F69: 3.18-25-1 | G69: Установка радиаторов стальных панельных однорядных с креплением к стене длиной до 1600 мм | H69: 100 шт. | I69: =ROUND((1+3+2+20+1+9)/100,9) -> 0.36 | J69: 0 | K69: =ROUND((1+3+2+20+1+9)/100,9) -> 0.36 | O69: =ROUND(CP69,2) -> 1244.15 | P69: =ROUND((ROUND((AC69*AW69*I69),2)*BC69),2) -> 748.4 | Q69: =(ROUND((ROUND(((((ET69*1.25)*1.1))*AV69*I69),2)*BB69),2)+ROUND((ROUND(((AE69-(((EU69*1.25)*1.1)))*AV69*I69),2)*BS69),2)) -> 50.36 | R69: =(ROUND((ROUND(((((EU69*1.25)*1.1))*AV69*I69),2)*BS69),2)+ROUND((ROUND(((AE69-(((EU69*1.25)*1.1)))*AV69*I69),2)*BS69),2)) -> 5.44 | S69: =ROUND((ROUND((AF69*AV69*I69),2)*BA69),2) -> 445.39 | T69: =ROUND(CU69*I69,2) -> 0 | U69: =CV69*I69 -> 36.297611 | V69: =CW69*I69 -> 0 | W69: =ROUND(CX69*I69,2) -> 0 | X69: =(ROUND((((S69+ROUND((ROUND(((((EU69*1.25)*1.1))*AV69*I69),2)*BS69),2))*AT69)/100),2)+ROUND(((ROUND((ROUND(((AE69-(((EU69*1.25)*1.1)))*AV69*I69),2)*BS69),2)*AT69)/100),2)) -> 491.4 | Y69: =(ROUND((((S69+ROUND((ROUND(((((EU69*1.25)*1.1))*AV69*I69),2)*BS69),2))*AU69)/100),2)+ROUND(((ROUND((ROUND(((AE69-(((EU69*1.25)*1.1)))*AV69*I69),2)*BS69),2)*AU69)/100),2)) -> 275.01 | AA69: 60255014 | AB69: =ROUND((AC69+AD69+AF69),6) -> 3369.5053 | AC69: =ROUND((ES69),6) -> 2078.9 | AD69: =ROUND((((((ET69*1.25)*1.1))-(((EU69*1.25)*1.1)))+AE69),6) -> 131.10625 | AE69: =ROUND((((EU69*1.25)*1.1)),6) -> 14.1625 | AF69: =ROUND((((EV69*1.15)*1.1)),6) -> 1159.499 | AG69: =ROUND((AP69),6) -> 0 | AH69: =(((EW69*1.15)*1.1)) -> 94.4955 | AI69: =(((EX69*1.25)*1.1)) -> 0 | AJ69: =(AS69) -> 0 | AK69: 3090.85 | AL69: 2078.9 | AM69: 95.35 | AN69: 10.3 | AO69: 916.6 | AP69: 0 | AQ69: 74.7 | AR69: 0 | AS69: 0 | AT69: 109 | AU69: 61 | AV69: 1.067 | AW69: 1 | AZ69: 1 | BA69: 1 | BB69: 1 | BC69: 1 | BH69: 0 | BI69: 1 | BJ69: ТСН-2001.3 Доп. 80, Сб. 18, т. 25, поз. 1 | BM69: 23 | BN69: 0 | BO69: 3.18-25-1 | BP69: 1 | BQ69: 30 | BR69: 0 | BS69: 1 | BT69: 1 | BU69: 1 | BV69: 1 | BW69: 1 | BX69: 1 | BZ69: 109 | CA69: 61 | CE69: 1566 | CF69: 0 | CG69: 0 | CM69: 0 | CN69: Поправка: О.П. п.3.4. 6 Наименование: Выполняемые при ремонте и реконструкции работы аналогичные технологическим процессам, характерным для нового строительства и отсутствующим в сборниках на ремонтно-строительные работы Поправка: О.П. п.3.4.30.в Наименование: При применении территориальных сметных нормативов для города Москвы затраты, учитывающие напряженные и стесненные условия производства работ (стесненность, сложность складирования и транспортной логистики и т.п.), исчисляются с применением коэффициентов к затратам труда и заработной плате рабочих, машинистов, времени эксплуатации машин и механизмов, стоимости эксплуатации машин в размере: для объектов, расположенных за пределами Третьего транспортного кольца города Москвы, но в пределах Московской кольцевой автомобильной дороги | CO69: 0 | CP69: =(P69+Q69+S69) -> 1244.15 | CQ69: =ROUND((ROUND((AC69*AW69*1),2)*BC69),2) -> 2078.9 | CR69: =(ROUND((ROUND(((((ET69*1.25)*1.1))*AV69*1),2)*BB69),2)+ROUND((ROUND(((AE69-(((EU69*1.25)*1.1)))*AV69*1),2)*BS69),2)) -> 139.89 | CS69: =(ROUND((ROUND(((((EU69*1.25)*1.1))*AV69*1),2)*BS69),2)+ROUND((ROUND(((AE69-(((EU69*1.25)*1.1)))*AV69*1),2)*BS69),2)) -> 15.11 | CT69: =ROUND((ROUND((AF69*AV69*1),2)*BA69),2) -> 1237.19 | CU69: =AG69 -> 0 | CV69: =(AH69*AV69) -> 100.8267 | CW69: =AI69 -> 0 | CX69: =AJ69 -> 0 | CY69: =(ROUND((((S69+ROUND((ROUND(((((EU69*1.25)*1.1))*AV69*1),2)*BS69),2))*AT69)/100),2)+ROUND(((ROUND((ROUND(((AE69-(((EU69*1.25)*1.1)))*AV69*1),2)*BS69),2)*AT69)/100),2)) -> 501.95 | CZ69: =(ROUND((((S69+ROUND((ROUND(((((EU69*1.25)*1.1))*AV69*1),2)*BS69),2))*AU69)/100),2)+ROUND(((ROUND((ROUND(((AE69-(((EU69*1.25)*1.1)))*AV69*1),2)*BS69),2)*AU69)/100),2)) -> 280.91 | DB69: 1 | DE69: *1,25)*1,1 | DF69: *1,25)*1,1 | DG69: *1,15)*1,1 | DI69: *1,15)*1,1 | DJ69: *1,25)*1,1 | DN69: 0 | DO69: 0 | DP69: 1 | DQ69: 1 | DU69: 1010 | DV69: 100 шт. | DW69: 100 шт. | DX69: 100 | EE69: 60088254 | EF69: 30 | EG69: Строительные работы | EH69: 0 | EJ69: 1 | EK69: 23 | EL69: ТСН-2001.3-18. Отопление - внутренние устройства | EM69: ТСН-2001.3-18-1 | EO69: Поправка: О.П. п.3.4. 6 Поправка: О.П. п.3.4.30.в | EQ69: 0 | ER69: 3090.85 | ES69: 2078.9 | ET69: 95.35 | EU69: 10.3 | EV69: 916.6 | EW69: 74.7 | EX69: 0 | EY69: 0 | FQ69: 0 | FR69: 0 | FS69: 0 | FX69: 109 | FY69: 61 | GD69: 1 | GF69: -961949121 | GG69: 2 | GH69: 1 | GI69: 2 | GJ69: 0 | GK69: 0 | GL69: =ROUND(IF(AND(BH69=3,BI69=3,FS69<>0),P69,0),2) -> 0 | GM69: =ROUND(O69+X69+Y69,2)+GX69 -> 2010.56 | GN69: =IF(OR(BI69=0,BI69=1),GM69-GX69,0) -> 2010.56 | GO69: =IF(BI69=2,GM69-GX69,0) -> 0 | GP69: =IF(BI69=4,GM69-GX69,0) -> 0 | GR69: 0 | GS69: 3 | GT69: 0 | GV69: =ROUND((GT69),6) -> 0 | GW69: 1 | GX69: =ROUND(HC69*I69,2) -> 0 | HA69: 0 | HB69: 0 | HC69: =GV69*GW69 -> 0 | HS69: 0 | IK69: 0
A70: 17 | B70: 1 | C70: =ROW(SmtRes!A28) -> 28 | D70: =ROW(EtalonRes!A32) -> 32 | E70: 4 | F70: 3.18-25-1 | G70: Установка радиаторов стальных панельных однорядных с креплением к стене длиной до 1600 мм | H70: 100 шт. | I70: =ROUND((1+3+2+20+1+9)/100,9) -> 0.36 | J70: 0 | K70: =ROUND((1+3+2+20+1+9)/100,9) -> 0.36 | O70: =ROUND(CP70,2) -> 40623.22 | P70: =ROUND((ROUND((AC70*AW70*I70),2)*BC70),2) -> 15409.56 | Q70: =(ROUND((ROUND(((((ET70*1.25)*1.1))*AV70*I70),2)*BB70),2)+ROUND((ROUND(((AE70-(((EU70*1.25)*1.1)))*AV70*I70),2)*BS70),2)) -> 721.66 | R70: =(ROUND((ROUND(((((EU70*1.25)*1.1))*AV70*I70),2)*BS70),2)+ROUND((ROUND(((AE70-(((EU70*1.25)*1.1)))*AV70*I70),2)*BS70),2)) -> 299.15 | S70: =ROUND((ROUND((AF70*AV70*I70),2)*BA70),2) -> 24492 | T70: =ROUND(CU70*I70,2) -> 0 | U70: =CV70*I70 -> 36.297611 | V70: =CW70*I70 -> 0 | W70: =ROUND(CX70*I70,2) -> 0 | X70: =(ROUND((((S70+ROUND((ROUND(((((EU70*1.25)*1.1))*AV70*I70),2)*BS70),2))*AT70)/100),2)+ROUND(((ROUND((ROUND(((AE70-(((EU70*1.25)*1.1)))*AV70*I70),2)*BS70),2)*AT70)/100),2)) -> 27022.35 | Y70: =(ROUND((((S70+ROUND((ROUND(((((EU70*1.25)*1.1))*AV70*I70),2)*BS70),2))*AU70)/100),2)+ROUND(((ROUND((ROUND(((AE70-(((EU70*1.25)*1.1)))*AV70*I70),2)*BS70),2)*AU70)/100),2)) -> 15122.6 | AA70: 60255011 | AB70: =ROUND((AC70+AD70+AF70),6) -> 3369.5053 | AC70: =ROUND((ES70),6) -> 2078.9 | AD70: =ROUND((((((ET70*1.25)*1.1))-(((EU70*1.25)*1.1)))+AE70),6) -> 131.10625 | AE70: =ROUND((((EU70*1.25)*1.1)),6) -> 14.1625 | AF70: =ROUND((((EV70*1.15)*1.1)),6) -> 1159.499 | AG70: =ROUND((AP70),6) -> 0 | AH70: =(((EW70*1.15)*1.1)) -> 94.4955 | AI70: =(((EX70*1.25)*1.1)) -> 0 | AJ70: =(AS70) -> 0 | AK70: 3090.85 | AL70: 2078.9 | AM70: 95.35 | AN70: 10.3 | AO70: 916.6 | AP70: 0 | AQ70: 74.7 | AR70: 0 | AS70: 0 | AT70: 109 | AU70: 61 | AV70: 1.067 | AW70: 1 | AZ70: 1 | BA70: 54.99 | BB70: 14.33 | BC70: 20.59 | BH70: 0 | BI70: 1 | BJ70: ТСН-2001.3 Доп. 80, Сб. 18, т. 25, поз. 1 | BM70: 23 | BN70: 0 | BO70: 3.18-25-1 | BP70: 1 | BQ70: 30 | BR70: 0 | BS70: 54.99 | BT70: 1 | BU70: 1 | BV70: 1 | BW70: 1 | BX70: 1 | BZ70: 109 | CA70: 61 | CE70: 1566 | CF70: 0 | CG70: 0 | CM70: 0 | CN70: Поправка: О.П. п.3.4. 6 Наименование: Выполняемые при ремонте и реконструкции работы аналогичные технологическим процессам, характерным для нового строительства и отсутствующим в сборниках на ремонтно-строительные работы Поправка: О.П. п.3.4.30.в Наименование: При применении территориальных сметных нормативов для города Москвы затраты, учитывающие напряженные и стесненные условия производства работ (стесненность, сложность складирования и транспортной логистики и т.п.), исчисляются с применением коэффициентов к затратам труда и заработной плате рабочих, машинистов, времени эксплуатации машин и механизмов, стоимости эксплуатации машин в размере: для объектов, расположенных за пределами Третьего транспортного кольца города Москвы, но в пределах Московской кольцевой автомобильной дороги | CO70: 0 | CP70: =(P70+Q70+S70) -> 40623.22 | CQ70: =ROUND((ROUND((AC70*AW70*1),2)*BC70),2) -> 42804.55 | CR70: =(ROUND((ROUND(((((ET70*1.25)*1.1))*AV70*1),2)*BB70),2)+ROUND((ROUND(((AE70-(((EU70*1.25)*1.1)))*AV70*1),2)*BS70),2)) -> 2004.62 | CS70: =(ROUND((ROUND(((((EU70*1.25)*1.1))*AV70*1),2)*BS70),2)+ROUND((ROUND(((AE70-(((EU70*1.25)*1.1)))*AV70*1),2)*BS70),2)) -> 830.9 | CT70: =ROUND((ROUND((AF70*AV70*1),2)*BA70),2) -> 68033.08 | CU70: =AG70 -> 0 | CV70: =(AH70*AV70) -> 100.8267 | CW70: =AI70 -> 0 | CX70: =AJ70 -> 0 | CY70: =(ROUND((((S70+ROUND((ROUND(((((EU70*1.25)*1.1))*AV70*1),2)*BS70),2))*AT70)/100),2)+ROUND(((ROUND((ROUND(((AE70-(((EU70*1.25)*1.1)))*AV70*1),2)*BS70),2)*AT70)/100),2)) -> 27601.96 | CZ70: =(ROUND((((S70+ROUND((ROUND(((((EU70*1.25)*1.1))*AV70*1),2)*BS70),2))*AU70)/100),2)+ROUND(((ROUND((ROUND(((AE70-(((EU70*1.25)*1.1)))*AV70*1),2)*BS70),2)*AU70)/100),2)) -> 15446.97 | DB70: 3 | DE70: *1,25)*1,1 | DF70: *1,25)*1,1 | DG70: *1,15)*1,1 | DI70: *1,15)*1,1 | DJ70: *1,25)*1,1 | DN70: 0 | DO70: 0 | DP70: 1 | DQ70: 1 | DU70: 1010 | DV70: 100 шт. | DW70: 100 шт. | DX70: 100 | EE70: 60088254 | EF70: 30 | EG70: Строительные работы | EH70: 0 | EJ70: 1 | EK70: 23 | EL70: ТСН-2001.3-18. Отопление - внутренние устройства | EM70: ТСН-2001.3-18-1 | EO70: Поправка: О.П. п.3.4. 6 Поправка: О.П. п.3.4.30.в | EQ70: 0 | ER70: 3090.85 | ES70: 2078.9 | ET70: 95.35 | EU70: 10.3 | EV70: 916.6 | EW70: 74.7 | EX70: 0 | EY70: 0 | FQ70: 0 | FR70: 0 | FS70: 0 | FX70: 109 | FY70: 61 | GD70: 1 | GF70: -961949121 | GG70: 2 | GH70: 1 | GI70: 2 | GJ70: 0 | GK70: 0 | GL70: =ROUND(IF(AND(BH70=3,BI70=3,FS70<>0),P70,0),2) -> 0 | GM70: =ROUND(O70+X70+Y70,2)+GX70 -> 82768.17 | GN70: =IF(OR(BI70=0,BI70=1),GM70-GX70,0) -> 82768.17 | GO70: =IF(BI70=2,GM70-GX70,0) -> 0 | GP70: =IF(BI70=4,GM70-GX70,0) -> 0 | GR70: 0 | GS70: 3 | GT70: 0 | GV70: =ROUND((GT70),6) -> 0 | GW70: 1 | GX70: =ROUND(HC70*I70,2) -> 0 | HA70: 0 | HB70: 0 | HC70: =GV70*GW70 -> 0 | HS70: 0 | IK70: 0
A71: 17 | B71: 1 | E71: 5 | F71: КА-1 | G71: Радиатор стальной трубчатый GUARDO TORRE 3D, 400 мм (BK-VER-BLACK), черный 3D-400-350 (мощность 0,336 кВт) | H71: ШТ | I71: 1 | J71: 0 | K71: 1 | O71: =ROUND(CP71,2) -> 988.51 | P71: =ROUND((ROUND((AC71*AW71*I71),2)*BC71),2) -> 988.51 | Q71: =(ROUND((ROUND(((ET71)*AV71*I71),2)*BB71),2)+ROUND((ROUND(((AE71-(EU71))*AV71*I71),2)*BS71),2)) -> 0 | R71: =(ROUND((ROUND(((EU71)*AV71*I71),2)*BS71),2)+ROUND((ROUND(((AE71-(EU71))*AV71*I71),2)*BS71),2)) -> 0 | S71: =ROUND((ROUND((AF71*AV71*I71),2)*BA71),2) -> 0 | T71: =ROUND(CU71*I71,2) -> 0 | U71: =CV71*I71 -> 0 | V71: =CW71*I71 -> 0 | W71: =ROUND(CX71*I71,2) -> 0 | X71: =(ROUND((((S71+ROUND((ROUND(((EU71)*AV71*I71),2)*BS71),2))*AT71)/100),2)+ROUND(((ROUND((ROUND(((AE71-(EU71))*AV71*I71),2)*BS71),2)*AT71)/100),2)) -> 0 | Y71: =(ROUND((((S71+ROUND((ROUND(((EU71)*AV71*I71),2)*BS71),2))*AU71)/100),2)+ROUND(((ROUND((ROUND(((AE71-(EU71))*AV71*I71),2)*BS71),2)*AU71)/100),2)) -> 0 | AA71: 60255014 | AB71: =ROUND((AC71+AD71+AF71),6) -> 988.51 | AC71: =ROUND((ES71),6) -> 988.51 | AD71: =ROUND((((ET71)-(EU71))+AE71),6) -> 0 | AE71: =ROUND((EU71),6) -> 0 | AF71: =ROUND((EV71),6) -> 0 | AG71: =ROUND((AP71),6) -> 0 | AH71: =(EW71) -> 0 | AI71: =(EX71) -> 0 | AJ71: =(AS71) -> 0 | AK71: 988.51 | AL71: 988.51 | AM71: 0 | AN71: 0 | AO71: 0 | AP71: 0 | AQ71: 0 | AR71: 0 | AS71: 0 | AT71: 0 | AU71: 0 | AV71: 1 | AW71: 1 | AZ71: 1 | BA71: 1 | BB71: 1 | BC71: 1 | BH71: 3 | BI71: 1 | BM71: 400002 | BN71: 0 | BP71: 0 | BQ71: 202 | BR71: 0 | BS71: 1 | BT71: 1 | BU71: 1 | BV71: 1 | BW71: 1 | BX71: 1 | BZ71: 0 | CA71: 0 | CE71: 1566 | CF71: 0 | CG71: 0 | CM71: 0 | CO71: 0 | CP71: =(P71+Q71+S71) -> 988.51 | CQ71: =ROUND((ROUND((AC71*AW71*1),2)*BC71),2) -> 988.51 | CR71: =(ROUND((ROUND(((ET71)*AV71*1),2)*BB71),2)+ROUND((ROUND(((AE71-(EU71))*AV71*1),2)*BS71),2)) -> 0 | CS71: =(ROUND((ROUND(((EU71)*AV71*1),2)*BS71),2)+ROUND((ROUND(((AE71-(EU71))*AV71*1),2)*BS71),2)) -> 0 | CT71: =ROUND((ROUND((AF71*AV71*1),2)*BA71),2) -> 0 | CU71: =AG71 -> 0 | CV71: =(AH71*AV71) -> 0 | CW71: =AI71 -> 0 | CX71: =AJ71 -> 0 | CY71: =(ROUND((((S71+ROUND((ROUND(((EU71)*AV71*1),2)*BS71),2))*AT71)/100),2)+ROUND(((ROUND((ROUND(((AE71-(EU71))*AV71*1),2)*BS71),2)*AT71)/100),2)) -> 0 | CZ71: =(ROUND((((S71+ROUND((ROUND(((EU71)*AV71*1),2)*BS71),2))*AU71)/100),2)+ROUND(((ROUND((ROUND(((AE71-(EU71))*AV71*1),2)*BS71),2)*AU71)/100),2)) -> 0 | DN71: 0 | DO71: 0 | DP71: 1 | DQ71: 1 | DU71: 1013 | DV71: ШТ | DW71: ШТ | DX71: 1 | EE71: 60088211 | EF71: 202 | EG71: Материалы | EH71: 0 | EJ71: 1 | EK71: 400002 | EL71: Материалы, изделия и конструкции | EM71: Материалы | EQ71: 0 | ER71: 0 | ES71: 988.51 | ET71: 0 | EU71: 0 | EV71: 0 | EW71: 0 | EX71: 0 | EY71: 0 | FQ71: 0 | FR71: 0 | FS71: 0 | FX71: 0 | FY71: 0 | GA71: [11 490 / 1,2 / 9,88] + 2% Заг.скл | GD71: 1 | GF71: -1745178148 | GG71: 2 | GH71: 4 | GI71: -2 | GJ71: 0 | GK71: 0 | GL71: =ROUND(IF(AND(BH71=3,BI71=3,FS71<>0),P71,0),2) -> 0 | GM71: =ROUND(O71+X71+Y71,2)+GX71 -> 988.51 | GN71: =IF(OR(BI71=0,BI71=1),GM71-GX71,0) -> 988.51 | GO71: =IF(BI71=2,GM71-GX71,0) -> 0 | GP71: =IF(BI71=4,GM71-GX71,0) -> 0 | GR71: 0 | GS71: 2 | GT71: 0 | GV71: =ROUND((GT71),6) -> 0 | GW71: 1 | GX71: =ROUND(HC71*I71,2) -> 0 | HA71: 0 | HB71: 0 | HC71: =GV71*GW71 -> 0 | HE71: 0 | HF71: 2 | HS71: 0 | IK71: 0
A72: 17 | B72: 1 | E72: 5 | F72: КА-1 | G72: Радиатор стальной трубчатый GUARDO TORRE 3D, 400 мм (BK-VER-BLACK), черный 3D-400-350 (мощность 0,336 кВт) | H72: ШТ | I72: 1 | J72: 0 | K72: 1 | O72: =ROUND(CP72,2) -> 9766.48 | P72: =ROUND((ROUND((AC72*AW72*I72),2)*BC72),2) -> 9766.48 | Q72: =(ROUND((ROUND(((ET72)*AV72*I72),2)*BB72),2)+ROUND((ROUND(((AE72-(EU72))*AV72*I72),2)*BS72),2)) -> 0 | R72: =(ROUND((ROUND(((EU72)*AV72*I72),2)*BS72),2)+ROUND((ROUND(((AE72-(EU72))*AV72*I72),2)*BS72),2)) -> 0 | S72: =ROUND((ROUND((AF72*AV72*I72),2)*BA72),2) -> 0 | T72: =ROUND(CU72*I72,2) -> 0 | U72: =CV72*I72 -> 0 | V72: =CW72*I72 -> 0 | W72: =ROUND(CX72*I72,2) -> 0 | X72: =(ROUND((((S72+ROUND((ROUND(((EU72)*AV72*I72),2)*BS72),2))*AT72)/100),2)+ROUND(((ROUND((ROUND(((AE72-(EU72))*AV72*I72),2)*BS72),2)*AT72)/100),2)) -> 0 | Y72: =(ROUND((((S72+ROUND((ROUND(((EU72)*AV72*I72),2)*BS72),2))*AU72)/100),2)+ROUND(((ROUND((ROUND(((AE72-(EU72))*AV72*I72),2)*BS72),2)*AU72)/100),2)) -> 0 | AA72: 60255011 | AB72: =ROUND((AC72+AD72+AF72),6) -> 988.51 | AC72: =ROUND((ES72),6) -> 988.51 | AD72: =ROUND((((ET72)-(EU72))+AE72),6) -> 0 | AE72: =ROUND((EU72),6) -> 0 | AF72: =ROUND((EV72),6) -> 0 | AG72: =ROUND((AP72),6) -> 0 | AH72: =(EW72) -> 0 | AI72: =(EX72) -> 0 | AJ72: =(AS72) -> 0 | AK72: 988.51 | AL72: 988.51 | AM72: 0 | AN72: 0 | AO72: 0 | AP72: 0 | AQ72: 0 | AR72: 0 | AS72: 0 | AT72: 0 | AU72: 0 | AV72: 1 | AW72: 1 | AZ72: 1 | BA72: 1 | BB72: 1 | BC72: 9.88 | BH72: 3 | BI72: 1 | BM72: 400002 | BN72: 0 | BP72: 0 | BQ72: 202 | BR72: 0 | BS72: 1 | BT72: 1 | BU72: 1 | BV72: 1 | BW72: 1 | BX72: 1 | BZ72: 0 | CA72: 0 | CE72: 1566 | CF72: 0 | CG72: 0 | CM72: 0 | CO72: 0 | CP72: =(P72+Q72+S72) -> 9766.48 | CQ72: =ROUND((ROUND((AC72*AW72*1),2)*BC72),2) -> 9766.48 | CR72: =(ROUND((ROUND(((ET72)*AV72*1),2)*BB72),2)+ROUND((ROUND(((AE72-(EU72))*AV72*1),2)*BS72),2)) -> 0 | CS72: =(ROUND((ROUND(((EU72)*AV72*1),2)*BS72),2)+ROUND((ROUND(((AE72-(EU72))*AV72*1),2)*BS72),2)) -> 0 | CT72: =ROUND((ROUND((AF72*AV72*1),2)*BA72),2) -> 0 | CU72: =AG72 -> 0 | CV72: =(AH72*AV72) -> 0 | CW72: =AI72 -> 0 | CX72: =AJ72 -> 0 | CY72: =(ROUND((((S72+ROUND((ROUND(((EU72)*AV72*1),2)*BS72),2))*AT72)/100),2)+ROUND(((ROUND((ROUND(((AE72-(EU72))*AV72*1),2)*BS72),2)*AT72)/100),2)) -> 0 | CZ72: =(ROUND((((S72+ROUND((ROUND(((EU72)*AV72*1),2)*BS72),2))*AU72)/100),2)+ROUND(((ROUND((ROUND(((AE72-(EU72))*AV72*1),2)*BS72),2)*AU72)/100),2)) -> 0 | DN72: 0 | DO72: 0 | DP72: 1 | DQ72: 1 | DU72: 1013 | DV72: ШТ | DW72: ШТ | DX72: 1 | EE72: 60088211 | EF72: 202 | EG72: Материалы | EH72: 0 | EJ72: 1 | EK72: 400002 | EL72: Материалы, изделия и конструкции | EM72: Материалы | EQ72: 0 | ER72: 988.51 | ES72: 988.51 | ET72: 0 | EU72: 0 | EV72: 0 | EW72: 0 | EX72: 0 | EY72: 0 | EZ72: 5 | FC72: 1 | FD72: 18 | FF72: 11490 | FQ72: 0 | FR72: 0 | FS72: 0 | FX72: 0 | FY72: 0 | GA72: [11 490 / 1,2 / 9,88] + 2% Заг.скл | GD72: 1 | GF72: -1745178148 | GG72: 2 | GH72: 3 | GI72: 5 | GJ72: 0 | GK72: 0 | GL72: =ROUND(IF(AND(BH72=3,BI72=3,FS72<>0),P72,0),2) -> 0 | GM72: =ROUND(O72+X72+Y72,2)+GX72 -> 9766.48 | GN72: =IF(OR(BI72=0,BI72=1),GM72-GX72,0) -> 9766.48 | GO72: =IF(BI72=2,GM72-GX72,0) -> 0 | GP72: =IF(BI72=4,GM72-GX72,0) -> 0 | GR72: 1 | GS72: 1 | GT72: 0 | GV72: =ROUND((GT72),6) -> 0 | GW72: 1 | GX72: =ROUND(HC72*I72,2) -> 0 | HA72: 0 | HB72: 0 | HC72: =GV72*GW72 -> 0 | HE72: 0 | HF72: 2 | HS72: 0 | IK72: 0
A73: 17 | B73: 1 | E73: 6 | F73: КА-2 | G73: Радиатор стальной трубчатый GUARDO TORRE 3D, 400 мм (BK-VER-BLACK), черный 3D-400-750 (мощность 0,663 кВт) | H73: ШТ | I73: 3 | J73: 0 | K73: 3 | O73: =ROUND(CP73,2) -> 4939.98 | P73: =ROUND((ROUND((AC73*AW73*I73),2)*BC73),2) -> 4939.98 | Q73: =(ROUND((ROUND(((ET73)*AV73*I73),2)*BB73),2)+ROUND((ROUND(((AE73-(EU73))*AV73*I73),2)*BS73),2)) -> 0 | R73: =(ROUND((ROUND(((EU73)*AV73*I73),2)*BS73),2)+ROUND((ROUND(((AE73-(EU73))*AV73*I73),2)*BS73),2)) -> 0 | S73: =ROUND((ROUND((AF73*AV73*I73),2)*BA73),2) -> 0 | T73: =ROUND(CU73*I73,2) -> 0 | U73: =CV73*I73 -> 0 | V73: =CW73*I73 -> 0 | W73: =ROUND(CX73*I73,2) -> 0 | X73: =(ROUND((((S73+ROUND((ROUND(((EU73)*AV73*I73),2)*BS73),2))*AT73)/100),2)+ROUND(((ROUND((ROUND(((AE73-(EU73))*AV73*I73),2)*BS73),2)*AT73)/100),2)) -> 0 | Y73: =(ROUND((((S73+ROUND((ROUND(((EU73)*AV73*I73),2)*BS73),2))*AU73)/100),2)+ROUND(((ROUND((ROUND(((AE73-(EU73))*AV73*I73),2)*BS73),2)*AU73)/100),2)) -> 0 | AA73: 60255014 | AB73: =ROUND((AC73+AD73+AF73),6) -> 1646.66 | AC73: =ROUND((ES73),6) -> 1646.66 | AD73: =ROUND((((ET73)-(EU73))+AE73),6) -> 0 | AE73: =ROUND((EU73),6) -> 0 | AF73: =ROUND((EV73),6) -> 0 | AG73: =ROUND((AP73),6) -> 0 | AH73: =(EW73) -> 0 | AI73: =(EX73) -> 0 | AJ73: =(AS73) -> 0 | AK73: 1646.66 | AL73: 1646.66 | AM73: 0 | AN73: 0 | AO73: 0 | AP73: 0 | AQ73: 0 | AR73: 0 | AS73: 0 | AT73: 0 | AU73: 0 | AV73: 1 | AW73: 1 | AZ73: 1 | BA73: 1 | BB73: 1 | BC73: 1 | BH73: 3 | BI73: 1 | BM73: 400002 | BN73: 0 | BP73: 0 | BQ73: 202 | BR73: 0 | BS73: 1 | BT73: 1 | BU73: 1 | BV73: 1 | BW73: 1 | BX73: 1 | BZ73: 0 | CA73: 0 | CE73: 1566 | CF73: 0 | CG73: 0 | CM73: 0 | CO73: 0 | CP73: =(P73+Q73+S73) -> 4939.98 | CQ73: =ROUND((ROUND((AC73*AW73*1),2)*BC73),2) -> 1646.66 | CR73: =(ROUND((ROUND(((ET73)*AV73*1),2)*BB73),2)+ROUND((ROUND(((AE73-(EU73))*AV73*1),2)*BS73),2)) -> 0 | CS73: =(ROUND((ROUND(((EU73)*AV73*1),2)*BS73),2)+ROUND((ROUND(((AE73-(EU73))*AV73*1),2)*BS73),2)) -> 0 | CT73: =ROUND((ROUND((AF73*AV73*1),2)*BA73),2) -> 0 | CU73: =AG73 -> 0 | CV73: =(AH73*AV73) -> 0 | CW73: =AI73 -> 0 | CX73: =AJ73 -> 0 | CY73: =(ROUND((((S73+ROUND((ROUND(((EU73)*AV73*1),2)*BS73),2))*AT73)/100),2)+ROUND(((ROUND((ROUND(((AE73-(EU73))*AV73*1),2)*BS73),2)*AT73)/100),2)) -> 0 | CZ73: =(ROUND((((S73+ROUND((ROUND(((EU73)*AV73*1),2)*BS73),2))*AU73)/100),2)+ROUND(((ROUND((ROUND(((AE73-(EU73))*AV73*1),2)*BS73),2)*AU73)/100),2)) -> 0 | DN73: 0 | DO73: 0 | DP73: 1 | DQ73: 1 | DU73: 1013 | DV73: ШТ | DW73: ШТ | DX73: 1 | EE73: 60088211 | EF73: 202 | EG73: Материалы | EH73: 0 | EJ73: 1 | EK73: 400002 | EL73: Материалы, изделия и конструкции | EM73: Материалы | EQ73: 0 | ER73: 0 | ES73: 1646.66 | ET73: 0 | EU73: 0 | EV73: 0 | EW73: 0 | EX73: 0 | EY73: 0 | FQ73: 0 | FR73: 0 | FS73: 0 | FX73: 0 | FY73: 0 | GA73: [19 140 / 1,2 / 9,88] + 2% Заг.скл | GD73: 1 | GF73: 1989700705 | GG73: 2 | GH73: 4 | GI73: -2 | GJ73: 0 | GK73: 0 | GL73: =ROUND(IF(AND(BH73=3,BI73=3,FS73<>0),P73,0),2) -> 0 | GM73: =ROUND(O73+X73+Y73,2)+GX73 -> 4939.98 | GN73: =IF(OR(BI73=0,BI73=1),GM73-GX73,0) -> 4939.98 | GO73: =IF(BI73=2,GM73-GX73,0) -> 0 | GP73: =IF(BI73=4,GM73-GX73,0) -> 0 | GR73: 0 | GS73: 2 | GT73: 0 | GV73: =ROUND((GT73),6) -> 0 | GW73: 1 | GX73: =ROUND(HC73*I73,2) -> 0 | HA73: 0 | HB73: 0 | HC73: =GV73*GW73 -> 0 | HE73: 0 | HF73: 2 | HS73: 0 | IK73: 0
A74: 17 | B74: 1 | E74: 6 | F74: КА-2 | G74: Радиатор стальной трубчатый GUARDO TORRE 3D, 400 мм (BK-VER-BLACK), черный 3D-400-750 (мощность 0,663 кВт) | H74: ШТ | I74: 3 | J74: 0 | K74: 3 | O74: =ROUND(CP74,2) -> 48807 | P74: =ROUND((ROUND((AC74*AW74*I74),2)*BC74),2) -> 48807 | Q74: =(ROUND((ROUND(((ET74)*AV74*I74),2)*BB74),2)+ROUND((ROUND(((AE74-(EU74))*AV74*I74),2)*BS74),2)) -> 0 | R74: =(ROUND((ROUND(((EU74)*AV74*I74),2)*BS74),2)+ROUND((ROUND(((AE74-(EU74))*AV74*I74),2)*BS74),2)) -> 0 | S74: =ROUND((ROUND((AF74*AV74*I74),2)*BA74),2) -> 0 | T74: =ROUND(CU74*I74,2) -> 0 | U74: =CV74*I74 -> 0 | V74: =CW74*I74 -> 0 | W74: =ROUND(CX74*I74,2) -> 0 | X74: =(ROUND((((S74+ROUND((ROUND(((EU74)*AV74*I74),2)*BS74),2))*AT74)/100),2)+ROUND(((ROUND((ROUND(((AE74-(EU74))*AV74*I74),2)*BS74),2)*AT74)/100),2)) -> 0 | Y74: =(ROUND((((S74+ROUND((ROUND(((EU74)*AV74*I74),2)*BS74),2))*AU74)/100),2)+ROUND(((ROUND((ROUND(((AE74-(EU74))*AV74*I74),2)*BS74),2)*AU74)/100),2)) -> 0 | AA74: 60255011 | AB74: =ROUND((AC74+AD74+AF74),6) -> 1646.66 | AC74: =ROUND((ES74),6) -> 1646.66 | AD74: =ROUND((((ET74)-(EU74))+AE74),6) -> 0 | AE74: =ROUND((EU74),6) -> 0 | AF74: =ROUND((EV74),6) -> 0 | AG74: =ROUND((AP74),6) -> 0 | AH74: =(EW74) -> 0 | AI74: =(EX74) -> 0 | AJ74: =(AS74) -> 0 | AK74: 1646.66 | AL74: 1646.66 | AM74: 0 | AN74: 0 | AO74: 0 | AP74: 0 | AQ74: 0 | AR74: 0 | AS74: 0 | AT74: 0 | AU74: 0 | AV74: 1 | AW74: 1 | AZ74: 1 | BA74: 1 | BB74: 1 | BC74: 9.88 | BH74: 3 | BI74: 1 | BM74: 400002 | BN74: 0 | BP74: 0 | BQ74: 202 | BR74: 0 | BS74: 1 | BT74: 1 | BU74: 1 | BV74: 1 | BW74: 1 | BX74: 1 | BZ74: 0 | CA74: 0 | CE74: 1566 | CF74: 0 | CG74: 0 | CM74: 0 | CO74: 0 | CP74: =(P74+Q74+S74) -> 48807 | CQ74: =ROUND((ROUND((AC74*AW74*1),2)*BC74),2) -> 16269 | CR74: =(ROUND((ROUND(((ET74)*AV74*1),2)*BB74),2)+ROUND((ROUND(((AE74-(EU74))*AV74*1),2)*BS74),2)) -> 0 | CS74: =(ROUND((ROUND(((EU74)*AV74*1),2)*BS74),2)+ROUND((ROUND(((AE74-(EU74))*AV74*1),2)*BS74),2)) -> 0 | CT74: =ROUND((ROUND((AF74*AV74*1),2)*BA74),2) -> 0 | CU74: =AG74 -> 0 | CV74: =(AH74*AV74) -> 0 | CW74: =AI74 -> 0 | CX74: =AJ74 -> 0 | CY74: =(ROUND((((S74+ROUND((ROUND(((EU74)*AV74*1),2)*BS74),2))*AT74)/100),2)+ROUND(((ROUND((ROUND(((AE74-(EU74))*AV74*1),2)*BS74),2)*AT74)/100),2)) -> 0 | CZ74: =(ROUND((((S74+ROUND((ROUND(((EU74)*AV74*1),2)*BS74),2))*AU74)/100),2)+ROUND(((ROUND((ROUND(((AE74-(EU74))*AV74*1),2)*BS74),2)*AU74)/100),2)) -> 0 | DN74: 0 | DO74: 0 | DP74: 1 | DQ74: 1 | DU74: 1013 | DV74: ШТ | DW74: ШТ | DX74: 1 | EE74: 60088211 | EF74: 202 | EG74: Материалы | EH74: 0 | EJ74: 1 | EK74: 400002 | EL74: Материалы, изделия и конструкции | EM74: Материалы | EQ74: 0 | ER74: 1646.66 | ES74: 1646.66 | ET74: 0 | EU74: 0 | EV74: 0 | EW74: 0 | EX74: 0 | EY74: 0 | EZ74: 5 | FC74: 1 | FD74: 18 | FF74: 19140 | FQ74: 0 | FR74: 0 | FS74: 0 | FX74: 0 | FY74: 0 | GA74: [19 140 / 1,2 / 9,88] + 2% Заг.скл | GD74: 1 | GF74: 1989700705 | GG74: 2 | GH74: 3 | GI74: 5 | GJ74: 0 | GK74: 0 | GL74: =ROUND(IF(AND(BH74=3,BI74=3,FS74<>0),P74,0),2) -> 0 | GM74: =ROUND(O74+X74+Y74,2)+GX74 -> 48807 | GN74: =IF(OR(BI74=0,BI74=1),GM74-GX74,0) -> 48807 | GO74: =IF(BI74=2,GM74-GX74,0) -> 0 | GP74: =IF(BI74=4,GM74-GX74,0) -> 0 | GR74: 1 | GS74: 1 | GT74: 0 | GV74: =ROUND((GT74),6) -> 0 | GW74: 1 | GX74: =ROUND(HC74*I74,2) -> 0 | HA74: 0 | HB74: 0 | HC74: =GV74*GW74 -> 0 | HE74: 0 | HF74: 2 | HS74: 0 | IK74: 0
A75: 17 | B75: 1 | E75: 7 | F75: КА-3 | G75: Радиатор стальной трубчатый GUARDO TORRE 3D, 400 мм (BK-VER-WHITE), белый 3D-400-1650 (мощность 1,330 кВт) | H75: ШТ | I75: 2 | J75: 0 | K75: 2 | O75: =ROUND(CP75,2) -> 6364.68 | P75: =ROUND((ROUND((AC75*AW75*I75),2)*BC75),2) -> 6364.68 | Q75: =(ROUND((ROUND(((ET75)*AV75*I75),2)*BB75),2)+ROUND((ROUND(((AE75-(EU75))*AV75*I75),2)*BS75),2)) -> 0 | R75: =(ROUND((ROUND(((EU75)*AV75*I75),2)*BS75),2)+ROUND((ROUND(((AE75-(EU75))*AV75*I75),2)*BS75),2)) -> 0 | S75: =ROUND((ROUND((AF75*AV75*I75),2)*BA75),2) -> 0 | T75: =ROUND(CU75*I75,2) -> 0 | U75: =CV75*I75 -> 0 | V75: =CW75*I75 -> 0 | W75: =ROUND(CX75*I75,2) -> 0 | X75: =(ROUND((((S75+ROUND((ROUND(((EU75)*AV75*I75),2)*BS75),2))*AT75)/100),2)+ROUND(((ROUND((ROUND(((AE75-(EU75))*AV75*I75),2)*BS75),2)*AT75)/100),2)) -> 0 | Y75: =(ROUND((((S75+ROUND((ROUND(((EU75)*AV75*I75),2)*BS75),2))*AU75)/100),2)+ROUND(((ROUND((ROUND(((AE75-(EU75))*AV75*I75),2)*BS75),2)*AU75)/100),2)) -> 0 | AA75: 60255014 | AB75: =ROUND((AC75+AD75+AF75),6) -> 3182.34 | AC75: =ROUND((ES75),6) -> 3182.34 | AD75: =ROUND((((ET75)-(EU75))+AE75),6) -> 0 | AE75: =ROUND((EU75),6) -> 0 | AF75: =ROUND((EV75),6) -> 0 | AG75: =ROUND((AP75),6) -> 0 | AH75: =(EW75) -> 0 | AI75: =(EX75) -> 0 | AJ75: =(AS75) -> 0 | AK75: 3182.34 | AL75: 3182.34 | AM75: 0 | AN75: 0 | AO75: 0 | AP75: 0 | AQ75: 0 | AR75: 0 | AS75: 0 | AT75: 0 | AU75: 0 | AV75: 1 | AW75: 1 | AZ75: 1 | BA75: 1 | BB75: 1 | BC75: 1 | BH75: 3 | BI75: 1 | BM75: 400002 | BN75: 0 | BP75: 0 | BQ75: 202 | BR75: 0 | BS75: 1 | BT75: 1 | BU75: 1 | BV75: 1 | BW75: 1 | BX75: 1 | BZ75: 0 | CA75: 0 | CE75: 1566 | CF75: 0 | CG75: 0 | CM75: 0 | CO75: 0 | CP75: =(P75+Q75+S75) -> 6364.68 | CQ75: =ROUND((ROUND((AC75*AW75*1),2)*BC75),2) -> 3182.34 | CR75: =(ROUND((ROUND(((ET75)*AV75*1),2)*BB75),2)+ROUND((ROUND(((AE75-(EU75))*AV75*1),2)*BS75),2)) -> 0 | CS75: =(ROUND((ROUND(((EU75)*AV75*1),2)*BS75),2)+ROUND((ROUND(((AE75-(EU75))*AV75*1),2)*BS75),2)) -> 0 | CT75: =ROUND((ROUND((AF75*AV75*1),2)*BA75),2) -> 0 | CU75: =AG75 -> 0 | CV75: =(AH75*AV75) -> 0 | CW75: =AI75 -> 0 | CX75: =AJ75 -> 0 | CY75: =(ROUND((((S75+ROUND((ROUND(((EU75)*AV75*1),2)*BS75),2))*AT75)/100),2)+ROUND(((ROUND((ROUND(((AE75-(EU75))*AV75*1),2)*BS75),2)*AT75)/100),2)) -> 0 | CZ75: =(ROUND((((S75+ROUND((ROUND(((EU75)*AV75*1),2)*BS75),2))*AU75)/100),2)+ROUND(((ROUND((ROUND(((AE75-(EU75))*AV75*1),2)*BS75),2)*AU75)/100),2)) -> 0 | DN75: 0 | DO75: 0 | DP75: 1 | DQ75: 1 | DU75: 1013 | DV75: ШТ | DW75: ШТ | DX75: 1 | EE75: 60088211 | EF75: 202 | EG75: Материалы | EH75: 0 | EJ75: 1 | EK75: 400002 | EL75: Материалы, изделия и конструкции | EM75: Материалы | EQ75: 0 | ER75: 0 | ES75: 3182.34 | ET75: 0 | EU75: 0 | EV75: 0 | EW75: 0 | EX75: 0 | EY75: 0 | FQ75: 0 | FR75: 0 | FS75: 0 | FX75: 0 | FY75: 0 | GA75: [36 990 / 1,2 / 9,88] + 2% Заг.скл | GD75: 1 | GF75: -345521507 | GG75: 2 | GH75: 4 | GI75: -2 | GJ75: 0 | GK75: 0 | GL75: =ROUND(IF(AND(BH75=3,BI75=3,FS75<>0),P75,0),2) -> 0 | GM75: =ROUND(O75+X75+Y75,2)+GX75 -> 6364.68 | GN75: =IF(OR(BI75=0,BI75=1),GM75-GX75,0) -> 6364.68 | GO75: =IF(BI75=2,GM75-GX75,0) -> 0 | GP75: =IF(BI75=4,GM75-GX75,0) -> 0 | GR75: 0 | GS75: 2 | GT75: 0 | GV75: =ROUND((GT75),6) -> 0 | GW75: 1 | GX75: =ROUND(HC75*I75,2) -> 0 | HA75: 0 | HB75: 0 | HC75: =GV75*GW75 -> 0 | HE75: 0 | HF75: 2 | HS75: 0 | IK75: 0
A76: 17 | B76: 1 | E76: 7 | F76: КА-3 | G76: Радиатор стальной трубчатый GUARDO TORRE 3D, 400 мм (BK-VER-WHITE), белый 3D-400-1650 (мощность 1,330 кВт) | H76: ШТ | I76: 2 | J76: 0 | K76: 2 | O76: =ROUND(CP76,2) -> 62883.04 | P76: =ROUND((ROUND((AC76*AW76*I76),2)*BC76),2) -> 62883.04 | Q76: =(ROUND((ROUND(((ET76)*AV76*I76),2)*BB76),2)+ROUND((ROUND(((AE76-(EU76))*AV76*I76),2)*BS76),2)) -> 0 | R76: =(ROUND((ROUND(((EU76)*AV76*I76),2)*BS76),2)+ROUND((ROUND(((AE76-(EU76))*AV76*I76),2)*BS76),2)) -> 0 | S76: =ROUND((ROUND((AF76*AV76*I76),2)*BA76),2) -> 0 | T76: =ROUND(CU76*I76,2) -> 0 | U76: =CV76*I76 -> 0 | V76: =CW76*I76 -> 0 | W76: =ROUND(CX76*I76,2) -> 0 | X76: =(ROUND((((S76+ROUND((ROUND(((EU76)*AV76*I76),2)*BS76),2))*AT76)/100),2)+ROUND(((ROUND((ROUND(((AE76-(EU76))*AV76*I76),2)*BS76),2)*AT76)/100),2)) -> 0 | Y76: =(ROUND((((S76+ROUND((ROUND(((EU76)*AV76*I76),2)*BS76),2))*AU76)/100),2)+ROUND(((ROUND((ROUND(((AE76-(EU76))*AV76*I76),2)*BS76),2)*AU76)/100),2)) -> 0 | AA76: 60255011 | AB76: =ROUND((AC76+AD76+AF76),6) -> 3182.34 | AC76: =ROUND((ES76),6) -> 3182.34 | AD76: =ROUND((((ET76)-(EU76))+AE76),6) -> 0 | AE76: =ROUND((EU76),6) -> 0 | AF76: =ROUND((EV76),6) -> 0 | AG76: =ROUND((AP76),6) -> 0 | AH76: =(EW76) -> 0 | AI76: =(EX76) -> 0 | AJ76: =(AS76) -> 0 | AK76: 3182.34 | AL76: 3182.34 | AM76: 0 | AN76: 0 | AO76: 0 | AP76: 0 | AQ76: 0 | AR76: 0 | AS76: 0 | AT76: 0 | AU76: 0 | AV76: 1 | AW76: 1 | AZ76: 1 | BA76: 1 | BB76: 1 | BC76: 9.88 | BH76: 3 | BI76: 1 | BM76: 400002 | BN76: 0 | BP76: 0 | BQ76: 202 | BR76: 0 | BS76: 1 | BT76: 1 | BU76: 1 | BV76: 1 | BW76: 1 | BX76: 1 | BZ76: 0 | CA76: 0 | CE76: 1566 | CF76: 0 | CG76: 0 | CM76: 0 | CO76: 0 | CP76: =(P76+Q76+S76) -> 62883.04 | CQ76: =ROUND((ROUND((AC76*AW76*1),2)*BC76),2) -> 31441.52 | CR76: =(ROUND((ROUND(((ET76)*AV76*1),2)*BB76),2)+ROUND((ROUND(((AE76-(EU76))*AV76*1),2)*BS76),2)) -> 0 | CS76: =(ROUND((ROUND(((EU76)*AV76*1),2)*BS76),2)+ROUND((ROUND(((AE76-(EU76))*AV76*1),2)*BS76),2)) -> 0 | CT76: =ROUND((ROUND((AF76*AV76*1),2)*BA76),2) -> 0 | CU76: =AG76 -> 0 | CV76: =(AH76*AV76) -> 0 | CW76: =AI76 -> 0 | CX76: =AJ76 -> 0 | CY76: =(ROUND((((S76+ROUND((ROUND(((EU76)*AV76*1),2)*BS76),2))*AT76)/100),2)+ROUND(((ROUND((ROUND(((AE76-(EU76))*AV76*1),2)*BS76),2)*AT76)/100),2)) -> 0 | CZ76: =(ROUND((((S76+ROUND((ROUND(((EU76)*AV76*1),2)*BS76),2))*AU76)/100),2)+ROUND(((ROUND((ROUND(((AE76-(EU76))*AV76*1),2)*BS76),2)*AU76)/100),2)) -> 0 | DN76: 0 | DO76: 0 | DP76: 1 | DQ76: 1 | DU76: 1013 | DV76: ШТ | DW76: ШТ | DX76: 1 | EE76: 60088211 | EF76: 202 | EG76: Материалы | EH76: 0 | EJ76: 1 | EK76: 400002 | EL76: Материалы, изделия и конструкции | EM76: Материалы | EQ76: 0 | ER76: 3182.34 | ES76: 3182.34 | ET76: 0 | EU76: 0 | EV76: 0 | EW76: 0 | EX76: 0 | EY76: 0 | EZ76: 5 | FC76: 1 | FD76: 18 | FF76: 36990 | FQ76: 0 | FR76: 0 | FS76: 0 | FX76: 0 | FY76: 0 | GA76: [36 990 / 1,2 / 9,88] + 2% Заг.скл | GD76: 1 | GF76: -345521507 | GG76: 2 | GH76: 3 | GI76: 5 | GJ76: 0 | GK76: 0 | GL76: =ROUND(IF(AND(BH76=3,BI76=3,FS76<>0),P76,0),2) -> 0 | GM76: =ROUND(O76+X76+Y76,2)+GX76 -> 62883.04 | GN76: =IF(OR(BI76=0,BI76=1),GM76-GX76,0) -> 62883.04 | GO76: =IF(BI76=2,GM76-GX76,0) -> 0 | GP76: =IF(BI76=4,GM76-GX76,0) -> 0 | GR76: 1 | GS76: 1 | GT76: 0 | GV76: =ROUND((GT76),6) -> 0 | GW76: 1 | GX76: =ROUND(HC76*I76,2) -> 0 | HA76: 0 | HB76: 0 | HC76: =GV76*GW76 -> 0 | HE76: 0 | HF76: 2 | HS76: 0 | IK76: 0
A77: 17 | B77: 1 | E77: 8 | F77: КА-4 | G77: Радиатор стальной трубчатый GUARDO TORRE 3D, 400 мм (BK-VER-WHITE), белый 3D-400-1950 (мощность 1,552 кВт) | H77: ШТ | I77: 20 | J77: 0 | K77: 20 | O77: =ROUND(CP77,2) -> 74280.2 | P77: =ROUND((ROUND((AC77*AW77*I77),2)*BC77),2) -> 74280.2 | Q77: =(ROUND((ROUND(((ET77)*AV77*I77),2)*BB77),2)+ROUND((ROUND(((AE77-(EU77))*AV77*I77),2)*BS77),2)) -> 0 | R77: =(ROUND((ROUND(((EU77)*AV77*I77),2)*BS77),2)+ROUND((ROUND(((AE77-(EU77))*AV77*I77),2)*BS77),2)) -> 0 | S77: =ROUND((ROUND((AF77*AV77*I77),2)*BA77),2) -> 0 | T77: =ROUND(CU77*I77,2) -> 0 | U77: =CV77*I77 -> 0 | V77: =CW77*I77 -> 0 | W77: =ROUND(CX77*I77,2) -> 0 | X77: =(ROUND((((S77+ROUND((ROUND(((EU77)*AV77*I77),2)*BS77),2))*AT77)/100),2)+ROUND(((ROUND((ROUND(((AE77-(EU77))*AV77*I77),2)*BS77),2)*AT77)/100),2)) -> 0 | Y77: =(ROUND((((S77+ROUND((ROUND(((EU77)*AV77*I77),2)*BS77),2))*AU77)/100),2)+ROUND(((ROUND((ROUND(((AE77-(EU77))*AV77*I77),2)*BS77),2)*AU77)/100),2)) -> 0 | AA77: 60255014 | AB77: =ROUND((AC77+AD77+AF77),6) -> 3714.01 | AC77: =ROUND((ES77),6) -> 3714.01 | AD77: =ROUND((((ET77)-(EU77))+AE77),6) -> 0 | AE77: =ROUND((EU77),6) -> 0 | AF77: =ROUND((EV77),6) -> 0 | AG77: =ROUND((AP77),6) -> 0 | AH77: =(EW77) -> 0 | AI77: =(EX77) -> 0 | AJ77: =(AS77) -> 0 | AK77: 3714.01 | AL77: 3714.01 | AM77: 0 | AN77: 0 | AO77: 0 | AP77: 0 | AQ77: 0 | AR77: 0 | AS77: 0 | AT77: 0 | AU77: 0 | AV77: 1 | AW77: 1 | AZ77: 1 | BA77: 1 | BB77: 1 | BC77: 1 | BH77: 3 | BI77: 1 | BM77: 400002 | BN77: 0 | BP77: 0 | BQ77: 202 | BR77: 0 | BS77: 1 | BT77: 1 | BU77: 1 | BV77: 1 | BW77: 1 | BX77: 1 | BZ77: 0 | CA77: 0 | CE77: 1566 | CF77: 0 | CG77: 0 | CM77: 0 | CO77: 0 | CP77: =(P77+Q77+S77) -> 74280.2 | CQ77: =ROUND((ROUND((AC77*AW77*1),2)*BC77),2) -> 3714.01 | CR77: =(ROUND((ROUND(((ET77)*AV77*1),2)*BB77),2)+ROUND((ROUND(((AE77-(EU77))*AV77*1),2)*BS77),2)) -> 0 | CS77: =(ROUND((ROUND(((EU77)*AV77*1),2)*BS77),2)+ROUND((ROUND(((AE77-(EU77))*AV77*1),2)*BS77),2)) -> 0 | CT77: =ROUND((ROUND((AF77*AV77*1),2)*BA77),2) -> 0 | CU77: =AG77 -> 0 | CV77: =(AH77*AV77) -> 0 | CW77: =AI77 -> 0 | CX77: =AJ77 -> 0 | CY77: =(ROUND((((S77+ROUND((ROUND(((EU77)*AV77*1),2)*BS77),2))*AT77)/100),2)+ROUND(((ROUND((ROUND(((AE77-(EU77))*AV77*1),2)*BS77),2)*AT77)/100),2)) -> 0 | CZ77: =(ROUND((((S77+ROUND((ROUND(((EU77)*AV77*1),2)*BS77),2))*AU77)/100),2)+ROUND(((ROUND((ROUND(((AE77-(EU77))*AV77*1),2)*BS77),2)*AU77)/100),2)) -> 0 | DN77: 0 | DO77: 0 | DP77: 1 | DQ77: 1 | DU77: 1013 | DV77: ШТ | DW77: ШТ | DX77: 1 | EE77: 60088211 | EF77: 202 | EG77: Материалы | EH77: 0 | EJ77: 1 | EK77: 400002 | EL77: Материалы, изделия и конструкции | EM77: Материалы | EQ77: 0 | ER77: 0 | ES77: 3714.01 | ET77: 0 | EU77: 0 | EV77: 0 | EW77: 0 | EX77: 0 | EY77: 0 | FQ77: 0 | FR77: 0 | FS77: 0 | FX77: 0 | FY77: 0 | GA77: [43 170 / 1,2 / 9,88] + 2% Заг.скл | GD77: 1 | GF77: 1656172231 | GG77: 2 | GH77: 4 | GI77: -2 | GJ77: 0 | GK77: 0 | GL77: =ROUND(IF(AND(BH77=3,BI77=3,FS77<>0),P77,0),2) -> 0 | GM77: =ROUND(O77+X77+Y77,2)+GX77 -> 74280.2 | GN77: =IF(OR(BI77=0,BI77=1),GM77-GX77,0) -> 74280.2 | GO77: =IF(BI77=2,GM77-GX77,0) -> 0 | GP77: =IF(BI77=4,GM77-GX77,0) -> 0 | GR77: 0 | GS77: 2 | GT77: 0 | GV77: =ROUND((GT77),6) -> 0 | GW77: 1 | GX77: =ROUND(HC77*I77,2) -> 0 | HA77: 0 | HB77: 0 | HC77: =GV77*GW77 -> 0 | HE77: 0 | HF77: 2 | HS77: 0 | IK77: 0
A78: 17 | B78: 1 | E78: 8 | F78: КА-4 | G78: Радиатор стальной трубчатый GUARDO TORRE 3D, 400 мм (BK-VER-WHITE), белый 3D-400-1950 (мощность 1,552 кВт) | H78: ШТ | I78: 20 | J78: 0 | K78: 20 | O78: =ROUND(CP78,2) -> 733888.38 | P78: =ROUND((ROUND((AC78*AW78*I78),2)*BC78),2) -> 733888.38 | Q78: =(ROUND((ROUND(((ET78)*AV78*I78),2)*BB78),2)+ROUND((ROUND(((AE78-(EU78))*AV78*I78),2)*BS78),2)) -> 0 | R78: =(ROUND((ROUND(((EU78)*AV78*I78),2)*BS78),2)+ROUND((ROUND(((AE78-(EU78))*AV78*I78),2)*BS78),2)) -> 0 | S78: =ROUND((ROUND((AF78*AV78*I78),2)*BA78),2) -> 0 | T78: =ROUND(CU78*I78,2) -> 0 | U78: =CV78*I78 -> 0 | V78: =CW78*I78 -> 0 | W78: =ROUND(CX78*I78,2) -> 0 | X78: =(ROUND((((S78+ROUND((ROUND(((EU78)*AV78*I78),2)*BS78),2))*AT78)/100),2)+ROUND(((ROUND((ROUND(((AE78-(EU78))*AV78*I78),2)*BS78),2)*AT78)/100),2)) -> 0 | Y78: =(ROUND((((S78+ROUND((ROUND(((EU78)*AV78*I78),2)*BS78),2))*AU78)/100),2)+ROUND(((ROUND((ROUND(((AE78-(EU78))*AV78*I78),2)*BS78),2)*AU78)/100),2)) -> 0 | AA78: 60255011 | AB78: =ROUND((AC78+AD78+AF78),6) -> 3714.01 | AC78: =ROUND((ES78),6) -> 3714.01 | AD78: =ROUND((((ET78)-(EU78))+AE78),6) -> 0 | AE78: =ROUND((EU78),6) -> 0 | AF78: =ROUND((EV78),6) -> 0 | AG78: =ROUND((AP78),6) -> 0 | AH78: =(EW78) -> 0 | AI78: =(EX78) -> 0 | AJ78: =(AS78) -> 0 | AK78: 3714.01 | AL78: 3714.01 | AM78: 0 | AN78: 0 | AO78: 0 | AP78: 0 | AQ78: 0 | AR78: 0 | AS78: 0 | AT78: 0 | AU78: 0 | AV78: 1 | AW78: 1 | AZ78: 1 | BA78: 1 | BB78: 1 | BC78: 9.88 | BH78: 3 | BI78: 1 | BM78: 400002 | BN78: 0 | BP78: 0 | BQ78: 202 | BR78: 0 | BS78: 1 | BT78: 1 | BU78: 1 | BV78: 1 | BW78: 1 | BX78: 1 | BZ78: 0 | CA78: 0 | CE78: 1566 | CF78: 0 | CG78: 0 | CM78: 0 | CO78: 0 | CP78: =(P78+Q78+S78) -> 733888.38 | CQ78: =ROUND((ROUND((AC78*AW78*1),2)*BC78),2) -> 36694.42 | CR78: =(ROUND((ROUND(((ET78)*AV78*1),2)*BB78),2)+ROUND((ROUND(((AE78-(EU78))*AV78*1),2)*BS78),2)) -> 0 | CS78: =(ROUND((ROUND(((EU78)*AV78*1),2)*BS78),2)+ROUND((ROUND(((AE78-(EU78))*AV78*1),2)*BS78),2)) -> 0 | CT78: =ROUND((ROUND((AF78*AV78*1),2)*BA78),2) -> 0 | CU78: =AG78 -> 0 | CV78: =(AH78*AV78) -> 0 | CW78: =AI78 -> 0 | CX78: =AJ78 -> 0 | CY78: =(ROUND((((S78+ROUND((ROUND(((EU78)*AV78*1),2)*BS78),2))*AT78)/100),2)+ROUND(((ROUND((ROUND(((AE78-(EU78))*AV78*1),2)*BS78),2)*AT78)/100),2)) -> 0 | CZ78: =(ROUND((((S78+ROUND((ROUND(((EU78)*AV78*1),2)*BS78),2))*AU78)/100),2)+ROUND(((ROUND((ROUND(((AE78-(EU78))*AV78*1),2)*BS78),2)*AU78)/100),2)) -> 0 | DN78: 0 | DO78: 0 | DP78: 1 | DQ78: 1 | DU78: 1013 | DV78: ШТ | DW78: ШТ | DX78: 1 | EE78: 60088211 | EF78: 202 | EG78: Материалы | EH78: 0 | EJ78: 1 | EK78: 400002 | EL78: Материалы, изделия и конструкции | EM78: Материалы | EQ78: 0 | ER78: 3714.01 | ES78: 3714.01 | ET78: 0 | EU78: 0 | EV78: 0 | EW78: 0 | EX78: 0 | EY78: 0 | EZ78: 5 | FC78: 1 | FD78: 18 | FF78: 43170 | FQ78: 0 | FR78: 0 | FS78: 0 | FX78: 0 | FY78: 0 | GA78: [43 170 / 1,2 / 9,88] + 2% Заг.скл | GD78: 1 | GF78: 1656172231 | GG78: 2 | GH78: 3 | GI78: 5 | GJ78: 0 | GK78: 0 | GL78: =ROUND(IF(AND(BH78=3,BI78=3,FS78<>0),P78,0),2) -> 0 | GM78: =ROUND(O78+X78+Y78,2)+GX78 -> 733888.38 | GN78: =IF(OR(BI78=0,BI78=1),GM78-GX78,0) -> 733888.38 | GO78: =IF(BI78=2,GM78-GX78,0) -> 0 | GP78: =IF(BI78=4,GM78-GX78,0) -> 0 | GR78: 1 | GS78: 1 | GT78: 0 | GV78: =ROUND((GT78),6) -> 0 | GW78: 1 | GX78: =ROUND(HC78*I78,2) -> 0 | HA78: 0 | HB78: 0 | HC78: =GV78*GW78 -> 0 | HE78: 0 | HF78: 2 | HS78: 0 | IK78: 0
A79: 17 | B79: 1 | E79: 9 | F79: КА-5 | G79: Радиатор стальной трубчатый GUARDO TORRE 3D, 400 мм (BK-VER-WHITE), белый 3D-400-350 (мощность 0,336 к Вт) | H79: ШТ | I79: 1 | J79: 0 | K79: 1 | O79: =ROUND(CP79,2) -> 988.51 | P79: =ROUND((ROUND((AC79*AW79*I79),2)*BC79),2) -> 988.51 | Q79: =(ROUND((ROUND(((ET79)*AV79*I79),2)*BB79),2)+ROUND((ROUND(((AE79-(EU79))*AV79*I79),2)*BS79),2)) -> 0 | R79: =(ROUND((ROUND(((EU79)*AV79*I79),2)*BS79),2)+ROUND((ROUND(((AE79-(EU79))*AV79*I79),2)*BS79),2)) -> 0 | S79: =ROUND((ROUND((AF79*AV79*I79),2)*BA79),2) -> 0 | T79: =ROUND(CU79*I79,2) -> 0 | U79: =CV79*I79 -> 0 | V79: =CW79*I79 -> 0 | W79: =ROUND(CX79*I79,2) -> 0 | X79: =(ROUND((((S79+ROUND((ROUND(((EU79)*AV79*I79),2)*BS79),2))*AT79)/100),2)+ROUND(((ROUND((ROUND(((AE79-(EU79))*AV79*I79),2)*BS79),2)*AT79)/100),2)) -> 0 | Y79: =(ROUND((((S79+ROUND((ROUND(((EU79)*AV79*I79),2)*BS79),2))*AU79)/100),2)+ROUND(((ROUND((ROUND(((AE79-(EU79))*AV79*I79),2)*BS79),2)*AU79)/100),2)) -> 0 | AA79: 60255014 | AB79: =ROUND((AC79+AD79+AF79),6) -> 988.51 | AC79: =ROUND((ES79),6) -> 988.51 | AD79: =ROUND((((ET79)-(EU79))+AE79),6) -> 0 | AE79: =ROUND((EU79),6) -> 0 | AF79: =ROUND((EV79),6) -> 0 | AG79: =ROUND((AP79),6) -> 0 | AH79: =(EW79) -> 0 | AI79: =(EX79) -> 0 | AJ79: =(AS79) -> 0 | AK79: 988.51 | AL79: 988.51 | AM79: 0 | AN79: 0 | AO79: 0 | AP79: 0 | AQ79: 0 | AR79: 0 | AS79: 0 | AT79: 0 | AU79: 0 | AV79: 1 | AW79: 1 | AZ79: 1 | BA79: 1 | BB79: 1 | BC79: 1 | BH79: 3 | BI79: 1 | BM79: 400002 | BN79: 0 | BP79: 0 | BQ79: 202 | BR79: 0 | BS79: 1 | BT79: 1 | BU79: 1 | BV79: 1 | BW79: 1 | BX79: 1 | BZ79: 0 | CA79: 0 | CE79: 1566 | CF79: 0 | CG79: 0 | CM79: 0 | CO79: 0 | CP79: =(P79+Q79+S79) -> 988.51 | CQ79: =ROUND((ROUND((AC79*AW79*1),2)*BC79),2) -> 988.51 | CR79: =(ROUND((ROUND(((ET79)*AV79*1),2)*BB79),2)+ROUND((ROUND(((AE79-(EU79))*AV79*1),2)*BS79),2)) -> 0 | CS79: =(ROUND((ROUND(((EU79)*AV79*1),2)*BS79),2)+ROUND((ROUND(((AE79-(EU79))*AV79*1),2)*BS79),2)) -> 0 | CT79: =ROUND((ROUND((AF79*AV79*1),2)*BA79),2) -> 0 | CU79: =AG79 -> 0 | CV79: =(AH79*AV79) -> 0 | CW79: =AI79 -> 0 | CX79: =AJ79 -> 0 | CY79: =(ROUND((((S79+ROUND((ROUND(((EU79)*AV79*1),2)*BS79),2))*AT79)/100),2)+ROUND(((ROUND((ROUND(((AE79-(EU79))*AV79*1),2)*BS79),2)*AT79)/100),2)) -> 0 | CZ79: =(ROUND((((S79+ROUND((ROUND(((EU79)*AV79*1),2)*BS79),2))*AU79)/100),2)+ROUND(((ROUND((ROUND(((AE79-(EU79))*AV79*1),2)*BS79),2)*AU79)/100),2)) -> 0 | DN79: 0 | DO79: 0 | DP79: 1 | DQ79: 1 | DU79: 1013 | DV79: ШТ | DW79: ШТ | DX79: 1 | EE79: 60088211 | EF79: 202 | EG79: Материалы | EH79: 0 | EJ79: 1 | EK79: 400002 | EL79: Материалы, изделия и конструкции | EM79: Материалы | EQ79: 0 | ER79: 0 | ES79: 988.51 | ET79: 0 | EU79: 0 | EV79: 0 | EW79: 0 | EX79: 0 | EY79: 0 | FQ79: 0 | FR79: 0 | FS79: 0 | FX79: 0 | FY79: 0 | GA79: [11 490 / 1,2 / 9,88] + 2% Заг.скл | GD79: 1 | GF79: 1287037358 | GG79: 2 | GH79: 4 | GI79: -2 | GJ79: 0 | GK79: 0 | GL79: =ROUND(IF(AND(BH79=3,BI79=3,FS79<>0),P79,0),2) -> 0 | GM79: =ROUND(O79+X79+Y79,2)+GX79 -> 988.51 | GN79: =IF(OR(BI79=0,BI79=1),GM79-GX79,0) -> 988.51 | GO79: =IF(BI79=2,GM79-GX79,0) -> 0 | GP79: =IF(BI79=4,GM79-GX79,0) -> 0 | GR79: 0 | GS79: 2 | GT79: 0 | GV79: =ROUND((GT79),6) -> 0 | GW79: 1 | GX79: =ROUND(HC79*I79,2) -> 0 | HA79: 0 | HB79: 0 | HC79: =GV79*GW79 -> 0 | HE79: 0 | HF79: 2 | HS79: 0 | IK79: 0
A80: 17 | B80: 1 | E80: 9 | F80: КА-5 | G80: Радиатор стальной трубчатый GUARDO TORRE 3D, 400 мм (BK-VER-WHITE), белый 3D-400-350 (мощность 0,336 к Вт) | H80: ШТ | I80: 1 | J80: 0 | K80: 1 | O80: =ROUND(CP80,2) -> 9766.48 | P80: =ROUND((ROUND((AC80*AW80*I80),2)*BC80),2) -> 9766.48 | Q80: =(ROUND((ROUND(((ET80)*AV80*I80),2)*BB80),2)+ROUND((ROUND(((AE80-(EU80))*AV80*I80),2)*BS80),2)) -> 0 | R80: =(ROUND((ROUND(((EU80)*AV80*I80),2)*BS80),2)+ROUND((ROUND(((AE80-(EU80))*AV80*I80),2)*BS80),2)) -> 0 | S80: =ROUND((ROUND((AF80*AV80*I80),2)*BA80),2) -> 0 | T80: =ROUND(CU80*I80,2) -> 0 | U80: =CV80*I80 -> 0 | V80: =CW80*I80 -> 0 | W80: =ROUND(CX80*I80,2) -> 0 | X80: =(ROUND((((S80+ROUND((ROUND(((EU80)*AV80*I80),2)*BS80),2))*AT80)/100),2)+ROUND(((ROUND((ROUND(((AE80-(EU80))*AV80*I80),2)*BS80),2)*AT80)/100),2)) -> 0 | Y80: =(ROUND((((S80+ROUND((ROUND(((EU80)*AV80*I80),2)*BS80),2))*AU80)/100),2)+ROUND(((ROUND((ROUND(((AE80-(EU80))*AV80*I80),2)*BS80),2)*AU80)/100),2)) -> 0 | AA80: 60255011 | AB80: =ROUND((AC80+AD80+AF80),6) -> 988.51 | AC80: =ROUND((ES80),6) -> 988.51 | AD80: =ROUND((((ET80)-(EU80))+AE80),6) -> 0 | AE80: =ROUND((EU80),6) -> 0 | AF80: =ROUND((EV80),6) -> 0 | AG80: =ROUND((AP80),6) -> 0 | AH80: =(EW80) -> 0 | AI80: =(EX80) -> 0 | AJ80: =(AS80) -> 0 | AK80: 988.51 | AL80: 988.51 | AM80: 0 | AN80: 0 | AO80: 0 | AP80: 0 | AQ80: 0 | AR80: 0 | AS80: 0 | AT80: 0 | AU80: 0 | AV80: 1 | AW80: 1 | AZ80: 1 | BA80: 1 | BB80: 1 | BC80: 9.88 | BH80: 3 | BI80: 1 | BM80: 400002 | BN80: 0 | BP80: 0 | BQ80: 202 | BR80: 0 | BS80: 1 | BT80: 1 | BU80: 1 | BV80: 1 | BW80: 1 | BX80: 1 | BZ80: 0 | CA80: 0 | CE80: 1566 | CF80: 0 | CG80: 0 | CM80: 0 | CO80: 0 | CP80: =(P80+Q80+S80) -> 9766.48 | CQ80: =ROUND((ROUND((AC80*AW80*1),2)*BC80),2) -> 9766.48 | CR80: =(ROUND((ROUND(((ET80)*AV80*1),2)*BB80),2)+ROUND((ROUND(((AE80-(EU80))*AV80*1),2)*BS80),2)) -> 0 | CS80: =(ROUND((ROUND(((EU80)*AV80*1),2)*BS80),2)+ROUND((ROUND(((AE80-(EU80))*AV80*1),2)*BS80),2)) -> 0 | CT80: =ROUND((ROUND((AF80*AV80*1),2)*BA80),2) -> 0 | CU80: =AG80 -> 0 | CV80: =(AH80*AV80) -> 0 | CW80: =AI80 -> 0 | CX80: =AJ80 -> 0 | CY80: =(ROUND((((S80+ROUND((ROUND(((EU80)*AV80*1),2)*BS80),2))*AT80)/100),2)+ROUND(((ROUND((ROUND(((AE80-(EU80))*AV80*1),2)*BS80),2)*AT80)/100),2)) -> 0 | CZ80: =(ROUND((((S80+ROUND((ROUND(((EU80)*AV80*1),2)*BS80),2))*AU80)/100),2)+ROUND(((ROUND((ROUND(((AE80-(EU80))*AV80*1),2)*BS80),2)*AU80)/100),2)) -> 0 | DN80: 0 | DO80: 0 | DP80: 1 | DQ80: 1 | DU80: 1013 | DV80: ШТ | DW80: ШТ | DX80: 1 | EE80: 60088211 | EF80: 202 | EG80: Материалы | EH80: 0 | EJ80: 1 | EK80: 400002 | EL80: Материалы, изделия и конструкции | EM80: Материалы | EQ80: 0 | ER80: 988.51 | ES80: 988.51 | ET80: 0 | EU80: 0 | EV80: 0 | EW80: 0 | EX80: 0 | EY80: 0 | EZ80: 5 | FC80: 1 | FD80: 18 | FF80: 11490 | FQ80: 0 | FR80: 0 | FS80: 0 | FX80: 0 | FY80: 0 | GA80: [11 490 / 1,2 / 9,88] + 2% Заг.скл | GD80: 1 | GF80: 1287037358 | GG80: 2 | GH80: 3 | GI80: 5 | GJ80: 0 | GK80: 0 | GL80: =ROUND(IF(AND(BH80=3,BI80=3,FS80<>0),P80,0),2) -> 0 | GM80: =ROUND(O80+X80+Y80,2)+GX80 -> 9766.48 | GN80: =IF(OR(BI80=0,BI80=1),GM80-GX80,0) -> 9766.48 | GO80: =IF(BI80=2,GM80-GX80,0) -> 0 | GP80: =IF(BI80=4,GM80-GX80,0) -> 0 | GR80: 1 | GS80: 1 | GT80: 0 | GV80: =ROUND((GT80),6) -> 0 | GW80: 1 | GX80: =ROUND(HC80*I80,2) -> 0 | HA80: 0 | HB80: 0 | HC80: =GV80*GW80 -> 0 | HE80: 0 | HF80: 2 | HS80: 0 | IK80: 0
A81: 17 | B81: 1 | E81: 10 | F81: КА-6 | G81: Радиатор стальной трубчатый GUARDO TORRE 3D, 400 мм (BK-VER-WHITE), белый 3D-400-750 (мощность 0,663 кВт) | H81: ШТ | I81: 9 | J81: 0 | K81: 9 | O81: =ROUND(CP81,2) -> 14819.94 | P81: =ROUND((ROUND((AC81*AW81*I81),2)*BC81),2) -> 14819.94 | Q81: =(ROUND((ROUND(((ET81)*AV81*I81),2)*BB81),2)+ROUND((ROUND(((AE81-(EU81))*AV81*I81),2)*BS81),2)) -> 0 | R81: =(ROUND((ROUND(((EU81)*AV81*I81),2)*BS81),2)+ROUND((ROUND(((AE81-(EU81))*AV81*I81),2)*BS81),2)) -> 0 | S81: =ROUND((ROUND((AF81*AV81*I81),2)*BA81),2) -> 0 | T81: =ROUND(CU81*I81,2) -> 0 | U81: =CV81*I81 -> 0 | V81: =CW81*I81 -> 0 | W81: =ROUND(CX81*I81,2) -> 0 | X81: =(ROUND((((S81+ROUND((ROUND(((EU81)*AV81*I81),2)*BS81),2))*AT81)/100),2)+ROUND(((ROUND((ROUND(((AE81-(EU81))*AV81*I81),2)*BS81),2)*AT81)/100),2)) -> 0 | Y81: =(ROUND((((S81+ROUND((ROUND(((EU81)*AV81*I81),2)*BS81),2))*AU81)/100),2)+ROUND(((ROUND((ROUND(((AE81-(EU81))*AV81*I81),2)*BS81),2)*AU81)/100),2)) -> 0 | AA81: 60255014 | AB81: =ROUND((AC81+AD81+AF81),6) -> 1646.66 | AC81: =ROUND((ES81),6) -> 1646.66 | AD81: =ROUND((((ET81)-(EU81))+AE81),6) -> 0 | AE81: =ROUND((EU81),6) -> 0 | AF81: =ROUND((EV81),6) -> 0 | AG81: =ROUND((AP81),6) -> 0 | AH81: =(EW81) -> 0 | AI81: =(EX81) -> 0 | AJ81: =(AS81) -> 0 | AK81: 1646.66 | AL81: 1646.66 | AM81: 0 | AN81: 0 | AO81: 0 | AP81: 0 | AQ81: 0 | AR81: 0 | AS81: 0 | AT81: 0 | AU81: 0 | AV81: 1 | AW81: 1 | AZ81: 1 | BA81: 1 | BB81: 1 | BC81: 1 | BH81: 3 | BI81: 1 | BM81: 400002 | BN81: 0 | BP81: 0 | BQ81: 202 | BR81: 0 | BS81: 1 | BT81: 1 | BU81: 1 | BV81: 1 | BW81: 1 | BX81: 1 | BZ81: 0 | CA81: 0 | CE81: 1566 | CF81: 0 | CG81: 0 | CM81: 0 | CO81: 0 | CP81: =(P81+Q81+S81) -> 14819.94 | CQ81: =ROUND((ROUND((AC81*AW81*1),2)*BC81),2) -> 1646.66 | CR81: =(ROUND((ROUND(((ET81)*AV81*1),2)*BB81),2)+ROUND((ROUND(((AE81-(EU81))*AV81*1),2)*BS81),2)) -> 0 | CS81: =(ROUND((ROUND(((EU81)*AV81*1),2)*BS81),2)+ROUND((ROUND(((AE81-(EU81))*AV81*1),2)*BS81),2)) -> 0 | CT81: =ROUND((ROUND((AF81*AV81*1),2)*BA81),2) -> 0 | CU81: =AG81 -> 0 | CV81: =(AH81*AV81) -> 0 | CW81: =AI81 -> 0 | CX81: =AJ81 -> 0 | CY81: =(ROUND((((S81+ROUND((ROUND(((EU81)*AV81*1),2)*BS81),2))*AT81)/100),2)+ROUND(((ROUND((ROUND(((AE81-(EU81))*AV81*1),2)*BS81),2)*AT81)/100),2)) -> 0 | CZ81: =(ROUND((((S81+ROUND((ROUND(((EU81)*AV81*1),2)*BS81),2))*AU81)/100),2)+ROUND(((ROUND((ROUND(((AE81-(EU81))*AV81*1),2)*BS81),2)*AU81)/100),2)) -> 0 | DN81: 0 | DO81: 0 | DP81: 1 | DQ81: 1 | DU81: 1013 | DV81: ШТ | DW81: ШТ | DX81: 1 | EE81: 60088211 | EF81: 202 | EG81: Материалы | EH81: 0 | EJ81: 1 | EK81: 400002 | EL81: Материалы, изделия и конструкции | EM81: Материалы | EQ81: 0 | ER81: 0 | ES81: 1646.66 | ET81: 0 | EU81: 0 | EV81: 0 | EW81: 0 | EX81: 0 | EY81: 0 | FQ81: 0 | FR81: 0 | FS81: 0 | FX81: 0 | FY81: 0 | GA81: [19 140 / 1,2 / 9,88] + 2% Заг.скл | GD81: 1 | GF81: -1847788681 | GG81: 2 | GH81: 4 | GI81: -2 | GJ81: 0 | GK81: 0 | GL81: =ROUND(IF(AND(BH81=3,BI81=3,FS81<>0),P81,0),2) -> 0 | GM81: =ROUND(O81+X81+Y81,2)+GX81 -> 14819.94 | GN81: =IF(OR(BI81=0,BI81=1),GM81-GX81,0) -> 14819.94 | GO81: =IF(BI81=2,GM81-GX81,0) -> 0 | GP81: =IF(BI81=4,GM81-GX81,0) -> 0 | GR81: 0 | GS81: 2 | GT81: 0 | GV81: =ROUND((GT81),6) -> 0 | GW81: 1 | GX81: =ROUND(HC81*I81,2) -> 0 | HA81: 0 | HB81: 0 | HC81: =GV81*GW81 -> 0 | HE81: 0 | HF81: 2 | HS81: 0 | IK81: 0
A82: 17 | B82: 1 | E82: 10 | F82: КА-6 | G82: Радиатор стальной трубчатый GUARDO TORRE 3D, 400 мм (BK-VER-WHITE), белый 3D-400-750 (мощность 0,663 кВт) | H82: ШТ | I82: 9 | J82: 0 | K82: 9 | O82: =ROUND(CP82,2) -> 146421.01 | P82: =ROUND((ROUND((AC82*AW82*I82),2)*BC82),2) -> 146421.01 | Q82: =(ROUND((ROUND(((ET82)*AV82*I82),2)*BB82),2)+ROUND((ROUND(((AE82-(EU82))*AV82*I82),2)*BS82),2)) -> 0 | R82: =(ROUND((ROUND(((EU82)*AV82*I82),2)*BS82),2)+ROUND((ROUND(((AE82-(EU82))*AV82*I82),2)*BS82),2)) -> 0 | S82: =ROUND((ROUND((AF82*AV82*I82),2)*BA82),2) -> 0 | T82: =ROUND(CU82*I82,2) -> 0 | U82: =CV82*I82 -> 0 | V82: =CW82*I82 -> 0 | W82: =ROUND(CX82*I82,2) -> 0 | X82: =(ROUND((((S82+ROUND((ROUND(((EU82)*AV82*I82),2)*BS82),2))*AT82)/100),2)+ROUND(((ROUND((ROUND(((AE82-(EU82))*AV82*I82),2)*BS82),2)*AT82)/100),2)) -> 0 | Y82: =(ROUND((((S82+ROUND((ROUND(((EU82)*AV82*I82),2)*BS82),2))*AU82)/100),2)+ROUND(((ROUND((ROUND(((AE82-(EU82))*AV82*I82),2)*BS82),2)*AU82)/100),2)) -> 0 | AA82: 60255011 | AB82: =ROUND((AC82+AD82+AF82),6) -> 1646.66 | AC82: =ROUND((ES82),6) -> 1646.66 | AD82: =ROUND((((ET82)-(EU82))+AE82),6) -> 0 | AE82: =ROUND((EU82),6) -> 0 | AF82: =ROUND((EV82),6) -> 0 | AG82: =ROUND((AP82),6) -> 0 | AH82: =(EW82) -> 0 | AI82: =(EX82) -> 0 | AJ82: =(AS82) -> 0 | AK82: 1646.66 | AL82: 1646.66 | AM82: 0 | AN82: 0 | AO82: 0 | AP82: 0 | AQ82: 0 | AR82: 0 | AS82: 0 | AT82: 0 | AU82: 0 | AV82: 1 | AW82: 1 | AZ82: 1 | BA82: 1 | BB82: 1 | BC82: 9.88 | BH82: 3 | BI82: 1 | BM82: 400002 | BN82: 0 | BP82: 0 | BQ82: 202 | BR82: 0 | BS82: 1 | BT82: 1 | BU82: 1 | BV82: 1 | BW82: 1 | BX82: 1 | BZ82: 0 | CA82: 0 | CE82: 1566 | CF82: 0 | CG82: 0 | CM82: 0 | CO82: 0 | CP82: =(P82+Q82+S82) -> 146421.01 | CQ82: =ROUND((ROUND((AC82*AW82*1),2)*BC82),2) -> 16269 | CR82: =(ROUND((ROUND(((ET82)*AV82*1),2)*BB82),2)+ROUND((ROUND(((AE82-(EU82))*AV82*1),2)*BS82),2)) -> 0 | CS82: =(ROUND((ROUND(((EU82)*AV82*1),2)*BS82),2)+ROUND((ROUND(((AE82-(EU82))*AV82*1),2)*BS82),2)) -> 0 | CT82: =ROUND((ROUND((AF82*AV82*1),2)*BA82),2) -> 0 | CU82: =AG82 -> 0 | CV82: =(AH82*AV82) -> 0 | CW82: =AI82 -> 0 | CX82: =AJ82 -> 0 | CY82: =(ROUND((((S82+ROUND((ROUND(((EU82)*AV82*1),2)*BS82),2))*AT82)/100),2)+ROUND(((ROUND((ROUND(((AE82-(EU82))*AV82*1),2)*BS82),2)*AT82)/100),2)) -> 0 | CZ82: =(ROUND((((S82+ROUND((ROUND(((EU82)*AV82*1),2)*BS82),2))*AU82)/100),2)+ROUND(((ROUND((ROUND(((AE82-(EU82))*AV82*1),2)*BS82),2)*AU82)/100),2)) -> 0 | DN82: 0 | DO82: 0 | DP82: 1 | DQ82: 1 | DU82: 1013 | DV82: ШТ | DW82: ШТ | DX82: 1 | EE82: 60088211 | EF82: 202 | EG82: Материалы | EH82: 0 | EJ82: 1 | EK82: 400002 | EL82: Материалы, изделия и конструкции | EM82: Материалы | EQ82: 0 | ER82: 1646.66 | ES82: 1646.66 | ET82: 0 | EU82: 0 | EV82: 0 | EW82: 0 | EX82: 0 | EY82: 0 | EZ82: 5 | FC82: 1 | FD82: 18 | FF82: 19140 | FQ82: 0 | FR82: 0 | FS82: 0 | FX82: 0 | FY82: 0 | GA82: [19 140 / 1,2 / 9,88] + 2% Заг.скл | GD82: 1 | GF82: -1847788681 | GG82: 2 | GH82: 3 | GI82: 5 | GJ82: 0 | GK82: 0 | GL82: =ROUND(IF(AND(BH82=3,BI82=3,FS82<>0),P82,0),2) -> 0 | GM82: =ROUND(O82+X82+Y82,2)+GX82 -> 146421.01 | GN82: =IF(OR(BI82=0,BI82=1),GM82-GX82,0) -> 146421.01 | GO82: =IF(BI82=2,GM82-GX82,0) -> 0 | GP82: =IF(BI82=4,GM82-GX82,0) -> 0 | GR82: 1 | GS82: 1 | GT82: 0 | GV82: =ROUND((GT82),6) -> 0 | GW82: 1 | GX82: =ROUND(HC82*I82,2) -> 0 | HA82: 0 | HB82: 0 | HC82: =GV82*GW82 -> 0 | HE82: 0 | HF82: 2 | HS82: 0 | IK82: 0
A83: 17 | B83: 1 | C83: =ROW(SmtRes!A38) -> 38 | D83: =ROW(EtalonRes!A43) -> 43 | E83: 11 | F83: 3.18-25-1 | G83: Установка радиаторов стальных панельных однорядных с креплением к стене длиной до 1600 мм | H83: 100 шт. | I83: =ROUND((1+2+1+1+3+2)/100,9) -> 0.1 | J83: 0 | K83: =ROUND((1+2+1+1+3+2)/100,9) -> 0.1 | O83: =ROUND(CP83,2) -> 345.6 | P83: =ROUND((ROUND((AC83*AW83*I83),2)*BC83),2) -> 207.89 | Q83: =(ROUND((ROUND(((((ET83*1.25)*1.1))*AV83*I83),2)*BB83),2)+ROUND((ROUND(((AE83-(((EU83*1.25)*1.1)))*AV83*I83),2)*BS83),2)) -> 13.99 | R83: =(ROUND((ROUND(((((EU83*1.25)*1.1))*AV83*I83),2)*BS83),2)+ROUND((ROUND(((AE83-(((EU83*1.25)*1.1)))*AV83*I83),2)*BS83),2)) -> 1.51 | S83: =ROUND((ROUND((AF83*AV83*I83),2)*BA83),2) -> 123.72 | T83: =ROUND(CU83*I83,2) -> 0 | U83: =CV83*I83 -> 10.08267 | V83: =CW83*I83 -> 0 | W83: =ROUND(CX83*I83,2) -> 0 | X83: =(ROUND((((S83+ROUND((ROUND(((((EU83*1.25)*1.1))*AV83*I83),2)*BS83),2))*AT83)/100),2)+ROUND(((ROUND((ROUND(((AE83-(((EU83*1.25)*1.1)))*AV83*I83),2)*BS83),2)*AT83)/100),2)) -> 136.5 | Y83: =(ROUND((((S83+ROUND((ROUND(((((EU83*1.25)*1.1))*AV83*I83),2)*BS83),2))*AU83)/100),2)+ROUND(((ROUND((ROUND(((AE83-(((EU83*1.25)*1.1)))*AV83*I83),2)*BS83),2)*AU83)/100),2)) -> 76.39 | AA83: 60255014 | AB83: =ROUND((AC83+AD83+AF83),6) -> 3369.5053 | AC83: =ROUND((ES83),6) -> 2078.9 | AD83: =ROUND((((((ET83*1.25)*1.1))-(((EU83*1.25)*1.1)))+AE83),6) -> 131.10625 | AE83: =ROUND((((EU83*1.25)*1.1)),6) -> 14.1625 | AF83: =ROUND((((EV83*1.15)*1.1)),6) -> 1159.499 | AG83: =ROUND((AP83),6) -> 0 | AH83: =(((EW83*1.15)*1.1)) -> 94.4955 | AI83: =(((EX83*1.25)*1.1)) -> 0 | AJ83: =(AS83) -> 0 | AK83: 3090.85 | AL83: 2078.9 | AM83: 95.35 | AN83: 10.3 | AO83: 916.6 | AP83: 0 | AQ83: 74.7 | AR83: 0 | AS83: 0 | AT83: 109 | AU83: 61 | AV83: 1.067 | AW83: 1 | AZ83: 1 | BA83: 1 | BB83: 1 | BC83: 1 | BH83: 0 | BI83: 1 | BJ83: ТСН-2001.3 Доп. 80, Сб. 18, т. 25, поз. 1 | BM83: 23 | BN83: 0 | BO83: 3.18-25-1 | BP83: 1 | BQ83: 30 | BR83: 0 | BS83: 1 | BT83: 1 | BU83: 1 | BV83: 1 | BW83: 1 | BX83: 1 | BZ83: 109 | CA83: 61 | CE83: 1566 | CF83: 0 | CG83: 0 | CM83: 0 | CN83: Поправка: О.П. п.3.4. 6 Наименование: Выполняемые при ремонте и реконструкции работы аналогичные технологическим процессам, характерным для нового строительства и отсутствующим в сборниках на ремонтно-строительные работы Поправка: О.П. п.3.4.30.в Наименование: При применении территориальных сметных нормативов для города Москвы затраты, учитывающие напряженные и стесненные условия производства работ (стесненность, сложность складирования и транспортной логистики и т.п.), исчисляются с применением коэффициентов к затратам труда и заработной плате рабочих, машинистов, времени эксплуатации машин и механизмов, стоимости эксплуатации машин в размере: для объектов, расположенных за пределами Третьего транспортного кольца города Москвы, но в пределах Московской кольцевой автомобильной дороги | CO83: 0 | CP83: =(P83+Q83+S83) -> 345.6 | CQ83: =ROUND((ROUND((AC83*AW83*1),2)*BC83),2) -> 2078.9 | CR83: =(ROUND((ROUND(((((ET83*1.25)*1.1))*AV83*1),2)*BB83),2)+ROUND((ROUND(((AE83-(((EU83*1.25)*1.1)))*AV83*1),2)*BS83),2)) -> 139.89 | CS83: =(ROUND((ROUND(((((EU83*1.25)*1.1))*AV83*1),2)*BS83),2)+ROUND((ROUND(((AE83-(((EU83*1.25)*1.1)))*AV83*1),2)*BS83),2)) -> 15.11 | CT83: =ROUND((ROUND((AF83*AV83*1),2)*BA83),2) -> 1237.19 | CU83: =AG83 -> 0 | CV83: =(AH83*AV83) -> 100.8267 | CW83: =AI83 -> 0 | CX83: =AJ83 -> 0 | CY83: =(ROUND((((S83+ROUND((ROUND(((((EU83*1.25)*1.1))*AV83*1),2)*BS83),2))*AT83)/100),2)+ROUND(((ROUND((ROUND(((AE83-(((EU83*1.25)*1.1)))*AV83*1),2)*BS83),2)*AT83)/100),2)) -> 151.32 | CZ83: =(ROUND((((S83+ROUND((ROUND(((((EU83*1.25)*1.1))*AV83*1),2)*BS83),2))*AU83)/100),2)+ROUND(((ROUND((ROUND(((AE83-(((EU83*1.25)*1.1)))*AV83*1),2)*BS83),2)*AU83)/100),2)) -> 84.69 | DB83: 5 | DE83: *1,25)*1,1 | DF83: *1,25)*1,1 | DG83: *1,15)*1,1 | DI83: *1,15)*1,1 | DJ83: *1,25)*1,1 | DN83: 0 | DO83: 0 | DP83: 1 | DQ83: 1 | DU83: 1010 | DV83: 100 шт. | DW83: 100 шт. | DX83: 100 | EE83: 60088254 | EF83: 30 | EG83: Строительные работы | EH83: 0 | EJ83: 1 | EK83: 23 | EL83: ТСН-2001.3-18. Отопление - внутренние устройства | EM83: ТСН-2001.3-18-1 | EO83: Поправка: О.П. п.3.4. 6 Поправка: О.П. п.3.4.30.в | EQ83: 0 | ER83: 3090.85 | ES83: 2078.9 | ET83: 95.35 | EU83: 10.3 | EV83: 916.6 | EW83: 74.7 | EX83: 0 | EY83: 0 | FQ83: 0 | FR83: 0 | FS83: 0 | FX83: 109 | FY83: 61 | GD83: 1 | GF83: -961949121 | GG83: 2 | GH83: 1 | GI83: 2 | GJ83: 0 | GK83: 0 | GL83: =ROUND(IF(AND(BH83=3,BI83=3,FS83<>0),P83,0),2) -> 0 | GM83: =ROUND(O83+X83+Y83,2)+GX83 -> 558.49 | GN83: =IF(OR(BI83=0,BI83=1),GM83-GX83,0) -> 558.49 | GO83: =IF(BI83=2,GM83-GX83,0) -> 0 | GP83: =IF(BI83=4,GM83-GX83,0) -> 0 | GR83: 0 | GS83: 3 | GT83: 0 | GV83: =ROUND((GT83),6) -> 0 | GW83: 1 | GX83: =ROUND(HC83*I83,2) -> 0 | HA83: 0 | HB83: 0 | HC83: =GV83*GW83 -> 0 | HS83: 0 | IK83: 0
A84: 17 | B84: 1 | C84: =ROW(SmtRes!A48) -> 48 | D84: =ROW(EtalonRes!A54) -> 54 | E84: 11 | F84: 3.18-25-1 | G84: Установка радиаторов стальных панельных однорядных с креплением к стене длиной до 1600 мм | H84: 100 шт. | I84: =ROUND((1+2+1+1+3+2)/100,9) -> 0.1 | J84: 0 | K84: =ROUND((1+2+1+1+3+2)/100,9) -> 0.1 | O84: =ROUND(CP84,2) -> 11284.3 | P84: =ROUND((ROUND((AC84*AW84*I84),2)*BC84),2) -> 4280.46 | Q84: =(ROUND((ROUND(((((ET84*1.25)*1.1))*AV84*I84),2)*BB84),2)+ROUND((ROUND(((AE84-(((EU84*1.25)*1.1)))*AV84*I84),2)*BS84),2)) -> 200.48 | R84: =(ROUND((ROUND(((((EU84*1.25)*1.1))*AV84*I84),2)*BS84),2)+ROUND((ROUND(((AE84-(((EU84*1.25)*1.1)))*AV84*I84),2)*BS84),2)) -> 83.03 | S84: =ROUND((ROUND((AF84*AV84*I84),2)*BA84),2) -> 6803.36 | T84: =ROUND(CU84*I84,2) -> 0 | U84: =CV84*I84 -> 10.08267 | V84: =CW84*I84 -> 0 | W84: =ROUND(CX84*I84,2) -> 0 | X84: =(ROUND((((S84+ROUND((ROUND(((((EU84*1.25)*1.1))*AV84*I84),2)*BS84),2))*AT84)/100),2)+ROUND(((ROUND((ROUND(((AE84-(((EU84*1.25)*1.1)))*AV84*I84),2)*BS84),2)*AT84)/100),2)) -> 7506.17 | Y84: =(ROUND((((S84+ROUND((ROUND(((((EU84*1.25)*1.1))*AV84*I84),2)*BS84),2))*AU84)/100),2)+ROUND(((ROUND((ROUND(((AE84-(((EU84*1.25)*1.1)))*AV84*I84),2)*BS84),2)*AU84)/100),2)) -> 4200.7 | AA84: 60255011 | AB84: =ROUND((AC84+AD84+AF84),6) -> 3369.5053 | AC84: =ROUND((ES84),6) -> 2078.9 | AD84: =ROUND((((((ET84*1.25)*1.1))-(((EU84*1.25)*1.1)))+AE84),6) -> 131.10625 | AE84: =ROUND((((EU84*1.25)*1.1)),6) -> 14.1625 | AF84: =ROUND((((EV84*1.15)*1.1)),6) -> 1159.499 | AG84: =ROUND((AP84),6) -> 0 | AH84: =(((EW84*1.15)*1.1)) -> 94.4955 | AI84: =(((EX84*1.25)*1.1)) -> 0 | AJ84: =(AS84) -> 0 | AK84: 3090.85 | AL84: 2078.9 | AM84: 95.35 | AN84: 10.3 | AO84: 916.6 | AP84: 0 | AQ84: 74.7 | AR84: 0 | AS84: 0 | AT84: 109 | AU84: 61 | AV84: 1.067 | AW84: 1 | AZ84: 1 | BA84: 54.99 | BB84: 14.33 | BC84: 20.59 | BH84: 0 | BI84: 1 | BJ84: ТСН-2001.3 Доп. 80, Сб. 18, т. 25, поз. 1 | BM84: 23 | BN84: 0 | BO84: 3.18-25-1 | BP84: 1 | BQ84: 30 | BR84: 0 | BS84: 54.99 | BT84: 1 | BU84: 1 | BV84: 1 | BW84: 1 | BX84: 1 | BZ84: 109 | CA84: 61 | CE84: 1566 | CF84: 0 | CG84: 0 | CM84: 0 | CN84: Поправка: О.П. п.3.4. 6 Наименование: Выполняемые при ремонте и реконструкции работы аналогичные технологическим процессам, характерным для нового строительства и отсутствующим в сборниках на ремонтно-строительные работы Поправка: О.П. п.3.4.30.в Наименование: При применении территориальных сметных нормативов для города Москвы затраты, учитывающие напряженные и стесненные условия производства работ (стесненность, сложность складирования и транспортной логистики и т.п.), исчисляются с применением коэффициентов к затратам труда и заработной плате рабочих, машинистов, времени эксплуатации машин и механизмов, стоимости эксплуатации машин в размере: для объектов, расположенных за пределами Третьего транспортного кольца города Москвы, но в пределах Московской кольцевой автомобильной дороги | CO84: 0 | CP84: =(P84+Q84+S84) -> 11284.3 | CQ84: =ROUND((ROUND((AC84*AW84*1),2)*BC84),2) -> 42804.55 | CR84: =(ROUND((ROUND(((((ET84*1.25)*1.1))*AV84*1),2)*BB84),2)+ROUND((ROUND(((AE84-(((EU84*1.25)*1.1)))*AV84*1),2)*BS84),2)) -> 2004.62 | CS84: =(ROUND((ROUND(((((EU84*1.25)*1.1))*AV84*1),2)*BS84),2)+ROUND((ROUND(((AE84-(((EU84*1.25)*1.1)))*AV84*1),2)*BS84),2)) -> 830.9 | CT84: =ROUND((ROUND((AF84*AV84*1),2)*BA84),2) -> 68033.08 | CU84: =AG84 -> 0 | CV84: =(AH84*AV84) -> 100.8267 | CW84: =AI84 -> 0 | CX84: =AJ84 -> 0 | CY84: =(ROUND((((S84+ROUND((ROUND(((((EU84*1.25)*1.1))*AV84*1),2)*BS84),2))*AT84)/100),2)+ROUND(((ROUND((ROUND(((AE84-(((EU84*1.25)*1.1)))*AV84*1),2)*BS84),2)*AT84)/100),2)) -> 8321.34 | CZ84: =(ROUND((((S84+ROUND((ROUND(((((EU84*1.25)*1.1))*AV84*1),2)*BS84),2))*AU84)/100),2)+ROUND(((ROUND((ROUND(((AE84-(((EU84*1.25)*1.1)))*AV84*1),2)*BS84),2)*AU84)/100),2)) -> 4656.9 | DB84: 7 | DE84: *1,25)*1,1 | DF84: *1,25)*1,1 | DG84: *1,15)*1,1 | DI84: *1,15)*1,1 | DJ84: *1,25)*1,1 | DN84: 0 | DO84: 0 | DP84: 1 | DQ84: 1 | DU84: 1010 | DV84: 100 шт. | DW84: 100 шт. | DX84: 100 | EE84: 60088254 | EF84: 30 | EG84: Строительные работы | EH84: 0 | EJ84: 1 | EK84: 23 | EL84: ТСН-2001.3-18. Отопление - внутренние устройства | EM84: ТСН-2001.3-18-1 | EO84: Поправка: О.П. п.3.4. 6 Поправка: О.П. п.3.4.30.в | EQ84: 0 | ER84: 3090.85 | ES84: 2078.9 | ET84: 95.35 | EU84: 10.3 | EV84: 916.6 | EW84: 74.7 | EX84: 0 | EY84: 0 | FQ84: 0 | FR84: 0 | FS84: 0 | FX84: 109 | FY84: 61 | GD84: 1 | GF84: -961949121 | GG84: 2 | GH84: 1 | GI84: 2 | GJ84: 0 | GK84: 0 | GL84: =ROUND(IF(AND(BH84=3,BI84=3,FS84<>0),P84,0),2) -> 0 | GM84: =ROUND(O84+X84+Y84,2)+GX84 -> 22991.17 | GN84: =IF(OR(BI84=0,BI84=1),GM84-GX84,0) -> 22991.17 | GO84: =IF(BI84=2,GM84-GX84,0) -> 0 | GP84: =IF(BI84=4,GM84-GX84,0) -> 0 | GR84: 0 | GS84: 3 | GT84: 0 | GV84: =ROUND((GT84),6) -> 0 | GW84: 1 | GX84: =ROUND(HC84*I84,2) -> 0 | HA84: 0 | HB84: 0 | HC84: =GV84*GW84 -> 0 | HS84: 0 | IK84: 0
A85: 17 | B85: 1 | E85: 12 | F85: КА-7 | G85: Стальной панельный радиатор, гигиеническое исполнение Royal Thermo H 20-0400-0400 (тепловая мощность 0,488 кВт) | H85: ШТ | I85: 1 | J85: 0 | K85: 1 | O85: =ROUND(CP85,2) -> 345.85 | P85: =ROUND((ROUND((AC85*AW85*I85),2)*BC85),2) -> 345.85 | Q85: =(ROUND((ROUND(((ET85)*AV85*I85),2)*BB85),2)+ROUND((ROUND(((AE85-(EU85))*AV85*I85),2)*BS85),2)) -> 0 | R85: =(ROUND((ROUND(((EU85)*AV85*I85),2)*BS85),2)+ROUND((ROUND(((AE85-(EU85))*AV85*I85),2)*BS85),2)) -> 0 | S85: =ROUND((ROUND((AF85*AV85*I85),2)*BA85),2) -> 0 | T85: =ROUND(CU85*I85,2) -> 0 | U85: =CV85*I85 -> 0 | V85: =CW85*I85 -> 0 | W85: =ROUND(CX85*I85,2) -> 0 | X85: =(ROUND((((S85+ROUND((ROUND(((EU85)*AV85*I85),2)*BS85),2))*AT85)/100),2)+ROUND(((ROUND((ROUND(((AE85-(EU85))*AV85*I85),2)*BS85),2)*AT85)/100),2)) -> 0 | Y85: =(ROUND((((S85+ROUND((ROUND(((EU85)*AV85*I85),2)*BS85),2))*AU85)/100),2)+ROUND(((ROUND((ROUND(((AE85-(EU85))*AV85*I85),2)*BS85),2)*AU85)/100),2)) -> 0 | AA85: 60255014 | AB85: =ROUND((AC85+AD85+AF85),6) -> 345.85 | AC85: =ROUND((ES85),6) -> 345.85 | AD85: =ROUND((((ET85)-(EU85))+AE85),6) -> 0 | AE85: =ROUND((EU85),6) -> 0 | AF85: =ROUND((EV85),6) -> 0 | AG85: =ROUND((AP85),6) -> 0 | AH85: =(EW85) -> 0 | AI85: =(EX85) -> 0 | AJ85: =(AS85) -> 0 | AK85: 345.85 | AL85: 345.85 | AM85: 0 | AN85: 0 | AO85: 0 | AP85: 0 | AQ85: 0 | AR85: 0 | AS85: 0 | AT85: 0 | AU85: 0 | AV85: 1 | AW85: 1 | AZ85: 1 | BA85: 1 | BB85: 1 | BC85: 1 | BH85: 3 | BI85: 1 | BM85: 400002 | BN85: 0 | BP85: 0 | BQ85: 202 | BR85: 0 | BS85: 1 | BT85: 1 | BU85: 1 | BV85: 1 | BW85: 1 | BX85: 1 | BZ85: 0 | CA85: 0 | CE85: 1566 | CF85: 0 | CG85: 0 | CM85: 0 | CO85: 0 | CP85: =(P85+Q85+S85) -> 345.85 | CQ85: =ROUND((ROUND((AC85*AW85*1),2)*BC85),2) -> 345.85 | CR85: =(ROUND((ROUND(((ET85)*AV85*1),2)*BB85),2)+ROUND((ROUND(((AE85-(EU85))*AV85*1),2)*BS85),2)) -> 0 | CS85: =(ROUND((ROUND(((EU85)*AV85*1),2)*BS85),2)+ROUND((ROUND(((AE85-(EU85))*AV85*1),2)*BS85),2)) -> 0 | CT85: =ROUND((ROUND((AF85*AV85*1),2)*BA85),2) -> 0 | CU85: =AG85 -> 0 | CV85: =(AH85*AV85) -> 0 | CW85: =AI85 -> 0 | CX85: =AJ85 -> 0 | CY85: =(ROUND((((S85+ROUND((ROUND(((EU85)*AV85*1),2)*BS85),2))*AT85)/100),2)+ROUND(((ROUND((ROUND(((AE85-(EU85))*AV85*1),2)*BS85),2)*AT85)/100),2)) -> 0 | CZ85: =(ROUND((((S85+ROUND((ROUND(((EU85)*AV85*1),2)*BS85),2))*AU85)/100),2)+ROUND(((ROUND((ROUND(((AE85-(EU85))*AV85*1),2)*BS85),2)*AU85)/100),2)) -> 0 | DN85: 0 | DO85: 0 | DP85: 1 | DQ85: 1 | DU85: 1013 | DV85: ШТ | DW85: ШТ | DX85: 1 | EE85: 60088211 | EF85: 202 | EG85: Материалы | EH85: 0 | EJ85: 1 | EK85: 400002 | EL85: Материалы, изделия и конструкции | EM85: Материалы | EQ85: 0 | ER85: 0 | ES85: 345.85 | ET85: 0 | EU85: 0 | EV85: 0 | EW85: 0 | EX85: 0 | EY85: 0 | FQ85: 0 | FR85: 0 | FS85: 0 | FX85: 0 | FY85: 0 | GA85: [4 020 / 1,2 / 9,88] + 2% Заг.скл | GD85: 1 | GF85: 722466062 | GG85: 2 | GH85: 4 | GI85: -2 | GJ85: 0 | GK85: 0 | GL85: =ROUND(IF(AND(BH85=3,BI85=3,FS85<>0),P85,0),2) -> 0 | GM85: =ROUND(O85+X85+Y85,2)+GX85 -> 345.85 | GN85: =IF(OR(BI85=0,BI85=1),GM85-GX85,0) -> 345.85 | GO85: =IF(BI85=2,GM85-GX85,0) -> 0 | GP85: =IF(BI85=4,GM85-GX85,0) -> 0 | GR85: 0 | GS85: 2 | GT85: 0 | GV85: =ROUND((GT85),6) -> 0 | GW85: 1 | GX85: =ROUND(HC85*I85,2) -> 0 | HA85: 0 | HB85: 0 | HC85: =GV85*GW85 -> 0 | HE85: 0 | HF85: 2 | HS85: 0 | IK85: 0
A86: 17 | B86: 1 | E86: 12 | F86: КА-7 | G86: Стальной панельный радиатор, гигиеническое исполнение Royal Thermo H 20-0400-0400 (тепловая мощность 0,488 кВт) | H86: ШТ | I86: 1 | J86: 0 | K86: 1 | O86: =ROUND(CP86,2) -> 3417 | P86: =ROUND((ROUND((AC86*AW86*I86),2)*BC86),2) -> 3417 | Q86: =(ROUND((ROUND(((ET86)*AV86*I86),2)*BB86),2)+ROUND((ROUND(((AE86-(EU86))*AV86*I86),2)*BS86),2)) -> 0 | R86: =(ROUND((ROUND(((EU86)*AV86*I86),2)*BS86),2)+ROUND((ROUND(((AE86-(EU86))*AV86*I86),2)*BS86),2)) -> 0 | S86: =ROUND((ROUND((AF86*AV86*I86),2)*BA86),2) -> 0 | T86: =ROUND(CU86*I86,2) -> 0 | U86: =CV86*I86 -> 0 | V86: =CW86*I86 -> 0 | W86: =ROUND(CX86*I86,2) -> 0 | X86: =(ROUND((((S86+ROUND((ROUND(((EU86)*AV86*I86),2)*BS86),2))*AT86)/100),2)+ROUND(((ROUND((ROUND(((AE86-(EU86))*AV86*I86),2)*BS86),2)*AT86)/100),2)) -> 0 | Y86: =(ROUND((((S86+ROUND((ROUND(((EU86)*AV86*I86),2)*BS86),2))*AU86)/100),2)+ROUND(((ROUND((ROUND(((AE86-(EU86))*AV86*I86),2)*BS86),2)*AU86)/100),2)) -> 0 | AA86: 60255011 | AB86: =ROUND((AC86+AD86+AF86),6) -> 345.85 | AC86: =ROUND((ES86),6) -> 345.85 | AD86: =ROUND((((ET86)-(EU86))+AE86),6) -> 0 | AE86: =ROUND((EU86),6) -> 0 | AF86: =ROUND((EV86),6) -> 0 | AG86: =ROUND((AP86),6) -> 0 | AH86: =(EW86) -> 0 | AI86: =(EX86) -> 0 | AJ86: =(AS86) -> 0 | AK86: 345.85 | AL86: 345.85 | AM86: 0 | AN86: 0 | AO86: 0 | AP86: 0 | AQ86: 0 | AR86: 0 | AS86: 0 | AT86: 0 | AU86: 0 | AV86: 1 | AW86: 1 | AZ86: 1 | BA86: 1 | BB86: 1 | BC86: 9.88 | BH86: 3 | BI86: 1 | BM86: 400002 | BN86: 0 | BP86: 0 | BQ86: 202 | BR86: 0 | BS86: 1 | BT86: 1 | BU86: 1 | BV86: 1 | BW86: 1 | BX86: 1 | BZ86: 0 | CA86: 0 | CE86: 1566 | CF86: 0 | CG86: 0 | CM86: 0 | CO86: 0 | CP86: =(P86+Q86+S86) -> 3417 | CQ86: =ROUND((ROUND((AC86*AW86*1),2)*BC86),2) -> 3417 | CR86: =(ROUND((ROUND(((ET86)*AV86*1),2)*BB86),2)+ROUND((ROUND(((AE86-(EU86))*AV86*1),2)*BS86),2)) -> 0 | CS86: =(ROUND((ROUND(((EU86)*AV86*1),2)*BS86),2)+ROUND((ROUND(((AE86-(EU86))*AV86*1),2)*BS86),2)) -> 0 | CT86: =ROUND((ROUND((AF86*AV86*1),2)*BA86),2) -> 0 | CU86: =AG86 -> 0 | CV86: =(AH86*AV86) -> 0 | CW86: =AI86 -> 0 | CX86: =AJ86 -> 0 | CY86: =(ROUND((((S86+ROUND((ROUND(((EU86)*AV86*1),2)*BS86),2))*AT86)/100),2)+ROUND(((ROUND((ROUND(((AE86-(EU86))*AV86*1),2)*BS86),2)*AT86)/100),2)) -> 0 | CZ86: =(ROUND((((S86+ROUND((ROUND(((EU86)*AV86*1),2)*BS86),2))*AU86)/100),2)+ROUND(((ROUND((ROUND(((AE86-(EU86))*AV86*1),2)*BS86),2)*AU86)/100),2)) -> 0 | DN86: 0 | DO86: 0 | DP86: 1 | DQ86: 1 | DU86: 1013 | DV86: ШТ | DW86: ШТ | DX86: 1 | EE86: 60088211 | EF86: 202 | EG86: Материалы | EH86: 0 | EJ86: 1 | EK86: 400002 | EL86: Материалы, изделия и конструкции | EM86: Материалы | EQ86: 0 | ER86: 345.85 | ES86: 345.85 | ET86: 0 | EU86: 0 | EV86: 0 | EW86: 0 | EX86: 0 | EY86: 0 | EZ86: 5 | FC86: 1 | FD86: 18 | FF86: 4020 | FQ86: 0 | FR86: 0 | FS86: 0 | FX86: 0 | FY86: 0 | GA86: [4 020 / 1,2 / 9,88] + 2% Заг.скл | GD86: 1 | GF86: 722466062 | GG86: 2 | GH86: 3 | GI86: 5 | GJ86: 0 | GK86: 0 | GL86: =ROUND(IF(AND(BH86=3,BI86=3,FS86<>0),P86,0),2) -> 0 | GM86: =ROUND(O86+X86+Y86,2)+GX86 -> 3417 | GN86: =IF(OR(BI86=0,BI86=1),GM86-GX86,0) -> 3417 | GO86: =IF(BI86=2,GM86-GX86,0) -> 0 | GP86: =IF(BI86=4,GM86-GX86,0) -> 0 | GR86: 1 | GS86: 1 | GT86: 0 | GV86: =ROUND((GT86),6) -> 0 | GW86: 1 | GX86: =ROUND(HC86*I86,2) -> 0 | HA86: 0 | HB86: 0 | HC86: =GV86*GW86 -> 0 | HE86: 0 | HF86: 2 | HS86: 0 | IK86: 0
A87: 17 | B87: 1 | E87: 13 | F87: КА-8 | G87: Стальной панельный радиатор, гигиеническое исполнение Royal Thermо H 20-0400-0600 (тепловая мощность 0,732 кВт) | H87: ШТ | I87: 2 | J87: 0 | K87: 2 | O87: =ROUND(CP87,2) -> 703.74 | P87: =ROUND((ROUND((AC87*AW87*I87),2)*BC87),2) -> 703.74 | Q87: =(ROUND((ROUND(((ET87)*AV87*I87),2)*BB87),2)+ROUND((ROUND(((AE87-(EU87))*AV87*I87),2)*BS87),2)) -> 0 | R87: =(ROUND((ROUND(((EU87)*AV87*I87),2)*BS87),2)+ROUND((ROUND(((AE87-(EU87))*AV87*I87),2)*BS87),2)) -> 0 | S87: =ROUND((ROUND((AF87*AV87*I87),2)*BA87),2) -> 0 | T87: =ROUND(CU87*I87,2) -> 0 | U87: =CV87*I87 -> 0 | V87: =CW87*I87 -> 0 | W87: =ROUND(CX87*I87,2) -> 0 | X87: =(ROUND((((S87+ROUND((ROUND(((EU87)*AV87*I87),2)*BS87),2))*AT87)/100),2)+ROUND(((ROUND((ROUND(((AE87-(EU87))*AV87*I87),2)*BS87),2)*AT87)/100),2)) -> 0 | Y87: =(ROUND((((S87+ROUND((ROUND(((EU87)*AV87*I87),2)*BS87),2))*AU87)/100),2)+ROUND(((ROUND((ROUND(((AE87-(EU87))*AV87*I87),2)*BS87),2)*AU87)/100),2)) -> 0 | AA87: 60255014 | AB87: =ROUND((AC87+AD87+AF87),6) -> 351.87 | AC87: =ROUND((ES87),6) -> 351.87 | AD87: =ROUND((((ET87)-(EU87))+AE87),6) -> 0 | AE87: =ROUND((EU87),6) -> 0 | AF87: =ROUND((EV87),6) -> 0 | AG87: =ROUND((AP87),6) -> 0 | AH87: =(EW87) -> 0 | AI87: =(EX87) -> 0 | AJ87: =(AS87) -> 0 | AK87: 351.87 | AL87: 351.87 | AM87: 0 | AN87: 0 | AO87: 0 | AP87: 0 | AQ87: 0 | AR87: 0 | AS87: 0 | AT87: 0 | AU87: 0 | AV87: 1 | AW87: 1 | AZ87: 1 | BA87: 1 | BB87: 1 | BC87: 1 | BH87: 3 | BI87: 1 | BM87: 400002 | BN87: 0 | BP87: 0 | BQ87: 202 | BR87: 0 | BS87: 1 | BT87: 1 | BU87: 1 | BV87: 1 | BW87: 1 | BX87: 1 | BZ87: 0 | CA87: 0 | CE87: 1566 | CF87: 0 | CG87: 0 | CM87: 0 | CO87: 0 | CP87: =(P87+Q87+S87) -> 703.74 | CQ87: =ROUND((ROUND((AC87*AW87*1),2)*BC87),2) -> 351.87 | CR87: =(ROUND((ROUND(((ET87)*AV87*1),2)*BB87),2)+ROUND((ROUND(((AE87-(EU87))*AV87*1),2)*BS87),2)) -> 0 | CS87: =(ROUND((ROUND(((EU87)*AV87*1),2)*BS87),2)+ROUND((ROUND(((AE87-(EU87))*AV87*1),2)*BS87),2)) -> 0 | CT87: =ROUND((ROUND((AF87*AV87*1),2)*BA87),2) -> 0 | CU87: =AG87 -> 0 | CV87: =(AH87*AV87) -> 0 | CW87: =AI87 -> 0 | CX87: =AJ87 -> 0 | CY87: =(ROUND((((S87+ROUND((ROUND(((EU87)*AV87*1),2)*BS87),2))*AT87)/100),2)+ROUND(((ROUND((ROUND(((AE87-(EU87))*AV87*1),2)*BS87),2)*AT87)/100),2)) -> 0 | CZ87: =(ROUND((((S87+ROUND((ROUND(((EU87)*AV87*1),2)*BS87),2))*AU87)/100),2)+ROUND(((ROUND((ROUND(((AE87-(EU87))*AV87*1),2)*BS87),2)*AU87)/100),2)) -> 0 | DN87: 0 | DO87: 0 | DP87: 1 | DQ87: 1 | DU87: 1013 | DV87: ШТ | DW87: ШТ | DX87: 1 | EE87: 60088211 | EF87: 202 | EG87: Материалы | EH87: 0 | EJ87: 1 | EK87: 400002 | EL87: Материалы, изделия и конструкции | EM87: Материалы | EQ87: 0 | ER87: 0 | ES87: 351.87 | ET87: 0 | EU87: 0 | EV87: 0 | EW87: 0 | EX87: 0 | EY87: 0 | FQ87: 0 | FR87: 0 | FS87: 0 | FX87: 0 | FY87: 0 | GA87: [4 090 / 1,2 / 9,88] + 2% Заг.скл | GD87: 1 | GF87: 484917105 | GG87: 2 | GH87: 4 | GI87: -2 | GJ87: 0 | GK87: 0 | GL87: =ROUND(IF(AND(BH87=3,BI87=3,FS87<>0),P87,0),2) -> 0 | GM87: =ROUND(O87+X87+Y87,2)+GX87 -> 703.74 | GN87: =IF(OR(BI87=0,BI87=1),GM87-GX87,0) -> 703.74 | GO87: =IF(BI87=2,GM87-GX87,0) -> 0 | GP87: =IF(BI87=4,GM87-GX87,0) -> 0 | GR87: 0 | GS87: 2 | GT87: 0 | GV87: =ROUND((GT87),6) -> 0 | GW87: 1 | GX87: =ROUND(HC87*I87,2) -> 0 | HA87: 0 | HB87: 0 | HC87: =GV87*GW87 -> 0 | HE87: 0 | HF87: 2 | HS87: 0 | IK87: 0
A88: 17 | B88: 1 | E88: 13 | F88: КА-8 | G88: Стальной панельный радиатор, гигиеническое исполнение Royal Thermо H 20-0400-0600 (тепловая мощность 0,732 кВт) | H88: ШТ | I88: 2 | J88: 0 | K88: 2 | O88: =ROUND(CP88,2) -> 6952.95 | P88: =ROUND((ROUND((AC88*AW88*I88),2)*BC88),2) -> 6952.95 | Q88: =(ROUND((ROUND(((ET88)*AV88*I88),2)*BB88),2)+ROUND((ROUND(((AE88-(EU88))*AV88*I88),2)*BS88),2)) -> 0 | R88: =(ROUND((ROUND(((EU88)*AV88*I88),2)*BS88),2)+ROUND((ROUND(((AE88-(EU88))*AV88*I88),2)*BS88),2)) -> 0 | S88: =ROUND((ROUND((AF88*AV88*I88),2)*BA88),2) -> 0 | T88: =ROUND(CU88*I88,2) -> 0 | U88: =CV88*I88 -> 0 | V88: =CW88*I88 -> 0 | W88: =ROUND(CX88*I88,2) -> 0 | X88: =(ROUND((((S88+ROUND((ROUND(((EU88)*AV88*I88),2)*BS88),2))*AT88)/100),2)+ROUND(((ROUND((ROUND(((AE88-(EU88))*AV88*I88),2)*BS88),2)*AT88)/100),2)) -> 0 | Y88: =(ROUND((((S88+ROUND((ROUND(((EU88)*AV88*I88),2)*BS88),2))*AU88)/100),2)+ROUND(((ROUND((ROUND(((AE88-(EU88))*AV88*I88),2)*BS88),2)*AU88)/100),2)) -> 0 | AA88: 60255011 | AB88: =ROUND((AC88+AD88+AF88),6) -> 351.87 | AC88: =ROUND((ES88),6) -> 351.87 | AD88: =ROUND((((ET88)-(EU88))+AE88),6) -> 0 | AE88: =ROUND((EU88),6) -> 0 | AF88: =ROUND((EV88),6) -> 0 | AG88: =ROUND((AP88),6) -> 0 | AH88: =(EW88) -> 0 | AI88: =(EX88) -> 0 | AJ88: =(AS88) -> 0 | AK88: 351.87 | AL88: 351.87 | AM88: 0 | AN88: 0 | AO88: 0 | AP88: 0 | AQ88: 0 | AR88: 0 | AS88: 0 | AT88: 0 | AU88: 0 | AV88: 1 | AW88: 1 | AZ88: 1 | BA88: 1 | BB88: 1 | BC88: 9.88 | BH88: 3 | BI88: 1 | BM88: 400002 | BN88: 0 | BP88: 0 | BQ88: 202 | BR88: 0 | BS88: 1 | BT88: 1 | BU88: 1 | BV88: 1 | BW88: 1 | BX88: 1 | BZ88: 0 | CA88: 0 | CE88: 1566 | CF88: 0 | CG88: 0 | CM88: 0 | CO88: 0 | CP88: =(P88+Q88+S88) -> 6952.95 | CQ88: =ROUND((ROUND((AC88*AW88*1),2)*BC88),2) -> 3476.48 | CR88: =(ROUND((ROUND(((ET88)*AV88*1),2)*BB88),2)+ROUND((ROUND(((AE88-(EU88))*AV88*1),2)*BS88),2)) -> 0 | CS88: =(ROUND((ROUND(((EU88)*AV88*1),2)*BS88),2)+ROUND((ROUND(((AE88-(EU88))*AV88*1),2)*BS88),2)) -> 0 | CT88: =ROUND((ROUND((AF88*AV88*1),2)*BA88),2) -> 0 | CU88: =AG88 -> 0 | CV88: =(AH88*AV88) -> 0 | CW88: =AI88 -> 0 | CX88: =AJ88 -> 0 | CY88: =(ROUND((((S88+ROUND((ROUND(((EU88)*AV88*1),2)*BS88),2))*AT88)/100),2)+ROUND(((ROUND((ROUND(((AE88-(EU88))*AV88*1),2)*BS88),2)*AT88)/100),2)) -> 0 | CZ88: =(ROUND((((S88+ROUND((ROUND(((EU88)*AV88*1),2)*BS88),2))*AU88)/100),2)+ROUND(((ROUND((ROUND(((AE88-(EU88))*AV88*1),2)*BS88),2)*AU88)/100),2)) -> 0 | DN88: 0 | DO88: 0 | DP88: 1 | DQ88: 1 | DU88: 1013 | DV88: ШТ | DW88: ШТ | DX88: 1 | EE88: 60088211 | EF88: 202 | EG88: Материалы | EH88: 0 | EJ88: 1 | EK88: 400002 | EL88: Материалы, изделия и конструкции | EM88: Материалы | EQ88: 0 | ER88: 351.87 | ES88: 351.87 | ET88: 0 | EU88: 0 | EV88: 0 | EW88: 0 | EX88: 0 | EY88: 0 | EZ88: 5 | FC88: 1 | FD88: 18 | FF88: 4090 | FQ88: 0 | FR88: 0 | FS88: 0 | FX88: 0 | FY88: 0 | GA88: [4 090 / 1,2 / 9,88] + 2% Заг.скл | GD88: 1 | GF88: 484917105 | GG88: 2 | GH88: 3 | GI88: 5 | GJ88: 0 | GK88: 0 | GL88: =ROUND(IF(AND(BH88=3,BI88=3,FS88<>0),P88,0),2) -> 0 | GM88: =ROUND(O88+X88+Y88,2)+GX88 -> 6952.95 | GN88: =IF(OR(BI88=0,BI88=1),GM88-GX88,0) -> 6952.95 | GO88: =IF(BI88=2,GM88-GX88,0) -> 0 | GP88: =IF(BI88=4,GM88-GX88,0) -> 0 | GR88: 1 | GS88: 1 | GT88: 0 | GV88: =ROUND((GT88),6) -> 0 | GW88: 1 | GX88: =ROUND(HC88*I88,2) -> 0 | HA88: 0 | HB88: 0 | HC88: =GV88*GW88 -> 0 | HE88: 0 | HF88: 2 | HS88: 0 | IK88: 0
A89: 17 | B89: 1 | E89: 14 | F89: КА-9 | G89: Стальной панельный радиатор, гигиеническое исполнение Royal Thermо H 20-0400-0800 (тепловая мощность 0,9759 кВт) | H89: ШТ | I89: 1 | J89: 0 | K89: 1 | O89: =ROUND(CP89,2) -> 417.26 | P89: =ROUND((ROUND((AC89*AW89*I89),2)*BC89),2) -> 417.26 | Q89: =(ROUND((ROUND(((ET89)*AV89*I89),2)*BB89),2)+ROUND((ROUND(((AE89-(EU89))*AV89*I89),2)*BS89),2)) -> 0 | R89: =(ROUND((ROUND(((EU89)*AV89*I89),2)*BS89),2)+ROUND((ROUND(((AE89-(EU89))*AV89*I89),2)*BS89),2)) -> 0 | S89: =ROUND((ROUND((AF89*AV89*I89),2)*BA89),2) -> 0 | T89: =ROUND(CU89*I89,2) -> 0 | U89: =CV89*I89 -> 0 | V89: =CW89*I89 -> 0 | W89: =ROUND(CX89*I89,2) -> 0 | X89: =(ROUND((((S89+ROUND((ROUND(((EU89)*AV89*I89),2)*BS89),2))*AT89)/100),2)+ROUND(((ROUND((ROUND(((AE89-(EU89))*AV89*I89),2)*BS89),2)*AT89)/100),2)) -> 0 | Y89: =(ROUND((((S89+ROUND((ROUND(((EU89)*AV89*I89),2)*BS89),2))*AU89)/100),2)+ROUND(((ROUND((ROUND(((AE89-(EU89))*AV89*I89),2)*BS89),2)*AU89)/100),2)) -> 0 | AA89: 60255014 | AB89: =ROUND((AC89+AD89+AF89),6) -> 417.26 | AC89: =ROUND((ES89),6) -> 417.26 | AD89: =ROUND((((ET89)-(EU89))+AE89),6) -> 0 | AE89: =ROUND((EU89),6) -> 0 | AF89: =ROUND((EV89),6) -> 0 | AG89: =ROUND((AP89),6) -> 0 | AH89: =(EW89) -> 0 | AI89: =(EX89) -> 0 | AJ89: =(AS89) -> 0 | AK89: 417.26 | AL89: 417.26 | AM89: 0 | AN89: 0 | AO89: 0 | AP89: 0 | AQ89: 0 | AR89: 0 | AS89: 0 | AT89: 0 | AU89: 0 | AV89: 1 | AW89: 1 | AZ89: 1 | BA89: 1 | BB89: 1 | BC89: 1 | BH89: 3 | BI89: 1 | BM89: 400002 | BN89: 0 | BP89: 0 | BQ89: 202 | BR89: 0 | BS89: 1 | BT89: 1 | BU89: 1 | BV89: 1 | BW89: 1 | BX89: 1 | BZ89: 0 | CA89: 0 | CE89: 1566 | CF89: 0 | CG89: 0 | CM89: 0 | CO89: 0 | CP89: =(P89+Q89+S89) -> 417.26 | CQ89: =ROUND((ROUND((AC89*AW89*1),2)*BC89),2) -> 417.26 | CR89: =(ROUND((ROUND(((ET89)*AV89*1),2)*BB89),2)+ROUND((ROUND(((AE89-(EU89))*AV89*1),2)*BS89),2)) -> 0 | CS89: =(ROUND((ROUND(((EU89)*AV89*1),2)*BS89),2)+ROUND((ROUND(((AE89-(EU89))*AV89*1),2)*BS89),2)) -> 0 | CT89: =ROUND((ROUND((AF89*AV89*1),2)*BA89),2) -> 0 | CU89: =AG89 -> 0 | CV89: =(AH89*AV89) -> 0 | CW89: =AI89 -> 0 | CX89: =AJ89 -> 0 | CY89: =(ROUND((((S89+ROUND((ROUND(((EU89)*AV89*1),2)*BS89),2))*AT89)/100),2)+ROUND(((ROUND((ROUND(((AE89-(EU89))*AV89*1),2)*BS89),2)*AT89)/100),2)) -> 0 | CZ89: =(ROUND((((S89+ROUND((ROUND(((EU89)*AV89*1),2)*BS89),2))*AU89)/100),2)+ROUND(((ROUND((ROUND(((AE89-(EU89))*AV89*1),2)*BS89),2)*AU89)/100),2)) -> 0 | DN89: 0 | DO89: 0 | DP89: 1 | DQ89: 1 | DU89: 1013 | DV89: ШТ | DW89: ШТ | DX89: 1 | EE89: 60088211 | EF89: 202 | EG89: Материалы | EH89: 0 | EJ89: 1 | EK89: 400002 | EL89: Материалы, изделия и конструкции | EM89: Материалы | EQ89: 0 | ER89: 0 | ES89: 417.26 | ET89: 0 | EU89: 0 | EV89: 0 | EW89: 0 | EX89: 0 | EY89: 0 | FQ89: 0 | FR89: 0 | FS89: 0 | FX89: 0 | FY89: 0 | GA89: [4 850 / 1,2 / 9,88] + 2% Заг.скл | GD89: 1 | GF89: -1028478906 | GG89: 2 | GH89: 4 | GI89: -2 | GJ89: 0 | GK89: 0 | GL89: =ROUND(IF(AND(BH89=3,BI89=3,FS89<>0),P89,0),2) -> 0 | GM89: =ROUND(O89+X89+Y89,2)+GX89 -> 417.26 | GN89: =IF(OR(BI89=0,BI89=1),GM89-GX89,0) -> 417.26 | GO89: =IF(BI89=2,GM89-GX89,0) -> 0 | GP89: =IF(BI89=4,GM89-GX89,0) -> 0 | GR89: 0 | GS89: 2 | GT89: 0 | GV89: =ROUND((GT89),6) -> 0 | GW89: 1 | GX89: =ROUND(HC89*I89,2) -> 0 | HA89: 0 | HB89: 0 | HC89: =GV89*GW89 -> 0 | HE89: 0 | HF89: 2 | HS89: 0 | IK89: 0
A90: 17 | B90: 1 | E90: 14 | F90: КА-9 | G90: Стальной панельный радиатор, гигиеническое исполнение Royal Thermо H 20-0400-0800 (тепловая мощность 0,9759 кВт) | H90: ШТ | I90: 1 | J90: 0 | K90: 1 | O90: =ROUND(CP90,2) -> 4122.53 | P90: =ROUND((ROUND((AC90*AW90*I90),2)*BC90),2) -> 4122.53 | Q90: =(ROUND((ROUND(((ET90)*AV90*I90),2)*BB90),2)+ROUND((ROUND(((AE90-(EU90))*AV90*I90),2)*BS90),2)) -> 0 | R90: =(ROUND((ROUND(((EU90)*AV90*I90),2)*BS90),2)+ROUND((ROUND(((AE90-(EU90))*AV90*I90),2)*BS90),2)) -> 0 | S90: =ROUND((ROUND((AF90*AV90*I90),2)*BA90),2) -> 0 | T90: =ROUND(CU90*I90,2) -> 0 | U90: =CV90*I90 -> 0 | V90: =CW90*I90 -> 0 | W90: =ROUND(CX90*I90,2) -> 0 | X90: =(ROUND((((S90+ROUND((ROUND(((EU90)*AV90*I90),2)*BS90),2))*AT90)/100),2)+ROUND(((ROUND((ROUND(((AE90-(EU90))*AV90*I90),2)*BS90),2)*AT90)/100),2)) -> 0 | Y90: =(ROUND((((S90+ROUND((ROUND(((EU90)*AV90*I90),2)*BS90),2))*AU90)/100),2)+ROUND(((ROUND((ROUND(((AE90-(EU90))*AV90*I90),2)*BS90),2)*AU90)/100),2)) -> 0 | AA90: 60255011 | AB90: =ROUND((AC90+AD90+AF90),6) -> 417.26 | AC90: =ROUND((ES90),6) -> 417.26 | AD90: =ROUND((((ET90)-(EU90))+AE90),6) -> 0 | AE90: =ROUND((EU90),6) -> 0 | AF90: =ROUND((EV90),6) -> 0 | AG90: =ROUND((AP90),6) -> 0 | AH90: =(EW90) -> 0 | AI90: =(EX90) -> 0 | AJ90: =(AS90) -> 0 | AK90: 417.26 | AL90: 417.26 | AM90: 0 | AN90: 0 | AO90: 0 | AP90: 0 | AQ90: 0 | AR90: 0 | AS90: 0 | AT90: 0 | AU90: 0 | AV90: 1 | AW90: 1 | AZ90: 1 | BA90: 1 | BB90: 1 | BC90: 9.88 | BH90: 3 | BI90: 1 | BM90: 400002 | BN90: 0 | BP90: 0 | BQ90: 202 | BR90: 0 | BS90: 1 | BT90: 1 | BU90: 1 | BV90: 1 | BW90: 1 | BX90: 1 | BZ90: 0 | CA90: 0 | CE90: 1566 | CF90: 0 | CG90: 0 | CM90: 0 | CO90: 0 | CP90: =(P90+Q90+S90) -> 4122.53 | CQ90: =ROUND((ROUND((AC90*AW90*1),2)*BC90),2) -> 4122.53 | CR90: =(ROUND((ROUND(((ET90)*AV90*1),2)*BB90),2)+ROUND((ROUND(((AE90-(EU90))*AV90*1),2)*BS90),2)) -> 0 | CS90: =(ROUND((ROUND(((EU90)*AV90*1),2)*BS90),2)+ROUND((ROUND(((AE90-(EU90))*AV90*1),2)*BS90),2)) -> 0 | CT90: =ROUND((ROUND((AF90*AV90*1),2)*BA90),2) -> 0 | CU90: =AG90 -> 0 | CV90: =(AH90*AV90) -> 0 | CW90: =AI90 -> 0 | CX90: =AJ90 -> 0 | CY90: =(ROUND((((S90+ROUND((ROUND(((EU90)*AV90*1),2)*BS90),2))*AT90)/100),2)+ROUND(((ROUND((ROUND(((AE90-(EU90))*AV90*1),2)*BS90),2)*AT90)/100),2)) -> 0 | CZ90: =(ROUND((((S90+ROUND((ROUND(((EU90)*AV90*1),2)*BS90),2))*AU90)/100),2)+ROUND(((ROUND((ROUND(((AE90-(EU90))*AV90*1),2)*BS90),2)*AU90)/100),2)) -> 0 | DN90: 0 | DO90: 0 | DP90: 1 | DQ90: 1 | DU90: 1013 | DV90: ШТ | DW90: ШТ | DX90: 1 | EE90: 60088211 | EF90: 202 | EG90: Материалы | EH90: 0 | EJ90: 1 | EK90: 400002 | EL90: Материалы, изделия и конструкции | EM90: Материалы | EQ90: 0 | ER90: 417.26 | ES90: 417.26 | ET90: 0 | EU90: 0 | EV90: 0 | EW90: 0 | EX90: 0 | EY90: 0 | EZ90: 5 | FC90: 1 | FD90: 18 | FF90: 4850 | FQ90: 0 | FR90: 0 | FS90: 0 | FX90: 0 | FY90: 0 | GA90: [4 850 / 1,2 / 9,88] + 2% Заг.скл | GD90: 1 | GF90: -1028478906 | GG90: 2 | GH90: 3 | GI90: 5 | GJ90: 0 | GK90: 0 | GL90: =ROUND(IF(AND(BH90=3,BI90=3,FS90<>0),P90,0),2) -> 0 | GM90: =ROUND(O90+X90+Y90,2)+GX90 -> 4122.53 | GN90: =IF(OR(BI90=0,BI90=1),GM90-GX90,0) -> 4122.53 | GO90: =IF(BI90=2,GM90-GX90,0) -> 0 | GP90: =IF(BI90=4,GM90-GX90,0) -> 0 | GR90: 1 | GS90: 1 | GT90: 0 | GV90: =ROUND((GT90),6) -> 0 | GW90: 1 | GX90: =ROUND(HC90*I90,2) -> 0 | HA90: 0 | HB90: 0 | HC90: =GV90*GW90 -> 0 | HE90: 0 | HF90: 2 | HS90: 0 | IK90: 0
A91: 17 | B91: 1 | E91: 15 | F91: КА-10 | G91: Стальной панельный радиатор, гигиеническое исполнение Royal Thermо H 20-0400-1000 (тепловая мощность1,2199 кВт) | H91: ШТ | I91: 1 | J91: 0 | K91: 1 | O91: =ROUND(CP91,2) -> 503.29 | P91: =ROUND((ROUND((AC91*AW91*I91),2)*BC91),2) -> 503.29 | Q91: =(ROUND((ROUND(((ET91)*AV91*I91),2)*BB91),2)+ROUND((ROUND(((AE91-(EU91))*AV91*I91),2)*BS91),2)) -> 0 | R91: =(ROUND((ROUND(((EU91)*AV91*I91),2)*BS91),2)+ROUND((ROUND(((AE91-(EU91))*AV91*I91),2)*BS91),2)) -> 0 | S91: =ROUND((ROUND((AF91*AV91*I91),2)*BA91),2) -> 0 | T91: =ROUND(CU91*I91,2) -> 0 | U91: =CV91*I91 -> 0 | V91: =CW91*I91 -> 0 | W91: =ROUND(CX91*I91,2) -> 0 | X91: =(ROUND((((S91+ROUND((ROUND(((EU91)*AV91*I91),2)*BS91),2))*AT91)/100),2)+ROUND(((ROUND((ROUND(((AE91-(EU91))*AV91*I91),2)*BS91),2)*AT91)/100),2)) -> 0 | Y91: =(ROUND((((S91+ROUND((ROUND(((EU91)*AV91*I91),2)*BS91),2))*AU91)/100),2)+ROUND(((ROUND((ROUND(((AE91-(EU91))*AV91*I91),2)*BS91),2)*AU91)/100),2)) -> 0 | AA91: 60255014 | AB91: =ROUND((AC91+AD91+AF91),6) -> 503.29 | AC91: =ROUND((ES91),6) -> 503.29 | AD91: =ROUND((((ET91)-(EU91))+AE91),6) -> 0 | AE91: =ROUND((EU91),6) -> 0 | AF91: =ROUND((EV91),6) -> 0 | AG91: =ROUND((AP91),6) -> 0 | AH91: =(EW91) -> 0 | AI91: =(EX91) -> 0 | AJ91: =(AS91) -> 0 | AK91: 503.29 | AL91: 503.29 | AM91: 0 | AN91: 0 | AO91: 0 | AP91: 0 | AQ91: 0 | AR91: 0 | AS91: 0 | AT91: 0 | AU91: 0 | AV91: 1 | AW91: 1 | AZ91: 1 | BA91: 1 | BB91: 1 | BC91: 1 | BH91: 3 | BI91: 1 | BM91: 400002 | BN91: 0 | BP91: 0 | BQ91: 202 | BR91: 0 | BS91: 1 | BT91: 1 | BU91: 1 | BV91: 1 | BW91: 1 | BX91: 1 | BZ91: 0 | CA91: 0 | CE91: 1566 | CF91: 0 | CG91: 0 | CM91: 0 | CO91: 0 | CP91: =(P91+Q91+S91) -> 503.29 | CQ91: =ROUND((ROUND((AC91*AW91*1),2)*BC91),2) -> 503.29 | CR91: =(ROUND((ROUND(((ET91)*AV91*1),2)*BB91),2)+ROUND((ROUND(((AE91-(EU91))*AV91*1),2)*BS91),2)) -> 0 | CS91: =(ROUND((ROUND(((EU91)*AV91*1),2)*BS91),2)+ROUND((ROUND(((AE91-(EU91))*AV91*1),2)*BS91),2)) -> 0 | CT91: =ROUND((ROUND((AF91*AV91*1),2)*BA91),2) -> 0 | CU91: =AG91 -> 0 | CV91: =(AH91*AV91) -> 0 | CW91: =AI91 -> 0 | CX91: =AJ91 -> 0 | CY91: =(ROUND((((S91+ROUND((ROUND(((EU91)*AV91*1),2)*BS91),2))*AT91)/100),2)+ROUND(((ROUND((ROUND(((AE91-(EU91))*AV91*1),2)*BS91),2)*AT91)/100),2)) -> 0 | CZ91: =(ROUND((((S91+ROUND((ROUND(((EU91)*AV91*1),2)*BS91),2))*AU91)/100),2)+ROUND(((ROUND((ROUND(((AE91-(EU91))*AV91*1),2)*BS91),2)*AU91)/100),2)) -> 0 | DN91: 0 | DO91: 0 | DP91: 1 | DQ91: 1 | DU91: 1013 | DV91: ШТ | DW91: ШТ | DX91: 1 | EE91: 60088211 | EF91: 202 | EG91: Материалы | EH91: 0 | EJ91: 1 | EK91: 400002 | EL91: Материалы, изделия и конструкции | EM91: Материалы | EQ91: 0 | ER91: 0 | ES91: 503.29 | ET91: 0 | EU91: 0 | EV91: 0 | EW91: 0 | EX91: 0 | EY91: 0 | FQ91: 0 | FR91: 0 | FS91: 0 | FX91: 0 | FY91: 0 | GA91: [5 850 / 1,2 / 9,88] + 2% Заг.скл | GD91: 1 | GF91: -837258373 | GG91: 2 | GH91: 4 | GI91: -2 | GJ91: 0 | GK91: 0 | GL91: =ROUND(IF(AND(BH91=3,BI91=3,FS91<>0),P91,0),2) -> 0 | GM91: =ROUND(O91+X91+Y91,2)+GX91 -> 503.29 | GN91: =IF(OR(BI91=0,BI91=1),GM91-GX91,0) -> 503.29 | GO91: =IF(BI91=2,GM91-GX91,0) -> 0 | GP91: =IF(BI91=4,GM91-GX91,0) -> 0 | GR91: 0 | GS91: 2 | GT91: 0 | GV91: =ROUND((GT91),6) -> 0 | GW91: 1 | GX91: =ROUND(HC91*I91,2) -> 0 | HA91: 0 | HB91: 0 | HC91: =GV91*GW91 -> 0 | HE91: 0 | HF91: 2 | HS91: 0 | IK91: 0
A92: 17 | B92: 1 | E92: 15 | F92: КА-10 | G92: Стальной панельный радиатор, гигиеническое исполнение Royal Thermо H 20-0400-1000 (тепловая мощность1,2199 кВт) | H92: ШТ | I92: 1 | J92: 0 | K92: 1 | O92: =ROUND(CP92,2) -> 4972.51 | P92: =ROUND((ROUND((AC92*AW92*I92),2)*BC92),2) -> 4972.51 | Q92: =(ROUND((ROUND(((ET92)*AV92*I92),2)*BB92),2)+ROUND((ROUND(((AE92-(EU92))*AV92*I92),2)*BS92),2)) -> 0 | R92: =(ROUND((ROUND(((EU92)*AV92*I92),2)*BS92),2)+ROUND((ROUND(((AE92-(EU92))*AV92*I92),2)*BS92),2)) -> 0 | S92: =ROUND((ROUND((AF92*AV92*I92),2)*BA92),2) -> 0 | T92: =ROUND(CU92*I92,2) -> 0 | U92: =CV92*I92 -> 0 | V92: =CW92*I92 -> 0 | W92: =ROUND(CX92*I92,2) -> 0 | X92: =(ROUND((((S92+ROUND((ROUND(((EU92)*AV92*I92),2)*BS92),2))*AT92)/100),2)+ROUND(((ROUND((ROUND(((AE92-(EU92))*AV92*I92),2)*BS92),2)*AT92)/100),2)) -> 0 | Y92: =(ROUND((((S92+ROUND((ROUND(((EU92)*AV92*I92),2)*BS92),2))*AU92)/100),2)+ROUND(((ROUND((ROUND(((AE92-(EU92))*AV92*I92),2)*BS92),2)*AU92)/100),2)) -> 0 | AA92: 60255011 | AB92: =ROUND((AC92+AD92+AF92),6) -> 503.29 | AC92: =ROUND((ES92),6) -> 503.29 | AD92: =ROUND((((ET92)-(EU92))+AE92),6) -> 0 | AE92: =ROUND((EU92),6) -> 0 | AF92: =ROUND((EV92),6) -> 0 | AG92: =ROUND((AP92),6) -> 0 | AH92: =(EW92) -> 0 | AI92: =(EX92) -> 0 | AJ92: =(AS92) -> 0 | AK92: 503.29 | AL92: 503.29 | AM92: 0 | AN92: 0 | AO92: 0 | AP92: 0 | AQ92: 0 | AR92: 0 | AS92: 0 | AT92: 0 | AU92: 0 | AV92: 1 | AW92: 1 | AZ92: 1 | BA92: 1 | BB92: 1 | BC92: 9.88 | BH92: 3 | BI92: 1 | BM92: 400002 | BN92: 0 | BP92: 0 | BQ92: 202 | BR92: 0 | BS92: 1 | BT92: 1 | BU92: 1 | BV92: 1 | BW92: 1 | BX92: 1 | BZ92: 0 | CA92: 0 | CE92: 1566 | CF92: 0 | CG92: 0 | CM92: 0 | CO92: 0 | CP92: =(P92+Q92+S92) -> 4972.51 | CQ92: =ROUND((ROUND((AC92*AW92*1),2)*BC92),2) -> 4972.51 | CR92: =(ROUND((ROUND(((ET92)*AV92*1),2)*BB92),2)+ROUND((ROUND(((AE92-(EU92))*AV92*1),2)*BS92),2)) -> 0 | CS92: =(ROUND((ROUND(((EU92)*AV92*1),2)*BS92),2)+ROUND((ROUND(((AE92-(EU92))*AV92*1),2)*BS92),2)) -> 0 | CT92: =ROUND((ROUND((AF92*AV92*1),2)*BA92),2) -> 0 | CU92: =AG92 -> 0 | CV92: =(AH92*AV92) -> 0 | CW92: =AI92 -> 0 | CX92: =AJ92 -> 0 | CY92: =(ROUND((((S92+ROUND((ROUND(((EU92)*AV92*1),2)*BS92),2))*AT92)/100),2)+ROUND(((ROUND((ROUND(((AE92-(EU92))*AV92*1),2)*BS92),2)*AT92)/100),2)) -> 0 | CZ92: =(ROUND((((S92+ROUND((ROUND(((EU92)*AV92*1),2)*BS92),2))*AU92)/100),2)+ROUND(((ROUND((ROUND(((AE92-(EU92))*AV92*1),2)*BS92),2)*AU92)/100),2)) -> 0 | DN92: 0 | DO92: 0 | DP92: 1 | DQ92: 1 | DU92: 1013 | DV92: ШТ | DW92: ШТ | DX92: 1 | EE92: 60088211 | EF92: 202 | EG92: Материалы | EH92: 0 | EJ92: 1 | EK92: 400002 | EL92: Материалы, изделия и конструкции | EM92: Материалы | EQ92: 0 | ER92: 503.29 | ES92: 503.29 | ET92: 0 | EU92: 0 | EV92: 0 | EW92: 0 | EX92: 0 | EY92: 0 | EZ92: 5 | FC92: 1 | FD92: 18 | FF92: 5850 | FQ92: 0 | FR92: 0 | FS92: 0 | FX92: 0 | FY92: 0 | GA92: [5 850 / 1,2 / 9,88] + 2% Заг.скл | GD92: 1 | GF92: -837258373 | GG92: 2 | GH92: 3 | GI92: 5 | GJ92: 0 | GK92: 0 | GL92: =ROUND(IF(AND(BH92=3,BI92=3,FS92<>0),P92,0),2) -> 0 | GM92: =ROUND(O92+X92+Y92,2)+GX92 -> 4972.51 | GN92: =IF(OR(BI92=0,BI92=1),GM92-GX92,0) -> 4972.51 | GO92: =IF(BI92=2,GM92-GX92,0) -> 0 | GP92: =IF(BI92=4,GM92-GX92,0) -> 0 | GR92: 1 | GS92: 1 | GT92: 0 | GV92: =ROUND((GT92),6) -> 0 | GW92: 1 | GX92: =ROUND(HC92*I92,2) -> 0 | HA92: 0 | HB92: 0 | HC92: =GV92*GW92 -> 0 | HE92: 0 | HF92: 2 | HS92: 0 | IK92: 0
A93: 17 | B93: 1 | E93: 16 | F93: КА-11 | G93: Стальной панельный радиатор, гигиеническое исполнение Royal Thermо H 20-0400-1200 (тепловая мощность 1,4639 кВт) | H93: ШТ | I93: 3 | J93: 0 | K93: 3 | O93: =ROUND(CP93,2) -> 1716.36 | P93: =ROUND((ROUND((AC93*AW93*I93),2)*BC93),2) -> 1716.36 | Q93: =(ROUND((ROUND(((ET93)*AV93*I93),2)*BB93),2)+ROUND((ROUND(((AE93-(EU93))*AV93*I93),2)*BS93),2)) -> 0 | R93: =(ROUND((ROUND(((EU93)*AV93*I93),2)*BS93),2)+ROUND((ROUND(((AE93-(EU93))*AV93*I93),2)*BS93),2)) -> 0 | S93: =ROUND((ROUND((AF93*AV93*I93),2)*BA93),2) -> 0 | T93: =ROUND(CU93*I93,2) -> 0 | U93: =CV93*I93 -> 0 | V93: =CW93*I93 -> 0 | W93: =ROUND(CX93*I93,2) -> 0 | X93: =(ROUND((((S93+ROUND((ROUND(((EU93)*AV93*I93),2)*BS93),2))*AT93)/100),2)+ROUND(((ROUND((ROUND(((AE93-(EU93))*AV93*I93),2)*BS93),2)*AT93)/100),2)) -> 0 | Y93: =(ROUND((((S93+ROUND((ROUND(((EU93)*AV93*I93),2)*BS93),2))*AU93)/100),2)+ROUND(((ROUND((ROUND(((AE93-(EU93))*AV93*I93),2)*BS93),2)*AU93)/100),2)) -> 0 | AA93: 60255014 | AB93: =ROUND((AC93+AD93+AF93),6) -> 572.12 | AC93: =ROUND((ES93),6) -> 572.12 | AD93: =ROUND((((ET93)-(EU93))+AE93),6) -> 0 | AE93: =ROUND((EU93),6) -> 0 | AF93: =ROUND((EV93),6) -> 0 | AG93: =ROUND((AP93),6) -> 0 | AH93: =(EW93) -> 0 | AI93: =(EX93) -> 0 | AJ93: =(AS93) -> 0 | AK93: 572.12 | AL93: 572.12 | AM93: 0 | AN93: 0 | AO93: 0 | AP93: 0 | AQ93: 0 | AR93: 0 | AS93: 0 | AT93: 0 | AU93: 0 | AV93: 1 | AW93: 1 | AZ93: 1 | BA93: 1 | BB93: 1 | BC93: 1 | BH93: 3 | BI93: 1 | BM93: 400002 | BN93: 0 | BP93: 0 | BQ93: 202 | BR93: 0 | BS93: 1 | BT93: 1 | BU93: 1 | BV93: 1 | BW93: 1 | BX93: 1 | BZ93: 0 | CA93: 0 | CE93: 1566 | CF93: 0 | CG93: 0 | CM93: 0 | CO93: 0 | CP93: =(P93+Q93+S93) -> 1716.36 | CQ93: =ROUND((ROUND((AC93*AW93*1),2)*BC93),2) -> 572.12 | CR93: =(ROUND((ROUND(((ET93)*AV93*1),2)*BB93),2)+ROUND((ROUND(((AE93-(EU93))*AV93*1),2)*BS93),2)) -> 0 | CS93: =(ROUND((ROUND(((EU93)*AV93*1),2)*BS93),2)+ROUND((ROUND(((AE93-(EU93))*AV93*1),2)*BS93),2)) -> 0 | CT93: =ROUND((ROUND((AF93*AV93*1),2)*BA93),2) -> 0 | CU93: =AG93 -> 0 | CV93: =(AH93*AV93) -> 0 | CW93: =AI93 -> 0 | CX93: =AJ93 -> 0 | CY93: =(ROUND((((S93+ROUND((ROUND(((EU93)*AV93*1),2)*BS93),2))*AT93)/100),2)+ROUND(((ROUND((ROUND(((AE93-(EU93))*AV93*1),2)*BS93),2)*AT93)/100),2)) -> 0 | CZ93: =(ROUND((((S93+ROUND((ROUND(((EU93)*AV93*1),2)*BS93),2))*AU93)/100),2)+ROUND(((ROUND((ROUND(((AE93-(EU93))*AV93*1),2)*BS93),2)*AU93)/100),2)) -> 0 | DN93: 0 | DO93: 0 | DP93: 1 | DQ93: 1 | DU93: 1013 | DV93: ШТ | DW93: ШТ | DX93: 1 | EE93: 60088211 | EF93: 202 | EG93: Материалы | EH93: 0 | EJ93: 1 | EK93: 400002 | EL93: Материалы, изделия и конструкции | EM93: Материалы | EQ93: 0 | ER93: 0 | ES93: 572.12 | ET93: 0 | EU93: 0 | EV93: 0 | EW93: 0 | EX93: 0 | EY93: 0 | FQ93: 0 | FR93: 0 | FS93: 0 | FX93: 0 | FY93: 0 | GA93: [6 650 / 1,2 / 9,88] + 2% Заг.скл | GD93: 1 | GF93: 1061292250 | GG93: 2 | GH93: 4 | GI93: -2 | GJ93: 0 | GK93: 0 | GL93: =ROUND(IF(AND(BH93=3,BI93=3,FS93<>0),P93,0),2) -> 0 | GM93: =ROUND(O93+X93+Y93,2)+GX93 -> 1716.36 | GN93: =IF(OR(BI93=0,BI93=1),GM93-GX93,0) -> 1716.36 | GO93: =IF(BI93=2,GM93-GX93,0) -> 0 | GP93: =IF(BI93=4,GM93-GX93,0) -> 0 | GR93: 0 | GS93: 2 | GT93: 0 | GV93: =ROUND((GT93),6) -> 0 | GW93: 1 | GX93: =ROUND(HC93*I93,2) -> 0 | HA93: 0 | HB93: 0 | HC93: =GV93*GW93 -> 0 | HE93: 0 | HF93: 2 | HS93: 0 | IK93: 0
A94: 17 | B94: 1 | E94: 16 | F94: КА-11 | G94: Стальной панельный радиатор, гигиеническое исполнение Royal Thermо H 20-0400-1200 (тепловая мощность 1,4639 кВт) | H94: ШТ | I94: 3 | J94: 0 | K94: 3 | O94: =ROUND(CP94,2) -> 16957.64 | P94: =ROUND((ROUND((AC94*AW94*I94),2)*BC94),2) -> 16957.64 | Q94: =(ROUND((ROUND(((ET94)*AV94*I94),2)*BB94),2)+ROUND((ROUND(((AE94-(EU94))*AV94*I94),2)*BS94),2)) -> 0 | R94: =(ROUND((ROUND(((EU94)*AV94*I94),2)*BS94),2)+ROUND((ROUND(((AE94-(EU94))*AV94*I94),2)*BS94),2)) -> 0 | S94: =ROUND((ROUND((AF94*AV94*I94),2)*BA94),2) -> 0 | T94: =ROUND(CU94*I94,2) -> 0 | U94: =CV94*I94 -> 0 | V94: =CW94*I94 -> 0 | W94: =ROUND(CX94*I94,2) -> 0 | X94: =(ROUND((((S94+ROUND((ROUND(((EU94)*AV94*I94),2)*BS94),2))*AT94)/100),2)+ROUND(((ROUND((ROUND(((AE94-(EU94))*AV94*I94),2)*BS94),2)*AT94)/100),2)) -> 0 | Y94: =(ROUND((((S94+ROUND((ROUND(((EU94)*AV94*I94),2)*BS94),2))*AU94)/100),2)+ROUND(((ROUND((ROUND(((AE94-(EU94))*AV94*I94),2)*BS94),2)*AU94)/100),2)) -> 0 | AA94: 60255011 | AB94: =ROUND((AC94+AD94+AF94),6) -> 572.12 | AC94: =ROUND((ES94),6) -> 572.12 | AD94: =ROUND((((ET94)-(EU94))+AE94),6) -> 0 | AE94: =ROUND((EU94),6) -> 0 | AF94: =ROUND((EV94),6) -> 0 | AG94: =ROUND((AP94),6) -> 0 | AH94: =(EW94) -> 0 | AI94: =(EX94) -> 0 | AJ94: =(AS94) -> 0 | AK94: 572.12 | AL94: 572.12 | AM94: 0 | AN94: 0 | AO94: 0 | AP94: 0 | AQ94: 0 | AR94: 0 | AS94: 0 | AT94: 0 | AU94: 0 | AV94: 1 | AW94: 1 | AZ94: 1 | BA94: 1 | BB94: 1 | BC94: 9.88 | BH94: 3 | BI94: 1 | BM94: 400002 | BN94: 0 | BP94: 0 | BQ94: 202 | BR94: 0 | BS94: 1 | BT94: 1 | BU94: 1 | BV94: 1 | BW94: 1 | BX94: 1 | BZ94: 0 | CA94: 0 | CE94: 1566 | CF94: 0 | CG94: 0 | CM94: 0 | CO94: 0 | CP94: =(P94+Q94+S94) -> 16957.64 | CQ94: =ROUND((ROUND((AC94*AW94*1),2)*BC94),2) -> 5652.55 | CR94: =(ROUND((ROUND(((ET94)*AV94*1),2)*BB94),2)+ROUND((ROUND(((AE94-(EU94))*AV94*1),2)*BS94),2)) -> 0 | CS94: =(ROUND((ROUND(((EU94)*AV94*1),2)*BS94),2)+ROUND((ROUND(((AE94-(EU94))*AV94*1),2)*BS94),2)) -> 0 | CT94: =ROUND((ROUND((AF94*AV94*1),2)*BA94),2) -> 0 | CU94: =AG94 -> 0 | CV94: =(AH94*AV94) -> 0 | CW94: =AI94 -> 0 | CX94: =AJ94 -> 0 | CY94: =(ROUND((((S94+ROUND((ROUND(((EU94)*AV94*1),2)*BS94),2))*AT94)/100),2)+ROUND(((ROUND((ROUND(((AE94-(EU94))*AV94*1),2)*BS94),2)*AT94)/100),2)) -> 0 | CZ94: =(ROUND((((S94+ROUND((ROUND(((EU94)*AV94*1),2)*BS94),2))*AU94)/100),2)+ROUND(((ROUND((ROUND(((AE94-(EU94))*AV94*1),2)*BS94),2)*AU94)/100),2)) -> 0 | DN94: 0 | DO94: 0 | DP94: 1 | DQ94: 1 | DU94: 1013 | DV94: ШТ | DW94: ШТ | DX94: 1 | EE94: 60088211 | EF94: 202 | EG94: Материалы | EH94: 0 | EJ94: 1 | EK94: 400002 | EL94: Материалы, изделия и конструкции | EM94: Материалы | EQ94: 0 | ER94: 572.12 | ES94: 572.12 | ET94: 0 | EU94: 0 | EV94: 0 | EW94: 0 | EX94: 0 | EY94: 0 | EZ94: 5 | FC94: 1 | FD94: 18 | FF94: 6650 | FQ94: 0 | FR94: 0 | FS94: 0 | FX94: 0 | FY94: 0 | GA94: [6 650 / 1,2 / 9,88] + 2% Заг.скл | GD94: 1 | GF94: 1061292250 | GG94: 2 | GH94: 3 | GI94: 5 | GJ94: 0 | GK94: 0 | GL94: =ROUND(IF(AND(BH94=3,BI94=3,FS94<>0),P94,0),2) -> 0 | GM94: =ROUND(O94+X94+Y94,2)+GX94 -> 16957.64 | GN94: =IF(OR(BI94=0,BI94=1),GM94-GX94,0) -> 16957.64 | GO94: =IF(BI94=2,GM94-GX94,0) -> 0 | GP94: =IF(BI94=4,GM94-GX94,0) -> 0 | GR94: 1 | GS94: 1 | GT94: 0 | GV94: =ROUND((GT94),6) -> 0 | GW94: 1 | GX94: =ROUND(HC94*I94,2) -> 0 | HA94: 0 | HB94: 0 | HC94: =GV94*GW94 -> 0 | HE94: 0 | HF94: 2 | HS94: 0 | IK94: 0
A95: 17 | B95: 1 | E95: 17 | F95: КА-12 | G95: Стальной панельный радиатор, гигиеническое исполнение Royal Thermо H 20-0400-1400 (тепловая мощность 1,7079 кВт) | H95: ШТ | I95: 2 | J95: 0 | K95: 2 | O95: =ROUND(CP95,2) -> 1288.78 | P95: =ROUND((ROUND((AC95*AW95*I95),2)*BC95),2) -> 1288.78 | Q95: =(ROUND((ROUND(((ET95)*AV95*I95),2)*BB95),2)+ROUND((ROUND(((AE95-(EU95))*AV95*I95),2)*BS95),2)) -> 0 | R95: =(ROUND((ROUND(((EU95)*AV95*I95),2)*BS95),2)+ROUND((ROUND(((AE95-(EU95))*AV95*I95),2)*BS95),2)) -> 0 | S95: =ROUND((ROUND((AF95*AV95*I95),2)*BA95),2) -> 0 | T95: =ROUND(CU95*I95,2) -> 0 | U95: =CV95*I95 -> 0 | V95: =CW95*I95 -> 0 | W95: =ROUND(CX95*I95,2) -> 0 | X95: =(ROUND((((S95+ROUND((ROUND(((EU95)*AV95*I95),2)*BS95),2))*AT95)/100),2)+ROUND(((ROUND((ROUND(((AE95-(EU95))*AV95*I95),2)*BS95),2)*AT95)/100),2)) -> 0 | Y95: =(ROUND((((S95+ROUND((ROUND(((EU95)*AV95*I95),2)*BS95),2))*AU95)/100),2)+ROUND(((ROUND((ROUND(((AE95-(EU95))*AV95*I95),2)*BS95),2)*AU95)/100),2)) -> 0 | AA95: 60255014 | AB95: =ROUND((AC95+AD95+AF95),6) -> 644.39 | AC95: =ROUND((ES95),6) -> 644.39 | AD95: =ROUND((((ET95)-(EU95))+AE95),6) -> 0 | AE95: =ROUND((EU95),6) -> 0 | AF95: =ROUND((EV95),6) -> 0 | AG95: =ROUND((AP95),6) -> 0 | AH95: =(EW95) -> 0 | AI95: =(EX95) -> 0 | AJ95: =(AS95) -> 0 | AK95: 644.39 | AL95: 644.39 | AM95: 0 | AN95: 0 | AO95: 0 | AP95: 0 | AQ95: 0 | AR95: 0 | AS95: 0 | AT95: 0 | AU95: 0 | AV95: 1 | AW95: 1 | AZ95: 1 | BA95: 1 | BB95: 1 | BC95: 1 | BH95: 3 | BI95: 1 | BM95: 400002 | BN95: 0 | BP95: 0 | BQ95: 202 | BR95: 0 | BS95: 1 | BT95: 1 | BU95: 1 | BV95: 1 | BW95: 1 | BX95: 1 | BZ95: 0 | CA95: 0 | CE95: 1566 | CF95: 0 | CG95: 0 | CM95: 0 | CO95: 0 | CP95: =(P95+Q95+S95) -> 1288.78 | CQ95: =ROUND((ROUND((AC95*AW95*1),2)*BC95),2) -> 644.39 | CR95: =(ROUND((ROUND(((ET95)*AV95*1),2)*BB95),2)+ROUND((ROUND(((AE95-(EU95))*AV95*1),2)*BS95),2)) -> 0 | CS95: =(ROUND((ROUND(((EU95)*AV95*1),2)*BS95),2)+ROUND((ROUND(((AE95-(EU95))*AV95*1),2)*BS95),2)) -> 0 | CT95: =ROUND((ROUND((AF95*AV95*1),2)*BA95),2) -> 0 | CU95: =AG95 -> 0 | CV95: =(AH95*AV95) -> 0 | CW95: =AI95 -> 0 | CX95: =AJ95 -> 0 | CY95: =(ROUND((((S95+ROUND((ROUND(((EU95)*AV95*1),2)*BS95),2))*AT95)/100),2)+ROUND(((ROUND((ROUND(((AE95-(EU95))*AV95*1),2)*BS95),2)*AT95)/100),2)) -> 0 | CZ95: =(ROUND((((S95+ROUND((ROUND(((EU95)*AV95*1),2)*BS95),2))*AU95)/100),2)+ROUND(((ROUND((ROUND(((AE95-(EU95))*AV95*1),2)*BS95),2)*AU95)/100),2)) -> 0 | DN95: 0 | DO95: 0 | DP95: 1 | DQ95: 1 | DU95: 1013 | DV95: ШТ | DW95: ШТ | DX95: 1 | EE95: 60088211 | EF95: 202 | EG95: Материалы | EH95: 0 | EJ95: 1 | EK95: 400002 | EL95: Материалы, изделия и конструкции | EM95: Материалы | EQ95: 0 | ER95: 0 | ES95: 644.39 | ET95: 0 | EU95: 0 | EV95: 0 | EW95: 0 | EX95: 0 | EY95: 0 | FQ95: 0 | FR95: 0 | FS95: 0 | FX95: 0 | FY95: 0 | GA95: [7 490 / 1,2 / 9,88] + 2% Заг.скл | GD95: 1 | GF95: 694050816 | GG95: 2 | GH95: 4 | GI95: -2 | GJ95: 0 | GK95: 0 | GL95: =ROUND(IF(AND(BH95=3,BI95=3,FS95<>0),P95,0),2) -> 0 | GM95: =ROUND(O95+X95+Y95,2)+GX95 -> 1288.78 | GN95: =IF(OR(BI95=0,BI95=1),GM95-GX95,0) -> 1288.78 | GO95: =IF(BI95=2,GM95-GX95,0) -> 0 | GP95: =IF(BI95=4,GM95-GX95,0) -> 0 | GR95: 0 | GS95: 2 | GT95: 0 | GV95: =ROUND((GT95),6) -> 0 | GW95: 1 | GX95: =ROUND(HC95*I95,2) -> 0 | HA95: 0 | HB95: 0 | HC95: =GV95*GW95 -> 0 | HE95: 0 | HF95: 2 | HS95: 0 | IK95: 0
A96: 17 | B96: 1 | E96: 17 | F96: КА-12 | G96: Стальной панельный радиатор, гигиеническое исполнение Royal Thermо H 20-0400-1400 (тепловая мощность 1,7079 кВт) | H96: ШТ | I96: 2 | J96: 0 | K96: 2 | O96: =ROUND(CP96,2) -> 12733.15 | P96: =ROUND((ROUND((AC96*AW96*I96),2)*BC96),2) -> 12733.15 | Q96: =(ROUND((ROUND(((ET96)*AV96*I96),2)*BB96),2)+ROUND((ROUND(((AE96-(EU96))*AV96*I96),2)*BS96),2)) -> 0 | R96: =(ROUND((ROUND(((EU96)*AV96*I96),2)*BS96),2)+ROUND((ROUND(((AE96-(EU96))*AV96*I96),2)*BS96),2)) -> 0 | S96: =ROUND((ROUND((AF96*AV96*I96),2)*BA96),2) -> 0 | T96: =ROUND(CU96*I96,2) -> 0 | U96: =CV96*I96 -> 0 | V96: =CW96*I96 -> 0 | W96: =ROUND(CX96*I96,2) -> 0 | X96: =(ROUND((((S96+ROUND((ROUND(((EU96)*AV96*I96),2)*BS96),2))*AT96)/100),2)+ROUND(((ROUND((ROUND(((AE96-(EU96))*AV96*I96),2)*BS96),2)*AT96)/100),2)) -> 0 | Y96: =(ROUND((((S96+ROUND((ROUND(((EU96)*AV96*I96),2)*BS96),2))*AU96)/100),2)+ROUND(((ROUND((ROUND(((AE96-(EU96))*AV96*I96),2)*BS96),2)*AU96)/100),2)) -> 0 | AA96: 60255011 | AB96: =ROUND((AC96+AD96+AF96),6) -> 644.39 | AC96: =ROUND((ES96),6) -> 644.39 | AD96: =ROUND((((ET96)-(EU96))+AE96),6) -> 0 | AE96: =ROUND((EU96),6) -> 0 | AF96: =ROUND((EV96),6) -> 0 | AG96: =ROUND((AP96),6) -> 0 | AH96: =(EW96) -> 0 | AI96: =(EX96) -> 0 | AJ96: =(AS96) -> 0 | AK96: 644.39 | AL96: 644.39 | AM96: 0 | AN96: 0 | AO96: 0 | AP96: 0 | AQ96: 0 | AR96: 0 | AS96: 0 | AT96: 0 | AU96: 0 | AV96: 1 | AW96: 1 | AZ96: 1 | BA96: 1 | BB96: 1 | BC96: 9.88 | BH96: 3 | BI96: 1 | BM96: 400002 | BN96: 0 | BP96: 0 | BQ96: 202 | BR96: 0 | BS96: 1 | BT96: 1 | BU96: 1 | BV96: 1 | BW96: 1 | BX96: 1 | BZ96: 0 | CA96: 0 | CE96: 1566 | CF96: 0 | CG96: 0 | CM96: 0 | CO96: 0 | CP96: =(P96+Q96+S96) -> 12733.15 | CQ96: =ROUND((ROUND((AC96*AW96*1),2)*BC96),2) -> 6366.57 | CR96: =(ROUND((ROUND(((ET96)*AV96*1),2)*BB96),2)+ROUND((ROUND(((AE96-(EU96))*AV96*1),2)*BS96),2)) -> 0 | CS96: =(ROUND((ROUND(((EU96)*AV96*1),2)*BS96),2)+ROUND((ROUND(((AE96-(EU96))*AV96*1),2)*BS96),2)) -> 0 | CT96: =ROUND((ROUND((AF96*AV96*1),2)*BA96),2) -> 0 | CU96: =AG96 -> 0 | CV96: =(AH96*AV96) -> 0 | CW96: =AI96 -> 0 | CX96: =AJ96 -> 0 | CY96: =(ROUND((((S96+ROUND((ROUND(((EU96)*AV96*1),2)*BS96),2))*AT96)/100),2)+ROUND(((ROUND((ROUND(((AE96-(EU96))*AV96*1),2)*BS96),2)*AT96)/100),2)) -> 0 | CZ96: =(ROUND((((S96+ROUND((ROUND(((EU96)*AV96*1),2)*BS96),2))*AU96)/100),2)+ROUND(((ROUND((ROUND(((AE96-(EU96))*AV96*1),2)*BS96),2)*AU96)/100),2)) -> 0 | DN96: 0 | DO96: 0 | DP96: 1 | DQ96: 1 | DU96: 1013 | DV96: ШТ | DW96: ШТ | DX96: 1 | EE96: 60088211 | EF96: 202 | EG96: Материалы | EH96: 0 | EJ96: 1 | EK96: 400002 | EL96: Материалы, изделия и конструкции | EM96: Материалы | EQ96: 0 | ER96: 644.39 | ES96: 644.39 | ET96: 0 | EU96: 0 | EV96: 0 | EW96: 0 | EX96: 0 | EY96: 0 | EZ96: 5 | FC96: 1 | FD96: 18 | FF96: 7490 | FQ96: 0 | FR96: 0 | FS96: 0 | FX96: 0 | FY96: 0 | GA96: [7 490 / 1,2 / 9,88] + 2% Заг.скл | GD96: 1 | GF96: 694050816 | GG96: 2 | GH96: 3 | GI96: 5 | GJ96: 0 | GK96: 0 | GL96: =ROUND(IF(AND(BH96=3,BI96=3,FS96<>0),P96,0),2) -> 0 | GM96: =ROUND(O96+X96+Y96,2)+GX96 -> 12733.15 | GN96: =IF(OR(BI96=0,BI96=1),GM96-GX96,0) -> 12733.15 | GO96: =IF(BI96=2,GM96-GX96,0) -> 0 | GP96: =IF(BI96=4,GM96-GX96,0) -> 0 | GR96: 1 | GS96: 1 | GT96: 0 | GV96: =ROUND((GT96),6) -> 0 | GW96: 1 | GX96: =ROUND(HC96*I96,2) -> 0 | HA96: 0 | HB96: 0 | HC96: =GV96*GW96 -> 0 | HE96: 0 | HF96: 2 | HS96: 0 | IK96: 0
A97: 17 | B97: 1 | C97: =ROW(SmtRes!A58) -> 58 | D97: =ROW(EtalonRes!A65) -> 65 | E97: 18 | F97: 3.18-25-1 | G97: Установка радиаторов стальных панельных однорядных с креплением к стене длиной до 1600 мм | H97: 100 шт. | I97: =ROUND((1+5+8+2)/100,9) -> 0.16 | J97: 0 | K97: =ROUND((1+5+8+2)/100,9) -> 0.16 | O97: =ROUND(CP97,2) -> 552.95 | P97: =ROUND((ROUND((AC97*AW97*I97),2)*BC97),2) -> 332.62 | Q97: =(ROUND((ROUND(((((ET97*1.25)*1.1))*AV97*I97),2)*BB97),2)+ROUND((ROUND(((AE97-(((EU97*1.25)*1.1)))*AV97*I97),2)*BS97),2)) -> 22.38 | R97: =(ROUND((ROUND(((((EU97*1.25)*1.1))*AV97*I97),2)*BS97),2)+ROUND((ROUND(((AE97-(((EU97*1.25)*1.1)))*AV97*I97),2)*BS97),2)) -> 2.42 | S97: =ROUND((ROUND((AF97*AV97*I97),2)*BA97),2) -> 197.95 | T97: =ROUND(CU97*I97,2) -> 0 | U97: =CV97*I97 -> 16.132272 | V97: =CW97*I97 -> 0 | W97: =ROUND(CX97*I97,2) -> 0 | X97: =(ROUND((((S97+ROUND((ROUND(((((EU97*1.25)*1.1))*AV97*I97),2)*BS97),2))*AT97)/100),2)+ROUND(((ROUND((ROUND(((AE97-(((EU97*1.25)*1.1)))*AV97*I97),2)*BS97),2)*AT97)/100),2)) -> 218.4 | Y97: =(ROUND((((S97+ROUND((ROUND(((((EU97*1.25)*1.1))*AV97*I97),2)*BS97),2))*AU97)/100),2)+ROUND(((ROUND((ROUND(((AE97-(((EU97*1.25)*1.1)))*AV97*I97),2)*BS97),2)*AU97)/100),2)) -> 122.23 | AA97: 60255014 | AB97: =ROUND((AC97+AD97+AF97),6) -> 3369.5053 | AC97: =ROUND((ES97),6) -> 2078.9 | AD97: =ROUND((((((ET97*1.25)*1.1))-(((EU97*1.25)*1.1)))+AE97),6) -> 131.10625 | AE97: =ROUND((((EU97*1.25)*1.1)),6) -> 14.1625 | AF97: =ROUND((((EV97*1.15)*1.1)),6) -> 1159.499 | AG97: =ROUND((AP97),6) -> 0 | AH97: =(((EW97*1.15)*1.1)) -> 94.4955 | AI97: =(((EX97*1.25)*1.1)) -> 0 | AJ97: =(AS97) -> 0 | AK97: 3090.85 | AL97: 2078.9 | AM97: 95.35 | AN97: 10.3 | AO97: 916.6 | AP97: 0 | AQ97: 74.7 | AR97: 0 | AS97: 0 | AT97: 109 | AU97: 61 | AV97: 1.067 | AW97: 1 | AZ97: 1 | BA97: 1 | BB97: 1 | BC97: 1 | BH97: 0 | BI97: 1 | BJ97: ТСН-2001.3 Доп. 80, Сб. 18, т. 25, поз. 1 | BM97: 23 | BN97: 0 | BO97: 3.18-25-1 | BP97: 1 | BQ97: 30 | BR97: 0 | BS97: 1 | BT97: 1 | BU97: 1 | BV97: 1 | BW97: 1 | BX97: 1 | BZ97: 109 | CA97: 61 | CE97: 1566 | CF97: 0 | CG97: 0 | CM97: 0 | CN97: Поправка: О.П. п.3.4. 6 Наименование: Выполняемые при ремонте и реконструкции работы аналогичные технологическим процессам, характерным для нового строительства и отсутствующим в сборниках на ремонтно-строительные работы Поправка: О.П. п.3.4.30.в Наименование: При применении территориальных сметных нормативов для города Москвы затраты, учитывающие напряженные и стесненные условия производства работ (стесненность, сложность складирования и транспортной логистики и т.п.), исчисляются с применением коэффициентов к затратам труда и заработной плате рабочих, машинистов, времени эксплуатации машин и механизмов, стоимости эксплуатации машин в размере: для объектов, расположенных за пределами Третьего транспортного кольца города Москвы, но в пределах Московской кольцевой автомобильной дороги | CO97: 0 | CP97: =(P97+Q97+S97) -> 552.95 | CQ97: =ROUND((ROUND((AC97*AW97*1),2)*BC97),2) -> 2078.9 | CR97: =(ROUND((ROUND(((((ET97*1.25)*1.1))*AV97*1),2)*BB97),2)+ROUND((ROUND(((AE97-(((EU97*1.25)*1.1)))*AV97*1),2)*BS97),2)) -> 139.89 | CS97: =(ROUND((ROUND(((((EU97*1.25)*1.1))*AV97*1),2)*BS97),2)+ROUND((ROUND(((AE97-(((EU97*1.25)*1.1)))*AV97*1),2)*BS97),2)) -> 15.11 | CT97: =ROUND((ROUND((AF97*AV97*1),2)*BA97),2) -> 1237.19 | CU97: =AG97 -> 0 | CV97: =(AH97*AV97) -> 100.8267 | CW97: =AI97 -> 0 | CX97: =AJ97 -> 0 | CY97: =(ROUND((((S97+ROUND((ROUND(((((EU97*1.25)*1.1))*AV97*1),2)*BS97),2))*AT97)/100),2)+ROUND(((ROUND((ROUND(((AE97-(((EU97*1.25)*1.1)))*AV97*1),2)*BS97),2)*AT97)/100),2)) -> 232.24 | CZ97: =(ROUND((((S97+ROUND((ROUND(((((EU97*1.25)*1.1))*AV97*1),2)*BS97),2))*AU97)/100),2)+ROUND(((ROUND((ROUND(((AE97-(((EU97*1.25)*1.1)))*AV97*1),2)*BS97),2)*AU97)/100),2)) -> 129.97 | DB97: 9 | DE97: *1,25)*1,1 | DF97: *1,25)*1,1 | DG97: *1,15)*1,1 | DI97: *1,15)*1,1 | DJ97: *1,25)*1,1 | DN97: 0 | DO97: 0 | DP97: 1 | DQ97: 1 | DU97: 1010 | DV97: 100 шт. | DW97: 100 шт. | DX97: 100 | EE97: 60088254 | EF97: 30 | EG97: Строительные работы | EH97: 0 | EJ97: 1 | EK97: 23 | EL97: ТСН-2001.3-18. Отопление - внутренние устройства | EM97: ТСН-2001.3-18-1 | EO97: Поправка: О.П. п.3.4. 6 Поправка: О.П. п.3.4.30.в | EQ97: 0 | ER97: 3090.85 | ES97: 2078.9 | ET97: 95.35 | EU97: 10.3 | EV97: 916.6 | EW97: 74.7 | EX97: 0 | EY97: 0 | FQ97: 0 | FR97: 0 | FS97: 0 | FX97: 109 | FY97: 61 | GD97: 1 | GF97: -961949121 | GG97: 2 | GH97: 1 | GI97: 2 | GJ97: 0 | GK97: 0 | GL97: =ROUND(IF(AND(BH97=3,BI97=3,FS97<>0),P97,0),2) -> 0 | GM97: =ROUND(O97+X97+Y97,2)+GX97 -> 893.58 | GN97: =IF(OR(BI97=0,BI97=1),GM97-GX97,0) -> 893.58 | GO97: =IF(BI97=2,GM97-GX97,0) -> 0 | GP97: =IF(BI97=4,GM97-GX97,0) -> 0 | GR97: 0 | GS97: 3 | GT97: 0 | GV97: =ROUND((GT97),6) -> 0 | GW97: 1 | GX97: =ROUND(HC97*I97,2) -> 0 | HA97: 0 | HB97: 0 | HC97: =GV97*GW97 -> 0 | HS97: 0 | IK97: 0
A98: 17 | B98: 1 | C98: =ROW(SmtRes!A68) -> 68 | D98: =ROW(EtalonRes!A76) -> 76 | E98: 18 | F98: 3.18-25-1 | G98: Установка радиаторов стальных панельных однорядных с креплением к стене длиной до 1600 мм | H98: 100 шт. | I98: =ROUND((1+5+8+2)/100,9) -> 0.16 | J98: 0 | K98: =ROUND((1+5+8+2)/100,9) -> 0.16 | O98: =ROUND(CP98,2) -> 18054.63 | P98: =ROUND((ROUND((AC98*AW98*I98),2)*BC98),2) -> 6848.65 | Q98: =(ROUND((ROUND(((((ET98*1.25)*1.1))*AV98*I98),2)*BB98),2)+ROUND((ROUND(((AE98-(((EU98*1.25)*1.1)))*AV98*I98),2)*BS98),2)) -> 320.71 | R98: =(ROUND((ROUND(((((EU98*1.25)*1.1))*AV98*I98),2)*BS98),2)+ROUND((ROUND(((AE98-(((EU98*1.25)*1.1)))*AV98*I98),2)*BS98),2)) -> 133.08 | S98: =ROUND((ROUND((AF98*AV98*I98),2)*BA98),2) -> 10885.27 | T98: =ROUND(CU98*I98,2) -> 0 | U98: =CV98*I98 -> 16.132272 | V98: =CW98*I98 -> 0 | W98: =ROUND(CX98*I98,2) -> 0 | X98: =(ROUND((((S98+ROUND((ROUND(((((EU98*1.25)*1.1))*AV98*I98),2)*BS98),2))*AT98)/100),2)+ROUND(((ROUND((ROUND(((AE98-(((EU98*1.25)*1.1)))*AV98*I98),2)*BS98),2)*AT98)/100),2)) -> 12010 | Y98: =(ROUND((((S98+ROUND((ROUND(((((EU98*1.25)*1.1))*AV98*I98),2)*BS98),2))*AU98)/100),2)+ROUND(((ROUND((ROUND(((AE98-(((EU98*1.25)*1.1)))*AV98*I98),2)*BS98),2)*AU98)/100),2)) -> 6721.19 | AA98: 60255011 | AB98: =ROUND((AC98+AD98+AF98),6) -> 3369.5053 | AC98: =ROUND((ES98),6) -> 2078.9 | AD98: =ROUND((((((ET98*1.25)*1.1))-(((EU98*1.25)*1.1)))+AE98),6) -> 131.10625 | AE98: =ROUND((((EU98*1.25)*1.1)),6) -> 14.1625 | AF98: =ROUND((((EV98*1.15)*1.1)),6) -> 1159.499 | AG98: =ROUND((AP98),6) -> 0 | AH98: =(((EW98*1.15)*1.1)) -> 94.4955 | AI98: =(((EX98*1.25)*1.1)) -> 0 | AJ98: =(AS98) -> 0 | AK98: 3090.85 | AL98: 2078.9 | AM98: 95.35 | AN98: 10.3 | AO98: 916.6 | AP98: 0 | AQ98: 74.7 | AR98: 0 | AS98: 0 | AT98: 109 | AU98: 61 | AV98: 1.067 | AW98: 1 | AZ98: 1 | BA98: 54.99 | BB98: 14.33 | BC98: 20.59 | BH98: 0 | BI98: 1 | BJ98: ТСН-2001.3 Доп. 80, Сб. 18, т. 25, поз. 1 | BM98: 23 | BN98: 0 | BO98: 3.18-25-1 | BP98: 1 | BQ98: 30 | BR98: 0 | BS98: 54.99 | BT98: 1 | BU98: 1 | BV98: 1 | BW98: 1 | BX98: 1 | BZ98: 109 | CA98: 61 | CE98: 1566 | CF98: 0 | CG98: 0 | CM98: 0 | CN98: Поправка: О.П. п.3.4. 6 Наименование: Выполняемые при ремонте и реконструкции работы аналогичные технологическим процессам, характерным для нового строительства и отсутствующим в сборниках на ремонтно-строительные работы Поправка: О.П. п.3.4.30.в Наименование: При применении территориальных сметных нормативов для города Москвы затраты, учитывающие напряженные и стесненные условия производства работ (стесненность, сложность складирования и транспортной логистики и т.п.), исчисляются с применением коэффициентов к затратам труда и заработной плате рабочих, машинистов, времени эксплуатации машин и механизмов, стоимости эксплуатации машин в размере: для объектов, расположенных за пределами Третьего транспортного кольца города Москвы, но в пределах Московской кольцевой автомобильной дороги | CO98: 0 | CP98: =(P98+Q98+S98) -> 18054.63 | CQ98: =ROUND((ROUND((AC98*AW98*1),2)*BC98),2) -> 42804.55 | CR98: =(ROUND((ROUND(((((ET98*1.25)*1.1))*AV98*1),2)*BB98),2)+ROUND((ROUND(((AE98-(((EU98*1.25)*1.1)))*AV98*1),2)*BS98),2)) -> 2004.62 | CS98: =(ROUND((ROUND(((((EU98*1.25)*1.1))*AV98*1),2)*BS98),2)+ROUND((ROUND(((AE98-(((EU98*1.25)*1.1)))*AV98*1),2)*BS98),2)) -> 830.9 | CT98: =ROUND((ROUND((AF98*AV98*1),2)*BA98),2) -> 68033.08 | CU98: =AG98 -> 0 | CV98: =(AH98*AV98) -> 100.8267 | CW98: =AI98 -> 0 | CX98: =AJ98 -> 0 | CY98: =(ROUND((((S98+ROUND((ROUND(((((EU98*1.25)*1.1))*AV98*1),2)*BS98),2))*AT98)/100),2)+ROUND(((ROUND((ROUND(((AE98-(((EU98*1.25)*1.1)))*AV98*1),2)*BS98),2)*AT98)/100),2)) -> 12770.63 | CZ98: =(ROUND((((S98+ROUND((ROUND(((((EU98*1.25)*1.1))*AV98*1),2)*BS98),2))*AU98)/100),2)+ROUND(((ROUND((ROUND(((AE98-(((EU98*1.25)*1.1)))*AV98*1),2)*BS98),2)*AU98)/100),2)) -> 7146.86 | DB98: 11 | DE98: *1,25)*1,1 | DF98: *1,25)*1,1 | DG98: *1,15)*1,1 | DI98: *1,15)*1,1 | DJ98: *1,25)*1,1 | DN98: 0 | DO98: 0 | DP98: 1 | DQ98: 1 | DU98: 1010 | DV98: 100 шт. | DW98: 100 шт. | DX98: 100 | EE98: 60088254 | EF98: 30 | EG98: Строительные работы | EH98: 0 | EJ98: 1 | EK98: 23 | EL98: ТСН-2001.3-18. Отопление - внутренние устройства | EM98: ТСН-2001.3-18-1 | EO98: Поправка: О.П. п.3.4. 6 Поправка: О.П. п.3.4.30.в | EQ98: 0 | ER98: 3090.85 | ES98: 2078.9 | ET98: 95.35 | EU98: 10.3 | EV98: 916.6 | EW98: 74.7 | EX98: 0 | EY98: 0 | FQ98: 0 | FR98: 0 | FS98: 0 | FX98: 109 | FY98: 61 | GD98: 1 | GF98: -961949121 | GG98: 2 | GH98: 1 | GI98: 2 | GJ98: 0 | GK98: 0 | GL98: =ROUND(IF(AND(BH98=3,BI98=3,FS98<>0),P98,0),2) -> 0 | GM98: =ROUND(O98+X98+Y98,2)+GX98 -> 36785.82 | GN98: =IF(OR(BI98=0,BI98=1),GM98-GX98,0) -> 36785.82 | GO98: =IF(BI98=2,GM98-GX98,0) -> 0 | GP98: =IF(BI98=4,GM98-GX98,0) -> 0 | GR98: 0 | GS98: 3 | GT98: 0 | GV98: =ROUND((GT98),6) -> 0 | GW98: 1 | GX98: =ROUND(HC98*I98,2) -> 0 | HA98: 0 | HB98: 0 | HC98: =GV98*GW98 -> 0 | HS98: 0 | IK98: 0
A99: 17 | B99: 1 | E99: 19 | F99: КА-13 | G99: Стальной панельный радиатор, гигиеническое исполнение Royal Thermо H 10-0400-0600 (тепловая мощность 0,4221 кВт) | H99: ШТ | I99: 1 | J99: 0 | K99: 1 | O99: =ROUND(CP99,2) -> 271 | P99: =ROUND((ROUND((AC99*AW99*I99),2)*BC99),2) -> 271 | Q99: =(ROUND((ROUND(((ET99)*AV99*I99),2)*BB99),2)+ROUND((ROUND(((AE99-(EU99))*AV99*I99),2)*BS99),2)) -> 0 | R99: =(ROUND((ROUND(((EU99)*AV99*I99),2)*BS99),2)+ROUND((ROUND(((AE99-(EU99))*AV99*I99),2)*BS99),2)) -> 0 | S99: =ROUND((ROUND((AF99*AV99*I99),2)*BA99),2) -> 0 | T99: =ROUND(CU99*I99,2) -> 0 | U99: =CV99*I99 -> 0 | V99: =CW99*I99 -> 0 | W99: =ROUND(CX99*I99,2) -> 0 | X99: =(ROUND((((S99+ROUND((ROUND(((EU99)*AV99*I99),2)*BS99),2))*AT99)/100),2)+ROUND(((ROUND((ROUND(((AE99-(EU99))*AV99*I99),2)*BS99),2)*AT99)/100),2)) -> 0 | Y99: =(ROUND((((S99+ROUND((ROUND(((EU99)*AV99*I99),2)*BS99),2))*AU99)/100),2)+ROUND(((ROUND((ROUND(((AE99-(EU99))*AV99*I99),2)*BS99),2)*AU99)/100),2)) -> 0 | AA99: 60255014 | AB99: =ROUND((AC99+AD99+AF99),6) -> 271 | AC99: =ROUND((ES99),6) -> 271 | AD99: =ROUND((((ET99)-(EU99))+AE99),6) -> 0 | AE99: =ROUND((EU99),6) -> 0 | AF99: =ROUND((EV99),6) -> 0 | AG99: =ROUND((AP99),6) -> 0 | AH99: =(EW99) -> 0 | AI99: =(EX99) -> 0 | AJ99: =(AS99) -> 0 | AK99: 271 | AL99: 271 | AM99: 0 | AN99: 0 | AO99: 0 | AP99: 0 | AQ99: 0 | AR99: 0 | AS99: 0 | AT99: 0 | AU99: 0 | AV99: 1 | AW99: 1 | AZ99: 1 | BA99: 1 | BB99: 1 | BC99: 1 | BH99: 3 | BI99: 1 | BM99: 400002 | BN99: 0 | BP99: 0 | BQ99: 202 | BR99: 0 | BS99: 1 | BT99: 1 | BU99: 1 | BV99: 1 | BW99: 1 | BX99: 1 | BZ99: 0 | CA99: 0 | CE99: 1566 | CF99: 0 | CG99: 0 | CM99: 0 | CO99: 0 | CP99: =(P99+Q99+S99) -> 271 | CQ99: =ROUND((ROUND((AC99*AW99*1),2)*BC99),2) -> 271 | CR99: =(ROUND((ROUND(((ET99)*AV99*1),2)*BB99),2)+ROUND((ROUND(((AE99-(EU99))*AV99*1),2)*BS99),2)) -> 0 | CS99: =(ROUND((ROUND(((EU99)*AV99*1),2)*BS99),2)+ROUND((ROUND(((AE99-(EU99))*AV99*1),2)*BS99),2)) -> 0 | CT99: =ROUND((ROUND((AF99*AV99*1),2)*BA99),2) -> 0 | CU99: =AG99 -> 0 | CV99: =(AH99*AV99) -> 0 | CW99: =AI99 -> 0 | CX99: =AJ99 -> 0 | CY99: =(ROUND((((S99+ROUND((ROUND(((EU99)*AV99*1),2)*BS99),2))*AT99)/100),2)+ROUND(((ROUND((ROUND(((AE99-(EU99))*AV99*1),2)*BS99),2)*AT99)/100),2)) -> 0 | CZ99: =(ROUND((((S99+ROUND((ROUND(((EU99)*AV99*1),2)*BS99),2))*AU99)/100),2)+ROUND(((ROUND((ROUND(((AE99-(EU99))*AV99*1),2)*BS99),2)*AU99)/100),2)) -> 0 | DN99: 0 | DO99: 0 | DP99: 1 | DQ99: 1 | DU99: 1013 | DV99: ШТ | DW99: ШТ | DX99: 1 | EE99: 60088211 | EF99: 202 | EG99: Материалы | EH99: 0 | EJ99: 1 | EK99: 400002 | EL99: Материалы, изделия и конструкции | EM99: Материалы | EQ99: 0 | ER99: 0 | ES99: 271 | ET99: 0 | EU99: 0 | EV99: 0 | EW99: 0 | EX99: 0 | EY99: 0 | FQ99: 0 | FR99: 0 | FS99: 0 | FX99: 0 | FY99: 0 | GA99: [3 150 / 1,2 / 9,88] + 2% Заг.скл | GD99: 1 | GF99: -1636431227 | GG99: 2 | GH99: 4 | GI99: -2 | GJ99: 0 | GK99: 0 | GL99: =ROUND(IF(AND(BH99=3,BI99=3,FS99<>0),P99,0),2) -> 0 | GM99: =ROUND(O99+X99+Y99,2)+GX99 -> 271 | GN99: =IF(OR(BI99=0,BI99=1),GM99-GX99,0) -> 271 | GO99: =IF(BI99=2,GM99-GX99,0) -> 0 | GP99: =IF(BI99=4,GM99-GX99,0) -> 0 | GR99: 0 | GS99: 2 | GT99: 0 | GV99: =ROUND((GT99),6) -> 0 | GW99: 1 | GX99: =ROUND(HC99*I99,2) -> 0 | HA99: 0 | HB99: 0 | HC99: =GV99*GW99 -> 0 | HE99: 0 | HF99: 2 | HS99: 0 | IK99: 0
A100: 17 | B100: 1 | E100: 19 | F100: КА-13 | G100: Стальной панельный радиатор, гигиеническое исполнение Royal Thermо H 10-0400-0600 (тепловая мощность 0,4221 кВт) | H100: ШТ | I100: 1 | J100: 0 | K100: 1 | O100: =ROUND(CP100,2) -> 2677.48 | P100: =ROUND((ROUND((AC100*AW100*I100),2)*BC100),2) -> 2677.48 | Q100: =(ROUND((ROUND(((ET100)*AV100*I100),2)*BB100),2)+ROUND((ROUND(((AE100-(EU100))*AV100*I100),2)*BS100),2)) -> 0 | R100: =(ROUND((ROUND(((EU100)*AV100*I100),2)*BS100),2)+ROUND((ROUND(((AE100-(EU100))*AV100*I100),2)*BS100),2)) -> 0 | S100: =ROUND((ROUND((AF100*AV100*I100),2)*BA100),2) -> 0 | T100: =ROUND(CU100*I100,2) -> 0 | U100: =CV100*I100 -> 0 | V100: =CW100*I100 -> 0 | W100: =ROUND(CX100*I100,2) -> 0 | X100: =(ROUND((((S100+ROUND((ROUND(((EU100)*AV100*I100),2)*BS100),2))*AT100)/100),2)+ROUND(((ROUND((ROUND(((AE100-(EU100))*AV100*I100),2)*BS100),2)*AT100)/100),2)) -> 0 | Y100: =(ROUND((((S100+ROUND((ROUND(((EU100)*AV100*I100),2)*BS100),2))*AU100)/100),2)+ROUND(((ROUND((ROUND(((AE100-(EU100))*AV100*I100),2)*BS100),2)*AU100)/100),2)) -> 0 | AA100: 60255011 | AB100: =ROUND((AC100+AD100+AF100),6) -> 271 | AC100: =ROUND((ES100),6) -> 271 | AD100: =ROUND((((ET100)-(EU100))+AE100),6) -> 0 | AE100: =ROUND((EU100),6) -> 0 | AF100: =ROUND((EV100),6) -> 0 | AG100: =ROUND((AP100),6) -> 0 | AH100: =(EW100) -> 0 | AI100: =(EX100) -> 0 | AJ100: =(AS100) -> 0 | AK100: 271 | AL100: 271 | AM100: 0 | AN100: 0 | AO100: 0 | AP100: 0 | AQ100: 0 | AR100: 0 | AS100: 0 | AT100: 0 | AU100: 0 | AV100: 1 | AW100: 1 | AZ100: 1 | BA100: 1 | BB100: 1 | BC100: 9.88 | BH100: 3 | BI100: 1 | BM100: 400002 | BN100: 0 | BP100: 0 | BQ100: 202 | BR100: 0 | BS100: 1 | BT100: 1 | BU100: 1 | BV100: 1 | BW100: 1 | BX100: 1 | BZ100: 0 | CA100: 0 | CE100: 1566 | CF100: 0 | CG100: 0 | CM100: 0 | CO100: 0 | CP100: =(P100+Q100+S100) -> 2677.48 | CQ100: =ROUND((ROUND((AC100*AW100*1),2)*BC100),2) -> 2677.48 | CR100: =(ROUND((ROUND(((ET100)*AV100*1),2)*BB100),2)+ROUND((ROUND(((AE100-(EU100))*AV100*1),2)*BS100),2)) -> 0 | CS100: =(ROUND((ROUND(((EU100)*AV100*1),2)*BS100),2)+ROUND((ROUND(((AE100-(EU100))*AV100*1),2)*BS100),2)) -> 0 | CT100: =ROUND((ROUND((AF100*AV100*1),2)*BA100),2) -> 0 | CU100: =AG100 -> 0 | CV100: =(AH100*AV100) -> 0 | CW100: =AI100 -> 0 | CX100: =AJ100 -> 0 | CY100: =(ROUND((((S100+ROUND((ROUND(((EU100)*AV100*1),2)*BS100),2))*AT100)/100),2)+ROUND(((ROUND((ROUND(((AE100-(EU100))*AV100*1),2)*BS100),2)*AT100)/100),2)) -> 0 | CZ100: =(ROUND((((S100+ROUND((ROUND(((EU100)*AV100*1),2)*BS100),2))*AU100)/100),2)+ROUND(((ROUND((ROUND(((AE100-(EU100))*AV100*1),2)*BS100),2)*AU100)/100),2)) -> 0 | DN100: 0 | DO100: 0 | DP100: 1 | DQ100: 1 | DU100: 1013 | DV100: ШТ | DW100: ШТ | DX100: 1 | EE100: 60088211 | EF100: 202 | EG100: Материалы | EH100: 0 | EJ100: 1 | EK100: 400002 | EL100: Материалы, изделия и конструкции | EM100: Материалы | EQ100: 0 | ER100: 271 | ES100: 271 | ET100: 0 | EU100: 0 | EV100: 0 | EW100: 0 | EX100: 0 | EY100: 0 | EZ100: 5 | FC100: 1 | FD100: 18 | FF100: 3150 | FQ100: 0 | FR100: 0 | FS100: 0 | FX100: 0 | FY100: 0 | GA100: [3 150 / 1,2 / 9,88] + 2% Заг.скл | GD100: 1 | GF100: -1636431227 | GG100: 2 | GH100: 3 | GI100: 5 | GJ100: 0 | GK100: 0 | GL100: =ROUND(IF(AND(BH100=3,BI100=3,FS100<>0),P100,0),2) -> 0 | GM100: =ROUND(O100+X100+Y100,2)+GX100 -> 2677.48 | GN100: =IF(OR(BI100=0,BI100=1),GM100-GX100,0) -> 2677.48 | GO100: =IF(BI100=2,GM100-GX100,0) -> 0 | GP100: =IF(BI100=4,GM100-GX100,0) -> 0 | GR100: 1 | GS100: 1 | GT100: 0 | GV100: =ROUND((GT100),6) -> 0 | GW100: 1 | GX100: =ROUND(HC100*I100,2) -> 0 | HA100: 0 | HB100: 0 | HC100: =GV100*GW100 -> 0 | HE100: 0 | HF100: 2 | HS100: 0 | IK100: 0
