Workbook

Sheet 02-01-08
A1: =Source!B1 -> Smeta.RU (495) 974-1589
J2: Форма № 4б
A3: Капитальный ремонт здания Государственного бюджетного общеобразовательного учреждения города Москвы «Школа № 236» по адресу: г. Москва, ул. Клязьминская, д. 7, к. 4. I этап | AP3: Капитальный ремонт здания Государственного бюджетного общеобразовательного учреждения города Москвы «Школа № 236» по адресу: г. Москва, ул. Клязьминская, д. 7, к. 4. I этап. 02-01-08 АПС
A4: (наименование стройки и/или объекта)
A6: =CONCATENATE( "ЛОКАЛЬНАЯ СМЕТА № ",IF(Source!F20<>"Новая локальная смета", Source!F20, "")) -> ЛОКАЛЬНАЯ СМЕТА № 02-01-08
A8: =IF(Source!G20<>"Новая локальная смета", Source!G20, "") -> Автоматическая пожарная сигнализация
A9: (наименование работ и затрат)
A11: =CONCATENATE( "Основание: чертежи № ", Source!J20) -> Основание: чертежи № 2024-00272-01-0-ИОС5.1
I13: В базисном уровне цен | J13: В текущем уровне цен
E14: Сметная стоимость | I14: =I15+I16+I17+I18 -> 426.77 | J14: =J15+J16+J17+J18 -> 8690.28 | K14: тыс.руб.
E15: Строительные работы | I15: =ROUND((Source!F274)/1000, 2) -> 0 | J15: =ROUND((Source!P274)/1000, 2) -> 0 | K15: тыс.руб.
E16: Работы по монтажу оборудования | I16: =ROUND((Source!F275)/1000, 2) -> 185.3 | J16: =ROUND((Source!P275)/1000, 2) -> 6829.43 | K16: тыс.руб.
E17: Оборудование | I17: =ROUND((Source!F266)/1000, 2) -> 241.47 | J17: =ROUND((Source!P266)/1000, 2) -> 1860.85 | K17: тыс.руб.
E18: Прочие работы и затраты | I18: =ROUND((Source!F276+Source!F277)/1000, 2) -> 0 | J18: =ROUND((Source!P276+Source!P277)/1000, 2) -> 0 | K18: тыс.руб.
E19: Средства на оплату труда | I19: =(Source!F272+ Source!F271)/1000 -> 47.25248 | J19: =((Source!P272 + Source!P271)/1000) -> 2598.4139 | K19: тыс.руб.
E20: Затраты труда | I20: =Source!F279 -> 3826.3565 | K20: чел.-ч.
E21: Кроме того:
E22: Возврат материалов | I22: =SUM(Y28:Y332)/1000 -> 0 | J22: =SUM(Z28:Z332)/1000 -> 0 | K22: тыс.руб.
A24: Составлен(а) по ТСН-2001 с учетом Дополнения №: 80
A25: № и период сборника коэффициентов (индексов) пересчета: Коэффициенты к ТСН-2001 МГЭ Дополнение 80, строительство №217/80 III квартал 2025 года и Коэффициенты к ТСН-2001.13-2 Дополнение 46 №62/46 III квартал 2025 года | AP25: № и период сборника коэффициентов (индексов) пересчета: Коэффициенты к ТСН-2001 МГЭ Дополнение 80, строительство №217/80 III квартал 2025 года и Коэффициенты к ТСН-2001.13-2 Дополнение 46 №62/46 III квартал 2025 года
A26: № п/п | B26: Шифр расценки и коды ресурсов | C26: Наименование работ и затрат | D26: Ед. изм. | E26: Кол-во единиц | F26: Цена на ед. изм., руб. | G26: Попра- вочные коэффи- циенты | H26: Коэффи- циенты зимних удорожа- ний | I26: Всего в ценах на январь 2000 года, руб. | J26: Коэффи- циенты (индек- сы) пере- счета, нормы НР и СП | K26: ВСЕГО затрат в текущем уровне цен, руб.
A27: 1 | B27: 2 | C27: 3 | D27: 4 | E27: 5 | F27: 6 | G27: 7 | H27: 8 | I27: 9 | J27: 10 | K27: 11
A29: =CONCATENATE("Раздел: ",IF(Source!G24<>"Новый раздел", Source!G24, "")) -> Раздел: Монтажные работы
A30: 1 | B30: 4.10-80-4 Поправка: Гл.12.Прил.8.п.8. 5_12.00.01.11.003 | C30: Аппараты приемные, приборы ПС приемно-контрольные, пусковые, прибор ПС на 4 луча | D30: =Source!H28 -> 1 ШТ. | E30: =Source!I28 -> 7 | Q30: =Source!X28 -> 324.98 | R30: =Source!X29 -> 17870.71 | S30: =Source!Y28 -> 166.1 | T30: =Source!Y29 -> 9133.92 | U30: =ROUND((175/100)*ROUND(Source!R28, 2), 2) -> 0.14 | V30: =ROUND((0/100)*ROUND(Source!R29, 2), 2) -> 0 | AC30: 0
C31: ЗП | F31: =Source!AO28 -> 44.78 | G31: =Source!DG28 -> *1,1 | H31: =Source!AV29 -> 1.047 | I31: =Source!S28 -> 361.01 | J31: =IF(Source!BA29<> 0, Source!BA29, 1) -> 54.99 | K31: =Source!S29 -> 19851.94
C32: ЭМ | F32: =Source!AM28 -> 0.12 | G32: =Source!DE28 -> *1,1 | H32: =Source!AV29 -> 1.047 | I32: =Source!Q28 -> 0.97 | J32: =IF(Source!BB29<> 0, Source!BB29, 1) -> 13.75 | K32: =Source!Q29 -> 13.34
C33: в т.ч. ЗПМ | F33: =Source!AN28 -> 0.01 | G33: =Source!DF28 -> *1,1 | H33: =Source!AV29 -> 1.047 | I33: =Source!R28 -> 0.08 | J33: =IF(Source!BS29<> 0, Source!BS29, 1) -> 54.99 | K33: =Source!R29 -> 4.4
C34: МР | F34: =Source!AL28 -> 6.44 | G34: =Source!DD28 | H34: =Source!AW29 -> 1 | I34: =Source!P28 -> 45.08 | J34: =IF(Source!BC29<> 0, Source!BC29, 1) -> 9.89 | K34: =Source!P29 -> 445.84
A35: 1,1 | B35: =Source!F30 -> КА 1 | C35: ОБОРУДОВАНИЕ:_x000D_ Прибор приемно-контрольный и управления пожарный адресный R3-Рубеж 20П 319538 4 873,98 = [42 981 / 1,2 / 7,66] + 3% Трансп + 1,2% Заг.скл | D35: =Source!H30 -> шт. | E35: =Source!I30 -> 7 | F35: =Source!AK30 -> 4873.98 | H35: =Source!AW31 -> 1 | I35: =Source!O30 -> 34117.86 | J35: =IF(Source!BC31<> 0, Source!BC31, 1) -> 7.66 | K35: =Source!O31 -> 261342.81 | Q35: =Source!X30 -> 0 | R35: =Source!X31 -> 0 | S35: =Source!Y30 -> 0 | T35: =Source!Y31 -> 0 | U35: =ROUND((175/100)*ROUND(Source!R30, 2), 2) -> 0 | V35: =ROUND((0/100)*ROUND(Source!R31, 2), 2) -> 0 | AC35: 5
C36: НР от ФОТ | D36: % | E36: =Source!BZ29 -> 90 | I36: =SUM(Q30:Q35) -> 324.98 | J36: =Source!AT29 -> 90 | K36: =SUM(R30:R35) -> 17870.71
C37: СП от ФОТ | D37: % | E37: =Source!CA29 -> 46 | I37: =SUM(S30:S36) -> 166.1 | J37: =Source!AU29 -> 46 | K37: =SUM(T30:T36) -> 9133.92
C38: ЗТР | D38: чел-ч | E38: =Source!AQ28 -> 3.3 | G38: =Source!DI28 -> *1,1 | H38: =Source!AV29 -> 1.047 | I38: =Source!U28 -> 26.60427
C39: ВСЕГО работ по позиции: | H39: =I31+I32+I34+I36+I37+SUM(I35:I35)-SUMIF(AC35:AC35, 5, I35:I35)-SUMIF(AC35:AC35, 6, I35:I35) -> 898.14 | J39: =K31+K32+K34+K36+K37+SUM(K35:K35)-SUMIF(AC35:AC35, 5, K35:K35)-SUMIF(AC35:AC35, 6, K35:K35) -> 47315.75
C40: ВСЕГО оборудование по позиции: | H40: =SUMIF(AC35:AC35, 5, I35:I35)+SUMIF(AC35:AC35, 6, I35:I35) -> 34117.86 | J40: =SUMIF(AC35:AC35, 5, K35:K35)+SUMIF(AC35:AC35, 6, K35:K35) -> 261342.81
C41: ВСЕГО по позиции: | H41: =I31+I32+I34+I36+I37+SUM(I35:I35) -> 35016 | J41: =K31+K32+K34+K36+K37+SUM(K35:K35) -> 308658.56 | O41: =I31+I32+I34+I36+I37+SUM(I35:I35) -> 35016 | P41: =K31+K32+K34+K36+K37+SUM(K35:K35) -> 308658.56
A43: 2 | B43: 4.10-170-2 Поправка: Гл.12.Прил.8.п.8. 5_12.00.01.11.003 | C43: Монтаж блока информационно-управляющего (БИУ) в диспетчерской | D43: =Source!H32 -> 1 ШТ. | E43: =Source!I32 -> 2 | Q43: =Source!X32 -> 69.38 | R43: =Source!X33 -> 3815.26 | S43: =Source!Y32 -> 35.46 | T43: =Source!Y33 -> 1950.02 | U43: =ROUND((175/100)*ROUND(Source!R32, 2), 2) -> 0 | V43: =ROUND((0/100)*ROUND(Source!R33, 2), 2) -> 0 | AC43: 0
C44: ЗП | F44: =Source!AO32 -> 33.47 | G44: =Source!DG32 -> *1,1 | H44: =Source!AV33 -> 1.047 | I44: =Source!S32 -> 77.09 | J44: =IF(Source!BA33<> 0, Source!BA33, 1) -> 54.99 | K44: =Source!S33 -> 4239.18
C45: МР | F45: =Source!AL32 -> 2.34 | G45: =Source!DD32 | H45: =Source!AW33 -> 1 | I45: =Source!P32 -> 4.68 | J45: =IF(Source!BC33<> 0, Source!BC33, 1) -> 10.26 | K45: =Source!P33 -> 48.02
A46: 2,1 | B46: =Source!F34 -> КА 2 | C46: ОБОРУДОВАНИЕ:_x000D_ Блок индикации и управления R3-Рубеж-БИУ 319531 2 396,35 = [21 132 / 1,2 / 7,66] + 3% Трансп + 1,2% Заг.скл | D46: =Source!H34 -> шт. | E46: =Source!I34 -> 2 | F46: =Source!AK34 -> 2396.35 | H46: =Source!AW35 -> 1 | I46: =Source!O34 -> 4792.7 | J46: =IF(Source!BC35<> 0, Source!BC35, 1) -> 7.66 | K46: =Source!O35 -> 36712.08 | Q46: =Source!X34 -> 0 | R46: =Source!X35 -> 0 | S46: =Source!Y34 -> 0 | T46: =Source!Y35 -> 0 | U46: =ROUND((175/100)*ROUND(Source!R34, 2), 2) -> 0 | V46: =ROUND((0/100)*ROUND(Source!R35, 2), 2) -> 0 | AC46: 5
C47: НР от ФОТ | D47: % | E47: =Source!BZ33 -> 90 | I47: =SUM(Q43:Q46) -> 69.38 | J47: =Source!AT33 -> 90 | K47: =SUM(R43:R46) -> 3815.26
C48: СП от ФОТ | D48: % | E48: =Source!CA33 -> 46 | I48: =SUM(S43:S47) -> 35.46 | J48: =Source!AU33 -> 46 | K48: =SUM(T43:T47) -> 1950.02
C49: ЗТР | D49: чел-ч | E49: =Source!AQ32 -> 2.65 | G49: =Source!DI32 -> *1,1 | H49: =Source!AV33 -> 1.047 | I49: =Source!U32 -> 6.10401
C50: ВСЕГО работ по позиции: | H50: =I44+I45+I47+I48+SUM(I46:I46)-SUMIF(AC46:AC46, 5, I46:I46)-SUMIF(AC46:AC46, 6, I46:I46) -> 186.61 | J50: =K44+K45+K47+K48+SUM(K46:K46)-SUMIF(AC46:AC46, 5, K46:K46)-SUMIF(AC46:AC46, 6, K46:K46) -> 10052.48
C51: ВСЕГО оборудование по позиции: | H51: =SUMIF(AC46:AC46, 5, I46:I46)+SUMIF(AC46:AC46, 6, I46:I46) -> 4792.7 | J51: =SUMIF(AC46:AC46, 5, K46:K46)+SUMIF(AC46:AC46, 6, K46:K46) -> 36712.08
C52: ВСЕГО по позиции: | H52: =I44+I45+I47+I48+SUM(I46:I46) -> 4979.31 | J52: =K44+K45+K47+K48+SUM(K46:K46) -> 46764.56 | O52: =I44+I45+I47+I48+SUM(I46:I46) -> 4979.31 | P52: =K44+K45+K47+K48+SUM(K46:K46) -> 46764.56
A54: 3 | B54: 4.11-12-1 Поправка: Гл.12.Прил.8.п.8. 5_12.00.01.11.003 | C54: Установка съемных и выдвижных блоков (модулей, ячеек, ТЭЗ) массой до 5 кг | D54: =Source!H36 -> 1 ШТ. | E54: =Source!I36 -> 1 | Q54: =Source!X36 -> 12.16 | R54: =Source!X37 -> 668.63 | S54: =Source!Y36 -> 6.21 | T54: =Source!Y37 -> 341.74 | U54: =ROUND((175/100)*ROUND(Source!R36, 2), 2) -> 0.16 | V54: =ROUND((0/100)*ROUND(Source!R37, 2), 2) -> 0 | AC54: 0
C55: ЗП | F55: =Source!AO36 -> 11.65 | G55: =Source!DG36 -> *1,1 | H55: =Source!AV37 -> 1.047 | I55: =Source!S36 -> 13.42 | J55: =IF(Source!BA37<> 0, Source!BA37, 1) -> 54.99 | K55: =Source!S37 -> 737.97
C56: ЭМ | F56: =Source!AM36 -> 0.5 | G56: =Source!DE36 -> *1,1 | H56: =Source!AV37 -> 1.047 | I56: =Source!Q36 -> 0.58 | J56: =IF(Source!BB37<> 0, Source!BB37, 1) -> 16.26 | K56: =Source!Q37 -> 9.43
C57: в т.ч. ЗПМ | F57: =Source!AN36 -> 0.08 | G57: =Source!DF36 -> *1,1 | H57: =Source!AV37 -> 1.047 | I57: =Source!R36 -> 0.09 | J57: =IF(Source!BS37<> 0, Source!BS37, 1) -> 54.99 | K57: =Source!R37 -> 4.95
A58: 3,1 | B58: =Source!F38 -> КА 3 | C58: ОБОРУДОВАНИЕ:_x000D_ Модуль связи R3-МС 377218 1 908,27 = [16 828 / 1,2 / 7,66] + 3% Трансп + 1,2% Заг.скл | D58: =Source!H38 -> шт. | E58: =Source!I38 -> 1 | F58: =Source!AK38 -> 1908.27 | H58: =Source!AW39 -> 1 | I58: =Source!O38 -> 1908.27 | J58: =IF(Source!BC39<> 0, Source!BC39, 1) -> 7.66 | K58: =Source!O39 -> 14617.35 | Q58: =Source!X38 -> 0 | R58: =Source!X39 -> 0 | S58: =Source!Y38 -> 0 | T58: =Source!Y39 -> 0 | U58: =ROUND((175/100)*ROUND(Source!R38, 2), 2) -> 0 | V58: =ROUND((0/100)*ROUND(Source!R39, 2), 2) -> 0 | AC58: 5
C59: НР от ФОТ | D59: % | E59: =Source!BZ37 -> 90 | I59: =SUM(Q54:Q58) -> 12.16 | J59: =Source!AT37 -> 90 | K59: =SUM(R54:R58) -> 668.63
C60: СП от ФОТ | D60: % | E60: =Source!CA37 -> 46 | I60: =SUM(S54:S59) -> 6.21 | J60: =Source!AU37 -> 46 | K60: =SUM(T54:T59) -> 341.74
C61: ЗТР | D61: чел-ч | E61: =Source!AQ36 -> 1.03 | G61: =Source!DI36 -> *1,1 | H61: =Source!AV37 -> 1.047 | I61: =Source!U36 -> 1.186251
C62: ВСЕГО работ по позиции: | H62: =I55+I56+I59+I60+SUM(I58:I58)-SUMIF(AC58:AC58, 5, I58:I58)-SUMIF(AC58:AC58, 6, I58:I58) -> 32.37 | J62: =K55+K56+K59+K60+SUM(K58:K58)-SUMIF(AC58:AC58, 5, K58:K58)-SUMIF(AC58:AC58, 6, K58:K58) -> 1757.77
C63: ВСЕГО оборудование по позиции: | H63: =SUMIF(AC58:AC58, 5, I58:I58)+SUMIF(AC58:AC58, 6, I58:I58) -> 1908.27 | J63: =SUMIF(AC58:AC58, 5, K58:K58)+SUMIF(AC58:AC58, 6, K58:K58) -> 14617.35
C64: ВСЕГО по позиции: | H64: =I55+I56+I59+I60+SUM(I58:I58) -> 1940.64 | J64: =K55+K56+K59+K60+SUM(K58:K58) -> 16375.12 | O64: =I55+I56+I59+I60+SUM(I58:I58) -> 1940.64 | P64: =K55+K56+K59+K60+SUM(K58:K58) -> 16375.12
A66: 4 | B66: 4.10-81-2 Поправка: Гл.12.Прил.8.п.8. 5_12.00.01.11.003 | C66: Извещатели ПС автоматические, дымовой, фотоэлектрический, радиоизотопный, световой в нормальном исполнении | D66: =Source!H40 -> 1 ШТ. | E66: =Source!I40 -> 589 | Q66: =Source!X40 -> 12949.05 | R66: =Source!X41 -> 712068.09 | S66: =Source!Y40 -> 6618.4 | T66: =Source!Y41 -> 363945.91 | U66: =ROUND((175/100)*ROUND(Source!R40, 2), 2) -> 11.87 | V66: =ROUND((0/100)*ROUND(Source!R41, 2), 2) -> 0 | AC66: 0
C67: ЗП | F67: =Source!AO40 -> 21.2 | G67: =Source!DG40 -> *1,1 | H67: =Source!AV41 -> 1.047 | I67: =Source!S40 -> 14381.05 | J67: =IF(Source!BA41<> 0, Source!BA41, 1) -> 54.99 | K67: =Source!S41 -> 790813.94
C68: ЭМ | F68: =Source!AM40 -> 0.06 | G68: =Source!DE40 -> *1,1 | H68: =Source!AV41 -> 1.047 | I68: =Source!Q40 -> 40.7 | J68: =IF(Source!BB41<> 0, Source!BB41, 1) -> 17.5 | K68: =Source!Q41 -> 712.25
C69: в т.ч. ЗПМ | F69: =Source!AN40 -> 0.01 | G69: =Source!DF40 -> *1,1 | H69: =Source!AV41 -> 1.047 | I69: =Source!R40 -> 6.78 | J69: =IF(Source!BS41<> 0, Source!BS41, 1) -> 54.99 | K69: =Source!R41 -> 372.83
C70: МР | F70: =Source!AL40 -> 1.26 | G70: =Source!DD40 | H70: =Source!AW41 -> 1 | I70: =Source!P40 -> 742.14 | J70: =IF(Source!BC41<> 0, Source!BC41, 1) -> 9.89 | K70: =Source!P41 -> 7339.76
A71: 4,1 | B71: =Source!F42 -> КА 4 | C71: ОБОРУДОВАНИЕ:_x000D_ Извещатель дымовой ИП 212-64-R3 без б/о 337936 159,44 = [1 406 / 1,2 / 7,66] + 3% Трансп + 1,2% Заг.скл | D71: =Source!H42 -> шт. | E71: =Source!I42 -> 589 | F71: =Source!AK42 -> 159.44 | H71: =Source!AW43 -> 1 | I71: =Source!O42 -> 93910.16 | J71: =IF(Source!BC43<> 0, Source!BC43, 1) -> 7.66 | K71: =Source!O43 -> 719351.83 | Q71: =Source!X42 -> 0 | R71: =Source!X43 -> 0 | S71: =Source!Y42 -> 0 | T71: =Source!Y43 -> 0 | U71: =ROUND((175/100)*ROUND(Source!R42, 2), 2) -> 0 | V71: =ROUND((0/100)*ROUND(Source!R43, 2), 2) -> 0 | AC71: 5
C72: НР от ФОТ | D72: % | E72: =Source!BZ41 -> 90 | I72: =SUM(Q66:Q71) -> 12949.05 | J72: =Source!AT41 -> 90 | K72: =SUM(R66:R71) -> 712068.09
C73: СП от ФОТ | D73: % | E73: =Source!CA41 -> 46 | I73: =SUM(S66:S72) -> 6618.4 | J73: =Source!AU41 -> 46 | K73: =SUM(T66:T72) -> 363945.91
C74: ЗТР | D74: чел-ч | E74: =Source!AQ40 -> 1.68 | G74: =Source!DI40 -> *1,1 | H74: =Source!AV41 -> 1.047 | I74: =Source!U40 -> 1139.6302
C75: ВСЕГО работ по позиции: | H75: =I67+I68+I70+I72+I73+SUM(I71:I71)-SUMIF(AC71:AC71, 5, I71:I71)-SUMIF(AC71:AC71, 6, I71:I71) -> 34731.34 | J75: =K67+K68+K70+K72+K73+SUM(K71:K71)-SUMIF(AC71:AC71, 5, K71:K71)-SUMIF(AC71:AC71, 6, K71:K71) -> 1874879.9
C76: ВСЕГО оборудование по позиции: | H76: =SUMIF(AC71:AC71, 5, I71:I71)+SUMIF(AC71:AC71, 6, I71:I71) -> 93910.16 | J76: =SUMIF(AC71:AC71, 5, K71:K71)+SUMIF(AC71:AC71, 6, K71:K71) -> 719351.83
C77: ВСЕГО по позиции: | H77: =I67+I68+I70+I72+I73+SUM(I71:I71) -> 128641.5 | J77: =K67+K68+K70+K72+K73+SUM(K71:K71) -> 2594231.8 | O77: =I67+I68+I70+I72+I73+SUM(I71:I71) -> 128641.5 | P77: =K67+K68+K70+K72+K73+SUM(K71:K71) -> 2594231.8
A79: 5 | B79: 4.10-81-6 Поправка: Гл.12.Прил.8.п.8. 5_12.00.01.11.003 | C79: Конструкция для установки извещателя | D79: =Source!H44 -> 1 ШТ. | E79: =Source!I44 -> 589 | Q79: =Source!X44 -> 2869.43 | R79: =Source!X45 -> 157789.68 | S79: =Source!Y44 -> 1466.6 | T79: =Source!Y45 -> 80648.06 | U79: =ROUND((175/100)*ROUND(Source!R44, 2), 2) -> 332.4 | V79: =ROUND((0/100)*ROUND(Source!R45, 2), 2) -> 0 | AC79: 0
C80: ="Объем: "&Source!I44&"=136+"&"453" -> Объем: 589=136+453
C81: ЗП | F81: =Source!AO44 -> 4.42 | G81: =Source!DG44 -> *1,1 | H81: =Source!AV45 -> 1.047 | I81: =Source!S44 -> 2998.31 | J81: =IF(Source!BA45<> 0, Source!BA45, 1) -> 54.99 | K81: =Source!S45 -> 164877.07
C82: ЭМ | F82: =Source!AM44 -> 4.56 | G82: =Source!DE44 -> *1,1 | H82: =Source!AV45 -> 1.047 | I82: =Source!Q44 -> 3093.28 | J82: =IF(Source!BB45<> 0, Source!BB45, 1) -> 12.8 | K82: =Source!Q45 -> 39593.98
C83: в т.ч. ЗПМ | F83: =Source!AN44 -> 0.28 | G83: =Source!DF44 -> *1,1 | H83: =Source!AV45 -> 1.047 | I83: =Source!R44 -> 189.94 | J83: =IF(Source!BS45<> 0, Source!BS45, 1) -> 54.99 | K83: =Source!R45 -> 10444.8
C84: МР | F84: =Source!AL44 -> 1.05 | G84: =Source!DD44 | H84: =Source!AW45 -> 1 | I84: =Source!P44 -> 618.45 | J84: =IF(Source!BC45<> 0, Source!BC45, 1) -> 9.89 | K84: =Source!P45 -> 6116.47
A85: 5,1 | B85: =Source!F46 -> КА 5 | C85: Базовое основание W2.03 342655 44,99 = [523 / 1,2 / 9,88] + 2% Заг.скл | D85: =Source!H46 -> шт. | E85: =Source!I46 -> 136 | F85: =Source!AK46 -> 44.99 | H85: =Source!AW47 -> 1 | I85: =Source!O46 -> 6118.64 | J85: =IF(Source!BC47<> 0, Source!BC47, 1) -> 9.88 | K85: =Source!O47 -> 60452.16 | Q85: =Source!X46 -> 0 | R85: =Source!X47 -> 0 | S85: =Source!Y46 -> 0 | T85: =Source!Y47 -> 0 | U85: =ROUND((175/100)*ROUND(Source!R46, 2), 2) -> 0 | V85: =ROUND((0/100)*ROUND(Source!R47, 2), 2) -> 0 | AC85: 3
A86: 5,2 | B86: =Source!F48 -> КА 6 | C86: Базовое основание W1.02 338227 17,89 = [208 / 1,2 / 9,88] + 2% Заг.скл | D86: =Source!H48 -> шт. | E86: =Source!I48 -> 453 | F86: =Source!AK48 -> 17.89 | H86: =Source!AW49 -> 1 | I86: =Source!O48 -> 8104.17 | J86: =IF(Source!BC49<> 0, Source!BC49, 1) -> 9.88 | K86: =Source!O49 -> 80069.2 | Q86: =Source!X48 -> 0 | R86: =Source!X49 -> 0 | S86: =Source!Y48 -> 0 | T86: =Source!Y49 -> 0 | U86: =ROUND((175/100)*ROUND(Source!R48, 2), 2) -> 0 | V86: =ROUND((0/100)*ROUND(Source!R49, 2), 2) -> 0 | AC86: 3
C87: НР от ФОТ | D87: % | E87: =Source!BZ45 -> 90 | I87: =SUM(Q79:Q86) -> 2869.43 | J87: =Source!AT45 -> 90 | K87: =SUM(R79:R86) -> 157789.68
C88: СП от ФОТ | D88: % | E88: =Source!CA45 -> 46 | I88: =SUM(S79:S87) -> 1466.6 | J88: =Source!AU45 -> 46 | K88: =SUM(T79:T87) -> 80648.06
C89: ЗТР | D89: чел-ч | E89: =Source!AQ44 -> 0.35 | G89: =Source!DI44 -> *1,1 | H89: =Source!AV45 -> 1.047 | I89: =Source!U44 -> 237.42296
C90: ВСЕГО работ по позиции: | H90: =I81+I82+I84+I87+I88+SUM(I85:I86)-SUMIF(AC85:AC86, 5, I85:I86)-SUMIF(AC85:AC86, 6, I85:I86) -> 25268.88 | J90: =K81+K82+K84+K87+K88+SUM(K85:K86)-SUMIF(AC85:AC86, 5, K85:K86)-SUMIF(AC85:AC86, 6, K85:K86) -> 589546.62
C91: ВСЕГО оборудование по позиции: | H91: =SUMIF(AC85:AC86, 5, I85:I86)+SUMIF(AC85:AC86, 6, I85:I86) -> 0 | J91: =SUMIF(AC85:AC86, 5, K85:K86)+SUMIF(AC85:AC86, 6, K85:K86) -> 0
C92: ВСЕГО по позиции: | H92: =I81+I82+I84+I87+I88+SUM(I85:I86) -> 25268.88 | J92: =K81+K82+K84+K87+K88+SUM(K85:K86) -> 589546.62 | O92: =I81+I82+I84+I87+I88+SUM(I85:I86) -> 25268.88 | P92: =K81+K82+K84+K87+K88+SUM(K85:K86) -> 589546.62
A94: 6 | B94: 4.10-81-2 Поправка: Гл.12.Прил.8.п.8. 5_12.00.01.11.003 | C94: Извещатели ПС автоматические, дымовой, фотоэлектрический, радиоизотопный, световой в нормальном исполнении | D94: =Source!H50 -> 1 ШТ. | E94: =Source!I50 -> 12 | Q94: =Source!X50 -> 263.82 | R94: =Source!X51 -> 14507.3 | S94: =Source!Y50 -> 134.84 | T94: =Source!Y51 -> 7414.84 | U94: =ROUND((175/100)*ROUND(Source!R50, 2), 2) -> 0.25 | V94: =ROUND((0/100)*ROUND(Source!R51, 2), 2) -> 0 | AC94: 0
C95: ЗП | F95: =Source!AO50 -> 21.2 | G95: =Source!DG50 -> *1,1 | H95: =Source!AV51 -> 1.047 | I95: =Source!S50 -> 292.99 | J95: =IF(Source!BA51<> 0, Source!BA51, 1) -> 54.99 | K95: =Source!S51 -> 16111.52
C96: ЭМ | F96: =Source!AM50 -> 0.06 | G96: =Source!DE50 -> *1,1 | H96: =Source!AV51 -> 1.047 | I96: =Source!Q50 -> 0.83 | J96: =IF(Source!BB51<> 0, Source!BB51, 1) -> 17.5 | K96: =Source!Q51 -> 14.53
C97: в т.ч. ЗПМ | F97: =Source!AN50 -> 0.01 | G97: =Source!DF50 -> *1,1 | H97: =Source!AV51 -> 1.047 | I97: =Source!R50 -> 0.14 | J97: =IF(Source!BS51<> 0, Source!BS51, 1) -> 54.99 | K97: =Source!R51 -> 7.7
C98: МР | F98: =Source!AL50 -> 1.26 | G98: =Source!DD50 | H98: =Source!AW51 -> 1 | I98: =Source!P50 -> 15.12 | J98: =IF(Source!BC51<> 0, Source!BC51, 1) -> 9.89 | K98: =Source!P51 -> 149.54
A99: 6,1 | B99: =Source!F52 -> КА 7 | C99: ОБОРУДОВАНИЕ:_x000D_ Извещатель пожарный дымовой оптико-электронный линейный ИПДЛ-264/1-50-R3 342260 2 479,80 = [21 868 / 1,2 / 7,66] + 3% Трансп + 1,2% Заг.скл | D99: =Source!H52 -> шт. | E99: =Source!I52 -> 12 | F99: =Source!AK52 -> 2479.8 | H99: =Source!AW53 -> 1 | I99: =Source!O52 -> 29757.6 | J99: =IF(Source!BC53<> 0, Source!BC53, 1) -> 7.66 | K99: =Source!O53 -> 227943.22 | Q99: =Source!X52 -> 0 | R99: =Source!X53 -> 0 | S99: =Source!Y52 -> 0 | T99: =Source!Y53 -> 0 | U99: =ROUND((175/100)*ROUND(Source!R52, 2), 2) -> 0 | V99: =ROUND((0/100)*ROUND(Source!R53, 2), 2) -> 0 | AC99: 5
C100: НР от ФОТ | D100: % | E100: =Source!BZ51 -> 90 | I100: =SUM(Q94:Q99) -> 263.82 | J100: =Source!AT51 -> 90 | K100: =SUM(R94:R99) -> 14507.3
C101: СП от ФОТ | D101: % | E101: =Source!CA51 -> 46 | I101: =SUM(S94:S100) -> 134.84 | J101: =Source!AU51 -> 46 | K101: =SUM(T94:T100) -> 7414.84
C102: ЗТР | D102: чел-ч | E102: =Source!AQ50 -> 1.68 | G102: =Source!DI50 -> *1,1 | H102: =Source!AV51 -> 1.047 | I102: =Source!U50 -> 23.218272
C103: ВСЕГО работ по позиции: | H103: =I95+I96+I98+I100+I101+SUM(I99:I99)-SUMIF(AC99:AC99, 5, I99:I99)-SUMIF(AC99:AC99, 6, I99:I99) -> 707.6 | J103: =K95+K96+K98+K100+K101+SUM(K99:K99)-SUMIF(AC99:AC99, 5, K99:K99)-SUMIF(AC99:AC99, 6, K99:K99) -> 38197.73
C104: ВСЕГО оборудование по позиции: | H104: =SUMIF(AC99:AC99, 5, I99:I99)+SUMIF(AC99:AC99, 6, I99:I99) -> 29757.6 | J104: =SUMIF(AC99:AC99, 5, K99:K99)+SUMIF(AC99:AC99, 6, K99:K99) -> 227943.22
C105: ВСЕГО по позиции: | H105: =I95+I96+I98+I100+I101+SUM(I99:I99) -> 30465.2 | J105: =K95+K96+K98+K100+K101+SUM(K99:K99) -> 266140.95 | O105: =I95+I96+I98+I100+I101+SUM(I99:I99) -> 30465.2 | P105: =K95+K96+K98+K100+K101+SUM(K99:K99) -> 266140.95
A107: 7 | B107: 4.10-76-10 Поправка: Гл.12.Прил.8.п.8. 5_12.00.01.11.003 | C107: Монтаж ключа или кнопки на панели | D107: =Source!H54 -> 1 ШТ. | E107: =Source!I54 -> 24 | Q107: =Source!X54 -> 312.22 | R107: =Source!X55 -> 17168.84 | S107: =Source!Y54 -> 174.18 | T107: =Source!Y55 -> 9578.4 | U107: =ROUND((175/100)*ROUND(Source!R54, 2), 2) -> 0 | V107: =ROUND((0/100)*ROUND(Source!R55, 2), 2) -> 0 | AC107: 0
C108: ЗП | F108: =Source!AO54 -> 11.89 | G108: =Source!DG54 -> *1,1 | H108: =Source!AV55 -> 1.047 | I108: =Source!S54 -> 328.65 | J108: =IF(Source!BA55<> 0, Source!BA55, 1) -> 54.99 | K108: =Source!S55 -> 18072.46
C109: МР | F109: =Source!AL54 -> 1.67 | G109: =Source!DD54 | H109: =Source!AW55 -> 1 | I109: =Source!P54 -> 40.08 | J109: =IF(Source!BC55<> 0, Source!BC55, 1) -> 18.61 | K109: =Source!P55 -> 745.89
A110: 7,1 | B110: =Source!F56 -> КА 8 | C110: ОБОРУДОВАНИЕ:_x000D_ Извещатель пожарный ручной адресный с изолятором ИПР 513-11ИКЗ-А-R3 301159 140,96 = [1 243 / 1,2 / 7,66] + 3% Трансп + 1,2% Заг.скл | D110: =Source!H56 -> шт. | E110: =Source!I56 -> 24 | F110: =Source!AK56 -> 140.96 | H110: =Source!AW57 -> 1 | I110: =Source!O56 -> 3383.04 | J110: =IF(Source!BC57<> 0, Source!BC57, 1) -> 7.66 | K110: =Source!O57 -> 25914.09 | Q110: =Source!X56 -> 0 | R110: =Source!X57 -> 0 | S110: =Source!Y56 -> 0 | T110: =Source!Y57 -> 0 | U110: =ROUND((175/100)*ROUND(Source!R56, 2), 2) -> 0 | V110: =ROUND((0/100)*ROUND(Source!R57, 2), 2) -> 0 | AC110: 5
C111: НР от ФОТ | D111: % | E111: =Source!BZ55 -> 95 | I111: =SUM(Q107:Q110) -> 312.22 | J111: =Source!AT55 -> 95 | K111: =SUM(R107:R110) -> 17168.84
C112: СП от ФОТ | D112: % | E112: =Source!CA55 -> 53 | I112: =SUM(S107:S111) -> 174.18 | J112: =Source!AU55 -> 53 | K112: =SUM(T107:T111) -> 9578.4
...

Sheet Ведомость объемов работ
A1: =Source!B1 -> Smeta.RU (495) 974-1589
E3: "УТВЕРЖДАЮ"
D5: ___________________________
D7: ___________________________
D9: " ___ " ___________ 20 ___ г.
B12: =CONCATENATE("Ведомость объемов работ ", IF(Source!AN15<>"", Source!AN15," ")) -> Ведомость объемов работ
B13: =CONCATENATE(Source!F12, " ", Source!G12) -> 02-01-08 02-01-08 АПС
A16: № п/п | B16: № в ЛСР | C16: Наименование работ и затрат | D16: Единица измерения | E16: Количество | F16: Ссылка на чертежи, спецификации | G16: Формула расчета, расчет объемов работ и расхода материалов | H16: Примечание
A17: 1 | B17: 2 | C17: 3 | D17: 4 | E17: 5 | F17: 6 | G17: 7 | H17: 8
A18: =CONCATENATE("Локальная смета: ", Source!G20) -> Локальная смета: Автоматическая пожарная сигнализация
A19: =CONCATENATE("Раздел: ", Source!G24) -> Раздел: Монтажные работы
A20: 1 | B20: =Source!E28 -> 1 | C20: =Source!G28 -> Аппараты приемные, приборы ПС приемно-контрольные, пусковые, прибор ПС на 4 луча | D20: 1 ШТ. | E20: =Source!I28 -> 7 | F20: =Source!U24 | G20: =Source!I28 -> 7
A21: 1.1 | B21: =Source!E30 -> 1,1 | C21: =Source!G30 -> Прибор приемно-контрольный и управления пожарный адресный R3-Рубеж 20П 319538 | D21: шт. | E21: =Source!I30 -> 7 | F21: =Source!U24
A22: 2 | B22: =Source!E32 -> 2 | C22: =Source!G32 -> Монтаж блока информационно-управляющего (БИУ) в диспетчерской | D22: 1 ШТ. | E22: =Source!I32 -> 2 | F22: =Source!U24 | G22: =Source!I32 -> 2
A23: 2.1 | B23: =Source!E34 -> 2,1 | C23: =Source!G34 -> Блок индикации и управления R3-Рубеж-БИУ 319531 | D23: шт. | E23: =Source!I34 -> 2 | F23: =Source!U24
A24: 3 | B24: =Source!E36 -> 3 | C24: =Source!G36 -> Установка съемных и выдвижных блоков (модулей, ячеек, ТЭЗ) массой до 5 кг | D24: 1 ШТ. | E24: =Source!I36 -> 1 | F24: =Source!U24 | G24: =Source!I36 -> 1
A25: 3.1 | B25: =Source!E38 -> 3,1 | C25: =Source!G38 -> Модуль связи R3-МС 377218 | D25: шт. | E25: =Source!I38 -> 1 | F25: =Source!U24
A26: 4 | B26: =Source!E40 -> 4 | C26: =Source!G40 -> Извещатели ПС автоматические, дымовой, фотоэлектрический, радиоизотопный, световой в нормальном исполнении | D26: 1 ШТ. | E26: =Source!I40 -> 589 | F26: =Source!U24 | G26: =Source!I40 -> 589
A27: 4.1 | B27: =Source!E42 -> 4,1 | C27: =Source!G42 -> Извещатель дымовой ИП 212-64-R3 без б/о 337936 | D27: шт. | E27: =Source!I42 -> 589 | F27: =Source!U24
A28: 5 | B28: =Source!E44 -> 5 | C28: =Source!G44 -> Конструкция для установки извещателя | D28: 1 ШТ. | E28: =Source!I44 -> 589 | F28: =Source!U24 | G28: ="=136+"&"453" -> =136+453
A29: 5.1 | B29: =Source!E46 -> 5,1 | C29: =Source!G46 -> Базовое основание W2.03 342655 | D29: шт. | E29: =Source!I46 -> 136 | F29: =Source!U24
A30: 5.2 | B30: =Source!E48 -> 5,2 | C30: =Source!G48 -> Базовое основание W1.02 338227 | D30: шт. | E30: =Source!I48 -> 453 | F30: =Source!U24
A31: 6 | B31: =Source!E50 -> 6 | C31: =Source!G50 -> Извещатели ПС автоматические, дымовой, фотоэлектрический, радиоизотопный, световой в нормальном исполнении | D31: 1 ШТ. | E31: =Source!I50 -> 12 | F31: =Source!U24 | G31: =Source!I50 -> 12
A32: 6.1 | B32: =Source!E52 -> 6,1 | C32: =Source!G52 -> Извещатель пожарный дымовой оптико-электронный линейный ИПДЛ-264/1-50-R3 342260 | D32: шт. | E32: =Source!I52 -> 12 | F32: =Source!U24
A33: 7 | B33: =Source!E54 -> 7 | C33: =Source!G54 -> Монтаж ключа или кнопки на панели | D33: 1 ШТ. | E33: =Source!I54 -> 24 | F33: =Source!U24 | G33: =Source!I54 -> 24
A34: 7.1 | B34: =Source!E56 -> 7,1 | C34: =Source!G56 -> Извещатель пожарный ручной адресный с изолятором ИПР 513-11ИКЗ-А-R3 301159 | D34: шт. | E34: =Source!I56 -> 24 | F34: =Source!U24
A35: 8 | B35: =Source!E58 -> 8 | C35: =Source!G58 -> Извещатели ПС автоматические, тепловой электроконтактный, магнито-контактный в нормальном исполнении | D35: 1 ШТ. | E35: =Source!I58 -> 5 | F35: =Source!U24 | G35: =Source!I58 -> 5
A36: 8.1 | B36: =Source!E60 -> 8,1 | C36: =Source!G60 -> Извещатель пожарный тепловой адресный ИП 101-29-PR-R3 337480 | D36: шт. | E36: =Source!I60 -> 5 | F36: =Source!U24
A37: 9 | B37: =Source!E62 -> 9 | C37: =Source!G62 -> Монтаж устройства сигнально-блокировочного | D37: 1 ШТ. | E37: =Source!I62 -> 89 | F37: =Source!U24 | G37: =Source!I62 -> 89
A38: 9.1 | B38: =Source!E64 -> 9,1 | C38: =Source!G64 -> Изолятор шлейфа ИЗ-1-R3 337647 | D38: шт. | E38: =Source!I64 -> 89 | F38: =Source!U24
A39: 10 | B39: =Source!E66 -> 10 | C39: =Source!G66 -> Извещатели ПС автоматические, дымовой, фотоэлектрический, радиоизотопный, световой в нормальном исполнении | D39: 1 ШТ. | E39: =Source!I66 -> 104 | F39: =Source!U24 | G39: ="=78+"&"1+"&"25" -> =78+1+25
A40: 10.1 | B40: =Source!E68 -> 10,1 | C40: =Source!G68 -> Оповещатель охранно-пожарный световой адресный ОПОП 1-R3 "Выход" 337637 | D40: шт. | E40: =Source!I68 -> 78 | F40: =Source!U24
A41: 10.2 | B41: =Source!E70 -> 10,2 | C41: =Source!G70 -> Оповещатель охранно-пожарный световой адресный ОПОП 1-R3 "Пожар" 338202 | D41: шт. | E41: =Source!I70 -> 1 | F41: =Source!U24
A42: 10.3 | B42: =Source!E72 -> 10,3 | C42: =Source!G72 -> Оповещатель охранно-пожарный световой ОПОП 1-R3 Стрелка | D42: шт. | E42: =Source!I72 -> 25 | F42: =Source!U24
A43: 11 | B43: =Source!E74 -> 11 | C43: =Source!G74 -> Монтаж блока бесперебойного питания (ББП) в диспетчерской | D43: 1 ШТ. | E43: =Source!I74 -> 7 | F43: =Source!U24 | G43: ="=2+"&"1+"&"4" -> =2+1+4
A44: 11.1 | B44: =Source!E76 -> 11,1 | C44: =Source!G76 -> Источник вторичного электропитания резервированный адресный ИВЭПР 12/2 RS-R3 2х17 БР-R3 | D44: шт. | E44: =Source!I76 -> 2 | F44: =Source!U24
A45: 11.2 | B45: =Source!E78 -> 11,2 | C45: =Source!G78 -> Источник вторичного электропитания резервированный адресный ИВЭПР 12/5 RS-R3 2х40 БР-R3 | D45: шт. | E45: =Source!I78 -> 1 | F45: =Source!U24
A46: 11.3 | B46: =Source!E80 -> 11,3 | C46: =Source!G80 -> Источник вторичного электропитания резервированный адресный ИВЭПР 12/2 RS-R3 2х12 БР-R3 | D46: шт. | E46: =Source!I80 -> 4 | F46: =Source!U24
A47: 11.4 | B47: =Source!E82 -> 11,4 | C47: =Source!G82 -> Аккумулятор герметичный свинцово-кислотный 12 В, 12 А·ч | D47: шт. | E47: =Source!I82 -> 8 | F47: =Source!U24
A48: 11.5 | B48: =Source!E84 -> 11,5 | C48: =Source!G84 -> Батарея аккумуляторная, емкость 17 А·ч, напряжение 12 В | D48: шт. | E48: =Source!I84 -> 4 | F48: =Source!U24
A49: 11.6 | B49: =Source!E86 -> 11,6 | C49: =Source!G86 -> Батарея аккумуляторная, емкость 40 А·ч, напряжение 12 В | D49: шт. | E49: =Source!I86 -> 2 | F49: =Source!U24
A50: 12 | B50: =Source!E88 -> 12 | C50: =Source!G88 -> Аппараты приемные, устройства промежуточные на 1 луч | D50: 1 ШТ. | E50: =Source!I88 -> 30 | F50: =Source!U24 | G50: ="=1+"&"26+"&"1+"&"2" -> =1+26+1+2
A51: 12.1 | B51: =Source!E90 -> 12,1 | C51: =Source!G90 -> Адресный релейный модуль РМ-1К-R3 337614 | D51: шт. | E51: =Source!I90 -> 1 | F51: =Source!U24
A52: 12.2 | B52: =Source!E92 -> 12,2 | C52: =Source!G92 -> Адресный релейный модуль РМ-1С-R3 337648 | D52: шт. | E52: =Source!I92 -> 26 | F52: =Source!U24
A53: 12.3 | B53: =Source!E94 -> 12,3 | C53: =Source!G94 -> Адресный релейный модуль РМ-4-R3 337434 | D53: шт. | E53: =Source!I94 -> 1 | F53: =Source!U24
A54: 12.4 | B54: =Source!E96 -> 12,4 | C54: =Source!G96 -> Адресный релейный модуль РМ-4К-R3 | D54: шт. | E54: =Source!I96 -> 2 | F54: =Source!U24
A55: 13 | B55: =Source!E98 -> 13 | C55: =Source!G98 -> Монтаж блока питания сети (БПС) в диспетчерской | D55: 1 ШТ. | E55: =Source!I98 -> 2 | F55: =Source!U24 | G55: =Source!I98 -> 2
A56: 13.1 | B56: =Source!E100 -> 13,1 | C56: =Source!G100 -> Бокс резервного электропитания БР12 исп. 2х40 045569 | D56: шт. | E56: =Source!I100 -> 2 | F56: =Source!U24
A57: 14 | B57: =Source!E102 -> 14 | C57: =Source!G102 -> Монтаж громкоговорителя или звуковой колонки в помещении | D57: 1 ШТ. | E57: =Source!I102 -> 24 | F57: =Source!U24 | G57: =Source!I102 -> 24
A58: 14.1 | B58: =Source!E104 -> 14,1 | C58: =Source!G104 -> Оповещатель охранно-пожарный светозвуковой ОПОП 124-7 12В | D58: шт. | E58: =Source!I104 -> 24 | F58: =Source!U24
A59: 15 | B59: =Source!E106 -> 15 | C59: =Source!G106 -> Монтаж светильников с лампами накаливания, светового настенного указателя | D59: 100 шт. | E59: =Source!I106 -> 0.04 | F59: =Source!U24 | G59: ="=(2+"&"2)/"&"100" -> =(2+2)/100
A60: 15.1 | B60: =Source!E108 -> 15,1 | C60: =Source!G108 -> Оповещатель охранно-пожарный световой, типа МАЯК-12-С | D60: шт. | E60: =Source!I108 -> 2 | F60: =Source!U24
A61: 15.2 | B61: =Source!E110 -> 15,2 | C61: =Source!G110 -> Оповещатель охранно-пожарный, световой, типа Молния-220 РИП "Выход" | D61: шт. | E61: =Source!I110 -> 2 | F61: =Source!U24
A62: =CONCATENATE("Раздел: ", Source!G143) -> Раздел: Огнестойкая кабельная линия
A63: 16 | B63: =Source!E147 -> 16 | C63: =Source!G147 -> Прокладка кабеля связи огнестойкого в трубах гофрированных с использованием скобы СМО: по бетонным поверхностям | D63: 100 м | E63: =Source!I147 -> 59.84 | F63: =Source!U143 | G63: ="=(500+"&"4+"&"430+"&"5050)/"&"100" -> =(500+4+430+5050)/100
A64: 16.1 | B64: =Source!E149 -> 16,1 | C64: =Source!G149 -> Трубы электротехнические из ПВХ, гофрированные, гибкие, легкие, с протяжкой, прочность при сжатии 350 Н, прочность на разрыв 100 Н, диапазон температур от -25 до + 60°С, негорючие, для скрытой прокладки проводов и кабелей, наружный диаметр 20 мм | D64: 10 м | E64: =Source!I149 -> 610.368 | F64: =Source!U143
A65: 16.2 | B65: =Source!E151 -> 16,2 | C65: =Source!G151 -> Муфта соединительная из АБС пластика, универсальная, для электротехнических труб, наружный диаметр 20 мм | D65: шт. | E65: =Source!I151 -> 200 | F65: =Source!U143
A66: 16.3 | B66: =Source!E153 -> 16,3 | C66: =Source!G153 -> Скоба однолапковая стальная оцинкованная, для кабелей диаметром от 19 до 20 мм | D66: 1000 шт. | E66: =Source!I153 -> 17.952 | F66: =Source!U143
A67: 16.4 | B67: =Source!E155 -> 16,4 | C67: =Source!G155 -> Кабель КПСЭнг(А)-FRLSLTx 1х2х0,5 мм | D67: км | E67: =Source!I155 -> 0.51 | F67: =Source!U143
A68: 16.5 | B68: =Source!E157 -> 16,5 | C68: =Source!G157 -> Кабель КПСнг(А)-FRLSLTx 1х2х1,5 мм | D68: км | E68: =Source!I157 -> 0.00408 | F68: =Source!U143
A69: 16.6 | B69: =Source!E159 -> 16,6 | C69: =Source!G159 -> Кабель КПСнг(А)-FRLSLTx 1х2х1 мм | D69: км | E69: =Source!I159 -> 0.4386 | F69: =Source!U143
A70: 16.7 | B70: =Source!E161 -> 16,7 | C70: =Source!G161 -> Кабель КПСнг(А)-FRLSLTx 1х2х0,75 мм | D70: км | E70: =Source!I161 -> 5.151 | F70: =Source!U143
A71: 16.8 | B71: =Source!E163 -> 16,8 | C71: =Source!G163 -> Анкер клиновой стальной оцинкованный, М6х55 мм | D71: 100 шт. | E71: =Source!I163 -> 141.2224 | F71: =Source!U143
A72: 17 | B72: =Source!E165 -> 17 | C72: =Source!G165 -> Прокладка по установленным конструкциям, по стенам и колоннам с креплением скобами винипластовой трубы диаметром до 25 мм | D72: 100 м | E72: =Source!I165 -> 0.3 | F72: =Source!U143 | G72: ="=30/"&"100" -> =30/100
A73: 17.1 | B73: =Source!E167 -> 17,1 | C73: =Source!G167 -> Трубы из непластифицированного вторичного ПВХ, гладкие, самозатухающие, усиленного типа, наружный диаметр 25 мм, толщина стенки 1,5 мм, для электропроводок | D73: м | E73: =Source!I167 -> 30.6 | F73: =Source!U143
A74: 17.2 | B74: =Source!E169 -> 17,2 | C74: =Source!G169 -> Скоба двухлапковая стальная оцинкованная, для кабелей диаметром от 25 до 26 | D74: 1000 шт. | E74: =Source!I169 -> 0.066 | F74: =Source!U143
A75: 17.3 | B75: =Source!E171 -> 17,3 | C75: =Source!G171 -> Мастика тиоколовая, герметизирующая, нетвердеющая, типа АМ-05 | D75: кг | E75: =Source!I171 -> 5 | F75: =Source!U143
A76: 18 | B76: =Source!E173 -> 18 | C76: =Source!G173 -> Монтаж огнестойкой ответвительной коробки для кабельных линий связи: по бетонным поверхностям | D76: 100 шт. | E76: =Source!I173 -> 1 | F76: =Source!U143 | G76: ="=100/"&"100" -> =100/100
A77: 18.1 | B77: =Source!E175 -> 18,1 | C77: =Source!G175 -> Коробка ответвительная пластиковая, огнестойкая, 6 вводов для труб и кабеля, крышка с уплотнителем и фиксатором, с керамическими клеммными колодками, 4 контакта, степень защиты IP 55, габаритные размеры без учета кабельных вводов 100х100х50 мм | D77: шт. | E77: =Source!I175 -> 100 | F77: =Source!U143
A78: 18.2 | B78: =Source!E177 -> 18,2 | C78: =Source!G177 -> Анкер клиновой стальной оцинкованный, М6х55 мм | D78: 100 шт. | E78: =Source!I177 -> 2.02 | F78: =Source!U143
A79: 19 | B79: =Source!E179 -> 19 | C79: =Source!G179 -> Добавлять или исключать при каждом изменении количества присоединяемых кабелей в огнестойкой ответвительной коробке к нормам и расценкам: 4.10-185-11, 4.10-185-12, 4.10-185-13, 4.10-185-14 | D79: 100 шт. | E79: =Source!I179 -> 1 | F79: =Source!U143 | G79: ="=100/"&"100" -> =100/100
A80: =CONCATENATE("Раздел: ", Source!G212) -> Раздел: АРМ диспетчера
A81: 20 | B81: =Source!E216 -> 20 | C81: =Source!G216 -> Монтаж аппаратуры настольной массой до 20 кг | D81: 1 ШТ. | E81: =Source!I216 -> 1 | F81: =Source!U212 | G81: =Source!I216 -> 1
A82: 20.1 | B82: =Source!E218 -> 20,1 | C82: =Source!G218 -> Моноблок Aquarius Mnb Pro T924, клавиатура, мышь | D82: шт. | E82: =Source!I218 -> 1 | F82: =Source!U212
A83: 20.2 | B83: =Source!E220 -> 20,2 | C83: =Source!G220 -> ПО "FireSec" оперативная задача | D83: шт. | E83: =Source!I220 -> 1 | F83: =Source!U212
A84: 21 | B84: =Source!E222 -> 21 | C84: =Source!G222 -> Монтаж блока питания сети (БПС) в диспетчерской | D84: 1 ШТ. | E84: =Source!I222 -> 1 | F84: =Source!U212 | G84: =Source!I222 -> 1
A85: 21.1 | B85: =Source!E224 -> 21,1 | C85: =Source!G224 -> Источник бесперебойного питания двойного преобразования со встроенными аккумуляторами, напольный / стоечный, 1-фазный, полная мощность 1 кВА, активная мощность 0,9 кВт, панель управления с ЖК-дисплеем | D85: шт. | E85: =Source!I224 -> 1 | F85: =Source!U212
C88: Главный инженер проекта _________________ | D88: =IF(Source!X12<>"", Source!X12," ")
C90: Составил _________________ | D90: =IF(Source!AB12<>"", Source!AB12," ") -> Лукьянова А.Л.

Sheet Source
A1: 0 | B1: Smeta.RU (495) 974-1589 | D1: _PS_ | F1: 0 | G1: 0 | H1: 0 | I1: Smeta.RU | K1: 1 | L1: 74562 | M1: 10 | N1: 12 | O1: 0 | P1: 0 | Q1: 3
A4: 1 | B4: 1 | C4: -1 | G4: Капитальный ремонт здания Государственного бюджетного общеобразовательного учреждения города Москвы «Школа № 236» по адресу: г. Москва, ул. Клязьминская, д. 7, к. 4. I этап | EC4: 0
A12: 1 | B12: 326 | C12: 0 | D12: =ROW(A287) -> 287 | E12: 0 | F12: 02-01-08 | G12: 02-01-08 АПС | I12: 0 | J12: 2024-00272-01-0-ИОС5.1 | K12: 0 | L12: 0 | M12: 4098 | O12: 0 | P12: 0 | Q12: 0 | R12: 0 | S12: 0 | T12: 1 | V12: 0 | AB12: Лукьянова А.Л. | BB12: 0 | BH12: Сметные нормы списания | BI12: Коды ОКП для ТСН-2001 МГЭ Дополнение 80 | BJ12: 1 | BK12: 1 | BL12: 0 | BM12: 0 | BN12: 1 | BO12: 0 | BP12: 6 | BQ12: 2 | BR12: 1 | BS12: 1 | BT12: 1 | BU12: 0 | BV12: 1 | BW12: 0 | BX12: 0 | BY12: ТСН-2001 (МГЭ) Доп 80 - Новое строительство | BZ12: Типовой расчет для ТСН-2001 МГЭ, Дополнение 80, строительство | CA12: Территориальные сметные нормативы для Москвы ТСН-2001 (МГЭ), дополнение 80 | CB12: Территориальные сметные нормативы для Москвы ТСН-2001 (МГЭ), дополнение 80 | CC12: Территориальные сметные нормативы для Москвы ТСН-2001 (МГЭ), дополнение 80 | CD12: Территориальные сметные нормативы для Москвы ТСН-2001 (МГЭ), дополнение 80 | CE12: Поправки для ТСН-2001 от 03.02.2026 г. доп.80 | CF12: 0 | CG12: 0 | CH12: 8202 | CK12: 80 | CQ12: Территориальные сметные нормативы для Москвы (ТСН-2001) | CR12: ТЕР | CS12: 41660 | CT12: 1 | CU12: 80 | CY12: 0 | EC12: 0
A15: 15 | B15: 1
A18: 52 | B18: =B287 -> 326 | C18: =C287 -> 1 | D18: =D287 -> 12 | E18: =E287 -> 0 | F18: =F287 -> 02-01-08 | G18: =G287 -> 02-01-08 АПС | O18: =O287 -> 362047.07 | P18: =P287 -> 311548.58 | Q18: =Q287 -> 3445.63 | R18: =R287 -> 199.62 | S18: =S287 -> 47052.86 | T18: =T287 -> 0 | U18: =U287 -> 3826.3565 | V18: =V287 -> 0 | ... GX18: =GX287 -> 0
A20: 3 | B20: 1 | D20: =ROW(A257) -> 257 | F20: 02-01-08 | G20: Автоматическая пожарная сигнализация | I20: 0 | J20: 2024-00272-01-0-ИОС5.1 | K20: -1 | L20: 02-01-08 | S20: 0 | T20: 0 | V20: 0 | AB20: Лукьянова А.Л. | BX20: 0 | CF20: 0 | CG20: 0
A22: 52 | B22: =B257 -> 1 | C22: =C257 -> 3 | D22: =D257 -> 20 | E22: =E257 -> 0 | F22: =F257 -> 02-01-08 | G22: =G257 -> Автоматическая пожарная сигнализация | O22: =O257 -> 362047.07 | P22: =P257 -> 311548.58 | Q22: =Q257 -> 3445.63 | R22: =R257 -> 199.62 | S22: =S257 -> 47052.86 | T22: =T257 -> 0 | U22: =U257 -> 3826.3565 | V22: =V257 -> 0 | ... GX22: =GX257 -> 0
A24: 4 | B24: 1 | D24: =ROW(A113) -> 113 | G24: Монтажные работы | I24: 0 | K24: -1 | S24: 0 | T24: 0 | V24: 0 | BX24: 0 | CJ24: 0
A26: 52 | B26: =B113 -> 1 | C26: =C113 -> 4 | D26: =D113 -> 24 | E26: =E113 -> 0 | F26: =F113 | G26: =G113 -> Монтажные работы | O26: =O113 -> 268696.12 | P26: =P113 -> 240197.78 | Q26: =Q113 -> 3149.8 | R26: =R113 -> 199.18 | S26: =S113 -> 25348.54 | T26: =T113 -> 0 | U26: =U113 -> 2008.4344 | V26: =V113 -> 0 | ... GX26: =GX113 -> 0
A28: 17 | B28: 1 | D28: =ROW(EtalonRes!A1) -> 1 | E28: 1 | F28: 4.10-80-4 | G28: Аппараты приемные, приборы ПС приемно-контрольные, пусковые, прибор ПС на 4 луча | H28: 1 ШТ. | I28: 7 | J28: 0 | K28: 7 | O28: =ROUND(CP28,2) -> 407.06 | P28: =ROUND((ROUND((AC28*AW28*I28),2)*BC28),2) -> 45.08 | Q28: =(ROUND((ROUND((((ET28*1.1))*AV28*I28),2)*BB28),2)+ROUND((ROUND(((AE28-((EU28*1.1)))*AV28*I28),2)*BS28),2)) -> 0.97 | R28: =ROUND((ROUND((AE28*AV28*I28),2)*BS28),2) -> 0.08 | S28: =ROUND((ROUND((AF28*AV28*I28),2)*BA28),2) -> 361.01 | T28: =ROUND(CU28*I28,2) -> 0 | U28: =CV28*I28 -> 26.60427 | V28: =CW28*I28 -> 0 | W28: =ROUND(CX28*I28,2) -> 0 | X28: =ROUND(CY28,2) -> 324.98 | Y28: =ROUND(CZ28,2) -> 166.1 | AA28: 56498966 | AB28: =ROUND((AC28+AD28+AF28),6) -> 55.83 | AC28: =ROUND((ES28),6) -> 6.44 | AD28: =ROUND(((((ET28*1.1))-((EU28*1.1)))+AE28),6) -> 0.132 | AE28: =ROUND(((EU28*1.1)),6) -> 0.011 | AF28: =ROUND(((EV28*1.1)),6) -> 49.258 | AG28: =ROUND((AP28),6) -> 0 | AH28: =((EW28*1.1)) -> 3.63 | AI28: =((EX28*1.1)) -> 0 | AJ28: =(AS28) -> 0 | AK28: 51.34 | AL28: 6.44 | AM28: 0.12 | AN28: 0.01 | AO28: 44.78 | AP28: 0 | AQ28: 3.3 | AR28: 0 | AS28: 0 | AT28: 90 | AU28: 46 | AV28: 1.047 | AW28: 1 | AZ28: 1 | BA28: 1 | BB28: 1 | BC28: 1 | BH28: 0 | BI28: 2 | BJ28: ТСН-2001.4. Доп. 1-42. Сб. 10, т. 80, поз. 4 | BM28: 68 | BN28: 0 | BO28: 4.10-80-4 | BP28: 1 | BQ28: 40 | BR28: 0 | BS28: 1 | BT28: 1 | BU28: 1 | BV28: 1 | BW28: 1 | BX28: 1 | BZ28: 90 | CA28: 46 | CE28: 30 | CF28: 0 | CG28: 0 | CM28: 0 | CO28: 0 | CP28: =(P28+Q28+S28) -> 407.06 | CQ28: =ROUND((ROUND((AC28*AW28*1),2)*BC28),2) -> 6.44 | CR28: =(ROUND((ROUND((((ET28*1.1))*AV28*1),2)*BB28),2)+ROUND((ROUND(((AE28-((EU28*1.1)))*AV28*1),2)*BS28),2)) -> 0.14 | CS28: =ROUND((ROUND((AE28*AV28*1),2)*BS28),2) -> 0.01 | CT28: =ROUND((ROUND((AF28*AV28*1),2)*BA28),2) -> 51.57 | CU28: =AG28 -> 0 | CV28: =(AH28*AV28) -> 3.80061 | CW28: =AI28 -> 0 | CX28: =AJ28 -> 0 | CY28: =(((S28+R28)*AT28)/100) -> 324.981 | CZ28: =(((S28+R28)*AU28)/100) -> 166.1014 | DE28: *1,1 | DF28: *1,1 | DG28: *1,1 | DI28: *1,1 | DJ28: *1,1 | DN28: 0 | DO28: 0 | DP28: 1 | DQ28: 1 | DU28: 1013 | DV28: 1 ШТ. | DW28: 1 ШТ. | DX28: 1 | EE28: 58162630 | EF28: 40 | EG28: Монтаж оборудования | EH28: 0 | EJ28: 2 | EK28: 68 | EL28: ТСН-2001.4-10. Прокладка и монтаж сетей связи | EM28: ТСН-2001.4-10-1 | EO28: Поправка: Гл.12.Прил.8.п.8. 5_12.00.01.11.003 | EQ28: 0 | ER28: 51.34 | ES28: 6.44 | ET28: 0.12 | EU28: 0.01 | EV28: 44.78 | EW28: 3.3 | EX28: 0 | EY28: 0 | FQ28: 0 | FR28: 0 | FS28: 0 | FX28: 90 | FY28: 46 | GD28: 1 | GF28: -1862862500 | GG28: 2 | GH28: 1 | GI28: 2 | GJ28: 0 | GK28: 0 | GL28: =ROUND(IF(AND(BH28=3,BI28=3,FS28<>0),P28,0),2) -> 0 | GM28: =ROUND(O28+X28+Y28,2)+GX28 -> 898.14 | GN28: =IF(OR(BI28=0,BI28=1),GM28-GX28,0) -> 0 | GO28: =IF(BI28=2,GM28-GX28,0) -> 898.14 | GP28: =IF(BI28=4,GM28-GX28,0) -> 0 | GR28: 0 | GS28: 3 | GT28: 0 | GV28: =ROUND((GT28),6) -> 0 | GW28: 1 | GX28: =ROUND(HC28*I28,2) -> 0 | HA28: 0 | HB28: 0 | HC28: =GV28*GW28 -> 0 | HS28: 0 | IK28: 0
A29: 17 | B29: 1 | D29: =ROW(EtalonRes!A2) -> 2 | E29: 1 | F29: 4.10-80-4 | G29: Аппараты приемные, приборы ПС приемно-контрольные, пусковые, прибор ПС на 4 луча | H29: 1 ШТ. | I29: 7 | J29: 0 | K29: 7 | O29: =ROUND(CP29,2) -> 20311.12 | P29: =ROUND((ROUND((AC29*AW29*I29),2)*BC29),2) -> 445.84 | Q29: =(ROUND((ROUND((((ET29*1.1))*AV29*I29),2)*BB29),2)+ROUND((ROUND(((AE29-((EU29*1.1)))*AV29*I29),2)*BS29),2)) -> 13.34 | R29: =ROUND((ROUND((AE29*AV29*I29),2)*BS29),2) -> 4.4 | S29: =ROUND((ROUND((AF29*AV29*I29),2)*BA29),2) -> 19851.94 | T29: =ROUND(CU29*I29,2) -> 0 | U29: =CV29*I29 -> 26.60427 | V29: =CW29*I29 -> 0 | W29: =ROUND(CX29*I29,2) -> 0 | X29: =ROUND(CY29,2) -> 17870.71 | Y29: =ROUND(CZ29,2) -> 9133.92 | AA29: 56498968 | AB29: =ROUND((AC29+AD29+AF29),6) -> 55.83 | AC29: =ROUND((ES29),6) -> 6.44 | AD29: =ROUND(((((ET29*1.1))-((EU29*1.1)))+AE29),6) -> 0.132 | AE29: =ROUND(((EU29*1.1)),6) -> 0.011 | AF29: =ROUND(((EV29*1.1)),6) -> 49.258 | AG29: =ROUND((AP29),6) -> 0 | AH29: =((EW29*1.1)) -> 3.63 | AI29: =((EX29*1.1)) -> 0 | AJ29: =(AS29) -> 0 | AK29: 51.34 | AL29: 6.44 | AM29: 0.12 | AN29: 0.01 | AO29: 44.78 | AP29: 0 | AQ29: 3.3 | AR29: 0 | AS29: 0 | AT29: 90 | AU29: 46 | AV29: 1.047 | AW29: 1 | AZ29: 1 | BA29: 54.99 | BB29: 13.75 | BC29: 9.89 | BH29: 0 | BI29: 2 | BJ29: ТСН-2001.4. Доп. 1-42. Сб. 10, т. 80, поз. 4 | BM29: 68 | BN29: 0 | BO29: 4.10-80-4 | BP29: 1 | BQ29: 40 | BR29: 0 | BS29: 54.99 | BT29: 1 | BU29: 1 | BV29: 1 | BW29: 1 | BX29: 1 | BZ29: 90 | CA29: 46 | CE29: 30 | CF29: 0 | CG29: 0 | CM29: 0 | CO29: 0 | CP29: =(P29+Q29+S29) -> 20311.12 | CQ29: =ROUND((ROUND((AC29*AW29*1),2)*BC29),2) -> 63.69 | CR29: =(ROUND((ROUND((((ET29*1.1))*AV29*1),2)*BB29),2)+ROUND((ROUND(((AE29-((EU29*1.1)))*AV29*1),2)*BS29),2)) -> 1.93 | CS29: =ROUND((ROUND((AE29*AV29*1),2)*BS29),2) -> 0.55 | CT29: =ROUND((ROUND((AF29*AV29*1),2)*BA29),2) -> 2835.83 | CU29: =AG29 -> 0 | CV29: =(AH29*AV29) -> 3.80061 | CW29: =AI29 -> 0 | CX29: =AJ29 -> 0 | CY29: =(((S29+R29)*AT29)/100) -> 17870.706 | CZ29: =(((S29+R29)*AU29)/100) -> 9133.9164 | DE29: *1,1 | DF29: *1,1 | DG29: *1,1 | DI29: *1,1 | DJ29: *1,1 | DN29: 0 | DO29: 0 | DP29: 1 | DQ29: 1 | DU29: 1013 | DV29: 1 ШТ. | DW29: 1 ШТ. | DX29: 1 | EE29: 58162630 | EF29: 40 | EG29: Монтаж оборудования | EH29: 0 | EJ29: 2 | EK29: 68 | EL29: ТСН-2001.4-10. Прокладка и монтаж сетей связи | EM29: ТСН-2001.4-10-1 | EO29: Поправка: Гл.12.Прил.8.п.8. 5_12.00.01.11.003 | EQ29: 0 | ER29: 51.34 | ES29: 6.44 | ET29: 0.12 | EU29: 0.01 | EV29: 44.78 | EW29: 3.3 | EX29: 0 | EY29: 0 | FQ29: 0 | FR29: 0 | FS29: 0 | FX29: 90 | FY29: 46 | GD29: 1 | GF29: -1862862500 | GG29: 2 | GH29: 1 | GI29: 2 | GJ29: 0 | GK29: 0 | GL29: =ROUND(IF(AND(BH29=3,BI29=3,FS29<>0),P29,0),2) -> 0 | GM29: =ROUND(O29+X29+Y29,2)+GX29 -> 47315.75 | GN29: =IF(OR(BI29=0,BI29=1),GM29-GX29,0) -> 0 | GO29: =IF(BI29=2,GM29-GX29,0) -> 47315.75 | GP29: =IF(BI29=4,GM29-GX29,0) -> 0 | GR29: 0 | GS29: 3 | GT29: 0 | GV29: =ROUND((GT29),6) -> 0 | GW29: 1 | GX29: =ROUND(HC29*I29,2) -> 0 | HA29: 0 | HB29: 0 | HC29: =GV29*GW29 -> 0 | HS29: 0 | IK29: 0
A30: 18 | B30: 1 | E30: 1,1 | F30: КА 1 | G30: Прибор приемно-контрольный и управления пожарный адресный R3-Рубеж 20П 319538 | H30: шт. | I30: =I28*J30 -> 7 | J30: 1 | K30: 1 | O30: =ROUND(CP30,2) -> 34117.86 | P30: =ROUND((ROUND((AC30*I30),2)*BC30),2) -> 34117.86 | Q30: =(ROUND((ROUND(((ET30)*AV30*I30),2)*BB30),2)+ROUND((ROUND(((AE30-(EU30))*AV30*I30),2)*BS30),2)) -> 0 | R30: =ROUND((ROUND((AE30*AV30*I30),2)*BS30),2) -> 0 | S30: =ROUND((ROUND((AF30*AV30*I30),2)*BA30),2) -> 0 | T30: =ROUND(CU30*I30,2) -> 0 | U30: =CV30*I30 -> 0 | V30: =CW30*I30 -> 0 | W30: =ROUND(CX30*I30,2) -> 0 | X30: =ROUND(CY30,2) -> 0 | Y30: =ROUND(CZ30,2) -> 0 | AA30: 56498966 | AB30: =ROUND((AC30+AD30+AF30),6) -> 4873.98 | AC30: =ROUND((ES30),6) -> 4873.98 | AD30: =ROUND((((ET30)-(EU30))+AE30),6) -> 0 | AE30: =ROUND((EU30),6) -> 0 | AF30: =ROUND((EV30),6) -> 0 | AG30: =ROUND((AP30),6) -> 0 | AH30: =(EW30) -> 0 | AI30: =(EX30) -> 0 | AJ30: =(AS30) -> 0 | AK30: 4873.98 | AL30: 4873.98 | AM30: 0 | AN30: 0 | AO30: 0 | AP30: 0 | AQ30: 0 | AR30: 0 | AS30: 0 | AT30: 0 | AU30: 0 | AV30: 1 | AW30: 1 | AZ30: 1 | BA30: 1 | BB30: 1 | BC30: 1 | BH30: 3 | BI30: 3 | BM30: 746 | BN30: 0 | BP30: 0 | BQ30: 130 | BR30: 0 | BS30: 1 | BT30: 1 | BU30: 1 | BV30: 1 | BW30: 1 | BX30: 1 | BZ30: 90 | CA30: 46 | CE30: 30 | CF30: 0 | CG30: 0 | CM30: 0 | CO30: 0 | CP30: =(P30+Q30+S30) -> 34117.86 | CQ30: =ROUND((ROUND((AC30*1),2)*BC30),2) -> 4873.98 | CR30: =(ROUND((ROUND(((ET30)*AV30*1),2)*BB30),2)+ROUND((ROUND(((AE30-(EU30))*AV30*1),2)*BS30),2)) -> 0 | CS30: =ROUND((ROUND((AE30*AV30*1),2)*BS30),2) -> 0 | CT30: =ROUND((ROUND((AF30*AV30*1),2)*BA30),2) -> 0 | CU30: =AG30 -> 0 | CV30: =(AH30*AV30) -> 0 | CW30: =AI30 -> 0 | CX30: =AJ30 -> 0 | CY30: =(((S30+R30)*AT30)/100) -> 0 | CZ30: =(((S30+R30)*AU30)/100) -> 0 | DN30: 0 | DO30: 0 | DP30: 1 | DQ30: 1 | DU30: 1010 | DV30: шт. | DW30: шт. | DX30: 1 | EE30: 58162750 | EF30: 130 | EG30: Сметная стоимость оборудования | EH30: 0 | EJ30: 3 | EK30: 746 | EL30: ТСН-2001.13. Сметная стоимость оборудования | EM30: ТСН-2001.13 | EQ30: 0 | ER30: 0 | ES30: 4873.98 | ET30: 0 | EU30: 0 | EV30: 0 | EW30: 0 | EX30: 0 | FQ30: 0 | FR30: =P30 -> 34117.86 | FS30: 0 | FX30: 90 | FY30: 46 | GA30: [42 981 / 1,2 / 7,66] + 3% Трансп + 1,2% Заг.скл | GD30: 1 | GF30: 1356071934 | GG30: 2 | GH30: 4 | GI30: -2 | GJ30: 0 | GK30: 0 | GL30: =ROUND(IF(AND(BH30=3,BI30=3,FS30<>0),P30,0),2) -> 0 | GM30: =ROUND(O30+X30+Y30,2)+GX30 -> 34117.86 | GN30: =IF(OR(BI30=0,BI30=1),GM30-GX30,0) -> 0 | GO30: =IF(BI30=2,GM30-GX30,0) -> 0 | GP30: =IF(BI30=4,GM30-GX30,0) -> 0 | GR30: 0 | GS30: 2 | GT30: 0 | GV30: =ROUND((GT30),6) -> 0 | GW30: 1 | GX30: =ROUND(HC30*I30,2) -> 0 | HA30: 0 | HB30: 0 | HC30: =GV30*GW30 -> 0 | HE30: 3 | HF30: 1,2 | HS30: 0 | IK30: 0
A31: 18 | B31: 1 | E31: 1,1 | F31: КА 1 | G31: Прибор приемно-контрольный и управления пожарный адресный R3-Рубеж 20П 319538 | H31: шт. | I31: =I29*J31 -> 7 | J31: 1 | K31: 1 | O31: =ROUND(CP31,2) -> 261342.81 | P31: =ROUND((ROUND((AC31*I31),2)*BC31),2) -> 261342.81 | Q31: =(ROUND((ROUND(((ET31)*AV31*I31),2)*BB31),2)+ROUND((ROUND(((AE31-(EU31))*AV31*I31),2)*BS31),2)) -> 0 | R31: =ROUND((ROUND((AE31*AV31*I31),2)*BS31),2) -> 0 | S31: =ROUND((ROUND((AF31*AV31*I31),2)*BA31),2) -> 0 | T31: =ROUND(CU31*I31,2) -> 0 | U31: =CV31*I31 -> 0 | V31: =CW31*I31 -> 0 | W31: =ROUND(CX31*I31,2) -> 0 | X31: =ROUND(CY31,2) -> 0 | Y31: =ROUND(CZ31,2) -> 0 | AA31: 56498968 | AB31: =ROUND((AC31+AD31+AF31),6) -> 4873.98 | AC31: =ROUND((ES31),6) -> 4873.98 | AD31: =ROUND((((ET31)-(EU31))+AE31),6) -> 0 | AE31: =ROUND((EU31),6) -> 0 | AF31: =ROUND((EV31),6) -> 0 | AG31: =ROUND((AP31),6) -> 0 | AH31: =(EW31) -> 0 | AI31: =(EX31) -> 0 | AJ31: =(AS31) -> 0 | AK31: 4873.98 | AL31: 4873.98 | AM31: 0 | AN31: 0 | AO31: 0 | AP31: 0 | AQ31: 0 | AR31: 0 | AS31: 0 | AT31: 0 | AU31: 0 | AV31: 1 | AW31: 1 | AZ31: 1 | BA31: 1 | BB31: 1 | BC31: 7.66 | BH31: 3 | BI31: 3 | BM31: 746 | BN31: 0 | BP31: 0 | BQ31: 130 | BR31: 0 | BS31: 1 | BT31: 1 | BU31: 1 | BV31: 1 | BW31: 1 | BX31: 1 | BZ31: 90 | CA31: 46 | CE31: 30 | CF31: 0 | CG31: 0 | CM31: 0 | CO31: 0 | CP31: =(P31+Q31+S31) -> 261342.81 | CQ31: =ROUND((ROUND((AC31*1),2)*BC31),2) -> 37334.69 | CR31: =(ROUND((ROUND(((ET31)*AV31*1),2)*BB31),2)+ROUND((ROUND(((AE31-(EU31))*AV31*1),2)*BS31),2)) -> 0 | CS31: =ROUND((ROUND((AE31*AV31*1),2)*BS31),2) -> 0 | CT31: =ROUND((ROUND((AF31*AV31*1),2)*BA31),2) -> 0 | CU31: =AG31 -> 0 | CV31: =(AH31*AV31) -> 0 | CW31: =AI31 -> 0 | CX31: =AJ31 -> 0 | CY31: =(((S31+R31)*AT31)/100) -> 0 | CZ31: =(((S31+R31)*AU31)/100) -> 0 | DN31: 0 | DO31: 0 | DP31: 1 | DQ31: 1 | DU31: 1010 | DV31: шт. | DW31: шт. | DX31: 1 | EE31: 58162750 | EF31: 130 | EG31: Сметная стоимость оборудования | EH31: 0 | EJ31: 3 | EK31: 746 | EL31: ТСН-2001.13. Сметная стоимость оборудования | EM31: ТСН-2001.13 | EQ31: 0 | ER31: 4873.98 | ES31: 4873.98 | ET31: 0 | EU31: 0 | EV31: 0 | EW31: 0 | EX31: 0 | EZ31: 5 | FC31: 1 | FD31: 18 | FF31: 42981 | FQ31: 0 | FR31: =P31 -> 261342.81 | FS31: 0 | FX31: 90 | FY31: 46 | GA31: [42 981 / 1,2 / 7,66] + 3% Трансп + 1,2% Заг.скл | GD31: 1 | GF31: 1356071934 | GG31: 2 | GH31: 3 | GI31: 5 | GJ31: 0 | GK31: 0 | GL31: =ROUND(IF(AND(BH31=3,BI31=3,FS31<>0),P31,0),2) -> 0 | GM31: =ROUND(O31+X31+Y31,2)+GX31 -> 261342.81 | GN31: =IF(OR(BI31=0,BI31=1),GM31-GX31,0) -> 0 | GO31: =IF(BI31=2,GM31-GX31,0) -> 0 | GP31: =IF(BI31=4,GM31-GX31,0) -> 0 | GR31: 1 | GS31: 1 | GT31: 0 | GV31: =ROUND((GT31),6) -> 0 | GW31: 1 | GX31: =ROUND(HC31*I31,2) -> 0 | HA31: 0 | HB31: 0 | HC31: =GV31*GW31 -> 0 | HE31: 3 | HF31: 1,2 | HS31: 0 | IK31: 0
A32: 17 | B32: 1 | D32: =ROW(EtalonRes!A7) -> 7 | E32: 2 | F32: 4.10-170-2 | G32: Монтаж блока информационно-управляющего (БИУ) в диспетчерской | H32: 1 ШТ. | I32: 2 | J32: 0 | K32: 2 | O32: =ROUND(CP32,2) -> 81.77 | P32: =ROUND((ROUND((AC32*AW32*I32),2)*BC32),2) -> 4.68 | Q32: =(ROUND((ROUND((((ET32*1.1))*AV32*I32),2)*BB32),2)+ROUND((ROUND(((AE32-((EU32*1.1)))*AV32*I32),2)*BS32),2)) -> 0 | R32: =ROUND((ROUND((AE32*AV32*I32),2)*BS32),2) -> 0 | S32: =ROUND((ROUND((AF32*AV32*I32),2)*BA32),2) -> 77.09 | T32: =ROUND(CU32*I32,2) -> 0 | U32: =CV32*I32 -> 6.10401 | V32: =CW32*I32 -> 0 | W32: =ROUND(CX32*I32,2) -> 0 | X32: =ROUND(CY32,2) -> 69.38 | Y32: =ROUND(CZ32,2) -> 35.46 | AA32: 56498966 | AB32: =ROUND((AC32+AD32+AF32),6) -> 39.157 | AC32: =ROUND((ES32),6) -> 2.34 | AD32: =ROUND(((((ET32*1.1))-((EU32*1.1)))+AE32),6) -> 0 | AE32: =ROUND(((EU32*1.1)),6) -> 0 | AF32: =ROUND(((EV32*1.1)),6) -> 36.817 | AG32: =ROUND((AP32),6) -> 0 | AH32: =((EW32*1.1)) -> 2.915 | AI32: =((EX32*1.1)) -> 0 | AJ32: =(AS32) -> 0 | AK32: 35.81 | AL32: 2.34 | AM32: 0 | AN32: 0 | AO32: 33.47 | AP32: 0 | AQ32: 2.65 | AR32: 0 | AS32: 0 | AT32: 90 | AU32: 46 | AV32: 1.047 | AW32: 1 | AZ32: 1 | BA32: 1 | BB32: 1 | BC32: 1 | BH32: 0 | BI32: 2 | BJ32: ТСН-2001.4 Доп. 67, Сб. 10, т. 170, поз. 2 | BM32: 68 | BN32: 0 | BO32: 4.10-170-2 | BP32: 1 | BQ32: 40 | BR32: 0 | BS32: 1 | BT32: 1 | BU32: 1 | BV32: 1 | BW32: 1 | BX32: 1 | BZ32: 90 | CA32: 46 | CE32: 30 | CF32: 0 | CG32: 0 | CM32: 0 | CO32: 0 | CP32: =(P32+Q32+S32) -> 81.77 | CQ32: =ROUND((ROUND((AC32*AW32*1),2)*BC32),2) -> 2.34 | CR32: =(ROUND((ROUND((((ET32*1.1))*AV32*1),2)*BB32),2)+ROUND((ROUND(((AE32-((EU32*1.1)))*AV32*1),2)*BS32),2)) -> 0 | CS32: =ROUND((ROUND((AE32*AV32*1),2)*BS32),2) -> 0 | CT32: =ROUND((ROUND((AF32*AV32*1),2)*BA32),2) -> 38.55 | CU32: =AG32 -> 0 | CV32: =(AH32*AV32) -> 3.052005 | CW32: =AI32 -> 0 | CX32: =AJ32 -> 0 | CY32: =(((S32+R32)*AT32)/100) -> 69.381 | CZ32: =(((S32+R32)*AU32)/100) -> 35.4614 | DE32: *1,1 | DF32: *1,1 | DG32: *1,1 | DI32: *1,1 | DJ32: *1,1 | DN32: 0 | DO32: 0 | DP32: 1 | DQ32: 1 | DU32: 1013 | DV32: 1 ШТ. | DW32: 1 ШТ. | DX32: 1 | EE32: 58162630 | EF32: 40 | EG32: Монтаж оборудования | EH32: 0 | EJ32: 2 | EK32: 68 | EL32: ТСН-2001.4-10. Прокладка и монтаж сетей связи | EM32: ТСН-2001.4-10-1 | EO32: Поправка: Гл.12.Прил.8.п.8. 5_12.00.01.11.003 | EQ32: 0 | ER32: 35.81 | ES32: 2.34 | ET32: 0 | EU32: 0 | EV32: 33.47 | EW32: 2.65 | EX32: 0 | EY32: 0 | FQ32: 0 | FR32: 0 | FS32: 0 | FX32: 90 | FY32: 46 | GD32: 1 | GF32: -1323780471 | GG32: 2 | GH32: 1 | GI32: 2 | GJ32: 0 | GK32: 0 | GL32: =ROUND(IF(AND(BH32=3,BI32=3,FS32<>0),P32,0),2) -> 0 | GM32: =ROUND(O32+X32+Y32,2)+GX32 -> 186.61 | GN32: =IF(OR(BI32=0,BI32=1),GM32-GX32,0) -> 0 | GO32: =IF(BI32=2,GM32-GX32,0) -> 186.61 | GP32: =IF(BI32=4,GM32-GX32,0) -> 0 | GR32: 0 | GS32: 3 | GT32: 0 | GV32: =ROUND((GT32),6) -> 0 | GW32: 1 | GX32: =ROUND(HC32*I32,2) -> 0 | HA32: 0 | HB32: 0 | HC32: =GV32*GW32 -> 0 | HS32: 0 | IK32: 0
A33: 17 | B33: 1 | D33: =ROW(EtalonRes!A12) -> 12 | E33: 2 | F33: 4.10-170-2 | G33: Монтаж блока информационно-управляющего (БИУ) в диспетчерской | H33: 1 ШТ. | I33: 2 | J33: 0 | K33: 2 | O33: =ROUND(CP33,2) -> 4287.2 | P33: =ROUND((ROUND((AC33*AW33*I33),2)*BC33),2) -> 48.02 | Q33: =(ROUND((ROUND((((ET33*1.1))*AV33*I33),2)*BB33),2)+ROUND((ROUND(((AE33-((EU33*1.1)))*AV33*I33),2)*BS33),2)) -> 0 | R33: =ROUND((ROUND((AE33*AV33*I33),2)*BS33),2) -> 0 | S33: =ROUND((ROUND((AF33*AV33*I33),2)*BA33),2) -> 4239.18 | T33: =ROUND(CU33*I33,2) -> 0 | U33: =CV33*I33 -> 6.10401 | V33: =CW33*I33 -> 0 | W33: =ROUND(CX33*I33,2) -> 0 | X33: =ROUND(CY33,2) -> 3815.26 | Y33: =ROUND(CZ33,2) -> 1950.02 | AA33: 56498968 | AB33: =ROUND((AC33+AD33+AF33),6) -> 39.157 | AC33: =ROUND((ES33),6) -> 2.34 | AD33: =ROUND(((((ET33*1.1))-((EU33*1.1)))+AE33),6) -> 0 | AE33: =ROUND(((EU33*1.1)),6) -> 0 | AF33: =ROUND(((EV33*1.1)),6) -> 36.817 | AG33: =ROUND((AP33),6) -> 0 | AH33: =((EW33*1.1)) -> 2.915 | AI33: =((EX33*1.1)) -> 0 | AJ33: =(AS33) -> 0 | AK33: 35.81 | AL33: 2.34 | AM33: 0 | AN33: 0 | AO33: 33.47 | AP33: 0 | AQ33: 2.65 | AR33: 0 | AS33: 0 | AT33: 90 | AU33: 46 | AV33: 1.047 | AW33: 1 | AZ33: 1 | BA33: 54.99 | BB33: 1 | BC33: 10.26 | BH33: 0 | BI33: 2 | BJ33: ТСН-2001.4 Доп. 67, Сб. 10, т. 170, поз. 2 | BM33: 68 | BN33: 0 | BO33: 4.10-170-2 | BP33: 1 | BQ33: 40 | BR33: 0 | BS33: 54.99 | BT33: 1 | BU33: 1 | BV33: 1 | BW33: 1 | BX33: 1 | BZ33: 90 | CA33: 46 | CE33: 30 | CF33: 0 | CG33: 0 | CM33: 0 | CO33: 0 | CP33: =(P33+Q33+S33) -> 4287.2 | CQ33: =ROUND((ROUND((AC33*AW33*1),2)*BC33),2) -> 24.01 | CR33: =(ROUND((ROUND((((ET33*1.1))*AV33*1),2)*BB33),2)+ROUND((ROUND(((AE33-((EU33*1.1)))*AV33*1),2)*BS33),2)) -> 0 | CS33: =ROUND((ROUND((AE33*AV33*1),2)*BS33),2) -> 0 | CT33: =ROUND((ROUND((AF33*AV33*1),2)*BA33),2) -> 2119.86 | CU33: =AG33 -> 0 | CV33: =(AH33*AV33) -> 3.052005 | CW33: =AI33 -> 0 | CX33: =AJ33 -> 0 | CY33: =(((S33+R33)*AT33)/100) -> 3815.262 | CZ33: =(((S33+R33)*AU33)/100) -> 1950.0228 | DE33: *1,1 | DF33: *1,1 | DG33: *1,1 | DI33: *1,1 | DJ33: *1,1 | DN33: 0 | DO33: 0 | DP33: 1 | DQ33: 1 | DU33: 1013 | DV33: 1 ШТ. | DW33: 1 ШТ. | DX33: 1 | EE33: 58162630 | EF33: 40 | EG33: Монтаж оборудования | EH33: 0 | EJ33: 2 | EK33: 68 | EL33: ТСН-2001.4-10. Прокладка и монтаж сетей связи | EM33: ТСН-2001.4-10-1 | EO33: Поправка: Гл.12.Прил.8.п.8. 5_12.00.01.11.003 | EQ33: 0 | ER33: 35.81 | ES33: 2.34 | ET33: 0 | EU33: 0 | EV33: 33.47 | EW33: 2.65 | EX33: 0 | EY33: 0 | FQ33: 0 | FR33: 0 | FS33: 0 | FX33: 90 | FY33: 46 | GD33: 1 | GF33: -1323780471 | GG33: 2 | GH33: 1 | GI33: 2 | GJ33: 0 | GK33: 0 | GL33: =ROUND(IF(AND(BH33=3,BI33=3,FS33<>0),P33,0),2) -> 0 | GM33: =ROUND(O33+X33+Y33,2)+GX33 -> 10052.48 | GN33: =IF(OR(BI33=0,BI33=1),GM33-GX33,0) -> 0 | GO33: =IF(BI33=2,GM33-GX33,0) -> 10052.48 | GP33: =IF(BI33=4,GM33-GX33,0) -> 0 | GR33: 0 | GS33: 3 | GT33: 0 | GV33: =ROUND((GT33),6) -> 0 | GW33: 1 | GX33: =ROUND(HC33*I33,2) -> 0 | HA33: 0 | HB33: 0 | HC33: =GV33*GW33 -> 0 | HS33: 0 | IK33: 0
A34: 18 | B34: 1 | E34: 2,1 | F34: КА 2 | G34: Блок индикации и управления R3-Рубеж-БИУ 319531 | H34: шт. | I34: =I32*J34 -> 2 | J34: 1 | K34: 1 | O34: =ROUND(CP34,2) -> 4792.7 | P34: =ROUND((ROUND((AC34*I34),2)*BC34),2) -> 4792.7 | Q34: =(ROUND((ROUND(((ET34)*AV34*I34),2)*BB34),2)+ROUND((ROUND(((AE34-(EU34))*AV34*I34),2)*BS34),2)) -> 0 | R34: =ROUND((ROUND((AE34*AV34*I34),2)*BS34),2) -> 0 | S34: =ROUND((ROUND((AF34*AV34*I34),2)*BA34),2) -> 0 | T34: =ROUND(CU34*I34,2) -> 0 | U34: =CV34*I34 -> 0 | V34: =CW34*I34 -> 0 | W34: =ROUND(CX34*I34,2) -> 0 | X34: =ROUND(CY34,2) -> 0 | Y34: =ROUND(CZ34,2) -> 0 | AA34: 56498966 | AB34: =ROUND((AC34+AD34+AF34),6) -> 2396.35 | AC34: =ROUND((ES34),6) -> 2396.35 | AD34: =ROUND((((ET34)-(EU34))+AE34),6) -> 0 | AE34: =ROUND((EU34),6) -> 0 | AF34: =ROUND((EV34),6) -> 0 | AG34: =ROUND((AP34),6) -> 0 | AH34: =(EW34) -> 0 | AI34: =(EX34) -> 0 | AJ34: =(AS34) -> 0 | AK34: 2396.35 | AL34: 2396.35 | AM34: 0 | AN34: 0 | AO34: 0 | AP34: 0 | AQ34: 0 | AR34: 0 | AS34: 0 | AT34: 0 | AU34: 0 | AV34: 1 | AW34: 1 | AZ34: 1 | BA34: 1 | BB34: 1 | BC34: 1 | BH34: 3 | BI34: 3 | BM34: 746 | BN34: 0 | BP34: 0 | BQ34: 130 | BR34: 0 | BS34: 1 | BT34: 1 | BU34: 1 | BV34: 1 | BW34: 1 | BX34: 1 | BZ34: 90 | CA34: 46 | CE34: 30 | CF34: 0 | CG34: 0 | CM34: 0 | CO34: 0 | CP34: =(P34+Q34+S34) -> 4792.7 | CQ34: =ROUND((ROUND((AC34*1),2)*BC34),2) -> 2396.35 | CR34: =(ROUND((ROUND(((ET34)*AV34*1),2)*BB34),2)+ROUND((ROUND(((AE34-(EU34))*AV34*1),2)*BS34),2)) -> 0 | CS34: =ROUND((ROUND((AE34*AV34*1),2)*BS34),2) -> 0 | CT34: =ROUND((ROUND((AF34*AV34*1),2)*BA34),2) -> 0 | CU34: =AG34 -> 0 | CV34: =(AH34*AV34) -> 0 | CW34: =AI34 -> 0 | CX34: =AJ34 -> 0 | CY34: =(((S34+R34)*AT34)/100) -> 0 | CZ34: =(((S34+R34)*AU34)/100) -> 0 | DN34: 0 | DO34: 0 | DP34: 1 | DQ34: 1 | DU34: 1010 | DV34: шт. | DW34: шт. | DX34: 1 | EE34: 58162750 | EF34: 130 | EG34: Сметная стоимость оборудования | EH34: 0 | EJ34: 3 | EK34: 746 | EL34: ТСН-2001.13. Сметная стоимость оборудования | EM34: ТСН-2001.13 | EQ34: 0 | ER34: 0 | ES34: 2396.35 | ET34: 0 | EU34: 0 | EV34: 0 | EW34: 0 | EX34: 0 | FQ34: 0 | FR34: =P34 -> 4792.7 | FS34: 0 | FX34: 90 | FY34: 46 | GA34: [21 132 / 1,2 / 7,66] + 3% Трансп + 1,2% Заг.скл | GD34: 1 | GF34: 212161352 | GG34: 2 | GH34: 4 | GI34: -2 | GJ34: 0 | GK34: 0 | GL34: =ROUND(IF(AND(BH34=3,BI34=3,FS34<>0),P34,0),2) -> 0 | GM34: =ROUND(O34+X34+Y34,2)+GX34 -> 4792.7 | GN34: =IF(OR(BI34=0,BI34=1),GM34-GX34,0) -> 0 | GO34: =IF(BI34=2,GM34-GX34,0) -> 0 | GP34: =IF(BI34=4,GM34-GX34,0) -> 0 | GR34: 0 | GS34: 2 | GT34: 0 | GV34: =ROUND((GT34),6) -> 0 | GW34: 1 | GX34: =ROUND(HC34*I34,2) -> 0 | HA34: 0 | HB34: 0 | HC34: =GV34*GW34 -> 0 | HE34: 3 | HF34: 1,2 | HS34: 0 | IK34: 0
A35: 18 | B35: 1 | E35: 2,1 | F35: КА 2 | G35: Блок индикации и управления R3-Рубеж-БИУ 319531 | H35: шт. | I35: =I33*J35 -> 2 | J35: 1 | K35: 1 | O35: =ROUND(CP35,2) -> 36712.08 | P35: =ROUND((ROUND((AC35*I35),2)*BC35),2) -> 36712.08 | Q35: =(ROUND((ROUND(((ET35)*AV35*I35),2)*BB35),2)+ROUND((ROUND(((AE35-(EU35))*AV35*I35),2)*BS35),2)) -> 0 | R35: =ROUND((ROUND((AE35*AV35*I35),2)*BS35),2) -> 0 | S35: =ROUND((ROUND((AF35*AV35*I35),2)*BA35),2) -> 0 | T35: =ROUND(CU35*I35,2) -> 0 | U35: =CV35*I35 -> 0 | V35: =CW35*I35 -> 0 | W35: =ROUND(CX35*I35,2) -> 0 | X35: =ROUND(CY35,2) -> 0 | Y35: =ROUND(CZ35,2) -> 0 | AA35: 56498968 | AB35: =ROUND((AC35+AD35+AF35),6) -> 2396.35 | AC35: =ROUND((ES35),6) -> 2396.35 | AD35: =ROUND((((ET35)-(EU35))+AE35),6) -> 0 | AE35: =ROUND((EU35),6) -> 0 | AF35: =ROUND((EV35),6) -> 0 | AG35: =ROUND((AP35),6) -> 0 | AH35: =(EW35) -> 0 | AI35: =(EX35) -> 0 | AJ35: =(AS35) -> 0 | AK35: 2396.35 | AL35: 2396.35 | AM35: 0 | AN35: 0 | AO35: 0 | AP35: 0 | AQ35: 0 | AR35: 0 | AS35: 0 | AT35: 0 | AU35: 0 | AV35: 1 | AW35: 1 | AZ35: 1 | BA35: 1 | BB35: 1 | BC35: 7.66 | BH35: 3 | BI35: 3 | BM35: 746 | BN35: 0 | BP35: 0 | BQ35: 130 | BR35: 0 | BS35: 1 | BT35: 1 | BU35: 1 | BV35: 1 | BW35: 1 | BX35: 1 | BZ35: 90 | CA35: 46 | CE35: 30 | CF35: 0 | CG35: 0 | CM35: 0 | CO35: 0 | CP35: =(P35+Q35+S35) -> 36712.08 | CQ35: =ROUND((ROUND((AC35*1),2)*BC35),2) -> 18356.04 | CR35: =(ROUND((ROUND(((ET35)*AV35*1),2)*BB35),2)+ROUND((ROUND(((AE35-(EU35))*AV35*1),2)*BS35),2)) -> 0 | CS35: =ROUND((ROUND((AE35*AV35*1),2)*BS35),2) -> 0 | CT35: =ROUND((ROUND((AF35*AV35*1),2)*BA35),2) -> 0 | CU35: =AG35 -> 0 | CV35: =(AH35*AV35) -> 0 | CW35: =AI35 -> 0 | CX35: =AJ35 -> 0 | CY35: =(((S35+R35)*AT35)/100) -> 0 | CZ35: =(((S35+R35)*AU35)/100) -> 0 | DN35: 0 | DO35: 0 | DP35: 1 | DQ35: 1 | DU35: 1010 | DV35: шт. | DW35: шт. | DX35: 1 | EE35: 58162750 | EF35: 130 | EG35: Сметная стоимость оборудования | EH35: 0 | EJ35: 3 | EK35: 746 | EL35: ТСН-2001.13. Сметная стоимость оборудования | EM35: ТСН-2001.13 | EQ35: 0 | ER35: 2396.35 | ES35: 2396.35 | ET35: 0 | EU35: 0 | EV35: 0 | EW35: 0 | EX35: 0 | EZ35: 5 | FC35: 1 | FD35: 18 | FF35: 21132 | FQ35: 0 | FR35: =P35 -> 36712.08 | FS35: 0 | FX35: 90 | FY35: 46 | GA35: [21 132 / 1,2 / 7,66] + 3% Трансп + 1,2% Заг.скл | GD35: 1 | GF35: 212161352 | GG35: 2 | GH35: 3 | GI35: 5 | GJ35: 0 | GK35: 0 | GL35: =ROUND(IF(AND(BH35=3,BI35=3,FS35<>0),P35,0),2) -> 0 | GM35: =ROUND(O35+X35+Y35,2)+GX35 -> 36712.08 | GN35: =IF(OR(BI35=0,BI35=1),GM35-GX35,0) -> 0 | GO35: =IF(BI35=2,GM35-GX35,0) -> 0 | GP35: =IF(BI35=4,GM35-GX35,0) -> 0 | GR35: 1 | GS35: 1 | GT35: 0 | GV35: =ROUND((GT35),6) -> 0 | GW35: 1 | GX35: =ROUND(HC35*I35,2) -> 0 | HA35: 0 | HB35: 0 | HC35: =GV35*GW35 -> 0 | HE35: 3 | HF35: 1,2 | HS35: 0 | IK35: 0
A36: 17 | B36: 1 | D36: =ROW(EtalonRes!A15) -> 15 | E36: 3 | F36: 4.11-12-1 | G36: Установка съемных и выдвижных блоков (модулей, ячеек, ТЭЗ) массой до 5 кг | H36: 1 ШТ. | I36: =ROUND(ROUND(1,4),9) -> 1 | J36: 0 | K36: =ROUND(ROUND(1,4),9) -> 1 | O36: =ROUND(CP36,2) -> 14 | P36: =ROUND((ROUND((AC36*AW36*I36),2)*BC36),2) -> 0 | Q36: =(ROUND((ROUND((((ET36*1.1))*AV36*I36),2)*BB36),2)+ROUND((ROUND(((AE36-((EU36*1.1)))*AV36*I36),2)*BS36),2)) -> 0.58 | R36: =ROUND((ROUND((AE36*AV36*I36),2)*BS36),2) -> 0.09 | S36: =ROUND((ROUND((AF36*AV36*I36),2)*BA36),2) -> 13.42 | T36: =ROUND(CU36*I36,2) -> 0 | U36: =CV36*I36 -> 1.186251 | V36: =CW36*I36 -> 0 | W36: =ROUND(CX36*I36,2) -> 0 | X36: =ROUND(CY36,2) -> 12.16 | Y36: =ROUND(CZ36,2) -> 6.21 | AA36: 56498966 | AB36: =ROUND((AC36+AD36+AF36),6) -> 13.365 | AC36: =ROUND((ES36),6) -> 0 | AD36: =ROUND(((((ET36*1.1))-((EU36*1.1)))+AE36),6) -> 0.55 | AE36: =ROUND(((EU36*1.1)),6) -> 0.088 | AF36: =ROUND(((EV36*1.1)),6) -> 12.815 | AG36: =ROUND((AP36),6) -> 0 | AH36: =((EW36*1.1)) -> 1.133 | AI36: =((EX36*1.1)) -> 0 | AJ36: =(AS36) -> 0 | AK36: 12.15 | AL36: 0 | AM36: 0.5 | AN36: 0.08 | AO36: 11.65 | AP36: 0 | AQ36: 1.03 | AR36: 0 | AS36: 0 | AT36: 90 | AU36: 46 | AV36: 1.047 | AW36: 1 | AZ36: 1 | BA36: 1 | BB36: 1 | BC36: 1 | BH36: 0 | BI36: 2 | BJ36: ТСН-2001.4 Доп. 68, Сб. 11, т. 12, поз. 1 | BM36: 72 | BN36: 0 | BO36: 4.11-12-1 | BP36: 1 | BQ36: 40 | BR36: 0 | BS36: 1 | BT36: 1 | BU36: 1 | BV36: 1 | BW36: 1 | BX36: 1 | BZ36: 90 | CA36: 46 | CE36: 30 | CF36: 0 | CG36: 0 | CM36: 0 | CO36: 0 | CP36: =(P36+Q36+S36) -> 14 | CQ36: =ROUND((ROUND((AC36*AW36*1),2)*BC36),2) -> 0 | CR36: =(ROUND((ROUND((((ET36*1.1))*AV36*1),2)*BB36),2)+ROUND((ROUND(((AE36-((EU36*1.1)))*AV36*1),2)*BS36),2)) -> 0.58 | CS36: =ROUND((ROUND((AE36*AV36*1),2)*BS36),2) -> 0.09 | CT36: =ROUND((ROUND((AF36*AV36*1),2)*BA36),2) -> 13.42 | CU36: =AG36 -> 0 | CV36: =(AH36*AV36) -> 1.186251 | CW36: =AI36 -> 0 | CX36: =AJ36 -> 0 | CY36: =(((S36+R36)*AT36)/100) -> 12.159 | CZ36: =(((S36+R36)*AU36)/100) -> 6.2146 | DE36: *1,1 | DF36: *1,1 | DG36: *1,1 | DI36: *1,1 | DJ36: *1,1 | DN36: 0 | DO36: 0 | DP36: 1 | DQ36: 1 | DU36: 1013 | DV36: 1 ШТ. | DW36: 1 ШТ. | DX36: 1 | EE36: 58162634 | EF36: 40 | EG36: Монтаж оборудования | EH36: 0 | EJ36: 2 | EK36: 72 | EL36: ТСН-2001.4-11. Приборы и средства автоматизации и вычислительной техники | EM36: ТСН-2001.4-11-1 | EO36: Поправка: Гл.12.Прил.8.п.8. 5_12.00.01.11.003 | EQ36: 0 | ER36: 12.15 | ES36: 0 | ET36: 0.5 | EU36: 0.08 | EV36: 11.65 | EW36: 1.03 | EX36: 0 | EY36: 0 | FQ36: 0 | FR36: 0 | FS36: 0 | FX36: 90 | FY36: 46 | GD36: 1 | GF36: 1708693888 | GG36: 2 | GH36: 1 | GI36: 2 | GJ36: 0 | GK36: 0 | GL36: =ROUND(IF(AND(BH36=3,BI36=3,FS36<>0),P36,0),2) -> 0 | GM36: =ROUND(O36+X36+Y36,2)+GX36 -> 32.37 | GN36: =IF(OR(BI36=0,BI36=1),GM36-GX36,0) -> 0 | GO36: =IF(BI36=2,GM36-GX36,0) -> 32.37 | GP36: =IF(BI36=4,GM36-GX36,0) -> 0 | GR36: 0 | GS36: 3 | GT36: 0 | GV36: =ROUND((GT36),6) -> 0 | GW36: 1 | GX36: =ROUND(HC36*I36,2) -> 0 | HA36: 0 | HB36: 0 | HC36: =GV36*GW36 -> 0 | HS36: 0 | IK36: 0
A37: 17 | B37: 1 | D37: =ROW(EtalonRes!A18) -> 18 | E37: 3 | F37: 4.11-12-1 | G37: Установка съемных и выдвижных блоков (модулей, ячеек, ТЭЗ) массой до 5 кг | H37: 1 ШТ. | I37: =ROUND(ROUND(1,4),9) -> 1 | J37: 0 | K37: =ROUND(ROUND(1,4),9) -> 1 | O37: =ROUND(CP37,2) -> 747.4 | P37: =ROUND((ROUND((AC37*AW37*I37),2)*BC37),2) -> 0 | Q37: =(ROUND((ROUND((((ET37*1.1))*AV37*I37),2)*BB37),2)+ROUND((ROUND(((AE37-((EU37*1.1)))*AV37*I37),2)*BS37),2)) -> 9.43 | R37: =ROUND((ROUND((AE37*AV37*I37),2)*BS37),2) -> 4.95 | S37: =ROUND((ROUND((AF37*AV37*I37),2)*BA37),2) -> 737.97 | T37: =ROUND(CU37*I37,2) -> 0 | U37: =CV37*I37 -> 1.186251 | V37: =CW37*I37 -> 0 | W37: =ROUND(CX37*I37,2) -> 0 | X37: =ROUND(CY37,2) -> 668.63 | Y37: =ROUND(CZ37,2) -> 341.74 | AA37: 56498968 | AB37: =ROUND((AC37+AD37+AF37),6) -> 13.365 | AC37: =ROUND((ES37),6) -> 0 | AD37: =ROUND(((((ET37*1.1))-((EU37*1.1)))+AE37),6) -> 0.55 | AE37: =ROUND(((EU37*1.1)),6) -> 0.088 | AF37: =ROUND(((EV37*1.1)),6) -> 12.815 | AG37: =ROUND((AP37),6) -> 0 | AH37: =((EW37*1.1)) -> 1.133 | AI37: =((EX37*1.1)) -> 0 | AJ37: =(AS37) -> 0 | AK37: 12.15 | AL37: 0 | AM37: 0.5 | AN37: 0.08 | AO37: 11.65 | AP37: 0 | AQ37: 1.03 | AR37: 0 | AS37: 0 | AT37: 90 | AU37: 46 | AV37: 1.047 | AW37: 1 | AZ37: 1 | BA37: 54.99 | BB37: 16.26 | BC37: 1 | BH37: 0 | BI37: 2 | BJ37: ТСН-2001.4 Доп. 68, Сб. 11, т. 12, поз. 1 | BM37: 72 | BN37: 0 | BO37: 4.11-12-1 | BP37: 1 | BQ37: 40 | BR37: 0 | BS37: 54.99 | BT37: 1 | BU37: 1 | BV37: 1 | BW37: 1 | BX37: 1 | BZ37: 90 | CA37: 46 | CE37: 30 | CF37: 0 | CG37: 0 | CM37: 0 | CO37: 0 | CP37: =(P37+Q37+S37) -> 747.4 | CQ37: =ROUND((ROUND((AC37*AW37*1),2)*BC37),2) -> 0 | CR37: =(ROUND((ROUND((((ET37*1.1))*AV37*1),2)*BB37),2)+ROUND((ROUND(((AE37-((EU37*1.1)))*AV37*1),2)*BS37),2)) -> 9.43 | CS37: =ROUND((ROUND((AE37*AV37*1),2)*BS37),2) -> 4.95 | CT37: =ROUND((ROUND((AF37*AV37*1),2)*BA37),2) -> 737.97 | CU37: =AG37 -> 0 | CV37: =(AH37*AV37) -> 1.186251 | CW37: =AI37 -> 0 | CX37: =AJ37 -> 0 | CY37: =(((S37+R37)*AT37)/100) -> 668.628 | CZ37: =(((S37+R37)*AU37)/100) -> 341.7432 | DE37: *1,1 | DF37: *1,1 | DG37: *1,1 | DI37: *1,1 | DJ37: *1,1 | DN37: 0 | DO37: 0 | DP37: 1 | DQ37: 1 | DU37: 1013 | DV37: 1 ШТ. | DW37: 1 ШТ. | DX37: 1 | EE37: 58162634 | EF37: 40 | EG37: Монтаж оборудования | EH37: 0 | EJ37: 2 | EK37: 72 | EL37: ТСН-2001.4-11. Приборы и средства автоматизации и вычислительной техники | EM37: ТСН-2001.4-11-1 | EO37: Поправка: Гл.12.Прил.8.п.8. 5_12.00.01.11.003 | EQ37: 0 | ER37: 12.15 | ES37: 0 | ET37: 0.5 | EU37: 0.08 | EV37: 11.65 | EW37: 1.03 | EX37: 0 | EY37: 0 | FQ37: 0 | FR37: 0 | FS37: 0 | FX37: 90 | FY37: 46 | GD37: 1 | GF37: 1708693888 | GG37: 2 | GH37: 1 | GI37: 2 | GJ37: 0 | GK37: 0 | GL37: =ROUND(IF(AND(BH37=3,BI37=3,FS37<>0),P37,0),2) -> 0 | GM37: =ROUND(O37+X37+Y37,2)+GX37 -> 1757.77 | GN37: =IF(OR(BI37=0,BI37=1),GM37-GX37,0) -> 0 | GO37: =IF(BI37=2,GM37-GX37,0) -> 1757.77 | GP37: =IF(BI37=4,GM37-GX37,0) -> 0 | GR37: 0 | GS37: 3 | GT37: 0 | GV37: =ROUND((GT37),6) -> 0 | GW37: 1 | GX37: =ROUND(HC37*I37,2) -> 0 | HA37: 0 | HB37: 0 | HC37: =GV37*GW37 -> 0 | HS37: 0 | IK37: 0
A38: 18 | B38: 1 | E38: 3,1 | F38: КА 3 | G38: Модуль связи R3-МС 377218 | H38: шт. | I38: =I36*J38 -> 1 | J38: 1 | K38: 1 | O38: =ROUND(CP38,2) -> 1908.27 | P38: =ROUND((ROUND((AC38*I38),2)*BC38),2) -> 1908.27 | Q38: =(ROUND((ROUND(((ET38)*AV38*I38),2)*BB38),2)+ROUND((ROUND(((AE38-(EU38))*AV38*I38),2)*BS38),2)) -> 0 | R38: =ROUND((ROUND((AE38*AV38*I38),2)*BS38),2) -> 0 | S38: =ROUND((ROUND((AF38*AV38*I38),2)*BA38),2) -> 0 | T38: =ROUND(CU38*I38,2) -> 0 | U38: =CV38*I38 -> 0 | V38: =CW38*I38 -> 0 | W38: =ROUND(CX38*I38,2) -> 0 | X38: =ROUND(CY38,2) -> 0 | Y38: =ROUND(CZ38,2) -> 0 | AA38: 56498966 | AB38: =ROUND((AC38+AD38+AF38),6) -> 1908.27 | AC38: =ROUND((ES38),6) -> 1908.27 | AD38: =ROUND((((ET38)-(EU38))+AE38),6) -> 0 | AE38: =ROUND((EU38),6) -> 0 | AF38: =ROUND((EV38),6) -> 0 | AG38: =ROUND((AP38),6) -> 0 | AH38: =(EW38) -> 0 | AI38: =(EX38) -> 0 | AJ38: =(AS38) -> 0 | AK38: 1908.27 | AL38: 1908.27 | AM38: 0 | AN38: 0 | AO38: 0 | AP38: 0 | AQ38: 0 | AR38: 0 | AS38: 0 | AT38: 0 | AU38: 0 | AV38: 1 | AW38: 1 | AZ38: 1 | BA38: 1 | BB38: 1 | BC38: 1 | BH38: 3 | BI38: 3 | BM38: 746 | BN38: 0 | BP38: 0 | BQ38: 130 | BR38: 0 | BS38: 1 | BT38: 1 | BU38: 1 | BV38: 1 | BW38: 1 | BX38: 1 | BZ38: 90 | CA38: 46 | CE38: 30 | CF38: 0 | CG38: 0 | CM38: 0 | CO38: 0 | CP38: =(P38+Q38+S38) -> 1908.27 | CQ38: =ROUND((ROUND((AC38*1),2)*BC38),2) -> 1908.27 | CR38: =(ROUND((ROUND(((ET38)*AV38*1),2)*BB38),2)+ROUND((ROUND(((AE38-(EU38))*AV38*1),2)*BS38),2)) -> 0 | CS38: =ROUND((ROUND((AE38*AV38*1),2)*BS38),2) -> 0 | CT38: =ROUND((ROUND((AF38*AV38*1),2)*BA38),2) -> 0 | CU38: =AG38 -> 0 | CV38: =(AH38*AV38) -> 0 | CW38: =AI38 -> 0 | CX38: =AJ38 -> 0 | CY38: =(((S38+R38)*AT38)/100) -> 0 | CZ38: =(((S38+R38)*AU38)/100) -> 0 | DN38: 0 | DO38: 0 | DP38: 1 | DQ38: 1 | DU38: 1010 | DV38: шт. | DW38: шт. | DX38: 1 | EE38: 58162750 | EF38: 130 | EG38: Сметная стоимость оборудования | EH38: 0 | EJ38: 3 | EK38: 746 | EL38: ТСН-2001.13. Сметная стоимость оборудования | EM38: ТСН-2001.13 | EQ38: 0 | ER38: 0 | ES38: 1908.27 | ET38: 0 | EU38: 0 | EV38: 0 | EW38: 0 | EX38: 0 | FQ38: 0 | FR38: =P38 -> 1908.27 | FS38: 0 | FX38: 90 | FY38: 46 | GA38: [16 828 / 1,2 / 7,66] + 3% Трансп + 1,2% Заг.скл | GD38: 1 | GF38: 1719580913 | GG38: 2 | GH38: 4 | GI38: -2 | GJ38: 0 | GK38: 0 | GL38: =ROUND(IF(AND(BH38=3,BI38=3,FS38<>0),P38,0),2) -> 0 | GM38: =ROUND(O38+X38+Y38,2)+GX38 -> 1908.27 | GN38: =IF(OR(BI38=0,BI38=1),GM38-GX38,0) -> 0 | GO38: =IF(BI38=2,GM38-GX38,0) -> 0 | GP38: =IF(BI38=4,GM38-GX38,0) -> 0 | GR38: 0 | GS38: 2 | GT38: 0 | GV38: =ROUND((GT38),6) -> 0 | GW38: 1 | GX38: =ROUND(HC38*I38,2) -> 0 | HA38: 0 | HB38: 0 | HC38: =GV38*GW38 -> 0 | HE38: 3 | HF38: 1,2 | HS38: 0 | IK38: 0
A39: 18 | B39: 1 | E39: 3,1 | F39: КА 3 | G39: Модуль связи R3-МС 377218 | H39: шт. | I39: =I37*J39 -> 1 | J39: 1 | K39: 1 | O39: =ROUND(CP39,2) -> 14617.35 | P39: =ROUND((ROUND((AC39*I39),2)*BC39),2) -> 14617.35 | Q39: =(ROUND((ROUND(((ET39)*AV39*I39),2)*BB39),2)+ROUND((ROUND(((AE39-(EU39))*AV39*I39),2)*BS39),2)) -> 0 | R39: =ROUND((ROUND((AE39*AV39*I39),2)*BS39),2) -> 0 | S39: =ROUND((ROUND((AF39*AV39*I39),2)*BA39),2) -> 0 | T39: =ROUND(CU39*I39,2) -> 0 | U39: =CV39*I39 -> 0 | V39: =CW39*I39 -> 0 | W39: =ROUND(CX39*I39,2) -> 0 | X39: =ROUND(CY39,2) -> 0 | Y39: =ROUND(CZ39,2) -> 0 | AA39: 56498968 | AB39: =ROUND((AC39+AD39+AF39),6) -> 1908.27 | AC39: =ROUND((ES39),6) -> 1908.27 | AD39: =ROUND((((ET39)-(EU39))+AE39),6) -> 0 | AE39: =ROUND((EU39),6) -> 0 | AF39: =ROUND((EV39),6) -> 0 | AG39: =ROUND((AP39),6) -> 0 | AH39: =(EW39) -> 0 | AI39: =(EX39) -> 0 | AJ39: =(AS39) -> 0 | AK39: 1908.27 | AL39: 1908.27 | AM39: 0 | AN39: 0 | AO39: 0 | AP39: 0 | AQ39: 0 | AR39: 0 | AS39: 0 | AT39: 0 | AU39: 0 | AV39: 1 | AW39: 1 | AZ39: 1 | BA39: 1 | BB39: 1 | BC39: 7.66 | BH39: 3 | BI39: 3 | BM39: 746 | BN39: 0 | BP39: 0 | BQ39: 130 | BR39: 0 | BS39: 1 | BT39: 1 | BU39: 1 | BV39: 1 | BW39: 1 | BX39: 1 | BZ39: 90 | CA39: 46 | CE39: 30 | CF39: 0 | CG39: 0 | CM39: 0 | CO39: 0 | CP39: =(P39+Q39+S39) -> 14617.35 | CQ39: =ROUND((ROUND((AC39*1),2)*BC39),2) -> 14617.35 | CR39: =(ROUND((ROUND(((ET39)*AV39*1),2)*BB39),2)+ROUND((ROUND(((AE39-(EU39))*AV39*1),2)*BS39),2)) -> 0 | CS39: =ROUND((ROUND((AE39*AV39*1),2)*BS39),2) -> 0 | CT39: =ROUND((ROUND((AF39*AV39*1),2)*BA39),2) -> 0 | CU39: =AG39 -> 0 | CV39: =(AH39*AV39) -> 0 | CW39: =AI39 -> 0 | CX39: =AJ39 -> 0 | CY39: =(((S39+R39)*AT39)/100) -> 0 | CZ39: =(((S39+R39)*AU39)/100) -> 0 | DN39: 0 | DO39: 0 | DP39: 1 | DQ39: 1 | DU39: 1010 | DV39: шт. | DW39: шт. | DX39: 1 | EE39: 58162750 | EF39: 130 | EG39: Сметная стоимость оборудования | EH39: 0 | EJ39: 3 | EK39: 746 | EL39: ТСН-2001.13. Сметная стоимость оборудования | EM39: ТСН-2001.13 | EQ39: 0 | ER39: 1908.27 | ES39: 1908.27 | ET39: 0 | EU39: 0 | EV39: 0 | EW39: 0 | EX39: 0 | EZ39: 5 | FC39: 1 | FD39: 18 | FF39: 16828 | FQ39: 0 | FR39: =P39 -> 14617.35 | FS39: 0 | FX39: 90 | FY39: 46 | GA39: [16 828 / 1,2 / 7,66] + 3% Трансп + 1,2% Заг.скл | GD39: 1 | GF39: 1719580913 | GG39: 2 | GH39: 3 | GI39: 5 | GJ39: 0 | GK39: 0 | GL39: =ROUND(IF(AND(BH39=3,BI39=3,FS39<>0),P39,0),2) -> 0 | GM39: =ROUND(O39+X39+Y39,2)+GX39 -> 14617.35 | GN39: =IF(OR(BI39=0,BI39=1),GM39-GX39,0) -> 0 | GO39: =IF(BI39=2,GM39-GX39,0) -> 0 | GP39: =IF(BI39=4,GM39-GX39,0) -> 0 | GR39: 1 | GS39: 1 | GT39: 0 | GV39: =ROUND((GT39),6) -> 0 | GW39: 1 | GX39: =ROUND(HC39*I39,2) -> 0 | HA39: 0 | HB39: 0 | HC39: =GV39*GW39 -> 0 | HE39: 3 | HF39: 1,2 | HS39: 0 | IK39: 0
A40: 17 | B40: 1 | D40: =ROW(EtalonRes!A19) -> 19 | E40: 4 | F40: 4.10-81-2 | G40: Извещатели ПС автоматические, дымовой, фотоэлектрический, радиоизотопный, световой в нормальном исполнении | H40: 1 ШТ. | I40: 589 | J40: 0 | K40: 589 | O40: =ROUND(CP40,2) -> 15163.89 | P40: =ROUND((ROUND((AC40*AW40*I40),2)*BC40),2) -> 742.14 | Q40: =(ROUND((ROUND((((ET40*1.1))*AV40*I40),2)*BB40),2)+ROUND((ROUND(((AE40-((EU40*1.1)))*AV40*I40),2)*BS40),2)) -> 40.7 | R40: =ROUND((ROUND((AE40*AV40*I40),2)*BS40),2) -> 6.78 | S40: =ROUND((ROUND((AF40*AV40*I40),2)*BA40),2) -> 14381.05 | T40: =ROUND(CU40*I40,2) -> 0 | U40: =CV40*I40 -> 1139.6302 | V40: =CW40*I40 -> 0 | W40: =ROUND(CX40*I40,2) -> 0 | X40: =ROUND(CY40,2) -> 12949.05 | Y40: =ROUND(CZ40,2) -> 6618.4 | AA40: 56498966 | AB40: =ROUND((AC40+AD40+AF40),6) -> 24.646 | AC40: =ROUND((ES40),6) -> 1.26 | AD40: =ROUND(((((ET40*1.1))-((EU40*1.1)))+AE40),6) -> 0.066 | AE40: =ROUND(((EU40*1.1)),6) -> 0.011 | AF40: =ROUND(((EV40*1.1)),6) -> 23.32 | AG40: =ROUND((AP40),6) -> 0 | AH40: =((EW40*1.1)) -> 1.848 | AI40: =((EX40*1.1)) -> 0 | AJ40: =(AS40) -> 0 | AK40: 22.52 | AL40: 1.26 | AM40: 0.06 | AN40: 0.01 | AO40: 21.2 | AP40: 0 | AQ40: 1.68 | AR40: 0 | AS40: 0 | AT40: 90 | AU40: 46 | AV40: 1.047 | AW40: 1 | AZ40: 1 | BA40: 1 | BB40: 1 | BC40: 1 | BH40: 0 | BI40: 2 | BJ40: ТСН-2001.4. Доп. 1-42. Сб. 10, т. 81, поз. 2 | BM40: 68 | BN40: 0 | BO40: 4.10-81-2 | BP40: 1 | BQ40: 40 | BR40: 0 | BS40: 1 | BT40: 1 | BU40: 1 | BV40: 1 | BW40: 1 | BX40: 1 | BZ40: 90 | CA40: 46 | CE40: 30 | CF40: 0 | CG40: 0 | CM40: 0 | CO40: 0 | CP40: =(P40+Q40+S40) -> 15163.89 | CQ40: =ROUND((ROUND((AC40*AW40*1),2)*BC40),2) -> 1.26 | CR40: =(ROUND((ROUND((((ET40*1.1))*AV40*1),2)*BB40),2)+ROUND((ROUND(((AE40-((EU40*1.1)))*AV40*1),2)*BS40),2)) -> 0.07 | CS40: =ROUND((ROUND((AE40*AV40*1),2)*BS40),2) -> 0.01 | CT40: =ROUND((ROUND((AF40*AV40*1),2)*BA40),2) -> 24.42 | CU40: =AG40 -> 0 | CV40: =(AH40*AV40) -> 1.934856 | CW40: =AI40 -> 0 | CX40: =AJ40 -> 0 | CY40: =(((S40+R40)*AT40)/100) -> 12949.047 | CZ40: =(((S40+R40)*AU40)/100) -> 6618.4018 | DE40: *1,1 | DF40: *1,1 | DG40: *1,1 | DI40: *1,1 | DJ40: *1,1 | DN40: 0 | DO40: 0 | DP40: 1 | DQ40: 1 | DU40: 1013 | DV40: 1 ШТ. | DW40: 1 ШТ. | DX40: 1 | EE40: 58162630 | EF40: 40 | EG40: Монтаж оборудования | EH40: 0 | EJ40: 2 | EK40: 68 | EL40: ТСН-2001.4-10. Прокладка и монтаж сетей связи | EM40: ТСН-2001.4-10-1 | EO40: Поправка: Гл.12.Прил.8.п.8. 5_12.00.01.11.003 | EQ40: 0 | ER40: 22.52 | ES40: 1.26 | ET40: 0.06 | EU40: 0.01 | EV40: 21.2 | EW40: 1.68 | EX40: 0 | EY40: 0 | FQ40: 0 | FR40: 0 | FS40: 0 | FX40: 90 | FY40: 46 | GD40: 1 | GF40: -1912799884 | GG40: 2 | GH40: 1 | GI40: 2 | GJ40: 0 | GK40: 0 | GL40: =ROUND(IF(AND(BH40=3,BI40=3,FS40<>0),P40,0),2) -> 0 | GM40: =ROUND(O40+X40+Y40,2)+GX40 -> 34731.34 | GN40: =IF(OR(BI40=0,BI40=1),GM40-GX40,0) -> 0 | GO40: =IF(BI40=2,GM40-GX40,0) -> 34731.34 | GP40: =IF(BI40=4,GM40-GX40,0) -> 0 | GR40: 0 | GS40: 3 | GT40: 0 | GV40: =ROUND((GT40),6) -> 0 | GW40: 1 | GX40: =ROUND(HC40*I40,2) -> 0 | HA40: 0 | HB40: 0 | HC40: =GV40*GW40 -> 0 | HS40: 0 | IK40: 0
A41: 17 | B41: 1 | D41: =ROW(EtalonRes!A20) -> 20 | E41: 4 | F41: 4.10-81-2 | G41: Извещатели ПС автоматические, дымовой, фотоэлектрический, радиоизотопный, световой в нормальном исполнении | H41: 1 ШТ. | I41: 589 | J41: 0 | K41: 589 | O41: =ROUND(CP41,2) -> 798865.95 | P41: =ROUND((ROUND((AC41*AW41*I41),2)*BC41),2) -> 7339.76 | Q41: =(ROUND((ROUND((((ET41*1.1))*AV41*I41),2)*BB41),2)+ROUND((ROUND(((AE41-((EU41*1.1)))*AV41*I41),2)*BS41),2)) -> 712.25 | R41: =ROUND((ROUND((AE41*AV41*I41),2)*BS41),2) -> 372.83 | S41: =ROUND((ROUND((AF41*AV41*I41),2)*BA41),2) -> 790813.94 | T41: =ROUND(CU41*I41,2) -> 0 | U41: =CV41*I41 -> 1139.6302 | V41: =CW41*I41 -> 0 | W41: =ROUND(CX41*I41,2) -> 0 | X41: =ROUND(CY41,2) -> 712068.09 | Y41: =ROUND(CZ41,2) -> 363945.91 | AA41: 56498968 | AB41: =ROUND((AC41+AD41+AF41),6) -> 24.646 | AC41: =ROUND((ES41),6) -> 1.26 | AD41: =ROUND(((((ET41*1.1))-((EU41*1.1)))+AE41),6) -> 0.066 | AE41: =ROUND(((EU41*1.1)),6) -> 0.011 | AF41: =ROUND(((EV41*1.1)),6) -> 23.32 | AG41: =ROUND((AP41),6) -> 0 | AH41: =((EW41*1.1)) -> 1.848 | AI41: =((EX41*1.1)) -> 0 | AJ41: =(AS41) -> 0 | AK41: 22.52 | AL41: 1.26 | AM41: 0.06 | AN41: 0.01 | AO41: 21.2 | AP41: 0 | AQ41: 1.68 | AR41: 0 | AS41: 0 | AT41: 90 | AU41: 46 | AV41: 1.047 | AW41: 1 | AZ41: 1 | BA41: 54.99 | BB41: 17.5 | BC41: 9.89 | BH41: 0 | BI41: 2 | BJ41: ТСН-2001.4. Доп. 1-42. Сб. 10, т. 81, поз. 2 | BM41: 68 | BN41: 0 | BO41: 4.10-81-2 | BP41: 1 | BQ41: 40 | BR41: 0 | BS41: 54.99 | BT41: 1 | BU41: 1 | BV41: 1 | BW41: 1 | BX41: 1 | BZ41: 90 | CA41: 46 | CE41: 30 | CF41: 0 | CG41: 0 | CM41: 0 | CO41: 0 | CP41: =(P41+Q41+S41) -> 798865.95 | CQ41: =ROUND((ROUND((AC41*AW41*1),2)*BC41),2) -> 12.46 | CR41: =(ROUND((ROUND((((ET41*1.1))*AV41*1),2)*BB41),2)+ROUND((ROUND(((AE41-((EU41*1.1)))*AV41*1),2)*BS41),2)) -> 1.23 | CS41: =ROUND((ROUND((AE41*AV41*1),2)*BS41),2) -> 0.55 | CT41: =ROUND((ROUND((AF41*AV41*1),2)*BA41),2) -> 1342.86 | CU41: =AG41 -> 0 | CV41: =(AH41*AV41) -> 1.934856 | CW41: =AI41 -> 0 | CX41: =AJ41 -> 0 | CY41: =(((S41+R41)*AT41)/100) -> 712068.09 | CZ41: =(((S41+R41)*AU41)/100) -> 363945.91 | DE41: *1,1 | DF41: *1,1 | DG41: *1,1 | DI41: *1,1 | DJ41: *1,1 | DN41: 0 | DO41: 0 | DP41: 1 | DQ41: 1 | DU41: 1013 | DV41: 1 ШТ. | DW41: 1 ШТ. | DX41: 1 | EE41: 58162630 | EF41: 40 | EG41: Монтаж оборудования | EH41: 0 | EJ41: 2 | EK41: 68 | EL41: ТСН-2001.4-10. Прокладка и монтаж сетей связи | EM41: ТСН-2001.4-10-1 | EO41: Поправка: Гл.12.Прил.8.п.8. 5_12.00.01.11.003 | EQ41: 0 | ER41: 22.52 | ES41: 1.26 | ET41: 0.06 | EU41: 0.01 | EV41: 21.2 | EW41: 1.68 | EX41: 0 | EY41: 0 | FQ41: 0 | FR41: 0 | FS41: 0 | FX41: 90 | FY41: 46 | GD41: 1 | GF41: -1912799884 | GG41: 2 | GH41: 1 | GI41: 2 | GJ41: 0 | GK41: 0 | GL41: =ROUND(IF(AND(BH41=3,BI41=3,FS41<>0),P41,0),2) -> 0 | GM41: =ROUND(O41+X41+Y41,2)+GX41 -> 1874879.9 | GN41: =IF(OR(BI41=0,BI41=1),GM41-GX41,0) -> 0 | GO41: =IF(BI41=2,GM41-GX41,0) -> 1874879.9 | GP41: =IF(BI41=4,GM41-GX41,0) -> 0 | GR41: 0 | GS41: 3 | GT41: 0 | GV41: =ROUND((GT41),6) -> 0 | GW41: 1 | GX41: =ROUND(HC41*I41,2) -> 0 | HA41: 0 | HB41: 0 | HC41: =GV41*GW41 -> 0 | HS41: 0 | IK41: 0
A42: 18 | B42: 1 | E42: 4,1 | F42: КА 4 | G42: Извещатель дымовой ИП 212-64-R3 без б/о 337936 | H42: шт. | I42: =I40*J42 -> 589 | J42: 1 | K42: 1 | O42: =ROUND(CP42,2) -> 93910.16 | P42: =ROUND((ROUND((AC42*I42),2)*BC42),2) -> 93910.16 | Q42: =(ROUND((ROUND(((ET42)*AV42*I42),2)*BB42),2)+ROUND((ROUND(((AE42-(EU42))*AV42*I42),2)*BS42),2)) -> 0 | R42: =ROUND((ROUND((AE42*AV42*I42),2)*BS42),2) -> 0 | S42: =ROUND((ROUND((AF42*AV42*I42),2)*BA42),2) -> 0 | T42: =ROUND(CU42*I42,2) -> 0 | U42: =CV42*I42 -> 0 | V42: =CW42*I42 -> 0 | W42: =ROUND(CX42*I42,2) -> 0 | X42: =ROUND(CY42,2) -> 0 | Y42: =ROUND(CZ42,2) -> 0 | AA42: 56498966 | AB42: =ROUND((AC42+AD42+AF42),6) -> 159.44 | AC42: =ROUND((ES42),6) -> 159.44 | AD42: =ROUND((((ET42)-(EU42))+AE42),6) -> 0 | AE42: =ROUND((EU42),6) -> 0 | AF42: =ROUND((EV42),6) -> 0 | AG42: =ROUND((AP42),6) -> 0 | AH42: =(EW42) -> 0 | AI42: =(EX42) -> 0 | AJ42: =(AS42) -> 0 | AK42: 159.44 | AL42: 159.44 | AM42: 0 | AN42: 0 | AO42: 0 | AP42: 0 | AQ42: 0 | AR42: 0 | AS42: 0 | AT42: 0 | AU42: 0 | AV42: 1 | AW42: 1 | AZ42: 1 | BA42: 1 | BB42: 1 | BC42: 1 | BH42: 3 | BI42: 3 | BM42: 746 | BN42: 0 | BP42: 0 | BQ42: 130 | BR42: 0 | BS42: 1 | BT42: 1 | BU42: 1 | BV42: 1 | BW42: 1 | BX42: 1 | BZ42: 90 | CA42: 46 | CE42: 30 | CF42: 0 | CG42: 0 | CM42: 0 | CO42: 0 | CP42: =(P42+Q42+S42) -> 93910.16 | CQ42: =ROUND((ROUND((AC42*1),2)*BC42),2) -> 159.44 | CR42: =(ROUND((ROUND(((ET42)*AV42*1),2)*BB42),2)+ROUND((ROUND(((AE42-(EU42))*AV42*1),2)*BS42),2)) -> 0 | CS42: =ROUND((ROUND((AE42*AV42*1),2)*BS42),2) -> 0 | CT42: =ROUND((ROUND((AF42*AV42*1),2)*BA42),2) -> 0 | CU42: =AG42 -> 0 | CV42: =(AH42*AV42) -> 0 | CW42: =AI42 -> 0 | CX42: =AJ42 -> 0 | CY42: =(((S42+R42)*AT42)/100) -> 0 | CZ42: =(((S42+R42)*AU42)/100) -> 0 | DN42: 0 | DO42: 0 | DP42: 1 | DQ42: 1 | DU42: 1010 | DV42: шт. | DW42: шт. | DX42: 1 | EE42: 58162750 | EF42: 130 | EG42: Сметная стоимость оборудования | EH42: 0 | EJ42: 3 | EK42: 746 | EL42: ТСН-2001.13. Сметная стоимость оборудования | EM42: ТСН-2001.13 | EQ42: 0 | ER42: 0 | ES42: 159.44 | ET42: 0 | EU42: 0 | EV42: 0 | EW42: 0 | EX42: 0 | FQ42: 0 | FR42: =P42 -> 93910.16 | FS42: 0 | FX42: 90 | FY42: 46 | GA42: [1 406 / 1,2 / 7,66] + 3% Трансп + 1,2% Заг.скл | GD42: 1 | GF42: -1225386436 | GG42: 2 | GH42: 4 | GI42: -2 | GJ42: 0 | GK42: 0 | GL42: =ROUND(IF(AND(BH42=3,BI42=3,FS42<>0),P42,0),2) -> 0 | GM42: =ROUND(O42+X42+Y42,2)+GX42 -> 93910.16 | GN42: =IF(OR(BI42=0,BI42=1),GM42-GX42,0) -> 0 | GO42: =IF(BI42=2,GM42-GX42,0) -> 0 | GP42: =IF(BI42=4,GM42-GX42,0) -> 0 | GR42: 0 | GS42: 2 | GT42: 0 | GV42: =ROUND((GT42),6) -> 0 | GW42: 1 | GX42: =ROUND(HC42*I42,2) -> 0 | HA42: 0 | HB42: 0 | HC42: =GV42*GW42 -> 0 | HE42: 3 | HF42: 1,2 | HS42: 0 | IK42: 0
A43: 18 | B43: 1 | E43: 4,1 | F43: КА 4 | G43: Извещатель дымовой ИП 212-64-R3 без б/о 337936 | H43: шт. | I43: =I41*J43 -> 589 | J43: 1 | K43: 1 | O43: =ROUND(CP43,2) -> 719351.83 | P43: =ROUND((ROUND((AC43*I43),2)*BC43),2) -> 719351.83 | Q43: =(ROUND((ROUND(((ET43)*AV43*I43),2)*BB43),2)+ROUND((ROUND(((AE43-(EU43))*AV43*I43),2)*BS43),2)) -> 0 | R43: =ROUND((ROUND((AE43*AV43*I43),2)*BS43),2) -> 0 | S43: =ROUND((ROUND((AF43*AV43*I43),2)*BA43),2) -> 0 | T43: =ROUND(CU43*I43,2) -> 0 | U43: =CV43*I43 -> 0 | V43: =CW43*I43 -> 0 | W43: =ROUND(CX43*I43,2) -> 0 | X43: =ROUND(CY43,2) -> 0 | Y43: =ROUND(CZ43,2) -> 0 | AA43: 56498968 | AB43: =ROUND((AC43+AD43+AF43),6) -> 159.44 | AC43: =ROUND((ES43),6) -> 159.44 | AD43: =ROUND((((ET43)-(EU43))+AE43),6) -> 0 | AE43: =ROUND((EU43),6) -> 0 | AF43: =ROUND((EV43),6) -> 0 | AG43: =ROUND((AP43),6) -> 0 | AH43: =(EW43) -> 0 | AI43: =(EX43) -> 0 | AJ43: =(AS43) -> 0 | AK43: 159.44 | AL43: 159.44 | AM43: 0 | AN43: 0 | AO43: 0 | AP43: 0 | AQ43: 0 | AR43: 0 | AS43: 0 | AT43: 0 | AU43: 0 | AV43: 1 | AW43: 1 | AZ43: 1 | BA43: 1 | BB43: 1 | BC43: 7.66 | BH43: 3 | BI43: 3 | BM43: 746 | BN43: 0 | BP43: 0 | BQ43: 130 | BR43: 0 | BS43: 1 | BT43: 1 | BU43: 1 | BV43: 1 | BW43: 1 | BX43: 1 | BZ43: 90 | CA43: 46 | CE43: 30 | CF43: 0 | CG43: 0 | CM43: 0 | CO43: 0 | CP43: =(P43+Q43+S43) -> 719351.83 | CQ43: =ROUND((ROUND((AC43*1),2)*BC43),2) -> 1221.31 | CR43: =(ROUND((ROUND(((ET43)*AV43*1),2)*BB43),2)+ROUND((ROUND(((AE43-(EU43))*AV43*1),2)*BS43),2)) -> 0 | CS43: =ROUND((ROUND((AE43*AV43*1),2)*BS43),2) -> 0 | CT43: =ROUND((ROUND((AF43*AV43*1),2)*BA43),2) -> 0 | CU43: =AG43 -> 0 | CV43: =(AH43*AV43) -> 0 | CW43: =AI43 -> 0 | CX43: =AJ43 -> 0 | CY43: =(((S43+R43)*AT43)/100) -> 0 | CZ43: =(((S43+R43)*AU43)/100) -> 0 | DN43: 0 | DO43: 0 | DP43: 1 | DQ43: 1 | DU43: 1010 | DV43: шт. | DW43: шт. | DX43: 1 | EE43: 58162750 | EF43: 130 | EG43: Сметная стоимость оборудования | EH43: 0 | EJ43: 3 | EK43: 746 | EL43: ТСН-2001.13. Сметная стоимость оборудования | EM43: ТСН-2001.13 | EQ43: 0 | ER43: 159.44 | ES43: 159.44 | ET43: 0 | EU43: 0 | EV43: 0 | EW43: 0 | EX43: 0 | EZ43: 5 | FC43: 1 | FD43: 18 | FF43: 1406 | FQ43: 0 | FR43: =P43 -> 719351.83 | FS43: 0 | FX43: 90 | FY43: 46 | GA43: [1 406 / 1,2 / 7,66] + 3% Трансп + 1,2% Заг.скл | GD43: 1 | GF43: -1225386436 | GG43: 2 | GH43: 3 | GI43: 5 | GJ43: 0 | GK43: 0 | GL43: =ROUND(IF(AND(BH43=3,BI43=3,FS43<>0),P43,0),2) -> 0 | GM43: =ROUND(O43+X43+Y43,2)+GX43 -> 719351.83 | GN43: =IF(OR(BI43=0,BI43=1),GM43-GX43,0) -> 0 | GO43: =IF(BI43=2,GM43-GX43,0) -> 0 | GP43: =IF(BI43=4,GM43-GX43,0) -> 0 | GR43: 1 | GS43: 1 | GT43: 0 | GV43: =ROUND((GT43),6) -> 0 | GW43: 1 | GX43: =ROUND(HC43*I43,2) -> 0 | HA43: 0 | HB43: 0 | HC43: =GV43*GW43 -> 0 | HE43: 3 | HF43: 1,2 | HS43: 0 | IK43: 0
A44: 17 | B44: 1 | D44: =ROW(EtalonRes!A21) -> 21 | E44: 5 | F44: 4.10-81-6 | G44: Конструкция для установки извещателя | H44: 1 ШТ. | I44: =ROUND(136+453,9) -> 589 | J44: 0 | K44: =ROUND(136+453,9) -> 589 | O44: =ROUND(CP44,2) -> 6710.04 | P44: =ROUND((ROUND((AC44*AW44*I44),2)*BC44),2) -> 618.45 | Q44: =(ROUND((ROUND((((ET44*1.1))*AV44*I44),2)*BB44),2)+ROUND((ROUND(((AE44-((EU44*1.1)))*AV44*I44),2)*BS44),2)) -> 3093.28 | R44: =ROUND((ROUND((AE44*AV44*I44),2)*BS44),2) -> 189.94 | S44: =ROUND((ROUND((AF44*AV44*I44),2)*BA44),2) -> 2998.31 | T44: =ROUND(CU44*I44,2) -> 0 | U44: =CV44*I44 -> 237.42296 | V44: =CW44*I44 -> 0 | W44: =ROUND(CX44*I44,2) -> 0 | X44: =ROUND(CY44,2) -> 2869.43 | Y44: =ROUND(CZ44,2) -> 1466.6 | AA44: 56498966 | AB44: =ROUND((AC44+AD44+AF44),6) -> 10.928 | AC44: =ROUND((ES44),6) -> 1.05 | AD44: =ROUND(((((ET44*1.1))-((EU44*1.1)))+AE44),6) -> 5.016 | AE44: =ROUND(((EU44*1.1)),6) -> 0.308 | AF44: =ROUND(((EV44*1.1)),6) -> 4.862 | AG44: =ROUND((AP44),6) -> 0 | AH44: =((EW44*1.1)) -> 0.385 | AI44: =((EX44*1.1)) -> 0 | AJ44: =(AS44) -> 0 | AK44: 10.03 | AL44: 1.05 | AM44: 4.56 | AN44: 0.28 | AO44: 4.42 | AP44: 0 | AQ44: 0.35 | AR44: 0 | AS44: 0 | AT44: 90 | AU44: 46 | AV44: 1.047 | AW44: 1 | AZ44: 1 | BA44: 1 | BB44: 1 | BC44: 1 | BH44: 0 | BI44: 2 | BJ44: ТСН-2001.4. Доп. 1-42. Сб. 10, т. 81, поз. 6 | BM44: 68 | BN44: 0 | BO44: 4.10-81-6 | BP44: 1 | BQ44: 40 | BR44: 0 | BS44: 1 | BT44: 1 | BU44: 1 | BV44: 1 | BW44: 1 | BX44: 1 | BZ44: 90 | CA44: 46 | CE44: 30 | CF44: 0 | CG44: 0 | CM44: 0 | CO44: 0 | CP44: =(P44+Q44+S44) -> 6710.04 | CQ44: =ROUND((ROUND((AC44*AW44*1),2)*BC44),2) -> 1.05 | CR44: =(ROUND((ROUND((((ET44*1.1))*AV44*1),2)*BB44),2)+ROUND((ROUND(((AE44-((EU44*1.1)))*AV44*1),2)*BS44),2)) -> 5.25 | CS44: =ROUND((ROUND((AE44*AV44*1),2)*BS44),2) -> 0.32 | CT44: =ROUND((ROUND((AF44*AV44*1),2)*BA44),2) -> 5.09 | CU44: =AG44 -> 0 | CV44: =(AH44*AV44) -> 0.403095 | CW44: =AI44 -> 0 | CX44: =AJ44 -> 0 | CY44: =(((S44+R44)*AT44)/100) -> 2869.425 | CZ44: =(((S44+R44)*AU44)/100) -> 1466.595 | DE44: *1,1 | DF44: *1,1 | DG44: *1,1 | DI44: *1,1 | DJ44: *1,1 | DN44: 0 | DO44: 0 | DP44: 1 | DQ44: 1 | DU44: 1013 | DV44: 1 ШТ. | DW44: 1 ШТ. | DX44: 1 | EE44: 58162630 | EF44: 40 | EG44: Монтаж оборудования | EH44: 0 | EJ44: 2 | EK44: 68 | EL44: ТСН-2001.4-10. Прокладка и монтаж сетей связи | EM44: ТСН-2001.4-10-1 | EO44: Поправка: Гл.12.Прил.8.п.8. 5_12.00.01.11.003 | EQ44: 0 | ER44: 10.03 | ES44: 1.05 | ET44: 4.56 | EU44: 0.28 | EV44: 4.42 | EW44: 0.35 | EX44: 0 | EY44: 0 | FQ44: 0 | FR44: 0 | FS44: 0 | FX44: 90 | FY44: 46 | GD44: 1 | GF44: 1040190154 | GG44: 2 | GH44: 1 | GI44: 2 | GJ44: 0 | GK44: 0 | GL44: =ROUND(IF(AND(BH44=3,BI44=3,FS44<>0),P44,0),2) -> 0 | GM44: =ROUND(O44+X44+Y44,2)+GX44 -> 11046.07 | GN44: =IF(OR(BI44=0,BI44=1),GM44-GX44,0) -> 0 | GO44: =IF(BI44=2,GM44-GX44,0) -> 11046.07 | GP44: =IF(BI44=4,GM44-GX44,0) -> 0 | GR44: 0 | GS44: 3 | GT44: 0 | GV44: =ROUND((GT44),6) -> 0 | GW44: 1 | GX44: =ROUND(HC44*I44,2) -> 0 | HA44: 0 | HB44: 0 | HC44: =GV44*GW44 -> 0 | HS44: 0 | IK44: 0
A45: 17 | B45: 1 | D45: =ROW(EtalonRes!A22) -> 22 | E45: 5 | F45: 4.10-81-6 | G45: Конструкция для установки извещателя | H45: 1 ШТ. | I45: =ROUND(136+453,9) -> 589 | J45: 0 | K45: =ROUND(136+453,9) -> 589 | O45: =ROUND(CP45,2) -> 210587.52 | P45: =ROUND((ROUND((AC45*AW45*I45),2)*BC45),2) -> 6116.47 | Q45: =(ROUND((ROUND((((ET45*1.1))*AV45*I45),2)*BB45),2)+ROUND((ROUND(((AE45-((EU45*1.1)))*AV45*I45),2)*BS45),2)) -> 39593.98 | R45: =ROUND((ROUND((AE45*AV45*I45),2)*BS45),2) -> 10444.8 | S45: =ROUND((ROUND((AF45*AV45*I45),2)*BA45),2) -> 164877.07 | T45: =ROUND(CU45*I45,2) -> 0 | U45: =CV45*I45 -> 237.42296 | V45: =CW45*I45 -> 0 | W45: =ROUND(CX45*I45,2) -> 0 | X45: =ROUND(CY45,2) -> 157789.68 | Y45: =ROUND(CZ45,2) -> 80648.06 | AA45: 56498968 | AB45: =ROUND((AC45+AD45+AF45),6) -> 10.928 | AC45: =ROUND((ES45),6) -> 1.05 | AD45: =ROUND(((((ET45*1.1))-((EU45*1.1)))+AE45),6) -> 5.016 | AE45: =ROUND(((EU45*1.1)),6) -> 0.308 | AF45: =ROUND(((EV45*1.1)),6) -> 4.862 | AG45: =ROUND((AP45),6) -> 0 | AH45: =((EW45*1.1)) -> 0.385 | AI45: =((EX45*1.1)) -> 0 | AJ45: =(AS45) -> 0 | AK45: 10.03 | AL45: 1.05 | AM45: 4.56 | AN45: 0.28 | AO45: 4.42 | AP45: 0 | AQ45: 0.35 | AR45: 0 | AS45: 0 | AT45: 90 | AU45: 46 | AV45: 1.047 | AW45: 1 | AZ45: 1 | BA45: 54.99 | BB45: 12.8 | BC45: 9.89 | BH45: 0 | BI45: 2 | BJ45: ТСН-2001.4. Доп. 1-42. Сб. 10, т. 81, поз. 6 | BM45: 68 | BN45: 0 | BO45: 4.10-81-6 | BP45: 1 | BQ45: 40 | BR45: 0 | BS45: 54.99 | BT45: 1 | BU45: 1 | BV45: 1 | BW45: 1 | BX45: 1 | BZ45: 90 | CA45: 46 | CE45: 30 | CF45: 0 | CG45: 0 | CM45: 0 | CO45: 0 | CP45: =(P45+Q45+S45) -> 210587.52 | CQ45: =ROUND((ROUND((AC45*AW45*1),2)*BC45),2) -> 10.38 | CR45: =(ROUND((ROUND((((ET45*1.1))*AV45*1),2)*BB45),2)+ROUND((ROUND(((AE45-((EU45*1.1)))*AV45*1),2)*BS45),2)) -> 67.2 | CS45: =ROUND((ROUND((AE45*AV45*1),2)*BS45),2) -> 17.6 | CT45: =ROUND((ROUND((AF45*AV45*1),2)*BA45),2) -> 279.9 | CU45: =AG45 -> 0 | CV45: =(AH45*AV45) -> 0.403095 | CW45: =AI45 -> 0 | CX45: =AJ45 -> 0 | CY45: =(((S45+R45)*AT45)/100) -> 157789.68 | CZ45: =(((S45+R45)*AU45)/100) -> 80648.06 | DE45: *1,1 | DF45: *1,1 | DG45: *1,1 | DI45: *1,1 | DJ45: *1,1 | DN45: 0 | DO45: 0 | DP45: 1 | DQ45: 1 | DU45: 1013 | DV45: 1 ШТ. | DW45: 1 ШТ. | DX45: 1 | EE45: 58162630 | EF45: 40 | EG45: Монтаж оборудования | EH45: 0 | EJ45: 2 | EK45: 68 | EL45: ТСН-2001.4-10. Прокладка и монтаж сетей связи | EM45: ТСН-2001.4-10-1 | EO45: Поправка: Гл.12.Прил.8.п.8. 5_12.00.01.11.003 | EQ45: 0 | ER45: 10.03 | ES45: 1.05 | ET45: 4.56 | EU45: 0.28 | EV45: 4.42 | EW45: 0.35 | EX45: 0 | EY45: 0 | FQ45: 0 | FR45: 0 | FS45: 0 | FX45: 90 | FY45: 46 | GD45: 1 | GF45: 1040190154 | GG45: 2 | GH45: 1 | GI45: 2 | GJ45: 0 | GK45: 0 | GL45: =ROUND(IF(AND(BH45=3,BI45=3,FS45<>0),P45,0),2) -> 0 | GM45: =ROUND(O45+X45+Y45,2)+GX45 -> 449025.26 | GN45: =IF(OR(BI45=0,BI45=1),GM45-GX45,0) -> 0 | GO45: =IF(BI45=2,GM45-GX45,0) -> 449025.26 | GP45: =IF(BI45=4,GM45-GX45,0) -> 0 | GR45: 0 | GS45: 3 | GT45: 0 | GV45: =ROUND((GT45),6) -> 0 | GW45: 1 | GX45: =ROUND(HC45*I45,2) -> 0 | HA45: 0 | HB45: 0 | HC45: =GV45*GW45 -> 0 | HS45: 0 | IK45: 0
A46: 18 | B46: 1 | E46: 5,1 | F46: КА 5 | G46: Базовое основание W2.03 342655 | H46: шт. | I46: =I44*J46 -> 136 | J46: 0.23089983 | K46: 0.23089983 | O46: =ROUND(CP46,2) -> 6118.64 | P46: =ROUND((ROUND((AC46*AW46*I46),2)*BC46),2) -> 6118.64 | Q46: =(ROUND((ROUND(((ET46)*AV46*I46),2)*BB46),2)+ROUND((ROUND(((AE46-(EU46))*AV46*I46),2)*BS46),2)) -> 0 | R46: =ROUND((ROUND((AE46*AV46*I46),2)*BS46),2) -> 0 | S46: =ROUND((ROUND((AF46*AV46*I46),2)*BA46),2) -> 0 | T46: =ROUND(CU46*I46,2) -> 0 | U46: =CV46*I46 -> 0 | V46: =CW46*I46 -> 0 | W46: =ROUND(CX46*I46,2) -> 0 | X46: =ROUND(CY46,2) -> 0 | Y46: =ROUND(CZ46,2) -> 0 | AA46: 56498966 | AB46: =ROUND((AC46+AD46+AF46),6) -> 44.99 | AC46: =ROUND((ES46),6) -> 44.99 | AD46: =ROUND((((ET46)-(EU46))+AE46),6) -> 0 | AE46: =ROUND((EU46),6) -> 0 | AF46: =ROUND((EV46),6) -> 0 | AG46: =ROUND((AP46),6) -> 0 | AH46: =(EW46) -> 0 | AI46: =(EX46) -> 0 | AJ46: =(AS46) -> 0 | AK46: 44.99 | AL46: 44.99 | AM46: 0 | AN46: 0 | AO46: 0 | AP46: 0 | AQ46: 0 | AR46: 0 | AS46: 0 | AT46: 90 | AU46: 46 | AV46: 1 | AW46: 1 | AZ46: 1 | BA46: 1 | BB46: 1 | BC46: 1 | BH46: 3 | BI46: 2 | BM46: 68 | BN46: 0 | BP46: 0 | BQ46: 40 | BR46: 0 | BS46: 1 | BT46: 1 | BU46: 1 | BV46: 1 | BW46: 1 | BX46: 1 | BZ46: 90 | CA46: 46 | CE46: 30 | CF46: 0 | CG46: 0 | CM46: 0 | CO46: 0 | CP46: =(P46+Q46+S46) -> 6118.64 | CQ46: =ROUND((ROUND((AC46*AW46*1),2)*BC46),2) -> 44.99 | CR46: =(ROUND((ROUND(((ET46)*AV46*1),2)*BB46),2)+ROUND((ROUND(((AE46-(EU46))*AV46*1),2)*BS46),2)) -> 0 | CS46: =ROUND((ROUND((AE46*AV46*1),2)*BS46),2) -> 0 | CT46: =ROUND((ROUND((AF46*AV46*1),2)*BA46),2) -> 0 | CU46: =AG46 -> 0 | CV46: =(AH46*AV46) -> 0 | CW46: =AI46 -> 0 | CX46: =AJ46 -> 0 | CY46: =(((S46+R46)*AT46)/100) -> 0 | CZ46: =(((S46+R46)*AU46)/100) -> 0 | DN46: 0 | DO46: 0 | DP46: 1 | DQ46: 1 | DU46: 1010 | DV46: шт. | DW46: шт. | DX46: 1 | EE46: 58162630 | EF46: 40 | EG46: Монтаж оборудования | EH46: 0 | EJ46: 2 | EK46: 68 | EL46: ТСН-2001.4-10. Прокладка и монтаж сетей связи | EM46: ТСН-2001.4-10-1 | EQ46: 0 | ER46: 0 | ES46: 44.99 | ET46: 0 | EU46: 0 | EV46: 0 | EW46: 0 | EX46: 0 | FQ46: 0 | FR46: 0 | FS46: 0 | FX46: 90 | FY46: 46 | GA46: [523 / 1,2 / 9,88] + 2% Заг.скл | GD46: 1 | GF46: -810448224 | GG46: 2 | GH46: 4 | GI46: -2 | GJ46: 0 | GK46: 0 | GL46: =ROUND(IF(AND(BH46=3,BI46=3,FS46<>0),P46,0),2) -> 0 | GM46: =ROUND(O46+X46+Y46,2)+GX46 -> 6118.64 | GN46: =IF(OR(BI46=0,BI46=1),GM46-GX46,0) -> 0 | GO46: =IF(BI46=2,GM46-GX46,0) -> 6118.64 | GP46: =IF(BI46=4,GM46-GX46,0) -> 0 | GR46: 0 | GS46: 2 | GT46: 0 | GV46: =ROUND((GT46),6) -> 0 | GW46: 1 | GX46: =ROUND(HC46*I46,2) -> 0 | HA46: 0 | HB46: 0 | HC46: =GV46*GW46 -> 0 | HE46: 0 | HF46: 2 | HS46: 0 | IK46: 0
A47: 18 | B47: 1 | E47: 5,1 | F47: КА 5 | G47: Базовое основание W2.03 342655 | H47: шт. | I47: =I45*J47 -> 136 | J47: 0.23089983 | K47: 0.23089983 | O47: =ROUND(CP47,2) -> 60452.16 | P47: =ROUND((ROUND((AC47*AW47*I47),2)*BC47),2) -> 60452.16 | Q47: =(ROUND((ROUND(((ET47)*AV47*I47),2)*BB47),2)+ROUND((ROUND(((AE47-(EU47))*AV47*I47),2)*BS47),2)) -> 0 | R47: =ROUND((ROUND((AE47*AV47*I47),2)*BS47),2) -> 0 | S47: =ROUND((ROUND((AF47*AV47*I47),2)*BA47),2) -> 0 | T47: =ROUND(CU47*I47,2) -> 0 | U47: =CV47*I47 -> 0 | V47: =CW47*I47 -> 0 | W47: =ROUND(CX47*I47,2) -> 0 | X47: =ROUND(CY47,2) -> 0 | Y47: =ROUND(CZ47,2) -> 0 | AA47: 56498968 | AB47: =ROUND((AC47+AD47+AF47),6) -> 44.99 | AC47: =ROUND((ES47),6) -> 44.99 | AD47: =ROUND((((ET47)-(EU47))+AE47),6) -> 0 | AE47: =ROUND((EU47),6) -> 0 | AF47: =ROUND((EV47),6) -> 0 | AG47: =ROUND((AP47),6) -> 0 | AH47: =(EW47) -> 0 | AI47: =(EX47) -> 0 | AJ47: =(AS47) -> 0 | AK47: 44.99 | AL47: 44.99 | AM47: 0 | AN47: 0 | AO47: 0 | AP47: 0 | AQ47: 0 | AR47: 0 | AS47: 0 | AT47: 90 | AU47: 46 | AV47: 1 | AW47: 1 | AZ47: 1 | BA47: 1 | BB47: 1 | BC47: 9.88 | BH47: 3 | BI47: 2 | BM47: 68 | BN47: 0 | BP47: 0 | BQ47: 40 | BR47: 0 | BS47: 1 | BT47: 1 | BU47: 1 | BV47: 1 | BW47: 1 | BX47: 1 | BZ47: 90 | CA47: 46 | CE47: 30 | CF47: 0 | CG47: 0 | CM47: 0 | CO47: 0 | CP47: =(P47+Q47+S47) -> 60452.16 | CQ47: =ROUND((ROUND((AC47*AW47*1),2)*BC47),2) -> 444.5 | CR47: =(ROUND((ROUND(((ET47)*AV47*1),2)*BB47),2)+ROUND((ROUND(((AE47-(EU47))*AV47*1),2)*BS47),2)) -> 0 | CS47: =ROUND((ROUND((AE47*AV47*1),2)*BS47),2) -> 0 | CT47: =ROUND((ROUND((AF47*AV47*1),2)*BA47),2) -> 0 | CU47: =AG47 -> 0 | CV47: =(AH47*AV47) -> 0 | CW47: =AI47 -> 0 | CX47: =AJ47 -> 0 | CY47: =(((S47+R47)*AT47)/100) -> 0 | CZ47: =(((S47+R47)*AU47)/100) -> 0 | DN47: 0 | DO47: 0 | DP47: 1 | DQ47: 1 | DU47: 1010 | DV47: шт. | DW47: шт. | DX47: 1 | EE47: 58162630 | EF47: 40 | EG47: Монтаж оборудования | EH47: 0 | EJ47: 2 | EK47: 68 | EL47: ТСН-2001.4-10. Прокладка и монтаж сетей связи | EM47: ТСН-2001.4-10-1 | EQ47: 0 | ER47: 44.99 | ES47: 44.99 | ET47: 0 | EU47: 0 | EV47: 0 | EW47: 0 | EX47: 0 | EZ47: 5 | FC47: 1 | FD47: 18 | FF47: 523 | FQ47: 0 | FR47: 0 | FS47: 0 | FX47: 90 | FY47: 46 | GA47: [523 / 1,2 / 9,88] + 2% Заг.скл | GD47: 1 | GF47: -810448224 | GG47: 2 | GH47: 3 | GI47: 5 | GJ47: 0 | GK47: 0 | GL47: =ROUND(IF(AND(BH47=3,BI47=3,FS47<>0),P47,0),2) -> 0 | GM47: =ROUND(O47+X47+Y47,2)+GX47 -> 60452.16 | GN47: =IF(OR(BI47=0,BI47=1),GM47-GX47,0) -> 0 | GO47: =IF(BI47=2,GM47-GX47,0) -> 60452.16 | GP47: =IF(BI47=4,GM47-GX47,0) -> 0 | GR47: 1 | GS47: 1 | GT47: 0 | GV47: =ROUND((GT47),6) -> 0 | GW47: 1 | GX47: =ROUND(HC47*I47,2) -> 0 | HA47: 0 | HB47: 0 | HC47: =GV47*GW47 -> 0 | HE47: 0 | HF47: 2 | HS47: 0 | IK47: 0
A48: 18 | B48: 1 | E48: 5,2 | F48: КА 6 | G48: Базовое основание W1.02 338227 | H48: шт. | I48: =I44*J48 -> 453 | J48: 0.76910017 | K48: 0.76910017 | O48: =ROUND(CP48,2) -> 8104.17 | P48: =ROUND((ROUND((AC48*AW48*I48),2)*BC48),2) -> 8104.17 | Q48: =(ROUND((ROUND(((ET48)*AV48*I48),2)*BB48),2)+ROUND((ROUND(((AE48-(EU48))*AV48*I48),2)*BS48),2)) -> 0 | R48: =ROUND((ROUND((AE48*AV48*I48),2)*BS48),2) -> 0 | S48: =ROUND((ROUND((AF48*AV48*I48),2)*BA48),2) -> 0 | T48: =ROUND(CU48*I48,2) -> 0 | U48: =CV48*I48 -> 0 | V48: =CW48*I48 -> 0 | W48: =ROUND(CX48*I48,2) -> 0 | X48: =ROUND(CY48,2) -> 0 | Y48: =ROUND(CZ48,2) -> 0 | AA48: 56498966 | AB48: =ROUND((AC48+AD48+AF48),6) -> 17.89 | AC48: =ROUND((ES48),6) -> 17.89 | AD48: =ROUND((((ET48)-(EU48))+AE48),6) -> 0 | AE48: =ROUND((EU48),6) -> 0 | AF48: =ROUND((EV48),6) -> 0 | AG48: =ROUND((AP48),6) -> 0 | AH48: =(EW48) -> 0 | AI48: =(EX48) -> 0 | AJ48: =(AS48) -> 0 | AK48: 17.89 | AL48: 17.89 | AM48: 0 | AN48: 0 | AO48: 0 | AP48: 0 | AQ48: 0 | AR48: 0 | AS48: 0 | AT48: 90 | AU48: 46 | AV48: 1 | AW48: 1 | AZ48: 1 | BA48: 1 | BB48: 1 | BC48: 1 | BH48: 3 | BI48: 2 | BM48: 68 | BN48: 0 | BP48: 0 | BQ48: 40 | BR48: 0 | BS48: 1 | BT48: 1 | BU48: 1 | BV48: 1 | BW48: 1 | BX48: 1 | BZ48: 90 | CA48: 46 | CE48: 30 | CF48: 0 | CG48: 0 | CM48: 0 | CO48: 0 | CP48: =(P48+Q48+S48) -> 8104.17 | CQ48: =ROUND((ROUND((AC48*AW48*1),2)*BC48),2) -> 17.89 | CR48: =(ROUND((ROUND(((ET48)*AV48*1),2)*BB48),2)+ROUND((ROUND(((AE48-(EU48))*AV48*1),2)*BS48),2)) -> 0 | CS48: =ROUND((ROUND((AE48*AV48*1),2)*BS48),2) -> 0 | CT48: =ROUND((ROUND((AF48*AV48*1),2)*BA48),2) -> 0 | CU48: =AG48 -> 0 | CV48: =(AH48*AV48) -> 0 | CW48: =AI48 -> 0 | CX48: =AJ48 -> 0 | CY48: =(((S48+R48)*AT48)/100) -> 0 | CZ48: =(((S48+R48)*AU48)/100) -> 0 | DN48: 0 | DO48: 0 | DP48: 1 | DQ48: 1 | DU48: 1010 | DV48: шт. | DW48: шт. | DX48: 1 | EE48: 58162630 | EF48: 40 | EG48: Монтаж оборудования | EH48: 0 | EJ48: 2 | EK48: 68 | EL48: ТСН-2001.4-10. Прокладка и монтаж сетей связи | EM48: ТСН-2001.4-10-1 | EQ48: 0 | ER48: 0 | ES48: 17.89 | ET48: 0 | EU48: 0 | EV48: 0 | EW48: 0 | EX48: 0 | FQ48: 0 | FR48: 0 | FS48: 0 | FX48: 90 | FY48: 46 | GA48: [208 / 1,2 / 9,88] + 2% Заг.скл | GD48: 1 | GF48: 1151310423 | GG48: 2 | GH48: 4 | GI48: -2 | GJ48: 0 | GK48: 0 | GL48: =ROUND(IF(AND(BH48=3,BI48=3,FS48<>0),P48,0),2) -> 0 | GM48: =ROUND(O48+X48+Y48,2)+GX48 -> 8104.17 | GN48: =IF(OR(BI48=0,BI48=1),GM48-GX48,0) -> 0 | GO48: =IF(BI48=2,GM48-GX48,0) -> 8104.17 | GP48: =IF(BI48=4,GM48-GX48,0) -> 0 | GR48: 0 | GS48: 2 | GT48: 0 | GV48: =ROUND((GT48),6) -> 0 | GW48: 1 | GX48: =ROUND(HC48*I48,2) -> 0 | HA48: 0 | HB48: 0 | HC48: =GV48*GW48 -> 0 | HE48: 0 | HF48: 2 | HS48: 0 | IK48: 0
A49: 18 | B49: 1 | E49: 5,2 | F49: КА 6 | G49: Базовое основание W1.02 338227 | H49: шт. | I49: =I45*J49 -> 453 | J49: 0.76910017 | K49: 0.76910017 | O49: =ROUND(CP49,2) -> 80069.2 | P49: =ROUND((ROUND((AC49*AW49*I49),2)*BC49),2) -> 80069.2 | Q49: =(ROUND((ROUND(((ET49)*AV49*I49),2)*BB49),2)+ROUND((ROUND(((AE49-(EU49))*AV49*I49),2)*BS49),2)) -> 0 | R49: =ROUND((ROUND((AE49*AV49*I49),2)*BS49),2) -> 0 | S49: =ROUND((ROUND((AF49*AV49*I49),2)*BA49),2) -> 0 | T49: =ROUND(CU49*I49,2) -> 0 | U49: =CV49*I49 -> 0 | V49: =CW49*I49 -> 0 | W49: =ROUND(CX49*I49,2) -> 0 | X49: =ROUND(CY49,2) -> 0 | Y49: =ROUND(CZ49,2) -> 0 | AA49: 56498968 | AB49: =ROUND((AC49+AD49+AF49),6) -> 17.89 | AC49: =ROUND((ES49),6) -> 17.89 | AD49: =ROUND((((ET49)-(EU49))+AE49),6) -> 0 | AE49: =ROUND((EU49),6) -> 0 | AF49: =ROUND((EV49),6) -> 0 | AG49: =ROUND((AP49),6) -> 0 | AH49: =(EW49) -> 0 | AI49: =(EX49) -> 0 | AJ49: =(AS49) -> 0 | AK49: 17.89 | AL49: 17.89 | AM49: 0 | AN49: 0 | AO49: 0 | AP49: 0 | AQ49: 0 | AR49: 0 | AS49: 0 | AT49: 90 | AU49: 46 | AV49: 1 | AW49: 1 | AZ49: 1 | BA49: 1 | BB49: 1 | BC49: 9.88 | BH49: 3 | BI49: 2 | BM49: 68 | BN49: 0 | BP49: 0 | BQ49: 40 | BR49: 0 | BS49: 1 | BT49: 1 | BU49: 1 | BV49: 1 | BW49: 1 | BX49: 1 | BZ49: 90 | CA49: 46 | CE49: 30 | CF49: 0 | CG49: 0 | CM49: 0 | CO49: 0 | CP49: =(P49+Q49+S49) -> 80069.2 | CQ49: =ROUND((ROUND((AC49*AW49*1),2)*BC49),2) -> 176.75 | CR49: =(ROUND((ROUND(((ET49)*AV49*1),2)*BB49),2)+ROUND((ROUND(((AE49-(EU49))*AV49*1),2)*BS49),2)) -> 0 | CS49: =ROUND((ROUND((AE49*AV49*1),2)*BS49),2) -> 0 | CT49: =ROUND((ROUND((AF49*AV49*1),2)*BA49),2) -> 0 | CU49: =AG49 -> 0 | CV49: =(AH49*AV49) -> 0 | CW49: =AI49 -> 0 | CX49: =AJ49 -> 0 | CY49: =(((S49+R49)*AT49)/100) -> 0 | CZ49: =(((S49+R49)*AU49)/100) -> 0 | DN49: 0 | DO49: 0 | DP49: 1 | DQ49: 1 | DU49: 1010 | DV49: шт. | DW49: шт. | DX49: 1 | EE49: 58162630 | EF49: 40 | EG49: Монтаж оборудования | EH49: 0 | EJ49: 2 | EK49: 68 | EL49: ТСН-2001.4-10. Прокладка и монтаж сетей связи | EM49: ТСН-2001.4-10-1 | EQ49: 0 | ER49: 17.89 | ES49: 17.89 | ET49: 0 | EU49: 0 | EV49: 0 | EW49: 0 | EX49: 0 | EZ49: 5 | FC49: 1 | FD49: 18 | FF49: 208 | FQ49: 0 | FR49: 0 | FS49: 0 | FX49: 90 | FY49: 46 | GA49: [208 / 1,2 / 9,88] + 2% Заг.скл | GD49: 1 | GF49: 1151310423 | GG49: 2 | GH49: 3 | GI49: 5 | GJ49: 0 | GK49: 0 | GL49: =ROUND(IF(AND(BH49=3,BI49=3,FS49<>0),P49,0),2) -> 0 | GM49: =ROUND(O49+X49+Y49,2)+GX49 -> 80069.2 | GN49: =IF(OR(BI49=0,BI49=1),GM49-GX49,0) -> 0 | GO49: =IF(BI49=2,GM49-GX49,0) -> 80069.2 | GP49: =IF(BI49=4,GM49-GX49,0) -> 0 | GR49: 1 | GS49: 1 | GT49: 0 | GV49: =ROUND((GT49),6) -> 0 | GW49: 1 | GX49: =ROUND(HC49*I49,2) -> 0 | HA49: 0 | HB49: 0 | HC49: =GV49*GW49 -> 0 | HE49: 0 | HF49: 2 | HS49: 0 | IK49: 0
A50: 17 | B50: 1 | D50: =ROW(EtalonRes!A23) -> 23 | E50: 6 | F50: 4.10-81-2 | G50: Извещатели ПС автоматические, дымовой, фотоэлектрический, радиоизотопный, световой в нормальном исполнении | H50: 1 ШТ. | I50: 12 | J50: 0 | K50: 12 | O50: =ROUND(CP50,2) -> 308.94 | P50: =ROUND((ROUND((AC50*AW50*I50),2)*BC50),2) -> 15.12 | Q50: =(ROUND((ROUND((((ET50*1.1))*AV50*I50),2)*BB50),2)+ROUND((ROUND(((AE50-((EU50*1.1)))*AV50*I50),2)*BS50),2)) -> 0.83 | R50: =ROUND((ROUND((AE50*AV50*I50),2)*BS50),2) -> 0.14 | S50: =ROUND((ROUND((AF50*AV50*I50),2)*BA50),2) -> 292.99 | T50: =ROUND(CU50*I50,2) -> 0 | U50: =CV50*I50 -> 23.218272 | V50: =CW50*I50 -> 0 | W50: =ROUND(CX50*I50,2) -> 0 | X50: =ROUND(CY50,2) -> 263.82 | Y50: =ROUND(CZ50,2) -> 134.84 | AA50: 56498966 | AB50: =ROUND((AC50+AD50+AF50),6) -> 24.646 | AC50: =ROUND((ES50),6) -> 1.26 | AD50: =ROUND(((((ET50*1.1))-((EU50*1.1)))+AE50),6) -> 0.066 | AE50: =ROUND(((EU50*1.1)),6) -> 0.011 | AF50: =ROUND(((EV50*1.1)),6) -> 23.32 | AG50: =ROUND((AP50),6) -> 0 | AH50: =((EW50*1.1)) -> 1.848 | AI50: =((EX50*1.1)) -> 0 | AJ50: =(AS50) -> 0 | AK50: 22.52 | AL50: 1.26 | AM50: 0.06 | AN50: 0.01 | AO50: 21.2 | AP50: 0 | AQ50: 1.68 | AR50: 0 | AS50: 0 | AT50: 90 | AU50: 46 | AV50: 1.047 | AW50: 1 | AZ50: 1 | BA50: 1 | BB50: 1 | BC50: 1 | BH50: 0 | BI50: 2 | BJ50: ТСН-2001.4. Доп. 1-42. Сб. 10, т. 81, поз. 2 | BM50: 68 | BN50: 0 | BO50: 4.10-81-2 | BP50: 1 | BQ50: 40 | BR50: 0 | BS50: 1 | BT50: 1 | BU50: 1 | BV50: 1 | BW50: 1 | BX50: 1 | BZ50: 90 | CA50: 46 | CE50: 30 | CF50: 0 | CG50: 0 | CM50: 0 | CO50: 0 | CP50: =(P50+Q50+S50) -> 308.94 | CQ50: =ROUND((ROUND((AC50*AW50*1),2)*BC50),2) -> 1.26 | CR50: =(ROUND((ROUND((((ET50*1.1))*AV50*1),2)*BB50),2)+ROUND((ROUND(((AE50-((EU50*1.1)))*AV50*1),2)*BS50),2)) -> 0.07 | CS50: =ROUND((ROUND((AE50*AV50*1),2)*BS50),2) -> 0.01 | CT50: =ROUND((ROUND((AF50*AV50*1),2)*BA50),2) -> 24.42 | CU50: =AG50 -> 0 | CV50: =(AH50*AV50) -> 1.934856 | CW50: =AI50 -> 0 | CX50: =AJ50 -> 0 | CY50: =(((S50+R50)*AT50)/100) -> 263.817 | CZ50: =(((S50+R50)*AU50)/100) -> 134.8398 | DE50: *1,1 | DF50: *1,1 | DG50: *1,1 | DI50: *1,1 | DJ50: *1,1 | DN50: 0 | DO50: 0 | DP50: 1 | DQ50: 1 | DU50: 1013 | DV50: 1 ШТ. | DW50: 1 ШТ. | DX50: 1 | EE50: 58162630 | EF50: 40 | EG50: Монтаж оборудования | EH50: 0 | EJ50: 2 | EK50: 68 | EL50: ТСН-2001.4-10. Прокладка и монтаж сетей связи | EM50: ТСН-2001.4-10-1 | EO50: Поправка: Гл.12.Прил.8.п.8. 5_12.00.01.11.003 | EQ50: 0 | ER50: 22.52 | ES50: 1.26 | ET50: 0.06 | EU50: 0.01 | EV50: 21.2 | EW50: 1.68 | EX50: 0 | EY50: 0 | FQ50: 0 | FR50: 0 | FS50: 0 | FX50: 90 | FY50: 46 | GD50: 1 | GF50: -1912799884 | GG50: 2 | GH50: 1 | GI50: 2 | GJ50: 0 | GK50: 0 | GL50: =ROUND(IF(AND(BH50=3,BI50=3,FS50<>0),P50,0),2) -> 0 | GM50: =ROUND(O50+X50+Y50,2)+GX50 -> 707.6 | GN50: =IF(OR(BI50=0,BI50=1),GM50-GX50,0) -> 0 | GO50: =IF(BI50=2,GM50-GX50,0) -> 707.6 | GP50: =IF(BI50=4,GM50-GX50,0) -> 0 | GR50: 0 | GS50: 3 | GT50: 0 | GV50: =ROUND((GT50),6) -> 0 | GW50: 1 | GX50: =ROUND(HC50*I50,2) -> 0 | HA50: 0 | HB50: 0 | HC50: =GV50*GW50 -> 0 | HS50: 0 | IK50: 0
A51: 17 | B51: 1 | D51: =ROW(EtalonRes!A24) -> 24 | E51: 6 | F51: 4.10-81-2 | G51: Извещатели ПС автоматические, дымовой, фотоэлектрический, радиоизотопный, световой в нормальном исполнении | H51: 1 ШТ. | I51: 12 | J51: 0 | K51: 12 | O51: =ROUND(CP51,2) -> 16275.59 | P51: =ROUND((ROUND((AC51*AW51*I51),2)*BC51),2) -> 149.54 | Q51: =(ROUND((ROUND((((ET51*1.1))*AV51*I51),2)*BB51),2)+ROUND((ROUND(((AE51-((EU51*1.1)))*AV51*I51),2)*BS51),2)) -> 14.53 | R51: =ROUND((ROUND((AE51*AV51*I51),2)*BS51),2) -> 7.7 | S51: =ROUND((ROUND((AF51*AV51*I51),2)*BA51),2) -> 16111.52 | T51: =ROUND(CU51*I51,2) -> 0 | U51: =CV51*I51 -> 23.218272 | V51: =CW51*I51 -> 0 | W51: =ROUND(CX51*I51,2) -> 0 | X51: =ROUND(CY51,2) -> 14507.3 | Y51: =ROUND(CZ51,2) -> 7414.84 | AA51: 56498968 | AB51: =ROUND((AC51+AD51+AF51),6) -> 24.646 | AC51: =ROUND((ES51),6) -> 1.26 | AD51: =ROUND(((((ET51*1.1))-((EU51*1.1)))+AE51),6) -> 0.066 | AE51: =ROUND(((EU51*1.1)),6) -> 0.011 | AF51: =ROUND(((EV51*1.1)),6) -> 23.32 | AG51: =ROUND((AP51),6) -> 0 | AH51: =((EW51*1.1)) -> 1.848 | AI51: =((EX51*1.1)) -> 0 | AJ51: =(AS51) -> 0 | AK51: 22.52 | AL51: 1.26 | AM51: 0.06 | AN51: 0.01 | AO51: 21.2 | AP51: 0 | AQ51: 1.68 | AR51: 0 | AS51: 0 | AT51: 90 | AU51: 46 | AV51: 1.047 | AW51: 1 | AZ51: 1 | BA51: 54.99 | BB51: 17.5 | BC51: 9.89 | BH51: 0 | BI51: 2 | BJ51: ТСН-2001.4. Доп. 1-42. Сб. 10, т. 81, поз. 2 | BM51: 68 | BN51: 0 | BO51: 4.10-81-2 | BP51: 1 | BQ51: 40 | BR51: 0 | BS51: 54.99 | BT51: 1 | BU51: 1 | BV51: 1 | BW51: 1 | BX51: 1 | BZ51: 90 | CA51: 46 | CE51: 30 | CF51: 0 | CG51: 0 | CM51: 0 | CO51: 0 | CP51: =(P51+Q51+S51) -> 16275.59 | CQ51: =ROUND((ROUND((AC51*AW51*1),2)*BC51),2) -> 12.46 | CR51: =(ROUND((ROUND((((ET51*1.1))*AV51*1),2)*BB51),2)+ROUND((ROUND(((AE51-((EU51*1.1)))*AV51*1),2)*BS51),2)) -> 1.23 | CS51: =ROUND((ROUND((AE51*AV51*1),2)*BS51),2) -> 0.55 | CT51: =ROUND((ROUND((AF51*AV51*1),2)*BA51),2) -> 1342.86 | CU51: =AG51 -> 0 | CV51: =(AH51*AV51) -> 1.934856 | CW51: =AI51 -> 0 | CX51: =AJ51 -> 0 | CY51: =(((S51+R51)*AT51)/100) -> 14507.298 | CZ51: =(((S51+R51)*AU51)/100) -> 7414.8412 | DE51: *1,1 | DF51: *1,1 | DG51: *1,1 | DI51: *1,1 | DJ51: *1,1 | DN51: 0 | DO51: 0 | DP51: 1 | DQ51: 1 | DU51: 1013 | DV51: 1 ШТ. | DW51: 1 ШТ. | DX51: 1 | EE51: 58162630 | EF51: 40 | EG51: Монтаж оборудования | EH51: 0 | EJ51: 2 | EK51: 68 | EL51: ТСН-2001.4-10. Прокладка и монтаж сетей связи | EM51: ТСН-2001.4-10-1 | EO51: Поправка: Гл.12.Прил.8.п.8. 5_12.00.01.11.003 | EQ51: 0 | ER51: 22.52 | ES51: 1.26 | ET51: 0.06 | EU51: 0.01 | EV51: 21.2 | EW51: 1.68 | EX51: 0 | EY51: 0 | FQ51: 0 | FR51: 0 | FS51: 0 | FX51: 90 | FY51: 46 | GD51: 1 | GF51: -1912799884 | GG51: 2 | GH51: 1 | GI51: 2 | GJ51: 0 | GK51: 0 | GL51: =ROUND(IF(AND(BH51=3,BI51=3,FS51<>0),P51,0),2) -> 0 | GM51: =ROUND(O51+X51+Y51,2)+GX51 -> 38197.73 | GN51: =IF(OR(BI51=0,BI51=1),GM51-GX51,0) -> 0 | GO51: =IF(BI51=2,GM51-GX51,0) -> 38197.73 | GP51: =IF(BI51=4,GM51-GX51,0) -> 0 | GR51: 0 | GS51: 3 | GT51: 0 | GV51: =ROUND((GT51),6) -> 0 | GW51: 1 | GX51: =ROUND(HC51*I51,2) -> 0 | HA51: 0 | HB51: 0 | HC51: =GV51*GW51 -> 0 | HS51: 0 | IK51: 0
A52: 18 | B52: 1 | E52: 6,1 | F52: КА 7 | G52: Извещатель пожарный дымовой оптико-электронный линейный ИПДЛ-264/1-50-R3 342260 | H52: шт. | I52: =I50*J52 -> 12 | J52: 1 | K52: 1 | O52: =ROUND(CP52,2) -> 29757.6 | P52: =ROUND((ROUND((AC52*I52),2)*BC52),2) -> 29757.6 | Q52: =(ROUND((ROUND(((ET52)*AV52*I52),2)*BB52),2)+ROUND((ROUND(((AE52-(EU52))*AV52*I52),2)*BS52),2)) -> 0 | R52: =ROUND((ROUND((AE52*AV52*I52),2)*BS52),2) -> 0 | S52: =ROUND((ROUND((AF52*AV52*I52),2)*BA52),2) -> 0 | T52: =ROUND(CU52*I52,2) -> 0 | U52: =CV52*I52 -> 0 | V52: =CW52*I52 -> 0 | W52: =ROUND(CX52*I52,2) -> 0 | X52: =ROUND(CY52,2) -> 0 | Y52: =ROUND(CZ52,2) -> 0 | AA52: 56498966 | AB52: =ROUND((AC52+AD52+AF52),6) -> 2479.8 | AC52: =ROUND((ES52),6) -> 2479.8 | AD52: =ROUND((((ET52)-(EU52))+AE52),6) -> 0 | AE52: =ROUND((EU52),6) -> 0 | AF52: =ROUND((EV52),6) -> 0 | AG52: =ROUND((AP52),6) -> 0 | AH52: =(EW52) -> 0 | AI52: =(EX52) -> 0 | AJ52: =(AS52) -> 0 | AK52: 2479.8 | AL52: 2479.8 | AM52: 0 | AN52: 0 | AO52: 0 | AP52: 0 | AQ52: 0 | AR52: 0 | AS52: 0 | AT52: 0 | AU52: 0 | AV52: 1 | AW52: 1 | AZ52: 1 | BA52: 1 | BB52: 1 | BC52: 1 | BH52: 3 | BI52: 3 | BM52: 746 | BN52: 0 | BP52: 0 | BQ52: 130 | BR52: 0 | BS52: 1 | BT52: 1 | BU52: 1 | BV52: 1 | BW52: 1 | BX52: 1 | BZ52: 90 | CA52: 46 | CE52: 30 | CF52: 0 | CG52: 0 | CM52: 0 | CO52: 0 | CP52: =(P52+Q52+S52) -> 29757.6 | CQ52: =ROUND((ROUND((AC52*1),2)*BC52),2) -> 2479.8 | CR52: =(ROUND((ROUND(((ET52)*AV52*1),2)*BB52),2)+ROUND((ROUND(((AE52-(EU52))*AV52*1),2)*BS52),2)) -> 0 | CS52: =ROUND((ROUND((AE52*AV52*1),2)*BS52),2) -> 0 | CT52: =ROUND((ROUND((AF52*AV52*1),2)*BA52),2) -> 0 | CU52: =AG52 -> 0 | CV52: =(AH52*AV52) -> 0 | CW52: =AI52 -> 0 | CX52: =AJ52 -> 0 | CY52: =(((S52+R52)*AT52)/100) -> 0 | CZ52: =(((S52+R52)*AU52)/100) -> 0 | DN52: 0 | DO52: 0 | DP52: 1 | DQ52: 1 | DU52: 1010 | DV52: шт. | DW52: шт. | DX52: 1 | EE52: 58162750 | EF52: 130 | EG52: Сметная стоимость оборудования | EH52: 0 | EJ52: 3 | EK52: 746 | EL52: ТСН-2001.13. Сметная стоимость оборудования | EM52: ТСН-2001.13 | EQ52: 0 | ER52: 0 | ES52: 2479.8 | ET52: 0 | EU52: 0 | EV52: 0 | EW52: 0 | EX52: 0 | FQ52: 0 | FR52: =P52 -> 29757.6 | FS52: 0 | FX52: 90 | FY52: 46 | GA52: [21 868 / 1,2 / 7,66] + 3% Трансп + 1,2% Заг.скл | GD52: 1 | GF52: -759074686 | GG52: 2 | GH52: 4 | GI52: -2 | GJ52: 0 | GK52: 0 | GL52: =ROUND(IF(AND(BH52=3,BI52=3,FS52<>0),P52,0),2) -> 0 | GM52: =ROUND(O52+X52+Y52,2)+GX52 -> 29757.6 | GN52: =IF(OR(BI52=0,BI52=1),GM52-GX52,0) -> 0 | GO52: =IF(BI52=2,GM52-GX52,0) -> 0 | GP52: =IF(BI52=4,GM52-GX52,0) -> 0 | GR52: 0 | GS52: 2 | GT52: 0 | GV52: =ROUND((GT52),6) -> 0 | GW52: 1 | GX52: =ROUND(HC52*I52,2) -> 0 | HA52: 0 | HB52: 0 | HC52: =GV52*GW52 -> 0 | HE52: 3 | HF52: 1,2 | HS52: 0 | IK52: 0
A53: 18 | B53: 1 | E53: 6,1 | F53: КА 7 | G53: Извещатель пожарный дымовой оптико-электронный линейный ИПДЛ-264/1-50-R3 342260 | H53: шт. | I53: =I51*J53 -> 12 | J53: 1 | K53: 1 | O53: =ROUND(CP53,2) -> 227943.22 | P53: =ROUND((ROUND((AC53*I53),2)*BC53),2) -> 227943.22 | Q53: =(ROUND((ROUND(((ET53)*AV53*I53),2)*BB53),2)+ROUND((ROUND(((AE53-(EU53))*AV53*I53),2)*BS53),2)) -> 0 | R53: =ROUND((ROUND((AE53*AV53*I53),2)*BS53),2) -> 0 | S53: =ROUND((ROUND((AF53*AV53*I53),2)*BA53),2) -> 0 | T53: =ROUND(CU53*I53,2) -> 0 | U53: =CV53*I53 -> 0 | V53: =CW53*I53 -> 0 | W53: =ROUND(CX53*I53,2) -> 0 | X53: =ROUND(CY53,2) -> 0 | Y53: =ROUND(CZ53,2) -> 0 | AA53: 56498968 | AB53: =ROUND((AC53+AD53+AF53),6) -> 2479.8 | AC53: =ROUND((ES53),6) -> 2479.8 | AD53: =ROUND((((ET53)-(EU53))+AE53),6) -> 0 | AE53: =ROUND((EU53),6) -> 0 | AF53: =ROUND((EV53),6) -> 0 | AG53: =ROUND((AP53),6) -> 0 | AH53: =(EW53) -> 0 | AI53: =(EX53) -> 0 | AJ53: =(AS53) -> 0 | AK53: 2479.8 | AL53: 2479.8 | AM53: 0 | AN53: 0 | AO53: 0 | AP53: 0 | AQ53: 0 | AR53: 0 | AS53: 0 | AT53: 0 | AU53: 0 | AV53: 1 | AW53: 1 | AZ53: 1 | BA53: 1 | BB53: 1 | BC53: 7.66 | BH53: 3 | BI53: 3 | BM53: 746 | BN53: 0 | BP53: 0 | BQ53: 130 | BR53: 0 | BS53: 1 | BT53: 1 | BU53: 1 | BV53: 1 | BW53: 1 | BX53: 1 | BZ53: 90 | CA53: 46 | CE53: 30 | CF53: 0 | CG53: 0 | CM53: 0 | CO53: 0 | CP53: =(P53+Q53+S53) -> 227943.22 | CQ53: =ROUND((ROUND((AC53*1),2)*BC53),2) -> 18995.27 | CR53: =(ROUND((ROUND(((ET53)*AV53*1),2)*BB53),2)+ROUND((ROUND(((AE53-(EU53))*AV53*1),2)*BS53),2)) -> 0 | CS53: =ROUND((ROUND((AE53*AV53*1),2)*BS53),2) -> 0 | CT53: =ROUND((ROUND((AF53*AV53*1),2)*BA53),2) -> 0 | CU53: =AG53 -> 0 | CV53: =(AH53*AV53) -> 0 | CW53: =AI53 -> 0 | CX53: =AJ53 -> 0 | CY53: =(((S53+R53)*AT53)/100) -> 0 | CZ53: =(((S53+R53)*AU53)/100) -> 0 | DN53: 0 | DO53: 0 | DP53: 1 | DQ53: 1 | DU53: 1010 | DV53: шт. | DW53: шт. | DX53: 1 | EE53: 58162750 | EF53: 130 | EG53: Сметная стоимость оборудования | EH53: 0 | EJ53: 3 | EK53: 746 | EL53: ТСН-2001.13. Сметная стоимость оборудования | EM53: ТСН-2001.13 | EQ53: 0 | ER53: 2479.8 | ES53: 2479.8 | ET53: 0 | EU53: 0 | EV53: 0 | EW53: 0 | EX53: 0 | EZ53: 5 | FC53: 1 | FD53: 18 | FF53: 21868 | FQ53: 0 | FR53: =P53 -> 227943.22 | FS53: 0 | FX53: 90 | FY53: 46 | GA53: [21 868 / 1,2 / 7,66] + 3% Трансп + 1,2% Заг.скл | GD53: 1 | GF53: -759074686 | GG53: 2 | GH53: 3 | GI53: 5 | GJ53: 0 | GK53: 0 | GL53: =ROUND(IF(AND(BH53=3,BI53=3,FS53<>0),P53,0),2) -> 0 | GM53: =ROUND(O53+X53+Y53,2)+GX53 -> 227943.22 | GN53: =IF(OR(BI53=0,BI53=1),GM53-GX53,0) -> 0 | GO53: =IF(BI53=2,GM53-GX53,0) -> 0 | GP53: =IF(BI53=4,GM53-GX53,0) -> 0 | GR53: 1 | GS53: 1 | GT53: 0 | GV53: =ROUND((GT53),6) -> 0 | GW53: 1 | GX53: =ROUND(HC53*I53,2) -> 0 | HA53: 0 | HB53: 0 | HC53: =GV53*GW53 -> 0 | HE53: 3 | HF53: 1,2 | HS53: 0 | IK53: 0
A54: 17 | B54: 1 | D54: =ROW(EtalonRes!A28) -> 28 | E54: 7 | F54: 4.10-76-10 | G54: Монтаж ключа или кнопки на панели | H54: 1 ШТ. | I54: 24 | J54: 0 | K54: 24 | O54: =ROUND(CP54,2) -> 368.73 | P54: =ROUND((ROUND((AC54*AW54*I54),2)*BC54),2) -> 40.08 | Q54: =(ROUND((ROUND((((ET54*1.1))*AV54*I54),2)*BB54),2)+ROUND((ROUND(((AE54-((EU54*1.1)))*AV54*I54),2)*BS54),2)) -> 0 | R54: =ROUND((ROUND((AE54*AV54*I54),2)*BS54),2) -> 0 | S54: =ROUND((ROUND((AF54*AV54*I54),2)*BA54),2) -> 328.65 | T54: =ROUND(CU54*I54,2) -> 0 | U54: =CV54*I54 -> 27.6408 | V54: =CW54*I54 -> 0 | W54: =ROUND(CX54*I54,2) -> 0 | X54: =ROUND(CY54,2) -> 312.22 | Y54: =ROUND(CZ54,2) -> 174.18 | AA54: 56498966 | AB54: =ROUND((AC54+AD54+AF54),6) -> 14.749 | AC54: =ROUND((ES54),6) -> 1.67 | AD54: =ROUND(((((ET54*1.1))-((EU54*1.1)))+AE54),6) -> 0 | AE54: =ROUND(((EU54*1.1)),6) -> 0 | AF54: =ROUND(((EV54*1.1)),6) -> 13.079 | AG54: =ROUND((AP54),6) -> 0 | AH54: =((EW54*1.1)) -> 1.1 | AI54: =((EX54*1.1)) -> 0 | AJ54: =(AS54) -> 0 | AK54: 13.56 | AL54: 1.67 | AM54: 0 | AN54: 0 | AO54: 11.89 | AP54: 0 | AQ54: 1 | AR54: 0 | AS54: 0 | AT54: 95 | AU54: 53 | AV54: 1.047 | AW54: 1 | AZ54: 1 | BA54: 1 | BB54: 1 | BC54: 1 | BH54: 0 | BI54: 2 | BJ54: ТСН-2001.4 Доп. 79, Сб. 10, т. 76, поз. 10 | BM54: 69 | BN54: 0 | BO54: 4.10-76-10 | BP54: 1 | BQ54: 40 | BR54: 0 | BS54: 1 | BT54: 1 | BU54: 1 | BV54: 1 | BW54: 1 | BX54: 1 | BZ54: 95 | CA54: 53 | CE54: 30 | CF54: 0 | CG54: 0 | CM54: 0 | CO54: 0 | CP54: =(P54+Q54+S54) -> 368.73 | CQ54: =ROUND((ROUND((AC54*AW54*1),2)*BC54),2) -> 1.67 | CR54: =(ROUND((ROUND((((ET54*1.1))*AV54*1),2)*BB54),2)+ROUND((ROUND(((AE54-((EU54*1.1)))*AV54*1),2)*BS54),2)) -> 0 | CS54: =ROUND((ROUND((AE54*AV54*1),2)*BS54),2) -> 0 | CT54: =ROUND((ROUND((AF54*AV54*1),2)*BA54),2) -> 13.69 | CU54: =AG54 -> 0 | CV54: =(AH54*AV54) -> 1.1517 | CW54: =AI54 -> 0 | CX54: =AJ54 -> 0 | CY54: =(((S54+R54)*AT54)/100) -> 312.2175 | CZ54: =(((S54+R54)*AU54)/100) -> 174.1845 | DE54: *1,1 | DF54: *1,1 | DG54: *1,1 | DI54: *1,1 | DJ54: *1,1 | DN54: 0 | DO54: 0 | DP54: 1 | DQ54: 1 | DU54: 1013 | DV54: 1 ШТ. | DW54: 1 ШТ. | DX54: 1 | EE54: 58162631 | EF54: 40 | EG54: Монтаж оборудования | EH54: 0 | EJ54: 2 | EK54: 69 | EL54: ТСН-2001.4-10. Монтаж радиотелевизионного и электронного оборудования | EM54: ТСН-2001.4-10-2 | EO54: Поправка: Гл.12.Прил.8.п.8. 5_12.00.01.11.003 | EQ54: 0 | ER54: 13.56 | ES54: 1.67 | ET54: 0 | EU54: 0 | EV54: 11.89 | EW54: 1 | EX54: 0 | EY54: 0 | FQ54: 0 | FR54: 0 | FS54: 0 | FX54: 95 | FY54: 53 | GD54: 1 | GF54: -508473279 | GG54: 2 | GH54: 1 | GI54: 2 | GJ54: 0 | GK54: 0 | GL54: =ROUND(IF(AND(BH54=3,BI54=3,FS54<>0),P54,0),2) -> 0 | GM54: =ROUND(O54+X54+Y54,2)+GX54 -> 855.13 | GN54: =IF(OR(BI54=0,BI54=1),GM54-GX54,0) -> 0 | GO54: =IF(BI54=2,GM54-GX54,0) -> 855.13 | GP54: =IF(BI54=4,GM54-GX54,0) -> 0 | GR54: 0 | GS54: 3 | GT54: 0 | GV54: =ROUND((GT54),6) -> 0 | GW54: 1 | GX54: =ROUND(HC54*I54,2) -> 0 | HA54: 0 | HB54: 0 | HC54: =GV54*GW54 -> 0 | HS54: 0 | IK54: 0
A55: 17 | B55: 1 | D55: =ROW(EtalonRes!A32) -> 32 | E55: 7 | F55: 4.10-76-10 | G55: Монтаж ключа или кнопки на панели | H55: 1 ШТ. | I55: 24 | J55: 0 | K55: 24 | O55: =ROUND(CP55,2) -> 18818.35 | P55: =ROUND((ROUND((AC55*AW55*I55),2)*BC55),2) -> 745.89 | Q55: =(ROUND((ROUND((((ET55*1.1))*AV55*I55),2)*BB55),2)+ROUND((ROUND(((AE55-((EU55*1.1)))*AV55*I55),2)*BS55),2)) -> 0 | R55: =ROUND((ROUND((AE55*AV55*I55),2)*BS55),2) -> 0 | S55: =ROUND((ROUND((AF55*AV55*I55),2)*BA55),2) -> 18072.46 | T55: =ROUND(CU55*I55,2) -> 0 | U55: =CV55*I55 -> 27.6408 | V55: =CW55*I55 -> 0 | W55: =ROUND(CX55*I55,2) -> 0 | X55: =ROUND(CY55,2) -> 17168.84 | Y55: =ROUND(CZ55,2) -> 9578.4 | AA55: 56498968 | AB55: =ROUND((AC55+AD55+AF55),6) -> 14.749 | AC55: =ROUND((ES55),6) -> 1.67 | AD55: =ROUND(((((ET55*1.1))-((EU55*1.1)))+AE55),6) -> 0 | AE55: =ROUND(((EU55*1.1)),6) -> 0 | AF55: =ROUND(((EV55*1.1)),6) -> 13.079 | AG55: =ROUND((AP55),6) -> 0 | AH55: =((EW55*1.1)) -> 1.1 | AI55: =((EX55*1.1)) -> 0 | AJ55: =(AS55) -> 0 | AK55: 13.56 | AL55: 1.67 | AM55: 0 | AN55: 0 | AO55: 11.89 | AP55: 0 | AQ55: 1 | AR55: 0 | AS55: 0 | AT55: 95 | AU55: 53 | AV55: 1.047 | AW55: 1 | AZ55: 1 | BA55: 54.99 | BB55: 1 | BC55: 18.61 | BH55: 0 | BI55: 2 | BJ55: ТСН-2001.4 Доп. 79, Сб. 10, т. 76, поз. 10 | BM55: 69 | BN55: 0 | BO55: 4.10-76-10 | BP55: 1 | BQ55: 40 | BR55: 0 | BS55: 54.99 | BT55: 1 | BU55: 1 | BV55: 1 | BW55: 1 | BX55: 1 | BZ55: 95 | CA55: 53 | CE55: 30 | CF55: 0 | CG55: 0 | CM55: 0 | CO55: 0 | CP55: =(P55+Q55+S55) -> 18818.35 | CQ55: =ROUND((ROUND((AC55*AW55*1),2)*BC55),2) -> 31.08 | CR55: =(ROUND((ROUND((((ET55*1.1))*AV55*1),2)*BB55),2)+ROUND((ROUND(((AE55-((EU55*1.1)))*AV55*1),2)*BS55),2)) -> 0 | CS55: =ROUND((ROUND((AE55*AV55*1),2)*BS55),2) -> 0 | CT55: =ROUND((ROUND((AF55*AV55*1),2)*BA55),2) -> 752.81 | CU55: =AG55 -> 0 | CV55: =(AH55*AV55) -> 1.1517 | CW55: =AI55 -> 0 | CX55: =AJ55 -> 0 | CY55: =(((S55+R55)*AT55)/100) -> 17168.837 | CZ55: =(((S55+R55)*AU55)/100) -> 9578.4038 | DE55: *1,1 | DF55: *1,1 | DG55: *1,1 | DI55: *1,1 | DJ55: *1,1 | DN55: 0 | DO55: 0 | DP55: 1 | DQ55: 1 | DU55: 1013 | DV55: 1 ШТ. | DW55: 1 ШТ. | DX55: 1 | EE55: 58162631 | EF55: 40 | EG55: Монтаж оборудования | EH55: 0 | EJ55: 2 | EK55: 69 | EL55: ТСН-2001.4-10. Монтаж радиотелевизионного и электронного оборудования | EM55: ТСН-2001.4-10-2 | EO55: Поправка: Гл.12.Прил.8.п.8. 5_12.00.01.11.003 | EQ55: 0 | ER55: 13.56 | ES55: 1.67 | ET55: 0 | EU55: 0 | EV55: 11.89 | EW55: 1 | EX55: 0 | EY55: 0 | FQ55: 0 | FR55: 0 | FS55: 0 | FX55: 95 | FY55: 53 | GD55: 1 | GF55: -508473279 | GG55: 2 | GH55: 1 | GI55: 2 | GJ55: 0 | GK55: 0 | GL55: =ROUND(IF(AND(BH55=3,BI55=3,FS55<>0),P55,0),2) -> 0 | GM55: =ROUND(O55+X55+Y55,2)+GX55 -> 45565.59 | GN55: =IF(OR(BI55=0,BI55=1),GM55-GX55,0) -> 0 | GO55: =IF(BI55=2,GM55-GX55,0) -> 45565.59 | GP55: =IF(BI55=4,GM55-GX55,0) -> 0 | GR55: 0 | GS55: 3 | GT55: 0 | GV55: =ROUND((GT55),6) -> 0 | GW55: 1 | GX55: =ROUND(HC55*I55,2) -> 0 | HA55: 0 | HB55: 0 | HC55: =GV55*GW55 -> 0 | HS55: 0 | IK55: 0
A56: 18 | B56: 1 | E56: 7,1 | F56: КА 8 | G56: Извещатель пожарный ручной адресный с изолятором ИПР 513-11ИКЗ-А-R3 301159 | H56: шт. | I56: =I54*J56 -> 24 | J56: 1 | K56: 1 | O56: =ROUND(CP56,2) -> 3383.04 | P56: =ROUND((ROUND((AC56*I56),2)*BC56),2) -> 3383.04 | Q56: =(ROUND((ROUND(((ET56)*AV56*I56),2)*BB56),2)+ROUND((ROUND(((AE56-(EU56))*AV56*I56),2)*BS56),2)) -> 0 | R56: =ROUND((ROUND((AE56*AV56*I56),2)*BS56),2) -> 0 | S56: =ROUND((ROUND((AF56*AV56*I56),2)*BA56),2) -> 0 | T56: =ROUND(CU56*I56,2) -> 0 | U56: =CV56*I56 -> 0 | V56: =CW56*I56 -> 0 | W56: =ROUND(CX56*I56,2) -> 0 | X56: =ROUND(CY56,2) -> 0 | Y56: =ROUND(CZ56,2) -> 0 | AA56: 56498966 | AB56: =ROUND((AC56+AD56+AF56),6) -> 140.96 | AC56: =ROUND((ES56),6) -> 140.96 | AD56: =ROUND((((ET56)-(EU56))+AE56),6) -> 0 | AE56: =ROUND((EU56),6) -> 0 | AF56: =ROUND((EV56),6) -> 0 | AG56: =ROUND((AP56),6) -> 0 | AH56: =(EW56) -> 0 | AI56: =(EX56) -> 0 | AJ56: =(AS56) -> 0 | AK56: 140.96 | AL56: 140.96 | AM56: 0 | AN56: 0 | AO56: 0 | AP56: 0 | AQ56: 0 | AR56: 0 | AS56: 0 | AT56: 0 | AU56: 0 | AV56: 1 | AW56: 1 | AZ56: 1 | BA56: 1 | BB56: 1 | BC56: 1 | BH56: 3 | BI56: 3 | BM56: 746 | BN56: 0 | BP56: 0 | BQ56: 130 | BR56: 0 | BS56: 1 | BT56: 1 | BU56: 1 | BV56: 1 | BW56: 1 | BX56: 1 | BZ56: 95 | CA56: 53 | CE56: 30 | CF56: 0 | CG56: 0 | CM56: 0 | CO56: 0 | CP56: =(P56+Q56+S56) -> 3383.04 | CQ56: =ROUND((ROUND((AC56*1),2)*BC56),2) -> 140.96 | CR56: =(ROUND((ROUND(((ET56)*AV56*1),2)*BB56),2)+ROUND((ROUND(((AE56-(EU56))*AV56*1),2)*BS56),2)) -> 0 | CS56: =ROUND((ROUND((AE56*AV56*1),2)*BS56),2) -> 0 | CT56: =ROUND((ROUND((AF56*AV56*1),2)*BA56),2) -> 0 | CU56: =AG56 -> 0 | CV56: =(AH56*AV56) -> 0 | CW56: =AI56 -> 0 | CX56: =AJ56 -> 0 | CY56: =(((S56+R56)*AT56)/100) -> 0 | CZ56: =(((S56+R56)*AU56)/100) -> 0 | DN56: 0 | DO56: 0 | DP56: 1 | DQ56: 1 | DU56: 1010 | DV56: шт. | DW56: шт. | DX56: 1 | EE56: 58162750 | EF56: 130 | EG56: Сметная стоимость оборудования | EH56: 0 | EJ56: 3 | EK56: 746 | EL56: ТСН-2001.13. Сметная стоимость оборудования | EM56: ТСН-2001.13 | EQ56: 0 | ER56: 0 | ES56: 140.96 | ET56: 0 | EU56: 0 | EV56: 0 | EW56: 0 | EX56: 0 | FQ56: 0 | FR56: =P56 -> 3383.04 | FS56: 0 | FX56: 95 | FY56: 53 | GA56: [1 243 / 1,2 / 7,66] + 3% Трансп + 1,2% Заг.скл | GD56: 1 | GF56: 2140523987 | GG56: 2 | GH56: 4 | GI56: -2 | GJ56: 0 | GK56: 0 | GL56: =ROUND(IF(AND(BH56=3,BI56=3,FS56<>0),P56,0),2) -> 0 | GM56: =ROUND(O56+X56+Y56,2)+GX56 -> 3383.04 | GN56: =IF(OR(BI56=0,BI56=1),GM56-GX56,0) -> 0 | GO56: =IF(BI56=2,GM56-GX56,0) -> 0 | GP56: =IF(BI56=4,GM56-GX56,0) -> 0 | GR56: 0 | GS56: 2 | GT56: 0 | GV56: =ROUND((GT56),6) -> 0 | GW56: 1 | GX56: =ROUND(HC56*I56,2) -> 0 | HA56: 0 | HB56: 0 | HC56: =GV56*GW56 -> 0 | HE56: 3 | HF56: 1,2 | HS56: 0 | IK56: 0
A57: 18 | B57: 1 | E57: 7,1 | F57: КА 8 | G57: Извещатель пожарный ручной адресный с изолятором ИПР 513-11ИКЗ-А-R3 301159 | H57: шт. | I57: =I55*J57 -> 24 | J57: 1 | K57: 1 | O57: =ROUND(CP57,2) -> 25914.09 | P57: =ROUND((ROUND((AC57*I57),2)*BC57),2) -> 25914.09 | Q57: =(ROUND((ROUND(((ET57)*AV57*I57),2)*BB57),2)+ROUND((ROUND(((AE57-(EU57))*AV57*I57),2)*BS57),2)) -> 0 | R57: =ROUND((ROUND((AE57*AV57*I57),2)*BS57),2) -> 0 | S57: =ROUND((ROUND((AF57*AV57*I57),2)*BA57),2) -> 0 | T57: =ROUND(CU57*I57,2) -> 0 | U57: =CV57*I57 -> 0 | V57: =CW57*I57 -> 0 | W57: =ROUND(CX57*I57,2) -> 0 | X57: =ROUND(CY57,2) -> 0 | Y57: =ROUND(CZ57,2) -> 0 | AA57: 56498968 | AB57: =ROUND((AC57+AD57+AF57),6) -> 140.96 | AC57: =ROUND((ES57),6) -> 140.96 | AD57: =ROUND((((ET57)-(EU57))+AE57),6) -> 0 | AE57: =ROUND((EU57),6) -> 0 | AF57: =ROUND((EV57),6) -> 0 | AG57: =ROUND((AP57),6) -> 0 | AH57: =(EW57) -> 0 | AI57: =(EX57) -> 0 | AJ57: =(AS57) -> 0 | AK57: 140.96 | AL57: 140.96 | AM57: 0 | AN57: 0 | AO57: 0 | AP57: 0 | AQ57: 0 | AR57: 0 | AS57: 0 | AT57: 0 | AU57: 0 | AV57: 1 | AW57: 1 | AZ57: 1 | BA57: 1 | BB57: 1 | BC57: 7.66 | BH57: 3 | BI57: 3 | BM57: 746 | BN57: 0 | BP57: 0 | BQ57: 130 | BR57: 0 | BS57: 1 | BT57: 1 | BU57: 1 | BV57: 1 | BW57: 1 | BX57: 1 | BZ57: 95 | CA57: 53 | CE57: 30 | CF57: 0 | CG57: 0 | CM57: 0 | CO57: 0 | CP57: =(P57+Q57+S57) -> 25914.09 | CQ57: =ROUND((ROUND((AC57*1),2)*BC57),2) -> 1079.75 | CR57: =(ROUND((ROUND(((ET57)*AV57*1),2)*BB57),2)+ROUND((ROUND(((AE57-(EU57))*AV57*1),2)*BS57),2)) -> 0 | CS57: =ROUND((ROUND((AE57*AV57*1),2)*BS57),2) -> 0 | CT57: =ROUND((ROUND((AF57*AV57*1),2)*BA57),2) -> 0 | CU57: =AG57 -> 0 | CV57: =(AH57*AV57) -> 0 | CW57: =AI57 -> 0 | CX57: =AJ57 -> 0 | CY57: =(((S57+R57)*AT57)/100) -> 0 | CZ57: =(((S57+R57)*AU57)/100) -> 0 | DN57: 0 | DO57: 0 | DP57: 1 | DQ57: 1 | DU57: 1010 | DV57: шт. | DW57: шт. | DX57: 1 | EE57: 58162750 | EF57: 130 | EG57: Сметная стоимость оборудования | EH57: 0 | EJ57: 3 | EK57: 746 | EL57: ТСН-2001.13. Сметная стоимость оборудования | EM57: ТСН-2001.13 | EQ57: 0 | ER57: 140.96 | ES57: 140.96 | ET57: 0 | EU57: 0 | EV57: 0 | EW57: 0 | EX57: 0 | EZ57: 5 | FC57: 1 | FD57: 18 | FF57: 1243 | FQ57: 0 | FR57: =P57 -> 25914.09 | FS57: 0 | FX57: 95 | FY57: 53 | GA57: [1 243 / 1,2 / 7,66] + 3% Трансп + 1,2% Заг.скл | GD57: 1 | GF57: 2140523987 | GG57: 2 | GH57: 3 | GI57: 5 | GJ57: 0 | GK57: 0 | GL57: =ROUND(IF(AND(BH57=3,BI57=3,FS57<>0),P57,0),2) -> 0 | GM57: =ROUND(O57+X57+Y57,2)+GX57 -> 25914.09 | GN57: =IF(OR(BI57=0,BI57=1),GM57-GX57,0) -> 0 | GO57: =IF(BI57=2,GM57-GX57,0) -> 0 | GP57: =IF(BI57=4,GM57-GX57,0) -> 0 | GR57: 1 | GS57: 1 | GT57: 0 | GV57: =ROUND((GT57),6) -> 0 | GW57: 1 | GX57: =ROUND(HC57*I57,2) -> 0 | HA57: 0 | HB57: 0 | HC57: =GV57*GW57 -> 0 | HE57: 3 | HF57: 1,2 | HS57: 0 | IK57: 0
A58: 17 | B58: 1 | D58: =ROW(EtalonRes!A33) -> 33 | E58: 8 | F58: 4.10-81-1 | G58: Извещатели ПС автоматические, тепловой электроконтактный, магнито-контактный в нормальном исполнении | H58: 1 ШТ. | I58: 5 | J58: 0 | K58: 5 | O58: =ROUND(CP58,2) -> 64.01 | P58: =ROUND((ROUND((AC58*AW58*I58),2)*BC58),2) -> 2.8 | Q58: =(ROUND((ROUND((((ET58*1.1))*AV58*I58),2)*BB58),2)+ROUND((ROUND(((AE58-((EU58*1.1)))*AV58*I58),2)*BS58),2)) -> 0.17 | R58: =ROUND((ROUND((AE58*AV58*I58),2)*BS58),2) -> 0 | S58: =ROUND((ROUND((AF58*AV58*I58),2)*BA58),2) -> 61.04 | T58: =ROUND(CU58*I58,2) -> 0 | U58: =CV58*I58 -> 4.83714 | V58: =CW58*I58 -> 0 | W58: =ROUND(CX58*I58,2) -> 0 | X58: =ROUND(CY58,2) -> 54.94 | Y58: =ROUND(CZ58,2) -> 28.08 | AA58: 56498966 | AB58: =ROUND((AC58+AD58+AF58),6) -> 12.253 | AC58: =ROUND((ES58),6) -> 0.56 | AD58: =ROUND(((((ET58*1.1))-((EU58*1.1)))+AE58),6) -> 0.033 | AE58: =ROUND(((EU58*1.1)),6) -> 0 | AF58: =ROUND(((EV58*1.1)),6) -> 11.66 | AG58: =ROUND((AP58),6) -> 0 | AH58: =((EW58*1.1)) -> 0.924 | AI58: =((EX58*1.1)) -> 0 | AJ58: =(AS58) -> 0 | AK58: 11.19 | AL58: 0.56 | AM58: 0.03 | AN58: 0 | AO58: 10.6 | AP58: 0 | AQ58: 0.84 | AR58: 0 | AS58: 0 | AT58: 90 | AU58: 46 | AV58: 1.047 | AW58: 1 | AZ58: 1 | BA58: 1 | BB58: 1 | BC58: 1 | BH58: 0 | BI58: 2 | BJ58: ТСН-2001.4. Доп. 1-42. Сб. 10, т. 81, поз. 1 | BM58: 68 | BN58: 0 | BO58: 4.10-81-1 | BP58: 1 | BQ58: 40 | BR58: 0 | BS58: 1 | BT58: 1 | BU58: 1 | BV58: 1 | BW58: 1 | BX58: 1 | BZ58: 90 | CA58: 46 | CE58: 30 | CF58: 0 | CG58: 0 | CM58: 0 | CO58: 0 | CP58: =(P58+Q58+S58) -> 64.01 | CQ58: =ROUND((ROUND((AC58*AW58*1),2)*BC58),2) -> 0.56 | CR58: =(ROUND((ROUND((((ET58*1.1))*AV58*1),2)*BB58),2)+ROUND((ROUND(((AE58-((EU58*1.1)))*AV58*1),2)*BS58),2)) -> 0.03 | CS58: =ROUND((ROUND((AE58*AV58*1),2)*BS58),2) -> 0 | CT58: =ROUND((ROUND((AF58*AV58*1),2)*BA58),2) -> 12.21 | CU58: =AG58 -> 0 | CV58: =(AH58*AV58) -> 0.967428 | CW58: =AI58 -> 0 | CX58: =AJ58 -> 0 | CY58: =(((S58+R58)*AT58)/100) -> 54.936 | CZ58: =(((S58+R58)*AU58)/100) -> 28.0784 | DE58: *1,1 | DF58: *1,1 | DG58: *1,1 | DI58: *1,1 | DJ58: *1,1 | DN58: 0 | DO58: 0 | DP58: 1 | DQ58: 1 | DU58: 1013 | DV58: 1 ШТ. | DW58: 1 ШТ. | DX58: 1 | EE58: 58162630 | EF58: 40 | EG58: Монтаж оборудования | EH58: 0 | EJ58: 2 | EK58: 68 | EL58: ТСН-2001.4-10. Прокладка и монтаж сетей связи | EM58: ТСН-2001.4-10-1 | EO58: Поправка: Гл.12.Прил.8.п.8. 5_12.00.01.11.003 | EQ58: 0 | ER58: 11.19 | ES58: 0.56 | ET58: 0.03 | EU58: 0 | EV58: 10.6 | EW58: 0.84 | EX58: 0 | EY58: 0 | FQ58: 0 | FR58: 0 | FS58: 0 | FX58: 90 | FY58: 46 | GD58: 1 | GF58: -1257928153 | GG58: 2 | GH58: 1 | GI58: 2 | GJ58: 0 | GK58: 0 | GL58: =ROUND(IF(AND(BH58=3,BI58=3,FS58<>0),P58,0),2) -> 0 | GM58: =ROUND(O58+X58+Y58,2)+GX58 -> 147.03 | GN58: =IF(OR(BI58=0,BI58=1),GM58-GX58,0) -> 0 | GO58: =IF(BI58=2,GM58-GX58,0) -> 147.03 | GP58: =IF(BI58=4,GM58-GX58,0) -> 0 | GR58: 0 | GS58: 3 | GT58: 0 | GV58: =ROUND((GT58),6) -> 0 | GW58: 1 | GX58: =ROUND(HC58*I58,2) -> 0 | HA58: 0 | HB58: 0 | HC58: =GV58*GW58 -> 0 | HS58: 0 | IK58: 0
A59: 17 | B59: 1 | D59: =ROW(EtalonRes!A34) -> 34 | E59: 8 | F59: 4.10-81-1 | G59: Извещатели ПС автоматические, тепловой электроконтактный, магнито-контактный в нормальном исполнении | H59: 1 ШТ. | I59: 5 | J59: 0 | K59: 5 | O59: =ROUND(CP59,2) -> 3385.98 | P59: =ROUND((ROUND((AC59*AW59*I59),2)*BC59),2) -> 27.69 | Q59: =(ROUND((ROUND((((ET59*1.1))*AV59*I59),2)*BB59),2)+ROUND((ROUND(((AE59-((EU59*1.1)))*AV59*I59),2)*BS59),2)) -> 1.7 | R59: =ROUND((ROUND((AE59*AV59*I59),2)*BS59),2) -> 0 | S59: =ROUND((ROUND((AF59*AV59*I59),2)*BA59),2) -> 3356.59 | T59: =ROUND(CU59*I59,2) -> 0 | U59: =CV59*I59 -> 4.83714 | V59: =CW59*I59 -> 0 | W59: =ROUND(CX59*I59,2) -> 0 | X59: =ROUND(CY59,2) -> 3020.93 | Y59: =ROUND(CZ59,2) -> 1544.03 | AA59: 56498968 | AB59: =ROUND((AC59+AD59+AF59),6) -> 12.253 | AC59: =ROUND((ES59),6) -> 0.56 | AD59: =ROUND(((((ET59*1.1))-((EU59*1.1)))+AE59),6) -> 0.033 | AE59: =ROUND(((EU59*1.1)),6) -> 0 | AF59: =ROUND(((EV59*1.1)),6) -> 11.66 | AG59: =ROUND((AP59),6) -> 0 | AH59: =((EW59*1.1)) -> 0.924 | AI59: =((EX59*1.1)) -> 0 | AJ59: =(AS59) -> 0 | AK59: 11.19 | AL59: 0.56 | AM59: 0.03 | AN59: 0 | AO59: 10.6 | AP59: 0 | AQ59: 0.84 | AR59: 0 | AS59: 0 | AT59: 90 | AU59: 46 | AV59: 1.047 | AW59: 1 | AZ59: 1 | BA59: 54.99 | BB59: 10 | BC59: 9.89 | BH59: 0 | BI59: 2 | BJ59: ТСН-2001.4. Доп. 1-42. Сб. 10, т. 81, поз. 1 | BM59: 68 | BN59: 0 | BO59: 4.10-81-1 | BP59: 1 | BQ59: 40 | BR59: 0 | BS59: 54.99 | BT59: 1 | BU59: 1 | BV59: 1 | BW59: 1 | BX59: 1 | BZ59: 90 | CA59: 46 | CE59: 30 | CF59: 0 | CG59: 0 | CM59: 0 | CO59: 0 | CP59: =(P59+Q59+S59) -> 3385.98 | CQ59: =ROUND((ROUND((AC59*AW59*1),2)*BC59),2) -> 5.54 | CR59: =(ROUND((ROUND((((ET59*1.1))*AV59*1),2)*BB59),2)+ROUND((ROUND(((AE59-((EU59*1.1)))*AV59*1),2)*BS59),2)) -> 0.3 | CS59: =ROUND((ROUND((AE59*AV59*1),2)*BS59),2) -> 0 | CT59: =ROUND((ROUND((AF59*AV59*1),2)*BA59),2) -> 671.43 | CU59: =AG59 -> 0 | CV59: =(AH59*AV59) -> 0.967428 | CW59: =AI59 -> 0 | CX59: =AJ59 -> 0 | CY59: =(((S59+R59)*AT59)/100) -> 3020.931 | CZ59: =(((S59+R59)*AU59)/100) -> 1544.0314 | DE59: *1,1 | DF59: *1,1 | DG59: *1,1 | DI59: *1,1 | DJ59: *1,1 | DN59: 0 | DO59: 0 | DP59: 1 | DQ59: 1 | DU59: 1013 | DV59: 1 ШТ. | DW59: 1 ШТ. | DX59: 1 | EE59: 58162630 | EF59: 40 | EG59: Монтаж оборудования | EH59: 0 | EJ59: 2 | EK59: 68 | EL59: ТСН-2001.4-10. Прокладка и монтаж сетей связи | EM59: ТСН-2001.4-10-1 | EO59: Поправка: Гл.12.Прил.8.п.8. 5_12.00.01.11.003 | EQ59: 0 | ER59: 11.19 | ES59: 0.56 | ET59: 0.03 | EU59: 0 | EV59: 10.6 | EW59: 0.84 | EX59: 0 | EY59: 0 | FQ59: 0 | FR59: 0 | FS59: 0 | FX59: 90 | FY59: 46 | GD59: 1 | GF59: -1257928153 | GG59: 2 | GH59: 1 | GI59: 2 | GJ59: 0 | GK59: 0 | GL59: =ROUND(IF(AND(BH59=3,BI59=3,FS59<>0),P59,0),2) -> 0 | GM59: =ROUND(O59+X59+Y59,2)+GX59 -> 7950.94 | GN59: =IF(OR(BI59=0,BI59=1),GM59-GX59,0) -> 0 | GO59: =IF(BI59=2,GM59-GX59,0) -> 7950.94 | GP59: =IF(BI59=4,GM59-GX59,0) -> 0 | GR59: 0 | GS59: 3 | GT59: 0 | GV59: =ROUND((GT59),6) -> 0 | GW59: 1 | GX59: =ROUND(HC59*I59,2) -> 0 | HA59: 0 | HB59: 0 | HC59: =GV59*GW59 -> 0 | HS59: 0 | IK59: 0
A60: 18 | B60: 1 | E60: 8,1 | F60: КА 9 | G60: Извещатель пожарный тепловой адресный ИП 101-29-PR-R3 337480 | H60: шт. | I60: =I58*J60 -> 5 | J60: 1 | K60: 1 | O60: =ROUND(CP60,2) -> 852.75 | P60: =ROUND((ROUND((AC60*I60),2)*BC60),2) -> 852.75 | Q60: =(ROUND((ROUND(((ET60)*AV60*I60),2)*BB60),2)+ROUND((ROUND(((AE60-(EU60))*AV60*I60),2)*BS60),2)) -> 0 | R60: =ROUND((ROUND((AE60*AV60*I60),2)*BS60),2) -> 0 | S60: =ROUND((ROUND((AF60*AV60*I60),2)*BA60),2) -> 0 | T60: =ROUND(CU60*I60,2) -> 0 | U60: =CV60*I60 -> 0 | V60: =CW60*I60 -> 0 | W60: =ROUND(CX60*I60,2) -> 0 | X60: =ROUND(CY60,2) -> 0 | Y60: =ROUND(CZ60,2) -> 0 | AA60: 56498966 | AB60: =ROUND((AC60+AD60+AF60),6) -> 170.55 | AC60: =ROUND((ES60),6) -> 170.55 | AD60: =ROUND((((ET60)-(EU60))+AE60),6) -> 0 | AE60: =ROUND((EU60),6) -> 0 | AF60: =ROUND((EV60),6) -> 0 | AG60: =ROUND((AP60),6) -> 0 | AH60: =(EW60) -> 0 | AI60: =(EX60) -> 0 | AJ60: =(AS60) -> 0 | AK60: 170.55 | AL60: 170.55 | AM60: 0 | AN60: 0 | AO60: 0 | AP60: 0 | AQ60: 0 | AR60: 0 | AS60: 0 | AT60: 0 | AU60: 0 | AV60: 1 | AW60: 1 | AZ60: 1 | BA60: 1 | BB60: 1 | BC60: 1 | BH60: 3 | BI60: 3 | BM60: 746 | BN60: 0 | BP60: 0 | BQ60: 130 | BR60: 0 | BS60: 1 | BT60: 1 | BU60: 1 | BV60: 1 | BW60: 1 | BX60: 1 | BZ60: 90 | CA60: 46 | CE60: 30 | CF60: 0 | CG60: 0 | CM60: 0 | CO60: 0 | CP60: =(P60+Q60+S60) -> 852.75 | CQ60: =ROUND((ROUND((AC60*1),2)*BC60),2) -> 170.55 | CR60: =(ROUND((ROUND(((ET60)*AV60*1),2)*BB60),2)+ROUND((ROUND(((AE60-(EU60))*AV60*1),2)*BS60),2)) -> 0 | CS60: =ROUND((ROUND((AE60*AV60*1),2)*BS60),2) -> 0 | CT60: =ROUND((ROUND((AF60*AV60*1),2)*BA60),2) -> 0 | CU60: =AG60 -> 0 | CV60: =(AH60*AV60) -> 0 | CW60: =AI60 -> 0 | CX60: =AJ60 -> 0 | CY60: =(((S60+R60)*AT60)/100) -> 0 | CZ60: =(((S60+R60)*AU60)/100) -> 0 | DN60: 0 | DO60: 0 | DP60: 1 | DQ60: 1 | DU60: 1010 | DV60: шт. | DW60: шт. | DX60: 1 | EE60: 58162750 | EF60: 130 | EG60: Сметная стоимость оборудования | EH60: 0 | EJ60: 3 | EK60: 746 | EL60: ТСН-2001.13. Сметная стоимость оборудования | EM60: ТСН-2001.13 | EQ60: 0 | ER60: 0 | ES60: 170.55 | ET60: 0 | EU60: 0 | EV60: 0 | EW60: 0 | EX60: 0 | FQ60: 0 | FR60: =P60 -> 852.75 | FS60: 0 | FX60: 90 | FY60: 46 | GA60: [1 504 / 1,2 / 7,66] + 3% Трансп + 1,2% Заг.скл | GD60: 1 | GF60: -467566734 | GG60: 2 | GH60: 4 | GI60: -2 | GJ60: 0 | GK60: 0 | GL60: =ROUND(IF(AND(BH60=3,BI60=3,FS60<>0),P60,0),2) -> 0 | GM60: =ROUND(O60+X60+Y60,2)+GX60 -> 852.75 | GN60: =IF(OR(BI60=0,BI60=1),GM60-GX60,0) -> 0 | GO60: =IF(BI60=2,GM60-GX60,0) -> 0 | GP60: =IF(BI60=4,GM60-GX60,0) -> 0 | GR60: 0 | GS60: 2 | GT60: 0 | GV60: =ROUND((GT60),6) -> 0 | GW60: 1 | GX60: =ROUND(HC60*I60,2) -> 0 | HA60: 0 | HB60: 0 | HC60: =GV60*GW60 -> 0 | HE60: 3 | HF60: 1,2 | HS60: 0 | IK60: 0
A61: 18 | B61: 1 | E61: 8,1 | F61: КА 9 | G61: Извещатель пожарный тепловой адресный ИП 101-29-PR-R3 337480 | H61: шт. | I61: =I59*J61 -> 5 | J61: 1 | K61: 1 | O61: =ROUND(CP61,2) -> 6532.07 | P61: =ROUND((ROUND((AC61*I61),2)*BC61),2) -> 6532.07 | Q61: =(ROUND((ROUND(((ET61)*AV61*I61),2)*BB61),2)+ROUND((ROUND(((AE61-(EU61))*AV61*I61),2)*BS61),2)) -> 0 | R61: =ROUND((ROUND((AE61*AV61*I61),2)*BS61),2) -> 0 | S61: =ROUND((ROUND((AF61*AV61*I61),2)*BA61),2) -> 0 | T61: =ROUND(CU61*I61,2) -> 0 | U61: =CV61*I61 -> 0 | V61: =CW61*I61 -> 0 | W61: =ROUND(CX61*I61,2) -> 0 | X61: =ROUND(CY61,2) -> 0 | Y61: =ROUND(CZ61,2) -> 0 | AA61: 56498968 | AB61: =ROUND((AC61+AD61+AF61),6) -> 170.55 | AC61: =ROUND((ES61),6) -> 170.55 | AD61: =ROUND((((ET61)-(EU61))+AE61),6) -> 0 | AE61: =ROUND((EU61),6) -> 0 | AF61: =ROUND((EV61),6) -> 0 | AG61: =ROUND((AP61),6) -> 0 | AH61: =(EW61) -> 0 | AI61: =(EX61) -> 0 | AJ61: =(AS61) -> 0 | AK61: 170.55 | AL61: 170.55 | AM61: 0 | AN61: 0 | AO61: 0 | AP61: 0 | AQ61: 0 | AR61: 0 | AS61: 0 | AT61: 0 | AU61: 0 | AV61: 1 | AW61: 1 | AZ61: 1 | BA61: 1 | BB61: 1 | BC61: 7.66 | BH61: 3 | BI61: 3 | BM61: 746 | BN61: 0 | BP61: 0 | BQ61: 130 | BR61: 0 | BS61: 1 | BT61: 1 | BU61: 1 | BV61: 1 | BW61: 1 | BX61: 1 | BZ61: 90 | CA61: 46 | CE61: 30 | CF61: 0 | CG61: 0 | CM61: 0 | CO61: 0 | CP61: =(P61+Q61+S61) -> 6532.07 | CQ61: =ROUND((ROUND((AC61*1),2)*BC61),2) -> 1306.41 | CR61: =(ROUND((ROUND(((ET61)*AV61*1),2)*BB61),2)+ROUND((ROUND(((AE61-(EU61))*AV61*1),2)*BS61),2)) -> 0 | CS61: =ROUND((ROUND((AE61*AV61*1),2)*BS61),2) -> 0 | CT61: =ROUND((ROUND((AF61*AV61*1),2)*BA61),2) -> 0 | CU61: =AG61 -> 0 | CV61: =(AH61*AV61) -> 0 | CW61: =AI61 -> 0 | CX61: =AJ61 -> 0 | CY61: =(((S61+R61)*AT61)/100) -> 0 | CZ61: =(((S61+R61)*AU61)/100) -> 0 | DN61: 0 | DO61: 0 | DP61: 1 | DQ61: 1 | DU61: 1010 | DV61: шт. | DW61: шт. | DX61: 1 | EE61: 58162750 | EF61: 130 | EG61: Сметная стоимость оборудования | EH61: 0 | EJ61: 3 | EK61: 746 | EL61: ТСН-2001.13. Сметная стоимость оборудования | EM61: ТСН-2001.13 | EQ61: 0 | ER61: 170.55 | ES61: 170.55 | ET61: 0 | EU61: 0 | EV61: 0 | EW61: 0 | EX61: 0 | EZ61: 5 | FC61: 1 | FD61: 18 | FF61: 1504 | FQ61: 0 | FR61: =P61 -> 6532.07 | FS61: 0 | FX61: 90 | FY61: 46 | GA61: [1 504 / 1,2 / 7,66] + 3% Трансп + 1,2% Заг.скл | GD61: 1 | GF61: -467566734 | GG61: 2 | GH61: 3 | GI61: 5 | GJ61: 0 | GK61: 0 | GL61: =ROUND(IF(AND(BH61=3,BI61=3,FS61<>0),P61,0),2) -> 0 | GM61: =ROUND(O61+X61+Y61,2)+GX61 -> 6532.07 | GN61: =IF(OR(BI61=0,BI61=1),GM61-GX61,0) -> 0 | GO61: =IF(BI61=2,GM61-GX61,0) -> 0 | GP61: =IF(BI61=4,GM61-GX61,0) -> 0 | GR61: 1 | GS61: 1 | GT61: 0 | GV61: =ROUND((GT61),6) -> 0 | GW61: 1 | GX61: =ROUND(HC61*I61,2) -> 0 | HA61: 0 | HB61: 0 | HC61: =GV61*GW61 -> 0 | HE61: 3 | HF61: 1,2 | HS61: 0 | IK61: 0
A62: 17 | B62: 1 | D62: =ROW(EtalonRes!A39) -> 39 | E62: 9 | F62: 4.8-60-1 | G62: Монтаж устройства сигнально-блокировочного | H62: 1 ШТ. | I62: 89 | J62: 0 | K62: 89 | O62: =ROUND(CP62,2) -> 5197.08 | P62: =ROUND((ROUND((AC62*AW62*I62),2)*BC62),2) -> 2532.05 | Q62: =(ROUND((ROUND((((ET62*1.1))*AV62*I62),2)*BB62),2)+ROUND((ROUND(((AE62-((EU62*1.1)))*AV62*I62),2)*BS62),2)) -> 0 | R62: =ROUND((ROUND((AE62*AV62*I62),2)*BS62),2) -> 0 | S62: =ROUND((ROUND((AF62*AV62*I62),2)*BA62),2) -> 2665.03 | T62: =ROUND(CU62*I62,2) -> 0 | U62: =CV62*I62 -> 211.15268 | V62: =CW62*I62 -> 0 | W62: =ROUND(CX62*I62,2) -> 0 | X62: =ROUND(CY62,2) -> 2585.08 | Y62: =ROUND(CZ62,2) -> 1359.17 | AA62: 56498966 | AB62: =ROUND((AC62+AD62+AF62),6) -> 57.05 | AC62: =ROUND((ES62),6) -> 28.45 | AD62: =ROUND(((((ET62*1.1))-((EU62*1.1)))+AE62),6) -> 0 | AE62: =ROUND(((EU62*1.1)),6) -> 0 | AF62: =ROUND(((EV62*1.1)),6) -> 28.6 | AG62: =ROUND((AP62),6) -> 0 | AH62: =((EW62*1.1)) -> 2.266 | AI62: =((EX62*1.1)) -> 0 | AJ62: =(AS62) -> 0 | AK62: 54.45 | AL62: 28.45 | AM62: 0 | AN62: 0 | AO62: 26 | AP62: 0 | AQ62: 2.06 | AR62: 0 | AS62: 0 | AT62: 97 | AU62: 51 | AV62: 1.047 | AW62: 1 | AZ62: 1 | BA62: 1 | BB62: 1 | BC62: 1 | BH62: 0 | BI62: 2 | BJ62: ТСН-2001.4 Доп. 79, Сб. 8, т. 60, поз. 1 | BM62: 67 | BN62: 0 | BO62: 4.8-60-1 | BP62: 1 | BQ62: 40 | BR62: 0 | BS62: 1 | BT62: 1 | BU62: 1 | BV62: 1 | BW62: 1 | BX62: 1 | BZ62: 97 | CA62: 51 | CE62: 30 | CF62: 0 | CG62: 0 | CM62: 0 | CO62: 0 | CP62: =(P62+Q62+S62) -> 5197.08 | CQ62: =ROUND((ROUND((AC62*AW62*1),2)*BC62),2) -> 28.45 | CR62: =(ROUND((ROUND((((ET62*1.1))*AV62*1),2)*BB62),2)+ROUND((ROUND(((AE62-((EU62*1.1)))*AV62*1),2)*BS62),2)) -> 0 | CS62: =ROUND((ROUND((AE62*AV62*1),2)*BS62),2) -> 0 | CT62: =ROUND((ROUND((AF62*AV62*1),2)*BA62),2) -> 29.94 | CU62: =AG62 -> 0 | CV62: =(AH62*AV62) -> 2.372502 | CW62: =AI62 -> 0 | CX62: =AJ62 -> 0 | CY62: =(((S62+R62)*AT62)/100) -> 2585.0791 | CZ62: =(((S62+R62)*AU62)/100) -> 1359.1653 | DE62: *1,1 | DF62: *1,1 | DG62: *1,1 | DI62: *1,1 | DJ62: *1,1 | DN62: 0 | DO62: 0 | DP62: 1 | DQ62: 1 | DU62: 1013 | DV62: 1 ШТ. | DW62: 1 ШТ. | DX62: 1 | EE62: 58162629 | EF62: 40 | EG62: Монтаж оборудования | EH62: 0 | EJ62: 2 | EK62: 67 | EL62: ТСН-2001.4-8. Электротехнические установки | EM62: ТСН-2001.4-8-1 | EO62: Поправка: Гл.12.Прил.8.п.8. 5_12.00.01.11.003 | EQ62: 0 | ER62: 54.45 | ES62: 28.45 | ET62: 0 | EU62: 0 | EV62: 26 | EW62: 2.06 | EX62: 0 | EY62: 0 | FQ62: 0 | FR62: 0 | FS62: 0 | FX62: 97 | FY62: 51 | GD62: 1 | GF62: 1398713646 | GG62: 2 | GH62: 1 | GI62: 2 | GJ62: 0 | GK62: 0 | GL62: =ROUND(IF(AND(BH62=3,BI62=3,FS62<>0),P62,0),2) -> 0 | GM62: =ROUND(O62+X62+Y62,2)+GX62 -> 9141.33 | GN62: =IF(OR(BI62=0,BI62=1),GM62-GX62,0) -> 0 | GO62: =IF(BI62=2,GM62-GX62,0) -> 9141.33 | GP62: =IF(BI62=4,GM62-GX62,0) -> 0 | GR62: 0 | GS62: 3 | GT62: 0 | GV62: =ROUND((GT62),6) -> 0 | GW62: 1 | GX62: =ROUND(HC62*I62,2) -> 0 | HA62: 0 | HB62: 0 | HC62: =GV62*GW62 -> 0 | HS62: 0 | IK62: 0
A63: 17 | B63: 1 | D63: =ROW(EtalonRes!A44) -> 44 | E63: 9 | F63: 4.8-60-1 | G63: Монтаж устройства сигнально-блокировочного | H63: 1 ШТ. | I63: 89 | J63: 0 | K63: 89 | O63: =ROUND(CP63,2) -> 164400.95 | P63: =ROUND((ROUND((AC63*AW63*I63),2)*BC63),2) -> 17850.95 | Q63: =(ROUND((ROUND((((ET63*1.1))*AV63*I63),2)*BB63),2)+ROUND((ROUND(((AE63-((EU63*1.1)))*AV63*I63),2)*BS63),2)) -> 0 | R63: =ROUND((ROUND((AE63*AV63*I63),2)*BS63),2) -> 0 | S63: =ROUND((ROUND((AF63*AV63*I63),2)*BA63),2) -> 146550 | T63: =ROUND(CU63*I63,2) -> 0 | U63: =CV63*I63 -> 211.15268 | V63: =CW63*I63 -> 0 | W63: =ROUND(CX63*I63,2) -> 0 | X63: =ROUND(CY63,2) -> 142153.5 | Y63: =ROUND(CZ63,2) -> 74740.5 | AA63: 56498968 | AB63: =ROUND((AC63+AD63+AF63),6) -> 57.05 | AC63: =ROUND((ES63),6) -> 28.45 | AD63: =ROUND(((((ET63*1.1))-((EU63*1.1)))+AE63),6) -> 0 | AE63: =ROUND(((EU63*1.1)),6) -> 0 | AF63: =ROUND(((EV63*1.1)),6) -> 28.6 | AG63: =ROUND((AP63),6) -> 0 | AH63: =((EW63*1.1)) -> 2.266 | AI63: =((EX63*1.1)) -> 0 | AJ63: =(AS63) -> 0 | AK63: 54.45 | AL63: 28.45 | AM63: 0 | AN63: 0 | AO63: 26 | AP63: 0 | AQ63: 2.06 | AR63: 0 | AS63: 0 | AT63: 97 | AU63: 51 | AV63: 1.047 | AW63: 1 | AZ63: 1 | BA63: 54.99 | BB63: 1 | BC63: 7.05 | BH63: 0 | BI63: 2 | BJ63: ТСН-2001.4 Доп. 79, Сб. 8, т. 60, поз. 1 | BM63: 67 | BN63: 0 | BO63: 4.8-60-1 | BP63: 1 | BQ63: 40 | BR63: 0 | BS63: 54.99 | BT63: 1 | BU63: 1 | BV63: 1 | BW63: 1 | BX63: 1 | BZ63: 97 | CA63: 51 | CE63: 30 | CF63: 0 | CG63: 0 | CM63: 0 | CO63: 0 | CP63: =(P63+Q63+S63) -> 164400.95 | CQ63: =ROUND((ROUND((AC63*AW63*1),2)*BC63),2) -> 200.57 | CR63: =(ROUND((ROUND((((ET63*1.1))*AV63*1),2)*BB63),2)+ROUND((ROUND(((AE63-((EU63*1.1)))*AV63*1),2)*BS63),2)) -> 0 | CS63: =ROUND((ROUND((AE63*AV63*1),2)*BS63),2) -> 0 | CT63: =ROUND((ROUND((AF63*AV63*1),2)*BA63),2) -> 1646.4 | CU63: =AG63 -> 0 | CV63: =(AH63*AV63) -> 2.372502 | CW63: =AI63 -> 0 | CX63: =AJ63 -> 0 | CY63: =(((S63+R63)*AT63)/100) -> 142153.5 | CZ63: =(((S63+R63)*AU63)/100) -> 74740.5 | DE63: *1,1 | DF63: *1,1 | DG63: *1,1 | DI63: *1,1 | DJ63: *1,1 | DN63: 0 | DO63: 0 | DP63: 1 | DQ63: 1 | DU63: 1013 | DV63: 1 ШТ. | DW63: 1 ШТ. | DX63: 1 | EE63: 58162629 | EF63: 40 | EG63: Монтаж оборудования | EH63: 0 | EJ63: 2 | EK63: 67 | EL63: ТСН-2001.4-8. Электротехнические установки | EM63: ТСН-2001.4-8-1 | EO63: Поправка: Гл.12.Прил.8.п.8. 5_12.00.01.11.003 | EQ63: 0 | ER63: 54.45 | ES63: 28.45 | ET63: 0 | EU63: 0 | EV63: 26 | EW63: 2.06 | EX63: 0 | EY63: 0 | FQ63: 0 | FR63: 0 | FS63: 0 | FX63: 97 | FY63: 51 | GD63: 1 | GF63: 1398713646 | GG63: 2 | GH63: 1 | GI63: 2 | GJ63: 0 | GK63: 0 | GL63: =ROUND(IF(AND(BH63=3,BI63=3,FS63<>0),P63,0),2) -> 0 | GM63: =ROUND(O63+X63+Y63,2)+GX63 -> 381294.95 | GN63: =IF(OR(BI63=0,BI63=1),GM63-GX63,0) -> 0 | GO63: =IF(BI63=2,GM63-GX63,0) -> 381294.95 | GP63: =IF(BI63=4,GM63-GX63,0) -> 0 | GR63: 0 | GS63: 3 | GT63: 0 | GV63: =ROUND((GT63),6) -> 0 | GW63: 1 | GX63: =ROUND(HC63*I63,2) -> 0 | HA63: 0 | HB63: 0 | HC63: =GV63*GW63 -> 0 | HS63: 0 | IK63: 0
A64: 18 | B64: 1 | E64: 9,1 | F64: КА 10 | G64: Изолятор шлейфа ИЗ-1-R3 337647 | H64: шт. | I64: =I62*J64 -> 89 | J64: 1 | K64: 1 | O64: =ROUND(CP64,2) -> 6873.47 | P64: =ROUND((ROUND((AC64*I64),2)*BC64),2) -> 6873.47 | Q64: =(ROUND((ROUND(((ET64)*AV64*I64),2)*BB64),2)+ROUND((ROUND(((AE64-(EU64))*AV64*I64),2)*BS64),2)) -> 0 | R64: =ROUND((ROUND((AE64*AV64*I64),2)*BS64),2) -> 0 | S64: =ROUND((ROUND((AF64*AV64*I64),2)*BA64),2) -> 0 | T64: =ROUND(CU64*I64,2) -> 0 | U64: =CV64*I64 -> 0 | V64: =CW64*I64 -> 0 | W64: =ROUND(CX64*I64,2) -> 0 | X64: =ROUND(CY64,2) -> 0 | Y64: =ROUND(CZ64,2) -> 0 | AA64: 56498966 | AB64: =ROUND((AC64+AD64+AF64),6) -> 77.23 | AC64: =ROUND((ES64),6) -> 77.23 | AD64: =ROUND((((ET64)-(EU64))+AE64),6) -> 0 | AE64: =ROUND((EU64),6) -> 0 | AF64: =ROUND((EV64),6) -> 0 | AG64: =ROUND((AP64),6) -> 0 | AH64: =(EW64) -> 0 | AI64: =(EX64) -> 0 | AJ64: =(AS64) -> 0 | AK64: 77.23 | AL64: 77.23 | AM64: 0 | AN64: 0 | AO64: 0 | AP64: 0 | AQ64: 0 | AR64: 0 | AS64: 0 | AT64: 0 | AU64: 0 | AV64: 1 | AW64: 1 | AZ64: 1 | BA64: 1 | BB64: 1 | BC64: 1 | BH64: 3 | BI64: 3 | BM64: 746 | BN64: 0 | BP64: 0 | BQ64: 130 | BR64: 0 | BS64: 1 | BT64: 1 | BU64: 1 | BV64: 1 | BW64: 1 | BX64: 1 | BZ64: 97 | CA64: 51 | CE64: 30 | CF64: 0 | CG64: 0 | CM64: 0 | CO64: 0 | CP64: =(P64+Q64+S64) -> 6873.47 | CQ64: =ROUND((ROUND((AC64*1),2)*BC64),2) -> 77.23 | CR64: =(ROUND((ROUND(((ET64)*AV64*1),2)*BB64),2)+ROUND((ROUND(((AE64-(EU64))*AV64*1),2)*BS64),2)) -> 0 | CS64: =ROUND((ROUND((AE64*AV64*1),2)*BS64),2) -> 0 | CT64: =ROUND((ROUND((AF64*AV64*1),2)*BA64),2) -> 0 | CU64: =AG64 -> 0 | CV64: =(AH64*AV64) -> 0 | CW64: =AI64 -> 0 | CX64: =AJ64 -> 0 | CY64: =(((S64+R64)*AT64)/100) -> 0 | CZ64: =(((S64+R64)*AU64)/100) -> 0 | DN64: 0 | DO64: 0 | DP64: 1 | DQ64: 1 | DU64: 1010 | DV64: шт. | DW64: шт. | DX64: 1 | EE64: 58162750 | EF64: 130 | EG64: Сметная стоимость оборудования | EH64: 0 | EJ64: 3 | EK64: 746 | EL64: ТСН-2001.13. Сметная стоимость оборудования | EM64: ТСН-2001.13 | EQ64: 0 | ER64: 0 | ES64: 77.23 | ET64: 0 | EU64: 0 | EV64: 0 | EW64: 0 | EX64: 0 | FQ64: 0 | FR64: =P64 -> 6873.47 | FS64: 0 | FX64: 97 | FY64: 51 | GA64: [681 / 1,2 / 7,66] + 3% Трансп + 1,2% Заг.скл | GD64: 1 | GF64: -1365184430 | GG64: 2 | GH64: 4 | GI64: -2 | GJ64: 0 | GK64: 0 | GL64: =ROUND(IF(AND(BH64=3,BI64=3,FS64<>0),P64,0),2) -> 0 | GM64: =ROUND(O64+X64+Y64,2)+GX64 -> 6873.47 | GN64: =IF(OR(BI64=0,BI64=1),GM64-GX64,0) -> 0 | GO64: =IF(BI64=2,GM64-GX64,0) -> 0 | GP64: =IF(BI64=4,GM64-GX64,0) -> 0 | GR64: 0 | GS64: 2 | GT64: 0 | GV64: =ROUND((GT64),6) -> 0 | GW64: 1 | GX64: =ROUND(HC64*I64,2) -> 0 | HA64: 0 | HB64: 0 | HC64: =GV64*GW64 -> 0 | HE64: 3 | HF64: 1,2 | HS64: 0 | IK64: 0
A65: 18 | B65: 1 | E65: 9,1 | F65: КА 10 | G65: Изолятор шлейфа ИЗ-1-R3 337647 | H65: шт. | I65: =I63*J65 -> 89 | J65: 1 | K65: 1 | O65: =ROUND(CP65,2) -> 52650.78 | P65: =ROUND((ROUND((AC65*I65),2)*BC65),2) -> 52650.78 | Q65: =(ROUND((ROUND(((ET65)*AV65*I65),2)*BB65),2)+ROUND((ROUND(((AE65-(EU65))*AV65*I65),2)*BS65),2)) -> 0 | R65: =ROUND((ROUND((AE65*AV65*I65),2)*BS65),2) -> 0 | S65: =ROUND((ROUND((AF65*AV65*I65),2)*BA65),2) -> 0 | T65: =ROUND(CU65*I65,2) -> 0 | U65: =CV65*I65 -> 0 | V65: =CW65*I65 -> 0 | W65: =ROUND(CX65*I65,2) -> 0 | X65: =ROUND(CY65,2) -> 0 | Y65: =ROUND(CZ65,2) -> 0 | AA65: 56498968 | AB65: =ROUND((AC65+AD65+AF65),6) -> 77.23 | AC65: =ROUND((ES65),6) -> 77.23 | AD65: =ROUND((((ET65)-(EU65))+AE65),6) -> 0 | AE65: =ROUND((EU65),6) -> 0 | AF65: =ROUND((EV65),6) -> 0 | AG65: =ROUND((AP65),6) -> 0 | AH65: =(EW65) -> 0 | AI65: =(EX65) -> 0 | AJ65: =(AS65) -> 0 | AK65: 77.23 | AL65: 77.23 | AM65: 0 | AN65: 0 | AO65: 0 | AP65: 0 | AQ65: 0 | AR65: 0 | AS65: 0 | AT65: 0 | AU65: 0 | AV65: 1 | AW65: 1 | AZ65: 1 | BA65: 1 | BB65: 1 | BC65: 7.66 | BH65: 3 | BI65: 3 | BM65: 746 | BN65: 0 | BP65: 0 | BQ65: 130 | BR65: 0 | BS65: 1 | BT65: 1 | BU65: 1 | BV65: 1 | BW65: 1 | BX65: 1 | BZ65: 97 | CA65: 51 | CE65: 30 | CF65: 0 | CG65: 0 | CM65: 0 | CO65: 0 | CP65: =(P65+Q65+S65) -> 52650.78 | CQ65: =ROUND((ROUND((AC65*1),2)*BC65),2) -> 591.58 | CR65: =(ROUND((ROUND(((ET65)*AV65*1),2)*BB65),2)+ROUND((ROUND(((AE65-(EU65))*AV65*1),2)*BS65),2)) -> 0 | CS65: =ROUND((ROUND((AE65*AV65*1),2)*BS65),2) -> 0 | CT65: =ROUND((ROUND((AF65*AV65*1),2)*BA65),2) -> 0 | CU65: =AG65 -> 0 | CV65: =(AH65*AV65) -> 0 | CW65: =AI65 -> 0 | CX65: =AJ65 -> 0 | CY65: =(((S65+R65)*AT65)/100) -> 0 | CZ65: =(((S65+R65)*AU65)/100) -> 0 | DN65: 0 | DO65: 0 | DP65: 1 | DQ65: 1 | DU65: 1010 | DV65: шт. | DW65: шт. | DX65: 1 | EE65: 58162750 | EF65: 130 | EG65: Сметная стоимость оборудования | EH65: 0 | EJ65: 3 | EK65: 746 | EL65: ТСН-2001.13. Сметная стоимость оборудования | EM65: ТСН-2001.13 | EQ65: 0 | ER65: 77.23 | ES65: 77.23 | ET65: 0 | EU65: 0 | EV65: 0 | EW65: 0 | EX65: 0 | EZ65: 5 | FC65: 1 | FD65: 18 | FF65: 681 | FQ65: 0 | FR65: =P65 -> 52650.78 | FS65: 0 | FX65: 97 | FY65: 51 | GA65: [681 / 1,2 / 7,66] + 3% Трансп + 1,2% Заг.скл | GD65: 1 | GF65: -1365184430 | GG65: 2 | GH65: 3 | GI65: 5 | GJ65: 0 | GK65: 0 | GL65: =ROUND(IF(AND(BH65=3,BI65=3,FS65<>0),P65,0),2) -> 0 | GM65: =ROUND(O65+X65+Y65,2)+GX65 -> 52650.78 | GN65: =IF(OR(BI65=0,BI65=1),GM65-GX65,0) -> 0 | GO65: =IF(BI65=2,GM65-GX65,0) -> 0 | GP65: =IF(BI65=4,GM65-GX65,0) -> 0 | GR65: 1 | GS65: 1 | GT65: 0 | GV65: =ROUND((GT65),6) -> 0 | GW65: 1 | GX65: =ROUND(HC65*I65,2) -> 0 | HA65: 0 | HB65: 0 | HC65: =GV65*GW65 -> 0 | HE65: 3 | HF65: 1,2 | HS65: 0 | IK65: 0
A66: 17 | B66: 1 | D66: =ROW(EtalonRes!A45) -> 45 | E66: 10 | F66: 4.10-81-2 | G66: Извещатели ПС автоматические, дымовой, фотоэлектрический, радиоизотопный, световой в нормальном исполнении | H66: 1 ШТ. | I66: =ROUND(78+1+25,9) -> 104 | J66: 0 | K66: =ROUND(78+1+25,9) -> 104 | O66: =ROUND(CP66,2) -> 2677.5 | P66: =ROUND((ROUND((AC66*AW66*I66),2)*BC66),2) -> 131.04 | Q66: =(ROUND((ROUND((((ET66*1.1))*AV66*I66),2)*BB66),2)+ROUND((ROUND(((AE66-((EU66*1.1)))*AV66*I66),2)*BS66),2)) -> 7.19 | R66: =ROUND((ROUND((AE66*AV66*I66),2)*BS66),2) -> 1.2 | S66: =ROUND((ROUND((AF66*AV66*I66),2)*BA66),2) -> 2539.27 | T66: =ROUND(CU66*I66,2) -> 0 | U66: =CV66*I66 -> 201.22502 | V66: =CW66*I66 -> 0 | W66: =ROUND(CX66*I66,2) -> 0 | X66: =ROUND(CY66,2) -> 2286.42 | Y66: =ROUND(CZ66,2) -> 1168.62 | AA66: 56498966 | AB66: =ROUND((AC66+AD66+AF66),6) -> 24.646 | AC66: =ROUND((ES66),6) -> 1.26 | AD66: =ROUND(((((ET66*1.1))-((EU66*1.1)))+AE66),6) -> 0.066 | AE66: =ROUND(((EU66*1.1)),6) -> 0.011 | AF66: =ROUND(((EV66*1.1)),6) -> 23.32 | AG66: =ROUND((AP66),6) -> 0 | AH66: =((EW66*1.1)) -> 1.848 | AI66: =((EX66*1.1)) -> 0 | AJ66: =(AS66) -> 0 | AK66: 22.52 | AL66: 1.26 | AM66: 0.06 | AN66: 0.01 | AO66: 21.2 | AP66: 0 | AQ66: 1.68 | AR66: 0 | AS66: 0 | AT66: 90 | AU66: 46 | AV66: 1.047 | AW66: 1 | AZ66: 1 | BA66: 1 | BB66: 1 | BC66: 1 | BH66: 0 | BI66: 2 | BJ66: ТСН-2001.4. Доп. 1-42. Сб. 10, т. 81, поз. 2 | BM66: 68 | BN66: 0 | BO66: 4.10-81-2 | BP66: 1 | BQ66: 40 | BR66: 0 | BS66: 1 | BT66: 1 | BU66: 1 | BV66: 1 | BW66: 1 | BX66: 1 | BZ66: 90 | CA66: 46 | CE66: 30 | CF66: 0 | CG66: 0 | CM66: 0 | CO66: 0 | CP66: =(P66+Q66+S66) -> 2677.5 | CQ66: =ROUND((ROUND((AC66*AW66*1),2)*BC66),2) -> 1.26 | CR66: =(ROUND((ROUND((((ET66*1.1))*AV66*1),2)*BB66),2)+ROUND((ROUND(((AE66-((EU66*1.1)))*AV66*1),2)*BS66),2)) -> 0.07 | CS66: =ROUND((ROUND((AE66*AV66*1),2)*BS66),2) -> 0.01 | CT66: =ROUND((ROUND((AF66*AV66*1),2)*BA66),2) -> 24.42 | CU66: =AG66 -> 0 | CV66: =(AH66*AV66) -> 1.934856 | CW66: =AI66 -> 0 | CX66: =AJ66 -> 0 | CY66: =(((S66+R66)*AT66)/100) -> 2286.423 | CZ66: =(((S66+R66)*AU66)/100) -> 1168.6162 | DE66: *1,1 | DF66: *1,1 | DG66: *1,1 | DI66: *1,1 | DJ66: *1,1 | DN66: 0 | DO66: 0 | DP66: 1 | DQ66: 1 | DU66: 1013 | DV66: 1 ШТ. | DW66: 1 ШТ. | DX66: 1 | EE66: 58162630 | EF66: 40 | EG66: Монтаж оборудования | EH66: 0 | EJ66: 2 | EK66: 68 | EL66: ТСН-2001.4-10. Прокладка и монтаж сетей связи | EM66: ТСН-2001.4-10-1 | EO66: Поправка: Гл.12.Прил.8.п.8. 5_12.00.01.11.003 | EQ66: 0 | ER66: 22.52 | ES66: 1.26 | ET66: 0.06 | EU66: 0.01 | EV66: 21.2 | EW66: 1.68 | EX66: 0 | EY66: 0 | FQ66: 0 | FR66: 0 | FS66: 0 | FX66: 90 | FY66: 46 | GD66: 1 | GF66: -1912799884 | GG66: 2 | GH66: 1 | GI66: 2 | GJ66: 0 | GK66: 0 | GL66: =ROUND(IF(AND(BH66=3,BI66=3,FS66<>0),P66,0),2) -> 0 | GM66: =ROUND(O66+X66+Y66,2)+GX66 -> 6132.54 | GN66: =IF(OR(BI66=0,BI66=1),GM66-GX66,0) -> 0 | GO66: =IF(BI66=2,GM66-GX66,0) -> 6132.54 | GP66: =IF(BI66=4,GM66-GX66,0) -> 0 | GR66: 0 | GS66: 3 | GT66: 0 | GV66: =ROUND((GT66),6) -> 0 | GW66: 1 | GX66: =ROUND(HC66*I66,2) -> 0 | HA66: 0 | HB66: 0 | HC66: =GV66*GW66 -> 0 | HS66: 0 | IK66: 0
A67: 17 | B67: 1 | D67: =ROW(EtalonRes!A46) -> 46 | E67: 10 | F67: 4.10-81-2 | G67: Извещатели ПС автоматические, дымовой, фотоэлектрический, радиоизотопный, световой в нормальном исполнении | H67: 1 ШТ. | I67: =ROUND(78+1+25,9) -> 104 | J67: 0 | K67: =ROUND(78+1+25,9) -> 104 | O67: =ROUND(CP67,2) -> 141056.28 | P67: =ROUND((ROUND((AC67*AW67*I67),2)*BC67),2) -> 1295.99 | Q67: =(ROUND((ROUND((((ET67*1.1))*AV67*I67),2)*BB67),2)+ROUND((ROUND(((AE67-((EU67*1.1)))*AV67*I67),2)*BS67),2)) -> 125.83 | R67: =ROUND((ROUND((AE67*AV67*I67),2)*BS67),2) -> 65.99 | S67: =ROUND((ROUND((AF67*AV67*I67),2)*BA67),2) -> 139634.46 | T67: =ROUND(CU67*I67,2) -> 0 | U67: =CV67*I67 -> 201.22502 | V67: =CW67*I67 -> 0 | W67: =ROUND(CX67*I67,2) -> 0 | X67: =ROUND(CY67,2) -> 125730.41 | Y67: =ROUND(CZ67,2) -> 64262.21 | AA67: 56498968 | AB67: =ROUND((AC67+AD67+AF67),6) -> 24.646 | AC67: =ROUND((ES67),6) -> 1.26 | AD67: =ROUND(((((ET67*1.1))-((EU67*1.1)))+AE67),6) -> 0.066 | AE67: =ROUND(((EU67*1.1)),6) -> 0.011 | AF67: =ROUND(((EV67*1.1)),6) -> 23.32 | AG67: =ROUND((AP67),6) -> 0 | AH67: =((EW67*1.1)) -> 1.848 | AI67: =((EX67*1.1)) -> 0 | AJ67: =(AS67) -> 0 | AK67: 22.52 | AL67: 1.26 | AM67: 0.06 | AN67: 0.01 | AO67: 21.2 | AP67: 0 | AQ67: 1.68 | AR67: 0 | AS67: 0 | AT67: 90 | AU67: 46 | AV67: 1.047 | AW67: 1 | AZ67: 1 | BA67: 54.99 | BB67: 17.5 | BC67: 9.89 | BH67: 0 | BI67: 2 | BJ67: ТСН-2001.4. Доп. 1-42. Сб. 10, т. 81, поз. 2 | BM67: 68 | BN67: 0 | BO67: 4.10-81-2 | BP67: 1 | BQ67: 40 | BR67: 0 | BS67: 54.99 | BT67: 1 | BU67: 1 | BV67: 1 | BW67: 1 | BX67: 1 | BZ67: 90 | CA67: 46 | CE67: 30 | CF67: 0 | CG67: 0 | CM67: 0 | CO67: 0 | CP67: =(P67+Q67+S67) -> 141056.28 | CQ67: =ROUND((ROUND((AC67*AW67*1),2)*BC67),2) -> 12.46 | CR67: =(ROUND((ROUND((((ET67*1.1))*AV67*1),2)*BB67),2)+ROUND((ROUND(((AE67-((EU67*1.1)))*AV67*1),2)*BS67),2)) -> 1.23 | CS67: =ROUND((ROUND((AE67*AV67*1),2)*BS67),2) -> 0.55 | CT67: =ROUND((ROUND((AF67*AV67*1),2)*BA67),2) -> 1342.86 | CU67: =AG67 -> 0 | CV67: =(AH67*AV67) -> 1.934856 | CW67: =AI67 -> 0 | CX67: =AJ67 -> 0 | CY67: =(((S67+R67)*AT67)/100) -> 125730.4 | CZ67: =(((S67+R67)*AU67)/100) -> 64262.207 | DE67: *1,1 | DF67: *1,1 | DG67: *1,1 | DI67: *1,1 | DJ67: *1,1 | DN67: 0 | DO67: 0 | DP67: 1 | DQ67: 1 | DU67: 1013 | DV67: 1 ШТ. | DW67: 1 ШТ. | DX67: 1 | EE67: 58162630 | EF67: 40 | EG67: Монтаж оборудования | EH67: 0 | EJ67: 2 | EK67: 68 | EL67: ТСН-2001.4-10. Прокладка и монтаж сетей связи | EM67: ТСН-2001.4-10-1 | EO67: Поправка: Гл.12.Прил.8.п.8. 5_12.00.01.11.003 | EQ67: 0 | ER67: 22.52 | ES67: 1.26 | ET67: 0.06 | EU67: 0.01 | EV67: 21.2 | EW67: 1.68 | EX67: 0 | EY67: 0 | FQ67: 0 | FR67: 0 | FS67: 0 | FX67: 90 | FY67: 46 | GD67: 1 | GF67: -1912799884 | GG67: 2 | GH67: 1 | GI67: 2 | GJ67: 0 | GK67: 0 | GL67: =ROUND(IF(AND(BH67=3,BI67=3,FS67<>0),P67,0),2) -> 0 | GM67: =ROUND(O67+X67+Y67,2)+GX67 -> 331048.9 | GN67: =IF(OR(BI67=0,BI67=1),GM67-GX67,0) -> 0 | GO67: =IF(BI67=2,GM67-GX67,0) -> 331048.9 | GP67: =IF(BI67=4,GM67-GX67,0) -> 0 | GR67: 0 | GS67: 3 | GT67: 0 | GV67: =ROUND((GT67),6) -> 0 | GW67: 1 | GX67: =ROUND(HC67*I67,2) -> 0 | HA67: 0 | HB67: 0 | HC67: =GV67*GW67 -> 0 | HS67: 0 | IK67: 0
A68: 18 | B68: 1 | E68: 10,1 | F68: КА 11 | G68: Оповещатель охранно-пожарный световой адресный ОПОП 1-R3 "Выход" 337637 | H68: шт. | I68: =I66*J68 -> 78 | J68: 0.75 | K68: 0.75 | O68: =ROUND(CP68,2) -> 14266.98 | P68: =ROUND((ROUND((AC68*I68),2)*BC68),2) -> 14266.98 | Q68: =(ROUND((ROUND(((ET68)*AV68*I68),2)*BB68),2)+ROUND((ROUND(((AE68-(EU68))*AV68*I68),2)*BS68),2)) -> 0 | R68: =ROUND((ROUND((AE68*AV68*I68),2)*BS68),2) -> 0 | S68: =ROUND((ROUND((AF68*AV68*I68),2)*BA68),2) -> 0 | T68: =ROUND(CU68*I68,2) -> 0 | U68: =CV68*I68 -> 0 | V68: =CW68*I68 -> 0 | W68: =ROUND(CX68*I68,2) -> 0 | X68: =ROUND(CY68,2) -> 0 | Y68: =ROUND(CZ68,2) -> 0 | AA68: 56498966 | AB68: =ROUND((AC68+AD68+AF68),6) -> 182.91 | AC68: =ROUND((ES68),6) -> 182.91 | AD68: =ROUND((((ET68)-(EU68))+AE68),6) -> 0 | AE68: =ROUND((EU68),6) -> 0 | AF68: =ROUND((EV68),6) -> 0 | AG68: =ROUND((AP68),6) -> 0 | AH68: =(EW68) -> 0 | AI68: =(EX68) -> 0 | AJ68: =(AS68) -> 0 | AK68: 182.91 | AL68: 182.91 | AM68: 0 | AN68: 0 | AO68: 0 | AP68: 0 | AQ68: 0 | AR68: 0 | AS68: 0 | AT68: 0 | AU68: 0 | AV68: 1 | AW68: 1 | AZ68: 1 | BA68: 1 | BB68: 1 | BC68: 1 | BH68: 3 | BI68: 3 | BM68: 746 | BN68: 0 | BP68: 0 | BQ68: 130 | BR68: 0 | BS68: 1 | BT68: 1 | BU68: 1 | BV68: 1 | BW68: 1 | BX68: 1 | BZ68: 90 | CA68: 46 | CE68: 30 | CF68: 0 | CG68: 0 | CM68: 0 | CO68: 0 | CP68: =(P68+Q68+S68) -> 14266.98 | CQ68: =ROUND((ROUND((AC68*1),2)*BC68),2) -> 182.91 | CR68: =(ROUND((ROUND(((ET68)*AV68*1),2)*BB68),2)+ROUND((ROUND(((AE68-(EU68))*AV68*1),2)*BS68),2)) -> 0 | CS68: =ROUND((ROUND((AE68*AV68*1),2)*BS68),2) -> 0 | CT68: =ROUND((ROUND((AF68*AV68*1),2)*BA68),2) -> 0 | CU68: =AG68 -> 0 | CV68: =(AH68*AV68) -> 0 | CW68: =AI68 -> 0 | CX68: =AJ68 -> 0 | CY68: =(((S68+R68)*AT68)/100) -> 0 | CZ68: =(((S68+R68)*AU68)/100) -> 0 | DN68: 0 | DO68: 0 | DP68: 1 | DQ68: 1 | DU68: 1010 | DV68: шт. | DW68: шт. | DX68: 1 | EE68: 58162750 | EF68: 130 | EG68: Сметная стоимость оборудования | EH68: 0 | EJ68: 3 | EK68: 746 | EL68: ТСН-2001.13. Сметная стоимость оборудования | EM68: ТСН-2001.13 | EQ68: 0 | ER68: 0 | ES68: 182.91 | ET68: 0 | EU68: 0 | EV68: 0 | EW68: 0 | EX68: 0 | FQ68: 0 | FR68: =P68 -> 14266.98 | FS68: 0 | FX68: 90 | FY68: 46 | GA68: [1 613 / 1,2 / 7,66] + 3% Трансп + 1,2% Заг.скл | GD68: 1 | GF68: -212259153 | GG68: 2 | GH68: 4 | GI68: -2 | GJ68: 0 | GK68: 0 | GL68: =ROUND(IF(AND(BH68=3,BI68=3,FS68<>0),P68,0),2) -> 0 | GM68: =ROUND(O68+X68+Y68,2)+GX68 -> 14266.98 | GN68: =IF(OR(BI68=0,BI68=1),GM68-GX68,0) -> 0 | GO68: =IF(BI68=2,GM68-GX68,0) -> 0 | GP68: =IF(BI68=4,GM68-GX68,0) -> 0 | GR68: 0 | GS68: 2 | GT68: 0 | GV68: =ROUND((GT68),6) -> 0 | GW68: 1 | GX68: =ROUND(HC68*I68,2) -> 0 | HA68: 0 | HB68: 0 | HC68: =GV68*GW68 -> 0 | HE68: 3 | HF68: 1,2 | HS68: 0 | IK68: 0
A69: 18 | B69: 1 | E69: 10,1 | F69: КА 11 | G69: Оповещатель охранно-пожарный световой адресный ОПОП 1-R3 "Выход" 337637 | H69: шт. | I69: =I67*J69 -> 78 | J69: 0.75 | K69: 0.75 | O69: =ROUND(CP69,2) -> 109285.07 | P69: =ROUND((ROUND((AC69*I69),2)*BC69),2) -> 109285.07 | Q69: =(ROUND((ROUND(((ET69)*AV69*I69),2)*BB69),2)+ROUND((ROUND(((AE69-(EU69))*AV69*I69),2)*BS69),2)) -> 0 | R69: =ROUND((ROUND((AE69*AV69*I69),2)*BS69),2) -> 0 | S69: =ROUND((ROUND((AF69*AV69*I69),2)*BA69),2) -> 0 | T69: =ROUND(CU69*I69,2) -> 0 | U69: =CV69*I69 -> 0 | V69: =CW69*I69 -> 0 | W69: =ROUND(CX69*I69,2) -> 0 | X69: =ROUND(CY69,2) -> 0 | Y69: =ROUND(CZ69,2) -> 0 | AA69: 56498968 | AB69: =ROUND((AC69+AD69+AF69),6) -> 182.91 | AC69: =ROUND((ES69),6) -> 182.91 | AD69: =ROUND((((ET69)-(EU69))+AE69),6) -> 0 | AE69: =ROUND((EU69),6) -> 0 | AF69: =ROUND((EV69),6) -> 0 | AG69: =ROUND((AP69),6) -> 0 | AH69: =(EW69) -> 0 | AI69: =(EX69) -> 0 | AJ69: =(AS69) -> 0 | AK69: 182.91 | AL69: 182.91 | AM69: 0 | AN69: 0 | AO69: 0 | AP69: 0 | AQ69: 0 | AR69: 0 | AS69: 0 | AT69: 0 | AU69: 0 | AV69: 1 | AW69: 1 | AZ69: 1 | BA69: 1 | BB69: 1 | BC69: 7.66 | BH69: 3 | BI69: 3 | BM69: 746 | BN69: 0 | BP69: 0 | BQ69: 130 | BR69: 0 | BS69: 1 | BT69: 1 | BU69: 1 | BV69: 1 | BW69: 1 | BX69: 1 | BZ69: 90 | CA69: 46 | CE69: 30 | CF69: 0 | CG69: 0 | CM69: 0 | CO69: 0 | CP69: =(P69+Q69+S69) -> 109285.07 | CQ69: =ROUND((ROUND((AC69*1),2)*BC69),2) -> 1401.09 | CR69: =(ROUND((ROUND(((ET69)*AV69*1),2)*BB69),2)+ROUND((ROUND(((AE69-(EU69))*AV69*1),2)*BS69),2)) -> 0 | CS69: =ROUND((ROUND((AE69*AV69*1),2)*BS69),2) -> 0 | CT69: =ROUND((ROUND((AF69*AV69*1),2)*BA69),2) -> 0 | CU69: =AG69 -> 0 | CV69: =(AH69*AV69) -> 0 | CW69: =AI69 -> 0 | CX69: =AJ69 -> 0 | CY69: =(((S69+R69)*AT69)/100) -> 0 | CZ69: =(((S69+R69)*AU69)/100) -> 0 | DN69: 0 | DO69: 0 | DP69: 1 | DQ69: 1 | DU69: 1010 | DV69: шт. | DW69: шт. | DX69: 1 | EE69: 58162750 | EF69: 130 | EG69: Сметная стоимость оборудования | EH69: 0 | EJ69: 3 | EK69: 746 | EL69: ТСН-2001.13. Сметная стоимость оборудования | EM69: ТСН-2001.13 | EQ69: 0 | ER69: 182.91 | ES69: 182.91 | ET69: 0 | EU69: 0 | EV69: 0 | EW69: 0 | EX69: 0 | EZ69: 5 | FC69: 1 | FD69: 18 | FF69: 1613 | FQ69: 0 | FR69: =P69 -> 109285.07 | FS69: 0 | FX69: 90 | FY69: 46 | GA69: [1 613 / 1,2 / 7,66] + 3% Трансп + 1,2% Заг.скл | GD69: 1 | GF69: -212259153 | GG69: 2 | GH69: 3 | GI69: 5 | GJ69: 0 | GK69: 0 | GL69: =ROUND(IF(AND(BH69=3,BI69=3,FS69<>0),P69,0),2) -> 0 | GM69: =ROUND(O69+X69+Y69,2)+GX69 -> 109285.07 | GN69: =IF(OR(BI69=0,BI69=1),GM69-GX69,0) -> 0 | GO69: =IF(BI69=2,GM69-GX69,0) -> 0 | GP69: =IF(BI69=4,GM69-GX69,0) -> 0 | GR69: 1 | GS69: 1 | GT69: 0 | GV69: =ROUND((GT69),6) -> 0 | GW69: 1 | GX69: =ROUND(HC69*I69,2) -> 0 | HA69: 0 | HB69: 0 | HC69: =GV69*GW69 -> 0 | HE69: 3 | HF69: 1,2 | HS69: 0 | IK69: 0
A70: 18 | B70: 1 | E70: 10,2 | F70: КА 12 | G70: Оповещатель охранно-пожарный световой адресный ОПОП 1-R3 "Пожар" 338202 | H70: шт. | I70: =I66*J70 -> 1 | J70: 0.0096153846 | K70: 0.00961538 | O70: =ROUND(CP70,2) -> 157.29 | P70: =ROUND((ROUND((AC70*I70),2)*BC70),2) -> 157.29 | Q70: =(ROUND((ROUND(((ET70)*AV70*I70),2)*BB70),2)+ROUND((ROUND(((AE70-(EU70))*AV70*I70),2)*BS70),2)) -> 0 | R70: =ROUND((ROUND((AE70*AV70*I70),2)*BS70),2) -> 0 | S70: =ROUND((ROUND((AF70*AV70*I70),2)*BA70),2) -> 0 | T70: =ROUND(CU70*I70,2) -> 0 | U70: =CV70*I70 -> 0 | V70: =CW70*I70 -> 0 | W70: =ROUND(CX70*I70,2) -> 0 | X70: =ROUND(CY70,2) -> 0 | Y70: =ROUND(CZ70,2) -> 0 | AA70: 56498966 | AB70: =ROUND((AC70+AD70+AF70),6) -> 157.29 | AC70: =ROUND((ES70),6) -> 157.29 | AD70: =ROUND((((ET70)-(EU70))+AE70),6) -> 0 | AE70: =ROUND((EU70),6) -> 0 | AF70: =ROUND((EV70),6) -> 0 | AG70: =ROUND((AP70),6) -> 0 | AH70: =(EW70) -> 0 | AI70: =(EX70) -> 0 | AJ70: =(AS70) -> 0 | AK70: 157.29 | AL70: 157.29 | AM70: 0 | AN70: 0 | AO70: 0 | AP70: 0 | AQ70: 0 | AR70: 0 | AS70: 0 | AT70: 0 | AU70: 0 | AV70: 1 | AW70: 1 | AZ70: 1 | BA70: 1 | BB70: 1 | BC70: 1 | BH70: 3 | BI70: 3 | BM70: 746 | BN70: 0 | BP70: 0 | BQ70: 130 | BR70: 0 | BS70: 1 | BT70: 1 | BU70: 1 | BV70: 1 | BW70: 1 | BX70: 1 | BZ70: 90 | CA70: 46 | CE70: 30 | CF70: 0 | CG70: 0 | CM70: 0 | CO70: 0 | CP70: =(P70+Q70+S70) -> 157.29 | CQ70: =ROUND((ROUND((AC70*1),2)*BC70),2) -> 157.29 | CR70: =(ROUND((ROUND(((ET70)*AV70*1),2)*BB70),2)+ROUND((ROUND(((AE70-(EU70))*AV70*1),2)*BS70),2)) -> 0 | CS70: =ROUND((ROUND((AE70*AV70*1),2)*BS70),2) -> 0 | CT70: =ROUND((ROUND((AF70*AV70*1),2)*BA70),2) -> 0 | CU70: =AG70 -> 0 | CV70: =(AH70*AV70) -> 0 | CW70: =AI70 -> 0 | CX70: =AJ70 -> 0 | CY70: =(((S70+R70)*AT70)/100) -> 0 | CZ70: =(((S70+R70)*AU70)/100) -> 0 | DN70: 0 | DO70: 0 | DP70: 1 | DQ70: 1 | DU70: 1010 | DV70: шт. | DW70: шт. | DX70: 1 | EE70: 58162750 | EF70: 130 | EG70: Сметная стоимость оборудования | EH70: 0 | EJ70: 3 | EK70: 746 | EL70: ТСН-2001.13. Сметная стоимость оборудования | EM70: ТСН-2001.13 | EQ70: 0 | ER70: 0 | ES70: 157.29 | ET70: 0 | EU70: 0 | EV70: 0 | EW70: 0 | EX70: 0 | FQ70: 0 | FR70: =P70 -> 157.29 | FS70: 0 | FX70: 90 | FY70: 46 | GA70: [1 387 / 1,2 / 7,66] + 3% Трансп + 1,2% Заг.скл | GD70: 1 | GF70: 51725811 | GG70: 2 | GH70: 4 | GI70: -2 | GJ70: 0 | GK70: 0 | GL70: =ROUND(IF(AND(BH70=3,BI70=3,FS70<>0),P70,0),2) -> 0 | GM70: =ROUND(O70+X70+Y70,2)+GX70 -> 157.29 | GN70: =IF(OR(BI70=0,BI70=1),GM70-GX70,0) -> 0 | GO70: =IF(BI70=2,GM70-GX70,0) -> 0 | GP70: =IF(BI70=4,GM70-GX70,0) -> 0 | GR70: 0 | GS70: 2 | GT70: 0 | GV70: =ROUND((GT70),6) -> 0 | GW70: 1 | GX70: =ROUND(HC70*I70,2) -> 0 | HA70: 0 | HB70: 0 | HC70: =GV70*GW70 -> 0 | HE70: 3 | HF70: 1,2 | HS70: 0 | IK70: 0
A71: 18 | B71: 1 | E71: 10,2 | F71: КА 12 | G71: Оповещатель охранно-пожарный световой адресный ОПОП 1-R3 "Пожар" 338202 | H71: шт. | I71: =I67*J71 -> 1 | J71: 0.0096153846 | K71: 0.00961538 | O71: =ROUND(CP71,2) -> 1204.84 | P71: =ROUND((ROUND((AC71*I71),2)*BC71),2) -> 1204.84 | Q71: =(ROUND((ROUND(((ET71)*AV71*I71),2)*BB71),2)+ROUND((ROUND(((AE71-(EU71))*AV71*I71),2)*BS71),2)) -> 0 | R71: =ROUND((ROUND((AE71*AV71*I71),2)*BS71),2) -> 0 | S71: =ROUND((ROUND((AF71*AV71*I71),2)*BA71),2) -> 0 | T71: =ROUND(CU71*I71,2) -> 0 | U71: =CV71*I71 -> 0 | V71: =CW71*I71 -> 0 | W71: =ROUND(CX71*I71,2) -> 0 | X71: =ROUND(CY71,2) -> 0 | Y71: =ROUND(CZ71,2) -> 0 | AA71: 56498968 | AB71: =ROUND((AC71+AD71+AF71),6) -> 157.29 | AC71: =ROUND((ES71),6) -> 157.29 | AD71: =ROUND((((ET71)-(EU71))+AE71),6) -> 0 | AE71: =ROUND((EU71),6) -> 0 | AF71: =ROUND((EV71),6) -> 0 | AG71: =ROUND((AP71),6) -> 0 | AH71: =(EW71) -> 0 | AI71: =(EX71) -> 0 | AJ71: =(AS71) -> 0 | AK71: 157.29 | AL71: 157.29 | AM71: 0 | AN71: 0 | AO71: 0 | AP71: 0 | AQ71: 0 | AR71: 0 | AS71: 0 | AT71: 0 | AU71: 0 | AV71: 1 | AW71: 1 | AZ71: 1 | BA71: 1 | BB71: 1 | BC71: 7.66 | BH71: 3 | BI71: 3 | BM71: 746 | BN71: 0 | BP71: 0 | BQ71: 130 | BR71: 0 | BS71: 1 | BT71: 1 | BU71: 1 | BV71: 1 | BW71: 1 | BX71: 1 | BZ71: 90 | CA71: 46 | CE71: 30 | CF71: 0 | CG71: 0 | CM71: 0 | CO71: 0 | CP71: =(P71+Q71+S71) -> 1204.84 | CQ71: =ROUND((ROUND((AC71*1),2)*BC71),2) -> 1204.84 | CR71: =(ROUND((ROUND(((ET71)*AV71*1),2)*BB71),2)+ROUND((ROUND(((AE71-(EU71))*AV71*1),2)*BS71),2)) -> 0 | CS71: =ROUND((ROUND((AE71*AV71*1),2)*BS71),2) -> 0 | CT71: =ROUND((ROUND((AF71*AV71*1),2)*BA71),2) -> 0 | CU71: =AG71 -> 0 | CV71: =(AH71*AV71) -> 0 | CW71: =AI71 -> 0 | CX71: =AJ71 -> 0 | CY71: =(((S71+R71)*AT71)/100) -> 0 | CZ71: =(((S71+R71)*AU71)/100) -> 0 | DN71: 0 | DO71: 0 | DP71: 1 | DQ71: 1 | DU71: 1010 | DV71: шт. | DW71: шт. | DX71: 1 | EE71: 58162750 | EF71: 130 | EG71: Сметная стоимость оборудования | EH71: 0 | EJ71: 3 | EK71: 746 | EL71: ТСН-2001.13. Сметная стоимость оборудования | EM71: ТСН-2001.13 | EQ71: 0 | ER71: 157.29 | ES71: 157.29 | ET71: 0 | EU71: 0 | EV71: 0 | EW71: 0 | EX71: 0 | EZ71: 5 | FC71: 1 | FD71: 18 | FF71: 1387 | FQ71: 0 | FR71: =P71 -> 1204.84 | FS71: 0 | FX71: 90 | FY71: 46 | GA71: [1 387 / 1,2 / 7,66] + 3% Трансп + 1,2% Заг.скл | GD71: 1 | GF71: 51725811 | GG71: 2 | GH71: 3 | GI71: 5 | GJ71: 0 | GK71: 0 | GL71: =ROUND(IF(AND(BH71=3,BI71=3,FS71<>0),P71,0),2) -> 0 | GM71: =ROUND(O71+X71+Y71,2)+GX71 -> 1204.84 | GN71: =IF(OR(BI71=0,BI71=1),GM71-GX71,0) -> 0 | GO71: =IF(BI71=2,GM71-GX71,0) -> 0 | GP71: =IF(BI71=4,GM71-GX71,0) -> 0 | GR71: 1 | GS71: 1 | GT71: 0 | GV71: =ROUND((GT71),6) -> 0 | GW71: 1 | GX71: =ROUND(HC71*I71,2) -> 0 | HA71: 0 | HB71: 0 | HC71: =GV71*GW71 -> 0 | HE71: 3 | HF71: 1,2 | HS71: 0 | IK71: 0
A72: 18 | B72: 1 | E72: 10,3 | F72: КА 13 | G72: Оповещатель охранно-пожарный световой ОПОП 1-R3 Стрелка | H72: шт. | I72: =I66*J72 -> 25 | J72: 0.24038462 | K72: 0.24038462 | O72: =ROUND(CP72,2) -> 4572.75 | P72: =ROUND((ROUND((AC72*I72),2)*BC72),2) -> 4572.75 | Q72: =(ROUND((ROUND(((ET72)*AV72*I72),2)*BB72),2)+ROUND((ROUND(((AE72-(EU72))*AV72*I72),2)*BS72),2)) -> 0 | R72: =ROUND((ROUND((AE72*AV72*I72),2)*BS72),2) -> 0 | S72: =ROUND((ROUND((AF72*AV72*I72),2)*BA72),2) -> 0 | T72: =ROUND(CU72*I72,2) -> 0 | U72: =CV72*I72 -> 0 | V72: =CW72*I72 -> 0 | W72: =ROUND(CX72*I72,2) -> 0 | X72: =ROUND(CY72,2) -> 0 | Y72: =ROUND(CZ72,2) -> 0 | AA72: 56498966 | AB72: =ROUND((AC72+AD72+AF72),6) -> 182.91 | AC72: =ROUND((ES72),6) -> 182.91 | AD72: =ROUND((((ET72)-(EU72))+AE72),6) -> 0 | AE72: =ROUND((EU72),6) -> 0 | AF72: =ROUND((EV72),6) -> 0 | AG72: =ROUND((AP72),6) -> 0 | AH72: =(EW72) -> 0 | AI72: =(EX72) -> 0 | AJ72: =(AS72) -> 0 | AK72: 182.91 | AL72: 182.91 | AM72: 0 | AN72: 0 | AO72: 0 | AP72: 0 | AQ72: 0 | AR72: 0 | AS72: 0 | AT72: 0 | AU72: 0 | AV72: 1 | AW72: 1 | AZ72: 1 | BA72: 1 | BB72: 1 | BC72: 1 | BH72: 3 | BI72: 3 | BM72: 746 | BN72: 0 | BP72: 0 | BQ72: 130 | BR72: 0 | BS72: 1 | BT72: 1 | BU72: 1 | BV72: 1 | BW72: 1 | BX72: 1 | BZ72: 90 | CA72: 46 | CE72: 30 | CF72: 0 | CG72: 0 | CM72: 0 | CO72: 0 | CP72: =(P72+Q72+S72) -> 4572.75 | CQ72: =ROUND((ROUND((AC72*1),2)*BC72),2) -> 182.91 | CR72: =(ROUND((ROUND(((ET72)*AV72*1),2)*BB72),2)+ROUND((ROUND(((AE72-(EU72))*AV72*1),2)*BS72),2)) -> 0 | CS72: =ROUND((ROUND((AE72*AV72*1),2)*BS72),2) -> 0 | CT72: =ROUND((ROUND((AF72*AV72*1),2)*BA72),2) -> 0 | CU72: =AG72 -> 0 | CV72: =(AH72*AV72) -> 0 | CW72: =AI72 -> 0 | CX72: =AJ72 -> 0 | CY72: =(((S72+R72)*AT72)/100) -> 0 | CZ72: =(((S72+R72)*AU72)/100) -> 0 | DN72: 0 | DO72: 0 | DP72: 1 | DQ72: 1 | DU72: 1010 | DV72: шт. | DW72: шт. | DX72: 1 | EE72: 58162750 | EF72: 130 | EG72: Сметная стоимость оборудования | EH72: 0 | EJ72: 3 | EK72: 746 | EL72: ТСН-2001.13. Сметная стоимость оборудования | EM72: ТСН-2001.13 | EQ72: 0 | ER72: 0 | ES72: 182.91 | ET72: 0 | EU72: 0 | EV72: 0 | EW72: 0 | EX72: 0 | FQ72: 0 | FR72: =P72 -> 4572.75 | FS72: 0 | FX72: 90 | FY72: 46 | GA72: [1 613 / 1,2 / 7,66] + 3% Трансп + 1,2% Заг.скл | GD72: 1 | GF72: -1412008601 | GG72: 2 | GH72: 4 | GI72: -2 | GJ72: 0 | GK72: 0 | GL72: =ROUND(IF(AND(BH72=3,BI72=3,FS72<>0),P72,0),2) -> 0 | GM72: =ROUND(O72+X72+Y72,2)+GX72 -> 4572.75 | GN72: =IF(OR(BI72=0,BI72=1),GM72-GX72,0) -> 0 | GO72: =IF(BI72=2,GM72-GX72,0) -> 0 | GP72: =IF(BI72=4,GM72-GX72,0) -> 0 | GR72: 0 | GS72: 2 | GT72: 0 | GV72: =ROUND((GT72),6) -> 0 | GW72: 1 | GX72: =ROUND(HC72*I72,2) -> 0 | HA72: 0 | HB72: 0 | HC72: =GV72*GW72 -> 0 | HE72: 3 | HF72: 1,2 | HS72: 0 | IK72: 0
A73: 18 | B73: 1 | E73: 10,3 | F73: КА 13 | G73: Оповещатель охранно-пожарный световой ОПОП 1-R3 Стрелка | H73: шт. | I73: =I67*J73 -> 25 | J73: 0.24038462 | K73: 0.24038462 | O73: =ROUND(CP73,2) -> 35027.27 | P73: =ROUND((ROUND((AC73*I73),2)*BC73),2) -> 35027.27 | Q73: =(ROUND((ROUND(((ET73)*AV73*I73),2)*BB73),2)+ROUND((ROUND(((AE73-(EU73))*AV73*I73),2)*BS73),2)) -> 0 | R73: =ROUND((ROUND((AE73*AV73*I73),2)*BS73),2) -> 0 | S73: =ROUND((ROUND((AF73*AV73*I73),2)*BA73),2) -> 0 | T73: =ROUND(CU73*I73,2) -> 0 | U73: =CV73*I73 -> 0 | V73: =CW73*I73 -> 0 | W73: =ROUND(CX73*I73,2) -> 0 | X73: =ROUND(CY73,2) -> 0 | Y73: =ROUND(CZ73,2) -> 0 | AA73: 56498968 | AB73: =ROUND((AC73+AD73+AF73),6) -> 182.91 | AC73: =ROUND((ES73),6) -> 182.91 | AD73: =ROUND((((ET73)-(EU73))+AE73),6) -> 0 | AE73: =ROUND((EU73),6) -> 0 | AF73: =ROUND((EV73),6) -> 0 | AG73: =ROUND((AP73),6) -> 0 | AH73: =(EW73) -> 0 | AI73: =(EX73) -> 0 | AJ73: =(AS73) -> 0 | AK73: 182.91 | AL73: 182.91 | AM73: 0 | AN73: 0 | AO73: 0 | AP73: 0 | AQ73: 0 | AR73: 0 | AS73: 0 | AT73: 0 | AU73: 0 | AV73: 1 | AW73: 1 | AZ73: 1 | BA73: 1 | BB73: 1 | BC73: 7.66 | BH73: 3 | BI73: 3 | BM73: 746 | BN73: 0 | BP73: 0 | BQ73: 130 | BR73: 0 | BS73: 1 | BT73: 1 | BU73: 1 | BV73: 1 | BW73: 1 | BX73: 1 | BZ73: 90 | CA73: 46 | CE73: 30 | CF73: 0 | CG73: 0 | CM73: 0 | CO73: 0 | CP73: =(P73+Q73+S73) -> 35027.27 | CQ73: =ROUND((ROUND((AC73*1),2)*BC73),2) -> 1401.09 | CR73: =(ROUND((ROUND(((ET73)*AV73*1),2)*BB73),2)+ROUND((ROUND(((AE73-(EU73))*AV73*1),2)*BS73),2)) -> 0 | CS73: =ROUND((ROUND((AE73*AV73*1),2)*BS73),2) -> 0 | CT73: =ROUND((ROUND((AF73*AV73*1),2)*BA73),2) -> 0 | CU73: =AG73 -> 0 | CV73: =(AH73*AV73) -> 0 | CW73: =AI73 -> 0 | CX73: =AJ73 -> 0 | CY73: =(((S73+R73)*AT73)/100) -> 0 | CZ73: =(((S73+R73)*AU73)/100) -> 0 | DN73: 0 | DO73: 0 | DP73: 1 | DQ73: 1 | DU73: 1010 | DV73: шт. | DW73: шт. | DX73: 1 | EE73: 58162750 | EF73: 130 | EG73: Сметная стоимость оборудования | EH73: 0 | EJ73: 3 | EK73: 746 | EL73: ТСН-2001.13. Сметная стоимость оборудования | EM73: ТСН-2001.13 | EQ73: 0 | ER73: 182.91 | ES73: 182.91 | ET73: 0 | EU73: 0 | EV73: 0 | EW73: 0 | EX73: 0 | EZ73: 5 | FC73: 1 | FD73: 18 | FF73: 1613 | FQ73: 0 | FR73: =P73 -> 35027.27 | FS73: 0 | FX73: 90 | FY73: 46 | GA73: [1 613 / 1,2 / 7,66] + 3% Трансп + 1,2% Заг.скл | GD73: 1 | GF73: -1412008601 | GG73: 2 | GH73: 3 | GI73: 5 | GJ73: 0 | GK73: 0 | GL73: =ROUND(IF(AND(BH73=3,BI73=3,FS73<>0),P73,0),2) -> 0 | GM73: =ROUND(O73+X73+Y73,2)+GX73 -> 35027.27 | GN73: =IF(OR(BI73=0,BI73=1),GM73-GX73,0) -> 0 | GO73: =IF(BI73=2,GM73-GX73,0) -> 0 | GP73: =IF(BI73=4,GM73-GX73,0) -> 0 | GR73: 1 | GS73: 1 | GT73: 0 | GV73: =ROUND((GT73),6) -> 0 | GW73: 1 | GX73: =ROUND(HC73*I73,2) -> 0 | HA73: 0 | HB73: 0 | HC73: =GV73*GW73 -> 0 | HE73: 3 | HF73: 1,2 | HS73: 0 | IK73: 0
A74: 17 | B74: 1 | D74: =ROW(EtalonRes!A51) -> 51 | E74: 11 | F74: 4.10-173-2 | G74: Монтаж блока бесперебойного питания (ББП) в диспетчерской | H74: 1 ШТ. | I74: =ROUND(2+1+4,9) -> 7 | J74: 0 | K74: =ROUND(2+1+4,9) -> 7 | O74: =ROUND(CP74,2) -> 340.23 | P74: =ROUND((ROUND((AC74*AW74*I74),2)*BC74),2) -> 16.38 | Q74: =(ROUND((ROUND((((ET74*1.1))*AV74*I74),2)*BB74),2)+ROUND((ROUND(((AE74-((EU74*1.1)))*AV74*I74),2)*BS74),2)) -> 0 | R74: =ROUND((ROUND((AE74*AV74*I74),2)*BS74),2) -> 0 | S74: =ROUND((ROUND((AF74*AV74*I74),2)*BA74),2) -> 323.85 | T74: =ROUND(CU74*I74,2) -> 0 | U74: =CV74*I74 -> 25.636842 | V74: =CW74*I74 -> 0 | W74: =ROUND(CX74*I74,2) -> 0 | X74: =ROUND(CY74,2) -> 291.47 | Y74: =ROUND(CZ74,2) -> 148.97 | AA74: 56498966 | AB74: =ROUND((AC74+AD74+AF74),6) -> 46.527 | AC74: =ROUND((ES74),6) -> 2.34 | AD74: =ROUND(((((ET74*1.1))-((EU74*1.1)))+AE74),6) -> 0 | AE74: =ROUND(((EU74*1.1)),6) -> 0 | AF74: =ROUND(((EV74*1.1)),6) -> 44.187 | AG74: =ROUND((AP74),6) -> 0 | AH74: =((EW74*1.1)) -> 3.498 | AI74: =((EX74*1.1)) -> 0 | AJ74: =(AS74) -> 0 | AK74: 42.51 | AL74: 2.34 | AM74: 0 | AN74: 0 | AO74: 40.17 | AP74: 0 | AQ74: 3.18 | AR74: 0 | AS74: 0 | AT74: 90 | AU74: 46 | AV74: 1.047 | AW74: 1 | AZ74: 1 | BA74: 1 | BB74: 1 | BC74: 1 | BH74: 0 | BI74: 2 | BJ74: ТСН-2001.4 Доп. 67, Сб. 10, т. 173, поз. 2 | BM74: 68 | BN74: 0 | BO74: 4.10-173-2 | BP74: 1 | BQ74: 40 | BR74: 0 | BS74: 1 | BT74: 1 | BU74: 1 | BV74: 1 | BW74: 1 | BX74: 1 | BZ74: 90 | CA74: 46 | CE74: 30 | CF74: 0 | CG74: 0 | CM74: 0 | CO74: 0 | CP74: =(P74+Q74+S74) -> 340.23 | CQ74: =ROUND((ROUND((AC74*AW74*1),2)*BC74),2) -> 2.34 | CR74: =(ROUND((ROUND((((ET74*1.1))*AV74*1),2)*BB74),2)+ROUND((ROUND(((AE74-((EU74*1.1)))*AV74*1),2)*BS74),2)) -> 0 | CS74: =ROUND((ROUND((AE74*AV74*1),2)*BS74),2) -> 0 | CT74: =ROUND((ROUND((AF74*AV74*1),2)*BA74),2) -> 46.26 | CU74: =AG74 -> 0 | CV74: =(AH74*AV74) -> 3.662406 | CW74: =AI74 -> 0 | CX74: =AJ74 -> 0 | CY74: =(((S74+R74)*AT74)/100) -> 291.465 | CZ74: =(((S74+R74)*AU74)/100) -> 148.971 | DE74: *1,1 | DF74: *1,1 | DG74: *1,1 | DI74: *1,1 | DJ74: *1,1 | DN74: 0 | DO74: 0 | DP74: 1 | DQ74: 1 | DU74: 1013 | DV74: 1 ШТ. | DW74: 1 ШТ. | DX74: 1 | EE74: 58162630 | EF74: 40 | EG74: Монтаж оборудования | EH74: 0 | EJ74: 2 | EK74: 68 | EL74: ТСН-2001.4-10. Прокладка и монтаж сетей связи | EM74: ТСН-2001.4-10-1 | EO74: Поправка: Гл.12.Прил.8.п.8. 5_12.00.01.11.003 | EQ74: 0 | ER74: 42.51 | ES74: 2.34 | ET74: 0 | EU74: 0 | EV74: 40.17 | EW74: 3.18 | EX74: 0 | EY74: 0 | FQ74: 0 | FR74: 0 | FS74: 0 | FX74: 90 | FY74: 46 | GD74: 1 | GF74: 1548884140 | GG74: 2 | GH74: 1 | GI74: 2 | GJ74: 0 | GK74: 0 | GL74: =ROUND(IF(AND(BH74=3,BI74=3,FS74<>0),P74,0),2) -> 0 | GM74: =ROUND(O74+X74+Y74,2)+GX74 -> 780.67 | GN74: =IF(OR(BI74=0,BI74=1),GM74-GX74,0) -> 0 | GO74: =IF(BI74=2,GM74-GX74,0) -> 780.67 | GP74: =IF(BI74=4,GM74-GX74,0) -> 0 | GR74: 0 | GS74: 3 | GT74: 0 | GV74: =ROUND((GT74),6) -> 0 | GW74: 1 | GX74: =ROUND(HC74*I74,2) -> 0 | HA74: 0 | HB74: 0 | HC74: =GV74*GW74 -> 0 | HS74: 0 | IK74: 0
A75: 17 | B75: 1 | D75: =ROW(EtalonRes!A56) -> 56 | E75: 11 | F75: 4.10-173-2 | G75: Монтаж блока бесперебойного питания (ББП) в диспетчерской | H75: 1 ШТ. | I75: =ROUND(2+1+4,9) -> 7 | J75: 0 | K75: =ROUND(2+1+4,9) -> 7 | O75: =ROUND(CP75,2) -> 17976.57 | P75: =ROUND((ROUND((AC75*AW75*I75),2)*BC75),2) -> 168.06 | Q75: =(ROUND((ROUND((((ET75*1.1))*AV75*I75),2)*BB75),2)+ROUND((ROUND(((AE75-((EU75*1.1)))*AV75*I75),2)*BS75),2)) -> 0 | R75: =ROUND((ROUND((AE75*AV75*I75),2)*BS75),2) -> 0 | S75: =ROUND((ROUND((AF75*AV75*I75),2)*BA75),2) -> 17808.51 | T75: =ROUND(CU75*I75,2) -> 0 | U75: =CV75*I75 -> 25.636842 | V75: =CW75*I75 -> 0 | W75: =ROUND(CX75*I75,2) -> 0 | X75: =ROUND(CY75,2) -> 16027.66 | Y75: =ROUND(CZ75,2) -> 8191.91 | AA75: 56498968 | AB75: =ROUND((AC75+AD75+AF75),6) -> 46.527 | AC75: =ROUND((ES75),6) -> 2.34 | AD75: =ROUND(((((ET75*1.1))-((EU75*1.1)))+AE75),6) -> 0 | AE75: =ROUND(((EU75*1.1)),6) -> 0 | AF75: =ROUND(((EV75*1.1)),6) -> 44.187 | AG75: =ROUND((AP75),6) -> 0 | AH75: =((EW75*1.1)) -> 3.498 | AI75: =((EX75*1.1)) -> 0 | AJ75: =(AS75) -> 0 | AK75: 42.51 | AL75: 2.34 | AM75: 0 | AN75: 0 | AO75: 40.17 | AP75: 0 | AQ75: 3.18 | AR75: 0 | AS75: 0 | AT75: 90 | AU75: 46 | AV75: 1.047 | AW75: 1 | AZ75: 1 | BA75: 54.99 | BB75: 1 | BC75: 10.26 | BH75: 0 | BI75: 2 | BJ75: ТСН-2001.4 Доп. 67, Сб. 10, т. 173, поз. 2 | BM75: 68 | BN75: 0 | BO75: 4.10-173-2 | BP75: 1 | BQ75: 40 | BR75: 0 | BS75: 54.99 | BT75: 1 | BU75: 1 | BV75: 1 | BW75: 1 | BX75: 1 | BZ75: 90 | CA75: 46 | CE75: 30 | CF75: 0 | CG75: 0 | CM75: 0 | CO75: 0 | CP75: =(P75+Q75+S75) -> 17976.57 | CQ75: =ROUND((ROUND((AC75*AW75*1),2)*BC75),2) -> 24.01 | CR75: =(ROUND((ROUND((((ET75*1.1))*AV75*1),2)*BB75),2)+ROUND((ROUND(((AE75-((EU75*1.1)))*AV75*1),2)*BS75),2)) -> 0 | CS75: =ROUND((ROUND((AE75*AV75*1),2)*BS75),2) -> 0 | CT75: =ROUND((ROUND((AF75*AV75*1),2)*BA75),2) -> 2543.84 | CU75: =AG75 -> 0 | CV75: =(AH75*AV75) -> 3.662406 | CW75: =AI75 -> 0 | CX75: =AJ75 -> 0 | CY75: =(((S75+R75)*AT75)/100) -> 16027.659 | CZ75: =(((S75+R75)*AU75)/100) -> 8191.9146 | DE75: *1,1 | DF75: *1,1 | DG75: *1,1 | DI75: *1,1 | DJ75: *1,1 | DN75: 0 | DO75: 0 | DP75: 1 | DQ75: 1 | DU75: 1013 | DV75: 1 ШТ. | DW75: 1 ШТ. | DX75: 1 | EE75: 58162630 | EF75: 40 | EG75: Монтаж оборудования | EH75: 0 | EJ75: 2 | EK75: 68 | EL75: ТСН-2001.4-10. Прокладка и монтаж сетей связи | EM75: ТСН-2001.4-10-1 | EO75: Поправка: Гл.12.Прил.8.п.8. 5_12.00.01.11.003 | EQ75: 0 | ER75: 42.51 | ES75: 2.34 | ET75: 0 | EU75: 0 | EV75: 40.17 | EW75: 3.18 | EX75: 0 | EY75: 0 | FQ75: 0 | FR75: 0 | FS75: 0 | FX75: 90 | FY75: 46 | GD75: 1 | GF75: 1548884140 | GG75: 2 | GH75: 1 | GI75: 2 | GJ75: 0 | GK75: 0 | GL75: =ROUND(IF(AND(BH75=3,BI75=3,FS75<>0),P75,0),2) -> 0 | GM75: =ROUND(O75+X75+Y75,2)+GX75 -> 42196.14 | GN75: =IF(OR(BI75=0,BI75=1),GM75-GX75,0) -> 0 | GO75: =IF(BI75=2,GM75-GX75,0) -> 42196.14 | GP75: =IF(BI75=4,GM75-GX75,0) -> 0 | GR75: 0 | GS75: 3 | GT75: 0 | GV75: =ROUND((GT75),6) -> 0 | GW75: 1 | GX75: =ROUND(HC75*I75,2) -> 0 | HA75: 0 | HB75: 0 | HC75: =GV75*GW75 -> 0 | HS75: 0 | IK75: 0
A76: 18 | B76: 1 | E76: 11,1 | F76: КА 14 | G76: Источник вторичного электропитания резервированный адресный ИВЭПР 12/2 RS-R3 2х17 БР-R3 | H76: шт. | I76: =I74*J76 -> 2 | J76: 0.28571429 | K76: 0.2857143 | O76: =ROUND(CP76,2) -> 1883.78 | P76: =ROUND((ROUND((AC76*I76),2)*BC76),2) -> 1883.78 | Q76: =(ROUND((ROUND(((ET76)*AV76*I76),2)*BB76),2)+ROUND((ROUND(((AE76-(EU76))*AV76*I76),2)*BS76),2)) -> 0 | R76: =ROUND((ROUND((AE76*AV76*I76),2)*BS76),2) -> 0 | S76: =ROUND((ROUND((AF76*AV76*I76),2)*BA76),2) -> 0 | T76: =ROUND(CU76*I76,2) -> 0 | U76: =CV76*I76 -> 0 | V76: =CW76*I76 -> 0 | W76: =ROUND(CX76*I76,2) -> 0 | X76: =ROUND(CY76,2) -> 0 | Y76: =ROUND(CZ76,2) -> 0 | AA76: 56498966 | AB76: =ROUND((AC76+AD76+AF76),6) -> 941.89 | AC76: =ROUND((ES76),6) -> 941.89 | AD76: =ROUND((((ET76)-(EU76))+AE76),6) -> 0 | AE76: =ROUND((EU76),6) -> 0 | AF76: =ROUND((EV76),6) -> 0 | AG76: =ROUND((AP76),6) -> 0 | AH76: =(EW76) -> 0 | AI76: =(EX76) -> 0 | AJ76: =(AS76) -> 0 | AK76: 941.89 | AL76: 941.89 | AM76: 0 | AN76: 0 | AO76: 0 | AP76: 0 | AQ76: 0 | AR76: 0 | AS76: 0 | AT76: 0 | AU76: 0 | AV76: 1 | AW76: 1 | AZ76: 1 | BA76: 1 | BB76: 1 | BC76: 1 | BH76: 3 | BI76: 3 | BM76: 746 | BN76: 0 | BP76: 0 | BQ76: 130 | BR76: 0 | BS76: 1 | BT76: 1 | BU76: 1 | BV76: 1 | BW76: 1 | BX76: 1 | BZ76: 90 | CA76: 46 | CE76: 30 | CF76: 0 | CG76: 0 | CM76: 0 | CO76: 0 | CP76: =(P76+Q76+S76) -> 1883.78 | CQ76: =ROUND((ROUND((AC76*1),2)*BC76),2) -> 941.89 | CR76: =(ROUND((ROUND(((ET76)*AV76*1),2)*BB76),2)+ROUND((ROUND(((AE76-(EU76))*AV76*1),2)*BS76),2)) -> 0 | CS76: =ROUND((ROUND((AE76*AV76*1),2)*BS76),2) -> 0 | CT76: =ROUND((ROUND((AF76*AV76*1),2)*BA76),2) -> 0 | CU76: =AG76 -> 0 | CV76: =(AH76*AV76) -> 0 | CW76: =AI76 -> 0 | CX76: =AJ76 -> 0 | CY76: =(((S76+R76)*AT76)/100) -> 0 | CZ76: =(((S76+R76)*AU76)/100) -> 0 | DN76: 0 | DO76: 0 | DP76: 1 | DQ76: 1 | DU76: 1010 | DV76: шт. | DW76: шт. | DX76: 1 | EE76: 58162750 | EF76: 130 | EG76: Сметная стоимость оборудования | EH76: 0 | EJ76: 3 | EK76: 746 | EL76: ТСН-2001.13. Сметная стоимость оборудования | EM76: ТСН-2001.13 | EQ76: 0 | ER76: 0 | ES76: 941.89 | ET76: 0 | EU76: 0 | EV76: 0 | EW76: 0 | EX76: 0 | FQ76: 0 | FR76: =P76 -> 1883.78 | FS76: 0 | FX76: 90 | FY76: 46 | GA76: [8 306 / 1,2 / 7,66] + 3% Трансп + 1,2% Заг.скл | GD76: 1 | GF76: -99932320 | GG76: 2 | GH76: 4 | GI76: -2 | GJ76: 0 | GK76: 0 | GL76: =ROUND(IF(AND(BH76=3,BI76=3,FS76<>0),P76,0),2) -> 0 | GM76: =ROUND(O76+X76+Y76,2)+GX76 -> 1883.78 | GN76: =IF(OR(BI76=0,BI76=1),GM76-GX76,0) -> 0 | GO76: =IF(BI76=2,GM76-GX76,0) -> 0 | GP76: =IF(BI76=4,GM76-GX76,0) -> 0 | GR76: 0 | GS76: 2 | GT76: 0 | GV76: =ROUND((GT76),6) -> 0 | GW76: 1 | GX76: =ROUND(HC76*I76,2) -> 0 | HA76: 0 | HB76: 0 | HC76: =GV76*GW76 -> 0 | HE76: 3 | HF76: 1,2 | HS76: 0 | IK76: 0
A77: 18 | B77: 1 | E77: 11,1 | F77: КА 14 | G77: Источник вторичного электропитания резервированный адресный ИВЭПР 12/2 RS-R3 2х17 БР-R3 | H77: шт. | I77: =I75*J77 -> 2 | J77: 0.28571429 | K77: 0.2857143 | O77: =ROUND(CP77,2) -> 14429.75 | P77: =ROUND((ROUND((AC77*I77),2)*BC77),2) -> 14429.75 | Q77: =(ROUND((ROUND(((ET77)*AV77*I77),2)*BB77),2)+ROUND((ROUND(((AE77-(EU77))*AV77*I77),2)*BS77),2)) -> 0 | R77: =ROUND((ROUND((AE77*AV77*I77),2)*BS77),2) -> 0 | S77: =ROUND((ROUND((AF77*AV77*I77),2)*BA77),2) -> 0 | T77: =ROUND(CU77*I77,2) -> 0 | U77: =CV77*I77 -> 0 | V77: =CW77*I77 -> 0 | W77: =ROUND(CX77*I77,2) -> 0 | X77: =ROUND(CY77,2) -> 0 | Y77: =ROUND(CZ77,2) -> 0 | AA77: 56498968 | AB77: =ROUND((AC77+AD77+AF77),6) -> 941.89 | AC77: =ROUND((ES77),6) -> 941.89 | AD77: =ROUND((((ET77)-(EU77))+AE77),6) -> 0 | AE77: =ROUND((EU77),6) -> 0 | AF77: =ROUND((EV77),6) -> 0 | AG77: =ROUND((AP77),6) -> 0 | AH77: =(EW77) -> 0 | AI77: =(EX77) -> 0 | AJ77: =(AS77) -> 0 | AK77: 941.89 | AL77: 941.89 | AM77: 0 | AN77: 0 | AO77: 0 | AP77: 0 | AQ77: 0 | AR77: 0 | AS77: 0 | AT77: 0 | AU77: 0 | AV77: 1 | AW77: 1 | AZ77: 1 | BA77: 1 | BB77: 1 | BC77: 7.66 | BH77: 3 | BI77: 3 | BM77: 746 | BN77: 0 | BP77: 0 | BQ77: 130 | BR77: 0 | BS77: 1 | BT77: 1 | BU77: 1 | BV77: 1 | BW77: 1 | BX77: 1 | BZ77: 90 | CA77: 46 | CE77: 30 | CF77: 0 | CG77: 0 | CM77: 0 | CO77: 0 | CP77: =(P77+Q77+S77) -> 14429.75 | CQ77: =ROUND((ROUND((AC77*1),2)*BC77),2) -> 7214.88 | CR77: =(ROUND((ROUND(((ET77)*AV77*1),2)*BB77),2)+ROUND((ROUND(((AE77-(EU77))*AV77*1),2)*BS77),2)) -> 0 | CS77: =ROUND((ROUND((AE77*AV77*1),2)*BS77),2) -> 0 | CT77: =ROUND((ROUND((AF77*AV77*1),2)*BA77),2) -> 0 | CU77: =AG77 -> 0 | CV77: =(AH77*AV77) -> 0 | CW77: =AI77 -> 0 | CX77: =AJ77 -> 0 | CY77: =(((S77+R77)*AT77)/100) -> 0 | CZ77: =(((S77+R77)*AU77)/100) -> 0 | DN77: 0 | DO77: 0 | DP77: 1 | DQ77: 1 | DU77: 1010 | DV77: шт. | DW77: шт. | DX77: 1 | EE77: 58162750 | EF77: 130 | EG77: Сметная стоимость оборудования | EH77: 0 | EJ77: 3 | EK77: 746 | EL77: ТСН-2001.13. Сметная стоимость оборудования | EM77: ТСН-2001.13 | EQ77: 0 | ER77: 941.89 | ES77: 941.89 | ET77: 0 | EU77: 0 | EV77: 0 | EW77: 0 | EX77: 0 | EZ77: 5 | FC77: 1 | FD77: 18 | FF77: 8306 | FQ77: 0 | FR77: =P77 -> 14429.75 | FS77: 0 | FX77: 90 | FY77: 46 | GA77: [8 306 / 1,2 / 7,66] + 3% Трансп + 1,2% Заг.скл | GD77: 1 | GF77: -99932320 | GG77: 2 | GH77: 3 | GI77: 5 | GJ77: 0 | GK77: 0 | GL77: =ROUND(IF(AND(BH77=3,BI77=3,FS77<>0),P77,0),2) -> 0 | GM77: =ROUND(O77+X77+Y77,2)+GX77 -> 14429.75 | GN77: =IF(OR(BI77=0,BI77=1),GM77-GX77,0) -> 0 | GO77: =IF(BI77=2,GM77-GX77,0) -> 0 | GP77: =IF(BI77=4,GM77-GX77,0) -> 0 | GR77: 1 | GS77: 1 | GT77: 0 | GV77: =ROUND((GT77),6) -> 0 | GW77: 1 | GX77: =ROUND(HC77*I77,2) -> 0 | HA77: 0 | HB77: 0 | HC77: =GV77*GW77 -> 0 | HE77: 3 | HF77: 1,2 | HS77: 0 | IK77: 0
A78: 18 | B78: 1 | E78: 11,2 | F78: КА 15 | G78: Источник вторичного электропитания резервированный адресный ИВЭПР 12/5 RS-R3 2х40 БР-R3 | H78: шт. | I78: =I74*J78 -> 1 | J78: 0.14285714 | K78: 0.1428571 | O78: =ROUND(CP78,2) -> 1477.01 | P78: =ROUND((ROUND((AC78*I78),2)*BC78),2) -> 1477.01 | Q78: =(ROUND((ROUND(((ET78)*AV78*I78),2)*BB78),2)+ROUND((ROUND(((AE78-(EU78))*AV78*I78),2)*BS78),2)) -> 0 | R78: =ROUND((ROUND((AE78*AV78*I78),2)*BS78),2) -> 0 | S78: =ROUND((ROUND((AF78*AV78*I78),2)*BA78),2) -> 0 | T78: =ROUND(CU78*I78,2) -> 0 | U78: =CV78*I78 -> 0 | V78: =CW78*I78 -> 0 | W78: =ROUND(CX78*I78,2) -> 0 | X78: =ROUND(CY78,2) -> 0 | Y78: =ROUND(CZ78,2) -> 0 | AA78: 56498966 | AB78: =ROUND((AC78+AD78+AF78),6) -> 1477.01 | AC78: =ROUND((ES78),6) -> 1477.01 | AD78: =ROUND((((ET78)-(EU78))+AE78),6) -> 0 | AE78: =ROUND((EU78),6) -> 0 | AF78: =ROUND((EV78),6) -> 0 | AG78: =ROUND((AP78),6) -> 0 | AH78: =(EW78) -> 0 | AI78: =(EX78) -> 0 | AJ78: =(AS78) -> 0 | AK78: 1477.01 | AL78: 1477.01 | AM78: 0 | AN78: 0 | AO78: 0 | AP78: 0 | AQ78: 0 | AR78: 0 | AS78: 0 | AT78: 0 | AU78: 0 | AV78: 1 | AW78: 1 | AZ78: 1 | BA78: 1 | BB78: 1 | BC78: 1 | BH78: 3 | BI78: 3 | BM78: 746 | BN78: 0 | BP78: 0 | BQ78: 130 | BR78: 0 | BS78: 1 | BT78: 1 | BU78: 1 | BV78: 1 | BW78: 1 | BX78: 1 | BZ78: 90 | CA78: 46 | CE78: 30 | CF78: 0 | CG78: 0 | CM78: 0 | CO78: 0 | CP78: =(P78+Q78+S78) -> 1477.01 | CQ78: =ROUND((ROUND((AC78*1),2)*BC78),2) -> 1477.01 | CR78: =(ROUND((ROUND(((ET78)*AV78*1),2)*BB78),2)+ROUND((ROUND(((AE78-(EU78))*AV78*1),2)*BS78),2)) -> 0 | CS78: =ROUND((ROUND((AE78*AV78*1),2)*BS78),2) -> 0 | CT78: =ROUND((ROUND((AF78*AV78*1),2)*BA78),2) -> 0 | CU78: =AG78 -> 0 | CV78: =(AH78*AV78) -> 0 | CW78: =AI78 -> 0 | CX78: =AJ78 -> 0 | CY78: =(((S78+R78)*AT78)/100) -> 0 | CZ78: =(((S78+R78)*AU78)/100) -> 0 | DN78: 0 | DO78: 0 | DP78: 1 | DQ78: 1 | DU78: 1010 | DV78: шт. | DW78: шт. | DX78: 1 | EE78: 58162750 | EF78: 130 | EG78: Сметная стоимость оборудования | EH78: 0 | EJ78: 3 | EK78: 746 | EL78: ТСН-2001.13. Сметная стоимость оборудования | EM78: ТСН-2001.13 | EQ78: 0 | ER78: 0 | ES78: 1477.01 | ET78: 0 | EU78: 0 | EV78: 0 | EW78: 0 | EX78: 0 | FQ78: 0 | FR78: =P78 -> 1477.01 | FS78: 0 | FX78: 90 | FY78: 46 | GA78: [13 025 / 1,2 / 7,66] + 3% Трансп + 1,2% Заг.скл | GD78: 1 | GF78: 1106697559 | GG78: 2 | GH78: 4 | GI78: -2 | GJ78: 0 | GK78: 0 | GL78: =ROUND(IF(AND(BH78=3,BI78=3,FS78<>0),P78,0),2) -> 0 | GM78: =ROUND(O78+X78+Y78,2)+GX78 -> 1477.01 | GN78: =IF(OR(BI78=0,BI78=1),GM78-GX78,0) -> 0 | GO78: =IF(BI78=2,GM78-GX78,0) -> 0 | GP78: =IF(BI78=4,GM78-GX78,0) -> 0 | GR78: 0 | GS78: 2 | GT78: 0 | GV78: =ROUND((GT78),6) -> 0 | GW78: 1 | GX78: =ROUND(HC78*I78,2) -> 0 | HA78: 0 | HB78: 0 | HC78: =GV78*GW78 -> 0 | HE78: 3 | HF78: 1,2 | HS78: 0 | IK78: 0
A79: 18 | B79: 1 | E79: 11,2 | F79: КА 15 | G79: Источник вторичного электропитания резервированный адресный ИВЭПР 12/5 RS-R3 2х40 БР-R3 | H79: шт. | I79: =I75*J79 -> 1 | J79: 0.14285714 | K79: 0.1428571 | O79: =ROUND(CP79,2) -> 11313.9 | P79: =ROUND((ROUND((AC79*I79),2)*BC79),2) -> 11313.9 | Q79: =(ROUND((ROUND(((ET79)*AV79*I79),2)*BB79),2)+ROUND((ROUND(((AE79-(EU79))*AV79*I79),2)*BS79),2)) -> 0 | R79: =ROUND((ROUND((AE79*AV79*I79),2)*BS79),2) -> 0 | S79: =ROUND((ROUND((AF79*AV79*I79),2)*BA79),2) -> 0 | T79: =ROUND(CU79*I79,2) -> 0 | U79: =CV79*I79 -> 0 | V79: =CW79*I79 -> 0 | W79: =ROUND(CX79*I79,2) -> 0 | X79: =ROUND(CY79,2) -> 0 | Y79: =ROUND(CZ79,2) -> 0 | AA79: 56498968 | AB79: =ROUND((AC79+AD79+AF79),6) -> 1477.01 | AC79: =ROUND((ES79),6) -> 1477.01 | AD79: =ROUND((((ET79)-(EU79))+AE79),6) -> 0 | AE79: =ROUND((EU79),6) -> 0 | AF79: =ROUND((EV79),6) -> 0 | AG79: =ROUND((AP79),6) -> 0 | AH79: =(EW79) -> 0 | AI79: =(EX79) -> 0 | AJ79: =(AS79) -> 0 | AK79: 1477.01 | AL79: 1477.01 | AM79: 0 | AN79: 0 | AO79: 0 | AP79: 0 | AQ79: 0 | AR79: 0 | AS79: 0 | AT79: 0 | AU79: 0 | AV79: 1 | AW79: 1 | AZ79: 1 | BA79: 1 | BB79: 1 | BC79: 7.66 | BH79: 3 | BI79: 3 | BM79: 746 | BN79: 0 | BP79: 0 | BQ79: 130 | BR79: 0 | BS79: 1 | BT79: 1 | BU79: 1 | BV79: 1 | BW79: 1 | BX79: 1 | BZ79: 90 | CA79: 46 | CE79: 30 | CF79: 0 | CG79: 0 | CM79: 0 | CO79: 0 | CP79: =(P79+Q79+S79) -> 11313.9 | CQ79: =ROUND((ROUND((AC79*1),2)*BC79),2) -> 11313.9 | CR79: =(ROUND((ROUND(((ET79)*AV79*1),2)*BB79),2)+ROUND((ROUND(((AE79-(EU79))*AV79*1),2)*BS79),2)) -> 0 | CS79: =ROUND((ROUND((AE79*AV79*1),2)*BS79),2) -> 0 | CT79: =ROUND((ROUND((AF79*AV79*1),2)*BA79),2) -> 0 | CU79: =AG79 -> 0 | CV79: =(AH79*AV79) -> 0 | CW79: =AI79 -> 0 | CX79: =AJ79 -> 0 | CY79: =(((S79+R79)*AT79)/100) -> 0 | CZ79: =(((S79+R79)*AU79)/100) -> 0 | DN79: 0 | DO79: 0 | DP79: 1 | DQ79: 1 | DU79: 1010 | DV79: шт. | DW79: шт. | DX79: 1 | EE79: 58162750 | EF79: 130 | EG79: Сметная стоимость оборудования | EH79: 0 | EJ79: 3 | EK79: 746 | EL79: ТСН-2001.13. Сметная стоимость оборудования | EM79: ТСН-2001.13 | EQ79: 0 | ER79: 1477.01 | ES79: 1477.01 | ET79: 0 | EU79: 0 | EV79: 0 | EW79: 0 | EX79: 0 | EZ79: 5 | FC79: 1 | FD79: 18 | FF79: 13025 | FQ79: 0 | FR79: =P79 -> 11313.9 | FS79: 0 | FX79: 90 | FY79: 46 | GA79: [13 025 / 1,2 / 7,66] + 3% Трансп + 1,2% Заг.скл | GD79: 1 | GF79: 1106697559 | GG79: 2 | GH79: 3 | GI79: 5 | GJ79: 0 | GK79: 0 | GL79: =ROUND(IF(AND(BH79=3,BI79=3,FS79<>0),P79,0),2) -> 0 | GM79: =ROUND(O79+X79+Y79,2)+GX79 -> 11313.9 | GN79: =IF(OR(BI79=0,BI79=1),GM79-GX79,0) -> 0 | GO79: =IF(BI79=2,GM79-GX79,0) -> 0 | GP79: =IF(BI79=4,GM79-GX79,0) -> 0 | GR79: 1 | GS79: 1 | GT79: 0 | GV79: =ROUND((GT79),6) -> 0 | GW79: 1 | GX79: =ROUND(HC79*I79,2) -> 0 | HA79: 0 | HB79: 0 | HC79: =GV79*GW79 -> 0 | HE79: 3 | HF79: 1,2 | HS79: 0 | IK79: 0
A80: 18 | B80: 1 | E80: 11,3 | F80: КА 16 | G80: Источник вторичного электропитания резервированный адресный ИВЭПР 12/2 RS-R3 2х12 БР-R3 | H80: шт. | I80: =I74*J80 -> 4 | J80: 0.57142857 | K80: 0.5714286 | O80: =ROUND(CP80,2) -> 3462.76 | P80: =ROUND((ROUND((AC80*I80),2)*BC80),2) -> 3462.76 | Q80: =(ROUND((ROUND(((ET80)*AV80*I80),2)*BB80),2)+ROUND((ROUND(((AE80-(EU80))*AV80*I80),2)*BS80),2)) -> 0 | R80: =ROUND((ROUND((AE80*AV80*I80),2)*BS80),2) -> 0 | S80: =ROUND((ROUND((AF80*AV80*I80),2)*BA80),2) -> 0 | T80: =ROUND(CU80*I80,2) -> 0 | U80: =CV80*I80 -> 0 | V80: =CW80*I80 -> 0 | W80: =ROUND(CX80*I80,2) -> 0 | X80: =ROUND(CY80,2) -> 0 | Y80: =ROUND(CZ80,2) -> 0 | AA80: 56498966 | AB80: =ROUND((AC80+AD80+AF80),6) -> 865.69 | AC80: =ROUND((ES80),6) -> 865.69 | AD80: =ROUND((((ET80)-(EU80))+AE80),6) -> 0 | AE80: =ROUND((EU80),6) -> 0 | AF80: =ROUND((EV80),6) -> 0 | AG80: =ROUND((AP80),6) -> 0 | AH80: =(EW80) -> 0 | AI80: =(EX80) -> 0 | AJ80: =(AS80) -> 0 | AK80: 865.69 | AL80: 865.69 | AM80: 0 | AN80: 0 | AO80: 0 | AP80: 0 | AQ80: 0 | AR80: 0 | AS80: 0 | AT80: 0 | AU80: 0 | AV80: 1 | AW80: 1 | AZ80: 1 | BA80: 1 | BB80: 1 | BC80: 1 | BH80: 3 | BI80: 3 | BM80: 746 | BN80: 0 | BP80: 0 | BQ80: 130 | BR80: 0 | BS80: 1 | BT80: 1 | BU80: 1 | BV80: 1 | BW80: 1 | BX80: 1 | BZ80: 90 | CA80: 46 | CE80: 30 | CF80: 0 | CG80: 0 | CM80: 0 | CO80: 0 | CP80: =(P80+Q80+S80) -> 3462.76 | CQ80: =ROUND((ROUND((AC80*1),2)*BC80),2) -> 865.69 | CR80: =(ROUND((ROUND(((ET80)*AV80*1),2)*BB80),2)+ROUND((ROUND(((AE80-(EU80))*AV80*1),2)*BS80),2)) -> 0 | CS80: =ROUND((ROUND((AE80*AV80*1),2)*BS80),2) -> 0 | CT80: =ROUND((ROUND((AF80*AV80*1),2)*BA80),2) -> 0 | CU80: =AG80 -> 0 | CV80: =(AH80*AV80) -> 0 | CW80: =AI80 -> 0 | CX80: =AJ80 -> 0 | CY80: =(((S80+R80)*AT80)/100) -> 0 | CZ80: =(((S80+R80)*AU80)/100) -> 0 | DN80: 0 | DO80: 0 | DP80: 1 | DQ80: 1 | DU80: 1010 | DV80: шт. | DW80: шт. | DX80: 1 | EE80: 58162750 | EF80: 130 | EG80: Сметная стоимость оборудования | EH80: 0 | EJ80: 3 | EK80: 746 | EL80: ТСН-2001.13. Сметная стоимость оборудования | EM80: ТСН-2001.13 | EQ80: 0 | ER80: 0 | ES80: 865.69 | ET80: 0 | EU80: 0 | EV80: 0 | EW80: 0 | EX80: 0 | FQ80: 0 | FR80: =P80 -> 3462.76 | FS80: 0 | FX80: 90 | FY80: 46 | GA80: [7 634 / 1,2 / 7,66] + 3% Трансп + 1,2% Заг.скл | GD80: 1 | GF80: 1341912761 | GG80: 2 | GH80: 4 | GI80: -2 | GJ80: 0 | GK80: 0 | GL80: =ROUND(IF(AND(BH80=3,BI80=3,FS80<>0),P80,0),2) -> 0 | GM80: =ROUND(O80+X80+Y80,2)+GX80 -> 3462.76 | GN80: =IF(OR(BI80=0,BI80=1),GM80-GX80,0) -> 0 | GO80: =IF(BI80=2,GM80-GX80,0) -> 0 | GP80: =IF(BI80=4,GM80-GX80,0) -> 0 | GR80: 0 | GS80: 2 | GT80: 0 | GV80: =ROUND((GT80),6) -> 0 | GW80: 1 | GX80: =ROUND(HC80*I80,2) -> 0 | HA80: 0 | HB80: 0 | HC80: =GV80*GW80 -> 0 | HE80: 3 | HF80: 1,2 | HS80: 0 | IK80: 0
A81: 18 | B81: 1 | E81: 11,3 | F81: КА 16 | G81: Источник вторичного электропитания резервированный адресный ИВЭПР 12/2 RS-R3 2х12 БР-R3 | H81: шт. | I81: =I75*J81 -> 4 | J81: 0.57142857 | K81: 0.5714286 | O81: =ROUND(CP81,2) -> 26524.74 | P81: =ROUND((ROUND((AC81*I81),2)*BC81),2) -> 26524.74 | Q81: =(ROUND((ROUND(((ET81)*AV81*I81),2)*BB81),2)+ROUND((ROUND(((AE81-(EU81))*AV81*I81),2)*BS81),2)) -> 0 | R81: =ROUND((ROUND((AE81*AV81*I81),2)*BS81),2) -> 0 | S81: =ROUND((ROUND((AF81*AV81*I81),2)*BA81),2) -> 0 | T81: =ROUND(CU81*I81,2) -> 0 | U81: =CV81*I81 -> 0 | V81: =CW81*I81 -> 0 | W81: =ROUND(CX81*I81,2) -> 0 | X81: =ROUND(CY81,2) -> 0 | Y81: =ROUND(CZ81,2) -> 0 | AA81: 56498968 | AB81: =ROUND((AC81+AD81+AF81),6) -> 865.69 | AC81: =ROUND((ES81),6) -> 865.69 | AD81: =ROUND((((ET81)-(EU81))+AE81),6) -> 0 | AE81: =ROUND((EU81),6) -> 0 | AF81: =ROUND((EV81),6) -> 0 | AG81: =ROUND((AP81),6) -> 0 | AH81: =(EW81) -> 0 | AI81: =(EX81) -> 0 | AJ81: =(AS81) -> 0 | AK81: 865.69 | AL81: 865.69 | AM81: 0 | AN81: 0 | AO81: 0 | AP81: 0 | AQ81: 0 | AR81: 0 | AS81: 0 | AT81: 0 | AU81: 0 | AV81: 1 | AW81: 1 | AZ81: 1 | BA81: 1 | BB81: 1 | BC81: 7.66 | BH81: 3 | BI81: 3 | BM81: 746 | BN81: 0 | BP81: 0 | BQ81: 130 | BR81: 0 | BS81: 1 | BT81: 1 | BU81: 1 | BV81: 1 | BW81: 1 | BX81: 1 | BZ81: 90 | CA81: 46 | CE81: 30 | CF81: 0 | CG81: 0 | CM81: 0 | CO81: 0 | CP81: =(P81+Q81+S81) -> 26524.74 | CQ81: =ROUND((ROUND((AC81*1),2)*BC81),2) -> 6631.19 | CR81: =(ROUND((ROUND(((ET81)*AV81*1),2)*BB81),2)+ROUND((ROUND(((AE81-(EU81))*AV81*1),2)*BS81),2)) -> 0 | CS81: =ROUND((ROUND((AE81*AV81*1),2)*BS81),2) -> 0 | CT81: =ROUND((ROUND((AF81*AV81*1),2)*BA81),2) -> 0 | CU81: =AG81 -> 0 | CV81: =(AH81*AV81) -> 0 | CW81: =AI81 -> 0 | CX81: =AJ81 -> 0 | CY81: =(((S81+R81)*AT81)/100) -> 0 | CZ81: =(((S81+R81)*AU81)/100) -> 0 | DN81: 0 | DO81: 0 | DP81: 1 | DQ81: 1 | DU81: 1010 | DV81: шт. | DW81: шт. | DX81: 1 | EE81: 58162750 | EF81: 130 | EG81: Сметная стоимость оборудования | EH81: 0 | EJ81: 3 | EK81: 746 | EL81: ТСН-2001.13. Сметная стоимость оборудования | EM81: ТСН-2001.13 | EQ81: 0 | ER81: 865.69 | ES81: 865.69 | ET81: 0 | EU81: 0 | EV81: 0 | EW81: 0 | EX81: 0 | EZ81: 5 | FC81: 1 | FD81: 18 | FF81: 7634 | FQ81: 0 | FR81: =P81 -> 26524.74 | FS81: 0 | FX81: 90 | FY81: 46 | GA81: [7 634 / 1,2 / 7,66] + 3% Трансп + 1,2% Заг.скл | GD81: 1 | GF81: 1341912761 | GG81: 2 | GH81: 3 | GI81: 5 | GJ81: 0 | GK81: 0 | GL81: =ROUND(IF(AND(BH81=3,BI81=3,FS81<>0),P81,0),2) -> 0 | GM81: =ROUND(O81+X81+Y81,2)+GX81 -> 26524.74 | GN81: =IF(OR(BI81=0,BI81=1),GM81-GX81,0) -> 0 | GO81: =IF(BI81=2,GM81-GX81,0) -> 0 | GP81: =IF(BI81=4,GM81-GX81,0) -> 0 | GR81: 1 | GS81: 1 | GT81: 0 | GV81: =ROUND((GT81),6) -> 0 | GW81: 1 | GX81: =ROUND(HC81*I81,2) -> 0 | HA81: 0 | HB81: 0 | HC81: =GV81*GW81 -> 0 | HE81: 3 | HF81: 1,2 | HS81: 0 | IK81: 0
A82: 18 | B82: 1 | E82: 11,4 | F82: 13.1-1-660 | G82: Аккумулятор герметичный свинцово-кислотный 12 В, 12 А·ч | H82: шт. | I82: =I74*J82 -> 8 | J82: 1.1428571 | K82: 1.1428571 | O82: =ROUND(CP82,2) -> 2281.6 | P82: =ROUND((ROUND((AC82*I82),2)*BC82),2) -> 2281.6 | Q82: =(ROUND((ROUND(((ET82)*AV82*I82),2)*BB82),2)+ROUND((ROUND(((AE82-(EU82))*AV82*I82),2)*BS82),2)) -> 0 | R82: =ROUND((ROUND((AE82*AV82*I82),2)*BS82),2) -> 0 | S82: =ROUND((ROUND((AF82*AV82*I82),2)*BA82),2) -> 0 | T82: =ROUND(CU82*I82,2) -> 0 | U82: =CV82*I82 -> 0 | V82: =CW82*I82 -> 0 | W82: =ROUND(CX82*I82,2) -> 0 | X82: =ROUND(CY82,2) -> 0 | Y82: =ROUND(CZ82,2) -> 0 | AA82: 56498966 | AB82: =ROUND((AC82+AD82+AF82),6) -> 285.2 | AC82: =ROUND((ES82),6) -> 285.2 | AD82: =ROUND((((ET82)-(EU82))+AE82),6) -> 0 | AE82: =ROUND((EU82),6) -> 0 | AF82: =ROUND((EV82),6) -> 0 | AG82: =ROUND((AP82),6) -> 0 | AH82: =(EW82) -> 0 | AI82: =(EX82) -> 0 | AJ82: =(AS82) -> 0 | AK82: 285.2 | AL82: 285.2 | AM82: 0 | AN82: 0 | AO82: 0 | AP82: 0 | AQ82: 0 | AR82: 0 | AS82: 0 | AT82: 0 | AU82: 0 | AV82: 1 | AW82: 1 | AZ82: 1 | BA82: 1 | BB82: 1 | BC82: 1 | BH82: 3 | BI82: 3 | BM82: 746 | BN82: 0 | BP82: 0 | BQ82: 130 | BR82: 0 | BS82: 1 | BT82: 1 | BU82: 1 | BV82: 1 | BW82: 1 | BX82: 1 | BZ82: 90 | CA82: 46 | CE82: 30 | CF82: 0 | CG82: 0 | CM82: 0 | CO82: 0 | CP82: =(P82+Q82+S82) -> 2281.6 | CQ82: =ROUND((ROUND((AC82*1),2)*BC82),2) -> 285.2 | CR82: =(ROUND((ROUND(((ET82)*AV82*1),2)*BB82),2)+ROUND((ROUND(((AE82-(EU82))*AV82*1),2)*BS82),2)) -> 0 | CS82: =ROUND((ROUND((AE82*AV82*1),2)*BS82),2) -> 0 | CT82: =ROUND((ROUND((AF82*AV82*1),2)*BA82),2) -> 0 | CU82: =AG82 -> 0 | CV82: =(AH82*AV82) -> 0 | CW82: =AI82 -> 0 | CX82: =AJ82 -> 0 | CY82: =(((S82+R82)*AT82)/100) -> 0 | CZ82: =(((S82+R82)*AU82)/100) -> 0 | DN82: 0 | DO82: 0 | DP82: 1 | DQ82: 1 | DU82: 1010 | DV82: шт. | DW82: шт. | DX82: 1 | EE82: 58162750 | EF82: 130 | EG82: Сметная стоимость оборудования | EH82: 0 | EJ82: 3 | EK82: 746 | EL82: ТСН-2001.13. Сметная стоимость оборудования | EM82: ТСН-2001.13 | EQ82: 0 | ER82: 285.2 | ES82: 285.2 | ET82: 0 | EU82: 0 | EV82: 0 | EW82: 0 | EX82: 0 | FQ82: 0 | FR82: =P82 -> 2281.6 | FS82: 0 | FX82: 90 | FY82: 46 | GD82: 1 | GF82: 1694751249 | GG82: 2 | GH82: 1 | GI82: -2 | GJ82: 0 | GK82: 0 | GL82: =ROUND(IF(AND(BH82=3,BI82=3,FS82<>0),P82,0),2) -> 0 | GM82: =ROUND(O82+X82+Y82,2)+GX82 -> 2281.6 | GN82: =IF(OR(BI82=0,BI82=1),GM82-GX82,0) -> 0 | GO82: =IF(BI82=2,GM82-GX82,0) -> 0 | GP82: =IF(BI82=4,GM82-GX82,0) -> 0 | GR82: 0 | GS82: 3 | GT82: 0 | GV82: =ROUND((GT82),6) -> 0 | GW82: 1 | GX82: =ROUND(HC82*I82,2) -> 0 | HA82: 0 | HB82: 0 | HC82: =GV82*GW82 -> 0 | HS82: 0 | IK82: 0
