Workbook

Sheet 02-01-14
A1: =Source!B1 -> Smeta.RU (495) 974-1589
J2: Форма № 4б
A3: Капитальный ремонт здания Государственного бюджетного общеобразовательного учреждения города Москвы "Школа №236" по адресу: г. Москва, улица Клязьминская, дом 7, корпус 4. | AP3: Капитальный ремонт здания Государственного бюджетного общеобразовательного учреждения города Москвы "Школа №236" по адресу: г. Москва, улица Клязьминская, дом 7, корпус 4. 02-01-14 СОТ
A4: (наименование стройки и/или объекта)
A6: =CONCATENATE( "ЛОКАЛЬНАЯ СМЕТА № ",IF(Source!F20<>"Новая локальная смета", Source!F20, "")) -> ЛОКАЛЬНАЯ СМЕТА № 02-01-14
A8: =IF(Source!G20<>"Новая локальная смета", Source!G20, "") -> Система охранного теленаблюдения
A9: (наименование работ и затрат)
A11: =CONCATENATE( "Основание: чертежи № ", Source!J20) -> Основание: чертежи № 2024-00281-00-ИОС5.7
I13: В базисном уровне цен | J13: В текущем уровне цен
E14: Сметная стоимость | I14: =I15+I16+I17+I18 -> 1045.29 | J14: =J15+J16+J17+J18 -> 10298 | K14: тыс.руб.
E15: Строительные работы | I15: =ROUND((Source!F222)/1000, 2) -> 0 | J15: =ROUND((Source!P222)/1000, 2) -> 0 | K15: тыс.руб.
E16: Работы по монтажу оборудования | I16: =ROUND((Source!F223)/1000, 2) -> 135.31 | J16: =ROUND((Source!P223)/1000, 2) -> 3332.58 | K16: тыс.руб.
E17: Оборудование | I17: =ROUND((Source!F214)/1000, 2) -> 909.98 | J17: =ROUND((Source!P214)/1000, 2) -> 6965.42 | K17: тыс.руб.
E18: Прочие работы и затраты | I18: =ROUND((Source!F224+Source!F225)/1000, 2) -> 0 | J18: =ROUND((Source!P224+Source!P225)/1000, 2) -> 0 | K18: тыс.руб.
E19: Средства на оплату труда | I19: =(Source!F220+ Source!F219)/1000 -> 19.03358 | J19: =((Source!P220 + Source!P219)/1000) -> 1046.6566 | K19: тыс.руб.
E20: Затраты труда | I20: =Source!F227 -> 1399.7195 | K20: чел.-ч.
E21: Кроме того:
E22: Возврат материалов | I22: =SUM(Y28:Y283)/1000 -> 0 | J22: =SUM(Z28:Z283)/1000 -> 0 | K22: тыс.руб.
A24: Составлен(а) по ТСН-2001 с учетом Дополнения №: 80
A25: № и период сборника коэффициентов (индексов) пересчета: Коэффициенты к ТСН-2001 МГЭ Дополнение 80, строительство №217/80 III квартал 2025 года и Коэффициенты к ТСН-2001.13-2 Дополнение 46 №62/46 III квартал 2025 года | AP25: № и период сборника коэффициентов (индексов) пересчета: Коэффициенты к ТСН-2001 МГЭ Дополнение 80, строительство №217/80 III квартал 2025 года и Коэффициенты к ТСН-2001.13-2 Дополнение 46 №62/46 III квартал 2025 года
A26: № п/п | B26: Шифр расценки и коды ресурсов | C26: Наименование работ и затрат | D26: Ед. изм. | E26: Кол-во единиц | F26: Цена на ед. изм., руб. | G26: Попра- вочные коэффи- циенты | H26: Коэффи- циенты зимних удорожа- ний | I26: Всего в ценах на январь 2000 года, руб. | J26: Коэффи- циенты (индек- сы) пере- счета, нормы НР и СП | K26: ВСЕГО затрат в текущем уровне цен, руб.
A27: 1 | B27: 2 | C27: 3 | D27: 4 | E27: 5 | F27: 6 | G27: 7 | H27: 8 | I27: 9 | J27: 10 | K27: 11
A29: =CONCATENATE("Раздел: ",IF(Source!G24<>"Новый раздел", Source!G24, "")) -> Раздел: Оборудование
A30: 1 | B30: =Source!F28 -> 4.10-174-1 | C30: Монтаж внутренней камеры видеонаблюдения | D30: =Source!H28 -> 10 шт. | E30: =Source!I28 -> 2.8 | Q30: =Source!X28 -> 718.46 | R30: =Source!X29 -> 39508.17 | S30: =Source!Y28 -> 367.21 | T30: =Source!Y29 -> 20193.07 | U30: =ROUND((175/100)*ROUND(Source!R28, 2), 2) -> 0.74 | V30: =ROUND((0/100)*ROUND(Source!R29, 2), 2) -> 0 | AC30: 0
C31: ="Объем: "&Source!I28&"=28/"&"10" -> Объем: 2,8=28/10
C32: ЗП | F32: =Source!AO28 -> 247.42 | G32: =Source!DG28 -> *1,1 | H32: =Source!AV29 -> 1.047 | I32: =Source!S28 -> 797.87 | J32: =IF(Source!BA29<> 0, Source!BA29, 1) -> 54.99 | K32: =Source!S29 -> 43874.87
C33: ЭМ | F33: =Source!AM28 -> 2.36 | G33: =Source!DE28 -> *1,1 | H33: =Source!AV29 -> 1.047 | I33: =Source!Q28 -> 7.61 | J33: =IF(Source!BB29<> 0, Source!BB29, 1) -> 11.36 | K33: =Source!Q29 -> 86.45
C34: в т.ч. ЗПМ | F34: =Source!AN28 -> 0.13 | G34: =Source!DF28 -> *1,1 | H34: =Source!AV29 -> 1.047 | I34: =Source!R28 -> 0.42 | J34: =IF(Source!BS29<> 0, Source!BS29, 1) -> 54.99 | K34: =Source!R29 -> 23.1
C35: МР | F35: =Source!AL28 -> 42.51 | G35: =Source!DD28 | H35: =Source!AW29 -> 1 | I35: =Source!P28 -> 119.03 | J35: =IF(Source!BC29<> 0, Source!BC29, 1) -> 1.93 | K35: =Source!P29 -> 229.73
C36: НР от ФОТ | D36: % | E36: =Source!BZ29 -> 90 | I36: =SUM(Q30:Q35) -> 718.46 | J36: =Source!AT29 -> 90 | K36: =SUM(R30:R35) -> 39508.17
C37: СП от ФОТ | D37: % | E37: =Source!CA29 -> 46 | I37: =SUM(S30:S36) -> 367.21 | J37: =Source!AU29 -> 46 | K37: =SUM(T30:T36) -> 20193.07
C38: ЗТР | D38: чел-ч | E38: =Source!AQ28 -> 15.54 | G38: =Source!DI28 -> *1,1 | H38: =Source!AV29 -> 1.047 | I38: =Source!U28 -> 50.11277
C39: ВСЕГО работ по позиции: | H39: =I32+I33+I35+I36+I37+0-0-0 -> 2010.18 | J39: =K32+K33+K35+K36+K37+0-0-0 -> 103892.29
C40: ВСЕГО оборудование по позиции: | H40: =0+0 -> 0 | J40: =0+0 -> 0
C41: ВСЕГО по позиции: | H41: =I32+I33+I35+I36+I37+0 -> 2010.18 | J41: =K32+K33+K35+K36+K37+0 -> 103892.29 | O41: =I32+I33+I35+I36+I37+0 -> 2010.18 | P41: =K32+K33+K35+K36+K37+0 -> 103892.29
A43: 2 | B43: =Source!F30 -> КА-1 | C43: ОБОРУДОВАНИЕ:_x000D_ Цилиндрическая IP-видеокамера с фиксированным объективом IP 2 Мп; 1/3" КМОП, 1920х1080-25/30к/с; встроенный микрофон; Дальность ИК подсветки 30м; объектив 2.8мм(3.6мм, 6ммопционально) ; режим "день/ночь", H264/ MJPEG ( Доп. поток) ; ; PoE 5 Вт; -40 ~ +60°C, TR-D2121CL3 4.0 1 011,06 = [8 916 / 1,2 / 7,66] + 3% Трансп + 1,2% Заг.скл | D43: =Source!H30 -> ШТ | E43: =Source!I30 -> 28 | F43: =Source!AL30 -> 1011.06 | G43: =Source!DD30 | H43: =Source!AW31 -> 1 | I43: =Source!P30 -> 28309.68 | J43: =IF(Source!BC31<> 0, Source!BC31, 1) -> 7.66 | K43: =Source!P31 -> 216852.15 | Q43: =Source!X30 -> 0 | R43: =Source!X31 -> 0 | S43: =Source!Y30 -> 0 | T43: =Source!Y31 -> 0 | U43: =ROUND((175/100)*ROUND(Source!R30, 2), 2) -> 0 | V43: =ROUND((0/100)*ROUND(Source!R31, 2), 2) -> 0 | AC43: 5
C44: ВСЕГО по позиции: | H44: =I43+0 -> 28309.68 | J44: =K43+0 -> 216852.15 | O44: =I43+0 -> 28309.68 | P44: =K43+0 -> 216852.15
A46: 3 | B46: =Source!F32 -> 4.10-136-1 | C46: Разные устройства, монтаж коробки телевизионной (ответвители, разветвители магистральные, домовые, абонентские), УСС, БФТК | D46: =Source!H32 -> 1 ШТ. | E46: =Source!I32 -> 28 | Q46: =Source!X32 -> 350.5 | R46: =Source!X33 -> 19274.13 | S46: =Source!Y32 -> 195.54 | T46: =Source!Y33 -> 10752.94 | U46: =ROUND((175/100)*ROUND(Source!R32, 2), 2) -> 0 | V46: =ROUND((0/100)*ROUND(Source!R33, 2), 2) -> 0 | AC46: 0
C47: ЗП | F47: =Source!AO32 -> 11.02 | G47: =Source!DG32 -> *1,1 | H47: =Source!AV33 -> 1.087 | I47: =Source!S32 -> 368.95 | J47: =IF(Source!BA33<> 0, Source!BA33, 1) -> 54.99 | K47: =Source!S33 -> 20288.56
C48: МР | F48: =Source!AL32 -> 0.29 | G48: =Source!DD32 | H48: =Source!AW33 -> 1 | I48: =Source!P32 -> 8.12 | J48: =IF(Source!BC33<> 0, Source!BC33, 1) -> 9.9 | K48: =Source!P33 -> 80.39
C49: НР от ФОТ | D49: % | E49: =Source!BZ33 -> 95 | I49: =SUM(Q46:Q48) -> 350.5 | J49: =Source!AT33 -> 95 | K49: =SUM(R46:R48) -> 19274.13
C50: СП от ФОТ | D50: % | E50: =Source!CA33 -> 53 | I50: =SUM(S46:S49) -> 195.54 | J50: =Source!AU33 -> 53 | K50: =SUM(T46:T49) -> 10752.94
C51: ЗТР | D51: чел-ч | E51: =Source!AQ32 -> 0.8 | G51: =Source!DI32 -> *1,1 | H51: =Source!AV33 -> 1.087 | I51: =Source!U32 -> 26.78368
C52: ВСЕГО работ по позиции: | H52: =I47+I48+I49+I50+0-0-0 -> 923.11 | J52: =K47+K48+K49+K50+0-0-0 -> 50396.02
C53: ВСЕГО оборудование по позиции: | H53: =0+0 -> 0 | J53: =0+0 -> 0
C54: ВСЕГО по позиции: | H54: =I47+I48+I49+I50+0 -> 923.11 | J54: =K47+K48+K49+K50+0 -> 50396.02 | O54: =I47+I48+I49+I50+0 -> 923.11 | P54: =K47+K48+K49+K50+0 -> 50396.02
A56: 4 | B56: =Source!F34 -> КА-2 | C56: Устройство грозозащиты NST NS-LP-1GP/D 279,52 = [3 249 / 1,2 / 9,88] + 2% Заг.скл | D56: =Source!H34 -> ШТ | E56: =Source!I34 -> 28 | F56: =Source!AL34 -> 279.52 | G56: =Source!DD34 | H56: =Source!AW35 -> 1 | I56: =Source!P34 -> 7826.56 | J56: =IF(Source!BC35<> 0, Source!BC35, 1) -> 9.88 | K56: =Source!P35 -> 77326.41 | Q56: =Source!X34 -> 0 | R56: =Source!X35 -> 0 | S56: =Source!Y34 -> 0 | T56: =Source!Y35 -> 0 | U56: =ROUND((175/100)*ROUND(Source!R34, 2), 2) -> 0 | V56: =ROUND((0/100)*ROUND(Source!R35, 2), 2) -> 0 | AC56: 3
C57: ВСЕГО по позиции: | H57: =I56+0 -> 7826.56 | J57: =K56+0 -> 77326.41 | O57: =I56+0 -> 7826.56 | P57: =K56+0 -> 77326.41
A59: 5 | B59: =Source!F36 -> 4.10-174-2 | C59: Монтаж наружной камеры видеонаблюдения | D59: =Source!H36 -> 10 шт. | E59: =Source!I36 -> 10.9 | Q59: =Source!X36 -> 4535.08 | R59: =Source!X37 -> 249384.16 | S59: =Source!Y36 -> 2317.93 | T59: =Source!Y37 -> 127463.01 | U59: =ROUND((175/100)*ROUND(Source!R36, 2), 2) -> 2.85 | V59: =ROUND((0/100)*ROUND(Source!R37, 2), 2) -> 0 | AC59: 0
C60: ="Объем: "&Source!I36&"=109/"&"10" -> Объем: 10,9=109/10
C61: ЗП | F61: =Source!AO36 -> 401.27 | G61: =Source!DG36 -> *1,1 | H61: =Source!AV37 -> 1.047 | I61: =Source!S36 -> 5037.35 | J61: =IF(Source!BA37<> 0, Source!BA37, 1) -> 54.99 | K61: =Source!S37 -> 277003.88
C62: ЭМ | F62: =Source!AM36 -> 2.36 | G62: =Source!DE36 -> *1,1 | H62: =Source!AV37 -> 1.047 | I62: =Source!Q36 -> 29.63 | J62: =IF(Source!BB37<> 0, Source!BB37, 1) -> 11.36 | K62: =Source!Q37 -> 336.6
C63: в т.ч. ЗПМ | F63: =Source!AN36 -> 0.13 | G63: =Source!DF36 -> *1,1 | H63: =Source!AV37 -> 1.047 | I63: =Source!R36 -> 1.63 | J63: =IF(Source!BS37<> 0, Source!BS37, 1) -> 54.99 | K63: =Source!R37 -> 89.63
C64: МР | F64: =Source!AL36 -> 42.51 | G64: =Source!DD36 | H64: =Source!AW37 -> 1 | I64: =Source!P36 -> 463.36 | J64: =IF(Source!BC37<> 0, Source!BC37, 1) -> 1.93 | K64: =Source!P37 -> 894.28
C65: НР от ФОТ | D65: % | E65: =Source!BZ37 -> 90 | I65: =SUM(Q59:Q64) -> 4535.08 | J65: =Source!AT37 -> 90 | K65: =SUM(R59:R64) -> 249384.16
C66: СП от ФОТ | D66: % | E66: =Source!CA37 -> 46 | I66: =SUM(S59:S65) -> 2317.93 | J66: =Source!AU37 -> 46 | K66: =SUM(T59:T65) -> 127463.01
C67: ЗТР | D67: чел-ч | E67: =Source!AQ36 -> 25.33 | G67: =Source!DI36 -> *1,1 | H67: =Source!AV37 -> 1.047 | I67: =Source!U36 -> 317.98091
C68: ВСЕГО работ по позиции: | H68: =I61+I62+I64+I65+I66+0-0-0 -> 12383.35 | J68: =K61+K62+K64+K65+K66+0-0-0 -> 655081.93
C69: ВСЕГО оборудование по позиции: | H69: =0+0 -> 0 | J69: =0+0 -> 0
C70: ВСЕГО по позиции: | H70: =I61+I62+I64+I65+I66+0 -> 12383.35 | J70: =K61+K62+K64+K65+K66+0 -> 655081.93 | O70: =I61+I62+I64+I65+I66+0 -> 12383.35 | P70: =K61+K62+K64+K65+K66+0 -> 655081.93
A72: 6 | B72: =Source!F38 -> КА-3 | C72: ОБОРУДОВАНИЕ:_x000D_ Купольная IP-видеокамера с фиксированным объективом IP 2 Мп; 1/2.8" КМОП, 1920х1080-25/30к/с; встроенный микрофон; Дальность ИК подсветки 25м; объектив 2.8мм(3.6мм, 6ммопционально) ; режим "день/ночь", H264/ MJPEG ( Доп. поток) ; ; PoE 5 Вт; TR-D2D2 v2 2.7-13.5 1 301,25 = [11 475 / 1,2 / 7,66] + 3% Трансп + 1,2% Заг.скл | D72: =Source!H38 -> ШТ | E72: =Source!I38 -> 109 | F72: =Source!AL38 -> 1301.25 | G72: =Source!DD38 | H72: =Source!AW39 -> 1 | I72: =Source!P38 -> 141836.25 | J72: =IF(Source!BC39<> 0, Source!BC39, 1) -> 7.66 | K72: =Source!P39 -> 1086465.7 | Q72: =Source!X38 -> 0 | R72: =Source!X39 -> 0 | S72: =Source!Y38 -> 0 | T72: =Source!Y39 -> 0 | U72: =ROUND((175/100)*ROUND(Source!R38, 2), 2) -> 0 | V72: =ROUND((0/100)*ROUND(Source!R39, 2), 2) -> 0 | AC72: 5
C73: ВСЕГО по позиции: | H73: =I72+0 -> 141836.25 | J73: =K72+0 -> 1086465.7 | O73: =I72+0 -> 141836.25 | P73: =K72+0 -> 1086465.7
A75: 7 | B75: =Source!F40 -> 4.10-72-14 | C75: Монтаж устройства цифровой регистрации | D75: =Source!H40 -> 1 устройство | E75: =Source!I40 -> 1 | Q75: =Source!X40 -> 104.07 | R75: =Source!X41 -> 5722.94 | S75: =Source!Y40 -> 58.06 | T75: =Source!Y41 -> 3192.8 | U75: =ROUND((175/100)*ROUND(Source!R40, 2), 2) -> 0 | V75: =ROUND((0/100)*ROUND(Source!R41, 2), 2) -> 0 | AC75: 0
C76: ЗП | F76: =Source!AO40 -> 95.12 | G76: =Source!DG40 -> *1,1 | H76: =Source!AV41 -> 1.047 | I76: =Source!S40 -> 109.55 | J76: =IF(Source!BA41<> 0, Source!BA41, 1) -> 54.99 | K76: =Source!S41 -> 6024.15
C77: МР | F77: =Source!AL40 -> 1.1 | G77: =Source!DD40 | H77: =Source!AW41 -> 1 | I77: =Source!P40 -> 1.1 | J77: =IF(Source!BC41<> 0, Source!BC41, 1) -> 16.72 | K77: =Source!P41 -> 18.39
C78: НР от ФОТ | D78: % | E78: =Source!BZ41 -> 95 | I78: =SUM(Q75:Q77) -> 104.07 | J78: =Source!AT41 -> 95 | K78: =SUM(R75:R77) -> 5722.94
C79: СП от ФОТ | D79: % | E79: =Source!CA41 -> 53 | I79: =SUM(S75:S78) -> 58.06 | J79: =Source!AU41 -> 53 | K79: =SUM(T75:T78) -> 3192.8
C80: ЗТР | D80: чел-ч | E80: =Source!AQ40 -> 8 | G80: =Source!DI40 -> *1,1 | H80: =Source!AV41 -> 1.047 | I80: =Source!U40 -> 9.2136
C81: ВСЕГО работ по позиции: | H81: =I76+I77+I78+I79+0-0-0 -> 272.78 | J81: =K76+K77+K78+K79+0-0-0 -> 14958.28
C82: ВСЕГО оборудование по позиции: | H82: =0+0 -> 0 | J82: =0+0 -> 0
C83: ВСЕГО по позиции: | H83: =I76+I77+I78+I79+0 -> 272.78 | J83: =K76+K77+K78+K79+0 -> 14958.28 | O83: =I76+I77+I78+I79+0 -> 272.78 | P83: =K76+K77+K78+K79+0 -> 14958.28
A85: 8 | B85: =Source!F42 -> КА-4 | C85: ОБОРУДОВАНИЕ:_x000D_ IP-видеорегистратор UltraStation 24/10 на 256 каналов, 24 HDD на 10 Тбайт UltraStation 24/10 256 v2 с 24 HDD 304 239,85 = [2 682 924 / 1,2 / 7,66] + 3% Трансп + 1,2% Заг.скл | D85: =Source!H42 -> ШТ | E85: =Source!I42 -> 1 | F85: =Source!AL42 -> 304239.85 | G85: =Source!DD42 | H85: =Source!AW43 -> 1 | I85: =Source!P42 -> 304239.85 | J85: =IF(Source!BC43<> 0, Source!BC43, 1) -> 7.66 | K85: =Source!P43 -> 2330477.2 | Q85: =Source!X42 -> 0 | R85: =Source!X43 -> 0 | S85: =Source!Y42 -> 0 | T85: =Source!Y43 -> 0 | U85: =ROUND((175/100)*ROUND(Source!R42, 2), 2) -> 0 | V85: =ROUND((0/100)*ROUND(Source!R43, 2), 2) -> 0 | AC85: 5
C86: ВСЕГО по позиции: | H86: =I85+0 -> 304239.85 | J86: =K85+0 -> 2330477.2 | O86: =I85+0 -> 304239.85 | P86: =K85+0 -> 2330477.2
A88: 9 | B88: =Source!F44 -> КА-5 | C88: ОБОРУДОВАНИЕ:_x000D_ Программное обеспечение TRASSIR ЕЦХД 20 298,35 = [179 000 / 1,2 / 7,66] + 3% Трансп + 1,2% Заг.скл | D88: =Source!H44 -> ШТ | E88: =Source!I44 -> 1 | F88: =Source!AL44 -> 20298.35 | G88: =Source!DD44 | H88: =Source!AW45 -> 1 | I88: =Source!P44 -> 20298.35 | J88: =IF(Source!BC45<> 0, Source!BC45, 1) -> 7.66 | K88: =Source!P45 -> 155485.36 | Q88: =Source!X44 -> 0 | R88: =Source!X45 -> 0 | S88: =Source!Y44 -> 0 | T88: =Source!Y45 -> 0 | U88: =ROUND((175/100)*ROUND(Source!R44, 2), 2) -> 0 | V88: =ROUND((0/100)*ROUND(Source!R45, 2), 2) -> 0 | AC88: 5
C89: ВСЕГО по позиции: | H89: =I88+0 -> 20298.35 | J89: =K88+0 -> 155485.36 | O89: =I88+0 -> 20298.35 | P89: =K88+0 -> 155485.36
A91: 10 | B91: =Source!F46 -> 4.10-34-5 | C91: Монтаж коммутатора служебной связи | D91: =Source!H46 -> 1 ШТ. | E91: =Source!I46 -> 9 | Q91: =Source!X46 -> 759.36 | R91: =Source!X47 -> 41757.04 | S91: =Source!Y46 -> 388.12 | T91: =Source!Y47 -> 21342.49 | U91: =ROUND((175/100)*ROUND(Source!R46, 2), 2) -> 57.31 | V91: =ROUND((0/100)*ROUND(Source!R47, 2), 2) -> 0 | AC91: 0
C92: ="Объем: "&Source!I46&"=1+"&"1+"&"7" -> Объем: 9=1+1+7
C93: ЗП | F93: =Source!AO46 -> 78.24 | G93: =Source!DG46 -> *1,1 | H93: =Source!AV47 -> 1.047 | I93: =Source!S46 -> 810.98 | J93: =IF(Source!BA47<> 0, Source!BA47, 1) -> 54.99 | K93: =Source!S47 -> 44595.79
C94: ЭМ | F94: =Source!AM46 -> 28.71 | G94: =Source!DE46 -> *1,1 | H94: =Source!AV47 -> 1.047 | I94: =Source!Q46 -> 297.59 | J94: =IF(Source!BB47<> 0, Source!BB47, 1) -> 15.46 | K94: =Source!Q47 -> 4600.74
C95: в т.ч. ЗПМ | F95: =Source!AN46 -> 3.16 | G95: =Source!DF46 -> *1,1 | H95: =Source!AV47 -> 1.047 | I95: =Source!R46 -> 32.75 | J95: =IF(Source!BS47<> 0, Source!BS47, 1) -> 54.99 | K95: =Source!R47 -> 1800.92
C96: МР | F96: =Source!AL46 -> 12.35 | G96: =Source!DD46 | H96: =Source!AW47 -> 1 | I96: =Source!P46 -> 111.15 | J96: =IF(Source!BC47<> 0, Source!BC47, 1) -> 14.7 | K96: =Source!P47 -> 1633.91
C97: НР от ФОТ | D97: % | E97: =Source!BZ47 -> 90 | I97: =SUM(Q91:Q96) -> 759.36 | J97: =Source!AT47 -> 90 | K97: =SUM(R91:R96) -> 41757.04
C98: СП от ФОТ | D98: % | E98: =Source!CA47 -> 46 | I98: =SUM(S91:S97) -> 388.12 | J98: =Source!AU47 -> 46 | K98: =SUM(T91:T97) -> 21342.49
C99: ЗТР | D99: чел-ч | E99: =Source!AQ46 -> 6.2 | G99: =Source!DI46 -> *1,1 | H99: =Source!AV47 -> 1.047 | I99: =Source!U46 -> 64.26486
C100: ВСЕГО работ по позиции: | H100: =I93+I94+I96+I97+I98+0-0-0 -> 2367.2 | J100: =K93+K94+K96+K97+K98+0-0-0 -> 113929.97
C101: ВСЕГО оборудование по позиции: | H101: =0+0 -> 0 | J101: =0+0 -> 0
C102: ВСЕГО по позиции: | H102: =I93+I94+I96+I97+I98+0 -> 2367.2 | J102: =K93+K94+K96+K97+K98+0 -> 113929.97 | O102: =I93+I94+I96+I97+I98+0 -> 2367.2 | P102: =K93+K94+K96+K97+K98+0 -> 113929.97
A104: 11 | B104: =Source!F48 -> КА-6 | C104: ОБОРУДОВАНИЕ:_x000D_ Коммутатор агрегации MES3300-16F 34 992,32 = [308 578 / 1,2 / 7,66] + 3% Трансп + 1,2% Заг.скл | D104: =Source!H48 -> ШТ | E104: =Source!I48 -> 1 | F104: =Source!AL48 -> 34992.32 | G104: =Source!DD48 | H104: =Source!AW49 -> 1 | I104: =Source!P48 -> 34992.32 | J104: =IF(Source!BC49<> 0, Source!BC49, 1) -> 7.66 | K104: =Source!P49 -> 268041.17 | Q104: =Source!X48 -> 0 | R104: =Source!X49 -> 0 | S104: =Source!Y48 -> 0 | T104: =Source!Y49 -> 0 | U104: =ROUND((175/100)*ROUND(Source!R48, 2), 2) -> 0 | V104: =ROUND((0/100)*ROUND(Source!R49, 2), 2) -> 0 | AC104: 5
C105: ВСЕГО по позиции: | H105: =I104+0 -> 34992.32 | J105: =K104+0 -> 268041.17 | O105: =I104+0 -> 34992.32 | P105: =K104+0 -> 268041.17
A107: 12 | B107: =Source!F50 -> КА-7 | C107: ОБОРУДОВАНИЕ:_x000D_ Коммутатор доступа 48 PoE MES2420-48P 53 571,20 = [472 415 / 1,2 / 7,66] + 3% Трансп + 1,2% Заг.скл | D107: =Source!H50 -> ШТ | E107: =Source!I50 -> 1 | F107: =Source!AL50 -> 53571.2 | G107: =Source!DD50 | H107: =Source!AW51 -> 1 | I107: =Source!P50 -> 53571.2 | J107: =IF(Source!BC51<> 0, Source!BC51, 1) -> 7.66 | K107: =Source!P51 -> 410355.39 | Q107: =Source!X50 -> 0 | R107: =Source!X51 -> 0 | S107: =Source!Y50 -> 0 | T107: =Source!Y51 -> 0 | U107: =ROUND((175/100)*ROUND(Source!R50, 2), 2) -> 0 | V107: =ROUND((0/100)*ROUND(Source!R51, 2), 2) -> 0 | AC107: 5
C108: ВСЕГО по позиции: | H108: =I107+0 -> 53571.2 | J108: =K107+0 -> 410355.39 | O108: =I107+0 -> 53571.2 | P108: =K107+0 -> 410355.39
A110: 13 | B110: =Source!F52 -> КА-8 | C110: ОБОРУДОВАНИЕ:_x000D_ Коммутатор доступа 24 PoE MES2300-24P 13 997,58 = [123 437 / 1,2 / 7,66] + 3% Трансп + 1,2% Заг.скл | D110: =Source!H52 -> ШТ | E110: =Source!I52 -> 7 | F110: =Source!AL52 -> 13997.58 | G110: =Source!DD52 | H110: =Source!AW53 -> 1 | I110: =Source!P52 -> 97983.06 | J110: =IF(Source!BC53<> 0, Source!BC53, 1) -> 7.66 | K110: =Source!P53 -> 750550.24 | Q110: =Source!X52 -> 0 | R110: =Source!X53 -> 0 | S110: =Source!Y52 -> 0 | T110: =Source!Y53 -> 0 | U110: =ROUND((175/100)*ROUND(Source!R52, 2), 2) -> 0 | V110: =ROUND((0/100)*ROUND(Source!R53, 2), 2) -> 0 | AC110: 5
C111: ВСЕГО по позиции: | H111: =I110+0 -> 97983.06 | J111: =K110+0 -> 750550.24 | O111: =I110+0 -> 97983.06 | P111: =K110+0 -> 750550.24
A113: 14 | B113: =Source!F54 -> 4.10-32-4 | C113: Монтаж платы дополнительной, устанавливаемой на готовом месте стойки | D113: =Source!H54 -> 1 ШТ. | E113: =Source!I54 -> 18 | Q113: =Source!X54 -> 456.92 | R113: =Source!X55 -> 25126.08 | S113: =Source!Y54 -> 233.54 | T113: =Source!Y55 -> 12842.22 | U113: =ROUND((175/100)*ROUND(Source!R54, 2), 2) -> 36.65 | V113: =ROUND((0/100)*ROUND(Source!R55, 2), 2) -> 0 | AC113: 0
C114: ЗП | F114: =Source!AO54 -> 23.48 | G114: =Source!DG54 -> *1,1 | H114: =Source!AV55 -> 1.047 | I114: =Source!S54 -> 486.75 | J114: =IF(Source!BA55<> 0, Source!BA55, 1) -> 54.99 | K114: =Source!S55 -> 26766.38
C115: ЭМ | F115: =Source!AM54 -> 9.19 | G115: =Source!DE54 -> *1,1 | H115: =Source!AV55 -> 1.047 | I115: =Source!Q54 -> 190.51 | J115: =IF(Source!BB55<> 0, Source!BB55, 1) -> 15.45 | K115: =Source!Q55 -> 2943.38
C116: в т.ч. ЗПМ | F116: =Source!AN54 -> 1.01 | G116: =Source!DF54 -> *1,1 | H116: =Source!AV55 -> 1.047 | I116: =Source!R54 -> 20.94 | J116: =IF(Source!BS55<> 0, Source!BS55, 1) -> 54.99 | K116: =Source!R55 -> 1151.49
C117: НР от ФОТ | D117: % | E117: =Source!BZ55 -> 90 | I117: =SUM(Q113:Q116) -> 456.92 | J117: =Source!AT55 -> 90 | K117: =SUM(R113:R116) -> 25126.08
C118: СП от ФОТ | D118: % | E118: =Source!CA55 -> 46 | I118: =SUM(S113:S117) -> 233.54 | J118: =Source!AU55 -> 46 | K118: =SUM(T113:T117) -> 12842.22
C119: ЗТР | D119: чел-ч | E119: =Source!AQ54 -> 2.1 | G119: =Source!DI54 -> *1,1 | H119: =Source!AV55 -> 1.047 | I119: =Source!U54 -> 43.53426
...

Sheet Ведомость объемов работ
A1: =Source!B1 -> Smeta.RU (495) 974-1589
B4: =CONCATENATE("Ведомость объемов работ ", IF(Source!AN15<>"", Source!AN15," ")) -> Ведомость объемов работ
B5: =CONCATENATE(Source!F12, " ", Source!G12) -> 02-01-14 СОТ
A8: № п/п | B8: № в ЛСР | C8: Наименование работ и затрат | D8: Единица измерения | E8: Количество | F8: Ссылка на чертежи, спецификации | G8: Формула расчета, расчет объемов работ и расхода материалов | H8: Примечание
A9: 1 | B9: 2 | C9: 3 | D9: 4 | E9: 5 | F9: 6 | G9: 7 | H9: 8
A10: =CONCATENATE("Локальная смета: ", Source!G20) -> Локальная смета: Система охранного теленаблюдения
A11: =CONCATENATE("Раздел: ", Source!G24) -> Раздел: Оборудование
A12: 1 | B12: =Source!E28 -> 1 | C12: =Source!G28 -> Монтаж внутренней камеры видеонаблюдения | D12: 10 шт. | E12: =Source!I28 -> 2.8 | F12: =Source!U24 | G12: ="=28/"&"10" -> =28/10
A13: 2 | B13: =Source!E30 -> 2 | C13: =Source!G30 -> Цилиндрическая IP-видеокамера с фиксированным объективом IP 2 Мп; 1/3" КМОП, 1920х1080-25/30к/с; встроенный микрофон; Дальность ИК подсветки 30м; объектив 2.8мм(3.6мм, 6ммопционально) ; режим "день/ночь", H264/ MJPEG ( Доп. поток) ; ; PoE 5 Вт; -40 ~ +60°C, TR-D2121CL3 4.0 | D13: ШТ | E13: =Source!I30 -> 28 | F13: =Source!U24 | G13: =Source!I30 -> 28
A14: 3 | B14: =Source!E32 -> 3 | C14: =Source!G32 -> Разные устройства, монтаж коробки телевизионной (ответвители, разветвители магистральные, домовые, абонентские), УСС, БФТК | D14: 1 ШТ. | E14: =Source!I32 -> 28 | F14: =Source!U24 | G14: =Source!I32 -> 28
A15: 4 | B15: =Source!E34 -> 4 | C15: =Source!G34 -> Устройство грозозащиты NST NS-LP-1GP/D | D15: ШТ | E15: =Source!I34 -> 28 | F15: =Source!U24 | G15: =Source!I34 -> 28
A16: 5 | B16: =Source!E36 -> 5 | C16: =Source!G36 -> Монтаж наружной камеры видеонаблюдения | D16: 10 шт. | E16: =Source!I36 -> 10.9 | F16: =Source!U24 | G16: ="=109/"&"10" -> =109/10
A17: 6 | B17: =Source!E38 -> 6 | C17: =Source!G38 -> Купольная IP-видеокамера с фиксированным объективом IP 2 Мп; 1/2.8" КМОП, 1920х1080-25/30к/с; встроенный микрофон; Дальность ИК подсветки 25м; объектив 2.8мм(3.6мм, 6ммопционально) ; режим "день/ночь", H264/ MJPEG ( Доп. поток) ; ; PoE 5 Вт; TR-D2D2 v2 2.7-13.5 | D17: ШТ | E17: =Source!I38 -> 109 | F17: =Source!U24 | G17: =Source!I38 -> 109
A18: 7 | B18: =Source!E40 -> 7 | C18: =Source!G40 -> Монтаж устройства цифровой регистрации | D18: 1 устройство | E18: =Source!I40 -> 1 | F18: =Source!U24 | G18: =Source!I40 -> 1
A19: 8 | B19: =Source!E42 -> 8 | C19: =Source!G42 -> IP-видеорегистратор UltraStation 24/10 на 256 каналов, 24 HDD на 10 Тбайт UltraStation 24/10 256 v2 с 24 HDD | D19: ШТ | E19: =Source!I42 -> 1 | F19: =Source!U24 | G19: =Source!I42 -> 1
A20: 9 | B20: =Source!E44 -> 9 | C20: =Source!G44 -> Программное обеспечение TRASSIR ЕЦХД | D20: ШТ | E20: =Source!I44 -> 1 | F20: =Source!U24 | G20: =Source!I44 -> 1
A21: 10 | B21: =Source!E46 -> 10 | C21: =Source!G46 -> Монтаж коммутатора служебной связи | D21: 1 ШТ. | E21: =Source!I46 -> 9 | F21: =Source!U24 | G21: ="=1+"&"1+"&"7" -> =1+1+7
A22: 11 | B22: =Source!E48 -> 11 | C22: =Source!G48 -> Коммутатор агрегации MES3300-16F | D22: ШТ | E22: =Source!I48 -> 1 | F22: =Source!U24 | G22: =Source!I48 -> 1
A23: 12 | B23: =Source!E50 -> 12 | C23: =Source!G50 -> Коммутатор доступа 48 PoE MES2420-48P | D23: ШТ | E23: =Source!I50 -> 1 | F23: =Source!U24 | G23: =Source!I50 -> 1
A24: 13 | B24: =Source!E52 -> 13 | C24: =Source!G52 -> Коммутатор доступа 24 PoE MES2300-24P | D24: ШТ | E24: =Source!I52 -> 7 | F24: =Source!U24 | G24: =Source!I52 -> 7
A25: 14 | B25: =Source!E54 -> 14 | C25: =Source!G54 -> Монтаж платы дополнительной, устанавливаемой на готовом месте стойки | D25: 1 ШТ. | E25: =Source!I54 -> 18 | F25: =Source!U24 | G25: =Source!I54 -> 18
A26: 15 | B26: =Source!E56 -> 15 | C26: =Source!G56 -> SFP 1,25 GE модуль 550 м, ММ, 2 волокна, 850 пт, LC, DDM FH-S8512CDL05 | D26: ШТ | E26: =Source!I56 -> 18 | F26: =Source!U24 | G26: =Source!I56 -> 18
A27: 16 | B27: =Source!E58 -> 16 | C27: =Source!G58 -> Монтаж платы дополнительной, устанавливаемой на готовом месте стойки | D27: 1 ШТ. | E27: =Source!I58 -> 3 | F27: =Source!U24 | G27: =Source!I58 -> 3
A28: 17 | B28: =Source!E60 -> 17 | C28: =Source!G60 -> Грозозащита для локальной вычислительной сети, 16 GE RJ-45 SP-IP16/1000PR | D28: ШТ | E28: =Source!I60 -> 3 | F28: =Source!U24 | G28: =Source!I60 -> 3
A29: 18 | B29: =Source!E62 -> 18 | C29: =Source!G62 -> Монтаж аппаратуры настенной | D29: 1 ШТ. | E29: =Source!I62 -> 4 | F29: =Source!U24 | G29: =Source!I62 -> 4
A30: 19 | B30: =Source!E64 -> 19 | C30: =Source!G64 -> Кронштейн настенного крепления RDW 2701K | D30: ШТ | E30: =Source!I64 -> 4 | F30: =Source!U24 | G30: =Source!I64 -> 4
A31: 20 | B31: =Source!E66 -> 20 | C31: =Source!G66 -> Монитор RDW 2701K | D31: ШТ | E31: =Source!I66 -> 4 | F31: =Source!U24 | G31: =Source!I66 -> 4
A32: 21 | B32: =Source!E68 -> 21 | C32: =Source!G68 -> Монтаж аппаратуры настольной массой до 20 кг | D32: 1 ШТ. | E32: =Source!I68 -> 1 | F32: =Source!U24 | G32: =Source!I68 -> 1
A33: 22 | B33: =Source!E70 -> 22 | C33: =Source!G70 -> Рабочая станция DEPO Race VT955 | D33: ШТ | E33: =Source!I70 -> 1 | F33: =Source!U24 | G33: =Source!I70 -> 1
A34: 23 | B34: =Source!E72 -> 23 | C34: =Source!G72 -> Монтаж блока бесперебойного питания (ББП) в диспетчерской | D34: 1 ШТ. | E34: =Source!I72 -> 8 | F34: =Source!U24 | G34: =Source!I72 -> 8
A35: 24 | B35: =Source!E74 -> 24 | C35: =Source!G74 -> Источник бесперебойного питания 3000 ВА/2700 Вт SKAT-UPS 3000-RACK-ON-6x9-E | D35: ШТ | E35: =Source!I74 -> 8 | F35: =Source!U24 | G35: =Source!I74 -> 8
A36: 25 | B36: =Source!E76 -> 25 | C36: =Source!G76 -> Батарейный блок 18Ач/72В SKAT BC 72/18S3 RACK | D36: ШТ | E36: =Source!I76 -> 2 | F36: =Source!U24 | G36: =Source!I76 -> 2
A37: =CONCATENATE("Раздел: ", Source!G109) -> Раздел: Материалы и кабельные изделия
A38: 26 | B38: =Source!E113 -> 26 | C38: =Source!G113 -> Установка съемных и выдвижных блоков (модулей, ячеек, ТЭЗ) массой до 5 кг | D38: 1 ШТ. | E38: =Source!I113 -> 18 | F38: =Source!U109 | G38: ="=2+"&"8+"&"1+"&"7" -> =2+8+1+7
A39: 27 | B39: =Source!E115 -> 27 | C39: =Source!G115 -> Оптический распределительный кросс укомплектованный: LC (Duplex) 24 шт, (ОМЗ) FOBX24-1U-24LCUD03 | D39: ШТ | E39: =Source!I115 -> 2 | F39: =Source!U109 | G39: =Source!I115 -> 2
A40: 28 | B40: =Source!E117 -> 28 | C40: =Source!G117 -> Оптический распределительный кросс укомплектованный: LC (Duplex) 8 шт, (ОМЗ) FOBX24-1U-8LCUD03 | D40: ШТ | E40: =Source!I117 -> 8 | F40: =Source!U109 | G40: =Source!I117 -> 8
A41: 29 | B41: =Source!E119 -> 29 | C41: =Source!G119 -> 1U патч-панель кат.5E UTP 48 портов (DUAL IDC) высокой плотности PP48-1UC5EU-D05H | D41: ШТ | E41: =Source!I119 -> 1 | F41: =Source!U109 | G41: =Source!I119 -> 1
A42: 30 | B42: =Source!E121 -> 30 | C42: =Source!G121 -> 1U патч-панель кат.5E UTP 24портов (DUAL IDC) высокой плотности PP24-1UC5EU-D05-1 | D42: ШТ | E42: =Source!I121 -> 7 | F42: =Source!U109 | G42: =Source!I121 -> 7
A43: =CONCATENATE("Раздел: ", Source!G154) -> Раздел: Кабельные изделия
A44: 31 | B44: =Source!E158 -> 31 | C44: =Source!G158 -> Трубы гофрированные поливинилхлоридные наружным диаметром 20 мм открыто по стенам и потолкам с установкой соединительных коробок | D44: 100 м | E44: =Source!I158 -> 30 | F44: =Source!U154 | G44: ="=3000/"&"100" -> =3000/100
A45: 32 | B45: =Source!E162 -> 32 | C45: =Source!G162 -> Затягивание провода в проложенные трубы и металлические рукава, первого одножильного или многожильного в общей оплетке, суммарное сечение до 6 мм2 | D45: 100 м | E45: =Source!I162 -> 30 | F45: =Source!U154 | G45: ="=3000/"&"100" -> =3000/100
A46: 33 | B46: =Source!E164 -> 33 | C46: =Source!G164 -> Добавлять на затягивание провода в проложенные трубы и металлические рукава каждого последующего одножильного или многожильного в общей оплетке, суммарное сечение до 6 мм2 (к нормам и расценкам 4.8-175-1 и 4.8-175-2) | D46: 100 м | E46: =Source!I164 -> 38.2 | F46: =Source!U154 | G46: ="=((500+"&"6320)-"&"3000)/"&"100" -> =((500+6320)-3000)/100
A47: 34 | B47: =Source!E166 -> 34 | C47: =Source!G166 -> Волоконно-оптический кабель, 8 волокон, многомод 50/125 мкм ОБР-В-нг(Ф)-HFLTx 8 G/651 400H | D47: км | E47: =Source!I166 -> 0.51 | F47: =Source!U154 | G47: ="=(500*"&"1,02)/"&"1000" -> =(500*1,02)/1000
A48: 35 | B48: =Source!E168 -> 35 | C48: =Source!G168 -> Кабель витая пара ParLan U/UTP Cat5e PVCLS нг(А)-LSLTx 4x20,52 | D48: км | E48: =Source!I168 -> 6.4464 | F48: =Source!U154 | G48: ="=(6320*"&"1,02)/"&"1000" -> =(6320*1,02)/1000
A49: 36 | B49: =Source!E170 -> 36 | C49: =Source!G170 -> Шнур оптический соединительный (патч-корд), тип разъемов LC/UPC-SC/UPC, 9/125 мкм, одномодовый, дуплексный, оболочка LSZH, длина 1 м | D49: шт. | E49: =Source!I170 -> 20 | F49: =Source!U154 | G49: =Source!I170 -> 20
A50: 37 | B50: =Source!E172 -> 37 | C50: =Source!G172 -> Шнур коммутационный (патч-корд) тип разъемов RJ45 - RJ45, категория 5E, оболочка LSZH, длина 1 м, неэкранированный | D50: шт. | E50: =Source!I172 -> 150 | F50: =Source!U154 | G50: =Source!I172 -> 150
C53: Главный инженер проекта _________________ | D53: =IF(Source!X12<>"", Source!X12," ")
C55: Составил _________________ | D55: =IF(Source!AB12<>"", Source!AB12," ") -> Соколова И.Н.

Sheet Source
A1: 0 | B1: Smeta.RU (495) 974-1589 | D1: _PS_ | F1: 0 | G1: 0 | H1: 0 | I1: Smeta.RU | K1: 1 | L1: 74563 | M1: 10 | N1: 12 | O1: 0 | P1: 0 | Q1: 3
A4: 1 | B4: 1 | C4: -1 | G4: Капитальный ремонт здания Государственного бюджетного общеобразовательного учреждения города Москвы "Школа №236" по адресу: г. Москва, улица Клязьминская, дом 7, корпус 4 | EC4: 0
A12: 1 | B12: 274 | C12: 0 | D12: =ROW(A235) -> 235 | E12: 0 | G12: 02-01-14 СОТ | I12: 0 | J12: 2024-00281-00-ИОС5.7 | K12: 0 | L12: 0 | M12: 4098 | O12: 0 | P12: 0 | Q12: 0 | R12: 0 | S12: 0 | T12: 1 | V12: 0 | AB12: Соколова И.Н. | BB12: 0 | BH12: Сметные нормы списания | BI12: Коды ОКП для ТСН-2001 МГЭ Дополнение 80 | BJ12: 1 | BK12: 1 | BL12: 0 | BM12: 0 | BN12: 1 | BO12: 0 | BP12: 6 | BQ12: 2 | BR12: 1 | BS12: 1 | BT12: 0 | BU12: 0 | BV12: 0 | BW12: 0 | BX12: 0 | BZ12: Типовой расчет для ТСН-2001 МГЭ, Дополнение 80, строительство (1) | CA12: Территориальные сметные нормативы для Москвы ТСН-2001 (МГЭ), дополнение 80 | CB12: Территориальные сметные нормативы для Москвы ТСН-2001 (МГЭ), дополнение 80 | CC12: Территориальные сметные нормативы для Москвы ТСН-2001 (МГЭ), дополнение 80 | CD12: Территориальные сметные нормативы для Москвы ТСН-2001 (МГЭ), дополнение 80 | CE12: Поправки для ТСН-2001 от 28.11.2025 г. доп.79 | CF12: 0 | CG12: 0 | CH12: 8200 | CK12: 80 | CQ12: Территориальные сметные нормативы для Москвы (ТСН-2001) | CR12: ТЕР | CS12: 41660 | CT12: 1 | CU12: 80 | CY12: 0 | EC12: 0
A15: 15 | B15: 1
A18: 52 | B18: =B235 -> 274 | C18: =C235 -> 1 | D18: =D235 -> 12 | E18: =E235 -> 0 | F18: =F235 | G18: =G235 -> 02-01-14 СОТ | O18: =O235 -> 1018066.3 | P18: =P235 -> 997324.72 | Q18: =Q235 -> 1999.81 | R18: =R235 -> 291.77 | S18: =S235 -> 18741.81 | T18: =T235 -> 0 | U18: =U235 -> 1399.7195 | V18: =V235 -> 0 | ... GX18: =GX235 -> 0
A20: 3 | B20: 1 | D20: =ROW(A205) -> 205 | F20: 02-01-14 | G20: Система охранного теленаблюдения | I20: 0 | J20: 2024-00281-00-ИОС5.7 | K20: -1 | L20: 02-01-14 | S20: 0 | T20: 0 | V20: 2 | BX20: 0 | CF20: 0 | CG20: 0
A22: 52 | B22: =B205 -> 1 | C22: =C205 -> 3 | D22: =D205 -> 20 | E22: =E205 -> 0 | F22: =F205 -> 02-01-14 | G22: =G205 -> Система охранного теленаблюдения | O22: =O205 -> 1018066.3 | P22: =P205 -> 997324.72 | Q22: =Q205 -> 1999.81 | R22: =R205 -> 291.77 | S22: =S205 -> 18741.81 | T22: =T205 -> 0 | U22: =U205 -> 1399.7195 | V22: =V205 -> 0 | ... GX22: =GX205 -> 0
A24: 4 | B24: 1 | D24: =ROW(A79) -> 79 | G24: Оборудование | I24: 0 | K24: -1 | S24: 0 | T24: 0 | V24: 2 | BX24: 0 | CJ24: 0
A26: 52 | B26: =B79 -> 1 | C26: =C79 -> 4 | D26: =D79 -> 24 | E26: =E79 -> 0 | F26: =F79 | G26: =G79 -> Оборудование | O26: =O79 -> 899801.87 | P26: =P79 -> 890668.32 | Q26: =Q79 -> 557.09 | R26: =R79 -> 59.23 | S26: =S79 -> 8576.46 | T26: =T79 -> 0 | U26: =U79 -> 593.36134 | V26: =V79 -> 0 | ... GX26: =GX79 -> 0
A28: 17 | B28: 1 | C28: =ROW(SmtRes!A6) -> 6 | D28: =ROW(EtalonRes!A7) -> 7 | E28: 1 | F28: 4.10-174-1 | G28: Монтаж внутренней камеры видеонаблюдения | H28: 10 шт. | I28: =ROUND(28/10,9) -> 2.8 | J28: 0 | K28: =ROUND(28/10,9) -> 2.8 | O28: =ROUND(CP28,2) -> 924.51 | P28: =ROUND((ROUND((AC28*AW28*I28),2)*BC28),2) -> 119.03 | Q28: =(ROUND((ROUND((((ET28*1.1))*AV28*I28),2)*BB28),2)+ROUND((ROUND(((AE28-((EU28*1.1)))*AV28*I28),2)*BS28),2)) -> 7.61 | R28: =(ROUND((ROUND((((EU28*1.1))*AV28*I28),2)*BS28),2)+ROUND((ROUND(((AE28-((EU28*1.1)))*AV28*I28),2)*BS28),2)) -> 0.42 | S28: =ROUND((ROUND((AF28*AV28*I28),2)*BA28),2) -> 797.87 | T28: =ROUND(CU28*I28,2) -> 0 | U28: =CV28*I28 -> 50.11277 | V28: =CW28*I28 -> 0 | W28: =ROUND(CX28*I28,2) -> 0 | X28: =(ROUND((((S28+ROUND((ROUND((((EU28*1.1))*AV28*I28),2)*BS28),2))*AT28)/100),2)+ROUND(((ROUND((ROUND(((AE28-((EU28*1.1)))*AV28*I28),2)*BS28),2)*AT28)/100),2)) -> 718.46 | Y28: =(ROUND((((S28+ROUND((ROUND((((EU28*1.1))*AV28*I28),2)*BS28),2))*AU28)/100),2)+ROUND(((ROUND((ROUND(((AE28-((EU28*1.1)))*AV28*I28),2)*BS28),2)*AU28)/100),2)) -> 367.21 | AA28: 60258064 | AB28: =ROUND((AC28+AD28+AF28),6) -> 317.268 | AC28: =ROUND((ES28),6) -> 42.51 | AD28: =ROUND(((((ET28*1.1))-((EU28*1.1)))+AE28),6) -> 2.596 | AE28: =ROUND(((EU28*1.1)),6) -> 0.143 | AF28: =ROUND(((EV28*1.1)),6) -> 272.162 | AG28: =ROUND((AP28),6) -> 0 | AH28: =((EW28*1.1)) -> 17.094 | AI28: =((EX28*1.1)) -> 0 | AJ28: =(AS28) -> 0 | AK28: 292.29 | AL28: 42.51 | AM28: 2.36 | AN28: 0.13 | AO28: 247.42 | AP28: 0 | AQ28: 15.54 | AR28: 0 | AS28: 0 | AT28: 90 | AU28: 46 | AV28: 1.047 | AW28: 1 | AZ28: 1 | BA28: 1 | BB28: 1 | BC28: 1 | BH28: 0 | BI28: 2 | BJ28: ТСН-2001.4 Доп. 68, Сб. 10, т. 174, поз. 1 | BM28: 68 | BN28: 58973116 | BO28: 4.10-174-1 | BP28: 1 | BQ28: 40 | BR28: 0 | BS28: 1 | BT28: 1 | BU28: 1 | BV28: 1 | BW28: 1 | BX28: 1 | BZ28: 90 | CA28: 46 | CE28: 1566 | CF28: 0 | CG28: 0 | CM28: 0 | CN28: Поправка: О.П. п.3.4.30.в Наименование: При применении территориальных сметных нормативов для города Москвы затраты, учитывающие напряженные и стесненные условия производства работ (стесненность, сложность складирования и транспортной логистики и т.п.), исчисляются с применением коэффициентов к затратам труда и заработной плате рабочих, машинистов, времени эксплуатации машин и механизмов, стоимости эксплуатации машин в размере: для объектов, расположенных за пределами Третьего транспортного кольца города Москвы, но в пределах Московской кольцевой автомобильной дороги | CO28: 0 | CP28: =(P28+Q28+S28) -> 924.51 | CQ28: =ROUND((ROUND((AC28*AW28*1),2)*BC28),2) -> 42.51 | CR28: =(ROUND((ROUND((((ET28*1.1))*AV28*1),2)*BB28),2)+ROUND((ROUND(((AE28-((EU28*1.1)))*AV28*1),2)*BS28),2)) -> 2.72 | CS28: =(ROUND((ROUND((((EU28*1.1))*AV28*1),2)*BS28),2)+ROUND((ROUND(((AE28-((EU28*1.1)))*AV28*1),2)*BS28),2)) -> 0.15 | CT28: =ROUND((ROUND((AF28*AV28*1),2)*BA28),2) -> 284.95 | CU28: =AG28 -> 0 | CV28: =(AH28*AV28) -> 17.897418 | CW28: =AI28 -> 0 | CX28: =AJ28 -> 0 | CY28: =(ROUND((((S28+ROUND((ROUND((((EU28*1.1))*AV28*1),2)*BS28),2))*AT28)/100),2)+ROUND(((ROUND((ROUND(((AE28-((EU28*1.1)))*AV28*1),2)*BS28),2)*AT28)/100),2)) -> 718.22 | CZ28: =(ROUND((((S28+ROUND((ROUND((((EU28*1.1))*AV28*1),2)*BS28),2))*AU28)/100),2)+ROUND(((ROUND((ROUND(((AE28-((EU28*1.1)))*AV28*1),2)*BS28),2)*AU28)/100),2)) -> 367.09 | DB28: 1 | DE28: *1,1 | DF28: *1,1 | DG28: *1,1 | DI28: *1,1 | DJ28: *1,1 | DN28: 0 | DO28: 0 | DP28: 1 | DQ28: 1 | DU28: 1010 | DV28: 10 шт. | DW28: 10 шт. | DX28: 10 | EE28: 60088532 | EF28: 40 | EG28: Монтаж оборудования | EH28: 0 | EJ28: 2 | EK28: 68 | EL28: ТСН-2001.4-10. Прокладка и монтаж сетей связи | EM28: ТСН-2001.4-10-1 | EO28: Поправка: О.П. п.3.4.30.в | EQ28: 0 | ER28: 292.29 | ES28: 42.51 | ET28: 2.36 | EU28: 0.13 | EV28: 247.42 | EW28: 15.54 | EX28: 0 | EY28: 0 | FQ28: 0 | FR28: 0 | FS28: 0 | FX28: 90 | FY28: 46 | GD28: 1 | GF28: -1957665847 | GG28: 2 | GH28: 1 | GI28: 2 | GJ28: 0 | GK28: 0 | GL28: =ROUND(IF(AND(BH28=3,BI28=3,FS28<>0),P28,0),2) -> 0 | GM28: =ROUND(O28+X28+Y28,2)+GX28 -> 2010.18 | GN28: =IF(OR(BI28=0,BI28=1),GM28-GX28,0) -> 0 | GO28: =IF(BI28=2,GM28-GX28,0) -> 2010.18 | GP28: =IF(BI28=4,GM28-GX28,0) -> 0 | GR28: 0 | GS28: 3 | GT28: 0 | GV28: =ROUND((GT28),6) -> 0 | GW28: 1 | GX28: =ROUND(HC28*I28,2) -> 0 | HA28: 0 | HB28: 0 | HC28: =GV28*GW28 -> 0 | HS28: 0 | IK28: 0
A29: 17 | B29: 1 | C29: =ROW(SmtRes!A12) -> 12 | D29: =ROW(EtalonRes!A14) -> 14 | E29: 1 | F29: 4.10-174-1 | G29: Монтаж внутренней камеры видеонаблюдения | H29: 10 шт. | I29: =ROUND(28/10,9) -> 2.8 | J29: 0 | K29: =ROUND(28/10,9) -> 2.8 | O29: =ROUND(CP29,2) -> 44191.05 | P29: =ROUND((ROUND((AC29*AW29*I29),2)*BC29),2) -> 229.73 | Q29: =(ROUND((ROUND((((ET29*1.1))*AV29*I29),2)*BB29),2)+ROUND((ROUND(((AE29-((EU29*1.1)))*AV29*I29),2)*BS29),2)) -> 86.45 | R29: =(ROUND((ROUND((((EU29*1.1))*AV29*I29),2)*BS29),2)+ROUND((ROUND(((AE29-((EU29*1.1)))*AV29*I29),2)*BS29),2)) -> 23.1 | S29: =ROUND((ROUND((AF29*AV29*I29),2)*BA29),2) -> 43874.87 | T29: =ROUND(CU29*I29,2) -> 0 | U29: =CV29*I29 -> 50.11277 | V29: =CW29*I29 -> 0 | W29: =ROUND(CX29*I29,2) -> 0 | X29: =(ROUND((((S29+ROUND((ROUND((((EU29*1.1))*AV29*I29),2)*BS29),2))*AT29)/100),2)+ROUND(((ROUND((ROUND(((AE29-((EU29*1.1)))*AV29*I29),2)*BS29),2)*AT29)/100),2)) -> 39508.17 | Y29: =(ROUND((((S29+ROUND((ROUND((((EU29*1.1))*AV29*I29),2)*BS29),2))*AU29)/100),2)+ROUND(((ROUND((ROUND(((AE29-((EU29*1.1)))*AV29*I29),2)*BS29),2)*AU29)/100),2)) -> 20193.07 | AA29: 60258061 | AB29: =ROUND((AC29+AD29+AF29),6) -> 317.268 | AC29: =ROUND((ES29),6) -> 42.51 | AD29: =ROUND(((((ET29*1.1))-((EU29*1.1)))+AE29),6) -> 2.596 | AE29: =ROUND(((EU29*1.1)),6) -> 0.143 | AF29: =ROUND(((EV29*1.1)),6) -> 272.162 | AG29: =ROUND((AP29),6) -> 0 | AH29: =((EW29*1.1)) -> 17.094 | AI29: =((EX29*1.1)) -> 0 | AJ29: =(AS29) -> 0 | AK29: 292.29 | AL29: 42.51 | AM29: 2.36 | AN29: 0.13 | AO29: 247.42 | AP29: 0 | AQ29: 15.54 | AR29: 0 | AS29: 0 | AT29: 90 | AU29: 46 | AV29: 1.047 | AW29: 1 | AZ29: 1 | BA29: 54.99 | BB29: 11.36 | BC29: 1.93 | BH29: 0 | BI29: 2 | BJ29: ТСН-2001.4 Доп. 68, Сб. 10, т. 174, поз. 1 | BM29: 68 | BN29: 58973116 | BO29: 4.10-174-1 | BP29: 1 | BQ29: 40 | BR29: 0 | BS29: 54.99 | BT29: 1 | BU29: 1 | BV29: 1 | BW29: 1 | BX29: 1 | BZ29: 90 | CA29: 46 | CE29: 1566 | CF29: 0 | CG29: 0 | CM29: 0 | CN29: Поправка: О.П. п.3.4.30.в Наименование: При применении территориальных сметных нормативов для города Москвы затраты, учитывающие напряженные и стесненные условия производства работ (стесненность, сложность складирования и транспортной логистики и т.п.), исчисляются с применением коэффициентов к затратам труда и заработной плате рабочих, машинистов, времени эксплуатации машин и механизмов, стоимости эксплуатации машин в размере: для объектов, расположенных за пределами Третьего транспортного кольца города Москвы, но в пределах Московской кольцевой автомобильной дороги | CO29: 0 | CP29: =(P29+Q29+S29) -> 44191.05 | CQ29: =ROUND((ROUND((AC29*AW29*1),2)*BC29),2) -> 82.04 | CR29: =(ROUND((ROUND((((ET29*1.1))*AV29*1),2)*BB29),2)+ROUND((ROUND(((AE29-((EU29*1.1)))*AV29*1),2)*BS29),2)) -> 30.9 | CS29: =(ROUND((ROUND((((EU29*1.1))*AV29*1),2)*BS29),2)+ROUND((ROUND(((AE29-((EU29*1.1)))*AV29*1),2)*BS29),2)) -> 8.25 | CT29: =ROUND((ROUND((AF29*AV29*1),2)*BA29),2) -> 15669.4 | CU29: =AG29 -> 0 | CV29: =(AH29*AV29) -> 17.897418 | CW29: =AI29 -> 0 | CX29: =AJ29 -> 0 | CY29: =(ROUND((((S29+ROUND((ROUND((((EU29*1.1))*AV29*1),2)*BS29),2))*AT29)/100),2)+ROUND(((ROUND((ROUND(((AE29-((EU29*1.1)))*AV29*1),2)*BS29),2)*AT29)/100),2)) -> 39494.81 | CZ29: =(ROUND((((S29+ROUND((ROUND((((EU29*1.1))*AV29*1),2)*BS29),2))*AU29)/100),2)+ROUND(((ROUND((ROUND(((AE29-((EU29*1.1)))*AV29*1),2)*BS29),2)*AU29)/100),2)) -> 20186.24 | DB29: 2 | DE29: *1,1 | DF29: *1,1 | DG29: *1,1 | DI29: *1,1 | DJ29: *1,1 | DN29: 0 | DO29: 0 | DP29: 1 | DQ29: 1 | DU29: 1010 | DV29: 10 шт. | DW29: 10 шт. | DX29: 10 | EE29: 60088532 | EF29: 40 | EG29: Монтаж оборудования | EH29: 0 | EJ29: 2 | EK29: 68 | EL29: ТСН-2001.4-10. Прокладка и монтаж сетей связи | EM29: ТСН-2001.4-10-1 | EO29: Поправка: О.П. п.3.4.30.в | EQ29: 0 | ER29: 292.29 | ES29: 42.51 | ET29: 2.36 | EU29: 0.13 | EV29: 247.42 | EW29: 15.54 | EX29: 0 | EY29: 0 | FQ29: 0 | FR29: 0 | FS29: 0 | FX29: 90 | FY29: 46 | GD29: 1 | GF29: -1957665847 | GG29: 2 | GH29: 1 | GI29: 2 | GJ29: 0 | GK29: 0 | GL29: =ROUND(IF(AND(BH29=3,BI29=3,FS29<>0),P29,0),2) -> 0 | GM29: =ROUND(O29+X29+Y29,2)+GX29 -> 103892.29 | GN29: =IF(OR(BI29=0,BI29=1),GM29-GX29,0) -> 0 | GO29: =IF(BI29=2,GM29-GX29,0) -> 103892.29 | GP29: =IF(BI29=4,GM29-GX29,0) -> 0 | GR29: 0 | GS29: 3 | GT29: 0 | GV29: =ROUND((GT29),6) -> 0 | GW29: 1 | GX29: =ROUND(HC29*I29,2) -> 0 | HA29: 0 | HB29: 0 | HC29: =GV29*GW29 -> 0 | HS29: 0 | IK29: 0
A30: 17 | B30: 1 | E30: 2 | F30: КА-1 | G30: Цилиндрическая IP-видеокамера с фиксированным объективом IP 2 Мп; 1/3" КМОП, 1920х1080-25/30к/с; встроенный микрофон; Дальность ИК подсветки 30м; объектив 2.8мм(3.6мм, 6ммопционально) ; режим "день/ночь", H264/ MJPEG ( Доп. поток) ; ; PoE 5 Вт; -40 ~ +60°C, TR-D2121CL3 4.0 | H30: ШТ | I30: 28 | J30: 0 | K30: 28 | O30: =ROUND(CP30,2) -> 28309.68 | P30: =ROUND((ROUND((AC30*I30),2)*BC30),2) -> 28309.68 | Q30: =(ROUND((ROUND(((ET30)*AV30*I30),2)*BB30),2)+ROUND((ROUND(((AE30-(EU30))*AV30*I30),2)*BS30),2)) -> 0 | R30: =(ROUND((ROUND(((EU30)*AV30*I30),2)*BS30),2)+ROUND((ROUND(((AE30-(EU30))*AV30*I30),2)*BS30),2)) -> 0 | S30: =ROUND((ROUND((AF30*AV30*I30),2)*BA30),2) -> 0 | T30: =ROUND(CU30*I30,2) -> 0 | U30: =CV30*I30 -> 0 | V30: =CW30*I30 -> 0 | W30: =ROUND(CX30*I30,2) -> 0 | X30: =(ROUND((((S30+ROUND((ROUND(((EU30)*AV30*I30),2)*BS30),2))*AT30)/100),2)+ROUND(((ROUND((ROUND(((AE30-(EU30))*AV30*I30),2)*BS30),2)*AT30)/100),2)) -> 0 | Y30: =(ROUND((((S30+ROUND((ROUND(((EU30)*AV30*I30),2)*BS30),2))*AU30)/100),2)+ROUND(((ROUND((ROUND(((AE30-(EU30))*AV30*I30),2)*BS30),2)*AU30)/100),2)) -> 0 | AA30: 60258064 | AB30: =ROUND((AC30+AD30+AF30),6) -> 1011.06 | AC30: =ROUND((ES30),6) -> 1011.06 | AD30: =ROUND((((ET30)-(EU30))+AE30),6) -> 0 | AE30: =ROUND((EU30),6) -> 0 | AF30: =ROUND((EV30),6) -> 0 | AG30: =ROUND((AP30),6) -> 0 | AH30: =(EW30) -> 0 | AI30: =(EX30) -> 0 | AJ30: =(AS30) -> 0 | AK30: 1011.06 | AL30: 1011.06 | AM30: 0 | AN30: 0 | AO30: 0 | AP30: 0 | AQ30: 0 | AR30: 0 | AS30: 0 | AT30: 0 | AU30: 0 | AV30: 1 | AW30: 1 | AZ30: 1 | BA30: 1 | BB30: 1 | BC30: 1 | BH30: 3 | BI30: 3 | BM30: 746 | BN30: 0 | BP30: 0 | BQ30: 130 | BR30: 0 | BS30: 1 | BT30: 1 | BU30: 1 | BV30: 1 | BW30: 1 | BX30: 1 | BZ30: 0 | CA30: 0 | CE30: 1566 | CF30: 0 | CG30: 0 | CM30: 0 | CO30: 0 | CP30: =(P30+Q30+S30) -> 28309.68 | CQ30: =ROUND((ROUND((AC30*1),2)*BC30),2) -> 1011.06 | CR30: =(ROUND((ROUND(((ET30)*AV30*1),2)*BB30),2)+ROUND((ROUND(((AE30-(EU30))*AV30*1),2)*BS30),2)) -> 0 | CS30: =(ROUND((ROUND(((EU30)*AV30*1),2)*BS30),2)+ROUND((ROUND(((AE30-(EU30))*AV30*1),2)*BS30),2)) -> 0 | CT30: =ROUND((ROUND((AF30*AV30*1),2)*BA30),2) -> 0 | CU30: =AG30 -> 0 | CV30: =(AH30*AV30) -> 0 | CW30: =AI30 -> 0 | CX30: =AJ30 -> 0 | CY30: =(ROUND((((S30+ROUND((ROUND(((EU30)*AV30*1),2)*BS30),2))*AT30)/100),2)+ROUND(((ROUND((ROUND(((AE30-(EU30))*AV30*1),2)*BS30),2)*AT30)/100),2)) -> 0 | CZ30: =(ROUND((((S30+ROUND((ROUND(((EU30)*AV30*1),2)*BS30),2))*AU30)/100),2)+ROUND(((ROUND((ROUND(((AE30-(EU30))*AV30*1),2)*BS30),2)*AU30)/100),2)) -> 0 | DN30: 0 | DO30: 0 | DP30: 1 | DQ30: 1 | DU30: 1013 | DV30: ШТ | DW30: ШТ | DX30: 1 | EE30: 60088638 | EF30: 130 | EG30: Сметная стоимость оборудования | EH30: 0 | EJ30: 3 | EK30: 746 | EL30: ТСН-2001.13. Сметная стоимость оборудования | EM30: ТСН-2001.13 | EQ30: 0 | ER30: 0 | ES30: 1011.06 | ET30: 0 | EU30: 0 | EV30: 0 | EW30: 0 | EX30: 0 | EY30: 0 | FQ30: 0 | FR30: =P30 -> 28309.68 | FS30: 0 | FX30: 0 | FY30: 0 | GA30: [8 916 / 1,2 / 7,66] + 3% Трансп + 1,2% Заг.скл | GD30: 1 | GF30: -1132090366 | GG30: 2 | GH30: 4 | GI30: -2 | GJ30: 0 | GK30: 0 | GL30: =ROUND(IF(AND(BH30=3,BI30=3,FS30<>0),P30,0),2) -> 0 | GM30: =ROUND(O30+X30+Y30,2)+GX30 -> 28309.68 | GN30: =IF(OR(BI30=0,BI30=1),GM30-GX30,0) -> 0 | GO30: =IF(BI30=2,GM30-GX30,0) -> 0 | GP30: =IF(BI30=4,GM30-GX30,0) -> 0 | GR30: 0 | GS30: 2 | GT30: 0 | GV30: =ROUND((GT30),6) -> 0 | GW30: 1 | GX30: =ROUND(HC30*I30,2) -> 0 | HA30: 0 | HB30: 0 | HC30: =GV30*GW30 -> 0 | HE30: 3 | HF30: 1,2 | HS30: 0 | IK30: 0
A31: 17 | B31: 1 | E31: 2 | F31: КА-1 | G31: Цилиндрическая IP-видеокамера с фиксированным объективом IP 2 Мп; 1/3" КМОП, 1920х1080-25/30к/с; встроенный микрофон; Дальность ИК подсветки 30м; объектив 2.8мм(3.6мм, 6ммопционально) ; режим "день/ночь", H264/ MJPEG ( Доп. поток) ; ; PoE 5 Вт; -40 ~ +60°C, TR-D2121CL3 4.0 | H31: ШТ | I31: 28 | J31: 0 | K31: 28 | O31: =ROUND(CP31,2) -> 216852.15 | P31: =ROUND((ROUND((AC31*I31),2)*BC31),2) -> 216852.15 | Q31: =(ROUND((ROUND(((ET31)*AV31*I31),2)*BB31),2)+ROUND((ROUND(((AE31-(EU31))*AV31*I31),2)*BS31),2)) -> 0 | R31: =(ROUND((ROUND(((EU31)*AV31*I31),2)*BS31),2)+ROUND((ROUND(((AE31-(EU31))*AV31*I31),2)*BS31),2)) -> 0 | S31: =ROUND((ROUND((AF31*AV31*I31),2)*BA31),2) -> 0 | T31: =ROUND(CU31*I31,2) -> 0 | U31: =CV31*I31 -> 0 | V31: =CW31*I31 -> 0 | W31: =ROUND(CX31*I31,2) -> 0 | X31: =(ROUND((((S31+ROUND((ROUND(((EU31)*AV31*I31),2)*BS31),2))*AT31)/100),2)+ROUND(((ROUND((ROUND(((AE31-(EU31))*AV31*I31),2)*BS31),2)*AT31)/100),2)) -> 0 | Y31: =(ROUND((((S31+ROUND((ROUND(((EU31)*AV31*I31),2)*BS31),2))*AU31)/100),2)+ROUND(((ROUND((ROUND(((AE31-(EU31))*AV31*I31),2)*BS31),2)*AU31)/100),2)) -> 0 | AA31: 60258061 | AB31: =ROUND((AC31+AD31+AF31),6) -> 1011.06 | AC31: =ROUND((ES31),6) -> 1011.06 | AD31: =ROUND((((ET31)-(EU31))+AE31),6) -> 0 | AE31: =ROUND((EU31),6) -> 0 | AF31: =ROUND((EV31),6) -> 0 | AG31: =ROUND((AP31),6) -> 0 | AH31: =(EW31) -> 0 | AI31: =(EX31) -> 0 | AJ31: =(AS31) -> 0 | AK31: 1011.06 | AL31: 1011.06 | AM31: 0 | AN31: 0 | AO31: 0 | AP31: 0 | AQ31: 0 | AR31: 0 | AS31: 0 | AT31: 0 | AU31: 0 | AV31: 1 | AW31: 1 | AZ31: 1 | BA31: 1 | BB31: 1 | BC31: 7.66 | BH31: 3 | BI31: 3 | BM31: 746 | BN31: 0 | BP31: 0 | BQ31: 130 | BR31: 0 | BS31: 1 | BT31: 1 | BU31: 1 | BV31: 1 | BW31: 1 | BX31: 1 | BZ31: 0 | CA31: 0 | CE31: 1566 | CF31: 0 | CG31: 0 | CM31: 0 | CO31: 0 | CP31: =(P31+Q31+S31) -> 216852.15 | CQ31: =ROUND((ROUND((AC31*1),2)*BC31),2) -> 7744.72 | CR31: =(ROUND((ROUND(((ET31)*AV31*1),2)*BB31),2)+ROUND((ROUND(((AE31-(EU31))*AV31*1),2)*BS31),2)) -> 0 | CS31: =(ROUND((ROUND(((EU31)*AV31*1),2)*BS31),2)+ROUND((ROUND(((AE31-(EU31))*AV31*1),2)*BS31),2)) -> 0 | CT31: =ROUND((ROUND((AF31*AV31*1),2)*BA31),2) -> 0 | CU31: =AG31 -> 0 | CV31: =(AH31*AV31) -> 0 | CW31: =AI31 -> 0 | CX31: =AJ31 -> 0 | CY31: =(ROUND((((S31+ROUND((ROUND(((EU31)*AV31*1),2)*BS31),2))*AT31)/100),2)+ROUND(((ROUND((ROUND(((AE31-(EU31))*AV31*1),2)*BS31),2)*AT31)/100),2)) -> 0 | CZ31: =(ROUND((((S31+ROUND((ROUND(((EU31)*AV31*1),2)*BS31),2))*AU31)/100),2)+ROUND(((ROUND((ROUND(((AE31-(EU31))*AV31*1),2)*BS31),2)*AU31)/100),2)) -> 0 | DN31: 0 | DO31: 0 | DP31: 1 | DQ31: 1 | DU31: 1013 | DV31: ШТ | DW31: ШТ | DX31: 1 | EE31: 60088638 | EF31: 130 | EG31: Сметная стоимость оборудования | EH31: 0 | EJ31: 3 | EK31: 746 | EL31: ТСН-2001.13. Сметная стоимость оборудования | EM31: ТСН-2001.13 | EQ31: 0 | ER31: 0 | ES31: 1011.06 | ET31: 0 | EU31: 0 | EV31: 0 | EW31: 0 | EX31: 0 | EY31: 0 | EZ31: 5 | FC31: 1 | FD31: 18 | FF31: 8916 | FQ31: 0 | FR31: =P31 -> 216852.15 | FS31: 0 | FX31: 0 | FY31: 0 | GA31: [8 916 / 1,2 / 7,66] + 3% Трансп + 1,2% Заг.скл | GD31: 1 | GF31: -1132090366 | GG31: 2 | GH31: 3 | GI31: 5 | GJ31: 0 | GK31: 0 | GL31: =ROUND(IF(AND(BH31=3,BI31=3,FS31<>0),P31,0),2) -> 0 | GM31: =ROUND(O31+X31+Y31,2)+GX31 -> 216852.15 | GN31: =IF(OR(BI31=0,BI31=1),GM31-GX31,0) -> 0 | GO31: =IF(BI31=2,GM31-GX31,0) -> 0 | GP31: =IF(BI31=4,GM31-GX31,0) -> 0 | GR31: 1 | GS31: 1 | GT31: 0 | GV31: =ROUND((GT31),6) -> 0 | GW31: 1 | GX31: =ROUND(HC31*I31,2) -> 0 | HA31: 0 | HB31: 0 | HC31: =GV31*GW31 -> 0 | HE31: 3 | HF31: 1,2 | HS31: 0 | IK31: 0
A32: 17 | B32: 1 | C32: =ROW(SmtRes!A13) -> 13 | D32: =ROW(EtalonRes!A15) -> 15 | E32: 3 | F32: 4.10-136-1 | G32: Разные устройства, монтаж коробки телевизионной (ответвители, разветвители магистральные, домовые, абонентские), УСС, БФТК | H32: 1 ШТ. | I32: 28 | J32: 0 | K32: 28 | O32: =ROUND(CP32,2) -> 377.07 | P32: =ROUND((ROUND((AC32*AW32*I32),2)*BC32),2) -> 8.12 | Q32: =(ROUND((ROUND((((ET32*1.1))*AV32*I32),2)*BB32),2)+ROUND((ROUND(((AE32-((EU32*1.1)))*AV32*I32),2)*BS32),2)) -> 0 | R32: =(ROUND((ROUND((((EU32*1.1))*AV32*I32),2)*BS32),2)+ROUND((ROUND(((AE32-((EU32*1.1)))*AV32*I32),2)*BS32),2)) -> 0 | S32: =ROUND((ROUND((AF32*AV32*I32),2)*BA32),2) -> 368.95 | T32: =ROUND(CU32*I32,2) -> 0 | U32: =CV32*I32 -> 26.78368 | V32: =CW32*I32 -> 0 | W32: =ROUND(CX32*I32,2) -> 0 | X32: =(ROUND((((S32+ROUND((ROUND((((EU32*1.1))*AV32*I32),2)*BS32),2))*AT32)/100),2)+ROUND(((ROUND((ROUND(((AE32-((EU32*1.1)))*AV32*I32),2)*BS32),2)*AT32)/100),2)) -> 350.5 | Y32: =(ROUND((((S32+ROUND((ROUND((((EU32*1.1))*AV32*I32),2)*BS32),2))*AU32)/100),2)+ROUND(((ROUND((ROUND(((AE32-((EU32*1.1)))*AV32*I32),2)*BS32),2)*AU32)/100),2)) -> 195.54 | AA32: 60258064 | AB32: =ROUND((AC32+AD32+AF32),6) -> 12.412 | AC32: =ROUND((ES32),6) -> 0.29 | AD32: =ROUND(((((ET32*1.1))-((EU32*1.1)))+AE32),6) -> 0 | AE32: =ROUND(((EU32*1.1)),6) -> 0 | AF32: =ROUND(((EV32*1.1)),6) -> 12.122 | AG32: =ROUND((AP32),6) -> 0 | AH32: =((EW32*1.1)) -> 0.88 | AI32: =((EX32*1.1)) -> 0 | AJ32: =(AS32) -> 0 | AK32: 11.31 | AL32: 0.29 | AM32: 0 | AN32: 0 | AO32: 11.02 | AP32: 0 | AQ32: 0.8 | AR32: 0 | AS32: 0 | AT32: 95 | AU32: 53 | AV32: 1.087 | AW32: 1 | AZ32: 1 | BA32: 1 | BB32: 1 | BC32: 1 | BH32: 0 | BI32: 2 | BJ32: ТСН-2001.4. Доп. 1-42. Сб. 10, т. 136, поз. 1 | BM32: 69 | BN32: 58973116 | BO32: 4.10-136-1 | BP32: 1 | BQ32: 40 | BR32: 0 | BS32: 1 | BT32: 1 | BU32: 1 | BV32: 1 | BW32: 1 | BX32: 1 | BZ32: 95 | CA32: 53 | CE32: 1566 | CF32: 0 | CG32: 0 | CM32: 0 | CN32: Поправка: О.П. п.3.4.30.в Наименование: При применении территориальных сметных нормативов для города Москвы затраты, учитывающие напряженные и стесненные условия производства работ (стесненность, сложность складирования и транспортной логистики и т.п.), исчисляются с применением коэффициентов к затратам труда и заработной плате рабочих, машинистов, времени эксплуатации машин и механизмов, стоимости эксплуатации машин в размере: для объектов, расположенных за пределами Третьего транспортного кольца города Москвы, но в пределах Московской кольцевой автомобильной дороги | CO32: 0 | CP32: =(P32+Q32+S32) -> 377.07 | CQ32: =ROUND((ROUND((AC32*AW32*1),2)*BC32),2) -> 0.29 | CR32: =(ROUND((ROUND((((ET32*1.1))*AV32*1),2)*BB32),2)+ROUND((ROUND(((AE32-((EU32*1.1)))*AV32*1),2)*BS32),2)) -> 0 | CS32: =(ROUND((ROUND((((EU32*1.1))*AV32*1),2)*BS32),2)+ROUND((ROUND(((AE32-((EU32*1.1)))*AV32*1),2)*BS32),2)) -> 0 | CT32: =ROUND((ROUND((AF32*AV32*1),2)*BA32),2) -> 13.18 | CU32: =AG32 -> 0 | CV32: =(AH32*AV32) -> 0.95656 | CW32: =AI32 -> 0 | CX32: =AJ32 -> 0 | CY32: =(ROUND((((S32+ROUND((ROUND((((EU32*1.1))*AV32*1),2)*BS32),2))*AT32)/100),2)+ROUND(((ROUND((ROUND(((AE32-((EU32*1.1)))*AV32*1),2)*BS32),2)*AT32)/100),2)) -> 350.5 | CZ32: =(ROUND((((S32+ROUND((ROUND((((EU32*1.1))*AV32*1),2)*BS32),2))*AU32)/100),2)+ROUND(((ROUND((ROUND(((AE32-((EU32*1.1)))*AV32*1),2)*BS32),2)*AU32)/100),2)) -> 195.54 | DB32: 3 | DE32: *1,1 | DF32: *1,1 | DG32: *1,1 | DI32: *1,1 | DJ32: *1,1 | DN32: 0 | DO32: 0 | DP32: 1 | DQ32: 1 | DU32: 1013 | DV32: 1 ШТ. | DW32: 1 ШТ. | DX32: 1 | EE32: 60088533 | EF32: 40 | EG32: Монтаж оборудования | EH32: 0 | EJ32: 2 | EK32: 69 | EL32: ТСН-2001.4-10. Монтаж радиотелевизионного и электронного оборудования | EM32: ТСН-2001.4-10-2 | EO32: Поправка: О.П. п.3.4.30.в | EQ32: 0 | ER32: 11.31 | ES32: 0.29 | ET32: 0 | EU32: 0 | EV32: 11.02 | EW32: 0.8 | EX32: 0 | EY32: 0 | FQ32: 0 | FR32: 0 | FS32: 0 | FX32: 95 | FY32: 53 | GD32: 1 | GF32: 105814318 | GG32: 2 | GH32: 1 | GI32: 2 | GJ32: 0 | GK32: 0 | GL32: =ROUND(IF(AND(BH32=3,BI32=3,FS32<>0),P32,0),2) -> 0 | GM32: =ROUND(O32+X32+Y32,2)+GX32 -> 923.11 | GN32: =IF(OR(BI32=0,BI32=1),GM32-GX32,0) -> 0 | GO32: =IF(BI32=2,GM32-GX32,0) -> 923.11 | GP32: =IF(BI32=4,GM32-GX32,0) -> 0 | GR32: 0 | GS32: 3 | GT32: 0 | GV32: =ROUND((GT32),6) -> 0 | GW32: 1 | GX32: =ROUND(HC32*I32,2) -> 0 | HA32: 0 | HB32: 0 | HC32: =GV32*GW32 -> 0 | HS32: 0 | IK32: 0
A33: 17 | B33: 1 | C33: =ROW(SmtRes!A14) -> 14 | D33: =ROW(EtalonRes!A16) -> 16 | E33: 3 | F33: 4.10-136-1 | G33: Разные устройства, монтаж коробки телевизионной (ответвители, разветвители магистральные, домовые, абонентские), УСС, БФТК | H33: 1 ШТ. | I33: 28 | J33: 0 | K33: 28 | O33: =ROUND(CP33,2) -> 20368.95 | P33: =ROUND((ROUND((AC33*AW33*I33),2)*BC33),2) -> 80.39 | Q33: =(ROUND((ROUND((((ET33*1.1))*AV33*I33),2)*BB33),2)+ROUND((ROUND(((AE33-((EU33*1.1)))*AV33*I33),2)*BS33),2)) -> 0 | R33: =(ROUND((ROUND((((EU33*1.1))*AV33*I33),2)*BS33),2)+ROUND((ROUND(((AE33-((EU33*1.1)))*AV33*I33),2)*BS33),2)) -> 0 | S33: =ROUND((ROUND((AF33*AV33*I33),2)*BA33),2) -> 20288.56 | T33: =ROUND(CU33*I33,2) -> 0 | U33: =CV33*I33 -> 26.78368 | V33: =CW33*I33 -> 0 | W33: =ROUND(CX33*I33,2) -> 0 | X33: =(ROUND((((S33+ROUND((ROUND((((EU33*1.1))*AV33*I33),2)*BS33),2))*AT33)/100),2)+ROUND(((ROUND((ROUND(((AE33-((EU33*1.1)))*AV33*I33),2)*BS33),2)*AT33)/100),2)) -> 19274.13 | Y33: =(ROUND((((S33+ROUND((ROUND((((EU33*1.1))*AV33*I33),2)*BS33),2))*AU33)/100),2)+ROUND(((ROUND((ROUND(((AE33-((EU33*1.1)))*AV33*I33),2)*BS33),2)*AU33)/100),2)) -> 10752.94 | AA33: 60258061 | AB33: =ROUND((AC33+AD33+AF33),6) -> 12.412 | AC33: =ROUND((ES33),6) -> 0.29 | AD33: =ROUND(((((ET33*1.1))-((EU33*1.1)))+AE33),6) -> 0 | AE33: =ROUND(((EU33*1.1)),6) -> 0 | AF33: =ROUND(((EV33*1.1)),6) -> 12.122 | AG33: =ROUND((AP33),6) -> 0 | AH33: =((EW33*1.1)) -> 0.88 | AI33: =((EX33*1.1)) -> 0 | AJ33: =(AS33) -> 0 | AK33: 11.31 | AL33: 0.29 | AM33: 0 | AN33: 0 | AO33: 11.02 | AP33: 0 | AQ33: 0.8 | AR33: 0 | AS33: 0 | AT33: 95 | AU33: 53 | AV33: 1.087 | AW33: 1 | AZ33: 1 | BA33: 54.99 | BB33: 1 | BC33: 9.9 | BH33: 0 | BI33: 2 | BJ33: ТСН-2001.4. Доп. 1-42. Сб. 10, т. 136, поз. 1 | BM33: 69 | BN33: 58973116 | BO33: 4.10-136-1 | BP33: 1 | BQ33: 40 | BR33: 0 | BS33: 54.99 | BT33: 1 | BU33: 1 | BV33: 1 | BW33: 1 | BX33: 1 | BZ33: 95 | CA33: 53 | CE33: 1566 | CF33: 0 | CG33: 0 | CM33: 0 | CN33: Поправка: О.П. п.3.4.30.в Наименование: При применении территориальных сметных нормативов для города Москвы затраты, учитывающие напряженные и стесненные условия производства работ (стесненность, сложность складирования и транспортной логистики и т.п.), исчисляются с применением коэффициентов к затратам труда и заработной плате рабочих, машинистов, времени эксплуатации машин и механизмов, стоимости эксплуатации машин в размере: для объектов, расположенных за пределами Третьего транспортного кольца города Москвы, но в пределах Московской кольцевой автомобильной дороги | CO33: 0 | CP33: =(P33+Q33+S33) -> 20368.95 | CQ33: =ROUND((ROUND((AC33*AW33*1),2)*BC33),2) -> 2.87 | CR33: =(ROUND((ROUND((((ET33*1.1))*AV33*1),2)*BB33),2)+ROUND((ROUND(((AE33-((EU33*1.1)))*AV33*1),2)*BS33),2)) -> 0 | CS33: =(ROUND((ROUND((((EU33*1.1))*AV33*1),2)*BS33),2)+ROUND((ROUND(((AE33-((EU33*1.1)))*AV33*1),2)*BS33),2)) -> 0 | CT33: =ROUND((ROUND((AF33*AV33*1),2)*BA33),2) -> 724.77 | CU33: =AG33 -> 0 | CV33: =(AH33*AV33) -> 0.95656 | CW33: =AI33 -> 0 | CX33: =AJ33 -> 0 | CY33: =(ROUND((((S33+ROUND((ROUND((((EU33*1.1))*AV33*1),2)*BS33),2))*AT33)/100),2)+ROUND(((ROUND((ROUND(((AE33-((EU33*1.1)))*AV33*1),2)*BS33),2)*AT33)/100),2)) -> 19274.13 | CZ33: =(ROUND((((S33+ROUND((ROUND((((EU33*1.1))*AV33*1),2)*BS33),2))*AU33)/100),2)+ROUND(((ROUND((ROUND(((AE33-((EU33*1.1)))*AV33*1),2)*BS33),2)*AU33)/100),2)) -> 10752.94 | DB33: 4 | DE33: *1,1 | DF33: *1,1 | DG33: *1,1 | DI33: *1,1 | DJ33: *1,1 | DN33: 0 | DO33: 0 | DP33: 1 | DQ33: 1 | DU33: 1013 | DV33: 1 ШТ. | DW33: 1 ШТ. | DX33: 1 | EE33: 60088533 | EF33: 40 | EG33: Монтаж оборудования | EH33: 0 | EJ33: 2 | EK33: 69 | EL33: ТСН-2001.4-10. Монтаж радиотелевизионного и электронного оборудования | EM33: ТСН-2001.4-10-2 | EO33: Поправка: О.П. п.3.4.30.в | EQ33: 0 | ER33: 11.31 | ES33: 0.29 | ET33: 0 | EU33: 0 | EV33: 11.02 | EW33: 0.8 | EX33: 0 | EY33: 0 | FQ33: 0 | FR33: 0 | FS33: 0 | FX33: 95 | FY33: 53 | GD33: 1 | GF33: 105814318 | GG33: 2 | GH33: 1 | GI33: 2 | GJ33: 0 | GK33: 0 | GL33: =ROUND(IF(AND(BH33=3,BI33=3,FS33<>0),P33,0),2) -> 0 | GM33: =ROUND(O33+X33+Y33,2)+GX33 -> 50396.02 | GN33: =IF(OR(BI33=0,BI33=1),GM33-GX33,0) -> 0 | GO33: =IF(BI33=2,GM33-GX33,0) -> 50396.02 | GP33: =IF(BI33=4,GM33-GX33,0) -> 0 | GR33: 0 | GS33: 3 | GT33: 0 | GV33: =ROUND((GT33),6) -> 0 | GW33: 1 | GX33: =ROUND(HC33*I33,2) -> 0 | HA33: 0 | HB33: 0 | HC33: =GV33*GW33 -> 0 | HS33: 0 | IK33: 0
A34: 17 | B34: 1 | E34: 4 | F34: КА-2 | G34: Устройство грозозащиты NST NS-LP-1GP/D | H34: ШТ | I34: 28 | J34: 0 | K34: 28 | O34: =ROUND(CP34,2) -> 7826.56 | P34: =ROUND((ROUND((AC34*AW34*I34),2)*BC34),2) -> 7826.56 | Q34: =(ROUND((ROUND(((ET34)*AV34*I34),2)*BB34),2)+ROUND((ROUND(((AE34-(EU34))*AV34*I34),2)*BS34),2)) -> 0 | R34: =(ROUND((ROUND(((EU34)*AV34*I34),2)*BS34),2)+ROUND((ROUND(((AE34-(EU34))*AV34*I34),2)*BS34),2)) -> 0 | S34: =ROUND((ROUND((AF34*AV34*I34),2)*BA34),2) -> 0 | T34: =ROUND(CU34*I34,2) -> 0 | U34: =CV34*I34 -> 0 | V34: =CW34*I34 -> 0 | W34: =ROUND(CX34*I34,2) -> 0 | X34: =(ROUND((((S34+ROUND((ROUND(((EU34)*AV34*I34),2)*BS34),2))*AT34)/100),2)+ROUND(((ROUND((ROUND(((AE34-(EU34))*AV34*I34),2)*BS34),2)*AT34)/100),2)) -> 0 | Y34: =(ROUND((((S34+ROUND((ROUND(((EU34)*AV34*I34),2)*BS34),2))*AU34)/100),2)+ROUND(((ROUND((ROUND(((AE34-(EU34))*AV34*I34),2)*BS34),2)*AU34)/100),2)) -> 0 | AA34: 60258064 | AB34: =ROUND((AC34+AD34+AF34),6) -> 279.52 | AC34: =ROUND((ES34),6) -> 279.52 | AD34: =ROUND((((ET34)-(EU34))+AE34),6) -> 0 | AE34: =ROUND((EU34),6) -> 0 | AF34: =ROUND((EV34),6) -> 0 | AG34: =ROUND((AP34),6) -> 0 | AH34: =(EW34) -> 0 | AI34: =(EX34) -> 0 | AJ34: =(AS34) -> 0 | AK34: 279.52 | AL34: 279.52 | AM34: 0 | AN34: 0 | AO34: 0 | AP34: 0 | AQ34: 0 | AR34: 0 | AS34: 0 | AT34: 0 | AU34: 0 | AV34: 1 | AW34: 1 | AZ34: 1 | BA34: 1 | BB34: 1 | BC34: 1 | BH34: 3 | BI34: 2 | BM34: 400002 | BN34: 0 | BP34: 0 | BQ34: 202 | BR34: 0 | BS34: 1 | BT34: 1 | BU34: 1 | BV34: 1 | BW34: 1 | BX34: 1 | BZ34: 0 | CA34: 0 | CE34: 1566 | CF34: 0 | CG34: 0 | CM34: 0 | CO34: 0 | CP34: =(P34+Q34+S34) -> 7826.56 | CQ34: =ROUND((ROUND((AC34*AW34*1),2)*BC34),2) -> 279.52 | CR34: =(ROUND((ROUND(((ET34)*AV34*1),2)*BB34),2)+ROUND((ROUND(((AE34-(EU34))*AV34*1),2)*BS34),2)) -> 0 | CS34: =(ROUND((ROUND(((EU34)*AV34*1),2)*BS34),2)+ROUND((ROUND(((AE34-(EU34))*AV34*1),2)*BS34),2)) -> 0 | CT34: =ROUND((ROUND((AF34*AV34*1),2)*BA34),2) -> 0 | CU34: =AG34 -> 0 | CV34: =(AH34*AV34) -> 0 | CW34: =AI34 -> 0 | CX34: =AJ34 -> 0 | CY34: =(ROUND((((S34+ROUND((ROUND(((EU34)*AV34*1),2)*BS34),2))*AT34)/100),2)+ROUND(((ROUND((ROUND(((AE34-(EU34))*AV34*1),2)*BS34),2)*AT34)/100),2)) -> 0 | CZ34: =(ROUND((((S34+ROUND((ROUND(((EU34)*AV34*1),2)*BS34),2))*AU34)/100),2)+ROUND(((ROUND((ROUND(((AE34-(EU34))*AV34*1),2)*BS34),2)*AU34)/100),2)) -> 0 | DN34: 0 | DO34: 0 | DP34: 1 | DQ34: 1 | DU34: 1013 | DV34: ШТ | DW34: ШТ | DX34: 1 | EE34: 60088644 | EF34: 202 | EG34: Материалы | EH34: 0 | EJ34: 1 | EK34: 400002 | EL34: Материалы, изделия и конструкции | EM34: Материалы | EQ34: 0 | ER34: 0 | ES34: 279.52 | ET34: 0 | EU34: 0 | EV34: 0 | EW34: 0 | EX34: 0 | EY34: 0 | FQ34: 0 | FR34: 0 | FS34: 0 | FX34: 0 | FY34: 0 | GA34: [3 249 / 1,2 / 9,88] + 2% Заг.скл | GD34: 1 | GF34: 1071266394 | GG34: 2 | GH34: 4 | GI34: -2 | GJ34: 0 | GK34: 0 | GL34: =ROUND(IF(AND(BH34=3,BI34=3,FS34<>0),P34,0),2) -> 0 | GM34: =ROUND(O34+X34+Y34,2)+GX34 -> 7826.56 | GN34: =IF(OR(BI34=0,BI34=1),GM34-GX34,0) -> 0 | GO34: =IF(BI34=2,GM34-GX34,0) -> 7826.56 | GP34: =IF(BI34=4,GM34-GX34,0) -> 0 | GR34: 0 | GS34: 2 | GT34: 0 | GV34: =ROUND((GT34),6) -> 0 | GW34: 1 | GX34: =ROUND(HC34*I34,2) -> 0 | HA34: 0 | HB34: 0 | HC34: =GV34*GW34 -> 0 | HE34: 0 | HF34: 2 | HS34: 0 | IK34: 0
A35: 17 | B35: 1 | E35: 4 | F35: КА-2 | G35: Устройство грозозащиты NST NS-LP-1GP/D | H35: ШТ | I35: 28 | J35: 0 | K35: 28 | O35: =ROUND(CP35,2) -> 77326.41 | P35: =ROUND((ROUND((AC35*AW35*I35),2)*BC35),2) -> 77326.41 | Q35: =(ROUND((ROUND(((ET35)*AV35*I35),2)*BB35),2)+ROUND((ROUND(((AE35-(EU35))*AV35*I35),2)*BS35),2)) -> 0 | R35: =(ROUND((ROUND(((EU35)*AV35*I35),2)*BS35),2)+ROUND((ROUND(((AE35-(EU35))*AV35*I35),2)*BS35),2)) -> 0 | S35: =ROUND((ROUND((AF35*AV35*I35),2)*BA35),2) -> 0 | T35: =ROUND(CU35*I35,2) -> 0 | U35: =CV35*I35 -> 0 | V35: =CW35*I35 -> 0 | W35: =ROUND(CX35*I35,2) -> 0 | X35: =(ROUND((((S35+ROUND((ROUND(((EU35)*AV35*I35),2)*BS35),2))*AT35)/100),2)+ROUND(((ROUND((ROUND(((AE35-(EU35))*AV35*I35),2)*BS35),2)*AT35)/100),2)) -> 0 | Y35: =(ROUND((((S35+ROUND((ROUND(((EU35)*AV35*I35),2)*BS35),2))*AU35)/100),2)+ROUND(((ROUND((ROUND(((AE35-(EU35))*AV35*I35),2)*BS35),2)*AU35)/100),2)) -> 0 | AA35: 60258061 | AB35: =ROUND((AC35+AD35+AF35),6) -> 279.52 | AC35: =ROUND((ES35),6) -> 279.52 | AD35: =ROUND((((ET35)-(EU35))+AE35),6) -> 0 | AE35: =ROUND((EU35),6) -> 0 | AF35: =ROUND((EV35),6) -> 0 | AG35: =ROUND((AP35),6) -> 0 | AH35: =(EW35) -> 0 | AI35: =(EX35) -> 0 | AJ35: =(AS35) -> 0 | AK35: 279.52 | AL35: 279.52 | AM35: 0 | AN35: 0 | AO35: 0 | AP35: 0 | AQ35: 0 | AR35: 0 | AS35: 0 | AT35: 0 | AU35: 0 | AV35: 1 | AW35: 1 | AZ35: 1 | BA35: 1 | BB35: 1 | BC35: 9.88 | BH35: 3 | BI35: 2 | BM35: 400002 | BN35: 0 | BP35: 0 | BQ35: 202 | BR35: 0 | BS35: 1 | BT35: 1 | BU35: 1 | BV35: 1 | BW35: 1 | BX35: 1 | BZ35: 0 | CA35: 0 | CE35: 1566 | CF35: 0 | CG35: 0 | CM35: 0 | CO35: 0 | CP35: =(P35+Q35+S35) -> 77326.41 | CQ35: =ROUND((ROUND((AC35*AW35*1),2)*BC35),2) -> 2761.66 | CR35: =(ROUND((ROUND(((ET35)*AV35*1),2)*BB35),2)+ROUND((ROUND(((AE35-(EU35))*AV35*1),2)*BS35),2)) -> 0 | CS35: =(ROUND((ROUND(((EU35)*AV35*1),2)*BS35),2)+ROUND((ROUND(((AE35-(EU35))*AV35*1),2)*BS35),2)) -> 0 | CT35: =ROUND((ROUND((AF35*AV35*1),2)*BA35),2) -> 0 | CU35: =AG35 -> 0 | CV35: =(AH35*AV35) -> 0 | CW35: =AI35 -> 0 | CX35: =AJ35 -> 0 | CY35: =(ROUND((((S35+ROUND((ROUND(((EU35)*AV35*1),2)*BS35),2))*AT35)/100),2)+ROUND(((ROUND((ROUND(((AE35-(EU35))*AV35*1),2)*BS35),2)*AT35)/100),2)) -> 0 | CZ35: =(ROUND((((S35+ROUND((ROUND(((EU35)*AV35*1),2)*BS35),2))*AU35)/100),2)+ROUND(((ROUND((ROUND(((AE35-(EU35))*AV35*1),2)*BS35),2)*AU35)/100),2)) -> 0 | DN35: 0 | DO35: 0 | DP35: 1 | DQ35: 1 | DU35: 1013 | DV35: ШТ | DW35: ШТ | DX35: 1 | EE35: 60088644 | EF35: 202 | EG35: Материалы | EH35: 0 | EJ35: 1 | EK35: 400002 | EL35: Материалы, изделия и конструкции | EM35: Материалы | EQ35: 0 | ER35: 0 | ES35: 279.52 | ET35: 0 | EU35: 0 | EV35: 0 | EW35: 0 | EX35: 0 | EY35: 0 | EZ35: 5 | FC35: 1 | FD35: 18 | FF35: 3249 | FQ35: 0 | FR35: 0 | FS35: 0 | FX35: 0 | FY35: 0 | GA35: [3 249 / 1,2 / 9,88] + 2% Заг.скл | GD35: 1 | GF35: 1071266394 | GG35: 2 | GH35: 3 | GI35: 5 | GJ35: 0 | GK35: 0 | GL35: =ROUND(IF(AND(BH35=3,BI35=3,FS35<>0),P35,0),2) -> 0 | GM35: =ROUND(O35+X35+Y35,2)+GX35 -> 77326.41 | GN35: =IF(OR(BI35=0,BI35=1),GM35-GX35,0) -> 0 | GO35: =IF(BI35=2,GM35-GX35,0) -> 77326.41 | GP35: =IF(BI35=4,GM35-GX35,0) -> 0 | GR35: 1 | GS35: 1 | GT35: 0 | GV35: =ROUND((GT35),6) -> 0 | GW35: 1 | GX35: =ROUND(HC35*I35,2) -> 0 | HA35: 0 | HB35: 0 | HC35: =GV35*GW35 -> 0 | HE35: 0 | HF35: 2 | HS35: 0 | IK35: 0
A36: 17 | B36: 1 | C36: =ROW(SmtRes!A20) -> 20 | D36: =ROW(EtalonRes!A23) -> 23 | E36: 5 | F36: 4.10-174-2 | G36: Монтаж наружной камеры видеонаблюдения | H36: 10 шт. | I36: =ROUND(109/10,9) -> 10.9 | J36: 0 | K36: =ROUND(109/10,9) -> 10.9 | O36: =ROUND(CP36,2) -> 5530.34 | P36: =ROUND((ROUND((AC36*AW36*I36),2)*BC36),2) -> 463.36 | Q36: =(ROUND((ROUND((((ET36*1.1))*AV36*I36),2)*BB36),2)+ROUND((ROUND(((AE36-((EU36*1.1)))*AV36*I36),2)*BS36),2)) -> 29.63 | R36: =(ROUND((ROUND((((EU36*1.1))*AV36*I36),2)*BS36),2)+ROUND((ROUND(((AE36-((EU36*1.1)))*AV36*I36),2)*BS36),2)) -> 1.63 | S36: =ROUND((ROUND((AF36*AV36*I36),2)*BA36),2) -> 5037.35 | T36: =ROUND(CU36*I36,2) -> 0 | U36: =CV36*I36 -> 317.98091 | V36: =CW36*I36 -> 0 | W36: =ROUND(CX36*I36,2) -> 0 | X36: =(ROUND((((S36+ROUND((ROUND((((EU36*1.1))*AV36*I36),2)*BS36),2))*AT36)/100),2)+ROUND(((ROUND((ROUND(((AE36-((EU36*1.1)))*AV36*I36),2)*BS36),2)*AT36)/100),2)) -> 4535.08 | Y36: =(ROUND((((S36+ROUND((ROUND((((EU36*1.1))*AV36*I36),2)*BS36),2))*AU36)/100),2)+ROUND(((ROUND((ROUND(((AE36-((EU36*1.1)))*AV36*I36),2)*BS36),2)*AU36)/100),2)) -> 2317.93 | AA36: 60258064 | AB36: =ROUND((AC36+AD36+AF36),6) -> 486.503 | AC36: =ROUND((ES36),6) -> 42.51 | AD36: =ROUND(((((ET36*1.1))-((EU36*1.1)))+AE36),6) -> 2.596 | AE36: =ROUND(((EU36*1.1)),6) -> 0.143 | AF36: =ROUND(((EV36*1.1)),6) -> 441.397 | AG36: =ROUND((AP36),6) -> 0 | AH36: =((EW36*1.1)) -> 27.863 | AI36: =((EX36*1.1)) -> 0 | AJ36: =(AS36) -> 0 | AK36: 446.14 | AL36: 42.51 | AM36: 2.36 | AN36: 0.13 | AO36: 401.27 | AP36: 0 | AQ36: 25.33 | AR36: 0 | AS36: 0 | AT36: 90 | AU36: 46 | AV36: 1.047 | AW36: 1 | AZ36: 1 | BA36: 1 | BB36: 1 | BC36: 1 | BH36: 0 | BI36: 2 | BJ36: ТСН-2001.4 Доп. 68, Сб. 10, т. 174, поз. 2 | BM36: 68 | BN36: 58973116 | BO36: 4.10-174-2 | BP36: 1 | BQ36: 40 | BR36: 0 | BS36: 1 | BT36: 1 | BU36: 1 | BV36: 1 | BW36: 1 | BX36: 1 | BZ36: 90 | CA36: 46 | CE36: 1566 | CF36: 0 | CG36: 0 | CM36: 0 | CN36: Поправка: О.П. п.3.4.30.в Наименование: При применении территориальных сметных нормативов для города Москвы затраты, учитывающие напряженные и стесненные условия производства работ (стесненность, сложность складирования и транспортной логистики и т.п.), исчисляются с применением коэффициентов к затратам труда и заработной плате рабочих, машинистов, времени эксплуатации машин и механизмов, стоимости эксплуатации машин в размере: для объектов, расположенных за пределами Третьего транспортного кольца города Москвы, но в пределах Московской кольцевой автомобильной дороги | CO36: 0 | CP36: =(P36+Q36+S36) -> 5530.34 | CQ36: =ROUND((ROUND((AC36*AW36*1),2)*BC36),2) -> 42.51 | CR36: =(ROUND((ROUND((((ET36*1.1))*AV36*1),2)*BB36),2)+ROUND((ROUND(((AE36-((EU36*1.1)))*AV36*1),2)*BS36),2)) -> 2.72 | CS36: =(ROUND((ROUND((((EU36*1.1))*AV36*1),2)*BS36),2)+ROUND((ROUND(((AE36-((EU36*1.1)))*AV36*1),2)*BS36),2)) -> 0.15 | CT36: =ROUND((ROUND((AF36*AV36*1),2)*BA36),2) -> 462.14 | CU36: =AG36 -> 0 | CV36: =(AH36*AV36) -> 29.172561 | CW36: =AI36 -> 0 | CX36: =AJ36 -> 0 | CY36: =(ROUND((((S36+ROUND((ROUND((((EU36*1.1))*AV36*1),2)*BS36),2))*AT36)/100),2)+ROUND(((ROUND((ROUND(((AE36-((EU36*1.1)))*AV36*1),2)*BS36),2)*AT36)/100),2)) -> 4533.75 | CZ36: =(ROUND((((S36+ROUND((ROUND((((EU36*1.1))*AV36*1),2)*BS36),2))*AU36)/100),2)+ROUND(((ROUND((ROUND(((AE36-((EU36*1.1)))*AV36*1),2)*BS36),2)*AU36)/100),2)) -> 2317.25 | DB36: 5 | DE36: *1,1 | DF36: *1,1 | DG36: *1,1 | DI36: *1,1 | DJ36: *1,1 | DN36: 0 | DO36: 0 | DP36: 1 | DQ36: 1 | DU36: 1010 | DV36: 10 шт. | DW36: 10 шт. | DX36: 10 | EE36: 60088532 | EF36: 40 | EG36: Монтаж оборудования | EH36: 0 | EJ36: 2 | EK36: 68 | EL36: ТСН-2001.4-10. Прокладка и монтаж сетей связи | EM36: ТСН-2001.4-10-1 | EO36: Поправка: О.П. п.3.4.30.в | EQ36: 0 | ER36: 446.14 | ES36: 42.51 | ET36: 2.36 | EU36: 0.13 | EV36: 401.27 | EW36: 25.33 | EX36: 0 | EY36: 0 | FQ36: 0 | FR36: 0 | FS36: 0 | FX36: 90 | FY36: 46 | GD36: 1 | GF36: -2118561153 | GG36: 2 | GH36: 1 | GI36: 2 | GJ36: 0 | GK36: 0 | GL36: =ROUND(IF(AND(BH36=3,BI36=3,FS36<>0),P36,0),2) -> 0 | GM36: =ROUND(O36+X36+Y36,2)+GX36 -> 12383.35 | GN36: =IF(OR(BI36=0,BI36=1),GM36-GX36,0) -> 0 | GO36: =IF(BI36=2,GM36-GX36,0) -> 12383.35 | GP36: =IF(BI36=4,GM36-GX36,0) -> 0 | GR36: 0 | GS36: 3 | GT36: 0 | GV36: =ROUND((GT36),6) -> 0 | GW36: 1 | GX36: =ROUND(HC36*I36,2) -> 0 | HA36: 0 | HB36: 0 | HC36: =GV36*GW36 -> 0 | HS36: 0 | IK36: 0
A37: 17 | B37: 1 | C37: =ROW(SmtRes!A26) -> 26 | D37: =ROW(EtalonRes!A30) -> 30 | E37: 5 | F37: 4.10-174-2 | G37: Монтаж наружной камеры видеонаблюдения | H37: 10 шт. | I37: =ROUND(109/10,9) -> 10.9 | J37: 0 | K37: =ROUND(109/10,9) -> 10.9 | O37: =ROUND(CP37,2) -> 278234.76 | P37: =ROUND((ROUND((AC37*AW37*I37),2)*BC37),2) -> 894.28 | Q37: =(ROUND((ROUND((((ET37*1.1))*AV37*I37),2)*BB37),2)+ROUND((ROUND(((AE37-((EU37*1.1)))*AV37*I37),2)*BS37),2)) -> 336.6 | R37: =(ROUND((ROUND((((EU37*1.1))*AV37*I37),2)*BS37),2)+ROUND((ROUND(((AE37-((EU37*1.1)))*AV37*I37),2)*BS37),2)) -> 89.63 | S37: =ROUND((ROUND((AF37*AV37*I37),2)*BA37),2) -> 277003.88 | T37: =ROUND(CU37*I37,2) -> 0 | U37: =CV37*I37 -> 317.98091 | V37: =CW37*I37 -> 0 | W37: =ROUND(CX37*I37,2) -> 0 | X37: =(ROUND((((S37+ROUND((ROUND((((EU37*1.1))*AV37*I37),2)*BS37),2))*AT37)/100),2)+ROUND(((ROUND((ROUND(((AE37-((EU37*1.1)))*AV37*I37),2)*BS37),2)*AT37)/100),2)) -> 249384.16 | Y37: =(ROUND((((S37+ROUND((ROUND((((EU37*1.1))*AV37*I37),2)*BS37),2))*AU37)/100),2)+ROUND(((ROUND((ROUND(((AE37-((EU37*1.1)))*AV37*I37),2)*BS37),2)*AU37)/100),2)) -> 127463.01 | AA37: 60258061 | AB37: =ROUND((AC37+AD37+AF37),6) -> 486.503 | AC37: =ROUND((ES37),6) -> 42.51 | AD37: =ROUND(((((ET37*1.1))-((EU37*1.1)))+AE37),6) -> 2.596 | AE37: =ROUND(((EU37*1.1)),6) -> 0.143 | AF37: =ROUND(((EV37*1.1)),6) -> 441.397 | AG37: =ROUND((AP37),6) -> 0 | AH37: =((EW37*1.1)) -> 27.863 | AI37: =((EX37*1.1)) -> 0 | AJ37: =(AS37) -> 0 | AK37: 446.14 | AL37: 42.51 | AM37: 2.36 | AN37: 0.13 | AO37: 401.27 | AP37: 0 | AQ37: 25.33 | AR37: 0 | AS37: 0 | AT37: 90 | AU37: 46 | AV37: 1.047 | AW37: 1 | AZ37: 1 | BA37: 54.99 | BB37: 11.36 | BC37: 1.93 | BH37: 0 | BI37: 2 | BJ37: ТСН-2001.4 Доп. 68, Сб. 10, т. 174, поз. 2 | BM37: 68 | BN37: 58973116 | BO37: 4.10-174-2 | BP37: 1 | BQ37: 40 | BR37: 0 | BS37: 54.99 | BT37: 1 | BU37: 1 | BV37: 1 | BW37: 1 | BX37: 1 | BZ37: 90 | CA37: 46 | CE37: 1566 | CF37: 0 | CG37: 0 | CM37: 0 | CN37: Поправка: О.П. п.3.4.30.в Наименование: При применении территориальных сметных нормативов для города Москвы затраты, учитывающие напряженные и стесненные условия производства работ (стесненность, сложность складирования и транспортной логистики и т.п.), исчисляются с применением коэффициентов к затратам труда и заработной плате рабочих, машинистов, времени эксплуатации машин и механизмов, стоимости эксплуатации машин в размере: для объектов, расположенных за пределами Третьего транспортного кольца города Москвы, но в пределах Московской кольцевой автомобильной дороги | CO37: 0 | CP37: =(P37+Q37+S37) -> 278234.76 | CQ37: =ROUND((ROUND((AC37*AW37*1),2)*BC37),2) -> 82.04 | CR37: =(ROUND((ROUND((((ET37*1.1))*AV37*1),2)*BB37),2)+ROUND((ROUND(((AE37-((EU37*1.1)))*AV37*1),2)*BS37),2)) -> 30.9 | CS37: =(ROUND((ROUND((((EU37*1.1))*AV37*1),2)*BS37),2)+ROUND((ROUND(((AE37-((EU37*1.1)))*AV37*1),2)*BS37),2)) -> 8.25 | CT37: =ROUND((ROUND((AF37*AV37*1),2)*BA37),2) -> 25413.08 | CU37: =AG37 -> 0 | CV37: =(AH37*AV37) -> 29.172561 | CW37: =AI37 -> 0 | CX37: =AJ37 -> 0 | CY37: =(ROUND((((S37+ROUND((ROUND((((EU37*1.1))*AV37*1),2)*BS37),2))*AT37)/100),2)+ROUND(((ROUND((ROUND(((AE37-((EU37*1.1)))*AV37*1),2)*BS37),2)*AT37)/100),2)) -> 249310.92 | CZ37: =(ROUND((((S37+ROUND((ROUND((((EU37*1.1))*AV37*1),2)*BS37),2))*AU37)/100),2)+ROUND(((ROUND((ROUND(((AE37-((EU37*1.1)))*AV37*1),2)*BS37),2)*AU37)/100),2)) -> 127425.58 | DB37: 6 | DE37: *1,1 | DF37: *1,1 | DG37: *1,1 | DI37: *1,1 | DJ37: *1,1 | DN37: 0 | DO37: 0 | DP37: 1 | DQ37: 1 | DU37: 1010 | DV37: 10 шт. | DW37: 10 шт. | DX37: 10 | EE37: 60088532 | EF37: 40 | EG37: Монтаж оборудования | EH37: 0 | EJ37: 2 | EK37: 68 | EL37: ТСН-2001.4-10. Прокладка и монтаж сетей связи | EM37: ТСН-2001.4-10-1 | EO37: Поправка: О.П. п.3.4.30.в | EQ37: 0 | ER37: 446.14 | ES37: 42.51 | ET37: 2.36 | EU37: 0.13 | EV37: 401.27 | EW37: 25.33 | EX37: 0 | EY37: 0 | FQ37: 0 | FR37: 0 | FS37: 0 | FX37: 90 | FY37: 46 | GD37: 1 | GF37: -2118561153 | GG37: 2 | GH37: 1 | GI37: 2 | GJ37: 0 | GK37: 0 | GL37: =ROUND(IF(AND(BH37=3,BI37=3,FS37<>0),P37,0),2) -> 0 | GM37: =ROUND(O37+X37+Y37,2)+GX37 -> 655081.93 | GN37: =IF(OR(BI37=0,BI37=1),GM37-GX37,0) -> 0 | GO37: =IF(BI37=2,GM37-GX37,0) -> 655081.93 | GP37: =IF(BI37=4,GM37-GX37,0) -> 0 | GR37: 0 | GS37: 3 | GT37: 0 | GV37: =ROUND((GT37),6) -> 0 | GW37: 1 | GX37: =ROUND(HC37*I37,2) -> 0 | HA37: 0 | HB37: 0 | HC37: =GV37*GW37 -> 0 | HS37: 0 | IK37: 0
A38: 17 | B38: 1 | E38: 6 | F38: КА-3 | G38: Купольная IP-видеокамера с фиксированным объективом IP 2 Мп; 1/2.8" КМОП, 1920х1080-25/30к/с; встроенный микрофон; Дальность ИК подсветки 25м; объектив 2.8мм(3.6мм, 6ммопционально) ; режим "день/ночь", H264/ MJPEG ( Доп. поток) ; ; PoE 5 Вт; TR-D2D2 v2 2.7-13.5 | H38: ШТ | I38: 109 | J38: 0 | K38: 109 | O38: =ROUND(CP38,2) -> 141836.25 | P38: =ROUND((ROUND((AC38*I38),2)*BC38),2) -> 141836.25 | Q38: =(ROUND((ROUND(((ET38)*AV38*I38),2)*BB38),2)+ROUND((ROUND(((AE38-(EU38))*AV38*I38),2)*BS38),2)) -> 0 | R38: =(ROUND((ROUND(((EU38)*AV38*I38),2)*BS38),2)+ROUND((ROUND(((AE38-(EU38))*AV38*I38),2)*BS38),2)) -> 0 | S38: =ROUND((ROUND((AF38*AV38*I38),2)*BA38),2) -> 0 | T38: =ROUND(CU38*I38,2) -> 0 | U38: =CV38*I38 -> 0 | V38: =CW38*I38 -> 0 | W38: =ROUND(CX38*I38,2) -> 0 | X38: =(ROUND((((S38+ROUND((ROUND(((EU38)*AV38*I38),2)*BS38),2))*AT38)/100),2)+ROUND(((ROUND((ROUND(((AE38-(EU38))*AV38*I38),2)*BS38),2)*AT38)/100),2)) -> 0 | Y38: =(ROUND((((S38+ROUND((ROUND(((EU38)*AV38*I38),2)*BS38),2))*AU38)/100),2)+ROUND(((ROUND((ROUND(((AE38-(EU38))*AV38*I38),2)*BS38),2)*AU38)/100),2)) -> 0 | AA38: 60258064 | AB38: =ROUND((AC38+AD38+AF38),6) -> 1301.25 | AC38: =ROUND((ES38),6) -> 1301.25 | AD38: =ROUND((((ET38)-(EU38))+AE38),6) -> 0 | AE38: =ROUND((EU38),6) -> 0 | AF38: =ROUND((EV38),6) -> 0 | AG38: =ROUND((AP38),6) -> 0 | AH38: =(EW38) -> 0 | AI38: =(EX38) -> 0 | AJ38: =(AS38) -> 0 | AK38: 1301.25 | AL38: 1301.25 | AM38: 0 | AN38: 0 | AO38: 0 | AP38: 0 | AQ38: 0 | AR38: 0 | AS38: 0 | AT38: 0 | AU38: 0 | AV38: 1 | AW38: 1 | AZ38: 1 | BA38: 1 | BB38: 1 | BC38: 1 | BH38: 3 | BI38: 3 | BM38: 746 | BN38: 0 | BP38: 0 | BQ38: 130 | BR38: 0 | BS38: 1 | BT38: 1 | BU38: 1 | BV38: 1 | BW38: 1 | BX38: 1 | BZ38: 0 | CA38: 0 | CE38: 1566 | CF38: 0 | CG38: 0 | CM38: 0 | CO38: 0 | CP38: =(P38+Q38+S38) -> 141836.25 | CQ38: =ROUND((ROUND((AC38*1),2)*BC38),2) -> 1301.25 | CR38: =(ROUND((ROUND(((ET38)*AV38*1),2)*BB38),2)+ROUND((ROUND(((AE38-(EU38))*AV38*1),2)*BS38),2)) -> 0 | CS38: =(ROUND((ROUND(((EU38)*AV38*1),2)*BS38),2)+ROUND((ROUND(((AE38-(EU38))*AV38*1),2)*BS38),2)) -> 0 | CT38: =ROUND((ROUND((AF38*AV38*1),2)*BA38),2) -> 0 | CU38: =AG38 -> 0 | CV38: =(AH38*AV38) -> 0 | CW38: =AI38 -> 0 | CX38: =AJ38 -> 0 | CY38: =(ROUND((((S38+ROUND((ROUND(((EU38)*AV38*1),2)*BS38),2))*AT38)/100),2)+ROUND(((ROUND((ROUND(((AE38-(EU38))*AV38*1),2)*BS38),2)*AT38)/100),2)) -> 0 | CZ38: =(ROUND((((S38+ROUND((ROUND(((EU38)*AV38*1),2)*BS38),2))*AU38)/100),2)+ROUND(((ROUND((ROUND(((AE38-(EU38))*AV38*1),2)*BS38),2)*AU38)/100),2)) -> 0 | DN38: 0 | DO38: 0 | DP38: 1 | DQ38: 1 | DU38: 1013 | DV38: ШТ | DW38: ШТ | DX38: 1 | EE38: 60088638 | EF38: 130 | EG38: Сметная стоимость оборудования | EH38: 0 | EJ38: 3 | EK38: 746 | EL38: ТСН-2001.13. Сметная стоимость оборудования | EM38: ТСН-2001.13 | EQ38: 0 | ER38: 0 | ES38: 1301.25 | ET38: 0 | EU38: 0 | EV38: 0 | EW38: 0 | EX38: 0 | EY38: 0 | FQ38: 0 | FR38: =P38 -> 141836.25 | FS38: 0 | FX38: 0 | FY38: 0 | GA38: [11 475 / 1,2 / 7,66] + 3% Трансп + 1,2% Заг.скл | GD38: 1 | GF38: -758232571 | GG38: 2 | GH38: 4 | GI38: -2 | GJ38: 0 | GK38: 0 | GL38: =ROUND(IF(AND(BH38=3,BI38=3,FS38<>0),P38,0),2) -> 0 | GM38: =ROUND(O38+X38+Y38,2)+GX38 -> 141836.25 | GN38: =IF(OR(BI38=0,BI38=1),GM38-GX38,0) -> 0 | GO38: =IF(BI38=2,GM38-GX38,0) -> 0 | GP38: =IF(BI38=4,GM38-GX38,0) -> 0 | GR38: 0 | GS38: 2 | GT38: 0 | GV38: =ROUND((GT38),6) -> 0 | GW38: 1 | GX38: =ROUND(HC38*I38,2) -> 0 | HA38: 0 | HB38: 0 | HC38: =GV38*GW38 -> 0 | HE38: 3 | HF38: 1,2 | HS38: 0 | IK38: 0
A39: 17 | B39: 1 | E39: 6 | F39: КА-3 | G39: Купольная IP-видеокамера с фиксированным объективом IP 2 Мп; 1/2.8" КМОП, 1920х1080-25/30к/с; встроенный микрофон; Дальность ИК подсветки 25м; объектив 2.8мм(3.6мм, 6ммопционально) ; режим "день/ночь", H264/ MJPEG ( Доп. поток) ; ; PoE 5 Вт; TR-D2D2 v2 2.7-13.5 | H39: ШТ | I39: 109 | J39: 0 | K39: 109 | O39: =ROUND(CP39,2) -> 1086465.7 | P39: =ROUND((ROUND((AC39*I39),2)*BC39),2) -> 1086465.7 | Q39: =(ROUND((ROUND(((ET39)*AV39*I39),2)*BB39),2)+ROUND((ROUND(((AE39-(EU39))*AV39*I39),2)*BS39),2)) -> 0 | R39: =(ROUND((ROUND(((EU39)*AV39*I39),2)*BS39),2)+ROUND((ROUND(((AE39-(EU39))*AV39*I39),2)*BS39),2)) -> 0 | S39: =ROUND((ROUND((AF39*AV39*I39),2)*BA39),2) -> 0 | T39: =ROUND(CU39*I39,2) -> 0 | U39: =CV39*I39 -> 0 | V39: =CW39*I39 -> 0 | W39: =ROUND(CX39*I39,2) -> 0 | X39: =(ROUND((((S39+ROUND((ROUND(((EU39)*AV39*I39),2)*BS39),2))*AT39)/100),2)+ROUND(((ROUND((ROUND(((AE39-(EU39))*AV39*I39),2)*BS39),2)*AT39)/100),2)) -> 0 | Y39: =(ROUND((((S39+ROUND((ROUND(((EU39)*AV39*I39),2)*BS39),2))*AU39)/100),2)+ROUND(((ROUND((ROUND(((AE39-(EU39))*AV39*I39),2)*BS39),2)*AU39)/100),2)) -> 0 | AA39: 60258061 | AB39: =ROUND((AC39+AD39+AF39),6) -> 1301.25 | AC39: =ROUND((ES39),6) -> 1301.25 | AD39: =ROUND((((ET39)-(EU39))+AE39),6) -> 0 | AE39: =ROUND((EU39),6) -> 0 | AF39: =ROUND((EV39),6) -> 0 | AG39: =ROUND((AP39),6) -> 0 | AH39: =(EW39) -> 0 | AI39: =(EX39) -> 0 | AJ39: =(AS39) -> 0 | AK39: 1301.25 | AL39: 1301.25 | AM39: 0 | AN39: 0 | AO39: 0 | AP39: 0 | AQ39: 0 | AR39: 0 | AS39: 0 | AT39: 0 | AU39: 0 | AV39: 1 | AW39: 1 | AZ39: 1 | BA39: 1 | BB39: 1 | BC39: 7.66 | BH39: 3 | BI39: 3 | BM39: 746 | BN39: 0 | BP39: 0 | BQ39: 130 | BR39: 0 | BS39: 1 | BT39: 1 | BU39: 1 | BV39: 1 | BW39: 1 | BX39: 1 | BZ39: 0 | CA39: 0 | CE39: 1566 | CF39: 0 | CG39: 0 | CM39: 0 | CO39: 0 | CP39: =(P39+Q39+S39) -> 1086465.7 | CQ39: =ROUND((ROUND((AC39*1),2)*BC39),2) -> 9967.58 | CR39: =(ROUND((ROUND(((ET39)*AV39*1),2)*BB39),2)+ROUND((ROUND(((AE39-(EU39))*AV39*1),2)*BS39),2)) -> 0 | CS39: =(ROUND((ROUND(((EU39)*AV39*1),2)*BS39),2)+ROUND((ROUND(((AE39-(EU39))*AV39*1),2)*BS39),2)) -> 0 | CT39: =ROUND((ROUND((AF39*AV39*1),2)*BA39),2) -> 0 | CU39: =AG39 -> 0 | CV39: =(AH39*AV39) -> 0 | CW39: =AI39 -> 0 | CX39: =AJ39 -> 0 | CY39: =(ROUND((((S39+ROUND((ROUND(((EU39)*AV39*1),2)*BS39),2))*AT39)/100),2)+ROUND(((ROUND((ROUND(((AE39-(EU39))*AV39*1),2)*BS39),2)*AT39)/100),2)) -> 0 | CZ39: =(ROUND((((S39+ROUND((ROUND(((EU39)*AV39*1),2)*BS39),2))*AU39)/100),2)+ROUND(((ROUND((ROUND(((AE39-(EU39))*AV39*1),2)*BS39),2)*AU39)/100),2)) -> 0 | DN39: 0 | DO39: 0 | DP39: 1 | DQ39: 1 | DU39: 1013 | DV39: ШТ | DW39: ШТ | DX39: 1 | EE39: 60088638 | EF39: 130 | EG39: Сметная стоимость оборудования | EH39: 0 | EJ39: 3 | EK39: 746 | EL39: ТСН-2001.13. Сметная стоимость оборудования | EM39: ТСН-2001.13 | EQ39: 0 | ER39: 0 | ES39: 1301.25 | ET39: 0 | EU39: 0 | EV39: 0 | EW39: 0 | EX39: 0 | EY39: 0 | EZ39: 5 | FC39: 1 | FD39: 18 | FF39: 11475 | FQ39: 0 | FR39: =P39 -> 1086465.7 | FS39: 0 | FX39: 0 | FY39: 0 | GA39: [11 475 / 1,2 / 7,66] + 3% Трансп + 1,2% Заг.скл | GD39: 1 | GF39: -758232571 | GG39: 2 | GH39: 3 | GI39: 5 | GJ39: 0 | GK39: 0 | GL39: =ROUND(IF(AND(BH39=3,BI39=3,FS39<>0),P39,0),2) -> 0 | GM39: =ROUND(O39+X39+Y39,2)+GX39 -> 1086465.7 | GN39: =IF(OR(BI39=0,BI39=1),GM39-GX39,0) -> 0 | GO39: =IF(BI39=2,GM39-GX39,0) -> 0 | GP39: =IF(BI39=4,GM39-GX39,0) -> 0 | GR39: 1 | GS39: 1 | GT39: 0 | GV39: =ROUND((GT39),6) -> 0 | GW39: 1 | GX39: =ROUND(HC39*I39,2) -> 0 | HA39: 0 | HB39: 0 | HC39: =GV39*GW39 -> 0 | HE39: 3 | HF39: 1,2 | HS39: 0 | IK39: 0
A40: 17 | B40: 1 | C40: =ROW(SmtRes!A31) -> 31 | D40: =ROW(EtalonRes!A37) -> 37 | E40: 7 | F40: 4.10-72-14 | G40: Монтаж устройства цифровой регистрации | H40: 1 устройство | I40: 1 | J40: 0 | K40: 1 | O40: =ROUND(CP40,2) -> 110.65 | P40: =ROUND((ROUND((AC40*AW40*I40),2)*BC40),2) -> 1.1 | Q40: =(ROUND((ROUND((((ET40*1.1))*AV40*I40),2)*BB40),2)+ROUND((ROUND(((AE40-((EU40*1.1)))*AV40*I40),2)*BS40),2)) -> 0 | R40: =(ROUND((ROUND((((EU40*1.1))*AV40*I40),2)*BS40),2)+ROUND((ROUND(((AE40-((EU40*1.1)))*AV40*I40),2)*BS40),2)) -> 0 | S40: =ROUND((ROUND((AF40*AV40*I40),2)*BA40),2) -> 109.55 | T40: =ROUND(CU40*I40,2) -> 0 | U40: =CV40*I40 -> 9.2136 | V40: =CW40*I40 -> 0 | W40: =ROUND(CX40*I40,2) -> 0 | X40: =(ROUND((((S40+ROUND((ROUND((((EU40*1.1))*AV40*I40),2)*BS40),2))*AT40)/100),2)+ROUND(((ROUND((ROUND(((AE40-((EU40*1.1)))*AV40*I40),2)*BS40),2)*AT40)/100),2)) -> 104.07 | Y40: =(ROUND((((S40+ROUND((ROUND((((EU40*1.1))*AV40*I40),2)*BS40),2))*AU40)/100),2)+ROUND(((ROUND((ROUND(((AE40-((EU40*1.1)))*AV40*I40),2)*BS40),2)*AU40)/100),2)) -> 58.06 | AA40: 60258064 | AB40: =ROUND((AC40+AD40+AF40),6) -> 105.732 | AC40: =ROUND((ES40),6) -> 1.1 | AD40: =ROUND(((((ET40*1.1))-((EU40*1.1)))+AE40),6) -> 0 | AE40: =ROUND(((EU40*1.1)),6) -> 0 | AF40: =ROUND(((EV40*1.1)),6) -> 104.632 | AG40: =ROUND((AP40),6) -> 0 | AH40: =((EW40*1.1)) -> 8.8 | AI40: =((EX40*1.1)) -> 0 | AJ40: =(AS40) -> 0 | AK40: 96.22 | AL40: 1.1 | AM40: 0 | AN40: 0 | AO40: 95.12 | AP40: 0 | AQ40: 8 | AR40: 0 | AS40: 0 | AT40: 95 | AU40: 53 | AV40: 1.047 | AW40: 1 | AZ40: 1 | BA40: 1 | BB40: 1 | BC40: 1 | BH40: 0 | BI40: 2 | BJ40: ТСН-2001.4 Доп. 67, Сб. 10, т. 72, поз. 14 | BM40: 69 | BN40: 58973116 | BO40: 4.10-72-14 | BP40: 1 | BQ40: 40 | BR40: 0 | BS40: 1 | BT40: 1 | BU40: 1 | BV40: 1 | BW40: 1 | BX40: 1 | BZ40: 95 | CA40: 53 | CE40: 1566 | CF40: 0 | CG40: 0 | CM40: 0 | CN40: Поправка: О.П. п.3.4.30.в Наименование: При применении территориальных сметных нормативов для города Москвы затраты, учитывающие напряженные и стесненные условия производства работ (стесненность, сложность складирования и транспортной логистики и т.п.), исчисляются с применением коэффициентов к затратам труда и заработной плате рабочих, машинистов, времени эксплуатации машин и механизмов, стоимости эксплуатации машин в размере: для объектов, расположенных за пределами Третьего транспортного кольца города Москвы, но в пределах Московской кольцевой автомобильной дороги | CO40: 0 | CP40: =(P40+Q40+S40) -> 110.65 | CQ40: =ROUND((ROUND((AC40*AW40*1),2)*BC40),2) -> 1.1 | CR40: =(ROUND((ROUND((((ET40*1.1))*AV40*1),2)*BB40),2)+ROUND((ROUND(((AE40-((EU40*1.1)))*AV40*1),2)*BS40),2)) -> 0 | CS40: =(ROUND((ROUND((((EU40*1.1))*AV40*1),2)*BS40),2)+ROUND((ROUND(((AE40-((EU40*1.1)))*AV40*1),2)*BS40),2)) -> 0 | CT40: =ROUND((ROUND((AF40*AV40*1),2)*BA40),2) -> 109.55 | CU40: =AG40 -> 0 | CV40: =(AH40*AV40) -> 9.2136 | CW40: =AI40 -> 0 | CX40: =AJ40 -> 0 | CY40: =(ROUND((((S40+ROUND((ROUND((((EU40*1.1))*AV40*1),2)*BS40),2))*AT40)/100),2)+ROUND(((ROUND((ROUND(((AE40-((EU40*1.1)))*AV40*1),2)*BS40),2)*AT40)/100),2)) -> 104.07 | CZ40: =(ROUND((((S40+ROUND((ROUND((((EU40*1.1))*AV40*1),2)*BS40),2))*AU40)/100),2)+ROUND(((ROUND((ROUND(((AE40-((EU40*1.1)))*AV40*1),2)*BS40),2)*AU40)/100),2)) -> 58.06 | DB40: 7 | DE40: *1,1 | DF40: *1,1 | DG40: *1,1 | DI40: *1,1 | DJ40: *1,1 | DN40: 0 | DO40: 0 | DP40: 1 | DQ40: 1 | DU40: 1013 | DV40: 1 устройство | DW40: 1 устройство | DX40: 1 | EE40: 60088533 | EF40: 40 | EG40: Монтаж оборудования | EH40: 0 | EJ40: 2 | EK40: 69 | EL40: ТСН-2001.4-10. Монтаж радиотелевизионного и электронного оборудования | EM40: ТСН-2001.4-10-2 | EO40: Поправка: О.П. п.3.4.30.в | EQ40: 0 | ER40: 96.22 | ES40: 1.1 | ET40: 0 | EU40: 0 | EV40: 95.12 | EW40: 8 | EX40: 0 | EY40: 0 | FQ40: 0 | FR40: 0 | FS40: 0 | FX40: 95 | FY40: 53 | GD40: 1 | GF40: 2121377083 | GG40: 2 | GH40: 1 | GI40: 2 | GJ40: 0 | GK40: 0 | GL40: =ROUND(IF(AND(BH40=3,BI40=3,FS40<>0),P40,0),2) -> 0 | GM40: =ROUND(O40+X40+Y40,2)+GX40 -> 272.78 | GN40: =IF(OR(BI40=0,BI40=1),GM40-GX40,0) -> 0 | GO40: =IF(BI40=2,GM40-GX40,0) -> 272.78 | GP40: =IF(BI40=4,GM40-GX40,0) -> 0 | GR40: 0 | GS40: 3 | GT40: 0 | GV40: =ROUND((GT40),6) -> 0 | GW40: 1 | GX40: =ROUND(HC40*I40,2) -> 0 | HA40: 0 | HB40: 0 | HC40: =GV40*GW40 -> 0 | HS40: 0 | IK40: 0
A41: 17 | B41: 1 | C41: =ROW(SmtRes!A36) -> 36 | D41: =ROW(EtalonRes!A44) -> 44 | E41: 7 | F41: 4.10-72-14 | G41: Монтаж устройства цифровой регистрации | H41: 1 устройство | I41: 1 | J41: 0 | K41: 1 | O41: =ROUND(CP41,2) -> 6042.54 | P41: =ROUND((ROUND((AC41*AW41*I41),2)*BC41),2) -> 18.39 | Q41: =(ROUND((ROUND((((ET41*1.1))*AV41*I41),2)*BB41),2)+ROUND((ROUND(((AE41-((EU41*1.1)))*AV41*I41),2)*BS41),2)) -> 0 | R41: =(ROUND((ROUND((((EU41*1.1))*AV41*I41),2)*BS41),2)+ROUND((ROUND(((AE41-((EU41*1.1)))*AV41*I41),2)*BS41),2)) -> 0 | S41: =ROUND((ROUND((AF41*AV41*I41),2)*BA41),2) -> 6024.15 | T41: =ROUND(CU41*I41,2) -> 0 | U41: =CV41*I41 -> 9.2136 | V41: =CW41*I41 -> 0 | W41: =ROUND(CX41*I41,2) -> 0 | X41: =(ROUND((((S41+ROUND((ROUND((((EU41*1.1))*AV41*I41),2)*BS41),2))*AT41)/100),2)+ROUND(((ROUND((ROUND(((AE41-((EU41*1.1)))*AV41*I41),2)*BS41),2)*AT41)/100),2)) -> 5722.94 | Y41: =(ROUND((((S41+ROUND((ROUND((((EU41*1.1))*AV41*I41),2)*BS41),2))*AU41)/100),2)+ROUND(((ROUND((ROUND(((AE41-((EU41*1.1)))*AV41*I41),2)*BS41),2)*AU41)/100),2)) -> 3192.8 | AA41: 60258061 | AB41: =ROUND((AC41+AD41+AF41),6) -> 105.732 | AC41: =ROUND((ES41),6) -> 1.1 | AD41: =ROUND(((((ET41*1.1))-((EU41*1.1)))+AE41),6) -> 0 | AE41: =ROUND(((EU41*1.1)),6) -> 0 | AF41: =ROUND(((EV41*1.1)),6) -> 104.632 | AG41: =ROUND((AP41),6) -> 0 | AH41: =((EW41*1.1)) -> 8.8 | AI41: =((EX41*1.1)) -> 0 | AJ41: =(AS41) -> 0 | AK41: 96.22 | AL41: 1.1 | AM41: 0 | AN41: 0 | AO41: 95.12 | AP41: 0 | AQ41: 8 | AR41: 0 | AS41: 0 | AT41: 95 | AU41: 53 | AV41: 1.047 | AW41: 1 | AZ41: 1 | BA41: 54.99 | BB41: 1 | BC41: 16.72 | BH41: 0 | BI41: 2 | BJ41: ТСН-2001.4 Доп. 67, Сб. 10, т. 72, поз. 14 | BM41: 69 | BN41: 58973116 | BO41: 4.10-72-14 | BP41: 1 | BQ41: 40 | BR41: 0 | BS41: 54.99 | BT41: 1 | BU41: 1 | BV41: 1 | BW41: 1 | BX41: 1 | BZ41: 95 | CA41: 53 | CE41: 1566 | CF41: 0 | CG41: 0 | CM41: 0 | CN41: Поправка: О.П. п.3.4.30.в Наименование: При применении территориальных сметных нормативов для города Москвы затраты, учитывающие напряженные и стесненные условия производства работ (стесненность, сложность складирования и транспортной логистики и т.п.), исчисляются с применением коэффициентов к затратам труда и заработной плате рабочих, машинистов, времени эксплуатации машин и механизмов, стоимости эксплуатации машин в размере: для объектов, расположенных за пределами Третьего транспортного кольца города Москвы, но в пределах Московской кольцевой автомобильной дороги | CO41: 0 | CP41: =(P41+Q41+S41) -> 6042.54 | CQ41: =ROUND((ROUND((AC41*AW41*1),2)*BC41),2) -> 18.39 | CR41: =(ROUND((ROUND((((ET41*1.1))*AV41*1),2)*BB41),2)+ROUND((ROUND(((AE41-((EU41*1.1)))*AV41*1),2)*BS41),2)) -> 0 | CS41: =(ROUND((ROUND((((EU41*1.1))*AV41*1),2)*BS41),2)+ROUND((ROUND(((AE41-((EU41*1.1)))*AV41*1),2)*BS41),2)) -> 0 | CT41: =ROUND((ROUND((AF41*AV41*1),2)*BA41),2) -> 6024.15 | CU41: =AG41 -> 0 | CV41: =(AH41*AV41) -> 9.2136 | CW41: =AI41 -> 0 | CX41: =AJ41 -> 0 | CY41: =(ROUND((((S41+ROUND((ROUND((((EU41*1.1))*AV41*1),2)*BS41),2))*AT41)/100),2)+ROUND(((ROUND((ROUND(((AE41-((EU41*1.1)))*AV41*1),2)*BS41),2)*AT41)/100),2)) -> 5722.94 | CZ41: =(ROUND((((S41+ROUND((ROUND((((EU41*1.1))*AV41*1),2)*BS41),2))*AU41)/100),2)+ROUND(((ROUND((ROUND(((AE41-((EU41*1.1)))*AV41*1),2)*BS41),2)*AU41)/100),2)) -> 3192.8 | DB41: 8 | DE41: *1,1 | DF41: *1,1 | DG41: *1,1 | DI41: *1,1 | DJ41: *1,1 | DN41: 0 | DO41: 0 | DP41: 1 | DQ41: 1 | DU41: 1013 | DV41: 1 устройство | DW41: 1 устройство | DX41: 1 | EE41: 60088533 | EF41: 40 | EG41: Монтаж оборудования | EH41: 0 | EJ41: 2 | EK41: 69 | EL41: ТСН-2001.4-10. Монтаж радиотелевизионного и электронного оборудования | EM41: ТСН-2001.4-10-2 | EO41: Поправка: О.П. п.3.4.30.в | EQ41: 0 | ER41: 96.22 | ES41: 1.1 | ET41: 0 | EU41: 0 | EV41: 95.12 | EW41: 8 | EX41: 0 | EY41: 0 | FQ41: 0 | FR41: 0 | FS41: 0 | FX41: 95 | FY41: 53 | GD41: 1 | GF41: 2121377083 | GG41: 2 | GH41: 1 | GI41: 2 | GJ41: 0 | GK41: 0 | GL41: =ROUND(IF(AND(BH41=3,BI41=3,FS41<>0),P41,0),2) -> 0 | GM41: =ROUND(O41+X41+Y41,2)+GX41 -> 14958.28 | GN41: =IF(OR(BI41=0,BI41=1),GM41-GX41,0) -> 0 | GO41: =IF(BI41=2,GM41-GX41,0) -> 14958.28 | GP41: =IF(BI41=4,GM41-GX41,0) -> 0 | GR41: 0 | GS41: 3 | GT41: 0 | GV41: =ROUND((GT41),6) -> 0 | GW41: 1 | GX41: =ROUND(HC41*I41,2) -> 0 | HA41: 0 | HB41: 0 | HC41: =GV41*GW41 -> 0 | HS41: 0 | IK41: 0
A42: 17 | B42: 1 | E42: 8 | F42: КА-4 | G42: IP-видеорегистратор UltraStation 24/10 на 256 каналов, 24 HDD на 10 Тбайт UltraStation 24/10 256 v2 с 24 HDD | H42: ШТ | I42: 1 | J42: 0 | K42: 1 | O42: =ROUND(CP42,2) -> 304239.85 | P42: =ROUND((ROUND((AC42*I42),2)*BC42),2) -> 304239.85 | Q42: =(ROUND((ROUND(((ET42)*AV42*I42),2)*BB42),2)+ROUND((ROUND(((AE42-(EU42))*AV42*I42),2)*BS42),2)) -> 0 | R42: =(ROUND((ROUND(((EU42)*AV42*I42),2)*BS42),2)+ROUND((ROUND(((AE42-(EU42))*AV42*I42),2)*BS42),2)) -> 0 | S42: =ROUND((ROUND((AF42*AV42*I42),2)*BA42),2) -> 0 | T42: =ROUND(CU42*I42,2) -> 0 | U42: =CV42*I42 -> 0 | V42: =CW42*I42 -> 0 | W42: =ROUND(CX42*I42,2) -> 0 | X42: =(ROUND((((S42+ROUND((ROUND(((EU42)*AV42*I42),2)*BS42),2))*AT42)/100),2)+ROUND(((ROUND((ROUND(((AE42-(EU42))*AV42*I42),2)*BS42),2)*AT42)/100),2)) -> 0 | Y42: =(ROUND((((S42+ROUND((ROUND(((EU42)*AV42*I42),2)*BS42),2))*AU42)/100),2)+ROUND(((ROUND((ROUND(((AE42-(EU42))*AV42*I42),2)*BS42),2)*AU42)/100),2)) -> 0 | AA42: 60258064 | AB42: =ROUND((AC42+AD42+AF42),6) -> 304239.85 | AC42: =ROUND((ES42),6) -> 304239.85 | AD42: =ROUND((((ET42)-(EU42))+AE42),6) -> 0 | AE42: =ROUND((EU42),6) -> 0 | AF42: =ROUND((EV42),6) -> 0 | AG42: =ROUND((AP42),6) -> 0 | AH42: =(EW42) -> 0 | AI42: =(EX42) -> 0 | AJ42: =(AS42) -> 0 | AK42: 304239.85 | AL42: 304239.85 | AM42: 0 | AN42: 0 | AO42: 0 | AP42: 0 | AQ42: 0 | AR42: 0 | AS42: 0 | AT42: 0 | AU42: 0 | AV42: 1 | AW42: 1 | AZ42: 1 | BA42: 1 | BB42: 1 | BC42: 1 | BH42: 3 | BI42: 3 | BM42: 746 | BN42: 0 | BP42: 0 | BQ42: 130 | BR42: 0 | BS42: 1 | BT42: 1 | BU42: 1 | BV42: 1 | BW42: 1 | BX42: 1 | BZ42: 0 | CA42: 0 | CE42: 1566 | CF42: 0 | CG42: 0 | CM42: 0 | CO42: 0 | CP42: =(P42+Q42+S42) -> 304239.85 | CQ42: =ROUND((ROUND((AC42*1),2)*BC42),2) -> 304239.85 | CR42: =(ROUND((ROUND(((ET42)*AV42*1),2)*BB42),2)+ROUND((ROUND(((AE42-(EU42))*AV42*1),2)*BS42),2)) -> 0 | CS42: =(ROUND((ROUND(((EU42)*AV42*1),2)*BS42),2)+ROUND((ROUND(((AE42-(EU42))*AV42*1),2)*BS42),2)) -> 0 | CT42: =ROUND((ROUND((AF42*AV42*1),2)*BA42),2) -> 0 | CU42: =AG42 -> 0 | CV42: =(AH42*AV42) -> 0 | CW42: =AI42 -> 0 | CX42: =AJ42 -> 0 | CY42: =(ROUND((((S42+ROUND((ROUND(((EU42)*AV42*1),2)*BS42),2))*AT42)/100),2)+ROUND(((ROUND((ROUND(((AE42-(EU42))*AV42*1),2)*BS42),2)*AT42)/100),2)) -> 0 | CZ42: =(ROUND((((S42+ROUND((ROUND(((EU42)*AV42*1),2)*BS42),2))*AU42)/100),2)+ROUND(((ROUND((ROUND(((AE42-(EU42))*AV42*1),2)*BS42),2)*AU42)/100),2)) -> 0 | DN42: 0 | DO42: 0 | DP42: 1 | DQ42: 1 | DU42: 1013 | DV42: ШТ | DW42: ШТ | DX42: 1 | EE42: 60088638 | EF42: 130 | EG42: Сметная стоимость оборудования | EH42: 0 | EJ42: 3 | EK42: 746 | EL42: ТСН-2001.13. Сметная стоимость оборудования | EM42: ТСН-2001.13 | EQ42: 0 | ER42: 0 | ES42: 304239.85 | ET42: 0 | EU42: 0 | EV42: 0 | EW42: 0 | EX42: 0 | EY42: 0 | FQ42: 0 | FR42: =P42 -> 304239.85 | FS42: 0 | FX42: 0 | FY42: 0 | GA42: [2 682 924 / 1,2 / 7,66] + 3% Трансп + 1,2% Заг.скл | GD42: 1 | GF42: 183725230 | GG42: 2 | GH42: 4 | GI42: -2 | GJ42: 0 | GK42: 0 | GL42: =ROUND(IF(AND(BH42=3,BI42=3,FS42<>0),P42,0),2) -> 0 | GM42: =ROUND(O42+X42+Y42,2)+GX42 -> 304239.85 | GN42: =IF(OR(BI42=0,BI42=1),GM42-GX42,0) -> 0 | GO42: =IF(BI42=2,GM42-GX42,0) -> 0 | GP42: =IF(BI42=4,GM42-GX42,0) -> 0 | GR42: 0 | GS42: 2 | GT42: 0 | GV42: =ROUND((GT42),6) -> 0 | GW42: 1 | GX42: =ROUND(HC42*I42,2) -> 0 | HA42: 0 | HB42: 0 | HC42: =GV42*GW42 -> 0 | HE42: 3 | HF42: 1,2 | HS42: 0 | IK42: 0
A43: 17 | B43: 1 | E43: 8 | F43: КА-4 | G43: IP-видеорегистратор UltraStation 24/10 на 256 каналов, 24 HDD на 10 Тбайт UltraStation 24/10 256 v2 с 24 HDD | H43: ШТ | I43: 1 | J43: 0 | K43: 1 | O43: =ROUND(CP43,2) -> 2330477.2 | P43: =ROUND((ROUND((AC43*I43),2)*BC43),2) -> 2330477.2 | Q43: =(ROUND((ROUND(((ET43)*AV43*I43),2)*BB43),2)+ROUND((ROUND(((AE43-(EU43))*AV43*I43),2)*BS43),2)) -> 0 | R43: =(ROUND((ROUND(((EU43)*AV43*I43),2)*BS43),2)+ROUND((ROUND(((AE43-(EU43))*AV43*I43),2)*BS43),2)) -> 0 | S43: =ROUND((ROUND((AF43*AV43*I43),2)*BA43),2) -> 0 | T43: =ROUND(CU43*I43,2) -> 0 | U43: =CV43*I43 -> 0 | V43: =CW43*I43 -> 0 | W43: =ROUND(CX43*I43,2) -> 0 | X43: =(ROUND((((S43+ROUND((ROUND(((EU43)*AV43*I43),2)*BS43),2))*AT43)/100),2)+ROUND(((ROUND((ROUND(((AE43-(EU43))*AV43*I43),2)*BS43),2)*AT43)/100),2)) -> 0 | Y43: =(ROUND((((S43+ROUND((ROUND(((EU43)*AV43*I43),2)*BS43),2))*AU43)/100),2)+ROUND(((ROUND((ROUND(((AE43-(EU43))*AV43*I43),2)*BS43),2)*AU43)/100),2)) -> 0 | AA43: 60258061 | AB43: =ROUND((AC43+AD43+AF43),6) -> 304239.85 | AC43: =ROUND((ES43),6) -> 304239.85 | AD43: =ROUND((((ET43)-(EU43))+AE43),6) -> 0 | AE43: =ROUND((EU43),6) -> 0 | AF43: =ROUND((EV43),6) -> 0 | AG43: =ROUND((AP43),6) -> 0 | AH43: =(EW43) -> 0 | AI43: =(EX43) -> 0 | AJ43: =(AS43) -> 0 | AK43: 304239.85 | AL43: 304239.85 | AM43: 0 | AN43: 0 | AO43: 0 | AP43: 0 | AQ43: 0 | AR43: 0 | AS43: 0 | AT43: 0 | AU43: 0 | AV43: 1 | AW43: 1 | AZ43: 1 | BA43: 1 | BB43: 1 | BC43: 7.66 | BH43: 3 | BI43: 3 | BM43: 746 | BN43: 0 | BP43: 0 | BQ43: 130 | BR43: 0 | BS43: 1 | BT43: 1 | BU43: 1 | BV43: 1 | BW43: 1 | BX43: 1 | BZ43: 0 | CA43: 0 | CE43: 1566 | CF43: 0 | CG43: 0 | CM43: 0 | CO43: 0 | CP43: =(P43+Q43+S43) -> 2330477.2 | CQ43: =ROUND((ROUND((AC43*1),2)*BC43),2) -> 2330477.2 | CR43: =(ROUND((ROUND(((ET43)*AV43*1),2)*BB43),2)+ROUND((ROUND(((AE43-(EU43))*AV43*1),2)*BS43),2)) -> 0 | CS43: =(ROUND((ROUND(((EU43)*AV43*1),2)*BS43),2)+ROUND((ROUND(((AE43-(EU43))*AV43*1),2)*BS43),2)) -> 0 | CT43: =ROUND((ROUND((AF43*AV43*1),2)*BA43),2) -> 0 | CU43: =AG43 -> 0 | CV43: =(AH43*AV43) -> 0 | CW43: =AI43 -> 0 | CX43: =AJ43 -> 0 | CY43: =(ROUND((((S43+ROUND((ROUND(((EU43)*AV43*1),2)*BS43),2))*AT43)/100),2)+ROUND(((ROUND((ROUND(((AE43-(EU43))*AV43*1),2)*BS43),2)*AT43)/100),2)) -> 0 | CZ43: =(ROUND((((S43+ROUND((ROUND(((EU43)*AV43*1),2)*BS43),2))*AU43)/100),2)+ROUND(((ROUND((ROUND(((AE43-(EU43))*AV43*1),2)*BS43),2)*AU43)/100),2)) -> 0 | DN43: 0 | DO43: 0 | DP43: 1 | DQ43: 1 | DU43: 1013 | DV43: ШТ | DW43: ШТ | DX43: 1 | EE43: 60088638 | EF43: 130 | EG43: Сметная стоимость оборудования | EH43: 0 | EJ43: 3 | EK43: 746 | EL43: ТСН-2001.13. Сметная стоимость оборудования | EM43: ТСН-2001.13 | EQ43: 0 | ER43: 0 | ES43: 304239.85 | ET43: 0 | EU43: 0 | EV43: 0 | EW43: 0 | EX43: 0 | EY43: 0 | EZ43: 5 | FC43: 1 | FD43: 18 | FF43: 2682924 | FQ43: 0 | FR43: =P43 -> 2330477.2 | FS43: 0 | FX43: 0 | FY43: 0 | GA43: [2 682 924 / 1,2 / 7,66] + 3% Трансп + 1,2% Заг.скл | GD43: 1 | GF43: 183725230 | GG43: 2 | GH43: 3 | GI43: 5 | GJ43: 0 | GK43: 0 | GL43: =ROUND(IF(AND(BH43=3,BI43=3,FS43<>0),P43,0),2) -> 0 | GM43: =ROUND(O43+X43+Y43,2)+GX43 -> 2330477.2 | GN43: =IF(OR(BI43=0,BI43=1),GM43-GX43,0) -> 0 | GO43: =IF(BI43=2,GM43-GX43,0) -> 0 | GP43: =IF(BI43=4,GM43-GX43,0) -> 0 | GR43: 1 | GS43: 1 | GT43: 0 | GV43: =ROUND((GT43),6) -> 0 | GW43: 1 | GX43: =ROUND(HC43*I43,2) -> 0 | HA43: 0 | HB43: 0 | HC43: =GV43*GW43 -> 0 | HE43: 3 | HF43: 1,2 | HS43: 0 | IK43: 0
A44: 17 | B44: 1 | E44: 9 | F44: КА-5 | G44: Программное обеспечение TRASSIR ЕЦХД | H44: ШТ | I44: 1 | J44: 0 | K44: 1 | O44: =ROUND(CP44,2) -> 20298.35 | P44: =ROUND((ROUND((AC44*I44),2)*BC44),2) -> 20298.35 | Q44: =(ROUND((ROUND(((ET44)*AV44*I44),2)*BB44),2)+ROUND((ROUND(((AE44-(EU44))*AV44*I44),2)*BS44),2)) -> 0 | R44: =(ROUND((ROUND(((EU44)*AV44*I44),2)*BS44),2)+ROUND((ROUND(((AE44-(EU44))*AV44*I44),2)*BS44),2)) -> 0 | S44: =ROUND((ROUND((AF44*AV44*I44),2)*BA44),2) -> 0 | T44: =ROUND(CU44*I44,2) -> 0 | U44: =CV44*I44 -> 0 | V44: =CW44*I44 -> 0 | W44: =ROUND(CX44*I44,2) -> 0 | X44: =(ROUND((((S44+ROUND((ROUND(((EU44)*AV44*I44),2)*BS44),2))*AT44)/100),2)+ROUND(((ROUND((ROUND(((AE44-(EU44))*AV44*I44),2)*BS44),2)*AT44)/100),2)) -> 0 | Y44: =(ROUND((((S44+ROUND((ROUND(((EU44)*AV44*I44),2)*BS44),2))*AU44)/100),2)+ROUND(((ROUND((ROUND(((AE44-(EU44))*AV44*I44),2)*BS44),2)*AU44)/100),2)) -> 0 | AA44: 60258064 | AB44: =ROUND((AC44+AD44+AF44),6) -> 20298.35 | AC44: =ROUND((ES44),6) -> 20298.35 | AD44: =ROUND((((ET44)-(EU44))+AE44),6) -> 0 | AE44: =ROUND((EU44),6) -> 0 | AF44: =ROUND((EV44),6) -> 0 | AG44: =ROUND((AP44),6) -> 0 | AH44: =(EW44) -> 0 | AI44: =(EX44) -> 0 | AJ44: =(AS44) -> 0 | AK44: 20298.35 | AL44: 20298.35 | AM44: 0 | AN44: 0 | AO44: 0 | AP44: 0 | AQ44: 0 | AR44: 0 | AS44: 0 | AT44: 0 | AU44: 0 | AV44: 1 | AW44: 1 | AZ44: 1 | BA44: 1 | BB44: 1 | BC44: 1 | BH44: 3 | BI44: 3 | BM44: 746 | BN44: 0 | BP44: 0 | BQ44: 130 | BR44: 0 | BS44: 1 | BT44: 1 | BU44: 1 | BV44: 1 | BW44: 1 | BX44: 1 | BZ44: 0 | CA44: 0 | CE44: 1566 | CF44: 0 | CG44: 0 | CM44: 0 | CO44: 0 | CP44: =(P44+Q44+S44) -> 20298.35 | CQ44: =ROUND((ROUND((AC44*1),2)*BC44),2) -> 20298.35 | CR44: =(ROUND((ROUND(((ET44)*AV44*1),2)*BB44),2)+ROUND((ROUND(((AE44-(EU44))*AV44*1),2)*BS44),2)) -> 0 | CS44: =(ROUND((ROUND(((EU44)*AV44*1),2)*BS44),2)+ROUND((ROUND(((AE44-(EU44))*AV44*1),2)*BS44),2)) -> 0 | CT44: =ROUND((ROUND((AF44*AV44*1),2)*BA44),2) -> 0 | CU44: =AG44 -> 0 | CV44: =(AH44*AV44) -> 0 | CW44: =AI44 -> 0 | CX44: =AJ44 -> 0 | CY44: =(ROUND((((S44+ROUND((ROUND(((EU44)*AV44*1),2)*BS44),2))*AT44)/100),2)+ROUND(((ROUND((ROUND(((AE44-(EU44))*AV44*1),2)*BS44),2)*AT44)/100),2)) -> 0 | CZ44: =(ROUND((((S44+ROUND((ROUND(((EU44)*AV44*1),2)*BS44),2))*AU44)/100),2)+ROUND(((ROUND((ROUND(((AE44-(EU44))*AV44*1),2)*BS44),2)*AU44)/100),2)) -> 0 | DN44: 0 | DO44: 0 | DP44: 1 | DQ44: 1 | DU44: 1013 | DV44: ШТ | DW44: ШТ | DX44: 1 | EE44: 60088638 | EF44: 130 | EG44: Сметная стоимость оборудования | EH44: 0 | EJ44: 3 | EK44: 746 | EL44: ТСН-2001.13. Сметная стоимость оборудования | EM44: ТСН-2001.13 | EQ44: 0 | ER44: 0 | ES44: 20298.35 | ET44: 0 | EU44: 0 | EV44: 0 | EW44: 0 | EX44: 0 | EY44: 0 | FQ44: 0 | FR44: =P44 -> 20298.35 | FS44: 0 | FX44: 0 | FY44: 0 | GA44: [179 000 / 1,2 / 7,66] + 3% Трансп + 1,2% Заг.скл | GD44: 1 | GF44: 867537067 | GG44: 2 | GH44: 4 | GI44: -2 | GJ44: 0 | GK44: 0 | GL44: =ROUND(IF(AND(BH44=3,BI44=3,FS44<>0),P44,0),2) -> 0 | GM44: =ROUND(O44+X44+Y44,2)+GX44 -> 20298.35 | GN44: =IF(OR(BI44=0,BI44=1),GM44-GX44,0) -> 0 | GO44: =IF(BI44=2,GM44-GX44,0) -> 0 | GP44: =IF(BI44=4,GM44-GX44,0) -> 0 | GR44: 0 | GS44: 2 | GT44: 0 | GV44: =ROUND((GT44),6) -> 0 | GW44: 1 | GX44: =ROUND(HC44*I44,2) -> 0 | HA44: 0 | HB44: 0 | HC44: =GV44*GW44 -> 0 | HE44: 3 | HF44: 1,2 | HS44: 0 | IK44: 0
A45: 17 | B45: 1 | E45: 9 | F45: КА-5 | G45: Программное обеспечение TRASSIR ЕЦХД | H45: ШТ | I45: 1 | J45: 0 | K45: 1 | O45: =ROUND(CP45,2) -> 155485.36 | P45: =ROUND((ROUND((AC45*I45),2)*BC45),2) -> 155485.36 | Q45: =(ROUND((ROUND(((ET45)*AV45*I45),2)*BB45),2)+ROUND((ROUND(((AE45-(EU45))*AV45*I45),2)*BS45),2)) -> 0 | R45: =(ROUND((ROUND(((EU45)*AV45*I45),2)*BS45),2)+ROUND((ROUND(((AE45-(EU45))*AV45*I45),2)*BS45),2)) -> 0 | S45: =ROUND((ROUND((AF45*AV45*I45),2)*BA45),2) -> 0 | T45: =ROUND(CU45*I45,2) -> 0 | U45: =CV45*I45 -> 0 | V45: =CW45*I45 -> 0 | W45: =ROUND(CX45*I45,2) -> 0 | X45: =(ROUND((((S45+ROUND((ROUND(((EU45)*AV45*I45),2)*BS45),2))*AT45)/100),2)+ROUND(((ROUND((ROUND(((AE45-(EU45))*AV45*I45),2)*BS45),2)*AT45)/100),2)) -> 0 | Y45: =(ROUND((((S45+ROUND((ROUND(((EU45)*AV45*I45),2)*BS45),2))*AU45)/100),2)+ROUND(((ROUND((ROUND(((AE45-(EU45))*AV45*I45),2)*BS45),2)*AU45)/100),2)) -> 0 | AA45: 60258061 | AB45: =ROUND((AC45+AD45+AF45),6) -> 20298.35 | AC45: =ROUND((ES45),6) -> 20298.35 | AD45: =ROUND((((ET45)-(EU45))+AE45),6) -> 0 | AE45: =ROUND((EU45),6) -> 0 | AF45: =ROUND((EV45),6) -> 0 | AG45: =ROUND((AP45),6) -> 0 | AH45: =(EW45) -> 0 | AI45: =(EX45) -> 0 | AJ45: =(AS45) -> 0 | AK45: 20298.35 | AL45: 20298.35 | AM45: 0 | AN45: 0 | AO45: 0 | AP45: 0 | AQ45: 0 | AR45: 0 | AS45: 0 | AT45: 0 | AU45: 0 | AV45: 1 | AW45: 1 | AZ45: 1 | BA45: 1 | BB45: 1 | BC45: 7.66 | BH45: 3 | BI45: 3 | BM45: 746 | BN45: 0 | BP45: 0 | BQ45: 130 | BR45: 0 | BS45: 1 | BT45: 1 | BU45: 1 | BV45: 1 | BW45: 1 | BX45: 1 | BZ45: 0 | CA45: 0 | CE45: 1566 | CF45: 0 | CG45: 0 | CM45: 0 | CO45: 0 | CP45: =(P45+Q45+S45) -> 155485.36 | CQ45: =ROUND((ROUND((AC45*1),2)*BC45),2) -> 155485.36 | CR45: =(ROUND((ROUND(((ET45)*AV45*1),2)*BB45),2)+ROUND((ROUND(((AE45-(EU45))*AV45*1),2)*BS45),2)) -> 0 | CS45: =(ROUND((ROUND(((EU45)*AV45*1),2)*BS45),2)+ROUND((ROUND(((AE45-(EU45))*AV45*1),2)*BS45),2)) -> 0 | CT45: =ROUND((ROUND((AF45*AV45*1),2)*BA45),2) -> 0 | CU45: =AG45 -> 0 | CV45: =(AH45*AV45) -> 0 | CW45: =AI45 -> 0 | CX45: =AJ45 -> 0 | CY45: =(ROUND((((S45+ROUND((ROUND(((EU45)*AV45*1),2)*BS45),2))*AT45)/100),2)+ROUND(((ROUND((ROUND(((AE45-(EU45))*AV45*1),2)*BS45),2)*AT45)/100),2)) -> 0 | CZ45: =(ROUND((((S45+ROUND((ROUND(((EU45)*AV45*1),2)*BS45),2))*AU45)/100),2)+ROUND(((ROUND((ROUND(((AE45-(EU45))*AV45*1),2)*BS45),2)*AU45)/100),2)) -> 0 | DN45: 0 | DO45: 0 | DP45: 1 | DQ45: 1 | DU45: 1013 | DV45: ШТ | DW45: ШТ | DX45: 1 | EE45: 60088638 | EF45: 130 | EG45: Сметная стоимость оборудования | EH45: 0 | EJ45: 3 | EK45: 746 | EL45: ТСН-2001.13. Сметная стоимость оборудования | EM45: ТСН-2001.13 | EQ45: 0 | ER45: 0 | ES45: 20298.35 | ET45: 0 | EU45: 0 | EV45: 0 | EW45: 0 | EX45: 0 | EY45: 0 | EZ45: 5 | FC45: 1 | FD45: 18 | FF45: 179000 | FQ45: 0 | FR45: =P45 -> 155485.36 | FS45: 0 | FX45: 0 | FY45: 0 | GA45: [179 000 / 1,2 / 7,66] + 3% Трансп + 1,2% Заг.скл | GD45: 1 | GF45: 867537067 | GG45: 2 | GH45: 3 | GI45: 5 | GJ45: 0 | GK45: 0 | GL45: =ROUND(IF(AND(BH45=3,BI45=3,FS45<>0),P45,0),2) -> 0 | GM45: =ROUND(O45+X45+Y45,2)+GX45 -> 155485.36 | GN45: =IF(OR(BI45=0,BI45=1),GM45-GX45,0) -> 0 | GO45: =IF(BI45=2,GM45-GX45,0) -> 0 | GP45: =IF(BI45=4,GM45-GX45,0) -> 0 | GR45: 1 | GS45: 1 | GT45: 0 | GV45: =ROUND((GT45),6) -> 0 | GW45: 1 | GX45: =ROUND(HC45*I45,2) -> 0 | HA45: 0 | HB45: 0 | HC45: =GV45*GW45 -> 0 | HE45: 3 | HF45: 1,2 | HS45: 0 | IK45: 0
A46: 17 | B46: 1 | C46: =ROW(SmtRes!A40) -> 40 | D46: =ROW(EtalonRes!A49) -> 49 | E46: 10 | F46: 4.10-34-5 | G46: Монтаж коммутатора служебной связи | H46: 1 ШТ. | I46: =ROUND(1+1+7,9) -> 9 | J46: 0 | K46: =ROUND(1+1+7,9) -> 9 | O46: =ROUND(CP46,2) -> 1219.72 | P46: =ROUND((ROUND((AC46*AW46*I46),2)*BC46),2) -> 111.15 | Q46: =(ROUND((ROUND((((ET46*1.1))*AV46*I46),2)*BB46),2)+ROUND((ROUND(((AE46-((EU46*1.1)))*AV46*I46),2)*BS46),2)) -> 297.59 | R46: =(ROUND((ROUND((((EU46*1.1))*AV46*I46),2)*BS46),2)+ROUND((ROUND(((AE46-((EU46*1.1)))*AV46*I46),2)*BS46),2)) -> 32.75 | S46: =ROUND((ROUND((AF46*AV46*I46),2)*BA46),2) -> 810.98 | T46: =ROUND(CU46*I46,2) -> 0 | U46: =CV46*I46 -> 64.26486 | V46: =CW46*I46 -> 0 | W46: =ROUND(CX46*I46,2) -> 0 | X46: =(ROUND((((S46+ROUND((ROUND((((EU46*1.1))*AV46*I46),2)*BS46),2))*AT46)/100),2)+ROUND(((ROUND((ROUND(((AE46-((EU46*1.1)))*AV46*I46),2)*BS46),2)*AT46)/100),2)) -> 759.36 | Y46: =(ROUND((((S46+ROUND((ROUND((((EU46*1.1))*AV46*I46),2)*BS46),2))*AU46)/100),2)+ROUND(((ROUND((ROUND(((AE46-((EU46*1.1)))*AV46*I46),2)*BS46),2)*AU46)/100),2)) -> 388.12 | AA46: 60258064 | AB46: =ROUND((AC46+AD46+AF46),6) -> 129.995 | AC46: =ROUND((ES46),6) -> 12.35 | AD46: =ROUND(((((ET46*1.1))-((EU46*1.1)))+AE46),6) -> 31.581 | AE46: =ROUND(((EU46*1.1)),6) -> 3.476 | AF46: =ROUND(((EV46*1.1)),6) -> 86.064 | AG46: =ROUND((AP46),6) -> 0 | AH46: =((EW46*1.1)) -> 6.82 | AI46: =((EX46*1.1)) -> 0 | AJ46: =(AS46) -> 0 | AK46: 119.3 | AL46: 12.35 | AM46: 28.71 | AN46: 3.16 | AO46: 78.24 | AP46: 0 | AQ46: 6.2 | AR46: 0 | AS46: 0 | AT46: 90 | AU46: 46 | AV46: 1.047 | AW46: 1 | AZ46: 1 | BA46: 1 | BB46: 1 | BC46: 1 | BH46: 0 | BI46: 2 | BJ46: ТСН-2001.4 Доп. 80, Сб. 10, т. 34, поз. 5 | BM46: 68 | BN46: 58973116 | BO46: 4.10-34-5 | BP46: 1 | BQ46: 40 | BR46: 0 | BS46: 1 | BT46: 1 | BU46: 1 | BV46: 1 | BW46: 1 | BX46: 1 | BZ46: 90 | CA46: 46 | CE46: 1566 | CF46: 0 | CG46: 0 | CM46: 0 | CN46: Поправка: О.П. п.3.4.30.в Наименование: При применении территориальных сметных нормативов для города Москвы затраты, учитывающие напряженные и стесненные условия производства работ (стесненность, сложность складирования и транспортной логистики и т.п.), исчисляются с применением коэффициентов к затратам труда и заработной плате рабочих, машинистов, времени эксплуатации машин и механизмов, стоимости эксплуатации машин в размере: для объектов, расположенных за пределами Третьего транспортного кольца города Москвы, но в пределах Московской кольцевой автомобильной дороги | CO46: 0 | CP46: =(P46+Q46+S46) -> 1219.72 | CQ46: =ROUND((ROUND((AC46*AW46*1),2)*BC46),2) -> 12.35 | CR46: =(ROUND((ROUND((((ET46*1.1))*AV46*1),2)*BB46),2)+ROUND((ROUND(((AE46-((EU46*1.1)))*AV46*1),2)*BS46),2)) -> 33.07 | CS46: =(ROUND((ROUND((((EU46*1.1))*AV46*1),2)*BS46),2)+ROUND((ROUND(((AE46-((EU46*1.1)))*AV46*1),2)*BS46),2)) -> 3.64 | CT46: =ROUND((ROUND((AF46*AV46*1),2)*BA46),2) -> 90.11 | CU46: =AG46 -> 0 | CV46: =(AH46*AV46) -> 7.14054 | CW46: =AI46 -> 0 | CX46: =AJ46 -> 0 | CY46: =(ROUND((((S46+ROUND((ROUND((((EU46*1.1))*AV46*1),2)*BS46),2))*AT46)/100),2)+ROUND(((ROUND((ROUND(((AE46-((EU46*1.1)))*AV46*1),2)*BS46),2)*AT46)/100),2)) -> 733.16 | CZ46: =(ROUND((((S46+ROUND((ROUND((((EU46*1.1))*AV46*1),2)*BS46),2))*AU46)/100),2)+ROUND(((ROUND((ROUND(((AE46-((EU46*1.1)))*AV46*1),2)*BS46),2)*AU46)/100),2)) -> 374.73 | DB46: 9 | DE46: *1,1 | DF46: *1,1 | DG46: *1,1 | DI46: *1,1 | DJ46: *1,1 | DN46: 0 | DO46: 0 | DP46: 1 | DQ46: 1 | DU46: 1013 | DV46: 1 ШТ. | DW46: 1 ШТ. | DX46: 1 | EE46: 60088532 | EF46: 40 | EG46: Монтаж оборудования | EH46: 0 | EJ46: 2 | EK46: 68 | EL46: ТСН-2001.4-10. Прокладка и монтаж сетей связи | EM46: ТСН-2001.4-10-1 | EO46: Поправка: О.П. п.3.4.30.в | EQ46: 0 | ER46: 119.3 | ES46: 12.35 | ET46: 28.71 | EU46: 3.16 | EV46: 78.24 | EW46: 6.2 | EX46: 0 | EY46: 0 | FQ46: 0 | FR46: 0 | FS46: 0 | FX46: 90 | FY46: 46 | GD46: 1 | GF46: -210614787 | GG46: 2 | GH46: 1 | GI46: 2 | GJ46: 0 | GK46: 0 | GL46: =ROUND(IF(AND(BH46=3,BI46=3,FS46<>0),P46,0),2) -> 0 | GM46: =ROUND(O46+X46+Y46,2)+GX46 -> 2367.2 | GN46: =IF(OR(BI46=0,BI46=1),GM46-GX46,0) -> 0 | GO46: =IF(BI46=2,GM46-GX46,0) -> 2367.2 | GP46: =IF(BI46=4,GM46-GX46,0) -> 0 | GR46: 0 | GS46: 3 | GT46: 0 | GV46: =ROUND((GT46),6) -> 0 | GW46: 1 | GX46: =ROUND(HC46*I46,2) -> 0 | HA46: 0 | HB46: 0 | HC46: =GV46*GW46 -> 0 | HS46: 0 | IK46: 0
A47: 17 | B47: 1 | C47: =ROW(SmtRes!A44) -> 44 | D47: =ROW(EtalonRes!A54) -> 54 | E47: 10 | F47: 4.10-34-5 | G47: Монтаж коммутатора служебной связи | H47: 1 ШТ. | I47: =ROUND(1+1+7,9) -> 9 | J47: 0 | K47: =ROUND(1+1+7,9) -> 9 | O47: =ROUND(CP47,2) -> 50830.44 | P47: =ROUND((ROUND((AC47*AW47*I47),2)*BC47),2) -> 1633.91 | Q47: =(ROUND((ROUND((((ET47*1.1))*AV47*I47),2)*BB47),2)+ROUND((ROUND(((AE47-((EU47*1.1)))*AV47*I47),2)*BS47),2)) -> 4600.74 | R47: =(ROUND((ROUND((((EU47*1.1))*AV47*I47),2)*BS47),2)+ROUND((ROUND(((AE47-((EU47*1.1)))*AV47*I47),2)*BS47),2)) -> 1800.92 | S47: =ROUND((ROUND((AF47*AV47*I47),2)*BA47),2) -> 44595.79 | T47: =ROUND(CU47*I47,2) -> 0 | U47: =CV47*I47 -> 64.26486 | V47: =CW47*I47 -> 0 | W47: =ROUND(CX47*I47,2) -> 0 | X47: =(ROUND((((S47+ROUND((ROUND((((EU47*1.1))*AV47*I47),2)*BS47),2))*AT47)/100),2)+ROUND(((ROUND((ROUND(((AE47-((EU47*1.1)))*AV47*I47),2)*BS47),2)*AT47)/100),2)) -> 41757.04 | Y47: =(ROUND((((S47+ROUND((ROUND((((EU47*1.1))*AV47*I47),2)*BS47),2))*AU47)/100),2)+ROUND(((ROUND((ROUND(((AE47-((EU47*1.1)))*AV47*I47),2)*BS47),2)*AU47)/100),2)) -> 21342.49 | AA47: 60258061 | AB47: =ROUND((AC47+AD47+AF47),6) -> 129.995 | AC47: =ROUND((ES47),6) -> 12.35 | AD47: =ROUND(((((ET47*1.1))-((EU47*1.1)))+AE47),6) -> 31.581 | AE47: =ROUND(((EU47*1.1)),6) -> 3.476 | AF47: =ROUND(((EV47*1.1)),6) -> 86.064 | AG47: =ROUND((AP47),6) -> 0 | AH47: =((EW47*1.1)) -> 6.82 | AI47: =((EX47*1.1)) -> 0 | AJ47: =(AS47) -> 0 | AK47: 119.3 | AL47: 12.35 | AM47: 28.71 | AN47: 3.16 | AO47: 78.24 | AP47: 0 | AQ47: 6.2 | AR47: 0 | AS47: 0 | AT47: 90 | AU47: 46 | AV47: 1.047 | AW47: 1 | AZ47: 1 | BA47: 54.99 | BB47: 15.46 | BC47: 14.7 | BH47: 0 | BI47: 2 | BJ47: ТСН-2001.4 Доп. 80, Сб. 10, т. 34, поз. 5 | BM47: 68 | BN47: 58973116 | BO47: 4.10-34-5 | BP47: 1 | BQ47: 40 | BR47: 0 | BS47: 54.99 | BT47: 1 | BU47: 1 | BV47: 1 | BW47: 1 | BX47: 1 | BZ47: 90 | CA47: 46 | CE47: 1566 | CF47: 0 | CG47: 0 | CM47: 0 | CN47: Поправка: О.П. п.3.4.30.в Наименование: При применении территориальных сметных нормативов для города Москвы затраты, учитывающие напряженные и стесненные условия производства работ (стесненность, сложность складирования и транспортной логистики и т.п.), исчисляются с применением коэффициентов к затратам труда и заработной плате рабочих, машинистов, времени эксплуатации машин и механизмов, стоимости эксплуатации машин в размере: для объектов, расположенных за пределами Третьего транспортного кольца города Москвы, но в пределах Московской кольцевой автомобильной дороги | CO47: 0 | CP47: =(P47+Q47+S47) -> 50830.44 | CQ47: =ROUND((ROUND((AC47*AW47*1),2)*BC47),2) -> 181.55 | CR47: =(ROUND((ROUND((((ET47*1.1))*AV47*1),2)*BB47),2)+ROUND((ROUND(((AE47-((EU47*1.1)))*AV47*1),2)*BS47),2)) -> 511.26 | CS47: =(ROUND((ROUND((((EU47*1.1))*AV47*1),2)*BS47),2)+ROUND((ROUND(((AE47-((EU47*1.1)))*AV47*1),2)*BS47),2)) -> 200.16 | CT47: =ROUND((ROUND((AF47*AV47*1),2)*BA47),2) -> 4955.15 | CU47: =AG47 -> 0 | CV47: =(AH47*AV47) -> 7.14054 | CW47: =AI47 -> 0 | CX47: =AJ47 -> 0 | CY47: =(ROUND((((S47+ROUND((ROUND((((EU47*1.1))*AV47*1),2)*BS47),2))*AT47)/100),2)+ROUND(((ROUND((ROUND(((AE47-((EU47*1.1)))*AV47*1),2)*BS47),2)*AT47)/100),2)) -> 40316.36 | CZ47: =(ROUND((((S47+ROUND((ROUND((((EU47*1.1))*AV47*1),2)*BS47),2))*AU47)/100),2)+ROUND(((ROUND((ROUND(((AE47-((EU47*1.1)))*AV47*1),2)*BS47),2)*AU47)/100),2)) -> 20606.14 | DB47: 10 | DE47: *1,1 | DF47: *1,1 | DG47: *1,1 | DI47: *1,1 | DJ47: *1,1 | DN47: 0 | DO47: 0 | DP47: 1 | DQ47: 1 | DU47: 1013 | DV47: 1 ШТ. | DW47: 1 ШТ. | DX47: 1 | EE47: 60088532 | EF47: 40 | EG47: Монтаж оборудования | EH47: 0 | EJ47: 2 | EK47: 68 | EL47: ТСН-2001.4-10. Прокладка и монтаж сетей связи | EM47: ТСН-2001.4-10-1 | EO47: Поправка: О.П. п.3.4.30.в | EQ47: 0 | ER47: 119.3 | ES47: 12.35 | ET47: 28.71 | EU47: 3.16 | EV47: 78.24 | EW47: 6.2 | EX47: 0 | EY47: 0 | FQ47: 0 | FR47: 0 | FS47: 0 | FX47: 90 | FY47: 46 | GD47: 1 | GF47: -210614787 | GG47: 2 | GH47: 1 | GI47: 2 | GJ47: 0 | GK47: 0 | GL47: =ROUND(IF(AND(BH47=3,BI47=3,FS47<>0),P47,0),2) -> 0 | GM47: =ROUND(O47+X47+Y47,2)+GX47 -> 113929.97 | GN47: =IF(OR(BI47=0,BI47=1),GM47-GX47,0) -> 0 | GO47: =IF(BI47=2,GM47-GX47,0) -> 113929.97 | GP47: =IF(BI47=4,GM47-GX47,0) -> 0 | GR47: 0 | GS47: 3 | GT47: 0 | GV47: =ROUND((GT47),6) -> 0 | GW47: 1 | GX47: =ROUND(HC47*I47,2) -> 0 | HA47: 0 | HB47: 0 | HC47: =GV47*GW47 -> 0 | HS47: 0 | IK47: 0
A48: 17 | B48: 1 | E48: 11 | F48: КА-6 | G48: Коммутатор агрегации MES3300-16F | H48: ШТ | I48: 1 | J48: 0 | K48: 1 | O48: =ROUND(CP48,2) -> 34992.32 | P48: =ROUND((ROUND((AC48*I48),2)*BC48),2) -> 34992.32 | Q48: =(ROUND((ROUND(((ET48)*AV48*I48),2)*BB48),2)+ROUND((ROUND(((AE48-(EU48))*AV48*I48),2)*BS48),2)) -> 0 | R48: =(ROUND((ROUND(((EU48)*AV48*I48),2)*BS48),2)+ROUND((ROUND(((AE48-(EU48))*AV48*I48),2)*BS48),2)) -> 0 | S48: =ROUND((ROUND((AF48*AV48*I48),2)*BA48),2) -> 0 | T48: =ROUND(CU48*I48,2) -> 0 | U48: =CV48*I48 -> 0 | V48: =CW48*I48 -> 0 | W48: =ROUND(CX48*I48,2) -> 0 | X48: =(ROUND((((S48+ROUND((ROUND(((EU48)*AV48*I48),2)*BS48),2))*AT48)/100),2)+ROUND(((ROUND((ROUND(((AE48-(EU48))*AV48*I48),2)*BS48),2)*AT48)/100),2)) -> 0 | Y48: =(ROUND((((S48+ROUND((ROUND(((EU48)*AV48*I48),2)*BS48),2))*AU48)/100),2)+ROUND(((ROUND((ROUND(((AE48-(EU48))*AV48*I48),2)*BS48),2)*AU48)/100),2)) -> 0 | AA48: 60258064 | AB48: =ROUND((AC48+AD48+AF48),6) -> 34992.32 | AC48: =ROUND((ES48),6) -> 34992.32 | AD48: =ROUND((((ET48)-(EU48))+AE48),6) -> 0 | AE48: =ROUND((EU48),6) -> 0 | AF48: =ROUND((EV48),6) -> 0 | AG48: =ROUND((AP48),6) -> 0 | AH48: =(EW48) -> 0 | AI48: =(EX48) -> 0 | AJ48: =(AS48) -> 0 | AK48: 34992.32 | AL48: 34992.32 | AM48: 0 | AN48: 0 | AO48: 0 | AP48: 0 | AQ48: 0 | AR48: 0 | AS48: 0 | AT48: 0 | AU48: 0 | AV48: 1 | AW48: 1 | AZ48: 1 | BA48: 1 | BB48: 1 | BC48: 1 | BH48: 3 | BI48: 3 | BM48: 746 | BN48: 0 | BP48: 0 | BQ48: 130 | BR48: 0 | BS48: 1 | BT48: 1 | BU48: 1 | BV48: 1 | BW48: 1 | BX48: 1 | BZ48: 0 | CA48: 0 | CE48: 1566 | CF48: 0 | CG48: 0 | CM48: 0 | CO48: 0 | CP48: =(P48+Q48+S48) -> 34992.32 | CQ48: =ROUND((ROUND((AC48*1),2)*BC48),2) -> 34992.32 | CR48: =(ROUND((ROUND(((ET48)*AV48*1),2)*BB48),2)+ROUND((ROUND(((AE48-(EU48))*AV48*1),2)*BS48),2)) -> 0 | CS48: =(ROUND((ROUND(((EU48)*AV48*1),2)*BS48),2)+ROUND((ROUND(((AE48-(EU48))*AV48*1),2)*BS48),2)) -> 0 | CT48: =ROUND((ROUND((AF48*AV48*1),2)*BA48),2) -> 0 | CU48: =AG48 -> 0 | CV48: =(AH48*AV48) -> 0 | CW48: =AI48 -> 0 | CX48: =AJ48 -> 0 | CY48: =(ROUND((((S48+ROUND((ROUND(((EU48)*AV48*1),2)*BS48),2))*AT48)/100),2)+ROUND(((ROUND((ROUND(((AE48-(EU48))*AV48*1),2)*BS48),2)*AT48)/100),2)) -> 0 | CZ48: =(ROUND((((S48+ROUND((ROUND(((EU48)*AV48*1),2)*BS48),2))*AU48)/100),2)+ROUND(((ROUND((ROUND(((AE48-(EU48))*AV48*1),2)*BS48),2)*AU48)/100),2)) -> 0 | DN48: 0 | DO48: 0 | DP48: 1 | DQ48: 1 | DU48: 1013 | DV48: ШТ | DW48: ШТ | DX48: 1 | EE48: 60088638 | EF48: 130 | EG48: Сметная стоимость оборудования | EH48: 0 | EJ48: 3 | EK48: 746 | EL48: ТСН-2001.13. Сметная стоимость оборудования | EM48: ТСН-2001.13 | EQ48: 0 | ER48: 0 | ES48: 34992.32 | ET48: 0 | EU48: 0 | EV48: 0 | EW48: 0 | EX48: 0 | EY48: 0 | FQ48: 0 | FR48: =P48 -> 34992.32 | FS48: 0 | FX48: 0 | FY48: 0 | GA48: [308 578 / 1,2 / 7,66] + 3% Трансп + 1,2% Заг.скл | GD48: 1 | GF48: 1507352899 | GG48: 2 | GH48: 4 | GI48: -2 | GJ48: 0 | GK48: 0 | GL48: =ROUND(IF(AND(BH48=3,BI48=3,FS48<>0),P48,0),2) -> 0 | GM48: =ROUND(O48+X48+Y48,2)+GX48 -> 34992.32 | GN48: =IF(OR(BI48=0,BI48=1),GM48-GX48,0) -> 0 | GO48: =IF(BI48=2,GM48-GX48,0) -> 0 | GP48: =IF(BI48=4,GM48-GX48,0) -> 0 | GR48: 0 | GS48: 2 | GT48: 0 | GV48: =ROUND((GT48),6) -> 0 | GW48: 1 | GX48: =ROUND(HC48*I48,2) -> 0 | HA48: 0 | HB48: 0 | HC48: =GV48*GW48 -> 0 | HE48: 3 | HF48: 1,2 | HS48: 0 | IK48: 0
A49: 17 | B49: 1 | E49: 11 | F49: КА-6 | G49: Коммутатор агрегации MES3300-16F | H49: ШТ | I49: 1 | J49: 0 | K49: 1 | O49: =ROUND(CP49,2) -> 268041.17 | P49: =ROUND((ROUND((AC49*I49),2)*BC49),2) -> 268041.17 | Q49: =(ROUND((ROUND(((ET49)*AV49*I49),2)*BB49),2)+ROUND((ROUND(((AE49-(EU49))*AV49*I49),2)*BS49),2)) -> 0 | R49: =(ROUND((ROUND(((EU49)*AV49*I49),2)*BS49),2)+ROUND((ROUND(((AE49-(EU49))*AV49*I49),2)*BS49),2)) -> 0 | S49: =ROUND((ROUND((AF49*AV49*I49),2)*BA49),2) -> 0 | T49: =ROUND(CU49*I49,2) -> 0 | U49: =CV49*I49 -> 0 | V49: =CW49*I49 -> 0 | W49: =ROUND(CX49*I49,2) -> 0 | X49: =(ROUND((((S49+ROUND((ROUND(((EU49)*AV49*I49),2)*BS49),2))*AT49)/100),2)+ROUND(((ROUND((ROUND(((AE49-(EU49))*AV49*I49),2)*BS49),2)*AT49)/100),2)) -> 0 | Y49: =(ROUND((((S49+ROUND((ROUND(((EU49)*AV49*I49),2)*BS49),2))*AU49)/100),2)+ROUND(((ROUND((ROUND(((AE49-(EU49))*AV49*I49),2)*BS49),2)*AU49)/100),2)) -> 0 | AA49: 60258061 | AB49: =ROUND((AC49+AD49+AF49),6) -> 34992.32 | AC49: =ROUND((ES49),6) -> 34992.32 | AD49: =ROUND((((ET49)-(EU49))+AE49),6) -> 0 | AE49: =ROUND((EU49),6) -> 0 | AF49: =ROUND((EV49),6) -> 0 | AG49: =ROUND((AP49),6) -> 0 | AH49: =(EW49) -> 0 | AI49: =(EX49) -> 0 | AJ49: =(AS49) -> 0 | AK49: 34992.32 | AL49: 34992.32 | AM49: 0 | AN49: 0 | AO49: 0 | AP49: 0 | AQ49: 0 | AR49: 0 | AS49: 0 | AT49: 0 | AU49: 0 | AV49: 1 | AW49: 1 | AZ49: 1 | BA49: 1 | BB49: 1 | BC49: 7.66 | BH49: 3 | BI49: 3 | BM49: 746 | BN49: 0 | BP49: 0 | BQ49: 130 | BR49: 0 | BS49: 1 | BT49: 1 | BU49: 1 | BV49: 1 | BW49: 1 | BX49: 1 | BZ49: 0 | CA49: 0 | CE49: 1566 | CF49: 0 | CG49: 0 | CM49: 0 | CO49: 0 | CP49: =(P49+Q49+S49) -> 268041.17 | CQ49: =ROUND((ROUND((AC49*1),2)*BC49),2) -> 268041.17 | CR49: =(ROUND((ROUND(((ET49)*AV49*1),2)*BB49),2)+ROUND((ROUND(((AE49-(EU49))*AV49*1),2)*BS49),2)) -> 0 | CS49: =(ROUND((ROUND(((EU49)*AV49*1),2)*BS49),2)+ROUND((ROUND(((AE49-(EU49))*AV49*1),2)*BS49),2)) -> 0 | CT49: =ROUND((ROUND((AF49*AV49*1),2)*BA49),2) -> 0 | CU49: =AG49 -> 0 | CV49: =(AH49*AV49) -> 0 | CW49: =AI49 -> 0 | CX49: =AJ49 -> 0 | CY49: =(ROUND((((S49+ROUND((ROUND(((EU49)*AV49*1),2)*BS49),2))*AT49)/100),2)+ROUND(((ROUND((ROUND(((AE49-(EU49))*AV49*1),2)*BS49),2)*AT49)/100),2)) -> 0 | CZ49: =(ROUND((((S49+ROUND((ROUND(((EU49)*AV49*1),2)*BS49),2))*AU49)/100),2)+ROUND(((ROUND((ROUND(((AE49-(EU49))*AV49*1),2)*BS49),2)*AU49)/100),2)) -> 0 | DN49: 0 | DO49: 0 | DP49: 1 | DQ49: 1 | DU49: 1013 | DV49: ШТ | DW49: ШТ | DX49: 1 | EE49: 60088638 | EF49: 130 | EG49: Сметная стоимость оборудования | EH49: 0 | EJ49: 3 | EK49: 746 | EL49: ТСН-2001.13. Сметная стоимость оборудования | EM49: ТСН-2001.13 | EQ49: 0 | ER49: 0 | ES49: 34992.32 | ET49: 0 | EU49: 0 | EV49: 0 | EW49: 0 | EX49: 0 | EY49: 0 | EZ49: 5 | FC49: 1 | FD49: 18 | FF49: 308578 | FQ49: 0 | FR49: =P49 -> 268041.17 | FS49: 0 | FX49: 0 | FY49: 0 | GA49: [308 578 / 1,2 / 7,66] + 3% Трансп + 1,2% Заг.скл | GD49: 1 | GF49: 1507352899 | GG49: 2 | GH49: 3 | GI49: 5 | GJ49: 0 | GK49: 0 | GL49: =ROUND(IF(AND(BH49=3,BI49=3,FS49<>0),P49,0),2) -> 0 | GM49: =ROUND(O49+X49+Y49,2)+GX49 -> 268041.17 | GN49: =IF(OR(BI49=0,BI49=1),GM49-GX49,0) -> 0 | GO49: =IF(BI49=2,GM49-GX49,0) -> 0 | GP49: =IF(BI49=4,GM49-GX49,0) -> 0 | GR49: 1 | GS49: 1 | GT49: 0 | GV49: =ROUND((GT49),6) -> 0 | GW49: 1 | GX49: =ROUND(HC49*I49,2) -> 0 | HA49: 0 | HB49: 0 | HC49: =GV49*GW49 -> 0 | HE49: 3 | HF49: 1,2 | HS49: 0 | IK49: 0
A50: 17 | B50: 1 | E50: 12 | F50: КА-7 | G50: Коммутатор доступа 48 PoE MES2420-48P | H50: ШТ | I50: 1 | J50: 0 | K50: 1 | O50: =ROUND(CP50,2) -> 53571.2 | P50: =ROUND((ROUND((AC50*I50),2)*BC50),2) -> 53571.2 | Q50: =(ROUND((ROUND(((ET50)*AV50*I50),2)*BB50),2)+ROUND((ROUND(((AE50-(EU50))*AV50*I50),2)*BS50),2)) -> 0 | R50: =(ROUND((ROUND(((EU50)*AV50*I50),2)*BS50),2)+ROUND((ROUND(((AE50-(EU50))*AV50*I50),2)*BS50),2)) -> 0 | S50: =ROUND((ROUND((AF50*AV50*I50),2)*BA50),2) -> 0 | T50: =ROUND(CU50*I50,2) -> 0 | U50: =CV50*I50 -> 0 | V50: =CW50*I50 -> 0 | W50: =ROUND(CX50*I50,2) -> 0 | X50: =(ROUND((((S50+ROUND((ROUND(((EU50)*AV50*I50),2)*BS50),2))*AT50)/100),2)+ROUND(((ROUND((ROUND(((AE50-(EU50))*AV50*I50),2)*BS50),2)*AT50)/100),2)) -> 0 | Y50: =(ROUND((((S50+ROUND((ROUND(((EU50)*AV50*I50),2)*BS50),2))*AU50)/100),2)+ROUND(((ROUND((ROUND(((AE50-(EU50))*AV50*I50),2)*BS50),2)*AU50)/100),2)) -> 0 | AA50: 60258064 | AB50: =ROUND((AC50+AD50+AF50),6) -> 53571.2 | AC50: =ROUND((ES50),6) -> 53571.2 | AD50: =ROUND((((ET50)-(EU50))+AE50),6) -> 0 | AE50: =ROUND((EU50),6) -> 0 | AF50: =ROUND((EV50),6) -> 0 | AG50: =ROUND((AP50),6) -> 0 | AH50: =(EW50) -> 0 | AI50: =(EX50) -> 0 | AJ50: =(AS50) -> 0 | AK50: 53571.2 | AL50: 53571.2 | AM50: 0 | AN50: 0 | AO50: 0 | AP50: 0 | AQ50: 0 | AR50: 0 | AS50: 0 | AT50: 0 | AU50: 0 | AV50: 1 | AW50: 1 | AZ50: 1 | BA50: 1 | BB50: 1 | BC50: 1 | BH50: 3 | BI50: 3 | BM50: 746 | BN50: 0 | BP50: 0 | BQ50: 130 | BR50: 0 | BS50: 1 | BT50: 1 | BU50: 1 | BV50: 1 | BW50: 1 | BX50: 1 | BZ50: 0 | CA50: 0 | CE50: 1566 | CF50: 0 | CG50: 0 | CM50: 0 | CO50: 0 | CP50: =(P50+Q50+S50) -> 53571.2 | CQ50: =ROUND((ROUND((AC50*1),2)*BC50),2) -> 53571.2 | CR50: =(ROUND((ROUND(((ET50)*AV50*1),2)*BB50),2)+ROUND((ROUND(((AE50-(EU50))*AV50*1),2)*BS50),2)) -> 0 | CS50: =(ROUND((ROUND(((EU50)*AV50*1),2)*BS50),2)+ROUND((ROUND(((AE50-(EU50))*AV50*1),2)*BS50),2)) -> 0 | CT50: =ROUND((ROUND((AF50*AV50*1),2)*BA50),2) -> 0 | CU50: =AG50 -> 0 | CV50: =(AH50*AV50) -> 0 | CW50: =AI50 -> 0 | CX50: =AJ50 -> 0 | CY50: =(ROUND((((S50+ROUND((ROUND(((EU50)*AV50*1),2)*BS50),2))*AT50)/100),2)+ROUND(((ROUND((ROUND(((AE50-(EU50))*AV50*1),2)*BS50),2)*AT50)/100),2)) -> 0 | CZ50: =(ROUND((((S50+ROUND((ROUND(((EU50)*AV50*1),2)*BS50),2))*AU50)/100),2)+ROUND(((ROUND((ROUND(((AE50-(EU50))*AV50*1),2)*BS50),2)*AU50)/100),2)) -> 0 | DN50: 0 | DO50: 0 | DP50: 1 | DQ50: 1 | DU50: 1013 | DV50: ШТ | DW50: ШТ | DX50: 1 | EE50: 60088638 | EF50: 130 | EG50: Сметная стоимость оборудования | EH50: 0 | EJ50: 3 | EK50: 746 | EL50: ТСН-2001.13. Сметная стоимость оборудования | EM50: ТСН-2001.13 | EQ50: 0 | ER50: 0 | ES50: 53571.2 | ET50: 0 | EU50: 0 | EV50: 0 | EW50: 0 | EX50: 0 | EY50: 0 | FQ50: 0 | FR50: =P50 -> 53571.2 | FS50: 0 | FX50: 0 | FY50: 0 | GA50: [472 415 / 1,2 / 7,66] + 3% Трансп + 1,2% Заг.скл | GD50: 1 | GF50: 441519637 | GG50: 2 | GH50: 4 | GI50: -2 | GJ50: 0 | GK50: 0 | GL50: =ROUND(IF(AND(BH50=3,BI50=3,FS50<>0),P50,0),2) -> 0 | GM50: =ROUND(O50+X50+Y50,2)+GX50 -> 53571.2 | GN50: =IF(OR(BI50=0,BI50=1),GM50-GX50,0) -> 0 | GO50: =IF(BI50=2,GM50-GX50,0) -> 0 | GP50: =IF(BI50=4,GM50-GX50,0) -> 0 | GR50: 0 | GS50: 2 | GT50: 0 | GV50: =ROUND((GT50),6) -> 0 | GW50: 1 | GX50: =ROUND(HC50*I50,2) -> 0 | HA50: 0 | HB50: 0 | HC50: =GV50*GW50 -> 0 | HE50: 3 | HF50: 1,2 | HS50: 0 | IK50: 0
A51: 17 | B51: 1 | E51: 12 | F51: КА-7 | G51: Коммутатор доступа 48 PoE MES2420-48P | H51: ШТ | I51: 1 | J51: 0 | K51: 1 | O51: =ROUND(CP51,2) -> 410355.39 | P51: =ROUND((ROUND((AC51*I51),2)*BC51),2) -> 410355.39 | Q51: =(ROUND((ROUND(((ET51)*AV51*I51),2)*BB51),2)+ROUND((ROUND(((AE51-(EU51))*AV51*I51),2)*BS51),2)) -> 0 | R51: =(ROUND((ROUND(((EU51)*AV51*I51),2)*BS51),2)+ROUND((ROUND(((AE51-(EU51))*AV51*I51),2)*BS51),2)) -> 0 | S51: =ROUND((ROUND((AF51*AV51*I51),2)*BA51),2) -> 0 | T51: =ROUND(CU51*I51,2) -> 0 | U51: =CV51*I51 -> 0 | V51: =CW51*I51 -> 0 | W51: =ROUND(CX51*I51,2) -> 0 | X51: =(ROUND((((S51+ROUND((ROUND(((EU51)*AV51*I51),2)*BS51),2))*AT51)/100),2)+ROUND(((ROUND((ROUND(((AE51-(EU51))*AV51*I51),2)*BS51),2)*AT51)/100),2)) -> 0 | Y51: =(ROUND((((S51+ROUND((ROUND(((EU51)*AV51*I51),2)*BS51),2))*AU51)/100),2)+ROUND(((ROUND((ROUND(((AE51-(EU51))*AV51*I51),2)*BS51),2)*AU51)/100),2)) -> 0 | AA51: 60258061 | AB51: =ROUND((AC51+AD51+AF51),6) -> 53571.2 | AC51: =ROUND((ES51),6) -> 53571.2 | AD51: =ROUND((((ET51)-(EU51))+AE51),6) -> 0 | AE51: =ROUND((EU51),6) -> 0 | AF51: =ROUND((EV51),6) -> 0 | AG51: =ROUND((AP51),6) -> 0 | AH51: =(EW51) -> 0 | AI51: =(EX51) -> 0 | AJ51: =(AS51) -> 0 | AK51: 53571.2 | AL51: 53571.2 | AM51: 0 | AN51: 0 | AO51: 0 | AP51: 0 | AQ51: 0 | AR51: 0 | AS51: 0 | AT51: 0 | AU51: 0 | AV51: 1 | AW51: 1 | AZ51: 1 | BA51: 1 | BB51: 1 | BC51: 7.66 | BH51: 3 | BI51: 3 | BM51: 746 | BN51: 0 | BP51: 0 | BQ51: 130 | BR51: 0 | BS51: 1 | BT51: 1 | BU51: 1 | BV51: 1 | BW51: 1 | BX51: 1 | BZ51: 0 | CA51: 0 | CE51: 1566 | CF51: 0 | CG51: 0 | CM51: 0 | CO51: 0 | CP51: =(P51+Q51+S51) -> 410355.39 | CQ51: =ROUND((ROUND((AC51*1),2)*BC51),2) -> 410355.39 | CR51: =(ROUND((ROUND(((ET51)*AV51*1),2)*BB51),2)+ROUND((ROUND(((AE51-(EU51))*AV51*1),2)*BS51),2)) -> 0 | CS51: =(ROUND((ROUND(((EU51)*AV51*1),2)*BS51),2)+ROUND((ROUND(((AE51-(EU51))*AV51*1),2)*BS51),2)) -> 0 | CT51: =ROUND((ROUND((AF51*AV51*1),2)*BA51),2) -> 0 | CU51: =AG51 -> 0 | CV51: =(AH51*AV51) -> 0 | CW51: =AI51 -> 0 | CX51: =AJ51 -> 0 | CY51: =(ROUND((((S51+ROUND((ROUND(((EU51)*AV51*1),2)*BS51),2))*AT51)/100),2)+ROUND(((ROUND((ROUND(((AE51-(EU51))*AV51*1),2)*BS51),2)*AT51)/100),2)) -> 0 | CZ51: =(ROUND((((S51+ROUND((ROUND(((EU51)*AV51*1),2)*BS51),2))*AU51)/100),2)+ROUND(((ROUND((ROUND(((AE51-(EU51))*AV51*1),2)*BS51),2)*AU51)/100),2)) -> 0 | DN51: 0 | DO51: 0 | DP51: 1 | DQ51: 1 | DU51: 1013 | DV51: ШТ | DW51: ШТ | DX51: 1 | EE51: 60088638 | EF51: 130 | EG51: Сметная стоимость оборудования | EH51: 0 | EJ51: 3 | EK51: 746 | EL51: ТСН-2001.13. Сметная стоимость оборудования | EM51: ТСН-2001.13 | EQ51: 0 | ER51: 0 | ES51: 53571.2 | ET51: 0 | EU51: 0 | EV51: 0 | EW51: 0 | EX51: 0 | EY51: 0 | EZ51: 5 | FC51: 1 | FD51: 18 | FF51: 472415 | FQ51: 0 | FR51: =P51 -> 410355.39 | FS51: 0 | FX51: 0 | FY51: 0 | GA51: [472 415 / 1,2 / 7,66] + 3% Трансп + 1,2% Заг.скл | GD51: 1 | GF51: 441519637 | GG51: 2 | GH51: 3 | GI51: 5 | GJ51: 0 | GK51: 0 | GL51: =ROUND(IF(AND(BH51=3,BI51=3,FS51<>0),P51,0),2) -> 0 | GM51: =ROUND(O51+X51+Y51,2)+GX51 -> 410355.39 | GN51: =IF(OR(BI51=0,BI51=1),GM51-GX51,0) -> 0 | GO51: =IF(BI51=2,GM51-GX51,0) -> 0 | GP51: =IF(BI51=4,GM51-GX51,0) -> 0 | GR51: 1 | GS51: 1 | GT51: 0 | GV51: =ROUND((GT51),6) -> 0 | GW51: 1 | GX51: =ROUND(HC51*I51,2) -> 0 | HA51: 0 | HB51: 0 | HC51: =GV51*GW51 -> 0 | HE51: 3 | HF51: 1,2 | HS51: 0 | IK51: 0
A52: 17 | B52: 1 | E52: 13 | F52: КА-8 | G52: Коммутатор доступа 24 PoE MES2300-24P | H52: ШТ | I52: 7 | J52: 0 | K52: 7 | O52: =ROUND(CP52,2) -> 97983.06 | P52: =ROUND((ROUND((AC52*I52),2)*BC52),2) -> 97983.06 | Q52: =(ROUND((ROUND(((ET52)*AV52*I52),2)*BB52),2)+ROUND((ROUND(((AE52-(EU52))*AV52*I52),2)*BS52),2)) -> 0 | R52: =(ROUND((ROUND(((EU52)*AV52*I52),2)*BS52),2)+ROUND((ROUND(((AE52-(EU52))*AV52*I52),2)*BS52),2)) -> 0 | S52: =ROUND((ROUND((AF52*AV52*I52),2)*BA52),2) -> 0 | T52: =ROUND(CU52*I52,2) -> 0 | U52: =CV52*I52 -> 0 | V52: =CW52*I52 -> 0 | W52: =ROUND(CX52*I52,2) -> 0 | X52: =(ROUND((((S52+ROUND((ROUND(((EU52)*AV52*I52),2)*BS52),2))*AT52)/100),2)+ROUND(((ROUND((ROUND(((AE52-(EU52))*AV52*I52),2)*BS52),2)*AT52)/100),2)) -> 0 | Y52: =(ROUND((((S52+ROUND((ROUND(((EU52)*AV52*I52),2)*BS52),2))*AU52)/100),2)+ROUND(((ROUND((ROUND(((AE52-(EU52))*AV52*I52),2)*BS52),2)*AU52)/100),2)) -> 0 | AA52: 60258064 | AB52: =ROUND((AC52+AD52+AF52),6) -> 13997.58 | AC52: =ROUND((ES52),6) -> 13997.58 | AD52: =ROUND((((ET52)-(EU52))+AE52),6) -> 0 | AE52: =ROUND((EU52),6) -> 0 | AF52: =ROUND((EV52),6) -> 0 | AG52: =ROUND((AP52),6) -> 0 | AH52: =(EW52) -> 0 | AI52: =(EX52) -> 0 | AJ52: =(AS52) -> 0 | AK52: 13997.58 | AL52: 13997.58 | AM52: 0 | AN52: 0 | AO52: 0 | AP52: 0 | AQ52: 0 | AR52: 0 | AS52: 0 | AT52: 0 | AU52: 0 | AV52: 1 | AW52: 1 | AZ52: 1 | BA52: 1 | BB52: 1 | BC52: 1 | BH52: 3 | BI52: 3 | BM52: 746 | BN52: 0 | BP52: 0 | BQ52: 130 | BR52: 0 | BS52: 1 | BT52: 1 | BU52: 1 | BV52: 1 | BW52: 1 | BX52: 1 | BZ52: 0 | CA52: 0 | CE52: 1566 | CF52: 0 | CG52: 0 | CM52: 0 | CO52: 0 | CP52: =(P52+Q52+S52) -> 97983.06 | CQ52: =ROUND((ROUND((AC52*1),2)*BC52),2) -> 13997.58 | CR52: =(ROUND((ROUND(((ET52)*AV52*1),2)*BB52),2)+ROUND((ROUND(((AE52-(EU52))*AV52*1),2)*BS52),2)) -> 0 | CS52: =(ROUND((ROUND(((EU52)*AV52*1),2)*BS52),2)+ROUND((ROUND(((AE52-(EU52))*AV52*1),2)*BS52),2)) -> 0 | CT52: =ROUND((ROUND((AF52*AV52*1),2)*BA52),2) -> 0 | CU52: =AG52 -> 0 | CV52: =(AH52*AV52) -> 0 | CW52: =AI52 -> 0 | CX52: =AJ52 -> 0 | CY52: =(ROUND((((S52+ROUND((ROUND(((EU52)*AV52*1),2)*BS52),2))*AT52)/100),2)+ROUND(((ROUND((ROUND(((AE52-(EU52))*AV52*1),2)*BS52),2)*AT52)/100),2)) -> 0 | CZ52: =(ROUND((((S52+ROUND((ROUND(((EU52)*AV52*1),2)*BS52),2))*AU52)/100),2)+ROUND(((ROUND((ROUND(((AE52-(EU52))*AV52*1),2)*BS52),2)*AU52)/100),2)) -> 0 | DN52: 0 | DO52: 0 | DP52: 1 | DQ52: 1 | DU52: 1013 | DV52: ШТ | DW52: ШТ | DX52: 1 | EE52: 60088638 | EF52: 130 | EG52: Сметная стоимость оборудования | EH52: 0 | EJ52: 3 | EK52: 746 | EL52: ТСН-2001.13. Сметная стоимость оборудования | EM52: ТСН-2001.13 | EQ52: 0 | ER52: 0 | ES52: 13997.58 | ET52: 0 | EU52: 0 | EV52: 0 | EW52: 0 | EX52: 0 | EY52: 0 | FQ52: 0 | FR52: =P52 -> 97983.06 | FS52: 0 | FX52: 0 | FY52: 0 | GA52: [123 437 / 1,2 / 7,66] + 3% Трансп + 1,2% Заг.скл | GD52: 1 | GF52: 1048200997 | GG52: 2 | GH52: 4 | GI52: -2 | GJ52: 0 | GK52: 0 | GL52: =ROUND(IF(AND(BH52=3,BI52=3,FS52<>0),P52,0),2) -> 0 | GM52: =ROUND(O52+X52+Y52,2)+GX52 -> 97983.06 | GN52: =IF(OR(BI52=0,BI52=1),GM52-GX52,0) -> 0 | GO52: =IF(BI52=2,GM52-GX52,0) -> 0 | GP52: =IF(BI52=4,GM52-GX52,0) -> 0 | GR52: 0 | GS52: 2 | GT52: 0 | GV52: =ROUND((GT52),6) -> 0 | GW52: 1 | GX52: =ROUND(HC52*I52,2) -> 0 | HA52: 0 | HB52: 0 | HC52: =GV52*GW52 -> 0 | HE52: 3 | HF52: 1,2 | HS52: 0 | IK52: 0
A53: 17 | B53: 1 | E53: 13 | F53: КА-8 | G53: Коммутатор доступа 24 PoE MES2300-24P | H53: ШТ | I53: 7 | J53: 0 | K53: 7 | O53: =ROUND(CP53,2) -> 750550.24 | P53: =ROUND((ROUND((AC53*I53),2)*BC53),2) -> 750550.24 | Q53: =(ROUND((ROUND(((ET53)*AV53*I53),2)*BB53),2)+ROUND((ROUND(((AE53-(EU53))*AV53*I53),2)*BS53),2)) -> 0 | R53: =(ROUND((ROUND(((EU53)*AV53*I53),2)*BS53),2)+ROUND((ROUND(((AE53-(EU53))*AV53*I53),2)*BS53),2)) -> 0 | S53: =ROUND((ROUND((AF53*AV53*I53),2)*BA53),2) -> 0 | T53: =ROUND(CU53*I53,2) -> 0 | U53: =CV53*I53 -> 0 | V53: =CW53*I53 -> 0 | W53: =ROUND(CX53*I53,2) -> 0 | X53: =(ROUND((((S53+ROUND((ROUND(((EU53)*AV53*I53),2)*BS53),2))*AT53)/100),2)+ROUND(((ROUND((ROUND(((AE53-(EU53))*AV53*I53),2)*BS53),2)*AT53)/100),2)) -> 0 | Y53: =(ROUND((((S53+ROUND((ROUND(((EU53)*AV53*I53),2)*BS53),2))*AU53)/100),2)+ROUND(((ROUND((ROUND(((AE53-(EU53))*AV53*I53),2)*BS53),2)*AU53)/100),2)) -> 0 | AA53: 60258061 | AB53: =ROUND((AC53+AD53+AF53),6) -> 13997.58 | AC53: =ROUND((ES53),6) -> 13997.58 | AD53: =ROUND((((ET53)-(EU53))+AE53),6) -> 0 | AE53: =ROUND((EU53),6) -> 0 | AF53: =ROUND((EV53),6) -> 0 | AG53: =ROUND((AP53),6) -> 0 | AH53: =(EW53) -> 0 | AI53: =(EX53) -> 0 | AJ53: =(AS53) -> 0 | AK53: 13997.58 | AL53: 13997.58 | AM53: 0 | AN53: 0 | AO53: 0 | AP53: 0 | AQ53: 0 | AR53: 0 | AS53: 0 | AT53: 0 | AU53: 0 | AV53: 1 | AW53: 1 | AZ53: 1 | BA53: 1 | BB53: 1 | BC53: 7.66 | BH53: 3 | BI53: 3 | BM53: 746 | BN53: 0 | BP53: 0 | BQ53: 130 | BR53: 0 | BS53: 1 | BT53: 1 | BU53: 1 | BV53: 1 | BW53: 1 | BX53: 1 | BZ53: 0 | CA53: 0 | CE53: 1566 | CF53: 0 | CG53: 0 | CM53: 0 | CO53: 0 | CP53: =(P53+Q53+S53) -> 750550.24 | CQ53: =ROUND((ROUND((AC53*1),2)*BC53),2) -> 107221.46 | CR53: =(ROUND((ROUND(((ET53)*AV53*1),2)*BB53),2)+ROUND((ROUND(((AE53-(EU53))*AV53*1),2)*BS53),2)) -> 0 | CS53: =(ROUND((ROUND(((EU53)*AV53*1),2)*BS53),2)+ROUND((ROUND(((AE53-(EU53))*AV53*1),2)*BS53),2)) -> 0 | CT53: =ROUND((ROUND((AF53*AV53*1),2)*BA53),2) -> 0 | CU53: =AG53 -> 0 | CV53: =(AH53*AV53) -> 0 | CW53: =AI53 -> 0 | CX53: =AJ53 -> 0 | CY53: =(ROUND((((S53+ROUND((ROUND(((EU53)*AV53*1),2)*BS53),2))*AT53)/100),2)+ROUND(((ROUND((ROUND(((AE53-(EU53))*AV53*1),2)*BS53),2)*AT53)/100),2)) -> 0 | CZ53: =(ROUND((((S53+ROUND((ROUND(((EU53)*AV53*1),2)*BS53),2))*AU53)/100),2)+ROUND(((ROUND((ROUND(((AE53-(EU53))*AV53*1),2)*BS53),2)*AU53)/100),2)) -> 0 | DN53: 0 | DO53: 0 | DP53: 1 | DQ53: 1 | DU53: 1013 | DV53: ШТ | DW53: ШТ | DX53: 1 | EE53: 60088638 | EF53: 130 | EG53: Сметная стоимость оборудования | EH53: 0 | EJ53: 3 | EK53: 746 | EL53: ТСН-2001.13. Сметная стоимость оборудования | EM53: ТСН-2001.13 | EQ53: 0 | ER53: 0 | ES53: 13997.58 | ET53: 0 | EU53: 0 | EV53: 0 | EW53: 0 | EX53: 0 | EY53: 0 | EZ53: 5 | FC53: 1 | FD53: 18 | FF53: 123437 | FQ53: 0 | FR53: =P53 -> 750550.24 | FS53: 0 | FX53: 0 | FY53: 0 | GA53: [123 437 / 1,2 / 7,66] + 3% Трансп + 1,2% Заг.скл | GD53: 1 | GF53: 1048200997 | GG53: 2 | GH53: 3 | GI53: 5 | GJ53: 0 | GK53: 0 | GL53: =ROUND(IF(AND(BH53=3,BI53=3,FS53<>0),P53,0),2) -> 0 | GM53: =ROUND(O53+X53+Y53,2)+GX53 -> 750550.24 | GN53: =IF(OR(BI53=0,BI53=1),GM53-GX53,0) -> 0 | GO53: =IF(BI53=2,GM53-GX53,0) -> 0 | GP53: =IF(BI53=4,GM53-GX53,0) -> 0 | GR53: 1 | GS53: 1 | GT53: 0 | GV53: =ROUND((GT53),6) -> 0 | GW53: 1 | GX53: =ROUND(HC53*I53,2) -> 0 | HA53: 0 | HB53: 0 | HC53: =GV53*GW53 -> 0 | HE53: 3 | HF53: 1,2 | HS53: 0 | IK53: 0
A54: 17 | B54: 1 | C54: =ROW(SmtRes!A46) -> 46 | D54: =ROW(EtalonRes!A57) -> 57 | E54: 14 | F54: 4.10-32-4 | G54: Монтаж платы дополнительной, устанавливаемой на готовом месте стойки | H54: 1 ШТ. | I54: 18 | J54: 0 | K54: 18 | O54: =ROUND(CP54,2) -> 677.26 | P54: =ROUND((ROUND((AC54*AW54*I54),2)*BC54),2) -> 0 | Q54: =(ROUND((ROUND((((ET54*1.1))*AV54*I54),2)*BB54),2)+ROUND((ROUND(((AE54-((EU54*1.1)))*AV54*I54),2)*BS54),2)) -> 190.51 | R54: =(ROUND((ROUND((((EU54*1.1))*AV54*I54),2)*BS54),2)+ROUND((ROUND(((AE54-((EU54*1.1)))*AV54*I54),2)*BS54),2)) -> 20.94 | S54: =ROUND((ROUND((AF54*AV54*I54),2)*BA54),2) -> 486.75 | T54: =ROUND(CU54*I54,2) -> 0 | U54: =CV54*I54 -> 43.53426 | V54: =CW54*I54 -> 0 | W54: =ROUND(CX54*I54,2) -> 0 | X54: =(ROUND((((S54+ROUND((ROUND((((EU54*1.1))*AV54*I54),2)*BS54),2))*AT54)/100),2)+ROUND(((ROUND((ROUND(((AE54-((EU54*1.1)))*AV54*I54),2)*BS54),2)*AT54)/100),2)) -> 456.92 | Y54: =(ROUND((((S54+ROUND((ROUND((((EU54*1.1))*AV54*I54),2)*BS54),2))*AU54)/100),2)+ROUND(((ROUND((ROUND(((AE54-((EU54*1.1)))*AV54*I54),2)*BS54),2)*AU54)/100),2)) -> 233.54 | AA54: 60258064 | AB54: =ROUND((AC54+AD54+AF54),6) -> 35.937 | AC54: =ROUND((ES54),6) -> 0 | AD54: =ROUND(((((ET54*1.1))-((EU54*1.1)))+AE54),6) -> 10.109 | AE54: =ROUND(((EU54*1.1)),6) -> 1.111 | AF54: =ROUND(((EV54*1.1)),6) -> 25.828 | AG54: =ROUND((AP54),6) -> 0 | AH54: =((EW54*1.1)) -> 2.31 | AI54: =((EX54*1.1)) -> 0 | AJ54: =(AS54) -> 0 | AK54: 32.67 | AL54: 0 | AM54: 9.19 | AN54: 1.01 | AO54: 23.48 | AP54: 0 | AQ54: 2.1 | AR54: 0 | AS54: 0 | AT54: 90 | AU54: 46 | AV54: 1.047 | AW54: 1 | AZ54: 1 | BA54: 1 | BB54: 1 | BC54: 1 | BH54: 0 | BI54: 2 | BJ54: ТСН-2001.4 Доп. 68, Сб. 10, т. 32, поз. 4 | BM54: 68 | BN54: 58973116 | BO54: 4.10-32-4 | BP54: 1 | BQ54: 40 | BR54: 0 | BS54: 1 | BT54: 1 | BU54: 1 | BV54: 1 | BW54: 1 | BX54: 1 | BZ54: 90 | CA54: 46 | CE54: 1566 | CF54: 0 | CG54: 0 | CM54: 0 | CN54: Поправка: О.П. п.3.4.30.в Наименование: При применении территориальных сметных нормативов для города Москвы затраты, учитывающие напряженные и стесненные условия производства работ (стесненность, сложность складирования и транспортной логистики и т.п.), исчисляются с применением коэффициентов к затратам труда и заработной плате рабочих, машинистов, времени эксплуатации машин и механизмов, стоимости эксплуатации машин в размере: для объектов, расположенных за пределами Третьего транспортного кольца города Москвы, но в пределах Московской кольцевой автомобильной дороги | CO54: 0 | CP54: =(P54+Q54+S54) -> 677.26 | CQ54: =ROUND((ROUND((AC54*AW54*1),2)*BC54),2) -> 0 | CR54: =(ROUND((ROUND((((ET54*1.1))*AV54*1),2)*BB54),2)+ROUND((ROUND(((AE54-((EU54*1.1)))*AV54*1),2)*BS54),2)) -> 10.58 | CS54: =(ROUND((ROUND((((EU54*1.1))*AV54*1),2)*BS54),2)+ROUND((ROUND(((AE54-((EU54*1.1)))*AV54*1),2)*BS54),2)) -> 1.16 | CT54: =ROUND((ROUND((AF54*AV54*1),2)*BA54),2) -> 27.04 | CU54: =AG54 -> 0 | CV54: =(AH54*AV54) -> 2.41857 | CW54: =AI54 -> 0 | CX54: =AJ54 -> 0 | CY54: =(ROUND((((S54+ROUND((ROUND((((EU54*1.1))*AV54*1),2)*BS54),2))*AT54)/100),2)+ROUND(((ROUND((ROUND(((AE54-((EU54*1.1)))*AV54*1),2)*BS54),2)*AT54)/100),2)) -> 439.12 | CZ54: =(ROUND((((S54+ROUND((ROUND((((EU54*1.1))*AV54*1),2)*BS54),2))*AU54)/100),2)+ROUND(((ROUND((ROUND(((AE54-((EU54*1.1)))*AV54*1),2)*BS54),2)*AU54)/100),2)) -> 224.44 | DB54: 11 | DE54: *1,1 | DF54: *1,1 | DG54: *1,1 | DI54: *1,1 | DJ54: *1,1 | DN54: 0 | DO54: 0 | DP54: 1 | DQ54: 1 | DU54: 1013 | DV54: 1 ШТ. | DW54: 1 ШТ. | DX54: 1 | EE54: 60088532 | EF54: 40 | EG54: Монтаж оборудования | EH54: 0 | EJ54: 2 | EK54: 68 | EL54: ТСН-2001.4-10. Прокладка и монтаж сетей связи | EM54: ТСН-2001.4-10-1 | EO54: Поправка: О.П. п.3.4.30.в | EQ54: 0 | ER54: 32.67 | ES54: 0 | ET54: 9.19 | EU54: 1.01 | EV54: 23.48 | EW54: 2.1 | EX54: 0 | EY54: 0 | FQ54: 0 | FR54: 0 | FS54: 0 | FX54: 90 | FY54: 46 | GD54: 1 | GF54: 329085480 | GG54: 2 | GH54: 1 | GI54: 2 | GJ54: 0 | GK54: 0 | GL54: =ROUND(IF(AND(BH54=3,BI54=3,FS54<>0),P54,0),2) -> 0 | GM54: =ROUND(O54+X54+Y54,2)+GX54 -> 1367.72 | GN54: =IF(OR(BI54=0,BI54=1),GM54-GX54,0) -> 0 | GO54: =IF(BI54=2,GM54-GX54,0) -> 1367.72 | GP54: =IF(BI54=4,GM54-GX54,0) -> 0 | GR54: 0 | GS54: 3 | GT54: 0 | GV54: =ROUND((GT54),6) -> 0 | GW54: 1 | GX54: =ROUND(HC54*I54,2) -> 0 | HA54: 0 | HB54: 0 | HC54: =GV54*GW54 -> 0 | HS54: 0 | IK54: 0
A55: 17 | B55: 1 | C55: =ROW(SmtRes!A48) -> 48 | D55: =ROW(EtalonRes!A60) -> 60 | E55: 14 | F55: 4.10-32-4 | G55: Монтаж платы дополнительной, устанавливаемой на готовом месте стойки | H55: 1 ШТ. | I55: 18 | J55: 0 | K55: 18 | O55: =ROUND(CP55,2) -> 29709.76 | P55: =ROUND((ROUND((AC55*AW55*I55),2)*BC55),2) -> 0 | Q55: =(ROUND((ROUND((((ET55*1.1))*AV55*I55),2)*BB55),2)+ROUND((ROUND(((AE55-((EU55*1.1)))*AV55*I55),2)*BS55),2)) -> 2943.38 | R55: =(ROUND((ROUND((((EU55*1.1))*AV55*I55),2)*BS55),2)+ROUND((ROUND(((AE55-((EU55*1.1)))*AV55*I55),2)*BS55),2)) -> 1151.49 | S55: =ROUND((ROUND((AF55*AV55*I55),2)*BA55),2) -> 26766.38 | T55: =ROUND(CU55*I55,2) -> 0 | U55: =CV55*I55 -> 43.53426 | V55: =CW55*I55 -> 0 | W55: =ROUND(CX55*I55,2) -> 0 | X55: =(ROUND((((S55+ROUND((ROUND((((EU55*1.1))*AV55*I55),2)*BS55),2))*AT55)/100),2)+ROUND(((ROUND((ROUND(((AE55-((EU55*1.1)))*AV55*I55),2)*BS55),2)*AT55)/100),2)) -> 25126.08 | Y55: =(ROUND((((S55+ROUND((ROUND((((EU55*1.1))*AV55*I55),2)*BS55),2))*AU55)/100),2)+ROUND(((ROUND((ROUND(((AE55-((EU55*1.1)))*AV55*I55),2)*BS55),2)*AU55)/100),2)) -> 12842.22 | AA55: 60258061 | AB55: =ROUND((AC55+AD55+AF55),6) -> 35.937 | AC55: =ROUND((ES55),6) -> 0 | AD55: =ROUND(((((ET55*1.1))-((EU55*1.1)))+AE55),6) -> 10.109 | AE55: =ROUND(((EU55*1.1)),6) -> 1.111 | AF55: =ROUND(((EV55*1.1)),6) -> 25.828 | AG55: =ROUND((AP55),6) -> 0 | AH55: =((EW55*1.1)) -> 2.31 | AI55: =((EX55*1.1)) -> 0 | AJ55: =(AS55) -> 0 | AK55: 32.67 | AL55: 0 | AM55: 9.19 | AN55: 1.01 | AO55: 23.48 | AP55: 0 | AQ55: 2.1 | AR55: 0 | AS55: 0 | AT55: 90 | AU55: 46 | AV55: 1.047 | AW55: 1 | AZ55: 1 | BA55: 54.99 | BB55: 15.45 | BC55: 1 | BH55: 0 | BI55: 2 | BJ55: ТСН-2001.4 Доп. 68, Сб. 10, т. 32, поз. 4 | BM55: 68 | BN55: 58973116 | BO55: 4.10-32-4 | BP55: 1 | BQ55: 40 | BR55: 0 | BS55: 54.99 | BT55: 1 | BU55: 1 | BV55: 1 | BW55: 1 | BX55: 1 | BZ55: 90 | CA55: 46 | CE55: 1566 | CF55: 0 | CG55: 0 | CM55: 0 | CN55: Поправка: О.П. п.3.4.30.в Наименование: При применении территориальных сметных нормативов для города Москвы затраты, учитывающие напряженные и стесненные условия производства работ (стесненность, сложность складирования и транспортной логистики и т.п.), исчисляются с применением коэффициентов к затратам труда и заработной плате рабочих, машинистов, времени эксплуатации машин и механизмов, стоимости эксплуатации машин в размере: для объектов, расположенных за пределами Третьего транспортного кольца города Москвы, но в пределах Московской кольцевой автомобильной дороги | CO55: 0 | CP55: =(P55+Q55+S55) -> 29709.76 | CQ55: =ROUND((ROUND((AC55*AW55*1),2)*BC55),2) -> 0 | CR55: =(ROUND((ROUND((((ET55*1.1))*AV55*1),2)*BB55),2)+ROUND((ROUND(((AE55-((EU55*1.1)))*AV55*1),2)*BS55),2)) -> 163.46 | CS55: =(ROUND((ROUND((((EU55*1.1))*AV55*1),2)*BS55),2)+ROUND((ROUND(((AE55-((EU55*1.1)))*AV55*1),2)*BS55),2)) -> 63.79 | CT55: =ROUND((ROUND((AF55*AV55*1),2)*BA55),2) -> 1486.93 | CU55: =AG55 -> 0 | CV55: =(AH55*AV55) -> 2.41857 | CW55: =AI55 -> 0 | CX55: =AJ55 -> 0 | CY55: =(ROUND((((S55+ROUND((ROUND((((EU55*1.1))*AV55*1),2)*BS55),2))*AT55)/100),2)+ROUND(((ROUND((ROUND(((AE55-((EU55*1.1)))*AV55*1),2)*BS55),2)*AT55)/100),2)) -> 24147.15 | CZ55: =(ROUND((((S55+ROUND((ROUND((((EU55*1.1))*AV55*1),2)*BS55),2))*AU55)/100),2)+ROUND(((ROUND((ROUND(((AE55-((EU55*1.1)))*AV55*1),2)*BS55),2)*AU55)/100),2)) -> 12341.88 | DB55: 12 | DE55: *1,1 | DF55: *1,1 | DG55: *1,1 | DI55: *1,1 | DJ55: *1,1 | DN55: 0 | DO55: 0 | DP55: 1 | DQ55: 1 | DU55: 1013 | DV55: 1 ШТ. | DW55: 1 ШТ. | DX55: 1 | EE55: 60088532 | EF55: 40 | EG55: Монтаж оборудования | EH55: 0 | EJ55: 2 | EK55: 68 | EL55: ТСН-2001.4-10. Прокладка и монтаж сетей связи | EM55: ТСН-2001.4-10-1 | EO55: Поправка: О.П. п.3.4.30.в | EQ55: 0 | ER55: 32.67 | ES55: 0 | ET55: 9.19 | EU55: 1.01 | EV55: 23.48 | EW55: 2.1 | EX55: 0 | EY55: 0 | FQ55: 0 | FR55: 0 | FS55: 0 | FX55: 90 | FY55: 46 | GD55: 1 | GF55: 329085480 | GG55: 2 | GH55: 1 | GI55: 2 | GJ55: 0 | GK55: 0 | GL55: =ROUND(IF(AND(BH55=3,BI55=3,FS55<>0),P55,0),2) -> 0 | GM55: =ROUND(O55+X55+Y55,2)+GX55 -> 67678.06 | GN55: =IF(OR(BI55=0,BI55=1),GM55-GX55,0) -> 0 | GO55: =IF(BI55=2,GM55-GX55,0) -> 67678.06 | GP55: =IF(BI55=4,GM55-GX55,0) -> 0 | GR55: 0 | GS55: 3 | GT55: 0 | GV55: =ROUND((GT55),6) -> 0 | GW55: 1 | GX55: =ROUND(HC55*I55,2) -> 0 | HA55: 0 | HB55: 0 | HC55: =GV55*GW55 -> 0 | HS55: 0 | IK55: 0
A56: 17 | B56: 1 | E56: 15 | F56: КА-9 | G56: SFP 1,25 GE модуль 550 м, ММ, 2 волокна, 850 пт, LC, DDM FH-S8512CDL05 | H56: ШТ | I56: 18 | J56: 0 | K56: 18 | O56: =ROUND(CP56,2) -> 5807.34 | P56: =ROUND((ROUND((AC56*I56),2)*BC56),2) -> 5807.34 | Q56: =(ROUND((ROUND(((ET56)*AV56*I56),2)*BB56),2)+ROUND((ROUND(((AE56-(EU56))*AV56*I56),2)*BS56),2)) -> 0 | R56: =(ROUND((ROUND(((EU56)*AV56*I56),2)*BS56),2)+ROUND((ROUND(((AE56-(EU56))*AV56*I56),2)*BS56),2)) -> 0 | S56: =ROUND((ROUND((AF56*AV56*I56),2)*BA56),2) -> 0 | T56: =ROUND(CU56*I56,2) -> 0 | U56: =CV56*I56 -> 0 | V56: =CW56*I56 -> 0 | W56: =ROUND(CX56*I56,2) -> 0 | X56: =(ROUND((((S56+ROUND((ROUND(((EU56)*AV56*I56),2)*BS56),2))*AT56)/100),2)+ROUND(((ROUND((ROUND(((AE56-(EU56))*AV56*I56),2)*BS56),2)*AT56)/100),2)) -> 0 | Y56: =(ROUND((((S56+ROUND((ROUND(((EU56)*AV56*I56),2)*BS56),2))*AU56)/100),2)+ROUND(((ROUND((ROUND(((AE56-(EU56))*AV56*I56),2)*BS56),2)*AU56)/100),2)) -> 0 | AA56: 60258064 | AB56: =ROUND((AC56+AD56+AF56),6) -> 322.63 | AC56: =ROUND((ES56),6) -> 322.63 | AD56: =ROUND((((ET56)-(EU56))+AE56),6) -> 0 | AE56: =ROUND((EU56),6) -> 0 | AF56: =ROUND((EV56),6) -> 0 | AG56: =ROUND((AP56),6) -> 0 | AH56: =(EW56) -> 0 | AI56: =(EX56) -> 0 | AJ56: =(AS56) -> 0 | AK56: 322.63 | AL56: 322.63 | AM56: 0 | AN56: 0 | AO56: 0 | AP56: 0 | AQ56: 0 | AR56: 0 | AS56: 0 | AT56: 0 | AU56: 0 | AV56: 1 | AW56: 1 | AZ56: 1 | BA56: 1 | BB56: 1 | BC56: 1 | BH56: 3 | BI56: 3 | BM56: 746 | BN56: 0 | BP56: 0 | BQ56: 130 | BR56: 0 | BS56: 1 | BT56: 1 | BU56: 1 | BV56: 1 | BW56: 1 | BX56: 1 | BZ56: 0 | CA56: 0 | CE56: 1566 | CF56: 0 | CG56: 0 | CM56: 0 | CO56: 0 | CP56: =(P56+Q56+S56) -> 5807.34 | CQ56: =ROUND((ROUND((AC56*1),2)*BC56),2) -> 322.63 | CR56: =(ROUND((ROUND(((ET56)*AV56*1),2)*BB56),2)+ROUND((ROUND(((AE56-(EU56))*AV56*1),2)*BS56),2)) -> 0 | CS56: =(ROUND((ROUND(((EU56)*AV56*1),2)*BS56),2)+ROUND((ROUND(((AE56-(EU56))*AV56*1),2)*BS56),2)) -> 0 | CT56: =ROUND((ROUND((AF56*AV56*1),2)*BA56),2) -> 0 | CU56: =AG56 -> 0 | CV56: =(AH56*AV56) -> 0 | CW56: =AI56 -> 0 | CX56: =AJ56 -> 0 | CY56: =(ROUND((((S56+ROUND((ROUND(((EU56)*AV56*1),2)*BS56),2))*AT56)/100),2)+ROUND(((ROUND((ROUND(((AE56-(EU56))*AV56*1),2)*BS56),2)*AT56)/100),2)) -> 0 | CZ56: =(ROUND((((S56+ROUND((ROUND(((EU56)*AV56*1),2)*BS56),2))*AU56)/100),2)+ROUND(((ROUND((ROUND(((AE56-(EU56))*AV56*1),2)*BS56),2)*AU56)/100),2)) -> 0 | DN56: 0 | DO56: 0 | DP56: 1 | DQ56: 1 | DU56: 1013 | DV56: ШТ | DW56: ШТ | DX56: 1 | EE56: 60088638 | EF56: 130 | EG56: Сметная стоимость оборудования | EH56: 0 | EJ56: 3 | EK56: 746 | EL56: ТСН-2001.13. Сметная стоимость оборудования | EM56: ТСН-2001.13 | EQ56: 0 | ER56: 0 | ES56: 322.63 | ET56: 0 | EU56: 0 | EV56: 0 | EW56: 0 | EX56: 0 | EY56: 0 | FQ56: 0 | FR56: =P56 -> 5807.34 | FS56: 0 | FX56: 0 | FY56: 0 | GA56: [2 845 / 1,2 / 7,66] + 3% Трансп + 1,2% Заг.скл | GD56: 1 | GF56: 2127587981 | GG56: 2 | GH56: 4 | GI56: -2 | GJ56: 0 | GK56: 0 | GL56: =ROUND(IF(AND(BH56=3,BI56=3,FS56<>0),P56,0),2) -> 0 | GM56: =ROUND(O56+X56+Y56,2)+GX56 -> 5807.34 | GN56: =IF(OR(BI56=0,BI56=1),GM56-GX56,0) -> 0 | GO56: =IF(BI56=2,GM56-GX56,0) -> 0 | GP56: =IF(BI56=4,GM56-GX56,0) -> 0 | GR56: 0 | GS56: 2 | GT56: 0 | GV56: =ROUND((GT56),6) -> 0 | GW56: 1 | GX56: =ROUND(HC56*I56,2) -> 0 | HA56: 0 | HB56: 0 | HC56: =GV56*GW56 -> 0 | HE56: 3 | HF56: 1,2 | HS56: 0 | IK56: 0
A57: 17 | B57: 1 | E57: 15 | F57: КА-9 | G57: SFP 1,25 GE модуль 550 м, ММ, 2 волокна, 850 пт, LC, DDM FH-S8512CDL05 | H57: ШТ | I57: 18 | J57: 0 | K57: 18 | O57: =ROUND(CP57,2) -> 44484.22 | P57: =ROUND((ROUND((AC57*I57),2)*BC57),2) -> 44484.22 | Q57: =(ROUND((ROUND(((ET57)*AV57*I57),2)*BB57),2)+ROUND((ROUND(((AE57-(EU57))*AV57*I57),2)*BS57),2)) -> 0 | R57: =(ROUND((ROUND(((EU57)*AV57*I57),2)*BS57),2)+ROUND((ROUND(((AE57-(EU57))*AV57*I57),2)*BS57),2)) -> 0 | S57: =ROUND((ROUND((AF57*AV57*I57),2)*BA57),2) -> 0 | T57: =ROUND(CU57*I57,2) -> 0 | U57: =CV57*I57 -> 0 | V57: =CW57*I57 -> 0 | W57: =ROUND(CX57*I57,2) -> 0 | X57: =(ROUND((((S57+ROUND((ROUND(((EU57)*AV57*I57),2)*BS57),2))*AT57)/100),2)+ROUND(((ROUND((ROUND(((AE57-(EU57))*AV57*I57),2)*BS57),2)*AT57)/100),2)) -> 0 | Y57: =(ROUND((((S57+ROUND((ROUND(((EU57)*AV57*I57),2)*BS57),2))*AU57)/100),2)+ROUND(((ROUND((ROUND(((AE57-(EU57))*AV57*I57),2)*BS57),2)*AU57)/100),2)) -> 0 | AA57: 60258061 | AB57: =ROUND((AC57+AD57+AF57),6) -> 322.63 | AC57: =ROUND((ES57),6) -> 322.63 | AD57: =ROUND((((ET57)-(EU57))+AE57),6) -> 0 | AE57: =ROUND((EU57),6) -> 0 | AF57: =ROUND((EV57),6) -> 0 | AG57: =ROUND((AP57),6) -> 0 | AH57: =(EW57) -> 0 | AI57: =(EX57) -> 0 | AJ57: =(AS57) -> 0 | AK57: 322.63 | AL57: 322.63 | AM57: 0 | AN57: 0 | AO57: 0 | AP57: 0 | AQ57: 0 | AR57: 0 | AS57: 0 | AT57: 0 | AU57: 0 | AV57: 1 | AW57: 1 | AZ57: 1 | BA57: 1 | BB57: 1 | BC57: 7.66 | BH57: 3 | BI57: 3 | BM57: 746 | BN57: 0 | BP57: 0 | BQ57: 130 | BR57: 0 | BS57: 1 | BT57: 1 | BU57: 1 | BV57: 1 | BW57: 1 | BX57: 1 | BZ57: 0 | CA57: 0 | CE57: 1566 | CF57: 0 | CG57: 0 | CM57: 0 | CO57: 0 | CP57: =(P57+Q57+S57) -> 44484.22 | CQ57: =ROUND((ROUND((AC57*1),2)*BC57),2) -> 2471.35 | CR57: =(ROUND((ROUND(((ET57)*AV57*1),2)*BB57),2)+ROUND((ROUND(((AE57-(EU57))*AV57*1),2)*BS57),2)) -> 0 | CS57: =(ROUND((ROUND(((EU57)*AV57*1),2)*BS57),2)+ROUND((ROUND(((AE57-(EU57))*AV57*1),2)*BS57),2)) -> 0 | CT57: =ROUND((ROUND((AF57*AV57*1),2)*BA57),2) -> 0 | CU57: =AG57 -> 0 | CV57: =(AH57*AV57) -> 0 | CW57: =AI57 -> 0 | CX57: =AJ57 -> 0 | CY57: =(ROUND((((S57+ROUND((ROUND(((EU57)*AV57*1),2)*BS57),2))*AT57)/100),2)+ROUND(((ROUND((ROUND(((AE57-(EU57))*AV57*1),2)*BS57),2)*AT57)/100),2)) -> 0 | CZ57: =(ROUND((((S57+ROUND((ROUND(((EU57)*AV57*1),2)*BS57),2))*AU57)/100),2)+ROUND(((ROUND((ROUND(((AE57-(EU57))*AV57*1),2)*BS57),2)*AU57)/100),2)) -> 0 | DN57: 0 | DO57: 0 | DP57: 1 | DQ57: 1 | DU57: 1013 | DV57: ШТ | DW57: ШТ | DX57: 1 | EE57: 60088638 | EF57: 130 | EG57: Сметная стоимость оборудования | EH57: 0 | EJ57: 3 | EK57: 746 | EL57: ТСН-2001.13. Сметная стоимость оборудования | EM57: ТСН-2001.13 | EQ57: 0 | ER57: 0 | ES57: 322.63 | ET57: 0 | EU57: 0 | EV57: 0 | EW57: 0 | EX57: 0 | EY57: 0 | EZ57: 5 | FC57: 1 | FD57: 18 | FF57: 2845 | FQ57: 0 | FR57: =P57 -> 44484.22 | FS57: 0 | FX57: 0 | FY57: 0 | GA57: [2 845 / 1,2 / 7,66] + 3% Трансп + 1,2% Заг.скл | GD57: 1 | GF57: 2127587981 | GG57: 2 | GH57: 3 | GI57: 5 | GJ57: 0 | GK57: 0 | GL57: =ROUND(IF(AND(BH57=3,BI57=3,FS57<>0),P57,0),2) -> 0 | GM57: =ROUND(O57+X57+Y57,2)+GX57 -> 44484.22 | GN57: =IF(OR(BI57=0,BI57=1),GM57-GX57,0) -> 0 | GO57: =IF(BI57=2,GM57-GX57,0) -> 0 | GP57: =IF(BI57=4,GM57-GX57,0) -> 0 | GR57: 1 | GS57: 1 | GT57: 0 | GV57: =ROUND((GT57),6) -> 0 | GW57: 1 | GX57: =ROUND(HC57*I57,2) -> 0 | HA57: 0 | HB57: 0 | HC57: =GV57*GW57 -> 0 | HE57: 3 | HF57: 1,2 | HS57: 0 | IK57: 0
A58: 17 | B58: 1 | C58: =ROW(SmtRes!A50) -> 50 | D58: =ROW(EtalonRes!A63) -> 63 | E58: 16 | F58: 4.10-32-4 | G58: Монтаж платы дополнительной, устанавливаемой на готовом месте стойки | H58: 1 ШТ. | I58: 3 | J58: 0 | K58: 3 | O58: =ROUND(CP58,2) -> 112.88 | P58: =ROUND((ROUND((AC58*AW58*I58),2)*BC58),2) -> 0 | Q58: =(ROUND((ROUND((((ET58*1.1))*AV58*I58),2)*BB58),2)+ROUND((ROUND(((AE58-((EU58*1.1)))*AV58*I58),2)*BS58),2)) -> 31.75 | R58: =(ROUND((ROUND((((EU58*1.1))*AV58*I58),2)*BS58),2)+ROUND((ROUND(((AE58-((EU58*1.1)))*AV58*I58),2)*BS58),2)) -> 3.49 | S58: =ROUND((ROUND((AF58*AV58*I58),2)*BA58),2) -> 81.13 | T58: =ROUND(CU58*I58,2) -> 0 | U58: =CV58*I58 -> 7.25571 | V58: =CW58*I58 -> 0 | W58: =ROUND(CX58*I58,2) -> 0 | X58: =(ROUND((((S58+ROUND((ROUND((((EU58*1.1))*AV58*I58),2)*BS58),2))*AT58)/100),2)+ROUND(((ROUND((ROUND(((AE58-((EU58*1.1)))*AV58*I58),2)*BS58),2)*AT58)/100),2)) -> 76.16 | Y58: =(ROUND((((S58+ROUND((ROUND((((EU58*1.1))*AV58*I58),2)*BS58),2))*AU58)/100),2)+ROUND(((ROUND((ROUND(((AE58-((EU58*1.1)))*AV58*I58),2)*BS58),2)*AU58)/100),2)) -> 38.93 | AA58: 60258064 | AB58: =ROUND((AC58+AD58+AF58),6) -> 35.937 | AC58: =ROUND((ES58),6) -> 0 | AD58: =ROUND(((((ET58*1.1))-((EU58*1.1)))+AE58),6) -> 10.109 | AE58: =ROUND(((EU58*1.1)),6) -> 1.111 | AF58: =ROUND(((EV58*1.1)),6) -> 25.828 | AG58: =ROUND((AP58),6) -> 0 | AH58: =((EW58*1.1)) -> 2.31 | AI58: =((EX58*1.1)) -> 0 | AJ58: =(AS58) -> 0 | AK58: 32.67 | AL58: 0 | AM58: 9.19 | AN58: 1.01 | AO58: 23.48 | AP58: 0 | AQ58: 2.1 | AR58: 0 | AS58: 0 | AT58: 90 | AU58: 46 | AV58: 1.047 | AW58: 1 | AZ58: 1 | BA58: 1 | BB58: 1 | BC58: 1 | BH58: 0 | BI58: 2 | BJ58: ТСН-2001.4 Доп. 68, Сб. 10, т. 32, поз. 4 | BM58: 68 | BN58: 58973116 | BO58: 4.10-32-4 | BP58: 1 | BQ58: 40 | BR58: 0 | BS58: 1 | BT58: 1 | BU58: 1 | BV58: 1 | BW58: 1 | BX58: 1 | BZ58: 90 | CA58: 46 | CE58: 1566 | CF58: 0 | CG58: 0 | CM58: 0 | CN58: Поправка: О.П. п.3.4.30.в Наименование: При применении территориальных сметных нормативов для города Москвы затраты, учитывающие напряженные и стесненные условия производства работ (стесненность, сложность складирования и транспортной логистики и т.п.), исчисляются с применением коэффициентов к затратам труда и заработной плате рабочих, машинистов, времени эксплуатации машин и механизмов, стоимости эксплуатации машин в размере: для объектов, расположенных за пределами Третьего транспортного кольца города Москвы, но в пределах Московской кольцевой автомобильной дороги | CO58: 0 | CP58: =(P58+Q58+S58) -> 112.88 | CQ58: =ROUND((ROUND((AC58*AW58*1),2)*BC58),2) -> 0 | CR58: =(ROUND((ROUND((((ET58*1.1))*AV58*1),2)*BB58),2)+ROUND((ROUND(((AE58-((EU58*1.1)))*AV58*1),2)*BS58),2)) -> 10.58 | CS58: =(ROUND((ROUND((((EU58*1.1))*AV58*1),2)*BS58),2)+ROUND((ROUND(((AE58-((EU58*1.1)))*AV58*1),2)*BS58),2)) -> 1.16 | CT58: =ROUND((ROUND((AF58*AV58*1),2)*BA58),2) -> 27.04 | CU58: =AG58 -> 0 | CV58: =(AH58*AV58) -> 2.41857 | CW58: =AI58 -> 0 | CX58: =AJ58 -> 0 | CY58: =(ROUND((((S58+ROUND((ROUND((((EU58*1.1))*AV58*1),2)*BS58),2))*AT58)/100),2)+ROUND(((ROUND((ROUND(((AE58-((EU58*1.1)))*AV58*1),2)*BS58),2)*AT58)/100),2)) -> 74.06 | CZ58: =(ROUND((((S58+ROUND((ROUND((((EU58*1.1))*AV58*1),2)*BS58),2))*AU58)/100),2)+ROUND(((ROUND((ROUND(((AE58-((EU58*1.1)))*AV58*1),2)*BS58),2)*AU58)/100),2)) -> 37.85 | DB58: 13 | DE58: *1,1 | DF58: *1,1 | DG58: *1,1 | DI58: *1,1 | DJ58: *1,1 | DN58: 0 | DO58: 0 | DP58: 1 | DQ58: 1 | DU58: 1013 | DV58: 1 ШТ. | DW58: 1 ШТ. | DX58: 1 | EE58: 60088532 | EF58: 40 | EG58: Монтаж оборудования | EH58: 0 | EJ58: 2 | EK58: 68 | EL58: ТСН-2001.4-10. Прокладка и монтаж сетей связи | EM58: ТСН-2001.4-10-1 | EO58: Поправка: О.П. п.3.4.30.в | EQ58: 0 | ER58: 32.67 | ES58: 0 | ET58: 9.19 | EU58: 1.01 | EV58: 23.48 | EW58: 2.1 | EX58: 0 | EY58: 0 | FQ58: 0 | FR58: 0 | FS58: 0 | FX58: 90 | FY58: 46 | GD58: 1 | GF58: 329085480 | GG58: 2 | GH58: 1 | GI58: 2 | GJ58: 0 | GK58: 0 | GL58: =ROUND(IF(AND(BH58=3,BI58=3,FS58<>0),P58,0),2) -> 0 | GM58: =ROUND(O58+X58+Y58,2)+GX58 -> 227.97 | GN58: =IF(OR(BI58=0,BI58=1),GM58-GX58,0) -> 0 | GO58: =IF(BI58=2,GM58-GX58,0) -> 227.97 | GP58: =IF(BI58=4,GM58-GX58,0) -> 0 | GR58: 0 | GS58: 3 | GT58: 0 | GV58: =ROUND((GT58),6) -> 0 | GW58: 1 | GX58: =ROUND(HC58*I58,2) -> 0 | HA58: 0 | HB58: 0 | HC58: =GV58*GW58 -> 0 | HS58: 0 | IK58: 0
A59: 17 | B59: 1 | C59: =ROW(SmtRes!A52) -> 52 | D59: =ROW(EtalonRes!A66) -> 66 | E59: 16 | F59: 4.10-32-4 | G59: Монтаж платы дополнительной, устанавливаемой на готовом месте стойки | H59: 1 ШТ. | I59: 3 | J59: 0 | K59: 3 | O59: =ROUND(CP59,2) -> 4951.88 | P59: =ROUND((ROUND((AC59*AW59*I59),2)*BC59),2) -> 0 | Q59: =(ROUND((ROUND((((ET59*1.1))*AV59*I59),2)*BB59),2)+ROUND((ROUND(((AE59-((EU59*1.1)))*AV59*I59),2)*BS59),2)) -> 490.54 | R59: =(ROUND((ROUND((((EU59*1.1))*AV59*I59),2)*BS59),2)+ROUND((ROUND(((AE59-((EU59*1.1)))*AV59*I59),2)*BS59),2)) -> 191.92 | S59: =ROUND((ROUND((AF59*AV59*I59),2)*BA59),2) -> 4461.34 | T59: =ROUND(CU59*I59,2) -> 0 | U59: =CV59*I59 -> 7.25571 | V59: =CW59*I59 -> 0 | W59: =ROUND(CX59*I59,2) -> 0 | X59: =(ROUND((((S59+ROUND((ROUND((((EU59*1.1))*AV59*I59),2)*BS59),2))*AT59)/100),2)+ROUND(((ROUND((ROUND(((AE59-((EU59*1.1)))*AV59*I59),2)*BS59),2)*AT59)/100),2)) -> 4187.93 | Y59: =(ROUND((((S59+ROUND((ROUND((((EU59*1.1))*AV59*I59),2)*BS59),2))*AU59)/100),2)+ROUND(((ROUND((ROUND(((AE59-((EU59*1.1)))*AV59*I59),2)*BS59),2)*AU59)/100),2)) -> 2140.5 | AA59: 60258061 | AB59: =ROUND((AC59+AD59+AF59),6) -> 35.937 | AC59: =ROUND((ES59),6) -> 0 | AD59: =ROUND(((((ET59*1.1))-((EU59*1.1)))+AE59),6) -> 10.109 | AE59: =ROUND(((EU59*1.1)),6) -> 1.111 | AF59: =ROUND(((EV59*1.1)),6) -> 25.828 | AG59: =ROUND((AP59),6) -> 0 | AH59: =((EW59*1.1)) -> 2.31 | AI59: =((EX59*1.1)) -> 0 | AJ59: =(AS59) -> 0 | AK59: 32.67 | AL59: 0 | AM59: 9.19 | AN59: 1.01 | AO59: 23.48 | AP59: 0 | AQ59: 2.1 | AR59: 0 | AS59: 0 | AT59: 90 | AU59: 46 | AV59: 1.047 | AW59: 1 | AZ59: 1 | BA59: 54.99 | BB59: 15.45 | BC59: 1 | BH59: 0 | BI59: 2 | BJ59: ТСН-2001.4 Доп. 68, Сб. 10, т. 32, поз. 4 | BM59: 68 | BN59: 58973116 | BO59: 4.10-32-4 | BP59: 1 | BQ59: 40 | BR59: 0 | BS59: 54.99 | BT59: 1 | BU59: 1 | BV59: 1 | BW59: 1 | BX59: 1 | BZ59: 90 | CA59: 46 | CE59: 1566 | CF59: 0 | CG59: 0 | CM59: 0 | CN59: Поправка: О.П. п.3.4.30.в Наименование: При применении территориальных сметных нормативов для города Москвы затраты, учитывающие напряженные и стесненные условия производства работ (стесненность, сложность складирования и транспортной логистики и т.п.), исчисляются с применением коэффициентов к затратам труда и заработной плате рабочих, машинистов, времени эксплуатации машин и механизмов, стоимости эксплуатации машин в размере: для объектов, расположенных за пределами Третьего транспортного кольца города Москвы, но в пределах Московской кольцевой автомобильной дороги | CO59: 0 | CP59: =(P59+Q59+S59) -> 4951.88 | CQ59: =ROUND((ROUND((AC59*AW59*1),2)*BC59),2) -> 0 | CR59: =(ROUND((ROUND((((ET59*1.1))*AV59*1),2)*BB59),2)+ROUND((ROUND(((AE59-((EU59*1.1)))*AV59*1),2)*BS59),2)) -> 163.46 | CS59: =(ROUND((ROUND((((EU59*1.1))*AV59*1),2)*BS59),2)+ROUND((ROUND(((AE59-((EU59*1.1)))*AV59*1),2)*BS59),2)) -> 63.79 | CT59: =ROUND((ROUND((AF59*AV59*1),2)*BA59),2) -> 1486.93 | CU59: =AG59 -> 0 | CV59: =(AH59*AV59) -> 2.41857 | CW59: =AI59 -> 0 | CX59: =AJ59 -> 0 | CY59: =(ROUND((((S59+ROUND((ROUND((((EU59*1.1))*AV59*1),2)*BS59),2))*AT59)/100),2)+ROUND(((ROUND((ROUND(((AE59-((EU59*1.1)))*AV59*1),2)*BS59),2)*AT59)/100),2)) -> 4072.62 | CZ59: =(ROUND((((S59+ROUND((ROUND((((EU59*1.1))*AV59*1),2)*BS59),2))*AU59)/100),2)+ROUND(((ROUND((ROUND(((AE59-((EU59*1.1)))*AV59*1),2)*BS59),2)*AU59)/100),2)) -> 2081.56 | DB59: 14 | DE59: *1,1 | DF59: *1,1 | DG59: *1,1 | DI59: *1,1 | DJ59: *1,1 | DN59: 0 | DO59: 0 | DP59: 1 | DQ59: 1 | DU59: 1013 | DV59: 1 ШТ. | DW59: 1 ШТ. | DX59: 1 | EE59: 60088532 | EF59: 40 | EG59: Монтаж оборудования | EH59: 0 | EJ59: 2 | EK59: 68 | EL59: ТСН-2001.4-10. Прокладка и монтаж сетей связи | EM59: ТСН-2001.4-10-1 | EO59: Поправка: О.П. п.3.4.30.в | EQ59: 0 | ER59: 32.67 | ES59: 0 | ET59: 9.19 | EU59: 1.01 | EV59: 23.48 | EW59: 2.1 | EX59: 0 | EY59: 0 | FQ59: 0 | FR59: 0 | FS59: 0 | FX59: 90 | FY59: 46 | GD59: 1 | GF59: 329085480 | GG59: 2 | GH59: 1 | GI59: 2 | GJ59: 0 | GK59: 0 | GL59: =ROUND(IF(AND(BH59=3,BI59=3,FS59<>0),P59,0),2) -> 0 | GM59: =ROUND(O59+X59+Y59,2)+GX59 -> 11280.31 | GN59: =IF(OR(BI59=0,BI59=1),GM59-GX59,0) -> 0 | GO59: =IF(BI59=2,GM59-GX59,0) -> 11280.31 | GP59: =IF(BI59=4,GM59-GX59,0) -> 0 | GR59: 0 | GS59: 3 | GT59: 0 | GV59: =ROUND((GT59),6) -> 0 | GW59: 1 | GX59: =ROUND(HC59*I59,2) -> 0 | HA59: 0 | HB59: 0 | HC59: =GV59*GW59 -> 0 | HS59: 0 | IK59: 0
A60: 17 | B60: 1 | E60: 17 | F60: КА-10 | G60: Грозозащита для локальной вычислительной сети, 16 GE RJ-45 SP-IP16/1000PR | H60: ШТ | I60: 3 | J60: 0 | K60: 3 | O60: =ROUND(CP60,2) -> 17130.54 | P60: =ROUND((ROUND((AC60*I60),2)*BC60),2) -> 17130.54 | Q60: =(ROUND((ROUND(((ET60)*AV60*I60),2)*BB60),2)+ROUND((ROUND(((AE60-(EU60))*AV60*I60),2)*BS60),2)) -> 0 | R60: =(ROUND((ROUND(((EU60)*AV60*I60),2)*BS60),2)+ROUND((ROUND(((AE60-(EU60))*AV60*I60),2)*BS60),2)) -> 0 | S60: =ROUND((ROUND((AF60*AV60*I60),2)*BA60),2) -> 0 | T60: =ROUND(CU60*I60,2) -> 0 | U60: =CV60*I60 -> 0 | V60: =CW60*I60 -> 0 | W60: =ROUND(CX60*I60,2) -> 0 | X60: =(ROUND((((S60+ROUND((ROUND(((EU60)*AV60*I60),2)*BS60),2))*AT60)/100),2)+ROUND(((ROUND((ROUND(((AE60-(EU60))*AV60*I60),2)*BS60),2)*AT60)/100),2)) -> 0 | Y60: =(ROUND((((S60+ROUND((ROUND(((EU60)*AV60*I60),2)*BS60),2))*AU60)/100),2)+ROUND(((ROUND((ROUND(((AE60-(EU60))*AV60*I60),2)*BS60),2)*AU60)/100),2)) -> 0 | AA60: 60258064 | AB60: =ROUND((AC60+AD60+AF60),6) -> 5710.18 | AC60: =ROUND((ES60),6) -> 5710.18 | AD60: =ROUND((((ET60)-(EU60))+AE60),6) -> 0 | AE60: =ROUND((EU60),6) -> 0 | AF60: =ROUND((EV60),6) -> 0 | AG60: =ROUND((AP60),6) -> 0 | AH60: =(EW60) -> 0 | AI60: =(EX60) -> 0 | AJ60: =(AS60) -> 0 | AK60: 5710.18 | AL60: 5710.18 | AM60: 0 | AN60: 0 | AO60: 0 | AP60: 0 | AQ60: 0 | AR60: 0 | AS60: 0 | AT60: 0 | AU60: 0 | AV60: 1 | AW60: 1 | AZ60: 1 | BA60: 1 | BB60: 1 | BC60: 1 | BH60: 3 | BI60: 3 | BM60: 746 | BN60: 0 | BP60: 0 | BQ60: 130 | BR60: 0 | BS60: 1 | BT60: 1 | BU60: 1 | BV60: 1 | BW60: 1 | BX60: 1 | BZ60: 0 | CA60: 0 | CE60: 1566 | CF60: 0 | CG60: 0 | CM60: 0 | CO60: 0 | CP60: =(P60+Q60+S60) -> 17130.54 | CQ60: =ROUND((ROUND((AC60*1),2)*BC60),2) -> 5710.18 | CR60: =(ROUND((ROUND(((ET60)*AV60*1),2)*BB60),2)+ROUND((ROUND(((AE60-(EU60))*AV60*1),2)*BS60),2)) -> 0 | CS60: =(ROUND((ROUND(((EU60)*AV60*1),2)*BS60),2)+ROUND((ROUND(((AE60-(EU60))*AV60*1),2)*BS60),2)) -> 0 | CT60: =ROUND((ROUND((AF60*AV60*1),2)*BA60),2) -> 0 | CU60: =AG60 -> 0 | CV60: =(AH60*AV60) -> 0 | CW60: =AI60 -> 0 | CX60: =AJ60 -> 0 | CY60: =(ROUND((((S60+ROUND((ROUND(((EU60)*AV60*1),2)*BS60),2))*AT60)/100),2)+ROUND(((ROUND((ROUND(((AE60-(EU60))*AV60*1),2)*BS60),2)*AT60)/100),2)) -> 0 | CZ60: =(ROUND((((S60+ROUND((ROUND(((EU60)*AV60*1),2)*BS60),2))*AU60)/100),2)+ROUND(((ROUND((ROUND(((AE60-(EU60))*AV60*1),2)*BS60),2)*AU60)/100),2)) -> 0 | DN60: 0 | DO60: 0 | DP60: 1 | DQ60: 1 | DU60: 1013 | DV60: ШТ | DW60: ШТ | DX60: 1 | EE60: 60088638 | EF60: 130 | EG60: Сметная стоимость оборудования | EH60: 0 | EJ60: 3 | EK60: 746 | EL60: ТСН-2001.13. Сметная стоимость оборудования | EM60: ТСН-2001.13 | EQ60: 0 | ER60: 0 | ES60: 5710.18 | ET60: 0 | EU60: 0 | EV60: 0 | EW60: 0 | EX60: 0 | EY60: 0 | FQ60: 0 | FR60: =P60 -> 17130.54 | FS60: 0 | FX60: 0 | FY60: 0 | GA60: [50 355 / 1,2 / 7,66] + 3% Трансп + 1,2% Заг.скл | GD60: 1 | GF60: 1629149040 | GG60: 2 | GH60: 4 | GI60: -2 | GJ60: 0 | GK60: 0 | GL60: =ROUND(IF(AND(BH60=3,BI60=3,FS60<>0),P60,0),2) -> 0 | GM60: =ROUND(O60+X60+Y60,2)+GX60 -> 17130.54 | GN60: =IF(OR(BI60=0,BI60=1),GM60-GX60,0) -> 0 | GO60: =IF(BI60=2,GM60-GX60,0) -> 0 | GP60: =IF(BI60=4,GM60-GX60,0) -> 0 | GR60: 0 | GS60: 2 | GT60: 0 | GV60: =ROUND((GT60),6) -> 0 | GW60: 1 | GX60: =ROUND(HC60*I60,2) -> 0 | HA60: 0 | HB60: 0 | HC60: =GV60*GW60 -> 0 | HE60: 3 | HF60: 1,2 | HS60: 0 | IK60: 0
A61: 17 | B61: 1 | E61: 17 | F61: КА-10 | G61: Грозозащита для локальной вычислительной сети, 16 GE RJ-45 SP-IP16/1000PR | H61: ШТ | I61: 3 | J61: 0 | K61: 3 | O61: =ROUND(CP61,2) -> 131219.94 | P61: =ROUND((ROUND((AC61*I61),2)*BC61),2) -> 131219.94 | Q61: =(ROUND((ROUND(((ET61)*AV61*I61),2)*BB61),2)+ROUND((ROUND(((AE61-(EU61))*AV61*I61),2)*BS61),2)) -> 0 | R61: =(ROUND((ROUND(((EU61)*AV61*I61),2)*BS61),2)+ROUND((ROUND(((AE61-(EU61))*AV61*I61),2)*BS61),2)) -> 0 | S61: =ROUND((ROUND((AF61*AV61*I61),2)*BA61),2) -> 0 | T61: =ROUND(CU61*I61,2) -> 0 | U61: =CV61*I61 -> 0 | V61: =CW61*I61 -> 0 | W61: =ROUND(CX61*I61,2) -> 0 | X61: =(ROUND((((S61+ROUND((ROUND(((EU61)*AV61*I61),2)*BS61),2))*AT61)/100),2)+ROUND(((ROUND((ROUND(((AE61-(EU61))*AV61*I61),2)*BS61),2)*AT61)/100),2)) -> 0 | Y61: =(ROUND((((S61+ROUND((ROUND(((EU61)*AV61*I61),2)*BS61),2))*AU61)/100),2)+ROUND(((ROUND((ROUND(((AE61-(EU61))*AV61*I61),2)*BS61),2)*AU61)/100),2)) -> 0 | AA61: 60258061 | AB61: =ROUND((AC61+AD61+AF61),6) -> 5710.18 | AC61: =ROUND((ES61),6) -> 5710.18 | AD61: =ROUND((((ET61)-(EU61))+AE61),6) -> 0 | AE61: =ROUND((EU61),6) -> 0 | AF61: =ROUND((EV61),6) -> 0 | AG61: =ROUND((AP61),6) -> 0 | AH61: =(EW61) -> 0 | AI61: =(EX61) -> 0 | AJ61: =(AS61) -> 0 | AK61: 5710.18 | AL61: 5710.18 | AM61: 0 | AN61: 0 | AO61: 0 | AP61: 0 | AQ61: 0 | AR61: 0 | AS61: 0 | AT61: 0 | AU61: 0 | AV61: 1 | AW61: 1 | AZ61: 1 | BA61: 1 | BB61: 1 | BC61: 7.66 | BH61: 3 | BI61: 3 | BM61: 746 | BN61: 0 | BP61: 0 | BQ61: 130 | BR61: 0 | BS61: 1 | BT61: 1 | BU61: 1 | BV61: 1 | BW61: 1 | BX61: 1 | BZ61: 0 | CA61: 0 | CE61: 1566 | CF61: 0 | CG61: 0 | CM61: 0 | CO61: 0 | CP61: =(P61+Q61+S61) -> 131219.94 | CQ61: =ROUND((ROUND((AC61*1),2)*BC61),2) -> 43739.98 | CR61: =(ROUND((ROUND(((ET61)*AV61*1),2)*BB61),2)+ROUND((ROUND(((AE61-(EU61))*AV61*1),2)*BS61),2)) -> 0 | CS61: =(ROUND((ROUND(((EU61)*AV61*1),2)*BS61),2)+ROUND((ROUND(((AE61-(EU61))*AV61*1),2)*BS61),2)) -> 0 | CT61: =ROUND((ROUND((AF61*AV61*1),2)*BA61),2) -> 0 | CU61: =AG61 -> 0 | CV61: =(AH61*AV61) -> 0 | CW61: =AI61 -> 0 | CX61: =AJ61 -> 0 | CY61: =(ROUND((((S61+ROUND((ROUND(((EU61)*AV61*1),2)*BS61),2))*AT61)/100),2)+ROUND(((ROUND((ROUND(((AE61-(EU61))*AV61*1),2)*BS61),2)*AT61)/100),2)) -> 0 | CZ61: =(ROUND((((S61+ROUND((ROUND(((EU61)*AV61*1),2)*BS61),2))*AU61)/100),2)+ROUND(((ROUND((ROUND(((AE61-(EU61))*AV61*1),2)*BS61),2)*AU61)/100),2)) -> 0 | DN61: 0 | DO61: 0 | DP61: 1 | DQ61: 1 | DU61: 1013 | DV61: ШТ | DW61: ШТ | DX61: 1 | EE61: 60088638 | EF61: 130 | EG61: Сметная стоимость оборудования | EH61: 0 | EJ61: 3 | EK61: 746 | EL61: ТСН-2001.13. Сметная стоимость оборудования | EM61: ТСН-2001.13 | EQ61: 0 | ER61: 0 | ES61: 5710.18 | ET61: 0 | EU61: 0 | EV61: 0 | EW61: 0 | EX61: 0 | EY61: 0 | EZ61: 5 | FC61: 1 | FD61: 18 | FF61: 50355 | FQ61: 0 | FR61: =P61 -> 131219.94 | FS61: 0 | FX61: 0 | FY61: 0 | GA61: [50 355 / 1,2 / 7,66] + 3% Трансп + 1,2% Заг.скл | GD61: 1 | GF61: 1629149040 | GG61: 2 | GH61: 3 | GI61: 5 | GJ61: 0 | GK61: 0 | GL61: =ROUND(IF(AND(BH61=3,BI61=3,FS61<>0),P61,0),2) -> 0 | GM61: =ROUND(O61+X61+Y61,2)+GX61 -> 131219.94 | GN61: =IF(OR(BI61=0,BI61=1),GM61-GX61,0) -> 0 | GO61: =IF(BI61=2,GM61-GX61,0) -> 0 | GP61: =IF(BI61=4,GM61-GX61,0) -> 0 | GR61: 1 | GS61: 1 | GT61: 0 | GV61: =ROUND((GT61),6) -> 0 | GW61: 1 | GX61: =ROUND(HC61*I61,2) -> 0 | HA61: 0 | HB61: 0 | HC61: =GV61*GW61 -> 0 | HE61: 3 | HF61: 1,2 | HS61: 0 | IK61: 0
A62: 17 | B62: 1 | C62: =ROW(SmtRes!A57) -> 57 | D62: =ROW(EtalonRes!A72) -> 72 | E62: 18 | F62: 4.10-75-9 | G62: Монтаж аппаратуры настенной | H62: 1 ШТ. | I62: 4 | J62: 0 | K62: 4 | O62: =ROUND(CP62,2) -> 508.43 | P62: =ROUND((ROUND((AC62*AW62*I62),2)*BC62),2) -> 96.4 | Q62: =(ROUND((ROUND((((ET62*1.1))*AV62*I62),2)*BB62),2)+ROUND((ROUND(((AE62-((EU62*1.1)))*AV62*I62),2)*BS62),2)) -> 0 | R62: =(ROUND((ROUND((((EU62*1.1))*AV62*I62),2)*BS62),2)+ROUND((ROUND(((AE62-((EU62*1.1)))*AV62*I62),2)*BS62),2)) -> 0 | S62: =ROUND((ROUND((AF62*AV62*I62),2)*BA62),2) -> 412.03 | T62: =ROUND(CU62*I62,2) -> 0 | U62: =CV62*I62 -> 36.8544 | V62: =CW62*I62 -> 0 | W62: =ROUND(CX62*I62,2) -> 0 | X62: =(ROUND((((S62+ROUND((ROUND((((EU62*1.1))*AV62*I62),2)*BS62),2))*AT62)/100),2)+ROUND(((ROUND((ROUND(((AE62-((EU62*1.1)))*AV62*I62),2)*BS62),2)*AT62)/100),2)) -> 391.43 | Y62: =(ROUND((((S62+ROUND((ROUND((((EU62*1.1))*AV62*I62),2)*BS62),2))*AU62)/100),2)+ROUND(((ROUND((ROUND(((AE62-((EU62*1.1)))*AV62*I62),2)*BS62),2)*AU62)/100),2)) -> 218.38 | AA62: 60258064 | AB62: =ROUND((AC62+AD62+AF62),6) -> 122.484 | AC62: =ROUND((ES62),6) -> 24.1 | AD62: =ROUND(((((ET62*1.1))-((EU62*1.1)))+AE62),6) -> 0 | AE62: =ROUND(((EU62*1.1)),6) -> 0 | AF62: =ROUND(((EV62*1.1)),6) -> 98.384 | AG62: =ROUND((AP62),6) -> 0 | AH62: =((EW62*1.1)) -> 8.8 | AI62: =((EX62*1.1)) -> 0 | AJ62: =(AS62) -> 0 | AK62: 113.54 | AL62: 24.1 | AM62: 0 | AN62: 0 | AO62: 89.44 | AP62: 0 | AQ62: 8 | AR62: 0 | AS62: 0 | AT62: 95 | AU62: 53 | AV62: 1.047 | AW62: 1 | AZ62: 1 | BA62: 1 | BB62: 1 | BC62: 1 | BH62: 0 | BI62: 2 | BJ62: ТСН-2001.4 Доп. 80, Сб. 10, т. 75, поз. 9 | BM62: 69 | BN62: 58973116 | BO62: 4.10-75-9 | BP62: 1 | BQ62: 40 | BR62: 0 | BS62: 1 | BT62: 1 | BU62: 1 | BV62: 1 | BW62: 1 | BX62: 1 | BZ62: 95 | CA62: 53 | CE62: 1566 | CF62: 0 | CG62: 0 | CM62: 0 | CN62: Поправка: О.П. п.3.4.30.в Наименование: При применении территориальных сметных нормативов для города Москвы затраты, учитывающие напряженные и стесненные условия производства работ (стесненность, сложность складирования и транспортной логистики и т.п.), исчисляются с применением коэффициентов к затратам труда и заработной плате рабочих, машинистов, времени эксплуатации машин и механизмов, стоимости эксплуатации машин в размере: для объектов, расположенных за пределами Третьего транспортного кольца города Москвы, но в пределах Московской кольцевой автомобильной дороги | CO62: 0 | CP62: =(P62+Q62+S62) -> 508.43 | CQ62: =ROUND((ROUND((AC62*AW62*1),2)*BC62),2) -> 24.1 | CR62: =(ROUND((ROUND((((ET62*1.1))*AV62*1),2)*BB62),2)+ROUND((ROUND(((AE62-((EU62*1.1)))*AV62*1),2)*BS62),2)) -> 0 | CS62: =(ROUND((ROUND((((EU62*1.1))*AV62*1),2)*BS62),2)+ROUND((ROUND(((AE62-((EU62*1.1)))*AV62*1),2)*BS62),2)) -> 0 | CT62: =ROUND((ROUND((AF62*AV62*1),2)*BA62),2) -> 103.01 | CU62: =AG62 -> 0 | CV62: =(AH62*AV62) -> 9.2136 | CW62: =AI62 -> 0 | CX62: =AJ62 -> 0 | CY62: =(ROUND((((S62+ROUND((ROUND((((EU62*1.1))*AV62*1),2)*BS62),2))*AT62)/100),2)+ROUND(((ROUND((ROUND(((AE62-((EU62*1.1)))*AV62*1),2)*BS62),2)*AT62)/100),2)) -> 391.43 | CZ62: =(ROUND((((S62+ROUND((ROUND((((EU62*1.1))*AV62*1),2)*BS62),2))*AU62)/100),2)+ROUND(((ROUND((ROUND(((AE62-((EU62*1.1)))*AV62*1),2)*BS62),2)*AU62)/100),2)) -> 218.38 | DB62: 15 | DE62: *1,1 | DF62: *1,1 | DG62: *1,1 | DI62: *1,1 | DJ62: *1,1 | DN62: 0 | DO62: 0 | DP62: 1 | DQ62: 1 | DU62: 1013 | DV62: 1 ШТ. | DW62: 1 ШТ. | DX62: 1 | EE62: 60088533 | EF62: 40 | EG62: Монтаж оборудования | EH62: 0 | EJ62: 2 | EK62: 69 | EL62: ТСН-2001.4-10. Монтаж радиотелевизионного и электронного оборудования | EM62: ТСН-2001.4-10-2 | EO62: Поправка: О.П. п.3.4.30.в | EQ62: 0 | ER62: 113.54 | ES62: 24.1 | ET62: 0 | EU62: 0 | EV62: 89.44 | EW62: 8 | EX62: 0 | EY62: 0 | FQ62: 0 | FR62: 0 | FS62: 0 | FX62: 95 | FY62: 53 | GD62: 1 | GF62: -1490315940 | GG62: 2 | GH62: 1 | GI62: 2 | GJ62: 0 | GK62: 0 | GL62: =ROUND(IF(AND(BH62=3,BI62=3,FS62<>0),P62,0),2) -> 0 | GM62: =ROUND(O62+X62+Y62,2)+GX62 -> 1118.24 | GN62: =IF(OR(BI62=0,BI62=1),GM62-GX62,0) -> 0 | GO62: =IF(BI62=2,GM62-GX62,0) -> 1118.24 | GP62: =IF(BI62=4,GM62-GX62,0) -> 0 | GR62: 0 | GS62: 3 | GT62: 0 | GV62: =ROUND((GT62),6) -> 0 | GW62: 1 | GX62: =ROUND(HC62*I62,2) -> 0 | HA62: 0 | HB62: 0 | HC62: =GV62*GW62 -> 0 | HS62: 0 | IK62: 0
A63: 17 | B63: 1 | C63: =ROW(SmtRes!A62) -> 62 | D63: =ROW(EtalonRes!A78) -> 78 | E63: 18 | F63: 4.10-75-9 | G63: Монтаж аппаратуры настенной | H63: 1 ШТ. | I63: 4 | J63: 0 | K63: 4 | O63: =ROUND(CP63,2) -> 23434.51 | P63: =ROUND((ROUND((AC63*AW63*I63),2)*BC63),2) -> 776.98 | Q63: =(ROUND((ROUND((((ET63*1.1))*AV63*I63),2)*BB63),2)+ROUND((ROUND(((AE63-((EU63*1.1)))*AV63*I63),2)*BS63),2)) -> 0 | R63: =(ROUND((ROUND((((EU63*1.1))*AV63*I63),2)*BS63),2)+ROUND((ROUND(((AE63-((EU63*1.1)))*AV63*I63),2)*BS63),2)) -> 0 | S63: =ROUND((ROUND((AF63*AV63*I63),2)*BA63),2) -> 22657.53 | T63: =ROUND(CU63*I63,2) -> 0 | U63: =CV63*I63 -> 36.8544 | V63: =CW63*I63 -> 0 | W63: =ROUND(CX63*I63,2) -> 0 | X63: =(ROUND((((S63+ROUND((ROUND((((EU63*1.1))*AV63*I63),2)*BS63),2))*AT63)/100),2)+ROUND(((ROUND((ROUND(((AE63-((EU63*1.1)))*AV63*I63),2)*BS63),2)*AT63)/100),2)) -> 21524.65 | Y63: =(ROUND((((S63+ROUND((ROUND((((EU63*1.1))*AV63*I63),2)*BS63),2))*AU63)/100),2)+ROUND(((ROUND((ROUND(((AE63-((EU63*1.1)))*AV63*I63),2)*BS63),2)*AU63)/100),2)) -> 12008.49 | AA63: 60258061 | AB63: =ROUND((AC63+AD63+AF63),6) -> 122.484 | AC63: =ROUND((ES63),6) -> 24.1 | AD63: =ROUND(((((ET63*1.1))-((EU63*1.1)))+AE63),6) -> 0 | AE63: =ROUND(((EU63*1.1)),6) -> 0 | AF63: =ROUND(((EV63*1.1)),6) -> 98.384 | AG63: =ROUND((AP63),6) -> 0 | AH63: =((EW63*1.1)) -> 8.8 | AI63: =((EX63*1.1)) -> 0 | AJ63: =(AS63) -> 0 | AK63: 113.54 | AL63: 24.1 | AM63: 0 | AN63: 0 | AO63: 89.44 | AP63: 0 | AQ63: 8 | AR63: 0 | AS63: 0 | AT63: 95 | AU63: 53 | AV63: 1.047 | AW63: 1 | AZ63: 1 | BA63: 54.99 | BB63: 1 | BC63: 8.06 | BH63: 0 | BI63: 2 | BJ63: ТСН-2001.4 Доп. 80, Сб. 10, т. 75, поз. 9 | BM63: 69 | BN63: 58973116 | BO63: 4.10-75-9 | BP63: 1 | BQ63: 40 | BR63: 0 | BS63: 54.99 | BT63: 1 | BU63: 1 | BV63: 1 | BW63: 1 | BX63: 1 | BZ63: 95 | CA63: 53 | CE63: 1566 | CF63: 0 | CG63: 0 | CM63: 0 | CN63: Поправка: О.П. п.3.4.30.в Наименование: При применении территориальных сметных нормативов для города Москвы затраты, учитывающие напряженные и стесненные условия производства работ (стесненность, сложность складирования и транспортной логистики и т.п.), исчисляются с применением коэффициентов к затратам труда и заработной плате рабочих, машинистов, времени эксплуатации машин и механизмов, стоимости эксплуатации машин в размере: для объектов, расположенных за пределами Третьего транспортного кольца города Москвы, но в пределах Московской кольцевой автомобильной дороги | CO63: 0 | CP63: =(P63+Q63+S63) -> 23434.51 | CQ63: =ROUND((ROUND((AC63*AW63*1),2)*BC63),2) -> 194.25 | CR63: =(ROUND((ROUND((((ET63*1.1))*AV63*1),2)*BB63),2)+ROUND((ROUND(((AE63-((EU63*1.1)))*AV63*1),2)*BS63),2)) -> 0 | CS63: =(ROUND((ROUND((((EU63*1.1))*AV63*1),2)*BS63),2)+ROUND((ROUND(((AE63-((EU63*1.1)))*AV63*1),2)*BS63),2)) -> 0 | CT63: =ROUND((ROUND((AF63*AV63*1),2)*BA63),2) -> 5664.52 | CU63: =AG63 -> 0 | CV63: =(AH63*AV63) -> 9.2136 | CW63: =AI63 -> 0 | CX63: =AJ63 -> 0 | CY63: =(ROUND((((S63+ROUND((ROUND((((EU63*1.1))*AV63*1),2)*BS63),2))*AT63)/100),2)+ROUND(((ROUND((ROUND(((AE63-((EU63*1.1)))*AV63*1),2)*BS63),2)*AT63)/100),2)) -> 21524.65 | CZ63: =(ROUND((((S63+ROUND((ROUND((((EU63*1.1))*AV63*1),2)*BS63),2))*AU63)/100),2)+ROUND(((ROUND((ROUND(((AE63-((EU63*1.1)))*AV63*1),2)*BS63),2)*AU63)/100),2)) -> 12008.49 | DB63: 16 | DE63: *1,1 | DF63: *1,1 | DG63: *1,1 | DI63: *1,1 | DJ63: *1,1 | DN63: 0 | DO63: 0 | DP63: 1 | DQ63: 1 | DU63: 1013 | DV63: 1 ШТ. | DW63: 1 ШТ. | DX63: 1 | EE63: 60088533 | EF63: 40 | EG63: Монтаж оборудования | EH63: 0 | EJ63: 2 | EK63: 69 | EL63: ТСН-2001.4-10. Монтаж радиотелевизионного и электронного оборудования | EM63: ТСН-2001.4-10-2 | EO63: Поправка: О.П. п.3.4.30.в | EQ63: 0 | ER63: 113.54 | ES63: 24.1 | ET63: 0 | EU63: 0 | EV63: 89.44 | EW63: 8 | EX63: 0 | EY63: 0 | FQ63: 0 | FR63: 0 | FS63: 0 | FX63: 95 | FY63: 53 | GD63: 1 | GF63: -1490315940 | GG63: 2 | GH63: 1 | GI63: 2 | GJ63: 0 | GK63: 0 | GL63: =ROUND(IF(AND(BH63=3,BI63=3,FS63<>0),P63,0),2) -> 0 | GM63: =ROUND(O63+X63+Y63,2)+GX63 -> 56967.65 | GN63: =IF(OR(BI63=0,BI63=1),GM63-GX63,0) -> 0 | GO63: =IF(BI63=2,GM63-GX63,0) -> 56967.65 | GP63: =IF(BI63=4,GM63-GX63,0) -> 0 | GR63: 0 | GS63: 3 | GT63: 0 | GV63: =ROUND((GT63),6) -> 0 | GW63: 1 | GX63: =ROUND(HC63*I63,2) -> 0 | HA63: 0 | HB63: 0 | HC63: =GV63*GW63 -> 0 | HS63: 0 | IK63: 0
A64: 17 | B64: 1 | E64: 19 | F64: КА-11 | G64: Кронштейн настенного крепления RDW 2701K | H64: ШТ | I64: 4 | J64: 0 | K64: 4 | O64: =ROUND(CP64,2) -> 481.76 | P64: =ROUND((ROUND((AC64*AW64*I64),2)*BC64),2) -> 481.76 | Q64: =(ROUND((ROUND(((ET64)*AV64*I64),2)*BB64),2)+ROUND((ROUND(((AE64-(EU64))*AV64*I64),2)*BS64),2)) -> 0 | R64: =(ROUND((ROUND(((EU64)*AV64*I64),2)*BS64),2)+ROUND((ROUND(((AE64-(EU64))*AV64*I64),2)*BS64),2)) -> 0 | S64: =ROUND((ROUND((AF64*AV64*I64),2)*BA64),2) -> 0 | T64: =ROUND(CU64*I64,2) -> 0 | U64: =CV64*I64 -> 0 | V64: =CW64*I64 -> 0 | W64: =ROUND(CX64*I64,2) -> 0 | X64: =(ROUND((((S64+ROUND((ROUND(((EU64)*AV64*I64),2)*BS64),2))*AT64)/100),2)+ROUND(((ROUND((ROUND(((AE64-(EU64))*AV64*I64),2)*BS64),2)*AT64)/100),2)) -> 0 | Y64: =(ROUND((((S64+ROUND((ROUND(((EU64)*AV64*I64),2)*BS64),2))*AU64)/100),2)+ROUND(((ROUND((ROUND(((AE64-(EU64))*AV64*I64),2)*BS64),2)*AU64)/100),2)) -> 0 | AA64: 60258064 | AB64: =ROUND((AC64+AD64+AF64),6) -> 120.44 | AC64: =ROUND((ES64),6) -> 120.44 | AD64: =ROUND((((ET64)-(EU64))+AE64),6) -> 0 | AE64: =ROUND((EU64),6) -> 0 | AF64: =ROUND((EV64),6) -> 0 | AG64: =ROUND((AP64),6) -> 0 | AH64: =(EW64) -> 0 | AI64: =(EX64) -> 0 | AJ64: =(AS64) -> 0 | AK64: 120.44 | AL64: 120.44 | AM64: 0 | AN64: 0 | AO64: 0 | AP64: 0 | AQ64: 0 | AR64: 0 | AS64: 0 | AT64: 0 | AU64: 0 | AV64: 1 | AW64: 1 | AZ64: 1 | BA64: 1 | BB64: 1 | BC64: 1 | BH64: 3 | BI64: 2 | BM64: 400002 | BN64: 0 | BP64: 0 | BQ64: 202 | BR64: 0 | BS64: 1 | BT64: 1 | BU64: 1 | BV64: 1 | BW64: 1 | BX64: 1 | BZ64: 0 | CA64: 0 | CE64: 1566 | CF64: 0 | CG64: 0 | CM64: 0 | CO64: 0 | CP64: =(P64+Q64+S64) -> 481.76 | CQ64: =ROUND((ROUND((AC64*AW64*1),2)*BC64),2) -> 120.44 | CR64: =(ROUND((ROUND(((ET64)*AV64*1),2)*BB64),2)+ROUND((ROUND(((AE64-(EU64))*AV64*1),2)*BS64),2)) -> 0 | CS64: =(ROUND((ROUND(((EU64)*AV64*1),2)*BS64),2)+ROUND((ROUND(((AE64-(EU64))*AV64*1),2)*BS64),2)) -> 0 | CT64: =ROUND((ROUND((AF64*AV64*1),2)*BA64),2) -> 0 | CU64: =AG64 -> 0 | CV64: =(AH64*AV64) -> 0 | CW64: =AI64 -> 0 | CX64: =AJ64 -> 0 | CY64: =(ROUND((((S64+ROUND((ROUND(((EU64)*AV64*1),2)*BS64),2))*AT64)/100),2)+ROUND(((ROUND((ROUND(((AE64-(EU64))*AV64*1),2)*BS64),2)*AT64)/100),2)) -> 0 | CZ64: =(ROUND((((S64+ROUND((ROUND(((EU64)*AV64*1),2)*BS64),2))*AU64)/100),2)+ROUND(((ROUND((ROUND(((AE64-(EU64))*AV64*1),2)*BS64),2)*AU64)/100),2)) -> 0 | DN64: 0 | DO64: 0 | DP64: 1 | DQ64: 1 | DU64: 1013 | DV64: ШТ | DW64: ШТ | DX64: 1 | EE64: 60088644 | EF64: 202 | EG64: Материалы | EH64: 0 | EJ64: 1 | EK64: 400002 | EL64: Материалы, изделия и конструкции | EM64: Материалы | EQ64: 0 | ER64: 0 | ES64: 120.44 | ET64: 0 | EU64: 0 | EV64: 0 | EW64: 0 | EX64: 0 | EY64: 0 | FQ64: 0 | FR64: 0 | FS64: 0 | FX64: 0 | FY64: 0 | GA64: [1 400 / 1,2 / 9,88] + 2% Заг.скл | GD64: 1 | GF64: -778550206 | GG64: 2 | GH64: 4 | GI64: -2 | GJ64: 0 | GK64: 0 | GL64: =ROUND(IF(AND(BH64=3,BI64=3,FS64<>0),P64,0),2) -> 0 | GM64: =ROUND(O64+X64+Y64,2)+GX64 -> 481.76 | GN64: =IF(OR(BI64=0,BI64=1),GM64-GX64,0) -> 0 | GO64: =IF(BI64=2,GM64-GX64,0) -> 481.76 | GP64: =IF(BI64=4,GM64-GX64,0) -> 0 | GR64: 0 | GS64: 2 | GT64: 0 | GV64: =ROUND((GT64),6) -> 0 | GW64: 1 | GX64: =ROUND(HC64*I64,2) -> 0 | HA64: 0 | HB64: 0 | HC64: =GV64*GW64 -> 0 | HE64: 0 | HF64: 2 | HS64: 0 | IK64: 0
A65: 17 | B65: 1 | E65: 19 | F65: КА-11 | G65: Кронштейн настенного крепления RDW 2701K | H65: ШТ | I65: 4 | J65: 0 | K65: 4 | O65: =ROUND(CP65,2) -> 4759.79 | P65: =ROUND((ROUND((AC65*AW65*I65),2)*BC65),2) -> 4759.79 | Q65: =(ROUND((ROUND(((ET65)*AV65*I65),2)*BB65),2)+ROUND((ROUND(((AE65-(EU65))*AV65*I65),2)*BS65),2)) -> 0 | R65: =(ROUND((ROUND(((EU65)*AV65*I65),2)*BS65),2)+ROUND((ROUND(((AE65-(EU65))*AV65*I65),2)*BS65),2)) -> 0 | S65: =ROUND((ROUND((AF65*AV65*I65),2)*BA65),2) -> 0 | T65: =ROUND(CU65*I65,2) -> 0 | U65: =CV65*I65 -> 0 | V65: =CW65*I65 -> 0 | W65: =ROUND(CX65*I65,2) -> 0 | X65: =(ROUND((((S65+ROUND((ROUND(((EU65)*AV65*I65),2)*BS65),2))*AT65)/100),2)+ROUND(((ROUND((ROUND(((AE65-(EU65))*AV65*I65),2)*BS65),2)*AT65)/100),2)) -> 0 | Y65: =(ROUND((((S65+ROUND((ROUND(((EU65)*AV65*I65),2)*BS65),2))*AU65)/100),2)+ROUND(((ROUND((ROUND(((AE65-(EU65))*AV65*I65),2)*BS65),2)*AU65)/100),2)) -> 0 | AA65: 60258061 | AB65: =ROUND((AC65+AD65+AF65),6) -> 120.44 | AC65: =ROUND((ES65),6) -> 120.44 | AD65: =ROUND((((ET65)-(EU65))+AE65),6) -> 0 | AE65: =ROUND((EU65),6) -> 0 | AF65: =ROUND((EV65),6) -> 0 | AG65: =ROUND((AP65),6) -> 0 | AH65: =(EW65) -> 0 | AI65: =(EX65) -> 0 | AJ65: =(AS65) -> 0 | AK65: 120.44 | AL65: 120.44 | AM65: 0 | AN65: 0 | AO65: 0 | AP65: 0 | AQ65: 0 | AR65: 0 | AS65: 0 | AT65: 0 | AU65: 0 | AV65: 1 | AW65: 1 | AZ65: 1 | BA65: 1 | BB65: 1 | BC65: 9.88 | BH65: 3 | BI65: 2 | BM65: 400002 | BN65: 0 | BP65: 0 | BQ65: 202 | BR65: 0 | BS65: 1 | BT65: 1 | BU65: 1 | BV65: 1 | BW65: 1 | BX65: 1 | BZ65: 0 | CA65: 0 | CE65: 1566 | CF65: 0 | CG65: 0 | CM65: 0 | CO65: 0 | CP65: =(P65+Q65+S65) -> 4759.79 | CQ65: =ROUND((ROUND((AC65*AW65*1),2)*BC65),2) -> 1189.95 | CR65: =(ROUND((ROUND(((ET65)*AV65*1),2)*BB65),2)+ROUND((ROUND(((AE65-(EU65))*AV65*1),2)*BS65),2)) -> 0 | CS65: =(ROUND((ROUND(((EU65)*AV65*1),2)*BS65),2)+ROUND((ROUND(((AE65-(EU65))*AV65*1),2)*BS65),2)) -> 0 | CT65: =ROUND((ROUND((AF65*AV65*1),2)*BA65),2) -> 0 | CU65: =AG65 -> 0 | CV65: =(AH65*AV65) -> 0 | CW65: =AI65 -> 0 | CX65: =AJ65 -> 0 | CY65: =(ROUND((((S65+ROUND((ROUND(((EU65)*AV65*1),2)*BS65),2))*AT65)/100),2)+ROUND(((ROUND((ROUND(((AE65-(EU65))*AV65*1),2)*BS65),2)*AT65)/100),2)) -> 0 | CZ65: =(ROUND((((S65+ROUND((ROUND(((EU65)*AV65*1),2)*BS65),2))*AU65)/100),2)+ROUND(((ROUND((ROUND(((AE65-(EU65))*AV65*1),2)*BS65),2)*AU65)/100),2)) -> 0 | DN65: 0 | DO65: 0 | DP65: 1 | DQ65: 1 | DU65: 1013 | DV65: ШТ | DW65: ШТ | DX65: 1 | EE65: 60088644 | EF65: 202 | EG65: Материалы | EH65: 0 | EJ65: 1 | EK65: 400002 | EL65: Материалы, изделия и конструкции | EM65: Материалы | EQ65: 0 | ER65: 0 | ES65: 120.44 | ET65: 0 | EU65: 0 | EV65: 0 | EW65: 0 | EX65: 0 | EY65: 0 | EZ65: 5 | FC65: 1 | FD65: 18 | FF65: 1400 | FQ65: 0 | FR65: 0 | FS65: 0 | FX65: 0 | FY65: 0 | GA65: [1 400 / 1,2 / 9,88] + 2% Заг.скл | GD65: 1 | GF65: -778550206 | GG65: 2 | GH65: 3 | GI65: 5 | GJ65: 0 | GK65: 0 | GL65: =ROUND(IF(AND(BH65=3,BI65=3,FS65<>0),P65,0),2) -> 0 | GM65: =ROUND(O65+X65+Y65,2)+GX65 -> 4759.79 | GN65: =IF(OR(BI65=0,BI65=1),GM65-GX65,0) -> 0 | GO65: =IF(BI65=2,GM65-GX65,0) -> 4759.79 | GP65: =IF(BI65=4,GM65-GX65,0) -> 0 | GR65: 1 | GS65: 1 | GT65: 0 | GV65: =ROUND((GT65),6) -> 0 | GW65: 1 | GX65: =ROUND(HC65*I65,2) -> 0 | HA65: 0 | HB65: 0 | HC65: =GV65*GW65 -> 0 | HE65: 0 | HF65: 2 | HS65: 0 | IK65: 0
A66: 17 | B66: 1 | E66: 20 | F66: КА-12 | G66: Монитор RDW 2701K | H66: ШТ | I66: 4 | J66: 0 | K66: 4 | O66: =ROUND(CP66,2) -> 9684.24 | P66: =ROUND((ROUND((AC66*I66),2)*BC66),2) -> 9684.24 | Q66: =(ROUND((ROUND(((ET66)*AV66*I66),2)*BB66),2)+ROUND((ROUND(((AE66-(EU66))*AV66*I66),2)*BS66),2)) -> 0 | R66: =(ROUND((ROUND(((EU66)*AV66*I66),2)*BS66),2)+ROUND((ROUND(((AE66-(EU66))*AV66*I66),2)*BS66),2)) -> 0 | S66: =ROUND((ROUND((AF66*AV66*I66),2)*BA66),2) -> 0 | T66: =ROUND(CU66*I66,2) -> 0 | U66: =CV66*I66 -> 0 | V66: =CW66*I66 -> 0 | W66: =ROUND(CX66*I66,2) -> 0 | X66: =(ROUND((((S66+ROUND((ROUND(((EU66)*AV66*I66),2)*BS66),2))*AT66)/100),2)+ROUND(((ROUND((ROUND(((AE66-(EU66))*AV66*I66),2)*BS66),2)*AT66)/100),2)) -> 0 | Y66: =(ROUND((((S66+ROUND((ROUND(((EU66)*AV66*I66),2)*BS66),2))*AU66)/100),2)+ROUND(((ROUND((ROUND(((AE66-(EU66))*AV66*I66),2)*BS66),2)*AU66)/100),2)) -> 0 | AA66: 60258064 | AB66: =ROUND((AC66+AD66+AF66),6) -> 2421.06 | AC66: =ROUND((ES66),6) -> 2421.06 | AD66: =ROUND((((ET66)-(EU66))+AE66),6) -> 0 | AE66: =ROUND((EU66),6) -> 0 | AF66: =ROUND((EV66),6) -> 0 | AG66: =ROUND((AP66),6) -> 0 | AH66: =(EW66) -> 0 | AI66: =(EX66) -> 0 | AJ66: =(AS66) -> 0 | AK66: 2421.06 | AL66: 2421.06 | AM66: 0 | AN66: 0 | AO66: 0 | AP66: 0 | AQ66: 0 | AR66: 0 | AS66: 0 | AT66: 0 | AU66: 0 | AV66: 1 | AW66: 1 | AZ66: 1 | BA66: 1 | BB66: 1 | BC66: 1 | BH66: 3 | BI66: 3 | BM66: 746 | BN66: 0 | BP66: 0 | BQ66: 130 | BR66: 0 | BS66: 1 | BT66: 1 | BU66: 1 | BV66: 1 | BW66: 1 | BX66: 1 | BZ66: 0 | CA66: 0 | CE66: 1566 | CF66: 0 | CG66: 0 | CM66: 0 | CO66: 0 | CP66: =(P66+Q66+S66) -> 9684.24 | CQ66: =ROUND((ROUND((AC66*1),2)*BC66),2) -> 2421.06 | CR66: =(ROUND((ROUND(((ET66)*AV66*1),2)*BB66),2)+ROUND((ROUND(((AE66-(EU66))*AV66*1),2)*BS66),2)) -> 0 | CS66: =(ROUND((ROUND(((EU66)*AV66*1),2)*BS66),2)+ROUND((ROUND(((AE66-(EU66))*AV66*1),2)*BS66),2)) -> 0 | CT66: =ROUND((ROUND((AF66*AV66*1),2)*BA66),2) -> 0 | CU66: =AG66 -> 0 | CV66: =(AH66*AV66) -> 0 | CW66: =AI66 -> 0 | CX66: =AJ66 -> 0 | CY66: =(ROUND((((S66+ROUND((ROUND(((EU66)*AV66*1),2)*BS66),2))*AT66)/100),2)+ROUND(((ROUND((ROUND(((AE66-(EU66))*AV66*1),2)*BS66),2)*AT66)/100),2)) -> 0 | CZ66: =(ROUND((((S66+ROUND((ROUND(((EU66)*AV66*1),2)*BS66),2))*AU66)/100),2)+ROUND(((ROUND((ROUND(((AE66-(EU66))*AV66*1),2)*BS66),2)*AU66)/100),2)) -> 0 | DN66: 0 | DO66: 0 | DP66: 1 | DQ66: 1 | DU66: 1013 | DV66: ШТ | DW66: ШТ | DX66: 1 | EE66: 60088638 | EF66: 130 | EG66: Сметная стоимость оборудования | EH66: 0 | EJ66: 3 | EK66: 746 | EL66: ТСН-2001.13. Сметная стоимость оборудования | EM66: ТСН-2001.13 | EQ66: 0 | ER66: 0 | ES66: 2421.06 | ET66: 0 | EU66: 0 | EV66: 0 | EW66: 0 | EX66: 0 | EY66: 0 | FQ66: 0 | FR66: =P66 -> 9684.24 | FS66: 0 | FX66: 0 | FY66: 0 | GA66: [21 350 / 1,2 / 7,66] + 3% Трансп + 1,2% Заг.скл | GD66: 1 | GF66: -790680475 | GG66: 2 | GH66: 4 | GI66: -2 | GJ66: 0 | GK66: 0 | GL66: =ROUND(IF(AND(BH66=3,BI66=3,FS66<>0),P66,0),2) -> 0 | GM66: =ROUND(O66+X66+Y66,2)+GX66 -> 9684.24 | GN66: =IF(OR(BI66=0,BI66=1),GM66-GX66,0) -> 0 | GO66: =IF(BI66=2,GM66-GX66,0) -> 0 | GP66: =IF(BI66=4,GM66-GX66,0) -> 0 | GR66: 0 | GS66: 2 | GT66: 0 | GV66: =ROUND((GT66),6) -> 0 | GW66: 1 | GX66: =ROUND(HC66*I66,2) -> 0 | HA66: 0 | HB66: 0 | HC66: =GV66*GW66 -> 0 | HE66: 3 | HF66: 1,2 | HS66: 0 | IK66: 0
A67: 17 | B67: 1 | E67: 20 | F67: КА-12 | G67: Монитор RDW 2701K | H67: ШТ | I67: 4 | J67: 0 | K67: 4 | O67: =ROUND(CP67,2) -> 74181.28 | P67: =ROUND((ROUND((AC67*I67),2)*BC67),2) -> 74181.28 | Q67: =(ROUND((ROUND(((ET67)*AV67*I67),2)*BB67),2)+ROUND((ROUND(((AE67-(EU67))*AV67*I67),2)*BS67),2)) -> 0 | R67: =(ROUND((ROUND(((EU67)*AV67*I67),2)*BS67),2)+ROUND((ROUND(((AE67-(EU67))*AV67*I67),2)*BS67),2)) -> 0 | S67: =ROUND((ROUND((AF67*AV67*I67),2)*BA67),2) -> 0 | T67: =ROUND(CU67*I67,2) -> 0 | U67: =CV67*I67 -> 0 | V67: =CW67*I67 -> 0 | W67: =ROUND(CX67*I67,2) -> 0 | X67: =(ROUND((((S67+ROUND((ROUND(((EU67)*AV67*I67),2)*BS67),2))*AT67)/100),2)+ROUND(((ROUND((ROUND(((AE67-(EU67))*AV67*I67),2)*BS67),2)*AT67)/100),2)) -> 0 | Y67: =(ROUND((((S67+ROUND((ROUND(((EU67)*AV67*I67),2)*BS67),2))*AU67)/100),2)+ROUND(((ROUND((ROUND(((AE67-(EU67))*AV67*I67),2)*BS67),2)*AU67)/100),2)) -> 0 | AA67: 60258061 | AB67: =ROUND((AC67+AD67+AF67),6) -> 2421.06 | AC67: =ROUND((ES67),6) -> 2421.06 | AD67: =ROUND((((ET67)-(EU67))+AE67),6) -> 0 | AE67: =ROUND((EU67),6) -> 0 | AF67: =ROUND((EV67),6) -> 0 | AG67: =ROUND((AP67),6) -> 0 | AH67: =(EW67) -> 0 | AI67: =(EX67) -> 0 | AJ67: =(AS67) -> 0 | AK67: 2421.06 | AL67: 2421.06 | AM67: 0 | AN67: 0 | AO67: 0 | AP67: 0 | AQ67: 0 | AR67: 0 | AS67: 0 | AT67: 0 | AU67: 0 | AV67: 1 | AW67: 1 | AZ67: 1 | BA67: 1 | BB67: 1 | BC67: 7.66 | BH67: 3 | BI67: 3 | BM67: 746 | BN67: 0 | BP67: 0 | BQ67: 130 | BR67: 0 | BS67: 1 | BT67: 1 | BU67: 1 | BV67: 1 | BW67: 1 | BX67: 1 | BZ67: 0 | CA67: 0 | CE67: 1566 | CF67: 0 | CG67: 0 | CM67: 0 | CO67: 0 | CP67: =(P67+Q67+S67) -> 74181.28 | CQ67: =ROUND((ROUND((AC67*1),2)*BC67),2) -> 18545.32 | CR67: =(ROUND((ROUND(((ET67)*AV67*1),2)*BB67),2)+ROUND((ROUND(((AE67-(EU67))*AV67*1),2)*BS67),2)) -> 0 | CS67: =(ROUND((ROUND(((EU67)*AV67*1),2)*BS67),2)+ROUND((ROUND(((AE67-(EU67))*AV67*1),2)*BS67),2)) -> 0 | CT67: =ROUND((ROUND((AF67*AV67*1),2)*BA67),2) -> 0 | CU67: =AG67 -> 0 | CV67: =(AH67*AV67) -> 0 | CW67: =AI67 -> 0 | CX67: =AJ67 -> 0 | CY67: =(ROUND((((S67+ROUND((ROUND(((EU67)*AV67*1),2)*BS67),2))*AT67)/100),2)+ROUND(((ROUND((ROUND(((AE67-(EU67))*AV67*1),2)*BS67),2)*AT67)/100),2)) -> 0 | CZ67: =(ROUND((((S67+ROUND((ROUND(((EU67)*AV67*1),2)*BS67),2))*AU67)/100),2)+ROUND(((ROUND((ROUND(((AE67-(EU67))*AV67*1),2)*BS67),2)*AU67)/100),2)) -> 0 | DN67: 0 | DO67: 0 | DP67: 1 | DQ67: 1 | DU67: 1013 | DV67: ШТ | DW67: ШТ | DX67: 1 | EE67: 60088638 | EF67: 130 | EG67: Сметная стоимость оборудования | EH67: 0 | EJ67: 3 | EK67: 746 | EL67: ТСН-2001.13. Сметная стоимость оборудования | EM67: ТСН-2001.13 | EQ67: 0 | ER67: 0 | ES67: 2421.06 | ET67: 0 | EU67: 0 | EV67: 0 | EW67: 0 | EX67: 0 | EY67: 0 | EZ67: 5 | FC67: 1 | FD67: 18 | FF67: 21350 | FQ67: 0 | FR67: =P67 -> 74181.28 | FS67: 0 | FX67: 0 | FY67: 0 | GA67: [21 350 / 1,2 / 7,66] + 3% Трансп + 1,2% Заг.скл | GD67: 1 | GF67: -790680475 | GG67: 2 | GH67: 3 | GI67: 5 | GJ67: 0 | GK67: 0 | GL67: =ROUND(IF(AND(BH67=3,BI67=3,FS67<>0),P67,0),2) -> 0 | GM67: =ROUND(O67+X67+Y67,2)+GX67 -> 74181.28 | GN67: =IF(OR(BI67=0,BI67=1),GM67-GX67,0) -> 0 | GO67: =IF(BI67=2,GM67-GX67,0) -> 0 | GP67: =IF(BI67=4,GM67-GX67,0) -> 0 | GR67: 1 | GS67: 1 | GT67: 0 | GV67: =ROUND((GT67),6) -> 0 | GW67: 1 | GX67: =ROUND(HC67*I67,2) -> 0 | HA67: 0 | HB67: 0 | HC67: =GV67*GW67 -> 0 | HE67: 3 | HF67: 1,2 | HS67: 0 | IK67: 0
A68: 17 | B68: 1 | C68: =ROW(SmtRes!A67) -> 67 | D68: =ROW(EtalonRes!A85) -> 85 | E68: 21 | F68: 4.10-75-6 | G68: Монтаж аппаратуры настольной массой до 20 кг | H68: 1 ШТ. | I68: 1 | J68: 0 | K68: 1 | O68: =ROUND(CP68,2) -> 136.61 | P68: =ROUND((ROUND((AC68*AW68*I68),2)*BC68),2) -> 34.87 | Q68: =(ROUND((ROUND((((ET68*1.1))*AV68*I68),2)*BB68),2)+ROUND((ROUND(((AE68-((EU68*1.1)))*AV68*I68),2)*BS68),2)) -> 0 | R68: =(ROUND((ROUND((((EU68*1.1))*AV68*I68),2)*BS68),2)+ROUND((ROUND(((AE68-((EU68*1.1)))*AV68*I68),2)*BS68),2)) -> 0 | S68: =ROUND((ROUND((AF68*AV68*I68),2)*BA68),2) -> 101.74 | T68: =ROUND(CU68*I68,2) -> 0 | U68: =CV68*I68 -> 8.0619 | V68: =CW68*I68 -> 0 | W68: =ROUND(CX68*I68,2) -> 0 | X68: =(ROUND((((S68+ROUND((ROUND((((EU68*1.1))*AV68*I68),2)*BS68),2))*AT68)/100),2)+ROUND(((ROUND((ROUND(((AE68-((EU68*1.1)))*AV68*I68),2)*BS68),2)*AT68)/100),2)) -> 96.65 | Y68: =(ROUND((((S68+ROUND((ROUND((((EU68*1.1))*AV68*I68),2)*BS68),2))*AU68)/100),2)+ROUND(((ROUND((ROUND(((AE68-((EU68*1.1)))*AV68*I68),2)*BS68),2)*AU68)/100),2)) -> 53.92 | AA68: 60258064 | AB68: =ROUND((AC68+AD68+AF68),6) -> 132.044 | AC68: =ROUND((ES68),6) -> 34.87 | AD68: =ROUND(((((ET68*1.1))-((EU68*1.1)))+AE68),6) -> 0 | AE68: =ROUND(((EU68*1.1)),6) -> 0 | AF68: =ROUND(((EV68*1.1)),6) -> 97.174 | AG68: =ROUND((AP68),6) -> 0 | AH68: =((EW68*1.1)) -> 7.7 | AI68: =((EX68*1.1)) -> 0 | AJ68: =(AS68) -> 0 | AK68: 123.21 | AL68: 34.87 | AM68: 0 | AN68: 0 | AO68: 88.34 | AP68: 0 | AQ68: 7 | AR68: 0 | AS68: 0 | AT68: 95 | AU68: 53 | AV68: 1.047 | AW68: 1 | AZ68: 1 | BA68: 1 | BB68: 1 | BC68: 1 | BH68: 0 | BI68: 2 | BJ68: ТСН-2001.4 Доп. 79, Сб. 10, т. 75, поз. 6 | BM68: 69 | BN68: 58973116 | BO68: 4.10-75-6 | BP68: 1 | BQ68: 40 | BR68: 0 | BS68: 1 | BT68: 1 | BU68: 1 | BV68: 1 | BW68: 1 | BX68: 1 | BZ68: 95 | CA68: 53 | CE68: 1566 | CF68: 0 | CG68: 0 | CM68: 0 | CN68: Поправка: О.П. п.3.4.30.в Наименование: При применении территориальных сметных нормативов для города Москвы затраты, учитывающие напряженные и стесненные условия производства работ (стесненность, сложность складирования и транспортной логистики и т.п.), исчисляются с применением коэффициентов к затратам труда и заработной плате рабочих, машинистов, времени эксплуатации машин и механизмов, стоимости эксплуатации машин в размере: для объектов, расположенных за пределами Третьего транспортного кольца города Москвы, но в пределах Московской кольцевой автомобильной дороги | CO68: 0 | CP68: =(P68+Q68+S68) -> 136.61 | CQ68: =ROUND((ROUND((AC68*AW68*1),2)*BC68),2) -> 34.87 | CR68: =(ROUND((ROUND((((ET68*1.1))*AV68*1),2)*BB68),2)+ROUND((ROUND(((AE68-((EU68*1.1)))*AV68*1),2)*BS68),2)) -> 0 | CS68: =(ROUND((ROUND((((EU68*1.1))*AV68*1),2)*BS68),2)+ROUND((ROUND(((AE68-((EU68*1.1)))*AV68*1),2)*BS68),2)) -> 0 | CT68: =ROUND((ROUND((AF68*AV68*1),2)*BA68),2) -> 101.74 | CU68: =AG68 -> 0 | CV68: =(AH68*AV68) -> 8.0619 | CW68: =AI68 -> 0 | CX68: =AJ68 -> 0 | CY68: =(ROUND((((S68+ROUND((ROUND((((EU68*1.1))*AV68*1),2)*BS68),2))*AT68)/100),2)+ROUND(((ROUND((ROUND(((AE68-((EU68*1.1)))*AV68*1),2)*BS68),2)*AT68)/100),2)) -> 96.65 | CZ68: =(ROUND((((S68+ROUND((ROUND((((EU68*1.1))*AV68*1),2)*BS68),2))*AU68)/100),2)+ROUND(((ROUND((ROUND(((AE68-((EU68*1.1)))*AV68*1),2)*BS68),2)*AU68)/100),2)) -> 53.92 | DB68: 17 | DE68: *1,1 | DF68: *1,1 | DG68: *1,1 | DI68: *1,1 | DJ68: *1,1 | DN68: 0 | DO68: 0 | DP68: 1 | DQ68: 1 | DU68: 1013 | DV68: 1 ШТ. | DW68: 1 ШТ. | DX68: 1 | EE68: 60088533 | EF68: 40 | EG68: Монтаж оборудования | EH68: 0 | EJ68: 2 | EK68: 69 | EL68: ТСН-2001.4-10. Монтаж радиотелевизионного и электронного оборудования | EM68: ТСН-2001.4-10-2 | EO68: Поправка: О.П. п.3.4.30.в | EQ68: 0 | ER68: 123.21 | ES68: 34.87 | ET68: 0 | EU68: 0 | EV68: 88.34 | EW68: 7 | EX68: 0 | EY68: 0 | FQ68: 0 | FR68: 0 | FS68: 0 | FX68: 95 | FY68: 53 | GD68: 1 | GF68: 1652728637 | GG68: 2 | GH68: 1 | GI68: 2 | GJ68: 0 | GK68: 0 | GL68: =ROUND(IF(AND(BH68=3,BI68=3,FS68<>0),P68,0),2) -> 0 | GM68: =ROUND(O68+X68+Y68,2)+GX68 -> 287.18 | GN68: =IF(OR(BI68=0,BI68=1),GM68-GX68,0) -> 0 | GO68: =IF(BI68=2,GM68-GX68,0) -> 287.18 | GP68: =IF(BI68=4,GM68-GX68,0) -> 0 | GR68: 0 | GS68: 3 | GT68: 0 | GV68: =ROUND((GT68),6) -> 0 | GW68: 1 | GX68: =ROUND(HC68*I68,2) -> 0 | HA68: 0 | HB68: 0 | HC68: =GV68*GW68 -> 0 | HS68: 0 | IK68: 0
A69: 17 | B69: 1 | C69: =ROW(SmtRes!A72) -> 72 | D69: =ROW(EtalonRes!A92) -> 92 | E69: 21 | F69: 4.10-75-6 | G69: Монтаж аппаратуры настольной массой до 20 кг | H69: 1 ШТ. | I69: 1 | J69: 0 | K69: 1 | O69: =ROUND(CP69,2) -> 5990.45 | P69: =ROUND((ROUND((AC69*AW69*I69),2)*BC69),2) -> 395.77 | Q69: =(ROUND((ROUND((((ET69*1.1))*AV69*I69),2)*BB69),2)+ROUND((ROUND(((AE69-((EU69*1.1)))*AV69*I69),2)*BS69),2)) -> 0 | R69: =(ROUND((ROUND((((EU69*1.1))*AV69*I69),2)*BS69),2)+ROUND((ROUND(((AE69-((EU69*1.1)))*AV69*I69),2)*BS69),2)) -> 0 | S69: =ROUND((ROUND((AF69*AV69*I69),2)*BA69),2) -> 5594.68 | T69: =ROUND(CU69*I69,2) -> 0 | U69: =CV69*I69 -> 8.0619 | V69: =CW69*I69 -> 0 | W69: =ROUND(CX69*I69,2) -> 0 | X69: =(ROUND((((S69+ROUND((ROUND((((EU69*1.1))*AV69*I69),2)*BS69),2))*AT69)/100),2)+ROUND(((ROUND((ROUND(((AE69-((EU69*1.1)))*AV69*I69),2)*BS69),2)*AT69)/100),2)) -> 5314.95 | Y69: =(ROUND((((S69+ROUND((ROUND((((EU69*1.1))*AV69*I69),2)*BS69),2))*AU69)/100),2)+ROUND(((ROUND((ROUND(((AE69-((EU69*1.1)))*AV69*I69),2)*BS69),2)*AU69)/100),2)) -> 2965.18 | AA69: 60258061 | AB69: =ROUND((AC69+AD69+AF69),6) -> 132.044 | AC69: =ROUND((ES69),6) -> 34.87 | AD69: =ROUND(((((ET69*1.1))-((EU69*1.1)))+AE69),6) -> 0 | AE69: =ROUND(((EU69*1.1)),6) -> 0 | AF69: =ROUND(((EV69*1.1)),6) -> 97.174 | AG69: =ROUND((AP69),6) -> 0 | AH69: =((EW69*1.1)) -> 7.7 | AI69: =((EX69*1.1)) -> 0 | AJ69: =(AS69) -> 0 | AK69: 123.21 | AL69: 34.87 | AM69: 0 | AN69: 0 | AO69: 88.34 | AP69: 0 | AQ69: 7 | AR69: 0 | AS69: 0 | AT69: 95 | AU69: 53 | AV69: 1.047 | AW69: 1 | AZ69: 1 | BA69: 54.99 | BB69: 1 | BC69: 11.35 | BH69: 0 | BI69: 2 | BJ69: ТСН-2001.4 Доп. 79, Сб. 10, т. 75, поз. 6 | BM69: 69 | BN69: 58973116 | BO69: 4.10-75-6 | BP69: 1 | BQ69: 40 | BR69: 0 | BS69: 54.99 | BT69: 1 | BU69: 1 | BV69: 1 | BW69: 1 | BX69: 1 | BZ69: 95 | CA69: 53 | CE69: 1566 | CF69: 0 | CG69: 0 | CM69: 0 | CN69: Поправка: О.П. п.3.4.30.в Наименование: При применении территориальных сметных нормативов для города Москвы затраты, учитывающие напряженные и стесненные условия производства работ (стесненность, сложность складирования и транспортной логистики и т.п.), исчисляются с применением коэффициентов к затратам труда и заработной плате рабочих, машинистов, времени эксплуатации машин и механизмов, стоимости эксплуатации машин в размере: для объектов, расположенных за пределами Третьего транспортного кольца города Москвы, но в пределах Московской кольцевой автомобильной дороги | CO69: 0 | CP69: =(P69+Q69+S69) -> 5990.45 | CQ69: =ROUND((ROUND((AC69*AW69*1),2)*BC69),2) -> 395.77 | CR69: =(ROUND((ROUND((((ET69*1.1))*AV69*1),2)*BB69),2)+ROUND((ROUND(((AE69-((EU69*1.1)))*AV69*1),2)*BS69),2)) -> 0 | CS69: =(ROUND((ROUND((((EU69*1.1))*AV69*1),2)*BS69),2)+ROUND((ROUND(((AE69-((EU69*1.1)))*AV69*1),2)*BS69),2)) -> 0 | CT69: =ROUND((ROUND((AF69*AV69*1),2)*BA69),2) -> 5594.68 | CU69: =AG69 -> 0 | CV69: =(AH69*AV69) -> 8.0619 | CW69: =AI69 -> 0 | CX69: =AJ69 -> 0 | CY69: =(ROUND((((S69+ROUND((ROUND((((EU69*1.1))*AV69*1),2)*BS69),2))*AT69)/100),2)+ROUND(((ROUND((ROUND(((AE69-((EU69*1.1)))*AV69*1),2)*BS69),2)*AT69)/100),2)) -> 5314.95 | CZ69: =(ROUND((((S69+ROUND((ROUND((((EU69*1.1))*AV69*1),2)*BS69),2))*AU69)/100),2)+ROUND(((ROUND((ROUND(((AE69-((EU69*1.1)))*AV69*1),2)*BS69),2)*AU69)/100),2)) -> 2965.18 | DB69: 18 | DE69: *1,1 | DF69: *1,1 | DG69: *1,1 | DI69: *1,1 | DJ69: *1,1 | DN69: 0 | DO69: 0 | DP69: 1 | DQ69: 1 | DU69: 1013 | DV69: 1 ШТ. | DW69: 1 ШТ. | DX69: 1 | EE69: 60088533 | EF69: 40 | EG69: Монтаж оборудования | EH69: 0 | EJ69: 2 | EK69: 69 | EL69: ТСН-2001.4-10. Монтаж радиотелевизионного и электронного оборудования | EM69: ТСН-2001.4-10-2 | EO69: Поправка: О.П. п.3.4.30.в | EQ69: 0 | ER69: 123.21 | ES69: 34.87 | ET69: 0 | EU69: 0 | EV69: 88.34 | EW69: 7 | EX69: 0 | EY69: 0 | FQ69: 0 | FR69: 0 | FS69: 0 | FX69: 95 | FY69: 53 | GD69: 1 | GF69: 1652728637 | GG69: 2 | GH69: 1 | GI69: 2 | GJ69: 0 | GK69: 0 | GL69: =ROUND(IF(AND(BH69=3,BI69=3,FS69<>0),P69,0),2) -> 0 | GM69: =ROUND(O69+X69+Y69,2)+GX69 -> 14270.58 | GN69: =IF(OR(BI69=0,BI69=1),GM69-GX69,0) -> 0 | GO69: =IF(BI69=2,GM69-GX69,0) -> 14270.58 | GP69: =IF(BI69=4,GM69-GX69,0) -> 0 | GR69: 0 | GS69: 3 | GT69: 0 | GV69: =ROUND((GT69),6) -> 0 | GW69: 1 | GX69: =ROUND(HC69*I69,2) -> 0 | HA69: 0 | HB69: 0 | HC69: =GV69*GW69 -> 0 | HS69: 0 | IK69: 0
A70: 17 | B70: 1 | E70: 22 | F70: КА-13 | G70: Рабочая станция DEPO Race VT955 | H70: ШТ | I70: 1 | J70: 0 | K70: 1 | O70: =ROUND(CP70,2) -> 62216.14 | P70: =ROUND((ROUND((AC70*I70),2)*BC70),2) -> 62216.14 | Q70: =(ROUND((ROUND(((ET70)*AV70*I70),2)*BB70),2)+ROUND((ROUND(((AE70-(EU70))*AV70*I70),2)*BS70),2)) -> 0 | R70: =(ROUND((ROUND(((EU70)*AV70*I70),2)*BS70),2)+ROUND((ROUND(((AE70-(EU70))*AV70*I70),2)*BS70),2)) -> 0 | S70: =ROUND((ROUND((AF70*AV70*I70),2)*BA70),2) -> 0 | T70: =ROUND(CU70*I70,2) -> 0 | U70: =CV70*I70 -> 0 | V70: =CW70*I70 -> 0 | W70: =ROUND(CX70*I70,2) -> 0 | X70: =(ROUND((((S70+ROUND((ROUND(((EU70)*AV70*I70),2)*BS70),2))*AT70)/100),2)+ROUND(((ROUND((ROUND(((AE70-(EU70))*AV70*I70),2)*BS70),2)*AT70)/100),2)) -> 0 | Y70: =(ROUND((((S70+ROUND((ROUND(((EU70)*AV70*I70),2)*BS70),2))*AU70)/100),2)+ROUND(((ROUND((ROUND(((AE70-(EU70))*AV70*I70),2)*BS70),2)*AU70)/100),2)) -> 0 | AA70: 60258064 | AB70: =ROUND((AC70+AD70+AF70),6) -> 62216.14 | AC70: =ROUND((ES70),6) -> 62216.14 | AD70: =ROUND((((ET70)-(EU70))+AE70),6) -> 0 | AE70: =ROUND((EU70),6) -> 0 | AF70: =ROUND((EV70),6) -> 0 | AG70: =ROUND((AP70),6) -> 0 | AH70: =(EW70) -> 0 | AI70: =(EX70) -> 0 | AJ70: =(AS70) -> 0 | AK70: 62216.14 | AL70: 62216.14 | AM70: 0 | AN70: 0 | AO70: 0 | AP70: 0 | AQ70: 0 | AR70: 0 | AS70: 0 | AT70: 0 | AU70: 0 | AV70: 1 | AW70: 1 | AZ70: 1 | BA70: 1 | BB70: 1 | BC70: 1 | BH70: 3 | BI70: 3 | BM70: 746 | BN70: 0 | BP70: 0 | BQ70: 130 | BR70: 0 | BS70: 1 | BT70: 1 | BU70: 1 | BV70: 1 | BW70: 1 | BX70: 1 | BZ70: 0 | CA70: 0 | CE70: 1566 | CF70: 0 | CG70: 0 | CM70: 0 | CO70: 0 | CP70: =(P70+Q70+S70) -> 62216.14 | CQ70: =ROUND((ROUND((AC70*1),2)*BC70),2) -> 62216.14 | CR70: =(ROUND((ROUND(((ET70)*AV70*1),2)*BB70),2)+ROUND((ROUND(((AE70-(EU70))*AV70*1),2)*BS70),2)) -> 0 | CS70: =(ROUND((ROUND(((EU70)*AV70*1),2)*BS70),2)+ROUND((ROUND(((AE70-(EU70))*AV70*1),2)*BS70),2)) -> 0 | CT70: =ROUND((ROUND((AF70*AV70*1),2)*BA70),2) -> 0 | CU70: =AG70 -> 0 | CV70: =(AH70*AV70) -> 0 | CW70: =AI70 -> 0 | CX70: =AJ70 -> 0 | CY70: =(ROUND((((S70+ROUND((ROUND(((EU70)*AV70*1),2)*BS70),2))*AT70)/100),2)+ROUND(((ROUND((ROUND(((AE70-(EU70))*AV70*1),2)*BS70),2)*AT70)/100),2)) -> 0 | CZ70: =(ROUND((((S70+ROUND((ROUND(((EU70)*AV70*1),2)*BS70),2))*AU70)/100),2)+ROUND(((ROUND((ROUND(((AE70-(EU70))*AV70*1),2)*BS70),2)*AU70)/100),2)) -> 0 | DN70: 0 | DO70: 0 | DP70: 1 | DQ70: 1 | DU70: 1013 | DV70: ШТ | DW70: ШТ | DX70: 1 | EE70: 60088638 | EF70: 130 | EG70: Сметная стоимость оборудования | EH70: 0 | EJ70: 3 | EK70: 746 | EL70: ТСН-2001.13. Сметная стоимость оборудования | EM70: ТСН-2001.13 | EQ70: 0 | ER70: 0 | ES70: 62216.14 | ET70: 0 | EU70: 0 | EV70: 0 | EW70: 0 | EX70: 0 | EY70: 0 | FQ70: 0 | FR70: =P70 -> 62216.14 | FS70: 0 | FX70: 0 | FY70: 0 | GA70: [548 650 / 1,2 / 7,66] + 3% Трансп + 1,2% Заг.скл | GD70: 1 | GF70: 2015310264 | GG70: 2 | GH70: 4 | GI70: -2 | GJ70: 0 | GK70: 0 | GL70: =ROUND(IF(AND(BH70=3,BI70=3,FS70<>0),P70,0),2) -> 0 | GM70: =ROUND(O70+X70+Y70,2)+GX70 -> 62216.14 | GN70: =IF(OR(BI70=0,BI70=1),GM70-GX70,0) -> 0 | GO70: =IF(BI70=2,GM70-GX70,0) -> 0 | GP70: =IF(BI70=4,GM70-GX70,0) -> 0 | GR70: 0 | GS70: 2 | GT70: 0 | GV70: =ROUND((GT70),6) -> 0 | GW70: 1 | GX70: =ROUND(HC70*I70,2) -> 0 | HA70: 0 | HB70: 0 | HC70: =GV70*GW70 -> 0 | HE70: 3 | HF70: 1,2 | HS70: 0 | IK70: 0
A71: 17 | B71: 1 | E71: 22 | F71: КА-13 | G71: Рабочая станция DEPO Race VT955 | H71: ШТ | I71: 1 | J71: 0 | K71: 1 | O71: =ROUND(CP71,2) -> 476575.63 | P71: =ROUND((ROUND((AC71*I71),2)*BC71),2) -> 476575.63 | Q71: =(ROUND((ROUND(((ET71)*AV71*I71),2)*BB71),2)+ROUND((ROUND(((AE71-(EU71))*AV71*I71),2)*BS71),2)) -> 0 | R71: =(ROUND((ROUND(((EU71)*AV71*I71),2)*BS71),2)+ROUND((ROUND(((AE71-(EU71))*AV71*I71),2)*BS71),2)) -> 0 | S71: =ROUND((ROUND((AF71*AV71*I71),2)*BA71),2) -> 0 | T71: =ROUND(CU71*I71,2) -> 0 | U71: =CV71*I71 -> 0 | V71: =CW71*I71 -> 0 | W71: =ROUND(CX71*I71,2) -> 0 | X71: =(ROUND((((S71+ROUND((ROUND(((EU71)*AV71*I71),2)*BS71),2))*AT71)/100),2)+ROUND(((ROUND((ROUND(((AE71-(EU71))*AV71*I71),2)*BS71),2)*AT71)/100),2)) -> 0 | Y71: =(ROUND((((S71+ROUND((ROUND(((EU71)*AV71*I71),2)*BS71),2))*AU71)/100),2)+ROUND(((ROUND((ROUND(((AE71-(EU71))*AV71*I71),2)*BS71),2)*AU71)/100),2)) -> 0 | AA71: 60258061 | AB71: =ROUND((AC71+AD71+AF71),6) -> 62216.14 | AC71: =ROUND((ES71),6) -> 62216.14 | AD71: =ROUND((((ET71)-(EU71))+AE71),6) -> 0 | AE71: =ROUND((EU71),6) -> 0 | AF71: =ROUND((EV71),6) -> 0 | AG71: =ROUND((AP71),6) -> 0 | AH71: =(EW71) -> 0 | AI71: =(EX71) -> 0 | AJ71: =(AS71) -> 0 | AK71: 62216.14 | AL71: 62216.14 | AM71: 0 | AN71: 0 | AO71: 0 | AP71: 0 | AQ71: 0 | AR71: 0 | AS71: 0 | AT71: 0 | AU71: 0 | AV71: 1 | AW71: 1 | AZ71: 1 | BA71: 1 | BB71: 1 | BC71: 7.66 | BH71: 3 | BI71: 3 | BM71: 746 | BN71: 0 | BP71: 0 | BQ71: 130 | BR71: 0 | BS71: 1 | BT71: 1 | BU71: 1 | BV71: 1 | BW71: 1 | BX71: 1 | BZ71: 0 | CA71: 0 | CE71: 1566 | CF71: 0 | CG71: 0 | CM71: 0 | CO71: 0 | CP71: =(P71+Q71+S71) -> 476575.63 | CQ71: =ROUND((ROUND((AC71*1),2)*BC71),2) -> 476575.63 | CR71: =(ROUND((ROUND(((ET71)*AV71*1),2)*BB71),2)+ROUND((ROUND(((AE71-(EU71))*AV71*1),2)*BS71),2)) -> 0 | CS71: =(ROUND((ROUND(((EU71)*AV71*1),2)*BS71),2)+ROUND((ROUND(((AE71-(EU71))*AV71*1),2)*BS71),2)) -> 0 | CT71: =ROUND((ROUND((AF71*AV71*1),2)*BA71),2) -> 0 | CU71: =AG71 -> 0 | CV71: =(AH71*AV71) -> 0 | CW71: =AI71 -> 0 | CX71: =AJ71 -> 0 | CY71: =(ROUND((((S71+ROUND((ROUND(((EU71)*AV71*1),2)*BS71),2))*AT71)/100),2)+ROUND(((ROUND((ROUND(((AE71-(EU71))*AV71*1),2)*BS71),2)*AT71)/100),2)) -> 0 | CZ71: =(ROUND((((S71+ROUND((ROUND(((EU71)*AV71*1),2)*BS71),2))*AU71)/100),2)+ROUND(((ROUND((ROUND(((AE71-(EU71))*AV71*1),2)*BS71),2)*AU71)/100),2)) -> 0 | DN71: 0 | DO71: 0 | DP71: 1 | DQ71: 1 | DU71: 1013 | DV71: ШТ | DW71: ШТ | DX71: 1 | EE71: 60088638 | EF71: 130 | EG71: Сметная стоимость оборудования | EH71: 0 | EJ71: 3 | EK71: 746 | EL71: ТСН-2001.13. Сметная стоимость оборудования | EM71: ТСН-2001.13 | EQ71: 0 | ER71: 0 | ES71: 62216.14 | ET71: 0 | EU71: 0 | EV71: 0 | EW71: 0 | EX71: 0 | EY71: 0 | EZ71: 5 | FC71: 1 | FD71: 18 | FF71: 548650 | FQ71: 0 | FR71: =P71 -> 476575.63 | FS71: 0 | FX71: 0 | FY71: 0 | GA71: [548 650 / 1,2 / 7,66] + 3% Трансп + 1,2% Заг.скл | GD71: 1 | GF71: 2015310264 | GG71: 2 | GH71: 3 | GI71: 5 | GJ71: 0 | GK71: 0 | GL71: =ROUND(IF(AND(BH71=3,BI71=3,FS71<>0),P71,0),2) -> 0 | GM71: =ROUND(O71+X71+Y71,2)+GX71 -> 476575.63 | GN71: =IF(OR(BI71=0,BI71=1),GM71-GX71,0) -> 0 | GO71: =IF(BI71=2,GM71-GX71,0) -> 0 | GP71: =IF(BI71=4,GM71-GX71,0) -> 0 | GR71: 1 | GS71: 1 | GT71: 0 | GV71: =ROUND((GT71),6) -> 0 | GW71: 1 | GX71: =ROUND(HC71*I71,2) -> 0 | HA71: 0 | HB71: 0 | HC71: =GV71*GW71 -> 0 | HE71: 3 | HF71: 1,2 | HS71: 0 | IK71: 0
