Workbook

Sheet 02-01-17
A1: =Source!B1 -> Smeta.RU (495) 974-1589
J2: Форма № 4б
A3: Капитальный ремонт здания Государственного бюджетного общеобразовательного учреждения города Москвы «Школа № 236» по адресу: г. Москва, ул. Клязьминская, д. 7, к. 4. I этап | AP3: Капитальный ремонт здания Государственного бюджетного общеобразовательного учреждения города Москвы «Школа № 236» по адресу: г. Москва, ул. Клязьминская, д. 7, к. 4. I этап. 02-01-17 СДС
A4: (наименование стройки и/или объекта)
A6: =CONCATENATE( "ЛОКАЛЬНАЯ СМЕТА № ",IF(Source!F20<>"Новая локальная смета", Source!F20, "")) -> ЛОКАЛЬНАЯ СМЕТА № 02-01-17
A8: =IF(Source!G20<>"Новая локальная смета", Source!G20, "") -> Система двусторонней связи
A9: (наименование работ и затрат)
A11: =CONCATENATE( "Основание: чертежи № ", Source!J20) -> Основание: чертежи № 2024-00272-01-0-ИОС5.10
I13: В базисном уровне цен | J13: В текущем уровне цен
E14: Сметная стоимость | I14: =I15+I16+I17+I18 -> 115.84 | J14: =J15+J16+J17+J18 -> 1137.88 | K14: тыс.руб.
E15: Строительные работы | I15: =ROUND((Source!F189)/1000, 2) -> 0 | J15: =ROUND((Source!P189)/1000, 2) -> 0 | K15: тыс.руб.
E16: Работы по монтажу оборудования | I16: =ROUND((Source!F190)/1000, 2) -> 33.96 | J16: =ROUND((Source!P190)/1000, 2) -> 510.48 | K16: тыс.руб.
E17: Оборудование | I17: =ROUND((Source!F181)/1000, 2) -> 81.88 | J17: =ROUND((Source!P181)/1000, 2) -> 627.4 | K17: тыс.руб.
E18: Прочие работы и затраты | I18: =ROUND((Source!F191+Source!F192)/1000, 2) -> 0 | J18: =ROUND((Source!P191+Source!P192)/1000, 2) -> 0 | K18: тыс.руб.
E19: Средства на оплату труда | I19: =(Source!F187+ Source!F186)/1000 -> 1.76544 | J19: =((Source!P187 + Source!P186)/1000) -> 97.08155 | K19: тыс.руб.
E20: Затраты труда | I20: =Source!F194 -> 136.29448 | K20: чел.-ч.
E21: Кроме того:
E22: Возврат материалов | I22: =SUM(Y28:Y164)/1000 -> 0 | J22: =SUM(Z28:Z164)/1000 -> 0 | K22: тыс.руб.
A24: Составлен(а) по ТСН-2001 с учетом Дополнения №: 80
A25: № и период сборника коэффициентов (индексов) пересчета: Коэффициенты к ТСН-2001 МГЭ Дополнение 80, строительство №217/80 III квартал 2025 года и Коэффициенты к ТСН-2001.13-2 Дополнение 46 №62/46 III квартал 2025 года | AP25: № и период сборника коэффициентов (индексов) пересчета: Коэффициенты к ТСН-2001 МГЭ Дополнение 80, строительство №217/80 III квартал 2025 года и Коэффициенты к ТСН-2001.13-2 Дополнение 46 №62/46 III квартал 2025 года
A26: № п/п | B26: Шифр расценки и коды ресурсов | C26: Наименование работ и затрат | D26: Ед. изм. | E26: Кол-во единиц | F26: Цена на ед. изм., руб. | G26: Попра- вочные коэффи- циенты | H26: Коэффи- циенты зимних удорожа- ний | I26: Всего в ценах на январь 2000 года, руб. | J26: Коэффи- циенты (индек- сы) пере- счета, нормы НР и СП | K26: ВСЕГО затрат в текущем уровне цен, руб.
A27: 1 | B27: 2 | C27: 3 | D27: 4 | E27: 5 | F27: 6 | G27: 7 | H27: 8 | I27: 9 | J27: 10 | K27: 11
A29: =CONCATENATE("Раздел: ",IF(Source!G24<>"Новый раздел", Source!G24, "")) -> Раздел: Оборудование
A30: 1 | B30: 4.10-175-1 Поправка: Гл.12.Прил.8.п.8. 5_12.00.01.11.003 | C30: Монтаж домового регистратора | D30: =Source!H28 -> 1 ШТ. | E30: =Source!I28 -> 1 | Q30: =Source!X28 -> 21.52 | R30: =Source!X29 -> 1183.33 | S30: =Source!Y28 -> 11 | T30: =Source!Y29 -> 604.81 | U30: =ROUND((175/100)*ROUND(Source!R28, 2), 2) -> 0.26 | V30: =ROUND((0/100)*ROUND(Source!R29, 2), 2) -> 0 | AC30: 0
C31: ЗП | F31: =Source!AO28 -> 20.63 | G31: =Source!DG28 -> *1,1 | H31: =Source!AV29 -> 1.047 | I31: =Source!S28 -> 23.76 | J31: =IF(Source!BA29<> 0, Source!BA29, 1) -> 54.99 | K31: =Source!S29 -> 1306.56
C32: ЭМ | F32: =Source!AM28 -> 0.91 | G32: =Source!DE28 -> *1,1 | H32: =Source!AV29 -> 1.047 | I32: =Source!Q28 -> 1.05 | J32: =IF(Source!BB29<> 0, Source!BB29, 1) -> 15.65 | K32: =Source!Q29 -> 16.43
C33: в т.ч. ЗПМ | F33: =Source!AN28 -> 0.13 | G33: =Source!DF28 -> *1,1 | H33: =Source!AV29 -> 1.047 | I33: =Source!R28 -> 0.15 | J33: =IF(Source!BS29<> 0, Source!BS29, 1) -> 54.99 | K33: =Source!R29 -> 8.25
C34: МР | F34: =Source!AL28 -> 1.22 | G34: =Source!DD28 | H34: =Source!AW29 -> 1 | I34: =Source!P28 -> 1.22 | J34: =IF(Source!BC29<> 0, Source!BC29, 1) -> 25.52 | K34: =Source!P29 -> 31.13
A35: 1,1 | B35: =Source!F30 -> КА 1 | C35: ОБОРУДОВАНИЕ:_x000D_ Монитор видеодомофона Модус-Н Vizit-M406 1 062,54 = [9 370 / 1,2 / 7,66] + 3% Трансп + 1,2% Заг.скл | D35: =Source!H30 -> шт. | E35: =Source!I30 -> 1 | F35: =Source!AK30 -> 1062.54 | H35: =Source!AW31 -> 1 | I35: =Source!O30 -> 1062.54 | J35: =IF(Source!BC31<> 0, Source!BC31, 1) -> 7.66 | K35: =Source!O31 -> 8139.06 | Q35: =Source!X30 -> 0 | R35: =Source!X31 -> 0 | S35: =Source!Y30 -> 0 | T35: =Source!Y31 -> 0 | U35: =ROUND((175/100)*ROUND(Source!R30, 2), 2) -> 0 | V35: =ROUND((0/100)*ROUND(Source!R31, 2), 2) -> 0 | AC35: 5
C36: НР от ФОТ | D36: % | E36: =Source!BZ29 -> 90 | I36: =SUM(Q30:Q35) -> 21.52 | J36: =Source!AT29 -> 90 | K36: =SUM(R30:R35) -> 1183.33
C37: СП от ФОТ | D37: % | E37: =Source!CA29 -> 46 | I37: =SUM(S30:S36) -> 11 | J37: =Source!AU29 -> 46 | K37: =SUM(T30:T36) -> 604.81
C38: ЗТР | D38: чел-ч | E38: =Source!AQ28 -> 1.35 | G38: =Source!DI28 -> *1,1 | H38: =Source!AV29 -> 1.047 | I38: =Source!U28 -> 1.554795
C39: ВСЕГО работ по позиции: | H39: =I31+I32+I34+I36+I37+SUM(I35:I35)-SUMIF(AC35:AC35, 5, I35:I35)-SUMIF(AC35:AC35, 6, I35:I35) -> 58.55 | J39: =K31+K32+K34+K36+K37+SUM(K35:K35)-SUMIF(AC35:AC35, 5, K35:K35)-SUMIF(AC35:AC35, 6, K35:K35) -> 3142.26
C40: ВСЕГО оборудование по позиции: | H40: =SUMIF(AC35:AC35, 5, I35:I35)+SUMIF(AC35:AC35, 6, I35:I35) -> 1062.54 | J40: =SUMIF(AC35:AC35, 5, K35:K35)+SUMIF(AC35:AC35, 6, K35:K35) -> 8139.06
C41: ВСЕГО по позиции: | H41: =I31+I32+I34+I36+I37+SUM(I35:I35) -> 1121.09 | J41: =K31+K32+K34+K36+K37+SUM(K35:K35) -> 11281.32 | O41: =I31+I32+I34+I36+I37+SUM(I35:I35) -> 1121.09 | P41: =K31+K32+K34+K36+K37+SUM(K35:K35) -> 11281.32
A43: 2 | B43: 4.10-177-1 Поправка: Гл.12.Прил.8.п.8. 5_12.00.01.11.003 | C43: Монтаж устройства связи с согласующим устройством (вызывная панель) | D43: =Source!H32 -> 10 шт. | E43: =Source!I32 -> 0.1 | Q43: =Source!X32 -> 23.65 | R43: =Source!X33 -> 1300.63 | S43: =Source!Y32 -> 12.09 | T43: =Source!Y33 -> 664.76 | U43: =ROUND((175/100)*ROUND(Source!R32, 2), 2) -> 0.16 | V43: =ROUND((0/100)*ROUND(Source!R33, 2), 2) -> 0 | AC43: 0
C44: ="Объем: "&Source!I32&"=1/"&"10" -> Объем: 0,1=1/10
C45: ЗП | F45: =Source!AO32 -> 227.44 | G45: =Source!DG32 -> *1,1 | H45: =Source!AV33 -> 1.047 | I45: =Source!S32 -> 26.19 | J45: =IF(Source!BA33<> 0, Source!BA33, 1) -> 54.99 | K45: =Source!S33 -> 1440.19
C46: ЭМ | F46: =Source!AM32 -> 6.07 | G46: =Source!DE32 -> *1,1 | H46: =Source!AV33 -> 1.047 | I46: =Source!Q32 -> 0.7 | J46: =IF(Source!BB33<> 0, Source!BB33, 1) -> 14.94 | K46: =Source!Q33 -> 10.46
C47: в т.ч. ЗПМ | F47: =Source!AN32 -> 0.76 | G47: =Source!DF32 -> *1,1 | H47: =Source!AV33 -> 1.047 | I47: =Source!R32 -> 0.09 | J47: =IF(Source!BS33<> 0, Source!BS33, 1) -> 54.99 | K47: =Source!R33 -> 4.95
C48: МР | F48: =Source!AL32 -> 2.44 | G48: =Source!DD32 | H48: =Source!AW33 -> 1 | I48: =Source!P32 -> 0.24 | J48: =IF(Source!BC33<> 0, Source!BC33, 1) -> 7.23 | K48: =Source!P33 -> 1.74
A49: 2,1 | B49: =Source!F34 -> КА 2 | C49: ОБОРУДОВАНИЕ:_x000D_ Вызывная панель Activision AVC-305 439,99 = [3 880 / 1,2 / 7,66] + 3% Трансп + 1,2% Заг.скл | D49: =Source!H34 -> шт. | E49: =Source!I34 -> 1 | F49: =Source!AK34 -> 439.99 | H49: =Source!AW35 -> 1 | I49: =Source!O34 -> 439.99 | J49: =IF(Source!BC35<> 0, Source!BC35, 1) -> 7.66 | K49: =Source!O35 -> 3370.32 | Q49: =Source!X34 -> 0 | R49: =Source!X35 -> 0 | S49: =Source!Y34 -> 0 | T49: =Source!Y35 -> 0 | U49: =ROUND((175/100)*ROUND(Source!R34, 2), 2) -> 0 | V49: =ROUND((0/100)*ROUND(Source!R35, 2), 2) -> 0 | AC49: 5
C50: НР от ФОТ | D50: % | E50: =Source!BZ33 -> 90 | I50: =SUM(Q43:Q49) -> 23.65 | J50: =Source!AT33 -> 90 | K50: =SUM(R43:R49) -> 1300.63
C51: СП от ФОТ | D51: % | E51: =Source!CA33 -> 46 | I51: =SUM(S43:S50) -> 12.09 | J51: =Source!AU33 -> 46 | K51: =SUM(T43:T50) -> 664.76
C52: ЗТР | D52: чел-ч | E52: =Source!AQ32 -> 14.64 | G52: =Source!DI32 -> *1,1 | H52: =Source!AV33 -> 1.047 | I52: =Source!U32 -> 1.6860888
C53: ВСЕГО работ по позиции: | H53: =I45+I46+I48+I50+I51+SUM(I49:I49)-SUMIF(AC49:AC49, 5, I49:I49)-SUMIF(AC49:AC49, 6, I49:I49) -> 62.87 | J53: =K45+K46+K48+K50+K51+SUM(K49:K49)-SUMIF(AC49:AC49, 5, K49:K49)-SUMIF(AC49:AC49, 6, K49:K49) -> 3417.78
C54: ВСЕГО оборудование по позиции: | H54: =SUMIF(AC49:AC49, 5, I49:I49)+SUMIF(AC49:AC49, 6, I49:I49) -> 439.99 | J54: =SUMIF(AC49:AC49, 5, K49:K49)+SUMIF(AC49:AC49, 6, K49:K49) -> 3370.32
C55: ВСЕГО по позиции: | H55: =I45+I46+I48+I50+I51+SUM(I49:I49) -> 502.86 | J55: =K45+K46+K48+K50+K51+SUM(K49:K49) -> 6788.1 | O55: =I45+I46+I48+I50+I51+SUM(I49:I49) -> 502.86 | P55: =K45+K46+K48+K50+K51+SUM(K49:K49) -> 6788.1
A57: 3 | B57: 4.11-1-4 Поправка: Гл.12.Прил.8.п.8. 5_12.00.01.11.003 | C57: Монтаж конструкции для установки приборов и средств автоматизации массой до 5 кг | D57: =Source!H36 -> 1 ШТ. | E57: =Source!I36 -> 1 | Q57: =Source!X36 -> 13.5 | R57: =Source!X37 -> 742.37 | S57: =Source!Y36 -> 6.9 | T57: =Source!Y37 -> 379.43 | U57: =ROUND((175/100)*ROUND(Source!R36, 2), 2) -> 2.49 | V57: =ROUND((0/100)*ROUND(Source!R37, 2), 2) -> 0 | AC57: 0
C58: ЗП | F58: =Source!AO36 -> 11.79 | G58: =Source!DG36 -> *1,1 | H58: =Source!AV37 -> 1.047 | I58: =Source!S36 -> 13.58 | J58: =IF(Source!BA37<> 0, Source!BA37, 1) -> 54.99 | K58: =Source!S37 -> 746.76
C59: ЭМ | F59: =Source!AM36 -> 5.37 | G59: =Source!DE36 -> *1,1 | H59: =Source!AV37 -> 1.047 | I59: =Source!Q36 -> 6.18 | J59: =IF(Source!BB37<> 0, Source!BB37, 1) -> 21.37 | K59: =Source!Q37 -> 132.07
C60: в т.ч. ЗПМ | F60: =Source!AN36 -> 1.23 | G60: =Source!DF36 -> *1,1 | H60: =Source!AV37 -> 1.047 | I60: =Source!R36 -> 1.42 | J60: =IF(Source!BS37<> 0, Source!BS37, 1) -> 54.99 | K60: =Source!R37 -> 78.09
C61: МР | F61: =Source!AL36 -> 51.03 | G61: =Source!DD36 | H61: =Source!AW37 -> 1 | I61: =Source!P36 -> 51.03 | J61: =IF(Source!BC37<> 0, Source!BC37, 1) -> 9.98 | K61: =Source!P37 -> 509.28
A62: 3,1 | B62: =Source!F38 -> КА 3 | C62: Стойка для вызывной панели AR-GO STS-03 546,30 = [6 350 / 1,2 / 9,88] + 2% Заг.скл | D62: =Source!H38 -> шт. | E62: =Source!I38 -> 1 | F62: =Source!AK38 -> 546.3 | H62: =Source!AW39 -> 1 | I62: =Source!O38 -> 546.3 | J62: =IF(Source!BC39<> 0, Source!BC39, 1) -> 9.88 | K62: =Source!O39 -> 5397.44 | Q62: =Source!X38 -> 0 | R62: =Source!X39 -> 0 | S62: =Source!Y38 -> 0 | T62: =Source!Y39 -> 0 | U62: =ROUND((175/100)*ROUND(Source!R38, 2), 2) -> 0 | V62: =ROUND((0/100)*ROUND(Source!R39, 2), 2) -> 0 | AC62: 3
C63: НР от ФОТ | D63: % | E63: =Source!BZ37 -> 90 | I63: =SUM(Q57:Q62) -> 13.5 | J63: =Source!AT37 -> 90 | K63: =SUM(R57:R62) -> 742.37
C64: СП от ФОТ | D64: % | E64: =Source!CA37 -> 46 | I64: =SUM(S57:S63) -> 6.9 | J64: =Source!AU37 -> 46 | K64: =SUM(T57:T63) -> 379.43
C65: ЗТР | D65: чел-ч | E65: =Source!AQ36 -> 1.03 | G65: =Source!DI36 -> *1,1 | H65: =Source!AV37 -> 1.047 | I65: =Source!U36 -> 1.186251
C66: ВСЕГО работ по позиции: | H66: =I58+I59+I61+I63+I64+SUM(I62:I62)-SUMIF(AC62:AC62, 5, I62:I62)-SUMIF(AC62:AC62, 6, I62:I62) -> 637.49 | J66: =K58+K59+K61+K63+K64+SUM(K62:K62)-SUMIF(AC62:AC62, 5, K62:K62)-SUMIF(AC62:AC62, 6, K62:K62) -> 7907.35
C67: ВСЕГО оборудование по позиции: | H67: =SUMIF(AC62:AC62, 5, I62:I62)+SUMIF(AC62:AC62, 6, I62:I62) -> 0 | J67: =SUMIF(AC62:AC62, 5, K62:K62)+SUMIF(AC62:AC62, 6, K62:K62) -> 0
C68: ВСЕГО по позиции: | H68: =I58+I59+I61+I63+I64+SUM(I62:I62) -> 637.49 | J68: =K58+K59+K61+K63+K64+SUM(K62:K62) -> 7907.35 | O68: =I58+I59+I61+I63+I64+SUM(I62:I62) -> 637.49 | P68: =K58+K59+K61+K63+K64+SUM(K62:K62) -> 7907.35
A70: 4 | B70: 4.10-152-5 Поправка: Гл.12.Прил.8.п.8. 5_12.00.01.11.003 | C70: Сигнализация дистанционная, блок оконечный | D70: =Source!H40 -> 1 ШТ. | E70: =Source!I40 -> 1 | Q70: =Source!X40 -> 313.95 | R70: =Source!X41 -> 17263.94 | S70: =Source!Y40 -> 160.46 | T70: =Source!Y41 -> 8823.79 | U70: =ROUND((175/100)*ROUND(Source!R40, 2), 2) -> 0 | V70: =ROUND((0/100)*ROUND(Source!R41, 2), 2) -> 0 | AC70: 0
C71: ЗП | F71: =Source!AO40 -> 302.88 | G71: =Source!DG40 -> *1,1 | H71: =Source!AV41 -> 1.047 | I71: =Source!S40 -> 348.83 | J71: =IF(Source!BA41<> 0, Source!BA41, 1) -> 54.99 | K71: =Source!S41 -> 19182.16
C72: МР | F72: =Source!AL40 -> 17 | G72: =Source!DD40 | H72: =Source!AW41 -> 1 | I72: =Source!P40 -> 17 | J72: =IF(Source!BC41<> 0, Source!BC41, 1) -> 9.89 | K72: =Source!P41 -> 168.13
A73: 4,1 | B73: =Source!F42 -> КА 5 | C73: ОБОРУДОВАНИЕ:_x000D_ Локальный блок связи Тромбон ЛБС 12 025,03 = [106 042,16 / 1,2 / 7,66] + 3% Трансп + 1,2% Заг.скл | D73: =Source!H42 -> шт. | E73: =Source!I42 -> 1 | F73: =Source!AK42 -> 12025.03 | H73: =Source!AW43 -> 1 | I73: =Source!O42 -> 12025.03 | J73: =IF(Source!BC43<> 0, Source!BC43, 1) -> 7.66 | K73: =Source!O43 -> 92111.73 | Q73: =Source!X42 -> 0 | R73: =Source!X43 -> 0 | S73: =Source!Y42 -> 0 | T73: =Source!Y43 -> 0 | U73: =ROUND((175/100)*ROUND(Source!R42, 2), 2) -> 0 | V73: =ROUND((0/100)*ROUND(Source!R43, 2), 2) -> 0 | AC73: 5
A74: 4,2 | B74: =Source!F44 -> 13.1-1-20 | C74: ОБОРУДОВАНИЕ:_x000D_ Батарея аккумуляторная, емкость 7 А·ч, напряжение 12 В | D74: =Source!H44 -> шт. | E74: =Source!I44 -> 2 | F74: =Source!AK44 -> 89.39 | H74: =Source!AW45 -> 1 | I74: =Source!O44 -> 178.78 | J74: =IF(Source!BC45<> 0, Source!BC45, 1) -> 8.75 | K74: =Source!O45 -> 1564.33 | Q74: =Source!X44 -> 0 | R74: =Source!X45 -> 0 | S74: =Source!Y44 -> 0 | T74: =Source!Y45 -> 0 | U74: =ROUND((175/100)*ROUND(Source!R44, 2), 2) -> 0 | V74: =ROUND((0/100)*ROUND(Source!R45, 2), 2) -> 0 | AC74: 5
C75: НР от ФОТ | D75: % | E75: =Source!BZ41 -> 90 | I75: =SUM(Q70:Q74) -> 313.95 | J75: =Source!AT41 -> 90 | K75: =SUM(R70:R74) -> 17263.94
C76: СП от ФОТ | D76: % | E76: =Source!CA41 -> 46 | I76: =SUM(S70:S75) -> 160.46 | J76: =Source!AU41 -> 46 | K76: =SUM(T70:T75) -> 8823.79
C77: ЗТР | D77: чел-ч | E77: =Source!AQ40 -> 24 | G77: =Source!DI40 -> *1,1 | H77: =Source!AV41 -> 1.047 | I77: =Source!U40 -> 27.6408
C78: ВСЕГО работ по позиции: | H78: =I71+I72+I75+I76+SUM(I73:I74)-SUMIF(AC73:AC74, 5, I73:I74)-SUMIF(AC73:AC74, 6, I73:I74) -> 840.24 | J78: =K71+K72+K75+K76+SUM(K73:K74)-SUMIF(AC73:AC74, 5, K73:K74)-SUMIF(AC73:AC74, 6, K73:K74) -> 45438.02
C79: ВСЕГО оборудование по позиции: | H79: =SUMIF(AC73:AC74, 5, I73:I74)+SUMIF(AC73:AC74, 6, I73:I74) -> 12203.81 | J79: =SUMIF(AC73:AC74, 5, K73:K74)+SUMIF(AC73:AC74, 6, K73:K74) -> 93676.06
C80: ВСЕГО по позиции: | H80: =I71+I72+I75+I76+SUM(I73:I74) -> 13044.05 | J80: =K71+K72+K75+K76+SUM(K73:K74) -> 139114.08 | O80: =I71+I72+I75+I76+SUM(I73:I74) -> 13044.05 | P80: =K71+K72+K75+K76+SUM(K73:K74) -> 139114.08
A82: 5 | B82: 4.10-151-2 Поправка: Гл.12.Прил.8.п.8. 5_12.00.01.11.003 | C82: Установка пульта или табло вызывной сигнализации с количеством сигналов до 10 | D82: =Source!H46 -> 1 ШТ. | E82: =Source!I46 -> 1 | Q82: =Source!X46 -> 69.35 | R82: =Source!X47 -> 3813.28 | S82: =Source!Y46 -> 35.44 | T82: =Source!Y47 -> 1949.01 | U82: =ROUND((175/100)*ROUND(Source!R46, 2), 2) -> 0 | V82: =ROUND((0/100)*ROUND(Source!R47, 2), 2) -> 0 | AC82: 0
C83: ЗП | F83: =Source!AO46 -> 66.9 | G83: =Source!DG46 -> *1,1 | H83: =Source!AV47 -> 1.047 | I83: =Source!S46 -> 77.05 | J83: =IF(Source!BA47<> 0, Source!BA47, 1) -> 54.99 | K83: =Source!S47 -> 4236.98
C84: ЭМ | F84: =Source!AM46 -> 0.1 | G84: =Source!DE46 -> *1,1 | H84: =Source!AV47 -> 1.047 | I84: =Source!Q46 -> 0.12 | J84: =IF(Source!BB47<> 0, Source!BB47, 1) -> 8.9 | K84: =Source!Q47 -> 1.07
C85: МР | F85: =Source!AL46 -> 2.67 | G85: =Source!DD46 | H85: =Source!AW47 -> 1 | I85: =Source!P46 -> 2.67 | J85: =IF(Source!BC47<> 0, Source!BC47, 1) -> 0.9 | K85: =Source!P47 -> 2.4
A86: 5,1 | B86: =Source!F48 -> КА 6 | C86: ОБОРУДОВАНИЕ:_x000D_ Пульт диспетчера Тромбон ПД 9 139,90 = [80 599,79 / 1,2 / 7,66] + 3% Трансп + 1,2% Заг.скл | D86: =Source!H48 -> шт. | E86: =Source!I48 -> 1 | F86: =Source!AK48 -> 9139.9 | H86: =Source!AW49 -> 1 | I86: =Source!O48 -> 9139.9 | J86: =IF(Source!BC49<> 0, Source!BC49, 1) -> 7.66 | K86: =Source!O49 -> 70011.63 | Q86: =Source!X48 -> 0 | R86: =Source!X49 -> 0 | S86: =Source!Y48 -> 0 | T86: =Source!Y49 -> 0 | U86: =ROUND((175/100)*ROUND(Source!R48, 2), 2) -> 0 | V86: =ROUND((0/100)*ROUND(Source!R49, 2), 2) -> 0 | AC86: 5
C87: НР от ФОТ | D87: % | E87: =Source!BZ47 -> 90 | I87: =SUM(Q82:Q86) -> 69.35 | J87: =Source!AT47 -> 90 | K87: =SUM(R82:R86) -> 3813.28
C88: СП от ФОТ | D88: % | E88: =Source!CA47 -> 46 | I88: =SUM(S82:S87) -> 35.44 | J88: =Source!AU47 -> 46 | K88: =SUM(T82:T87) -> 1949.01
C89: ЗТР | D89: чел-ч | E89: =Source!AQ46 -> 5 | G89: =Source!DI46 -> *1,1 | H89: =Source!AV47 -> 1.047 | I89: =Source!U46 -> 5.7585
C90: ВСЕГО работ по позиции: | H90: =I83+I84+I85+I87+I88+SUM(I86:I86)-SUMIF(AC86:AC86, 5, I86:I86)-SUMIF(AC86:AC86, 6, I86:I86) -> 184.63 | J90: =K83+K84+K85+K87+K88+SUM(K86:K86)-SUMIF(AC86:AC86, 5, K86:K86)-SUMIF(AC86:AC86, 6, K86:K86) -> 10002.74
C91: ВСЕГО оборудование по позиции: | H91: =SUMIF(AC86:AC86, 5, I86:I86)+SUMIF(AC86:AC86, 6, I86:I86) -> 9139.9 | J91: =SUMIF(AC86:AC86, 5, K86:K86)+SUMIF(AC86:AC86, 6, K86:K86) -> 70011.63
C92: ВСЕГО по позиции: | H92: =I83+I84+I85+I87+I88+SUM(I86:I86) -> 9324.53 | J92: =K83+K84+K85+K87+K88+SUM(K86:K86) -> 80014.37 | O92: =I83+I84+I85+I87+I88+SUM(I86:I86) -> 9324.53 | P92: =K83+K84+K85+K87+K88+SUM(K86:K86) -> 80014.37
A94: 6 | B94: 4.10-177-1 Поправка: Гл.12.Прил.8.п.8. 5_12.00.01.11.003 | C94: Монтаж устройства связи с согласующим устройством (вызывная панель) | D94: =Source!H50 -> 10 шт. | E94: =Source!I50 -> 1.7 | Q94: =Source!X50 -> 402.11 | R94: =Source!X51 -> 22112.09 | S94: =Source!Y50 -> 205.52 | T94: =Source!Y51 -> 11301.74 | U94: =ROUND((175/100)*ROUND(Source!R50, 2), 2) -> 2.61 | V94: =ROUND((0/100)*ROUND(Source!R51, 2), 2) -> 0 | AC94: 0
C95: ="Объем: "&Source!I50&"=17/"&"10" -> Объем: 1,7=17/10
C96: ЗП | F96: =Source!AO50 -> 227.44 | G96: =Source!DG50 -> *1,1 | H96: =Source!AV51 -> 1.047 | I96: =Source!S50 -> 445.3 | J96: =IF(Source!BA51<> 0, Source!BA51, 1) -> 54.99 | K96: =Source!S51 -> 24487.05
C97: ЭМ | F97: =Source!AM50 -> 6.07 | G97: =Source!DE50 -> *1,1 | H97: =Source!AV51 -> 1.047 | I97: =Source!Q50 -> 11.88 | J97: =IF(Source!BB51<> 0, Source!BB51, 1) -> 14.94 | K97: =Source!Q51 -> 177.49
C98: в т.ч. ЗПМ | F98: =Source!AN50 -> 0.76 | G98: =Source!DF50 -> *1,1 | H98: =Source!AV51 -> 1.047 | I98: =Source!R50 -> 1.49 | J98: =IF(Source!BS51<> 0, Source!BS51, 1) -> 54.99 | K98: =Source!R51 -> 81.94
C99: МР | F99: =Source!AL50 -> 2.44 | G99: =Source!DD50 | H99: =Source!AW51 -> 1 | I99: =Source!P50 -> 4.15 | J99: =IF(Source!BC51<> 0, Source!BC51, 1) -> 7.23 | K99: =Source!P51 -> 30
A100: 6,1 | B100: =Source!F52 -> КА 7 | C100: ОБОРУДОВАНИЕ:_x000D_ Абонентское вызывное устройство Тромбон АВУ 3 340,83 = [29 461 / 1,2 / 7,66] + 3% Трансп + 1,2% Заг.скл | D100: =Source!H52 -> шт. | E100: =Source!I52 -> 17 | F100: =Source!AK52 -> 3340.83 | H100: =Source!AW53 -> 1 | I100: =Source!O52 -> 56794.11 | J100: =IF(Source!BC53<> 0, Source!BC53, 1) -> 7.66 | K100: =Source!O53 -> 435042.88 | Q100: =Source!X52 -> 0 | R100: =Source!X53 -> 0 | S100: =Source!Y52 -> 0 | T100: =Source!Y53 -> 0 | U100: =ROUND((175/100)*ROUND(Source!R52, 2), 2) -> 0 | V100: =ROUND((0/100)*ROUND(Source!R53, 2), 2) -> 0 | AC100: 5
C101: НР от ФОТ | D101: % | E101: =Source!BZ51 -> 90 | I101: =SUM(Q94:Q100) -> 402.11 | J101: =Source!AT51 -> 90 | K101: =SUM(R94:R100) -> 22112.09
C102: СП от ФОТ | D102: % | E102: =Source!CA51 -> 46 | I102: =SUM(S94:S101) -> 205.52 | J102: =Source!AU51 -> 46 | K102: =SUM(T94:T101) -> 11301.74
C103: ЗТР | D103: чел-ч | E103: =Source!AQ50 -> 14.64 | G103: =Source!DI50 -> *1,1 | H103: =Source!AV51 -> 1.047 | I103: =Source!U50 -> 28.66351
C104: ВСЕГО работ по позиции: | H104: =I96+I97+I99+I101+I102+SUM(I100:I100)-SUMIF(AC100:AC100, 5, I100:I100)-SUMIF(AC100:AC100, 6, I100:I100) -> 1068.96 | J104: =K96+K97+K99+K101+K102+SUM(K100:K100)-SUMIF(AC100:AC100, 5, K100:K100)-SUMIF(AC100:AC100, 6, K100:K100) -> 58108.37
C105: ВСЕГО оборудование по позиции: | H105: =SUMIF(AC100:AC100, 5, I100:I100)+SUMIF(AC100:AC100, 6, I100:I100) -> 56794.11 | J105: =SUMIF(AC100:AC100, 5, K100:K100)+SUMIF(AC100:AC100, 6, K100:K100) -> 435042.88
C106: ВСЕГО по позиции: | H106: =I96+I97+I99+I101+I102+SUM(I100:I100) -> 57863.07 | J106: =K96+K97+K99+K101+K102+SUM(K100:K100) -> 493151.25 | O106: =I96+I97+I99+I101+I102+SUM(I100:I100) -> 57863.07 | P106: =K96+K97+K99+K101+K102+SUM(K100:K100) -> 493151.25
A108: 7 | B108: 4.10-151-1 Поправка: Гл.12.Прил.8.п.8. 5_12.00.01.11.003 | C108: Установка пульта или табло вызывной сигнализации с количеством сигналов до 5 | D108: =Source!H54 -> 1 ШТ. | E108: =Source!I54 -> 1 | Q108: =Source!X54 -> 47.48 | R108: =Source!X55 -> 2610.65 | S108: =Source!Y54 -> 24.27 | T108: =Source!Y55 -> 1334.33 | U108: =ROUND((175/100)*ROUND(Source!R54, 2), 2) -> 0 | V108: =ROUND((0/100)*ROUND(Source!R55, 2), 2) -> 0 | AC108: 0
C109: ЗП | F109: =Source!AO54 -> 45.8 | G109: =Source!DG54 -> *1,1 | H109: =Source!AV55 -> 1.047 | I109: =Source!S54 -> 52.75 | J109: =IF(Source!BA55<> 0, Source!BA55, 1) -> 54.99 | K109: =Source!S55 -> 2900.72
C110: ЭМ | F110: =Source!AM54 -> 0.08 | G110: =Source!DE54 -> *1,1 | H110: =Source!AV55 -> 1.047 | I110: =Source!Q54 -> 0.09 | J110: =IF(Source!BB55<> 0, Source!BB55, 1) -> 8.63 | K110: =Source!Q55 -> 0.78
C111: МР | F111: =Source!AL54 -> 1.78 | G111: =Source!DD54 | H111: =Source!AW55 -> 1 | I111: =Source!P54 -> 1.78 | J111: =IF(Source!BC55<> 0, Source!BC55, 1) -> 0.9 | K111: =Source!P55 -> 1.6
A112: 7,1 | B112: =Source!F56 -> КА 8 | C112: ОБОРУДОВАНИЕ:_x000D_ Светозвуковое табло Тромбон ИСТ 1 273,69 = [11 232 / 1,2 / 7,66] + 3% Трансп + 1,2% Заг.скл | D112: =Source!H56 -> шт. | E112: =Source!I56 -> 1 | F112: =Source!AK56 -> 1273.69 | H112: =Source!AW57 -> 1 | I112: =Source!O56 -> 1273.69 | J112: =IF(Source!BC57<> 0, Source!BC57, 1) -> 7.66 | K112: =Source!O57 -> 9756.47 | Q112: =Source!X56 -> 0 | R112: =Source!X57 -> 0 | S112: =Source!Y56 -> 0 | T112: =Source!Y57 -> 0 | U112: =ROUND((175/100)*ROUND(Source!R56, 2), 2) -> 0 | V112: =ROUND((0/100)*ROUND(Source!R57, 2), 2) -> 0 | AC112: 5
...

Sheet Ведомость объемов работ
A1: =Source!B1 -> Smeta.RU (495) 974-1589
E3: "УТВЕРЖДАЮ"
D5: ___________________________
D7: ___________________________
D9: " ___ " ___________ 20 ___ г.
B12: =CONCATENATE("Ведомость объемов работ ", IF(Source!AN15<>"", Source!AN15," ")) -> Ведомость объемов работ
B13: =CONCATENATE(Source!F12, " ", Source!G12) -> 02-01-17 02-01-17 СДС
A16: № п/п | B16: № в ЛСР | C16: Наименование работ и затрат | D16: Единица измерения | E16: Количество | F16: Ссылка на чертежи, спецификации | G16: Формула расчета, расчет объемов работ и расхода материалов | H16: Примечание
A17: 1 | B17: 2 | C17: 3 | D17: 4 | E17: 5 | F17: 6 | G17: 7 | H17: 8
A18: =CONCATENATE("Локальная смета: ", Source!G20) -> Локальная смета: Система двусторонней связи
A19: =CONCATENATE("Раздел: ", Source!G24) -> Раздел: Оборудование
A20: 1 | B20: =Source!E28 -> 1 | C20: =Source!G28 -> Монтаж домового регистратора | D20: 1 ШТ. | E20: =Source!I28 -> 1 | F20: =Source!U24 | G20: =Source!I28 -> 1
A21: 1.1 | B21: =Source!E30 -> 1,1 | C21: =Source!G30 -> Монитор видеодомофона Модус-Н Vizit-M406 | D21: шт. | E21: =Source!I30 -> 1 | F21: =Source!U24
A22: 2 | B22: =Source!E32 -> 2 | C22: =Source!G32 -> Монтаж устройства связи с согласующим устройством (вызывная панель) | D22: 10 шт. | E22: =Source!I32 -> 0.1 | F22: =Source!U24 | G22: ="=1/"&"10" -> =1/10
A23: 2.1 | B23: =Source!E34 -> 2,1 | C23: =Source!G34 -> Вызывная панель Activision AVC-305 | D23: шт. | E23: =Source!I34 -> 1 | F23: =Source!U24
A24: 3 | B24: =Source!E36 -> 3 | C24: =Source!G36 -> Монтаж конструкции для установки приборов и средств автоматизации массой до 5 кг | D24: 1 ШТ. | E24: =Source!I36 -> 1 | F24: =Source!U24 | G24: =Source!I36 -> 1
A25: 3.1 | B25: =Source!E38 -> 3,1 | C25: =Source!G38 -> Стойка для вызывной панели AR-GO STS-03 | D25: шт. | E25: =Source!I38 -> 1 | F25: =Source!U24
A26: 4 | B26: =Source!E40 -> 4 | C26: =Source!G40 -> Сигнализация дистанционная, блок оконечный | D26: 1 ШТ. | E26: =Source!I40 -> 1 | F26: =Source!U24 | G26: =Source!I40 -> 1
A27: 4.1 | B27: =Source!E42 -> 4,1 | C27: =Source!G42 -> Локальный блок связи Тромбон ЛБС | D27: шт. | E27: =Source!I42 -> 1 | F27: =Source!U24
A28: 4.2 | B28: =Source!E44 -> 4,2 | C28: =Source!G44 -> Батарея аккумуляторная, емкость 7 А·ч, напряжение 12 В | D28: шт. | E28: =Source!I44 -> 2 | F28: =Source!U24
A29: 5 | B29: =Source!E46 -> 5 | C29: =Source!G46 -> Установка пульта или табло вызывной сигнализации с количеством сигналов до 10 | D29: 1 ШТ. | E29: =Source!I46 -> 1 | F29: =Source!U24 | G29: =Source!I46 -> 1
A30: 5.1 | B30: =Source!E48 -> 5,1 | C30: =Source!G48 -> Пульт диспетчера Тромбон ПД | D30: шт. | E30: =Source!I48 -> 1 | F30: =Source!U24
A31: 6 | B31: =Source!E50 -> 6 | C31: =Source!G50 -> Монтаж устройства связи с согласующим устройством (вызывная панель) | D31: 10 шт. | E31: =Source!I50 -> 1.7 | F31: =Source!U24 | G31: ="=17/"&"10" -> =17/10
A32: 6.1 | B32: =Source!E52 -> 6,1 | C32: =Source!G52 -> Абонентское вызывное устройство Тромбон АВУ | D32: шт. | E32: =Source!I52 -> 17 | F32: =Source!U24
A33: 7 | B33: =Source!E54 -> 7 | C33: =Source!G54 -> Установка пульта или табло вызывной сигнализации с количеством сигналов до 5 | D33: 1 ШТ. | E33: =Source!I54 -> 1 | F33: =Source!U24 | G33: =Source!I54 -> 1
A34: 7.1 | B34: =Source!E56 -> 7,1 | C34: =Source!G56 -> Светозвуковое табло Тромбон ИСТ | D34: шт. | E34: =Source!I56 -> 1 | F34: =Source!U24
A35: 8 | B35: =Source!E58 -> 8 | C35: =Source!G58 -> Монтаж ключа или кнопки на панели | D35: 1 ШТ. | E35: =Source!I58 -> 1 | F35: =Source!U24 | G35: =Source!I58 -> 1
A36: 8.1 | B36: =Source!E60 -> 8,1 | C36: =Source!G60 -> Устройство вызов/сброс Тромбон-ВС-С | D36: шт. | E36: =Source!I60 -> 1 | F36: =Source!U24
A37: =CONCATENATE("Раздел: ", Source!G93) -> Раздел: Кабельные изделия и материалы
A38: 9 | B38: =Source!E97 -> 9 | C38: =Source!G97 -> Прокладка кабеля связи симметричного для цифровых систем передачи в трубах гофрированных: по бетонным и кирпичным поверхностям стен и потолка | D38: 100 м | E38: =Source!I97 -> 3.35 | F38: =Source!U93 | G38: ="=(35+"&"300)/"&"100" -> =(35+300)/100
A39: 9.1 | B39: =Source!E99 -> 9,1 | C39: =Source!G99 -> Трубы из непластифицированного вторичного ПВХ, гладкие, самозатухающие, усиленного типа, наружный диаметр 20 мм, толщина стенки 1,5 мм, для электропроводок | D39: м | E39: =Source!I99 -> 35.7 | F39: =Source!U93
A40: 9.2 | B40: =Source!E101 -> 9,2 | C40: =Source!G101 -> Трубы из непластифицированного вторичного ПВХ, гладкие, самозатухающие, усиленного типа, наружный диаметр 25 мм, толщина стенки 1,5 мм, для электропроводок | D40: м | E40: =Source!I101 -> 306 | F40: =Source!U93
A41: 9.3 | B41: =Source!E103 -> 9,3 | C41: =Source!G103 -> Держатель пластиковый с защелкой для крепления труб, рукавов и гибких вводов диаметром 20 мм | D41: 100 шт. | E41: =Source!I103 -> 1 | F41: =Source!U93
A42: 9.4 | B42: =Source!E105 -> 9,4 | C42: =Source!G105 -> Держатель пластиковый с защелкой для крепления труб, рукавов и гибких вводов диаметром 25 мм | D42: 100 шт. | E42: =Source!I105 -> 2 | F42: =Source!U93
A43: 9.5 | B43: =Source!E107 -> 9,5 | C43: =Source!G107 -> Кабель U/UTP Cat5e PVCLSнг(А)-LSLTx 2х2х0,52 мм | D43: км | E43: =Source!I107 -> 0.0357 | F43: =Source!U93
A44: 9.6 | B44: =Source!E109 -> 9,6 | C44: =Source!G109 -> Кабель КИС-РВнг(А)-LSLTx 4х2х0,64 мм | D44: км | E44: =Source!I109 -> 0.0357 | F44: =Source!U93
A45: 9.7 | B45: =Source!E111 -> 9,7 | C45: =Source!G111 -> Кабель КИС-РВнг(А)-LSLTx 2х2х0,64 мм | D45: км | E45: =Source!I111 -> 0.9129 | F45: =Source!U93
A46: 9.8 | B46: =Source!E113 -> 9,8 | C46: =Source!G113 -> Кабель КСПЭнг(А)-LSLTx 2х2х0,5 мм | D46: км | E46: =Source!I113 -> 0.0153 | F46: =Source!U93
C49: Главный инженер проекта _________________ | D49: =IF(Source!X12<>"", Source!X12," ")
C51: Составил _________________ | D51: =IF(Source!AB12<>"", Source!AB12," ") -> Лукьянова А.Л.

Sheet Source
A1: 0 | B1: Smeta.RU (495) 974-1589 | D1: _PS_ | F1: 0 | G1: 0 | H1: 0 | I1: Smeta.RU | K1: 1 | L1: 74562 | M1: 10 | N1: 12 | O1: 0 | P1: 0 | Q1: 3
A4: 1 | B4: 1 | C4: -1 | G4: Капитальный ремонт здания Государственного бюджетного общеобразовательного учреждения города Москвы «Школа № 236» по адресу: г. Москва, ул. Клязьминская, д. 7, к. 4. I этап | EC4: 0
A12: 1 | B12: 241 | C12: 0 | D12: =ROW(A202) -> 202 | E12: 0 | F12: 02-01-17 | G12: 02-01-17 СДС | I12: 0 | J12: 2024-00272-01-0-ИОС5.10 | K12: 0 | L12: 0 | M12: 4098 | O12: 0 | P12: 0 | Q12: 0 | R12: 0 | S12: 0 | T12: 1 | V12: 0 | AB12: Лукьянова А.Л. | BB12: 0 | BH12: Сметные нормы списания | BI12: Коды ОКП для ТСН-2001 МГЭ Дополнение 80 | BJ12: 1 | BK12: 1 | BL12: 0 | BM12: 0 | BN12: 1 | BO12: 0 | BP12: 6 | BQ12: 2 | BR12: 1 | BS12: 1 | BT12: 1 | BU12: 0 | BV12: 1 | BW12: 0 | BX12: 0 | BY12: ТСН-2001 (МГЭ) Доп 80 - Новое строительство | BZ12: Типовой расчет для ТСН-2001 МГЭ, Дополнение 80, строительство | CA12: Территориальные сметные нормативы для Москвы ТСН-2001 (МГЭ), дополнение 80 | CB12: Территориальные сметные нормативы для Москвы ТСН-2001 (МГЭ), дополнение 80 | CC12: Территориальные сметные нормативы для Москвы ТСН-2001 (МГЭ), дополнение 80 | CD12: Территориальные сметные нормативы для Москвы ТСН-2001 (МГЭ), дополнение 80 | CE12: Поправки для ТСН-2001 от 03.02.2026 г. доп.80 | CF12: 0 | CG12: 0 | CH12: 8202 | CK12: 80 | CQ12: Территориальные сметные нормативы для Москвы (ТСН-2001) | CR12: ТЕР | CS12: 41660 | CT12: 1 | CU12: 80 | CY12: 0 | EC12: 0
A15: 15 | B15: 1
A18: 52 | B18: =B202 -> 241 | C18: =C202 -> 1 | D18: =D202 -> 12 | E18: =E202 -> 0 | F18: =F202 -> 02-01-17 | G18: =G202 -> 02-01-17 СДС | O18: =O202 -> 113436.02 | P18: =P202 -> 111647.04 | Q18: =Q202 -> 26.69 | R18: =R202 -> 3.15 | S18: =S202 -> 1762.29 | T18: =T202 -> 0 | U18: =U202 -> 136.29448 | V18: =V202 -> 0 | ... GX18: =GX202 -> 0
A20: 3 | B20: 1 | D20: =ROW(A172) -> 172 | F20: 02-01-17 | G20: Система двусторонней связи | I20: 0 | J20: 2024-00272-01-0-ИОС5.10 | K20: -1 | L20: 02-01-17 | S20: 0 | T20: 0 | V20: 0 | AB20: Лукьянова А.Л. | BX20: 0 | CF20: 0 | CG20: 0
A22: 52 | B22: =B172 -> 1 | C22: =C172 -> 3 | D22: =D172 -> 20 | E22: =E172 -> 0 | F22: =F172 -> 02-01-17 | G22: =G172 -> Система двусторонней связи | O22: =O172 -> 113436.02 | P22: =P172 -> 111647.04 | Q22: =Q172 -> 26.69 | R22: =R172 -> 3.15 | S22: =S172 -> 1762.29 | T22: =T172 -> 0 | U22: =U172 -> 136.29448 | V22: =V172 -> 0 | ... GX22: =GX172 -> 0
A24: 4 | B24: 1 | D24: =ROW(A63) -> 63 | G24: Оборудование | I24: 0 | K24: -1 | S24: 0 | T24: 0 | V24: 0 | BX24: 0 | CJ24: 0
A26: 52 | B26: =B63 -> 1 | C26: =C63 -> 4 | D26: =D63 -> 24 | E26: =E63 -> 0 | F26: =F63 | G26: =G63 -> Оборудование | O26: =O63 -> 83527.43 | P26: =P63 -> 82506.26 | Q26: =Q63 -> 20.02 | R26: =R63 -> 3.15 | S26: =S63 -> 1001.15 | T26: =T63 -> 0 | U26: =U63 -> 72.248444 | V26: =V63 -> 0 | ... GX26: =GX63 -> 0
A28: 17 | B28: 1 | D28: =ROW(EtalonRes!A6) -> 6 | E28: 1 | F28: 4.10-175-1 | G28: Монтаж домового регистратора | H28: 1 ШТ. | I28: 1 | J28: 0 | K28: 1 | O28: =ROUND(CP28,2) -> 26.03 | P28: =ROUND((ROUND((AC28*AW28*I28),2)*BC28),2) -> 1.22 | Q28: =(ROUND((ROUND((((ET28*1.1))*AV28*I28),2)*BB28),2)+ROUND((ROUND(((AE28-((EU28*1.1)))*AV28*I28),2)*BS28),2)) -> 1.05 | R28: =ROUND((ROUND((AE28*AV28*I28),2)*BS28),2) -> 0.15 | S28: =ROUND((ROUND((AF28*AV28*I28),2)*BA28),2) -> 23.76 | T28: =ROUND(CU28*I28,2) -> 0 | U28: =CV28*I28 -> 1.554795 | V28: =CW28*I28 -> 0 | W28: =ROUND(CX28*I28,2) -> 0 | X28: =ROUND(CY28,2) -> 21.52 | Y28: =ROUND(CZ28,2) -> 11 | AA28: 56511233 | AB28: =ROUND((AC28+AD28+AF28),6) -> 24.914 | AC28: =ROUND((ES28),6) -> 1.22 | AD28: =ROUND(((((ET28*1.1))-((EU28*1.1)))+AE28),6) -> 1.001 | AE28: =ROUND(((EU28*1.1)),6) -> 0.143 | AF28: =ROUND(((EV28*1.1)),6) -> 22.693 | AG28: =ROUND((AP28),6) -> 0 | AH28: =((EW28*1.1)) -> 1.485 | AI28: =((EX28*1.1)) -> 0 | AJ28: =(AS28) -> 0 | AK28: 22.76 | AL28: 1.22 | AM28: 0.91 | AN28: 0.13 | AO28: 20.63 | AP28: 0 | AQ28: 1.35 | AR28: 0 | AS28: 0 | AT28: 90 | AU28: 46 | AV28: 1.047 | AW28: 1 | AZ28: 1 | BA28: 1 | BB28: 1 | BC28: 1 | BH28: 0 | BI28: 2 | BJ28: ТСН-2001.4 Доп. 80, Сб. 10, т. 175, поз. 1 | BM28: 68 | BN28: 0 | BO28: 4.10-175-1 | BP28: 1 | BQ28: 40 | BR28: 0 | BS28: 1 | BT28: 1 | BU28: 1 | BV28: 1 | BW28: 1 | BX28: 1 | BZ28: 90 | CA28: 46 | CE28: 30 | CF28: 0 | CG28: 0 | CM28: 0 | CO28: 0 | CP28: =(P28+Q28+S28) -> 26.03 | CQ28: =ROUND((ROUND((AC28*AW28*1),2)*BC28),2) -> 1.22 | CR28: =(ROUND((ROUND((((ET28*1.1))*AV28*1),2)*BB28),2)+ROUND((ROUND(((AE28-((EU28*1.1)))*AV28*1),2)*BS28),2)) -> 1.05 | CS28: =ROUND((ROUND((AE28*AV28*1),2)*BS28),2) -> 0.15 | CT28: =ROUND((ROUND((AF28*AV28*1),2)*BA28),2) -> 23.76 | CU28: =AG28 -> 0 | CV28: =(AH28*AV28) -> 1.554795 | CW28: =AI28 -> 0 | CX28: =AJ28 -> 0 | CY28: =(((S28+R28)*AT28)/100) -> 21.519 | CZ28: =(((S28+R28)*AU28)/100) -> 10.9986 | DE28: *1,1 | DF28: *1,1 | DG28: *1,1 | DI28: *1,1 | DJ28: *1,1 | DN28: 0 | DO28: 0 | DP28: 1 | DQ28: 1 | DU28: 1013 | DV28: 1 ШТ. | DW28: 1 ШТ. | DX28: 1 | EE28: 58162630 | EF28: 40 | EG28: Монтаж оборудования | EH28: 0 | EJ28: 2 | EK28: 68 | EL28: ТСН-2001.4-10. Прокладка и монтаж сетей связи | EM28: ТСН-2001.4-10-1 | EO28: Поправка: Гл.12.Прил.8.п.8. 5_12.00.01.11.003 | EQ28: 0 | ER28: 22.76 | ES28: 1.22 | ET28: 0.91 | EU28: 0.13 | EV28: 20.63 | EW28: 1.35 | EX28: 0 | EY28: 0 | FQ28: 0 | FR28: 0 | FS28: 0 | FX28: 90 | FY28: 46 | GD28: 1 | GF28: 1735237289 | GG28: 2 | GH28: 1 | GI28: 2 | GJ28: 0 | GK28: 0 | GL28: =ROUND(IF(AND(BH28=3,BI28=3,FS28<>0),P28,0),2) -> 0 | GM28: =ROUND(O28+X28+Y28,2)+GX28 -> 58.55 | GN28: =IF(OR(BI28=0,BI28=1),GM28-GX28,0) -> 0 | GO28: =IF(BI28=2,GM28-GX28,0) -> 58.55 | GP28: =IF(BI28=4,GM28-GX28,0) -> 0 | GR28: 0 | GS28: 3 | GT28: 0 | GV28: =ROUND((GT28),6) -> 0 | GW28: 1 | GX28: =ROUND(HC28*I28,2) -> 0 | HA28: 0 | HB28: 0 | HC28: =GV28*GW28 -> 0 | HS28: 0 | IK28: 0
A29: 17 | B29: 1 | D29: =ROW(EtalonRes!A12) -> 12 | E29: 1 | F29: 4.10-175-1 | G29: Монтаж домового регистратора | H29: 1 ШТ. | I29: 1 | J29: 0 | K29: 1 | O29: =ROUND(CP29,2) -> 1354.12 | P29: =ROUND((ROUND((AC29*AW29*I29),2)*BC29),2) -> 31.13 | Q29: =(ROUND((ROUND((((ET29*1.1))*AV29*I29),2)*BB29),2)+ROUND((ROUND(((AE29-((EU29*1.1)))*AV29*I29),2)*BS29),2)) -> 16.43 | R29: =ROUND((ROUND((AE29*AV29*I29),2)*BS29),2) -> 8.25 | S29: =ROUND((ROUND((AF29*AV29*I29),2)*BA29),2) -> 1306.56 | T29: =ROUND(CU29*I29,2) -> 0 | U29: =CV29*I29 -> 1.554795 | V29: =CW29*I29 -> 0 | W29: =ROUND(CX29*I29,2) -> 0 | X29: =ROUND(CY29,2) -> 1183.33 | Y29: =ROUND(CZ29,2) -> 604.81 | AA29: 56511235 | AB29: =ROUND((AC29+AD29+AF29),6) -> 24.914 | AC29: =ROUND((ES29),6) -> 1.22 | AD29: =ROUND(((((ET29*1.1))-((EU29*1.1)))+AE29),6) -> 1.001 | AE29: =ROUND(((EU29*1.1)),6) -> 0.143 | AF29: =ROUND(((EV29*1.1)),6) -> 22.693 | AG29: =ROUND((AP29),6) -> 0 | AH29: =((EW29*1.1)) -> 1.485 | AI29: =((EX29*1.1)) -> 0 | AJ29: =(AS29) -> 0 | AK29: 22.76 | AL29: 1.22 | AM29: 0.91 | AN29: 0.13 | AO29: 20.63 | AP29: 0 | AQ29: 1.35 | AR29: 0 | AS29: 0 | AT29: 90 | AU29: 46 | AV29: 1.047 | AW29: 1 | AZ29: 1 | BA29: 54.99 | BB29: 15.65 | BC29: 25.52 | BH29: 0 | BI29: 2 | BJ29: ТСН-2001.4 Доп. 80, Сб. 10, т. 175, поз. 1 | BM29: 68 | BN29: 0 | BO29: 4.10-175-1 | BP29: 1 | BQ29: 40 | BR29: 0 | BS29: 54.99 | BT29: 1 | BU29: 1 | BV29: 1 | BW29: 1 | BX29: 1 | BZ29: 90 | CA29: 46 | CE29: 30 | CF29: 0 | CG29: 0 | CM29: 0 | CO29: 0 | CP29: =(P29+Q29+S29) -> 1354.12 | CQ29: =ROUND((ROUND((AC29*AW29*1),2)*BC29),2) -> 31.13 | CR29: =(ROUND((ROUND((((ET29*1.1))*AV29*1),2)*BB29),2)+ROUND((ROUND(((AE29-((EU29*1.1)))*AV29*1),2)*BS29),2)) -> 16.43 | CS29: =ROUND((ROUND((AE29*AV29*1),2)*BS29),2) -> 8.25 | CT29: =ROUND((ROUND((AF29*AV29*1),2)*BA29),2) -> 1306.56 | CU29: =AG29 -> 0 | CV29: =(AH29*AV29) -> 1.554795 | CW29: =AI29 -> 0 | CX29: =AJ29 -> 0 | CY29: =(((S29+R29)*AT29)/100) -> 1183.329 | CZ29: =(((S29+R29)*AU29)/100) -> 604.8126 | DE29: *1,1 | DF29: *1,1 | DG29: *1,1 | DI29: *1,1 | DJ29: *1,1 | DN29: 0 | DO29: 0 | DP29: 1 | DQ29: 1 | DU29: 1013 | DV29: 1 ШТ. | DW29: 1 ШТ. | DX29: 1 | EE29: 58162630 | EF29: 40 | EG29: Монтаж оборудования | EH29: 0 | EJ29: 2 | EK29: 68 | EL29: ТСН-2001.4-10. Прокладка и монтаж сетей связи | EM29: ТСН-2001.4-10-1 | EO29: Поправка: Гл.12.Прил.8.п.8. 5_12.00.01.11.003 | EQ29: 0 | ER29: 22.76 | ES29: 1.22 | ET29: 0.91 | EU29: 0.13 | EV29: 20.63 | EW29: 1.35 | EX29: 0 | EY29: 0 | FQ29: 0 | FR29: 0 | FS29: 0 | FX29: 90 | FY29: 46 | GD29: 1 | GF29: 1735237289 | GG29: 2 | GH29: 1 | GI29: 2 | GJ29: 0 | GK29: 0 | GL29: =ROUND(IF(AND(BH29=3,BI29=3,FS29<>0),P29,0),2) -> 0 | GM29: =ROUND(O29+X29+Y29,2)+GX29 -> 3142.26 | GN29: =IF(OR(BI29=0,BI29=1),GM29-GX29,0) -> 0 | GO29: =IF(BI29=2,GM29-GX29,0) -> 3142.26 | GP29: =IF(BI29=4,GM29-GX29,0) -> 0 | GR29: 0 | GS29: 3 | GT29: 0 | GV29: =ROUND((GT29),6) -> 0 | GW29: 1 | GX29: =ROUND(HC29*I29,2) -> 0 | HA29: 0 | HB29: 0 | HC29: =GV29*GW29 -> 0 | HS29: 0 | IK29: 0
A30: 18 | B30: 1 | E30: 1,1 | F30: КА 1 | G30: Монитор видеодомофона Модус-Н Vizit-M406 | H30: шт. | I30: =I28*J30 -> 1 | J30: 1 | K30: 1 | O30: =ROUND(CP30,2) -> 1062.54 | P30: =ROUND((ROUND((AC30*I30),2)*BC30),2) -> 1062.54 | Q30: =(ROUND((ROUND(((ET30)*AV30*I30),2)*BB30),2)+ROUND((ROUND(((AE30-(EU30))*AV30*I30),2)*BS30),2)) -> 0 | R30: =ROUND((ROUND((AE30*AV30*I30),2)*BS30),2) -> 0 | S30: =ROUND((ROUND((AF30*AV30*I30),2)*BA30),2) -> 0 | T30: =ROUND(CU30*I30,2) -> 0 | U30: =CV30*I30 -> 0 | V30: =CW30*I30 -> 0 | W30: =ROUND(CX30*I30,2) -> 0 | X30: =ROUND(CY30,2) -> 0 | Y30: =ROUND(CZ30,2) -> 0 | AA30: 56511233 | AB30: =ROUND((AC30+AD30+AF30),6) -> 1062.54 | AC30: =ROUND((ES30),6) -> 1062.54 | AD30: =ROUND((((ET30)-(EU30))+AE30),6) -> 0 | AE30: =ROUND((EU30),6) -> 0 | AF30: =ROUND((EV30),6) -> 0 | AG30: =ROUND((AP30),6) -> 0 | AH30: =(EW30) -> 0 | AI30: =(EX30) -> 0 | AJ30: =(AS30) -> 0 | AK30: 1062.54 | AL30: 1062.54 | AM30: 0 | AN30: 0 | AO30: 0 | AP30: 0 | AQ30: 0 | AR30: 0 | AS30: 0 | AT30: 0 | AU30: 0 | AV30: 1 | AW30: 1 | AZ30: 1 | BA30: 1 | BB30: 1 | BC30: 1 | BH30: 3 | BI30: 3 | BM30: 746 | BN30: 0 | BP30: 0 | BQ30: 130 | BR30: 0 | BS30: 1 | BT30: 1 | BU30: 1 | BV30: 1 | BW30: 1 | BX30: 1 | BZ30: 90 | CA30: 46 | CE30: 30 | CF30: 0 | CG30: 0 | CM30: 0 | CO30: 0 | CP30: =(P30+Q30+S30) -> 1062.54 | CQ30: =ROUND((ROUND((AC30*1),2)*BC30),2) -> 1062.54 | CR30: =(ROUND((ROUND(((ET30)*AV30*1),2)*BB30),2)+ROUND((ROUND(((AE30-(EU30))*AV30*1),2)*BS30),2)) -> 0 | CS30: =ROUND((ROUND((AE30*AV30*1),2)*BS30),2) -> 0 | CT30: =ROUND((ROUND((AF30*AV30*1),2)*BA30),2) -> 0 | CU30: =AG30 -> 0 | CV30: =(AH30*AV30) -> 0 | CW30: =AI30 -> 0 | CX30: =AJ30 -> 0 | CY30: =(((S30+R30)*AT30)/100) -> 0 | CZ30: =(((S30+R30)*AU30)/100) -> 0 | DN30: 0 | DO30: 0 | DP30: 1 | DQ30: 1 | DU30: 1010 | DV30: шт. | DW30: шт. | DX30: 1 | EE30: 58162750 | EF30: 130 | EG30: Сметная стоимость оборудования | EH30: 0 | EJ30: 3 | EK30: 746 | EL30: ТСН-2001.13. Сметная стоимость оборудования | EM30: ТСН-2001.13 | EQ30: 0 | ER30: 0 | ES30: 1062.54 | ET30: 0 | EU30: 0 | EV30: 0 | EW30: 0 | EX30: 0 | FQ30: 0 | FR30: =P30 -> 1062.54 | FS30: 0 | FX30: 90 | FY30: 46 | GA30: [9 370 / 1,2 / 7,66] + 3% Трансп + 1,2% Заг.скл | GD30: 1 | GF30: 975157399 | GG30: 2 | GH30: 4 | GI30: -2 | GJ30: 0 | GK30: 0 | GL30: =ROUND(IF(AND(BH30=3,BI30=3,FS30<>0),P30,0),2) -> 0 | GM30: =ROUND(O30+X30+Y30,2)+GX30 -> 1062.54 | GN30: =IF(OR(BI30=0,BI30=1),GM30-GX30,0) -> 0 | GO30: =IF(BI30=2,GM30-GX30,0) -> 0 | GP30: =IF(BI30=4,GM30-GX30,0) -> 0 | GR30: 0 | GS30: 2 | GT30: 0 | GV30: =ROUND((GT30),6) -> 0 | GW30: 1 | GX30: =ROUND(HC30*I30,2) -> 0 | HA30: 0 | HB30: 0 | HC30: =GV30*GW30 -> 0 | HE30: 3 | HF30: 1,2 | HS30: 0 | IK30: 0
A31: 18 | B31: 1 | E31: 1,1 | F31: КА 1 | G31: Монитор видеодомофона Модус-Н Vizit-M406 | H31: шт. | I31: =I29*J31 -> 1 | J31: 1 | K31: 1 | O31: =ROUND(CP31,2) -> 8139.06 | P31: =ROUND((ROUND((AC31*I31),2)*BC31),2) -> 8139.06 | Q31: =(ROUND((ROUND(((ET31)*AV31*I31),2)*BB31),2)+ROUND((ROUND(((AE31-(EU31))*AV31*I31),2)*BS31),2)) -> 0 | R31: =ROUND((ROUND((AE31*AV31*I31),2)*BS31),2) -> 0 | S31: =ROUND((ROUND((AF31*AV31*I31),2)*BA31),2) -> 0 | T31: =ROUND(CU31*I31,2) -> 0 | U31: =CV31*I31 -> 0 | V31: =CW31*I31 -> 0 | W31: =ROUND(CX31*I31,2) -> 0 | X31: =ROUND(CY31,2) -> 0 | Y31: =ROUND(CZ31,2) -> 0 | AA31: 56511235 | AB31: =ROUND((AC31+AD31+AF31),6) -> 1062.54 | AC31: =ROUND((ES31),6) -> 1062.54 | AD31: =ROUND((((ET31)-(EU31))+AE31),6) -> 0 | AE31: =ROUND((EU31),6) -> 0 | AF31: =ROUND((EV31),6) -> 0 | AG31: =ROUND((AP31),6) -> 0 | AH31: =(EW31) -> 0 | AI31: =(EX31) -> 0 | AJ31: =(AS31) -> 0 | AK31: 1062.54 | AL31: 1062.54 | AM31: 0 | AN31: 0 | AO31: 0 | AP31: 0 | AQ31: 0 | AR31: 0 | AS31: 0 | AT31: 0 | AU31: 0 | AV31: 1 | AW31: 1 | AZ31: 1 | BA31: 1 | BB31: 1 | BC31: 7.66 | BH31: 3 | BI31: 3 | BM31: 746 | BN31: 0 | BP31: 0 | BQ31: 130 | BR31: 0 | BS31: 1 | BT31: 1 | BU31: 1 | BV31: 1 | BW31: 1 | BX31: 1 | BZ31: 90 | CA31: 46 | CE31: 30 | CF31: 0 | CG31: 0 | CM31: 0 | CO31: 0 | CP31: =(P31+Q31+S31) -> 8139.06 | CQ31: =ROUND((ROUND((AC31*1),2)*BC31),2) -> 8139.06 | CR31: =(ROUND((ROUND(((ET31)*AV31*1),2)*BB31),2)+ROUND((ROUND(((AE31-(EU31))*AV31*1),2)*BS31),2)) -> 0 | CS31: =ROUND((ROUND((AE31*AV31*1),2)*BS31),2) -> 0 | CT31: =ROUND((ROUND((AF31*AV31*1),2)*BA31),2) -> 0 | CU31: =AG31 -> 0 | CV31: =(AH31*AV31) -> 0 | CW31: =AI31 -> 0 | CX31: =AJ31 -> 0 | CY31: =(((S31+R31)*AT31)/100) -> 0 | CZ31: =(((S31+R31)*AU31)/100) -> 0 | DN31: 0 | DO31: 0 | DP31: 1 | DQ31: 1 | DU31: 1010 | DV31: шт. | DW31: шт. | DX31: 1 | EE31: 58162750 | EF31: 130 | EG31: Сметная стоимость оборудования | EH31: 0 | EJ31: 3 | EK31: 746 | EL31: ТСН-2001.13. Сметная стоимость оборудования | EM31: ТСН-2001.13 | EQ31: 0 | ER31: 8139.09 | ES31: 1062.54 | ET31: 0 | EU31: 0 | EV31: 0 | EW31: 0 | EX31: 0 | EZ31: 5 | FC31: 1 | FD31: 18 | FF31: 9370 | FQ31: 0 | FR31: =P31 -> 8139.06 | FS31: 0 | FX31: 90 | FY31: 46 | GA31: [9 370 / 1,2 / 7,66] + 3% Трансп + 1,2% Заг.скл | GD31: 1 | GF31: 975157399 | GG31: 2 | GH31: 3 | GI31: 5 | GJ31: 0 | GK31: 0 | GL31: =ROUND(IF(AND(BH31=3,BI31=3,FS31<>0),P31,0),2) -> 0 | GM31: =ROUND(O31+X31+Y31,2)+GX31 -> 8139.06 | GN31: =IF(OR(BI31=0,BI31=1),GM31-GX31,0) -> 0 | GO31: =IF(BI31=2,GM31-GX31,0) -> 0 | GP31: =IF(BI31=4,GM31-GX31,0) -> 0 | GR31: 1 | GS31: 1 | GT31: 0 | GV31: =ROUND((GT31),6) -> 0 | GW31: 1 | GX31: =ROUND(HC31*I31,2) -> 0 | HA31: 0 | HB31: 0 | HC31: =GV31*GW31 -> 0 | HE31: 3 | HF31: 1,2 | HS31: 0 | IK31: 0
A32: 17 | B32: 1 | D32: =ROW(EtalonRes!A18) -> 18 | E32: 2 | F32: 4.10-177-1 | G32: Монтаж устройства связи с согласующим устройством (вызывная панель) | H32: 10 шт. | I32: =ROUND(1/10,9) -> 0.1 | J32: 0 | K32: =ROUND(1/10,9) -> 0.1 | O32: =ROUND(CP32,2) -> 27.13 | P32: =ROUND((ROUND((AC32*AW32*I32),2)*BC32),2) -> 0.24 | Q32: =(ROUND((ROUND((((ET32*1.1))*AV32*I32),2)*BB32),2)+ROUND((ROUND(((AE32-((EU32*1.1)))*AV32*I32),2)*BS32),2)) -> 0.7 | R32: =ROUND((ROUND((AE32*AV32*I32),2)*BS32),2) -> 0.09 | S32: =ROUND((ROUND((AF32*AV32*I32),2)*BA32),2) -> 26.19 | T32: =ROUND(CU32*I32,2) -> 0 | U32: =CV32*I32 -> 1.6860888 | V32: =CW32*I32 -> 0 | W32: =ROUND(CX32*I32,2) -> 0 | X32: =ROUND(CY32,2) -> 23.65 | Y32: =ROUND(CZ32,2) -> 12.09 | AA32: 56511233 | AB32: =ROUND((AC32+AD32+AF32),6) -> 259.301 | AC32: =ROUND((ES32),6) -> 2.44 | AD32: =ROUND(((((ET32*1.1))-((EU32*1.1)))+AE32),6) -> 6.677 | AE32: =ROUND(((EU32*1.1)),6) -> 0.836 | AF32: =ROUND(((EV32*1.1)),6) -> 250.184 | AG32: =ROUND((AP32),6) -> 0 | AH32: =((EW32*1.1)) -> 16.104 | AI32: =((EX32*1.1)) -> 0 | AJ32: =(AS32) -> 0 | AK32: 235.95 | AL32: 2.44 | AM32: 6.07 | AN32: 0.76 | AO32: 227.44 | AP32: 0 | AQ32: 14.64 | AR32: 0 | AS32: 0 | AT32: 90 | AU32: 46 | AV32: 1.047 | AW32: 1 | AZ32: 1 | BA32: 1 | BB32: 1 | BC32: 1 | BH32: 0 | BI32: 2 | BJ32: ТСН-2001.4 Доп. 80, Сб. 10, т. 177, поз. 1 | BM32: 68 | BN32: 0 | BO32: 4.10-177-1 | BP32: 1 | BQ32: 40 | BR32: 0 | BS32: 1 | BT32: 1 | BU32: 1 | BV32: 1 | BW32: 1 | BX32: 1 | BZ32: 90 | CA32: 46 | CE32: 30 | CF32: 0 | CG32: 0 | CM32: 0 | CO32: 0 | CP32: =(P32+Q32+S32) -> 27.13 | CQ32: =ROUND((ROUND((AC32*AW32*1),2)*BC32),2) -> 2.44 | CR32: =(ROUND((ROUND((((ET32*1.1))*AV32*1),2)*BB32),2)+ROUND((ROUND(((AE32-((EU32*1.1)))*AV32*1),2)*BS32),2)) -> 6.99 | CS32: =ROUND((ROUND((AE32*AV32*1),2)*BS32),2) -> 0.88 | CT32: =ROUND((ROUND((AF32*AV32*1),2)*BA32),2) -> 261.94 | CU32: =AG32 -> 0 | CV32: =(AH32*AV32) -> 16.860888 | CW32: =AI32 -> 0 | CX32: =AJ32 -> 0 | CY32: =(((S32+R32)*AT32)/100) -> 23.652 | CZ32: =(((S32+R32)*AU32)/100) -> 12.0888 | DE32: *1,1 | DF32: *1,1 | DG32: *1,1 | DI32: *1,1 | DJ32: *1,1 | DN32: 0 | DO32: 0 | DP32: 1 | DQ32: 1 | DU32: 1010 | DV32: 10 шт. | DW32: 10 шт. | DX32: 10 | EE32: 58162630 | EF32: 40 | EG32: Монтаж оборудования | EH32: 0 | EJ32: 2 | EK32: 68 | EL32: ТСН-2001.4-10. Прокладка и монтаж сетей связи | EM32: ТСН-2001.4-10-1 | EO32: Поправка: Гл.12.Прил.8.п.8. 5_12.00.01.11.003 | EQ32: 0 | ER32: 235.95 | ES32: 2.44 | ET32: 6.07 | EU32: 0.76 | EV32: 227.44 | EW32: 14.64 | EX32: 0 | EY32: 0 | FQ32: 0 | FR32: 0 | FS32: 0 | FX32: 90 | FY32: 46 | GD32: 1 | GF32: -1147212458 | GG32: 2 | GH32: 1 | GI32: 2 | GJ32: 0 | GK32: 0 | GL32: =ROUND(IF(AND(BH32=3,BI32=3,FS32<>0),P32,0),2) -> 0 | GM32: =ROUND(O32+X32+Y32,2)+GX32 -> 62.87 | GN32: =IF(OR(BI32=0,BI32=1),GM32-GX32,0) -> 0 | GO32: =IF(BI32=2,GM32-GX32,0) -> 62.87 | GP32: =IF(BI32=4,GM32-GX32,0) -> 0 | GR32: 0 | GS32: 3 | GT32: 0 | GV32: =ROUND((GT32),6) -> 0 | GW32: 1 | GX32: =ROUND(HC32*I32,2) -> 0 | HA32: 0 | HB32: 0 | HC32: =GV32*GW32 -> 0 | HS32: 0 | IK32: 0
A33: 17 | B33: 1 | D33: =ROW(EtalonRes!A24) -> 24 | E33: 2 | F33: 4.10-177-1 | G33: Монтаж устройства связи с согласующим устройством (вызывная панель) | H33: 10 шт. | I33: =ROUND(1/10,9) -> 0.1 | J33: 0 | K33: =ROUND(1/10,9) -> 0.1 | O33: =ROUND(CP33,2) -> 1452.39 | P33: =ROUND((ROUND((AC33*AW33*I33),2)*BC33),2) -> 1.74 | Q33: =(ROUND((ROUND((((ET33*1.1))*AV33*I33),2)*BB33),2)+ROUND((ROUND(((AE33-((EU33*1.1)))*AV33*I33),2)*BS33),2)) -> 10.46 | R33: =ROUND((ROUND((AE33*AV33*I33),2)*BS33),2) -> 4.95 | S33: =ROUND((ROUND((AF33*AV33*I33),2)*BA33),2) -> 1440.19 | T33: =ROUND(CU33*I33,2) -> 0 | U33: =CV33*I33 -> 1.6860888 | V33: =CW33*I33 -> 0 | W33: =ROUND(CX33*I33,2) -> 0 | X33: =ROUND(CY33,2) -> 1300.63 | Y33: =ROUND(CZ33,2) -> 664.76 | AA33: 56511235 | AB33: =ROUND((AC33+AD33+AF33),6) -> 259.301 | AC33: =ROUND((ES33),6) -> 2.44 | AD33: =ROUND(((((ET33*1.1))-((EU33*1.1)))+AE33),6) -> 6.677 | AE33: =ROUND(((EU33*1.1)),6) -> 0.836 | AF33: =ROUND(((EV33*1.1)),6) -> 250.184 | AG33: =ROUND((AP33),6) -> 0 | AH33: =((EW33*1.1)) -> 16.104 | AI33: =((EX33*1.1)) -> 0 | AJ33: =(AS33) -> 0 | AK33: 235.95 | AL33: 2.44 | AM33: 6.07 | AN33: 0.76 | AO33: 227.44 | AP33: 0 | AQ33: 14.64 | AR33: 0 | AS33: 0 | AT33: 90 | AU33: 46 | AV33: 1.047 | AW33: 1 | AZ33: 1 | BA33: 54.99 | BB33: 14.94 | BC33: 7.23 | BH33: 0 | BI33: 2 | BJ33: ТСН-2001.4 Доп. 80, Сб. 10, т. 177, поз. 1 | BM33: 68 | BN33: 0 | BO33: 4.10-177-1 | BP33: 1 | BQ33: 40 | BR33: 0 | BS33: 54.99 | BT33: 1 | BU33: 1 | BV33: 1 | BW33: 1 | BX33: 1 | BZ33: 90 | CA33: 46 | CE33: 30 | CF33: 0 | CG33: 0 | CM33: 0 | CO33: 0 | CP33: =(P33+Q33+S33) -> 1452.39 | CQ33: =ROUND((ROUND((AC33*AW33*1),2)*BC33),2) -> 17.64 | CR33: =(ROUND((ROUND((((ET33*1.1))*AV33*1),2)*BB33),2)+ROUND((ROUND(((AE33-((EU33*1.1)))*AV33*1),2)*BS33),2)) -> 104.43 | CS33: =ROUND((ROUND((AE33*AV33*1),2)*BS33),2) -> 48.39 | CT33: =ROUND((ROUND((AF33*AV33*1),2)*BA33),2) -> 14404.08 | CU33: =AG33 -> 0 | CV33: =(AH33*AV33) -> 16.860888 | CW33: =AI33 -> 0 | CX33: =AJ33 -> 0 | CY33: =(((S33+R33)*AT33)/100) -> 1300.626 | CZ33: =(((S33+R33)*AU33)/100) -> 664.7644 | DE33: *1,1 | DF33: *1,1 | DG33: *1,1 | DI33: *1,1 | DJ33: *1,1 | DN33: 0 | DO33: 0 | DP33: 1 | DQ33: 1 | DU33: 1010 | DV33: 10 шт. | DW33: 10 шт. | DX33: 10 | EE33: 58162630 | EF33: 40 | EG33: Монтаж оборудования | EH33: 0 | EJ33: 2 | EK33: 68 | EL33: ТСН-2001.4-10. Прокладка и монтаж сетей связи | EM33: ТСН-2001.4-10-1 | EO33: Поправка: Гл.12.Прил.8.п.8. 5_12.00.01.11.003 | EQ33: 0 | ER33: 235.95 | ES33: 2.44 | ET33: 6.07 | EU33: 0.76 | EV33: 227.44 | EW33: 14.64 | EX33: 0 | EY33: 0 | FQ33: 0 | FR33: 0 | FS33: 0 | FX33: 90 | FY33: 46 | GD33: 1 | GF33: -1147212458 | GG33: 2 | GH33: 1 | GI33: 2 | GJ33: 0 | GK33: 0 | GL33: =ROUND(IF(AND(BH33=3,BI33=3,FS33<>0),P33,0),2) -> 0 | GM33: =ROUND(O33+X33+Y33,2)+GX33 -> 3417.78 | GN33: =IF(OR(BI33=0,BI33=1),GM33-GX33,0) -> 0 | GO33: =IF(BI33=2,GM33-GX33,0) -> 3417.78 | GP33: =IF(BI33=4,GM33-GX33,0) -> 0 | GR33: 0 | GS33: 3 | GT33: 0 | GV33: =ROUND((GT33),6) -> 0 | GW33: 1 | GX33: =ROUND(HC33*I33,2) -> 0 | HA33: 0 | HB33: 0 | HC33: =GV33*GW33 -> 0 | HS33: 0 | IK33: 0
A34: 18 | B34: 1 | E34: 2,1 | F34: КА 2 | G34: Вызывная панель Activision AVC-305 | H34: шт. | I34: =I32*J34 -> 1 | J34: 10 | K34: 10 | O34: =ROUND(CP34,2) -> 439.99 | P34: =ROUND((ROUND((AC34*I34),2)*BC34),2) -> 439.99 | Q34: =(ROUND((ROUND(((ET34)*AV34*I34),2)*BB34),2)+ROUND((ROUND(((AE34-(EU34))*AV34*I34),2)*BS34),2)) -> 0 | R34: =ROUND((ROUND((AE34*AV34*I34),2)*BS34),2) -> 0 | S34: =ROUND((ROUND((AF34*AV34*I34),2)*BA34),2) -> 0 | T34: =ROUND(CU34*I34,2) -> 0 | U34: =CV34*I34 -> 0 | V34: =CW34*I34 -> 0 | W34: =ROUND(CX34*I34,2) -> 0 | X34: =ROUND(CY34,2) -> 0 | Y34: =ROUND(CZ34,2) -> 0 | AA34: 56511233 | AB34: =ROUND((AC34+AD34+AF34),6) -> 439.99 | AC34: =ROUND((ES34),6) -> 439.99 | AD34: =ROUND((((ET34)-(EU34))+AE34),6) -> 0 | AE34: =ROUND((EU34),6) -> 0 | AF34: =ROUND((EV34),6) -> 0 | AG34: =ROUND((AP34),6) -> 0 | AH34: =(EW34) -> 0 | AI34: =(EX34) -> 0 | AJ34: =(AS34) -> 0 | AK34: 439.99 | AL34: 439.99 | AM34: 0 | AN34: 0 | AO34: 0 | AP34: 0 | AQ34: 0 | AR34: 0 | AS34: 0 | AT34: 0 | AU34: 0 | AV34: 1 | AW34: 1 | AZ34: 1 | BA34: 1 | BB34: 1 | BC34: 1 | BH34: 3 | BI34: 3 | BM34: 746 | BN34: 0 | BP34: 0 | BQ34: 130 | BR34: 0 | BS34: 1 | BT34: 1 | BU34: 1 | BV34: 1 | BW34: 1 | BX34: 1 | BZ34: 90 | CA34: 46 | CE34: 30 | CF34: 0 | CG34: 0 | CM34: 0 | CO34: 0 | CP34: =(P34+Q34+S34) -> 439.99 | CQ34: =ROUND((ROUND((AC34*1),2)*BC34),2) -> 439.99 | CR34: =(ROUND((ROUND(((ET34)*AV34*1),2)*BB34),2)+ROUND((ROUND(((AE34-(EU34))*AV34*1),2)*BS34),2)) -> 0 | CS34: =ROUND((ROUND((AE34*AV34*1),2)*BS34),2) -> 0 | CT34: =ROUND((ROUND((AF34*AV34*1),2)*BA34),2) -> 0 | CU34: =AG34 -> 0 | CV34: =(AH34*AV34) -> 0 | CW34: =AI34 -> 0 | CX34: =AJ34 -> 0 | CY34: =(((S34+R34)*AT34)/100) -> 0 | CZ34: =(((S34+R34)*AU34)/100) -> 0 | DN34: 0 | DO34: 0 | DP34: 1 | DQ34: 1 | DU34: 1010 | DV34: шт. | DW34: шт. | DX34: 1 | EE34: 58162750 | EF34: 130 | EG34: Сметная стоимость оборудования | EH34: 0 | EJ34: 3 | EK34: 746 | EL34: ТСН-2001.13. Сметная стоимость оборудования | EM34: ТСН-2001.13 | EQ34: 0 | ER34: 0 | ES34: 439.99 | ET34: 0 | EU34: 0 | EV34: 0 | EW34: 0 | EX34: 0 | FQ34: 0 | FR34: =P34 -> 439.99 | FS34: 0 | FX34: 90 | FY34: 46 | GA34: [3 880 / 1,2 / 7,66] + 3% Трансп + 1,2% Заг.скл | GD34: 1 | GF34: -1280061895 | GG34: 2 | GH34: 4 | GI34: -2 | GJ34: 0 | GK34: 0 | GL34: =ROUND(IF(AND(BH34=3,BI34=3,FS34<>0),P34,0),2) -> 0 | GM34: =ROUND(O34+X34+Y34,2)+GX34 -> 439.99 | GN34: =IF(OR(BI34=0,BI34=1),GM34-GX34,0) -> 0 | GO34: =IF(BI34=2,GM34-GX34,0) -> 0 | GP34: =IF(BI34=4,GM34-GX34,0) -> 0 | GR34: 0 | GS34: 2 | GT34: 0 | GV34: =ROUND((GT34),6) -> 0 | GW34: 1 | GX34: =ROUND(HC34*I34,2) -> 0 | HA34: 0 | HB34: 0 | HC34: =GV34*GW34 -> 0 | HE34: 3 | HF34: 1,2 | HS34: 0 | IK34: 0
A35: 18 | B35: 1 | E35: 2,1 | F35: КА 2 | G35: Вызывная панель Activision AVC-305 | H35: шт. | I35: =I33*J35 -> 1 | J35: 10 | K35: 10 | O35: =ROUND(CP35,2) -> 3370.32 | P35: =ROUND((ROUND((AC35*I35),2)*BC35),2) -> 3370.32 | Q35: =(ROUND((ROUND(((ET35)*AV35*I35),2)*BB35),2)+ROUND((ROUND(((AE35-(EU35))*AV35*I35),2)*BS35),2)) -> 0 | R35: =ROUND((ROUND((AE35*AV35*I35),2)*BS35),2) -> 0 | S35: =ROUND((ROUND((AF35*AV35*I35),2)*BA35),2) -> 0 | T35: =ROUND(CU35*I35,2) -> 0 | U35: =CV35*I35 -> 0 | V35: =CW35*I35 -> 0 | W35: =ROUND(CX35*I35,2) -> 0 | X35: =ROUND(CY35,2) -> 0 | Y35: =ROUND(CZ35,2) -> 0 | AA35: 56511235 | AB35: =ROUND((AC35+AD35+AF35),6) -> 439.99 | AC35: =ROUND((ES35),6) -> 439.99 | AD35: =ROUND((((ET35)-(EU35))+AE35),6) -> 0 | AE35: =ROUND((EU35),6) -> 0 | AF35: =ROUND((EV35),6) -> 0 | AG35: =ROUND((AP35),6) -> 0 | AH35: =(EW35) -> 0 | AI35: =(EX35) -> 0 | AJ35: =(AS35) -> 0 | AK35: 439.99 | AL35: 439.99 | AM35: 0 | AN35: 0 | AO35: 0 | AP35: 0 | AQ35: 0 | AR35: 0 | AS35: 0 | AT35: 0 | AU35: 0 | AV35: 1 | AW35: 1 | AZ35: 1 | BA35: 1 | BB35: 1 | BC35: 7.66 | BH35: 3 | BI35: 3 | BM35: 746 | BN35: 0 | BP35: 0 | BQ35: 130 | BR35: 0 | BS35: 1 | BT35: 1 | BU35: 1 | BV35: 1 | BW35: 1 | BX35: 1 | BZ35: 90 | CA35: 46 | CE35: 30 | CF35: 0 | CG35: 0 | CM35: 0 | CO35: 0 | CP35: =(P35+Q35+S35) -> 3370.32 | CQ35: =ROUND((ROUND((AC35*1),2)*BC35),2) -> 3370.32 | CR35: =(ROUND((ROUND(((ET35)*AV35*1),2)*BB35),2)+ROUND((ROUND(((AE35-(EU35))*AV35*1),2)*BS35),2)) -> 0 | CS35: =ROUND((ROUND((AE35*AV35*1),2)*BS35),2) -> 0 | CT35: =ROUND((ROUND((AF35*AV35*1),2)*BA35),2) -> 0 | CU35: =AG35 -> 0 | CV35: =(AH35*AV35) -> 0 | CW35: =AI35 -> 0 | CX35: =AJ35 -> 0 | CY35: =(((S35+R35)*AT35)/100) -> 0 | CZ35: =(((S35+R35)*AU35)/100) -> 0 | DN35: 0 | DO35: 0 | DP35: 1 | DQ35: 1 | DU35: 1010 | DV35: шт. | DW35: шт. | DX35: 1 | EE35: 58162750 | EF35: 130 | EG35: Сметная стоимость оборудования | EH35: 0 | EJ35: 3 | EK35: 746 | EL35: ТСН-2001.13. Сметная стоимость оборудования | EM35: ТСН-2001.13 | EQ35: 0 | ER35: 3370.29 | ES35: 439.99 | ET35: 0 | EU35: 0 | EV35: 0 | EW35: 0 | EX35: 0 | EZ35: 5 | FC35: 1 | FD35: 18 | FF35: 3880 | FQ35: 0 | FR35: =P35 -> 3370.32 | FS35: 0 | FX35: 90 | FY35: 46 | GA35: [3 880 / 1,2 / 7,66] + 3% Трансп + 1,2% Заг.скл | GD35: 1 | GF35: -1280061895 | GG35: 2 | GH35: 3 | GI35: 5 | GJ35: 0 | GK35: 0 | GL35: =ROUND(IF(AND(BH35=3,BI35=3,FS35<>0),P35,0),2) -> 0 | GM35: =ROUND(O35+X35+Y35,2)+GX35 -> 3370.32 | GN35: =IF(OR(BI35=0,BI35=1),GM35-GX35,0) -> 0 | GO35: =IF(BI35=2,GM35-GX35,0) -> 0 | GP35: =IF(BI35=4,GM35-GX35,0) -> 0 | GR35: 1 | GS35: 1 | GT35: 0 | GV35: =ROUND((GT35),6) -> 0 | GW35: 1 | GX35: =ROUND(HC35*I35,2) -> 0 | HA35: 0 | HB35: 0 | HC35: =GV35*GW35 -> 0 | HE35: 3 | HF35: 1,2 | HS35: 0 | IK35: 0
A36: 17 | B36: 1 | D36: =ROW(EtalonRes!A41) -> 41 | E36: 3 | F36: 4.11-1-4 | G36: Монтаж конструкции для установки приборов и средств автоматизации массой до 5 кг | H36: 1 ШТ. | I36: 1 | J36: 0 | K36: 1 | O36: =ROUND(CP36,2) -> 70.79 | P36: =ROUND((ROUND((AC36*AW36*I36),2)*BC36),2) -> 51.03 | Q36: =(ROUND((ROUND((((ET36*1.1))*AV36*I36),2)*BB36),2)+ROUND((ROUND(((AE36-((EU36*1.1)))*AV36*I36),2)*BS36),2)) -> 6.18 | R36: =ROUND((ROUND((AE36*AV36*I36),2)*BS36),2) -> 1.42 | S36: =ROUND((ROUND((AF36*AV36*I36),2)*BA36),2) -> 13.58 | T36: =ROUND(CU36*I36,2) -> 0 | U36: =CV36*I36 -> 1.186251 | V36: =CW36*I36 -> 0 | W36: =ROUND(CX36*I36,2) -> 0 | X36: =ROUND(CY36,2) -> 13.5 | Y36: =ROUND(CZ36,2) -> 6.9 | AA36: 56511233 | AB36: =ROUND((AC36+AD36+AF36),6) -> 69.906 | AC36: =ROUND((ES36),6) -> 51.03 | AD36: =ROUND(((((ET36*1.1))-((EU36*1.1)))+AE36),6) -> 5.907 | AE36: =ROUND(((EU36*1.1)),6) -> 1.353 | AF36: =ROUND(((EV36*1.1)),6) -> 12.969 | AG36: =ROUND((AP36),6) -> 0 | AH36: =((EW36*1.1)) -> 1.133 | AI36: =((EX36*1.1)) -> 0 | AJ36: =(AS36) -> 0 | AK36: 68.19 | AL36: 51.03 | AM36: 5.37 | AN36: 1.23 | AO36: 11.79 | AP36: 0 | AQ36: 1.03 | AR36: 0 | AS36: 0 | AT36: 90 | AU36: 46 | AV36: 1.047 | AW36: 1 | AZ36: 1 | BA36: 1 | BB36: 1 | BC36: 1 | BH36: 0 | BI36: 2 | BJ36: ТСН-2001.4 Доп. 79, Сб. 11, т. 1, поз. 4 | BM36: 72 | BN36: 0 | BO36: 4.11-1-4 | BP36: 1 | BQ36: 40 | BR36: 0 | BS36: 1 | BT36: 1 | BU36: 1 | BV36: 1 | BW36: 1 | BX36: 1 | BZ36: 90 | CA36: 46 | CE36: 30 | CF36: 0 | CG36: 0 | CM36: 0 | CO36: 0 | CP36: =(P36+Q36+S36) -> 70.79 | CQ36: =ROUND((ROUND((AC36*AW36*1),2)*BC36),2) -> 51.03 | CR36: =(ROUND((ROUND((((ET36*1.1))*AV36*1),2)*BB36),2)+ROUND((ROUND(((AE36-((EU36*1.1)))*AV36*1),2)*BS36),2)) -> 6.18 | CS36: =ROUND((ROUND((AE36*AV36*1),2)*BS36),2) -> 1.42 | CT36: =ROUND((ROUND((AF36*AV36*1),2)*BA36),2) -> 13.58 | CU36: =AG36 -> 0 | CV36: =(AH36*AV36) -> 1.186251 | CW36: =AI36 -> 0 | CX36: =AJ36 -> 0 | CY36: =(((S36+R36)*AT36)/100) -> 13.5 | CZ36: =(((S36+R36)*AU36)/100) -> 6.9 | DE36: *1,1 | DF36: *1,1 | DG36: *1,1 | DI36: *1,1 | DJ36: *1,1 | DN36: 0 | DO36: 0 | DP36: 1 | DQ36: 1 | DU36: 1013 | DV36: 1 ШТ. | DW36: 1 ШТ. | DX36: 1 | EE36: 58162634 | EF36: 40 | EG36: Монтаж оборудования | EH36: 0 | EJ36: 2 | EK36: 72 | EL36: ТСН-2001.4-11. Приборы и средства автоматизации и вычислительной техники | EM36: ТСН-2001.4-11-1 | EO36: Поправка: Гл.12.Прил.8.п.8. 5_12.00.01.11.003 | EQ36: 0 | ER36: 68.19 | ES36: 51.03 | ET36: 5.37 | EU36: 1.23 | EV36: 11.79 | EW36: 1.03 | EX36: 0 | EY36: 0 | FQ36: 0 | FR36: 0 | FS36: 0 | FX36: 90 | FY36: 46 | GD36: 1 | GF36: -167093633 | GG36: 2 | GH36: 1 | GI36: 2 | GJ36: 0 | GK36: 0 | GL36: =ROUND(IF(AND(BH36=3,BI36=3,FS36<>0),P36,0),2) -> 0 | GM36: =ROUND(O36+X36+Y36,2)+GX36 -> 91.19 | GN36: =IF(OR(BI36=0,BI36=1),GM36-GX36,0) -> 0 | GO36: =IF(BI36=2,GM36-GX36,0) -> 91.19 | GP36: =IF(BI36=4,GM36-GX36,0) -> 0 | GR36: 0 | GS36: 3 | GT36: 0 | GV36: =ROUND((GT36),6) -> 0 | GW36: 1 | GX36: =ROUND(HC36*I36,2) -> 0 | HA36: 0 | HB36: 0 | HC36: =GV36*GW36 -> 0 | HS36: 0 | IK36: 0
A37: 17 | B37: 1 | D37: =ROW(EtalonRes!A58) -> 58 | E37: 3 | F37: 4.11-1-4 | G37: Монтаж конструкции для установки приборов и средств автоматизации массой до 5 кг | H37: 1 ШТ. | I37: 1 | J37: 0 | K37: 1 | O37: =ROUND(CP37,2) -> 1388.11 | P37: =ROUND((ROUND((AC37*AW37*I37),2)*BC37),2) -> 509.28 | Q37: =(ROUND((ROUND((((ET37*1.1))*AV37*I37),2)*BB37),2)+ROUND((ROUND(((AE37-((EU37*1.1)))*AV37*I37),2)*BS37),2)) -> 132.07 | R37: =ROUND((ROUND((AE37*AV37*I37),2)*BS37),2) -> 78.09 | S37: =ROUND((ROUND((AF37*AV37*I37),2)*BA37),2) -> 746.76 | T37: =ROUND(CU37*I37,2) -> 0 | U37: =CV37*I37 -> 1.186251 | V37: =CW37*I37 -> 0 | W37: =ROUND(CX37*I37,2) -> 0 | X37: =ROUND(CY37,2) -> 742.37 | Y37: =ROUND(CZ37,2) -> 379.43 | AA37: 56511235 | AB37: =ROUND((AC37+AD37+AF37),6) -> 69.906 | AC37: =ROUND((ES37),6) -> 51.03 | AD37: =ROUND(((((ET37*1.1))-((EU37*1.1)))+AE37),6) -> 5.907 | AE37: =ROUND(((EU37*1.1)),6) -> 1.353 | AF37: =ROUND(((EV37*1.1)),6) -> 12.969 | AG37: =ROUND((AP37),6) -> 0 | AH37: =((EW37*1.1)) -> 1.133 | AI37: =((EX37*1.1)) -> 0 | AJ37: =(AS37) -> 0 | AK37: 68.19 | AL37: 51.03 | AM37: 5.37 | AN37: 1.23 | AO37: 11.79 | AP37: 0 | AQ37: 1.03 | AR37: 0 | AS37: 0 | AT37: 90 | AU37: 46 | AV37: 1.047 | AW37: 1 | AZ37: 1 | BA37: 54.99 | BB37: 21.37 | BC37: 9.98 | BH37: 0 | BI37: 2 | BJ37: ТСН-2001.4 Доп. 79, Сб. 11, т. 1, поз. 4 | BM37: 72 | BN37: 0 | BO37: 4.11-1-4 | BP37: 1 | BQ37: 40 | BR37: 0 | BS37: 54.99 | BT37: 1 | BU37: 1 | BV37: 1 | BW37: 1 | BX37: 1 | BZ37: 90 | CA37: 46 | CE37: 30 | CF37: 0 | CG37: 0 | CM37: 0 | CO37: 0 | CP37: =(P37+Q37+S37) -> 1388.11 | CQ37: =ROUND((ROUND((AC37*AW37*1),2)*BC37),2) -> 509.28 | CR37: =(ROUND((ROUND((((ET37*1.1))*AV37*1),2)*BB37),2)+ROUND((ROUND(((AE37-((EU37*1.1)))*AV37*1),2)*BS37),2)) -> 132.07 | CS37: =ROUND((ROUND((AE37*AV37*1),2)*BS37),2) -> 78.09 | CT37: =ROUND((ROUND((AF37*AV37*1),2)*BA37),2) -> 746.76 | CU37: =AG37 -> 0 | CV37: =(AH37*AV37) -> 1.186251 | CW37: =AI37 -> 0 | CX37: =AJ37 -> 0 | CY37: =(((S37+R37)*AT37)/100) -> 742.365 | CZ37: =(((S37+R37)*AU37)/100) -> 379.431 | DE37: *1,1 | DF37: *1,1 | DG37: *1,1 | DI37: *1,1 | DJ37: *1,1 | DN37: 0 | DO37: 0 | DP37: 1 | DQ37: 1 | DU37: 1013 | DV37: 1 ШТ. | DW37: 1 ШТ. | DX37: 1 | EE37: 58162634 | EF37: 40 | EG37: Монтаж оборудования | EH37: 0 | EJ37: 2 | EK37: 72 | EL37: ТСН-2001.4-11. Приборы и средства автоматизации и вычислительной техники | EM37: ТСН-2001.4-11-1 | EO37: Поправка: Гл.12.Прил.8.п.8. 5_12.00.01.11.003 | EQ37: 0 | ER37: 68.19 | ES37: 51.03 | ET37: 5.37 | EU37: 1.23 | EV37: 11.79 | EW37: 1.03 | EX37: 0 | EY37: 0 | FQ37: 0 | FR37: 0 | FS37: 0 | FX37: 90 | FY37: 46 | GD37: 1 | GF37: -167093633 | GG37: 2 | GH37: 1 | GI37: 2 | GJ37: 0 | GK37: 0 | GL37: =ROUND(IF(AND(BH37=3,BI37=3,FS37<>0),P37,0),2) -> 0 | GM37: =ROUND(O37+X37+Y37,2)+GX37 -> 2509.91 | GN37: =IF(OR(BI37=0,BI37=1),GM37-GX37,0) -> 0 | GO37: =IF(BI37=2,GM37-GX37,0) -> 2509.91 | GP37: =IF(BI37=4,GM37-GX37,0) -> 0 | GR37: 0 | GS37: 3 | GT37: 0 | GV37: =ROUND((GT37),6) -> 0 | GW37: 1 | GX37: =ROUND(HC37*I37,2) -> 0 | HA37: 0 | HB37: 0 | HC37: =GV37*GW37 -> 0 | HS37: 0 | IK37: 0
A38: 18 | B38: 1 | E38: 3,1 | F38: КА 3 | G38: Стойка для вызывной панели AR-GO STS-03 | H38: шт. | I38: =I36*J38 -> 1 | J38: 1 | K38: 1 | O38: =ROUND(CP38,2) -> 546.3 | P38: =ROUND((ROUND((AC38*AW38*I38),2)*BC38),2) -> 546.3 | Q38: =(ROUND((ROUND(((ET38)*AV38*I38),2)*BB38),2)+ROUND((ROUND(((AE38-(EU38))*AV38*I38),2)*BS38),2)) -> 0 | R38: =ROUND((ROUND((AE38*AV38*I38),2)*BS38),2) -> 0 | S38: =ROUND((ROUND((AF38*AV38*I38),2)*BA38),2) -> 0 | T38: =ROUND(CU38*I38,2) -> 0 | U38: =CV38*I38 -> 0 | V38: =CW38*I38 -> 0 | W38: =ROUND(CX38*I38,2) -> 0 | X38: =ROUND(CY38,2) -> 0 | Y38: =ROUND(CZ38,2) -> 0 | AA38: 56511233 | AB38: =ROUND((AC38+AD38+AF38),6) -> 546.3 | AC38: =ROUND((ES38),6) -> 546.3 | AD38: =ROUND((((ET38)-(EU38))+AE38),6) -> 0 | AE38: =ROUND((EU38),6) -> 0 | AF38: =ROUND((EV38),6) -> 0 | AG38: =ROUND((AP38),6) -> 0 | AH38: =(EW38) -> 0 | AI38: =(EX38) -> 0 | AJ38: =(AS38) -> 0 | AK38: 546.3 | AL38: 546.3 | AM38: 0 | AN38: 0 | AO38: 0 | AP38: 0 | AQ38: 0 | AR38: 0 | AS38: 0 | AT38: 90 | AU38: 46 | AV38: 1 | AW38: 1 | AZ38: 1 | BA38: 1 | BB38: 1 | BC38: 1 | BH38: 3 | BI38: 2 | BM38: 72 | BN38: 0 | BP38: 0 | BQ38: 40 | BR38: 0 | BS38: 1 | BT38: 1 | BU38: 1 | BV38: 1 | BW38: 1 | BX38: 1 | BZ38: 90 | CA38: 46 | CE38: 30 | CF38: 0 | CG38: 0 | CM38: 0 | CO38: 0 | CP38: =(P38+Q38+S38) -> 546.3 | CQ38: =ROUND((ROUND((AC38*AW38*1),2)*BC38),2) -> 546.3 | CR38: =(ROUND((ROUND(((ET38)*AV38*1),2)*BB38),2)+ROUND((ROUND(((AE38-(EU38))*AV38*1),2)*BS38),2)) -> 0 | CS38: =ROUND((ROUND((AE38*AV38*1),2)*BS38),2) -> 0 | CT38: =ROUND((ROUND((AF38*AV38*1),2)*BA38),2) -> 0 | CU38: =AG38 -> 0 | CV38: =(AH38*AV38) -> 0 | CW38: =AI38 -> 0 | CX38: =AJ38 -> 0 | CY38: =(((S38+R38)*AT38)/100) -> 0 | CZ38: =(((S38+R38)*AU38)/100) -> 0 | DN38: 0 | DO38: 0 | DP38: 1 | DQ38: 1 | DU38: 1010 | DV38: шт. | DW38: шт. | DX38: 1 | EE38: 58162634 | EF38: 40 | EG38: Монтаж оборудования | EH38: 0 | EJ38: 2 | EK38: 72 | EL38: ТСН-2001.4-11. Приборы и средства автоматизации и вычислительной техники | EM38: ТСН-2001.4-11-1 | EQ38: 0 | ER38: 0 | ES38: 546.3 | ET38: 0 | EU38: 0 | EV38: 0 | EW38: 0 | EX38: 0 | FQ38: 0 | FR38: 0 | FS38: 0 | FX38: 90 | FY38: 46 | GA38: [6 350 / 1,2 / 9,88] + 2% Заг.скл | GD38: 1 | GF38: -149574411 | GG38: 2 | GH38: 4 | GI38: -2 | GJ38: 0 | GK38: 0 | GL38: =ROUND(IF(AND(BH38=3,BI38=3,FS38<>0),P38,0),2) -> 0 | GM38: =ROUND(O38+X38+Y38,2)+GX38 -> 546.3 | GN38: =IF(OR(BI38=0,BI38=1),GM38-GX38,0) -> 0 | GO38: =IF(BI38=2,GM38-GX38,0) -> 546.3 | GP38: =IF(BI38=4,GM38-GX38,0) -> 0 | GR38: 0 | GS38: 2 | GT38: 0 | GV38: =ROUND((GT38),6) -> 0 | GW38: 1 | GX38: =ROUND(HC38*I38,2) -> 0 | HA38: 0 | HB38: 0 | HC38: =GV38*GW38 -> 0 | HE38: 0 | HF38: 2 | HS38: 0 | IK38: 0
A39: 18 | B39: 1 | E39: 3,1 | F39: КА 3 | G39: Стойка для вызывной панели AR-GO STS-03 | H39: шт. | I39: =I37*J39 -> 1 | J39: 1 | K39: 1 | O39: =ROUND(CP39,2) -> 5397.44 | P39: =ROUND((ROUND((AC39*AW39*I39),2)*BC39),2) -> 5397.44 | Q39: =(ROUND((ROUND(((ET39)*AV39*I39),2)*BB39),2)+ROUND((ROUND(((AE39-(EU39))*AV39*I39),2)*BS39),2)) -> 0 | R39: =ROUND((ROUND((AE39*AV39*I39),2)*BS39),2) -> 0 | S39: =ROUND((ROUND((AF39*AV39*I39),2)*BA39),2) -> 0 | T39: =ROUND(CU39*I39,2) -> 0 | U39: =CV39*I39 -> 0 | V39: =CW39*I39 -> 0 | W39: =ROUND(CX39*I39,2) -> 0 | X39: =ROUND(CY39,2) -> 0 | Y39: =ROUND(CZ39,2) -> 0 | AA39: 56511235 | AB39: =ROUND((AC39+AD39+AF39),6) -> 546.3 | AC39: =ROUND((ES39),6) -> 546.3 | AD39: =ROUND((((ET39)-(EU39))+AE39),6) -> 0 | AE39: =ROUND((EU39),6) -> 0 | AF39: =ROUND((EV39),6) -> 0 | AG39: =ROUND((AP39),6) -> 0 | AH39: =(EW39) -> 0 | AI39: =(EX39) -> 0 | AJ39: =(AS39) -> 0 | AK39: 546.3 | AL39: 546.3 | AM39: 0 | AN39: 0 | AO39: 0 | AP39: 0 | AQ39: 0 | AR39: 0 | AS39: 0 | AT39: 90 | AU39: 46 | AV39: 1 | AW39: 1 | AZ39: 1 | BA39: 1 | BB39: 1 | BC39: 9.88 | BH39: 3 | BI39: 2 | BM39: 72 | BN39: 0 | BP39: 0 | BQ39: 40 | BR39: 0 | BS39: 1 | BT39: 1 | BU39: 1 | BV39: 1 | BW39: 1 | BX39: 1 | BZ39: 90 | CA39: 46 | CE39: 30 | CF39: 0 | CG39: 0 | CM39: 0 | CO39: 0 | CP39: =(P39+Q39+S39) -> 5397.44 | CQ39: =ROUND((ROUND((AC39*AW39*1),2)*BC39),2) -> 5397.44 | CR39: =(ROUND((ROUND(((ET39)*AV39*1),2)*BB39),2)+ROUND((ROUND(((AE39-(EU39))*AV39*1),2)*BS39),2)) -> 0 | CS39: =ROUND((ROUND((AE39*AV39*1),2)*BS39),2) -> 0 | CT39: =ROUND((ROUND((AF39*AV39*1),2)*BA39),2) -> 0 | CU39: =AG39 -> 0 | CV39: =(AH39*AV39) -> 0 | CW39: =AI39 -> 0 | CX39: =AJ39 -> 0 | CY39: =(((S39+R39)*AT39)/100) -> 0 | CZ39: =(((S39+R39)*AU39)/100) -> 0 | DN39: 0 | DO39: 0 | DP39: 1 | DQ39: 1 | DU39: 1010 | DV39: шт. | DW39: шт. | DX39: 1 | EE39: 58162634 | EF39: 40 | EG39: Монтаж оборудования | EH39: 0 | EJ39: 2 | EK39: 72 | EL39: ТСН-2001.4-11. Приборы и средства автоматизации и вычислительной техники | EM39: ТСН-2001.4-11-1 | EQ39: 0 | ER39: 5397.5 | ES39: 546.3 | ET39: 0 | EU39: 0 | EV39: 0 | EW39: 0 | EX39: 0 | EZ39: 5 | FC39: 1 | FD39: 18 | FF39: 6350 | FQ39: 0 | FR39: 0 | FS39: 0 | FX39: 90 | FY39: 46 | GA39: [6 350 / 1,2 / 9,88] + 2% Заг.скл | GD39: 1 | GF39: -149574411 | GG39: 2 | GH39: 3 | GI39: 5 | GJ39: 0 | GK39: 0 | GL39: =ROUND(IF(AND(BH39=3,BI39=3,FS39<>0),P39,0),2) -> 0 | GM39: =ROUND(O39+X39+Y39,2)+GX39 -> 5397.44 | GN39: =IF(OR(BI39=0,BI39=1),GM39-GX39,0) -> 0 | GO39: =IF(BI39=2,GM39-GX39,0) -> 5397.44 | GP39: =IF(BI39=4,GM39-GX39,0) -> 0 | GR39: 1 | GS39: 1 | GT39: 0 | GV39: =ROUND((GT39),6) -> 0 | GW39: 1 | GX39: =ROUND(HC39*I39,2) -> 0 | HA39: 0 | HB39: 0 | HC39: =GV39*GW39 -> 0 | HE39: 0 | HF39: 2 | HS39: 0 | IK39: 0
A40: 17 | B40: 1 | D40: =ROW(EtalonRes!A59) -> 59 | E40: 4 | F40: 4.10-152-5 | G40: Сигнализация дистанционная, блок оконечный | H40: 1 ШТ. | I40: 1 | J40: 0 | K40: 1 | O40: =ROUND(CP40,2) -> 365.83 | P40: =ROUND((ROUND((AC40*AW40*I40),2)*BC40),2) -> 17 | Q40: =(ROUND((ROUND((((ET40*1.1))*AV40*I40),2)*BB40),2)+ROUND((ROUND(((AE40-((EU40*1.1)))*AV40*I40),2)*BS40),2)) -> 0 | R40: =ROUND((ROUND((AE40*AV40*I40),2)*BS40),2) -> 0 | S40: =ROUND((ROUND((AF40*AV40*I40),2)*BA40),2) -> 348.83 | T40: =ROUND(CU40*I40,2) -> 0 | U40: =CV40*I40 -> 27.6408 | V40: =CW40*I40 -> 0 | W40: =ROUND(CX40*I40,2) -> 0 | X40: =ROUND(CY40,2) -> 313.95 | Y40: =ROUND(CZ40,2) -> 160.46 | AA40: 56511233 | AB40: =ROUND((AC40+AD40+AF40),6) -> 350.168 | AC40: =ROUND((ES40),6) -> 17 | AD40: =ROUND(((((ET40*1.1))-((EU40*1.1)))+AE40),6) -> 0 | AE40: =ROUND(((EU40*1.1)),6) -> 0 | AF40: =ROUND(((EV40*1.1)),6) -> 333.168 | AG40: =ROUND((AP40),6) -> 0 | AH40: =((EW40*1.1)) -> 26.4 | AI40: =((EX40*1.1)) -> 0 | AJ40: =(AS40) -> 0 | AK40: 319.88 | AL40: 17 | AM40: 0 | AN40: 0 | AO40: 302.88 | AP40: 0 | AQ40: 24 | AR40: 0 | AS40: 0 | AT40: 90 | AU40: 46 | AV40: 1.047 | AW40: 1 | AZ40: 1 | BA40: 1 | BB40: 1 | BC40: 1 | BH40: 0 | BI40: 2 | BJ40: ТСН-2001.4. Доп. 1-42. Сб. 10, т. 152, поз. 5 | BM40: 68 | BN40: 0 | BO40: 4.10-152-5 | BP40: 1 | BQ40: 40 | BR40: 0 | BS40: 1 | BT40: 1 | BU40: 1 | BV40: 1 | BW40: 1 | BX40: 1 | BZ40: 90 | CA40: 46 | CE40: 30 | CF40: 0 | CG40: 0 | CM40: 0 | CO40: 0 | CP40: =(P40+Q40+S40) -> 365.83 | CQ40: =ROUND((ROUND((AC40*AW40*1),2)*BC40),2) -> 17 | CR40: =(ROUND((ROUND((((ET40*1.1))*AV40*1),2)*BB40),2)+ROUND((ROUND(((AE40-((EU40*1.1)))*AV40*1),2)*BS40),2)) -> 0 | CS40: =ROUND((ROUND((AE40*AV40*1),2)*BS40),2) -> 0 | CT40: =ROUND((ROUND((AF40*AV40*1),2)*BA40),2) -> 348.83 | CU40: =AG40 -> 0 | CV40: =(AH40*AV40) -> 27.6408 | CW40: =AI40 -> 0 | CX40: =AJ40 -> 0 | CY40: =(((S40+R40)*AT40)/100) -> 313.947 | CZ40: =(((S40+R40)*AU40)/100) -> 160.4618 | DE40: *1,1 | DF40: *1,1 | DG40: *1,1 | DI40: *1,1 | DJ40: *1,1 | DN40: 0 | DO40: 0 | DP40: 1 | DQ40: 1 | DU40: 1013 | DV40: 1 ШТ. | DW40: 1 ШТ. | DX40: 1 | EE40: 58162630 | EF40: 40 | EG40: Монтаж оборудования | EH40: 0 | EJ40: 2 | EK40: 68 | EL40: ТСН-2001.4-10. Прокладка и монтаж сетей связи | EM40: ТСН-2001.4-10-1 | EO40: Поправка: Гл.12.Прил.8.п.8. 5_12.00.01.11.003 | EQ40: 0 | ER40: 319.88 | ES40: 17 | ET40: 0 | EU40: 0 | EV40: 302.88 | EW40: 24 | EX40: 0 | EY40: 0 | FQ40: 0 | FR40: 0 | FS40: 0 | FX40: 90 | FY40: 46 | GD40: 1 | GF40: -1788126512 | GG40: 2 | GH40: 1 | GI40: 2 | GJ40: 0 | GK40: 0 | GL40: =ROUND(IF(AND(BH40=3,BI40=3,FS40<>0),P40,0),2) -> 0 | GM40: =ROUND(O40+X40+Y40,2)+GX40 -> 840.24 | GN40: =IF(OR(BI40=0,BI40=1),GM40-GX40,0) -> 0 | GO40: =IF(BI40=2,GM40-GX40,0) -> 840.24 | GP40: =IF(BI40=4,GM40-GX40,0) -> 0 | GR40: 0 | GS40: 3 | GT40: 0 | GV40: =ROUND((GT40),6) -> 0 | GW40: 1 | GX40: =ROUND(HC40*I40,2) -> 0 | HA40: 0 | HB40: 0 | HC40: =GV40*GW40 -> 0 | HS40: 0 | IK40: 0
A41: 17 | B41: 1 | D41: =ROW(EtalonRes!A60) -> 60 | E41: 4 | F41: 4.10-152-5 | G41: Сигнализация дистанционная, блок оконечный | H41: 1 ШТ. | I41: 1 | J41: 0 | K41: 1 | O41: =ROUND(CP41,2) -> 19350.29 | P41: =ROUND((ROUND((AC41*AW41*I41),2)*BC41),2) -> 168.13 | Q41: =(ROUND((ROUND((((ET41*1.1))*AV41*I41),2)*BB41),2)+ROUND((ROUND(((AE41-((EU41*1.1)))*AV41*I41),2)*BS41),2)) -> 0 | R41: =ROUND((ROUND((AE41*AV41*I41),2)*BS41),2) -> 0 | S41: =ROUND((ROUND((AF41*AV41*I41),2)*BA41),2) -> 19182.16 | T41: =ROUND(CU41*I41,2) -> 0 | U41: =CV41*I41 -> 27.6408 | V41: =CW41*I41 -> 0 | W41: =ROUND(CX41*I41,2) -> 0 | X41: =ROUND(CY41,2) -> 17263.94 | Y41: =ROUND(CZ41,2) -> 8823.79 | AA41: 56511235 | AB41: =ROUND((AC41+AD41+AF41),6) -> 350.168 | AC41: =ROUND((ES41),6) -> 17 | AD41: =ROUND(((((ET41*1.1))-((EU41*1.1)))+AE41),6) -> 0 | AE41: =ROUND(((EU41*1.1)),6) -> 0 | AF41: =ROUND(((EV41*1.1)),6) -> 333.168 | AG41: =ROUND((AP41),6) -> 0 | AH41: =((EW41*1.1)) -> 26.4 | AI41: =((EX41*1.1)) -> 0 | AJ41: =(AS41) -> 0 | AK41: 319.88 | AL41: 17 | AM41: 0 | AN41: 0 | AO41: 302.88 | AP41: 0 | AQ41: 24 | AR41: 0 | AS41: 0 | AT41: 90 | AU41: 46 | AV41: 1.047 | AW41: 1 | AZ41: 1 | BA41: 54.99 | BB41: 1 | BC41: 9.89 | BH41: 0 | BI41: 2 | BJ41: ТСН-2001.4. Доп. 1-42. Сб. 10, т. 152, поз. 5 | BM41: 68 | BN41: 0 | BO41: 4.10-152-5 | BP41: 1 | BQ41: 40 | BR41: 0 | BS41: 54.99 | BT41: 1 | BU41: 1 | BV41: 1 | BW41: 1 | BX41: 1 | BZ41: 90 | CA41: 46 | CE41: 30 | CF41: 0 | CG41: 0 | CM41: 0 | CO41: 0 | CP41: =(P41+Q41+S41) -> 19350.29 | CQ41: =ROUND((ROUND((AC41*AW41*1),2)*BC41),2) -> 168.13 | CR41: =(ROUND((ROUND((((ET41*1.1))*AV41*1),2)*BB41),2)+ROUND((ROUND(((AE41-((EU41*1.1)))*AV41*1),2)*BS41),2)) -> 0 | CS41: =ROUND((ROUND((AE41*AV41*1),2)*BS41),2) -> 0 | CT41: =ROUND((ROUND((AF41*AV41*1),2)*BA41),2) -> 19182.16 | CU41: =AG41 -> 0 | CV41: =(AH41*AV41) -> 27.6408 | CW41: =AI41 -> 0 | CX41: =AJ41 -> 0 | CY41: =(((S41+R41)*AT41)/100) -> 17263.944 | CZ41: =(((S41+R41)*AU41)/100) -> 8823.7936 | DE41: *1,1 | DF41: *1,1 | DG41: *1,1 | DI41: *1,1 | DJ41: *1,1 | DN41: 0 | DO41: 0 | DP41: 1 | DQ41: 1 | DU41: 1013 | DV41: 1 ШТ. | DW41: 1 ШТ. | DX41: 1 | EE41: 58162630 | EF41: 40 | EG41: Монтаж оборудования | EH41: 0 | EJ41: 2 | EK41: 68 | EL41: ТСН-2001.4-10. Прокладка и монтаж сетей связи | EM41: ТСН-2001.4-10-1 | EO41: Поправка: Гл.12.Прил.8.п.8. 5_12.00.01.11.003 | EQ41: 0 | ER41: 319.88 | ES41: 17 | ET41: 0 | EU41: 0 | EV41: 302.88 | EW41: 24 | EX41: 0 | EY41: 0 | FQ41: 0 | FR41: 0 | FS41: 0 | FX41: 90 | FY41: 46 | GD41: 1 | GF41: -1788126512 | GG41: 2 | GH41: 1 | GI41: 2 | GJ41: 0 | GK41: 0 | GL41: =ROUND(IF(AND(BH41=3,BI41=3,FS41<>0),P41,0),2) -> 0 | GM41: =ROUND(O41+X41+Y41,2)+GX41 -> 45438.02 | GN41: =IF(OR(BI41=0,BI41=1),GM41-GX41,0) -> 0 | GO41: =IF(BI41=2,GM41-GX41,0) -> 45438.02 | GP41: =IF(BI41=4,GM41-GX41,0) -> 0 | GR41: 0 | GS41: 3 | GT41: 0 | GV41: =ROUND((GT41),6) -> 0 | GW41: 1 | GX41: =ROUND(HC41*I41,2) -> 0 | HA41: 0 | HB41: 0 | HC41: =GV41*GW41 -> 0 | HS41: 0 | IK41: 0
A42: 18 | B42: 1 | E42: 4,1 | F42: КА 5 | G42: Локальный блок связи Тромбон ЛБС | H42: шт. | I42: =I40*J42 -> 1 | J42: 1 | K42: 1 | O42: =ROUND(CP42,2) -> 12025.03 | P42: =ROUND((ROUND((AC42*I42),2)*BC42),2) -> 12025.03 | Q42: =(ROUND((ROUND(((ET42)*AV42*I42),2)*BB42),2)+ROUND((ROUND(((AE42-(EU42))*AV42*I42),2)*BS42),2)) -> 0 | R42: =ROUND((ROUND((AE42*AV42*I42),2)*BS42),2) -> 0 | S42: =ROUND((ROUND((AF42*AV42*I42),2)*BA42),2) -> 0 | T42: =ROUND(CU42*I42,2) -> 0 | U42: =CV42*I42 -> 0 | V42: =CW42*I42 -> 0 | W42: =ROUND(CX42*I42,2) -> 0 | X42: =ROUND(CY42,2) -> 0 | Y42: =ROUND(CZ42,2) -> 0 | AA42: 56511233 | AB42: =ROUND((AC42+AD42+AF42),6) -> 12025.03 | AC42: =ROUND((ES42),6) -> 12025.03 | AD42: =ROUND((((ET42)-(EU42))+AE42),6) -> 0 | AE42: =ROUND((EU42),6) -> 0 | AF42: =ROUND((EV42),6) -> 0 | AG42: =ROUND((AP42),6) -> 0 | AH42: =(EW42) -> 0 | AI42: =(EX42) -> 0 | AJ42: =(AS42) -> 0 | AK42: 12025.03 | AL42: 12025.03 | AM42: 0 | AN42: 0 | AO42: 0 | AP42: 0 | AQ42: 0 | AR42: 0 | AS42: 0 | AT42: 0 | AU42: 0 | AV42: 1 | AW42: 1 | AZ42: 1 | BA42: 1 | BB42: 1 | BC42: 1 | BH42: 3 | BI42: 3 | BM42: 746 | BN42: 0 | BP42: 0 | BQ42: 130 | BR42: 0 | BS42: 1 | BT42: 1 | BU42: 1 | BV42: 1 | BW42: 1 | BX42: 1 | BZ42: 90 | CA42: 46 | CE42: 30 | CF42: 0 | CG42: 0 | CM42: 0 | CO42: 0 | CP42: =(P42+Q42+S42) -> 12025.03 | CQ42: =ROUND((ROUND((AC42*1),2)*BC42),2) -> 12025.03 | CR42: =(ROUND((ROUND(((ET42)*AV42*1),2)*BB42),2)+ROUND((ROUND(((AE42-(EU42))*AV42*1),2)*BS42),2)) -> 0 | CS42: =ROUND((ROUND((AE42*AV42*1),2)*BS42),2) -> 0 | CT42: =ROUND((ROUND((AF42*AV42*1),2)*BA42),2) -> 0 | CU42: =AG42 -> 0 | CV42: =(AH42*AV42) -> 0 | CW42: =AI42 -> 0 | CX42: =AJ42 -> 0 | CY42: =(((S42+R42)*AT42)/100) -> 0 | CZ42: =(((S42+R42)*AU42)/100) -> 0 | DN42: 0 | DO42: 0 | DP42: 1 | DQ42: 1 | DU42: 1010 | DV42: шт. | DW42: шт. | DX42: 1 | EE42: 58162750 | EF42: 130 | EG42: Сметная стоимость оборудования | EH42: 0 | EJ42: 3 | EK42: 746 | EL42: ТСН-2001.13. Сметная стоимость оборудования | EM42: ТСН-2001.13 | EQ42: 0 | ER42: 0 | ES42: 12025.03 | ET42: 0 | EU42: 0 | EV42: 0 | EW42: 0 | EX42: 0 | FQ42: 0 | FR42: =P42 -> 12025.03 | FS42: 0 | FX42: 90 | FY42: 46 | GA42: [106 042,16 / 1,2 / 7,66] + 3% Трансп + 1,2% Заг.скл | GD42: 1 | GF42: 1404242535 | GG42: 2 | GH42: 4 | GI42: -2 | GJ42: 0 | GK42: 0 | GL42: =ROUND(IF(AND(BH42=3,BI42=3,FS42<>0),P42,0),2) -> 0 | GM42: =ROUND(O42+X42+Y42,2)+GX42 -> 12025.03 | GN42: =IF(OR(BI42=0,BI42=1),GM42-GX42,0) -> 0 | GO42: =IF(BI42=2,GM42-GX42,0) -> 0 | GP42: =IF(BI42=4,GM42-GX42,0) -> 0 | GR42: 0 | GS42: 2 | GT42: 0 | GV42: =ROUND((GT42),6) -> 0 | GW42: 1 | GX42: =ROUND(HC42*I42,2) -> 0 | HA42: 0 | HB42: 0 | HC42: =GV42*GW42 -> 0 | HE42: 3 | HF42: 1,2 | HS42: 0 | IK42: 0
A43: 18 | B43: 1 | E43: 4,1 | F43: КА 5 | G43: Локальный блок связи Тромбон ЛБС | H43: шт. | I43: =I41*J43 -> 1 | J43: 1 | K43: 1 | O43: =ROUND(CP43,2) -> 92111.73 | P43: =ROUND((ROUND((AC43*I43),2)*BC43),2) -> 92111.73 | Q43: =(ROUND((ROUND(((ET43)*AV43*I43),2)*BB43),2)+ROUND((ROUND(((AE43-(EU43))*AV43*I43),2)*BS43),2)) -> 0 | R43: =ROUND((ROUND((AE43*AV43*I43),2)*BS43),2) -> 0 | S43: =ROUND((ROUND((AF43*AV43*I43),2)*BA43),2) -> 0 | T43: =ROUND(CU43*I43,2) -> 0 | U43: =CV43*I43 -> 0 | V43: =CW43*I43 -> 0 | W43: =ROUND(CX43*I43,2) -> 0 | X43: =ROUND(CY43,2) -> 0 | Y43: =ROUND(CZ43,2) -> 0 | AA43: 56511235 | AB43: =ROUND((AC43+AD43+AF43),6) -> 12025.03 | AC43: =ROUND((ES43),6) -> 12025.03 | AD43: =ROUND((((ET43)-(EU43))+AE43),6) -> 0 | AE43: =ROUND((EU43),6) -> 0 | AF43: =ROUND((EV43),6) -> 0 | AG43: =ROUND((AP43),6) -> 0 | AH43: =(EW43) -> 0 | AI43: =(EX43) -> 0 | AJ43: =(AS43) -> 0 | AK43: 12025.03 | AL43: 12025.03 | AM43: 0 | AN43: 0 | AO43: 0 | AP43: 0 | AQ43: 0 | AR43: 0 | AS43: 0 | AT43: 0 | AU43: 0 | AV43: 1 | AW43: 1 | AZ43: 1 | BA43: 1 | BB43: 1 | BC43: 7.66 | BH43: 3 | BI43: 3 | BM43: 746 | BN43: 0 | BP43: 0 | BQ43: 130 | BR43: 0 | BS43: 1 | BT43: 1 | BU43: 1 | BV43: 1 | BW43: 1 | BX43: 1 | BZ43: 90 | CA43: 46 | CE43: 30 | CF43: 0 | CG43: 0 | CM43: 0 | CO43: 0 | CP43: =(P43+Q43+S43) -> 92111.73 | CQ43: =ROUND((ROUND((AC43*1),2)*BC43),2) -> 92111.73 | CR43: =(ROUND((ROUND(((ET43)*AV43*1),2)*BB43),2)+ROUND((ROUND(((AE43-(EU43))*AV43*1),2)*BS43),2)) -> 0 | CS43: =ROUND((ROUND((AE43*AV43*1),2)*BS43),2) -> 0 | CT43: =ROUND((ROUND((AF43*AV43*1),2)*BA43),2) -> 0 | CU43: =AG43 -> 0 | CV43: =(AH43*AV43) -> 0 | CW43: =AI43 -> 0 | CX43: =AJ43 -> 0 | CY43: =(((S43+R43)*AT43)/100) -> 0 | CZ43: =(((S43+R43)*AU43)/100) -> 0 | DN43: 0 | DO43: 0 | DP43: 1 | DQ43: 1 | DU43: 1010 | DV43: шт. | DW43: шт. | DX43: 1 | EE43: 58162750 | EF43: 130 | EG43: Сметная стоимость оборудования | EH43: 0 | EJ43: 3 | EK43: 746 | EL43: ТСН-2001.13. Сметная стоимость оборудования | EM43: ТСН-2001.13 | EQ43: 0 | ER43: 92111.75 | ES43: 12025.03 | ET43: 0 | EU43: 0 | EV43: 0 | EW43: 0 | EX43: 0 | EZ43: 5 | FC43: 1 | FD43: 18 | FF43: 106042.16 | FQ43: 0 | FR43: =P43 -> 92111.73 | FS43: 0 | FX43: 90 | FY43: 46 | GA43: [106 042,16 / 1,2 / 7,66] + 3% Трансп + 1,2% Заг.скл | GD43: 1 | GF43: 1404242535 | GG43: 2 | GH43: 3 | GI43: 5 | GJ43: 0 | GK43: 0 | GL43: =ROUND(IF(AND(BH43=3,BI43=3,FS43<>0),P43,0),2) -> 0 | GM43: =ROUND(O43+X43+Y43,2)+GX43 -> 92111.73 | GN43: =IF(OR(BI43=0,BI43=1),GM43-GX43,0) -> 0 | GO43: =IF(BI43=2,GM43-GX43,0) -> 0 | GP43: =IF(BI43=4,GM43-GX43,0) -> 0 | GR43: 1 | GS43: 1 | GT43: 0 | GV43: =ROUND((GT43),6) -> 0 | GW43: 1 | GX43: =ROUND(HC43*I43,2) -> 0 | HA43: 0 | HB43: 0 | HC43: =GV43*GW43 -> 0 | HE43: 3 | HF43: 1,2 | HS43: 0 | IK43: 0
A44: 18 | B44: 1 | E44: 4,2 | F44: 13.1-1-20 | G44: Батарея аккумуляторная, емкость 7 А·ч, напряжение 12 В | H44: шт. | I44: =I40*J44 -> 2 | J44: 2 | K44: 2 | O44: =ROUND(CP44,2) -> 178.78 | P44: =ROUND((ROUND((AC44*I44),2)*BC44),2) -> 178.78 | Q44: =(ROUND((ROUND(((ET44)*AV44*I44),2)*BB44),2)+ROUND((ROUND(((AE44-(EU44))*AV44*I44),2)*BS44),2)) -> 0 | R44: =ROUND((ROUND((AE44*AV44*I44),2)*BS44),2) -> 0 | S44: =ROUND((ROUND((AF44*AV44*I44),2)*BA44),2) -> 0 | T44: =ROUND(CU44*I44,2) -> 0 | U44: =CV44*I44 -> 0 | V44: =CW44*I44 -> 0 | W44: =ROUND(CX44*I44,2) -> 0 | X44: =ROUND(CY44,2) -> 0 | Y44: =ROUND(CZ44,2) -> 0 | AA44: 56511233 | AB44: =ROUND((AC44+AD44+AF44),6) -> 89.39 | AC44: =ROUND((ES44),6) -> 89.39 | AD44: =ROUND((((ET44)-(EU44))+AE44),6) -> 0 | AE44: =ROUND((EU44),6) -> 0 | AF44: =ROUND((EV44),6) -> 0 | AG44: =ROUND((AP44),6) -> 0 | AH44: =(EW44) -> 0 | AI44: =(EX44) -> 0 | AJ44: =(AS44) -> 0 | AK44: 89.39 | AL44: 89.39 | AM44: 0 | AN44: 0 | AO44: 0 | AP44: 0 | AQ44: 0 | AR44: 0 | AS44: 0 | AT44: 0 | AU44: 0 | AV44: 1 | AW44: 1 | AZ44: 1 | BA44: 1 | BB44: 1 | BC44: 1 | BH44: 3 | BI44: 3 | BM44: 746 | BN44: 0 | BP44: 0 | BQ44: 130 | BR44: 0 | BS44: 1 | BT44: 1 | BU44: 1 | BV44: 1 | BW44: 1 | BX44: 1 | BZ44: 90 | CA44: 46 | CE44: 30 | CF44: 0 | CG44: 0 | CM44: 0 | CO44: 0 | CP44: =(P44+Q44+S44) -> 178.78 | CQ44: =ROUND((ROUND((AC44*1),2)*BC44),2) -> 89.39 | CR44: =(ROUND((ROUND(((ET44)*AV44*1),2)*BB44),2)+ROUND((ROUND(((AE44-(EU44))*AV44*1),2)*BS44),2)) -> 0 | CS44: =ROUND((ROUND((AE44*AV44*1),2)*BS44),2) -> 0 | CT44: =ROUND((ROUND((AF44*AV44*1),2)*BA44),2) -> 0 | CU44: =AG44 -> 0 | CV44: =(AH44*AV44) -> 0 | CW44: =AI44 -> 0 | CX44: =AJ44 -> 0 | CY44: =(((S44+R44)*AT44)/100) -> 0 | CZ44: =(((S44+R44)*AU44)/100) -> 0 | DN44: 0 | DO44: 0 | DP44: 1 | DQ44: 1 | DU44: 1010 | DV44: шт. | DW44: шт. | DX44: 1 | EE44: 58162750 | EF44: 130 | EG44: Сметная стоимость оборудования | EH44: 0 | EJ44: 3 | EK44: 746 | EL44: ТСН-2001.13. Сметная стоимость оборудования | EM44: ТСН-2001.13 | EQ44: 0 | ER44: 89.39 | ES44: 89.39 | ET44: 0 | EU44: 0 | EV44: 0 | EW44: 0 | EX44: 0 | FQ44: 0 | FR44: =P44 -> 178.78 | FS44: 0 | FX44: 90 | FY44: 46 | GD44: 1 | GF44: -836002113 | GG44: 2 | GH44: 1 | GI44: -2 | GJ44: 0 | GK44: 0 | GL44: =ROUND(IF(AND(BH44=3,BI44=3,FS44<>0),P44,0),2) -> 0 | GM44: =ROUND(O44+X44+Y44,2)+GX44 -> 178.78 | GN44: =IF(OR(BI44=0,BI44=1),GM44-GX44,0) -> 0 | GO44: =IF(BI44=2,GM44-GX44,0) -> 0 | GP44: =IF(BI44=4,GM44-GX44,0) -> 0 | GR44: 0 | GS44: 3 | GT44: 0 | GV44: =ROUND((GT44),6) -> 0 | GW44: 1 | GX44: =ROUND(HC44*I44,2) -> 0 | HA44: 0 | HB44: 0 | HC44: =GV44*GW44 -> 0 | HS44: 0 | IK44: 0
A45: 18 | B45: 1 | E45: 4,2 | F45: 13.1-1-20 | G45: Батарея аккумуляторная, емкость 7 А·ч, напряжение 12 В | H45: шт. | I45: =I41*J45 -> 2 | J45: 2 | K45: 2 | O45: =ROUND(CP45,2) -> 1564.33 | P45: =ROUND((ROUND((AC45*I45),2)*BC45),2) -> 1564.33 | Q45: =(ROUND((ROUND(((ET45)*AV45*I45),2)*BB45),2)+ROUND((ROUND(((AE45-(EU45))*AV45*I45),2)*BS45),2)) -> 0 | R45: =ROUND((ROUND((AE45*AV45*I45),2)*BS45),2) -> 0 | S45: =ROUND((ROUND((AF45*AV45*I45),2)*BA45),2) -> 0 | T45: =ROUND(CU45*I45,2) -> 0 | U45: =CV45*I45 -> 0 | V45: =CW45*I45 -> 0 | W45: =ROUND(CX45*I45,2) -> 0 | X45: =ROUND(CY45,2) -> 0 | Y45: =ROUND(CZ45,2) -> 0 | AA45: 56511235 | AB45: =ROUND((AC45+AD45+AF45),6) -> 89.39 | AC45: =ROUND((ES45),6) -> 89.39 | AD45: =ROUND((((ET45)-(EU45))+AE45),6) -> 0 | AE45: =ROUND((EU45),6) -> 0 | AF45: =ROUND((EV45),6) -> 0 | AG45: =ROUND((AP45),6) -> 0 | AH45: =(EW45) -> 0 | AI45: =(EX45) -> 0 | AJ45: =(AS45) -> 0 | AK45: 89.39 | AL45: 89.39 | AM45: 0 | AN45: 0 | AO45: 0 | AP45: 0 | AQ45: 0 | AR45: 0 | AS45: 0 | AT45: 0 | AU45: 0 | AV45: 1 | AW45: 1 | AZ45: 1 | BA45: 1 | BB45: 1 | BC45: 8.75 | BH45: 3 | BI45: 3 | BM45: 746 | BN45: 0 | BP45: 0 | BQ45: 130 | BR45: 0 | BS45: 1 | BT45: 1 | BU45: 1 | BV45: 1 | BW45: 1 | BX45: 1 | BZ45: 90 | CA45: 46 | CE45: 30 | CF45: 0 | CG45: 0 | CM45: 0 | CO45: 0 | CP45: =(P45+Q45+S45) -> 1564.33 | CQ45: =ROUND((ROUND((AC45*1),2)*BC45),2) -> 782.16 | CR45: =(ROUND((ROUND(((ET45)*AV45*1),2)*BB45),2)+ROUND((ROUND(((AE45-(EU45))*AV45*1),2)*BS45),2)) -> 0 | CS45: =ROUND((ROUND((AE45*AV45*1),2)*BS45),2) -> 0 | CT45: =ROUND((ROUND((AF45*AV45*1),2)*BA45),2) -> 0 | CU45: =AG45 -> 0 | CV45: =(AH45*AV45) -> 0 | CW45: =AI45 -> 0 | CX45: =AJ45 -> 0 | CY45: =(((S45+R45)*AT45)/100) -> 0 | CZ45: =(((S45+R45)*AU45)/100) -> 0 | DN45: 0 | DO45: 0 | DP45: 1 | DQ45: 1 | DU45: 1010 | DV45: шт. | DW45: шт. | DX45: 1 | EE45: 58162750 | EF45: 130 | EG45: Сметная стоимость оборудования | EH45: 0 | EJ45: 3 | EK45: 746 | EL45: ТСН-2001.13. Сметная стоимость оборудования | EM45: ТСН-2001.13 | EQ45: 0 | ER45: 89.39 | ES45: 89.39 | ET45: 0 | EU45: 0 | EV45: 0 | EW45: 0 | EX45: 0 | FQ45: 0 | FR45: =P45 -> 1564.33 | FS45: 0 | FX45: 90 | FY45: 46 | GD45: 1 | GF45: -836002113 | GG45: 2 | GH45: 1 | GI45: 2 | GJ45: 0 | GK45: 0 | GL45: =ROUND(IF(AND(BH45=3,BI45=3,FS45<>0),P45,0),2) -> 0 | GM45: =ROUND(O45+X45+Y45,2)+GX45 -> 1564.33 | GN45: =IF(OR(BI45=0,BI45=1),GM45-GX45,0) -> 0 | GO45: =IF(BI45=2,GM45-GX45,0) -> 0 | GP45: =IF(BI45=4,GM45-GX45,0) -> 0 | GR45: 0 | GS45: 3 | GT45: 0 | GV45: =ROUND((GT45),6) -> 0 | GW45: 1 | GX45: =ROUND(HC45*I45,2) -> 0 | HA45: 0 | HB45: 0 | HC45: =GV45*GW45 -> 0 | HS45: 0 | IK45: 0
A46: 17 | B46: 1 | D46: =ROW(EtalonRes!A64) -> 64 | E46: 5 | F46: 4.10-151-2 | G46: Установка пульта или табло вызывной сигнализации с количеством сигналов до 10 | H46: 1 ШТ. | I46: 1 | J46: 0 | K46: 1 | O46: =ROUND(CP46,2) -> 79.84 | P46: =ROUND((ROUND((AC46*AW46*I46),2)*BC46),2) -> 2.67 | Q46: =(ROUND((ROUND((((ET46*1.1))*AV46*I46),2)*BB46),2)+ROUND((ROUND(((AE46-((EU46*1.1)))*AV46*I46),2)*BS46),2)) -> 0.12 | R46: =ROUND((ROUND((AE46*AV46*I46),2)*BS46),2) -> 0 | S46: =ROUND((ROUND((AF46*AV46*I46),2)*BA46),2) -> 77.05 | T46: =ROUND(CU46*I46,2) -> 0 | U46: =CV46*I46 -> 5.7585 | V46: =CW46*I46 -> 0 | W46: =ROUND(CX46*I46,2) -> 0 | X46: =ROUND(CY46,2) -> 69.35 | Y46: =ROUND(CZ46,2) -> 35.44 | AA46: 56511233 | AB46: =ROUND((AC46+AD46+AF46),6) -> 76.37 | AC46: =ROUND((ES46),6) -> 2.67 | AD46: =ROUND(((((ET46*1.1))-((EU46*1.1)))+AE46),6) -> 0.11 | AE46: =ROUND(((EU46*1.1)),6) -> 0 | AF46: =ROUND(((EV46*1.1)),6) -> 73.59 | AG46: =ROUND((AP46),6) -> 0 | AH46: =((EW46*1.1)) -> 5.5 | AI46: =((EX46*1.1)) -> 0 | AJ46: =(AS46) -> 0 | AK46: 69.67 | AL46: 2.67 | AM46: 0.1 | AN46: 0 | AO46: 66.9 | AP46: 0 | AQ46: 5 | AR46: 0 | AS46: 0 | AT46: 90 | AU46: 46 | AV46: 1.047 | AW46: 1 | AZ46: 1 | BA46: 1 | BB46: 1 | BC46: 1 | BH46: 0 | BI46: 2 | BJ46: ТСН-2001.4 Доп. 67, Сб. 10, т. 151, поз. 2 | BM46: 68 | BN46: 0 | BO46: 4.10-151-2 | BP46: 1 | BQ46: 40 | BR46: 0 | BS46: 1 | BT46: 1 | BU46: 1 | BV46: 1 | BW46: 1 | BX46: 1 | BZ46: 90 | CA46: 46 | CE46: 30 | CF46: 0 | CG46: 0 | CM46: 0 | CO46: 0 | CP46: =(P46+Q46+S46) -> 79.84 | CQ46: =ROUND((ROUND((AC46*AW46*1),2)*BC46),2) -> 2.67 | CR46: =(ROUND((ROUND((((ET46*1.1))*AV46*1),2)*BB46),2)+ROUND((ROUND(((AE46-((EU46*1.1)))*AV46*1),2)*BS46),2)) -> 0.12 | CS46: =ROUND((ROUND((AE46*AV46*1),2)*BS46),2) -> 0 | CT46: =ROUND((ROUND((AF46*AV46*1),2)*BA46),2) -> 77.05 | CU46: =AG46 -> 0 | CV46: =(AH46*AV46) -> 5.7585 | CW46: =AI46 -> 0 | CX46: =AJ46 -> 0 | CY46: =(((S46+R46)*AT46)/100) -> 69.345 | CZ46: =(((S46+R46)*AU46)/100) -> 35.443 | DE46: *1,1 | DF46: *1,1 | DG46: *1,1 | DI46: *1,1 | DJ46: *1,1 | DN46: 0 | DO46: 0 | DP46: 1 | DQ46: 1 | DU46: 1013 | DV46: 1 ШТ. | DW46: 1 ШТ. | DX46: 1 | EE46: 58162630 | EF46: 40 | EG46: Монтаж оборудования | EH46: 0 | EJ46: 2 | EK46: 68 | EL46: ТСН-2001.4-10. Прокладка и монтаж сетей связи | EM46: ТСН-2001.4-10-1 | EO46: Поправка: Гл.12.Прил.8.п.8. 5_12.00.01.11.003 | EQ46: 0 | ER46: 69.67 | ES46: 2.67 | ET46: 0.1 | EU46: 0 | EV46: 66.9 | EW46: 5 | EX46: 0 | EY46: 0 | FQ46: 0 | FR46: 0 | FS46: 0 | FX46: 90 | FY46: 46 | GD46: 1 | GF46: -1786768696 | GG46: 2 | GH46: 1 | GI46: 2 | GJ46: 0 | GK46: 0 | GL46: =ROUND(IF(AND(BH46=3,BI46=3,FS46<>0),P46,0),2) -> 0 | GM46: =ROUND(O46+X46+Y46,2)+GX46 -> 184.63 | GN46: =IF(OR(BI46=0,BI46=1),GM46-GX46,0) -> 0 | GO46: =IF(BI46=2,GM46-GX46,0) -> 184.63 | GP46: =IF(BI46=4,GM46-GX46,0) -> 0 | GR46: 0 | GS46: 3 | GT46: 0 | GV46: =ROUND((GT46),6) -> 0 | GW46: 1 | GX46: =ROUND(HC46*I46,2) -> 0 | HA46: 0 | HB46: 0 | HC46: =GV46*GW46 -> 0 | HS46: 0 | IK46: 0
A47: 17 | B47: 1 | D47: =ROW(EtalonRes!A68) -> 68 | E47: 5 | F47: 4.10-151-2 | G47: Установка пульта или табло вызывной сигнализации с количеством сигналов до 10 | H47: 1 ШТ. | I47: 1 | J47: 0 | K47: 1 | O47: =ROUND(CP47,2) -> 4240.45 | P47: =ROUND((ROUND((AC47*AW47*I47),2)*BC47),2) -> 2.4 | Q47: =(ROUND((ROUND((((ET47*1.1))*AV47*I47),2)*BB47),2)+ROUND((ROUND(((AE47-((EU47*1.1)))*AV47*I47),2)*BS47),2)) -> 1.07 | R47: =ROUND((ROUND((AE47*AV47*I47),2)*BS47),2) -> 0 | S47: =ROUND((ROUND((AF47*AV47*I47),2)*BA47),2) -> 4236.98 | T47: =ROUND(CU47*I47,2) -> 0 | U47: =CV47*I47 -> 5.7585 | V47: =CW47*I47 -> 0 | W47: =ROUND(CX47*I47,2) -> 0 | X47: =ROUND(CY47,2) -> 3813.28 | Y47: =ROUND(CZ47,2) -> 1949.01 | AA47: 56511235 | AB47: =ROUND((AC47+AD47+AF47),6) -> 76.37 | AC47: =ROUND((ES47),6) -> 2.67 | AD47: =ROUND(((((ET47*1.1))-((EU47*1.1)))+AE47),6) -> 0.11 | AE47: =ROUND(((EU47*1.1)),6) -> 0 | AF47: =ROUND(((EV47*1.1)),6) -> 73.59 | AG47: =ROUND((AP47),6) -> 0 | AH47: =((EW47*1.1)) -> 5.5 | AI47: =((EX47*1.1)) -> 0 | AJ47: =(AS47) -> 0 | AK47: 69.67 | AL47: 2.67 | AM47: 0.1 | AN47: 0 | AO47: 66.9 | AP47: 0 | AQ47: 5 | AR47: 0 | AS47: 0 | AT47: 90 | AU47: 46 | AV47: 1.047 | AW47: 1 | AZ47: 1 | BA47: 54.99 | BB47: 8.9 | BC47: 0.9 | BH47: 0 | BI47: 2 | BJ47: ТСН-2001.4 Доп. 67, Сб. 10, т. 151, поз. 2 | BM47: 68 | BN47: 0 | BO47: 4.10-151-2 | BP47: 1 | BQ47: 40 | BR47: 0 | BS47: 54.99 | BT47: 1 | BU47: 1 | BV47: 1 | BW47: 1 | BX47: 1 | BZ47: 90 | CA47: 46 | CE47: 30 | CF47: 0 | CG47: 0 | CM47: 0 | CO47: 0 | CP47: =(P47+Q47+S47) -> 4240.45 | CQ47: =ROUND((ROUND((AC47*AW47*1),2)*BC47),2) -> 2.4 | CR47: =(ROUND((ROUND((((ET47*1.1))*AV47*1),2)*BB47),2)+ROUND((ROUND(((AE47-((EU47*1.1)))*AV47*1),2)*BS47),2)) -> 1.07 | CS47: =ROUND((ROUND((AE47*AV47*1),2)*BS47),2) -> 0 | CT47: =ROUND((ROUND((AF47*AV47*1),2)*BA47),2) -> 4236.98 | CU47: =AG47 -> 0 | CV47: =(AH47*AV47) -> 5.7585 | CW47: =AI47 -> 0 | CX47: =AJ47 -> 0 | CY47: =(((S47+R47)*AT47)/100) -> 3813.282 | CZ47: =(((S47+R47)*AU47)/100) -> 1949.0108 | DE47: *1,1 | DF47: *1,1 | DG47: *1,1 | DI47: *1,1 | DJ47: *1,1 | DN47: 0 | DO47: 0 | DP47: 1 | DQ47: 1 | DU47: 1013 | DV47: 1 ШТ. | DW47: 1 ШТ. | DX47: 1 | EE47: 58162630 | EF47: 40 | EG47: Монтаж оборудования | EH47: 0 | EJ47: 2 | EK47: 68 | EL47: ТСН-2001.4-10. Прокладка и монтаж сетей связи | EM47: ТСН-2001.4-10-1 | EO47: Поправка: Гл.12.Прил.8.п.8. 5_12.00.01.11.003 | EQ47: 0 | ER47: 69.67 | ES47: 2.67 | ET47: 0.1 | EU47: 0 | EV47: 66.9 | EW47: 5 | EX47: 0 | EY47: 0 | FQ47: 0 | FR47: 0 | FS47: 0 | FX47: 90 | FY47: 46 | GD47: 1 | GF47: -1786768696 | GG47: 2 | GH47: 1 | GI47: 2 | GJ47: 0 | GK47: 0 | GL47: =ROUND(IF(AND(BH47=3,BI47=3,FS47<>0),P47,0),2) -> 0 | GM47: =ROUND(O47+X47+Y47,2)+GX47 -> 10002.74 | GN47: =IF(OR(BI47=0,BI47=1),GM47-GX47,0) -> 0 | GO47: =IF(BI47=2,GM47-GX47,0) -> 10002.74 | GP47: =IF(BI47=4,GM47-GX47,0) -> 0 | GR47: 0 | GS47: 3 | GT47: 0 | GV47: =ROUND((GT47),6) -> 0 | GW47: 1 | GX47: =ROUND(HC47*I47,2) -> 0 | HA47: 0 | HB47: 0 | HC47: =GV47*GW47 -> 0 | HS47: 0 | IK47: 0
A48: 18 | B48: 1 | E48: 5,1 | F48: КА 6 | G48: Пульт диспетчера Тромбон ПД | H48: шт. | I48: =I46*J48 -> 1 | J48: 1 | K48: 1 | O48: =ROUND(CP48,2) -> 9139.9 | P48: =ROUND((ROUND((AC48*I48),2)*BC48),2) -> 9139.9 | Q48: =(ROUND((ROUND(((ET48)*AV48*I48),2)*BB48),2)+ROUND((ROUND(((AE48-(EU48))*AV48*I48),2)*BS48),2)) -> 0 | R48: =ROUND((ROUND((AE48*AV48*I48),2)*BS48),2) -> 0 | S48: =ROUND((ROUND((AF48*AV48*I48),2)*BA48),2) -> 0 | T48: =ROUND(CU48*I48,2) -> 0 | U48: =CV48*I48 -> 0 | V48: =CW48*I48 -> 0 | W48: =ROUND(CX48*I48,2) -> 0 | X48: =ROUND(CY48,2) -> 0 | Y48: =ROUND(CZ48,2) -> 0 | AA48: 56511233 | AB48: =ROUND((AC48+AD48+AF48),6) -> 9139.9 | AC48: =ROUND((ES48),6) -> 9139.9 | AD48: =ROUND((((ET48)-(EU48))+AE48),6) -> 0 | AE48: =ROUND((EU48),6) -> 0 | AF48: =ROUND((EV48),6) -> 0 | AG48: =ROUND((AP48),6) -> 0 | AH48: =(EW48) -> 0 | AI48: =(EX48) -> 0 | AJ48: =(AS48) -> 0 | AK48: 9139.9 | AL48: 9139.9 | AM48: 0 | AN48: 0 | AO48: 0 | AP48: 0 | AQ48: 0 | AR48: 0 | AS48: 0 | AT48: 0 | AU48: 0 | AV48: 1 | AW48: 1 | AZ48: 1 | BA48: 1 | BB48: 1 | BC48: 1 | BH48: 3 | BI48: 3 | BM48: 746 | BN48: 0 | BP48: 0 | BQ48: 130 | BR48: 0 | BS48: 1 | BT48: 1 | BU48: 1 | BV48: 1 | BW48: 1 | BX48: 1 | BZ48: 90 | CA48: 46 | CE48: 30 | CF48: 0 | CG48: 0 | CM48: 0 | CO48: 0 | CP48: =(P48+Q48+S48) -> 9139.9 | CQ48: =ROUND((ROUND((AC48*1),2)*BC48),2) -> 9139.9 | CR48: =(ROUND((ROUND(((ET48)*AV48*1),2)*BB48),2)+ROUND((ROUND(((AE48-(EU48))*AV48*1),2)*BS48),2)) -> 0 | CS48: =ROUND((ROUND((AE48*AV48*1),2)*BS48),2) -> 0 | CT48: =ROUND((ROUND((AF48*AV48*1),2)*BA48),2) -> 0 | CU48: =AG48 -> 0 | CV48: =(AH48*AV48) -> 0 | CW48: =AI48 -> 0 | CX48: =AJ48 -> 0 | CY48: =(((S48+R48)*AT48)/100) -> 0 | CZ48: =(((S48+R48)*AU48)/100) -> 0 | DN48: 0 | DO48: 0 | DP48: 1 | DQ48: 1 | DU48: 1010 | DV48: шт. | DW48: шт. | DX48: 1 | EE48: 58162750 | EF48: 130 | EG48: Сметная стоимость оборудования | EH48: 0 | EJ48: 3 | EK48: 746 | EL48: ТСН-2001.13. Сметная стоимость оборудования | EM48: ТСН-2001.13 | EQ48: 0 | ER48: 0 | ES48: 9139.9 | ET48: 0 | EU48: 0 | EV48: 0 | EW48: 0 | EX48: 0 | FQ48: 0 | FR48: =P48 -> 9139.9 | FS48: 0 | FX48: 90 | FY48: 46 | GA48: [80 599,79 / 1,2 / 7,66] + 3% Трансп + 1,2% Заг.скл | GD48: 1 | GF48: -1974328641 | GG48: 2 | GH48: 4 | GI48: -2 | GJ48: 0 | GK48: 0 | GL48: =ROUND(IF(AND(BH48=3,BI48=3,FS48<>0),P48,0),2) -> 0 | GM48: =ROUND(O48+X48+Y48,2)+GX48 -> 9139.9 | GN48: =IF(OR(BI48=0,BI48=1),GM48-GX48,0) -> 0 | GO48: =IF(BI48=2,GM48-GX48,0) -> 0 | GP48: =IF(BI48=4,GM48-GX48,0) -> 0 | GR48: 0 | GS48: 2 | GT48: 0 | GV48: =ROUND((GT48),6) -> 0 | GW48: 1 | GX48: =ROUND(HC48*I48,2) -> 0 | HA48: 0 | HB48: 0 | HC48: =GV48*GW48 -> 0 | HE48: 3 | HF48: 1,2 | HS48: 0 | IK48: 0
A49: 18 | B49: 1 | E49: 5,1 | F49: КА 6 | G49: Пульт диспетчера Тромбон ПД | H49: шт. | I49: =I47*J49 -> 1 | J49: 1 | K49: 1 | O49: =ROUND(CP49,2) -> 70011.63 | P49: =ROUND((ROUND((AC49*I49),2)*BC49),2) -> 70011.63 | Q49: =(ROUND((ROUND(((ET49)*AV49*I49),2)*BB49),2)+ROUND((ROUND(((AE49-(EU49))*AV49*I49),2)*BS49),2)) -> 0 | R49: =ROUND((ROUND((AE49*AV49*I49),2)*BS49),2) -> 0 | S49: =ROUND((ROUND((AF49*AV49*I49),2)*BA49),2) -> 0 | T49: =ROUND(CU49*I49,2) -> 0 | U49: =CV49*I49 -> 0 | V49: =CW49*I49 -> 0 | W49: =ROUND(CX49*I49,2) -> 0 | X49: =ROUND(CY49,2) -> 0 | Y49: =ROUND(CZ49,2) -> 0 | AA49: 56511235 | AB49: =ROUND((AC49+AD49+AF49),6) -> 9139.9 | AC49: =ROUND((ES49),6) -> 9139.9 | AD49: =ROUND((((ET49)-(EU49))+AE49),6) -> 0 | AE49: =ROUND((EU49),6) -> 0 | AF49: =ROUND((EV49),6) -> 0 | AG49: =ROUND((AP49),6) -> 0 | AH49: =(EW49) -> 0 | AI49: =(EX49) -> 0 | AJ49: =(AS49) -> 0 | AK49: 9139.9 | AL49: 9139.9 | AM49: 0 | AN49: 0 | AO49: 0 | AP49: 0 | AQ49: 0 | AR49: 0 | AS49: 0 | AT49: 0 | AU49: 0 | AV49: 1 | AW49: 1 | AZ49: 1 | BA49: 1 | BB49: 1 | BC49: 7.66 | BH49: 3 | BI49: 3 | BM49: 746 | BN49: 0 | BP49: 0 | BQ49: 130 | BR49: 0 | BS49: 1 | BT49: 1 | BU49: 1 | BV49: 1 | BW49: 1 | BX49: 1 | BZ49: 90 | CA49: 46 | CE49: 30 | CF49: 0 | CG49: 0 | CM49: 0 | CO49: 0 | CP49: =(P49+Q49+S49) -> 70011.63 | CQ49: =ROUND((ROUND((AC49*1),2)*BC49),2) -> 70011.63 | CR49: =(ROUND((ROUND(((ET49)*AV49*1),2)*BB49),2)+ROUND((ROUND(((AE49-(EU49))*AV49*1),2)*BS49),2)) -> 0 | CS49: =ROUND((ROUND((AE49*AV49*1),2)*BS49),2) -> 0 | CT49: =ROUND((ROUND((AF49*AV49*1),2)*BA49),2) -> 0 | CU49: =AG49 -> 0 | CV49: =(AH49*AV49) -> 0 | CW49: =AI49 -> 0 | CX49: =AJ49 -> 0 | CY49: =(((S49+R49)*AT49)/100) -> 0 | CZ49: =(((S49+R49)*AU49)/100) -> 0 | DN49: 0 | DO49: 0 | DP49: 1 | DQ49: 1 | DU49: 1010 | DV49: шт. | DW49: шт. | DX49: 1 | EE49: 58162750 | EF49: 130 | EG49: Сметная стоимость оборудования | EH49: 0 | EJ49: 3 | EK49: 746 | EL49: ТСН-2001.13. Сметная стоимость оборудования | EM49: ТСН-2001.13 | EQ49: 0 | ER49: 70011.66 | ES49: 9139.9 | ET49: 0 | EU49: 0 | EV49: 0 | EW49: 0 | EX49: 0 | EZ49: 5 | FC49: 1 | FD49: 18 | FF49: 80599.79 | FQ49: 0 | FR49: =P49 -> 70011.63 | FS49: 0 | FX49: 90 | FY49: 46 | GA49: [80 599,79 / 1,2 / 7,66] + 3% Трансп + 1,2% Заг.скл | GD49: 1 | GF49: -1974328641 | GG49: 2 | GH49: 3 | GI49: 5 | GJ49: 0 | GK49: 0 | GL49: =ROUND(IF(AND(BH49=3,BI49=3,FS49<>0),P49,0),2) -> 0 | GM49: =ROUND(O49+X49+Y49,2)+GX49 -> 70011.63 | GN49: =IF(OR(BI49=0,BI49=1),GM49-GX49,0) -> 0 | GO49: =IF(BI49=2,GM49-GX49,0) -> 0 | GP49: =IF(BI49=4,GM49-GX49,0) -> 0 | GR49: 1 | GS49: 1 | GT49: 0 | GV49: =ROUND((GT49),6) -> 0 | GW49: 1 | GX49: =ROUND(HC49*I49,2) -> 0 | HA49: 0 | HB49: 0 | HC49: =GV49*GW49 -> 0 | HE49: 3 | HF49: 1,2 | HS49: 0 | IK49: 0
A50: 17 | B50: 1 | D50: =ROW(EtalonRes!A74) -> 74 | E50: 6 | F50: 4.10-177-1 | G50: Монтаж устройства связи с согласующим устройством (вызывная панель) | H50: 10 шт. | I50: =ROUND(17/10,9) -> 1.7 | J50: 0 | K50: =ROUND(17/10,9) -> 1.7 | O50: =ROUND(CP50,2) -> 461.33 | P50: =ROUND((ROUND((AC50*AW50*I50),2)*BC50),2) -> 4.15 | Q50: =(ROUND((ROUND((((ET50*1.1))*AV50*I50),2)*BB50),2)+ROUND((ROUND(((AE50-((EU50*1.1)))*AV50*I50),2)*BS50),2)) -> 11.88 | R50: =ROUND((ROUND((AE50*AV50*I50),2)*BS50),2) -> 1.49 | S50: =ROUND((ROUND((AF50*AV50*I50),2)*BA50),2) -> 445.3 | T50: =ROUND(CU50*I50,2) -> 0 | U50: =CV50*I50 -> 28.66351 | V50: =CW50*I50 -> 0 | W50: =ROUND(CX50*I50,2) -> 0 | X50: =ROUND(CY50,2) -> 402.11 | Y50: =ROUND(CZ50,2) -> 205.52 | AA50: 56511233 | AB50: =ROUND((AC50+AD50+AF50),6) -> 259.301 | AC50: =ROUND((ES50),6) -> 2.44 | AD50: =ROUND(((((ET50*1.1))-((EU50*1.1)))+AE50),6) -> 6.677 | AE50: =ROUND(((EU50*1.1)),6) -> 0.836 | AF50: =ROUND(((EV50*1.1)),6) -> 250.184 | AG50: =ROUND((AP50),6) -> 0 | AH50: =((EW50*1.1)) -> 16.104 | AI50: =((EX50*1.1)) -> 0 | AJ50: =(AS50) -> 0 | AK50: 235.95 | AL50: 2.44 | AM50: 6.07 | AN50: 0.76 | AO50: 227.44 | AP50: 0 | AQ50: 14.64 | AR50: 0 | AS50: 0 | AT50: 90 | AU50: 46 | AV50: 1.047 | AW50: 1 | AZ50: 1 | BA50: 1 | BB50: 1 | BC50: 1 | BH50: 0 | BI50: 2 | BJ50: ТСН-2001.4 Доп. 80, Сб. 10, т. 177, поз. 1 | BM50: 68 | BN50: 0 | BO50: 4.10-177-1 | BP50: 1 | BQ50: 40 | BR50: 0 | BS50: 1 | BT50: 1 | BU50: 1 | BV50: 1 | BW50: 1 | BX50: 1 | BZ50: 90 | CA50: 46 | CE50: 30 | CF50: 0 | CG50: 0 | CM50: 0 | CO50: 0 | CP50: =(P50+Q50+S50) -> 461.33 | CQ50: =ROUND((ROUND((AC50*AW50*1),2)*BC50),2) -> 2.44 | CR50: =(ROUND((ROUND((((ET50*1.1))*AV50*1),2)*BB50),2)+ROUND((ROUND(((AE50-((EU50*1.1)))*AV50*1),2)*BS50),2)) -> 6.99 | CS50: =ROUND((ROUND((AE50*AV50*1),2)*BS50),2) -> 0.88 | CT50: =ROUND((ROUND((AF50*AV50*1),2)*BA50),2) -> 261.94 | CU50: =AG50 -> 0 | CV50: =(AH50*AV50) -> 16.860888 | CW50: =AI50 -> 0 | CX50: =AJ50 -> 0 | CY50: =(((S50+R50)*AT50)/100) -> 402.111 | CZ50: =(((S50+R50)*AU50)/100) -> 205.5234 | DE50: *1,1 | DF50: *1,1 | DG50: *1,1 | DI50: *1,1 | DJ50: *1,1 | DN50: 0 | DO50: 0 | DP50: 1 | DQ50: 1 | DU50: 1010 | DV50: 10 шт. | DW50: 10 шт. | DX50: 10 | EE50: 58162630 | EF50: 40 | EG50: Монтаж оборудования | EH50: 0 | EJ50: 2 | EK50: 68 | EL50: ТСН-2001.4-10. Прокладка и монтаж сетей связи | EM50: ТСН-2001.4-10-1 | EO50: Поправка: Гл.12.Прил.8.п.8. 5_12.00.01.11.003 | EQ50: 0 | ER50: 235.95 | ES50: 2.44 | ET50: 6.07 | EU50: 0.76 | EV50: 227.44 | EW50: 14.64 | EX50: 0 | EY50: 0 | FQ50: 0 | FR50: 0 | FS50: 0 | FX50: 90 | FY50: 46 | GD50: 1 | GF50: -1147212458 | GG50: 2 | GH50: 1 | GI50: 2 | GJ50: 0 | GK50: 0 | GL50: =ROUND(IF(AND(BH50=3,BI50=3,FS50<>0),P50,0),2) -> 0 | GM50: =ROUND(O50+X50+Y50,2)+GX50 -> 1068.96 | GN50: =IF(OR(BI50=0,BI50=1),GM50-GX50,0) -> 0 | GO50: =IF(BI50=2,GM50-GX50,0) -> 1068.96 | GP50: =IF(BI50=4,GM50-GX50,0) -> 0 | GR50: 0 | GS50: 3 | GT50: 0 | GV50: =ROUND((GT50),6) -> 0 | GW50: 1 | GX50: =ROUND(HC50*I50,2) -> 0 | HA50: 0 | HB50: 0 | HC50: =GV50*GW50 -> 0 | HS50: 0 | IK50: 0
A51: 17 | B51: 1 | D51: =ROW(EtalonRes!A80) -> 80 | E51: 6 | F51: 4.10-177-1 | G51: Монтаж устройства связи с согласующим устройством (вызывная панель) | H51: 10 шт. | I51: =ROUND(17/10,9) -> 1.7 | J51: 0 | K51: =ROUND(17/10,9) -> 1.7 | O51: =ROUND(CP51,2) -> 24694.54 | P51: =ROUND((ROUND((AC51*AW51*I51),2)*BC51),2) -> 30 | Q51: =(ROUND((ROUND((((ET51*1.1))*AV51*I51),2)*BB51),2)+ROUND((ROUND(((AE51-((EU51*1.1)))*AV51*I51),2)*BS51),2)) -> 177.49 | R51: =ROUND((ROUND((AE51*AV51*I51),2)*BS51),2) -> 81.94 | S51: =ROUND((ROUND((AF51*AV51*I51),2)*BA51),2) -> 24487.05 | T51: =ROUND(CU51*I51,2) -> 0 | U51: =CV51*I51 -> 28.66351 | V51: =CW51*I51 -> 0 | W51: =ROUND(CX51*I51,2) -> 0 | X51: =ROUND(CY51,2) -> 22112.09 | Y51: =ROUND(CZ51,2) -> 11301.74 | AA51: 56511235 | AB51: =ROUND((AC51+AD51+AF51),6) -> 259.301 | AC51: =ROUND((ES51),6) -> 2.44 | AD51: =ROUND(((((ET51*1.1))-((EU51*1.1)))+AE51),6) -> 6.677 | AE51: =ROUND(((EU51*1.1)),6) -> 0.836 | AF51: =ROUND(((EV51*1.1)),6) -> 250.184 | AG51: =ROUND((AP51),6) -> 0 | AH51: =((EW51*1.1)) -> 16.104 | AI51: =((EX51*1.1)) -> 0 | AJ51: =(AS51) -> 0 | AK51: 235.95 | AL51: 2.44 | AM51: 6.07 | AN51: 0.76 | AO51: 227.44 | AP51: 0 | AQ51: 14.64 | AR51: 0 | AS51: 0 | AT51: 90 | AU51: 46 | AV51: 1.047 | AW51: 1 | AZ51: 1 | BA51: 54.99 | BB51: 14.94 | BC51: 7.23 | BH51: 0 | BI51: 2 | BJ51: ТСН-2001.4 Доп. 80, Сб. 10, т. 177, поз. 1 | BM51: 68 | BN51: 0 | BO51: 4.10-177-1 | BP51: 1 | BQ51: 40 | BR51: 0 | BS51: 54.99 | BT51: 1 | BU51: 1 | BV51: 1 | BW51: 1 | BX51: 1 | BZ51: 90 | CA51: 46 | CE51: 30 | CF51: 0 | CG51: 0 | CM51: 0 | CO51: 0 | CP51: =(P51+Q51+S51) -> 24694.54 | CQ51: =ROUND((ROUND((AC51*AW51*1),2)*BC51),2) -> 17.64 | CR51: =(ROUND((ROUND((((ET51*1.1))*AV51*1),2)*BB51),2)+ROUND((ROUND(((AE51-((EU51*1.1)))*AV51*1),2)*BS51),2)) -> 104.43 | CS51: =ROUND((ROUND((AE51*AV51*1),2)*BS51),2) -> 48.39 | CT51: =ROUND((ROUND((AF51*AV51*1),2)*BA51),2) -> 14404.08 | CU51: =AG51 -> 0 | CV51: =(AH51*AV51) -> 16.860888 | CW51: =AI51 -> 0 | CX51: =AJ51 -> 0 | CY51: =(((S51+R51)*AT51)/100) -> 22112.091 | CZ51: =(((S51+R51)*AU51)/100) -> 11301.735 | DE51: *1,1 | DF51: *1,1 | DG51: *1,1 | DI51: *1,1 | DJ51: *1,1 | DN51: 0 | DO51: 0 | DP51: 1 | DQ51: 1 | DU51: 1010 | DV51: 10 шт. | DW51: 10 шт. | DX51: 10 | EE51: 58162630 | EF51: 40 | EG51: Монтаж оборудования | EH51: 0 | EJ51: 2 | EK51: 68 | EL51: ТСН-2001.4-10. Прокладка и монтаж сетей связи | EM51: ТСН-2001.4-10-1 | EO51: Поправка: Гл.12.Прил.8.п.8. 5_12.00.01.11.003 | EQ51: 0 | ER51: 235.95 | ES51: 2.44 | ET51: 6.07 | EU51: 0.76 | EV51: 227.44 | EW51: 14.64 | EX51: 0 | EY51: 0 | FQ51: 0 | FR51: 0 | FS51: 0 | FX51: 90 | FY51: 46 | GD51: 1 | GF51: -1147212458 | GG51: 2 | GH51: 1 | GI51: 2 | GJ51: 0 | GK51: 0 | GL51: =ROUND(IF(AND(BH51=3,BI51=3,FS51<>0),P51,0),2) -> 0 | GM51: =ROUND(O51+X51+Y51,2)+GX51 -> 58108.37 | GN51: =IF(OR(BI51=0,BI51=1),GM51-GX51,0) -> 0 | GO51: =IF(BI51=2,GM51-GX51,0) -> 58108.37 | GP51: =IF(BI51=4,GM51-GX51,0) -> 0 | GR51: 0 | GS51: 3 | GT51: 0 | GV51: =ROUND((GT51),6) -> 0 | GW51: 1 | GX51: =ROUND(HC51*I51,2) -> 0 | HA51: 0 | HB51: 0 | HC51: =GV51*GW51 -> 0 | HS51: 0 | IK51: 0
A52: 18 | B52: 1 | E52: 6,1 | F52: КА 7 | G52: Абонентское вызывное устройство Тромбон АВУ | H52: шт. | I52: =I50*J52 -> 17 | J52: 10 | K52: 10 | O52: =ROUND(CP52,2) -> 56794.11 | P52: =ROUND((ROUND((AC52*I52),2)*BC52),2) -> 56794.11 | Q52: =(ROUND((ROUND(((ET52)*AV52*I52),2)*BB52),2)+ROUND((ROUND(((AE52-(EU52))*AV52*I52),2)*BS52),2)) -> 0 | R52: =ROUND((ROUND((AE52*AV52*I52),2)*BS52),2) -> 0 | S52: =ROUND((ROUND((AF52*AV52*I52),2)*BA52),2) -> 0 | T52: =ROUND(CU52*I52,2) -> 0 | U52: =CV52*I52 -> 0 | V52: =CW52*I52 -> 0 | W52: =ROUND(CX52*I52,2) -> 0 | X52: =ROUND(CY52,2) -> 0 | Y52: =ROUND(CZ52,2) -> 0 | AA52: 56511233 | AB52: =ROUND((AC52+AD52+AF52),6) -> 3340.83 | AC52: =ROUND((ES52),6) -> 3340.83 | AD52: =ROUND((((ET52)-(EU52))+AE52),6) -> 0 | AE52: =ROUND((EU52),6) -> 0 | AF52: =ROUND((EV52),6) -> 0 | AG52: =ROUND((AP52),6) -> 0 | AH52: =(EW52) -> 0 | AI52: =(EX52) -> 0 | AJ52: =(AS52) -> 0 | AK52: 3340.83 | AL52: 3340.83 | AM52: 0 | AN52: 0 | AO52: 0 | AP52: 0 | AQ52: 0 | AR52: 0 | AS52: 0 | AT52: 0 | AU52: 0 | AV52: 1 | AW52: 1 | AZ52: 1 | BA52: 1 | BB52: 1 | BC52: 1 | BH52: 3 | BI52: 3 | BM52: 746 | BN52: 0 | BP52: 0 | BQ52: 130 | BR52: 0 | BS52: 1 | BT52: 1 | BU52: 1 | BV52: 1 | BW52: 1 | BX52: 1 | BZ52: 90 | CA52: 46 | CE52: 30 | CF52: 0 | CG52: 0 | CM52: 0 | CO52: 0 | CP52: =(P52+Q52+S52) -> 56794.11 | CQ52: =ROUND((ROUND((AC52*1),2)*BC52),2) -> 3340.83 | CR52: =(ROUND((ROUND(((ET52)*AV52*1),2)*BB52),2)+ROUND((ROUND(((AE52-(EU52))*AV52*1),2)*BS52),2)) -> 0 | CS52: =ROUND((ROUND((AE52*AV52*1),2)*BS52),2) -> 0 | CT52: =ROUND((ROUND((AF52*AV52*1),2)*BA52),2) -> 0 | CU52: =AG52 -> 0 | CV52: =(AH52*AV52) -> 0 | CW52: =AI52 -> 0 | CX52: =AJ52 -> 0 | CY52: =(((S52+R52)*AT52)/100) -> 0 | CZ52: =(((S52+R52)*AU52)/100) -> 0 | DN52: 0 | DO52: 0 | DP52: 1 | DQ52: 1 | DU52: 1010 | DV52: шт. | DW52: шт. | DX52: 1 | EE52: 58162750 | EF52: 130 | EG52: Сметная стоимость оборудования | EH52: 0 | EJ52: 3 | EK52: 746 | EL52: ТСН-2001.13. Сметная стоимость оборудования | EM52: ТСН-2001.13 | EQ52: 0 | ER52: 0 | ES52: 3340.83 | ET52: 0 | EU52: 0 | EV52: 0 | EW52: 0 | EX52: 0 | FQ52: 0 | FR52: =P52 -> 56794.11 | FS52: 0 | FX52: 90 | FY52: 46 | GA52: [29 461 / 1,2 / 7,66] + 3% Трансп + 1,2% Заг.скл | GD52: 1 | GF52: 851379823 | GG52: 2 | GH52: 4 | GI52: -2 | GJ52: 0 | GK52: 0 | GL52: =ROUND(IF(AND(BH52=3,BI52=3,FS52<>0),P52,0),2) -> 0 | GM52: =ROUND(O52+X52+Y52,2)+GX52 -> 56794.11 | GN52: =IF(OR(BI52=0,BI52=1),GM52-GX52,0) -> 0 | GO52: =IF(BI52=2,GM52-GX52,0) -> 0 | GP52: =IF(BI52=4,GM52-GX52,0) -> 0 | GR52: 0 | GS52: 2 | GT52: 0 | GV52: =ROUND((GT52),6) -> 0 | GW52: 1 | GX52: =ROUND(HC52*I52,2) -> 0 | HA52: 0 | HB52: 0 | HC52: =GV52*GW52 -> 0 | HE52: 3 | HF52: 1,2 | HS52: 0 | IK52: 0
A53: 18 | B53: 1 | E53: 6,1 | F53: КА 7 | G53: Абонентское вызывное устройство Тромбон АВУ | H53: шт. | I53: =I51*J53 -> 17 | J53: 10 | K53: 10 | O53: =ROUND(CP53,2) -> 435042.88 | P53: =ROUND((ROUND((AC53*I53),2)*BC53),2) -> 435042.88 | Q53: =(ROUND((ROUND(((ET53)*AV53*I53),2)*BB53),2)+ROUND((ROUND(((AE53-(EU53))*AV53*I53),2)*BS53),2)) -> 0 | R53: =ROUND((ROUND((AE53*AV53*I53),2)*BS53),2) -> 0 | S53: =ROUND((ROUND((AF53*AV53*I53),2)*BA53),2) -> 0 | T53: =ROUND(CU53*I53,2) -> 0 | U53: =CV53*I53 -> 0 | V53: =CW53*I53 -> 0 | W53: =ROUND(CX53*I53,2) -> 0 | X53: =ROUND(CY53,2) -> 0 | Y53: =ROUND(CZ53,2) -> 0 | AA53: 56511235 | AB53: =ROUND((AC53+AD53+AF53),6) -> 3340.83 | AC53: =ROUND((ES53),6) -> 3340.83 | AD53: =ROUND((((ET53)-(EU53))+AE53),6) -> 0 | AE53: =ROUND((EU53),6) -> 0 | AF53: =ROUND((EV53),6) -> 0 | AG53: =ROUND((AP53),6) -> 0 | AH53: =(EW53) -> 0 | AI53: =(EX53) -> 0 | AJ53: =(AS53) -> 0 | AK53: 3340.83 | AL53: 3340.83 | AM53: 0 | AN53: 0 | AO53: 0 | AP53: 0 | AQ53: 0 | AR53: 0 | AS53: 0 | AT53: 0 | AU53: 0 | AV53: 1 | AW53: 1 | AZ53: 1 | BA53: 1 | BB53: 1 | BC53: 7.66 | BH53: 3 | BI53: 3 | BM53: 746 | BN53: 0 | BP53: 0 | BQ53: 130 | BR53: 0 | BS53: 1 | BT53: 1 | BU53: 1 | BV53: 1 | BW53: 1 | BX53: 1 | BZ53: 90 | CA53: 46 | CE53: 30 | CF53: 0 | CG53: 0 | CM53: 0 | CO53: 0 | CP53: =(P53+Q53+S53) -> 435042.88 | CQ53: =ROUND((ROUND((AC53*1),2)*BC53),2) -> 25590.76 | CR53: =(ROUND((ROUND(((ET53)*AV53*1),2)*BB53),2)+ROUND((ROUND(((AE53-(EU53))*AV53*1),2)*BS53),2)) -> 0 | CS53: =ROUND((ROUND((AE53*AV53*1),2)*BS53),2) -> 0 | CT53: =ROUND((ROUND((AF53*AV53*1),2)*BA53),2) -> 0 | CU53: =AG53 -> 0 | CV53: =(AH53*AV53) -> 0 | CW53: =AI53 -> 0 | CX53: =AJ53 -> 0 | CY53: =(((S53+R53)*AT53)/100) -> 0 | CZ53: =(((S53+R53)*AU53)/100) -> 0 | DN53: 0 | DO53: 0 | DP53: 1 | DQ53: 1 | DU53: 1010 | DV53: шт. | DW53: шт. | DX53: 1 | EE53: 58162750 | EF53: 130 | EG53: Сметная стоимость оборудования | EH53: 0 | EJ53: 3 | EK53: 746 | EL53: ТСН-2001.13. Сметная стоимость оборудования | EM53: ТСН-2001.13 | EQ53: 0 | ER53: 25590.8 | ES53: 3340.83 | ET53: 0 | EU53: 0 | EV53: 0 | EW53: 0 | EX53: 0 | EZ53: 5 | FC53: 1 | FD53: 18 | FF53: 29461 | FQ53: 0 | FR53: =P53 -> 435042.88 | FS53: 0 | FX53: 90 | FY53: 46 | GA53: [29 461 / 1,2 / 7,66] + 3% Трансп + 1,2% Заг.скл | GD53: 1 | GF53: 851379823 | GG53: 2 | GH53: 3 | GI53: 5 | GJ53: 0 | GK53: 0 | GL53: =ROUND(IF(AND(BH53=3,BI53=3,FS53<>0),P53,0),2) -> 0 | GM53: =ROUND(O53+X53+Y53,2)+GX53 -> 435042.88 | GN53: =IF(OR(BI53=0,BI53=1),GM53-GX53,0) -> 0 | GO53: =IF(BI53=2,GM53-GX53,0) -> 0 | GP53: =IF(BI53=4,GM53-GX53,0) -> 0 | GR53: 1 | GS53: 1 | GT53: 0 | GV53: =ROUND((GT53),6) -> 0 | GW53: 1 | GX53: =ROUND(HC53*I53,2) -> 0 | HA53: 0 | HB53: 0 | HC53: =GV53*GW53 -> 0 | HE53: 3 | HF53: 1,2 | HS53: 0 | IK53: 0
A54: 17 | B54: 1 | D54: =ROW(EtalonRes!A84) -> 84 | E54: 7 | F54: 4.10-151-1 | G54: Установка пульта или табло вызывной сигнализации с количеством сигналов до 5 | H54: 1 ШТ. | I54: 1 | J54: 0 | K54: 1 | O54: =ROUND(CP54,2) -> 54.62 | P54: =ROUND((ROUND((AC54*AW54*I54),2)*BC54),2) -> 1.78 | Q54: =(ROUND((ROUND((((ET54*1.1))*AV54*I54),2)*BB54),2)+ROUND((ROUND(((AE54-((EU54*1.1)))*AV54*I54),2)*BS54),2)) -> 0.09 | R54: =ROUND((ROUND((AE54*AV54*I54),2)*BS54),2) -> 0 | S54: =ROUND((ROUND((AF54*AV54*I54),2)*BA54),2) -> 52.75 | T54: =ROUND(CU54*I54,2) -> 0 | U54: =CV54*I54 -> 4.6068 | V54: =CW54*I54 -> 0 | W54: =ROUND(CX54*I54,2) -> 0 | X54: =ROUND(CY54,2) -> 47.48 | Y54: =ROUND(CZ54,2) -> 24.27 | AA54: 56511233 | AB54: =ROUND((AC54+AD54+AF54),6) -> 52.248 | AC54: =ROUND((ES54),6) -> 1.78 | AD54: =ROUND(((((ET54*1.1))-((EU54*1.1)))+AE54),6) -> 0.088 | AE54: =ROUND(((EU54*1.1)),6) -> 0 | AF54: =ROUND(((EV54*1.1)),6) -> 50.38 | AG54: =ROUND((AP54),6) -> 0 | AH54: =((EW54*1.1)) -> 4.4 | AI54: =((EX54*1.1)) -> 0 | AJ54: =(AS54) -> 0 | AK54: 47.66 | AL54: 1.78 | AM54: 0.08 | AN54: 0 | AO54: 45.8 | AP54: 0 | AQ54: 4 | AR54: 0 | AS54: 0 | AT54: 90 | AU54: 46 | AV54: 1.047 | AW54: 1 | AZ54: 1 | BA54: 1 | BB54: 1 | BC54: 1 | BH54: 0 | BI54: 2 | BJ54: ТСН-2001.4 Доп. 67, Сб. 10, т. 151, поз. 1 | BM54: 68 | BN54: 0 | BO54: 4.10-151-1 | BP54: 1 | BQ54: 40 | BR54: 0 | BS54: 1 | BT54: 1 | BU54: 1 | BV54: 1 | BW54: 1 | BX54: 1 | BZ54: 90 | CA54: 46 | CE54: 30 | CF54: 0 | CG54: 0 | CM54: 0 | CO54: 0 | CP54: =(P54+Q54+S54) -> 54.62 | CQ54: =ROUND((ROUND((AC54*AW54*1),2)*BC54),2) -> 1.78 | CR54: =(ROUND((ROUND((((ET54*1.1))*AV54*1),2)*BB54),2)+ROUND((ROUND(((AE54-((EU54*1.1)))*AV54*1),2)*BS54),2)) -> 0.09 | CS54: =ROUND((ROUND((AE54*AV54*1),2)*BS54),2) -> 0 | CT54: =ROUND((ROUND((AF54*AV54*1),2)*BA54),2) -> 52.75 | CU54: =AG54 -> 0 | CV54: =(AH54*AV54) -> 4.6068 | CW54: =AI54 -> 0 | CX54: =AJ54 -> 0 | CY54: =(((S54+R54)*AT54)/100) -> 47.475 | CZ54: =(((S54+R54)*AU54)/100) -> 24.265 | DE54: *1,1 | DF54: *1,1 | DG54: *1,1 | DI54: *1,1 | DJ54: *1,1 | DN54: 0 | DO54: 0 | DP54: 1 | DQ54: 1 | DU54: 1013 | DV54: 1 ШТ. | DW54: 1 ШТ. | DX54: 1 | EE54: 58162630 | EF54: 40 | EG54: Монтаж оборудования | EH54: 0 | EJ54: 2 | EK54: 68 | EL54: ТСН-2001.4-10. Прокладка и монтаж сетей связи | EM54: ТСН-2001.4-10-1 | EO54: Поправка: Гл.12.Прил.8.п.8. 5_12.00.01.11.003 | EQ54: 0 | ER54: 47.66 | ES54: 1.78 | ET54: 0.08 | EU54: 0 | EV54: 45.8 | EW54: 4 | EX54: 0 | EY54: 0 | FQ54: 0 | FR54: 0 | FS54: 0 | FX54: 90 | FY54: 46 | GD54: 1 | GF54: -852032405 | GG54: 2 | GH54: 1 | GI54: 2 | GJ54: 0 | GK54: 0 | GL54: =ROUND(IF(AND(BH54=3,BI54=3,FS54<>0),P54,0),2) -> 0 | GM54: =ROUND(O54+X54+Y54,2)+GX54 -> 126.37 | GN54: =IF(OR(BI54=0,BI54=1),GM54-GX54,0) -> 0 | GO54: =IF(BI54=2,GM54-GX54,0) -> 126.37 | GP54: =IF(BI54=4,GM54-GX54,0) -> 0 | GR54: 0 | GS54: 3 | GT54: 0 | GV54: =ROUND((GT54),6) -> 0 | GW54: 1 | GX54: =ROUND(HC54*I54,2) -> 0 | HA54: 0 | HB54: 0 | HC54: =GV54*GW54 -> 0 | HS54: 0 | IK54: 0
A55: 17 | B55: 1 | D55: =ROW(EtalonRes!A88) -> 88 | E55: 7 | F55: 4.10-151-1 | G55: Установка пульта или табло вызывной сигнализации с количеством сигналов до 5 | H55: 1 ШТ. | I55: 1 | J55: 0 | K55: 1 | O55: =ROUND(CP55,2) -> 2903.1 | P55: =ROUND((ROUND((AC55*AW55*I55),2)*BC55),2) -> 1.6 | Q55: =(ROUND((ROUND((((ET55*1.1))*AV55*I55),2)*BB55),2)+ROUND((ROUND(((AE55-((EU55*1.1)))*AV55*I55),2)*BS55),2)) -> 0.78 | R55: =ROUND((ROUND((AE55*AV55*I55),2)*BS55),2) -> 0 | S55: =ROUND((ROUND((AF55*AV55*I55),2)*BA55),2) -> 2900.72 | T55: =ROUND(CU55*I55,2) -> 0 | U55: =CV55*I55 -> 4.6068 | V55: =CW55*I55 -> 0 | W55: =ROUND(CX55*I55,2) -> 0 | X55: =ROUND(CY55,2) -> 2610.65 | Y55: =ROUND(CZ55,2) -> 1334.33 | AA55: 56511235 | AB55: =ROUND((AC55+AD55+AF55),6) -> 52.248 | AC55: =ROUND((ES55),6) -> 1.78 | AD55: =ROUND(((((ET55*1.1))-((EU55*1.1)))+AE55),6) -> 0.088 | AE55: =ROUND(((EU55*1.1)),6) -> 0 | AF55: =ROUND(((EV55*1.1)),6) -> 50.38 | AG55: =ROUND((AP55),6) -> 0 | AH55: =((EW55*1.1)) -> 4.4 | AI55: =((EX55*1.1)) -> 0 | AJ55: =(AS55) -> 0 | AK55: 47.66 | AL55: 1.78 | AM55: 0.08 | AN55: 0 | AO55: 45.8 | AP55: 0 | AQ55: 4 | AR55: 0 | AS55: 0 | AT55: 90 | AU55: 46 | AV55: 1.047 | AW55: 1 | AZ55: 1 | BA55: 54.99 | BB55: 8.63 | BC55: 0.9 | BH55: 0 | BI55: 2 | BJ55: ТСН-2001.4 Доп. 67, Сб. 10, т. 151, поз. 1 | BM55: 68 | BN55: 0 | BO55: 4.10-151-1 | BP55: 1 | BQ55: 40 | BR55: 0 | BS55: 54.99 | BT55: 1 | BU55: 1 | BV55: 1 | BW55: 1 | BX55: 1 | BZ55: 90 | CA55: 46 | CE55: 30 | CF55: 0 | CG55: 0 | CM55: 0 | CO55: 0 | CP55: =(P55+Q55+S55) -> 2903.1 | CQ55: =ROUND((ROUND((AC55*AW55*1),2)*BC55),2) -> 1.6 | CR55: =(ROUND((ROUND((((ET55*1.1))*AV55*1),2)*BB55),2)+ROUND((ROUND(((AE55-((EU55*1.1)))*AV55*1),2)*BS55),2)) -> 0.78 | CS55: =ROUND((ROUND((AE55*AV55*1),2)*BS55),2) -> 0 | CT55: =ROUND((ROUND((AF55*AV55*1),2)*BA55),2) -> 2900.72 | CU55: =AG55 -> 0 | CV55: =(AH55*AV55) -> 4.6068 | CW55: =AI55 -> 0 | CX55: =AJ55 -> 0 | CY55: =(((S55+R55)*AT55)/100) -> 2610.648 | CZ55: =(((S55+R55)*AU55)/100) -> 1334.3312 | DE55: *1,1 | DF55: *1,1 | DG55: *1,1 | DI55: *1,1 | DJ55: *1,1 | DN55: 0 | DO55: 0 | DP55: 1 | DQ55: 1 | DU55: 1013 | DV55: 1 ШТ. | DW55: 1 ШТ. | DX55: 1 | EE55: 58162630 | EF55: 40 | EG55: Монтаж оборудования | EH55: 0 | EJ55: 2 | EK55: 68 | EL55: ТСН-2001.4-10. Прокладка и монтаж сетей связи | EM55: ТСН-2001.4-10-1 | EO55: Поправка: Гл.12.Прил.8.п.8. 5_12.00.01.11.003 | EQ55: 0 | ER55: 47.66 | ES55: 1.78 | ET55: 0.08 | EU55: 0 | EV55: 45.8 | EW55: 4 | EX55: 0 | EY55: 0 | FQ55: 0 | FR55: 0 | FS55: 0 | FX55: 90 | FY55: 46 | GD55: 1 | GF55: -852032405 | GG55: 2 | GH55: 1 | GI55: 2 | GJ55: 0 | GK55: 0 | GL55: =ROUND(IF(AND(BH55=3,BI55=3,FS55<>0),P55,0),2) -> 0 | GM55: =ROUND(O55+X55+Y55,2)+GX55 -> 6848.08 | GN55: =IF(OR(BI55=0,BI55=1),GM55-GX55,0) -> 0 | GO55: =IF(BI55=2,GM55-GX55,0) -> 6848.08 | GP55: =IF(BI55=4,GM55-GX55,0) -> 0 | GR55: 0 | GS55: 3 | GT55: 0 | GV55: =ROUND((GT55),6) -> 0 | GW55: 1 | GX55: =ROUND(HC55*I55,2) -> 0 | HA55: 0 | HB55: 0 | HC55: =GV55*GW55 -> 0 | HS55: 0 | IK55: 0
A56: 18 | B56: 1 | E56: 7,1 | F56: КА 8 | G56: Светозвуковое табло Тромбон ИСТ | H56: шт. | I56: =I54*J56 -> 1 | J56: 1 | K56: 1 | O56: =ROUND(CP56,2) -> 1273.69 | P56: =ROUND((ROUND((AC56*I56),2)*BC56),2) -> 1273.69 | Q56: =(ROUND((ROUND(((ET56)*AV56*I56),2)*BB56),2)+ROUND((ROUND(((AE56-(EU56))*AV56*I56),2)*BS56),2)) -> 0 | R56: =ROUND((ROUND((AE56*AV56*I56),2)*BS56),2) -> 0 | S56: =ROUND((ROUND((AF56*AV56*I56),2)*BA56),2) -> 0 | T56: =ROUND(CU56*I56,2) -> 0 | U56: =CV56*I56 -> 0 | V56: =CW56*I56 -> 0 | W56: =ROUND(CX56*I56,2) -> 0 | X56: =ROUND(CY56,2) -> 0 | Y56: =ROUND(CZ56,2) -> 0 | AA56: 56511233 | AB56: =ROUND((AC56+AD56+AF56),6) -> 1273.69 | AC56: =ROUND((ES56),6) -> 1273.69 | AD56: =ROUND((((ET56)-(EU56))+AE56),6) -> 0 | AE56: =ROUND((EU56),6) -> 0 | AF56: =ROUND((EV56),6) -> 0 | AG56: =ROUND((AP56),6) -> 0 | AH56: =(EW56) -> 0 | AI56: =(EX56) -> 0 | AJ56: =(AS56) -> 0 | AK56: 1273.69 | AL56: 1273.69 | AM56: 0 | AN56: 0 | AO56: 0 | AP56: 0 | AQ56: 0 | AR56: 0 | AS56: 0 | AT56: 0 | AU56: 0 | AV56: 1 | AW56: 1 | AZ56: 1 | BA56: 1 | BB56: 1 | BC56: 1 | BH56: 3 | BI56: 3 | BM56: 746 | BN56: 0 | BP56: 0 | BQ56: 130 | BR56: 0 | BS56: 1 | BT56: 1 | BU56: 1 | BV56: 1 | BW56: 1 | BX56: 1 | BZ56: 90 | CA56: 46 | CE56: 30 | CF56: 0 | CG56: 0 | CM56: 0 | CO56: 0 | CP56: =(P56+Q56+S56) -> 1273.69 | CQ56: =ROUND((ROUND((AC56*1),2)*BC56),2) -> 1273.69 | CR56: =(ROUND((ROUND(((ET56)*AV56*1),2)*BB56),2)+ROUND((ROUND(((AE56-(EU56))*AV56*1),2)*BS56),2)) -> 0 | CS56: =ROUND((ROUND((AE56*AV56*1),2)*BS56),2) -> 0 | CT56: =ROUND((ROUND((AF56*AV56*1),2)*BA56),2) -> 0 | CU56: =AG56 -> 0 | CV56: =(AH56*AV56) -> 0 | CW56: =AI56 -> 0 | CX56: =AJ56 -> 0 | CY56: =(((S56+R56)*AT56)/100) -> 0 | CZ56: =(((S56+R56)*AU56)/100) -> 0 | DN56: 0 | DO56: 0 | DP56: 1 | DQ56: 1 | DU56: 1010 | DV56: шт. | DW56: шт. | DX56: 1 | EE56: 58162750 | EF56: 130 | EG56: Сметная стоимость оборудования | EH56: 0 | EJ56: 3 | EK56: 746 | EL56: ТСН-2001.13. Сметная стоимость оборудования | EM56: ТСН-2001.13 | EQ56: 0 | ER56: 0 | ES56: 1273.69 | ET56: 0 | EU56: 0 | EV56: 0 | EW56: 0 | EX56: 0 | FQ56: 0 | FR56: =P56 -> 1273.69 | FS56: 0 | FX56: 90 | FY56: 46 | GA56: [11 232 / 1,2 / 7,66] + 3% Трансп + 1,2% Заг.скл | GD56: 1 | GF56: 1852694742 | GG56: 2 | GH56: 4 | GI56: -2 | GJ56: 0 | GK56: 0 | GL56: =ROUND(IF(AND(BH56=3,BI56=3,FS56<>0),P56,0),2) -> 0 | GM56: =ROUND(O56+X56+Y56,2)+GX56 -> 1273.69 | GN56: =IF(OR(BI56=0,BI56=1),GM56-GX56,0) -> 0 | GO56: =IF(BI56=2,GM56-GX56,0) -> 0 | GP56: =IF(BI56=4,GM56-GX56,0) -> 0 | GR56: 0 | GS56: 2 | GT56: 0 | GV56: =ROUND((GT56),6) -> 0 | GW56: 1 | GX56: =ROUND(HC56*I56,2) -> 0 | HA56: 0 | HB56: 0 | HC56: =GV56*GW56 -> 0 | HE56: 3 | HF56: 1,2 | HS56: 0 | IK56: 0
A57: 18 | B57: 1 | E57: 7,1 | F57: КА 8 | G57: Светозвуковое табло Тромбон ИСТ | H57: шт. | I57: =I55*J57 -> 1 | J57: 1 | K57: 1 | O57: =ROUND(CP57,2) -> 9756.47 | P57: =ROUND((ROUND((AC57*I57),2)*BC57),2) -> 9756.47 | Q57: =(ROUND((ROUND(((ET57)*AV57*I57),2)*BB57),2)+ROUND((ROUND(((AE57-(EU57))*AV57*I57),2)*BS57),2)) -> 0 | R57: =ROUND((ROUND((AE57*AV57*I57),2)*BS57),2) -> 0 | S57: =ROUND((ROUND((AF57*AV57*I57),2)*BA57),2) -> 0 | T57: =ROUND(CU57*I57,2) -> 0 | U57: =CV57*I57 -> 0 | V57: =CW57*I57 -> 0 | W57: =ROUND(CX57*I57,2) -> 0 | X57: =ROUND(CY57,2) -> 0 | Y57: =ROUND(CZ57,2) -> 0 | AA57: 56511235 | AB57: =ROUND((AC57+AD57+AF57),6) -> 1273.69 | AC57: =ROUND((ES57),6) -> 1273.69 | AD57: =ROUND((((ET57)-(EU57))+AE57),6) -> 0 | AE57: =ROUND((EU57),6) -> 0 | AF57: =ROUND((EV57),6) -> 0 | AG57: =ROUND((AP57),6) -> 0 | AH57: =(EW57) -> 0 | AI57: =(EX57) -> 0 | AJ57: =(AS57) -> 0 | AK57: 1273.69 | AL57: 1273.69 | AM57: 0 | AN57: 0 | AO57: 0 | AP57: 0 | AQ57: 0 | AR57: 0 | AS57: 0 | AT57: 0 | AU57: 0 | AV57: 1 | AW57: 1 | AZ57: 1 | BA57: 1 | BB57: 1 | BC57: 7.66 | BH57: 3 | BI57: 3 | BM57: 746 | BN57: 0 | BP57: 0 | BQ57: 130 | BR57: 0 | BS57: 1 | BT57: 1 | BU57: 1 | BV57: 1 | BW57: 1 | BX57: 1 | BZ57: 90 | CA57: 46 | CE57: 30 | CF57: 0 | CG57: 0 | CM57: 0 | CO57: 0 | CP57: =(P57+Q57+S57) -> 9756.47 | CQ57: =ROUND((ROUND((AC57*1),2)*BC57),2) -> 9756.47 | CR57: =(ROUND((ROUND(((ET57)*AV57*1),2)*BB57),2)+ROUND((ROUND(((AE57-(EU57))*AV57*1),2)*BS57),2)) -> 0 | CS57: =ROUND((ROUND((AE57*AV57*1),2)*BS57),2) -> 0 | CT57: =ROUND((ROUND((AF57*AV57*1),2)*BA57),2) -> 0 | CU57: =AG57 -> 0 | CV57: =(AH57*AV57) -> 0 | CW57: =AI57 -> 0 | CX57: =AJ57 -> 0 | CY57: =(((S57+R57)*AT57)/100) -> 0 | CZ57: =(((S57+R57)*AU57)/100) -> 0 | DN57: 0 | DO57: 0 | DP57: 1 | DQ57: 1 | DU57: 1010 | DV57: шт. | DW57: шт. | DX57: 1 | EE57: 58162750 | EF57: 130 | EG57: Сметная стоимость оборудования | EH57: 0 | EJ57: 3 | EK57: 746 | EL57: ТСН-2001.13. Сметная стоимость оборудования | EM57: ТСН-2001.13 | EQ57: 0 | ER57: 9756.49 | ES57: 1273.69 | ET57: 0 | EU57: 0 | EV57: 0 | EW57: 0 | EX57: 0 | EZ57: 5 | FC57: 1 | FD57: 18 | FF57: 11232 | FQ57: 0 | FR57: =P57 -> 9756.47 | FS57: 0 | FX57: 90 | FY57: 46 | GA57: [11 232 / 1,2 / 7,66] + 3% Трансп + 1,2% Заг.скл | GD57: 1 | GF57: 1852694742 | GG57: 2 | GH57: 3 | GI57: 5 | GJ57: 0 | GK57: 0 | GL57: =ROUND(IF(AND(BH57=3,BI57=3,FS57<>0),P57,0),2) -> 0 | GM57: =ROUND(O57+X57+Y57,2)+GX57 -> 9756.47 | GN57: =IF(OR(BI57=0,BI57=1),GM57-GX57,0) -> 0 | GO57: =IF(BI57=2,GM57-GX57,0) -> 0 | GP57: =IF(BI57=4,GM57-GX57,0) -> 0 | GR57: 1 | GS57: 1 | GT57: 0 | GV57: =ROUND((GT57),6) -> 0 | GW57: 1 | GX57: =ROUND(HC57*I57,2) -> 0 | HA57: 0 | HB57: 0 | HC57: =GV57*GW57 -> 0 | HE57: 3 | HF57: 1,2 | HS57: 0 | IK57: 0
A58: 17 | B58: 1 | D58: =ROW(EtalonRes!A92) -> 92 | E58: 8 | F58: 4.10-76-10 | G58: Монтаж ключа или кнопки на панели | H58: 1 ШТ. | I58: 1 | J58: 0 | K58: 1 | O58: =ROUND(CP58,2) -> 15.36 | P58: =ROUND((ROUND((AC58*AW58*I58),2)*BC58),2) -> 1.67 | Q58: =(ROUND((ROUND((((ET58*1.1))*AV58*I58),2)*BB58),2)+ROUND((ROUND(((AE58-((EU58*1.1)))*AV58*I58),2)*BS58),2)) -> 0 | R58: =ROUND((ROUND((AE58*AV58*I58),2)*BS58),2) -> 0 | S58: =ROUND((ROUND((AF58*AV58*I58),2)*BA58),2) -> 13.69 | T58: =ROUND(CU58*I58,2) -> 0 | U58: =CV58*I58 -> 1.1517 | V58: =CW58*I58 -> 0 | W58: =ROUND(CX58*I58,2) -> 0 | X58: =ROUND(CY58,2) -> 13.01 | Y58: =ROUND(CZ58,2) -> 7.26 | AA58: 56511233 | AB58: =ROUND((AC58+AD58+AF58),6) -> 14.749 | AC58: =ROUND((ES58),6) -> 1.67 | AD58: =ROUND(((((ET58*1.1))-((EU58*1.1)))+AE58),6) -> 0 | AE58: =ROUND(((EU58*1.1)),6) -> 0 | AF58: =ROUND(((EV58*1.1)),6) -> 13.079 | AG58: =ROUND((AP58),6) -> 0 | AH58: =((EW58*1.1)) -> 1.1 | AI58: =((EX58*1.1)) -> 0 | AJ58: =(AS58) -> 0 | AK58: 13.56 | AL58: 1.67 | AM58: 0 | AN58: 0 | AO58: 11.89 | AP58: 0 | AQ58: 1 | AR58: 0 | AS58: 0 | AT58: 95 | AU58: 53 | AV58: 1.047 | AW58: 1 | AZ58: 1 | BA58: 1 | BB58: 1 | BC58: 1 | BH58: 0 | BI58: 2 | BJ58: ТСН-2001.4 Доп. 79, Сб. 10, т. 76, поз. 10 | BM58: 69 | BN58: 0 | BO58: 4.10-76-10 | BP58: 1 | BQ58: 40 | BR58: 0 | BS58: 1 | BT58: 1 | BU58: 1 | BV58: 1 | BW58: 1 | BX58: 1 | BZ58: 95 | CA58: 53 | CE58: 30 | CF58: 0 | CG58: 0 | CM58: 0 | CO58: 0 | CP58: =(P58+Q58+S58) -> 15.36 | CQ58: =ROUND((ROUND((AC58*AW58*1),2)*BC58),2) -> 1.67 | CR58: =(ROUND((ROUND((((ET58*1.1))*AV58*1),2)*BB58),2)+ROUND((ROUND(((AE58-((EU58*1.1)))*AV58*1),2)*BS58),2)) -> 0 | CS58: =ROUND((ROUND((AE58*AV58*1),2)*BS58),2) -> 0 | CT58: =ROUND((ROUND((AF58*AV58*1),2)*BA58),2) -> 13.69 | CU58: =AG58 -> 0 | CV58: =(AH58*AV58) -> 1.1517 | CW58: =AI58 -> 0 | CX58: =AJ58 -> 0 | CY58: =(((S58+R58)*AT58)/100) -> 13.0055 | CZ58: =(((S58+R58)*AU58)/100) -> 7.2557 | DE58: *1,1 | DF58: *1,1 | DG58: *1,1 | DI58: *1,1 | DJ58: *1,1 | DN58: 0 | DO58: 0 | DP58: 1 | DQ58: 1 | DU58: 1013 | DV58: 1 ШТ. | DW58: 1 ШТ. | DX58: 1 | EE58: 58162631 | EF58: 40 | EG58: Монтаж оборудования | EH58: 0 | EJ58: 2 | EK58: 69 | EL58: ТСН-2001.4-10. Монтаж радиотелевизионного и электронного оборудования | EM58: ТСН-2001.4-10-2 | EO58: Поправка: Гл.12.Прил.8.п.8. 5_12.00.01.11.003 | EQ58: 0 | ER58: 13.56 | ES58: 1.67 | ET58: 0 | EU58: 0 | EV58: 11.89 | EW58: 1 | EX58: 0 | EY58: 0 | FQ58: 0 | FR58: 0 | FS58: 0 | FX58: 95 | FY58: 53 | GD58: 1 | GF58: -508473279 | GG58: 2 | GH58: 1 | GI58: 2 | GJ58: 0 | GK58: 0 | GL58: =ROUND(IF(AND(BH58=3,BI58=3,FS58<>0),P58,0),2) -> 0 | GM58: =ROUND(O58+X58+Y58,2)+GX58 -> 35.63 | GN58: =IF(OR(BI58=0,BI58=1),GM58-GX58,0) -> 0 | GO58: =IF(BI58=2,GM58-GX58,0) -> 35.63 | GP58: =IF(BI58=4,GM58-GX58,0) -> 0 | GR58: 0 | GS58: 3 | GT58: 0 | GV58: =ROUND((GT58),6) -> 0 | GW58: 1 | GX58: =ROUND(HC58*I58,2) -> 0 | HA58: 0 | HB58: 0 | HC58: =GV58*GW58 -> 0 | HS58: 0 | IK58: 0
A59: 17 | B59: 1 | D59: =ROW(EtalonRes!A96) -> 96 | E59: 8 | F59: 4.10-76-10 | G59: Монтаж ключа или кнопки на панели | H59: 1 ШТ. | I59: 1 | J59: 0 | K59: 1 | O59: =ROUND(CP59,2) -> 783.89 | P59: =ROUND((ROUND((AC59*AW59*I59),2)*BC59),2) -> 31.08 | Q59: =(ROUND((ROUND((((ET59*1.1))*AV59*I59),2)*BB59),2)+ROUND((ROUND(((AE59-((EU59*1.1)))*AV59*I59),2)*BS59),2)) -> 0 | R59: =ROUND((ROUND((AE59*AV59*I59),2)*BS59),2) -> 0 | S59: =ROUND((ROUND((AF59*AV59*I59),2)*BA59),2) -> 752.81 | T59: =ROUND(CU59*I59,2) -> 0 | U59: =CV59*I59 -> 1.1517 | V59: =CW59*I59 -> 0 | W59: =ROUND(CX59*I59,2) -> 0 | X59: =ROUND(CY59,2) -> 715.17 | Y59: =ROUND(CZ59,2) -> 398.99 | AA59: 56511235 | AB59: =ROUND((AC59+AD59+AF59),6) -> 14.749 | AC59: =ROUND((ES59),6) -> 1.67 | AD59: =ROUND(((((ET59*1.1))-((EU59*1.1)))+AE59),6) -> 0 | AE59: =ROUND(((EU59*1.1)),6) -> 0 | AF59: =ROUND(((EV59*1.1)),6) -> 13.079 | AG59: =ROUND((AP59),6) -> 0 | AH59: =((EW59*1.1)) -> 1.1 | AI59: =((EX59*1.1)) -> 0 | AJ59: =(AS59) -> 0 | AK59: 13.56 | AL59: 1.67 | AM59: 0 | AN59: 0 | AO59: 11.89 | AP59: 0 | AQ59: 1 | AR59: 0 | AS59: 0 | AT59: 95 | AU59: 53 | AV59: 1.047 | AW59: 1 | AZ59: 1 | BA59: 54.99 | BB59: 1 | BC59: 18.61 | BH59: 0 | BI59: 2 | BJ59: ТСН-2001.4 Доп. 79, Сб. 10, т. 76, поз. 10 | BM59: 69 | BN59: 0 | BO59: 4.10-76-10 | BP59: 1 | BQ59: 40 | BR59: 0 | BS59: 54.99 | BT59: 1 | BU59: 1 | BV59: 1 | BW59: 1 | BX59: 1 | BZ59: 95 | CA59: 53 | CE59: 30 | CF59: 0 | CG59: 0 | CM59: 0 | CO59: 0 | CP59: =(P59+Q59+S59) -> 783.89 | CQ59: =ROUND((ROUND((AC59*AW59*1),2)*BC59),2) -> 31.08 | CR59: =(ROUND((ROUND((((ET59*1.1))*AV59*1),2)*BB59),2)+ROUND((ROUND(((AE59-((EU59*1.1)))*AV59*1),2)*BS59),2)) -> 0 | CS59: =ROUND((ROUND((AE59*AV59*1),2)*BS59),2) -> 0 | CT59: =ROUND((ROUND((AF59*AV59*1),2)*BA59),2) -> 752.81 | CU59: =AG59 -> 0 | CV59: =(AH59*AV59) -> 1.1517 | CW59: =AI59 -> 0 | CX59: =AJ59 -> 0 | CY59: =(((S59+R59)*AT59)/100) -> 715.1695 | CZ59: =(((S59+R59)*AU59)/100) -> 398.9893 | DE59: *1,1 | DF59: *1,1 | DG59: *1,1 | DI59: *1,1 | DJ59: *1,1 | DN59: 0 | DO59: 0 | DP59: 1 | DQ59: 1 | DU59: 1013 | DV59: 1 ШТ. | DW59: 1 ШТ. | DX59: 1 | EE59: 58162631 | EF59: 40 | EG59: Монтаж оборудования | EH59: 0 | EJ59: 2 | EK59: 69 | EL59: ТСН-2001.4-10. Монтаж радиотелевизионного и электронного оборудования | EM59: ТСН-2001.4-10-2 | EO59: Поправка: Гл.12.Прил.8.п.8. 5_12.00.01.11.003 | EQ59: 0 | ER59: 13.56 | ES59: 1.67 | ET59: 0 | EU59: 0 | EV59: 11.89 | EW59: 1 | EX59: 0 | EY59: 0 | FQ59: 0 | FR59: 0 | FS59: 0 | FX59: 95 | FY59: 53 | GD59: 1 | GF59: -508473279 | GG59: 2 | GH59: 1 | GI59: 2 | GJ59: 0 | GK59: 0 | GL59: =ROUND(IF(AND(BH59=3,BI59=3,FS59<>0),P59,0),2) -> 0 | GM59: =ROUND(O59+X59+Y59,2)+GX59 -> 1898.05 | GN59: =IF(OR(BI59=0,BI59=1),GM59-GX59,0) -> 0 | GO59: =IF(BI59=2,GM59-GX59,0) -> 1898.05 | GP59: =IF(BI59=4,GM59-GX59,0) -> 0 | GR59: 0 | GS59: 3 | GT59: 0 | GV59: =ROUND((GT59),6) -> 0 | GW59: 1 | GX59: =ROUND(HC59*I59,2) -> 0 | HA59: 0 | HB59: 0 | HC59: =GV59*GW59 -> 0 | HS59: 0 | IK59: 0
A60: 18 | B60: 1 | E60: 8,1 | F60: КА 9 | G60: Устройство вызов/сброс Тромбон-ВС-С | H60: шт. | I60: =I58*J60 -> 1 | J60: 1 | K60: 1 | O60: =ROUND(CP60,2) -> 966.16 | P60: =ROUND((ROUND((AC60*I60),2)*BC60),2) -> 966.16 | Q60: =(ROUND((ROUND(((ET60)*AV60*I60),2)*BB60),2)+ROUND((ROUND(((AE60-(EU60))*AV60*I60),2)*BS60),2)) -> 0 | R60: =ROUND((ROUND((AE60*AV60*I60),2)*BS60),2) -> 0 | S60: =ROUND((ROUND((AF60*AV60*I60),2)*BA60),2) -> 0 | T60: =ROUND(CU60*I60,2) -> 0 | U60: =CV60*I60 -> 0 | V60: =CW60*I60 -> 0 | W60: =ROUND(CX60*I60,2) -> 0 | X60: =ROUND(CY60,2) -> 0 | Y60: =ROUND(CZ60,2) -> 0 | AA60: 56511233 | AB60: =ROUND((AC60+AD60+AF60),6) -> 966.16 | AC60: =ROUND((ES60),6) -> 966.16 | AD60: =ROUND((((ET60)-(EU60))+AE60),6) -> 0 | AE60: =ROUND((EU60),6) -> 0 | AF60: =ROUND((EV60),6) -> 0 | AG60: =ROUND((AP60),6) -> 0 | AH60: =(EW60) -> 0 | AI60: =(EX60) -> 0 | AJ60: =(AS60) -> 0 | AK60: 966.16 | AL60: 966.16 | AM60: 0 | AN60: 0 | AO60: 0 | AP60: 0 | AQ60: 0 | AR60: 0 | AS60: 0 | AT60: 0 | AU60: 0 | AV60: 1 | AW60: 1 | AZ60: 1 | BA60: 1 | BB60: 1 | BC60: 1 | BH60: 3 | BI60: 3 | BM60: 746 | BN60: 0 | BP60: 0 | BQ60: 130 | BR60: 0 | BS60: 1 | BT60: 1 | BU60: 1 | BV60: 1 | BW60: 1 | BX60: 1 | BZ60: 95 | CA60: 53 | CE60: 30 | CF60: 0 | CG60: 0 | CM60: 0 | CO60: 0 | CP60: =(P60+Q60+S60) -> 966.16 | CQ60: =ROUND((ROUND((AC60*1),2)*BC60),2) -> 966.16 | CR60: =(ROUND((ROUND(((ET60)*AV60*1),2)*BB60),2)+ROUND((ROUND(((AE60-(EU60))*AV60*1),2)*BS60),2)) -> 0 | CS60: =ROUND((ROUND((AE60*AV60*1),2)*BS60),2) -> 0 | CT60: =ROUND((ROUND((AF60*AV60*1),2)*BA60),2) -> 0 | CU60: =AG60 -> 0 | CV60: =(AH60*AV60) -> 0 | CW60: =AI60 -> 0 | CX60: =AJ60 -> 0 | CY60: =(((S60+R60)*AT60)/100) -> 0 | CZ60: =(((S60+R60)*AU60)/100) -> 0 | DN60: 0 | DO60: 0 | DP60: 1 | DQ60: 1 | DU60: 1010 | DV60: шт. | DW60: шт. | DX60: 1 | EE60: 58162750 | EF60: 130 | EG60: Сметная стоимость оборудования | EH60: 0 | EJ60: 3 | EK60: 746 | EL60: ТСН-2001.13. Сметная стоимость оборудования | EM60: ТСН-2001.13 | EQ60: 0 | ER60: 0 | ES60: 966.16 | ET60: 0 | EU60: 0 | EV60: 0 | EW60: 0 | EX60: 0 | FQ60: 0 | FR60: =P60 -> 966.16 | FS60: 0 | FX60: 95 | FY60: 53 | GA60: [8 520 / 1,2 / 7,66] + 3% Трансп + 1,2% Заг.скл | GD60: 1 | GF60: 2045652835 | GG60: 2 | GH60: 4 | GI60: -2 | GJ60: 0 | GK60: 0 | GL60: =ROUND(IF(AND(BH60=3,BI60=3,FS60<>0),P60,0),2) -> 0 | GM60: =ROUND(O60+X60+Y60,2)+GX60 -> 966.16 | GN60: =IF(OR(BI60=0,BI60=1),GM60-GX60,0) -> 0 | GO60: =IF(BI60=2,GM60-GX60,0) -> 0 | GP60: =IF(BI60=4,GM60-GX60,0) -> 0 | GR60: 0 | GS60: 2 | GT60: 0 | GV60: =ROUND((GT60),6) -> 0 | GW60: 1 | GX60: =ROUND(HC60*I60,2) -> 0 | HA60: 0 | HB60: 0 | HC60: =GV60*GW60 -> 0 | HE60: 3 | HF60: 1,2 | HS60: 0 | IK60: 0
A61: 18 | B61: 1 | E61: 8,1 | F61: КА 9 | G61: Устройство вызов/сброс Тромбон-ВС-С | H61: шт. | I61: =I59*J61 -> 1 | J61: 1 | K61: 1 | O61: =ROUND(CP61,2) -> 7400.79 | P61: =ROUND((ROUND((AC61*I61),2)*BC61),2) -> 7400.79 | Q61: =(ROUND((ROUND(((ET61)*AV61*I61),2)*BB61),2)+ROUND((ROUND(((AE61-(EU61))*AV61*I61),2)*BS61),2)) -> 0 | R61: =ROUND((ROUND((AE61*AV61*I61),2)*BS61),2) -> 0 | S61: =ROUND((ROUND((AF61*AV61*I61),2)*BA61),2) -> 0 | T61: =ROUND(CU61*I61,2) -> 0 | U61: =CV61*I61 -> 0 | V61: =CW61*I61 -> 0 | W61: =ROUND(CX61*I61,2) -> 0 | X61: =ROUND(CY61,2) -> 0 | Y61: =ROUND(CZ61,2) -> 0 | AA61: 56511235 | AB61: =ROUND((AC61+AD61+AF61),6) -> 966.16 | AC61: =ROUND((ES61),6) -> 966.16 | AD61: =ROUND((((ET61)-(EU61))+AE61),6) -> 0 | AE61: =ROUND((EU61),6) -> 0 | AF61: =ROUND((EV61),6) -> 0 | AG61: =ROUND((AP61),6) -> 0 | AH61: =(EW61) -> 0 | AI61: =(EX61) -> 0 | AJ61: =(AS61) -> 0 | AK61: 966.16 | AL61: 966.16 | AM61: 0 | AN61: 0 | AO61: 0 | AP61: 0 | AQ61: 0 | AR61: 0 | AS61: 0 | AT61: 0 | AU61: 0 | AV61: 1 | AW61: 1 | AZ61: 1 | BA61: 1 | BB61: 1 | BC61: 7.66 | BH61: 3 | BI61: 3 | BM61: 746 | BN61: 0 | BP61: 0 | BQ61: 130 | BR61: 0 | BS61: 1 | BT61: 1 | BU61: 1 | BV61: 1 | BW61: 1 | BX61: 1 | BZ61: 95 | CA61: 53 | CE61: 30 | CF61: 0 | CG61: 0 | CM61: 0 | CO61: 0 | CP61: =(P61+Q61+S61) -> 7400.79 | CQ61: =ROUND((ROUND((AC61*1),2)*BC61),2) -> 7400.79 | CR61: =(ROUND((ROUND(((ET61)*AV61*1),2)*BB61),2)+ROUND((ROUND(((AE61-(EU61))*AV61*1),2)*BS61),2)) -> 0 | CS61: =ROUND((ROUND((AE61*AV61*1),2)*BS61),2) -> 0 | CT61: =ROUND((ROUND((AF61*AV61*1),2)*BA61),2) -> 0 | CU61: =AG61 -> 0 | CV61: =(AH61*AV61) -> 0 | CW61: =AI61 -> 0 | CX61: =AJ61 -> 0 | CY61: =(((S61+R61)*AT61)/100) -> 0 | CZ61: =(((S61+R61)*AU61)/100) -> 0 | DN61: 0 | DO61: 0 | DP61: 1 | DQ61: 1 | DU61: 1010 | DV61: шт. | DW61: шт. | DX61: 1 | EE61: 58162750 | EF61: 130 | EG61: Сметная стоимость оборудования | EH61: 0 | EJ61: 3 | EK61: 746 | EL61: ТСН-2001.13. Сметная стоимость оборудования | EM61: ТСН-2001.13 | EQ61: 0 | ER61: 7400.76 | ES61: 966.16 | ET61: 0 | EU61: 0 | EV61: 0 | EW61: 0 | EX61: 0 | EZ61: 5 | FC61: 1 | FD61: 18 | FF61: 8520 | FQ61: 0 | FR61: =P61 -> 7400.79 | FS61: 0 | FX61: 95 | FY61: 53 | GA61: [8 520 / 1,2 / 7,66] + 3% Трансп + 1,2% Заг.скл | GD61: 1 | GF61: 2045652835 | GG61: 2 | GH61: 3 | GI61: 5 | GJ61: 0 | GK61: 0 | GL61: =ROUND(IF(AND(BH61=3,BI61=3,FS61<>0),P61,0),2) -> 0 | GM61: =ROUND(O61+X61+Y61,2)+GX61 -> 7400.79 | GN61: =IF(OR(BI61=0,BI61=1),GM61-GX61,0) -> 0 | GO61: =IF(BI61=2,GM61-GX61,0) -> 0 | GP61: =IF(BI61=4,GM61-GX61,0) -> 0 | GR61: 1 | GS61: 1 | GT61: 0 | GV61: =ROUND((GT61),6) -> 0 | GW61: 1 | GX61: =ROUND(HC61*I61,2) -> 0 | HA61: 0 | HB61: 0 | HC61: =GV61*GW61 -> 0 | HE61: 3 | HF61: 1,2 | HS61: 0 | IK61: 0
A63: 51 | B63: =B24 -> 1 | C63: =A24 -> 4 | D63: =ROW(A24) -> 24 | F63: =IF(F24<>"",F24,"") | G63: =IF(G24<>"",G24,"") -> Оборудование | H63: 0 | O63: =ROUND(AB63,2) -> 83527.43 | P63: =ROUND(AC63,2) -> 82506.26 | Q63: =ROUND(AD63,2) -> 20.02 | R63: =ROUND(AE63,2) -> 3.15 | S63: =ROUND(AF63,2) -> 1001.15 | T63: =ROUND(AG63,2) -> 0 | U63: =AH63 -> 72.248444 | V63: =AI63 -> 0 | W63: =ROUND(AJ63,2) -> 0 | X63: =ROUND(AK63,2) -> 904.57 | Y63: =ROUND(AL63,2) -> 462.94 | AB63: =ROUND(SUMIF(AA28:AA61,"=56511233",O28:O61),2) -> 83527.43 | AC63: =ROUND(SUMIF(AA28:AA61,"=56511233",P28:P61),2) -> 82506.26 | AD63: =ROUND(SUMIF(AA28:AA61,"=56511233",Q28:Q61),2) -> 20.02 | AE63: =ROUND(SUMIF(AA28:AA61,"=56511233",R28:R61),2) -> 3.15 | AF63: =ROUND(SUMIF(AA28:AA61,"=56511233",S28:S61),2) -> 1001.15 | AG63: =ROUND(SUMIF(AA28:AA61,"=56511233",T28:T61),2) -> 0 | AH63: =SUMIF(AA28:AA61,"=56511233",U28:U61) -> 72.248444 | AI63: =SUMIF(AA28:AA61,"=56511233",V28:V61) -> 0 | AJ63: =ROUND(SUMIF(AA28:AA61,"=56511233",W28:W61),2) -> 0 | AK63: =ROUND(SUMIF(AA28:AA61,"=56511233",X28:X61),2) -> 904.57 | AL63: =ROUND(SUMIF(AA28:AA61,"=56511233",Y28:Y61),2) -> 462.94 | AO63: =ROUND(BX63,2) -> 0 | AP63: =ROUND(BY63,2) -> 81880.2 | AQ63: =ROUND(BZ63,2) -> 0 | AR63: =ROUND(CA63,2) -> 84894.94 | AS63: =ROUND(CB63,2) -> 0 | AT63: =ROUND(CC63,2) -> 3014.74 | AU63: =ROUND(CD63,2) -> 0 | AV63: =ROUND(CE63,2) -> 82506.26 | ... BD63: =ROUND(CM63,2) -> 0 | BX63: =ROUND(SUMIF(AA28:AA61,"=56511233",FQ28:FQ61),2) -> 0 | BY63: =ROUND(SUMIF(AA28:AA61,"=56511233",FR28:FR61),2) -> 81880.2 | BZ63: =ROUND(SUMIF(AA28:AA61,"=56511233",GL28:GL61),2) -> 0 | CA63: =ROUND(SUMIF(AA28:AA61,"=56511233",GM28:GM61),2) -> 84894.94 | CB63: =ROUND(SUMIF(AA28:AA61,"=56511233",GN28:GN61),2) -> 0 | CC63: =ROUND(SUMIF(AA28:AA61,"=56511233",GO28:GO61),2) -> 3014.74 | CD63: =ROUND(SUMIF(AA28:AA61,"=56511233",GP28:GP61),2) -> 0 | CE63: =AC63-BX63 -> 82506.26 | CF63: =AC63-BY63 -> 626.06 | CG63: =BX63-BZ63 -> 0 | CH63: =AC63-BX63-BY63+BZ63 -> 626.06 | CI63: =BY63-BZ63 -> 81880.2 | CJ63: =ROUND(SUMIF(AA28:AA61,"=56511233",GX28:GX61),2) -> 0 | CK63: =ROUND(SUMIF(AA28:AA61,"=56511233",GY28:GY61),2) -> 0 | CL63: =ROUND(SUMIF(AA28:AA61,"=56511233",GZ28:GZ61),2) -> 0 | CM63: =ROUND(SUMIF(AA28:AA61,"=56511233",HD28:HD61),2) -> 0 | DG63: =ROUND(DT63,2) -> 688961.54 | DH63: =ROUND(DU63,2) -> 633570.01 | DI63: =ROUND(DV63,2) -> 338.3 | DJ63: =ROUND(DW63,2) -> 173.23 | DK63: =ROUND(DX63,2) -> 55053.23 | DL63: =ROUND(DY63,2) -> 0 | DM63: =DZ63 -> 72.248444 | DN63: =EA63 -> 0 | DO63: =ROUND(EB63,2) -> 0 | DP63: =ROUND(EC63,2) -> 49741.46 | DQ63: =ROUND(ED63,2) -> 25456.86 | DT63: =ROUND(SUMIF(AA28:AA61,"=56511235",O28:O61),2) -> 688961.54 | DU63: =ROUND(SUMIF(AA28:AA61,"=56511235",P28:P61),2) -> 633570.01 | DV63: =ROUND(SUMIF(AA28:AA61,"=56511235",Q28:Q61),2) -> 338.3 | DW63: =ROUND(SUMIF(AA28:AA61,"=56511235",R28:R61),2) -> 173.23 | DX63: =ROUND(SUMIF(AA28:AA61,"=56511235",S28:S61),2) -> 55053.23 | DY63: =ROUND(SUMIF(AA28:AA61,"=56511235",T28:T61),2) -> 0 | DZ63: =SUMIF(AA28:AA61,"=56511235",U28:U61) -> 72.248444 | EA63: =SUMIF(AA28:AA61,"=56511235",V28:V61) -> 0 | EB63: =ROUND(SUMIF(AA28:AA61,"=56511235",W28:W61),2) -> 0 | EC63: =ROUND(SUMIF(AA28:AA61,"=56511235",X28:X61),2) -> 49741.46 | ED63: =ROUND(SUMIF(AA28:AA61,"=56511235",Y28:Y61),2) -> 25456.86 | EG63: =ROUND(FP63,2) -> 0 | EH63: =ROUND(FQ63,2) -> 627397.21 | EI63: =ROUND(FR63,2) -> 0 | EJ63: =ROUND(FS63,2) -> 764159.86 | EK63: =ROUND(FT63,2) -> 0 | EL63: =ROUND(FU63,2) -> 136762.65 | EM63: =ROUND(FV63,2) -> 0 | EN63: =ROUND(FW63,2) -> 633570.01 | ... EV63: =ROUND(GE63,2) -> 0 | FP63: =ROUND(SUMIF(AA28:AA61,"=56511235",FQ28:FQ61),2) -> 0 | FQ63: =ROUND(SUMIF(AA28:AA61,"=56511235",FR28:FR61),2) -> 627397.21 | FR63: =ROUND(SUMIF(AA28:AA61,"=56511235",GL28:GL61),2) -> 0 | FS63: =ROUND(SUMIF(AA28:AA61,"=56511235",GM28:GM61),2) -> 764159.86 | FT63: =ROUND(SUMIF(AA28:AA61,"=56511235",GN28:GN61),2) -> 0 | FU63: =ROUND(SUMIF(AA28:AA61,"=56511235",GO28:GO61),2) -> 136762.65 | FV63: =ROUND(SUMIF(AA28:AA61,"=56511235",GP28:GP61),2) -> 0 | FW63: =DU63-FP63 -> 633570.01 | FX63: =DU63-FQ63 -> 6172.8 | FY63: =FP63-FR63 -> 0 | FZ63: =DU63-FP63-FQ63+FR63 -> 6172.8 | GA63: =FQ63-FR63 -> 627397.21 | GB63: =ROUND(SUMIF(AA28:AA61,"=56511235",GX28:GX61),2) -> 0 | GC63: =ROUND(SUMIF(AA28:AA61,"=56511235",GY28:GY61),2) -> 0 | GD63: =ROUND(SUMIF(AA28:AA61,"=56511235",GZ28:GZ61),2) -> 0 | GE63: =ROUND(SUMIF(AA28:AA61,"=56511235",HD28:HD61),2) -> 0 | GX63: 0
A65: 50 | B65: 0 | C65: 0 | D65: 1 | E65: 201 | F65: =ROUND(Source!O63,O65) -> 83527.43 | G65: ПЗ | H65: Прямые затраты | K65: 201 | L65: 1 | M65: 3 | O65: 2 | P65: =ROUND(Source!DG63,O65) -> 688961.54 | W65: 83527.43 | X65: 1 | Y65: 83527.43 | Z65: 688961.54 | AA65: 1 | AB65: 688961.54
A66: 50 | B66: 0 | C66: 0 | D66: 1 | E66: 202 | F66: =ROUND(Source!P63,O66) -> 82506.26 | G66: СтМатОб | H66: Стоимость материальных ресурсов (всего) | K66: 202 | L66: 2 | M66: 3 | O66: 2 | P66: =ROUND(Source!DH63,O66) -> 633570.01 | W66: 82506.26 | X66: 1 | Y66: 82506.26 | Z66: 633570.01 | AA66: 1 | AB66: 633570.01
A67: 50 | B67: 0 | C67: 0 | D67: 1 | E67: 222 | F67: =ROUND(Source!AO63,O67) -> 0 | G67: СтМатОбЗак | H67: Стоимость материалов и оборудования заказчика | K67: 222 | L67: 3 | M67: 3 | O67: 2 | P67: =ROUND(Source!EG63,O67) -> 0 | W67: 0 | X67: 1 | Y67: 0 | Z67: 0 | AA67: 1 | AB67: 0
A68: 50 | B68: 0 | C68: 0 | D68: 1 | E68: 225 | F68: =ROUND(Source!AV63,O68) -> 82506.26 | G68: СтМатОбПод | H68: Стоимость материалов и оборудования подрядчика | K68: 225 | L68: 4 | M68: 3 | O68: 2 | P68: =ROUND(Source!EN63,O68) -> 633570.01 | W68: 82506.26 | X68: 1 | Y68: 82506.26 | Z68: 633570.01 | AA68: 1 | AB68: 633570.01
A69: 50 | B69: 0 | C69: 0 | D69: 1 | E69: 226 | F69: =ROUND(Source!AW63,O69) -> 626.06 | G69: СтМат | H69: Стоимость материалов (всего) | K69: 226 | L69: 5 | M69: 3 | O69: 2 | P69: =ROUND(Source!EO63,O69) -> 6172.8 | W69: 626.06 | X69: 1 | Y69: 626.06 | Z69: 6172.8 | AA69: 1 | AB69: 6172.8
A70: 50 | B70: 0 | C70: 0 | D70: 1 | E70: 227 | F70: =ROUND(Source!AX63,O70) -> 0 | G70: СтМатЗак | H70: Стоимость материалов заказчика | K70: 227 | L70: 6 | M70: 3 | O70: 2 | P70: =ROUND(Source!EP63,O70) -> 0 | W70: 0 | X70: 1 | Y70: 0 | Z70: 0 | AA70: 1 | AB70: 0
A71: 50 | B71: 0 | C71: 0 | D71: 1 | E71: 228 | F71: =ROUND(Source!AY63,O71) -> 626.06 | G71: СтМатПод | H71: Стоимость материалов подрядчика | K71: 228 | L71: 7 | M71: 3 | O71: 2 | P71: =ROUND(Source!EQ63,O71) -> 6172.8 | W71: 626.06 | X71: 1 | Y71: 626.06 | Z71: 6172.8 | AA71: 1 | AB71: 6172.8
A72: 50 | B72: 0 | C72: 0 | D72: 1 | E72: 216 | F72: =ROUND(Source!AP63,O72) -> 81880.2 | G72: Оборуд | H72: Стоимость оборудования (всего) | K72: 216 | L72: 8 | M72: 3 | O72: 2 | P72: =ROUND(Source!EH63,O72) -> 627397.21 | W72: 81880.2 | X72: 1 | Y72: 81880.2 | Z72: 627397.21 | AA72: 1 | AB72: 627397.21
A73: 50 | B73: 0 | C73: 0 | D73: 1 | E73: 223 | F73: =ROUND(Source!AQ63,O73) -> 0 | G73: ОборудЗак | H73: Стоимость оборудования заказчика | K73: 223 | L73: 9 | M73: 3 | O73: 2 | P73: =ROUND(Source!EI63,O73) -> 0 | W73: 0 | X73: 1 | Y73: 0 | Z73: 0 | AA73: 1 | AB73: 0
A74: 50 | B74: 0 | C74: 0 | D74: 1 | E74: 229 | F74: =ROUND(Source!AZ63,O74) -> 81880.2 | G74: ОборудПод | H74: Стоимость оборудования подрядчика | K74: 229 | L74: 10 | M74: 3 | O74: 2 | P74: =ROUND(Source!ER63,O74) -> 627397.21 | W74: 81880.2 | X74: 1 | Y74: 81880.2 | Z74: 627397.21 | AA74: 1 | AB74: 627397.21
A75: 50 | B75: 0 | C75: 0 | D75: 1 | E75: 203 | F75: =ROUND(Source!Q63,O75) -> 20.02 | G75: ЭММ | H75: Эксплуатация машин | K75: 203 | L75: 11 | M75: 3 | O75: 2 | P75: =ROUND(Source!DI63,O75) -> 338.3 | W75: 20.02 | X75: 1 | Y75: 20.02 | Z75: 338.3 | AA75: 1 | AB75: 338.3
A76: 50 | B76: 0 | C76: 0 | D76: 1 | E76: 231 | F76: =ROUND(Source!BB63,O76) -> 0 | G76: ЭММсНРиСП | H76: Эксплуатация машин по ТСН-2001.16 | K76: 231 | L76: 12 | M76: 3 | O76: 2 | P76: =ROUND(Source!ET63,O76) -> 0 | W76: 0 | X76: 1 | Y76: 0 | Z76: 0 | AA76: 1 | AB76: 0
A77: 50 | B77: 0 | C77: 0 | D77: 1 | E77: 204 | F77: =ROUND(Source!R63,O77) -> 3.15 | G77: ЗПМ | H77: ЗП машинистов | K77: 204 | L77: 13 | M77: 3 | O77: 2 | P77: =ROUND(Source!DJ63,O77) -> 173.23 | W77: 3.15 | X77: 1 | Y77: 3.15 | Z77: 173.23 | AA77: 1 | AB77: 173.23
A78: 50 | B78: 0 | C78: 0 | D78: 1 | E78: 205 | F78: =ROUND(Source!S63,O78) -> 1001.15 | G78: ОЗП | H78: Основная ЗП рабочих | K78: 205 | L78: 14 | M78: 3 | O78: 2 | P78: =ROUND(Source!DK63,O78) -> 55053.23 | W78: 1001.15 | X78: 1 | Y78: 1001.15 | Z78: 55053.23 | AA78: 1 | AB78: 55053.23
A79: 50 | B79: 0 | C79: 0 | D79: 1 | E79: 232 | F79: =ROUND(Source!BC63,O79) -> 0 | G79: ОЗПсНРиСП | H79: Основная ЗП рабочих по ТСН-2001.16 | K79: 232 | L79: 15 | M79: 3 | O79: 2 | P79: =ROUND(Source!EU63,O79) -> 0 | W79: 0 | X79: 1 | Y79: 0 | Z79: 0 | AA79: 1 | AB79: 0
A80: 50 | B80: 0 | C80: 0 | D80: 1 | E80: 214 | F80: =ROUND(Source!AS63,O80) -> 0 | G80: Строит | H80: Строительные работы с НР и СП | K80: 214 | L80: 16 | M80: 3 | O80: 2 | P80: =ROUND(Source!EK63,O80) -> 0 | W80: 0 | X80: 1 | Y80: 0 | Z80: 0 | AA80: 1 | AB80: 0
A81: 50 | B81: 0 | C81: 0 | D81: 1 | E81: 215 | F81: =ROUND(Source!AT63,O81) -> 3014.74 | G81: Монтаж | H81: Монтажные работы с НР и СП | K81: 215 | L81: 17 | M81: 3 | O81: 2 | P81: =ROUND(Source!EL63,O81) -> 136762.65 | W81: 3014.74 | X81: 1 | Y81: 3014.74 | Z81: 136762.65 | AA81: 1 | AB81: 136762.65
A82: 50 | B82: 0 | C82: 0 | D82: 1 | E82: 217 | F82: =ROUND(Source!AU63,O82) -> 0 | G82: Прочие | H82: Прочие работы с НР и СП | K82: 217 | L82: 18 | M82: 3 | O82: 2 | P82: =ROUND(Source!EM63,O82) -> 0 | W82: 0 | X82: 1 | Y82: 0 | Z82: 0 | AA82: 1 | AB82: 0
A83: 50 | B83: 0 | C83: 0 | D83: 1 | E83: 230 | F83: =ROUND(Source!BA63,O83) -> 0 | G83: ПрочиеЗатр | H83: Прочие затраты по ТСН-2001.16 | K83: 230 | L83: 19 | M83: 3 | O83: 2 | P83: =ROUND(Source!ES63,O83) -> 0 | W83: 0 | X83: 1 | Y83: 0 | Z83: 0 | AA83: 1 | AB83: 0
A84: 50 | B84: 0 | C84: 0 | D84: 1 | E84: 206 | F84: =ROUND(Source!T63,O84) -> 0 | G84: ВозврМат | H84: Возврат материалов | K84: 206 | L84: 20 | M84: 3 | O84: 2 | P84: =ROUND(Source!DL63,O84) -> 0 | W84: 0 | X84: 1 | Y84: 0 | Z84: 0 | AA84: 1 | AB84: 0
A85: 50 | B85: 0 | C85: 0 | D85: 1 | E85: 207 | F85: =Source!U63 -> 72.248444 | G85: ТрудСтр | H85: Трудозатраты строителей | K85: 207 | L85: 21 | M85: 3 | O85: -1 | P85: =Source!DM63 -> 72.248444 | W85: 72.248444 | X85: 1 | Y85: 72.248444 | Z85: 72.248444 | AA85: 1 | AB85: 72.248444
A86: 50 | B86: 0 | C86: 0 | D86: 1 | E86: 208 | F86: =Source!V63 -> 0 | G86: ТрудМаш | H86: Трудозатраты машинистов | K86: 208 | L86: 22 | M86: 3 | O86: -1 | P86: =Source!DN63 -> 0 | W86: 0 | X86: 1 | Y86: 0 | Z86: 0 | AA86: 1 | AB86: 0
A87: 50 | B87: 0 | C87: 0 | D87: 1 | E87: 209 | F87: =ROUND(Source!W63,O87) -> 0 | G87: ТранспМат | H87: Транспорт материалов | K87: 209 | L87: 23 | M87: 3 | O87: 2 | P87: =ROUND(Source!DO63,O87) -> 0 | W87: 0 | X87: 1 | Y87: 0 | Z87: 0 | AA87: 1 | AB87: 0
A88: 50 | B88: 0 | C88: 0 | D88: 1 | E88: 233 | F88: =ROUND(Source!BD63,O88) -> 0 | G88: Перевозка | H88: Перевозка грузов | K88: 233 | L88: 24 | M88: 3 | O88: 2 | P88: =ROUND(Source!EV63,O88) -> 0 | W88: 0 | X88: 1 | Y88: 0 | Z88: 0 | AA88: 1 | AB88: 0
A89: 50 | B89: 0 | C89: 0 | D89: 1 | E89: 210 | F89: =ROUND(Source!X63,O89) -> 904.57 | G89: НР | H89: Накладные расходы | K89: 210 | L89: 25 | M89: 3 | O89: 2 | P89: =ROUND(Source!DP63,O89) -> 49741.46 | W89: 904.57 | X89: 1 | Y89: 904.57 | Z89: 49741.46 | AA89: 1 | AB89: 49741.46
A90: 50 | B90: 0 | C90: 0 | D90: 1 | E90: 211 | F90: =ROUND(Source!Y63,O90) -> 462.94 | G90: СмПриб | H90: Сметная прибыль | K90: 211 | L90: 26 | M90: 3 | O90: 2 | P90: =ROUND(Source!DQ63,O90) -> 25456.86 | W90: 462.94 | X90: 1 | Y90: 462.94 | Z90: 25456.86 | AA90: 1 | AB90: 25456.86
A91: 50 | B91: 0 | C91: 0 | D91: 1 | E91: 224 | F91: =ROUND(Source!AR63,O91) -> 84894.94 | G91: Всего | H91: Всего с НР и СП | K91: 224 | L91: 27 | M91: 3 | O91: 2 | P91: =ROUND(Source!EJ63,O91) -> 764159.86 | W91: 84894.94 | X91: 1 | Y91: 84894.94 | Z91: 764159.86 | AA91: 1 | AB91: 764159.86
A93: 4 | B93: 1 | D93: =ROW(A142) -> 142 | G93: Кабельные изделия и материалы | I93: 0 | K93: -1 | S93: 0 | T93: 0 | V93: 0 | BX93: 0 | CJ93: 0
A95: 52 | B95: =B142 -> 1 | C95: =C142 -> 4 | D95: =D142 -> 93 | E95: =E142 -> 0 | F95: =F142 | G95: =G142 -> Кабельные изделия и материалы | O95: =O142 -> 29908.59 | P95: =P142 -> 29140.78 | Q95: =Q142 -> 6.67 | R95: =R142 -> 0 | S95: =S142 -> 761.14 | T95: =T142 -> 0 | U95: =U142 -> 64.046037 | V95: =V142 -> 0 | ... GX95: =GX142 -> 0
A97: 17 | B97: 1 | D97: =ROW(EtalonRes!A107) -> 107 | E97: 9 | F97: 4.10-186-5 | G97: Прокладка кабеля связи симметричного для цифровых систем передачи в трубах гофрированных: по бетонным и кирпичным поверхностям стен и потолка | H97: 100 м | I97: =ROUND((35+300)/100,9) -> 3.35 | J97: 0 | K97: =ROUND((35+300)/100,9) -> 3.35 | O97: =ROUND(CP97,2) -> 1075.71 | P97: =ROUND((ROUND((AC97*AW97*I97),2)*BC97),2) -> 307.9 | Q97: =(ROUND((ROUND((((ET97*1.1))*AV97*I97),2)*BB97),2)+ROUND((ROUND(((AE97-((EU97*1.1)))*AV97*I97),2)*BS97),2)) -> 6.67 | R97: =ROUND((ROUND((AE97*AV97*I97),2)*BS97),2) -> 0 | S97: =ROUND((ROUND((AF97*AV97*I97),2)*BA97),2) -> 761.14 | T97: =ROUND(CU97*I97,2) -> 0 | U97: =CV97*I97 -> 64.046037 | V97: =CW97*I97 -> 0 | W97: =ROUND(CX97*I97,2) -> 0 | X97: =ROUND(CY97,2) -> 685.03 | Y97: =ROUND(CZ97,2) -> 350.12 | AA97: 56511233 | AB97: =ROUND((AC97+AD97+AF97),6) -> 310.821 | AC97: =ROUND((ES97),6) -> 91.91 | AD97: =ROUND(((((ET97*1.1))-((EU97*1.1)))+AE97),6) -> 1.903 | AE97: =ROUND(((EU97*1.1)),6) -> 0 | AF97: =ROUND(((EV97*1.1)),6) -> 217.008 | AG97: =ROUND((AP97),6) -> 0 | AH97: =((EW97*1.1)) -> 18.26 | AI97: =((EX97*1.1)) -> 0 | AJ97: =(AS97) -> 0 | AK97: 290.92 | AL97: 91.91 | AM97: 1.73 | AN97: 0 | AO97: 197.28 | AP97: 0 | AQ97: 16.6 | AR97: 0 | AS97: 0 | AT97: 90 | AU97: 46 | AV97: 1.047 | AW97: 1 | AZ97: 1 | BA97: 1 | BB97: 1 | BC97: 1 | BH97: 0 | BI97: 2 | BJ97: ТСН-2001.4 Доп. 79, Сб. 10, т. 186, поз. 5 | BM97: 68 | BN97: 0 | BO97: 4.10-186-5 | BP97: 1 | BQ97: 40 | BR97: 0 | BS97: 1 | BT97: 1 | BU97: 1 | BV97: 1 | BW97: 1 | BX97: 1 | BZ97: 90 | CA97: 46 | CE97: 30 | CF97: 0 | CG97: 0 | CM97: 0 | CO97: 0 | CP97: =(P97+Q97+S97) -> 1075.71 | CQ97: =ROUND((ROUND((AC97*AW97*1),2)*BC97),2) -> 91.91 | CR97: =(ROUND((ROUND((((ET97*1.1))*AV97*1),2)*BB97),2)+ROUND((ROUND(((AE97-((EU97*1.1)))*AV97*1),2)*BS97),2)) -> 1.99 | CS97: =ROUND((ROUND((AE97*AV97*1),2)*BS97),2) -> 0 | CT97: =ROUND((ROUND((AF97*AV97*1),2)*BA97),2) -> 227.21 | CU97: =AG97 -> 0 | CV97: =(AH97*AV97) -> 19.11822 | CW97: =AI97 -> 0 | CX97: =AJ97 -> 0 | CY97: =(((S97+R97)*AT97)/100) -> 685.026 | CZ97: =(((S97+R97)*AU97)/100) -> 350.1244 | DE97: *1,1 | DF97: *1,1 | DG97: *1,1 | DI97: *1,1 | DJ97: *1,1 | DN97: 0 | DO97: 0 | DP97: 1 | DQ97: 1 | DU97: 1003 | DV97: 100 м | DW97: 100 м | DX97: 100 | EE97: 58162630 | EF97: 40 | EG97: Монтаж оборудования | EH97: 0 | EJ97: 2 | EK97: 68 | EL97: ТСН-2001.4-10. Прокладка и монтаж сетей связи | EM97: ТСН-2001.4-10-1 | EO97: Поправка: Гл.12.Прил.8.п.8. 5_12.00.01.11.003 | EQ97: 0 | ER97: 290.92 | ES97: 91.91 | ET97: 1.73 | EU97: 0 | EV97: 197.28 | EW97: 16.6 | EX97: 0 | EY97: 0 | FQ97: 0 | FR97: 0 | FS97: 0 | FX97: 90 | FY97: 46 | GD97: 1 | GF97: -250176620 | GG97: 2 | GH97: 1 | GI97: 2 | GJ97: 0 | GK97: 0 | GL97: =ROUND(IF(AND(BH97=3,BI97=3,FS97<>0),P97,0),2) -> 0 | GM97: =ROUND(O97+X97+Y97,2)+GX97 -> 2110.86 | GN97: =IF(OR(BI97=0,BI97=1),GM97-GX97,0) -> 0 | GO97: =IF(BI97=2,GM97-GX97,0) -> 2110.86 | GP97: =IF(BI97=4,GM97-GX97,0) -> 0 | GR97: 0 | GS97: 3 | GT97: 0 | GV97: =ROUND((GT97),6) -> 0 | GW97: 1 | GX97: =ROUND(HC97*I97,2) -> 0 | HA97: 0 | HB97: 0 | HC97: =GV97*GW97 -> 0 | HS97: 0 | IK97: 0
A98: 17 | B98: 1 | D98: =ROW(EtalonRes!A118) -> 118 | E98: 9 | F98: 4.10-186-5 | G98: Прокладка кабеля связи симметричного для цифровых систем передачи в трубах гофрированных: по бетонным и кирпичным поверхностям стен и потолка | H98: 100 м | I98: =ROUND((35+300)/100,9) -> 3.35 | J98: 0 | K98: =ROUND((35+300)/100,9) -> 3.35 | O98: =ROUND(CP98,2) -> 42762.99 | P98: =ROUND((ROUND((AC98*AW98*I98),2)*BC98),2) -> 849.8 | Q98: =(ROUND((ROUND((((ET98*1.1))*AV98*I98),2)*BB98),2)+ROUND((ROUND(((AE98-((EU98*1.1)))*AV98*I98),2)*BS98),2)) -> 58.1 | R98: =ROUND((ROUND((AE98*AV98*I98),2)*BS98),2) -> 0 | S98: =ROUND((ROUND((AF98*AV98*I98),2)*BA98),2) -> 41855.09 | T98: =ROUND(CU98*I98,2) -> 0 | U98: =CV98*I98 -> 64.046037 | V98: =CW98*I98 -> 0 | W98: =ROUND(CX98*I98,2) -> 0 | X98: =ROUND(CY98,2) -> 37669.58 | Y98: =ROUND(CZ98,2) -> 19253.34 | AA98: 56511235 | AB98: =ROUND((AC98+AD98+AF98),6) -> 310.821 | AC98: =ROUND((ES98),6) -> 91.91 | AD98: =ROUND(((((ET98*1.1))-((EU98*1.1)))+AE98),6) -> 1.903 | AE98: =ROUND(((EU98*1.1)),6) -> 0 | AF98: =ROUND(((EV98*1.1)),6) -> 217.008 | AG98: =ROUND((AP98),6) -> 0 | AH98: =((EW98*1.1)) -> 18.26 | AI98: =((EX98*1.1)) -> 0 | AJ98: =(AS98) -> 0 | AK98: 290.92 | AL98: 91.91 | AM98: 1.73 | AN98: 0 | AO98: 197.28 | AP98: 0 | AQ98: 16.6 | AR98: 0 | AS98: 0 | AT98: 90 | AU98: 46 | AV98: 1.047 | AW98: 1 | AZ98: 1 | BA98: 54.99 | BB98: 8.71 | BC98: 2.76 | BH98: 0 | BI98: 2 | BJ98: ТСН-2001.4 Доп. 79, Сб. 10, т. 186, поз. 5 | BM98: 68 | BN98: 0 | BO98: 4.10-186-5 | BP98: 1 | BQ98: 40 | BR98: 0 | BS98: 54.99 | BT98: 1 | BU98: 1 | BV98: 1 | BW98: 1 | BX98: 1 | BZ98: 90 | CA98: 46 | CE98: 30 | CF98: 0 | CG98: 0 | CM98: 0 | CO98: 0 | CP98: =(P98+Q98+S98) -> 42762.99 | CQ98: =ROUND((ROUND((AC98*AW98*1),2)*BC98),2) -> 253.67 | CR98: =(ROUND((ROUND((((ET98*1.1))*AV98*1),2)*BB98),2)+ROUND((ROUND(((AE98-((EU98*1.1)))*AV98*1),2)*BS98),2)) -> 17.33 | CS98: =ROUND((ROUND((AE98*AV98*1),2)*BS98),2) -> 0 | CT98: =ROUND((ROUND((AF98*AV98*1),2)*BA98),2) -> 12494.28 | CU98: =AG98 -> 0 | CV98: =(AH98*AV98) -> 19.11822 | CW98: =AI98 -> 0 | CX98: =AJ98 -> 0 | CY98: =(((S98+R98)*AT98)/100) -> 37669.581 | CZ98: =(((S98+R98)*AU98)/100) -> 19253.341 | DE98: *1,1 | DF98: *1,1 | DG98: *1,1 | DI98: *1,1 | DJ98: *1,1 | DN98: 0 | DO98: 0 | DP98: 1 | DQ98: 1 | DU98: 1003 | DV98: 100 м | DW98: 100 м | DX98: 100 | EE98: 58162630 | EF98: 40 | EG98: Монтаж оборудования | EH98: 0 | EJ98: 2 | EK98: 68 | EL98: ТСН-2001.4-10. Прокладка и монтаж сетей связи | EM98: ТСН-2001.4-10-1 | EO98: Поправка: Гл.12.Прил.8.п.8. 5_12.00.01.11.003 | EQ98: 0 | ER98: 290.92 | ES98: 91.91 | ET98: 1.73 | EU98: 0 | EV98: 197.28 | EW98: 16.6 | EX98: 0 | EY98: 0 | FQ98: 0 | FR98: 0 | FS98: 0 | FX98: 90 | FY98: 46 | GD98: 1 | GF98: -250176620 | GG98: 2 | GH98: 1 | GI98: 2 | GJ98: 0 | GK98: 0 | GL98: =ROUND(IF(AND(BH98=3,BI98=3,FS98<>0),P98,0),2) -> 0 | GM98: =ROUND(O98+X98+Y98,2)+GX98 -> 99685.91 | GN98: =IF(OR(BI98=0,BI98=1),GM98-GX98,0) -> 0 | GO98: =IF(BI98=2,GM98-GX98,0) -> 99685.91 | GP98: =IF(BI98=4,GM98-GX98,0) -> 0 | GR98: 0 | GS98: 3 | GT98: 0 | GV98: =ROUND((GT98),6) -> 0 | GW98: 1 | GX98: =ROUND(HC98*I98,2) -> 0 | HA98: 0 | HB98: 0 | HC98: =GV98*GW98 -> 0 | HS98: 0 | IK98: 0
A99: 18 | B99: 1 | E99: 9,1 | F99: 1.12-5-42 | G99: Трубы из непластифицированного вторичного ПВХ, гладкие, самозатухающие, усиленного типа, наружный диаметр 20 мм, толщина стенки 1,5 мм, для электропроводок | H99: м | I99: =I97*J99 -> 35.7 | J99: 10.656716 | K99: 10.656716 | O99: =ROUND(CP99,2) -> 163.86 | P99: =ROUND((ROUND((AC99*AW99*I99),2)*BC99),2) -> 163.86 | Q99: =(ROUND((ROUND(((ET99)*AV99*I99),2)*BB99),2)+ROUND((ROUND(((AE99-(EU99))*AV99*I99),2)*BS99),2)) -> 0 | R99: =ROUND((ROUND((AE99*AV99*I99),2)*BS99),2) -> 0 | S99: =ROUND((ROUND((AF99*AV99*I99),2)*BA99),2) -> 0 | T99: =ROUND(CU99*I99,2) -> 0 | U99: =CV99*I99 -> 0 | V99: =CW99*I99 -> 0 | W99: =ROUND(CX99*I99,2) -> 0 | X99: =ROUND(CY99,2) -> 0 | Y99: =ROUND(CZ99,2) -> 0 | AA99: 56511233 | AB99: =ROUND((AC99+AD99+AF99),6) -> 4.59 | AC99: =ROUND((ES99),6) -> 4.59 | AD99: =ROUND((((ET99)-(EU99))+AE99),6) -> 0 | AE99: =ROUND((EU99),6) -> 0 | AF99: =ROUND((EV99),6) -> 0 | AG99: =ROUND((AP99),6) -> 0 | AH99: =(EW99) -> 0 | AI99: =(EX99) -> 0 | AJ99: =(AS99) -> 0 | AK99: 4.59 | AL99: 4.59 | AM99: 0 | AN99: 0 | AO99: 0 | AP99: 0 | AQ99: 0 | AR99: 0 | AS99: 0 | AT99: 90 | AU99: 46 | AV99: 1 | AW99: 1 | AZ99: 1 | BA99: 1 | BB99: 1 | BC99: 1 | BH99: 3 | BI99: 2 | BJ99: ТСН-2001.1 Доп. 67, Р. 12, о. 5, поз. 42 | BM99: 68 | BN99: 0 | BP99: 0 | BQ99: 40 | BR99: 0 | BS99: 1 | BT99: 1 | BU99: 1 | BV99: 1 | BW99: 1 | BX99: 1 | BZ99: 90 | CA99: 46 | CE99: 30 | CF99: 0 | CG99: 0 | CM99: 0 | CO99: 0 | CP99: =(P99+Q99+S99) -> 163.86 | CQ99: =ROUND((ROUND((AC99*AW99*1),2)*BC99),2) -> 4.59 | CR99: =(ROUND((ROUND(((ET99)*AV99*1),2)*BB99),2)+ROUND((ROUND(((AE99-(EU99))*AV99*1),2)*BS99),2)) -> 0 | CS99: =ROUND((ROUND((AE99*AV99*1),2)*BS99),2) -> 0 | CT99: =ROUND((ROUND((AF99*AV99*1),2)*BA99),2) -> 0 | CU99: =AG99 -> 0 | CV99: =(AH99*AV99) -> 0 | CW99: =AI99 -> 0 | CX99: =AJ99 -> 0 | CY99: =(((S99+R99)*AT99)/100) -> 0 | CZ99: =(((S99+R99)*AU99)/100) -> 0 | DN99: 0 | DO99: 0 | DP99: 1 | DQ99: 1 | DU99: 1003 | DV99: м | DW99: м | DX99: 1 | EE99: 58162630 | EF99: 40 | EG99: Монтаж оборудования | EH99: 0 | EJ99: 2 | EK99: 68 | EL99: ТСН-2001.4-10. Прокладка и монтаж сетей связи | EM99: ТСН-2001.4-10-1 | EQ99: 0 | ER99: 4.59 | ES99: 4.59 | ET99: 0 | EU99: 0 | EV99: 0 | EW99: 0 | EX99: 0 | FQ99: 0 | FR99: 0 | FS99: 0 | FX99: 90 | FY99: 46 | GD99: 1 | GF99: 1515925975 | GG99: 2 | GH99: 1 | GI99: -2 | GJ99: 0 | GK99: 0 | GL99: =ROUND(IF(AND(BH99=3,BI99=3,FS99<>0),P99,0),2) -> 0 | GM99: =ROUND(O99+X99+Y99,2)+GX99 -> 163.86 | GN99: =IF(OR(BI99=0,BI99=1),GM99-GX99,0) -> 0 | GO99: =IF(BI99=2,GM99-GX99,0) -> 163.86 | GP99: =IF(BI99=4,GM99-GX99,0) -> 0 | GR99: 0 | GS99: 3 | GT99: 0 | GV99: =ROUND((GT99),6) -> 0 | GW99: 1 | GX99: =ROUND(HC99*I99,2) -> 0 | HA99: 0 | HB99: 0 | HC99: =GV99*GW99 -> 0 | HS99: 0 | IK99: 0
A100: 18 | B100: 1 | E100: 9,1 | F100: 1.12-5-42 | G100: Трубы из непластифицированного вторичного ПВХ, гладкие, самозатухающие, усиленного типа, наружный диаметр 20 мм, толщина стенки 1,5 мм, для электропроводок | H100: м | I100: =I98*J100 -> 35.7 | J100: 10.656716 | K100: 10.656716 | O100: =ROUND(CP100,2) -> 961.86 | P100: =ROUND((ROUND((AC100*AW100*I100),2)*BC100),2) -> 961.86 | Q100: =(ROUND((ROUND(((ET100)*AV100*I100),2)*BB100),2)+ROUND((ROUND(((AE100-(EU100))*AV100*I100),2)*BS100),2)) -> 0 | R100: =ROUND((ROUND((AE100*AV100*I100),2)*BS100),2) -> 0 | S100: =ROUND((ROUND((AF100*AV100*I100),2)*BA100),2) -> 0 | T100: =ROUND(CU100*I100,2) -> 0 | U100: =CV100*I100 -> 0 | V100: =CW100*I100 -> 0 | W100: =ROUND(CX100*I100,2) -> 0 | X100: =ROUND(CY100,2) -> 0 | Y100: =ROUND(CZ100,2) -> 0 | AA100: 56511235 | AB100: =ROUND((AC100+AD100+AF100),6) -> 4.59 | AC100: =ROUND((ES100),6) -> 4.59 | AD100: =ROUND((((ET100)-(EU100))+AE100),6) -> 0 | AE100: =ROUND((EU100),6) -> 0 | AF100: =ROUND((EV100),6) -> 0 | AG100: =ROUND((AP100),6) -> 0 | AH100: =(EW100) -> 0 | AI100: =(EX100) -> 0 | AJ100: =(AS100) -> 0 | AK100: 4.59 | AL100: 4.59 | AM100: 0 | AN100: 0 | AO100: 0 | AP100: 0 | AQ100: 0 | AR100: 0 | AS100: 0 | AT100: 90 | AU100: 46 | AV100: 1 | AW100: 1 | AZ100: 1 | BA100: 1 | BB100: 1 | BC100: 5.87 | BH100: 3 | BI100: 2 | BJ100: ТСН-2001.1 Доп. 67, Р. 12, о. 5, поз. 42 | BM100: 68 | BN100: 0 | BO100: 1.12-5-42 | BP100: 1 | BQ100: 40 | BR100: 0 | BS100: 1 | BT100: 1 | BU100: 1 | BV100: 1 | BW100: 1 | BX100: 1 | BZ100: 90 | CA100: 46 | CE100: 30 | CF100: 0 | CG100: 0 | CM100: 0 | CO100: 0 | CP100: =(P100+Q100+S100) -> 961.86 | CQ100: =ROUND((ROUND((AC100*AW100*1),2)*BC100),2) -> 26.94 | CR100: =(ROUND((ROUND(((ET100)*AV100*1),2)*BB100),2)+ROUND((ROUND(((AE100-(EU100))*AV100*1),2)*BS100),2)) -> 0 | CS100: =ROUND((ROUND((AE100*AV100*1),2)*BS100),2) -> 0 | CT100: =ROUND((ROUND((AF100*AV100*1),2)*BA100),2) -> 0 | CU100: =AG100 -> 0 | CV100: =(AH100*AV100) -> 0 | CW100: =AI100 -> 0 | CX100: =AJ100 -> 0 | CY100: =(((S100+R100)*AT100)/100) -> 0 | CZ100: =(((S100+R100)*AU100)/100) -> 0 | DN100: 0 | DO100: 0 | DP100: 1 | DQ100: 1 | DU100: 1003 | DV100: м | DW100: м | DX100: 1 | EE100: 58162630 | EF100: 40 | EG100: Монтаж оборудования | EH100: 0 | EJ100: 2 | EK100: 68 | EL100: ТСН-2001.4-10. Прокладка и монтаж сетей связи | EM100: ТСН-2001.4-10-1 | EQ100: 0 | ER100: 4.59 | ES100: 4.59 | ET100: 0 | EU100: 0 | EV100: 0 | EW100: 0 | EX100: 0 | FQ100: 0 | FR100: 0 | FS100: 0 | FX100: 90 | FY100: 46 | GD100: 1 | GF100: 1515925975 | GG100: 2 | GH100: 1 | GI100: 2 | GJ100: 0 | GK100: 0 | GL100: =ROUND(IF(AND(BH100=3,BI100=3,FS100<>0),P100,0),2) -> 0 | GM100: =ROUND(O100+X100+Y100,2)+GX100 -> 961.86 | GN100: =IF(OR(BI100=0,BI100=1),GM100-GX100,0) -> 0 | GO100: =IF(BI100=2,GM100-GX100,0) -> 961.86 | GP100: =IF(BI100=4,GM100-GX100,0) -> 0 | GR100: 0 | GS100: 3 | GT100: 0 | GV100: =ROUND((GT100),6) -> 0 | GW100: 1 | GX100: =ROUND(HC100*I100,2) -> 0 | HA100: 0 | HB100: 0 | HC100: =GV100*GW100 -> 0 | HS100: 0 | IK100: 0
A101: 18 | B101: 1 | E101: 9,2 | F101: 1.12-5-43 | G101: Трубы из непластифицированного вторичного ПВХ, гладкие, самозатухающие, усиленного типа, наружный диаметр 25 мм, толщина стенки 1,5 мм, для электропроводок | H101: м | I101: =I97*J101 -> 306 | J101: 91.343284 | K101: 91.343284 | O101: =ROUND(CP101,2) -> 1768.68 | P101: =ROUND((ROUND((AC101*AW101*I101),2)*BC101),2) -> 1768.68 | Q101: =(ROUND((ROUND(((ET101)*AV101*I101),2)*BB101),2)+ROUND((ROUND(((AE101-(EU101))*AV101*I101),2)*BS101),2)) -> 0 | R101: =ROUND((ROUND((AE101*AV101*I101),2)*BS101),2) -> 0 | S101: =ROUND((ROUND((AF101*AV101*I101),2)*BA101),2) -> 0 | T101: =ROUND(CU101*I101,2) -> 0 | U101: =CV101*I101 -> 0 | V101: =CW101*I101 -> 0 | W101: =ROUND(CX101*I101,2) -> 0 | X101: =ROUND(CY101,2) -> 0 | Y101: =ROUND(CZ101,2) -> 0 | AA101: 56511233 | AB101: =ROUND((AC101+AD101+AF101),6) -> 5.78 | AC101: =ROUND((ES101),6) -> 5.78 | AD101: =ROUND((((ET101)-(EU101))+AE101),6) -> 0 | AE101: =ROUND((EU101),6) -> 0 | AF101: =ROUND((EV101),6) -> 0 | AG101: =ROUND((AP101),6) -> 0 | AH101: =(EW101) -> 0 | AI101: =(EX101) -> 0 | AJ101: =(AS101) -> 0 | AK101: 5.78 | AL101: 5.78 | AM101: 0 | AN101: 0 | AO101: 0 | AP101: 0 | AQ101: 0 | AR101: 0 | AS101: 0 | AT101: 90 | AU101: 46 | AV101: 1 | AW101: 1 | AZ101: 1 | BA101: 1 | BB101: 1 | BC101: 1 | BH101: 3 | BI101: 2 | BJ101: ТСН-2001.1 Доп. 67, Р. 12, о. 5, поз. 43 | BM101: 68 | BN101: 0 | BP101: 0 | BQ101: 40 | BR101: 0 | BS101: 1 | BT101: 1 | BU101: 1 | BV101: 1 | BW101: 1 | BX101: 1 | BZ101: 90 | CA101: 46 | CE101: 30 | CF101: 0 | CG101: 0 | CM101: 0 | CO101: 0 | CP101: =(P101+Q101+S101) -> 1768.68 | CQ101: =ROUND((ROUND((AC101*AW101*1),2)*BC101),2) -> 5.78 | CR101: =(ROUND((ROUND(((ET101)*AV101*1),2)*BB101),2)+ROUND((ROUND(((AE101-(EU101))*AV101*1),2)*BS101),2)) -> 0 | CS101: =ROUND((ROUND((AE101*AV101*1),2)*BS101),2) -> 0 | CT101: =ROUND((ROUND((AF101*AV101*1),2)*BA101),2) -> 0 | CU101: =AG101 -> 0 | CV101: =(AH101*AV101) -> 0 | CW101: =AI101 -> 0 | CX101: =AJ101 -> 0 | CY101: =(((S101+R101)*AT101)/100) -> 0 | CZ101: =(((S101+R101)*AU101)/100) -> 0 | DN101: 0 | DO101: 0 | DP101: 1 | DQ101: 1 | DU101: 1003 | DV101: м | DW101: м | DX101: 1 | EE101: 58162630 | EF101: 40 | EG101: Монтаж оборудования | EH101: 0 | EJ101: 2 | EK101: 68 | EL101: ТСН-2001.4-10. Прокладка и монтаж сетей связи | EM101: ТСН-2001.4-10-1 | EQ101: 0 | ER101: 5.78 | ES101: 5.78 | ET101: 0 | EU101: 0 | EV101: 0 | EW101: 0 | EX101: 0 | FQ101: 0 | FR101: 0 | FS101: 0 | FX101: 90 | FY101: 46 | GD101: 1 | GF101: -2129111418 | GG101: 2 | GH101: 1 | GI101: -2 | GJ101: 0 | GK101: 0 | GL101: =ROUND(IF(AND(BH101=3,BI101=3,FS101<>0),P101,0),2) -> 0 | GM101: =ROUND(O101+X101+Y101,2)+GX101 -> 1768.68 | GN101: =IF(OR(BI101=0,BI101=1),GM101-GX101,0) -> 0 | GO101: =IF(BI101=2,GM101-GX101,0) -> 1768.68 | GP101: =IF(BI101=4,GM101-GX101,0) -> 0 | GR101: 0 | GS101: 3 | GT101: 0 | GV101: =ROUND((GT101),6) -> 0 | GW101: 1 | GX101: =ROUND(HC101*I101,2) -> 0 | HA101: 0 | HB101: 0 | HC101: =GV101*GW101 -> 0 | HS101: 0 | IK101: 0
A102: 18 | B102: 1 | E102: 9,2 | F102: 1.12-5-43 | G102: Трубы из непластифицированного вторичного ПВХ, гладкие, самозатухающие, усиленного типа, наружный диаметр 25 мм, толщина стенки 1,5 мм, для электропроводок | H102: м | I102: =I98*J102 -> 306 | J102: 91.343284 | K102: 91.343284 | O102: =ROUND(CP102,2) -> 10859.7 | P102: =ROUND((ROUND((AC102*AW102*I102),2)*BC102),2) -> 10859.7 | Q102: =(ROUND((ROUND(((ET102)*AV102*I102),2)*BB102),2)+ROUND((ROUND(((AE102-(EU102))*AV102*I102),2)*BS102),2)) -> 0 | R102: =ROUND((ROUND((AE102*AV102*I102),2)*BS102),2) -> 0 | S102: =ROUND((ROUND((AF102*AV102*I102),2)*BA102),2) -> 0 | T102: =ROUND(CU102*I102,2) -> 0 | U102: =CV102*I102 -> 0 | V102: =CW102*I102 -> 0 | W102: =ROUND(CX102*I102,2) -> 0 | X102: =ROUND(CY102,2) -> 0 | Y102: =ROUND(CZ102,2) -> 0 | AA102: 56511235 | AB102: =ROUND((AC102+AD102+AF102),6) -> 5.78 | AC102: =ROUND((ES102),6) -> 5.78 | AD102: =ROUND((((ET102)-(EU102))+AE102),6) -> 0 | AE102: =ROUND((EU102),6) -> 0 | AF102: =ROUND((EV102),6) -> 0 | AG102: =ROUND((AP102),6) -> 0 | AH102: =(EW102) -> 0 | AI102: =(EX102) -> 0 | AJ102: =(AS102) -> 0 | AK102: 5.78 | AL102: 5.78 | AM102: 0 | AN102: 0 | AO102: 0 | AP102: 0 | AQ102: 0 | AR102: 0 | AS102: 0 | AT102: 90 | AU102: 46 | AV102: 1 | AW102: 1 | AZ102: 1 | BA102: 1 | BB102: 1 | BC102: 6.14 | BH102: 3 | BI102: 2 | BJ102: ТСН-2001.1 Доп. 67, Р. 12, о. 5, поз. 43 | BM102: 68 | BN102: 0 | BO102: 1.12-5-43 | BP102: 1 | BQ102: 40 | BR102: 0 | BS102: 1 | BT102: 1 | BU102: 1 | BV102: 1 | BW102: 1 | BX102: 1 | BZ102: 90 | CA102: 46 | CE102: 30 | CF102: 0 | CG102: 0 | CM102: 0 | CO102: 0 | CP102: =(P102+Q102+S102) -> 10859.7 | CQ102: =ROUND((ROUND((AC102*AW102*1),2)*BC102),2) -> 35.49 | CR102: =(ROUND((ROUND(((ET102)*AV102*1),2)*BB102),2)+ROUND((ROUND(((AE102-(EU102))*AV102*1),2)*BS102),2)) -> 0 | CS102: =ROUND((ROUND((AE102*AV102*1),2)*BS102),2) -> 0 | CT102: =ROUND((ROUND((AF102*AV102*1),2)*BA102),2) -> 0 | CU102: =AG102 -> 0 | CV102: =(AH102*AV102) -> 0 | CW102: =AI102 -> 0 | CX102: =AJ102 -> 0 | CY102: =(((S102+R102)*AT102)/100) -> 0 | CZ102: =(((S102+R102)*AU102)/100) -> 0 | DN102: 0 | DO102: 0 | DP102: 1 | DQ102: 1 | DU102: 1003 | DV102: м | DW102: м | DX102: 1 | EE102: 58162630 | EF102: 40 | EG102: Монтаж оборудования | EH102: 0 | EJ102: 2 | EK102: 68 | EL102: ТСН-2001.4-10. Прокладка и монтаж сетей связи | EM102: ТСН-2001.4-10-1 | EQ102: 0 | ER102: 5.78 | ES102: 5.78 | ET102: 0 | EU102: 0 | EV102: 0 | EW102: 0 | EX102: 0 | FQ102: 0 | FR102: 0 | FS102: 0 | FX102: 90 | FY102: 46 | GD102: 1 | GF102: -2129111418 | GG102: 2 | GH102: 1 | GI102: 2 | GJ102: 0 | GK102: 0 | GL102: =ROUND(IF(AND(BH102=3,BI102=3,FS102<>0),P102,0),2) -> 0 | GM102: =ROUND(O102+X102+Y102,2)+GX102 -> 10859.7 | GN102: =IF(OR(BI102=0,BI102=1),GM102-GX102,0) -> 0 | GO102: =IF(BI102=2,GM102-GX102,0) -> 10859.7 | GP102: =IF(BI102=4,GM102-GX102,0) -> 0 | GR102: 0 | GS102: 3 | GT102: 0 | GV102: =ROUND((GT102),6) -> 0 | GW102: 1 | GX102: =ROUND(HC102*I102,2) -> 0 | HA102: 0 | HB102: 0 | HC102: =GV102*GW102 -> 0 | HS102: 0 | IK102: 0
A103: 18 | B103: 1 | E103: 9,3 | F103: 1.21-5-1136 | G103: Держатель пластиковый с защелкой для крепления труб, рукавов и гибких вводов диаметром 20 мм | H103: 100 шт. | I103: =I97*J103 -> 1 | J103: 0.29850746 | K103: 0.2985075 | O103: =ROUND(CP103,2) -> 146.89 | P103: =ROUND((ROUND((AC103*AW103*I103),2)*BC103),2) -> 146.89 | Q103: =(ROUND((ROUND(((ET103)*AV103*I103),2)*BB103),2)+ROUND((ROUND(((AE103-(EU103))*AV103*I103),2)*BS103),2)) -> 0 | R103: =ROUND((ROUND((AE103*AV103*I103),2)*BS103),2) -> 0 | S103: =ROUND((ROUND((AF103*AV103*I103),2)*BA103),2) -> 0 | T103: =ROUND(CU103*I103,2) -> 0 | U103: =CV103*I103 -> 0 | V103: =CW103*I103 -> 0 | W103: =ROUND(CX103*I103,2) -> 0 | X103: =ROUND(CY103,2) -> 0 | Y103: =ROUND(CZ103,2) -> 0 | AA103: 56511233 | AB103: =ROUND((AC103+AD103+AF103),6) -> 146.89 | AC103: =ROUND((ES103),6) -> 146.89 | AD103: =ROUND((((ET103)-(EU103))+AE103),6) -> 0 | AE103: =ROUND((EU103),6) -> 0 | AF103: =ROUND((EV103),6) -> 0 | AG103: =ROUND((AP103),6) -> 0 | AH103: =(EW103) -> 0 | AI103: =(EX103) -> 0 | AJ103: =(AS103) -> 0 | AK103: 146.89 | AL103: 146.89 | AM103: 0 | AN103: 0 | AO103: 0 | AP103: 0 | AQ103: 0 | AR103: 0 | AS103: 0 | AT103: 90 | AU103: 46 | AV103: 1 | AW103: 1 | AZ103: 1 | BA103: 1 | BB103: 1 | BC103: 1 | BH103: 3 | BI103: 2 | BJ103: ТСН-2001.1 Доп. 73, Р. 21, о. 5, поз. 1136 | BM103: 68 | BN103: 0 | BP103: 0 | BQ103: 40 | BR103: 0 | BS103: 1 | BT103: 1 | BU103: 1 | BV103: 1 | BW103: 1 | BX103: 1 | BZ103: 90 | CA103: 46 | CE103: 30 | CF103: 0 | CG103: 0 | CM103: 0 | CO103: 0 | CP103: =(P103+Q103+S103) -> 146.89 | CQ103: =ROUND((ROUND((AC103*AW103*1),2)*BC103),2) -> 146.89 | CR103: =(ROUND((ROUND(((ET103)*AV103*1),2)*BB103),2)+ROUND((ROUND(((AE103-(EU103))*AV103*1),2)*BS103),2)) -> 0 | CS103: =ROUND((ROUND((AE103*AV103*1),2)*BS103),2) -> 0 | CT103: =ROUND((ROUND((AF103*AV103*1),2)*BA103),2) -> 0 | CU103: =AG103 -> 0 | CV103: =(AH103*AV103) -> 0 | CW103: =AI103 -> 0 | CX103: =AJ103 -> 0 | CY103: =(((S103+R103)*AT103)/100) -> 0 | CZ103: =(((S103+R103)*AU103)/100) -> 0 | DN103: 0 | DO103: 0 | DP103: 1 | DQ103: 1 | DU103: 1010 | DV103: 100 шт. | DW103: 100 шт. | DX103: 100 | EE103: 58162630 | EF103: 40 | EG103: Монтаж оборудования | EH103: 0 | EJ103: 2 | EK103: 68 | EL103: ТСН-2001.4-10. Прокладка и монтаж сетей связи | EM103: ТСН-2001.4-10-1 | EQ103: 0 | ER103: 146.89 | ES103: 146.89 | ET103: 0 | EU103: 0 | EV103: 0 | EW103: 0 | EX103: 0 | FQ103: 0 | FR103: 0 | FS103: 0 | FX103: 90 | FY103: 46 | GD103: 1 | GF103: -1171050213 | GG103: 2 | GH103: 1 | GI103: -2 | GJ103: 0 | GK103: 0 | GL103: =ROUND(IF(AND(BH103=3,BI103=3,FS103<>0),P103,0),2) -> 0 | GM103: =ROUND(O103+X103+Y103,2)+GX103 -> 146.89 | GN103: =IF(OR(BI103=0,BI103=1),GM103-GX103,0) -> 0 | GO103: =IF(BI103=2,GM103-GX103,0) -> 146.89 | GP103: =IF(BI103=4,GM103-GX103,0) -> 0 | GR103: 0 | GS103: 3 | GT103: 0 | GV103: =ROUND((GT103),6) -> 0 | GW103: 1 | GX103: =ROUND(HC103*I103,2) -> 0 | HA103: 0 | HB103: 0 | HC103: =GV103*GW103 -> 0 | HS103: 0 | IK103: 0
A104: 18 | B104: 1 | E104: 9,3 | F104: 1.21-5-1136 | G104: Держатель пластиковый с защелкой для крепления труб, рукавов и гибких вводов диаметром 20 мм | H104: 100 шт. | I104: =I98*J104 -> 1 | J104: 0.29850746 | K104: 0.2985075 | O104: =ROUND(CP104,2) -> 298.19 | P104: =ROUND((ROUND((AC104*AW104*I104),2)*BC104),2) -> 298.19 | Q104: =(ROUND((ROUND(((ET104)*AV104*I104),2)*BB104),2)+ROUND((ROUND(((AE104-(EU104))*AV104*I104),2)*BS104),2)) -> 0 | R104: =ROUND((ROUND((AE104*AV104*I104),2)*BS104),2) -> 0 | S104: =ROUND((ROUND((AF104*AV104*I104),2)*BA104),2) -> 0 | T104: =ROUND(CU104*I104,2) -> 0 | U104: =CV104*I104 -> 0 | V104: =CW104*I104 -> 0 | W104: =ROUND(CX104*I104,2) -> 0 | X104: =ROUND(CY104,2) -> 0 | Y104: =ROUND(CZ104,2) -> 0 | AA104: 56511235 | AB104: =ROUND((AC104+AD104+AF104),6) -> 146.89 | AC104: =ROUND((ES104),6) -> 146.89 | AD104: =ROUND((((ET104)-(EU104))+AE104),6) -> 0 | AE104: =ROUND((EU104),6) -> 0 | AF104: =ROUND((EV104),6) -> 0 | AG104: =ROUND((AP104),6) -> 0 | AH104: =(EW104) -> 0 | AI104: =(EX104) -> 0 | AJ104: =(AS104) -> 0 | AK104: 146.89 | AL104: 146.89 | AM104: 0 | AN104: 0 | AO104: 0 | AP104: 0 | AQ104: 0 | AR104: 0 | AS104: 0 | AT104: 90 | AU104: 46 | AV104: 1 | AW104: 1 | AZ104: 1 | BA104: 1 | BB104: 1 | BC104: 2.03 | BH104: 3 | BI104: 2 | BJ104: ТСН-2001.1 Доп. 73, Р. 21, о. 5, поз. 1136 | BM104: 68 | BN104: 0 | BO104: 1.21-5-1136 | BP104: 1 | BQ104: 40 | BR104: 0 | BS104: 1 | BT104: 1 | BU104: 1 | BV104: 1 | BW104: 1 | BX104: 1 | BZ104: 90 | CA104: 46 | CE104: 30 | CF104: 0 | CG104: 0 | CM104: 0 | CO104: 0 | CP104: =(P104+Q104+S104) -> 298.19 | CQ104: =ROUND((ROUND((AC104*AW104*1),2)*BC104),2) -> 298.19 | CR104: =(ROUND((ROUND(((ET104)*AV104*1),2)*BB104),2)+ROUND((ROUND(((AE104-(EU104))*AV104*1),2)*BS104),2)) -> 0 | CS104: =ROUND((ROUND((AE104*AV104*1),2)*BS104),2) -> 0 | CT104: =ROUND((ROUND((AF104*AV104*1),2)*BA104),2) -> 0 | CU104: =AG104 -> 0 | CV104: =(AH104*AV104) -> 0 | CW104: =AI104 -> 0 | CX104: =AJ104 -> 0 | CY104: =(((S104+R104)*AT104)/100) -> 0 | CZ104: =(((S104+R104)*AU104)/100) -> 0 | DN104: 0 | DO104: 0 | DP104: 1 | DQ104: 1 | DU104: 1010 | DV104: 100 шт. | DW104: 100 шт. | DX104: 100 | EE104: 58162630 | EF104: 40 | EG104: Монтаж оборудования | EH104: 0 | EJ104: 2 | EK104: 68 | EL104: ТСН-2001.4-10. Прокладка и монтаж сетей связи | EM104: ТСН-2001.4-10-1 | EQ104: 0 | ER104: 146.89 | ES104: 146.89 | ET104: 0 | EU104: 0 | EV104: 0 | EW104: 0 | EX104: 0 | FQ104: 0 | FR104: 0 | FS104: 0 | FX104: 90 | FY104: 46 | GD104: 1 | GF104: -1171050213 | GG104: 2 | GH104: 1 | GI104: 2 | GJ104: 0 | GK104: 0 | GL104: =ROUND(IF(AND(BH104=3,BI104=3,FS104<>0),P104,0),2) -> 0 | GM104: =ROUND(O104+X104+Y104,2)+GX104 -> 298.19 | GN104: =IF(OR(BI104=0,BI104=1),GM104-GX104,0) -> 0 | GO104: =IF(BI104=2,GM104-GX104,0) -> 298.19 | GP104: =IF(BI104=4,GM104-GX104,0) -> 0 | GR104: 0 | GS104: 3 | GT104: 0 | GV104: =ROUND((GT104),6) -> 0 | GW104: 1 | GX104: =ROUND(HC104*I104,2) -> 0 | HA104: 0 | HB104: 0 | HC104: =GV104*GW104 -> 0 | HS104: 0 | IK104: 0
A105: 18 | B105: 1 | E105: 9,4 | F105: 1.21-5-1137 | G105: Держатель пластиковый с защелкой для крепления труб, рукавов и гибких вводов диаметром 25 мм | H105: 100 шт. | I105: =I97*J105 -> 2 | J105: 0.59701493 | K105: 0.597015 | O105: =ROUND(CP105,2) -> 308.72 | P105: =ROUND((ROUND((AC105*AW105*I105),2)*BC105),2) -> 308.72 | Q105: =(ROUND((ROUND(((ET105)*AV105*I105),2)*BB105),2)+ROUND((ROUND(((AE105-(EU105))*AV105*I105),2)*BS105),2)) -> 0 | R105: =ROUND((ROUND((AE105*AV105*I105),2)*BS105),2) -> 0 | S105: =ROUND((ROUND((AF105*AV105*I105),2)*BA105),2) -> 0 | T105: =ROUND(CU105*I105,2) -> 0 | U105: =CV105*I105 -> 0 | V105: =CW105*I105 -> 0 | W105: =ROUND(CX105*I105,2) -> 0 | X105: =ROUND(CY105,2) -> 0 | Y105: =ROUND(CZ105,2) -> 0 | AA105: 56511233 | AB105: =ROUND((AC105+AD105+AF105),6) -> 154.36 | AC105: =ROUND((ES105),6) -> 154.36 | AD105: =ROUND((((ET105)-(EU105))+AE105),6) -> 0 | AE105: =ROUND((EU105),6) -> 0 | AF105: =ROUND((EV105),6) -> 0 | AG105: =ROUND((AP105),6) -> 0 | AH105: =(EW105) -> 0 | AI105: =(EX105) -> 0 | AJ105: =(AS105) -> 0 | AK105: 154.36 | AL105: 154.36 | AM105: 0 | AN105: 0 | AO105: 0 | AP105: 0 | AQ105: 0 | AR105: 0 | AS105: 0 | AT105: 90 | AU105: 46 | AV105: 1 | AW105: 1 | AZ105: 1 | BA105: 1 | BB105: 1 | BC105: 1 | BH105: 3 | BI105: 2 | BJ105: ТСН-2001.1 Доп. 79, Р. 21, о. 5, поз. 1137 | BM105: 68 | BN105: 0 | BP105: 0 | BQ105: 40 | BR105: 0 | BS105: 1 | BT105: 1 | BU105: 1 | BV105: 1 | BW105: 1 | BX105: 1 | BZ105: 90 | CA105: 46 | CE105: 30 | CF105: 0 | CG105: 0 | CM105: 0 | CO105: 0 | CP105: =(P105+Q105+S105) -> 308.72 | CQ105: =ROUND((ROUND((AC105*AW105*1),2)*BC105),2) -> 154.36 | CR105: =(ROUND((ROUND(((ET105)*AV105*1),2)*BB105),2)+ROUND((ROUND(((AE105-(EU105))*AV105*1),2)*BS105),2)) -> 0 | CS105: =ROUND((ROUND((AE105*AV105*1),2)*BS105),2) -> 0 | CT105: =ROUND((ROUND((AF105*AV105*1),2)*BA105),2) -> 0 | CU105: =AG105 -> 0 | CV105: =(AH105*AV105) -> 0 | CW105: =AI105 -> 0 | CX105: =AJ105 -> 0 | CY105: =(((S105+R105)*AT105)/100) -> 0 | CZ105: =(((S105+R105)*AU105)/100) -> 0 | DN105: 0 | DO105: 0 | DP105: 1 | DQ105: 1 | DU105: 1010 | DV105: 100 шт. | DW105: 100 шт. | DX105: 100 | EE105: 58162630 | EF105: 40 | EG105: Монтаж оборудования | EH105: 0 | EJ105: 2 | EK105: 68 | EL105: ТСН-2001.4-10. Прокладка и монтаж сетей связи | EM105: ТСН-2001.4-10-1 | EQ105: 0 | ER105: 154.36 | ES105: 154.36 | ET105: 0 | EU105: 0 | EV105: 0 | EW105: 0 | EX105: 0 | FQ105: 0 | FR105: 0 | FS105: 0 | FX105: 90 | FY105: 46 | GD105: 1 | GF105: -171069705 | GG105: 2 | GH105: 1 | GI105: -2 | GJ105: 0 | GK105: 0 | GL105: =ROUND(IF(AND(BH105=3,BI105=3,FS105<>0),P105,0),2) -> 0 | GM105: =ROUND(O105+X105+Y105,2)+GX105 -> 308.72 | GN105: =IF(OR(BI105=0,BI105=1),GM105-GX105,0) -> 0 | GO105: =IF(BI105=2,GM105-GX105,0) -> 308.72 | GP105: =IF(BI105=4,GM105-GX105,0) -> 0 | GR105: 0 | GS105: 3 | GT105: 0 | GV105: =ROUND((GT105),6) -> 0 | GW105: 1 | GX105: =ROUND(HC105*I105,2) -> 0 | HA105: 0 | HB105: 0 | HC105: =GV105*GW105 -> 0 | HS105: 0 | IK105: 0
A106: 18 | B106: 1 | E106: 9,4 | F106: 1.21-5-1137 | G106: Держатель пластиковый с защелкой для крепления труб, рукавов и гибких вводов диаметром 25 мм | H106: 100 шт. | I106: =I98*J106 -> 2 | J106: 0.59701493 | K106: 0.597015 | O106: =ROUND(CP106,2) -> 635.96 | P106: =ROUND((ROUND((AC106*AW106*I106),2)*BC106),2) -> 635.96 | Q106: =(ROUND((ROUND(((ET106)*AV106*I106),2)*BB106),2)+ROUND((ROUND(((AE106-(EU106))*AV106*I106),2)*BS106),2)) -> 0 | R106: =ROUND((ROUND((AE106*AV106*I106),2)*BS106),2) -> 0 | S106: =ROUND((ROUND((AF106*AV106*I106),2)*BA106),2) -> 0 | T106: =ROUND(CU106*I106,2) -> 0 | U106: =CV106*I106 -> 0 | V106: =CW106*I106 -> 0 | W106: =ROUND(CX106*I106,2) -> 0 | X106: =ROUND(CY106,2) -> 0 | Y106: =ROUND(CZ106,2) -> 0 | AA106: 56511235 | AB106: =ROUND((AC106+AD106+AF106),6) -> 154.36 | AC106: =ROUND((ES106),6) -> 154.36 | AD106: =ROUND((((ET106)-(EU106))+AE106),6) -> 0 | AE106: =ROUND((EU106),6) -> 0 | AF106: =ROUND((EV106),6) -> 0 | AG106: =ROUND((AP106),6) -> 0 | AH106: =(EW106) -> 0 | AI106: =(EX106) -> 0 | AJ106: =(AS106) -> 0 | AK106: 154.36 | AL106: 154.36 | AM106: 0 | AN106: 0 | AO106: 0 | AP106: 0 | AQ106: 0 | AR106: 0 | AS106: 0 | AT106: 90 | AU106: 46 | AV106: 1 | AW106: 1 | AZ106: 1 | BA106: 1 | BB106: 1 | BC106: 2.06 | BH106: 3 | BI106: 2 | BJ106: ТСН-2001.1 Доп. 79, Р. 21, о. 5, поз. 1137 | BM106: 68 | BN106: 0 | BO106: 1.21-5-1137 | BP106: 1 | BQ106: 40 | BR106: 0 | BS106: 1 | BT106: 1 | BU106: 1 | BV106: 1 | BW106: 1 | BX106: 1 | BZ106: 90 | CA106: 46 | CE106: 30 | CF106: 0 | CG106: 0 | CM106: 0 | CO106: 0 | CP106: =(P106+Q106+S106) -> 635.96 | CQ106: =ROUND((ROUND((AC106*AW106*1),2)*BC106),2) -> 317.98 | CR106: =(ROUND((ROUND(((ET106)*AV106*1),2)*BB106),2)+ROUND((ROUND(((AE106-(EU106))*AV106*1),2)*BS106),2)) -> 0 | CS106: =ROUND((ROUND((AE106*AV106*1),2)*BS106),2) -> 0 | CT106: =ROUND((ROUND((AF106*AV106*1),2)*BA106),2) -> 0 | CU106: =AG106 -> 0 | CV106: =(AH106*AV106) -> 0 | CW106: =AI106 -> 0 | CX106: =AJ106 -> 0 | CY106: =(((S106+R106)*AT106)/100) -> 0 | CZ106: =(((S106+R106)*AU106)/100) -> 0 | DN106: 0 | DO106: 0 | DP106: 1 | DQ106: 1 | DU106: 1010 | DV106: 100 шт. | DW106: 100 шт. | DX106: 100 | EE106: 58162630 | EF106: 40 | EG106: Монтаж оборудования | EH106: 0 | EJ106: 2 | EK106: 68 | EL106: ТСН-2001.4-10. Прокладка и монтаж сетей связи | EM106: ТСН-2001.4-10-1 | EQ106: 0 | ER106: 154.36 | ES106: 154.36 | ET106: 0 | EU106: 0 | EV106: 0 | EW106: 0 | EX106: 0 | FQ106: 0 | FR106: 0 | FS106: 0 | FX106: 90 | FY106: 46 | GD106: 1 | GF106: -171069705 | GG106: 2 | GH106: 1 | GI106: 2 | GJ106: 0 | GK106: 0 | GL106: =ROUND(IF(AND(BH106=3,BI106=3,FS106<>0),P106,0),2) -> 0 | GM106: =ROUND(O106+X106+Y106,2)+GX106 -> 635.96 | GN106: =IF(OR(BI106=0,BI106=1),GM106-GX106,0) -> 0 | GO106: =IF(BI106=2,GM106-GX106,0) -> 635.96 | GP106: =IF(BI106=4,GM106-GX106,0) -> 0 | GR106: 0 | GS106: 3 | GT106: 0 | GV106: =ROUND((GT106),6) -> 0 | GW106: 1 | GX106: =ROUND(HC106*I106,2) -> 0 | HA106: 0 | HB106: 0 | HC106: =GV106*GW106 -> 0 | HS106: 0 | IK106: 0
A107: 18 | B107: 1 | E107: 9,5 | F107: КА 4 | G107: Кабель U/UTP Cat5e PVCLSнг(А)-LSLTx 2х2х0,52 мм | H107: км | I107: =I97*J107 -> 0.0357 | J107: 0.010656716 | K107: 0.0106567 | O107: =ROUND(CP107,2) -> 168.92 | P107: =ROUND((ROUND((AC107*AW107*I107),2)*BC107),2) -> 168.92 | Q107: =(ROUND((ROUND(((ET107)*AV107*I107),2)*BB107),2)+ROUND((ROUND(((AE107-(EU107))*AV107*I107),2)*BS107),2)) -> 0 | R107: =ROUND((ROUND((AE107*AV107*I107),2)*BS107),2) -> 0 | S107: =ROUND((ROUND((AF107*AV107*I107),2)*BA107),2) -> 0 | T107: =ROUND(CU107*I107,2) -> 0 | U107: =CV107*I107 -> 0 | V107: =CW107*I107 -> 0 | W107: =ROUND(CX107*I107,2) -> 0 | X107: =ROUND(CY107,2) -> 0 | Y107: =ROUND(CZ107,2) -> 0 | AA107: 56511233 | AB107: =ROUND((AC107+AD107+AF107),6) -> 4731.78 | AC107: =ROUND((ES107),6) -> 4731.78 | AD107: =ROUND((((ET107)-(EU107))+AE107),6) -> 0 | AE107: =ROUND((EU107),6) -> 0 | AF107: =ROUND((EV107),6) -> 0 | AG107: =ROUND((AP107),6) -> 0 | AH107: =(EW107) -> 0 | AI107: =(EX107) -> 0 | AJ107: =(AS107) -> 0 | AK107: 4731.78 | AL107: 4731.78 | AM107: 0 | AN107: 0 | AO107: 0 | AP107: 0 | AQ107: 0 | AR107: 0 | AS107: 0 | AT107: 90 | AU107: 46 | AV107: 1 | AW107: 1 | AZ107: 1 | BA107: 1 | BB107: 1 | BC107: 1 | BH107: 3 | BI107: 2 | BM107: 68 | BN107: 0 | BP107: 0 | BQ107: 40 | BR107: 0 | BS107: 1 | BT107: 1 | BU107: 1 | BV107: 1 | BW107: 1 | BX107: 1 | BZ107: 90 | CA107: 46 | CE107: 30 | CF107: 0 | CG107: 0 | CM107: 0 | CO107: 0 | CP107: =(P107+Q107+S107) -> 168.92 | CQ107: =ROUND((ROUND((AC107*AW107*1),2)*BC107),2) -> 4731.78 | CR107: =(ROUND((ROUND(((ET107)*AV107*1),2)*BB107),2)+ROUND((ROUND(((AE107-(EU107))*AV107*1),2)*BS107),2)) -> 0 | CS107: =ROUND((ROUND((AE107*AV107*1),2)*BS107),2) -> 0 | CT107: =ROUND((ROUND((AF107*AV107*1),2)*BA107),2) -> 0 | CU107: =AG107 -> 0 | CV107: =(AH107*AV107) -> 0 | CW107: =AI107 -> 0 | CX107: =AJ107 -> 0 | CY107: =(((S107+R107)*AT107)/100) -> 0 | CZ107: =(((S107+R107)*AU107)/100) -> 0 | DN107: 0 | DO107: 0 | DP107: 1 | DQ107: 1 | DU107: 1003 | DV107: км | DW107: км | DX107: 1000 | EE107: 58162630 | EF107: 40 | EG107: Монтаж оборудования | EH107: 0 | EJ107: 2 | EK107: 68 | EL107: ТСН-2001.4-10. Прокладка и монтаж сетей связи | EM107: ТСН-2001.4-10-1 | EQ107: 0 | ER107: 0 | ES107: 4731.78 | ET107: 0 | EU107: 0 | EV107: 0 | EW107: 0 | EX107: 0 | FQ107: 0 | FR107: 0 | FS107: 0 | FX107: 90 | FY107: 46 | GA107: [55 000 / 1,2 / 9,88] + 2% Заг.скл | GD107: 1 | GF107: 878106166 | GG107: 2 | GH107: 4 | GI107: -2 | GJ107: 0 | GK107: 0 | GL107: =ROUND(IF(AND(BH107=3,BI107=3,FS107<>0),P107,0),2) -> 0 | GM107: =ROUND(O107+X107+Y107,2)+GX107 -> 168.92 | GN107: =IF(OR(BI107=0,BI107=1),GM107-GX107,0) -> 0 | GO107: =IF(BI107=2,GM107-GX107,0) -> 168.92 | GP107: =IF(BI107=4,GM107-GX107,0) -> 0 | GR107: 0 | GS107: 2 | GT107: 0 | GV107: =ROUND((GT107),6) -> 0 | GW107: 1 | GX107: =ROUND(HC107*I107,2) -> 0 | HA107: 0 | HB107: 0 | HC107: =GV107*GW107 -> 0 | HE107: 0 | HF107: 2 | HS107: 0 | IK107: 0
A108: 18 | B108: 1 | E108: 9,5 | F108: КА 4 | G108: Кабель U/UTP Cat5e PVCLSнг(А)-LSLTx 2х2х0,52 мм | H108: км | I108: =I98*J108 -> 0.0357 | J108: 0.010656716 | K108: 0.0106567 | O108: =ROUND(CP108,2) -> 1668.93 | P108: =ROUND((ROUND((AC108*AW108*I108),2)*BC108),2) -> 1668.93 | Q108: =(ROUND((ROUND(((ET108)*AV108*I108),2)*BB108),2)+ROUND((ROUND(((AE108-(EU108))*AV108*I108),2)*BS108),2)) -> 0 | R108: =ROUND((ROUND((AE108*AV108*I108),2)*BS108),2) -> 0 | S108: =ROUND((ROUND((AF108*AV108*I108),2)*BA108),2) -> 0 | T108: =ROUND(CU108*I108,2) -> 0 | U108: =CV108*I108 -> 0 | V108: =CW108*I108 -> 0 | W108: =ROUND(CX108*I108,2) -> 0 | X108: =ROUND(CY108,2) -> 0 | Y108: =ROUND(CZ108,2) -> 0 | AA108: 56511235 | AB108: =ROUND((AC108+AD108+AF108),6) -> 4731.78 | AC108: =ROUND((ES108),6) -> 4731.78 | AD108: =ROUND((((ET108)-(EU108))+AE108),6) -> 0 | AE108: =ROUND((EU108),6) -> 0 | AF108: =ROUND((EV108),6) -> 0 | AG108: =ROUND((AP108),6) -> 0 | AH108: =(EW108) -> 0 | AI108: =(EX108) -> 0 | AJ108: =(AS108) -> 0 | AK108: 4731.78 | AL108: 4731.78 | AM108: 0 | AN108: 0 | AO108: 0 | AP108: 0 | AQ108: 0 | AR108: 0 | AS108: 0 | AT108: 90 | AU108: 46 | AV108: 1 | AW108: 1 | AZ108: 1 | BA108: 1 | BB108: 1 | BC108: 9.88 | BH108: 3 | BI108: 2 | BM108: 68 | BN108: 0 | BP108: 0 | BQ108: 40 | BR108: 0 | BS108: 1 | BT108: 1 | BU108: 1 | BV108: 1 | BW108: 1 | BX108: 1 | BZ108: 90 | CA108: 46 | CE108: 30 | CF108: 0 | CG108: 0 | CM108: 0 | CO108: 0 | CP108: =(P108+Q108+S108) -> 1668.93 | CQ108: =ROUND((ROUND((AC108*AW108*1),2)*BC108),2) -> 46749.99 | CR108: =(ROUND((ROUND(((ET108)*AV108*1),2)*BB108),2)+ROUND((ROUND(((AE108-(EU108))*AV108*1),2)*BS108),2)) -> 0 | CS108: =ROUND((ROUND((AE108*AV108*1),2)*BS108),2) -> 0 | CT108: =ROUND((ROUND((AF108*AV108*1),2)*BA108),2) -> 0 | CU108: =AG108 -> 0 | CV108: =(AH108*AV108) -> 0 | CW108: =AI108 -> 0 | CX108: =AJ108 -> 0 | CY108: =(((S108+R108)*AT108)/100) -> 0 | CZ108: =(((S108+R108)*AU108)/100) -> 0 | DN108: 0 | DO108: 0 | DP108: 1 | DQ108: 1 | DU108: 1003 | DV108: км | DW108: км | DX108: 1000 | EE108: 58162630 | EF108: 40 | EG108: Монтаж оборудования | EH108: 0 | EJ108: 2 | EK108: 68 | EL108: ТСН-2001.4-10. Прокладка и монтаж сетей связи | EM108: ТСН-2001.4-10-1 | EQ108: 0 | ER108: 46750 | ES108: 4731.78 | ET108: 0 | EU108: 0 | EV108: 0 | EW108: 0 | EX108: 0 | EZ108: 5 | FC108: 1 | FD108: 18 | FF108: 55000 | FQ108: 0 | FR108: 0 | FS108: 0 | FX108: 90 | FY108: 46 | GA108: [55 000 / 1,2 / 9,88] + 2% Заг.скл | GD108: 1 | GF108: 878106166 | GG108: 2 | GH108: 3 | GI108: 5 | GJ108: 0 | GK108: 0 | GL108: =ROUND(IF(AND(BH108=3,BI108=3,FS108<>0),P108,0),2) -> 0 | GM108: =ROUND(O108+X108+Y108,2)+GX108 -> 1668.93 | GN108: =IF(OR(BI108=0,BI108=1),GM108-GX108,0) -> 0 | GO108: =IF(BI108=2,GM108-GX108,0) -> 1668.93 | GP108: =IF(BI108=4,GM108-GX108,0) -> 0 | GR108: 1 | GS108: 1 | GT108: 0 | GV108: =ROUND((GT108),6) -> 0 | GW108: 1 | GX108: =ROUND(HC108*I108,2) -> 0 | HA108: 0 | HB108: 0 | HC108: =GV108*GW108 -> 0 | HE108: 0 | HF108: 2 | HS108: 0 | IK108: 0
A109: 18 | B109: 1 | E109: 9,6 | F109: КА 10 | G109: Кабель КИС-РВнг(А)-LSLTx 4х2х0,64 мм | H109: км | I109: =I97*J109 -> 0.0357 | J109: 0.010656716 | K109: 0.0106567 | O109: =ROUND(CP109,2) -> 1869.14 | P109: =ROUND((ROUND((AC109*AW109*I109),2)*BC109),2) -> 1869.14 | Q109: =(ROUND((ROUND(((ET109)*AV109*I109),2)*BB109),2)+ROUND((ROUND(((AE109-(EU109))*AV109*I109),2)*BS109),2)) -> 0 | R109: =ROUND((ROUND((AE109*AV109*I109),2)*BS109),2) -> 0 | S109: =ROUND((ROUND((AF109*AV109*I109),2)*BA109),2) -> 0 | T109: =ROUND(CU109*I109,2) -> 0 | U109: =CV109*I109 -> 0 | V109: =CW109*I109 -> 0 | W109: =ROUND(CX109*I109,2) -> 0 | X109: =ROUND(CY109,2) -> 0 | Y109: =ROUND(CZ109,2) -> 0 | AA109: 56511233 | AB109: =ROUND((AC109+AD109+AF109),6) -> 52356.73 | AC109: =ROUND((ES109),6) -> 52356.73 | AD109: =ROUND((((ET109)-(EU109))+AE109),6) -> 0 | AE109: =ROUND((EU109),6) -> 0 | AF109: =ROUND((EV109),6) -> 0 | AG109: =ROUND((AP109),6) -> 0 | AH109: =(EW109) -> 0 | AI109: =(EX109) -> 0 | AJ109: =(AS109) -> 0 | AK109: 52356.73 | AL109: 52356.73 | AM109: 0 | AN109: 0 | AO109: 0 | AP109: 0 | AQ109: 0 | AR109: 0 | AS109: 0 | AT109: 90 | AU109: 46 | AV109: 1 | AW109: 1 | AZ109: 1 | BA109: 1 | BB109: 1 | BC109: 1 | BH109: 3 | BI109: 2 | BM109: 68 | BN109: 0 | BP109: 0 | BQ109: 40 | BR109: 0 | BS109: 1 | BT109: 1 | BU109: 1 | BV109: 1 | BW109: 1 | BX109: 1 | BZ109: 90 | CA109: 46 | CE109: 30 | CF109: 0 | CG109: 0 | CM109: 0 | CO109: 0 | CP109: =(P109+Q109+S109) -> 1869.14 | CQ109: =ROUND((ROUND((AC109*AW109*1),2)*BC109),2) -> 52356.73 | CR109: =(ROUND((ROUND(((ET109)*AV109*1),2)*BB109),2)+ROUND((ROUND(((AE109-(EU109))*AV109*1),2)*BS109),2)) -> 0 | CS109: =ROUND((ROUND((AE109*AV109*1),2)*BS109),2) -> 0 | CT109: =ROUND((ROUND((AF109*AV109*1),2)*BA109),2) -> 0 | CU109: =AG109 -> 0 | CV109: =(AH109*AV109) -> 0 | CW109: =AI109 -> 0 | CX109: =AJ109 -> 0 | CY109: =(((S109+R109)*AT109)/100) -> 0 | CZ109: =(((S109+R109)*AU109)/100) -> 0 | DN109: 0 | DO109: 0 | DP109: 1 | DQ109: 1 | DU109: 1003 | DV109: км | DW109: км | DX109: 1000 | EE109: 58162630 | EF109: 40 | EG109: Монтаж оборудования | EH109: 0 | EJ109: 2 | EK109: 68 | EL109: ТСН-2001.4-10. Прокладка и монтаж сетей связи | EM109: ТСН-2001.4-10-1 | EQ109: 0 | ER109: 0 | ES109: 52356.73 | ET109: 0 | EU109: 0 | EV109: 0 | EW109: 0 | EX109: 0 | FQ109: 0 | FR109: 0 | FS109: 0 | FX109: 90 | FY109: 46 | GA109: [608 570 / 1,2 / 9,88] + 2% Заг.скл | GD109: 1 | GF109: 343940696 | GG109: 2 | GH109: 4 | GI109: -2 | GJ109: 0 | GK109: 0 | GL109: =ROUND(IF(AND(BH109=3,BI109=3,FS109<>0),P109,0),2) -> 0 | GM109: =ROUND(O109+X109+Y109,2)+GX109 -> 1869.14 | GN109: =IF(OR(BI109=0,BI109=1),GM109-GX109,0) -> 0 | GO109: =IF(BI109=2,GM109-GX109,0) -> 1869.14 | GP109: =IF(BI109=4,GM109-GX109,0) -> 0 | GR109: 0 | GS109: 2 | GT109: 0 | GV109: =ROUND((GT109),6) -> 0 | GW109: 1 | GX109: =ROUND(HC109*I109,2) -> 0 | HA109: 0 | HB109: 0 | HC109: =GV109*GW109 -> 0 | HE109: 0 | HF109: 2 | HS109: 0 | IK109: 0
A110: 18 | B110: 1 | E110: 9,6 | F110: КА 10 | G110: Кабель КИС-РВнг(А)-LSLTx 4х2х0,64 мм | H110: км | I110: =I98*J110 -> 0.0357 | J110: 0.010656716 | K110: 0.0106567 | O110: =ROUND(CP110,2) -> 18467.1 | P110: =ROUND((ROUND((AC110*AW110*I110),2)*BC110),2) -> 18467.1 | Q110: =(ROUND((ROUND(((ET110)*AV110*I110),2)*BB110),2)+ROUND((ROUND(((AE110-(EU110))*AV110*I110),2)*BS110),2)) -> 0 | R110: =ROUND((ROUND((AE110*AV110*I110),2)*BS110),2) -> 0 | S110: =ROUND((ROUND((AF110*AV110*I110),2)*BA110),2) -> 0 | T110: =ROUND(CU110*I110,2) -> 0 | U110: =CV110*I110 -> 0 | V110: =CW110*I110 -> 0 | W110: =ROUND(CX110*I110,2) -> 0 | X110: =ROUND(CY110,2) -> 0 | Y110: =ROUND(CZ110,2) -> 0 | AA110: 56511235 | AB110: =ROUND((AC110+AD110+AF110),6) -> 52356.73 | AC110: =ROUND((ES110),6) -> 52356.73 | AD110: =ROUND((((ET110)-(EU110))+AE110),6) -> 0 | AE110: =ROUND((EU110),6) -> 0 | AF110: =ROUND((EV110),6) -> 0 | AG110: =ROUND((AP110),6) -> 0 | AH110: =(EW110) -> 0 | AI110: =(EX110) -> 0 | AJ110: =(AS110) -> 0 | AK110: 52356.73 | AL110: 52356.73 | AM110: 0 | AN110: 0 | AO110: 0 | AP110: 0 | AQ110: 0 | AR110: 0 | AS110: 0 | AT110: 90 | AU110: 46 | AV110: 1 | AW110: 1 | AZ110: 1 | BA110: 1 | BB110: 1 | BC110: 9.88 | BH110: 3 | BI110: 2 | BM110: 68 | BN110: 0 | BP110: 0 | BQ110: 40 | BR110: 0 | BS110: 1 | BT110: 1 | BU110: 1 | BV110: 1 | BW110: 1 | BX110: 1 | BZ110: 90 | CA110: 46 | CE110: 30 | CF110: 0 | CG110: 0 | CM110: 0 | CO110: 0 | CP110: =(P110+Q110+S110) -> 18467.1 | CQ110: =ROUND((ROUND((AC110*AW110*1),2)*BC110),2) -> 517284.49 | CR110: =(ROUND((ROUND(((ET110)*AV110*1),2)*BB110),2)+ROUND((ROUND(((AE110-(EU110))*AV110*1),2)*BS110),2)) -> 0 | CS110: =ROUND((ROUND((AE110*AV110*1),2)*BS110),2) -> 0 | CT110: =ROUND((ROUND((AF110*AV110*1),2)*BA110),2) -> 0 | CU110: =AG110 -> 0 | CV110: =(AH110*AV110) -> 0 | CW110: =AI110 -> 0 | CX110: =AJ110 -> 0 | CY110: =(((S110+R110)*AT110)/100) -> 0 | CZ110: =(((S110+R110)*AU110)/100) -> 0 | DN110: 0 | DO110: 0 | DP110: 1 | DQ110: 1 | DU110: 1003 | DV110: км | DW110: км | DX110: 1000 | EE110: 58162630 | EF110: 40 | EG110: Монтаж оборудования | EH110: 0 | EJ110: 2 | EK110: 68 | EL110: ТСН-2001.4-10. Прокладка и монтаж сетей связи | EM110: ТСН-2001.4-10-1 | EQ110: 0 | ER110: 517284.5 | ES110: 52356.73 | ET110: 0 | EU110: 0 | EV110: 0 | EW110: 0 | EX110: 0 | EZ110: 5 | FC110: 1 | FD110: 18 | FF110: 608570 | FQ110: 0 | FR110: 0 | FS110: 0 | FX110: 90 | FY110: 46 | GA110: [608 570 / 1,2 / 9,88] + 2% Заг.скл | GD110: 1 | GF110: 343940696 | GG110: 2 | GH110: 3 | GI110: 5 | GJ110: 0 | GK110: 0 | GL110: =ROUND(IF(AND(BH110=3,BI110=3,FS110<>0),P110,0),2) -> 0 | GM110: =ROUND(O110+X110+Y110,2)+GX110 -> 18467.1 | GN110: =IF(OR(BI110=0,BI110=1),GM110-GX110,0) -> 0 | GO110: =IF(BI110=2,GM110-GX110,0) -> 18467.1 | GP110: =IF(BI110=4,GM110-GX110,0) -> 0 | GR110: 1 | GS110: 1 | GT110: 0 | GV110: =ROUND((GT110),6) -> 0 | GW110: 1 | GX110: =ROUND(HC110*I110,2) -> 0 | HA110: 0 | HB110: 0 | HC110: =GV110*GW110 -> 0 | HE110: 0 | HF110: 2 | HS110: 0 | IK110: 0
A111: 18 | B111: 1 | E111: 9,7 | F111: КА 11 | G111: Кабель КИС-РВнг(А)-LSLTx 2х2х0,64 мм | H111: км | I111: =I97*J111 -> 0.9129 | J111: 0.27250746 | K111: 0.2725075 | O111: =ROUND(CP111,2) -> 24347.08 | P111: =ROUND((ROUND((AC111*AW111*I111),2)*BC111),2) -> 24347.08 | Q111: =(ROUND((ROUND(((ET111)*AV111*I111),2)*BB111),2)+ROUND((ROUND(((AE111-(EU111))*AV111*I111),2)*BS111),2)) -> 0 | R111: =ROUND((ROUND((AE111*AV111*I111),2)*BS111),2) -> 0 | S111: =ROUND((ROUND((AF111*AV111*I111),2)*BA111),2) -> 0 | T111: =ROUND(CU111*I111,2) -> 0 | U111: =CV111*I111 -> 0 | V111: =CW111*I111 -> 0 | W111: =ROUND(CX111*I111,2) -> 0 | X111: =ROUND(CY111,2) -> 0 | Y111: =ROUND(CZ111,2) -> 0 | AA111: 56511233 | AB111: =ROUND((AC111+AD111+AF111),6) -> 26670.04 | AC111: =ROUND((ES111),6) -> 26670.04 | AD111: =ROUND((((ET111)-(EU111))+AE111),6) -> 0 | AE111: =ROUND((EU111),6) -> 0 | AF111: =ROUND((EV111),6) -> 0 | AG111: =ROUND((AP111),6) -> 0 | AH111: =(EW111) -> 0 | AI111: =(EX111) -> 0 | AJ111: =(AS111) -> 0 | AK111: 26670.04 | AL111: 26670.04 | AM111: 0 | AN111: 0 | AO111: 0 | AP111: 0 | AQ111: 0 | AR111: 0 | AS111: 0 | AT111: 90 | AU111: 46 | AV111: 1 | AW111: 1 | AZ111: 1 | BA111: 1 | BB111: 1 | BC111: 1 | BH111: 3 | BI111: 2 | BM111: 68 | BN111: 0 | BP111: 0 | BQ111: 40 | BR111: 0 | BS111: 1 | BT111: 1 | BU111: 1 | BV111: 1 | BW111: 1 | BX111: 1 | BZ111: 90 | CA111: 46 | CE111: 30 | CF111: 0 | CG111: 0 | CM111: 0 | CO111: 0 | CP111: =(P111+Q111+S111) -> 24347.08 | CQ111: =ROUND((ROUND((AC111*AW111*1),2)*BC111),2) -> 26670.04 | CR111: =(ROUND((ROUND(((ET111)*AV111*1),2)*BB111),2)+ROUND((ROUND(((AE111-(EU111))*AV111*1),2)*BS111),2)) -> 0 | CS111: =ROUND((ROUND((AE111*AV111*1),2)*BS111),2) -> 0 | CT111: =ROUND((ROUND((AF111*AV111*1),2)*BA111),2) -> 0 | CU111: =AG111 -> 0 | CV111: =(AH111*AV111) -> 0 | CW111: =AI111 -> 0 | CX111: =AJ111 -> 0 | CY111: =(((S111+R111)*AT111)/100) -> 0 | CZ111: =(((S111+R111)*AU111)/100) -> 0 | DN111: 0 | DO111: 0 | DP111: 1 | DQ111: 1 | DU111: 1003 | DV111: км | DW111: км | DX111: 1000 | EE111: 58162630 | EF111: 40 | EG111: Монтаж оборудования | EH111: 0 | EJ111: 2 | EK111: 68 | EL111: ТСН-2001.4-10. Прокладка и монтаж сетей связи | EM111: ТСН-2001.4-10-1 | EQ111: 0 | ER111: 0 | ES111: 26670.04 | ET111: 0 | EU111: 0 | EV111: 0 | EW111: 0 | EX111: 0 | FQ111: 0 | FR111: 0 | FS111: 0 | FX111: 90 | FY111: 46 | GA111: [310 000 / 1,2 / 9,88] + 2% Заг.скл | GD111: 1 | GF111: -407592442 | GG111: 2 | GH111: 4 | GI111: -2 | GJ111: 0 | GK111: 0 | GL111: =ROUND(IF(AND(BH111=3,BI111=3,FS111<>0),P111,0),2) -> 0 | GM111: =ROUND(O111+X111+Y111,2)+GX111 -> 24347.08 | GN111: =IF(OR(BI111=0,BI111=1),GM111-GX111,0) -> 0 | GO111: =IF(BI111=2,GM111-GX111,0) -> 24347.08 | GP111: =IF(BI111=4,GM111-GX111,0) -> 0 | GR111: 0 | GS111: 2 | GT111: 0 | GV111: =ROUND((GT111),6) -> 0 | GW111: 1 | GX111: =ROUND(HC111*I111,2) -> 0 | HA111: 0 | HB111: 0 | HC111: =GV111*GW111 -> 0 | HE111: 0 | HF111: 2 | HS111: 0 | IK111: 0
A112: 18 | B112: 1 | E112: 9,7 | F112: КА 11 | G112: Кабель КИС-РВнг(А)-LSLTx 2х2х0,64 мм | H112: км | I112: =I98*J112 -> 0.9129 | J112: 0.27250746 | K112: 0.2725075 | O112: =ROUND(CP112,2) -> 240549.15 | P112: =ROUND((ROUND((AC112*AW112*I112),2)*BC112),2) -> 240549.15 | Q112: =(ROUND((ROUND(((ET112)*AV112*I112),2)*BB112),2)+ROUND((ROUND(((AE112-(EU112))*AV112*I112),2)*BS112),2)) -> 0 | R112: =ROUND((ROUND((AE112*AV112*I112),2)*BS112),2) -> 0 | S112: =ROUND((ROUND((AF112*AV112*I112),2)*BA112),2) -> 0 | T112: =ROUND(CU112*I112,2) -> 0 | U112: =CV112*I112 -> 0 | V112: =CW112*I112 -> 0 | W112: =ROUND(CX112*I112,2) -> 0 | X112: =ROUND(CY112,2) -> 0 | Y112: =ROUND(CZ112,2) -> 0 | AA112: 56511235 | AB112: =ROUND((AC112+AD112+AF112),6) -> 26670.04 | AC112: =ROUND((ES112),6) -> 26670.04 | AD112: =ROUND((((ET112)-(EU112))+AE112),6) -> 0 | AE112: =ROUND((EU112),6) -> 0 | AF112: =ROUND((EV112),6) -> 0 | AG112: =ROUND((AP112),6) -> 0 | AH112: =(EW112) -> 0 | AI112: =(EX112) -> 0 | AJ112: =(AS112) -> 0 | AK112: 26670.04 | AL112: 26670.04 | AM112: 0 | AN112: 0 | AO112: 0 | AP112: 0 | AQ112: 0 | AR112: 0 | AS112: 0 | AT112: 90 | AU112: 46 | AV112: 1 | AW112: 1 | AZ112: 1 | BA112: 1 | BB112: 1 | BC112: 9.88 | BH112: 3 | BI112: 2 | BM112: 68 | BN112: 0 | BP112: 0 | BQ112: 40 | BR112: 0 | BS112: 1 | BT112: 1 | BU112: 1 | BV112: 1 | BW112: 1 | BX112: 1 | BZ112: 90 | CA112: 46 | CE112: 30 | CF112: 0 | CG112: 0 | CM112: 0 | CO112: 0 | CP112: =(P112+Q112+S112) -> 240549.15 | CQ112: =ROUND((ROUND((AC112*AW112*1),2)*BC112),2) -> 263500 | CR112: =(ROUND((ROUND(((ET112)*AV112*1),2)*BB112),2)+ROUND((ROUND(((AE112-(EU112))*AV112*1),2)*BS112),2)) -> 0 | CS112: =ROUND((ROUND((AE112*AV112*1),2)*BS112),2) -> 0 | CT112: =ROUND((ROUND((AF112*AV112*1),2)*BA112),2) -> 0 | CU112: =AG112 -> 0 | CV112: =(AH112*AV112) -> 0 | CW112: =AI112 -> 0 | CX112: =AJ112 -> 0 | CY112: =(((S112+R112)*AT112)/100) -> 0 | CZ112: =(((S112+R112)*AU112)/100) -> 0 | DN112: 0 | DO112: 0 | DP112: 1 | DQ112: 1 | DU112: 1003 | DV112: км | DW112: км | DX112: 1000 | EE112: 58162630 | EF112: 40 | EG112: Монтаж оборудования | EH112: 0 | EJ112: 2 | EK112: 68 | EL112: ТСН-2001.4-10. Прокладка и монтаж сетей связи | EM112: ТСН-2001.4-10-1 | EQ112: 0 | ER112: 263500 | ES112: 26670.04 | ET112: 0 | EU112: 0 | EV112: 0 | EW112: 0 | EX112: 0 | EZ112: 5 | FC112: 1 | FD112: 18 | FF112: 310000 | FQ112: 0 | FR112: 0 | FS112: 0 | FX112: 90 | FY112: 46 | GA112: [310 000 / 1,2 / 9,88] + 2% Заг.скл | GD112: 1 | GF112: -407592442 | GG112: 2 | GH112: 3 | GI112: 5 | GJ112: 0 | GK112: 0 | GL112: =ROUND(IF(AND(BH112=3,BI112=3,FS112<>0),P112,0),2) -> 0 | GM112: =ROUND(O112+X112+Y112,2)+GX112 -> 240549.15 | GN112: =IF(OR(BI112=0,BI112=1),GM112-GX112,0) -> 0 | GO112: =IF(BI112=2,GM112-GX112,0) -> 240549.15 | GP112: =IF(BI112=4,GM112-GX112,0) -> 0 | GR112: 1 | GS112: 1 | GT112: 0 | GV112: =ROUND((GT112),6) -> 0 | GW112: 1 | GX112: =ROUND(HC112*I112,2) -> 0 | HA112: 0 | HB112: 0 | HC112: =GV112*GW112 -> 0 | HE112: 0 | HF112: 2 | HS112: 0 | IK112: 0
A113: 18 | B113: 1 | E113: 9,8 | F113: КА 12 | G113: Кабель КСПЭнг(А)-LSLTx 2х2х0,5 мм | H113: км | I113: =I97*J113 -> 0.0153 | J113: 0.0045671642 | K113: 0.0045672 | O113: =ROUND(CP113,2) -> 59.59 | P113: =ROUND((ROUND((AC113*AW113*I113),2)*BC113),2) -> 59.59 | Q113: =(ROUND((ROUND(((ET113)*AV113*I113),2)*BB113),2)+ROUND((ROUND(((AE113-(EU113))*AV113*I113),2)*BS113),2)) -> 0 | R113: =ROUND((ROUND((AE113*AV113*I113),2)*BS113),2) -> 0 | S113: =ROUND((ROUND((AF113*AV113*I113),2)*BA113),2) -> 0 | T113: =ROUND(CU113*I113,2) -> 0 | U113: =CV113*I113 -> 0 | V113: =CW113*I113 -> 0 | W113: =ROUND(CX113*I113,2) -> 0 | X113: =ROUND(CY113,2) -> 0 | Y113: =ROUND(CZ113,2) -> 0 | AA113: 56511233 | AB113: =ROUND((AC113+AD113+AF113),6) -> 3894.69 | AC113: =ROUND((ES113),6) -> 3894.69 | AD113: =ROUND((((ET113)-(EU113))+AE113),6) -> 0 | AE113: =ROUND((EU113),6) -> 0 | AF113: =ROUND((EV113),6) -> 0 | AG113: =ROUND((AP113),6) -> 0 | AH113: =(EW113) -> 0 | AI113: =(EX113) -> 0 | AJ113: =(AS113) -> 0 | AK113: 3894.69 | AL113: 3894.69 | AM113: 0 | AN113: 0 | AO113: 0 | AP113: 0 | AQ113: 0 | AR113: 0 | AS113: 0 | AT113: 90 | AU113: 46 | AV113: 1 | AW113: 1 | AZ113: 1 | BA113: 1 | BB113: 1 | BC113: 1 | BH113: 3 | BI113: 2 | BM113: 68 | BN113: 0 | BP113: 0 | BQ113: 40 | BR113: 0 | BS113: 1 | BT113: 1 | BU113: 1 | BV113: 1 | BW113: 1 | BX113: 1 | BZ113: 90 | CA113: 46 | CE113: 30 | CF113: 0 | CG113: 0 | CM113: 0 | CO113: 0 | CP113: =(P113+Q113+S113) -> 59.59 | CQ113: =ROUND((ROUND((AC113*AW113*1),2)*BC113),2) -> 3894.69 | CR113: =(ROUND((ROUND(((ET113)*AV113*1),2)*BB113),2)+ROUND((ROUND(((AE113-(EU113))*AV113*1),2)*BS113),2)) -> 0 | CS113: =ROUND((ROUND((AE113*AV113*1),2)*BS113),2) -> 0 | CT113: =ROUND((ROUND((AF113*AV113*1),2)*BA113),2) -> 0 | CU113: =AG113 -> 0 | CV113: =(AH113*AV113) -> 0 | CW113: =AI113 -> 0 | CX113: =AJ113 -> 0 | CY113: =(((S113+R113)*AT113)/100) -> 0 | CZ113: =(((S113+R113)*AU113)/100) -> 0 | DN113: 0 | DO113: 0 | DP113: 1 | DQ113: 1 | DU113: 1003 | DV113: км | DW113: км | DX113: 1000 | EE113: 58162630 | EF113: 40 | EG113: Монтаж оборудования | EH113: 0 | EJ113: 2 | EK113: 68 | EL113: ТСН-2001.4-10. Прокладка и монтаж сетей связи | EM113: ТСН-2001.4-10-1 | EQ113: 0 | ER113: 0 | ES113: 3894.69 | ET113: 0 | EU113: 0 | EV113: 0 | EW113: 0 | EX113: 0 | FQ113: 0 | FR113: 0 | FS113: 0 | FX113: 90 | FY113: 46 | GA113: [45 270 / 1,2 / 9,88] + 2% Заг.скл | GD113: 1 | GF113: -127249305 | GG113: 2 | GH113: 4 | GI113: -2 | GJ113: 0 | GK113: 0 | GL113: =ROUND(IF(AND(BH113=3,BI113=3,FS113<>0),P113,0),2) -> 0 | GM113: =ROUND(O113+X113+Y113,2)+GX113 -> 59.59 | GN113: =IF(OR(BI113=0,BI113=1),GM113-GX113,0) -> 0 | GO113: =IF(BI113=2,GM113-GX113,0) -> 59.59 | GP113: =IF(BI113=4,GM113-GX113,0) -> 0 | GR113: 0 | GS113: 2 | GT113: 0 | GV113: =ROUND((GT113),6) -> 0 | GW113: 1 | GX113: =ROUND(HC113*I113,2) -> 0 | HA113: 0 | HB113: 0 | HC113: =GV113*GW113 -> 0 | HE113: 0 | HF113: 2 | HS113: 0 | IK113: 0
A114: 18 | B114: 1 | E114: 9,8 | F114: КА 12 | G114: Кабель КСПЭнг(А)-LSLTx 2х2х0,5 мм | H114: км | I114: =I98*J114 -> 0.0153 | J114: 0.0045671642 | K114: 0.0045672 | O114: =ROUND(CP114,2) -> 588.75 | P114: =ROUND((ROUND((AC114*AW114*I114),2)*BC114),2) -> 588.75 | Q114: =(ROUND((ROUND(((ET114)*AV114*I114),2)*BB114),2)+ROUND((ROUND(((AE114-(EU114))*AV114*I114),2)*BS114),2)) -> 0 | R114: =ROUND((ROUND((AE114*AV114*I114),2)*BS114),2) -> 0 | S114: =ROUND((ROUND((AF114*AV114*I114),2)*BA114),2) -> 0 | T114: =ROUND(CU114*I114,2) -> 0 | U114: =CV114*I114 -> 0 | V114: =CW114*I114 -> 0 | W114: =ROUND(CX114*I114,2) -> 0 | X114: =ROUND(CY114,2) -> 0 | Y114: =ROUND(CZ114,2) -> 0 | AA114: 56511235 | AB114: =ROUND((AC114+AD114+AF114),6) -> 3894.69 | AC114: =ROUND((ES114),6) -> 3894.69 | AD114: =ROUND((((ET114)-(EU114))+AE114),6) -> 0 | AE114: =ROUND((EU114),6) -> 0 | AF114: =ROUND((EV114),6) -> 0 | AG114: =ROUND((AP114),6) -> 0 | AH114: =(EW114) -> 0 | AI114: =(EX114) -> 0 | AJ114: =(AS114) -> 0 | AK114: 3894.69 | AL114: 3894.69 | AM114: 0 | AN114: 0 | AO114: 0 | AP114: 0 | AQ114: 0 | AR114: 0 | AS114: 0 | AT114: 90 | AU114: 46 | AV114: 1 | AW114: 1 | AZ114: 1 | BA114: 1 | BB114: 1 | BC114: 9.88 | BH114: 3 | BI114: 2 | BM114: 68 | BN114: 0 | BP114: 0 | BQ114: 40 | BR114: 0 | BS114: 1 | BT114: 1 | BU114: 1 | BV114: 1 | BW114: 1 | BX114: 1 | BZ114: 90 | CA114: 46 | CE114: 30 | CF114: 0 | CG114: 0 | CM114: 0 | CO114: 0 | CP114: =(P114+Q114+S114) -> 588.75 | CQ114: =ROUND((ROUND((AC114*AW114*1),2)*BC114),2) -> 38479.54 | CR114: =(ROUND((ROUND(((ET114)*AV114*1),2)*BB114),2)+ROUND((ROUND(((AE114-(EU114))*AV114*1),2)*BS114),2)) -> 0 | CS114: =ROUND((ROUND((AE114*AV114*1),2)*BS114),2) -> 0 | CT114: =ROUND((ROUND((AF114*AV114*1),2)*BA114),2) -> 0 | CU114: =AG114 -> 0 | CV114: =(AH114*AV114) -> 0 | CW114: =AI114 -> 0 | CX114: =AJ114 -> 0 | CY114: =(((S114+R114)*AT114)/100) -> 0 | CZ114: =(((S114+R114)*AU114)/100) -> 0 | DN114: 0 | DO114: 0 | DP114: 1 | DQ114: 1 | DU114: 1003 | DV114: км | DW114: км | DX114: 1000 | EE114: 58162630 | EF114: 40 | EG114: Монтаж оборудования | EH114: 0 | EJ114: 2 | EK114: 68 | EL114: ТСН-2001.4-10. Прокладка и монтаж сетей связи | EM114: ТСН-2001.4-10-1 | EQ114: 0 | ER114: 38479.5 | ES114: 3894.69 | ET114: 0 | EU114: 0 | EV114: 0 | EW114: 0 | EX114: 0 | EZ114: 5 | FC114: 1 | FD114: 18 | FF114: 45270 | FQ114: 0 | FR114: 0 | FS114: 0 | FX114: 90 | FY114: 46 | GA114: [45 270 / 1,2 / 9,88] + 2% Заг.скл | GD114: 1 | GF114: -127249305 | GG114: 2 | GH114: 3 | GI114: 5 | GJ114: 0 | GK114: 0 | GL114: =ROUND(IF(AND(BH114=3,BI114=3,FS114<>0),P114,0),2) -> 0 | GM114: =ROUND(O114+X114+Y114,2)+GX114 -> 588.75 | GN114: =IF(OR(BI114=0,BI114=1),GM114-GX114,0) -> 0 | GO114: =IF(BI114=2,GM114-GX114,0) -> 588.75 | GP114: =IF(BI114=4,GM114-GX114,0) -> 0 | GR114: 1 | GS114: 1 | GT114: 0 | GV114: =ROUND((GT114),6) -> 0 | GW114: 1 | GX114: =ROUND(HC114*I114,2) -> 0 | HA114: 0 | HB114: 0 | HC114: =GV114*GW114 -> 0 | HE114: 0 | HF114: 2 | HS114: 0 | IK114: 0
A115: 17 | B115: 1 | D115: =ROW(EtalonRes!A128) -> 128 | F115: 4.8-175-1 | G115: Затягивание провода в проложенные трубы и металлические рукава, первого одножильного или многожильного в общей оплетке, суммарное сечение до 2,5 мм2 | H115: 100 м | I115: =ROUND(35/100,9) -> 0.35 | J115: 0 | K115: =ROUND(35/100,9) -> 0.35 | O115: =ROUND(CP115,2) -> 43.67 | P115: =ROUND((ROUND((AC115*AW115*I115),2)*BC115),2) -> 20.35 | Q115: =(ROUND((ROUND((((ET115*1.1))*AV115*I115),2)*BB115),2)+ROUND((ROUND(((AE115-((EU115*1.1)))*AV115*I115),2)*BS115),2)) -> 1.06 | R115: =ROUND((ROUND((AE115*AV115*I115),2)*BS115),2) -> 0.12 | S115: =ROUND((ROUND((AF115*AV115*I115),2)*BA115),2) -> 22.26 | T115: =ROUND(CU115*I115,2) -> 0 | U115: =CV115*I115 -> 1.8098966 | V115: =CW115*I115 -> 0 | W115: =ROUND(CX115*I115,2) -> 0 | X115: =ROUND(CY115,2) -> 21.71 | Y115: =ROUND(CZ115,2) -> 11.41 | AA115: -1 | AB115: =ROUND((AC115+AD115+AF115),6) -> 121.785 | AC115: =ROUND((ES115),6) -> 58.15 | AD115: =ROUND(((((ET115*1.1))-((EU115*1.1)))+AE115),6) -> 2.882 | AE115: =ROUND(((EU115*1.1)),6) -> 0.33 | AF115: =ROUND(((EV115*1.1)),6) -> 60.753 | AG115: =ROUND((AP115),6) -> 0 | AH115: =((EW115*1.1)) -> 4.939 | AI115: =((EX115*1.1)) -> 0 | AJ115: =(AS115) -> 0 | AK115: 116 | AL115: 58.15 | AM115: 2.62 | AN115: 0.3 | AO115: 55.23 | AP115: 0 | AQ115: 4.49 | AR115: 0 | AS115: 0 | AT115: 97 | AU115: 51 | AV115: 1.047 | AW115: 1 | AZ115: 1 | BA115: 1 | BB115: 1 | BC115: 1 | BH115: 0 | BI115: 2 | BJ115: ТСН-2001.4 Доп. 71, Сб. 8, т. 175, поз. 1 | BM115: 67 | BN115: 0 | BO115: 4.8-175-1 | BP115: 1 | BQ115: 40 | BR115: 0 | BS115: 1 | BT115: 1 | BU115: 1 | BV115: 1 | BW115: 1 | BX115: 1 | BZ115: 97 | CA115: 51 | CE115: 30 | CF115: 0 | CG115: 0 | CM115: 0 | CO115: 0 | CP115: =(P115+Q115+S115) -> 43.67 | CQ115: =ROUND((ROUND((AC115*AW115*1),2)*BC115),2) -> 58.15 | CR115: =(ROUND((ROUND((((ET115*1.1))*AV115*1),2)*BB115),2)+ROUND((ROUND(((AE115-((EU115*1.1)))*AV115*1),2)*BS115),2)) -> 3.02 | CS115: =ROUND((ROUND((AE115*AV115*1),2)*BS115),2) -> 0.35 | CT115: =ROUND((ROUND((AF115*AV115*1),2)*BA115),2) -> 63.61 | CU115: =AG115 -> 0 | CV115: =(AH115*AV115) -> 5.171133 | CW115: =AI115 -> 0 | CX115: =AJ115 -> 0 | CY115: =(((S115+R115)*AT115)/100) -> 21.7086 | CZ115: =(((S115+R115)*AU115)/100) -> 11.4138 | DE115: *1,1 | DF115: *1,1 | DG115: *1,1 | DI115: *1,1 | DJ115: *1,1 | DN115: 0 | DO115: 0 | DP115: 1 | DQ115: 1 | DU115: 1003 | DV115: 100 м | DW115: 100 м | DX115: 100 | EE115: 58162629 | EF115: 40 | EG115: Монтаж оборудования | EH115: 0 | EJ115: 2 | EK115: 67 | EL115: ТСН-2001.4-8. Электротехнические установки | EM115: ТСН-2001.4-8-1 | EO115: Поправка: Гл.12.Прил.8.п.8. 5_12.00.01.11.003 | EQ115: 1024 | ER115: 116 | ES115: 58.15 | ET115: 2.62 | EU115: 0.3 | EV115: 55.23 | EW115: 4.49 | EX115: 0 | EY115: 0 | FQ115: 0 | FR115: 0 | FS115: 0 | FX115: 97 | FY115: 51 | GD115: 1 | GF115: 770559996 | GG115: 2 | GH115: 1 | GI115: 2 | GJ115: 0 | GK115: 0 | GL115: =ROUND(IF(AND(BH115=3,BI115=3,FS115<>0),P115,0),2) -> 0 | GM115: =ROUND(O115+X115+Y115,2)+GX115 -> 76.79 | GN115: =IF(OR(BI115=0,BI115=1),GM115-GX115,0) -> 0 | GO115: =IF(BI115=2,GM115-GX115,0) -> 76.79 | GP115: =IF(BI115=4,GM115-GX115,0) -> 0 | GR115: 0 | GS115: 3 | GT115: 0 | GV115: =ROUND((GT115),6) -> 0 | GW115: 1 | GX115: =ROUND(HC115*I115,2) -> 0 | HA115: 0 | HB115: 0 | HC115: =GV115*GW115 -> 0 | HS115: 0 | IK115: 0
