Workbook

Sheet 02-01-15
A1: =Source!B1 -> Smeta.RU (495) 974-1589
J2: Форма № 4б
A3: Капитальный ремонт здания Государственного бюджетного общеобразовательного учреждения города Москвы "Школа № 236" по адресу: г. Москва ул. Клязьминская, д. 7 к. 4. 1 этап. | AP3: Капитальный ремонт здания Государственного бюджетного общеобразовательного учреждения города Москвы "Школа № 236" по адресу: г. Москва ул. Клязьминская, д. 7 к. 4. 1 этап. 02-01-15 Система контроля и управления доступом
A4: (наименование стройки и/или объекта)
A6: =CONCATENATE( "ЛОКАЛЬНАЯ СМЕТА № ",IF(Source!F20<>"Новая локальная смета", Source!F20, "")) -> ЛОКАЛЬНАЯ СМЕТА № 02-01-15
A8: =IF(Source!G20<>"Новая локальная смета", Source!G20, "") -> Система контроля и управления доступом
A9: (наименование работ и затрат)
A11: =CONCATENATE( "Основание: чертежи № ", Source!J20) -> Основание: чертежи № 2024-00272-00-ИОС5.8
I13: В базисном уровне цен | J13: В текущем уровне цен
E14: Сметная стоимость | I14: =I15+I16+I17+I18 -> 572.71 | J14: =J15+J16+J17+J18 -> 5607.16 | K14: тыс.руб.
E15: Строительные работы | I15: =ROUND((Source!F270)/1000, 2) -> 0.13 | J15: =ROUND((Source!P270)/1000, 2) -> 1.03 | K15: тыс.руб.
E16: Работы по монтажу оборудования | I16: =ROUND((Source!F271)/1000, 2) -> 73.21 | J16: =ROUND((Source!P271)/1000, 2) -> 1780.46 | K16: тыс.руб.
E17: Оборудование | I17: =ROUND((Source!F262)/1000, 2) -> 499.37 | J17: =ROUND((Source!P262)/1000, 2) -> 3825.67 | K17: тыс.руб.
E18: Прочие работы и затраты | I18: =ROUND((Source!F272+Source!F273)/1000, 2) -> 0 | J18: =ROUND((Source!P272+Source!P273)/1000, 2) -> 0 | K18: тыс.руб.
E19: Средства на оплату труда | I19: =(Source!F268+ Source!F267)/1000 -> 10.39772 | J19: =((Source!P268 + Source!P267)/1000) -> 571.77061 | K19: тыс.руб.
E20: Затраты труда | I20: =Source!F275 -> 787.70867 | K20: чел.-ч.
E21: Кроме того:
E22: Возврат материалов | I22: =SUM(Y28:Y387)/1000 -> 0 | J22: =SUM(Z28:Z387)/1000 -> 0 | K22: тыс.руб.
A24: Составлен(а) по ТСН-2001 с учетом Дополнения №: 80
A25: № и период сборника коэффициентов (индексов) пересчета: Коэффициенты к ТСН-2001 МГЭ Дополнение 80, строительство №217/80 III квартал 2025 года и Коэффициенты к ТСН-2001.13-2 Дополнение 46 №62/46 III квартал 2025 года | AP25: № и период сборника коэффициентов (индексов) пересчета: Коэффициенты к ТСН-2001 МГЭ Дополнение 80, строительство №217/80 III квартал 2025 года и Коэффициенты к ТСН-2001.13-2 Дополнение 46 №62/46 III квартал 2025 года
A26: № п/п | B26: Шифр расценки и коды ресурсов | C26: Наименование работ и затрат | D26: Ед. изм. | E26: Кол-во единиц | F26: Цена на ед. изм., руб. | G26: Попра- вочные коэффи- циенты | H26: Коэффи- циенты зимних удорожа- ний | I26: Всего в ценах на январь 2000 года, руб. | J26: Коэффи- циенты (индек- сы) пере- счета, нормы НР и СП | K26: ВСЕГО затрат в текущем уровне цен, руб.
A27: 1 | B27: 2 | C27: 3 | D27: 4 | E27: 5 | F27: 6 | G27: 7 | H27: 8 | I27: 9 | J27: 10 | K27: 11
A29: =CONCATENATE("Раздел: ",IF(Source!G24<>"Новый раздел", Source!G24, "")) -> Раздел: Оборудование
A30: 1 | B30: 4.10-176-1 Поправка: Гл.12.Прил.8.п.8. 5_12.00.01.11.003 | C30: Монтаж блока контроля датчиков (контроллер) | D30: =Source!H28 -> 10 шт. | E30: =Source!I28 -> 0.2 | Q30: =Source!X28 -> 97.66 | R30: =Source!X29 -> 5370.27 | S30: =Source!Y28 -> 49.91 | T30: =Source!Y29 -> 2744.81 | U30: =ROUND((175/100)*ROUND(Source!R28, 2), 2) -> 0.05 | V30: =ROUND((0/100)*ROUND(Source!R29, 2), 2) -> 0 | AC30: 0
C31: ="Объем: "&Source!I28&"=2/"&"10" -> Объем: 0,2=2/10
C32: ЗП | F32: =Source!AO28 -> 470.94 | G32: =Source!DG28 -> *1,1 | H32: =Source!AV29 -> 1.047 | I32: =Source!S28 -> 108.48 | J32: =IF(Source!BA29<> 0, Source!BA29, 1) -> 54.99 | K32: =Source!S29 -> 5965.32
C33: ЭМ | F33: =Source!AM28 -> 1.1 | G33: =Source!DE28 -> *1,1 | H33: =Source!AV29 -> 1.047 | I33: =Source!Q28 -> 0.25 | J33: =IF(Source!BB29<> 0, Source!BB29, 1) -> 14.48 | K33: =Source!Q29 -> 3.62
C34: в т.ч. ЗПМ | F34: =Source!AN28 -> 0.13 | G34: =Source!DF28 -> *1,1 | H34: =Source!AV29 -> 1.047 | I34: =Source!R28 -> 0.03 | J34: =IF(Source!BS29<> 0, Source!BS29, 1) -> 54.99 | K34: =Source!R29 -> 1.65
C35: МР | F35: =Source!AL28 -> 1.29 | G35: =Source!DD28 -> *1 | H35: =Source!AW29 -> 1 | I35: =Source!P28 -> 0.26 | J35: =IF(Source!BC29<> 0, Source!BC29, 1) -> 7.25 | K35: =Source!P29 -> 1.89
C36: НР от ФОТ | D36: % | E36: =Source!BZ29 -> 90 | I36: =SUM(Q30:Q35) -> 97.66 | J36: =Source!AT29 -> 90 | K36: =SUM(R30:R35) -> 5370.27
C37: СП от ФОТ | D37: % | E37: =Source!CA29 -> 46 | I37: =SUM(S30:S36) -> 49.91 | J37: =Source!AU29 -> 46 | K37: =SUM(T30:T36) -> 2744.81
C38: ЗТР | D38: чел-ч | E38: =Source!AQ28 -> 29.96 | G38: =Source!DI28 -> *1,1 | H38: =Source!AV29 -> 1.047 | I38: =Source!U28 -> 6.9009864
C39: Всего по позиции: | H39: =I32+I33+I35+I36+I37+0 -> 256.56 | J39: =K32+K33+K35+K36+K37+0 -> 14085.91 | O39: =I32+I33+I35+I36+I37+0 -> 256.56 | P39: =K32+K33+K35+K36+K37+0 -> 14085.91
A41: 2 | B41: =Source!F30 -> КА 1 | C41: ОБОРУДОВАНИЕ:_x000D_ Сетевой контроллер доступа "STR20-IP" до 8 точек, встроенное ПО 7 314,21 = [64 500 / 1,2 / 7,66] + 3% Трансп + 1,2% Заг.скл | D41: =Source!H30 -> шт. | E41: =Source!I30 -> 20 | F41: =Source!AL30 -> 7314.21 | G41: =Source!DD30 | H41: =Source!AW31 -> 1 | I41: =Source!P30 -> 146284.2 | J41: =IF(Source!BC31<> 0, Source!BC31, 1) -> 7.66 | K41: =Source!P31 -> 1120537 | Q41: =Source!X30 -> 0 | R41: =Source!X31 -> 0 | S41: =Source!Y30 -> 0 | T41: =Source!Y31 -> 0 | U41: =ROUND((175/100)*ROUND(Source!R30, 2), 2) -> 0 | V41: =ROUND((0/100)*ROUND(Source!R31, 2), 2) -> 0 | AC41: 5
C42: Всего по позиции: | H42: =I41+0 -> 146284.2 | J42: =K41+0 -> 1120537 | O42: =I41+0 -> 146284.2 | P42: =K41+0 -> 1120537
A44: 3 | B44: 4.10-80-4 Поправка: Гл.12.Прил.8.п.8. 5_12.00.01.11.003 | C44: Аппараты приемные, приборы ПС приемно-контрольные, пусковые, прибор ПС на 4 луча | D44: =Source!H32 -> 1 ШТ. | E44: =Source!I32 -> 12 | Q44: =Source!X32 -> 557.12 | R44: =Source!X33 -> 30635.92 | S44: =Source!Y32 -> 284.75 | T44: =Source!Y33 -> 15658.36 | U44: =ROUND((175/100)*ROUND(Source!R32, 2), 2) -> 0.25 | V44: =ROUND((0/100)*ROUND(Source!R33, 2), 2) -> 0 | AC44: 0
C45: ЗП | F45: =Source!AO32 -> 44.78 | G45: =Source!DG32 -> *1,1 | H45: =Source!AV33 -> 1.047 | I45: =Source!S32 -> 618.88 | J45: =IF(Source!BA33<> 0, Source!BA33, 1) -> 54.99 | K45: =Source!S33 -> 34032.21
C46: ЭМ | F46: =Source!AM32 -> 0.12 | G46: =Source!DE32 -> *1,1 | H46: =Source!AV33 -> 1.047 | I46: =Source!Q32 -> 1.66 | J46: =IF(Source!BB33<> 0, Source!BB33, 1) -> 13.75 | K46: =Source!Q33 -> 22.83
C47: в т.ч. ЗПМ | F47: =Source!AN32 -> 0.01 | G47: =Source!DF32 -> *1,1 | H47: =Source!AV33 -> 1.047 | I47: =Source!R32 -> 0.14 | J47: =IF(Source!BS33<> 0, Source!BS33, 1) -> 54.99 | K47: =Source!R33 -> 7.7
C48: МР | F48: =Source!AL32 -> 6.44 | G48: =Source!DD32 -> *1 | H48: =Source!AW33 -> 1 | I48: =Source!P32 -> 77.28 | J48: =IF(Source!BC33<> 0, Source!BC33, 1) -> 9.89 | K48: =Source!P33 -> 764.3
C49: НР от ФОТ | D49: % | E49: =Source!BZ33 -> 90 | I49: =SUM(Q44:Q48) -> 557.12 | J49: =Source!AT33 -> 90 | K49: =SUM(R44:R48) -> 30635.92
C50: СП от ФОТ | D50: % | E50: =Source!CA33 -> 46 | I50: =SUM(S44:S49) -> 284.75 | J50: =Source!AU33 -> 46 | K50: =SUM(T44:T49) -> 15658.36
C51: ЗТР | D51: чел-ч | E51: =Source!AQ32 -> 3.3 | G51: =Source!DI32 -> *1,1 | H51: =Source!AV33 -> 1.047 | I51: =Source!U32 -> 45.60732
C52: Всего по позиции: | H52: =I45+I46+I48+I49+I50+0 -> 1539.69 | J52: =K45+K46+K48+K49+K50+0 -> 81113.62 | O52: =I45+I46+I48+I49+I50+0 -> 1539.69 | P52: =K45+K46+K48+K49+K50+0 -> 81113.62
A54: 4 | B54: =Source!F34 -> КА 2 | C54: ОБОРУДОВАНИЕ:_x000D_ Модуль доступа-контроллер доступа STR-1AP-M на 2 точки 1 803,04 = [15 900 / 1,2 / 7,66] + 3% Трансп + 1,2% Заг.скл | D54: =Source!H34 -> шт. | E54: =Source!I34 -> 12 | F54: =Source!AL34 -> 1803.04 | G54: =Source!DD34 | H54: =Source!AW35 -> 1 | I54: =Source!P34 -> 21636.48 | J54: =IF(Source!BC35<> 0, Source!BC35, 1) -> 7.66 | K54: =Source!P35 -> 165735.44 | Q54: =Source!X34 -> 0 | R54: =Source!X35 -> 0 | S54: =Source!Y34 -> 0 | T54: =Source!Y35 -> 0 | U54: =ROUND((175/100)*ROUND(Source!R34, 2), 2) -> 0 | V54: =ROUND((0/100)*ROUND(Source!R35, 2), 2) -> 0 | AC54: 5
C55: Всего по позиции: | H55: =I54+0 -> 21636.48 | J55: =K54+0 -> 165735.44 | O55: =I54+0 -> 21636.48 | P55: =K54+0 -> 165735.44
A57: 5 | B57: 4.10-80-4 Поправка: Гл.12.Прил.8.п.8. 5_12.00.01.11.003 | C57: Аппараты приемные, приборы ПС приемно-контрольные, пусковые, прибор ПС на 4 луча | D57: =Source!H36 -> 1 ШТ. | E57: =Source!I36 -> 15 | Q57: =Source!X36 -> 696.39 | R57: =Source!X37 -> 38294.65 | S57: =Source!Y36 -> 355.93 | T57: =Source!Y37 -> 19572.82 | U57: =ROUND((175/100)*ROUND(Source!R36, 2), 2) -> 0.3 | V57: =ROUND((0/100)*ROUND(Source!R37, 2), 2) -> 0 | AC57: 0
C58: ЗП | F58: =Source!AO36 -> 44.78 | G58: =Source!DG36 -> *1,1 | H58: =Source!AV37 -> 1.047 | I58: =Source!S36 -> 773.6 | J58: =IF(Source!BA37<> 0, Source!BA37, 1) -> 54.99 | K58: =Source!S37 -> 42540.26
C59: ЭМ | F59: =Source!AM36 -> 0.12 | G59: =Source!DE36 -> *1,1 | H59: =Source!AV37 -> 1.047 | I59: =Source!Q36 -> 2.07 | J59: =IF(Source!BB37<> 0, Source!BB37, 1) -> 13.75 | K59: =Source!Q37 -> 28.46
C60: в т.ч. ЗПМ | F60: =Source!AN36 -> 0.01 | G60: =Source!DF36 -> *1,1 | H60: =Source!AV37 -> 1.047 | I60: =Source!R36 -> 0.17 | J60: =IF(Source!BS37<> 0, Source!BS37, 1) -> 54.99 | K60: =Source!R37 -> 9.35
C61: МР | F61: =Source!AL36 -> 6.44 | G61: =Source!DD36 -> *1 | H61: =Source!AW37 -> 1 | I61: =Source!P36 -> 96.6 | J61: =IF(Source!BC37<> 0, Source!BC37, 1) -> 9.89 | K61: =Source!P37 -> 955.37
C62: НР от ФОТ | D62: % | E62: =Source!BZ37 -> 90 | I62: =SUM(Q57:Q61) -> 696.39 | J62: =Source!AT37 -> 90 | K62: =SUM(R57:R61) -> 38294.65
C63: СП от ФОТ | D63: % | E63: =Source!CA37 -> 46 | I63: =SUM(S57:S62) -> 355.93 | J63: =Source!AU37 -> 46 | K63: =SUM(T57:T62) -> 19572.82
C64: ЗТР | D64: чел-ч | E64: =Source!AQ36 -> 3.3 | G64: =Source!DI36 -> *1,1 | H64: =Source!AV37 -> 1.047 | I64: =Source!U36 -> 57.00915
C65: Всего по позиции: | H65: =I58+I59+I61+I62+I63+0 -> 1924.59 | J65: =K58+K59+K61+K62+K63+0 -> 101391.56 | O65: =I58+I59+I61+I62+I63+0 -> 1924.59 | P65: =K58+K59+K61+K62+K63+0 -> 101391.56
A67: 6 | B67: =Source!F38 -> КА 3 | C67: ОБОРУДОВАНИЕ:_x000D_ Модуль доступа-контроллер доступа STR-2AP-M на 4 точки 7 409,47 = [65 340 / 1,2 / 7,66] + 3% Трансп + 1,2% Заг.скл | D67: =Source!H38 -> шт. | E67: =Source!I38 -> 15 | F67: =Source!AL38 -> 7409.47 | G67: =Source!DD38 | H67: =Source!AW39 -> 1 | I67: =Source!P38 -> 111142.05 | J67: =IF(Source!BC39<> 0, Source!BC39, 1) -> 7.66 | K67: =Source!P39 -> 851348.1 | Q67: =Source!X38 -> 0 | R67: =Source!X39 -> 0 | S67: =Source!Y38 -> 0 | T67: =Source!Y39 -> 0 | U67: =ROUND((175/100)*ROUND(Source!R38, 2), 2) -> 0 | V67: =ROUND((0/100)*ROUND(Source!R39, 2), 2) -> 0 | AC67: 5
C68: Всего по позиции: | H68: =I67+0 -> 111142.05 | J68: =K67+0 -> 851348.1 | O68: =I67+0 -> 111142.05 | P68: =K67+0 -> 851348.1
A70: 7 | B70: 4.11-1-2 Поправка: Гл.12.Прил.8.п.8. 5_12.00.01.11.003 | C70: Монтаж конструкции для установки приборов и средств автоматизации массой до 2 кг | D70: =Source!H40 -> 1 ШТ. | E70: =Source!I40 -> 27 | Q70: =Source!X40 -> 176.88 | R70: =Source!X41 -> 9726.46 | S70: =Source!Y40 -> 90.4 | T70: =Source!Y41 -> 4971.3 | U70: =ROUND((175/100)*ROUND(Source!R40, 2), 2) -> 20.14 | V70: =ROUND((0/100)*ROUND(Source!R41, 2), 2) -> 0 | AC70: 0
C71: ЗП | F71: =Source!AO40 -> 5.95 | G71: =Source!DG40 -> *1,1 | H71: =Source!AV41 -> 1.047 | I71: =Source!S40 -> 185.02 | J71: =IF(Source!BA41<> 0, Source!BA41, 1) -> 54.99 | K71: =Source!S41 -> 10174.25
C72: ЭМ | F72: =Source!AM40 -> 1.76 | G72: =Source!DE40 -> *1,1 | H72: =Source!AV41 -> 1.047 | I72: =Source!Q40 -> 54.73 | J72: =IF(Source!BB41<> 0, Source!BB41, 1) -> 20.59 | K72: =Source!Q41 -> 1126.89
C73: в т.ч. ЗПМ | F73: =Source!AN40 -> 0.37 | G73: =Source!DF40 -> *1,1 | H73: =Source!AV41 -> 1.047 | I73: =Source!R40 -> 11.51 | J73: =IF(Source!BS41<> 0, Source!BS41, 1) -> 54.99 | K73: =Source!R41 -> 632.93
C74: МР | F74: =Source!AL40 -> 35.58 | G74: =Source!DD40 -> *1 | H74: =Source!AW41 -> 1 | I74: =Source!P40 -> 960.66 | J74: =IF(Source!BC41<> 0, Source!BC41, 1) -> 10.76 | K74: =Source!P41 -> 10336.7
C75: НР от ФОТ | D75: % | E75: =Source!BZ41 -> 90 | I75: =SUM(Q70:Q74) -> 176.88 | J75: =Source!AT41 -> 90 | K75: =SUM(R70:R74) -> 9726.46
C76: СП от ФОТ | D76: % | E76: =Source!CA41 -> 46 | I76: =SUM(S70:S75) -> 90.4 | J76: =Source!AU41 -> 46 | K76: =SUM(T70:T75) -> 4971.3
C77: ЗТР | D77: чел-ч | E77: =Source!AQ40 -> 0.52 | G77: =Source!DI40 -> *1,1 | H77: =Source!AV41 -> 1.047 | I77: =Source!U40 -> 16.169868
C78: Всего по позиции: | H78: =I71+I72+I74+I75+I76+0 -> 1467.69 | J78: =K71+K72+K74+K75+K76+0 -> 36335.6 | O78: =I71+I72+I74+I75+I76+0 -> 1467.69 | P78: =K71+K72+K74+K75+K76+0 -> 36335.6
A80: 8 | B80: =Source!F42 -> КА 4 | C80: ОБОРУДОВАНИЕ:_x000D_ Электромагнитный замок с монтажным комплектом "AL-400 Premium " 1 608,44 = [14 184 / 1,2 / 7,66] + 3% Трансп + 1,2% Заг.скл | D80: =Source!H42 -> шт. | E80: =Source!I42 -> 27 | F80: =Source!AL42 -> 1608.44 | G80: =Source!DD42 | H80: =Source!AW43 -> 1 | I80: =Source!P42 -> 43427.88 | J80: =IF(Source!BC43<> 0, Source!BC43, 1) -> 7.66 | K80: =Source!P43 -> 332657.56 | Q80: =Source!X42 -> 0 | R80: =Source!X43 -> 0 | S80: =Source!Y42 -> 0 | T80: =Source!Y43 -> 0 | U80: =ROUND((175/100)*ROUND(Source!R42, 2), 2) -> 0 | V80: =ROUND((0/100)*ROUND(Source!R43, 2), 2) -> 0 | AC80: 5
C81: Всего по позиции: | H81: =I80+0 -> 43427.88 | J81: =K80+0 -> 332657.56 | O81: =I80+0 -> 43427.88 | P81: =K80+0 -> 332657.56
A83: 9 | B83: 4.10-81-4 Поправка: Гл.12.Прил.8.п.8. 5_12.00.01.11.003 | C83: Извещатели ОС автоматические, контактный, магнито-контактный на открывание окон, дверей | D83: =Source!H44 -> 1 ШТ. | E83: =Source!I44 -> 42 | Q83: =Source!X44 -> 461.47 | R83: =Source!X45 -> 25376.01 | S83: =Source!Y44 -> 235.86 | T83: =Source!Y45 -> 12969.96 | U83: =ROUND((175/100)*ROUND(Source!R44, 2), 2) -> 0 | V83: =ROUND((0/100)*ROUND(Source!R45, 2), 2) -> 0 | AC83: 0
C84: ="Объем: "&Source!I44&"=38+"&"4" -> Объем: 42=38+4
C85: ЗП | F85: =Source!AO44 -> 10.6 | G85: =Source!DG44 -> *1,1 | H85: =Source!AV45 -> 1.047 | I85: =Source!S44 -> 512.74 | J85: =IF(Source!BA45<> 0, Source!BA45, 1) -> 54.99 | K85: =Source!S45 -> 28195.57
C86: МР | F86: =Source!AL44 -> 1.05 | G86: =Source!DD44 -> *1 | H86: =Source!AW45 -> 1 | I86: =Source!P44 -> 44.1 | J86: =IF(Source!BC45<> 0, Source!BC45, 1) -> 9.89 | K86: =Source!P45 -> 436.15
C87: НР от ФОТ | D87: % | E87: =Source!BZ45 -> 90 | I87: =SUM(Q83:Q86) -> 461.47 | J87: =Source!AT45 -> 90 | K87: =SUM(R83:R86) -> 25376.01
C88: СП от ФОТ | D88: % | E88: =Source!CA45 -> 46 | I88: =SUM(S83:S87) -> 235.86 | J88: =Source!AU45 -> 46 | K88: =SUM(T83:T87) -> 12969.96
C89: ЗТР | D89: чел-ч | E89: =Source!AQ44 -> 0.84 | G89: =Source!DI44 -> *1,1 | H89: =Source!AV45 -> 1.047 | I89: =Source!U44 -> 40.631976
C90: Всего по позиции: | H90: =I85+I86+I87+I88+0 -> 1254.17 | J90: =K85+K86+K87+K88+0 -> 66977.69 | O90: =I85+I86+I87+I88+0 -> 1254.17 | P90: =K85+K86+K87+K88+0 -> 66977.69
A92: 10 | B92: =Source!F46 -> КА 5 | C92: ОБОРУДОВАНИЕ:_x000D_ Извещатель охр. магнито-контактный для металлических дверей ИО 102-26 исп. Аякс 47,18 = [416 / 1,2 / 7,66] + 3% Трансп + 1,2% Заг.скл | D92: =Source!H46 -> шт. | E92: =Source!I46 -> 38 | F92: =Source!AL46 -> 47.18 | G92: =Source!DD46 | H92: =Source!AW47 -> 1 | I92: =Source!P46 -> 1792.84 | J92: =IF(Source!BC47<> 0, Source!BC47, 1) -> 7.66 | K92: =Source!P47 -> 13733.15 | Q92: =Source!X46 -> 0 | R92: =Source!X47 -> 0 | S92: =Source!Y46 -> 0 | T92: =Source!Y47 -> 0 | U92: =ROUND((175/100)*ROUND(Source!R46, 2), 2) -> 0 | V92: =ROUND((0/100)*ROUND(Source!R47, 2), 2) -> 0 | AC92: 5
C93: Всего по позиции: | H93: =I92+0 -> 1792.84 | J93: =K92+0 -> 13733.15 | O93: =I92+0 -> 1792.84 | P93: =K92+0 -> 13733.15
A95: 11 | B95: =Source!F48 -> КА 6 | C95: ОБОРУДОВАНИЕ:_x000D_ Извещатель охр. магнито-контактный для неметалл. поверхностей ИО 102-2 СМК 12,79 = [112,8 / 1,2 / 7,66] + 3% Трансп + 1,2% Заг.скл | D95: =Source!H48 -> шт. | E95: =Source!I48 -> 4 | F95: =Source!AL48 -> 12.79 | G95: =Source!DD48 | H95: =Source!AW49 -> 1 | I95: =Source!P48 -> 51.16 | J95: =IF(Source!BC49<> 0, Source!BC49, 1) -> 7.66 | K95: =Source!P49 -> 391.89 | Q95: =Source!X48 -> 0 | R95: =Source!X49 -> 0 | S95: =Source!Y48 -> 0 | T95: =Source!Y49 -> 0 | U95: =ROUND((175/100)*ROUND(Source!R48, 2), 2) -> 0 | V95: =ROUND((0/100)*ROUND(Source!R49, 2), 2) -> 0 | AC95: 5
C96: Всего по позиции: | H96: =I95+0 -> 51.16 | J96: =K95+0 -> 391.89 | O96: =I95+0 -> 51.16 | P96: =K95+0 -> 391.89
A98: 12 | B98: 4.10-177-1 Поправка: Гл.12.Прил.8.п.8. 5_12.00.01.11.003 | C98: Монтаж устройства связи с согласующим устройством (вызывная панель) | D98: =Source!H50 -> 10 шт. | E98: =Source!I50 -> 4.2 | Q98: =Source!X50 -> 993.46 | R98: =Source!X51 -> 54630.14 | S98: =Source!Y50 -> 507.77 | T98: =Source!Y51 -> 27922.07 | U98: =ROUND((175/100)*ROUND(Source!R50, 2), 2) -> 6.44 | V98: =ROUND((0/100)*ROUND(Source!R51, 2), 2) -> 0 | AC98: 0
C99: ="Объем: "&Source!I50&"=42/"&"10" -> Объем: 4,2=42/10
C100: ЗП | F100: =Source!AO50 -> 227.44 | G100: =Source!DG50 -> *1,1 | H100: =Source!AV51 -> 1.047 | I100: =Source!S50 -> 1100.16 | J100: =IF(Source!BA51<> 0, Source!BA51, 1) -> 54.99 | K100: =Source!S51 -> 60497.8
C101: ЭМ | F101: =Source!AM50 -> 6.07 | G101: =Source!DE50 -> *1,1 | H101: =Source!AV51 -> 1.047 | I101: =Source!Q50 -> 29.36 | J101: =IF(Source!BB51<> 0, Source!BB51, 1) -> 14.94 | K101: =Source!Q51 -> 438.64
C102: в т.ч. ЗПМ | F102: =Source!AN50 -> 0.76 | G102: =Source!DF50 -> *1,1 | H102: =Source!AV51 -> 1.047 | I102: =Source!R50 -> 3.68 | J102: =IF(Source!BS51<> 0, Source!BS51, 1) -> 54.99 | K102: =Source!R51 -> 202.36
C103: МР | F103: =Source!AL50 -> 2.44 | G103: =Source!DD50 -> *1 | H103: =Source!AW51 -> 1 | I103: =Source!P50 -> 10.25 | J103: =IF(Source!BC51<> 0, Source!BC51, 1) -> 7.23 | K103: =Source!P51 -> 74.11
C104: НР от ФОТ | D104: % | E104: =Source!BZ51 -> 90 | I104: =SUM(Q98:Q103) -> 993.46 | J104: =Source!AT51 -> 90 | K104: =SUM(R98:R103) -> 54630.14
C105: СП от ФОТ | D105: % | E105: =Source!CA51 -> 46 | I105: =SUM(S98:S104) -> 507.77 | J105: =Source!AU51 -> 46 | K105: =SUM(T98:T104) -> 27922.07
C106: ЗТР | D106: чел-ч | E106: =Source!AQ50 -> 14.64 | G106: =Source!DI50 -> *1,1 | H106: =Source!AV51 -> 1.047 | I106: =Source!U50 -> 70.81573
C107: Всего по позиции: | H107: =I100+I101+I103+I104+I105+0 -> 2641 | J107: =K100+K101+K103+K104+K105+0 -> 143562.76 | O107: =I100+I101+I103+I104+I105+0 -> 2641 | P107: =K100+K101+K103+K104+K105+0 -> 143562.76
A109: 13 | B109: =Source!F52 -> КА 7 | C109: ОБОРУДОВАНИЕ:_x000D_ Считыватель для установки на улице и в помещение,-40....+55гр интерфейс Wiegand 26-58, формат карт Mifare, EM-Marin,HID Prox RusGuard R-15 multi 1 803,04 = [15 900 / 1,2 / 7,66] + 3% Трансп + 1,2% Заг.скл | D109: =Source!H52 -> шт. | E109: =Source!I52 -> 42 | F109: =Source!AL52 -> 1803.04 | G109: =Source!DD52 | H109: =Source!AW53 -> 1 | I109: =Source!P52 -> 75727.68 | J109: =IF(Source!BC53<> 0, Source!BC53, 1) -> 7.66 | K109: =Source!P53 -> 580074.03 | Q109: =Source!X52 -> 0 | R109: =Source!X53 -> 0 | S109: =Source!Y52 -> 0 | T109: =Source!Y53 -> 0 | U109: =ROUND((175/100)*ROUND(Source!R52, 2), 2) -> 0 | V109: =ROUND((0/100)*ROUND(Source!R53, 2), 2) -> 0 | AC109: 5
C110: Всего по позиции: | H110: =I109+0 -> 75727.68 | J110: =K109+0 -> 580074.03 | O110: =I109+0 -> 75727.68 | P110: =K109+0 -> 580074.03
A112: 14 | B112: 4.10-76-10 Поправка: Гл.12.Прил.8.п.8. 5_12.00.01.11.003 | C112: Монтаж ключа или кнопки на панели | D112: =Source!H54 -> 1 ШТ. | E112: =Source!I54 -> 12 | Q112: =Source!X54 -> 156.1 | R112: =Source!X55 -> 8584.16 | S112: =Source!Y54 -> 87.09 | T112: =Source!Y55 -> 4789.06 | U112: =ROUND((175/100)*ROUND(Source!R54, 2), 2) -> 0 | V112: =ROUND((0/100)*ROUND(Source!R55, 2), 2) -> 0 | AC112: 0
C113: ЗП | F113: =Source!AO54 -> 11.89 | G113: =Source!DG54 -> *1,1 | H113: =Source!AV55 -> 1.047 | I113: =Source!S54 -> 164.32 | J113: =IF(Source!BA55<> 0, Source!BA55, 1) -> 54.99 | K113: =Source!S55 -> 9035.96
C114: МР | F114: =Source!AL54 -> 1.67 | G114: =Source!DD54 -> *1 | H114: =Source!AW55 -> 1 | I114: =Source!P54 -> 20.04 | J114: =IF(Source!BC55<> 0, Source!BC55, 1) -> 18.61 | K114: =Source!P55 -> 372.94
A115: 14,1 | B115: =Source!F56 -> КА 8 | C115: Кнопка экстренного выхода ST-FR115 98,94 = [1 150 / 1,2 / 9,88] + 2% Заг.скл | D115: =Source!H56 -> шт. | E115: =Source!I56 -> 12 | F115: =Source!AK56 -> 98.94 | H115: =Source!AW57 -> 1 | I115: =Source!O56 -> 1187.28 | J115: =IF(Source!BC57<> 0, Source!BC57, 1) -> 9.88 | K115: =Source!O57 -> 11730.33 | Q115: =Source!X56 -> 0 | R115: =Source!X57 -> 0 | S115: =Source!Y56 -> 0 | T115: =Source!Y57 -> 0 | U115: =ROUND((175/100)*ROUND(Source!R56, 2), 2) -> 0 | V115: =ROUND((0/100)*ROUND(Source!R57, 2), 2) -> 0 | AC115: 3
C116: НР от ФОТ | D116: % | E116: =Source!BZ55 -> 95 | I116: =SUM(Q112:Q115) -> 156.1 | J116: =Source!AT55 -> 95 | K116: =SUM(R112:R115) -> 8584.16
C117: СП от ФОТ | D117: % | E117: =Source!CA55 -> 53 | I117: =SUM(S112:S116) -> 87.09 | J117: =Source!AU55 -> 53 | K117: =SUM(T112:T116) -> 4789.06
C118: ЗТР | D118: чел-ч | E118: =Source!AQ54 -> 1 | G118: =Source!DI54 -> *1,1 | H118: =Source!AV55 -> 1.047 | I118: =Source!U54 -> 13.8204
C119: Всего по позиции: | H119: =I113+I114+I116+I117+SUM(I115:I115) -> 1614.83 | J119: =K113+K114+K116+K117+SUM(K115:K115) -> 34512.45 | O119: =I113+I114+I116+I117+SUM(I115:I115) -> 1614.83 | P119: =K113+K114+K116+K117+SUM(K115:K115) -> 34512.45
...

Sheet Ведомость объемов работ
A1: =Source!B1 -> Smeta.RU (495) 974-1589
E3: "УТВЕРЖДАЮ"
D5: ___________________________
D7: ___________________________
D9: " ___ " ___________ 20 ___ г.
B12: =CONCATENATE("Ведомость объемов работ ", IF(Source!AN15<>"", Source!AN15," ")) -> Ведомость объемов работ
B13: =CONCATENATE(Source!F12, " ", Source!G12) -> Новый объект (ТСН-2001 (Мосгосэкспертиза)) 02-01-15 Система контроля и управления доступом | AE13: =CONCATENATE(Source!F12, " ", Source!G12) -> Новый объект (ТСН-2001 (Мосгосэкспертиза)) 02-01-15 Система контроля и управления доступом
A16: № п/п | B16: № в ЛСР | C16: Наименование работ и затрат | D16: Единица измерения | E16: Количество | F16: Ссылка на чертежи, спецификации | G16: Формула расчета, расчет объемов работ и расхода материалов | H16: Примечание
A17: 1 | B17: 2 | C17: 3 | D17: 4 | E17: 5 | F17: 6 | G17: 7 | H17: 8
A18: =CONCATENATE("Локальная смета: ", Source!G20) -> Локальная смета: Система контроля и управления доступом
A19: =CONCATENATE("Раздел: ", Source!G24) -> Раздел: Оборудование
A20: 1 | B20: =Source!E28 -> 1 | C20: =Source!G28 -> Монтаж блока контроля датчиков (контроллер) | D20: 10 шт. | E20: =Source!I28 -> 0.2 | F20: =Source!U24 | G20: ="=2/"&"10" -> =2/10
A21: 2 | B21: =Source!E30 -> 2 | C21: =Source!G30 -> Сетевой контроллер доступа "STR20-IP" до 8 точек, встроенное ПО | D21: шт. | E21: =Source!I30 -> 20 | F21: =Source!U24 | G21: =Source!I30 -> 20
A22: 3 | B22: =Source!E32 -> 3 | C22: =Source!G32 -> Аппараты приемные, приборы ПС приемно-контрольные, пусковые, прибор ПС на 4 луча | D22: 1 ШТ. | E22: =Source!I32 -> 12 | F22: =Source!U24 | G22: =Source!I32 -> 12
A23: 4 | B23: =Source!E34 -> 4 | C23: =Source!G34 -> Модуль доступа-контроллер доступа STR-1AP-M на 2 точки | D23: шт. | E23: =Source!I34 -> 12 | F23: =Source!U24 | G23: =Source!I34 -> 12
A24: 5 | B24: =Source!E36 -> 5 | C24: =Source!G36 -> Аппараты приемные, приборы ПС приемно-контрольные, пусковые, прибор ПС на 4 луча | D24: 1 ШТ. | E24: =Source!I36 -> 15 | F24: =Source!U24 | G24: =Source!I36 -> 15
A25: 6 | B25: =Source!E38 -> 6 | C25: =Source!G38 -> Модуль доступа-контроллер доступа STR-2AP-M на 4 точки | D25: шт. | E25: =Source!I38 -> 15 | F25: =Source!U24 | G25: =Source!I38 -> 15
A26: 7 | B26: =Source!E40 -> 7 | C26: =Source!G40 -> Монтаж конструкции для установки приборов и средств автоматизации массой до 2 кг | D26: 1 ШТ. | E26: =Source!I40 -> 27 | F26: =Source!U24 | G26: =Source!I40 -> 27
A27: 8 | B27: =Source!E42 -> 8 | C27: =Source!G42 -> Электромагнитный замок с монтажным комплектом "AL-400 Premium " | D27: шт. | E27: =Source!I42 -> 27 | F27: =Source!U24 | G27: =Source!I42 -> 27
A28: 9 | B28: =Source!E44 -> 9 | C28: =Source!G44 -> Извещатели ОС автоматические, контактный, магнито-контактный на открывание окон, дверей | D28: 1 ШТ. | E28: =Source!I44 -> 42 | F28: =Source!U24 | G28: ="=38+"&"4" -> =38+4
A29: 10 | B29: =Source!E46 -> 10 | C29: =Source!G46 -> Извещатель охр. магнито-контактный для металлических дверей ИО 102-26 исп. Аякс | D29: шт. | E29: =Source!I46 -> 38 | F29: =Source!U24 | G29: =Source!I46 -> 38
A30: 11 | B30: =Source!E48 -> 11 | C30: =Source!G48 -> Извещатель охр. магнито-контактный для неметалл. поверхностей ИО 102-2 СМК | D30: шт. | E30: =Source!I48 -> 4 | F30: =Source!U24 | G30: =Source!I48 -> 4
A31: 12 | B31: =Source!E50 -> 12 | C31: =Source!G50 -> Монтаж устройства связи с согласующим устройством (вызывная панель) | D31: 10 шт. | E31: =Source!I50 -> 4.2 | F31: =Source!U24 | G31: ="=42/"&"10" -> =42/10
A32: 13 | B32: =Source!E52 -> 13 | C32: =Source!G52 -> Считыватель для установки на улице и в помещение,-40....+55гр интерфейс Wiegand 26-58, формат карт Mifare, EM-Marin,HID Prox RusGuard R-15 multi | D32: шт. | E32: =Source!I52 -> 42 | F32: =Source!U24 | G32: =Source!I52 -> 42
A33: 14 | B33: =Source!E54 -> 14 | C33: =Source!G54 -> Монтаж ключа или кнопки на панели | D33: 1 ШТ. | E33: =Source!I54 -> 12 | F33: =Source!U24 | G33: =Source!I54 -> 12
A34: 14.1 | B34: =Source!E56 -> 14,1 | C34: =Source!G56 -> Кнопка экстренного выхода ST-FR115 | D34: шт. | E34: =Source!I56 -> 12 | F34: =Source!U24
A35: 15 | B35: =Source!E58 -> 15 | C35: =Source!G58 -> Монтаж детали на пультах и панелях - кнопка | D35: 1 ШТ. | E35: =Source!I58 -> 27 | F35: =Source!U24 | G35: =Source!I58 -> 27
A36: 16 | B36: =Source!E60 -> 16 | C36: =Source!G60 -> Кнопка разблокировки дверей "ИПР 513-10" "АВАРИЙНЫЙ ВЫХОД" SB 1 | D36: шт. | E36: =Source!I60 -> 27 | F36: =Source!U24 | G36: =Source!I60 -> 27
A37: 17 | B37: =Source!E62 -> 17 | C37: =Source!G62 -> Монтаж блока бесперебойного питания (ББП) в диспетчерской | D37: 1 ШТ. | E37: =Source!I62 -> 2 | F37: =Source!U24 | G37: =Source!I62 -> 2
A38: 18 | B38: =Source!E64 -> 18 | C38: =Source!G64 -> Резервный источник питания,12В ИВЭПР 12/3,5 2x7 -Р | D38: шт. | E38: =Source!I64 -> 2 | F38: =Source!U24 | G38: =Source!I64 -> 2
A39: 19 | B39: =Source!E66 -> 19 | C39: =Source!G66 -> Батарея аккумуляторная, емкость 7 А·ч, напряжение 12 В. | D39: шт. | E39: =Source!I66 -> 4 | F39: =Source!U24 | G39: =Source!I66 -> 4
A40: 20 | B40: =Source!E68 -> 20 | C40: =Source!G68 -> Установка съемных и выдвижных блоков (модулей, ячеек, ТЭЗ) массой до 5 кг | D40: 1 ШТ. | E40: =Source!I68 -> 7 | F40: =Source!U24 | G40: =Source!I68 -> 7
A41: 20.1 | B41: =Source!E70 -> 20,1 | C41: =Source!G70 -> Коммутационная панель категории 5е UTP19",1U,24xRj45,п-корды PLHD-24 Dual IDC-1U | D41: шт. | E41: =Source!I70 -> 49 | F41: =Source!U24
A42: 21 | B42: =Source!E72 -> 21 | C42: =Source!G72 -> Установка рамки со штифтами на винтах в нарезных отверстиях | D42: 1 рамка | E42: =Source!I72 -> 7 | F42: =Source!U24 | G42: =Source!I72 -> 7
A43: 21.1 | B43: =Source!E74 -> 21,1 | C43: =Source!G74 -> Горизонтальный органайзер, слотовый с крышкой, MX-CMC-1U-45-B | D43: шт. | E43: =Source!I74 -> 7 | F43: =Source!U24
A44: 22 | B44: =Source!E76 -> 22 | C44: =Source!G76 -> Установка аппарата настольного массой до 0,03 т | D44: 1 ШТ. | E44: =Source!I76 -> 1 | F44: =Source!U24 | G44: =Source!I76 -> 1
A45: 23 | B45: =Source!E78 -> 23 | C45: =Source!G78 -> Центральный прибор индикации и управления с ПО FireSec в составе: блок системный, монитор- размер 21.5 дюйм, пульт индикации и управления, блок АВР ЦПИУ, Рубеж-АРМ исп.1 | D45: шт. | E45: =Source!I78 -> 1 | F45: =Source!U24 | G45: =Source!I78 -> 1
A46: 24 | B46: =Source!E80 -> 24 | C46: =Source!G80 -> Монтаж блока бесперебойного питания (ББП) в диспетчерской | D46: 1 ШТ. | E46: =Source!I80 -> 1 | F46: =Source!U24 | G46: =Source!I80 -> 1
A47: 25 | B47: =Source!E82 -> 25 | C47: =Source!G82 -> Источник бесперебойного питания Rapan-USB 3000 | D47: шт. | E47: =Source!I82 -> 1 | F47: =Source!U24 | G47: =Source!I82 -> 1
A48: 26 | B48: =Source!E84 -> 26 | C48: =Source!G84 -> Монтаж коммутатора служебной связи | D48: 1 ШТ. | E48: =Source!I84 -> 7 | F48: =Source!U24 | G48: =Source!I84 -> 7
A49: 27 | B49: =Source!E86 -> 27 | C49: =Source!G86 -> Сетевой коммутатор RVI-1NSM16G-4H 16 портов RVI-1NSM 16G-4H | D49: шт. | E49: =Source!I86 -> 7 | F49: =Source!U24 | G49: =Source!I86 -> 7
A50: 28 | B50: =Source!E88 -> 28 | C50: =Source!G88 -> Карта Mifare стандартная ST-PC010MF | D50: шт. | E50: =Source!I88 -> 50 | F50: =Source!U24 | G50: =Source!I88 -> 50
A51: =CONCATENATE("Раздел: ", Source!G121) -> Раздел: Кабельные изделия и материалы
A52: 29 | B52: =Source!E125 -> 29 | C52: =Source!G125 -> Трубы гофрированные поливинилхлоридные наружным диаметром 20 мм открыто по стенам и потолкам с установкой соединительных коробок | D52: 100 м | E52: =Source!I125 -> 8.7 | F52: =Source!U121 | G52: ="=870/"&"100" -> =870/100
A53: 29.1 | B53: =Source!E127 -> 29,1 | C53: =Source!G127 -> Трубы электротехнические, гофрированные, из ПВХ, негорючие, с зондом, наружный диаметр 20 мм | D53: м | E53: =Source!I127 -> 887.4 | F53: =Source!U121
A54: 29.2 | B54: =Source!E129 -> 29,2 | C54: =Source!G129 -> Держатель пластиковый с защелкой для крепления труб, рукавов и гибких вводов диаметром 20 мм | D54: 100 шт. | E54: =Source!I129 -> 17.4 | F54: =Source!U121
A55: 30 | B55: =Source!E131 -> 30 | C55: =Source!G131 -> Трубы гофрированные поливинилхлоридные наружным диаметром 16 мм открыто по стенам и потолкам с установкой соединительных коробок | D55: 100 м | E55: =Source!I131 -> 4.7 | F55: =Source!U121 | G55: ="=470/"&"100" -> =470/100
A56: 30.1 | B56: =Source!E133 -> 30,1 | C56: =Source!G133 -> Трубы электротехнические, гофрированные, из ПВХ, негорючие, с зондом, наружный диаметр 16 мм | D56: м | E56: =Source!I133 -> 479.4 | F56: =Source!U121
A57: 30.2 | B57: =Source!E135 -> 30,2 | C57: =Source!G135 -> Держатель пластиковый с защелкой для крепления труб, рукавов и гибких вводов диаметром 16 мм | D57: 100 шт. | E57: =Source!I135 -> 9.4 | F57: =Source!U121
A58: 31 | B58: =Source!E137 -> 31 | C58: =Source!G137 -> Мастика тиоколовая, герметизирующая, нетвердеющая, типа АМ-05 | D58: кг | E58: =Source!I137 -> 1 | F58: =Source!U121 | G58: =Source!I137 -> 1
A59: 32 | B59: =Source!E139 -> 32 | C59: =Source!G139 -> Затягивание провода в проложенные трубы и металлические рукава, первого одножильного или многожильного в общей оплетке, суммарное сечение до 2,5 мм2 | D59: 100 м | E59: =Source!I139 -> 2.9 | F59: =Source!U121 | G59: ="=290/"&"100" -> =290/100
A60: 32.1 | B60: =Source!E141 -> 32,1 | C60: =Source!G141 -> Кабель КПСВВнг(А)-LSLT 1х2х0,75мм "Спецкабель" | D60: км | E60: =Source!I141 -> 0.2958 | F60: =Source!U121
A61: 33 | B61: =Source!E143 -> 33 | C61: =Source!G143 -> Затягивание провода в проложенные трубы и металлические рукава, первого одножильного или многожильного в общей оплетке, суммарное сечение до 2,5 мм2 | D61: 100 м | E61: =Source!I143 -> 0.8 | F61: =Source!U121 | G61: ="=80/"&"100" -> =80/100
A62: 33.1 | B62: =Source!E145 -> 33,1 | C62: =Source!G145 -> Кабель КПСВВнг(А)-LSLT 1х2х1,0мм "Спецкабель" | D62: км | E62: =Source!I145 -> 0.0816 | F62: =Source!U121
A63: 34 | B63: =Source!E147 -> 34 | C63: =Source!G147 -> Затягивание провода в проложенные трубы и металлические рукава, первого одножильного или многожильного в общей оплетке, суммарное сечение до 2,5 мм2 | D63: 100 м | E63: =Source!I147 -> 1 | F63: =Source!U121 | G63: ="=100/"&"100" -> =100/100
A64: 34.1 | B64: =Source!E149 -> 34,1 | C64: =Source!G149 -> Кабель ЛОУТОКС 20нг(А)-FRLSLTx -1х2х0.5 "Спецкабель" | D64: км | E64: =Source!I149 -> 0.102 | F64: =Source!U121
A65: 35 | B65: =Source!E151 -> 35 | C65: =Source!G151 -> Затягивание провода в проложенные трубы и металлические рукава, первого одножильного или многожильного в общей оплетке, суммарное сечение до 6 мм2 | D65: 100 м | E65: =Source!I151 -> 8.7 | F65: =Source!U121 | G65: ="=870/"&"100" -> =870/100
A66: 35.1 | B66: =Source!E153 -> 35,1 | C66: =Source!G153 -> Кабель U/UTPнг(А)-LSLTx -4х2х0.52 кат 5е | D66: км | E66: =Source!I153 -> 0.8874 | F66: =Source!U121
A67: 36 | B67: =Source!E155 -> 36 | C67: =Source!G155 -> Добавлять на затягивание провода в проложенные трубы и металлические рукава каждого последующего одножильного или многожильного в общей оплетке, суммарное сечение до 6 мм2 (к нормам и расценкам 4.8-175-1 и 4.8-175-2) | D67: 100 м | E67: =Source!I155 -> 0.3 | F67: =Source!U121 | G67: ="=30/"&"100" -> =30/100
A68: 36.1 | B68: =Source!E157 -> 36,1 | C68: =Source!G157 -> Кабель U/UTPнг(А)-LSLTx -4х2х0.52 кат 5е | D68: км | E68: =Source!I157 -> 0.0306 | F68: =Source!U121
A69: 37 | B69: =Source!E159 -> 37 | C69: =Source!G159 -> Добавлять на затягивание провода в проложенные трубы и металлические рукава каждого последующего одножильного или многожильного в общей оплетке, суммарное сечение до 6 мм2 (к нормам и расценкам 4.8-175-1 и 4.8-175-2) | D69: 100 м | E69: =Source!I159 -> 4.5 | F69: =Source!U121 | G69: ="=450/"&"100" -> =450/100
A70: 37.1 | B70: =Source!E161 -> 37,1 | C70: =Source!G161 -> Кабель ВВГнг(А)-LSLTx -1х2х1.5мм | D70: м | E70: =Source!I161 -> 459 | F70: =Source!U121
A71: =CONCATENATE("Раздел: ", Source!G194) -> Раздел: Видеодомофон
A72: 38 | B72: =Source!E198 -> 38 | C72: =Source!G198 -> Монтаж телефонного аппарата настенного системы ЦБ или АТС | D72: 1 ШТ. | E72: =Source!I198 -> 1 | F72: =Source!U194 | G72: =Source!I198 -> 1
A73: 39 | B73: =Source!E200 -> 39 | C73: =Source!G200 -> Монитор IP-видеодомофона 4.3" SIP протокол ,РоЕ, ОС Linux с поддержкой подключения IP-вызывных панелей и IP-камер, SM-400W | D73: шт. | E73: =Source!I200 -> 1 | F73: =Source!U194 | G73: =Source!I200 -> 1
A74: 40 | B74: =Source!E202 -> 40 | C74: =Source!G202 -> Монтаж устройства связи с согласующим устройством (вызывная панель) | D74: 10 шт. | E74: =Source!I202 -> 0.7 | F74: =Source!U194 | G74: ="=7/"&"10" -> =7/10
A75: 41 | B75: =Source!E204 -> 41 | C75: =Source!G204 -> Вызывная Full HD IP-панель для видеодомофонов с углом обзора 146° врезной установки, DS06AP | D75: шт. | E75: =Source!I204 -> 7 | F75: =Source!U194 | G75: =Source!I204 -> 7
A76: 42 | B76: =Source!E206 -> 42 | C76: =Source!G206 -> Трубы гофрированные поливинилхлоридные наружным диаметром 20 мм открыто по стенам и потолкам с установкой соединительных коробок | D76: 100 м | E76: =Source!I206 -> 4.4 | F76: =Source!U194 | G76: ="=440/"&"100" -> =440/100
A77: 42.1 | B77: =Source!E208 -> 42,1 | C77: =Source!G208 -> Трубы электротехнические, гофрированные, из ПВХ, негорючие, с зондом, наружный диаметр 20 мм | D77: м | E77: =Source!I208 -> 448.8 | F77: =Source!U194
A78: 42.2 | B78: =Source!E210 -> 42,2 | C78: =Source!G210 -> Держатель пластиковый с защелкой для крепления труб, рукавов и гибких вводов диаметром 20 мм | D78: 100 шт. | E78: =Source!I210 -> 8.8 | F78: =Source!U194
A79: 43 | B79: =Source!E212 -> 43 | C79: =Source!G212 -> Затягивание провода в проложенные трубы и металлические рукава, первого одножильного или многожильного в общей оплетке, суммарное сечение до 2,5 мм2 | D79: 100 м | E79: =Source!I212 -> 0.2 | F79: =Source!U194 | G79: ="=20/"&"100" -> =20/100
A80: 43.1 | B80: =Source!E214 -> 43,1 | C80: =Source!G214 -> Кабель ВВГнг(А)-LSLTx -1х2х1.5мм | D80: м | E80: =Source!I214 -> 20.4 | F80: =Source!U194
A81: 44 | B81: =Source!E216 -> 44 | C81: =Source!G216 -> Затягивание провода в проложенные трубы и металлические рукава, первого одножильного или многожильного в общей оплетке, суммарное сечение до 6 мм2 | D81: 100 м | E81: =Source!I216 -> 4.2 | F81: =Source!U194 | G81: ="=420/"&"100" -> =420/100
A82: 44.1 | B82: =Source!E218 -> 44,1 | C82: =Source!G218 -> Кабель "витая пара" негорючий с низким выделением газа, дыма КПСВВнг(А)-LSLTx -4х2х0.5мм | D82: м | E82: =Source!I218 -> 428.4 | F82: =Source!U194
A83: 45 | B83: =Source!E220 -> 45 | C83: =Source!G220 -> Шнур оптический соединительный (патч-корд), тип разъемов SC/UPC-SC/UPC, 9/125 мкм, одномодовый, дуплексный, длина 1 м. | D83: шт. | E83: =Source!I220 -> 9 | F83: =Source!U194 | G83: =Source!I220 -> 9
C86: Главный инженер проекта _________________ | D86: =IF(Source!X12<>"", Source!X12," ")
C88: Составил _________________ | D88: =IF(Source!AB12<>"", Source!AB12," ") -> Кузнецова Е.А.

Sheet Source
A1: 0 | B1: Smeta.RU (495) 974-1589 | D1: _PS_ | F1: 0 | G1: 0 | H1: 0 | I1: Smeta.RU | K1: 1 | L1: 74402 | M1: 10 | N1: 12 | O1: 0 | P1: 0 | Q1: 3
A4: 1 | B4: 1 | C4: -1 | G4: Капитальный ремонт здания Государственного бюджетного общеобразовательного учреждения города Москвы "Школа № 236" по адресу: г. Москва ул. Клязьминская, д. 7 к. 4. 1 этап | EC4: 0
A12: 1 | B12: 322 | C12: 0 | D12: =ROW(A283) -> 283 | E12: 0 | F12: Новый объект (ТСН-2001 (Мосгосэкспертиза)) | G12: 02-01-15 Система контроля и управления доступом | I12: 0 | K12: 0 | L12: 0 | M12: 4098 | O12: 0 | P12: 0 | Q12: 0 | R12: 0 | S12: 0 | T12: 1 | V12: 0 | AB12: Кузнецова Е.А. | BB12: 0 | BH12: Сметные нормы списания | BI12: Коды ОКП для ТСН-2001 МГЭ Дополнение 80 | BJ12: 1 | BK12: 1 | BL12: 0 | BM12: 0 | BN12: 1 | BO12: 0 | BP12: 6 | BQ12: 2 | BR12: 1 | BS12: 1 | BT12: 0 | BU12: 0 | BV12: 0 | BW12: 0 | BX12: 0 | BZ12: Типовой расчет для ТСН-2001 МГЭ, Дополнение 80, строительство | CA12: Территориальные сметные нормативы для Москвы ТСН-2001 (МГЭ), дополнение 80 | CB12: Территориальные сметные нормативы для Москвы ТСН-2001 (МГЭ), дополнение 80 | CC12: Территориальные сметные нормативы для Москвы ТСН-2001 (МГЭ), дополнение 80 | CD12: Территориальные сметные нормативы для Москвы ТСН-2001 (МГЭ), дополнение 80 | CE12: Поправки для ТСН-2001 от 03.10.2025 г. доп.79 | CF12: 0 | CG12: 0 | CH12: 327688 | CK12: 80 | CQ12: Территориальные сметные нормативы для Москвы (ТСН-2001) | CR12: ТЕР | CS12: 41660 | CT12: 1 | CU12: 80 | CY12: 0 | EC12: 0
A15: 15 | B15: 1
A18: 52 | B18: =B283 -> 322 | C18: =C283 -> 1 | D18: =D283 -> 12 | E18: =E283 -> 0 | F18: =F283 -> Новый объект (ТСН-2001 (Мосгосэкспертиза)) | G18: =G283 -> 02-01-15 Система контроля и управления доступом | O18: =O283 -> 557859.14 | P18: =P283 -> 546496.67 | Q18: =Q283 -> 1139.47 | R18: =R283 -> 174.72 | S18: =S283 -> 10223 | T18: =T283 -> 0 | U18: =U283 -> 787.70867 | V18: =V283 -> 0 | ... GX18: =GX283 -> 0
A20: 3 | B20: 1 | D20: =ROW(A253) -> 253 | F20: 02-01-15 | G20: Система контроля и управления доступом | I20: 0 | J20: 2024-00272-00-ИОС5.8 | K20: -1 | L20: 02-01-15 | S20: 0 | T20: 0 | V20: 2 | BX20: 0 | CF20: 0 | CG20: 0
A22: 52 | B22: =B253 -> 1 | C22: =C253 -> 3 | D22: =D253 -> 20 | E22: =E253 -> 0 | F22: =F253 -> 02-01-15 | G22: =G253 -> Система контроля и управления доступом | O22: =O253 -> 557859.14 | P22: =P253 -> 546496.67 | Q22: =Q253 -> 1139.47 | R22: =R253 -> 174.72 | S22: =S253 -> 10223 | T22: =T253 -> 0 | U22: =U253 -> 787.70867 | V22: =V253 -> 0 | ... GX22: =GX253 -> 0
A24: 4 | B24: 1 | D24: =ROW(A91) -> 91 | F24: Новый раздел | G24: Оборудование | I24: 0 | K24: 0 | S24: 0 | T24: 0 | V24: 2 | BX24: 0 | CJ24: 0
A26: 52 | B26: =B91 -> 1 | C26: =C91 -> 4 | D26: =D91 -> 24 | E26: =E91 -> 0 | F26: =F91 -> Новый раздел | G26: =G91 -> Оборудование | O26: =O91 -> 500427.42 | P26: =P91 -> 495367.76 | Q26: =Q91 -> 354.18 | R26: =R91 -> 46.3 | S26: =S91 -> 4705.48 | T26: =T91 -> 0 | U26: =U91 -> 355.44917 | V26: =V91 -> 0 | ... GX26: =GX91 -> 0
A28: 17 | B28: 1 | C28: =ROW(SmtRes!A4) -> 4 | D28: =ROW(EtalonRes!A5) -> 5 | E28: 1 | F28: 4.10-176-1 | G28: Монтаж блока контроля датчиков (контроллер) | H28: 10 шт. | I28: =ROUND(ROUND(2/10,4),9) -> 0.2 | J28: 0 | K28: =ROUND(ROUND(2/10,4),9) -> 0.2 | O28: =ROUND(CP28,2) -> 108.99 | P28: =ROUND((ROUND((AC28*AW28*I28),2)*BC28),2) -> 0.26 | Q28: =(ROUND((ROUND((((ET28*1.1))*AV28*I28),2)*BB28),2)+ROUND((ROUND(((AE28-((EU28*1.1)))*AV28*I28),2)*BS28),2)) -> 0.25 | R28: =ROUND((ROUND((AE28*AV28*I28),2)*BS28),2) -> 0.03 | S28: =ROUND((ROUND((AF28*AV28*I28),2)*BA28),2) -> 108.48 | T28: =ROUND(CU28*I28,2) -> 0 | U28: =CV28*I28 -> 6.9009864 | V28: =CW28*I28 -> 0 | W28: =ROUND(CX28*I28,2) -> 0 | X28: =ROUND(CY28,2) -> 97.66 | Y28: =ROUND(CZ28,2) -> 49.91 | AA28: 59213216 | AB28: =ROUND((AC28+AD28+AF28),6) -> 520.534 | AC28: =ROUND(((ES28*1)),6) -> 1.29 | AD28: =ROUND(((((ET28*1.1))-((EU28*1.1)))+AE28),6) -> 1.21 | AE28: =ROUND(((EU28*1.1)),6) -> 0.143 | AF28: =ROUND(((EV28*1.1)),6) -> 518.034 | AG28: =ROUND((AP28),6) -> 0 | AH28: =((EW28*1.1)) -> 32.956 | AI28: =((EX28*1.1)) -> 0 | AJ28: =(AS28) -> 0 | AK28: 473.33 | AL28: 1.29 | AM28: 1.1 | AN28: 0.13 | AO28: 470.94 | AP28: 0 | AQ28: 29.96 | AR28: 0 | AS28: 0 | AT28: 90 | AU28: 46 | AV28: 1.047 | AW28: 1 | AZ28: 1 | BA28: 1 | BB28: 1 | BC28: 1 | BH28: 0 | BI28: 2 | BJ28: ТСН-2001.4 Доп. 80, Сб. 10, т. 176, поз. 1 | BM28: 68 | BN28: 58808062 | BO28: 4.10-176-1 | BP28: 1 | BQ28: 40 | BR28: 0 | BS28: 1 | BT28: 1 | BU28: 1 | BV28: 1 | BW28: 1 | BX28: 1 | BZ28: 90 | CA28: 46 | CE28: 30 | CF28: 0 | CG28: 0 | CM28: 0 | CN28: Поправка: Гл.12.Прил.8.п.8. 5_12.00.01.11.003 Наименование: При наличии усложненных условий производства работ (стесненность, сложность складирования и транспортной логистики, наличие в зоне производства работ действующего технологического оборудования или движения технологического транспорта и т.п.) для объектов, расположенных за пределами территории круговой магистральной системы улиц "Садовое кольцо" и за пределами Третьего транспортного кольца города Москвы пунктов "а" и "б", но в пределах Московской кольцевой автомобильной дороги | CO28: 0 | CP28: =(P28+Q28+S28) -> 108.99 | CQ28: =ROUND((ROUND((AC28*AW28*1),2)*BC28),2) -> 1.29 | CR28: =(ROUND((ROUND((((ET28*1.1))*AV28*1),2)*BB28),2)+ROUND((ROUND(((AE28-((EU28*1.1)))*AV28*1),2)*BS28),2)) -> 1.27 | CS28: =ROUND((ROUND((AE28*AV28*1),2)*BS28),2) -> 0.15 | CT28: =ROUND((ROUND((AF28*AV28*1),2)*BA28),2) -> 542.38 | CU28: =AG28 -> 0 | CV28: =(AH28*AV28) -> 34.504932 | CW28: =AI28 -> 0 | CX28: =AJ28 -> 0 | CY28: =(((S28+R28)*AT28)/100) -> 97.659 | CZ28: =(((S28+R28)*AU28)/100) -> 49.9146 | DB28: 1 | DD28: *1 | DE28: *1,1 | DF28: *1,1 | DG28: *1,1 | DI28: *1,1 | DJ28: *1,1 | DN28: 0 | DO28: 0 | DP28: 1 | DQ28: 1 | DU28: 1010 | DV28: 10 шт. | DW28: 10 шт. | DX28: 10 | EE28: 58808178 | EF28: 40 | EG28: Монтаж оборудования | EH28: 0 | EJ28: 2 | EK28: 68 | EL28: ТСН-2001.4-10. Прокладка и монтаж сетей связи | EM28: ТСН-2001.4-10-1 | EO28: Поправка: Гл.12.Прил.8.п.8. 5_12.00.01.11.003 | EQ28: 0 | ER28: 473.33 | ES28: 1.29 | ET28: 1.1 | EU28: 0.13 | EV28: 470.94 | EW28: 29.96 | EX28: 0 | EY28: 0 | FQ28: 0 | FR28: 0 | FS28: 0 | FX28: 90 | FY28: 46 | GD28: 1 | GF28: -733186695 | GG28: 2 | GH28: 1 | GI28: 2 | GJ28: 0 | GK28: 0 | GL28: =ROUND(IF(AND(BH28=3,BI28=3,FS28<>0),P28,0),2) -> 0 | GM28: =ROUND(O28+X28+Y28,2)+GX28 -> 256.56 | GN28: =IF(OR(BI28=0,BI28=1),GM28-GX28,0) -> 0 | GO28: =IF(BI28=2,GM28-GX28,0) -> 256.56 | GP28: =IF(BI28=4,GM28-GX28,0) -> 0 | GR28: 0 | GS28: 3 | GT28: 0 | GV28: =ROUND((GT28),6) -> 0 | GW28: 1 | GX28: =ROUND(HC28*I28,2) -> 0 | HA28: 0 | HB28: 0 | HC28: =GV28*GW28 -> 0 | HS28: 0 | IK28: 0
A29: 17 | B29: 1 | C29: =ROW(SmtRes!A8) -> 8 | D29: =ROW(EtalonRes!A10) -> 10 | E29: 1 | F29: 4.10-176-1 | G29: Монтаж блока контроля датчиков (контроллер) | H29: 10 шт. | I29: =ROUND(ROUND(2/10,4),9) -> 0.2 | J29: 0 | K29: =ROUND(ROUND(2/10,4),9) -> 0.2 | O29: =ROUND(CP29,2) -> 5970.83 | P29: =ROUND((ROUND((AC29*AW29*I29),2)*BC29),2) -> 1.89 | Q29: =(ROUND((ROUND((((ET29*1.1))*AV29*I29),2)*BB29),2)+ROUND((ROUND(((AE29-((EU29*1.1)))*AV29*I29),2)*BS29),2)) -> 3.62 | R29: =ROUND((ROUND((AE29*AV29*I29),2)*BS29),2) -> 1.65 | S29: =ROUND((ROUND((AF29*AV29*I29),2)*BA29),2) -> 5965.32 | T29: =ROUND(CU29*I29,2) -> 0 | U29: =CV29*I29 -> 6.9009864 | V29: =CW29*I29 -> 0 | W29: =ROUND(CX29*I29,2) -> 0 | X29: =ROUND(CY29,2) -> 5370.27 | Y29: =ROUND(CZ29,2) -> 2744.81 | AA29: 59213213 | AB29: =ROUND((AC29+AD29+AF29),6) -> 520.534 | AC29: =ROUND(((ES29*1)),6) -> 1.29 | AD29: =ROUND(((((ET29*1.1))-((EU29*1.1)))+AE29),6) -> 1.21 | AE29: =ROUND(((EU29*1.1)),6) -> 0.143 | AF29: =ROUND(((EV29*1.1)),6) -> 518.034 | AG29: =ROUND((AP29),6) -> 0 | AH29: =((EW29*1.1)) -> 32.956 | AI29: =((EX29*1.1)) -> 0 | AJ29: =(AS29) -> 0 | AK29: 473.33 | AL29: 1.29 | AM29: 1.1 | AN29: 0.13 | AO29: 470.94 | AP29: 0 | AQ29: 29.96 | AR29: 0 | AS29: 0 | AT29: 90 | AU29: 46 | AV29: 1.047 | AW29: 1 | AZ29: 1 | BA29: 54.99 | BB29: 14.48 | BC29: 7.25 | BH29: 0 | BI29: 2 | BJ29: ТСН-2001.4 Доп. 80, Сб. 10, т. 176, поз. 1 | BM29: 68 | BN29: 58808062 | BO29: 4.10-176-1 | BP29: 1 | BQ29: 40 | BR29: 0 | BS29: 54.99 | BT29: 1 | BU29: 1 | BV29: 1 | BW29: 1 | BX29: 1 | BZ29: 90 | CA29: 46 | CE29: 30 | CF29: 0 | CG29: 0 | CM29: 0 | CN29: Поправка: Гл.12.Прил.8.п.8. 5_12.00.01.11.003 Наименование: При наличии усложненных условий производства работ (стесненность, сложность складирования и транспортной логистики, наличие в зоне производства работ действующего технологического оборудования или движения технологического транспорта и т.п.) для объектов, расположенных за пределами территории круговой магистральной системы улиц "Садовое кольцо" и за пределами Третьего транспортного кольца города Москвы пунктов "а" и "б", но в пределах Московской кольцевой автомобильной дороги | CO29: 0 | CP29: =(P29+Q29+S29) -> 5970.83 | CQ29: =ROUND((ROUND((AC29*AW29*1),2)*BC29),2) -> 9.35 | CR29: =(ROUND((ROUND((((ET29*1.1))*AV29*1),2)*BB29),2)+ROUND((ROUND(((AE29-((EU29*1.1)))*AV29*1),2)*BS29),2)) -> 18.39 | CS29: =ROUND((ROUND((AE29*AV29*1),2)*BS29),2) -> 8.25 | CT29: =ROUND((ROUND((AF29*AV29*1),2)*BA29),2) -> 29825.48 | CU29: =AG29 -> 0 | CV29: =(AH29*AV29) -> 34.504932 | CW29: =AI29 -> 0 | CX29: =AJ29 -> 0 | CY29: =(((S29+R29)*AT29)/100) -> 5370.273 | CZ29: =(((S29+R29)*AU29)/100) -> 2744.8062 | DB29: 2 | DD29: *1 | DE29: *1,1 | DF29: *1,1 | DG29: *1,1 | DI29: *1,1 | DJ29: *1,1 | DN29: 0 | DO29: 0 | DP29: 1 | DQ29: 1 | DU29: 1010 | DV29: 10 шт. | DW29: 10 шт. | DX29: 10 | EE29: 58808178 | EF29: 40 | EG29: Монтаж оборудования | EH29: 0 | EJ29: 2 | EK29: 68 | EL29: ТСН-2001.4-10. Прокладка и монтаж сетей связи | EM29: ТСН-2001.4-10-1 | EO29: Поправка: Гл.12.Прил.8.п.8. 5_12.00.01.11.003 | EQ29: 0 | ER29: 473.33 | ES29: 1.29 | ET29: 1.1 | EU29: 0.13 | EV29: 470.94 | EW29: 29.96 | EX29: 0 | EY29: 0 | FQ29: 0 | FR29: 0 | FS29: 0 | FX29: 90 | FY29: 46 | GD29: 1 | GF29: -733186695 | GG29: 2 | GH29: 1 | GI29: 2 | GJ29: 0 | GK29: 0 | GL29: =ROUND(IF(AND(BH29=3,BI29=3,FS29<>0),P29,0),2) -> 0 | GM29: =ROUND(O29+X29+Y29,2)+GX29 -> 14085.91 | GN29: =IF(OR(BI29=0,BI29=1),GM29-GX29,0) -> 0 | GO29: =IF(BI29=2,GM29-GX29,0) -> 14085.91 | GP29: =IF(BI29=4,GM29-GX29,0) -> 0 | GR29: 0 | GS29: 3 | GT29: 0 | GV29: =ROUND((GT29),6) -> 0 | GW29: 1 | GX29: =ROUND(HC29*I29,2) -> 0 | HA29: 0 | HB29: 0 | HC29: =GV29*GW29 -> 0 | HS29: 0 | IK29: 0
A30: 17 | B30: 1 | E30: 2 | F30: КА 1 | G30: Сетевой контроллер доступа "STR20-IP" до 8 точек, встроенное ПО | H30: шт. | I30: =ROUND(ROUND(20,4),9) -> 20 | J30: 0 | K30: =ROUND(ROUND(20,4),9) -> 20 | O30: =ROUND(CP30,2) -> 146284.2 | P30: =ROUND((ROUND((AC30*I30),2)*BC30),2) -> 146284.2 | Q30: =(ROUND((ROUND(((ET30)*AV30*I30),2)*BB30),2)+ROUND((ROUND(((AE30-(EU30))*AV30*I30),2)*BS30),2)) -> 0 | R30: =ROUND((ROUND((AE30*AV30*I30),2)*BS30),2) -> 0 | S30: =ROUND((ROUND((AF30*AV30*I30),2)*BA30),2) -> 0 | T30: =ROUND(CU30*I30,2) -> 0 | U30: =CV30*I30 -> 0 | V30: =CW30*I30 -> 0 | W30: =ROUND(CX30*I30,2) -> 0 | X30: =ROUND(CY30,2) -> 0 | Y30: =ROUND(CZ30,2) -> 0 | AA30: 59213216 | AB30: =ROUND((AC30+AD30+AF30),6) -> 7314.21 | AC30: =ROUND((ES30),6) -> 7314.21 | AD30: =ROUND((((ET30)-(EU30))+AE30),6) -> 0 | AE30: =ROUND((EU30),6) -> 0 | AF30: =ROUND((EV30),6) -> 0 | AG30: =ROUND((AP30),6) -> 0 | AH30: =(EW30) -> 0 | AI30: =(EX30) -> 0 | AJ30: =(AS30) -> 0 | AK30: 7314.21 | AL30: 7314.21 | AM30: 0 | AN30: 0 | AO30: 0 | AP30: 0 | AQ30: 0 | AR30: 0 | AS30: 0 | AT30: 0 | AU30: 0 | AV30: 1 | AW30: 1 | AZ30: 1 | BA30: 1 | BB30: 1 | BC30: 1 | BH30: 3 | BI30: 3 | BM30: 746 | BN30: 0 | BP30: 0 | BQ30: 130 | BR30: 0 | BS30: 1 | BT30: 1 | BU30: 1 | BV30: 1 | BW30: 1 | BX30: 1 | BZ30: 0 | CA30: 0 | CE30: 30 | CF30: 0 | CG30: 0 | CM30: 0 | CO30: 0 | CP30: =(P30+Q30+S30) -> 146284.2 | CQ30: =ROUND((ROUND((AC30*1),2)*BC30),2) -> 7314.21 | CR30: =(ROUND((ROUND(((ET30)*AV30*1),2)*BB30),2)+ROUND((ROUND(((AE30-(EU30))*AV30*1),2)*BS30),2)) -> 0 | CS30: =ROUND((ROUND((AE30*AV30*1),2)*BS30),2) -> 0 | CT30: =ROUND((ROUND((AF30*AV30*1),2)*BA30),2) -> 0 | CU30: =AG30 -> 0 | CV30: =(AH30*AV30) -> 0 | CW30: =AI30 -> 0 | CX30: =AJ30 -> 0 | CY30: =(((S30+R30)*AT30)/100) -> 0 | CZ30: =(((S30+R30)*AU30)/100) -> 0 | DN30: 0 | DO30: 0 | DP30: 1 | DQ30: 1 | DU30: 1010 | DV30: шт. | DW30: шт. | DX30: 1 | EE30: 58808284 | EF30: 130 | EG30: Сметная стоимость оборудования | EH30: 0 | EJ30: 3 | EK30: 746 | EL30: ТСН-2001.13. Сметная стоимость оборудования | EM30: ТСН-2001.13 | EQ30: 0 | ER30: 0 | ES30: 7314.21 | ET30: 0 | EU30: 0 | EV30: 0 | EW30: 0 | EX30: 0 | EY30: 0 | FQ30: 0 | FR30: =P30 -> 146284.2 | FS30: 0 | FX30: 0 | FY30: 0 | GA30: [64 500 / 1,2 / 7,66] + 3% Трансп + 1,2% Заг.скл | GD30: 1 | GF30: -1151737737 | GG30: 2 | GH30: 4 | GI30: -2 | GJ30: 0 | GK30: 0 | GL30: =ROUND(IF(AND(BH30=3,BI30=3,FS30<>0),P30,0),2) -> 0 | GM30: =ROUND(O30+X30+Y30,2)+GX30 -> 146284.2 | GN30: =IF(OR(BI30=0,BI30=1),GM30-GX30,0) -> 0 | GO30: =IF(BI30=2,GM30-GX30,0) -> 0 | GP30: =IF(BI30=4,GM30-GX30,0) -> 0 | GR30: 0 | GS30: 2 | GT30: 0 | GV30: =ROUND((GT30),6) -> 0 | GW30: 1 | GX30: =ROUND(HC30*I30,2) -> 0 | HA30: 0 | HB30: 0 | HC30: =GV30*GW30 -> 0 | HE30: 3 | HF30: 1,2 | HS30: 0 | IK30: 0
A31: 17 | B31: 1 | E31: 2 | F31: КА 1 | G31: Сетевой контроллер доступа "STR20-IP" до 8 точек, встроенное ПО | H31: шт. | I31: =ROUND(ROUND(20,4),9) -> 20 | J31: 0 | K31: =ROUND(ROUND(20,4),9) -> 20 | O31: =ROUND(CP31,2) -> 1120537 | P31: =ROUND((ROUND((AC31*I31),2)*BC31),2) -> 1120537 | Q31: =(ROUND((ROUND(((ET31)*AV31*I31),2)*BB31),2)+ROUND((ROUND(((AE31-(EU31))*AV31*I31),2)*BS31),2)) -> 0 | R31: =ROUND((ROUND((AE31*AV31*I31),2)*BS31),2) -> 0 | S31: =ROUND((ROUND((AF31*AV31*I31),2)*BA31),2) -> 0 | T31: =ROUND(CU31*I31,2) -> 0 | U31: =CV31*I31 -> 0 | V31: =CW31*I31 -> 0 | W31: =ROUND(CX31*I31,2) -> 0 | X31: =ROUND(CY31,2) -> 0 | Y31: =ROUND(CZ31,2) -> 0 | AA31: 59213213 | AB31: =ROUND((AC31+AD31+AF31),6) -> 7314.21 | AC31: =ROUND((ES31),6) -> 7314.21 | AD31: =ROUND((((ET31)-(EU31))+AE31),6) -> 0 | AE31: =ROUND((EU31),6) -> 0 | AF31: =ROUND((EV31),6) -> 0 | AG31: =ROUND((AP31),6) -> 0 | AH31: =(EW31) -> 0 | AI31: =(EX31) -> 0 | AJ31: =(AS31) -> 0 | AK31: 7314.21 | AL31: 7314.21 | AM31: 0 | AN31: 0 | AO31: 0 | AP31: 0 | AQ31: 0 | AR31: 0 | AS31: 0 | AT31: 0 | AU31: 0 | AV31: 1 | AW31: 1 | AZ31: 1 | BA31: 1 | BB31: 1 | BC31: 7.66 | BH31: 3 | BI31: 3 | BM31: 746 | BN31: 0 | BP31: 0 | BQ31: 130 | BR31: 0 | BS31: 1 | BT31: 1 | BU31: 1 | BV31: 1 | BW31: 1 | BX31: 1 | BZ31: 0 | CA31: 0 | CE31: 30 | CF31: 0 | CG31: 0 | CM31: 0 | CO31: 0 | CP31: =(P31+Q31+S31) -> 1120537 | CQ31: =ROUND((ROUND((AC31*1),2)*BC31),2) -> 56026.85 | CR31: =(ROUND((ROUND(((ET31)*AV31*1),2)*BB31),2)+ROUND((ROUND(((AE31-(EU31))*AV31*1),2)*BS31),2)) -> 0 | CS31: =ROUND((ROUND((AE31*AV31*1),2)*BS31),2) -> 0 | CT31: =ROUND((ROUND((AF31*AV31*1),2)*BA31),2) -> 0 | CU31: =AG31 -> 0 | CV31: =(AH31*AV31) -> 0 | CW31: =AI31 -> 0 | CX31: =AJ31 -> 0 | CY31: =(((S31+R31)*AT31)/100) -> 0 | CZ31: =(((S31+R31)*AU31)/100) -> 0 | DN31: 0 | DO31: 0 | DP31: 1 | DQ31: 1 | DU31: 1010 | DV31: шт. | DW31: шт. | DX31: 1 | EE31: 58808284 | EF31: 130 | EG31: Сметная стоимость оборудования | EH31: 0 | EJ31: 3 | EK31: 746 | EL31: ТСН-2001.13. Сметная стоимость оборудования | EM31: ТСН-2001.13 | EQ31: 0 | ER31: 7314.21 | ES31: 7314.21 | ET31: 0 | EU31: 0 | EV31: 0 | EW31: 0 | EX31: 0 | EY31: 0 | EZ31: 5 | FC31: 1 | FD31: 18 | FF31: 64500 | FQ31: 0 | FR31: =P31 -> 1120537 | FS31: 0 | FX31: 0 | FY31: 0 | GA31: [64 500 / 1,2 / 7,66] + 3% Трансп + 1,2% Заг.скл | GD31: 1 | GF31: -1151737737 | GG31: 2 | GH31: 3 | GI31: 5 | GJ31: 0 | GK31: 0 | GL31: =ROUND(IF(AND(BH31=3,BI31=3,FS31<>0),P31,0),2) -> 0 | GM31: =ROUND(O31+X31+Y31,2)+GX31 -> 1120537 | GN31: =IF(OR(BI31=0,BI31=1),GM31-GX31,0) -> 0 | GO31: =IF(BI31=2,GM31-GX31,0) -> 0 | GP31: =IF(BI31=4,GM31-GX31,0) -> 0 | GR31: 2 | GS31: 1 | GT31: 0 | GV31: =ROUND((GT31),6) -> 0 | GW31: 1 | GX31: =ROUND(HC31*I31,2) -> 0 | HA31: 0 | HB31: 0 | HC31: =GV31*GW31 -> 0 | HE31: 3 | HF31: 1,2 | HS31: 0 | IK31: 0
A32: 17 | B32: 1 | C32: =ROW(SmtRes!A9) -> 9 | D32: =ROW(EtalonRes!A11) -> 11 | E32: 3 | F32: 4.10-80-4 | G32: Аппараты приемные, приборы ПС приемно-контрольные, пусковые, прибор ПС на 4 луча | H32: 1 ШТ. | I32: =ROUND(ROUND(12,4),9) -> 12 | J32: 0 | K32: =ROUND(ROUND(12,4),9) -> 12 | O32: =ROUND(CP32,2) -> 697.82 | P32: =ROUND((ROUND((AC32*AW32*I32),2)*BC32),2) -> 77.28 | Q32: =(ROUND((ROUND((((ET32*1.1))*AV32*I32),2)*BB32),2)+ROUND((ROUND(((AE32-((EU32*1.1)))*AV32*I32),2)*BS32),2)) -> 1.66 | R32: =ROUND((ROUND((AE32*AV32*I32),2)*BS32),2) -> 0.14 | S32: =ROUND((ROUND((AF32*AV32*I32),2)*BA32),2) -> 618.88 | T32: =ROUND(CU32*I32,2) -> 0 | U32: =CV32*I32 -> 45.60732 | V32: =CW32*I32 -> 0 | W32: =ROUND(CX32*I32,2) -> 0 | X32: =ROUND(CY32,2) -> 557.12 | Y32: =ROUND(CZ32,2) -> 284.75 | AA32: 59213216 | AB32: =ROUND((AC32+AD32+AF32),6) -> 55.83 | AC32: =ROUND(((ES32*1)),6) -> 6.44 | AD32: =ROUND(((((ET32*1.1))-((EU32*1.1)))+AE32),6) -> 0.132 | AE32: =ROUND(((EU32*1.1)),6) -> 0.011 | AF32: =ROUND(((EV32*1.1)),6) -> 49.258 | AG32: =ROUND((AP32),6) -> 0 | AH32: =((EW32*1.1)) -> 3.63 | AI32: =((EX32*1.1)) -> 0 | AJ32: =(AS32) -> 0 | AK32: 51.34 | AL32: 6.44 | AM32: 0.12 | AN32: 0.01 | AO32: 44.78 | AP32: 0 | AQ32: 3.3 | AR32: 0 | AS32: 0 | AT32: 90 | AU32: 46 | AV32: 1.047 | AW32: 1 | AZ32: 1 | BA32: 1 | BB32: 1 | BC32: 1 | BH32: 0 | BI32: 2 | BJ32: ТСН-2001.4. Доп. 1-42. Сб. 10, т. 80, поз. 4 | BM32: 68 | BN32: 58808062 | BO32: 4.10-80-4 | BP32: 1 | BQ32: 40 | BR32: 0 | BS32: 1 | BT32: 1 | BU32: 1 | BV32: 1 | BW32: 1 | BX32: 1 | BZ32: 90 | CA32: 46 | CE32: 30 | CF32: 0 | CG32: 0 | CM32: 0 | CN32: Поправка: Гл.12.Прил.8.п.8. 5_12.00.01.11.003 Наименование: При наличии усложненных условий производства работ (стесненность, сложность складирования и транспортной логистики, наличие в зоне производства работ действующего технологического оборудования или движения технологического транспорта и т.п.) для объектов, расположенных за пределами территории круговой магистральной системы улиц "Садовое кольцо" и за пределами Третьего транспортного кольца города Москвы пунктов "а" и "б", но в пределах Московской кольцевой автомобильной дороги | CO32: 0 | CP32: =(P32+Q32+S32) -> 697.82 | CQ32: =ROUND((ROUND((AC32*AW32*1),2)*BC32),2) -> 6.44 | CR32: =(ROUND((ROUND((((ET32*1.1))*AV32*1),2)*BB32),2)+ROUND((ROUND(((AE32-((EU32*1.1)))*AV32*1),2)*BS32),2)) -> 0.14 | CS32: =ROUND((ROUND((AE32*AV32*1),2)*BS32),2) -> 0.01 | CT32: =ROUND((ROUND((AF32*AV32*1),2)*BA32),2) -> 51.57 | CU32: =AG32 -> 0 | CV32: =(AH32*AV32) -> 3.80061 | CW32: =AI32 -> 0 | CX32: =AJ32 -> 0 | CY32: =(((S32+R32)*AT32)/100) -> 557.118 | CZ32: =(((S32+R32)*AU32)/100) -> 284.7492 | DB32: 3 | DD32: *1 | DE32: *1,1 | DF32: *1,1 | DG32: *1,1 | DI32: *1,1 | DJ32: *1,1 | DN32: 0 | DO32: 0 | DP32: 1 | DQ32: 1 | DU32: 1013 | DV32: 1 ШТ. | DW32: 1 ШТ. | DX32: 1 | EE32: 58808178 | EF32: 40 | EG32: Монтаж оборудования | EH32: 0 | EJ32: 2 | EK32: 68 | EL32: ТСН-2001.4-10. Прокладка и монтаж сетей связи | EM32: ТСН-2001.4-10-1 | EO32: Поправка: Гл.12.Прил.8.п.8. 5_12.00.01.11.003 | EQ32: 0 | ER32: 51.34 | ES32: 6.44 | ET32: 0.12 | EU32: 0.01 | EV32: 44.78 | EW32: 3.3 | EX32: 0 | EY32: 0 | FQ32: 0 | FR32: 0 | FS32: 0 | FX32: 90 | FY32: 46 | GD32: 1 | GF32: -1862862500 | GG32: 2 | GH32: 1 | GI32: 2 | GJ32: 0 | GK32: 0 | GL32: =ROUND(IF(AND(BH32=3,BI32=3,FS32<>0),P32,0),2) -> 0 | GM32: =ROUND(O32+X32+Y32,2)+GX32 -> 1539.69 | GN32: =IF(OR(BI32=0,BI32=1),GM32-GX32,0) -> 0 | GO32: =IF(BI32=2,GM32-GX32,0) -> 1539.69 | GP32: =IF(BI32=4,GM32-GX32,0) -> 0 | GR32: 0 | GS32: 3 | GT32: 0 | GV32: =ROUND((GT32),6) -> 0 | GW32: 1 | GX32: =ROUND(HC32*I32,2) -> 0 | HA32: 0 | HB32: 0 | HC32: =GV32*GW32 -> 0 | HS32: 0 | IK32: 0
A33: 17 | B33: 1 | C33: =ROW(SmtRes!A10) -> 10 | D33: =ROW(EtalonRes!A12) -> 12 | E33: 3 | F33: 4.10-80-4 | G33: Аппараты приемные, приборы ПС приемно-контрольные, пусковые, прибор ПС на 4 луча | H33: 1 ШТ. | I33: =ROUND(ROUND(12,4),9) -> 12 | J33: 0 | K33: =ROUND(ROUND(12,4),9) -> 12 | O33: =ROUND(CP33,2) -> 34819.34 | P33: =ROUND((ROUND((AC33*AW33*I33),2)*BC33),2) -> 764.3 | Q33: =(ROUND((ROUND((((ET33*1.1))*AV33*I33),2)*BB33),2)+ROUND((ROUND(((AE33-((EU33*1.1)))*AV33*I33),2)*BS33),2)) -> 22.83 | R33: =ROUND((ROUND((AE33*AV33*I33),2)*BS33),2) -> 7.7 | S33: =ROUND((ROUND((AF33*AV33*I33),2)*BA33),2) -> 34032.21 | T33: =ROUND(CU33*I33,2) -> 0 | U33: =CV33*I33 -> 45.60732 | V33: =CW33*I33 -> 0 | W33: =ROUND(CX33*I33,2) -> 0 | X33: =ROUND(CY33,2) -> 30635.92 | Y33: =ROUND(CZ33,2) -> 15658.36 | AA33: 59213213 | AB33: =ROUND((AC33+AD33+AF33),6) -> 55.83 | AC33: =ROUND(((ES33*1)),6) -> 6.44 | AD33: =ROUND(((((ET33*1.1))-((EU33*1.1)))+AE33),6) -> 0.132 | AE33: =ROUND(((EU33*1.1)),6) -> 0.011 | AF33: =ROUND(((EV33*1.1)),6) -> 49.258 | AG33: =ROUND((AP33),6) -> 0 | AH33: =((EW33*1.1)) -> 3.63 | AI33: =((EX33*1.1)) -> 0 | AJ33: =(AS33) -> 0 | AK33: 51.34 | AL33: 6.44 | AM33: 0.12 | AN33: 0.01 | AO33: 44.78 | AP33: 0 | AQ33: 3.3 | AR33: 0 | AS33: 0 | AT33: 90 | AU33: 46 | AV33: 1.047 | AW33: 1 | AZ33: 1 | BA33: 54.99 | BB33: 13.75 | BC33: 9.89 | BH33: 0 | BI33: 2 | BJ33: ТСН-2001.4. Доп. 1-42. Сб. 10, т. 80, поз. 4 | BM33: 68 | BN33: 58808062 | BO33: 4.10-80-4 | BP33: 1 | BQ33: 40 | BR33: 0 | BS33: 54.99 | BT33: 1 | BU33: 1 | BV33: 1 | BW33: 1 | BX33: 1 | BZ33: 90 | CA33: 46 | CE33: 30 | CF33: 0 | CG33: 0 | CM33: 0 | CN33: Поправка: Гл.12.Прил.8.п.8. 5_12.00.01.11.003 Наименование: При наличии усложненных условий производства работ (стесненность, сложность складирования и транспортной логистики, наличие в зоне производства работ действующего технологического оборудования или движения технологического транспорта и т.п.) для объектов, расположенных за пределами территории круговой магистральной системы улиц "Садовое кольцо" и за пределами Третьего транспортного кольца города Москвы пунктов "а" и "б", но в пределах Московской кольцевой автомобильной дороги | CO33: 0 | CP33: =(P33+Q33+S33) -> 34819.34 | CQ33: =ROUND((ROUND((AC33*AW33*1),2)*BC33),2) -> 63.69 | CR33: =(ROUND((ROUND((((ET33*1.1))*AV33*1),2)*BB33),2)+ROUND((ROUND(((AE33-((EU33*1.1)))*AV33*1),2)*BS33),2)) -> 1.93 | CS33: =ROUND((ROUND((AE33*AV33*1),2)*BS33),2) -> 0.55 | CT33: =ROUND((ROUND((AF33*AV33*1),2)*BA33),2) -> 2835.83 | CU33: =AG33 -> 0 | CV33: =(AH33*AV33) -> 3.80061 | CW33: =AI33 -> 0 | CX33: =AJ33 -> 0 | CY33: =(((S33+R33)*AT33)/100) -> 30635.919 | CZ33: =(((S33+R33)*AU33)/100) -> 15658.359 | DB33: 4 | DD33: *1 | DE33: *1,1 | DF33: *1,1 | DG33: *1,1 | DI33: *1,1 | DJ33: *1,1 | DN33: 0 | DO33: 0 | DP33: 1 | DQ33: 1 | DU33: 1013 | DV33: 1 ШТ. | DW33: 1 ШТ. | DX33: 1 | EE33: 58808178 | EF33: 40 | EG33: Монтаж оборудования | EH33: 0 | EJ33: 2 | EK33: 68 | EL33: ТСН-2001.4-10. Прокладка и монтаж сетей связи | EM33: ТСН-2001.4-10-1 | EO33: Поправка: Гл.12.Прил.8.п.8. 5_12.00.01.11.003 | EQ33: 0 | ER33: 51.34 | ES33: 6.44 | ET33: 0.12 | EU33: 0.01 | EV33: 44.78 | EW33: 3.3 | EX33: 0 | EY33: 0 | FQ33: 0 | FR33: 0 | FS33: 0 | FX33: 90 | FY33: 46 | GD33: 1 | GF33: -1862862500 | GG33: 2 | GH33: 1 | GI33: 2 | GJ33: 0 | GK33: 0 | GL33: =ROUND(IF(AND(BH33=3,BI33=3,FS33<>0),P33,0),2) -> 0 | GM33: =ROUND(O33+X33+Y33,2)+GX33 -> 81113.62 | GN33: =IF(OR(BI33=0,BI33=1),GM33-GX33,0) -> 0 | GO33: =IF(BI33=2,GM33-GX33,0) -> 81113.62 | GP33: =IF(BI33=4,GM33-GX33,0) -> 0 | GR33: 0 | GS33: 3 | GT33: 0 | GV33: =ROUND((GT33),6) -> 0 | GW33: 1 | GX33: =ROUND(HC33*I33,2) -> 0 | HA33: 0 | HB33: 0 | HC33: =GV33*GW33 -> 0 | HS33: 0 | IK33: 0
A34: 17 | B34: 1 | E34: 4 | F34: КА 2 | G34: Модуль доступа-контроллер доступа STR-1AP-M на 2 точки | H34: шт. | I34: =ROUND(ROUND(12,4),9) -> 12 | J34: 0 | K34: =ROUND(ROUND(12,4),9) -> 12 | O34: =ROUND(CP34,2) -> 21636.48 | P34: =ROUND((ROUND((AC34*I34),2)*BC34),2) -> 21636.48 | Q34: =(ROUND((ROUND(((ET34)*AV34*I34),2)*BB34),2)+ROUND((ROUND(((AE34-(EU34))*AV34*I34),2)*BS34),2)) -> 0 | R34: =ROUND((ROUND((AE34*AV34*I34),2)*BS34),2) -> 0 | S34: =ROUND((ROUND((AF34*AV34*I34),2)*BA34),2) -> 0 | T34: =ROUND(CU34*I34,2) -> 0 | U34: =CV34*I34 -> 0 | V34: =CW34*I34 -> 0 | W34: =ROUND(CX34*I34,2) -> 0 | X34: =ROUND(CY34,2) -> 0 | Y34: =ROUND(CZ34,2) -> 0 | AA34: 59213216 | AB34: =ROUND((AC34+AD34+AF34),6) -> 1803.04 | AC34: =ROUND((ES34),6) -> 1803.04 | AD34: =ROUND((((ET34)-(EU34))+AE34),6) -> 0 | AE34: =ROUND((EU34),6) -> 0 | AF34: =ROUND((EV34),6) -> 0 | AG34: =ROUND((AP34),6) -> 0 | AH34: =(EW34) -> 0 | AI34: =(EX34) -> 0 | AJ34: =(AS34) -> 0 | AK34: 1803.04 | AL34: 1803.04 | AM34: 0 | AN34: 0 | AO34: 0 | AP34: 0 | AQ34: 0 | AR34: 0 | AS34: 0 | AT34: 0 | AU34: 0 | AV34: 1 | AW34: 1 | AZ34: 1 | BA34: 1 | BB34: 1 | BC34: 1 | BH34: 3 | BI34: 3 | BM34: 746 | BN34: 0 | BP34: 0 | BQ34: 130 | BR34: 0 | BS34: 1 | BT34: 1 | BU34: 1 | BV34: 1 | BW34: 1 | BX34: 1 | BZ34: 0 | CA34: 0 | CE34: 30 | CF34: 0 | CG34: 0 | CM34: 0 | CO34: 0 | CP34: =(P34+Q34+S34) -> 21636.48 | CQ34: =ROUND((ROUND((AC34*1),2)*BC34),2) -> 1803.04 | CR34: =(ROUND((ROUND(((ET34)*AV34*1),2)*BB34),2)+ROUND((ROUND(((AE34-(EU34))*AV34*1),2)*BS34),2)) -> 0 | CS34: =ROUND((ROUND((AE34*AV34*1),2)*BS34),2) -> 0 | CT34: =ROUND((ROUND((AF34*AV34*1),2)*BA34),2) -> 0 | CU34: =AG34 -> 0 | CV34: =(AH34*AV34) -> 0 | CW34: =AI34 -> 0 | CX34: =AJ34 -> 0 | CY34: =(((S34+R34)*AT34)/100) -> 0 | CZ34: =(((S34+R34)*AU34)/100) -> 0 | DN34: 0 | DO34: 0 | DP34: 1 | DQ34: 1 | DU34: 1010 | DV34: шт. | DW34: шт. | DX34: 1 | EE34: 58808284 | EF34: 130 | EG34: Сметная стоимость оборудования | EH34: 0 | EJ34: 3 | EK34: 746 | EL34: ТСН-2001.13. Сметная стоимость оборудования | EM34: ТСН-2001.13 | EQ34: 0 | ER34: 0 | ES34: 1803.04 | ET34: 0 | EU34: 0 | EV34: 0 | EW34: 0 | EX34: 0 | EY34: 0 | FQ34: 0 | FR34: =P34 -> 21636.48 | FS34: 0 | FX34: 0 | FY34: 0 | GA34: [15 900 / 1,2 / 7,66] + 3% Трансп + 1,2% Заг.скл | GD34: 1 | GF34: 1328923490 | GG34: 2 | GH34: 4 | GI34: -2 | GJ34: 0 | GK34: 0 | GL34: =ROUND(IF(AND(BH34=3,BI34=3,FS34<>0),P34,0),2) -> 0 | GM34: =ROUND(O34+X34+Y34,2)+GX34 -> 21636.48 | GN34: =IF(OR(BI34=0,BI34=1),GM34-GX34,0) -> 0 | GO34: =IF(BI34=2,GM34-GX34,0) -> 0 | GP34: =IF(BI34=4,GM34-GX34,0) -> 0 | GR34: 0 | GS34: 2 | GT34: 0 | GV34: =ROUND((GT34),6) -> 0 | GW34: 1 | GX34: =ROUND(HC34*I34,2) -> 0 | HA34: 0 | HB34: 0 | HC34: =GV34*GW34 -> 0 | HE34: 3 | HF34: 1,2 | HS34: 0 | IK34: 0
A35: 17 | B35: 1 | E35: 4 | F35: КА 2 | G35: Модуль доступа-контроллер доступа STR-1AP-M на 2 точки | H35: шт. | I35: =ROUND(ROUND(12,4),9) -> 12 | J35: 0 | K35: =ROUND(ROUND(12,4),9) -> 12 | O35: =ROUND(CP35,2) -> 165735.44 | P35: =ROUND((ROUND((AC35*I35),2)*BC35),2) -> 165735.44 | Q35: =(ROUND((ROUND(((ET35)*AV35*I35),2)*BB35),2)+ROUND((ROUND(((AE35-(EU35))*AV35*I35),2)*BS35),2)) -> 0 | R35: =ROUND((ROUND((AE35*AV35*I35),2)*BS35),2) -> 0 | S35: =ROUND((ROUND((AF35*AV35*I35),2)*BA35),2) -> 0 | T35: =ROUND(CU35*I35,2) -> 0 | U35: =CV35*I35 -> 0 | V35: =CW35*I35 -> 0 | W35: =ROUND(CX35*I35,2) -> 0 | X35: =ROUND(CY35,2) -> 0 | Y35: =ROUND(CZ35,2) -> 0 | AA35: 59213213 | AB35: =ROUND((AC35+AD35+AF35),6) -> 1803.04 | AC35: =ROUND((ES35),6) -> 1803.04 | AD35: =ROUND((((ET35)-(EU35))+AE35),6) -> 0 | AE35: =ROUND((EU35),6) -> 0 | AF35: =ROUND((EV35),6) -> 0 | AG35: =ROUND((AP35),6) -> 0 | AH35: =(EW35) -> 0 | AI35: =(EX35) -> 0 | AJ35: =(AS35) -> 0 | AK35: 1803.04 | AL35: 1803.04 | AM35: 0 | AN35: 0 | AO35: 0 | AP35: 0 | AQ35: 0 | AR35: 0 | AS35: 0 | AT35: 0 | AU35: 0 | AV35: 1 | AW35: 1 | AZ35: 1 | BA35: 1 | BB35: 1 | BC35: 7.66 | BH35: 3 | BI35: 3 | BM35: 746 | BN35: 0 | BP35: 0 | BQ35: 130 | BR35: 0 | BS35: 1 | BT35: 1 | BU35: 1 | BV35: 1 | BW35: 1 | BX35: 1 | BZ35: 0 | CA35: 0 | CE35: 30 | CF35: 0 | CG35: 0 | CM35: 0 | CO35: 0 | CP35: =(P35+Q35+S35) -> 165735.44 | CQ35: =ROUND((ROUND((AC35*1),2)*BC35),2) -> 13811.29 | CR35: =(ROUND((ROUND(((ET35)*AV35*1),2)*BB35),2)+ROUND((ROUND(((AE35-(EU35))*AV35*1),2)*BS35),2)) -> 0 | CS35: =ROUND((ROUND((AE35*AV35*1),2)*BS35),2) -> 0 | CT35: =ROUND((ROUND((AF35*AV35*1),2)*BA35),2) -> 0 | CU35: =AG35 -> 0 | CV35: =(AH35*AV35) -> 0 | CW35: =AI35 -> 0 | CX35: =AJ35 -> 0 | CY35: =(((S35+R35)*AT35)/100) -> 0 | CZ35: =(((S35+R35)*AU35)/100) -> 0 | DN35: 0 | DO35: 0 | DP35: 1 | DQ35: 1 | DU35: 1010 | DV35: шт. | DW35: шт. | DX35: 1 | EE35: 58808284 | EF35: 130 | EG35: Сметная стоимость оборудования | EH35: 0 | EJ35: 3 | EK35: 746 | EL35: ТСН-2001.13. Сметная стоимость оборудования | EM35: ТСН-2001.13 | EQ35: 0 | ER35: 1803.04 | ES35: 1803.04 | ET35: 0 | EU35: 0 | EV35: 0 | EW35: 0 | EX35: 0 | EY35: 0 | EZ35: 5 | FC35: 1 | FD35: 18 | FF35: 15900 | FQ35: 0 | FR35: =P35 -> 165735.44 | FS35: 0 | FX35: 0 | FY35: 0 | GA35: [15 900 / 1,2 / 7,66] + 3% Трансп + 1,2% Заг.скл | GD35: 1 | GF35: 1328923490 | GG35: 2 | GH35: 3 | GI35: 5 | GJ35: 0 | GK35: 0 | GL35: =ROUND(IF(AND(BH35=3,BI35=3,FS35<>0),P35,0),2) -> 0 | GM35: =ROUND(O35+X35+Y35,2)+GX35 -> 165735.44 | GN35: =IF(OR(BI35=0,BI35=1),GM35-GX35,0) -> 0 | GO35: =IF(BI35=2,GM35-GX35,0) -> 0 | GP35: =IF(BI35=4,GM35-GX35,0) -> 0 | GR35: 2 | GS35: 1 | GT35: 0 | GV35: =ROUND((GT35),6) -> 0 | GW35: 1 | GX35: =ROUND(HC35*I35,2) -> 0 | HA35: 0 | HB35: 0 | HC35: =GV35*GW35 -> 0 | HE35: 3 | HF35: 1,2 | HS35: 0 | IK35: 0
A36: 17 | B36: 1 | C36: =ROW(SmtRes!A11) -> 11 | D36: =ROW(EtalonRes!A13) -> 13 | E36: 5 | F36: 4.10-80-4 | G36: Аппараты приемные, приборы ПС приемно-контрольные, пусковые, прибор ПС на 4 луча | H36: 1 ШТ. | I36: =ROUND(ROUND(15,4),9) -> 15 | J36: 0 | K36: =ROUND(ROUND(15,4),9) -> 15 | O36: =ROUND(CP36,2) -> 872.27 | P36: =ROUND((ROUND((AC36*AW36*I36),2)*BC36),2) -> 96.6 | Q36: =(ROUND((ROUND((((ET36*1.1))*AV36*I36),2)*BB36),2)+ROUND((ROUND(((AE36-((EU36*1.1)))*AV36*I36),2)*BS36),2)) -> 2.07 | R36: =ROUND((ROUND((AE36*AV36*I36),2)*BS36),2) -> 0.17 | S36: =ROUND((ROUND((AF36*AV36*I36),2)*BA36),2) -> 773.6 | T36: =ROUND(CU36*I36,2) -> 0 | U36: =CV36*I36 -> 57.00915 | V36: =CW36*I36 -> 0 | W36: =ROUND(CX36*I36,2) -> 0 | X36: =ROUND(CY36,2) -> 696.39 | Y36: =ROUND(CZ36,2) -> 355.93 | AA36: 59213216 | AB36: =ROUND((AC36+AD36+AF36),6) -> 55.83 | AC36: =ROUND(((ES36*1)),6) -> 6.44 | AD36: =ROUND(((((ET36*1.1))-((EU36*1.1)))+AE36),6) -> 0.132 | AE36: =ROUND(((EU36*1.1)),6) -> 0.011 | AF36: =ROUND(((EV36*1.1)),6) -> 49.258 | AG36: =ROUND((AP36),6) -> 0 | AH36: =((EW36*1.1)) -> 3.63 | AI36: =((EX36*1.1)) -> 0 | AJ36: =(AS36) -> 0 | AK36: 51.34 | AL36: 6.44 | AM36: 0.12 | AN36: 0.01 | AO36: 44.78 | AP36: 0 | AQ36: 3.3 | AR36: 0 | AS36: 0 | AT36: 90 | AU36: 46 | AV36: 1.047 | AW36: 1 | AZ36: 1 | BA36: 1 | BB36: 1 | BC36: 1 | BH36: 0 | BI36: 2 | BJ36: ТСН-2001.4. Доп. 1-42. Сб. 10, т. 80, поз. 4 | BM36: 68 | BN36: 58808062 | BO36: 4.10-80-4 | BP36: 1 | BQ36: 40 | BR36: 0 | BS36: 1 | BT36: 1 | BU36: 1 | BV36: 1 | BW36: 1 | BX36: 1 | BZ36: 90 | CA36: 46 | CE36: 30 | CF36: 0 | CG36: 0 | CM36: 0 | CN36: Поправка: Гл.12.Прил.8.п.8. 5_12.00.01.11.003 Наименование: При наличии усложненных условий производства работ (стесненность, сложность складирования и транспортной логистики, наличие в зоне производства работ действующего технологического оборудования или движения технологического транспорта и т.п.) для объектов, расположенных за пределами территории круговой магистральной системы улиц "Садовое кольцо" и за пределами Третьего транспортного кольца города Москвы пунктов "а" и "б", но в пределах Московской кольцевой автомобильной дороги | CO36: 0 | CP36: =(P36+Q36+S36) -> 872.27 | CQ36: =ROUND((ROUND((AC36*AW36*1),2)*BC36),2) -> 6.44 | CR36: =(ROUND((ROUND((((ET36*1.1))*AV36*1),2)*BB36),2)+ROUND((ROUND(((AE36-((EU36*1.1)))*AV36*1),2)*BS36),2)) -> 0.14 | CS36: =ROUND((ROUND((AE36*AV36*1),2)*BS36),2) -> 0.01 | CT36: =ROUND((ROUND((AF36*AV36*1),2)*BA36),2) -> 51.57 | CU36: =AG36 -> 0 | CV36: =(AH36*AV36) -> 3.80061 | CW36: =AI36 -> 0 | CX36: =AJ36 -> 0 | CY36: =(((S36+R36)*AT36)/100) -> 696.393 | CZ36: =(((S36+R36)*AU36)/100) -> 355.9342 | DB36: 5 | DD36: *1 | DE36: *1,1 | DF36: *1,1 | DG36: *1,1 | DI36: *1,1 | DJ36: *1,1 | DN36: 0 | DO36: 0 | DP36: 1 | DQ36: 1 | DU36: 1013 | DV36: 1 ШТ. | DW36: 1 ШТ. | DX36: 1 | EE36: 58808178 | EF36: 40 | EG36: Монтаж оборудования | EH36: 0 | EJ36: 2 | EK36: 68 | EL36: ТСН-2001.4-10. Прокладка и монтаж сетей связи | EM36: ТСН-2001.4-10-1 | EO36: Поправка: Гл.12.Прил.8.п.8. 5_12.00.01.11.003 | EQ36: 0 | ER36: 51.34 | ES36: 6.44 | ET36: 0.12 | EU36: 0.01 | EV36: 44.78 | EW36: 3.3 | EX36: 0 | EY36: 0 | FQ36: 0 | FR36: 0 | FS36: 0 | FX36: 90 | FY36: 46 | GD36: 1 | GF36: -1862862500 | GG36: 2 | GH36: 1 | GI36: 2 | GJ36: 0 | GK36: 0 | GL36: =ROUND(IF(AND(BH36=3,BI36=3,FS36<>0),P36,0),2) -> 0 | GM36: =ROUND(O36+X36+Y36,2)+GX36 -> 1924.59 | GN36: =IF(OR(BI36=0,BI36=1),GM36-GX36,0) -> 0 | GO36: =IF(BI36=2,GM36-GX36,0) -> 1924.59 | GP36: =IF(BI36=4,GM36-GX36,0) -> 0 | GR36: 0 | GS36: 3 | GT36: 0 | GV36: =ROUND((GT36),6) -> 0 | GW36: 1 | GX36: =ROUND(HC36*I36,2) -> 0 | HA36: 0 | HB36: 0 | HC36: =GV36*GW36 -> 0 | HS36: 0 | IK36: 0
A37: 17 | B37: 1 | C37: =ROW(SmtRes!A12) -> 12 | D37: =ROW(EtalonRes!A14) -> 14 | E37: 5 | F37: 4.10-80-4 | G37: Аппараты приемные, приборы ПС приемно-контрольные, пусковые, прибор ПС на 4 луча | H37: 1 ШТ. | I37: =ROUND(ROUND(15,4),9) -> 15 | J37: 0 | K37: =ROUND(ROUND(15,4),9) -> 15 | O37: =ROUND(CP37,2) -> 43524.09 | P37: =ROUND((ROUND((AC37*AW37*I37),2)*BC37),2) -> 955.37 | Q37: =(ROUND((ROUND((((ET37*1.1))*AV37*I37),2)*BB37),2)+ROUND((ROUND(((AE37-((EU37*1.1)))*AV37*I37),2)*BS37),2)) -> 28.46 | R37: =ROUND((ROUND((AE37*AV37*I37),2)*BS37),2) -> 9.35 | S37: =ROUND((ROUND((AF37*AV37*I37),2)*BA37),2) -> 42540.26 | T37: =ROUND(CU37*I37,2) -> 0 | U37: =CV37*I37 -> 57.00915 | V37: =CW37*I37 -> 0 | W37: =ROUND(CX37*I37,2) -> 0 | X37: =ROUND(CY37,2) -> 38294.65 | Y37: =ROUND(CZ37,2) -> 19572.82 | AA37: 59213213 | AB37: =ROUND((AC37+AD37+AF37),6) -> 55.83 | AC37: =ROUND(((ES37*1)),6) -> 6.44 | AD37: =ROUND(((((ET37*1.1))-((EU37*1.1)))+AE37),6) -> 0.132 | AE37: =ROUND(((EU37*1.1)),6) -> 0.011 | AF37: =ROUND(((EV37*1.1)),6) -> 49.258 | AG37: =ROUND((AP37),6) -> 0 | AH37: =((EW37*1.1)) -> 3.63 | AI37: =((EX37*1.1)) -> 0 | AJ37: =(AS37) -> 0 | AK37: 51.34 | AL37: 6.44 | AM37: 0.12 | AN37: 0.01 | AO37: 44.78 | AP37: 0 | AQ37: 3.3 | AR37: 0 | AS37: 0 | AT37: 90 | AU37: 46 | AV37: 1.047 | AW37: 1 | AZ37: 1 | BA37: 54.99 | BB37: 13.75 | BC37: 9.89 | BH37: 0 | BI37: 2 | BJ37: ТСН-2001.4. Доп. 1-42. Сб. 10, т. 80, поз. 4 | BM37: 68 | BN37: 58808062 | BO37: 4.10-80-4 | BP37: 1 | BQ37: 40 | BR37: 0 | BS37: 54.99 | BT37: 1 | BU37: 1 | BV37: 1 | BW37: 1 | BX37: 1 | BZ37: 90 | CA37: 46 | CE37: 30 | CF37: 0 | CG37: 0 | CM37: 0 | CN37: Поправка: Гл.12.Прил.8.п.8. 5_12.00.01.11.003 Наименование: При наличии усложненных условий производства работ (стесненность, сложность складирования и транспортной логистики, наличие в зоне производства работ действующего технологического оборудования или движения технологического транспорта и т.п.) для объектов, расположенных за пределами территории круговой магистральной системы улиц "Садовое кольцо" и за пределами Третьего транспортного кольца города Москвы пунктов "а" и "б", но в пределах Московской кольцевой автомобильной дороги | CO37: 0 | CP37: =(P37+Q37+S37) -> 43524.09 | CQ37: =ROUND((ROUND((AC37*AW37*1),2)*BC37),2) -> 63.69 | CR37: =(ROUND((ROUND((((ET37*1.1))*AV37*1),2)*BB37),2)+ROUND((ROUND(((AE37-((EU37*1.1)))*AV37*1),2)*BS37),2)) -> 1.93 | CS37: =ROUND((ROUND((AE37*AV37*1),2)*BS37),2) -> 0.55 | CT37: =ROUND((ROUND((AF37*AV37*1),2)*BA37),2) -> 2835.83 | CU37: =AG37 -> 0 | CV37: =(AH37*AV37) -> 3.80061 | CW37: =AI37 -> 0 | CX37: =AJ37 -> 0 | CY37: =(((S37+R37)*AT37)/100) -> 38294.649 | CZ37: =(((S37+R37)*AU37)/100) -> 19572.821 | DB37: 6 | DD37: *1 | DE37: *1,1 | DF37: *1,1 | DG37: *1,1 | DI37: *1,1 | DJ37: *1,1 | DN37: 0 | DO37: 0 | DP37: 1 | DQ37: 1 | DU37: 1013 | DV37: 1 ШТ. | DW37: 1 ШТ. | DX37: 1 | EE37: 58808178 | EF37: 40 | EG37: Монтаж оборудования | EH37: 0 | EJ37: 2 | EK37: 68 | EL37: ТСН-2001.4-10. Прокладка и монтаж сетей связи | EM37: ТСН-2001.4-10-1 | EO37: Поправка: Гл.12.Прил.8.п.8. 5_12.00.01.11.003 | EQ37: 0 | ER37: 51.34 | ES37: 6.44 | ET37: 0.12 | EU37: 0.01 | EV37: 44.78 | EW37: 3.3 | EX37: 0 | EY37: 0 | FQ37: 0 | FR37: 0 | FS37: 0 | FX37: 90 | FY37: 46 | GD37: 1 | GF37: -1862862500 | GG37: 2 | GH37: 1 | GI37: 2 | GJ37: 0 | GK37: 0 | GL37: =ROUND(IF(AND(BH37=3,BI37=3,FS37<>0),P37,0),2) -> 0 | GM37: =ROUND(O37+X37+Y37,2)+GX37 -> 101391.56 | GN37: =IF(OR(BI37=0,BI37=1),GM37-GX37,0) -> 0 | GO37: =IF(BI37=2,GM37-GX37,0) -> 101391.56 | GP37: =IF(BI37=4,GM37-GX37,0) -> 0 | GR37: 0 | GS37: 3 | GT37: 0 | GV37: =ROUND((GT37),6) -> 0 | GW37: 1 | GX37: =ROUND(HC37*I37,2) -> 0 | HA37: 0 | HB37: 0 | HC37: =GV37*GW37 -> 0 | HS37: 0 | IK37: 0
A38: 17 | B38: 1 | E38: 6 | F38: КА 3 | G38: Модуль доступа-контроллер доступа STR-2AP-M на 4 точки | H38: шт. | I38: =ROUND(ROUND(15,4),9) -> 15 | J38: 0 | K38: =ROUND(ROUND(15,4),9) -> 15 | O38: =ROUND(CP38,2) -> 111142.05 | P38: =ROUND((ROUND((AC38*I38),2)*BC38),2) -> 111142.05 | Q38: =(ROUND((ROUND(((ET38)*AV38*I38),2)*BB38),2)+ROUND((ROUND(((AE38-(EU38))*AV38*I38),2)*BS38),2)) -> 0 | R38: =ROUND((ROUND((AE38*AV38*I38),2)*BS38),2) -> 0 | S38: =ROUND((ROUND((AF38*AV38*I38),2)*BA38),2) -> 0 | T38: =ROUND(CU38*I38,2) -> 0 | U38: =CV38*I38 -> 0 | V38: =CW38*I38 -> 0 | W38: =ROUND(CX38*I38,2) -> 0 | X38: =ROUND(CY38,2) -> 0 | Y38: =ROUND(CZ38,2) -> 0 | AA38: 59213216 | AB38: =ROUND((AC38+AD38+AF38),6) -> 7409.47 | AC38: =ROUND((ES38),6) -> 7409.47 | AD38: =ROUND((((ET38)-(EU38))+AE38),6) -> 0 | AE38: =ROUND((EU38),6) -> 0 | AF38: =ROUND((EV38),6) -> 0 | AG38: =ROUND((AP38),6) -> 0 | AH38: =(EW38) -> 0 | AI38: =(EX38) -> 0 | AJ38: =(AS38) -> 0 | AK38: 7409.47 | AL38: 7409.47 | AM38: 0 | AN38: 0 | AO38: 0 | AP38: 0 | AQ38: 0 | AR38: 0 | AS38: 0 | AT38: 0 | AU38: 0 | AV38: 1 | AW38: 1 | AZ38: 1 | BA38: 1 | BB38: 1 | BC38: 1 | BH38: 3 | BI38: 3 | BM38: 746 | BN38: 0 | BP38: 0 | BQ38: 130 | BR38: 0 | BS38: 1 | BT38: 1 | BU38: 1 | BV38: 1 | BW38: 1 | BX38: 1 | BZ38: 0 | CA38: 0 | CE38: 30 | CF38: 0 | CG38: 0 | CM38: 0 | CO38: 0 | CP38: =(P38+Q38+S38) -> 111142.05 | CQ38: =ROUND((ROUND((AC38*1),2)*BC38),2) -> 7409.47 | CR38: =(ROUND((ROUND(((ET38)*AV38*1),2)*BB38),2)+ROUND((ROUND(((AE38-(EU38))*AV38*1),2)*BS38),2)) -> 0 | CS38: =ROUND((ROUND((AE38*AV38*1),2)*BS38),2) -> 0 | CT38: =ROUND((ROUND((AF38*AV38*1),2)*BA38),2) -> 0 | CU38: =AG38 -> 0 | CV38: =(AH38*AV38) -> 0 | CW38: =AI38 -> 0 | CX38: =AJ38 -> 0 | CY38: =(((S38+R38)*AT38)/100) -> 0 | CZ38: =(((S38+R38)*AU38)/100) -> 0 | DN38: 0 | DO38: 0 | DP38: 1 | DQ38: 1 | DU38: 1010 | DV38: шт. | DW38: шт. | DX38: 1 | EE38: 58808284 | EF38: 130 | EG38: Сметная стоимость оборудования | EH38: 0 | EJ38: 3 | EK38: 746 | EL38: ТСН-2001.13. Сметная стоимость оборудования | EM38: ТСН-2001.13 | EQ38: 0 | ER38: 0 | ES38: 7409.47 | ET38: 0 | EU38: 0 | EV38: 0 | EW38: 0 | EX38: 0 | EY38: 0 | FQ38: 0 | FR38: =P38 -> 111142.05 | FS38: 0 | FX38: 0 | FY38: 0 | GA38: [65 340 / 1,2 / 7,66] + 3% Трансп + 1,2% Заг.скл | GD38: 1 | GF38: -1498015221 | GG38: 2 | GH38: 4 | GI38: 0 | GJ38: 0 | GK38: 0 | GL38: =ROUND(IF(AND(BH38=3,BI38=3,FS38<>0),P38,0),2) -> 0 | GM38: =ROUND(O38+X38+Y38,2)+GX38 -> 111142.05 | GN38: =IF(OR(BI38=0,BI38=1),GM38-GX38,0) -> 0 | GO38: =IF(BI38=2,GM38-GX38,0) -> 0 | GP38: =IF(BI38=4,GM38-GX38,0) -> 0 | GR38: 0 | GS38: 2 | GT38: 0 | GV38: =ROUND((GT38),6) -> 0 | GW38: 1 | GX38: =ROUND(HC38*I38,2) -> 0 | HA38: 0 | HB38: 0 | HC38: =GV38*GW38 -> 0 | HE38: 3 | HF38: 1,2 | HS38: 0 | IK38: 0
A39: 17 | B39: 1 | E39: 6 | F39: КА 3 | G39: Модуль доступа-контроллер доступа STR-2AP-M на 4 точки | H39: шт. | I39: =ROUND(ROUND(15,4),9) -> 15 | J39: 0 | K39: =ROUND(ROUND(15,4),9) -> 15 | O39: =ROUND(CP39,2) -> 851348.1 | P39: =ROUND((ROUND((AC39*I39),2)*BC39),2) -> 851348.1 | Q39: =(ROUND((ROUND(((ET39)*AV39*I39),2)*BB39),2)+ROUND((ROUND(((AE39-(EU39))*AV39*I39),2)*BS39),2)) -> 0 | R39: =ROUND((ROUND((AE39*AV39*I39),2)*BS39),2) -> 0 | S39: =ROUND((ROUND((AF39*AV39*I39),2)*BA39),2) -> 0 | T39: =ROUND(CU39*I39,2) -> 0 | U39: =CV39*I39 -> 0 | V39: =CW39*I39 -> 0 | W39: =ROUND(CX39*I39,2) -> 0 | X39: =ROUND(CY39,2) -> 0 | Y39: =ROUND(CZ39,2) -> 0 | AA39: 59213213 | AB39: =ROUND((AC39+AD39+AF39),6) -> 7409.47 | AC39: =ROUND((ES39),6) -> 7409.47 | AD39: =ROUND((((ET39)-(EU39))+AE39),6) -> 0 | AE39: =ROUND((EU39),6) -> 0 | AF39: =ROUND((EV39),6) -> 0 | AG39: =ROUND((AP39),6) -> 0 | AH39: =(EW39) -> 0 | AI39: =(EX39) -> 0 | AJ39: =(AS39) -> 0 | AK39: 7409.47 | AL39: 7409.47 | AM39: 0 | AN39: 0 | AO39: 0 | AP39: 0 | AQ39: 0 | AR39: 0 | AS39: 0 | AT39: 0 | AU39: 0 | AV39: 1 | AW39: 1 | AZ39: 1 | BA39: 1 | BB39: 1 | BC39: 7.66 | BH39: 3 | BI39: 3 | BM39: 746 | BN39: 0 | BP39: 0 | BQ39: 130 | BR39: 0 | BS39: 1 | BT39: 1 | BU39: 1 | BV39: 1 | BW39: 1 | BX39: 1 | BZ39: 0 | CA39: 0 | CE39: 30 | CF39: 0 | CG39: 0 | CM39: 0 | CO39: 0 | CP39: =(P39+Q39+S39) -> 851348.1 | CQ39: =ROUND((ROUND((AC39*1),2)*BC39),2) -> 56756.54 | CR39: =(ROUND((ROUND(((ET39)*AV39*1),2)*BB39),2)+ROUND((ROUND(((AE39-(EU39))*AV39*1),2)*BS39),2)) -> 0 | CS39: =ROUND((ROUND((AE39*AV39*1),2)*BS39),2) -> 0 | CT39: =ROUND((ROUND((AF39*AV39*1),2)*BA39),2) -> 0 | CU39: =AG39 -> 0 | CV39: =(AH39*AV39) -> 0 | CW39: =AI39 -> 0 | CX39: =AJ39 -> 0 | CY39: =(((S39+R39)*AT39)/100) -> 0 | CZ39: =(((S39+R39)*AU39)/100) -> 0 | DN39: 0 | DO39: 0 | DP39: 1 | DQ39: 1 | DU39: 1010 | DV39: шт. | DW39: шт. | DX39: 1 | EE39: 58808284 | EF39: 130 | EG39: Сметная стоимость оборудования | EH39: 0 | EJ39: 3 | EK39: 746 | EL39: ТСН-2001.13. Сметная стоимость оборудования | EM39: ТСН-2001.13 | EQ39: 0 | ER39: 7409.47 | ES39: 7409.47 | ET39: 0 | EU39: 0 | EV39: 0 | EW39: 0 | EX39: 0 | EY39: 0 | EZ39: 5 | FC39: 1 | FD39: 18 | FF39: 65340 | FQ39: 0 | FR39: =P39 -> 851348.1 | FS39: 0 | FX39: 0 | FY39: 0 | GA39: [65 340 / 1,2 / 7,66] + 3% Трансп + 1,2% Заг.скл | GD39: 1 | GF39: -1498015221 | GG39: 2 | GH39: 3 | GI39: 5 | GJ39: 0 | GK39: 0 | GL39: =ROUND(IF(AND(BH39=3,BI39=3,FS39<>0),P39,0),2) -> 0 | GM39: =ROUND(O39+X39+Y39,2)+GX39 -> 851348.1 | GN39: =IF(OR(BI39=0,BI39=1),GM39-GX39,0) -> 0 | GO39: =IF(BI39=2,GM39-GX39,0) -> 0 | GP39: =IF(BI39=4,GM39-GX39,0) -> 0 | GR39: 2 | GS39: 1 | GT39: 0 | GV39: =ROUND((GT39),6) -> 0 | GW39: 1 | GX39: =ROUND(HC39*I39,2) -> 0 | HA39: 0 | HB39: 0 | HC39: =GV39*GW39 -> 0 | HE39: 3 | HF39: 1,2 | HS39: 0 | IK39: 0
A40: 17 | B40: 1 | C40: =ROW(SmtRes!A28) -> 28 | D40: =ROW(EtalonRes!A31) -> 31 | E40: 7 | F40: 4.11-1-2 | G40: Монтаж конструкции для установки приборов и средств автоматизации массой до 2 кг | H40: 1 ШТ. | I40: =ROUND(ROUND(27,4),9) -> 27 | J40: 0 | K40: =ROUND(ROUND(27,4),9) -> 27 | O40: =ROUND(CP40,2) -> 1200.41 | P40: =ROUND((ROUND((AC40*AW40*I40),2)*BC40),2) -> 960.66 | Q40: =(ROUND((ROUND((((ET40*1.1))*AV40*I40),2)*BB40),2)+ROUND((ROUND(((AE40-((EU40*1.1)))*AV40*I40),2)*BS40),2)) -> 54.73 | R40: =ROUND((ROUND((AE40*AV40*I40),2)*BS40),2) -> 11.51 | S40: =ROUND((ROUND((AF40*AV40*I40),2)*BA40),2) -> 185.02 | T40: =ROUND(CU40*I40,2) -> 0 | U40: =CV40*I40 -> 16.169868 | V40: =CW40*I40 -> 0 | W40: =ROUND(CX40*I40,2) -> 0 | X40: =ROUND(CY40,2) -> 176.88 | Y40: =ROUND(CZ40,2) -> 90.4 | AA40: 59213216 | AB40: =ROUND((AC40+AD40+AF40),6) -> 44.061 | AC40: =ROUND(((ES40*1)),6) -> 35.58 | AD40: =ROUND(((((ET40*1.1))-((EU40*1.1)))+AE40),6) -> 1.936 | AE40: =ROUND(((EU40*1.1)),6) -> 0.407 | AF40: =ROUND(((EV40*1.1)),6) -> 6.545 | AG40: =ROUND((AP40),6) -> 0 | AH40: =((EW40*1.1)) -> 0.572 | AI40: =((EX40*1.1)) -> 0 | AJ40: =(AS40) -> 0 | AK40: 43.29 | AL40: 35.58 | AM40: 1.76 | AN40: 0.37 | AO40: 5.95 | AP40: 0 | AQ40: 0.52 | AR40: 0 | AS40: 0 | AT40: 90 | AU40: 46 | AV40: 1.047 | AW40: 1 | AZ40: 1 | BA40: 1 | BB40: 1 | BC40: 1 | BH40: 0 | BI40: 2 | BJ40: ТСН-2001.4 Доп. 80, Сб. 11, т. 1, поз. 2 | BM40: 72 | BN40: 58808062 | BO40: 4.11-1-2 | BP40: 1 | BQ40: 40 | BR40: 0 | BS40: 1 | BT40: 1 | BU40: 1 | BV40: 1 | BW40: 1 | BX40: 1 | BZ40: 90 | CA40: 46 | CE40: 30 | CF40: 0 | CG40: 0 | CM40: 0 | CN40: Поправка: Гл.12.Прил.8.п.8. 5_12.00.01.11.003 Наименование: При наличии усложненных условий производства работ (стесненность, сложность складирования и транспортной логистики, наличие в зоне производства работ действующего технологического оборудования или движения технологического транспорта и т.п.) для объектов, расположенных за пределами территории круговой магистральной системы улиц "Садовое кольцо" и за пределами Третьего транспортного кольца города Москвы пунктов "а" и "б", но в пределах Московской кольцевой автомобильной дороги | CO40: 0 | CP40: =(P40+Q40+S40) -> 1200.41 | CQ40: =ROUND((ROUND((AC40*AW40*1),2)*BC40),2) -> 35.58 | CR40: =(ROUND((ROUND((((ET40*1.1))*AV40*1),2)*BB40),2)+ROUND((ROUND(((AE40-((EU40*1.1)))*AV40*1),2)*BS40),2)) -> 2.03 | CS40: =ROUND((ROUND((AE40*AV40*1),2)*BS40),2) -> 0.43 | CT40: =ROUND((ROUND((AF40*AV40*1),2)*BA40),2) -> 6.85 | CU40: =AG40 -> 0 | CV40: =(AH40*AV40) -> 0.598884 | CW40: =AI40 -> 0 | CX40: =AJ40 -> 0 | CY40: =(((S40+R40)*AT40)/100) -> 176.877 | CZ40: =(((S40+R40)*AU40)/100) -> 90.4038 | DB40: 7 | DD40: *1 | DE40: *1,1 | DF40: *1,1 | DG40: *1,1 | DI40: *1,1 | DJ40: *1,1 | DN40: 0 | DO40: 0 | DP40: 1 | DQ40: 1 | DU40: 1013 | DV40: 1 ШТ. | DW40: 1 ШТ. | DX40: 1 | EE40: 58808182 | EF40: 40 | EG40: Монтаж оборудования | EH40: 0 | EJ40: 2 | EK40: 72 | EL40: ТСН-2001.4-11. Приборы и средства автоматизации и вычислительной техники | EM40: ТСН-2001.4-11-1 | EO40: Поправка: Гл.12.Прил.8.п.8. 5_12.00.01.11.003 | EQ40: 0 | ER40: 43.29 | ES40: 35.58 | ET40: 1.76 | EU40: 0.37 | EV40: 5.95 | EW40: 0.52 | EX40: 0 | EY40: 0 | FQ40: 0 | FR40: 0 | FS40: 0 | FX40: 90 | FY40: 46 | GD40: 1 | GF40: -1951604615 | GG40: 2 | GH40: 1 | GI40: 2 | GJ40: 0 | GK40: 0 | GL40: =ROUND(IF(AND(BH40=3,BI40=3,FS40<>0),P40,0),2) -> 0 | GM40: =ROUND(O40+X40+Y40,2)+GX40 -> 1467.69 | GN40: =IF(OR(BI40=0,BI40=1),GM40-GX40,0) -> 0 | GO40: =IF(BI40=2,GM40-GX40,0) -> 1467.69 | GP40: =IF(BI40=4,GM40-GX40,0) -> 0 | GR40: 0 | GS40: 3 | GT40: 0 | GV40: =ROUND((GT40),6) -> 0 | GW40: 1 | GX40: =ROUND(HC40*I40,2) -> 0 | HA40: 0 | HB40: 0 | HC40: =GV40*GW40 -> 0 | HS40: 0 | IK40: 0
A41: 17 | B41: 1 | C41: =ROW(SmtRes!A44) -> 44 | D41: =ROW(EtalonRes!A48) -> 48 | E41: 7 | F41: 4.11-1-2 | G41: Монтаж конструкции для установки приборов и средств автоматизации массой до 2 кг | H41: 1 ШТ. | I41: =ROUND(ROUND(27,4),9) -> 27 | J41: 0 | K41: =ROUND(ROUND(27,4),9) -> 27 | O41: =ROUND(CP41,2) -> 21637.84 | P41: =ROUND((ROUND((AC41*AW41*I41),2)*BC41),2) -> 10336.7 | Q41: =(ROUND((ROUND((((ET41*1.1))*AV41*I41),2)*BB41),2)+ROUND((ROUND(((AE41-((EU41*1.1)))*AV41*I41),2)*BS41),2)) -> 1126.89 | R41: =ROUND((ROUND((AE41*AV41*I41),2)*BS41),2) -> 632.93 | S41: =ROUND((ROUND((AF41*AV41*I41),2)*BA41),2) -> 10174.25 | T41: =ROUND(CU41*I41,2) -> 0 | U41: =CV41*I41 -> 16.169868 | V41: =CW41*I41 -> 0 | W41: =ROUND(CX41*I41,2) -> 0 | X41: =ROUND(CY41,2) -> 9726.46 | Y41: =ROUND(CZ41,2) -> 4971.3 | AA41: 59213213 | AB41: =ROUND((AC41+AD41+AF41),6) -> 44.061 | AC41: =ROUND(((ES41*1)),6) -> 35.58 | AD41: =ROUND(((((ET41*1.1))-((EU41*1.1)))+AE41),6) -> 1.936 | AE41: =ROUND(((EU41*1.1)),6) -> 0.407 | AF41: =ROUND(((EV41*1.1)),6) -> 6.545 | AG41: =ROUND((AP41),6) -> 0 | AH41: =((EW41*1.1)) -> 0.572 | AI41: =((EX41*1.1)) -> 0 | AJ41: =(AS41) -> 0 | AK41: 43.29 | AL41: 35.58 | AM41: 1.76 | AN41: 0.37 | AO41: 5.95 | AP41: 0 | AQ41: 0.52 | AR41: 0 | AS41: 0 | AT41: 90 | AU41: 46 | AV41: 1.047 | AW41: 1 | AZ41: 1 | BA41: 54.99 | BB41: 20.59 | BC41: 10.76 | BH41: 0 | BI41: 2 | BJ41: ТСН-2001.4 Доп. 80, Сб. 11, т. 1, поз. 2 | BM41: 72 | BN41: 58808062 | BO41: 4.11-1-2 | BP41: 1 | BQ41: 40 | BR41: 0 | BS41: 54.99 | BT41: 1 | BU41: 1 | BV41: 1 | BW41: 1 | BX41: 1 | BZ41: 90 | CA41: 46 | CE41: 30 | CF41: 0 | CG41: 0 | CM41: 0 | CN41: Поправка: Гл.12.Прил.8.п.8. 5_12.00.01.11.003 Наименование: При наличии усложненных условий производства работ (стесненность, сложность складирования и транспортной логистики, наличие в зоне производства работ действующего технологического оборудования или движения технологического транспорта и т.п.) для объектов, расположенных за пределами территории круговой магистральной системы улиц "Садовое кольцо" и за пределами Третьего транспортного кольца города Москвы пунктов "а" и "б", но в пределах Московской кольцевой автомобильной дороги | CO41: 0 | CP41: =(P41+Q41+S41) -> 21637.84 | CQ41: =ROUND((ROUND((AC41*AW41*1),2)*BC41),2) -> 382.84 | CR41: =(ROUND((ROUND((((ET41*1.1))*AV41*1),2)*BB41),2)+ROUND((ROUND(((AE41-((EU41*1.1)))*AV41*1),2)*BS41),2)) -> 41.8 | CS41: =ROUND((ROUND((AE41*AV41*1),2)*BS41),2) -> 23.65 | CT41: =ROUND((ROUND((AF41*AV41*1),2)*BA41),2) -> 376.68 | CU41: =AG41 -> 0 | CV41: =(AH41*AV41) -> 0.598884 | CW41: =AI41 -> 0 | CX41: =AJ41 -> 0 | CY41: =(((S41+R41)*AT41)/100) -> 9726.462 | CZ41: =(((S41+R41)*AU41)/100) -> 4971.3028 | DB41: 8 | DD41: *1 | DE41: *1,1 | DF41: *1,1 | DG41: *1,1 | DI41: *1,1 | DJ41: *1,1 | DN41: 0 | DO41: 0 | DP41: 1 | DQ41: 1 | DU41: 1013 | DV41: 1 ШТ. | DW41: 1 ШТ. | DX41: 1 | EE41: 58808182 | EF41: 40 | EG41: Монтаж оборудования | EH41: 0 | EJ41: 2 | EK41: 72 | EL41: ТСН-2001.4-11. Приборы и средства автоматизации и вычислительной техники | EM41: ТСН-2001.4-11-1 | EO41: Поправка: Гл.12.Прил.8.п.8. 5_12.00.01.11.003 | EQ41: 0 | ER41: 43.29 | ES41: 35.58 | ET41: 1.76 | EU41: 0.37 | EV41: 5.95 | EW41: 0.52 | EX41: 0 | EY41: 0 | FQ41: 0 | FR41: 0 | FS41: 0 | FX41: 90 | FY41: 46 | GD41: 1 | GF41: -1951604615 | GG41: 2 | GH41: 1 | GI41: 2 | GJ41: 0 | GK41: 0 | GL41: =ROUND(IF(AND(BH41=3,BI41=3,FS41<>0),P41,0),2) -> 0 | GM41: =ROUND(O41+X41+Y41,2)+GX41 -> 36335.6 | GN41: =IF(OR(BI41=0,BI41=1),GM41-GX41,0) -> 0 | GO41: =IF(BI41=2,GM41-GX41,0) -> 36335.6 | GP41: =IF(BI41=4,GM41-GX41,0) -> 0 | GR41: 0 | GS41: 3 | GT41: 0 | GV41: =ROUND((GT41),6) -> 0 | GW41: 1 | GX41: =ROUND(HC41*I41,2) -> 0 | HA41: 0 | HB41: 0 | HC41: =GV41*GW41 -> 0 | HS41: 0 | IK41: 0
A42: 17 | B42: 1 | E42: 8 | F42: КА 4 | G42: Электромагнитный замок с монтажным комплектом "AL-400 Premium " | H42: шт. | I42: =ROUND(ROUND(27,4),9) -> 27 | J42: 0 | K42: =ROUND(ROUND(27,4),9) -> 27 | O42: =ROUND(CP42,2) -> 43427.88 | P42: =ROUND((ROUND((AC42*I42),2)*BC42),2) -> 43427.88 | Q42: =(ROUND((ROUND(((ET42)*AV42*I42),2)*BB42),2)+ROUND((ROUND(((AE42-(EU42))*AV42*I42),2)*BS42),2)) -> 0 | R42: =ROUND((ROUND((AE42*AV42*I42),2)*BS42),2) -> 0 | S42: =ROUND((ROUND((AF42*AV42*I42),2)*BA42),2) -> 0 | T42: =ROUND(CU42*I42,2) -> 0 | U42: =CV42*I42 -> 0 | V42: =CW42*I42 -> 0 | W42: =ROUND(CX42*I42,2) -> 0 | X42: =ROUND(CY42,2) -> 0 | Y42: =ROUND(CZ42,2) -> 0 | AA42: 59213216 | AB42: =ROUND((AC42+AD42+AF42),6) -> 1608.44 | AC42: =ROUND((ES42),6) -> 1608.44 | AD42: =ROUND((((ET42)-(EU42))+AE42),6) -> 0 | AE42: =ROUND((EU42),6) -> 0 | AF42: =ROUND((EV42),6) -> 0 | AG42: =ROUND((AP42),6) -> 0 | AH42: =(EW42) -> 0 | AI42: =(EX42) -> 0 | AJ42: =(AS42) -> 0 | AK42: 1608.44 | AL42: 1608.44 | AM42: 0 | AN42: 0 | AO42: 0 | AP42: 0 | AQ42: 0 | AR42: 0 | AS42: 0 | AT42: 0 | AU42: 0 | AV42: 1 | AW42: 1 | AZ42: 1 | BA42: 1 | BB42: 1 | BC42: 1 | BH42: 3 | BI42: 3 | BM42: 746 | BN42: 0 | BP42: 0 | BQ42: 130 | BR42: 0 | BS42: 1 | BT42: 1 | BU42: 1 | BV42: 1 | BW42: 1 | BX42: 1 | BZ42: 0 | CA42: 0 | CE42: 30 | CF42: 0 | CG42: 0 | CM42: 0 | CO42: 0 | CP42: =(P42+Q42+S42) -> 43427.88 | CQ42: =ROUND((ROUND((AC42*1),2)*BC42),2) -> 1608.44 | CR42: =(ROUND((ROUND(((ET42)*AV42*1),2)*BB42),2)+ROUND((ROUND(((AE42-(EU42))*AV42*1),2)*BS42),2)) -> 0 | CS42: =ROUND((ROUND((AE42*AV42*1),2)*BS42),2) -> 0 | CT42: =ROUND((ROUND((AF42*AV42*1),2)*BA42),2) -> 0 | CU42: =AG42 -> 0 | CV42: =(AH42*AV42) -> 0 | CW42: =AI42 -> 0 | CX42: =AJ42 -> 0 | CY42: =(((S42+R42)*AT42)/100) -> 0 | CZ42: =(((S42+R42)*AU42)/100) -> 0 | DN42: 0 | DO42: 0 | DP42: 1 | DQ42: 1 | DU42: 1010 | DV42: шт. | DW42: шт. | DX42: 1 | EE42: 58808284 | EF42: 130 | EG42: Сметная стоимость оборудования | EH42: 0 | EJ42: 3 | EK42: 746 | EL42: ТСН-2001.13. Сметная стоимость оборудования | EM42: ТСН-2001.13 | EQ42: 0 | ER42: 0 | ES42: 1608.44 | ET42: 0 | EU42: 0 | EV42: 0 | EW42: 0 | EX42: 0 | EY42: 0 | FQ42: 0 | FR42: =P42 -> 43427.88 | FS42: 0 | FX42: 0 | FY42: 0 | GA42: [14 184 / 1,2 / 7,66] + 3% Трансп + 1,2% Заг.скл | GD42: 1 | GF42: 17706835 | GG42: 2 | GH42: 4 | GI42: -2 | GJ42: 0 | GK42: 0 | GL42: =ROUND(IF(AND(BH42=3,BI42=3,FS42<>0),P42,0),2) -> 0 | GM42: =ROUND(O42+X42+Y42,2)+GX42 -> 43427.88 | GN42: =IF(OR(BI42=0,BI42=1),GM42-GX42,0) -> 0 | GO42: =IF(BI42=2,GM42-GX42,0) -> 0 | GP42: =IF(BI42=4,GM42-GX42,0) -> 0 | GR42: 0 | GS42: 2 | GT42: 0 | GV42: =ROUND((GT42),6) -> 0 | GW42: 1 | GX42: =ROUND(HC42*I42,2) -> 0 | HA42: 0 | HB42: 0 | HC42: =GV42*GW42 -> 0 | HE42: 3 | HF42: 1,2 | HS42: 0 | IK42: 0
A43: 17 | B43: 1 | E43: 8 | F43: КА 4 | G43: Электромагнитный замок с монтажным комплектом "AL-400 Premium " | H43: шт. | I43: =ROUND(ROUND(27,4),9) -> 27 | J43: 0 | K43: =ROUND(ROUND(27,4),9) -> 27 | O43: =ROUND(CP43,2) -> 332657.56 | P43: =ROUND((ROUND((AC43*I43),2)*BC43),2) -> 332657.56 | Q43: =(ROUND((ROUND(((ET43)*AV43*I43),2)*BB43),2)+ROUND((ROUND(((AE43-(EU43))*AV43*I43),2)*BS43),2)) -> 0 | R43: =ROUND((ROUND((AE43*AV43*I43),2)*BS43),2) -> 0 | S43: =ROUND((ROUND((AF43*AV43*I43),2)*BA43),2) -> 0 | T43: =ROUND(CU43*I43,2) -> 0 | U43: =CV43*I43 -> 0 | V43: =CW43*I43 -> 0 | W43: =ROUND(CX43*I43,2) -> 0 | X43: =ROUND(CY43,2) -> 0 | Y43: =ROUND(CZ43,2) -> 0 | AA43: 59213213 | AB43: =ROUND((AC43+AD43+AF43),6) -> 1608.44 | AC43: =ROUND((ES43),6) -> 1608.44 | AD43: =ROUND((((ET43)-(EU43))+AE43),6) -> 0 | AE43: =ROUND((EU43),6) -> 0 | AF43: =ROUND((EV43),6) -> 0 | AG43: =ROUND((AP43),6) -> 0 | AH43: =(EW43) -> 0 | AI43: =(EX43) -> 0 | AJ43: =(AS43) -> 0 | AK43: 1608.44 | AL43: 1608.44 | AM43: 0 | AN43: 0 | AO43: 0 | AP43: 0 | AQ43: 0 | AR43: 0 | AS43: 0 | AT43: 0 | AU43: 0 | AV43: 1 | AW43: 1 | AZ43: 1 | BA43: 1 | BB43: 1 | BC43: 7.66 | BH43: 3 | BI43: 3 | BM43: 746 | BN43: 0 | BP43: 0 | BQ43: 130 | BR43: 0 | BS43: 1 | BT43: 1 | BU43: 1 | BV43: 1 | BW43: 1 | BX43: 1 | BZ43: 0 | CA43: 0 | CE43: 30 | CF43: 0 | CG43: 0 | CM43: 0 | CO43: 0 | CP43: =(P43+Q43+S43) -> 332657.56 | CQ43: =ROUND((ROUND((AC43*1),2)*BC43),2) -> 12320.65 | CR43: =(ROUND((ROUND(((ET43)*AV43*1),2)*BB43),2)+ROUND((ROUND(((AE43-(EU43))*AV43*1),2)*BS43),2)) -> 0 | CS43: =ROUND((ROUND((AE43*AV43*1),2)*BS43),2) -> 0 | CT43: =ROUND((ROUND((AF43*AV43*1),2)*BA43),2) -> 0 | CU43: =AG43 -> 0 | CV43: =(AH43*AV43) -> 0 | CW43: =AI43 -> 0 | CX43: =AJ43 -> 0 | CY43: =(((S43+R43)*AT43)/100) -> 0 | CZ43: =(((S43+R43)*AU43)/100) -> 0 | DN43: 0 | DO43: 0 | DP43: 1 | DQ43: 1 | DU43: 1010 | DV43: шт. | DW43: шт. | DX43: 1 | EE43: 58808284 | EF43: 130 | EG43: Сметная стоимость оборудования | EH43: 0 | EJ43: 3 | EK43: 746 | EL43: ТСН-2001.13. Сметная стоимость оборудования | EM43: ТСН-2001.13 | EQ43: 0 | ER43: 1608.44 | ES43: 1608.44 | ET43: 0 | EU43: 0 | EV43: 0 | EW43: 0 | EX43: 0 | EY43: 0 | EZ43: 5 | FC43: 1 | FD43: 18 | FF43: 14184 | FQ43: 0 | FR43: =P43 -> 332657.56 | FS43: 0 | FX43: 0 | FY43: 0 | GA43: [14 184 / 1,2 / 7,66] + 3% Трансп + 1,2% Заг.скл | GD43: 1 | GF43: 17706835 | GG43: 2 | GH43: 3 | GI43: 5 | GJ43: 0 | GK43: 0 | GL43: =ROUND(IF(AND(BH43=3,BI43=3,FS43<>0),P43,0),2) -> 0 | GM43: =ROUND(O43+X43+Y43,2)+GX43 -> 332657.56 | GN43: =IF(OR(BI43=0,BI43=1),GM43-GX43,0) -> 0 | GO43: =IF(BI43=2,GM43-GX43,0) -> 0 | GP43: =IF(BI43=4,GM43-GX43,0) -> 0 | GR43: 2 | GS43: 1 | GT43: 0 | GV43: =ROUND((GT43),6) -> 0 | GW43: 1 | GX43: =ROUND(HC43*I43,2) -> 0 | HA43: 0 | HB43: 0 | HC43: =GV43*GW43 -> 0 | HE43: 3 | HF43: 1,2 | HS43: 0 | IK43: 0
A44: 17 | B44: 1 | C44: =ROW(SmtRes!A45) -> 45 | D44: =ROW(EtalonRes!A49) -> 49 | E44: 9 | F44: 4.10-81-4 | G44: Извещатели ОС автоматические, контактный, магнито-контактный на открывание окон, дверей | H44: 1 ШТ. | I44: =ROUND(ROUND(38+4,4),9) -> 42 | J44: 0 | K44: =ROUND(ROUND(38+4,4),9) -> 42 | O44: =ROUND(CP44,2) -> 556.84 | P44: =ROUND((ROUND((AC44*AW44*I44),2)*BC44),2) -> 44.1 | Q44: =(ROUND((ROUND((((ET44*1.1))*AV44*I44),2)*BB44),2)+ROUND((ROUND(((AE44-((EU44*1.1)))*AV44*I44),2)*BS44),2)) -> 0 | R44: =ROUND((ROUND((AE44*AV44*I44),2)*BS44),2) -> 0 | S44: =ROUND((ROUND((AF44*AV44*I44),2)*BA44),2) -> 512.74 | T44: =ROUND(CU44*I44,2) -> 0 | U44: =CV44*I44 -> 40.631976 | V44: =CW44*I44 -> 0 | W44: =ROUND(CX44*I44,2) -> 0 | X44: =ROUND(CY44,2) -> 461.47 | Y44: =ROUND(CZ44,2) -> 235.86 | AA44: 59213216 | AB44: =ROUND((AC44+AD44+AF44),6) -> 12.71 | AC44: =ROUND(((ES44*1)),6) -> 1.05 | AD44: =ROUND(((((ET44*1.1))-((EU44*1.1)))+AE44),6) -> 0 | AE44: =ROUND(((EU44*1.1)),6) -> 0 | AF44: =ROUND(((EV44*1.1)),6) -> 11.66 | AG44: =ROUND((AP44),6) -> 0 | AH44: =((EW44*1.1)) -> 0.924 | AI44: =((EX44*1.1)) -> 0 | AJ44: =(AS44) -> 0 | AK44: 11.65 | AL44: 1.05 | AM44: 0 | AN44: 0 | AO44: 10.6 | AP44: 0 | AQ44: 0.84 | AR44: 0 | AS44: 0 | AT44: 90 | AU44: 46 | AV44: 1.047 | AW44: 1 | AZ44: 1 | BA44: 1 | BB44: 1 | BC44: 1 | BH44: 0 | BI44: 2 | BJ44: ТСН-2001.4. Доп. 1-42. Сб. 10, т. 81, поз. 4 | BM44: 68 | BN44: 58808062 | BO44: 4.10-81-4 | BP44: 1 | BQ44: 40 | BR44: 0 | BS44: 1 | BT44: 1 | BU44: 1 | BV44: 1 | BW44: 1 | BX44: 1 | BZ44: 90 | CA44: 46 | CE44: 30 | CF44: 0 | CG44: 0 | CM44: 0 | CN44: Поправка: Гл.12.Прил.8.п.8. 5_12.00.01.11.003 Наименование: При наличии усложненных условий производства работ (стесненность, сложность складирования и транспортной логистики, наличие в зоне производства работ действующего технологического оборудования или движения технологического транспорта и т.п.) для объектов, расположенных за пределами территории круговой магистральной системы улиц "Садовое кольцо" и за пределами Третьего транспортного кольца города Москвы пунктов "а" и "б", но в пределах Московской кольцевой автомобильной дороги | CO44: 0 | CP44: =(P44+Q44+S44) -> 556.84 | CQ44: =ROUND((ROUND((AC44*AW44*1),2)*BC44),2) -> 1.05 | CR44: =(ROUND((ROUND((((ET44*1.1))*AV44*1),2)*BB44),2)+ROUND((ROUND(((AE44-((EU44*1.1)))*AV44*1),2)*BS44),2)) -> 0 | CS44: =ROUND((ROUND((AE44*AV44*1),2)*BS44),2) -> 0 | CT44: =ROUND((ROUND((AF44*AV44*1),2)*BA44),2) -> 12.21 | CU44: =AG44 -> 0 | CV44: =(AH44*AV44) -> 0.967428 | CW44: =AI44 -> 0 | CX44: =AJ44 -> 0 | CY44: =(((S44+R44)*AT44)/100) -> 461.466 | CZ44: =(((S44+R44)*AU44)/100) -> 235.8604 | DB44: 9 | DD44: *1 | DE44: *1,1 | DF44: *1,1 | DG44: *1,1 | DI44: *1,1 | DJ44: *1,1 | DN44: 0 | DO44: 0 | DP44: 1 | DQ44: 1 | DU44: 1013 | DV44: 1 ШТ. | DW44: 1 ШТ. | DX44: 1 | EE44: 58808178 | EF44: 40 | EG44: Монтаж оборудования | EH44: 0 | EJ44: 2 | EK44: 68 | EL44: ТСН-2001.4-10. Прокладка и монтаж сетей связи | EM44: ТСН-2001.4-10-1 | EO44: Поправка: Гл.12.Прил.8.п.8. 5_12.00.01.11.003 | EQ44: 0 | ER44: 11.65 | ES44: 1.05 | ET44: 0 | EU44: 0 | EV44: 10.6 | EW44: 0.84 | EX44: 0 | EY44: 0 | FQ44: 0 | FR44: 0 | FS44: 0 | FX44: 90 | FY44: 46 | GD44: 1 | GF44: 1491178318 | GG44: 2 | GH44: 1 | GI44: 2 | GJ44: 0 | GK44: 0 | GL44: =ROUND(IF(AND(BH44=3,BI44=3,FS44<>0),P44,0),2) -> 0 | GM44: =ROUND(O44+X44+Y44,2)+GX44 -> 1254.17 | GN44: =IF(OR(BI44=0,BI44=1),GM44-GX44,0) -> 0 | GO44: =IF(BI44=2,GM44-GX44,0) -> 1254.17 | GP44: =IF(BI44=4,GM44-GX44,0) -> 0 | GR44: 0 | GS44: 3 | GT44: 0 | GV44: =ROUND((GT44),6) -> 0 | GW44: 1 | GX44: =ROUND(HC44*I44,2) -> 0 | HA44: 0 | HB44: 0 | HC44: =GV44*GW44 -> 0 | HS44: 0 | IK44: 0
A45: 17 | B45: 1 | C45: =ROW(SmtRes!A46) -> 46 | D45: =ROW(EtalonRes!A50) -> 50 | E45: 9 | F45: 4.10-81-4 | G45: Извещатели ОС автоматические, контактный, магнито-контактный на открывание окон, дверей | H45: 1 ШТ. | I45: =ROUND(ROUND(38+4,4),9) -> 42 | J45: 0 | K45: =ROUND(ROUND(38+4,4),9) -> 42 | O45: =ROUND(CP45,2) -> 28631.72 | P45: =ROUND((ROUND((AC45*AW45*I45),2)*BC45),2) -> 436.15 | Q45: =(ROUND((ROUND((((ET45*1.1))*AV45*I45),2)*BB45),2)+ROUND((ROUND(((AE45-((EU45*1.1)))*AV45*I45),2)*BS45),2)) -> 0 | R45: =ROUND((ROUND((AE45*AV45*I45),2)*BS45),2) -> 0 | S45: =ROUND((ROUND((AF45*AV45*I45),2)*BA45),2) -> 28195.57 | T45: =ROUND(CU45*I45,2) -> 0 | U45: =CV45*I45 -> 40.631976 | V45: =CW45*I45 -> 0 | W45: =ROUND(CX45*I45,2) -> 0 | X45: =ROUND(CY45,2) -> 25376.01 | Y45: =ROUND(CZ45,2) -> 12969.96 | AA45: 59213213 | AB45: =ROUND((AC45+AD45+AF45),6) -> 12.71 | AC45: =ROUND(((ES45*1)),6) -> 1.05 | AD45: =ROUND(((((ET45*1.1))-((EU45*1.1)))+AE45),6) -> 0 | AE45: =ROUND(((EU45*1.1)),6) -> 0 | AF45: =ROUND(((EV45*1.1)),6) -> 11.66 | AG45: =ROUND((AP45),6) -> 0 | AH45: =((EW45*1.1)) -> 0.924 | AI45: =((EX45*1.1)) -> 0 | AJ45: =(AS45) -> 0 | AK45: 11.65 | AL45: 1.05 | AM45: 0 | AN45: 0 | AO45: 10.6 | AP45: 0 | AQ45: 0.84 | AR45: 0 | AS45: 0 | AT45: 90 | AU45: 46 | AV45: 1.047 | AW45: 1 | AZ45: 1 | BA45: 54.99 | BB45: 1 | BC45: 9.89 | BH45: 0 | BI45: 2 | BJ45: ТСН-2001.4. Доп. 1-42. Сб. 10, т. 81, поз. 4 | BM45: 68 | BN45: 58808062 | BO45: 4.10-81-4 | BP45: 1 | BQ45: 40 | BR45: 0 | BS45: 54.99 | BT45: 1 | BU45: 1 | BV45: 1 | BW45: 1 | BX45: 1 | BZ45: 90 | CA45: 46 | CE45: 30 | CF45: 0 | CG45: 0 | CM45: 0 | CN45: Поправка: Гл.12.Прил.8.п.8. 5_12.00.01.11.003 Наименование: При наличии усложненных условий производства работ (стесненность, сложность складирования и транспортной логистики, наличие в зоне производства работ действующего технологического оборудования или движения технологического транспорта и т.п.) для объектов, расположенных за пределами территории круговой магистральной системы улиц "Садовое кольцо" и за пределами Третьего транспортного кольца города Москвы пунктов "а" и "б", но в пределах Московской кольцевой автомобильной дороги | CO45: 0 | CP45: =(P45+Q45+S45) -> 28631.72 | CQ45: =ROUND((ROUND((AC45*AW45*1),2)*BC45),2) -> 10.38 | CR45: =(ROUND((ROUND((((ET45*1.1))*AV45*1),2)*BB45),2)+ROUND((ROUND(((AE45-((EU45*1.1)))*AV45*1),2)*BS45),2)) -> 0 | CS45: =ROUND((ROUND((AE45*AV45*1),2)*BS45),2) -> 0 | CT45: =ROUND((ROUND((AF45*AV45*1),2)*BA45),2) -> 671.43 | CU45: =AG45 -> 0 | CV45: =(AH45*AV45) -> 0.967428 | CW45: =AI45 -> 0 | CX45: =AJ45 -> 0 | CY45: =(((S45+R45)*AT45)/100) -> 25376.013 | CZ45: =(((S45+R45)*AU45)/100) -> 12969.962 | DB45: 10 | DD45: *1 | DE45: *1,1 | DF45: *1,1 | DG45: *1,1 | DI45: *1,1 | DJ45: *1,1 | DN45: 0 | DO45: 0 | DP45: 1 | DQ45: 1 | DU45: 1013 | DV45: 1 ШТ. | DW45: 1 ШТ. | DX45: 1 | EE45: 58808178 | EF45: 40 | EG45: Монтаж оборудования | EH45: 0 | EJ45: 2 | EK45: 68 | EL45: ТСН-2001.4-10. Прокладка и монтаж сетей связи | EM45: ТСН-2001.4-10-1 | EO45: Поправка: Гл.12.Прил.8.п.8. 5_12.00.01.11.003 | EQ45: 0 | ER45: 11.65 | ES45: 1.05 | ET45: 0 | EU45: 0 | EV45: 10.6 | EW45: 0.84 | EX45: 0 | EY45: 0 | FQ45: 0 | FR45: 0 | FS45: 0 | FX45: 90 | FY45: 46 | GD45: 1 | GF45: 1491178318 | GG45: 2 | GH45: 1 | GI45: 2 | GJ45: 0 | GK45: 0 | GL45: =ROUND(IF(AND(BH45=3,BI45=3,FS45<>0),P45,0),2) -> 0 | GM45: =ROUND(O45+X45+Y45,2)+GX45 -> 66977.69 | GN45: =IF(OR(BI45=0,BI45=1),GM45-GX45,0) -> 0 | GO45: =IF(BI45=2,GM45-GX45,0) -> 66977.69 | GP45: =IF(BI45=4,GM45-GX45,0) -> 0 | GR45: 0 | GS45: 3 | GT45: 0 | GV45: =ROUND((GT45),6) -> 0 | GW45: 1 | GX45: =ROUND(HC45*I45,2) -> 0 | HA45: 0 | HB45: 0 | HC45: =GV45*GW45 -> 0 | HS45: 0 | IK45: 0
A46: 17 | B46: 1 | E46: 10 | F46: КА 5 | G46: Извещатель охр. магнито-контактный для металлических дверей ИО 102-26 исп. Аякс | H46: шт. | I46: =ROUND(ROUND(38,4),9) -> 38 | J46: 0 | K46: =ROUND(ROUND(38,4),9) -> 38 | O46: =ROUND(CP46,2) -> 1792.84 | P46: =ROUND((ROUND((AC46*I46),2)*BC46),2) -> 1792.84 | Q46: =(ROUND((ROUND(((ET46)*AV46*I46),2)*BB46),2)+ROUND((ROUND(((AE46-(EU46))*AV46*I46),2)*BS46),2)) -> 0 | R46: =ROUND((ROUND((AE46*AV46*I46),2)*BS46),2) -> 0 | S46: =ROUND((ROUND((AF46*AV46*I46),2)*BA46),2) -> 0 | T46: =ROUND(CU46*I46,2) -> 0 | U46: =CV46*I46 -> 0 | V46: =CW46*I46 -> 0 | W46: =ROUND(CX46*I46,2) -> 0 | X46: =ROUND(CY46,2) -> 0 | Y46: =ROUND(CZ46,2) -> 0 | AA46: 59213216 | AB46: =ROUND((AC46+AD46+AF46),6) -> 47.18 | AC46: =ROUND((ES46),6) -> 47.18 | AD46: =ROUND((((ET46)-(EU46))+AE46),6) -> 0 | AE46: =ROUND((EU46),6) -> 0 | AF46: =ROUND((EV46),6) -> 0 | AG46: =ROUND((AP46),6) -> 0 | AH46: =(EW46) -> 0 | AI46: =(EX46) -> 0 | AJ46: =(AS46) -> 0 | AK46: 47.18 | AL46: 47.18 | AM46: 0 | AN46: 0 | AO46: 0 | AP46: 0 | AQ46: 0 | AR46: 0 | AS46: 0 | AT46: 0 | AU46: 0 | AV46: 1 | AW46: 1 | AZ46: 1 | BA46: 1 | BB46: 1 | BC46: 1 | BH46: 3 | BI46: 3 | BM46: 746 | BN46: 0 | BP46: 0 | BQ46: 130 | BR46: 0 | BS46: 1 | BT46: 1 | BU46: 1 | BV46: 1 | BW46: 1 | BX46: 1 | BZ46: 0 | CA46: 0 | CE46: 30 | CF46: 0 | CG46: 0 | CM46: 0 | CO46: 0 | CP46: =(P46+Q46+S46) -> 1792.84 | CQ46: =ROUND((ROUND((AC46*1),2)*BC46),2) -> 47.18 | CR46: =(ROUND((ROUND(((ET46)*AV46*1),2)*BB46),2)+ROUND((ROUND(((AE46-(EU46))*AV46*1),2)*BS46),2)) -> 0 | CS46: =ROUND((ROUND((AE46*AV46*1),2)*BS46),2) -> 0 | CT46: =ROUND((ROUND((AF46*AV46*1),2)*BA46),2) -> 0 | CU46: =AG46 -> 0 | CV46: =(AH46*AV46) -> 0 | CW46: =AI46 -> 0 | CX46: =AJ46 -> 0 | CY46: =(((S46+R46)*AT46)/100) -> 0 | CZ46: =(((S46+R46)*AU46)/100) -> 0 | DN46: 0 | DO46: 0 | DP46: 1 | DQ46: 1 | DU46: 1010 | DV46: шт. | DW46: шт. | DX46: 1 | EE46: 58808284 | EF46: 130 | EG46: Сметная стоимость оборудования | EH46: 0 | EJ46: 3 | EK46: 746 | EL46: ТСН-2001.13. Сметная стоимость оборудования | EM46: ТСН-2001.13 | EQ46: 0 | ER46: 0 | ES46: 47.18 | ET46: 0 | EU46: 0 | EV46: 0 | EW46: 0 | EX46: 0 | EY46: 0 | FQ46: 0 | FR46: =P46 -> 1792.84 | FS46: 0 | FX46: 0 | FY46: 0 | GA46: [416 / 1,2 / 7,66] + 3% Трансп + 1,2% Заг.скл | GD46: 1 | GF46: 890166502 | GG46: 2 | GH46: 4 | GI46: -2 | GJ46: 0 | GK46: 0 | GL46: =ROUND(IF(AND(BH46=3,BI46=3,FS46<>0),P46,0),2) -> 0 | GM46: =ROUND(O46+X46+Y46,2)+GX46 -> 1792.84 | GN46: =IF(OR(BI46=0,BI46=1),GM46-GX46,0) -> 0 | GO46: =IF(BI46=2,GM46-GX46,0) -> 0 | GP46: =IF(BI46=4,GM46-GX46,0) -> 0 | GR46: 0 | GS46: 2 | GT46: 0 | GV46: =ROUND((GT46),6) -> 0 | GW46: 1 | GX46: =ROUND(HC46*I46,2) -> 0 | HA46: 0 | HB46: 0 | HC46: =GV46*GW46 -> 0 | HE46: 3 | HF46: 1,2 | HS46: 0 | IK46: 0
A47: 17 | B47: 1 | E47: 10 | F47: КА 5 | G47: Извещатель охр. магнито-контактный для металлических дверей ИО 102-26 исп. Аякс | H47: шт. | I47: =ROUND(ROUND(38,4),9) -> 38 | J47: 0 | K47: =ROUND(ROUND(38,4),9) -> 38 | O47: =ROUND(CP47,2) -> 13733.15 | P47: =ROUND((ROUND((AC47*I47),2)*BC47),2) -> 13733.15 | Q47: =(ROUND((ROUND(((ET47)*AV47*I47),2)*BB47),2)+ROUND((ROUND(((AE47-(EU47))*AV47*I47),2)*BS47),2)) -> 0 | R47: =ROUND((ROUND((AE47*AV47*I47),2)*BS47),2) -> 0 | S47: =ROUND((ROUND((AF47*AV47*I47),2)*BA47),2) -> 0 | T47: =ROUND(CU47*I47,2) -> 0 | U47: =CV47*I47 -> 0 | V47: =CW47*I47 -> 0 | W47: =ROUND(CX47*I47,2) -> 0 | X47: =ROUND(CY47,2) -> 0 | Y47: =ROUND(CZ47,2) -> 0 | AA47: 59213213 | AB47: =ROUND((AC47+AD47+AF47),6) -> 47.18 | AC47: =ROUND((ES47),6) -> 47.18 | AD47: =ROUND((((ET47)-(EU47))+AE47),6) -> 0 | AE47: =ROUND((EU47),6) -> 0 | AF47: =ROUND((EV47),6) -> 0 | AG47: =ROUND((AP47),6) -> 0 | AH47: =(EW47) -> 0 | AI47: =(EX47) -> 0 | AJ47: =(AS47) -> 0 | AK47: 47.18 | AL47: 47.18 | AM47: 0 | AN47: 0 | AO47: 0 | AP47: 0 | AQ47: 0 | AR47: 0 | AS47: 0 | AT47: 0 | AU47: 0 | AV47: 1 | AW47: 1 | AZ47: 1 | BA47: 1 | BB47: 1 | BC47: 7.66 | BH47: 3 | BI47: 3 | BM47: 746 | BN47: 0 | BP47: 0 | BQ47: 130 | BR47: 0 | BS47: 1 | BT47: 1 | BU47: 1 | BV47: 1 | BW47: 1 | BX47: 1 | BZ47: 0 | CA47: 0 | CE47: 30 | CF47: 0 | CG47: 0 | CM47: 0 | CO47: 0 | CP47: =(P47+Q47+S47) -> 13733.15 | CQ47: =ROUND((ROUND((AC47*1),2)*BC47),2) -> 361.4 | CR47: =(ROUND((ROUND(((ET47)*AV47*1),2)*BB47),2)+ROUND((ROUND(((AE47-(EU47))*AV47*1),2)*BS47),2)) -> 0 | CS47: =ROUND((ROUND((AE47*AV47*1),2)*BS47),2) -> 0 | CT47: =ROUND((ROUND((AF47*AV47*1),2)*BA47),2) -> 0 | CU47: =AG47 -> 0 | CV47: =(AH47*AV47) -> 0 | CW47: =AI47 -> 0 | CX47: =AJ47 -> 0 | CY47: =(((S47+R47)*AT47)/100) -> 0 | CZ47: =(((S47+R47)*AU47)/100) -> 0 | DN47: 0 | DO47: 0 | DP47: 1 | DQ47: 1 | DU47: 1010 | DV47: шт. | DW47: шт. | DX47: 1 | EE47: 58808284 | EF47: 130 | EG47: Сметная стоимость оборудования | EH47: 0 | EJ47: 3 | EK47: 746 | EL47: ТСН-2001.13. Сметная стоимость оборудования | EM47: ТСН-2001.13 | EQ47: 0 | ER47: 47.18 | ES47: 47.18 | ET47: 0 | EU47: 0 | EV47: 0 | EW47: 0 | EX47: 0 | EY47: 0 | EZ47: 5 | FC47: 1 | FD47: 18 | FF47: 416 | FQ47: 0 | FR47: =P47 -> 13733.15 | FS47: 0 | FX47: 0 | FY47: 0 | GA47: [416 / 1,2 / 7,66] + 3% Трансп + 1,2% Заг.скл | GD47: 1 | GF47: 890166502 | GG47: 2 | GH47: 3 | GI47: 5 | GJ47: 0 | GK47: 0 | GL47: =ROUND(IF(AND(BH47=3,BI47=3,FS47<>0),P47,0),2) -> 0 | GM47: =ROUND(O47+X47+Y47,2)+GX47 -> 13733.15 | GN47: =IF(OR(BI47=0,BI47=1),GM47-GX47,0) -> 0 | GO47: =IF(BI47=2,GM47-GX47,0) -> 0 | GP47: =IF(BI47=4,GM47-GX47,0) -> 0 | GR47: 2 | GS47: 1 | GT47: 0 | GV47: =ROUND((GT47),6) -> 0 | GW47: 1 | GX47: =ROUND(HC47*I47,2) -> 0 | HA47: 0 | HB47: 0 | HC47: =GV47*GW47 -> 0 | HE47: 3 | HF47: 1,2 | HS47: 0 | IK47: 0
A48: 17 | B48: 1 | E48: 11 | F48: КА 6 | G48: Извещатель охр. магнито-контактный для неметалл. поверхностей ИО 102-2 СМК | H48: шт. | I48: =ROUND(ROUND(4,4),9) -> 4 | J48: 0 | K48: =ROUND(ROUND(4,4),9) -> 4 | O48: =ROUND(CP48,2) -> 51.16 | P48: =ROUND((ROUND((AC48*I48),2)*BC48),2) -> 51.16 | Q48: =(ROUND((ROUND(((ET48)*AV48*I48),2)*BB48),2)+ROUND((ROUND(((AE48-(EU48))*AV48*I48),2)*BS48),2)) -> 0 | R48: =ROUND((ROUND((AE48*AV48*I48),2)*BS48),2) -> 0 | S48: =ROUND((ROUND((AF48*AV48*I48),2)*BA48),2) -> 0 | T48: =ROUND(CU48*I48,2) -> 0 | U48: =CV48*I48 -> 0 | V48: =CW48*I48 -> 0 | W48: =ROUND(CX48*I48,2) -> 0 | X48: =ROUND(CY48,2) -> 0 | Y48: =ROUND(CZ48,2) -> 0 | AA48: 59213216 | AB48: =ROUND((AC48+AD48+AF48),6) -> 12.79 | AC48: =ROUND((ES48),6) -> 12.79 | AD48: =ROUND((((ET48)-(EU48))+AE48),6) -> 0 | AE48: =ROUND((EU48),6) -> 0 | AF48: =ROUND((EV48),6) -> 0 | AG48: =ROUND((AP48),6) -> 0 | AH48: =(EW48) -> 0 | AI48: =(EX48) -> 0 | AJ48: =(AS48) -> 0 | AK48: 12.79 | AL48: 12.79 | AM48: 0 | AN48: 0 | AO48: 0 | AP48: 0 | AQ48: 0 | AR48: 0 | AS48: 0 | AT48: 0 | AU48: 0 | AV48: 1 | AW48: 1 | AZ48: 1 | BA48: 1 | BB48: 1 | BC48: 1 | BH48: 3 | BI48: 3 | BM48: 746 | BN48: 0 | BP48: 0 | BQ48: 130 | BR48: 0 | BS48: 1 | BT48: 1 | BU48: 1 | BV48: 1 | BW48: 1 | BX48: 1 | BZ48: 0 | CA48: 0 | CE48: 30 | CF48: 0 | CG48: 0 | CM48: 0 | CO48: 0 | CP48: =(P48+Q48+S48) -> 51.16 | CQ48: =ROUND((ROUND((AC48*1),2)*BC48),2) -> 12.79 | CR48: =(ROUND((ROUND(((ET48)*AV48*1),2)*BB48),2)+ROUND((ROUND(((AE48-(EU48))*AV48*1),2)*BS48),2)) -> 0 | CS48: =ROUND((ROUND((AE48*AV48*1),2)*BS48),2) -> 0 | CT48: =ROUND((ROUND((AF48*AV48*1),2)*BA48),2) -> 0 | CU48: =AG48 -> 0 | CV48: =(AH48*AV48) -> 0 | CW48: =AI48 -> 0 | CX48: =AJ48 -> 0 | CY48: =(((S48+R48)*AT48)/100) -> 0 | CZ48: =(((S48+R48)*AU48)/100) -> 0 | DN48: 0 | DO48: 0 | DP48: 1 | DQ48: 1 | DU48: 1010 | DV48: шт. | DW48: шт. | DX48: 1 | EE48: 58808284 | EF48: 130 | EG48: Сметная стоимость оборудования | EH48: 0 | EJ48: 3 | EK48: 746 | EL48: ТСН-2001.13. Сметная стоимость оборудования | EM48: ТСН-2001.13 | EQ48: 0 | ER48: 0 | ES48: 12.79 | ET48: 0 | EU48: 0 | EV48: 0 | EW48: 0 | EX48: 0 | EY48: 0 | FQ48: 0 | FR48: =P48 -> 51.16 | FS48: 0 | FX48: 0 | FY48: 0 | GA48: [112,8 / 1,2 / 7,66] + 3% Трансп + 1,2% Заг.скл | GD48: 1 | GF48: 1231063478 | GG48: 2 | GH48: 4 | GI48: -2 | GJ48: 0 | GK48: 0 | GL48: =ROUND(IF(AND(BH48=3,BI48=3,FS48<>0),P48,0),2) -> 0 | GM48: =ROUND(O48+X48+Y48,2)+GX48 -> 51.16 | GN48: =IF(OR(BI48=0,BI48=1),GM48-GX48,0) -> 0 | GO48: =IF(BI48=2,GM48-GX48,0) -> 0 | GP48: =IF(BI48=4,GM48-GX48,0) -> 0 | GR48: 0 | GS48: 2 | GT48: 0 | GV48: =ROUND((GT48),6) -> 0 | GW48: 1 | GX48: =ROUND(HC48*I48,2) -> 0 | HA48: 0 | HB48: 0 | HC48: =GV48*GW48 -> 0 | HE48: 3 | HF48: 1,2 | HS48: 0 | IK48: 0
A49: 17 | B49: 1 | E49: 11 | F49: КА 6 | G49: Извещатель охр. магнито-контактный для неметалл. поверхностей ИО 102-2 СМК | H49: шт. | I49: =ROUND(ROUND(4,4),9) -> 4 | J49: 0 | K49: =ROUND(ROUND(4,4),9) -> 4 | O49: =ROUND(CP49,2) -> 391.89 | P49: =ROUND((ROUND((AC49*I49),2)*BC49),2) -> 391.89 | Q49: =(ROUND((ROUND(((ET49)*AV49*I49),2)*BB49),2)+ROUND((ROUND(((AE49-(EU49))*AV49*I49),2)*BS49),2)) -> 0 | R49: =ROUND((ROUND((AE49*AV49*I49),2)*BS49),2) -> 0 | S49: =ROUND((ROUND((AF49*AV49*I49),2)*BA49),2) -> 0 | T49: =ROUND(CU49*I49,2) -> 0 | U49: =CV49*I49 -> 0 | V49: =CW49*I49 -> 0 | W49: =ROUND(CX49*I49,2) -> 0 | X49: =ROUND(CY49,2) -> 0 | Y49: =ROUND(CZ49,2) -> 0 | AA49: 59213213 | AB49: =ROUND((AC49+AD49+AF49),6) -> 12.79 | AC49: =ROUND((ES49),6) -> 12.79 | AD49: =ROUND((((ET49)-(EU49))+AE49),6) -> 0 | AE49: =ROUND((EU49),6) -> 0 | AF49: =ROUND((EV49),6) -> 0 | AG49: =ROUND((AP49),6) -> 0 | AH49: =(EW49) -> 0 | AI49: =(EX49) -> 0 | AJ49: =(AS49) -> 0 | AK49: 12.79 | AL49: 12.79 | AM49: 0 | AN49: 0 | AO49: 0 | AP49: 0 | AQ49: 0 | AR49: 0 | AS49: 0 | AT49: 0 | AU49: 0 | AV49: 1 | AW49: 1 | AZ49: 1 | BA49: 1 | BB49: 1 | BC49: 7.66 | BH49: 3 | BI49: 3 | BM49: 746 | BN49: 0 | BP49: 0 | BQ49: 130 | BR49: 0 | BS49: 1 | BT49: 1 | BU49: 1 | BV49: 1 | BW49: 1 | BX49: 1 | BZ49: 0 | CA49: 0 | CE49: 30 | CF49: 0 | CG49: 0 | CM49: 0 | CO49: 0 | CP49: =(P49+Q49+S49) -> 391.89 | CQ49: =ROUND((ROUND((AC49*1),2)*BC49),2) -> 97.97 | CR49: =(ROUND((ROUND(((ET49)*AV49*1),2)*BB49),2)+ROUND((ROUND(((AE49-(EU49))*AV49*1),2)*BS49),2)) -> 0 | CS49: =ROUND((ROUND((AE49*AV49*1),2)*BS49),2) -> 0 | CT49: =ROUND((ROUND((AF49*AV49*1),2)*BA49),2) -> 0 | CU49: =AG49 -> 0 | CV49: =(AH49*AV49) -> 0 | CW49: =AI49 -> 0 | CX49: =AJ49 -> 0 | CY49: =(((S49+R49)*AT49)/100) -> 0 | CZ49: =(((S49+R49)*AU49)/100) -> 0 | DN49: 0 | DO49: 0 | DP49: 1 | DQ49: 1 | DU49: 1010 | DV49: шт. | DW49: шт. | DX49: 1 | EE49: 58808284 | EF49: 130 | EG49: Сметная стоимость оборудования | EH49: 0 | EJ49: 3 | EK49: 746 | EL49: ТСН-2001.13. Сметная стоимость оборудования | EM49: ТСН-2001.13 | EQ49: 0 | ER49: 12.79 | ES49: 12.79 | ET49: 0 | EU49: 0 | EV49: 0 | EW49: 0 | EX49: 0 | EY49: 0 | EZ49: 5 | FC49: 1 | FD49: 18 | FF49: 112.8 | FQ49: 0 | FR49: =P49 -> 391.89 | FS49: 0 | FX49: 0 | FY49: 0 | GA49: [112,8 / 1,2 / 7,66] + 3% Трансп + 1,2% Заг.скл | GD49: 1 | GF49: 1231063478 | GG49: 2 | GH49: 3 | GI49: 5 | GJ49: 0 | GK49: 0 | GL49: =ROUND(IF(AND(BH49=3,BI49=3,FS49<>0),P49,0),2) -> 0 | GM49: =ROUND(O49+X49+Y49,2)+GX49 -> 391.89 | GN49: =IF(OR(BI49=0,BI49=1),GM49-GX49,0) -> 0 | GO49: =IF(BI49=2,GM49-GX49,0) -> 0 | GP49: =IF(BI49=4,GM49-GX49,0) -> 0 | GR49: 2 | GS49: 1 | GT49: 0 | GV49: =ROUND((GT49),6) -> 0 | GW49: 1 | GX49: =ROUND(HC49*I49,2) -> 0 | HA49: 0 | HB49: 0 | HC49: =GV49*GW49 -> 0 | HE49: 3 | HF49: 1,2 | HS49: 0 | IK49: 0
A50: 17 | B50: 1 | C50: =ROW(SmtRes!A51) -> 51 | D50: =ROW(EtalonRes!A56) -> 56 | E50: 12 | F50: 4.10-177-1 | G50: Монтаж устройства связи с согласующим устройством (вызывная панель) | H50: 10 шт. | I50: =ROUND(ROUND(42/10,4),9) -> 4.2 | J50: 0 | K50: =ROUND(ROUND(42/10,4),9) -> 4.2 | O50: =ROUND(CP50,2) -> 1139.77 | P50: =ROUND((ROUND((AC50*AW50*I50),2)*BC50),2) -> 10.25 | Q50: =(ROUND((ROUND((((ET50*1.1))*AV50*I50),2)*BB50),2)+ROUND((ROUND(((AE50-((EU50*1.1)))*AV50*I50),2)*BS50),2)) -> 29.36 | R50: =ROUND((ROUND((AE50*AV50*I50),2)*BS50),2) -> 3.68 | S50: =ROUND((ROUND((AF50*AV50*I50),2)*BA50),2) -> 1100.16 | T50: =ROUND(CU50*I50,2) -> 0 | U50: =CV50*I50 -> 70.81573 | V50: =CW50*I50 -> 0 | W50: =ROUND(CX50*I50,2) -> 0 | X50: =ROUND(CY50,2) -> 993.46 | Y50: =ROUND(CZ50,2) -> 507.77 | AA50: 59213216 | AB50: =ROUND((AC50+AD50+AF50),6) -> 259.301 | AC50: =ROUND(((ES50*1)),6) -> 2.44 | AD50: =ROUND(((((ET50*1.1))-((EU50*1.1)))+AE50),6) -> 6.677 | AE50: =ROUND(((EU50*1.1)),6) -> 0.836 | AF50: =ROUND(((EV50*1.1)),6) -> 250.184 | AG50: =ROUND((AP50),6) -> 0 | AH50: =((EW50*1.1)) -> 16.104 | AI50: =((EX50*1.1)) -> 0 | AJ50: =(AS50) -> 0 | AK50: 235.95 | AL50: 2.44 | AM50: 6.07 | AN50: 0.76 | AO50: 227.44 | AP50: 0 | AQ50: 14.64 | AR50: 0 | AS50: 0 | AT50: 90 | AU50: 46 | AV50: 1.047 | AW50: 1 | AZ50: 1 | BA50: 1 | BB50: 1 | BC50: 1 | BH50: 0 | BI50: 2 | BJ50: ТСН-2001.4 Доп. 80, Сб. 10, т. 177, поз. 1 | BM50: 68 | BN50: 58808062 | BO50: 4.10-177-1 | BP50: 1 | BQ50: 40 | BR50: 0 | BS50: 1 | BT50: 1 | BU50: 1 | BV50: 1 | BW50: 1 | BX50: 1 | BZ50: 90 | CA50: 46 | CE50: 30 | CF50: 0 | CG50: 0 | CM50: 0 | CN50: Поправка: Гл.12.Прил.8.п.8. 5_12.00.01.11.003 Наименование: При наличии усложненных условий производства работ (стесненность, сложность складирования и транспортной логистики, наличие в зоне производства работ действующего технологического оборудования или движения технологического транспорта и т.п.) для объектов, расположенных за пределами территории круговой магистральной системы улиц "Садовое кольцо" и за пределами Третьего транспортного кольца города Москвы пунктов "а" и "б", но в пределах Московской кольцевой автомобильной дороги | CO50: 0 | CP50: =(P50+Q50+S50) -> 1139.77 | CQ50: =ROUND((ROUND((AC50*AW50*1),2)*BC50),2) -> 2.44 | CR50: =(ROUND((ROUND((((ET50*1.1))*AV50*1),2)*BB50),2)+ROUND((ROUND(((AE50-((EU50*1.1)))*AV50*1),2)*BS50),2)) -> 6.99 | CS50: =ROUND((ROUND((AE50*AV50*1),2)*BS50),2) -> 0.88 | CT50: =ROUND((ROUND((AF50*AV50*1),2)*BA50),2) -> 261.94 | CU50: =AG50 -> 0 | CV50: =(AH50*AV50) -> 16.860888 | CW50: =AI50 -> 0 | CX50: =AJ50 -> 0 | CY50: =(((S50+R50)*AT50)/100) -> 993.456 | CZ50: =(((S50+R50)*AU50)/100) -> 507.7664 | DB50: 11 | DD50: *1 | DE50: *1,1 | DF50: *1,1 | DG50: *1,1 | DI50: *1,1 | DJ50: *1,1 | DN50: 0 | DO50: 0 | DP50: 1 | DQ50: 1 | DU50: 1010 | DV50: 10 шт. | DW50: 10 шт. | DX50: 10 | EE50: 58808178 | EF50: 40 | EG50: Монтаж оборудования | EH50: 0 | EJ50: 2 | EK50: 68 | EL50: ТСН-2001.4-10. Прокладка и монтаж сетей связи | EM50: ТСН-2001.4-10-1 | EO50: Поправка: Гл.12.Прил.8.п.8. 5_12.00.01.11.003 | EQ50: 0 | ER50: 235.95 | ES50: 2.44 | ET50: 6.07 | EU50: 0.76 | EV50: 227.44 | EW50: 14.64 | EX50: 0 | EY50: 0 | FQ50: 0 | FR50: 0 | FS50: 0 | FX50: 90 | FY50: 46 | GD50: 1 | GF50: -1147212458 | GG50: 2 | GH50: 1 | GI50: 2 | GJ50: 0 | GK50: 0 | GL50: =ROUND(IF(AND(BH50=3,BI50=3,FS50<>0),P50,0),2) -> 0 | GM50: =ROUND(O50+X50+Y50,2)+GX50 -> 2641 | GN50: =IF(OR(BI50=0,BI50=1),GM50-GX50,0) -> 0 | GO50: =IF(BI50=2,GM50-GX50,0) -> 2641 | GP50: =IF(BI50=4,GM50-GX50,0) -> 0 | GR50: 0 | GS50: 3 | GT50: 0 | GV50: =ROUND((GT50),6) -> 0 | GW50: 1 | GX50: =ROUND(HC50*I50,2) -> 0 | HA50: 0 | HB50: 0 | HC50: =GV50*GW50 -> 0 | HS50: 0 | IK50: 0
A51: 17 | B51: 1 | C51: =ROW(SmtRes!A56) -> 56 | D51: =ROW(EtalonRes!A62) -> 62 | E51: 12 | F51: 4.10-177-1 | G51: Монтаж устройства связи с согласующим устройством (вызывная панель) | H51: 10 шт. | I51: =ROUND(ROUND(42/10,4),9) -> 4.2 | J51: 0 | K51: =ROUND(ROUND(42/10,4),9) -> 4.2 | O51: =ROUND(CP51,2) -> 61010.55 | P51: =ROUND((ROUND((AC51*AW51*I51),2)*BC51),2) -> 74.11 | Q51: =(ROUND((ROUND((((ET51*1.1))*AV51*I51),2)*BB51),2)+ROUND((ROUND(((AE51-((EU51*1.1)))*AV51*I51),2)*BS51),2)) -> 438.64 | R51: =ROUND((ROUND((AE51*AV51*I51),2)*BS51),2) -> 202.36 | S51: =ROUND((ROUND((AF51*AV51*I51),2)*BA51),2) -> 60497.8 | T51: =ROUND(CU51*I51,2) -> 0 | U51: =CV51*I51 -> 70.81573 | V51: =CW51*I51 -> 0 | W51: =ROUND(CX51*I51,2) -> 0 | X51: =ROUND(CY51,2) -> 54630.14 | Y51: =ROUND(CZ51,2) -> 27922.07 | AA51: 59213213 | AB51: =ROUND((AC51+AD51+AF51),6) -> 259.301 | AC51: =ROUND(((ES51*1)),6) -> 2.44 | AD51: =ROUND(((((ET51*1.1))-((EU51*1.1)))+AE51),6) -> 6.677 | AE51: =ROUND(((EU51*1.1)),6) -> 0.836 | AF51: =ROUND(((EV51*1.1)),6) -> 250.184 | AG51: =ROUND((AP51),6) -> 0 | AH51: =((EW51*1.1)) -> 16.104 | AI51: =((EX51*1.1)) -> 0 | AJ51: =(AS51) -> 0 | AK51: 235.95 | AL51: 2.44 | AM51: 6.07 | AN51: 0.76 | AO51: 227.44 | AP51: 0 | AQ51: 14.64 | AR51: 0 | AS51: 0 | AT51: 90 | AU51: 46 | AV51: 1.047 | AW51: 1 | AZ51: 1 | BA51: 54.99 | BB51: 14.94 | BC51: 7.23 | BH51: 0 | BI51: 2 | BJ51: ТСН-2001.4 Доп. 80, Сб. 10, т. 177, поз. 1 | BM51: 68 | BN51: 58808062 | BO51: 4.10-177-1 | BP51: 1 | BQ51: 40 | BR51: 0 | BS51: 54.99 | BT51: 1 | BU51: 1 | BV51: 1 | BW51: 1 | BX51: 1 | BZ51: 90 | CA51: 46 | CE51: 30 | CF51: 0 | CG51: 0 | CM51: 0 | CN51: Поправка: Гл.12.Прил.8.п.8. 5_12.00.01.11.003 Наименование: При наличии усложненных условий производства работ (стесненность, сложность складирования и транспортной логистики, наличие в зоне производства работ действующего технологического оборудования или движения технологического транспорта и т.п.) для объектов, расположенных за пределами территории круговой магистральной системы улиц "Садовое кольцо" и за пределами Третьего транспортного кольца города Москвы пунктов "а" и "б", но в пределах Московской кольцевой автомобильной дороги | CO51: 0 | CP51: =(P51+Q51+S51) -> 61010.55 | CQ51: =ROUND((ROUND((AC51*AW51*1),2)*BC51),2) -> 17.64 | CR51: =(ROUND((ROUND((((ET51*1.1))*AV51*1),2)*BB51),2)+ROUND((ROUND(((AE51-((EU51*1.1)))*AV51*1),2)*BS51),2)) -> 104.43 | CS51: =ROUND((ROUND((AE51*AV51*1),2)*BS51),2) -> 48.39 | CT51: =ROUND((ROUND((AF51*AV51*1),2)*BA51),2) -> 14404.08 | CU51: =AG51 -> 0 | CV51: =(AH51*AV51) -> 16.860888 | CW51: =AI51 -> 0 | CX51: =AJ51 -> 0 | CY51: =(((S51+R51)*AT51)/100) -> 54630.144 | CZ51: =(((S51+R51)*AU51)/100) -> 27922.074 | DB51: 12 | DD51: *1 | DE51: *1,1 | DF51: *1,1 | DG51: *1,1 | DI51: *1,1 | DJ51: *1,1 | DN51: 0 | DO51: 0 | DP51: 1 | DQ51: 1 | DU51: 1010 | DV51: 10 шт. | DW51: 10 шт. | DX51: 10 | EE51: 58808178 | EF51: 40 | EG51: Монтаж оборудования | EH51: 0 | EJ51: 2 | EK51: 68 | EL51: ТСН-2001.4-10. Прокладка и монтаж сетей связи | EM51: ТСН-2001.4-10-1 | EO51: Поправка: Гл.12.Прил.8.п.8. 5_12.00.01.11.003 | EQ51: 0 | ER51: 235.95 | ES51: 2.44 | ET51: 6.07 | EU51: 0.76 | EV51: 227.44 | EW51: 14.64 | EX51: 0 | EY51: 0 | FQ51: 0 | FR51: 0 | FS51: 0 | FX51: 90 | FY51: 46 | GD51: 1 | GF51: -1147212458 | GG51: 2 | GH51: 1 | GI51: 2 | GJ51: 0 | GK51: 0 | GL51: =ROUND(IF(AND(BH51=3,BI51=3,FS51<>0),P51,0),2) -> 0 | GM51: =ROUND(O51+X51+Y51,2)+GX51 -> 143562.76 | GN51: =IF(OR(BI51=0,BI51=1),GM51-GX51,0) -> 0 | GO51: =IF(BI51=2,GM51-GX51,0) -> 143562.76 | GP51: =IF(BI51=4,GM51-GX51,0) -> 0 | GR51: 0 | GS51: 3 | GT51: 0 | GV51: =ROUND((GT51),6) -> 0 | GW51: 1 | GX51: =ROUND(HC51*I51,2) -> 0 | HA51: 0 | HB51: 0 | HC51: =GV51*GW51 -> 0 | HS51: 0 | IK51: 0
A52: 17 | B52: 1 | E52: 13 | F52: КА 7 | G52: Считыватель для установки на улице и в помещение,-40....+55гр интерфейс Wiegand 26-58, формат карт Mifare, EM-Marin,HID Prox RusGuard R-15 multi | H52: шт. | I52: =ROUND(ROUND(42,4),9) -> 42 | J52: 0 | K52: =ROUND(ROUND(42,4),9) -> 42 | O52: =ROUND(CP52,2) -> 75727.68 | P52: =ROUND((ROUND((AC52*I52),2)*BC52),2) -> 75727.68 | Q52: =(ROUND((ROUND(((ET52)*AV52*I52),2)*BB52),2)+ROUND((ROUND(((AE52-(EU52))*AV52*I52),2)*BS52),2)) -> 0 | R52: =ROUND((ROUND((AE52*AV52*I52),2)*BS52),2) -> 0 | S52: =ROUND((ROUND((AF52*AV52*I52),2)*BA52),2) -> 0 | T52: =ROUND(CU52*I52,2) -> 0 | U52: =CV52*I52 -> 0 | V52: =CW52*I52 -> 0 | W52: =ROUND(CX52*I52,2) -> 0 | X52: =ROUND(CY52,2) -> 0 | Y52: =ROUND(CZ52,2) -> 0 | AA52: 59213216 | AB52: =ROUND((AC52+AD52+AF52),6) -> 1803.04 | AC52: =ROUND((ES52),6) -> 1803.04 | AD52: =ROUND((((ET52)-(EU52))+AE52),6) -> 0 | AE52: =ROUND((EU52),6) -> 0 | AF52: =ROUND((EV52),6) -> 0 | AG52: =ROUND((AP52),6) -> 0 | AH52: =(EW52) -> 0 | AI52: =(EX52) -> 0 | AJ52: =(AS52) -> 0 | AK52: 1803.04 | AL52: 1803.04 | AM52: 0 | AN52: 0 | AO52: 0 | AP52: 0 | AQ52: 0 | AR52: 0 | AS52: 0 | AT52: 0 | AU52: 0 | AV52: 1 | AW52: 1 | AZ52: 1 | BA52: 1 | BB52: 1 | BC52: 1 | BH52: 3 | BI52: 3 | BM52: 746 | BN52: 0 | BP52: 0 | BQ52: 130 | BR52: 0 | BS52: 1 | BT52: 1 | BU52: 1 | BV52: 1 | BW52: 1 | BX52: 1 | BZ52: 0 | CA52: 0 | CE52: 30 | CF52: 0 | CG52: 0 | CM52: 0 | CO52: 0 | CP52: =(P52+Q52+S52) -> 75727.68 | CQ52: =ROUND((ROUND((AC52*1),2)*BC52),2) -> 1803.04 | CR52: =(ROUND((ROUND(((ET52)*AV52*1),2)*BB52),2)+ROUND((ROUND(((AE52-(EU52))*AV52*1),2)*BS52),2)) -> 0 | CS52: =ROUND((ROUND((AE52*AV52*1),2)*BS52),2) -> 0 | CT52: =ROUND((ROUND((AF52*AV52*1),2)*BA52),2) -> 0 | CU52: =AG52 -> 0 | CV52: =(AH52*AV52) -> 0 | CW52: =AI52 -> 0 | CX52: =AJ52 -> 0 | CY52: =(((S52+R52)*AT52)/100) -> 0 | CZ52: =(((S52+R52)*AU52)/100) -> 0 | DN52: 0 | DO52: 0 | DP52: 1 | DQ52: 1 | DU52: 1010 | DV52: шт. | DW52: шт. | DX52: 1 | EE52: 58808284 | EF52: 130 | EG52: Сметная стоимость оборудования | EH52: 0 | EJ52: 3 | EK52: 746 | EL52: ТСН-2001.13. Сметная стоимость оборудования | EM52: ТСН-2001.13 | EQ52: 0 | ER52: 0 | ES52: 1803.04 | ET52: 0 | EU52: 0 | EV52: 0 | EW52: 0 | EX52: 0 | EY52: 0 | FQ52: 0 | FR52: =P52 -> 75727.68 | FS52: 0 | FX52: 0 | FY52: 0 | GA52: [15 900 / 1,2 / 7,66] + 3% Трансп + 1,2% Заг.скл | GD52: 1 | GF52: 56064933 | GG52: 2 | GH52: 4 | GI52: 0 | GJ52: 0 | GK52: 0 | GL52: =ROUND(IF(AND(BH52=3,BI52=3,FS52<>0),P52,0),2) -> 0 | GM52: =ROUND(O52+X52+Y52,2)+GX52 -> 75727.68 | GN52: =IF(OR(BI52=0,BI52=1),GM52-GX52,0) -> 0 | GO52: =IF(BI52=2,GM52-GX52,0) -> 0 | GP52: =IF(BI52=4,GM52-GX52,0) -> 0 | GR52: 0 | GS52: 2 | GT52: 0 | GV52: =ROUND((GT52),6) -> 0 | GW52: 1 | GX52: =ROUND(HC52*I52,2) -> 0 | HA52: 0 | HB52: 0 | HC52: =GV52*GW52 -> 0 | HE52: 3 | HF52: 1,2 | HS52: 0 | IK52: 0
A53: 17 | B53: 1 | E53: 13 | F53: КА 7 | G53: Считыватель для установки на улице и в помещение,-40....+55гр интерфейс Wiegand 26-58, формат карт Mifare, EM-Marin,HID Prox RusGuard R-15 multi | H53: шт. | I53: =ROUND(ROUND(42,4),9) -> 42 | J53: 0 | K53: =ROUND(ROUND(42,4),9) -> 42 | O53: =ROUND(CP53,2) -> 580074.03 | P53: =ROUND((ROUND((AC53*I53),2)*BC53),2) -> 580074.03 | Q53: =(ROUND((ROUND(((ET53)*AV53*I53),2)*BB53),2)+ROUND((ROUND(((AE53-(EU53))*AV53*I53),2)*BS53),2)) -> 0 | R53: =ROUND((ROUND((AE53*AV53*I53),2)*BS53),2) -> 0 | S53: =ROUND((ROUND((AF53*AV53*I53),2)*BA53),2) -> 0 | T53: =ROUND(CU53*I53,2) -> 0 | U53: =CV53*I53 -> 0 | V53: =CW53*I53 -> 0 | W53: =ROUND(CX53*I53,2) -> 0 | X53: =ROUND(CY53,2) -> 0 | Y53: =ROUND(CZ53,2) -> 0 | AA53: 59213213 | AB53: =ROUND((AC53+AD53+AF53),6) -> 1803.04 | AC53: =ROUND((ES53),6) -> 1803.04 | AD53: =ROUND((((ET53)-(EU53))+AE53),6) -> 0 | AE53: =ROUND((EU53),6) -> 0 | AF53: =ROUND((EV53),6) -> 0 | AG53: =ROUND((AP53),6) -> 0 | AH53: =(EW53) -> 0 | AI53: =(EX53) -> 0 | AJ53: =(AS53) -> 0 | AK53: 1803.04 | AL53: 1803.04 | AM53: 0 | AN53: 0 | AO53: 0 | AP53: 0 | AQ53: 0 | AR53: 0 | AS53: 0 | AT53: 0 | AU53: 0 | AV53: 1 | AW53: 1 | AZ53: 1 | BA53: 1 | BB53: 1 | BC53: 7.66 | BH53: 3 | BI53: 3 | BM53: 746 | BN53: 0 | BP53: 0 | BQ53: 130 | BR53: 0 | BS53: 1 | BT53: 1 | BU53: 1 | BV53: 1 | BW53: 1 | BX53: 1 | BZ53: 0 | CA53: 0 | CE53: 30 | CF53: 0 | CG53: 0 | CM53: 0 | CO53: 0 | CP53: =(P53+Q53+S53) -> 580074.03 | CQ53: =ROUND((ROUND((AC53*1),2)*BC53),2) -> 13811.29 | CR53: =(ROUND((ROUND(((ET53)*AV53*1),2)*BB53),2)+ROUND((ROUND(((AE53-(EU53))*AV53*1),2)*BS53),2)) -> 0 | CS53: =ROUND((ROUND((AE53*AV53*1),2)*BS53),2) -> 0 | CT53: =ROUND((ROUND((AF53*AV53*1),2)*BA53),2) -> 0 | CU53: =AG53 -> 0 | CV53: =(AH53*AV53) -> 0 | CW53: =AI53 -> 0 | CX53: =AJ53 -> 0 | CY53: =(((S53+R53)*AT53)/100) -> 0 | CZ53: =(((S53+R53)*AU53)/100) -> 0 | DN53: 0 | DO53: 0 | DP53: 1 | DQ53: 1 | DU53: 1010 | DV53: шт. | DW53: шт. | DX53: 1 | EE53: 58808284 | EF53: 130 | EG53: Сметная стоимость оборудования | EH53: 0 | EJ53: 3 | EK53: 746 | EL53: ТСН-2001.13. Сметная стоимость оборудования | EM53: ТСН-2001.13 | EQ53: 0 | ER53: 1803.04 | ES53: 1803.04 | ET53: 0 | EU53: 0 | EV53: 0 | EW53: 0 | EX53: 0 | EY53: 0 | EZ53: 5 | FC53: 1 | FD53: 18 | FF53: 15900 | FQ53: 0 | FR53: =P53 -> 580074.03 | FS53: 0 | FX53: 0 | FY53: 0 | GA53: [15 900 / 1,2 / 7,66] + 3% Трансп + 1,2% Заг.скл | GD53: 1 | GF53: 56064933 | GG53: 2 | GH53: 3 | GI53: 5 | GJ53: 0 | GK53: 0 | GL53: =ROUND(IF(AND(BH53=3,BI53=3,FS53<>0),P53,0),2) -> 0 | GM53: =ROUND(O53+X53+Y53,2)+GX53 -> 580074.03 | GN53: =IF(OR(BI53=0,BI53=1),GM53-GX53,0) -> 0 | GO53: =IF(BI53=2,GM53-GX53,0) -> 0 | GP53: =IF(BI53=4,GM53-GX53,0) -> 0 | GR53: 2 | GS53: 1 | GT53: 0 | GV53: =ROUND((GT53),6) -> 0 | GW53: 1 | GX53: =ROUND(HC53*I53,2) -> 0 | HA53: 0 | HB53: 0 | HC53: =GV53*GW53 -> 0 | HE53: 3 | HF53: 1,2 | HS53: 0 | IK53: 0
A54: 17 | B54: 1 | C54: =ROW(SmtRes!A60) -> 60 | D54: =ROW(EtalonRes!A66) -> 66 | E54: 14 | F54: 4.10-76-10 | G54: Монтаж ключа или кнопки на панели | H54: 1 ШТ. | I54: =ROUND(ROUND(12,4),9) -> 12 | J54: 0 | K54: =ROUND(ROUND(12,4),9) -> 12 | O54: =ROUND(CP54,2) -> 184.36 | P54: =ROUND((ROUND((AC54*AW54*I54),2)*BC54),2) -> 20.04 | Q54: =(ROUND((ROUND((((ET54*1.1))*AV54*I54),2)*BB54),2)+ROUND((ROUND(((AE54-((EU54*1.1)))*AV54*I54),2)*BS54),2)) -> 0 | R54: =ROUND((ROUND((AE54*AV54*I54),2)*BS54),2) -> 0 | S54: =ROUND((ROUND((AF54*AV54*I54),2)*BA54),2) -> 164.32 | T54: =ROUND(CU54*I54,2) -> 0 | U54: =CV54*I54 -> 13.8204 | V54: =CW54*I54 -> 0 | W54: =ROUND(CX54*I54,2) -> 0 | X54: =ROUND(CY54,2) -> 156.1 | Y54: =ROUND(CZ54,2) -> 87.09 | AA54: 59213216 | AB54: =ROUND((AC54+AD54+AF54),6) -> 14.749 | AC54: =ROUND(((ES54*1)),6) -> 1.67 | AD54: =ROUND(((((ET54*1.1))-((EU54*1.1)))+AE54),6) -> 0 | AE54: =ROUND(((EU54*1.1)),6) -> 0 | AF54: =ROUND(((EV54*1.1)),6) -> 13.079 | AG54: =ROUND((AP54),6) -> 0 | AH54: =((EW54*1.1)) -> 1.1 | AI54: =((EX54*1.1)) -> 0 | AJ54: =(AS54) -> 0 | AK54: 13.56 | AL54: 1.67 | AM54: 0 | AN54: 0 | AO54: 11.89 | AP54: 0 | AQ54: 1 | AR54: 0 | AS54: 0 | AT54: 95 | AU54: 53 | AV54: 1.047 | AW54: 1 | AZ54: 1 | BA54: 1 | BB54: 1 | BC54: 1 | BH54: 0 | BI54: 2 | BJ54: ТСН-2001.4 Доп. 79, Сб. 10, т. 76, поз. 10 | BM54: 69 | BN54: 58808062 | BO54: 4.10-76-10 | BP54: 1 | BQ54: 40 | BR54: 0 | BS54: 1 | BT54: 1 | BU54: 1 | BV54: 1 | BW54: 1 | BX54: 1 | BZ54: 95 | CA54: 53 | CE54: 30 | CF54: 0 | CG54: 0 | CM54: 0 | CN54: Поправка: Гл.12.Прил.8.п.8. 5_12.00.01.11.003 Наименование: При наличии усложненных условий производства работ (стесненность, сложность складирования и транспортной логистики, наличие в зоне производства работ действующего технологического оборудования или движения технологического транспорта и т.п.) для объектов, расположенных за пределами территории круговой магистральной системы улиц "Садовое кольцо" и за пределами Третьего транспортного кольца города Москвы пунктов "а" и "б", но в пределах Московской кольцевой автомобильной дороги | CO54: 0 | CP54: =(P54+Q54+S54) -> 184.36 | CQ54: =ROUND((ROUND((AC54*AW54*1),2)*BC54),2) -> 1.67 | CR54: =(ROUND((ROUND((((ET54*1.1))*AV54*1),2)*BB54),2)+ROUND((ROUND(((AE54-((EU54*1.1)))*AV54*1),2)*BS54),2)) -> 0 | CS54: =ROUND((ROUND((AE54*AV54*1),2)*BS54),2) -> 0 | CT54: =ROUND((ROUND((AF54*AV54*1),2)*BA54),2) -> 13.69 | CU54: =AG54 -> 0 | CV54: =(AH54*AV54) -> 1.1517 | CW54: =AI54 -> 0 | CX54: =AJ54 -> 0 | CY54: =(((S54+R54)*AT54)/100) -> 156.104 | CZ54: =(((S54+R54)*AU54)/100) -> 87.0896 | DB54: 13 | DD54: *1 | DE54: *1,1 | DF54: *1,1 | DG54: *1,1 | DI54: *1,1 | DJ54: *1,1 | DN54: 0 | DO54: 0 | DP54: 1 | DQ54: 1 | DU54: 1013 | DV54: 1 ШТ. | DW54: 1 ШТ. | DX54: 1 | EE54: 58808179 | EF54: 40 | EG54: Монтаж оборудования | EH54: 0 | EJ54: 2 | EK54: 69 | EL54: ТСН-2001.4-10. Монтаж радиотелевизионного и электронного оборудования | EM54: ТСН-2001.4-10-2 | EO54: Поправка: Гл.12.Прил.8.п.8. 5_12.00.01.11.003 | EQ54: 0 | ER54: 13.56 | ES54: 1.67 | ET54: 0 | EU54: 0 | EV54: 11.89 | EW54: 1 | EX54: 0 | EY54: 0 | FQ54: 0 | FR54: 0 | FS54: 0 | FX54: 95 | FY54: 53 | GD54: 1 | GF54: -508473279 | GG54: 2 | GH54: 1 | GI54: 2 | GJ54: 0 | GK54: 0 | GL54: =ROUND(IF(AND(BH54=3,BI54=3,FS54<>0),P54,0),2) -> 0 | GM54: =ROUND(O54+X54+Y54,2)+GX54 -> 427.55 | GN54: =IF(OR(BI54=0,BI54=1),GM54-GX54,0) -> 0 | GO54: =IF(BI54=2,GM54-GX54,0) -> 427.55 | GP54: =IF(BI54=4,GM54-GX54,0) -> 0 | GR54: 0 | GS54: 3 | GT54: 0 | GV54: =ROUND((GT54),6) -> 0 | GW54: 1 | GX54: =ROUND(HC54*I54,2) -> 0 | HA54: 0 | HB54: 0 | HC54: =GV54*GW54 -> 0 | HS54: 0 | IK54: 0
A55: 17 | B55: 1 | C55: =ROW(SmtRes!A64) -> 64 | D55: =ROW(EtalonRes!A70) -> 70 | E55: 14 | F55: 4.10-76-10 | G55: Монтаж ключа или кнопки на панели | H55: 1 ШТ. | I55: =ROUND(ROUND(12,4),9) -> 12 | J55: 0 | K55: =ROUND(ROUND(12,4),9) -> 12 | O55: =ROUND(CP55,2) -> 9408.9 | P55: =ROUND((ROUND((AC55*AW55*I55),2)*BC55),2) -> 372.94 | Q55: =(ROUND((ROUND((((ET55*1.1))*AV55*I55),2)*BB55),2)+ROUND((ROUND(((AE55-((EU55*1.1)))*AV55*I55),2)*BS55),2)) -> 0 | R55: =ROUND((ROUND((AE55*AV55*I55),2)*BS55),2) -> 0 | S55: =ROUND((ROUND((AF55*AV55*I55),2)*BA55),2) -> 9035.96 | T55: =ROUND(CU55*I55,2) -> 0 | U55: =CV55*I55 -> 13.8204 | V55: =CW55*I55 -> 0 | W55: =ROUND(CX55*I55,2) -> 0 | X55: =ROUND(CY55,2) -> 8584.16 | Y55: =ROUND(CZ55,2) -> 4789.06 | AA55: 59213213 | AB55: =ROUND((AC55+AD55+AF55),6) -> 14.749 | AC55: =ROUND(((ES55*1)),6) -> 1.67 | AD55: =ROUND(((((ET55*1.1))-((EU55*1.1)))+AE55),6) -> 0 | AE55: =ROUND(((EU55*1.1)),6) -> 0 | AF55: =ROUND(((EV55*1.1)),6) -> 13.079 | AG55: =ROUND((AP55),6) -> 0 | AH55: =((EW55*1.1)) -> 1.1 | AI55: =((EX55*1.1)) -> 0 | AJ55: =(AS55) -> 0 | AK55: 13.56 | AL55: 1.67 | AM55: 0 | AN55: 0 | AO55: 11.89 | AP55: 0 | AQ55: 1 | AR55: 0 | AS55: 0 | AT55: 95 | AU55: 53 | AV55: 1.047 | AW55: 1 | AZ55: 1 | BA55: 54.99 | BB55: 1 | BC55: 18.61 | BH55: 0 | BI55: 2 | BJ55: ТСН-2001.4 Доп. 79, Сб. 10, т. 76, поз. 10 | BM55: 69 | BN55: 58808062 | BO55: 4.10-76-10 | BP55: 1 | BQ55: 40 | BR55: 0 | BS55: 54.99 | BT55: 1 | BU55: 1 | BV55: 1 | BW55: 1 | BX55: 1 | BZ55: 95 | CA55: 53 | CE55: 30 | CF55: 0 | CG55: 0 | CM55: 0 | CN55: Поправка: Гл.12.Прил.8.п.8. 5_12.00.01.11.003 Наименование: При наличии усложненных условий производства работ (стесненность, сложность складирования и транспортной логистики, наличие в зоне производства работ действующего технологического оборудования или движения технологического транспорта и т.п.) для объектов, расположенных за пределами территории круговой магистральной системы улиц "Садовое кольцо" и за пределами Третьего транспортного кольца города Москвы пунктов "а" и "б", но в пределах Московской кольцевой автомобильной дороги | CO55: 0 | CP55: =(P55+Q55+S55) -> 9408.9 | CQ55: =ROUND((ROUND((AC55*AW55*1),2)*BC55),2) -> 31.08 | CR55: =(ROUND((ROUND((((ET55*1.1))*AV55*1),2)*BB55),2)+ROUND((ROUND(((AE55-((EU55*1.1)))*AV55*1),2)*BS55),2)) -> 0 | CS55: =ROUND((ROUND((AE55*AV55*1),2)*BS55),2) -> 0 | CT55: =ROUND((ROUND((AF55*AV55*1),2)*BA55),2) -> 752.81 | CU55: =AG55 -> 0 | CV55: =(AH55*AV55) -> 1.1517 | CW55: =AI55 -> 0 | CX55: =AJ55 -> 0 | CY55: =(((S55+R55)*AT55)/100) -> 8584.162 | CZ55: =(((S55+R55)*AU55)/100) -> 4789.0588 | DB55: 14 | DD55: *1 | DE55: *1,1 | DF55: *1,1 | DG55: *1,1 | DI55: *1,1 | DJ55: *1,1 | DN55: 0 | DO55: 0 | DP55: 1 | DQ55: 1 | DU55: 1013 | DV55: 1 ШТ. | DW55: 1 ШТ. | DX55: 1 | EE55: 58808179 | EF55: 40 | EG55: Монтаж оборудования | EH55: 0 | EJ55: 2 | EK55: 69 | EL55: ТСН-2001.4-10. Монтаж радиотелевизионного и электронного оборудования | EM55: ТСН-2001.4-10-2 | EO55: Поправка: Гл.12.Прил.8.п.8. 5_12.00.01.11.003 | EQ55: 0 | ER55: 13.56 | ES55: 1.67 | ET55: 0 | EU55: 0 | EV55: 11.89 | EW55: 1 | EX55: 0 | EY55: 0 | FQ55: 0 | FR55: 0 | FS55: 0 | FX55: 95 | FY55: 53 | GD55: 1 | GF55: -508473279 | GG55: 2 | GH55: 1 | GI55: 2 | GJ55: 0 | GK55: 0 | GL55: =ROUND(IF(AND(BH55=3,BI55=3,FS55<>0),P55,0),2) -> 0 | GM55: =ROUND(O55+X55+Y55,2)+GX55 -> 22782.12 | GN55: =IF(OR(BI55=0,BI55=1),GM55-GX55,0) -> 0 | GO55: =IF(BI55=2,GM55-GX55,0) -> 22782.12 | GP55: =IF(BI55=4,GM55-GX55,0) -> 0 | GR55: 0 | GS55: 3 | GT55: 0 | GV55: =ROUND((GT55),6) -> 0 | GW55: 1 | GX55: =ROUND(HC55*I55,2) -> 0 | HA55: 0 | HB55: 0 | HC55: =GV55*GW55 -> 0 | HS55: 0 | IK55: 0
A56: 18 | B56: 1 | C56: 60 | E56: 14,1 | F56: КА 8 | G56: Кнопка экстренного выхода ST-FR115 | H56: шт. | I56: =I54*J56 -> 12 | J56: 1 | K56: 1 | O56: =ROUND(CP56,2) -> 1187.28 | P56: =ROUND((ROUND((AC56*AW56*I56),2)*BC56),2) -> 1187.28 | Q56: =(ROUND((ROUND(((ET56)*AV56*I56),2)*BB56),2)+ROUND((ROUND(((AE56-(EU56))*AV56*I56),2)*BS56),2)) -> 0 | R56: =ROUND((ROUND((AE56*AV56*I56),2)*BS56),2) -> 0 | S56: =ROUND((ROUND((AF56*AV56*I56),2)*BA56),2) -> 0 | T56: =ROUND(CU56*I56,2) -> 0 | U56: =CV56*I56 -> 0 | V56: =CW56*I56 -> 0 | W56: =ROUND(CX56*I56,2) -> 0 | X56: =ROUND(CY56,2) -> 0 | Y56: =ROUND(CZ56,2) -> 0 | AA56: 59213216 | AB56: =ROUND((AC56+AD56+AF56),6) -> 98.94 | AC56: =ROUND((ES56),6) -> 98.94 | AD56: =ROUND((((ET56)-(EU56))+AE56),6) -> 0 | AE56: =ROUND((EU56),6) -> 0 | AF56: =ROUND((EV56),6) -> 0 | AG56: =ROUND((AP56),6) -> 0 | AH56: =(EW56) -> 0 | AI56: =(EX56) -> 0 | AJ56: =(AS56) -> 0 | AK56: 98.94 | AL56: 98.94 | AM56: 0 | AN56: 0 | AO56: 0 | AP56: 0 | AQ56: 0 | AR56: 0 | AS56: 0 | AT56: 95 | AU56: 53 | AV56: 1 | AW56: 1 | AZ56: 1 | BA56: 1 | BB56: 1 | BC56: 1 | BH56: 3 | BI56: 2 | BM56: 69 | BN56: 0 | BP56: 0 | BQ56: 40 | BR56: 0 | BS56: 1 | BT56: 1 | BU56: 1 | BV56: 1 | BW56: 1 | BX56: 1 | BZ56: 95 | CA56: 53 | CE56: 30 | CF56: 0 | CG56: 0 | CM56: 0 | CO56: 0 | CP56: =(P56+Q56+S56) -> 1187.28 | CQ56: =ROUND((ROUND((AC56*AW56*1),2)*BC56),2) -> 98.94 | CR56: =(ROUND((ROUND(((ET56)*AV56*1),2)*BB56),2)+ROUND((ROUND(((AE56-(EU56))*AV56*1),2)*BS56),2)) -> 0 | CS56: =ROUND((ROUND((AE56*AV56*1),2)*BS56),2) -> 0 | CT56: =ROUND((ROUND((AF56*AV56*1),2)*BA56),2) -> 0 | CU56: =AG56 -> 0 | CV56: =(AH56*AV56) -> 0 | CW56: =AI56 -> 0 | CX56: =AJ56 -> 0 | CY56: =(((S56+R56)*AT56)/100) -> 0 | CZ56: =(((S56+R56)*AU56)/100) -> 0 | DN56: 0 | DO56: 0 | DP56: 1 | DQ56: 1 | DU56: 1010 | DV56: шт. | DW56: шт. | DX56: 1 | EE56: 58808179 | EF56: 40 | EG56: Монтаж оборудования | EH56: 0 | EJ56: 2 | EK56: 69 | EL56: ТСН-2001.4-10. Монтаж радиотелевизионного и электронного оборудования | EM56: ТСН-2001.4-10-2 | EQ56: 0 | ER56: 0 | ES56: 98.94 | ET56: 0 | EU56: 0 | EV56: 0 | EW56: 0 | EX56: 0 | FQ56: 0 | FR56: 0 | FS56: 0 | FX56: 95 | FY56: 53 | GA56: [1 150 / 1,2 / 9,88] + 2% Заг.скл | GD56: 1 | GF56: -871963031 | GG56: 2 | GH56: 4 | GI56: -2 | GJ56: 0 | GK56: 0 | GL56: =ROUND(IF(AND(BH56=3,BI56=3,FS56<>0),P56,0),2) -> 0 | GM56: =ROUND(O56+X56+Y56,2)+GX56 -> 1187.28 | GN56: =IF(OR(BI56=0,BI56=1),GM56-GX56,0) -> 0 | GO56: =IF(BI56=2,GM56-GX56,0) -> 1187.28 | GP56: =IF(BI56=4,GM56-GX56,0) -> 0 | GR56: 0 | GS56: 2 | GT56: 0 | GV56: =ROUND((GT56),6) -> 0 | GW56: 1 | GX56: =ROUND(HC56*I56,2) -> 0 | HA56: 0 | HB56: 0 | HC56: =GV56*GW56 -> 0 | HE56: 0 | HF56: 2 | HS56: 0 | IK56: 0
A57: 18 | B57: 1 | C57: 64 | E57: 14,1 | F57: КА 8 | G57: Кнопка экстренного выхода ST-FR115 | H57: шт. | I57: =I55*J57 -> 12 | J57: 1 | K57: 1 | O57: =ROUND(CP57,2) -> 11730.33 | P57: =ROUND((ROUND((AC57*AW57*I57),2)*BC57),2) -> 11730.33 | Q57: =(ROUND((ROUND(((ET57)*AV57*I57),2)*BB57),2)+ROUND((ROUND(((AE57-(EU57))*AV57*I57),2)*BS57),2)) -> 0 | R57: =ROUND((ROUND((AE57*AV57*I57),2)*BS57),2) -> 0 | S57: =ROUND((ROUND((AF57*AV57*I57),2)*BA57),2) -> 0 | T57: =ROUND(CU57*I57,2) -> 0 | U57: =CV57*I57 -> 0 | V57: =CW57*I57 -> 0 | W57: =ROUND(CX57*I57,2) -> 0 | X57: =ROUND(CY57,2) -> 0 | Y57: =ROUND(CZ57,2) -> 0 | AA57: 59213213 | AB57: =ROUND((AC57+AD57+AF57),6) -> 98.94 | AC57: =ROUND((ES57),6) -> 98.94 | AD57: =ROUND((((ET57)-(EU57))+AE57),6) -> 0 | AE57: =ROUND((EU57),6) -> 0 | AF57: =ROUND((EV57),6) -> 0 | AG57: =ROUND((AP57),6) -> 0 | AH57: =(EW57) -> 0 | AI57: =(EX57) -> 0 | AJ57: =(AS57) -> 0 | AK57: 98.94 | AL57: 98.94 | AM57: 0 | AN57: 0 | AO57: 0 | AP57: 0 | AQ57: 0 | AR57: 0 | AS57: 0 | AT57: 95 | AU57: 53 | AV57: 1 | AW57: 1 | AZ57: 1 | BA57: 1 | BB57: 1 | BC57: 9.88 | BH57: 3 | BI57: 2 | BM57: 69 | BN57: 0 | BP57: 0 | BQ57: 40 | BR57: 0 | BS57: 1 | BT57: 1 | BU57: 1 | BV57: 1 | BW57: 1 | BX57: 1 | BZ57: 95 | CA57: 53 | CE57: 30 | CF57: 0 | CG57: 0 | CM57: 0 | CO57: 0 | CP57: =(P57+Q57+S57) -> 11730.33 | CQ57: =ROUND((ROUND((AC57*AW57*1),2)*BC57),2) -> 977.53 | CR57: =(ROUND((ROUND(((ET57)*AV57*1),2)*BB57),2)+ROUND((ROUND(((AE57-(EU57))*AV57*1),2)*BS57),2)) -> 0 | CS57: =ROUND((ROUND((AE57*AV57*1),2)*BS57),2) -> 0 | CT57: =ROUND((ROUND((AF57*AV57*1),2)*BA57),2) -> 0 | CU57: =AG57 -> 0 | CV57: =(AH57*AV57) -> 0 | CW57: =AI57 -> 0 | CX57: =AJ57 -> 0 | CY57: =(((S57+R57)*AT57)/100) -> 0 | CZ57: =(((S57+R57)*AU57)/100) -> 0 | DN57: 0 | DO57: 0 | DP57: 1 | DQ57: 1 | DU57: 1010 | DV57: шт. | DW57: шт. | DX57: 1 | EE57: 58808179 | EF57: 40 | EG57: Монтаж оборудования | EH57: 0 | EJ57: 2 | EK57: 69 | EL57: ТСН-2001.4-10. Монтаж радиотелевизионного и электронного оборудования | EM57: ТСН-2001.4-10-2 | EQ57: 0 | ER57: 130.41 | ES57: 98.94 | ET57: 0 | EU57: 0 | EV57: 0 | EW57: 0 | EX57: 0 | EZ57: 5 | FC57: 1 | FD57: 18 | FF57: 1150 | FQ57: 0 | FR57: 0 | FS57: 0 | FX57: 95 | FY57: 53 | GA57: [1 150 / 1,2 / 9,88] + 2% Заг.скл | GD57: 1 | GF57: -871963031 | GG57: 2 | GH57: 3 | GI57: 5 | GJ57: 0 | GK57: 0 | GL57: =ROUND(IF(AND(BH57=3,BI57=3,FS57<>0),P57,0),2) -> 0 | GM57: =ROUND(O57+X57+Y57,2)+GX57 -> 11730.33 | GN57: =IF(OR(BI57=0,BI57=1),GM57-GX57,0) -> 0 | GO57: =IF(BI57=2,GM57-GX57,0) -> 11730.33 | GP57: =IF(BI57=4,GM57-GX57,0) -> 0 | GR57: 2 | GS57: 1 | GT57: 0 | GV57: =ROUND((GT57),6) -> 0 | GW57: 1 | GX57: =ROUND(HC57*I57,2) -> 0 | HA57: 0 | HB57: 0 | HC57: =GV57*GW57 -> 0 | HE57: 0 | HF57: 2 | HS57: 0 | IK57: 0
A58: 17 | B58: 1 | C58: =ROW(SmtRes!A66) -> 66 | D58: =ROW(EtalonRes!A73) -> 73 | E58: 15 | F58: 4.10-59-3 | G58: Монтаж детали на пультах и панелях - кнопка | H58: 1 ШТ. | I58: =ROUND(ROUND(27,4),9) -> 27 | J58: 0 | K58: =ROUND(ROUND(27,4),9) -> 27 | O58: =ROUND(CP58,2) -> 332.73 | P58: =ROUND((ROUND((AC58*AW58*I58),2)*BC58),2) -> 0 | Q58: =(ROUND((ROUND((((ET58*1.1))*AV58*I58),2)*BB58),2)+ROUND((ROUND(((AE58-((EU58*1.1)))*AV58*I58),2)*BS58),2)) -> 0 | R58: =ROUND((ROUND((AE58*AV58*I58),2)*BS58),2) -> 0 | S58: =ROUND((ROUND((AF58*AV58*I58),2)*BA58),2) -> 332.73 | T58: =ROUND(CU58*I58,2) -> 0 | U58: =CV58*I58 -> 31.0959 | V58: =CW58*I58 -> 0 | W58: =ROUND(CX58*I58,2) -> 0 | X58: =ROUND(CY58,2) -> 316.09 | Y58: =ROUND(CZ58,2) -> 176.35 | AA58: 59213216 | AB58: =ROUND((AC58+AD58+AF58),6) -> 11.77 | AC58: =ROUND(((ES58*1)),6) -> 0 | AD58: =ROUND(((((ET58*1.1))-((EU58*1.1)))+AE58),6) -> 0 | AE58: =ROUND(((EU58*1.1)),6) -> 0 | AF58: =ROUND(((EV58*1.1)),6) -> 11.77 | AG58: =ROUND((AP58),6) -> 0 | AH58: =((EW58*1.1)) -> 1.1 | AI58: =((EX58*1.1)) -> 0 | AJ58: =(AS58) -> 0 | AK58: 10.7 | AL58: 0 | AM58: 0 | AN58: 0 | AO58: 10.7 | AP58: 0 | AQ58: 1 | AR58: 0 | AS58: 0 | AT58: 95 | AU58: 53 | AV58: 1.047 | AW58: 1 | AZ58: 1 | BA58: 1 | BB58: 1 | BC58: 1 | BH58: 0 | BI58: 2 | BJ58: ТСН-2001.4 Доп. 67, Сб. 10, т. 59, поз. 3 | BM58: 69 | BN58: 58808062 | BO58: 4.10-59-3 | BP58: 1 | BQ58: 40 | BR58: 0 | BS58: 1 | BT58: 1 | BU58: 1 | BV58: 1 | BW58: 1 | BX58: 1 | BZ58: 95 | CA58: 53 | CE58: 30 | CF58: 0 | CG58: 0 | CM58: 0 | CN58: Поправка: Гл.12.Прил.8.п.8. 5_12.00.01.11.003 Наименование: При наличии усложненных условий производства работ (стесненность, сложность складирования и транспортной логистики, наличие в зоне производства работ действующего технологического оборудования или движения технологического транспорта и т.п.) для объектов, расположенных за пределами территории круговой магистральной системы улиц "Садовое кольцо" и за пределами Третьего транспортного кольца города Москвы пунктов "а" и "б", но в пределах Московской кольцевой автомобильной дороги | CO58: 0 | CP58: =(P58+Q58+S58) -> 332.73 | CQ58: =ROUND((ROUND((AC58*AW58*1),2)*BC58),2) -> 0 | CR58: =(ROUND((ROUND((((ET58*1.1))*AV58*1),2)*BB58),2)+ROUND((ROUND(((AE58-((EU58*1.1)))*AV58*1),2)*BS58),2)) -> 0 | CS58: =ROUND((ROUND((AE58*AV58*1),2)*BS58),2) -> 0 | CT58: =ROUND((ROUND((AF58*AV58*1),2)*BA58),2) -> 12.32 | CU58: =AG58 -> 0 | CV58: =(AH58*AV58) -> 1.1517 | CW58: =AI58 -> 0 | CX58: =AJ58 -> 0 | CY58: =(((S58+R58)*AT58)/100) -> 316.0935 | CZ58: =(((S58+R58)*AU58)/100) -> 176.3469 | DB58: 15 | DD58: *1 | DE58: *1,1 | DF58: *1,1 | DG58: *1,1 | DI58: *1,1 | DJ58: *1,1 | DN58: 0 | DO58: 0 | DP58: 1 | DQ58: 1 | DU58: 1013 | DV58: 1 ШТ. | DW58: 1 ШТ. | DX58: 1 | EE58: 58808179 | EF58: 40 | EG58: Монтаж оборудования | EH58: 0 | EJ58: 2 | EK58: 69 | EL58: ТСН-2001.4-10. Монтаж радиотелевизионного и электронного оборудования | EM58: ТСН-2001.4-10-2 | EO58: Поправка: Гл.12.Прил.8.п.8. 5_12.00.01.11.003 | EQ58: 0 | ER58: 10.7 | ES58: 0 | ET58: 0 | EU58: 0 | EV58: 10.7 | EW58: 1 | EX58: 0 | EY58: 0 | FQ58: 0 | FR58: 0 | FS58: 0 | FX58: 95 | FY58: 53 | GD58: 1 | GF58: -1595364230 | GG58: 2 | GH58: 1 | GI58: 2 | GJ58: 0 | GK58: 0 | GL58: =ROUND(IF(AND(BH58=3,BI58=3,FS58<>0),P58,0),2) -> 0 | GM58: =ROUND(O58+X58+Y58,2)+GX58 -> 825.17 | GN58: =IF(OR(BI58=0,BI58=1),GM58-GX58,0) -> 0 | GO58: =IF(BI58=2,GM58-GX58,0) -> 825.17 | GP58: =IF(BI58=4,GM58-GX58,0) -> 0 | GR58: 0 | GS58: 3 | GT58: 0 | GV58: =ROUND((GT58),6) -> 0 | GW58: 1 | GX58: =ROUND(HC58*I58,2) -> 0 | HA58: 0 | HB58: 0 | HC58: =GV58*GW58 -> 0 | HS58: 0 | IK58: 0
A59: 17 | B59: 1 | C59: =ROW(SmtRes!A68) -> 68 | D59: =ROW(EtalonRes!A76) -> 76 | E59: 15 | F59: 4.10-59-3 | G59: Монтаж детали на пультах и панелях - кнопка | H59: 1 ШТ. | I59: =ROUND(ROUND(27,4),9) -> 27 | J59: 0 | K59: =ROUND(ROUND(27,4),9) -> 27 | O59: =ROUND(CP59,2) -> 18296.82 | P59: =ROUND((ROUND((AC59*AW59*I59),2)*BC59),2) -> 0 | Q59: =(ROUND((ROUND((((ET59*1.1))*AV59*I59),2)*BB59),2)+ROUND((ROUND(((AE59-((EU59*1.1)))*AV59*I59),2)*BS59),2)) -> 0 | R59: =ROUND((ROUND((AE59*AV59*I59),2)*BS59),2) -> 0 | S59: =ROUND((ROUND((AF59*AV59*I59),2)*BA59),2) -> 18296.82 | T59: =ROUND(CU59*I59,2) -> 0 | U59: =CV59*I59 -> 31.0959 | V59: =CW59*I59 -> 0 | W59: =ROUND(CX59*I59,2) -> 0 | X59: =ROUND(CY59,2) -> 17381.98 | Y59: =ROUND(CZ59,2) -> 9697.31 | AA59: 59213213 | AB59: =ROUND((AC59+AD59+AF59),6) -> 11.77 | AC59: =ROUND(((ES59*1)),6) -> 0 | AD59: =ROUND(((((ET59*1.1))-((EU59*1.1)))+AE59),6) -> 0 | AE59: =ROUND(((EU59*1.1)),6) -> 0 | AF59: =ROUND(((EV59*1.1)),6) -> 11.77 | AG59: =ROUND((AP59),6) -> 0 | AH59: =((EW59*1.1)) -> 1.1 | AI59: =((EX59*1.1)) -> 0 | AJ59: =(AS59) -> 0 | AK59: 10.7 | AL59: 0 | AM59: 0 | AN59: 0 | AO59: 10.7 | AP59: 0 | AQ59: 1 | AR59: 0 | AS59: 0 | AT59: 95 | AU59: 53 | AV59: 1.047 | AW59: 1 | AZ59: 1 | BA59: 54.99 | BB59: 1 | BC59: 1 | BH59: 0 | BI59: 2 | BJ59: ТСН-2001.4 Доп. 67, Сб. 10, т. 59, поз. 3 | BM59: 69 | BN59: 58808062 | BO59: 4.10-59-3 | BP59: 1 | BQ59: 40 | BR59: 0 | BS59: 54.99 | BT59: 1 | BU59: 1 | BV59: 1 | BW59: 1 | BX59: 1 | BZ59: 95 | CA59: 53 | CE59: 30 | CF59: 0 | CG59: 0 | CM59: 0 | CN59: Поправка: Гл.12.Прил.8.п.8. 5_12.00.01.11.003 Наименование: При наличии усложненных условий производства работ (стесненность, сложность складирования и транспортной логистики, наличие в зоне производства работ действующего технологического оборудования или движения технологического транспорта и т.п.) для объектов, расположенных за пределами территории круговой магистральной системы улиц "Садовое кольцо" и за пределами Третьего транспортного кольца города Москвы пунктов "а" и "б", но в пределах Московской кольцевой автомобильной дороги | CO59: 0 | CP59: =(P59+Q59+S59) -> 18296.82 | CQ59: =ROUND((ROUND((AC59*AW59*1),2)*BC59),2) -> 0 | CR59: =(ROUND((ROUND((((ET59*1.1))*AV59*1),2)*BB59),2)+ROUND((ROUND(((AE59-((EU59*1.1)))*AV59*1),2)*BS59),2)) -> 0 | CS59: =ROUND((ROUND((AE59*AV59*1),2)*BS59),2) -> 0 | CT59: =ROUND((ROUND((AF59*AV59*1),2)*BA59),2) -> 677.48 | CU59: =AG59 -> 0 | CV59: =(AH59*AV59) -> 1.1517 | CW59: =AI59 -> 0 | CX59: =AJ59 -> 0 | CY59: =(((S59+R59)*AT59)/100) -> 17381.979 | CZ59: =(((S59+R59)*AU59)/100) -> 9697.3146 | DB59: 16 | DD59: *1 | DE59: *1,1 | DF59: *1,1 | DG59: *1,1 | DI59: *1,1 | DJ59: *1,1 | DN59: 0 | DO59: 0 | DP59: 1 | DQ59: 1 | DU59: 1013 | DV59: 1 ШТ. | DW59: 1 ШТ. | DX59: 1 | EE59: 58808179 | EF59: 40 | EG59: Монтаж оборудования | EH59: 0 | EJ59: 2 | EK59: 69 | EL59: ТСН-2001.4-10. Монтаж радиотелевизионного и электронного оборудования | EM59: ТСН-2001.4-10-2 | EO59: Поправка: Гл.12.Прил.8.п.8. 5_12.00.01.11.003 | EQ59: 0 | ER59: 10.7 | ES59: 0 | ET59: 0 | EU59: 0 | EV59: 10.7 | EW59: 1 | EX59: 0 | EY59: 0 | FQ59: 0 | FR59: 0 | FS59: 0 | FX59: 95 | FY59: 53 | GD59: 1 | GF59: -1595364230 | GG59: 2 | GH59: 1 | GI59: 2 | GJ59: 0 | GK59: 0 | GL59: =ROUND(IF(AND(BH59=3,BI59=3,FS59<>0),P59,0),2) -> 0 | GM59: =ROUND(O59+X59+Y59,2)+GX59 -> 45376.11 | GN59: =IF(OR(BI59=0,BI59=1),GM59-GX59,0) -> 0 | GO59: =IF(BI59=2,GM59-GX59,0) -> 45376.11 | GP59: =IF(BI59=4,GM59-GX59,0) -> 0 | GR59: 0 | GS59: 3 | GT59: 0 | GV59: =ROUND((GT59),6) -> 0 | GW59: 1 | GX59: =ROUND(HC59*I59,2) -> 0 | HA59: 0 | HB59: 0 | HC59: =GV59*GW59 -> 0 | HS59: 0 | IK59: 0
A60: 17 | B60: 1 | E60: 16 | F60: КА 9 | G60: Кнопка разблокировки дверей "ИПР 513-10" "АВАРИЙНЫЙ ВЫХОД" SB 1 | H60: шт. | I60: 27 | J60: 0 | K60: 27 | O60: =ROUND(CP60,2) -> 3329.64 | P60: =ROUND((ROUND((AC60*I60),2)*BC60),2) -> 3329.64 | Q60: =(ROUND((ROUND(((ET60)*AV60*I60),2)*BB60),2)+ROUND((ROUND(((AE60-(EU60))*AV60*I60),2)*BS60),2)) -> 0 | R60: =ROUND((ROUND((AE60*AV60*I60),2)*BS60),2) -> 0 | S60: =ROUND((ROUND((AF60*AV60*I60),2)*BA60),2) -> 0 | T60: =ROUND(CU60*I60,2) -> 0 | U60: =CV60*I60 -> 0 | V60: =CW60*I60 -> 0 | W60: =ROUND(CX60*I60,2) -> 0 | X60: =ROUND(CY60,2) -> 0 | Y60: =ROUND(CZ60,2) -> 0 | AA60: 59213216 | AB60: =ROUND((AC60+AD60+AF60),6) -> 123.32 | AC60: =ROUND((ES60),6) -> 123.32 | AD60: =ROUND((((ET60)-(EU60))+AE60),6) -> 0 | AE60: =ROUND((EU60),6) -> 0 | AF60: =ROUND((EV60),6) -> 0 | AG60: =ROUND((AP60),6) -> 0 | AH60: =(EW60) -> 0 | AI60: =(EX60) -> 0 | AJ60: =(AS60) -> 0 | AK60: 123.32 | AL60: 123.32 | AM60: 0 | AN60: 0 | AO60: 0 | AP60: 0 | AQ60: 0 | AR60: 0 | AS60: 0 | AT60: 0 | AU60: 0 | AV60: 1 | AW60: 1 | AZ60: 1 | BA60: 1 | BB60: 1 | BC60: 1 | BH60: 3 | BI60: 3 | BM60: 746 | BN60: 0 | BP60: 0 | BQ60: 130 | BR60: 0 | BS60: 1 | BT60: 1 | BU60: 1 | BV60: 1 | BW60: 1 | BX60: 1 | BZ60: 0 | CA60: 0 | CE60: 30 | CF60: 0 | CG60: 0 | CM60: 0 | CO60: 0 | CP60: =(P60+Q60+S60) -> 3329.64 | CQ60: =ROUND((ROUND((AC60*1),2)*BC60),2) -> 123.32 | CR60: =(ROUND((ROUND(((ET60)*AV60*1),2)*BB60),2)+ROUND((ROUND(((AE60-(EU60))*AV60*1),2)*BS60),2)) -> 0 | CS60: =ROUND((ROUND((AE60*AV60*1),2)*BS60),2) -> 0 | CT60: =ROUND((ROUND((AF60*AV60*1),2)*BA60),2) -> 0 | CU60: =AG60 -> 0 | CV60: =(AH60*AV60) -> 0 | CW60: =AI60 -> 0 | CX60: =AJ60 -> 0 | CY60: =(((S60+R60)*AT60)/100) -> 0 | CZ60: =(((S60+R60)*AU60)/100) -> 0 | DN60: 0 | DO60: 0 | DP60: 1 | DQ60: 1 | DU60: 1010 | DV60: шт. | DW60: шт. | DX60: 1 | EE60: 58808284 | EF60: 130 | EG60: Сметная стоимость оборудования | EH60: 0 | EJ60: 3 | EK60: 746 | EL60: ТСН-2001.13. Сметная стоимость оборудования | EM60: ТСН-2001.13 | EQ60: 0 | ER60: 0 | ES60: 123.32 | ET60: 0 | EU60: 0 | EV60: 0 | EW60: 0 | EX60: 0 | EY60: 0 | FQ60: 0 | FR60: =P60 -> 3329.64 | FS60: 0 | FX60: 0 | FY60: 0 | GA60: [1 087,5 / 1,2 / 7,66] + 3% Трансп + 1,2% Заг.скл | GD60: 1 | GF60: -859608360 | GG60: 2 | GH60: 4 | GI60: -2 | GJ60: 0 | GK60: 0 | GL60: =ROUND(IF(AND(BH60=3,BI60=3,FS60<>0),P60,0),2) -> 0 | GM60: =ROUND(O60+X60+Y60,2)+GX60 -> 3329.64 | GN60: =IF(OR(BI60=0,BI60=1),GM60-GX60,0) -> 0 | GO60: =IF(BI60=2,GM60-GX60,0) -> 0 | GP60: =IF(BI60=4,GM60-GX60,0) -> 0 | GR60: 0 | GS60: 2 | GT60: 0 | GV60: =ROUND((GT60),6) -> 0 | GW60: 1 | GX60: =ROUND(HC60*I60,2) -> 0 | HA60: 0 | HB60: 0 | HC60: =GV60*GW60 -> 0 | HE60: 3 | HF60: 1,2 | HS60: 0 | IK60: 0
A61: 17 | B61: 1 | E61: 16 | F61: КА 9 | G61: Кнопка разблокировки дверей "ИПР 513-10" "АВАРИЙНЫЙ ВЫХОД" SB 1 | H61: шт. | I61: 27 | J61: 0 | K61: 27 | O61: =ROUND(CP61,2) -> 25505.04 | P61: =ROUND((ROUND((AC61*I61),2)*BC61),2) -> 25505.04 | Q61: =(ROUND((ROUND(((ET61)*AV61*I61),2)*BB61),2)+ROUND((ROUND(((AE61-(EU61))*AV61*I61),2)*BS61),2)) -> 0 | R61: =ROUND((ROUND((AE61*AV61*I61),2)*BS61),2) -> 0 | S61: =ROUND((ROUND((AF61*AV61*I61),2)*BA61),2) -> 0 | T61: =ROUND(CU61*I61,2) -> 0 | U61: =CV61*I61 -> 0 | V61: =CW61*I61 -> 0 | W61: =ROUND(CX61*I61,2) -> 0 | X61: =ROUND(CY61,2) -> 0 | Y61: =ROUND(CZ61,2) -> 0 | AA61: 59213213 | AB61: =ROUND((AC61+AD61+AF61),6) -> 123.32 | AC61: =ROUND((ES61),6) -> 123.32 | AD61: =ROUND((((ET61)-(EU61))+AE61),6) -> 0 | AE61: =ROUND((EU61),6) -> 0 | AF61: =ROUND((EV61),6) -> 0 | AG61: =ROUND((AP61),6) -> 0 | AH61: =(EW61) -> 0 | AI61: =(EX61) -> 0 | AJ61: =(AS61) -> 0 | AK61: 123.32 | AL61: 123.32 | AM61: 0 | AN61: 0 | AO61: 0 | AP61: 0 | AQ61: 0 | AR61: 0 | AS61: 0 | AT61: 0 | AU61: 0 | AV61: 1 | AW61: 1 | AZ61: 1 | BA61: 1 | BB61: 1 | BC61: 7.66 | BH61: 3 | BI61: 3 | BM61: 746 | BN61: 0 | BP61: 0 | BQ61: 130 | BR61: 0 | BS61: 1 | BT61: 1 | BU61: 1 | BV61: 1 | BW61: 1 | BX61: 1 | BZ61: 0 | CA61: 0 | CE61: 30 | CF61: 0 | CG61: 0 | CM61: 0 | CO61: 0 | CP61: =(P61+Q61+S61) -> 25505.04 | CQ61: =ROUND((ROUND((AC61*1),2)*BC61),2) -> 944.63 | CR61: =(ROUND((ROUND(((ET61)*AV61*1),2)*BB61),2)+ROUND((ROUND(((AE61-(EU61))*AV61*1),2)*BS61),2)) -> 0 | CS61: =ROUND((ROUND((AE61*AV61*1),2)*BS61),2) -> 0 | CT61: =ROUND((ROUND((AF61*AV61*1),2)*BA61),2) -> 0 | CU61: =AG61 -> 0 | CV61: =(AH61*AV61) -> 0 | CW61: =AI61 -> 0 | CX61: =AJ61 -> 0 | CY61: =(((S61+R61)*AT61)/100) -> 0 | CZ61: =(((S61+R61)*AU61)/100) -> 0 | DN61: 0 | DO61: 0 | DP61: 1 | DQ61: 1 | DU61: 1010 | DV61: шт. | DW61: шт. | DX61: 1 | EE61: 58808284 | EF61: 130 | EG61: Сметная стоимость оборудования | EH61: 0 | EJ61: 3 | EK61: 746 | EL61: ТСН-2001.13. Сметная стоимость оборудования | EM61: ТСН-2001.13 | EQ61: 0 | ER61: 123.32 | ES61: 123.32 | ET61: 0 | EU61: 0 | EV61: 0 | EW61: 0 | EX61: 0 | EY61: 0 | EZ61: 5 | FC61: 1 | FD61: 18 | FF61: 1087.5 | FQ61: 0 | FR61: =P61 -> 25505.04 | FS61: 0 | FX61: 0 | FY61: 0 | GA61: [1 087,5 / 1,2 / 7,66] + 3% Трансп + 1,2% Заг.скл | GD61: 1 | GF61: -859608360 | GG61: 2 | GH61: 3 | GI61: 5 | GJ61: 0 | GK61: 0 | GL61: =ROUND(IF(AND(BH61=3,BI61=3,FS61<>0),P61,0),2) -> 0 | GM61: =ROUND(O61+X61+Y61,2)+GX61 -> 25505.04 | GN61: =IF(OR(BI61=0,BI61=1),GM61-GX61,0) -> 0 | GO61: =IF(BI61=2,GM61-GX61,0) -> 0 | GP61: =IF(BI61=4,GM61-GX61,0) -> 0 | GR61: 2 | GS61: 1 | GT61: 0 | GV61: =ROUND((GT61),6) -> 0 | GW61: 1 | GX61: =ROUND(HC61*I61,2) -> 0 | HA61: 0 | HB61: 0 | HC61: =GV61*GW61 -> 0 | HE61: 3 | HF61: 1,2 | HS61: 0 | IK61: 0
A62: 17 | B62: 1 | C62: =ROW(SmtRes!A72) -> 72 | D62: =ROW(EtalonRes!A81) -> 81 | E62: 17 | F62: 4.10-173-2 | G62: Монтаж блока бесперебойного питания (ББП) в диспетчерской | H62: 1 ШТ. | I62: =ROUND(ROUND(2,4),9) -> 2 | J62: 0 | K62: =ROUND(ROUND(2,4),9) -> 2 | O62: =ROUND(CP62,2) -> 97.21 | P62: =ROUND((ROUND((AC62*AW62*I62),2)*BC62),2) -> 4.68 | Q62: =(ROUND((ROUND((((ET62*1.1))*AV62*I62),2)*BB62),2)+ROUND((ROUND(((AE62-((EU62*1.1)))*AV62*I62),2)*BS62),2)) -> 0 | R62: =ROUND((ROUND((AE62*AV62*I62),2)*BS62),2) -> 0 | S62: =ROUND((ROUND((AF62*AV62*I62),2)*BA62),2) -> 92.53 | T62: =ROUND(CU62*I62,2) -> 0 | U62: =CV62*I62 -> 7.324812 | V62: =CW62*I62 -> 0 | W62: =ROUND(CX62*I62,2) -> 0 | X62: =ROUND(CY62,2) -> 83.28 | Y62: =ROUND(CZ62,2) -> 42.56 | AA62: 59213216 | AB62: =ROUND((AC62+AD62+AF62),6) -> 46.527 | AC62: =ROUND(((ES62*1)),6) -> 2.34 | AD62: =ROUND(((((ET62*1.1))-((EU62*1.1)))+AE62),6) -> 0 | AE62: =ROUND(((EU62*1.1)),6) -> 0 | AF62: =ROUND(((EV62*1.1)),6) -> 44.187 | AG62: =ROUND((AP62),6) -> 0 | AH62: =((EW62*1.1)) -> 3.498 | AI62: =((EX62*1.1)) -> 0 | AJ62: =(AS62) -> 0 | AK62: 42.51 | AL62: 2.34 | AM62: 0 | AN62: 0 | AO62: 40.17 | AP62: 0 | AQ62: 3.18 | AR62: 0 | AS62: 0 | AT62: 90 | AU62: 46 | AV62: 1.047 | AW62: 1 | AZ62: 1 | BA62: 1 | BB62: 1 | BC62: 1 | BH62: 0 | BI62: 2 | BJ62: ТСН-2001.4 Доп. 67, Сб. 10, т. 173, поз. 2 | BM62: 68 | BN62: 58808062 | BO62: 4.10-173-2 | BP62: 1 | BQ62: 40 | BR62: 0 | BS62: 1 | BT62: 1 | BU62: 1 | BV62: 1 | BW62: 1 | BX62: 1 | BZ62: 90 | CA62: 46 | CE62: 30 | CF62: 0 | CG62: 0 | CM62: 0 | CN62: Поправка: Гл.12.Прил.8.п.8. 5_12.00.01.11.003 Наименование: При наличии усложненных условий производства работ (стесненность, сложность складирования и транспортной логистики, наличие в зоне производства работ действующего технологического оборудования или движения технологического транспорта и т.п.) для объектов, расположенных за пределами территории круговой магистральной системы улиц "Садовое кольцо" и за пределами Третьего транспортного кольца города Москвы пунктов "а" и "б", но в пределах Московской кольцевой автомобильной дороги | CO62: 0 | CP62: =(P62+Q62+S62) -> 97.21 | CQ62: =ROUND((ROUND((AC62*AW62*1),2)*BC62),2) -> 2.34 | CR62: =(ROUND((ROUND((((ET62*1.1))*AV62*1),2)*BB62),2)+ROUND((ROUND(((AE62-((EU62*1.1)))*AV62*1),2)*BS62),2)) -> 0 | CS62: =ROUND((ROUND((AE62*AV62*1),2)*BS62),2) -> 0 | CT62: =ROUND((ROUND((AF62*AV62*1),2)*BA62),2) -> 46.26 | CU62: =AG62 -> 0 | CV62: =(AH62*AV62) -> 3.662406 | CW62: =AI62 -> 0 | CX62: =AJ62 -> 0 | CY62: =(((S62+R62)*AT62)/100) -> 83.277 | CZ62: =(((S62+R62)*AU62)/100) -> 42.5638 | DB62: 17 | DD62: *1 | DE62: *1,1 | DF62: *1,1 | DG62: *1,1 | DI62: *1,1 | DJ62: *1,1 | DN62: 0 | DO62: 0 | DP62: 1 | DQ62: 1 | DU62: 1013 | DV62: 1 ШТ. | DW62: 1 ШТ. | DX62: 1 | EE62: 58808178 | EF62: 40 | EG62: Монтаж оборудования | EH62: 0 | EJ62: 2 | EK62: 68 | EL62: ТСН-2001.4-10. Прокладка и монтаж сетей связи | EM62: ТСН-2001.4-10-1 | EO62: Поправка: Гл.12.Прил.8.п.8. 5_12.00.01.11.003 | EQ62: 0 | ER62: 42.51 | ES62: 2.34 | ET62: 0 | EU62: 0 | EV62: 40.17 | EW62: 3.18 | EX62: 0 | EY62: 0 | FQ62: 0 | FR62: 0 | FS62: 0 | FX62: 90 | FY62: 46 | GD62: 1 | GF62: 1548884140 | GG62: 2 | GH62: 1 | GI62: 2 | GJ62: 0 | GK62: 0 | GL62: =ROUND(IF(AND(BH62=3,BI62=3,FS62<>0),P62,0),2) -> 0 | GM62: =ROUND(O62+X62+Y62,2)+GX62 -> 223.05 | GN62: =IF(OR(BI62=0,BI62=1),GM62-GX62,0) -> 0 | GO62: =IF(BI62=2,GM62-GX62,0) -> 223.05 | GP62: =IF(BI62=4,GM62-GX62,0) -> 0 | GR62: 0 | GS62: 3 | GT62: 0 | GV62: =ROUND((GT62),6) -> 0 | GW62: 1 | GX62: =ROUND(HC62*I62,2) -> 0 | HA62: 0 | HB62: 0 | HC62: =GV62*GW62 -> 0 | HS62: 0 | IK62: 0
A63: 17 | B63: 1 | C63: =ROW(SmtRes!A76) -> 76 | D63: =ROW(EtalonRes!A86) -> 86 | E63: 17 | F63: 4.10-173-2 | G63: Монтаж блока бесперебойного питания (ББП) в диспетчерской | H63: 1 ШТ. | I63: =ROUND(ROUND(2,4),9) -> 2 | J63: 0 | K63: =ROUND(ROUND(2,4),9) -> 2 | O63: =ROUND(CP63,2) -> 5136.24 | P63: =ROUND((ROUND((AC63*AW63*I63),2)*BC63),2) -> 48.02 | Q63: =(ROUND((ROUND((((ET63*1.1))*AV63*I63),2)*BB63),2)+ROUND((ROUND(((AE63-((EU63*1.1)))*AV63*I63),2)*BS63),2)) -> 0 | R63: =ROUND((ROUND((AE63*AV63*I63),2)*BS63),2) -> 0 | S63: =ROUND((ROUND((AF63*AV63*I63),2)*BA63),2) -> 5088.22 | T63: =ROUND(CU63*I63,2) -> 0 | U63: =CV63*I63 -> 7.324812 | V63: =CW63*I63 -> 0 | W63: =ROUND(CX63*I63,2) -> 0 | X63: =ROUND(CY63,2) -> 4579.4 | Y63: =ROUND(CZ63,2) -> 2340.58 | AA63: 59213213 | AB63: =ROUND((AC63+AD63+AF63),6) -> 46.527 | AC63: =ROUND(((ES63*1)),6) -> 2.34 | AD63: =ROUND(((((ET63*1.1))-((EU63*1.1)))+AE63),6) -> 0 | AE63: =ROUND(((EU63*1.1)),6) -> 0 | AF63: =ROUND(((EV63*1.1)),6) -> 44.187 | AG63: =ROUND((AP63),6) -> 0 | AH63: =((EW63*1.1)) -> 3.498 | AI63: =((EX63*1.1)) -> 0 | AJ63: =(AS63) -> 0 | AK63: 42.51 | AL63: 2.34 | AM63: 0 | AN63: 0 | AO63: 40.17 | AP63: 0 | AQ63: 3.18 | AR63: 0 | AS63: 0 | AT63: 90 | AU63: 46 | AV63: 1.047 | AW63: 1 | AZ63: 1 | BA63: 54.99 | BB63: 1 | BC63: 10.26 | BH63: 0 | BI63: 2 | BJ63: ТСН-2001.4 Доп. 67, Сб. 10, т. 173, поз. 2 | BM63: 68 | BN63: 58808062 | BO63: 4.10-173-2 | BP63: 1 | BQ63: 40 | BR63: 0 | BS63: 54.99 | BT63: 1 | BU63: 1 | BV63: 1 | BW63: 1 | BX63: 1 | BZ63: 90 | CA63: 46 | CE63: 30 | CF63: 0 | CG63: 0 | CM63: 0 | CN63: Поправка: Гл.12.Прил.8.п.8. 5_12.00.01.11.003 Наименование: При наличии усложненных условий производства работ (стесненность, сложность складирования и транспортной логистики, наличие в зоне производства работ действующего технологического оборудования или движения технологического транспорта и т.п.) для объектов, расположенных за пределами территории круговой магистральной системы улиц "Садовое кольцо" и за пределами Третьего транспортного кольца города Москвы пунктов "а" и "б", но в пределах Московской кольцевой автомобильной дороги | CO63: 0 | CP63: =(P63+Q63+S63) -> 5136.24 | CQ63: =ROUND((ROUND((AC63*AW63*1),2)*BC63),2) -> 24.01 | CR63: =(ROUND((ROUND((((ET63*1.1))*AV63*1),2)*BB63),2)+ROUND((ROUND(((AE63-((EU63*1.1)))*AV63*1),2)*BS63),2)) -> 0 | CS63: =ROUND((ROUND((AE63*AV63*1),2)*BS63),2) -> 0 | CT63: =ROUND((ROUND((AF63*AV63*1),2)*BA63),2) -> 2543.84 | CU63: =AG63 -> 0 | CV63: =(AH63*AV63) -> 3.662406 | CW63: =AI63 -> 0 | CX63: =AJ63 -> 0 | CY63: =(((S63+R63)*AT63)/100) -> 4579.398 | CZ63: =(((S63+R63)*AU63)/100) -> 2340.5812 | DB63: 18 | DD63: *1 | DE63: *1,1 | DF63: *1,1 | DG63: *1,1 | DI63: *1,1 | DJ63: *1,1 | DN63: 0 | DO63: 0 | DP63: 1 | DQ63: 1 | DU63: 1013 | DV63: 1 ШТ. | DW63: 1 ШТ. | DX63: 1 | EE63: 58808178 | EF63: 40 | EG63: Монтаж оборудования | EH63: 0 | EJ63: 2 | EK63: 68 | EL63: ТСН-2001.4-10. Прокладка и монтаж сетей связи | EM63: ТСН-2001.4-10-1 | EO63: Поправка: Гл.12.Прил.8.п.8. 5_12.00.01.11.003 | EQ63: 0 | ER63: 42.51 | ES63: 2.34 | ET63: 0 | EU63: 0 | EV63: 40.17 | EW63: 3.18 | EX63: 0 | EY63: 0 | FQ63: 0 | FR63: 0 | FS63: 0 | FX63: 90 | FY63: 46 | GD63: 1 | GF63: 1548884140 | GG63: 2 | GH63: 1 | GI63: 2 | GJ63: 0 | GK63: 0 | GL63: =ROUND(IF(AND(BH63=3,BI63=3,FS63<>0),P63,0),2) -> 0 | GM63: =ROUND(O63+X63+Y63,2)+GX63 -> 12056.22 | GN63: =IF(OR(BI63=0,BI63=1),GM63-GX63,0) -> 0 | GO63: =IF(BI63=2,GM63-GX63,0) -> 12056.22 | GP63: =IF(BI63=4,GM63-GX63,0) -> 0 | GR63: 0 | GS63: 3 | GT63: 0 | GV63: =ROUND((GT63),6) -> 0 | GW63: 1 | GX63: =ROUND(HC63*I63,2) -> 0 | HA63: 0 | HB63: 0 | HC63: =GV63*GW63 -> 0 | HS63: 0 | IK63: 0
A64: 17 | B64: 1 | E64: 18 | F64: КА 10 | G64: Резервный источник питания,12В ИВЭПР 12/3,5 2x7 -Р | H64: шт. | I64: =ROUND(ROUND(2,4),9) -> 2 | J64: 0 | K64: =ROUND(ROUND(2,4),9) -> 2 | O64: =ROUND(CP64,2) -> 1976.54 | P64: =ROUND((ROUND((AC64*I64),2)*BC64),2) -> 1976.54 | Q64: =(ROUND((ROUND(((ET64)*AV64*I64),2)*BB64),2)+ROUND((ROUND(((AE64-(EU64))*AV64*I64),2)*BS64),2)) -> 0 | R64: =ROUND((ROUND((AE64*AV64*I64),2)*BS64),2) -> 0 | S64: =ROUND((ROUND((AF64*AV64*I64),2)*BA64),2) -> 0 | T64: =ROUND(CU64*I64,2) -> 0 | U64: =CV64*I64 -> 0 | V64: =CW64*I64 -> 0 | W64: =ROUND(CX64*I64,2) -> 0 | X64: =ROUND(CY64,2) -> 0 | Y64: =ROUND(CZ64,2) -> 0 | AA64: 59213216 | AB64: =ROUND((AC64+AD64+AF64),6) -> 988.27 | AC64: =ROUND((ES64),6) -> 988.27 | AD64: =ROUND((((ET64)-(EU64))+AE64),6) -> 0 | AE64: =ROUND((EU64),6) -> 0 | AF64: =ROUND((EV64),6) -> 0 | AG64: =ROUND((AP64),6) -> 0 | AH64: =(EW64) -> 0 | AI64: =(EX64) -> 0 | AJ64: =(AS64) -> 0 | AK64: 988.27 | AL64: 988.27 | AM64: 0 | AN64: 0 | AO64: 0 | AP64: 0 | AQ64: 0 | AR64: 0 | AS64: 0 | AT64: 0 | AU64: 0 | AV64: 1 | AW64: 1 | AZ64: 1 | BA64: 1 | BB64: 1 | BC64: 1 | BH64: 3 | BI64: 3 | BM64: 746 | BN64: 0 | BP64: 0 | BQ64: 130 | BR64: 0 | BS64: 1 | BT64: 1 | BU64: 1 | BV64: 1 | BW64: 1 | BX64: 1 | BZ64: 0 | CA64: 0 | CE64: 30 | CF64: 0 | CG64: 0 | CM64: 0 | CO64: 0 | CP64: =(P64+Q64+S64) -> 1976.54 | CQ64: =ROUND((ROUND((AC64*1),2)*BC64),2) -> 988.27 | CR64: =(ROUND((ROUND(((ET64)*AV64*1),2)*BB64),2)+ROUND((ROUND(((AE64-(EU64))*AV64*1),2)*BS64),2)) -> 0 | CS64: =ROUND((ROUND((AE64*AV64*1),2)*BS64),2) -> 0 | CT64: =ROUND((ROUND((AF64*AV64*1),2)*BA64),2) -> 0 | CU64: =AG64 -> 0 | CV64: =(AH64*AV64) -> 0 | CW64: =AI64 -> 0 | CX64: =AJ64 -> 0 | CY64: =(((S64+R64)*AT64)/100) -> 0 | CZ64: =(((S64+R64)*AU64)/100) -> 0 | DN64: 0 | DO64: 0 | DP64: 1 | DQ64: 1 | DU64: 1010 | DV64: шт. | DW64: шт. | DX64: 1 | EE64: 58808284 | EF64: 130 | EG64: Сметная стоимость оборудования | EH64: 0 | EJ64: 3 | EK64: 746 | EL64: ТСН-2001.13. Сметная стоимость оборудования | EM64: ТСН-2001.13 | EQ64: 0 | ER64: 0 | ES64: 988.27 | ET64: 0 | EU64: 0 | EV64: 0 | EW64: 0 | EX64: 0 | EY64: 0 | FQ64: 0 | FR64: =P64 -> 1976.54 | FS64: 0 | FX64: 0 | FY64: 0 | GA64: [8 715 / 1,2 / 7,66] + 3% Трансп + 1,2% Заг.скл | GD64: 1 | GF64: 253381566 | GG64: 2 | GH64: 4 | GI64: -2 | GJ64: 0 | GK64: 0 | GL64: =ROUND(IF(AND(BH64=3,BI64=3,FS64<>0),P64,0),2) -> 0 | GM64: =ROUND(O64+X64+Y64,2)+GX64 -> 1976.54 | GN64: =IF(OR(BI64=0,BI64=1),GM64-GX64,0) -> 0 | GO64: =IF(BI64=2,GM64-GX64,0) -> 0 | GP64: =IF(BI64=4,GM64-GX64,0) -> 0 | GR64: 0 | GS64: 2 | GT64: 0 | GV64: =ROUND((GT64),6) -> 0 | GW64: 1 | GX64: =ROUND(HC64*I64,2) -> 0 | HA64: 0 | HB64: 0 | HC64: =GV64*GW64 -> 0 | HE64: 3 | HF64: 1,2 | HS64: 0 | IK64: 0
A65: 17 | B65: 1 | E65: 18 | F65: КА 10 | G65: Резервный источник питания,12В ИВЭПР 12/3,5 2x7 -Р | H65: шт. | I65: =ROUND(ROUND(2,4),9) -> 2 | J65: 0 | K65: =ROUND(ROUND(2,4),9) -> 2 | O65: =ROUND(CP65,2) -> 15140.3 | P65: =ROUND((ROUND((AC65*I65),2)*BC65),2) -> 15140.3 | Q65: =(ROUND((ROUND(((ET65)*AV65*I65),2)*BB65),2)+ROUND((ROUND(((AE65-(EU65))*AV65*I65),2)*BS65),2)) -> 0 | R65: =ROUND((ROUND((AE65*AV65*I65),2)*BS65),2) -> 0 | S65: =ROUND((ROUND((AF65*AV65*I65),2)*BA65),2) -> 0 | T65: =ROUND(CU65*I65,2) -> 0 | U65: =CV65*I65 -> 0 | V65: =CW65*I65 -> 0 | W65: =ROUND(CX65*I65,2) -> 0 | X65: =ROUND(CY65,2) -> 0 | Y65: =ROUND(CZ65,2) -> 0 | AA65: 59213213 | AB65: =ROUND((AC65+AD65+AF65),6) -> 988.27 | AC65: =ROUND((ES65),6) -> 988.27 | AD65: =ROUND((((ET65)-(EU65))+AE65),6) -> 0 | AE65: =ROUND((EU65),6) -> 0 | AF65: =ROUND((EV65),6) -> 0 | AG65: =ROUND((AP65),6) -> 0 | AH65: =(EW65) -> 0 | AI65: =(EX65) -> 0 | AJ65: =(AS65) -> 0 | AK65: 988.27 | AL65: 988.27 | AM65: 0 | AN65: 0 | AO65: 0 | AP65: 0 | AQ65: 0 | AR65: 0 | AS65: 0 | AT65: 0 | AU65: 0 | AV65: 1 | AW65: 1 | AZ65: 1 | BA65: 1 | BB65: 1 | BC65: 7.66 | BH65: 3 | BI65: 3 | BM65: 746 | BN65: 0 | BP65: 0 | BQ65: 130 | BR65: 0 | BS65: 1 | BT65: 1 | BU65: 1 | BV65: 1 | BW65: 1 | BX65: 1 | BZ65: 0 | CA65: 0 | CE65: 30 | CF65: 0 | CG65: 0 | CM65: 0 | CO65: 0 | CP65: =(P65+Q65+S65) -> 15140.3 | CQ65: =ROUND((ROUND((AC65*1),2)*BC65),2) -> 7570.15 | CR65: =(ROUND((ROUND(((ET65)*AV65*1),2)*BB65),2)+ROUND((ROUND(((AE65-(EU65))*AV65*1),2)*BS65),2)) -> 0 | CS65: =ROUND((ROUND((AE65*AV65*1),2)*BS65),2) -> 0 | CT65: =ROUND((ROUND((AF65*AV65*1),2)*BA65),2) -> 0 | CU65: =AG65 -> 0 | CV65: =(AH65*AV65) -> 0 | CW65: =AI65 -> 0 | CX65: =AJ65 -> 0 | CY65: =(((S65+R65)*AT65)/100) -> 0 | CZ65: =(((S65+R65)*AU65)/100) -> 0 | DN65: 0 | DO65: 0 | DP65: 1 | DQ65: 1 | DU65: 1010 | DV65: шт. | DW65: шт. | DX65: 1 | EE65: 58808284 | EF65: 130 | EG65: Сметная стоимость оборудования | EH65: 0 | EJ65: 3 | EK65: 746 | EL65: ТСН-2001.13. Сметная стоимость оборудования | EM65: ТСН-2001.13 | EQ65: 0 | ER65: 988.27 | ES65: 988.27 | ET65: 0 | EU65: 0 | EV65: 0 | EW65: 0 | EX65: 0 | EY65: 0 | EZ65: 5 | FC65: 1 | FD65: 18 | FF65: 8715 | FQ65: 0 | FR65: =P65 -> 15140.3 | FS65: 0 | FX65: 0 | FY65: 0 | GA65: [8 715 / 1,2 / 7,66] + 3% Трансп + 1,2% Заг.скл | GD65: 1 | GF65: 253381566 | GG65: 2 | GH65: 3 | GI65: 5 | GJ65: 0 | GK65: 0 | GL65: =ROUND(IF(AND(BH65=3,BI65=3,FS65<>0),P65,0),2) -> 0 | GM65: =ROUND(O65+X65+Y65,2)+GX65 -> 15140.3 | GN65: =IF(OR(BI65=0,BI65=1),GM65-GX65,0) -> 0 | GO65: =IF(BI65=2,GM65-GX65,0) -> 0 | GP65: =IF(BI65=4,GM65-GX65,0) -> 0 | GR65: 2 | GS65: 1 | GT65: 0 | GV65: =ROUND((GT65),6) -> 0 | GW65: 1 | GX65: =ROUND(HC65*I65,2) -> 0 | HA65: 0 | HB65: 0 | HC65: =GV65*GW65 -> 0 | HE65: 3 | HF65: 1,2 | HS65: 0 | IK65: 0
A66: 17 | B66: 1 | E66: 19 | F66: 13.1-1-20 | G66: Батарея аккумуляторная, емкость 7 А·ч, напряжение 12 В. | H66: шт. | I66: =ROUND(ROUND(4,4),9) -> 4 | J66: 0 | K66: =ROUND(ROUND(4,4),9) -> 4 | O66: =ROUND(CP66,2) -> 357.56 | P66: =ROUND((ROUND((AC66*I66),2)*BC66),2) -> 357.56 | Q66: =(ROUND((ROUND(((ET66)*AV66*I66),2)*BB66),2)+ROUND((ROUND(((AE66-(EU66))*AV66*I66),2)*BS66),2)) -> 0 | R66: =ROUND((ROUND((AE66*AV66*I66),2)*BS66),2) -> 0 | S66: =ROUND((ROUND((AF66*AV66*I66),2)*BA66),2) -> 0 | T66: =ROUND(CU66*I66,2) -> 0 | U66: =CV66*I66 -> 0 | V66: =CW66*I66 -> 0 | W66: =ROUND(CX66*I66,2) -> 0 | X66: =ROUND(CY66,2) -> 0 | Y66: =ROUND(CZ66,2) -> 0 | AA66: 59213216 | AB66: =ROUND((AC66+AD66+AF66),6) -> 89.39 | AC66: =ROUND((ES66),6) -> 89.39 | AD66: =ROUND((((ET66)-(EU66))+AE66),6) -> 0 | AE66: =ROUND((EU66),6) -> 0 | AF66: =ROUND((EV66),6) -> 0 | AG66: =ROUND((AP66),6) -> 0 | AH66: =(EW66) -> 0 | AI66: =(EX66) -> 0 | AJ66: =(AS66) -> 0 | AK66: 89.39 | AL66: 89.39 | AM66: 0 | AN66: 0 | AO66: 0 | AP66: 0 | AQ66: 0 | AR66: 0 | AS66: 0 | AT66: 0 | AU66: 0 | AV66: 1 | AW66: 1 | AZ66: 1 | BA66: 1 | BB66: 1 | BC66: 1 | BH66: 3 | BI66: 3 | BM66: 746 | BN66: 58808062 | BP66: 0 | BQ66: 130 | BR66: 0 | BS66: 1 | BT66: 1 | BU66: 1 | BV66: 1 | BW66: 1 | BX66: 1 | BZ66: 0 | CA66: 0 | CE66: 30 | CF66: 0 | CG66: 0 | CM66: 0 | CO66: 0 | CP66: =(P66+Q66+S66) -> 357.56 | CQ66: =ROUND((ROUND((AC66*1),2)*BC66),2) -> 89.39 | CR66: =(ROUND((ROUND(((ET66)*AV66*1),2)*BB66),2)+ROUND((ROUND(((AE66-(EU66))*AV66*1),2)*BS66),2)) -> 0 | CS66: =ROUND((ROUND((AE66*AV66*1),2)*BS66),2) -> 0 | CT66: =ROUND((ROUND((AF66*AV66*1),2)*BA66),2) -> 0 | CU66: =AG66 -> 0 | CV66: =(AH66*AV66) -> 0 | CW66: =AI66 -> 0 | CX66: =AJ66 -> 0 | CY66: =(((S66+R66)*AT66)/100) -> 0 | CZ66: =(((S66+R66)*AU66)/100) -> 0 | DN66: 0 | DO66: 0 | DP66: 1 | DQ66: 1 | DU66: 1010 | DV66: шт. | DW66: шт. | DX66: 1 | EE66: 58808284 | EF66: 130 | EG66: Сметная стоимость оборудования | EH66: 0 | EJ66: 3 | EK66: 746 | EL66: ТСН-2001.13. Сметная стоимость оборудования | EM66: ТСН-2001.13 | EQ66: 0 | ER66: 89.39 | ES66: 89.39 | ET66: 0 | EU66: 0 | EV66: 0 | EW66: 0 | EX66: 0 | EY66: 0 | FQ66: 0 | FR66: =P66 -> 357.56 | FS66: 0 | FX66: 0 | FY66: 0 | GD66: 1 | GF66: -1135192264 | GG66: 2 | GH66: 1 | GI66: -2 | GJ66: 0 | GK66: 0 | GL66: =ROUND(IF(AND(BH66=3,BI66=3,FS66<>0),P66,0),2) -> 0 | GM66: =ROUND(O66+X66+Y66,2)+GX66 -> 357.56 | GN66: =IF(OR(BI66=0,BI66=1),GM66-GX66,0) -> 0 | GO66: =IF(BI66=2,GM66-GX66,0) -> 0 | GP66: =IF(BI66=4,GM66-GX66,0) -> 0 | GR66: 0 | GS66: 3 | GT66: 0 | GV66: =ROUND((GT66),6) -> 0 | GW66: 1 | GX66: =ROUND(HC66*I66,2) -> 0 | HA66: 0 | HB66: 0 | HC66: =GV66*GW66 -> 0 | HS66: 0 | IK66: 0
A67: 17 | B67: 1 | E67: 19 | F67: 13.1-1-20 | G67: Батарея аккумуляторная, емкость 7 А·ч, напряжение 12 В. | H67: шт. | I67: =ROUND(ROUND(4,4),9) -> 4 | J67: 0 | K67: =ROUND(ROUND(4,4),9) -> 4 | O67: =ROUND(CP67,2) -> 3128.65 | P67: =ROUND((ROUND((AC67*I67),2)*BC67),2) -> 3128.65 | Q67: =(ROUND((ROUND(((ET67)*AV67*I67),2)*BB67),2)+ROUND((ROUND(((AE67-(EU67))*AV67*I67),2)*BS67),2)) -> 0 | R67: =ROUND((ROUND((AE67*AV67*I67),2)*BS67),2) -> 0 | S67: =ROUND((ROUND((AF67*AV67*I67),2)*BA67),2) -> 0 | T67: =ROUND(CU67*I67,2) -> 0 | U67: =CV67*I67 -> 0 | V67: =CW67*I67 -> 0 | W67: =ROUND(CX67*I67,2) -> 0 | X67: =ROUND(CY67,2) -> 0 | Y67: =ROUND(CZ67,2) -> 0 | AA67: 59213213 | AB67: =ROUND((AC67+AD67+AF67),6) -> 89.39 | AC67: =ROUND((ES67),6) -> 89.39 | AD67: =ROUND((((ET67)-(EU67))+AE67),6) -> 0 | AE67: =ROUND((EU67),6) -> 0 | AF67: =ROUND((EV67),6) -> 0 | AG67: =ROUND((AP67),6) -> 0 | AH67: =(EW67) -> 0 | AI67: =(EX67) -> 0 | AJ67: =(AS67) -> 0 | AK67: 89.39 | AL67: 89.39 | AM67: 0 | AN67: 0 | AO67: 0 | AP67: 0 | AQ67: 0 | AR67: 0 | AS67: 0 | AT67: 0 | AU67: 0 | AV67: 1 | AW67: 1 | AZ67: 1 | BA67: 1 | BB67: 1 | BC67: 8.75 | BH67: 3 | BI67: 3 | BM67: 746 | BN67: 58808062 | BP67: 0 | BQ67: 130 | BR67: 0 | BS67: 1 | BT67: 1 | BU67: 1 | BV67: 1 | BW67: 1 | BX67: 1 | BZ67: 0 | CA67: 0 | CE67: 30 | CF67: 0 | CG67: 0 | CM67: 0 | CO67: 0 | CP67: =(P67+Q67+S67) -> 3128.65 | CQ67: =ROUND((ROUND((AC67*1),2)*BC67),2) -> 782.16 | CR67: =(ROUND((ROUND(((ET67)*AV67*1),2)*BB67),2)+ROUND((ROUND(((AE67-(EU67))*AV67*1),2)*BS67),2)) -> 0 | CS67: =ROUND((ROUND((AE67*AV67*1),2)*BS67),2) -> 0 | CT67: =ROUND((ROUND((AF67*AV67*1),2)*BA67),2) -> 0 | CU67: =AG67 -> 0 | CV67: =(AH67*AV67) -> 0 | CW67: =AI67 -> 0 | CX67: =AJ67 -> 0 | CY67: =(((S67+R67)*AT67)/100) -> 0 | CZ67: =(((S67+R67)*AU67)/100) -> 0 | DN67: 0 | DO67: 0 | DP67: 1 | DQ67: 1 | DU67: 1010 | DV67: шт. | DW67: шт. | DX67: 1 | EE67: 58808284 | EF67: 130 | EG67: Сметная стоимость оборудования | EH67: 0 | EJ67: 3 | EK67: 746 | EL67: ТСН-2001.13. Сметная стоимость оборудования | EM67: ТСН-2001.13 | EQ67: 0 | ER67: 89.39 | ES67: 89.39 | ET67: 0 | EU67: 0 | EV67: 0 | EW67: 0 | EX67: 0 | EY67: 0 | FQ67: 0 | FR67: =P67 -> 3128.65 | FS67: 0 | FX67: 0 | FY67: 0 | GD67: 1 | GF67: -1135192264 | GG67: 2 | GH67: 1 | GI67: 2 | GJ67: 0 | GK67: 0 | GL67: =ROUND(IF(AND(BH67=3,BI67=3,FS67<>0),P67,0),2) -> 0 | GM67: =ROUND(O67+X67+Y67,2)+GX67 -> 3128.65 | GN67: =IF(OR(BI67=0,BI67=1),GM67-GX67,0) -> 0 | GO67: =IF(BI67=2,GM67-GX67,0) -> 0 | GP67: =IF(BI67=4,GM67-GX67,0) -> 0 | GR67: 0 | GS67: 3 | GT67: 0 | GV67: =ROUND((GT67),6) -> 0 | GW67: 1 | GX67: =ROUND(HC67*I67,2) -> 0 | HA67: 0 | HB67: 0 | HC67: =GV67*GW67 -> 0 | HS67: 0 | IK67: 0
A68: 17 | B68: 1 | C68: =ROW(SmtRes!A79) -> 79 | D68: =ROW(EtalonRes!A89) -> 89 | E68: 20 | F68: 4.11-12-1 | G68: Установка съемных и выдвижных блоков (модулей, ячеек, ТЭЗ) массой до 5 кг | H68: 1 ШТ. | I68: =ROUND(ROUND(7,4),9) -> 7 | J68: 0 | K68: =ROUND(ROUND(7,4),9) -> 7 | O68: =ROUND(CP68,2) -> 97.95 | P68: =ROUND((ROUND((AC68*AW68*I68),2)*BC68),2) -> 0 | Q68: =(ROUND((ROUND((((ET68*1.1))*AV68*I68),2)*BB68),2)+ROUND((ROUND(((AE68-((EU68*1.1)))*AV68*I68),2)*BS68),2)) -> 4.03 | R68: =ROUND((ROUND((AE68*AV68*I68),2)*BS68),2) -> 0.64 | S68: =ROUND((ROUND((AF68*AV68*I68),2)*BA68),2) -> 93.92 | T68: =ROUND(CU68*I68,2) -> 0 | U68: =CV68*I68 -> 8.303757 | V68: =CW68*I68 -> 0 | W68: =ROUND(CX68*I68,2) -> 0 | X68: =ROUND(CY68,2) -> 85.1 | Y68: =ROUND(CZ68,2) -> 43.5 | AA68: 59213216 | AB68: =ROUND((AC68+AD68+AF68),6) -> 13.365 | AC68: =ROUND(((ES68*1)),6) -> 0 | AD68: =ROUND(((((ET68*1.1))-((EU68*1.1)))+AE68),6) -> 0.55 | AE68: =ROUND(((EU68*1.1)),6) -> 0.088 | AF68: =ROUND(((EV68*1.1)),6) -> 12.815 | AG68: =ROUND((AP68),6) -> 0 | AH68: =((EW68*1.1)) -> 1.133 | AI68: =((EX68*1.1)) -> 0 | AJ68: =(AS68) -> 0 | AK68: 12.15 | AL68: 0 | AM68: 0.5 | AN68: 0.08 | AO68: 11.65 | AP68: 0 | AQ68: 1.03 | AR68: 0 | AS68: 0 | AT68: 90 | AU68: 46 | AV68: 1.047 | AW68: 1 | AZ68: 1 | BA68: 1 | BB68: 1 | BC68: 1 | BH68: 0 | BI68: 2 | BJ68: ТСН-2001.4 Доп. 68, Сб. 11, т. 12, поз. 1 | BM68: 72 | BN68: 58808062 | BO68: 4.11-12-1 | BP68: 1 | BQ68: 40 | BR68: 0 | BS68: 1 | BT68: 1 | BU68: 1 | BV68: 1 | BW68: 1 | BX68: 1 | BZ68: 90 | CA68: 46 | CE68: 30 | CF68: 0 | CG68: 0 | CM68: 0 | CN68: Поправка: Гл.12.Прил.8.п.8. 5_12.00.01.11.003 Наименование: При наличии усложненных условий производства работ (стесненность, сложность складирования и транспортной логистики, наличие в зоне производства работ действующего технологического оборудования или движения технологического транспорта и т.п.) для объектов, расположенных за пределами территории круговой магистральной системы улиц "Садовое кольцо" и за пределами Третьего транспортного кольца города Москвы пунктов "а" и "б", но в пределах Московской кольцевой автомобильной дороги | CO68: 0 | CP68: =(P68+Q68+S68) -> 97.95 | CQ68: =ROUND((ROUND((AC68*AW68*1),2)*BC68),2) -> 0 | CR68: =(ROUND((ROUND((((ET68*1.1))*AV68*1),2)*BB68),2)+ROUND((ROUND(((AE68-((EU68*1.1)))*AV68*1),2)*BS68),2)) -> 0.58 | CS68: =ROUND((ROUND((AE68*AV68*1),2)*BS68),2) -> 0.09 | CT68: =ROUND((ROUND((AF68*AV68*1),2)*BA68),2) -> 13.42 | CU68: =AG68 -> 0 | CV68: =(AH68*AV68) -> 1.186251 | CW68: =AI68 -> 0 | CX68: =AJ68 -> 0 | CY68: =(((S68+R68)*AT68)/100) -> 85.104 | CZ68: =(((S68+R68)*AU68)/100) -> 43.4976 | DB68: 19 | DD68: *1 | DE68: *1,1 | DF68: *1,1 | DG68: *1,1 | DI68: *1,1 | DJ68: *1,1 | DN68: 0 | DO68: 0 | DP68: 1 | DQ68: 1 | DU68: 1013 | DV68: 1 ШТ. | DW68: 1 ШТ. | DX68: 1 | EE68: 58808182 | EF68: 40 | EG68: Монтаж оборудования | EH68: 0 | EJ68: 2 | EK68: 72 | EL68: ТСН-2001.4-11. Приборы и средства автоматизации и вычислительной техники | EM68: ТСН-2001.4-11-1 | EO68: Поправка: Гл.12.Прил.8.п.8. 5_12.00.01.11.003 | EQ68: 0 | ER68: 12.15 | ES68: 0 | ET68: 0.5 | EU68: 0.08 | EV68: 11.65 | EW68: 1.03 | EX68: 0 | EY68: 0 | FQ68: 0 | FR68: 0 | FS68: 0 | FX68: 90 | FY68: 46 | GD68: 1 | GF68: 1708693888 | GG68: 2 | GH68: 1 | GI68: 2 | GJ68: 0 | GK68: 0 | GL68: =ROUND(IF(AND(BH68=3,BI68=3,FS68<>0),P68,0),2) -> 0 | GM68: =ROUND(O68+X68+Y68,2)+GX68 -> 226.55 | GN68: =IF(OR(BI68=0,BI68=1),GM68-GX68,0) -> 0 | GO68: =IF(BI68=2,GM68-GX68,0) -> 226.55 | GP68: =IF(BI68=4,GM68-GX68,0) -> 0 | GR68: 0 | GS68: 3 | GT68: 0 | GV68: =ROUND((GT68),6) -> 0 | GW68: 1 | GX68: =ROUND(HC68*I68,2) -> 0 | HA68: 0 | HB68: 0 | HC68: =GV68*GW68 -> 0 | HS68: 0 | IK68: 0
A69: 17 | B69: 1 | C69: =ROW(SmtRes!A82) -> 82 | D69: =ROW(EtalonRes!A92) -> 92 | E69: 20 | F69: 4.11-12-1 | G69: Установка съемных и выдвижных блоков (модулей, ячеек, ТЭЗ) массой до 5 кг | H69: 1 ШТ. | I69: =ROUND(ROUND(7,4),9) -> 7 | J69: 0 | K69: =ROUND(ROUND(7,4),9) -> 7 | O69: =ROUND(CP69,2) -> 5230.19 | P69: =ROUND((ROUND((AC69*AW69*I69),2)*BC69),2) -> 0 | Q69: =(ROUND((ROUND((((ET69*1.1))*AV69*I69),2)*BB69),2)+ROUND((ROUND(((AE69-((EU69*1.1)))*AV69*I69),2)*BS69),2)) -> 65.53 | R69: =ROUND((ROUND((AE69*AV69*I69),2)*BS69),2) -> 35.19 | S69: =ROUND((ROUND((AF69*AV69*I69),2)*BA69),2) -> 5164.66 | T69: =ROUND(CU69*I69,2) -> 0 | U69: =CV69*I69 -> 8.303757 | V69: =CW69*I69 -> 0 | W69: =ROUND(CX69*I69,2) -> 0 | X69: =ROUND(CY69,2) -> 4679.87 | Y69: =ROUND(CZ69,2) -> 2391.93 | AA69: 59213213 | AB69: =ROUND((AC69+AD69+AF69),6) -> 13.365 | AC69: =ROUND(((ES69*1)),6) -> 0 | AD69: =ROUND(((((ET69*1.1))-((EU69*1.1)))+AE69),6) -> 0.55 | AE69: =ROUND(((EU69*1.1)),6) -> 0.088 | AF69: =ROUND(((EV69*1.1)),6) -> 12.815 | AG69: =ROUND((AP69),6) -> 0 | AH69: =((EW69*1.1)) -> 1.133 | AI69: =((EX69*1.1)) -> 0 | AJ69: =(AS69) -> 0 | AK69: 12.15 | AL69: 0 | AM69: 0.5 | AN69: 0.08 | AO69: 11.65 | AP69: 0 | AQ69: 1.03 | AR69: 0 | AS69: 0 | AT69: 90 | AU69: 46 | AV69: 1.047 | AW69: 1 | AZ69: 1 | BA69: 54.99 | BB69: 16.26 | BC69: 1 | BH69: 0 | BI69: 2 | BJ69: ТСН-2001.4 Доп. 68, Сб. 11, т. 12, поз. 1 | BM69: 72 | BN69: 58808062 | BO69: 4.11-12-1 | BP69: 1 | BQ69: 40 | BR69: 0 | BS69: 54.99 | BT69: 1 | BU69: 1 | BV69: 1 | BW69: 1 | BX69: 1 | BZ69: 90 | CA69: 46 | CE69: 30 | CF69: 0 | CG69: 0 | CM69: 0 | CN69: Поправка: Гл.12.Прил.8.п.8. 5_12.00.01.11.003 Наименование: При наличии усложненных условий производства работ (стесненность, сложность складирования и транспортной логистики, наличие в зоне производства работ действующего технологического оборудования или движения технологического транспорта и т.п.) для объектов, расположенных за пределами территории круговой магистральной системы улиц "Садовое кольцо" и за пределами Третьего транспортного кольца города Москвы пунктов "а" и "б", но в пределах Московской кольцевой автомобильной дороги | CO69: 0 | CP69: =(P69+Q69+S69) -> 5230.19 | CQ69: =ROUND((ROUND((AC69*AW69*1),2)*BC69),2) -> 0 | CR69: =(ROUND((ROUND((((ET69*1.1))*AV69*1),2)*BB69),2)+ROUND((ROUND(((AE69-((EU69*1.1)))*AV69*1),2)*BS69),2)) -> 9.43 | CS69: =ROUND((ROUND((AE69*AV69*1),2)*BS69),2) -> 4.95 | CT69: =ROUND((ROUND((AF69*AV69*1),2)*BA69),2) -> 737.97 | CU69: =AG69 -> 0 | CV69: =(AH69*AV69) -> 1.186251 | CW69: =AI69 -> 0 | CX69: =AJ69 -> 0 | CY69: =(((S69+R69)*AT69)/100) -> 4679.865 | CZ69: =(((S69+R69)*AU69)/100) -> 2391.931 | DB69: 20 | DD69: *1 | DE69: *1,1 | DF69: *1,1 | DG69: *1,1 | DI69: *1,1 | DJ69: *1,1 | DN69: 0 | DO69: 0 | DP69: 1 | DQ69: 1 | DU69: 1013 | DV69: 1 ШТ. | DW69: 1 ШТ. | DX69: 1 | EE69: 58808182 | EF69: 40 | EG69: Монтаж оборудования | EH69: 0 | EJ69: 2 | EK69: 72 | EL69: ТСН-2001.4-11. Приборы и средства автоматизации и вычислительной техники | EM69: ТСН-2001.4-11-1 | EO69: Поправка: Гл.12.Прил.8.п.8. 5_12.00.01.11.003 | EQ69: 0 | ER69: 12.15 | ES69: 0 | ET69: 0.5 | EU69: 0.08 | EV69: 11.65 | EW69: 1.03 | EX69: 0 | EY69: 0 | FQ69: 0 | FR69: 0 | FS69: 0 | FX69: 90 | FY69: 46 | GD69: 1 | GF69: 1708693888 | GG69: 2 | GH69: 1 | GI69: 2 | GJ69: 0 | GK69: 0 | GL69: =ROUND(IF(AND(BH69=3,BI69=3,FS69<>0),P69,0),2) -> 0 | GM69: =ROUND(O69+X69+Y69,2)+GX69 -> 12301.99 | GN69: =IF(OR(BI69=0,BI69=1),GM69-GX69,0) -> 0 | GO69: =IF(BI69=2,GM69-GX69,0) -> 12301.99 | GP69: =IF(BI69=4,GM69-GX69,0) -> 0 | GR69: 0 | GS69: 3 | GT69: 0 | GV69: =ROUND((GT69),6) -> 0 | GW69: 1 | GX69: =ROUND(HC69*I69,2) -> 0 | HA69: 0 | HB69: 0 | HC69: =GV69*GW69 -> 0 | HS69: 0 | IK69: 0
A70: 18 | B70: 1 | C70: 79 | E70: 20,1 | F70: КА 11 | G70: Коммутационная панель категории 5е UTP19",1U,24xRj45,п-корды PLHD-24 Dual IDC-1U | H70: шт. | I70: =I68*J70 -> 49 | J70: 7 | K70: 7 | O70: =ROUND(CP70,2) -> 11403.77 | P70: =ROUND((ROUND((AC70*AW70*I70),2)*BC70),2) -> 11403.77 | Q70: =(ROUND((ROUND(((ET70)*AV70*I70),2)*BB70),2)+ROUND((ROUND(((AE70-(EU70))*AV70*I70),2)*BS70),2)) -> 0 | R70: =ROUND((ROUND((AE70*AV70*I70),2)*BS70),2) -> 0 | S70: =ROUND((ROUND((AF70*AV70*I70),2)*BA70),2) -> 0 | T70: =ROUND(CU70*I70,2) -> 0 | U70: =CV70*I70 -> 0 | V70: =CW70*I70 -> 0 | W70: =ROUND(CX70*I70,2) -> 0 | X70: =ROUND(CY70,2) -> 0 | Y70: =ROUND(CZ70,2) -> 0 | AA70: 59213216 | AB70: =ROUND((AC70+AD70+AF70),6) -> 232.73 | AC70: =ROUND((ES70),6) -> 232.73 | AD70: =ROUND((((ET70)-(EU70))+AE70),6) -> 0 | AE70: =ROUND((EU70),6) -> 0 | AF70: =ROUND((EV70),6) -> 0 | AG70: =ROUND((AP70),6) -> 0 | AH70: =(EW70) -> 0 | AI70: =(EX70) -> 0 | AJ70: =(AS70) -> 0 | AK70: 232.73 | AL70: 232.73 | AM70: 0 | AN70: 0 | AO70: 0 | AP70: 0 | AQ70: 0 | AR70: 0 | AS70: 0 | AT70: 90 | AU70: 46 | AV70: 1 | AW70: 1 | AZ70: 1 | BA70: 1 | BB70: 1 | BC70: 1 | BH70: 3 | BI70: 2 | BM70: 72 | BN70: 0 | BP70: 0 | BQ70: 40 | BR70: 0 | BS70: 1 | BT70: 1 | BU70: 1 | BV70: 1 | BW70: 1 | BX70: 1 | BZ70: 90 | CA70: 46 | CE70: 30 | CF70: 0 | CG70: 0 | CM70: 0 | CO70: 0 | CP70: =(P70+Q70+S70) -> 11403.77 | CQ70: =ROUND((ROUND((AC70*AW70*1),2)*BC70),2) -> 232.73 | CR70: =(ROUND((ROUND(((ET70)*AV70*1),2)*BB70),2)+ROUND((ROUND(((AE70-(EU70))*AV70*1),2)*BS70),2)) -> 0 | CS70: =ROUND((ROUND((AE70*AV70*1),2)*BS70),2) -> 0 | CT70: =ROUND((ROUND((AF70*AV70*1),2)*BA70),2) -> 0 | CU70: =AG70 -> 0 | CV70: =(AH70*AV70) -> 0 | CW70: =AI70 -> 0 | CX70: =AJ70 -> 0 | CY70: =(((S70+R70)*AT70)/100) -> 0 | CZ70: =(((S70+R70)*AU70)/100) -> 0 | DN70: 0 | DO70: 0 | DP70: 1 | DQ70: 1 | DU70: 1010 | DV70: шт. | DW70: шт. | DX70: 1 | EE70: 58808182 | EF70: 40 | EG70: Монтаж оборудования | EH70: 0 | EJ70: 2 | EK70: 72 | EL70: ТСН-2001.4-11. Приборы и средства автоматизации и вычислительной техники | EM70: ТСН-2001.4-11-1 | EQ70: 0 | ER70: 0 | ES70: 232.73 | ET70: 0 | EU70: 0 | EV70: 0 | EW70: 0 | EX70: 0 | FQ70: 0 | FR70: 0 | FS70: 0 | FX70: 90 | FY70: 46 | GA70: [2 705,14 / 1,2 / 9,88] + 2% Заг.скл | GD70: 1 | GF70: -1498373408 | GG70: 2 | GH70: 4 | GI70: -2 | GJ70: 0 | GK70: 0 | GL70: =ROUND(IF(AND(BH70=3,BI70=3,FS70<>0),P70,0),2) -> 0 | GM70: =ROUND(O70+X70+Y70,2)+GX70 -> 11403.77 | GN70: =IF(OR(BI70=0,BI70=1),GM70-GX70,0) -> 0 | GO70: =IF(BI70=2,GM70-GX70,0) -> 11403.77 | GP70: =IF(BI70=4,GM70-GX70,0) -> 0 | GR70: 0 | GS70: 2 | GT70: 0 | GV70: =ROUND((GT70),6) -> 0 | GW70: 1 | GX70: =ROUND(HC70*I70,2) -> 0 | HA70: 0 | HB70: 0 | HC70: =GV70*GW70 -> 0 | HE70: 0 | HF70: 2 | HS70: 0 | IK70: 0
A71: 18 | B71: 1 | C71: 82 | E71: 20,1 | F71: КА 11 | G71: Коммутационная панель категории 5е UTP19",1U,24xRj45,п-корды PLHD-24 Dual IDC-1U | H71: шт. | I71: =I69*J71 -> 49 | J71: 7 | K71: 7 | O71: =ROUND(CP71,2) -> 112669.25 | P71: =ROUND((ROUND((AC71*AW71*I71),2)*BC71),2) -> 112669.25 | Q71: =(ROUND((ROUND(((ET71)*AV71*I71),2)*BB71),2)+ROUND((ROUND(((AE71-(EU71))*AV71*I71),2)*BS71),2)) -> 0 | R71: =ROUND((ROUND((AE71*AV71*I71),2)*BS71),2) -> 0 | S71: =ROUND((ROUND((AF71*AV71*I71),2)*BA71),2) -> 0 | T71: =ROUND(CU71*I71,2) -> 0 | U71: =CV71*I71 -> 0 | V71: =CW71*I71 -> 0 | W71: =ROUND(CX71*I71,2) -> 0 | X71: =ROUND(CY71,2) -> 0 | Y71: =ROUND(CZ71,2) -> 0 | AA71: 59213213 | AB71: =ROUND((AC71+AD71+AF71),6) -> 232.73 | AC71: =ROUND((ES71),6) -> 232.73 | AD71: =ROUND((((ET71)-(EU71))+AE71),6) -> 0 | AE71: =ROUND((EU71),6) -> 0 | AF71: =ROUND((EV71),6) -> 0 | AG71: =ROUND((AP71),6) -> 0 | AH71: =(EW71) -> 0 | AI71: =(EX71) -> 0 | AJ71: =(AS71) -> 0 | AK71: 232.73 | AL71: 232.73 | AM71: 0 | AN71: 0 | AO71: 0 | AP71: 0 | AQ71: 0 | AR71: 0 | AS71: 0 | AT71: 90 | AU71: 46 | AV71: 1 | AW71: 1 | AZ71: 1 | BA71: 1 | BB71: 1 | BC71: 9.88 | BH71: 3 | BI71: 2 | BM71: 72 | BN71: 0 | BP71: 0 | BQ71: 40 | BR71: 0 | BS71: 1 | BT71: 1 | BU71: 1 | BV71: 1 | BW71: 1 | BX71: 1 | BZ71: 90 | CA71: 46 | CE71: 30 | CF71: 0 | CG71: 0 | CM71: 0 | CO71: 0 | CP71: =(P71+Q71+S71) -> 112669.25 | CQ71: =ROUND((ROUND((AC71*AW71*1),2)*BC71),2) -> 2299.37 | CR71: =(ROUND((ROUND(((ET71)*AV71*1),2)*BB71),2)+ROUND((ROUND(((AE71-(EU71))*AV71*1),2)*BS71),2)) -> 0 | CS71: =ROUND((ROUND((AE71*AV71*1),2)*BS71),2) -> 0 | CT71: =ROUND((ROUND((AF71*AV71*1),2)*BA71),2) -> 0 | CU71: =AG71 -> 0 | CV71: =(AH71*AV71) -> 0 | CW71: =AI71 -> 0 | CX71: =AJ71 -> 0 | CY71: =(((S71+R71)*AT71)/100) -> 0 | CZ71: =(((S71+R71)*AU71)/100) -> 0 | DN71: 0 | DO71: 0 | DP71: 1 | DQ71: 1 | DU71: 1010 | DV71: шт. | DW71: шт. | DX71: 1 | EE71: 58808182 | EF71: 40 | EG71: Монтаж оборудования | EH71: 0 | EJ71: 2 | EK71: 72 | EL71: ТСН-2001.4-11. Приборы и средства автоматизации и вычислительной техники | EM71: ТСН-2001.4-11-1 | EQ71: 0 | ER71: 306.76 | ES71: 232.73 | ET71: 0 | EU71: 0 | EV71: 0 | EW71: 0 | EX71: 0 | EZ71: 5 | FC71: 1 | FD71: 18 | FF71: 2705.14 | FQ71: 0 | FR71: 0 | FS71: 0 | FX71: 90 | FY71: 46 | GA71: [2 705,14 / 1,2 / 9,88] + 2% Заг.скл | GD71: 1 | GF71: -1498373408 | GG71: 2 | GH71: 3 | GI71: 5 | GJ71: 0 | GK71: 0 | GL71: =ROUND(IF(AND(BH71=3,BI71=3,FS71<>0),P71,0),2) -> 0 | GM71: =ROUND(O71+X71+Y71,2)+GX71 -> 112669.25 | GN71: =IF(OR(BI71=0,BI71=1),GM71-GX71,0) -> 0 | GO71: =IF(BI71=2,GM71-GX71,0) -> 112669.25 | GP71: =IF(BI71=4,GM71-GX71,0) -> 0 | GR71: 1 | GS71: 1 | GT71: 0 | GV71: =ROUND((GT71),6) -> 0 | GW71: 1 | GX71: =ROUND(HC71*I71,2) -> 0 | HA71: 0 | HB71: 0 | HC71: =GV71*GW71 -> 0 | HE71: 0 | HF71: 2 | HS71: 0 | IK71: 0
A72: 17 | B72: 1 | C72: =ROW(SmtRes!A84) -> 84 | D72: =ROW(EtalonRes!A94) -> 94 | E72: 21 | F72: 4.10-1-12 | G72: Установка рамки со штифтами на винтах в нарезных отверстиях | H72: 1 рамка | I72: =ROUND(ROUND(7,4),9) -> 7 | J72: 0 | K72: =ROUND(ROUND(7,4),9) -> 7 | O72: =ROUND(CP72,2) -> 6.29 | P72: =ROUND((ROUND((AC72*AW72*I72),2)*BC72),2) -> 0 | Q72: =(ROUND((ROUND((((ET72*1.1))*AV72*I72),2)*BB72),2)+ROUND((ROUND(((AE72-((EU72*1.1)))*AV72*I72),2)*BS72),2)) -> 0 | R72: =ROUND((ROUND((AE72*AV72*I72),2)*BS72),2) -> 0 | S72: =ROUND((ROUND((AF72*AV72*I72),2)*BA72),2) -> 6.29 | T72: =ROUND(CU72*I72,2) -> 0 | U72: =CV72*I72 -> 0.564333 | V72: =CW72*I72 -> 0 | W72: =ROUND(CX72*I72,2) -> 0 | X72: =ROUND(CY72,2) -> 5.66 | Y72: =ROUND(CZ72,2) -> 2.89 | AA72: 59213216 | AB72: =ROUND((AC72+AD72+AF72),6) -> 0.858 | AC72: =ROUND(((ES72*1)),6) -> 0 | AD72: =ROUND(((((ET72*1.1))-((EU72*1.1)))+AE72),6) -> 0 | AE72: =ROUND(((EU72*1.1)),6) -> 0 | AF72: =ROUND(((EV72*1.1)),6) -> 0.858 | AG72: =ROUND((AP72),6) -> 0 | AH72: =((EW72*1.1)) -> 0.077 | AI72: =((EX72*1.1)) -> 0 | AJ72: =(AS72) -> 0 | AK72: 0.78 | AL72: 0 | AM72: 0 | AN72: 0 | AO72: 0.78 | AP72: 0 | AQ72: 0.07 | AR72: 0 | AS72: 0 | AT72: 90 | AU72: 46 | AV72: 1.047 | AW72: 1 | AZ72: 1 | BA72: 1 | BB72: 1 | BC72: 1 | BH72: 0 | BI72: 2 | BJ72: ТСН-2001.4 Доп. 67, Сб. 10, т. 1, поз. 12 | BM72: 68 | BN72: 58808062 | BO72: 4.10-1-12 | BP72: 1 | BQ72: 40 | BR72: 0 | BS72: 1 | BT72: 1 | BU72: 1 | BV72: 1 | BW72: 1 | BX72: 1 | BZ72: 90 | CA72: 46 | CE72: 30 | CF72: 0 | CG72: 0 | CM72: 0 | CN72: Поправка: Гл.12.Прил.8.п.8. 5_12.00.01.11.003 Наименование: При наличии усложненных условий производства работ (стесненность, сложность складирования и транспортной логистики, наличие в зоне производства работ действующего технологического оборудования или движения технологического транспорта и т.п.) для объектов, расположенных за пределами территории круговой магистральной системы улиц "Садовое кольцо" и за пределами Третьего транспортного кольца города Москвы пунктов "а" и "б", но в пределах Московской кольцевой автомобильной дороги | CO72: 0 | CP72: =(P72+Q72+S72) -> 6.29 | CQ72: =ROUND((ROUND((AC72*AW72*1),2)*BC72),2) -> 0 | CR72: =(ROUND((ROUND((((ET72*1.1))*AV72*1),2)*BB72),2)+ROUND((ROUND(((AE72-((EU72*1.1)))*AV72*1),2)*BS72),2)) -> 0 | CS72: =ROUND((ROUND((AE72*AV72*1),2)*BS72),2) -> 0 | CT72: =ROUND((ROUND((AF72*AV72*1),2)*BA72),2) -> 0.9 | CU72: =AG72 -> 0 | CV72: =(AH72*AV72) -> 0.080619 | CW72: =AI72 -> 0 | CX72: =AJ72 -> 0 | CY72: =(((S72+R72)*AT72)/100) -> 5.661 | CZ72: =(((S72+R72)*AU72)/100) -> 2.8934 | DB72: 21 | DD72: *1 | DE72: *1,1 | DF72: *1,1 | DG72: *1,1 | DI72: *1,1 | DJ72: *1,1 | DN72: 0 | DO72: 0 | DP72: 1 | DQ72: 1 | DU72: 1013 | DV72: 1 рамка | DW72: 1 рамка | DX72: 1 | EE72: 58808178 | EF72: 40 | EG72: Монтаж оборудования | EH72: 0 | EJ72: 2 | EK72: 68 | EL72: ТСН-2001.4-10. Прокладка и монтаж сетей связи | EM72: ТСН-2001.4-10-1 | EO72: Поправка: Гл.12.Прил.8.п.8. 5_12.00.01.11.003 | EQ72: 0 | ER72: 0.78 | ES72: 0 | ET72: 0 | EU72: 0 | EV72: 0.78 | EW72: 0.07 | EX72: 0 | EY72: 0 | FQ72: 0 | FR72: 0 | FS72: 0 | FX72: 90 | FY72: 46 | GD72: 1 | GF72: -1730397577 | GG72: 2 | GH72: 1 | GI72: 2 | GJ72: 0 | GK72: 0 | GL72: =ROUND(IF(AND(BH72=3,BI72=3,FS72<>0),P72,0),2) -> 0 | GM72: =ROUND(O72+X72+Y72,2)+GX72 -> 14.84 | GN72: =IF(OR(BI72=0,BI72=1),GM72-GX72,0) -> 0 | GO72: =IF(BI72=2,GM72-GX72,0) -> 14.84 | GP72: =IF(BI72=4,GM72-GX72,0) -> 0 | GR72: 0 | GS72: 3 | GT72: 0 | GV72: =ROUND((GT72),6) -> 0 | GW72: 1 | GX72: =ROUND(HC72*I72,2) -> 0 | HA72: 0 | HB72: 0 | HC72: =GV72*GW72 -> 0 | HS72: 0 | IK72: 0
A73: 17 | B73: 1 | C73: =ROW(SmtRes!A86) -> 86 | D73: =ROW(EtalonRes!A96) -> 96 | E73: 21 | F73: 4.10-1-12 | G73: Установка рамки со штифтами на винтах в нарезных отверстиях | H73: 1 рамка | I73: =ROUND(ROUND(7,4),9) -> 7 | J73: 0 | K73: =ROUND(ROUND(7,4),9) -> 7 | O73: =ROUND(CP73,2) -> 345.89 | P73: =ROUND((ROUND((AC73*AW73*I73),2)*BC73),2) -> 0 | Q73: =(ROUND((ROUND((((ET73*1.1))*AV73*I73),2)*BB73),2)+ROUND((ROUND(((AE73-((EU73*1.1)))*AV73*I73),2)*BS73),2)) -> 0 | R73: =ROUND((ROUND((AE73*AV73*I73),2)*BS73),2) -> 0 | S73: =ROUND((ROUND((AF73*AV73*I73),2)*BA73),2) -> 345.89 | T73: =ROUND(CU73*I73,2) -> 0 | U73: =CV73*I73 -> 0.564333 | V73: =CW73*I73 -> 0 | W73: =ROUND(CX73*I73,2) -> 0 | X73: =ROUND(CY73,2) -> 311.3 | Y73: =ROUND(CZ73,2) -> 159.11 | AA73: 59213213 | AB73: =ROUND((AC73+AD73+AF73),6) -> 0.858 | AC73: =ROUND(((ES73*1)),6) -> 0 | AD73: =ROUND(((((ET73*1.1))-((EU73*1.1)))+AE73),6) -> 0 | AE73: =ROUND(((EU73*1.1)),6) -> 0 | AF73: =ROUND(((EV73*1.1)),6) -> 0.858 | AG73: =ROUND((AP73),6) -> 0 | AH73: =((EW73*1.1)) -> 0.077 | AI73: =((EX73*1.1)) -> 0 | AJ73: =(AS73) -> 0 | AK73: 0.78 | AL73: 0 | AM73: 0 | AN73: 0 | AO73: 0.78 | AP73: 0 | AQ73: 0.07 | AR73: 0 | AS73: 0 | AT73: 90 | AU73: 46 | AV73: 1.047 | AW73: 1 | AZ73: 1 | BA73: 54.99 | BB73: 1 | BC73: 1 | BH73: 0 | BI73: 2 | BJ73: ТСН-2001.4 Доп. 67, Сб. 10, т. 1, поз. 12 | BM73: 68 | BN73: 58808062 | BO73: 4.10-1-12 | BP73: 1 | BQ73: 40 | BR73: 0 | BS73: 54.99 | BT73: 1 | BU73: 1 | BV73: 1 | BW73: 1 | BX73: 1 | BZ73: 90 | CA73: 46 | CE73: 30 | CF73: 0 | CG73: 0 | CM73: 0 | CN73: Поправка: Гл.12.Прил.8.п.8. 5_12.00.01.11.003 Наименование: При наличии усложненных условий производства работ (стесненность, сложность складирования и транспортной логистики, наличие в зоне производства работ действующего технологического оборудования или движения технологического транспорта и т.п.) для объектов, расположенных за пределами территории круговой магистральной системы улиц "Садовое кольцо" и за пределами Третьего транспортного кольца города Москвы пунктов "а" и "б", но в пределах Московской кольцевой автомобильной дороги | CO73: 0 | CP73: =(P73+Q73+S73) -> 345.89 | CQ73: =ROUND((ROUND((AC73*AW73*1),2)*BC73),2) -> 0 | CR73: =(ROUND((ROUND((((ET73*1.1))*AV73*1),2)*BB73),2)+ROUND((ROUND(((AE73-((EU73*1.1)))*AV73*1),2)*BS73),2)) -> 0 | CS73: =ROUND((ROUND((AE73*AV73*1),2)*BS73),2) -> 0 | CT73: =ROUND((ROUND((AF73*AV73*1),2)*BA73),2) -> 49.49 | CU73: =AG73 -> 0 | CV73: =(AH73*AV73) -> 0.080619 | CW73: =AI73 -> 0 | CX73: =AJ73 -> 0 | CY73: =(((S73+R73)*AT73)/100) -> 311.301 | CZ73: =(((S73+R73)*AU73)/100) -> 159.1094 | DB73: 22 | DD73: *1 | DE73: *1,1 | DF73: *1,1 | DG73: *1,1 | DI73: *1,1 | DJ73: *1,1 | DN73: 0 | DO73: 0 | DP73: 1 | DQ73: 1 | DU73: 1013 | DV73: 1 рамка | DW73: 1 рамка | DX73: 1 | EE73: 58808178 | EF73: 40 | EG73: Монтаж оборудования | EH73: 0 | EJ73: 2 | EK73: 68 | EL73: ТСН-2001.4-10. Прокладка и монтаж сетей связи | EM73: ТСН-2001.4-10-1 | EO73: Поправка: Гл.12.Прил.8.п.8. 5_12.00.01.11.003 | EQ73: 0 | ER73: 0.78 | ES73: 0 | ET73: 0 | EU73: 0 | EV73: 0.78 | EW73: 0.07 | EX73: 0 | EY73: 0 | FQ73: 0 | FR73: 0 | FS73: 0 | FX73: 90 | FY73: 46 | GD73: 1 | GF73: -1730397577 | GG73: 2 | GH73: 1 | GI73: 2 | GJ73: 0 | GK73: 0 | GL73: =ROUND(IF(AND(BH73=3,BI73=3,FS73<>0),P73,0),2) -> 0 | GM73: =ROUND(O73+X73+Y73,2)+GX73 -> 816.3 | GN73: =IF(OR(BI73=0,BI73=1),GM73-GX73,0) -> 0 | GO73: =IF(BI73=2,GM73-GX73,0) -> 816.3 | GP73: =IF(BI73=4,GM73-GX73,0) -> 0 | GR73: 0 | GS73: 3 | GT73: 0 | GV73: =ROUND((GT73),6) -> 0 | GW73: 1 | GX73: =ROUND(HC73*I73,2) -> 0 | HA73: 0 | HB73: 0 | HC73: =GV73*GW73 -> 0 | HS73: 0 | IK73: 0
A74: 18 | B74: 1 | C74: 84 | E74: 21,1 | F74: КА 12 | G74: Горизонтальный органайзер, слотовый с крышкой, MX-CMC-1U-45-B | H74: шт. | I74: =I72*J74 -> 7 | J74: 1 | K74: 1 | O74: =ROUND(CP74,2) -> 259 | P74: =ROUND((ROUND((AC74*AW74*I74),2)*BC74),2) -> 259 | Q74: =(ROUND((ROUND(((ET74)*AV74*I74),2)*BB74),2)+ROUND((ROUND(((AE74-(EU74))*AV74*I74),2)*BS74),2)) -> 0 | R74: =ROUND((ROUND((AE74*AV74*I74),2)*BS74),2) -> 0 | S74: =ROUND((ROUND((AF74*AV74*I74),2)*BA74),2) -> 0 | T74: =ROUND(CU74*I74,2) -> 0 | U74: =CV74*I74 -> 0 | V74: =CW74*I74 -> 0 | W74: =ROUND(CX74*I74,2) -> 0 | X74: =ROUND(CY74,2) -> 0 | Y74: =ROUND(CZ74,2) -> 0 | AA74: 59213216 | AB74: =ROUND((AC74+AD74+AF74),6) -> 37 | AC74: =ROUND((ES74),6) -> 37 | AD74: =ROUND((((ET74)-(EU74))+AE74),6) -> 0 | AE74: =ROUND((EU74),6) -> 0 | AF74: =ROUND((EV74),6) -> 0 | AG74: =ROUND((AP74),6) -> 0 | AH74: =(EW74) -> 0 | AI74: =(EX74) -> 0 | AJ74: =(AS74) -> 0 | AK74: 37 | AL74: 37 | AM74: 0 | AN74: 0 | AO74: 0 | AP74: 0 | AQ74: 0 | AR74: 0 | AS74: 0 | AT74: 90 | AU74: 46 | AV74: 1 | AW74: 1 | AZ74: 1 | BA74: 1 | BB74: 1 | BC74: 1 | BH74: 3 | BI74: 2 | BM74: 68 | BN74: 0 | BP74: 0 | BQ74: 40 | BR74: 0 | BS74: 1 | BT74: 1 | BU74: 1 | BV74: 1 | BW74: 1 | BX74: 1 | BZ74: 90 | CA74: 46 | CE74: 30 | CF74: 0 | CG74: 0 | CM74: 0 | CO74: 0 | CP74: =(P74+Q74+S74) -> 259 | CQ74: =ROUND((ROUND((AC74*AW74*1),2)*BC74),2) -> 37 | CR74: =(ROUND((ROUND(((ET74)*AV74*1),2)*BB74),2)+ROUND((ROUND(((AE74-(EU74))*AV74*1),2)*BS74),2)) -> 0 | CS74: =ROUND((ROUND((AE74*AV74*1),2)*BS74),2) -> 0 | CT74: =ROUND((ROUND((AF74*AV74*1),2)*BA74),2) -> 0 | CU74: =AG74 -> 0 | CV74: =(AH74*AV74) -> 0 | CW74: =AI74 -> 0 | CX74: =AJ74 -> 0 | CY74: =(((S74+R74)*AT74)/100) -> 0 | CZ74: =(((S74+R74)*AU74)/100) -> 0 | DN74: 0 | DO74: 0 | DP74: 1 | DQ74: 1 | DU74: 1010 | DV74: шт. | DW74: шт. | DX74: 1 | EE74: 58808178 | EF74: 40 | EG74: Монтаж оборудования | EH74: 0 | EJ74: 2 | EK74: 68 | EL74: ТСН-2001.4-10. Прокладка и монтаж сетей связи | EM74: ТСН-2001.4-10-1 | EQ74: 0 | ER74: 0 | ES74: 37 | ET74: 0 | EU74: 0 | EV74: 0 | EW74: 0 | EX74: 0 | FQ74: 0 | FR74: 0 | FS74: 0 | FX74: 90 | FY74: 46 | GA74: [430 / 1,2 / 9,88] + 2% Заг.скл | GD74: 1 | GF74: -1209925472 | GG74: 2 | GH74: 4 | GI74: -2 | GJ74: 0 | GK74: 0 | GL74: =ROUND(IF(AND(BH74=3,BI74=3,FS74<>0),P74,0),2) -> 0 | GM74: =ROUND(O74+X74+Y74,2)+GX74 -> 259 | GN74: =IF(OR(BI74=0,BI74=1),GM74-GX74,0) -> 0 | GO74: =IF(BI74=2,GM74-GX74,0) -> 259 | GP74: =IF(BI74=4,GM74-GX74,0) -> 0 | GR74: 2 | GS74: 2 | GT74: 0 | GV74: =ROUND((GT74),6) -> 0 | GW74: 1 | GX74: =ROUND(HC74*I74,2) -> 0 | HA74: 0 | HB74: 0 | HC74: =GV74*GW74 -> 0 | HE74: 0 | HF74: 2 | HS74: 0 | IK74: 0
A75: 18 | B75: 1 | C75: 86 | E75: 21,1 | F75: КА 12 | G75: Горизонтальный органайзер, слотовый с крышкой, MX-CMC-1U-45-B | H75: шт. | I75: =I73*J75 -> 7 | J75: 1 | K75: 1 | O75: =ROUND(CP75,2) -> 2558.92 | P75: =ROUND((ROUND((AC75*AW75*I75),2)*BC75),2) -> 2558.92 | Q75: =(ROUND((ROUND(((ET75)*AV75*I75),2)*BB75),2)+ROUND((ROUND(((AE75-(EU75))*AV75*I75),2)*BS75),2)) -> 0 | R75: =ROUND((ROUND((AE75*AV75*I75),2)*BS75),2) -> 0 | S75: =ROUND((ROUND((AF75*AV75*I75),2)*BA75),2) -> 0 | T75: =ROUND(CU75*I75,2) -> 0 | U75: =CV75*I75 -> 0 | V75: =CW75*I75 -> 0 | W75: =ROUND(CX75*I75,2) -> 0 | X75: =ROUND(CY75,2) -> 0 | Y75: =ROUND(CZ75,2) -> 0 | AA75: 59213213 | AB75: =ROUND((AC75+AD75+AF75),6) -> 37 | AC75: =ROUND((ES75),6) -> 37 | AD75: =ROUND((((ET75)-(EU75))+AE75),6) -> 0 | AE75: =ROUND((EU75),6) -> 0 | AF75: =ROUND((EV75),6) -> 0 | AG75: =ROUND((AP75),6) -> 0 | AH75: =(EW75) -> 0 | AI75: =(EX75) -> 0 | AJ75: =(AS75) -> 0 | AK75: 37 | AL75: 37 | AM75: 0 | AN75: 0 | AO75: 0 | AP75: 0 | AQ75: 0 | AR75: 0 | AS75: 0 | AT75: 90 | AU75: 46 | AV75: 1 | AW75: 1 | AZ75: 1 | BA75: 1 | BB75: 1 | BC75: 9.88 | BH75: 3 | BI75: 2 | BM75: 68 | BN75: 0 | BP75: 0 | BQ75: 40 | BR75: 0 | BS75: 1 | BT75: 1 | BU75: 1 | BV75: 1 | BW75: 1 | BX75: 1 | BZ75: 90 | CA75: 46 | CE75: 30 | CF75: 0 | CG75: 0 | CM75: 0 | CO75: 0 | CP75: =(P75+Q75+S75) -> 2558.92 | CQ75: =ROUND((ROUND((AC75*AW75*1),2)*BC75),2) -> 365.56 | CR75: =(ROUND((ROUND(((ET75)*AV75*1),2)*BB75),2)+ROUND((ROUND(((AE75-(EU75))*AV75*1),2)*BS75),2)) -> 0 | CS75: =ROUND((ROUND((AE75*AV75*1),2)*BS75),2) -> 0 | CT75: =ROUND((ROUND((AF75*AV75*1),2)*BA75),2) -> 0 | CU75: =AG75 -> 0 | CV75: =(AH75*AV75) -> 0 | CW75: =AI75 -> 0 | CX75: =AJ75 -> 0 | CY75: =(((S75+R75)*AT75)/100) -> 0 | CZ75: =(((S75+R75)*AU75)/100) -> 0 | DN75: 0 | DO75: 0 | DP75: 1 | DQ75: 1 | DU75: 1010 | DV75: шт. | DW75: шт. | DX75: 1 | EE75: 58808178 | EF75: 40 | EG75: Монтаж оборудования | EH75: 0 | EJ75: 2 | EK75: 68 | EL75: ТСН-2001.4-10. Прокладка и монтаж сетей связи | EM75: ТСН-2001.4-10-1 | EQ75: 0 | ER75: 0 | ES75: 37 | ET75: 0 | EU75: 0 | EV75: 0 | EW75: 0 | EX75: 0 | EZ75: 5 | FC75: 1 | FD75: 18 | FF75: 430 | FQ75: 0 | FR75: 0 | FS75: 0 | FX75: 90 | FY75: 46 | GA75: [430 / 1,2 / 9,88] + 2% Заг.скл | GD75: 1 | GF75: -1209925472 | GG75: 2 | GH75: 2 | GI75: 5 | GJ75: 0 | GK75: 0 | GL75: =ROUND(IF(AND(BH75=3,BI75=3,FS75<>0),P75,0),2) -> 0 | GM75: =ROUND(O75+X75+Y75,2)+GX75 -> 2558.92 | GN75: =IF(OR(BI75=0,BI75=1),GM75-GX75,0) -> 0 | GO75: =IF(BI75=2,GM75-GX75,0) -> 2558.92 | GP75: =IF(BI75=4,GM75-GX75,0) -> 0 | GR75: 2 | GS75: 1 | GT75: 0 | GV75: =ROUND((GT75),6) -> 0 | GW75: 1 | GX75: =ROUND(HC75*I75,2) -> 0 | HA75: 0 | HB75: 0 | HC75: =GV75*GW75 -> 0 | HE75: 0 | HF75: 2 | HS75: 0 | IK75: 0
A76: 17 | B76: 1 | C76: =ROW(SmtRes!A88) -> 88 | D76: =ROW(EtalonRes!A99) -> 99 | E76: 22 | F76: 4.11-7-2 | G76: Установка аппарата настольного массой до 0,03 т | H76: 1 ШТ. | I76: =ROUND(ROUND(1,4),9) -> 1 | J76: 0 | K76: =ROUND(ROUND(1,4),9) -> 1 | O76: =ROUND(CP76,2) -> 70.41 | P76: =ROUND((ROUND((AC76*AW76*I76),2)*BC76),2) -> 0 | Q76: =(ROUND((ROUND((((ET76*1.1))*AV76*I76),2)*BB76),2)+ROUND((ROUND(((AE76-((EU76*1.1)))*AV76*I76),2)*BS76),2)) -> 30.62 | R76: =ROUND((ROUND((AE76*AV76*I76),2)*BS76),2) -> 4.65 | S76: =ROUND((ROUND((AF76*AV76*I76),2)*BA76),2) -> 39.79 | T76: =ROUND(CU76*I76,2) -> 0 | U76: =CV76*I76 -> 3.558753 | V76: =CW76*I76 -> 0 | W76: =ROUND(CX76*I76,2) -> 0 | X76: =ROUND(CY76,2) -> 40 | Y76: =ROUND(CZ76,2) -> 20.44 | AA76: 59213216 | AB76: =ROUND((AC76+AD76+AF76),6) -> 67.254 | AC76: =ROUND(((ES76*1)),6) -> 0 | AD76: =ROUND(((((ET76*1.1))-((EU76*1.1)))+AE76),6) -> 29.249 | AE76: =ROUND(((EU76*1.1)),6) -> 4.444 | AF76: =ROUND(((EV76*1.1)),6) -> 38.005 | AG76: =ROUND((AP76),6) -> 0 | AH76: =((EW76*1.1)) -> 3.399 | AI76: =((EX76*1.1)) -> 0 | AJ76: =(AS76) -> 0 | AK76: 61.14 | AL76: 0 | AM76: 26.59 | AN76: 4.04 | AO76: 34.55 | AP76: 0 | AQ76: 3.09 | AR76: 0 | AS76: 0 | AT76: 90 | AU76: 46 | AV76: 1.047 | AW76: 1 | AZ76: 1 | BA76: 1 | BB76: 1 | BC76: 1 | BH76: 0 | BI76: 2 | BJ76: ТСН-2001.4 Доп. 68, Сб. 11, т. 7, поз. 2 | BM76: 72 | BN76: 58808062 | BO76: 4.11-7-2 | BP76: 1 | BQ76: 40 | BR76: 0 | BS76: 1 | BT76: 1 | BU76: 1 | BV76: 1 | BW76: 1 | BX76: 1 | BZ76: 90 | CA76: 46 | CE76: 30 | CF76: 0 | CG76: 0 | CM76: 0 | CN76: Поправка: Гл.12.Прил.8.п.8. 5_12.00.01.11.003 Наименование: При наличии усложненных условий производства работ (стесненность, сложность складирования и транспортной логистики, наличие в зоне производства работ действующего технологического оборудования или движения технологического транспорта и т.п.) для объектов, расположенных за пределами территории круговой магистральной системы улиц "Садовое кольцо" и за пределами Третьего транспортного кольца города Москвы пунктов "а" и "б", но в пределах Московской кольцевой автомобильной дороги | CO76: 0 | CP76: =(P76+Q76+S76) -> 70.41 | CQ76: =ROUND((ROUND((AC76*AW76*1),2)*BC76),2) -> 0 | CR76: =(ROUND((ROUND((((ET76*1.1))*AV76*1),2)*BB76),2)+ROUND((ROUND(((AE76-((EU76*1.1)))*AV76*1),2)*BS76),2)) -> 30.62 | CS76: =ROUND((ROUND((AE76*AV76*1),2)*BS76),2) -> 4.65 | CT76: =ROUND((ROUND((AF76*AV76*1),2)*BA76),2) -> 39.79 | CU76: =AG76 -> 0 | CV76: =(AH76*AV76) -> 3.558753 | CW76: =AI76 -> 0 | CX76: =AJ76 -> 0 | CY76: =(((S76+R76)*AT76)/100) -> 39.996 | CZ76: =(((S76+R76)*AU76)/100) -> 20.4424 | DB76: 23 | DD76: *1 | DE76: *1,1 | DF76: *1,1 | DG76: *1,1 | DI76: *1,1 | DJ76: *1,1 | DN76: 0 | DO76: 0 | DP76: 1 | DQ76: 1 | DU76: 1013 | DV76: 1 ШТ. | DW76: 1 ШТ. | DX76: 1 | EE76: 58808182 | EF76: 40 | EG76: Монтаж оборудования | EH76: 0 | EJ76: 2 | EK76: 72 | EL76: ТСН-2001.4-11. Приборы и средства автоматизации и вычислительной техники | EM76: ТСН-2001.4-11-1 | EO76: Поправка: Гл.12.Прил.8.п.8. 5_12.00.01.11.003 | EQ76: 0 | ER76: 61.14 | ES76: 0 | ET76: 26.59 | EU76: 4.04 | EV76: 34.55 | EW76: 3.09 | EX76: 0 | EY76: 0 | FQ76: 0 | FR76: 0 | FS76: 0 | FX76: 90 | FY76: 46 | GD76: 1 | GF76: -1491520468 | GG76: 2 | GH76: 1 | GI76: 2 | GJ76: 0 | GK76: 0 | GL76: =ROUND(IF(AND(BH76=3,BI76=3,FS76<>0),P76,0),2) -> 0 | GM76: =ROUND(O76+X76+Y76,2)+GX76 -> 130.85 | GN76: =IF(OR(BI76=0,BI76=1),GM76-GX76,0) -> 0 | GO76: =IF(BI76=2,GM76-GX76,0) -> 130.85 | GP76: =IF(BI76=4,GM76-GX76,0) -> 0 | GR76: 0 | GS76: 3 | GT76: 0 | GV76: =ROUND((GT76),6) -> 0 | GW76: 1 | GX76: =ROUND(HC76*I76,2) -> 0 | HA76: 0 | HB76: 0 | HC76: =GV76*GW76 -> 0 | HS76: 0 | IK76: 0
