Workbook

Sheet 02-01-19
A1: =Source!B1 -> Smeta.RU (495) 974-1589
J2: Форма № 4б
A3: Капитальный ремонт здания Государственного бюджетного общеобразовательного учреждения города Москвы «Школа № 236» по адресу: г. Москва, ул. Клязьминская, д. 7, к. 4. I этап | AP3: Капитальный ремонт здания Государственного бюджетного общеобразовательного учреждения города Москвы «Школа № 236» по адресу: г. Москва, ул. Клязьминская, д. 7, к. 4. I этап. 02-01-19 Вертикальный транспорт
A4: (наименование стройки и/или объекта)
A6: =CONCATENATE( "ЛОКАЛЬНАЯ СМЕТА № ",IF(Source!F20<>"Новая локальная смета", Source!F20, "")) -> ЛОКАЛЬНАЯ СМЕТА № 02-01-19
A8: =IF(Source!G20<>"Новая локальная смета", Source!G20, "") -> Вертикальный транспорт
A9: (наименование работ и затрат)
A11: =CONCATENATE( "Основание: чертежи № ", Source!J20) -> Основание: чертежи № 2024-00272-01-0-ВТ
I13: В базисном уровне цен | J13: В текущем уровне цен
E14: Сметная стоимость | I14: =I15+I16+I17+I18 -> 58.02 | J14: =J15+J16+J17+J18 -> 837.05 | K14: тыс.руб.
E15: Строительные работы | I15: =ROUND((Source!F93)/1000, 2) -> 0 | J15: =ROUND((Source!P93)/1000, 2) -> 0 | K15: тыс.руб.
E16: Работы по монтажу оборудования | I16: =ROUND((Source!F94)/1000, 2) -> 9.26 | J16: =ROUND((Source!P94)/1000, 2) -> 463.54 | K16: тыс.руб.
E17: Оборудование | I17: =ROUND((Source!F85)/1000, 2) -> 48.76 | J17: =ROUND((Source!P85)/1000, 2) -> 373.51 | K17: тыс.руб.
E18: Прочие работы и затраты | I18: =ROUND((Source!F95+Source!F96)/1000, 2) -> 0 | J18: =ROUND((Source!P95+Source!P96)/1000, 2) -> 0 | K18: тыс.руб.
E19: Средства на оплату труда | I19: =(Source!F91+ Source!F90)/1000 -> 3.42149 | J19: =((Source!P91 + Source!P90)/1000) -> 188.14774 | K19: тыс.руб.
E20: Затраты труда | I20: =Source!F98 -> 252.13564 | K20: чел.-ч.
E21: Кроме того:
E22: Возврат материалов | I22: =SUM(Y28:Y112)/1000 -> 0 | J22: =SUM(Z28:Z112)/1000 -> 0 | K22: тыс.руб.
A24: Составлен(а) по ТСН-2001 с учетом Дополнения №: 80
A25: № и период сборника коэффициентов (индексов) пересчета: Коэффициенты к ТСН-2001 МГЭ Дополнение 80, строительство №217/80 III квартал 2025 года и Коэффициенты к ТСН-2001.13-2 Дополнение 46 №62/46 III квартал 2025 года | AP25: № и период сборника коэффициентов (индексов) пересчета: Коэффициенты к ТСН-2001 МГЭ Дополнение 80, строительство №217/80 III квартал 2025 года и Коэффициенты к ТСН-2001.13-2 Дополнение 46 №62/46 III квартал 2025 года
A26: № п/п | B26: Шифр расценки и коды ресурсов | C26: Наименование работ и затрат | D26: Ед. изм. | E26: Кол-во единиц | F26: Цена на ед. изм., руб. | G26: Попра- вочные коэффи- циенты | H26: Коэффи- циенты зимних удорожа- ний | I26: Всего в ценах на январь 2000 года, руб. | J26: Коэффи- циенты (индек- сы) пере- счета, нормы НР и СП | K26: ВСЕГО затрат в текущем уровне цен, руб.
A27: 1 | B27: 2 | C27: 3 | D27: 4 | E27: 5 | F27: 6 | G27: 7 | H27: 8 | I27: 9 | J27: 10 | K27: 11
A29: =CONCATENATE("Раздел: ",IF(Source!G24<>"Новый раздел", Source!G24, "")) -> Раздел: Подъемник грузовой консольный в осях «Ж-И/4-5»
C30: =Source!G28 -> Демонтажные работы
A31: 1 | B31: 4.3-32-1 Поправка: Гл.12.Прил.8.п.8. 5_12.00.01.11.003 | C31: Лифт малогрузовой со скоростью движения кабины до 0,5 м/с, грузоподъемностью 100 кг, на 6 остановок, в глухой шахте, высота 21 м (схема управления релейно-контакторная)/ грузовой подъёмник | D31: =Source!H29 -> 1 лифт | E31: =Source!I29 -> 1 | Q31: =Source!X29 -> 1487.35 | R31: =Source!X30 -> 81789.13 | S31: =Source!Y29 -> 792.17 | T31: =Source!Y30 -> 43561.6 | U31: =ROUND((175/100)*ROUND(Source!R29, 2), 2) -> 14.91 | V31: =ROUND((0/100)*ROUND(Source!R30, 2), 2) -> 0 | AC31: 0
C32: ЗП | F32: =Source!AO29 -> 4567.2 | G32: =Source!DG29 -> *0,3)*1,1 | H32: =Source!AV30 -> 1.067 | I32: =Source!S29 -> 1608.16 | J32: =IF(Source!BA30<> 0, Source!BA30, 1) -> 54.99 | K32: =Source!S30 -> 88432.72
C33: ЭМ | F33: =Source!AM29 -> 338.32 | G33: =Source!DE29 -> *0,3)*1,1 | H33: =Source!AV30 -> 1.067 | I33: =Source!Q29 -> 119.13 | J33: =IF(Source!BB30<> 0, Source!BB30, 1) -> 13.26 | K33: =Source!Q30 -> 1579.66
C34: в т.ч. ЗПМ | F34: =Source!AN29 -> 24.21 | G34: =Source!DF29 -> *0,3)*1,1 | H34: =Source!AV30 -> 1.067 | I34: =Source!R29 -> 8.52 | J34: =IF(Source!BS30<> 0, Source!BS30, 1) -> 54.99 | K34: =Source!R30 -> 468.51
C35: НР от ФОТ | D35: % | E35: =Source!BZ30 -> 92 | I35: =SUM(Q31:Q34) -> 1487.35 | J35: =Source!AT30 -> 92 | K35: =SUM(R31:R34) -> 81789.13
C36: СП от ФОТ | D36: % | E36: =Source!CA30 -> 49 | I36: =SUM(S31:S35) -> 792.17 | J36: =Source!AU30 -> 49 | K36: =SUM(T31:T35) -> 43561.6
C37: ЗТР | D37: чел-ч | E37: =Source!AQ29 -> 346 | G37: =Source!DI29 -> *0,3)*1,1 | H37: =Source!AV30 -> 1.067 | I37: =Source!U29 -> 121.83006
C38: ВСЕГО работ по позиции: | H38: =I32+I33+I35+I36+0-0-0 -> 4006.81 | J38: =K32+K33+K35+K36+0-0-0 -> 215363.11
C39: ВСЕГО оборудование по позиции: | H39: =0+0 -> 0 | J39: =0+0 -> 0
C40: ВСЕГО по позиции: | H40: =I32+I33+I35+I36+0 -> 4006.81 | J40: =K32+K33+K35+K36+0 -> 215363.11 | O40: =I32+I33+I35+I36+0 -> 4006.81 | P40: =K32+K33+K35+K36+0 -> 215363.11
A42: 2 | B42: 4.3-32-3 Поправка: Гл.12.Прил.8.п.8. 5_12.00.01.11.003 | C42: За каждую остановку, более или менее указанных в характеристике лифта грузоподъемностью 100 кг в глухой шахте добавлять или уменьшать (схема управления релейно-контакторная)/ грузовой подъёмник | D42: =Source!H31 -> 1 остановка | E42: =Source!I31 -> -4 | Q42: =Source!X31 -> -388.23 | R42: =Source!X32 -> -21348.81 | S42: =Source!Y31 -> -206.78 | T42: =Source!Y32 -> -11370.56 | U42: =ROUND((175/100)*ROUND(Source!R31, 2), 2) -> -6.44 | V42: =ROUND((0/100)*ROUND(Source!R32, 2), 2) -> 0 | AC42: 0
C43: ="Объем: "&Source!I31&"=2-"&"6" -> Объем: -4=2-6
C44: ЗП | F44: =Source!AO31 -> 297 | G44: =Source!DG31 -> *0,3)*1,1 | H44: =Source!AV32 -> 1.067 | I44: =Source!S31 -> -418.31 | J44: =IF(Source!BA32<> 0, Source!BA32, 1) -> 54.99 | K44: =Source!S32 -> -23002.87
C45: ЭМ | F45: =Source!AM31 -> 34.82 | G45: =Source!DE31 -> *0,3)*1,1 | H45: =Source!AV32 -> 1.067 | I45: =Source!Q31 -> -49.04 | J45: =IF(Source!BB32<> 0, Source!BB32, 1) -> 13.41 | K45: =Source!Q32 -> -657.63
C46: в т.ч. ЗПМ | F46: =Source!AN31 -> 2.61 | G46: =Source!DF31 -> *0,3)*1,1 | H46: =Source!AV32 -> 1.067 | I46: =Source!R31 -> -3.68 | J46: =IF(Source!BS32<> 0, Source!BS32, 1) -> 54.99 | K46: =Source!R32 -> -202.36
C47: НР от ФОТ | D47: % | E47: =Source!BZ32 -> 92 | I47: =SUM(Q42:Q46) -> -388.23 | J47: =Source!AT32 -> 92 | K47: =SUM(R42:R46) -> -21348.81
C48: СП от ФОТ | D48: % | E48: =Source!CA32 -> 49 | I48: =SUM(S42:S47) -> -206.78 | J48: =Source!AU32 -> 49 | K48: =SUM(T42:T47) -> -11370.56
C49: ЗТР | D49: чел-ч | E49: =Source!AQ31 -> 22.5 | G49: =Source!DI31 -> *0,3)*1,1 | H49: =Source!AV32 -> 1.067 | I49: =Source!U31 -> -31.6899
C50: ВСЕГО работ по позиции: | H50: =I44+I45+I47+I48+0-0-0 -> -1062.36 | J50: =K44+K45+K47+K48+0-0-0 -> -56379.87
C51: ВСЕГО оборудование по позиции: | H51: =0+0 -> 0 | J51: =0+0 -> 0
C52: ВСЕГО по позиции: | H52: =I44+I45+I47+I48+0 -> -1062.36 | J52: =K44+K45+K47+K48+0 -> -56379.87 | O52: =I44+I45+I47+I48+0 -> -1062.36 | P52: =K44+K45+K47+K48+0 -> -56379.87
A54: 3 | B54: 4.3-32-4 Поправка: Гл.12.Прил.8.п.8. 5_12.00.01.11.003 | C54: За каждый 1 м высоты шахты, более или менее указанных в характеристике малогрузового лифта грузоподъемностью 100 кг в глухой шахте добавлять или уменьшать (схема управления релейно-контакторная)/ грузовой подъёмник | D54: =Source!H33 -> 1 М | E54: =Source!I33 -> -14.92 | Q54: =Source!X33 -> -401.93 | R54: =Source!X34 -> -22102.11 | S54: =Source!Y33 -> -214.07 | T54: =Source!Y34 -> -11771.77 | U54: =ROUND((175/100)*ROUND(Source!R33, 2), 2) -> 0 | V54: =ROUND((0/100)*ROUND(Source!R34, 2), 2) -> 0 | AC54: 0
C55: ="Объем: "&Source!I33&"=(3,15+"&"2,93-"&"21)" -> Объем: -14,92=(3,15+2,93-21)
C56: ЗП | F56: =Source!AO33 -> 83.16 | G56: =Source!DG33 -> *0,3)*1,1 | H56: =Source!AV34 -> 1.067 | I56: =Source!S33 -> -436.88 | J56: =IF(Source!BA34<> 0, Source!BA34, 1) -> 54.99 | K56: =Source!S34 -> -24024.03
C57: НР от ФОТ | D57: % | E57: =Source!BZ34 -> 92 | I57: =SUM(Q54:Q56) -> -401.93 | J57: =Source!AT34 -> 92 | K57: =SUM(R54:R56) -> -22102.11
C58: СП от ФОТ | D58: % | E58: =Source!CA34 -> 49 | I58: =SUM(S54:S57) -> -214.07 | J58: =Source!AU34 -> 49 | K58: =SUM(T54:T57) -> -11771.77
C59: ЗТР | D59: чел-ч | E59: =Source!AQ33 -> 6.3 | G59: =Source!DI33 -> *0,3)*1,1 | H59: =Source!AV34 -> 1.067 | I59: =Source!U33 -> -33.096932
C60: ВСЕГО работ по позиции: | H60: =I56+I57+I58+0-0-0 -> -1052.88 | J60: =K56+K57+K58+0-0-0 -> -57897.91
C61: ВСЕГО оборудование по позиции: | H61: =0+0 -> 0 | J61: =0+0 -> 0
C62: ВСЕГО по позиции: | H62: =I56+I57+I58+0 -> -1052.88 | J62: =K56+K57+K58+0 -> -57897.91 | O62: =I56+I57+I58+0 -> -1052.88 | P62: =K56+K57+K58+0 -> -57897.91
C64: =Source!G35 -> Монтажные работы
A65: 4 | B65: 4.3-34-1 Поправка: Гл.12.Прил.8.п.8. 5_12.00.01.11.003 | C65: Лифт малогрузовой со скоростью движения кабины до 0,5 м/с, грузоподъемностью 100 кг, на 6 остановок, в глухой шахте, высота 21 м (схема управления микроэлектронная и микропроцессорная)/ грузовой подъёмник | D65: =Source!H36 -> 1 лифт | E65: =Source!I36 -> 1 | Q65: =Source!X36 -> 5242.59 | R65: =Source!X37 -> 288290.16 | S65: =Source!Y36 -> 2792.25 | T65: =Source!Y37 -> 153545.85 | U65: =ROUND((175/100)*ROUND(Source!R36, 2), 2) -> 49.74 | V65: =ROUND((0/100)*ROUND(Source!R37, 2), 2) -> 0 | AC65: 0
C66: ЗП | F66: =Source!AO36 -> 4830.92 | G66: =Source!DG36 -> *1,1 | H66: =Source!AV37 -> 1.067 | I66: =Source!S36 -> 5670.05 | J66: =IF(Source!BA37<> 0, Source!BA37, 1) -> 54.99 | K66: =Source!S37 -> 311796.05
C67: ЭМ | F67: =Source!AM36 -> 338.32 | G67: =Source!DE36 -> *1,1 | H67: =Source!AV37 -> 1.067 | I67: =Source!Q36 -> 397.09 | J67: =IF(Source!BB37<> 0, Source!BB37, 1) -> 13.26 | K67: =Source!Q37 -> 5265.41
C68: в т.ч. ЗПМ | F68: =Source!AN36 -> 24.21 | G68: =Source!DF36 -> *1,1 | H68: =Source!AV37 -> 1.067 | I68: =Source!R36 -> 28.42 | J68: =IF(Source!BS37<> 0, Source!BS37, 1) -> 54.99 | K68: =Source!R37 -> 1562.82
C69: МР | F69: =Source!AL36 -> 959 | G69: =Source!DD36 -> *1 | H69: =Source!AW37 -> 1.028 | I69: =Source!P36 -> 985.85 | J69: =IF(Source!BC37<> 0, Source!BC37, 1) -> 9.89 | K69: =Source!P37 -> 9750.06
C70: НР от ФОТ | D70: % | E70: =Source!BZ37 -> 92 | I70: =SUM(Q65:Q69) -> 5242.59 | J70: =Source!AT37 -> 92 | K70: =SUM(R65:R69) -> 288290.16
C71: СП от ФОТ | D71: % | E71: =Source!CA37 -> 49 | I71: =SUM(S65:S70) -> 2792.25 | J71: =Source!AU37 -> 49 | K71: =SUM(T65:T70) -> 153545.85
C72: ЗТР | D72: чел-ч | E72: =Source!AQ36 -> 356 | G72: =Source!DI36 -> *1,1 | H72: =Source!AV37 -> 1.067 | I72: =Source!U36 -> 417.8372
C73: ВСЕГО работ по позиции: | H73: =I66+I67+I69+I70+I71+0-0-0 -> 15087.83 | J73: =K66+K67+K69+K70+K71+0-0-0 -> 768647.53
C74: ВСЕГО оборудование по позиции: | H74: =0+0 -> 0 | J74: =0+0 -> 0
C75: ВСЕГО по позиции: | H75: =I66+I67+I69+I70+I71+0 -> 15087.83 | J75: =K66+K67+K69+K70+K71+0 -> 768647.53 | O75: =I66+I67+I69+I70+I71+0 -> 15087.83 | P75: =K66+K67+K69+K70+K71+0 -> 768647.53
A77: 5 | B77: 4.3-34-3 Поправка: Гл.12.Прил.8.п.8. 5_12.00.01.11.003 | C77: За каждую остановку, более или менее указанных в характеристике лифта грузоподъемностью 100 кг в глухой шахте добавлять или уменьшать (схема управления микроэлектронная и микропроцессорная)/ грузовой подъёмник | D77: =Source!H38 -> 1 остановка | E77: =Source!I38 -> -4 | Q77: =Source!X38 -> -1371.05 | R77: =Source!X39 -> -75393.95 | S77: =Source!Y38 -> -730.23 | T77: =Source!Y39 -> -40155.48 | U77: =ROUND((175/100)*ROUND(Source!R38, 2), 2) -> -21.44 | V77: =ROUND((0/100)*ROUND(Source!R39, 2), 2) -> 0 | AC77: 0
C78: ="Объем: "&Source!I38&"=2-"&"6" -> Объем: -4=2-6
C79: ЗП | F79: =Source!AO38 -> 314.82 | G79: =Source!DG38 -> *1,1 | H79: =Source!AV39 -> 1.067 | I79: =Source!S38 -> -1478.02 | J79: =IF(Source!BA39<> 0, Source!BA39, 1) -> 54.99 | K79: =Source!S39 -> -81276.32
C80: ЭМ | F80: =Source!AM38 -> 34.82 | G80: =Source!DE38 -> *1,1 | H80: =Source!AV39 -> 1.067 | I80: =Source!Q38 -> -163.47 | J80: =IF(Source!BB39<> 0, Source!BB39, 1) -> 13.41 | K80: =Source!Q39 -> -2192.13
C81: в т.ч. ЗПМ | F81: =Source!AN38 -> 2.61 | G81: =Source!DF38 -> *1,1 | H81: =Source!AV39 -> 1.067 | I81: =Source!R38 -> -12.25 | J81: =IF(Source!BS39<> 0, Source!BS39, 1) -> 54.99 | K81: =Source!R39 -> -673.63
C82: МР | F82: =Source!AL38 -> 58.8 | G82: =Source!DD38 -> *1 | H82: =Source!AW39 -> 1.028 | I82: =Source!P38 -> -241.79 | J82: =IF(Source!BC39<> 0, Source!BC39, 1) -> 9.89 | K82: =Source!P39 -> -2391.3
C83: НР от ФОТ | D83: % | E83: =Source!BZ39 -> 92 | I83: =SUM(Q77:Q82) -> -1371.05 | J83: =Source!AT39 -> 92 | K83: =SUM(R77:R82) -> -75393.95
C84: СП от ФОТ | D84: % | E84: =Source!CA39 -> 49 | I84: =SUM(S77:S83) -> -730.23 | J84: =Source!AU39 -> 49 | K84: =SUM(T77:T83) -> -40155.48
C85: ЗТР | D85: чел-ч | E85: =Source!AQ38 -> 23.2 | G85: =Source!DI38 -> *1,1 | H85: =Source!AV39 -> 1.067 | I85: =Source!U38 -> -108.91936
C86: ВСЕГО работ по позиции: | H86: =I79+I80+I82+I83+I84+0-0-0 -> -3984.56 | J86: =K79+K80+K82+K83+K84+0-0-0 -> -201409.18
C87: ВСЕГО оборудование по позиции: | H87: =0+0 -> 0 | J87: =0+0 -> 0
C88: ВСЕГО по позиции: | H88: =I79+I80+I82+I83+I84+0 -> -3984.56 | J88: =K79+K80+K82+K83+K84+0 -> -201409.18 | O88: =I79+I80+I82+I83+I84+0 -> -3984.56 | P88: =K79+K80+K82+K83+K84+0 -> -201409.18
A90: 6 | B90: 4.3-34-4 Поправка: Гл.12.Прил.8.п.8. 5_12.00.01.11.003 | C90: За каждый 1 м высоты шахты, более или менее указанных в характеристике малогрузового лифта грузоподъемностью 100 кг в глухой шахте добавлять или уменьшать (схема управления микроэлектронная и микропроцессорная)/ грузовой подъёмник | D90: =Source!H40 -> 1 М | E90: =Source!I40 -> -14.92 | Q90: =Source!X40 -> -1420.96 | R90: =Source!X41 -> -78138.5 | S90: =Source!Y40 -> -756.81 | T90: =Source!Y41 -> -41617.24 | U90: =ROUND((175/100)*ROUND(Source!R40, 2), 2) -> 0 | V90: =ROUND((0/100)*ROUND(Source!R41, 2), 2) -> 0 | AC90: 0
C91: ="Объем: "&Source!I40&"=(3,15+"&"2,93-"&"21)" -> Объем: -14,92=(3,15+2,93-21)
C92: ЗП | F92: =Source!AO40 -> 88.2 | G92: =Source!DG40 -> *1,1 | H92: =Source!AV41 -> 1.067 | I92: =Source!S40 -> -1544.52 | J92: =IF(Source!BA41<> 0, Source!BA41, 1) -> 54.99 | K92: =Source!S41 -> -84933.15
C93: МР | F93: =Source!AL40 -> 0.63 | G93: =Source!DD40 -> *1 | H93: =Source!AW41 -> 1.028 | I93: =Source!P40 -> -9.66 | J93: =IF(Source!BC41<> 0, Source!BC41, 1) -> 9.89 | K93: =Source!P41 -> -95.54
C94: НР от ФОТ | D94: % | E94: =Source!BZ41 -> 92 | I94: =SUM(Q90:Q93) -> -1420.96 | J94: =Source!AT41 -> 92 | K94: =SUM(R90:R93) -> -78138.5
C95: СП от ФОТ | D95: % | E95: =Source!CA41 -> 49 | I95: =SUM(S90:S94) -> -756.81 | J95: =Source!AU41 -> 49 | K95: =SUM(T90:T94) -> -41617.24
C96: ЗТР | D96: чел-ч | E96: =Source!AQ40 -> 6.5 | G96: =Source!DI40 -> *1,1 | H96: =Source!AV41 -> 1.067 | I96: =Source!U40 -> -113.82543
C97: ВСЕГО работ по позиции: | H97: =I92+I93+I94+I95+0-0-0 -> -3731.95 | J97: =K92+K93+K94+K95+0-0-0 -> -204784.43
C98: ВСЕГО оборудование по позиции: | H98: =0+0 -> 0 | J98: =0+0 -> 0
C99: ВСЕГО по позиции: | H99: =I92+I93+I94+I95+0 -> -3731.95 | J99: =K92+K93+K94+K95+0 -> -204784.43 | O99: =I92+I93+I94+I95+0 -> -3731.95 | P99: =K92+K93+K94+K95+0 -> -204784.43
C101: =Source!G42 -> Оборудование
A102: 7 | B102: =Source!F43 -> КА 1 | C102: ОБОРУДОВАНИЕ:_x000D_ Подъемник грузовой консольный РЕСТО-ПГ-Ш-100-3150 ТТ 48 761,40 = [430 000 / 1,2 / 7,66] + 3% Трансп + 1,2% Заг.скл | D102: =Source!H43 -> шт. | E102: =Source!I43 -> 1 | F102: =Source!AL43 -> 48761.4 | G102: =Source!DD43 | H102: =Source!AW44 -> 1 | I102: =Source!P43 -> 48761.4 | J102: =IF(Source!BC44<> 0, Source!BC44, 1) -> 7.66 | K102: =Source!P44 -> 373512.32 | Q102: =Source!X43 -> 0 | R102: =Source!X44 -> 0 | S102: =Source!Y43 -> 0 | T102: =Source!Y44 -> 0 | U102: =ROUND((175/100)*ROUND(Source!R43, 2), 2) -> 0 | V102: =ROUND((0/100)*ROUND(Source!R44, 2), 2) -> 0 | AC102: 5
C103: ВСЕГО по позиции: | H103: =I102+0 -> 48761.4 | J103: =K102+0 -> 373512.32 | O103: =I102+0 -> 48761.4 | P103: =K102+0 -> 373512.32
A106: =CONCATENATE("Итого по разделу: ",IF(Source!G46<>"Новый раздел", Source!G46, "")) -> Итого по разделу: Подъемник грузовой консольный в осях «Ж-И/4-5» | H106: =SUM(O29:O105) -> 58024.29 | J106: =SUM(P29:P105) -> 837051.57 | AQ106: =CONCATENATE("Итого по разделу: ",IF(Source!G46<>"Новый раздел", Source!G46, "")) -> Итого по разделу: Подъемник грузовой консольный в осях «Ж-И/4-5»
A107: Итого по ТСН-2001.16 | I107: =SUM(W29:W106) -> 0 | J107: =SUM(X29:X106) -> 0
A108: Итого возвратных сумм | I108: =SUM(Y29:Y107) -> 0 | J108: =SUM(Z29:Z107) -> 0
A110: =CONCATENATE("Итого по локальной смете: ",IF(Source!G76<>"Новая локальная смета", Source!G76, "")) -> Итого по локальной смете: Вертикальный транспорт | H110: =SUM(O28:O109) -> 58024.29 | J110: =SUM(P28:P109) -> 837051.57
A111: Итого по ТСН-2001.16 | I111: =SUM(W28:W110) -> 0 | J111: =SUM(X28:X110) -> 0
A112: Итого возвратных сумм | I112: =SUM(Y28:Y111) -> 0 | J112: =SUM(Z28:Z111) -> 0
A115: Составил | C115: =IF(Source!AC12<>"", Source!AC12," ") | H115: =IF(Source!AB12<>"", Source!AB12," ") -> Борисова Е.С.
C116: (должность, подпись, инициалы, фамилия)
A118: Проверил | C118: =IF(Source!AE12<>"", Source!AE12," ") | H118: =IF(Source!AD12<>"", Source!AD12," ")
...

Sheet 02-01-19_1
A1: =Source!B1 -> Smeta.RU (495) 974-1589
E3: "УТВЕРЖДАЮ"
D5: ___________________________
D7: ___________________________
D9: " ___ " ___________ 20 ___ г.
B12: =CONCATENATE("Ведомость объемов работ ", IF(Source!AN15<>"", Source!AN15," ")) -> Ведомость объемов работ
B13: =CONCATENATE(Source!F12, " ", Source!G12) -> 02-01-19 02-01-19 Вертикальный транспорт
B14: =CONCATENATE(Source!F20, " ", Source!G20) -> 02-01-19 Вертикальный транспорт
A16: № п/п | B16: № в ЛСР | C16: Наименование работ и затрат | D16: Единица измерения | E16: Количество | F16: Ссылка на чертежи, спецификации | G16: Формула расчета, расчет объемов работ и расхода материалов | H16: Примечание
A17: 1 | B17: 2 | C17: 3 | D17: 4 | E17: 5 | F17: 6 | G17: 7 | H17: 8
A18: =CONCATENATE("Раздел: ", Source!G24) -> Раздел: Подъемник грузовой консольный в осях «Ж-И/4-5»
A19: 1 | B19: =Source!E29 -> 1 | C19: =Source!G29 -> Лифт малогрузовой со скоростью движения кабины до 0,5 м/с, грузоподъемностью 100 кг, на 6 остановок, в глухой шахте, высота 21 м (схема управления релейно-контакторная)/ грузовой подъёмник | D19: 1 лифт | E19: =Source!I29 -> 1 | F19: =Source!U24 | G19: =Source!I29 -> 1
A20: 2 | B20: =Source!E31 -> 2 | C20: =Source!G31 -> За каждую остановку, более или менее указанных в характеристике лифта грузоподъемностью 100 кг в глухой шахте добавлять или уменьшать (схема управления релейно-контакторная)/ грузовой подъёмник | D20: 1 остановка | E20: =Source!I31 -> -4 | F20: =Source!U24 | G20: ="=2-"&"6" -> =2-6
A21: 3 | B21: =Source!E33 -> 3 | C21: =Source!G33 -> За каждый 1 м высоты шахты, более или менее указанных в характеристике малогрузового лифта грузоподъемностью 100 кг в глухой шахте добавлять или уменьшать (схема управления релейно-контакторная)/ грузовой подъёмник | D21: 1 М | E21: =Source!I33 -> -14.92 | F21: =Source!U24 | G21: ="=(3,15+"&"2,93-"&"21)" -> =(3,15+2,93-21)
A22: 4 | B22: =Source!E36 -> 4 | C22: =Source!G36 -> Лифт малогрузовой со скоростью движения кабины до 0,5 м/с, грузоподъемностью 100 кг, на 6 остановок, в глухой шахте, высота 21 м (схема управления микроэлектронная и микропроцессорная)/ грузовой подъёмник | D22: 1 лифт | E22: =Source!I36 -> 1 | F22: =Source!U24 | G22: =Source!I36 -> 1
A23: 5 | B23: =Source!E38 -> 5 | C23: =Source!G38 -> За каждую остановку, более или менее указанных в характеристике лифта грузоподъемностью 100 кг в глухой шахте добавлять или уменьшать (схема управления микроэлектронная и микропроцессорная)/ грузовой подъёмник | D23: 1 остановка | E23: =Source!I38 -> -4 | F23: =Source!U24 | G23: ="=2-"&"6" -> =2-6
A24: 6 | B24: =Source!E40 -> 6 | C24: =Source!G40 -> За каждый 1 м высоты шахты, более или менее указанных в характеристике малогрузового лифта грузоподъемностью 100 кг в глухой шахте добавлять или уменьшать (схема управления микроэлектронная и микропроцессорная)/ грузовой подъёмник | D24: 1 М | E24: =Source!I40 -> -14.92 | F24: =Source!U24 | G24: ="=(3,15+"&"2,93-"&"21)" -> =(3,15+2,93-21)
A25: 7 | B25: =Source!E43 -> 7 | C25: =Source!G43 -> Подъемник грузовой консольный РЕСТО-ПГ-Ш-100-3150 ТТ | D25: шт. | E25: =Source!I43 -> 1 | F25: =Source!U24 | G25: =Source!I43 -> 1
C28: Главный инженер проекта _________________ | D28: =IF(Source!X12<>"", Source!X12," ")
C30: Составил _________________ | D30: =IF(Source!AB12<>"", Source!AB12," ") -> Борисова Е.С.

Sheet Source
A1: 0 | B1: Smeta.RU (495) 974-1589 | D1: _PS_ | F1: 0 | G1: 0 | H1: 0 | I1: Smeta.RU | K1: 1 | L1: 74561 | M1: 10 | N1: 11 | O1: 15 | P1: 0 | Q1: 2
A4: 1 | B4: 1 | C4: -1 | G4: Капитальный ремонт здания Государственного бюджетного общеобразовательного учреждения города Москвы «Школа № 236» по адресу: г. Москва, ул. Клязьминская, д. 7, к. 4. I этап | EC4: 0
A12: 1 | B12: 145 | C12: 0 | D12: =ROW(A106) -> 106 | E12: 0 | F12: 02-01-19 | G12: 02-01-19 Вертикальный транспорт | I12: 0 | J12: 2024-00272-01-0-ВТ | K12: 0 | L12: 0 | M12: 4098 | O12: 0 | P12: 0 | Q12: 0 | R12: 0 | S12: 0 | T12: 1 | V12: 2 | AB12: Борисова Е.С. | BB12: 0 | BH12: Сметные нормы списания | BI12: Коды ОКП для ТСН-2001 МГЭ Дополнение 80 | BJ12: 1 | BK12: 1 | BL12: 0 | BM12: 0 | BN12: 1 | BO12: 0 | BP12: 6 | BQ12: 2 | BR12: 1 | BS12: 1 | BT12: 1 | BU12: 0 | BV12: 1 | BW12: 0 | BX12: 0 | BZ12: Типовой расчет для ТСН-2001 МГЭ, Дополнение 80, строительство | CA12: Территориальные сметные нормативы для Москвы ТСН-2001 (МГЭ), дополнение 80 | CB12: Территориальные сметные нормативы для Москвы ТСН-2001 (МГЭ), дополнение 80 | CC12: Территориальные сметные нормативы для Москвы ТСН-2001 (МГЭ), дополнение 80 | CD12: Территориальные сметные нормативы для Москвы ТСН-2001 (МГЭ), дополнение 80 | CE12: Поправки для ТСН-2001 от 03.02.2026 г. доп.80 | CF12: 0 | CG12: 0 | CH12: 10 | CK12: 80 | CQ12: Территориальные сметные нормативы для Москвы (ТСН-2001) | CR12: ТЕР | CS12: 41660 | CT12: 1 | CU12: 80 | CY12: 0 | EC12: 0
A15: 15 | B15: 1
A18: 52 | B18: =B106 -> 145 | C18: =C106 -> 1 | D18: =D106 -> 12 | E18: =E106 -> 0 | F18: =F106 -> 02-01-19 | G18: =G106 -> 02-01-19 Вертикальный транспорт | O18: =O106 -> 53199.99 | P18: =P106 -> 49495.8 | Q18: =Q106 -> 303.71 | R18: =R106 -> 21.01 | S18: =S106 -> 3400.48 | T18: =T106 -> 0 | U18: =U106 -> 252.13564 | V18: =V106 -> 0 | ... GX18: =GX106 -> 0
A20: 3 | B20: 1 | D20: =ROW(A76) -> 76 | F20: 02-01-19 | G20: Вертикальный транспорт | I20: 0 | J20: 2024-00272-01-0-ВТ | K20: -1 | L20: 02-01-19 | S20: 0 | T20: 0 | V20: 2 | AB20: Борисова Е.С. | BX20: 0 | CF20: 0 | CG20: 0
A22: 52 | B22: =B76 -> 1 | C22: =C76 -> 3 | D22: =D76 -> 20 | E22: =E76 -> 0 | F22: =F76 -> 02-01-19 | G22: =G76 -> Вертикальный транспорт | O22: =O76 -> 53199.99 | P22: =P76 -> 49495.8 | Q22: =Q76 -> 303.71 | R22: =R76 -> 21.01 | S22: =S76 -> 3400.48 | T22: =T76 -> 0 | U22: =U76 -> 252.13564 | V22: =V76 -> 0 | ... GX22: =GX76 -> 0
A24: 4 | B24: 1 | D24: =ROW(A46) -> 46 | G24: Подъемник грузовой консольный в осях «Ж-И/4-5» | I24: 0 | K24: -1 | S24: 0 | T24: 0 | V24: 2 | BX24: 0 | CJ24: 0
A26: 52 | B26: =B46 -> 1 | C26: =C46 -> 4 | D26: =D46 -> 24 | E26: =E46 -> 0 | F26: =F46 | G26: =G46 -> Подъемник грузовой консольный в осях «Ж-И/4-5» | O26: =O46 -> 53199.99 | P26: =P46 -> 49495.8 | Q26: =Q46 -> 303.71 | R26: =R46 -> 21.01 | S26: =S46 -> 3400.48 | T26: =T46 -> 0 | U26: =U46 -> 252.13564 | V26: =V46 -> 0 | ... GX26: =GX46 -> 0
A28: 19 | B28: 1 | G28: Демонтажные работы | AA28: 1 | IK28: 0
A29: 17 | B29: 1 | C29: =ROW(SmtRes!A2) -> 2 | D29: =ROW(EtalonRes!A2) -> 2 | E29: 1 | F29: 4.3-32-1 | G29: Лифт малогрузовой со скоростью движения кабины до 0,5 м/с, грузоподъемностью 100 кг, на 6 остановок, в глухой шахте, высота 21 м (схема управления релейно-контакторная)/ грузовой подъёмник | H29: 1 лифт | I29: 1 | J29: 0 | K29: 1 | O29: =ROUND(CP29,2) -> 1727.29 | P29: =ROUND((ROUND((AC29*AW29*I29),2)*BC29),2) -> 0 | Q29: =(ROUND((ROUND(((((ET29*0.3)*1.1))*AV29*I29),2)*BB29),2)+ROUND((ROUND(((AE29-(((EU29*0.3)*1.1)))*AV29*I29),2)*BS29),2)) -> 119.13 | R29: =ROUND((ROUND((AE29*AV29*I29),2)*BS29),2) -> 8.52 | S29: =ROUND((ROUND((AF29*AV29*I29),2)*BA29),2) -> 1608.16 | T29: =ROUND(CU29*I29,2) -> 0 | U29: =CV29*I29 -> 121.83006 | V29: =CW29*I29 -> 0 | W29: =ROUND(CX29*I29,2) -> 0 | X29: =ROUND(CY29,2) -> 1487.35 | Y29: =ROUND(CZ29,2) -> 792.17 | AA29: 59499003 | AB29: =ROUND((AC29+AD29+AF29),6) -> 1618.8216 | AC29: =ROUND((((ES29*0)*1)),6) -> 0 | AD29: =ROUND((((((ET29*0.3)*1.1))-(((EU29*0.3)*1.1)))+AE29),6) -> 111.6456 | AE29: =ROUND((((EU29*0.3)*1.1)),6) -> 7.9893 | AF29: =ROUND((((EV29*0.3)*1.1)),6) -> 1507.176 | AG29: =ROUND((AP29),6) -> 0 | AH29: =(((EW29*0.3)*1.1)) -> 114.18 | AI29: =(((EX29*0.3)*1.1)) -> 0 | AJ29: =(AS29) -> 0 | AK29: 5864.52 | AL29: 959 | AM29: 338.32 | AN29: 24.21 | AO29: 4567.2 | AP29: 0 | AQ29: 346 | AR29: 0 | AS29: 0 | AT29: 92 | AU29: 49 | AV29: 1.067 | AW29: 1.028 | AZ29: 1 | BA29: 1 | BB29: 1 | BC29: 1 | BH29: 0 | BI29: 2 | BJ29: ТСН-2001.4. Доп. 1-42. Сб. 3, т. 32, поз. 1 | BM29: 64 | BN29: 59073636 | BO29: 4.3-32-1 | BP29: 1 | BQ29: 40 | BR29: 0 | BS29: 1 | BT29: 1 | BU29: 1 | BV29: 1 | BW29: 1 | BX29: 1 | BZ29: 92 | CA29: 49 | CE29: 30 | CF29: 0 | CG29: 0 | CM29: 0 | CN29: Поправка: Гл.12.Прил.8.п.8. 5_12.00.01.11.003 Наименование: При наличии усложненных условий производства работ (стесненность, сложность складирования и транспортной логистики, наличие в зоне производства работ действующего технологического оборудования или движения технологического транспорта и т.п.) для объектов, расположенных за пределами территории круговой магистральной системы улиц "Садовое кольцо" и за пределами Третьего транспортного кольца города Москвы пунктов "а" и "б", но в пределах Московской кольцевой автомобильной дороги | CO29: 0 | CP29: =(P29+Q29+S29) -> 1727.29 | CQ29: =ROUND((ROUND((AC29*AW29*1),2)*BC29),2) -> 0 | CR29: =(ROUND((ROUND(((((ET29*0.3)*1.1))*AV29*1),2)*BB29),2)+ROUND((ROUND(((AE29-(((EU29*0.3)*1.1)))*AV29*1),2)*BS29),2)) -> 119.13 | CS29: =ROUND((ROUND((AE29*AV29*1),2)*BS29),2) -> 8.52 | CT29: =ROUND((ROUND((AF29*AV29*1),2)*BA29),2) -> 1608.16 | CU29: =AG29 -> 0 | CV29: =(AH29*AV29) -> 121.83006 | CW29: =AI29 -> 0 | CX29: =AJ29 -> 0 | CY29: =(((S29+R29)*AT29)/100) -> 1487.3456 | CZ29: =(((S29+R29)*AU29)/100) -> 792.1732 | DB29: 1 | DD29: *0)*1 | DE29: *0,3)*1,1 | DF29: *0,3)*1,1 | DG29: *0,3)*1,1 | DI29: *0,3)*1,1 | DJ29: *0,3)*1,1 | DN29: 0 | DO29: 0 | DP29: 1 | DQ29: 1 | DU29: 1013 | DV29: 1 лифт | DW29: 1 лифт | DX29: 1 | EE29: 59073703 | EF29: 40 | EG29: Монтаж оборудования | EH29: 0 | EJ29: 2 | EK29: 64 | EL29: ТСН-2001.4-3. Подъемно-транспортное оборудование | EM29: ТСН-2001.4-3-1 | EO29: Поправка: Гл.12.Прил.8.п.8. 5_12.00.01.11.003 | EQ29: 0 | ER29: 5864.52 | ES29: 959 | ET29: 338.32 | EU29: 24.21 | EV29: 4567.2 | EW29: 346 | EX29: 0 | EY29: 0 | FQ29: 0 | FR29: 0 | FS29: 0 | FX29: 92 | FY29: 49 | GD29: 1 | GF29: 1437378821 | GG29: 2 | GH29: 1 | GI29: 2 | GJ29: 0 | GK29: 0 | GL29: =ROUND(IF(AND(BH29=3,BI29=3,FS29<>0),P29,0),2) -> 0 | GM29: =ROUND(O29+X29+Y29,2)+GX29 -> 4006.81 | GN29: =IF(OR(BI29=0,BI29=1),GM29-GX29,0) -> 0 | GO29: =IF(BI29=2,GM29-GX29,0) -> 4006.81 | GP29: =IF(BI29=4,GM29-GX29,0) -> 0 | GR29: 0 | GS29: 3 | GT29: 0 | GV29: =ROUND((GT29),6) -> 0 | GW29: 1 | GX29: =ROUND(HC29*I29,2) -> 0 | HA29: 0 | HB29: 0 | HC29: =GV29*GW29 -> 0 | HS29: 0 | IK29: 0
A30: 17 | B30: 1 | C30: =ROW(SmtRes!A4) -> 4 | D30: =ROW(EtalonRes!A4) -> 4 | E30: 1 | F30: 4.3-32-1 | G30: Лифт малогрузовой со скоростью движения кабины до 0,5 м/с, грузоподъемностью 100 кг, на 6 остановок, в глухой шахте, высота 21 м (схема управления релейно-контакторная)/ грузовой подъёмник | H30: 1 лифт | I30: 1 | J30: 0 | K30: 1 | O30: =ROUND(CP30,2) -> 90012.38 | P30: =ROUND((ROUND((AC30*AW30*I30),2)*BC30),2) -> 0 | Q30: =(ROUND((ROUND(((((ET30*0.3)*1.1))*AV30*I30),2)*BB30),2)+ROUND((ROUND(((AE30-(((EU30*0.3)*1.1)))*AV30*I30),2)*BS30),2)) -> 1579.66 | R30: =ROUND((ROUND((AE30*AV30*I30),2)*BS30),2) -> 468.51 | S30: =ROUND((ROUND((AF30*AV30*I30),2)*BA30),2) -> 88432.72 | T30: =ROUND(CU30*I30,2) -> 0 | U30: =CV30*I30 -> 121.83006 | V30: =CW30*I30 -> 0 | W30: =ROUND(CX30*I30,2) -> 0 | X30: =ROUND(CY30,2) -> 81789.13 | Y30: =ROUND(CZ30,2) -> 43561.6 | AA30: 59499000 | AB30: =ROUND((AC30+AD30+AF30),6) -> 1618.8216 | AC30: =ROUND((((ES30*0)*1)),6) -> 0 | AD30: =ROUND((((((ET30*0.3)*1.1))-(((EU30*0.3)*1.1)))+AE30),6) -> 111.6456 | AE30: =ROUND((((EU30*0.3)*1.1)),6) -> 7.9893 | AF30: =ROUND((((EV30*0.3)*1.1)),6) -> 1507.176 | AG30: =ROUND((AP30),6) -> 0 | AH30: =(((EW30*0.3)*1.1)) -> 114.18 | AI30: =(((EX30*0.3)*1.1)) -> 0 | AJ30: =(AS30) -> 0 | AK30: 5864.52 | AL30: 959 | AM30: 338.32 | AN30: 24.21 | AO30: 4567.2 | AP30: 0 | AQ30: 346 | AR30: 0 | AS30: 0 | AT30: 92 | AU30: 49 | AV30: 1.067 | AW30: 1.028 | AZ30: 1 | BA30: 54.99 | BB30: 13.26 | BC30: 9.89 | BH30: 0 | BI30: 2 | BJ30: ТСН-2001.4. Доп. 1-42. Сб. 3, т. 32, поз. 1 | BM30: 64 | BN30: 59073636 | BO30: 4.3-32-1 | BP30: 1 | BQ30: 40 | BR30: 0 | BS30: 54.99 | BT30: 1 | BU30: 1 | BV30: 1 | BW30: 1 | BX30: 1 | BZ30: 92 | CA30: 49 | CE30: 30 | CF30: 0 | CG30: 0 | CM30: 0 | CN30: Поправка: Гл.12.Прил.8.п.8. 5_12.00.01.11.003 Наименование: При наличии усложненных условий производства работ (стесненность, сложность складирования и транспортной логистики, наличие в зоне производства работ действующего технологического оборудования или движения технологического транспорта и т.п.) для объектов, расположенных за пределами территории круговой магистральной системы улиц "Садовое кольцо" и за пределами Третьего транспортного кольца города Москвы пунктов "а" и "б", но в пределах Московской кольцевой автомобильной дороги | CO30: 0 | CP30: =(P30+Q30+S30) -> 90012.38 | CQ30: =ROUND((ROUND((AC30*AW30*1),2)*BC30),2) -> 0 | CR30: =(ROUND((ROUND(((((ET30*0.3)*1.1))*AV30*1),2)*BB30),2)+ROUND((ROUND(((AE30-(((EU30*0.3)*1.1)))*AV30*1),2)*BS30),2)) -> 1579.66 | CS30: =ROUND((ROUND((AE30*AV30*1),2)*BS30),2) -> 468.51 | CT30: =ROUND((ROUND((AF30*AV30*1),2)*BA30),2) -> 88432.72 | CU30: =AG30 -> 0 | CV30: =(AH30*AV30) -> 121.83006 | CW30: =AI30 -> 0 | CX30: =AJ30 -> 0 | CY30: =(((S30+R30)*AT30)/100) -> 81789.132 | CZ30: =(((S30+R30)*AU30)/100) -> 43561.603 | DB30: 3 | DD30: *0)*1 | DE30: *0,3)*1,1 | DF30: *0,3)*1,1 | DG30: *0,3)*1,1 | DI30: *0,3)*1,1 | DJ30: *0,3)*1,1 | DN30: 0 | DO30: 0 | DP30: 1 | DQ30: 1 | DU30: 1013 | DV30: 1 лифт | DW30: 1 лифт | DX30: 1 | EE30: 59073703 | EF30: 40 | EG30: Монтаж оборудования | EH30: 0 | EJ30: 2 | EK30: 64 | EL30: ТСН-2001.4-3. Подъемно-транспортное оборудование | EM30: ТСН-2001.4-3-1 | EO30: Поправка: Гл.12.Прил.8.п.8. 5_12.00.01.11.003 | EQ30: 0 | ER30: 5864.52 | ES30: 959 | ET30: 338.32 | EU30: 24.21 | EV30: 4567.2 | EW30: 346 | EX30: 0 | EY30: 0 | FQ30: 0 | FR30: 0 | FS30: 0 | FX30: 92 | FY30: 49 | GD30: 1 | GF30: 1437378821 | GG30: 2 | GH30: 1 | GI30: 2 | GJ30: 0 | GK30: 0 | GL30: =ROUND(IF(AND(BH30=3,BI30=3,FS30<>0),P30,0),2) -> 0 | GM30: =ROUND(O30+X30+Y30,2)+GX30 -> 215363.11 | GN30: =IF(OR(BI30=0,BI30=1),GM30-GX30,0) -> 0 | GO30: =IF(BI30=2,GM30-GX30,0) -> 215363.11 | GP30: =IF(BI30=4,GM30-GX30,0) -> 0 | GR30: 0 | GS30: 3 | GT30: 0 | GV30: =ROUND((GT30),6) -> 0 | GW30: 1 | GX30: =ROUND(HC30*I30,2) -> 0 | HA30: 0 | HB30: 0 | HC30: =GV30*GW30 -> 0 | HS30: 0 | IK30: 0
A31: 17 | B31: 1 | C31: =ROW(SmtRes!A5) -> 5 | D31: =ROW(EtalonRes!A5) -> 5 | E31: 2 | F31: 4.3-32-3 | G31: За каждую остановку, более или менее указанных в характеристике лифта грузоподъемностью 100 кг в глухой шахте добавлять или уменьшать (схема управления релейно-контакторная)/ грузовой подъёмник | H31: 1 остановка | I31: =ROUND(2-6,9) -> -4 | J31: 0 | K31: =ROUND(2-6,9) -> -4 | O31: =ROUND(CP31,2) -> -467.35 | P31: =ROUND((ROUND((AC31*AW31*I31),2)*BC31),2) -> 0 | Q31: =(ROUND((ROUND(((((ET31*0.3)*1.1))*AV31*I31),2)*BB31),2)+ROUND((ROUND(((AE31-(((EU31*0.3)*1.1)))*AV31*I31),2)*BS31),2)) -> -49.04 | R31: =ROUND((ROUND((AE31*AV31*I31),2)*BS31),2) -> -3.68 | S31: =ROUND((ROUND((AF31*AV31*I31),2)*BA31),2) -> -418.31 | T31: =ROUND(CU31*I31,2) -> 0 | U31: =CV31*I31 -> -31.6899 | V31: =CW31*I31 -> 0 | W31: =ROUND(CX31*I31,2) -> 0 | X31: =ROUND(CY31,2) -> -388.23 | Y31: =ROUND(CZ31,2) -> -206.78 | AA31: 59499003 | AB31: =ROUND((AC31+AD31+AF31),6) -> 109.5006 | AC31: =ROUND((((ES31*0)*1)),6) -> 0 | AD31: =ROUND((((((ET31*0.3)*1.1))-(((EU31*0.3)*1.1)))+AE31),6) -> 11.4906 | AE31: =ROUND((((EU31*0.3)*1.1)),6) -> 0.8613 | AF31: =ROUND((((EV31*0.3)*1.1)),6) -> 98.01 | AG31: =ROUND((AP31),6) -> 0 | AH31: =(((EW31*0.3)*1.1)) -> 7.425 | AI31: =(((EX31*0.3)*1.1)) -> 0 | AJ31: =(AS31) -> 0 | AK31: 390.62 | AL31: 58.8 | AM31: 34.82 | AN31: 2.61 | AO31: 297 | AP31: 0 | AQ31: 22.5 | AR31: 0 | AS31: 0 | AT31: 92 | AU31: 49 | AV31: 1.067 | AW31: 1.028 | AZ31: 1 | BA31: 1 | BB31: 1 | BC31: 1 | BH31: 0 | BI31: 2 | BJ31: ТСН-2001.4. Доп. 1-42. Сб. 3, т. 32, поз. 3 | BM31: 64 | BN31: 59073636 | BO31: 4.3-32-3 | BP31: 1 | BQ31: 40 | BR31: 0 | BS31: 1 | BT31: 1 | BU31: 1 | BV31: 1 | BW31: 1 | BX31: 1 | BZ31: 92 | CA31: 49 | CE31: 30 | CF31: 0 | CG31: 0 | CM31: 0 | CN31: Поправка: Гл.12.Прил.8.п.8. 5_12.00.01.11.003 Наименование: При наличии усложненных условий производства работ (стесненность, сложность складирования и транспортной логистики, наличие в зоне производства работ действующего технологического оборудования или движения технологического транспорта и т.п.) для объектов, расположенных за пределами территории круговой магистральной системы улиц "Садовое кольцо" и за пределами Третьего транспортного кольца города Москвы пунктов "а" и "б", но в пределах Московской кольцевой автомобильной дороги | CO31: 0 | CP31: =(P31+Q31+S31) -> -467.35 | CQ31: =ROUND((ROUND((AC31*AW31*1),2)*BC31),2) -> 0 | CR31: =(ROUND((ROUND(((((ET31*0.3)*1.1))*AV31*1),2)*BB31),2)+ROUND((ROUND(((AE31-(((EU31*0.3)*1.1)))*AV31*1),2)*BS31),2)) -> 12.26 | CS31: =ROUND((ROUND((AE31*AV31*1),2)*BS31),2) -> 0.92 | CT31: =ROUND((ROUND((AF31*AV31*1),2)*BA31),2) -> 104.58 | CU31: =AG31 -> 0 | CV31: =(AH31*AV31) -> 7.922475 | CW31: =AI31 -> 0 | CX31: =AJ31 -> 0 | CY31: =(((S31+R31)*AT31)/100) -> -388.2308 | CZ31: =(((S31+R31)*AU31)/100) -> -206.7751 | DB31: 5 | DD31: *0)*1 | DE31: *0,3)*1,1 | DF31: *0,3)*1,1 | DG31: *0,3)*1,1 | DI31: *0,3)*1,1 | DJ31: *0,3)*1,1 | DN31: 0 | DO31: 0 | DP31: 1 | DQ31: 1 | DU31: 1013 | DV31: 1 остановка | DW31: 1 остановка | DX31: 1 | EE31: 59073703 | EF31: 40 | EG31: Монтаж оборудования | EH31: 0 | EJ31: 2 | EK31: 64 | EL31: ТСН-2001.4-3. Подъемно-транспортное оборудование | EM31: ТСН-2001.4-3-1 | EO31: Поправка: Гл.12.Прил.8.п.8. 5_12.00.01.11.003 | EQ31: 0 | ER31: 390.62 | ES31: 58.8 | ET31: 34.82 | EU31: 2.61 | EV31: 297 | EW31: 22.5 | EX31: 0 | EY31: 0 | FQ31: 0 | FR31: 0 | FS31: 0 | FX31: 92 | FY31: 49 | GD31: 1 | GF31: -1024034014 | GG31: 2 | GH31: 1 | GI31: 2 | GJ31: 0 | GK31: 0 | GL31: =ROUND(IF(AND(BH31=3,BI31=3,FS31<>0),P31,0),2) -> 0 | GM31: =ROUND(O31+X31+Y31,2)+GX31 -> -1062.36 | GN31: =IF(OR(BI31=0,BI31=1),GM31-GX31,0) -> 0 | GO31: =IF(BI31=2,GM31-GX31,0) -> -1062.36 | GP31: =IF(BI31=4,GM31-GX31,0) -> 0 | GR31: 0 | GS31: 3 | GT31: 0 | GV31: =ROUND((GT31),6) -> 0 | GW31: 1 | GX31: =ROUND(HC31*I31,2) -> 0 | HA31: 0 | HB31: 0 | HC31: =GV31*GW31 -> 0 | HS31: 0 | IK31: 0
A32: 17 | B32: 1 | C32: =ROW(SmtRes!A6) -> 6 | D32: =ROW(EtalonRes!A6) -> 6 | E32: 2 | F32: 4.3-32-3 | G32: За каждую остановку, более или менее указанных в характеристике лифта грузоподъемностью 100 кг в глухой шахте добавлять или уменьшать (схема управления релейно-контакторная)/ грузовой подъёмник | H32: 1 остановка | I32: =ROUND(2-6,9) -> -4 | J32: 0 | K32: =ROUND(2-6,9) -> -4 | O32: =ROUND(CP32,2) -> -23660.5 | P32: =ROUND((ROUND((AC32*AW32*I32),2)*BC32),2) -> 0 | Q32: =(ROUND((ROUND(((((ET32*0.3)*1.1))*AV32*I32),2)*BB32),2)+ROUND((ROUND(((AE32-(((EU32*0.3)*1.1)))*AV32*I32),2)*BS32),2)) -> -657.63 | R32: =ROUND((ROUND((AE32*AV32*I32),2)*BS32),2) -> -202.36 | S32: =ROUND((ROUND((AF32*AV32*I32),2)*BA32),2) -> -23002.87 | T32: =ROUND(CU32*I32,2) -> 0 | U32: =CV32*I32 -> -31.6899 | V32: =CW32*I32 -> 0 | W32: =ROUND(CX32*I32,2) -> 0 | X32: =ROUND(CY32,2) -> -21348.81 | Y32: =ROUND(CZ32,2) -> -11370.56 | AA32: 59499000 | AB32: =ROUND((AC32+AD32+AF32),6) -> 109.5006 | AC32: =ROUND((((ES32*0)*1)),6) -> 0 | AD32: =ROUND((((((ET32*0.3)*1.1))-(((EU32*0.3)*1.1)))+AE32),6) -> 11.4906 | AE32: =ROUND((((EU32*0.3)*1.1)),6) -> 0.8613 | AF32: =ROUND((((EV32*0.3)*1.1)),6) -> 98.01 | AG32: =ROUND((AP32),6) -> 0 | AH32: =(((EW32*0.3)*1.1)) -> 7.425 | AI32: =(((EX32*0.3)*1.1)) -> 0 | AJ32: =(AS32) -> 0 | AK32: 390.62 | AL32: 58.8 | AM32: 34.82 | AN32: 2.61 | AO32: 297 | AP32: 0 | AQ32: 22.5 | AR32: 0 | AS32: 0 | AT32: 92 | AU32: 49 | AV32: 1.067 | AW32: 1.028 | AZ32: 1 | BA32: 54.99 | BB32: 13.41 | BC32: 9.89 | BH32: 0 | BI32: 2 | BJ32: ТСН-2001.4. Доп. 1-42. Сб. 3, т. 32, поз. 3 | BM32: 64 | BN32: 59073636 | BO32: 4.3-32-3 | BP32: 1 | BQ32: 40 | BR32: 0 | BS32: 54.99 | BT32: 1 | BU32: 1 | BV32: 1 | BW32: 1 | BX32: 1 | BZ32: 92 | CA32: 49 | CE32: 30 | CF32: 0 | CG32: 0 | CM32: 0 | CN32: Поправка: Гл.12.Прил.8.п.8. 5_12.00.01.11.003 Наименование: При наличии усложненных условий производства работ (стесненность, сложность складирования и транспортной логистики, наличие в зоне производства работ действующего технологического оборудования или движения технологического транспорта и т.п.) для объектов, расположенных за пределами территории круговой магистральной системы улиц "Садовое кольцо" и за пределами Третьего транспортного кольца города Москвы пунктов "а" и "б", но в пределах Московской кольцевой автомобильной дороги | CO32: 0 | CP32: =(P32+Q32+S32) -> -23660.5 | CQ32: =ROUND((ROUND((AC32*AW32*1),2)*BC32),2) -> 0 | CR32: =(ROUND((ROUND(((((ET32*0.3)*1.1))*AV32*1),2)*BB32),2)+ROUND((ROUND(((AE32-(((EU32*0.3)*1.1)))*AV32*1),2)*BS32),2)) -> 164.41 | CS32: =ROUND((ROUND((AE32*AV32*1),2)*BS32),2) -> 50.59 | CT32: =ROUND((ROUND((AF32*AV32*1),2)*BA32),2) -> 5750.85 | CU32: =AG32 -> 0 | CV32: =(AH32*AV32) -> 7.922475 | CW32: =AI32 -> 0 | CX32: =AJ32 -> 0 | CY32: =(((S32+R32)*AT32)/100) -> -21348.812 | CZ32: =(((S32+R32)*AU32)/100) -> -11370.563 | DB32: 7 | DD32: *0)*1 | DE32: *0,3)*1,1 | DF32: *0,3)*1,1 | DG32: *0,3)*1,1 | DI32: *0,3)*1,1 | DJ32: *0,3)*1,1 | DN32: 0 | DO32: 0 | DP32: 1 | DQ32: 1 | DU32: 1013 | DV32: 1 остановка | DW32: 1 остановка | DX32: 1 | EE32: 59073703 | EF32: 40 | EG32: Монтаж оборудования | EH32: 0 | EJ32: 2 | EK32: 64 | EL32: ТСН-2001.4-3. Подъемно-транспортное оборудование | EM32: ТСН-2001.4-3-1 | EO32: Поправка: Гл.12.Прил.8.п.8. 5_12.00.01.11.003 | EQ32: 0 | ER32: 390.62 | ES32: 58.8 | ET32: 34.82 | EU32: 2.61 | EV32: 297 | EW32: 22.5 | EX32: 0 | EY32: 0 | FQ32: 0 | FR32: 0 | FS32: 0 | FX32: 92 | FY32: 49 | GD32: 1 | GF32: -1024034014 | GG32: 2 | GH32: 1 | GI32: 2 | GJ32: 0 | GK32: 0 | GL32: =ROUND(IF(AND(BH32=3,BI32=3,FS32<>0),P32,0),2) -> 0 | GM32: =ROUND(O32+X32+Y32,2)+GX32 -> -56379.87 | GN32: =IF(OR(BI32=0,BI32=1),GM32-GX32,0) -> 0 | GO32: =IF(BI32=2,GM32-GX32,0) -> -56379.87 | GP32: =IF(BI32=4,GM32-GX32,0) -> 0 | GR32: 0 | GS32: 3 | GT32: 0 | GV32: =ROUND((GT32),6) -> 0 | GW32: 1 | GX32: =ROUND(HC32*I32,2) -> 0 | HA32: 0 | HB32: 0 | HC32: =GV32*GW32 -> 0 | HS32: 0 | IK32: 0
A33: 17 | B33: 1 | C33: =ROW(SmtRes!A7) -> 7 | D33: =ROW(EtalonRes!A7) -> 7 | E33: 3 | F33: 4.3-32-4 | G33: За каждый 1 м высоты шахты, более или менее указанных в характеристике малогрузового лифта грузоподъемностью 100 кг в глухой шахте добавлять или уменьшать (схема управления релейно-контакторная)/ грузовой подъёмник | H33: 1 М | I33: =ROUND((3.15+2.93-21),9) -> -14.92 | J33: 0 | K33: =ROUND((3.15+2.93-21),9) -> -14.92 | O33: =ROUND(CP33,2) -> -436.88 | P33: =ROUND((ROUND((AC33*AW33*I33),2)*BC33),2) -> 0 | Q33: =(ROUND((ROUND(((((ET33*0.3)*1.1))*AV33*I33),2)*BB33),2)+ROUND((ROUND(((AE33-(((EU33*0.3)*1.1)))*AV33*I33),2)*BS33),2)) -> 0 | R33: =ROUND((ROUND((AE33*AV33*I33),2)*BS33),2) -> 0 | S33: =ROUND((ROUND((AF33*AV33*I33),2)*BA33),2) -> -436.88 | T33: =ROUND(CU33*I33,2) -> 0 | U33: =CV33*I33 -> -33.096932 | V33: =CW33*I33 -> 0 | W33: =ROUND(CX33*I33,2) -> 0 | X33: =ROUND(CY33,2) -> -401.93 | Y33: =ROUND(CZ33,2) -> -214.07 | AA33: 59499003 | AB33: =ROUND((AC33+AD33+AF33),6) -> 27.4428 | AC33: =ROUND((((ES33*0)*1)),6) -> 0 | AD33: =ROUND((((((ET33*0.3)*1.1))-(((EU33*0.3)*1.1)))+AE33),6) -> 0 | AE33: =ROUND((((EU33*0.3)*1.1)),6) -> 0 | AF33: =ROUND((((EV33*0.3)*1.1)),6) -> 27.4428 | AG33: =ROUND((AP33),6) -> 0 | AH33: =(((EW33*0.3)*1.1)) -> 2.079 | AI33: =(((EX33*0.3)*1.1)) -> 0 | AJ33: =(AS33) -> 0 | AK33: 83.79 | AL33: 0.63 | AM33: 0 | AN33: 0 | AO33: 83.16 | AP33: 0 | AQ33: 6.3 | AR33: 0 | AS33: 0 | AT33: 92 | AU33: 49 | AV33: 1.067 | AW33: 1.028 | AZ33: 1 | BA33: 1 | BB33: 1 | BC33: 1 | BH33: 0 | BI33: 2 | BJ33: ТСН-2001.4 Доп. 68, Сб. 3, т. 32, поз. 4 | BM33: 64 | BN33: 59073636 | BO33: 4.3-32-4 | BP33: 1 | BQ33: 40 | BR33: 0 | BS33: 1 | BT33: 1 | BU33: 1 | BV33: 1 | BW33: 1 | BX33: 1 | BZ33: 92 | CA33: 49 | CE33: 30 | CF33: 0 | CG33: 0 | CM33: 0 | CN33: Поправка: Гл.12.Прил.8.п.8. 5_12.00.01.11.003 Наименование: При наличии усложненных условий производства работ (стесненность, сложность складирования и транспортной логистики, наличие в зоне производства работ действующего технологического оборудования или движения технологического транспорта и т.п.) для объектов, расположенных за пределами территории круговой магистральной системы улиц "Садовое кольцо" и за пределами Третьего транспортного кольца города Москвы пунктов "а" и "б", но в пределах Московской кольцевой автомобильной дороги | CO33: 0 | CP33: =(P33+Q33+S33) -> -436.88 | CQ33: =ROUND((ROUND((AC33*AW33*1),2)*BC33),2) -> 0 | CR33: =(ROUND((ROUND(((((ET33*0.3)*1.1))*AV33*1),2)*BB33),2)+ROUND((ROUND(((AE33-(((EU33*0.3)*1.1)))*AV33*1),2)*BS33),2)) -> 0 | CS33: =ROUND((ROUND((AE33*AV33*1),2)*BS33),2) -> 0 | CT33: =ROUND((ROUND((AF33*AV33*1),2)*BA33),2) -> 29.28 | CU33: =AG33 -> 0 | CV33: =(AH33*AV33) -> 2.218293 | CW33: =AI33 -> 0 | CX33: =AJ33 -> 0 | CY33: =(((S33+R33)*AT33)/100) -> -401.9296 | CZ33: =(((S33+R33)*AU33)/100) -> -214.0712 | DB33: 9 | DD33: *0)*1 | DE33: *0,3)*1,1 | DF33: *0,3)*1,1 | DG33: *0,3)*1,1 | DI33: *0,3)*1,1 | DJ33: *0,3)*1,1 | DN33: 0 | DO33: 0 | DP33: 1 | DQ33: 1 | DU33: 1013 | DV33: 1 М | DW33: 1 М | DX33: 1 | EE33: 59073703 | EF33: 40 | EG33: Монтаж оборудования | EH33: 0 | EJ33: 2 | EK33: 64 | EL33: ТСН-2001.4-3. Подъемно-транспортное оборудование | EM33: ТСН-2001.4-3-1 | EO33: Поправка: Гл.12.Прил.8.п.8. 5_12.00.01.11.003 | EQ33: 0 | ER33: 83.79 | ES33: 0.63 | ET33: 0 | EU33: 0 | EV33: 83.16 | EW33: 6.3 | EX33: 0 | EY33: 0 | FQ33: 0 | FR33: 0 | FS33: 0 | FX33: 92 | FY33: 49 | GD33: 1 | GF33: -1760320444 | GG33: 2 | GH33: 1 | GI33: 2 | GJ33: 0 | GK33: 0 | GL33: =ROUND(IF(AND(BH33=3,BI33=3,FS33<>0),P33,0),2) -> 0 | GM33: =ROUND(O33+X33+Y33,2)+GX33 -> -1052.88 | GN33: =IF(OR(BI33=0,BI33=1),GM33-GX33,0) -> 0 | GO33: =IF(BI33=2,GM33-GX33,0) -> -1052.88 | GP33: =IF(BI33=4,GM33-GX33,0) -> 0 | GR33: 0 | GS33: 3 | GT33: 0 | GV33: =ROUND((GT33),6) -> 0 | GW33: 1 | GX33: =ROUND(HC33*I33,2) -> 0 | HA33: 0 | HB33: 0 | HC33: =GV33*GW33 -> 0 | HS33: 0 | IK33: 0
A34: 17 | B34: 1 | C34: =ROW(SmtRes!A8) -> 8 | D34: =ROW(EtalonRes!A8) -> 8 | E34: 3 | F34: 4.3-32-4 | G34: За каждый 1 м высоты шахты, более или менее указанных в характеристике малогрузового лифта грузоподъемностью 100 кг в глухой шахте добавлять или уменьшать (схема управления релейно-контакторная)/ грузовой подъёмник | H34: 1 М | I34: =ROUND((3.15+2.93-21),9) -> -14.92 | J34: 0 | K34: =ROUND((3.15+2.93-21),9) -> -14.92 | O34: =ROUND(CP34,2) -> -24024.03 | P34: =ROUND((ROUND((AC34*AW34*I34),2)*BC34),2) -> 0 | Q34: =(ROUND((ROUND(((((ET34*0.3)*1.1))*AV34*I34),2)*BB34),2)+ROUND((ROUND(((AE34-(((EU34*0.3)*1.1)))*AV34*I34),2)*BS34),2)) -> 0 | R34: =ROUND((ROUND((AE34*AV34*I34),2)*BS34),2) -> 0 | S34: =ROUND((ROUND((AF34*AV34*I34),2)*BA34),2) -> -24024.03 | T34: =ROUND(CU34*I34,2) -> 0 | U34: =CV34*I34 -> -33.096932 | V34: =CW34*I34 -> 0 | W34: =ROUND(CX34*I34,2) -> 0 | X34: =ROUND(CY34,2) -> -22102.11 | Y34: =ROUND(CZ34,2) -> -11771.77 | AA34: 59499000 | AB34: =ROUND((AC34+AD34+AF34),6) -> 27.4428 | AC34: =ROUND((((ES34*0)*1)),6) -> 0 | AD34: =ROUND((((((ET34*0.3)*1.1))-(((EU34*0.3)*1.1)))+AE34),6) -> 0 | AE34: =ROUND((((EU34*0.3)*1.1)),6) -> 0 | AF34: =ROUND((((EV34*0.3)*1.1)),6) -> 27.4428 | AG34: =ROUND((AP34),6) -> 0 | AH34: =(((EW34*0.3)*1.1)) -> 2.079 | AI34: =(((EX34*0.3)*1.1)) -> 0 | AJ34: =(AS34) -> 0 | AK34: 83.79 | AL34: 0.63 | AM34: 0 | AN34: 0 | AO34: 83.16 | AP34: 0 | AQ34: 6.3 | AR34: 0 | AS34: 0 | AT34: 92 | AU34: 49 | AV34: 1.067 | AW34: 1.028 | AZ34: 1 | BA34: 54.99 | BB34: 1 | BC34: 9.89 | BH34: 0 | BI34: 2 | BJ34: ТСН-2001.4 Доп. 68, Сб. 3, т. 32, поз. 4 | BM34: 64 | BN34: 59073636 | BO34: 4.3-32-4 | BP34: 1 | BQ34: 40 | BR34: 0 | BS34: 54.99 | BT34: 1 | BU34: 1 | BV34: 1 | BW34: 1 | BX34: 1 | BZ34: 92 | CA34: 49 | CE34: 30 | CF34: 0 | CG34: 0 | CM34: 0 | CN34: Поправка: Гл.12.Прил.8.п.8. 5_12.00.01.11.003 Наименование: При наличии усложненных условий производства работ (стесненность, сложность складирования и транспортной логистики, наличие в зоне производства работ действующего технологического оборудования или движения технологического транспорта и т.п.) для объектов, расположенных за пределами территории круговой магистральной системы улиц "Садовое кольцо" и за пределами Третьего транспортного кольца города Москвы пунктов "а" и "б", но в пределах Московской кольцевой автомобильной дороги | CO34: 0 | CP34: =(P34+Q34+S34) -> -24024.03 | CQ34: =ROUND((ROUND((AC34*AW34*1),2)*BC34),2) -> 0 | CR34: =(ROUND((ROUND(((((ET34*0.3)*1.1))*AV34*1),2)*BB34),2)+ROUND((ROUND(((AE34-(((EU34*0.3)*1.1)))*AV34*1),2)*BS34),2)) -> 0 | CS34: =ROUND((ROUND((AE34*AV34*1),2)*BS34),2) -> 0 | CT34: =ROUND((ROUND((AF34*AV34*1),2)*BA34),2) -> 1610.11 | CU34: =AG34 -> 0 | CV34: =(AH34*AV34) -> 2.218293 | CW34: =AI34 -> 0 | CX34: =AJ34 -> 0 | CY34: =(((S34+R34)*AT34)/100) -> -22102.108 | CZ34: =(((S34+R34)*AU34)/100) -> -11771.775 | DB34: 11 | DD34: *0)*1 | DE34: *0,3)*1,1 | DF34: *0,3)*1,1 | DG34: *0,3)*1,1 | DI34: *0,3)*1,1 | DJ34: *0,3)*1,1 | DN34: 0 | DO34: 0 | DP34: 1 | DQ34: 1 | DU34: 1013 | DV34: 1 М | DW34: 1 М | DX34: 1 | EE34: 59073703 | EF34: 40 | EG34: Монтаж оборудования | EH34: 0 | EJ34: 2 | EK34: 64 | EL34: ТСН-2001.4-3. Подъемно-транспортное оборудование | EM34: ТСН-2001.4-3-1 | EO34: Поправка: Гл.12.Прил.8.п.8. 5_12.00.01.11.003 | EQ34: 0 | ER34: 83.79 | ES34: 0.63 | ET34: 0 | EU34: 0 | EV34: 83.16 | EW34: 6.3 | EX34: 0 | EY34: 0 | FQ34: 0 | FR34: 0 | FS34: 0 | FX34: 92 | FY34: 49 | GD34: 1 | GF34: -1760320444 | GG34: 2 | GH34: 1 | GI34: 2 | GJ34: 0 | GK34: 0 | GL34: =ROUND(IF(AND(BH34=3,BI34=3,FS34<>0),P34,0),2) -> 0 | GM34: =ROUND(O34+X34+Y34,2)+GX34 -> -57897.91 | GN34: =IF(OR(BI34=0,BI34=1),GM34-GX34,0) -> 0 | GO34: =IF(BI34=2,GM34-GX34,0) -> -57897.91 | GP34: =IF(BI34=4,GM34-GX34,0) -> 0 | GR34: 0 | GS34: 3 | GT34: 0 | GV34: =ROUND((GT34),6) -> 0 | GW34: 1 | GX34: =ROUND(HC34*I34,2) -> 0 | HA34: 0 | HB34: 0 | HC34: =GV34*GW34 -> 0 | HS34: 0 | IK34: 0
A35: 19 | B35: 1 | G35: Монтажные работы | AA35: 1 | IK35: 0
A36: 17 | B36: 1 | C36: =ROW(SmtRes!A10) -> 10 | D36: =ROW(EtalonRes!A10) -> 10 | E36: 4 | F36: 4.3-34-1 | G36: Лифт малогрузовой со скоростью движения кабины до 0,5 м/с, грузоподъемностью 100 кг, на 6 остановок, в глухой шахте, высота 21 м (схема управления микроэлектронная и микропроцессорная)/ грузовой подъёмник | H36: 1 лифт | I36: 1 | J36: 0 | K36: 1 | O36: =ROUND(CP36,2) -> 7052.99 | P36: =ROUND((ROUND((AC36*AW36*I36),2)*BC36),2) -> 985.85 | Q36: =(ROUND((ROUND((((ET36*1.1))*AV36*I36),2)*BB36),2)+ROUND((ROUND(((AE36-((EU36*1.1)))*AV36*I36),2)*BS36),2)) -> 397.09 | R36: =ROUND((ROUND((AE36*AV36*I36),2)*BS36),2) -> 28.42 | S36: =ROUND((ROUND((AF36*AV36*I36),2)*BA36),2) -> 5670.05 | T36: =ROUND(CU36*I36,2) -> 0 | U36: =CV36*I36 -> 417.8372 | V36: =CW36*I36 -> 0 | W36: =ROUND(CX36*I36,2) -> 0 | X36: =ROUND(CY36,2) -> 5242.59 | Y36: =ROUND(CZ36,2) -> 2792.25 | AA36: 59499003 | AB36: =ROUND((AC36+AD36+AF36),6) -> 6645.164 | AC36: =ROUND(((ES36*1)),6) -> 959 | AD36: =ROUND(((((ET36*1.1))-((EU36*1.1)))+AE36),6) -> 372.152 | AE36: =ROUND(((EU36*1.1)),6) -> 26.631 | AF36: =ROUND(((EV36*1.1)),6) -> 5314.012 | AG36: =ROUND((AP36),6) -> 0 | AH36: =((EW36*1.1)) -> 391.6 | AI36: =((EX36*1.1)) -> 0 | AJ36: =(AS36) -> 0 | AK36: 6128.24 | AL36: 959 | AM36: 338.32 | AN36: 24.21 | AO36: 4830.92 | AP36: 0 | AQ36: 356 | AR36: 0 | AS36: 0 | AT36: 92 | AU36: 49 | AV36: 1.067 | AW36: 1.028 | AZ36: 1 | BA36: 1 | BB36: 1 | BC36: 1 | BH36: 0 | BI36: 2 | BJ36: ТСН-2001.4. Доп. 1-42. Сб. 3, т. 34, поз. 1 | BM36: 64 | BN36: 59073636 | BO36: 4.3-34-1 | BP36: 1 | BQ36: 40 | BR36: 0 | BS36: 1 | BT36: 1 | BU36: 1 | BV36: 1 | BW36: 1 | BX36: 1 | BZ36: 92 | CA36: 49 | CE36: 30 | CF36: 0 | CG36: 0 | CM36: 0 | CN36: Поправка: Гл.12.Прил.8.п.8. 5_12.00.01.11.003 Наименование: При наличии усложненных условий производства работ (стесненность, сложность складирования и транспортной логистики, наличие в зоне производства работ действующего технологического оборудования или движения технологического транспорта и т.п.) для объектов, расположенных за пределами территории круговой магистральной системы улиц "Садовое кольцо" и за пределами Третьего транспортного кольца города Москвы пунктов "а" и "б", но в пределах Московской кольцевой автомобильной дороги | CO36: 0 | CP36: =(P36+Q36+S36) -> 7052.99 | CQ36: =ROUND((ROUND((AC36*AW36*1),2)*BC36),2) -> 985.85 | CR36: =(ROUND((ROUND((((ET36*1.1))*AV36*1),2)*BB36),2)+ROUND((ROUND(((AE36-((EU36*1.1)))*AV36*1),2)*BS36),2)) -> 397.09 | CS36: =ROUND((ROUND((AE36*AV36*1),2)*BS36),2) -> 28.42 | CT36: =ROUND((ROUND((AF36*AV36*1),2)*BA36),2) -> 5670.05 | CU36: =AG36 -> 0 | CV36: =(AH36*AV36) -> 417.8372 | CW36: =AI36 -> 0 | CX36: =AJ36 -> 0 | CY36: =(((S36+R36)*AT36)/100) -> 5242.5924 | CZ36: =(((S36+R36)*AU36)/100) -> 2792.2503 | DB36: 13 | DD36: *1 | DE36: *1,1 | DF36: *1,1 | DG36: *1,1 | DI36: *1,1 | DJ36: *1,1 | DN36: 0 | DO36: 0 | DP36: 1 | DQ36: 1 | DU36: 1013 | DV36: 1 лифт | DW36: 1 лифт | DX36: 1 | EE36: 59073703 | EF36: 40 | EG36: Монтаж оборудования | EH36: 0 | EJ36: 2 | EK36: 64 | EL36: ТСН-2001.4-3. Подъемно-транспортное оборудование | EM36: ТСН-2001.4-3-1 | EO36: Поправка: Гл.12.Прил.8.п.8. 5_12.00.01.11.003 | EQ36: 0 | ER36: 6128.24 | ES36: 959 | ET36: 338.32 | EU36: 24.21 | EV36: 4830.92 | EW36: 356 | EX36: 0 | EY36: 0 | FQ36: 0 | FR36: 0 | FS36: 0 | FX36: 92 | FY36: 49 | GD36: 1 | GF36: 1940847450 | GG36: 2 | GH36: 1 | GI36: 2 | GJ36: 0 | GK36: 0 | GL36: =ROUND(IF(AND(BH36=3,BI36=3,FS36<>0),P36,0),2) -> 0 | GM36: =ROUND(O36+X36+Y36,2)+GX36 -> 15087.83 | GN36: =IF(OR(BI36=0,BI36=1),GM36-GX36,0) -> 0 | GO36: =IF(BI36=2,GM36-GX36,0) -> 15087.83 | GP36: =IF(BI36=4,GM36-GX36,0) -> 0 | GR36: 0 | GS36: 3 | GT36: 0 | GV36: =ROUND((GT36),6) -> 0 | GW36: 1 | GX36: =ROUND(HC36*I36,2) -> 0 | HA36: 0 | HB36: 0 | HC36: =GV36*GW36 -> 0 | HS36: 0 | IK36: 0
A37: 17 | B37: 1 | C37: =ROW(SmtRes!A12) -> 12 | D37: =ROW(EtalonRes!A12) -> 12 | E37: 4 | F37: 4.3-34-1 | G37: Лифт малогрузовой со скоростью движения кабины до 0,5 м/с, грузоподъемностью 100 кг, на 6 остановок, в глухой шахте, высота 21 м (схема управления микроэлектронная и микропроцессорная)/ грузовой подъёмник | H37: 1 лифт | I37: 1 | J37: 0 | K37: 1 | O37: =ROUND(CP37,2) -> 326811.52 | P37: =ROUND((ROUND((AC37*AW37*I37),2)*BC37),2) -> 9750.06 | Q37: =(ROUND((ROUND((((ET37*1.1))*AV37*I37),2)*BB37),2)+ROUND((ROUND(((AE37-((EU37*1.1)))*AV37*I37),2)*BS37),2)) -> 5265.41 | R37: =ROUND((ROUND((AE37*AV37*I37),2)*BS37),2) -> 1562.82 | S37: =ROUND((ROUND((AF37*AV37*I37),2)*BA37),2) -> 311796.05 | T37: =ROUND(CU37*I37,2) -> 0 | U37: =CV37*I37 -> 417.8372 | V37: =CW37*I37 -> 0 | W37: =ROUND(CX37*I37,2) -> 0 | X37: =ROUND(CY37,2) -> 288290.16 | Y37: =ROUND(CZ37,2) -> 153545.85 | AA37: 59499000 | AB37: =ROUND((AC37+AD37+AF37),6) -> 6645.164 | AC37: =ROUND(((ES37*1)),6) -> 959 | AD37: =ROUND(((((ET37*1.1))-((EU37*1.1)))+AE37),6) -> 372.152 | AE37: =ROUND(((EU37*1.1)),6) -> 26.631 | AF37: =ROUND(((EV37*1.1)),6) -> 5314.012 | AG37: =ROUND((AP37),6) -> 0 | AH37: =((EW37*1.1)) -> 391.6 | AI37: =((EX37*1.1)) -> 0 | AJ37: =(AS37) -> 0 | AK37: 6128.24 | AL37: 959 | AM37: 338.32 | AN37: 24.21 | AO37: 4830.92 | AP37: 0 | AQ37: 356 | AR37: 0 | AS37: 0 | AT37: 92 | AU37: 49 | AV37: 1.067 | AW37: 1.028 | AZ37: 1 | BA37: 54.99 | BB37: 13.26 | BC37: 9.89 | BH37: 0 | BI37: 2 | BJ37: ТСН-2001.4. Доп. 1-42. Сб. 3, т. 34, поз. 1 | BM37: 64 | BN37: 59073636 | BO37: 4.3-34-1 | BP37: 1 | BQ37: 40 | BR37: 0 | BS37: 54.99 | BT37: 1 | BU37: 1 | BV37: 1 | BW37: 1 | BX37: 1 | BZ37: 92 | CA37: 49 | CE37: 30 | CF37: 0 | CG37: 0 | CM37: 0 | CN37: Поправка: Гл.12.Прил.8.п.8. 5_12.00.01.11.003 Наименование: При наличии усложненных условий производства работ (стесненность, сложность складирования и транспортной логистики, наличие в зоне производства работ действующего технологического оборудования или движения технологического транспорта и т.п.) для объектов, расположенных за пределами территории круговой магистральной системы улиц "Садовое кольцо" и за пределами Третьего транспортного кольца города Москвы пунктов "а" и "б", но в пределах Московской кольцевой автомобильной дороги | CO37: 0 | CP37: =(P37+Q37+S37) -> 326811.52 | CQ37: =ROUND((ROUND((AC37*AW37*1),2)*BC37),2) -> 9750.06 | CR37: =(ROUND((ROUND((((ET37*1.1))*AV37*1),2)*BB37),2)+ROUND((ROUND(((AE37-((EU37*1.1)))*AV37*1),2)*BS37),2)) -> 5265.41 | CS37: =ROUND((ROUND((AE37*AV37*1),2)*BS37),2) -> 1562.82 | CT37: =ROUND((ROUND((AF37*AV37*1),2)*BA37),2) -> 311796.05 | CU37: =AG37 -> 0 | CV37: =(AH37*AV37) -> 417.8372 | CW37: =AI37 -> 0 | CX37: =AJ37 -> 0 | CY37: =(((S37+R37)*AT37)/100) -> 288290.16 | CZ37: =(((S37+R37)*AU37)/100) -> 153545.85 | DB37: 14 | DD37: *1 | DE37: *1,1 | DF37: *1,1 | DG37: *1,1 | DI37: *1,1 | DJ37: *1,1 | DN37: 0 | DO37: 0 | DP37: 1 | DQ37: 1 | DU37: 1013 | DV37: 1 лифт | DW37: 1 лифт | DX37: 1 | EE37: 59073703 | EF37: 40 | EG37: Монтаж оборудования | EH37: 0 | EJ37: 2 | EK37: 64 | EL37: ТСН-2001.4-3. Подъемно-транспортное оборудование | EM37: ТСН-2001.4-3-1 | EO37: Поправка: Гл.12.Прил.8.п.8. 5_12.00.01.11.003 | EQ37: 0 | ER37: 6128.24 | ES37: 959 | ET37: 338.32 | EU37: 24.21 | EV37: 4830.92 | EW37: 356 | EX37: 0 | EY37: 0 | FQ37: 0 | FR37: 0 | FS37: 0 | FX37: 92 | FY37: 49 | GD37: 1 | GF37: 1940847450 | GG37: 2 | GH37: 1 | GI37: 2 | GJ37: 0 | GK37: 0 | GL37: =ROUND(IF(AND(BH37=3,BI37=3,FS37<>0),P37,0),2) -> 0 | GM37: =ROUND(O37+X37+Y37,2)+GX37 -> 768647.53 | GN37: =IF(OR(BI37=0,BI37=1),GM37-GX37,0) -> 0 | GO37: =IF(BI37=2,GM37-GX37,0) -> 768647.53 | GP37: =IF(BI37=4,GM37-GX37,0) -> 0 | GR37: 0 | GS37: 3 | GT37: 0 | GV37: =ROUND((GT37),6) -> 0 | GW37: 1 | GX37: =ROUND(HC37*I37,2) -> 0 | HA37: 0 | HB37: 0 | HC37: =GV37*GW37 -> 0 | HS37: 0 | IK37: 0
A38: 17 | B38: 1 | C38: =ROW(SmtRes!A13) -> 13 | D38: =ROW(EtalonRes!A13) -> 13 | E38: 5 | F38: 4.3-34-3 | G38: За каждую остановку, более или менее указанных в характеристике лифта грузоподъемностью 100 кг в глухой шахте добавлять или уменьшать (схема управления микроэлектронная и микропроцессорная)/ грузовой подъёмник | H38: 1 остановка | I38: =ROUND(2-6,9) -> -4 | J38: 0 | K38: =ROUND(2-6,9) -> -4 | O38: =ROUND(CP38,2) -> -1883.28 | P38: =ROUND((ROUND((AC38*AW38*I38),2)*BC38),2) -> -241.79 | Q38: =(ROUND((ROUND((((ET38*1.1))*AV38*I38),2)*BB38),2)+ROUND((ROUND(((AE38-((EU38*1.1)))*AV38*I38),2)*BS38),2)) -> -163.47 | R38: =ROUND((ROUND((AE38*AV38*I38),2)*BS38),2) -> -12.25 | S38: =ROUND((ROUND((AF38*AV38*I38),2)*BA38),2) -> -1478.02 | T38: =ROUND(CU38*I38,2) -> 0 | U38: =CV38*I38 -> -108.91936 | V38: =CW38*I38 -> 0 | W38: =ROUND(CX38*I38,2) -> 0 | X38: =ROUND(CY38,2) -> -1371.05 | Y38: =ROUND(CZ38,2) -> -730.23 | AA38: 59499003 | AB38: =ROUND((AC38+AD38+AF38),6) -> 443.404 | AC38: =ROUND(((ES38*1)),6) -> 58.8 | AD38: =ROUND(((((ET38*1.1))-((EU38*1.1)))+AE38),6) -> 38.302 | AE38: =ROUND(((EU38*1.1)),6) -> 2.871 | AF38: =ROUND(((EV38*1.1)),6) -> 346.302 | AG38: =ROUND((AP38),6) -> 0 | AH38: =((EW38*1.1)) -> 25.52 | AI38: =((EX38*1.1)) -> 0 | AJ38: =(AS38) -> 0 | AK38: 408.44 | AL38: 58.8 | AM38: 34.82 | AN38: 2.61 | AO38: 314.82 | AP38: 0 | AQ38: 23.2 | AR38: 0 | AS38: 0 | AT38: 92 | AU38: 49 | AV38: 1.067 | AW38: 1.028 | AZ38: 1 | BA38: 1 | BB38: 1 | BC38: 1 | BH38: 0 | BI38: 2 | BJ38: ТСН-2001.4. Доп. 1-42. Сб. 3, т. 34, поз. 3 | BM38: 64 | BN38: 59073636 | BO38: 4.3-34-3 | BP38: 1 | BQ38: 40 | BR38: 0 | BS38: 1 | BT38: 1 | BU38: 1 | BV38: 1 | BW38: 1 | BX38: 1 | BZ38: 92 | CA38: 49 | CE38: 30 | CF38: 0 | CG38: 0 | CM38: 0 | CN38: Поправка: Гл.12.Прил.8.п.8. 5_12.00.01.11.003 Наименование: При наличии усложненных условий производства работ (стесненность, сложность складирования и транспортной логистики, наличие в зоне производства работ действующего технологического оборудования или движения технологического транспорта и т.п.) для объектов, расположенных за пределами территории круговой магистральной системы улиц "Садовое кольцо" и за пределами Третьего транспортного кольца города Москвы пунктов "а" и "б", но в пределах Московской кольцевой автомобильной дороги | CO38: 0 | CP38: =(P38+Q38+S38) -> -1883.28 | CQ38: =ROUND((ROUND((AC38*AW38*1),2)*BC38),2) -> 60.45 | CR38: =(ROUND((ROUND((((ET38*1.1))*AV38*1),2)*BB38),2)+ROUND((ROUND(((AE38-((EU38*1.1)))*AV38*1),2)*BS38),2)) -> 40.87 | CS38: =ROUND((ROUND((AE38*AV38*1),2)*BS38),2) -> 3.06 | CT38: =ROUND((ROUND((AF38*AV38*1),2)*BA38),2) -> 369.5 | CU38: =AG38 -> 0 | CV38: =(AH38*AV38) -> 27.22984 | CW38: =AI38 -> 0 | CX38: =AJ38 -> 0 | CY38: =(((S38+R38)*AT38)/100) -> -1371.0484 | CZ38: =(((S38+R38)*AU38)/100) -> -730.2323 | DB38: 15 | DD38: *1 | DE38: *1,1 | DF38: *1,1 | DG38: *1,1 | DI38: *1,1 | DJ38: *1,1 | DN38: 0 | DO38: 0 | DP38: 1 | DQ38: 1 | DU38: 1013 | DV38: 1 остановка | DW38: 1 остановка | DX38: 1 | EE38: 59073703 | EF38: 40 | EG38: Монтаж оборудования | EH38: 0 | EJ38: 2 | EK38: 64 | EL38: ТСН-2001.4-3. Подъемно-транспортное оборудование | EM38: ТСН-2001.4-3-1 | EO38: Поправка: Гл.12.Прил.8.п.8. 5_12.00.01.11.003 | EQ38: 0 | ER38: 408.44 | ES38: 58.8 | ET38: 34.82 | EU38: 2.61 | EV38: 314.82 | EW38: 23.2 | EX38: 0 | EY38: 0 | FQ38: 0 | FR38: 0 | FS38: 0 | FX38: 92 | FY38: 49 | GD38: 1 | GF38: -1647615880 | GG38: 2 | GH38: 1 | GI38: 2 | GJ38: 0 | GK38: 0 | GL38: =ROUND(IF(AND(BH38=3,BI38=3,FS38<>0),P38,0),2) -> 0 | GM38: =ROUND(O38+X38+Y38,2)+GX38 -> -3984.56 | GN38: =IF(OR(BI38=0,BI38=1),GM38-GX38,0) -> 0 | GO38: =IF(BI38=2,GM38-GX38,0) -> -3984.56 | GP38: =IF(BI38=4,GM38-GX38,0) -> 0 | GR38: 0 | GS38: 3 | GT38: 0 | GV38: =ROUND((GT38),6) -> 0 | GW38: 1 | GX38: =ROUND(HC38*I38,2) -> 0 | HA38: 0 | HB38: 0 | HC38: =GV38*GW38 -> 0 | HS38: 0 | IK38: 0
A39: 17 | B39: 1 | C39: =ROW(SmtRes!A14) -> 14 | D39: =ROW(EtalonRes!A14) -> 14 | E39: 5 | F39: 4.3-34-3 | G39: За каждую остановку, более или менее указанных в характеристике лифта грузоподъемностью 100 кг в глухой шахте добавлять или уменьшать (схема управления микроэлектронная и микропроцессорная)/ грузовой подъёмник | H39: 1 остановка | I39: =ROUND(2-6,9) -> -4 | J39: 0 | K39: =ROUND(2-6,9) -> -4 | O39: =ROUND(CP39,2) -> -85859.75 | P39: =ROUND((ROUND((AC39*AW39*I39),2)*BC39),2) -> -2391.3 | Q39: =(ROUND((ROUND((((ET39*1.1))*AV39*I39),2)*BB39),2)+ROUND((ROUND(((AE39-((EU39*1.1)))*AV39*I39),2)*BS39),2)) -> -2192.13 | R39: =ROUND((ROUND((AE39*AV39*I39),2)*BS39),2) -> -673.63 | S39: =ROUND((ROUND((AF39*AV39*I39),2)*BA39),2) -> -81276.32 | T39: =ROUND(CU39*I39,2) -> 0 | U39: =CV39*I39 -> -108.91936 | V39: =CW39*I39 -> 0 | W39: =ROUND(CX39*I39,2) -> 0 | X39: =ROUND(CY39,2) -> -75393.95 | Y39: =ROUND(CZ39,2) -> -40155.48 | AA39: 59499000 | AB39: =ROUND((AC39+AD39+AF39),6) -> 443.404 | AC39: =ROUND(((ES39*1)),6) -> 58.8 | AD39: =ROUND(((((ET39*1.1))-((EU39*1.1)))+AE39),6) -> 38.302 | AE39: =ROUND(((EU39*1.1)),6) -> 2.871 | AF39: =ROUND(((EV39*1.1)),6) -> 346.302 | AG39: =ROUND((AP39),6) -> 0 | AH39: =((EW39*1.1)) -> 25.52 | AI39: =((EX39*1.1)) -> 0 | AJ39: =(AS39) -> 0 | AK39: 408.44 | AL39: 58.8 | AM39: 34.82 | AN39: 2.61 | AO39: 314.82 | AP39: 0 | AQ39: 23.2 | AR39: 0 | AS39: 0 | AT39: 92 | AU39: 49 | AV39: 1.067 | AW39: 1.028 | AZ39: 1 | BA39: 54.99 | BB39: 13.41 | BC39: 9.89 | BH39: 0 | BI39: 2 | BJ39: ТСН-2001.4. Доп. 1-42. Сб. 3, т. 34, поз. 3 | BM39: 64 | BN39: 59073636 | BO39: 4.3-34-3 | BP39: 1 | BQ39: 40 | BR39: 0 | BS39: 54.99 | BT39: 1 | BU39: 1 | BV39: 1 | BW39: 1 | BX39: 1 | BZ39: 92 | CA39: 49 | CE39: 30 | CF39: 0 | CG39: 0 | CM39: 0 | CN39: Поправка: Гл.12.Прил.8.п.8. 5_12.00.01.11.003 Наименование: При наличии усложненных условий производства работ (стесненность, сложность складирования и транспортной логистики, наличие в зоне производства работ действующего технологического оборудования или движения технологического транспорта и т.п.) для объектов, расположенных за пределами территории круговой магистральной системы улиц "Садовое кольцо" и за пределами Третьего транспортного кольца города Москвы пунктов "а" и "б", но в пределах Московской кольцевой автомобильной дороги | CO39: 0 | CP39: =(P39+Q39+S39) -> -85859.75 | CQ39: =ROUND((ROUND((AC39*AW39*1),2)*BC39),2) -> 597.85 | CR39: =(ROUND((ROUND((((ET39*1.1))*AV39*1),2)*BB39),2)+ROUND((ROUND(((AE39-((EU39*1.1)))*AV39*1),2)*BS39),2)) -> 548.07 | CS39: =ROUND((ROUND((AE39*AV39*1),2)*BS39),2) -> 168.27 | CT39: =ROUND((ROUND((AF39*AV39*1),2)*BA39),2) -> 20318.81 | CU39: =AG39 -> 0 | CV39: =(AH39*AV39) -> 27.22984 | CW39: =AI39 -> 0 | CX39: =AJ39 -> 0 | CY39: =(((S39+R39)*AT39)/100) -> -75393.954 | CZ39: =(((S39+R39)*AU39)/100) -> -40155.476 | DB39: 16 | DD39: *1 | DE39: *1,1 | DF39: *1,1 | DG39: *1,1 | DI39: *1,1 | DJ39: *1,1 | DN39: 0 | DO39: 0 | DP39: 1 | DQ39: 1 | DU39: 1013 | DV39: 1 остановка | DW39: 1 остановка | DX39: 1 | EE39: 59073703 | EF39: 40 | EG39: Монтаж оборудования | EH39: 0 | EJ39: 2 | EK39: 64 | EL39: ТСН-2001.4-3. Подъемно-транспортное оборудование | EM39: ТСН-2001.4-3-1 | EO39: Поправка: Гл.12.Прил.8.п.8. 5_12.00.01.11.003 | EQ39: 0 | ER39: 408.44 | ES39: 58.8 | ET39: 34.82 | EU39: 2.61 | EV39: 314.82 | EW39: 23.2 | EX39: 0 | EY39: 0 | FQ39: 0 | FR39: 0 | FS39: 0 | FX39: 92 | FY39: 49 | GD39: 1 | GF39: -1647615880 | GG39: 2 | GH39: 1 | GI39: 2 | GJ39: 0 | GK39: 0 | GL39: =ROUND(IF(AND(BH39=3,BI39=3,FS39<>0),P39,0),2) -> 0 | GM39: =ROUND(O39+X39+Y39,2)+GX39 -> -201409.18 | GN39: =IF(OR(BI39=0,BI39=1),GM39-GX39,0) -> 0 | GO39: =IF(BI39=2,GM39-GX39,0) -> -201409.18 | GP39: =IF(BI39=4,GM39-GX39,0) -> 0 | GR39: 0 | GS39: 3 | GT39: 0 | GV39: =ROUND((GT39),6) -> 0 | GW39: 1 | GX39: =ROUND(HC39*I39,2) -> 0 | HA39: 0 | HB39: 0 | HC39: =GV39*GW39 -> 0 | HS39: 0 | IK39: 0
A40: 17 | B40: 1 | C40: =ROW(SmtRes!A15) -> 15 | D40: =ROW(EtalonRes!A15) -> 15 | E40: 6 | F40: 4.3-34-4 | G40: За каждый 1 м высоты шахты, более или менее указанных в характеристике малогрузового лифта грузоподъемностью 100 кг в глухой шахте добавлять или уменьшать (схема управления микроэлектронная и микропроцессорная)/ грузовой подъёмник | H40: 1 М | I40: =ROUND((3.15+2.93-21),9) -> -14.92 | J40: 0 | K40: =ROUND((3.15+2.93-21),9) -> -14.92 | O40: =ROUND(CP40,2) -> -1554.18 | P40: =ROUND((ROUND((AC40*AW40*I40),2)*BC40),2) -> -9.66 | Q40: =(ROUND((ROUND((((ET40*1.1))*AV40*I40),2)*BB40),2)+ROUND((ROUND(((AE40-((EU40*1.1)))*AV40*I40),2)*BS40),2)) -> 0 | R40: =ROUND((ROUND((AE40*AV40*I40),2)*BS40),2) -> 0 | S40: =ROUND((ROUND((AF40*AV40*I40),2)*BA40),2) -> -1544.52 | T40: =ROUND(CU40*I40,2) -> 0 | U40: =CV40*I40 -> -113.82543 | V40: =CW40*I40 -> 0 | W40: =ROUND(CX40*I40,2) -> 0 | X40: =ROUND(CY40,2) -> -1420.96 | Y40: =ROUND(CZ40,2) -> -756.81 | AA40: 59499003 | AB40: =ROUND((AC40+AD40+AF40),6) -> 97.65 | AC40: =ROUND(((ES40*1)),6) -> 0.63 | AD40: =ROUND(((((ET40*1.1))-((EU40*1.1)))+AE40),6) -> 0 | AE40: =ROUND(((EU40*1.1)),6) -> 0 | AF40: =ROUND(((EV40*1.1)),6) -> 97.02 | AG40: =ROUND((AP40),6) -> 0 | AH40: =((EW40*1.1)) -> 7.15 | AI40: =((EX40*1.1)) -> 0 | AJ40: =(AS40) -> 0 | AK40: 88.83 | AL40: 0.63 | AM40: 0 | AN40: 0 | AO40: 88.2 | AP40: 0 | AQ40: 6.5 | AR40: 0 | AS40: 0 | AT40: 92 | AU40: 49 | AV40: 1.067 | AW40: 1.028 | AZ40: 1 | BA40: 1 | BB40: 1 | BC40: 1 | BH40: 0 | BI40: 2 | BJ40: ТСН-2001.4 Доп. 68, Сб. 3, т. 34, поз. 4 | BM40: 64 | BN40: 59073636 | BO40: 4.3-34-4 | BP40: 1 | BQ40: 40 | BR40: 0 | BS40: 1 | BT40: 1 | BU40: 1 | BV40: 1 | BW40: 1 | BX40: 1 | BZ40: 92 | CA40: 49 | CE40: 30 | CF40: 0 | CG40: 0 | CM40: 0 | CN40: Поправка: Гл.12.Прил.8.п.8. 5_12.00.01.11.003 Наименование: При наличии усложненных условий производства работ (стесненность, сложность складирования и транспортной логистики, наличие в зоне производства работ действующего технологического оборудования или движения технологического транспорта и т.п.) для объектов, расположенных за пределами территории круговой магистральной системы улиц "Садовое кольцо" и за пределами Третьего транспортного кольца города Москвы пунктов "а" и "б", но в пределах Московской кольцевой автомобильной дороги | CO40: 0 | CP40: =(P40+Q40+S40) -> -1554.18 | CQ40: =ROUND((ROUND((AC40*AW40*1),2)*BC40),2) -> 0.65 | CR40: =(ROUND((ROUND((((ET40*1.1))*AV40*1),2)*BB40),2)+ROUND((ROUND(((AE40-((EU40*1.1)))*AV40*1),2)*BS40),2)) -> 0 | CS40: =ROUND((ROUND((AE40*AV40*1),2)*BS40),2) -> 0 | CT40: =ROUND((ROUND((AF40*AV40*1),2)*BA40),2) -> 103.52 | CU40: =AG40 -> 0 | CV40: =(AH40*AV40) -> 7.62905 | CW40: =AI40 -> 0 | CX40: =AJ40 -> 0 | CY40: =(((S40+R40)*AT40)/100) -> -1420.9584 | CZ40: =(((S40+R40)*AU40)/100) -> -756.8148 | DB40: 17 | DD40: *1 | DE40: *1,1 | DF40: *1,1 | DG40: *1,1 | DI40: *1,1 | DJ40: *1,1 | DN40: 0 | DO40: 0 | DP40: 1 | DQ40: 1 | DU40: 1013 | DV40: 1 М | DW40: 1 М | DX40: 1 | EE40: 59073703 | EF40: 40 | EG40: Монтаж оборудования | EH40: 0 | EJ40: 2 | EK40: 64 | EL40: ТСН-2001.4-3. Подъемно-транспортное оборудование | EM40: ТСН-2001.4-3-1 | EO40: Поправка: Гл.12.Прил.8.п.8. 5_12.00.01.11.003 | EQ40: 0 | ER40: 88.83 | ES40: 0.63 | ET40: 0 | EU40: 0 | EV40: 88.2 | EW40: 6.5 | EX40: 0 | EY40: 0 | FQ40: 0 | FR40: 0 | FS40: 0 | FX40: 92 | FY40: 49 | GD40: 1 | GF40: -887566346 | GG40: 2 | GH40: 1 | GI40: 2 | GJ40: 0 | GK40: 0 | GL40: =ROUND(IF(AND(BH40=3,BI40=3,FS40<>0),P40,0),2) -> 0 | GM40: =ROUND(O40+X40+Y40,2)+GX40 -> -3731.95 | GN40: =IF(OR(BI40=0,BI40=1),GM40-GX40,0) -> 0 | GO40: =IF(BI40=2,GM40-GX40,0) -> -3731.95 | GP40: =IF(BI40=4,GM40-GX40,0) -> 0 | GR40: 0 | GS40: 3 | GT40: 0 | GV40: =ROUND((GT40),6) -> 0 | GW40: 1 | GX40: =ROUND(HC40*I40,2) -> 0 | HA40: 0 | HB40: 0 | HC40: =GV40*GW40 -> 0 | HS40: 0 | IK40: 0
A41: 17 | B41: 1 | C41: =ROW(SmtRes!A16) -> 16 | D41: =ROW(EtalonRes!A16) -> 16 | E41: 6 | F41: 4.3-34-4 | G41: За каждый 1 м высоты шахты, более или менее указанных в характеристике малогрузового лифта грузоподъемностью 100 кг в глухой шахте добавлять или уменьшать (схема управления микроэлектронная и микропроцессорная)/ грузовой подъёмник | H41: 1 М | I41: =ROUND((3.15+2.93-21),9) -> -14.92 | J41: 0 | K41: =ROUND((3.15+2.93-21),9) -> -14.92 | O41: =ROUND(CP41,2) -> -85028.69 | P41: =ROUND((ROUND((AC41*AW41*I41),2)*BC41),2) -> -95.54 | Q41: =(ROUND((ROUND((((ET41*1.1))*AV41*I41),2)*BB41),2)+ROUND((ROUND(((AE41-((EU41*1.1)))*AV41*I41),2)*BS41),2)) -> 0 | R41: =ROUND((ROUND((AE41*AV41*I41),2)*BS41),2) -> 0 | S41: =ROUND((ROUND((AF41*AV41*I41),2)*BA41),2) -> -84933.15 | T41: =ROUND(CU41*I41,2) -> 0 | U41: =CV41*I41 -> -113.82543 | V41: =CW41*I41 -> 0 | W41: =ROUND(CX41*I41,2) -> 0 | X41: =ROUND(CY41,2) -> -78138.5 | Y41: =ROUND(CZ41,2) -> -41617.24 | AA41: 59499000 | AB41: =ROUND((AC41+AD41+AF41),6) -> 97.65 | AC41: =ROUND(((ES41*1)),6) -> 0.63 | AD41: =ROUND(((((ET41*1.1))-((EU41*1.1)))+AE41),6) -> 0 | AE41: =ROUND(((EU41*1.1)),6) -> 0 | AF41: =ROUND(((EV41*1.1)),6) -> 97.02 | AG41: =ROUND((AP41),6) -> 0 | AH41: =((EW41*1.1)) -> 7.15 | AI41: =((EX41*1.1)) -> 0 | AJ41: =(AS41) -> 0 | AK41: 88.83 | AL41: 0.63 | AM41: 0 | AN41: 0 | AO41: 88.2 | AP41: 0 | AQ41: 6.5 | AR41: 0 | AS41: 0 | AT41: 92 | AU41: 49 | AV41: 1.067 | AW41: 1.028 | AZ41: 1 | BA41: 54.99 | BB41: 1 | BC41: 9.89 | BH41: 0 | BI41: 2 | BJ41: ТСН-2001.4 Доп. 68, Сб. 3, т. 34, поз. 4 | BM41: 64 | BN41: 59073636 | BO41: 4.3-34-4 | BP41: 1 | BQ41: 40 | BR41: 0 | BS41: 54.99 | BT41: 1 | BU41: 1 | BV41: 1 | BW41: 1 | BX41: 1 | BZ41: 92 | CA41: 49 | CE41: 30 | CF41: 0 | CG41: 0 | CM41: 0 | CN41: Поправка: Гл.12.Прил.8.п.8. 5_12.00.01.11.003 Наименование: При наличии усложненных условий производства работ (стесненность, сложность складирования и транспортной логистики, наличие в зоне производства работ действующего технологического оборудования или движения технологического транспорта и т.п.) для объектов, расположенных за пределами территории круговой магистральной системы улиц "Садовое кольцо" и за пределами Третьего транспортного кольца города Москвы пунктов "а" и "б", но в пределах Московской кольцевой автомобильной дороги | CO41: 0 | CP41: =(P41+Q41+S41) -> -85028.69 | CQ41: =ROUND((ROUND((AC41*AW41*1),2)*BC41),2) -> 6.43 | CR41: =(ROUND((ROUND((((ET41*1.1))*AV41*1),2)*BB41),2)+ROUND((ROUND(((AE41-((EU41*1.1)))*AV41*1),2)*BS41),2)) -> 0 | CS41: =ROUND((ROUND((AE41*AV41*1),2)*BS41),2) -> 0 | CT41: =ROUND((ROUND((AF41*AV41*1),2)*BA41),2) -> 5692.56 | CU41: =AG41 -> 0 | CV41: =(AH41*AV41) -> 7.62905 | CW41: =AI41 -> 0 | CX41: =AJ41 -> 0 | CY41: =(((S41+R41)*AT41)/100) -> -78138.498 | CZ41: =(((S41+R41)*AU41)/100) -> -41617.243 | DB41: 18 | DD41: *1 | DE41: *1,1 | DF41: *1,1 | DG41: *1,1 | DI41: *1,1 | DJ41: *1,1 | DN41: 0 | DO41: 0 | DP41: 1 | DQ41: 1 | DU41: 1013 | DV41: 1 М | DW41: 1 М | DX41: 1 | EE41: 59073703 | EF41: 40 | EG41: Монтаж оборудования | EH41: 0 | EJ41: 2 | EK41: 64 | EL41: ТСН-2001.4-3. Подъемно-транспортное оборудование | EM41: ТСН-2001.4-3-1 | EO41: Поправка: Гл.12.Прил.8.п.8. 5_12.00.01.11.003 | EQ41: 0 | ER41: 88.83 | ES41: 0.63 | ET41: 0 | EU41: 0 | EV41: 88.2 | EW41: 6.5 | EX41: 0 | EY41: 0 | FQ41: 0 | FR41: 0 | FS41: 0 | FX41: 92 | FY41: 49 | GD41: 1 | GF41: -887566346 | GG41: 2 | GH41: 1 | GI41: 2 | GJ41: 0 | GK41: 0 | GL41: =ROUND(IF(AND(BH41=3,BI41=3,FS41<>0),P41,0),2) -> 0 | GM41: =ROUND(O41+X41+Y41,2)+GX41 -> -204784.43 | GN41: =IF(OR(BI41=0,BI41=1),GM41-GX41,0) -> 0 | GO41: =IF(BI41=2,GM41-GX41,0) -> -204784.43 | GP41: =IF(BI41=4,GM41-GX41,0) -> 0 | GR41: 0 | GS41: 3 | GT41: 0 | GV41: =ROUND((GT41),6) -> 0 | GW41: 1 | GX41: =ROUND(HC41*I41,2) -> 0 | HA41: 0 | HB41: 0 | HC41: =GV41*GW41 -> 0 | HS41: 0 | IK41: 0
A42: 19 | B42: 1 | G42: Оборудование | AA42: 1 | IK42: 0
A43: 17 | B43: 1 | E43: 7 | F43: КА 1 | G43: Подъемник грузовой консольный РЕСТО-ПГ-Ш-100-3150 ТТ | H43: шт. | I43: 1 | J43: 0 | K43: 1 | O43: =ROUND(CP43,2) -> 48761.4 | P43: =ROUND((ROUND((AC43*I43),2)*BC43),2) -> 48761.4 | Q43: =(ROUND((ROUND(((ET43)*AV43*I43),2)*BB43),2)+ROUND((ROUND(((AE43-(EU43))*AV43*I43),2)*BS43),2)) -> 0 | R43: =ROUND((ROUND((AE43*AV43*I43),2)*BS43),2) -> 0 | S43: =ROUND((ROUND((AF43*AV43*I43),2)*BA43),2) -> 0 | T43: =ROUND(CU43*I43,2) -> 0 | U43: =CV43*I43 -> 0 | V43: =CW43*I43 -> 0 | W43: =ROUND(CX43*I43,2) -> 0 | X43: =ROUND(CY43,2) -> 0 | Y43: =ROUND(CZ43,2) -> 0 | AA43: 59499003 | AB43: =ROUND((AC43+AD43+AF43),6) -> 48761.4 | AC43: =ROUND((ES43),6) -> 48761.4 | AD43: =ROUND((((ET43)-(EU43))+AE43),6) -> 0 | AE43: =ROUND((EU43),6) -> 0 | AF43: =ROUND((EV43),6) -> 0 | AG43: =ROUND((AP43),6) -> 0 | AH43: =(EW43) -> 0 | AI43: =(EX43) -> 0 | AJ43: =(AS43) -> 0 | AK43: 48761.4 | AL43: 48761.4 | AM43: 0 | AN43: 0 | AO43: 0 | AP43: 0 | AQ43: 0 | AR43: 0 | AS43: 0 | AT43: 0 | AU43: 0 | AV43: 1 | AW43: 1 | AZ43: 1 | BA43: 1 | BB43: 1 | BC43: 1 | BH43: 3 | BI43: 3 | BM43: 746 | BN43: 0 | BP43: 0 | BQ43: 130 | BR43: 0 | BS43: 1 | BT43: 1 | BU43: 1 | BV43: 1 | BW43: 1 | BX43: 1 | BZ43: 0 | CA43: 0 | CE43: 30 | CF43: 0 | CG43: 0 | CM43: 0 | CO43: 0 | CP43: =(P43+Q43+S43) -> 48761.4 | CQ43: =ROUND((ROUND((AC43*1),2)*BC43),2) -> 48761.4 | CR43: =(ROUND((ROUND(((ET43)*AV43*1),2)*BB43),2)+ROUND((ROUND(((AE43-(EU43))*AV43*1),2)*BS43),2)) -> 0 | CS43: =ROUND((ROUND((AE43*AV43*1),2)*BS43),2) -> 0 | CT43: =ROUND((ROUND((AF43*AV43*1),2)*BA43),2) -> 0 | CU43: =AG43 -> 0 | CV43: =(AH43*AV43) -> 0 | CW43: =AI43 -> 0 | CX43: =AJ43 -> 0 | CY43: =(((S43+R43)*AT43)/100) -> 0 | CZ43: =(((S43+R43)*AU43)/100) -> 0 | DN43: 0 | DO43: 0 | DP43: 1 | DQ43: 1 | DU43: 1010 | DV43: шт. | DW43: шт. | DX43: 1 | EE43: 59073827 | EF43: 130 | EG43: Сметная стоимость оборудования | EH43: 0 | EJ43: 3 | EK43: 746 | EL43: ТСН-2001.13. Сметная стоимость оборудования | EM43: ТСН-2001.13 | EQ43: 0 | ER43: 0 | ES43: 48761.4 | ET43: 0 | EU43: 0 | EV43: 0 | EW43: 0 | EX43: 0 | EY43: 0 | FQ43: 0 | FR43: =P43 -> 48761.4 | FS43: 0 | FX43: 0 | FY43: 0 | GA43: [430 000 / 1,2 / 7,66] + 3% Трансп + 1,2% Заг.скл | GD43: 1 | GF43: 1287371177 | GG43: 2 | GH43: 4 | GI43: -2 | GJ43: 0 | GK43: 0 | GL43: =ROUND(IF(AND(BH43=3,BI43=3,FS43<>0),P43,0),2) -> 0 | GM43: =ROUND(O43+X43+Y43,2)+GX43 -> 48761.4 | GN43: =IF(OR(BI43=0,BI43=1),GM43-GX43,0) -> 0 | GO43: =IF(BI43=2,GM43-GX43,0) -> 0 | GP43: =IF(BI43=4,GM43-GX43,0) -> 0 | GR43: 0 | GS43: 2 | GT43: 0 | GV43: =ROUND((GT43),6) -> 0 | GW43: 1 | GX43: =ROUND(HC43*I43,2) -> 0 | HA43: 0 | HB43: 0 | HC43: =GV43*GW43 -> 0 | HE43: 3 | HF43: 1,2 | HS43: 0 | IK43: 0
A44: 17 | B44: 1 | E44: 7 | F44: КА 1 | G44: Подъемник грузовой консольный РЕСТО-ПГ-Ш-100-3150 ТТ | H44: шт. | I44: 1 | J44: 0 | K44: 1 | O44: =ROUND(CP44,2) -> 373512.32 | P44: =ROUND((ROUND((AC44*I44),2)*BC44),2) -> 373512.32 | Q44: =(ROUND((ROUND(((ET44)*AV44*I44),2)*BB44),2)+ROUND((ROUND(((AE44-(EU44))*AV44*I44),2)*BS44),2)) -> 0 | R44: =ROUND((ROUND((AE44*AV44*I44),2)*BS44),2) -> 0 | S44: =ROUND((ROUND((AF44*AV44*I44),2)*BA44),2) -> 0 | T44: =ROUND(CU44*I44,2) -> 0 | U44: =CV44*I44 -> 0 | V44: =CW44*I44 -> 0 | W44: =ROUND(CX44*I44,2) -> 0 | X44: =ROUND(CY44,2) -> 0 | Y44: =ROUND(CZ44,2) -> 0 | AA44: 59499000 | AB44: =ROUND((AC44+AD44+AF44),6) -> 48761.4 | AC44: =ROUND((ES44),6) -> 48761.4 | AD44: =ROUND((((ET44)-(EU44))+AE44),6) -> 0 | AE44: =ROUND((EU44),6) -> 0 | AF44: =ROUND((EV44),6) -> 0 | AG44: =ROUND((AP44),6) -> 0 | AH44: =(EW44) -> 0 | AI44: =(EX44) -> 0 | AJ44: =(AS44) -> 0 | AK44: 48761.4 | AL44: 48761.4 | AM44: 0 | AN44: 0 | AO44: 0 | AP44: 0 | AQ44: 0 | AR44: 0 | AS44: 0 | AT44: 0 | AU44: 0 | AV44: 1 | AW44: 1 | AZ44: 1 | BA44: 1 | BB44: 1 | BC44: 7.66 | BH44: 3 | BI44: 3 | BM44: 746 | BN44: 0 | BP44: 0 | BQ44: 130 | BR44: 0 | BS44: 1 | BT44: 1 | BU44: 1 | BV44: 1 | BW44: 1 | BX44: 1 | BZ44: 0 | CA44: 0 | CE44: 30 | CF44: 0 | CG44: 0 | CM44: 0 | CO44: 0 | CP44: =(P44+Q44+S44) -> 373512.32 | CQ44: =ROUND((ROUND((AC44*1),2)*BC44),2) -> 373512.32 | CR44: =(ROUND((ROUND(((ET44)*AV44*1),2)*BB44),2)+ROUND((ROUND(((AE44-(EU44))*AV44*1),2)*BS44),2)) -> 0 | CS44: =ROUND((ROUND((AE44*AV44*1),2)*BS44),2) -> 0 | CT44: =ROUND((ROUND((AF44*AV44*1),2)*BA44),2) -> 0 | CU44: =AG44 -> 0 | CV44: =(AH44*AV44) -> 0 | CW44: =AI44 -> 0 | CX44: =AJ44 -> 0 | CY44: =(((S44+R44)*AT44)/100) -> 0 | CZ44: =(((S44+R44)*AU44)/100) -> 0 | DN44: 0 | DO44: 0 | DP44: 1 | DQ44: 1 | DU44: 1010 | DV44: шт. | DW44: шт. | DX44: 1 | EE44: 59073827 | EF44: 130 | EG44: Сметная стоимость оборудования | EH44: 0 | EJ44: 3 | EK44: 746 | EL44: ТСН-2001.13. Сметная стоимость оборудования | EM44: ТСН-2001.13 | EQ44: 0 | ER44: 48761.4 | ES44: 48761.4 | ET44: 0 | EU44: 0 | EV44: 0 | EW44: 0 | EX44: 0 | EY44: 0 | EZ44: 5 | FC44: 1 | FD44: 18 | FF44: 430000 | FQ44: 0 | FR44: =P44 -> 373512.32 | FS44: 0 | FX44: 0 | FY44: 0 | GA44: [430 000 / 1,2 / 7,66] + 3% Трансп + 1,2% Заг.скл | GD44: 1 | GF44: 1287371177 | GG44: 2 | GH44: 3 | GI44: 3 | GJ44: 0 | GK44: 0 | GL44: =ROUND(IF(AND(BH44=3,BI44=3,FS44<>0),P44,0),2) -> 0 | GM44: =ROUND(O44+X44+Y44,2)+GX44 -> 373512.32 | GN44: =IF(OR(BI44=0,BI44=1),GM44-GX44,0) -> 0 | GO44: =IF(BI44=2,GM44-GX44,0) -> 0 | GP44: =IF(BI44=4,GM44-GX44,0) -> 0 | GR44: 1 | GS44: 1 | GT44: 0 | GV44: =ROUND((GT44),6) -> 0 | GW44: 1 | GX44: =ROUND(HC44*I44,2) -> 0 | HA44: 0 | HB44: 0 | HC44: =GV44*GW44 -> 0 | HE44: 3 | HF44: 1,2 | HS44: 0 | IK44: 0
A46: 51 | B46: =B24 -> 1 | C46: =A24 -> 4 | D46: =ROW(A24) -> 24 | F46: =IF(F24<>"",F24,"") | G46: =IF(G24<>"",G24,"") -> Подъемник грузовой консольный в осях «Ж-И/4-5» | H46: 0 | O46: =ROUND(AB46,2) -> 53199.99 | P46: =ROUND(AC46,2) -> 49495.8 | Q46: =ROUND(AD46,2) -> 303.71 | R46: =ROUND(AE46,2) -> 21.01 | S46: =ROUND(AF46,2) -> 3400.48 | T46: =ROUND(AG46,2) -> 0 | U46: =AH46 -> 252.13564 | V46: =AI46 -> 0 | W46: =ROUND(AJ46,2) -> 0 | X46: =ROUND(AK46,2) -> 3147.77 | Y46: =ROUND(AL46,2) -> 1676.53 | AB46: =ROUND(SUMIF(AA28:AA44,"=59499003",O28:O44),2) -> 53199.99 | AC46: =ROUND(SUMIF(AA28:AA44,"=59499003",P28:P44),2) -> 49495.8 | AD46: =ROUND(SUMIF(AA28:AA44,"=59499003",Q28:Q44),2) -> 303.71 | AE46: =ROUND(SUMIF(AA28:AA44,"=59499003",R28:R44),2) -> 21.01 | AF46: =ROUND(SUMIF(AA28:AA44,"=59499003",S28:S44),2) -> 3400.48 | AG46: =ROUND(SUMIF(AA28:AA44,"=59499003",T28:T44),2) -> 0 | AH46: =SUMIF(AA28:AA44,"=59499003",U28:U44) -> 252.13564 | AI46: =SUMIF(AA28:AA44,"=59499003",V28:V44) -> 0 | AJ46: =ROUND(SUMIF(AA28:AA44,"=59499003",W28:W44),2) -> 0 | AK46: =ROUND(SUMIF(AA28:AA44,"=59499003",X28:X44),2) -> 3147.77 | AL46: =ROUND(SUMIF(AA28:AA44,"=59499003",Y28:Y44),2) -> 1676.53 | AO46: =ROUND(BX46,2) -> 0 | AP46: =ROUND(BY46,2) -> 48761.4 | AQ46: =ROUND(BZ46,2) -> 0 | AR46: =ROUND(CA46,2) -> 58024.29 | AS46: =ROUND(CB46,2) -> 0 | AT46: =ROUND(CC46,2) -> 9262.89 | AU46: =ROUND(CD46,2) -> 0 | AV46: =ROUND(CE46,2) -> 49495.8 | ... BD46: =ROUND(CM46,2) -> 0 | BX46: =ROUND(SUMIF(AA28:AA44,"=59499003",FQ28:FQ44),2) -> 0 | BY46: =ROUND(SUMIF(AA28:AA44,"=59499003",FR28:FR44),2) -> 48761.4 | BZ46: =ROUND(SUMIF(AA28:AA44,"=59499003",GL28:GL44),2) -> 0 | CA46: =ROUND(SUMIF(AA28:AA44,"=59499003",GM28:GM44),2) -> 58024.29 | CB46: =ROUND(SUMIF(AA28:AA44,"=59499003",GN28:GN44),2) -> 0 | CC46: =ROUND(SUMIF(AA28:AA44,"=59499003",GO28:GO44),2) -> 9262.89 | CD46: =ROUND(SUMIF(AA28:AA44,"=59499003",GP28:GP44),2) -> 0 | CE46: =AC46-BX46 -> 49495.8 | CF46: =AC46-BY46 -> 734.4 | CG46: =BX46-BZ46 -> 0 | CH46: =AC46-BX46-BY46+BZ46 -> 734.4 | CI46: =BY46-BZ46 -> 48761.4 | CJ46: =ROUND(SUMIF(AA28:AA44,"=59499003",GX28:GX44),2) -> 0 | CK46: =ROUND(SUMIF(AA28:AA44,"=59499003",GY28:GY44),2) -> 0 | CL46: =ROUND(SUMIF(AA28:AA44,"=59499003",GZ28:GZ44),2) -> 0 | CM46: =ROUND(SUMIF(AA28:AA44,"=59499003",HD28:HD44),2) -> 0 | DG46: =ROUND(DT46,2) -> 571763.25 | DH46: =ROUND(DU46,2) -> 380775.54 | DI46: =ROUND(DV46,2) -> 3995.31 | DJ46: =ROUND(DW46,2) -> 1155.34 | DK46: =ROUND(DX46,2) -> 186992.4 | DL46: =ROUND(DY46,2) -> 0 | DM46: =DZ46 -> 252.13564 | DN46: =EA46 -> 0 | DO46: =ROUND(EB46,2) -> 0 | DP46: =ROUND(EC46,2) -> 173095.92 | DQ46: =ROUND(ED46,2) -> 92192.4 | DT46: =ROUND(SUMIF(AA28:AA44,"=59499000",O28:O44),2) -> 571763.25 | DU46: =ROUND(SUMIF(AA28:AA44,"=59499000",P28:P44),2) -> 380775.54 | DV46: =ROUND(SUMIF(AA28:AA44,"=59499000",Q28:Q44),2) -> 3995.31 | DW46: =ROUND(SUMIF(AA28:AA44,"=59499000",R28:R44),2) -> 1155.34 | DX46: =ROUND(SUMIF(AA28:AA44,"=59499000",S28:S44),2) -> 186992.4 | DY46: =ROUND(SUMIF(AA28:AA44,"=59499000",T28:T44),2) -> 0 | DZ46: =SUMIF(AA28:AA44,"=59499000",U28:U44) -> 252.13564 | EA46: =SUMIF(AA28:AA44,"=59499000",V28:V44) -> 0 | EB46: =ROUND(SUMIF(AA28:AA44,"=59499000",W28:W44),2) -> 0 | EC46: =ROUND(SUMIF(AA28:AA44,"=59499000",X28:X44),2) -> 173095.92 | ED46: =ROUND(SUMIF(AA28:AA44,"=59499000",Y28:Y44),2) -> 92192.4 | EG46: =ROUND(FP46,2) -> 0 | EH46: =ROUND(FQ46,2) -> 373512.32 | EI46: =ROUND(FR46,2) -> 0 | EJ46: =ROUND(FS46,2) -> 837051.57 | EK46: =ROUND(FT46,2) -> 0 | EL46: =ROUND(FU46,2) -> 463539.25 | EM46: =ROUND(FV46,2) -> 0 | EN46: =ROUND(FW46,2) -> 380775.54 | ... EV46: =ROUND(GE46,2) -> 0 | FP46: =ROUND(SUMIF(AA28:AA44,"=59499000",FQ28:FQ44),2) -> 0 | FQ46: =ROUND(SUMIF(AA28:AA44,"=59499000",FR28:FR44),2) -> 373512.32 | FR46: =ROUND(SUMIF(AA28:AA44,"=59499000",GL28:GL44),2) -> 0 | FS46: =ROUND(SUMIF(AA28:AA44,"=59499000",GM28:GM44),2) -> 837051.57 | FT46: =ROUND(SUMIF(AA28:AA44,"=59499000",GN28:GN44),2) -> 0 | FU46: =ROUND(SUMIF(AA28:AA44,"=59499000",GO28:GO44),2) -> 463539.25 | FV46: =ROUND(SUMIF(AA28:AA44,"=59499000",GP28:GP44),2) -> 0 | FW46: =DU46-FP46 -> 380775.54 | FX46: =DU46-FQ46 -> 7263.22 | FY46: =FP46-FR46 -> 0 | FZ46: =DU46-FP46-FQ46+FR46 -> 7263.22 | GA46: =FQ46-FR46 -> 373512.32 | GB46: =ROUND(SUMIF(AA28:AA44,"=59499000",GX28:GX44),2) -> 0 | GC46: =ROUND(SUMIF(AA28:AA44,"=59499000",GY28:GY44),2) -> 0 | GD46: =ROUND(SUMIF(AA28:AA44,"=59499000",GZ28:GZ44),2) -> 0 | GE46: =ROUND(SUMIF(AA28:AA44,"=59499000",HD28:HD44),2) -> 0 | GX46: 0
A48: 50 | B48: 0 | C48: 0 | D48: 1 | E48: 201 | F48: =ROUND(Source!O46,O48) -> 53199.99 | G48: ПЗ | H48: Прямые затраты | K48: 201 | L48: 1 | M48: 3 | O48: 2 | P48: =ROUND(Source!DG46,O48) -> 571763.25 | W48: 53199.99 | X48: 1 | Y48: 53199.99 | Z48: 571763.25 | AA48: 1 | AB48: 571763.25
A49: 50 | B49: 0 | C49: 0 | D49: 1 | E49: 202 | F49: =ROUND(Source!P46,O49) -> 49495.8 | G49: СтМатОб | H49: Стоимость материальных ресурсов (всего) | K49: 202 | L49: 2 | M49: 3 | O49: 2 | P49: =ROUND(Source!DH46,O49) -> 380775.54 | W49: 49495.8 | X49: 1 | Y49: 49495.8 | Z49: 380775.54 | AA49: 1 | AB49: 380775.54
A50: 50 | B50: 0 | C50: 0 | D50: 1 | E50: 222 | F50: =ROUND(Source!AO46,O50) -> 0 | G50: СтМатОбЗак | H50: Стоимость материалов и оборудования заказчика | K50: 222 | L50: 3 | M50: 3 | O50: 2 | P50: =ROUND(Source!EG46,O50) -> 0 | W50: 0 | X50: 1 | Y50: 0 | Z50: 0 | AA50: 1 | AB50: 0
A51: 50 | B51: 0 | C51: 0 | D51: 1 | E51: 225 | F51: =ROUND(Source!AV46,O51) -> 49495.8 | G51: СтМатОбПод | H51: Стоимость материалов и оборудования подрядчика | K51: 225 | L51: 4 | M51: 3 | O51: 2 | P51: =ROUND(Source!EN46,O51) -> 380775.54 | W51: 49495.8 | X51: 1 | Y51: 49495.8 | Z51: 380775.54 | AA51: 1 | AB51: 380775.54
A52: 50 | B52: 0 | C52: 0 | D52: 1 | E52: 226 | F52: =ROUND(Source!AW46,O52) -> 734.4 | G52: СтМат | H52: Стоимость материалов (всего) | K52: 226 | L52: 5 | M52: 3 | O52: 2 | P52: =ROUND(Source!EO46,O52) -> 7263.22 | W52: 734.4 | X52: 1 | Y52: 734.4 | Z52: 7263.22 | AA52: 1 | AB52: 7263.22
A53: 50 | B53: 0 | C53: 0 | D53: 1 | E53: 227 | F53: =ROUND(Source!AX46,O53) -> 0 | G53: СтМатЗак | H53: Стоимость материалов заказчика | K53: 227 | L53: 6 | M53: 3 | O53: 2 | P53: =ROUND(Source!EP46,O53) -> 0 | W53: 0 | X53: 1 | Y53: 0 | Z53: 0 | AA53: 1 | AB53: 0
A54: 50 | B54: 0 | C54: 0 | D54: 1 | E54: 228 | F54: =ROUND(Source!AY46,O54) -> 734.4 | G54: СтМатПод | H54: Стоимость материалов подрядчика | K54: 228 | L54: 7 | M54: 3 | O54: 2 | P54: =ROUND(Source!EQ46,O54) -> 7263.22 | W54: 734.4 | X54: 1 | Y54: 734.4 | Z54: 7263.22 | AA54: 1 | AB54: 7263.22
A55: 50 | B55: 0 | C55: 0 | D55: 1 | E55: 216 | F55: =ROUND(Source!AP46,O55) -> 48761.4 | G55: Оборуд | H55: Стоимость оборудования (всего) | K55: 216 | L55: 8 | M55: 3 | O55: 2 | P55: =ROUND(Source!EH46,O55) -> 373512.32 | W55: 48761.4 | X55: 1 | Y55: 48761.4 | Z55: 373512.32 | AA55: 1 | AB55: 373512.32
A56: 50 | B56: 0 | C56: 0 | D56: 1 | E56: 223 | F56: =ROUND(Source!AQ46,O56) -> 0 | G56: ОборудЗак | H56: Стоимость оборудования заказчика | K56: 223 | L56: 9 | M56: 3 | O56: 2 | P56: =ROUND(Source!EI46,O56) -> 0 | W56: 0 | X56: 1 | Y56: 0 | Z56: 0 | AA56: 1 | AB56: 0
A57: 50 | B57: 0 | C57: 0 | D57: 1 | E57: 229 | F57: =ROUND(Source!AZ46,O57) -> 48761.4 | G57: ОборудПод | H57: Стоимость оборудования подрядчика | K57: 229 | L57: 10 | M57: 3 | O57: 2 | P57: =ROUND(Source!ER46,O57) -> 373512.32 | W57: 48761.4 | X57: 1 | Y57: 48761.4 | Z57: 373512.32 | AA57: 1 | AB57: 373512.32
A58: 50 | B58: 0 | C58: 0 | D58: 1 | E58: 203 | F58: =ROUND(Source!Q46,O58) -> 303.71 | G58: ЭММ | H58: Эксплуатация машин | K58: 203 | L58: 11 | M58: 3 | O58: 2 | P58: =ROUND(Source!DI46,O58) -> 3995.31 | W58: 303.71 | X58: 1 | Y58: 303.71 | Z58: 3995.31 | AA58: 1 | AB58: 3995.31
A59: 50 | B59: 0 | C59: 0 | D59: 1 | E59: 231 | F59: =ROUND(Source!BB46,O59) -> 0 | G59: ЭММсНРиСП | H59: Эксплуатация машин по ТСН-2001.16 | K59: 231 | L59: 12 | M59: 3 | O59: 2 | P59: =ROUND(Source!ET46,O59) -> 0 | W59: 0 | X59: 1 | Y59: 0 | Z59: 0 | AA59: 1 | AB59: 0
A60: 50 | B60: 0 | C60: 0 | D60: 1 | E60: 204 | F60: =ROUND(Source!R46,O60) -> 21.01 | G60: ЗПМ | H60: ЗП машинистов | K60: 204 | L60: 13 | M60: 3 | O60: 2 | P60: =ROUND(Source!DJ46,O60) -> 1155.34 | W60: 21.01 | X60: 1 | Y60: 21.01 | Z60: 1155.34 | AA60: 1 | AB60: 1155.34
A61: 50 | B61: 0 | C61: 0 | D61: 1 | E61: 205 | F61: =ROUND(Source!S46,O61) -> 3400.48 | G61: ОЗП | H61: Основная ЗП рабочих | K61: 205 | L61: 14 | M61: 3 | O61: 2 | P61: =ROUND(Source!DK46,O61) -> 186992.4 | W61: 3400.48 | X61: 1 | Y61: 3400.48 | Z61: 186992.4 | AA61: 1 | AB61: 186992.4
A62: 50 | B62: 0 | C62: 0 | D62: 1 | E62: 232 | F62: =ROUND(Source!BC46,O62) -> 0 | G62: ОЗПсНРиСП | H62: Основная ЗП рабочих по ТСН-2001.16 | K62: 232 | L62: 15 | M62: 3 | O62: 2 | P62: =ROUND(Source!EU46,O62) -> 0 | W62: 0 | X62: 1 | Y62: 0 | Z62: 0 | AA62: 1 | AB62: 0
A63: 50 | B63: 0 | C63: 0 | D63: 1 | E63: 214 | F63: =ROUND(Source!AS46,O63) -> 0 | G63: Строит | H63: Строительные работы с НР и СП | K63: 214 | L63: 16 | M63: 3 | O63: 2 | P63: =ROUND(Source!EK46,O63) -> 0 | W63: 0 | X63: 1 | Y63: 0 | Z63: 0 | AA63: 1 | AB63: 0
A64: 50 | B64: 0 | C64: 0 | D64: 1 | E64: 215 | F64: =ROUND(Source!AT46,O64) -> 9262.89 | G64: Монтаж | H64: Монтажные работы с НР и СП | K64: 215 | L64: 17 | M64: 3 | O64: 2 | P64: =ROUND(Source!EL46,O64) -> 463539.25 | W64: 9262.89 | X64: 1 | Y64: 9262.89 | Z64: 463539.25 | AA64: 1 | AB64: 463539.25
A65: 50 | B65: 0 | C65: 0 | D65: 1 | E65: 217 | F65: =ROUND(Source!AU46,O65) -> 0 | G65: Прочие | H65: Прочие работы с НР и СП | K65: 217 | L65: 18 | M65: 3 | O65: 2 | P65: =ROUND(Source!EM46,O65) -> 0 | W65: 0 | X65: 1 | Y65: 0 | Z65: 0 | AA65: 1 | AB65: 0
A66: 50 | B66: 0 | C66: 0 | D66: 1 | E66: 230 | F66: =ROUND(Source!BA46,O66) -> 0 | G66: ПрочиеЗатр | H66: Прочие затраты по ТСН-2001.16 | K66: 230 | L66: 19 | M66: 3 | O66: 2 | P66: =ROUND(Source!ES46,O66) -> 0 | W66: 0 | X66: 1 | Y66: 0 | Z66: 0 | AA66: 1 | AB66: 0
A67: 50 | B67: 0 | C67: 0 | D67: 1 | E67: 206 | F67: =ROUND(Source!T46,O67) -> 0 | G67: ВозврМат | H67: Возврат материалов | K67: 206 | L67: 20 | M67: 3 | O67: 2 | P67: =ROUND(Source!DL46,O67) -> 0 | W67: 0 | X67: 1 | Y67: 0 | Z67: 0 | AA67: 1 | AB67: 0
A68: 50 | B68: 0 | C68: 0 | D68: 1 | E68: 207 | F68: =Source!U46 -> 252.13564 | G68: ТрудСтр | H68: Трудозатраты строителей | K68: 207 | L68: 21 | M68: 3 | O68: -1 | P68: =Source!DM46 -> 252.13564 | W68: 252.13564 | X68: 1 | Y68: 252.13564 | Z68: 252.13564 | AA68: 1 | AB68: 252.13564
A69: 50 | B69: 0 | C69: 0 | D69: 1 | E69: 208 | F69: =Source!V46 -> 0 | G69: ТрудМаш | H69: Трудозатраты машинистов | K69: 208 | L69: 22 | M69: 3 | O69: -1 | P69: =Source!DN46 -> 0 | W69: 0 | X69: 1 | Y69: 0 | Z69: 0 | AA69: 1 | AB69: 0
A70: 50 | B70: 0 | C70: 0 | D70: 1 | E70: 209 | F70: =ROUND(Source!W46,O70) -> 0 | G70: ТранспМат | H70: Транспорт материалов | K70: 209 | L70: 23 | M70: 3 | O70: 2 | P70: =ROUND(Source!DO46,O70) -> 0 | W70: 0 | X70: 1 | Y70: 0 | Z70: 0 | AA70: 1 | AB70: 0
A71: 50 | B71: 0 | C71: 0 | D71: 1 | E71: 233 | F71: =ROUND(Source!BD46,O71) -> 0 | G71: Перевозка | H71: Перевозка грузов | K71: 233 | L71: 24 | M71: 3 | O71: 2 | P71: =ROUND(Source!EV46,O71) -> 0 | W71: 0 | X71: 1 | Y71: 0 | Z71: 0 | AA71: 1 | AB71: 0
A72: 50 | B72: 0 | C72: 0 | D72: 1 | E72: 210 | F72: =ROUND(Source!X46,O72) -> 3147.77 | G72: НР | H72: Накладные расходы | K72: 210 | L72: 25 | M72: 3 | O72: 2 | P72: =ROUND(Source!DP46,O72) -> 173095.92 | W72: 3147.77 | X72: 1 | Y72: 3147.77 | Z72: 173095.92 | AA72: 1 | AB72: 173095.92
A73: 50 | B73: 0 | C73: 0 | D73: 1 | E73: 211 | F73: =ROUND(Source!Y46,O73) -> 1676.53 | G73: СмПриб | H73: Сметная прибыль | K73: 211 | L73: 26 | M73: 3 | O73: 2 | P73: =ROUND(Source!DQ46,O73) -> 92192.4 | W73: 1676.53 | X73: 1 | Y73: 1676.53 | Z73: 92192.4 | AA73: 1 | AB73: 92192.4
A74: 50 | B74: 0 | C74: 0 | D74: 1 | E74: 224 | F74: =ROUND(Source!AR46,O74) -> 58024.29 | G74: Всего | H74: Всего с НР и СП | K74: 224 | L74: 27 | M74: 3 | O74: 2 | P74: =ROUND(Source!EJ46,O74) -> 837051.57 | W74: 58024.29 | X74: 1 | Y74: 58024.29 | Z74: 837051.57 | AA74: 1 | AB74: 837051.57
A76: 51 | B76: =B20 -> 1 | C76: =A20 -> 3 | D76: =ROW(A20) -> 20 | F76: =IF(F20<>"",F20,"") -> 02-01-19 | G76: =IF(G20<>"",G20,"") -> Вертикальный транспорт | H76: 0 | O76: =ROUND(O46+AB76,2) -> 53199.99 | P76: =ROUND(P46+AC76,2) -> 49495.8 | Q76: =ROUND(Q46+AD76,2) -> 303.71 | R76: =ROUND(R46+AE76,2) -> 21.01 | S76: =ROUND(S46+AF76,2) -> 3400.48 | T76: =ROUND(T46+AG76,2) -> 0 | U76: =U46+AH76 -> 252.13564 | V76: =V46+AI76 -> 0 | W76: =ROUND(W46+AJ76,2) -> 0 | X76: =ROUND(X46+AK76,2) -> 3147.77 | Y76: =ROUND(Y46+AL76,2) -> 1676.53 | AO76: =ROUND(AO46+BX76,2) -> 0 | AP76: =ROUND(AP46+BY76,2) -> 48761.4 | AQ76: =ROUND(AQ46+BZ76,2) -> 0 | AR76: =ROUND(AR46+CA76,2) -> 58024.29 | AS76: =ROUND(AS46+CB76,2) -> 0 | AT76: =ROUND(AT46+CC76,2) -> 9262.89 | AU76: =ROUND(AU46+CD76,2) -> 0 | AV76: =ROUND(AV46+CE76,2) -> 49495.8 | ... BD76: =ROUND(BD46+CM76,2) -> 0 | DG76: =ROUND(DG46+DT76,2) -> 571763.25 | DH76: =ROUND(DH46+DU76,2) -> 380775.54 | DI76: =ROUND(DI46+DV76,2) -> 3995.31 | DJ76: =ROUND(DJ46+DW76,2) -> 1155.34 | DK76: =ROUND(DK46+DX76,2) -> 186992.4 | DL76: =ROUND(DL46+DY76,2) -> 0 | DM76: =DM46+DZ76 -> 252.13564 | DN76: =DN46+EA76 -> 0 | DO76: =ROUND(DO46+EB76,2) -> 0 | DP76: =ROUND(DP46+EC76,2) -> 173095.92 | DQ76: =ROUND(DQ46+ED76,2) -> 92192.4 | EG76: =ROUND(EG46+FP76,2) -> 0 | EH76: =ROUND(EH46+FQ76,2) -> 373512.32 | EI76: =ROUND(EI46+FR76,2) -> 0 | EJ76: =ROUND(EJ46+FS76,2) -> 837051.57 | EK76: =ROUND(EK46+FT76,2) -> 0 | EL76: =ROUND(EL46+FU76,2) -> 463539.25 | EM76: =ROUND(EM46+FV76,2) -> 0 | EN76: =ROUND(EN46+FW76,2) -> 380775.54 | ... EV76: =ROUND(EV46+GE76,2) -> 0 | GX76: 0
A78: 50 | B78: 0 | C78: 0 | D78: 1 | E78: 201 | F78: =ROUND(Source!O76,O78) -> 53199.99 | G78: ПЗ | H78: Прямые затраты | K78: 201 | L78: 1 | M78: 3 | O78: 2 | P78: =ROUND(Source!DG76,O78) -> 571763.25 | W78: 53199.99 | X78: 1 | Y78: 53199.99 | Z78: 571763.25 | AA78: 1 | AB78: 571763.25
A79: 50 | B79: 0 | C79: 0 | D79: 1 | E79: 202 | F79: =ROUND(Source!P76,O79) -> 49495.8 | G79: СтМатОб | H79: Стоимость материальных ресурсов (всего) | K79: 202 | L79: 2 | M79: 3 | O79: 2 | P79: =ROUND(Source!DH76,O79) -> 380775.54 | W79: 49495.8 | X79: 1 | Y79: 49495.8 | Z79: 380775.54 | AA79: 1 | AB79: 380775.54
A80: 50 | B80: 0 | C80: 0 | D80: 1 | E80: 222 | F80: =ROUND(Source!AO76,O80) -> 0 | G80: СтМатОбЗак | H80: Стоимость материалов и оборудования заказчика | K80: 222 | L80: 3 | M80: 3 | O80: 2 | P80: =ROUND(Source!EG76,O80) -> 0 | W80: 0 | X80: 1 | Y80: 0 | Z80: 0 | AA80: 1 | AB80: 0
A81: 50 | B81: 0 | C81: 0 | D81: 1 | E81: 225 | F81: =ROUND(Source!AV76,O81) -> 49495.8 | G81: СтМатОбПод | H81: Стоимость материалов и оборудования подрядчика | K81: 225 | L81: 4 | M81: 3 | O81: 2 | P81: =ROUND(Source!EN76,O81) -> 380775.54 | W81: 49495.8 | X81: 1 | Y81: 49495.8 | Z81: 380775.54 | AA81: 1 | AB81: 380775.54
A82: 50 | B82: 0 | C82: 0 | D82: 1 | E82: 226 | F82: =ROUND(Source!AW76,O82) -> 734.4 | G82: СтМат | H82: Стоимость материалов (всего) | K82: 226 | L82: 5 | M82: 3 | O82: 2 | P82: =ROUND(Source!EO76,O82) -> 7263.22 | W82: 734.4 | X82: 1 | Y82: 734.4 | Z82: 7263.22 | AA82: 1 | AB82: 7263.22
A83: 50 | B83: 0 | C83: 0 | D83: 1 | E83: 227 | F83: =ROUND(Source!AX76,O83) -> 0 | G83: СтМатЗак | H83: Стоимость материалов заказчика | K83: 227 | L83: 6 | M83: 3 | O83: 2 | P83: =ROUND(Source!EP76,O83) -> 0 | W83: 0 | X83: 1 | Y83: 0 | Z83: 0 | AA83: 1 | AB83: 0
A84: 50 | B84: 0 | C84: 0 | D84: 1 | E84: 228 | F84: =ROUND(Source!AY76,O84) -> 734.4 | G84: СтМатПод | H84: Стоимость материалов подрядчика | K84: 228 | L84: 7 | M84: 3 | O84: 2 | P84: =ROUND(Source!EQ76,O84) -> 7263.22 | W84: 734.4 | X84: 1 | Y84: 734.4 | Z84: 7263.22 | AA84: 1 | AB84: 7263.22
A85: 50 | B85: 0 | C85: 0 | D85: 1 | E85: 216 | F85: =ROUND(Source!AP76,O85) -> 48761.4 | G85: Оборуд | H85: Стоимость оборудования (всего) | K85: 216 | L85: 8 | M85: 3 | O85: 2 | P85: =ROUND(Source!EH76,O85) -> 373512.32 | W85: 48761.4 | X85: 1 | Y85: 48761.4 | Z85: 373512.32 | AA85: 1 | AB85: 373512.32
A86: 50 | B86: 0 | C86: 0 | D86: 1 | E86: 223 | F86: =ROUND(Source!AQ76,O86) -> 0 | G86: ОборудЗак | H86: Стоимость оборудования заказчика | K86: 223 | L86: 9 | M86: 3 | O86: 2 | P86: =ROUND(Source!EI76,O86) -> 0 | W86: 0 | X86: 1 | Y86: 0 | Z86: 0 | AA86: 1 | AB86: 0
A87: 50 | B87: 0 | C87: 0 | D87: 1 | E87: 229 | F87: =ROUND(Source!AZ76,O87) -> 48761.4 | G87: ОборудПод | H87: Стоимость оборудования подрядчика | K87: 229 | L87: 10 | M87: 3 | O87: 2 | P87: =ROUND(Source!ER76,O87) -> 373512.32 | W87: 48761.4 | X87: 1 | Y87: 48761.4 | Z87: 373512.32 | AA87: 1 | AB87: 373512.32
A88: 50 | B88: 0 | C88: 0 | D88: 1 | E88: 203 | F88: =ROUND(Source!Q76,O88) -> 303.71 | G88: ЭММ | H88: Эксплуатация машин | K88: 203 | L88: 11 | M88: 3 | O88: 2 | P88: =ROUND(Source!DI76,O88) -> 3995.31 | W88: 303.71 | X88: 1 | Y88: 303.71 | Z88: 3995.31 | AA88: 1 | AB88: 3995.31
A89: 50 | B89: 0 | C89: 0 | D89: 1 | E89: 231 | F89: =ROUND(Source!BB76,O89) -> 0 | G89: ЭММсНРиСП | H89: Эксплуатация машин по ТСН-2001.16 | K89: 231 | L89: 12 | M89: 3 | O89: 2 | P89: =ROUND(Source!ET76,O89) -> 0 | W89: 0 | X89: 1 | Y89: 0 | Z89: 0 | AA89: 1 | AB89: 0
A90: 50 | B90: 0 | C90: 0 | D90: 1 | E90: 204 | F90: =ROUND(Source!R76,O90) -> 21.01 | G90: ЗПМ | H90: ЗП машинистов | K90: 204 | L90: 13 | M90: 3 | O90: 2 | P90: =ROUND(Source!DJ76,O90) -> 1155.34 | W90: 21.01 | X90: 1 | Y90: 21.01 | Z90: 1155.34 | AA90: 1 | AB90: 1155.34
A91: 50 | B91: 0 | C91: 0 | D91: 1 | E91: 205 | F91: =ROUND(Source!S76,O91) -> 3400.48 | G91: ОЗП | H91: Основная ЗП рабочих | K91: 205 | L91: 14 | M91: 3 | O91: 2 | P91: =ROUND(Source!DK76,O91) -> 186992.4 | W91: 3400.48 | X91: 1 | Y91: 3400.48 | Z91: 186992.4 | AA91: 1 | AB91: 186992.4
A92: 50 | B92: 0 | C92: 0 | D92: 1 | E92: 232 | F92: =ROUND(Source!BC76,O92) -> 0 | G92: ОЗПсНРиСП | H92: Основная ЗП рабочих по ТСН-2001.16 | K92: 232 | L92: 15 | M92: 3 | O92: 2 | P92: =ROUND(Source!EU76,O92) -> 0 | W92: 0 | X92: 1 | Y92: 0 | Z92: 0 | AA92: 1 | AB92: 0
A93: 50 | B93: 0 | C93: 0 | D93: 1 | E93: 214 | F93: =ROUND(Source!AS76,O93) -> 0 | G93: Строит | H93: Строительные работы с НР и СП | K93: 214 | L93: 16 | M93: 3 | O93: 2 | P93: =ROUND(Source!EK76,O93) -> 0 | W93: 0 | X93: 1 | Y93: 0 | Z93: 0 | AA93: 1 | AB93: 0
A94: 50 | B94: 0 | C94: 0 | D94: 1 | E94: 215 | F94: =ROUND(Source!AT76,O94) -> 9262.89 | G94: Монтаж | H94: Монтажные работы с НР и СП | K94: 215 | L94: 17 | M94: 3 | O94: 2 | P94: =ROUND(Source!EL76,O94) -> 463539.25 | W94: 9262.89 | X94: 1 | Y94: 9262.89 | Z94: 463539.25 | AA94: 1 | AB94: 463539.25
A95: 50 | B95: 0 | C95: 0 | D95: 1 | E95: 217 | F95: =ROUND(Source!AU76,O95) -> 0 | G95: Прочие | H95: Прочие работы с НР и СП | K95: 217 | L95: 18 | M95: 3 | O95: 2 | P95: =ROUND(Source!EM76,O95) -> 0 | W95: 0 | X95: 1 | Y95: 0 | Z95: 0 | AA95: 1 | AB95: 0
A96: 50 | B96: 0 | C96: 0 | D96: 1 | E96: 230 | F96: =ROUND(Source!BA76,O96) -> 0 | G96: ПрочиеЗатр | H96: Прочие затраты по ТСН-2001.16 | K96: 230 | L96: 19 | M96: 3 | O96: 2 | P96: =ROUND(Source!ES76,O96) -> 0 | W96: 0 | X96: 1 | Y96: 0 | Z96: 0 | AA96: 1 | AB96: 0
A97: 50 | B97: 0 | C97: 0 | D97: 1 | E97: 206 | F97: =ROUND(Source!T76,O97) -> 0 | G97: ВозврМат | H97: Возврат материалов | K97: 206 | L97: 20 | M97: 3 | O97: 2 | P97: =ROUND(Source!DL76,O97) -> 0 | W97: 0 | X97: 1 | Y97: 0 | Z97: 0 | AA97: 1 | AB97: 0
A98: 50 | B98: 0 | C98: 0 | D98: 1 | E98: 207 | F98: =Source!U76 -> 252.13564 | G98: ТрудСтр | H98: Трудозатраты строителей | K98: 207 | L98: 21 | M98: 3 | O98: -1 | P98: =Source!DM76 -> 252.13564 | W98: 252.13564 | X98: 1 | Y98: 252.13564 | Z98: 252.13564 | AA98: 1 | AB98: 252.13564
A99: 50 | B99: 0 | C99: 0 | D99: 1 | E99: 208 | F99: =Source!V76 -> 0 | G99: ТрудМаш | H99: Трудозатраты машинистов | K99: 208 | L99: 22 | M99: 3 | O99: -1 | P99: =Source!DN76 -> 0 | W99: 0 | X99: 1 | Y99: 0 | Z99: 0 | AA99: 1 | AB99: 0
A100: 50 | B100: 0 | C100: 0 | D100: 1 | E100: 209 | F100: =ROUND(Source!W76,O100) -> 0 | G100: ТранспМат | H100: Транспорт материалов | K100: 209 | L100: 23 | M100: 3 | O100: 2 | P100: =ROUND(Source!DO76,O100) -> 0 | W100: 0 | X100: 1 | Y100: 0 | Z100: 0 | AA100: 1 | AB100: 0
A101: 50 | B101: 0 | C101: 0 | D101: 1 | E101: 233 | F101: =ROUND(Source!BD76,O101) -> 0 | G101: Перевозка | H101: Перевозка грузов | K101: 233 | L101: 24 | M101: 3 | O101: 2 | P101: =ROUND(Source!EV76,O101) -> 0 | W101: 0 | X101: 1 | Y101: 0 | Z101: 0 | AA101: 1 | AB101: 0
A102: 50 | B102: 0 | C102: 0 | D102: 1 | E102: 210 | F102: =ROUND(Source!X76,O102) -> 3147.77 | G102: НР | H102: Накладные расходы | K102: 210 | L102: 25 | M102: 3 | O102: 2 | P102: =ROUND(Source!DP76,O102) -> 173095.92 | W102: 3147.77 | X102: 1 | Y102: 3147.77 | Z102: 173095.92 | AA102: 1 | AB102: 173095.92
A103: 50 | B103: 0 | C103: 0 | D103: 1 | E103: 211 | F103: =ROUND(Source!Y76,O103) -> 1676.53 | G103: СмПриб | H103: Сметная прибыль | K103: 211 | L103: 26 | M103: 3 | O103: 2 | P103: =ROUND(Source!DQ76,O103) -> 92192.4 | W103: 1676.53 | X103: 1 | Y103: 1676.53 | Z103: 92192.4 | AA103: 1 | AB103: 92192.4
A104: 50 | B104: 0 | C104: 0 | D104: 1 | E104: 224 | F104: =ROUND(Source!AR76,O104) -> 58024.29 | G104: Всего | H104: Всего с НР и СП | K104: 224 | L104: 27 | M104: 3 | O104: 2 | P104: =ROUND(Source!EJ76,O104) -> 837051.57 | W104: 58024.29 | X104: 1 | Y104: 58024.29 | Z104: 837051.57 | AA104: 1 | AB104: 837051.57
A106: 51 | B106: =B12 -> 145 | C106: =A12 -> 1 | D106: =ROW(A12) -> 12 | F106: =IF(F12<>"",F12,"") -> 02-01-19 | G106: =IF(G12<>"",G12,"") -> 02-01-19 Вертикальный транспорт | H106: 0 | O106: =ROUND(O76,2) -> 53199.99 | P106: =ROUND(P76,2) -> 49495.8 | Q106: =ROUND(Q76,2) -> 303.71 | R106: =ROUND(R76,2) -> 21.01 | S106: =ROUND(S76,2) -> 3400.48 | T106: =ROUND(T76,2) -> 0 | U106: =U76 -> 252.13564 | V106: =V76 -> 0 | W106: =ROUND(W76,2) -> 0 | X106: =ROUND(X76,2) -> 3147.77 | Y106: =ROUND(Y76,2) -> 1676.53 | AO106: =ROUND(AO76,2) -> 0 | AP106: =ROUND(AP76,2) -> 48761.4 | AQ106: =ROUND(AQ76,2) -> 0 | AR106: =ROUND(AR76,2) -> 58024.29 | AS106: =ROUND(AS76,2) -> 0 | AT106: =ROUND(AT76,2) -> 9262.89 | AU106: =ROUND(AU76,2) -> 0 | AV106: =ROUND(AV76,2) -> 49495.8 | ... BD106: =ROUND(BD76,2) -> 0 | DG106: =ROUND(DG76,2) -> 571763.25 | DH106: =ROUND(DH76,2) -> 380775.54 | DI106: =ROUND(DI76,2) -> 3995.31 | DJ106: =ROUND(DJ76,2) -> 1155.34 | DK106: =ROUND(DK76,2) -> 186992.4 | DL106: =ROUND(DL76,2) -> 0 | DM106: =DM76 -> 252.13564 | DN106: =DN76 -> 0 | DO106: =ROUND(DO76,2) -> 0 | DP106: =ROUND(DP76,2) -> 173095.92 | DQ106: =ROUND(DQ76,2) -> 92192.4 | EG106: =ROUND(EG76,2) -> 0 | EH106: =ROUND(EH76,2) -> 373512.32 | EI106: =ROUND(EI76,2) -> 0 | EJ106: =ROUND(EJ76,2) -> 837051.57 | EK106: =ROUND(EK76,2) -> 0 | EL106: =ROUND(EL76,2) -> 463539.25 | EM106: =ROUND(EM76,2) -> 0 | EN106: =ROUND(EN76,2) -> 380775.54 | ... EV106: =ROUND(EV76,2) -> 0 | GX106: 0
A108: 50 | B108: 0 | C108: 0 | D108: 1 | E108: 201 | F108: =ROUND(Source!O106,O108) -> 53199.99 | G108: ПЗ | H108: Прямые затраты | K108: 201 | L108: 1 | M108: 3 | O108: 2 | P108: =ROUND(Source!DG106,O108) -> 571763.25 | W108: 53199.99 | X108: 1 | Y108: 53199.99 | Z108: 571763.25 | AA108: 1 | AB108: 571763.25
A109: 50 | B109: 0 | C109: 0 | D109: 1 | E109: 202 | F109: =ROUND(Source!P106,O109) -> 49495.8 | G109: СтМатОб | H109: Стоимость материальных ресурсов (всего) | K109: 202 | L109: 2 | M109: 3 | O109: 2 | P109: =ROUND(Source!DH106,O109) -> 380775.54 | W109: 49495.8 | X109: 1 | Y109: 49495.8 | Z109: 380775.54 | AA109: 1 | AB109: 380775.54
A110: 50 | B110: 0 | C110: 0 | D110: 1 | E110: 222 | F110: =ROUND(Source!AO106,O110) -> 0 | G110: СтМатОбЗак | H110: Стоимость материалов и оборудования заказчика | K110: 222 | L110: 3 | M110: 3 | O110: 2 | P110: =ROUND(Source!EG106,O110) -> 0 | W110: 0 | X110: 1 | Y110: 0 | Z110: 0 | AA110: 1 | AB110: 0
A111: 50 | B111: 0 | C111: 0 | D111: 1 | E111: 225 | F111: =ROUND(Source!AV106,O111) -> 49495.8 | G111: СтМатОбПод | H111: Стоимость материалов и оборудования подрядчика | K111: 225 | L111: 4 | M111: 3 | O111: 2 | P111: =ROUND(Source!EN106,O111) -> 380775.54 | W111: 49495.8 | X111: 1 | Y111: 49495.8 | Z111: 380775.54 | AA111: 1 | AB111: 380775.54
A112: 50 | B112: 0 | C112: 0 | D112: 1 | E112: 226 | F112: =ROUND(Source!AW106,O112) -> 734.4 | G112: СтМат | H112: Стоимость материалов (всего) | K112: 226 | L112: 5 | M112: 3 | O112: 2 | P112: =ROUND(Source!EO106,O112) -> 7263.22 | W112: 734.4 | X112: 1 | Y112: 734.4 | Z112: 7263.22 | AA112: 1 | AB112: 7263.22
A113: 50 | B113: 0 | C113: 0 | D113: 1 | E113: 227 | F113: =ROUND(Source!AX106,O113) -> 0 | G113: СтМатЗак | H113: Стоимость материалов заказчика | K113: 227 | L113: 6 | M113: 3 | O113: 2 | P113: =ROUND(Source!EP106,O113) -> 0 | W113: 0 | X113: 1 | Y113: 0 | Z113: 0 | AA113: 1 | AB113: 0
A114: 50 | B114: 0 | C114: 0 | D114: 1 | E114: 228 | F114: =ROUND(Source!AY106,O114) -> 734.4 | G114: СтМатПод | H114: Стоимость материалов подрядчика | K114: 228 | L114: 7 | M114: 3 | O114: 2 | P114: =ROUND(Source!EQ106,O114) -> 7263.22 | W114: 734.4 | X114: 1 | Y114: 734.4 | Z114: 7263.22 | AA114: 1 | AB114: 7263.22
A115: 50 | B115: 0 | C115: 0 | D115: 1 | E115: 216 | F115: =ROUND(Source!AP106,O115) -> 48761.4 | G115: Оборуд | H115: Стоимость оборудования (всего) | K115: 216 | L115: 8 | M115: 3 | O115: 2 | P115: =ROUND(Source!EH106,O115) -> 373512.32 | W115: 48761.4 | X115: 1 | Y115: 48761.4 | Z115: 373512.32 | AA115: 1 | AB115: 373512.32
A116: 50 | B116: 0 | C116: 0 | D116: 1 | E116: 223 | F116: =ROUND(Source!AQ106,O116) -> 0 | G116: ОборудЗак | H116: Стоимость оборудования заказчика | K116: 223 | L116: 9 | M116: 3 | O116: 2 | P116: =ROUND(Source!EI106,O116) -> 0 | W116: 0 | X116: 1 | Y116: 0 | Z116: 0 | AA116: 1 | AB116: 0
A117: 50 | B117: 0 | C117: 0 | D117: 1 | E117: 229 | F117: =ROUND(Source!AZ106,O117) -> 48761.4 | G117: ОборудПод | H117: Стоимость оборудования подрядчика | K117: 229 | L117: 10 | M117: 3 | O117: 2 | P117: =ROUND(Source!ER106,O117) -> 373512.32 | W117: 48761.4 | X117: 1 | Y117: 48761.4 | Z117: 373512.32 | AA117: 1 | AB117: 373512.32
A118: 50 | B118: 0 | C118: 0 | D118: 1 | E118: 203 | F118: =ROUND(Source!Q106,O118) -> 303.71 | G118: ЭММ | H118: Эксплуатация машин | K118: 203 | L118: 11 | M118: 3 | O118: 2 | P118: =ROUND(Source!DI106,O118) -> 3995.31 | W118: 303.71 | X118: 1 | Y118: 303.71 | Z118: 3995.31 | AA118: 1 | AB118: 3995.31
A119: 50 | B119: 0 | C119: 0 | D119: 1 | E119: 231 | F119: =ROUND(Source!BB106,O119) -> 0 | G119: ЭММсНРиСП | H119: Эксплуатация машин по ТСН-2001.16 | K119: 231 | L119: 12 | M119: 3 | O119: 2 | P119: =ROUND(Source!ET106,O119) -> 0 | W119: 0 | X119: 1 | Y119: 0 | Z119: 0 | AA119: 1 | AB119: 0
A120: 50 | B120: 0 | C120: 0 | D120: 1 | E120: 204 | F120: =ROUND(Source!R106,O120) -> 21.01 | G120: ЗПМ | H120: ЗП машинистов | K120: 204 | L120: 13 | M120: 3 | O120: 2 | P120: =ROUND(Source!DJ106,O120) -> 1155.34 | W120: 21.01 | X120: 1 | Y120: 21.01 | Z120: 1155.34 | AA120: 1 | AB120: 1155.34
A121: 50 | B121: 0 | C121: 0 | D121: 1 | E121: 205 | F121: =ROUND(Source!S106,O121) -> 3400.48 | G121: ОЗП | H121: Основная ЗП рабочих | K121: 205 | L121: 14 | M121: 3 | O121: 2 | P121: =ROUND(Source!DK106,O121) -> 186992.4 | W121: 3400.48 | X121: 1 | Y121: 3400.48 | Z121: 186992.4 | AA121: 1 | AB121: 186992.4
A122: 50 | B122: 0 | C122: 0 | D122: 1 | E122: 232 | F122: =ROUND(Source!BC106,O122) -> 0 | G122: ОЗПсНРиСП | H122: Основная ЗП рабочих по ТСН-2001.16 | K122: 232 | L122: 15 | M122: 3 | O122: 2 | P122: =ROUND(Source!EU106,O122) -> 0 | W122: 0 | X122: 1 | Y122: 0 | Z122: 0 | AA122: 1 | AB122: 0
A123: 50 | B123: 0 | C123: 0 | D123: 1 | E123: 214 | F123: =ROUND(Source!AS106,O123) -> 0 | G123: Строит | H123: Строительные работы с НР и СП | K123: 214 | L123: 16 | M123: 3 | O123: 2 | P123: =ROUND(Source!EK106,O123) -> 0 | W123: 0 | X123: 1 | Y123: 0 | Z123: 0 | AA123: 1 | AB123: 0
A124: 50 | B124: 0 | C124: 0 | D124: 1 | E124: 215 | F124: =ROUND(Source!AT106,O124) -> 9262.89 | G124: Монтаж | H124: Монтажные работы с НР и СП | K124: 215 | L124: 17 | M124: 3 | O124: 2 | P124: =ROUND(Source!EL106,O124) -> 463539.25 | W124: 9262.89 | X124: 1 | Y124: 9262.89 | Z124: 463539.25 | AA124: 1 | AB124: 463539.25
...

Sheet SourceObSm
A1: 0 | B1: Smeta.RU (495) 974-1589 | D1: _OBSM_ | F1: 0 | G1: 0 | H1: 0 | I1: Smeta.RU | K1: 1 | L1: 74561 | M1: 10 | N1: 11 | O1: 15 | P1: 0 | Q1: 2
A4: 1 | B4: 1 | C4: -1 | G4: Капитальный ремонт здания Государственного бюджетного общеобразовательного учреждения города Москвы «Школа № 236» по адресу: г. Москва, ул. Клязьминская, д. 7, к. 4. I этап | EC4: 0
A12: 1 | B12: 51 | C12: 0 | E12: 0 | F12: 02-01-19 | G12: 02-01-19 Вертикальный транспорт | I12: 0 | J12: 2024-00272-01-0-ВТ | K12: 0 | L12: 0 | M12: 4098 | O12: 0 | P12: 0 | Q12: 0 | R12: 0 | S12: 0 | T12: 1 | V12: 2 | AB12: Борисова Е.С. | BB12: 0 | BH12: Сметные нормы списания | BI12: Коды ОКП для ТСН-2001 МГЭ Дополнение 80 | BJ12: 1 | BK12: 1 | BL12: 0 | BM12: 0 | BN12: 1 | BO12: 0 | BP12: 6 | BQ12: 2 | BR12: 1 | BS12: 1 | BT12: 1 | BU12: 0 | BV12: 1 | BW12: 0 | BX12: 0 | BZ12: Типовой расчет для ТСН-2001 МГЭ, Дополнение 80, строительство | CA12: Территориальные сметные нормативы для Москвы ТСН-2001 (МГЭ), дополнение 80 | CB12: Территориальные сметные нормативы для Москвы ТСН-2001 (МГЭ), дополнение 80 | CC12: Территориальные сметные нормативы для Москвы ТСН-2001 (МГЭ), дополнение 80 | CD12: Территориальные сметные нормативы для Москвы ТСН-2001 (МГЭ), дополнение 80 | CE12: Поправки для ТСН-2001 от 03.02.2026 г. доп.80 | CF12: 0 | CG12: 0 | CH12: 10 | CK12: 80 | CQ12: Территориальные сметные нормативы для Москвы (ТСН-2001) | CR12: ТЕР | CS12: 41660 | CT12: 1 | CU12: 80 | CY12: 0 | EC12: 0
A14: 22 | B14: 1 | C14: 0 | D14: 59499000 | E14: 59499003 | F14: 2 | G14: 1
A16: 3 | B16: 1 | C16: 02-01-19 | D16: Вертикальный транспорт | E16: =ROUND((Source!P93)/1000,2) -> 0 | F16: =ROUND((Source!P94)/1000,2) -> 463.54 | G16: =ROUND((Source!P85)/1000,2) -> 373.51 | H16: =ROUND((Source!P95)/1000+(Source!P96)/1000,2) -> 0 | I16: =E16+F16+G16+H16 -> 837.05 | J16: =ROUND((Source!P91+Source!P90)/1000,2) -> 188.15 | K16: 952.54 | L16: 0 | M16: 0 | N16: =I16+L16+M16 -> 837.05 | T16: =ROUND((Source!F93)/1000,2) -> 0 | U16: =ROUND((Source!F94)/1000,2) -> 9.26 | V16: =ROUND((Source!F85)/1000,2) -> 48.76 | W16: =ROUND((Source!F95)/1000+(Source!F96)/1000,2) -> 0 | X16: =T16+U16+V16+W16 -> 58.02 | Y16: =ROUND((Source!F91+Source!F90)/1000,2) -> 3.42 | Z16: 102.7 | AA16: 0 | AB16: 0 | AC16: =X16+AA16+AB16 -> 58.02 | AI16: 2 | AJ16: -1 | AN16: 0 | AT16: 571763.25 | AU16: 380775.54 | AV16: 0 | AW16: 373512.32 | AX16: 0 | AY16: 3995.31 | AZ16: 1155.34 | BA16: 186992.4 | BB16: 0 | BC16: 463539.25 | BD16: 0 | BE16: 0 | BF16: 252.13564 | BG16: 0 | BH16: 0 | BI16: 173095.92 | BJ16: 92192.4 | BK16: 837051.57 | BR16: 53199.99 | BS16: 49495.8 | BT16: 0 | BU16: 48761.4 | BV16: 0 | BW16: 303.71 | BX16: 21.01 | BY16: 3400.48 | BZ16: 0 | CA16: 9262.89 | CB16: 0 | CC16: 0 | CD16: 252.13564 | CE16: 0 | CF16: 0 | CG16: 3147.77 | CH16: 1676.53 | CI16: 58024.29
A18: 51 | E18: 0 | F18: 463.54 | G18: 373.51 | H18: 0 | I18: 837.05 | J18: 188.15 | K18: 952.54 | L18: 0 | M18: 0 | N18: 837.05 | T18: 0 | U18: 9.26 | V18: 48.76 | W18: 0 | X18: 58.02 | Y18: 3.42 | Z18: 102.7 | AA18: 0 | AB18: 0 | AC18: 58.02
A20: 50 | B20: 0 | C20: 0 | D20: 1 | E20: 201 | F20: 571763.25 | G20: ПЗ | H20: Прямые затраты | K20: 201 | L20: 1 | M20: 3 | O20: 2 | P20: 53199.99
A21: 50 | B21: 0 | C21: 0 | D21: 1 | E21: 202 | F21: 380775.54 | G21: СтМатОб | H21: Стоимость материальных ресурсов (всего) | K21: 202 | L21: 2 | M21: 3 | O21: 2 | P21: 49495.8
A22: 50 | B22: 0 | C22: 0 | D22: 1 | E22: 222 | F22: 0 | G22: СтМатОбЗак | H22: Стоимость материалов и оборудования заказчика | K22: 222 | L22: 3 | M22: 3 | O22: 2 | P22: 0
A23: 50 | B23: 0 | C23: 0 | D23: 1 | E23: 225 | F23: 380775.54 | G23: СтМатОбПод | H23: Стоимость материалов и оборудования подрядчика | K23: 225 | L23: 4 | M23: 3 | O23: 2 | P23: 49495.8
A24: 50 | B24: 0 | C24: 0 | D24: 1 | E24: 226 | F24: 7263.22 | G24: СтМат | H24: Стоимость материалов (всего) | K24: 226 | L24: 5 | M24: 3 | O24: 2 | P24: 734.4
A25: 50 | B25: 0 | C25: 0 | D25: 1 | E25: 227 | F25: 0 | G25: СтМатЗак | H25: Стоимость материалов заказчика | K25: 227 | L25: 6 | M25: 3 | O25: 2 | P25: 0
A26: 50 | B26: 0 | C26: 0 | D26: 1 | E26: 228 | F26: 7263.22 | G26: СтМатПод | H26: Стоимость материалов подрядчика | K26: 228 | L26: 7 | M26: 3 | O26: 2 | P26: 734.4
A27: 50 | B27: 0 | C27: 0 | D27: 1 | E27: 216 | F27: 373512.32 | G27: Оборуд | H27: Стоимость оборудования (всего) | K27: 216 | L27: 8 | M27: 3 | O27: 2 | P27: 48761.4
A28: 50 | B28: 0 | C28: 0 | D28: 1 | E28: 223 | F28: 0 | G28: ОборудЗак | H28: Стоимость оборудования заказчика | K28: 223 | L28: 9 | M28: 3 | O28: 2 | P28: 0
A29: 50 | B29: 0 | C29: 0 | D29: 1 | E29: 229 | F29: 373512.32 | G29: ОборудПод | H29: Стоимость оборудования подрядчика | K29: 229 | L29: 10 | M29: 3 | O29: 2 | P29: 48761.4
A30: 50 | B30: 0 | C30: 0 | D30: 1 | E30: 203 | F30: 3995.31 | G30: ЭММ | H30: Эксплуатация машин | K30: 203 | L30: 11 | M30: 3 | O30: 2 | P30: 303.71
A31: 50 | B31: 0 | C31: 0 | D31: 1 | E31: 231 | F31: 0 | G31: ЭММсНРиСП | H31: Эксплуатация машин по ТСН-2001.16 | K31: 231 | L31: 12 | M31: 3 | O31: 2 | P31: 0
... A46: 50 | B46: 0 | C46: 0 | D46: 1 | E46: 224 | F46: 837051.57 | G46: Всего | H46: Всего с НР и СП | K46: 224 | L46: 27 | M46: 3 | O46: 2 | P46: 58024.29
A48: -1
A51: 75 | B51: Текущий уровень цен | C51: 2025 | D51: 0 | E51: 9 | G51: 0 | H51: 1 | I51: 1 | J51: 3 | K51: 0 | L51: 0 | M51: 1 | N51: 59499000 | O51: 1
A52: 1 | B52: Сборник индексов | C52: Коэффициенты к ТСН-2001 МГЭ Дополнение 80, строительство | D52: 2025 | E52: 9 | F52: 1 | G52: 1 | H52: 0 | I52: 2 | J52: 1 | K52: 9.88 | L52: 7.66 | M52: 1 | N52: 1 | O52: 9.88 | P52: 7.66 | Q52: 1 | AA52: 217/80 | AN52: 59499001
A53: 1 | B53: Сборник индексов | C53: Коэффициенты к ТСН-2001.13-2 Дополнение 46 | D53: 2025 | E53: 7 | F53: 1 | G53: 1 | H53: 0 | I53: 2 | J53: 1 | K53: 1 | L53: 1 | M53: 1 | N53: 1 | O53: 1 | P53: 1 | Q53: 1 | AA53: 62/46 | AN53: 59499002
A54: 75 | B54: Базовый уровень цен | C54: 2000 | D54: 0 | E54: 1 | G54: 0 | H54: 1 | I54: 1 | J54: 3 | K54: 0 | L54: 0 | M54: 0 | N54: 59499003 | O54: 2
A55: 1 | B55: Сборник индексов | C55: Коэффициенты к ТСН-2001 МГЭ Дополнение 80, строительство | D55: 2000 | E55: 1 | F55: 1 | G55: 1 | H55: 0 | I55: 2 | J55: 1 | K55: 1 | L55: 1 | M55: 1 | N55: 1 | O55: 1 | P55: 1 | Q55: 1 | AA55: 0 | AN55: 59499004

Sheet SmtRes
A1: =ROW(Source!A29) -> 29 | B1: 59499003 | C1: 59499118 | D1: 58532980 | E1: 1080 | F1: 1 | G1: 1080 | H1: 1 | I1: 9999990008 | K1: Трудозатраты рабочих | L1: 1191 | N1: 1013 | O1: чел.-ч. | P1: чел.-ч. | Q1: 1 | W1: 0 | X1: 476480486 | Y1: =((AT1*0.3)*1.1) -> 114.18 | AA1: 0 | AB1: 0 | AC1: 0 | AD1: 0 | AE1: 0 | AF1: 0 | AG1: 0 | AH1: 0 | AI1: 1 | AJ1: 1 | AK1: 1 | AL1: 1 | AM1: -2 | AN1: 0 | AO1: 1 | AP1: 1 | AQ1: 0 | AR1: 0 | AT1: 346 | AU1: *0,3)*1,1 | AV1: 1 | AW1: 2 | AX1: 59499143 | AY1: 1 | AZ1: 0 | BA1: 1 | BB1: 0 | BC1: 0 | BD1: 0 | BE1: 0 | BF1: 0 | BG1: 0 | BH1: 0 | BI1: 0 | BJ1: 0 | BK1: 0 | BL1: 0 | BM1: 0 | BN1: 0 | BO1: 0 | BP1: 0 | BQ1: 0 | BR1: 0 | BS1: 0 | BT1: 0 | BU1: 0 | BV1: 0 | BW1: 0 | CU1: =ROUND(AT1*Source!I29*AH1*AL1,2) -> 0 | CV1: =ROUND(Y1*Source!I29,9) -> 114.18 | CW1: 0 | CX1: =ROUND(Y1*Source!I29,9) -> 114.18 | CY1: =AD1 -> 0 | CZ1: =AH1 -> 0 | DA1: =AL1 -> 1 | DB1: =ROUND(((ROUND(AT1*CZ1,2)*0.3)*1.1),6) -> 0 | DC1: =ROUND(((ROUND(AT1*AG1,2)*0.3)*1.1),6) -> 0 | DF1: =ROUND(ROUND(AE1,2)*CX1,2) -> 0 | DG1: =ROUND(ROUND(AF1,2)*CX1,2) -> 0 | DH1: =ROUND(ROUND(AG1,2)*CX1,2) -> 0 | DI1: =ROUND(ROUND(AH1,2)*CX1,2) -> 0 | DJ1: =DI1 -> 0 | DK1: 0 | DM1: 0 | DO1: 0
A2: =ROW(Source!A29) -> 29 | B2: 59499003 | C2: 59499118 | D2: 58537982 | E2: 1080 | F2: 1 | G2: 1080 | H2: 3 | I2: 9999990002 | K2: Масса оборудования | L2: 1348 | N2: 1009 | O2: т | P2: т | Q2: 1000 | W2: 0 | X2: -783086922 | Y2: =((AT2*0)*1) -> 0 | AA2: 0 | AB2: 0 | AC2: 0 | AD2: 0 | AE2: 0 | AF2: 0 | AG2: 0 | AH2: 0 | AI2: 1 | AJ2: 1 | AK2: 1 | AL2: 1 | AM2: -2 | AN2: 0 | AO2: 1 | AP2: 1 | AQ2: 0 | AR2: 0 | AT2: 1.5 | AU2: *0)*1 | AV2: 0 | AW2: 2 | AX2: 59499144 | AY2: 1 | AZ2: 0 | BA2: 2 | BB2: 0 | BC2: 0 | BD2: 0 | BE2: 0 | BF2: 0 | BG2: 0 | BH2: 0 | BI2: 0 | BJ2: 0 | BK2: 0 | BL2: 0 | BM2: 0 | BN2: 0 | BO2: 0 | BP2: 0 | BQ2: 0 | BR2: 0 | BS2: 0 | BT2: 0 | BU2: 0 | BV2: 0 | BW2: 0 | CV2: 0 | CW2: 0 | CX2: =ROUND(Y2*Source!I29,9) -> 0 | CY2: =AA2 -> 0 | CZ2: =AE2 -> 0 | DA2: =AI2 -> 1 | DB2: =ROUND(((ROUND(AT2*CZ2,2)*0)*1),6) -> 0 | DC2: =ROUND(((ROUND(AT2*AG2,2)*0)*1),6) -> 0 | DF2: =ROUND(ROUND(AE2,2)*CX2,2) -> 0 | DG2: =ROUND(ROUND(AF2,2)*CX2,2) -> 0 | DH2: =ROUND(ROUND(AG2,2)*CX2,2) -> 0 | DI2: =ROUND(ROUND(AH2,2)*CX2,2) -> 0 | DJ2: =DF2 -> 0 | DK2: 0 | DM2: 0 | DO2: 0
A3: =ROW(Source!A30) -> 30 | B3: 59499000 | C3: 59499118 | D3: 58532980 | E3: 1080 | F3: 1 | G3: 1080 | H3: 1 | I3: 9999990008 | K3: Трудозатраты рабочих | L3: 1191 | N3: 1013 | O3: чел.-ч. | P3: чел.-ч. | Q3: 1 | W3: 0 | X3: 476480486 | Y3: =((AT3*0.3)*1.1) -> 114.18 | AA3: 0 | AB3: 0 | AC3: 0 | AD3: 0 | AE3: 0 | AF3: 0 | AG3: 0 | AH3: 0 | AI3: 1 | AJ3: 1 | AK3: 1 | AL3: 1 | AM3: 5 | AN3: 0 | AO3: 1 | AP3: 1 | AQ3: 0 | AR3: 0 | AT3: 346 | AU3: *0,3)*1,1 | AV3: 1 | AW3: 2 | AX3: 59499143 | AY3: 1 | AZ3: 0 | BA3: 3 | BB3: 0 | BC3: 0 | BD3: 0 | BE3: 0 | BF3: 0 | BG3: 0 | BH3: 0 | BI3: 0 | BJ3: 0 | BK3: 0 | BL3: 0 | BM3: 0 | BN3: 0 | BO3: 0 | BP3: 0 | BQ3: 0 | BR3: 0 | BS3: 0 | BT3: 0 | BU3: 0 | BV3: 0 | BW3: 0 | CU3: =ROUND(AT3*Source!I30*AH3*AL3,2) -> 0 | CV3: =ROUND(Y3*Source!I30,9) -> 114.18 | CW3: 0 | CX3: =ROUND(Y3*Source!I30,9) -> 114.18 | CY3: =AD3 -> 0 | CZ3: =AH3 -> 0 | DA3: =AL3 -> 1 | DB3: =ROUND(((ROUND(AT3*CZ3,2)*0.3)*1.1),6) -> 0 | DC3: =ROUND(((ROUND(AT3*AG3,2)*0.3)*1.1),6) -> 0 | DF3: =ROUND(ROUND(AE3,2)*CX3,2) -> 0 | DG3: =ROUND(ROUND(AF3,2)*CX3,2) -> 0 | DH3: =ROUND(ROUND(AG3,2)*CX3,2) -> 0 | DI3: =ROUND(ROUND(AH3,2)*CX3,2) -> 0 | DJ3: =DI3 -> 0 | DK3: 0 | DM3: 0 | DO3: 0
A4: =ROW(Source!A30) -> 30 | B4: 59499000 | C4: 59499118 | D4: 58537982 | E4: 1080 | F4: 1 | G4: 1080 | H4: 3 | I4: 9999990002 | K4: Масса оборудования | L4: 1348 | N4: 1009 | O4: т | P4: т | Q4: 1000 | W4: 0 | X4: -783086922 | Y4: =((AT4*0)*1) -> 0 | AA4: 0 | AB4: 0 | AC4: 0 | AD4: 0 | AE4: 0 | AF4: 0 | AG4: 0 | AH4: 0 | AI4: 9.88 | AJ4: 1 | AK4: 1 | AL4: 1 | AM4: 5 | AN4: 0 | AO4: 1 | AP4: 1 | AQ4: 0 | AR4: 0 | AT4: 1.5 | AU4: *0)*1 | AV4: 0 | AW4: 2 | AX4: 59499144 | AY4: 1 | AZ4: 0 | BA4: 4 | BB4: 0 | BC4: 0 | BD4: 0 | BE4: 0 | BF4: 0 | BG4: 0 | BH4: 0 | BI4: 0 | BJ4: 0 | BK4: 0 | BL4: 0 | BM4: 0 | BN4: 0 | BO4: 0 | BP4: 0 | BQ4: 0 | BR4: 0 | BS4: 0 | BT4: 0 | BU4: 0 | BV4: 0 | BW4: 0 | CV4: 0 | CW4: 0 | CX4: =ROUND(Y4*Source!I30,9) -> 0 | CY4: =AA4 -> 0 | CZ4: =AE4 -> 0 | DA4: =AI4 -> 9.88 | DB4: =ROUND(((ROUND(AT4*CZ4,2)*0)*1),6) -> 0 | DC4: =ROUND(((ROUND(AT4*AG4,2)*0)*1),6) -> 0 | DF4: =ROUND(ROUND(AE4*AI4,2)*CX4,2) -> 0 | DG4: =ROUND(ROUND(AF4,2)*CX4,2) -> 0 | DH4: =ROUND(ROUND(AG4,2)*CX4,2) -> 0 | DI4: =ROUND(ROUND(AH4,2)*CX4,2) -> 0 | DJ4: =DF4 -> 0 | DK4: 0 | DM4: 0 | DO4: 0
A5: =ROW(Source!A31) -> 31 | B5: 59499003 | C5: 59499123 | D5: 58532980 | E5: 1080 | F5: 1 | G5: 1080 | H5: 1 | I5: 9999990008 | K5: Трудозатраты рабочих | L5: 1191 | N5: 1013 | O5: чел.-ч. | P5: чел.-ч. | Q5: 1 | W5: 0 | X5: 476480486 | Y5: =((AT5*0.3)*1.1) -> 7.425 | AA5: 0 | AB5: 0 | AC5: 0 | AD5: 0 | AE5: 0 | AF5: 0 | AG5: 0 | AH5: 0 | AI5: 1 | AJ5: 1 | AK5: 1 | AL5: 1 | AM5: -2 | AN5: 0 | AO5: 1 | AP5: 1 | AQ5: 0 | AR5: 0 | AT5: 22.5 | AU5: *0,3)*1,1 | AV5: 1 | AW5: 2 | AX5: 59499145 | AY5: 1 | AZ5: 0 | BA5: 5 | BB5: 0 | BC5: 0 | BD5: 0 | BE5: 0 | BF5: 0 | BG5: 0 | BH5: 0 | BI5: 0 | BJ5: 0 | BK5: 0 | BL5: 0 | BM5: 0 | BN5: 0 | BO5: 0 | BP5: 0 | BQ5: 0 | BR5: 0 | BS5: 0 | BT5: 0 | BU5: 0 | BV5: 0 | BW5: 0 | CU5: =ROUND(AT5*Source!I31*AH5*AL5,2) -> 0 | CV5: =ROUND(Y5*Source!I31,9) -> -29.7 | CW5: 0 | CX5: =ROUND(Y5*Source!I31,9) -> -29.7 | CY5: =AD5 -> 0 | CZ5: =AH5 -> 0 | DA5: =AL5 -> 1 | DB5: =ROUND(((ROUND(AT5*CZ5,2)*0.3)*1.1),6) -> 0 | DC5: =ROUND(((ROUND(AT5*AG5,2)*0.3)*1.1),6) -> 0 | DF5: =ROUND(ROUND(AE5,2)*CX5,2) -> 0 | DG5: =ROUND(ROUND(AF5,2)*CX5,2) -> 0 | DH5: =ROUND(ROUND(AG5,2)*CX5,2) -> 0 | DI5: =ROUND(ROUND(AH5,2)*CX5,2) -> 0 | DJ5: =DI5 -> 0 | DK5: 0 | DM5: 0 | DO5: 0
A6: =ROW(Source!A32) -> 32 | B6: 59499000 | C6: 59499123 | D6: 58532980 | E6: 1080 | F6: 1 | G6: 1080 | H6: 1 | I6: 9999990008 | K6: Трудозатраты рабочих | L6: 1191 | N6: 1013 | O6: чел.-ч. | P6: чел.-ч. | Q6: 1 | W6: 0 | X6: 476480486 | Y6: =((AT6*0.3)*1.1) -> 7.425 | AA6: 0 | AB6: 0 | AC6: 0 | AD6: 0 | AE6: 0 | AF6: 0 | AG6: 0 | AH6: 0 | AI6: 1 | AJ6: 1 | AK6: 1 | AL6: 1 | AM6: 5 | AN6: 0 | AO6: 1 | AP6: 1 | AQ6: 0 | AR6: 0 | AT6: 22.5 | AU6: *0,3)*1,1 | AV6: 1 | AW6: 2 | AX6: 59499145 | AY6: 1 | AZ6: 0 | BA6: 6 | BB6: 0 | BC6: 0 | BD6: 0 | BE6: 0 | BF6: 0 | BG6: 0 | BH6: 0 | BI6: 0 | BJ6: 0 | BK6: 0 | BL6: 0 | BM6: 0 | BN6: 0 | BO6: 0 | BP6: 0 | BQ6: 0 | BR6: 0 | BS6: 0 | BT6: 0 | BU6: 0 | BV6: 0 | BW6: 0 | CU6: =ROUND(AT6*Source!I32*AH6*AL6,2) -> 0 | CV6: =ROUND(Y6*Source!I32,9) -> -29.7 | CW6: 0 | CX6: =ROUND(Y6*Source!I32,9) -> -29.7 | CY6: =AD6 -> 0 | CZ6: =AH6 -> 0 | DA6: =AL6 -> 1 | DB6: =ROUND(((ROUND(AT6*CZ6,2)*0.3)*1.1),6) -> 0 | DC6: =ROUND(((ROUND(AT6*AG6,2)*0.3)*1.1),6) -> 0 | DF6: =ROUND(ROUND(AE6,2)*CX6,2) -> 0 | DG6: =ROUND(ROUND(AF6,2)*CX6,2) -> 0 | DH6: =ROUND(ROUND(AG6,2)*CX6,2) -> 0 | DI6: =ROUND(ROUND(AH6,2)*CX6,2) -> 0 | DJ6: =DI6 -> 0 | DK6: 0 | DM6: 0 | DO6: 0
A7: =ROW(Source!A33) -> 33 | B7: 59499003 | C7: 59499126 | D7: 58532980 | E7: 1080 | F7: 1 | G7: 1080 | H7: 1 | I7: 9999990008 | K7: Трудозатраты рабочих | L7: 1191 | N7: 1013 | O7: чел.-ч. | P7: чел.-ч. | Q7: 1 | W7: 0 | X7: 476480486 | Y7: =((AT7*0.3)*1.1) -> 2.079 | AA7: 0 | AB7: 0 | AC7: 0 | AD7: 0 | AE7: 0 | AF7: 0 | AG7: 0 | AH7: 0 | AI7: 1 | AJ7: 1 | AK7: 1 | AL7: 1 | AM7: -2 | AN7: 0 | AO7: 1 | AP7: 1 | AQ7: 0 | AR7: 0 | AT7: 6.3 | AU7: *0,3)*1,1 | AV7: 1 | AW7: 2 | AX7: 59499146 | AY7: 1 | AZ7: 0 | BA7: 7 | BB7: 0 | BC7: 0 | BD7: 0 | BE7: 0 | BF7: 0 | BG7: 0 | BH7: 0 | BI7: 0 | BJ7: 0 | BK7: 0 | BL7: 0 | BM7: 0 | BN7: 0 | BO7: 0 | BP7: 0 | BQ7: 0 | BR7: 0 | BS7: 0 | BT7: 0 | BU7: 0 | BV7: 0 | BW7: 0 | CU7: =ROUND(AT7*Source!I33*AH7*AL7,2) -> 0 | CV7: =ROUND(Y7*Source!I33,9) -> -31.01868 | CW7: 0 | CX7: =ROUND(Y7*Source!I33,9) -> -31.01868 | CY7: =AD7 -> 0 | CZ7: =AH7 -> 0 | DA7: =AL7 -> 1 | DB7: =ROUND(((ROUND(AT7*CZ7,2)*0.3)*1.1),6) -> 0 | DC7: =ROUND(((ROUND(AT7*AG7,2)*0.3)*1.1),6) -> 0 | DF7: =ROUND(ROUND(AE7,2)*CX7,2) -> 0 | DG7: =ROUND(ROUND(AF7,2)*CX7,2) -> 0 | DH7: =ROUND(ROUND(AG7,2)*CX7,2) -> 0 | DI7: =ROUND(ROUND(AH7,2)*CX7,2) -> 0 | DJ7: =DI7 -> 0 | DK7: 0 | DM7: 0 | DO7: 0
A8: =ROW(Source!A34) -> 34 | B8: 59499000 | C8: 59499126 | D8: 58532980 | E8: 1080 | F8: 1 | G8: 1080 | H8: 1 | I8: 9999990008 | K8: Трудозатраты рабочих | L8: 1191 | N8: 1013 | O8: чел.-ч. | P8: чел.-ч. | Q8: 1 | W8: 0 | X8: 476480486 | Y8: =((AT8*0.3)*1.1) -> 2.079 | AA8: 0 | AB8: 0 | AC8: 0 | AD8: 0 | AE8: 0 | AF8: 0 | AG8: 0 | AH8: 0 | AI8: 1 | AJ8: 1 | AK8: 1 | AL8: 1 | AM8: 5 | AN8: 0 | AO8: 1 | AP8: 1 | AQ8: 0 | AR8: 0 | AT8: 6.3 | AU8: *0,3)*1,1 | AV8: 1 | AW8: 2 | AX8: 59499146 | AY8: 1 | AZ8: 0 | BA8: 8 | BB8: 0 | BC8: 0 | BD8: 0 | BE8: 0 | BF8: 0 | BG8: 0 | BH8: 0 | BI8: 0 | BJ8: 0 | BK8: 0 | BL8: 0 | BM8: 0 | BN8: 0 | BO8: 0 | BP8: 0 | BQ8: 0 | BR8: 0 | BS8: 0 | BT8: 0 | BU8: 0 | BV8: 0 | BW8: 0 | CU8: =ROUND(AT8*Source!I34*AH8*AL8,2) -> 0 | CV8: =ROUND(Y8*Source!I34,9) -> -31.01868 | CW8: 0 | CX8: =ROUND(Y8*Source!I34,9) -> -31.01868 | CY8: =AD8 -> 0 | CZ8: =AH8 -> 0 | DA8: =AL8 -> 1 | DB8: =ROUND(((ROUND(AT8*CZ8,2)*0.3)*1.1),6) -> 0 | DC8: =ROUND(((ROUND(AT8*AG8,2)*0.3)*1.1),6) -> 0 | DF8: =ROUND(ROUND(AE8,2)*CX8,2) -> 0 | DG8: =ROUND(ROUND(AF8,2)*CX8,2) -> 0 | DH8: =ROUND(ROUND(AG8,2)*CX8,2) -> 0 | DI8: =ROUND(ROUND(AH8,2)*CX8,2) -> 0 | DJ8: =DI8 -> 0 | DK8: 0 | DM8: 0 | DO8: 0
A9: =ROW(Source!A36) -> 36 | B9: 59499003 | C9: 59499130 | D9: 58532980 | E9: 1080 | F9: 1 | G9: 1080 | H9: 1 | I9: 9999990008 | K9: Трудозатраты рабочих | L9: 1191 | N9: 1013 | O9: чел.-ч. | P9: чел.-ч. | Q9: 1 | W9: 0 | X9: 476480486 | Y9: =(AT9*1.1) -> 380.6 | AA9: 0 | AB9: 0 | AC9: 0 | AD9: 0 | AE9: 0 | AF9: 0 | AG9: 0 | AH9: 0 | AI9: 1 | AJ9: 1 | AK9: 1 | AL9: 1 | AM9: -2 | AN9: 0 | AO9: 1 | AP9: 1 | AQ9: 0 | AR9: 0 | AT9: 346 | AU9: *1,1 | AV9: 1 | AW9: 2 | AX9: 59499147 | AY9: 1 | AZ9: 6144 | BA9: 9 | BB9: 0 | BC9: 0 | BD9: 0 | BE9: 0 | BF9: 0 | BG9: 0 | BH9: 0 | BI9: 0 | BJ9: 0 | BK9: 0 | BL9: 0 | BM9: 0 | BN9: 0 | BO9: 0 | BP9: 0 | BQ9: 0 | BR9: 0 | BS9: 0 | BT9: 0 | BU9: 0 | BV9: 0 | BW9: 0 | CU9: =ROUND(AT9*Source!I36*AH9*AL9,2) -> 0 | CV9: =ROUND(Y9*Source!I36,9) -> 380.6 | CW9: 0 | CX9: =ROUND(Y9*Source!I36,9) -> 380.6 | CY9: =AD9 -> 0 | CZ9: =AH9 -> 0 | DA9: =AL9 -> 1 | DB9: =ROUND((ROUND(AT9*CZ9,2)*1.1),6) -> 0 | DC9: =ROUND((ROUND(AT9*AG9,2)*1.1),6) -> 0 | DF9: =ROUND(ROUND(AE9,2)*CX9,2) -> 0 | DG9: =ROUND(ROUND(AF9,2)*CX9,2) -> 0 | DH9: =ROUND(ROUND(AG9,2)*CX9,2) -> 0 | DI9: =ROUND(ROUND(AH9,2)*CX9,2) -> 0 | DJ9: =DI9 -> 0 | DK9: 0 | DM9: 0 | DO9: 0
A10: =ROW(Source!A36) -> 36 | B10: 59499003 | C10: 59499130 | D10: 58537982 | E10: 1080 | F10: 1 | G10: 1080 | H10: 3 | I10: 9999990002 | K10: Масса оборудования | L10: 1348 | N10: 1009 | O10: т | P10: т | Q10: 1000 | W10: 0 | X10: -783086922 | Y10: =(AT10*1) -> 1.5 | AA10: 0 | AB10: 0 | AC10: 0 | AD10: 0 | AE10: 0 | AF10: 0 | AG10: 0 | AH10: 0 | AI10: 1 | AJ10: 1 | AK10: 1 | AL10: 1 | AM10: -2 | AN10: 0 | AO10: 1 | AP10: 1 | AQ10: 0 | AR10: 0 | AT10: 1.5 | AU10: *1 | AV10: 0 | AW10: 2 | AX10: 59499148 | AY10: 1 | AZ10: 0 | BA10: 10 | BB10: 0 | BC10: 0 | BD10: 0 | BE10: 0 | BF10: 0 | BG10: 0 | BH10: 0 | BI10: 0 | BJ10: 0 | BK10: 0 | BL10: 0 | BM10: 0 | BN10: 0 | BO10: 0 | BP10: 0 | BQ10: 0 | BR10: 0 | BS10: 0 | BT10: 0 | BU10: 0 | BV10: 0 | BW10: 0 | CV10: 0 | CW10: 0 | CX10: =ROUND(Y10*Source!I36,9) -> 1.5 | CY10: =AA10 -> 0 | CZ10: =AE10 -> 0 | DA10: =AI10 -> 1 | DB10: =ROUND((ROUND(AT10*CZ10,2)*1),6) -> 0 | DC10: =ROUND((ROUND(AT10*AG10,2)*1),6) -> 0 | DF10: =ROUND(ROUND(AE10,2)*CX10,2) -> 0 | DG10: =ROUND(ROUND(AF10,2)*CX10,2) -> 0 | DH10: =ROUND(ROUND(AG10,2)*CX10,2) -> 0 | DI10: =ROUND(ROUND(AH10,2)*CX10,2) -> 0 | DJ10: =DF10 -> 0 | DK10: 0 | DM10: 0 | DO10: 0
A11: =ROW(Source!A37) -> 37 | B11: 59499000 | C11: 59499130 | D11: 58532980 | E11: 1080 | F11: 1 | G11: 1080 | H11: 1 | I11: 9999990008 | K11: Трудозатраты рабочих | L11: 1191 | N11: 1013 | O11: чел.-ч. | P11: чел.-ч. | Q11: 1 | W11: 0 | X11: 476480486 | Y11: =(AT11*1.1) -> 380.6 | AA11: 0 | AB11: 0 | AC11: 0 | AD11: 0 | AE11: 0 | AF11: 0 | AG11: 0 | AH11: 0 | AI11: 1 | AJ11: 1 | AK11: 1 | AL11: 1 | AM11: 5 | AN11: 0 | AO11: 1 | AP11: 1 | AQ11: 0 | AR11: 0 | AT11: 346 | AU11: *1,1 | AV11: 1 | AW11: 2 | AX11: 59499147 | AY11: 1 | AZ11: 6144 | BA11: 11 | BB11: 0 | BC11: 0 | BD11: 0 | BE11: 0 | BF11: 0 | BG11: 0 | BH11: 0 | BI11: 0 | BJ11: 0 | BK11: 0 | BL11: 0 | BM11: 0 | BN11: 0 | BO11: 0 | BP11: 0 | BQ11: 0 | BR11: 0 | BS11: 0 | BT11: 0 | BU11: 0 | BV11: 0 | BW11: 0 | CU11: =ROUND(AT11*Source!I37*AH11*AL11,2) -> 0 | CV11: =ROUND(Y11*Source!I37,9) -> 380.6 | CW11: 0 | CX11: =ROUND(Y11*Source!I37,9) -> 380.6 | CY11: =AD11 -> 0 | CZ11: =AH11 -> 0 | DA11: =AL11 -> 1 | DB11: =ROUND((ROUND(AT11*CZ11,2)*1.1),6) -> 0 | DC11: =ROUND((ROUND(AT11*AG11,2)*1.1),6) -> 0 | DF11: =ROUND(ROUND(AE11,2)*CX11,2) -> 0 | DG11: =ROUND(ROUND(AF11,2)*CX11,2) -> 0 | DH11: =ROUND(ROUND(AG11,2)*CX11,2) -> 0 | DI11: =ROUND(ROUND(AH11,2)*CX11,2) -> 0 | DJ11: =DI11 -> 0 | DK11: 0 | DM11: 0 | DO11: 0
A12: =ROW(Source!A37) -> 37 | B12: 59499000 | C12: 59499130 | D12: 58537982 | E12: 1080 | F12: 1 | G12: 1080 | H12: 3 | I12: 9999990002 | K12: Масса оборудования | L12: 1348 | N12: 1009 | O12: т | P12: т | Q12: 1000 | W12: 0 | X12: -783086922 | Y12: =(AT12*1) -> 1.5 | AA12: 0 | AB12: 0 | AC12: 0 | AD12: 0 | AE12: 0 | AF12: 0 | AG12: 0 | AH12: 0 | AI12: 9.88 | AJ12: 1 | AK12: 1 | AL12: 1 | AM12: 5 | AN12: 0 | AO12: 1 | AP12: 1 | AQ12: 0 | AR12: 0 | AT12: 1.5 | AU12: *1 | AV12: 0 | AW12: 2 | AX12: 59499148 | AY12: 1 | AZ12: 0 | BA12: 12 | BB12: 0 | BC12: 0 | BD12: 0 | BE12: 0 | BF12: 0 | BG12: 0 | BH12: 0 | BI12: 0 | BJ12: 0 | BK12: 0 | BL12: 0 | BM12: 0 | BN12: 0 | BO12: 0 | BP12: 0 | BQ12: 0 | BR12: 0 | BS12: 0 | BT12: 0 | BU12: 0 | BV12: 0 | BW12: 0 | CV12: 0 | CW12: 0 | CX12: =ROUND(Y12*Source!I37,9) -> 1.5 | CY12: =AA12 -> 0 | CZ12: =AE12 -> 0 | DA12: =AI12 -> 9.88 | DB12: =ROUND((ROUND(AT12*CZ12,2)*1),6) -> 0 | DC12: =ROUND((ROUND(AT12*AG12,2)*1),6) -> 0 | DF12: =ROUND(ROUND(AE12*AI12,2)*CX12,2) -> 0 | DG12: =ROUND(ROUND(AF12,2)*CX12,2) -> 0 | DH12: =ROUND(ROUND(AG12,2)*CX12,2) -> 0 | DI12: =ROUND(ROUND(AH12,2)*CX12,2) -> 0 | DJ12: =DF12 -> 0 | DK12: 0 | DM12: 0 | DO12: 0
A13: =ROW(Source!A38) -> 38 | B13: 59499003 | C13: 59499135 | D13: 58532980 | E13: 1080 | F13: 1 | G13: 1080 | H13: 1 | I13: 9999990008 | K13: Трудозатраты рабочих | L13: 1191 | N13: 1013 | O13: чел.-ч. | P13: чел.-ч. | Q13: 1 | W13: 0 | X13: 476480486 | Y13: =(AT13*1.1) -> 24.75 | AA13: 0 | AB13: 0 | AC13: 0 | AD13: 0 | AE13: 0 | AF13: 0 | AG13: 0 | AH13: 0 | AI13: 1 | AJ13: 1 | AK13: 1 | AL13: 1 | AM13: -2 | AN13: 0 | AO13: 1 | AP13: 1 | AQ13: 0 | AR13: 0 | AT13: 22.5 | AU13: *1,1 | AV13: 1 | AW13: 2 | AX13: 59499149 | AY13: 1 | AZ13: 6144 | BA13: 13 | BB13: 0 | BC13: 0 | BD13: 0 | BE13: 0 | BF13: 0 | BG13: 0 | BH13: 0 | BI13: 0 | BJ13: 0 | BK13: 0 | BL13: 0 | BM13: 0 | BN13: 0 | BO13: 0 | BP13: 0 | BQ13: 0 | BR13: 0 | BS13: 0 | BT13: 0 | BU13: 0 | BV13: 0 | BW13: 0 | CU13: =ROUND(AT13*Source!I38*AH13*AL13,2) -> 0 | CV13: =ROUND(Y13*Source!I38,9) -> -99 | CW13: 0 | CX13: =ROUND(Y13*Source!I38,9) -> -99 | CY13: =AD13 -> 0 | CZ13: =AH13 -> 0 | DA13: =AL13 -> 1 | DB13: =ROUND((ROUND(AT13*CZ13,2)*1.1),6) -> 0 | DC13: =ROUND((ROUND(AT13*AG13,2)*1.1),6) -> 0 | DF13: =ROUND(ROUND(AE13,2)*CX13,2) -> 0 | DG13: =ROUND(ROUND(AF13,2)*CX13,2) -> 0 | DH13: =ROUND(ROUND(AG13,2)*CX13,2) -> 0 | DI13: =ROUND(ROUND(AH13,2)*CX13,2) -> 0 | DJ13: =DI13 -> 0 | DK13: 0 | DM13: 0 | DO13: 0
A14: =ROW(Source!A39) -> 39 | B14: 59499000 | C14: 59499135 | D14: 58532980 | E14: 1080 | F14: 1 | G14: 1080 | H14: 1 | I14: 9999990008 | K14: Трудозатраты рабочих | L14: 1191 | N14: 1013 | O14: чел.-ч. | P14: чел.-ч. | Q14: 1 | W14: 0 | X14: 476480486 | Y14: =(AT14*1.1) -> 24.75 | AA14: 0 | AB14: 0 | AC14: 0 | AD14: 0 | AE14: 0 | AF14: 0 | AG14: 0 | AH14: 0 | AI14: 1 | AJ14: 1 | AK14: 1 | AL14: 1 | AM14: 5 | AN14: 0 | AO14: 1 | AP14: 1 | AQ14: 0 | AR14: 0 | AT14: 22.5 | AU14: *1,1 | AV14: 1 | AW14: 2 | AX14: 59499149 | AY14: 1 | AZ14: 6144 | BA14: 14 | BB14: 0 | BC14: 0 | BD14: 0 | BE14: 0 | BF14: 0 | BG14: 0 | BH14: 0 | BI14: 0 | BJ14: 0 | BK14: 0 | BL14: 0 | BM14: 0 | BN14: 0 | BO14: 0 | BP14: 0 | BQ14: 0 | BR14: 0 | BS14: 0 | BT14: 0 | BU14: 0 | BV14: 0 | BW14: 0 | CU14: =ROUND(AT14*Source!I39*AH14*AL14,2) -> 0 | CV14: =ROUND(Y14*Source!I39,9) -> -99 | CW14: 0 | CX14: =ROUND(Y14*Source!I39,9) -> -99 | CY14: =AD14 -> 0 | CZ14: =AH14 -> 0 | DA14: =AL14 -> 1 | DB14: =ROUND((ROUND(AT14*CZ14,2)*1.1),6) -> 0 | DC14: =ROUND((ROUND(AT14*AG14,2)*1.1),6) -> 0 | DF14: =ROUND(ROUND(AE14,2)*CX14,2) -> 0 | DG14: =ROUND(ROUND(AF14,2)*CX14,2) -> 0 | DH14: =ROUND(ROUND(AG14,2)*CX14,2) -> 0 | DI14: =ROUND(ROUND(AH14,2)*CX14,2) -> 0 | DJ14: =DI14 -> 0 | DK14: 0 | DM14: 0 | DO14: 0
A15: =ROW(Source!A40) -> 40 | B15: 59499003 | C15: 59499138 | D15: 58532980 | E15: 1080 | F15: 1 | G15: 1080 | H15: 1 | I15: 9999990008 | K15: Трудозатраты рабочих | L15: 1191 | N15: 1013 | O15: чел.-ч. | P15: чел.-ч. | Q15: 1 | W15: 0 | X15: 476480486 | Y15: =(AT15*1.1) -> 6.93 | AA15: 0 | AB15: 0 | AC15: 0 | AD15: 0 | AE15: 0 | AF15: 0 | AG15: 0 | AH15: 0 | AI15: 1 | AJ15: 1 | AK15: 1 | AL15: 1 | AM15: -2 | AN15: 0 | AO15: 1 | AP15: 1 | AQ15: 0 | AR15: 0 | AT15: 6.3 | AU15: *1,1 | AV15: 1 | AW15: 2 | AX15: 59499150 | AY15: 1 | AZ15: 6144 | BA15: 15 | BB15: 0 | BC15: 0 | BD15: 0 | BE15: 0 | BF15: 0 | BG15: 0 | BH15: 0 | BI15: 0 | BJ15: 0 | BK15: 0 | BL15: 0 | BM15: 0 | BN15: 0 | BO15: 0 | BP15: 0 | BQ15: 0 | BR15: 0 | BS15: 0 | BT15: 0 | BU15: 0 | BV15: 0 | BW15: 0 | CU15: =ROUND(AT15*Source!I40*AH15*AL15,2) -> 0 | CV15: =ROUND(Y15*Source!I40,9) -> -103.3956 | CW15: 0 | CX15: =ROUND(Y15*Source!I40,9) -> -103.3956 | CY15: =AD15 -> 0 | CZ15: =AH15 -> 0 | DA15: =AL15 -> 1 | DB15: =ROUND((ROUND(AT15*CZ15,2)*1.1),6) -> 0 | DC15: =ROUND((ROUND(AT15*AG15,2)*1.1),6) -> 0 | DF15: =ROUND(ROUND(AE15,2)*CX15,2) -> 0 | DG15: =ROUND(ROUND(AF15,2)*CX15,2) -> 0 | DH15: =ROUND(ROUND(AG15,2)*CX15,2) -> 0 | DI15: =ROUND(ROUND(AH15,2)*CX15,2) -> 0 | DJ15: =DI15 -> 0 | DK15: 0 | DM15: 0 | DO15: 0
A16: =ROW(Source!A41) -> 41 | B16: 59499000 | C16: 59499138 | D16: 58532980 | E16: 1080 | F16: 1 | G16: 1080 | H16: 1 | I16: 9999990008 | K16: Трудозатраты рабочих | L16: 1191 | N16: 1013 | O16: чел.-ч. | P16: чел.-ч. | Q16: 1 | W16: 0 | X16: 476480486 | Y16: =(AT16*1.1) -> 6.93 | AA16: 0 | AB16: 0 | AC16: 0 | AD16: 0 | AE16: 0 | AF16: 0 | AG16: 0 | AH16: 0 | AI16: 1 | AJ16: 1 | AK16: 1 | AL16: 1 | AM16: 5 | AN16: 0 | AO16: 1 | AP16: 1 | AQ16: 0 | AR16: 0 | AT16: 6.3 | AU16: *1,1 | AV16: 1 | AW16: 2 | AX16: 59499150 | AY16: 1 | AZ16: 6144 | BA16: 16 | BB16: 0 | BC16: 0 | BD16: 0 | BE16: 0 | BF16: 0 | BG16: 0 | BH16: 0 | BI16: 0 | BJ16: 0 | BK16: 0 | BL16: 0 | BM16: 0 | BN16: 0 | BO16: 0 | BP16: 0 | BQ16: 0 | BR16: 0 | BS16: 0 | BT16: 0 | BU16: 0 | BV16: 0 | BW16: 0 | CU16: =ROUND(AT16*Source!I41*AH16*AL16,2) -> 0 | CV16: =ROUND(Y16*Source!I41,9) -> -103.3956 | CW16: 0 | CX16: =ROUND(Y16*Source!I41,9) -> -103.3956 | CY16: =AD16 -> 0 | CZ16: =AH16 -> 0 | DA16: =AL16 -> 1 | DB16: =ROUND((ROUND(AT16*CZ16,2)*1.1),6) -> 0 | DC16: =ROUND((ROUND(AT16*AG16,2)*1.1),6) -> 0 | DF16: =ROUND(ROUND(AE16,2)*CX16,2) -> 0 | DG16: =ROUND(ROUND(AF16,2)*CX16,2) -> 0 | DH16: =ROUND(ROUND(AG16,2)*CX16,2) -> 0 | DI16: =ROUND(ROUND(AH16,2)*CX16,2) -> 0 | DJ16: =DI16 -> 0 | DK16: 0 | DM16: 0 | DO16: 0

Sheet EtalonRes
A1: =ROW(Source!A29) -> 29 | B1: 59499143 | C1: 59499118 | D1: 58532980 | E1: 1080 | F1: 1 | G1: 1080 | H1: 1 | I1: 9999990008 | K1: Трудозатраты рабочих | L1: 1191 | N1: 1013 | O1: чел.-ч. | P1: чел.-ч. | Q1: 1 | X1: 346 | Y1: 0 | Z1: 0 | AA1: 0 | AB1: 0 | AC1: 0 | AD1: 1 | AE1: 1 | AF1: *0,3)*1,1 | AG1: 114.18 | AH1: 2 | AI1: 59499119 | AJ1: 1 | AK1: 0 | AL1: 0 | AM1: 0 | AN1: 0 | AO1: 0 | AP1: 0 | AQ1: 0 | AR1: 0
A2: =ROW(Source!A29) -> 29 | B2: 59499144 | C2: 59499118 | D2: 58537982 | E2: 1080 | F2: 1 | G2: 1080 | H2: 3 | I2: 9999990002 | K2: Масса оборудования | L2: 1348 | N2: 1009 | O2: т | P2: т | Q2: 1000 | X2: 1.5 | Y2: 0 | Z2: 0 | AA2: 0 | AB2: 0 | AC2: 0 | AD2: 1 | AE2: 0 | AF2: *0)*1 | AG2: 0 | AH2: 2 | AI2: 59499120 | AJ2: 2 | AK2: 0 | AL2: 0 | AM2: 0 | AN2: 0 | AO2: 0 | AP2: 0 | AQ2: 0 | AR2: 0
A3: =ROW(Source!A30) -> 30 | B3: 59499143 | C3: 59499118 | D3: 58532980 | E3: 1080 | F3: 1 | G3: 1080 | H3: 1 | I3: 9999990008 | K3: Трудозатраты рабочих | L3: 1191 | N3: 1013 | O3: чел.-ч. | P3: чел.-ч. | Q3: 1 | X3: 346 | Y3: 0 | Z3: 0 | AA3: 0 | AB3: 0 | AC3: 0 | AD3: 1 | AE3: 1 | AF3: *0,3)*1,1 | AG3: 114.18 | AH3: 2 | AI3: 59499119 | AJ3: 3 | AK3: 0 | AL3: 0 | AM3: 0 | AN3: 0 | AO3: 0 | AP3: 0 | AQ3: 0 | AR3: 0
A4: =ROW(Source!A30) -> 30 | B4: 59499144 | C4: 59499118 | D4: 58537982 | E4: 1080 | F4: 1 | G4: 1080 | H4: 3 | I4: 9999990002 | K4: Масса оборудования | L4: 1348 | N4: 1009 | O4: т | P4: т | Q4: 1000 | X4: 1.5 | Y4: 0 | Z4: 0 | AA4: 0 | AB4: 0 | AC4: 0 | AD4: 1 | AE4: 0 | AF4: *0)*1 | AG4: 0 | AH4: 2 | AI4: 59499120 | AJ4: 4 | AK4: 0 | AL4: 0 | AM4: 0 | AN4: 0 | AO4: 0 | AP4: 0 | AQ4: 0 | AR4: 0
A5: =ROW(Source!A31) -> 31 | B5: 59499145 | C5: 59499123 | D5: 58532980 | E5: 1080 | F5: 1 | G5: 1080 | H5: 1 | I5: 9999990008 | K5: Трудозатраты рабочих | L5: 1191 | N5: 1013 | O5: чел.-ч. | P5: чел.-ч. | Q5: 1 | X5: 22.5 | Y5: 0 | Z5: 0 | AA5: 0 | AB5: 0 | AC5: 0 | AD5: 1 | AE5: 1 | AF5: *0,3)*1,1 | AG5: 7.425 | AH5: 2 | AI5: 59499124 | AJ5: 5 | AK5: 0 | AL5: 0 | AM5: 0 | AN5: 0 | AO5: 0 | AP5: 0 | AQ5: 0 | AR5: 0
A6: =ROW(Source!A32) -> 32 | B6: 59499145 | C6: 59499123 | D6: 58532980 | E6: 1080 | F6: 1 | G6: 1080 | H6: 1 | I6: 9999990008 | K6: Трудозатраты рабочих | L6: 1191 | N6: 1013 | O6: чел.-ч. | P6: чел.-ч. | Q6: 1 | X6: 22.5 | Y6: 0 | Z6: 0 | AA6: 0 | AB6: 0 | AC6: 0 | AD6: 1 | AE6: 1 | AF6: *0,3)*1,1 | AG6: 7.425 | AH6: 2 | AI6: 59499124 | AJ6: 6 | AK6: 0 | AL6: 0 | AM6: 0 | AN6: 0 | AO6: 0 | AP6: 0 | AQ6: 0 | AR6: 0
A7: =ROW(Source!A33) -> 33 | B7: 59499146 | C7: 59499126 | D7: 58532980 | E7: 1080 | F7: 1 | G7: 1080 | H7: 1 | I7: 9999990008 | K7: Трудозатраты рабочих | L7: 1191 | N7: 1013 | O7: чел.-ч. | P7: чел.-ч. | Q7: 1 | X7: 6.3 | Y7: 0 | Z7: 0 | AA7: 0 | AB7: 0 | AC7: 0 | AD7: 1 | AE7: 1 | AF7: *0,3)*1,1 | AG7: 2.079 | AH7: 2 | AI7: 59499127 | AJ7: 7 | AK7: 0 | AL7: 0 | AM7: 0 | AN7: 0 | AO7: 0 | AP7: 0 | AQ7: 0 | AR7: 0
A8: =ROW(Source!A34) -> 34 | B8: 59499146 | C8: 59499126 | D8: 58532980 | E8: 1080 | F8: 1 | G8: 1080 | H8: 1 | I8: 9999990008 | K8: Трудозатраты рабочих | L8: 1191 | N8: 1013 | O8: чел.-ч. | P8: чел.-ч. | Q8: 1 | X8: 6.3 | Y8: 0 | Z8: 0 | AA8: 0 | AB8: 0 | AC8: 0 | AD8: 1 | AE8: 1 | AF8: *0,3)*1,1 | AG8: 2.079 | AH8: 2 | AI8: 59499127 | AJ8: 8 | AK8: 0 | AL8: 0 | AM8: 0 | AN8: 0 | AO8: 0 | AP8: 0 | AQ8: 0 | AR8: 0
A9: =ROW(Source!A36) -> 36 | B9: 59499147 | C9: 59499130 | D9: 58532980 | E9: 1080 | F9: 1 | G9: 1080 | H9: 1 | I9: 9999990008 | K9: Трудозатраты рабочих | L9: 1191 | N9: 1013 | O9: чел.-ч. | P9: чел.-ч. | Q9: 1 | X9: 356 | Y9: 0 | Z9: 0 | AA9: 0 | AB9: 0 | AC9: 0 | AD9: 1 | AE9: 1 | AF9: *1,1 | AG9: 391.6 | AH9: 2 | AI9: 59499131 | AJ9: 9 | AK9: 0 | AL9: 0 | AM9: 0 | AN9: 0 | AO9: 0 | AP9: 0 | AQ9: 0 | AR9: 0
A10: =ROW(Source!A36) -> 36 | B10: 59499148 | C10: 59499130 | D10: 58537982 | E10: 1080 | F10: 1 | G10: 1080 | H10: 3 | I10: 9999990002 | K10: Масса оборудования | L10: 1348 | N10: 1009 | O10: т | P10: т | Q10: 1000 | X10: 1.5 | Y10: 0 | Z10: 0 | AA10: 0 | AB10: 0 | AC10: 0 | AD10: 1 | AE10: 0 | AF10: *1 | AG10: 1.5 | AH10: 2 | AI10: 59499132 | AJ10: 10 | AK10: 0 | AL10: 0 | AM10: 0 | AN10: 0 | AO10: 0 | AP10: 0 | AQ10: 0 | AR10: 0
A11: =ROW(Source!A37) -> 37 | B11: 59499147 | C11: 59499130 | D11: 58532980 | E11: 1080 | F11: 1 | G11: 1080 | H11: 1 | I11: 9999990008 | K11: Трудозатраты рабочих | L11: 1191 | N11: 1013 | O11: чел.-ч. | P11: чел.-ч. | Q11: 1 | X11: 356 | Y11: 0 | Z11: 0 | AA11: 0 | AB11: 0 | AC11: 0 | AD11: 1 | AE11: 1 | AF11: *1,1 | AG11: 391.6 | AH11: 2 | AI11: 59499131 | AJ11: 11 | AK11: 0 | AL11: 0 | AM11: 0 | AN11: 0 | AO11: 0 | AP11: 0 | AQ11: 0 | AR11: 0
A12: =ROW(Source!A37) -> 37 | B12: 59499148 | C12: 59499130 | D12: 58537982 | E12: 1080 | F12: 1 | G12: 1080 | H12: 3 | I12: 9999990002 | K12: Масса оборудования | L12: 1348 | N12: 1009 | O12: т | P12: т | Q12: 1000 | X12: 1.5 | Y12: 0 | Z12: 0 | AA12: 0 | AB12: 0 | AC12: 0 | AD12: 1 | AE12: 0 | AF12: *1 | AG12: 1.5 | AH12: 2 | AI12: 59499132 | AJ12: 12 | AK12: 0 | AL12: 0 | AM12: 0 | AN12: 0 | AO12: 0 | AP12: 0 | AQ12: 0 | AR12: 0
A13: =ROW(Source!A38) -> 38 | B13: 59499149 | C13: 59499135 | D13: 58532980 | E13: 1080 | F13: 1 | G13: 1080 | H13: 1 | I13: 9999990008 | K13: Трудозатраты рабочих | L13: 1191 | N13: 1013 | O13: чел.-ч. | P13: чел.-ч. | Q13: 1 | X13: 23.2 | Y13: 0 | Z13: 0 | AA13: 0 | AB13: 0 | AC13: 0 | AD13: 1 | AE13: 1 | AF13: *1,1 | AG13: 25.52 | AH13: 2 | AI13: 59499136 | AJ13: 13 | AK13: 0 | AL13: 0 | AM13: 0 | AN13: 0 | AO13: 0 | AP13: 0 | AQ13: 0 | AR13: 0
A14: =ROW(Source!A39) -> 39 | B14: 59499149 | C14: 59499135 | D14: 58532980 | E14: 1080 | F14: 1 | G14: 1080 | H14: 1 | I14: 9999990008 | K14: Трудозатраты рабочих | L14: 1191 | N14: 1013 | O14: чел.-ч. | P14: чел.-ч. | Q14: 1 | X14: 23.2 | Y14: 0 | Z14: 0 | AA14: 0 | AB14: 0 | AC14: 0 | AD14: 1 | AE14: 1 | AF14: *1,1 | AG14: 25.52 | AH14: 2 | AI14: 59499136 | AJ14: 14 | AK14: 0 | AL14: 0 | AM14: 0 | AN14: 0 | AO14: 0 | AP14: 0 | AQ14: 0 | AR14: 0
A15: =ROW(Source!A40) -> 40 | B15: 59499150 | C15: 59499138 | D15: 58532980 | E15: 1080 | F15: 1 | G15: 1080 | H15: 1 | I15: 9999990008 | K15: Трудозатраты рабочих | L15: 1191 | N15: 1013 | O15: чел.-ч. | P15: чел.-ч. | Q15: 1 | X15: 6.5 | Y15: 0 | Z15: 0 | AA15: 0 | AB15: 0 | AC15: 0 | AD15: 1 | AE15: 1 | AF15: *1,1 | AG15: 7.15 | AH15: 2 | AI15: 59499139 | AJ15: 15 | AK15: 0 | AL15: 0 | AM15: 0 | AN15: 0 | AO15: 0 | AP15: 0 | AQ15: 0 | AR15: 0
A16: =ROW(Source!A41) -> 41 | B16: 59499150 | C16: 59499138 | D16: 58532980 | E16: 1080 | F16: 1 | G16: 1080 | H16: 1 | I16: 9999990008 | K16: Трудозатраты рабочих | L16: 1191 | N16: 1013 | O16: чел.-ч. | P16: чел.-ч. | Q16: 1 | X16: 6.5 | Y16: 0 | Z16: 0 | AA16: 0 | AB16: 0 | AC16: 0 | AD16: 1 | AE16: 1 | AF16: *1,1 | AG16: 7.15 | AH16: 2 | AI16: 59499139 | AJ16: 16 | AK16: 0 | AL16: 0 | AM16: 0 | AN16: 0 | AO16: 0 | AP16: 0 | AQ16: 0 | AR16: 0

Sheet SrcPoprs
A1: 29 | B1: 1 | D1: *0 | E1: *0,3 | F1: *0,3 | G1: *0,3 | I1: *0,3 | J1: *0,3 | N1: *0 | O1: *0,3
A2: 29 | B2: 1 | D2: *1 | E2: *1,1 | F2: *1,1 | G2: *1,1 | I2: *1,1 | J2: *1,1 | N2: *1 | O2: *1,1 | S2: Гл.12.Прил.8.п.8. 5_12.00.01.11.003 | T2: При наличии усложненных условий производства работ (стесненность, сложность складирования и транспортной логистики, наличие в зоне производства работ действующего технологического оборудования или движения технологического транспорта и т.п.) для объектов, расположенных за пределами территории круговой магистральной системы улиц "Садовое кольцо" и за пределами Третьего транспортного кольца города Москвы пунктов "а" и "б", но в пределах Московской кольцевой автомобильной дороги | U2: Глава 12
A3: 30 | B3: 1 | D3: *0 | E3: *0,3 | F3: *0,3 | G3: *0,3 | I3: *0,3 | J3: *0,3 | N3: *0 | O3: *0,3
A4: 30 | B4: 1 | D4: *1 | E4: *1,1 | F4: *1,1 | G4: *1,1 | I4: *1,1 | J4: *1,1 | N4: *1 | O4: *1,1 | S4: Гл.12.Прил.8.п.8. 5_12.00.01.11.003 | T4: При наличии усложненных условий производства работ (стесненность, сложность складирования и транспортной логистики, наличие в зоне производства работ действующего технологического оборудования или движения технологического транспорта и т.п.) для объектов, расположенных за пределами территории круговой магистральной системы улиц "Садовое кольцо" и за пределами Третьего транспортного кольца города Москвы пунктов "а" и "б", но в пределах Московской кольцевой автомобильной дороги | U4: Глава 12
A5: 31 | B5: 1 | D5: *0 | E5: *0,3 | F5: *0,3 | G5: *0,3 | I5: *0,3 | J5: *0,3 | N5: *0 | O5: *0,3
A6: 31 | B6: 1 | D6: *1 | E6: *1,1 | F6: *1,1 | G6: *1,1 | I6: *1,1 | J6: *1,1 | N6: *1 | O6: *1,1 | S6: Гл.12.Прил.8.п.8. 5_12.00.01.11.003 | T6: При наличии усложненных условий производства работ (стесненность, сложность складирования и транспортной логистики, наличие в зоне производства работ действующего технологического оборудования или движения технологического транспорта и т.п.) для объектов, расположенных за пределами территории круговой магистральной системы улиц "Садовое кольцо" и за пределами Третьего транспортного кольца города Москвы пунктов "а" и "б", но в пределах Московской кольцевой автомобильной дороги | U6: Глава 12
A7: 32 | B7: 1 | D7: *0 | E7: *0,3 | F7: *0,3 | G7: *0,3 | I7: *0,3 | J7: *0,3 | N7: *0 | O7: *0,3
A8: 32 | B8: 1 | D8: *1 | E8: *1,1 | F8: *1,1 | G8: *1,1 | I8: *1,1 | J8: *1,1 | N8: *1 | O8: *1,1 | S8: Гл.12.Прил.8.п.8. 5_12.00.01.11.003 | T8: При наличии усложненных условий производства работ (стесненность, сложность складирования и транспортной логистики, наличие в зоне производства работ действующего технологического оборудования или движения технологического транспорта и т.п.) для объектов, расположенных за пределами территории круговой магистральной системы улиц "Садовое кольцо" и за пределами Третьего транспортного кольца города Москвы пунктов "а" и "б", но в пределах Московской кольцевой автомобильной дороги | U8: Глава 12
A9: 33 | B9: 1 | D9: *0 | E9: *0,3 | F9: *0,3 | G9: *0,3 | I9: *0,3 | J9: *0,3 | N9: *0 | O9: *0,3
A10: 33 | B10: 1 | D10: *1 | E10: *1,1 | F10: *1,1 | G10: *1,1 | I10: *1,1 | J10: *1,1 | N10: *1 | O10: *1,1 | S10: Гл.12.Прил.8.п.8. 5_12.00.01.11.003 | T10: При наличии усложненных условий производства работ (стесненность, сложность складирования и транспортной логистики, наличие в зоне производства работ действующего технологического оборудования или движения технологического транспорта и т.п.) для объектов, расположенных за пределами территории круговой магистральной системы улиц "Садовое кольцо" и за пределами Третьего транспортного кольца города Москвы пунктов "а" и "б", но в пределах Московской кольцевой автомобильной дороги | U10: Глава 12
A11: 34 | B11: 1 | D11: *0 | E11: *0,3 | F11: *0,3 | G11: *0,3 | I11: *0,3 | J11: *0,3 | N11: *0 | O11: *0,3
A12: 34 | B12: 1 | D12: *1 | E12: *1,1 | F12: *1,1 | G12: *1,1 | I12: *1,1 | J12: *1,1 | N12: *1 | O12: *1,1 | S12: Гл.12.Прил.8.п.8. 5_12.00.01.11.003 | T12: При наличии усложненных условий производства работ (стесненность, сложность складирования и транспортной логистики, наличие в зоне производства работ действующего технологического оборудования или движения технологического транспорта и т.п.) для объектов, расположенных за пределами территории круговой магистральной системы улиц "Садовое кольцо" и за пределами Третьего транспортного кольца города Москвы пунктов "а" и "б", но в пределах Московской кольцевой автомобильной дороги | U12: Глава 12
A13: 36 | B13: 1 | D13: *1 | E13: *1,1 | F13: *1,1 | G13: *1,1 | I13: *1,1 | J13: *1,1 | N13: *1 | O13: *1,1 | S13: Гл.12.Прил.8.п.8. 5_12.00.01.11.003 | T13: При наличии усложненных условий производства работ (стесненность, сложность складирования и транспортной логистики, наличие в зоне производства работ действующего технологического оборудования или движения технологического транспорта и т.п.) для объектов, расположенных за пределами территории круговой магистральной системы улиц "Садовое кольцо" и за пределами Третьего транспортного кольца города Москвы пунктов "а" и "б", но в пределах Московской кольцевой автомобильной дороги | U13: Глава 12
A14: 37 | B14: 1 | D14: *1 | E14: *1,1 | F14: *1,1 | G14: *1,1 | I14: *1,1 | J14: *1,1 | N14: *1 | O14: *1,1 | S14: Гл.12.Прил.8.п.8. 5_12.00.01.11.003 | T14: При наличии усложненных условий производства работ (стесненность, сложность складирования и транспортной логистики, наличие в зоне производства работ действующего технологического оборудования или движения технологического транспорта и т.п.) для объектов, расположенных за пределами территории круговой магистральной системы улиц "Садовое кольцо" и за пределами Третьего транспортного кольца города Москвы пунктов "а" и "б", но в пределах Московской кольцевой автомобильной дороги | U14: Глава 12
A15: 38 | B15: 1 | D15: *1 | E15: *1,1 | F15: *1,1 | G15: *1,1 | I15: *1,1 | J15: *1,1 | N15: *1 | O15: *1,1 | S15: Гл.12.Прил.8.п.8. 5_12.00.01.11.003 | T15: При наличии усложненных условий производства работ (стесненность, сложность складирования и транспортной логистики, наличие в зоне производства работ действующего технологического оборудования или движения технологического транспорта и т.п.) для объектов, расположенных за пределами территории круговой магистральной системы улиц "Садовое кольцо" и за пределами Третьего транспортного кольца города Москвы пунктов "а" и "б", но в пределах Московской кольцевой автомобильной дороги | U15: Глава 12
A16: 39 | B16: 1 | D16: *1 | E16: *1,1 | F16: *1,1 | G16: *1,1 | I16: *1,1 | J16: *1,1 | N16: *1 | O16: *1,1 | S16: Гл.12.Прил.8.п.8. 5_12.00.01.11.003 | T16: При наличии усложненных условий производства работ (стесненность, сложность складирования и транспортной логистики, наличие в зоне производства работ действующего технологического оборудования или движения технологического транспорта и т.п.) для объектов, расположенных за пределами территории круговой магистральной системы улиц "Садовое кольцо" и за пределами Третьего транспортного кольца города Москвы пунктов "а" и "б", но в пределах Московской кольцевой автомобильной дороги | U16: Глава 12
A17: 40 | B17: 1 | D17: *1 | E17: *1,1 | F17: *1,1 | G17: *1,1 | I17: *1,1 | J17: *1,1 | N17: *1 | O17: *1,1 | S17: Гл.12.Прил.8.п.8. 5_12.00.01.11.003 | T17: При наличии усложненных условий производства работ (стесненность, сложность складирования и транспортной логистики, наличие в зоне производства работ действующего технологического оборудования или движения технологического транспорта и т.п.) для объектов, расположенных за пределами территории круговой магистральной системы улиц "Садовое кольцо" и за пределами Третьего транспортного кольца города Москвы пунктов "а" и "б", но в пределах Московской кольцевой автомобильной дороги | U17: Глава 12
A18: 41 | B18: 1 | D18: *1 | E18: *1,1 | F18: *1,1 | G18: *1,1 | I18: *1,1 | J18: *1,1 | N18: *1 | O18: *1,1 | S18: Гл.12.Прил.8.п.8. 5_12.00.01.11.003 | T18: При наличии усложненных условий производства работ (стесненность, сложность складирования и транспортной логистики, наличие в зоне производства работ действующего технологического оборудования или движения технологического транспорта и т.п.) для объектов, расположенных за пределами территории круговой магистральной системы улиц "Садовое кольцо" и за пределами Третьего транспортного кольца города Москвы пунктов "а" и "б", но в пределах Московской кольцевой автомобильной дороги | U18: Глава 12

Sheet SrcKA
A1: 0 | B1: Smeta.RU (495) 974-1589 | D1: _PS_ | F1: 0 | G1: 0 | H1: 0 | I1: Smeta.RU | K1: 1 | L1: 74561 | M1: 10 | N1: 11 | O1: 15 | P1: 0 | Q1: 2
F12: =Source!F12 -> 02-01-19 | G12: =Source!G12 -> 02-01-19 Вертикальный транспорт | AJ12: 0 | CY12: 0
