Workbook

Sheet 02-01-12
A1: =Source!B1 -> Smeta.RU (495) 974-1589
J2: Форма № 4б
A3: Клязьминская улица, д. 7, к. 4, Дмитровский район Северного административного округа города Москвы Капитальный ремонт здания Государственного бюджетного общеобразовательного учреждения города Москвы «Школа № 236». 1 этап | AP3: Клязьминская улица, д. 7, к. 4, Дмитровский район Северного административного округа города Москвы Капитальный ремонт здания Государственного бюджетного общеобразовательного учреждения города Москвы «Школа № 236». 1 этап. 02-01-12 СКС
A4: (наименование стройки и/или объекта)
A6: =CONCATENATE( "ЛОКАЛЬНАЯ СМЕТА № ",IF(Source!F20<>"Новая локальная смета", Source!F20, "")) -> ЛОКАЛЬНАЯ СМЕТА № 02-01-12
A8: =IF(Source!G20<>"Новая локальная смета", Source!G20, "") -> Структурированная кабельная сеть
A9: (наименование работ и затрат)
A11: =CONCATENATE( "Основание: чертежи № ", Source!J20) -> Основание: чертежи № 2024-00272-01-0-ИОС5.5
I13: В базисном уровне цен | J13: В текущем уровне цен
E14: Сметная стоимость | I14: =I15+I16+I17+I18 -> 1018.2 | J14: =J15+J16+J17+J18 -> 12126.02 | K14: тыс.руб.
E15: Строительные работы | I15: =ROUND((Source!F386)/1000, 2) -> 0 | J15: =ROUND((Source!P386)/1000, 2) -> 0 | K15: тыс.руб.
E16: Работы по монтажу оборудования | I16: =ROUND((Source!F387)/1000, 2) -> 548.47 | J16: =ROUND((Source!P387)/1000, 2) -> 8650.89 | K16: тыс.руб.
E17: Оборудование | I17: =ROUND((Source!F378)/1000, 2) -> 469.73 | J17: =ROUND((Source!P378)/1000, 2) -> 3475.13 | K17: тыс.руб.
E18: Прочие работы и затраты | I18: =ROUND((Source!F388+Source!F389)/1000, 2) -> 0 | J18: =ROUND((Source!P388+Source!P389)/1000, 2) -> 0 | K18: тыс.руб.
E19: Средства на оплату труда | I19: =(Source!F384+ Source!F383)/1000 -> 36.28346 | J19: =((Source!P384 + Source!P383)/1000) -> 1995.2275 | K19: тыс.руб.
E20: Затраты труда | I20: =Source!F391 -> 3008.2474 | K20: чел.-ч.
E21: Кроме того:
E22: Возврат материалов | I22: =SUM(Y28:Y321)/1000 -> 0 | J22: =SUM(Z28:Z321)/1000 -> 0 | K22: тыс.руб.
A24: Составлен(а) по ТСН-2001 с учетом Дополнения №: 80
A25: № и период сборника коэффициентов (индексов) пересчета: Коэффициенты к ТСН-2001 МГЭ Дополнение 80, строительство №217/80 III квартал 2025 года и Коэффициенты к ТСН-2001.13-2 Дополнение 46 №62/46 III квартал 2025 года | AP25: № и период сборника коэффициентов (индексов) пересчета: Коэффициенты к ТСН-2001 МГЭ Дополнение 80, строительство №217/80 III квартал 2025 года и Коэффициенты к ТСН-2001.13-2 Дополнение 46 №62/46 III квартал 2025 года
A26: № п/п | B26: Шифр расценки и коды ресурсов | C26: Наименование работ и затрат | D26: Ед. изм. | E26: Кол-во единиц | F26: Цена на ед. изм., руб. | G26: Попра- вочные коэффи- циенты | H26: Коэффи- циенты зимних удорожа- ний | I26: Всего в ценах на январь 2000 года, руб. | J26: Коэффи- циенты (индек- сы) пере- счета, нормы НР и СП | K26: ВСЕГО затрат в текущем уровне цен, руб.
A27: 1 | B27: 2 | C27: 3 | D27: 4 | E27: 5 | F27: 6 | G27: 7 | H27: 8 | I27: 9 | J27: 10 | K27: 11
A29: =CONCATENATE("Раздел: ",IF(Source!G24<>"Новый раздел", Source!G24, "")) -> Раздел: Телекоммуникационный шкаф 47U 19" ШТ1-01
A30: 1 | B30: 4.10-32-1 Поправка: Гл.12.Прил.8.п.8. 5_12.00.01.11.003 | C30: Монтаж стойки, полустойки, каркаса стойки или шкафа массой до 100 кг | D30: =Source!H28 -> 1 ШТ. | E30: =Source!I28 -> 1 | Q30: =Source!X28 -> 99.34 | R30: =Source!X29 -> 5462.81 | S30: =Source!Y28 -> 50.77 | T30: =Source!Y29 -> 2792.1 | U30: =ROUND((175/100)*ROUND(Source!R28, 2), 2) -> 8.38 | V30: =ROUND((0/100)*ROUND(Source!R29, 2), 2) -> 0 | AC30: 0
C31: ЗП | F31: =Source!AO28 -> 91.68 | G31: 1,1 | H31: =Source!AV29 -> 1.047 | I31: =Source!S28 -> 105.59 | J31: =IF(Source!BA29<> 0, Source!BA29, 1) -> 54.99 | K31: =Source!S29 -> 5806.39
C32: ЭМ | F32: =Source!AM28 -> 38.92 | G32: 1,1 | H32: =Source!AV29 -> 1.047 | I32: =Source!Q28 -> 44.82 | J32: =IF(Source!BB29<> 0, Source!BB29, 1) -> 15.29 | K32: =Source!Q29 -> 685.3
C33: в т.ч. ЗПМ | F33: =Source!AN28 -> 4.16 | G33: 1,1 | H33: =Source!AV29 -> 1.047 | I33: =Source!R28 -> 4.79 | J33: =IF(Source!BS29<> 0, Source!BS29, 1) -> 54.99 | K33: =Source!R29 -> 263.4
C34: МР | F34: =Source!AL28 -> 3.92 | H34: =Source!AW29 -> 1 | I34: =Source!P28 -> 3.92 | J34: =IF(Source!BC29<> 0, Source!BC29, 1) -> 8.3 | K34: =Source!P29 -> 32.54
A35: 1,1 | B35: =Source!F30 -> КА 1 | C35: Шкаф 19" серии Racknet S3000, 47U 60F-47-7C-94BL 16 818,37 = [195 488,81 / 1,2 / 9,88] + 2% Заг.скл | D35: =Source!H30 -> шт. | E35: =Source!I30 -> 1 | F35: =Source!AK30 -> 16818.37 | H35: =Source!AW31 -> 1 | I35: =Source!O30 -> 16818.37 | J35: =IF(Source!BC31<> 0, Source!BC31, 1) -> 9.88 | K35: =Source!O31 -> 166165.5 | Q35: =Source!X30 -> 0 | R35: =Source!X31 -> 0 | S35: =Source!Y30 -> 0 | T35: =Source!Y31 -> 0 | U35: =ROUND((175/100)*ROUND(Source!R30, 2), 2) -> 0 | V35: =ROUND((0/100)*ROUND(Source!R31, 2), 2) -> 0 | AC35: 3
A36: 1,2 | B36: =Source!F32 -> КА 2 | C36: Вертикальный органайзер 60А-18-47-01-31BL 3 548,41 = [41 245 / 1,2 / 9,88] + 2% Заг.скл | D36: =Source!H32 -> шт. | E36: =Source!I32 -> 1 | F36: =Source!AK32 -> 3548.41 | H36: =Source!AW33 -> 1 | I36: =Source!O32 -> 3548.41 | J36: =IF(Source!BC33<> 0, Source!BC33, 1) -> 9.88 | K36: =Source!O33 -> 35058.29 | Q36: =Source!X32 -> 0 | R36: =Source!X33 -> 0 | S36: =Source!Y32 -> 0 | T36: =Source!Y33 -> 0 | U36: =ROUND((175/100)*ROUND(Source!R32, 2), 2) -> 0 | V36: =ROUND((0/100)*ROUND(Source!R33, 2), 2) -> 0 | AC36: 3
A37: 1,3 | B37: =Source!F34 -> КА 7 | C37: Набор для креnленuя лоmков к крышке шкафов, высоmа 50мм 60А-31-08-ЗЗВL 147,62 = [1 715,95 / 1,2 / 9,88] + 2% Заг.скл | D37: =Source!H34 -> шт. | E37: =Source!I34 -> 1 | F37: =Source!AK34 -> 147.62 | H37: =Source!AW35 -> 1 | I37: =Source!O34 -> 147.62 | J37: =IF(Source!BC35<> 0, Source!BC35, 1) -> 9.88 | K37: =Source!O35 -> 1458.49 | Q37: =Source!X34 -> 0 | R37: =Source!X35 -> 0 | S37: =Source!Y34 -> 0 | T37: =Source!Y35 -> 0 | U37: =ROUND((175/100)*ROUND(Source!R34, 2), 2) -> 0 | V37: =ROUND((0/100)*ROUND(Source!R35, 2), 2) -> 0 | AC37: 3
C38: НР от ФОТ | D38: % | E38: =Source!BZ29 -> 90 | I38: =SUM(Q30:Q37) -> 99.34 | J38: =Source!AT29 -> 90 | K38: =SUM(R30:R37) -> 5462.81
C39: СП от ФОТ | D39: % | E39: =Source!CA29 -> 46 | I39: =SUM(S30:S38) -> 50.77 | J39: =Source!AU29 -> 46 | K39: =SUM(T30:T38) -> 2792.1
C40: ЗТР | D40: чел-ч | E40: =Source!AQ28 -> 8.2 | G40: 1,1 | H40: =Source!AV29 -> 1.047 | I40: =Source!U28 -> 9.44394
C41: ВСЕГО работ по позиции: | H41: =I31+I32+I34+I38+I39+SUM(I35:I37)-SUMIF(AC35:AC37, 5, I35:I37)-SUMIF(AC35:AC37, 6, I35:I37) -> 20818.84 | J41: =K31+K32+K34+K38+K39+SUM(K35:K37)-SUMIF(AC35:AC37, 5, K35:K37)-SUMIF(AC35:AC37, 6, K35:K37) -> 217461.42
C42: ВСЕГО оборудование по позиции: | H42: =SUMIF(AC35:AC37, 5, I35:I37)+SUMIF(AC35:AC37, 6, I35:I37) -> 0 | J42: =SUMIF(AC35:AC37, 5, K35:K37)+SUMIF(AC35:AC37, 6, K35:K37) -> 0
C43: ВСЕГО по позиции: | H43: =I31+I32+I34+I38+I39+SUM(I35:I37) -> 20818.84 | J43: =K31+K32+K34+K38+K39+SUM(K35:K37) -> 217461.42 | O43: =I31+I32+I34+I38+I39+SUM(I35:I37) -> 20818.84 | P43: =K31+K32+K34+K38+K39+SUM(K35:K37) -> 217461.42
A45: 2 | B45: 4.11-12-1 Поправка: Гл.12.Прил.8.п.8. 5_12.00.01.11.003 | C45: Установка съемных и выдвижных блоков (модулей, ячеек, ТЭЗ) массой до 5 кг | D45: =Source!H36 -> 1 ШТ. | E45: =Source!I36 -> 4 | Q45: =Source!X36 -> 48.64 | R45: =Source!X37 -> 2674.49 | S45: =Source!Y36 -> 24.86 | T45: =Source!Y37 -> 1366.96 | U45: =ROUND((175/100)*ROUND(Source!R36, 2), 2) -> 0.65 | V45: =ROUND((0/100)*ROUND(Source!R37, 2), 2) -> 0 | AC45: 0
C46: ="Объем: "&Source!I36&"=1+"&"1+"&"1+"&"1" -> Объем: 4=1+1+1+1
C47: ЗП | F47: =Source!AO36 -> 11.65 | G47: 1,1 | H47: =Source!AV37 -> 1.047 | I47: =Source!S36 -> 53.67 | J47: =IF(Source!BA37<> 0, Source!BA37, 1) -> 54.99 | K47: =Source!S37 -> 2951.31
C48: ЭМ | F48: =Source!AM36 -> 0.5 | G48: 1,1 | H48: =Source!AV37 -> 1.047 | I48: =Source!Q36 -> 2.3 | J48: =IF(Source!BB37<> 0, Source!BB37, 1) -> 16.26 | K48: =Source!Q37 -> 37.4
C49: в т.ч. ЗПМ | F49: =Source!AN36 -> 0.08 | G49: 1,1 | H49: =Source!AV37 -> 1.047 | I49: =Source!R36 -> 0.37 | J49: =IF(Source!BS37<> 0, Source!BS37, 1) -> 54.99 | K49: =Source!R37 -> 20.35
A50: 2,1 | B50: =Source!F38 -> КА 3 | C50: ОБОРУДОВАНИЕ:_x000D_ Вентиляторная панель 60А-91-11-30ВL 3 213,03 = [28 334 / 1,2 / 7,66] + 3% Трансп + 1,2% Заг.скл | D50: =Source!H38 -> шт. | E50: =Source!I38 -> 1 | F50: =Source!AK38 -> 3213.03 | H50: =Source!AW39 -> 1 | I50: =Source!O38 -> 3213.03 | J50: =IF(Source!BC39<> 0, Source!BC39, 1) -> 7.66 | K50: =Source!O39 -> 24611.81 | Q50: =Source!X38 -> 0 | R50: =Source!X39 -> 0 | S50: =Source!Y38 -> 0 | T50: =Source!Y39 -> 0 | U50: =ROUND((175/100)*ROUND(Source!R38, 2), 2) -> 0 | V50: =ROUND((0/100)*ROUND(Source!R39, 2), 2) -> 0 | AC50: 5
A51: 2,2 | B51: =Source!F40 -> КА 5 | C51: Выдвижная полка для клавиатуры 60А-04-45-11BL 553,19 = [6 430 / 1,2 / 9,88] + 2% Заг.скл | D51: =Source!H40 -> шт. | E51: =Source!I40 -> 1 | F51: =Source!AK40 -> 553.19 | H51: =Source!AW41 -> 1 | I51: =Source!O40 -> 553.19 | J51: =IF(Source!BC41<> 0, Source!BC41, 1) -> 9.88 | K51: =Source!O41 -> 5465.52 | Q51: =Source!X40 -> 0 | R51: =Source!X41 -> 0 | S51: =Source!Y40 -> 0 | T51: =Source!Y41 -> 0 | U51: =ROUND((175/100)*ROUND(Source!R40, 2), 2) -> 0 | V51: =ROUND((0/100)*ROUND(Source!R41, 2), 2) -> 0 | AC51: 3
A52: 2,3 | B52: =Source!F42 -> КА 6 | C52: Полка сmацuонарная регулuруемая 1U до 50кг, 370мм, для 600мм 381,47 = [4 434 / 1,2 / 9,88] + 2% Заг.скл | D52: =Source!H42 -> шт. | E52: =Source!I42 -> 1 | F52: =Source!AK42 -> 381.47 | H52: =Source!AW43 -> 1 | I52: =Source!O42 -> 381.47 | J52: =IF(Source!BC43<> 0, Source!BC43, 1) -> 9.88 | K52: =Source!O43 -> 3768.92 | Q52: =Source!X42 -> 0 | R52: =Source!X43 -> 0 | S52: =Source!Y42 -> 0 | T52: =Source!Y43 -> 0 | U52: =ROUND((175/100)*ROUND(Source!R42, 2), 2) -> 0 | V52: =ROUND((0/100)*ROUND(Source!R43, 2), 2) -> 0 | AC52: 3
A53: 2,4 | B53: =Source!F44 -> КА 8 | C53: Панель освещенuя на магнumах, унuверсальная цвеm черныu 60A-05-15BL 720,68 = [8 376,8 / 1,2 / 9,88] + 2% Заг.скл | D53: =Source!H44 -> шт. | E53: =Source!I44 -> 1 | F53: =Source!AK44 -> 720.68 | H53: =Source!AW45 -> 1 | I53: =Source!O44 -> 720.68 | J53: =IF(Source!BC45<> 0, Source!BC45, 1) -> 9.88 | K53: =Source!O45 -> 7120.32 | Q53: =Source!X44 -> 0 | R53: =Source!X45 -> 0 | S53: =Source!Y44 -> 0 | T53: =Source!Y45 -> 0 | U53: =ROUND((175/100)*ROUND(Source!R44, 2), 2) -> 0 | V53: =ROUND((0/100)*ROUND(Source!R45, 2), 2) -> 0 | AC53: 3
C54: НР от ФОТ | D54: % | E54: =Source!BZ37 -> 90 | I54: =SUM(Q45:Q53) -> 48.64 | J54: =Source!AT37 -> 90 | K54: =SUM(R45:R53) -> 2674.49
C55: СП от ФОТ | D55: % | E55: =Source!CA37 -> 46 | I55: =SUM(S45:S54) -> 24.86 | J55: =Source!AU37 -> 46 | K55: =SUM(T45:T54) -> 1366.96
C56: ЗТР | D56: чел-ч | E56: =Source!AQ36 -> 1.03 | G56: 1,1 | H56: =Source!AV37 -> 1.047 | I56: =Source!U36 -> 4.745004
C57: ВСЕГО работ по позиции: | H57: =I47+I48+I54+I55+SUM(I50:I53)-SUMIF(AC50:AC53, 5, I50:I53)-SUMIF(AC50:AC53, 6, I50:I53) -> 1784.81 | J57: =K47+K48+K54+K55+SUM(K50:K53)-SUMIF(AC50:AC53, 5, K50:K53)-SUMIF(AC50:AC53, 6, K50:K53) -> 23384.92
C58: ВСЕГО оборудование по позиции: | H58: =SUMIF(AC50:AC53, 5, I50:I53)+SUMIF(AC50:AC53, 6, I50:I53) -> 3213.03 | J58: =SUMIF(AC50:AC53, 5, K50:K53)+SUMIF(AC50:AC53, 6, K50:K53) -> 24611.81
C59: ВСЕГО по позиции: | H59: =I47+I48+I54+I55+SUM(I50:I53) -> 4997.84 | J59: =K47+K48+K54+K55+SUM(K50:K53) -> 47996.73 | O59: =I47+I48+I54+I55+SUM(I50:I53) -> 4997.84 | P59: =K47+K48+K54+K55+SUM(K50:K53) -> 47996.73
A61: 3 | B61: 4.11-14-1 Поправка: Гл.12.Прил.8.п.8. 5_12.00.01.11.003 | C61: Включение штепсельных разъемов в аппаратуру, количество контактов в разъеме до 14 | D61: =Source!H46 -> 1 разъем | E61: =Source!I46 -> 1 | Q61: =Source!X46 -> 2.61 | R61: =Source!X47 -> 143.52 | S61: =Source!Y46 -> 1.33 | T61: =Source!Y47 -> 73.36 | U61: =ROUND((175/100)*ROUND(Source!R46, 2), 2) -> 0 | V61: =ROUND((0/100)*ROUND(Source!R47, 2), 2) -> 0 | AC61: 0
C62: ЗП | F62: =Source!AO46 -> 2.52 | G62: 1,1 | H62: =Source!AV47 -> 1.047 | I62: =Source!S46 -> 2.9 | J62: =IF(Source!BA47<> 0, Source!BA47, 1) -> 54.99 | K62: =Source!S47 -> 159.47
A63: 3,1 | B63: =Source!F48 -> КА 4 | C63: Шнур питания для вент. панели IEC 320 C14 55,92 = [650 / 1,2 / 9,88] + 2% Заг.скл | D63: =Source!H48 -> шт. | E63: =Source!I48 -> 1 | F63: =Source!AK48 -> 55.92 | H63: =Source!AW49 -> 1 | I63: =Source!O48 -> 55.92 | J63: =IF(Source!BC49<> 0, Source!BC49, 1) -> 9.88 | K63: =Source!O49 -> 552.49 | Q63: =Source!X48 -> 0 | R63: =Source!X49 -> 0 | S63: =Source!Y48 -> 0 | T63: =Source!Y49 -> 0 | U63: =ROUND((175/100)*ROUND(Source!R48, 2), 2) -> 0 | V63: =ROUND((0/100)*ROUND(Source!R49, 2), 2) -> 0 | AC63: 3
C64: НР от ФОТ | D64: % | E64: =Source!BZ47 -> 90 | I64: =SUM(Q61:Q63) -> 2.61 | J64: =Source!AT47 -> 90 | K64: =SUM(R61:R63) -> 143.52
C65: СП от ФОТ | D65: % | E65: =Source!CA47 -> 46 | I65: =SUM(S61:S64) -> 1.33 | J65: =Source!AU47 -> 46 | K65: =SUM(T61:T64) -> 73.36
C66: ЗТР | D66: чел-ч | E66: =Source!AQ46 -> 0.22 | G66: 1,1 | H66: =Source!AV47 -> 1.047 | I66: =Source!U46 -> 0.253374
C67: ВСЕГО работ по позиции: | H67: =I62+I64+I65+SUM(I63:I63)-SUMIF(AC63:AC63, 5, I63:I63)-SUMIF(AC63:AC63, 6, I63:I63) -> 62.76 | J67: =K62+K64+K65+SUM(K63:K63)-SUMIF(AC63:AC63, 5, K63:K63)-SUMIF(AC63:AC63, 6, K63:K63) -> 928.84
C68: ВСЕГО оборудование по позиции: | H68: =SUMIF(AC63:AC63, 5, I63:I63)+SUMIF(AC63:AC63, 6, I63:I63) -> 0 | J68: =SUMIF(AC63:AC63, 5, K63:K63)+SUMIF(AC63:AC63, 6, K63:K63) -> 0
C69: ВСЕГО по позиции: | H69: =I62+I64+I65+SUM(I63:I63) -> 62.76 | J69: =K62+K64+K65+SUM(K63:K63) -> 928.84 | O69: =I62+I64+I65+SUM(I63:I63) -> 62.76 | P69: =K62+K64+K65+SUM(K63:K63) -> 928.84
A72: =CONCATENATE("Итого по разделу: ",IF(Source!G51<>"Новый раздел", Source!G51, "")) -> Итого по разделу: Телекоммуникационный шкаф 47U 19" ШТ1-01 | H72: =SUM(O29:O71) -> 25879.44 | J72: =SUM(P29:P71) -> 266386.99
A73: Итого по ТСН-2001.16 | I73: =SUM(W29:W72) -> 0 | J73: =SUM(X29:X72) -> 0
A74: Итого возвратных сумм | I74: =SUM(Y29:Y73) -> 0 | J74: =SUM(Z29:Z73) -> 0
A76: =CONCATENATE("Раздел: ",IF(Source!G81<>"Новый раздел", Source!G81, "")) -> Раздел: Телекоммуникационный шкаф 42U 19" ШТ1-2,1-3,1-4; ШТ2-5,2-6; ШТ3-7,3-8
A77: 4 | B77: 4.10-32-1 Поправка: Гл.12.Прил.8.п.8. 5_12.00.01.11.003 | C77: Монтаж стойки, полустойки, каркаса стойки или шкафа массой до 100 кг | D77: =Source!H85 -> 1 ШТ. | E77: =Source!I85 -> 7 | Q77: =Source!X85 -> 695.39 | R77: =Source!X86 -> 38239.22 | S77: =Source!Y85 -> 355.42 | T77: =Source!Y86 -> 19544.49 | U77: =ROUND((175/100)*ROUND(Source!R85, 2), 2) -> 58.7 | V77: =ROUND((0/100)*ROUND(Source!R86, 2), 2) -> 0 | AC77: 0
C78: ЗП | F78: =Source!AO85 -> 91.68 | G78: 1,1 | H78: =Source!AV86 -> 1.047 | I78: =Source!S85 -> 739.11 | J78: =IF(Source!BA86<> 0, Source!BA86, 1) -> 54.99 | K78: =Source!S86 -> 40643.66
C79: ЭМ | F79: =Source!AM85 -> 38.92 | G79: 1,1 | H79: =Source!AV86 -> 1.047 | I79: =Source!Q85 -> 313.77 | J79: =IF(Source!BB86<> 0, Source!BB86, 1) -> 15.29 | K79: =Source!Q86 -> 4797.54
C80: в т.ч. ЗПМ | F80: =Source!AN85 -> 4.16 | G80: 1,1 | H80: =Source!AV86 -> 1.047 | I80: =Source!R85 -> 33.54 | J80: =IF(Source!BS86<> 0, Source!BS86, 1) -> 54.99 | K80: =Source!R86 -> 1844.36
C81: МР | F81: =Source!AL85 -> 3.92 | H81: =Source!AW86 -> 1 | I81: =Source!P85 -> 27.44 | J81: =IF(Source!BC86<> 0, Source!BC86, 1) -> 8.3 | K81: =Source!P86 -> 227.75
A82: 4,1 | B82: =Source!F87 -> КА 9 | C82: Шкаф 19" серии Racknet S3000, 42U 60F-42-88-31BL 14 177,70 = [164 795 / 1,2 / 9,88] + 2% Заг.скл | D82: =Source!H87 -> шт. | E82: =Source!I87 -> 7 | F82: =Source!AK87 -> 14177.7 | H82: =Source!AW88 -> 1 | I82: =Source!O87 -> 99243.9 | J82: =IF(Source!BC88<> 0, Source!BC88, 1) -> 9.88 | K82: =Source!O88 -> 980529.73 | Q82: =Source!X87 -> 0 | R82: =Source!X88 -> 0 | S82: =Source!Y87 -> 0 | T82: =Source!Y88 -> 0 | U82: =ROUND((175/100)*ROUND(Source!R87, 2), 2) -> 0 | V82: =ROUND((0/100)*ROUND(Source!R88, 2), 2) -> 0 | AC82: 3
A83: 4,2 | B83: =Source!F89 -> КА 10 | C83: Вертикальный органайзер 60А-18-42-01-31BL 3 232,45 = [37 572,47 / 1,2 / 9,88] + 2% Заг.скл | D83: =Source!H89 -> шт. | E83: =Source!I89 -> 7 | F83: =Source!AK89 -> 3232.45 | H83: =Source!AW90 -> 1 | I83: =Source!O89 -> 22627.15 | J83: =IF(Source!BC90<> 0, Source!BC90, 1) -> 9.88 | K83: =Source!O90 -> 223556.24 | Q83: =Source!X89 -> 0 | R83: =Source!X90 -> 0 | S83: =Source!Y89 -> 0 | T83: =Source!Y90 -> 0 | U83: =ROUND((175/100)*ROUND(Source!R89, 2), 2) -> 0 | V83: =ROUND((0/100)*ROUND(Source!R90, 2), 2) -> 0 | AC83: 3
A84: 4,3 | B84: =Source!F91 -> КА 11 | C84: Шuна заземленuя 19" (500мм), 20 mочек, 5х15мм 60A-14-11GR 346,71 = [4 030 / 1,2 / 9,88] + 2% Заг.скл | D84: =Source!H91 -> шт. | E84: =Source!I91 -> 8 | F84: =Source!AK91 -> 346.71 | H84: =Source!AW92 -> 1 | I84: =Source!O91 -> 2773.68 | J84: =IF(Source!BC92<> 0, Source!BC92, 1) -> 9.88 | K84: =Source!O92 -> 27403.96 | Q84: =Source!X91 -> 0 | R84: =Source!X92 -> 0 | S84: =Source!Y91 -> 0 | T84: =Source!Y92 -> 0 | U84: =ROUND((175/100)*ROUND(Source!R91, 2), 2) -> 0 | V84: =ROUND((0/100)*ROUND(Source!R92, 2), 2) -> 0 | AC84: 3
A85: 4,4 | B85: =Source!F93 -> КА 7 | C85: Набор для креnленuя лоmков к крышке шкафов, высоmа 50мм 60А-31-08-ЗЗВL 147,62 = [1 715,95 / 1,2 / 9,88] + 2% Заг.скл | D85: =Source!H93 -> шт. | E85: =Source!I93 -> 7 | F85: =Source!AK93 -> 147.62 | H85: =Source!AW94 -> 1 | I85: =Source!O93 -> 1033.34 | J85: =IF(Source!BC94<> 0, Source!BC94, 1) -> 9.88 | K85: =Source!O94 -> 10209.4 | Q85: =Source!X93 -> 0 | R85: =Source!X94 -> 0 | S85: =Source!Y93 -> 0 | T85: =Source!Y94 -> 0 | U85: =ROUND((175/100)*ROUND(Source!R93, 2), 2) -> 0 | V85: =ROUND((0/100)*ROUND(Source!R94, 2), 2) -> 0 | AC85: 3
C86: НР от ФОТ | D86: % | E86: =Source!BZ86 -> 90 | I86: =SUM(Q77:Q85) -> 695.39 | J86: =Source!AT86 -> 90 | K86: =SUM(R77:R85) -> 38239.22
C87: СП от ФОТ | D87: % | E87: =Source!CA86 -> 46 | I87: =SUM(S77:S86) -> 355.42 | J87: =Source!AU86 -> 46 | K87: =SUM(T77:T86) -> 19544.49
C88: ЗТР | D88: чел-ч | E88: =Source!AQ85 -> 8.2 | G88: 1,1 | H88: =Source!AV86 -> 1.047 | I88: =Source!U85 -> 66.10758
C89: ВСЕГО работ по позиции: | H89: =I78+I79+I81+I86+I87+SUM(I82:I85)-SUMIF(AC82:AC85, 5, I82:I85)-SUMIF(AC82:AC85, 6, I82:I85) -> 127809.2 | J89: =K78+K79+K81+K86+K87+SUM(K82:K85)-SUMIF(AC82:AC85, 5, K82:K85)-SUMIF(AC82:AC85, 6, K82:K85) -> 1345152
C90: ВСЕГО оборудование по позиции: | H90: =SUMIF(AC82:AC85, 5, I82:I85)+SUMIF(AC82:AC85, 6, I82:I85) -> 0 | J90: =SUMIF(AC82:AC85, 5, K82:K85)+SUMIF(AC82:AC85, 6, K82:K85) -> 0
C91: ВСЕГО по позиции: | H91: =I78+I79+I81+I86+I87+SUM(I82:I85) -> 127809.2 | J91: =K78+K79+K81+K86+K87+SUM(K82:K85) -> 1345152 | O91: =I78+I79+I81+I86+I87+SUM(I82:I85) -> 127809.2 | P91: =K78+K79+K81+K86+K87+SUM(K82:K85) -> 1345152
A93: 5 | B93: 4.11-14-1 Поправка: Гл.12.Прил.8.п.8. 5_12.00.01.11.003 | C93: Включение штепсельных разъемов в аппаратуру, количество контактов в разъеме до 14 | D93: =Source!H95 -> 1 разъем | E93: =Source!I95 -> 71 | Q93: =Source!X95 -> 185.45 | R93: =Source!X96 -> 10198.12 | S93: =Source!Y95 -> 94.79 | T93: =Source!Y96 -> 5212.37 | U93: =ROUND((175/100)*ROUND(Source!R95, 2), 2) -> 0 | V93: =ROUND((0/100)*ROUND(Source!R96, 2), 2) -> 0 | AC93: 0
C94: ="Объем: "&Source!I95&"=7+"&"8*"&"8" -> Объем: 71=7+8*8
C95: ЗП | F95: =Source!AO95 -> 2.52 | G95: 1,1 | H95: =Source!AV96 -> 1.047 | I95: =Source!S95 -> 206.06 | J95: =IF(Source!BA96<> 0, Source!BA96, 1) -> 54.99 | K95: =Source!S96 -> 11331.24
A96: 5,1 | B96: =Source!F97 -> КА 4 | C96: Шнур питания для вент. панели IEC 320 C14 55,92 = [650 / 1,2 / 9,88] + 2% Заг.скл | D96: =Source!H97 -> шт. | E96: =Source!I97 -> 7 | F96: =Source!AK97 -> 55.92 | H96: =Source!AW98 -> 1 | I96: =Source!O97 -> 391.44 | J96: =IF(Source!BC98<> 0, Source!BC98, 1) -> 9.88 | K96: =Source!O98 -> 3867.43 | Q96: =Source!X97 -> 0 | R96: =Source!X98 -> 0 | S96: =Source!Y97 -> 0 | T96: =Source!Y98 -> 0 | U96: =ROUND((175/100)*ROUND(Source!R97, 2), 2) -> 0 | V96: =ROUND((0/100)*ROUND(Source!R98, 2), 2) -> 0 | AC96: 3
A97: 5,2 | B97: =Source!F99 -> КА 12 | C97: Набор nроводов заземленuя, 4 nровода 250ммх4мм2, 4 nровода, 150мм х4мм2 60A-14-13GR 164,59 = [1 913,04 / 1,2 / 9,88] + 2% Заг.скл | D97: =Source!H99 -> шт. | E97: =Source!I99 -> 8 | F97: =Source!AK99 -> 164.59 | H97: =Source!AW100 -> 1 | I97: =Source!O99 -> 1316.72 | J97: =IF(Source!BC100<> 0, Source!BC100, 1) -> 9.88 | K97: =Source!O100 -> 13009.19 | Q97: =Source!X99 -> 0 | R97: =Source!X100 -> 0 | S97: =Source!Y99 -> 0 | T97: =Source!Y100 -> 0 | U97: =ROUND((175/100)*ROUND(Source!R99, 2), 2) -> 0 | V97: =ROUND((0/100)*ROUND(Source!R100, 2), 2) -> 0 | AC97: 3
C98: НР от ФОТ | D98: % | E98: =Source!BZ96 -> 90 | I98: =SUM(Q93:Q97) -> 185.45 | J98: =Source!AT96 -> 90 | K98: =SUM(R93:R97) -> 10198.12
C99: СП от ФОТ | D99: % | E99: =Source!CA96 -> 46 | I99: =SUM(S93:S98) -> 94.79 | J99: =Source!AU96 -> 46 | K99: =SUM(T93:T98) -> 5212.37
C100: ЗТР | D100: чел-ч | E100: =Source!AQ95 -> 0.22 | G100: 1,1 | H100: =Source!AV96 -> 1.047 | I100: =Source!U95 -> 17.989554
C101: ВСЕГО работ по позиции: | H101: =I95+I98+I99+SUM(I96:I97)-SUMIF(AC96:AC97, 5, I96:I97)-SUMIF(AC96:AC97, 6, I96:I97) -> 2194.46 | J101: =K95+K98+K99+SUM(K96:K97)-SUMIF(AC96:AC97, 5, K96:K97)-SUMIF(AC96:AC97, 6, K96:K97) -> 43618.35
C102: ВСЕГО оборудование по позиции: | H102: =SUMIF(AC96:AC97, 5, I96:I97)+SUMIF(AC96:AC97, 6, I96:I97) -> 0 | J102: =SUMIF(AC96:AC97, 5, K96:K97)+SUMIF(AC96:AC97, 6, K96:K97) -> 0
C103: ВСЕГО по позиции: | H103: =I95+I98+I99+SUM(I96:I97) -> 2194.46 | J103: =K95+K98+K99+SUM(K96:K97) -> 43618.35 | O103: =I95+I98+I99+SUM(I96:I97) -> 2194.46 | P103: =K95+K98+K99+SUM(K96:K97) -> 43618.35
A105: 6 | B105: 4.11-12-1 Поправка: Гл.12.Прил.8.п.8. 5_12.00.01.11.003 | C105: Установка съемных и выдвижных блоков (модулей, ячеек, ТЭЗ) массой до 5 кг | D105: =Source!H101 -> 1 ШТ. | E105: =Source!I101 -> 28 | Q105: =Source!X101 -> 340.43 | R105: =Source!X102 -> 18720.46 | S105: =Source!Y101 -> 174 | T105: =Source!Y102 -> 9568.23 | U105: =ROUND((175/100)*ROUND(Source!R101, 2), 2) -> 4.52 | V105: =ROUND((0/100)*ROUND(Source!R102, 2), 2) -> 0 | AC105: 0
C106: ="Объем: "&Source!I101&"=7+"&"7+"&"7+"&"7" -> Объем: 28=7+7+7+7
C107: ЗП | F107: =Source!AO101 -> 11.65 | G107: 1,1 | H107: =Source!AV102 -> 1.047 | I107: =Source!S101 -> 375.68 | J107: =IF(Source!BA102<> 0, Source!BA102, 1) -> 54.99 | K107: =Source!S102 -> 20658.64
C108: ЭМ | F108: =Source!AM101 -> 0.5 | G108: 1,1 | H108: =Source!AV102 -> 1.047 | I108: =Source!Q101 -> 16.12 | J108: =IF(Source!BB102<> 0, Source!BB102, 1) -> 16.26 | K108: =Source!Q102 -> 262.11
C109: в т.ч. ЗПМ | F109: =Source!AN101 -> 0.08 | G109: 1,1 | H109: =Source!AV102 -> 1.047 | I109: =Source!R101 -> 2.58 | J109: =IF(Source!BS102<> 0, Source!BS102, 1) -> 54.99 | K109: =Source!R102 -> 141.87
A110: 6,1 | B110: =Source!F103 -> КА 3 | C110: ОБОРУДОВАНИЕ:_x000D_ Вентиляторная панель 60А-91-11-30ВL 3 213,03 = [28 334 / 1,2 / 7,66] + 3% Трансп + 1,2% Заг.скл | D110: =Source!H103 -> шт. | E110: =Source!I103 -> 7 | F110: =Source!AK103 -> 3213.03 | H110: =Source!AW104 -> 1 | I110: =Source!O103 -> 22491.21 | J110: =IF(Source!BC104<> 0, Source!BC104, 1) -> 7.66 | K110: =Source!O104 -> 172282.67 | Q110: =Source!X103 -> 0 | R110: =Source!X104 -> 0 | S110: =Source!Y103 -> 0 | T110: =Source!Y104 -> 0 | U110: =ROUND((175/100)*ROUND(Source!R103, 2), 2) -> 0 | V110: =ROUND((0/100)*ROUND(Source!R104, 2), 2) -> 0 | AC110: 5
A111: 6,2 | B111: =Source!F105 -> КА 5 | C111: Выдвижная полка для клавиатуры 60А-04-45-11BL 553,19 = [6 430 / 1,2 / 9,88] + 2% Заг.скл | D111: =Source!H105 -> шт. | E111: =Source!I105 -> 7 | F111: =Source!AK105 -> 553.19 | H111: =Source!AW106 -> 1 | I111: =Source!O105 -> 3872.33 | J111: =IF(Source!BC106<> 0, Source!BC106, 1) -> 9.88 | K111: =Source!O106 -> 38258.62 | Q111: =Source!X105 -> 0 | R111: =Source!X106 -> 0 | S111: =Source!Y105 -> 0 | T111: =Source!Y106 -> 0 | U111: =ROUND((175/100)*ROUND(Source!R105, 2), 2) -> 0 | V111: =ROUND((0/100)*ROUND(Source!R106, 2), 2) -> 0 | AC111: 3
A112: 6,3 | B112: =Source!F107 -> КА 6 | C112: Полка сmацuонарная регулuруемая 1U до 50кг, 370мм, для 600мм 381,47 = [4 434 / 1,2 / 9,88] + 2% Заг.скл | D112: =Source!H107 -> шт. | E112: =Source!I107 -> 7 | F112: =Source!AK107 -> 381.47 | H112: =Source!AW108 -> 1 | I112: =Source!O107 -> 2670.29 | J112: =IF(Source!BC108<> 0, Source!BC108, 1) -> 9.88 | K112: =Source!O108 -> 26382.47 | Q112: =Source!X107 -> 0 | R112: =Source!X108 -> 0 | S112: =Source!Y107 -> 0 | T112: =Source!Y108 -> 0 | U112: =ROUND((175/100)*ROUND(Source!R107, 2), 2) -> 0 | V112: =ROUND((0/100)*ROUND(Source!R108, 2), 2) -> 0 | AC112: 3
A113: 6,4 | B113: =Source!F109 -> КА 8 | C113: Панель освещенuя на магнumах, унuверсальная цвеm черныu 60A-05-15BL 720,68 = [8 376,8 / 1,2 / 9,88] + 2% Заг.скл | D113: =Source!H109 -> шт. | E113: =Source!I109 -> 7 | F113: =Source!AK109 -> 720.68 | H113: =Source!AW110 -> 1 | I113: =Source!O109 -> 5044.76 | J113: =IF(Source!BC110<> 0, Source!BC110, 1) -> 9.88 | K113: =Source!O110 -> 49842.23 | Q113: =Source!X109 -> 0 | R113: =Source!X110 -> 0 | S113: =Source!Y109 -> 0 | T113: =Source!Y110 -> 0 | U113: =ROUND((175/100)*ROUND(Source!R109, 2), 2) -> 0 | V113: =ROUND((0/100)*ROUND(Source!R110, 2), 2) -> 0 | AC113: 3
...

Sheet Ведомость объемов работ
A1: =Source!B1 -> Smeta.RU (495) 974-1589
E3: "УТВЕРЖДАЮ"
D5: ___________________________
D7: ___________________________
D9: " ___ " ___________ 20 ___ г.
B12: =CONCATENATE("Ведомость объемов работ ", IF(Source!AN15<>"", Source!AN15," ")) -> Ведомость объемов работ
B13: =CONCATENATE(Source!F12, " ", Source!G12) -> 02-01-12 02-01-12 СКС
A16: № п/п | B16: № в ЛСР | C16: Наименование работ и затрат | D16: Единица измерения | E16: Количество | F16: Ссылка на чертежи, спецификации | G16: Формула расчета, расчет объемов работ и расхода материалов | H16: Примечание
A17: 1 | B17: 2 | C17: 3 | D17: 4 | E17: 5 | F17: 6 | G17: 7 | H17: 8
A18: =CONCATENATE("Локальная смета: ", Source!G20) -> Локальная смета: Структурированная кабельная сеть
A19: =CONCATENATE("Раздел: ", Source!G24) -> Раздел: Телекоммуникационный шкаф 47U 19" ШТ1-01
A20: 1 | B20: =Source!E28 -> 1 | C20: =Source!G28 -> Монтаж стойки, полустойки, каркаса стойки или шкафа массой до 100 кг | D20: 1 ШТ. | E20: =Source!I28 -> 1 | F20: =Source!U24 | G20: =Source!I28 -> 1
A21: 1.1 | B21: =Source!E30 -> 1,1 | C21: =Source!G30 -> Шкаф 19" серии Racknet S3000, 47U 60F-47-7C-94BL | D21: шт. | E21: =Source!I30 -> 1 | F21: =Source!U24
A22: 1.2 | B22: =Source!E32 -> 1,2 | C22: =Source!G32 -> Вертикальный органайзер 60А-18-47-01-31BL | D22: шт. | E22: =Source!I32 -> 1 | F22: =Source!U24
A23: 1.3 | B23: =Source!E34 -> 1,3 | C23: =Source!G34 -> Набор для креnленuя лоmков к крышке шкафов, высоmа 50мм 60А-31-08-ЗЗВL | D23: шт. | E23: =Source!I34 -> 1 | F23: =Source!U24
A24: 2 | B24: =Source!E36 -> 2 | C24: =Source!G36 -> Установка съемных и выдвижных блоков (модулей, ячеек, ТЭЗ) массой до 5 кг | D24: 1 ШТ. | E24: =Source!I36 -> 4 | F24: =Source!U24 | G24: ="=1+"&"1+"&"1+"&"1" -> =1+1+1+1
A25: 2.1 | B25: =Source!E38 -> 2,1 | C25: =Source!G38 -> Вентиляторная панель 60А-91-11-30ВL | D25: шт. | E25: =Source!I38 -> 1 | F25: =Source!U24
A26: 2.2 | B26: =Source!E40 -> 2,2 | C26: =Source!G40 -> Выдвижная полка для клавиатуры 60А-04-45-11BL | D26: шт. | E26: =Source!I40 -> 1 | F26: =Source!U24
A27: 2.3 | B27: =Source!E42 -> 2,3 | C27: =Source!G42 -> Полка сmацuонарная регулuруемая 1U до 50кг, 370мм, для 600мм | D27: шт. | E27: =Source!I42 -> 1 | F27: =Source!U24
A28: 2.4 | B28: =Source!E44 -> 2,4 | C28: =Source!G44 -> Панель освещенuя на магнumах, унuверсальная цвеm черныu 60A-05-15BL | D28: шт. | E28: =Source!I44 -> 1 | F28: =Source!U24
A29: 3 | B29: =Source!E46 -> 3 | C29: =Source!G46 -> Включение штепсельных разъемов в аппаратуру, количество контактов в разъеме до 14 | D29: 1 разъем | E29: =Source!I46 -> 1 | F29: =Source!U24 | G29: =Source!I46 -> 1
A30: 3.1 | B30: =Source!E48 -> 3,1 | C30: =Source!G48 -> Шнур питания для вент. панели IEC 320 C14 | D30: шт. | E30: =Source!I48 -> 1 | F30: =Source!U24
A31: =CONCATENATE("Раздел: ", Source!G81) -> Раздел: Телекоммуникационный шкаф 42U 19" ШТ1-2,1-3,1-4; ШТ2-5,2-6; ШТ3-7,3-8
A32: 4 | B32: =Source!E85 -> 4 | C32: =Source!G85 -> Монтаж стойки, полустойки, каркаса стойки или шкафа массой до 100 кг | D32: 1 ШТ. | E32: =Source!I85 -> 7 | F32: =Source!U81 | G32: =Source!I85 -> 7
A33: 4.1 | B33: =Source!E87 -> 4,1 | C33: =Source!G87 -> Шкаф 19" серии Racknet S3000, 42U 60F-42-88-31BL | D33: шт. | E33: =Source!I87 -> 7 | F33: =Source!U81
A34: 4.2 | B34: =Source!E89 -> 4,2 | C34: =Source!G89 -> Вертикальный органайзер 60А-18-42-01-31BL | D34: шт. | E34: =Source!I89 -> 7 | F34: =Source!U81
A35: 4.3 | B35: =Source!E91 -> 4,3 | C35: =Source!G91 -> Шuна заземленuя 19" (500мм), 20 mочек, 5х15мм 60A-14-11GR | D35: шт. | E35: =Source!I91 -> 8 | F35: =Source!U81
A36: 4.4 | B36: =Source!E93 -> 4,4 | C36: =Source!G93 -> Набор для креnленuя лоmков к крышке шкафов, высоmа 50мм 60А-31-08-ЗЗВL | D36: шт. | E36: =Source!I93 -> 7 | F36: =Source!U81
A37: 5 | B37: =Source!E95 -> 5 | C37: =Source!G95 -> Включение штепсельных разъемов в аппаратуру, количество контактов в разъеме до 14 | D37: 1 разъем | E37: =Source!I95 -> 71 | F37: =Source!U81 | G37: ="=7+"&"8*"&"8" -> =7+8*8
A38: 5.1 | B38: =Source!E97 -> 5,1 | C38: =Source!G97 -> Шнур питания для вент. панели IEC 320 C14 | D38: шт. | E38: =Source!I97 -> 7 | F38: =Source!U81
A39: 5.2 | B39: =Source!E99 -> 5,2 | C39: =Source!G99 -> Набор nроводов заземленuя, 4 nровода 250ммх4мм2, 4 nровода, 150мм х4мм2 60A-14-13GR | D39: шт. | E39: =Source!I99 -> 8 | F39: =Source!U81
A40: 6 | B40: =Source!E101 -> 6 | C40: =Source!G101 -> Установка съемных и выдвижных блоков (модулей, ячеек, ТЭЗ) массой до 5 кг | D40: 1 ШТ. | E40: =Source!I101 -> 28 | F40: =Source!U81 | G40: ="=7+"&"7+"&"7+"&"7" -> =7+7+7+7
A41: 6.1 | B41: =Source!E103 -> 6,1 | C41: =Source!G103 -> Вентиляторная панель 60А-91-11-30ВL | D41: шт. | E41: =Source!I103 -> 7 | F41: =Source!U81
A42: 6.2 | B42: =Source!E105 -> 6,2 | C42: =Source!G105 -> Выдвижная полка для клавиатуры 60А-04-45-11BL | D42: шт. | E42: =Source!I105 -> 7 | F42: =Source!U81
A43: 6.3 | B43: =Source!E107 -> 6,3 | C43: =Source!G107 -> Полка сmацuонарная регулuруемая 1U до 50кг, 370мм, для 600мм | D43: шт. | E43: =Source!I107 -> 7 | F43: =Source!U81
A44: 6.4 | B44: =Source!E109 -> 6,4 | C44: =Source!G109 -> Панель освещенuя на магнumах, унuверсальная цвеm черныu 60A-05-15BL | D44: шт. | E44: =Source!I109 -> 7 | F44: =Source!U81
A45: =CONCATENATE("Раздел: ", Source!G142) -> Раздел: Источники электропитания
A46: 7 | B46: =Source!E146 -> 7 | C46: =Source!G146 -> Монтаж отдельно устанавливаемого преобразователя или блока питания | D46: 1 ШТ. | E46: =Source!I146 -> 8 | F46: =Source!U142 | G46: =Source!I146 -> 8
A47: 7.1 | B47: =Source!E148 -> 7,1 | C47: =Source!G148 -> Болты строительные с гайками, оцинкованные, М10х100 мм | D47: т | E47: =Source!I148 -> 0.0024 | F47: =Source!U142
A48: 7.2 | B48: =Source!E150 -> 7,2 | C48: =Source!G150 -> Наконечник кабельный, латунный, кольцевой, неизолированный, для жил сечением от 1,0 до 2,5 мм2 | D48: шт. | E48: =Source!I150 -> 80 | F48: =Source!U142
A49: 7.3 | B49: =Source!E152 -> 7,3 | C49: =Source!G152 -> ИБП ДКС Small-UPS Rackmount 3000VA/2700W 230B, 9A/ч | D49: шт. | E49: =Source!I152 -> 8 | F49: =Source!U142
A50: 7.4 | B50: =Source!E154 -> 7,4 | C50: =Source!G154 -> Батарейный блок Small-R3AO Rack BPSMLR3-96V | D50: шт. | E50: =Source!I154 -> 8 | F50: =Source!U142
A51: 8 | B51: =Source!E156 -> 8 | C51: =Source!G156 -> Установка прибора массой до 5 кг на металлоконструкциях или щитах | D51: 1 ШТ. | E51: =Source!I156 -> 16 | F51: =Source!U142 | G51: =Source!I156 -> 16
A52: 8.1 | B52: =Source!E158 -> 8,1 | C52: =Source!G158 -> Блок базовый распределения питания, 8 выходных розеток | D52: шт. | E52: =Source!I158 -> 16 | F52: =Source!U142
A53: =CONCATENATE("Раздел: ", Source!G191) -> Раздел: Материалы
A54: 9 | B54: =Source!E195 -> 9 | C54: =Source!G195 -> Монтаж платы дополнительной, устанавливаемой на готовом месте стойки | D54: 1 ШТ. | E54: =Source!I195 -> 33 | F54: =Source!U191 | G54: ="=12+"&"6+"&"1+"&"13+"&"1" -> =12+6+1+13+1
A55: 9.1 | B55: =Source!E197 -> 9,1 | C55: =Source!G197 -> Коммутационная панель кат. 5е PLHD-48 Dual IDC-1U | D55: шт. | E55: =Source!I197 -> 12 | F55: =Source!U191
A56: 9.2 | B56: =Source!E199 -> 9,2 | C56: =Source!G199 -> Коммутационная панель кат. 5е PLHD-24 Dual IDC-1U | D56: шт. | E56: =Source!I199 -> 6 | F56: =Source!U191
A57: 9.3 | B57: =Source!E201 -> 9,3 | C57: =Source!G201 -> Горuзонmальныu органайзер, слоmовыu с крышкой, белый, 1U MX-CMC-1U-45-B | D57: шт. | E57: =Source!I201 -> 63 | F57: =Source!U191
A58: 9.4 | B58: =Source!E203 -> 9,4 | C58: =Source!G203 -> Оптическая панель кроссовая КСП-19-3U-64FC/UPC-ОМ3 50/125 | D58: шт. | E58: =Source!I203 -> 1 | F58: =Source!U191
A59: 9.5 | B59: =Source!E205 -> 9,5 | C59: =Source!G205 -> Оптическая панель кроссовая 1U-RU24-LC/MM-4d-8-1 | D59: шт. | E59: =Source!I205 -> 13 | F59: =Source!U191
A60: 9.6 | B60: =Source!E207 -> 9,6 | C60: =Source!G207 -> Фальш-панель 1U | D60: шт. | E60: =Source!I207 -> 1 | F60: =Source!U191
A61: 10 | B61: =Source!E209 -> 10 | C61: =Source!G209 -> Установка съемных и выдвижных блоков (модулей, ячеек, ТЭЗ) массой до 5 кг | D61: 1 ШТ. | E61: =Source!I209 -> 8 | F61: =Source!U191 | G61: =Source!I209 -> 8
A62: 10.1 | B62: =Source!E211 -> 10,1 | C62: =Source!G211 -> Консольная полка 60А-01-30-08BL | D62: шт. | E62: =Source!I211 -> 8 | F62: =Source!U191
A63: 11 | B63: =Source!E213 -> 11 | C63: =Source!G213 -> Монтаж розетки штепсельной трехполюсной | D63: 100 шт. | E63: =Source!I213 -> 3.65 | F63: =Source!U191 | G63: ="=(90+"&"187+"&"44+"&"44)/"&"100" -> =(90+187+44+44)/100
A64: 11.1 | B64: =Source!E215 -> 11,1 | C64: =Source!G215 -> Болты строительные с гайками, оцинкованные, М10х100 мм | D64: т | E64: =Source!I215 -> 0.005475 | F64: =Source!U191
A65: 11.2 | B65: =Source!E217 -> 11,2 | C65: =Source!G217 -> Втулки полихлорвиниловые | D65: 100 шт. | E65: =Source!I217 -> 3.723 | F65: =Source!U191
A66: 11.3 | B66: =Source!E219 -> 11,3 | C66: =Source!G219 -> Розетка локальной сети, разъем RJ-45, скрытой установки, раздельная, 1-местная, степень защиты IP20 | D66: шт. | E66: =Source!I219 -> 90 | F66: =Source!U191
A67: 11.4 | B67: =Source!E221 -> 11,4 | C67: =Source!G221 -> Розетка локальной сети, разъем RJ-45, скрытой установки, раздельная, 2-местная BR-U21-D-31-R01 | D67: шт. | E67: =Source!I221 -> 187 | F67: =Source!U191
A68: 11.5 | B68: =Source!E223 -> 11,5 | C68: =Source!G223 -> Коробка для установки выключателей, переключателей, штепсельных розеток в сборных гипсовых перегородках | D68: шт. | E68: =Source!I223 -> 1 | F68: =Source!U191
A69: 11.6 | B69: =Source!E225 -> 11,6 | C69: =Source!G225 -> Розетка HDMI BR-H10-K01 | D69: шт. | E69: =Source!I225 -> 44 | F69: =Source!U191
A70: 11.7 | B70: =Source!E227 -> 11,7 | C70: =Source!G227 -> Розетка USB одноместная BR-U21-D-31-R01 | D70: шт. | E70: =Source!I227 -> 44 | F70: =Source!U191
A71: 12 | B71: =Source!E229 -> 12 | C71: =Source!G229 -> Монтаж коммутатора испытательно-измерительного | D71: 1 ШТ. | E71: =Source!I229 -> 12 | F71: =Source!U191 | G71: =Source!I229 -> 12
A72: 12.1 | B72: =Source!E231 -> 12,1 | C72: =Source!G231 -> Коммутатор доступа 48 портов уровня L3 MES2448B | D72: шт. | E72: =Source!I231 -> 12 | F72: =Source!U191
A73: 13 | B73: =Source!E233 -> 13 | C73: =Source!G233 -> Монтаж и настройка электронных АТС типа Миником DX-500, станция с количеством номеров до 100, монтаж станции | D73: 100 номеров | E73: =Source!I233 -> 0.5 | F73: =Source!U191 | G73: ="=50/"&"100" -> =50/100
A74: 13.1 | B74: =Source!E235 -> 13,1 | C74: =Source!G235 -> Гибридная IP-ATC на 50 абонентов Artcom TC50 | D74: шт. | E74: =Source!I235 -> 1 | F74: =Source!U191
A75: 14 | B75: =Source!E237 -> 14 | C75: =Source!G237 -> Монтаж телефонного аппарата настольного системы ЦБ или АТС | D75: 1 ШТ. | E75: =Source!I237 -> 21 | F75: =Source!U191 | G75: =Source!I237 -> 21
A76: 14.1 | B76: =Source!E239 -> 14,1 | C76: =Source!G239 -> IP-телефон VP-30P-WB | D76: шт. | E76: =Source!I239 -> 21 | F76: =Source!U191
A77: =CONCATENATE("Раздел: ", Source!G272) -> Раздел: Кабель, трубы
A78: 15 | B78: =Source!E276 -> 15 | C78: =Source!G276 -> Прокладка кабеля связи симметричного для цифровых систем передачи в трубах гофрированных: по бетонным и кирпичным поверхностям стен и потолка | D78: 100 м | E78: =Source!I276 -> 84.4 | F78: =Source!U272 | G78: ="=8440/"&"100" -> =8440/100
A79: 15.1 | B79: =Source!E278 -> 15,1 | C79: =Source!G278 -> Трубы из непластифицированного вторичного ПВХ, гладкие, самозатухающие, усиленного типа, наружный диаметр 25 мм, толщина стенки 1,5 мм, для электропроводок | D79: м | E79: =Source!I278 -> 8608.8 | F79: =Source!U272
A80: 15.2 | B80: =Source!E280 -> 15,2 | C80: =Source!G280 -> Держатель пластиковый с защелкой для крепления труб, рукавов и гибких вводов диаметром 25 мм | D80: 100 шт. | E80: =Source!I280 -> 182.6416 | F80: =Source!U272
A81: 15.3 | B81: =Source!E282 -> 15,3 | C81: =Source!G282 -> Кабель cat.5е U/UTPнг(А)-LSLTx 4х0,52 арт.101162 | D81: км | E81: =Source!I282 -> 17.2176 | F81: =Source!U272
A82: 16 | B82: =Source!E292 -> 16 | C82: =Source!G292 -> Прокладка кабеля связи симметричного для цифровых систем передачи по лоткам перфорированным | D82: 100 м | E82: =Source!I292 -> 31.9 | F82: =Source!U272 | G82: ="=(500+"&"18600+"&"970-"&"8440*"&"2)/"&"100" -> =(500+18600+970-8440*2)/100
A83: 16.1 | B83: =Source!E294 -> 16,1 | C83: =Source!G294 -> Кабель волоконно-оптический 50/125 многомодовый 8-волоконный ОБР-Внг(А) HFLTx 8 G651.1(ОМЗ) арт.46863 | D83: км | E83: =Source!I294 -> 0.51 | F83: =Source!U272
A84: 16.2 | B84: =Source!E296 -> 16,2 | C84: =Source!G296 -> Кабель cat.5е U/UTPнг(А)-LSLTx 4х0,52 арт.101162 | D84: км | E84: =Source!I296 -> 1.7544 | F84: =Source!U272
A85: 16.3 | B85: =Source!E298 -> 16,3 | C85: =Source!G298 -> Кабель cat.6е F/UTPнг(А)-LSLTx 4х2х0,57 арт.100458 | D85: км | E85: =Source!I298 -> 0.9894 | F85: =Source!U272
A86: 16.4 | B86: =Source!E300 -> 16,4 | C86: =Source!G300 -> Механизм HDMI 2.0, разъём Type A | D86: шт. | E86: =Source!I300 -> 44 | F86: =Source!U272
A87: 16.5 | B87: =Source!E302 -> 16,5 | C87: =Source!G302 -> Коннектор (вилка) телекоммуникационный 8P8C, RJ45, категория 5E | D87: 100 шт. | E87: =Source!I302 -> 0.16 | F87: =Source!U272
A88: 16.6 | B88: =Source!E304 -> 16,6 | C88: =Source!G304 -> Разъём Type C для розетки USB | D88: шт. | E88: =Source!I304 -> 44 | F88: =Source!U272
A89: 17 | B89: =Source!E320 -> 17 | C89: =Source!G320 -> Прокладка металлического перфорированного лотка по установленным конструкциям, массой погонного метра до 2 кг | D89: 100 М ТРАССЫ | E89: =Source!I320 -> 6.39 | F89: =Source!U272 | G89: ="=(81+"&"124+"&"8)*"&"3/"&"100" -> =(81+124+8)*3/100
A90: 17.1 | B90: =Source!E322 -> 17,1 | C90: =Source!G322 -> Лоток кабельный проволочный стальной, оцинкованный, без крышки, диаметр проволоки 4,0 мм, размер 3000х400х50 мм | D90: шт. | E90: =Source!I322 -> 81 | F90: =Source!U272
A91: 17.2 | B91: =Source!E324 -> 17,2 | C91: =Source!G324 -> Лоток кабельный проволочный стальной, оцинкованный, без крышки, диаметр проволоки 4,0 мм, размер 3000х200х50 мм | D91: шт. | E91: =Source!I324 -> 124 | F91: =Source!U272
A92: 17.3 | B92: =Source!E326 -> 17,3 | C92: =Source!G326 -> Лоток кабельный проволочный стальной, оцинкованный, без крышки, диаметр проволоки 4,0 мм, размер 3000х150х50 мм | D92: шт. | E92: =Source!I326 -> 8 | F92: =Source!U272
A93: 17.4 | B93: =Source!E330 -> 17,5 | C93: =Source!G330 -> Винты с полукруглой головкой, оцинкованные, диаметр 5 мм, длина 50 мм | D93: т | E93: =Source!I330 -> 0.055785 | F93: =Source!U272
A94: 18 | B94: =Source!E332 -> 18 | C94: =Source!G332 -> Прокладка по установленным конструкциям, по стенам и колоннам с креплением скобами винипластовой трубы диаметром до 50 мм (2024-00272-01-0-ИОС5.5СО, лист 5, п.11 - гильзы) | D94: 100 м | E94: =Source!I332 -> 2.79 | F94: =Source!U272 | G94: ="=279/"&"100" -> =279/100
A95: 18.1 | B95: =Source!E334 -> 18,1 | C95: =Source!G334 -> Трубы из непластифицированного вторичного ПВХ, гладкие, самозатухающие, усиленного типа, наружный диаметр 32 мм, толщина стенки 1,8 мм, для электропроводок | D95: м | E95: =Source!I334 -> 284.58 | F95: =Source!U272
A96: 18.2 | B96: =Source!E336 -> 18,2 | C96: =Source!G336 -> Мастика тиоколовая, герметизирующая, нетвердеющая, типа АМ-05 | D96: кг | E96: =Source!I336 -> 5 | F96: =Source!U272
C99: Главный инженер проекта _________________ | D99: =IF(Source!X12<>"", Source!X12," ")
C101: Составил _________________ | D101: =IF(Source!AB12<>"", Source!AB12," ") -> Лукьянова А.Л.

Sheet Source
A1: 0 | B1: Smeta.RU (495) 974-1589 | D1: _PS_ | F1: 0 | G1: 0 | H1: 0 | I1: Smeta.RU | K1: 1 | L1: 74562 | M1: 10 | N1: 12 | O1: 1 | P1: 0 | Q1: 1
A4: 1 | B4: 1 | C4: -1 | G4: Клязьминская улица, д. 7, к. 4, Дмитровский район Северного административного округа города Москвы Капитальный ремонт здания Государственного бюджетного общеобразовательного учреждения города Москвы «Школа № 236». 1 этап | EC4: 0
A12: 1 | B12: 438 | C12: 0 | D12: =ROW(A399) -> 399 | E12: 0 | F12: 02-01-12 | G12: 02-01-12 СКС | I12: 0 | J12: 2024-00272-01-0-ИОС5.5 | K12: 0 | L12: 0 | M12: 4098 | O12: 0 | P12: 0 | Q12: 0 | R12: 0 | S12: 0 | T12: 1 | V12: 0 | AB12: Лукьянова А.Л. | BB12: 0 | BH12: Сметные нормы списания | BI12: Коды ОКП для ТСН-2001 МГЭ Дополнение 80 | BJ12: 1 | BK12: 1 | BL12: 0 | BM12: 0 | BN12: 1 | BO12: 0 | BP12: 6 | BQ12: 2 | BR12: 1 | BS12: 1 | BT12: 1 | BU12: 0 | BV12: 1 | BW12: 0 | BX12: 0 | BY12: ТСН-2001 (МГЭ) Доп 80 - Новое строительство | BZ12: Типовой расчет для ТСН-2001 МГЭ, Дополнение 80, строительство | CA12: Территориальные сметные нормативы для Москвы ТСН-2001 (МГЭ), дополнение 80 | CB12: Территориальные сметные нормативы для Москвы ТСН-2001 (МГЭ), дополнение 80 | CC12: Территориальные сметные нормативы для Москвы ТСН-2001 (МГЭ), дополнение 80 | CD12: Территориальные сметные нормативы для Москвы ТСН-2001 (МГЭ), дополнение 80 | CE12: Поправки для ТСН-2001 от 03.02.2026 г. доп.80 | CF12: 0 | CG12: 0 | CH12: 8202 | CK12: 81 | CQ12: Территориальные сметные нормативы для Москвы (ТСН-2001) | CR12: ТЕР | CS12: 41660 | CT12: 1 | CU12: 80 | CY12: 0 | EC12: 0
A15: 15 | B15: 1
A18: 52 | B18: =B399 -> 438 | C18: =C399 -> 1 | D18: =D399 -> 12 | E18: =E399 -> 0 | F18: =F399 -> 02-01-12 | G18: =G399 -> 02-01-12 СКС | O18: =O399 -> 968093.54 | P18: =P399 -> 929001.41 | Q18: =Q399 -> 3132.9 | R18: =R399 -> 324.23 | S18: =S399 -> 35959.23 | T18: =T399 -> 0 | U18: =U399 -> 3008.2474 | V18: =V399 -> 0 | ... GX18: =GX399 -> 0
A20: 3 | B20: 1 | D20: =ROW(A369) -> 369 | F20: 02-01-12 | G20: Структурированная кабельная сеть | I20: 0 | J20: 2024-00272-01-0-ИОС5.5 | K20: -1 | L20: 02-01-12 | S20: 0 | T20: 0 | V20: 0 | AB20: Лукьянова А.Л. | BX20: 0 | CF20: 0 | CG20: 0
A22: 52 | B22: =B369 -> 1 | C22: =C369 -> 3 | D22: =D369 -> 20 | E22: =E369 -> 0 | F22: =F369 -> 02-01-12 | G22: =G369 -> Структурированная кабельная сеть | O22: =O369 -> 968093.54 | P22: =P369 -> 929001.41 | Q22: =Q369 -> 3132.9 | R22: =R369 -> 324.23 | S22: =S369 -> 35959.23 | T22: =T369 -> 0 | U22: =U369 -> 3008.2474 | V22: =V369 -> 0 | ... GX22: =GX369 -> 0
A24: 4 | B24: 1 | D24: =ROW(A51) -> 51 | G24: Телекоммуникационный шкаф 47U 19" ШТ1-01 | I24: 0 | K24: -1 | S24: 0 | T24: 0 | V24: 0 | BX24: 0 | CJ24: 0
A26: 52 | B26: =B51 -> 1 | C26: =C51 -> 4 | D26: =D51 -> 24 | E26: =E51 -> 0 | F26: =F51 | G26: =G51 -> Телекоммуникационный шкаф 47U 19" ШТ1-01 | O26: =O51 -> 25651.89 | P26: =P51 -> 25442.61 | Q26: =Q51 -> 47.12 | R26: =R51 -> 5.16 | S26: =S51 -> 162.16 | T26: =T51 -> 0 | U26: =U51 -> 14.442318 | V26: =V51 -> 0 | ... GX26: =GX51 -> 0
A28: 17 | B28: 1 | D28: =ROW(EtalonRes!A6) -> 6 | E28: 1 | F28: 4.10-32-1 | G28: Монтаж стойки, полустойки, каркаса стойки или шкафа массой до 100 кг | H28: 1 ШТ. | I28: 1 | J28: 0 | K28: 1 | O28: =ROUND(CP28,2) -> 154.33 | P28: =ROUND((ROUND((AC28*AW28*I28),2)*BC28),2) -> 3.92 | Q28: =(ROUND((ROUND((((ET28*1.1))*AV28*I28),2)*BB28),2)+ROUND((ROUND(((AE28-((EU28*1.1)))*AV28*I28),2)*BS28),2)) -> 44.82 | R28: =ROUND((ROUND((AE28*AV28*I28),2)*BS28),2) -> 4.79 | S28: =ROUND((ROUND((AF28*AV28*I28),2)*BA28),2) -> 105.59 | T28: =ROUND(CU28*I28,2) -> 0 | U28: =CV28*I28 -> 9.44394 | V28: =CW28*I28 -> 0 | W28: =ROUND(CX28*I28,2) -> 0 | X28: =ROUND(CY28,2) -> 99.34 | Y28: =ROUND(CZ28,2) -> 50.77 | AA28: 56505403 | AB28: =ROUND((AC28+AD28+AF28),6) -> 147.58 | AC28: =ROUND((ES28),6) -> 3.92 | AD28: =ROUND(((((ET28*1.1))-((EU28*1.1)))+AE28),6) -> 42.812 | AE28: =ROUND(((EU28*1.1)),6) -> 4.576 | AF28: =ROUND(((EV28*1.1)),6) -> 100.848 | AG28: =ROUND((AP28),6) -> 0 | AH28: =((EW28*1.1)) -> 9.02 | AI28: =((EX28*1.1)) -> 0 | AJ28: =(AS28) -> 0 | AK28: 134.52 | AL28: 3.92 | AM28: 38.92 | AN28: 4.16 | AO28: 91.68 | AP28: 0 | AQ28: 8.2 | AR28: 0 | AS28: 0 | AT28: 90 | AU28: 46 | AV28: 1.047 | AW28: 1 | AZ28: 1 | BA28: 1 | BB28: 1 | BC28: 1 | BH28: 0 | BI28: 2 | BJ28: ТСН-2001.4 Доп. 80, Сб. 10, т. 32, поз. 1 | BM28: 68 | BN28: 0 | BO28: 4.10-32-1 | BP28: 1 | BQ28: 40 | BR28: 0 | BS28: 1 | BT28: 1 | BU28: 1 | BV28: 1 | BW28: 1 | BX28: 1 | BZ28: 90 | CA28: 46 | CE28: 30 | CF28: 0 | CG28: 0 | CM28: 0 | CO28: 0 | CP28: =(P28+Q28+S28) -> 154.33 | CQ28: =ROUND((ROUND((AC28*AW28*1),2)*BC28),2) -> 3.92 | CR28: =(ROUND((ROUND((((ET28*1.1))*AV28*1),2)*BB28),2)+ROUND((ROUND(((AE28-((EU28*1.1)))*AV28*1),2)*BS28),2)) -> 44.82 | CS28: =ROUND((ROUND((AE28*AV28*1),2)*BS28),2) -> 4.79 | CT28: =ROUND((ROUND((AF28*AV28*1),2)*BA28),2) -> 105.59 | CU28: =AG28 -> 0 | CV28: =(AH28*AV28) -> 9.44394 | CW28: =AI28 -> 0 | CX28: =AJ28 -> 0 | CY28: =(((S28+R28)*AT28)/100) -> 99.342 | CZ28: =(((S28+R28)*AU28)/100) -> 50.7748 | DE28: *1,1 | DF28: *1,1 | DG28: *1,1 | DI28: *1,1 | DJ28: *1,1 | DN28: 0 | DO28: 0 | DP28: 1 | DQ28: 1 | DU28: 1013 | DV28: 1 ШТ. | DW28: 1 ШТ. | DX28: 1 | EE28: 58162630 | EF28: 40 | EG28: Монтаж оборудования | EH28: 0 | EJ28: 2 | EK28: 68 | EL28: ТСН-2001.4-10. Прокладка и монтаж сетей связи | EM28: ТСН-2001.4-10-1 | EO28: Поправка: Гл.12.Прил.8.п.8. 5_12.00.01.11.003 | EQ28: 0 | ER28: 134.52 | ES28: 3.92 | ET28: 38.92 | EU28: 4.16 | EV28: 91.68 | EW28: 8.2 | EX28: 0 | EY28: 0 | FQ28: 0 | FR28: 0 | FS28: 0 | FX28: 90 | FY28: 46 | GD28: 1 | GF28: -1576476159 | GG28: 2 | GH28: 1 | GI28: 2 | GJ28: 0 | GK28: 0 | GL28: =ROUND(IF(AND(BH28=3,BI28=3,FS28<>0),P28,0),2) -> 0 | GM28: =ROUND(O28+X28+Y28,2)+GX28 -> 304.44 | GN28: =IF(OR(BI28=0,BI28=1),GM28-GX28,0) -> 0 | GO28: =IF(BI28=2,GM28-GX28,0) -> 304.44 | GP28: =IF(BI28=4,GM28-GX28,0) -> 0 | GR28: 0 | GS28: 3 | GT28: 0 | GV28: =ROUND((GT28),6) -> 0 | GW28: 1 | GX28: =ROUND(HC28*I28,2) -> 0 | HA28: 0 | HB28: 0 | HC28: =GV28*GW28 -> 0 | HS28: 0 | IK28: 0
A29: 17 | B29: 1 | D29: =ROW(EtalonRes!A12) -> 12 | E29: 1 | F29: 4.10-32-1 | G29: Монтаж стойки, полустойки, каркаса стойки или шкафа массой до 100 кг | H29: 1 ШТ. | I29: 1 | J29: 0 | K29: 1 | O29: =ROUND(CP29,2) -> 6524.23 | P29: =ROUND((ROUND((AC29*AW29*I29),2)*BC29),2) -> 32.54 | Q29: =(ROUND((ROUND((((ET29*1.1))*AV29*I29),2)*BB29),2)+ROUND((ROUND(((AE29-((EU29*1.1)))*AV29*I29),2)*BS29),2)) -> 685.3 | R29: =ROUND((ROUND((AE29*AV29*I29),2)*BS29),2) -> 263.4 | S29: =ROUND((ROUND((AF29*AV29*I29),2)*BA29),2) -> 5806.39 | T29: =ROUND(CU29*I29,2) -> 0 | U29: =CV29*I29 -> 9.44394 | V29: =CW29*I29 -> 0 | W29: =ROUND(CX29*I29,2) -> 0 | X29: =ROUND(CY29,2) -> 5462.81 | Y29: =ROUND(CZ29,2) -> 2792.1 | AA29: 56505405 | AB29: =ROUND((AC29+AD29+AF29),6) -> 147.58 | AC29: =ROUND((ES29),6) -> 3.92 | AD29: =ROUND(((((ET29*1.1))-((EU29*1.1)))+AE29),6) -> 42.812 | AE29: =ROUND(((EU29*1.1)),6) -> 4.576 | AF29: =ROUND(((EV29*1.1)),6) -> 100.848 | AG29: =ROUND((AP29),6) -> 0 | AH29: =((EW29*1.1)) -> 9.02 | AI29: =((EX29*1.1)) -> 0 | AJ29: =(AS29) -> 0 | AK29: 134.52 | AL29: 3.92 | AM29: 38.92 | AN29: 4.16 | AO29: 91.68 | AP29: 0 | AQ29: 8.2 | AR29: 0 | AS29: 0 | AT29: 90 | AU29: 46 | AV29: 1.047 | AW29: 1 | AZ29: 1 | BA29: 54.99 | BB29: 15.29 | BC29: 8.3 | BH29: 0 | BI29: 2 | BJ29: ТСН-2001.4 Доп. 80, Сб. 10, т. 32, поз. 1 | BM29: 68 | BN29: 0 | BO29: 4.10-32-1 | BP29: 1 | BQ29: 40 | BR29: 0 | BS29: 54.99 | BT29: 1 | BU29: 1 | BV29: 1 | BW29: 1 | BX29: 1 | BZ29: 90 | CA29: 46 | CE29: 30 | CF29: 0 | CG29: 0 | CM29: 0 | CO29: 0 | CP29: =(P29+Q29+S29) -> 6524.23 | CQ29: =ROUND((ROUND((AC29*AW29*1),2)*BC29),2) -> 32.54 | CR29: =(ROUND((ROUND((((ET29*1.1))*AV29*1),2)*BB29),2)+ROUND((ROUND(((AE29-((EU29*1.1)))*AV29*1),2)*BS29),2)) -> 685.3 | CS29: =ROUND((ROUND((AE29*AV29*1),2)*BS29),2) -> 263.4 | CT29: =ROUND((ROUND((AF29*AV29*1),2)*BA29),2) -> 5806.39 | CU29: =AG29 -> 0 | CV29: =(AH29*AV29) -> 9.44394 | CW29: =AI29 -> 0 | CX29: =AJ29 -> 0 | CY29: =(((S29+R29)*AT29)/100) -> 5462.811 | CZ29: =(((S29+R29)*AU29)/100) -> 2792.1034 | DE29: *1,1 | DF29: *1,1 | DG29: *1,1 | DI29: *1,1 | DJ29: *1,1 | DN29: 0 | DO29: 0 | DP29: 1 | DQ29: 1 | DU29: 1013 | DV29: 1 ШТ. | DW29: 1 ШТ. | DX29: 1 | EE29: 58162630 | EF29: 40 | EG29: Монтаж оборудования | EH29: 0 | EJ29: 2 | EK29: 68 | EL29: ТСН-2001.4-10. Прокладка и монтаж сетей связи | EM29: ТСН-2001.4-10-1 | EO29: Поправка: Гл.12.Прил.8.п.8. 5_12.00.01.11.003 | EQ29: 0 | ER29: 134.52 | ES29: 3.92 | ET29: 38.92 | EU29: 4.16 | EV29: 91.68 | EW29: 8.2 | EX29: 0 | EY29: 0 | FQ29: 0 | FR29: 0 | FS29: 0 | FX29: 90 | FY29: 46 | GD29: 1 | GF29: -1576476159 | GG29: 2 | GH29: 1 | GI29: 2 | GJ29: 0 | GK29: 0 | GL29: =ROUND(IF(AND(BH29=3,BI29=3,FS29<>0),P29,0),2) -> 0 | GM29: =ROUND(O29+X29+Y29,2)+GX29 -> 14779.14 | GN29: =IF(OR(BI29=0,BI29=1),GM29-GX29,0) -> 0 | GO29: =IF(BI29=2,GM29-GX29,0) -> 14779.14 | GP29: =IF(BI29=4,GM29-GX29,0) -> 0 | GR29: 0 | GS29: 3 | GT29: 0 | GV29: =ROUND((GT29),6) -> 0 | GW29: 1 | GX29: =ROUND(HC29*I29,2) -> 0 | HA29: 0 | HB29: 0 | HC29: =GV29*GW29 -> 0 | HS29: 0 | IK29: 0
A30: 18 | B30: 1 | E30: 1,1 | F30: КА 1 | G30: Шкаф 19" серии Racknet S3000, 47U 60F-47-7C-94BL | H30: шт. | I30: =I28*J30 -> 1 | J30: 1 | K30: 1 | O30: =ROUND(CP30,2) -> 16818.37 | P30: =ROUND((ROUND((AC30*AW30*I30),2)*BC30),2) -> 16818.37 | Q30: =(ROUND((ROUND(((ET30)*AV30*I30),2)*BB30),2)+ROUND((ROUND(((AE30-(EU30))*AV30*I30),2)*BS30),2)) -> 0 | R30: =ROUND((ROUND((AE30*AV30*I30),2)*BS30),2) -> 0 | S30: =ROUND((ROUND((AF30*AV30*I30),2)*BA30),2) -> 0 | T30: =ROUND(CU30*I30,2) -> 0 | U30: =CV30*I30 -> 0 | V30: =CW30*I30 -> 0 | W30: =ROUND(CX30*I30,2) -> 0 | X30: =ROUND(CY30,2) -> 0 | Y30: =ROUND(CZ30,2) -> 0 | AA30: 56505403 | AB30: =ROUND((AC30+AD30+AF30),6) -> 16818.37 | AC30: =ROUND((ES30),6) -> 16818.37 | AD30: =ROUND((((ET30)-(EU30))+AE30),6) -> 0 | AE30: =ROUND((EU30),6) -> 0 | AF30: =ROUND((EV30),6) -> 0 | AG30: =ROUND((AP30),6) -> 0 | AH30: =(EW30) -> 0 | AI30: =(EX30) -> 0 | AJ30: =(AS30) -> 0 | AK30: 16818.37 | AL30: 16818.37 | AM30: 0 | AN30: 0 | AO30: 0 | AP30: 0 | AQ30: 0 | AR30: 0 | AS30: 0 | AT30: 90 | AU30: 46 | AV30: 1 | AW30: 1 | AZ30: 1 | BA30: 1 | BB30: 1 | BC30: 1 | BH30: 3 | BI30: 2 | BM30: 68 | BN30: 0 | BP30: 0 | BQ30: 40 | BR30: 0 | BS30: 1 | BT30: 1 | BU30: 1 | BV30: 1 | BW30: 1 | BX30: 1 | BZ30: 90 | CA30: 46 | CE30: 30 | CF30: 0 | CG30: 0 | CM30: 0 | CO30: 0 | CP30: =(P30+Q30+S30) -> 16818.37 | CQ30: =ROUND((ROUND((AC30*AW30*1),2)*BC30),2) -> 16818.37 | CR30: =(ROUND((ROUND(((ET30)*AV30*1),2)*BB30),2)+ROUND((ROUND(((AE30-(EU30))*AV30*1),2)*BS30),2)) -> 0 | CS30: =ROUND((ROUND((AE30*AV30*1),2)*BS30),2) -> 0 | CT30: =ROUND((ROUND((AF30*AV30*1),2)*BA30),2) -> 0 | CU30: =AG30 -> 0 | CV30: =(AH30*AV30) -> 0 | CW30: =AI30 -> 0 | CX30: =AJ30 -> 0 | CY30: =(((S30+R30)*AT30)/100) -> 0 | CZ30: =(((S30+R30)*AU30)/100) -> 0 | DN30: 0 | DO30: 0 | DP30: 1 | DQ30: 1 | DU30: 1010 | DV30: шт. | DW30: шт. | DX30: 1 | EE30: 58162630 | EF30: 40 | EG30: Монтаж оборудования | EH30: 0 | EJ30: 2 | EK30: 68 | EL30: ТСН-2001.4-10. Прокладка и монтаж сетей связи | EM30: ТСН-2001.4-10-1 | EQ30: 0 | ER30: 0 | ES30: 16818.37 | ET30: 0 | EU30: 0 | EV30: 0 | EW30: 0 | EX30: 0 | FQ30: 0 | FR30: 0 | FS30: 0 | FX30: 90 | FY30: 46 | GA30: [195 488,81 / 1,2 / 9,88] + 2% Заг.скл | GD30: 1 | GF30: -199742500 | GG30: 2 | GH30: 4 | GI30: -2 | GJ30: 0 | GK30: 0 | GL30: =ROUND(IF(AND(BH30=3,BI30=3,FS30<>0),P30,0),2) -> 0 | GM30: =ROUND(O30+X30+Y30,2)+GX30 -> 16818.37 | GN30: =IF(OR(BI30=0,BI30=1),GM30-GX30,0) -> 0 | GO30: =IF(BI30=2,GM30-GX30,0) -> 16818.37 | GP30: =IF(BI30=4,GM30-GX30,0) -> 0 | GR30: 0 | GS30: 2 | GT30: 0 | GV30: =ROUND((GT30),6) -> 0 | GW30: 1 | GX30: =ROUND(HC30*I30,2) -> 0 | HA30: 0 | HB30: 0 | HC30: =GV30*GW30 -> 0 | HE30: 0 | HF30: 2 | HS30: 0 | IK30: 0
A31: 18 | B31: 1 | E31: 1,1 | F31: КА 1 | G31: Шкаф 19" серии Racknet S3000, 47U 60F-47-7C-94BL | H31: шт. | I31: =I29*J31 -> 1 | J31: 1 | K31: 1 | O31: =ROUND(CP31,2) -> 166165.5 | P31: =ROUND((ROUND((AC31*AW31*I31),2)*BC31),2) -> 166165.5 | Q31: =(ROUND((ROUND(((ET31)*AV31*I31),2)*BB31),2)+ROUND((ROUND(((AE31-(EU31))*AV31*I31),2)*BS31),2)) -> 0 | R31: =ROUND((ROUND((AE31*AV31*I31),2)*BS31),2) -> 0 | S31: =ROUND((ROUND((AF31*AV31*I31),2)*BA31),2) -> 0 | T31: =ROUND(CU31*I31,2) -> 0 | U31: =CV31*I31 -> 0 | V31: =CW31*I31 -> 0 | W31: =ROUND(CX31*I31,2) -> 0 | X31: =ROUND(CY31,2) -> 0 | Y31: =ROUND(CZ31,2) -> 0 | AA31: 56505405 | AB31: =ROUND((AC31+AD31+AF31),6) -> 16818.37 | AC31: =ROUND((ES31),6) -> 16818.37 | AD31: =ROUND((((ET31)-(EU31))+AE31),6) -> 0 | AE31: =ROUND((EU31),6) -> 0 | AF31: =ROUND((EV31),6) -> 0 | AG31: =ROUND((AP31),6) -> 0 | AH31: =(EW31) -> 0 | AI31: =(EX31) -> 0 | AJ31: =(AS31) -> 0 | AK31: 16818.37 | AL31: 16818.37 | AM31: 0 | AN31: 0 | AO31: 0 | AP31: 0 | AQ31: 0 | AR31: 0 | AS31: 0 | AT31: 90 | AU31: 46 | AV31: 1 | AW31: 1 | AZ31: 1 | BA31: 1 | BB31: 1 | BC31: 9.88 | BH31: 3 | BI31: 2 | BM31: 68 | BN31: 0 | BP31: 0 | BQ31: 40 | BR31: 0 | BS31: 1 | BT31: 1 | BU31: 1 | BV31: 1 | BW31: 1 | BX31: 1 | BZ31: 90 | CA31: 46 | CE31: 30 | CF31: 0 | CG31: 0 | CM31: 0 | CO31: 0 | CP31: =(P31+Q31+S31) -> 166165.5 | CQ31: =ROUND((ROUND((AC31*AW31*1),2)*BC31),2) -> 166165.5 | CR31: =(ROUND((ROUND(((ET31)*AV31*1),2)*BB31),2)+ROUND((ROUND(((AE31-(EU31))*AV31*1),2)*BS31),2)) -> 0 | CS31: =ROUND((ROUND((AE31*AV31*1),2)*BS31),2) -> 0 | CT31: =ROUND((ROUND((AF31*AV31*1),2)*BA31),2) -> 0 | CU31: =AG31 -> 0 | CV31: =(AH31*AV31) -> 0 | CW31: =AI31 -> 0 | CX31: =AJ31 -> 0 | CY31: =(((S31+R31)*AT31)/100) -> 0 | CZ31: =(((S31+R31)*AU31)/100) -> 0 | DN31: 0 | DO31: 0 | DP31: 1 | DQ31: 1 | DU31: 1010 | DV31: шт. | DW31: шт. | DX31: 1 | EE31: 58162630 | EF31: 40 | EG31: Монтаж оборудования | EH31: 0 | EJ31: 2 | EK31: 68 | EL31: ТСН-2001.4-10. Прокладка и монтаж сетей связи | EM31: ТСН-2001.4-10-1 | EQ31: 0 | ER31: 16818.37 | ES31: 16818.37 | ET31: 0 | EU31: 0 | EV31: 0 | EW31: 0 | EX31: 0 | EZ31: 5 | FC31: 1 | FD31: 18 | FF31: 195488.81 | FQ31: 0 | FR31: 0 | FS31: 0 | FX31: 90 | FY31: 46 | GA31: [195 488,81 / 1,2 / 9,88] + 2% Заг.скл | GD31: 1 | GF31: -199742500 | GG31: 2 | GH31: 3 | GI31: 5 | GJ31: 0 | GK31: 0 | GL31: =ROUND(IF(AND(BH31=3,BI31=3,FS31<>0),P31,0),2) -> 0 | GM31: =ROUND(O31+X31+Y31,2)+GX31 -> 166165.5 | GN31: =IF(OR(BI31=0,BI31=1),GM31-GX31,0) -> 0 | GO31: =IF(BI31=2,GM31-GX31,0) -> 166165.5 | GP31: =IF(BI31=4,GM31-GX31,0) -> 0 | GR31: 1 | GS31: 1 | GT31: 0 | GV31: =ROUND((GT31),6) -> 0 | GW31: 1 | GX31: =ROUND(HC31*I31,2) -> 0 | HA31: 0 | HB31: 0 | HC31: =GV31*GW31 -> 0 | HE31: 0 | HF31: 2 | HS31: 0 | IK31: 0
A32: 18 | B32: 1 | E32: 1,2 | F32: КА 2 | G32: Вертикальный органайзер 60А-18-47-01-31BL | H32: шт. | I32: =I28*J32 -> 1 | J32: 1 | K32: 1 | O32: =ROUND(CP32,2) -> 3548.41 | P32: =ROUND((ROUND((AC32*AW32*I32),2)*BC32),2) -> 3548.41 | Q32: =(ROUND((ROUND(((ET32)*AV32*I32),2)*BB32),2)+ROUND((ROUND(((AE32-(EU32))*AV32*I32),2)*BS32),2)) -> 0 | R32: =ROUND((ROUND((AE32*AV32*I32),2)*BS32),2) -> 0 | S32: =ROUND((ROUND((AF32*AV32*I32),2)*BA32),2) -> 0 | T32: =ROUND(CU32*I32,2) -> 0 | U32: =CV32*I32 -> 0 | V32: =CW32*I32 -> 0 | W32: =ROUND(CX32*I32,2) -> 0 | X32: =ROUND(CY32,2) -> 0 | Y32: =ROUND(CZ32,2) -> 0 | AA32: 56505403 | AB32: =ROUND((AC32+AD32+AF32),6) -> 3548.41 | AC32: =ROUND((ES32),6) -> 3548.41 | AD32: =ROUND((((ET32)-(EU32))+AE32),6) -> 0 | AE32: =ROUND((EU32),6) -> 0 | AF32: =ROUND((EV32),6) -> 0 | AG32: =ROUND((AP32),6) -> 0 | AH32: =(EW32) -> 0 | AI32: =(EX32) -> 0 | AJ32: =(AS32) -> 0 | AK32: 3548.41 | AL32: 3548.41 | AM32: 0 | AN32: 0 | AO32: 0 | AP32: 0 | AQ32: 0 | AR32: 0 | AS32: 0 | AT32: 90 | AU32: 46 | AV32: 1 | AW32: 1 | AZ32: 1 | BA32: 1 | BB32: 1 | BC32: 1 | BH32: 3 | BI32: 2 | BM32: 68 | BN32: 0 | BP32: 0 | BQ32: 40 | BR32: 0 | BS32: 1 | BT32: 1 | BU32: 1 | BV32: 1 | BW32: 1 | BX32: 1 | BZ32: 90 | CA32: 46 | CE32: 30 | CF32: 0 | CG32: 0 | CM32: 0 | CO32: 0 | CP32: =(P32+Q32+S32) -> 3548.41 | CQ32: =ROUND((ROUND((AC32*AW32*1),2)*BC32),2) -> 3548.41 | CR32: =(ROUND((ROUND(((ET32)*AV32*1),2)*BB32),2)+ROUND((ROUND(((AE32-(EU32))*AV32*1),2)*BS32),2)) -> 0 | CS32: =ROUND((ROUND((AE32*AV32*1),2)*BS32),2) -> 0 | CT32: =ROUND((ROUND((AF32*AV32*1),2)*BA32),2) -> 0 | CU32: =AG32 -> 0 | CV32: =(AH32*AV32) -> 0 | CW32: =AI32 -> 0 | CX32: =AJ32 -> 0 | CY32: =(((S32+R32)*AT32)/100) -> 0 | CZ32: =(((S32+R32)*AU32)/100) -> 0 | DN32: 0 | DO32: 0 | DP32: 1 | DQ32: 1 | DU32: 1010 | DV32: шт. | DW32: шт. | DX32: 1 | EE32: 58162630 | EF32: 40 | EG32: Монтаж оборудования | EH32: 0 | EJ32: 2 | EK32: 68 | EL32: ТСН-2001.4-10. Прокладка и монтаж сетей связи | EM32: ТСН-2001.4-10-1 | EQ32: 0 | ER32: 0 | ES32: 3548.41 | ET32: 0 | EU32: 0 | EV32: 0 | EW32: 0 | EX32: 0 | FQ32: 0 | FR32: 0 | FS32: 0 | FX32: 90 | FY32: 46 | GA32: [41 245 / 1,2 / 9,88] + 2% Заг.скл | GD32: 1 | GF32: 1007668642 | GG32: 2 | GH32: 4 | GI32: -2 | GJ32: 0 | GK32: 0 | GL32: =ROUND(IF(AND(BH32=3,BI32=3,FS32<>0),P32,0),2) -> 0 | GM32: =ROUND(O32+X32+Y32,2)+GX32 -> 3548.41 | GN32: =IF(OR(BI32=0,BI32=1),GM32-GX32,0) -> 0 | GO32: =IF(BI32=2,GM32-GX32,0) -> 3548.41 | GP32: =IF(BI32=4,GM32-GX32,0) -> 0 | GR32: 0 | GS32: 2 | GT32: 0 | GV32: =ROUND((GT32),6) -> 0 | GW32: 1 | GX32: =ROUND(HC32*I32,2) -> 0 | HA32: 0 | HB32: 0 | HC32: =GV32*GW32 -> 0 | HE32: 0 | HF32: 2 | HS32: 0 | IK32: 0
A33: 18 | B33: 1 | E33: 1,2 | F33: КА 2 | G33: Вертикальный органайзер 60А-18-47-01-31BL | H33: шт. | I33: =I29*J33 -> 1 | J33: 1 | K33: 1 | O33: =ROUND(CP33,2) -> 35058.29 | P33: =ROUND((ROUND((AC33*AW33*I33),2)*BC33),2) -> 35058.29 | Q33: =(ROUND((ROUND(((ET33)*AV33*I33),2)*BB33),2)+ROUND((ROUND(((AE33-(EU33))*AV33*I33),2)*BS33),2)) -> 0 | R33: =ROUND((ROUND((AE33*AV33*I33),2)*BS33),2) -> 0 | S33: =ROUND((ROUND((AF33*AV33*I33),2)*BA33),2) -> 0 | T33: =ROUND(CU33*I33,2) -> 0 | U33: =CV33*I33 -> 0 | V33: =CW33*I33 -> 0 | W33: =ROUND(CX33*I33,2) -> 0 | X33: =ROUND(CY33,2) -> 0 | Y33: =ROUND(CZ33,2) -> 0 | AA33: 56505405 | AB33: =ROUND((AC33+AD33+AF33),6) -> 3548.41 | AC33: =ROUND((ES33),6) -> 3548.41 | AD33: =ROUND((((ET33)-(EU33))+AE33),6) -> 0 | AE33: =ROUND((EU33),6) -> 0 | AF33: =ROUND((EV33),6) -> 0 | AG33: =ROUND((AP33),6) -> 0 | AH33: =(EW33) -> 0 | AI33: =(EX33) -> 0 | AJ33: =(AS33) -> 0 | AK33: 3548.41 | AL33: 3548.41 | AM33: 0 | AN33: 0 | AO33: 0 | AP33: 0 | AQ33: 0 | AR33: 0 | AS33: 0 | AT33: 90 | AU33: 46 | AV33: 1 | AW33: 1 | AZ33: 1 | BA33: 1 | BB33: 1 | BC33: 9.88 | BH33: 3 | BI33: 2 | BM33: 68 | BN33: 0 | BP33: 0 | BQ33: 40 | BR33: 0 | BS33: 1 | BT33: 1 | BU33: 1 | BV33: 1 | BW33: 1 | BX33: 1 | BZ33: 90 | CA33: 46 | CE33: 30 | CF33: 0 | CG33: 0 | CM33: 0 | CO33: 0 | CP33: =(P33+Q33+S33) -> 35058.29 | CQ33: =ROUND((ROUND((AC33*AW33*1),2)*BC33),2) -> 35058.29 | CR33: =(ROUND((ROUND(((ET33)*AV33*1),2)*BB33),2)+ROUND((ROUND(((AE33-(EU33))*AV33*1),2)*BS33),2)) -> 0 | CS33: =ROUND((ROUND((AE33*AV33*1),2)*BS33),2) -> 0 | CT33: =ROUND((ROUND((AF33*AV33*1),2)*BA33),2) -> 0 | CU33: =AG33 -> 0 | CV33: =(AH33*AV33) -> 0 | CW33: =AI33 -> 0 | CX33: =AJ33 -> 0 | CY33: =(((S33+R33)*AT33)/100) -> 0 | CZ33: =(((S33+R33)*AU33)/100) -> 0 | DN33: 0 | DO33: 0 | DP33: 1 | DQ33: 1 | DU33: 1010 | DV33: шт. | DW33: шт. | DX33: 1 | EE33: 58162630 | EF33: 40 | EG33: Монтаж оборудования | EH33: 0 | EJ33: 2 | EK33: 68 | EL33: ТСН-2001.4-10. Прокладка и монтаж сетей связи | EM33: ТСН-2001.4-10-1 | EQ33: 0 | ER33: 3548.41 | ES33: 3548.41 | ET33: 0 | EU33: 0 | EV33: 0 | EW33: 0 | EX33: 0 | EZ33: 5 | FC33: 1 | FD33: 18 | FF33: 41245 | FQ33: 0 | FR33: 0 | FS33: 0 | FX33: 90 | FY33: 46 | GA33: [41 245 / 1,2 / 9,88] + 2% Заг.скл | GD33: 1 | GF33: 1007668642 | GG33: 2 | GH33: 3 | GI33: 5 | GJ33: 0 | GK33: 0 | GL33: =ROUND(IF(AND(BH33=3,BI33=3,FS33<>0),P33,0),2) -> 0 | GM33: =ROUND(O33+X33+Y33,2)+GX33 -> 35058.29 | GN33: =IF(OR(BI33=0,BI33=1),GM33-GX33,0) -> 0 | GO33: =IF(BI33=2,GM33-GX33,0) -> 35058.29 | GP33: =IF(BI33=4,GM33-GX33,0) -> 0 | GR33: 1 | GS33: 1 | GT33: 0 | GV33: =ROUND((GT33),6) -> 0 | GW33: 1 | GX33: =ROUND(HC33*I33,2) -> 0 | HA33: 0 | HB33: 0 | HC33: =GV33*GW33 -> 0 | HE33: 0 | HF33: 2 | HS33: 0 | IK33: 0
A34: 18 | B34: 1 | E34: 1,3 | F34: КА 7 | G34: Набор для креnленuя лоmков к крышке шкафов, высоmа 50мм 60А-31-08-ЗЗВL | H34: шт. | I34: =I28*J34 -> 1 | J34: 1 | K34: 1 | O34: =ROUND(CP34,2) -> 147.62 | P34: =ROUND((ROUND((AC34*AW34*I34),2)*BC34),2) -> 147.62 | Q34: =(ROUND((ROUND(((ET34)*AV34*I34),2)*BB34),2)+ROUND((ROUND(((AE34-(EU34))*AV34*I34),2)*BS34),2)) -> 0 | R34: =ROUND((ROUND((AE34*AV34*I34),2)*BS34),2) -> 0 | S34: =ROUND((ROUND((AF34*AV34*I34),2)*BA34),2) -> 0 | T34: =ROUND(CU34*I34,2) -> 0 | U34: =CV34*I34 -> 0 | V34: =CW34*I34 -> 0 | W34: =ROUND(CX34*I34,2) -> 0 | X34: =ROUND(CY34,2) -> 0 | Y34: =ROUND(CZ34,2) -> 0 | AA34: 56505403 | AB34: =ROUND((AC34+AD34+AF34),6) -> 147.62 | AC34: =ROUND((ES34),6) -> 147.62 | AD34: =ROUND((((ET34)-(EU34))+AE34),6) -> 0 | AE34: =ROUND((EU34),6) -> 0 | AF34: =ROUND((EV34),6) -> 0 | AG34: =ROUND((AP34),6) -> 0 | AH34: =(EW34) -> 0 | AI34: =(EX34) -> 0 | AJ34: =(AS34) -> 0 | AK34: 147.62 | AL34: 147.62 | AM34: 0 | AN34: 0 | AO34: 0 | AP34: 0 | AQ34: 0 | AR34: 0 | AS34: 0 | AT34: 90 | AU34: 46 | AV34: 1 | AW34: 1 | AZ34: 1 | BA34: 1 | BB34: 1 | BC34: 1 | BH34: 3 | BI34: 2 | BM34: 68 | BN34: 0 | BP34: 0 | BQ34: 40 | BR34: 0 | BS34: 1 | BT34: 1 | BU34: 1 | BV34: 1 | BW34: 1 | BX34: 1 | BZ34: 90 | CA34: 46 | CE34: 30 | CF34: 0 | CG34: 0 | CM34: 0 | CO34: 0 | CP34: =(P34+Q34+S34) -> 147.62 | CQ34: =ROUND((ROUND((AC34*AW34*1),2)*BC34),2) -> 147.62 | CR34: =(ROUND((ROUND(((ET34)*AV34*1),2)*BB34),2)+ROUND((ROUND(((AE34-(EU34))*AV34*1),2)*BS34),2)) -> 0 | CS34: =ROUND((ROUND((AE34*AV34*1),2)*BS34),2) -> 0 | CT34: =ROUND((ROUND((AF34*AV34*1),2)*BA34),2) -> 0 | CU34: =AG34 -> 0 | CV34: =(AH34*AV34) -> 0 | CW34: =AI34 -> 0 | CX34: =AJ34 -> 0 | CY34: =(((S34+R34)*AT34)/100) -> 0 | CZ34: =(((S34+R34)*AU34)/100) -> 0 | DN34: 0 | DO34: 0 | DP34: 1 | DQ34: 1 | DU34: 1010 | DV34: шт. | DW34: шт. | DX34: 1 | EE34: 58162630 | EF34: 40 | EG34: Монтаж оборудования | EH34: 0 | EJ34: 2 | EK34: 68 | EL34: ТСН-2001.4-10. Прокладка и монтаж сетей связи | EM34: ТСН-2001.4-10-1 | EQ34: 0 | ER34: 0 | ES34: 147.62 | ET34: 0 | EU34: 0 | EV34: 0 | EW34: 0 | EX34: 0 | FQ34: 0 | FR34: 0 | FS34: 0 | FX34: 90 | FY34: 46 | GA34: [1 715,95 / 1,2 / 9,88] + 2% Заг.скл | GD34: 1 | GF34: -957674279 | GG34: 2 | GH34: 4 | GI34: -2 | GJ34: 0 | GK34: 0 | GL34: =ROUND(IF(AND(BH34=3,BI34=3,FS34<>0),P34,0),2) -> 0 | GM34: =ROUND(O34+X34+Y34,2)+GX34 -> 147.62 | GN34: =IF(OR(BI34=0,BI34=1),GM34-GX34,0) -> 0 | GO34: =IF(BI34=2,GM34-GX34,0) -> 147.62 | GP34: =IF(BI34=4,GM34-GX34,0) -> 0 | GR34: 0 | GS34: 2 | GT34: 0 | GV34: =ROUND((GT34),6) -> 0 | GW34: 1 | GX34: =ROUND(HC34*I34,2) -> 0 | HA34: 0 | HB34: 0 | HC34: =GV34*GW34 -> 0 | HE34: 0 | HF34: 2 | HS34: 0 | IK34: 0
A35: 18 | B35: 1 | E35: 1,3 | F35: КА 7 | G35: Набор для креnленuя лоmков к крышке шкафов, высоmа 50мм 60А-31-08-ЗЗВL | H35: шт. | I35: =I29*J35 -> 1 | J35: 1 | K35: 1 | O35: =ROUND(CP35,2) -> 1458.49 | P35: =ROUND((ROUND((AC35*AW35*I35),2)*BC35),2) -> 1458.49 | Q35: =(ROUND((ROUND(((ET35)*AV35*I35),2)*BB35),2)+ROUND((ROUND(((AE35-(EU35))*AV35*I35),2)*BS35),2)) -> 0 | R35: =ROUND((ROUND((AE35*AV35*I35),2)*BS35),2) -> 0 | S35: =ROUND((ROUND((AF35*AV35*I35),2)*BA35),2) -> 0 | T35: =ROUND(CU35*I35,2) -> 0 | U35: =CV35*I35 -> 0 | V35: =CW35*I35 -> 0 | W35: =ROUND(CX35*I35,2) -> 0 | X35: =ROUND(CY35,2) -> 0 | Y35: =ROUND(CZ35,2) -> 0 | AA35: 56505405 | AB35: =ROUND((AC35+AD35+AF35),6) -> 147.62 | AC35: =ROUND((ES35),6) -> 147.62 | AD35: =ROUND((((ET35)-(EU35))+AE35),6) -> 0 | AE35: =ROUND((EU35),6) -> 0 | AF35: =ROUND((EV35),6) -> 0 | AG35: =ROUND((AP35),6) -> 0 | AH35: =(EW35) -> 0 | AI35: =(EX35) -> 0 | AJ35: =(AS35) -> 0 | AK35: 147.62 | AL35: 147.62 | AM35: 0 | AN35: 0 | AO35: 0 | AP35: 0 | AQ35: 0 | AR35: 0 | AS35: 0 | AT35: 90 | AU35: 46 | AV35: 1 | AW35: 1 | AZ35: 1 | BA35: 1 | BB35: 1 | BC35: 9.88 | BH35: 3 | BI35: 2 | BM35: 68 | BN35: 0 | BP35: 0 | BQ35: 40 | BR35: 0 | BS35: 1 | BT35: 1 | BU35: 1 | BV35: 1 | BW35: 1 | BX35: 1 | BZ35: 90 | CA35: 46 | CE35: 30 | CF35: 0 | CG35: 0 | CM35: 0 | CO35: 0 | CP35: =(P35+Q35+S35) -> 1458.49 | CQ35: =ROUND((ROUND((AC35*AW35*1),2)*BC35),2) -> 1458.49 | CR35: =(ROUND((ROUND(((ET35)*AV35*1),2)*BB35),2)+ROUND((ROUND(((AE35-(EU35))*AV35*1),2)*BS35),2)) -> 0 | CS35: =ROUND((ROUND((AE35*AV35*1),2)*BS35),2) -> 0 | CT35: =ROUND((ROUND((AF35*AV35*1),2)*BA35),2) -> 0 | CU35: =AG35 -> 0 | CV35: =(AH35*AV35) -> 0 | CW35: =AI35 -> 0 | CX35: =AJ35 -> 0 | CY35: =(((S35+R35)*AT35)/100) -> 0 | CZ35: =(((S35+R35)*AU35)/100) -> 0 | DN35: 0 | DO35: 0 | DP35: 1 | DQ35: 1 | DU35: 1010 | DV35: шт. | DW35: шт. | DX35: 1 | EE35: 58162630 | EF35: 40 | EG35: Монтаж оборудования | EH35: 0 | EJ35: 2 | EK35: 68 | EL35: ТСН-2001.4-10. Прокладка и монтаж сетей связи | EM35: ТСН-2001.4-10-1 | EQ35: 0 | ER35: 147.62 | ES35: 147.62 | ET35: 0 | EU35: 0 | EV35: 0 | EW35: 0 | EX35: 0 | EZ35: 5 | FC35: 1 | FD35: 18 | FF35: 1715.95 | FQ35: 0 | FR35: 0 | FS35: 0 | FX35: 90 | FY35: 46 | GA35: [1 715,95 / 1,2 / 9,88] + 2% Заг.скл | GD35: 1 | GF35: -957674279 | GG35: 2 | GH35: 3 | GI35: 5 | GJ35: 0 | GK35: 0 | GL35: =ROUND(IF(AND(BH35=3,BI35=3,FS35<>0),P35,0),2) -> 0 | GM35: =ROUND(O35+X35+Y35,2)+GX35 -> 1458.49 | GN35: =IF(OR(BI35=0,BI35=1),GM35-GX35,0) -> 0 | GO35: =IF(BI35=2,GM35-GX35,0) -> 1458.49 | GP35: =IF(BI35=4,GM35-GX35,0) -> 0 | GR35: 1 | GS35: 1 | GT35: 0 | GV35: =ROUND((GT35),6) -> 0 | GW35: 1 | GX35: =ROUND(HC35*I35,2) -> 0 | HA35: 0 | HB35: 0 | HC35: =GV35*GW35 -> 0 | HE35: 0 | HF35: 2 | HS35: 0 | IK35: 0
A36: 17 | B36: 1 | D36: =ROW(EtalonRes!A15) -> 15 | E36: 2 | F36: 4.11-12-1 | G36: Установка съемных и выдвижных блоков (модулей, ячеек, ТЭЗ) массой до 5 кг | H36: 1 ШТ. | I36: =ROUND(1+1+1+1,9) -> 4 | J36: 0 | K36: =ROUND(1+1+1+1,9) -> 4 | O36: =ROUND(CP36,2) -> 55.97 | P36: =ROUND((ROUND((AC36*AW36*I36),2)*BC36),2) -> 0 | Q36: =(ROUND((ROUND((((ET36*1.1))*AV36*I36),2)*BB36),2)+ROUND((ROUND(((AE36-((EU36*1.1)))*AV36*I36),2)*BS36),2)) -> 2.3 | R36: =ROUND((ROUND((AE36*AV36*I36),2)*BS36),2) -> 0.37 | S36: =ROUND((ROUND((AF36*AV36*I36),2)*BA36),2) -> 53.67 | T36: =ROUND(CU36*I36,2) -> 0 | U36: =CV36*I36 -> 4.745004 | V36: =CW36*I36 -> 0 | W36: =ROUND(CX36*I36,2) -> 0 | X36: =ROUND(CY36,2) -> 48.64 | Y36: =ROUND(CZ36,2) -> 24.86 | AA36: 56505403 | AB36: =ROUND((AC36+AD36+AF36),6) -> 13.365 | AC36: =ROUND((ES36),6) -> 0 | AD36: =ROUND(((((ET36*1.1))-((EU36*1.1)))+AE36),6) -> 0.55 | AE36: =ROUND(((EU36*1.1)),6) -> 0.088 | AF36: =ROUND(((EV36*1.1)),6) -> 12.815 | AG36: =ROUND((AP36),6) -> 0 | AH36: =((EW36*1.1)) -> 1.133 | AI36: =((EX36*1.1)) -> 0 | AJ36: =(AS36) -> 0 | AK36: 12.15 | AL36: 0 | AM36: 0.5 | AN36: 0.08 | AO36: 11.65 | AP36: 0 | AQ36: 1.03 | AR36: 0 | AS36: 0 | AT36: 90 | AU36: 46 | AV36: 1.047 | AW36: 1 | AZ36: 1 | BA36: 1 | BB36: 1 | BC36: 1 | BH36: 0 | BI36: 2 | BJ36: ТСН-2001.4 Доп. 68, Сб. 11, т. 12, поз. 1 | BM36: 72 | BN36: 0 | BO36: 4.11-12-1 | BP36: 1 | BQ36: 40 | BR36: 0 | BS36: 1 | BT36: 1 | BU36: 1 | BV36: 1 | BW36: 1 | BX36: 1 | BZ36: 90 | CA36: 46 | CE36: 30 | CF36: 0 | CG36: 0 | CM36: 0 | CO36: 0 | CP36: =(P36+Q36+S36) -> 55.97 | CQ36: =ROUND((ROUND((AC36*AW36*1),2)*BC36),2) -> 0 | CR36: =(ROUND((ROUND((((ET36*1.1))*AV36*1),2)*BB36),2)+ROUND((ROUND(((AE36-((EU36*1.1)))*AV36*1),2)*BS36),2)) -> 0.58 | CS36: =ROUND((ROUND((AE36*AV36*1),2)*BS36),2) -> 0.09 | CT36: =ROUND((ROUND((AF36*AV36*1),2)*BA36),2) -> 13.42 | CU36: =AG36 -> 0 | CV36: =(AH36*AV36) -> 1.186251 | CW36: =AI36 -> 0 | CX36: =AJ36 -> 0 | CY36: =(((S36+R36)*AT36)/100) -> 48.636 | CZ36: =(((S36+R36)*AU36)/100) -> 24.8584 | DE36: *1,1 | DF36: *1,1 | DG36: *1,1 | DI36: *1,1 | DJ36: *1,1 | DN36: 0 | DO36: 0 | DP36: 1 | DQ36: 1 | DU36: 1013 | DV36: 1 ШТ. | DW36: 1 ШТ. | DX36: 1 | EE36: 58162634 | EF36: 40 | EG36: Монтаж оборудования | EH36: 0 | EJ36: 2 | EK36: 72 | EL36: ТСН-2001.4-11. Приборы и средства автоматизации и вычислительной техники | EM36: ТСН-2001.4-11-1 | EO36: Поправка: Гл.12.Прил.8.п.8. 5_12.00.01.11.003 | EQ36: 0 | ER36: 12.15 | ES36: 0 | ET36: 0.5 | EU36: 0.08 | EV36: 11.65 | EW36: 1.03 | EX36: 0 | EY36: 0 | FQ36: 0 | FR36: 0 | FS36: 0 | FX36: 90 | FY36: 46 | GD36: 1 | GF36: 1708693888 | GG36: 2 | GH36: 1 | GI36: 2 | GJ36: 0 | GK36: 0 | GL36: =ROUND(IF(AND(BH36=3,BI36=3,FS36<>0),P36,0),2) -> 0 | GM36: =ROUND(O36+X36+Y36,2)+GX36 -> 129.47 | GN36: =IF(OR(BI36=0,BI36=1),GM36-GX36,0) -> 0 | GO36: =IF(BI36=2,GM36-GX36,0) -> 129.47 | GP36: =IF(BI36=4,GM36-GX36,0) -> 0 | GR36: 0 | GS36: 3 | GT36: 0 | GV36: =ROUND((GT36),6) -> 0 | GW36: 1 | GX36: =ROUND(HC36*I36,2) -> 0 | HA36: 0 | HB36: 0 | HC36: =GV36*GW36 -> 0 | HS36: 0 | IK36: 0
A37: 17 | B37: 1 | D37: =ROW(EtalonRes!A18) -> 18 | E37: 2 | F37: 4.11-12-1 | G37: Установка съемных и выдвижных блоков (модулей, ячеек, ТЭЗ) массой до 5 кг | H37: 1 ШТ. | I37: =ROUND(1+1+1+1,9) -> 4 | J37: 0 | K37: =ROUND(1+1+1+1,9) -> 4 | O37: =ROUND(CP37,2) -> 2988.71 | P37: =ROUND((ROUND((AC37*AW37*I37),2)*BC37),2) -> 0 | Q37: =(ROUND((ROUND((((ET37*1.1))*AV37*I37),2)*BB37),2)+ROUND((ROUND(((AE37-((EU37*1.1)))*AV37*I37),2)*BS37),2)) -> 37.4 | R37: =ROUND((ROUND((AE37*AV37*I37),2)*BS37),2) -> 20.35 | S37: =ROUND((ROUND((AF37*AV37*I37),2)*BA37),2) -> 2951.31 | T37: =ROUND(CU37*I37,2) -> 0 | U37: =CV37*I37 -> 4.745004 | V37: =CW37*I37 -> 0 | W37: =ROUND(CX37*I37,2) -> 0 | X37: =ROUND(CY37,2) -> 2674.49 | Y37: =ROUND(CZ37,2) -> 1366.96 | AA37: 56505405 | AB37: =ROUND((AC37+AD37+AF37),6) -> 13.365 | AC37: =ROUND((ES37),6) -> 0 | AD37: =ROUND(((((ET37*1.1))-((EU37*1.1)))+AE37),6) -> 0.55 | AE37: =ROUND(((EU37*1.1)),6) -> 0.088 | AF37: =ROUND(((EV37*1.1)),6) -> 12.815 | AG37: =ROUND((AP37),6) -> 0 | AH37: =((EW37*1.1)) -> 1.133 | AI37: =((EX37*1.1)) -> 0 | AJ37: =(AS37) -> 0 | AK37: 12.15 | AL37: 0 | AM37: 0.5 | AN37: 0.08 | AO37: 11.65 | AP37: 0 | AQ37: 1.03 | AR37: 0 | AS37: 0 | AT37: 90 | AU37: 46 | AV37: 1.047 | AW37: 1 | AZ37: 1 | BA37: 54.99 | BB37: 16.26 | BC37: 1 | BH37: 0 | BI37: 2 | BJ37: ТСН-2001.4 Доп. 68, Сб. 11, т. 12, поз. 1 | BM37: 72 | BN37: 0 | BO37: 4.11-12-1 | BP37: 1 | BQ37: 40 | BR37: 0 | BS37: 54.99 | BT37: 1 | BU37: 1 | BV37: 1 | BW37: 1 | BX37: 1 | BZ37: 90 | CA37: 46 | CE37: 30 | CF37: 0 | CG37: 0 | CM37: 0 | CO37: 0 | CP37: =(P37+Q37+S37) -> 2988.71 | CQ37: =ROUND((ROUND((AC37*AW37*1),2)*BC37),2) -> 0 | CR37: =(ROUND((ROUND((((ET37*1.1))*AV37*1),2)*BB37),2)+ROUND((ROUND(((AE37-((EU37*1.1)))*AV37*1),2)*BS37),2)) -> 9.43 | CS37: =ROUND((ROUND((AE37*AV37*1),2)*BS37),2) -> 4.95 | CT37: =ROUND((ROUND((AF37*AV37*1),2)*BA37),2) -> 737.97 | CU37: =AG37 -> 0 | CV37: =(AH37*AV37) -> 1.186251 | CW37: =AI37 -> 0 | CX37: =AJ37 -> 0 | CY37: =(((S37+R37)*AT37)/100) -> 2674.494 | CZ37: =(((S37+R37)*AU37)/100) -> 1366.9636 | DE37: *1,1 | DF37: *1,1 | DG37: *1,1 | DI37: *1,1 | DJ37: *1,1 | DN37: 0 | DO37: 0 | DP37: 1 | DQ37: 1 | DU37: 1013 | DV37: 1 ШТ. | DW37: 1 ШТ. | DX37: 1 | EE37: 58162634 | EF37: 40 | EG37: Монтаж оборудования | EH37: 0 | EJ37: 2 | EK37: 72 | EL37: ТСН-2001.4-11. Приборы и средства автоматизации и вычислительной техники | EM37: ТСН-2001.4-11-1 | EO37: Поправка: Гл.12.Прил.8.п.8. 5_12.00.01.11.003 | EQ37: 0 | ER37: 12.15 | ES37: 0 | ET37: 0.5 | EU37: 0.08 | EV37: 11.65 | EW37: 1.03 | EX37: 0 | EY37: 0 | FQ37: 0 | FR37: 0 | FS37: 0 | FX37: 90 | FY37: 46 | GD37: 1 | GF37: 1708693888 | GG37: 2 | GH37: 1 | GI37: 2 | GJ37: 0 | GK37: 0 | GL37: =ROUND(IF(AND(BH37=3,BI37=3,FS37<>0),P37,0),2) -> 0 | GM37: =ROUND(O37+X37+Y37,2)+GX37 -> 7030.16 | GN37: =IF(OR(BI37=0,BI37=1),GM37-GX37,0) -> 0 | GO37: =IF(BI37=2,GM37-GX37,0) -> 7030.16 | GP37: =IF(BI37=4,GM37-GX37,0) -> 0 | GR37: 0 | GS37: 3 | GT37: 0 | GV37: =ROUND((GT37),6) -> 0 | GW37: 1 | GX37: =ROUND(HC37*I37,2) -> 0 | HA37: 0 | HB37: 0 | HC37: =GV37*GW37 -> 0 | HS37: 0 | IK37: 0
A38: 18 | B38: 1 | E38: 2,1 | F38: КА 3 | G38: Вентиляторная панель 60А-91-11-30ВL | H38: шт. | I38: =I36*J38 -> 1 | J38: 0.25 | K38: 0.25 | O38: =ROUND(CP38,2) -> 3213.03 | P38: =ROUND((ROUND((AC38*I38),2)*BC38),2) -> 3213.03 | Q38: =(ROUND((ROUND(((ET38)*AV38*I38),2)*BB38),2)+ROUND((ROUND(((AE38-(EU38))*AV38*I38),2)*BS38),2)) -> 0 | R38: =ROUND((ROUND((AE38*AV38*I38),2)*BS38),2) -> 0 | S38: =ROUND((ROUND((AF38*AV38*I38),2)*BA38),2) -> 0 | T38: =ROUND(CU38*I38,2) -> 0 | U38: =CV38*I38 -> 0 | V38: =CW38*I38 -> 0 | W38: =ROUND(CX38*I38,2) -> 0 | X38: =ROUND(CY38,2) -> 0 | Y38: =ROUND(CZ38,2) -> 0 | AA38: 56505403 | AB38: =ROUND((AC38+AD38+AF38),6) -> 3213.03 | AC38: =ROUND((ES38),6) -> 3213.03 | AD38: =ROUND((((ET38)-(EU38))+AE38),6) -> 0 | AE38: =ROUND((EU38),6) -> 0 | AF38: =ROUND((EV38),6) -> 0 | AG38: =ROUND((AP38),6) -> 0 | AH38: =(EW38) -> 0 | AI38: =(EX38) -> 0 | AJ38: =(AS38) -> 0 | AK38: 3213.03 | AL38: 3213.03 | AM38: 0 | AN38: 0 | AO38: 0 | AP38: 0 | AQ38: 0 | AR38: 0 | AS38: 0 | AT38: 0 | AU38: 0 | AV38: 1 | AW38: 1 | AZ38: 1 | BA38: 1 | BB38: 1 | BC38: 1 | BH38: 3 | BI38: 3 | BM38: 746 | BN38: 0 | BP38: 0 | BQ38: 130 | BR38: 0 | BS38: 1 | BT38: 1 | BU38: 1 | BV38: 1 | BW38: 1 | BX38: 1 | BZ38: 90 | CA38: 46 | CE38: 30 | CF38: 0 | CG38: 0 | CM38: 0 | CO38: 0 | CP38: =(P38+Q38+S38) -> 3213.03 | CQ38: =ROUND((ROUND((AC38*1),2)*BC38),2) -> 3213.03 | CR38: =(ROUND((ROUND(((ET38)*AV38*1),2)*BB38),2)+ROUND((ROUND(((AE38-(EU38))*AV38*1),2)*BS38),2)) -> 0 | CS38: =ROUND((ROUND((AE38*AV38*1),2)*BS38),2) -> 0 | CT38: =ROUND((ROUND((AF38*AV38*1),2)*BA38),2) -> 0 | CU38: =AG38 -> 0 | CV38: =(AH38*AV38) -> 0 | CW38: =AI38 -> 0 | CX38: =AJ38 -> 0 | CY38: =(((S38+R38)*AT38)/100) -> 0 | CZ38: =(((S38+R38)*AU38)/100) -> 0 | DN38: 0 | DO38: 0 | DP38: 1 | DQ38: 1 | DU38: 1010 | DV38: шт. | DW38: шт. | DX38: 1 | EE38: 58162750 | EF38: 130 | EG38: Сметная стоимость оборудования | EH38: 0 | EJ38: 3 | EK38: 746 | EL38: ТСН-2001.13. Сметная стоимость оборудования | EM38: ТСН-2001.13 | EQ38: 0 | ER38: 0 | ES38: 3213.03 | ET38: 0 | EU38: 0 | EV38: 0 | EW38: 0 | EX38: 0 | FQ38: 0 | FR38: =P38 -> 3213.03 | FS38: 0 | FX38: 90 | FY38: 46 | GA38: [28 334 / 1,2 / 7,66] + 3% Трансп + 1,2% Заг.скл | GD38: 1 | GF38: 174995452 | GG38: 2 | GH38: 4 | GI38: -2 | GJ38: 0 | GK38: 0 | GL38: =ROUND(IF(AND(BH38=3,BI38=3,FS38<>0),P38,0),2) -> 0 | GM38: =ROUND(O38+X38+Y38,2)+GX38 -> 3213.03 | GN38: =IF(OR(BI38=0,BI38=1),GM38-GX38,0) -> 0 | GO38: =IF(BI38=2,GM38-GX38,0) -> 0 | GP38: =IF(BI38=4,GM38-GX38,0) -> 0 | GR38: 0 | GS38: 2 | GT38: 0 | GV38: =ROUND((GT38),6) -> 0 | GW38: 1 | GX38: =ROUND(HC38*I38,2) -> 0 | HA38: 0 | HB38: 0 | HC38: =GV38*GW38 -> 0 | HE38: 3 | HF38: 1,2 | HS38: 0 | IK38: 0
A39: 18 | B39: 1 | E39: 2,1 | F39: КА 3 | G39: Вентиляторная панель 60А-91-11-30ВL | H39: шт. | I39: =I37*J39 -> 1 | J39: 0.25 | K39: 0.25 | O39: =ROUND(CP39,2) -> 24611.81 | P39: =ROUND((ROUND((AC39*I39),2)*BC39),2) -> 24611.81 | Q39: =(ROUND((ROUND(((ET39)*AV39*I39),2)*BB39),2)+ROUND((ROUND(((AE39-(EU39))*AV39*I39),2)*BS39),2)) -> 0 | R39: =ROUND((ROUND((AE39*AV39*I39),2)*BS39),2) -> 0 | S39: =ROUND((ROUND((AF39*AV39*I39),2)*BA39),2) -> 0 | T39: =ROUND(CU39*I39,2) -> 0 | U39: =CV39*I39 -> 0 | V39: =CW39*I39 -> 0 | W39: =ROUND(CX39*I39,2) -> 0 | X39: =ROUND(CY39,2) -> 0 | Y39: =ROUND(CZ39,2) -> 0 | AA39: 56505405 | AB39: =ROUND((AC39+AD39+AF39),6) -> 3213.03 | AC39: =ROUND((ES39),6) -> 3213.03 | AD39: =ROUND((((ET39)-(EU39))+AE39),6) -> 0 | AE39: =ROUND((EU39),6) -> 0 | AF39: =ROUND((EV39),6) -> 0 | AG39: =ROUND((AP39),6) -> 0 | AH39: =(EW39) -> 0 | AI39: =(EX39) -> 0 | AJ39: =(AS39) -> 0 | AK39: 3213.03 | AL39: 3213.03 | AM39: 0 | AN39: 0 | AO39: 0 | AP39: 0 | AQ39: 0 | AR39: 0 | AS39: 0 | AT39: 0 | AU39: 0 | AV39: 1 | AW39: 1 | AZ39: 1 | BA39: 1 | BB39: 1 | BC39: 7.66 | BH39: 3 | BI39: 3 | BM39: 746 | BN39: 0 | BP39: 0 | BQ39: 130 | BR39: 0 | BS39: 1 | BT39: 1 | BU39: 1 | BV39: 1 | BW39: 1 | BX39: 1 | BZ39: 90 | CA39: 46 | CE39: 30 | CF39: 0 | CG39: 0 | CM39: 0 | CO39: 0 | CP39: =(P39+Q39+S39) -> 24611.81 | CQ39: =ROUND((ROUND((AC39*1),2)*BC39),2) -> 24611.81 | CR39: =(ROUND((ROUND(((ET39)*AV39*1),2)*BB39),2)+ROUND((ROUND(((AE39-(EU39))*AV39*1),2)*BS39),2)) -> 0 | CS39: =ROUND((ROUND((AE39*AV39*1),2)*BS39),2) -> 0 | CT39: =ROUND((ROUND((AF39*AV39*1),2)*BA39),2) -> 0 | CU39: =AG39 -> 0 | CV39: =(AH39*AV39) -> 0 | CW39: =AI39 -> 0 | CX39: =AJ39 -> 0 | CY39: =(((S39+R39)*AT39)/100) -> 0 | CZ39: =(((S39+R39)*AU39)/100) -> 0 | DN39: 0 | DO39: 0 | DP39: 1 | DQ39: 1 | DU39: 1010 | DV39: шт. | DW39: шт. | DX39: 1 | EE39: 58162750 | EF39: 130 | EG39: Сметная стоимость оборудования | EH39: 0 | EJ39: 3 | EK39: 746 | EL39: ТСН-2001.13. Сметная стоимость оборудования | EM39: ТСН-2001.13 | EQ39: 0 | ER39: 2437.64 | ES39: 3213.03 | ET39: 0 | EU39: 0 | EV39: 0 | EW39: 0 | EX39: 0 | EZ39: 5 | FC39: 1 | FD39: 18 | FF39: 28334 | FQ39: 0 | FR39: =P39 -> 24611.81 | FS39: 0 | FX39: 90 | FY39: 46 | GA39: [28 334 / 1,2 / 7,66] + 3% Трансп + 1,2% Заг.скл | GD39: 1 | GF39: 174995452 | GG39: 2 | GH39: 3 | GI39: 5 | GJ39: 0 | GK39: 0 | GL39: =ROUND(IF(AND(BH39=3,BI39=3,FS39<>0),P39,0),2) -> 0 | GM39: =ROUND(O39+X39+Y39,2)+GX39 -> 24611.81 | GN39: =IF(OR(BI39=0,BI39=1),GM39-GX39,0) -> 0 | GO39: =IF(BI39=2,GM39-GX39,0) -> 0 | GP39: =IF(BI39=4,GM39-GX39,0) -> 0 | GR39: 1 | GS39: 1 | GT39: 0 | GV39: =ROUND((GT39),6) -> 0 | GW39: 1 | GX39: =ROUND(HC39*I39,2) -> 0 | HA39: 0 | HB39: 0 | HC39: =GV39*GW39 -> 0 | HE39: 3 | HF39: 1,2 | HS39: 0 | IK39: 0
A40: 18 | B40: 1 | E40: 2,2 | F40: КА 5 | G40: Выдвижная полка для клавиатуры 60А-04-45-11BL | H40: шт. | I40: =I36*J40 -> 1 | J40: 0.25 | K40: 0.25 | O40: =ROUND(CP40,2) -> 553.19 | P40: =ROUND((ROUND((AC40*AW40*I40),2)*BC40),2) -> 553.19 | Q40: =(ROUND((ROUND(((ET40)*AV40*I40),2)*BB40),2)+ROUND((ROUND(((AE40-(EU40))*AV40*I40),2)*BS40),2)) -> 0 | R40: =ROUND((ROUND((AE40*AV40*I40),2)*BS40),2) -> 0 | S40: =ROUND((ROUND((AF40*AV40*I40),2)*BA40),2) -> 0 | T40: =ROUND(CU40*I40,2) -> 0 | U40: =CV40*I40 -> 0 | V40: =CW40*I40 -> 0 | W40: =ROUND(CX40*I40,2) -> 0 | X40: =ROUND(CY40,2) -> 0 | Y40: =ROUND(CZ40,2) -> 0 | AA40: 56505403 | AB40: =ROUND((AC40+AD40+AF40),6) -> 553.19 | AC40: =ROUND((ES40),6) -> 553.19 | AD40: =ROUND((((ET40)-(EU40))+AE40),6) -> 0 | AE40: =ROUND((EU40),6) -> 0 | AF40: =ROUND((EV40),6) -> 0 | AG40: =ROUND((AP40),6) -> 0 | AH40: =(EW40) -> 0 | AI40: =(EX40) -> 0 | AJ40: =(AS40) -> 0 | AK40: 553.19 | AL40: 553.19 | AM40: 0 | AN40: 0 | AO40: 0 | AP40: 0 | AQ40: 0 | AR40: 0 | AS40: 0 | AT40: 90 | AU40: 46 | AV40: 1 | AW40: 1 | AZ40: 1 | BA40: 1 | BB40: 1 | BC40: 1 | BH40: 3 | BI40: 2 | BM40: 72 | BN40: 0 | BP40: 0 | BQ40: 40 | BR40: 0 | BS40: 1 | BT40: 1 | BU40: 1 | BV40: 1 | BW40: 1 | BX40: 1 | BZ40: 90 | CA40: 46 | CE40: 30 | CF40: 0 | CG40: 0 | CM40: 0 | CO40: 0 | CP40: =(P40+Q40+S40) -> 553.19 | CQ40: =ROUND((ROUND((AC40*AW40*1),2)*BC40),2) -> 553.19 | CR40: =(ROUND((ROUND(((ET40)*AV40*1),2)*BB40),2)+ROUND((ROUND(((AE40-(EU40))*AV40*1),2)*BS40),2)) -> 0 | CS40: =ROUND((ROUND((AE40*AV40*1),2)*BS40),2) -> 0 | CT40: =ROUND((ROUND((AF40*AV40*1),2)*BA40),2) -> 0 | CU40: =AG40 -> 0 | CV40: =(AH40*AV40) -> 0 | CW40: =AI40 -> 0 | CX40: =AJ40 -> 0 | CY40: =(((S40+R40)*AT40)/100) -> 0 | CZ40: =(((S40+R40)*AU40)/100) -> 0 | DN40: 0 | DO40: 0 | DP40: 1 | DQ40: 1 | DU40: 1010 | DV40: шт. | DW40: шт. | DX40: 1 | EE40: 58162634 | EF40: 40 | EG40: Монтаж оборудования | EH40: 0 | EJ40: 2 | EK40: 72 | EL40: ТСН-2001.4-11. Приборы и средства автоматизации и вычислительной техники | EM40: ТСН-2001.4-11-1 | EQ40: 0 | ER40: 0 | ES40: 553.19 | ET40: 0 | EU40: 0 | EV40: 0 | EW40: 0 | EX40: 0 | FQ40: 0 | FR40: 0 | FS40: 0 | FX40: 90 | FY40: 46 | GA40: [6 430 / 1,2 / 9,88] + 2% Заг.скл | GD40: 1 | GF40: 1122354003 | GG40: 2 | GH40: 4 | GI40: -2 | GJ40: 0 | GK40: 0 | GL40: =ROUND(IF(AND(BH40=3,BI40=3,FS40<>0),P40,0),2) -> 0 | GM40: =ROUND(O40+X40+Y40,2)+GX40 -> 553.19 | GN40: =IF(OR(BI40=0,BI40=1),GM40-GX40,0) -> 0 | GO40: =IF(BI40=2,GM40-GX40,0) -> 553.19 | GP40: =IF(BI40=4,GM40-GX40,0) -> 0 | GR40: 0 | GS40: 2 | GT40: 0 | GV40: =ROUND((GT40),6) -> 0 | GW40: 1 | GX40: =ROUND(HC40*I40,2) -> 0 | HA40: 0 | HB40: 0 | HC40: =GV40*GW40 -> 0 | HE40: 0 | HF40: 2 | HS40: 0 | IK40: 0
A41: 18 | B41: 1 | E41: 2,2 | F41: КА 5 | G41: Выдвижная полка для клавиатуры 60А-04-45-11BL | H41: шт. | I41: =I37*J41 -> 1 | J41: 0.25 | K41: 0.25 | O41: =ROUND(CP41,2) -> 5465.52 | P41: =ROUND((ROUND((AC41*AW41*I41),2)*BC41),2) -> 5465.52 | Q41: =(ROUND((ROUND(((ET41)*AV41*I41),2)*BB41),2)+ROUND((ROUND(((AE41-(EU41))*AV41*I41),2)*BS41),2)) -> 0 | R41: =ROUND((ROUND((AE41*AV41*I41),2)*BS41),2) -> 0 | S41: =ROUND((ROUND((AF41*AV41*I41),2)*BA41),2) -> 0 | T41: =ROUND(CU41*I41,2) -> 0 | U41: =CV41*I41 -> 0 | V41: =CW41*I41 -> 0 | W41: =ROUND(CX41*I41,2) -> 0 | X41: =ROUND(CY41,2) -> 0 | Y41: =ROUND(CZ41,2) -> 0 | AA41: 56505405 | AB41: =ROUND((AC41+AD41+AF41),6) -> 553.19 | AC41: =ROUND((ES41),6) -> 553.19 | AD41: =ROUND((((ET41)-(EU41))+AE41),6) -> 0 | AE41: =ROUND((EU41),6) -> 0 | AF41: =ROUND((EV41),6) -> 0 | AG41: =ROUND((AP41),6) -> 0 | AH41: =(EW41) -> 0 | AI41: =(EX41) -> 0 | AJ41: =(AS41) -> 0 | AK41: 553.19 | AL41: 553.19 | AM41: 0 | AN41: 0 | AO41: 0 | AP41: 0 | AQ41: 0 | AR41: 0 | AS41: 0 | AT41: 90 | AU41: 46 | AV41: 1 | AW41: 1 | AZ41: 1 | BA41: 1 | BB41: 1 | BC41: 9.88 | BH41: 3 | BI41: 2 | BM41: 72 | BN41: 0 | BP41: 0 | BQ41: 40 | BR41: 0 | BS41: 1 | BT41: 1 | BU41: 1 | BV41: 1 | BW41: 1 | BX41: 1 | BZ41: 90 | CA41: 46 | CE41: 30 | CF41: 0 | CG41: 0 | CM41: 0 | CO41: 0 | CP41: =(P41+Q41+S41) -> 5465.52 | CQ41: =ROUND((ROUND((AC41*AW41*1),2)*BC41),2) -> 5465.52 | CR41: =(ROUND((ROUND(((ET41)*AV41*1),2)*BB41),2)+ROUND((ROUND(((AE41-(EU41))*AV41*1),2)*BS41),2)) -> 0 | CS41: =ROUND((ROUND((AE41*AV41*1),2)*BS41),2) -> 0 | CT41: =ROUND((ROUND((AF41*AV41*1),2)*BA41),2) -> 0 | CU41: =AG41 -> 0 | CV41: =(AH41*AV41) -> 0 | CW41: =AI41 -> 0 | CX41: =AJ41 -> 0 | CY41: =(((S41+R41)*AT41)/100) -> 0 | CZ41: =(((S41+R41)*AU41)/100) -> 0 | DN41: 0 | DO41: 0 | DP41: 1 | DQ41: 1 | DU41: 1010 | DV41: шт. | DW41: шт. | DX41: 1 | EE41: 58162634 | EF41: 40 | EG41: Монтаж оборудования | EH41: 0 | EJ41: 2 | EK41: 72 | EL41: ТСН-2001.4-11. Приборы и средства автоматизации и вычислительной техники | EM41: ТСН-2001.4-11-1 | EQ41: 0 | ER41: 553.19 | ES41: 553.19 | ET41: 0 | EU41: 0 | EV41: 0 | EW41: 0 | EX41: 0 | EZ41: 5 | FC41: 1 | FD41: 18 | FF41: 6430 | FQ41: 0 | FR41: 0 | FS41: 0 | FX41: 90 | FY41: 46 | GA41: [6 430 / 1,2 / 9,88] + 2% Заг.скл | GD41: 1 | GF41: 1122354003 | GG41: 2 | GH41: 3 | GI41: 5 | GJ41: 0 | GK41: 0 | GL41: =ROUND(IF(AND(BH41=3,BI41=3,FS41<>0),P41,0),2) -> 0 | GM41: =ROUND(O41+X41+Y41,2)+GX41 -> 5465.52 | GN41: =IF(OR(BI41=0,BI41=1),GM41-GX41,0) -> 0 | GO41: =IF(BI41=2,GM41-GX41,0) -> 5465.52 | GP41: =IF(BI41=4,GM41-GX41,0) -> 0 | GR41: 1 | GS41: 1 | GT41: 0 | GV41: =ROUND((GT41),6) -> 0 | GW41: 1 | GX41: =ROUND(HC41*I41,2) -> 0 | HA41: 0 | HB41: 0 | HC41: =GV41*GW41 -> 0 | HE41: 0 | HF41: 2 | HS41: 0 | IK41: 0
A42: 18 | B42: 1 | E42: 2,3 | F42: КА 6 | G42: Полка сmацuонарная регулuруемая 1U до 50кг, 370мм, для 600мм | H42: шт. | I42: =I36*J42 -> 1 | J42: 0.25 | K42: 0.25 | O42: =ROUND(CP42,2) -> 381.47 | P42: =ROUND((ROUND((AC42*AW42*I42),2)*BC42),2) -> 381.47 | Q42: =(ROUND((ROUND(((ET42)*AV42*I42),2)*BB42),2)+ROUND((ROUND(((AE42-(EU42))*AV42*I42),2)*BS42),2)) -> 0 | R42: =ROUND((ROUND((AE42*AV42*I42),2)*BS42),2) -> 0 | S42: =ROUND((ROUND((AF42*AV42*I42),2)*BA42),2) -> 0 | T42: =ROUND(CU42*I42,2) -> 0 | U42: =CV42*I42 -> 0 | V42: =CW42*I42 -> 0 | W42: =ROUND(CX42*I42,2) -> 0 | X42: =ROUND(CY42,2) -> 0 | Y42: =ROUND(CZ42,2) -> 0 | AA42: 56505403 | AB42: =ROUND((AC42+AD42+AF42),6) -> 381.47 | AC42: =ROUND((ES42),6) -> 381.47 | AD42: =ROUND((((ET42)-(EU42))+AE42),6) -> 0 | AE42: =ROUND((EU42),6) -> 0 | AF42: =ROUND((EV42),6) -> 0 | AG42: =ROUND((AP42),6) -> 0 | AH42: =(EW42) -> 0 | AI42: =(EX42) -> 0 | AJ42: =(AS42) -> 0 | AK42: 381.47 | AL42: 381.47 | AM42: 0 | AN42: 0 | AO42: 0 | AP42: 0 | AQ42: 0 | AR42: 0 | AS42: 0 | AT42: 90 | AU42: 46 | AV42: 1 | AW42: 1 | AZ42: 1 | BA42: 1 | BB42: 1 | BC42: 1 | BH42: 3 | BI42: 2 | BM42: 72 | BN42: 0 | BP42: 0 | BQ42: 40 | BR42: 0 | BS42: 1 | BT42: 1 | BU42: 1 | BV42: 1 | BW42: 1 | BX42: 1 | BZ42: 90 | CA42: 46 | CE42: 30 | CF42: 0 | CG42: 0 | CM42: 0 | CO42: 0 | CP42: =(P42+Q42+S42) -> 381.47 | CQ42: =ROUND((ROUND((AC42*AW42*1),2)*BC42),2) -> 381.47 | CR42: =(ROUND((ROUND(((ET42)*AV42*1),2)*BB42),2)+ROUND((ROUND(((AE42-(EU42))*AV42*1),2)*BS42),2)) -> 0 | CS42: =ROUND((ROUND((AE42*AV42*1),2)*BS42),2) -> 0 | CT42: =ROUND((ROUND((AF42*AV42*1),2)*BA42),2) -> 0 | CU42: =AG42 -> 0 | CV42: =(AH42*AV42) -> 0 | CW42: =AI42 -> 0 | CX42: =AJ42 -> 0 | CY42: =(((S42+R42)*AT42)/100) -> 0 | CZ42: =(((S42+R42)*AU42)/100) -> 0 | DN42: 0 | DO42: 0 | DP42: 1 | DQ42: 1 | DU42: 1010 | DV42: шт. | DW42: шт. | DX42: 1 | EE42: 58162634 | EF42: 40 | EG42: Монтаж оборудования | EH42: 0 | EJ42: 2 | EK42: 72 | EL42: ТСН-2001.4-11. Приборы и средства автоматизации и вычислительной техники | EM42: ТСН-2001.4-11-1 | EQ42: 0 | ER42: 0 | ES42: 381.47 | ET42: 0 | EU42: 0 | EV42: 0 | EW42: 0 | EX42: 0 | FQ42: 0 | FR42: 0 | FS42: 0 | FX42: 90 | FY42: 46 | GA42: [4 434 / 1,2 / 9,88] + 2% Заг.скл | GD42: 1 | GF42: -1998996946 | GG42: 2 | GH42: 4 | GI42: -2 | GJ42: 0 | GK42: 0 | GL42: =ROUND(IF(AND(BH42=3,BI42=3,FS42<>0),P42,0),2) -> 0 | GM42: =ROUND(O42+X42+Y42,2)+GX42 -> 381.47 | GN42: =IF(OR(BI42=0,BI42=1),GM42-GX42,0) -> 0 | GO42: =IF(BI42=2,GM42-GX42,0) -> 381.47 | GP42: =IF(BI42=4,GM42-GX42,0) -> 0 | GR42: 0 | GS42: 2 | GT42: 0 | GV42: =ROUND((GT42),6) -> 0 | GW42: 1 | GX42: =ROUND(HC42*I42,2) -> 0 | HA42: 0 | HB42: 0 | HC42: =GV42*GW42 -> 0 | HE42: 0 | HF42: 2 | HS42: 0 | IK42: 0
A43: 18 | B43: 1 | E43: 2,3 | F43: КА 6 | G43: Полка сmацuонарная регулuруемая 1U до 50кг, 370мм, для 600мм | H43: шт. | I43: =I37*J43 -> 1 | J43: 0.25 | K43: 0.25 | O43: =ROUND(CP43,2) -> 3768.92 | P43: =ROUND((ROUND((AC43*AW43*I43),2)*BC43),2) -> 3768.92 | Q43: =(ROUND((ROUND(((ET43)*AV43*I43),2)*BB43),2)+ROUND((ROUND(((AE43-(EU43))*AV43*I43),2)*BS43),2)) -> 0 | R43: =ROUND((ROUND((AE43*AV43*I43),2)*BS43),2) -> 0 | S43: =ROUND((ROUND((AF43*AV43*I43),2)*BA43),2) -> 0 | T43: =ROUND(CU43*I43,2) -> 0 | U43: =CV43*I43 -> 0 | V43: =CW43*I43 -> 0 | W43: =ROUND(CX43*I43,2) -> 0 | X43: =ROUND(CY43,2) -> 0 | Y43: =ROUND(CZ43,2) -> 0 | AA43: 56505405 | AB43: =ROUND((AC43+AD43+AF43),6) -> 381.47 | AC43: =ROUND((ES43),6) -> 381.47 | AD43: =ROUND((((ET43)-(EU43))+AE43),6) -> 0 | AE43: =ROUND((EU43),6) -> 0 | AF43: =ROUND((EV43),6) -> 0 | AG43: =ROUND((AP43),6) -> 0 | AH43: =(EW43) -> 0 | AI43: =(EX43) -> 0 | AJ43: =(AS43) -> 0 | AK43: 381.47 | AL43: 381.47 | AM43: 0 | AN43: 0 | AO43: 0 | AP43: 0 | AQ43: 0 | AR43: 0 | AS43: 0 | AT43: 90 | AU43: 46 | AV43: 1 | AW43: 1 | AZ43: 1 | BA43: 1 | BB43: 1 | BC43: 9.88 | BH43: 3 | BI43: 2 | BM43: 72 | BN43: 0 | BP43: 0 | BQ43: 40 | BR43: 0 | BS43: 1 | BT43: 1 | BU43: 1 | BV43: 1 | BW43: 1 | BX43: 1 | BZ43: 90 | CA43: 46 | CE43: 30 | CF43: 0 | CG43: 0 | CM43: 0 | CO43: 0 | CP43: =(P43+Q43+S43) -> 3768.92 | CQ43: =ROUND((ROUND((AC43*AW43*1),2)*BC43),2) -> 3768.92 | CR43: =(ROUND((ROUND(((ET43)*AV43*1),2)*BB43),2)+ROUND((ROUND(((AE43-(EU43))*AV43*1),2)*BS43),2)) -> 0 | CS43: =ROUND((ROUND((AE43*AV43*1),2)*BS43),2) -> 0 | CT43: =ROUND((ROUND((AF43*AV43*1),2)*BA43),2) -> 0 | CU43: =AG43 -> 0 | CV43: =(AH43*AV43) -> 0 | CW43: =AI43 -> 0 | CX43: =AJ43 -> 0 | CY43: =(((S43+R43)*AT43)/100) -> 0 | CZ43: =(((S43+R43)*AU43)/100) -> 0 | DN43: 0 | DO43: 0 | DP43: 1 | DQ43: 1 | DU43: 1010 | DV43: шт. | DW43: шт. | DX43: 1 | EE43: 58162634 | EF43: 40 | EG43: Монтаж оборудования | EH43: 0 | EJ43: 2 | EK43: 72 | EL43: ТСН-2001.4-11. Приборы и средства автоматизации и вычислительной техники | EM43: ТСН-2001.4-11-1 | EQ43: 0 | ER43: 381.47 | ES43: 381.47 | ET43: 0 | EU43: 0 | EV43: 0 | EW43: 0 | EX43: 0 | EZ43: 5 | FC43: 1 | FD43: 18 | FF43: 4434 | FQ43: 0 | FR43: 0 | FS43: 0 | FX43: 90 | FY43: 46 | GA43: [4 434 / 1,2 / 9,88] + 2% Заг.скл | GD43: 1 | GF43: -1998996946 | GG43: 2 | GH43: 3 | GI43: 5 | GJ43: 0 | GK43: 0 | GL43: =ROUND(IF(AND(BH43=3,BI43=3,FS43<>0),P43,0),2) -> 0 | GM43: =ROUND(O43+X43+Y43,2)+GX43 -> 3768.92 | GN43: =IF(OR(BI43=0,BI43=1),GM43-GX43,0) -> 0 | GO43: =IF(BI43=2,GM43-GX43,0) -> 3768.92 | GP43: =IF(BI43=4,GM43-GX43,0) -> 0 | GR43: 1 | GS43: 1 | GT43: 0 | GV43: =ROUND((GT43),6) -> 0 | GW43: 1 | GX43: =ROUND(HC43*I43,2) -> 0 | HA43: 0 | HB43: 0 | HC43: =GV43*GW43 -> 0 | HE43: 0 | HF43: 2 | HS43: 0 | IK43: 0
A44: 18 | B44: 1 | E44: 2,4 | F44: КА 8 | G44: Панель освещенuя на магнumах, унuверсальная цвеm черныu 60A-05-15BL | H44: шт. | I44: =I36*J44 -> 1 | J44: 0.25 | K44: 0.25 | O44: =ROUND(CP44,2) -> 720.68 | P44: =ROUND((ROUND((AC44*AW44*I44),2)*BC44),2) -> 720.68 | Q44: =(ROUND((ROUND(((ET44)*AV44*I44),2)*BB44),2)+ROUND((ROUND(((AE44-(EU44))*AV44*I44),2)*BS44),2)) -> 0 | R44: =ROUND((ROUND((AE44*AV44*I44),2)*BS44),2) -> 0 | S44: =ROUND((ROUND((AF44*AV44*I44),2)*BA44),2) -> 0 | T44: =ROUND(CU44*I44,2) -> 0 | U44: =CV44*I44 -> 0 | V44: =CW44*I44 -> 0 | W44: =ROUND(CX44*I44,2) -> 0 | X44: =ROUND(CY44,2) -> 0 | Y44: =ROUND(CZ44,2) -> 0 | AA44: 56505403 | AB44: =ROUND((AC44+AD44+AF44),6) -> 720.68 | AC44: =ROUND((ES44),6) -> 720.68 | AD44: =ROUND((((ET44)-(EU44))+AE44),6) -> 0 | AE44: =ROUND((EU44),6) -> 0 | AF44: =ROUND((EV44),6) -> 0 | AG44: =ROUND((AP44),6) -> 0 | AH44: =(EW44) -> 0 | AI44: =(EX44) -> 0 | AJ44: =(AS44) -> 0 | AK44: 720.68 | AL44: 720.68 | AM44: 0 | AN44: 0 | AO44: 0 | AP44: 0 | AQ44: 0 | AR44: 0 | AS44: 0 | AT44: 90 | AU44: 46 | AV44: 1 | AW44: 1 | AZ44: 1 | BA44: 1 | BB44: 1 | BC44: 1 | BH44: 3 | BI44: 2 | BM44: 72 | BN44: 0 | BP44: 0 | BQ44: 40 | BR44: 0 | BS44: 1 | BT44: 1 | BU44: 1 | BV44: 1 | BW44: 1 | BX44: 1 | BZ44: 90 | CA44: 46 | CE44: 30 | CF44: 0 | CG44: 0 | CM44: 0 | CO44: 0 | CP44: =(P44+Q44+S44) -> 720.68 | CQ44: =ROUND((ROUND((AC44*AW44*1),2)*BC44),2) -> 720.68 | CR44: =(ROUND((ROUND(((ET44)*AV44*1),2)*BB44),2)+ROUND((ROUND(((AE44-(EU44))*AV44*1),2)*BS44),2)) -> 0 | CS44: =ROUND((ROUND((AE44*AV44*1),2)*BS44),2) -> 0 | CT44: =ROUND((ROUND((AF44*AV44*1),2)*BA44),2) -> 0 | CU44: =AG44 -> 0 | CV44: =(AH44*AV44) -> 0 | CW44: =AI44 -> 0 | CX44: =AJ44 -> 0 | CY44: =(((S44+R44)*AT44)/100) -> 0 | CZ44: =(((S44+R44)*AU44)/100) -> 0 | DN44: 0 | DO44: 0 | DP44: 1 | DQ44: 1 | DU44: 1010 | DV44: шт. | DW44: шт. | DX44: 1 | EE44: 58162634 | EF44: 40 | EG44: Монтаж оборудования | EH44: 0 | EJ44: 2 | EK44: 72 | EL44: ТСН-2001.4-11. Приборы и средства автоматизации и вычислительной техники | EM44: ТСН-2001.4-11-1 | EQ44: 0 | ER44: 0 | ES44: 720.68 | ET44: 0 | EU44: 0 | EV44: 0 | EW44: 0 | EX44: 0 | FQ44: 0 | FR44: 0 | FS44: 0 | FX44: 90 | FY44: 46 | GA44: [8 376,8 / 1,2 / 9,88] + 2% Заг.скл | GD44: 1 | GF44: -1548011914 | GG44: 2 | GH44: 4 | GI44: -2 | GJ44: 0 | GK44: 0 | GL44: =ROUND(IF(AND(BH44=3,BI44=3,FS44<>0),P44,0),2) -> 0 | GM44: =ROUND(O44+X44+Y44,2)+GX44 -> 720.68 | GN44: =IF(OR(BI44=0,BI44=1),GM44-GX44,0) -> 0 | GO44: =IF(BI44=2,GM44-GX44,0) -> 720.68 | GP44: =IF(BI44=4,GM44-GX44,0) -> 0 | GR44: 0 | GS44: 2 | GT44: 0 | GV44: =ROUND((GT44),6) -> 0 | GW44: 1 | GX44: =ROUND(HC44*I44,2) -> 0 | HA44: 0 | HB44: 0 | HC44: =GV44*GW44 -> 0 | HE44: 0 | HF44: 2 | HS44: 0 | IK44: 0
A45: 18 | B45: 1 | E45: 2,4 | F45: КА 8 | G45: Панель освещенuя на магнumах, унuверсальная цвеm черныu 60A-05-15BL | H45: шт. | I45: =I37*J45 -> 1 | J45: 0.25 | K45: 0.25 | O45: =ROUND(CP45,2) -> 7120.32 | P45: =ROUND((ROUND((AC45*AW45*I45),2)*BC45),2) -> 7120.32 | Q45: =(ROUND((ROUND(((ET45)*AV45*I45),2)*BB45),2)+ROUND((ROUND(((AE45-(EU45))*AV45*I45),2)*BS45),2)) -> 0 | R45: =ROUND((ROUND((AE45*AV45*I45),2)*BS45),2) -> 0 | S45: =ROUND((ROUND((AF45*AV45*I45),2)*BA45),2) -> 0 | T45: =ROUND(CU45*I45,2) -> 0 | U45: =CV45*I45 -> 0 | V45: =CW45*I45 -> 0 | W45: =ROUND(CX45*I45,2) -> 0 | X45: =ROUND(CY45,2) -> 0 | Y45: =ROUND(CZ45,2) -> 0 | AA45: 56505405 | AB45: =ROUND((AC45+AD45+AF45),6) -> 720.68 | AC45: =ROUND((ES45),6) -> 720.68 | AD45: =ROUND((((ET45)-(EU45))+AE45),6) -> 0 | AE45: =ROUND((EU45),6) -> 0 | AF45: =ROUND((EV45),6) -> 0 | AG45: =ROUND((AP45),6) -> 0 | AH45: =(EW45) -> 0 | AI45: =(EX45) -> 0 | AJ45: =(AS45) -> 0 | AK45: 720.68 | AL45: 720.68 | AM45: 0 | AN45: 0 | AO45: 0 | AP45: 0 | AQ45: 0 | AR45: 0 | AS45: 0 | AT45: 90 | AU45: 46 | AV45: 1 | AW45: 1 | AZ45: 1 | BA45: 1 | BB45: 1 | BC45: 9.88 | BH45: 3 | BI45: 2 | BM45: 72 | BN45: 0 | BP45: 0 | BQ45: 40 | BR45: 0 | BS45: 1 | BT45: 1 | BU45: 1 | BV45: 1 | BW45: 1 | BX45: 1 | BZ45: 90 | CA45: 46 | CE45: 30 | CF45: 0 | CG45: 0 | CM45: 0 | CO45: 0 | CP45: =(P45+Q45+S45) -> 7120.32 | CQ45: =ROUND((ROUND((AC45*AW45*1),2)*BC45),2) -> 7120.32 | CR45: =(ROUND((ROUND(((ET45)*AV45*1),2)*BB45),2)+ROUND((ROUND(((AE45-(EU45))*AV45*1),2)*BS45),2)) -> 0 | CS45: =ROUND((ROUND((AE45*AV45*1),2)*BS45),2) -> 0 | CT45: =ROUND((ROUND((AF45*AV45*1),2)*BA45),2) -> 0 | CU45: =AG45 -> 0 | CV45: =(AH45*AV45) -> 0 | CW45: =AI45 -> 0 | CX45: =AJ45 -> 0 | CY45: =(((S45+R45)*AT45)/100) -> 0 | CZ45: =(((S45+R45)*AU45)/100) -> 0 | DN45: 0 | DO45: 0 | DP45: 1 | DQ45: 1 | DU45: 1010 | DV45: шт. | DW45: шт. | DX45: 1 | EE45: 58162634 | EF45: 40 | EG45: Монтаж оборудования | EH45: 0 | EJ45: 2 | EK45: 72 | EL45: ТСН-2001.4-11. Приборы и средства автоматизации и вычислительной техники | EM45: ТСН-2001.4-11-1 | EQ45: 0 | ER45: 720.68 | ES45: 720.68 | ET45: 0 | EU45: 0 | EV45: 0 | EW45: 0 | EX45: 0 | EZ45: 5 | FC45: 1 | FD45: 18 | FF45: 8376.8 | FQ45: 0 | FR45: 0 | FS45: 0 | FX45: 90 | FY45: 46 | GA45: [8 376,8 / 1,2 / 9,88] + 2% Заг.скл | GD45: 1 | GF45: -1548011914 | GG45: 2 | GH45: 3 | GI45: 5 | GJ45: 0 | GK45: 0 | GL45: =ROUND(IF(AND(BH45=3,BI45=3,FS45<>0),P45,0),2) -> 0 | GM45: =ROUND(O45+X45+Y45,2)+GX45 -> 7120.32 | GN45: =IF(OR(BI45=0,BI45=1),GM45-GX45,0) -> 0 | GO45: =IF(BI45=2,GM45-GX45,0) -> 7120.32 | GP45: =IF(BI45=4,GM45-GX45,0) -> 0 | GR45: 1 | GS45: 1 | GT45: 0 | GV45: =ROUND((GT45),6) -> 0 | GW45: 1 | GX45: =ROUND(HC45*I45,2) -> 0 | HA45: 0 | HB45: 0 | HC45: =GV45*GW45 -> 0 | HE45: 0 | HF45: 2 | HS45: 0 | IK45: 0
A46: 17 | B46: 1 | D46: =ROW(EtalonRes!A19) -> 19 | E46: 3 | F46: 4.11-14-1 | G46: Включение штепсельных разъемов в аппаратуру, количество контактов в разъеме до 14 | H46: 1 разъем | I46: 1 | J46: 0 | K46: 1 | O46: =ROUND(CP46,2) -> 2.9 | P46: =ROUND((ROUND((AC46*AW46*I46),2)*BC46),2) -> 0 | Q46: =(ROUND((ROUND((((ET46*1.1))*AV46*I46),2)*BB46),2)+ROUND((ROUND(((AE46-((EU46*1.1)))*AV46*I46),2)*BS46),2)) -> 0 | R46: =ROUND((ROUND((AE46*AV46*I46),2)*BS46),2) -> 0 | S46: =ROUND((ROUND((AF46*AV46*I46),2)*BA46),2) -> 2.9 | T46: =ROUND(CU46*I46,2) -> 0 | U46: =CV46*I46 -> 0.253374 | V46: =CW46*I46 -> 0 | W46: =ROUND(CX46*I46,2) -> 0 | X46: =ROUND(CY46,2) -> 2.61 | Y46: =ROUND(CZ46,2) -> 1.33 | AA46: 56505403 | AB46: =ROUND((AC46+AD46+AF46),6) -> 2.772 | AC46: =ROUND((ES46),6) -> 0 | AD46: =ROUND(((((ET46*1.1))-((EU46*1.1)))+AE46),6) -> 0 | AE46: =ROUND(((EU46*1.1)),6) -> 0 | AF46: =ROUND(((EV46*1.1)),6) -> 2.772 | AG46: =ROUND((AP46),6) -> 0 | AH46: =((EW46*1.1)) -> 0.242 | AI46: =((EX46*1.1)) -> 0 | AJ46: =(AS46) -> 0 | AK46: 2.52 | AL46: 0 | AM46: 0 | AN46: 0 | AO46: 2.52 | AP46: 0 | AQ46: 0.22 | AR46: 0 | AS46: 0 | AT46: 90 | AU46: 46 | AV46: 1.047 | AW46: 1 | AZ46: 1 | BA46: 1 | BB46: 1 | BC46: 1 | BH46: 0 | BI46: 2 | BJ46: ТСН-2001.4 Доп. 67, Сб. 11, т. 14, поз. 1 | BM46: 72 | BN46: 0 | BO46: 4.11-14-1 | BP46: 1 | BQ46: 40 | BR46: 0 | BS46: 1 | BT46: 1 | BU46: 1 | BV46: 1 | BW46: 1 | BX46: 1 | BZ46: 90 | CA46: 46 | CE46: 30 | CF46: 0 | CG46: 0 | CM46: 0 | CO46: 0 | CP46: =(P46+Q46+S46) -> 2.9 | CQ46: =ROUND((ROUND((AC46*AW46*1),2)*BC46),2) -> 0 | CR46: =(ROUND((ROUND((((ET46*1.1))*AV46*1),2)*BB46),2)+ROUND((ROUND(((AE46-((EU46*1.1)))*AV46*1),2)*BS46),2)) -> 0 | CS46: =ROUND((ROUND((AE46*AV46*1),2)*BS46),2) -> 0 | CT46: =ROUND((ROUND((AF46*AV46*1),2)*BA46),2) -> 2.9 | CU46: =AG46 -> 0 | CV46: =(AH46*AV46) -> 0.253374 | CW46: =AI46 -> 0 | CX46: =AJ46 -> 0 | CY46: =(((S46+R46)*AT46)/100) -> 2.61 | CZ46: =(((S46+R46)*AU46)/100) -> 1.334 | DE46: *1,1 | DF46: *1,1 | DG46: *1,1 | DI46: *1,1 | DJ46: *1,1 | DN46: 0 | DO46: 0 | DP46: 1 | DQ46: 1 | DU46: 1013 | DV46: 1 разъем | DW46: 1 разъем | DX46: 1 | EE46: 58162634 | EF46: 40 | EG46: Монтаж оборудования | EH46: 0 | EJ46: 2 | EK46: 72 | EL46: ТСН-2001.4-11. Приборы и средства автоматизации и вычислительной техники | EM46: ТСН-2001.4-11-1 | EO46: Поправка: Гл.12.Прил.8.п.8. 5_12.00.01.11.003 | EQ46: 0 | ER46: 2.52 | ES46: 0 | ET46: 0 | EU46: 0 | EV46: 2.52 | EW46: 0.22 | EX46: 0 | EY46: 0 | FQ46: 0 | FR46: 0 | FS46: 0 | FX46: 90 | FY46: 46 | GD46: 1 | GF46: 1774518925 | GG46: 2 | GH46: 1 | GI46: 2 | GJ46: 0 | GK46: 0 | GL46: =ROUND(IF(AND(BH46=3,BI46=3,FS46<>0),P46,0),2) -> 0 | GM46: =ROUND(O46+X46+Y46,2)+GX46 -> 6.84 | GN46: =IF(OR(BI46=0,BI46=1),GM46-GX46,0) -> 0 | GO46: =IF(BI46=2,GM46-GX46,0) -> 6.84 | GP46: =IF(BI46=4,GM46-GX46,0) -> 0 | GR46: 0 | GS46: 3 | GT46: 0 | GV46: =ROUND((GT46),6) -> 0 | GW46: 1 | GX46: =ROUND(HC46*I46,2) -> 0 | HA46: 0 | HB46: 0 | HC46: =GV46*GW46 -> 0 | HS46: 0 | IK46: 0
A47: 17 | B47: 1 | D47: =ROW(EtalonRes!A20) -> 20 | E47: 3 | F47: 4.11-14-1 | G47: Включение штепсельных разъемов в аппаратуру, количество контактов в разъеме до 14 | H47: 1 разъем | I47: 1 | J47: 0 | K47: 1 | O47: =ROUND(CP47,2) -> 159.47 | P47: =ROUND((ROUND((AC47*AW47*I47),2)*BC47),2) -> 0 | Q47: =(ROUND((ROUND((((ET47*1.1))*AV47*I47),2)*BB47),2)+ROUND((ROUND(((AE47-((EU47*1.1)))*AV47*I47),2)*BS47),2)) -> 0 | R47: =ROUND((ROUND((AE47*AV47*I47),2)*BS47),2) -> 0 | S47: =ROUND((ROUND((AF47*AV47*I47),2)*BA47),2) -> 159.47 | T47: =ROUND(CU47*I47,2) -> 0 | U47: =CV47*I47 -> 0.253374 | V47: =CW47*I47 -> 0 | W47: =ROUND(CX47*I47,2) -> 0 | X47: =ROUND(CY47,2) -> 143.52 | Y47: =ROUND(CZ47,2) -> 73.36 | AA47: 56505405 | AB47: =ROUND((AC47+AD47+AF47),6) -> 2.772 | AC47: =ROUND((ES47),6) -> 0 | AD47: =ROUND(((((ET47*1.1))-((EU47*1.1)))+AE47),6) -> 0 | AE47: =ROUND(((EU47*1.1)),6) -> 0 | AF47: =ROUND(((EV47*1.1)),6) -> 2.772 | AG47: =ROUND((AP47),6) -> 0 | AH47: =((EW47*1.1)) -> 0.242 | AI47: =((EX47*1.1)) -> 0 | AJ47: =(AS47) -> 0 | AK47: 2.52 | AL47: 0 | AM47: 0 | AN47: 0 | AO47: 2.52 | AP47: 0 | AQ47: 0.22 | AR47: 0 | AS47: 0 | AT47: 90 | AU47: 46 | AV47: 1.047 | AW47: 1 | AZ47: 1 | BA47: 54.99 | BB47: 1 | BC47: 1 | BH47: 0 | BI47: 2 | BJ47: ТСН-2001.4 Доп. 67, Сб. 11, т. 14, поз. 1 | BM47: 72 | BN47: 0 | BO47: 4.11-14-1 | BP47: 1 | BQ47: 40 | BR47: 0 | BS47: 54.99 | BT47: 1 | BU47: 1 | BV47: 1 | BW47: 1 | BX47: 1 | BZ47: 90 | CA47: 46 | CE47: 30 | CF47: 0 | CG47: 0 | CM47: 0 | CO47: 0 | CP47: =(P47+Q47+S47) -> 159.47 | CQ47: =ROUND((ROUND((AC47*AW47*1),2)*BC47),2) -> 0 | CR47: =(ROUND((ROUND((((ET47*1.1))*AV47*1),2)*BB47),2)+ROUND((ROUND(((AE47-((EU47*1.1)))*AV47*1),2)*BS47),2)) -> 0 | CS47: =ROUND((ROUND((AE47*AV47*1),2)*BS47),2) -> 0 | CT47: =ROUND((ROUND((AF47*AV47*1),2)*BA47),2) -> 159.47 | CU47: =AG47 -> 0 | CV47: =(AH47*AV47) -> 0.253374 | CW47: =AI47 -> 0 | CX47: =AJ47 -> 0 | CY47: =(((S47+R47)*AT47)/100) -> 143.523 | CZ47: =(((S47+R47)*AU47)/100) -> 73.3562 | DE47: *1,1 | DF47: *1,1 | DG47: *1,1 | DI47: *1,1 | DJ47: *1,1 | DN47: 0 | DO47: 0 | DP47: 1 | DQ47: 1 | DU47: 1013 | DV47: 1 разъем | DW47: 1 разъем | DX47: 1 | EE47: 58162634 | EF47: 40 | EG47: Монтаж оборудования | EH47: 0 | EJ47: 2 | EK47: 72 | EL47: ТСН-2001.4-11. Приборы и средства автоматизации и вычислительной техники | EM47: ТСН-2001.4-11-1 | EO47: Поправка: Гл.12.Прил.8.п.8. 5_12.00.01.11.003 | EQ47: 0 | ER47: 2.52 | ES47: 0 | ET47: 0 | EU47: 0 | EV47: 2.52 | EW47: 0.22 | EX47: 0 | EY47: 0 | FQ47: 0 | FR47: 0 | FS47: 0 | FX47: 90 | FY47: 46 | GD47: 1 | GF47: 1774518925 | GG47: 2 | GH47: 1 | GI47: 2 | GJ47: 0 | GK47: 0 | GL47: =ROUND(IF(AND(BH47=3,BI47=3,FS47<>0),P47,0),2) -> 0 | GM47: =ROUND(O47+X47+Y47,2)+GX47 -> 376.35 | GN47: =IF(OR(BI47=0,BI47=1),GM47-GX47,0) -> 0 | GO47: =IF(BI47=2,GM47-GX47,0) -> 376.35 | GP47: =IF(BI47=4,GM47-GX47,0) -> 0 | GR47: 0 | GS47: 3 | GT47: 0 | GV47: =ROUND((GT47),6) -> 0 | GW47: 1 | GX47: =ROUND(HC47*I47,2) -> 0 | HA47: 0 | HB47: 0 | HC47: =GV47*GW47 -> 0 | HS47: 0 | IK47: 0
A48: 18 | B48: 1 | E48: 3,1 | F48: КА 4 | G48: Шнур питания для вент. панели IEC 320 C14 | H48: шт. | I48: =I46*J48 -> 1 | J48: 1 | K48: 1 | O48: =ROUND(CP48,2) -> 55.92 | P48: =ROUND((ROUND((AC48*AW48*I48),2)*BC48),2) -> 55.92 | Q48: =(ROUND((ROUND(((ET48)*AV48*I48),2)*BB48),2)+ROUND((ROUND(((AE48-(EU48))*AV48*I48),2)*BS48),2)) -> 0 | R48: =ROUND((ROUND((AE48*AV48*I48),2)*BS48),2) -> 0 | S48: =ROUND((ROUND((AF48*AV48*I48),2)*BA48),2) -> 0 | T48: =ROUND(CU48*I48,2) -> 0 | U48: =CV48*I48 -> 0 | V48: =CW48*I48 -> 0 | W48: =ROUND(CX48*I48,2) -> 0 | X48: =ROUND(CY48,2) -> 0 | Y48: =ROUND(CZ48,2) -> 0 | AA48: 56505403 | AB48: =ROUND((AC48+AD48+AF48),6) -> 55.92 | AC48: =ROUND((ES48),6) -> 55.92 | AD48: =ROUND((((ET48)-(EU48))+AE48),6) -> 0 | AE48: =ROUND((EU48),6) -> 0 | AF48: =ROUND((EV48),6) -> 0 | AG48: =ROUND((AP48),6) -> 0 | AH48: =(EW48) -> 0 | AI48: =(EX48) -> 0 | AJ48: =(AS48) -> 0 | AK48: 55.92 | AL48: 55.92 | AM48: 0 | AN48: 0 | AO48: 0 | AP48: 0 | AQ48: 0 | AR48: 0 | AS48: 0 | AT48: 90 | AU48: 46 | AV48: 1 | AW48: 1 | AZ48: 1 | BA48: 1 | BB48: 1 | BC48: 1 | BH48: 3 | BI48: 2 | BM48: 72 | BN48: 0 | BP48: 0 | BQ48: 40 | BR48: 0 | BS48: 1 | BT48: 1 | BU48: 1 | BV48: 1 | BW48: 1 | BX48: 1 | BZ48: 90 | CA48: 46 | CE48: 30 | CF48: 0 | CG48: 0 | CM48: 0 | CO48: 0 | CP48: =(P48+Q48+S48) -> 55.92 | CQ48: =ROUND((ROUND((AC48*AW48*1),2)*BC48),2) -> 55.92 | CR48: =(ROUND((ROUND(((ET48)*AV48*1),2)*BB48),2)+ROUND((ROUND(((AE48-(EU48))*AV48*1),2)*BS48),2)) -> 0 | CS48: =ROUND((ROUND((AE48*AV48*1),2)*BS48),2) -> 0 | CT48: =ROUND((ROUND((AF48*AV48*1),2)*BA48),2) -> 0 | CU48: =AG48 -> 0 | CV48: =(AH48*AV48) -> 0 | CW48: =AI48 -> 0 | CX48: =AJ48 -> 0 | CY48: =(((S48+R48)*AT48)/100) -> 0 | CZ48: =(((S48+R48)*AU48)/100) -> 0 | DN48: 0 | DO48: 0 | DP48: 1 | DQ48: 1 | DU48: 1010 | DV48: шт. | DW48: шт. | DX48: 1 | EE48: 58162634 | EF48: 40 | EG48: Монтаж оборудования | EH48: 0 | EJ48: 2 | EK48: 72 | EL48: ТСН-2001.4-11. Приборы и средства автоматизации и вычислительной техники | EM48: ТСН-2001.4-11-1 | EQ48: 0 | ER48: 0 | ES48: 55.92 | ET48: 0 | EU48: 0 | EV48: 0 | EW48: 0 | EX48: 0 | FQ48: 0 | FR48: 0 | FS48: 0 | FX48: 90 | FY48: 46 | GA48: [650 / 1,2 / 9,88] + 2% Заг.скл | GD48: 1 | GF48: 1530715677 | GG48: 2 | GH48: 4 | GI48: -2 | GJ48: 0 | GK48: 0 | GL48: =ROUND(IF(AND(BH48=3,BI48=3,FS48<>0),P48,0),2) -> 0 | GM48: =ROUND(O48+X48+Y48,2)+GX48 -> 55.92 | GN48: =IF(OR(BI48=0,BI48=1),GM48-GX48,0) -> 0 | GO48: =IF(BI48=2,GM48-GX48,0) -> 55.92 | GP48: =IF(BI48=4,GM48-GX48,0) -> 0 | GR48: 0 | GS48: 2 | GT48: 0 | GV48: =ROUND((GT48),6) -> 0 | GW48: 1 | GX48: =ROUND(HC48*I48,2) -> 0 | HA48: 0 | HB48: 0 | HC48: =GV48*GW48 -> 0 | HE48: 0 | HF48: 2 | HS48: 0 | IK48: 0
A49: 18 | B49: 1 | E49: 3,1 | F49: КА 4 | G49: Шнур питания для вент. панели IEC 320 C14 | H49: шт. | I49: =I47*J49 -> 1 | J49: 1 | K49: 1 | O49: =ROUND(CP49,2) -> 552.49 | P49: =ROUND((ROUND((AC49*AW49*I49),2)*BC49),2) -> 552.49 | Q49: =(ROUND((ROUND(((ET49)*AV49*I49),2)*BB49),2)+ROUND((ROUND(((AE49-(EU49))*AV49*I49),2)*BS49),2)) -> 0 | R49: =ROUND((ROUND((AE49*AV49*I49),2)*BS49),2) -> 0 | S49: =ROUND((ROUND((AF49*AV49*I49),2)*BA49),2) -> 0 | T49: =ROUND(CU49*I49,2) -> 0 | U49: =CV49*I49 -> 0 | V49: =CW49*I49 -> 0 | W49: =ROUND(CX49*I49,2) -> 0 | X49: =ROUND(CY49,2) -> 0 | Y49: =ROUND(CZ49,2) -> 0 | AA49: 56505405 | AB49: =ROUND((AC49+AD49+AF49),6) -> 55.92 | AC49: =ROUND((ES49),6) -> 55.92 | AD49: =ROUND((((ET49)-(EU49))+AE49),6) -> 0 | AE49: =ROUND((EU49),6) -> 0 | AF49: =ROUND((EV49),6) -> 0 | AG49: =ROUND((AP49),6) -> 0 | AH49: =(EW49) -> 0 | AI49: =(EX49) -> 0 | AJ49: =(AS49) -> 0 | AK49: 55.92 | AL49: 55.92 | AM49: 0 | AN49: 0 | AO49: 0 | AP49: 0 | AQ49: 0 | AR49: 0 | AS49: 0 | AT49: 90 | AU49: 46 | AV49: 1 | AW49: 1 | AZ49: 1 | BA49: 1 | BB49: 1 | BC49: 9.88 | BH49: 3 | BI49: 2 | BM49: 72 | BN49: 0 | BP49: 0 | BQ49: 40 | BR49: 0 | BS49: 1 | BT49: 1 | BU49: 1 | BV49: 1 | BW49: 1 | BX49: 1 | BZ49: 90 | CA49: 46 | CE49: 30 | CF49: 0 | CG49: 0 | CM49: 0 | CO49: 0 | CP49: =(P49+Q49+S49) -> 552.49 | CQ49: =ROUND((ROUND((AC49*AW49*1),2)*BC49),2) -> 552.49 | CR49: =(ROUND((ROUND(((ET49)*AV49*1),2)*BB49),2)+ROUND((ROUND(((AE49-(EU49))*AV49*1),2)*BS49),2)) -> 0 | CS49: =ROUND((ROUND((AE49*AV49*1),2)*BS49),2) -> 0 | CT49: =ROUND((ROUND((AF49*AV49*1),2)*BA49),2) -> 0 | CU49: =AG49 -> 0 | CV49: =(AH49*AV49) -> 0 | CW49: =AI49 -> 0 | CX49: =AJ49 -> 0 | CY49: =(((S49+R49)*AT49)/100) -> 0 | CZ49: =(((S49+R49)*AU49)/100) -> 0 | DN49: 0 | DO49: 0 | DP49: 1 | DQ49: 1 | DU49: 1010 | DV49: шт. | DW49: шт. | DX49: 1 | EE49: 58162634 | EF49: 40 | EG49: Монтаж оборудования | EH49: 0 | EJ49: 2 | EK49: 72 | EL49: ТСН-2001.4-11. Приборы и средства автоматизации и вычислительной техники | EM49: ТСН-2001.4-11-1 | EQ49: 0 | ER49: 55.92 | ES49: 55.92 | ET49: 0 | EU49: 0 | EV49: 0 | EW49: 0 | EX49: 0 | EZ49: 5 | FC49: 1 | FD49: 18 | FF49: 650 | FQ49: 0 | FR49: 0 | FS49: 0 | FX49: 90 | FY49: 46 | GA49: [650 / 1,2 / 9,88] + 2% Заг.скл | GD49: 1 | GF49: 1530715677 | GG49: 2 | GH49: 3 | GI49: 5 | GJ49: 0 | GK49: 0 | GL49: =ROUND(IF(AND(BH49=3,BI49=3,FS49<>0),P49,0),2) -> 0 | GM49: =ROUND(O49+X49+Y49,2)+GX49 -> 552.49 | GN49: =IF(OR(BI49=0,BI49=1),GM49-GX49,0) -> 0 | GO49: =IF(BI49=2,GM49-GX49,0) -> 552.49 | GP49: =IF(BI49=4,GM49-GX49,0) -> 0 | GR49: 1 | GS49: 1 | GT49: 0 | GV49: =ROUND((GT49),6) -> 0 | GW49: 1 | GX49: =ROUND(HC49*I49,2) -> 0 | HA49: 0 | HB49: 0 | HC49: =GV49*GW49 -> 0 | HE49: 0 | HF49: 2 | HS49: 0 | IK49: 0
A51: 51 | B51: =B24 -> 1 | C51: =A24 -> 4 | D51: =ROW(A24) -> 24 | F51: =IF(F24<>"",F24,"") | G51: =IF(G24<>"",G24,"") -> Телекоммуникационный шкаф 47U 19" ШТ1-01 | H51: 0 | O51: =ROUND(AB51,2) -> 25651.89 | P51: =ROUND(AC51,2) -> 25442.61 | Q51: =ROUND(AD51,2) -> 47.12 | R51: =ROUND(AE51,2) -> 5.16 | S51: =ROUND(AF51,2) -> 162.16 | T51: =ROUND(AG51,2) -> 0 | U51: =AH51 -> 14.442318 | V51: =AI51 -> 0 | W51: =ROUND(AJ51,2) -> 0 | X51: =ROUND(AK51,2) -> 150.59 | Y51: =ROUND(AL51,2) -> 76.96 | AB51: =ROUND(SUMIF(AA28:AA49,"=56505403",O28:O49),2) -> 25651.89 | AC51: =ROUND(SUMIF(AA28:AA49,"=56505403",P28:P49),2) -> 25442.61 | AD51: =ROUND(SUMIF(AA28:AA49,"=56505403",Q28:Q49),2) -> 47.12 | AE51: =ROUND(SUMIF(AA28:AA49,"=56505403",R28:R49),2) -> 5.16 | AF51: =ROUND(SUMIF(AA28:AA49,"=56505403",S28:S49),2) -> 162.16 | AG51: =ROUND(SUMIF(AA28:AA49,"=56505403",T28:T49),2) -> 0 | AH51: =SUMIF(AA28:AA49,"=56505403",U28:U49) -> 14.442318 | AI51: =SUMIF(AA28:AA49,"=56505403",V28:V49) -> 0 | AJ51: =ROUND(SUMIF(AA28:AA49,"=56505403",W28:W49),2) -> 0 | AK51: =ROUND(SUMIF(AA28:AA49,"=56505403",X28:X49),2) -> 150.59 | AL51: =ROUND(SUMIF(AA28:AA49,"=56505403",Y28:Y49),2) -> 76.96 | AO51: =ROUND(BX51,2) -> 0 | AP51: =ROUND(BY51,2) -> 3213.03 | AQ51: =ROUND(BZ51,2) -> 0 | AR51: =ROUND(CA51,2) -> 25879.44 | AS51: =ROUND(CB51,2) -> 0 | AT51: =ROUND(CC51,2) -> 22666.41 | AU51: =ROUND(CD51,2) -> 0 | AV51: =ROUND(CE51,2) -> 25442.61 | ... BD51: =ROUND(CM51,2) -> 0 | BX51: =ROUND(SUMIF(AA28:AA49,"=56505403",FQ28:FQ49),2) -> 0 | BY51: =ROUND(SUMIF(AA28:AA49,"=56505403",FR28:FR49),2) -> 3213.03 | BZ51: =ROUND(SUMIF(AA28:AA49,"=56505403",GL28:GL49),2) -> 0 | CA51: =ROUND(SUMIF(AA28:AA49,"=56505403",GM28:GM49),2) -> 25879.44 | CB51: =ROUND(SUMIF(AA28:AA49,"=56505403",GN28:GN49),2) -> 0 | CC51: =ROUND(SUMIF(AA28:AA49,"=56505403",GO28:GO49),2) -> 22666.41 | CD51: =ROUND(SUMIF(AA28:AA49,"=56505403",GP28:GP49),2) -> 0 | CE51: =AC51-BX51 -> 25442.61 | CF51: =AC51-BY51 -> 22229.58 | CG51: =BX51-BZ51 -> 0 | CH51: =AC51-BX51-BY51+BZ51 -> 22229.58 | CI51: =BY51-BZ51 -> 3213.03 | CJ51: =ROUND(SUMIF(AA28:AA49,"=56505403",GX28:GX49),2) -> 0 | CK51: =ROUND(SUMIF(AA28:AA49,"=56505403",GY28:GY49),2) -> 0 | CL51: =ROUND(SUMIF(AA28:AA49,"=56505403",GZ28:GZ49),2) -> 0 | CM51: =ROUND(SUMIF(AA28:AA49,"=56505403",HD28:HD49),2) -> 0 | DG51: =ROUND(DT51,2) -> 253873.75 | DH51: =ROUND(DU51,2) -> 244233.88 | DI51: =ROUND(DV51,2) -> 722.7 | DJ51: =ROUND(DW51,2) -> 283.75 | DK51: =ROUND(DX51,2) -> 8917.17 | DL51: =ROUND(DY51,2) -> 0 | DM51: =DZ51 -> 14.442318 | DN51: =EA51 -> 0 | DO51: =ROUND(EB51,2) -> 0 | DP51: =ROUND(EC51,2) -> 8280.82 | DQ51: =ROUND(ED51,2) -> 4232.42 | DT51: =ROUND(SUMIF(AA28:AA49,"=56505405",O28:O49),2) -> 253873.75 | DU51: =ROUND(SUMIF(AA28:AA49,"=56505405",P28:P49),2) -> 244233.88 | DV51: =ROUND(SUMIF(AA28:AA49,"=56505405",Q28:Q49),2) -> 722.7 | DW51: =ROUND(SUMIF(AA28:AA49,"=56505405",R28:R49),2) -> 283.75 | DX51: =ROUND(SUMIF(AA28:AA49,"=56505405",S28:S49),2) -> 8917.17 | DY51: =ROUND(SUMIF(AA28:AA49,"=56505405",T28:T49),2) -> 0 | DZ51: =SUMIF(AA28:AA49,"=56505405",U28:U49) -> 14.442318 | EA51: =SUMIF(AA28:AA49,"=56505405",V28:V49) -> 0 | EB51: =ROUND(SUMIF(AA28:AA49,"=56505405",W28:W49),2) -> 0 | EC51: =ROUND(SUMIF(AA28:AA49,"=56505405",X28:X49),2) -> 8280.82 | ED51: =ROUND(SUMIF(AA28:AA49,"=56505405",Y28:Y49),2) -> 4232.42 | EG51: =ROUND(FP51,2) -> 0 | EH51: =ROUND(FQ51,2) -> 24611.81 | EI51: =ROUND(FR51,2) -> 0 | EJ51: =ROUND(FS51,2) -> 266386.99 | EK51: =ROUND(FT51,2) -> 0 | EL51: =ROUND(FU51,2) -> 241775.18 | EM51: =ROUND(FV51,2) -> 0 | EN51: =ROUND(FW51,2) -> 244233.88 | ... EV51: =ROUND(GE51,2) -> 0 | FP51: =ROUND(SUMIF(AA28:AA49,"=56505405",FQ28:FQ49),2) -> 0 | FQ51: =ROUND(SUMIF(AA28:AA49,"=56505405",FR28:FR49),2) -> 24611.81 | FR51: =ROUND(SUMIF(AA28:AA49,"=56505405",GL28:GL49),2) -> 0 | FS51: =ROUND(SUMIF(AA28:AA49,"=56505405",GM28:GM49),2) -> 266386.99 | FT51: =ROUND(SUMIF(AA28:AA49,"=56505405",GN28:GN49),2) -> 0 | FU51: =ROUND(SUMIF(AA28:AA49,"=56505405",GO28:GO49),2) -> 241775.18 | FV51: =ROUND(SUMIF(AA28:AA49,"=56505405",GP28:GP49),2) -> 0 | FW51: =DU51-FP51 -> 244233.88 | FX51: =DU51-FQ51 -> 219622.07 | FY51: =FP51-FR51 -> 0 | FZ51: =DU51-FP51-FQ51+FR51 -> 219622.07 | GA51: =FQ51-FR51 -> 24611.81 | GB51: =ROUND(SUMIF(AA28:AA49,"=56505405",GX28:GX49),2) -> 0 | GC51: =ROUND(SUMIF(AA28:AA49,"=56505405",GY28:GY49),2) -> 0 | GD51: =ROUND(SUMIF(AA28:AA49,"=56505405",GZ28:GZ49),2) -> 0 | GE51: =ROUND(SUMIF(AA28:AA49,"=56505405",HD28:HD49),2) -> 0 | GX51: 0
A53: 50 | B53: 0 | C53: 0 | D53: 1 | E53: 201 | F53: =ROUND(Source!O51,O53) -> 25651.89 | G53: ПЗ | H53: Прямые затраты | K53: 201 | L53: 1 | M53: 3 | O53: 2 | P53: =ROUND(Source!DG51,O53) -> 253873.75 | W53: 25651.89 | X53: 1 | Y53: 25651.89 | Z53: 253873.75 | AA53: 1 | AB53: 253873.75
A54: 50 | B54: 0 | C54: 0 | D54: 1 | E54: 202 | F54: =ROUND(Source!P51,O54) -> 25442.61 | G54: СтМатОб | H54: Стоимость материальных ресурсов (всего) | K54: 202 | L54: 2 | M54: 3 | O54: 2 | P54: =ROUND(Source!DH51,O54) -> 244233.88 | W54: 25442.61 | X54: 1 | Y54: 25442.61 | Z54: 244233.88 | AA54: 1 | AB54: 244233.88
A55: 50 | B55: 0 | C55: 0 | D55: 1 | E55: 222 | F55: =ROUND(Source!AO51,O55) -> 0 | G55: СтМатОбЗак | H55: Стоимость материалов и оборудования заказчика | K55: 222 | L55: 3 | M55: 3 | O55: 2 | P55: =ROUND(Source!EG51,O55) -> 0 | W55: 0 | X55: 1 | Y55: 0 | Z55: 0 | AA55: 1 | AB55: 0
A56: 50 | B56: 0 | C56: 0 | D56: 1 | E56: 225 | F56: =ROUND(Source!AV51,O56) -> 25442.61 | G56: СтМатОбПод | H56: Стоимость материалов и оборудования подрядчика | K56: 225 | L56: 4 | M56: 3 | O56: 2 | P56: =ROUND(Source!EN51,O56) -> 244233.88 | W56: 25442.61 | X56: 1 | Y56: 25442.61 | Z56: 244233.88 | AA56: 1 | AB56: 244233.88
A57: 50 | B57: 0 | C57: 0 | D57: 1 | E57: 226 | F57: =ROUND(Source!AW51,O57) -> 22229.58 | G57: СтМат | H57: Стоимость материалов (всего) | K57: 226 | L57: 5 | M57: 3 | O57: 2 | P57: =ROUND(Source!EO51,O57) -> 219622.07 | W57: 22229.58 | X57: 1 | Y57: 22229.58 | Z57: 219622.07 | AA57: 1 | AB57: 219622.07
A58: 50 | B58: 0 | C58: 0 | D58: 1 | E58: 227 | F58: =ROUND(Source!AX51,O58) -> 0 | G58: СтМатЗак | H58: Стоимость материалов заказчика | K58: 227 | L58: 6 | M58: 3 | O58: 2 | P58: =ROUND(Source!EP51,O58) -> 0 | W58: 0 | X58: 1 | Y58: 0 | Z58: 0 | AA58: 1 | AB58: 0
A59: 50 | B59: 0 | C59: 0 | D59: 1 | E59: 228 | F59: =ROUND(Source!AY51,O59) -> 22229.58 | G59: СтМатПод | H59: Стоимость материалов подрядчика | K59: 228 | L59: 7 | M59: 3 | O59: 2 | P59: =ROUND(Source!EQ51,O59) -> 219622.07 | W59: 22229.58 | X59: 1 | Y59: 22229.58 | Z59: 219622.07 | AA59: 1 | AB59: 219622.07
A60: 50 | B60: 0 | C60: 0 | D60: 1 | E60: 216 | F60: =ROUND(Source!AP51,O60) -> 3213.03 | G60: Оборуд | H60: Стоимость оборудования (всего) | K60: 216 | L60: 8 | M60: 3 | O60: 2 | P60: =ROUND(Source!EH51,O60) -> 24611.81 | W60: 3213.03 | X60: 1 | Y60: 3213.03 | Z60: 24611.81 | AA60: 1 | AB60: 24611.81
A61: 50 | B61: 0 | C61: 0 | D61: 1 | E61: 223 | F61: =ROUND(Source!AQ51,O61) -> 0 | G61: ОборудЗак | H61: Стоимость оборудования заказчика | K61: 223 | L61: 9 | M61: 3 | O61: 2 | P61: =ROUND(Source!EI51,O61) -> 0 | W61: 0 | X61: 1 | Y61: 0 | Z61: 0 | AA61: 1 | AB61: 0
A62: 50 | B62: 0 | C62: 0 | D62: 1 | E62: 229 | F62: =ROUND(Source!AZ51,O62) -> 3213.03 | G62: ОборудПод | H62: Стоимость оборудования подрядчика | K62: 229 | L62: 10 | M62: 3 | O62: 2 | P62: =ROUND(Source!ER51,O62) -> 24611.81 | W62: 3213.03 | X62: 1 | Y62: 3213.03 | Z62: 24611.81 | AA62: 1 | AB62: 24611.81
A63: 50 | B63: 0 | C63: 0 | D63: 1 | E63: 203 | F63: =ROUND(Source!Q51,O63) -> 47.12 | G63: ЭММ | H63: Эксплуатация машин | K63: 203 | L63: 11 | M63: 3 | O63: 2 | P63: =ROUND(Source!DI51,O63) -> 722.7 | W63: 47.12 | X63: 1 | Y63: 47.12 | Z63: 722.7 | AA63: 1 | AB63: 722.7
A64: 50 | B64: 0 | C64: 0 | D64: 1 | E64: 231 | F64: =ROUND(Source!BB51,O64) -> 0 | G64: ЭММсНРиСП | H64: Эксплуатация машин по ТСН-2001.16 | K64: 231 | L64: 12 | M64: 3 | O64: 2 | P64: =ROUND(Source!ET51,O64) -> 0 | W64: 0 | X64: 1 | Y64: 0 | Z64: 0 | AA64: 1 | AB64: 0
A65: 50 | B65: 0 | C65: 0 | D65: 1 | E65: 204 | F65: =ROUND(Source!R51,O65) -> 5.16 | G65: ЗПМ | H65: ЗП машинистов | K65: 204 | L65: 13 | M65: 3 | O65: 2 | P65: =ROUND(Source!DJ51,O65) -> 283.75 | W65: 5.16 | X65: 1 | Y65: 5.16 | Z65: 283.75 | AA65: 1 | AB65: 283.75
A66: 50 | B66: 0 | C66: 0 | D66: 1 | E66: 205 | F66: =ROUND(Source!S51,O66) -> 162.16 | G66: ОЗП | H66: Основная ЗП рабочих | K66: 205 | L66: 14 | M66: 3 | O66: 2 | P66: =ROUND(Source!DK51,O66) -> 8917.17 | W66: 162.16 | X66: 1 | Y66: 162.16 | Z66: 8917.17 | AA66: 1 | AB66: 8917.17
A67: 50 | B67: 0 | C67: 0 | D67: 1 | E67: 232 | F67: =ROUND(Source!BC51,O67) -> 0 | G67: ОЗПсНРиСП | H67: Основная ЗП рабочих по ТСН-2001.16 | K67: 232 | L67: 15 | M67: 3 | O67: 2 | P67: =ROUND(Source!EU51,O67) -> 0 | W67: 0 | X67: 1 | Y67: 0 | Z67: 0 | AA67: 1 | AB67: 0
A68: 50 | B68: 0 | C68: 0 | D68: 1 | E68: 214 | F68: =ROUND(Source!AS51,O68) -> 0 | G68: Строит | H68: Строительные работы с НР и СП | K68: 214 | L68: 16 | M68: 3 | O68: 2 | P68: =ROUND(Source!EK51,O68) -> 0 | W68: 0 | X68: 1 | Y68: 0 | Z68: 0 | AA68: 1 | AB68: 0
A69: 50 | B69: 0 | C69: 0 | D69: 1 | E69: 215 | F69: =ROUND(Source!AT51,O69) -> 22666.41 | G69: Монтаж | H69: Монтажные работы с НР и СП | K69: 215 | L69: 17 | M69: 3 | O69: 2 | P69: =ROUND(Source!EL51,O69) -> 241775.18 | W69: 22666.41 | X69: 1 | Y69: 22666.41 | Z69: 241775.18 | AA69: 1 | AB69: 241775.18
A70: 50 | B70: 0 | C70: 0 | D70: 1 | E70: 217 | F70: =ROUND(Source!AU51,O70) -> 0 | G70: Прочие | H70: Прочие работы с НР и СП | K70: 217 | L70: 18 | M70: 3 | O70: 2 | P70: =ROUND(Source!EM51,O70) -> 0 | W70: 0 | X70: 1 | Y70: 0 | Z70: 0 | AA70: 1 | AB70: 0
A71: 50 | B71: 0 | C71: 0 | D71: 1 | E71: 230 | F71: =ROUND(Source!BA51,O71) -> 0 | G71: ПрочиеЗатр | H71: Прочие затраты по ТСН-2001.16 | K71: 230 | L71: 19 | M71: 3 | O71: 2 | P71: =ROUND(Source!ES51,O71) -> 0 | W71: 0 | X71: 1 | Y71: 0 | Z71: 0 | AA71: 1 | AB71: 0
A72: 50 | B72: 0 | C72: 0 | D72: 1 | E72: 206 | F72: =ROUND(Source!T51,O72) -> 0 | G72: ВозврМат | H72: Возврат материалов | K72: 206 | L72: 20 | M72: 3 | O72: 2 | P72: =ROUND(Source!DL51,O72) -> 0 | W72: 0 | X72: 1 | Y72: 0 | Z72: 0 | AA72: 1 | AB72: 0
A73: 50 | B73: 0 | C73: 0 | D73: 1 | E73: 207 | F73: =Source!U51 -> 14.442318 | G73: ТрудСтр | H73: Трудозатраты строителей | K73: 207 | L73: 21 | M73: 3 | O73: -1 | P73: =Source!DM51 -> 14.442318 | W73: 14.442318 | X73: 1 | Y73: 14.442318 | Z73: 14.442318 | AA73: 1 | AB73: 14.442318
A74: 50 | B74: 0 | C74: 0 | D74: 1 | E74: 208 | F74: =Source!V51 -> 0 | G74: ТрудМаш | H74: Трудозатраты машинистов | K74: 208 | L74: 22 | M74: 3 | O74: -1 | P74: =Source!DN51 -> 0 | W74: 0 | X74: 1 | Y74: 0 | Z74: 0 | AA74: 1 | AB74: 0
A75: 50 | B75: 0 | C75: 0 | D75: 1 | E75: 209 | F75: =ROUND(Source!W51,O75) -> 0 | G75: ТранспМат | H75: Транспорт материалов | K75: 209 | L75: 23 | M75: 3 | O75: 2 | P75: =ROUND(Source!DO51,O75) -> 0 | W75: 0 | X75: 1 | Y75: 0 | Z75: 0 | AA75: 1 | AB75: 0
A76: 50 | B76: 0 | C76: 0 | D76: 1 | E76: 233 | F76: =ROUND(Source!BD51,O76) -> 0 | G76: Перевозка | H76: Перевозка грузов | K76: 233 | L76: 24 | M76: 3 | O76: 2 | P76: =ROUND(Source!EV51,O76) -> 0 | W76: 0 | X76: 1 | Y76: 0 | Z76: 0 | AA76: 1 | AB76: 0
A77: 50 | B77: 0 | C77: 0 | D77: 1 | E77: 210 | F77: =ROUND(Source!X51,O77) -> 150.59 | G77: НР | H77: Накладные расходы | K77: 210 | L77: 25 | M77: 3 | O77: 2 | P77: =ROUND(Source!DP51,O77) -> 8280.82 | W77: 150.59 | X77: 1 | Y77: 150.59 | Z77: 8280.82 | AA77: 1 | AB77: 8280.82
A78: 50 | B78: 0 | C78: 0 | D78: 1 | E78: 211 | F78: =ROUND(Source!Y51,O78) -> 76.96 | G78: СмПриб | H78: Сметная прибыль | K78: 211 | L78: 26 | M78: 3 | O78: 2 | P78: =ROUND(Source!DQ51,O78) -> 4232.42 | W78: 76.96 | X78: 1 | Y78: 76.96 | Z78: 4232.42 | AA78: 1 | AB78: 4232.42
A79: 50 | B79: 0 | C79: 0 | D79: 1 | E79: 224 | F79: =ROUND(Source!AR51,O79) -> 25879.44 | G79: Всего | H79: Всего с НР и СП | K79: 224 | L79: 27 | M79: 3 | O79: 2 | P79: =ROUND(Source!EJ51,O79) -> 266386.99 | W79: 25879.44 | X79: 1 | Y79: 25879.44 | Z79: 266386.99 | AA79: 1 | AB79: 266386.99
A81: 4 | B81: 1 | D81: =ROW(A112) -> 112 | G81: Телекоммуникационный шкаф 42U 19" ШТ1-2,1-3,1-4; ШТ2-5,2-6; ШТ3-7,3-8 | I81: 0 | K81: -1 | S81: 0 | T81: 0 | V81: 0 | BX81: 0 | CJ81: 0
A83: 52 | B83: =B112 -> 1 | C83: =C112 -> 4 | D83: =D112 -> 81 | E83: =E112 -> 0 | F83: =F112 | G83: =G112 -> Телекоммуникационный шкаф 42U 19" ШТ1-2,1-3,1-4; ШТ2-5,2-6; ШТ3-7,3-8 | O83: =O112 -> 163143 | P83: =P112 -> 161492.26 | Q83: =Q112 -> 329.89 | R83: =R112 -> 36.12 | S83: =S112 -> 1320.85 | T83: =T112 -> 0 | U83: =U112 -> 117.31216 | V83: =V112 -> 0 | ... GX83: =GX112 -> 0
A85: 17 | B85: 1 | D85: =ROW(EtalonRes!A26) -> 26 | E85: 4 | F85: 4.10-32-1 | G85: Монтаж стойки, полустойки, каркаса стойки или шкафа массой до 100 кг | H85: 1 ШТ. | I85: 7 | J85: 0 | K85: 7 | O85: =ROUND(CP85,2) -> 1080.32 | P85: =ROUND((ROUND((AC85*AW85*I85),2)*BC85),2) -> 27.44 | Q85: =(ROUND((ROUND((((ET85*1.1))*AV85*I85),2)*BB85),2)+ROUND((ROUND(((AE85-((EU85*1.1)))*AV85*I85),2)*BS85),2)) -> 313.77 | R85: =ROUND((ROUND((AE85*AV85*I85),2)*BS85),2) -> 33.54 | S85: =ROUND((ROUND((AF85*AV85*I85),2)*BA85),2) -> 739.11 | T85: =ROUND(CU85*I85,2) -> 0 | U85: =CV85*I85 -> 66.10758 | V85: =CW85*I85 -> 0 | W85: =ROUND(CX85*I85,2) -> 0 | X85: =ROUND(CY85,2) -> 695.39 | Y85: =ROUND(CZ85,2) -> 355.42 | AA85: 56505403 | AB85: =ROUND((AC85+AD85+AF85),6) -> 147.58 | AC85: =ROUND((ES85),6) -> 3.92 | AD85: =ROUND(((((ET85*1.1))-((EU85*1.1)))+AE85),6) -> 42.812 | AE85: =ROUND(((EU85*1.1)),6) -> 4.576 | AF85: =ROUND(((EV85*1.1)),6) -> 100.848 | AG85: =ROUND((AP85),6) -> 0 | AH85: =((EW85*1.1)) -> 9.02 | AI85: =((EX85*1.1)) -> 0 | AJ85: =(AS85) -> 0 | AK85: 134.52 | AL85: 3.92 | AM85: 38.92 | AN85: 4.16 | AO85: 91.68 | AP85: 0 | AQ85: 8.2 | AR85: 0 | AS85: 0 | AT85: 90 | AU85: 46 | AV85: 1.047 | AW85: 1 | AZ85: 1 | BA85: 1 | BB85: 1 | BC85: 1 | BH85: 0 | BI85: 2 | BJ85: ТСН-2001.4 Доп. 80, Сб. 10, т. 32, поз. 1 | BM85: 68 | BN85: 0 | BO85: 4.10-32-1 | BP85: 1 | BQ85: 40 | BR85: 0 | BS85: 1 | BT85: 1 | BU85: 1 | BV85: 1 | BW85: 1 | BX85: 1 | BZ85: 90 | CA85: 46 | CE85: 30 | CF85: 0 | CG85: 0 | CM85: 0 | CO85: 0 | CP85: =(P85+Q85+S85) -> 1080.32 | CQ85: =ROUND((ROUND((AC85*AW85*1),2)*BC85),2) -> 3.92 | CR85: =(ROUND((ROUND((((ET85*1.1))*AV85*1),2)*BB85),2)+ROUND((ROUND(((AE85-((EU85*1.1)))*AV85*1),2)*BS85),2)) -> 44.82 | CS85: =ROUND((ROUND((AE85*AV85*1),2)*BS85),2) -> 4.79 | CT85: =ROUND((ROUND((AF85*AV85*1),2)*BA85),2) -> 105.59 | CU85: =AG85 -> 0 | CV85: =(AH85*AV85) -> 9.44394 | CW85: =AI85 -> 0 | CX85: =AJ85 -> 0 | CY85: =(((S85+R85)*AT85)/100) -> 695.385 | CZ85: =(((S85+R85)*AU85)/100) -> 355.419 | DE85: *1,1 | DF85: *1,1 | DG85: *1,1 | DI85: *1,1 | DJ85: *1,1 | DN85: 0 | DO85: 0 | DP85: 1 | DQ85: 1 | DU85: 1013 | DV85: 1 ШТ. | DW85: 1 ШТ. | DX85: 1 | EE85: 58162630 | EF85: 40 | EG85: Монтаж оборудования | EH85: 0 | EJ85: 2 | EK85: 68 | EL85: ТСН-2001.4-10. Прокладка и монтаж сетей связи | EM85: ТСН-2001.4-10-1 | EO85: Поправка: Гл.12.Прил.8.п.8. 5_12.00.01.11.003 | EQ85: 0 | ER85: 134.52 | ES85: 3.92 | ET85: 38.92 | EU85: 4.16 | EV85: 91.68 | EW85: 8.2 | EX85: 0 | EY85: 0 | FQ85: 0 | FR85: 0 | FS85: 0 | FX85: 90 | FY85: 46 | GD85: 1 | GF85: -1576476159 | GG85: 2 | GH85: 1 | GI85: 2 | GJ85: 0 | GK85: 0 | GL85: =ROUND(IF(AND(BH85=3,BI85=3,FS85<>0),P85,0),2) -> 0 | GM85: =ROUND(O85+X85+Y85,2)+GX85 -> 2131.13 | GN85: =IF(OR(BI85=0,BI85=1),GM85-GX85,0) -> 0 | GO85: =IF(BI85=2,GM85-GX85,0) -> 2131.13 | GP85: =IF(BI85=4,GM85-GX85,0) -> 0 | GR85: 0 | GS85: 3 | GT85: 0 | GV85: =ROUND((GT85),6) -> 0 | GW85: 1 | GX85: =ROUND(HC85*I85,2) -> 0 | HA85: 0 | HB85: 0 | HC85: =GV85*GW85 -> 0 | HS85: 0 | IK85: 0
A86: 17 | B86: 1 | D86: =ROW(EtalonRes!A32) -> 32 | E86: 4 | F86: 4.10-32-1 | G86: Монтаж стойки, полустойки, каркаса стойки или шкафа массой до 100 кг | H86: 1 ШТ. | I86: 7 | J86: 0 | K86: 7 | O86: =ROUND(CP86,2) -> 45668.95 | P86: =ROUND((ROUND((AC86*AW86*I86),2)*BC86),2) -> 227.75 | Q86: =(ROUND((ROUND((((ET86*1.1))*AV86*I86),2)*BB86),2)+ROUND((ROUND(((AE86-((EU86*1.1)))*AV86*I86),2)*BS86),2)) -> 4797.54 | R86: =ROUND((ROUND((AE86*AV86*I86),2)*BS86),2) -> 1844.36 | S86: =ROUND((ROUND((AF86*AV86*I86),2)*BA86),2) -> 40643.66 | T86: =ROUND(CU86*I86,2) -> 0 | U86: =CV86*I86 -> 66.10758 | V86: =CW86*I86 -> 0 | W86: =ROUND(CX86*I86,2) -> 0 | X86: =ROUND(CY86,2) -> 38239.22 | Y86: =ROUND(CZ86,2) -> 19544.49 | AA86: 56505405 | AB86: =ROUND((AC86+AD86+AF86),6) -> 147.58 | AC86: =ROUND((ES86),6) -> 3.92 | AD86: =ROUND(((((ET86*1.1))-((EU86*1.1)))+AE86),6) -> 42.812 | AE86: =ROUND(((EU86*1.1)),6) -> 4.576 | AF86: =ROUND(((EV86*1.1)),6) -> 100.848 | AG86: =ROUND((AP86),6) -> 0 | AH86: =((EW86*1.1)) -> 9.02 | AI86: =((EX86*1.1)) -> 0 | AJ86: =(AS86) -> 0 | AK86: 134.52 | AL86: 3.92 | AM86: 38.92 | AN86: 4.16 | AO86: 91.68 | AP86: 0 | AQ86: 8.2 | AR86: 0 | AS86: 0 | AT86: 90 | AU86: 46 | AV86: 1.047 | AW86: 1 | AZ86: 1 | BA86: 54.99 | BB86: 15.29 | BC86: 8.3 | BH86: 0 | BI86: 2 | BJ86: ТСН-2001.4 Доп. 80, Сб. 10, т. 32, поз. 1 | BM86: 68 | BN86: 0 | BO86: 4.10-32-1 | BP86: 1 | BQ86: 40 | BR86: 0 | BS86: 54.99 | BT86: 1 | BU86: 1 | BV86: 1 | BW86: 1 | BX86: 1 | BZ86: 90 | CA86: 46 | CE86: 30 | CF86: 0 | CG86: 0 | CM86: 0 | CO86: 0 | CP86: =(P86+Q86+S86) -> 45668.95 | CQ86: =ROUND((ROUND((AC86*AW86*1),2)*BC86),2) -> 32.54 | CR86: =(ROUND((ROUND((((ET86*1.1))*AV86*1),2)*BB86),2)+ROUND((ROUND(((AE86-((EU86*1.1)))*AV86*1),2)*BS86),2)) -> 685.3 | CS86: =ROUND((ROUND((AE86*AV86*1),2)*BS86),2) -> 263.4 | CT86: =ROUND((ROUND((AF86*AV86*1),2)*BA86),2) -> 5806.39 | CU86: =AG86 -> 0 | CV86: =(AH86*AV86) -> 9.44394 | CW86: =AI86 -> 0 | CX86: =AJ86 -> 0 | CY86: =(((S86+R86)*AT86)/100) -> 38239.218 | CZ86: =(((S86+R86)*AU86)/100) -> 19544.489 | DE86: *1,1 | DF86: *1,1 | DG86: *1,1 | DI86: *1,1 | DJ86: *1,1 | DN86: 0 | DO86: 0 | DP86: 1 | DQ86: 1 | DU86: 1013 | DV86: 1 ШТ. | DW86: 1 ШТ. | DX86: 1 | EE86: 58162630 | EF86: 40 | EG86: Монтаж оборудования | EH86: 0 | EJ86: 2 | EK86: 68 | EL86: ТСН-2001.4-10. Прокладка и монтаж сетей связи | EM86: ТСН-2001.4-10-1 | EO86: Поправка: Гл.12.Прил.8.п.8. 5_12.00.01.11.003 | EQ86: 0 | ER86: 134.52 | ES86: 3.92 | ET86: 38.92 | EU86: 4.16 | EV86: 91.68 | EW86: 8.2 | EX86: 0 | EY86: 0 | FQ86: 0 | FR86: 0 | FS86: 0 | FX86: 90 | FY86: 46 | GD86: 1 | GF86: -1576476159 | GG86: 2 | GH86: 1 | GI86: 2 | GJ86: 0 | GK86: 0 | GL86: =ROUND(IF(AND(BH86=3,BI86=3,FS86<>0),P86,0),2) -> 0 | GM86: =ROUND(O86+X86+Y86,2)+GX86 -> 103452.66 | GN86: =IF(OR(BI86=0,BI86=1),GM86-GX86,0) -> 0 | GO86: =IF(BI86=2,GM86-GX86,0) -> 103452.66 | GP86: =IF(BI86=4,GM86-GX86,0) -> 0 | GR86: 0 | GS86: 3 | GT86: 0 | GV86: =ROUND((GT86),6) -> 0 | GW86: 1 | GX86: =ROUND(HC86*I86,2) -> 0 | HA86: 0 | HB86: 0 | HC86: =GV86*GW86 -> 0 | HS86: 0 | IK86: 0
A87: 18 | B87: 1 | E87: 4,1 | F87: КА 9 | G87: Шкаф 19" серии Racknet S3000, 42U 60F-42-88-31BL | H87: шт. | I87: =I85*J87 -> 7 | J87: 1 | K87: 1 | O87: =ROUND(CP87,2) -> 99243.9 | P87: =ROUND((ROUND((AC87*AW87*I87),2)*BC87),2) -> 99243.9 | Q87: =(ROUND((ROUND(((ET87)*AV87*I87),2)*BB87),2)+ROUND((ROUND(((AE87-(EU87))*AV87*I87),2)*BS87),2)) -> 0 | R87: =ROUND((ROUND((AE87*AV87*I87),2)*BS87),2) -> 0 | S87: =ROUND((ROUND((AF87*AV87*I87),2)*BA87),2) -> 0 | T87: =ROUND(CU87*I87,2) -> 0 | U87: =CV87*I87 -> 0 | V87: =CW87*I87 -> 0 | W87: =ROUND(CX87*I87,2) -> 0 | X87: =ROUND(CY87,2) -> 0 | Y87: =ROUND(CZ87,2) -> 0 | AA87: 56505403 | AB87: =ROUND((AC87+AD87+AF87),6) -> 14177.7 | AC87: =ROUND((ES87),6) -> 14177.7 | AD87: =ROUND((((ET87)-(EU87))+AE87),6) -> 0 | AE87: =ROUND((EU87),6) -> 0 | AF87: =ROUND((EV87),6) -> 0 | AG87: =ROUND((AP87),6) -> 0 | AH87: =(EW87) -> 0 | AI87: =(EX87) -> 0 | AJ87: =(AS87) -> 0 | AK87: 14177.7 | AL87: 14177.7 | AM87: 0 | AN87: 0 | AO87: 0 | AP87: 0 | AQ87: 0 | AR87: 0 | AS87: 0 | AT87: 90 | AU87: 46 | AV87: 1 | AW87: 1 | AZ87: 1 | BA87: 1 | BB87: 1 | BC87: 1 | BH87: 3 | BI87: 2 | BM87: 68 | BN87: 0 | BP87: 0 | BQ87: 40 | BR87: 0 | BS87: 1 | BT87: 1 | BU87: 1 | BV87: 1 | BW87: 1 | BX87: 1 | BZ87: 90 | CA87: 46 | CE87: 30 | CF87: 0 | CG87: 0 | CM87: 0 | CO87: 0 | CP87: =(P87+Q87+S87) -> 99243.9 | CQ87: =ROUND((ROUND((AC87*AW87*1),2)*BC87),2) -> 14177.7 | CR87: =(ROUND((ROUND(((ET87)*AV87*1),2)*BB87),2)+ROUND((ROUND(((AE87-(EU87))*AV87*1),2)*BS87),2)) -> 0 | CS87: =ROUND((ROUND((AE87*AV87*1),2)*BS87),2) -> 0 | CT87: =ROUND((ROUND((AF87*AV87*1),2)*BA87),2) -> 0 | CU87: =AG87 -> 0 | CV87: =(AH87*AV87) -> 0 | CW87: =AI87 -> 0 | CX87: =AJ87 -> 0 | CY87: =(((S87+R87)*AT87)/100) -> 0 | CZ87: =(((S87+R87)*AU87)/100) -> 0 | DN87: 0 | DO87: 0 | DP87: 1 | DQ87: 1 | DU87: 1010 | DV87: шт. | DW87: шт. | DX87: 1 | EE87: 58162630 | EF87: 40 | EG87: Монтаж оборудования | EH87: 0 | EJ87: 2 | EK87: 68 | EL87: ТСН-2001.4-10. Прокладка и монтаж сетей связи | EM87: ТСН-2001.4-10-1 | EQ87: 0 | ER87: 0 | ES87: 14177.7 | ET87: 0 | EU87: 0 | EV87: 0 | EW87: 0 | EX87: 0 | FQ87: 0 | FR87: 0 | FS87: 0 | FX87: 90 | FY87: 46 | GA87: [164 795 / 1,2 / 9,88] + 2% Заг.скл | GD87: 1 | GF87: -165771226 | GG87: 2 | GH87: 4 | GI87: -2 | GJ87: 0 | GK87: 0 | GL87: =ROUND(IF(AND(BH87=3,BI87=3,FS87<>0),P87,0),2) -> 0 | GM87: =ROUND(O87+X87+Y87,2)+GX87 -> 99243.9 | GN87: =IF(OR(BI87=0,BI87=1),GM87-GX87,0) -> 0 | GO87: =IF(BI87=2,GM87-GX87,0) -> 99243.9 | GP87: =IF(BI87=4,GM87-GX87,0) -> 0 | GR87: 0 | GS87: 2 | GT87: 0 | GV87: =ROUND((GT87),6) -> 0 | GW87: 1 | GX87: =ROUND(HC87*I87,2) -> 0 | HA87: 0 | HB87: 0 | HC87: =GV87*GW87 -> 0 | HE87: 0 | HF87: 2 | HS87: 0 | IK87: 0
A88: 18 | B88: 1 | E88: 4,1 | F88: КА 9 | G88: Шкаф 19" серии Racknet S3000, 42U 60F-42-88-31BL | H88: шт. | I88: =I86*J88 -> 7 | J88: 1 | K88: 1 | O88: =ROUND(CP88,2) -> 980529.73 | P88: =ROUND((ROUND((AC88*AW88*I88),2)*BC88),2) -> 980529.73 | Q88: =(ROUND((ROUND(((ET88)*AV88*I88),2)*BB88),2)+ROUND((ROUND(((AE88-(EU88))*AV88*I88),2)*BS88),2)) -> 0 | R88: =ROUND((ROUND((AE88*AV88*I88),2)*BS88),2) -> 0 | S88: =ROUND((ROUND((AF88*AV88*I88),2)*BA88),2) -> 0 | T88: =ROUND(CU88*I88,2) -> 0 | U88: =CV88*I88 -> 0 | V88: =CW88*I88 -> 0 | W88: =ROUND(CX88*I88,2) -> 0 | X88: =ROUND(CY88,2) -> 0 | Y88: =ROUND(CZ88,2) -> 0 | AA88: 56505405 | AB88: =ROUND((AC88+AD88+AF88),6) -> 14177.7 | AC88: =ROUND((ES88),6) -> 14177.7 | AD88: =ROUND((((ET88)-(EU88))+AE88),6) -> 0 | AE88: =ROUND((EU88),6) -> 0 | AF88: =ROUND((EV88),6) -> 0 | AG88: =ROUND((AP88),6) -> 0 | AH88: =(EW88) -> 0 | AI88: =(EX88) -> 0 | AJ88: =(AS88) -> 0 | AK88: 14177.7 | AL88: 14177.7 | AM88: 0 | AN88: 0 | AO88: 0 | AP88: 0 | AQ88: 0 | AR88: 0 | AS88: 0 | AT88: 90 | AU88: 46 | AV88: 1 | AW88: 1 | AZ88: 1 | BA88: 1 | BB88: 1 | BC88: 9.88 | BH88: 3 | BI88: 2 | BM88: 68 | BN88: 0 | BP88: 0 | BQ88: 40 | BR88: 0 | BS88: 1 | BT88: 1 | BU88: 1 | BV88: 1 | BW88: 1 | BX88: 1 | BZ88: 90 | CA88: 46 | CE88: 30 | CF88: 0 | CG88: 0 | CM88: 0 | CO88: 0 | CP88: =(P88+Q88+S88) -> 980529.73 | CQ88: =ROUND((ROUND((AC88*AW88*1),2)*BC88),2) -> 140075.68 | CR88: =(ROUND((ROUND(((ET88)*AV88*1),2)*BB88),2)+ROUND((ROUND(((AE88-(EU88))*AV88*1),2)*BS88),2)) -> 0 | CS88: =ROUND((ROUND((AE88*AV88*1),2)*BS88),2) -> 0 | CT88: =ROUND((ROUND((AF88*AV88*1),2)*BA88),2) -> 0 | CU88: =AG88 -> 0 | CV88: =(AH88*AV88) -> 0 | CW88: =AI88 -> 0 | CX88: =AJ88 -> 0 | CY88: =(((S88+R88)*AT88)/100) -> 0 | CZ88: =(((S88+R88)*AU88)/100) -> 0 | DN88: 0 | DO88: 0 | DP88: 1 | DQ88: 1 | DU88: 1010 | DV88: шт. | DW88: шт. | DX88: 1 | EE88: 58162630 | EF88: 40 | EG88: Монтаж оборудования | EH88: 0 | EJ88: 2 | EK88: 68 | EL88: ТСН-2001.4-10. Прокладка и монтаж сетей связи | EM88: ТСН-2001.4-10-1 | EQ88: 0 | ER88: 14177.7 | ES88: 14177.7 | ET88: 0 | EU88: 0 | EV88: 0 | EW88: 0 | EX88: 0 | EZ88: 5 | FC88: 1 | FD88: 18 | FF88: 164795 | FQ88: 0 | FR88: 0 | FS88: 0 | FX88: 90 | FY88: 46 | GA88: [164 795 / 1,2 / 9,88] + 2% Заг.скл | GD88: 1 | GF88: -165771226 | GG88: 2 | GH88: 3 | GI88: 5 | GJ88: 0 | GK88: 0 | GL88: =ROUND(IF(AND(BH88=3,BI88=3,FS88<>0),P88,0),2) -> 0 | GM88: =ROUND(O88+X88+Y88,2)+GX88 -> 980529.73 | GN88: =IF(OR(BI88=0,BI88=1),GM88-GX88,0) -> 0 | GO88: =IF(BI88=2,GM88-GX88,0) -> 980529.73 | GP88: =IF(BI88=4,GM88-GX88,0) -> 0 | GR88: 1 | GS88: 1 | GT88: 0 | GV88: =ROUND((GT88),6) -> 0 | GW88: 1 | GX88: =ROUND(HC88*I88,2) -> 0 | HA88: 0 | HB88: 0 | HC88: =GV88*GW88 -> 0 | HE88: 0 | HF88: 2 | HS88: 0 | IK88: 0
A89: 18 | B89: 1 | E89: 4,2 | F89: КА 10 | G89: Вертикальный органайзер 60А-18-42-01-31BL | H89: шт. | I89: =I85*J89 -> 7 | J89: 1 | K89: 1 | O89: =ROUND(CP89,2) -> 22627.15 | P89: =ROUND((ROUND((AC89*AW89*I89),2)*BC89),2) -> 22627.15 | Q89: =(ROUND((ROUND(((ET89)*AV89*I89),2)*BB89),2)+ROUND((ROUND(((AE89-(EU89))*AV89*I89),2)*BS89),2)) -> 0 | R89: =ROUND((ROUND((AE89*AV89*I89),2)*BS89),2) -> 0 | S89: =ROUND((ROUND((AF89*AV89*I89),2)*BA89),2) -> 0 | T89: =ROUND(CU89*I89,2) -> 0 | U89: =CV89*I89 -> 0 | V89: =CW89*I89 -> 0 | W89: =ROUND(CX89*I89,2) -> 0 | X89: =ROUND(CY89,2) -> 0 | Y89: =ROUND(CZ89,2) -> 0 | AA89: 56505403 | AB89: =ROUND((AC89+AD89+AF89),6) -> 3232.45 | AC89: =ROUND((ES89),6) -> 3232.45 | AD89: =ROUND((((ET89)-(EU89))+AE89),6) -> 0 | AE89: =ROUND((EU89),6) -> 0 | AF89: =ROUND((EV89),6) -> 0 | AG89: =ROUND((AP89),6) -> 0 | AH89: =(EW89) -> 0 | AI89: =(EX89) -> 0 | AJ89: =(AS89) -> 0 | AK89: 3232.45 | AL89: 3232.45 | AM89: 0 | AN89: 0 | AO89: 0 | AP89: 0 | AQ89: 0 | AR89: 0 | AS89: 0 | AT89: 90 | AU89: 46 | AV89: 1 | AW89: 1 | AZ89: 1 | BA89: 1 | BB89: 1 | BC89: 1 | BH89: 3 | BI89: 2 | BM89: 68 | BN89: 0 | BP89: 0 | BQ89: 40 | BR89: 0 | BS89: 1 | BT89: 1 | BU89: 1 | BV89: 1 | BW89: 1 | BX89: 1 | BZ89: 90 | CA89: 46 | CE89: 30 | CF89: 0 | CG89: 0 | CM89: 0 | CO89: 0 | CP89: =(P89+Q89+S89) -> 22627.15 | CQ89: =ROUND((ROUND((AC89*AW89*1),2)*BC89),2) -> 3232.45 | CR89: =(ROUND((ROUND(((ET89)*AV89*1),2)*BB89),2)+ROUND((ROUND(((AE89-(EU89))*AV89*1),2)*BS89),2)) -> 0 | CS89: =ROUND((ROUND((AE89*AV89*1),2)*BS89),2) -> 0 | CT89: =ROUND((ROUND((AF89*AV89*1),2)*BA89),2) -> 0 | CU89: =AG89 -> 0 | CV89: =(AH89*AV89) -> 0 | CW89: =AI89 -> 0 | CX89: =AJ89 -> 0 | CY89: =(((S89+R89)*AT89)/100) -> 0 | CZ89: =(((S89+R89)*AU89)/100) -> 0 | DN89: 0 | DO89: 0 | DP89: 1 | DQ89: 1 | DU89: 1010 | DV89: шт. | DW89: шт. | DX89: 1 | EE89: 58162630 | EF89: 40 | EG89: Монтаж оборудования | EH89: 0 | EJ89: 2 | EK89: 68 | EL89: ТСН-2001.4-10. Прокладка и монтаж сетей связи | EM89: ТСН-2001.4-10-1 | EQ89: 0 | ER89: 0 | ES89: 3232.45 | ET89: 0 | EU89: 0 | EV89: 0 | EW89: 0 | EX89: 0 | FQ89: 0 | FR89: 0 | FS89: 0 | FX89: 90 | FY89: 46 | GA89: [37 572,47 / 1,2 / 9,88] + 2% Заг.скл | GD89: 1 | GF89: 362987725 | GG89: 2 | GH89: 4 | GI89: -2 | GJ89: 0 | GK89: 0 | GL89: =ROUND(IF(AND(BH89=3,BI89=3,FS89<>0),P89,0),2) -> 0 | GM89: =ROUND(O89+X89+Y89,2)+GX89 -> 22627.15 | GN89: =IF(OR(BI89=0,BI89=1),GM89-GX89,0) -> 0 | GO89: =IF(BI89=2,GM89-GX89,0) -> 22627.15 | GP89: =IF(BI89=4,GM89-GX89,0) -> 0 | GR89: 0 | GS89: 2 | GT89: 0 | GV89: =ROUND((GT89),6) -> 0 | GW89: 1 | GX89: =ROUND(HC89*I89,2) -> 0 | HA89: 0 | HB89: 0 | HC89: =GV89*GW89 -> 0 | HE89: 0 | HF89: 2 | HS89: 0 | IK89: 0
A90: 18 | B90: 1 | E90: 4,2 | F90: КА 10 | G90: Вертикальный органайзер 60А-18-42-01-31BL | H90: шт. | I90: =I86*J90 -> 7 | J90: 1 | K90: 1 | O90: =ROUND(CP90,2) -> 223556.24 | P90: =ROUND((ROUND((AC90*AW90*I90),2)*BC90),2) -> 223556.24 | Q90: =(ROUND((ROUND(((ET90)*AV90*I90),2)*BB90),2)+ROUND((ROUND(((AE90-(EU90))*AV90*I90),2)*BS90),2)) -> 0 | R90: =ROUND((ROUND((AE90*AV90*I90),2)*BS90),2) -> 0 | S90: =ROUND((ROUND((AF90*AV90*I90),2)*BA90),2) -> 0 | T90: =ROUND(CU90*I90,2) -> 0 | U90: =CV90*I90 -> 0 | V90: =CW90*I90 -> 0 | W90: =ROUND(CX90*I90,2) -> 0 | X90: =ROUND(CY90,2) -> 0 | Y90: =ROUND(CZ90,2) -> 0 | AA90: 56505405 | AB90: =ROUND((AC90+AD90+AF90),6) -> 3232.45 | AC90: =ROUND((ES90),6) -> 3232.45 | AD90: =ROUND((((ET90)-(EU90))+AE90),6) -> 0 | AE90: =ROUND((EU90),6) -> 0 | AF90: =ROUND((EV90),6) -> 0 | AG90: =ROUND((AP90),6) -> 0 | AH90: =(EW90) -> 0 | AI90: =(EX90) -> 0 | AJ90: =(AS90) -> 0 | AK90: 3232.45 | AL90: 3232.45 | AM90: 0 | AN90: 0 | AO90: 0 | AP90: 0 | AQ90: 0 | AR90: 0 | AS90: 0 | AT90: 90 | AU90: 46 | AV90: 1 | AW90: 1 | AZ90: 1 | BA90: 1 | BB90: 1 | BC90: 9.88 | BH90: 3 | BI90: 2 | BM90: 68 | BN90: 0 | BP90: 0 | BQ90: 40 | BR90: 0 | BS90: 1 | BT90: 1 | BU90: 1 | BV90: 1 | BW90: 1 | BX90: 1 | BZ90: 90 | CA90: 46 | CE90: 30 | CF90: 0 | CG90: 0 | CM90: 0 | CO90: 0 | CP90: =(P90+Q90+S90) -> 223556.24 | CQ90: =ROUND((ROUND((AC90*AW90*1),2)*BC90),2) -> 31936.61 | CR90: =(ROUND((ROUND(((ET90)*AV90*1),2)*BB90),2)+ROUND((ROUND(((AE90-(EU90))*AV90*1),2)*BS90),2)) -> 0 | CS90: =ROUND((ROUND((AE90*AV90*1),2)*BS90),2) -> 0 | CT90: =ROUND((ROUND((AF90*AV90*1),2)*BA90),2) -> 0 | CU90: =AG90 -> 0 | CV90: =(AH90*AV90) -> 0 | CW90: =AI90 -> 0 | CX90: =AJ90 -> 0 | CY90: =(((S90+R90)*AT90)/100) -> 0 | CZ90: =(((S90+R90)*AU90)/100) -> 0 | DN90: 0 | DO90: 0 | DP90: 1 | DQ90: 1 | DU90: 1010 | DV90: шт. | DW90: шт. | DX90: 1 | EE90: 58162630 | EF90: 40 | EG90: Монтаж оборудования | EH90: 0 | EJ90: 2 | EK90: 68 | EL90: ТСН-2001.4-10. Прокладка и монтаж сетей связи | EM90: ТСН-2001.4-10-1 | EQ90: 0 | ER90: 3232.45 | ES90: 3232.45 | ET90: 0 | EU90: 0 | EV90: 0 | EW90: 0 | EX90: 0 | EZ90: 5 | FC90: 1 | FD90: 18 | FF90: 37572.47 | FQ90: 0 | FR90: 0 | FS90: 0 | FX90: 90 | FY90: 46 | GA90: [37 572,47 / 1,2 / 9,88] + 2% Заг.скл | GD90: 1 | GF90: 362987725 | GG90: 2 | GH90: 3 | GI90: 5 | GJ90: 0 | GK90: 0 | GL90: =ROUND(IF(AND(BH90=3,BI90=3,FS90<>0),P90,0),2) -> 0 | GM90: =ROUND(O90+X90+Y90,2)+GX90 -> 223556.24 | GN90: =IF(OR(BI90=0,BI90=1),GM90-GX90,0) -> 0 | GO90: =IF(BI90=2,GM90-GX90,0) -> 223556.24 | GP90: =IF(BI90=4,GM90-GX90,0) -> 0 | GR90: 1 | GS90: 1 | GT90: 0 | GV90: =ROUND((GT90),6) -> 0 | GW90: 1 | GX90: =ROUND(HC90*I90,2) -> 0 | HA90: 0 | HB90: 0 | HC90: =GV90*GW90 -> 0 | HE90: 0 | HF90: 2 | HS90: 0 | IK90: 0
A91: 18 | B91: 1 | E91: 4,3 | F91: КА 11 | G91: Шuна заземленuя 19" (500мм), 20 mочек, 5х15мм 60A-14-11GR | H91: шт. | I91: =I85*J91 -> 8 | J91: 1.1428571 | K91: 1.1428571 | O91: =ROUND(CP91,2) -> 2773.68 | P91: =ROUND((ROUND((AC91*AW91*I91),2)*BC91),2) -> 2773.68 | Q91: =(ROUND((ROUND(((ET91)*AV91*I91),2)*BB91),2)+ROUND((ROUND(((AE91-(EU91))*AV91*I91),2)*BS91),2)) -> 0 | R91: =ROUND((ROUND((AE91*AV91*I91),2)*BS91),2) -> 0 | S91: =ROUND((ROUND((AF91*AV91*I91),2)*BA91),2) -> 0 | T91: =ROUND(CU91*I91,2) -> 0 | U91: =CV91*I91 -> 0 | V91: =CW91*I91 -> 0 | W91: =ROUND(CX91*I91,2) -> 0 | X91: =ROUND(CY91,2) -> 0 | Y91: =ROUND(CZ91,2) -> 0 | AA91: 56505403 | AB91: =ROUND((AC91+AD91+AF91),6) -> 346.71 | AC91: =ROUND((ES91),6) -> 346.71 | AD91: =ROUND((((ET91)-(EU91))+AE91),6) -> 0 | AE91: =ROUND((EU91),6) -> 0 | AF91: =ROUND((EV91),6) -> 0 | AG91: =ROUND((AP91),6) -> 0 | AH91: =(EW91) -> 0 | AI91: =(EX91) -> 0 | AJ91: =(AS91) -> 0 | AK91: 346.71 | AL91: 346.71 | AM91: 0 | AN91: 0 | AO91: 0 | AP91: 0 | AQ91: 0 | AR91: 0 | AS91: 0 | AT91: 90 | AU91: 46 | AV91: 1 | AW91: 1 | AZ91: 1 | BA91: 1 | BB91: 1 | BC91: 1 | BH91: 3 | BI91: 2 | BM91: 68 | BN91: 0 | BP91: 0 | BQ91: 40 | BR91: 0 | BS91: 1 | BT91: 1 | BU91: 1 | BV91: 1 | BW91: 1 | BX91: 1 | BZ91: 90 | CA91: 46 | CE91: 30 | CF91: 0 | CG91: 0 | CM91: 0 | CO91: 0 | CP91: =(P91+Q91+S91) -> 2773.68 | CQ91: =ROUND((ROUND((AC91*AW91*1),2)*BC91),2) -> 346.71 | CR91: =(ROUND((ROUND(((ET91)*AV91*1),2)*BB91),2)+ROUND((ROUND(((AE91-(EU91))*AV91*1),2)*BS91),2)) -> 0 | CS91: =ROUND((ROUND((AE91*AV91*1),2)*BS91),2) -> 0 | CT91: =ROUND((ROUND((AF91*AV91*1),2)*BA91),2) -> 0 | CU91: =AG91 -> 0 | CV91: =(AH91*AV91) -> 0 | CW91: =AI91 -> 0 | CX91: =AJ91 -> 0 | CY91: =(((S91+R91)*AT91)/100) -> 0 | CZ91: =(((S91+R91)*AU91)/100) -> 0 | DN91: 0 | DO91: 0 | DP91: 1 | DQ91: 1 | DU91: 1010 | DV91: шт. | DW91: шт. | DX91: 1 | EE91: 58162630 | EF91: 40 | EG91: Монтаж оборудования | EH91: 0 | EJ91: 2 | EK91: 68 | EL91: ТСН-2001.4-10. Прокладка и монтаж сетей связи | EM91: ТСН-2001.4-10-1 | EQ91: 0 | ER91: 0 | ES91: 346.71 | ET91: 0 | EU91: 0 | EV91: 0 | EW91: 0 | EX91: 0 | FQ91: 0 | FR91: 0 | FS91: 0 | FX91: 90 | FY91: 46 | GA91: [4 030 / 1,2 / 9,88] + 2% Заг.скл | GD91: 1 | GF91: 1874541176 | GG91: 2 | GH91: 4 | GI91: -2 | GJ91: 0 | GK91: 0 | GL91: =ROUND(IF(AND(BH91=3,BI91=3,FS91<>0),P91,0),2) -> 0 | GM91: =ROUND(O91+X91+Y91,2)+GX91 -> 2773.68 | GN91: =IF(OR(BI91=0,BI91=1),GM91-GX91,0) -> 0 | GO91: =IF(BI91=2,GM91-GX91,0) -> 2773.68 | GP91: =IF(BI91=4,GM91-GX91,0) -> 0 | GR91: 0 | GS91: 2 | GT91: 0 | GV91: =ROUND((GT91),6) -> 0 | GW91: 1 | GX91: =ROUND(HC91*I91,2) -> 0 | HA91: 0 | HB91: 0 | HC91: =GV91*GW91 -> 0 | HE91: 0 | HF91: 2 | HS91: 0 | IK91: 0
A92: 18 | B92: 1 | E92: 4,3 | F92: КА 11 | G92: Шuна заземленuя 19" (500мм), 20 mочек, 5х15мм 60A-14-11GR | H92: шт. | I92: =I86*J92 -> 8 | J92: 1.1428571 | K92: 1.1428571 | O92: =ROUND(CP92,2) -> 27403.96 | P92: =ROUND((ROUND((AC92*AW92*I92),2)*BC92),2) -> 27403.96 | Q92: =(ROUND((ROUND(((ET92)*AV92*I92),2)*BB92),2)+ROUND((ROUND(((AE92-(EU92))*AV92*I92),2)*BS92),2)) -> 0 | R92: =ROUND((ROUND((AE92*AV92*I92),2)*BS92),2) -> 0 | S92: =ROUND((ROUND((AF92*AV92*I92),2)*BA92),2) -> 0 | T92: =ROUND(CU92*I92,2) -> 0 | U92: =CV92*I92 -> 0 | V92: =CW92*I92 -> 0 | W92: =ROUND(CX92*I92,2) -> 0 | X92: =ROUND(CY92,2) -> 0 | Y92: =ROUND(CZ92,2) -> 0 | AA92: 56505405 | AB92: =ROUND((AC92+AD92+AF92),6) -> 346.71 | AC92: =ROUND((ES92),6) -> 346.71 | AD92: =ROUND((((ET92)-(EU92))+AE92),6) -> 0 | AE92: =ROUND((EU92),6) -> 0 | AF92: =ROUND((EV92),6) -> 0 | AG92: =ROUND((AP92),6) -> 0 | AH92: =(EW92) -> 0 | AI92: =(EX92) -> 0 | AJ92: =(AS92) -> 0 | AK92: 346.71 | AL92: 346.71 | AM92: 0 | AN92: 0 | AO92: 0 | AP92: 0 | AQ92: 0 | AR92: 0 | AS92: 0 | AT92: 90 | AU92: 46 | AV92: 1 | AW92: 1 | AZ92: 1 | BA92: 1 | BB92: 1 | BC92: 9.88 | BH92: 3 | BI92: 2 | BM92: 68 | BN92: 0 | BP92: 0 | BQ92: 40 | BR92: 0 | BS92: 1 | BT92: 1 | BU92: 1 | BV92: 1 | BW92: 1 | BX92: 1 | BZ92: 90 | CA92: 46 | CE92: 30 | CF92: 0 | CG92: 0 | CM92: 0 | CO92: 0 | CP92: =(P92+Q92+S92) -> 27403.96 | CQ92: =ROUND((ROUND((AC92*AW92*1),2)*BC92),2) -> 3425.49 | CR92: =(ROUND((ROUND(((ET92)*AV92*1),2)*BB92),2)+ROUND((ROUND(((AE92-(EU92))*AV92*1),2)*BS92),2)) -> 0 | CS92: =ROUND((ROUND((AE92*AV92*1),2)*BS92),2) -> 0 | CT92: =ROUND((ROUND((AF92*AV92*1),2)*BA92),2) -> 0 | CU92: =AG92 -> 0 | CV92: =(AH92*AV92) -> 0 | CW92: =AI92 -> 0 | CX92: =AJ92 -> 0 | CY92: =(((S92+R92)*AT92)/100) -> 0 | CZ92: =(((S92+R92)*AU92)/100) -> 0 | DN92: 0 | DO92: 0 | DP92: 1 | DQ92: 1 | DU92: 1010 | DV92: шт. | DW92: шт. | DX92: 1 | EE92: 58162630 | EF92: 40 | EG92: Монтаж оборудования | EH92: 0 | EJ92: 2 | EK92: 68 | EL92: ТСН-2001.4-10. Прокладка и монтаж сетей связи | EM92: ТСН-2001.4-10-1 | EQ92: 0 | ER92: 346.71 | ES92: 346.71 | ET92: 0 | EU92: 0 | EV92: 0 | EW92: 0 | EX92: 0 | EZ92: 5 | FC92: 1 | FD92: 18 | FF92: 4030 | FQ92: 0 | FR92: 0 | FS92: 0 | FX92: 90 | FY92: 46 | GA92: [4 030 / 1,2 / 9,88] + 2% Заг.скл | GD92: 1 | GF92: 1874541176 | GG92: 2 | GH92: 3 | GI92: 5 | GJ92: 0 | GK92: 0 | GL92: =ROUND(IF(AND(BH92=3,BI92=3,FS92<>0),P92,0),2) -> 0 | GM92: =ROUND(O92+X92+Y92,2)+GX92 -> 27403.96 | GN92: =IF(OR(BI92=0,BI92=1),GM92-GX92,0) -> 0 | GO92: =IF(BI92=2,GM92-GX92,0) -> 27403.96 | GP92: =IF(BI92=4,GM92-GX92,0) -> 0 | GR92: 1 | GS92: 1 | GT92: 0 | GV92: =ROUND((GT92),6) -> 0 | GW92: 1 | GX92: =ROUND(HC92*I92,2) -> 0 | HA92: 0 | HB92: 0 | HC92: =GV92*GW92 -> 0 | HE92: 0 | HF92: 2 | HS92: 0 | IK92: 0
A93: 18 | B93: 1 | E93: 4,4 | F93: КА 7 | G93: Набор для креnленuя лоmков к крышке шкафов, высоmа 50мм 60А-31-08-ЗЗВL | H93: шт. | I93: =I85*J93 -> 7 | J93: 1 | K93: 1 | O93: =ROUND(CP93,2) -> 1033.34 | P93: =ROUND((ROUND((AC93*AW93*I93),2)*BC93),2) -> 1033.34 | Q93: =(ROUND((ROUND(((ET93)*AV93*I93),2)*BB93),2)+ROUND((ROUND(((AE93-(EU93))*AV93*I93),2)*BS93),2)) -> 0 | R93: =ROUND((ROUND((AE93*AV93*I93),2)*BS93),2) -> 0 | S93: =ROUND((ROUND((AF93*AV93*I93),2)*BA93),2) -> 0 | T93: =ROUND(CU93*I93,2) -> 0 | U93: =CV93*I93 -> 0 | V93: =CW93*I93 -> 0 | W93: =ROUND(CX93*I93,2) -> 0 | X93: =ROUND(CY93,2) -> 0 | Y93: =ROUND(CZ93,2) -> 0 | AA93: 56505403 | AB93: =ROUND((AC93+AD93+AF93),6) -> 147.62 | AC93: =ROUND((ES93),6) -> 147.62 | AD93: =ROUND((((ET93)-(EU93))+AE93),6) -> 0 | AE93: =ROUND((EU93),6) -> 0 | AF93: =ROUND((EV93),6) -> 0 | AG93: =ROUND((AP93),6) -> 0 | AH93: =(EW93) -> 0 | AI93: =(EX93) -> 0 | AJ93: =(AS93) -> 0 | AK93: 147.62 | AL93: 147.62 | AM93: 0 | AN93: 0 | AO93: 0 | AP93: 0 | AQ93: 0 | AR93: 0 | AS93: 0 | AT93: 90 | AU93: 46 | AV93: 1 | AW93: 1 | AZ93: 1 | BA93: 1 | BB93: 1 | BC93: 1 | BH93: 3 | BI93: 2 | BM93: 68 | BN93: 0 | BP93: 0 | BQ93: 40 | BR93: 0 | BS93: 1 | BT93: 1 | BU93: 1 | BV93: 1 | BW93: 1 | BX93: 1 | BZ93: 90 | CA93: 46 | CE93: 30 | CF93: 0 | CG93: 0 | CM93: 0 | CO93: 0 | CP93: =(P93+Q93+S93) -> 1033.34 | CQ93: =ROUND((ROUND((AC93*AW93*1),2)*BC93),2) -> 147.62 | CR93: =(ROUND((ROUND(((ET93)*AV93*1),2)*BB93),2)+ROUND((ROUND(((AE93-(EU93))*AV93*1),2)*BS93),2)) -> 0 | CS93: =ROUND((ROUND((AE93*AV93*1),2)*BS93),2) -> 0 | CT93: =ROUND((ROUND((AF93*AV93*1),2)*BA93),2) -> 0 | CU93: =AG93 -> 0 | CV93: =(AH93*AV93) -> 0 | CW93: =AI93 -> 0 | CX93: =AJ93 -> 0 | CY93: =(((S93+R93)*AT93)/100) -> 0 | CZ93: =(((S93+R93)*AU93)/100) -> 0 | DN93: 0 | DO93: 0 | DP93: 1 | DQ93: 1 | DU93: 1010 | DV93: шт. | DW93: шт. | DX93: 1 | EE93: 58162630 | EF93: 40 | EG93: Монтаж оборудования | EH93: 0 | EJ93: 2 | EK93: 68 | EL93: ТСН-2001.4-10. Прокладка и монтаж сетей связи | EM93: ТСН-2001.4-10-1 | EQ93: 0 | ER93: 0 | ES93: 147.62 | ET93: 0 | EU93: 0 | EV93: 0 | EW93: 0 | EX93: 0 | FQ93: 0 | FR93: 0 | FS93: 0 | FX93: 90 | FY93: 46 | GA93: [1 715,95 / 1,2 / 9,88] + 2% Заг.скл | GD93: 1 | GF93: -957674279 | GG93: 2 | GH93: 4 | GI93: -2 | GJ93: 0 | GK93: 0 | GL93: =ROUND(IF(AND(BH93=3,BI93=3,FS93<>0),P93,0),2) -> 0 | GM93: =ROUND(O93+X93+Y93,2)+GX93 -> 1033.34 | GN93: =IF(OR(BI93=0,BI93=1),GM93-GX93,0) -> 0 | GO93: =IF(BI93=2,GM93-GX93,0) -> 1033.34 | GP93: =IF(BI93=4,GM93-GX93,0) -> 0 | GR93: 0 | GS93: 2 | GT93: 0 | GV93: =ROUND((GT93),6) -> 0 | GW93: 1 | GX93: =ROUND(HC93*I93,2) -> 0 | HA93: 0 | HB93: 0 | HC93: =GV93*GW93 -> 0 | HE93: 0 | HF93: 2 | HS93: 0 | IK93: 0
A94: 18 | B94: 1 | E94: 4,4 | F94: КА 7 | G94: Набор для креnленuя лоmков к крышке шкафов, высоmа 50мм 60А-31-08-ЗЗВL | H94: шт. | I94: =I86*J94 -> 7 | J94: 1 | K94: 1 | O94: =ROUND(CP94,2) -> 10209.4 | P94: =ROUND((ROUND((AC94*AW94*I94),2)*BC94),2) -> 10209.4 | Q94: =(ROUND((ROUND(((ET94)*AV94*I94),2)*BB94),2)+ROUND((ROUND(((AE94-(EU94))*AV94*I94),2)*BS94),2)) -> 0 | R94: =ROUND((ROUND((AE94*AV94*I94),2)*BS94),2) -> 0 | S94: =ROUND((ROUND((AF94*AV94*I94),2)*BA94),2) -> 0 | T94: =ROUND(CU94*I94,2) -> 0 | U94: =CV94*I94 -> 0 | V94: =CW94*I94 -> 0 | W94: =ROUND(CX94*I94,2) -> 0 | X94: =ROUND(CY94,2) -> 0 | Y94: =ROUND(CZ94,2) -> 0 | AA94: 56505405 | AB94: =ROUND((AC94+AD94+AF94),6) -> 147.62 | AC94: =ROUND((ES94),6) -> 147.62 | AD94: =ROUND((((ET94)-(EU94))+AE94),6) -> 0 | AE94: =ROUND((EU94),6) -> 0 | AF94: =ROUND((EV94),6) -> 0 | AG94: =ROUND((AP94),6) -> 0 | AH94: =(EW94) -> 0 | AI94: =(EX94) -> 0 | AJ94: =(AS94) -> 0 | AK94: 147.62 | AL94: 147.62 | AM94: 0 | AN94: 0 | AO94: 0 | AP94: 0 | AQ94: 0 | AR94: 0 | AS94: 0 | AT94: 90 | AU94: 46 | AV94: 1 | AW94: 1 | AZ94: 1 | BA94: 1 | BB94: 1 | BC94: 9.88 | BH94: 3 | BI94: 2 | BM94: 68 | BN94: 0 | BP94: 0 | BQ94: 40 | BR94: 0 | BS94: 1 | BT94: 1 | BU94: 1 | BV94: 1 | BW94: 1 | BX94: 1 | BZ94: 90 | CA94: 46 | CE94: 30 | CF94: 0 | CG94: 0 | CM94: 0 | CO94: 0 | CP94: =(P94+Q94+S94) -> 10209.4 | CQ94: =ROUND((ROUND((AC94*AW94*1),2)*BC94),2) -> 1458.49 | CR94: =(ROUND((ROUND(((ET94)*AV94*1),2)*BB94),2)+ROUND((ROUND(((AE94-(EU94))*AV94*1),2)*BS94),2)) -> 0 | CS94: =ROUND((ROUND((AE94*AV94*1),2)*BS94),2) -> 0 | CT94: =ROUND((ROUND((AF94*AV94*1),2)*BA94),2) -> 0 | CU94: =AG94 -> 0 | CV94: =(AH94*AV94) -> 0 | CW94: =AI94 -> 0 | CX94: =AJ94 -> 0 | CY94: =(((S94+R94)*AT94)/100) -> 0 | CZ94: =(((S94+R94)*AU94)/100) -> 0 | DN94: 0 | DO94: 0 | DP94: 1 | DQ94: 1 | DU94: 1010 | DV94: шт. | DW94: шт. | DX94: 1 | EE94: 58162630 | EF94: 40 | EG94: Монтаж оборудования | EH94: 0 | EJ94: 2 | EK94: 68 | EL94: ТСН-2001.4-10. Прокладка и монтаж сетей связи | EM94: ТСН-2001.4-10-1 | EQ94: 0 | ER94: 147.62 | ES94: 147.62 | ET94: 0 | EU94: 0 | EV94: 0 | EW94: 0 | EX94: 0 | EZ94: 5 | FC94: 1 | FD94: 18 | FF94: 1715.95 | FQ94: 0 | FR94: 0 | FS94: 0 | FX94: 90 | FY94: 46 | GA94: [1 715,95 / 1,2 / 9,88] + 2% Заг.скл | GD94: 1 | GF94: -957674279 | GG94: 2 | GH94: 3 | GI94: 5 | GJ94: 0 | GK94: 0 | GL94: =ROUND(IF(AND(BH94=3,BI94=3,FS94<>0),P94,0),2) -> 0 | GM94: =ROUND(O94+X94+Y94,2)+GX94 -> 10209.4 | GN94: =IF(OR(BI94=0,BI94=1),GM94-GX94,0) -> 0 | GO94: =IF(BI94=2,GM94-GX94,0) -> 10209.4 | GP94: =IF(BI94=4,GM94-GX94,0) -> 0 | GR94: 1 | GS94: 1 | GT94: 0 | GV94: =ROUND((GT94),6) -> 0 | GW94: 1 | GX94: =ROUND(HC94*I94,2) -> 0 | HA94: 0 | HB94: 0 | HC94: =GV94*GW94 -> 0 | HE94: 0 | HF94: 2 | HS94: 0 | IK94: 0
A95: 17 | B95: 1 | D95: =ROW(EtalonRes!A33) -> 33 | E95: 5 | F95: 4.11-14-1 | G95: Включение штепсельных разъемов в аппаратуру, количество контактов в разъеме до 14 | H95: 1 разъем | I95: =ROUND(7+8*8,9) -> 71 | J95: 0 | K95: =ROUND(7+8*8,9) -> 71 | O95: =ROUND(CP95,2) -> 206.06 | P95: =ROUND((ROUND((AC95*AW95*I95),2)*BC95),2) -> 0 | Q95: =(ROUND((ROUND((((ET95*1.1))*AV95*I95),2)*BB95),2)+ROUND((ROUND(((AE95-((EU95*1.1)))*AV95*I95),2)*BS95),2)) -> 0 | R95: =ROUND((ROUND((AE95*AV95*I95),2)*BS95),2) -> 0 | S95: =ROUND((ROUND((AF95*AV95*I95),2)*BA95),2) -> 206.06 | T95: =ROUND(CU95*I95,2) -> 0 | U95: =CV95*I95 -> 17.989554 | V95: =CW95*I95 -> 0 | W95: =ROUND(CX95*I95,2) -> 0 | X95: =ROUND(CY95,2) -> 185.45 | Y95: =ROUND(CZ95,2) -> 94.79 | AA95: 56505403 | AB95: =ROUND((AC95+AD95+AF95),6) -> 2.772 | AC95: =ROUND((ES95),6) -> 0 | AD95: =ROUND(((((ET95*1.1))-((EU95*1.1)))+AE95),6) -> 0 | AE95: =ROUND(((EU95*1.1)),6) -> 0 | AF95: =ROUND(((EV95*1.1)),6) -> 2.772 | AG95: =ROUND((AP95),6) -> 0 | AH95: =((EW95*1.1)) -> 0.242 | AI95: =((EX95*1.1)) -> 0 | AJ95: =(AS95) -> 0 | AK95: 2.52 | AL95: 0 | AM95: 0 | AN95: 0 | AO95: 2.52 | AP95: 0 | AQ95: 0.22 | AR95: 0 | AS95: 0 | AT95: 90 | AU95: 46 | AV95: 1.047 | AW95: 1 | AZ95: 1 | BA95: 1 | BB95: 1 | BC95: 1 | BH95: 0 | BI95: 2 | BJ95: ТСН-2001.4 Доп. 67, Сб. 11, т. 14, поз. 1 | BM95: 72 | BN95: 0 | BO95: 4.11-14-1 | BP95: 1 | BQ95: 40 | BR95: 0 | BS95: 1 | BT95: 1 | BU95: 1 | BV95: 1 | BW95: 1 | BX95: 1 | BZ95: 90 | CA95: 46 | CE95: 30 | CF95: 0 | CG95: 0 | CM95: 0 | CO95: 0 | CP95: =(P95+Q95+S95) -> 206.06 | CQ95: =ROUND((ROUND((AC95*AW95*1),2)*BC95),2) -> 0 | CR95: =(ROUND((ROUND((((ET95*1.1))*AV95*1),2)*BB95),2)+ROUND((ROUND(((AE95-((EU95*1.1)))*AV95*1),2)*BS95),2)) -> 0 | CS95: =ROUND((ROUND((AE95*AV95*1),2)*BS95),2) -> 0 | CT95: =ROUND((ROUND((AF95*AV95*1),2)*BA95),2) -> 2.9 | CU95: =AG95 -> 0 | CV95: =(AH95*AV95) -> 0.253374 | CW95: =AI95 -> 0 | CX95: =AJ95 -> 0 | CY95: =(((S95+R95)*AT95)/100) -> 185.454 | CZ95: =(((S95+R95)*AU95)/100) -> 94.7876 | DE95: *1,1 | DF95: *1,1 | DG95: *1,1 | DI95: *1,1 | DJ95: *1,1 | DN95: 0 | DO95: 0 | DP95: 1 | DQ95: 1 | DU95: 1013 | DV95: 1 разъем | DW95: 1 разъем | DX95: 1 | EE95: 58162634 | EF95: 40 | EG95: Монтаж оборудования | EH95: 0 | EJ95: 2 | EK95: 72 | EL95: ТСН-2001.4-11. Приборы и средства автоматизации и вычислительной техники | EM95: ТСН-2001.4-11-1 | EO95: Поправка: Гл.12.Прил.8.п.8. 5_12.00.01.11.003 | EQ95: 0 | ER95: 2.52 | ES95: 0 | ET95: 0 | EU95: 0 | EV95: 2.52 | EW95: 0.22 | EX95: 0 | EY95: 0 | FQ95: 0 | FR95: 0 | FS95: 0 | FX95: 90 | FY95: 46 | GD95: 1 | GF95: 1774518925 | GG95: 2 | GH95: 1 | GI95: 2 | GJ95: 0 | GK95: 0 | GL95: =ROUND(IF(AND(BH95=3,BI95=3,FS95<>0),P95,0),2) -> 0 | GM95: =ROUND(O95+X95+Y95,2)+GX95 -> 486.3 | GN95: =IF(OR(BI95=0,BI95=1),GM95-GX95,0) -> 0 | GO95: =IF(BI95=2,GM95-GX95,0) -> 486.3 | GP95: =IF(BI95=4,GM95-GX95,0) -> 0 | GR95: 0 | GS95: 3 | GT95: 0 | GV95: =ROUND((GT95),6) -> 0 | GW95: 1 | GX95: =ROUND(HC95*I95,2) -> 0 | HA95: 0 | HB95: 0 | HC95: =GV95*GW95 -> 0 | HS95: 0 | IK95: 0
A96: 17 | B96: 1 | D96: =ROW(EtalonRes!A34) -> 34 | E96: 5 | F96: 4.11-14-1 | G96: Включение штепсельных разъемов в аппаратуру, количество контактов в разъеме до 14 | H96: 1 разъем | I96: =ROUND(7+8*8,9) -> 71 | J96: 0 | K96: =ROUND(7+8*8,9) -> 71 | O96: =ROUND(CP96,2) -> 11331.24 | P96: =ROUND((ROUND((AC96*AW96*I96),2)*BC96),2) -> 0 | Q96: =(ROUND((ROUND((((ET96*1.1))*AV96*I96),2)*BB96),2)+ROUND((ROUND(((AE96-((EU96*1.1)))*AV96*I96),2)*BS96),2)) -> 0 | R96: =ROUND((ROUND((AE96*AV96*I96),2)*BS96),2) -> 0 | S96: =ROUND((ROUND((AF96*AV96*I96),2)*BA96),2) -> 11331.24 | T96: =ROUND(CU96*I96,2) -> 0 | U96: =CV96*I96 -> 17.989554 | V96: =CW96*I96 -> 0 | W96: =ROUND(CX96*I96,2) -> 0 | X96: =ROUND(CY96,2) -> 10198.12 | Y96: =ROUND(CZ96,2) -> 5212.37 | AA96: 56505405 | AB96: =ROUND((AC96+AD96+AF96),6) -> 2.772 | AC96: =ROUND((ES96),6) -> 0 | AD96: =ROUND(((((ET96*1.1))-((EU96*1.1)))+AE96),6) -> 0 | AE96: =ROUND(((EU96*1.1)),6) -> 0 | AF96: =ROUND(((EV96*1.1)),6) -> 2.772 | AG96: =ROUND((AP96),6) -> 0 | AH96: =((EW96*1.1)) -> 0.242 | AI96: =((EX96*1.1)) -> 0 | AJ96: =(AS96) -> 0 | AK96: 2.52 | AL96: 0 | AM96: 0 | AN96: 0 | AO96: 2.52 | AP96: 0 | AQ96: 0.22 | AR96: 0 | AS96: 0 | AT96: 90 | AU96: 46 | AV96: 1.047 | AW96: 1 | AZ96: 1 | BA96: 54.99 | BB96: 1 | BC96: 1 | BH96: 0 | BI96: 2 | BJ96: ТСН-2001.4 Доп. 67, Сб. 11, т. 14, поз. 1 | BM96: 72 | BN96: 0 | BO96: 4.11-14-1 | BP96: 1 | BQ96: 40 | BR96: 0 | BS96: 54.99 | BT96: 1 | BU96: 1 | BV96: 1 | BW96: 1 | BX96: 1 | BZ96: 90 | CA96: 46 | CE96: 30 | CF96: 0 | CG96: 0 | CM96: 0 | CO96: 0 | CP96: =(P96+Q96+S96) -> 11331.24 | CQ96: =ROUND((ROUND((AC96*AW96*1),2)*BC96),2) -> 0 | CR96: =(ROUND((ROUND((((ET96*1.1))*AV96*1),2)*BB96),2)+ROUND((ROUND(((AE96-((EU96*1.1)))*AV96*1),2)*BS96),2)) -> 0 | CS96: =ROUND((ROUND((AE96*AV96*1),2)*BS96),2) -> 0 | CT96: =ROUND((ROUND((AF96*AV96*1),2)*BA96),2) -> 159.47 | CU96: =AG96 -> 0 | CV96: =(AH96*AV96) -> 0.253374 | CW96: =AI96 -> 0 | CX96: =AJ96 -> 0 | CY96: =(((S96+R96)*AT96)/100) -> 10198.116 | CZ96: =(((S96+R96)*AU96)/100) -> 5212.3704 | DE96: *1,1 | DF96: *1,1 | DG96: *1,1 | DI96: *1,1 | DJ96: *1,1 | DN96: 0 | DO96: 0 | DP96: 1 | DQ96: 1 | DU96: 1013 | DV96: 1 разъем | DW96: 1 разъем | DX96: 1 | EE96: 58162634 | EF96: 40 | EG96: Монтаж оборудования | EH96: 0 | EJ96: 2 | EK96: 72 | EL96: ТСН-2001.4-11. Приборы и средства автоматизации и вычислительной техники | EM96: ТСН-2001.4-11-1 | EO96: Поправка: Гл.12.Прил.8.п.8. 5_12.00.01.11.003 | EQ96: 0 | ER96: 2.52 | ES96: 0 | ET96: 0 | EU96: 0 | EV96: 2.52 | EW96: 0.22 | EX96: 0 | EY96: 0 | FQ96: 0 | FR96: 0 | FS96: 0 | FX96: 90 | FY96: 46 | GD96: 1 | GF96: 1774518925 | GG96: 2 | GH96: 1 | GI96: 2 | GJ96: 0 | GK96: 0 | GL96: =ROUND(IF(AND(BH96=3,BI96=3,FS96<>0),P96,0),2) -> 0 | GM96: =ROUND(O96+X96+Y96,2)+GX96 -> 26741.73 | GN96: =IF(OR(BI96=0,BI96=1),GM96-GX96,0) -> 0 | GO96: =IF(BI96=2,GM96-GX96,0) -> 26741.73 | GP96: =IF(BI96=4,GM96-GX96,0) -> 0 | GR96: 0 | GS96: 3 | GT96: 0 | GV96: =ROUND((GT96),6) -> 0 | GW96: 1 | GX96: =ROUND(HC96*I96,2) -> 0 | HA96: 0 | HB96: 0 | HC96: =GV96*GW96 -> 0 | HS96: 0 | IK96: 0
A97: 18 | B97: 1 | E97: 5,1 | F97: КА 4 | G97: Шнур питания для вент. панели IEC 320 C14 | H97: шт. | I97: =I95*J97 -> 7 | J97: 0.098591549 | K97: 0.09859155 | O97: =ROUND(CP97,2) -> 391.44 | P97: =ROUND((ROUND((AC97*AW97*I97),2)*BC97),2) -> 391.44 | Q97: =(ROUND((ROUND(((ET97)*AV97*I97),2)*BB97),2)+ROUND((ROUND(((AE97-(EU97))*AV97*I97),2)*BS97),2)) -> 0 | R97: =ROUND((ROUND((AE97*AV97*I97),2)*BS97),2) -> 0 | S97: =ROUND((ROUND((AF97*AV97*I97),2)*BA97),2) -> 0 | T97: =ROUND(CU97*I97,2) -> 0 | U97: =CV97*I97 -> 0 | V97: =CW97*I97 -> 0 | W97: =ROUND(CX97*I97,2) -> 0 | X97: =ROUND(CY97,2) -> 0 | Y97: =ROUND(CZ97,2) -> 0 | AA97: 56505403 | AB97: =ROUND((AC97+AD97+AF97),6) -> 55.92 | AC97: =ROUND((ES97),6) -> 55.92 | AD97: =ROUND((((ET97)-(EU97))+AE97),6) -> 0 | AE97: =ROUND((EU97),6) -> 0 | AF97: =ROUND((EV97),6) -> 0 | AG97: =ROUND((AP97),6) -> 0 | AH97: =(EW97) -> 0 | AI97: =(EX97) -> 0 | AJ97: =(AS97) -> 0 | AK97: 55.92 | AL97: 55.92 | AM97: 0 | AN97: 0 | AO97: 0 | AP97: 0 | AQ97: 0 | AR97: 0 | AS97: 0 | AT97: 90 | AU97: 46 | AV97: 1 | AW97: 1 | AZ97: 1 | BA97: 1 | BB97: 1 | BC97: 1 | BH97: 3 | BI97: 2 | BM97: 72 | BN97: 0 | BP97: 0 | BQ97: 40 | BR97: 0 | BS97: 1 | BT97: 1 | BU97: 1 | BV97: 1 | BW97: 1 | BX97: 1 | BZ97: 90 | CA97: 46 | CE97: 30 | CF97: 0 | CG97: 0 | CM97: 0 | CO97: 0 | CP97: =(P97+Q97+S97) -> 391.44 | CQ97: =ROUND((ROUND((AC97*AW97*1),2)*BC97),2) -> 55.92 | CR97: =(ROUND((ROUND(((ET97)*AV97*1),2)*BB97),2)+ROUND((ROUND(((AE97-(EU97))*AV97*1),2)*BS97),2)) -> 0 | CS97: =ROUND((ROUND((AE97*AV97*1),2)*BS97),2) -> 0 | CT97: =ROUND((ROUND((AF97*AV97*1),2)*BA97),2) -> 0 | CU97: =AG97 -> 0 | CV97: =(AH97*AV97) -> 0 | CW97: =AI97 -> 0 | CX97: =AJ97 -> 0 | CY97: =(((S97+R97)*AT97)/100) -> 0 | CZ97: =(((S97+R97)*AU97)/100) -> 0 | DN97: 0 | DO97: 0 | DP97: 1 | DQ97: 1 | DU97: 1010 | DV97: шт. | DW97: шт. | DX97: 1 | EE97: 58162634 | EF97: 40 | EG97: Монтаж оборудования | EH97: 0 | EJ97: 2 | EK97: 72 | EL97: ТСН-2001.4-11. Приборы и средства автоматизации и вычислительной техники | EM97: ТСН-2001.4-11-1 | EQ97: 0 | ER97: 0 | ES97: 55.92 | ET97: 0 | EU97: 0 | EV97: 0 | EW97: 0 | EX97: 0 | FQ97: 0 | FR97: 0 | FS97: 0 | FX97: 90 | FY97: 46 | GA97: [650 / 1,2 / 9,88] + 2% Заг.скл | GD97: 1 | GF97: 1530715677 | GG97: 2 | GH97: 4 | GI97: -2 | GJ97: 0 | GK97: 0 | GL97: =ROUND(IF(AND(BH97=3,BI97=3,FS97<>0),P97,0),2) -> 0 | GM97: =ROUND(O97+X97+Y97,2)+GX97 -> 391.44 | GN97: =IF(OR(BI97=0,BI97=1),GM97-GX97,0) -> 0 | GO97: =IF(BI97=2,GM97-GX97,0) -> 391.44 | GP97: =IF(BI97=4,GM97-GX97,0) -> 0 | GR97: 0 | GS97: 2 | GT97: 0 | GV97: =ROUND((GT97),6) -> 0 | GW97: 1 | GX97: =ROUND(HC97*I97,2) -> 0 | HA97: 0 | HB97: 0 | HC97: =GV97*GW97 -> 0 | HE97: 0 | HF97: 2 | HS97: 0 | IK97: 0
A98: 18 | B98: 1 | E98: 5,1 | F98: КА 4 | G98: Шнур питания для вент. панели IEC 320 C14 | H98: шт. | I98: =I96*J98 -> 7 | J98: 0.098591549 | K98: 0.09859155 | O98: =ROUND(CP98,2) -> 3867.43 | P98: =ROUND((ROUND((AC98*AW98*I98),2)*BC98),2) -> 3867.43 | Q98: =(ROUND((ROUND(((ET98)*AV98*I98),2)*BB98),2)+ROUND((ROUND(((AE98-(EU98))*AV98*I98),2)*BS98),2)) -> 0 | R98: =ROUND((ROUND((AE98*AV98*I98),2)*BS98),2) -> 0 | S98: =ROUND((ROUND((AF98*AV98*I98),2)*BA98),2) -> 0 | T98: =ROUND(CU98*I98,2) -> 0 | U98: =CV98*I98 -> 0 | V98: =CW98*I98 -> 0 | W98: =ROUND(CX98*I98,2) -> 0 | X98: =ROUND(CY98,2) -> 0 | Y98: =ROUND(CZ98,2) -> 0 | AA98: 56505405 | AB98: =ROUND((AC98+AD98+AF98),6) -> 55.92 | AC98: =ROUND((ES98),6) -> 55.92 | AD98: =ROUND((((ET98)-(EU98))+AE98),6) -> 0 | AE98: =ROUND((EU98),6) -> 0 | AF98: =ROUND((EV98),6) -> 0 | AG98: =ROUND((AP98),6) -> 0 | AH98: =(EW98) -> 0 | AI98: =(EX98) -> 0 | AJ98: =(AS98) -> 0 | AK98: 55.92 | AL98: 55.92 | AM98: 0 | AN98: 0 | AO98: 0 | AP98: 0 | AQ98: 0 | AR98: 0 | AS98: 0 | AT98: 90 | AU98: 46 | AV98: 1 | AW98: 1 | AZ98: 1 | BA98: 1 | BB98: 1 | BC98: 9.88 | BH98: 3 | BI98: 2 | BM98: 72 | BN98: 0 | BP98: 0 | BQ98: 40 | BR98: 0 | BS98: 1 | BT98: 1 | BU98: 1 | BV98: 1 | BW98: 1 | BX98: 1 | BZ98: 90 | CA98: 46 | CE98: 30 | CF98: 0 | CG98: 0 | CM98: 0 | CO98: 0 | CP98: =(P98+Q98+S98) -> 3867.43 | CQ98: =ROUND((ROUND((AC98*AW98*1),2)*BC98),2) -> 552.49 | CR98: =(ROUND((ROUND(((ET98)*AV98*1),2)*BB98),2)+ROUND((ROUND(((AE98-(EU98))*AV98*1),2)*BS98),2)) -> 0 | CS98: =ROUND((ROUND((AE98*AV98*1),2)*BS98),2) -> 0 | CT98: =ROUND((ROUND((AF98*AV98*1),2)*BA98),2) -> 0 | CU98: =AG98 -> 0 | CV98: =(AH98*AV98) -> 0 | CW98: =AI98 -> 0 | CX98: =AJ98 -> 0 | CY98: =(((S98+R98)*AT98)/100) -> 0 | CZ98: =(((S98+R98)*AU98)/100) -> 0 | DN98: 0 | DO98: 0 | DP98: 1 | DQ98: 1 | DU98: 1010 | DV98: шт. | DW98: шт. | DX98: 1 | EE98: 58162634 | EF98: 40 | EG98: Монтаж оборудования | EH98: 0 | EJ98: 2 | EK98: 72 | EL98: ТСН-2001.4-11. Приборы и средства автоматизации и вычислительной техники | EM98: ТСН-2001.4-11-1 | EQ98: 0 | ER98: 55.92 | ES98: 55.92 | ET98: 0 | EU98: 0 | EV98: 0 | EW98: 0 | EX98: 0 | EZ98: 5 | FC98: 1 | FD98: 18 | FF98: 650 | FQ98: 0 | FR98: 0 | FS98: 0 | FX98: 90 | FY98: 46 | GA98: [650 / 1,2 / 9,88] + 2% Заг.скл | GD98: 1 | GF98: 1530715677 | GG98: 2 | GH98: 3 | GI98: 5 | GJ98: 0 | GK98: 0 | GL98: =ROUND(IF(AND(BH98=3,BI98=3,FS98<>0),P98,0),2) -> 0 | GM98: =ROUND(O98+X98+Y98,2)+GX98 -> 3867.43 | GN98: =IF(OR(BI98=0,BI98=1),GM98-GX98,0) -> 0 | GO98: =IF(BI98=2,GM98-GX98,0) -> 3867.43 | GP98: =IF(BI98=4,GM98-GX98,0) -> 0 | GR98: 1 | GS98: 1 | GT98: 0 | GV98: =ROUND((GT98),6) -> 0 | GW98: 1 | GX98: =ROUND(HC98*I98,2) -> 0 | HA98: 0 | HB98: 0 | HC98: =GV98*GW98 -> 0 | HE98: 0 | HF98: 2 | HS98: 0 | IK98: 0
A99: 18 | B99: 1 | E99: 5,2 | F99: КА 12 | G99: Набор nроводов заземленuя, 4 nровода 250ммх4мм2, 4 nровода, 150мм х4мм2 60A-14-13GR | H99: шт. | I99: =I95*J99 -> 8 | J99: 0.11267606 | K99: 0.11267606 | O99: =ROUND(CP99,2) -> 1316.72 | P99: =ROUND((ROUND((AC99*AW99*I99),2)*BC99),2) -> 1316.72 | Q99: =(ROUND((ROUND(((ET99)*AV99*I99),2)*BB99),2)+ROUND((ROUND(((AE99-(EU99))*AV99*I99),2)*BS99),2)) -> 0 | R99: =ROUND((ROUND((AE99*AV99*I99),2)*BS99),2) -> 0 | S99: =ROUND((ROUND((AF99*AV99*I99),2)*BA99),2) -> 0 | T99: =ROUND(CU99*I99,2) -> 0 | U99: =CV99*I99 -> 0 | V99: =CW99*I99 -> 0 | W99: =ROUND(CX99*I99,2) -> 0 | X99: =ROUND(CY99,2) -> 0 | Y99: =ROUND(CZ99,2) -> 0 | AA99: 56505403 | AB99: =ROUND((AC99+AD99+AF99),6) -> 164.59 | AC99: =ROUND((ES99),6) -> 164.59 | AD99: =ROUND((((ET99)-(EU99))+AE99),6) -> 0 | AE99: =ROUND((EU99),6) -> 0 | AF99: =ROUND((EV99),6) -> 0 | AG99: =ROUND((AP99),6) -> 0 | AH99: =(EW99) -> 0 | AI99: =(EX99) -> 0 | AJ99: =(AS99) -> 0 | AK99: 164.59 | AL99: 164.59 | AM99: 0 | AN99: 0 | AO99: 0 | AP99: 0 | AQ99: 0 | AR99: 0 | AS99: 0 | AT99: 90 | AU99: 46 | AV99: 1 | AW99: 1 | AZ99: 1 | BA99: 1 | BB99: 1 | BC99: 1 | BH99: 3 | BI99: 2 | BM99: 72 | BN99: 0 | BP99: 0 | BQ99: 40 | BR99: 0 | BS99: 1 | BT99: 1 | BU99: 1 | BV99: 1 | BW99: 1 | BX99: 1 | BZ99: 90 | CA99: 46 | CE99: 30 | CF99: 0 | CG99: 0 | CM99: 0 | CO99: 0 | CP99: =(P99+Q99+S99) -> 1316.72 | CQ99: =ROUND((ROUND((AC99*AW99*1),2)*BC99),2) -> 164.59 | CR99: =(ROUND((ROUND(((ET99)*AV99*1),2)*BB99),2)+ROUND((ROUND(((AE99-(EU99))*AV99*1),2)*BS99),2)) -> 0 | CS99: =ROUND((ROUND((AE99*AV99*1),2)*BS99),2) -> 0 | CT99: =ROUND((ROUND((AF99*AV99*1),2)*BA99),2) -> 0 | CU99: =AG99 -> 0 | CV99: =(AH99*AV99) -> 0 | CW99: =AI99 -> 0 | CX99: =AJ99 -> 0 | CY99: =(((S99+R99)*AT99)/100) -> 0 | CZ99: =(((S99+R99)*AU99)/100) -> 0 | DN99: 0 | DO99: 0 | DP99: 1 | DQ99: 1 | DU99: 1010 | DV99: шт. | DW99: шт. | DX99: 1 | EE99: 58162634 | EF99: 40 | EG99: Монтаж оборудования | EH99: 0 | EJ99: 2 | EK99: 72 | EL99: ТСН-2001.4-11. Приборы и средства автоматизации и вычислительной техники | EM99: ТСН-2001.4-11-1 | EQ99: 0 | ER99: 0 | ES99: 164.59 | ET99: 0 | EU99: 0 | EV99: 0 | EW99: 0 | EX99: 0 | FQ99: 0 | FR99: 0 | FS99: 0 | FX99: 90 | FY99: 46 | GA99: [1 913,04 / 1,2 / 9,88] + 2% Заг.скл | GD99: 1 | GF99: -502968707 | GG99: 2 | GH99: 4 | GI99: -2 | GJ99: 0 | GK99: 0 | GL99: =ROUND(IF(AND(BH99=3,BI99=3,FS99<>0),P99,0),2) -> 0 | GM99: =ROUND(O99+X99+Y99,2)+GX99 -> 1316.72 | GN99: =IF(OR(BI99=0,BI99=1),GM99-GX99,0) -> 0 | GO99: =IF(BI99=2,GM99-GX99,0) -> 1316.72 | GP99: =IF(BI99=4,GM99-GX99,0) -> 0 | GR99: 0 | GS99: 2 | GT99: 0 | GV99: =ROUND((GT99),6) -> 0 | GW99: 1 | GX99: =ROUND(HC99*I99,2) -> 0 | HA99: 0 | HB99: 0 | HC99: =GV99*GW99 -> 0 | HE99: 0 | HF99: 2 | HS99: 0 | IK99: 0
A100: 18 | B100: 1 | E100: 5,2 | F100: КА 12 | G100: Набор nроводов заземленuя, 4 nровода 250ммх4мм2, 4 nровода, 150мм х4мм2 60A-14-13GR | H100: шт. | I100: =I96*J100 -> 8 | J100: 0.11267606 | K100: 0.11267606 | O100: =ROUND(CP100,2) -> 13009.19 | P100: =ROUND((ROUND((AC100*AW100*I100),2)*BC100),2) -> 13009.19 | Q100: =(ROUND((ROUND(((ET100)*AV100*I100),2)*BB100),2)+ROUND((ROUND(((AE100-(EU100))*AV100*I100),2)*BS100),2)) -> 0 | R100: =ROUND((ROUND((AE100*AV100*I100),2)*BS100),2) -> 0 | S100: =ROUND((ROUND((AF100*AV100*I100),2)*BA100),2) -> 0 | T100: =ROUND(CU100*I100,2) -> 0 | U100: =CV100*I100 -> 0 | V100: =CW100*I100 -> 0 | W100: =ROUND(CX100*I100,2) -> 0 | X100: =ROUND(CY100,2) -> 0 | Y100: =ROUND(CZ100,2) -> 0 | AA100: 56505405 | AB100: =ROUND((AC100+AD100+AF100),6) -> 164.59 | AC100: =ROUND((ES100),6) -> 164.59 | AD100: =ROUND((((ET100)-(EU100))+AE100),6) -> 0 | AE100: =ROUND((EU100),6) -> 0 | AF100: =ROUND((EV100),6) -> 0 | AG100: =ROUND((AP100),6) -> 0 | AH100: =(EW100) -> 0 | AI100: =(EX100) -> 0 | AJ100: =(AS100) -> 0 | AK100: 164.59 | AL100: 164.59 | AM100: 0 | AN100: 0 | AO100: 0 | AP100: 0 | AQ100: 0 | AR100: 0 | AS100: 0 | AT100: 90 | AU100: 46 | AV100: 1 | AW100: 1 | AZ100: 1 | BA100: 1 | BB100: 1 | BC100: 9.88 | BH100: 3 | BI100: 2 | BM100: 72 | BN100: 0 | BP100: 0 | BQ100: 40 | BR100: 0 | BS100: 1 | BT100: 1 | BU100: 1 | BV100: 1 | BW100: 1 | BX100: 1 | BZ100: 90 | CA100: 46 | CE100: 30 | CF100: 0 | CG100: 0 | CM100: 0 | CO100: 0 | CP100: =(P100+Q100+S100) -> 13009.19 | CQ100: =ROUND((ROUND((AC100*AW100*1),2)*BC100),2) -> 1626.15 | CR100: =(ROUND((ROUND(((ET100)*AV100*1),2)*BB100),2)+ROUND((ROUND(((AE100-(EU100))*AV100*1),2)*BS100),2)) -> 0 | CS100: =ROUND((ROUND((AE100*AV100*1),2)*BS100),2) -> 0 | CT100: =ROUND((ROUND((AF100*AV100*1),2)*BA100),2) -> 0 | CU100: =AG100 -> 0 | CV100: =(AH100*AV100) -> 0 | CW100: =AI100 -> 0 | CX100: =AJ100 -> 0 | CY100: =(((S100+R100)*AT100)/100) -> 0 | CZ100: =(((S100+R100)*AU100)/100) -> 0 | DN100: 0 | DO100: 0 | DP100: 1 | DQ100: 1 | DU100: 1010 | DV100: шт. | DW100: шт. | DX100: 1 | EE100: 58162634 | EF100: 40 | EG100: Монтаж оборудования | EH100: 0 | EJ100: 2 | EK100: 72 | EL100: ТСН-2001.4-11. Приборы и средства автоматизации и вычислительной техники | EM100: ТСН-2001.4-11-1 | EQ100: 0 | ER100: 164.59 | ES100: 164.59 | ET100: 0 | EU100: 0 | EV100: 0 | EW100: 0 | EX100: 0 | EZ100: 5 | FC100: 1 | FD100: 18 | FF100: 1913.04 | FQ100: 0 | FR100: 0 | FS100: 0 | FX100: 90 | FY100: 46 | GA100: [1 913,04 / 1,2 / 9,88] + 2% Заг.скл | GD100: 1 | GF100: -502968707 | GG100: 2 | GH100: 3 | GI100: 5 | GJ100: 0 | GK100: 0 | GL100: =ROUND(IF(AND(BH100=3,BI100=3,FS100<>0),P100,0),2) -> 0 | GM100: =ROUND(O100+X100+Y100,2)+GX100 -> 13009.19 | GN100: =IF(OR(BI100=0,BI100=1),GM100-GX100,0) -> 0 | GO100: =IF(BI100=2,GM100-GX100,0) -> 13009.19 | GP100: =IF(BI100=4,GM100-GX100,0) -> 0 | GR100: 1 | GS100: 1 | GT100: 0 | GV100: =ROUND((GT100),6) -> 0 | GW100: 1 | GX100: =ROUND(HC100*I100,2) -> 0 | HA100: 0 | HB100: 0 | HC100: =GV100*GW100 -> 0 | HE100: 0 | HF100: 2 | HS100: 0 | IK100: 0
A101: 17 | B101: 1 | D101: =ROW(EtalonRes!A37) -> 37 | E101: 6 | F101: 4.11-12-1 | G101: Установка съемных и выдвижных блоков (модулей, ячеек, ТЭЗ) массой до 5 кг | H101: 1 ШТ. | I101: =ROUND(7+7+7+7,9) -> 28 | J101: 0 | K101: =ROUND(7+7+7+7,9) -> 28 | O101: =ROUND(CP101,2) -> 391.8 | P101: =ROUND((ROUND((AC101*AW101*I101),2)*BC101),2) -> 0 | Q101: =(ROUND((ROUND((((ET101*1.1))*AV101*I101),2)*BB101),2)+ROUND((ROUND(((AE101-((EU101*1.1)))*AV101*I101),2)*BS101),2)) -> 16.12 | R101: =ROUND((ROUND((AE101*AV101*I101),2)*BS101),2) -> 2.58 | S101: =ROUND((ROUND((AF101*AV101*I101),2)*BA101),2) -> 375.68 | T101: =ROUND(CU101*I101,2) -> 0 | U101: =CV101*I101 -> 33.215028 | V101: =CW101*I101 -> 0 | W101: =ROUND(CX101*I101,2) -> 0 | X101: =ROUND(CY101,2) -> 340.43 | Y101: =ROUND(CZ101,2) -> 174 | AA101: 56505403 | AB101: =ROUND((AC101+AD101+AF101),6) -> 13.365 | AC101: =ROUND((ES101),6) -> 0 | AD101: =ROUND(((((ET101*1.1))-((EU101*1.1)))+AE101),6) -> 0.55 | AE101: =ROUND(((EU101*1.1)),6) -> 0.088 | AF101: =ROUND(((EV101*1.1)),6) -> 12.815 | AG101: =ROUND((AP101),6) -> 0 | AH101: =((EW101*1.1)) -> 1.133 | AI101: =((EX101*1.1)) -> 0 | AJ101: =(AS101) -> 0 | AK101: 12.15 | AL101: 0 | AM101: 0.5 | AN101: 0.08 | AO101: 11.65 | AP101: 0 | AQ101: 1.03 | AR101: 0 | AS101: 0 | AT101: 90 | AU101: 46 | AV101: 1.047 | AW101: 1 | AZ101: 1 | BA101: 1 | BB101: 1 | BC101: 1 | BH101: 0 | BI101: 2 | BJ101: ТСН-2001.4 Доп. 68, Сб. 11, т. 12, поз. 1 | BM101: 72 | BN101: 0 | BO101: 4.11-12-1 | BP101: 1 | BQ101: 40 | BR101: 0 | BS101: 1 | BT101: 1 | BU101: 1 | BV101: 1 | BW101: 1 | BX101: 1 | BZ101: 90 | CA101: 46 | CE101: 30 | CF101: 0 | CG101: 0 | CM101: 0 | CO101: 0 | CP101: =(P101+Q101+S101) -> 391.8 | CQ101: =ROUND((ROUND((AC101*AW101*1),2)*BC101),2) -> 0 | CR101: =(ROUND((ROUND((((ET101*1.1))*AV101*1),2)*BB101),2)+ROUND((ROUND(((AE101-((EU101*1.1)))*AV101*1),2)*BS101),2)) -> 0.58 | CS101: =ROUND((ROUND((AE101*AV101*1),2)*BS101),2) -> 0.09 | CT101: =ROUND((ROUND((AF101*AV101*1),2)*BA101),2) -> 13.42 | CU101: =AG101 -> 0 | CV101: =(AH101*AV101) -> 1.186251 | CW101: =AI101 -> 0 | CX101: =AJ101 -> 0 | CY101: =(((S101+R101)*AT101)/100) -> 340.434 | CZ101: =(((S101+R101)*AU101)/100) -> 173.9996 | DE101: *1,1 | DF101: *1,1 | DG101: *1,1 | DI101: *1,1 | DJ101: *1,1 | DN101: 0 | DO101: 0 | DP101: 1 | DQ101: 1 | DU101: 1013 | DV101: 1 ШТ. | DW101: 1 ШТ. | DX101: 1 | EE101: 58162634 | EF101: 40 | EG101: Монтаж оборудования | EH101: 0 | EJ101: 2 | EK101: 72 | EL101: ТСН-2001.4-11. Приборы и средства автоматизации и вычислительной техники | EM101: ТСН-2001.4-11-1 | EO101: Поправка: Гл.12.Прил.8.п.8. 5_12.00.01.11.003 | EQ101: 0 | ER101: 12.15 | ES101: 0 | ET101: 0.5 | EU101: 0.08 | EV101: 11.65 | EW101: 1.03 | EX101: 0 | EY101: 0 | FQ101: 0 | FR101: 0 | FS101: 0 | FX101: 90 | FY101: 46 | GD101: 1 | GF101: 1708693888 | GG101: 2 | GH101: 1 | GI101: 2 | GJ101: 0 | GK101: 0 | GL101: =ROUND(IF(AND(BH101=3,BI101=3,FS101<>0),P101,0),2) -> 0 | GM101: =ROUND(O101+X101+Y101,2)+GX101 -> 906.23 | GN101: =IF(OR(BI101=0,BI101=1),GM101-GX101,0) -> 0 | GO101: =IF(BI101=2,GM101-GX101,0) -> 906.23 | GP101: =IF(BI101=4,GM101-GX101,0) -> 0 | GR101: 0 | GS101: 3 | GT101: 0 | GV101: =ROUND((GT101),6) -> 0 | GW101: 1 | GX101: =ROUND(HC101*I101,2) -> 0 | HA101: 0 | HB101: 0 | HC101: =GV101*GW101 -> 0 | HS101: 0 | IK101: 0
A102: 17 | B102: 1 | D102: =ROW(EtalonRes!A40) -> 40 | E102: 6 | F102: 4.11-12-1 | G102: Установка съемных и выдвижных блоков (модулей, ячеек, ТЭЗ) массой до 5 кг | H102: 1 ШТ. | I102: =ROUND(7+7+7+7,9) -> 28 | J102: 0 | K102: =ROUND(7+7+7+7,9) -> 28 | O102: =ROUND(CP102,2) -> 20920.75 | P102: =ROUND((ROUND((AC102*AW102*I102),2)*BC102),2) -> 0 | Q102: =(ROUND((ROUND((((ET102*1.1))*AV102*I102),2)*BB102),2)+ROUND((ROUND(((AE102-((EU102*1.1)))*AV102*I102),2)*BS102),2)) -> 262.11 | R102: =ROUND((ROUND((AE102*AV102*I102),2)*BS102),2) -> 141.87 | S102: =ROUND((ROUND((AF102*AV102*I102),2)*BA102),2) -> 20658.64 | T102: =ROUND(CU102*I102,2) -> 0 | U102: =CV102*I102 -> 33.215028 | V102: =CW102*I102 -> 0 | W102: =ROUND(CX102*I102,2) -> 0 | X102: =ROUND(CY102,2) -> 18720.46 | Y102: =ROUND(CZ102,2) -> 9568.23 | AA102: 56505405 | AB102: =ROUND((AC102+AD102+AF102),6) -> 13.365 | AC102: =ROUND((ES102),6) -> 0 | AD102: =ROUND(((((ET102*1.1))-((EU102*1.1)))+AE102),6) -> 0.55 | AE102: =ROUND(((EU102*1.1)),6) -> 0.088 | AF102: =ROUND(((EV102*1.1)),6) -> 12.815 | AG102: =ROUND((AP102),6) -> 0 | AH102: =((EW102*1.1)) -> 1.133 | AI102: =((EX102*1.1)) -> 0 | AJ102: =(AS102) -> 0 | AK102: 12.15 | AL102: 0 | AM102: 0.5 | AN102: 0.08 | AO102: 11.65 | AP102: 0 | AQ102: 1.03 | AR102: 0 | AS102: 0 | AT102: 90 | AU102: 46 | AV102: 1.047 | AW102: 1 | AZ102: 1 | BA102: 54.99 | BB102: 16.26 | BC102: 1 | BH102: 0 | BI102: 2 | BJ102: ТСН-2001.4 Доп. 68, Сб. 11, т. 12, поз. 1 | BM102: 72 | BN102: 0 | BO102: 4.11-12-1 | BP102: 1 | BQ102: 40 | BR102: 0 | BS102: 54.99 | BT102: 1 | BU102: 1 | BV102: 1 | BW102: 1 | BX102: 1 | BZ102: 90 | CA102: 46 | CE102: 30 | CF102: 0 | CG102: 0 | CM102: 0 | CO102: 0 | CP102: =(P102+Q102+S102) -> 20920.75 | CQ102: =ROUND((ROUND((AC102*AW102*1),2)*BC102),2) -> 0 | CR102: =(ROUND((ROUND((((ET102*1.1))*AV102*1),2)*BB102),2)+ROUND((ROUND(((AE102-((EU102*1.1)))*AV102*1),2)*BS102),2)) -> 9.43 | CS102: =ROUND((ROUND((AE102*AV102*1),2)*BS102),2) -> 4.95 | CT102: =ROUND((ROUND((AF102*AV102*1),2)*BA102),2) -> 737.97 | CU102: =AG102 -> 0 | CV102: =(AH102*AV102) -> 1.186251 | CW102: =AI102 -> 0 | CX102: =AJ102 -> 0 | CY102: =(((S102+R102)*AT102)/100) -> 18720.459 | CZ102: =(((S102+R102)*AU102)/100) -> 9568.2346 | DE102: *1,1 | DF102: *1,1 | DG102: *1,1 | DI102: *1,1 | DJ102: *1,1 | DN102: 0 | DO102: 0 | DP102: 1 | DQ102: 1 | DU102: 1013 | DV102: 1 ШТ. | DW102: 1 ШТ. | DX102: 1 | EE102: 58162634 | EF102: 40 | EG102: Монтаж оборудования | EH102: 0 | EJ102: 2 | EK102: 72 | EL102: ТСН-2001.4-11. Приборы и средства автоматизации и вычислительной техники | EM102: ТСН-2001.4-11-1 | EO102: Поправка: Гл.12.Прил.8.п.8. 5_12.00.01.11.003 | EQ102: 0 | ER102: 12.15 | ES102: 0 | ET102: 0.5 | EU102: 0.08 | EV102: 11.65 | EW102: 1.03 | EX102: 0 | EY102: 0 | FQ102: 0 | FR102: 0 | FS102: 0 | FX102: 90 | FY102: 46 | GD102: 1 | GF102: 1708693888 | GG102: 2 | GH102: 1 | GI102: 2 | GJ102: 0 | GK102: 0 | GL102: =ROUND(IF(AND(BH102=3,BI102=3,FS102<>0),P102,0),2) -> 0 | GM102: =ROUND(O102+X102+Y102,2)+GX102 -> 49209.44 | GN102: =IF(OR(BI102=0,BI102=1),GM102-GX102,0) -> 0 | GO102: =IF(BI102=2,GM102-GX102,0) -> 49209.44 | GP102: =IF(BI102=4,GM102-GX102,0) -> 0 | GR102: 0 | GS102: 3 | GT102: 0 | GV102: =ROUND((GT102),6) -> 0 | GW102: 1 | GX102: =ROUND(HC102*I102,2) -> 0 | HA102: 0 | HB102: 0 | HC102: =GV102*GW102 -> 0 | HS102: 0 | IK102: 0
A103: 18 | B103: 1 | E103: 6,1 | F103: КА 3 | G103: Вентиляторная панель 60А-91-11-30ВL | H103: шт. | I103: =I101*J103 -> 7 | J103: 0.25 | K103: 0.25 | O103: =ROUND(CP103,2) -> 22491.21 | P103: =ROUND((ROUND((AC103*I103),2)*BC103),2) -> 22491.21 | Q103: =(ROUND((ROUND(((ET103)*AV103*I103),2)*BB103),2)+ROUND((ROUND(((AE103-(EU103))*AV103*I103),2)*BS103),2)) -> 0 | R103: =ROUND((ROUND((AE103*AV103*I103),2)*BS103),2) -> 0 | S103: =ROUND((ROUND((AF103*AV103*I103),2)*BA103),2) -> 0 | T103: =ROUND(CU103*I103,2) -> 0 | U103: =CV103*I103 -> 0 | V103: =CW103*I103 -> 0 | W103: =ROUND(CX103*I103,2) -> 0 | X103: =ROUND(CY103,2) -> 0 | Y103: =ROUND(CZ103,2) -> 0 | AA103: 56505403 | AB103: =ROUND((AC103+AD103+AF103),6) -> 3213.03 | AC103: =ROUND((ES103),6) -> 3213.03 | AD103: =ROUND((((ET103)-(EU103))+AE103),6) -> 0 | AE103: =ROUND((EU103),6) -> 0 | AF103: =ROUND((EV103),6) -> 0 | AG103: =ROUND((AP103),6) -> 0 | AH103: =(EW103) -> 0 | AI103: =(EX103) -> 0 | AJ103: =(AS103) -> 0 | AK103: 3213.03 | AL103: 3213.03 | AM103: 0 | AN103: 0 | AO103: 0 | AP103: 0 | AQ103: 0 | AR103: 0 | AS103: 0 | AT103: 0 | AU103: 0 | AV103: 1 | AW103: 1 | AZ103: 1 | BA103: 1 | BB103: 1 | BC103: 1 | BH103: 3 | BI103: 3 | BM103: 746 | BN103: 0 | BP103: 0 | BQ103: 130 | BR103: 0 | BS103: 1 | BT103: 1 | BU103: 1 | BV103: 1 | BW103: 1 | BX103: 1 | BZ103: 90 | CA103: 46 | CE103: 30 | CF103: 0 | CG103: 0 | CM103: 0 | CO103: 0 | CP103: =(P103+Q103+S103) -> 22491.21 | CQ103: =ROUND((ROUND((AC103*1),2)*BC103),2) -> 3213.03 | CR103: =(ROUND((ROUND(((ET103)*AV103*1),2)*BB103),2)+ROUND((ROUND(((AE103-(EU103))*AV103*1),2)*BS103),2)) -> 0 | CS103: =ROUND((ROUND((AE103*AV103*1),2)*BS103),2) -> 0 | CT103: =ROUND((ROUND((AF103*AV103*1),2)*BA103),2) -> 0 | CU103: =AG103 -> 0 | CV103: =(AH103*AV103) -> 0 | CW103: =AI103 -> 0 | CX103: =AJ103 -> 0 | CY103: =(((S103+R103)*AT103)/100) -> 0 | CZ103: =(((S103+R103)*AU103)/100) -> 0 | DN103: 0 | DO103: 0 | DP103: 1 | DQ103: 1 | DU103: 1010 | DV103: шт. | DW103: шт. | DX103: 1 | EE103: 58162750 | EF103: 130 | EG103: Сметная стоимость оборудования | EH103: 0 | EJ103: 3 | EK103: 746 | EL103: ТСН-2001.13. Сметная стоимость оборудования | EM103: ТСН-2001.13 | EQ103: 0 | ER103: 0 | ES103: 3213.03 | ET103: 0 | EU103: 0 | EV103: 0 | EW103: 0 | EX103: 0 | FQ103: 0 | FR103: =P103 -> 22491.21 | FS103: 0 | FX103: 90 | FY103: 46 | GA103: [28 334 / 1,2 / 7,66] + 3% Трансп + 1,2% Заг.скл | GD103: 1 | GF103: 174995452 | GG103: 2 | GH103: 4 | GI103: -2 | GJ103: 0 | GK103: 0 | GL103: =ROUND(IF(AND(BH103=3,BI103=3,FS103<>0),P103,0),2) -> 0 | GM103: =ROUND(O103+X103+Y103,2)+GX103 -> 22491.21 | GN103: =IF(OR(BI103=0,BI103=1),GM103-GX103,0) -> 0 | GO103: =IF(BI103=2,GM103-GX103,0) -> 0 | GP103: =IF(BI103=4,GM103-GX103,0) -> 0 | GR103: 0 | GS103: 2 | GT103: 0 | GV103: =ROUND((GT103),6) -> 0 | GW103: 1 | GX103: =ROUND(HC103*I103,2) -> 0 | HA103: 0 | HB103: 0 | HC103: =GV103*GW103 -> 0 | HE103: 3 | HF103: 1,2 | HS103: 0 | IK103: 0
A104: 18 | B104: 1 | E104: 6,1 | F104: КА 3 | G104: Вентиляторная панель 60А-91-11-30ВL | H104: шт. | I104: =I102*J104 -> 7 | J104: 0.25 | K104: 0.25 | O104: =ROUND(CP104,2) -> 172282.67 | P104: =ROUND((ROUND((AC104*I104),2)*BC104),2) -> 172282.67 | Q104: =(ROUND((ROUND(((ET104)*AV104*I104),2)*BB104),2)+ROUND((ROUND(((AE104-(EU104))*AV104*I104),2)*BS104),2)) -> 0 | R104: =ROUND((ROUND((AE104*AV104*I104),2)*BS104),2) -> 0 | S104: =ROUND((ROUND((AF104*AV104*I104),2)*BA104),2) -> 0 | T104: =ROUND(CU104*I104,2) -> 0 | U104: =CV104*I104 -> 0 | V104: =CW104*I104 -> 0 | W104: =ROUND(CX104*I104,2) -> 0 | X104: =ROUND(CY104,2) -> 0 | Y104: =ROUND(CZ104,2) -> 0 | AA104: 56505405 | AB104: =ROUND((AC104+AD104+AF104),6) -> 3213.03 | AC104: =ROUND((ES104),6) -> 3213.03 | AD104: =ROUND((((ET104)-(EU104))+AE104),6) -> 0 | AE104: =ROUND((EU104),6) -> 0 | AF104: =ROUND((EV104),6) -> 0 | AG104: =ROUND((AP104),6) -> 0 | AH104: =(EW104) -> 0 | AI104: =(EX104) -> 0 | AJ104: =(AS104) -> 0 | AK104: 3213.03 | AL104: 3213.03 | AM104: 0 | AN104: 0 | AO104: 0 | AP104: 0 | AQ104: 0 | AR104: 0 | AS104: 0 | AT104: 0 | AU104: 0 | AV104: 1 | AW104: 1 | AZ104: 1 | BA104: 1 | BB104: 1 | BC104: 7.66 | BH104: 3 | BI104: 3 | BM104: 746 | BN104: 0 | BP104: 0 | BQ104: 130 | BR104: 0 | BS104: 1 | BT104: 1 | BU104: 1 | BV104: 1 | BW104: 1 | BX104: 1 | BZ104: 90 | CA104: 46 | CE104: 30 | CF104: 0 | CG104: 0 | CM104: 0 | CO104: 0 | CP104: =(P104+Q104+S104) -> 172282.67 | CQ104: =ROUND((ROUND((AC104*1),2)*BC104),2) -> 24611.81 | CR104: =(ROUND((ROUND(((ET104)*AV104*1),2)*BB104),2)+ROUND((ROUND(((AE104-(EU104))*AV104*1),2)*BS104),2)) -> 0 | CS104: =ROUND((ROUND((AE104*AV104*1),2)*BS104),2) -> 0 | CT104: =ROUND((ROUND((AF104*AV104*1),2)*BA104),2) -> 0 | CU104: =AG104 -> 0 | CV104: =(AH104*AV104) -> 0 | CW104: =AI104 -> 0 | CX104: =AJ104 -> 0 | CY104: =(((S104+R104)*AT104)/100) -> 0 | CZ104: =(((S104+R104)*AU104)/100) -> 0 | DN104: 0 | DO104: 0 | DP104: 1 | DQ104: 1 | DU104: 1010 | DV104: шт. | DW104: шт. | DX104: 1 | EE104: 58162750 | EF104: 130 | EG104: Сметная стоимость оборудования | EH104: 0 | EJ104: 3 | EK104: 746 | EL104: ТСН-2001.13. Сметная стоимость оборудования | EM104: ТСН-2001.13 | EQ104: 0 | ER104: 2437.64 | ES104: 3213.03 | ET104: 0 | EU104: 0 | EV104: 0 | EW104: 0 | EX104: 0 | EZ104: 5 | FC104: 1 | FD104: 18 | FF104: 28334 | FQ104: 0 | FR104: =P104 -> 172282.67 | FS104: 0 | FX104: 90 | FY104: 46 | GA104: [28 334 / 1,2 / 7,66] + 3% Трансп + 1,2% Заг.скл | GD104: 1 | GF104: 174995452 | GG104: 2 | GH104: 3 | GI104: 5 | GJ104: 0 | GK104: 0 | GL104: =ROUND(IF(AND(BH104=3,BI104=3,FS104<>0),P104,0),2) -> 0 | GM104: =ROUND(O104+X104+Y104,2)+GX104 -> 172282.67 | GN104: =IF(OR(BI104=0,BI104=1),GM104-GX104,0) -> 0 | GO104: =IF(BI104=2,GM104-GX104,0) -> 0 | GP104: =IF(BI104=4,GM104-GX104,0) -> 0 | GR104: 1 | GS104: 1 | GT104: 0 | GV104: =ROUND((GT104),6) -> 0 | GW104: 1 | GX104: =ROUND(HC104*I104,2) -> 0 | HA104: 0 | HB104: 0 | HC104: =GV104*GW104 -> 0 | HE104: 3 | HF104: 1,2 | HS104: 0 | IK104: 0
A105: 18 | B105: 1 | E105: 6,2 | F105: КА 5 | G105: Выдвижная полка для клавиатуры 60А-04-45-11BL | H105: шт. | I105: =I101*J105 -> 7 | J105: 0.25 | K105: 0.25 | O105: =ROUND(CP105,2) -> 3872.33 | P105: =ROUND((ROUND((AC105*AW105*I105),2)*BC105),2) -> 3872.33 | Q105: =(ROUND((ROUND(((ET105)*AV105*I105),2)*BB105),2)+ROUND((ROUND(((AE105-(EU105))*AV105*I105),2)*BS105),2)) -> 0 | R105: =ROUND((ROUND((AE105*AV105*I105),2)*BS105),2) -> 0 | S105: =ROUND((ROUND((AF105*AV105*I105),2)*BA105),2) -> 0 | T105: =ROUND(CU105*I105,2) -> 0 | U105: =CV105*I105 -> 0 | V105: =CW105*I105 -> 0 | W105: =ROUND(CX105*I105,2) -> 0 | X105: =ROUND(CY105,2) -> 0 | Y105: =ROUND(CZ105,2) -> 0 | AA105: 56505403 | AB105: =ROUND((AC105+AD105+AF105),6) -> 553.19 | AC105: =ROUND((ES105),6) -> 553.19 | AD105: =ROUND((((ET105)-(EU105))+AE105),6) -> 0 | AE105: =ROUND((EU105),6) -> 0 | AF105: =ROUND((EV105),6) -> 0 | AG105: =ROUND((AP105),6) -> 0 | AH105: =(EW105) -> 0 | AI105: =(EX105) -> 0 | AJ105: =(AS105) -> 0 | AK105: 553.19 | AL105: 553.19 | AM105: 0 | AN105: 0 | AO105: 0 | AP105: 0 | AQ105: 0 | AR105: 0 | AS105: 0 | AT105: 90 | AU105: 46 | AV105: 1 | AW105: 1 | AZ105: 1 | BA105: 1 | BB105: 1 | BC105: 1 | BH105: 3 | BI105: 2 | BM105: 72 | BN105: 0 | BP105: 0 | BQ105: 40 | BR105: 0 | BS105: 1 | BT105: 1 | BU105: 1 | BV105: 1 | BW105: 1 | BX105: 1 | BZ105: 90 | CA105: 46 | CE105: 30 | CF105: 0 | CG105: 0 | CM105: 0 | CO105: 0 | CP105: =(P105+Q105+S105) -> 3872.33 | CQ105: =ROUND((ROUND((AC105*AW105*1),2)*BC105),2) -> 553.19 | CR105: =(ROUND((ROUND(((ET105)*AV105*1),2)*BB105),2)+ROUND((ROUND(((AE105-(EU105))*AV105*1),2)*BS105),2)) -> 0 | CS105: =ROUND((ROUND((AE105*AV105*1),2)*BS105),2) -> 0 | CT105: =ROUND((ROUND((AF105*AV105*1),2)*BA105),2) -> 0 | CU105: =AG105 -> 0 | CV105: =(AH105*AV105) -> 0 | CW105: =AI105 -> 0 | CX105: =AJ105 -> 0 | CY105: =(((S105+R105)*AT105)/100) -> 0 | CZ105: =(((S105+R105)*AU105)/100) -> 0 | DN105: 0 | DO105: 0 | DP105: 1 | DQ105: 1 | DU105: 1010 | DV105: шт. | DW105: шт. | DX105: 1 | EE105: 58162634 | EF105: 40 | EG105: Монтаж оборудования | EH105: 0 | EJ105: 2 | EK105: 72 | EL105: ТСН-2001.4-11. Приборы и средства автоматизации и вычислительной техники | EM105: ТСН-2001.4-11-1 | EQ105: 0 | ER105: 0 | ES105: 553.19 | ET105: 0 | EU105: 0 | EV105: 0 | EW105: 0 | EX105: 0 | FQ105: 0 | FR105: 0 | FS105: 0 | FX105: 90 | FY105: 46 | GA105: [6 430 / 1,2 / 9,88] + 2% Заг.скл | GD105: 1 | GF105: 1122354003 | GG105: 2 | GH105: 4 | GI105: -2 | GJ105: 0 | GK105: 0 | GL105: =ROUND(IF(AND(BH105=3,BI105=3,FS105<>0),P105,0),2) -> 0 | GM105: =ROUND(O105+X105+Y105,2)+GX105 -> 3872.33 | GN105: =IF(OR(BI105=0,BI105=1),GM105-GX105,0) -> 0 | GO105: =IF(BI105=2,GM105-GX105,0) -> 3872.33 | GP105: =IF(BI105=4,GM105-GX105,0) -> 0 | GR105: 0 | GS105: 2 | GT105: 0 | GV105: =ROUND((GT105),6) -> 0 | GW105: 1 | GX105: =ROUND(HC105*I105,2) -> 0 | HA105: 0 | HB105: 0 | HC105: =GV105*GW105 -> 0 | HE105: 0 | HF105: 2 | HS105: 0 | IK105: 0
A106: 18 | B106: 1 | E106: 6,2 | F106: КА 5 | G106: Выдвижная полка для клавиатуры 60А-04-45-11BL | H106: шт. | I106: =I102*J106 -> 7 | J106: 0.25 | K106: 0.25 | O106: =ROUND(CP106,2) -> 38258.62 | P106: =ROUND((ROUND((AC106*AW106*I106),2)*BC106),2) -> 38258.62 | Q106: =(ROUND((ROUND(((ET106)*AV106*I106),2)*BB106),2)+ROUND((ROUND(((AE106-(EU106))*AV106*I106),2)*BS106),2)) -> 0 | R106: =ROUND((ROUND((AE106*AV106*I106),2)*BS106),2) -> 0 | S106: =ROUND((ROUND((AF106*AV106*I106),2)*BA106),2) -> 0 | T106: =ROUND(CU106*I106,2) -> 0 | U106: =CV106*I106 -> 0 | V106: =CW106*I106 -> 0 | W106: =ROUND(CX106*I106,2) -> 0 | X106: =ROUND(CY106,2) -> 0 | Y106: =ROUND(CZ106,2) -> 0 | AA106: 56505405 | AB106: =ROUND((AC106+AD106+AF106),6) -> 553.19 | AC106: =ROUND((ES106),6) -> 553.19 | AD106: =ROUND((((ET106)-(EU106))+AE106),6) -> 0 | AE106: =ROUND((EU106),6) -> 0 | AF106: =ROUND((EV106),6) -> 0 | AG106: =ROUND((AP106),6) -> 0 | AH106: =(EW106) -> 0 | AI106: =(EX106) -> 0 | AJ106: =(AS106) -> 0 | AK106: 553.19 | AL106: 553.19 | AM106: 0 | AN106: 0 | AO106: 0 | AP106: 0 | AQ106: 0 | AR106: 0 | AS106: 0 | AT106: 90 | AU106: 46 | AV106: 1 | AW106: 1 | AZ106: 1 | BA106: 1 | BB106: 1 | BC106: 9.88 | BH106: 3 | BI106: 2 | BM106: 72 | BN106: 0 | BP106: 0 | BQ106: 40 | BR106: 0 | BS106: 1 | BT106: 1 | BU106: 1 | BV106: 1 | BW106: 1 | BX106: 1 | BZ106: 90 | CA106: 46 | CE106: 30 | CF106: 0 | CG106: 0 | CM106: 0 | CO106: 0 | CP106: =(P106+Q106+S106) -> 38258.62 | CQ106: =ROUND((ROUND((AC106*AW106*1),2)*BC106),2) -> 5465.52 | CR106: =(ROUND((ROUND(((ET106)*AV106*1),2)*BB106),2)+ROUND((ROUND(((AE106-(EU106))*AV106*1),2)*BS106),2)) -> 0 | CS106: =ROUND((ROUND((AE106*AV106*1),2)*BS106),2) -> 0 | CT106: =ROUND((ROUND((AF106*AV106*1),2)*BA106),2) -> 0 | CU106: =AG106 -> 0 | CV106: =(AH106*AV106) -> 0 | CW106: =AI106 -> 0 | CX106: =AJ106 -> 0 | CY106: =(((S106+R106)*AT106)/100) -> 0 | CZ106: =(((S106+R106)*AU106)/100) -> 0 | DN106: 0 | DO106: 0 | DP106: 1 | DQ106: 1 | DU106: 1010 | DV106: шт. | DW106: шт. | DX106: 1 | EE106: 58162634 | EF106: 40 | EG106: Монтаж оборудования | EH106: 0 | EJ106: 2 | EK106: 72 | EL106: ТСН-2001.4-11. Приборы и средства автоматизации и вычислительной техники | EM106: ТСН-2001.4-11-1 | EQ106: 0 | ER106: 553.19 | ES106: 553.19 | ET106: 0 | EU106: 0 | EV106: 0 | EW106: 0 | EX106: 0 | EZ106: 5 | FC106: 1 | FD106: 18 | FF106: 6430 | FQ106: 0 | FR106: 0 | FS106: 0 | FX106: 90 | FY106: 46 | GA106: [6 430 / 1,2 / 9,88] + 2% Заг.скл | GD106: 1 | GF106: 1122354003 | GG106: 2 | GH106: 3 | GI106: 5 | GJ106: 0 | GK106: 0 | GL106: =ROUND(IF(AND(BH106=3,BI106=3,FS106<>0),P106,0),2) -> 0 | GM106: =ROUND(O106+X106+Y106,2)+GX106 -> 38258.62 | GN106: =IF(OR(BI106=0,BI106=1),GM106-GX106,0) -> 0 | GO106: =IF(BI106=2,GM106-GX106,0) -> 38258.62 | GP106: =IF(BI106=4,GM106-GX106,0) -> 0 | GR106: 1 | GS106: 1 | GT106: 0 | GV106: =ROUND((GT106),6) -> 0 | GW106: 1 | GX106: =ROUND(HC106*I106,2) -> 0 | HA106: 0 | HB106: 0 | HC106: =GV106*GW106 -> 0 | HE106: 0 | HF106: 2 | HS106: 0 | IK106: 0
A107: 18 | B107: 1 | E107: 6,3 | F107: КА 6 | G107: Полка сmацuонарная регулuруемая 1U до 50кг, 370мм, для 600мм | H107: шт. | I107: =I101*J107 -> 7 | J107: 0.25 | K107: 0.25 | O107: =ROUND(CP107,2) -> 2670.29 | P107: =ROUND((ROUND((AC107*AW107*I107),2)*BC107),2) -> 2670.29 | Q107: =(ROUND((ROUND(((ET107)*AV107*I107),2)*BB107),2)+ROUND((ROUND(((AE107-(EU107))*AV107*I107),2)*BS107),2)) -> 0 | R107: =ROUND((ROUND((AE107*AV107*I107),2)*BS107),2) -> 0 | S107: =ROUND((ROUND((AF107*AV107*I107),2)*BA107),2) -> 0 | T107: =ROUND(CU107*I107,2) -> 0 | U107: =CV107*I107 -> 0 | V107: =CW107*I107 -> 0 | W107: =ROUND(CX107*I107,2) -> 0 | X107: =ROUND(CY107,2) -> 0 | Y107: =ROUND(CZ107,2) -> 0 | AA107: 56505403 | AB107: =ROUND((AC107+AD107+AF107),6) -> 381.47 | AC107: =ROUND((ES107),6) -> 381.47 | AD107: =ROUND((((ET107)-(EU107))+AE107),6) -> 0 | AE107: =ROUND((EU107),6) -> 0 | AF107: =ROUND((EV107),6) -> 0 | AG107: =ROUND((AP107),6) -> 0 | AH107: =(EW107) -> 0 | AI107: =(EX107) -> 0 | AJ107: =(AS107) -> 0 | AK107: 381.47 | AL107: 381.47 | AM107: 0 | AN107: 0 | AO107: 0 | AP107: 0 | AQ107: 0 | AR107: 0 | AS107: 0 | AT107: 90 | AU107: 46 | AV107: 1 | AW107: 1 | AZ107: 1 | BA107: 1 | BB107: 1 | BC107: 1 | BH107: 3 | BI107: 2 | BM107: 72 | BN107: 0 | BP107: 0 | BQ107: 40 | BR107: 0 | BS107: 1 | BT107: 1 | BU107: 1 | BV107: 1 | BW107: 1 | BX107: 1 | BZ107: 90 | CA107: 46 | CE107: 30 | CF107: 0 | CG107: 0 | CM107: 0 | CO107: 0 | CP107: =(P107+Q107+S107) -> 2670.29 | CQ107: =ROUND((ROUND((AC107*AW107*1),2)*BC107),2) -> 381.47 | CR107: =(ROUND((ROUND(((ET107)*AV107*1),2)*BB107),2)+ROUND((ROUND(((AE107-(EU107))*AV107*1),2)*BS107),2)) -> 0 | CS107: =ROUND((ROUND((AE107*AV107*1),2)*BS107),2) -> 0 | CT107: =ROUND((ROUND((AF107*AV107*1),2)*BA107),2) -> 0 | CU107: =AG107 -> 0 | CV107: =(AH107*AV107) -> 0 | CW107: =AI107 -> 0 | CX107: =AJ107 -> 0 | CY107: =(((S107+R107)*AT107)/100) -> 0 | CZ107: =(((S107+R107)*AU107)/100) -> 0 | DN107: 0 | DO107: 0 | DP107: 1 | DQ107: 1 | DU107: 1010 | DV107: шт. | DW107: шт. | DX107: 1 | EE107: 58162634 | EF107: 40 | EG107: Монтаж оборудования | EH107: 0 | EJ107: 2 | EK107: 72 | EL107: ТСН-2001.4-11. Приборы и средства автоматизации и вычислительной техники | EM107: ТСН-2001.4-11-1 | EQ107: 0 | ER107: 0 | ES107: 381.47 | ET107: 0 | EU107: 0 | EV107: 0 | EW107: 0 | EX107: 0 | FQ107: 0 | FR107: 0 | FS107: 0 | FX107: 90 | FY107: 46 | GA107: [4 434 / 1,2 / 9,88] + 2% Заг.скл | GD107: 1 | GF107: -1998996946 | GG107: 2 | GH107: 4 | GI107: -2 | GJ107: 0 | GK107: 0 | GL107: =ROUND(IF(AND(BH107=3,BI107=3,FS107<>0),P107,0),2) -> 0 | GM107: =ROUND(O107+X107+Y107,2)+GX107 -> 2670.29 | GN107: =IF(OR(BI107=0,BI107=1),GM107-GX107,0) -> 0 | GO107: =IF(BI107=2,GM107-GX107,0) -> 2670.29 | GP107: =IF(BI107=4,GM107-GX107,0) -> 0 | GR107: 0 | GS107: 2 | GT107: 0 | GV107: =ROUND((GT107),6) -> 0 | GW107: 1 | GX107: =ROUND(HC107*I107,2) -> 0 | HA107: 0 | HB107: 0 | HC107: =GV107*GW107 -> 0 | HE107: 0 | HF107: 2 | HS107: 0 | IK107: 0
A108: 18 | B108: 1 | E108: 6,3 | F108: КА 6 | G108: Полка сmацuонарная регулuруемая 1U до 50кг, 370мм, для 600мм | H108: шт. | I108: =I102*J108 -> 7 | J108: 0.25 | K108: 0.25 | O108: =ROUND(CP108,2) -> 26382.47 | P108: =ROUND((ROUND((AC108*AW108*I108),2)*BC108),2) -> 26382.47 | Q108: =(ROUND((ROUND(((ET108)*AV108*I108),2)*BB108),2)+ROUND((ROUND(((AE108-(EU108))*AV108*I108),2)*BS108),2)) -> 0 | R108: =ROUND((ROUND((AE108*AV108*I108),2)*BS108),2) -> 0 | S108: =ROUND((ROUND((AF108*AV108*I108),2)*BA108),2) -> 0 | T108: =ROUND(CU108*I108,2) -> 0 | U108: =CV108*I108 -> 0 | V108: =CW108*I108 -> 0 | W108: =ROUND(CX108*I108,2) -> 0 | X108: =ROUND(CY108,2) -> 0 | Y108: =ROUND(CZ108,2) -> 0 | AA108: 56505405 | AB108: =ROUND((AC108+AD108+AF108),6) -> 381.47 | AC108: =ROUND((ES108),6) -> 381.47 | AD108: =ROUND((((ET108)-(EU108))+AE108),6) -> 0 | AE108: =ROUND((EU108),6) -> 0 | AF108: =ROUND((EV108),6) -> 0 | AG108: =ROUND((AP108),6) -> 0 | AH108: =(EW108) -> 0 | AI108: =(EX108) -> 0 | AJ108: =(AS108) -> 0 | AK108: 381.47 | AL108: 381.47 | AM108: 0 | AN108: 0 | AO108: 0 | AP108: 0 | AQ108: 0 | AR108: 0 | AS108: 0 | AT108: 90 | AU108: 46 | AV108: 1 | AW108: 1 | AZ108: 1 | BA108: 1 | BB108: 1 | BC108: 9.88 | BH108: 3 | BI108: 2 | BM108: 72 | BN108: 0 | BP108: 0 | BQ108: 40 | BR108: 0 | BS108: 1 | BT108: 1 | BU108: 1 | BV108: 1 | BW108: 1 | BX108: 1 | BZ108: 90 | CA108: 46 | CE108: 30 | CF108: 0 | CG108: 0 | CM108: 0 | CO108: 0 | CP108: =(P108+Q108+S108) -> 26382.47 | CQ108: =ROUND((ROUND((AC108*AW108*1),2)*BC108),2) -> 3768.92 | CR108: =(ROUND((ROUND(((ET108)*AV108*1),2)*BB108),2)+ROUND((ROUND(((AE108-(EU108))*AV108*1),2)*BS108),2)) -> 0 | CS108: =ROUND((ROUND((AE108*AV108*1),2)*BS108),2) -> 0 | CT108: =ROUND((ROUND((AF108*AV108*1),2)*BA108),2) -> 0 | CU108: =AG108 -> 0 | CV108: =(AH108*AV108) -> 0 | CW108: =AI108 -> 0 | CX108: =AJ108 -> 0 | CY108: =(((S108+R108)*AT108)/100) -> 0 | CZ108: =(((S108+R108)*AU108)/100) -> 0 | DN108: 0 | DO108: 0 | DP108: 1 | DQ108: 1 | DU108: 1010 | DV108: шт. | DW108: шт. | DX108: 1 | EE108: 58162634 | EF108: 40 | EG108: Монтаж оборудования | EH108: 0 | EJ108: 2 | EK108: 72 | EL108: ТСН-2001.4-11. Приборы и средства автоматизации и вычислительной техники | EM108: ТСН-2001.4-11-1 | EQ108: 0 | ER108: 381.47 | ES108: 381.47 | ET108: 0 | EU108: 0 | EV108: 0 | EW108: 0 | EX108: 0 | EZ108: 5 | FC108: 1 | FD108: 18 | FF108: 4434 | FQ108: 0 | FR108: 0 | FS108: 0 | FX108: 90 | FY108: 46 | GA108: [4 434 / 1,2 / 9,88] + 2% Заг.скл | GD108: 1 | GF108: -1998996946 | GG108: 2 | GH108: 3 | GI108: 5 | GJ108: 0 | GK108: 0 | GL108: =ROUND(IF(AND(BH108=3,BI108=3,FS108<>0),P108,0),2) -> 0 | GM108: =ROUND(O108+X108+Y108,2)+GX108 -> 26382.47 | GN108: =IF(OR(BI108=0,BI108=1),GM108-GX108,0) -> 0 | GO108: =IF(BI108=2,GM108-GX108,0) -> 26382.47 | GP108: =IF(BI108=4,GM108-GX108,0) -> 0 | GR108: 1 | GS108: 1 | GT108: 0 | GV108: =ROUND((GT108),6) -> 0 | GW108: 1 | GX108: =ROUND(HC108*I108,2) -> 0 | HA108: 0 | HB108: 0 | HC108: =GV108*GW108 -> 0 | HE108: 0 | HF108: 2 | HS108: 0 | IK108: 0
A109: 18 | B109: 1 | E109: 6,4 | F109: КА 8 | G109: Панель освещенuя на магнumах, унuверсальная цвеm черныu 60A-05-15BL | H109: шт. | I109: =I101*J109 -> 7 | J109: 0.25 | K109: 0.25 | O109: =ROUND(CP109,2) -> 5044.76 | P109: =ROUND((ROUND((AC109*AW109*I109),2)*BC109),2) -> 5044.76 | Q109: =(ROUND((ROUND(((ET109)*AV109*I109),2)*BB109),2)+ROUND((ROUND(((AE109-(EU109))*AV109*I109),2)*BS109),2)) -> 0 | R109: =ROUND((ROUND((AE109*AV109*I109),2)*BS109),2) -> 0 | S109: =ROUND((ROUND((AF109*AV109*I109),2)*BA109),2) -> 0 | T109: =ROUND(CU109*I109,2) -> 0 | U109: =CV109*I109 -> 0 | V109: =CW109*I109 -> 0 | W109: =ROUND(CX109*I109,2) -> 0 | X109: =ROUND(CY109,2) -> 0 | Y109: =ROUND(CZ109,2) -> 0 | AA109: 56505403 | AB109: =ROUND((AC109+AD109+AF109),6) -> 720.68 | AC109: =ROUND((ES109),6) -> 720.68 | AD109: =ROUND((((ET109)-(EU109))+AE109),6) -> 0 | AE109: =ROUND((EU109),6) -> 0 | AF109: =ROUND((EV109),6) -> 0 | AG109: =ROUND((AP109),6) -> 0 | AH109: =(EW109) -> 0 | AI109: =(EX109) -> 0 | AJ109: =(AS109) -> 0 | AK109: 720.68 | AL109: 720.68 | AM109: 0 | AN109: 0 | AO109: 0 | AP109: 0 | AQ109: 0 | AR109: 0 | AS109: 0 | AT109: 90 | AU109: 46 | AV109: 1 | AW109: 1 | AZ109: 1 | BA109: 1 | BB109: 1 | BC109: 1 | BH109: 3 | BI109: 2 | BM109: 72 | BN109: 0 | BP109: 0 | BQ109: 40 | BR109: 0 | BS109: 1 | BT109: 1 | BU109: 1 | BV109: 1 | BW109: 1 | BX109: 1 | BZ109: 90 | CA109: 46 | CE109: 30 | CF109: 0 | CG109: 0 | CM109: 0 | CO109: 0 | CP109: =(P109+Q109+S109) -> 5044.76 | CQ109: =ROUND((ROUND((AC109*AW109*1),2)*BC109),2) -> 720.68 | CR109: =(ROUND((ROUND(((ET109)*AV109*1),2)*BB109),2)+ROUND((ROUND(((AE109-(EU109))*AV109*1),2)*BS109),2)) -> 0 | CS109: =ROUND((ROUND((AE109*AV109*1),2)*BS109),2) -> 0 | CT109: =ROUND((ROUND((AF109*AV109*1),2)*BA109),2) -> 0 | CU109: =AG109 -> 0 | CV109: =(AH109*AV109) -> 0 | CW109: =AI109 -> 0 | CX109: =AJ109 -> 0 | CY109: =(((S109+R109)*AT109)/100) -> 0 | CZ109: =(((S109+R109)*AU109)/100) -> 0 | DN109: 0 | DO109: 0 | DP109: 1 | DQ109: 1 | DU109: 1010 | DV109: шт. | DW109: шт. | DX109: 1 | EE109: 58162634 | EF109: 40 | EG109: Монтаж оборудования | EH109: 0 | EJ109: 2 | EK109: 72 | EL109: ТСН-2001.4-11. Приборы и средства автоматизации и вычислительной техники | EM109: ТСН-2001.4-11-1 | EQ109: 0 | ER109: 0 | ES109: 720.68 | ET109: 0 | EU109: 0 | EV109: 0 | EW109: 0 | EX109: 0 | FQ109: 0 | FR109: 0 | FS109: 0 | FX109: 90 | FY109: 46 | GA109: [8 376,8 / 1,2 / 9,88] + 2% Заг.скл | GD109: 1 | GF109: -1548011914 | GG109: 2 | GH109: 4 | GI109: -2 | GJ109: 0 | GK109: 0 | GL109: =ROUND(IF(AND(BH109=3,BI109=3,FS109<>0),P109,0),2) -> 0 | GM109: =ROUND(O109+X109+Y109,2)+GX109 -> 5044.76 | GN109: =IF(OR(BI109=0,BI109=1),GM109-GX109,0) -> 0 | GO109: =IF(BI109=2,GM109-GX109,0) -> 5044.76 | GP109: =IF(BI109=4,GM109-GX109,0) -> 0 | GR109: 0 | GS109: 2 | GT109: 0 | GV109: =ROUND((GT109),6) -> 0 | GW109: 1 | GX109: =ROUND(HC109*I109,2) -> 0 | HA109: 0 | HB109: 0 | HC109: =GV109*GW109 -> 0 | HE109: 0 | HF109: 2 | HS109: 0 | IK109: 0
A110: 18 | B110: 1 | E110: 6,4 | F110: КА 8 | G110: Панель освещенuя на магнumах, унuверсальная цвеm черныu 60A-05-15BL | H110: шт. | I110: =I102*J110 -> 7 | J110: 0.25 | K110: 0.25 | O110: =ROUND(CP110,2) -> 49842.23 | P110: =ROUND((ROUND((AC110*AW110*I110),2)*BC110),2) -> 49842.23 | Q110: =(ROUND((ROUND(((ET110)*AV110*I110),2)*BB110),2)+ROUND((ROUND(((AE110-(EU110))*AV110*I110),2)*BS110),2)) -> 0 | R110: =ROUND((ROUND((AE110*AV110*I110),2)*BS110),2) -> 0 | S110: =ROUND((ROUND((AF110*AV110*I110),2)*BA110),2) -> 0 | T110: =ROUND(CU110*I110,2) -> 0 | U110: =CV110*I110 -> 0 | V110: =CW110*I110 -> 0 | W110: =ROUND(CX110*I110,2) -> 0 | X110: =ROUND(CY110,2) -> 0 | Y110: =ROUND(CZ110,2) -> 0 | AA110: 56505405 | AB110: =ROUND((AC110+AD110+AF110),6) -> 720.68 | AC110: =ROUND((ES110),6) -> 720.68 | AD110: =ROUND((((ET110)-(EU110))+AE110),6) -> 0 | AE110: =ROUND((EU110),6) -> 0 | AF110: =ROUND((EV110),6) -> 0 | AG110: =ROUND((AP110),6) -> 0 | AH110: =(EW110) -> 0 | AI110: =(EX110) -> 0 | AJ110: =(AS110) -> 0 | AK110: 720.68 | AL110: 720.68 | AM110: 0 | AN110: 0 | AO110: 0 | AP110: 0 | AQ110: 0 | AR110: 0 | AS110: 0 | AT110: 90 | AU110: 46 | AV110: 1 | AW110: 1 | AZ110: 1 | BA110: 1 | BB110: 1 | BC110: 9.88 | BH110: 3 | BI110: 2 | BM110: 72 | BN110: 0 | BP110: 0 | BQ110: 40 | BR110: 0 | BS110: 1 | BT110: 1 | BU110: 1 | BV110: 1 | BW110: 1 | BX110: 1 | BZ110: 90 | CA110: 46 | CE110: 30 | CF110: 0 | CG110: 0 | CM110: 0 | CO110: 0 | CP110: =(P110+Q110+S110) -> 49842.23 | CQ110: =ROUND((ROUND((AC110*AW110*1),2)*BC110),2) -> 7120.32 | CR110: =(ROUND((ROUND(((ET110)*AV110*1),2)*BB110),2)+ROUND((ROUND(((AE110-(EU110))*AV110*1),2)*BS110),2)) -> 0 | CS110: =ROUND((ROUND((AE110*AV110*1),2)*BS110),2) -> 0 | CT110: =ROUND((ROUND((AF110*AV110*1),2)*BA110),2) -> 0 | CU110: =AG110 -> 0 | CV110: =(AH110*AV110) -> 0 | CW110: =AI110 -> 0 | CX110: =AJ110 -> 0 | CY110: =(((S110+R110)*AT110)/100) -> 0 | CZ110: =(((S110+R110)*AU110)/100) -> 0 | DN110: 0 | DO110: 0 | DP110: 1 | DQ110: 1 | DU110: 1010 | DV110: шт. | DW110: шт. | DX110: 1 | EE110: 58162634 | EF110: 40 | EG110: Монтаж оборудования | EH110: 0 | EJ110: 2 | EK110: 72 | EL110: ТСН-2001.4-11. Приборы и средства автоматизации и вычислительной техники | EM110: ТСН-2001.4-11-1 | EQ110: 0 | ER110: 720.68 | ES110: 720.68 | ET110: 0 | EU110: 0 | EV110: 0 | EW110: 0 | EX110: 0 | EZ110: 5 | FC110: 1 | FD110: 18 | FF110: 8376.8 | FQ110: 0 | FR110: 0 | FS110: 0 | FX110: 90 | FY110: 46 | GA110: [8 376,8 / 1,2 / 9,88] + 2% Заг.скл | GD110: 1 | GF110: -1548011914 | GG110: 2 | GH110: 3 | GI110: 5 | GJ110: 0 | GK110: 0 | GL110: =ROUND(IF(AND(BH110=3,BI110=3,FS110<>0),P110,0),2) -> 0 | GM110: =ROUND(O110+X110+Y110,2)+GX110 -> 49842.23 | GN110: =IF(OR(BI110=0,BI110=1),GM110-GX110,0) -> 0 | GO110: =IF(BI110=2,GM110-GX110,0) -> 49842.23 | GP110: =IF(BI110=4,GM110-GX110,0) -> 0 | GR110: 1 | GS110: 1 | GT110: 0 | GV110: =ROUND((GT110),6) -> 0 | GW110: 1 | GX110: =ROUND(HC110*I110,2) -> 0 | HA110: 0 | HB110: 0 | HC110: =GV110*GW110 -> 0 | HE110: 0 | HF110: 2 | HS110: 0 | IK110: 0
A112: 51 | B112: =B81 -> 1 | C112: =A81 -> 4 | D112: =ROW(A81) -> 81 | F112: =IF(F81<>"",F81,"") | G112: =IF(G81<>"",G81,"") -> Телекоммуникационный шкаф 42U 19" ШТ1-2,1-3,1-4; ШТ2-5,2-6; ШТ3-7,3-8 | H112: 0 | O112: =ROUND(AB112,2) -> 163143 | P112: =ROUND(AC112,2) -> 161492.26 | Q112: =ROUND(AD112,2) -> 329.89 | R112: =ROUND(AE112,2) -> 36.12 | S112: =ROUND(AF112,2) -> 1320.85 | T112: =ROUND(AG112,2) -> 0 | U112: =AH112 -> 117.31216 | V112: =AI112 -> 0 | W112: =ROUND(AJ112,2) -> 0 | X112: =ROUND(AK112,2) -> 1221.27 | Y112: =ROUND(AL112,2) -> 624.21 | AB112: =ROUND(SUMIF(AA85:AA110,"=56505403",O85:O110),2) -> 163143 | AC112: =ROUND(SUMIF(AA85:AA110,"=56505403",P85:P110),2) -> 161492.26 | AD112: =ROUND(SUMIF(AA85:AA110,"=56505403",Q85:Q110),2) -> 329.89 | AE112: =ROUND(SUMIF(AA85:AA110,"=56505403",R85:R110),2) -> 36.12 | AF112: =ROUND(SUMIF(AA85:AA110,"=56505403",S85:S110),2) -> 1320.85 | AG112: =ROUND(SUMIF(AA85:AA110,"=56505403",T85:T110),2) -> 0 | AH112: =SUMIF(AA85:AA110,"=56505403",U85:U110) -> 117.31216 | AI112: =SUMIF(AA85:AA110,"=56505403",V85:V110) -> 0 | AJ112: =ROUND(SUMIF(AA85:AA110,"=56505403",W85:W110),2) -> 0 | AK112: =ROUND(SUMIF(AA85:AA110,"=56505403",X85:X110),2) -> 1221.27 | AL112: =ROUND(SUMIF(AA85:AA110,"=56505403",Y85:Y110),2) -> 624.21 | AO112: =ROUND(BX112,2) -> 0 | AP112: =ROUND(BY112,2) -> 22491.21 | AQ112: =ROUND(BZ112,2) -> 0 | AR112: =ROUND(CA112,2) -> 164988.48 | AS112: =ROUND(CB112,2) -> 0 | AT112: =ROUND(CC112,2) -> 142497.27 | AU112: =ROUND(CD112,2) -> 0 | AV112: =ROUND(CE112,2) -> 161492.26 | ... BD112: =ROUND(CM112,2) -> 0 | BX112: =ROUND(SUMIF(AA85:AA110,"=56505403",FQ85:FQ110),2) -> 0 | BY112: =ROUND(SUMIF(AA85:AA110,"=56505403",FR85:FR110),2) -> 22491.21 | BZ112: =ROUND(SUMIF(AA85:AA110,"=56505403",GL85:GL110),2) -> 0 | CA112: =ROUND(SUMIF(AA85:AA110,"=56505403",GM85:GM110),2) -> 164988.48 | CB112: =ROUND(SUMIF(AA85:AA110,"=56505403",GN85:GN110),2) -> 0 | CC112: =ROUND(SUMIF(AA85:AA110,"=56505403",GO85:GO110),2) -> 142497.27 | CD112: =ROUND(SUMIF(AA85:AA110,"=56505403",GP85:GP110),2) -> 0 | CE112: =AC112-BX112 -> 161492.26 | CF112: =AC112-BY112 -> 139001.05 | CG112: =BX112-BZ112 -> 0 | CH112: =AC112-BX112-BY112+BZ112 -> 139001.05 | CI112: =BY112-BZ112 -> 22491.21 | CJ112: =ROUND(SUMIF(AA85:AA110,"=56505403",GX85:GX110),2) -> 0 | CK112: =ROUND(SUMIF(AA85:AA110,"=56505403",GY85:GY110),2) -> 0 | CL112: =ROUND(SUMIF(AA85:AA110,"=56505403",GZ85:GZ110),2) -> 0 | CM112: =ROUND(SUMIF(AA85:AA110,"=56505403",HD85:HD110),2) -> 0 | DG112: =ROUND(DT112,2) -> 1623262.9 | DH112: =ROUND(DU112,2) -> 1545569.7 | DI112: =ROUND(DV112,2) -> 5059.65 | DJ112: =ROUND(DW112,2) -> 1986.23 | DK112: =ROUND(DX112,2) -> 72633.54 | DL112: =ROUND(DY112,2) -> 0 | DM112: =DZ112 -> 117.31216 | DN112: =EA112 -> 0 | DO112: =ROUND(EB112,2) -> 0 | DP112: =ROUND(EC112,2) -> 67157.8 | DQ112: =ROUND(ED112,2) -> 34325.09 | DT112: =ROUND(SUMIF(AA85:AA110,"=56505405",O85:O110),2) -> 1623262.9 | DU112: =ROUND(SUMIF(AA85:AA110,"=56505405",P85:P110),2) -> 1545569.7 | DV112: =ROUND(SUMIF(AA85:AA110,"=56505405",Q85:Q110),2) -> 5059.65 | DW112: =ROUND(SUMIF(AA85:AA110,"=56505405",R85:R110),2) -> 1986.23 | DX112: =ROUND(SUMIF(AA85:AA110,"=56505405",S85:S110),2) -> 72633.54 | DY112: =ROUND(SUMIF(AA85:AA110,"=56505405",T85:T110),2) -> 0 | DZ112: =SUMIF(AA85:AA110,"=56505405",U85:U110) -> 117.31216 | EA112: =SUMIF(AA85:AA110,"=56505405",V85:V110) -> 0 | EB112: =ROUND(SUMIF(AA85:AA110,"=56505405",W85:W110),2) -> 0 | EC112: =ROUND(SUMIF(AA85:AA110,"=56505405",X85:X110),2) -> 67157.8 | ED112: =ROUND(SUMIF(AA85:AA110,"=56505405",Y85:Y110),2) -> 34325.09 | EG112: =ROUND(FP112,2) -> 0 | EH112: =ROUND(FQ112,2) -> 172282.67 | EI112: =ROUND(FR112,2) -> 0 | EJ112: =ROUND(FS112,2) -> 1724745.8 | EK112: =ROUND(FT112,2) -> 0 | EL112: =ROUND(FU112,2) -> 1552463.1 | EM112: =ROUND(FV112,2) -> 0 | EN112: =ROUND(FW112,2) -> 1545569.7 | ... EV112: =ROUND(GE112,2) -> 0 | FP112: =ROUND(SUMIF(AA85:AA110,"=56505405",FQ85:FQ110),2) -> 0 | FQ112: =ROUND(SUMIF(AA85:AA110,"=56505405",FR85:FR110),2) -> 172282.67 | FR112: =ROUND(SUMIF(AA85:AA110,"=56505405",GL85:GL110),2) -> 0 | FS112: =ROUND(SUMIF(AA85:AA110,"=56505405",GM85:GM110),2) -> 1724745.8 | FT112: =ROUND(SUMIF(AA85:AA110,"=56505405",GN85:GN110),2) -> 0 | FU112: =ROUND(SUMIF(AA85:AA110,"=56505405",GO85:GO110),2) -> 1552463.1 | FV112: =ROUND(SUMIF(AA85:AA110,"=56505405",GP85:GP110),2) -> 0 | FW112: =DU112-FP112 -> 1545569.7 | FX112: =DU112-FQ112 -> 1373287 | FY112: =FP112-FR112 -> 0 | FZ112: =DU112-FP112-FQ112+FR112 -> 1373287 | GA112: =FQ112-FR112 -> 172282.67 | GB112: =ROUND(SUMIF(AA85:AA110,"=56505405",GX85:GX110),2) -> 0 | GC112: =ROUND(SUMIF(AA85:AA110,"=56505405",GY85:GY110),2) -> 0 | GD112: =ROUND(SUMIF(AA85:AA110,"=56505405",GZ85:GZ110),2) -> 0 | GE112: =ROUND(SUMIF(AA85:AA110,"=56505405",HD85:HD110),2) -> 0 | GX112: 0
A114: 50 | B114: 0 | C114: 0 | D114: 1 | E114: 201 | F114: =ROUND(Source!O112,O114) -> 163143 | G114: ПЗ | H114: Прямые затраты | K114: 201 | L114: 1 | M114: 3 | O114: 2 | P114: =ROUND(Source!DG112,O114) -> 1623262.9 | W114: 163143 | X114: 1 | Y114: 163143 | Z114: 1623262.9 | AA114: 1 | AB114: 1623262.9
