Workbook

Sheet 02-01-13
A1: =Source!B1 -> Smeta.RU (495) 974-1589
J2: Форма № 4б
A3: Капитальный ремонт здания Государственного бюджетного общеобразовательного учреждения города Москвы "Школа №236" по адресу: г. Москва, улица Клязьминская, дом 7, корпус 4. | AP3: Капитальный ремонт здания Государственного бюджетного общеобразовательного учреждения города Москвы "Школа №236" по адресу: г. Москва, улица Клязьминская, дом 7, корпус 4. 02-01-13 Электрочасофикация
A4: (наименование стройки и/или объекта)
A6: =CONCATENATE( "ЛОКАЛЬНАЯ СМЕТА № ",IF(Source!F20<>"Новая локальная смета", Source!F20, "")) -> ЛОКАЛЬНАЯ СМЕТА № 02-01-13
A8: =IF(Source!G20<>"Новая локальная смета", Source!G20, "") -> Электрочасофикация
A9: (наименование работ и затрат)
A11: =CONCATENATE( "Основание: чертежи № ", Source!J20) -> Основание: чертежи № 2024-00272-01-0-ИОС5.6
I13: В базисном уровне цен | J13: В текущем уровне цен
E14: Сметная стоимость | I14: =I15+I16+I17+I18 -> 14.83 | J14: =J15+J16+J17+J18 -> 140.65 | K14: тыс.руб.
E15: Строительные работы | I15: =ROUND((Source!F131)/1000, 2) -> 0 | J15: =ROUND((Source!P131)/1000, 2) -> 0 | K15: тыс.руб.
E16: Работы по монтажу оборудования | I16: =ROUND((Source!F132)/1000, 2) -> 2.85 | J16: =ROUND((Source!P132)/1000, 2) -> 52.48 | K16: тыс.руб.
E17: Оборудование | I17: =ROUND((Source!F123)/1000, 2) -> 11.98 | J17: =ROUND((Source!P123)/1000, 2) -> 88.17 | K17: тыс.руб.
E18: Прочие работы и затраты | I18: =ROUND((Source!F133+Source!F134)/1000, 2) -> 0 | J18: =ROUND((Source!P133+Source!P134)/1000, 2) -> 0 | K18: тыс.руб.
E19: Средства на оплату труда | I19: =(Source!F129+ Source!F128)/1000 -> 0.30977 | J19: =((Source!P129 + Source!P128)/1000) -> 17.03425 | K19: тыс.руб.
E20: Затраты труда | I20: =Source!F136 -> 25.366193 | K20: чел.-ч.
E21: Кроме того:
E22: Возврат материалов | I22: =SUM(Y28:Y101)/1000 -> 0 | J22: =SUM(Z28:Z101)/1000 -> 0 | K22: тыс.руб.
A24: Составлен(а) по ТСН-2001 с учетом Дополнения №: 80
A25: № и период сборника коэффициентов (индексов) пересчета: Коэффициенты к ТСН-2001 МГЭ Дополнение 80, строительство №217/80 III квартал 2025 года и Коэффициенты к ТСН-2001.13-2 Дополнение 46 №62/46 III квартал 2025 года | AP25: № и период сборника коэффициентов (индексов) пересчета: Коэффициенты к ТСН-2001 МГЭ Дополнение 80, строительство №217/80 III квартал 2025 года и Коэффициенты к ТСН-2001.13-2 Дополнение 46 №62/46 III квартал 2025 года
A26: № п/п | B26: Шифр расценки и коды ресурсов | C26: Наименование работ и затрат | D26: Ед. изм. | E26: Кол-во единиц | F26: Цена на ед. изм., руб. | G26: Попра- вочные коэффи- циенты | H26: Коэффи- циенты зимних удорожа- ний | I26: Всего в ценах на январь 2000 года, руб. | J26: Коэффи- циенты (индек- сы) пере- счета, нормы НР и СП | K26: ВСЕГО затрат в текущем уровне цен, руб.
A27: 1 | B27: 2 | C27: 3 | D27: 4 | E27: 5 | F27: 6 | G27: 7 | H27: 8 | I27: 9 | J27: 10 | K27: 11
A29: =CONCATENATE("Раздел: ",IF(Source!G24<>"Новый раздел", Source!G24, "")) -> Раздел: Оборудование
A30: 1 | B30: =Source!F28 -> 4.10-85-1 | C30: Электрочасы первичные, часы первичные электрические показывающие кварцевые типа ПКЧЗ-2-РИ-Р24-Р6-1 | D30: =Source!H28 -> 1 ШТ. | E30: =Source!I28 -> 1 | Q30: =Source!X28 -> 42.82 | R30: =Source!X29 -> 2354.78 | S30: =Source!Y28 -> 21.89 | T30: =Source!Y29 -> 1203.55 | U30: =ROUND((175/100)*ROUND(Source!R28, 2), 2) -> 0 | V30: =ROUND((0/100)*ROUND(Source!R29, 2), 2) -> 0 | AC30: 0
C31: ЗП | F31: =Source!AO28 -> 41.31 | G31: 1,1 | H31: =Source!AV29 -> 1.047 | I31: =Source!S28 -> 47.58 | J31: =IF(Source!BA29<> 0, Source!BA29, 1) -> 54.99 | K31: =Source!S29 -> 2616.42
C32: МР | F32: =Source!AL28 -> 0.49 | H32: =Source!AW29 -> 1 | I32: =Source!P28 -> 0.49 | J32: =IF(Source!BC29<> 0, Source!BC29, 1) -> 9.9 | K32: =Source!P29 -> 4.85
C33: НР от ФОТ | D33: % | E33: =Source!BZ29 -> 90 | I33: =SUM(Q30:Q32) -> 42.82 | J33: =Source!AT29 -> 90 | K33: =SUM(R30:R32) -> 2354.78
C34: СП от ФОТ | D34: % | E34: =Source!CA29 -> 46 | I34: =SUM(S30:S33) -> 21.89 | J34: =Source!AU29 -> 46 | K34: =SUM(T30:T33) -> 1203.55
C35: ЗТР | D35: чел-ч | E35: =Source!AQ28 -> 3 | G35: 1,1 | H35: =Source!AV29 -> 1.047 | I35: =Source!U28 -> 3.4551
C36: ВСЕГО работ по позиции: | H36: =I31+I32+I33+I34+0-0-0 -> 112.78 | J36: =K31+K32+K33+K34+0-0-0 -> 6179.6
C37: ВСЕГО оборудование по позиции: | H37: =0+0 -> 0 | J37: =0+0 -> 0
C38: ВСЕГО по позиции: | H38: =I31+I32+I33+I34+0 -> 112.78 | J38: =K31+K32+K33+K34+0 -> 6179.6 | O38: =I31+I32+I33+I34+0 -> 112.78 | P38: =K31+K32+K33+K34+0 -> 6179.6
A40: 2 | B40: =Source!F30 -> КА-1 | C40: ОБОРУДОВАНИЕ:_x000D_ Часовая станция "Первичные часы" ПИК-2М-4002 10 518,85 = [92 760 / 1,2 / 7,66] + 3% Трансп + 1,2% Заг.скл | D40: =Source!H30 -> ШТ | E40: =Source!I30 -> 1 | F40: =Source!AL30 -> 10518.85 | H40: =Source!AW31 -> 1 | I40: =Source!P30 -> 10518.85 | J40: =IF(Source!BC31<> 0, Source!BC31, 1) -> 7.66 | K40: =Source!P31 -> 80574.39 | Q40: =Source!X30 -> 0 | R40: =Source!X31 -> 0 | S40: =Source!Y30 -> 0 | T40: =Source!Y31 -> 0 | U40: =ROUND((175/100)*ROUND(Source!R30, 2), 2) -> 0 | V40: =ROUND((0/100)*ROUND(Source!R31, 2), 2) -> 0 | AC40: 5
C41: ВСЕГО по позиции: | H41: =I40+0 -> 10518.85 | J41: =K40+0 -> 80574.39 | O41: =I40+0 -> 10518.85 | P41: =K40+0 -> 80574.39
A43: 3 | B43: =Source!F32 -> 4.10-86-1 | C43: Электрочасы вторичные для помещений, электрочасы односторонние на стене | D43: =Source!H32 -> 1 ШТ. | E43: =Source!I32 -> 2 | Q43: =Source!X32 -> 49.34 | R43: =Source!X33 -> 2713.1 | S43: =Source!Y32 -> 25.22 | T43: =Source!Y33 -> 1386.69 | U43: =ROUND((175/100)*ROUND(Source!R32, 2), 2) -> 0 | V43: =ROUND((0/100)*ROUND(Source!R33, 2), 2) -> 0 | AC43: 0
C44: ЗП | F44: =Source!AO32 -> 23.8 | G44: 1,1 | H44: =Source!AV33 -> 1.047 | I44: =Source!S32 -> 54.82 | J44: =IF(Source!BA33<> 0, Source!BA33, 1) -> 54.99 | K44: =Source!S33 -> 3014.55
C45: МР | F45: =Source!AL32 -> 0.28 | H45: =Source!AW33 -> 1 | I45: =Source!P32 -> 0.56 | J45: =IF(Source!BC33<> 0, Source!BC33, 1) -> 9.89 | K45: =Source!P33 -> 5.54
C46: НР от ФОТ | D46: % | E46: =Source!BZ33 -> 90 | I46: =SUM(Q43:Q45) -> 49.34 | J46: =Source!AT33 -> 90 | K46: =SUM(R43:R45) -> 2713.1
C47: СП от ФОТ | D47: % | E47: =Source!CA33 -> 46 | I47: =SUM(S43:S46) -> 25.22 | J47: =Source!AU33 -> 46 | K47: =SUM(T43:T46) -> 1386.69
C48: ЗТР | D48: чел-ч | E48: =Source!AQ32 -> 2 | G48: 1,1 | H48: =Source!AV33 -> 1.047 | I48: =Source!U32 -> 4.6068
C49: ВСЕГО работ по позиции: | H49: =I44+I45+I46+I47+0-0-0 -> 129.94 | J49: =K44+K45+K46+K47+0-0-0 -> 7119.88
C50: ВСЕГО оборудование по позиции: | H50: =0+0 -> 0 | J50: =0+0 -> 0
C51: ВСЕГО по позиции: | H51: =I44+I45+I46+I47+0 -> 129.94 | J51: =K44+K45+K46+K47+0 -> 7119.88 | O51: =I44+I45+I46+I47+0 -> 129.94 | P51: =K44+K45+K46+K47+0 -> 7119.88
A53: 4 | B53: =Source!F34 -> 13.1-2-211 | C53: ОБОРУДОВАНИЕ:_x000D_ Часы электрические вторичные стрелочные, типа ВЧ03/03 | D53: =Source!H34 -> шт. | E53: =Source!I34 -> 2 | F53: =Source!AL34 -> 730.63 | H53: =Source!AW35 -> 1 | I53: =Source!P34 -> 1461.26 | J53: =IF(Source!BC35<> 0, Source!BC35, 1) -> 5.2 | K53: =Source!P35 -> 7598.55 | Q53: =Source!X34 -> 0 | R53: =Source!X35 -> 0 | S53: =Source!Y34 -> 0 | T53: =Source!Y35 -> 0 | U53: =ROUND((175/100)*ROUND(Source!R34, 2), 2) -> 0 | V53: =ROUND((0/100)*ROUND(Source!R35, 2), 2) -> 0 | AC53: 5
C54: ВСЕГО по позиции: | H54: =I53+0 -> 1461.26 | J54: =K53+0 -> 7598.55 | O54: =I53+0 -> 1461.26 | P54: =K53+0 -> 7598.55
A57: =CONCATENATE("Итого по разделу: ",IF(Source!G37<>"Новый раздел", Source!G37, "")) -> Итого по разделу: Оборудование | H57: =SUM(O29:O56) -> 12222.83 | J57: =SUM(P29:P56) -> 101472.42
A58: Итого по ТСН-2001.16 | I58: =SUM(W29:W57) -> 0 | J58: =SUM(X29:X57) -> 0
A59: Итого возвратных сумм | I59: =SUM(Y29:Y58) -> 0 | J59: =SUM(Z29:Z58) -> 0
A61: =CONCATENATE("Раздел: ",IF(Source!G67<>"Новый раздел", Source!G67, "")) -> Раздел: Кабельные изделия
A62: 5 | B62: =Source!F71 -> 4.10-185-3 | C62: Прокладка кабеля связи огнестойкого в трубах гофрированных с использованием скобы СМО: по бетонным поверхностям | D62: =Source!H71 -> 100 м | E62: =Source!I71 -> 0.5 | Q62: =Source!X71 -> 152.48 | R62: =Source!X72 -> 8384.77 | S62: =Source!Y71 -> 77.93 | T62: =Source!Y72 -> 4285.55 | U62: =ROUND((175/100)*ROUND(Source!R71, 2), 2) -> 0 | V62: =ROUND((0/100)*ROUND(Source!R72, 2), 2) -> 0 | AC62: 0
C63: ="Объем: "&Source!I71&"=50/"&"100" -> Объем: 0,5=50/100
C64: ЗП | F64: =Source!AO71 -> 294.21 | G64: 1,1 | H64: =Source!AV72 -> 1.047 | I64: =Source!S71 -> 169.42 | J64: =IF(Source!BA72<> 0, Source!BA72, 1) -> 54.99 | K64: =Source!S72 -> 9316.41
C65: ЭМ | F65: =Source!AM71 -> 4.05 | G65: 1,1 | H65: =Source!AV72 -> 1.047 | I65: =Source!Q71 -> 2.33 | J65: =IF(Source!BB72<> 0, Source!BB72, 1) -> 8.72 | K65: =Source!Q72 -> 20.32
C66: МР | F66: =Source!AL71 -> 19.42 | H66: =Source!AW72 -> 1 | I66: =Source!P71 -> 9.71 | J66: =IF(Source!BC72<> 0, Source!BC72, 1) -> 6.66 | K66: =Source!P72 -> 64.67
A67: 5,1 | B67: =Source!F73 -> 1.12-5-371 | C67: Трубы электротехнические, гофрированные, из ПВХ, негорючие, с зондом, наружный диаметр 16 мм | D67: =Source!H73 -> м | E67: =Source!I73 -> 51 | F67: =Source!AK73 -> 2.67 | H67: =Source!AW74 -> 1 | I67: =Source!O73 -> 136.17 | J67: =IF(Source!BC74<> 0, Source!BC74, 1) -> 3.83 | K67: =Source!O74 -> 521.53 | Q67: =Source!X73 -> 0 | R67: =Source!X74 -> 0 | S67: =Source!Y73 -> 0 | T67: =Source!Y74 -> 0 | U67: =ROUND((175/100)*ROUND(Source!R73, 2), 2) -> 0 | V67: =ROUND((0/100)*ROUND(Source!R74, 2), 2) -> 0 | AC67: 3
A68: 5,2 | B68: =Source!F75 -> 1.14-1-555 | C68: Скобы крепежные для радиочастотного коаксиального кабеля с номинальным диаметром по изоляции от 4 до 6 мм | D68: =Source!H75 -> 100 шт. | E68: =Source!I75 -> 1.19 | F68: =Source!AK75 -> 46.63 | H68: =Source!AW76 -> 1 | I68: =Source!O75 -> 55.49 | J68: =IF(Source!BC76<> 0, Source!BC76, 1) -> 1.08 | K68: =Source!O76 -> 59.93 | Q68: =Source!X75 -> 0 | R68: =Source!X76 -> 0 | S68: =Source!Y75 -> 0 | T68: =Source!Y76 -> 0 | U68: =ROUND((175/100)*ROUND(Source!R75, 2), 2) -> 0 | V68: =ROUND((0/100)*ROUND(Source!R76, 2), 2) -> 0 | AC68: 3
A69: 5,3 | B69: =Source!F77 -> 1.7-5-131 | C69: Анкер забивной расклинивающийся из оцинкованной стали, с внутренней резьбой М12, длина 25 мм | D69: =Source!H77 -> 100 шт. | E69: =Source!I77 -> 1.18 | F69: =Source!AK77 -> 1297.23 | H69: =Source!AW78 -> 1 | I69: =Source!O77 -> 1530.73 | J69: =IF(Source!BC78<> 0, Source!BC78, 1) -> 5.2 | K69: =Source!O78 -> 7959.8 | Q69: =Source!X77 -> 0 | R69: =Source!X78 -> 0 | S69: =Source!Y77 -> 0 | T69: =Source!Y78 -> 0 | U69: =ROUND((175/100)*ROUND(Source!R77, 2), 2) -> 0 | V69: =ROUND((0/100)*ROUND(Source!R78, 2), 2) -> 0 | AC69: 3
C70: НР от ФОТ | D70: % | E70: =Source!BZ72 -> 90 | I70: =SUM(Q62:Q69) -> 152.48 | J70: =Source!AT72 -> 90 | K70: =SUM(R62:R69) -> 8384.77
C71: СП от ФОТ | D71: % | E71: =Source!CA72 -> 46 | I71: =SUM(S62:S70) -> 77.93 | J71: =Source!AU72 -> 46 | K71: =SUM(T62:T70) -> 4285.55
C72: ЗТР | D72: чел-ч | E72: =Source!AQ71 -> 24.76 | G72: 1,1 | H72: =Source!AV72 -> 1.047 | I72: =Source!U71 -> 14.258046
C73: ВСЕГО работ по позиции: | H73: =I64+I65+I66+I70+I71+SUM(I67:I69)-SUMIF(AC67:AC69, 5, I67:I69)-SUMIF(AC67:AC69, 6, I67:I69) -> 2134.26 | J73: =K64+K65+K66+K70+K71+SUM(K67:K69)-SUMIF(AC67:AC69, 5, K67:K69)-SUMIF(AC67:AC69, 6, K67:K69) -> 30612.98
C74: ВСЕГО оборудование по позиции: | H74: =SUMIF(AC67:AC69, 5, I67:I69)+SUMIF(AC67:AC69, 6, I67:I69) -> 0 | J74: =SUMIF(AC67:AC69, 5, K67:K69)+SUMIF(AC67:AC69, 6, K67:K69) -> 0
C75: ВСЕГО по позиции: | H75: =I64+I65+I66+I70+I71+SUM(I67:I69) -> 2134.26 | J75: =K64+K65+K66+K70+K71+SUM(K67:K69) -> 30612.98 | O75: =I64+I65+I66+I70+I71+SUM(I67:I69) -> 2134.26 | P75: =K64+K65+K66+K70+K71+SUM(K67:K69) -> 30612.98
A77: 6 | B77: =Source!F79 -> 4.8-328-1 | C77: Прокладка кабельного изделия по установленным конструкциям и лоткам, при массе 1 м кабельного изделия до 0,5 кг на высоте до 5 м | D77: =Source!H79 -> 100 м | E77: =Source!I79 -> 0.5 | Q77: =Source!X79 -> 36.81 | R77: =Source!X80 -> 2024.26 | S77: =Source!Y79 -> 19.35 | T77: =Source!Y80 -> 1064.3 | U77: =ROUND((175/100)*ROUND(Source!R79, 2), 2) -> 0.3 | V77: =ROUND((0/100)*ROUND(Source!R80, 2), 2) -> 0 | AC77: 0
C78: ="Объем: "&Source!I79&"=50/"&"100" -> Объем: 0,5=50/100
C79: ЗП | F79: =Source!AO79 -> 65.6 | G79: 1,1 | H79: =Source!AV80 -> 1.047 | I79: =Source!S79 -> 37.78 | J79: =IF(Source!BA80<> 0, Source!BA80, 1) -> 54.99 | K79: =Source!S80 -> 2077.52
C80: ЭМ | F80: =Source!AM79 -> 2.62 | G80: 1,1 | H80: =Source!AV80 -> 1.047 | I80: =Source!Q79 -> 1.51 | J80: =IF(Source!BB80<> 0, Source!BB80, 1) -> 14.57 | K80: =Source!Q80 -> 22
C81: в т.ч. ЗПМ | F81: =Source!AN79 -> 0.3 | G81: 1,1 | H81: =Source!AV80 -> 1.047 | I81: =Source!R79 -> 0.17 | J81: =IF(Source!BS80<> 0, Source!BS80, 1) -> 54.99 | K81: =Source!R80 -> 9.35
C82: МР | F82: =Source!AL79 -> 125.83 | H82: =Source!AW80 -> 1 | I82: =Source!P79 -> 62.92 | J82: =IF(Source!BC80<> 0, Source!BC80, 1) -> 3.96 | K82: =Source!P80 -> 249.16
C83: НР от ФОТ | D83: % | E83: =Source!BZ80 -> 97 | I83: =SUM(Q77:Q82) -> 36.81 | J83: =Source!AT80 -> 97 | K83: =SUM(R77:R82) -> 2024.26
C84: СП от ФОТ | D84: % | E84: =Source!CA80 -> 51 | I84: =SUM(S77:S83) -> 19.35 | J84: =Source!AU80 -> 51 | K84: =SUM(T77:T83) -> 1064.3
C85: ЗТР | D85: чел-ч | E85: =Source!AQ79 -> 5.29 | G85: 1,1 | H85: =Source!AV80 -> 1.047 | I85: =Source!U79 -> 3.0462465
C86: ВСЕГО работ по позиции: | H86: =I79+I80+I82+I83+I84+0-0-0 -> 158.37 | J86: =K79+K80+K82+K83+K84+0-0-0 -> 5437.24
C87: ВСЕГО оборудование по позиции: | H87: =0+0 -> 0 | J87: =0+0 -> 0
C88: ВСЕГО по позиции: | H88: =I79+I80+I82+I83+I84+0 -> 158.37 | J88: =K79+K80+K82+K83+K84+0 -> 5437.24 | O88: =I79+I80+I82+I83+I84+0 -> 158.37 | P88: =K79+K80+K82+K83+K84+0 -> 5437.24
A90: 7 | B90: =Source!F81 -> КА-2 | C90: Кабель КПСВВнг(А)-LSLTx 1x2x1,0 3 104,91 = [36 090 / 1,2 / 9,88] + 2% Заг.скл | D90: =Source!H81 -> км | E90: =Source!I81 -> 0.102 | F90: =Source!AL81 -> 3104.91 | H90: =Source!AW82 -> 1 | I90: =Source!P81 -> 316.7 | J90: =IF(Source!BC82<> 0, Source!BC82, 1) -> 9.88 | K90: =Source!P82 -> 3129 | Q90: =Source!X81 -> 0 | R90: =Source!X82 -> 0 | S90: =Source!Y81 -> 0 | T90: =Source!Y82 -> 0 | U90: =ROUND((175/100)*ROUND(Source!R81, 2), 2) -> 0 | V90: =ROUND((0/100)*ROUND(Source!R82, 2), 2) -> 0 | AC90: 3
C91: ="Объем: "&Source!I81&"=0,1*"&"1,02" -> Объем: 0,102=0,1*1,02
C92: ВСЕГО по позиции: | H92: =I90+0 -> 316.7 | J92: =K90+0 -> 3129 | O92: =I90+0 -> 316.7 | P92: =K90+0 -> 3129
A95: =CONCATENATE("Итого по разделу: ",IF(Source!G84<>"Новый раздел", Source!G84, "")) -> Итого по разделу: Кабельные изделия | H95: =SUM(O61:O94) -> 2609.33 | J95: =SUM(P61:P94) -> 39179.22
A96: Итого по ТСН-2001.16 | I96: =SUM(W61:W95) -> 0 | J96: =SUM(X61:X95) -> 0
A97: Итого возвратных сумм | I97: =SUM(Y61:Y96) -> 0 | J97: =SUM(Z61:Z96) -> 0
A99: =CONCATENATE("Итого по локальной смете: ",IF(Source!G114<>"Новая локальная смета", Source!G114, "")) -> Итого по локальной смете: Электрочасофикация | H99: =SUM(O28:O98) -> 14832.16 | J99: =SUM(P28:P98) -> 140651.64
A100: Итого по ТСН-2001.16 | I100: =SUM(W28:W99) -> 0 | J100: =SUM(X28:X99) -> 0
A101: Итого возвратных сумм | I101: =SUM(Y28:Y100) -> 0 | J101: =SUM(Z28:Z100) -> 0
A103: =CONCATENATE("Итого по смете: ",IF(Source!G144<>"Новый объект", Source!G144, "")) -> Итого по смете: 02-01-13 Электрочасофикация | H103: =SUM(O1:O102) -> 14832.16 | J103: =SUM(P1:P102) -> 140651.64
A104: Итого по ТСН-2001.16 | I104: =SUM(W1:W103) -> 0 | J104: =SUM(X1:X103) -> 0
A105: Итого возвратных сумм | I105: =SUM(Y1:Y104) -> 0 | J105: =SUM(Z1:Z104) -> 0
A108: Составил | C108: =IF(Source!AC12<>"", Source!AC12," ") | H108: =IF(Source!AB12<>"", Source!AB12," ") -> Соколова И.Н.
C109: (должность, подпись, инициалы, фамилия)
A111: Проверил | C111: =IF(Source!AE12<>"", Source!AE12," ") | H111: =IF(Source!AD12<>"", Source!AD12," ")
C112: (должность, подпись, инициалы, фамилия)

Sheet Ведомость объемов работ
A1: =Source!B1 -> Smeta.RU (495) 974-1589
B4: =CONCATENATE("Ведомость объемов работ ", IF(Source!AN15<>"", Source!AN15," ")) -> Ведомость объемов работ
B5: =CONCATENATE(Source!F12, " ", Source!G12) -> 02-01-13 Электрочасофикация
A8: № п/п | B8: № в ЛСР | C8: Наименование работ и затрат | D8: Единица измерения | E8: Количество | F8: Ссылка на чертежи, спецификации | G8: Формула расчета, расчет объемов работ и расхода материалов | H8: Примечание
A9: 1 | B9: 2 | C9: 3 | D9: 4 | E9: 5 | F9: 6 | G9: 7 | H9: 8
A10: =CONCATENATE("Локальная смета: ", Source!G20) -> Локальная смета: Электрочасофикация
A11: =CONCATENATE("Раздел: ", Source!G24) -> Раздел: Оборудование
A12: 1 | B12: =Source!E28 -> 1 | C12: =Source!G28 -> Электрочасы первичные, часы первичные электрические показывающие кварцевые типа ПКЧЗ-2-РИ-Р24-Р6-1 | D12: 1 ШТ. | E12: =Source!I28 -> 1 | F12: =Source!U24 | G12: =Source!I28 -> 1
A13: 2 | B13: =Source!E30 -> 2 | C13: =Source!G30 -> Часовая станция "Первичные часы" ПИК-2М-4002 | D13: ШТ | E13: =Source!I30 -> 1 | F13: =Source!U24 | G13: =Source!I30 -> 1
A14: 3 | B14: =Source!E32 -> 3 | C14: =Source!G32 -> Электрочасы вторичные для помещений, электрочасы односторонние на стене | D14: 1 ШТ. | E14: =Source!I32 -> 2 | F14: =Source!U24 | G14: =Source!I32 -> 2
A15: 4 | B15: =Source!E34 -> 4 | C15: =Source!G34 -> Часы электрические вторичные стрелочные, типа ВЧ03/03 | D15: шт. | E15: =Source!I34 -> 2 | F15: =Source!U24 | G15: =Source!I34 -> 2
A16: =CONCATENATE("Раздел: ", Source!G67) -> Раздел: Кабельные изделия
A17: 5 | B17: =Source!E71 -> 5 | C17: =Source!G71 -> Прокладка кабеля связи огнестойкого в трубах гофрированных с использованием скобы СМО: по бетонным поверхностям | D17: 100 м | E17: =Source!I71 -> 0.5 | F17: =Source!U67 | G17: ="=50/"&"100" -> =50/100
A18: 6 | B18: =Source!E79 -> 6 | C18: =Source!G79 -> Прокладка кабельного изделия по установленным конструкциям и лоткам, при массе 1 м кабельного изделия до 0,5 кг на высоте до 5 м | D18: 100 м | E18: =Source!I79 -> 0.5 | F18: =Source!U67 | G18: ="=50/"&"100" -> =50/100
A19: 7 | B19: =Source!E81 -> 7 | C19: =Source!G81 -> Кабель КПСВВнг(А)-LSLTx 1x2x1,0 | D19: км | E19: =Source!I81 -> 0.102 | F19: =Source!U67 | G19: ="=0,1*"&"1,02" -> =0,1*1,02
C22: Главный инженер проекта _________________ | D22: =IF(Source!X12<>"", Source!X12," ")
C24: Составил _________________ | D24: =IF(Source!AB12<>"", Source!AB12," ") -> Соколова И.Н.

Sheet Source
A1: 0 | B1: Smeta.RU (495) 974-1589 | D1: _PS_ | F1: 0 | G1: 0 | H1: 0 | I1: Smeta.RU | K1: 1 | L1: 74563 | M1: 10 | N1: 12 | O1: 1 | P1: 0 | Q1: 0
A4: 1 | B4: 1 | C4: -1 | G4: Капитальный ремонт здания Государственного бюджетного общеобразовательного учреждения города Москвы "Школа №236" по адресу: г. Москва, улица Клязьминская, дом 7, корпус 4 | EC4: 0
A12: 1 | B12: 183 | C12: 0 | D12: =ROW(A144) -> 144 | E12: 0 | G12: 02-01-13 Электрочасофикация | I12: 0 | J12: 2024-00272-01-0-ИОС5.6 | K12: 0 | L12: 0 | M12: 4098 | O12: 0 | P12: 0 | Q12: 0 | R12: 0 | S12: 0 | T12: 1 | V12: 0 | AB12: Соколова И.Н. | BB12: 0 | BH12: Сметные нормы списания | BI12: Коды ОКП для ТСН-2001 МГЭ Дополнение 80 | BJ12: 1 | BK12: 1 | BL12: 0 | BM12: 0 | BN12: 1 | BO12: 0 | BP12: 6 | BQ12: 2 | BR12: 1 | BS12: 1 | BT12: 0 | BU12: 0 | BV12: 0 | BW12: 0 | BX12: 0 | BZ12: Типовой расчет для ТСН-2001 МГЭ, Дополнение 80, строительство (1) | CA12: Территориальные сметные нормативы для Москвы ТСН-2001 (МГЭ), дополнение 80 | CB12: Территориальные сметные нормативы для Москвы ТСН-2001 (МГЭ), дополнение 80 | CC12: Территориальные сметные нормативы для Москвы ТСН-2001 (МГЭ), дополнение 80 | CD12: Территориальные сметные нормативы для Москвы ТСН-2001 (МГЭ), дополнение 80 | CE12: Поправки для ТСН-2001 от 28.11.2025 г. доп.79 | CF12: 0 | CG12: 0 | CH12: 8200 | CK12: 81 | CQ12: Территориальные сметные нормативы для Москвы (ТСН-2001) | CR12: ТЕР | CS12: 41660 | CT12: 1 | CU12: 80 | CY12: 0 | EC12: 0
A15: 15 | B15: 1
A18: 52 | B18: =B144 -> 183 | C18: =C144 -> 1 | D18: =D144 -> 12 | E18: =E144 -> 0 | F18: =F144 | G18: =G144 -> 02-01-13 Электрочасофикация | O18: =O144 -> 14406.32 | P18: =P144 -> 14092.88 | Q18: =Q144 -> 3.84 | R18: =R144 -> 0.17 | S18: =S144 -> 309.6 | T18: =T144 -> 0 | U18: =U144 -> 25.366193 | V18: =V144 -> 0 | ... GX18: =GX144 -> 0
A20: 3 | B20: 1 | D20: =ROW(A114) -> 114 | F20: 02-01-13 | G20: Электрочасофикация | I20: 0 | J20: 2024-00272-01-0-ИОС5.6 | K20: -1 | L20: 02-01-13 | S20: 0 | T20: 0 | V20: 2 | BX20: 0 | CF20: 0 | CG20: 0
A22: 52 | B22: =B114 -> 1 | C22: =C114 -> 3 | D22: =D114 -> 20 | E22: =E114 -> 0 | F22: =F114 -> 02-01-13 | G22: =G114 -> Электрочасофикация | O22: =O114 -> 14406.32 | P22: =P114 -> 14092.88 | Q22: =Q114 -> 3.84 | R22: =R114 -> 0.17 | S22: =S114 -> 309.6 | T22: =T114 -> 0 | U22: =U114 -> 25.366193 | V22: =V114 -> 0 | ... GX22: =GX114 -> 0
A24: 4 | B24: 1 | D24: =ROW(A37) -> 37 | G24: Оборудование | I24: 0 | K24: -1 | S24: 0 | T24: 0 | V24: 2 | BX24: 0 | CJ24: 0
A26: 52 | B26: =B37 -> 1 | C26: =C37 -> 4 | D26: =D37 -> 24 | E26: =E37 -> 0 | F26: =F37 | G26: =G37 -> Оборудование | O26: =O37 -> 12083.56 | P26: =P37 -> 11981.16 | Q26: =Q37 -> 0 | R26: =R37 -> 0 | S26: =S37 -> 102.4 | T26: =T37 -> 0 | U26: =U37 -> 8.0619 | V26: =V37 -> 0 | ... GX26: =GX37 -> 0
A28: 17 | B28: 1 | C28: =ROW(SmtRes!A1) -> 1 | D28: =ROW(EtalonRes!A1) -> 1 | E28: 1 | F28: 4.10-85-1 | G28: Электрочасы первичные, часы первичные электрические показывающие кварцевые типа ПКЧЗ-2-РИ-Р24-Р6-1 | H28: 1 ШТ. | I28: 1 | J28: 0 | K28: 1 | O28: =ROUND(CP28,2) -> 48.07 | P28: =ROUND((ROUND((AC28*AW28*I28),2)*BC28),2) -> 0.49 | Q28: =(ROUND((ROUND((((ET28*1.1))*AV28*I28),2)*BB28),2)+ROUND((ROUND(((AE28-((EU28*1.1)))*AV28*I28),2)*BS28),2)) -> 0 | R28: =(ROUND((ROUND((((EU28*1.1))*AV28*I28),2)*BS28),2)+ROUND((ROUND(((AE28-((EU28*1.1)))*AV28*I28),2)*BS28),2)) -> 0 | S28: =ROUND((ROUND((AF28*AV28*I28),2)*BA28),2) -> 47.58 | T28: =ROUND(CU28*I28,2) -> 0 | U28: =CV28*I28 -> 3.4551 | V28: =CW28*I28 -> 0 | W28: =ROUND(CX28*I28,2) -> 0 | X28: =(ROUND((((S28+ROUND((ROUND((((EU28*1.1))*AV28*I28),2)*BS28),2))*AT28)/100),2)+ROUND(((ROUND((ROUND(((AE28-((EU28*1.1)))*AV28*I28),2)*BS28),2)*AT28)/100),2)) -> 42.82 | Y28: =(ROUND((((S28+ROUND((ROUND((((EU28*1.1))*AV28*I28),2)*BS28),2))*AU28)/100),2)+ROUND(((ROUND((ROUND(((AE28-((EU28*1.1)))*AV28*I28),2)*BS28),2)*AU28)/100),2)) -> 21.89 | AA28: 60257736 | AB28: =ROUND((AC28+AD28+AF28),6) -> 45.931 | AC28: =ROUND(((ES28*1)),6) -> 0.49 | AD28: =ROUND(((((ET28*1.1))-((EU28*1.1)))+AE28),6) -> 0 | AE28: =ROUND(((EU28*1.1)),6) -> 0 | AF28: =ROUND(((EV28*1.1)),6) -> 45.441 | AG28: =ROUND((AP28),6) -> 0 | AH28: =((EW28*1.1)) -> 3.3 | AI28: =((EX28*1.1)) -> 0 | AJ28: =(AS28) -> 0 | AK28: 41.8 | AL28: 0.49 | AM28: 0 | AN28: 0 | AO28: 41.31 | AP28: 0 | AQ28: 3 | AR28: 0 | AS28: 0 | AT28: 90 | AU28: 46 | AV28: 1.047 | AW28: 1 | AZ28: 1 | BA28: 1 | BB28: 1 | BC28: 1 | BH28: 0 | BI28: 2 | BJ28: ТСН-2001.4 Доп. 80, Сб. 10, т. 85, поз. 1 | BM28: 68 | BN28: 58973116 | BO28: 4.10-85-1 | BP28: 1 | BQ28: 40 | BR28: 0 | BS28: 1 | BT28: 1 | BU28: 1 | BV28: 1 | BW28: 1 | BX28: 1 | BZ28: 90 | CA28: 46 | CE28: 1566 | CF28: 0 | CG28: 0 | CM28: 0 | CN28: Поправка: Гл.12.Прил.8.п.8. 5_12.00.01.11.003 Наименование: При наличии усложненных условий производства работ (стесненность, сложность складирования и транспортной логистики, наличие в зоне производства работ действующего технологического оборудования или движения технологического транспорта и т.п.) для объектов, расположенных за пределами территории круговой магистральной системы улиц "Садовое кольцо" и за пределами Третьего транспортного кольца города Москвы пунктов "а" и "б", но в пределах Московской кольцевой автомобильной дороги | CO28: 0 | CP28: =(P28+Q28+S28) -> 48.07 | CQ28: =ROUND((ROUND((AC28*AW28*1),2)*BC28),2) -> 0.49 | CR28: =(ROUND((ROUND((((ET28*1.1))*AV28*1),2)*BB28),2)+ROUND((ROUND(((AE28-((EU28*1.1)))*AV28*1),2)*BS28),2)) -> 0 | CS28: =(ROUND((ROUND((((EU28*1.1))*AV28*1),2)*BS28),2)+ROUND((ROUND(((AE28-((EU28*1.1)))*AV28*1),2)*BS28),2)) -> 0 | CT28: =ROUND((ROUND((AF28*AV28*1),2)*BA28),2) -> 47.58 | CU28: =AG28 -> 0 | CV28: =(AH28*AV28) -> 3.4551 | CW28: =AI28 -> 0 | CX28: =AJ28 -> 0 | CY28: =(ROUND((((S28+ROUND((ROUND((((EU28*1.1))*AV28*1),2)*BS28),2))*AT28)/100),2)+ROUND(((ROUND((ROUND(((AE28-((EU28*1.1)))*AV28*1),2)*BS28),2)*AT28)/100),2)) -> 42.82 | CZ28: =(ROUND((((S28+ROUND((ROUND((((EU28*1.1))*AV28*1),2)*BS28),2))*AU28)/100),2)+ROUND(((ROUND((ROUND(((AE28-((EU28*1.1)))*AV28*1),2)*BS28),2)*AU28)/100),2)) -> 21.89 | DB28: 1 | DD28: *1 | DE28: *1,1 | DF28: *1,1 | DG28: *1,1 | DI28: *1,1 | DJ28: *1,1 | DN28: 0 | DO28: 0 | DP28: 1 | DQ28: 1 | DU28: 1013 | DV28: 1 ШТ. | DW28: 1 ШТ. | DX28: 1 | EE28: 60088532 | EF28: 40 | EG28: Монтаж оборудования | EH28: 0 | EJ28: 2 | EK28: 68 | EL28: ТСН-2001.4-10. Прокладка и монтаж сетей связи | EM28: ТСН-2001.4-10-1 | EO28: Поправка: Гл.12.Прил.8.п.8. 5_12.00.01.11.003 | EQ28: 0 | ER28: 41.8 | ES28: 0.49 | ET28: 0 | EU28: 0 | EV28: 41.31 | EW28: 3 | EX28: 0 | EY28: 0 | FQ28: 0 | FR28: 0 | FS28: 0 | FX28: 90 | FY28: 46 | GD28: 1 | GF28: -1862400035 | GG28: 2 | GH28: 1 | GI28: 2 | GJ28: 0 | GK28: 0 | GL28: =ROUND(IF(AND(BH28=3,BI28=3,FS28<>0),P28,0),2) -> 0 | GM28: =ROUND(O28+X28+Y28,2)+GX28 -> 112.78 | GN28: =IF(OR(BI28=0,BI28=1),GM28-GX28,0) -> 0 | GO28: =IF(BI28=2,GM28-GX28,0) -> 112.78 | GP28: =IF(BI28=4,GM28-GX28,0) -> 0 | GR28: 0 | GS28: 3 | GT28: 0 | GV28: =ROUND((GT28),6) -> 0 | GW28: 1 | GX28: =ROUND(HC28*I28,2) -> 0 | HA28: 0 | HB28: 0 | HC28: =GV28*GW28 -> 0 | HS28: 0 | IK28: 0
A29: 17 | B29: 1 | C29: =ROW(SmtRes!A2) -> 2 | D29: =ROW(EtalonRes!A2) -> 2 | E29: 1 | F29: 4.10-85-1 | G29: Электрочасы первичные, часы первичные электрические показывающие кварцевые типа ПКЧЗ-2-РИ-Р24-Р6-1 | H29: 1 ШТ. | I29: 1 | J29: 0 | K29: 1 | O29: =ROUND(CP29,2) -> 2621.27 | P29: =ROUND((ROUND((AC29*AW29*I29),2)*BC29),2) -> 4.85 | Q29: =(ROUND((ROUND((((ET29*1.1))*AV29*I29),2)*BB29),2)+ROUND((ROUND(((AE29-((EU29*1.1)))*AV29*I29),2)*BS29),2)) -> 0 | R29: =(ROUND((ROUND((((EU29*1.1))*AV29*I29),2)*BS29),2)+ROUND((ROUND(((AE29-((EU29*1.1)))*AV29*I29),2)*BS29),2)) -> 0 | S29: =ROUND((ROUND((AF29*AV29*I29),2)*BA29),2) -> 2616.42 | T29: =ROUND(CU29*I29,2) -> 0 | U29: =CV29*I29 -> 3.4551 | V29: =CW29*I29 -> 0 | W29: =ROUND(CX29*I29,2) -> 0 | X29: =(ROUND((((S29+ROUND((ROUND((((EU29*1.1))*AV29*I29),2)*BS29),2))*AT29)/100),2)+ROUND(((ROUND((ROUND(((AE29-((EU29*1.1)))*AV29*I29),2)*BS29),2)*AT29)/100),2)) -> 2354.78 | Y29: =(ROUND((((S29+ROUND((ROUND((((EU29*1.1))*AV29*I29),2)*BS29),2))*AU29)/100),2)+ROUND(((ROUND((ROUND(((AE29-((EU29*1.1)))*AV29*I29),2)*BS29),2)*AU29)/100),2)) -> 1203.55 | AA29: 60257733 | AB29: =ROUND((AC29+AD29+AF29),6) -> 45.931 | AC29: =ROUND(((ES29*1)),6) -> 0.49 | AD29: =ROUND(((((ET29*1.1))-((EU29*1.1)))+AE29),6) -> 0 | AE29: =ROUND(((EU29*1.1)),6) -> 0 | AF29: =ROUND(((EV29*1.1)),6) -> 45.441 | AG29: =ROUND((AP29),6) -> 0 | AH29: =((EW29*1.1)) -> 3.3 | AI29: =((EX29*1.1)) -> 0 | AJ29: =(AS29) -> 0 | AK29: 41.8 | AL29: 0.49 | AM29: 0 | AN29: 0 | AO29: 41.31 | AP29: 0 | AQ29: 3 | AR29: 0 | AS29: 0 | AT29: 90 | AU29: 46 | AV29: 1.047 | AW29: 1 | AZ29: 1 | BA29: 54.99 | BB29: 1 | BC29: 9.9 | BH29: 0 | BI29: 2 | BJ29: ТСН-2001.4 Доп. 80, Сб. 10, т. 85, поз. 1 | BM29: 68 | BN29: 58973116 | BO29: 4.10-85-1 | BP29: 1 | BQ29: 40 | BR29: 0 | BS29: 54.99 | BT29: 1 | BU29: 1 | BV29: 1 | BW29: 1 | BX29: 1 | BZ29: 90 | CA29: 46 | CE29: 1566 | CF29: 0 | CG29: 0 | CM29: 0 | CN29: Поправка: Гл.12.Прил.8.п.8. 5_12.00.01.11.003 Наименование: При наличии усложненных условий производства работ (стесненность, сложность складирования и транспортной логистики, наличие в зоне производства работ действующего технологического оборудования или движения технологического транспорта и т.п.) для объектов, расположенных за пределами территории круговой магистральной системы улиц "Садовое кольцо" и за пределами Третьего транспортного кольца города Москвы пунктов "а" и "б", но в пределах Московской кольцевой автомобильной дороги | CO29: 0 | CP29: =(P29+Q29+S29) -> 2621.27 | CQ29: =ROUND((ROUND((AC29*AW29*1),2)*BC29),2) -> 4.85 | CR29: =(ROUND((ROUND((((ET29*1.1))*AV29*1),2)*BB29),2)+ROUND((ROUND(((AE29-((EU29*1.1)))*AV29*1),2)*BS29),2)) -> 0 | CS29: =(ROUND((ROUND((((EU29*1.1))*AV29*1),2)*BS29),2)+ROUND((ROUND(((AE29-((EU29*1.1)))*AV29*1),2)*BS29),2)) -> 0 | CT29: =ROUND((ROUND((AF29*AV29*1),2)*BA29),2) -> 2616.42 | CU29: =AG29 -> 0 | CV29: =(AH29*AV29) -> 3.4551 | CW29: =AI29 -> 0 | CX29: =AJ29 -> 0 | CY29: =(ROUND((((S29+ROUND((ROUND((((EU29*1.1))*AV29*1),2)*BS29),2))*AT29)/100),2)+ROUND(((ROUND((ROUND(((AE29-((EU29*1.1)))*AV29*1),2)*BS29),2)*AT29)/100),2)) -> 2354.78 | CZ29: =(ROUND((((S29+ROUND((ROUND((((EU29*1.1))*AV29*1),2)*BS29),2))*AU29)/100),2)+ROUND(((ROUND((ROUND(((AE29-((EU29*1.1)))*AV29*1),2)*BS29),2)*AU29)/100),2)) -> 1203.55 | DB29: 2 | DD29: *1 | DE29: *1,1 | DF29: *1,1 | DG29: *1,1 | DI29: *1,1 | DJ29: *1,1 | DN29: 0 | DO29: 0 | DP29: 1 | DQ29: 1 | DU29: 1013 | DV29: 1 ШТ. | DW29: 1 ШТ. | DX29: 1 | EE29: 60088532 | EF29: 40 | EG29: Монтаж оборудования | EH29: 0 | EJ29: 2 | EK29: 68 | EL29: ТСН-2001.4-10. Прокладка и монтаж сетей связи | EM29: ТСН-2001.4-10-1 | EO29: Поправка: Гл.12.Прил.8.п.8. 5_12.00.01.11.003 | EQ29: 0 | ER29: 41.8 | ES29: 0.49 | ET29: 0 | EU29: 0 | EV29: 41.31 | EW29: 3 | EX29: 0 | EY29: 0 | FQ29: 0 | FR29: 0 | FS29: 0 | FX29: 90 | FY29: 46 | GD29: 1 | GF29: -1862400035 | GG29: 2 | GH29: 1 | GI29: 2 | GJ29: 0 | GK29: 0 | GL29: =ROUND(IF(AND(BH29=3,BI29=3,FS29<>0),P29,0),2) -> 0 | GM29: =ROUND(O29+X29+Y29,2)+GX29 -> 6179.6 | GN29: =IF(OR(BI29=0,BI29=1),GM29-GX29,0) -> 0 | GO29: =IF(BI29=2,GM29-GX29,0) -> 6179.6 | GP29: =IF(BI29=4,GM29-GX29,0) -> 0 | GR29: 0 | GS29: 3 | GT29: 0 | GV29: =ROUND((GT29),6) -> 0 | GW29: 1 | GX29: =ROUND(HC29*I29,2) -> 0 | HA29: 0 | HB29: 0 | HC29: =GV29*GW29 -> 0 | HS29: 0 | IK29: 0
A30: 17 | B30: 1 | E30: 2 | F30: КА-1 | G30: Часовая станция "Первичные часы" ПИК-2М-4002 | H30: ШТ | I30: 1 | J30: 0 | K30: 1 | O30: =ROUND(CP30,2) -> 10518.85 | P30: =ROUND((ROUND((AC30*I30),2)*BC30),2) -> 10518.85 | Q30: =(ROUND((ROUND(((ET30)*AV30*I30),2)*BB30),2)+ROUND((ROUND(((AE30-(EU30))*AV30*I30),2)*BS30),2)) -> 0 | R30: =(ROUND((ROUND(((EU30)*AV30*I30),2)*BS30),2)+ROUND((ROUND(((AE30-(EU30))*AV30*I30),2)*BS30),2)) -> 0 | S30: =ROUND((ROUND((AF30*AV30*I30),2)*BA30),2) -> 0 | T30: =ROUND(CU30*I30,2) -> 0 | U30: =CV30*I30 -> 0 | V30: =CW30*I30 -> 0 | W30: =ROUND(CX30*I30,2) -> 0 | X30: =(ROUND((((S30+ROUND((ROUND(((EU30)*AV30*I30),2)*BS30),2))*AT30)/100),2)+ROUND(((ROUND((ROUND(((AE30-(EU30))*AV30*I30),2)*BS30),2)*AT30)/100),2)) -> 0 | Y30: =(ROUND((((S30+ROUND((ROUND(((EU30)*AV30*I30),2)*BS30),2))*AU30)/100),2)+ROUND(((ROUND((ROUND(((AE30-(EU30))*AV30*I30),2)*BS30),2)*AU30)/100),2)) -> 0 | AA30: 60257736 | AB30: =ROUND((AC30+AD30+AF30),6) -> 10518.85 | AC30: =ROUND((ES30),6) -> 10518.85 | AD30: =ROUND((((ET30)-(EU30))+AE30),6) -> 0 | AE30: =ROUND((EU30),6) -> 0 | AF30: =ROUND((EV30),6) -> 0 | AG30: =ROUND((AP30),6) -> 0 | AH30: =(EW30) -> 0 | AI30: =(EX30) -> 0 | AJ30: =(AS30) -> 0 | AK30: 10518.85 | AL30: 10518.85 | AM30: 0 | AN30: 0 | AO30: 0 | AP30: 0 | AQ30: 0 | AR30: 0 | AS30: 0 | AT30: 0 | AU30: 0 | AV30: 1 | AW30: 1 | AZ30: 1 | BA30: 1 | BB30: 1 | BC30: 1 | BH30: 3 | BI30: 3 | BM30: 746 | BN30: 0 | BP30: 0 | BQ30: 130 | BR30: 0 | BS30: 1 | BT30: 1 | BU30: 1 | BV30: 1 | BW30: 1 | BX30: 1 | BZ30: 0 | CA30: 0 | CE30: 1566 | CF30: 0 | CG30: 0 | CM30: 0 | CO30: 0 | CP30: =(P30+Q30+S30) -> 10518.85 | CQ30: =ROUND((ROUND((AC30*1),2)*BC30),2) -> 10518.85 | CR30: =(ROUND((ROUND(((ET30)*AV30*1),2)*BB30),2)+ROUND((ROUND(((AE30-(EU30))*AV30*1),2)*BS30),2)) -> 0 | CS30: =(ROUND((ROUND(((EU30)*AV30*1),2)*BS30),2)+ROUND((ROUND(((AE30-(EU30))*AV30*1),2)*BS30),2)) -> 0 | CT30: =ROUND((ROUND((AF30*AV30*1),2)*BA30),2) -> 0 | CU30: =AG30 -> 0 | CV30: =(AH30*AV30) -> 0 | CW30: =AI30 -> 0 | CX30: =AJ30 -> 0 | CY30: =(ROUND((((S30+ROUND((ROUND(((EU30)*AV30*1),2)*BS30),2))*AT30)/100),2)+ROUND(((ROUND((ROUND(((AE30-(EU30))*AV30*1),2)*BS30),2)*AT30)/100),2)) -> 0 | CZ30: =(ROUND((((S30+ROUND((ROUND(((EU30)*AV30*1),2)*BS30),2))*AU30)/100),2)+ROUND(((ROUND((ROUND(((AE30-(EU30))*AV30*1),2)*BS30),2)*AU30)/100),2)) -> 0 | DN30: 0 | DO30: 0 | DP30: 1 | DQ30: 1 | DU30: 1013 | DV30: ШТ | DW30: ШТ | DX30: 1 | EE30: 60088638 | EF30: 130 | EG30: Сметная стоимость оборудования | EH30: 0 | EJ30: 3 | EK30: 746 | EL30: ТСН-2001.13. Сметная стоимость оборудования | EM30: ТСН-2001.13 | EQ30: 0 | ER30: 0 | ES30: 10518.85 | ET30: 0 | EU30: 0 | EV30: 0 | EW30: 0 | EX30: 0 | EY30: 0 | FQ30: 0 | FR30: =P30 -> 10518.85 | FS30: 0 | FX30: 0 | FY30: 0 | GA30: [92 760 / 1,2 / 7,66] + 3% Трансп + 1,2% Заг.скл | GD30: 1 | GF30: -2034863319 | GG30: 2 | GH30: 4 | GI30: -2 | GJ30: 0 | GK30: 0 | GL30: =ROUND(IF(AND(BH30=3,BI30=3,FS30<>0),P30,0),2) -> 0 | GM30: =ROUND(O30+X30+Y30,2)+GX30 -> 10518.85 | GN30: =IF(OR(BI30=0,BI30=1),GM30-GX30,0) -> 0 | GO30: =IF(BI30=2,GM30-GX30,0) -> 0 | GP30: =IF(BI30=4,GM30-GX30,0) -> 0 | GR30: 0 | GS30: 2 | GT30: 0 | GV30: =ROUND((GT30),6) -> 0 | GW30: 1 | GX30: =ROUND(HC30*I30,2) -> 0 | HA30: 0 | HB30: 0 | HC30: =GV30*GW30 -> 0 | HE30: 3 | HF30: 1,2 | HS30: 0 | IK30: 0
A31: 17 | B31: 1 | E31: 2 | F31: КА-1 | G31: Часовая станция "Первичные часы" ПИК-2М-4002 | H31: ШТ | I31: 1 | J31: 0 | K31: 1 | O31: =ROUND(CP31,2) -> 80574.39 | P31: =ROUND((ROUND((AC31*I31),2)*BC31),2) -> 80574.39 | Q31: =(ROUND((ROUND(((ET31)*AV31*I31),2)*BB31),2)+ROUND((ROUND(((AE31-(EU31))*AV31*I31),2)*BS31),2)) -> 0 | R31: =(ROUND((ROUND(((EU31)*AV31*I31),2)*BS31),2)+ROUND((ROUND(((AE31-(EU31))*AV31*I31),2)*BS31),2)) -> 0 | S31: =ROUND((ROUND((AF31*AV31*I31),2)*BA31),2) -> 0 | T31: =ROUND(CU31*I31,2) -> 0 | U31: =CV31*I31 -> 0 | V31: =CW31*I31 -> 0 | W31: =ROUND(CX31*I31,2) -> 0 | X31: =(ROUND((((S31+ROUND((ROUND(((EU31)*AV31*I31),2)*BS31),2))*AT31)/100),2)+ROUND(((ROUND((ROUND(((AE31-(EU31))*AV31*I31),2)*BS31),2)*AT31)/100),2)) -> 0 | Y31: =(ROUND((((S31+ROUND((ROUND(((EU31)*AV31*I31),2)*BS31),2))*AU31)/100),2)+ROUND(((ROUND((ROUND(((AE31-(EU31))*AV31*I31),2)*BS31),2)*AU31)/100),2)) -> 0 | AA31: 60257733 | AB31: =ROUND((AC31+AD31+AF31),6) -> 10518.85 | AC31: =ROUND((ES31),6) -> 10518.85 | AD31: =ROUND((((ET31)-(EU31))+AE31),6) -> 0 | AE31: =ROUND((EU31),6) -> 0 | AF31: =ROUND((EV31),6) -> 0 | AG31: =ROUND((AP31),6) -> 0 | AH31: =(EW31) -> 0 | AI31: =(EX31) -> 0 | AJ31: =(AS31) -> 0 | AK31: 10518.85 | AL31: 10518.85 | AM31: 0 | AN31: 0 | AO31: 0 | AP31: 0 | AQ31: 0 | AR31: 0 | AS31: 0 | AT31: 0 | AU31: 0 | AV31: 1 | AW31: 1 | AZ31: 1 | BA31: 1 | BB31: 1 | BC31: 7.66 | BH31: 3 | BI31: 3 | BM31: 746 | BN31: 0 | BP31: 0 | BQ31: 130 | BR31: 0 | BS31: 1 | BT31: 1 | BU31: 1 | BV31: 1 | BW31: 1 | BX31: 1 | BZ31: 0 | CA31: 0 | CE31: 1566 | CF31: 0 | CG31: 0 | CM31: 0 | CO31: 0 | CP31: =(P31+Q31+S31) -> 80574.39 | CQ31: =ROUND((ROUND((AC31*1),2)*BC31),2) -> 80574.39 | CR31: =(ROUND((ROUND(((ET31)*AV31*1),2)*BB31),2)+ROUND((ROUND(((AE31-(EU31))*AV31*1),2)*BS31),2)) -> 0 | CS31: =(ROUND((ROUND(((EU31)*AV31*1),2)*BS31),2)+ROUND((ROUND(((AE31-(EU31))*AV31*1),2)*BS31),2)) -> 0 | CT31: =ROUND((ROUND((AF31*AV31*1),2)*BA31),2) -> 0 | CU31: =AG31 -> 0 | CV31: =(AH31*AV31) -> 0 | CW31: =AI31 -> 0 | CX31: =AJ31 -> 0 | CY31: =(ROUND((((S31+ROUND((ROUND(((EU31)*AV31*1),2)*BS31),2))*AT31)/100),2)+ROUND(((ROUND((ROUND(((AE31-(EU31))*AV31*1),2)*BS31),2)*AT31)/100),2)) -> 0 | CZ31: =(ROUND((((S31+ROUND((ROUND(((EU31)*AV31*1),2)*BS31),2))*AU31)/100),2)+ROUND(((ROUND((ROUND(((AE31-(EU31))*AV31*1),2)*BS31),2)*AU31)/100),2)) -> 0 | DN31: 0 | DO31: 0 | DP31: 1 | DQ31: 1 | DU31: 1013 | DV31: ШТ | DW31: ШТ | DX31: 1 | EE31: 60088638 | EF31: 130 | EG31: Сметная стоимость оборудования | EH31: 0 | EJ31: 3 | EK31: 746 | EL31: ТСН-2001.13. Сметная стоимость оборудования | EM31: ТСН-2001.13 | EQ31: 0 | ER31: 0 | ES31: 10518.85 | ET31: 0 | EU31: 0 | EV31: 0 | EW31: 0 | EX31: 0 | EY31: 0 | EZ31: 5 | FC31: 1 | FD31: 18 | FF31: 92760 | FQ31: 0 | FR31: =P31 -> 80574.39 | FS31: 0 | FX31: 0 | FY31: 0 | GA31: [92 760 / 1,2 / 7,66] + 3% Трансп + 1,2% Заг.скл | GD31: 1 | GF31: -2034863319 | GG31: 2 | GH31: 3 | GI31: 5 | GJ31: 0 | GK31: 0 | GL31: =ROUND(IF(AND(BH31=3,BI31=3,FS31<>0),P31,0),2) -> 0 | GM31: =ROUND(O31+X31+Y31,2)+GX31 -> 80574.39 | GN31: =IF(OR(BI31=0,BI31=1),GM31-GX31,0) -> 0 | GO31: =IF(BI31=2,GM31-GX31,0) -> 0 | GP31: =IF(BI31=4,GM31-GX31,0) -> 0 | GR31: 1 | GS31: 1 | GT31: 0 | GV31: =ROUND((GT31),6) -> 0 | GW31: 1 | GX31: =ROUND(HC31*I31,2) -> 0 | HA31: 0 | HB31: 0 | HC31: =GV31*GW31 -> 0 | HE31: 3 | HF31: 1,2 | HS31: 0 | IK31: 0
A32: 17 | B32: 1 | C32: =ROW(SmtRes!A3) -> 3 | D32: =ROW(EtalonRes!A3) -> 3 | E32: 3 | F32: 4.10-86-1 | G32: Электрочасы вторичные для помещений, электрочасы односторонние на стене | H32: 1 ШТ. | I32: 2 | J32: 0 | K32: 2 | O32: =ROUND(CP32,2) -> 55.38 | P32: =ROUND((ROUND((AC32*AW32*I32),2)*BC32),2) -> 0.56 | Q32: =(ROUND((ROUND((((ET32*1.1))*AV32*I32),2)*BB32),2)+ROUND((ROUND(((AE32-((EU32*1.1)))*AV32*I32),2)*BS32),2)) -> 0 | R32: =(ROUND((ROUND((((EU32*1.1))*AV32*I32),2)*BS32),2)+ROUND((ROUND(((AE32-((EU32*1.1)))*AV32*I32),2)*BS32),2)) -> 0 | S32: =ROUND((ROUND((AF32*AV32*I32),2)*BA32),2) -> 54.82 | T32: =ROUND(CU32*I32,2) -> 0 | U32: =CV32*I32 -> 4.6068 | V32: =CW32*I32 -> 0 | W32: =ROUND(CX32*I32,2) -> 0 | X32: =(ROUND((((S32+ROUND((ROUND((((EU32*1.1))*AV32*I32),2)*BS32),2))*AT32)/100),2)+ROUND(((ROUND((ROUND(((AE32-((EU32*1.1)))*AV32*I32),2)*BS32),2)*AT32)/100),2)) -> 49.34 | Y32: =(ROUND((((S32+ROUND((ROUND((((EU32*1.1))*AV32*I32),2)*BS32),2))*AU32)/100),2)+ROUND(((ROUND((ROUND(((AE32-((EU32*1.1)))*AV32*I32),2)*BS32),2)*AU32)/100),2)) -> 25.22 | AA32: 60257736 | AB32: =ROUND((AC32+AD32+AF32),6) -> 26.46 | AC32: =ROUND(((ES32*1)),6) -> 0.28 | AD32: =ROUND(((((ET32*1.1))-((EU32*1.1)))+AE32),6) -> 0 | AE32: =ROUND(((EU32*1.1)),6) -> 0 | AF32: =ROUND(((EV32*1.1)),6) -> 26.18 | AG32: =ROUND((AP32),6) -> 0 | AH32: =((EW32*1.1)) -> 2.2 | AI32: =((EX32*1.1)) -> 0 | AJ32: =(AS32) -> 0 | AK32: 24.08 | AL32: 0.28 | AM32: 0 | AN32: 0 | AO32: 23.8 | AP32: 0 | AQ32: 2 | AR32: 0 | AS32: 0 | AT32: 90 | AU32: 46 | AV32: 1.047 | AW32: 1 | AZ32: 1 | BA32: 1 | BB32: 1 | BC32: 1 | BH32: 0 | BI32: 2 | BJ32: ТСН-2001.4. Доп. 1-42. Сб. 10, т. 86, поз. 1 | BM32: 68 | BN32: 58973116 | BO32: 4.10-86-1 | BP32: 1 | BQ32: 40 | BR32: 0 | BS32: 1 | BT32: 1 | BU32: 1 | BV32: 1 | BW32: 1 | BX32: 1 | BZ32: 90 | CA32: 46 | CE32: 1566 | CF32: 0 | CG32: 0 | CM32: 0 | CN32: Поправка: Гл.12.Прил.8.п.8. 5_12.00.01.11.003 Наименование: При наличии усложненных условий производства работ (стесненность, сложность складирования и транспортной логистики, наличие в зоне производства работ действующего технологического оборудования или движения технологического транспорта и т.п.) для объектов, расположенных за пределами территории круговой магистральной системы улиц "Садовое кольцо" и за пределами Третьего транспортного кольца города Москвы пунктов "а" и "б", но в пределах Московской кольцевой автомобильной дороги | CO32: 0 | CP32: =(P32+Q32+S32) -> 55.38 | CQ32: =ROUND((ROUND((AC32*AW32*1),2)*BC32),2) -> 0.28 | CR32: =(ROUND((ROUND((((ET32*1.1))*AV32*1),2)*BB32),2)+ROUND((ROUND(((AE32-((EU32*1.1)))*AV32*1),2)*BS32),2)) -> 0 | CS32: =(ROUND((ROUND((((EU32*1.1))*AV32*1),2)*BS32),2)+ROUND((ROUND(((AE32-((EU32*1.1)))*AV32*1),2)*BS32),2)) -> 0 | CT32: =ROUND((ROUND((AF32*AV32*1),2)*BA32),2) -> 27.41 | CU32: =AG32 -> 0 | CV32: =(AH32*AV32) -> 2.3034 | CW32: =AI32 -> 0 | CX32: =AJ32 -> 0 | CY32: =(ROUND((((S32+ROUND((ROUND((((EU32*1.1))*AV32*1),2)*BS32),2))*AT32)/100),2)+ROUND(((ROUND((ROUND(((AE32-((EU32*1.1)))*AV32*1),2)*BS32),2)*AT32)/100),2)) -> 49.34 | CZ32: =(ROUND((((S32+ROUND((ROUND((((EU32*1.1))*AV32*1),2)*BS32),2))*AU32)/100),2)+ROUND(((ROUND((ROUND(((AE32-((EU32*1.1)))*AV32*1),2)*BS32),2)*AU32)/100),2)) -> 25.22 | DB32: 3 | DD32: *1 | DE32: *1,1 | DF32: *1,1 | DG32: *1,1 | DI32: *1,1 | DJ32: *1,1 | DN32: 0 | DO32: 0 | DP32: 1 | DQ32: 1 | DU32: 1013 | DV32: 1 ШТ. | DW32: 1 ШТ. | DX32: 1 | EE32: 60088532 | EF32: 40 | EG32: Монтаж оборудования | EH32: 0 | EJ32: 2 | EK32: 68 | EL32: ТСН-2001.4-10. Прокладка и монтаж сетей связи | EM32: ТСН-2001.4-10-1 | EO32: Поправка: Гл.12.Прил.8.п.8. 5_12.00.01.11.003 | EQ32: 0 | ER32: 24.08 | ES32: 0.28 | ET32: 0 | EU32: 0 | EV32: 23.8 | EW32: 2 | EX32: 0 | EY32: 0 | FQ32: 0 | FR32: 0 | FS32: 0 | FX32: 90 | FY32: 46 | GD32: 1 | GF32: 1897857927 | GG32: 2 | GH32: 1 | GI32: 2 | GJ32: 0 | GK32: 0 | GL32: =ROUND(IF(AND(BH32=3,BI32=3,FS32<>0),P32,0),2) -> 0 | GM32: =ROUND(O32+X32+Y32,2)+GX32 -> 129.94 | GN32: =IF(OR(BI32=0,BI32=1),GM32-GX32,0) -> 0 | GO32: =IF(BI32=2,GM32-GX32,0) -> 129.94 | GP32: =IF(BI32=4,GM32-GX32,0) -> 0 | GR32: 0 | GS32: 3 | GT32: 0 | GV32: =ROUND((GT32),6) -> 0 | GW32: 1 | GX32: =ROUND(HC32*I32,2) -> 0 | HA32: 0 | HB32: 0 | HC32: =GV32*GW32 -> 0 | HS32: 0 | IK32: 0
A33: 17 | B33: 1 | C33: =ROW(SmtRes!A4) -> 4 | D33: =ROW(EtalonRes!A4) -> 4 | E33: 3 | F33: 4.10-86-1 | G33: Электрочасы вторичные для помещений, электрочасы односторонние на стене | H33: 1 ШТ. | I33: 2 | J33: 0 | K33: 2 | O33: =ROUND(CP33,2) -> 3020.09 | P33: =ROUND((ROUND((AC33*AW33*I33),2)*BC33),2) -> 5.54 | Q33: =(ROUND((ROUND((((ET33*1.1))*AV33*I33),2)*BB33),2)+ROUND((ROUND(((AE33-((EU33*1.1)))*AV33*I33),2)*BS33),2)) -> 0 | R33: =(ROUND((ROUND((((EU33*1.1))*AV33*I33),2)*BS33),2)+ROUND((ROUND(((AE33-((EU33*1.1)))*AV33*I33),2)*BS33),2)) -> 0 | S33: =ROUND((ROUND((AF33*AV33*I33),2)*BA33),2) -> 3014.55 | T33: =ROUND(CU33*I33,2) -> 0 | U33: =CV33*I33 -> 4.6068 | V33: =CW33*I33 -> 0 | W33: =ROUND(CX33*I33,2) -> 0 | X33: =(ROUND((((S33+ROUND((ROUND((((EU33*1.1))*AV33*I33),2)*BS33),2))*AT33)/100),2)+ROUND(((ROUND((ROUND(((AE33-((EU33*1.1)))*AV33*I33),2)*BS33),2)*AT33)/100),2)) -> 2713.1 | Y33: =(ROUND((((S33+ROUND((ROUND((((EU33*1.1))*AV33*I33),2)*BS33),2))*AU33)/100),2)+ROUND(((ROUND((ROUND(((AE33-((EU33*1.1)))*AV33*I33),2)*BS33),2)*AU33)/100),2)) -> 1386.69 | AA33: 60257733 | AB33: =ROUND((AC33+AD33+AF33),6) -> 26.46 | AC33: =ROUND(((ES33*1)),6) -> 0.28 | AD33: =ROUND(((((ET33*1.1))-((EU33*1.1)))+AE33),6) -> 0 | AE33: =ROUND(((EU33*1.1)),6) -> 0 | AF33: =ROUND(((EV33*1.1)),6) -> 26.18 | AG33: =ROUND((AP33),6) -> 0 | AH33: =((EW33*1.1)) -> 2.2 | AI33: =((EX33*1.1)) -> 0 | AJ33: =(AS33) -> 0 | AK33: 24.08 | AL33: 0.28 | AM33: 0 | AN33: 0 | AO33: 23.8 | AP33: 0 | AQ33: 2 | AR33: 0 | AS33: 0 | AT33: 90 | AU33: 46 | AV33: 1.047 | AW33: 1 | AZ33: 1 | BA33: 54.99 | BB33: 1 | BC33: 9.89 | BH33: 0 | BI33: 2 | BJ33: ТСН-2001.4. Доп. 1-42. Сб. 10, т. 86, поз. 1 | BM33: 68 | BN33: 58973116 | BO33: 4.10-86-1 | BP33: 1 | BQ33: 40 | BR33: 0 | BS33: 54.99 | BT33: 1 | BU33: 1 | BV33: 1 | BW33: 1 | BX33: 1 | BZ33: 90 | CA33: 46 | CE33: 1566 | CF33: 0 | CG33: 0 | CM33: 0 | CN33: Поправка: Гл.12.Прил.8.п.8. 5_12.00.01.11.003 Наименование: При наличии усложненных условий производства работ (стесненность, сложность складирования и транспортной логистики, наличие в зоне производства работ действующего технологического оборудования или движения технологического транспорта и т.п.) для объектов, расположенных за пределами территории круговой магистральной системы улиц "Садовое кольцо" и за пределами Третьего транспортного кольца города Москвы пунктов "а" и "б", но в пределах Московской кольцевой автомобильной дороги | CO33: 0 | CP33: =(P33+Q33+S33) -> 3020.09 | CQ33: =ROUND((ROUND((AC33*AW33*1),2)*BC33),2) -> 2.77 | CR33: =(ROUND((ROUND((((ET33*1.1))*AV33*1),2)*BB33),2)+ROUND((ROUND(((AE33-((EU33*1.1)))*AV33*1),2)*BS33),2)) -> 0 | CS33: =(ROUND((ROUND((((EU33*1.1))*AV33*1),2)*BS33),2)+ROUND((ROUND(((AE33-((EU33*1.1)))*AV33*1),2)*BS33),2)) -> 0 | CT33: =ROUND((ROUND((AF33*AV33*1),2)*BA33),2) -> 1507.28 | CU33: =AG33 -> 0 | CV33: =(AH33*AV33) -> 2.3034 | CW33: =AI33 -> 0 | CX33: =AJ33 -> 0 | CY33: =(ROUND((((S33+ROUND((ROUND((((EU33*1.1))*AV33*1),2)*BS33),2))*AT33)/100),2)+ROUND(((ROUND((ROUND(((AE33-((EU33*1.1)))*AV33*1),2)*BS33),2)*AT33)/100),2)) -> 2713.1 | CZ33: =(ROUND((((S33+ROUND((ROUND((((EU33*1.1))*AV33*1),2)*BS33),2))*AU33)/100),2)+ROUND(((ROUND((ROUND(((AE33-((EU33*1.1)))*AV33*1),2)*BS33),2)*AU33)/100),2)) -> 1386.69 | DB33: 4 | DD33: *1 | DE33: *1,1 | DF33: *1,1 | DG33: *1,1 | DI33: *1,1 | DJ33: *1,1 | DN33: 0 | DO33: 0 | DP33: 1 | DQ33: 1 | DU33: 1013 | DV33: 1 ШТ. | DW33: 1 ШТ. | DX33: 1 | EE33: 60088532 | EF33: 40 | EG33: Монтаж оборудования | EH33: 0 | EJ33: 2 | EK33: 68 | EL33: ТСН-2001.4-10. Прокладка и монтаж сетей связи | EM33: ТСН-2001.4-10-1 | EO33: Поправка: Гл.12.Прил.8.п.8. 5_12.00.01.11.003 | EQ33: 0 | ER33: 24.08 | ES33: 0.28 | ET33: 0 | EU33: 0 | EV33: 23.8 | EW33: 2 | EX33: 0 | EY33: 0 | FQ33: 0 | FR33: 0 | FS33: 0 | FX33: 90 | FY33: 46 | GD33: 1 | GF33: 1897857927 | GG33: 2 | GH33: 1 | GI33: 2 | GJ33: 0 | GK33: 0 | GL33: =ROUND(IF(AND(BH33=3,BI33=3,FS33<>0),P33,0),2) -> 0 | GM33: =ROUND(O33+X33+Y33,2)+GX33 -> 7119.88 | GN33: =IF(OR(BI33=0,BI33=1),GM33-GX33,0) -> 0 | GO33: =IF(BI33=2,GM33-GX33,0) -> 7119.88 | GP33: =IF(BI33=4,GM33-GX33,0) -> 0 | GR33: 0 | GS33: 3 | GT33: 0 | GV33: =ROUND((GT33),6) -> 0 | GW33: 1 | GX33: =ROUND(HC33*I33,2) -> 0 | HA33: 0 | HB33: 0 | HC33: =GV33*GW33 -> 0 | HS33: 0 | IK33: 0
A34: 17 | B34: 1 | E34: 4 | F34: 13.1-2-211 | G34: Часы электрические вторичные стрелочные, типа ВЧ03/03 | H34: шт. | I34: 2 | J34: 0 | K34: 2 | O34: =ROUND(CP34,2) -> 1461.26 | P34: =ROUND((ROUND((AC34*I34),2)*BC34),2) -> 1461.26 | Q34: =(ROUND((ROUND(((ET34)*AV34*I34),2)*BB34),2)+ROUND((ROUND(((AE34-(EU34))*AV34*I34),2)*BS34),2)) -> 0 | R34: =(ROUND((ROUND(((EU34)*AV34*I34),2)*BS34),2)+ROUND((ROUND(((AE34-(EU34))*AV34*I34),2)*BS34),2)) -> 0 | S34: =ROUND((ROUND((AF34*AV34*I34),2)*BA34),2) -> 0 | T34: =ROUND(CU34*I34,2) -> 0 | U34: =CV34*I34 -> 0 | V34: =CW34*I34 -> 0 | W34: =ROUND(CX34*I34,2) -> 0 | X34: =(ROUND((((S34+ROUND((ROUND(((EU34)*AV34*I34),2)*BS34),2))*AT34)/100),2)+ROUND(((ROUND((ROUND(((AE34-(EU34))*AV34*I34),2)*BS34),2)*AT34)/100),2)) -> 0 | Y34: =(ROUND((((S34+ROUND((ROUND(((EU34)*AV34*I34),2)*BS34),2))*AU34)/100),2)+ROUND(((ROUND((ROUND(((AE34-(EU34))*AV34*I34),2)*BS34),2)*AU34)/100),2)) -> 0 | AA34: 60257736 | AB34: =ROUND((AC34+AD34+AF34),6) -> 730.63 | AC34: =ROUND((ES34),6) -> 730.63 | AD34: =ROUND((((ET34)-(EU34))+AE34),6) -> 0 | AE34: =ROUND((EU34),6) -> 0 | AF34: =ROUND((EV34),6) -> 0 | AG34: =ROUND((AP34),6) -> 0 | AH34: =(EW34) -> 0 | AI34: =(EX34) -> 0 | AJ34: =(AS34) -> 0 | AK34: 730.63 | AL34: 730.63 | AM34: 0 | AN34: 0 | AO34: 0 | AP34: 0 | AQ34: 0 | AR34: 0 | AS34: 0 | AT34: 0 | AU34: 0 | AV34: 1 | AW34: 1 | AZ34: 1 | BA34: 1 | BB34: 1 | BC34: 1 | BH34: 3 | BI34: 3 | BM34: 746 | BN34: 58973116 | BP34: 0 | BQ34: 130 | BR34: 0 | BS34: 1 | BT34: 1 | BU34: 1 | BV34: 1 | BW34: 1 | BX34: 1 | BZ34: 0 | CA34: 0 | CE34: 1566 | CF34: 0 | CG34: 0 | CM34: 0 | CO34: 0 | CP34: =(P34+Q34+S34) -> 1461.26 | CQ34: =ROUND((ROUND((AC34*1),2)*BC34),2) -> 730.63 | CR34: =(ROUND((ROUND(((ET34)*AV34*1),2)*BB34),2)+ROUND((ROUND(((AE34-(EU34))*AV34*1),2)*BS34),2)) -> 0 | CS34: =(ROUND((ROUND(((EU34)*AV34*1),2)*BS34),2)+ROUND((ROUND(((AE34-(EU34))*AV34*1),2)*BS34),2)) -> 0 | CT34: =ROUND((ROUND((AF34*AV34*1),2)*BA34),2) -> 0 | CU34: =AG34 -> 0 | CV34: =(AH34*AV34) -> 0 | CW34: =AI34 -> 0 | CX34: =AJ34 -> 0 | CY34: =(ROUND((((S34+ROUND((ROUND(((EU34)*AV34*1),2)*BS34),2))*AT34)/100),2)+ROUND(((ROUND((ROUND(((AE34-(EU34))*AV34*1),2)*BS34),2)*AT34)/100),2)) -> 0 | CZ34: =(ROUND((((S34+ROUND((ROUND(((EU34)*AV34*1),2)*BS34),2))*AU34)/100),2)+ROUND(((ROUND((ROUND(((AE34-(EU34))*AV34*1),2)*BS34),2)*AU34)/100),2)) -> 0 | DN34: 0 | DO34: 0 | DP34: 1 | DQ34: 1 | DU34: 1010 | DV34: шт. | DW34: шт. | DX34: 1 | EE34: 60088638 | EF34: 130 | EG34: Сметная стоимость оборудования | EH34: 0 | EJ34: 3 | EK34: 746 | EL34: ТСН-2001.13. Сметная стоимость оборудования | EM34: ТСН-2001.13 | EQ34: 0 | ER34: 730.63 | ES34: 730.63 | ET34: 0 | EU34: 0 | EV34: 0 | EW34: 0 | EX34: 0 | EY34: 0 | FQ34: 0 | FR34: =P34 -> 1461.26 | FS34: 0 | FX34: 0 | FY34: 0 | GD34: 1 | GF34: -1868144852 | GG34: 2 | GH34: 1 | GI34: -2 | GJ34: 0 | GK34: 0 | GL34: =ROUND(IF(AND(BH34=3,BI34=3,FS34<>0),P34,0),2) -> 0 | GM34: =ROUND(O34+X34+Y34,2)+GX34 -> 1461.26 | GN34: =IF(OR(BI34=0,BI34=1),GM34-GX34,0) -> 0 | GO34: =IF(BI34=2,GM34-GX34,0) -> 0 | GP34: =IF(BI34=4,GM34-GX34,0) -> 0 | GR34: 0 | GS34: 3 | GT34: 0 | GV34: =ROUND((GT34),6) -> 0 | GW34: 1 | GX34: =ROUND(HC34*I34,2) -> 0 | HA34: 0 | HB34: 0 | HC34: =GV34*GW34 -> 0 | HS34: 0 | IK34: 0
A35: 17 | B35: 1 | E35: 4 | F35: 13.1-2-211 | G35: Часы электрические вторичные стрелочные, типа ВЧ03/03 | H35: шт. | I35: 2 | J35: 0 | K35: 2 | O35: =ROUND(CP35,2) -> 7598.55 | P35: =ROUND((ROUND((AC35*I35),2)*BC35),2) -> 7598.55 | Q35: =(ROUND((ROUND(((ET35)*AV35*I35),2)*BB35),2)+ROUND((ROUND(((AE35-(EU35))*AV35*I35),2)*BS35),2)) -> 0 | R35: =(ROUND((ROUND(((EU35)*AV35*I35),2)*BS35),2)+ROUND((ROUND(((AE35-(EU35))*AV35*I35),2)*BS35),2)) -> 0 | S35: =ROUND((ROUND((AF35*AV35*I35),2)*BA35),2) -> 0 | T35: =ROUND(CU35*I35,2) -> 0 | U35: =CV35*I35 -> 0 | V35: =CW35*I35 -> 0 | W35: =ROUND(CX35*I35,2) -> 0 | X35: =(ROUND((((S35+ROUND((ROUND(((EU35)*AV35*I35),2)*BS35),2))*AT35)/100),2)+ROUND(((ROUND((ROUND(((AE35-(EU35))*AV35*I35),2)*BS35),2)*AT35)/100),2)) -> 0 | Y35: =(ROUND((((S35+ROUND((ROUND(((EU35)*AV35*I35),2)*BS35),2))*AU35)/100),2)+ROUND(((ROUND((ROUND(((AE35-(EU35))*AV35*I35),2)*BS35),2)*AU35)/100),2)) -> 0 | AA35: 60257733 | AB35: =ROUND((AC35+AD35+AF35),6) -> 730.63 | AC35: =ROUND((ES35),6) -> 730.63 | AD35: =ROUND((((ET35)-(EU35))+AE35),6) -> 0 | AE35: =ROUND((EU35),6) -> 0 | AF35: =ROUND((EV35),6) -> 0 | AG35: =ROUND((AP35),6) -> 0 | AH35: =(EW35) -> 0 | AI35: =(EX35) -> 0 | AJ35: =(AS35) -> 0 | AK35: 730.63 | AL35: 730.63 | AM35: 0 | AN35: 0 | AO35: 0 | AP35: 0 | AQ35: 0 | AR35: 0 | AS35: 0 | AT35: 0 | AU35: 0 | AV35: 1 | AW35: 1 | AZ35: 1 | BA35: 1 | BB35: 1 | BC35: 5.2 | BH35: 3 | BI35: 3 | BM35: 746 | BN35: 58973116 | BP35: 0 | BQ35: 130 | BR35: 0 | BS35: 1 | BT35: 1 | BU35: 1 | BV35: 1 | BW35: 1 | BX35: 1 | BZ35: 0 | CA35: 0 | CE35: 1566 | CF35: 0 | CG35: 0 | CM35: 0 | CO35: 0 | CP35: =(P35+Q35+S35) -> 7598.55 | CQ35: =ROUND((ROUND((AC35*1),2)*BC35),2) -> 3799.28 | CR35: =(ROUND((ROUND(((ET35)*AV35*1),2)*BB35),2)+ROUND((ROUND(((AE35-(EU35))*AV35*1),2)*BS35),2)) -> 0 | CS35: =(ROUND((ROUND(((EU35)*AV35*1),2)*BS35),2)+ROUND((ROUND(((AE35-(EU35))*AV35*1),2)*BS35),2)) -> 0 | CT35: =ROUND((ROUND((AF35*AV35*1),2)*BA35),2) -> 0 | CU35: =AG35 -> 0 | CV35: =(AH35*AV35) -> 0 | CW35: =AI35 -> 0 | CX35: =AJ35 -> 0 | CY35: =(ROUND((((S35+ROUND((ROUND(((EU35)*AV35*1),2)*BS35),2))*AT35)/100),2)+ROUND(((ROUND((ROUND(((AE35-(EU35))*AV35*1),2)*BS35),2)*AT35)/100),2)) -> 0 | CZ35: =(ROUND((((S35+ROUND((ROUND(((EU35)*AV35*1),2)*BS35),2))*AU35)/100),2)+ROUND(((ROUND((ROUND(((AE35-(EU35))*AV35*1),2)*BS35),2)*AU35)/100),2)) -> 0 | DN35: 0 | DO35: 0 | DP35: 1 | DQ35: 1 | DU35: 1010 | DV35: шт. | DW35: шт. | DX35: 1 | EE35: 60088638 | EF35: 130 | EG35: Сметная стоимость оборудования | EH35: 0 | EJ35: 3 | EK35: 746 | EL35: ТСН-2001.13. Сметная стоимость оборудования | EM35: ТСН-2001.13 | EQ35: 0 | ER35: 730.63 | ES35: 730.63 | ET35: 0 | EU35: 0 | EV35: 0 | EW35: 0 | EX35: 0 | EY35: 0 | FQ35: 0 | FR35: =P35 -> 7598.55 | FS35: 0 | FX35: 0 | FY35: 0 | GD35: 1 | GF35: -1868144852 | GG35: 2 | GH35: 1 | GI35: 2 | GJ35: 0 | GK35: 0 | GL35: =ROUND(IF(AND(BH35=3,BI35=3,FS35<>0),P35,0),2) -> 0 | GM35: =ROUND(O35+X35+Y35,2)+GX35 -> 7598.55 | GN35: =IF(OR(BI35=0,BI35=1),GM35-GX35,0) -> 0 | GO35: =IF(BI35=2,GM35-GX35,0) -> 0 | GP35: =IF(BI35=4,GM35-GX35,0) -> 0 | GR35: 0 | GS35: 3 | GT35: 0 | GV35: =ROUND((GT35),6) -> 0 | GW35: 1 | GX35: =ROUND(HC35*I35,2) -> 0 | HA35: 0 | HB35: 0 | HC35: =GV35*GW35 -> 0 | HS35: 0 | IK35: 0
A37: 51 | B37: =B24 -> 1 | C37: =A24 -> 4 | D37: =ROW(A24) -> 24 | F37: =IF(F24<>"",F24,"") | G37: =IF(G24<>"",G24,"") -> Оборудование | H37: 0 | O37: =ROUND(AB37,2) -> 12083.56 | P37: =ROUND(AC37,2) -> 11981.16 | Q37: =ROUND(AD37,2) -> 0 | R37: =ROUND(AE37,2) -> 0 | S37: =ROUND(AF37,2) -> 102.4 | T37: =ROUND(AG37,2) -> 0 | U37: =AH37 -> 8.0619 | V37: =AI37 -> 0 | W37: =ROUND(AJ37,2) -> 0 | X37: =ROUND(AK37,2) -> 92.16 | Y37: =ROUND(AL37,2) -> 47.11 | AB37: =ROUND(SUMIF(AA28:AA35,"=60257736",O28:O35),2) -> 12083.56 | AC37: =ROUND(SUMIF(AA28:AA35,"=60257736",P28:P35),2) -> 11981.16 | AD37: =ROUND(SUMIF(AA28:AA35,"=60257736",Q28:Q35),2) -> 0 | AE37: =ROUND(SUMIF(AA28:AA35,"=60257736",R28:R35),2) -> 0 | AF37: =ROUND(SUMIF(AA28:AA35,"=60257736",S28:S35),2) -> 102.4 | AG37: =ROUND(SUMIF(AA28:AA35,"=60257736",T28:T35),2) -> 0 | AH37: =SUMIF(AA28:AA35,"=60257736",U28:U35) -> 8.0619 | AI37: =SUMIF(AA28:AA35,"=60257736",V28:V35) -> 0 | AJ37: =ROUND(SUMIF(AA28:AA35,"=60257736",W28:W35),2) -> 0 | AK37: =ROUND(SUMIF(AA28:AA35,"=60257736",X28:X35),2) -> 92.16 | AL37: =ROUND(SUMIF(AA28:AA35,"=60257736",Y28:Y35),2) -> 47.11 | AO37: =ROUND(BX37,2) -> 0 | AP37: =ROUND(BY37,2) -> 11980.11 | AQ37: =ROUND(BZ37,2) -> 0 | AR37: =ROUND(CA37,2) -> 12222.83 | AS37: =ROUND(CB37,2) -> 0 | AT37: =ROUND(CC37,2) -> 242.72 | AU37: =ROUND(CD37,2) -> 0 | AV37: =ROUND(CE37,2) -> 11981.16 | ... BD37: =ROUND(CM37,2) -> 0 | BX37: =ROUND(SUMIF(AA28:AA35,"=60257736",FQ28:FQ35),2) -> 0 | BY37: =ROUND(SUMIF(AA28:AA35,"=60257736",FR28:FR35),2) -> 11980.11 | BZ37: =ROUND(SUMIF(AA28:AA35,"=60257736",GL28:GL35),2) -> 0 | CA37: =ROUND(SUMIF(AA28:AA35,"=60257736",GM28:GM35),2) -> 12222.83 | CB37: =ROUND(SUMIF(AA28:AA35,"=60257736",GN28:GN35),2) -> 0 | CC37: =ROUND(SUMIF(AA28:AA35,"=60257736",GO28:GO35),2) -> 242.72 | CD37: =ROUND(SUMIF(AA28:AA35,"=60257736",GP28:GP35),2) -> 0 | CE37: =AC37-BX37 -> 11981.16 | CF37: =AC37-BY37 -> 1.05 | CG37: =BX37-BZ37 -> 0 | CH37: =AC37-BX37-BY37+BZ37 -> 1.05 | CI37: =BY37-BZ37 -> 11980.11 | CJ37: =ROUND(SUMIF(AA28:AA35,"=60257736",GX28:GX35),2) -> 0 | CK37: =ROUND(SUMIF(AA28:AA35,"=60257736",GY28:GY35),2) -> 0 | CL37: =ROUND(SUMIF(AA28:AA35,"=60257736",GZ28:GZ35),2) -> 0 | CM37: =ROUND(SUMIF(AA28:AA35,"=60257736",HD28:HD35),2) -> 0 | DG37: =ROUND(DT37,2) -> 93814.3 | DH37: =ROUND(DU37,2) -> 88183.33 | DI37: =ROUND(DV37,2) -> 0 | DJ37: =ROUND(DW37,2) -> 0 | DK37: =ROUND(DX37,2) -> 5630.97 | DL37: =ROUND(DY37,2) -> 0 | DM37: =DZ37 -> 8.0619 | DN37: =EA37 -> 0 | DO37: =ROUND(EB37,2) -> 0 | DP37: =ROUND(EC37,2) -> 5067.88 | DQ37: =ROUND(ED37,2) -> 2590.24 | DT37: =ROUND(SUMIF(AA28:AA35,"=60257733",O28:O35),2) -> 93814.3 | DU37: =ROUND(SUMIF(AA28:AA35,"=60257733",P28:P35),2) -> 88183.33 | DV37: =ROUND(SUMIF(AA28:AA35,"=60257733",Q28:Q35),2) -> 0 | DW37: =ROUND(SUMIF(AA28:AA35,"=60257733",R28:R35),2) -> 0 | DX37: =ROUND(SUMIF(AA28:AA35,"=60257733",S28:S35),2) -> 5630.97 | DY37: =ROUND(SUMIF(AA28:AA35,"=60257733",T28:T35),2) -> 0 | DZ37: =SUMIF(AA28:AA35,"=60257733",U28:U35) -> 8.0619 | EA37: =SUMIF(AA28:AA35,"=60257733",V28:V35) -> 0 | EB37: =ROUND(SUMIF(AA28:AA35,"=60257733",W28:W35),2) -> 0 | EC37: =ROUND(SUMIF(AA28:AA35,"=60257733",X28:X35),2) -> 5067.88 | ED37: =ROUND(SUMIF(AA28:AA35,"=60257733",Y28:Y35),2) -> 2590.24 | EG37: =ROUND(FP37,2) -> 0 | EH37: =ROUND(FQ37,2) -> 88172.94 | EI37: =ROUND(FR37,2) -> 0 | EJ37: =ROUND(FS37,2) -> 101472.42 | EK37: =ROUND(FT37,2) -> 0 | EL37: =ROUND(FU37,2) -> 13299.48 | EM37: =ROUND(FV37,2) -> 0 | EN37: =ROUND(FW37,2) -> 88183.33 | ... EV37: =ROUND(GE37,2) -> 0 | FP37: =ROUND(SUMIF(AA28:AA35,"=60257733",FQ28:FQ35),2) -> 0 | FQ37: =ROUND(SUMIF(AA28:AA35,"=60257733",FR28:FR35),2) -> 88172.94 | FR37: =ROUND(SUMIF(AA28:AA35,"=60257733",GL28:GL35),2) -> 0 | FS37: =ROUND(SUMIF(AA28:AA35,"=60257733",GM28:GM35),2) -> 101472.42 | FT37: =ROUND(SUMIF(AA28:AA35,"=60257733",GN28:GN35),2) -> 0 | FU37: =ROUND(SUMIF(AA28:AA35,"=60257733",GO28:GO35),2) -> 13299.48 | FV37: =ROUND(SUMIF(AA28:AA35,"=60257733",GP28:GP35),2) -> 0 | FW37: =DU37-FP37 -> 88183.33 | FX37: =DU37-FQ37 -> 10.39 | FY37: =FP37-FR37 -> 0 | FZ37: =DU37-FP37-FQ37+FR37 -> 10.39 | GA37: =FQ37-FR37 -> 88172.94 | GB37: =ROUND(SUMIF(AA28:AA35,"=60257733",GX28:GX35),2) -> 0 | GC37: =ROUND(SUMIF(AA28:AA35,"=60257733",GY28:GY35),2) -> 0 | GD37: =ROUND(SUMIF(AA28:AA35,"=60257733",GZ28:GZ35),2) -> 0 | GE37: =ROUND(SUMIF(AA28:AA35,"=60257733",HD28:HD35),2) -> 0 | GX37: 0
A39: 50 | B39: 0 | C39: 0 | D39: 1 | E39: 201 | F39: =ROUND(Source!O37,O39) -> 12083.56 | G39: ПЗ | H39: Прямые затраты | K39: 201 | L39: 1 | M39: 3 | O39: 2 | P39: =ROUND(Source!DG37,O39) -> 93814.3 | W39: 12083.56 | X39: 1 | Y39: 12083.56 | Z39: 93814.3 | AA39: 1 | AB39: 93814.3
A40: 50 | B40: 0 | C40: 0 | D40: 1 | E40: 202 | F40: =ROUND(Source!P37,O40) -> 11981.16 | G40: СтМатОб | H40: Стоимость материальных ресурсов (всего) | K40: 202 | L40: 2 | M40: 3 | O40: 2 | P40: =ROUND(Source!DH37,O40) -> 88183.33 | W40: 11981.16 | X40: 1 | Y40: 11981.16 | Z40: 88183.33 | AA40: 1 | AB40: 88183.33
A41: 50 | B41: 0 | C41: 0 | D41: 1 | E41: 222 | F41: =ROUND(Source!AO37,O41) -> 0 | G41: СтМатОбЗак | H41: Стоимость материалов и оборудования заказчика | K41: 222 | L41: 3 | M41: 3 | O41: 2 | P41: =ROUND(Source!EG37,O41) -> 0 | W41: 0 | X41: 1 | Y41: 0 | Z41: 0 | AA41: 1 | AB41: 0
A42: 50 | B42: 0 | C42: 0 | D42: 1 | E42: 225 | F42: =ROUND(Source!AV37,O42) -> 11981.16 | G42: СтМатОбПод | H42: Стоимость материалов и оборудования подрядчика | K42: 225 | L42: 4 | M42: 3 | O42: 2 | P42: =ROUND(Source!EN37,O42) -> 88183.33 | W42: 11981.16 | X42: 1 | Y42: 11981.16 | Z42: 88183.33 | AA42: 1 | AB42: 88183.33
A43: 50 | B43: 0 | C43: 0 | D43: 1 | E43: 226 | F43: =ROUND(Source!AW37,O43) -> 1.05 | G43: СтМат | H43: Стоимость материалов (всего) | K43: 226 | L43: 5 | M43: 3 | O43: 2 | P43: =ROUND(Source!EO37,O43) -> 10.39 | W43: 1.05 | X43: 1 | Y43: 1.05 | Z43: 10.39 | AA43: 1 | AB43: 10.39
A44: 50 | B44: 0 | C44: 0 | D44: 1 | E44: 227 | F44: =ROUND(Source!AX37,O44) -> 0 | G44: СтМатЗак | H44: Стоимость материалов заказчика | K44: 227 | L44: 6 | M44: 3 | O44: 2 | P44: =ROUND(Source!EP37,O44) -> 0 | W44: 0 | X44: 1 | Y44: 0 | Z44: 0 | AA44: 1 | AB44: 0
A45: 50 | B45: 0 | C45: 0 | D45: 1 | E45: 228 | F45: =ROUND(Source!AY37,O45) -> 1.05 | G45: СтМатПод | H45: Стоимость материалов подрядчика | K45: 228 | L45: 7 | M45: 3 | O45: 2 | P45: =ROUND(Source!EQ37,O45) -> 10.39 | W45: 1.05 | X45: 1 | Y45: 1.05 | Z45: 10.39 | AA45: 1 | AB45: 10.39
A46: 50 | B46: 0 | C46: 0 | D46: 1 | E46: 216 | F46: =ROUND(Source!AP37,O46) -> 11980.11 | G46: Оборуд | H46: Стоимость оборудования (всего) | K46: 216 | L46: 8 | M46: 3 | O46: 2 | P46: =ROUND(Source!EH37,O46) -> 88172.94 | W46: 11980.11 | X46: 1 | Y46: 11980.11 | Z46: 88172.94 | AA46: 1 | AB46: 88172.94
A47: 50 | B47: 0 | C47: 0 | D47: 1 | E47: 223 | F47: =ROUND(Source!AQ37,O47) -> 0 | G47: ОборудЗак | H47: Стоимость оборудования заказчика | K47: 223 | L47: 9 | M47: 3 | O47: 2 | P47: =ROUND(Source!EI37,O47) -> 0 | W47: 0 | X47: 1 | Y47: 0 | Z47: 0 | AA47: 1 | AB47: 0
A48: 50 | B48: 0 | C48: 0 | D48: 1 | E48: 229 | F48: =ROUND(Source!AZ37,O48) -> 11980.11 | G48: ОборудПод | H48: Стоимость оборудования подрядчика | K48: 229 | L48: 10 | M48: 3 | O48: 2 | P48: =ROUND(Source!ER37,O48) -> 88172.94 | W48: 11980.11 | X48: 1 | Y48: 11980.11 | Z48: 88172.94 | AA48: 1 | AB48: 88172.94
A49: 50 | B49: 0 | C49: 0 | D49: 1 | E49: 203 | F49: =ROUND(Source!Q37,O49) -> 0 | G49: ЭММ | H49: Эксплуатация машин | K49: 203 | L49: 11 | M49: 3 | O49: 2 | P49: =ROUND(Source!DI37,O49) -> 0 | W49: 0 | X49: 1 | Y49: 0 | Z49: 0 | AA49: 1 | AB49: 0
A50: 50 | B50: 0 | C50: 0 | D50: 1 | E50: 231 | F50: =ROUND(Source!BB37,O50) -> 0 | G50: ЭММсНРиСП | H50: Эксплуатация машин по ТСН-2001.16 | K50: 231 | L50: 12 | M50: 3 | O50: 2 | P50: =ROUND(Source!ET37,O50) -> 0 | W50: 0 | X50: 1 | Y50: 0 | Z50: 0 | AA50: 1 | AB50: 0
A51: 50 | B51: 0 | C51: 0 | D51: 1 | E51: 204 | F51: =ROUND(Source!R37,O51) -> 0 | G51: ЗПМ | H51: ЗП машинистов | K51: 204 | L51: 13 | M51: 3 | O51: 2 | P51: =ROUND(Source!DJ37,O51) -> 0 | W51: 0 | X51: 1 | Y51: 0 | Z51: 0 | AA51: 1 | AB51: 0
A52: 50 | B52: 0 | C52: 0 | D52: 1 | E52: 205 | F52: =ROUND(Source!S37,O52) -> 102.4 | G52: ОЗП | H52: Основная ЗП рабочих | K52: 205 | L52: 14 | M52: 3 | O52: 2 | P52: =ROUND(Source!DK37,O52) -> 5630.97 | W52: 102.4 | X52: 1 | Y52: 102.4 | Z52: 5630.97 | AA52: 1 | AB52: 5630.97
A53: 50 | B53: 0 | C53: 0 | D53: 1 | E53: 232 | F53: =ROUND(Source!BC37,O53) -> 0 | G53: ОЗПсНРиСП | H53: Основная ЗП рабочих по ТСН-2001.16 | K53: 232 | L53: 15 | M53: 3 | O53: 2 | P53: =ROUND(Source!EU37,O53) -> 0 | W53: 0 | X53: 1 | Y53: 0 | Z53: 0 | AA53: 1 | AB53: 0
A54: 50 | B54: 0 | C54: 0 | D54: 1 | E54: 214 | F54: =ROUND(Source!AS37,O54) -> 0 | G54: Строит | H54: Строительные работы с НР и СП | K54: 214 | L54: 16 | M54: 3 | O54: 2 | P54: =ROUND(Source!EK37,O54) -> 0 | W54: 0 | X54: 1 | Y54: 0 | Z54: 0 | AA54: 1 | AB54: 0
A55: 50 | B55: 0 | C55: 0 | D55: 1 | E55: 215 | F55: =ROUND(Source!AT37,O55) -> 242.72 | G55: Монтаж | H55: Монтажные работы с НР и СП | K55: 215 | L55: 17 | M55: 3 | O55: 2 | P55: =ROUND(Source!EL37,O55) -> 13299.48 | W55: 242.72 | X55: 1 | Y55: 242.72 | Z55: 13299.48 | AA55: 1 | AB55: 13299.48
A56: 50 | B56: 0 | C56: 0 | D56: 1 | E56: 217 | F56: =ROUND(Source!AU37,O56) -> 0 | G56: Прочие | H56: Прочие работы с НР и СП | K56: 217 | L56: 18 | M56: 3 | O56: 2 | P56: =ROUND(Source!EM37,O56) -> 0 | W56: 0 | X56: 1 | Y56: 0 | Z56: 0 | AA56: 1 | AB56: 0
A57: 50 | B57: 0 | C57: 0 | D57: 1 | E57: 230 | F57: =ROUND(Source!BA37,O57) -> 0 | G57: ПрочиеЗатр | H57: Прочие затраты по ТСН-2001.16 | K57: 230 | L57: 19 | M57: 3 | O57: 2 | P57: =ROUND(Source!ES37,O57) -> 0 | W57: 0 | X57: 1 | Y57: 0 | Z57: 0 | AA57: 1 | AB57: 0
A58: 50 | B58: 0 | C58: 0 | D58: 1 | E58: 206 | F58: =ROUND(Source!T37,O58) -> 0 | G58: ВозврМат | H58: Возврат материалов | K58: 206 | L58: 20 | M58: 3 | O58: 2 | P58: =ROUND(Source!DL37,O58) -> 0 | W58: 0 | X58: 1 | Y58: 0 | Z58: 0 | AA58: 1 | AB58: 0
A59: 50 | B59: 0 | C59: 0 | D59: 1 | E59: 207 | F59: =Source!U37 -> 8.0619 | G59: ТрудСтр | H59: Трудозатраты строителей | K59: 207 | L59: 21 | M59: 3 | O59: -1 | P59: =Source!DM37 -> 8.0619 | W59: 8.0619 | X59: 1 | Y59: 8.0619 | Z59: 8.0619 | AA59: 1 | AB59: 8.0619
A60: 50 | B60: 0 | C60: 0 | D60: 1 | E60: 208 | F60: =Source!V37 -> 0 | G60: ТрудМаш | H60: Трудозатраты машинистов | K60: 208 | L60: 22 | M60: 3 | O60: -1 | P60: =Source!DN37 -> 0 | W60: 0 | X60: 1 | Y60: 0 | Z60: 0 | AA60: 1 | AB60: 0
A61: 50 | B61: 0 | C61: 0 | D61: 1 | E61: 209 | F61: =ROUND(Source!W37,O61) -> 0 | G61: ТранспМат | H61: Транспорт материалов | K61: 209 | L61: 23 | M61: 3 | O61: 2 | P61: =ROUND(Source!DO37,O61) -> 0 | W61: 0 | X61: 1 | Y61: 0 | Z61: 0 | AA61: 1 | AB61: 0
A62: 50 | B62: 0 | C62: 0 | D62: 1 | E62: 233 | F62: =ROUND(Source!BD37,O62) -> 0 | G62: Перевозка | H62: Перевозка грузов | K62: 233 | L62: 24 | M62: 3 | O62: 2 | P62: =ROUND(Source!EV37,O62) -> 0 | W62: 0 | X62: 1 | Y62: 0 | Z62: 0 | AA62: 1 | AB62: 0
A63: 50 | B63: 0 | C63: 0 | D63: 1 | E63: 210 | F63: =ROUND(Source!X37,O63) -> 92.16 | G63: НР | H63: Накладные расходы | K63: 210 | L63: 25 | M63: 3 | O63: 2 | P63: =ROUND(Source!DP37,O63) -> 5067.88 | W63: 92.16 | X63: 1 | Y63: 92.16 | Z63: 5067.88 | AA63: 1 | AB63: 5067.88
A64: 50 | B64: 0 | C64: 0 | D64: 1 | E64: 211 | F64: =ROUND(Source!Y37,O64) -> 47.11 | G64: СмПриб | H64: Сметная прибыль | K64: 211 | L64: 26 | M64: 3 | O64: 2 | P64: =ROUND(Source!DQ37,O64) -> 2590.24 | W64: 47.11 | X64: 1 | Y64: 47.11 | Z64: 2590.24 | AA64: 1 | AB64: 2590.24
A65: 50 | B65: 0 | C65: 0 | D65: 1 | E65: 224 | F65: =ROUND(Source!AR37,O65) -> 12222.83 | G65: Всего | H65: Всего с НР и СП | K65: 224 | L65: 27 | M65: 3 | O65: 2 | P65: =ROUND(Source!EJ37,O65) -> 101472.42 | W65: 12222.83 | X65: 1 | Y65: 12222.83 | Z65: 101472.42 | AA65: 1 | AB65: 101472.42
A67: 4 | B67: 1 | D67: =ROW(A84) -> 84 | G67: Кабельные изделия | I67: 0 | K67: -1 | S67: 0 | T67: 0 | V67: 2 | BX67: 0 | CJ67: 0
A69: 52 | B69: =B84 -> 1 | C69: =C84 -> 4 | D69: =D84 -> 67 | E69: =E84 -> 0 | F69: =F84 | G69: =G84 -> Кабельные изделия | O69: =O84 -> 2322.76 | P69: =P84 -> 2111.72 | Q69: =Q84 -> 3.84 | R69: =R84 -> 0.17 | S69: =S84 -> 207.2 | T69: =T84 -> 0 | U69: =U84 -> 17.304293 | V69: =V84 -> 0 | ... GX69: =GX84 -> 0
A71: 17 | B71: 1 | C71: =ROW(SmtRes!A13) -> 13 | D71: =ROW(EtalonRes!A14) -> 14 | E71: 5 | F71: 4.10-185-3 | G71: Прокладка кабеля связи огнестойкого в трубах гофрированных с использованием скобы СМО: по бетонным поверхностям | H71: 100 м | I71: =ROUND(50/100,9) -> 0.5 | J71: 0 | K71: =ROUND(50/100,9) -> 0.5 | O71: =ROUND(CP71,2) -> 181.46 | P71: =ROUND((ROUND((AC71*AW71*I71),2)*BC71),2) -> 9.71 | Q71: =(ROUND((ROUND((((ET71*1.1))*AV71*I71),2)*BB71),2)+ROUND((ROUND(((AE71-((EU71*1.1)))*AV71*I71),2)*BS71),2)) -> 2.33 | R71: =(ROUND((ROUND((((EU71*1.1))*AV71*I71),2)*BS71),2)+ROUND((ROUND(((AE71-((EU71*1.1)))*AV71*I71),2)*BS71),2)) -> 0 | S71: =ROUND((ROUND((AF71*AV71*I71),2)*BA71),2) -> 169.42 | T71: =ROUND(CU71*I71,2) -> 0 | U71: =CV71*I71 -> 14.258046 | V71: =CW71*I71 -> 0 | W71: =ROUND(CX71*I71,2) -> 0 | X71: =(ROUND((((S71+ROUND((ROUND((((EU71*1.1))*AV71*I71),2)*BS71),2))*AT71)/100),2)+ROUND(((ROUND((ROUND(((AE71-((EU71*1.1)))*AV71*I71),2)*BS71),2)*AT71)/100),2)) -> 152.48 | Y71: =(ROUND((((S71+ROUND((ROUND((((EU71*1.1))*AV71*I71),2)*BS71),2))*AU71)/100),2)+ROUND(((ROUND((ROUND(((AE71-((EU71*1.1)))*AV71*I71),2)*BS71),2)*AU71)/100),2)) -> 77.93 | AA71: 60257736 | AB71: =ROUND((AC71+AD71+AF71),6) -> 347.506 | AC71: =ROUND((ES71),6) -> 19.42 | AD71: =ROUND(((((ET71*1.1))-((EU71*1.1)))+AE71),6) -> 4.455 | AE71: =ROUND(((EU71*1.1)),6) -> 0 | AF71: =ROUND(((EV71*1.1)),6) -> 323.631 | AG71: =ROUND((AP71),6) -> 0 | AH71: =((EW71*1.1)) -> 27.236 | AI71: =((EX71*1.1)) -> 0 | AJ71: =(AS71) -> 0 | AK71: 317.68 | AL71: 19.42 | AM71: 4.05 | AN71: 0 | AO71: 294.21 | AP71: 0 | AQ71: 24.76 | AR71: 0 | AS71: 0 | AT71: 90 | AU71: 46 | AV71: 1.047 | AW71: 1 | AZ71: 1 | BA71: 1 | BB71: 1 | BC71: 1 | BH71: 0 | BI71: 2 | BJ71: ТСН-2001.4 Доп. 80, Сб. 10, т. 185, поз. 3 | BM71: 68 | BN71: 0 | BO71: 4.10-185-3 | BP71: 1 | BQ71: 40 | BR71: 0 | BS71: 1 | BT71: 1 | BU71: 1 | BV71: 1 | BW71: 1 | BX71: 1 | BZ71: 90 | CA71: 46 | CE71: 1566 | CF71: 0 | CG71: 0 | CM71: 0 | CN71: Поправка: О.П. п.3.4.30.в Наименование: При применении территориальных сметных нормативов для города Москвы затраты, учитывающие напряженные и стесненные условия производства работ (стесненность, сложность складирования и транспортной логистики и т.п.), исчисляются с применением коэффициентов к затратам труда и заработной плате рабочих, машинистов, времени эксплуатации машин и механизмов, стоимости эксплуатации машин в размере: для объектов, расположенных за пределами Третьего транспортного кольца города Москвы, но в пределах Московской кольцевой автомобильной дороги | CO71: 0 | CP71: =(P71+Q71+S71) -> 181.46 | CQ71: =ROUND((ROUND((AC71*AW71*1),2)*BC71),2) -> 19.42 | CR71: =(ROUND((ROUND((((ET71*1.1))*AV71*1),2)*BB71),2)+ROUND((ROUND(((AE71-((EU71*1.1)))*AV71*1),2)*BS71),2)) -> 4.66 | CS71: =(ROUND((ROUND((((EU71*1.1))*AV71*1),2)*BS71),2)+ROUND((ROUND(((AE71-((EU71*1.1)))*AV71*1),2)*BS71),2)) -> 0 | CT71: =ROUND((ROUND((AF71*AV71*1),2)*BA71),2) -> 338.84 | CU71: =AG71 -> 0 | CV71: =(AH71*AV71) -> 28.516092 | CW71: =AI71 -> 0 | CX71: =AJ71 -> 0 | CY71: =(ROUND((((S71+ROUND((ROUND((((EU71*1.1))*AV71*1),2)*BS71),2))*AT71)/100),2)+ROUND(((ROUND((ROUND(((AE71-((EU71*1.1)))*AV71*1),2)*BS71),2)*AT71)/100),2)) -> 152.48 | CZ71: =(ROUND((((S71+ROUND((ROUND((((EU71*1.1))*AV71*1),2)*BS71),2))*AU71)/100),2)+ROUND(((ROUND((ROUND(((AE71-((EU71*1.1)))*AV71*1),2)*BS71),2)*AU71)/100),2)) -> 77.93 | DB71: 5 | DE71: *1,1 | DF71: *1,1 | DG71: *1,1 | DI71: *1,1 | DJ71: *1,1 | DN71: 0 | DO71: 0 | DP71: 1 | DQ71: 1 | DU71: 1003 | DV71: 100 м | DW71: 100 м | DX71: 100 | EE71: 60088532 | EF71: 40 | EG71: Монтаж оборудования | EH71: 0 | EJ71: 2 | EK71: 68 | EL71: ТСН-2001.4-10. Прокладка и монтаж сетей связи | EM71: ТСН-2001.4-10-1 | EO71: Поправка: О.П. п.3.4.30.в | EQ71: 0 | ER71: 317.68 | ES71: 19.42 | ET71: 4.05 | EU71: 0 | EV71: 294.21 | EW71: 24.76 | EX71: 0 | EY71: 0 | FQ71: 0 | FR71: 0 | FS71: 0 | FX71: 90 | FY71: 46 | GD71: 1 | GF71: -670664398 | GG71: 2 | GH71: 1 | GI71: 2 | GJ71: 0 | GK71: 0 | GL71: =ROUND(IF(AND(BH71=3,BI71=3,FS71<>0),P71,0),2) -> 0 | GM71: =ROUND(O71+X71+Y71,2)+GX71 -> 411.87 | GN71: =IF(OR(BI71=0,BI71=1),GM71-GX71,0) -> 0 | GO71: =IF(BI71=2,GM71-GX71,0) -> 411.87 | GP71: =IF(BI71=4,GM71-GX71,0) -> 0 | GR71: 0 | GS71: 3 | GT71: 0 | GV71: =ROUND((GT71),6) -> 0 | GW71: 1 | GX71: =ROUND(HC71*I71,2) -> 0 | HA71: 0 | HB71: 0 | HC71: =GV71*GW71 -> 0 | HS71: 0 | IK71: 0
A72: 17 | B72: 1 | C72: =ROW(SmtRes!A22) -> 22 | D72: =ROW(EtalonRes!A24) -> 24 | E72: 5 | F72: 4.10-185-3 | G72: Прокладка кабеля связи огнестойкого в трубах гофрированных с использованием скобы СМО: по бетонным поверхностям | H72: 100 м | I72: =ROUND(50/100,9) -> 0.5 | J72: 0 | K72: =ROUND(50/100,9) -> 0.5 | O72: =ROUND(CP72,2) -> 9401.4 | P72: =ROUND((ROUND((AC72*AW72*I72),2)*BC72),2) -> 64.67 | Q72: =(ROUND((ROUND((((ET72*1.1))*AV72*I72),2)*BB72),2)+ROUND((ROUND(((AE72-((EU72*1.1)))*AV72*I72),2)*BS72),2)) -> 20.32 | R72: =(ROUND((ROUND((((EU72*1.1))*AV72*I72),2)*BS72),2)+ROUND((ROUND(((AE72-((EU72*1.1)))*AV72*I72),2)*BS72),2)) -> 0 | S72: =ROUND((ROUND((AF72*AV72*I72),2)*BA72),2) -> 9316.41 | T72: =ROUND(CU72*I72,2) -> 0 | U72: =CV72*I72 -> 14.258046 | V72: =CW72*I72 -> 0 | W72: =ROUND(CX72*I72,2) -> 0 | X72: =(ROUND((((S72+ROUND((ROUND((((EU72*1.1))*AV72*I72),2)*BS72),2))*AT72)/100),2)+ROUND(((ROUND((ROUND(((AE72-((EU72*1.1)))*AV72*I72),2)*BS72),2)*AT72)/100),2)) -> 8384.77 | Y72: =(ROUND((((S72+ROUND((ROUND((((EU72*1.1))*AV72*I72),2)*BS72),2))*AU72)/100),2)+ROUND(((ROUND((ROUND(((AE72-((EU72*1.1)))*AV72*I72),2)*BS72),2)*AU72)/100),2)) -> 4285.55 | AA72: 60257733 | AB72: =ROUND((AC72+AD72+AF72),6) -> 347.506 | AC72: =ROUND((ES72),6) -> 19.42 | AD72: =ROUND(((((ET72*1.1))-((EU72*1.1)))+AE72),6) -> 4.455 | AE72: =ROUND(((EU72*1.1)),6) -> 0 | AF72: =ROUND(((EV72*1.1)),6) -> 323.631 | AG72: =ROUND((AP72),6) -> 0 | AH72: =((EW72*1.1)) -> 27.236 | AI72: =((EX72*1.1)) -> 0 | AJ72: =(AS72) -> 0 | AK72: 317.68 | AL72: 19.42 | AM72: 4.05 | AN72: 0 | AO72: 294.21 | AP72: 0 | AQ72: 24.76 | AR72: 0 | AS72: 0 | AT72: 90 | AU72: 46 | AV72: 1.047 | AW72: 1 | AZ72: 1 | BA72: 54.99 | BB72: 8.72 | BC72: 6.66 | BH72: 0 | BI72: 2 | BJ72: ТСН-2001.4 Доп. 80, Сб. 10, т. 185, поз. 3 | BM72: 68 | BN72: 0 | BO72: 4.10-185-3 | BP72: 1 | BQ72: 40 | BR72: 0 | BS72: 54.99 | BT72: 1 | BU72: 1 | BV72: 1 | BW72: 1 | BX72: 1 | BZ72: 90 | CA72: 46 | CE72: 1566 | CF72: 0 | CG72: 0 | CM72: 0 | CN72: Поправка: О.П. п.3.4.30.в Наименование: При применении территориальных сметных нормативов для города Москвы затраты, учитывающие напряженные и стесненные условия производства работ (стесненность, сложность складирования и транспортной логистики и т.п.), исчисляются с применением коэффициентов к затратам труда и заработной плате рабочих, машинистов, времени эксплуатации машин и механизмов, стоимости эксплуатации машин в размере: для объектов, расположенных за пределами Третьего транспортного кольца города Москвы, но в пределах Московской кольцевой автомобильной дороги | CO72: 0 | CP72: =(P72+Q72+S72) -> 9401.4 | CQ72: =ROUND((ROUND((AC72*AW72*1),2)*BC72),2) -> 129.34 | CR72: =(ROUND((ROUND((((ET72*1.1))*AV72*1),2)*BB72),2)+ROUND((ROUND(((AE72-((EU72*1.1)))*AV72*1),2)*BS72),2)) -> 40.64 | CS72: =(ROUND((ROUND((((EU72*1.1))*AV72*1),2)*BS72),2)+ROUND((ROUND(((AE72-((EU72*1.1)))*AV72*1),2)*BS72),2)) -> 0 | CT72: =ROUND((ROUND((AF72*AV72*1),2)*BA72),2) -> 18632.81 | CU72: =AG72 -> 0 | CV72: =(AH72*AV72) -> 28.516092 | CW72: =AI72 -> 0 | CX72: =AJ72 -> 0 | CY72: =(ROUND((((S72+ROUND((ROUND((((EU72*1.1))*AV72*1),2)*BS72),2))*AT72)/100),2)+ROUND(((ROUND((ROUND(((AE72-((EU72*1.1)))*AV72*1),2)*BS72),2)*AT72)/100),2)) -> 8384.77 | CZ72: =(ROUND((((S72+ROUND((ROUND((((EU72*1.1))*AV72*1),2)*BS72),2))*AU72)/100),2)+ROUND(((ROUND((ROUND(((AE72-((EU72*1.1)))*AV72*1),2)*BS72),2)*AU72)/100),2)) -> 4285.55 | DB72: 6 | DE72: *1,1 | DF72: *1,1 | DG72: *1,1 | DI72: *1,1 | DJ72: *1,1 | DN72: 0 | DO72: 0 | DP72: 1 | DQ72: 1 | DU72: 1003 | DV72: 100 м | DW72: 100 м | DX72: 100 | EE72: 60088532 | EF72: 40 | EG72: Монтаж оборудования | EH72: 0 | EJ72: 2 | EK72: 68 | EL72: ТСН-2001.4-10. Прокладка и монтаж сетей связи | EM72: ТСН-2001.4-10-1 | EO72: Поправка: О.П. п.3.4.30.в | EQ72: 0 | ER72: 317.68 | ES72: 19.42 | ET72: 4.05 | EU72: 0 | EV72: 294.21 | EW72: 24.76 | EX72: 0 | EY72: 0 | FQ72: 0 | FR72: 0 | FS72: 0 | FX72: 90 | FY72: 46 | GD72: 1 | GF72: -670664398 | GG72: 2 | GH72: 1 | GI72: 2 | GJ72: 0 | GK72: 0 | GL72: =ROUND(IF(AND(BH72=3,BI72=3,FS72<>0),P72,0),2) -> 0 | GM72: =ROUND(O72+X72+Y72,2)+GX72 -> 22071.72 | GN72: =IF(OR(BI72=0,BI72=1),GM72-GX72,0) -> 0 | GO72: =IF(BI72=2,GM72-GX72,0) -> 22071.72 | GP72: =IF(BI72=4,GM72-GX72,0) -> 0 | GR72: 0 | GS72: 3 | GT72: 0 | GV72: =ROUND((GT72),6) -> 0 | GW72: 1 | GX72: =ROUND(HC72*I72,2) -> 0 | HA72: 0 | HB72: 0 | HC72: =GV72*GW72 -> 0 | HS72: 0 | IK72: 0
A73: 18 | B73: 1 | C73: 8 | E73: 5,1 | F73: 1.12-5-371 | G73: Трубы электротехнические, гофрированные, из ПВХ, негорючие, с зондом, наружный диаметр 16 мм | H73: м | I73: =I71*J73 -> 51 | J73: 102 | K73: 102 | O73: =ROUND(CP73,2) -> 136.17 | P73: =ROUND((ROUND((AC73*AW73*I73),2)*BC73),2) -> 136.17 | Q73: =(ROUND((ROUND(((ET73)*AV73*I73),2)*BB73),2)+ROUND((ROUND(((AE73-(EU73))*AV73*I73),2)*BS73),2)) -> 0 | R73: =(ROUND((ROUND(((EU73)*AV73*I73),2)*BS73),2)+ROUND((ROUND(((AE73-(EU73))*AV73*I73),2)*BS73),2)) -> 0 | S73: =ROUND((ROUND((AF73*AV73*I73),2)*BA73),2) -> 0 | T73: =ROUND(CU73*I73,2) -> 0 | U73: =CV73*I73 -> 0 | V73: =CW73*I73 -> 0 | W73: =ROUND(CX73*I73,2) -> 0 | X73: =(ROUND((((S73+ROUND((ROUND(((EU73)*AV73*I73),2)*BS73),2))*AT73)/100),2)+ROUND(((ROUND((ROUND(((AE73-(EU73))*AV73*I73),2)*BS73),2)*AT73)/100),2)) -> 0 | Y73: =(ROUND((((S73+ROUND((ROUND(((EU73)*AV73*I73),2)*BS73),2))*AU73)/100),2)+ROUND(((ROUND((ROUND(((AE73-(EU73))*AV73*I73),2)*BS73),2)*AU73)/100),2)) -> 0 | AA73: 60257736 | AB73: =ROUND((AC73+AD73+AF73),6) -> 2.67 | AC73: =ROUND((ES73),6) -> 2.67 | AD73: =ROUND((((ET73)-(EU73))+AE73),6) -> 0 | AE73: =ROUND((EU73),6) -> 0 | AF73: =ROUND((EV73),6) -> 0 | AG73: =ROUND((AP73),6) -> 0 | AH73: =(EW73) -> 0 | AI73: =(EX73) -> 0 | AJ73: =(AS73) -> 0 | AK73: 2.67 | AL73: 2.67 | AM73: 0 | AN73: 0 | AO73: 0 | AP73: 0 | AQ73: 0 | AR73: 0 | AS73: 0 | AT73: 90 | AU73: 46 | AV73: 1 | AW73: 1 | AZ73: 1 | BA73: 1 | BB73: 1 | BC73: 1 | BH73: 3 | BI73: 2 | BJ73: ТСН-2001.1 Доп. 67, Р. 12, о. 5, поз. 371 | BM73: 68 | BN73: 0 | BP73: 0 | BQ73: 40 | BR73: 0 | BS73: 1 | BT73: 1 | BU73: 1 | BV73: 1 | BW73: 1 | BX73: 1 | BZ73: 90 | CA73: 46 | CE73: 1566 | CF73: 0 | CG73: 0 | CM73: 0 | CO73: 0 | CP73: =(P73+Q73+S73) -> 136.17 | CQ73: =ROUND((ROUND((AC73*AW73*1),2)*BC73),2) -> 2.67 | CR73: =(ROUND((ROUND(((ET73)*AV73*1),2)*BB73),2)+ROUND((ROUND(((AE73-(EU73))*AV73*1),2)*BS73),2)) -> 0 | CS73: =(ROUND((ROUND(((EU73)*AV73*1),2)*BS73),2)+ROUND((ROUND(((AE73-(EU73))*AV73*1),2)*BS73),2)) -> 0 | CT73: =ROUND((ROUND((AF73*AV73*1),2)*BA73),2) -> 0 | CU73: =AG73 -> 0 | CV73: =(AH73*AV73) -> 0 | CW73: =AI73 -> 0 | CX73: =AJ73 -> 0 | CY73: =(ROUND((((S73+ROUND((ROUND(((EU73)*AV73*1),2)*BS73),2))*AT73)/100),2)+ROUND(((ROUND((ROUND(((AE73-(EU73))*AV73*1),2)*BS73),2)*AT73)/100),2)) -> 0 | CZ73: =(ROUND((((S73+ROUND((ROUND(((EU73)*AV73*1),2)*BS73),2))*AU73)/100),2)+ROUND(((ROUND((ROUND(((AE73-(EU73))*AV73*1),2)*BS73),2)*AU73)/100),2)) -> 0 | DN73: 0 | DO73: 0 | DP73: 1 | DQ73: 1 | DU73: 1003 | DV73: м | DW73: м | DX73: 1 | EE73: 60088532 | EF73: 40 | EG73: Монтаж оборудования | EH73: 0 | EJ73: 2 | EK73: 68 | EL73: ТСН-2001.4-10. Прокладка и монтаж сетей связи | EM73: ТСН-2001.4-10-1 | EQ73: 0 | ER73: 2.67 | ES73: 2.67 | ET73: 0 | EU73: 0 | EV73: 0 | EW73: 0 | EX73: 0 | FQ73: 0 | FR73: 0 | FS73: 0 | FX73: 90 | FY73: 46 | GD73: 1 | GF73: 1184991115 | GG73: 2 | GH73: 1 | GI73: -2 | GJ73: 0 | GK73: 0 | GL73: =ROUND(IF(AND(BH73=3,BI73=3,FS73<>0),P73,0),2) -> 0 | GM73: =ROUND(O73+X73+Y73,2)+GX73 -> 136.17 | GN73: =IF(OR(BI73=0,BI73=1),GM73-GX73,0) -> 0 | GO73: =IF(BI73=2,GM73-GX73,0) -> 136.17 | GP73: =IF(BI73=4,GM73-GX73,0) -> 0 | GR73: 0 | GS73: 3 | GT73: 0 | GV73: =ROUND((GT73),6) -> 0 | GW73: 1 | GX73: =ROUND(HC73*I73,2) -> 0 | HA73: 0 | HB73: 0 | HC73: =GV73*GW73 -> 0 | HS73: 0 | IK73: 0
A74: 18 | B74: 1 | C74: 17 | E74: 5,1 | F74: 1.12-5-371 | G74: Трубы электротехнические, гофрированные, из ПВХ, негорючие, с зондом, наружный диаметр 16 мм | H74: м | I74: =I72*J74 -> 51 | J74: 102 | K74: 102 | O74: =ROUND(CP74,2) -> 521.53 | P74: =ROUND((ROUND((AC74*AW74*I74),2)*BC74),2) -> 521.53 | Q74: =(ROUND((ROUND(((ET74)*AV74*I74),2)*BB74),2)+ROUND((ROUND(((AE74-(EU74))*AV74*I74),2)*BS74),2)) -> 0 | R74: =(ROUND((ROUND(((EU74)*AV74*I74),2)*BS74),2)+ROUND((ROUND(((AE74-(EU74))*AV74*I74),2)*BS74),2)) -> 0 | S74: =ROUND((ROUND((AF74*AV74*I74),2)*BA74),2) -> 0 | T74: =ROUND(CU74*I74,2) -> 0 | U74: =CV74*I74 -> 0 | V74: =CW74*I74 -> 0 | W74: =ROUND(CX74*I74,2) -> 0 | X74: =(ROUND((((S74+ROUND((ROUND(((EU74)*AV74*I74),2)*BS74),2))*AT74)/100),2)+ROUND(((ROUND((ROUND(((AE74-(EU74))*AV74*I74),2)*BS74),2)*AT74)/100),2)) -> 0 | Y74: =(ROUND((((S74+ROUND((ROUND(((EU74)*AV74*I74),2)*BS74),2))*AU74)/100),2)+ROUND(((ROUND((ROUND(((AE74-(EU74))*AV74*I74),2)*BS74),2)*AU74)/100),2)) -> 0 | AA74: 60257733 | AB74: =ROUND((AC74+AD74+AF74),6) -> 2.67 | AC74: =ROUND((ES74),6) -> 2.67 | AD74: =ROUND((((ET74)-(EU74))+AE74),6) -> 0 | AE74: =ROUND((EU74),6) -> 0 | AF74: =ROUND((EV74),6) -> 0 | AG74: =ROUND((AP74),6) -> 0 | AH74: =(EW74) -> 0 | AI74: =(EX74) -> 0 | AJ74: =(AS74) -> 0 | AK74: 2.67 | AL74: 2.67 | AM74: 0 | AN74: 0 | AO74: 0 | AP74: 0 | AQ74: 0 | AR74: 0 | AS74: 0 | AT74: 90 | AU74: 46 | AV74: 1 | AW74: 1 | AZ74: 1 | BA74: 1 | BB74: 1 | BC74: 3.83 | BH74: 3 | BI74: 2 | BJ74: ТСН-2001.1 Доп. 67, Р. 12, о. 5, поз. 371 | BM74: 68 | BN74: 0 | BO74: 1.12-5-371 | BP74: 1 | BQ74: 40 | BR74: 0 | BS74: 1 | BT74: 1 | BU74: 1 | BV74: 1 | BW74: 1 | BX74: 1 | BZ74: 90 | CA74: 46 | CE74: 1566 | CF74: 0 | CG74: 0 | CM74: 0 | CO74: 0 | CP74: =(P74+Q74+S74) -> 521.53 | CQ74: =ROUND((ROUND((AC74*AW74*1),2)*BC74),2) -> 10.23 | CR74: =(ROUND((ROUND(((ET74)*AV74*1),2)*BB74),2)+ROUND((ROUND(((AE74-(EU74))*AV74*1),2)*BS74),2)) -> 0 | CS74: =(ROUND((ROUND(((EU74)*AV74*1),2)*BS74),2)+ROUND((ROUND(((AE74-(EU74))*AV74*1),2)*BS74),2)) -> 0 | CT74: =ROUND((ROUND((AF74*AV74*1),2)*BA74),2) -> 0 | CU74: =AG74 -> 0 | CV74: =(AH74*AV74) -> 0 | CW74: =AI74 -> 0 | CX74: =AJ74 -> 0 | CY74: =(ROUND((((S74+ROUND((ROUND(((EU74)*AV74*1),2)*BS74),2))*AT74)/100),2)+ROUND(((ROUND((ROUND(((AE74-(EU74))*AV74*1),2)*BS74),2)*AT74)/100),2)) -> 0 | CZ74: =(ROUND((((S74+ROUND((ROUND(((EU74)*AV74*1),2)*BS74),2))*AU74)/100),2)+ROUND(((ROUND((ROUND(((AE74-(EU74))*AV74*1),2)*BS74),2)*AU74)/100),2)) -> 0 | DN74: 0 | DO74: 0 | DP74: 1 | DQ74: 1 | DU74: 1003 | DV74: м | DW74: м | DX74: 1 | EE74: 60088532 | EF74: 40 | EG74: Монтаж оборудования | EH74: 0 | EJ74: 2 | EK74: 68 | EL74: ТСН-2001.4-10. Прокладка и монтаж сетей связи | EM74: ТСН-2001.4-10-1 | EQ74: 0 | ER74: 2.67 | ES74: 2.67 | ET74: 0 | EU74: 0 | EV74: 0 | EW74: 0 | EX74: 0 | FQ74: 0 | FR74: 0 | FS74: 0 | FX74: 90 | FY74: 46 | GD74: 1 | GF74: 1184991115 | GG74: 2 | GH74: 1 | GI74: 2 | GJ74: 0 | GK74: 0 | GL74: =ROUND(IF(AND(BH74=3,BI74=3,FS74<>0),P74,0),2) -> 0 | GM74: =ROUND(O74+X74+Y74,2)+GX74 -> 521.53 | GN74: =IF(OR(BI74=0,BI74=1),GM74-GX74,0) -> 0 | GO74: =IF(BI74=2,GM74-GX74,0) -> 521.53 | GP74: =IF(BI74=4,GM74-GX74,0) -> 0 | GR74: 0 | GS74: 3 | GT74: 0 | GV74: =ROUND((GT74),6) -> 0 | GW74: 1 | GX74: =ROUND(HC74*I74,2) -> 0 | HA74: 0 | HB74: 0 | HC74: =GV74*GW74 -> 0 | HS74: 0 | IK74: 0
A75: 18 | B75: 1 | C75: 9 | E75: 5,2 | F75: 1.14-1-555 | G75: Скобы крепежные для радиочастотного коаксиального кабеля с номинальным диаметром по изоляции от 4 до 6 мм | H75: 100 шт. | I75: =I71*J75 -> 1.19 | J75: 2.38 | K75: 2.38 | O75: =ROUND(CP75,2) -> 55.49 | P75: =ROUND((ROUND((AC75*AW75*I75),2)*BC75),2) -> 55.49 | Q75: =(ROUND((ROUND(((ET75)*AV75*I75),2)*BB75),2)+ROUND((ROUND(((AE75-(EU75))*AV75*I75),2)*BS75),2)) -> 0 | R75: =(ROUND((ROUND(((EU75)*AV75*I75),2)*BS75),2)+ROUND((ROUND(((AE75-(EU75))*AV75*I75),2)*BS75),2)) -> 0 | S75: =ROUND((ROUND((AF75*AV75*I75),2)*BA75),2) -> 0 | T75: =ROUND(CU75*I75,2) -> 0 | U75: =CV75*I75 -> 0 | V75: =CW75*I75 -> 0 | W75: =ROUND(CX75*I75,2) -> 0 | X75: =(ROUND((((S75+ROUND((ROUND(((EU75)*AV75*I75),2)*BS75),2))*AT75)/100),2)+ROUND(((ROUND((ROUND(((AE75-(EU75))*AV75*I75),2)*BS75),2)*AT75)/100),2)) -> 0 | Y75: =(ROUND((((S75+ROUND((ROUND(((EU75)*AV75*I75),2)*BS75),2))*AU75)/100),2)+ROUND(((ROUND((ROUND(((AE75-(EU75))*AV75*I75),2)*BS75),2)*AU75)/100),2)) -> 0 | AA75: 60257736 | AB75: =ROUND((AC75+AD75+AF75),6) -> 46.63 | AC75: =ROUND((ES75),6) -> 46.63 | AD75: =ROUND((((ET75)-(EU75))+AE75),6) -> 0 | AE75: =ROUND((EU75),6) -> 0 | AF75: =ROUND((EV75),6) -> 0 | AG75: =ROUND((AP75),6) -> 0 | AH75: =(EW75) -> 0 | AI75: =(EX75) -> 0 | AJ75: =(AS75) -> 0 | AK75: 46.63 | AL75: 46.63 | AM75: 0 | AN75: 0 | AO75: 0 | AP75: 0 | AQ75: 0 | AR75: 0 | AS75: 0 | AT75: 90 | AU75: 46 | AV75: 1 | AW75: 1 | AZ75: 1 | BA75: 1 | BB75: 1 | BC75: 1 | BH75: 3 | BI75: 2 | BJ75: ТСН-2001.1 Доп. 73, Р. 14, о. 1, поз. 555 | BM75: 68 | BN75: 0 | BP75: 0 | BQ75: 40 | BR75: 0 | BS75: 1 | BT75: 1 | BU75: 1 | BV75: 1 | BW75: 1 | BX75: 1 | BZ75: 90 | CA75: 46 | CE75: 1566 | CF75: 0 | CG75: 0 | CM75: 0 | CO75: 0 | CP75: =(P75+Q75+S75) -> 55.49 | CQ75: =ROUND((ROUND((AC75*AW75*1),2)*BC75),2) -> 46.63 | CR75: =(ROUND((ROUND(((ET75)*AV75*1),2)*BB75),2)+ROUND((ROUND(((AE75-(EU75))*AV75*1),2)*BS75),2)) -> 0 | CS75: =(ROUND((ROUND(((EU75)*AV75*1),2)*BS75),2)+ROUND((ROUND(((AE75-(EU75))*AV75*1),2)*BS75),2)) -> 0 | CT75: =ROUND((ROUND((AF75*AV75*1),2)*BA75),2) -> 0 | CU75: =AG75 -> 0 | CV75: =(AH75*AV75) -> 0 | CW75: =AI75 -> 0 | CX75: =AJ75 -> 0 | CY75: =(ROUND((((S75+ROUND((ROUND(((EU75)*AV75*1),2)*BS75),2))*AT75)/100),2)+ROUND(((ROUND((ROUND(((AE75-(EU75))*AV75*1),2)*BS75),2)*AT75)/100),2)) -> 0 | CZ75: =(ROUND((((S75+ROUND((ROUND(((EU75)*AV75*1),2)*BS75),2))*AU75)/100),2)+ROUND(((ROUND((ROUND(((AE75-(EU75))*AV75*1),2)*BS75),2)*AU75)/100),2)) -> 0 | DN75: 0 | DO75: 0 | DP75: 1 | DQ75: 1 | DU75: 1010 | DV75: 100 шт. | DW75: 100 шт. | DX75: 100 | EE75: 60088532 | EF75: 40 | EG75: Монтаж оборудования | EH75: 0 | EJ75: 2 | EK75: 68 | EL75: ТСН-2001.4-10. Прокладка и монтаж сетей связи | EM75: ТСН-2001.4-10-1 | EQ75: 0 | ER75: 46.63 | ES75: 46.63 | ET75: 0 | EU75: 0 | EV75: 0 | EW75: 0 | EX75: 0 | FQ75: 0 | FR75: 0 | FS75: 0 | FX75: 90 | FY75: 46 | GD75: 1 | GF75: -1288220709 | GG75: 2 | GH75: 1 | GI75: -2 | GJ75: 0 | GK75: 0 | GL75: =ROUND(IF(AND(BH75=3,BI75=3,FS75<>0),P75,0),2) -> 0 | GM75: =ROUND(O75+X75+Y75,2)+GX75 -> 55.49 | GN75: =IF(OR(BI75=0,BI75=1),GM75-GX75,0) -> 0 | GO75: =IF(BI75=2,GM75-GX75,0) -> 55.49 | GP75: =IF(BI75=4,GM75-GX75,0) -> 0 | GR75: 0 | GS75: 3 | GT75: 0 | GV75: =ROUND((GT75),6) -> 0 | GW75: 1 | GX75: =ROUND(HC75*I75,2) -> 0 | HA75: 0 | HB75: 0 | HC75: =GV75*GW75 -> 0 | HS75: 0 | IK75: 0
A76: 18 | B76: 1 | C76: 18 | E76: 5,2 | F76: 1.14-1-555 | G76: Скобы крепежные для радиочастотного коаксиального кабеля с номинальным диаметром по изоляции от 4 до 6 мм | H76: 100 шт. | I76: =I72*J76 -> 1.19 | J76: 2.38 | K76: 2.38 | O76: =ROUND(CP76,2) -> 59.93 | P76: =ROUND((ROUND((AC76*AW76*I76),2)*BC76),2) -> 59.93 | Q76: =(ROUND((ROUND(((ET76)*AV76*I76),2)*BB76),2)+ROUND((ROUND(((AE76-(EU76))*AV76*I76),2)*BS76),2)) -> 0 | R76: =(ROUND((ROUND(((EU76)*AV76*I76),2)*BS76),2)+ROUND((ROUND(((AE76-(EU76))*AV76*I76),2)*BS76),2)) -> 0 | S76: =ROUND((ROUND((AF76*AV76*I76),2)*BA76),2) -> 0 | T76: =ROUND(CU76*I76,2) -> 0 | U76: =CV76*I76 -> 0 | V76: =CW76*I76 -> 0 | W76: =ROUND(CX76*I76,2) -> 0 | X76: =(ROUND((((S76+ROUND((ROUND(((EU76)*AV76*I76),2)*BS76),2))*AT76)/100),2)+ROUND(((ROUND((ROUND(((AE76-(EU76))*AV76*I76),2)*BS76),2)*AT76)/100),2)) -> 0 | Y76: =(ROUND((((S76+ROUND((ROUND(((EU76)*AV76*I76),2)*BS76),2))*AU76)/100),2)+ROUND(((ROUND((ROUND(((AE76-(EU76))*AV76*I76),2)*BS76),2)*AU76)/100),2)) -> 0 | AA76: 60257733 | AB76: =ROUND((AC76+AD76+AF76),6) -> 46.63 | AC76: =ROUND((ES76),6) -> 46.63 | AD76: =ROUND((((ET76)-(EU76))+AE76),6) -> 0 | AE76: =ROUND((EU76),6) -> 0 | AF76: =ROUND((EV76),6) -> 0 | AG76: =ROUND((AP76),6) -> 0 | AH76: =(EW76) -> 0 | AI76: =(EX76) -> 0 | AJ76: =(AS76) -> 0 | AK76: 46.63 | AL76: 46.63 | AM76: 0 | AN76: 0 | AO76: 0 | AP76: 0 | AQ76: 0 | AR76: 0 | AS76: 0 | AT76: 90 | AU76: 46 | AV76: 1 | AW76: 1 | AZ76: 1 | BA76: 1 | BB76: 1 | BC76: 1.08 | BH76: 3 | BI76: 2 | BJ76: ТСН-2001.1 Доп. 73, Р. 14, о. 1, поз. 555 | BM76: 68 | BN76: 0 | BO76: 1.14-1-555 | BP76: 1 | BQ76: 40 | BR76: 0 | BS76: 1 | BT76: 1 | BU76: 1 | BV76: 1 | BW76: 1 | BX76: 1 | BZ76: 90 | CA76: 46 | CE76: 1566 | CF76: 0 | CG76: 0 | CM76: 0 | CO76: 0 | CP76: =(P76+Q76+S76) -> 59.93 | CQ76: =ROUND((ROUND((AC76*AW76*1),2)*BC76),2) -> 50.36 | CR76: =(ROUND((ROUND(((ET76)*AV76*1),2)*BB76),2)+ROUND((ROUND(((AE76-(EU76))*AV76*1),2)*BS76),2)) -> 0 | CS76: =(ROUND((ROUND(((EU76)*AV76*1),2)*BS76),2)+ROUND((ROUND(((AE76-(EU76))*AV76*1),2)*BS76),2)) -> 0 | CT76: =ROUND((ROUND((AF76*AV76*1),2)*BA76),2) -> 0 | CU76: =AG76 -> 0 | CV76: =(AH76*AV76) -> 0 | CW76: =AI76 -> 0 | CX76: =AJ76 -> 0 | CY76: =(ROUND((((S76+ROUND((ROUND(((EU76)*AV76*1),2)*BS76),2))*AT76)/100),2)+ROUND(((ROUND((ROUND(((AE76-(EU76))*AV76*1),2)*BS76),2)*AT76)/100),2)) -> 0 | CZ76: =(ROUND((((S76+ROUND((ROUND(((EU76)*AV76*1),2)*BS76),2))*AU76)/100),2)+ROUND(((ROUND((ROUND(((AE76-(EU76))*AV76*1),2)*BS76),2)*AU76)/100),2)) -> 0 | DN76: 0 | DO76: 0 | DP76: 1 | DQ76: 1 | DU76: 1010 | DV76: 100 шт. | DW76: 100 шт. | DX76: 100 | EE76: 60088532 | EF76: 40 | EG76: Монтаж оборудования | EH76: 0 | EJ76: 2 | EK76: 68 | EL76: ТСН-2001.4-10. Прокладка и монтаж сетей связи | EM76: ТСН-2001.4-10-1 | EQ76: 0 | ER76: 46.63 | ES76: 46.63 | ET76: 0 | EU76: 0 | EV76: 0 | EW76: 0 | EX76: 0 | FQ76: 0 | FR76: 0 | FS76: 0 | FX76: 90 | FY76: 46 | GD76: 1 | GF76: -1288220709 | GG76: 2 | GH76: 1 | GI76: 2 | GJ76: 0 | GK76: 0 | GL76: =ROUND(IF(AND(BH76=3,BI76=3,FS76<>0),P76,0),2) -> 0 | GM76: =ROUND(O76+X76+Y76,2)+GX76 -> 59.93 | GN76: =IF(OR(BI76=0,BI76=1),GM76-GX76,0) -> 0 | GO76: =IF(BI76=2,GM76-GX76,0) -> 59.93 | GP76: =IF(BI76=4,GM76-GX76,0) -> 0 | GR76: 0 | GS76: 3 | GT76: 0 | GV76: =ROUND((GT76),6) -> 0 | GW76: 1 | GX76: =ROUND(HC76*I76,2) -> 0 | HA76: 0 | HB76: 0 | HC76: =GV76*GW76 -> 0 | HS76: 0 | IK76: 0
A77: 18 | B77: 1 | C77: 13 | E77: 5,3 | F77: 1.7-5-131 | G77: Анкер забивной расклинивающийся из оцинкованной стали, с внутренней резьбой М12, длина 25 мм | H77: 100 шт. | I77: =I71*J77 -> 1.18 | J77: 2.36 | K77: 2.36 | O77: =ROUND(CP77,2) -> 1530.73 | P77: =ROUND((ROUND((AC77*AW77*I77),2)*BC77),2) -> 1530.73 | Q77: =(ROUND((ROUND(((ET77)*AV77*I77),2)*BB77),2)+ROUND((ROUND(((AE77-(EU77))*AV77*I77),2)*BS77),2)) -> 0 | R77: =(ROUND((ROUND(((EU77)*AV77*I77),2)*BS77),2)+ROUND((ROUND(((AE77-(EU77))*AV77*I77),2)*BS77),2)) -> 0 | S77: =ROUND((ROUND((AF77*AV77*I77),2)*BA77),2) -> 0 | T77: =ROUND(CU77*I77,2) -> 0 | U77: =CV77*I77 -> 0 | V77: =CW77*I77 -> 0 | W77: =ROUND(CX77*I77,2) -> 0 | X77: =(ROUND((((S77+ROUND((ROUND(((EU77)*AV77*I77),2)*BS77),2))*AT77)/100),2)+ROUND(((ROUND((ROUND(((AE77-(EU77))*AV77*I77),2)*BS77),2)*AT77)/100),2)) -> 0 | Y77: =(ROUND((((S77+ROUND((ROUND(((EU77)*AV77*I77),2)*BS77),2))*AU77)/100),2)+ROUND(((ROUND((ROUND(((AE77-(EU77))*AV77*I77),2)*BS77),2)*AU77)/100),2)) -> 0 | AA77: 60257736 | AB77: =ROUND((AC77+AD77+AF77),6) -> 1297.23 | AC77: =ROUND((ES77),6) -> 1297.23 | AD77: =ROUND((((ET77)-(EU77))+AE77),6) -> 0 | AE77: =ROUND((EU77),6) -> 0 | AF77: =ROUND((EV77),6) -> 0 | AG77: =ROUND((AP77),6) -> 0 | AH77: =(EW77) -> 0 | AI77: =(EX77) -> 0 | AJ77: =(AS77) -> 0 | AK77: 1297.23 | AL77: 1297.23 | AM77: 0 | AN77: 0 | AO77: 0 | AP77: 0 | AQ77: 0 | AR77: 0 | AS77: 0 | AT77: 90 | AU77: 46 | AV77: 1 | AW77: 1 | AZ77: 1 | BA77: 1 | BB77: 1 | BC77: 1 | BH77: 3 | BI77: 2 | BJ77: ТСН-2001.1 Доп. 79, Р. 7, о. 5, поз. 131 | BM77: 68 | BN77: 0 | BP77: 0 | BQ77: 40 | BR77: 0 | BS77: 1 | BT77: 1 | BU77: 1 | BV77: 1 | BW77: 1 | BX77: 1 | BZ77: 90 | CA77: 46 | CE77: 1566 | CF77: 0 | CG77: 0 | CM77: 0 | CO77: 0 | CP77: =(P77+Q77+S77) -> 1530.73 | CQ77: =ROUND((ROUND((AC77*AW77*1),2)*BC77),2) -> 1297.23 | CR77: =(ROUND((ROUND(((ET77)*AV77*1),2)*BB77),2)+ROUND((ROUND(((AE77-(EU77))*AV77*1),2)*BS77),2)) -> 0 | CS77: =(ROUND((ROUND(((EU77)*AV77*1),2)*BS77),2)+ROUND((ROUND(((AE77-(EU77))*AV77*1),2)*BS77),2)) -> 0 | CT77: =ROUND((ROUND((AF77*AV77*1),2)*BA77),2) -> 0 | CU77: =AG77 -> 0 | CV77: =(AH77*AV77) -> 0 | CW77: =AI77 -> 0 | CX77: =AJ77 -> 0 | CY77: =(ROUND((((S77+ROUND((ROUND(((EU77)*AV77*1),2)*BS77),2))*AT77)/100),2)+ROUND(((ROUND((ROUND(((AE77-(EU77))*AV77*1),2)*BS77),2)*AT77)/100),2)) -> 0 | CZ77: =(ROUND((((S77+ROUND((ROUND(((EU77)*AV77*1),2)*BS77),2))*AU77)/100),2)+ROUND(((ROUND((ROUND(((AE77-(EU77))*AV77*1),2)*BS77),2)*AU77)/100),2)) -> 0 | DN77: 0 | DO77: 0 | DP77: 1 | DQ77: 1 | DU77: 1010 | DV77: 100 шт. | DW77: 100 шт. | DX77: 100 | EE77: 60088532 | EF77: 40 | EG77: Монтаж оборудования | EH77: 0 | EJ77: 2 | EK77: 68 | EL77: ТСН-2001.4-10. Прокладка и монтаж сетей связи | EM77: ТСН-2001.4-10-1 | EQ77: 0 | ER77: 1297.23 | ES77: 1297.23 | ET77: 0 | EU77: 0 | EV77: 0 | EW77: 0 | EX77: 0 | FQ77: 0 | FR77: 0 | FS77: 0 | FX77: 90 | FY77: 46 | GD77: 1 | GF77: 1852901932 | GG77: 2 | GH77: 1 | GI77: -2 | GJ77: 0 | GK77: 0 | GL77: =ROUND(IF(AND(BH77=3,BI77=3,FS77<>0),P77,0),2) -> 0 | GM77: =ROUND(O77+X77+Y77,2)+GX77 -> 1530.73 | GN77: =IF(OR(BI77=0,BI77=1),GM77-GX77,0) -> 0 | GO77: =IF(BI77=2,GM77-GX77,0) -> 1530.73 | GP77: =IF(BI77=4,GM77-GX77,0) -> 0 | GR77: 0 | GS77: 3 | GT77: 0 | GV77: =ROUND((GT77),6) -> 0 | GW77: 1 | GX77: =ROUND(HC77*I77,2) -> 0 | HA77: 0 | HB77: 0 | HC77: =GV77*GW77 -> 0 | HS77: 0 | IK77: 0
A78: 18 | B78: 1 | C78: 22 | E78: 5,3 | F78: 1.7-5-131 | G78: Анкер забивной расклинивающийся из оцинкованной стали, с внутренней резьбой М12, длина 25 мм | H78: 100 шт. | I78: =I72*J78 -> 1.18 | J78: 2.36 | K78: 2.36 | O78: =ROUND(CP78,2) -> 7959.8 | P78: =ROUND((ROUND((AC78*AW78*I78),2)*BC78),2) -> 7959.8 | Q78: =(ROUND((ROUND(((ET78)*AV78*I78),2)*BB78),2)+ROUND((ROUND(((AE78-(EU78))*AV78*I78),2)*BS78),2)) -> 0 | R78: =(ROUND((ROUND(((EU78)*AV78*I78),2)*BS78),2)+ROUND((ROUND(((AE78-(EU78))*AV78*I78),2)*BS78),2)) -> 0 | S78: =ROUND((ROUND((AF78*AV78*I78),2)*BA78),2) -> 0 | T78: =ROUND(CU78*I78,2) -> 0 | U78: =CV78*I78 -> 0 | V78: =CW78*I78 -> 0 | W78: =ROUND(CX78*I78,2) -> 0 | X78: =(ROUND((((S78+ROUND((ROUND(((EU78)*AV78*I78),2)*BS78),2))*AT78)/100),2)+ROUND(((ROUND((ROUND(((AE78-(EU78))*AV78*I78),2)*BS78),2)*AT78)/100),2)) -> 0 | Y78: =(ROUND((((S78+ROUND((ROUND(((EU78)*AV78*I78),2)*BS78),2))*AU78)/100),2)+ROUND(((ROUND((ROUND(((AE78-(EU78))*AV78*I78),2)*BS78),2)*AU78)/100),2)) -> 0 | AA78: 60257733 | AB78: =ROUND((AC78+AD78+AF78),6) -> 1297.23 | AC78: =ROUND((ES78),6) -> 1297.23 | AD78: =ROUND((((ET78)-(EU78))+AE78),6) -> 0 | AE78: =ROUND((EU78),6) -> 0 | AF78: =ROUND((EV78),6) -> 0 | AG78: =ROUND((AP78),6) -> 0 | AH78: =(EW78) -> 0 | AI78: =(EX78) -> 0 | AJ78: =(AS78) -> 0 | AK78: 1297.23 | AL78: 1297.23 | AM78: 0 | AN78: 0 | AO78: 0 | AP78: 0 | AQ78: 0 | AR78: 0 | AS78: 0 | AT78: 90 | AU78: 46 | AV78: 1 | AW78: 1 | AZ78: 1 | BA78: 1 | BB78: 1 | BC78: 5.2 | BH78: 3 | BI78: 2 | BJ78: ТСН-2001.1 Доп. 79, Р. 7, о. 5, поз. 131 | BM78: 68 | BN78: 0 | BO78: 1.7-5-131 | BP78: 1 | BQ78: 40 | BR78: 0 | BS78: 1 | BT78: 1 | BU78: 1 | BV78: 1 | BW78: 1 | BX78: 1 | BZ78: 90 | CA78: 46 | CE78: 1566 | CF78: 0 | CG78: 0 | CM78: 0 | CO78: 0 | CP78: =(P78+Q78+S78) -> 7959.8 | CQ78: =ROUND((ROUND((AC78*AW78*1),2)*BC78),2) -> 6745.6 | CR78: =(ROUND((ROUND(((ET78)*AV78*1),2)*BB78),2)+ROUND((ROUND(((AE78-(EU78))*AV78*1),2)*BS78),2)) -> 0 | CS78: =(ROUND((ROUND(((EU78)*AV78*1),2)*BS78),2)+ROUND((ROUND(((AE78-(EU78))*AV78*1),2)*BS78),2)) -> 0 | CT78: =ROUND((ROUND((AF78*AV78*1),2)*BA78),2) -> 0 | CU78: =AG78 -> 0 | CV78: =(AH78*AV78) -> 0 | CW78: =AI78 -> 0 | CX78: =AJ78 -> 0 | CY78: =(ROUND((((S78+ROUND((ROUND(((EU78)*AV78*1),2)*BS78),2))*AT78)/100),2)+ROUND(((ROUND((ROUND(((AE78-(EU78))*AV78*1),2)*BS78),2)*AT78)/100),2)) -> 0 | CZ78: =(ROUND((((S78+ROUND((ROUND(((EU78)*AV78*1),2)*BS78),2))*AU78)/100),2)+ROUND(((ROUND((ROUND(((AE78-(EU78))*AV78*1),2)*BS78),2)*AU78)/100),2)) -> 0 | DN78: 0 | DO78: 0 | DP78: 1 | DQ78: 1 | DU78: 1010 | DV78: 100 шт. | DW78: 100 шт. | DX78: 100 | EE78: 60088532 | EF78: 40 | EG78: Монтаж оборудования | EH78: 0 | EJ78: 2 | EK78: 68 | EL78: ТСН-2001.4-10. Прокладка и монтаж сетей связи | EM78: ТСН-2001.4-10-1 | EQ78: 0 | ER78: 1297.23 | ES78: 1297.23 | ET78: 0 | EU78: 0 | EV78: 0 | EW78: 0 | EX78: 0 | FQ78: 0 | FR78: 0 | FS78: 0 | FX78: 90 | FY78: 46 | GD78: 1 | GF78: 1852901932 | GG78: 2 | GH78: 1 | GI78: 2 | GJ78: 0 | GK78: 0 | GL78: =ROUND(IF(AND(BH78=3,BI78=3,FS78<>0),P78,0),2) -> 0 | GM78: =ROUND(O78+X78+Y78,2)+GX78 -> 7959.8 | GN78: =IF(OR(BI78=0,BI78=1),GM78-GX78,0) -> 0 | GO78: =IF(BI78=2,GM78-GX78,0) -> 7959.8 | GP78: =IF(BI78=4,GM78-GX78,0) -> 0 | GR78: 0 | GS78: 3 | GT78: 0 | GV78: =ROUND((GT78),6) -> 0 | GW78: 1 | GX78: =ROUND(HC78*I78,2) -> 0 | HA78: 0 | HB78: 0 | HC78: =GV78*GW78 -> 0 | HS78: 0 | IK78: 0
A79: 17 | B79: 1 | C79: =ROW(SmtRes!A27) -> 27 | D79: =ROW(EtalonRes!A30) -> 30 | E79: 6 | F79: 4.8-328-1 | G79: Прокладка кабельного изделия по установленным конструкциям и лоткам, при массе 1 м кабельного изделия до 0,5 кг на высоте до 5 м | H79: 100 м | I79: =ROUND(50/100,9) -> 0.5 | J79: 0 | K79: =ROUND(50/100,9) -> 0.5 | O79: =ROUND(CP79,2) -> 102.21 | P79: =ROUND((ROUND((AC79*AW79*I79),2)*BC79),2) -> 62.92 | Q79: =(ROUND((ROUND((((ET79*1.1))*AV79*I79),2)*BB79),2)+ROUND((ROUND(((AE79-((EU79*1.1)))*AV79*I79),2)*BS79),2)) -> 1.51 | R79: =(ROUND((ROUND((((EU79*1.1))*AV79*I79),2)*BS79),2)+ROUND((ROUND(((AE79-((EU79*1.1)))*AV79*I79),2)*BS79),2)) -> 0.17 | S79: =ROUND((ROUND((AF79*AV79*I79),2)*BA79),2) -> 37.78 | T79: =ROUND(CU79*I79,2) -> 0 | U79: =CV79*I79 -> 3.0462465 | V79: =CW79*I79 -> 0 | W79: =ROUND(CX79*I79,2) -> 0 | X79: =(ROUND((((S79+ROUND((ROUND((((EU79*1.1))*AV79*I79),2)*BS79),2))*AT79)/100),2)+ROUND(((ROUND((ROUND(((AE79-((EU79*1.1)))*AV79*I79),2)*BS79),2)*AT79)/100),2)) -> 36.81 | Y79: =(ROUND((((S79+ROUND((ROUND((((EU79*1.1))*AV79*I79),2)*BS79),2))*AU79)/100),2)+ROUND(((ROUND((ROUND(((AE79-((EU79*1.1)))*AV79*I79),2)*BS79),2)*AU79)/100),2)) -> 19.35 | AA79: 60257736 | AB79: =ROUND((AC79+AD79+AF79),6) -> 200.872 | AC79: =ROUND((ES79),6) -> 125.83 | AD79: =ROUND(((((ET79*1.1))-((EU79*1.1)))+AE79),6) -> 2.882 | AE79: =ROUND(((EU79*1.1)),6) -> 0.33 | AF79: =ROUND(((EV79*1.1)),6) -> 72.16 | AG79: =ROUND((AP79),6) -> 0 | AH79: =((EW79*1.1)) -> 5.819 | AI79: =((EX79*1.1)) -> 0 | AJ79: =(AS79) -> 0 | AK79: 194.05 | AL79: 125.83 | AM79: 2.62 | AN79: 0.3 | AO79: 65.6 | AP79: 0 | AQ79: 5.29 | AR79: 0 | AS79: 0 | AT79: 97 | AU79: 51 | AV79: 1.047 | AW79: 1 | AZ79: 1 | BA79: 1 | BB79: 1 | BC79: 1 | BH79: 0 | BI79: 2 | BJ79: ТСН-2001.4 Доп. 75, Сб. 8, т. 328, поз. 1 | BM79: 67 | BN79: 0 | BO79: 4.8-328-1 | BP79: 1 | BQ79: 40 | BR79: 0 | BS79: 1 | BT79: 1 | BU79: 1 | BV79: 1 | BW79: 1 | BX79: 1 | BZ79: 97 | CA79: 51 | CE79: 1566 | CF79: 0 | CG79: 0 | CM79: 0 | CN79: Поправка: О.П. п.3.4.30.в Наименование: При применении территориальных сметных нормативов для города Москвы затраты, учитывающие напряженные и стесненные условия производства работ (стесненность, сложность складирования и транспортной логистики и т.п.), исчисляются с применением коэффициентов к затратам труда и заработной плате рабочих, машинистов, времени эксплуатации машин и механизмов, стоимости эксплуатации машин в размере: для объектов, расположенных за пределами Третьего транспортного кольца города Москвы, но в пределах Московской кольцевой автомобильной дороги | CO79: 0 | CP79: =(P79+Q79+S79) -> 102.21 | CQ79: =ROUND((ROUND((AC79*AW79*1),2)*BC79),2) -> 125.83 | CR79: =(ROUND((ROUND((((ET79*1.1))*AV79*1),2)*BB79),2)+ROUND((ROUND(((AE79-((EU79*1.1)))*AV79*1),2)*BS79),2)) -> 3.02 | CS79: =(ROUND((ROUND((((EU79*1.1))*AV79*1),2)*BS79),2)+ROUND((ROUND(((AE79-((EU79*1.1)))*AV79*1),2)*BS79),2)) -> 0.35 | CT79: =ROUND((ROUND((AF79*AV79*1),2)*BA79),2) -> 75.55 | CU79: =AG79 -> 0 | CV79: =(AH79*AV79) -> 6.092493 | CW79: =AI79 -> 0 | CX79: =AJ79 -> 0 | CY79: =(ROUND((((S79+ROUND((ROUND((((EU79*1.1))*AV79*1),2)*BS79),2))*AT79)/100),2)+ROUND(((ROUND((ROUND(((AE79-((EU79*1.1)))*AV79*1),2)*BS79),2)*AT79)/100),2)) -> 36.99 | CZ79: =(ROUND((((S79+ROUND((ROUND((((EU79*1.1))*AV79*1),2)*BS79),2))*AU79)/100),2)+ROUND(((ROUND((ROUND(((AE79-((EU79*1.1)))*AV79*1),2)*BS79),2)*AU79)/100),2)) -> 19.45 | DB79: 7 | DE79: *1,1 | DF79: *1,1 | DG79: *1,1 | DI79: *1,1 | DJ79: *1,1 | DN79: 0 | DO79: 0 | DP79: 1 | DQ79: 1 | DU79: 1003 | DV79: 100 м | DW79: 100 м | DX79: 100 | EE79: 60088531 | EF79: 40 | EG79: Монтаж оборудования | EH79: 0 | EJ79: 2 | EK79: 67 | EL79: ТСН-2001.4-8. Электротехнические установки | EM79: ТСН-2001.4-8-1 | EO79: Поправка: О.П. п.3.4.30.в | EQ79: 0 | ER79: 194.05 | ES79: 125.83 | ET79: 2.62 | EU79: 0.3 | EV79: 65.6 | EW79: 5.29 | EX79: 0 | EY79: 0 | FQ79: 0 | FR79: 0 | FS79: 0 | FX79: 97 | FY79: 51 | GD79: 1 | GF79: -261515912 | GG79: 2 | GH79: 1 | GI79: 2 | GJ79: 0 | GK79: 0 | GL79: =ROUND(IF(AND(BH79=3,BI79=3,FS79<>0),P79,0),2) -> 0 | GM79: =ROUND(O79+X79+Y79,2)+GX79 -> 158.37 | GN79: =IF(OR(BI79=0,BI79=1),GM79-GX79,0) -> 0 | GO79: =IF(BI79=2,GM79-GX79,0) -> 158.37 | GP79: =IF(BI79=4,GM79-GX79,0) -> 0 | GR79: 0 | GS79: 3 | GT79: 0 | GV79: =ROUND((GT79),6) -> 0 | GW79: 1 | GX79: =ROUND(HC79*I79,2) -> 0 | HA79: 0 | HB79: 0 | HC79: =GV79*GW79 -> 0 | HS79: 0 | IK79: 0
A80: 17 | B80: 1 | C80: =ROW(SmtRes!A32) -> 32 | D80: =ROW(EtalonRes!A36) -> 36 | E80: 6 | F80: 4.8-328-1 | G80: Прокладка кабельного изделия по установленным конструкциям и лоткам, при массе 1 м кабельного изделия до 0,5 кг на высоте до 5 м | H80: 100 м | I80: =ROUND(50/100,9) -> 0.5 | J80: 0 | K80: =ROUND(50/100,9) -> 0.5 | O80: =ROUND(CP80,2) -> 2348.68 | P80: =ROUND((ROUND((AC80*AW80*I80),2)*BC80),2) -> 249.16 | Q80: =(ROUND((ROUND((((ET80*1.1))*AV80*I80),2)*BB80),2)+ROUND((ROUND(((AE80-((EU80*1.1)))*AV80*I80),2)*BS80),2)) -> 22 | R80: =(ROUND((ROUND((((EU80*1.1))*AV80*I80),2)*BS80),2)+ROUND((ROUND(((AE80-((EU80*1.1)))*AV80*I80),2)*BS80),2)) -> 9.35 | S80: =ROUND((ROUND((AF80*AV80*I80),2)*BA80),2) -> 2077.52 | T80: =ROUND(CU80*I80,2) -> 0 | U80: =CV80*I80 -> 3.0462465 | V80: =CW80*I80 -> 0 | W80: =ROUND(CX80*I80,2) -> 0 | X80: =(ROUND((((S80+ROUND((ROUND((((EU80*1.1))*AV80*I80),2)*BS80),2))*AT80)/100),2)+ROUND(((ROUND((ROUND(((AE80-((EU80*1.1)))*AV80*I80),2)*BS80),2)*AT80)/100),2)) -> 2024.26 | Y80: =(ROUND((((S80+ROUND((ROUND((((EU80*1.1))*AV80*I80),2)*BS80),2))*AU80)/100),2)+ROUND(((ROUND((ROUND(((AE80-((EU80*1.1)))*AV80*I80),2)*BS80),2)*AU80)/100),2)) -> 1064.3 | AA80: 60257733 | AB80: =ROUND((AC80+AD80+AF80),6) -> 200.872 | AC80: =ROUND((ES80),6) -> 125.83 | AD80: =ROUND(((((ET80*1.1))-((EU80*1.1)))+AE80),6) -> 2.882 | AE80: =ROUND(((EU80*1.1)),6) -> 0.33 | AF80: =ROUND(((EV80*1.1)),6) -> 72.16 | AG80: =ROUND((AP80),6) -> 0 | AH80: =((EW80*1.1)) -> 5.819 | AI80: =((EX80*1.1)) -> 0 | AJ80: =(AS80) -> 0 | AK80: 194.05 | AL80: 125.83 | AM80: 2.62 | AN80: 0.3 | AO80: 65.6 | AP80: 0 | AQ80: 5.29 | AR80: 0 | AS80: 0 | AT80: 97 | AU80: 51 | AV80: 1.047 | AW80: 1 | AZ80: 1 | BA80: 54.99 | BB80: 14.57 | BC80: 3.96 | BH80: 0 | BI80: 2 | BJ80: ТСН-2001.4 Доп. 75, Сб. 8, т. 328, поз. 1 | BM80: 67 | BN80: 0 | BO80: 4.8-328-1 | BP80: 1 | BQ80: 40 | BR80: 0 | BS80: 54.99 | BT80: 1 | BU80: 1 | BV80: 1 | BW80: 1 | BX80: 1 | BZ80: 97 | CA80: 51 | CE80: 1566 | CF80: 0 | CG80: 0 | CM80: 0 | CN80: Поправка: О.П. п.3.4.30.в Наименование: При применении территориальных сметных нормативов для города Москвы затраты, учитывающие напряженные и стесненные условия производства работ (стесненность, сложность складирования и транспортной логистики и т.п.), исчисляются с применением коэффициентов к затратам труда и заработной плате рабочих, машинистов, времени эксплуатации машин и механизмов, стоимости эксплуатации машин в размере: для объектов, расположенных за пределами Третьего транспортного кольца города Москвы, но в пределах Московской кольцевой автомобильной дороги | CO80: 0 | CP80: =(P80+Q80+S80) -> 2348.68 | CQ80: =ROUND((ROUND((AC80*AW80*1),2)*BC80),2) -> 498.29 | CR80: =(ROUND((ROUND((((ET80*1.1))*AV80*1),2)*BB80),2)+ROUND((ROUND(((AE80-((EU80*1.1)))*AV80*1),2)*BS80),2)) -> 44 | CS80: =(ROUND((ROUND((((EU80*1.1))*AV80*1),2)*BS80),2)+ROUND((ROUND(((AE80-((EU80*1.1)))*AV80*1),2)*BS80),2)) -> 19.25 | CT80: =ROUND((ROUND((AF80*AV80*1),2)*BA80),2) -> 4154.49 | CU80: =AG80 -> 0 | CV80: =(AH80*AV80) -> 6.092493 | CW80: =AI80 -> 0 | CX80: =AJ80 -> 0 | CY80: =(ROUND((((S80+ROUND((ROUND((((EU80*1.1))*AV80*1),2)*BS80),2))*AT80)/100),2)+ROUND(((ROUND((ROUND(((AE80-((EU80*1.1)))*AV80*1),2)*BS80),2)*AT80)/100),2)) -> 2033.87 | CZ80: =(ROUND((((S80+ROUND((ROUND((((EU80*1.1))*AV80*1),2)*BS80),2))*AU80)/100),2)+ROUND(((ROUND((ROUND(((AE80-((EU80*1.1)))*AV80*1),2)*BS80),2)*AU80)/100),2)) -> 1069.35 | DB80: 8 | DE80: *1,1 | DF80: *1,1 | DG80: *1,1 | DI80: *1,1 | DJ80: *1,1 | DN80: 0 | DO80: 0 | DP80: 1 | DQ80: 1 | DU80: 1003 | DV80: 100 м | DW80: 100 м | DX80: 100 | EE80: 60088531 | EF80: 40 | EG80: Монтаж оборудования | EH80: 0 | EJ80: 2 | EK80: 67 | EL80: ТСН-2001.4-8. Электротехнические установки | EM80: ТСН-2001.4-8-1 | EO80: Поправка: О.П. п.3.4.30.в | EQ80: 0 | ER80: 194.05 | ES80: 125.83 | ET80: 2.62 | EU80: 0.3 | EV80: 65.6 | EW80: 5.29 | EX80: 0 | EY80: 0 | FQ80: 0 | FR80: 0 | FS80: 0 | FX80: 97 | FY80: 51 | GD80: 1 | GF80: -261515912 | GG80: 2 | GH80: 1 | GI80: 2 | GJ80: 0 | GK80: 0 | GL80: =ROUND(IF(AND(BH80=3,BI80=3,FS80<>0),P80,0),2) -> 0 | GM80: =ROUND(O80+X80+Y80,2)+GX80 -> 5437.24 | GN80: =IF(OR(BI80=0,BI80=1),GM80-GX80,0) -> 0 | GO80: =IF(BI80=2,GM80-GX80,0) -> 5437.24 | GP80: =IF(BI80=4,GM80-GX80,0) -> 0 | GR80: 0 | GS80: 3 | GT80: 0 | GV80: =ROUND((GT80),6) -> 0 | GW80: 1 | GX80: =ROUND(HC80*I80,2) -> 0 | HA80: 0 | HB80: 0 | HC80: =GV80*GW80 -> 0 | HS80: 0 | IK80: 0
A81: 17 | B81: 1 | E81: 7 | F81: КА-2 | G81: Кабель КПСВВнг(А)-LSLTx 1x2x1,0 | H81: км | I81: =ROUND(0.1*1.02,9) -> 0.102 | J81: 0 | K81: =ROUND(0.1*1.02,9) -> 0.102 | O81: =ROUND(CP81,2) -> 316.7 | P81: =ROUND((ROUND((AC81*AW81*I81),2)*BC81),2) -> 316.7 | Q81: =(ROUND((ROUND(((ET81)*AV81*I81),2)*BB81),2)+ROUND((ROUND(((AE81-(EU81))*AV81*I81),2)*BS81),2)) -> 0 | R81: =(ROUND((ROUND(((EU81)*AV81*I81),2)*BS81),2)+ROUND((ROUND(((AE81-(EU81))*AV81*I81),2)*BS81),2)) -> 0 | S81: =ROUND((ROUND((AF81*AV81*I81),2)*BA81),2) -> 0 | T81: =ROUND(CU81*I81,2) -> 0 | U81: =CV81*I81 -> 0 | V81: =CW81*I81 -> 0 | W81: =ROUND(CX81*I81,2) -> 0 | X81: =(ROUND((((S81+ROUND((ROUND(((EU81)*AV81*I81),2)*BS81),2))*AT81)/100),2)+ROUND(((ROUND((ROUND(((AE81-(EU81))*AV81*I81),2)*BS81),2)*AT81)/100),2)) -> 0 | Y81: =(ROUND((((S81+ROUND((ROUND(((EU81)*AV81*I81),2)*BS81),2))*AU81)/100),2)+ROUND(((ROUND((ROUND(((AE81-(EU81))*AV81*I81),2)*BS81),2)*AU81)/100),2)) -> 0 | AA81: 60257736 | AB81: =ROUND((AC81+AD81+AF81),6) -> 3104.91 | AC81: =ROUND((ES81),6) -> 3104.91 | AD81: =ROUND((((ET81)-(EU81))+AE81),6) -> 0 | AE81: =ROUND((EU81),6) -> 0 | AF81: =ROUND((EV81),6) -> 0 | AG81: =ROUND((AP81),6) -> 0 | AH81: =(EW81) -> 0 | AI81: =(EX81) -> 0 | AJ81: =(AS81) -> 0 | AK81: 3104.91 | AL81: 3104.91 | AM81: 0 | AN81: 0 | AO81: 0 | AP81: 0 | AQ81: 0 | AR81: 0 | AS81: 0 | AT81: 0 | AU81: 0 | AV81: 1 | AW81: 1 | AZ81: 1 | BA81: 1 | BB81: 1 | BC81: 1 | BH81: 3 | BI81: 2 | BM81: 400002 | BN81: 0 | BP81: 0 | BQ81: 202 | BR81: 0 | BS81: 1 | BT81: 1 | BU81: 1 | BV81: 1 | BW81: 1 | BX81: 1 | BZ81: 0 | CA81: 0 | CE81: 1566 | CF81: 0 | CG81: 0 | CM81: 0 | CO81: 0 | CP81: =(P81+Q81+S81) -> 316.7 | CQ81: =ROUND((ROUND((AC81*AW81*1),2)*BC81),2) -> 3104.91 | CR81: =(ROUND((ROUND(((ET81)*AV81*1),2)*BB81),2)+ROUND((ROUND(((AE81-(EU81))*AV81*1),2)*BS81),2)) -> 0 | CS81: =(ROUND((ROUND(((EU81)*AV81*1),2)*BS81),2)+ROUND((ROUND(((AE81-(EU81))*AV81*1),2)*BS81),2)) -> 0 | CT81: =ROUND((ROUND((AF81*AV81*1),2)*BA81),2) -> 0 | CU81: =AG81 -> 0 | CV81: =(AH81*AV81) -> 0 | CW81: =AI81 -> 0 | CX81: =AJ81 -> 0 | CY81: =(ROUND((((S81+ROUND((ROUND(((EU81)*AV81*1),2)*BS81),2))*AT81)/100),2)+ROUND(((ROUND((ROUND(((AE81-(EU81))*AV81*1),2)*BS81),2)*AT81)/100),2)) -> 0 | CZ81: =(ROUND((((S81+ROUND((ROUND(((EU81)*AV81*1),2)*BS81),2))*AU81)/100),2)+ROUND(((ROUND((ROUND(((AE81-(EU81))*AV81*1),2)*BS81),2)*AU81)/100),2)) -> 0 | DN81: 0 | DO81: 0 | DP81: 1 | DQ81: 1 | DU81: 1003 | DV81: км | DW81: км | DX81: 1000 | EE81: 60088644 | EF81: 202 | EG81: Материалы | EH81: 0 | EJ81: 1 | EK81: 400002 | EL81: Материалы, изделия и конструкции | EM81: Материалы | EQ81: 0 | ER81: 0 | ES81: 3104.91 | ET81: 0 | EU81: 0 | EV81: 0 | EW81: 0 | EX81: 0 | EY81: 0 | FQ81: 0 | FR81: 0 | FS81: 0 | FX81: 0 | FY81: 0 | GA81: [36 090 / 1,2 / 9,88] + 2% Заг.скл | GD81: 1 | GF81: 411873728 | GG81: 2 | GH81: 4 | GI81: -2 | GJ81: 0 | GK81: 0 | GL81: =ROUND(IF(AND(BH81=3,BI81=3,FS81<>0),P81,0),2) -> 0 | GM81: =ROUND(O81+X81+Y81,2)+GX81 -> 316.7 | GN81: =IF(OR(BI81=0,BI81=1),GM81-GX81,0) -> 0 | GO81: =IF(BI81=2,GM81-GX81,0) -> 316.7 | GP81: =IF(BI81=4,GM81-GX81,0) -> 0 | GR81: 0 | GS81: 2 | GT81: 0 | GV81: =ROUND((GT81),6) -> 0 | GW81: 1 | GX81: =ROUND(HC81*I81,2) -> 0 | HA81: 0 | HB81: 0 | HC81: =GV81*GW81 -> 0 | HE81: 0 | HF81: 2 | HS81: 0 | IK81: 0
A82: 17 | B82: 1 | E82: 7 | F82: КА-2 | G82: Кабель КПСВВнг(А)-LSLTx 1x2x1,0 | H82: км | I82: =ROUND(0.1*1.02,9) -> 0.102 | J82: 0 | K82: =ROUND(0.1*1.02,9) -> 0.102 | O82: =ROUND(CP82,2) -> 3129 | P82: =ROUND((ROUND((AC82*AW82*I82),2)*BC82),2) -> 3129 | Q82: =(ROUND((ROUND(((ET82)*AV82*I82),2)*BB82),2)+ROUND((ROUND(((AE82-(EU82))*AV82*I82),2)*BS82),2)) -> 0 | R82: =(ROUND((ROUND(((EU82)*AV82*I82),2)*BS82),2)+ROUND((ROUND(((AE82-(EU82))*AV82*I82),2)*BS82),2)) -> 0 | S82: =ROUND((ROUND((AF82*AV82*I82),2)*BA82),2) -> 0 | T82: =ROUND(CU82*I82,2) -> 0 | U82: =CV82*I82 -> 0 | V82: =CW82*I82 -> 0 | W82: =ROUND(CX82*I82,2) -> 0 | X82: =(ROUND((((S82+ROUND((ROUND(((EU82)*AV82*I82),2)*BS82),2))*AT82)/100),2)+ROUND(((ROUND((ROUND(((AE82-(EU82))*AV82*I82),2)*BS82),2)*AT82)/100),2)) -> 0 | Y82: =(ROUND((((S82+ROUND((ROUND(((EU82)*AV82*I82),2)*BS82),2))*AU82)/100),2)+ROUND(((ROUND((ROUND(((AE82-(EU82))*AV82*I82),2)*BS82),2)*AU82)/100),2)) -> 0 | AA82: 60257733 | AB82: =ROUND((AC82+AD82+AF82),6) -> 3104.91 | AC82: =ROUND((ES82),6) -> 3104.91 | AD82: =ROUND((((ET82)-(EU82))+AE82),6) -> 0 | AE82: =ROUND((EU82),6) -> 0 | AF82: =ROUND((EV82),6) -> 0 | AG82: =ROUND((AP82),6) -> 0 | AH82: =(EW82) -> 0 | AI82: =(EX82) -> 0 | AJ82: =(AS82) -> 0 | AK82: 3104.91 | AL82: 3104.91 | AM82: 0 | AN82: 0 | AO82: 0 | AP82: 0 | AQ82: 0 | AR82: 0 | AS82: 0 | AT82: 0 | AU82: 0 | AV82: 1 | AW82: 1 | AZ82: 1 | BA82: 1 | BB82: 1 | BC82: 9.88 | BH82: 3 | BI82: 2 | BM82: 400002 | BN82: 0 | BP82: 0 | BQ82: 202 | BR82: 0 | BS82: 1 | BT82: 1 | BU82: 1 | BV82: 1 | BW82: 1 | BX82: 1 | BZ82: 0 | CA82: 0 | CE82: 1566 | CF82: 0 | CG82: 0 | CM82: 0 | CO82: 0 | CP82: =(P82+Q82+S82) -> 3129 | CQ82: =ROUND((ROUND((AC82*AW82*1),2)*BC82),2) -> 30676.51 | CR82: =(ROUND((ROUND(((ET82)*AV82*1),2)*BB82),2)+ROUND((ROUND(((AE82-(EU82))*AV82*1),2)*BS82),2)) -> 0 | CS82: =(ROUND((ROUND(((EU82)*AV82*1),2)*BS82),2)+ROUND((ROUND(((AE82-(EU82))*AV82*1),2)*BS82),2)) -> 0 | CT82: =ROUND((ROUND((AF82*AV82*1),2)*BA82),2) -> 0 | CU82: =AG82 -> 0 | CV82: =(AH82*AV82) -> 0 | CW82: =AI82 -> 0 | CX82: =AJ82 -> 0 | CY82: =(ROUND((((S82+ROUND((ROUND(((EU82)*AV82*1),2)*BS82),2))*AT82)/100),2)+ROUND(((ROUND((ROUND(((AE82-(EU82))*AV82*1),2)*BS82),2)*AT82)/100),2)) -> 0 | CZ82: =(ROUND((((S82+ROUND((ROUND(((EU82)*AV82*1),2)*BS82),2))*AU82)/100),2)+ROUND(((ROUND((ROUND(((AE82-(EU82))*AV82*1),2)*BS82),2)*AU82)/100),2)) -> 0 | DN82: 0 | DO82: 0 | DP82: 1 | DQ82: 1 | DU82: 1003 | DV82: км | DW82: км | DX82: 1000 | EE82: 60088644 | EF82: 202 | EG82: Материалы | EH82: 0 | EJ82: 1 | EK82: 400002 | EL82: Материалы, изделия и конструкции | EM82: Материалы | EQ82: 0 | ER82: 0 | ES82: 3104.91 | ET82: 0 | EU82: 0 | EV82: 0 | EW82: 0 | EX82: 0 | EY82: 0 | EZ82: 5 | FC82: 1 | FD82: 18 | FF82: 36090 | FQ82: 0 | FR82: 0 | FS82: 0 | FX82: 0 | FY82: 0 | GA82: [36 090 / 1,2 / 9,88] + 2% Заг.скл | GD82: 1 | GF82: 411873728 | GG82: 2 | GH82: 3 | GI82: 5 | GJ82: 0 | GK82: 0 | GL82: =ROUND(IF(AND(BH82=3,BI82=3,FS82<>0),P82,0),2) -> 0 | GM82: =ROUND(O82+X82+Y82,2)+GX82 -> 3129 | GN82: =IF(OR(BI82=0,BI82=1),GM82-GX82,0) -> 0 | GO82: =IF(BI82=2,GM82-GX82,0) -> 3129 | GP82: =IF(BI82=4,GM82-GX82,0) -> 0 | GR82: 1 | GS82: 1 | GT82: 0 | GV82: =ROUND((GT82),6) -> 0 | GW82: 1 | GX82: =ROUND(HC82*I82,2) -> 0 | HA82: 0 | HB82: 0 | HC82: =GV82*GW82 -> 0 | HE82: 0 | HF82: 2 | HS82: 0 | IK82: 0
A84: 51 | B84: =B67 -> 1 | C84: =A67 -> 4 | D84: =ROW(A67) -> 67 | F84: =IF(F67<>"",F67,"") | G84: =IF(G67<>"",G67,"") -> Кабельные изделия | H84: 0 | O84: =ROUND(AB84,2) -> 2322.76 | P84: =ROUND(AC84,2) -> 2111.72 | Q84: =ROUND(AD84,2) -> 3.84 | R84: =ROUND(AE84,2) -> 0.17 | S84: =ROUND(AF84,2) -> 207.2 | T84: =ROUND(AG84,2) -> 0 | U84: =AH84 -> 17.304293 | V84: =AI84 -> 0 | W84: =ROUND(AJ84,2) -> 0 | X84: =ROUND(AK84,2) -> 189.29 | Y84: =ROUND(AL84,2) -> 97.28 | AB84: =ROUND(SUMIF(AA71:AA82,"=60257736",O71:O82),2) -> 2322.76 | AC84: =ROUND(SUMIF(AA71:AA82,"=60257736",P71:P82),2) -> 2111.72 | AD84: =ROUND(SUMIF(AA71:AA82,"=60257736",Q71:Q82),2) -> 3.84 | AE84: =ROUND(SUMIF(AA71:AA82,"=60257736",R71:R82),2) -> 0.17 | AF84: =ROUND(SUMIF(AA71:AA82,"=60257736",S71:S82),2) -> 207.2 | AG84: =ROUND(SUMIF(AA71:AA82,"=60257736",T71:T82),2) -> 0 | AH84: =SUMIF(AA71:AA82,"=60257736",U71:U82) -> 17.304293 | AI84: =SUMIF(AA71:AA82,"=60257736",V71:V82) -> 0 | AJ84: =ROUND(SUMIF(AA71:AA82,"=60257736",W71:W82),2) -> 0 | AK84: =ROUND(SUMIF(AA71:AA82,"=60257736",X71:X82),2) -> 189.29 | AL84: =ROUND(SUMIF(AA71:AA82,"=60257736",Y71:Y82),2) -> 97.28 | AO84: =ROUND(BX84,2) -> 0 | AP84: =ROUND(BY84,2) -> 0 | AQ84: =ROUND(BZ84,2) -> 0 | AR84: =ROUND(CA84,2) -> 2609.33 | AS84: =ROUND(CB84,2) -> 0 | AT84: =ROUND(CC84,2) -> 2609.33 | AU84: =ROUND(CD84,2) -> 0 | AV84: =ROUND(CE84,2) -> 2111.72 | ... BD84: =ROUND(CM84,2) -> 0 | BX84: =ROUND(SUMIF(AA71:AA82,"=60257736",FQ71:FQ82),2) -> 0 | BY84: =ROUND(SUMIF(AA71:AA82,"=60257736",FR71:FR82),2) -> 0 | BZ84: =ROUND(SUMIF(AA71:AA82,"=60257736",GL71:GL82),2) -> 0 | CA84: =ROUND(SUMIF(AA71:AA82,"=60257736",GM71:GM82),2) -> 2609.33 | CB84: =ROUND(SUMIF(AA71:AA82,"=60257736",GN71:GN82),2) -> 0 | CC84: =ROUND(SUMIF(AA71:AA82,"=60257736",GO71:GO82),2) -> 2609.33 | CD84: =ROUND(SUMIF(AA71:AA82,"=60257736",GP71:GP82),2) -> 0 | CE84: =AC84-BX84 -> 2111.72 | CF84: =AC84-BY84 -> 2111.72 | CG84: =BX84-BZ84 -> 0 | CH84: =AC84-BX84-BY84+BZ84 -> 2111.72 | CI84: =BY84-BZ84 -> 0 | CJ84: =ROUND(SUMIF(AA71:AA82,"=60257736",GX71:GX82),2) -> 0 | CK84: =ROUND(SUMIF(AA71:AA82,"=60257736",GY71:GY82),2) -> 0 | CL84: =ROUND(SUMIF(AA71:AA82,"=60257736",GZ71:GZ82),2) -> 0 | CM84: =ROUND(SUMIF(AA71:AA82,"=60257736",HD71:HD82),2) -> 0 | DG84: =ROUND(DT84,2) -> 23420.34 | DH84: =ROUND(DU84,2) -> 11984.09 | DI84: =ROUND(DV84,2) -> 42.32 | DJ84: =ROUND(DW84,2) -> 9.35 | DK84: =ROUND(DX84,2) -> 11393.93 | DL84: =ROUND(DY84,2) -> 0 | DM84: =DZ84 -> 17.304293 | DN84: =EA84 -> 0 | DO84: =ROUND(EB84,2) -> 0 | DP84: =ROUND(EC84,2) -> 10409.03 | DQ84: =ROUND(ED84,2) -> 5349.85 | DT84: =ROUND(SUMIF(AA71:AA82,"=60257733",O71:O82),2) -> 23420.34 | DU84: =ROUND(SUMIF(AA71:AA82,"=60257733",P71:P82),2) -> 11984.09 | DV84: =ROUND(SUMIF(AA71:AA82,"=60257733",Q71:Q82),2) -> 42.32 | DW84: =ROUND(SUMIF(AA71:AA82,"=60257733",R71:R82),2) -> 9.35 | DX84: =ROUND(SUMIF(AA71:AA82,"=60257733",S71:S82),2) -> 11393.93 | DY84: =ROUND(SUMIF(AA71:AA82,"=60257733",T71:T82),2) -> 0 | DZ84: =SUMIF(AA71:AA82,"=60257733",U71:U82) -> 17.304293 | EA84: =SUMIF(AA71:AA82,"=60257733",V71:V82) -> 0 | EB84: =ROUND(SUMIF(AA71:AA82,"=60257733",W71:W82),2) -> 0 | EC84: =ROUND(SUMIF(AA71:AA82,"=60257733",X71:X82),2) -> 10409.03 | ED84: =ROUND(SUMIF(AA71:AA82,"=60257733",Y71:Y82),2) -> 5349.85 | EG84: =ROUND(FP84,2) -> 0 | EH84: =ROUND(FQ84,2) -> 0 | EI84: =ROUND(FR84,2) -> 0 | EJ84: =ROUND(FS84,2) -> 39179.22 | EK84: =ROUND(FT84,2) -> 0 | EL84: =ROUND(FU84,2) -> 39179.22 | EM84: =ROUND(FV84,2) -> 0 | EN84: =ROUND(FW84,2) -> 11984.09 | ... EV84: =ROUND(GE84,2) -> 0 | FP84: =ROUND(SUMIF(AA71:AA82,"=60257733",FQ71:FQ82),2) -> 0 | FQ84: =ROUND(SUMIF(AA71:AA82,"=60257733",FR71:FR82),2) -> 0 | FR84: =ROUND(SUMIF(AA71:AA82,"=60257733",GL71:GL82),2) -> 0 | FS84: =ROUND(SUMIF(AA71:AA82,"=60257733",GM71:GM82),2) -> 39179.22 | FT84: =ROUND(SUMIF(AA71:AA82,"=60257733",GN71:GN82),2) -> 0 | FU84: =ROUND(SUMIF(AA71:AA82,"=60257733",GO71:GO82),2) -> 39179.22 | FV84: =ROUND(SUMIF(AA71:AA82,"=60257733",GP71:GP82),2) -> 0 | FW84: =DU84-FP84 -> 11984.09 | FX84: =DU84-FQ84 -> 11984.09 | FY84: =FP84-FR84 -> 0 | FZ84: =DU84-FP84-FQ84+FR84 -> 11984.09 | GA84: =FQ84-FR84 -> 0 | GB84: =ROUND(SUMIF(AA71:AA82,"=60257733",GX71:GX82),2) -> 0 | GC84: =ROUND(SUMIF(AA71:AA82,"=60257733",GY71:GY82),2) -> 0 | GD84: =ROUND(SUMIF(AA71:AA82,"=60257733",GZ71:GZ82),2) -> 0 | GE84: =ROUND(SUMIF(AA71:AA82,"=60257733",HD71:HD82),2) -> 0 | GX84: 0
A86: 50 | B86: 0 | C86: 0 | D86: 1 | E86: 201 | F86: =ROUND(Source!O84,O86) -> 2322.76 | G86: ПЗ | H86: Прямые затраты | K86: 201 | L86: 1 | M86: 3 | O86: 2 | P86: =ROUND(Source!DG84,O86) -> 23420.34 | W86: 2322.76 | X86: 1 | Y86: 2322.76 | Z86: 23420.34 | AA86: 1 | AB86: 23420.34
A87: 50 | B87: 0 | C87: 0 | D87: 1 | E87: 202 | F87: =ROUND(Source!P84,O87) -> 2111.72 | G87: СтМатОб | H87: Стоимость материальных ресурсов (всего) | K87: 202 | L87: 2 | M87: 3 | O87: 2 | P87: =ROUND(Source!DH84,O87) -> 11984.09 | W87: 2111.72 | X87: 1 | Y87: 2111.72 | Z87: 11984.09 | AA87: 1 | AB87: 11984.09
A88: 50 | B88: 0 | C88: 0 | D88: 1 | E88: 222 | F88: =ROUND(Source!AO84,O88) -> 0 | G88: СтМатОбЗак | H88: Стоимость материалов и оборудования заказчика | K88: 222 | L88: 3 | M88: 3 | O88: 2 | P88: =ROUND(Source!EG84,O88) -> 0 | W88: 0 | X88: 1 | Y88: 0 | Z88: 0 | AA88: 1 | AB88: 0
A89: 50 | B89: 0 | C89: 0 | D89: 1 | E89: 225 | F89: =ROUND(Source!AV84,O89) -> 2111.72 | G89: СтМатОбПод | H89: Стоимость материалов и оборудования подрядчика | K89: 225 | L89: 4 | M89: 3 | O89: 2 | P89: =ROUND(Source!EN84,O89) -> 11984.09 | W89: 2111.72 | X89: 1 | Y89: 2111.72 | Z89: 11984.09 | AA89: 1 | AB89: 11984.09
A90: 50 | B90: 0 | C90: 0 | D90: 1 | E90: 226 | F90: =ROUND(Source!AW84,O90) -> 2111.72 | G90: СтМат | H90: Стоимость материалов (всего) | K90: 226 | L90: 5 | M90: 3 | O90: 2 | P90: =ROUND(Source!EO84,O90) -> 11984.09 | W90: 2111.72 | X90: 1 | Y90: 2111.72 | Z90: 11984.09 | AA90: 1 | AB90: 11984.09
A91: 50 | B91: 0 | C91: 0 | D91: 1 | E91: 227 | F91: =ROUND(Source!AX84,O91) -> 0 | G91: СтМатЗак | H91: Стоимость материалов заказчика | K91: 227 | L91: 6 | M91: 3 | O91: 2 | P91: =ROUND(Source!EP84,O91) -> 0 | W91: 0 | X91: 1 | Y91: 0 | Z91: 0 | AA91: 1 | AB91: 0
A92: 50 | B92: 0 | C92: 0 | D92: 1 | E92: 228 | F92: =ROUND(Source!AY84,O92) -> 2111.72 | G92: СтМатПод | H92: Стоимость материалов подрядчика | K92: 228 | L92: 7 | M92: 3 | O92: 2 | P92: =ROUND(Source!EQ84,O92) -> 11984.09 | W92: 2111.72 | X92: 1 | Y92: 2111.72 | Z92: 11984.09 | AA92: 1 | AB92: 11984.09
A93: 50 | B93: 0 | C93: 0 | D93: 1 | E93: 216 | F93: =ROUND(Source!AP84,O93) -> 0 | G93: Оборуд | H93: Стоимость оборудования (всего) | K93: 216 | L93: 8 | M93: 3 | O93: 2 | P93: =ROUND(Source!EH84,O93) -> 0 | W93: 0 | X93: 1 | Y93: 0 | Z93: 0 | AA93: 1 | AB93: 0
A94: 50 | B94: 0 | C94: 0 | D94: 1 | E94: 223 | F94: =ROUND(Source!AQ84,O94) -> 0 | G94: ОборудЗак | H94: Стоимость оборудования заказчика | K94: 223 | L94: 9 | M94: 3 | O94: 2 | P94: =ROUND(Source!EI84,O94) -> 0 | W94: 0 | X94: 1 | Y94: 0 | Z94: 0 | AA94: 1 | AB94: 0
A95: 50 | B95: 0 | C95: 0 | D95: 1 | E95: 229 | F95: =ROUND(Source!AZ84,O95) -> 0 | G95: ОборудПод | H95: Стоимость оборудования подрядчика | K95: 229 | L95: 10 | M95: 3 | O95: 2 | P95: =ROUND(Source!ER84,O95) -> 0 | W95: 0 | X95: 1 | Y95: 0 | Z95: 0 | AA95: 1 | AB95: 0
A96: 50 | B96: 0 | C96: 0 | D96: 1 | E96: 203 | F96: =ROUND(Source!Q84,O96) -> 3.84 | G96: ЭММ | H96: Эксплуатация машин | K96: 203 | L96: 11 | M96: 3 | O96: 2 | P96: =ROUND(Source!DI84,O96) -> 42.32 | W96: 3.84 | X96: 1 | Y96: 3.84 | Z96: 42.32 | AA96: 1 | AB96: 42.32
A97: 50 | B97: 0 | C97: 0 | D97: 1 | E97: 231 | F97: =ROUND(Source!BB84,O97) -> 0 | G97: ЭММсНРиСП | H97: Эксплуатация машин по ТСН-2001.16 | K97: 231 | L97: 12 | M97: 3 | O97: 2 | P97: =ROUND(Source!ET84,O97) -> 0 | W97: 0 | X97: 1 | Y97: 0 | Z97: 0 | AA97: 1 | AB97: 0
A98: 50 | B98: 0 | C98: 0 | D98: 1 | E98: 204 | F98: =ROUND(Source!R84,O98) -> 0.17 | G98: ЗПМ | H98: ЗП машинистов | K98: 204 | L98: 13 | M98: 3 | O98: 2 | P98: =ROUND(Source!DJ84,O98) -> 9.35 | W98: 0.17 | X98: 1 | Y98: 0.17 | Z98: 9.35 | AA98: 1 | AB98: 9.35
A99: 50 | B99: 0 | C99: 0 | D99: 1 | E99: 205 | F99: =ROUND(Source!S84,O99) -> 207.2 | G99: ОЗП | H99: Основная ЗП рабочих | K99: 205 | L99: 14 | M99: 3 | O99: 2 | P99: =ROUND(Source!DK84,O99) -> 11393.93 | W99: 207.2 | X99: 1 | Y99: 207.2 | Z99: 11393.93 | AA99: 1 | AB99: 11393.93
A100: 50 | B100: 0 | C100: 0 | D100: 1 | E100: 232 | F100: =ROUND(Source!BC84,O100) -> 0 | G100: ОЗПсНРиСП | H100: Основная ЗП рабочих по ТСН-2001.16 | K100: 232 | L100: 15 | M100: 3 | O100: 2 | P100: =ROUND(Source!EU84,O100) -> 0 | W100: 0 | X100: 1 | Y100: 0 | Z100: 0 | AA100: 1 | AB100: 0
A101: 50 | B101: 0 | C101: 0 | D101: 1 | E101: 214 | F101: =ROUND(Source!AS84,O101) -> 0 | G101: Строит | H101: Строительные работы с НР и СП | K101: 214 | L101: 16 | M101: 3 | O101: 2 | P101: =ROUND(Source!EK84,O101) -> 0 | W101: 0 | X101: 1 | Y101: 0 | Z101: 0 | AA101: 1 | AB101: 0
A102: 50 | B102: 0 | C102: 0 | D102: 1 | E102: 215 | F102: =ROUND(Source!AT84,O102) -> 2609.33 | G102: Монтаж | H102: Монтажные работы с НР и СП | K102: 215 | L102: 17 | M102: 3 | O102: 2 | P102: =ROUND(Source!EL84,O102) -> 39179.22 | W102: 2609.33 | X102: 1 | Y102: 2609.33 | Z102: 39179.22 | AA102: 1 | AB102: 39179.22
A103: 50 | B103: 0 | C103: 0 | D103: 1 | E103: 217 | F103: =ROUND(Source!AU84,O103) -> 0 | G103: Прочие | H103: Прочие работы с НР и СП | K103: 217 | L103: 18 | M103: 3 | O103: 2 | P103: =ROUND(Source!EM84,O103) -> 0 | W103: 0 | X103: 1 | Y103: 0 | Z103: 0 | AA103: 1 | AB103: 0
A104: 50 | B104: 0 | C104: 0 | D104: 1 | E104: 230 | F104: =ROUND(Source!BA84,O104) -> 0 | G104: ПрочиеЗатр | H104: Прочие затраты по ТСН-2001.16 | K104: 230 | L104: 19 | M104: 3 | O104: 2 | P104: =ROUND(Source!ES84,O104) -> 0 | W104: 0 | X104: 1 | Y104: 0 | Z104: 0 | AA104: 1 | AB104: 0
A105: 50 | B105: 0 | C105: 0 | D105: 1 | E105: 206 | F105: =ROUND(Source!T84,O105) -> 0 | G105: ВозврМат | H105: Возврат материалов | K105: 206 | L105: 20 | M105: 3 | O105: 2 | P105: =ROUND(Source!DL84,O105) -> 0 | W105: 0 | X105: 1 | Y105: 0 | Z105: 0 | AA105: 1 | AB105: 0
A106: 50 | B106: 0 | C106: 0 | D106: 1 | E106: 207 | F106: =Source!U84 -> 17.304293 | G106: ТрудСтр | H106: Трудозатраты строителей | K106: 207 | L106: 21 | M106: 3 | O106: -1 | P106: =Source!DM84 -> 17.304293 | W106: 17.304292 | X106: 1 | Y106: 17.304292 | Z106: 17.304292 | AA106: 1 | AB106: 17.304292
A107: 50 | B107: 0 | C107: 0 | D107: 1 | E107: 208 | F107: =Source!V84 -> 0 | G107: ТрудМаш | H107: Трудозатраты машинистов | K107: 208 | L107: 22 | M107: 3 | O107: -1 | P107: =Source!DN84 -> 0 | W107: 0 | X107: 1 | Y107: 0 | Z107: 0 | AA107: 1 | AB107: 0
A108: 50 | B108: 0 | C108: 0 | D108: 1 | E108: 209 | F108: =ROUND(Source!W84,O108) -> 0 | G108: ТранспМат | H108: Транспорт материалов | K108: 209 | L108: 23 | M108: 3 | O108: 2 | P108: =ROUND(Source!DO84,O108) -> 0 | W108: 0 | X108: 1 | Y108: 0 | Z108: 0 | AA108: 1 | AB108: 0
A109: 50 | B109: 0 | C109: 0 | D109: 1 | E109: 233 | F109: =ROUND(Source!BD84,O109) -> 0 | G109: Перевозка | H109: Перевозка грузов | K109: 233 | L109: 24 | M109: 3 | O109: 2 | P109: =ROUND(Source!EV84,O109) -> 0 | W109: 0 | X109: 1 | Y109: 0 | Z109: 0 | AA109: 1 | AB109: 0
A110: 50 | B110: 0 | C110: 0 | D110: 1 | E110: 210 | F110: =ROUND(Source!X84,O110) -> 189.29 | G110: НР | H110: Накладные расходы | K110: 210 | L110: 25 | M110: 3 | O110: 2 | P110: =ROUND(Source!DP84,O110) -> 10409.03 | W110: 189.29 | X110: 1 | Y110: 189.29 | Z110: 10409.03 | AA110: 1 | AB110: 10409.03
A111: 50 | B111: 0 | C111: 0 | D111: 1 | E111: 211 | F111: =ROUND(Source!Y84,O111) -> 97.28 | G111: СмПриб | H111: Сметная прибыль | K111: 211 | L111: 26 | M111: 3 | O111: 2 | P111: =ROUND(Source!DQ84,O111) -> 5349.85 | W111: 97.28 | X111: 1 | Y111: 97.28 | Z111: 5349.85 | AA111: 1 | AB111: 5349.85
A112: 50 | B112: 0 | C112: 0 | D112: 1 | E112: 224 | F112: =ROUND(Source!AR84,O112) -> 2609.33 | G112: Всего | H112: Всего с НР и СП | K112: 224 | L112: 27 | M112: 3 | O112: 2 | P112: =ROUND(Source!EJ84,O112) -> 39179.22 | W112: 2609.33 | X112: 1 | Y112: 2609.33 | Z112: 39179.22 | AA112: 1 | AB112: 39179.22
A114: 51 | B114: =B20 -> 1 | C114: =A20 -> 3 | D114: =ROW(A20) -> 20 | F114: =IF(F20<>"",F20,"") -> 02-01-13 | G114: =IF(G20<>"",G20,"") -> Электрочасофикация | H114: 0 | O114: =ROUND(O37+O84+AB114,2) -> 14406.32 | P114: =ROUND(P37+P84+AC114,2) -> 14092.88 | Q114: =ROUND(Q37+Q84+AD114,2) -> 3.84 | R114: =ROUND(R37+R84+AE114,2) -> 0.17 | S114: =ROUND(S37+S84+AF114,2) -> 309.6 | T114: =ROUND(T37+T84+AG114,2) -> 0 | U114: =U37+U84+AH114 -> 25.366193 | V114: =V37+V84+AI114 -> 0 | W114: =ROUND(W37+W84+AJ114,2) -> 0 | X114: =ROUND(X37+X84+AK114,2) -> 281.45 | Y114: =ROUND(Y37+Y84+AL114,2) -> 144.39 | AO114: =ROUND(AO37+AO84+BX114,2) -> 0 | AP114: =ROUND(AP37+AP84+BY114,2) -> 11980.11 | AQ114: =ROUND(AQ37+AQ84+BZ114,2) -> 0 | AR114: =ROUND(AR37+AR84+CA114,2) -> 14832.16 | AS114: =ROUND(AS37+AS84+CB114,2) -> 0 | AT114: =ROUND(AT37+AT84+CC114,2) -> 2852.05 | AU114: =ROUND(AU37+AU84+CD114,2) -> 0 | AV114: =ROUND(AV37+AV84+CE114,2) -> 14092.88 | ... BD114: =ROUND(BD37+BD84+CM114,2) -> 0 | DG114: =ROUND(DG37+DG84+DT114,2) -> 117234.64 | DH114: =ROUND(DH37+DH84+DU114,2) -> 100167.42 | DI114: =ROUND(DI37+DI84+DV114,2) -> 42.32 | DJ114: =ROUND(DJ37+DJ84+DW114,2) -> 9.35 | DK114: =ROUND(DK37+DK84+DX114,2) -> 17024.9 | DL114: =ROUND(DL37+DL84+DY114,2) -> 0 | DM114: =DM37+DM84+DZ114 -> 25.366193 | DN114: =DN37+DN84+EA114 -> 0 | DO114: =ROUND(DO37+DO84+EB114,2) -> 0 | DP114: =ROUND(DP37+DP84+EC114,2) -> 15476.91 | DQ114: =ROUND(DQ37+DQ84+ED114,2) -> 7940.09 | EG114: =ROUND(EG37+EG84+FP114,2) -> 0 | EH114: =ROUND(EH37+EH84+FQ114,2) -> 88172.94 | EI114: =ROUND(EI37+EI84+FR114,2) -> 0 | EJ114: =ROUND(EJ37+EJ84+FS114,2) -> 140651.64 | EK114: =ROUND(EK37+EK84+FT114,2) -> 0 | EL114: =ROUND(EL37+EL84+FU114,2) -> 52478.7 | EM114: =ROUND(EM37+EM84+FV114,2) -> 0 | EN114: =ROUND(EN37+EN84+FW114,2) -> 100167.42 | ... EV114: =ROUND(EV37+EV84+GE114,2) -> 0 | GX114: 0
A116: 50 | B116: 0 | C116: 0 | D116: 1 | E116: 201 | F116: =ROUND(Source!O114,O116) -> 14406.32 | G116: ПЗ | H116: Прямые затраты | K116: 201 | L116: 1 | M116: 3 | O116: 2 | P116: =ROUND(Source!DG114,O116) -> 117234.64 | W116: 14406.32 | X116: 1 | Y116: 14406.32 | Z116: 117234.64 | AA116: 1 | AB116: 117234.64
A117: 50 | B117: 0 | C117: 0 | D117: 1 | E117: 202 | F117: =ROUND(Source!P114,O117) -> 14092.88 | G117: СтМатОб | H117: Стоимость материальных ресурсов (всего) | K117: 202 | L117: 2 | M117: 3 | O117: 2 | P117: =ROUND(Source!DH114,O117) -> 100167.42 | W117: 14092.88 | X117: 1 | Y117: 14092.88 | Z117: 100167.42 | AA117: 1 | AB117: 100167.42
A118: 50 | B118: 0 | C118: 0 | D118: 1 | E118: 222 | F118: =ROUND(Source!AO114,O118) -> 0 | G118: СтМатОбЗак | H118: Стоимость материалов и оборудования заказчика | K118: 222 | L118: 3 | M118: 3 | O118: 2 | P118: =ROUND(Source!EG114,O118) -> 0 | W118: 0 | X118: 1 | Y118: 0 | Z118: 0 | AA118: 1 | AB118: 0
A119: 50 | B119: 0 | C119: 0 | D119: 1 | E119: 225 | F119: =ROUND(Source!AV114,O119) -> 14092.88 | G119: СтМатОбПод | H119: Стоимость материалов и оборудования подрядчика | K119: 225 | L119: 4 | M119: 3 | O119: 2 | P119: =ROUND(Source!EN114,O119) -> 100167.42 | W119: 14092.88 | X119: 1 | Y119: 14092.88 | Z119: 100167.42 | AA119: 1 | AB119: 100167.42
A120: 50 | B120: 0 | C120: 0 | D120: 1 | E120: 226 | F120: =ROUND(Source!AW114,O120) -> 2112.77 | G120: СтМат | H120: Стоимость материалов (всего) | K120: 226 | L120: 5 | M120: 3 | O120: 2 | P120: =ROUND(Source!EO114,O120) -> 11994.48 | W120: 2112.77 | X120: 1 | Y120: 2112.77 | Z120: 11994.48 | AA120: 1 | AB120: 11994.48
A121: 50 | B121: 0 | C121: 0 | D121: 1 | E121: 227 | F121: =ROUND(Source!AX114,O121) -> 0 | G121: СтМатЗак | H121: Стоимость материалов заказчика | K121: 227 | L121: 6 | M121: 3 | O121: 2 | P121: =ROUND(Source!EP114,O121) -> 0 | W121: 0 | X121: 1 | Y121: 0 | Z121: 0 | AA121: 1 | AB121: 0
A122: 50 | B122: 0 | C122: 0 | D122: 1 | E122: 228 | F122: =ROUND(Source!AY114,O122) -> 2112.77 | G122: СтМатПод | H122: Стоимость материалов подрядчика | K122: 228 | L122: 7 | M122: 3 | O122: 2 | P122: =ROUND(Source!EQ114,O122) -> 11994.48 | W122: 2112.77 | X122: 1 | Y122: 2112.77 | Z122: 11994.48 | AA122: 1 | AB122: 11994.48
A123: 50 | B123: 0 | C123: 0 | D123: 1 | E123: 216 | F123: =ROUND(Source!AP114,O123) -> 11980.11 | G123: Оборуд | H123: Стоимость оборудования (всего) | K123: 216 | L123: 8 | M123: 3 | O123: 2 | P123: =ROUND(Source!EH114,O123) -> 88172.94 | W123: 11980.11 | X123: 1 | Y123: 11980.11 | Z123: 88172.94 | AA123: 1 | AB123: 88172.94
A124: 50 | B124: 0 | C124: 0 | D124: 1 | E124: 223 | F124: =ROUND(Source!AQ114,O124) -> 0 | G124: ОборудЗак | H124: Стоимость оборудования заказчика | K124: 223 | L124: 9 | M124: 3 | O124: 2 | P124: =ROUND(Source!EI114,O124) -> 0 | W124: 0 | X124: 1 | Y124: 0 | Z124: 0 | AA124: 1 | AB124: 0
A125: 50 | B125: 0 | C125: 0 | D125: 1 | E125: 229 | F125: =ROUND(Source!AZ114,O125) -> 11980.11 | G125: ОборудПод | H125: Стоимость оборудования подрядчика | K125: 229 | L125: 10 | M125: 3 | O125: 2 | P125: =ROUND(Source!ER114,O125) -> 88172.94 | W125: 11980.11 | X125: 1 | Y125: 11980.11 | Z125: 88172.94 | AA125: 1 | AB125: 88172.94
A126: 50 | B126: 0 | C126: 0 | D126: 1 | E126: 203 | F126: =ROUND(Source!Q114,O126) -> 3.84 | G126: ЭММ | H126: Эксплуатация машин | K126: 203 | L126: 11 | M126: 3 | O126: 2 | P126: =ROUND(Source!DI114,O126) -> 42.32 | W126: 3.84 | X126: 1 | Y126: 3.84 | Z126: 42.32 | AA126: 1 | AB126: 42.32
A127: 50 | B127: 0 | C127: 0 | D127: 1 | E127: 231 | F127: =ROUND(Source!BB114,O127) -> 0 | G127: ЭММсНРиСП | H127: Эксплуатация машин по ТСН-2001.16 | K127: 231 | L127: 12 | M127: 3 | O127: 2 | P127: =ROUND(Source!ET114,O127) -> 0 | W127: 0 | X127: 1 | Y127: 0 | Z127: 0 | AA127: 1 | AB127: 0
...

Sheet SourceObSm
A1: 0 | B1: Smeta.RU (495) 974-1589 | D1: _OBSM_ | F1: 0 | G1: 0 | H1: 0 | I1: Smeta.RU | K1: 1 | L1: 74563 | M1: 10 | N1: 12 | O1: 1 | P1: 0 | Q1: 0
A4: 1 | B4: 1 | C4: -1 | G4: Капитальный ремонт здания Государственного бюджетного общеобразовательного учреждения города Москвы "Школа №236" по адресу: г. Москва, улица Клязьминская, дом 7, корпус 4 | EC4: 0
A12: 1 | B12: 51 | C12: 0 | E12: 0 | G12: 02-01-13 Электрочасофикация | I12: 0 | J12: 2024-00272-01-0-ИОС5.6 | K12: 0 | L12: 0 | M12: 4098 | O12: 0 | P12: 0 | Q12: 0 | R12: 0 | S12: 0 | T12: 1 | V12: 0 | AB12: Соколова И.Н. | BB12: 0 | BH12: Сметные нормы списания | BI12: Коды ОКП для ТСН-2001 МГЭ Дополнение 80 | BJ12: 1 | BK12: 1 | BL12: 0 | BM12: 0 | BN12: 1 | BO12: 0 | BP12: 6 | BQ12: 2 | BR12: 1 | BS12: 1 | BT12: 0 | BU12: 0 | BV12: 0 | BW12: 0 | BX12: 0 | BZ12: Типовой расчет для ТСН-2001 МГЭ, Дополнение 80, строительство (1) | CA12: Территориальные сметные нормативы для Москвы ТСН-2001 (МГЭ), дополнение 80 | CB12: Территориальные сметные нормативы для Москвы ТСН-2001 (МГЭ), дополнение 80 | CC12: Территориальные сметные нормативы для Москвы ТСН-2001 (МГЭ), дополнение 80 | CD12: Территориальные сметные нормативы для Москвы ТСН-2001 (МГЭ), дополнение 80 | CE12: Поправки для ТСН-2001 от 28.11.2025 г. доп.79 | CF12: 0 | CG12: 0 | CH12: 8200 | CK12: 81 | CQ12: Территориальные сметные нормативы для Москвы (ТСН-2001) | CR12: ТЕР | CS12: 41660 | CT12: 1 | CU12: 80 | CY12: 0 | EC12: 0
A14: 22 | B14: 1 | C14: 0 | D14: 60257733 | E14: 60257736 | F14: 2 | G14: 1
A16: 3 | B16: 1 | C16: 02-01-13 | D16: Электрочасофикация | E16: =ROUND((Source!P131)/1000,2) -> 0 | F16: =ROUND((Source!P132)/1000,2) -> 52.48 | G16: =ROUND((Source!P123)/1000,2) -> 88.17 | H16: =ROUND((Source!P133)/1000+(Source!P134)/1000,2) -> 0 | I16: =E16+F16+G16+H16 -> 140.65 | J16: =ROUND((Source!P129+Source!P128)/1000,2) -> 17.03 | K16: 217.4 | L16: 0 | M16: 0 | N16: =I16+L16+M16 -> 140.65 | T16: =ROUND((Source!F131)/1000,2) -> 0 | U16: =ROUND((Source!F132)/1000,2) -> 2.85 | V16: =ROUND((Source!F123)/1000,2) -> 11.98 | W16: =ROUND((Source!F133)/1000+(Source!F134)/1000,2) -> 0 | X16: =T16+U16+V16+W16 -> 14.83 | Y16: =ROUND((Source!F129+Source!F128)/1000,2) -> 0.31 | Z16: 28.5 | AA16: 0 | AB16: 0 | AC16: =X16+AA16+AB16 -> 14.83 | AI16: 2 | AJ16: -1 | AN16: 0 | AT16: 117234.64 | AU16: 100167.42 | AV16: 0 | AW16: 88172.94 | AX16: 0 | AY16: 42.32 | AZ16: 9.35 | BA16: 17024.9 | BB16: 0 | BC16: 52478.7 | BD16: 0 | BE16: 0 | BF16: 25.366193 | BG16: 0 | BH16: 0 | BI16: 15476.91 | BJ16: 7940.09 | BK16: 140651.64 | BR16: 14406.32 | BS16: 14092.88 | BT16: 0 | BU16: 11980.11 | BV16: 0 | BW16: 3.84 | BX16: 0.17 | BY16: 309.6 | BZ16: 0 | CA16: 2852.05 | CB16: 0 | CC16: 0 | CD16: 25.366193 | CE16: 0 | CF16: 0 | CG16: 281.45 | CH16: 144.39 | CI16: 14832.16
A18: 51 | E18: 0 | F18: 52.48 | G18: 88.17 | H18: 0 | I18: 140.65 | J18: 17.03 | K18: 217.4 | L18: 0 | M18: 0 | N18: 140.65 | T18: 0 | U18: 2.85 | V18: 11.98 | W18: 0 | X18: 14.83 | Y18: 0.31 | Z18: 28.5 | AA18: 0 | AB18: 0 | AC18: 14.83
A20: 50 | B20: 0 | C20: 0 | D20: 1 | E20: 201 | F20: 117234.64 | G20: ПЗ | H20: Прямые затраты | K20: 201 | L20: 1 | M20: 3 | O20: 2 | P20: 14406.32
A21: 50 | B21: 0 | C21: 0 | D21: 1 | E21: 202 | F21: 100167.42 | G21: СтМатОб | H21: Стоимость материальных ресурсов (всего) | K21: 202 | L21: 2 | M21: 3 | O21: 2 | P21: 14092.88
A22: 50 | B22: 0 | C22: 0 | D22: 1 | E22: 222 | F22: 0 | G22: СтМатОбЗак | H22: Стоимость материалов и оборудования заказчика | K22: 222 | L22: 3 | M22: 3 | O22: 2 | P22: 0
A23: 50 | B23: 0 | C23: 0 | D23: 1 | E23: 225 | F23: 100167.42 | G23: СтМатОбПод | H23: Стоимость материалов и оборудования подрядчика | K23: 225 | L23: 4 | M23: 3 | O23: 2 | P23: 14092.88
A24: 50 | B24: 0 | C24: 0 | D24: 1 | E24: 226 | F24: 11994.48 | G24: СтМат | H24: Стоимость материалов (всего) | K24: 226 | L24: 5 | M24: 3 | O24: 2 | P24: 2112.77
A25: 50 | B25: 0 | C25: 0 | D25: 1 | E25: 227 | F25: 0 | G25: СтМатЗак | H25: Стоимость материалов заказчика | K25: 227 | L25: 6 | M25: 3 | O25: 2 | P25: 0
A26: 50 | B26: 0 | C26: 0 | D26: 1 | E26: 228 | F26: 11994.48 | G26: СтМатПод | H26: Стоимость материалов подрядчика | K26: 228 | L26: 7 | M26: 3 | O26: 2 | P26: 2112.77
A27: 50 | B27: 0 | C27: 0 | D27: 1 | E27: 216 | F27: 88172.94 | G27: Оборуд | H27: Стоимость оборудования (всего) | K27: 216 | L27: 8 | M27: 3 | O27: 2 | P27: 11980.11
A28: 50 | B28: 0 | C28: 0 | D28: 1 | E28: 223 | F28: 0 | G28: ОборудЗак | H28: Стоимость оборудования заказчика | K28: 223 | L28: 9 | M28: 3 | O28: 2 | P28: 0
A29: 50 | B29: 0 | C29: 0 | D29: 1 | E29: 229 | F29: 88172.94 | G29: ОборудПод | H29: Стоимость оборудования подрядчика | K29: 229 | L29: 10 | M29: 3 | O29: 2 | P29: 11980.11
A30: 50 | B30: 0 | C30: 0 | D30: 1 | E30: 203 | F30: 42.32 | G30: ЭММ | H30: Эксплуатация машин | K30: 203 | L30: 11 | M30: 3 | O30: 2 | P30: 3.84
A31: 50 | B31: 0 | C31: 0 | D31: 1 | E31: 231 | F31: 0 | G31: ЭММсНРиСП | H31: Эксплуатация машин по ТСН-2001.16 | K31: 231 | L31: 12 | M31: 3 | O31: 2 | P31: 0
... A46: 50 | B46: 0 | C46: 0 | D46: 1 | E46: 224 | F46: 140651.64 | G46: Всего | H46: Всего с НР и СП | K46: 224 | L46: 27 | M46: 3 | O46: 2 | P46: 14832.16
A48: -1
A51: 75 | B51: Текущий уровень цен | C51: 2025 | D51: 3 | E51: 0 | G51: 0 | H51: 1 | I51: 1 | J51: 3 | K51: 0 | L51: 0 | M51: 1 | N51: 60257733 | O51: 1
A52: 1 | B52: Сборник индексов | C52: Коэффициенты к ТСН-2001 МГЭ Дополнение 80, строительство | D52: 2025 | E52: 9 | F52: 1 | G52: 1 | H52: 0 | I52: 2 | J52: 1 | K52: 9.88 | L52: 7.66 | M52: 1 | N52: 1 | O52: 9.88 | P52: 7.66 | Q52: 1 | AA52: 217/80 | AN52: 60257734
A53: 1 | B53: Сборник индексов | C53: Коэффициенты к ТСН-2001.13-2 Дополнение 46 | D53: 2025 | E53: 7 | F53: 1 | G53: 1 | H53: 0 | I53: 2 | J53: 1 | K53: 1 | L53: 1 | M53: 1 | N53: 1 | O53: 1 | P53: 1 | Q53: 1 | AA53: 62/46 | AN53: 60257735
A54: 75 | B54: Базовый уровень цен | C54: 2000 | D54: 0 | E54: 1 | F54: 0 | G54: 0 | H54: 1 | I54: 1 | J54: 3 | K54: 0 | L54: 0 | M54: 0 | N54: 60257736 | O54: 2
A55: 1 | B55: Сборник индексов | C55: Коэффициенты к ТСН-2001 МГЭ Дополнение 80, строительство | D55: 2000 | E55: 1 | F55: 1 | G55: 1 | H55: 0 | I55: 2 | J55: 1 | K55: 1 | L55: 1 | M55: 1 | N55: 1 | O55: 1 | P55: 1 | Q55: 1 | AA55: 0 | AN55: 60257737

Sheet SmtRes
A1: =ROW(Source!A28) -> 28 | B1: 60257736 | C1: 60257850 | D1: 58999254 | E1: 1080 | F1: 1 | G1: 1080 | H1: 1 | I1: 9999990008 | K1: Трудозатраты рабочих | L1: 1191 | N1: 1013 | O1: чел.-ч. | P1: чел.-ч. | Q1: 1 | W1: 0 | X1: 476480486 | Y1: =(AT1*1.1) -> 3.3 | AA1: 0 | AB1: 0 | AC1: 0 | AD1: 0 | AE1: 0 | AF1: 0 | AG1: 0 | AH1: 0 | AI1: 1 | AJ1: 1 | AK1: 1 | AL1: 1 | AM1: -2 | AN1: 0 | AO1: 1 | AP1: 1 | AQ1: 0 | AR1: 0 | AT1: 3 | AU1: *1,1 | AV1: 1 | AW1: 2 | AX1: 60257963 | AY1: 1 | AZ1: 0 | BA1: 1 | BB1: 0 | BC1: 0 | BD1: 0 | BE1: 0 | BF1: 0 | BG1: 0 | BH1: 0 | BI1: 0 | BJ1: 0 | BK1: 0 | BL1: 0 | BM1: 0 | BN1: 0 | BO1: 0 | BP1: 0 | BQ1: 0 | BR1: 0 | BS1: 0 | BT1: 0 | BU1: 0 | BV1: 0 | BW1: 0 | CU1: =ROUND(AT1*Source!I28*AH1*AL1,2) -> 0 | CV1: =ROUND(Y1*Source!I28,9) -> 3.3 | CW1: 0 | CX1: =ROUND(Y1*Source!I28,9) -> 3.3 | CY1: =AD1 -> 0 | CZ1: =AH1 -> 0 | DA1: =AL1 -> 1 | DB1: =ROUND((ROUND(AT1*CZ1,2)*1.1),6) -> 0 | DC1: =ROUND((ROUND(AT1*AG1,2)*1.1),6) -> 0 | DF1: =ROUND(ROUND(AE1,2)*CX1,2) -> 0 | DG1: =ROUND(ROUND(AF1,2)*CX1,2) -> 0 | DH1: =ROUND(ROUND(AG1,2)*CX1,2) -> 0 | DI1: =ROUND(ROUND(AH1,2)*CX1,2) -> 0 | DJ1: =DI1 -> 0 | DK1: 0 | DM1: 0 | DO1: 0
A2: =ROW(Source!A29) -> 29 | B2: 60257733 | C2: 60257850 | D2: 58999254 | E2: 1080 | F2: 1 | G2: 1080 | H2: 1 | I2: 9999990008 | K2: Трудозатраты рабочих | L2: 1191 | N2: 1013 | O2: чел.-ч. | P2: чел.-ч. | Q2: 1 | W2: 0 | X2: 476480486 | Y2: =(AT2*1.1) -> 3.3 | AA2: 0 | AB2: 0 | AC2: 0 | AD2: 0 | AE2: 0 | AF2: 0 | AG2: 0 | AH2: 0 | AI2: 1 | AJ2: 1 | AK2: 1 | AL2: 1 | AM2: 5 | AN2: 0 | AO2: 1 | AP2: 1 | AQ2: 0 | AR2: 0 | AT2: 3 | AU2: *1,1 | AV2: 1 | AW2: 2 | AX2: 60257963 | AY2: 1 | AZ2: 0 | BA2: 2 | BB2: 0 | BC2: 0 | BD2: 0 | BE2: 0 | BF2: 0 | BG2: 0 | BH2: 0 | BI2: 0 | BJ2: 0 | BK2: 0 | BL2: 0 | BM2: 0 | BN2: 0 | BO2: 0 | BP2: 0 | BQ2: 0 | BR2: 0 | BS2: 0 | BT2: 0 | BU2: 0 | BV2: 0 | BW2: 0 | CU2: =ROUND(AT2*Source!I29*AH2*AL2,2) -> 0 | CV2: =ROUND(Y2*Source!I29,9) -> 3.3 | CW2: 0 | CX2: =ROUND(Y2*Source!I29,9) -> 3.3 | CY2: =AD2 -> 0 | CZ2: =AH2 -> 0 | DA2: =AL2 -> 1 | DB2: =ROUND((ROUND(AT2*CZ2,2)*1.1),6) -> 0 | DC2: =ROUND((ROUND(AT2*AG2,2)*1.1),6) -> 0 | DF2: =ROUND(ROUND(AE2,2)*CX2,2) -> 0 | DG2: =ROUND(ROUND(AF2,2)*CX2,2) -> 0 | DH2: =ROUND(ROUND(AG2,2)*CX2,2) -> 0 | DI2: =ROUND(ROUND(AH2,2)*CX2,2) -> 0 | DJ2: =DI2 -> 0 | DK2: 0 | DM2: 0 | DO2: 0
A3: =ROW(Source!A32) -> 32 | B3: 60257736 | C3: 60257854 | D3: 58999254 | E3: 1080 | F3: 1 | G3: 1080 | H3: 1 | I3: 9999990008 | K3: Трудозатраты рабочих | L3: 1191 | N3: 1013 | O3: чел.-ч. | P3: чел.-ч. | Q3: 1 | W3: 0 | X3: 476480486 | Y3: =(AT3*1.1) -> 2.2 | AA3: 0 | AB3: 0 | AC3: 0 | AD3: 0 | AE3: 0 | AF3: 0 | AG3: 0 | AH3: 0 | AI3: 1 | AJ3: 1 | AK3: 1 | AL3: 1 | AM3: -2 | AN3: 0 | AO3: 1 | AP3: 1 | AQ3: 0 | AR3: 0 | AT3: 2 | AU3: *1,1 | AV3: 1 | AW3: 2 | AX3: 60257964 | AY3: 1 | AZ3: 0 | BA3: 3 | BB3: 0 | BC3: 0 | BD3: 0 | BE3: 0 | BF3: 0 | BG3: 0 | BH3: 0 | BI3: 0 | BJ3: 0 | BK3: 0 | BL3: 0 | BM3: 0 | BN3: 0 | BO3: 0 | BP3: 0 | BQ3: 0 | BR3: 0 | BS3: 0 | BT3: 0 | BU3: 0 | BV3: 0 | BW3: 0 | CU3: =ROUND(AT3*Source!I32*AH3*AL3,2) -> 0 | CV3: =ROUND(Y3*Source!I32,9) -> 4.4 | CW3: 0 | CX3: =ROUND(Y3*Source!I32,9) -> 4.4 | CY3: =AD3 -> 0 | CZ3: =AH3 -> 0 | DA3: =AL3 -> 1 | DB3: =ROUND((ROUND(AT3*CZ3,2)*1.1),6) -> 0 | DC3: =ROUND((ROUND(AT3*AG3,2)*1.1),6) -> 0 | DF3: =ROUND(ROUND(AE3,2)*CX3,2) -> 0 | DG3: =ROUND(ROUND(AF3,2)*CX3,2) -> 0 | DH3: =ROUND(ROUND(AG3,2)*CX3,2) -> 0 | DI3: =ROUND(ROUND(AH3,2)*CX3,2) -> 0 | DJ3: =DI3 -> 0 | DK3: 0 | DM3: 0 | DO3: 0
A4: =ROW(Source!A33) -> 33 | B4: 60257733 | C4: 60257854 | D4: 58999254 | E4: 1080 | F4: 1 | G4: 1080 | H4: 1 | I4: 9999990008 | K4: Трудозатраты рабочих | L4: 1191 | N4: 1013 | O4: чел.-ч. | P4: чел.-ч. | Q4: 1 | W4: 0 | X4: 476480486 | Y4: =(AT4*1.1) -> 2.2 | AA4: 0 | AB4: 0 | AC4: 0 | AD4: 0 | AE4: 0 | AF4: 0 | AG4: 0 | AH4: 0 | AI4: 1 | AJ4: 1 | AK4: 1 | AL4: 1 | AM4: 5 | AN4: 0 | AO4: 1 | AP4: 1 | AQ4: 0 | AR4: 0 | AT4: 2 | AU4: *1,1 | AV4: 1 | AW4: 2 | AX4: 60257964 | AY4: 1 | AZ4: 0 | BA4: 4 | BB4: 0 | BC4: 0 | BD4: 0 | BE4: 0 | BF4: 0 | BG4: 0 | BH4: 0 | BI4: 0 | BJ4: 0 | BK4: 0 | BL4: 0 | BM4: 0 | BN4: 0 | BO4: 0 | BP4: 0 | BQ4: 0 | BR4: 0 | BS4: 0 | BT4: 0 | BU4: 0 | BV4: 0 | BW4: 0 | CU4: =ROUND(AT4*Source!I33*AH4*AL4,2) -> 0 | CV4: =ROUND(Y4*Source!I33,9) -> 4.4 | CW4: 0 | CX4: =ROUND(Y4*Source!I33,9) -> 4.4 | CY4: =AD4 -> 0 | CZ4: =AH4 -> 0 | DA4: =AL4 -> 1 | DB4: =ROUND((ROUND(AT4*CZ4,2)*1.1),6) -> 0 | DC4: =ROUND((ROUND(AT4*AG4,2)*1.1),6) -> 0 | DF4: =ROUND(ROUND(AE4,2)*CX4,2) -> 0 | DG4: =ROUND(ROUND(AF4,2)*CX4,2) -> 0 | DH4: =ROUND(ROUND(AG4,2)*CX4,2) -> 0 | DI4: =ROUND(ROUND(AH4,2)*CX4,2) -> 0 | DJ4: =DI4 -> 0 | DK4: 0 | DM4: 0 | DO4: 0
A5: =ROW(Source!A71) -> 71 | B5: 60257736 | C5: 61620566 | D5: 58999254 | E5: 1080 | F5: 1 | G5: 1080 | H5: 1 | I5: 9999990008 | K5: Трудозатраты рабочих | L5: 1191 | N5: 1013 | O5: чел.-ч. | P5: чел.-ч. | Q5: 1 | W5: 0 | X5: 476480486 | Y5: =(AT5*1.1) -> 27.236 | AA5: 0 | AB5: 0 | AC5: 0 | AD5: 0 | AE5: 0 | AF5: 0 | AG5: 0 | AH5: 0 | AI5: 1 | AJ5: 1 | AK5: 1 | AL5: 1 | AM5: -2 | AN5: 0 | AO5: 1 | AP5: 1 | AQ5: 0 | AR5: 0 | AT5: 24.76 | AU5: *1,1 | AV5: 1 | AW5: 2 | AX5: 61620567 | AY5: 1 | AZ5: 0 | BA5: 5 | BB5: 0 | BC5: 0 | BD5: 0 | BE5: 0 | BF5: 0 | BG5: 0 | BH5: 0 | BI5: 0 | BJ5: 0 | BK5: 0 | BL5: 0 | BM5: 0 | BN5: 0 | BO5: 0 | BP5: 0 | BQ5: 0 | BR5: 0 | BS5: 0 | BT5: 0 | BU5: 0 | BV5: 0 | BW5: 0 | CU5: =ROUND(AT5*Source!I71*AH5*AL5,2) -> 0 | CV5: =ROUND(Y5*Source!I71,9) -> 13.618 | CW5: 0 | CX5: =ROUND(Y5*Source!I71,9) -> 13.618 | CY5: =AD5 -> 0 | CZ5: =AH5 -> 0 | DA5: =AL5 -> 1 | DB5: =ROUND((ROUND(AT5*CZ5,2)*1.1),6) -> 0 | DC5: =ROUND((ROUND(AT5*AG5,2)*1.1),6) -> 0 | DF5: =ROUND(ROUND(AE5,2)*CX5,2) -> 0 | DG5: =ROUND(ROUND(AF5,2)*CX5,2) -> 0 | DH5: =ROUND(ROUND(AG5,2)*CX5,2) -> 0 | DI5: =ROUND(ROUND(AH5,2)*CX5,2) -> 0 | DJ5: =DI5 -> 0 | DK5: 0 | DM5: 0 | DO5: 0
A6: =ROW(Source!A71) -> 71 | B6: 60257736 | C6: 61620566 | D6: 59070721 | E6: 1 | F6: 1 | G6: 1080 | H6: 2 | I6: 2.1-30-10 | J6: ТСН-2001.2. Доп. 68. п.1-30-10 (304101) | K6: Перфораторы, мощность до 800 Вт | L6: 1368 | N6: 1011 | O6: маш.-ч | P6: маш.-ч | Q6: 1 | W6: 0 | X6: 1387779639 | Y6: =(AT6*1.1) -> 2.684 | AA6: 0 | AB6: 0.81 | AC6: 0 | AD6: 0 | AE6: 0 | AF6: 0.77 | AG6: 0 | AH6: 0 | AI6: 1 | AJ6: 1 | AK6: 1 | AL6: 1 | AM6: -2 | AN6: 0 | AO6: 1 | AP6: 1 | AQ6: 0 | AR6: 0 | AT6: 2.44 | AU6: *1,1 | AV6: 0 | AW6: 2 | AX6: 61620568 | AY6: 1 | AZ6: 0 | BA6: 6 | BB6: 0 | BC6: 0 | BD6: 0 | BE6: 0 | BF6: 0 | BG6: 0 | BH6: 0 | BI6: 0 | BJ6: 0 | BK6: 0 | BL6: 0 | BM6: 0 | BN6: 0 | BO6: 0 | BP6: 0 | BQ6: 0 | BR6: 0 | BS6: 0 | BT6: 0 | BU6: 0 | BV6: 0 | BW6: 0 | CV6: 0 | CW6: =ROUND(Y6*Source!I71*DO6,9) -> 0 | CX6: =ROUND(Y6*Source!I71,9) -> 1.342 | CY6: =AB6 -> 0.81 | CZ6: =AF6 -> 0.77 | DA6: =AJ6 -> 1 | DB6: =ROUND((ROUND(AT6*CZ6,2)*1.1),6) -> 2.068 | DC6: =ROUND((ROUND(AT6*AG6,2)*1.1),6) -> 0 | DF6: =ROUND(ROUND(AE6,2)*CX6,2) -> 0 | DG6: =ROUND(ROUND(AF6,2)*CX6,2) -> 1.03 | DH6: =ROUND(ROUND(AG6,2)*CX6,2) -> 0 | DI6: =ROUND(ROUND(AH6,2)*CX6,2) -> 0 | DJ6: =DG6 -> 1.03 | DK6: 0 | DM6: 0 | DO6: 0
A7: =ROW(Source!A71) -> 71 | B7: 60257736 | C7: 61620566 | D7: 59070754 | E7: 1 | F7: 1 | G7: 1080 | H7: 2 | I7: 2.1-30-56 | J7: ТСН-2001.2. Доп. 68. п.1-30-56 (309101) | K7: Шуруповерты | L7: 1368 | N7: 1011 | O7: маш.-ч | P7: маш.-ч | Q7: 1 | W7: 0 | X7: 1645565003 | Y7: =(AT7*1.1) -> 5.093 | AA7: 0 | AB7: 0.49 | AC7: 0 | AD7: 0 | AE7: 0 | AF7: 0.47 | AG7: 0 | AH7: 0 | AI7: 1 | AJ7: 1 | AK7: 1 | AL7: 1 | AM7: -2 | AN7: 0 | AO7: 1 | AP7: 1 | AQ7: 0 | AR7: 0 | AT7: 4.63 | AU7: *1,1 | AV7: 0 | AW7: 2 | AX7: 61620569 | AY7: 1 | AZ7: 0 | BA7: 7 | BB7: 0 | BC7: 0 | BD7: 0 | BE7: 0 | BF7: 0 | BG7: 0 | BH7: 0 | BI7: 0 | BJ7: 0 | BK7: 0 | BL7: 0 | BM7: 0 | BN7: 0 | BO7: 0 | BP7: 0 | BQ7: 0 | BR7: 0 | BS7: 0 | BT7: 0 | BU7: 0 | BV7: 0 | BW7: 0 | CV7: 0 | CW7: =ROUND(Y7*Source!I71*DO7,9) -> 0 | CX7: =ROUND(Y7*Source!I71,9) -> 2.5465 | CY7: =AB7 -> 0.49 | CZ7: =AF7 -> 0.47 | DA7: =AJ7 -> 1 | DB7: =ROUND((ROUND(AT7*CZ7,2)*1.1),6) -> 2.398 | DC7: =ROUND((ROUND(AT7*AG7,2)*1.1),6) -> 0 | DF7: =ROUND(ROUND(AE7,2)*CX7,2) -> 0 | DG7: =ROUND(ROUND(AF7,2)*CX7,2) -> 1.2 | DH7: =ROUND(ROUND(AG7,2)*CX7,2) -> 0 | DI7: =ROUND(ROUND(AH7,2)*CX7,2) -> 0 | DJ7: =DG7 -> 1.2 | DK7: 0 | DM7: 0 | DO7: 0
A8: =ROW(Source!A71) -> 71 | B8: 60257736 | C8: 61620566 | D8: 59052975 | E8: 1 | F8: 1 | G8: 1080 | H8: 3 | I8: 1.12-5-371 | J8: ТСН-2001.1 Доп. 67, Р. 12, о. 5, поз. 371 | K8: Трубы электротехнические, гофрированные, из ПВХ, негорючие, с зондом, наружный диаметр 16 мм | L8: 1301 | N8: 1003 | O8: м | P8: м | Q8: 1 | W8: 0 | X8: 1184991115 | Y8: =AT8 -> 102 | AA8: 2.67 | AB8: 0 | AC8: 0 | AD8: 0 | AE8: 2.67 | AF8: 0 | AG8: 0 | AH8: 0 | AI8: 1 | AJ8: 1 | AK8: 1 | AL8: 1 | AM8: 0 | AN8: 0 | AO8: 0 | AP8: 1 | AQ8: 0 | AR8: 0 | AT8: 102 | AV8: 0 | AW8: 1 | AX8: -1 | AY8: 0 | AZ8: 0 | BB8: 0 | BC8: 0 | BD8: 0 | BE8: 0 | BF8: 0 | BG8: 0 | BH8: 0 | BI8: 0 | BJ8: 0 | BK8: 0 | BL8: 0 | BM8: 0 | BN8: 0 | BO8: 0 | BP8: 0 | BQ8: 0 | BR8: 0 | BS8: 0 | BT8: 0 | BU8: 0 | BV8: 0 | BW8: 0 | CV8: 0 | CW8: 0 | CX8: =ROUND(Y8*Source!I71,9) -> 51 | CY8: =AA8 -> 2.67 | CZ8: =AE8 -> 2.67 | DA8: =AI8 -> 1 | DB8: =ROUND(ROUND(AT8*CZ8,2),6) -> 272.34 | DC8: =ROUND(ROUND(AT8*AG8,2),6) -> 0 | DF8: =ROUND(ROUND(AE8,2)*CX8,2) -> 136.17 | DG8: =ROUND(ROUND(AF8,2)*CX8,2) -> 0 | DH8: =ROUND(ROUND(AG8,2)*CX8,2) -> 0 | DI8: =ROUND(ROUND(AH8,2)*CX8,2) -> 0 | DJ8: =DF8 -> 136.17 | DK8: 0 | DM8: 0 | DO8: 0
A9: =ROW(Source!A71) -> 71 | B9: 60257736 | C9: 61620566 | D9: 59058215 | E9: 1 | F9: 1 | G9: 1080 | H9: 3 | I9: 1.14-1-555 | J9: ТСН-2001.1 Доп. 73, Р. 14, о. 1, поз. 555 | K9: Скобы крепежные для радиочастотного коаксиального кабеля с номинальным диаметром по изоляции от 4 до 6 мм | L9: 1355 | N9: 1010 | O9: 100 шт. | P9: 100 шт. | Q9: 100 | W9: 0 | X9: -1288220709 | Y9: =AT9 -> 2.38 | AA9: 46.63 | AB9: 0 | AC9: 0 | AD9: 0 | AE9: 46.63 | AF9: 0 | AG9: 0 | AH9: 0 | AI9: 1 | AJ9: 1 | AK9: 1 | AL9: 1 | AM9: 0 | AN9: 0 | AO9: 0 | AP9: 1 | AQ9: 0 | AR9: 0 | AT9: 2.38 | AV9: 0 | AW9: 1 | AX9: -1 | AY9: 0 | AZ9: 0 | BB9: 0 | BC9: 0 | BD9: 0 | BE9: 0 | BF9: 0 | BG9: 0 | BH9: 0 | BI9: 0 | BJ9: 0 | BK9: 0 | BL9: 0 | BM9: 0 | BN9: 0 | BO9: 0 | BP9: 0 | BQ9: 0 | BR9: 0 | BS9: 0 | BT9: 0 | BU9: 0 | BV9: 0 | BW9: 0 | CV9: 0 | CW9: 0 | CX9: =ROUND(Y9*Source!I71,9) -> 1.19 | CY9: =AA9 -> 46.63 | CZ9: =AE9 -> 46.63 | DA9: =AI9 -> 1 | DB9: =ROUND(ROUND(AT9*CZ9,2),6) -> 110.98 | DC9: =ROUND(ROUND(AT9*AG9,2),6) -> 0 | DF9: =ROUND(ROUND(AE9,2)*CX9,2) -> 55.49 | DG9: =ROUND(ROUND(AF9,2)*CX9,2) -> 0 | DH9: =ROUND(ROUND(AG9,2)*CX9,2) -> 0 | DI9: =ROUND(ROUND(AH9,2)*CX9,2) -> 0 | DJ9: =DF9 -> 55.49 | DK9: 0 | DM9: 0 | DO9: 0
A10: =ROW(Source!A71) -> 71 | B10: 60257736 | C10: 61620566 | D10: 59062734 | E10: 1 | F10: 1 | G10: 1080 | H10: 3 | I10: 1.21-5-1180 | J10: ТСН-2001.1 Доп. 79, Р. 21, о. 5, поз. 1180 | K10: Бирка маркировочная для кабелей и проводов, типа У134 У3,5 | L10: 1356 | N10: 1010 | O10: 1000 шт. | P10: 1000 шт. | Q10: 1000 | W10: 0 | X10: -1221558404 | Y10: =AT10 -> 0.031 | AA10: 226.66 | AB10: 0 | AC10: 0 | AD10: 0 | AE10: 226.66 | AF10: 0 | AG10: 0 | AH10: 0 | AI10: 1 | AJ10: 1 | AK10: 1 | AL10: 1 | AM10: -2 | AN10: 0 | AO10: 1 | AP10: 1 | AQ10: 0 | AR10: 0 | AT10: 0.031 | AV10: 0 | AW10: 2 | AX10: 61620570 | AY10: 1 | AZ10: 0 | BA10: 8 | BB10: 0 | BC10: 0 | BD10: 0 | BE10: 0 | BF10: 0 | BG10: 0 | BH10: 0 | BI10: 0 | BJ10: 0 | BK10: 0 | BL10: 0 | BM10: 0 | BN10: 0 | BO10: 0 | BP10: 0 | BQ10: 0 | BR10: 0 | BS10: 0 | BT10: 0 | BU10: 0 | BV10: 0 | BW10: 0 | CV10: 0 | CW10: 0 | CX10: =ROUND(Y10*Source!I71,9) -> 0.0155 | CY10: =AA10 -> 226.66 | CZ10: =AE10 -> 226.66 | DA10: =AI10 -> 1 | DB10: =ROUND(ROUND(AT10*CZ10,2),6) -> 7.03 | DC10: =ROUND(ROUND(AT10*AG10,2),6) -> 0 | DF10: =ROUND(ROUND(AE10,2)*CX10,2) -> 3.51 | DG10: =ROUND(ROUND(AF10,2)*CX10,2) -> 0 | DH10: =ROUND(ROUND(AG10,2)*CX10,2) -> 0 | DI10: =ROUND(ROUND(AH10,2)*CX10,2) -> 0 | DJ10: =DF10 -> 3.51 | DK10: 0 | DM10: 0 | DO10: 0
A11: =ROW(Source!A71) -> 71 | B11: 60257736 | C11: 61620566 | D11: 59062508 | E11: 1 | F11: 1 | G11: 1080 | H11: 3 | I11: 1.21-5-926 | J11: ТСН-2001.1 Доп. 67, Р. 21, о. 5, поз. 926 | K11: Хомут (стяжка) кабельный из полиамида, размеры 3,6х200 мм | L11: 1355 | N11: 1010 | O11: 100 шт. | P11: 100 шт. | Q11: 100 | W11: 0 | X11: -210805237 | Y11: =AT11 -> 0.315 | AA11: 26.71 | AB11: 0 | AC11: 0 | AD11: 0 | AE11: 26.71 | AF11: 0 | AG11: 0 | AH11: 0 | AI11: 1 | AJ11: 1 | AK11: 1 | AL11: 1 | AM11: -2 | AN11: 0 | AO11: 1 | AP11: 1 | AQ11: 0 | AR11: 0 | AT11: 0.315 | AV11: 0 | AW11: 2 | AX11: 61620571 | AY11: 1 | AZ11: 0 | BA11: 9 | BB11: 0 | BC11: 0 | BD11: 0 | BE11: 0 | BF11: 0 | BG11: 0 | BH11: 0 | BI11: 0 | BJ11: 0 | BK11: 0 | BL11: 0 | BM11: 0 | BN11: 0 | BO11: 0 | BP11: 0 | BQ11: 0 | BR11: 0 | BS11: 0 | BT11: 0 | BU11: 0 | BV11: 0 | BW11: 0 | CV11: 0 | CW11: 0 | CX11: =ROUND(Y11*Source!I71,9) -> 0.1575 | CY11: =AA11 -> 26.71 | CZ11: =AE11 -> 26.71 | DA11: =AI11 -> 1 | DB11: =ROUND(ROUND(AT11*CZ11,2),6) -> 8.41 | DC11: =ROUND(ROUND(AT11*AG11,2),6) -> 0 | DF11: =ROUND(ROUND(AE11,2)*CX11,2) -> 4.21 | DG11: =ROUND(ROUND(AF11,2)*CX11,2) -> 0 | DH11: =ROUND(ROUND(AG11,2)*CX11,2) -> 0 | DI11: =ROUND(ROUND(AH11,2)*CX11,2) -> 0 | DJ11: =DF11 -> 4.21 | DK11: 0 | DM11: 0 | DO11: 0
A12: =ROW(Source!A71) -> 71 | B12: 60257736 | C12: 61620566 | D12: 59049364 | E12: 1 | F12: 1 | G12: 1080 | H12: 3 | I12: 1.7-3-122 | J12: ТСН-2001.1 Доп. 79, Р. 7, о. 3, поз. 122 | K12: Бур с наконечником из твердого сплава, с хвостовиком SDS-plus, диаметр 10 мм, длина 260 мм | L12: 1354 | N12: 1010 | O12: шт. | P12: шт. | Q12: 1 | W12: 0 | X12: 309799599 | Y12: =AT12 -> 0.28 | AA12: 14.22 | AB12: 0 | AC12: 0 | AD12: 0 | AE12: 14.22 | AF12: 0 | AG12: 0 | AH12: 0 | AI12: 1 | AJ12: 1 | AK12: 1 | AL12: 1 | AM12: -2 | AN12: 0 | AO12: 1 | AP12: 1 | AQ12: 0 | AR12: 0 | AT12: 0.28 | AV12: 0 | AW12: 2 | AX12: 61620572 | AY12: 1 | AZ12: 0 | BA12: 10 | BB12: 0 | BC12: 0 | BD12: 0 | BE12: 0 | BF12: 0 | BG12: 0 | BH12: 0 | BI12: 0 | BJ12: 0 | BK12: 0 | BL12: 0 | BM12: 0 | BN12: 0 | BO12: 0 | BP12: 0 | BQ12: 0 | BR12: 0 | BS12: 0 | BT12: 0 | BU12: 0 | BV12: 0 | BW12: 0 | CV12: 0 | CW12: 0 | CX12: =ROUND(Y12*Source!I71,9) -> 0.14 | CY12: =AA12 -> 14.22 | CZ12: =AE12 -> 14.22 | DA12: =AI12 -> 1 | DB12: =ROUND(ROUND(AT12*CZ12,2),6) -> 3.98 | DC12: =ROUND(ROUND(AT12*AG12,2),6) -> 0 | DF12: =ROUND(ROUND(AE12,2)*CX12,2) -> 1.99 | DG12: =ROUND(ROUND(AF12,2)*CX12,2) -> 0 | DH12: =ROUND(ROUND(AG12,2)*CX12,2) -> 0 | DI12: =ROUND(ROUND(AH12,2)*CX12,2) -> 0 | DJ12: =DF12 -> 1.99 | DK12: 0 | DM12: 0 | DO12: 0
A13: =ROW(Source!A71) -> 71 | B13: 60257736 | C13: 61620566 | D13: 59049443 | E13: 1 | F13: 1 | G13: 1080 | H13: 3 | I13: 1.7-5-131 | J13: ТСН-2001.1 Доп. 79, Р. 7, о. 5, поз. 131 | K13: Анкер забивной расклинивающийся из оцинкованной стали, с внутренней резьбой М12, длина 25 мм | L13: 1355 | N13: 1010 | O13: 100 шт. | P13: 100 шт. | Q13: 100 | W13: 0 | X13: 1852901932 | Y13: =AT13 -> 2.36 | AA13: 1297.23 | AB13: 0 | AC13: 0 | AD13: 0 | AE13: 1297.23 | AF13: 0 | AG13: 0 | AH13: 0 | AI13: 1 | AJ13: 1 | AK13: 1 | AL13: 1 | AM13: 0 | AN13: 0 | AO13: 0 | AP13: 1 | AQ13: 0 | AR13: 0 | AT13: 2.36 | AV13: 0 | AW13: 1 | AX13: -1 | AY13: 0 | AZ13: 0 | BB13: 0 | BC13: 0 | BD13: 0 | BE13: 0 | BF13: 0 | BG13: 0 | BH13: 0 | BI13: 0 | BJ13: 0 | BK13: 0 | BL13: 0 | BM13: 0 | BN13: 0 | BO13: 0 | BP13: 0 | BQ13: 0 | BR13: 0 | BS13: 0 | BT13: 0 | BU13: 0 | BV13: 0 | BW13: 0 | CV13: 0 | CW13: 0 | CX13: =ROUND(Y13*Source!I71,9) -> 1.18 | CY13: =AA13 -> 1297.23 | CZ13: =AE13 -> 1297.23 | DA13: =AI13 -> 1 | DB13: =ROUND(ROUND(AT13*CZ13,2),6) -> 3061.46 | DC13: =ROUND(ROUND(AT13*AG13,2),6) -> 0 | DF13: =ROUND(ROUND(AE13,2)*CX13,2) -> 1530.73 | DG13: =ROUND(ROUND(AF13,2)*CX13,2) -> 0 | DH13: =ROUND(ROUND(AG13,2)*CX13,2) -> 0 | DI13: =ROUND(ROUND(AH13,2)*CX13,2) -> 0 | DJ13: =DF13 -> 1530.73 | DK13: 0 | DM13: 0 | DO13: 0
A14: =ROW(Source!A72) -> 72 | B14: 60257733 | C14: 61620566 | D14: 58999254 | E14: 1080 | F14: 1 | G14: 1080 | H14: 1 | I14: 9999990008 | K14: Трудозатраты рабочих | L14: 1191 | N14: 1013 | O14: чел.-ч. | P14: чел.-ч. | Q14: 1 | W14: 0 | X14: 476480486 | Y14: =(AT14*1.1) -> 27.236 | AA14: 0 | AB14: 0 | AC14: 0 | AD14: 0 | AE14: 0 | AF14: 0 | AG14: 0 | AH14: 0 | AI14: 1 | AJ14: 1 | AK14: 1 | AL14: 1 | AM14: 5 | AN14: 0 | AO14: 1 | AP14: 1 | AQ14: 0 | AR14: 0 | AT14: 24.76 | AU14: *1,1 | AV14: 1 | AW14: 2 | AX14: 61620567 | AY14: 1 | AZ14: 0 | BA14: 15 | BB14: 0 | BC14: 0 | BD14: 0 | BE14: 0 | BF14: 0 | BG14: 0 | BH14: 0 | BI14: 0 | BJ14: 0 | BK14: 0 | BL14: 0 | BM14: 0 | BN14: 0 | BO14: 0 | BP14: 0 | BQ14: 0 | BR14: 0 | BS14: 0 | BT14: 0 | BU14: 0 | BV14: 0 | BW14: 0 | CU14: =ROUND(AT14*Source!I72*AH14*AL14,2) -> 0 | CV14: =ROUND(Y14*Source!I72,9) -> 13.618 | CW14: 0 | CX14: =ROUND(Y14*Source!I72,9) -> 13.618 | CY14: =AD14 -> 0 | CZ14: =AH14 -> 0 | DA14: =AL14 -> 1 | DB14: =ROUND((ROUND(AT14*CZ14,2)*1.1),6) -> 0 | DC14: =ROUND((ROUND(AT14*AG14,2)*1.1),6) -> 0 | DF14: =ROUND(ROUND(AE14,2)*CX14,2) -> 0 | DG14: =ROUND(ROUND(AF14,2)*CX14,2) -> 0 | DH14: =ROUND(ROUND(AG14,2)*CX14,2) -> 0 | DI14: =ROUND(ROUND(AH14,2)*CX14,2) -> 0 | DJ14: =DI14 -> 0 | DK14: 0 | DM14: 0 | DO14: 0
A15: =ROW(Source!A72) -> 72 | B15: 60257733 | C15: 61620566 | D15: 59070721 | E15: 1 | F15: 1 | G15: 1080 | H15: 2 | I15: 2.1-30-10 | J15: ТСН-2001.2. Доп. 68. п.1-30-10 (304101) | K15: Перфораторы, мощность до 800 Вт | L15: 1368 | N15: 1011 | O15: маш.-ч | P15: маш.-ч | Q15: 1 | W15: 0 | X15: 1387779639 | Y15: =(AT15*1.1) -> 2.684 | AA15: 0 | AB15: 6.98 | AC15: 0 | AD15: 0 | AE15: 0 | AF15: 0.77 | AG15: 0 | AH15: 0 | AI15: 1 | AJ15: 8.66 | AK15: 54.99 | AL15: 1 | AM15: 2 | AN15: 0 | AO15: 1 | AP15: 1 | AQ15: 0 | AR15: 0 | AT15: 2.44 | AU15: *1,1 | AV15: 0 | AW15: 2 | AX15: 61620568 | AY15: 1 | AZ15: 0 | BA15: 16 | BB15: 0 | BC15: 0 | BD15: 0 | BE15: 0 | BF15: 0 | BG15: 0 | BH15: 0 | BI15: 0 | BJ15: 0 | BK15: 0 | BL15: 0 | BM15: 0 | BN15: 0 | BO15: 0 | BP15: 0 | BQ15: 0 | BR15: 0 | BS15: 0 | BT15: 0 | BU15: 0 | BV15: 0 | BW15: 0 | CV15: 0 | CW15: =ROUND(Y15*Source!I72*DO15,9) -> 0 | CX15: =ROUND(Y15*Source!I72,9) -> 1.342 | CY15: =AB15 -> 6.98 | CZ15: =AF15 -> 0.77 | DA15: =AJ15 -> 8.66 | DB15: =ROUND((ROUND(AT15*CZ15,2)*1.1),6) -> 2.068 | DC15: =ROUND((ROUND(AT15*AG15,2)*1.1),6) -> 0 | DF15: =ROUND(ROUND(AE15,2)*CX15,2) -> 0 | DG15: =ROUND(ROUND(AF15*AJ15,2)*CX15,2) -> 8.95 | DH15: =ROUND(ROUND(AG15*AK15,2)*CX15,2) -> 0 | DI15: =ROUND(ROUND(AH15,2)*CX15,2) -> 0 | DJ15: =DG15 -> 8.95 | DK15: 0 | DM15: 0 | DO15: 0
A16: =ROW(Source!A72) -> 72 | B16: 60257733 | C16: 61620566 | D16: 59070754 | E16: 1 | F16: 1 | G16: 1080 | H16: 2 | I16: 2.1-30-56 | J16: ТСН-2001.2. Доп. 68. п.1-30-56 (309101) | K16: Шуруповерты | L16: 1368 | N16: 1011 | O16: маш.-ч | P16: маш.-ч | Q16: 1 | W16: 0 | X16: 1645565003 | Y16: =(AT16*1.1) -> 5.093 | AA16: 0 | AB16: 4.3 | AC16: 0 | AD16: 0 | AE16: 0 | AF16: 0.47 | AG16: 0 | AH16: 0 | AI16: 1 | AJ16: 8.74 | AK16: 54.99 | AL16: 1 | AM16: 2 | AN16: 0 | AO16: 1 | AP16: 1 | AQ16: 0 | AR16: 0 | AT16: 4.63 | AU16: *1,1 | AV16: 0 | AW16: 2 | AX16: 61620569 | AY16: 1 | AZ16: 0 | BA16: 17 | BB16: 0 | BC16: 0 | BD16: 0 | BE16: 0 | BF16: 0 | BG16: 0 | BH16: 0 | BI16: 0 | BJ16: 0 | BK16: 0 | BL16: 0 | BM16: 0 | BN16: 0 | BO16: 0 | BP16: 0 | BQ16: 0 | BR16: 0 | BS16: 0 | BT16: 0 | BU16: 0 | BV16: 0 | BW16: 0 | CV16: 0 | CW16: =ROUND(Y16*Source!I72*DO16,9) -> 0 | CX16: =ROUND(Y16*Source!I72,9) -> 2.5465 | CY16: =AB16 -> 4.3 | CZ16: =AF16 -> 0.47 | DA16: =AJ16 -> 8.74 | DB16: =ROUND((ROUND(AT16*CZ16,2)*1.1),6) -> 2.398 | DC16: =ROUND((ROUND(AT16*AG16,2)*1.1),6) -> 0 | DF16: =ROUND(ROUND(AE16,2)*CX16,2) -> 0 | DG16: =ROUND(ROUND(AF16*AJ16,2)*CX16,2) -> 10.47 | DH16: =ROUND(ROUND(AG16*AK16,2)*CX16,2) -> 0 | DI16: =ROUND(ROUND(AH16,2)*CX16,2) -> 0 | DJ16: =DG16 -> 10.47 | DK16: 0 | DM16: 0 | DO16: 0
A17: =ROW(Source!A72) -> 72 | B17: 60257733 | C17: 61620566 | D17: 59052975 | E17: 1 | F17: 1 | G17: 1080 | H17: 3 | I17: 1.12-5-371 | J17: ТСН-2001.1 Доп. 67, Р. 12, о. 5, поз. 371 | K17: Трубы электротехнические, гофрированные, из ПВХ, негорючие, с зондом, наружный диаметр 16 мм | L17: 1301 | N17: 1003 | O17: м | P17: м | Q17: 1 | W17: 0 | X17: 1184991115 | Y17: =AT17 -> 102 | AA17: 10.23 | AB17: 0 | AC17: 0 | AD17: 0 | AE17: 2.67 | AF17: 0 | AG17: 0 | AH17: 0 | AI17: 3.83 | AJ17: 1 | AK17: 1 | AL17: 1 | AM17: 0 | AN17: 0 | AO17: 0 | AP17: 1 | AQ17: 0 | AR17: 0 | AT17: 102 | AV17: 0 | AW17: 1 | AX17: -1 | AY17: 0 | AZ17: 0 | BB17: 0 | BC17: 0 | BD17: 0 | BE17: 0 | BF17: 0 | BG17: 0 | BH17: 0 | BI17: 0 | BJ17: 0 | BK17: 0 | BL17: 0 | BM17: 0 | BN17: 0 | BO17: 0 | BP17: 0 | BQ17: 0 | BR17: 0 | BS17: 0 | BT17: 0 | BU17: 0 | BV17: 0 | BW17: 0 | CV17: 0 | CW17: 0 | CX17: =ROUND(Y17*Source!I72,9) -> 51 | CY17: =AA17 -> 10.23 | CZ17: =AE17 -> 2.67 | DA17: =AI17 -> 3.83 | DB17: =ROUND(ROUND(AT17*CZ17,2),6) -> 272.34 | DC17: =ROUND(ROUND(AT17*AG17,2),6) -> 0 | DF17: =ROUND(ROUND(AE17*AI17,2)*CX17,2) -> 521.73 | DG17: =ROUND(ROUND(AF17,2)*CX17,2) -> 0 | DH17: =ROUND(ROUND(AG17,2)*CX17,2) -> 0 | DI17: =ROUND(ROUND(AH17,2)*CX17,2) -> 0 | DJ17: =DF17 -> 521.73 | DK17: 0 | DM17: 0 | DO17: 0
A18: =ROW(Source!A72) -> 72 | B18: 60257733 | C18: 61620566 | D18: 59058215 | E18: 1 | F18: 1 | G18: 1080 | H18: 3 | I18: 1.14-1-555 | J18: ТСН-2001.1 Доп. 73, Р. 14, о. 1, поз. 555 | K18: Скобы крепежные для радиочастотного коаксиального кабеля с номинальным диаметром по изоляции от 4 до 6 мм | L18: 1355 | N18: 1010 | O18: 100 шт. | P18: 100 шт. | Q18: 100 | W18: 0 | X18: -1288220709 | Y18: =AT18 -> 2.38 | AA18: 50.36 | AB18: 0 | AC18: 0 | AD18: 0 | AE18: 46.63 | AF18: 0 | AG18: 0 | AH18: 0 | AI18: 1.08 | AJ18: 1 | AK18: 1 | AL18: 1 | AM18: 0 | AN18: 0 | AO18: 0 | AP18: 1 | AQ18: 0 | AR18: 0 | AT18: 2.38 | AV18: 0 | AW18: 1 | AX18: -1 | AY18: 0 | AZ18: 0 | BB18: 0 | BC18: 0 | BD18: 0 | BE18: 0 | BF18: 0 | BG18: 0 | BH18: 0 | BI18: 0 | BJ18: 0 | BK18: 0 | BL18: 0 | BM18: 0 | BN18: 0 | BO18: 0 | BP18: 0 | BQ18: 0 | BR18: 0 | BS18: 0 | BT18: 0 | BU18: 0 | BV18: 0 | BW18: 0 | CV18: 0 | CW18: 0 | CX18: =ROUND(Y18*Source!I72,9) -> 1.19 | CY18: =AA18 -> 50.36 | CZ18: =AE18 -> 46.63 | DA18: =AI18 -> 1.08 | DB18: =ROUND(ROUND(AT18*CZ18,2),6) -> 110.98 | DC18: =ROUND(ROUND(AT18*AG18,2),6) -> 0 | DF18: =ROUND(ROUND(AE18*AI18,2)*CX18,2) -> 59.93 | DG18: =ROUND(ROUND(AF18,2)*CX18,2) -> 0 | DH18: =ROUND(ROUND(AG18,2)*CX18,2) -> 0 | DI18: =ROUND(ROUND(AH18,2)*CX18,2) -> 0 | DJ18: =DF18 -> 59.93 | DK18: 0 | DM18: 0 | DO18: 0
A19: =ROW(Source!A72) -> 72 | B19: 60257733 | C19: 61620566 | D19: 59062734 | E19: 1 | F19: 1 | G19: 1080 | H19: 3 | I19: 1.21-5-1180 | J19: ТСН-2001.1 Доп. 79, Р. 21, о. 5, поз. 1180 | K19: Бирка маркировочная для кабелей и проводов, типа У134 У3,5 | L19: 1356 | N19: 1010 | O19: 1000 шт. | P19: 1000 шт. | Q19: 1000 | W19: 0 | X19: -1221558404 | Y19: =AT19 -> 0.031 | AA19: 1602.49 | AB19: 0 | AC19: 0 | AD19: 0 | AE19: 226.66 | AF19: 0 | AG19: 0 | AH19: 0 | AI19: 7.07 | AJ19: 1 | AK19: 1 | AL19: 1 | AM19: 2 | AN19: 0 | AO19: 1 | AP19: 1 | AQ19: 0 | AR19: 0 | AT19: 0.031 | AV19: 0 | AW19: 2 | AX19: 61620570 | AY19: 1 | AZ19: 0 | BA19: 18 | BB19: 0 | BC19: 0 | BD19: 0 | BE19: 0 | BF19: 0 | BG19: 0 | BH19: 0 | BI19: 0 | BJ19: 0 | BK19: 0 | BL19: 0 | BM19: 0 | BN19: 0 | BO19: 0 | BP19: 0 | BQ19: 0 | BR19: 0 | BS19: 0 | BT19: 0 | BU19: 0 | BV19: 0 | BW19: 0 | CV19: 0 | CW19: 0 | CX19: =ROUND(Y19*Source!I72,9) -> 0.0155 | CY19: =AA19 -> 1602.49 | CZ19: =AE19 -> 226.66 | DA19: =AI19 -> 7.07 | DB19: =ROUND(ROUND(AT19*CZ19,2),6) -> 7.03 | DC19: =ROUND(ROUND(AT19*AG19,2),6) -> 0 | DF19: =ROUND(ROUND(AE19*AI19,2)*CX19,2) -> 24.84 | DG19: =ROUND(ROUND(AF19,2)*CX19,2) -> 0 | DH19: =ROUND(ROUND(AG19,2)*CX19,2) -> 0 | DI19: =ROUND(ROUND(AH19,2)*CX19,2) -> 0 | DJ19: =DF19 -> 24.84 | DK19: 0 | DM19: 0 | DO19: 0
A20: =ROW(Source!A72) -> 72 | B20: 60257733 | C20: 61620566 | D20: 59062508 | E20: 1 | F20: 1 | G20: 1080 | H20: 3 | I20: 1.21-5-926 | J20: ТСН-2001.1 Доп. 67, Р. 21, о. 5, поз. 926 | K20: Хомут (стяжка) кабельный из полиамида, размеры 3,6х200 мм | L20: 1355 | N20: 1010 | O20: 100 шт. | P20: 100 шт. | Q20: 100 | W20: 0 | X20: -210805237 | Y20: =AT20 -> 0.315 | AA20: 105.5 | AB20: 0 | AC20: 0 | AD20: 0 | AE20: 26.71 | AF20: 0 | AG20: 0 | AH20: 0 | AI20: 3.95 | AJ20: 1 | AK20: 1 | AL20: 1 | AM20: 2 | AN20: 0 | AO20: 1 | AP20: 1 | AQ20: 0 | AR20: 0 | AT20: 0.315 | AV20: 0 | AW20: 2 | AX20: 61620571 | AY20: 1 | AZ20: 0 | BA20: 19 | BB20: 0 | BC20: 0 | BD20: 0 | BE20: 0 | BF20: 0 | BG20: 0 | BH20: 0 | BI20: 0 | BJ20: 0 | BK20: 0 | BL20: 0 | BM20: 0 | BN20: 0 | BO20: 0 | BP20: 0 | BQ20: 0 | BR20: 0 | BS20: 0 | BT20: 0 | BU20: 0 | BV20: 0 | BW20: 0 | CV20: 0 | CW20: 0 | CX20: =ROUND(Y20*Source!I72,9) -> 0.1575 | CY20: =AA20 -> 105.5 | CZ20: =AE20 -> 26.71 | DA20: =AI20 -> 3.95 | DB20: =ROUND(ROUND(AT20*CZ20,2),6) -> 8.41 | DC20: =ROUND(ROUND(AT20*AG20,2),6) -> 0 | DF20: =ROUND(ROUND(AE20*AI20,2)*CX20,2) -> 16.62 | DG20: =ROUND(ROUND(AF20,2)*CX20,2) -> 0 | DH20: =ROUND(ROUND(AG20,2)*CX20,2) -> 0 | DI20: =ROUND(ROUND(AH20,2)*CX20,2) -> 0 | DJ20: =DF20 -> 16.62 | DK20: 0 | DM20: 0 | DO20: 0
A21: =ROW(Source!A72) -> 72 | B21: 60257733 | C21: 61620566 | D21: 59049364 | E21: 1 | F21: 1 | G21: 1080 | H21: 3 | I21: 1.7-3-122 | J21: ТСН-2001.1 Доп. 79, Р. 7, о. 3, поз. 122 | K21: Бур с наконечником из твердого сплава, с хвостовиком SDS-plus, диаметр 10 мм, длина 260 мм | L21: 1354 | N21: 1010 | O21: шт. | P21: шт. | Q21: 1 | W21: 0 | X21: 309799599 | Y21: =AT21 -> 0.28 | AA21: 165.81 | AB21: 0 | AC21: 0 | AD21: 0 | AE21: 14.22 | AF21: 0 | AG21: 0 | AH21: 0 | AI21: 11.66 | AJ21: 1 | AK21: 1 | AL21: 1 | AM21: 2 | AN21: 0 | AO21: 1 | AP21: 1 | AQ21: 0 | AR21: 0 | AT21: 0.28 | AV21: 0 | AW21: 2 | AX21: 61620572 | AY21: 1 | AZ21: 0 | BA21: 20 | BB21: 0 | BC21: 0 | BD21: 0 | BE21: 0 | BF21: 0 | BG21: 0 | BH21: 0 | BI21: 0 | BJ21: 0 | BK21: 0 | BL21: 0 | BM21: 0 | BN21: 0 | BO21: 0 | BP21: 0 | BQ21: 0 | BR21: 0 | BS21: 0 | BT21: 0 | BU21: 0 | BV21: 0 | BW21: 0 | CV21: 0 | CW21: 0 | CX21: =ROUND(Y21*Source!I72,9) -> 0.14 | CY21: =AA21 -> 165.81 | CZ21: =AE21 -> 14.22 | DA21: =AI21 -> 11.66 | DB21: =ROUND(ROUND(AT21*CZ21,2),6) -> 3.98 | DC21: =ROUND(ROUND(AT21*AG21,2),6) -> 0 | DF21: =ROUND(ROUND(AE21*AI21,2)*CX21,2) -> 23.21 | DG21: =ROUND(ROUND(AF21,2)*CX21,2) -> 0 | DH21: =ROUND(ROUND(AG21,2)*CX21,2) -> 0 | DI21: =ROUND(ROUND(AH21,2)*CX21,2) -> 0 | DJ21: =DF21 -> 23.21 | DK21: 0 | DM21: 0 | DO21: 0
A22: =ROW(Source!A72) -> 72 | B22: 60257733 | C22: 61620566 | D22: 59049443 | E22: 1 | F22: 1 | G22: 1080 | H22: 3 | I22: 1.7-5-131 | J22: ТСН-2001.1 Доп. 79, Р. 7, о. 5, поз. 131 | K22: Анкер забивной расклинивающийся из оцинкованной стали, с внутренней резьбой М12, длина 25 мм | L22: 1355 | N22: 1010 | O22: 100 шт. | P22: 100 шт. | Q22: 100 | W22: 0 | X22: 1852901932 | Y22: =AT22 -> 2.36 | AA22: 6745.6 | AB22: 0 | AC22: 0 | AD22: 0 | AE22: 1297.23 | AF22: 0 | AG22: 0 | AH22: 0 | AI22: 5.2 | AJ22: 1 | AK22: 1 | AL22: 1 | AM22: 0 | AN22: 0 | AO22: 0 | AP22: 1 | AQ22: 0 | AR22: 0 | AT22: 2.36 | AV22: 0 | AW22: 1 | AX22: -1 | AY22: 0 | AZ22: 0 | BB22: 0 | BC22: 0 | BD22: 0 | BE22: 0 | BF22: 0 | BG22: 0 | BH22: 0 | BI22: 0 | BJ22: 0 | BK22: 0 | BL22: 0 | BM22: 0 | BN22: 0 | BO22: 0 | BP22: 0 | BQ22: 0 | BR22: 0 | BS22: 0 | BT22: 0 | BU22: 0 | BV22: 0 | BW22: 0 | CV22: 0 | CW22: 0 | CX22: =ROUND(Y22*Source!I72,9) -> 1.18 | CY22: =AA22 -> 6745.6 | CZ22: =AE22 -> 1297.23 | DA22: =AI22 -> 5.2 | DB22: =ROUND(ROUND(AT22*CZ22,2),6) -> 3061.46 | DC22: =ROUND(ROUND(AT22*AG22,2),6) -> 0 | DF22: =ROUND(ROUND(AE22*AI22,2)*CX22,2) -> 7959.81 | DG22: =ROUND(ROUND(AF22,2)*CX22,2) -> 0 | DH22: =ROUND(ROUND(AG22,2)*CX22,2) -> 0 | DI22: =ROUND(ROUND(AH22,2)*CX22,2) -> 0 | DJ22: =DF22 -> 7959.81 | DK22: 0 | DM22: 0 | DO22: 0
A23: =ROW(Source!A79) -> 79 | B23: 60257736 | C23: 61620608 | D23: 58999254 | E23: 1080 | F23: 1 | G23: 1080 | H23: 1 | I23: 9999990008 | K23: Трудозатраты рабочих | L23: 1191 | N23: 1013 | O23: чел.-ч. | P23: чел.-ч. | Q23: 1 | W23: 0 | X23: 476480486 | Y23: =(AT23*1.1) -> 5.819 | AA23: 0 | AB23: 0 | AC23: 0 | AD23: 0 | AE23: 0 | AF23: 0 | AG23: 0 | AH23: 0 | AI23: 1 | AJ23: 1 | AK23: 1 | AL23: 1 | AM23: -2 | AN23: 0 | AO23: 1 | AP23: 1 | AQ23: 0 | AR23: 0 | AT23: 5.29 | AU23: *1,1 | AV23: 1 | AW23: 2 | AX23: 61620614 | AY23: 1 | AZ23: 0 | BA23: 25 | BB23: 0 | BC23: 0 | BD23: 0 | BE23: 0 | BF23: 0 | BG23: 0 | BH23: 0 | BI23: 0 | BJ23: 0 | BK23: 0 | BL23: 0 | BM23: 0 | BN23: 0 | BO23: 0 | BP23: 0 | BQ23: 0 | BR23: 0 | BS23: 0 | BT23: 0 | BU23: 0 | BV23: 0 | BW23: 0 | CU23: =ROUND(AT23*Source!I79*AH23*AL23,2) -> 0 | CV23: =ROUND(Y23*Source!I79,9) -> 2.9095 | CW23: 0 | CX23: =ROUND(Y23*Source!I79,9) -> 2.9095 | CY23: =AD23 -> 0 | CZ23: =AH23 -> 0 | DA23: =AL23 -> 1 | DB23: =ROUND((ROUND(AT23*CZ23,2)*1.1),6) -> 0 | DC23: =ROUND((ROUND(AT23*AG23,2)*1.1),6) -> 0 | DF23: =ROUND(ROUND(AE23,2)*CX23,2) -> 0 | DG23: =ROUND(ROUND(AF23,2)*CX23,2) -> 0 | DH23: =ROUND(ROUND(AG23,2)*CX23,2) -> 0 | DI23: =ROUND(ROUND(AH23,2)*CX23,2) -> 0 | DJ23: =DI23 -> 0 | DK23: 0 | DM23: 0 | DO23: 0
A24: =ROW(Source!A79) -> 79 | B24: 60257736 | C24: 61620608 | D24: 59070669 | E24: 1 | F24: 1 | G24: 1080 | H24: 2 | I24: 2.1-18-7 | J24: ТСН-2001.2. Доп. 68. п.1-18-7 (183001) | K24: Автомобили грузовые бортовые, грузоподъемность до 5 т | L24: 1368 | N24: 1011 | O24: маш.-ч | P24: маш.-ч | Q24: 1 | W24: 0 | X24: -1985943078 | Y24: =(AT24*1.1) -> 0.011 | AA24: 0 | AB24: 87.01 | AC24: 13.21 | AD24: 0 | AE24: 0 | AF24: 83.1 | AG24: 12.62 | AH24: 0 | AI24: 1 | AJ24: 1 | AK24: 1 | AL24: 1 | AM24: -2 | AN24: 0 | AO24: 1 | AP24: 1 | AQ24: 0 | AR24: 0 | AT24: 0.01 | AU24: *1,1 | AV24: 0 | AW24: 2 | AX24: 61620615 | AY24: 1 | AZ24: 0 | BA24: 26 | BB24: 0 | BC24: 0 | BD24: 0 | BE24: 0 | BF24: 0 | BG24: 0 | BH24: 0 | BI24: 0 | BJ24: 0 | BK24: 0 | BL24: 0 | BM24: 0 | BN24: 0 | BO24: 0 | BP24: 0 | BQ24: 0 | BR24: 0 | BS24: 0 | BT24: 0 | BU24: 0 | BV24: 0 | BW24: 0 | CV24: 0 | CW24: =ROUND(Y24*Source!I79*DO24,9) -> 0.06941 | CX24: =ROUND(Y24*Source!I79,9) -> 0.0055 | CY24: =AB24 -> 87.01 | CZ24: =AF24 -> 83.1 | DA24: =AJ24 -> 1 | DB24: =ROUND((ROUND(AT24*CZ24,2)*1.1),6) -> 0.913 | DC24: =ROUND((ROUND(AT24*AG24,2)*1.1),6) -> 0.143 | DF24: =ROUND(ROUND(AE24,2)*CX24,2) -> 0 | DG24: =ROUND(ROUND(AF24,2)*CX24,2) -> 0.46 | DH24: =ROUND(ROUND(AG24,2)*CX24,2) -> 0.07 | DI24: =ROUND(ROUND(AH24,2)*CX24,2) -> 0 | DJ24: =DG24 -> 0.46 | DK24: 0 | DL24: 9999990009 | DM24: 0 | DN24: чел.-ч. | DO24: 12.62
A25: =ROW(Source!A79) -> 79 | B25: 60257736 | C25: 61620608 | D25: 59069905 | E25: 1 | F25: 1 | G25: 1080 | H25: 2 | I25: 2.1-3-38 | J25: ТСН-2001.2. Доп. 68. п.1-3-38 (032009) | K25: Краны на автомобильном ходу, грузоподъемность до 16 т | L25: 1368 | N25: 1011 | O25: маш.-ч | P25: маш.-ч | Q25: 1 | W25: 0 | X25: 1087580389 | Y25: =(AT25*1.1) -> 0.011 | AA25: 0 | AB25: 187.59 | AC25: 17.73 | AD25: 0 | AE25: 0 | AF25: 179.17 | AG25: 16.93 | AH25: 0 | AI25: 1 | AJ25: 1 | AK25: 1 | AL25: 1 | AM25: -2 | AN25: 0 | AO25: 1 | AP25: 1 | AQ25: 0 | AR25: 0 | AT25: 0.01 | AU25: *1,1 | AV25: 0 | AW25: 2 | AX25: 61620616 | AY25: 1 | AZ25: 0 | BA25: 27 | BB25: 0 | BC25: 0 | BD25: 0 | BE25: 0 | BF25: 0 | BG25: 0 | BH25: 0 | BI25: 0 | BJ25: 0 | BK25: 0 | BL25: 0 | BM25: 0 | BN25: 0 | BO25: 0 | BP25: 0 | BQ25: 0 | BR25: 0 | BS25: 0 | BT25: 0 | BU25: 0 | BV25: 0 | BW25: 0 | CV25: 0 | CW25: =ROUND(Y25*Source!I79*DO25,9) -> 0.093115 | CX25: =ROUND(Y25*Source!I79,9) -> 0.0055 | CY25: =AB25 -> 187.59 | CZ25: =AF25 -> 179.17 | DA25: =AJ25 -> 1 | DB25: =ROUND((ROUND(AT25*CZ25,2)*1.1),6) -> 1.969 | DC25: =ROUND((ROUND(AT25*AG25,2)*1.1),6) -> 0.187 | DF25: =ROUND(ROUND(AE25,2)*CX25,2) -> 0 | DG25: =ROUND(ROUND(AF25,2)*CX25,2) -> 0.99 | DH25: =ROUND(ROUND(AG25,2)*CX25,2) -> 0.09 | DI25: =ROUND(ROUND(AH25,2)*CX25,2) -> 0 | DJ25: =DG25 -> 0.99 | DK25: 0 | DL25: 9999990009 | DM25: 0 | DN25: чел.-ч. | DO25: 16.93
A26: =ROW(Source!A79) -> 79 | B26: 60257736 | C26: 61620608 | D26: 59062690 | E26: 1 | F26: 1 | G26: 1080 | H26: 3 | I26: 1.21-5-1134 | J26: ТСН-2001.1 Доп. 70, Р. 21, о. 5, поз. 1134 | K26: Хомут (стяжка) кабельный из полиамида, размеры 4,8х300 мм | L26: 1355 | N26: 1010 | O26: 100 шт. | P26: 100 шт. | Q26: 100 | W26: 0 | X26: 433898453 | Y26: =AT26 -> 2.1094 | AA26: 59.47 | AB26: 0 | AC26: 0 | AD26: 0 | AE26: 59.47 | AF26: 0 | AG26: 0 | AH26: 0 | AI26: 1 | AJ26: 1 | AK26: 1 | AL26: 1 | AM26: -2 | AN26: 0 | AO26: 1 | AP26: 1 | AQ26: 0 | AR26: 0 | AT26: 2.1094 | AV26: 0 | AW26: 2 | AX26: 61620617 | AY26: 1 | AZ26: 0 | BA26: 28 | BB26: 0 | BC26: 0 | BD26: 0 | BE26: 0 | BF26: 0 | BG26: 0 | BH26: 0 | BI26: 0 | BJ26: 0 | BK26: 0 | BL26: 0 | BM26: 0 | BN26: 0 | BO26: 0 | BP26: 0 | BQ26: 0 | BR26: 0 | BS26: 0 | BT26: 0 | BU26: 0 | BV26: 0 | BW26: 0 | CV26: 0 | CW26: 0 | CX26: =ROUND(Y26*Source!I79,9) -> 1.0547 | CY26: =AA26 -> 59.47 | CZ26: =AE26 -> 59.47 | DA26: =AI26 -> 1 | DB26: =ROUND(ROUND(AT26*CZ26,2),6) -> 125.45 | DC26: =ROUND(ROUND(AT26*AG26,2),6) -> 0 | DF26: =ROUND(ROUND(AE26,2)*CX26,2) -> 62.72 | DG26: =ROUND(ROUND(AF26,2)*CX26,2) -> 0 | DH26: =ROUND(ROUND(AG26,2)*CX26,2) -> 0 | DI26: =ROUND(ROUND(AH26,2)*CX26,2) -> 0 | DJ26: =DF26 -> 62.72 | DK26: 0 | DM26: 0 | DO26: 0
A27: =ROW(Source!A79) -> 79 | B27: 60257736 | C27: 61620608 | D27: 59062735 | E27: 1 | F27: 1 | G27: 1080 | H27: 3 | I27: 1.21-5-1181 | J27: ТСН-2001.1 Доп. 79, Р. 21, о. 5, поз. 1181 | K27: Бирка маркировочная для кабелей и проводов, типа У153 У3,5 | L27: 1356 | N27: 1010 | O27: 1000 шт. | P27: 1000 шт. | Q27: 1000 | W27: 0 | X27: 537260159 | Y27: =AT27 -> 0.0069 | AA27: 56.16 | AB27: 0 | AC27: 0 | AD27: 0 | AE27: 56.16 | AF27: 0 | AG27: 0 | AH27: 0 | AI27: 1 | AJ27: 1 | AK27: 1 | AL27: 1 | AM27: -2 | AN27: 0 | AO27: 1 | AP27: 1 | AQ27: 0 | AR27: 0 | AT27: 0.0069 | AV27: 0 | AW27: 2 | AX27: 61620618 | AY27: 1 | AZ27: 0 | BA27: 29 | BB27: 0 | BC27: 0 | BD27: 0 | BE27: 0 | BF27: 0 | BG27: 0 | BH27: 0 | BI27: 0 | BJ27: 0 | BK27: 0 | BL27: 0 | BM27: 0 | BN27: 0 | BO27: 0 | BP27: 0 | BQ27: 0 | BR27: 0 | BS27: 0 | BT27: 0 | BU27: 0 | BV27: 0 | BW27: 0 | CV27: 0 | CW27: 0 | CX27: =ROUND(Y27*Source!I79,9) -> 0.00345 | CY27: =AA27 -> 56.16 | CZ27: =AE27 -> 56.16 | DA27: =AI27 -> 1 | DB27: =ROUND(ROUND(AT27*CZ27,2),6) -> 0.39 | DC27: =ROUND(ROUND(AT27*AG27,2),6) -> 0 | DF27: =ROUND(ROUND(AE27,2)*CX27,2) -> 0.19 | DG27: =ROUND(ROUND(AF27,2)*CX27,2) -> 0 | DH27: =ROUND(ROUND(AG27,2)*CX27,2) -> 0 | DI27: =ROUND(ROUND(AH27,2)*CX27,2) -> 0 | DJ27: =DF27 -> 0.19 | DK27: 0 | DM27: 0 | DO27: 0
A28: =ROW(Source!A80) -> 80 | B28: 60257733 | C28: 61620608 | D28: 58999254 | E28: 1080 | F28: 1 | G28: 1080 | H28: 1 | I28: 9999990008 | K28: Трудозатраты рабочих | L28: 1191 | N28: 1013 | O28: чел.-ч. | P28: чел.-ч. | Q28: 1 | W28: 0 | X28: 476480486 | Y28: =(AT28*1.1) -> 5.819 | AA28: 0 | AB28: 0 | AC28: 0 | AD28: 0 | AE28: 0 | AF28: 0 | AG28: 0 | AH28: 0 | AI28: 1 | AJ28: 1 | AK28: 1 | AL28: 1 | AM28: 5 | AN28: 0 | AO28: 1 | AP28: 1 | AQ28: 0 | AR28: 0 | AT28: 5.29 | AU28: *1,1 | AV28: 1 | AW28: 2 | AX28: 61620614 | AY28: 1 | AZ28: 0 | BA28: 31 | BB28: 0 | BC28: 0 | BD28: 0 | BE28: 0 | BF28: 0 | BG28: 0 | BH28: 0 | BI28: 0 | BJ28: 0 | BK28: 0 | BL28: 0 | BM28: 0 | BN28: 0 | BO28: 0 | BP28: 0 | BQ28: 0 | BR28: 0 | BS28: 0 | BT28: 0 | BU28: 0 | BV28: 0 | BW28: 0 | CU28: =ROUND(AT28*Source!I80*AH28*AL28,2) -> 0 | CV28: =ROUND(Y28*Source!I80,9) -> 2.9095 | CW28: 0 | CX28: =ROUND(Y28*Source!I80,9) -> 2.9095 | CY28: =AD28 -> 0 | CZ28: =AH28 -> 0 | DA28: =AL28 -> 1 | DB28: =ROUND((ROUND(AT28*CZ28,2)*1.1),6) -> 0 | DC28: =ROUND((ROUND(AT28*AG28,2)*1.1),6) -> 0 | DF28: =ROUND(ROUND(AE28,2)*CX28,2) -> 0 | DG28: =ROUND(ROUND(AF28,2)*CX28,2) -> 0 | DH28: =ROUND(ROUND(AG28,2)*CX28,2) -> 0 | DI28: =ROUND(ROUND(AH28,2)*CX28,2) -> 0 | DJ28: =DI28 -> 0 | DK28: 0 | DM28: 0 | DO28: 0
A29: =ROW(Source!A80) -> 80 | B29: 60257733 | C29: 61620608 | D29: 59070669 | E29: 1 | F29: 1 | G29: 1080 | H29: 2 | I29: 2.1-18-7 | J29: ТСН-2001.2. Доп. 68. п.1-18-7 (183001) | K29: Автомобили грузовые бортовые, грузоподъемность до 5 т | L29: 1368 | N29: 1011 | O29: маш.-ч | P29: маш.-ч | Q29: 1 | W29: 0 | X29: -1985943078 | Y29: =(AT29*1.1) -> 0.011 | AA29: 0 | AB29: 1418.19 | AC29: 726.59 | AD29: 0 | AE29: 0 | AF29: 83.1 | AG29: 12.62 | AH29: 0 | AI29: 1 | AJ29: 16.3 | AK29: 54.99 | AL29: 1 | AM29: 2 | AN29: 0 | AO29: 1 | AP29: 1 | AQ29: 0 | AR29: 0 | AT29: 0.01 | AU29: *1,1 | AV29: 0 | AW29: 2 | AX29: 61620615 | AY29: 1 | AZ29: 0 | BA29: 32 | BB29: 0 | BC29: 0 | BD29: 0 | BE29: 0 | BF29: 0 | BG29: 0 | BH29: 0 | BI29: 0 | BJ29: 0 | BK29: 0 | BL29: 0 | BM29: 0 | BN29: 0 | BO29: 0 | BP29: 0 | BQ29: 0 | BR29: 0 | BS29: 0 | BT29: 0 | BU29: 0 | BV29: 0 | BW29: 0 | CV29: 0 | CW29: =ROUND(Y29*Source!I80*DO29,9) -> 0.06941 | CX29: =ROUND(Y29*Source!I80,9) -> 0.0055 | CY29: =AB29 -> 1418.19 | CZ29: =AF29 -> 83.1 | DA29: =AJ29 -> 16.3 | DB29: =ROUND((ROUND(AT29*CZ29,2)*1.1),6) -> 0.913 | DC29: =ROUND((ROUND(AT29*AG29,2)*1.1),6) -> 0.143 | DF29: =ROUND(ROUND(AE29,2)*CX29,2) -> 0 | DG29: =ROUND(ROUND(AF29*AJ29,2)*CX29,2) -> 7.45 | DH29: =ROUND(ROUND(AG29*AK29,2)*CX29,2) -> 3.82 | DI29: =ROUND(ROUND(AH29,2)*CX29,2) -> 0 | DJ29: =DG29 -> 7.45 | DK29: 0 | DL29: 9999990009 | DM29: 0 | DN29: чел.-ч. | DO29: 12.62
A30: =ROW(Source!A80) -> 80 | B30: 60257733 | C30: 61620608 | D30: 59069905 | E30: 1 | F30: 1 | G30: 1080 | H30: 2 | I30: 2.1-3-38 | J30: ТСН-2001.2. Доп. 68. п.1-3-38 (032009) | K30: Краны на автомобильном ходу, грузоподъемность до 16 т | L30: 1368 | N30: 1011 | O30: маш.-ч | P30: маш.-ч | Q30: 1 | W30: 0 | X30: 1087580389 | Y30: =(AT30*1.1) -> 0.011 | AA30: 0 | AB30: 2579.38 | AC30: 974.74 | AD30: 0 | AE30: 0 | AF30: 179.17 | AG30: 16.93 | AH30: 0 | AI30: 1 | AJ30: 13.75 | AK30: 54.99 | AL30: 1 | AM30: 2 | AN30: 0 | AO30: 1 | AP30: 1 | AQ30: 0 | AR30: 0 | AT30: 0.01 | AU30: *1,1 | AV30: 0 | AW30: 2 | AX30: 61620616 | AY30: 1 | AZ30: 0 | BA30: 33 | BB30: 0 | BC30: 0 | BD30: 0 | BE30: 0 | BF30: 0 | BG30: 0 | BH30: 0 | BI30: 0 | BJ30: 0 | BK30: 0 | BL30: 0 | BM30: 0 | BN30: 0 | BO30: 0 | BP30: 0 | BQ30: 0 | BR30: 0 | BS30: 0 | BT30: 0 | BU30: 0 | BV30: 0 | BW30: 0 | CV30: 0 | CW30: =ROUND(Y30*Source!I80*DO30,9) -> 0.093115 | CX30: =ROUND(Y30*Source!I80,9) -> 0.0055 | CY30: =AB30 -> 2579.38 | CZ30: =AF30 -> 179.17 | DA30: =AJ30 -> 13.75 | DB30: =ROUND((ROUND(AT30*CZ30,2)*1.1),6) -> 1.969 | DC30: =ROUND((ROUND(AT30*AG30,2)*1.1),6) -> 0.187 | DF30: =ROUND(ROUND(AE30,2)*CX30,2) -> 0 | DG30: =ROUND(ROUND(AF30*AJ30,2)*CX30,2) -> 13.55 | DH30: =ROUND(ROUND(AG30*AK30,2)*CX30,2) -> 5.12 | DI30: =ROUND(ROUND(AH30,2)*CX30,2) -> 0 | DJ30: =DG30 -> 13.55 | DK30: 0 | DL30: 9999990009 | DM30: 0 | DN30: чел.-ч. | DO30: 16.93
A31: =ROW(Source!A80) -> 80 | B31: 60257733 | C31: 61620608 | D31: 59062690 | E31: 1 | F31: 1 | G31: 1080 | H31: 3 | I31: 1.21-5-1134 | J31: ТСН-2001.1 Доп. 70, Р. 21, о. 5, поз. 1134 | K31: Хомут (стяжка) кабельный из полиамида, размеры 4,8х300 мм | L31: 1355 | N31: 1010 | O31: 100 шт. | P31: 100 шт. | Q31: 100 | W31: 0 | X31: 433898453 | Y31: =AT31 -> 2.1094 | AA31: 233.72 | AB31: 0 | AC31: 0 | AD31: 0 | AE31: 59.47 | AF31: 0 | AG31: 0 | AH31: 0 | AI31: 3.93 | AJ31: 1 | AK31: 1 | AL31: 1 | AM31: 2 | AN31: 0 | AO31: 1 | AP31: 1 | AQ31: 0 | AR31: 0 | AT31: 2.1094 | AV31: 0 | AW31: 2 | AX31: 61620617 | AY31: 1 | AZ31: 0 | BA31: 34 | BB31: 0 | BC31: 0 | BD31: 0 | BE31: 0 | BF31: 0 | BG31: 0 | BH31: 0 | BI31: 0 | BJ31: 0 | BK31: 0 | BL31: 0 | BM31: 0 | BN31: 0 | BO31: 0 | BP31: 0 | BQ31: 0 | BR31: 0 | BS31: 0 | BT31: 0 | BU31: 0 | BV31: 0 | BW31: 0 | CV31: 0 | CW31: 0 | CX31: =ROUND(Y31*Source!I80,9) -> 1.0547 | CY31: =AA31 -> 233.72 | CZ31: =AE31 -> 59.47 | DA31: =AI31 -> 3.93 | DB31: =ROUND(ROUND(AT31*CZ31,2),6) -> 125.45 | DC31: =ROUND(ROUND(AT31*AG31,2),6) -> 0 | DF31: =ROUND(ROUND(AE31*AI31,2)*CX31,2) -> 246.5 | DG31: =ROUND(ROUND(AF31,2)*CX31,2) -> 0 | DH31: =ROUND(ROUND(AG31,2)*CX31,2) -> 0 | DI31: =ROUND(ROUND(AH31,2)*CX31,2) -> 0 | DJ31: =DF31 -> 246.5 | DK31: 0 | DM31: 0 | DO31: 0
A32: =ROW(Source!A80) -> 80 | B32: 60257733 | C32: 61620608 | D32: 59062735 | E32: 1 | F32: 1 | G32: 1080 | H32: 3 | I32: 1.21-5-1181 | J32: ТСН-2001.1 Доп. 79, Р. 21, о. 5, поз. 1181 | K32: Бирка маркировочная для кабелей и проводов, типа У153 У3,5 | L32: 1356 | N32: 1010 | O32: 1000 шт. | P32: 1000 шт. | Q32: 1000 | W32: 0 | X32: 537260159 | Y32: =AT32 -> 0.0069 | AA32: 672.24 | AB32: 0 | AC32: 0 | AD32: 0 | AE32: 56.16 | AF32: 0 | AG32: 0 | AH32: 0 | AI32: 11.97 | AJ32: 1 | AK32: 1 | AL32: 1 | AM32: 2 | AN32: 0 | AO32: 1 | AP32: 1 | AQ32: 0 | AR32: 0 | AT32: 0.0069 | AV32: 0 | AW32: 2 | AX32: 61620618 | AY32: 1 | AZ32: 0 | BA32: 35 | BB32: 0 | BC32: 0 | BD32: 0 | BE32: 0 | BF32: 0 | BG32: 0 | BH32: 0 | BI32: 0 | BJ32: 0 | BK32: 0 | BL32: 0 | BM32: 0 | BN32: 0 | BO32: 0 | BP32: 0 | BQ32: 0 | BR32: 0 | BS32: 0 | BT32: 0 | BU32: 0 | BV32: 0 | BW32: 0 | CV32: 0 | CW32: 0 | CX32: =ROUND(Y32*Source!I80,9) -> 0.00345 | CY32: =AA32 -> 672.24 | CZ32: =AE32 -> 56.16 | DA32: =AI32 -> 11.97 | DB32: =ROUND(ROUND(AT32*CZ32,2),6) -> 0.39 | DC32: =ROUND(ROUND(AT32*AG32,2),6) -> 0 | DF32: =ROUND(ROUND(AE32*AI32,2)*CX32,2) -> 2.32 | DG32: =ROUND(ROUND(AF32,2)*CX32,2) -> 0 | DH32: =ROUND(ROUND(AG32,2)*CX32,2) -> 0 | DI32: =ROUND(ROUND(AH32,2)*CX32,2) -> 0 | DJ32: =DF32 -> 2.32 | DK32: 0 | DM32: 0 | DO32: 0

Sheet EtalonRes
A1: =ROW(Source!A28) -> 28 | B1: 60257963 | C1: 60257850 | D1: 58999254 | E1: 1080 | F1: 1 | G1: 1080 | H1: 1 | I1: 9999990008 | K1: Трудозатраты рабочих | L1: 1191 | N1: 1013 | O1: чел.-ч. | P1: чел.-ч. | Q1: 1 | X1: 3 | Y1: 0 | Z1: 0 | AA1: 0 | AB1: 0 | AC1: 0 | AD1: 1 | AE1: 1 | AF1: *1,1 | AG1: 3.3 | AH1: 2 | AI1: 60257851 | AJ1: 1 | AK1: 0 | AL1: 0 | AM1: 0 | AN1: 0 | AO1: 0 | AP1: 0 | AQ1: 0 | AR1: 0
A2: =ROW(Source!A29) -> 29 | B2: 60257963 | C2: 60257850 | D2: 58999254 | E2: 1080 | F2: 1 | G2: 1080 | H2: 1 | I2: 9999990008 | K2: Трудозатраты рабочих | L2: 1191 | N2: 1013 | O2: чел.-ч. | P2: чел.-ч. | Q2: 1 | X2: 3 | Y2: 0 | Z2: 0 | AA2: 0 | AB2: 0 | AC2: 0 | AD2: 1 | AE2: 1 | AF2: *1,1 | AG2: 3.3 | AH2: 2 | AI2: 60257851 | AJ2: 2 | AK2: 0 | AL2: 0 | AM2: 0 | AN2: 0 | AO2: 0 | AP2: 0 | AQ2: 0 | AR2: 0
A3: =ROW(Source!A32) -> 32 | B3: 60257964 | C3: 60257854 | D3: 58999254 | E3: 1080 | F3: 1 | G3: 1080 | H3: 1 | I3: 9999990008 | K3: Трудозатраты рабочих | L3: 1191 | N3: 1013 | O3: чел.-ч. | P3: чел.-ч. | Q3: 1 | X3: 2 | Y3: 0 | Z3: 0 | AA3: 0 | AB3: 0 | AC3: 0 | AD3: 1 | AE3: 1 | AF3: *1,1 | AG3: 2.2 | AH3: 2 | AI3: 60257855 | AJ3: 3 | AK3: 0 | AL3: 0 | AM3: 0 | AN3: 0 | AO3: 0 | AP3: 0 | AQ3: 0 | AR3: 0
A4: =ROW(Source!A33) -> 33 | B4: 60257964 | C4: 60257854 | D4: 58999254 | E4: 1080 | F4: 1 | G4: 1080 | H4: 1 | I4: 9999990008 | K4: Трудозатраты рабочих | L4: 1191 | N4: 1013 | O4: чел.-ч. | P4: чел.-ч. | Q4: 1 | X4: 2 | Y4: 0 | Z4: 0 | AA4: 0 | AB4: 0 | AC4: 0 | AD4: 1 | AE4: 1 | AF4: *1,1 | AG4: 2.2 | AH4: 2 | AI4: 60257855 | AJ4: 4 | AK4: 0 | AL4: 0 | AM4: 0 | AN4: 0 | AO4: 0 | AP4: 0 | AQ4: 0 | AR4: 0
A5: =ROW(Source!A71) -> 71 | B5: 61620567 | C5: 61620566 | D5: 58999254 | E5: 1080 | F5: 1 | G5: 1080 | H5: 1 | I5: 9999990008 | K5: Трудозатраты рабочих | L5: 1191 | N5: 1013 | O5: чел.-ч. | P5: чел.-ч. | Q5: 1 | X5: 24.76 | Y5: 0 | Z5: 0 | AA5: 0 | AB5: 0 | AC5: 0 | AD5: 1 | AE5: 1 | AF5: *1,1 | AG5: 27.236 | AH5: 2 | AI5: 61620567 | AJ5: 5 | AK5: 0 | AL5: 0 | AM5: 0 | AN5: 0 | AO5: 0 | AP5: 0 | AQ5: 0 | AR5: 0
A6: =ROW(Source!A71) -> 71 | B6: 61620568 | C6: 61620566 | D6: 59070721 | E6: 1 | F6: 1 | G6: 1080 | H6: 2 | I6: 2.1-30-10 | J6: ТСН-2001.2. Доп. 68. п.1-30-10 (304101) | K6: Перфораторы, мощность до 800 Вт | L6: 1368 | N6: 1011 | O6: маш.-ч | P6: маш.-ч | Q6: 1 | X6: 2.44 | Y6: 0 | Z6: 0.77 | AA6: 0 | AB6: 0 | AC6: 0 | AD6: 1 | AE6: 0 | AF6: *1,1 | AG6: 2.684 | AH6: 2 | AI6: 61620568 | AJ6: 6 | AK6: 0 | AL6: 0 | AM6: 0 | AN6: 0 | AO6: 0 | AP6: 0 | AQ6: 0 | AR6: 0
A7: =ROW(Source!A71) -> 71 | B7: 61620569 | C7: 61620566 | D7: 59070754 | E7: 1 | F7: 1 | G7: 1080 | H7: 2 | I7: 2.1-30-56 | J7: ТСН-2001.2. Доп. 68. п.1-30-56 (309101) | K7: Шуруповерты | L7: 1368 | N7: 1011 | O7: маш.-ч | P7: маш.-ч | Q7: 1 | X7: 4.63 | Y7: 0 | Z7: 0.47 | AA7: 0 | AB7: 0 | AC7: 0 | AD7: 1 | AE7: 0 | AF7: *1,1 | AG7: 5.093 | AH7: 2 | AI7: 61620569 | AJ7: 7 | AK7: 0 | AL7: 0 | AM7: 0 | AN7: 0 | AO7: 0 | AP7: 0 | AQ7: 0 | AR7: 0
A8: =ROW(Source!A71) -> 71 | B8: 61620570 | C8: 61620566 | D8: 59062734 | E8: 1 | F8: 1 | G8: 1080 | H8: 3 | I8: 1.21-5-1180 | J8: ТСН-2001.1 Доп. 79, Р. 21, о. 5, поз. 1180 | K8: Бирка маркировочная для кабелей и проводов, типа У134 У3,5 | L8: 1356 | N8: 1010 | O8: 1000 шт. | P8: 1000 шт. | Q8: 1000 | X8: 0.031 | Y8: 226.66 | Z8: 0 | AA8: 0 | AB8: 0 | AC8: 0 | AD8: 1 | AE8: 0 | AG8: 0.031 | AH8: 2 | AI8: 61620570 | AJ8: 10 | AK8: 0 | AL8: 0 | AM8: 0 | AN8: 0 | AO8: 0 | AP8: 0 | AQ8: 0 | AR8: 0
A9: =ROW(Source!A71) -> 71 | B9: 61620571 | C9: 61620566 | D9: 59062508 | E9: 1 | F9: 1 | G9: 1080 | H9: 3 | I9: 1.21-5-926 | J9: ТСН-2001.1 Доп. 67, Р. 21, о. 5, поз. 926 | K9: Хомут (стяжка) кабельный из полиамида, размеры 3,6х200 мм | L9: 1355 | N9: 1010 | O9: 100 шт. | P9: 100 шт. | Q9: 100 | X9: 0.315 | Y9: 26.71 | Z9: 0 | AA9: 0 | AB9: 0 | AC9: 0 | AD9: 1 | AE9: 0 | AG9: 0.315 | AH9: 2 | AI9: 61620571 | AJ9: 11 | AK9: 0 | AL9: 0 | AM9: 0 | AN9: 0 | AO9: 0 | AP9: 0 | AQ9: 0 | AR9: 0
A10: =ROW(Source!A71) -> 71 | B10: 61620572 | C10: 61620566 | D10: 59049364 | E10: 1 | F10: 1 | G10: 1080 | H10: 3 | I10: 1.7-3-122 | J10: ТСН-2001.1 Доп. 79, Р. 7, о. 3, поз. 122 | K10: Бур с наконечником из твердого сплава, с хвостовиком SDS-plus, диаметр 10 мм, длина 260 мм | L10: 1354 | N10: 1010 | O10: шт. | P10: шт. | Q10: 1 | X10: 0.28 | Y10: 14.22 | Z10: 0 | AA10: 0 | AB10: 0 | AC10: 0 | AD10: 1 | AE10: 0 | AG10: 0.28 | AH10: 2 | AI10: 61620572 | AJ10: 12 | AK10: 0 | AL10: 0 | AM10: 0 | AN10: 0 | AO10: 0 | AP10: 0 | AQ10: 0 | AR10: 0
A11: =ROW(Source!A71) -> 71 | B11: 61620573 | C11: 61620566 | D11: 59008659 | E11: 1080 | F11: 1 | G11: 1080 | H11: 3 | I11: 2248200000 | K11: Трубы электротехнические гофрированные (2248100000) | L11: 1301 | N11: 1003 | O11: м | P11: м | Q11: 1 | X11: 102 | Y11: 0 | Z11: 0 | AA11: 0 | AB11: 0 | AC11: 0 | AD11: 0 | AE11: 0 | AG11: 102 | AH11: 3 | AI11: -1 | AK11: 0 | AL11: 0 | AM11: 0 | AN11: 0 | AO11: 0 | AP11: 0 | AQ11: 0 | AR11: 0
A12: =ROW(Source!A71) -> 71 | B12: 61620574 | C12: 61620566 | D12: 59013737 | E12: 1080 | F12: 1 | G12: 1080 | H12: 3 | I12: 3449953000 | K12: Скобы для крепления кабеля | L12: 1356 | N12: 1010 | O12: 1000 шт. | P12: 1000 шт. | Q12: 1000 | X12: 0.238 | Y12: 0 | Z12: 0 | AA12: 0 | AB12: 0 | AC12: 0 | AD12: 0 | AE12: 0 | AG12: 0.238 | AH12: 3 | AI12: -1 | AK12: 0 | AL12: 0 | AM12: 0 | AN12: 0 | AO12: 0 | AP12: 0 | AQ12: 0 | AR12: 0
A13: =ROW(Source!A71) -> 71 | B13: 61620575 | C13: 61620566 | D13: 59019228 | E13: 1080 | F13: 1 | G13: 1080 | H13: 3 | I13: 3574000000 | K13: Кабели связи огнестойкие | L13: 1303 | N13: 1003 | O13: км | P13: км | Q13: 1000 | X13: 0.102 | Y13: 0 | Z13: 0 | AA13: 0 | AB13: 0 | AC13: 0 | AD13: 0 | AE13: 0 | AG13: 0.102 | AH13: 3 | AI13: -1 | AK13: 0 | AL13: 0 | AM13: 0 | AN13: 0 | AO13: 0 | AP13: 0 | AQ13: 0 | AR13: 0
A14: =ROW(Source!A71) -> 71 | B14: 61620576 | C14: 61620566 | D14: 59029455 | E14: 1080 | F14: 1 | G14: 1080 | H14: 3 | I14: 5285920000 | K14: Анкеры клиновые | L14: 1355 | N14: 1010 | O14: 100 шт. | P14: 100 шт. | Q14: 100 | X14: 2.36 | Y14: 0 | Z14: 0 | AA14: 0 | AB14: 0 | AC14: 0 | AD14: 0 | AE14: 0 | AG14: 2.36 | AH14: 3 | AI14: -1 | AK14: 0 | AL14: 0 | AM14: 0 | AN14: 0 | AO14: 0 | AP14: 0 | AQ14: 0 | AR14: 0
A15: =ROW(Source!A72) -> 72 | B15: 61620567 | C15: 61620566 | D15: 58999254 | E15: 1080 | F15: 1 | G15: 1080 | H15: 1 | I15: 9999990008 | K15: Трудозатраты рабочих | L15: 1191 | N15: 1013 | O15: чел.-ч. | P15: чел.-ч. | Q15: 1 | X15: 24.76 | Y15: 0 | Z15: 0 | AA15: 0 | AB15: 0 | AC15: 0 | AD15: 1 | AE15: 1 | AF15: *1,1 | AG15: 27.236 | AH15: 2 | AI15: 61620567 | AJ15: 14 | AK15: 0 | AL15: 0 | AM15: 0 | AN15: 0 | AO15: 0 | AP15: 0 | AQ15: 0 | AR15: 0
A16: =ROW(Source!A72) -> 72 | B16: 61620568 | C16: 61620566 | D16: 59070721 | E16: 1 | F16: 1 | G16: 1080 | H16: 2 | I16: 2.1-30-10 | J16: ТСН-2001.2. Доп. 68. п.1-30-10 (304101) | K16: Перфораторы, мощность до 800 Вт | L16: 1368 | N16: 1011 | O16: маш.-ч | P16: маш.-ч | Q16: 1 | X16: 2.44 | Y16: 0 | Z16: 0.77 | AA16: 0 | AB16: 0 | AC16: 0 | AD16: 1 | AE16: 0 | AF16: *1,1 | AG16: 2.684 | AH16: 2 | AI16: 61620568 | AJ16: 15 | AK16: 0 | AL16: 0 | AM16: 0 | AN16: 0 | AO16: 0 | AP16: 0 | AQ16: 0 | AR16: 0
A17: =ROW(Source!A72) -> 72 | B17: 61620569 | C17: 61620566 | D17: 59070754 | E17: 1 | F17: 1 | G17: 1080 | H17: 2 | I17: 2.1-30-56 | J17: ТСН-2001.2. Доп. 68. п.1-30-56 (309101) | K17: Шуруповерты | L17: 1368 | N17: 1011 | O17: маш.-ч | P17: маш.-ч | Q17: 1 | X17: 4.63 | Y17: 0 | Z17: 0.47 | AA17: 0 | AB17: 0 | AC17: 0 | AD17: 1 | AE17: 0 | AF17: *1,1 | AG17: 5.093 | AH17: 2 | AI17: 61620569 | AJ17: 16 | AK17: 0 | AL17: 0 | AM17: 0 | AN17: 0 | AO17: 0 | AP17: 0 | AQ17: 0 | AR17: 0
A18: =ROW(Source!A72) -> 72 | B18: 61620570 | C18: 61620566 | D18: 59062734 | E18: 1 | F18: 1 | G18: 1080 | H18: 3 | I18: 1.21-5-1180 | J18: ТСН-2001.1 Доп. 79, Р. 21, о. 5, поз. 1180 | K18: Бирка маркировочная для кабелей и проводов, типа У134 У3,5 | L18: 1356 | N18: 1010 | O18: 1000 шт. | P18: 1000 шт. | Q18: 1000 | X18: 0.031 | Y18: 226.66 | Z18: 0 | AA18: 0 | AB18: 0 | AC18: 0 | AD18: 1 | AE18: 0 | AG18: 0.031 | AH18: 2 | AI18: 61620570 | AJ18: 19 | AK18: 0 | AL18: 0 | AM18: 0 | AN18: 0 | AO18: 0 | AP18: 0 | AQ18: 0 | AR18: 0
A19: =ROW(Source!A72) -> 72 | B19: 61620571 | C19: 61620566 | D19: 59062508 | E19: 1 | F19: 1 | G19: 1080 | H19: 3 | I19: 1.21-5-926 | J19: ТСН-2001.1 Доп. 67, Р. 21, о. 5, поз. 926 | K19: Хомут (стяжка) кабельный из полиамида, размеры 3,6х200 мм | L19: 1355 | N19: 1010 | O19: 100 шт. | P19: 100 шт. | Q19: 100 | X19: 0.315 | Y19: 26.71 | Z19: 0 | AA19: 0 | AB19: 0 | AC19: 0 | AD19: 1 | AE19: 0 | AG19: 0.315 | AH19: 2 | AI19: 61620571 | AJ19: 20 | AK19: 0 | AL19: 0 | AM19: 0 | AN19: 0 | AO19: 0 | AP19: 0 | AQ19: 0 | AR19: 0
A20: =ROW(Source!A72) -> 72 | B20: 61620572 | C20: 61620566 | D20: 59049364 | E20: 1 | F20: 1 | G20: 1080 | H20: 3 | I20: 1.7-3-122 | J20: ТСН-2001.1 Доп. 79, Р. 7, о. 3, поз. 122 | K20: Бур с наконечником из твердого сплава, с хвостовиком SDS-plus, диаметр 10 мм, длина 260 мм | L20: 1354 | N20: 1010 | O20: шт. | P20: шт. | Q20: 1 | X20: 0.28 | Y20: 14.22 | Z20: 0 | AA20: 0 | AB20: 0 | AC20: 0 | AD20: 1 | AE20: 0 | AG20: 0.28 | AH20: 2 | AI20: 61620572 | AJ20: 21 | AK20: 0 | AL20: 0 | AM20: 0 | AN20: 0 | AO20: 0 | AP20: 0 | AQ20: 0 | AR20: 0
A21: =ROW(Source!A72) -> 72 | B21: 61620573 | C21: 61620566 | D21: 59008659 | E21: 1080 | F21: 1 | G21: 1080 | H21: 3 | I21: 2248200000 | K21: Трубы электротехнические гофрированные (2248100000) | L21: 1301 | N21: 1003 | O21: м | P21: м | Q21: 1 | X21: 102 | Y21: 0 | Z21: 0 | AA21: 0 | AB21: 0 | AC21: 0 | AD21: 0 | AE21: 0 | AG21: 102 | AH21: 3 | AI21: -1 | AK21: 0 | AL21: 0 | AM21: 0 | AN21: 0 | AO21: 0 | AP21: 0 | AQ21: 0 | AR21: 0
A22: =ROW(Source!A72) -> 72 | B22: 61620574 | C22: 61620566 | D22: 59013737 | E22: 1080 | F22: 1 | G22: 1080 | H22: 3 | I22: 3449953000 | K22: Скобы для крепления кабеля | L22: 1356 | N22: 1010 | O22: 1000 шт. | P22: 1000 шт. | Q22: 1000 | X22: 0.238 | Y22: 0 | Z22: 0 | AA22: 0 | AB22: 0 | AC22: 0 | AD22: 0 | AE22: 0 | AG22: 0.238 | AH22: 3 | AI22: -1 | AK22: 0 | AL22: 0 | AM22: 0 | AN22: 0 | AO22: 0 | AP22: 0 | AQ22: 0 | AR22: 0
A23: =ROW(Source!A72) -> 72 | B23: 61620575 | C23: 61620566 | D23: 59019228 | E23: 1080 | F23: 1 | G23: 1080 | H23: 3 | I23: 3574000000 | K23: Кабели связи огнестойкие | L23: 1303 | N23: 1003 | O23: км | P23: км | Q23: 1000 | X23: 0.102 | Y23: 0 | Z23: 0 | AA23: 0 | AB23: 0 | AC23: 0 | AD23: 0 | AE23: 0 | AG23: 0.102 | AH23: 3 | AI23: -1 | AK23: 0 | AL23: 0 | AM23: 0 | AN23: 0 | AO23: 0 | AP23: 0 | AQ23: 0 | AR23: 0
A24: =ROW(Source!A72) -> 72 | B24: 61620576 | C24: 61620566 | D24: 59029455 | E24: 1080 | F24: 1 | G24: 1080 | H24: 3 | I24: 5285920000 | K24: Анкеры клиновые | L24: 1355 | N24: 1010 | O24: 100 шт. | P24: 100 шт. | Q24: 100 | X24: 2.36 | Y24: 0 | Z24: 0 | AA24: 0 | AB24: 0 | AC24: 0 | AD24: 0 | AE24: 0 | AG24: 2.36 | AH24: 3 | AI24: -1 | AK24: 0 | AL24: 0 | AM24: 0 | AN24: 0 | AO24: 0 | AP24: 0 | AQ24: 0 | AR24: 0
A25: =ROW(Source!A79) -> 79 | B25: 61620614 | C25: 61620608 | D25: 58999254 | E25: 1080 | F25: 1 | G25: 1080 | H25: 1 | I25: 9999990008 | K25: Трудозатраты рабочих | L25: 1191 | N25: 1013 | O25: чел.-ч. | P25: чел.-ч. | Q25: 1 | X25: 5.29 | Y25: 0 | Z25: 0 | AA25: 0 | AB25: 0 | AC25: 0 | AD25: 1 | AE25: 1 | AF25: *1,1 | AG25: 5.819 | AH25: 2 | AI25: 61620609 | AJ25: 23 | AK25: 0 | AL25: 0 | AM25: 0 | AN25: 0 | AO25: 0 | AP25: 0 | AQ25: 0 | AR25: 0
A26: =ROW(Source!A79) -> 79 | B26: 61620615 | C26: 61620608 | D26: 59070669 | E26: 1 | F26: 1 | G26: 1080 | H26: 2 | I26: 2.1-18-7 | J26: ТСН-2001.2. Доп. 68. п.1-18-7 (183001) | K26: Автомобили грузовые бортовые, грузоподъемность до 5 т | L26: 1368 | N26: 1011 | O26: маш.-ч | P26: маш.-ч | Q26: 1 | X26: 0.01 | Y26: 0 | Z26: 83.1 | AA26: 12.62 | AB26: 0 | AC26: 0 | AD26: 1 | AE26: 0 | AF26: *1,1 | AG26: 0.011 | AH26: 2 | AI26: 61620610 | AJ26: 24 | AK26: 0 | AL26: 0 | AM26: 0 | AN26: 0 | AO26: 0 | AP26: 0 | AQ26: 0 | AR26: 0
A27: =ROW(Source!A79) -> 79 | B27: 61620616 | C27: 61620608 | D27: 59069905 | E27: 1 | F27: 1 | G27: 1080 | H27: 2 | I27: 2.1-3-38 | J27: ТСН-2001.2. Доп. 68. п.1-3-38 (032009) | K27: Краны на автомобильном ходу, грузоподъемность до 16 т | L27: 1368 | N27: 1011 | O27: маш.-ч | P27: маш.-ч | Q27: 1 | X27: 0.01 | Y27: 0 | Z27: 179.17 | AA27: 16.93 | AB27: 0 | AC27: 0 | AD27: 1 | AE27: 0 | AF27: *1,1 | AG27: 0.011 | AH27: 2 | AI27: 61620611 | AJ27: 25 | AK27: 0 | AL27: 0 | AM27: 0 | AN27: 0 | AO27: 0 | AP27: 0 | AQ27: 0 | AR27: 0
A28: =ROW(Source!A79) -> 79 | B28: 61620617 | C28: 61620608 | D28: 59062690 | E28: 1 | F28: 1 | G28: 1080 | H28: 3 | I28: 1.21-5-1134 | J28: ТСН-2001.1 Доп. 70, Р. 21, о. 5, поз. 1134 | K28: Хомут (стяжка) кабельный из полиамида, размеры 4,8х300 мм | L28: 1355 | N28: 1010 | O28: 100 шт. | P28: 100 шт. | Q28: 100 | X28: 2.1094 | Y28: 59.47 | Z28: 0 | AA28: 0 | AB28: 0 | AC28: 0 | AD28: 1 | AE28: 0 | AG28: 2.1094 | AH28: 2 | AI28: 61620612 | AJ28: 26 | AK28: 0 | AL28: 0 | AM28: 0 | AN28: 0 | AO28: 0 | AP28: 0 | AQ28: 0 | AR28: 0
A29: =ROW(Source!A79) -> 79 | B29: 61620618 | C29: 61620608 | D29: 59062735 | E29: 1 | F29: 1 | G29: 1080 | H29: 3 | I29: 1.21-5-1181 | J29: ТСН-2001.1 Доп. 79, Р. 21, о. 5, поз. 1181 | K29: Бирка маркировочная для кабелей и проводов, типа У153 У3,5 | L29: 1356 | N29: 1010 | O29: 1000 шт. | P29: 1000 шт. | Q29: 1000 | X29: 0.0069 | Y29: 56.16 | Z29: 0 | AA29: 0 | AB29: 0 | AC29: 0 | AD29: 1 | AE29: 0 | AG29: 0.0069 | AH29: 2 | AI29: 61620613 | AJ29: 27 | AK29: 0 | AL29: 0 | AM29: 0 | AN29: 0 | AO29: 0 | AP29: 0 | AQ29: 0 | AR29: 0
A30: =ROW(Source!A79) -> 79 | B30: 61620619 | C30: 61620608 | D30: 59014711 | E30: 1080 | F30: 1 | G30: 1080 | H30: 3 | I30: 3500000000 | K30: Кабели, провода | L30: 1303 | N30: 1003 | O30: км | P30: км | Q30: 1000 | X30: 0.102 | Y30: 0 | Z30: 0 | AA30: 0 | AB30: 0 | AC30: 0 | AD30: 0 | AE30: 0 | AG30: 0.102 | AH30: 3 | AI30: -1 | AK30: 0 | AL30: 0 | AM30: 0 | AN30: 0 | AO30: 0 | AP30: 0 | AQ30: 0 | AR30: 0
A31: =ROW(Source!A80) -> 80 | B31: 61620614 | C31: 61620608 | D31: 58999254 | E31: 1080 | F31: 1 | G31: 1080 | H31: 1 | I31: 9999990008 | K31: Трудозатраты рабочих | L31: 1191 | N31: 1013 | O31: чел.-ч. | P31: чел.-ч. | Q31: 1 | X31: 5.29 | Y31: 0 | Z31: 0 | AA31: 0 | AB31: 0 | AC31: 0 | AD31: 1 | AE31: 1 | AF31: *1,1 | AG31: 5.819 | AH31: 2 | AI31: 61620609 | AJ31: 28 | AK31: 0 | AL31: 0 | AM31: 0 | AN31: 0 | AO31: 0 | AP31: 0 | AQ31: 0 | AR31: 0
A32: =ROW(Source!A80) -> 80 | B32: 61620615 | C32: 61620608 | D32: 59070669 | E32: 1 | F32: 1 | G32: 1080 | H32: 2 | I32: 2.1-18-7 | J32: ТСН-2001.2. Доп. 68. п.1-18-7 (183001) | K32: Автомобили грузовые бортовые, грузоподъемность до 5 т | L32: 1368 | N32: 1011 | O32: маш.-ч | P32: маш.-ч | Q32: 1 | X32: 0.01 | Y32: 0 | Z32: 83.1 | AA32: 12.62 | AB32: 0 | AC32: 0 | AD32: 1 | AE32: 0 | AF32: *1,1 | AG32: 0.011 | AH32: 2 | AI32: 61620610 | AJ32: 29 | AK32: 0 | AL32: 0 | AM32: 0 | AN32: 0 | AO32: 0 | AP32: 0 | AQ32: 0 | AR32: 0
A33: =ROW(Source!A80) -> 80 | B33: 61620616 | C33: 61620608 | D33: 59069905 | E33: 1 | F33: 1 | G33: 1080 | H33: 2 | I33: 2.1-3-38 | J33: ТСН-2001.2. Доп. 68. п.1-3-38 (032009) | K33: Краны на автомобильном ходу, грузоподъемность до 16 т | L33: 1368 | N33: 1011 | O33: маш.-ч | P33: маш.-ч | Q33: 1 | X33: 0.01 | Y33: 0 | Z33: 179.17 | AA33: 16.93 | AB33: 0 | AC33: 0 | AD33: 1 | AE33: 0 | AF33: *1,1 | AG33: 0.011 | AH33: 2 | AI33: 61620611 | AJ33: 30 | AK33: 0 | AL33: 0 | AM33: 0 | AN33: 0 | AO33: 0 | AP33: 0 | AQ33: 0 | AR33: 0
A34: =ROW(Source!A80) -> 80 | B34: 61620617 | C34: 61620608 | D34: 59062690 | E34: 1 | F34: 1 | G34: 1080 | H34: 3 | I34: 1.21-5-1134 | J34: ТСН-2001.1 Доп. 70, Р. 21, о. 5, поз. 1134 | K34: Хомут (стяжка) кабельный из полиамида, размеры 4,8х300 мм | L34: 1355 | N34: 1010 | O34: 100 шт. | P34: 100 шт. | Q34: 100 | X34: 2.1094 | Y34: 59.47 | Z34: 0 | AA34: 0 | AB34: 0 | AC34: 0 | AD34: 1 | AE34: 0 | AG34: 2.1094 | AH34: 2 | AI34: 61620612 | AJ34: 31 | AK34: 0 | AL34: 0 | AM34: 0 | AN34: 0 | AO34: 0 | AP34: 0 | AQ34: 0 | AR34: 0
A35: =ROW(Source!A80) -> 80 | B35: 61620618 | C35: 61620608 | D35: 59062735 | E35: 1 | F35: 1 | G35: 1080 | H35: 3 | I35: 1.21-5-1181 | J35: ТСН-2001.1 Доп. 79, Р. 21, о. 5, поз. 1181 | K35: Бирка маркировочная для кабелей и проводов, типа У153 У3,5 | L35: 1356 | N35: 1010 | O35: 1000 шт. | P35: 1000 шт. | Q35: 1000 | X35: 0.0069 | Y35: 56.16 | Z35: 0 | AA35: 0 | AB35: 0 | AC35: 0 | AD35: 1 | AE35: 0 | AG35: 0.0069 | AH35: 2 | AI35: 61620613 | AJ35: 32 | AK35: 0 | AL35: 0 | AM35: 0 | AN35: 0 | AO35: 0 | AP35: 0 | AQ35: 0 | AR35: 0
A36: =ROW(Source!A80) -> 80 | B36: 61620619 | C36: 61620608 | D36: 59014711 | E36: 1080 | F36: 1 | G36: 1080 | H36: 3 | I36: 3500000000 | K36: Кабели, провода | L36: 1303 | N36: 1003 | O36: км | P36: км | Q36: 1000 | X36: 0.102 | Y36: 0 | Z36: 0 | AA36: 0 | AB36: 0 | AC36: 0 | AD36: 0 | AE36: 0 | AG36: 0.102 | AH36: 3 | AI36: -1 | AK36: 0 | AL36: 0 | AM36: 0 | AN36: 0 | AO36: 0 | AP36: 0 | AQ36: 0 | AR36: 0

Sheet SrcPoprs
A1: 28 | B1: 1 | D1: *1 | E1: *1,1 | F1: *1,1 | G1: *1,1 | I1: *1,1 | J1: *1,1 | N1: *1 | O1: *1,1 | S1: Гл.12.Прил.8.п.8. 5_12.00.01.11.003 | T1: При наличии усложненных условий производства работ (стесненность, сложность складирования и транспортной логистики, наличие в зоне производства работ действующего технологического оборудования или движения технологического транспорта и т.п.) для объектов, расположенных за пределами территории круговой магистральной системы улиц "Садовое кольцо" и за пределами Третьего транспортного кольца города Москвы пунктов "а" и "б", но в пределах Московской кольцевой автомобильной дороги | U1: Глава 12
A2: 29 | B2: 1 | D2: *1 | E2: *1,1 | F2: *1,1 | G2: *1,1 | I2: *1,1 | J2: *1,1 | N2: *1 | O2: *1,1 | S2: Гл.12.Прил.8.п.8. 5_12.00.01.11.003 | T2: При наличии усложненных условий производства работ (стесненность, сложность складирования и транспортной логистики, наличие в зоне производства работ действующего технологического оборудования или движения технологического транспорта и т.п.) для объектов, расположенных за пределами территории круговой магистральной системы улиц "Садовое кольцо" и за пределами Третьего транспортного кольца города Москвы пунктов "а" и "б", но в пределах Московской кольцевой автомобильной дороги | U2: Глава 12
A3: 32 | B3: 1 | D3: *1 | E3: *1,1 | F3: *1,1 | G3: *1,1 | I3: *1,1 | J3: *1,1 | N3: *1 | O3: *1,1 | S3: Гл.12.Прил.8.п.8. 5_12.00.01.11.003 | T3: При наличии усложненных условий производства работ (стесненность, сложность складирования и транспортной логистики, наличие в зоне производства работ действующего технологического оборудования или движения технологического транспорта и т.п.) для объектов, расположенных за пределами территории круговой магистральной системы улиц "Садовое кольцо" и за пределами Третьего транспортного кольца города Москвы пунктов "а" и "б", но в пределах Московской кольцевой автомобильной дороги | U3: Глава 12
A4: 33 | B4: 1 | D4: *1 | E4: *1,1 | F4: *1,1 | G4: *1,1 | I4: *1,1 | J4: *1,1 | N4: *1 | O4: *1,1 | S4: Гл.12.Прил.8.п.8. 5_12.00.01.11.003 | T4: При наличии усложненных условий производства работ (стесненность, сложность складирования и транспортной логистики, наличие в зоне производства работ действующего технологического оборудования или движения технологического транспорта и т.п.) для объектов, расположенных за пределами территории круговой магистральной системы улиц "Садовое кольцо" и за пределами Третьего транспортного кольца города Москвы пунктов "а" и "б", но в пределах Московской кольцевой автомобильной дороги | U4: Глава 12
A5: 71 | B5: 1 | E5: *1,1 | F5: *1,1 | G5: *1,1 | I5: *1,1 | J5: *1,1 | O5: *1,1 | S5: О.П. п.3.4.30.в | T5: При применении территориальных сметных нормативов для города Москвы затраты, учитывающие напряженные и стесненные условия производства работ (стесненность, сложность складирования и транспортной логистики и т.п.), исчисляются с применением коэффициентов к затратам труда и заработной плате рабочих, машинистов, времени эксплуатации машин и механизмов, стоимости эксплуатации машин в размере: для объектов, расположенных за пределами Третьего транспортного кольца города Москвы, но в пределах Московской кольцевой автомобильной дороги | U5: Глава 12
A6: 72 | B6: 1 | E6: *1,1 | F6: *1,1 | G6: *1,1 | I6: *1,1 | J6: *1,1 | O6: *1,1 | S6: О.П. п.3.4.30.в | T6: При применении территориальных сметных нормативов для города Москвы затраты, учитывающие напряженные и стесненные условия производства работ (стесненность, сложность складирования и транспортной логистики и т.п.), исчисляются с применением коэффициентов к затратам труда и заработной плате рабочих, машинистов, времени эксплуатации машин и механизмов, стоимости эксплуатации машин в размере: для объектов, расположенных за пределами Третьего транспортного кольца города Москвы, но в пределах Московской кольцевой автомобильной дороги | U6: Глава 12
A7: 79 | B7: 1 | E7: *1,1 | F7: *1,1 | G7: *1,1 | I7: *1,1 | J7: *1,1 | O7: *1,1 | S7: О.П. п.3.4.30.в | T7: При применении территориальных сметных нормативов для города Москвы затраты, учитывающие напряженные и стесненные условия производства работ (стесненность, сложность складирования и транспортной логистики и т.п.), исчисляются с применением коэффициентов к затратам труда и заработной плате рабочих, машинистов, времени эксплуатации машин и механизмов, стоимости эксплуатации машин в размере: для объектов, расположенных за пределами Третьего транспортного кольца города Москвы, но в пределах Московской кольцевой автомобильной дороги | U7: Глава 12
A8: 80 | B8: 1 | E8: *1,1 | F8: *1,1 | G8: *1,1 | I8: *1,1 | J8: *1,1 | O8: *1,1 | S8: О.П. п.3.4.30.в | T8: При применении территориальных сметных нормативов для города Москвы затраты, учитывающие напряженные и стесненные условия производства работ (стесненность, сложность складирования и транспортной логистики и т.п.), исчисляются с применением коэффициентов к затратам труда и заработной плате рабочих, машинистов, времени эксплуатации машин и механизмов, стоимости эксплуатации машин в размере: для объектов, расположенных за пределами Третьего транспортного кольца города Москвы, но в пределах Московской кольцевой автомобильной дороги | U8: Глава 12

Sheet SrcKA
A1: 0 | B1: Smeta.RU (495) 974-1589 | D1: _PS_ | F1: 0 | G1: 0 | H1: 0 | I1: Smeta.RU | K1: 1 | L1: 74563 | M1: 10 | N1: 12 | O1: 1 | P1: 0 | Q1: 0
F12: =Source!F12 | G12: =Source!G12 -> 02-01-13 Электрочасофикация | AJ12: 0 | CY12: 0
